Workbook

Sheet Sheet1
A1: Site Name | B1: Month | C1: Year | D1: Purchased Electricity Kwh | E1: Purchased Electricity Tariff ($/Kwh) | F1: Total Renewable Energy Production Kwh | G1: Electricity Total Budgeted | H1: Electricity Total Budgeted Cost ($) | I1: LPG Kitchen (Liters) | J1: LPG Kitchen $/Liters | K1: LPG Total Budgeted | L1: LPG Total Budgeted Cost ($) | M1: Fuel Oil Hot-Water Boilers (Liter) Liter | N1: Fuel Oil Hot-Water Boilers (Liter) $/Liter | O1: Fuel Oil Total Budgeted | P1: Fuel Oil Total Budgeted Cost ($) | Q1: District Energy Heating KWh | R1: District Energy Heating $/KWh | S1: Heating District Energy Total Budgeted | T1: Heating District Energy Total Budgeted Cost ($) | U1: Water Utility Supply (m3) m3 | V1: Water Utility Supply (m3) $/m3 | W1: Water Total Budgeted | X1: Water Total Budgeted Cost ($) | Y1: Room Nights | Z1: Total Guests
A2: Annabelle | B2: 1 | C2: 2026 | D2: =Worksheet!D86 -> 82116 | E2: =Worksheet!E86 -> 0.18 | F2: =Worksheet!AJ86 -> 15177 | G2: =Worksheet!I86 -> 124702 | H2: =Worksheet!J86 -> 31425 | I2: =Worksheet!K86 -> 1344 | J2: =Worksheet!L86 -> 0.76 | K2: =Worksheet!N86 -> 2237 | L2: =Worksheet!O86 -> 1566 | M2: =Worksheet!AP86 -> 8259 | N2: =Worksheet!AQ86 -> 0.74 | O2: =Worksheet!AX86 -> 0 | P2: =Worksheet!AY86 -> 0 | Q2: =Worksheet!P86 -> 0 | R2: =Worksheet!Q86 -> 0 | S2: =Worksheet!S86 -> 131947 | T2: =Worksheet!T86 -> 0 | U2: =Worksheet!U86 -> 76 | V2: =Worksheet!V86 -> 2.9 | W2: =Worksheet!X86 -> 807 | X2: =Worksheet!Y86 -> 2342 | Y2: =Worksheet!Z86 -> 1194 | Z2: =Worksheet!AC86 -> 1806
A3: Annabelle | B3: 2 | C3: 2026 | D3: =Worksheet!D87 -> 53711 | E3: =Worksheet!E87 -> 0.11 | F3: =Worksheet!AJ87 -> 25405 | G3: =Worksheet!I87 -> 125023 | H3: =Worksheet!J87 -> 31506 | I3: =Worksheet!K87 -> 500 | J3: =Worksheet!L87 -> 0.76 | K3: =Worksheet!N87 -> 2549 | L3: =Worksheet!O87 -> 1784 | M3: =Worksheet!AP87 -> 2143 | N3: =Worksheet!AQ87 -> 0.74 | O3: =Worksheet!AX87 -> 0 | P3: =Worksheet!AY87 -> 0 | Q3: =Worksheet!P87 -> 0 | R3: =Worksheet!Q87 -> 0 | S3: =Worksheet!S87 -> 198349 | T3: =Worksheet!T87 -> 0 | U3: =Worksheet!U87 -> 0 | V3: =Worksheet!V87 -> 0 | W3: =Worksheet!X87 -> 662 | X3: =Worksheet!Y87 -> 1602 | Y3: =Worksheet!Z87 -> 198 | Z3: =Worksheet!AC87 -> 377
A4: Annabelle | B4: 3 | C4: 2026 | D4: =Worksheet!D88 -> 146529 | E4: =Worksheet!E88 -> 0.16 | F4: =Worksheet!AJ88 -> 29080 | G4: =Worksheet!I88 -> 152841 | H4: =Worksheet!J88 -> 38516 | I4: =Worksheet!K88 -> 2825 | J4: =Worksheet!L88 -> 0.88 | K4: =Worksheet!N88 -> 3481 | L4: =Worksheet!O88 -> 2437 | M4: =Worksheet!AP88 -> 13232 | N4: =Worksheet!AQ88 -> 0.83 | O4: =Worksheet!AX88 -> 0 | P4: =Worksheet!AY88 -> 0 | Q4: =Worksheet!P88 -> 23461 | R4: =Worksheet!Q88 -> 0.0938 | S4: =Worksheet!S88 -> 183128 | T4: =Worksheet!T88 -> 2230 | U4: =Worksheet!U88 -> 1394 | V4: =Worksheet!V88 -> 2.88 | W4: =Worksheet!X88 -> 5072 | X4: =Worksheet!Y88 -> 12273 | Y4: =Worksheet!Z88 -> 3186 | Z4: =Worksheet!AC88 -> 5494
A5: Annabelle | B5: 4 | C5: 2026 | D5: =Worksheet!D89 -> 157388 | E5: =Worksheet!E89 -> 0.19 | F5: =Worksheet!AJ89 -> 27544 | G5: =Worksheet!I89 -> 178614 | H5: =Worksheet!J89 -> 45011 | I5: =Worksheet!K89 -> 3132 | J5: =Worksheet!L89 -> 1.03 | K5: =Worksheet!N89 -> 4411 | L5: =Worksheet!O89 -> 3088 | M5: =Worksheet!AP89 -> 10582 | N5: =Worksheet!AQ89 -> 1.08 | O5: =Worksheet!AX89 -> 1198 | P5: =Worksheet!AY89 -> 791 | Q5: =Worksheet!P89 -> 26762 | R5: =Worksheet!Q89 -> 0.1131 | S5: =Worksheet!S89 -> 164934 | T5: =Worksheet!T89 -> 2299 | U5: =Worksheet!U89 -> 2996 | V5: =Worksheet!V89 -> 2.88 | W5: =Worksheet!X89 -> 3509 | X5: =Worksheet!Y89 -> 8491 | Y5: =Worksheet!Z89 -> 5315 | Z5: =Worksheet!AC89 -> 9107
A6: Annabelle | B6: 5 | C6: 2026 | D6: 148633 | E6: =Worksheet!E91 -> 0.23 | F6: 34871 | G6: =Worksheet!I91 -> 303801 | H6: =Worksheet!J91 -> 77469 | I6: =Worksheet!K91 -> 7462 | J6: 0.62 | K6: =Worksheet!N91 -> 6682 | L6: =Worksheet!O91 -> 3063 | M6: 11342 | N6: 0.88 | O6: =Worksheet!AX91 -> 17582 | P6: =Worksheet!AY91 -> 11769 | Q6: =Worksheet!P91 -> 0 | R6: =Worksheet!Q91 -> 0 | S6: =Worksheet!S91 -> 77414 | T6: =Worksheet!T91 -> 7834 | U6: 3377 | V6: 2.42 | W6: =Worksheet!X91 -> 2997 | X6: =Worksheet!Y91 -> 4136 | Y6: 5907 | Z6: 11083
A7: Annabelle | B7: 6 | C7: 2026 | D7: 194344 | E7: =Worksheet!E92 -> 0.22 | F7: 46910 | G7: =Worksheet!I92 -> 202116 | H7: =Worksheet!J92 -> 50933 | I7: 3149 | J7: 0.62 | K7: =Worksheet!N92 -> 4079 | L7: =Worksheet!O92 -> 2855 | M7: =Worksheet!AP92 -> 4167 | N7: =Worksheet!AQ92 -> 0.88 | O7: =Worksheet!AX92 -> 0 | P7: =Worksheet!AY92 -> 0 | Q7: =Worksheet!P92 -> 0 | R7: =Worksheet!Q92 -> 0 | S7: =Worksheet!S92 -> 53273 | T7: =Worksheet!T92 -> 961 | U7: =Worksheet!U92 -> 3657 | V7: =Worksheet!V92 -> 2.42 | W7: =Worksheet!X92 -> 4092 | X7: =Worksheet!Y92 -> 9903 | Y7: =Worksheet!Z92 -> 6115 | Z7: =Worksheet!AC92 -> 11926
A8: Annabelle | B8: 7 | C8: 2026 | D8: =Worksheet!D93 -> 0 | E8: =Worksheet!E93 -> 0 | F8: =Worksheet!AJ93 -> 0 | G8: =Worksheet!I93 -> 218956 | H8: =Worksheet!J93 -> 55177 | I8: =Worksheet!K93 -> 0 | J8: =Worksheet!L93 -> 0 | K8: =Worksheet!N93 -> 3544 | L8: =Worksheet!O93 -> 2481 | M8: =Worksheet!AP93 -> 0 | N8: =Worksheet!AQ93 -> 0 | O8: =Worksheet!AX93 -> 0 | P8: =Worksheet!AY93 -> 0 | Q8: =Worksheet!P93 -> 0 | R8: =Worksheet!Q93 -> 0 | S8: =Worksheet!S93 -> 31777 | T8: =Worksheet!T93 -> 1530 | U8: =Worksheet!U93 -> 0 | V8: =Worksheet!V93 -> 0 | W8: =Worksheet!X93 -> 4399 | X8: =Worksheet!Y93 -> 10645 | Y8: =Worksheet!Z93 -> 0 | Z8: =Worksheet!AC93 -> 0
A9: Annabelle | B9: 8 | C9: 2026 | D9: =Worksheet!D94 -> 0 | E9: =Worksheet!E94 -> 0 | F9: =Worksheet!AJ94 -> 0 | G9: =Worksheet!I94 -> 236941 | H9: =Worksheet!J94 -> 59709 | I9: =Worksheet!K94 -> 0 | J9: =Worksheet!L94 -> 0 | K9: =Worksheet!N94 -> 4263 | L9: =Worksheet!O94 -> 2984 | M9: =Worksheet!AP94 -> 0 | N9: =Worksheet!AQ94 -> 0 | O9: =Worksheet!AX94 -> 0 | P9: =Worksheet!AY94 -> 0 | Q9: =Worksheet!P94 -> 0 | R9: =Worksheet!Q94 -> 0 | S9: =Worksheet!S94 -> 33894 | T9: =Worksheet!T94 -> 1377 | U9: =Worksheet!U94 -> 0 | V9: =Worksheet!V94 -> 0 | W9: =Worksheet!X94 -> 5196 | X9: =Worksheet!Y94 -> 12573 | Y9: =Worksheet!Z94 -> 0 | Z9: =Worksheet!AC94 -> 0
A10: Annabelle | B10: 9 | C10: 2026 | D10: =Worksheet!D95 -> 0 | E10: =Worksheet!E95 -> 0 | F10: =Worksheet!AJ95 -> 0 | G10: =Worksheet!I95 -> 245452 | H10: =Worksheet!J95 -> 61854 | I10: =Worksheet!K95 -> 0 | J10: =Worksheet!L95 -> 0 | K10: =Worksheet!N95 -> 3720 | L10: =Worksheet!O95 -> 2604 | M10: =Worksheet!AP95 -> 0 | N10: =Worksheet!AQ95 -> 0 | O10: =Worksheet!AX95 -> 0 | P10: =Worksheet!AY95 -> 0 | Q10: =Worksheet!P95 -> 0 | R10: =Worksheet!Q95 -> 0 | S10: =Worksheet!S95 -> 31298 | T10: =Worksheet!T95 -> 511 | U10: =Worksheet!U95 -> 0 | V10: =Worksheet!V95 -> 0 | W10: =Worksheet!X95 -> 3574 | X10: =Worksheet!Y95 -> 8649 | Y10: =Worksheet!Z95 -> 0 | Z10: =Worksheet!AC95 -> 0
A11: Annabelle | B11: 10 | C11: 2026 | D11: =Worksheet!D96 -> 0 | E11: =Worksheet!E96 -> 0 | F11: =Worksheet!AJ96 -> 0 | G11: =Worksheet!I96 -> 204561 | H11: =Worksheet!J96 -> 51549 | I11: =Worksheet!K96 -> 0 | J11: =Worksheet!L96 -> 0 | K11: =Worksheet!N96 -> 4649 | L11: =Worksheet!O96 -> 3254 | M11: =Worksheet!AP96 -> 0 | N11: =Worksheet!AQ96 -> 0 | O11: =Worksheet!AX96 -> 1034 | P11: =Worksheet!AY96 -> 693 | Q11: =Worksheet!P96 -> 0 | R11: =Worksheet!Q96 -> 0 | S11: =Worksheet!S96 -> 57582 | T11: =Worksheet!T96 -> 2522 | U11: =Worksheet!U96 -> 0 | V11: =Worksheet!V96 -> 0 | W11: =Worksheet!X96 -> 4648 | X11: =Worksheet!Y96 -> 11248 | Y11: =Worksheet!Z96 -> 0 | Z11: =Worksheet!AC96 -> 0
A12: Annabelle | B12: 11 | C12: 2026 | D12: =Worksheet!D97 -> 0 | E12: =Worksheet!E97 -> 0 | F12: =Worksheet!AJ97 -> 0 | G12: =Worksheet!I97 -> 163791 | H12: =Worksheet!J97 -> 41725 | I12: =Worksheet!K97 -> 0 | J12: =Worksheet!L97 -> 0 | K12: =Worksheet!N97 -> 3731 | L12: =Worksheet!O97 -> 2612 | M12: =Worksheet!AP97 -> 0 | N12: =Worksheet!AQ97 -> 0 | O12: =Worksheet!AX97 -> 0 | P12: =Worksheet!AY97 -> 0 | Q12: =Worksheet!P97 -> 0 | R12: =Worksheet!Q97 -> 0 | S12: =Worksheet!S97 -> 73256 | T12: =Worksheet!T97 -> 1024 | U12: =Worksheet!U97 -> 0 | V12: =Worksheet!V97 -> 0 | W12: =Worksheet!X97 -> 3565 | X12: =Worksheet!Y97 -> 8627 | Y12: =Worksheet!Z97 -> 0 | Z12: =Worksheet!AC97 -> 0
A13: Annabelle | B13: 12 | C13: 2026 | D13: =Worksheet!D98 -> 0 | E13: =Worksheet!E98 -> 0 | F13: =Worksheet!AJ98 -> 0 | G13: =Worksheet!I98 -> 140763 | H13: =Worksheet!J98 -> 35472 | I13: =Worksheet!K98 -> 0 | J13: =Worksheet!L98 -> 0 | K13: =Worksheet!N98 -> 2600 | L13: =Worksheet!O98 -> 1820 | M13: =Worksheet!AP98 -> 0 | N13: =Worksheet!AQ98 -> 0 | O13: =Worksheet!AX98 -> 0 | P13: =Worksheet!AY98 -> 0 | Q13: =Worksheet!P98 -> 0 | R13: =Worksheet!Q98 -> 0 | S13: =Worksheet!S98 -> 126000 | T13: =Worksheet!T98 -> 0 | U13: =Worksheet!U98 -> 0 | V13: =Worksheet!V98 -> 0 | W13: =Worksheet!X98 -> 2139 | X13: =Worksheet!Y98 -> 5177 | Y13: =Worksheet!Z98 -> 0 | Z13: =Worksheet!AC98 -> 0

Sheet Worksheet
A1: Site Name | B1: Month | C1: Year | D1: Purchased Electricity kWh | E1: Purchased Electricity Tariff ($/kWh) | F1: Maximum Demand KVA/KW | G1: Maximum Demand Tariff ($/KVA || $/KW) | H1: Fixed Fees Cost ($) | I1: Electricity Total Budgeted | J1: Electricity Total Budgeted Cost ($) | K1: LPG Kitchen (Liters) | L1: LPG Kitchen $/Liters | M1: LPG Fixed Cost | N1: LPG Total Budgeted | O1: LPG Total Budgeted Cost ($) | P1: District Energy Heating kWh | Q1: District Energy Heating $/kWh | R1: Heating Fixed Cost | S1: Heating District Energy Total Budgeted | T1: Heating District Energy Total Budgeted Cost ($) | U1: Water Utility Supply (m3) m3 | V1: Water Utility Supply (m3) $/m3 | W1: Water Fixed Cost | X1: Water Total Budgeted | Y1: Water Total Budgeted Cost ($) | Z1: Room Nights | AA1: Room Nights Budget | AB1: Total Guests Budget | AC1: Total Guests | AD1: Laundry Load | AE1: Cooling Degree Day | AF1: Heating Degree Day | AG1: Onsite Generators kWh | AH1: Onsite Generators Cost ($) | AI1: Average PF | AJ1: Total Renewable Energy Production kWh | AK1: Total Renewable Energy Cost ($) | AL1: Total Renewable Energy Exported kWh | AM1: Total Renewable Energy Exported Cost ($) | AN1: Total Electricity Cost | AO1: Total Electricity kWh | AP1: Fuel Oil Hot-Water Boilers (Liter) Liter | AQ1: Fuel Oil Hot-Water Boilers (Liter) $/Liter | AR1: Fuel Oil Steam Boilers (Liter) Liter | AS1: Fuel Oil Steam Boilers (Liter) $/Liter | AT1: Fuel Oil Others (Liter) Liter | AU1: Fuel Oil Others (Liter) $/Liter | AV1: Onsite Generator Fuel Oil Liter | AW1: Onsite Generator Fuel Oil $/Liter | AX1: Fuel Oil Total Budgeted | AY1: Fuel Oil Total Budgeted Cost ($) | AZ1: LPG Hot-Water Boilers (Liters) | BA1: LPG Hot-Water Boilers $/Liters | BB1: LPG Steam Boilers (Liters) | BC1: LPG Steam Boilers $/Liters | BD1: Water RO (m3) m3 | BE1: Water RO (m3) $/m3 | BF1: Water Cisterns (m3) m3 | BG1: Water Cisterns (m3) $/m3 | BH1: Food Covers | BI1: Revenue | BJ1: Forex
A2: Annabelle | B2: 1 | C2: 2019 | D2: 172333 | E2: 0.15 | F2: 0 | G2: 0 | H2: 0 | I2: 155000 | J2: 24769 | K2: 4963 | L2: 0.444 | M2: 0 | N2: 5200 | O2: 2704 | P2: 0 | Q2: 0 | S2: 0 | T2: 949 | U2: 1256 | V2: 2.1323 | W2: 0 | X2: 2476 | Y2: 5280 | Z2: 5868 | AC2: 11119 | AD2: 0 | AG2: 0 | AH2: 0 | AJ2: 0 | AK2: 0 | AM2: 0 | AN2: 25850 | AO2: 172333 | AP2: 20980 | AQ2: 0.68 | AV2: 0 | AW2: 0 | AX2: 26000 | AY2: 17160 | AZ2: 0 | BA2: 0 | BB2: 0 | BC2: 0 | BD2: 0 | BE2: 0 | BF2: 0 | BG2: 0 | BH2: 0 | BJ2: 1
A3: Annabelle | B3: 2 | C3: 2019 | D3: 156988 | E3: 0.15 | F3: 0 | G3: 0 | H3: 0 | I3: 160000 | J3: 25568 | K3: 6214 | L3: 0.453 | M3: 0 | N3: 3600 | O3: 1872 | P3: 0 | Q3: 0 | S3: 0 | T3: 795 | U3: 3442 | V3: 2.0164 | W3: 0 | X3: 3142 | Y3: 6336 | Z3: 6460 | AC3: 12020 | AD3: 0 | AG3: 0 | AH3: 0 | AJ3: 0 | AK3: 0 | AM3: 0 | AN3: 23234 | AO3: 156988 | AP3: 15120 | AQ3: 0.51 | AV3: 0 | AW3: 0 | AX3: 24000 | AY3: 15840 | AZ3: 0 | BA3: 0 | BB3: 0 | BC3: 0 | BD3: 0 | BE3: 0 | BF3: 0 | BG3: 0 | BH3: 0 | BJ3: 1
A4: Annabelle | B4: 3 | C4: 2019 | D4: 174995 | E4: 0.15 | F4: 0 | G4: 0 | H4: 0 | I4: 190000 | J4: 30362 | K4: 5278 | L4: 0.316 | M4: 0 | N4: 4500 | O4: 2340 | P4: 0 | Q4: 0 | S4: 0 | T4: 943 | U4: 3416 | V4: 2.0144 | W4: 0 | X4: 4174 | Y4: 8410 | Z4: 7161 | AC4: 13479 | AD4: 0 | AG4: 0 | AH4: 0 | AJ4: 0 | AK4: 0 | AM4: 0 | AN4: 25374 | AO4: 174995 | AP4: 15080 | AQ4: 0.66 | AV4: 0 | AW4: 0 | AX4: 17000 | AY4: 11220 | AZ4: 0 | BA4: 0 | BB4: 0 | BC4: 0 | BD4: 0 | BE4: 0 | BF4: 0 | BG4: 0 | BH4: 0 | BJ4: 1
A5: Annabelle | B5: 4 | C5: 2019 | D5: 182624 | E5: 0.15 | F5: 0 | G5: 0 | H5: 0 | I5: 190000 | J5: 33417 | K5: 5308 | L5: 0.499 | M5: 0 | N5: 8166 | O5: 3838 | P5: 0 | Q5: 0 | S5: 0 | T5: 1065 | U5: 3746 | V5: 1.9388 | W5: 0 | X5: 5070 | Y5: 9830 | Z5: 7018 | AC5: 13914 | AD5: 0 | AG5: 0 | AH5: 0 | AJ5: 0 | AK5: 0 | AM5: 0 | AN5: 26846 | AO5: 182624 | AP5: 16800 | AQ5: 0.65 | AV5: 0 | AW5: 0 | AX5: 16521 | AY5: 10590 | AZ5: 0 | BA5: 0 | BB5: 0 | BC5: 0 | BD5: 0 | BE5: 0 | BF5: 0 | BG5: 0 | BH5: 0 | BJ5: 1
A6: Annabelle | B6: 5 | C6: 2019 | D6: 222859 | E6: 0.16 | F6: 0 | G6: 0 | H6: 0 | I6: 263932 | J6: 43749 | K6: 4945 | L6: 0.495 | M6: 0 | N6: 5749 | O6: 2702 | P6: 0 | Q6: 0 | S6: 0 | T6: 580 | U6: 3817 | V6: 1.9452 | W6: 0 | X6: 4476 | Y6: 8707 | Z6: 6507 | AC6: 12912 | AD6: 0 | AG6: 0 | AH6: 0 | AJ6: 0 | AK6: 0 | AM6: 0 | AN6: 34989 | AO6: 222859 | AP6: 9780 | AQ6: 0.66 | AV6: 0 | AW6: 0 | AX6: 6890 | AY6: 4437 | AZ6: 0 | BA6: 0 | BB6: 0 | BC6: 0 | BD6: 0 | BE6: 0 | BF6: 0 | BG6: 0 | BH6: 0 | BJ6: 1
A7: Annabelle | B7: 6 | C7: 2019 | D7: 313305 | E7: 0.19 | F7: 0 | G7: 0 | H7: 0 | I7: 327988 | J7: 52384 | K7: 4977 | L7: 0.478 | M7: 0 | N7: 5859 | O7: 2994 | P7: 0 | Q7: 0 | S7: 0 | T7: 570 | U7: 3920 | V7: 1.9535 | W7: 0 | X7: 3345 | Y7: 6536 | Z7: 6559 | AC7: 12796 | AD7: 0 | AG7: 0 | AH7: 0 | AJ7: 0 | AK7: 0 | AM7: 0 | AN7: 58275 | AO7: 313305 | AP7: 7680 | AQ7: 0.65 | AV7: 0 | AW7: 0 | AX7: 5527 | AY7: 3913 | AZ7: 0 | BA7: 0 | BB7: 0 | BC7: 0 | BD7: 0 | BE7: 0 | BF7: 0 | BG7: 0 | BH7: 0 | BJ7: 1
A8: Annabelle | B8: 7 | C8: 2019 | D8: 371075 | E8: 0.18 | F8: 0 | G8: 0 | H8: 0 | I8: 366009 | J8: 65668 | K8: 4755 | L8: 0.454 | M8: 0 | N8: 4501 | O8: 2984 | P8: 0 | Q8: 0 | S8: 0 | T8: 470 | U8: 3972 | V8: 2.2263 | W8: 0 | X8: 4380 | Y8: 9752 | Z8: 5658 | AC8: 11964 | AD8: 0 | AG8: 0 | AH8: 0 | AJ8: 0 | AK8: 0 | AM8: 0 | AN8: 66422 | AO8: 371075 | AP8: 6720 | AQ8: 0.69 | AV8: 0 | AW8: 0 | AX8: 4523 | AY8: 3121 | AZ8: 0 | BA8: 0 | BB8: 0 | BC8: 0 | BD8: 0 | BE8: 0 | BF8: 0 | BG8: 0 | BH8: 0 | BJ8: 1
A9: Annabelle | B9: 8 | C9: 2019 | D9: 352685 | E9: 0.18 | F9: 0 | G9: 0 | H9: 0 | I9: 368312 | J9: 67645 | K9: 4862 | L9: 0.45 | M9: 0 | N9: 5303 | O9: 2784 | P9: 0 | Q9: 0 | S9: 0 | T9: 495 | U9: 4105 | V9: 2.2278 | W9: 0 | X9: 4338 | Y9: 9666 | Z9: 6231 | AC9: 13547 | AD9: 0 | AG9: 0 | AH9: 0 | AJ9: 0 | AK9: 0 | AM9: 0 | AN9: 64541 | AO9: 352685 | AP9: 5540 | AQ9: 0.66 | AV9: 0 | AW9: 0 | AX9: 4230 | AY9: 2919 | AZ9: 0 | BA9: 0 | BB9: 0 | BC9: 0 | BD9: 0 | BE9: 0 | BF9: 0 | BG9: 0 | BH9: 0 | BJ9: 1
A10: Annabelle | B10: 9 | C10: 2019 | D10: 309098 | E10: 0.19 | F10: 0 | G10: 0 | H10: 0 | I10: 330356 | J10: 56557 | K10: 4561 | L10: 0.409 | M10: 0 | N10: 5035 | O10: 2719 | P10: 0 | Q10: 0 | S10: 0 | T10: 444 | U10: 3749 | V10: 2.2238 | W10: 0 | X10: 3686 | Y10: 8199 | Z10: 6189 | AC10: 11866 | AD10: 0 | AG10: 0 | AH10: 0 | AJ10: 0 | AK10: 0 | AM10: 0 | AN10: 58420 | AO10: 309098 | AP10: 3780 | AQ10: 0.67 | AV10: 0 | AW10: 0 | AX10: 3725 | AY10: 2697 | AZ10: 0 | BA10: 0 | BB10: 0 | BC10: 0 | BD10: 0 | BE10: 0 | BF10: 0 | BG10: 0 | BH10: 0 | BJ10: 1
A11: Annabelle | B11: 10 | C11: 2019 | D11: 263139 | E11: 0.16 | F11: 0 | G11: 0 | H11: 0 | I11: 270935 | J11: 48033 | K11: 5125 | L11: 0.435 | M11: 0 | N11: 4841 | O11: 2677 | P11: 0 | Q11: 0 | S11: 0 | T11: 612 | U11: 4112 | V11: 2.2279 | W11: 0 | X11: 3861 | Y11: 8603 | Z11: 6813 | AC11: 13451 | AD11: 0 | AG11: 0 | AH11: 0 | AJ11: 0 | AK11: 0 | AM11: 0 | AN11: 42629 | AO11: 263139 | AP11: 7370 | AQ11: 0.67 | AV11: 0 | AW11: 0 | AX11: 8218 | AY11: 5950 | AZ11: 0 | BA11: 0 | BB11: 0 | BC11: 0 | BD11: 0 | BE11: 0 | BF11: 0 | BG11: 0 | BH11: 0 | BJ11: 1
A12: Annabelle | B12: 11 | C12: 2019 | D12: 192061 | E12: 0.16 | F12: 0 | G12: 0 | H12: 0 | I12: 186734 | J12: 28560 | K12: 4904 | L12: 0.457 | M12: 0 | N12: 4844 | O12: 2635 | P12: 0 | Q12: 0 | S12: 0 | T12: 1075 | U12: 3997 | V12: 2.2267 | W12: 0 | X12: 2429 | Y12: 5409 | Z12: 7012 | AC12: 13113 | AD12: 0 | AG12: 0 | AH12: 0 | AJ12: 0 | AK12: 0 | AM12: 0 | AN12: 30538 | AO12: 192061 | AP12: 6630 | AQ12: 0.67 | AV12: 0 | AW12: 0 | AX12: 8223 | AY12: 6134 | AZ12: 0 | BA12: 0 | BB12: 0 | BC12: 0 | BD12: 0 | BE12: 0 | BF12: 0 | BG12: 0 | BH12: 0 | BJ12: 1
A13: Annabelle | B13: 12 | C13: 2019 | D13: 168571 | E13: 0.16 | F13: 0 | G13: 0 | H13: 0 | I13: 170000 | J13: 28581 | K13: 5062 | L13: 0.477 | M13: 0 | N13: 3975 | O13: 2067 | P13: 0 | Q13: 0 | S13: 0 | T13: 1311 | U13: 3285 | V13: 2.2174 | W13: 0 | X13: 2473 | Y13: 5485 | Z13: 6256 | AC13: 11440 | AD13: 0 | AG13: 0 | AH13: 0 | AJ13: 0 | AK13: 0 | AM13: 0 | AN13: 26971 | AO13: 168571 | AP13: 14560 | AQ13: 0.65 | AV13: 0 | AW13: 0 | AX13: 17885 | AY13: 11804 | AZ13: 0 | BA13: 0 | BB13: 0 | BC13: 0 | BD13: 0 | BE13: 0 | BF13: 0 | BG13: 0 | BH13: 0 | BJ13: 1
... A25: Annabelle | B25: 12 | C25: 2020 | D25: 40902 | E25: 0.13 | F25: 0 | G25: 0 | H25: 0 | I25: 122289 | J25: 19697 | K25: 500 | L25: 0.46 | M25: 0 | N25: 3648 | O25: 1751 | P25: 0 | Q25: 0 | S25: 0 | T25: 0 | U25: 679 | V25: 2.5243 | W25: 0 | X25: 2093 | Y25: 5284 | Z25: 1000 | AC25: 1271 | AD25: 0 | AG25: 0 | AH25: 0 | AJ25: 0 | AK25: 0 | AM25: 0 | AN25: 5276 | AO25: 40902 | AP25: 3600 | AQ25: 0.46 | AV25: 0 | AW25: 0 | AX25: 10525 | AY25: 6841 | AZ25: 0 | BA25: 0 | BB25: 0 | BC25: 0 | BD25: 0 | BE25: 0 | BF25: 0 | BG25: 0 | BH25: 0 | BJ25: 1
A26: Annabelle | B26: 1 | C26: 2021 | D26: 52563 | E26: 0.12 | F26: 0 | G26: 0 | H26: 0 | I26: 3964 | J26: 0 | K26: 0 | L26: 0 | M26: 0 | N26: 0 | O26: 0 | P26: 0 | Q26: 0 | S26: 0 | T26: 0 | U26: 245 | V26: 2.2857 | W26: 0 | X26: 0 | Y26: 0 | Z26: 2270 | AC26: 3057 | AD26: 0 | AG26: 0 | AH26: 0 | AJ26: 0 | AK26: 0 | AM26: 0 | AN26: 6360 | AO26: 52563 | AP26: 5740 | AQ26: 0.46 | AV26: 0 | AW26: 0 | AZ26: 0 | BA26: 0 | BB26: 0 | BC26: 0 | BD26: 0 | BE26: 0 | BF26: 0 | BG26: 0 | BH26: 0 | BJ26: 1
A27: Annabelle | B27: 2 | C27: 2021 | D27: 25827 | E27: 0.13 | F27: 0 | G27: 0 | H27: 0 | I27: 0 | J27: 0 | K27: 0 | L27: 0 | M27: 0 | N27: 0 | O27: 0 | P27: 0 | Q27: 0 | S27: 0 | T27: 0 | U27: 676 | V27: 1.7663 | W27: 0 | X27: 0 | Y27: 0 | Z27: 5 | AC27: 10 | AD27: 0 | AG27: 0 | AH27: 0 | AJ27: 0 | AK27: 0 | AM27: 0 | AN27: 3254 | AO27: 25827 | AV27: 0 | AW27: 0 | AZ27: 0 | BA27: 0 | BB27: 0 | BC27: 0 | BD27: 0 | BE27: 0 | BF27: 0 | BG27: 0 | BH27: 0 | BJ27: 1
A28: Annabelle | B28: 3 | C28: 2021 | D28: 62984 | E28: 0.14 | F28: 0 | G28: 0 | H28: 0 | I28: 83179 | J28: 12065 | K28: 0 | L28: 0.46 | M28: 0 | N28: 2478 | O28: 793 | P28: 0 | Q28: 0 | S28: 0 | T28: 0 | U28: 1654 | V28: 2.1977 | W28: 0 | X28: 1488 | Y28: 3271 | Z28: 1137 | AC28: 2629 | AD28: 0 | AG28: 0 | AH28: 0 | AJ28: 0 | AK28: 0 | AM28: 0 | AN28: 8881 | AO28: 62984 | AP28: 8020 | AQ28: 0.5 | AV28: 0 | AW28: 0 | AX28: 7150 | AY28: 4719 | AZ28: 0 | BA28: 0 | BB28: 0 | BC28: 0 | BD28: 0 | BE28: 0 | BF28: 0 | BG28: 0 | BH28: 0 | BJ28: 1
A29: Annabelle | B29: 4 | C29: 2021 | D29: 116793 | E29: 0.14 | F29: 0 | G29: 0 | H29: 0 | I29: 139243 | J29: 20509 | K29: 1455 | L29: 0.376 | M29: 0 | N29: 4038 | O29: 2019 | P29: 0 | Q29: 0 | S29: 0 | T29: 0 | U29: 1652 | V29: 2.1973 | W29: 0 | X29: 2519 | Y29: 5537 | Z29: 1762 | AC29: 3369 | AD29: 0 | AG29: 0 | AH29: 0 | AJ29: 0 | AK29: 0 | AM29: 0 | AN29: 16701 | AO29: 116793 | AP29: 9580 | AQ29: 0.6 | AV29: 0 | AW29: 0 | AX29: 12883 | AY29: 8374 | AZ29: 0 | BA29: 0 | BB29: 0 | BC29: 0 | BD29: 0 | BE29: 0 | BF29: 0 | BG29: 0 | BH29: 0 | BJ29: 1
A30: Annabelle | B30: 5 | C30: 2021 | D30: 153573 | E30: 0.15 | F30: 0 | G30: 0 | H30: 0 | I30: 204399 | J30: 32061 | K30: 1644 | L30: 0.447 | M30: 0 | N30: 4494 | O30: 2247 | P30: 0 | Q30: 0 | S30: 0 | T30: 0 | U30: 2244 | V30: 2.193 | W30: 0 | X30: 3105 | Y30: 6810 | Z30: 1189 | AC30: 2040 | AD30: 0 | AG30: 0 | AH30: 0 | AJ30: 0 | AK30: 0 | AM30: 0 | AN30: 23343 | AO30: 153573 | AP30: 5266 | AQ30: 0.59 | AV30: 0 | AW30: 0 | AX30: 8974 | AY30: 5923 | AZ30: 0 | BA30: 0 | BB30: 0 | BC30: 0 | BD30: 0 | BE30: 0 | BF30: 0 | BG30: 0 | BH30: 0 | BJ30: 1
A31: Annabelle | B31: 6 | C31: 2021 | D31: 226807 | E31: 0.18 | F31: 0 | G31: 0 | H31: 0 | I31: 284270 | J31: 52777 | K31: 2217 | L31: 0.447 | M31: 0 | N31: 4496 | O31: 2158 | P31: 0 | Q31: 0 | S31: 0 | T31: 0 | U31: 2300 | V31: 2.19 | W31: 0 | X31: 3172 | Y31: 6948 | Z31: 2064 | AC31: 3907 | AD31: 0 | AG31: 0 | AH31: 0 | AJ31: 0 | AK31: 0 | AM31: 0 | AN31: 41279 | AO31: 226807 | AP31: 3480 | AQ31: 0.41 | AV31: 0 | AW31: 0 | AX31: 6994 | AY31: 4546 | AZ31: 0 | BA31: 0 | BB31: 0 | BC31: 0 | BD31: 0 | BE31: 0 | BF31: 0 | BG31: 0 | BH31: 0 | BJ31: 1
A32: Annabelle | B32: 7 | C32: 2021 | D32: 311641 | E32: 0.18 | F32: 0 | G32: 0 | H32: 0 | I32: 408769 | J32: 73327 | K32: 3185 | L32: 0.498 | M32: 0 | N32: 5282 | O32: 2377 | P32: 0 | Q32: 0 | S32: 0 | T32: 0 | U32: 2516 | V32: 2.2019 | W32: 0 | X32: 4423 | Y32: 9741 | Z32: 2310 | AC32: 4583 | AD32: 0 | AG32: 0 | AH32: 0 | AJ32: 0 | AK32: 0 | AM32: 0 | AN32: 56407 | AO32: 311641 | AP32: 3620 | AQ32: 0.63 | AV32: 0 | AW32: 0 | AX32: 7414 | AY32: 5116 | AZ32: 0 | BA32: 0 | BB32: 0 | BC32: 0 | BD32: 0 | BE32: 0 | BF32: 0 | BG32: 0 | BH32: 0 | BJ32: 1
A33: Annabelle | B33: 8 | C33: 2021 | D33: 368246 | E33: 0.18 | F33: 0 | G33: 0 | H33: 0 | I33: 364771 | J33: 66634 | K33: 3110 | L33: 0.52 | M33: 0 | N33: 5024 | O33: 2261 | P33: 0 | Q33: 0 | S33: 0 | T33: 0 | U33: 3240 | V33: 2.216 | W33: 0 | X33: 4268 | Y33: 9458 | Z33: 3888 | AC33: 8401 | AD33: 0 | AG33: 0 | AH33: 0 | AJ33: 0 | AK33: 0 | AM33: 0 | AN33: 66284 | AO33: 368246 | AP33: 3980 | AQ33: 0.58 | AV33: 0 | AW33: 0 | AX33: 5771 | AY33: 3809 | AZ33: 0 | BA33: 0 | BB33: 0 | BC33: 0 | BD33: 0 | BE33: 0 | BF33: 0 | BG33: 0 | BH33: 0 | BJ33: 1
A34: Annabelle | B34: 9 | C34: 2021 | D34: 285473 | E34: 0.19 | F34: 0 | G34: 0 | H34: 0 | I34: 290639 | J34: 54917 | K34: 2785 | L34: 0.55 | M34: 0 | N34: 4280 | O34: 1755 | P34: 0 | Q34: 0 | S34: 0 | T34: 0 | U34: 2810 | V34: 2.3616 | W34: 0 | X34: 3319 | Y34: 7839 | Z34: 3620 | AC34: 6621 | AD34: 0 | AG34: 0 | AH34: 0 | AJ34: 0 | AK34: 0 | AM34: 0 | AN34: 54525 | AO34: 285473 | AP34: 4260 | AQ34: 0.64 | AV34: 0 | AW34: 0 | AX34: 3533 | AY34: 2367 | AZ34: 0 | BA34: 0 | BB34: 0 | BC34: 0 | BD34: 0 | BE34: 0 | BF34: 0 | BG34: 0 | BH34: 0 | BJ34: 1
A35: Annabelle | B35: 10 | C35: 2021 | D35: 266723 | E35: 0.2 | F35: 0 | G35: 0 | H35: 0 | I35: 246639 | J35: 39962 | K35: 4282 | L35: 0.57 | M35: 0 | N35: 4757 | O35: 2093 | P35: 0 | Q35: 0 | S35: 0 | T35: 0 | U35: 3606 | V35: 2.2219 | W35: 0 | X35: 3867 | Y35: 8594 | Z35: 6372 | AC35: 12759 | AD35: 0 | AG35: 0 | AH35: 0 | AJ35: 0 | AK35: 0 | AM35: 0 | AN35: 52544 | AO35: 266723 | AP35: 8620 | AQ35: 0.58 | AV35: 0 | AW35: 0 | AX35: 6873 | AY35: 4605 | AZ35: 0 | BA35: 0 | BB35: 0 | BC35: 0 | BD35: 0 | BE35: 0 | BF35: 0 | BG35: 0 | BH35: 0 | BJ35: 1
A36: Annabelle | B36: 11 | C36: 2021 | D36: 189874 | E36: 0.21 | F36: 0 | G36: 0 | H36: 0 | I36: 160398 | J36: 25527 | K36: 3732 | L36: 0.67 | M36: 0 | N36: 4070 | O36: 1872 | P36: 0 | Q36: 0 | S36: 0 | T36: 0 | U36: 3296 | V36: 2.2178 | W36: 0 | X36: 3351 | Y36: 7433 | Z36: 5905 | AC36: 11104 | AD36: 0 | AG36: 0 | AH36: 0 | AJ36: 0 | AK36: 0 | AM36: 0 | AN36: 38924 | AO36: 189874 | AP36: 12080 | AQ36: 0.73 | AV36: 0 | AW36: 0 | AX36: 5503 | AY36: 3687 | AZ36: 0 | BA36: 0 | BB36: 0 | BC36: 0 | BD36: 0 | BE36: 0 | BF36: 0 | BG36: 0 | BH36: 0 | BJ36: 1
A37: Annabelle | B37: 12 | C37: 2021 | D37: 140763 | E37: 0.2 | F37: 0 | G37: 0 | H37: 0 | I37: 61145 | J37: 0 | K37: 3301 | L37: 0.65 | M37: 0 | N37: 0 | O37: 0 | P37: 0 | Q37: 0 | S37: 0 | T37: 0 | U37: 2285 | V37: 2.1934 | W37: 0 | X37: 0 | Y37: 0 | Z37: 3033 | AC37: 5416 | AD37: 0 | AG37: 0 | AH37: 0 | AJ37: 0 | AK37: 0 | AM37: 0 | AN37: 28153 | AO37: 140763 | AP37: 8655 | AQ37: 0.74 | AV37: 0 | AW37: 0 | AX37: 0 | AZ37: 0 | BA37: 0 | BB37: 0 | BC37: 0 | BD37: 0 | BE37: 0 | BF37: 0 | BG37: 0 | BH37: 0 | BJ37: 1
A38: Annabelle | B38: 1 | C38: 2022 | D38: 123469 | E38: 0.19 | F38: 0 | G38: 0 | H38: 0 | I38: 123469 | J38: 27348 | K38: 2615 | L38: 0.67 | M38: 0 | N38: 3983 | O38: 1832 | P38: 150494 | Q38: 0.0847 | S38: 67032 | T38: 5679 | U38: 1476 | V38: 2.15 | W38: 0 | X38: 1053 | Y38: 2269 | Z38: 1622 | AC38: 2729 | AD38: 0 | AG38: 0 | AH38: 0 | AJ38: 0 | AK38: 0 | AM38: 0 | AN38: 23089 | AO38: 123469 | AP38: 0 | AQ38: 0 | AV38: 0 | AW38: 0 | AX38: 0 | AZ38: 0 | BA38: 0 | BB38: 0 | BC38: 0 | BD38: 0 | BE38: 0 | BF38: 0 | BG38: 0 | BH38: 0 | BJ38: 1
A39: Annabelle | B39: 2 | C39: 2022 | D39: 113911 | E39: 0.18 | F39: 0 | G39: 0 | H39: 0 | I39: 113911 | J39: 24366 | K39: 2813 | L39: 0.63 | M39: 0 | N39: 2891 | O39: 1243 | P39: 155635 | Q39: 0.0847 | S39: 74592 | T39: 6320 | U39: 1779 | V39: 2.19 | W39: 0 | X39: 1940 | Y39: 4255 | Z39: 2980 | AC39: 5216 | AD39: 0 | AG39: 0 | AH39: 0 | AJ39: 0 | AK39: 0 | AM39: 0 | AN39: 20504 | AO39: 113911 | AP39: 160 | AQ39: 0.72 | AV39: 0 | AW39: 0 | AX39: 0 | AZ39: 0 | BA39: 0 | BB39: 0 | BC39: 0 | BD39: 0 | BE39: 0 | BF39: 0 | BG39: 0 | BH39: 0 | BJ39: 1
A40: Annabelle | B40: 3 | C40: 2022 | D40: 154893 | E40: 0.23 | F40: 0 | G40: 0 | H40: 0 | I40: 154893 | J40: 34851 | K40: 3664 | L40: 0.71 | M40: 0 | N40: 3348 | O40: 1540 | P40: 227758 | Q40: 0.0847 | S40: 123984 | T40: 10504 | U40: 2776 | V40: 2.19 | W40: 0 | X40: 2486 | Y40: 5436 | Z40: 4582 | AC40: 8590 | AD40: 0 | AG40: 0 | AH40: 0 | AJ40: 0 | AK40: 0 | AM40: 0 | AN40: 35006 | AO40: 154893 | AP40: 140 | AQ40: 0.73 | AV40: 0 | AW40: 0 | AX40: 0 | AZ40: 0 | BA40: 0 | BB40: 0 | BC40: 0 | BD40: 0 | BE40: 0 | BF40: 0 | BG40: 0 | BH40: 0 | BJ40: 1
A41: Annabelle | B41: 4 | C41: 2022 | D41: 188855 | E41: 0.23 | F41: 0 | G41: 0 | H41: 0 | I41: 154572 | J41: 34779 | K41: 4549 | L41: 0.73 | M41: 0 | N41: 4537 | O41: 2223 | P41: 198500 | Q41: 0.0847 | S41: 0 | T41: 0 | U41: 3758 | V41: 2.22 | W41: 0 | X41: 3528 | Y41: 7840 | Z41: 6172 | AC41: 12832 | AD41: 0 | AG41: 0 | AH41: 0 | AJ41: 0 | AK41: 0 | AM41: 0 | AN41: 43814 | AO41: 188855 | AP41: 0 | AQ41: 0 | AV41: 0 | AW41: 0 | AX41: 18461 | AY41: 12184 | AZ41: 0 | BA41: 0 | BB41: 0 | BC41: 0 | BD41: 0 | BE41: 0 | BF41: 0 | BG41: 0 | BH41: 0 | BJ41: 1
A42: Annabelle | B42: 5 | C42: 2022 | D42: 221809 | E42: 0.25 | F42: 0 | G42: 0 | H42: 0 | I42: 189124 | J42: 42553 | K42: 4125 | L42: 0.7 | M42: 0 | N42: 4160 | O42: 1997 | P42: 108108 | Q42: 0.0847 | S42: 0 | T42: 0 | U42: 3973 | V42: 2.23 | W42: 0 | X42: 3941 | Y42: 8776 | Z42: 5894 | AC42: 11361 | AD42: 0 | AG42: 0 | AH42: 0 | AJ42: 0 | AK42: 0 | AM42: 0 | AN42: 54343 | AO42: 221809 | AP42: 0 | AQ42: 0 | AV42: 0 | AW42: 0 | AX42: 10780 | AY42: 7007 | AZ42: 0 | BA42: 0 | BB42: 0 | BC42: 0 | BD42: 0 | BE42: 0 | BF42: 0 | BG42: 0 | BH42: 0 | BJ42: 1
A43: Annabelle | B43: 6 | C43: 2022 | D43: 294114 | E43: 0.33 | F43: 0 | G43: 0 | H43: 0 | I43: 298067 | J43: 67065 | K43: 4303 | L43: 0.77 | M43: 0 | N43: 4774 | O43: 2196 | P43: 51862 | Q43: 0.1058 | S43: 0 | T43: 0 | U43: 3757 | V43: 2.24 | W43: 0 | X43: 5005 | Y43: 11196 | Z43: 5977 | AC43: 11878 | AD43: 0 | AG43: 0 | AH43: 0 | AJ43: 0 | AK43: 0 | AM43: 0 | AN43: 97352 | AO43: 294114 | AP43: 620 | AQ43: 1.05 | AV43: 0 | AW43: 0 | AX43: 9532 | AY43: 6291 | AZ43: 0 | BA43: 0 | BB43: 0 | BC43: 0 | BD43: 0 | BE43: 0 | BF43: 0 | BG43: 0 | BH43: 0 | BJ43: 1
A44: Annabelle | B44: 7 | C44: 2022 | D44: 360191 | E44: 0.33 | F44: 0 | G44: 0 | H44: 0 | I44: 371775 | J44: 83649 | K44: 4637 | L44: 0.78 | M44: 0 | N44: 5304 | O44: 2493 | P44: 54180 | Q44: 0.0992 | S44: 0 | T44: 0 | U44: 4033 | V44: 2.35 | W44: 0 | X44: 5091 | Y44: 11965 | Z44: 5937 | AC44: 12747 | AD44: 0 | AG44: 0 | AH44: 0 | AJ44: 0 | AK44: 0 | AM44: 0 | AN44: 119583 | AO44: 360191 | AP44: 0 | AQ44: 0 | AV44: 0 | AW44: 0 | AX44: 9791 | AY44: 6560 | AZ44: 0 | BA44: 0 | BB44: 0 | BC44: 0 | BD44: 0 | BE44: 0 | BF44: 0 | BG44: 0 | BH44: 0 | BJ44: 1
A45: Annabelle | B45: 8 | C45: 2022 | D45: 393401 | E45: 0.33 | F45: 0 | G45: 0 | H45: 0 | I45: 387042 | J45: 87084 | K45: 3133 | L45: 0.73 | M45: 0 | N45: 5278 | O45: 2375 | P45: 53374 | Q45: 0.0992 | S45: 0 | T45: 0 | U45: 4022 | V45: 2.35 | W45: 0 | X45: 5145 | Y45: 12093 | Z45: 6064 | AC45: 14395 | AD45: 0 | AG45: 0 | AH45: 0 | AJ45: 0 | AK45: 0 | AM45: 0 | AN45: 131003 | AO45: 393401 | AP45: 0 | AQ45: 0 | AV45: 0 | AW45: 0 | AX45: 7893 | AY45: 5288 | AZ45: 0 | BA45: 0 | BB45: 0 | BC45: 0 | BD45: 0 | BE45: 0 | BF45: 0 | BG45: 0 | BH45: 0 | BJ45: 1
A46: Annabelle | B46: 9 | C46: 2022 | D46: 327771 | E46: 0.32 | F46: 0 | G46: 0 | H46: 0 | I46: 281729 | J46: 63389 | K46: 3788 | L46: 0.69 | M46: 0 | N46: 4145 | O46: 1741 | P46: 51106 | Q46: 0.1167 | S46: 0 | T46: 0 | U46: 3814 | V46: 2.35 | W46: 0 | X46: 4244 | Y46: 9974 | Z46: 5932 | AC46: 11392 | AD46: 0 | AG46: 0 | AH46: 0 | AJ46: 0 | AK46: 0 | AM46: 0 | AN46: 105214 | AO46: 327771 | AP46: 0 | AQ46: 0 | AV46: 0 | AW46: 0 | AX46: 4467 | AY46: 2993 | AZ46: 0 | BA46: 0 | BB46: 0 | BC46: 0 | BD46: 0 | BE46: 0 | BF46: 0 | BG46: 0 | BH46: 0 | BJ46: 1
A47: Annabelle | B47: 10 | C47: 2022 | D47: 257626 | E47: 0.28 | F47: 0 | G47: 0 | H47: 0 | I47: 257848 | J47: 58016 | K47: 4518 | L47: 0.82 | M47: 0 | N47: 50 | O47: 2143 | P47: 77742 | Q47: 0.0992 | S47: 0 | T47: 0 | U47: 3825 | V47: 2.35 | W47: 0 | X47: 4472 | Y47: 10510 | Z47: 6495 | AC47: 13192 | AD47: 0 | AG47: 0 | AH47: 0 | AJ47: 0 | AK47: 0 | AM47: 0 | AN47: 72651 | AO47: 257626 | AP47: 1660 | AQ47: 0.96 | AV47: 0 | AW47: 0 | AX47: 9331 | AY47: 6252 | AZ47: 0 | BA47: 0 | BB47: 0 | BC47: 0 | BD47: 0 | BE47: 0 | BF47: 0 | BG47: 0 | BH47: 0 | BJ47: 1
A48: Annabelle | B48: 11 | C48: 2022 | D48: 177666 | E48: 0.28 | F48: 0 | G48: 0 | H48: 0 | I48: 145087 | J48: 32644 | K48: 8048 | L48: 0.6 | M48: 0 | N48: 3682 | O48: 1841 | P48: 80917 | Q48: 0.0992 | S48: 0 | T48: 0 | U48: 2691 | V48: 2.4 | W48: 0 | X48: 3187 | Y48: 7651 | Z48: 4747 | AC48: 9084 | AD48: 0 | AG48: 0 | AH48: 0 | AJ48: 0 | AK48: 0 | AM48: 0 | AN48: 49924 | AO48: 177666 | AP48: 0 | AQ48: 0 | AV48: 0 | AW48: 0 | AX48: 6472 | AY48: 4336 | AZ48: 0 | BA48: 0 | BB48: 0 | BC48: 0 | BD48: 0 | BE48: 0 | BF48: 0 | BG48: 0 | BH48: 0 | BJ48: 1
A49: Annabelle | B49: 12 | C49: 2022 | D49: 135051 | E49: 0.28 | F49: 0 | G49: 0 | H49: 0 | I49: 79759 | J49: 17946 | K49: 2524 | L49: 0.84 | M49: 0 | N49: 2404 | O49: 1322 | P49: 0 | Q49: 0.0992 | S49: 0 | T49: 0 | U49: 1965 | V49: 1.99 | W49: 0 | X49: 2059 | Y49: 4103 | Z49: 2234 | AC49: 4185 | AD49: 0 | AG49: 0 | AH49: 0 | AJ49: 0 | AK49: 0 | AM49: 0 | AN49: 37949 | AO49: 135051 | AP49: 0 | AQ49: 0 | AV49: 0 | AW49: 0 | AX49: 8921 | AY49: 6245 | AZ49: 0 | BA49: 0 | BB49: 0 | BC49: 0 | BD49: 0 | BE49: 0 | BF49: 0 | BG49: 0 | BH49: 0 | BJ49: 1
A50: Annabelle | B50: 1 | C50: 2023 | D50: 124702 | E50: 0.28 | F50: 0 | G50: 0 | H50: 0 | I50: 123469 | J50: 31170 | K50: 2237 | L50: 0.77 | M50: 0 | N50: 2484 | O50: 1739 | P50: 131947 | Q50: 0.1151 | S50: 150494 | T50: 17319 | U50: 1958 | V50: 2.4 | W50: 0 | X50: 1059 | Y50: 2543 | Z50: 1956 | AC50: 0 | AD50: 0 | AE50: 0.1 | AF50: 72 | AG50: 0 | AH50: 0 | AJ50: 0 | AK50: 0 | AM50: 0 | AN50: 34418 | AO50: 124702 | AP50: 0 | AQ50: 0 | AV50: 0 | AW50: 0 | AX50: 0 | AY50: 0 | AZ50: 0 | BA50: 0 | BB50: 0 | BC50: 0 | BD50: 0 | BE50: 0 | BF50: 0 | BG50: 0 | BH50: 0 | BJ50: 1
A51: Annabelle | B51: 2 | C51: 2023 | D51: 125023 | E51: 0.28 | F51: 0 | G51: 0 | H51: 0 | I51: 113911 | J51: 28757 | K51: 2548 | L51: 0.63 | M51: 0 | N51: 3 | O51: 2 | P51: 198349 | Q51: 0.1151 | S51: 155635 | T51: 17910 | U51: 2226 | V51: 2.37 | W51: 0 | X51: 1298 | Y51: 3078 | Z51: 2871 | AC51: 0 | AD51: 0 | AE51: 1.2 | AF51: 110.4 | AG51: 0 | AH51: 0 | AJ51: 0 | AK51: 0 | AM51: 0 | AN51: 35256 | AO51: 125023 | AP51: 0 | AQ51: 0 | AV51: 0 | AW51: 0 | AX51: 0 | AY51: 0 | AZ51: 0 | BA51: 0 | BB51: 0 | BC51: 0 | BD51: 0 | BE51: 0 | BF51: 0 | BG51: 0 | BH51: 0 | BJ51: 1
A52: Annabelle | B52: 3 | C52: 2023 | D52: 152841 | E52: 0.27 | F52: 0 | G52: 0 | H52: 0 | I52: 154893 | J52: 39103 | K52: 3481 | L52: 0.56 | M52: 0 | N52: 3481 | O52: 2437 | P52: 183128 | Q52: 0.1151 | S52: 227758 | T52: 26210 | U52: 3033 | V52: 2.37 | W52: 0 | X52: 1668 | Y52: 3954 | Z52: 4507 | AC52: 0 | AD52: 0 | AE52: 1.8 | AF52: 39.1 | AG52: 0 | AH52: 0 | AJ52: 0 | AK52: 0 | AM52: 0 | AN52: 40656 | AO52: 152841 | AP52: 0 | AQ52: 0 | AV52: 0 | AW52: 0 | AX52: 0 | AY52: 0 | AZ52: 0 | BA52: 0 | BB52: 0 | BC52: 0 | BD52: 0 | BE52: 0 | BF52: 0 | BG52: 0 | BH52: 0 | BJ52: 1
A53: Annabelle | B53: 4 | C53: 2023 | D53: 178614 | E53: 0.27 | F53: 0 | G53: 0 | H53: 0 | I53: 188855 | J53: 47676 | K53: 4411 | L53: 0.62 | M53: 0 | N53: 4321 | O53: 3025 | P53: 164934 | Q53: 0.1151 | S53: 198500 | T53: 22843 | U53: 3962 | V53: 2.37 | W53: 0 | X53: 3018 | Y53: 7155 | Z53: 6121 | AC53: 0 | AD53: 0 | AE53: 6.4 | AF53: 16.5 | AG53: 0 | AH53: 0 | AJ53: 0 | AK53: 0 | AM53: 0 | AN53: 48404 | AO53: 178614 | AP53: 1200 | AQ53: 0.71 | AV53: 0 | AW53: 0 | AX53: 0 | AY53: 0 | AZ53: 0 | BA53: 0 | BB53: 0 | BC53: 0 | BD53: 0 | BE53: 0 | BF53: 0 | BG53: 0 | BH53: 0 | BJ53: 1
A54: Annabelle | B54: 5 | C54: 2023 | D54: 193764 | E54: 0.26 | F54: 0 | G54: 0 | H54: 0 | I54: 221809 | J54: 39197 | K54: 4051 | L54: 0.77 | M54: 0 | N54: 3919 | O54: 2743 | P54: 103194 | Q54: 0.1151 | S54: 108108 | T54: 12441 | U54: 3501 | V54: 2.37 | W54: 0 | X54: 3613 | Y54: 8563 | Z54: 5923 | AC54: 0 | AD54: 0 | AE54: 47.7 | AF54: 1.3 | AG54: 0 | AH54: 0 | AJ54: 0 | AK54: 0 | AM54: 0 | AN54: 49797 | AO54: 193764 | AP54: 0 | AQ54: 0 | AV54: 0 | AW54: 0 | AX54: 0 | AY54: 0 | AZ54: 0 | BA54: 0 | BB54: 0 | BC54: 0 | BD54: 0 | BE54: 0 | BF54: 0 | BG54: 0 | BH54: 0 | BJ54: 1
A55: Annabelle | B55: 6 | C55: 2023 | D55: 238174 | E55: 0.28 | F55: 0 | G55: 0 | H55: 0 | I55: 294114 | J55: 51974 | K55: 4078 | L55: 0.65 | M55: 0 | N55: 4087 | O55: 2861 | P55: 53273 | Q55: 0.1151 | S55: 51862 | T55: 5968 | U55: 3814 | V55: 2.37 | W55: 0 | X55: 3847 | Y55: 9119 | Z55: 6027 | AC55: 0 | AD55: 0 | AE55: 121.5 | AG55: 0 | AH55: 0 | AJ55: 18029 | AK55: 0 | AM55: 0 | AN55: 66212 | AO55: 256203 | AP55: 0 | AQ55: 0 | AV55: 0 | AW55: 0 | AX55: 0 | AY55: 0 | AZ55: 0 | BA55: 0 | BB55: 0 | BC55: 0 | BD55: 0 | BE55: 0 | BF55: 0 | BG55: 0 | BH55: 0 | BJ55: 1
A56: Annabelle | B56: 7 | C56: 2023 | D56: 313330 | E56: 0.27 | F56: 0 | G56: 0 | H56: 0 | I56: 360191 | J56: 63651 | K56: 3544 | L56: 0.73 | M56: 0 | N56: 4406 | O56: 3084 | P56: 31777 | Q56: 0.1151 | S56: 54180 | T56: 6235 | U56: 3889 | V56: 2.37 | W56: 0 | X56: 4177 | Y56: 9901 | Z56: 5999 | AC56: 0 | AD56: 0 | AE56: 244.9 | AG56: 0 | AH56: 0 | AI56: 0 | AJ56: 47187 | AK56: 0 | AM56: 0 | AN56: 83972 | AO56: 360517 | AP56: 0 | AQ56: 0 | AS56: 0 | AU56: 0 | AV56: 0 | AW56: 0 | AX56: 0 | AY56: 0 | AZ56: 0 | BA56: 0 | BB56: 0 | BC56: 0 | BD56: 0 | BE56: 0 | BF56: 0 | BG56: 0 | BH56: 0 | BJ56: 1
A57: Annabelle | B57: 8 | C57: 2023 | D57: 318865 | E57: 0.28 | F57: 0 | G57: 0 | H57: 0 | I57: 393401 | J57: 69520 | K57: 4263 | L57: 0.59 | M57: 0 | N57: 2976 | O57: 2083 | P57: 33894 | Q57: 0.1151 | S57: 53374 | T57: 6142 | U57: 4723 | V57: 2.35 | W57: 0 | X57: 4218 | Y57: 9914 | Z57: 6397 | AC57: 0 | AD57: 0 | AE57: 231.3 | AG57: 0 | AH57: 0 | AI57: 0 | AJ57: 40962 | AK57: 0 | AM57: 0 | AN57: 87688 | AO57: 359827 | AP57: 0 | AQ57: 0 | AS57: 0 | AU57: 0 | AV57: 0 | AW57: 0 | AX57: 0 | AY57: 0 | AZ57: 0 | BA57: 0 | BB57: 0 | BC57: 0 | BD57: 0 | BE57: 0 | BF57: 0 | BG57: 0 | BH57: 0 | BJ57: 1
A58: Annabelle | B58: 9 | C58: 2023 | D58: 281040 | E58: 0.29 | F58: 0 | G58: 0 | H58: 0 | I58: 327771 | J58: 57922 | K58: 3720 | L58: 0.63 | M58: 0 | N58: 3599 | O58: 2519 | P58: 31298 | Q58: 0.1151 | S58: 51106 | T58: 5881 | U58: 4041 | V58: 2.35 | W58: 0 | X58: 4078 | Y58: 9585 | Z58: 6343 | AC58: 0 | AD58: 0 | AE58: 182.4 | AG58: 0 | AH58: 0 | AJ58: 35588 | AK58: 0 | AM58: 0 | AN58: 80096 | AO58: 316628 | AP58: 0 | AQ58: 0 | AV58: 0 | AW58: 0 | AX58: 0 | AY58: 0 | AZ58: 0 | BA58: 0 | BB58: 0 | BC58: 0 | BD58: 0 | BE58: 0 | BF58: 0 | BG58: 0 | BH58: 0 | BJ58: 1
A59: Annabelle | B59: 10 | C59: 2023 | D59: 235993 | E59: 0.27 | F59: 0 | G59: 0 | H59: 0 | I59: 257626 | J59: 45526 | K59: 4648 | L59: 0.67 | M59: 0 | N59: 3599 | O59: 2519 | P59: 57582 | Q59: 0.1151 | S59: 77742 | T59: 8946 | U59: 4150 | V59: 2.35 | W59: 0 | X59: 3846 | Y59: 9039 | Z59: 6802 | AC59: 0 | AD59: 0 | AE59: 105.4 | AG59: 0 | AH59: 0 | AI59: 0 | AJ59: 31432 | AK59: 0 | AM59: 0 | AN59: 62538 | AO59: 267425 | AP59: 1040 | AQ59: 0.97 | AS59: 0 | AU59: 0 | AV59: 0 | AW59: 0 | AX59: 0 | AY59: 0 | AZ59: 0 | BA59: 0 | BB59: 0 | BC59: 0 | BD59: 0 | BE59: 0 | BF59: 0 | BG59: 0 | BH59: 0 | BJ59: 1
A60: Annabelle | B60: 11 | C60: 2023 | D60: 185810 | E60: 0.25 | F60: 0 | G60: 0 | H60: 0 | I60: 177666 | J60: 31396 | K60: 3732 | L60: 0.65 | M60: 0 | N60: 4291 | O60: 3004 | P60: 73256 | Q60: 0.1151 | S60: 80917 | T60: 9312 | U60: 3124 | V60: 2.35 | W60: 0 | X60: 2698 | Y60: 6341 | Z60: 4392 | AC60: 0 | AD60: 0 | AE60: 41.5 | AF60: 6.8 | AG60: 0 | AH60: 0 | AJ60: 22019 | AK60: 0 | AM60: 0 | AN60: 46824 | AO60: 207829 | AP60: 0 | AQ60: 0 | AV60: 0 | AW60: 0 | AX60: 0 | AY60: 0 | AZ60: 0 | BA60: 0 | BB60: 0 | BC60: 0 | BD60: 0 | BE60: 0 | BF60: 0 | BG60: 0 | BH60: 0 | BJ60: 1
A61: Annabelle | B61: 12 | C61: 2023 | D61: 115945 | E61: 0.24 | F61: 0 | G61: 0 | H61: 0 | I61: 140763 | J61: 24875 | K61: 2845 | L61: 0.64 | M61: 0 | N61: 2470 | O61: 1729 | P61: 109292 | Q61: 0.1151 | S61: 126000 | T61: 14500 | U61: 2103 | V61: 2.4 | W61: 0 | X61: 1067 | Y61: 2563 | Z61: 2088 | AC61: 0 | AD61: 0 | AE61: 4.2 | AF61: 28.2 | AG61: 0 | AH61: 0 | AJ61: 18395 | AK61: 0 | AM61: 0 | AN61: 27711 | AO61: 134340 | AP61: 0 | AQ61: 0 | AV61: 0 | AW61: 0 | AX61: 0 | AY61: 0 | AZ61: 0 | BA61: 0 | BB61: 0 | BC61: 0 | BD61: 0 | BE61: 0 | BF61: 0 | BG61: 0 | BH61: 0 | BJ61: 1
A62: Annabelle | B62: 1 | C62: 2024 | D62: 123409 | E62: 0.23 | F62: 0 | G62: 0 | H62: 0 | I62: 124702 | J62: 31425 | K62: 2282 | L62: 0.65 | M62: 0 | N62: 2237 | O62: 1566 | P62: 114332 | Q62: 0.1151 | S62: 131947 | T62: 15184 | U62: 1886 | V62: 2.4 | W62: 0 | X62: 1662 | Y62: 3989 | Z62: 1798 | AC62: 0 | AD62: 0 | AE62: 0.3 | AF62: 48.2 | AG62: 0 | AH62: 0 | AJ62: 18783 | AK62: 0 | AM62: 0 | AN62: 28754 | AO62: 142192 | AP62: 0 | AQ62: 0 | AV62: 0 | AW62: 0 | AX62: 0 | AY62: 0 | AZ62: 0 | BA62: 0 | BB62: 0 | BC62: 0 | BD62: 0 | BE62: 0 | BF62: 0 | BG62: 0 | BH62: 0 | BJ62: 1
A63: Annabelle | B63: 2 | C63: 2024 | D63: 111412 | E63: 0.22 | F63: 0 | G63: 0 | H63: 0 | I63: 125023 | J63: 31506 | K63: 2251 | L63: 0.65 | M63: 0 | N63: 2549 | O63: 1784 | P63: 126605 | Q63: 0.1151 | S63: 198349 | T63: 22826 | U63: 1983 | V63: 2.4 | W63: 0 | X63: 1936 | Y63: 4647 | Z63: 2425 | AC63: 0 | AD63: 0 | AE63: 0.2 | AF63: 60.9 | AG63: 0 | AH63: 0 | AJ63: 25932 | AK63: 0 | AM63: 0 | AN63: 24956 | AO63: 137344 | AP63: 0 | AQ63: 0 | AV63: 0 | AW63: 0 | AX63: 0 | AY63: 0 | AZ63: 0 | BA63: 0 | BB63: 0 | BC63: 0 | BD63: 0 | BE63: 0 | BF63: 0 | BG63: 0 | BH63: 0 | BJ63: 1
A64: Annabelle | B64: 3 | C64: 2024 | D64: 133630 | E64: 0.23 | F64: 0 | G64: 0 | H64: 0 | I64: 152841 | J64: 38516 | K64: 2560 | L64: 0.65 | M64: 0 | N64: 3481 | O64: 2437 | P64: 134089 | Q64: 0.1151 | S64: 183128 | T64: 21074 | U64: 2608 | V64: 2.4 | W64: 0 | X64: 2785 | Y64: 6684 | Z64: 3952 | AC64: 0 | AD64: 0 | AE64: 5.1 | AF64: 29.7 | AG64: 0 | AH64: 0 | AI64: 0 | AJ64: 38221 | AK64: 0 | AM64: 0 | AN64: 30869 | AO64: 171851 | AP64: 0 | AQ64: 0 | AS64: 0 | AU64: 0 | AV64: 0 | AW64: 0 | AX64: 0 | AY64: 0 | AZ64: 0 | BA64: 0 | BB64: 0 | BC64: 0 | BD64: 0 | BE64: 0 | BF64: 0 | BG64: 0 | BH64: 0 | BJ64: 1
A65: Annabelle | B65: 4 | C65: 2024 | D65: 159135 | E65: 0.23 | F65: 0 | G65: 0 | H65: 0 | I65: 178614 | J65: 45011 | K65: 3330 | L65: 0.66 | M65: 0 | N65: 4411 | O65: 3088 | P65: 130838 | Q65: 0.1151 | S65: 164934 | T65: 18980 | U65: 3416 | V65: 2.4 | W65: 0 | X65: 3572 | Y65: 8573 | Z65: 5505 | AC65: 0 | AD65: 0 | AE65: 38.7 | AF65: 3.1 | AG65: 0 | AH65: 0 | AI65: 0 | AJ65: 40969 | AK65: 0 | AM65: 0 | AN65: 36919 | AO65: 200104 | AP65: 0 | AQ65: 0 | AS65: 0 | AU65: 0 | AV65: 0 | AW65: 0 | AX65: 1198 | AY65: 791 | AZ65: 0 | BA65: 0 | BB65: 0 | BC65: 0 | BD65: 0 | BE65: 0 | BF65: 0 | BG65: 0 | BH65: 0 | BJ65: 1
A66: Annabelle | B66: 5 | C66: 2024 | D66: 193937 | E66: 0.24 | F66: 0 | G66: 0 | H66: 0 | I66: 193764 | J66: 48829 | K66: 3814 | L66: 0.64 | M66: 0 | N66: 4051 | O66: 2836 | P66: 74743 | Q66: 0.1151 | S66: 103194 | T66: 11876 | U66: 3760 | V66: 2.4 | W66: 0 | X66: 3458 | Y66: 8300 | Z66: 6114 | AC66: 0 | AD66: 0 | AE66: 58.4 | AF66: 0.7 | AG66: 0 | AH66: 0 | AI66: 0 | AJ66: 47707 | AK66: 0 | AM66: 0 | AN66: 45769 | AO66: 241644 | AP66: 0 | AQ66: 0 | AS66: 0 | AU66: 0 | AV66: 0 | AW66: 0 | AX66: 0 | AY66: 0 | AZ66: 0 | BA66: 0 | BB66: 0 | BC66: 0 | BD66: 0 | BE66: 0 | BF66: 0 | BG66: 0 | BH66: 0 | BJ66: 1
A67: Annabelle | B67: 6 | C67: 2024 | D67: 298174 | E67: 0.27 | F67: 0 | G67: 0 | H67: 0 | I67: 202116 | J67: 50933 | K67: 3415 | L67: 0.61 | M67: 0 | N67: 4079 | O67: 2855 | P67: 38934 | Q67: 0.1151 | S67: 53273 | T67: 6131 | U67: 3871 | V67: 2.4 | W67: 0 | X67: 4174 | Y67: 10019 | Z67: 6084 | AC67: 0 | AD67: 0 | AE67: 203.7 | AG67: 0 | AH67: 0 | AI67: 0 | AJ67: 46941 | AK67: 0 | AM67: 0 | AN67: 79612 | AO67: 345115 | AP67: 0 | AQ67: 0 | AS67: 0 | AU67: 0 | AV67: 0 | AW67: 0 | AX67: 0 | AY67: 0 | AZ67: 0 | BA67: 0 | BB67: 0 | BC67: 0 | BD67: 0 | BE67: 0 | BF67: 0 | BG67: 0 | BH67: 0 | BJ67: 1
A68: Annabelle | B68: 7 | C68: 2024 | D68: 361389 | E68: 0.27 | F68: 0 | G68: 0 | H68: 0 | I68: 218956 | J68: 55177 | K68: 3435 | L68: 0.62 | M68: 0 | N68: 3544 | O68: 2481 | P68: 34826 | Q68: 0.1151 | S68: 31777 | T68: 3657 | U68: 3831 | V68: 2.42 | W68: 0 | X68: 3807 | Y68: 9139 | Z68: 6333 | AC68: 0 | AD68: 0 | AE68: 253.2 | AG68: 0 | AH68: 0 | AJ68: 46475 | AK68: 0 | AM68: 0 | AN68: 97575 | AO68: 407864 | AP68: 0 | AQ68: 0 | AV68: 0 | AW68: 0 | AX68: 0 | AY68: 0 | AZ68: 0 | BA68: 0 | BB68: 0 | BC68: 0 | BD68: 0 | BE68: 0 | BF68: 0 | BG68: 0 | BH68: 0 | BJ68: 1
A69: Annabelle | B69: 8 | C69: 2024 | D69: 365437 | E69: 0 | F69: 0 | G69: 0 | H69: 0 | I69: 236941 | J69: 59709 | K69: 0 | L69: 0 | M69: 0 | N69: 4263 | O69: 2984 | P69: 0 | Q69: 0.1151 | S69: 33894 | T69: 3900 | U69: 0 | V69: 0 | W69: 0 | X69: 4622 | Y69: 11094 | Z69: 0 | AC69: 0 | AD69: 0 | AE69: 248.5 | AG69: 0 | AH69: 0 | AI69: 0 | AJ69: 0 | AK69: 0 | AM69: 0 | AN69: 0 | AO69: 365437 | AP69: 0 | AQ69: 0 | AS69: 0 | AU69: 0 | AV69: 0 | AW69: 0 | AX69: 0 | AY69: 0 | AZ69: 0 | BA69: 0 | BB69: 0 | BC69: 0 | BD69: 0 | BE69: 0 | BF69: 0 | BG69: 0 | BH69: 0 | BJ69: 1
A70: Annabelle | B70: 9 | C70: 2024 | D70: 0 | E70: 0 | F70: 0 | G70: 0 | H70: 0 | I70: 245452 | J70: 61854 | K70: 0 | L70: 0 | M70: 0 | N70: 3720 | O70: 2604 | P70: 0 | Q70: 0.1151 | S70: 31298 | T70: 3602 | U70: 0 | V70: 0 | W70: 0 | X70: 4300 | Y70: 10321 | Z70: 0 | AC70: 0 | AD70: 0 | AE70: 177.6 | AG70: 0 | AH70: 0 | AI70: 0 | AJ70: 0 | AK70: 0 | AM70: 0 | AN70: 0 | AO70: 0 | AP70: 0 | AQ70: 0 | AS70: 0 | AU70: 0 | AV70: 0 | AW70: 0 | AX70: 0 | AY70: 0 | AZ70: 0 | BA70: 0 | BB70: 0 | BC70: 0 | BD70: 0 | BE70: 0 | BF70: 0 | BG70: 0 | BH70: 0 | BJ70: 1
A71: Annabelle | B71: 10 | C71: 2024 | D71: 0 | E71: 0 | F71: 0 | G71: 0 | H71: 0 | I71: 204561 | J71: 51549 | K71: 0 | L71: 0 | M71: 0 | N71: 4649 | O71: 3254 | P71: 0 | Q71: 0.1151 | S71: 57582 | T71: 6626 | U71: 0 | V71: 0 | W71: 0 | X71: 3946 | Y71: 9472 | Z71: 0 | AC71: 0 | AD71: 0 | AE71: 92 | AG71: 0 | AH71: 0 | AI71: 0 | AJ71: 0 | AK71: 0 | AM71: 0 | AN71: 0 | AO71: 0 | AP71: 0 | AQ71: 0 | AS71: 0 | AU71: 0 | AV71: 0 | AW71: 0 | AX71: 1034 | AY71: 693 | AZ71: 0 | BA71: 0 | BB71: 0 | BC71: 0 | BD71: 0 | BE71: 0 | BF71: 0 | BG71: 0 | BH71: 0 | BJ71: 1
A72: Annabelle | B72: 11 | C72: 2024 | D72: 0 | E72: 0 | F72: 0 | G72: 0 | H72: 0 | I72: 163791 | J72: 41725 | K72: 0 | L72: 0 | M72: 0 | N72: 3731 | O72: 2612 | P72: 0 | Q72: 0.1151 | S72: 73256 | T72: 8430 | U72: 0 | V72: 0 | W72: 0 | X72: 2885 | Y72: 6926 | Z72: 0 | AC72: 0 | AD72: 0 | AE72: 24.3 | AF72: 19.4 | AG72: 0 | AH72: 0 | AI72: 0 | AJ72: 0 | AK72: 0 | AM72: 0 | AN72: 0 | AO72: 0 | AP72: 6983 | AQ72: 0.87 | AS72: 0 | AU72: 0 | AV72: 0 | AW72: 0 | AX72: 0 | AY72: 0 | AZ72: 0 | BA72: 0 | BB72: 0 | BC72: 0 | BD72: 0 | BE72: 0 | BF72: 0 | BG72: 0 | BH72: 0 | BJ72: 1
A73: Annabelle | B73: 12 | C73: 2024 | D73: 0 | E73: 0 | F73: 0 | G73: 0 | H73: 0 | I73: 140763 | J73: 35472 | K73: 0 | L73: 0 | M73: 0 | N73: 2600 | O73: 1820 | P73: 0 | Q73: 0.1151 | S73: 126000 | T73: 14500 | U73: 0 | V73: 0 | W73: 0 | X73: 2887 | Y73: 6930 | Z73: 0 | AC73: 0 | AD73: 0 | AE73: 1.1 | AF73: 56.9 | AG73: 0 | AH73: 0 | AJ73: 0 | AK73: 0 | AM73: 0 | AN73: 0 | AO73: 0 | AP73: 8000 | AQ73: 0.88 | AV73: 0 | AW73: 0 | AX73: 0 | AY73: 0 | AZ73: 0 | BA73: 0 | BB73: 0 | BC73: 0 | BD73: 0 | BE73: 0 | BF73: 0 | BG73: 0 | BH73: 0 | BJ73: 1
A74: Annabelle | B74: 1 | C74: 2025 | D74: 142337 | E74: 0.19 | I74: 124702 | J74: 31425 | K74: 2203 | L74: 0.74 | N74: 2237 | O74: 1566 | P74: 154904 | Q74: 0.1 | S74: 131947 | T74: 0 | U74: 2117 | V74: 2.34 | X74: 1.94 | Y74: 3989 | Z74: 2202 | AC74: 4485 | AD74: 0 | AE74: 0.2 | AF74: 75.5 | AI74: 0 | AJ74: 20 | AK74: 0 | AM74: 0 | AN74: 26902 | AO74: 142357 | AP74: 4300 | AQ74: 0.8 | AS74: 0 | AU74: 0 | AX74: 0 | AY74: 0 | AZ74: 0 | BA74: 0 | BC74: 0 | BE74: 0 | BG74: 0 | BH74: 0 | BJ74: 1
A75: Annabelle | B75: 2 | C75: 2025 | D75: 82326 | E75: 0.16 | F75: 0 | G75: 0 | H75: 0 | I75: 125023 | J75: 31506 | K75: 2170 | L75: 0.78 | M75: 0 | N75: 2549 | O75: 1784 | P75: 169898 | Q75: 0.1 | S75: 198349 | T75: 0 | U75: 2288 | V75: 2.9 | W75: 0 | X75: 1.99 | Y75: 4647 | Z75: 2689 | AC75: 5136 | AD75: 0 | AF75: 124.3 | AG75: 0 | AH75: 0 | AI75: 0 | AJ75: 23603 | AK75: 0 | AL75: 0 | AM75: 0 | AN75: 12925 | AO75: 105929 | AP75: 6388 | AQ75: 0.83 | AS75: 0 | AU75: 0 | AV75: 0 | AW75: 0 | AX75: 0 | AY75: 0 | AZ75: 0 | BA75: 0 | BB75: 0 | BC75: 0 | BD75: 0 | BE75: 0 | BF75: 0 | BG75: 0 | BH75: 0 | BJ75: 1
A76: Annabelle | B76: 3 | C76: 2025 | D76: 149559 | E76: 0.23 | F76: 0 | G76: 0 | H76: 0 | I76: 152841 | J76: 38516 | K76: 2812 | L76: 0.72 | M76: 0 | N76: 3481 | O76: 2437 | P76: 144774 | Q76: 0.0952 | S76: 183128 | T76: 2230 | U76: 3189 | V76: 2.34 | W76: 0 | X76: 2.1 | Y76: 6684 | Z76: 3888 | AC76: 7595 | AD76: 0 | AE76: 12.6 | AF76: 42.8 | AG76: 0 | AH76: 0 | AI76: 0 | AJ76: 30153 | AK76: 0 | AL76: 0 | AM76: 0 | AN76: 34399 | AO76: 179712 | AP76: 1526 | AQ76: 0.83 | AS76: 0 | AU76: 0 | AV76: 0 | AW76: 0 | AX76: 0 | AY76: 0 | AZ76: 0 | BA76: 0 | BB76: 0 | BC76: 0 | BD76: 0 | BE76: 0 | BF76: 0 | BG76: 0 | BH76: 0 | BJ76: 1
A77: Annabelle | B77: 4 | C77: 2025 | D77: 166918 | E77: 0.17 | F77: 0 | G77: 0 | H77: 0 | I77: 178614 | J77: 45011 | K77: 4269 | L77: 0.71 | M77: 0 | N77: 4411 | O77: 3088 | P77: 122875 | Q77: 0.0893 | S77: 164934 | T77: 2299 | U77: 3586 | V77: 2.34 | W77: 0 | X77: 2.06 | Y77: 8573 | Z77: 5790 | AC77: 8911 | AD77: 0 | AE77: 10 | AF77: 16 | AG77: 0 | AH77: 0 | AI77: 0 | AJ77: 37054 | AK77: 0 | AM77: 0 | AN77: 29044 | AO77: 203972 | AP77: 4172 | AQ77: 0.83 | AS77: 0 | AU77: 0 | AV77: 0 | AW77: 0 | AX77: 1198 | AY77: 791 | AZ77: 0 | BA77: 0 | BB77: 0 | BC77: 0 | BD77: 0 | BE77: 0 | BF77: 0 | BG77: 0 | BH77: 0 | BJ77: 1
A78: Annabelle | B78: 5 | C78: 2025 | D78: 188017 | E78: 0.17 | F78: 0 | G78: 0 | H78: 0 | I78: 193764 | J78: 48829 | K78: 3859 | L78: 0.64 | M78: 0 | N78: 4051 | O78: 2836 | P78: 85378 | Q78: 0.0893 | S78: 103194 | T78: 1517 | U78: 3629 | V78: 2.4 | W78: 0 | X78: 2.26 | Y78: 8300 | Z78: 5667 | AC78: 11335 | AD78: 0 | AE78: 52.9 | AF78: 1.1 | AG78: 0 | AH78: 0 | AI78: 0 | AJ78: 40941 | AK78: 0 | AL78: 0 | AM78: 0 | AN78: 32715 | AO78: 228958 | AP78: 2129 | AQ78: 0.73 | AS78: 0 | AU78: 0 | AV78: 0 | AW78: 0 | AX78: 0 | AY78: 0 | AZ78: 0 | BA78: 0 | BB78: 0 | BC78: 0 | BD78: 0 | BE78: 0 | BF78: 0 | BG78: 0 | BH78: 0 | BJ78: 1
A79: Annabelle | B79: 6 | C79: 2025 | D79: 269628 | E79: 0.21 | F79: 0 | G79: 0 | H79: 0 | I79: 202116 | J79: 50933 | K79: 3739 | L79: 0.68 | M79: 0 | N79: 4079 | O79: 2855 | P79: 61387 | Q79: 0.0913 | S79: 53273 | T79: 961 | U79: 3815 | V79: 2.34 | W79: 0 | X79: 2.5 | Y79: 10019 | Z79: 5651 | AC79: 11381 | AD79: 0 | AE79: 148.9 | AG79: 0 | AH79: 0 | AI79: 0 | AJ79: 47055 | AK79: 0 | AL79: 0 | AM79: 0 | AN79: 55274 | AO79: 316683 | AP79: 282 | AQ79: 0.73 | AS79: 0 | AU79: 0 | AV79: 0 | AW79: 0 | AX79: 0 | AY79: 0 | AZ79: 0 | BA79: 0 | BB79: 0 | BC79: 0 | BD79: 0 | BE79: 0 | BF79: 0 | BG79: 0 | BH79: 0 | BJ79: 1
A80: Annabelle | B80: 7 | C80: 2025 | D80: 321360 | E80: 0.21 | F80: 0 | G80: 0 | H80: 0 | I80: 218956 | J80: 55177 | K80: 3571 | L80: 0.7 | M80: 0 | N80: 3544 | O80: 2481 | P80: 53575 | Q80: 0.0937 | S80: 31777 | T80: 1530 | U80: 3620 | V80: 2.34 | W80: 0 | X80: 2.24 | Y80: 9139 | Z80: 5157 | AC80: 11186 | AD80: 0 | AE80: 226.1 | AG80: 0 | AH80: 0 | AI80: 0 | AJ80: 46328 | AK80: 0 | AL80: 0 | AM80: 0 | AN80: 66200 | AO80: 367688 | AP80: 0 | AQ80: 0 | AS80: 0 | AU80: 0 | AV80: 0 | AW80: 0 | AX80: 0 | AY80: 0 | AZ80: 0 | BA80: 0 | BB80: 0 | BC80: 0 | BD80: 0 | BE80: 0 | BF80: 0 | BG80: 0 | BH80: 0 | BJ80: 1
A81: Annabelle | B81: 8 | C81: 2025 | D81: 352059 | E81: 0.21 | I81: 236941 | J81: 59709 | K81: 4317 | L81: 0.7 | N81: 4263 | O81: 2984 | P81: 36641 | Q81: 0.0933 | S81: 33894 | T81: 1377 | U81: 4190 | V81: 2.9 | X81: 2.24 | Y81: 11094 | Z81: 6340 | AA81: 0 | AB81: 0 | AC81: 14421 | AD81: 0 | AE81: 233.7 | AI81: 0 | AJ81: 42316 | AK81: 0 | AM81: 0 | AN81: 74637 | AO81: 394375 | AP81: 0 | AQ81: 0 | AS81: 0 | AU81: 0 | AX81: 0 | AY81: 0 | AZ81: 0 | BA81: 0 | BC81: 0 | BE81: 0 | BG81: 0 | BH81: 0 | BJ81: 1
A82: Annabelle | B82: 9 | C82: 2025 | D82: 295720 | E82: 0.22 | F82: 0 | G82: 0 | H82: 0 | I82: 245452 | J82: 61854 | K82: 3721 | L82: 0.7 | M82: 0 | N82: 3720 | O82: 2604 | P82: 50 | Q82: 0.0933 | S82: 31298 | T82: 511 | U82: 3593 | V82: 2.29 | W82: 0 | X82: 2.43 | Y82: 10321 | Z82: 6010 | AC82: 11726 | AD82: 0 | AE82: 168.4 | AG82: 0 | AH82: 0 | AI82: 0 | AJ82: 34761 | AK82: 0 | AL82: 0 | AM82: 0 | AN82: 64763 | AO82: 330481 | AP82: 0 | AQ82: 0 | AS82: 0 | AU82: 0 | AV82: 0 | AW82: 0 | AX82: 0 | AY82: 0 | AZ82: 0 | BA82: 0 | BB82: 0 | BC82: 0 | BD82: 0 | BE82: 0 | BF82: 0 | BG82: 0 | BH82: 0 | BJ82: 1
A83: Annabelle | B83: 10 | C83: 2025 | D83: 228534 | E83: 0.2 | F83: 0 | G83: 0 | H83: 0 | I83: 204561 | J83: 51549 | K83: 4251 | L83: 0.72 | M83: 0 | N83: 4649 | O83: 3254 | P83: 33995 | Q83: 0.0933 | S83: 57582 | T83: 2522 | U83: 3871 | V83: 2.87 | W83: 0 | X83: 2.17 | Y83: 9472 | Z83: 6654 | AA83: 0 | AB83: 0 | AC83: 13364 | AD83: 0 | AE83: 71.5 | AG83: 0 | AH83: 0 | AI83: 0 | AJ83: 29930 | AK83: 0 | AL83: 0 | AM83: 0 | AN83: 45021 | AO83: 258464 | AP83: 4415 | AQ83: 0.73 | AS83: 0 | AU83: 0 | AV83: 0 | AW83: 0 | AX83: 1034 | AY83: 693 | AZ83: 0 | BA83: 0 | BB83: 0 | BC83: 0 | BD83: 0 | BE83: 0 | BF83: 0 | BG83: 0 | BH83: 0 | BJ83: 1
A84: Annabelle | B84: 11 | C84: 2025 | D84: 167370 | E84: 0.2 | F84: 0 | G84: 0 | H84: 0 | I84: 163791 | J84: 41725 | K84: 3227 | L84: 0.73 | M84: 0 | N84: 3731 | O84: 2612 | P84: 0 | Q84: 0 | S84: 73256 | T84: 1024 | U84: 2961 | V84: 2.87 | W84: 0 | X84: 2.11 | Y84: 6926 | Z84: 4930 | AA84: 0 | AB84: 0 | AC84: 8860 | AD84: 0 | AE84: 45.9 | AF84: 2.9 | AG84: 0 | AH84: 0 | AI84: 0 | AJ84: 18984 | AK84: 0 | AL84: 0 | AM84: 0 | AN84: 33307 | AO84: 186354 | AP84: 9380 | AQ84: 0.74 | AS84: 0 | AU84: 0 | AV84: 0 | AW84: 0 | AX84: 0 | AY84: 0 | AZ84: 0 | BA84: 0 | BB84: 0 | BC84: 0 | BD84: 0 | BE84: 0 | BF84: 0 | BG84: 0 | BH84: 0 | BJ84: 1
A85: Annabelle | B85: 12 | C85: 2025 | D85: 139375 | E85: 0.2 | F85: 0 | G85: 0 | H85: 0 | I85: 140763 | J85: 35472 | K85: 2908 | L85: 0.75 | M85: 0 | N85: 2600 | O85: 1820 | P85: 0 | Q85: 0 | S85: 126000 | T85: 0 | U85: 1742 | V85: 0 | W85: 0 | X85: 2.2 | Y85: 6930 | Z85: 2138 | AA85: 0 | AB85: 0 | AC85: 4023 | AD85: 0 | AE85: 2.9 | AF85: 34.2 | AG85: 0 | AH85: 0 | AI85: 0 | AJ85: 14961 | AK85: 0 | AL85: 0 | AM85: 0 | AN85: 27875 | AO85: 154336 | AP85: 11259 | AQ85: 0.74 | AS85: 0 | AU85: 0 | AV85: 0 | AW85: 0 | AX85: 0 | AY85: 0 | AZ85: 0 | BA85: 0 | BB85: 0 | BC85: 0 | BD85: 0 | BE85: 0 | BF85: 0 | BG85: 0 | BH85: 0 | BJ85: 1
A86: Annabelle | B86: 1 | C86: 2026 | D86: 82116 | E86: 0.18 | I86: 124702 | J86: 31425 | K86: 1344 | L86: 0.76 | N86: 2237 | O86: 1566 | P86: 0 | Q86: 0 | S86: 131947 | T86: 0 | U86: 76 | V86: 2.9 | X86: 807 | Y86: 2342 | Z86: 1194 | AA86: 992 | AB86: 0 | AC86: 1806 | AD86: 0 | AE86: 0.2 | AF86: 68.4 | AI86: 0 | AJ86: 15177 | AK86: 0 | AM86: 0 | AN86: 14617 | AO86: 97293 | AP86: 8259 | AQ86: 0.74 | AS86: 0 | AU86: 0 | AX86: 0 | AY86: 0 | AZ86: 0 | BA86: 0 | BC86: 0 | BE86: 0 | BG86: 0 | BH86: 0 | BJ86: 1
A87: Annabelle | B87: 2 | C87: 2026 | D87: 53711 | E87: 0.11 | I87: 125023 | J87: 31506 | K87: 500 | L87: 0.76 | N87: 2549 | O87: 1784 | P87: 0 | Q87: 0 | S87: 198349 | T87: 0 | U87: 0 | V87: 0 | X87: 662 | Y87: 1602 | Z87: 198 | AA87: 639 | AC87: 377 | AD87: 0 | AE87: 0.4 | AF87: 36.6 | AI87: 0 | AJ87: 25405 | AK87: 0 | AM87: 0 | AN87: 6016 | AO87: 79116 | AP87: 2143 | AQ87: 0.74 | AS87: 0 | AU87: 0 | AX87: 0 | AY87: 0 | BA87: 0 | BC87: 0 | BE87: 0 | BG87: 0 | BH87: 0 | BJ87: 1
A88: Annabelle | B88: 3 | C88: 2026 | D88: 146529 | E88: 0.16 | I88: 152841 | J88: 38516 | K88: 2825 | L88: 0.88 | N88: 3481 | O88: 2437 | P88: 23461 | Q88: 0.0938 | S88: 183128 | T88: 2230 | U88: 1394 | V88: 2.88 | X88: 5072 | Y88: 12273 | Z88: 3186 | AA88: 3574 | AC88: 5494 | AD88: 0 | AE88: 0.7 | AF88: 50.4 | AI88: 0 | AJ88: 29080 | AK88: 0 | AM88: 0 | AN88: 23445 | AO88: 175609 | AP88: 13232 | AQ88: 0.83 | AS88: 0 | AU88: 0 | AX88: 0 | AY88: 0 | BA88: 0 | BC88: 0 | BE88: 0 | BG88: 0 | BH88: 0 | BJ88: 1
A89: Annabelle | B89: 4 | C89: 2026 | D89: 157388 | E89: 0.19 | F89: 0 | G89: 0 | H89: 0 | I89: 178614 | J89: 45011 | K89: 3132 | L89: 1.03 | M89: 0 | N89: 4411 | O89: 3088 | P89: 26762 | Q89: 0.1131 | S89: 164934 | T89: 2299 | U89: 2996 | V89: 2.88 | W89: 0 | X89: 3509 | Y89: 8491 | Z89: 5315 | AA89: 5838 | AB89: 0 | AC89: 9107 | AD89: 0 | AE89: 9.5 | AF89: 13.7 | AG89: 0 | AH89: 0 | AI89: 0 | AJ89: 27544 | AK89: 0 | AL89: 0 | AM89: 0 | AN89: 29117 | AO89: 184932 | AP89: 10582 | AQ89: 1.08 | AS89: 0 | AU89: 0 | AV89: 0 | AW89: 0 | AX89: 1198 | AY89: 791 | AZ89: 0 | BA89: 0 | BB89: 0 | BC89: 0 | BD89: 0 | BE89: 0 | BF89: 0 | BG89: 0 | BH89: 0 | BJ89: 1
A90: Annabelle | B90: 5 | C90: 2026 | D90: 285946 | E90: 0.23 | F90: 0 | G90: 0 | H90: 0 | I90: 193764 | J90: 48829 | K90: 0 | L90: 0 | M90: 0 | N90: 4051 | O90: 2836 | P90: 0 | Q90: 0 | S90: 103194 | T90: 1517 | U90: 3377 | V90: 2.42 | W90: 0 | X90: 3645 | Y90: 8821 | Z90: 5907 | AA90: 5818 | AB90: 0 | AC90: 11083 | AD90: 0 | AE90: 29.5 | AF90: 4.1 | AG90: 0 | AH90: 0 | AI90: 0 | AJ90: 34871 | AK90: 0 | AL90: 0 | AM90: 0 | AN90: 32461 | AO90: 183504 | AP90: 11342 | AQ90: 0.88 | AS90: 0 | AU90: 0 | AV90: 0 | AW90: 0 | AX90: 0 | AY90: 0 | AZ90: 3375 | BA90: 0.62 | BB90: 0 | BC90: 0 | BD90: 0 | BE90: 0 | BF90: 0 | BG90: 0 | BH90: 0 | BJ90: 1
A91: Annabelle | B91: 5 | C91: 2026 | D91: 285946 | E91: 0.23 | F91: 0 | G91: 0 | H91: 0 | I91: 303801 | J91: 77469 | K91: 7462 | L91: 0.9493 | M91: 0 | N91: 6682 | O91: 3063 | P91: 0 | Q91: 0 | S91: 77414 | T91: 7834 | U91: 2624 | V91: 1.3168 | W91: 0 | X91: 2997 | Y91: 4136 | Z91: 1960 | AA91: 2751 | AB91: 0 | AC91: 1801 | AD91: 0 | AE91: 29.5 | AF91: 4.1 | AG91: 0 | AH91: 0 | AI91: 0 | AJ91: 0 | AK91: 0 | AL91: 0 | AM91: 0 | AN91: 65224 | AO91: 285946 | AP91: 0 | AQ91: 1.1031 | AS91: 0 | AT91: 29073 | AU91: 1.1031 | AV91: 0 | AW91: 0 | AX91: 17582 | AY91: 11769 | AZ91: 0 | BA91: 0 | BB91: 0 | BC91: 0 | BD91: 0 | BE91: 0 | BF91: 0 | BG91: 0 | BH91: 0 | BJ91: 1
A92: Annabelle | B92: 6 | C92: 2026 | D92: 241246 | E92: 0.22 | I92: 202116 | J92: 50933 | L92: 0 | N92: 4079 | O92: 2855 | P92: 0 | Q92: 0 | S92: 53273 | T92: 961 | U92: 3657 | V92: 2.42 | X92: 4092 | Y92: 9903 | Z92: 6115 | AA92: 6206 | AB92: 0 | AC92: 11926 | AD92: 0 | AE92: 120.9 | AF92: 0 | AI92: 0 | AK92: 0 | AM92: 0 | AN92: 52245 | AO92: 241246 | AP92: 4167 | AQ92: 0.88 | AS92: 0 | AU92: 0 | AY92: 0 | AZ92: 3149 | BA92: 0.62 | BC92: 0 | BE92: 0 | BG92: 0 | BH92: 0 | BJ92: 1
A93: Annabelle | B93: 7 | C93: 2026 | D93: 0 | E93: 0 | F93: 0 | G93: 0 | H93: 0 | I93: 218956 | J93: 55177 | K93: 0 | L93: 0 | M93: 0 | N93: 3544 | O93: 2481 | P93: 0 | Q93: 0 | S93: 31777 | T93: 1530 | U93: 0 | V93: 0 | W93: 0 | X93: 4399 | Y93: 10645 | Z93: 0 | AA93: 6405 | AB93: 0 | AC93: 0 | AD93: 0 | AG93: 0 | AH93: 0 | AI93: 0 | AJ93: 0 | AK93: 0 | AL93: 0 | AM93: 0 | AN93: 0 | AO93: 0 | AQ93: 0 | AS93: 0 | AU93: 0 | AV93: 0 | AW93: 0 | AX93: 0 | AY93: 0 | AZ93: 0 | BA93: 0 | BB93: 0 | BC93: 0 | BD93: 0 | BE93: 0 | BF93: 0 | BG93: 0 | BH93: 0 | BJ93: 1
A94: Annabelle | B94: 8 | C94: 2026 | D94: 0 | E94: 0 | F94: 0 | G94: 0 | H94: 0 | I94: 236941 | J94: 59709 | K94: 0 | L94: 0 | M94: 0 | N94: 4263 | O94: 2984 | P94: 0 | Q94: 0 | S94: 33894 | T94: 1377 | U94: 0 | V94: 0 | W94: 0 | X94: 5196 | Y94: 12573 | Z94: 0 | AA94: 6488 | AB94: 0 | AC94: 0 | AD94: 0 | AG94: 0 | AH94: 0 | AI94: 0 | AJ94: 0 | AK94: 0 | AL94: 0 | AM94: 0 | AN94: 0 | AO94: 0 | AQ94: 0 | AS94: 0 | AU94: 0 | AV94: 0 | AW94: 0 | AX94: 0 | AY94: 0 | AZ94: 0 | BA94: 0 | BB94: 0 | BC94: 0 | BD94: 0 | BE94: 0 | BF94: 0 | BG94: 0 | BH94: 0 | BJ94: 1
A95: Annabelle | B95: 9 | C95: 2026 | D95: 0 | E95: 0 | F95: 0 | G95: 0 | H95: 0 | I95: 245452 | J95: 61854 | K95: 0 | L95: 0 | M95: 0 | N95: 3720 | O95: 2604 | P95: 0 | Q95: 0 | S95: 31298 | T95: 511 | U95: 0 | V95: 0 | W95: 0 | X95: 3574 | Y95: 8649 | Z95: 0 | AA95: 6197 | AB95: 0 | AC95: 0 | AD95: 0 | AG95: 0 | AH95: 0 | AI95: 0 | AJ95: 0 | AK95: 0 | AL95: 0 | AM95: 0 | AN95: 0 | AO95: 0 | AQ95: 0 | AS95: 0 | AU95: 0 | AV95: 0 | AW95: 0 | AX95: 0 | AY95: 0 | AZ95: 0 | BA95: 0 | BB95: 0 | BC95: 0 | BD95: 0 | BE95: 0 | BF95: 0 | BG95: 0 | BH95: 0 | BJ95: 1
A96: Annabelle | B96: 10 | C96: 2026 | D96: 0 | E96: 0 | F96: 0 | G96: 0 | H96: 0 | I96: 204561 | J96: 51549 | K96: 0 | L96: 0 | M96: 0 | N96: 4649 | O96: 3254 | P96: 0 | Q96: 0 | S96: 57582 | T96: 2522 | U96: 0 | V96: 0 | W96: 0 | X96: 4648 | Y96: 11248 | Z96: 0 | AA96: 6654 | AB96: 0 | AC96: 0 | AD96: 0 | AG96: 0 | AH96: 0 | AI96: 0 | AJ96: 0 | AK96: 0 | AL96: 0 | AM96: 0 | AN96: 0 | AO96: 0 | AQ96: 0 | AS96: 0 | AU96: 0 | AV96: 0 | AW96: 0 | AX96: 1034 | AY96: 693 | AZ96: 0 | BA96: 0 | BB96: 0 | BC96: 0 | BD96: 0 | BE96: 0 | BF96: 0 | BG96: 0 | BH96: 0 | BJ96: 1
A97: Annabelle | B97: 11 | C97: 2026 | D97: 0 | E97: 0 | F97: 0 | G97: 0 | H97: 0 | I97: 163791 | J97: 41725 | K97: 0 | L97: 0 | M97: 0 | N97: 3731 | O97: 2612 | P97: 0 | Q97: 0 | S97: 73256 | T97: 1024 | U97: 0 | V97: 0 | W97: 0 | X97: 3565 | Y97: 8627 | Z97: 0 | AA97: 5047 | AB97: 0 | AC97: 0 | AD97: 0 | AG97: 0 | AH97: 0 | AI97: 0 | AJ97: 0 | AK97: 0 | AL97: 0 | AM97: 0 | AN97: 0 | AO97: 0 | AQ97: 0 | AS97: 0 | AU97: 0 | AV97: 0 | AW97: 0 | AX97: 0 | AY97: 0 | AZ97: 0 | BA97: 0 | BB97: 0 | BC97: 0 | BD97: 0 | BE97: 0 | BF97: 0 | BG97: 0 | BH97: 0 | BJ97: 1
A98: Annabelle | B98: 12 | C98: 2026 | D98: 0 | E98: 0 | F98: 0 | G98: 0 | H98: 0 | I98: 140763 | J98: 35472 | K98: 0 | L98: 0 | M98: 0 | N98: 2600 | O98: 1820 | P98: 0 | Q98: 0 | S98: 126000 | T98: 0 | U98: 0 | V98: 0 | W98: 0 | X98: 2139 | Y98: 5177 | Z98: 0 | AA98: 1800 | AB98: 0 | AC98: 0 | AD98: 0 | AG98: 0 | AH98: 0 | AI98: 0 | AJ98: 0 | AK98: 0 | AL98: 0 | AM98: 0 | AN98: 0 | AO98: 0 | AQ98: 0 | AS98: 0 | AU98: 0 | AV98: 0 | AW98: 0 | AX98: 0 | AY98: 0 | AZ98: 0 | BA98: 0 | BB98: 0 | BC98: 0 | BD98: 0 | BE98: 0 | BF98: 0 | BG98: 0 | BH98: 0 | BJ98: 1
