Workbook

Sheet Total
A1: Site Name | B1: Day | C1: Month | D1: Year | E1: Total Electricity Kwh | F1: Electricity Tariff ($/Kwh) | G1: Total Fuel Oil (Liters) | H1: Fuel Oil $/Liter | I1: LPG (Kg) | J1: LPG $/Kg | K1: Water Utility Supply (m3) m3 | L1: Water Utility Supply (m3) $/m3 | M1: Irrigation Water (m3) m3 | N1: Irrigation water $/m3 | O1: Room Nights
A2: Beirut | B2: 1 | C2: 10 | D2: 2019 | E2: =ELEC!N3 -> 30214 | F2: =SUM('EDl log'!T4) -> 0.10781691 | G2: =-tanks!AW6 -> 839.1 | H2: =SUM(tanks!AV6) -> 0.54 | I2: =('B5'!AU5)*0.51 -> 137.7 | J2: ='B5'!AX5/0.51 -> 1.372549 | K2: =WATER!I6 -> 132 | L2: =SUM(WATER!J6) -> 3.4928446 | M2: =WATER!Q6 -> 0 | N2: 0.6 | O2: =ELEC!B3 -> 158.999
A3: Beirut | B3: =B2+1 -> 2 | C3: 10 | D3: 2019 | E3: =ELEC!N4 -> 32504 | F3: =SUM('EDl log'!T5) -> 0.09055399 | G3: =-tanks!AW7 -> 802.6 | H3: =SUM(tanks!AV7) -> 0.54 | I3: =('B5'!AU6)*0.51 -> 122.4 | J3: ='B5'!AX6/0.51 -> 1.372549 | K3: =WATER!I7 -> 132 | L3: =SUM(WATER!J7) -> 3.4928446 | M3: =WATER!Q7 -> 0 | N3: 0.6 | O3: =ELEC!B4 -> 161.989
A4: Beirut | B4: =B3+1 -> 3 | C4: 10 | D4: 2019 | E4: =ELEC!N5 -> 29402 | F4: =SUM('EDl log'!T6) -> 0.1021838 | G4: =-tanks!AW8 -> 812.6 | H4: =SUM(tanks!AV8) -> 0.54 | I4: =('B5'!AU7)*0.51 -> 107.1 | J4: ='B5'!AX7/0.51 -> 1.372549 | K4: =WATER!I8 -> 185 | L4: =SUM(WATER!J8) -> 2.9677594 | M4: =WATER!Q8 -> 0 | N4: 0.6 | O4: =ELEC!B5 -> 188.991
A5: Beirut | B5: =B4+1 -> 4 | C5: 10 | D5: 2019 | E5: =ELEC!N6 -> 32164 | F5: =SUM('EDl log'!T7) -> 0.046038231 | G5: =-tanks!AW9 -> 932.5 | H5: =SUM(tanks!AV9) -> 0.54666 | I5: =('B5'!AU8)*0.51 -> 290.7 | J5: ='B5'!AX8/0.51 -> 1.372549 | K5: =WATER!I9 -> 306 | L5: =SUM(WATER!J9) -> 1.5121421 | M5: =WATER!Q9 -> 0 | N5: 0.6 | O5: =ELEC!B6 -> 191.82
A6: Beirut | B6: =B5+1 -> 5 | C6: 10 | D6: 2019 | E6: =ELEC!N7 -> 31146 | F6: =SUM('EDl log'!T8) -> 0.077974873 | G6: =-tanks!AW10 -> 1032.5 | H6: =SUM(tanks!AV10) -> 0.54666 | I6: =('B5'!AU9)*0.51 -> 229.5 | J6: ='B5'!AX9/0.51 -> 1.372549 | K6: =WATER!I10 -> 212 | L6: =SUM(WATER!J10) -> 2.8012051 | M6: =WATER!Q10 -> 0 | N6: 0.6 | O6: =ELEC!B7 -> 177.008
A7: Beirut | B7: =B6+1 -> 6 | C7: 10 | D7: 2019 | E7: =ELEC!N8 -> 26276.8 | F7: =SUM('EDl log'!T9) -> 0.075158299 | G7: =-tanks!AW11 -> 1043.2 | H7: =SUM(tanks!AV11) -> 0.54666 | I7: =('B5'!AU10)*0.51 -> 137.7 | J7: ='B5'!AX10/0.51 -> 1.372549 | K7: =WATER!I11 -> 325 | L7: =SUM(WATER!J11) -> 1.42374 | M7: =WATER!Q11 -> 0 | N7: 0.6 | O7: =ELEC!B8 -> 131.997
A8: Beirut | B8: =B7+1 -> 7 | C8: 10 | D8: 2019 | E8: =ELEC!N9 -> 29097.4 | F8: =SUM('EDl log'!T10) -> 0.079356749 | G8: =-tanks!AW12 -> 861.8 | H8: =SUM(tanks!AV12) -> 0.54666 | I8: =('B5'!AU11)*0.51 -> 183.6 | J8: ='B5'!AX11/0.51 -> 1.372549 | K8: =WATER!I12 -> 212 | L8: =SUM(WATER!J12) -> 2.8012051 | M8: =WATER!Q12 -> 0 | N8: 0.6 | O8: =ELEC!B9 -> 125.005
A9: Beirut | B9: =B8+1 -> 8 | C9: 10 | D9: 2019 | E9: =ELEC!N10 -> 28488.6 | F9: =SUM('EDl log'!T11) -> 0.075329674 | G9: =-tanks!AW13 -> 807.8 | H9: =SUM(tanks!AV13) -> 0.54666 | I9: =('B5'!AU12)*0.51 -> 122.4 | J9: ='B5'!AX12/0.51 -> 1.372549 | K9: =WATER!I13 -> 355 | L9: =SUM(WATER!J13) -> 1.5512549 | M9: =WATER!Q13 -> 0 | N9: 0.6 | O9: =ELEC!B10 -> 150.995
A10: Beirut | B10: =B9+1 -> 9 | C10: 10 | D10: 2019 | E10: =ELEC!N11 -> 30559.4 | F10: =SUM('EDl log'!T12) -> 0.07805182 | G10: =-tanks!AW14 -> 880.7 | H10: =SUM(tanks!AV14) -> 0.54666 | I10: =('B5'!AU13)*0.51 -> 107.1 | J10: ='B5'!AX13/0.51 -> 1.372549 | K10: =WATER!I14 -> 145 | L10: =SUM(WATER!J14) -> 3.1911413 | M10: =WATER!Q14 -> 0 | N10: 0.6 | O10: =ELEC!B11 -> 165.991
A11: Beirut | B11: =B10+1 -> 10 | C11: 10 | D11: 2019 | E11: =ELEC!N12 -> 34481.8 | F11: =SUM('EDl log'!T13) -> 0.079007137 | G11: =-tanks!AW15 -> 839.1 | H11: =SUM(tanks!AV15) -> 0.54666 | I11: =('B5'!AU14)*0.51 -> 122.4 | J11: ='B5'!AX14/0.51 -> 1.372549 | K11: =WATER!I15 -> 357 | L11: =SUM(WATER!J15) -> 1.5425644 | M11: =WATER!Q15 -> 0 | N11: 0.6 | O11: =ELEC!B12 -> 198.007
A12: Beirut | B12: =B11+1 -> 11 | C12: 10 | D12: 2019 | E12: =ELEC!N13 -> 30373.2 | F12: =SUM('EDl log'!T14) -> 0.047027516 | G12: =-tanks!AW16 -> 821.9 | H12: =SUM(tanks!AV16) -> 0.55 | I12: =('B5'!AU15)*0.51 -> 367.2 | J12: ='B5'!AX15/0.51 -> 1.372549 | K12: =WATER!I16 -> 132 | L12: =SUM(WATER!J16) -> 3.4928446 | M12: =WATER!Q16 -> 0 | N12: 0.6 | O12: =ELEC!B13 -> 194.994
A13: Beirut | B13: =B12+1 -> 12 | C13: 10 | D13: 2019 | E13: =ELEC!N14 -> 30850 | F13: =SUM('EDl log'!T15) -> 0.072366846 | G13: =-tanks!AW17 -> 844.2 | H13: =SUM(tanks!AV17) -> 0.55 | I13: =('B5'!AU16)*0.51 -> 76.5 | J13: ='B5'!AX16/0.51 -> 1.372549 | K13: =WATER!I17 -> 654 | L13: =SUM(WATER!J17) -> 0.36993193 | M13: =WATER!Q17 -> 0 | N13: 0.6 | O13: =ELEC!B14 -> 135.01
A14: Beirut | B14: =B13+1 -> 13 | C14: 10 | D14: 2019 | E14: =ELEC!N15 -> 30370.4 | F14: =SUM('EDl log'!T16) -> 0.0711857 | G14: =-tanks!AW18 -> 925.3 | H14: =SUM(tanks!AV18) -> 0.55 | I14: =('B5'!AU17)*0.51 -> 183.6 | J14: ='B5'!AX17/0.51 -> 1.372549 | K14: =WATER!I18 -> 133 | L14: =SUM(WATER!J18) -> 3.4790638 | M14: =WATER!Q18 -> 0 | N14: 0.6 | O14: =ELEC!B15 -> 121.003
... A32: Beirut | B32: =B31+1 -> 31 | C32: 10 | D32: 2019 | E32: =ELEC!N33 -> 0 | F32: =SUM('EDl log'!T34) -> 0 | G32: =-tanks!AW36 -> 0 | H32: =SUM(tanks!AV36) -> 0.55 | I32: =('B5'!AU35)*0.51 -> 0 | J32: ='B5'!AX35/0.51 -> 1.372549 | K32: =WATER!I36 -> 0 | L32: =SUM(WATER!J36) -> 0 | M32: =WATER!Q36 -> 0 | N32: 0.6 | O32: =ELEC!B33 -> 0

Sheet Submetering
A1: Site Name | B1: Day | C1: Month | D1: Year | E1: ATS1 Kwh | F1: ATS2 Kwh | G1: ATS3 Kwh | H1: ATS4 Kwh | I1: ATS5 Kwh | J1: Guest (m3) | K1: Kitchen & Laundry (m3) | L1: Room Nights
A2: Beirut | B2: 1 | C2: 10 | D2: 2019 | E2: =ELEC!M3 -> 5576 | F2: =ELEC!K3 -> 5414 | G2: =ELEC!I3 -> 4010 | H2: =ELEC!E3 -> 11780 | I2: =ELEC!G3 -> 3434 | J2: =WATER!Y6 -> 100 | K2: =WATER!AJ6 -> 48 | L2: =ELEC!B3 -> 158.999
A3: Beirut | B3: =B2+1 -> 2 | C3: 10 | D3: 2019 | E3: =ELEC!M4 -> 5830 | F3: =ELEC!K4 -> 6116 | G3: =ELEC!I4 -> 4362 | H3: =ELEC!E4 -> 12412 | I3: =ELEC!G4 -> 3784 | J3: =WATER!Y7 -> 25 | K3: =WATER!AJ7 -> 90 | L3: =ELEC!B4 -> 161.989
A4: Beirut | B4: =B3+1 -> 3 | C4: 10 | D4: 2019 | E4: =ELEC!M5 -> 5750 | F4: =ELEC!K5 -> 7216 | G4: =ELEC!I5 -> 4016 | H4: =ELEC!E5 -> 8900 | I4: =ELEC!G5 -> 3520 | J4: =WATER!Y8 -> 77 | K4: =WATER!AJ8 -> 102 | L4: =ELEC!B5 -> 188.991
A5: Beirut | B5: =B4+1 -> 4 | C5: 10 | D5: 2019 | E5: =ELEC!M6 -> 5848 | F5: =ELEC!K6 -> 5344 | G5: =ELEC!I6 -> 4342 | H5: =ELEC!E6 -> 12838 | I5: =ELEC!G6 -> 3792 | J5: =WATER!Y9 -> 136 | K5: =WATER!AJ9 -> 134 | L5: =ELEC!B6 -> 191.82
A6: Beirut | B6: =B5+1 -> 5 | C6: 10 | D6: 2019 | E6: =ELEC!M7 -> 5596 | F6: =ELEC!K7 -> 5198 | G6: =ELEC!I7 -> 4316 | H6: =ELEC!E7 -> 12226 | I6: =ELEC!G7 -> 3810 | J6: =WATER!Y10 -> 23 | K6: =WATER!AJ10 -> 97 | L6: =ELEC!B7 -> 177.008
A7: Beirut | B7: =B6+1 -> 6 | C7: 10 | D7: 2019 | E7: =ELEC!M8 -> 4540 | F7: =ELEC!K8 -> 4004 | G7: =ELEC!I8 -> 3684 | H7: =ELEC!E8 -> 10966 | I7: =ELEC!G8 -> 3082.8 | J7: =WATER!Y11 -> 88 | K7: =WATER!AJ11 -> 99 | L7: =ELEC!B8 -> 131.997
A8: Beirut | B8: =B7+1 -> 7 | C8: 10 | D8: 2019 | E8: =ELEC!M9 -> 5220 | F8: =ELEC!K9 -> 5526 | G8: =ELEC!I9 -> 4044 | H8: =ELEC!E9 -> 10792 | I8: =ELEC!G9 -> 3515.4 | J8: =WATER!Y12 -> 116 | K8: =WATER!AJ12 -> 34 | L8: =ELEC!B9 -> 125.005
A9: Beirut | B9: =B8+1 -> 8 | C9: 10 | D9: 2019 | E9: =ELEC!M10 -> 5216 | F9: =ELEC!K10 -> 3636 | G9: =ELEC!I10 -> 4056 | H9: =ELEC!E10 -> 12040 | I9: =ELEC!G10 -> 3540.6 | J9: =WATER!Y13 -> 97 | K9: =WATER!AJ13 -> 146 | L9: =ELEC!B10 -> 150.995
A10: Beirut | B10: =B9+1 -> 9 | C10: 10 | D10: 2019 | E10: =ELEC!M11 -> 7068 | F10: =ELEC!K11 -> 4976 | G10: =ELEC!I11 -> 4182 | H10: =ELEC!E11 -> 10628 | I10: =ELEC!G11 -> 3705.4 | J10: =WATER!Y14 -> 62 | K10: =WATER!AJ14 -> 119 | L10: =ELEC!B11 -> 165.991
A11: Beirut | B11: =B10+1 -> 10 | C11: 10 | D11: 2019 | E11: =ELEC!M12 -> 11152 | F11: =ELEC!K12 -> 4192 | G11: =ELEC!I12 -> 4536 | H11: =ELEC!E12 -> 10552 | I11: =ELEC!G12 -> 4049.8 | J11: =WATER!Y15 -> 107 | K11: =WATER!AJ15 -> 134 | L11: =ELEC!B12 -> 198.007
A12: Beirut | B12: =B11+1 -> 11 | C12: 10 | D12: 2019 | E12: =ELEC!M13 -> 6476 | F12: =ELEC!K13 -> 6918 | G12: =ELEC!I13 -> 4046 | H12: =ELEC!E13 -> 9476 | I12: =ELEC!G13 -> 3457.2 | J12: =WATER!Y16 -> 251 | K12: =WATER!AJ16 -> 103 | L12: =ELEC!B13 -> 194.994
A13: Beirut | B13: =B12+1 -> 12 | C13: 10 | D13: 2019 | E13: =ELEC!M14 -> 6960 | F13: =ELEC!K14 -> 8562 | G13: =ELEC!I14 -> 4318 | H13: =ELEC!E14 -> 7284 | I13: =ELEC!G14 -> 3726 | J13: =WATER!Y17 -> 80 | K13: =WATER!AJ17 -> 51 | L13: =ELEC!B14 -> 135.01
A14: Beirut | B14: =B13+1 -> 13 | C14: 10 | D14: 2019 | E14: =ELEC!M15 -> 11470 | F14: =ELEC!K15 -> 4040 | G14: =ELEC!I15 -> 4352 | H14: =ELEC!E15 -> 6856 | I14: =ELEC!G15 -> 3652.4 | J14: =WATER!Y18 -> 19 | K14: =WATER!AJ18 -> 76 | L14: =ELEC!B15 -> 121.003
... A32: Beirut | B32: =B31+1 -> 31 | C32: 10 | D32: 2019 | E32: =ELEC!M33 -> 0 | F32: =ELEC!K33 -> 0 | G32: =ELEC!I33 -> 0 | H32: =ELEC!E33 -> 0 | I32: =ELEC!G33 -> 0 | J32: =WATER!Y36 -> 0 | K32: =WATER!AJ36 -> 0 | L32: =ELEC!B33 -> 0

Sheet ELEC
A1: OOC | B1: Room OCC | D1: MDB3 | E1: MDB3/day | F1: EMDB2 | G1: EMDB2/day | H1: EMDB1 | I1: EMDB1/day | J1: MDB2 | K1: mdb2/day | L1: MDB1 | M1: MDB1/Day | N1: Total KWH | O1: KWH/Rooc | P1: Gen MHW | Q1: Gen/Day KWH | R1: EDL KWH | S1: CH1 RH | T1: RH | U1: C1h1 power | V1: CH1 Con KWH | W1: CH2 RH | X1: RH | Y1: Ch2 power | Z1: CH2 Con KWH | AA1: CH3 RH | AB1: RH | AC1: Ch3 power | AD1: CH3 Con KWH | AE1: RH total | AF1: KWH total | AG1: AVG chiller KW/Hr
A2: 0.7652 | B2: 175.996 | C2: 43738 | D2: 30782304 | E2: 13854 | F2: 3199141 | G2: 3784.8 | H2: 16972776 | I2: 4402 | J2: 27970652 | K2: 5446 | L2: 22059422 | M2: 6092 | N2: 33578.8 | O2: 226.87612 | P2: 14905.282 | Q2: 10578 | R2: 23000.8 | S2: 7954 | T2: 0 | U2: 931661 | V2: 0 | W2: 31411 | X2: 10 | Y2: 534793 | Z2: 2196 | AA2: 34291 | AB2: 24 | AC2: 613447 | AD2: 5698 | AE2: 34 | AF2: 7894 | AG2: 232.17647 | AH2: 0 | AI2: -47568596
A3: ='General information '!F6 -> 0.6913 | B3: =SUM(230*A3) -> 158.999 | C3: 43739 | D3: 30794084 | E3: =D3-D2 -> 11780 | F3: 3202575 | G3: =F3-F2 -> 3434 | H3: 16976786 | I3: =H3-H2 -> 4010 | J3: 27976066 | K3: =J3-J2 -> 5414 | L3: 22064998 | M3: =L3-L2 -> 5576 | N3: =M3+K3+I3+G3+E3 -> 30214 | O3: =IF(B3>0,N3/B3,0) -> 190.02635 | P3: 14915.716 | Q3: =(P3-P2)*1000 -> 10434 | R3: =+N3-Q3 -> 19780 | S3: 7954 | T3: =S3-S2 -> 0 | U3: 931661 | V3: =U3-U2 -> 0 | W3: 31421 | X3: =W3-W2 -> 10 | Y3: 537236 | Z3: =Y3-Y2 -> 2443 | AA3: 34310 | AB3: =AA3-AA2 -> 19 | AC3: 618417 | AD3: =AC3-AC2 -> 4970 | AE3: =AB3+X3+T3 -> 29 | AF3: =V3+Z3+AD3 -> 7413 | AG3: =IF(AE3>0,AF3/AE3,0) -> 255.62069
A4: ='General information '!F7 -> 0.7043 | B4: =SUM(230*A4) -> 161.989 | C4: 43740 | D4: 30806496 | E4: =D4-D3 -> 12412 | F4: 3206359 | G4: =F4-F3 -> 3784 | H4: 16981148 | I4: =H4-H3 -> 4362 | J4: 27982182 | K4: =J4-J3 -> 6116 | L4: 22070828 | M4: =L4-L3 -> 5830 | N4: =M4+K4+I4+G4+E4 -> 32504 | O4: =IF(B4>0,N4/B4,0) -> 200.6556 | P4: 14926 | Q4: =(P4-P3)*1000 -> 10284 | R4: =N4-Q4 -> 22220 | S4: =S3 -> 7954 | T4: =S4-S3 -> 0 | U4: =U3 -> 931661 | V4: =U4-U3 -> 0 | W4: 31432 | X4: =W4-W3 -> 11 | Y4: 539496 | Z4: =Y4-Y3 -> 2260 | AA4: 34332 | AB4: =AA4-AA3 -> 22 | AC4: 623604 | AD4: =AC4-AC3 -> 5187 | AE4: =AB4+X4+T4 -> 33 | AF4: =V4+Z4+AD4 -> 7447 | AG4: =IF(AE4>0,AF4/AE4,0) -> 225.66667
A5: ='General information '!F8 -> 0.8217 | B5: =SUM(230*A5) -> 188.991 | C5: 43741 | D5: 30815396 | E5: =D5-D4 -> 8900 | F5: 3209879 | G5: =F5-F4 -> 3520 | H5: 16985164 | I5: =H5-H4 -> 4016 | J5: 27989398 | K5: =J5-J4 -> 7216 | L5: 22076578 | M5: =L5-L4 -> 5750 | N5: =M5+K5+I5+G5+E5 -> 29402 | O5: =IF(B5>0,N5/B5,0) -> 155.57355 | P5: 14937.113 | Q5: =(P5-P4)*1000 -> 11113 | R5: =N5-Q5 -> 18289 | S5: =S4 -> 7954 | T5: =S5-S4 -> 0 | U5: =U4 -> 931661 | V5: =U5-U4 -> 0 | W5: 31452 | X5: =W5-W4 -> 20 | Y5: 544350 | Z5: =Y5-Y4 -> 4854 | AA5: 34340 | AB5: =AA5-AA4 -> 8 | AC5: 625359 | AD5: =AC5-AC4 -> 1755 | AE5: =AB5+X5+T5 -> 28 | AF5: =V5+Z5+AD5 -> 6609 | AG5: =IF(AE5>0,AF5/AE5,0) -> 236.03571 | AI5: =R5-'EDl log'!B3 -> -48526813
A6: ='General information '!F9 -> 0.834 | B6: =SUM(230*A6) -> 191.82 | C6: 43742 | D6: 30828234 | E6: =D6-D5 -> 12838 | F6: 3213671 | G6: =F6-F5 -> 3792 | H6: 16989506 | I6: =H6-H5 -> 4342 | J6: 27994742 | K6: =J6-J5 -> 5344 | L6: 22082426 | M6: =L6-L5 -> 5848 | N6: =M6+K6+I6+G6+E6 -> 32164 | O6: =IF(B6>0,N6/B6,0) -> 167.67803 | P6: 14944.5 | Q6: =(P6-P5)*1000 -> 7387 | R6: =N6-Q6 -> 24777 | S6: =S5 -> 7954 | T6: =S6-S5 -> 0 | U6: 931661 | V6: =U6-U5 -> 0 | W6: 31463 | X6: =W6-W5 -> 11 | Y6: 546324 | Z6: =Y6-Y5 -> 1974 | AA6: 34363 | AB6: =AA6-AA5 -> 23 | AC6: 630287 | AD6: =AC6-AC5 -> 4928 | AE6: =AB6+X6+T6 -> 34 | AF6: =V6+Z6+AD6 -> 6902 | AG6: =IF(AE6>0,AF6/AE6,0) -> 203 | AI6: =R6-'EDl log'!B4 -> -48530520
A7: ='General information '!F10 -> 0.7696 | B7: =SUM(230*A7) -> 177.008 | C7: 43743 | D7: 30840460 | E7: =D7-D6 -> 12226 | F7: 3217481 | G7: =F7-F6 -> 3810 | H7: 16993822 | I7: =H7-H6 -> 4316 | J7: 27999940 | K7: =J7-J6 -> 5198 | L7: 22088022 | M7: =L7-L6 -> 5596 | N7: =M7+K7+I7+G7+E7 -> 31146 | O7: =IF(B7>0,N7/B7,0) -> 175.95815 | P7: 14949.3 | Q7: =(P7-P6)*1000 -> 4800 | R7: =N7-Q24 -> 31146 | S7: =S6 -> 7954 | T7: =S7-S6 -> 0 | U7: =U6 -> 931661 | V7: =U7-U6 -> 0 | W7: 31472 | X7: =W7-W6 -> 9 | Y7: 548371 | Z7: =Y7-Y6 -> 2047 | AA7: 34384 | AB7: =AA7-AA6 -> 21 | AC7: 635089 | AD7: =AC7-AC6 -> 4802 | AE7: =AB7+X7+T7 -> 30 | AF7: =V7+Z7+AD7 -> 6849 | AG7: =IF(AE7>0,AF7/AE7,0) -> 228.3 | AI7: =R7-'EDl log'!B5 -> -48535368
A8: ='General information '!F11 -> 0.5739 | B8: =SUM(230*A8) -> 131.997 | C8: 43744 | D8: 30851426 | E8: =D8-D7 -> 10966 | F8: 3220563.8 | G8: =F8-F7 -> 3082.8 | H8: 16997506 | I8: =H8-H7 -> 3684 | J8: 28003944 | K8: =J8-J7 -> 4004 | L8: 22092562 | M8: =L8-L7 -> 4540 | N8: =M8+K8+I8+G8+E8 -> 26276.8 | O8: =IF(B8>0,N8/B8,0) -> 199.07119 | P8: 14953.444 | Q8: =(P8-P7)*1000 -> 4144 | R8: =N8-Q8 -> 22132.8 | S8: =S7 -> 7954 | T8: =S8-S7 -> 0 | U8: =U7 -> 931661 | V8: =U8-U7 -> 0 | W8: 31481 | X8: =W8-W7 -> 9 | Y8: 549937 | Z8: =Y8-Y7 -> 1566 | AA8: 34408 | AB8: =AA8-AA7 -> 24 | AC8: 640293 | AD8: =AC8-AC7 -> 5204 | AE8: =AB8+X8+T8 -> 33 | AF8: =V8+Z8+AD8 -> 6770 | AG8: =IF(AE8>0,AF8/AE8,0) -> 205.15152 | AI8: =R8-'EDl log'!B6 -> -48554069
A9: ='General information '!F12 -> 0.5435 | B9: =SUM(230*A9) -> 125.005 | C9: 43745 | D9: 30862218 | E9: =D9-D8 -> 10792 | F9: 3224079.2 | G9: =F9-F8 -> 3515.4 | H9: 17001550 | I9: =H9-H8 -> 4044 | J9: 28009470 | K9: =J9-J8 -> 5526 | L9: 22097782 | M9: =L9-L8 -> 5220 | N9: =M9+K9+I9+G9+E9 -> 29097.4 | O9: =IF(B9>0,N9/B9,0) -> 232.76989 | P9: 14958.183 | Q9: =(P9-P8)*1000 -> 4739 | R9: =N9-Q9 -> 24358.4 | S9: =S8 -> 7954 | T9: =S9-S8 -> 0 | U9: =U8 -> 931661 | V9: =U9-U8 -> 0 | W9: 31492 | X9: =W9-W8 -> 11 | Y9: 552458 | Z9: =Y9-Y8 -> 2521 | AA9: 34426 | AB9: =AA9-AA8 -> 18 | AC9: 644100 | AD9: =AC9-AC8 -> 3807 | AE9: =AB9+X9+T9 -> 29 | AF9: =V9+Z9+AD9 -> 6328 | AG9: =IF(AE9>0,AF9/AE9,0) -> 218.2069 | AI9: =R9-'EDl log'!B7 -> -48564582
A10: ='General information '!F13 -> 0.6565 | B10: =SUM(230*A10) -> 150.995 | C10: 43746 | D10: 30874258 | E10: =D10-D9 -> 12040 | F10: 3227619.8 | G10: =F10-F9 -> 3540.6 | H10: 17005606 | I10: =H10-H9 -> 4056 | J10: 28013106 | K10: =J10-J9 -> 3636 | L10: 22102998 | M10: =L10-L9 -> 5216 | N10: =M10+K10+I10+G10+E10 -> 28488.6 | O10: =IF(B10>0,N10/B10,0) -> 188.67247 | P10: 14962.741 | Q10: =(P10-P9)*1000 -> 4558 | R10: =N10-Q10 -> 23930.6 | S10: =S9 -> 7954 | T10: =S10-S9 -> 0 | U10: =U9 -> 931661 | V10: =U10-U9 -> 0 | W10: 31496 | X10: =W10-W9 -> 4 | Y10: 553173 | Z10: =Y10-Y9 -> 715 | AA10: 34450 | AB10: =AA10-AA9 -> 24 | AC10: 649709 | AD10: =AC10-AC9 -> 5609 | AE10: =AB10+X10+T10 -> 28 | AF10: =V10+Z10+AD10 -> 6324 | AG10: =IF(AE10>0,AF10/AE10,0) -> 225.85714 | AI10: =R10-'EDl log'!B8 -> -48578669
A11: ='General information '!F14 -> 0.7217 | B11: =SUM(230*A11) -> 165.991 | C11: 43747 | D11: 30884886 | E11: =D11-D10 -> 10628 | F11: 3231325.2 | G11: =F11-F10 -> 3705.4 | H11: 17009788 | I11: =H11-H10 -> 4182 | J11: 28018082 | K11: =J11-J10 -> 4976 | L11: 22110066 | M11: =L11-L10 -> 7068 | N11: =M11+K11+I11+G11+E11 -> 30559.4 | O11: =IF(B11>0,N11/B11,0) -> 184.10275 | P11: 14967.167 | Q11: =(P11-P10)*1000 -> 4426 | R11: =N11-Q11 -> 26133.4 | S11: 7962 | T11: =S11-S10 -> 8 | U11: 933540 | V11: =U11-U10 -> 1879 | W11: 31505 | X11: =W11-W10 -> 9 | Y11: 555087 | Z11: =Y11-Y10 -> 1914 | AA11: 34466 | AB11: =AA11-AA10 -> 16 | AC11: 653590 | AD11: =AC11-AC10 -> 3881 | AE11: =AB11+X11+T11 -> 33 | AF11: =V11+Z11+AD11 -> 7674 | AG11: =IF(AE11>0,AF11/AE11,0) -> 232.54545 | AI11: =R11-'EDl log'!B9 -> -48587708
A12: ='General information '!F15 -> 0.8609 | B12: =SUM(230*A12) -> 198.007 | C12: 43748 | D12: 30895438 | E12: =D12-D11 -> 10552 | F12: 3235375 | G12: =F12-F11 -> 4049.8 | H12: 17014324 | I12: =H12-H11 -> 4536 | J12: 28022274 | K12: =J12-J11 -> 4192 | L12: 22121218 | M12: =L12-L11 -> 11152 | N12: =M12+K12+I12+G12+E12 -> 34481.8 | O12: =IF(B12>0,N12/B12,0) -> 174.14435 | P12: 14976.67 | Q12: =(P12-P11)*1000 -> 9503 | R12: =N12-Q12 -> 24978.8 | S12: 7981 | T12: =S12-S11 -> 19 | U12: 937922 | V12: =U12-U11 -> 4382 | W12: 31509 | X12: =W12-W11 -> 4 | Y12: 555980 | Z12: =Y12-Y11 -> 893 | AA12: 34480 | AB12: =AA12-AA11 -> 14 | AC12: 656281 | AD12: =AC12-AC11 -> 2691 | AE12: =AB12+X12+T12 -> 37 | AF12: =V12+Z12+AD12 -> 7966 | AG12: =IF(AE12>0,AF12/AE12,0) -> 215.2973 | AI12: =R12-'EDl log'!B10 -> -48601367
A13: ='General information '!F16 -> 0.8478 | B13: =SUM(230*A13) -> 194.994 | C13: 43749 | D13: 30904914 | E13: =D13-D12 -> 9476 | F13: 3238832.2 | G13: =F13-F12 -> 3457.2 | H13: 17018370 | I13: =H13-H12 -> 4046 | J13: 28029192 | K13: =J13-J12 -> 6918 | L13: 22127694 | M13: =L13-L12 -> 6476 | N13: =M13+K13+I13+G13+E13 -> 30373.2 | O13: =IF(B13>0,N13/B13,0) -> 155.76479 | P13: 14987.311 | Q13: =(P13-P12)*1000 -> 10641 | R13: =N13-Q13 -> 19732.2 | S13: 7988 | T13: =S13-S12 -> 7 | U13: 939330 | V13: =U13-U12 -> 1408 | W13: 31527 | X13: =W13-W12 -> 18 | Y13: 559535 | Z13: =Y13-Y12 -> 3555 | AA13: 34491 | AB13: =AA13-AA12 -> 11 | AC13: 658290 | AD13: =AC13-AC12 -> 2009 | AE13: =AB13+X13+T13 -> 36 | AF13: =V13+Z13+AD13 -> 6972 | AG13: =IF(AE13>0,AF13/AE13,0) -> 193.66667 | AI13: =R13-'EDl log'!B11 -> -48618904
A14: ='General information '!F17 -> 0.587 | B14: =SUM(230*A14) -> 135.01 | C14: 43750 | D14: 30912198 | E14: =D14-D13 -> 7284 | F14: 3242558.2 | G14: =F14-F13 -> 3726 | H14: 17022688 | I14: =H14-H13 -> 4318 | J14: 28037754 | K14: =J14-J13 -> 8562 | L14: 22134654 | M14: =L14-L13 -> 6960 | N14: =M14+K14+I14+G14+E14 -> 30850 | O14: =IF(B14>0,N14/B14,0) -> 228.50159 | P14: 14991.858 | Q14: =(P14-P13)*1000 -> 4547 | R14: =N14-Q14 -> 26303 | S14: 7994 | T14: =S14-S13 -> 6 | U14: 940660 | V14: =U14-U13 -> 1330 | W14: 31549 | X14: =W14-W13 -> 22 | Y14: 564560 | Z14: =Y14-Y13 -> 5025 | AA14: 34492 | AB14: =AA14-AA13 -> 1 | AC14: 658475 | AD14: =AC14-AC13 -> 185 | AE14: =AB14+X14+T14 -> 29 | AF14: =V14+Z14+AD14 -> 6540 | AG14: =IF(AE14>0,AF14/AE14,0) -> 225.51724 | AI14: =R14-'EDl log'!B12 -> -48625713
A15: ='General information '!F18 -> 0.5261 | B15: =SUM(230*A15) -> 121.003 | C15: 43751 | D15: 30919054 | E15: =D15-D14 -> 6856 | F15: 3246210.6 | G15: =F15-F14 -> 3652.4 | H15: 17027040 | I15: =H15-H14 -> 4352 | J15: 28041794 | K15: =J15-J14 -> 4040 | L15: 22146124 | M15: =L15-L14 -> 11470 | N15: =M15+K15+I15+G15+E15 -> 30370.4 | O15: =IF(B15>0,N15/B15,0) -> 250.98882 | P15: 14995.875 | Q15: =(P15-P14)*1000 -> 4017 | R15: =N15-Q15 -> 26353.4 | S15: 8019 | T15: =S15-S14 -> 25 | U15: 946922 | V15: =U15-U14 -> 6262 | W15: 31555 | X15: =W15-W14 -> 6 | Y15: 565780 | Z15: =Y15-Y14 -> 1220 | AA15: =AA14 -> 34492 | AB15: =AA15-AA14 -> 0 | AC15: =AC14 -> 658475 | AD15: =AC15-AC14 -> 0 | AE15: =AB15+X15+T15 -> 31 | AF15: =V15+Z15+AD15 -> 7482 | AG15: =IF(AE15>0,AF15/AE15,0) -> 241.35484 | AI15: =R15-'EDl log'!B13 -> -48638573
A16: ='General information '!F19 -> 0.5826 | B16: =SUM(230*A16) -> 133.998 | C16: 43752 | D16: 30926498 | E16: =D16-D15 -> 7444 | F16: 3249618 | G16: =F16-F15 -> 3407.4 | H16: 17031052 | I16: =H16-H15 -> 4012 | J16: 28048670 | K16: =J16-J15 -> 6876 | L16: 22153700 | M16: =L16-L15 -> 7576 | N16: =M16+K16+I16+G16+E16 -> 29315.4 | O16: =IF(B16>0,N16/B16,0) -> 218.77491 | P16: 15007.06 | Q16: =(P16-P15)*1000 -> 11185 | R16: =N16-Q16 -> 18130.4 | S16: 8031 | T16: =S16-S15 -> 12 | U16: 949426 | V16: =U16-U15 -> 2504 | W16: 31574 | X16: =W16-W15 -> 19 | Y16: 569805 | Z16: =Y16-Y15 -> 4025 | AA16: 34492 | AB16: =AA16-AA15 -> 0 | AC16: 658787 | AD16: =AC16-AC15 -> 312 | AE16: =AB16+X16+T16 -> 31 | AF16: =V16+Z16+AD16 -> 6841 | AG16: =IF(AE16>0,AF16/AE16,0) -> 220.67742 | AI16: =R16-'EDl log'!B14 -> -48657029
A17: ='General information '!F20 -> 0 | B17: =SUM(230*A17) -> 0 | C17: 43753 | D17: =D16 -> 30926498 | E17: =D17-D16 -> 0 | F17: =F16 -> 3249618 | G17: =F17-F16 -> 0 | H17: =H16 -> 17031052 | I17: =H17-H16 -> 0 | J17: =J16 -> 28048670 | K17: =J17-J16 -> 0 | L17: =L16 -> 22153700 | M17: =L17-L16 -> 0 | N17: =M17+K17+I17+G17+E17 -> 0 | O17: =IF(B17>0,N17/B17,0) -> 0 | P17: =P16 -> 15007.06 | Q17: =(P17-P16)*1000 -> 0 | R17: =N17-Q17 -> 0 | S17: =S16 -> 8031 | T17: =S17-S16 -> 0 | U17: =U16 -> 949426 | V17: =U17-U16 -> 0 | W17: =W16 -> 31574 | X17: =W17-W16 -> 0 | Y17: =Y16 -> 569805 | Z17: =Y17-Y16 -> 0 | AA17: =AA16 -> 34492 | AB17: =AA17-AA16 -> 0 | AC17: =AC16 -> 658787 | AD17: =AC17-AC16 -> 0 | AE17: =AB17+X17+T17 -> 0 | AF17: =V17+Z17+AD17 -> 0 | AG17: =IF(AE17>0,AF17/AE17,0) -> 0 | AI17: =R17-'EDl log'!B15 -> -48688662
A18: ='General information '!F21 -> 0 | B18: =SUM(230*A18) -> 0 | C18: 43754 | D18: =D17 -> 30926498 | E18: =D18-D17 -> 0 | F18: =F17 -> 3249618 | G18: =F18-F17 -> 0 | H18: =H17 -> 17031052 | I18: =H18-H17 -> 0 | J18: =J17 -> 28048670 | K18: =J18-J17 -> 0 | L18: =L17 -> 22153700 | M18: =L18-L17 -> 0 | N18: =M18+K18+I18+G18+E18 -> 0 | O18: =IF(B18>0,N18/B18,0) -> 0 | P18: =P17 -> 15007.06 | Q18: =(P18-P17)*1000 -> 0 | R18: =N18-Q18 -> 0 | S18: =S17 -> 8031 | T18: =S18-S17 -> 0 | U18: =U17 -> 949426 | V18: =U18-U17 -> 0 | W18: =W17 -> 31574 | X18: =W18-W17 -> 0 | Y18: =Y17 -> 569805 | Z18: =Y18-Y17 -> 0 | AA18: =AA17 -> 34492 | AB18: =AA18-AA17 -> 0 | AC18: =AC17 -> 658787 | AD18: =AC18-AC17 -> 0 | AE18: =AB18+X18+T18 -> 0 | AF18: =V18+Z18+AD18 -> 0 | AG18: =IF(AE18>0,AF18/AE18,0) -> 0 | AI18: =R18-'EDl log'!B16 -> -48702158
A19: ='General information '!F22 -> 0 | B19: =SUM(230*A19) -> 0 | C19: 43755 | D19: =D18 -> 30926498 | E19: =D19-D18 -> 0 | F19: =F18 -> 3249618 | G19: =F19-F18 -> 0 | H19: =H18 -> 17031052 | I19: =H19-H18 -> 0 | J19: =J18 -> 28048670 | K19: =J19-J18 -> 0 | L19: =L18 -> 22153700 | M19: =L19-L18 -> 0 | N19: =M19+K19+I19+G19+E19 -> 0 | O19: =IF(B19>0,N19/B19,0) -> 0 | P19: =P18 -> 15007.06 | Q19: =(P19-P18)*1000 -> 0 | R19: =N19-Q19 -> 0 | S19: =S18 -> 8031 | T19: =S19-S18 -> 0 | U19: =U18 -> 949426 | V19: =U19-U18 -> 0 | W19: =W18 -> 31574 | X19: =W19-W18 -> 0 | Y19: =Y18 -> 569805 | Z19: =Y19-Y18 -> 0 | AA19: =AA18 -> 34492 | AB19: =AA19-AA18 -> 0 | AC19: =AC18 -> 658787 | AD19: =AC19-AC18 -> 0 | AE19: =AB19+X19+T19 -> 0 | AF19: =V19+Z19+AD19 -> 0 | AG19: =IF(AE19>0,AF19/AE19,0) -> 0 | AI19: =R19-'EDl log'!B17 -> -48711532
A20: ='General information '!F23 -> 0 | B20: =SUM(230*A20) -> 0 | C20: 43756 | D20: =D19 -> 30926498 | E20: =D20-D19 -> 0 | F20: =F19 -> 3249618 | G20: =F20-F19 -> 0 | H20: =H19 -> 17031052 | I20: =H20-H19 -> 0 | J20: =J19 -> 28048670 | K20: =J20-J19 -> 0 | L20: =L19 -> 22153700 | M20: =L20-L19 -> 0 | N20: =M20+K20+I20+G20+E20 -> 0 | O20: =IF(B20>0,N20/B20,0) -> 0 | P20: =P19 -> 15007.06 | Q20: =(P20-P19)*1000 -> 0 | R20: =N20-Q20 -> 0 | S20: =S19 -> 8031 | T20: =S20-S19 -> 0 | U20: =U19 -> 949426 | V20: =U20-U19 -> 0 | W20: =W19 -> 31574 | X20: =W20-W19 -> 0 | Y20: =Y19 -> 569805 | Z20: =Y20-Y19 -> 0 | AA20: =AA19 -> 34492 | AB20: =AA20-AA19 -> 0 | AC20: =AC19 -> 658787 | AD20: =AC20-AC19 -> 0 | AE20: =AB20+X20+T20 -> 0 | AF20: =V20+Z20+AD20 -> 0 | AG20: =IF(AE20>0,AF20/AE20,0) -> 0 | AI20: =R20-'EDl log'!B18 -> -48711532
A21: ='General information '!F24 -> 0 | B21: =SUM(230*A21) -> 0 | C21: 43757 | D21: =D20 -> 30926498 | E21: =D21-D20 -> 0 | F21: =F20 -> 3249618 | G21: =F21-F20 -> 0 | H21: =H20 -> 17031052 | I21: =H21-H20 -> 0 | J21: =J20 -> 28048670 | K21: =J21-J20 -> 0 | L21: =L20 -> 22153700 | M21: =L21-L20 -> 0 | N21: =M21+K21+I21+G21+E21 -> 0 | O21: =IF(B21>0,N21/B21,0) -> 0 | P21: =P20 -> 15007.06 | Q21: =(P21-P20)*1000 -> 0 | R21: =N21-Q21 -> 0 | S21: =S20 -> 8031 | T21: =S21-S20 -> 0 | U21: =U20 -> 949426 | V21: =U21-U20 -> 0 | W21: =W20 -> 31574 | X21: =W21-W20 -> 0 | Y21: =Y20 -> 569805 | Z21: =Y21-Y20 -> 0 | AA21: =AA20 -> 34492 | AB21: =AA21-AA20 -> 0 | AC21: =AC20 -> 658787 | AD21: =AC21-AC20 -> 0 | AE21: =AB21+X21+T21 -> 0 | AF21: =V21+Z21+AD21 -> 0 | AG21: =IF(AE21>0,AF21/AE21,0) -> 0 | AI21: =R21-'EDl log'!B19 -> -48711532
A22: ='General information '!F25 -> 0 | B22: =SUM(230*A22) -> 0 | C22: 43758 | D22: =D21 -> 30926498 | E22: =D22-D21 -> 0 | F22: =F21 -> 3249618 | G22: =F22-F21 -> 0 | H22: =H21 -> 17031052 | I22: =H22-H21 -> 0 | J22: =J21 -> 28048670 | K22: =J22-J21 -> 0 | L22: =L21 -> 22153700 | M22: =L22-L21 -> 0 | N22: =M22+K22+I22+G22+E22 -> 0 | O22: =IF(B22>0,N22/B22,0) -> 0 | P22: =P21 -> 15007.06 | Q22: =(P22-P21)*1000 -> 0 | R22: =N22-Q22 -> 0 | S22: =S21 -> 8031 | T22: =S22-S21 -> 0 | U22: =U21 -> 949426 | V22: =U22-U21 -> 0 | W22: =W21 -> 31574 | X22: =W22-W21 -> 0 | Y22: =Y21 -> 569805 | Z22: =Y22-Y21 -> 0 | AA22: =AA21 -> 34492 | AB22: =AA22-AA21 -> 0 | AC22: =AC21 -> 658787 | AD22: =AC22-AC21 -> 0 | AE22: =AB22+X22+T22 -> 0 | AF22: =V22+Z22+AD22 -> 0 | AG22: =IF(AE22>0,AF22/AE22,0) -> 0 | AI22: =R22-'EDl log'!B20 -> -48711532
A23: ='General information '!F26 -> 0 | B23: =SUM(230*A23) -> 0 | C23: 43759 | D23: =D22 -> 30926498 | E23: =D23-D22 -> 0 | F23: =F22 -> 3249618 | G23: =F23-F22 -> 0 | H23: =H22 -> 17031052 | I23: =H23-H22 -> 0 | J23: =J22 -> 28048670 | K23: =J23-J22 -> 0 | L23: =L22 -> 22153700 | M23: =L23-L22 -> 0 | N23: =M23+K23+I23+G23+E23 -> 0 | O23: =IF(B23>0,N23/B23,0) -> 0 | P23: =P22 -> 15007.06 | Q23: =(P23-P22)*1000 -> 0 | R23: =N23-Q23 -> 0 | S23: =S22 -> 8031 | T23: =S23-S22 -> 0 | U23: =U22 -> 949426 | V23: =U23-U22 -> 0 | W23: =W22 -> 31574 | X23: =W23-W22 -> 0 | Y23: =Y22 -> 569805 | Z23: =Y23-Y22 -> 0 | AA23: =AA22 -> 34492 | AB23: =AA23-AA22 -> 0 | AC23: =AC22 -> 658787 | AD23: =AC23-AC22 -> 0 | AE23: =AB23+X23+T23 -> 0 | AF23: =V23+Z23+AD23 -> 0 | AG23: =IF(AE23>0,AF23/AE23,0) -> 0 | AI23: =R23-'EDl log'!B21 -> -48711532
A24: ='General information '!F27 -> 0 | B24: =SUM(230*A24) -> 0 | C24: 43760 | D24: =D23 -> 30926498 | E24: =D24-D23 -> 0 | F24: =F23 -> 3249618 | G24: =F24-F23 -> 0 | H24: =H23 -> 17031052 | I24: =H24-H23 -> 0 | J24: =J23 -> 28048670 | K24: =J24-J23 -> 0 | L24: =L23 -> 22153700 | M24: =L24-L23 -> 0 | N24: =M24+K24+I24+G24+E24 -> 0 | O24: =IF(B24>0,N24/B24,0) -> 0 | P24: =P23 -> 15007.06 | Q24: =(P24-P23)*1000 -> 0 | R24: =N24-Q24 -> 0 | S24: =S23 -> 8031 | T24: =S24-S23 -> 0 | U24: =U23 -> 949426 | V24: =U24-U23 -> 0 | W24: =W23 -> 31574 | X24: =W24-W23 -> 0 | Y24: =Y23 -> 569805 | Z24: =Y24-Y23 -> 0 | AA24: =AA23 -> 34492 | AB24: =AA24-AA23 -> 0 | AC24: =AC23 -> 658787 | AD24: =AC24-AC23 -> 0 | AE24: =AB24+X24+T24 -> 0 | AF24: =V24+Z24+AD24 -> 0 | AG24: =IF(AE24>0,AF24/AE24,0) -> 0 | AI24: =R24-'EDl log'!B22 -> -48711532
A25: ='General information '!F28 -> 0 | B25: =SUM(230*A25) -> 0 | C25: 43761 | D25: =D24 -> 30926498 | E25: =D25-D24 -> 0 | F25: =F24 -> 3249618 | G25: =F25-F24 -> 0 | H25: =H24 -> 17031052 | I25: =H25-H24 -> 0 | J25: =J24 -> 28048670 | K25: =J25-J24 -> 0 | L25: =L24 -> 22153700 | M25: =L25-L24 -> 0 | N25: =M25+K25+I25+G25+E25 -> 0 | O25: =IF(B25>0,N25/B25,0) -> 0 | P25: =P24 -> 15007.06 | Q25: =(P25-P24)*1000 -> 0 | R25: =N25-Q25 -> 0 | S25: =S24 -> 8031 | T25: =S25-S24 -> 0 | U25: =U24 -> 949426 | V25: =U25-U24 -> 0 | W25: =W24 -> 31574 | X25: =W25-W24 -> 0 | Y25: =Y24 -> 569805 | Z25: =Y25-Y24 -> 0 | AA25: =AA24 -> 34492 | AB25: =AA25-AA24 -> 0 | AC25: =AC24 -> 658787 | AD25: =AC25-AC24 -> 0 | AE25: =AB25+X25+T25 -> 0 | AF25: =V25+Z25+AD25 -> 0 | AG25: =IF(AE25>0,AF25/AE25,0) -> 0 | AI25: =R25-'EDl log'!B23 -> -48711532
A26: ='General information '!F29 -> 0 | B26: =SUM(230*A26) -> 0 | C26: 43762 | D26: =D25 -> 30926498 | E26: =D26-D25 -> 0 | F26: =F25 -> 3249618 | G26: =F26-F25 -> 0 | H26: =H25 -> 17031052 | I26: =H26-H25 -> 0 | J26: =J25 -> 28048670 | K26: =J26-J25 -> 0 | L26: =L25 -> 22153700 | M26: =L26-L25 -> 0 | N26: =M26+K26+I26+G26+E26 -> 0 | O26: =IF(B26>0,N26/B26,0) -> 0 | P26: =P25 -> 15007.06 | Q26: =(P26-P25)*1000 -> 0 | R26: =N26-Q26 -> 0 | S26: =S25 -> 8031 | T26: =S26-S25 -> 0 | U26: =U25 -> 949426 | V26: =U26-U25 -> 0 | W26: =W25 -> 31574 | X26: =W26-W25 -> 0 | Y26: =Y25 -> 569805 | Z26: =Y26-Y25 -> 0 | AA26: =AA25 -> 34492 | AB26: =AA26-AA25 -> 0 | AC26: =AC25 -> 658787 | AD26: =AC26-AC25 -> 0 | AE26: =AB26+X26+T26 -> 0 | AF26: =V26+Z26+AD26 -> 0 | AG26: =IF(AE26>0,AF26/AE26,0) -> 0 | AI26: =R26-'EDl log'!B24 -> -48711532
A27: ='General information '!F30 -> 0 | B27: =SUM(230*A27) -> 0 | C27: 43763 | D27: =D26 -> 30926498 | E27: =D27-D26 -> 0 | F27: =F26 -> 3249618 | G27: =F27-F26 -> 0 | H27: =H26 -> 17031052 | I27: =H27-H26 -> 0 | J27: =J26 -> 28048670 | K27: =J27-J26 -> 0 | L27: =L26 -> 22153700 | M27: =L27-L26 -> 0 | N27: =M27+K27+I27+G27+E27 -> 0 | O27: =IF(B27>0,N27/B27,0) -> 0 | P27: =P26 -> 15007.06 | Q27: =(P27-P26)*1000 -> 0 | R27: =N27-Q27 -> 0 | S27: =S26 -> 8031 | T27: =S27-S26 -> 0 | U27: =U26 -> 949426 | V27: =U27-U26 -> 0 | W27: =W26 -> 31574 | X27: =W27-W26 -> 0 | Y27: =Y26 -> 569805 | Z27: =Y27-Y26 -> 0 | AA27: =AA26 -> 34492 | AB27: =AA27-AA26 -> 0 | AC27: =AC26 -> 658787 | AD27: =AC27-AC26 -> 0 | AE27: =AB27+X27+T27 -> 0 | AF27: =V27+Z27+AD27 -> 0 | AG27: =IF(AE27>0,AF27/AE27,0) -> 0 | AI27: =R27-'EDl log'!B25 -> -48711532
A28: ='General information '!F31 -> 0 | B28: =SUM(230*A28) -> 0 | C28: 43764 | D28: =D27 -> 30926498 | E28: =D28-D27 -> 0 | F28: =F27 -> 3249618 | G28: =F28-F27 -> 0 | H28: =H27 -> 17031052 | I28: =H28-H27 -> 0 | J28: =J27 -> 28048670 | K28: =J28-J27 -> 0 | L28: =L27 -> 22153700 | M28: =L28-L27 -> 0 | N28: =M28+K28+I28+G28+E28 -> 0 | O28: =IF(B28>0,N28/B28,0) -> 0 | P28: =P27 -> 15007.06 | Q28: =(P28-P27)*1000 -> 0 | R28: =N28-Q28 -> 0 | S28: =S27 -> 8031 | T28: =S28-S27 -> 0 | U28: =U27 -> 949426 | V28: =U28-U27 -> 0 | W28: =W27 -> 31574 | X28: =W28-W27 -> 0 | Y28: =Y27 -> 569805 | Z28: =Y28-Y27 -> 0 | AA28: =AA27 -> 34492 | AB28: =AA28-AA27 -> 0 | AC28: =AC27 -> 658787 | AD28: =AC28-AC27 -> 0 | AE28: =AB28+X28+T28 -> 0 | AF28: =V28+Z28+AD28 -> 0 | AG28: =IF(AE28>0,AF28/AE28,0) -> 0 | AI28: =R28-'EDl log'!B26 -> -48711532
... A33: ='General information '!F36 -> 0 | B33: =SUM(230*A33) -> 0 | C33: 43769 | D33: =D32 -> 30926498 | E33: =D33-D32 -> 0 | F33: =F32 -> 3249618 | G33: =F33-F32 -> 0 | H33: =H32 -> 17031052 | I33: =H33-H32 -> 0 | J33: =J32 -> 28048670 | K33: =J33-J32 -> 0 | L33: =L32 -> 22153700 | M33: =L33-L32 -> 0 | N33: =M33+K33+I33+G33+E33 -> 0 | O33: =IF(B33>0,N33/B33,0) -> 0 | P33: =P32 -> 15007.06 | Q33: =(P33-P32)*1000 -> 0 | R33: =N33-Q33 -> 0 | S33: =S32 -> 8031 | T33: =S33-S32 -> 0 | U33: =U32 -> 949426 | V33: =U33-U32 -> 0 | W33: =W32 -> 31574 | X33: =W33-W32 -> 0 | Y33: =Y32 -> 569805 | Z33: =Y33-Y32 -> 0 | AA33: =AA32 -> 34492 | AB33: =AA33-AA32 -> 0 | AC33: =AC32 -> 658787 | AD33: =AC33-AC32 -> 0 | AE33: =AB33+X33+T33 -> 0 | AF33: =V33+Z33+AD33 -> 0 | AG33: =IF(AE33>0,AF33/AE33,0) -> 0 | AI33: =R33-'EDl log'!B31 -> -48711532

Sheet B5
F1: Boiler A | J1: =J36 -> 76.791667 | K1: Boiler B | P1: Boiler C | V1: Boiler | X1: SteamA | AC1: SteamB | AH1: Steam | AI1: Boiler & steam | AL1: Total Boiler Runing H | AM1: Total Steam Runing H | AN1: GAS1 % | AO1: GAS1/L | AP1: GAS2% | AQ1: Gas2/L | AR1: GAS3% | AS1: GAS3/L | AU1: Gas Cons | AV1: Delivery | AW1: Cost/L
B2: Level Tank Gen | C2: Level tank Boiler | D2: Daily Cons Bo. | E2: Boiler litter | F2: Boiler A | G2: Run Hr a | H2: Boiler A fuel | I2: Daily consumption | J2: AVG | K2: index Run H | L2: Run Hrb | M2: Boiler B Fuel | O2: Daily consumption | P2: Boiler C | S2: Run C | U2: Total RH | V2: Total Fuel | X2: SteamA | Y2: Run SA | Z2: Steam A Conter | AA2: Liters | AC2: SteamB | AD2: Run SteamB | AE2: Steam B Conter | AF2: SB Litters | AG2: Avg | AH2: Total Fuel | AI2: Total Fuel
S3: 0
A4: =ELEC!C2 -> 43738 | B4: =[1]B5!B34 -> 202 | C4: =[1]B5!C34 -> 219 | D4: =[1]B5!D34 -> -29 | E4: =[1]B5!E34 -> -243.02 | F4: =[1]B5!F34 -> 1128 | G4: =[1]B5!G34 -> 0 | H4: =[1]B5!H34 -> 316410 | I4: =[1]B5!I34 -> 0 | ... AX4: =[1]B5!AX34 -> 0.7
A5: =ELEC!C3 -> 43739 | B5: 188 | C5: 194 | D5: =C4-C5 -> 25 | E5: =D5*8.38 -> 209.5 | F5: 1130 | G5: =F5-F4 -> 2 | H5: 316537 | I5: =SUM(H5-H4) -> 127 | J5: 1 | K5: =K4 -> 1523 | L5: =K5-K4 -> 0 | M5: =M4 -> 111660 | N5: =M5-M4 -> 0 | O5: =SUM(L5*$J$1) -> 0 | P5: 1334 | Q5: 116399 | R5: =Q5-Q4 -> 169 | S5: =SUM(P5-P4) -> 2 | T5: =SUM(S5*$T$2) -> 0 | U5: =SUM(G5+L5+S5) -> 4 | V5: =R5+N5+I5:I5 -> 296 | W5: =SUM(V5/U5) -> 74 | X5: 2185 | Y5: =X5-X4 -> 0 | Z5: 123531.8 | AA5: =Z5-Z4 -> 0 | AB5: =SUM(Y5*$AB$2) -> 0 | AC5: 1390 | AD5: =AC5-AC4 -> 12 | AE5: 337942.5 | AF5: =AE5-AE4 -> 543.1 | AG5: =IF(AD5>0,AF5/AD5,0) -> 45.258333 | AH5: =AF5+AA5 -> 543.1 | AI5: =SUM(AH5+V5) -> 839.1 | AJ5: =-tanks!AW6 -> 839.1 | AK5: =SUM(AJ5-AI5) -> 0 | AL5: =S5+L5+G5 -> 4 | AM5: =Y5+AD5 -> 12 | AN5: 68 | AO5: =(AN5/100)*3000 -> 2040 | AP5: 66 | AQ5: =(AP5/100)*3000 -> 1980 | AR5: 66 | AS5: =(AR5/100)*3000 -> 1980 | AT5: =SUM(AO5+AQ5+AS5) -> 6000 | AU5: =AT4-AT5+AV5 -> 270 | AV5: 0 | AW5: 0 | AX5: =IF(AV5>0,AW5,AX4) -> 0.7
A6: =ELEC!C4 -> 43740 | B6: 174 | C6: 180 | D6: =C5-C6 -> 14 | E6: =D6*8.38 -> 117.32 | F6: 1133 | G6: =F6-F5 -> 3 | H6: 316814 | I6: =SUM(H6-H5) -> 277 | J6: =IF(G6>0,I6/G6,0) -> 92.333333 | K6: =K5 -> 1523 | L6: =K6-K5 -> 0 | M6: =M5 -> 111660 | N6: =M6-M5 -> 0 | O6: =SUM(L6*$J$1) -> 0 | P6: 1335 | Q6: 116416 | R6: =Q6-Q5 -> 17 | S6: =SUM(P6-P5) -> 1 | T6: =SUM(S6*$T$2) -> 0 | U6: =SUM(G6+L6+S6) -> 4 | V6: =R6+N6+I6:I6 -> 294 | W6: =SUM(V6/U6) -> 73.5 | X6: =X5 -> 2185 | Y6: =X6-X5 -> 0 | Z6: =Z5 -> 123531.8 | AA6: =Z6-Z5 -> 0 | AB6: =SUM(Y6*$AB$2) -> 0 | AC6: 1401 | AD6: =AC6-AC5 -> 11 | AE6: 338451.1 | AF6: =AE6-AE5 -> 508.6 | AG6: =IF(AD6>0,AF6/AD6,0) -> 46.236364 | AH6: =AF6+AA6 -> 508.6 | AI6: =SUM(AH6+V6) -> 802.6 | AJ6: =-tanks!AW7 -> 802.6 | AK6: =SUM(AJ6-AI6) -> 0 | AL6: =S6+L6+G6 -> 4 | AM6: =Y6+AD6 -> 11 | AN6: 65 | AO6: =(AN6/100)*3000 -> 1950 | AP6: 64 | AQ6: =(AP6/100)*3000 -> 1920 | AR6: 63 | AS6: =(AR6/100)*3000 -> 1890 | AT6: =SUM(AO6+AQ6+AS6) -> 5760 | AU6: =AT5-AT6+AV6 -> 240 | AX6: =IF(AV6>0,AW6,AX5) -> 0.7
A7: =ELEC!C5 -> 43741 | B7: 159 | C7: 165 | D7: =C6-C7 -> 15 | E7: =D7*8.38 -> 125.7 | F7: 1135 | G7: =F7-F6 -> 2 | H7: 316977 | I7: =SUM(H7-H6) -> 163 | J7: =IF(G7>0,I7/G7,0) -> 81.5 | K7: =K6 -> 1523 | L7: =K7-K6 -> 0 | M7: =M6 -> 111660 | N7: =M7-M6 -> 0 | O7: 1 | P7: 1336 | Q7: 116541 | R7: =Q7-Q6 -> 125 | S7: =SUM(P7-P6) -> 1 | T7: =SUM(S7*$T$2) -> 0 | U7: =SUM(G7+L7+S7) -> 3 | V7: =R7+N7+I7:I7 -> 288 | W7: =SUM(V7/U7) -> 96 | X7: =X6 -> 2185 | Y7: =X7-X6 -> 0 | Z7: =Z6 -> 123531.8 | AA7: =Z7-Z6 -> 0 | AB7: =SUM(Y7*$AB$2) -> 0 | AC7: 1412 | AD7: =AC7-AC6 -> 11 | AE7: 338975.7 | AF7: =AE7-AE6 -> 524.6 | AG7: =IF(AD7>0,AF7/AD7,0) -> 47.690909 | AH7: =AF7+AA7 -> 524.6 | AI7: =SUM(AH7+V7) -> 812.6 | AJ7: =-tanks!AW8 -> 812.6 | AK7: =SUM(AJ7-AI7) -> 0 | AL7: =S7+L7+G7 -> 3 | AM7: =Y7+AD7 -> 11 | AN7: 63 | AO7: =(AN7/100)*3000 -> 1890 | AP7: 61 | AQ7: =(AP7/100)*3000 -> 1830 | AR7: 61 | AS7: =(AR7/100)*3000 -> 1830 | AT7: =SUM(AO7+AQ7+AS7) -> 5550 | AU7: =AT6-AT7+AV7 -> 210 | AX7: =IF(AV7>0,AW7,AX6) -> 0.7
A8: =ELEC!C6 -> 43742 | B8: 204 | C8: 210 | D8: =C7-C8 -> -45 | E8: =D8*8.38 -> -377.1 | F8: =F7 -> 1135 | G8: =F8-F7 -> 0 | H8: =H7 -> 316977 | I8: =SUM(H8-H7) -> 0 | J8: =IF(G8>0,I8/G8,0) -> 0 | K8: =K7 -> 1523 | L8: =K8-K7 -> 0 | M8: =M7 -> 111660 | N8: =M8-M7 -> 0 | O8: =SUM(L8*$J$1) -> 0 | P8: 1339 | Q8: 116834 | R8: =Q8-Q7 -> 293 | S8: =SUM(P8-P7) -> 3 | T8: =SUM(S8*$T$2) -> 0 | U8: =SUM(G8+L8+S8) -> 3 | V8: =R8+N8+I8:I8 -> 293 | W8: =SUM(V8/U8) -> 97.666667 | X8: =X7 -> 2185 | Y8: =X8-X7 -> 0 | Z8: =Z7 -> 123531.8 | AA8: =Z8-Z7 -> 0 | AB8: =SUM(Y8*$AB$2) -> 0 | AC8: 1426 | AD8: =AC8-AC7 -> 14 | AE8: 339615.2 | AF8: =AE8-AE7 -> 639.5 | AG8: =IF(AD8>0,AF8/AD8,0) -> 45.678571 | AH8: =AF8+AA8 -> 639.5 | AI8: =SUM(AH8+V8) -> 932.5 | AJ8: =-tanks!AW9 -> 932.5 | AK8: =SUM(AJ8-AI8) -> 0 | AL8: =S8+L8+G8 -> 3 | AM8: =Y8+AD8 -> 14 | AN8: 80 | AO8: =(AN8/100)*3000 -> 2400 | AP8: 83 | AQ8: =(AP8/100)*3000 -> 2490 | AR8: 83 | AS8: =(AR8/100)*3000 -> 2490 | AT8: =SUM(AO8+AQ8+AS8) -> 7380 | AU8: =AT7-AT8+AV8 -> 570 | AV8: 2400 | AW8: 0.7 | AX8: =IF(AV8>0,AW8,AX7) -> 0.7
A9: =ELEC!C7 -> 43743 | B9: 194 | C9: 201 | D9: =C8-C9 -> 9 | E9: =D9*8.38 -> 75.42 | F9: 1138 | G9: =F9-F8 -> 3 | H9: 317190 | I9: =SUM(H9-H8) -> 213 | J9: =IF(G9>0,I9/G9,0) -> 71 | K9: =K8 -> 1523 | L9: =K9-K8 -> 0 | M9: =M8 -> 111660 | N9: =M9-M8 -> 0 | O9: =SUM(L9*$J$1) -> 0 | P9: 1342 | Q9: 117015 | R9: =Q9-Q8 -> 181 | S9: =SUM(P9-P8) -> 3 | T9: =SUM(S9*$T$2) -> 0 | U9: =SUM(G9+L9+S9) -> 6 | V9: =R9+N9+I9:I9 -> 394 | W9: =SUM(V9/U9) -> 65.666667 | X9: =X8 -> 2185 | Y9: =X9-X8 -> 0 | Z9: =Z8 -> 123531.8 | AA9: =Z9-Z8 -> 0 | AB9: =SUM(Y9*$AB$2) -> 0 | AC9: 1440 | AD9: =AC9-AC8 -> 14 | AE9: 340253.7 | AF9: =AE9-AE8 -> 638.5 | AG9: =IF(AD9>0,AF9/AD9,0) -> 45.607143 | AH9: =AF9+AA9 -> 638.5 | AI9: =SUM(AH9+V9) -> 1032.5 | AJ9: =-tanks!AW10 -> 1032.5 | AK9: =SUM(AJ9-AI9) -> 0 | AL9: =S9+L9+G9 -> 6 | AM9: =Y9+AD9 -> 14 | AN9: 77 | AO9: =(AN9/100)*3000 -> 2310 | AP9: 77 | AQ9: =(AP9/100)*3000 -> 2310 | AR9: 77 | AS9: =(AR9/100)*3000 -> 2310 | AT9: =SUM(AO9+AQ9+AS9) -> 6930 | AU9: =AT8-AT9+AV9 -> 450 | AX9: =IF(AV9>0,AW9,AX8) -> 0.7
A10: =ELEC!C8 -> 43744 | B10: 186 | C10: 192 | D10: =C9-C10 -> 9 | E10: =D10*8.38 -> 75.42 | F10: 1142 | G10: =F10-F9 -> 4 | H10: 317483 | I10: =SUM(H10-H9) -> 293 | J10: =IF(G10>0,I10/G10,0) -> 73.25 | K10: =K9 -> 1523 | L10: =K10-K9 -> 0 | M10: =M9 -> 111660 | N10: =M10-M9 -> 0 | O10: =SUM(L10*$J$1) -> 0 | P10: 1343 | Q10: 117137 | R10: =Q10-Q9 -> 122 | S10: =SUM(P10-P9) -> 1 | T10: =SUM(S10*$T$2) -> 0 | U10: =SUM(G10+L10+S10) -> 5 | V10: =R10+N10+I10:I10 -> 415 | W10: =SUM(V10/U10) -> 83 | X10: =X9 -> 2185 | Y10: =X10-X9 -> 0 | Z10: =Z9 -> 123531.8 | AA10: =Z10-Z9 -> 0 | AB10: =SUM(Y10*$AB$2) -> 0 | AC10: 1453 | AD10: =AC10-AC9 -> 13 | AE10: 340881.9 | AF10: =AE10-AE9 -> 628.2 | AG10: =IF(AD10>0,AF10/AD10,0) -> 48.323077 | AH10: =AF10+AA10 -> 628.2 | AI10: =SUM(AH10+V10) -> 1043.2 | AJ10: =-tanks!AW11 -> 1043.2 | AK10: =SUM(AJ10-AI10) -> 0 | AL10: =S10+L10+G10 -> 5 | AM10: =Y10+AD10 -> 13 | AN10: 74 | AO10: =(AN10/100)*3000 -> 2220 | AP10: 74 | AQ10: =(AP10/100)*3000 -> 2220 | AR10: 74 | AS10: =(AR10/100)*3000 -> 2220 | AT10: =SUM(AO10+AQ10+AS10) -> 6660 | AU10: =AT9-AT10+AV10 -> 270 | AX10: =IF(AV10>0,AW10,AX9) -> 0.7
A11: =ELEC!C9 -> 43745 | B11: 177 | C11: 184 | D11: =C10-C11 -> 8 | E11: =D11*8.38 -> 67.04 | F11: =F10 -> 1142 | G11: =F11-F10 -> 0 | H11: =H10 -> 317483 | I11: =SUM(H11-H10) -> 0 | J11: =IF(G11>0,I11/G11,0) -> 0 | K11: =K10 -> 1523 | L11: =K11-K10 -> 0 | M11: =M10 -> 111660 | N11: =M11-M10 -> 0 | O11: =SUM(L11*$J$1) -> 0 | P11: 1346 | Q11: 117373 | R11: =Q11-Q10 -> 236 | S11: =SUM(P11-P10) -> 3 | T11: =SUM(S11*$T$2) -> 0 | U11: =SUM(G11+L11+S11) -> 3 | V11: =R11+N11+I11:I11 -> 236 | W11: =SUM(V11/U11) -> 78.666667 | X11: =X10 -> 2185 | Y11: =X11-X10 -> 0 | Z11: =Z10 -> 123531.8 | AA11: =Z11-Z10 -> 0 | AB11: =SUM(Y11*$AB$2) -> 0 | AC11: 1469 | AD11: =AC11-AC10 -> 16 | AE11: 341507.7 | AF11: =AE11-AE10 -> 625.8 | AG11: =IF(AD11>0,AF11/AD11,0) -> 39.1125 | AH11: =AF11+AA11 -> 625.8 | AI11: =SUM(AH11+V11) -> 861.8 | AJ11: =-tanks!AW12 -> 861.8 | AK11: =SUM(AJ11-AI11) -> 0 | AL11: =S11+L11+G11 -> 3 | AM11: =Y11+AD11 -> 16 | AN11: 70 | AO11: =(AN11/100)*3000 -> 2100 | AP11: 70 | AQ11: =(AP11/100)*3000 -> 2100 | AR11: 70 | AS11: =(AR11/100)*3000 -> 2100 | AT11: =SUM(AO11+AQ11+AS11) -> 6300 | AU11: =AT10-AT11+AV11 -> 360 | AX11: =IF(AV11>0,AW11,AX10) -> 0.7
A12: =ELEC!C10 -> 43746 | B12: 169 | C12: 175 | D12: =C11-C12 -> 9 | E12: =D12*8.38 -> 75.42 | F12: 1143 | G12: =F12-F11 -> 1 | H12: 317603 | I12: =SUM(H12-H11) -> 120 | J12: =IF(G12>0,I12/G12,0) -> 120 | K12: =K11 -> 1523 | L12: =K12-K11 -> 0 | M12: =M11 -> 111660 | N12: =M12-M11 -> 0 | O12: =SUM(L12*$J$1) -> 0 | P12: 1348 | Q12: 117536 | R12: =Q12-Q11 -> 163 | S12: =SUM(P12-P11) -> 2 | T12: =SUM(S12*$T$2) -> 0 | U12: =SUM(G12+L12+S12) -> 3 | V12: =R12+N12+I12:I12 -> 283 | W12: =SUM(V12/U12) -> 94.333333 | X12: =X11 -> 2185 | Y12: =X12-X11 -> 0 | Z12: =Z11 -> 123531.8 | AA12: =Z12-Z11 -> 0 | AB12: =SUM(Y12*$AB$2) -> 0 | AC12: 1481 | AD12: =AC12-AC11 -> 12 | AE12: 342032.5 | AF12: =AE12-AE11 -> 524.8 | AG12: =IF(AD12>0,AF12/AD12,0) -> 43.733333 | AH12: =AF12+AA12 -> 524.8 | AI12: =SUM(AH12+V12) -> 807.8 | AJ12: =-tanks!AW13 -> 807.8 | AK12: =SUM(AJ12-AI12) -> 0 | AL12: =S12+L12+G12 -> 3 | AM12: =Y12+AD12 -> 12 | AN12: 68 | AO12: =(AN12/100)*3000 -> 2040 | AP12: 67 | AQ12: =(AP12/100)*3000 -> 2010 | AR12: 67 | AS12: =(AR12/100)*3000 -> 2010 | AT12: =SUM(AO12+AQ12+AS12) -> 6060 | AU12: =AT11-AT12+AV12 -> 240 | AX12: =IF(AV12>0,AW12,AX11) -> 0.7
A13: =ELEC!C11 -> 43747 | B13: 160 | C13: 166 | D13: =C12-C13 -> 9 | E13: =D13*8.38 -> 75.42 | F13: 1145 | G13: =F13-F12 -> 2 | H13: 317736 | I13: =SUM(H13-H12) -> 133 | J13: =IF(G13>0,I13/G13,0) -> 66.5 | K13: 1523 | L13: =K13-K12 -> 0 | M13: =M12 -> 111660 | N13: =M13-M12 -> 0 | O13: =SUM(L13*$J$1) -> 0 | P13: 1350 | Q13: 117720 | R13: =Q13-Q12 -> 184 | S13: =SUM(P13-P12) -> 2 | T13: =SUM(S13*$T$2) -> 0 | U13: =SUM(G13+L13+S13) -> 4 | V13: =R13+N13+I13:I13 -> 317 | W13: =SUM(V13/U13) -> 79.25 | X13: 2185 | Y13: =X13-X12 -> 0 | Z13: 123531.8 | AA13: =Z13-Z12 -> 0 | AB13: =SUM(Y13*$AB$2) -> 0 | AC13: 1494 | AD13: =AC13-AC12 -> 13 | AE13: 342596.2 | AF13: =AE13-AE12 -> 563.7 | AG13: =IF(AD13>0,AF13/AD13,0) -> 43.361538 | AH13: =AF13+AA13 -> 563.7 | AI13: =SUM(AH13+V13) -> 880.7 | AJ13: =-tanks!AW14 -> 880.7 | AK13: =SUM(AJ13-AI13) -> 0 | AL13: =S13+L13+G13 -> 4 | AM13: =Y13+AD13 -> 13 | AN13: 65 | AO13: =(AN13/100)*3000 -> 1950 | AP13: 65 | AQ13: =(AP13/100)*3000 -> 1950 | AR13: 65 | AS13: =(AR13/100)*3000 -> 1950 | AT13: =SUM(AO13+AQ13+AS13) -> 5850 | AU13: =AT12-AT13+AV13 -> 210 | AX13: =IF(AV13>0,AW13,AX12) -> 0.7
A14: =ELEC!C12 -> 43748 | B14: 148 | C14: 154 | D14: =C13-C14 -> 12 | E14: =D14*8.38 -> 100.56 | F14: 1145 | G14: =F14-F13 -> 0 | H14: 317736 | I14: =SUM(H14-H13) -> 0 | J14: =IF(G14>0,I14/G14,0) -> 0 | K14: =K13 -> 1523 | L14: =K14-K13 -> 0 | M14: =M13 -> 111660 | N14: =M14-M13 -> 0 | O14: =SUM(L14*$J$1) -> 0 | P14: 1353 | Q14: 117973 | R14: =Q14-Q13 -> 253 | S14: =SUM(P14-P13) -> 3 | T14: =SUM(S14*$T$2) -> 0 | U14: =SUM(G14+L14+S14) -> 3 | V14: =R14+N14+I14:I14 -> 253 | W14: =SUM(V14/U14) -> 84.333333 | X14: 2185 | Y14: =X14-X13 -> 0 | Z14: 123531.8 | AA14: =Z14-Z13 -> 0 | AB14: =SUM(Y14*$AB$2) -> 0 | AC14: 1507 | AD14: =AC14-AC13 -> 13 | AE14: 343182.3 | AF14: =AE14-AE13 -> 586.1 | AG14: =IF(AD14>0,AF14/AD14,0) -> 45.084615 | AH14: =AF14+AA14 -> 586.1 | AI14: =SUM(AH14+V14) -> 839.1 | AJ14: =-tanks!AW15 -> 839.1 | AK14: =SUM(AJ14-AI14) -> 0 | AL14: =S14+L14+G14 -> 3 | AM14: =Y14+AD14 -> 13 | AN14: 63 | AO14: =(AN14/100)*3000 -> 1890 | AP14: 62 | AQ14: =(AP14/100)*3000 -> 1860 | AR14: 62 | AS14: =(AR14/100)*3000 -> 1860 | AT14: =SUM(AO14+AQ14+AS14) -> 5610 | AU14: =AT13-AT14+AV14 -> 240 | AX14: =IF(AV14>0,AW14,AX13) -> 0.7
A15: =ELEC!C13 -> 43749 | B15: 208 | C15: 214 | D15: =C14-C15 -> -60 | E15: =D15*8.38 -> -502.8 | F15: 1148 | G15: =F15-F14 -> 3 | H15: 317932 | I15: =SUM(H15-H14) -> 196 | J15: =IF(G15>0,I15/G15,0) -> 65.333333 | K15: =K14 -> 1523 | L15: =K15-K14 -> 0 | M15: =M14 -> 111660 | N15: =M15-M14 -> 0 | O15: =SUM(L15*$J$1) -> 0 | P15: 1355 | Q15: 118124 | R15: =Q15-Q14 -> 151 | S15: =SUM(P15-P14) -> 2 | T15: =SUM(S15*$T$2) -> 0 | U15: =SUM(G15+L15+S15) -> 5 | V15: =R15+N15+I15:I15 -> 347 | W15: =SUM(V15/U15) -> 69.4 | X15: =X14 -> 2185 | Y15: =X15-X14 -> 0 | Z15: =Z14 -> 123531.8 | AA15: =Z15-Z14 -> 0 | AB15: =SUM(Y15*$AB$2) -> 0 | AC15: 1517 | AD15: =AC15-AC14 -> 10 | AE15: 343657.2 | AF15: =AE15-AE14 -> 474.9 | AG15: =IF(AD15>0,AF15/AD15,0) -> 47.49 | AH15: =AF15+AA15 -> 474.9 | AI15: =SUM(AH15+V15) -> 821.9 | AJ15: =-tanks!AW16 -> 821.9 | AK15: =SUM(AJ15-AI15) -> 0 | AL15: =S15+L15+G15 -> 5 | AM15: =Y15+AD15 -> 10 | AN15: 83 | AO15: =(AN15/100)*3000 -> 2490 | AP15: 80 | AQ15: =(AP15/100)*3000 -> 2400 | AR15: 80 | AS15: =(AR15/100)*3000 -> 2400 | AT15: =SUM(AO15+AQ15+AS15) -> 7290 | AU15: =AT14-AT15+AV15 -> 720 | AV15: 2400 | AW15: 0.7 | AX15: =IF(AV15>0,AW15,AX14) -> 0.7
A16: =ELEC!C14 -> 43750 | B16: 200 | C16: 206 | D16: =C15-C16 -> 8 | E16: =D16*8.38 -> 67.04 | F16: 1150 | G16: =F16-F15 -> 2 | H16: 318104 | I16: =SUM(H16-H15) -> 172 | J16: =IF(G16>0,I16/G16,0) -> 86 | K16: =K15 -> 1523 | L16: =K16-K15 -> 0 | M16: =M15 -> 111660 | N16: =M16-M15 -> 0 | O16: =SUM(L16*$J$1) -> 0 | P16: 1356 | Q16: 118236 | R16: =Q16-Q15 -> 112 | S16: =SUM(P16-P15) -> 1 | T16: =SUM(S16*$T$2) -> 0 | U16: =SUM(G16+L16+S16) -> 3 | V16: =R16+N16+I16:I16 -> 284 | W16: =SUM(V16/U16) -> 94.666667 | X16: =X15 -> 2185 | Y16: =X16-X15 -> 0 | Z16: =Z15 -> 123531.8 | AA16: =Z16-Z15 -> 0 | AB16: =SUM(Y16*$AB$2) -> 0 | AC16: 1529 | AD16: =AC16-AC15 -> 12 | AE16: 344217.4 | AF16: =AE16-AE15 -> 560.2 | AG16: =IF(AD16>0,AF16/AD16,0) -> 46.683333 | AH16: =AF16+AA16 -> 560.2 | AI16: =SUM(AH16+V16) -> 844.2 | AJ16: =-tanks!AW17 -> 844.2 | AK16: =SUM(AJ16-AI16) -> 0 | AL16: =S16+L16+G16 -> 3 | AM16: =Y16+AD16 -> 12 | AN16: 80 | AO16: =(AN16/100)*3000 -> 2400 | AP16: 79 | AQ16: =(AP16/100)*3000 -> 2370 | AR16: 79 | AS16: =(AR16/100)*3000 -> 2370 | AT16: =SUM(AO16+AQ16+AS16) -> 7140 | AU16: =AT15-AT16+AV16 -> 150 | AX16: =IF(AV16>0,AW16,AX15) -> 0.7
A17: =ELEC!C15 -> 43751 | B17: 192 | C17: 198 | D17: =C16-C17 -> 8 | E17: =D17*8.38 -> 67.04 | F17: =F16 -> 1150 | G17: =F17-F16 -> 0 | H17: =H16 -> 318104 | I17: =SUM(H17-H16) -> 0 | J17: =IF(G17>0,I17/G17,0) -> 0 | K17: =K16 -> 1523 | L17: =K17-K16 -> 0 | M17: =M16 -> 111660 | N17: =M17-M16 -> 0 | O17: =SUM(L17*$J$1) -> 0 | P17: 1360 | Q17: 118540 | R17: =Q17-Q16 -> 304 | S17: =SUM(P17-P16) -> 4 | T17: =SUM(S17*$T$2) -> 0 | U17: =SUM(G17+L17+S17) -> 4 | V17: =R17+N17+I17:I17 -> 304 | X17: =X16 -> 2185 | Y17: =X17-X16 -> 0 | Z17: =Z16 -> 123531.8 | AA17: =Z17-Z16 -> 0 | AB17: =SUM(Y17*$AB$2) -> 0 | AC17: 1542 | AD17: =AC17-AC16 -> 13 | AE17: 344838.7 | AF17: =AE17-AE16 -> 621.3 | AG17: =IF(AD17>0,AF17/AD17,0) -> 47.792308 | AH17: =AF17+AA17 -> 621.3 | AI17: =SUM(AH17+V17) -> 925.3 | AJ17: =-tanks!AW18 -> 925.3 | AK17: =SUM(AJ17-AI17) -> 0 | AL17: =S17+L17+G17 -> 4 | AM17: =Y17+AD17 -> 13 | AN17: 75 | AO17: =(AN17/100)*3000 -> 2250 | AP17: 75 | AQ17: =(AP17/100)*3000 -> 2250 | AR17: 76 | AS17: =(AR17/100)*3000 -> 2280 | AT17: =SUM(AO17+AQ17+AS17) -> 6780 | AU17: =AT16-AT17+AV17 -> 360 | AX17: =IF(AV17>0,AW17,AX16) -> 0.7
A18: =ELEC!C16 -> 43752 | B18: 178 | C18: 184 | D18: =C17-C18 -> 14 | E18: =D18*8.38 -> 117.32 | F18: 1151 | G18: =F18-F17 -> 1 | H18: 318215 | I18: =SUM(H18-H17) -> 111 | J18: =IF(G18>0,I18/G18,0) -> 111 | K18: 1523 | L18: =K18-K17 -> 0 | M18: 111660 | N18: =M18-M17 -> 0 | O18: =SUM(L18*$J$1) -> 0 | P18: 1361 | Q18: 118669 | R18: =Q18-Q17 -> 129 | S18: =SUM(P18-P17) -> 1 | T18: =SUM(S18*$T$2) -> 0 | U18: =SUM(G18+L18+S18) -> 2 | V18: =R18+N18+I18:I18 -> 240 | X18: 2185 | Y18: =X18-X17 -> 0 | Z18: 123531.8 | AA18: =Z18-Z17 -> 0 | AB18: =SUM(Y18*$AB$2) -> 0 | AC18: 1552 | AD18: =AC18-AC17 -> 10 | AE18: 345307 | AF18: =AE18-AE17 -> 468.3 | AG18: =IF(AD18>0,AF18/AD18,0) -> 46.83 | AH18: =AF18+AA18 -> 468.3 | AI18: =SUM(AH18+V18) -> 708.3 | AJ18: =-tanks!AW19 -> 708.3 | AK18: =SUM(AJ18-AI18) -> 0 | AL18: =S18+L18+G18 -> 2 | AM18: =Y18+AD18 -> 10 | AN18: 74 | AO18: =(AN18/100)*3000 -> 2220 | AP18: 74 | AQ18: =(AP18/100)*3000 -> 2220 | AR18: 74 | AS18: =(AR18/100)*3000 -> 2220 | AT18: =SUM(AO18+AQ18+AS18) -> 6660 | AU18: =AT17-AT18+AV18 -> 120 | AX18: =IF(AV18>0,AW18,AX17) -> 0.7
A19: =ELEC!C17 -> 43753 | B19: =B18 -> 178 | C19: =C18 -> 184 | D19: =C18-C19 -> 0 | E19: =D19*8.38 -> 0 | F19: =F18 -> 1151 | G19: =F19-F18 -> 0 | H19: =H18 -> 318215 | I19: =SUM(H19-H18) -> 0 | J19: =IF(G19>0,I19/G19,0) -> 0 | K19: =K18 -> 1523 | L19: =K19-K18 -> 0 | M19: =M18 -> 111660 | N19: =M19-M18 -> 0 | O19: =SUM(L19*$J$1) -> 0 | P19: =P18 -> 1361 | Q19: =Q18 -> 118669 | R19: =Q19-Q18 -> 0 | S19: =SUM(P19-P18) -> 0 | T19: =SUM(S19*$T$2) -> 0 | U19: =SUM(G19+L19+S19) -> 0 | V19: =R19+N19+I19:I19 -> 0 | X19: =X18 -> 2185 | Y19: =X19-X18 -> 0 | Z19: =Z18 -> 123531.8 | AA19: =Z19-Z18 -> 0 | AB19: =SUM(Y19*$AB$2) -> 0 | AC19: =AC18 -> 1552 | AD19: =AC19-AC18 -> 0 | AE19: =AE18 -> 345307 | AF19: =AE19-AE18 -> 0 | AG19: =IF(AD19>0,AF19/AD19,0) -> 0 | AH19: =AF19+AA19 -> 0 | AI19: =SUM(AH19+V19) -> 0 | AJ19: =-tanks!AW20 -> 0 | AK19: =SUM(AJ19-AI19) -> 0 | AL19: =S19+L20+G19 -> 0 | AM19: =Y19+AD19 -> 0 | AN19: =AN18 -> 74 | AO19: =(AN19/100)*3000 -> 2220 | AP19: =AP18 -> 74 | AQ19: =(AP19/100)*3000 -> 2220 | AR19: =AR18 -> 74 | AS19: =(AR19/100)*3000 -> 2220 | AT19: =SUM(AO19+AQ19+AS19) -> 6660 | AU19: =AT18-AT19+AV19 -> 0 | AX19: =IF(AV19>0,AW19,AX18) -> 0.7
A20: =ELEC!C18 -> 43754 | B20: =B19 -> 178 | C20: =C19 -> 184 | D20: =C19-C20 -> 0 | E20: =D20*8.38 -> 0 | F20: =F19 -> 1151 | G20: =F20-F19 -> 0 | H20: =H19 -> 318215 | I20: =SUM(H20-H19) -> 0 | J20: =IF(G20>0,I20/G20,0) -> 0 | K20: =K19 -> 1523 | L20: =K20-K19 -> 0 | M20: =M19 -> 111660 | N20: =M20-M19 -> 0 | O20: =SUM(L20*$J$1) -> 0 | P20: =P19 -> 1361 | Q20: =Q19 -> 118669 | R20: =Q20-Q19 -> 0 | S20: =SUM(P20-P19) -> 0 | T20: =SUM(S20*$T$2) -> 0 | U20: =SUM(G20+L20+S20) -> 0 | V20: =R20+N20+I20:I20 -> 0 | X20: =X19 -> 2185 | Y20: =X20-X19 -> 0 | Z20: =Z19 -> 123531.8 | AA20: =Z20-Z19 -> 0 | AB20: =SUM(Y20*$AB$2) -> 0 | AC20: =AC19 -> 1552 | AD20: =AC20-AC19 -> 0 | AE20: =AE19 -> 345307 | AF20: =AE20-AE19 -> 0 | AG20: =IF(AD20>0,AF20/AD20,0) -> 0 | AH20: =AF20+AA20 -> 0 | AI20: =SUM(AH20+V20) -> 0 | AJ20: =-tanks!AW21 -> 0 | AK20: =SUM(AJ20-AI20) -> 0 | AL20: =S20+L21+G20 -> 0 | AM20: =Y20+AD20 -> 0 | AN20: =AN19 -> 74 | AO20: =(AN20/100)*3000 -> 2220 | AP20: =AP19 -> 74 | AQ20: =(AP20/100)*3000 -> 2220 | AR20: =AR19 -> 74 | AS20: =(AR20/100)*3000 -> 2220 | AT20: =SUM(AO20+AQ20+AS20) -> 6660 | AU20: =AT19-AT20+AV20 -> 0 | AX20: =IF(AV20>0,AW20,AX19) -> 0.7
A21: =ELEC!C19 -> 43755 | B21: =B20 -> 178 | C21: =C20 -> 184 | D21: =C20-C21 -> 0 | E21: =D21*8.38 -> 0 | F21: =F20 -> 1151 | G21: =F21-F20 -> 0 | H21: =H20 -> 318215 | I21: =SUM(H21-H20) -> 0 | J21: =IF(G21>0,I21/G21,0) -> 0 | K21: =K20 -> 1523 | L21: =K21-K20 -> 0 | M21: =M20 -> 111660 | N21: =M21-M20 -> 0 | O21: =SUM(L21*$J$1) -> 0 | P21: =P20 -> 1361 | Q21: =Q20 -> 118669 | R21: =Q21-Q20 -> 0 | S21: =SUM(P21-P20) -> 0 | T21: =SUM(S21*$T$2) -> 0 | U21: =SUM(G21+L21+S21) -> 0 | V21: =R21+N21+I21:I21 -> 0 | X21: =X20 -> 2185 | Y21: =X21-X20 -> 0 | Z21: =Z20 -> 123531.8 | AA21: =Z21-Z20 -> 0 | AB21: =SUM(Y21*$AB$2) -> 0 | AC21: =AC20 -> 1552 | AD21: =AC21-AC20 -> 0 | AE21: =AE20 -> 345307 | AF21: =AE21-AE20 -> 0 | AG21: =IF(AD21>0,AF21/AD21,0) -> 0 | AH21: =AF21+AA21 -> 0 | AI21: =SUM(AH21+V21) -> 0 | AJ21: =-tanks!AW22 -> 0 | AK21: =SUM(AJ21-AI21) -> 0 | AL21: =S21+L21+G21 -> 0 | AM21: =Y21+AD21 -> 0 | AN21: =AN20 -> 74 | AO21: =(AN21/100)*3000 -> 2220 | AP21: =AP20 -> 74 | AQ21: =(AP21/100)*3000 -> 2220 | AR21: =AR20 -> 74 | AS21: =(AR21/100)*3000 -> 2220 | AT21: =SUM(AO21+AQ21+AS21) -> 6660 | AU21: =AT20-AT21+AV21 -> 0 | AX21: =IF(AV21>0,AW21,AX20) -> 0.7
A22: =ELEC!C20 -> 43756 | B22: =B21 -> 178 | C22: =C21 -> 184 | D22: =C21-C22 -> 0 | E22: =D22*8.38 -> 0 | F22: =F21 -> 1151 | G22: =F22-F21 -> 0 | H22: =H21 -> 318215 | I22: =SUM(H22-H21) -> 0 | J22: =IF(G22>0,I22/G22,0) -> 0 | K22: =K21 -> 1523 | L22: =K22-K21 -> 0 | M22: =M21 -> 111660 | N22: =M22-M21 -> 0 | O22: =SUM(L22*$J$1) -> 0 | P22: =P21 -> 1361 | Q22: =Q21 -> 118669 | R22: =Q22-Q21 -> 0 | S22: =SUM(P22-P21) -> 0 | T22: =SUM(S22*$T$2) -> 0 | U22: =SUM(G22+L22+S22) -> 0 | V22: =R22+N22+I22:I22 -> 0 | X22: =X21 -> 2185 | Y22: =X22-X21 -> 0 | Z22: =Z21 -> 123531.8 | AA22: =Z22-Z21 -> 0 | AB22: =SUM(Y22*$AB$2) -> 0 | AC22: =AC21 -> 1552 | AD22: =AC22-AC21 -> 0 | AE22: =AE21 -> 345307 | AF22: =AE22-AE21 -> 0 | AG22: =IF(AD22>0,AF22/AD22,0) -> 0 | AH22: =AF22+AA22 -> 0 | AI22: =SUM(AH22+V22) -> 0 | AJ22: =-tanks!AW23 -> 0 | AK22: =SUM(AJ22-AI22) -> 0 | AL22: =S22+L22+G22 -> 0 | AM22: =Y22+AD22 -> 0 | AN22: =AN21 -> 74 | AO22: =(AN22/100)*3000 -> 2220 | AP22: =AP21 -> 74 | AQ22: =(AP22/100)*3000 -> 2220 | AR22: =AR21 -> 74 | AS22: =(AR22/100)*3000 -> 2220 | AT22: =SUM(AO22+AQ22+AS22) -> 6660 | AU22: =AT21-AT22+AV22 -> 0 | AX22: =IF(AV22>0,AW22,AX21) -> 0.7
A23: =ELEC!C21 -> 43757 | B23: =B22 -> 178 | C23: =C22 -> 184 | D23: =C22-C23 -> 0 | E23: =D23*8.38 -> 0 | F23: =F22 -> 1151 | G23: =F23-F22 -> 0 | H23: =H22 -> 318215 | I23: =SUM(H23-H22) -> 0 | J23: =IF(G23>0,I23/G23,0) -> 0 | K23: =K22 -> 1523 | L23: =K23-K22 -> 0 | M23: =M22 -> 111660 | N23: =M23-M22 -> 0 | O23: =SUM(L23*$J$1) -> 0 | P23: =P22 -> 1361 | Q23: =Q22 -> 118669 | R23: =Q23-Q22 -> 0 | S23: =SUM(P23-P22) -> 0 | T23: =SUM(S23*$T$2) -> 0 | U23: =SUM(G23+L23+S23) -> 0 | V23: =R23+N23+I23:I23 -> 0 | X23: =X22 -> 2185 | Y23: =X23-X22 -> 0 | Z23: =Z22 -> 123531.8 | AA23: =Z23-Z22 -> 0 | AB23: =SUM(Y23*$AB$2) -> 0 | AC23: =AC22 -> 1552 | AD23: =AC23-AC22 -> 0 | AE23: =AE22 -> 345307 | AF23: =AE23-AE22 -> 0 | AG23: =IF(AD23>0,AF23/AD23,0) -> 0 | AH23: =AF23+AA23 -> 0 | AI23: =SUM(AH23+V23) -> 0 | AJ23: =-tanks!AW24 -> 0 | AK23: =SUM(AJ23-AI23) -> 0 | AL23: =S23+L23+G23 -> 0 | AM23: =Y23+AD23 -> 0 | AN23: =AN22 -> 74 | AO23: =(AN23/100)*3000 -> 2220 | AP23: =AP22 -> 74 | AQ23: =(AP23/100)*3000 -> 2220 | AR23: =AR22 -> 74 | AS23: =(AR23/100)*3000 -> 2220 | AT23: =SUM(AO23+AQ23+AS23) -> 6660 | AU23: =AT22-AT23+AV23 -> 0 | AX23: =IF(AV23>0,AW23,AX22) -> 0.7
A24: =ELEC!C22 -> 43758 | B24: =B23 -> 178 | C24: =C23 -> 184 | D24: =C23-C24 -> 0 | E24: =D24*8.38 -> 0 | F24: =F23 -> 1151 | G24: =F24-F23 -> 0 | H24: =H23 -> 318215 | I24: =SUM(H24-H23) -> 0 | J24: =IF(G24>0,I24/G24,0) -> 0 | K24: =K23 -> 1523 | L24: =K24-K23 -> 0 | M24: =M23 -> 111660 | N24: =M24-M23 -> 0 | O24: =SUM(L24*$J$1) -> 0 | P24: =P23 -> 1361 | Q24: =Q23 -> 118669 | R24: =Q24-Q23 -> 0 | S24: =SUM(P24-P23) -> 0 | T24: =SUM(S24*$T$2) -> 0 | U24: =SUM(G24+L24+S24) -> 0 | V24: =R24+N24+I24:I24 -> 0 | X24: =X23 -> 2185 | Y24: =X24-X23 -> 0 | Z24: =Z23 -> 123531.8 | AA24: =Z24-Z23 -> 0 | AB24: =SUM(Y24*$AB$2) -> 0 | AC24: =AC23 -> 1552 | AD24: =AC24-AC23 -> 0 | AE24: =AE23 -> 345307 | AF24: =AE24-AE23 -> 0 | AG24: =IF(AD24>0,AF24/AD24,0) -> 0 | AH24: =AF24+AA24 -> 0 | AI24: =SUM(AH24+V24) -> 0 | AJ24: =-tanks!AW25 -> 0 | AK24: =SUM(AJ24-AI24) -> 0 | AL24: =S24+L24+G24 -> 0 | AM24: =Y24+AD24 -> 0 | AN24: =AN23 -> 74 | AO24: =(AN24/100)*3000 -> 2220 | AP24: =AP23 -> 74 | AQ24: =(AP24/100)*3000 -> 2220 | AR24: =AR23 -> 74 | AS24: =(AR24/100)*3000 -> 2220 | AT24: =SUM(AO24+AQ24+AS24) -> 6660 | AU24: =AT23-AT24+AV24 -> 0 | AX24: =IF(AV24>0,AW24,AX23) -> 0.7
A25: =ELEC!C23 -> 43759 | B25: =B24 -> 178 | C25: =C24 -> 184 | D25: =C24-C25 -> 0 | E25: =D25*8.38 -> 0 | F25: =F24 -> 1151 | G25: =F25-F24 -> 0 | H25: =H24 -> 318215 | I25: =SUM(H25-H24) -> 0 | J25: =IF(G25>0,I25/G25,0) -> 0 | K25: =K24 -> 1523 | L25: =K25-K24 -> 0 | M25: =M24 -> 111660 | N25: =M25-M24 -> 0 | O25: =SUM(L25*$J$1) -> 0 | P25: =P24 -> 1361 | Q25: =Q24 -> 118669 | R25: =Q25-Q24 -> 0 | S25: =SUM(P25-P24) -> 0 | T25: =SUM(S25*$T$2) -> 0 | U25: =SUM(G25+L25+S25) -> 0 | V25: =R25+N25+I25:I25 -> 0 | X25: =X24 -> 2185 | Y25: =X25-X24 -> 0 | Z25: =Z24 -> 123531.8 | AA25: =Z25-Z24 -> 0 | AB25: =SUM(Y25*$AB$2) -> 0 | AC25: =AC24 -> 1552 | AD25: =AC25-AC24 -> 0 | AE25: =AE24 -> 345307 | AF25: =AE25-AE24 -> 0 | AG25: =IF(AD25>0,AF25/AD25,0) -> 0 | AH25: =AF25+AA25 -> 0 | AI25: =SUM(AH25+V25) -> 0 | AJ25: =-tanks!AW26 -> 0 | AK25: =SUM(AJ25-AI25) -> 0 | AL25: =S25+L25+G25 -> 0 | AM25: =Y25+AD25 -> 0 | AN25: =AN24 -> 74 | AO25: =(AN25/100)*3000 -> 2220 | AP25: =AP24 -> 74 | AQ25: =(AP25/100)*3000 -> 2220 | AR25: =AR24 -> 74 | AS25: =(AR25/100)*3000 -> 2220 | AT25: =SUM(AO25+AQ25+AS25) -> 6660 | AU25: =AT24-AT25+AV25 -> 0 | AX25: =IF(AV25>0,AW25,AX24) -> 0.7
A26: =ELEC!C24 -> 43760 | B26: =B25 -> 178 | C26: =C25 -> 184 | D26: =C25-C26 -> 0 | E26: =D26*8.38 -> 0 | F26: =F25 -> 1151 | G26: =F26-F25 -> 0 | H26: =H25 -> 318215 | I26: =SUM(H26-H25) -> 0 | J26: =IF(G26>0,I26/G26,0) -> 0 | K26: =K25 -> 1523 | L26: =K26-K25 -> 0 | M26: =M25 -> 111660 | N26: =M26-M25 -> 0 | O26: =SUM(L26*$J$1) -> 0 | P26: =P25 -> 1361 | Q26: =Q25 -> 118669 | R26: =Q26-Q25 -> 0 | S26: =SUM(P26-P25) -> 0 | T26: =SUM(S26*$T$2) -> 0 | U26: =SUM(G26+L26+S26) -> 0 | V26: =R26+N26+I26:I26 -> 0 | X26: =X25 -> 2185 | Y26: =X26-X25 -> 0 | Z26: =Z25 -> 123531.8 | AA26: =Z26-Z25 -> 0 | AB26: =SUM(Y26*$AB$2) -> 0 | AC26: =AC25 -> 1552 | AD26: =AC26-AC25 -> 0 | AE26: =AE25 -> 345307 | AF26: =AE26-AE25 -> 0 | AG26: =IF(AD26>0,AF26/AD26,0) -> 0 | AH26: =AF26+AA26 -> 0 | AI26: =SUM(AH26+V26) -> 0 | AJ26: =-tanks!AW27 -> 0 | AK26: =SUM(AJ26-AI26) -> 0 | AL26: =S26+L26+G26 -> 0 | AM26: =Y26+AD26 -> 0 | AN26: =AN25 -> 74 | AO26: =(AN26/100)*3000 -> 2220 | AP26: =AP25 -> 74 | AQ26: =(AP26/100)*3000 -> 2220 | AR26: =AR25 -> 74 | AS26: =(AR26/100)*3000 -> 2220 | AT26: =SUM(AO26+AQ26+AS26) -> 6660 | AU26: =AT25-AT26+AV26 -> 0 | AX26: =IF(AV26>0,AW26,AX25) -> 0.7
A27: =ELEC!C25 -> 43761 | B27: =B26 -> 178 | C27: =C26 -> 184 | D27: =C26-C27 -> 0 | E27: =D27*8.38 -> 0 | F27: =F26 -> 1151 | G27: =F27-F26 -> 0 | H27: =H26 -> 318215 | I27: =SUM(H27-H26) -> 0 | J27: =IF(G27>0,I27/G27,0) -> 0 | K27: =K26 -> 1523 | L27: =K27-K26 -> 0 | M27: =M26 -> 111660 | N27: =M27-M26 -> 0 | O27: =SUM(L27*$J$1) -> 0 | P27: =P26 -> 1361 | Q27: =Q26 -> 118669 | R27: =Q27-Q26 -> 0 | S27: =SUM(P27-P26) -> 0 | T27: =SUM(S27*$T$2) -> 0 | U27: =SUM(G27+L27+S27) -> 0 | V27: =R27+N27+I27:I27 -> 0 | X27: =X26 -> 2185 | Y27: =X27-X26 -> 0 | Z27: =Z26 -> 123531.8 | AA27: =Z27-Z26 -> 0 | AB27: =SUM(Y27*$AB$2) -> 0 | AC27: =AC26 -> 1552 | AD27: =AC27-AC26 -> 0 | AE27: =AE26 -> 345307 | AF27: =AE27-AE26 -> 0 | AG27: =IF(AD27>0,AF27/AD27,0) -> 0 | AH27: =AF27+AA27 -> 0 | AI27: =SUM(AH27+V27) -> 0 | AJ27: =-tanks!AW28 -> 0 | AK27: =SUM(AJ27-AI27) -> 0 | AL27: =S27+L27+G27 -> 0 | AM27: =Y27+AD27 -> 0 | AN27: =AN26 -> 74 | AO27: =(AN27/100)*3000 -> 2220 | AP27: =AP26 -> 74 | AQ27: =(AP27/100)*3000 -> 2220 | AR27: =AR26 -> 74 | AS27: =(AR27/100)*3000 -> 2220 | AT27: =SUM(AO27+AQ27+AS27) -> 6660 | AU27: =AT26-AT27+AV27 -> 0 | AX27: =IF(AV27>0,AW27,AX26) -> 0.7
A28: =ELEC!C26 -> 43762 | B28: =B27 -> 178 | C28: =C27 -> 184 | D28: =C27-C28 -> 0 | E28: =D28*8.38 -> 0 | F28: =F27 -> 1151 | G28: =F28-F27 -> 0 | H28: =H27 -> 318215 | I28: =SUM(H28-H27) -> 0 | J28: =IF(G28>0,I28/G28,0) -> 0 | K28: =K27 -> 1523 | L28: =K28-K27 -> 0 | M28: =M27 -> 111660 | N28: =M28-M27 -> 0 | O28: =SUM(L28*$J$1) -> 0 | P28: =P27 -> 1361 | Q28: =Q27 -> 118669 | R28: =Q28-Q27 -> 0 | S28: =SUM(P28-P27) -> 0 | T28: =SUM(S28*$T$2) -> 0 | U28: =SUM(G28+L28+S28) -> 0 | V28: =R28+N28+I28:I28 -> 0 | X28: =X27 -> 2185 | Y28: =X28-X27 -> 0 | Z28: =Z27 -> 123531.8 | AA28: =Z28-Z27 -> 0 | AB28: =SUM(Y28*$AB$2) -> 0 | AC28: =AC27 -> 1552 | AD28: =AC28-AC27 -> 0 | AE28: =AE27 -> 345307 | AF28: =AE28-AE27 -> 0 | AG28: =IF(AD28>0,AF28/AD28,0) -> 0 | AH28: =AF28+AA28 -> 0 | AI28: =SUM(AH28+V28) -> 0 | AJ28: =-tanks!AW29 -> 0 | AK28: =SUM(AJ28-AI28) -> 0 | AL28: =S28+L28+G28 -> 0 | AM28: =Y28+AD28 -> 0 | AN28: =AN27 -> 74 | AO28: =(AN28/100)*3000 -> 2220 | AP28: =AP27 -> 74 | AQ28: =(AP28/100)*3000 -> 2220 | AR28: =AR27 -> 74 | AS28: =(AR28/100)*3000 -> 2220 | AT28: =SUM(AO28+AQ28+AS28) -> 6660 | AU28: =AT27-AT28+AV28 -> 0 | AX28: =IF(AV28>0,AW28,AX27) -> 0.7
A29: =ELEC!C27 -> 43763 | B29: =B28 -> 178 | C29: =C28 -> 184 | D29: =C28-C29 -> 0 | E29: =D29*8.38 -> 0 | F29: =F28 -> 1151 | G29: =F29-F28 -> 0 | H29: =H28 -> 318215 | I29: =SUM(H29-H28) -> 0 | J29: =IF(G29>0,I29/G29,0) -> 0 | K29: =K28 -> 1523 | L29: =K29-K28 -> 0 | M29: =M28 -> 111660 | N29: =M29-M28 -> 0 | O29: =SUM(L29*$J$1) -> 0 | P29: =P28 -> 1361 | Q29: =Q28 -> 118669 | R29: =Q29-Q28 -> 0 | S29: =SUM(P29-P28) -> 0 | T29: =SUM(S29*$T$2) -> 0 | U29: =SUM(G29+L29+S29) -> 0 | V29: =R29+N29+I29:I29 -> 0 | X29: =X28 -> 2185 | Y29: =X29-X28 -> 0 | Z29: =Z28 -> 123531.8 | AA29: =Z29-Z28 -> 0 | AB29: =SUM(Y29*$AB$2) -> 0 | AC29: =AC28 -> 1552 | AD29: =AC29-AC28 -> 0 | AE29: =AE28 -> 345307 | AF29: =AE29-AE28 -> 0 | AG29: =IF(AD29>0,AF29/AD29,0) -> 0 | AH29: =AF29+AA29 -> 0 | AI29: =SUM(AH29+V29) -> 0 | AJ29: =-tanks!AW30 -> 0 | AK29: =SUM(AJ29-AI29) -> 0 | AL29: =S29+L29+G29 -> 0 | AM29: =Y29+AD29 -> 0 | AN29: =AN28 -> 74 | AO29: =(AN29/100)*3000 -> 2220 | AP29: =AP28 -> 74 | AQ29: =(AP29/100)*3000 -> 2220 | AR29: =AR28 -> 74 | AS29: =(AR29/100)*3000 -> 2220 | AT29: =SUM(AO29+AQ29+AS29) -> 6660 | AU29: =AT28-AT29+AV29 -> 0 | AX29: =IF(AV29>0,AW29,AX28) -> 0.7
A30: =ELEC!C28 -> 43764 | B30: =B29 -> 178 | C30: =C29 -> 184 | D30: =C29-C30 -> 0 | E30: =D30*8.38 -> 0 | F30: =F29 -> 1151 | G30: =F30-F29 -> 0 | H30: =H29 -> 318215 | I30: =SUM(H30-H29) -> 0 | J30: =IF(G30>0,I30/G30,0) -> 0 | K30: =K29 -> 1523 | L30: =K30-K29 -> 0 | M30: =M29 -> 111660 | N30: =M30-M29 -> 0 | O30: =SUM(L30*$J$1) -> 0 | P30: =P29 -> 1361 | Q30: =Q29 -> 118669 | R30: =Q30-Q29 -> 0 | S30: =SUM(P30-P29) -> 0 | T30: =SUM(S30*$T$2) -> 0 | U30: =SUM(G30+L30+S30) -> 0 | V30: =R30+N30+I30:I30 -> 0 | X30: =X29 -> 2185 | Y30: =X30-X29 -> 0 | Z30: =Z29 -> 123531.8 | AA30: =Z30-Z29 -> 0 | AB30: =SUM(Y30*$AB$2) -> 0 | AC30: =AC29 -> 1552 | AD30: =AC30-AC29 -> 0 | AE30: =AE29 -> 345307 | AF30: =AE30-AE29 -> 0 | AG30: =IF(AD30>0,AF30/AD30,0) -> 0 | AH30: =AF30+AA30 -> 0 | AI30: =SUM(AH30+V30) -> 0 | AJ30: =-tanks!AW31 -> 0 | AK30: =SUM(AJ30-AI30) -> 0 | AL30: =S30+L30+G30 -> 0 | AM30: =Y30+AD30 -> 0 | AN30: =AN29 -> 74 | AO30: =(AN30/100)*3000 -> 2220 | AP30: =AP29 -> 74 | AQ30: =(AP30/100)*3000 -> 2220 | AR30: =AR29 -> 74 | AS30: =(AR30/100)*3000 -> 2220 | AT30: =SUM(AO30+AQ30+AS30) -> 6660 | AU30: =AT29-AT30+AV30 -> 0 | AX30: =IF(AV30>0,AW30,AX29) -> 0.7
A31: =ELEC!C29 -> 43765 | B31: =B30 -> 178 | C31: =C30 -> 184 | D31: =C30-C31 -> 0 | E31: =D31*8.38 -> 0 | F31: =F30 -> 1151 | G31: =F31-F30 -> 0 | H31: =H30 -> 318215 | I31: =SUM(H31-H30) -> 0 | J31: =IF(G31>0,I31/G31,0) -> 0 | K31: =K30 -> 1523 | L31: =K31-K30 -> 0 | M31: =M30 -> 111660 | N31: =M31-M30 -> 0 | O31: =SUM(L31*$J$1) -> 0 | P31: =P30 -> 1361 | Q31: =Q30 -> 118669 | R31: =Q31-Q30 -> 0 | S31: =SUM(P31-P30) -> 0 | T31: =SUM(S31*$T$2) -> 0 | U31: =SUM(G31+L31+S31) -> 0 | V31: =R31+N31+I31:I31 -> 0 | X31: =X30 -> 2185 | Y31: =X31-X30 -> 0 | Z31: =Z30 -> 123531.8 | AA31: =Z31-Z30 -> 0 | AB31: =SUM(Y31*$AB$2) -> 0 | AC31: =AC30 -> 1552 | AD31: =AC31-AC30 -> 0 | AE31: =AE30 -> 345307 | AF31: =AE31-AE30 -> 0 | AG31: =IF(AD31>0,AF31/AD31,0) -> 0 | AH31: =AF31+AA31 -> 0 | AI31: =SUM(AH31+V31) -> 0 | AJ31: =-tanks!AW32 -> 0 | AK31: =SUM(AJ31-AI31) -> 0 | AL31: =S31+L31+G31 -> 0 | AM31: =Y31+AD31 -> 0 | AN31: =AN30 -> 74 | AO31: =(AN31/100)*3000 -> 2220 | AP31: =AP30 -> 74 | AQ31: =(AP31/100)*3000 -> 2220 | AR31: =AR30 -> 74 | AS31: =(AR31/100)*3000 -> 2220 | AT31: =SUM(AO31+AQ31+AS31) -> 6660 | AU31: =AT30-AT31+AV31 -> 0 | AX31: =IF(AV31>0,AW31,AX30) -> 0.7
A32: =ELEC!C30 -> 43766 | B32: =B31 -> 178 | C32: =C31 -> 184 | D32: =C31-C32 -> 0 | E32: =D32*8.38 -> 0 | F32: =F31 -> 1151 | G32: =F32-F31 -> 0 | H32: =H31 -> 318215 | I32: =SUM(H32-H31) -> 0 | J32: =IF(G32>0,I32/G32,0) -> 0 | K32: =K31 -> 1523 | L32: =K32-K31 -> 0 | M32: =M31 -> 111660 | N32: =M32-M31 -> 0 | O32: =SUM(L32*$J$1) -> 0 | P32: =P31 -> 1361 | Q32: =Q31 -> 118669 | R32: =Q32-Q31 -> 0 | S32: =SUM(P32-P31) -> 0 | T32: =SUM(S32*$T$2) -> 0 | U32: =SUM(G32+L32+S32) -> 0 | V32: =R32+N32+I32:I32 -> 0 | X32: =X31 -> 2185 | Y32: =X32-X31 -> 0 | Z32: =Z31 -> 123531.8 | AA32: =Z32-Z31 -> 0 | AB32: =SUM(Y32*$AB$2) -> 0 | AC32: =AC31 -> 1552 | AD32: =AC32-AC31 -> 0 | AE32: =AE31 -> 345307 | AF32: =AE32-AE31 -> 0 | AG32: =IF(AD32>0,AF32/AD32,0) -> 0 | AH32: =AF32+AA32 -> 0 | AI32: =SUM(AH32+V32) -> 0 | AJ32: =-tanks!AW33 -> 0 | AK32: =SUM(AJ32-AI32) -> 0 | AL32: =S32+L32+G32 -> 0 | AM32: =Y32+AD32 -> 0 | AN32: =AN31 -> 74 | AO32: =(AN32/100)*3000 -> 2220 | AP32: =AP31 -> 74 | AQ32: =(AP32/100)*3000 -> 2220 | AR32: =AR31 -> 74 | AS32: =(AR32/100)*3000 -> 2220 | AT32: =SUM(AO32+AQ32+AS32) -> 6660 | AU32: =AT31-AT32+AV32 -> 0 | AX32: =IF(AV32>0,AW32,AX31) -> 0.7
... A35: =ELEC!C33 -> 43769 | B35: =B34 -> 178 | C35: =C34 -> 184 | D35: =C34-C35 -> 0 | E35: =D35*8.38 -> 0 | F35: =F34 -> 1151 | G35: =F35-F34 -> 0 | H35: =H34 -> 318215 | I35: =SUM(H35-H34) -> 0 | J35: =IF(G35>0,I35/G35,0) -> 0 | K35: =K34 -> 1523 | L35: =K35-K34 -> 0 | M35: =M34 -> 111660 | N35: =M35-M34 -> 0 | O35: =SUM(L35*$J$1) -> 0 | P35: =P34 -> 1361 | Q35: =Q34 -> 118669 | R35: =Q35-Q34 -> 0 | S35: =SUM(P35-P34) -> 0 | T35: =SUM(S35*$T$2) -> 0 | U35: =SUM(G35+L35+S35) -> 0 | V35: =R35+N35+I35:I35 -> 0 | X35: =X34 -> 2185 | Y35: =X35-X34 -> 0 | Z35: =Z34 -> 123531.8 | AA35: =Z35-Z34 -> 0 | AB35: =SUM(Y35*$AB$2) -> 0 | AC35: =AC34 -> 1552 | AD35: =AC35-AC34 -> 0 | AE35: =AE34 -> 345307 | AF35: =AE35-AE34 -> 0 | AG35: =IF(AD35>0,AF35/AD35,0) -> 0 | AH35: =AF35+AA35 -> 0 | AI35: =SUM(AH35+V35) -> 0 | AJ35: =-tanks!AW36 -> 0 | AK35: =SUM(AJ35-AI35) -> 0 | AL35: =S35+L35+G35 -> 0 | AM35: =Y35+AD35 -> 0 | AN35: =AN34 -> 74 | AO35: =(AN35/100)*3000 -> 2220 | AP35: =AP34 -> 74 | AQ35: =(AP35/100)*3000 -> 2220 | AR35: =AR34 -> 74 | AS35: =(AR35/100)*3000 -> 2220 | AT35: =SUM(AO35+AQ35+AS35) -> 6660 | AU35: =AT34-AT35+AV35 -> 0 | AX35: =IF(AV35>0,AW35,AX34) -> 0.7
J36: =SUM(J5:J34)/(COUNT(J5:J34)-COUNTIF(J5:J34,0)) -> 76.791667 | AE36: . | AR36: Nb Delivery | AS36: =COUNT(AW5:AW35) -> 3 | AU36: =SUM(AU5:AU35) -> 4410 | AV36: =SUM(AV5:AV35) -> 4800 | AW36: =SUM(AW5:AW35)/AS36 -> 0.46666667
AH37: =AF37+AA37 -> 0 | AI37: =SUM(AI5:AI35) -> 12151.6
AH38: =AF38+AA38 -> 0 | AU38: =AU36*0.51 -> 2249.1 | AV38: =AV36/0.51 -> 9411.7647 | AW38: =SUM(AW5:AW35)/AS36 -> 0.46666667
AV39: =AV36*0.51 -> 2448

Sheet WATER
D1: =SUM(G21:G35) -> 8672190 | AR1: Entrance | AT1: Tank 1 | AV1: Tank 2
AR2: Level | AW2: Quantity CM3 | AZ2: Var
A3: Date | B3: Truck | C3: Truck M3/day | D3: N0. Trucks | F3: REQ. # of trucks | G3: City | H3: City/day | I3: Total water delivery | K3: SW | L3: Cosum SW/day | M3: RO Guest/ Liter | O3: RO K&L/ Liter | Q3: TOTAL RO Production | R3: RO 1 RH | S3: RO 2 RH | T3: RO water counter | U3: RO Cons m3 | V3: Steam Boiler | W3: Steam Boiler/day | X3: Softener Guest | Y3: Guest Sotf/day | Z3: Softener K&L | AA3: K&L Soft/Day | AB3: Fire Tank Level | AC3: Fire Tank Counter | AE3: Laundry Hot Water Counter | AF3: Hot Water Cons/day | AG3: Laundry Cold Water Counter | AH3: Cold Water Cons/day | AI3: Laundry Water Total Cons | AJ3: K&L Sotf/day | AK3: Guest / day | AL3: K&L /day | AM3: Avg Outside Temp | AN3: Banquet Activity | AR3: Date | AT3: MainI | AV3: Kitchen and Laundry | AX3: Guest | AY3: Main Tank | AZ3: Kitchen and Laundry | BA3: Guest | BB3: Kitchen and Laundry | BC3: Main | BD3: Guest | BE3: Total VAR | BF3: Hotel Consumption
E4: 1.66 | AN4: Ball R | AO4: Meeting | AP4: outlet | AT4: 180 | AV4: 220 | AX4: 580 | AY4: =SUM(AT4) -> 180 | AZ4: =SUM(AV4) -> 220 | BA4: =SUM(AX4) -> 580
A5: =ELEC!C2 -> 43738 | B5: =[1]WATER!B33 -> 103210 | C5: =[1]WATER!C33 -> 213 | D5: =[1]WATER!D33 -> 7.8888889 | E5: =[1]WATER!E33 -> 250 | F5: =[1]WATER!F33 -> 8 | G5: =[1]WATER!G33 -> 576665 | H5: =[1]WATER!H33 -> 197 | I5: =[1]WATER!I33 -> 410 | ... AD5: =[1]WATER!AD33 -> 0 | AJ5: =[1]WATER!AE33 -> 111 | AK5: =[1]WATER!AF33 -> 107 | AL5: =[1]WATER!AG33 -> 109 | AM5: =[1]WATER!AH33 -> 26.5 | AN5: =[1]WATER!AI33 -> 400 | AO5: =[1]WATER!AJ33 -> 0 | AP5: =[1]WATER!AK33 -> 570 | AQ5: =[1]WATER!AL33 -> 0 | ... BG5: =[1]WATER!BB33 -> 77.7
A6: =ELEC!C3 -> 43739 | B6: 103342 | C6: =B6-B5 -> 132 | D6: =C6/27 -> 4.8888889 | E6: =SUM((C6*$E$4)+(7500/'EDl log'!$A$38)) -> 461.05548 | F6: 5 | G6: 576665 | H6: =G6-G5 -> 0 | I6: =C6+H6 -> 132 | J6: =IF(I6>0,E6/I6,0) -> 3.4928446 | K6: ='Swimming Pool quality check '!H6 -> 5910 | L6: =K6-K5 -> 3 | M6: =M5 -> 457.44 | N6: =SUM(M6-M5) -> 0 | O6: =O5 -> 529.52 | P6: =SUM(O6-O5) -> 0 | Q6: =P6+N6 -> 0 | T6: 3767 | U6: =SUM(T6-T5) -> 11 | V6: 189 | W6: =+V6-V5 -> 2 | X6: 133600 | Y6: =SUM(X6-X5) -> 100 | Z6: 86182 | AA6: =Z6-Z5 -> 48 | AB6: =AB5 -> 252 | AC6: =AC5 -> 575 | AD6: 0 | AJ6: =+Z6-Z5 -> 48 | AK6: =SUM(Y6-L6) -> 97 | AL6: =SUM(AJ6-W6) -> 46 | AM6: ='General information '!D6 -> 27 | AN6: ='General information '!H6 -> 230 | AP6: ='General information '!J6 -> 492 | AR6: =A6 -> 43739 | AS6: =AS5 -> 0.9 | AT6: 70 | AU6: =AU5 -> 1.1 | AV6: 83 | AW6: 2.9 | AX6: 110 | AY6: =AS6*AT6 -> 63 | AZ6: =AU6*AV6 -> 91.3 | BA6: =AW6*AX6 -> 319 | BB6: =AY6-AY5 -> -46.8 | BC6: =AZ6-AZ5 -> -40.7 | BD6: =BA6-BA5 -> 14.5 | BE6: =SUM(BB6:BD6) -> -73 | BF6: =SUM(I6-BE6) -> 205 | BG6: =SUM(I6-BF6) -> -73
A7: =ELEC!C4 -> 43740 | B7: 103474 | C7: =B7-B6 -> 132 | D7: =C7/27 -> 4.8888889 | E7: =SUM((C7*$E$4)+(7500/'EDl log'!$A$38)) -> 461.05548 | F7: 5 | G7: 576665 | H7: =G7-G6 -> 0 | I7: =C7+H7 -> 132 | J7: =IF(I7>0,E7/I7,0) -> 3.4928446 | K7: ='Swimming Pool quality check '!H7 -> 5913 | L7: =K7-K6 -> 3 | M7: =M6 -> 457.44 | N7: =SUM(M7-M6) -> 0 | O7: =O6 -> 529.52 | P7: =SUM(O7-O6) -> 0 | Q7: =P7+N7 -> 0 | T7: 3777 | U7: =SUM(T7-T6) -> 10 | V7: 191 | W7: =+V7-V6 -> 2 | X7: 133625 | Y7: =SUM(X7-X6) -> 25 | Z7: 86272 | AA7: =Z7-Z6 -> 90 | AB7: 260 | AC7: 643 | AD7: =AC7-AC6 -> 68 | AJ7: =+Z7-Z6 -> 90 | AK7: =SUM(Y7-L7) -> 22 | AL7: =SUM(AJ7-W7) -> 88 | AM7: ='General information '!D7 -> 26.5 | AN7: ='General information '!H7 -> 180 | AP7: ='General information '!J7 -> 636 | AR7: =A7 -> 43740 | AS7: =AS6 -> 0.9 | AT7: 79 | AU7: =AU6 -> 1.1 | AV7: 82 | AW7: 2.9 | AX7: 91 | AY7: =AS7*AT7 -> 71.1 | AZ7: =AU7*AV7 -> 90.2 | BA7: =AW7*AX7 -> 263.9 | BB7: =AY7-AY6 -> 8.1 | BC7: =AZ7-AZ6 -> -1.1 | BD7: =BA7-BA6 -> -55.1 | BE7: =SUM(BB7:BD7) -> -48.1 | BF7: =SUM(I7-BE7) -> 180.1 | BG7: =SUM(I7-BF7) -> -48.1
A8: =ELEC!C5 -> 43741 | B8: 103659 | C8: =B8-B7 -> 185 | D8: =C8/27 -> 6.8518519 | E8: =SUM((C8*$E$4)+(7500/'EDl log'!$A$38)) -> 549.03548 | F8: 7 | G8: =G7 -> 576665 | H8: =G8-G7 -> 0 | I8: =C8+H8 -> 185 | J8: =IF(I8>0,E8/I8,0) -> 2.9677594 | K8: ='Swimming Pool quality check '!H8 -> 5916 | L8: =K8-K7 -> 3 | M8: =M7 -> 457.44 | N8: =SUM(M8-M7) -> 0 | O8: =O7 -> 529.52 | P8: =SUM(O8-O7) -> 0 | Q8: =P8+N8 -> 0 | T8: 3789 | U8: =SUM(T8-T7) -> 12 | V8: 193 | W8: =+V8-V7 -> 2 | X8: 133702 | Y8: =SUM(X8-X7) -> 77 | Z8: 86374 | AA8: =Z8-Z7 -> 102 | AB8: =AB7 -> 260 | AC8: =AC7 -> 643 | AD8: =AC8-AC7 -> 0 | AJ8: =+Z8-Z7 -> 102 | AK8: =SUM(Y8-L8) -> 74 | AL8: =SUM(AJ8-W8) -> 100 | AM8: ='General information '!D8 -> 26 | AN8: ='General information '!H8 -> 32 | AP8: ='General information '!J8 -> 1043 | AR8: =A8 -> 43741 | AS8: =AS7 -> 0.9 | AT8: 57 | AU8: 1.1 | AV8: 87 | AW8: 2.9 | AX8: 88 | AY8: =AS8*AT8 -> 51.3 | AZ8: =AU8*AV8 -> 95.7 | BA8: =AW8*AX8 -> 255.2 | BB8: =AY8-AY7 -> -19.8 | BC8: =AZ8-AZ7 -> 5.5 | BD8: =BA8-BA7 -> -8.7 | BE8: =SUM(BB8:BD8) -> -23 | BF8: =SUM(I8-BE8) -> 208 | BG8: =SUM(I8-BF8) -> -23
A9: =ELEC!C6 -> 43742 | B9: 103792 | C9: =B9-B8 -> 133 | D9: =C9/27 -> 4.9259259 | E9: =SUM((C9*$E$4)+(7500/'EDl log'!$A$38)) -> 462.71548 | F9: 5 | G9: 576838 | H9: =G9-G8 -> 173 | I9: =C9+H9 -> 306 | J9: =IF(I9>0,E9/I9,0) -> 1.5121421 | K9: ='Swimming Pool quality check '!H9 -> 5916 | L9: =K9-K8 -> 0 | M9: =M8 -> 457.44 | N9: =SUM(M9-M8) -> 0 | O9: =O8 -> 529.52 | P9: =SUM(O9-O8) -> 0 | Q9: =P9+N9 -> 0 | T9: 3799 | U9: =SUM(T9-T8) -> 10 | V9: 208 | W9: =+V9-V8 -> 15 | X9: 133838 | Y9: =SUM(X9-X8) -> 136 | Z9: 86508 | AA9: =Z9-Z8 -> 134 | AB9: =AB8 -> 260 | AC9: 643 | AD9: =AC9-AC8 -> 0 | AJ9: =+Z9-Z8 -> 134 | AK9: =SUM(Y9-L9) -> 136 | AL9: =SUM(AJ9-W9) -> 119 | AM9: ='General information '!D9 -> 25.5 | AN9: ='General information '!H9 -> 491 | AP9: ='General information '!J9 -> 761 | AR9: =A9 -> 43742 | AS9: =AS8 -> 0.9 | AT9: 0 | AU9: =AU8 -> 1.1 | AV9: 95 | AW9: 2.9 | AX9: 106 | AY9: =AS9*AT9 -> 0 | AZ9: =AU9*AV9 -> 104.5 | BA9: =AW9*AX9 -> 307.4 | BB9: =AY9-AY8 -> -51.3 | BC9: =AZ9-AZ8 -> 8.8 | BD9: =BA9-BA8 -> 52.2 | BE9: =SUM(BB9:BD9) -> 9.7 | BF9: =SUM(I9-BE9) -> 296.3 | BG9: =SUM(I9-BF9) -> 9.7
A10: =ELEC!C7 -> 43743 | B10: 104004 | C10: =B10-B9 -> 212 | D10: =C10/27 -> 7.8518519 | E10: =SUM((C10*$E$4)+(7500/'EDl log'!$A$38)) -> 593.85548 | F10: 8 | G10: 576838 | H10: =G10-G9 -> 0 | I10: =C10+H10 -> 212 | J10: =IF(I10>0,E10/I10,0) -> 2.8012051 | K10: ='Swimming Pool quality check '!H10 -> 5926 | L10: =K10-K9 -> 10 | M10: =M9 -> 457.44 | N10: =SUM(M10-M9) -> 0 | O10: =O9 -> 529.52 | P10: =SUM(O10-O9) -> 0 | Q10: =P10+N10 -> 0 | T10: 3811 | U10: =SUM(T10-T9) -> 12 | V10: 210 | W10: =+V10-V9 -> 2 | X10: 133861 | Y10: =SUM(X10-X9) -> 23 | Z10: 86605 | AA10: =Z10-Z9 -> 97 | AB10: =AB9 -> 260 | AC10: =AC9 -> 643 | AD10: =AC10-AC9 -> 0 | AE10: 0.16 | AF10: 0 | AG10: 1.56 | AH10: 0 | AI10: =AF10+AH10 -> 0 | AJ10: =+Z10-Z9 -> 97 | AK10: =SUM(Y10-L10) -> 13 | AL10: =SUM(AJ10-W10) -> 95 | AM10: ='General information '!D10 -> 26 | AN10: ='General information '!H10 -> 140 | AP10: ='General information '!J10 -> 963 | AR10: =A10 -> 43743 | AS10: =AS9 -> 0.9 | AT10: 30 | AU10: =AU9 -> 1.1 | AV10: 90 | AW10: 2.9 | AX10: 70 | AY10: =AS10*AT10 -> 27 | AZ10: =AU10*AV10 -> 99 | BA10: =AW10*AX10 -> 203 | BB10: =AY10-AY9 -> 27 | BC10: =AZ10-AZ9 -> -5.5 | BD10: =BA10-BA9 -> -104.4 | BE10: =SUM(BB10:BD10) -> -82.9 | BF10: =SUM(I10-BE10) -> 294.9 | BG10: =SUM(I10-BF10) -> -82.9
A11: =ELEC!C8 -> 43744 | B11: 104137 | C11: =B11-B10 -> 133 | D11: =C11/27 -> 4.9259259 | E11: =SUM((C11*$E$4)+(7500/'EDl log'!$A$38)) -> 462.71548 | F11: 5 | G11: 577030 | H11: =G11-G10 -> 192 | I11: =C11+H11 -> 325 | J11: =IF(I11>0,E11/I11,0) -> 1.42374 | K11: ='Swimming Pool quality check '!H11 -> 5929 | L11: =K11-K10 -> 3 | M11: =M10 -> 457.44 | N11: =SUM(M11-M10) -> 0 | O11: =O10 -> 529.52 | P11: =SUM(O11-O10) -> 0 | Q11: =SUM(P11+N11) -> 0 | T11: 3824 | U11: =SUM(T11-T10) -> 13 | V11: 213 | W11: =+V11-V10 -> 3 | X11: 133949 | Y11: =SUM(X11-X10) -> 88 | Z11: 86704 | AA11: =Z11-Z10 -> 99 | AB11: =AB10 -> 260 | AC11: =AC10 -> 643 | AD11: =AC11-AC10 -> 0 | AE11: 0.18 | AF11: =AE11-AE10 -> 0.02 | AG11: 1.56 | AH11: =AG11-AG10 -> 0 | AI11: =AF11+AH11 -> 0.02 | AJ11: =+Z11-Z10 -> 99 | AK11: =SUM(Y11-L11) -> 85 | AL11: =SUM(AJ11-W11) -> 96 | AM11: ='General information '!D11 -> 26 | AN11: ='General information '!H11 -> 16 | AP11: ='General information '!J11 -> 564 | AR11: =A11 -> 43744 | AS11: =AS10 -> 0.9 | AT11: 73 | AU11: =AU10 -> 1.1 | AV11: 97 | AW11: 2.9 | AX11: 66 | AY11: =AS11*AT11 -> 65.7 | AZ11: =AU11*AV11 -> 106.7 | BA11: =AW11*AX11 -> 191.4 | BB11: =AY11-AY10 -> 38.7 | BC11: =AZ11-AZ10 -> 7.7 | BD11: =BA11-BA10 -> -11.6 | BE11: =SUM(BB11:BD11) -> 34.8 | BF11: =SUM(I11-BE11) -> 290.2 | BG11: =SUM(I11-BF11) -> 34.8
A12: =ELEC!C9 -> 43745 | B12: 104349 | C12: =B12-B11 -> 212 | D12: =C12/27 -> 7.8518519 | E12: =SUM((C12*$E$4)+(7500/'EDl log'!$A$38)) -> 593.85548 | F12: 8 | G12: =G11 -> 577030 | H12: =G12-G11 -> 0 | I12: =C12+H12 -> 212 | J12: =IF(I12>0,E12/I12,0) -> 2.8012051 | K12: ='Swimming Pool quality check '!H12 -> 5933 | L12: =K12-K11 -> 4 | M12: =M11 -> 457.44 | N12: =SUM(M12-M11) -> 0 | O12: =O11 -> 529.52 | P12: =SUM(O12-O11) -> 0 | Q12: =SUM(P12+N12) -> 0 | T12: 3834 | U12: =SUM(T12-T11) -> 10 | V12: 216 | W12: =+V12-V11 -> 3 | X12: 134065 | Y12: =SUM(X12-X11) -> 116 | Z12: 86738 | AA12: =Z12-Z11 -> 34 | AB12: =AB11 -> 260 | AC12: =AC11 -> 643 | AD12: =AC12-AC11 -> 0 | AE12: 0.22 | AF12: =AE12-AE11 -> 0.04 | AG12: 1.57 | AH12: =AG12-AG11 -> 0.01 | AI12: =AF12+AH12 -> 0.05 | AJ12: =+Z12-Z11 -> 34 | AK12: =SUM(Y12-L12) -> 112 | AL12: =SUM(AJ12-W12) -> 31 | AM12: ='General information '!D12 -> 26.5 | AN12: ='General information '!H12 -> 12 | AP12: ='General information '!J12 -> 425 | AR12: =A12 -> 43745 | AS12: =AS11 -> 0.9 | AT12: 80 | AU12: =AU11 -> 1.1 | AV12: 57 | AW12: 2.9 | AX12: 75 | AY12: =AS12*AT12 -> 72 | AZ12: =AU12*AV12 -> 62.7 | BA12: =AW12*AX12 -> 217.5 | BB12: =AY12-AY11 -> 6.3 | BC12: =AZ12-AZ11 -> -44 | BD12: =BA12-BA11 -> 26.1 | BE12: =SUM(BB12:BD12) -> -11.6 | BF12: =SUM(I12-BE12) -> 223.6 | BG12: =SUM(I12-BF12) -> -11.6
A13: =ELEC!C10 -> 43746 | B13: 104535 | C13: =B13-B12 -> 186 | D13: =C13/27 -> 6.8888889 | E13: =SUM((C13*$E$4)+(7500/'EDl log'!$A$38)) -> 550.69548 | F13: 7 | G13: 577199 | H13: =G13-G12 -> 169 | I13: =C13+H13 -> 355 | J13: =IF(I13>0,E13/I13,0) -> 1.5512549 | K13: ='Swimming Pool quality check '!H13 -> 5936 | L13: =K13-K12 -> 3 | M13: =M12 -> 457.44 | N13: =SUM(M13-M12) -> 0 | O13: =O12 -> 529.52 | P13: =SUM(O13-O12) -> 0 | Q13: =SUM(P13+N13) -> 0 | T13: 3846 | U13: =SUM(T13-T12) -> 12 | V13: 217 | W13: =+V13-V12 -> 1 | X13: 134162 | Y13: =SUM(X13-X12) -> 97 | Z13: 86884 | AA13: =Z13-Z12 -> 146 | AB13: =AB12 -> 260 | AC13: =AC12 -> 643 | AD13: =AC13-AC12 -> 0 | AE13: 0.39 | AF13: =AE13-AE12 -> 0.17 | AG13: 1.58 | AH13: =AG13-AG12 -> 0.01 | AI13: =AF13+AH13 -> 0.18 | AJ13: =+Z13-Z12 -> 146 | AK13: =SUM(Y13-L13) -> 94 | AL13: =SUM(AJ13-W13) -> 145 | AM13: ='General information '!D13 -> 26 | AN13: ='General information '!J13 -> 407 | AP13: ='General information '!J13 -> 407 | AR13: =A13 -> 43746 | AS13: =AS12 -> 0.9 | AT13: 100 | AU13: =AU12 -> 1.1 | AV13: 100 | AW13: 2.9 | AX13: 80 | AY13: =AS13*AT13 -> 90 | AZ13: =AU13*AV13 -> 110 | BA13: =AW13*AX13 -> 232 | BB13: =AY13-AY12 -> 18 | BC13: =AZ13-AZ12 -> 47.3 | BD13: =BA13-BA12 -> 14.5 | BE13: =SUM(BB13:BD13) -> 79.8 | BF13: =SUM(I13-BE13) -> 275.2 | BG13: =SUM(I13-BF13) -> 79.8
A14: =ELEC!C11 -> 43747 | B14: 104668 | C14: =B14-B13 -> 133 | D14: =C14/27 -> 4.9259259 | E14: =SUM((C14*$E$4)+(7500/'EDl log'!$A$38)) -> 462.71548 | F14: 5 | G14: 577211 | H14: =G14-G13 -> 12 | I14: =C14+H14 -> 145 | J14: =IF(I14>0,E14/I14,0) -> 3.1911413 | K14: ='Swimming Pool quality check '!H14 -> 5939 | L14: =K14-K13 -> 3 | M14: =M13 -> 457.44 | N14: =SUM(M14-M13) -> 0 | O14: =O13 -> 529.52 | P14: =SUM(O14-O13) -> 0 | Q14: =SUM(P14+N14) -> 0 | T14: 3861 | U14: =SUM(T14-T13) -> 15 | V14: 221 | W14: =+V14-V13 -> 4 | X14: 134224 | Y14: =SUM(X14-X13) -> 62 | Z14: 87003 | AA14: =Z14-Z13 -> 119 | AB14: =AB13 -> 260 | AC14: =AC13 -> 643 | AD14: =AC14-AC13 -> 0 | AE14: =AE13 -> 0.39 | AF14: =AE14-AE13 -> 0 | AG14: 1.92 | AH14: =AG14-AG13 -> 0.34 | AI14: =AF14+AH14 -> 0.34 | AJ14: =+Z14-Z13 -> 119 | AK14: =SUM(Y14-L14) -> 59 | AL14: =SUM(AJ14-W14) -> 115 | AM14: ='General information '!D14 -> 26 | AN14: ='General information '!H14 -> 71 | AP14: ='General information '!J14 -> 543 | AR14: =A14 -> 43747 | AS14: =AS13 -> 0.9 | AT14: 3 | AU14: =AU13 -> 1.1 | AV14: 106 | AW14: 2.9 | AX14: 73 | AY14: =AS14*AT14 -> 2.7 | AZ14: =AU14*AV14 -> 116.6 | BA14: =AW14*AX14 -> 211.7 | BB14: =AY14-AY13 -> -87.3 | BC14: =AZ14-AZ13 -> 6.6 | BD14: =BA14-BA13 -> -20.3 | BE14: =SUM(BB14:BD14) -> -101 | BF14: =SUM(I14-BE14) -> 246 | BG14: =SUM(I14-BF14) -> -101
A15: =ELEC!C12 -> 43748 | B15: 104854 | C15: =B15-B14 -> 186 | D15: =C15/27 -> 6.8888889 | E15: =SUM((C15*$E$4)+(7500/'EDl log'!$A$38)) -> 550.69548 | F15: 7 | G15: 577382 | H15: =G15-G14 -> 171 | I15: =C15+H15 -> 357 | J15: =IF(I15>0,E15/I15,0) -> 1.5425644 | K15: ='Swimming Pool quality check '!H15 -> 5942 | L15: =K15-K14 -> 3 | M15: =M14 -> 457.44 | N15: =SUM(M15-M14) -> 0 | O15: =O14 -> 529.52 | P15: =SUM(O15-O14) -> 0 | Q15: =SUM(P15+N15) -> 0 | T15: 3878 | U15: =SUM(T15-T14) -> 17 | V15: 224 | W15: =+V15-V14 -> 3 | X15: 134331 | Y15: =SUM(X15-X14) -> 107 | Z15: 87137 | AA15: =Z15-Z14 -> 134 | AB15: =AB14 -> 260 | AC15: =AC14 -> 643 | AD15: =AC15-AC14 -> 0 | AE15: 0 | AF15: =AE15-AE14 -> -0.39 | AG15: 12.58 | AH15: =AG15-AG14 -> 10.66 | AI15: =AF15+AH15 -> 10.27 | AJ15: =+Z15-Z14 -> 134 | AK15: =SUM(Y15-L15) -> 104 | AL15: =SUM(AJ15-W15) -> 131 | AM15: ='General information '!D15 -> 25 | AN15: ='General information '!H15 -> 345 | AP15: ='General information '!J15 -> 571 | AR15: =A15 -> 43748 | AS15: =AS14 -> 0.9 | AT15: 77 | AU15: =AU14 -> 1.1 | AV15: 117 | AW15: 2.9 | AX15: 66 | AY15: =AS15*AT15 -> 69.3 | AZ15: =AU15*AV15 -> 128.7 | BA15: =AW15*AX15 -> 191.4 | BB15: =AY15-AY14 -> 66.6 | BC15: =AZ15-AZ14 -> 12.1 | BD15: =BA15-BA14 -> -20.3 | BE15: =SUM(BB15:BD15) -> 58.4 | BF15: =SUM(I15-BE15) -> 298.6 | BG15: =SUM(I15-BF15) -> 58.4
A16: =ELEC!C13 -> 43749 | B16: 104986 | C16: =B16-B15 -> 132 | D16: =C16/27 -> 4.8888889 | E16: =SUM((C16*$E$4)+(7500/'EDl log'!$A$38)) -> 461.05548 | F16: 5 | G16: =G15 -> 577382 | H16: =G16-G15 -> 0 | I16: =C16+H16 -> 132 | J16: =IF(I16>0,E16/I16,0) -> 3.4928446 | K16: ='Swimming Pool quality check '!H16 -> 5945 | L16: =K16-K15 -> 3 | M16: =M15 -> 457.44 | N16: =SUM(M16-M15) -> 0 | O16: =O15 -> 529.52 | P16: =SUM(O16-O15) -> 0 | Q16: =SUM(P16+N16) -> 0 | T16: 3892 | U16: =SUM(T16-T15) -> 14 | V16: 227 | W16: =+V16-V15 -> 3 | X16: 134582 | Y16: =SUM(X16-X15) -> 251 | Z16: 87240 | AA16: =Z16-Z15 -> 103 | AB16: =AB15 -> 260 | AC16: =AC15 -> 643 | AD16: =AC16-AC15 -> 0 | AE16: 0 | AF16: =AE16-AE15 -> 0 | AG16: 39.64 | AH16: =AG16-AG15 -> 27.06 | AI16: =AF16+AH16 -> 27.06 | AJ16: =+Z16-Z15 -> 103 | AK16: =SUM(Y16-L16) -> 248 | AL16: =SUM(AJ16-W16) -> 100 | AM16: ='General information '!D16 -> 26 | AN16: ='General information '!H16 -> 0 | AP16: ='General information '!J16 -> 708 | AR16: =A16 -> 43749 | AS16: =AS15 -> 0.9 | AT16: 5 | AU16: =AU15 -> 1.1 | AV16: 143 | AW16: 2.9 | AX16: 102 | AY16: =AS16*AT16 -> 4.5 | AZ16: =AU16*AV16 -> 157.3 | BA16: =AW16*AX16 -> 295.8 | BB16: =AY16-AY15 -> -64.8 | BC16: =AZ16-AZ15 -> 28.6 | BD16: =BA16-BA15 -> 104.4 | BE16: =SUM(BB16:BD16) -> 68.2 | BF16: =SUM(I16-BE16) -> 63.8 | BG16: =SUM(I16-BF16) -> 68.2
A17: =ELEC!C14 -> 43750 | B17: 104986 | C17: =B17-B16 -> 0 | D17: =C17/27 -> 0 | E17: =SUM((C17*$E$4)+(7500/'EDl log'!$A$38)) -> 241.93548 | F17: 0 | G17: 578036 | H17: =G17-G16 -> 654 | I17: =C17+H17 -> 654 | J17: =IF(I17>0,E17/I17,0) -> 0.36993193 | K17: ='Swimming Pool quality check '!H17 -> 5949 | L17: =K17-K16 -> 4 | M17: =M16 -> 457.44 | N17: =SUM(M17-M16) -> 0 | O17: =O16 -> 529.52 | P17: =SUM(O17-O16) -> 0 | Q17: =SUM(P17+N17) -> 0 | T17: 3903 | U17: =SUM(T17-T16) -> 11 | V17: 237 | W17: =+V17-V16 -> 10 | X17: 134662 | Y17: =SUM(X17-X16) -> 80 | Z17: 87291 | AA17: =Z17-Z16 -> 51 | AB17: =AB16 -> 260 | AC17: =AC16 -> 643 | AD17: =AC17-AC16 -> 0 | AE17: =AE16 -> 0 | AF17: =AE17-AE16 -> 0 | AG17: 74.38 | AH17: =AG17-AG16 -> 34.74 | AI17: =AF17+AH17 -> 34.74 | AJ17: =+Z17-Z16 -> 51 | AK17: =SUM(Y17-L17) -> 76 | AL17: =SUM(AJ17-W17) -> 41 | AM17: ='General information '!D17 -> 25.5 | AN17: ='General information '!H17 -> 0 | AP17: ='General information '!J17 -> 668 | AR17: =A17 -> 43750 | AS17: =AS16 -> 0.9 | AT17: 0 | AU17: =AU16 -> 1.1 | AV17: 110 | AW17: 2.9 | AX17: 94 | AY17: =AS17*AT17 -> 0 | AZ17: =AU17*AV17 -> 121 | BA17: =AW17*AX17 -> 272.6 | BB17: =AY17-AY16 -> -4.5 | BC17: =AZ17-AZ16 -> -36.3 | BD17: =BA17-BA16 -> -23.2 | BE17: =SUM(BB17:BD17) -> -64 | BF17: =SUM(I17-BE17) -> 718 | BG17: =SUM(I17-BF17) -> -64
A18: =ELEC!C15 -> 43751 | B18: 105119 | C18: =B18-B17 -> 133 | D18: =C18/27 -> 4.9259259 | E18: =SUM((C18*$E$4)+(7500/'EDl log'!$A$38)) -> 462.71548 | F18: 5 | G18: =G17 -> 578036 | H18: =G18-G17 -> 0 | I18: =C18+H18 -> 133 | J18: =IF(I18>0,E18/I18,0) -> 3.4790638 | K18: ='Swimming Pool quality check '!H18 -> 5952 | L18: =K18-K17 -> 3 | M18: =M17 -> 457.44 | N18: =SUM(M18-M17) -> 0 | O18: =O17 -> 529.52 | P18: =SUM(O18-O17) -> 0 | Q18: =SUM(P18+N18) -> 0 | T18: 3916 | U18: =SUM(T18-T17) -> 13 | V18: 239 | W18: =+V18-V17 -> 2 | X18: 134681 | Y18: =SUM(X18-X17) -> 19 | Z18: 87367 | AA18: =Z18-Z17 -> 76 | AB18: =AB17 -> 260 | AC18: =AC17 -> 643 | AD18: =AC18-AC17 -> 0 | AE18: =AE17 -> 0 | AF18: =AE18-AE17 -> 0 | AG18: 111.8 | AH18: =AG18-AG17 -> 37.42 | AI18: =AF18+AH18 -> 37.42 | AJ18: =+Z18-Z17 -> 76 | AK18: =SUM(Y18-L18) -> 16 | AL18: =SUM(AJ18-W18) -> 74 | AM18: ='General information '!D18 -> 27 | AN18: ='General information '!H18 -> 0 | AP18: ='General information '!J18 -> 551 | AR18: =A18 -> 43751 | AS18: =AS17 -> 0.9 | AT18: 25 | AU18: =AU17 -> 1.1 | AV18: 103 | AW18: 2.9 | AX18: 72 | AY18: =AS18*AT18 -> 22.5 | AZ18: =AU18*AV18 -> 113.3 | BA18: =AW18*AX18 -> 208.8 | BB18: =AY18-AY17 -> 22.5 | BC18: =AZ18-AZ17 -> -7.7 | BD18: =BA18-BA17 -> -63.8 | BE18: =SUM(BB18:BD18) -> -49 | BF18: =SUM(I18-BE18) -> 182 | BG18: =SUM(I18-BF18) -> -49
A19: =ELEC!C16 -> 43752 | B19: 105252 | C19: =B19-B18 -> 133 | D19: =C19/27 -> 4.9259259 | E19: =SUM((C19*$E$4)+(7500/'EDl log'!$A$38)) -> 462.71548 | F19: 5 | G19: 578146 | H19: =G19-G18 -> 110 | I19: =C19+H19 -> 243 | J19: =IF(I19>0,E19/I19,0) -> 1.9041789 | K19: ='Swimming Pool quality check '!H19 -> 5955 | L19: =K19-K18 -> 3 | M19: =M18 -> 457.44 | N19: =SUM(M19-M18) -> 0 | O19: =O18 -> 529.52 | P19: =SUM(O19-O18) -> 0 | Q19: =SUM(P19+N19) -> 0 | T19: 3926 | U19: =SUM(T19-T18) -> 10 | V19: 242 | W19: =+V19-V18 -> 3 | X19: 134778 | Y19: =SUM(X19-X18) -> 97 | Z19: 87453 | AA19: =Z19-Z18 -> 86 | AB19: =AB18 -> 260 | AC19: =AC18 -> 643 | AD19: =AC19-AC18 -> 0 | AE19: =AE18 -> 0 | AF19: =AE19-AE18 -> 0 | AG19: =AG18 -> 111.8 | AH19: =AG19-AG18 -> 0 | AI19: =AF19+AH19 -> 0 | AJ19: =+Z19-Z18 -> 86 | AK19: =SUM(Y19-L19) -> 94 | AL19: =SUM(AJ19-W19) -> 83 | AM19: ='General information '!D19 -> 27 | AN19: ='General information '!H19 -> 4 | AP19: ='General information '!J19 -> 510 | AR19: =A19 -> 43752 | AS19: =AS18 -> 0.9 | AT19: 23 | AU19: =AU18 -> 1.1 | AV19: 110 | AW19: 2.9 | AX19: 77 | AY19: =AS19*AT19 -> 20.7 | AZ19: =AU19*AV19 -> 121 | BA19: =AW19*AX19 -> 223.3 | BB19: =AY19-AY18 -> -1.8 | BC19: =AZ19-AZ18 -> 7.7 | BD19: =BA19-BA18 -> 14.5 | BE19: =SUM(BB19:BD19) -> 20.4 | BF19: =SUM(I19-BE19) -> 222.6 | BG19: =SUM(I19-BF19) -> 20.4
A20: =ELEC!C17 -> 43753 | B20: =B19 -> 105252 | C20: =B20-B19 -> 0 | D20: =C20/27 -> 0 | E20: =SUM((C20*$E$4)+(7500/'EDl log'!$A$38)) -> 241.93548 | G20: =G19 -> 578146 | H20: =G20-G19 -> 0 | I20: =C20+H20 -> 0 | J20: =IF(I20>0,E20/I20,0) -> 0 | K20: ='Swimming Pool quality check '!H20 -> 5955 | L20: =K20-K19 -> 0 | M20: =M19 -> 457.44 | N20: =SUM(M20-M19) -> 0 | O20: =O19 -> 529.52 | P20: =SUM(O20-O19) -> 0 | Q20: =SUM(P20+N20) -> 0 | T20: =T19 -> 3926 | U20: =SUM(T20-T19) -> 0 | V20: =V19 -> 242 | W20: =+V20-V19 -> 0 | X20: =X19 -> 134778 | Y20: =SUM(X20-X19) -> 0 | Z20: =Z19 -> 87453 | AA20: =Z20-Z19 -> 0 | AB20: =AB19 -> 260 | AC20: =AC19 -> 643 | AD20: =AC20-AC19 -> 0 | AE20: =AE19 -> 0 | AF20: =AE20-AE19 -> 0 | AG20: =AG19 -> 111.8 | AH20: =AG20-AG19 -> 0 | AI20: =AF20+AH20 -> 0 | AJ20: =+Z20-Z19 -> 0 | AK20: =SUM(Y20-L20) -> 0 | AL20: =SUM(AJ20-W20) -> 0 | AM20: ='General information '!D20 -> 0 | AN20: ='General information '!H20 -> 0 | AP20: ='General information '!J20 -> 0 | AR20: =A20 -> 43753 | AS20: =AS19 -> 0.9 | AT20: =AT19 -> 23 | AU20: =AU19 -> 1.1 | AV20: =AV19 -> 110 | AW20: 2.9 | AX20: =AX19 -> 77 | AY20: =AS20*AT20 -> 20.7 | AZ20: =AU20*AV20 -> 121 | BA20: =AW20*AX20 -> 223.3 | BB20: =AY20-AY19 -> 0 | BC20: =AZ20-AZ19 -> 0 | BD20: =BA20-BA19 -> 0 | BE20: =SUM(BB20:BD20) -> 0 | BF20: =SUM(I20-BE20) -> 0 | BG20: =SUM(I20-BF20) -> 0
A21: =ELEC!C18 -> 43754 | B21: =B20 -> 105252 | C21: =B21-B20 -> 0 | D21: =C21/27 -> 0 | E21: =SUM((C21*$E$4)+(7500/'EDl log'!$A$38)) -> 241.93548 | G21: =G20 -> 578146 | H21: =G21-G20 -> 0 | I21: =C21+H21 -> 0 | J21: =IF(I21>0,E21/I21,0) -> 0 | K21: ='Swimming Pool quality check '!H21 -> 5955 | L21: =K21-K20 -> 0 | M21: =M20 -> 457.44 | N21: =SUM(M21-M20) -> 0 | O21: =O20 -> 529.52 | P21: =SUM(O21-O20) -> 0 | Q21: =SUM(P21+N21) -> 0 | T21: =T20 -> 3926 | U21: =SUM(T21-T20) -> 0 | V21: =V20 -> 242 | W21: =+V21-V20 -> 0 | X21: =X20 -> 134778 | Y21: =SUM(X21-X20) -> 0 | Z21: =Z20 -> 87453 | AA21: =Z21-Z20 -> 0 | AB21: =AB20 -> 260 | AC21: =AC20 -> 643 | AD21: =AC21-AC20 -> 0 | AE21: =AE20 -> 0 | AF21: =AE21-AE20 -> 0 | AG21: =AG20 -> 111.8 | AH21: =AG21-AG20 -> 0 | AI21: =AF21+AH21 -> 0 | AJ21: =+Z21-Z20 -> 0 | AK21: =SUM(Y21-L21) -> 0 | AL21: =SUM(AJ21-W21) -> 0 | AM21: ='General information '!D21 -> 0 | AN21: ='General information '!H21 -> 0 | AP21: ='General information '!J21 -> 0 | AR21: =A21 -> 43754 | AS21: =AS20 -> 0.9 | AT21: =AT20 -> 23 | AU21: =AU20 -> 1.1 | AV21: =AV20 -> 110 | AW21: 2.9 | AX21: =AX20 -> 77 | AY21: =AS21*AT21 -> 20.7 | AZ21: =AU21*AV21 -> 121 | BA21: =AW21*AX21 -> 223.3 | BB21: =AY21-AY20 -> 0 | BC21: =AZ21-AZ20 -> 0 | BD21: =BA21-BA20 -> 0 | BE21: =SUM(BB21:BD21) -> 0 | BF21: =SUM(I21-BE21) -> 0 | BG21: =SUM(I21-BF21) -> 0
A22: =ELEC!C19 -> 43755 | B22: =B21 -> 105252 | C22: =B22-B21 -> 0 | D22: =C22/27 -> 0 | E22: =SUM((C22*$E$4)+(7500/'EDl log'!$A$38)) -> 241.93548 | G22: =G21 -> 578146 | H22: =G22-G21 -> 0 | I22: =C22+H22 -> 0 | J22: =IF(I22>0,E22/I22,0) -> 0 | K22: ='Swimming Pool quality check '!H22 -> 5955 | L22: =K22-K21 -> 0 | M22: =M21 -> 457.44 | N22: =SUM(M22-M21) -> 0 | O22: =O21 -> 529.52 | P22: =SUM(O22-O21) -> 0 | Q22: =SUM(P22+N22) -> 0 | T22: =T21 -> 3926 | U22: =SUM(T22-T21) -> 0 | V22: =V21 -> 242 | W22: =+V22-V21 -> 0 | X22: =X21 -> 134778 | Y22: =SUM(X22-X21) -> 0 | Z22: =Z21 -> 87453 | AA22: =Z22-Z21 -> 0 | AB22: =AB21 -> 260 | AC22: =AC21 -> 643 | AD22: =AC22-AC21 -> 0 | AE22: =AE21 -> 0 | AF22: =AE22-AE21 -> 0 | AG22: =AG21 -> 111.8 | AH22: =AG22-AG21 -> 0 | AI22: =AF22+AH22 -> 0 | AJ22: =+Z22-Z21 -> 0 | AK22: =SUM(Y22-L22) -> 0 | AL22: =SUM(AJ22-W22) -> 0 | AM22: ='General information '!D22 -> 0 | AN22: ='General information '!H22 -> 0 | AP22: ='General information '!J22 -> 0 | AR22: =A22 -> 43755 | AS22: =AS21 -> 0.9 | AT22: =AT21 -> 23 | AU22: =AU21 -> 1.1 | AV22: =AV21 -> 110 | AW22: 2.9 | AX22: =AX21 -> 77 | AY22: =AS22*AT22 -> 20.7 | AZ22: =AU22*AV22 -> 121 | BA22: =AW22*AX22 -> 223.3 | BB22: =AY22-AY21 -> 0 | BC22: =AZ22-AZ21 -> 0 | BD22: =BA22-BA21 -> 0 | BE22: =SUM(BB22:BD22) -> 0 | BF22: =SUM(I22-BE22) -> 0 | BG22: =SUM(I22-BF22) -> 0
A23: =ELEC!C20 -> 43756 | B23: =B22 -> 105252 | C23: =B23-B22 -> 0 | D23: =C23/27 -> 0 | E23: =SUM((C23*$E$4)+(7500/'EDl log'!$A$38)) -> 241.93548 | G23: =G22 -> 578146 | H23: =G23-G22 -> 0 | I23: =C23+H23 -> 0 | J23: =IF(I23>0,E23/I23,0) -> 0 | K23: ='Swimming Pool quality check '!H23 -> 5955 | L23: =K23-K22 -> 0 | M23: =M22 -> 457.44 | N23: =SUM(M23-M22) -> 0 | O23: =O22 -> 529.52 | P23: =SUM(O23-O22) -> 0 | Q23: =SUM(P23+N23) -> 0 | T23: =T22 -> 3926 | U23: =SUM(T23-T22) -> 0 | V23: =V22 -> 242 | W23: =+V23-V22 -> 0 | X23: =X22 -> 134778 | Y23: =SUM(X23-X22) -> 0 | Z23: =Z22 -> 87453 | AA23: =Z23-Z22 -> 0 | AB23: =AB22 -> 260 | AC23: =AC22 -> 643 | AD23: =AC23-AC22 -> 0 | AE23: =AE22 -> 0 | AF23: =AE23-AE22 -> 0 | AG23: =AG22 -> 111.8 | AH23: =AG23-AG22 -> 0 | AI23: =AF23+AH23 -> 0 | AJ23: =+Z23-Z22 -> 0 | AK23: =SUM(Y23-L23) -> 0 | AL23: =SUM(AJ23-W23) -> 0 | AM23: ='General information '!D23 -> 0 | AN23: ='General information '!H23 -> 0 | AP23: ='General information '!J23 -> 0 | AR23: =A23 -> 43756 | AS23: =AS22 -> 0.9 | AT23: =AT22 -> 23 | AU23: =AU22 -> 1.1 | AV23: =AV22 -> 110 | AW23: 2.9 | AX23: =AX22 -> 77 | AY23: =AS23*AT23 -> 20.7 | AZ23: =AU23*AV23 -> 121 | BA23: =AW23*AX23 -> 223.3 | BB23: =AY23-AY22 -> 0 | BC23: =AZ23-AZ22 -> 0 | BD23: =BA23-BA22 -> 0 | BE23: =SUM(BB23:BD23) -> 0 | BF23: =SUM(I23-BE23) -> 0 | BG23: =SUM(I23-BF23) -> 0
A24: =ELEC!C21 -> 43757 | B24: =B23 -> 105252 | C24: =B24-B23 -> 0 | D24: =C24/27 -> 0 | E24: =SUM((C24*$E$4)+(7500/'EDl log'!$A$38)) -> 241.93548 | G24: =G23 -> 578146 | H24: =G24-G23 -> 0 | I24: =C24+H24 -> 0 | J24: =IF(I24>0,E24/I24,0) -> 0 | K24: ='Swimming Pool quality check '!H24 -> 5955 | L24: =K24-K23 -> 0 | M24: =M23 -> 457.44 | N24: =SUM(M24-M23) -> 0 | O24: =O23 -> 529.52 | P24: =SUM(O24-O23) -> 0 | Q24: =SUM(P24+N24) -> 0 | T24: =T23 -> 3926 | U24: =SUM(T24-T23) -> 0 | V24: =V23 -> 242 | W24: =+V24-V23 -> 0 | X24: =X23 -> 134778 | Y24: =SUM(X24-X23) -> 0 | Z24: =Z23 -> 87453 | AA24: =Z24-Z23 -> 0 | AB24: =AB23 -> 260 | AC24: =AC23 -> 643 | AD24: =AC24-AC23 -> 0 | AE24: =AE23 -> 0 | AF24: =AE24-AE23 -> 0 | AG24: =AG23 -> 111.8 | AH24: =AG24-AG23 -> 0 | AI24: =AF24+AH24 -> 0 | AJ24: =+Z24-Z23 -> 0 | AK24: =SUM(Y24-L24) -> 0 | AL24: =SUM(AJ24-W24) -> 0 | AM24: ='General information '!D24 -> 0 | AN24: ='General information '!H24 -> 0 | AP24: ='General information '!J24 -> 0 | AR24: =A24 -> 43757 | AS24: =AS23 -> 0.9 | AT24: =AT23 -> 23 | AU24: =AU23 -> 1.1 | AV24: =AV23 -> 110 | AW24: 2.9 | AX24: =AX23 -> 77 | AY24: =AS24*AT24 -> 20.7 | AZ24: =AU24*AV24 -> 121 | BA24: =AW24*AX24 -> 223.3 | BB24: =AY24-AY23 -> 0 | BC24: =AZ24-AZ23 -> 0 | BD24: =BA24-BA23 -> 0 | BE24: =SUM(BB24:BD24) -> 0 | BF24: =SUM(I24-BE24) -> 0 | BG24: =SUM(I24-BF24) -> 0
A25: =ELEC!C22 -> 43758 | B25: =B24 -> 105252 | C25: =B25-B24 -> 0 | D25: =C25/27 -> 0 | E25: =SUM((C25*$E$4)+(7500/'EDl log'!$A$38)) -> 241.93548 | G25: =G24 -> 578146 | H25: =G25-G24 -> 0 | I25: =C25+H25 -> 0 | J25: =IF(I25>0,E25/I25,0) -> 0 | K25: ='Swimming Pool quality check '!H25 -> 5955 | L25: =K25-K24 -> 0 | M25: =M24 -> 457.44 | N25: =SUM(M25-M24) -> 0 | O25: =O24 -> 529.52 | P25: =SUM(O25-O24) -> 0 | Q25: =SUM(P25+N25) -> 0 | T25: =T24 -> 3926 | U25: =SUM(T25-T24) -> 0 | V25: =V24 -> 242 | W25: =+V25-V24 -> 0 | X25: =X24 -> 134778 | Y25: =SUM(X25-X24) -> 0 | Z25: =Z24 -> 87453 | AA25: =Z25-Z24 -> 0 | AB25: =AB24 -> 260 | AC25: =AC24 -> 643 | AD25: =AC25-AC24 -> 0 | AE25: =AE24 -> 0 | AF25: =AE25-AE24 -> 0 | AG25: =AG24 -> 111.8 | AH25: =AG25-AG24 -> 0 | AI25: =AF25+AH25 -> 0 | AJ25: =+Z25-Z24 -> 0 | AK25: =SUM(Y25-L25) -> 0 | AL25: =SUM(AJ25-W25) -> 0 | AM25: ='General information '!D25 -> 0 | AN25: ='General information '!H25 -> 0 | AP25: ='General information '!J25 -> 0 | AR25: =A25 -> 43758 | AS25: =AS24 -> 0.9 | AT25: =AT24 -> 23 | AU25: =AU24 -> 1.1 | AV25: =AV24 -> 110 | AW25: 2.9 | AX25: =AX24 -> 77 | AY25: =AS25*AT25 -> 20.7 | AZ25: =AU25*AV25 -> 121 | BA25: =AW25*AX25 -> 223.3 | BB25: =AY25-AY24 -> 0 | BC25: =AZ25-AZ24 -> 0 | BD25: =BA25-BA24 -> 0 | BE25: =SUM(BB25:BD25) -> 0 | BF25: =SUM(I25-BE25) -> 0 | BG25: =SUM(I25-BF25) -> 0
A26: =ELEC!C23 -> 43759 | B26: =B25 -> 105252 | C26: =B26-B25 -> 0 | D26: =C26/27 -> 0 | E26: =SUM((C26*$E$4)+(7500/'EDl log'!$A$38)) -> 241.93548 | G26: =G25 -> 578146 | H26: =G26-G25 -> 0 | I26: =C26+H26 -> 0 | J26: =IF(I26>0,E26/I26,0) -> 0 | K26: ='Swimming Pool quality check '!H26 -> 5955 | L26: =K26-K25 -> 0 | M26: =M25 -> 457.44 | N26: =SUM(M26-M25) -> 0 | O26: =O25 -> 529.52 | P26: =SUM(O26-O25) -> 0 | Q26: =SUM(P26+N26) -> 0 | T26: =T25 -> 3926 | U26: =SUM(T26-T25) -> 0 | V26: =V25 -> 242 | W26: =+V26-V25 -> 0 | X26: =X25 -> 134778 | Y26: =SUM(X26-X25) -> 0 | Z26: =Z25 -> 87453 | AA26: =Z26-Z25 -> 0 | AB26: =AB25 -> 260 | AC26: =AC25 -> 643 | AD26: =AC26-AC25 -> 0 | AE26: =AE25 -> 0 | AF26: =AE26-AE25 -> 0 | AG26: =AG25 -> 111.8 | AH26: =AG26-AG25 -> 0 | AI26: =AF26+AH26 -> 0 | AJ26: =+Z26-Z25 -> 0 | AK26: =SUM(Y26-L26) -> 0 | AL26: =SUM(AJ26-W26) -> 0 | AM26: ='General information '!D26 -> 0 | AN26: ='General information '!H26 -> 0 | AP26: ='General information '!J26 -> 0 | AR26: =A26 -> 43759 | AS26: =AS25 -> 0.9 | AT26: =AT25 -> 23 | AU26: =AU25 -> 1.1 | AV26: =AV25 -> 110 | AW26: 2.9 | AX26: =AX25 -> 77 | AY26: =AS26*AT26 -> 20.7 | AZ26: =AU26*AV26 -> 121 | BA26: =AW26*AX26 -> 223.3 | BB26: =AY26-AY25 -> 0 | BC26: =AZ26-AZ25 -> 0 | BD26: =BA26-BA25 -> 0 | BE26: =SUM(BB26:BD26) -> 0 | BF26: =SUM(I26-BE26) -> 0 | BG26: =SUM(I26-BF26) -> 0
A27: =ELEC!C24 -> 43760 | B27: =B26 -> 105252 | C27: =B27-B26 -> 0 | D27: =C27/27 -> 0 | E27: =SUM((C27*$E$4)+(7500/'EDl log'!$A$38)) -> 241.93548 | G27: =G26 -> 578146 | H27: =G27-G26 -> 0 | I27: =C27+H27 -> 0 | J27: =IF(I27>0,E27/I27,0) -> 0 | K27: ='Swimming Pool quality check '!H27 -> 5955 | L27: =K27-K26 -> 0 | M27: =M26 -> 457.44 | N27: =SUM(M27-M26) -> 0 | O27: =O26 -> 529.52 | P27: =SUM(O27-O26) -> 0 | Q27: =SUM(P27+N27) -> 0 | T27: =T26 -> 3926 | U27: =SUM(T27-T26) -> 0 | V27: =V26 -> 242 | W27: =+V27-V26 -> 0 | X27: =X26 -> 134778 | Y27: =SUM(X27-X26) -> 0 | Z27: =Z26 -> 87453 | AA27: =Z27-Z26 -> 0 | AB27: =AB26 -> 260 | AC27: =AC26 -> 643 | AD27: =AC27-AC26 -> 0 | AE27: =AE26 -> 0 | AF27: =AE27-AE26 -> 0 | AG27: =AG26 -> 111.8 | AH27: =AG27-AG26 -> 0 | AI27: =AF27+AH27 -> 0 | AJ27: =+Z27-Z26 -> 0 | AK27: =SUM(Y27-L27) -> 0 | AL27: =SUM(AJ27-W27) -> 0 | AM27: ='General information '!D27 -> 0 | AN27: ='General information '!H27 -> 0 | AP27: ='General information '!J27 -> 0 | AR27: =A27 -> 43760 | AS27: =AS26 -> 0.9 | AT27: =AT26 -> 23 | AU27: =AU26 -> 1.1 | AV27: =AV26 -> 110 | AW27: 2.9 | AX27: =AX26 -> 77 | AY27: =AS27*AT27 -> 20.7 | AZ27: =AU27*AV27 -> 121 | BA27: =AW27*AX27 -> 223.3 | BB27: =AY27-AY26 -> 0 | BC27: =AZ27-AZ26 -> 0 | BD27: =BA27-BA26 -> 0 | BE27: =SUM(BB27:BD27) -> 0 | BF27: =SUM(I27-BE27) -> 0 | BG27: =SUM(I27-BF27) -> 0
A28: =ELEC!C25 -> 43761 | B28: =B27 -> 105252 | C28: =B28-B27 -> 0 | D28: =C28/27 -> 0 | E28: =SUM((C28*$E$4)+(7500/'EDl log'!$A$38)) -> 241.93548 | G28: =G27 -> 578146 | H28: =G28-G27 -> 0 | I28: =C28+H28 -> 0 | J28: =IF(I28>0,E28/I28,0) -> 0 | K28: ='Swimming Pool quality check '!H28 -> 5955 | L28: =K28-K27 -> 0 | M28: =M27 -> 457.44 | N28: =SUM(M28-M27) -> 0 | O28: =O27 -> 529.52 | P28: =SUM(O28-O27) -> 0 | Q28: =SUM(P28+N28) -> 0 | T28: =T27 -> 3926 | U28: =SUM(T28-T27) -> 0 | V28: =V27 -> 242 | W28: =+V28-V27 -> 0 | X28: =X27 -> 134778 | Y28: =SUM(X28-X27) -> 0 | Z28: =Z27 -> 87453 | AA28: =Z28-Z27 -> 0 | AB28: =AB27 -> 260 | AC28: =AC27 -> 643 | AD28: =AC28-AC27 -> 0 | AE28: =AE27 -> 0 | AF28: =AE28-AE27 -> 0 | AG28: =AG27 -> 111.8 | AH28: =AG28-AG27 -> 0 | AI28: =AF28+AH28 -> 0 | AJ28: =+Z28-Z27 -> 0 | AK28: =SUM(Y28-L28) -> 0 | AL28: =SUM(AJ28-W28) -> 0 | AM28: ='General information '!D28 -> 0 | AN28: ='General information '!H28 -> 0 | AP28: ='General information '!J28 -> 0 | AR28: =A28 -> 43761 | AS28: =AS27 -> 0.9 | AT28: =AT27 -> 23 | AU28: =AU27 -> 1.1 | AV28: =AV27 -> 110 | AW28: 2.9 | AX28: =AX27 -> 77 | AY28: =AS28*AT28 -> 20.7 | AZ28: =AU28*AV28 -> 121 | BA28: =AW28*AX28 -> 223.3 | BB28: =AY28-AY27 -> 0 | BC28: =AZ28-AZ27 -> 0 | BD28: =BA28-BA27 -> 0 | BE28: =SUM(BB28:BD28) -> 0 | BF28: =SUM(I28-BE28) -> 0 | BG28: =SUM(I28-BF28) -> 0
A29: =ELEC!C26 -> 43762 | B29: =B28 -> 105252 | C29: =B29-B28 -> 0 | D29: =C29/27 -> 0 | E29: =SUM((C29*$E$4)+(7500/'EDl log'!$A$38)) -> 241.93548 | G29: =G28 -> 578146 | H29: =G29-G28 -> 0 | I29: =C29+H29 -> 0 | J29: =IF(I29>0,E29/I29,0) -> 0 | K29: ='Swimming Pool quality check '!H29 -> 5955 | L29: =K29-K28 -> 0 | M29: =M28 -> 457.44 | N29: =SUM(M29-M28) -> 0 | O29: =O28 -> 529.52 | P29: =SUM(O29-O28) -> 0 | Q29: =SUM(P29+N29) -> 0 | T29: =T28 -> 3926 | U29: =SUM(T29-T28) -> 0 | V29: =V28 -> 242 | W29: =+V29-V28 -> 0 | X29: =X28 -> 134778 | Y29: =SUM(X29-X28) -> 0 | Z29: =Z28 -> 87453 | AA29: =Z29-Z28 -> 0 | AB29: =AB28 -> 260 | AC29: =AC28 -> 643 | AD29: =AC29-AC28 -> 0 | AE29: =AE28 -> 0 | AF29: =AE29-AE28 -> 0 | AG29: =AG28 -> 111.8 | AH29: =AG29-AG28 -> 0 | AI29: =AF29+AH29 -> 0 | AJ29: =+Z29-Z28 -> 0 | AK29: =SUM(Y29-L29) -> 0 | AL29: =SUM(AJ29-W29) -> 0 | AM29: ='General information '!D29 -> 0 | AN29: ='General information '!H29 -> 0 | AP29: ='General information '!J29 -> 0 | AR29: =A29 -> 43762 | AS29: =AS28 -> 0.9 | AT29: =AT28 -> 23 | AU29: =AU28 -> 1.1 | AV29: =AV28 -> 110 | AW29: 2.9 | AX29: =AX28 -> 77 | AY29: =AS29*AT29 -> 20.7 | AZ29: =AU29*AV29 -> 121 | BA29: =AW29*AX29 -> 223.3 | BB29: =AY29-AY28 -> 0 | BC29: =AZ29-AZ28 -> 0 | BD29: =BA29-BA28 -> 0 | BE29: =SUM(BB29:BD29) -> 0 | BF29: =SUM(I29-BE29) -> 0 | BG29: =SUM(I29-BF29) -> 0
A30: =ELEC!C27 -> 43763 | B30: =B29 -> 105252 | C30: =B30-B29 -> 0 | D30: =C30/27 -> 0 | E30: =SUM((C30*$E$4)+(7500/'EDl log'!$A$38)) -> 241.93548 | G30: =G29 -> 578146 | H30: =G30-G29 -> 0 | I30: =C30+H30 -> 0 | J30: =IF(I30>0,E30/I30,0) -> 0 | K30: ='Swimming Pool quality check '!H30 -> 5955 | L30: =K30-K29 -> 0 | M30: =M29 -> 457.44 | N30: =SUM(M30-M29) -> 0 | O30: =O29 -> 529.52 | P30: =SUM(O30-O29) -> 0 | Q30: =SUM(P30+N30) -> 0 | T30: =T29 -> 3926 | U30: =SUM(T30-T29) -> 0 | V30: =V29 -> 242 | W30: =+V30-V29 -> 0 | X30: =X29 -> 134778 | Y30: =SUM(X30-X29) -> 0 | Z30: =Z29 -> 87453 | AA30: =Z30-Z29 -> 0 | AB30: =AB29 -> 260 | AC30: =AC29 -> 643 | AD30: =AC30-AC29 -> 0 | AE30: =AE29 -> 0 | AF30: =AE30-AE29 -> 0 | AG30: =AG29 -> 111.8 | AH30: =AG30-AG29 -> 0 | AI30: =AF30+AH30 -> 0 | AJ30: =+Z30-Z29 -> 0 | AK30: =SUM(Y30-L30) -> 0 | AL30: =SUM(AJ30-W30) -> 0 | AM30: ='General information '!D30 -> 0 | AN30: ='General information '!H30 -> 0 | AP30: ='General information '!J30 -> 0 | AR30: =A30 -> 43763 | AS30: =AS29 -> 0.9 | AT30: =AT29 -> 23 | AU30: =AU29 -> 1.1 | AV30: =AV29 -> 110 | AW30: 2.9 | AX30: =AX29 -> 77 | AY30: =AS30*AT30 -> 20.7 | AZ30: =AU30*AV30 -> 121 | BA30: =AW30*AX30 -> 223.3 | BB30: =AY30-AY29 -> 0 | BC30: =AZ30-AZ29 -> 0 | BD30: =BA30-BA29 -> 0 | BE30: =SUM(BB30:BD30) -> 0 | BF30: =SUM(I30-BE30) -> 0 | BG30: =SUM(I30-BF30) -> 0
A31: =ELEC!C28 -> 43764 | B31: =B30 -> 105252 | C31: =B31-B30 -> 0 | D31: =C31/27 -> 0 | E31: =SUM((C31*$E$4)+(7500/'EDl log'!$A$38)) -> 241.93548 | G31: =G30 -> 578146 | H31: =G31-G30 -> 0 | I31: =C31+H31 -> 0 | J31: =IF(I31>0,E31/I31,0) -> 0 | K31: ='Swimming Pool quality check '!H31 -> 5955 | L31: =K31-K30 -> 0 | M31: =M30 -> 457.44 | N31: =SUM(M31-M30) -> 0 | O31: =O30 -> 529.52 | P31: =SUM(O31-O30) -> 0 | Q31: =SUM(P31+N31) -> 0 | T31: =T30 -> 3926 | U31: =SUM(T31-T30) -> 0 | V31: =V30 -> 242 | W31: =+V31-V30 -> 0 | X31: =X30 -> 134778 | Y31: =SUM(X31-X30) -> 0 | Z31: =Z30 -> 87453 | AA31: =Z31-Z30 -> 0 | AB31: =AB30 -> 260 | AC31: =AC30 -> 643 | AD31: =AC31-AC30 -> 0 | AE31: =AE30 -> 0 | AF31: =AE31-AE30 -> 0 | AG31: =AG30 -> 111.8 | AH31: =AG31-AG30 -> 0 | AI31: =AF31+AH31 -> 0 | AJ31: =+Z31-Z30 -> 0 | AK31: =SUM(Y31-L31) -> 0 | AL31: =SUM(AJ31-W31) -> 0 | AM31: ='General information '!D31 -> 0 | AN31: ='General information '!H31 -> 0 | AP31: ='General information '!J31 -> 0 | AR31: =A31 -> 43764 | AS31: =AS30 -> 0.9 | AT31: =AT30 -> 23 | AU31: =AU30 -> 1.1 | AV31: =AV30 -> 110 | AW31: 2.9 | AX31: =AX30 -> 77 | AY31: =AS31*AT31 -> 20.7 | AZ31: =AU31*AV31 -> 121 | BA31: =AW31*AX31 -> 223.3 | BB31: =AY31-AY30 -> 0 | BC31: =AZ31-AZ30 -> 0 | BD31: =BA31-BA30 -> 0 | BE31: =SUM(BB31:BD31) -> 0 | BF31: =SUM(I31-BE31) -> 0 | BG31: =SUM(I31-BF31) -> 0
... A36: =ELEC!C33 -> 43769 | B36: =B35 -> 105252 | C36: =B36-B35 -> 0 | D36: =C36/27 -> 0 | E36: =SUM((C36*$E$4)+(7500/'EDl log'!$A$38)) -> 241.93548 | G36: =G35 -> 578146 | H36: =G36-G35 -> 0 | I36: =C36+H36 -> 0 | J36: =IF(I36>0,E36/I36,0) -> 0 | K36: ='Swimming Pool quality check '!H36 -> 5955 | L36: =K36-K35 -> 0 | M36: =M35 -> 457.44 | N36: =SUM(M36-M35) -> 0 | O36: =O35 -> 529.52 | P36: =SUM(O36-O35) -> 0 | Q36: =SUM(P36+N36) -> 0 | T36: =T35 -> 3926 | U36: =SUM(T36-T35) -> 0 | V36: =V35 -> 242 | W36: =+V36-V35 -> 0 | X36: =X35 -> 134778 | Y36: =SUM(X36-X35) -> 0 | Z36: =Z35 -> 87453 | AA36: =Z36-Z35 -> 0 | AB36: =AB35 -> 260 | AC36: =AC35 -> 643 | AD36: =AC36-AC35 -> 0 | AE36: =AE35 -> 0 | AF36: =AE36-AE35 -> 0 | AG36: =AG35 -> 111.8 | AH36: =AG36-AG35 -> 0 | AI36: =AF36+AH36 -> 0 | AJ36: =+Z36-Z35 -> 0 | AK36: =SUM(Y36-L36) -> 0 | AL36: =SUM(AJ36-W36) -> 0 | AM36: ='General information '!D36 -> 0 | AN36: ='General information '!H36 -> 0 | AP36: ='General information '!J36 -> 0 | AR36: =A36 -> 43769 | AS36: =AS35 -> 0.9 | AT36: =AT35 -> 23 | AU36: =AU35 -> 1.1 | AV36: =AV35 -> 110 | AW36: 2.9 | AX36: =AX35 -> 77 | AY36: =AS36*AT36 -> 20.7 | AZ36: =AU36*AV36 -> 121 | BA36: =AW36*AX36 -> 223.3 | BB36: =AY36-AY35 -> 0 | BC36: =AZ36-AZ35 -> 0 | BD36: =BA36-BA35 -> 0 | BE36: =SUM(BB36:BD36) -> 0 | BF36: =SUM(I36-BE36) -> 0 | BG36: =SUM(I36-BF36) -> 0
C37: =SUM(C6:C36) -> 2042 | D37: =SUM(D6:D36) -> 75.62963 | F37: =SUM(F6:F36) -> 77 | H37: =SUM(H6:H36) -> 1481 | I37: =SUM(I6:I36) -> 3523 | L37: =SUM(L7:L36) -> 45 | Q37: =SUM(Q5:Q35) -> 0 | U37: =SUM(U6:U36) -> 170 | Y37: =SUM(Y35,Y33,Y31,Y29,Y27,Y25,Y23,Y21,Y19,Y17,Y15,Y13,Y11,Y9,Y7+Y36) -> 630 | AJ37: =SUM(AJ6:AJ36) -> 1319 | AK37: =SUM(Y37-L37) -> 585 | AL37: =SUM(AL6:AL36) -> 1264
A38: =298351-298175 -> 176 | C38: =+C37*1.66 -> 3389.72 | E38: =SUM(E6:E35) -> 10647.785 | F38: =SUM(F6:F35) -> 77 | H38: 7500 | I38: =SUM('General information '!G37/WATER!I37) -> 0.63463156 | O38: =SUM(Q37+I37) -> 3523 | Z38: =SUM(Y37:AJ37) -> 1949 | AK38: =SUM(Y38-L38) -> 0
B39: =9*27 -> 243 | D39: =SUM(D21:D35) -> 0 | F39: =SUM(F21:F35) -> 0 | G39: =SUM(I37) -> 3523 | H39: =SUM(H38+C38) -> 10889.72 | K39: =SUM(H39/G39) -> 3.091036 | AJ39: =SUM(C38-AK38) -> 3389.72 | AM39: =SUM(AJ39/AO38) -> #DIV/0!

Sheet graphic

Sheet General information 
A1: GENERAL & HOTEL'S INFORMATION SHEET
B4: Max Temp | C4: MIN TEMP | D4: AVE TEMP | E4: AVE Humidity | F4: AVE OCC | G4: # of OCC Rooms | H4: Ball room | I4: Meeting rooms | J4: Outlets | K4: Total covers | L4: # of permenant Emp | M4: # of casuals | N4: Total # of EMP | O4: # of EMP/OCC Room
A5: 43738 | B5: ='[1]General information '!B35 -> 28 | C5: ='[1]General information '!C35 -> 25 | D5: ='[1]General information '!D35 -> 26.5 | E5: ='[1]General information '!E35 -> 0.65 | F5: ='[1]General information '!F35 -> 0.6435 | G5: ='[1]General information '!G35 -> 148.005 | H5: ='[1]General information '!H35 -> 400 | I5: ='[1]General information '!I35 -> 0 | ... O5: ='[1]General information '!O35 -> 0
A6: 43739 | B6: 29 | C6: 25 | D6: =(C6+B6)/2 -> 27 | E6: 0.66 | F6: 0.6913 | G6: =F6*230 -> 158.999 | H6: 230 | J6: 492 | K6: =+J6+H6 -> 722
A7: 43740 | B7: 28 | C7: 25 | D7: =(C7+B7)/2 -> 26.5 | E7: 0.65 | F7: 0.7043 | G7: =F7*230 -> 161.989 | H7: 180 | J7: 636 | K7: =+J7+H7 -> 816
A8: 43741 | B8: 28 | C8: 24 | D8: =(C8+B8)/2 -> 26 | E8: 0.59 | F8: 0.8217 | G8: =F8*230 -> 188.991 | H8: 32 | J8: 1043 | K8: =+J8+H8 -> 1075
A9: 43742 | B9: 28 | C9: 23 | D9: =(C9+B9)/2 -> 25.5 | E9: 0.6 | F9: 0.834 | G9: =F9*230 -> 191.82 | H9: 491 | J9: 761 | K9: =+J9+H9 -> 1252
A10: 43743 | B10: 28 | C10: 24 | D10: =(C10+B10)/2 -> 26 | E10: 0.65 | F10: 0.7696 | G10: =F10*230 -> 177.008 | H10: 140 | J10: 963 | K10: =+J10+H10 -> 1103
A11: 43744 | B11: 29 | C11: 23 | D11: =(C11+B11)/2 -> 26 | E11: 0.61 | F11: 0.5739 | G11: =F11*230 -> 131.997 | H11: 16 | J11: 564 | K11: =+J11+H11 -> 580
A12: 43745 | B12: 29 | C12: 24 | D12: =(C12+B12)/2 -> 26.5 | E12: 0.58 | F12: 0.5435 | G12: =F12*230 -> 125.005 | H12: 12 | J12: 425 | K12: =+J12+H12 -> 437
A13: 43746 | B13: 29 | C13: 23 | D13: =(C13+B13)/2 -> 26 | E13: 0.59 | F13: 0.6565 | G13: =F13*230 -> 150.995 | H13: 26 | J13: 407 | K13: =+J13+H13 -> 433
A14: 43747 | B14: 29 | C14: 23 | D14: =(C14+B14)/2 -> 26 | E14: 0.6 | F14: 0.7217 | G14: =F14*230 -> 165.991 | H14: 71 | J14: 543 | K14: =+J14+H14 -> 614
A15: 43748 | B15: 28 | C15: 22 | D15: =(C15+B15)/2 -> 25 | E15: 0.61 | F15: 0.8609 | G15: =F15*230 -> 198.007 | H15: 345 | J15: 571 | K15: =+J15+H15 -> 916
A16: 43749 | B16: 29 | C16: 23 | D16: =(C16+B16)/2 -> 26 | E16: 0.67 | F16: 0.8478 | G16: =F16*230 -> 194.994 | H16: 0 | J16: 708 | K16: =+J16+H16 -> 708
A17: 43750 | B17: 28 | C17: 23 | D17: =(C17+B17)/2 -> 25.5 | E17: 0.69 | F17: 0.587 | G17: =F17*230 -> 135.01 | H17: 0 | J17: 668 | K17: =+J17+H17 -> 668
... A19: 43752 | B19: 29 | C19: 25 | D19: =(C19+B19)/2 -> 27 | E19: 0.6 | F19: 0.5826 | G19: =F19*230 -> 133.998 | H19: 4 | J19: 510 | K19: =+J19+H19 -> 514
A20: 43753 | D20: =(C20+B20)/2 -> 0 | G20: =F20*230 -> 0 | K20: =+J20+H20 -> 0
A21: 43754 | D21: =(C21+B21)/2 -> 0 | G21: =F21*230 -> 0 | K21: =+J21+H21 -> 0
A22: 43755 | D22: =(C22+B22)/2 -> 0 | G22: =F22*230 -> 0 | K22: =+J22+H22 -> 0
A23: 43756 | D23: =(C23+B23)/2 -> 0 | G23: =F23*230 -> 0 | K23: =+J23+H23 -> 0
A24: 43757 | D24: =(C24+B24)/2 -> 0 | G24: =F24*230 -> 0 | K24: =+J24+H24 -> 0
A25: 43758 | D25: =(C25+B25)/2 -> 0 | G25: =F25*230 -> 0 | K25: =+J25+H25 -> 0
A26: 43759 | D26: =(C26+B26)/2 -> 0 | G26: =F26*230 -> 0 | K26: =+J26+H26 -> 0
A27: 43760 | D27: =(C27+B27)/2 -> 0 | G27: =F27*230 -> 0 | K27: =+J27+H27+I27 -> 0
A28: 43761 | D28: =(C28+B28)/2 -> 0 | G28: =F28*230 -> 0 | K28: =+J28+H28+I28 -> 0
A29: 43762 | D29: =(C29+B29)/2 -> 0 | G29: =F29*230 -> 0 | K29: =+J29+H29+I29 -> 0
A30: 43763 | D30: =(C30+B30)/2 -> 0 | G30: =F30*230 -> 0 | K30: =+J30+H30+I30 -> 0
A31: 43764 | D31: =(C31+B31)/2 -> 0 | G31: =F31*230 -> 0 | K31: =+J31+H31+I31 -> 0
A32: 43765 | D32: =(C32+B32)/2 -> 0 | G32: =F32*230 -> 0 | K32: =+J32+H32+I32 -> 0
A33: 43766 | D33: =(C33+B33)/2 -> 0 | G33: =F33*230 -> 0 | K33: =+J33+H33+I33 -> 0
A34: 43767 | D34: =(C34+B34)/2 -> 0 | G34: =F34*230 -> 0 | K34: =+J34+H34+I34 -> 0
A35: 43768 | D35: =(C35+B35)/2 -> 0 | G35: =F35*230 -> 0 | K35: =+J35+H35+I35 -> 0
A36: 43769 | D36: =(C36+B36)/2 -> 0 | G36: =F36*230 -> 0 | K36: =+J36+H36+I36 -> 0
F37: =AVERAGE(F6:F36) -> 0.69435 | G37: =SUM(G6:G35) -> 2235.807
D38: =SUM(D6:D36)/'EDl log'!A36 -> 26.142857
I41: http://www.accuweather.com/en/lb/lebanon-weather

Sheet tanks
B2: Tank 1 | D2: Tank 2 | F2: Tank 3 | H2: Tank 4 | J2: Tank 5 | L2: Tank 6 | N2: Tank 7 | P2: Tank 8 | R2: Tank 9 | T2: Tank 10 | V2: Tank 11 | Z2: Tank 1 | AB2: Tank 2 | AD2: Tank 3 | AF2: Tank 4 | AH2: Tank 5 | AJ2: Tank 6 | AL2: Tank 7
B3: 6670 | D3: =SUM(B3) -> 6670 | F3: =SUM(D3) -> 6670 | H3: =SUM(F3) -> 6670 | J3: =SUM(H3) -> 6670 | L3: =SUM(J3) -> 6670 | N3: =SUM(L3) -> 6670 | P3: =SUM(N3) -> 6670 | R3: =SUM(P3) -> 6670 | T3: =SUM(R3) -> 6670 | V3: =SUM(T3) -> 6670 | W3: =SUM(B3:V3) -> 73370 | Z3: 2800 | AB3: 2800 | AD3: 2800 | AF3: 2800 | AH3: 2800 | AJ3: 2800 | AL3: 2800 | AM3: =SUM(Z3:AL3) -> 19600 | AO3: =SUM(AM3+W3) -> 92970 | AR3: Total sotck | AS3: Diesel Cons Per day | AT3: Diesel Delivery | BE3: Genset Co | BF3: Steam | BG3: Boil | BH3: Outdoor temperature
B4: =B3/310 -> 21.516129 | D4: =SUM(B4) -> 21.516129 | F4: =SUM(D4) -> 21.516129 | H4: =SUM(F4) -> 21.516129 | J4: =SUM(H4) -> 21.516129 | L4: =SUM(J4) -> 21.516129 | N4: =SUM(L4) -> 21.516129 | P4: =SUM(N4) -> 21.516129 | R4: =SUM(P4) -> 21.516129 | T4: =SUM(R4) -> 21.516129 | V4: =SUM(T4) -> 21.516129 | Z4: =Z3/280 -> 10 | AA4: =AA3/280 -> 0 | AB4: =AB3/280 -> 10 | AC4: =AC3/280 -> 0 | AD4: =AD3/280 -> 10 | AE4: =AE3/280 -> 0 | AF4: =AF3/280 -> 10 | AG4: =AG3/280 -> 0 | ... AL4: =AL3/280 -> 10 | AT4: Delivery | AU4: Cost /L | AW4: Boiler+Steam | AX4: Generator | AZ4: Occupancy | BA4: AVE TEPM | BB4: AVE Humidity
A5: =ELEC!C2 -> 43738 | B5: =[1]tanks!B35 -> 202 | C5: =[1]tanks!C35 -> 4346.2581 | D5: =[1]tanks!D35 -> 202 | E5: =[1]tanks!E35 -> 4346.2581 | F5: =[1]tanks!F35 -> 202 | G5: =[1]tanks!G35 -> 4346.2581 | H5: =[1]tanks!H35 -> 202 | I5: =[1]tanks!I35 -> 4346.2581 | ... AO5: =[1]tanks!AO35 -> 15330 | AP5: =[2]tanks!AP35 -> 0 | AQ5: =[1]tanks!AQ35 -> 0.67913132 | AR5: =[1]tanks!AR35 -> 63138.839 | AS5: =[1]tanks!AS35 -> -2493.8065 | AT5: =[1]tanks!AT35 -> 8784 | AU5: =[1]tanks!AU35 -> 0.54 | AV5: =[1]tanks!AV35 -> 0.54 | AW5: =[1]tanks!AW35 -> -888.1 | AX5: =[1]tanks!AX35 -> -1605.7065 | ... BB5: =[1]tanks!BB35 -> 0.65 | BC5: =[3]tanks!BC36 -> 0 | BD5: =[3]tanks!BD36 -> 19222 | BE5: =[3]tanks!BE36 -> #REF! | BF5: =[3]tanks!BF36 -> 0 | BG5: =[3]tanks!BG36 -> #REF! | BH5: =[3]tanks!BH36 -> 0
A6: =ELEC!C3 -> 43739 | B6: ='B5'!B5 -> 188 | C6: =B6*$B$4 -> 4045.0323 | D6: =SUM(B6) -> 188 | E6: =D6*$B$4 -> 4045.0323 | F6: =SUM(D6) -> 188 | G6: =F6*$B$4 -> 4045.0323 | H6: =SUM(F6) -> 188 | I6: =H6*$B$4 -> 4045.0323 | J6: =SUM(H6) -> 188 | K6: =J6*$B$4 -> 4045.0323 | L6: =SUM(J6) -> 188 | M6: =L6*$B$4 -> 4045.0323 | N6: =SUM(L6) -> 188 | O6: =N6*$B$4 -> 4045.0323 | P6: =SUM(N6) -> 188 | Q6: =P6*$B$4 -> 4045.0323 | R6: =SUM(P6) -> 188 | S6: =R6*$B$4 -> 4045.0323 | T6: =SUM(R6) -> 188 | U6: =T6*$B$4 -> 4045.0323 | V6: =SUM(T6) -> 188 | W6: =V6*$B$4 -> 4045.0323 | X6: =SUM(Y6/73370) -> 0.60645161 | Y6: =SUM(C6+E6+G6+I6+K6+M6+O6+Q6+S6+U6+W6) -> 44495.355 | Z6: ='B5'!C5 -> 194 | AA6: =SUM(Z6*$Z$4) -> 1940 | AB6: =SUM(Z6) -> 194 | AC6: =SUM(AB6*$Z$4) -> 1940 | AD6: =SUM(AB6) -> 194 | AE6: =SUM(AD6*$Z$4) -> 1940 | AF6: =SUM(AD6) -> 194 | AG6: =SUM(AF6*$Z$4) -> 1940 | AH6: =SUM(AF6) -> 194 | AI6: =SUM(AH6*$Z$4) -> 1940 | AJ6: =SUM(AH6) -> 194 | AK6: =SUM(AJ6*$Z$4) -> 1940 | AL6: =SUM(AJ6) -> 194 | AM6: =SUM(AL6*$Z$4) -> 1940 | AN6: =SUM(AO6/19600) -> 0.69285714 | AO6: =SUM(AA6+AC6+AE6+AG6+AI6+AK6+AM6) -> 13580 | AQ6: =SUM(AR6/92970) -> 0.62466769 | AR6: =SUM(AO6+Y6) -> 58075.355 | AS6: =SUM(AR6-AR5-AT6) -> -5063.4839 | AV6: =IF(AT6>0,AU6,AV5) -> 0.54 | AW6: =-SUM('B5'!AI5) -> -839.1 | AX6: =-SUM(AW6-AS6) -> -4224.3839 | AY6: =SUM(AX6+AW6) -> -5063.4839 | AZ6: =ELEC!A3 -> 0.6913 | BA6: ='General information '!D6 -> 27 | BB6: =SUM('General information '!E6) -> 0.66 | BC6: =IF(AR3>=AR6,0,1) -> 0 | BD6: 19222 | BE6: =(305/1185)*ELEC!Q4 -> 2646.9367 | BG6: =#REF!-BE6 -> #REF! | BH6: 21
A7: =ELEC!C4 -> 43740 | B7: ='B5'!B6 -> 174 | C7: =B7*$B$4 -> 3743.8065 | D7: =SUM(B7) -> 174 | E7: =D7*$B$4 -> 3743.8065 | F7: =SUM(D7) -> 174 | G7: =F7*$B$4 -> 3743.8065 | H7: =SUM(F7) -> 174 | I7: =H7*$B$4 -> 3743.8065 | J7: =SUM(H7) -> 174 | K7: =J7*$B$4 -> 3743.8065 | L7: =SUM(J7) -> 174 | M7: =L7*$B$4 -> 3743.8065 | N7: =SUM(L7) -> 174 | O7: =N7*$B$4 -> 3743.8065 | P7: =SUM(N7) -> 174 | Q7: =P7*$B$4 -> 3743.8065 | R7: =SUM(P7) -> 174 | S7: =R7*$B$4 -> 3743.8065 | T7: =SUM(R7) -> 174 | U7: =T7*$B$4 -> 3743.8065 | V7: =SUM(T7) -> 174 | W7: =V7*$B$4 -> 3743.8065 | X7: =SUM(Y7/73370) -> 0.56129032 | Y7: =SUM(C7+E7+G7+I7+K7+M7+O7+Q7+S7+U7+W7) -> 41181.871 | Z7: ='B5'!C6 -> 180 | AA7: =SUM(Z7*$Z$4) -> 1800 | AB7: =SUM(Z7) -> 180 | AC7: =SUM(AB7*$Z$4) -> 1800 | AD7: =SUM(AB7) -> 180 | AE7: =SUM(AD7*$Z$4) -> 1800 | AF7: =SUM(AD7) -> 180 | AG7: =SUM(AF7*$Z$4) -> 1800 | AH7: =SUM(AF7) -> 180 | AI7: =SUM(AH7*$Z$4) -> 1800 | AJ7: =SUM(AH7) -> 180 | AK7: =SUM(AJ7*$Z$4) -> 1800 | AL7: =SUM(AJ7) -> 180 | AM7: =SUM(AL7*$Z$4) -> 1800 | AN7: =SUM(AO7/19600) -> 0.64285714 | AO7: =SUM(AA7+AC7+AE7+AG7+AI7+AK7+AM7) -> 12600 | AQ7: =SUM(AR7/92970) -> 0.5784863 | AR7: =SUM(AO7+Y7) -> 53781.871 | AS7: =SUM(AR7-AR6-AT7) -> -4293.4839 | AV7: =IF(AT7>0,AU7,AV6) -> 0.54 | AW7: =-SUM('B5'!AI6) -> -802.6 | AX7: =-SUM(AW7-AS7) -> -3490.8839 | AY7: =SUM(AX7+AW7) -> -4293.4839 | AZ7: =ELEC!A4 -> 0.7043 | BA7: ='General information '!D7 -> 26.5 | BB7: =SUM('General information '!E7) -> 0.65 | BC7: 0 | BD7: 19222 | BE7: =(305/1185)*ELEC!Q5 -> 2860.308 | BG7: =#REF!-BE7 -> #REF! | BH7: 19
A8: =ELEC!C5 -> 43741 | B8: ='B5'!B7 -> 159 | C8: =B8*$B$4 -> 3421.0645 | D8: =SUM(B8) -> 159 | E8: =D8*$B$4 -> 3421.0645 | F8: =SUM(D8) -> 159 | G8: =F8*$B$4 -> 3421.0645 | H8: =SUM(F8) -> 159 | I8: =H8*$B$4 -> 3421.0645 | J8: =SUM(H8) -> 159 | K8: =J8*$B$4 -> 3421.0645 | L8: =SUM(J8) -> 159 | M8: =L8*$B$4 -> 3421.0645 | N8: =SUM(L8) -> 159 | O8: =N8*$B$4 -> 3421.0645 | P8: =SUM(N8) -> 159 | Q8: =P8*$B$4 -> 3421.0645 | R8: =SUM(P8) -> 159 | S8: =R8*$B$4 -> 3421.0645 | T8: =SUM(R8) -> 159 | U8: =T8*$B$4 -> 3421.0645 | V8: =SUM(T8) -> 159 | W8: =V8*$B$4 -> 3421.0645 | X8: =SUM(Y8/73370) -> 0.51290323 | Y8: =SUM(C8+E8+G8+I8+K8+M8+O8+Q8+S8+U8+W8) -> 37631.71 | Z8: ='B5'!C7 -> 165 | AA8: =SUM(Z8*$Z$4) -> 1650 | AB8: =SUM(Z8) -> 165 | AC8: =SUM(AB8*$Z$4) -> 1650 | AD8: =SUM(AB8) -> 165 | AE8: =SUM(AD8*$Z$4) -> 1650 | AF8: =SUM(AD8) -> 165 | AG8: =SUM(AF8*$Z$4) -> 1650 | AH8: =SUM(AF8) -> 165 | AI8: =SUM(AH8*$Z$4) -> 1650 | AJ8: =SUM(AH8) -> 165 | AK8: =SUM(AJ8*$Z$4) -> 1650 | AL8: =SUM(AJ8) -> 165 | AM8: =SUM(AL8*$Z$4) -> 1650 | AN8: =SUM(AO8/19600) -> 0.58928571 | AO8: =SUM(AA8+AC8+AE8+AG8+AI8+AK8+AM8) -> 11550 | AQ8: =SUM(AR8/92970) -> 0.52900624 | AR8: =SUM(AO8+Y8) -> 49181.71 | AS8: =SUM(AR8-AR7-AT8) -> -4600.1613 | AV8: =IF(AT8>0,AU8,AV7) -> 0.54 | AW8: =-SUM('B5'!AI7) -> -812.6 | AX8: =-SUM(AW8-AS8) -> -3787.5613 | AY8: =SUM(AX8+AW8) -> -4600.1613 | AZ8: =ELEC!A5 -> 0.8217 | BA8: ='General information '!D8 -> 26 | BB8: =SUM('General information '!E8) -> 0.59 | BC8: =IF(AR7>=AR8,0,1) -> 0 | BD8: 19222 | BE8: =(305/1185)*ELEC!Q6 -> 1901.2954 | BG8: =#REF!-BE8 -> #REF! | BH8: 16
A9: =ELEC!C6 -> 43742 | B9: ='B5'!B8 -> 204 | C9: =B9*$B$4 -> 4389.2903 | D9: =SUM(B9) -> 204 | E9: =D9*$B$4 -> 4389.2903 | F9: =SUM(D9) -> 204 | G9: =F9*$B$4 -> 4389.2903 | H9: =SUM(F9) -> 204 | I9: =H9*$B$4 -> 4389.2903 | J9: =SUM(H9) -> 204 | K9: =J9*$B$4 -> 4389.2903 | L9: =SUM(J9) -> 204 | M9: =L9*$B$4 -> 4389.2903 | N9: =SUM(L9) -> 204 | O9: =N9*$B$4 -> 4389.2903 | P9: =SUM(N9) -> 204 | Q9: =P9*$B$4 -> 4389.2903 | R9: =SUM(P9) -> 204 | S9: =R9*$B$4 -> 4389.2903 | T9: =SUM(R9) -> 204 | U9: =T9*$B$4 -> 4389.2903 | V9: =SUM(T9) -> 204 | W9: =V9*$B$4 -> 4389.2903 | X9: =SUM(Y9/73370) -> 0.65806452 | Y9: =SUM(C9+E9+G9+I9+K9+M9+O9+Q9+S9+U9+W9) -> 48282.194 | Z9: ='B5'!C8 -> 210 | AA9: =SUM(Z9*$Z$4) -> 2100 | AB9: =SUM(Z9) -> 210 | AC9: =SUM(AB9*$Z$4) -> 2100 | AD9: =SUM(AB9) -> 210 | AE9: =SUM(AD9*$Z$4) -> 2100 | AF9: =SUM(AD9) -> 210 | AG9: =SUM(AF9*$Z$4) -> 2100 | AH9: =SUM(AF9) -> 210 | AI9: =SUM(AH9*$Z$4) -> 2100 | AJ9: =SUM(AH9) -> 210 | AK9: =SUM(AJ9*$Z$4) -> 2100 | AL9: =SUM(AJ9) -> 210 | AM9: =SUM(AL9*$Z$4) -> 2100 | AN9: =SUM(AO9/19600) -> 0.75 | AO9: =SUM(AA9+AC9+AE9+AG9+AI9+AK9+AM9) -> 14700 | AQ9: =SUM(AR9/92970) -> 0.67744642 | AR9: =SUM(AO9+Y9) -> 62982.194 | AS9: =SUM(AR9-AR8-AT9) -> -1235.5161 | AT9: 15036 | AU9: 0.54666 | AV9: =IF(AT9>0,AU9,AV8) -> 0.54666 | AW9: =-SUM('B5'!AI8) -> -932.5 | AX9: =-SUM(AW9-AS9) -> -303.01613 | AY9: =SUM(AX9+AW9) -> -1235.5161 | AZ9: =ELEC!A6 -> 0.834 | BA9: ='General information '!D9 -> 25.5 | BB9: =SUM('General information '!E9) -> 0.6 | BC9: =IF(AR8>=AR9,0,1) -> 1 | BD9: 19222 | BE9: =(305/1185)*ELEC!Q7 -> 1235.443 | BG9: =#REF!-BE9 -> #REF! | BH9: 18
A10: =ELEC!C7 -> 43743 | B10: ='B5'!B9 -> 194 | C10: =B10*$B$4 -> 4174.129 | D10: =SUM(B10) -> 194 | E10: =D10*$B$4 -> 4174.129 | F10: =SUM(D10) -> 194 | G10: =F10*$B$4 -> 4174.129 | H10: =SUM(F10) -> 194 | I10: =H10*$B$4 -> 4174.129 | J10: =SUM(H10) -> 194 | K10: =J10*$B$4 -> 4174.129 | L10: =SUM(J10) -> 194 | M10: =L10*$B$4 -> 4174.129 | N10: =SUM(L10) -> 194 | O10: =N10*$B$4 -> 4174.129 | P10: =SUM(N10) -> 194 | Q10: =P10*$B$4 -> 4174.129 | R10: =SUM(P10) -> 194 | S10: =R10*$B$4 -> 4174.129 | T10: =SUM(R10) -> 194 | U10: =T10*$B$4 -> 4174.129 | V10: =SUM(T10) -> 194 | W10: =V10*$B$4 -> 4174.129 | X10: =SUM(Y10/73370) -> 0.62580645 | Y10: =SUM(C10+E10+G10+I10+K10+M10+O10+Q10+S10+U10+W10) -> 45915.419 | Z10: ='B5'!C9 -> 201 | AA10: =SUM(Z10*$Z$4) -> 2010 | AB10: =SUM(Z10) -> 201 | AC10: =SUM(AB10*$Z$4) -> 2010 | AD10: =SUM(AB10) -> 201 | AE10: =SUM(AD10*$Z$4) -> 2010 | AF10: =SUM(AD10) -> 201 | AG10: =SUM(AF10*$Z$4) -> 2010 | AH10: =SUM(AF10) -> 201 | AI10: =SUM(AH10*$Z$4) -> 2010 | AJ10: =SUM(AH10) -> 201 | AK10: =SUM(AJ10*$Z$4) -> 2010 | AL10: =SUM(AJ10) -> 201 | AM10: =SUM(AL10*$Z$4) -> 2010 | AN10: =SUM(AO10/19600) -> 0.71785714 | AO10: =SUM(AA10+AC10+AE10+AG10+AI10+AK10+AM10) -> 14070 | AQ10: =SUM(AR10/92970) -> 0.64521264 | AR10: =SUM(AO10+Y10) -> 59985.419 | AS10: =SUM(AR10-AR9-AT10) -> -2996.7742 | AV10: =IF(AT10>0,AU10,AV9) -> 0.54666 | AW10: =-SUM('B5'!AI9) -> -1032.5 | AX10: =-SUM(AW10-AS10) -> -1964.2742 | AY10: =SUM(AX10+AW10) -> -2996.7742 | AZ10: =ELEC!A7 -> 0.7696 | BA10: ='General information '!D10 -> 26 | BB10: =SUM('General information '!E10) -> 0.65 | BC10: =IF(AR9>=AR10,0,1) -> 0 | BD10: 19222 | BE10: =(305/1185)*ELEC!Q8 -> 1066.5992 | BG10: =#REF!-BE10 -> #REF! | BH10: 16
A11: =ELEC!C8 -> 43744 | B11: ='B5'!B10 -> 186 | C11: =B11*$B$4 -> 4002 | D11: =SUM(B11) -> 186 | E11: =D11*$B$4 -> 4002 | F11: =SUM(D11) -> 186 | G11: =F11*$B$4 -> 4002 | H11: =SUM(F11) -> 186 | I11: =H11*$B$4 -> 4002 | J11: =SUM(H11) -> 186 | K11: =J11*$B$4 -> 4002 | L11: =SUM(J11) -> 186 | M11: =L11*$B$4 -> 4002 | N11: =SUM(L11) -> 186 | O11: =N11*$B$4 -> 4002 | P11: =SUM(N11) -> 186 | Q11: =P11*$B$4 -> 4002 | R11: =SUM(P11) -> 186 | S11: =R11*$B$4 -> 4002 | T11: =SUM(R11) -> 186 | U11: =T11*$B$4 -> 4002 | V11: =SUM(T11) -> 186 | W11: =V11*$B$4 -> 4002 | X11: =SUM(Y11/73370) -> 0.6 | Y11: =SUM(C11+E11+G11+I11+K11+M11+O11+Q11+S11+U11+W11) -> 44022 | Z11: ='B5'!C10 -> 192 | AA11: =SUM(Z11*$Z$4) -> 1920 | AB11: =SUM(Z11) -> 192 | AC11: =SUM(AB11*$Z$4) -> 1920 | AD11: =SUM(AB11) -> 192 | AE11: =SUM(AD11*$Z$4) -> 1920 | AF11: =SUM(AD11) -> 192 | AG11: =SUM(AF11*$Z$4) -> 1920 | AH11: =SUM(AF11) -> 192 | AI11: =SUM(AH11*$Z$4) -> 1920 | AJ11: =SUM(AH11) -> 192 | AK11: =SUM(AJ11*$Z$4) -> 1920 | AL11: =SUM(AJ11) -> 192 | AM11: =SUM(AL11*$Z$4) -> 1920 | AN11: =SUM(AO11/19600) -> 0.68571429 | AO11: =SUM(AA11+AC11+AE11+AG11+AI11+AK11+AM11) -> 13440 | AQ11: =SUM(AR11/92970) -> 0.61807035 | AR11: =SUM(AO11+Y11) -> 57462 | AS11: =SUM(AR11-AR10-AT11) -> -2523.4194 | AV11: =IF(AT11>0,AU11,AV10) -> 0.54666 | AW11: =-SUM('B5'!AI10) -> -1043.2 | AX11: =-SUM(AW11-AS11) -> -1480.2194 | AY11: =SUM(AX11+AW11) -> -2523.4194 | AZ11: =ELEC!A8 -> 0.5739 | BA11: ='General information '!D11 -> 26 | BB11: =SUM('General information '!E11) -> 0.61 | BC11: =IF(AR10>=AR11,0,1) -> 0 | BD11: 19222 | BE11: =(305/1185)*ELEC!Q9 -> 1219.7426 | BG11: =#REF!-BE11 -> #REF! | BH11: 16.5
A12: =ELEC!C9 -> 43745 | B12: ='B5'!B11 -> 177 | C12: =B12*$B$4 -> 3808.3548 | D12: =SUM(B12) -> 177 | E12: =D12*$B$4 -> 3808.3548 | F12: =SUM(D12) -> 177 | G12: =F12*$B$4 -> 3808.3548 | H12: =SUM(F12) -> 177 | I12: =H12*$B$4 -> 3808.3548 | J12: =SUM(H12) -> 177 | K12: =J12*$B$4 -> 3808.3548 | L12: =SUM(J12) -> 177 | M12: =L12*$B$4 -> 3808.3548 | N12: =SUM(L12) -> 177 | O12: =N12*$B$4 -> 3808.3548 | P12: =SUM(N12) -> 177 | Q12: =P12*$B$4 -> 3808.3548 | R12: =SUM(P12) -> 177 | S12: =R12*$B$4 -> 3808.3548 | T12: =SUM(R12) -> 177 | U12: =T12*$B$4 -> 3808.3548 | V12: =SUM(T12) -> 177 | W12: =V12*$B$4 -> 3808.3548 | X12: =SUM(Y12/73370) -> 0.57096774 | Y12: =SUM(C12+E12+G12+I12+K12+M12+O12+Q12+S12+U12+W12) -> 41891.903 | Z12: ='B5'!C11 -> 184 | AA12: =SUM(Z12*$Z$4) -> 1840 | AB12: =SUM(Z12) -> 184 | AC12: =SUM(AB12*$Z$4) -> 1840 | AD12: =SUM(AB12) -> 184 | AE12: =SUM(AD12*$Z$4) -> 1840 | AF12: =SUM(AD12) -> 184 | AG12: =SUM(AF12*$Z$4) -> 1840 | AH12: =SUM(AF12) -> 184 | AI12: =SUM(AH12*$Z$4) -> 1840 | AJ12: =SUM(AH12) -> 184 | AK12: =SUM(AJ12*$Z$4) -> 1840 | AL12: =SUM(AJ12) -> 184 | AM12: =SUM(AL12*$Z$4) -> 1840 | AN12: =SUM(AO12/19600) -> 0.65714286 | AO12: =SUM(AA12+AC12+AE12+AG12+AI12+AK12+AM12) -> 12880 | AQ12: =SUM(AR12/92970) -> 0.58913524 | AR12: =SUM(AO12+Y12) -> 54771.903 | AS12: =SUM(AR12-AR11-AT12) -> -2690.0968 | AV12: =IF(AT12>0,AU12,AV11) -> 0.54666 | AW12: =-SUM('B5'!AI11) -> -861.8 | AX12: =-SUM(AW12-AS12) -> -1828.2968 | AY12: =SUM(AX12+AW12) -> -2690.0968 | AZ12: =ELEC!A9 -> 0.5435 | BA12: ='General information '!D12 -> 26.5 | BB12: =SUM('General information '!E12) -> 0.58 | BC12: =IF(AR11>=AR12,0,1) -> 0 | BD12: 19222 | BE12: =(305/1185)*ELEC!Q10 -> 1173.1561 | BG12: =#REF!-BE12 -> #REF! | BH12: 15.5
A13: =ELEC!C10 -> 43746 | B13: ='B5'!B12 -> 169 | C13: =B13*$B$4 -> 3636.2258 | D13: =SUM(B13) -> 169 | E13: =D13*$B$4 -> 3636.2258 | F13: =SUM(D13) -> 169 | G13: =F13*$B$4 -> 3636.2258 | H13: =SUM(F13) -> 169 | I13: =H13*$B$4 -> 3636.2258 | J13: =SUM(H13) -> 169 | K13: =J13*$B$4 -> 3636.2258 | L13: =SUM(J13) -> 169 | M13: =L13*$B$4 -> 3636.2258 | N13: =SUM(L13) -> 169 | O13: =N13*$B$4 -> 3636.2258 | P13: =SUM(N13) -> 169 | Q13: =P13*$B$4 -> 3636.2258 | R13: =SUM(P13) -> 169 | S13: =R13*$B$4 -> 3636.2258 | T13: =SUM(R13) -> 169 | U13: =T13*$B$4 -> 3636.2258 | V13: =SUM(T13) -> 169 | W13: =V13*$B$4 -> 3636.2258 | X13: =SUM(Y13/73370) -> 0.54516129 | Y13: =SUM(C13+E13+G13+I13+K13+M13+O13+Q13+S13+U13+W13) -> 39998.484 | Z13: ='B5'!C12 -> 175 | AA13: =SUM(Z13*$Z$4) -> 1750 | AB13: =SUM(Z13) -> 175 | AC13: =SUM(AB13*$Z$4) -> 1750 | AD13: =SUM(AB13) -> 175 | AE13: =SUM(AD13*$Z$4) -> 1750 | AF13: =SUM(AD13) -> 175 | AG13: =SUM(AF13*$Z$4) -> 1750 | AH13: =SUM(AF13) -> 175 | AI13: =SUM(AH13*$Z$4) -> 1750 | AJ13: =SUM(AH13) -> 175 | AK13: =SUM(AJ13*$Z$4) -> 1750 | AL13: =SUM(AJ13) -> 175 | AM13: =SUM(AL13*$Z$4) -> 1750 | AN13: =SUM(AO13/19600) -> 0.625 | AO13: =SUM(AA13+AC13+AE13+AG13+AI13+AK13+AM13) -> 12250 | AQ13: =SUM(AR13/92970) -> 0.56199294 | AR13: =SUM(AO13+Y13) -> 52248.484 | AS13: =SUM(AR13-AR12-AT13) -> -2523.4194 | AV13: =IF(AT13>0,AU13,AV12) -> 0.54666 | AW13: =-SUM('B5'!AI12) -> -807.8 | AX13: =-SUM(AW13-AS13) -> -1715.6194 | AY13: =SUM(AX13+AW13) -> -2523.4194 | AZ13: =ELEC!A10 -> 0.6565 | BA13: ='General information '!D13 -> 26 | BB13: =SUM('General information '!E13) -> 0.59 | BC13: =IF(AR12>=AR13,0,1) -> 0 | BD13: 19222 | BE13: =(305/1185)*ELEC!Q11 -> 1139.1814 | BG13: =#REF!-BE13 -> #REF!
A14: =ELEC!C11 -> 43747 | B14: ='B5'!B13 -> 160 | C14: =B14*$B$4 -> 3442.5806 | D14: =SUM(B14) -> 160 | E14: =D14*$B$4 -> 3442.5806 | F14: =SUM(D14) -> 160 | G14: =F14*$B$4 -> 3442.5806 | H14: =SUM(F14) -> 160 | I14: =H14*$B$4 -> 3442.5806 | J14: =SUM(H14) -> 160 | K14: =J14*$B$4 -> 3442.5806 | L14: =SUM(J14) -> 160 | M14: =L14*$B$4 -> 3442.5806 | N14: =SUM(L14) -> 160 | O14: =N14*$B$4 -> 3442.5806 | P14: =SUM(N14) -> 160 | Q14: =P14*$B$4 -> 3442.5806 | R14: =SUM(P14) -> 160 | S14: =R14*$B$4 -> 3442.5806 | T14: =SUM(R14) -> 160 | U14: =T14*$B$4 -> 3442.5806 | V14: =SUM(T14) -> 160 | W14: =V14*$B$4 -> 3442.5806 | X14: =SUM(Y14/73370) -> 0.51612903 | Y14: =SUM(C14+E14+G14+I14+K14+M14+O14+Q14+S14+U14+W14) -> 37868.387 | Z14: ='B5'!C13 -> 166 | AA14: =SUM(Z14*$Z$4) -> 1660 | AB14: =SUM(Z14) -> 166 | AC14: =SUM(AB14*$Z$4) -> 1660 | AD14: =SUM(AB14) -> 166 | AE14: =SUM(AD14*$Z$4) -> 1660 | AF14: =SUM(AD14) -> 166 | AG14: =SUM(AF14*$Z$4) -> 1660 | AH14: =SUM(AF14) -> 166 | AI14: =SUM(AH14*$Z$4) -> 1660 | AJ14: =SUM(AH14) -> 166 | AK14: =SUM(AJ14*$Z$4) -> 1660 | AL14: =SUM(AJ14) -> 166 | AM14: =SUM(AL14*$Z$4) -> 1660 | AN14: =SUM(AO14/19600) -> 0.59285714 | AO14: =SUM(AA14+AC14+AE14+AG14+AI14+AK14+AM14) -> 11620 | AQ14: =SUM(AR14/92970) -> 0.53230491 | AR14: =SUM(AO14+Y14) -> 49488.387 | AS14: =SUM(AR14-AR13-AT14) -> -2760.0968 | AV14: =IF(AT14>0,AU14,AV13) -> 0.54666 | AW14: =-SUM('B5'!AI13) -> -880.7 | AX14: =-SUM(AW14-AS14) -> -1879.3968 | AY14: =SUM(AX14+AW14) -> -2760.0968 | AZ14: =ELEC!A11 -> 0.7217 | BA14: ='General information '!D14 -> 26 | BB14: =SUM('General information '!E14) -> 0.6 | BC14: =IF(AR13>=AR14,0,1) -> 0 | BD14: 19222 | BE14: =(305/1185)*ELEC!Q12 -> 2445.9198 | BG14: =#REF!-BE14 -> #REF!
A15: =ELEC!C12 -> 43748 | B15: ='B5'!B14 -> 148 | C15: =B15*$B$4 -> 3184.3871 | D15: =SUM(B15) -> 148 | E15: =D15*$B$4 -> 3184.3871 | F15: =SUM(D15) -> 148 | G15: =F15*$B$4 -> 3184.3871 | H15: =SUM(F15) -> 148 | I15: =H15*$B$4 -> 3184.3871 | J15: =SUM(H15) -> 148 | K15: =J15*$B$4 -> 3184.3871 | L15: =SUM(J15) -> 148 | M15: =L15*$B$4 -> 3184.3871 | N15: =SUM(L15) -> 148 | O15: =N15*$B$4 -> 3184.3871 | P15: =SUM(N15) -> 148 | Q15: =P15*$B$4 -> 3184.3871 | R15: =SUM(P15) -> 148 | S15: =R15*$B$4 -> 3184.3871 | T15: =SUM(R15) -> 148 | U15: =T15*$B$4 -> 3184.3871 | V15: =SUM(T15) -> 148 | W15: =V15*$B$4 -> 3184.3871 | X15: =SUM(Y15/73370) -> 0.47741935 | Y15: =SUM(C15+E15+G15+I15+K15+M15+O15+Q15+S15+U15+W15) -> 35028.258 | Z15: ='B5'!C14 -> 154 | AA15: =SUM(Z15*$Z$4) -> 1540 | AB15: =SUM(Z15) -> 154 | AC15: =SUM(AB15*$Z$4) -> 1540 | AD15: =SUM(AB15) -> 154 | AE15: =SUM(AD15*$Z$4) -> 1540 | AF15: =SUM(AD15) -> 154 | AG15: =SUM(AF15*$Z$4) -> 1540 | AH15: =SUM(AF15) -> 154 | AI15: =SUM(AH15*$Z$4) -> 1540 | AJ15: =SUM(AH15) -> 154 | AK15: =SUM(AJ15*$Z$4) -> 1540 | AL15: =SUM(AJ15) -> 154 | AM15: =SUM(AL15*$Z$4) -> 1540 | AN15: =SUM(AO15/19600) -> 0.55 | AO15: =SUM(AA15+AC15+AE15+AG15+AI15+AK15+AM15) -> 10780 | AQ15: =SUM(AR15/92970) -> 0.49272086 | AR15: =SUM(AO15+Y15) -> 45808.258 | AS15: =SUM(AR15-AR14-AT15) -> -3680.129 | AV15: =IF(AT15>0,AU15,AV14) -> 0.54666 | AW15: =-SUM('B5'!AI14) -> -839.1 | AX15: =-SUM(AW15-AS15) -> -2841.029 | AY15: =SUM(AX15+AW15) -> -3680.129 | AZ15: =ELEC!A12 -> 0.8609 | BA15: ='General information '!D15 -> 25 | BB15: =SUM('General information '!E15) -> 0.61 | BC15: =IF(AR14>=AR15,0,1) -> 0 | BD15: 19222 | BE15: =(305/1185)*ELEC!Q13 -> 2738.8228 | BG15: =#REF!-BE15 -> #REF!
A16: =ELEC!C13 -> 43749 | B16: ='B5'!B15 -> 208 | C16: =B16*$B$4 -> 4475.3548 | D16: =SUM(B16) -> 208 | E16: =D16*$B$4 -> 4475.3548 | F16: =SUM(D16) -> 208 | G16: =F16*$B$4 -> 4475.3548 | H16: =SUM(F16) -> 208 | I16: =H16*$B$4 -> 4475.3548 | J16: =SUM(H16) -> 208 | K16: =J16*$B$4 -> 4475.3548 | L16: =SUM(J16) -> 208 | M16: =L16*$B$4 -> 4475.3548 | N16: =SUM(L16) -> 208 | O16: =N16*$B$4 -> 4475.3548 | P16: =SUM(N16) -> 208 | Q16: =P16*$B$4 -> 4475.3548 | R16: =SUM(P16) -> 208 | S16: =R16*$B$4 -> 4475.3548 | T16: =SUM(R16) -> 208 | U16: =T16*$B$4 -> 4475.3548 | V16: =SUM(T16) -> 208 | W16: =V16*$B$4 -> 4475.3548 | X16: =SUM(Y16/73370) -> 0.67096774 | Y16: =SUM(C16+E16+G16+I16+K16+M16+O16+Q16+S16+U16+W16) -> 49228.903 | Z16: ='B5'!C15 -> 214 | AA16: =SUM(Z16*$Z$4) -> 2140 | AB16: =SUM(Z16) -> 214 | AC16: =SUM(AB16*$Z$4) -> 2140 | AD16: =SUM(AB16) -> 214 | AE16: =SUM(AD16*$Z$4) -> 2140 | AF16: =SUM(AD16) -> 214 | AG16: =SUM(AF16*$Z$4) -> 2140 | AH16: =SUM(AF16) -> 214 | AI16: =SUM(AH16*$Z$4) -> 2140 | AJ16: =SUM(AH16) -> 214 | AK16: =SUM(AJ16*$Z$4) -> 2140 | AL16: =SUM(AJ16) -> 214 | AM16: =SUM(AL16*$Z$4) -> 2140 | AN16: =SUM(AO16/19600) -> 0.76428571 | AO16: =SUM(AA16+AC16+AE16+AG16+AI16+AK16+AM16) -> 14980 | AQ16: =SUM(AR16/92970) -> 0.6906411 | AR16: =SUM(AO16+Y16) -> 64208.903 | AS16: =SUM(AR16-AR15-AT16) -> -1619.3548 | AT16: 20020 | AU16: 0.55 | AV16: =IF(AT16>0,AU16,AV15) -> 0.55 | AW16: =-SUM('B5'!AI15) -> -821.9 | AX16: =-SUM(AW16-AS16) -> -797.45484 | AY16: =SUM(AX16+AW16) -> -1619.3548 | AZ16: =ELEC!A13 -> 0.8478 | BA16: ='General information '!D16 -> 26 | BB16: =SUM('General information '!E16) -> 0.67 | BC16: =IF(AR15>=AR16,0,1) -> 1 | BD16: 19222 | BE16: =(305/1185)*ELEC!Q14 -> 1170.3249 | BG16: =#REF!-BE16 -> #REF!
A17: =ELEC!C14 -> 43750 | B17: ='B5'!B16 -> 200 | C17: =B17*$B$4 -> 4303.2258 | D17: =SUM(B17) -> 200 | E17: =D17*$B$4 -> 4303.2258 | F17: =SUM(D17) -> 200 | G17: =F17*$B$4 -> 4303.2258 | H17: =SUM(F17) -> 200 | I17: =H17*$B$4 -> 4303.2258 | J17: =SUM(H17) -> 200 | K17: =J17*$B$4 -> 4303.2258 | L17: =SUM(J17) -> 200 | M17: =L17*$B$4 -> 4303.2258 | N17: =SUM(L17) -> 200 | O17: =N17*$B$4 -> 4303.2258 | P17: =SUM(N17) -> 200 | Q17: =P17*$B$4 -> 4303.2258 | R17: =SUM(P17) -> 200 | S17: =R17*$B$4 -> 4303.2258 | T17: =SUM(R17) -> 200 | U17: =T17*$B$4 -> 4303.2258 | V17: =SUM(T17) -> 200 | W17: =V17*$B$4 -> 4303.2258 | X17: =SUM(Y17/73370) -> 0.64516129 | Y17: =SUM(C17+E17+G17+I17+K17+M17+O17+Q17+S17+U17+W17) -> 47335.484 | Z17: ='B5'!C16 -> 206 | AA17: =SUM(Z17*$Z$4) -> 2060 | AB17: =SUM(Z17) -> 206 | AC17: =SUM(AB17*$Z$4) -> 2060 | AD17: =SUM(AB17) -> 206 | AE17: =SUM(AD17*$Z$4) -> 2060 | AF17: =SUM(AD17) -> 206 | AG17: =SUM(AF17*$Z$4) -> 2060 | AH17: =SUM(AF17) -> 206 | AI17: =SUM(AH17*$Z$4) -> 2060 | AJ17: =SUM(AH17) -> 206 | AK17: =SUM(AJ17*$Z$4) -> 2060 | AL17: =SUM(AJ17) -> 206 | AM17: =SUM(AL17*$Z$4) -> 2060 | AN17: =SUM(AO17/19600) -> 0.73571429 | AO17: =SUM(AA17+AC17+AE17+AG17+AI17+AK17+AM17) -> 14420 | AQ17: =SUM(AR17/92970) -> 0.66425174 | AR17: =SUM(AO17+Y17) -> 61755.484 | AS17: =SUM(AR17-AR16-AT17) -> -2453.4194 | AV17: =IF(AT17>0,AU17,AV16) -> 0.55 | AW17: =-SUM('B5'!AI16) -> -844.2 | AX17: =-SUM(AW17-AS17) -> -1609.2194 | AY17: =SUM(AX17+AW17) -> -2453.4194 | AZ17: =ELEC!A14 -> 0.587 | BA17: ='General information '!D17 -> 25.5 | BB17: =SUM('General information '!E17) -> 0.69 | BC17: =IF(AR16>=AR17,0,1) -> 0 | BD17: 19222 | BE17: =(305/1185)*ELEC!Q15 -> 1033.9114 | BG17: =#REF!-BE17 -> #REF!
A18: =ELEC!C15 -> 43751 | B18: ='B5'!B17 -> 192 | C18: =B18*$B$4 -> 4131.0968 | D18: =SUM(B18) -> 192 | E18: =D18*$B$4 -> 4131.0968 | F18: =SUM(D18) -> 192 | G18: =F18*$B$4 -> 4131.0968 | H18: =SUM(F18) -> 192 | I18: =H18*$B$4 -> 4131.0968 | J18: =SUM(H18) -> 192 | K18: =J18*$B$4 -> 4131.0968 | L18: =SUM(J18) -> 192 | M18: =L18*$B$4 -> 4131.0968 | N18: =SUM(L18) -> 192 | O18: =N18*$B$4 -> 4131.0968 | P18: =SUM(N18) -> 192 | Q18: =P18*$B$4 -> 4131.0968 | R18: =SUM(P18) -> 192 | S18: =R18*$B$4 -> 4131.0968 | T18: =SUM(R18) -> 192 | U18: =T18*$B$4 -> 4131.0968 | V18: =SUM(T18) -> 192 | W18: =V18*$B$4 -> 4131.0968 | X18: =SUM(Y18/73370) -> 0.61935484 | Y18: =SUM(C18+E18+G18+I18+K18+M18+O18+Q18+S18+U18+W18) -> 45442.065 | Z18: ='B5'!C17 -> 198 | AA18: =SUM(Z18*$Z$4) -> 1980 | AB18: =SUM(Z18) -> 198 | AC18: =SUM(AB18*$Z$4) -> 1980 | AD18: =SUM(AB18) -> 198 | AE18: =SUM(AD18*$Z$4) -> 1980 | AF18: =SUM(AD18) -> 198 | AG18: =SUM(AF18*$Z$4) -> 1980 | AH18: =SUM(AF18) -> 198 | AI18: =SUM(AH18*$Z$4) -> 1980 | AJ18: =SUM(AH18) -> 198 | AK18: =SUM(AJ18*$Z$4) -> 1980 | AL18: =SUM(AJ18) -> 198 | AM18: =SUM(AL18*$Z$4) -> 1980 | AN18: =SUM(AO18/19600) -> 0.70714286 | AO18: =SUM(AA18+AC18+AE18+AG18+AI18+AK18+AM18) -> 13860 | AQ18: =SUM(AR18/92970) -> 0.63786237 | AR18: =SUM(AO18+Y18) -> 59302.065 | AS18: =SUM(AR18-AR17-AT18) -> -2453.4194 | AV18: =IF(AT18>0,AU18,AV17) -> 0.55 | AW18: =-SUM('B5'!AI17) -> -925.3 | AX18: =-SUM(AW18-AS18) -> -1528.1194 | AY18: =SUM(AX18+AW18) -> -2453.4194 | AZ18: =ELEC!A15 -> 0.5261 | BA18: ='General information '!D18 -> 27 | BB18: =SUM('General information '!E18) -> 0.54 | BC18: =IF(AR17>=AR18,0,1) -> 0 | BD18: 19222 | BE18: =(305/1185)*ELEC!Q16 -> 2878.8397 | BG18: =#REF!-BE18 -> #REF!
A19: =ELEC!C16 -> 43752 | B19: ='B5'!B18 -> 178 | C19: =B19*$B$4 -> 3829.871 | D19: =SUM(B19) -> 178 | E19: =D19*$B$4 -> 3829.871 | F19: =SUM(D19) -> 178 | G19: =F19*$B$4 -> 3829.871 | H19: =SUM(F19) -> 178 | I19: =H19*$B$4 -> 3829.871 | J19: =SUM(H19) -> 178 | K19: =J19*$B$4 -> 3829.871 | L19: =SUM(J19) -> 178 | M19: =L19*$B$4 -> 3829.871 | N19: =SUM(L19) -> 178 | O19: =N19*$B$4 -> 3829.871 | P19: =SUM(N19) -> 178 | Q19: =P19*$B$4 -> 3829.871 | R19: =SUM(P19) -> 178 | S19: =R19*$B$4 -> 3829.871 | T19: =SUM(R19) -> 178 | U19: =T19*$B$4 -> 3829.871 | V19: =SUM(T19) -> 178 | W19: =V19*$B$4 -> 3829.871 | X19: =SUM(Y19/73370) -> 0.57419355 | Y19: =SUM(C19+E19+G19+I19+K19+M19+O19+Q19+S19+U19+W19) -> 42128.581 | Z19: ='B5'!C18 -> 184 | AA19: =SUM(Z19*$Z$4) -> 1840 | AB19: =SUM(Z19) -> 184 | AC19: =SUM(AB19*$Z$4) -> 1840 | AD19: =SUM(AB19) -> 184 | AE19: =SUM(AD19*$Z$4) -> 1840 | AF19: =SUM(AD19) -> 184 | AG19: =SUM(AF19*$Z$4) -> 1840 | AH19: =SUM(AF19) -> 184 | AI19: =SUM(AH19*$Z$4) -> 1840 | AJ19: =SUM(AH19) -> 184 | AK19: =SUM(AJ19*$Z$4) -> 1840 | AL19: =SUM(AJ19) -> 184 | AM19: =SUM(AL19*$Z$4) -> 1840 | AN19: =SUM(AO19/19600) -> 0.65714286 | AO19: =SUM(AA19+AC19+AE19+AG19+AI19+AK19+AM19) -> 12880 | AQ19: =SUM(AR19/92970) -> 0.59168098 | AR19: =SUM(AO19+Y19) -> 55008.581 | AS19: =SUM(AR19-AR18-AT19) -> -4293.4839 | AV19: =IF(AT19>0,AU19,AV18) -> 0.55 | AW19: =-SUM('B5'!AI18) -> -708.3 | AX19: =-SUM(AW19-AS19) -> -3585.1839 | AY19: =SUM(AX19+AW19) -> -4293.4839 | AZ19: =ELEC!A16 -> 0.5826 | BA19: ='General information '!D19 -> 27 | BB19: =SUM('General information '!E19) -> 0.6 | BC19: =IF(AR18>=AR19,0,1) -> 0 | BD19: 19222 | BE19: =(305/1185)*ELEC!Q17 -> 0 | BG19: =#REF!-BE19 -> #REF!
A20: =ELEC!C17 -> 43753 | B20: ='B5'!B19 -> 178 | C20: =B20*$B$4 -> 3829.871 | D20: =SUM(B20) -> 178 | E20: =D20*$B$4 -> 3829.871 | F20: =SUM(D20) -> 178 | G20: =F20*$B$4 -> 3829.871 | H20: =SUM(F20) -> 178 | I20: =H20*$B$4 -> 3829.871 | J20: =SUM(H20) -> 178 | K20: =J20*$B$4 -> 3829.871 | L20: =SUM(J20) -> 178 | M20: =L20*$B$4 -> 3829.871 | N20: =SUM(L20) -> 178 | O20: =N20*$B$4 -> 3829.871 | P20: =SUM(N20) -> 178 | Q20: =P20*$B$4 -> 3829.871 | R20: =SUM(P20) -> 178 | S20: =R20*$B$4 -> 3829.871 | T20: =SUM(R20) -> 178 | U20: =T20*$B$4 -> 3829.871 | V20: =SUM(T20) -> 178 | W20: =V20*$B$4 -> 3829.871 | X20: =SUM(Y20/73370) -> 0.57419355 | Y20: =SUM(C20+E20+G20+I20+K20+M20+O20+Q20+S20+U20+W20) -> 42128.581 | Z20: ='B5'!C19 -> 184 | AA20: =SUM(Z20*$Z$4) -> 1840 | AB20: =SUM(Z20) -> 184 | AC20: =SUM(AB20*$Z$4) -> 1840 | AD20: =SUM(AB20) -> 184 | AE20: =SUM(AD20*$Z$4) -> 1840 | AF20: =SUM(AD20) -> 184 | AG20: =SUM(AF20*$Z$4) -> 1840 | AH20: =SUM(AF20) -> 184 | AI20: =SUM(AH20*$Z$4) -> 1840 | AJ20: =SUM(AH20) -> 184 | AK20: =SUM(AJ20*$Z$4) -> 1840 | AL20: =SUM(AJ20) -> 184 | AM20: =SUM(AL20*$Z$4) -> 1840 | AN20: =SUM(AO20/19600) -> 0.65714286 | AO20: =SUM(AA20+AC20+AE20+AG20+AI20+AK20+AM20) -> 12880 | AQ20: =SUM(AR20/92970) -> 0.59168098 | AR20: =SUM(AO20+Y20) -> 55008.581 | AS20: =SUM(AR20-AR19-AT20) -> 0 | AV20: =IF(AT20>0,AU20,AV19) -> 0.55 | AW20: =-SUM('B5'!AI19) -> 0 | AX20: =-SUM(AW20-AS20) -> 0 | AY20: =SUM(AX20+AW20) -> 0 | AZ20: =ELEC!A17 -> 0 | BA20: ='General information '!D20 -> 0 | BB20: =SUM('General information '!E20) -> 0 | BC20: =IF(AR19>=AR20,0,1) -> 0 | BD20: 19222 | BE20: =(305/1185)*ELEC!Q18 -> 0 | BG20: =#REF!-BE20 -> #REF!
A21: =ELEC!C18 -> 43754 | B21: ='B5'!B20 -> 178 | C21: =B21*$B$4 -> 3829.871 | D21: =SUM(B21) -> 178 | E21: =D21*$B$4 -> 3829.871 | F21: =SUM(D21) -> 178 | G21: =F21*$B$4 -> 3829.871 | H21: =SUM(F21) -> 178 | I21: =H21*$B$4 -> 3829.871 | J21: =SUM(H21) -> 178 | K21: =J21*$B$4 -> 3829.871 | L21: =SUM(J21) -> 178 | M21: =L21*$B$4 -> 3829.871 | N21: =SUM(L21) -> 178 | O21: =N21*$B$4 -> 3829.871 | P21: =SUM(N21) -> 178 | Q21: =P21*$B$4 -> 3829.871 | R21: =SUM(P21) -> 178 | S21: =R21*$B$4 -> 3829.871 | T21: =SUM(R21) -> 178 | U21: =T21*$B$4 -> 3829.871 | V21: =SUM(T21) -> 178 | W21: =V21*$B$4 -> 3829.871 | X21: =SUM(Y21/73370) -> 0.57419355 | Y21: =SUM(C21+E21+G21+I21+K21+M21+O21+Q21+S21+U21+W21) -> 42128.581 | Z21: ='B5'!C20 -> 184 | AA21: =SUM(Z21*$Z$4) -> 1840 | AB21: =SUM(Z21) -> 184 | AC21: =SUM(AB21*$Z$4) -> 1840 | AD21: =SUM(AB21) -> 184 | AE21: =SUM(AD21*$Z$4) -> 1840 | AF21: =SUM(AD21) -> 184 | AG21: =SUM(AF21*$Z$4) -> 1840 | AH21: =SUM(AF21) -> 184 | AI21: =SUM(AH21*$Z$4) -> 1840 | AJ21: =SUM(AH21) -> 184 | AK21: =SUM(AJ21*$Z$4) -> 1840 | AL21: =SUM(AJ21) -> 184 | AM21: =SUM(AL21*$Z$4) -> 1840 | AN21: =SUM(AO21/19600) -> 0.65714286 | AO21: =SUM(AA21+AC21+AE21+AG21+AI21+AK21+AM21) -> 12880 | AQ21: =SUM(AR21/92970) -> 0.59168098 | AR21: =SUM(AO21+Y21) -> 55008.581 | AS21: =SUM(AR21-AR20-AT21) -> 0 | AV21: =IF(AT21>0,AU21,AV20) -> 0.55 | AW21: =-SUM('B5'!AI20) -> 0 | AX21: =-SUM(AW21-AS21) -> 0 | AY21: =SUM(AX21+AW21) -> 0 | AZ21: =ELEC!A18 -> 0 | BA21: ='General information '!D21 -> 0 | BB21: =SUM('General information '!E21) -> 0 | BC21: =IF(AR20>=AR21,0,1) -> 0 | BD21: 19222 | BE21: =(305/1185)*ELEC!Q19 -> 0 | BG21: =#REF!-BE21 -> #REF!
A22: =ELEC!C19 -> 43755 | B22: ='B5'!B21 -> 178 | C22: =B22*$B$4 -> 3829.871 | D22: =SUM(B22) -> 178 | E22: =D22*$B$4 -> 3829.871 | F22: =SUM(D22) -> 178 | G22: =F22*$B$4 -> 3829.871 | H22: =SUM(F22) -> 178 | I22: =H22*$B$4 -> 3829.871 | J22: =SUM(H22) -> 178 | K22: =J22*$B$4 -> 3829.871 | L22: =SUM(J22) -> 178 | M22: =L22*$B$4 -> 3829.871 | N22: =SUM(L22) -> 178 | O22: =N22*$B$4 -> 3829.871 | P22: =SUM(N22) -> 178 | Q22: =P22*$B$4 -> 3829.871 | R22: =SUM(P22) -> 178 | S22: =R22*$B$4 -> 3829.871 | T22: =SUM(R22) -> 178 | U22: =T22*$B$4 -> 3829.871 | V22: =SUM(T22) -> 178 | W22: =V22*$B$4 -> 3829.871 | X22: =SUM(Y22/73370) -> 0.57419355 | Y22: =SUM(C22+E22+G22+I22+K22+M22+O22+Q22+S22+U22+W22) -> 42128.581 | Z22: ='B5'!C21 -> 184 | AA22: =SUM(Z22*$Z$4) -> 1840 | AB22: =SUM(Z22) -> 184 | AC22: =SUM(AB22*$Z$4) -> 1840 | AD22: =SUM(AB22) -> 184 | AE22: =SUM(AD22*$Z$4) -> 1840 | AF22: =SUM(AD22) -> 184 | AG22: =SUM(AF22*$Z$4) -> 1840 | AH22: =SUM(AF22) -> 184 | AI22: =SUM(AH22*$Z$4) -> 1840 | AJ22: =SUM(AH22) -> 184 | AK22: =SUM(AJ22*$Z$4) -> 1840 | AL22: =SUM(AJ22) -> 184 | AM22: =SUM(AL22*$Z$4) -> 1840 | AN22: =SUM(AO22/19600) -> 0.65714286 | AO22: =SUM(AA22+AC22+AE22+AG22+AI22+AK22+AM22) -> 12880 | AQ22: =SUM(AR22/92970) -> 0.59168098 | AR22: =SUM(AO22+Y22) -> 55008.581 | AS22: =SUM(AR22-AR21-AT22) -> 0 | AV22: =IF(AT22>0,AU22,AV21) -> 0.55 | AW22: =-SUM('B5'!AI21) -> 0 | AX22: =-SUM(AW22-AS22) -> 0 | AY22: =SUM(AX22+AW22) -> 0 | AZ22: =ELEC!A19 -> 0 | BA22: ='General information '!D22 -> 0 | BB22: =SUM('General information '!E22) -> 0 | BC22: =IF(AR21>=AR22,0,1) -> 0 | BD22: 19222 | BE22: =(305/1185)*ELEC!Q20 -> 0 | BG22: =#REF!-BE22 -> #REF!
A23: =ELEC!C20 -> 43756 | B23: ='B5'!B22 -> 178 | C23: =B23*$B$4 -> 3829.871 | D23: =SUM(B23) -> 178 | E23: =D23*$B$4 -> 3829.871 | F23: =SUM(D23) -> 178 | G23: =F23*$B$4 -> 3829.871 | H23: =SUM(F23) -> 178 | I23: =H23*$B$4 -> 3829.871 | J23: =SUM(H23) -> 178 | K23: =J23*$B$4 -> 3829.871 | L23: =SUM(J23) -> 178 | M23: =L23*$B$4 -> 3829.871 | N23: =SUM(L23) -> 178 | O23: =N23*$B$4 -> 3829.871 | P23: =SUM(N23) -> 178 | Q23: =P23*$B$4 -> 3829.871 | R23: =SUM(P23) -> 178 | S23: =R23*$B$4 -> 3829.871 | T23: =SUM(R23) -> 178 | U23: =T23*$B$4 -> 3829.871 | V23: =SUM(T23) -> 178 | W23: =V23*$B$4 -> 3829.871 | X23: =SUM(Y23/73370) -> 0.57419355 | Y23: =SUM(C23+E23+G23+I23+K23+M23+O23+Q23+S23+U23+W23) -> 42128.581 | Z23: ='B5'!C22 -> 184 | AA23: =SUM(Z23*$Z$4) -> 1840 | AB23: =SUM(Z23) -> 184 | AC23: =SUM(AB23*$Z$4) -> 1840 | AD23: =SUM(AB23) -> 184 | AE23: =SUM(AD23*$Z$4) -> 1840 | AF23: =SUM(AD23) -> 184 | AG23: =SUM(AF23*$Z$4) -> 1840 | AH23: =SUM(AF23) -> 184 | AI23: =SUM(AH23*$Z$4) -> 1840 | AJ23: =SUM(AH23) -> 184 | AK23: =SUM(AJ23*$Z$4) -> 1840 | AL23: =SUM(AJ23) -> 184 | AM23: =SUM(AL23*$Z$4) -> 1840 | AN23: =SUM(AO23/19600) -> 0.65714286 | AO23: =SUM(AA23+AC23+AE23+AG23+AI23+AK23+AM23) -> 12880 | AQ23: =SUM(AR23/92970) -> 0.59168098 | AR23: =SUM(AO23+Y23) -> 55008.581 | AS23: =SUM(AR23-AR22-AT23) -> 0 | AV23: =IF(AT23>0,AU23,AV22) -> 0.55 | AW23: =-SUM('B5'!AI22) -> 0 | AX23: =-SUM(AW23-AS23) -> 0 | AY23: =SUM(AX23+AW23) -> 0 | AZ23: =ELEC!A20 -> 0 | BA23: ='General information '!D23 -> 0 | BB23: =SUM('General information '!E23) -> 0 | BC23: =IF(AR22>=AR23,0,1) -> 0 | BD23: 19222 | BE23: =(305/1185)*ELEC!Q21 -> 0 | BG23: =#REF!-BE23 -> #REF!
A24: =ELEC!C21 -> 43757 | B24: ='B5'!B23 -> 178 | C24: =B24*$B$4 -> 3829.871 | D24: =SUM(B24) -> 178 | E24: =D24*$B$4 -> 3829.871 | F24: =SUM(D24) -> 178 | G24: =F24*$B$4 -> 3829.871 | H24: =SUM(F24) -> 178 | I24: =H24*$B$4 -> 3829.871 | J24: =SUM(H24) -> 178 | K24: =J24*$B$4 -> 3829.871 | L24: =SUM(J24) -> 178 | M24: =L24*$B$4 -> 3829.871 | N24: =SUM(L24) -> 178 | O24: =N24*$B$4 -> 3829.871 | P24: =SUM(N24) -> 178 | Q24: =P24*$B$4 -> 3829.871 | R24: =SUM(P24) -> 178 | S24: =R24*$B$4 -> 3829.871 | T24: =SUM(R24) -> 178 | U24: =T24*$B$4 -> 3829.871 | V24: =SUM(T24) -> 178 | W24: =V24*$B$4 -> 3829.871 | X24: =SUM(Y24/73370) -> 0.57419355 | Y24: =SUM(C24+E24+G24+I24+K24+M24+O24+Q24+S24+U24+W24) -> 42128.581 | Z24: ='B5'!C23 -> 184 | AA24: =SUM(Z24*$Z$4) -> 1840 | AB24: =SUM(Z24) -> 184 | AC24: =SUM(AB24*$Z$4) -> 1840 | AD24: =SUM(AB24) -> 184 | AE24: =SUM(AD24*$Z$4) -> 1840 | AF24: =SUM(AD24) -> 184 | AG24: =SUM(AF24*$Z$4) -> 1840 | AH24: =SUM(AF24) -> 184 | AI24: =SUM(AH24*$Z$4) -> 1840 | AJ24: =SUM(AH24) -> 184 | AK24: =SUM(AJ24*$Z$4) -> 1840 | AL24: =SUM(AJ24) -> 184 | AM24: =SUM(AL24*$Z$4) -> 1840 | AN24: =SUM(AO24/19600) -> 0.65714286 | AO24: =SUM(AA24+AC24+AE24+AG24+AI24+AK24+AM24) -> 12880 | AQ24: =SUM(AR24/92970) -> 0.59168098 | AR24: =SUM(AO24+Y24) -> 55008.581 | AS24: =SUM(AR24-AR23-AT24) -> 0 | AV24: =IF(AT24>0,AU24,AV23) -> 0.55 | AW24: =-SUM('B5'!AI23) -> 0 | AX24: =-SUM(AW24-AS24) -> 0 | AY24: =SUM(AX24+AW24) -> 0 | AZ24: =ELEC!A21 -> 0 | BA24: ='General information '!D24 -> 0 | BB24: =SUM('General information '!E24) -> 0 | BC24: =IF(AR23>=AR24,0,1) -> 0 | BD24: 19222 | BE24: =(305/1185)*ELEC!Q22 -> 0 | BG24: =#REF!-BE24 -> #REF!
A25: =ELEC!C22 -> 43758 | B25: ='B5'!B24 -> 178 | C25: =B25*$B$4 -> 3829.871 | D25: =SUM(B25) -> 178 | E25: =D25*$B$4 -> 3829.871 | F25: =SUM(D25) -> 178 | G25: =F25*$B$4 -> 3829.871 | H25: =SUM(F25) -> 178 | I25: =H25*$B$4 -> 3829.871 | J25: =SUM(H25) -> 178 | K25: =J25*$B$4 -> 3829.871 | L25: =SUM(J25) -> 178 | M25: =L25*$B$4 -> 3829.871 | N25: =SUM(L25) -> 178 | O25: =N25*$B$4 -> 3829.871 | P25: =SUM(N25) -> 178 | Q25: =P25*$B$4 -> 3829.871 | R25: =SUM(P25) -> 178 | S25: =R25*$B$4 -> 3829.871 | T25: =SUM(R25) -> 178 | U25: =T25*$B$4 -> 3829.871 | V25: =SUM(T25) -> 178 | W25: =V25*$B$4 -> 3829.871 | X25: =SUM(Y25/73370) -> 0.57419355 | Y25: =SUM(C25+E25+G25+I25+K25+M25+O25+Q25+S25+U25+W25) -> 42128.581 | Z25: ='B5'!C24 -> 184 | AA25: =SUM(Z25*$Z$4) -> 1840 | AB25: =SUM(Z25) -> 184 | AC25: =SUM(AB25*$Z$4) -> 1840 | AD25: =SUM(AB25) -> 184 | AE25: =SUM(AD25*$Z$4) -> 1840 | AF25: =SUM(AD25) -> 184 | AG25: =SUM(AF25*$Z$4) -> 1840 | AH25: =SUM(AF25) -> 184 | AI25: =SUM(AH25*$Z$4) -> 1840 | AJ25: =SUM(AH25) -> 184 | AK25: =SUM(AJ25*$Z$4) -> 1840 | AL25: =SUM(AJ25) -> 184 | AM25: =SUM(AL25*$Z$4) -> 1840 | AN25: =SUM(AO25/19600) -> 0.65714286 | AO25: =SUM(AA25+AC25+AE25+AG25+AI25+AK25+AM25) -> 12880 | AQ25: =SUM(AR25/92970) -> 0.59168098 | AR25: =SUM(AO25+Y25) -> 55008.581 | AS25: =SUM(AR25-AR24-AT25) -> 0 | AV25: =IF(AT25>0,AU25,AV24) -> 0.55 | AW25: =-SUM('B5'!AI24) -> 0 | AX25: =-SUM(AW25-AS25) -> 0 | AY25: =SUM(AX25+AW25) -> 0 | AZ25: =ELEC!A22 -> 0 | BA25: ='General information '!D25 -> 0 | BB25: =SUM('General information '!E25) -> 0 | BC25: =IF(AR24>=AR25,0,1) -> 0 | BD25: 19222 | BE25: =(305/1185)*ELEC!Q23 -> 0 | BG25: =#REF!-BE25 -> #REF!
A26: =ELEC!C23 -> 43759 | B26: ='B5'!B25 -> 178 | C26: =B26*$B$4 -> 3829.871 | D26: =SUM(B26) -> 178 | E26: =D26*$B$4 -> 3829.871 | F26: =SUM(D26) -> 178 | G26: =F26*$B$4 -> 3829.871 | H26: =SUM(F26) -> 178 | I26: =H26*$B$4 -> 3829.871 | J26: =SUM(H26) -> 178 | K26: =J26*$B$4 -> 3829.871 | L26: =SUM(J26) -> 178 | M26: =L26*$B$4 -> 3829.871 | N26: =SUM(L26) -> 178 | O26: =N26*$B$4 -> 3829.871 | P26: =SUM(N26) -> 178 | Q26: =P26*$B$4 -> 3829.871 | R26: =SUM(P26) -> 178 | S26: =R26*$B$4 -> 3829.871 | T26: =SUM(R26) -> 178 | U26: =T26*$B$4 -> 3829.871 | V26: =SUM(T26) -> 178 | W26: =V26*$B$4 -> 3829.871 | X26: =SUM(Y26/73370) -> 0.57419355 | Y26: =SUM(C26+E26+G26+I26+K26+M26+O26+Q26+S26+U26+W26) -> 42128.581 | Z26: ='B5'!C25 -> 184 | AA26: =SUM(Z26*$Z$4) -> 1840 | AB26: =SUM(Z26) -> 184 | AC26: =SUM(AB26*$Z$4) -> 1840 | AD26: =SUM(AB26) -> 184 | AE26: =SUM(AD26*$Z$4) -> 1840 | AF26: =SUM(AD26) -> 184 | AG26: =SUM(AF26*$Z$4) -> 1840 | AH26: =SUM(AF26) -> 184 | AI26: =SUM(AH26*$Z$4) -> 1840 | AJ26: =SUM(AH26) -> 184 | AK26: =SUM(AJ26*$Z$4) -> 1840 | AL26: =SUM(AJ26) -> 184 | AM26: =SUM(AL26*$Z$4) -> 1840 | AN26: =SUM(AO26/19600) -> 0.65714286 | AO26: =SUM(AA26+AC26+AE26+AG26+AI26+AK26+AM26) -> 12880 | AQ26: =SUM(AR26/92970) -> 0.59168098 | AR26: =SUM(AO26+Y26) -> 55008.581 | AS26: =SUM(AR26-AR25-AT26) -> 0 | AV26: =IF(AT26>0,AU26,AV25) -> 0.55 | AW26: =-SUM('B5'!AI25) -> 0 | AX26: =-SUM(AW26-AS26) -> 0 | AY26: =SUM(AX26+AW26) -> 0 | AZ26: =ELEC!A23 -> 0 | BA26: ='General information '!D26 -> 0 | BB26: =SUM('General information '!E26) -> 0 | BC26: =IF(AR25>=AR26,0,1) -> 0 | BD26: 19222 | BE26: =(305/1185)*ELEC!Q24 -> 0 | BG26: =#REF!-BE26 -> #REF!
A27: =ELEC!C24 -> 43760 | B27: ='B5'!B26 -> 178 | C27: =B27*$B$4 -> 3829.871 | D27: =SUM(B27) -> 178 | E27: =D27*$B$4 -> 3829.871 | F27: =SUM(D27) -> 178 | G27: =F27*$B$4 -> 3829.871 | H27: =SUM(F27) -> 178 | I27: =H27*$B$4 -> 3829.871 | J27: =SUM(H27) -> 178 | K27: =J27*$B$4 -> 3829.871 | L27: =SUM(J27) -> 178 | M27: =L27*$B$4 -> 3829.871 | N27: =SUM(L27) -> 178 | O27: =N27*$B$4 -> 3829.871 | P27: =SUM(N27) -> 178 | Q27: =P27*$B$4 -> 3829.871 | R27: =SUM(P27) -> 178 | S27: =R27*$B$4 -> 3829.871 | T27: =SUM(R27) -> 178 | U27: =T27*$B$4 -> 3829.871 | V27: =SUM(T27) -> 178 | W27: =V27*$B$4 -> 3829.871 | X27: =SUM(Y27/73370) -> 0.57419355 | Y27: =SUM(C27+E27+G27+I27+K27+M27+O27+Q27+S27+U27+W27) -> 42128.581 | Z27: ='B5'!C26 -> 184 | AA27: =SUM(Z27*$Z$4) -> 1840 | AB27: =SUM(Z27) -> 184 | AC27: =SUM(AB27*$Z$4) -> 1840 | AD27: =SUM(AB27) -> 184 | AE27: =SUM(AD27*$Z$4) -> 1840 | AF27: =SUM(AD27) -> 184 | AG27: =SUM(AF27*$Z$4) -> 1840 | AH27: =SUM(AF27) -> 184 | AI27: =SUM(AH27*$Z$4) -> 1840 | AJ27: =SUM(AH27) -> 184 | AK27: =SUM(AJ27*$Z$4) -> 1840 | AL27: =SUM(AJ27) -> 184 | AM27: =SUM(AL27*$Z$4) -> 1840 | AN27: =SUM(AO27/19600) -> 0.65714286 | AO27: =SUM(AA27+AC27+AE27+AG27+AI27+AK27+AM27) -> 12880 | AQ27: =SUM(AR27/92970) -> 0.59168098 | AR27: =SUM(AO27+Y27) -> 55008.581 | AS27: =SUM(AR27-AR26-AT27) -> 0 | AV27: =IF(AT27>0,AU27,AV26) -> 0.55 | AW27: =-SUM('B5'!AI26) -> 0 | AX27: =-SUM(AW27-AS27) -> 0 | AY27: =SUM(AX27+AW27) -> 0 | AZ27: =ELEC!A24 -> 0 | BA27: ='General information '!D27 -> 0 | BB27: =SUM('General information '!E27) -> 0 | BC27: =IF(AR26>=AR27,0,1) -> 0 | BD27: 19222 | BE27: =(305/1185)*ELEC!Q25 -> 0 | BG27: =#REF!-BE27 -> #REF!
A28: =ELEC!C25 -> 43761 | B28: ='B5'!B27 -> 178 | C28: =B28*$B$4 -> 3829.871 | D28: =SUM(B28) -> 178 | E28: =D28*$B$4 -> 3829.871 | F28: =SUM(D28) -> 178 | G28: =F28*$B$4 -> 3829.871 | H28: =SUM(F28) -> 178 | I28: =H28*$B$4 -> 3829.871 | J28: =SUM(H28) -> 178 | K28: =J28*$B$4 -> 3829.871 | L28: =SUM(J28) -> 178 | M28: =L28*$B$4 -> 3829.871 | N28: =SUM(L28) -> 178 | O28: =N28*$B$4 -> 3829.871 | P28: =SUM(N28) -> 178 | Q28: =P28*$B$4 -> 3829.871 | R28: =SUM(P28) -> 178 | S28: =R28*$B$4 -> 3829.871 | T28: =SUM(R28) -> 178 | U28: =T28*$B$4 -> 3829.871 | V28: =SUM(T28) -> 178 | W28: =V28*$B$4 -> 3829.871 | X28: =SUM(Y28/73370) -> 0.57419355 | Y28: =SUM(C28+E28+G28+I28+K28+M28+O28+Q28+S28+U28+W28) -> 42128.581 | Z28: ='B5'!C27 -> 184 | AA28: =SUM(Z28*$Z$4) -> 1840 | AB28: =SUM(Z28) -> 184 | AC28: =SUM(AB28*$Z$4) -> 1840 | AD28: =SUM(AB28) -> 184 | AE28: =SUM(AD28*$Z$4) -> 1840 | AF28: =SUM(AD28) -> 184 | AG28: =SUM(AF28*$Z$4) -> 1840 | AH28: =SUM(AF28) -> 184 | AI28: =SUM(AH28*$Z$4) -> 1840 | AJ28: =SUM(AH28) -> 184 | AK28: =SUM(AJ28*$Z$4) -> 1840 | AL28: =SUM(AJ28) -> 184 | AM28: =SUM(AL28*$Z$4) -> 1840 | AN28: =SUM(AO28/19600) -> 0.65714286 | AO28: =SUM(AA28+AC28+AE28+AG28+AI28+AK28+AM28) -> 12880 | AQ28: =SUM(AR28/92970) -> 0.59168098 | AR28: =SUM(AO28+Y28) -> 55008.581 | AS28: =SUM(AR28-AR27-AT28) -> 0 | AV28: =IF(AT28>0,AU28,AV27) -> 0.55 | AW28: =-SUM('B5'!AI27) -> 0 | AX28: =-SUM(AW28-AS28) -> 0 | AY28: =SUM(AX28+AW28) -> 0 | AZ28: =ELEC!A25 -> 0 | BA28: ='General information '!D28 -> 0 | BB28: =SUM('General information '!E28) -> 0 | BC28: =IF(AR27>=AR28,0,1) -> 0 | BD28: 19222 | BE28: =(305/1185)*ELEC!Q26 -> 0 | BG28: =#REF!-BE28 -> #REF!
... A30: =ELEC!C27 -> 43763 | B30: ='B5'!B29 -> 178 | C30: =B30*$B$4 -> 3829.871 | D30: =SUM(B30) -> 178 | E30: =D30*$B$4 -> 3829.871 | F30: =SUM(D30) -> 178 | G30: =F30*$B$4 -> 3829.871 | H30: =SUM(F30) -> 178 | I30: =H30*$B$4 -> 3829.871 | J30: =SUM(H30) -> 178 | K30: =J30*$B$4 -> 3829.871 | L30: =SUM(J30) -> 178 | M30: =L30*$B$4 -> 3829.871 | N30: =SUM(L30) -> 178 | O30: =N30*$B$4 -> 3829.871 | P30: =SUM(N30) -> 178 | Q30: =P30*$B$4 -> 3829.871 | R30: =SUM(P30) -> 178 | S30: =R30*$B$4 -> 3829.871 | T30: =SUM(R30) -> 178 | U30: =T30*$B$4 -> 3829.871 | V30: =SUM(T30) -> 178 | W30: =V30*$B$4 -> 3829.871 | X30: =SUM(Y30/73370) -> 0.57419355 | Y30: =SUM(C30+E30+G30+I30+K30+M30+O30+Q30+S30+U30+W30) -> 42128.581 | Z30: ='B5'!C29 -> 184 | AA30: =SUM(Z30*$Z$4) -> 1840 | AB30: =SUM(Z30) -> 184 | AC30: =SUM(AB30*$Z$4) -> 1840 | AD30: =SUM(AB30) -> 184 | AE30: =SUM(AD30*$Z$4) -> 1840 | AF30: =SUM(AD30) -> 184 | AG30: =SUM(AF30*$Z$4) -> 1840 | AH30: =SUM(AF30) -> 184 | AI30: =SUM(AH30*$Z$4) -> 1840 | AJ30: =SUM(AH30) -> 184 | AK30: =SUM(AJ30*$Z$4) -> 1840 | AL30: =SUM(AJ30) -> 184 | AM30: =SUM(AL30*$Z$4) -> 1840 | AN30: =SUM(AO30/19600) -> 0.65714286 | AO30: =SUM(AA30+AC30+AE30+AG30+AI30+AK30+AM30) -> 12880 | AQ30: =SUM(AR30/92970) -> 0.59168098 | AR30: =SUM(AO30+Y30) -> 55008.581 | AS30: =SUM(AR30-AR29-AT30) -> 0 | AV30: =IF(AT30>0,AU30,AV29) -> 0.55 | AW30: =-SUM('B5'!AI29) -> 0 | AX30: =-SUM(AW30-AS30) -> 0 | AY30: =SUM(AX30+AW30) -> 0 | AZ30: =ELEC!A27 -> 0 | BA30: ='General information '!D30 -> 0 | BB30: =SUM('General information '!E30) -> 0 | BC30: =IF(AR29>=AR30,0,1) -> 0 | BD30: 19222 | BE30: =(305/1185)*ELEC!Q28 -> 0 | BG30: =#REF!-BE30 -> #REF!
A31: =ELEC!C28 -> 43764 | B31: ='B5'!B30 -> 178 | C31: =B31*$B$4 -> 3829.871 | D31: =SUM(B31) -> 178 | E31: =D31*$B$4 -> 3829.871 | F31: =SUM(D31) -> 178 | G31: =F31*$B$4 -> 3829.871 | H31: =SUM(F31) -> 178 | I31: =H31*$B$4 -> 3829.871 | J31: =SUM(H31) -> 178 | K31: =J31*$B$4 -> 3829.871 | L31: =SUM(J31) -> 178 | M31: =L31*$B$4 -> 3829.871 | N31: =SUM(L31) -> 178 | O31: =N31*$B$4 -> 3829.871 | P31: =SUM(N31) -> 178 | Q31: =P31*$B$4 -> 3829.871 | R31: =SUM(P31) -> 178 | S31: =R31*$B$4 -> 3829.871 | T31: =SUM(R31) -> 178 | U31: =T31*$B$4 -> 3829.871 | V31: =SUM(T31) -> 178 | W31: =V31*$B$4 -> 3829.871 | X31: =SUM(Y31/73370) -> 0.57419355 | Y31: =SUM(C31+E31+G31+I31+K31+M31+O31+Q31+S31+U31+W31) -> 42128.581 | Z31: ='B5'!C30 -> 184 | AA31: =SUM(Z31*$Z$4) -> 1840 | AB31: =SUM(Z31) -> 184 | AC31: =SUM(AB31*$Z$4) -> 1840 | AD31: =SUM(AB31) -> 184 | AE31: =SUM(AD31*$Z$4) -> 1840 | AF31: =SUM(AD31) -> 184 | AG31: =SUM(AF31*$Z$4) -> 1840 | AH31: =SUM(AF31) -> 184 | AI31: =SUM(AH31*$Z$4) -> 1840 | AJ31: =SUM(AH31) -> 184 | AK31: =SUM(AJ31*$Z$4) -> 1840 | AL31: =SUM(AJ31) -> 184 | AM31: =SUM(AL31*$Z$4) -> 1840 | AN31: =SUM(AO31/19600) -> 0.65714286 | AO31: =SUM(AA31+AC31+AE31+AG31+AI31+AK31+AM31) -> 12880 | AQ31: =SUM(AR31/92970) -> 0.59168098 | AR31: =SUM(AO31+Y31) -> 55008.581 | AS31: =SUM(AR31-AR30-AT31) -> 0 | AV31: =IF(AT31>0,AU31,AV30) -> 0.55 | AW31: =-SUM('B5'!AI30) -> 0 | AX31: =-SUM(AW31-AS31) -> 0 | AY31: =SUM(AX31+AW31) -> 0 | AZ31: =ELEC!A28 -> 0 | BA31: ='General information '!D31 -> 0 | BB31: =SUM('General information '!E32) -> 0 | BC31: =IF(AR30>=AR31,0,1) -> 0 | BD31: 19222 | BE31: =(305/1185)*ELEC!Q29 -> 0 | BG31: =#REF!-BE31 -> #REF!
A32: =ELEC!C29 -> 43765 | B32: ='B5'!B31 -> 178 | C32: =B32*$B$4 -> 3829.871 | D32: =SUM(B32) -> 178 | E32: =D32*$B$4 -> 3829.871 | F32: =SUM(D32) -> 178 | G32: =F32*$B$4 -> 3829.871 | H32: =SUM(F32) -> 178 | I32: =H32*$B$4 -> 3829.871 | J32: =SUM(H32) -> 178 | K32: =J32*$B$4 -> 3829.871 | L32: =SUM(J32) -> 178 | M32: =L32*$B$4 -> 3829.871 | N32: =SUM(L32) -> 178 | O32: =N32*$B$4 -> 3829.871 | P32: =SUM(N32) -> 178 | Q32: =P32*$B$4 -> 3829.871 | R32: =SUM(P32) -> 178 | S32: =R32*$B$4 -> 3829.871 | T32: =SUM(R32) -> 178 | U32: =T32*$B$4 -> 3829.871 | V32: =SUM(T32) -> 178 | W32: =V32*$B$4 -> 3829.871 | X32: =SUM(Y32/73370) -> 0.57419355 | Y32: =SUM(C32+E32+G32+I32+K32+M32+O32+Q32+S32+U32+W32) -> 42128.581 | Z32: ='B5'!C31 -> 184 | AA32: =SUM(Z32*$Z$4) -> 1840 | AB32: =SUM(Z32) -> 184 | AC32: =SUM(AB32*$Z$4) -> 1840 | AD32: =SUM(AB32) -> 184 | AE32: =SUM(AD32*$Z$4) -> 1840 | AF32: =SUM(AD32) -> 184 | AG32: =SUM(AF32*$Z$4) -> 1840 | AH32: =SUM(AF32) -> 184 | AI32: =SUM(AH32*$Z$4) -> 1840 | AJ32: =SUM(AH32) -> 184 | AK32: =SUM(AJ32*$Z$4) -> 1840 | AL32: =SUM(AJ32) -> 184 | AM32: =SUM(AL32*$Z$4) -> 1840 | AN32: =SUM(AO32/19600) -> 0.65714286 | AO32: =SUM(AA32+AC32+AE32+AG32+AI32+AK32+AM32) -> 12880 | AQ32: =SUM(AR32/92970) -> 0.59168098 | AR32: =SUM(AO32+Y32) -> 55008.581 | AS32: =SUM(AR32-AR31-AT32) -> 0 | AV32: =IF(AT32>0,AU32,AV31) -> 0.55 | AW32: =-SUM('B5'!AI31) -> 0 | AX32: =-SUM(AW32-AS32) -> 0 | AY32: =SUM(AX32+AW32) -> 0 | AZ32: =ELEC!A29 -> 0 | BA32: ='General information '!D32 -> 0 | BB32: =SUM('General information '!E33) -> 0 | BC32: =IF(AR31>=AR32,0,1) -> 0 | BD32: 19222 | BE32: =(305/1185)*ELEC!Q30 -> 0 | BG32: =#REF!-BE32 -> #REF!
A33: =ELEC!C30 -> 43766 | B33: ='B5'!B32 -> 178 | C33: =B33*$B$4 -> 3829.871 | D33: =SUM(B33) -> 178 | E33: =D33*$B$4 -> 3829.871 | F33: =SUM(D33) -> 178 | G33: =F33*$B$4 -> 3829.871 | H33: =SUM(F33) -> 178 | I33: =H33*$B$4 -> 3829.871 | J33: =SUM(H33) -> 178 | K33: =J33*$B$4 -> 3829.871 | L33: =SUM(J33) -> 178 | M33: =L33*$B$4 -> 3829.871 | N33: =SUM(L33) -> 178 | O33: =N33*$B$4 -> 3829.871 | P33: =SUM(N33) -> 178 | Q33: =P33*$B$4 -> 3829.871 | R33: =SUM(P33) -> 178 | S33: =R33*$B$4 -> 3829.871 | T33: =SUM(R33) -> 178 | U33: =T33*$B$4 -> 3829.871 | V33: =SUM(T33) -> 178 | W33: =V33*$B$4 -> 3829.871 | X33: =SUM(Y33/73370) -> 0.57419355 | Y33: =SUM(C33+E33+G33+I33+K33+M33+O33+Q33+S33+U33+W33) -> 42128.581 | Z33: ='B5'!C32 -> 184 | AA33: =SUM(Z33*$Z$4) -> 1840 | AB33: =SUM(Z33) -> 184 | AC33: =SUM(AB33*$Z$4) -> 1840 | AD33: =SUM(AB33) -> 184 | AE33: =SUM(AD33*$Z$4) -> 1840 | AF33: =SUM(AD33) -> 184 | AG33: =SUM(AF33*$Z$4) -> 1840 | AH33: =SUM(AF33) -> 184 | AI33: =SUM(AH33*$Z$4) -> 1840 | AJ33: =SUM(AH33) -> 184 | AK33: =SUM(AJ33*$Z$4) -> 1840 | AL33: =SUM(AJ33) -> 184 | AM33: =SUM(AL33*$Z$4) -> 1840 | AN33: =SUM(AO33/19600) -> 0.65714286 | AO33: =SUM(AA33+AC33+AE33+AG33+AI33+AK33+AM33) -> 12880 | AQ33: =SUM(AR33/92970) -> 0.59168098 | AR33: =SUM(AO33+Y33) -> 55008.581 | AS33: =SUM(AR33-AR32-AT33) -> 0 | AV33: =IF(AT33>0,AU33,AV32) -> 0.55 | AW33: =-SUM('B5'!AI32) -> 0 | AX33: =-SUM(AW33-AS33) -> 0 | AY33: =SUM(AX33+AW33) -> 0 | AZ33: =ELEC!A30 -> 0 | BA33: ='General information '!D33 -> 0 | BB33: =SUM('General information '!E33) -> 0 | BC33: =IF(AR32>=AR33,0,1) -> 0 | BD33: 19222 | BE33: =(305/1185)*ELEC!Q31 -> 0 | BG33: =#REF!-BE33 -> #REF!
A34: =ELEC!C31 -> 43767 | B34: ='B5'!B33 -> 178 | C34: =B34*$B$4 -> 3829.871 | D34: =SUM(B34) -> 178 | E34: =D34*$B$4 -> 3829.871 | F34: =SUM(D34) -> 178 | G34: =F34*$B$4 -> 3829.871 | H34: =SUM(F34) -> 178 | I34: =H34*$B$4 -> 3829.871 | J34: =SUM(H34) -> 178 | K34: =J34*$B$4 -> 3829.871 | L34: =SUM(J34) -> 178 | M34: =L34*$B$4 -> 3829.871 | N34: =SUM(L34) -> 178 | O34: =N34*$B$4 -> 3829.871 | P34: =SUM(N34) -> 178 | Q34: =P34*$B$4 -> 3829.871 | R34: =SUM(P34) -> 178 | S34: =R34*$B$4 -> 3829.871 | T34: =SUM(R34) -> 178 | U34: =T34*$B$4 -> 3829.871 | V34: =SUM(T34) -> 178 | W34: =V34*$B$4 -> 3829.871 | X34: =SUM(Y34/73370) -> 0.57419355 | Y34: =SUM(C34+E34+G34+I34+K34+M34+O34+Q34+S34+U34+W34) -> 42128.581 | Z34: ='B5'!C33 -> 184 | AA34: =SUM(Z34*$Z$4) -> 1840 | AB34: =SUM(Z34) -> 184 | AC34: =SUM(AB34*$Z$4) -> 1840 | AD34: =SUM(AB34) -> 184 | AE34: =SUM(AD34*$Z$4) -> 1840 | AF34: =SUM(AD34) -> 184 | AG34: =SUM(AF34*$Z$4) -> 1840 | AH34: =SUM(AF34) -> 184 | AI34: =SUM(AH34*$Z$4) -> 1840 | AJ34: =SUM(AH34) -> 184 | AK34: =SUM(AJ34*$Z$4) -> 1840 | AL34: =SUM(AJ34) -> 184 | AM34: =SUM(AL34*$Z$4) -> 1840 | AN34: =SUM(AO34/19600) -> 0.65714286 | AO34: =SUM(AA34+AC34+AE34+AG34+AI34+AK34+AM34) -> 12880 | AQ34: =SUM(AR34/92970) -> 0.59168098 | AR34: =SUM(AO34+Y34) -> 55008.581 | AS34: =SUM(AR34-AR33-AT34) -> 0 | AV34: =IF(AT34>0,AU34,AV33) -> 0.55 | AW34: =-SUM('B5'!AI33) -> 0 | AX34: =-SUM(AW34-AS34) -> 0 | AY34: =SUM(AX34+AW34) -> 0 | AZ34: =ELEC!A31 -> 0 | BA34: ='General information '!D34 -> 0 | BB34: =SUM('General information '!E34) -> 0 | BC34: =IF(AR33>=AR34,0,1) -> 0 | BD34: 19222 | BE34: =(305/1185)*ELEC!#REF! -> #REF! | BG34: =#REF!-BE34 -> #REF!
A35: =ELEC!C32 -> 43768 | B35: ='B5'!B34 -> 178 | C35: =B35*$B$4 -> 3829.871 | D35: =SUM(B35) -> 178 | E35: =D35*$B$4 -> 3829.871 | F35: =SUM(D35) -> 178 | G35: =F35*$B$4 -> 3829.871 | H35: =SUM(F35) -> 178 | I35: =H35*$B$4 -> 3829.871 | J35: =SUM(H35) -> 178 | K35: =J35*$B$4 -> 3829.871 | L35: =SUM(J35) -> 178 | M35: =L35*$B$4 -> 3829.871 | N35: =SUM(L35) -> 178 | O35: =N35*$B$4 -> 3829.871 | P35: =SUM(N35) -> 178 | Q35: =P35*$B$4 -> 3829.871 | R35: =SUM(P35) -> 178 | S35: =R35*$B$4 -> 3829.871 | T35: =SUM(R35) -> 178 | U35: =T35*$B$4 -> 3829.871 | V35: =SUM(T35) -> 178 | W35: =V35*$B$4 -> 3829.871 | X35: =SUM(Y35/73370) -> 0.57419355 | Y35: =SUM(C35+E35+G35+I35+K35+M35+O35+Q35+S35+U35+W35) -> 42128.581 | Z35: ='B5'!C34 -> 184 | AA35: =SUM(Z35*$Z$4) -> 1840 | AB35: =SUM(Z35) -> 184 | AC35: =SUM(AB35*$Z$4) -> 1840 | AD35: =SUM(AB35) -> 184 | AE35: =SUM(AD35*$Z$4) -> 1840 | AF35: =SUM(AD35) -> 184 | AG35: =SUM(AF35*$Z$4) -> 1840 | AH35: =SUM(AF35) -> 184 | AI35: =SUM(AH35*$Z$4) -> 1840 | AJ35: =SUM(AH35) -> 184 | AK35: =SUM(AJ35*$Z$4) -> 1840 | AL35: =SUM(AJ35) -> 184 | AM35: =SUM(AL35*$Z$4) -> 1840 | AN35: =SUM(AO35/19600) -> 0.65714286 | AO35: =SUM(AA35+AC35+AE35+AG35+AI35+AK35+AM35) -> 12880 | AQ35: =SUM(AR35/92970) -> 0.59168098 | AR35: =SUM(AO35+Y35) -> 55008.581 | AS35: =SUM(AR35-AR34-AT35) -> 0 | AV35: =IF(AT35>0,AU35,AV34) -> 0.55 | AW35: =-SUM('B5'!AI34) -> 0 | AX35: =-SUM(AW35-AS35) -> 0 | AY35: =SUM(AX35+AW35) -> 0 | AZ35: =ELEC!A32 -> 0 | BA35: ='General information '!D35 -> 0 | BB35: =SUM('General information '!E35) -> 0 | BC35: =IF(AR34>=AR35,0,1) -> 0 | BD35: 19222 | BE35: =(305/1185)*ELEC!#REF! -> #REF! | BG35: =#REF!-BE35 -> #REF!
A36: =ELEC!C33 -> 43769 | B36: ='B5'!B35 -> 178 | C36: =B36*$B$4 -> 3829.871 | D36: =SUM(B36) -> 178 | E36: =D36*$B$4 -> 3829.871 | F36: =SUM(D36) -> 178 | G36: =F36*$B$4 -> 3829.871 | H36: =SUM(F36) -> 178 | I36: =H36*$B$4 -> 3829.871 | J36: =SUM(H36) -> 178 | K36: =J36*$B$4 -> 3829.871 | L36: =SUM(J36) -> 178 | M36: =L36*$B$4 -> 3829.871 | N36: =SUM(L36) -> 178 | O36: =N36*$B$4 -> 3829.871 | P36: =SUM(N36) -> 178 | Q36: =P36*$B$4 -> 3829.871 | R36: =SUM(P36) -> 178 | S36: =R36*$B$4 -> 3829.871 | T36: =SUM(R36) -> 178 | U36: =T36*$B$4 -> 3829.871 | V36: =SUM(T36) -> 178 | W36: =V36*$B$4 -> 3829.871 | X36: =SUM(Y36/73370) -> 0.57419355 | Y36: =SUM(C36+E36+G36+I36+K36+M36+O36+Q36+S36+U36+W36) -> 42128.581 | Z36: ='B5'!C35 -> 184 | AA36: =SUM(Z36*$Z$4) -> 1840 | AB36: =SUM(Z36) -> 184 | AC36: =SUM(AB36*$Z$4) -> 1840 | AD36: =SUM(AB36) -> 184 | AE36: =SUM(AD36*$Z$4) -> 1840 | AF36: =SUM(AD36) -> 184 | AG36: =SUM(AF36*$Z$4) -> 1840 | AH36: =SUM(AF36) -> 184 | AI36: =SUM(AH36*$Z$4) -> 1840 | AJ36: =SUM(AH36) -> 184 | AK36: =SUM(AJ36*$Z$4) -> 1840 | AL36: =SUM(AJ36) -> 184 | AM36: =SUM(AL36*$Z$4) -> 1840 | AN36: =SUM(AO36/19600) -> 0.65714286 | AO36: =SUM(AA36+AC36+AE36+AG36+AI36+AK36+AM36) -> 12880 | AQ36: =SUM(AR36/92970) -> 0.59168098 | AR36: =SUM(AO36+Y36) -> 55008.581 | AS36: =SUM(AR36-AR35-AT36) -> 0 | AV36: =IF(AT36>0,AU36,AV35) -> 0.55 | AW36: =-SUM('B5'!AI35) -> 0 | AX36: =-SUM(AW36-AS36) -> 0 | AY36: =SUM(AX36+AW36) -> 0 | AZ36: =ELEC!A33 -> 0 | BA36: ='General information '!D36 -> 0 | BB36: =SUM('General information '!E36) -> 0
AR37: NB delivery | AS37: =COUNT(AT6:AT36) -> 2 | AT37: =SUM(AT6:AT36) -> 35056 | AU37: =SUM(AU6:AU36)/AS37 -> 0.54833 | AX37: =SUM(AX6:AX36) -> -31034.658 | AY37: =SUM(AY6:AY36) -> -43186.258
AT38: =+AT37*AU37 -> 19222.256
AS40: =SUM(AS6:AS36)/'EDl log'!A36 -> -3084.7327

Sheet GEN
B1: GEN1 | C1: RUN HR | D1: Fuel Counter Index | E1: Cons /day | F1: Diesel L/H | H1: next service | I1: ALARM | J1: GEN2 | K1: RUN HR | L1: Fuel Counter Index | M1: Cons /day | N1: Diesel L/H | P1: next service | Q1: ALARM | R1: GEN3 | S1: RUN HR | T1: Fuel Counter Index | U1: Cons /day | V1: Diesel L/H | X1: next service | Y1: ALARM | Z1: RH total | AA1: Gen Con /day | AB1: Total Deisel Cons/day | AC1: H /L | AD1: TOAL KW GEN | AI1: fuel Consuption | AK1: AVG KW/h
A2: =ELEC!C2 -> 43738 | B2: =[1]GEN!B32 -> 8418 | C2: =[1]GEN!C32 -> 0 | D2: =[1]GEN!D32 -> 108878.3 | E2: =[1]GEN!E32 -> 0 | F2: =[1]GEN!F32 -> 0 | G2: =[1]GEN!G32 -> 0 | H2: =[1]GEN!H32 -> 8517 | I2: =[1]GEN!I32 -> ok | ... AK2: =[1]GEN!AK32 -> 151.25598
A3: =ELEC!C3 -> 43739 | B3: 8418 | C3: =B3-B2 -> 0 | D3: 108878 | E3: =SUM(D3-D2) -> -0.3 | F3: =IF(C3>0,E3/C3,0) -> 0 | G3: =[4]GEN!G32 -> 0 | H3: =H2 -> 8517 | I3: =IF(B3-H3<=0,"ok","oil change") -> ok | J3: 10385 | K3: =J3-J2 -> 8 | L3: 189815 | M3: =SUM(L3-L2) -> 918 | N3: =IF(K3>0,M3/K3,0) -> 114.75 | O3: =[4]GEN!O32 -> 0 | P3: =P2 -> 10300 | Q3: =IF(J3-P3<=0,"ok","oil change") -> oil change | R3: 10706 | S3: =R3-R2 -> 8 | T3: 144739 | U3: =SUM(T3-T2) -> 1008.5 | V3: =IF(S3>0,U3/S3,0) -> 126.0625 | W3: =[4]GEN!W32 -> 0 | X3: =X2 -> 10809 | Y3: =IF(R3-X3<=0,"ok","oil change") -> ok | Z3: =C3+K3+S3 -> 16 | AA3: =U3+M3+E3 -> 1926.2 | AB3: =V3+N3+F3 -> 240.8125 | AC3: =IF(Z3>0,AA3/Z3,0) -> 120.3875 | AD3: =ELEC!Q3 -> 10434 | AE3: =SUM(AD3/Z3) -> 652.125 | AF3: =SUM(AE3/1600) -> 0.40757813 | AG3: =SUM(360*AF3) -> 146.72813 | AH3: =SUM(AC3-AG3) -> -26.340625 | AI3: =AD3*AJ3 -> 2685.5443 | AJ3: =305/1185 -> 0.25738397 | AK3: =AI3/Z3 -> 167.84652
A4: =ELEC!C4 -> 43740 | B4: =B3 -> 8418 | C4: =B4-B3 -> 0 | D4: =D3 -> 108878 | E4: =SUM(D4-D3) -> 0 | F4: =IF(C4>0,E4/C4,0) -> 0 | H4: =H3 -> 8517 | I4: =IF(B4-H4<=0,"ok","oil change") -> ok | J4: 10392 | K4: =J4-J3 -> 7 | L4: 190787.5 | M4: =SUM(L4-L3) -> 972.5 | N4: =IF(K4>0,M4/K4,0) -> 138.92857 | P4: =P3 -> 10300 | Q4: =IF(J4-P4<=0,"ok","oil change") -> oil change | R4: 10713 | S4: =R4-R3 -> 7 | T4: 145768.7 | U4: =SUM(T4-T3) -> 1029.7 | V4: =IF(S4>0,U4/S4,0) -> 147.1 | X4: =X3 -> 10809 | Y4: =IF(R4-X4<=0,"ok","oil change") -> ok | Z4: =C4+K4+S4 -> 14 | AA4: =U4+M4+E4 -> 2002.2 | AB4: =V4+N4+F4 -> 286.02857 | AC4: =IF(Z4>0,AA4/Z4,0) -> 143.01429 | AD4: =ELEC!Q4 -> 10284 | AE4: =SUM(AD4/Z4) -> 734.57143 | AF4: =SUM(AE4/1600) -> 0.45910714 | AG4: =SUM(360*AF4) -> 165.27857 | AH4: =SUM(AC4-AG4) -> -22.264286 | AI4: =AD4*AJ4 -> 2646.9367 | AJ4: =305/1185 -> 0.25738397 | AK4: =AI4/Z4 -> 189.06691
A5: =ELEC!C5 -> 43741 | B5: =B4 -> 8418 | C5: =B5-B4 -> 0 | D5: =D4 -> 108878 | E5: =SUM(D5-D4) -> 0 | F5: =IF(C5>0,E5/C5,0) -> 0 | H5: 8497 | I5: =IF(B5-H5<=0,"ok","oil change") -> ok | J5: 10400 | K5: =J5-J4 -> 8 | L5: 192040.5 | M5: =SUM(L5-L4) -> 1253 | N5: =IF(K5>0,M5/K5,0) -> 156.625 | P5: 10361 | Q5: =IF(J5-P5<=0,"ok","oil change") -> oil change | R5: 10722 | S5: =R5-R4 -> 9 | T5: 147040 | U5: =SUM(T5-T4) -> 1271.3 | V5: =IF(S5>0,U5/S5,0) -> 141.25556 | X5: =X4 -> 10809 | Y5: =IF(R5-X5<=0,"ok","oil change") -> ok | Z5: =C5+K5+S5 -> 17 | AA5: =U5+M5+E5 -> 2524.3 | AB5: =V5+N5+F5 -> 297.88056 | AC5: =IF(Z5>0,AA5/Z5,0) -> 148.48824 | AD5: =ELEC!Q5 -> 11113 | AE5: =SUM(AD5/Z5) -> 653.70588 | AF5: =SUM(AE5/1600) -> 0.40856618 | AG5: =SUM(320*AF5) -> 130.74118 | AH5: =SUM(AC5-AG5) -> 17.747059 | AI5: =AD5*AJ5 -> 2860.308 | AJ5: =305/1185 -> 0.25738397 | AK5: =AI5/Z5 -> 168.25341
A6: =ELEC!C6 -> 43742 | B6: =B5 -> 8418 | C6: =B6-B5 -> 0 | D6: =D5 -> 108878 | E6: =SUM(D6-D5) -> 0 | F6: =IF(C6>0,E6/C6,0) -> 0 | H6: =H5 -> 8497 | I6: =IF(B6-H6<=0,"ok","oil change") -> ok | J6: 10406 | K6: =J6-J5 -> 6 | L6: 192745 | M6: =SUM(L6-L5) -> 704.5 | N6: =IF(K6>0,M6/K6,0) -> 117.41667 | P6: =P5 -> 10361 | Q6: =IF(J6-P6<=0,"ok","oil change") -> oil change | R6: 10727 | S6: =R6-R5 -> 5 | T6: 147786.3 | U6: =SUM(T6-T5) -> 746.3 | V6: =IF(S6>0,U6/S6,0) -> 149.26 | X6: =X5 -> 10809 | Y6: =IF(R6-X6<=0,"ok","oil change") -> ok | Z6: =C6+K6+S6 -> 11 | AA6: =U6+M6+E6 -> 1450.8 | AB6: =V6+N6+F6 -> 266.67667 | AC6: =IF(Z6>0,AA6/Z6,0) -> 131.89091 | AD6: =ELEC!Q6 -> 7387 | AE6: =SUM(AD6/Z6) -> 671.54545 | AF6: =SUM(AE6/1600) -> 0.41971591 | AG6: =SUM(320*AF6) -> 134.30909 | AH6: =SUM(AC6-AG6) -> -2.4181818 | AI6: =AD6*AJ6 -> 1901.2954 | AJ6: =305/1185 -> 0.25738397 | AK6: =AI6/Z6 -> 172.84503
A7: =ELEC!C7 -> 43743 | B7: =B6 -> 8418 | C7: =B7-B6 -> 0 | D7: =D6 -> 108878 | E7: =SUM(D7-D6) -> 0 | F7: =IF(C7>0,E7/C7,0) -> 0 | H7: =H6 -> 8497 | I7: =IF(B7-H7<=0,"ok","oil change") -> ok | J7: 10409 | K7: =J7-J6 -> 3 | L7: 193155 | M7: =SUM(L7-L6) -> 410 | N7: =IF(K7>0,M7/K7,0) -> 136.66667 | P7: =P6 -> 10361 | Q7: =IF(J7-P7<=0,"ok","oil change") -> oil change | R7: 10730 | S7: =R7-R6 -> 3 | T7: 148219 | U7: =SUM(T7-T6) -> 432.7 | V7: =IF(S7>0,U7/S7,0) -> 144.23333 | X7: =X6 -> 10809 | Y7: =IF(R7-X7<=0,"ok","oil change") -> ok | Z7: =C7+K7+S7 -> 6 | AA7: =U7+M7+E7 -> 842.7 | AB7: =V7+N7+F7 -> 280.9 | AC7: =IF(Z7>0,AA7/Z7,0) -> 140.45 | AD7: =ELEC!Q7 -> 4800 | AE7: =SUM(AD7/Z7) -> 800 | AF7: =SUM(AE7/1600) -> 0.5 | AH7: =SUM(AC7-AG7) -> #VALUE! | AI7: =AD7*AJ7 -> 1235.443 | AJ7: =305/1185 -> 0.25738397 | AK7: =AI7/Z7 -> 205.90717
A8: =ELEC!C8 -> 43744 | B8: =B7 -> 8418 | C8: =B8-B7 -> 0 | D8: =D7 -> 108878 | E8: =SUM(D8-D7) -> 0 | F8: =IF(C8>0,E8/C8,0) -> 0 | H8: =H7 -> 8497 | I8: =IF(B8-H8<=0,"ok","oil change") -> ok | J8: 10412 | K8: =J8-J7 -> 3 | L8: 193726 | M8: =SUM(L8-L7) -> 571 | N8: =IF(K8>0,M8/K8,0) -> 190.33333 | P8: =P7 -> 10361 | Q8: =IF(J8-P8<=0,"ok","oil change") -> oil change | R8: 10733 | S8: =R8-R7 -> 3 | T8: 148760.3 | U8: =SUM(T8-T7) -> 541.3 | V8: =IF(S8>0,U8/S8,0) -> 180.43333 | X8: =X7 -> 10809 | Y8: =IF(R8-X8<=0,"ok","oil change") -> ok | Z8: =C8+K8+S8 -> 6 | AA8: =U8+M8+E8 -> 1112.3 | AB8: =V8+N8+F8 -> 370.76667 | AC8: =IF(Z8>0,AA8/Z8,0) -> 185.38333 | AD8: =ELEC!Q8 -> 4144 | AE8: =SUM(AD8/Z8) -> 690.66667 | AF8: =SUM(AE8/1600) -> 0.43166667 | AG8: =SUM(320*AF8) -> 138.13333 | AH8: =SUM(AC8-AG8) -> 47.25 | AI8: =AD8*AJ8 -> 1066.5992 | AJ8: =305/1185 -> 0.25738397 | AK8: =AI8/Z8 -> 177.76653
A9: =ELEC!C9 -> 43745 | B9: =B8 -> 8418 | C9: =B9-B8 -> 0 | D9: =D8 -> 108878 | E9: =SUM(D9-D8) -> 0 | F9: =IF(C9>0,E9/C9,0) -> 0 | H9: =H8 -> 8497 | I9: =IF(B9-H9<=0,"ok","oil change") -> ok | J9: 10417 | K9: =J9-J8 -> 5 | L9: 194705.1 | M9: =SUM(L9-L8) -> 979.1 | N9: =IF(K9>0,M9/K9,0) -> 195.82 | P9: =P8 -> 10361 | Q9: =IF(J9-P9<=0,"ok","oil change") -> oil change | R9: 10738 | S9: =R9-R8 -> 5 | T9: 149729.1 | U9: =SUM(T9-T8) -> 968.8 | V9: =IF(S9>0,U9/S9,0) -> 193.76 | X9: =X8 -> 10809 | Y9: =IF(R9-X9<=0,"ok","oil change") -> ok | Z9: =C9+K9+S9 -> 10 | AA9: =U9+M9+E9 -> 1947.9 | AB9: =V9+N9+F9 -> 389.58 | AC9: =IF(Z9>0,AA9/Z9,0) -> 194.79 | AD9: =ELEC!Q9 -> 4739 | AE9: =SUM(AD9/Z9) -> 473.9 | AF9: =SUM(AE9/1600) -> 0.2961875 | AG9: =SUM(320*AF9) -> 94.78 | AH9: =SUM(AC9-AG9) -> 100.01 | AI9: =AD9*AJ9 -> 1219.7426 | AJ9: 0.25738397 | AK9: =IF(Z9>0,AI9/Z9,0) -> 121.97426
A10: =ELEC!C10 -> 43746 | B10: =B9 -> 8418 | C10: =B10-B9 -> 0 | D10: =D9 -> 108878 | E10: =SUM(D10-D9) -> 0 | F10: =IF(C10>0,E10/C10,0) -> 0 | H10: =H9 -> 8497 | I10: =IF(B10-H10<=0,"ok","oil change") -> ok | J10: 10420 | K10: =J10-J9 -> 3 | L10: 195180.8 | M10: =SUM(L10-L9) -> 475.7 | N10: =IF(K10>0,M10/K10,0) -> 158.56667 | P10: =P9 -> 10361 | Q10: =IF(J10-P10<=0,"ok","oil change") -> oil change | R10: 10742 | S10: =R10-R9 -> 4 | T10: 150205.1 | U10: =SUM(T10-T9) -> 476 | V10: =IF(S10>0,U10/S10,0) -> 119 | X10: =X9 -> 10809 | Y10: =IF(R10-X10<=0,"ok","oil change") -> ok | Z10: =C10+K10+S10 -> 7 | AA10: =U10+M10+E10 -> 951.7 | AB10: =V10+N10+F10 -> 277.56667 | AC10: =IF(Z10>0,AA10/Z10,0) -> 135.95714 | AD10: =ELEC!Q10 -> 4558 | AE10: =SUM(AD10/Z10) -> 651.14286 | AF10: =SUM(AE10/1600) -> 0.40696429 | AG10: =SUM(320*AF10) -> 130.22857 | AH10: =SUM(AC10-AG10) -> 5.7285714 | AI10: =AD10*AJ10 -> 1173.1561 | AJ10: =305/1185 -> 0.25738397 | AK10: =IF(Z10>0,AI10/Z10,0) -> 167.59373
A11: =ELEC!C11 -> 43747 | B11: 8419 | C11: =B11-B10 -> 1 | D11: 108910 | E11: =SUM(D11-D10) -> 32 | F11: =IF(C11>0,E11/C11,0) -> 32 | H11: =H10 -> 8497 | I11: =IF(B11-H11<=0,"ok","oil change") -> ok | J11: 10423 | K11: =J11-J10 -> 3 | L11: 195630 | M11: =SUM(L11-L10) -> 449.2 | N11: =IF(K11>0,M11/K11,0) -> 149.73333 | P11: =P10 -> 10361 | Q11: =IF(J11-P11<=0,"ok","oil change") -> oil change | R11: 10745 | S11: =R11-R10 -> 3 | T11: 150668 | U11: =SUM(T11-T10) -> 462.9 | V11: =IF(S11>0,U11/S11,0) -> 154.3 | X11: =X10 -> 10809 | Y11: =IF(R11-X11<=0,"ok","oil change") -> ok | Z11: =C11+K11+S11 -> 7 | AA11: =U11+M11+E11 -> 944.1 | AB11: =V11+N11+F11 -> 336.03333 | AC11: =IF(Z11>0,AA11/Z11,0) -> 134.87143 | AD11: =ELEC!Q11 -> 4426 | AE11: =SUM(AD11/Z11) -> 632.28571 | AF11: =SUM(AE11/1600) -> 0.39517857 | AG11: =SUM(320*AF11) -> 126.45714 | AH11: =SUM(AC11-AG11) -> 8.4142857 | AI11: =AD11*AJ11 -> 1139.1814 | AJ11: =305/1185 -> 0.25738397 | AK11: =IF(Z11>0,AI11/Z11,0) -> 162.7402
A12: =ELEC!C12 -> 43748 | B12: 8419 | C12: =B12-B11 -> 0 | D12: 108938 | E12: =SUM(D12-D11) -> 28 | F12: =IF(C12>0,E12/C12,0) -> 0 | H12: =H11 -> 8497 | I12: =IF(B12-H12<=0,"ok","oil change") -> ok | J12: 10430 | K12: =J12-J11 -> 7 | L12: 196573.6 | M12: =SUM(L12-L11) -> 943.6 | N12: =IF(K12>0,M12/K12,0) -> 134.8 | P12: =P11 -> 10361 | Q12: =IF(J12-P12<=0,"ok","oil change") -> oil change | R12: 10752 | S12: =R12-R11 -> 7 | T12: 151668.3 | U12: =SUM(T12-T11) -> 1000.3 | V12: =IF(S12>0,U12/S12,0) -> 142.9 | X12: =X11 -> 10809 | Y12: =IF(R12-X12<=0,"ok","oil change") -> ok | Z12: =C12+K12+S12 -> 14 | AA12: =U12+M12+E12 -> 1971.9 | AB12: =V12+N12+F12 -> 277.7 | AC12: =IF(Z12>0,AA12/Z12,0) -> 140.85 | AD12: =ELEC!Q12 -> 9503 | AE12: =SUM(AD12/Z12) -> 678.78571 | AF12: =SUM(AE12/1600) -> 0.42424107 | AG12: =SUM(320*AF12) -> 135.75714 | AH12: =SUM(AC12-AG12) -> 5.0928571 | AI12: =AD12*AJ12 -> 2445.9198 | AJ12: =305/1185 -> 0.25738397 | AK12: =IF(Z12>0,AI12/Z12,0) -> 174.70856
A13: =ELEC!C13 -> 43749 | B13: =B12 -> 8419 | C13: =B13-B12 -> 0 | D13: =D12 -> 108938 | E13: =SUM(D13-D12) -> 0 | F13: =IF(C13>0,E13/C13,0) -> 0 | H13: =H12 -> 8497 | I13: =IF(B13-H13<=0,"ok","oil change") -> ok | J13: 10438 | K13: =J13-J12 -> 8 | L13: 197745.5 | M13: =SUM(L13-L12) -> 1171.9 | N13: =IF(K13>0,M13/K13,0) -> 146.4875 | P13: =P12 -> 10361 | Q13: =IF(J13-P13<=0,"ok","oil change") -> oil change | R13: 10760 | S13: =R13-R12 -> 8 | T13: 152849.1 | U13: =SUM(T13-T12) -> 1180.8 | V13: =IF(S13>0,U13/S13,0) -> 147.6 | X13: =X12 -> 10809 | Y13: =IF(R13-X13<=0,"ok","oil change") -> ok | Z13: =C13+K13+S13 -> 16 | AA13: =U13+M13+E13 -> 2352.7 | AB13: =V13+N13+F13 -> 294.0875 | AC13: =IF(Z13>0,AA13/Z13,0) -> 147.04375 | AD13: =ELEC!Q13 -> 10641 | AE13: =SUM(AD13/Z13) -> 665.0625 | AF13: =SUM(AE13/1600) -> 0.41566406 | AG13: =SUM(320*AF13) -> 133.0125 | AH13: =SUM(AC13-AG13) -> 14.03125 | AI13: =AD13*AJ13 -> 2738.8228 | AJ13: =305/1185 -> 0.25738397 | AK13: =IF(Z13>0,AI13/Z13,0) -> 171.17642
A14: =ELEC!C14 -> 43750 | B14: =B13 -> 8419 | C14: =B14-B13 -> 0 | D14: =D13 -> 108938 | E14: =SUM(D14-D13) -> 0 | F14: =IF(C14>0,E14/C14,0) -> 0 | H14: =H13 -> 8497 | I14: =IF(B14-H14<=0,"ok","oil change") -> ok | J14: 10441 | K14: =J14-J13 -> 3 | L14: 198130.7 | M14: =SUM(L14-L13) -> 385.2 | N14: =IF(K14>0,M14/K14,0) -> 128.4 | P14: =P13 -> 10361 | Q14: =IF(J14-P14<=0,"ok","oil change") -> oil change | R14: 10763 | S14: =R14-R13 -> 3 | T14: 153241.8 | U14: =SUM(T14-T13) -> 392.7 | V14: =IF(S14>0,U14/S14,0) -> 130.9 | X14: =X13 -> 10809 | Y14: =IF(R14-X14<=0,"ok","oil change") -> ok | Z14: =C14+K14+S14 -> 6 | AA14: =U14+M14+E14 -> 777.9 | AB14: =V14+N14+F14 -> 259.3 | AC14: =IF(Z14>0,AA14/Z14,0) -> 129.65 | AD14: =ELEC!Q14 -> 4547 | AE14: =SUM(AD14/Z14) -> 757.83333 | AF14: =SUM(AE14/1600) -> 0.47364583 | AG14: =SUM(320*AF14) -> 151.56667 | AH14: =SUM(AC14-AG14) -> -21.916667 | AI14: =AD14*AJ14 -> 1170.3249 | AJ14: =305/1185 -> 0.25738397 | AK14: =IF(Z14>0,AI14/Z14,0) -> 195.05415
A15: =ELEC!C15 -> 43751 | B15: =B14 -> 8419 | C15: =B15-B14 -> 0 | D15: =D14 -> 108938 | E15: =SUM(D15-D14) -> 0 | F15: =IF(C15>0,E15/C15,0) -> 0 | H15: =H14 -> 8497 | I15: =IF(B15-H15<=0,"ok","oil change") -> ok | J15: 10445 | K15: =J15-J14 -> 4 | L15: 198736.2 | M15: =SUM(L15-L14) -> 605.5 | N15: =IF(K15>0,M15/K15,0) -> 151.375 | P15: =P14 -> 10361 | Q15: =IF(J15-P15<=0,"ok","oil change") -> oil change | R15: 10766.25 | S15: =R15-R14 -> 3.25 | T15: 153815.5 | U15: =SUM(T15-T14) -> 573.7 | V15: =IF(S15>0,U15/S15,0) -> 176.52308 | X15: =X14 -> 10809 | Y15: =IF(R15-X15<=0,"ok","oil change") -> ok | Z15: =C15+K15+S15 -> 7.25 | AA15: =U15+M15+E15 -> 1179.2 | AB15: =V15+N15+F15 -> 327.89808 | AC15: =IF(Z15>0,AA15/Z15,0) -> 162.64828 | AD15: =ELEC!Q15 -> 4017 | AE15: =SUM(AD15/Z15) -> 554.06897 | AF15: =SUM(AE15/1600) -> 0.3462931 | AG15: =SUM(320*AF15) -> 110.81379 | AH15: =SUM(AC15-AG15) -> 51.834483 | AI15: =AD15*AJ15 -> 1033.9114 | AJ15: =305/1185 -> 0.25738397 | AK15: =IF(Z15>0,AI15/Z15,0) -> 142.60847
A16: =ELEC!C16 -> 43752 | B16: 8419.09 | C16: =B16-B15 -> 0.09 | D16: 108938.9 | E16: =SUM(D16-D15) -> 0.9 | F16: =IF(C16>0,E16/C16,0) -> 10 | H16: =H15 -> 8497 | I16: =IF(B16-H16<=0,"ok","oil change") -> ok | J16: 10453 | K16: =J16-J15 -> 8 | L16: 199931.3 | M16: =SUM(L16-L15) -> 1195.1 | N16: =IF(K16>0,M16/K16,0) -> 149.3875 | P16: =P15 -> 10361 | Q16: =IF(J16-P16<=0,"ok","oil change") -> oil change | R16: 10774.4 | S16: =R16-R15 -> 8.15 | T16: 155003 | U16: =SUM(T16-T15) -> 1187.5 | V16: =IF(S16>0,U16/S16,0) -> 145.70552 | X16: =X15 -> 10809 | Y16: =IF(R16-X16<=0,"ok","oil change") -> ok | Z16: =C16+K16+S16 -> 16.24 | AA16: =U16+M16+E16 -> 2383.5 | AB16: =V16+N16+F16 -> 305.09302 | AC16: =IF(Z16>0,AA16/Z16,0) -> 146.76724 | AD16: =ELEC!Q16 -> 11185 | AE16: =SUM(AD16/Z16) -> 688.73153 | AF16: =SUM(AE16/1600) -> 0.4304572 | AG16: =SUM(320*AF16) -> 137.74631 | AH16: =SUM(AC16-AG16) -> 9.020936 | AI16: =AD16*AJ16 -> 2878.8397 | AJ16: =305/1185 -> 0.25738397 | AK16: =IF(Z16>0,AI16/Z16,0) -> 177.26845
A17: =ELEC!C17 -> 43753 | B17: =B16 -> 8419.09 | C17: =B17-B16 -> 0 | D17: =D16 -> 108938.9 | E17: =SUM(D17-D16) -> 0 | F17: =IF(C17>0,E17/C17,0) -> 0 | H17: =H16 -> 8497 | I17: =IF(B17-H17<=0,"ok","oil change") -> ok | J17: =J16 -> 10453 | K17: =J17-J16 -> 0 | L17: =L16 -> 199931.3 | M17: =SUM(L17-L16) -> 0 | N17: =IF(K17>0,M17/K17,0) -> 0 | P17: =P16 -> 10361 | Q17: =IF(J17-P17<=0,"ok","oil change") -> oil change | R17: =R16 -> 10774.4 | S17: =R17-R16 -> 0 | T17: =T16 -> 155003 | U17: =SUM(T17-T16) -> 0 | V17: =IF(S17>0,U17/S17,0) -> 0 | X17: =X16 -> 10809 | Y17: =IF(R17-X17<=0,"ok","oil change") -> ok | Z17: =C17+K17+S17 -> 0 | AA17: =U17+M17+E17 -> 0 | AB17: =V17+N17+F17 -> 0 | AC17: =IF(Z17>0,AA17/Z17,0) -> 0 | AD17: =ELEC!Q17 -> 0 | AE17: =SUM(AD17/Z17) -> #DIV/0! | AF17: =SUM(AE17/1600) -> #DIV/0! | AG17: =SUM(320*AF17) -> #DIV/0! | AH17: =SUM(AC17-AG17) -> #DIV/0! | AI17: =AD17*AJ17 -> 0 | AJ17: =305/1185 -> 0.25738397 | AK17: =IF(Z17>0,AI17/Z17,0) -> 0
A18: =ELEC!C18 -> 43754 | B18: =B17 -> 8419.09 | C18: =B18-B17 -> 0 | D18: =D17 -> 108938.9 | E18: =SUM(D18-D17) -> 0 | F18: =IF(C18>0,E18/C18,0) -> 0 | H18: =H17 -> 8497 | I18: =IF(B18-H18<=0,"ok","oil change") -> ok | J18: =J17 -> 10453 | K18: =J18-J17 -> 0 | L18: =L17 -> 199931.3 | M18: =SUM(L18-L17) -> 0 | N18: =IF(K18>0,M18/K18,0) -> 0 | P18: =P17 -> 10361 | Q18: =IF(J18-P14<=0,"ok","oil change") -> oil change | R18: =R17 -> 10774.4 | S18: =R18-R17 -> 0 | T18: =T17 -> 155003 | U18: =SUM(T18-T17) -> 0 | V18: =IF(S18>0,U18/S18,0) -> 0 | X18: =X17 -> 10809 | Y18: =IF(R18-X18<=0,"ok","oil change") -> ok | Z18: =C18+K18+S18 -> 0 | AA18: =U18+M18+E18 -> 0 | AB18: =V18+N18+F18 -> 0 | AC18: =IF(Z18>0,AA18/Z18,0) -> 0 | AD18: =ELEC!Q18 -> 0 | AE18: =SUM(AD18/Z18) -> #DIV/0! | AF18: =SUM(AE18/1600) -> #DIV/0! | AG18: =SUM(320*AF18) -> #DIV/0! | AH18: =SUM(AC18-AG18) -> #DIV/0! | AI18: =AD18*AJ18 -> 0 | AJ18: =305/1185 -> 0.25738397 | AK18: =IF(Z18>0,AI18/Z18,0) -> 0
A19: =ELEC!C19 -> 43755 | B19: =B18 -> 8419.09 | C19: =B19-B18 -> 0 | D19: =D18 -> 108938.9 | E19: =SUM(D19-D18) -> 0 | F19: =IF(C19>0,E19/C19,0) -> 0 | H19: =H18 -> 8497 | I19: =IF(B19-H19<=0,"ok","oil change") -> ok | J19: =J18 -> 10453 | K19: =J19-J18 -> 0 | L19: =L18 -> 199931.3 | M19: =SUM(L19-L18) -> 0 | N19: =IF(K19>0,M19/K19,0) -> 0 | P19: =P18 -> 10361 | Q19: =IF(J19-P19<=0,"ok","oil change") -> oil change | R19: =R18 -> 10774.4 | S19: =R19-R18 -> 0 | T19: =T18 -> 155003 | U19: =SUM(T19-T18) -> 0 | V19: =IF(S19>0,U19/S19,0) -> 0 | X19: =X18 -> 10809 | Y19: =IF(R19-X19<=0,"ok","oil change") -> ok | Z19: =C19+K19+S19 -> 0 | AA19: =U19+M19+E19 -> 0 | AB19: =V19+N19+F19 -> 0 | AC19: =IF(Z19>0,AA19/Z19,0) -> 0 | AD19: =ELEC!Q19 -> 0 | AE19: =SUM(AD19/Z19) -> #DIV/0! | AF19: =SUM(AE19/1600) -> #DIV/0! | AG19: =SUM(320*AF19) -> #DIV/0! | AH19: =SUM(AC19-AG19) -> #DIV/0! | AI19: =AD19*AJ19 -> 0 | AJ19: =305/1185 -> 0.25738397 | AK19: =IF(Z19>0,AI19/Z19,0) -> 0
A20: =ELEC!C20 -> 43756 | B20: =B19 -> 8419.09 | C20: =B20-B19 -> 0 | D20: =D19 -> 108938.9 | E20: =SUM(D20-D19) -> 0 | F20: =IF(C20>0,E20/C20,0) -> 0 | H20: =H19 -> 8497 | I20: =IF(B20-H20<=0,"ok","oil change") -> ok | J20: =J19 -> 10453 | K20: =J20-J19 -> 0 | L20: =L19 -> 199931.3 | M20: =SUM(L20-L19) -> 0 | N20: =IF(K20>0,M20/K20,0) -> 0 | P20: =P19 -> 10361 | Q20: =IF(J20-P20<=0,"ok","oil change") -> oil change | R20: =R19 -> 10774.4 | S20: =R20-R19 -> 0 | T20: =T19 -> 155003 | U20: =SUM(T20-T19) -> 0 | V20: =IF(S20>0,U20/S20,0) -> 0 | X20: =X19 -> 10809 | Y20: =IF(R20-X20<=0,"ok","oil change") -> ok | Z20: =C20+K20+S20 -> 0 | AA20: =U20+M20+E20 -> 0 | AB20: =V20+N20+F20 -> 0 | AC20: =IF(Z20>0,AA20/Z20,0) -> 0 | AD20: =ELEC!Q20 -> 0 | AE20: =SUM(AD20/Z20) -> #DIV/0! | AF20: =SUM(AE20/1600) -> #DIV/0! | AG20: =SUM(320*AF20) -> #DIV/0! | AH20: =SUM(AC20-AG20) -> #DIV/0! | AI20: =AD20*AJ20 -> 0 | AJ20: =305/1185 -> 0.25738397 | AK20: =IF(Z20>0,AI20/Z20,0) -> 0
A21: =ELEC!C21 -> 43757 | B21: =B20 -> 8419.09 | C21: =B21-B20 -> 0 | D21: =D20 -> 108938.9 | E21: =SUM(D21-D20) -> 0 | F21: =IF(C21>0,E21/C21,0) -> 0 | H21: =H20 -> 8497 | I21: =IF(B21-H21<=0,"ok","oil change") -> ok | J21: =J20 -> 10453 | K21: =J21-J20 -> 0 | L21: =L20 -> 199931.3 | M21: =SUM(L21-L20) -> 0 | N21: =IF(K21>0,M21/K21,0) -> 0 | P21: =P20 -> 10361 | Q21: =IF(J21-P21<=0,"ok","oil change") -> oil change | R21: =R20 -> 10774.4 | S21: =R21-R20 -> 0 | T21: =T20 -> 155003 | U21: =SUM(T21-T20) -> 0 | V21: =IF(S21>0,U21/S21,0) -> 0 | X21: =X20 -> 10809 | Y21: =Y20 -> ok | Z21: =C21+K21+S21 -> 0 | AA21: =U21+M21+E21 -> 0 | AB21: =V21+N21+F21 -> 0 | AC21: =IF(Z21>0,AA21/Z21,0) -> 0 | AD21: =ELEC!Q21 -> 0 | AE21: =SUM(AD21/Z21) -> #DIV/0! | AF21: =SUM(AE21/1600) -> #DIV/0! | AG21: =SUM(320*AF21) -> #DIV/0! | AH21: =SUM(AC21-AG21) -> #DIV/0! | AI21: =AD21*AJ21 -> 0 | AJ21: =305/1185 -> 0.25738397 | AK21: =IF(Z21>0,AI21/Z21,0) -> 0
A22: =ELEC!C22 -> 43758 | B22: =B21 -> 8419.09 | C22: =B22-B21 -> 0 | D22: =D21 -> 108938.9 | E22: =SUM(D22-D21) -> 0 | F22: =IF(C22>0,E22/C22,0) -> 0 | H22: =H21 -> 8497 | I22: =IF(B22-H22<=0,"ok","oil change") -> ok | J22: =J21 -> 10453 | K22: =J22-J21 -> 0 | L22: =L21 -> 199931.3 | M22: =SUM(L22-L21) -> 0 | N22: =IF(K22>0,M22/K22,0) -> 0 | P22: =P21 -> 10361 | Q22: =IF(J22-P22<=0,"ok","oil change") -> oil change | R22: =R21 -> 10774.4 | S22: =R22-R21 -> 0 | T22: =T21 -> 155003 | U22: =SUM(T22-T21) -> 0 | V22: =IF(S22>0,U22/S22,0) -> 0 | X22: =X21 -> 10809 | Y22: =IF(R22-X22<=0,"ok","oil change") -> ok | Z22: =C22+K22+S22 -> 0 | AA22: =U22+M22+E22 -> 0 | AB22: =V22+N22+F22 -> 0 | AC22: =IF(Z22>0,AA22/Z22,0) -> 0 | AD22: =ELEC!Q22 -> 0 | AE22: =SUM(AD22/Z22) -> #DIV/0! | AF22: =SUM(AE22/1600) -> #DIV/0! | AG22: =SUM(320*AF22) -> #DIV/0! | AH22: =SUM(AC22-AG22) -> #DIV/0! | AI22: =AD22*AJ22 -> 0 | AJ22: =305/1185 -> 0.25738397 | AK22: =IF(Z22>0,AI22/Z22,0) -> 0
A23: =ELEC!C23 -> 43759 | B23: =B22 -> 8419.09 | C23: =B23-B22 -> 0 | D23: =D22 -> 108938.9 | E23: =SUM(D23-D22) -> 0 | F23: =IF(C23>0,E23/C23,0) -> 0 | H23: =H22 -> 8497 | I23: =IF(B23-H23<=0,"ok","oil change") -> ok | J23: =J22 -> 10453 | K23: =J23-J22 -> 0 | L23: =L22 -> 199931.3 | M23: =SUM(L23-L22) -> 0 | N23: =IF(K23>0,M23/K23,0) -> 0 | P23: =P22 -> 10361 | Q23: =IF(J23-P23<=0,"ok","oil change") -> oil change | R23: =R22 -> 10774.4 | S23: =R23-R22 -> 0 | T23: =T22 -> 155003 | U23: =SUM(T23-T22) -> 0 | V23: =IF(S23>0,U23/S23,0) -> 0 | X23: =X22 -> 10809 | Y23: =IF(R23-X23<=0,"ok","oil change") -> ok | Z23: =C23+K23+S23 -> 0 | AA23: =U23+M23+E23 -> 0 | AB23: =V23+N23+F23 -> 0 | AC23: =IF(Z23>0,AA23/Z23,0) -> 0 | AD23: =ELEC!Q23 -> 0 | AE23: =SUM(AD23/Z23) -> #DIV/0! | AF23: =SUM(AE23/1600) -> #DIV/0! | AG23: =SUM(320*AF23) -> #DIV/0! | AH23: =SUM(AC23-AG23) -> #DIV/0! | AI23: =AD23*AJ23 -> 0 | AJ23: =305/1185 -> 0.25738397 | AK23: =IF(Z23>0,AI23/Z23,0) -> 0
A24: =ELEC!C24 -> 43760 | B24: =B23 -> 8419.09 | C24: =B24-B23 -> 0 | D24: =D23 -> 108938.9 | E24: =SUM(D24-D23) -> 0 | F24: =IF(C24>0,E24/C24,0) -> 0 | H24: =H23 -> 8497 | I24: =IF(B24-H24<=0,"ok","oil change") -> ok | J24: =J23 -> 10453 | K24: =J24-J23 -> 0 | L24: =L23 -> 199931.3 | M24: =SUM(L24-L23) -> 0 | N24: =IF(K24>0,M24/K24,0) -> 0 | P24: =P23 -> 10361 | Q24: =IF(J24-P24<=0,"ok","oil change") -> oil change | R24: =R23 -> 10774.4 | S24: =R24-R23 -> 0 | T24: =T23 -> 155003 | U24: =SUM(T24-T23) -> 0 | V24: =IF(S24>0,U24/S24,0) -> 0 | X24: =X23 -> 10809 | Y24: =IF(R24-X24<=0,"ok","oil change") -> ok | Z24: =C24+K24+S24 -> 0 | AA24: =U24+M24+E24 -> 0 | AB24: =V24+N24+F24 -> 0 | AC24: =IF(Z24>0,AA24/Z24,0) -> 0 | AD24: =ELEC!Q24 -> 0 | AE24: =SUM(AD24/Z24) -> #DIV/0! | AF24: =SUM(AE24/1600) -> #DIV/0! | AG24: =SUM(320*AF24) -> #DIV/0! | AH24: =SUM(AC24-AG24) -> #DIV/0! | AI24: =AD24*AJ24 -> 0 | AJ24: =305/1185 -> 0.25738397 | AK24: =IF(Z24>0,AI24/Z24,0) -> 0
A25: =ELEC!C25 -> 43761 | B25: =B24 -> 8419.09 | C25: =B25-B24 -> 0 | D25: =D24 -> 108938.9 | E25: =SUM(D25-D24) -> 0 | F25: =IF(C25>0,E25/C25,0) -> 0 | H25: =H24 -> 8497 | I25: =IF(B25-H25<=0,"ok","oil change") -> ok | J25: =J24 -> 10453 | K25: =J25-J24 -> 0 | L25: =L24 -> 199931.3 | M25: =SUM(L25-L24) -> 0 | N25: =IF(K25>0,M25/K25,0) -> 0 | P25: =P24 -> 10361 | Q25: =IF(J25-P25<=0,"ok","oil change") -> oil change | R25: =R24 -> 10774.4 | S25: =R25-R24 -> 0 | T25: =T24 -> 155003 | U25: =SUM(T25-T24) -> 0 | V25: =IF(S25>0,U25/S25,0) -> 0 | X25: =X24 -> 10809 | Y25: =IF(R25-X25<=0,"ok","oil change") -> ok | Z25: =C25+K25+S25 -> 0 | AA25: =U25+M25+E25 -> 0 | AB25: =V25+N25+F25 -> 0 | AC25: =IF(Z25>0,AA25/Z25,0) -> 0 | AD25: =ELEC!Q25 -> 0 | AE25: =SUM(AD25/Z25) -> #DIV/0! | AF25: =SUM(AE25/1600) -> #DIV/0! | AG25: =SUM(320*AF25) -> #DIV/0! | AH25: =SUM(AC25-AG25) -> #DIV/0! | AI25: =AD25*AJ25 -> 0 | AJ25: =305/1185 -> 0.25738397 | AK25: =IF(Z25>0,AI25/Z25,0) -> 0
A26: =ELEC!C26 -> 43762 | B26: =B25 -> 8419.09 | C26: =B26-B25 -> 0 | D26: =D25 -> 108938.9 | E26: =SUM(D26-D25) -> 0 | F26: =IF(C26>0,E26/C26,0) -> 0 | H26: =H25 -> 8497 | I26: =IF(B26-H26<=0,"ok","oil change") -> ok | J26: =J25 -> 10453 | K26: =J26-J25 -> 0 | L26: =L25 -> 199931.3 | M26: =SUM(L26-L25) -> 0 | N26: =IF(K26>0,M26/K26,0) -> 0 | P26: =P25 -> 10361 | Q26: =IF(J26-P26<=0,"ok","oil change") -> oil change | R26: =R25 -> 10774.4 | S26: =R26-R25 -> 0 | T26: =T25 -> 155003 | U26: =SUM(T26-T25) -> 0 | V26: =IF(S26>0,U26/S26,0) -> 0 | X26: =X25 -> 10809 | Y26: =IF(R26-X26<=0,"ok","oil change") -> ok | Z26: =C26+K26+S26 -> 0 | AA26: =U26+M26+E26 -> 0 | AB26: =V26+N26+F26 -> 0 | AC26: =IF(Z26>0,AA26/Z26,0) -> 0 | AD26: =ELEC!Q26 -> 0 | AE26: =SUM(AD26/Z26) -> #DIV/0! | AF26: =SUM(AE26/1600) -> #DIV/0! | AG26: =SUM(320*AF26) -> #DIV/0! | AH26: =SUM(AC26-AG26) -> #DIV/0! | AI26: =AD26*AJ26 -> 0 | AJ26: =305/1185 -> 0.25738397 | AK26: =IF(Z26>0,AI26/Z26,0) -> 0
A27: =ELEC!C27 -> 43763 | B27: =B26 -> 8419.09 | C27: =B27-B26 -> 0 | D27: =D26 -> 108938.9 | E27: =SUM(D27-D26) -> 0 | F27: =IF(C27>0,E27/C27,0) -> 0 | H27: =H26 -> 8497 | I27: =IF(B27-H27<=0,"ok","oil change") -> ok | J27: =J26 -> 10453 | K27: =J27-J26 -> 0 | L27: =L26 -> 199931.3 | M27: =SUM(L27-L26) -> 0 | N27: =IF(K27>0,M27/K27,0) -> 0 | P27: =P26 -> 10361 | Q27: =IF(J27-P27<=0,"ok","oil change") -> oil change | R27: =R26 -> 10774.4 | S27: =R27-R26 -> 0 | T27: =T26 -> 155003 | U27: =SUM(T27-T26) -> 0 | V27: =IF(S27>0,U27/S27,0) -> 0 | X27: =X26 -> 10809 | Y27: =IF(R27-X27<=0,"ok","oil change") -> ok | Z27: =C27+K27+S27 -> 0 | AA27: =U27+M27+E27 -> 0 | AB27: =V27+N27+F27 -> 0 | AC27: =IF(Z27>0,AA27/Z27,0) -> 0 | AD27: =ELEC!Q27 -> 0 | AE27: =SUM(AD27/Z27) -> #DIV/0! | AF27: =SUM(AE27/1600) -> #DIV/0! | AG27: =SUM(320*AF27) -> #DIV/0! | AH27: =SUM(AC27-AG27) -> #DIV/0! | AI27: =AD27*AJ27 -> 0 | AJ27: =305/1185 -> 0.25738397 | AK27: =IF(Z27>0,AI27/Z27,0) -> 0
A28: =ELEC!C28 -> 43764 | B28: =B27 -> 8419.09 | C28: =B28-B27 -> 0 | D28: =D27 -> 108938.9 | E28: =SUM(D28-D27) -> 0 | F28: =IF(C28>0,E28/C28,0) -> 0 | H28: =H27 -> 8497 | I28: =IF(B28-H28<=0,"ok","oil change") -> ok | J28: =J27 -> 10453 | K28: =J28-J27 -> 0 | L28: =L27 -> 199931.3 | M28: =SUM(L28-L27) -> 0 | N28: =IF(K28>0,M28/K28,0) -> 0 | P28: =P27 -> 10361 | Q28: =IF(J28-P28<=0,"ok","oil change") -> oil change | R28: =R27 -> 10774.4 | S28: =R28-R27 -> 0 | T28: =T27 -> 155003 | U28: =SUM(T28-T27) -> 0 | V28: =IF(S28>0,U28/S28,0) -> 0 | X28: =X27 -> 10809 | Y28: =IF(R28-X28<=0,"ok","oil change") -> ok | Z28: =C28+K28+S28 -> 0 | AA28: =U28+M28+E28 -> 0 | AB28: =V28+N28+F28 -> 0 | AC28: =IF(Z28>0,AA28/Z28,0) -> 0 | AD28: =ELEC!Q28 -> 0 | AE28: =SUM(AD28/Z28) -> #DIV/0! | AF28: =SUM(AE28/1600) -> #DIV/0! | AG28: =SUM(320*AF28) -> #DIV/0! | AH28: =SUM(AC28-AG28) -> #DIV/0! | AI28: =AD28*AJ28 -> 0 | AJ28: =305/1185 -> 0.25738397 | AK28: =IF(Z28>0,AI28/Z28,0) -> 0
A29: =ELEC!C29 -> 43765 | B29: =B28 -> 8419.09 | C29: =B29-B28 -> 0 | D29: =D28 -> 108938.9 | E29: =SUM(D29-D28) -> 0 | F29: =IF(C29>0,E29/C29,0) -> 0 | H29: =H28 -> 8497 | I29: =IF(B29-H29<=0,"ok","oil change") -> ok | J29: =J28 -> 10453 | K29: =J29-J28 -> 0 | L29: =L28 -> 199931.3 | M29: =SUM(L29-L28) -> 0 | N29: =IF(K29>0,M29/K29,0) -> 0 | P29: 10535 | Q29: =IF(J29-P29<=0,"ok","oil change") -> ok | R29: =R28 -> 10774.4 | S29: =R29-R28 -> 0 | T29: =T28 -> 155003 | U29: =SUM(T29-T28) -> 0 | V29: =IF(S29>0,U29/S29,0) -> 0 | X29: =X28 -> 10809 | Y29: =IF(R29-X29<=0,"ok","oil change") -> ok | Z29: =C29+K29+S29 -> 0 | AA29: =U29+M29+E29 -> 0 | AB29: =V29+N29+F29 -> 0 | AC29: =IF(Z29>0,AA29/Z29,0) -> 0 | AD29: =ELEC!Q29 -> 0 | AE29: =SUM(AD29/Z29) -> #DIV/0! | AF29: =SUM(AE29/1600) -> #DIV/0! | AG29: =SUM(320*AF29) -> #DIV/0! | AH29: =SUM(AC29-AG29) -> #DIV/0! | AI29: =AD29*AJ29 -> 0 | AJ29: =305/1185 -> 0.25738397 | AK29: =IF(Z29>0,AI29/Z29,0) -> 0
A30: =ELEC!C30 -> 43766 | B30: =B29 -> 8419.09 | C30: =B30-B29 -> 0 | D30: =D29 -> 108938.9 | E30: =SUM(D30-D29) -> 0 | F30: =IF(C30>0,E30/C30,0) -> 0 | H30: =H29 -> 8497 | I30: =IF(B30-H30<=0,"ok","oil change") -> ok | J30: =J29 -> 10453 | K30: =J30-J29 -> 0 | L30: =L29 -> 199931.3 | M30: =SUM(L30-L29) -> 0 | N30: =IF(K30>0,M30/K30,0) -> 0 | P30: =P29 -> 10535 | Q30: =IF(J30-P30<=0,"ok","oil change") -> ok | R30: =R29 -> 10774.4 | S30: =R30-R29 -> 0 | T30: =T29 -> 155003 | U30: =SUM(T30-T29) -> 0 | V30: =IF(S30>0,U30/S30,0) -> 0 | X30: =X29 -> 10809 | Y30: =IF(R30-X30<=0,"ok","oil change") -> ok | Z30: =C30+K30+S30 -> 0 | AA30: =U30+M30+E30 -> 0 | AB30: =V30+N30+F30 -> 0 | AC30: =IF(Z30>0,AA30/Z30,0) -> 0 | AD30: =ELEC!Q30 -> 0 | AE30: =SUM(AD30/Z30) -> #DIV/0! | AF30: =SUM(AE30/1600) -> #DIV/0! | AG30: =SUM(320*AF30) -> #DIV/0! | AH30: =SUM(AC30-AG30) -> #DIV/0! | AI30: =AD30*AJ30 -> 0 | AJ30: =305/1185 -> 0.25738397 | AK30: =IF(Z30>0,AI30/Z30,0) -> 0
A31: =ELEC!C31 -> 43767 | B31: =B30 -> 8419.09 | C31: =B31-B30 -> 0 | D31: =D30 -> 108938.9 | E31: =SUM(D31-D30) -> 0 | F31: =IF(C31>0,E31/C31,0) -> 0 | H31: =H30 -> 8497 | I31: =IF(B31-H31<=0,"ok","oil change") -> ok | J31: =J30 -> 10453 | K31: =J31-J30 -> 0 | L31: =L30 -> 199931.3 | M31: =SUM(L31-L30) -> 0 | N31: =IF(K31>0,M31/K31,0) -> 0 | P31: =P30 -> 10535 | Q31: =IF(J31-P31<=0,"ok","oil change") -> ok | R31: =R30 -> 10774.4 | S31: =R31-R30 -> 0 | T31: =T30 -> 155003 | U31: =SUM(T31-T30) -> 0 | V31: =IF(S31>0,U31/S31,0) -> 0 | X31: =X30 -> 10809 | Y31: =IF(R31-X31<=0,"ok","oil change") -> ok | Z31: =C31+K31+S31 -> 0 | AA31: =U31+M31+E31 -> 0 | AB31: =V31+N31+F31 -> 0 | AC31: =IF(Z31>0,AA31/Z31,0) -> 0 | AD31: =ELEC!Q31 -> 0 | AE31: =SUM(AD31/Z31) -> #DIV/0! | AF31: =SUM(AE31/1600) -> #DIV/0! | AG31: =SUM(320*AF31) -> #DIV/0! | AH31: =SUM(AC31-AG31) -> #DIV/0! | AI31: =AD31*AJ31 -> 0 | AJ31: =305/1185 -> 0.25738397 | AK31: =IF(Z31>0,AI31/Z31,0) -> 0
A32: =ELEC!C32 -> 43768 | B32: =B31 -> 8419.09 | C32: =B32-B31 -> 0 | D32: =D31 -> 108938.9 | E32: =SUM(D32-D31) -> 0 | F32: =IF(C32>0,E32/C32,0) -> 0 | H32: =H31 -> 8497 | I32: =IF(B32-H32<=0,"ok","oil change") -> ok | J32: =J31 -> 10453 | K32: =J32-J31 -> 0 | L32: =L31 -> 199931.3 | M32: =SUM(L32-L31) -> 0 | N32: =IF(K32>0,M32/K32,0) -> 0 | P32: =P31 -> 10535 | Q32: =IF(J32-P32<=0,"ok","oil change") -> ok | R32: =R31 -> 10774.4 | S32: =R32-R31 -> 0 | T32: =T31 -> 155003 | U32: =SUM(T32-T31) -> 0 | V32: =IF(S32>0,U32/S32,0) -> 0 | X32: =X31 -> 10809 | Y32: =IF(R32-X32<=0,"ok","oil change") -> ok | Z32: =C32+K32+S32 -> 0 | AA32: =U32+M32+E32 -> 0 | AB32: =V32+N32+F32 -> 0 | AC32: =IF(Z32>0,AA32/Z32,0) -> 0 | AD32: =ELEC!Q32 -> 0 | AE32: =SUM(AD32/Z32) -> #DIV/0! | AF32: =SUM(AE32/1600) -> #DIV/0! | AG32: =SUM(320*AF32) -> #DIV/0! | AH32: =SUM(AC32-AG32) -> #DIV/0! | AI32: =AD32*AJ32 -> 0 | AJ32: =305/1185 -> 0.25738397 | AK32: =IF(Z32>0,AI32/Z32,0) -> 0
A33: =ELEC!C33 -> 43769 | B33: =B32 -> 8419.09 | C33: =B33-B32 -> 0 | D33: =D32 -> 108938.9 | E33: =SUM(D33-D32) -> 0 | F33: =IF(C33>0,E33/C33,0) -> 0 | H33: =H32 -> 8497 | I33: =IF(B33-H33<=0,"ok","oil change") -> ok | J33: =J32 -> 10453 | K33: =J33-J32 -> 0 | L33: =L32 -> 199931.3 | M33: =SUM(L33-L32) -> 0 | N33: =IF(K33>0,M33/K33,0) -> 0 | P33: =P32 -> 10535 | Q33: =IF(J33-P33<=0,"ok","oil change") -> ok | R33: =R32 -> 10774.4 | S33: =R33-R32 -> 0 | T33: =T32 -> 155003 | U33: =SUM(T33-T32) -> 0 | V33: =IF(S33>0,U33/S33,0) -> 0 | X33: =X32 -> 10809 | Y33: =IF(R33-X33<=0,"ok","oil change") -> ok | Z33: =C33+K33+S33 -> 0 | AA33: =U33+M33+E33 -> 0 | AB33: =V33+N33+F33 -> 0 | AC33: =IF(Z33>0,AA33/Z33,0) -> 0 | AD33: =ELEC!Q33 -> 0 | AE33: =SUM(AD33/Z33) -> #DIV/0! | AF33: =SUM(AE33/1600) -> #DIV/0! | AG33: =SUM(320*AF33) -> #DIV/0! | AH33: =SUM(AC33-AG33) -> #DIV/0!
H34: =#REF!-#REF! -> #REF! | M34: =#REF!-#REF! -> #REF! | P34: =+O34/3 -> 0 | U34: =SUM(C35:S35) -> 153.49 | X34: 341 | Z34: =SUM(Z3:Z33) -> 153.49
C35: =SUM(C3:C33) -> 1.09 | K35: =SUM(K3:K33) -> 76 | S35: =SUM(S3:S33) -> 76.4

Sheet Sheet1
A1: TOTAL CH RH | B1: TOTAL CH cons KW | C1: TOTAL ELIC KW | D1: TOTAL EDL | E1: TOTAL GEN KW | F1: GEN HR | G1: WATER IN | H1: TOTAL CT | I1: TOTAL WATER | J1: Date
A2: =ELEC!T3+ELEC!X1+ELEC!AB3 -> #VALUE! | B2: =ELEC!AF3 -> 7413 | C2: =ELEC!N3 -> 30214 | D2: =C2-E2 -> 19780 | E2: =ELEC!Q3 -> 10434 | F2: =GEN!Z2 -> 18 | G2: =WATER!C5+WATER!H5 -> 410 | H2: =WATER!L5 -> 2 | I2: =WATER!BC5+WATER!BD5+WATER!BE6-Sheet1!G2 -> -455.7 | J2: ='B5'!A4 -> 43738
A3: =ELEC!T4+ELEC!X2+ELEC!AB4 -> 32 | B3: =ELEC!AF4 -> 7447 | C3: =ELEC!N4 -> 32504 | D3: =C3-E3 -> 22220 | E3: =ELEC!Q4 -> 10284 | F3: =GEN!Z3 -> 16 | G3: =WATER!C6+WATER!H6 -> 132 | H3: =WATER!L6 -> 3 | I3: =WATER!BC6+WATER!BD6+WATER!BE7-Sheet1!G3 -> -206.3 | J3: ='B5'!A5 -> 43739
A4: =ELEC!T5+ELEC!X5+ELEC!AB5 -> 28 | B4: =ELEC!AF5 -> 6609 | C4: =ELEC!N5 -> 29402 | D4: =C4-E4 -> 18289 | E4: =ELEC!Q5 -> 11113 | F4: =GEN!Z4 -> 14 | G4: =WATER!C7+WATER!H7 -> 132 | H4: =WATER!L7 -> 3 | I4: =WATER!BC7+WATER!BD7+WATER!BE8-Sheet1!G4 -> -211.2 | J4: ='B5'!A6 -> 43740
A5: =ELEC!T6+ELEC!X6+ELEC!AB6 -> 34 | B5: =ELEC!AF6 -> 6902 | C5: =ELEC!N6 -> 32164 | D5: =C5-E5 -> 24777 | E5: =ELEC!Q6 -> 7387 | F5: =GEN!Z5 -> 17 | G5: =WATER!C8+WATER!H8 -> 185 | H5: =WATER!L8 -> 3 | I5: =WATER!BC8+WATER!BD8+WATER!BE9-Sheet1!G5 -> -178.5 | J5: ='B5'!A7 -> 43741
A6: =ELEC!T7+ELEC!X7+ELEC!AB7 -> 30 | B6: =ELEC!AF7 -> 6849 | C6: =ELEC!N7 -> 31146 | D6: =C6-E6 -> 31146 | E6: =ELEC!Q24 -> 0 | F6: =GEN!Z6 -> 11 | G6: =WATER!C9+WATER!H9 -> 306 | H6: =WATER!L9 -> 0 | I6: =WATER!BC9+WATER!BD9+WATER!BE10-Sheet1!G6 -> -327.9 | J6: ='B5'!A8 -> 43742
A7: =ELEC!T8+ELEC!X8+ELEC!AB8 -> 33 | B7: =ELEC!AF8 -> 6770 | C7: =ELEC!N8 -> 26276.8 | D7: =C7-E7 -> 22132.8 | E7: =ELEC!Q8 -> 4144 | F7: =GEN!Z7 -> 6 | G7: =WATER!C10+WATER!H10 -> 212 | H7: =WATER!L10 -> 10 | I7: =WATER!BC10+WATER!BD10+WATER!BE11-Sheet1!G7 -> -287.1 | J7: ='B5'!A9 -> 43743
A8: =ELEC!T9+ELEC!X9+ELEC!AB9 -> 29 | B8: =ELEC!AF9 -> 6328 | C8: =ELEC!N9 -> 29097.4 | D8: =C8-E8 -> 24358.4 | E8: =ELEC!Q9 -> 4739 | F8: =GEN!Z8 -> 6 | G8: =WATER!C11+WATER!H11 -> 325 | H8: =WATER!L11 -> 3 | I8: =WATER!BC11+WATER!BD11+WATER!BE12-Sheet1!G8 -> -340.5 | J8: ='B5'!A10 -> 43744
A9: =ELEC!T10+ELEC!X10+ELEC!AB10 -> 28 | B9: =ELEC!AF10 -> 6324 | C9: =ELEC!N10 -> 28488.6 | D9: =C9-E9 -> 23930.6 | E9: =ELEC!Q10 -> 4558 | F9: =GEN!Z9 -> 10 | G9: =WATER!C12+WATER!H12 -> 212 | H9: =WATER!L12 -> 4 | I9: =WATER!BC12+WATER!BD12+WATER!BE13-Sheet1!G9 -> -150.1 | J9: ='B5'!A11 -> 43745
A10: =ELEC!T11+ELEC!X11+ELEC!AB11 -> 33 | B10: =ELEC!AF11 -> 7674 | C10: =ELEC!N11 -> 30559.4 | D10: =C10-E10 -> 26133.4 | E10: =ELEC!Q11 -> 4426 | F10: =GEN!Z10 -> 7 | G10: =WATER!C13+WATER!H13 -> 355 | H10: =WATER!L13 -> 3 | I10: =WATER!BC13+WATER!BD13+WATER!BE14-Sheet1!G10 -> -394.2 | J10: ='B5'!A12 -> 43746
A11: =ELEC!T12+ELEC!X12+ELEC!AB12 -> 37 | B11: =ELEC!AF12 -> 7966 | C11: =ELEC!N12 -> 34481.8 | D11: =C11-E11 -> 24978.8 | E11: =ELEC!Q12 -> 9503 | F11: =GEN!Z11 -> 7 | G11: =WATER!C14+WATER!H14 -> 145 | H11: =WATER!L14 -> 3 | I11: =WATER!BC14+WATER!BD14+WATER!BE15-Sheet1!G11 -> -100.3 | J11: ='B5'!A13 -> 43747
A12: =ELEC!T13+ELEC!X13+ELEC!AB13 -> 36 | B12: =ELEC!AF13 -> 6972 | C12: =ELEC!N13 -> 30373.2 | D12: =C12-E12 -> 19732.2 | E12: =ELEC!Q13 -> 10641 | F12: =GEN!Z12 -> 14 | G12: =WATER!C15+WATER!H15 -> 357 | H12: =WATER!L15 -> 3 | I12: =WATER!BC15+WATER!BD15+WATER!BE16-Sheet1!G12 -> -297 | J12: ='B5'!A14 -> 43748
A13: =ELEC!T14+ELEC!X14+ELEC!AB14 -> 29 | B13: =ELEC!AF14 -> 6540 | C13: =ELEC!N14 -> 30850 | D13: =C13-E13 -> 26303 | E13: =ELEC!Q14 -> 4547 | F13: =GEN!Z13 -> 16 | G13: =WATER!C16+WATER!H16 -> 132 | H13: =WATER!L16 -> 3 | I13: =WATER!BC16+WATER!BD16+WATER!BE17-Sheet1!G13 -> -63 | J13: ='B5'!A15 -> 43749
A14: =ELEC!T15+ELEC!X15+ELEC!AB15 -> 31 | B14: =ELEC!AF15 -> 7482 | C14: =ELEC!N15 -> 30370.4 | D14: =C14-E14 -> 26353.4 | E14: =ELEC!Q15 -> 4017 | F14: =GEN!Z14 -> 6 | G14: =WATER!C17+WATER!H17 -> 654 | H14: =WATER!L17 -> 4 | I14: =WATER!BC17+WATER!BD17+WATER!BE18-Sheet1!G14 -> -762.5 | J14: ='B5'!A16 -> 43750
A15: =ELEC!T16+ELEC!X16+ELEC!AB16 -> 31 | B15: =ELEC!AF16 -> 6841 | C15: =ELEC!N16 -> 29315.4 | D15: =C15-E15 -> 18130.4 | E15: =ELEC!Q16 -> 11185 | F15: =GEN!Z15 -> 7.25 | G15: =WATER!C18+WATER!H18 -> 133 | H15: =WATER!L18 -> 3 | I15: =WATER!BC18+WATER!BD18+WATER!BE19-Sheet1!G15 -> -184.1 | J15: ='B5'!A17 -> 43751
A16: =ELEC!T17+ELEC!X17+ELEC!AB17 -> 0 | B16: =ELEC!AF17 -> 0 | C16: =ELEC!N17 -> 0 | D16: =C16-E16 -> 0 | E16: =ELEC!Q17 -> 0 | F16: =GEN!Z16 -> 16.24 | G16: =WATER!C19+WATER!H19 -> 243 | H16: =WATER!L19 -> 3 | I16: =WATER!BC19+WATER!BD19+WATER!BE20-Sheet1!G16 -> -220.8 | J16: ='B5'!A18 -> 43752
A17: =ELEC!T18+ELEC!X18+ELEC!AB18 -> 0 | B17: =ELEC!AF18 -> 0 | C17: =ELEC!N18 -> 0 | D17: =C17-E17 -> 0 | E17: =ELEC!Q18 -> 0 | F17: =GEN!Z17 -> 0 | G17: =WATER!C20+WATER!H20 -> 0 | H17: =WATER!L20 -> 0 | I17: =WATER!BC20+WATER!BD20+WATER!BE21-Sheet1!G17 -> 0 | J17: ='B5'!A19 -> 43753
A18: =ELEC!T19+ELEC!X19+ELEC!AB19 -> 0 | B18: =ELEC!AF19 -> 0 | C18: =ELEC!N19 -> 0 | D18: =C18-E18 -> 0 | E18: =ELEC!Q19 -> 0 | F18: =GEN!Z18 -> 0 | G18: =WATER!C21+WATER!H21 -> 0 | H18: =WATER!L21 -> 0 | I18: =WATER!BC21+WATER!BD21+WATER!BE22-Sheet1!G18 -> 0 | J18: ='B5'!A20 -> 43754
... A29: =ELEC!T30+ELEC!X30+ELEC!AB30 -> 0 | B29: =ELEC!AF30 -> 0 | C29: =ELEC!N30 -> 0 | D29: =C29-E29 -> 0 | E29: =ELEC!Q30 -> 0 | F29: =GEN!Z29 -> 0 | G29: =WATER!C32+WATER!H32 -> 0 | H29: =WATER!L32 -> 0 | I29: =WATER!BC32+WATER!BD32+WATER!BE33-Sheet1!G29 -> 0 | J29: ='B5'!A31 -> 43765
A30: =ELEC!T31+ELEC!X31+ELEC!#REF! -> #REF! | B30: =ELEC!AF31 -> 0 | C30: =ELEC!N31 -> 0 | D30: =C30-E30 -> 0 | E30: =ELEC!Q31 -> 0 | F30: =GEN!Z30 -> 0 | G30: =WATER!C33+WATER!H33 -> 0 | H30: =WATER!L33 -> 0 | I30: =WATER!BC33+WATER!BD33+WATER!BE34-Sheet1!G30 -> 0 | J30: ='B5'!A32 -> 43766
A31: =ELEC!T32+ELEC!X32+ELEC!AB31 -> 0 | B31: =ELEC!AF32 -> 0 | C31: =ELEC!N32 -> 0 | D31: =C31-E31 -> 0 | E31: =ELEC!Q32 -> 0 | F31: =GEN!Z31 -> 0 | G31: =WATER!C34+WATER!H34 -> 0 | H31: =WATER!L34 -> 0 | I31: =WATER!BC34+WATER!BD34+WATER!BE35-Sheet1!G31 -> 0 | J31: ='B5'!A33 -> 43767
A32: =ELEC!#REF!+ELEC!#REF!+ELEC!#REF! -> #REF! | B32: =ELEC!#REF! -> #REF! | C32: =ELEC!#REF! -> #REF! | D32: =C32-E32 -> #REF! | E32: =ELEC!#REF! -> #REF! | F32: =GEN!#REF! -> #REF! | G32: =WATER!#REF!+WATER!#REF! -> #REF! | H32: =WATER!#REF! -> #REF! | I32: =WATER!#REF!+WATER!#REF!+WATER!BE37-Sheet1!G32 -> #REF!

Sheet Report
B1: Boiler Fuel | C1: Steam Fuel | D1: GEN FUEL | E1: FUEL TOTAL | F1: CT/mᶾ | G1: Water Consumption | H1: Chiller KW | I1: GEN KW | J1: EDL KW | K1: occ | L1: covers | M1: temp. C⁰ | N1: RH %
B3: ='B5'!V3 -> 0 | C3: ='B5'!AH3 -> 0 | E3: =B3+C3+D3 -> 0
A4: 42704 | B4: 810 | C4: -606.1 | D4: 1420.5021 | E4: 1624.4021 | F4: 106 | G4: -58.4 | H4: 6284 | I4: 2399 | J4: 23932 | K4: 0 | L4: 0 | M4: 0 | N4: 0
A5: ='B5'!A5 -> 43739 | B5: ='B5'!V5 -> 296 | C5: ='B5'!AH5 -> 543.1 | D5: =GEN!AI3 -> 2685.5443 | E5: =B5+C5+D5 -> 3524.6443 | F5: =WATER!L5 -> 2 | G5: =WATER!BG5 -> 77.7 | H5: =ELEC!AF3 -> 7413 | I5: =ELEC!Q3 -> 10434 | J5: =ELEC!R3 -> 19780
A6: ='B5'!A6 -> 43740 | B6: ='B5'!V6 -> 294 | C6: ='B5'!AH6 -> 508.6 | D6: =GEN!AI4 -> 2646.9367 | E6: =B6+C6+D6 -> 3449.5367 | F6: =WATER!L6 -> 3 | G6: =WATER!BG6 -> -73 | H6: =ELEC!AF4 -> 7447 | I6: =ELEC!Q4 -> 10284 | J6: =ELEC!R4 -> 22220
