Workbook

Sheet Total
A1: Site Name | B1: Day | C1: Month | D1: Year | E1: Total Electricity Kwh | F1: Electricity Tariff ($/Kwh) | G1: LPG (Kg) | H1: LPG $/Kg | I1: Water Utility Supply (m3) m3 | J1: Water Utility Supply (m3) $/m3 | K1: Room Nights | L1: Utilities day cost dh
A2: Serengeti | B2: 1 | C2: 10 | D2: 2019 | E2: ='UTILITY REPORT 1'!F3 -> 5669 | F2: =('UTILITY REPORT 1'!E3*'UTILITY REPORT 1'!D3)/'UTILITY REPORT 1'!F3 -> 0.38445581 | G2: =IF('Utility summery'!M6<0,"0",'Utility summery'!M6) -> 95.964 | H2: 0 | I2: =IF('UTILITY REPORT 1'!G3<0,"0",'UTILITY REPORT 1'!G3) -> 130 | J2: 0 | K2: ='UTILITY REPORT 1'!C3 -> 48 | L2: =E2*F2+G2*H2+#REF!*#REF!+I2*J2 -> #REF!
A3: Serengeti | B3: =B2+1 -> 2 | C3: 10 | D3: 2019 | E3: ='UTILITY REPORT 1'!F4 -> 6159 | F3: =('UTILITY REPORT 1'!E4*'UTILITY REPORT 1'!D4)/'UTILITY REPORT 1'!F4 -> 0.40150187 | G3: =IF('Utility summery'!M7<0,"0",'Utility summery'!M7) -> 112.596 | H3: 0 | I3: =IF('UTILITY REPORT 1'!G4<0,"0",'UTILITY REPORT 1'!G4) -> 128 | J3: 0 | K3: ='UTILITY REPORT 1'!C4 -> 62 | L3: =E3*F3+G3*H3+#REF!*#REF!+I3*J3 -> #REF!
A4: Serengeti | B4: =B3+1 -> 3 | C4: 10 | D4: 2019 | E4: ='UTILITY REPORT 1'!F5 -> 6580 | F4: =('UTILITY REPORT 1'!E5*'UTILITY REPORT 1'!D5)/'UTILITY REPORT 1'!F5 -> 0.38820517 | G4: =IF('Utility summery'!M8<0,"0",'Utility summery'!M8) -> 116.16 | H4: 0 | I4: =IF('UTILITY REPORT 1'!G5<0,"0",'UTILITY REPORT 1'!G5) -> 120 | J4: 0 | K4: ='UTILITY REPORT 1'!C5 -> 41 | L4: =E4*F4+G4*H4+#REF!*#REF!+I4*J4 -> #REF!
A5: Serengeti | B5: =B4+1 -> 4 | C5: 10 | D5: 2019 | E5: ='UTILITY REPORT 1'!F6 -> 6223 | F5: =('UTILITY REPORT 1'!E6*'UTILITY REPORT 1'!D6)/'UTILITY REPORT 1'!F6 -> 0.39232203 | G5: =IF('Utility summery'!M9<0,"0",'Utility summery'!M9) -> 117.92 | H5: 0 | I5: =IF('UTILITY REPORT 1'!G6<0,"0",'UTILITY REPORT 1'!G6) -> 120 | J5: 0 | K5: ='UTILITY REPORT 1'!C6 -> 47 | L5: =E5*F5+G5*H5+#REF!*#REF!+I5*J5 -> #REF!
A6: Serengeti | B6: =B5+1 -> 5 | C6: 10 | D6: 2019 | E6: ='UTILITY REPORT 1'!F7 -> 5984 | F6: =('UTILITY REPORT 1'!E7*'UTILITY REPORT 1'!D7)/'UTILITY REPORT 1'!F7 -> 0.39076872 | G6: =IF('Utility summery'!M10<0,"0",'Utility summery'!M10) -> 121.44 | H6: 0 | I6: =IF('UTILITY REPORT 1'!G7<0,"0",'UTILITY REPORT 1'!G7) -> 114 | J6: 0 | K6: ='UTILITY REPORT 1'!C7 -> 53 | L6: =E6*F6+G6*H6+#REF!*#REF!+I6*J6 -> #REF!
A7: Serengeti | B7: =B6+1 -> 6 | C7: 10 | D7: 2019 | E7: ='UTILITY REPORT 1'!F8 -> 6103 | F7: =('UTILITY REPORT 1'!E8*'UTILITY REPORT 1'!D8)/'UTILITY REPORT 1'!F8 -> 0.40617729 | G7: =IF('Utility summery'!M11<0,"0",'Utility summery'!M11) -> 120.56 | H7: 0 | I7: =IF('UTILITY REPORT 1'!G8<0,"0",'UTILITY REPORT 1'!G8) -> 126 | J7: 0 | K7: ='UTILITY REPORT 1'!C8 -> 41 | L7: =E7*F7+G7*H7+#REF!*#REF!+I7*J7 -> #REF!
A8: Serengeti | B8: =B7+1 -> 7 | C8: 10 | D8: 2019 | E8: ='UTILITY REPORT 1'!F9 -> 5576 | F8: =('UTILITY REPORT 1'!E9*'UTILITY REPORT 1'!D9)/'UTILITY REPORT 1'!F9 -> 0.40825681 | G8: =IF('Utility summery'!M12<0,"0",'Utility summery'!M12) -> 119.68 | H8: 0 | I8: =IF('UTILITY REPORT 1'!G9<0,"0",'UTILITY REPORT 1'!G9) -> 116 | J8: 0 | K8: ='UTILITY REPORT 1'!C9 -> 58 | L8: =E8*F8+G8*H8+#REF!*#REF!+I8*J8 -> #REF!
A9: Serengeti | B9: =B8+1 -> 8 | C9: 10 | D9: 2019 | E9: ='UTILITY REPORT 1'!F10 -> 5532 | F9: =('UTILITY REPORT 1'!E10*'UTILITY REPORT 1'!D10)/'UTILITY REPORT 1'!F10 -> 0.40535069 | G9: =IF('Utility summery'!M13<0,"0",'Utility summery'!M13) -> 118.36 | H9: 0 | I9: =IF('UTILITY REPORT 1'!G10<0,"0",'UTILITY REPORT 1'!G10) -> 120 | J9: 0 | K9: ='UTILITY REPORT 1'!C10 -> 12 | L9: =E9*F9+G9*H9+#REF!*#REF!+I9*J9 -> #REF!
A10: Serengeti | B10: =B9+1 -> 9 | C10: 10 | D10: 2019 | E10: ='UTILITY REPORT 1'!F11 -> 6233 | F10: =('UTILITY REPORT 1'!E11*'UTILITY REPORT 1'!D11)/'UTILITY REPORT 1'!F11 -> 0.38990374 | G10: =IF('Utility summery'!M14<0,"0",'Utility summery'!M14) -> 117.04 | H10: 0 | I10: =IF('UTILITY REPORT 1'!G11<0,"0",'UTILITY REPORT 1'!G11) -> 107 | J10: 0 | K10: ='UTILITY REPORT 1'!C11 -> 34 | L10: =E10*F10+G10*H10+#REF!*#REF!+I10*J10 -> #REF!
A11: Serengeti | B11: =B10+1 -> 10 | C11: 10 | D11: 2019 | E11: ='UTILITY REPORT 1'!F12 -> 6063 | F11: =('UTILITY REPORT 1'!E12*'UTILITY REPORT 1'!D12)/'UTILITY REPORT 1'!F12 -> 0.40636154 | G11: =IF('Utility summery'!M15<0,"0",'Utility summery'!M15) -> 116.16 | H11: 0 | I11: =IF('UTILITY REPORT 1'!G12<0,"0",'UTILITY REPORT 1'!G12) -> 123 | J11: 0 | K11: ='UTILITY REPORT 1'!C12 -> 25 | L11: =E11*F11+G11*H11+#REF!*#REF!+I11*J11 -> #REF!
A12: Serengeti | B12: =B11+1 -> 11 | C12: 10 | D12: 2019 | E12: ='UTILITY REPORT 1'!F13 -> 5967 | F12: =('UTILITY REPORT 1'!E13*'UTILITY REPORT 1'!D13)/'UTILITY REPORT 1'!F13 -> 0.38716105 | G12: =IF('Utility summery'!M16<0,"0",'Utility summery'!M16) -> 110.88 | H12: 0 | I12: =IF('UTILITY REPORT 1'!G13<0,"0",'UTILITY REPORT 1'!G13) -> 112 | J12: 0 | K12: ='UTILITY REPORT 1'!C13 -> 35 | L12: =E12*F12+G12*H12+#REF!*#REF!+I12*J12 -> #REF!
A13: Serengeti | B13: =B12+1 -> 12 | C13: 10 | D13: 2019 | E13: ='UTILITY REPORT 1'!F14 -> 5863 | F13: =('UTILITY REPORT 1'!E14*'UTILITY REPORT 1'!D14)/'UTILITY REPORT 1'!F14 -> 0.41432202 | G13: =IF('Utility summery'!M17<0,"0",'Utility summery'!M17) -> 108.24 | H13: 0 | I13: =IF('UTILITY REPORT 1'!G14<0,"0",'UTILITY REPORT 1'!G14) -> 128 | J13: 0 | K13: ='UTILITY REPORT 1'!C14 -> 32 | L13: =E13*F13+G13*H13+#REF!*#REF!+I13*J13 -> #REF!
A14: Serengeti | B14: =B13+1 -> 13 | C14: 10 | D14: 2019 | E14: ='UTILITY REPORT 1'!F15 -> 5720 | F14: =('UTILITY REPORT 1'!E15*'UTILITY REPORT 1'!D15)/'UTILITY REPORT 1'!F15 -> 0.39327448 | G14: =IF('Utility summery'!M18<0,"0",'Utility summery'!M18) -> 104.28 | H14: 0 | I14: =IF('UTILITY REPORT 1'!G15<0,"0",'UTILITY REPORT 1'!G15) -> 114 | J14: 0 | K14: ='UTILITY REPORT 1'!C15 -> 30 | L14: =E14*F14+G14*H14+#REF!*#REF!+I14*J14 -> #REF!
... A31: Serengeti | B31: =B30+1 -> 30 | C31: 10 | D31: 2019 | E31: ='UTILITY REPORT 1'!F32 -> 5192 | F31: =('UTILITY REPORT 1'!E32*'UTILITY REPORT 1'!D32)/'UTILITY REPORT 1'!F32 -> 0.39170647 | G31: =IF('Utility summery'!M35<0,"0",'Utility summery'!M35) -> 106.92 | H31: 0 | I31: =IF('UTILITY REPORT 1'!G32<0,"0",'UTILITY REPORT 1'!G32) -> 99 | J31: 0 | K31: ='UTILITY REPORT 1'!C32 -> 32 | L31: =E31*F31+G31*H31+#REF!*#REF!+I31*J31 -> #REF!
A32: Serengeti | B32: =B31+1 -> 31 | C32: 10 | D32: 2019 | E32: ='UTILITY REPORT 1'!F33 -> 5234 | F32: =('UTILITY REPORT 1'!E33*'UTILITY REPORT 1'!D33)/'UTILITY REPORT 1'!F33 -> 0.40627054 | G32: =IF('Utility summery'!M36<0,"0",'Utility summery'!M36) -> 119.68 | H32: 0 | I32: =IF('UTILITY REPORT 1'!G33<0,"0",'UTILITY REPORT 1'!G33) -> 111 | J32: 0 | K32: ='UTILITY REPORT 1'!C33 -> 25

Sheet Submetering
A1: Site Name | B1: Day | C1: Month | D1: Year | E1: Transport Consumption (LT) | F1: Generators Consumption (LT) | G1: Total Electricity Kwh | H1: Kitchen (KWh) | I1: Laundry (KWh) | J1: STP (M3) | K1: RO prodution (M3) | L1: Amani Restaurant (M3) | M1: Kitchen (M3) | N1: Laundry (M3) | O1: Laundry (M3) | P1: Total water consumption (m3) | Q1: Borehole #1 (M3) | R1: Borehole #2 (M3) | S1: Borehole #3 (M3) | T1: Borehole #4 (M3) | U1: Borehole #5 (M3) | V1: Borehole #6 (M3) | W1: Total Bore Holes production (m3)
A2: Serengeti | B2: 1 | C2: 10 | D2: 2019 | E2: ='UTILITY REPORT 1'!I3 -> 203.28 | F2: ='UTILITY REPORT 1'!E3 -> 2179.48 | G2: ='UTILITY REPORT 1'!F3 -> 5669 | H2: =IF('Kit report'!F4<0,"0",'Kit report'!F4) -> 420 | I2: =IF('Kit report'!X4<0,"0",'Kit report'!X4) -> 740 | J2: =IF('Utility summery'!H6<0,"0",'Utility summery'!H6) -> 41 | K2: =IF('UTILITY REPORT 1'!H3<0,"0",'UTILITY REPORT 1'!H3) -> 26 | L2: =IF('Kit report'!Q4<0,"0",'Kit report'!Q4) -> 2 | M2: =IF('Kit report'!L4<0,"0",'Kit report'!L4) -> 11 | N2: =IF('Kit report'!AC4<0,"0",'Kit report'!AC4) -> 15149.1 | O2: =K2*E2+H2*I2+#REF!*#REF!+J2*L2 -> #REF! | P2: ='Water-Meter'!E6 -> 130 | Q2: =IF('Water-Meter'!U6<0,"0",'Water-Meter'!U6) -> 25 | R2: =IF('Water-Meter'!X6<0,"0",'Water-Meter'!X6) -> 51 | S2: =IF('Water-Meter'!AA6<0,"0",'Water-Meter'!AA6) -> 50 | T2: =IF('Water-Meter'!AD6<0,"0",'Water-Meter'!AD6) -> 0 | U2: =IF('Water-Meter'!AG6<0,"0",'Water-Meter'!AG6) -> 13 | V2: =IF('Water-Meter'!AJ6<0,"0",'Water-Meter'!AJ6) -> 21 | W2: ='Water-Meter'!AN6 -> 160
A3: Serengeti | B3: =B2+1 -> 2 | C3: 10 | D3: 2019 | E3: ='UTILITY REPORT 1'!I4 -> 31.45 | F3: ='UTILITY REPORT 1'!E4 -> 2472.85 | G3: ='UTILITY REPORT 1'!F4 -> 6159 | H3: =IF('Kit report'!F5<0,"0",'Kit report'!F5) -> 480 | I3: =IF('Kit report'!X5<0,"0",'Kit report'!X5) -> 900 | J3: =IF('Utility summery'!H7<0,"0",'Utility summery'!H7) -> 44 | K3: =IF('UTILITY REPORT 1'!H4<0,"0",'UTILITY REPORT 1'!H4) -> 177 | L3: =IF('Kit report'!Q5<0,"0",'Kit report'!Q5) -> 4 | M3: =IF('Kit report'!L5<0,"0",'Kit report'!L5) -> 20 | N3: =IF('Kit report'!AC5<0,"0",'Kit report'!AC5) -> 7 | O3: =K3*E3+H3*I3+#REF!*#REF!+J3*L3 -> #REF! | P3: ='Water-Meter'!E7 -> 128 | Q3: =IF('Water-Meter'!U7<0,"0",'Water-Meter'!U7) -> 29 | R3: =IF('Water-Meter'!X7<0,"0",'Water-Meter'!X7) -> 54 | S3: =IF('Water-Meter'!AA7<0,"0",'Water-Meter'!AA7) -> 52 | T3: =IF('Water-Meter'!AD7<0,"0",'Water-Meter'!AD7) -> 0 | U3: =IF('Water-Meter'!AG7<0,"0",'Water-Meter'!AG7) -> 13 | V3: =IF('Water-Meter'!AJ7<0,"0",'Water-Meter'!AJ7) -> 20 | W3: ='Water-Meter'!AN7 -> 168
A4: Serengeti | B4: =B3+1 -> 3 | C4: 10 | D4: 2019 | E4: ='UTILITY REPORT 1'!I5 -> 106.26 | F4: ='UTILITY REPORT 1'!E5 -> 2554.39 | G4: ='UTILITY REPORT 1'!F5 -> 6580 | H4: =IF('Kit report'!F6<0,"0",'Kit report'!F6) -> 504 | I4: =IF('Kit report'!X6<0,"0",'Kit report'!X6) -> 940 | J4: =IF('Utility summery'!H8<0,"0",'Utility summery'!H8) -> 41 | K4: =IF('UTILITY REPORT 1'!H5<0,"0",'UTILITY REPORT 1'!H5) -> 128 | L4: =IF('Kit report'!Q6<0,"0",'Kit report'!Q6) -> 3 | M4: =IF('Kit report'!L6<0,"0",'Kit report'!L6) -> 18 | N4: =IF('Kit report'!AC6<0,"0",'Kit report'!AC6) -> 9 | O4: =K4*E4+H4*I4+#REF!*#REF!+J4*L4 -> #REF! | P4: ='Water-Meter'!E8 -> 120 | Q4: =IF('Water-Meter'!U8<0,"0",'Water-Meter'!U8) -> 30 | R4: =IF('Water-Meter'!X8<0,"0",'Water-Meter'!X8) -> 52 | S4: =IF('Water-Meter'!AA8<0,"0",'Water-Meter'!AA8) -> 51 | T4: =IF('Water-Meter'!AD8<0,"0",'Water-Meter'!AD8) -> 0 | U4: =IF('Water-Meter'!AG8<0,"0",'Water-Meter'!AG8) -> 12 | V4: =IF('Water-Meter'!AJ8<0,"0",'Water-Meter'!AJ8) -> 22 | W4: ='Water-Meter'!AN8 -> 167
A5: Serengeti | B5: =B4+1 -> 4 | C5: 10 | D5: 2019 | E5: ='UTILITY REPORT 1'!I6 -> 292.31 | F5: ='UTILITY REPORT 1'!E6 -> 2441.42 | G5: ='UTILITY REPORT 1'!F6 -> 6223 | H5: =IF('Kit report'!F7<0,"0",'Kit report'!F7) -> 516 | I5: =IF('Kit report'!X7<0,"0",'Kit report'!X7) -> 920 | J5: =IF('Utility summery'!H9<0,"0",'Utility summery'!H9) -> 69 | K5: =IF('UTILITY REPORT 1'!H6<0,"0",'UTILITY REPORT 1'!H6) -> 115 | L5: =IF('Kit report'!Q7<0,"0",'Kit report'!Q7) -> 4 | M5: =IF('Kit report'!L7<0,"0",'Kit report'!L7) -> 13 | N5: =IF('Kit report'!AC7<0,"0",'Kit report'!AC7) -> 12 | O5: =K5*E5+H5*I5+#REF!*#REF!+J5*L5 -> #REF! | P5: ='Water-Meter'!E9 -> 120 | Q5: =IF('Water-Meter'!U9<0,"0",'Water-Meter'!U9) -> 41 | R5: =IF('Water-Meter'!X9<0,"0",'Water-Meter'!X9) -> 48 | S5: =IF('Water-Meter'!AA9<0,"0",'Water-Meter'!AA9) -> 62 | T5: =IF('Water-Meter'!AD9<0,"0",'Water-Meter'!AD9) -> 15 | U5: =IF('Water-Meter'!AG9<0,"0",'Water-Meter'!AG9) -> 10 | V5: =IF('Water-Meter'!AJ9<0,"0",'Water-Meter'!AJ9) -> 18 | W5: ='Water-Meter'!AN9 -> 194
A6: Serengeti | B6: =B5+1 -> 5 | C6: 10 | D6: 2019 | E6: ='UTILITY REPORT 1'!I7 -> 79.16 | F6: ='UTILITY REPORT 1'!E7 -> 2338.36 | G6: ='UTILITY REPORT 1'!F7 -> 5984 | H6: =IF('Kit report'!F8<0,"0",'Kit report'!F8) -> 540 | I6: =IF('Kit report'!X8<0,"0",'Kit report'!X8) -> 1040 | J6: =IF('Utility summery'!H10<0,"0",'Utility summery'!H10) -> 44 | K6: =IF('UTILITY REPORT 1'!H7<0,"0",'UTILITY REPORT 1'!H7) -> 86 | L6: =IF('Kit report'!Q8<0,"0",'Kit report'!Q8) -> 3 | M6: =IF('Kit report'!L8<0,"0",'Kit report'!L8) -> 15 | N6: =IF('Kit report'!AC8<0,"0",'Kit report'!AC8) -> 11 | O6: =K6*E6+H6*I6+#REF!*#REF!+J6*L6 -> #REF! | P6: ='Water-Meter'!E10 -> 114 | Q6: =IF('Water-Meter'!U10<0,"0",'Water-Meter'!U10) -> 29 | R6: =IF('Water-Meter'!X10<0,"0",'Water-Meter'!X10) -> 50 | S6: =IF('Water-Meter'!AA10<0,"0",'Water-Meter'!AA10) -> 63 | T6: =IF('Water-Meter'!AD10<0,"0",'Water-Meter'!AD10) -> 9 | U6: =IF('Water-Meter'!AG10<0,"0",'Water-Meter'!AG10) -> 11 | V6: =IF('Water-Meter'!AJ10<0,"0",'Water-Meter'!AJ10) -> 20 | W6: ='Water-Meter'!AN10 -> 182
A7: Serengeti | B7: =B6+1 -> 6 | C7: 10 | D7: 2019 | E7: ='UTILITY REPORT 1'!I8 -> 115.65 | F7: ='UTILITY REPORT 1'!E8 -> 2478.9 | G7: ='UTILITY REPORT 1'!F8 -> 6103 | H7: =IF('Kit report'!F9<0,"0",'Kit report'!F9) -> 444 | I7: =IF('Kit report'!X9<0,"0",'Kit report'!X9) -> 1060 | J7: =IF('Utility summery'!H11<0,"0",'Utility summery'!H11) -> 48 | K7: =IF('UTILITY REPORT 1'!H8<0,"0",'UTILITY REPORT 1'!H8) -> 114 | L7: =IF('Kit report'!Q9<0,"0",'Kit report'!Q9) -> 2 | M7: =IF('Kit report'!L9<0,"0",'Kit report'!L9) -> 16 | N7: =IF('Kit report'!AC9<0,"0",'Kit report'!AC9) -> 7 | O7: =K7*E7+H7*I7+#REF!*#REF!+J7*L7 -> #REF! | P7: ='Water-Meter'!E11 -> 126 | Q7: =IF('Water-Meter'!U11<0,"0",'Water-Meter'!U11) -> 30 | R7: =IF('Water-Meter'!X11<0,"0",'Water-Meter'!X11) -> 51 | S7: =IF('Water-Meter'!AA11<0,"0",'Water-Meter'!AA11) -> 68 | T7: =IF('Water-Meter'!AD11<0,"0",'Water-Meter'!AD11) -> 8 | U7: =IF('Water-Meter'!AG11<0,"0",'Water-Meter'!AG11) -> 11 | V7: =IF('Water-Meter'!AJ11<0,"0",'Water-Meter'!AJ11) -> 21 | W7: ='Water-Meter'!AN11 -> 189
A8: Serengeti | B8: =B7+1 -> 7 | C8: 10 | D8: 2019 | E8: ='UTILITY REPORT 1'!I9 -> 74.81 | F8: ='UTILITY REPORT 1'!E9 -> 2276.44 | G8: ='UTILITY REPORT 1'!F9 -> 5576 | H8: =IF('Kit report'!F10<0,"0",'Kit report'!F10) -> 528 | I8: =IF('Kit report'!X10<0,"0",'Kit report'!X10) -> 1120 | J8: =IF('Utility summery'!H12<0,"0",'Utility summery'!H12) -> 45 | K8: =IF('UTILITY REPORT 1'!H9<0,"0",'UTILITY REPORT 1'!H9) -> 107 | L8: =IF('Kit report'!Q10<0,"0",'Kit report'!Q10) -> 3 | M8: =IF('Kit report'!L10<0,"0",'Kit report'!L10) -> 13 | N8: =IF('Kit report'!AC10<0,"0",'Kit report'!AC10) -> 13 | O8: =K8*E8+H8*I8+#REF!*#REF!+J8*L8 -> #REF! | P8: ='Water-Meter'!E12 -> 116 | Q8: =IF('Water-Meter'!U12<0,"0",'Water-Meter'!U12) -> 30 | R8: =IF('Water-Meter'!X12<0,"0",'Water-Meter'!X12) -> 49 | S8: =IF('Water-Meter'!AA12<0,"0",'Water-Meter'!AA12) -> 56 | T8: =IF('Water-Meter'!AD12<0,"0",'Water-Meter'!AD12) -> 8 | U8: =IF('Water-Meter'!AG12<0,"0",'Water-Meter'!AG12) -> 6 | V8: =IF('Water-Meter'!AJ12<0,"0",'Water-Meter'!AJ12) -> 19 | W8: ='Water-Meter'!AN12 -> 168
A9: Serengeti | B9: =B8+1 -> 8 | C9: 10 | D9: 2019 | E9: ='UTILITY REPORT 1'!I10 -> 94.01 | F9: ='UTILITY REPORT 1'!E10 -> 2242.4 | G9: ='UTILITY REPORT 1'!F10 -> 5532 | H9: =IF('Kit report'!F11<0,"0",'Kit report'!F11) -> 492 | I9: =IF('Kit report'!X11<0,"0",'Kit report'!X11) -> 900 | J9: =IF('Utility summery'!H13<0,"0",'Utility summery'!H13) -> 50 | K9: =IF('UTILITY REPORT 1'!H10<0,"0",'UTILITY REPORT 1'!H10) -> 52 | L9: =IF('Kit report'!Q11<0,"0",'Kit report'!Q11) -> 2 | M9: =IF('Kit report'!L11<0,"0",'Kit report'!L11) -> 14 | N9: =IF('Kit report'!AC11<0,"0",'Kit report'!AC11) -> 10 | O9: =K9*E9+H9*I9+#REF!*#REF!+J9*L9 -> #REF! | P9: ='Water-Meter'!E13 -> 120 | Q9: =IF('Water-Meter'!U13<0,"0",'Water-Meter'!U13) -> 32 | R9: =IF('Water-Meter'!X13<0,"0",'Water-Meter'!X13) -> 50 | S9: =IF('Water-Meter'!AA13<0,"0",'Water-Meter'!AA13) -> 58 | T9: =IF('Water-Meter'!AD13<0,"0",'Water-Meter'!AD13) -> 8 | U9: =IF('Water-Meter'!AG13<0,"0",'Water-Meter'!AG13) -> 14 | V9: =IF('Water-Meter'!AJ13<0,"0",'Water-Meter'!AJ13) -> 20 | W9: ='Water-Meter'!AN13 -> 182
A10: Serengeti | B10: =B9+1 -> 9 | C10: 10 | D10: 2019 | E10: ='UTILITY REPORT 1'!I11 -> 284.83 | F10: ='UTILITY REPORT 1'!E11 -> 2430.27 | G10: ='UTILITY REPORT 1'!F11 -> 6233 | H10: =IF('Kit report'!F12<0,"0",'Kit report'!F12) -> 528 | I10: =IF('Kit report'!X12<0,"0",'Kit report'!X12) -> 860 | J10: =IF('Utility summery'!H14<0,"0",'Utility summery'!H14) -> 48 | K10: =IF('UTILITY REPORT 1'!H11<0,"0",'UTILITY REPORT 1'!H11) -> 33 | L10: =IF('Kit report'!Q12<0,"0",'Kit report'!Q12) -> 3 | M10: =IF('Kit report'!L12<0,"0",'Kit report'!L12) -> 17 | N10: =IF('Kit report'!AC12<0,"0",'Kit report'!AC12) -> 7 | O10: =K10*E10+H10*I10+#REF!*#REF!+J10*L10 -> #REF! | P10: ='Water-Meter'!E14 -> 107 | Q10: =IF('Water-Meter'!U14<0,"0",'Water-Meter'!U14) -> 31 | R10: =IF('Water-Meter'!X14<0,"0",'Water-Meter'!X14) -> 49 | S10: =IF('Water-Meter'!AA14<0,"0",'Water-Meter'!AA14) -> 58 | T10: =IF('Water-Meter'!AD14<0,"0",'Water-Meter'!AD14) -> 8 | U10: =IF('Water-Meter'!AG14<0,"0",'Water-Meter'!AG14) -> 10 | V10: =IF('Water-Meter'!AJ14<0,"0",'Water-Meter'!AJ14) -> 20 | W10: ='Water-Meter'!AN14 -> 176
A11: Serengeti | B11: =B10+1 -> 10 | C11: 10 | D11: 2019 | E11: ='UTILITY REPORT 1'!I12 -> 106.04 | F11: ='UTILITY REPORT 1'!E12 -> 2463.77 | G11: ='UTILITY REPORT 1'!F12 -> 6063 | H11: =IF('Kit report'!F13<0,"0",'Kit report'!F13) -> 528 | I11: =IF('Kit report'!X13<0,"0",'Kit report'!X13) -> 780 | J11: =IF('Utility summery'!H15<0,"0",'Utility summery'!H15) -> 47 | K11: =IF('UTILITY REPORT 1'!H12<0,"0",'UTILITY REPORT 1'!H12) -> 82 | L11: =IF('Kit report'!Q13<0,"0",'Kit report'!Q13) -> 4 | M11: =IF('Kit report'!L13<0,"0",'Kit report'!L13) -> 14 | N11: =IF('Kit report'!AC13<0,"0",'Kit report'!AC13) -> 11 | O11: =K11*E11+H11*I11+#REF!*#REF!+J11*L11 -> #REF! | P11: ='Water-Meter'!E15 -> 123 | Q11: =IF('Water-Meter'!U15<0,"0",'Water-Meter'!U15) -> 30 | R11: =IF('Water-Meter'!X15<0,"0",'Water-Meter'!X15) -> 50 | S11: =IF('Water-Meter'!AA15<0,"0",'Water-Meter'!AA15) -> 56 | T11: =IF('Water-Meter'!AD15<0,"0",'Water-Meter'!AD15) -> 8 | U11: =IF('Water-Meter'!AG15<0,"0",'Water-Meter'!AG15) -> 0 | V11: =IF('Water-Meter'!AJ15<0,"0",'Water-Meter'!AJ15) -> 19 | W11: ='Water-Meter'!AN15 -> 163
A12: Serengeti | B12: =B11+1 -> 11 | C12: 10 | D12: 2019 | E12: ='UTILITY REPORT 1'!I13 -> 263.09 | F12: ='UTILITY REPORT 1'!E13 -> 2310.19 | G12: ='UTILITY REPORT 1'!F13 -> 5967 | H12: =IF('Kit report'!F14<0,"0",'Kit report'!F14) -> 528 | I12: =IF('Kit report'!X14<0,"0",'Kit report'!X14) -> 900 | J12: =IF('Utility summery'!H16<0,"0",'Utility summery'!H16) -> 47 | K12: =IF('UTILITY REPORT 1'!H13<0,"0",'UTILITY REPORT 1'!H13) -> 115 | L12: =IF('Kit report'!Q14<0,"0",'Kit report'!Q14) -> 4 | M12: =IF('Kit report'!L14<0,"0",'Kit report'!L14) -> 17 | N12: =IF('Kit report'!AC14<0,"0",'Kit report'!AC14) -> 9 | O12: =K12*E12+H12*I12+#REF!*#REF!+J12*L12 -> #REF! | P12: ='Water-Meter'!E16 -> 112 | Q12: =IF('Water-Meter'!U16<0,"0",'Water-Meter'!U16) -> 29 | R12: =IF('Water-Meter'!X16<0,"0",'Water-Meter'!X16) -> 52 | S12: =IF('Water-Meter'!AA16<0,"0",'Water-Meter'!AA16) -> 63 | T12: =IF('Water-Meter'!AD16<0,"0",'Water-Meter'!AD16) -> 8 | U12: =IF('Water-Meter'!AG16<0,"0",'Water-Meter'!AG16) -> 0 | V12: =IF('Water-Meter'!AJ16<0,"0",'Water-Meter'!AJ16) -> 23 | W12: ='Water-Meter'!AN16 -> 175
A13: Serengeti | B13: =B12+1 -> 12 | C13: 10 | D13: 2019 | E13: ='UTILITY REPORT 1'!I14 -> 309.36 | F13: ='UTILITY REPORT 1'!E14 -> 2429.17 | G13: ='UTILITY REPORT 1'!F14 -> 5863 | H13: =IF('Kit report'!F15<0,"0",'Kit report'!F15) -> 552 | I13: =IF('Kit report'!X15<0,"0",'Kit report'!X15) -> 860 | J13: =IF('Utility summery'!H17<0,"0",'Utility summery'!H17) -> 46 | K13: =IF('UTILITY REPORT 1'!H14<0,"0",'UTILITY REPORT 1'!H14) -> 21 | L13: =IF('Kit report'!Q15<0,"0",'Kit report'!Q15) -> 3 | M13: =IF('Kit report'!L15<0,"0",'Kit report'!L15) -> 14 | N13: =IF('Kit report'!AC15<0,"0",'Kit report'!AC15) -> 9 | O13: =K13*E13+H13*I13+#REF!*#REF!+J13*L13 -> #REF! | P13: ='Water-Meter'!E17 -> 128 | Q13: =IF('Water-Meter'!U17<0,"0",'Water-Meter'!U17) -> 30 | R13: =IF('Water-Meter'!X17<0,"0",'Water-Meter'!X17) -> 51 | S13: =IF('Water-Meter'!AA17<0,"0",'Water-Meter'!AA17) -> 57 | T13: =IF('Water-Meter'!AD17<0,"0",'Water-Meter'!AD17) -> 8 | U13: =IF('Water-Meter'!AG17<0,"0",'Water-Meter'!AG17) -> 0 | V13: =IF('Water-Meter'!AJ17<0,"0",'Water-Meter'!AJ17) -> 19 | W13: ='Water-Meter'!AN17 -> 165
A14: Serengeti | B14: =B13+1 -> 13 | C14: 10 | D14: 2019 | E14: ='UTILITY REPORT 1'!I15 -> 63.78 | F14: ='UTILITY REPORT 1'!E15 -> 2249.53 | G14: ='UTILITY REPORT 1'!F15 -> 5720 | H14: =IF('Kit report'!F16<0,"0",'Kit report'!F16) -> 480 | I14: =IF('Kit report'!X16<0,"0",'Kit report'!X16) -> 1040 | J14: =IF('Utility summery'!H18<0,"0",'Utility summery'!H18) -> 51 | K14: =IF('UTILITY REPORT 1'!H15<0,"0",'UTILITY REPORT 1'!H15) -> 102 | L14: =IF('Kit report'!Q16<0,"0",'Kit report'!Q16) -> 2 | M14: =IF('Kit report'!L16<0,"0",'Kit report'!L16) -> 14 | N14: =IF('Kit report'!AC16<0,"0",'Kit report'!AC16) -> 9 | O14: =K14*E14+H14*I14+#REF!*#REF!+J14*L14 -> #REF! | P14: ='Water-Meter'!E18 -> 114 | Q14: =IF('Water-Meter'!U18<0,"0",'Water-Meter'!U18) -> 30 | R14: =IF('Water-Meter'!X18<0,"0",'Water-Meter'!X18) -> 44 | S14: =IF('Water-Meter'!AA18<0,"0",'Water-Meter'!AA18) -> 52 | T14: =IF('Water-Meter'!AD18<0,"0",'Water-Meter'!AD18) -> 6 | U14: =IF('Water-Meter'!AG18<0,"0",'Water-Meter'!AG18) -> 12 | V14: =IF('Water-Meter'!AJ18<0,"0",'Water-Meter'!AJ18) -> 18 | W14: ='Water-Meter'!AN18 -> 162
... A31: Serengeti | B31: =B30+1 -> 30 | C31: 10 | D31: 2019 | E31: ='UTILITY REPORT 1'!I32 -> 25.52 | F31: ='UTILITY REPORT 1'!E32 -> 2033.74 | G31: ='UTILITY REPORT 1'!F32 -> 5192 | H31: =IF('Kit report'!F33<0,"0",'Kit report'!F33) -> 960 | I31: =IF('Kit report'!X33<0,"0",'Kit report'!X33) -> 1880 | J31: =IF('Utility summery'!H35<0,"0",'Utility summery'!H35) -> 31 | K31: =IF('UTILITY REPORT 1'!H32<0,"0",'UTILITY REPORT 1'!H32) -> 122 | L31: =IF('Kit report'!Q33<0,"0",'Kit report'!Q33) -> 3 | M31: =IF('Kit report'!L33<0,"0",'Kit report'!L33) -> 16 | N31: =IF('Kit report'!AC33<0,"0",'Kit report'!AC33) -> 8 | O31: =K31*E31+H31*I31+#REF!*#REF!+J31*L31 -> #REF! | P31: ='Water-Meter'!E35 -> 99 | Q31: =IF('Water-Meter'!U35<0,"0",'Water-Meter'!U35) -> 29 | R31: =IF('Water-Meter'!X35<0,"0",'Water-Meter'!X35) -> 51 | S31: =IF('Water-Meter'!AA35<0,"0",'Water-Meter'!AA35) -> 56 | T31: =IF('Water-Meter'!AD35<0,"0",'Water-Meter'!AD35) -> 8 | U31: =IF('Water-Meter'!AG35<0,"0",'Water-Meter'!AG35) -> 14 | V31: =IF('Water-Meter'!AJ35<0,"0",'Water-Meter'!AJ35) -> 19 | W31: ='Water-Meter'!AN35 -> 177
A32: Serengeti | B32: =B31+1 -> 31 | C32: 10 | D32: 2019 | E32: ='UTILITY REPORT 1'!I33 -> 533.66 | F32: ='UTILITY REPORT 1'!E33 -> 2126.42 | G32: ='UTILITY REPORT 1'!F33 -> 5234 | H32: =IF('Kit report'!F34<0,"0",'Kit report'!F34) -> 516 | I32: =IF('Kit report'!X34<0,"0",'Kit report'!X34) -> 800 | J32: =IF('Utility summery'!H36<0,"0",'Utility summery'!H36) -> 30 | K32: =IF('UTILITY REPORT 1'!H33<0,"0",'UTILITY REPORT 1'!H33) -> 45 | L32: =IF('Kit report'!Q34<0,"0",'Kit report'!Q34) -> 3 | M32: =IF('Kit report'!L34<0,"0",'Kit report'!L34) -> 15 | N32: =IF('Kit report'!AC34<0,"0",'Kit report'!AC34) -> 10 | P32: ='Water-Meter'!E36 -> 111 | Q32: =IF('Water-Meter'!U36<0,"0",'Water-Meter'!U36) -> 30 | R32: =IF('Water-Meter'!X36<0,"0",'Water-Meter'!X36) -> 50 | S32: =IF('Water-Meter'!AA36<0,"0",'Water-Meter'!AA36) -> 45 | T32: =IF('Water-Meter'!AD36<0,"0",'Water-Meter'!AD36) -> 6 | U32: =IF('Water-Meter'!AG36<0,"0",'Water-Meter'!AG36) -> 15 | V32: =IF('Water-Meter'!AJ36<0,"0",'Water-Meter'!AJ36) -> 20 | W32: ='Water-Meter'!AN36 -> 166
L33: =IF('Kit report'!Q35<0,"0",'Kit report'!Q35) -> 91

Sheet UTILITY REPORT 1
A1: OCTOBER UTILITY REPORT
A2: Date | B2: % | C2: Guest Rooms Occupied | D2: Diesel cost Per Liter ($) | E2: Diesel consumption (LT) | F2: Power production (KW) | G2: Water consumption (M3) | H2: RO prodution (M3) | I2: Transport Consupmtion (LT)
A3: 43739 | B3: =Gen!B11 -> 0.623 | C3: ='Summery Report'!E5 -> 48 | D3: 1 | E3: =Gen!S11 -> 2179.48 | F3: =Gen!T11 -> 5669 | G3: ='Water-Meter'!E6 -> 130 | H3: ='Utility report '!AC6 -> 26 | I3: =Gen!AJ11 -> 203.28
A4: 43740 | B4: =Gen!B12 -> 0.779 | C4: ='Summery Report'!E6 -> 62 | D4: 1 | E4: =Gen!S12 -> 2472.85 | F4: =Gen!T12 -> 6159 | G4: ='Water-Meter'!E7 -> 128 | H4: ='Utility report '!AC7 -> 177 | I4: =Gen!AJ12 -> 31.45
A5: 43741 | B5: =Gen!B13 -> 0.532 | C5: ='Summery Report'!E7 -> 41 | D5: 1 | E5: =Gen!S13 -> 2554.39 | F5: =Gen!T13 -> 6580 | G5: ='Water-Meter'!E8 -> 120 | H5: ='Utility report '!AC8 -> 128 | I5: =Gen!AJ13 -> 106.26
A6: 43742 | B6: =Gen!B14 -> 0.61 | C6: ='Summery Report'!E8 -> 47 | D6: 1 | E6: =Gen!S14 -> 2441.42 | F6: =Gen!T14 -> 6223 | G6: ='Water-Meter'!E9 -> 120 | H6: ='Utility report '!AC9 -> 115 | I6: =Gen!AJ14 -> 292.31
A7: 43743 | B7: =Gen!B15 -> 0.688 | C7: ='Summery Report'!E9 -> 53 | D7: 1 | E7: =Gen!S15 -> 2338.36 | F7: =Gen!T15 -> 5984 | G7: ='Water-Meter'!E10 -> 114 | H7: ='Utility report '!AC10 -> 86 | I7: =Gen!AJ15 -> 79.16
A8: 43744 | B8: =Gen!B16 -> 0.532 | C8: ='Summery Report'!E10 -> 41 | D8: 1 | E8: =Gen!S16 -> 2478.9 | F8: =Gen!T16 -> 6103 | G8: ='Water-Meter'!E11 -> 126 | H8: ='Utility report '!AC11 -> 114 | I8: =Gen!AJ16 -> 115.65
A9: 43745 | B9: =Gen!B17 -> 0.753 | C9: ='Summery Report'!E11 -> 58 | D9: 1 | E9: =Gen!S17 -> 2276.44 | F9: =Gen!T17 -> 5576 | G9: ='Water-Meter'!E12 -> 116 | H9: ='Utility report '!AC12 -> 107 | I9: =Gen!AJ17 -> 74.81
A10: 43746 | B10: =Gen!B18 -> 0.156 | C10: ='Summery Report'!E12 -> 12 | D10: 1 | E10: =Gen!S18 -> 2242.4 | F10: =Gen!T18 -> 5532 | G10: ='Water-Meter'!E13 -> 120 | H10: ='Utility report '!AC13 -> 52 | I10: =Gen!AJ18 -> 94.01
A11: 43747 | B11: =Gen!B19 -> 0.442 | C11: ='Summery Report'!E13 -> 34 | D11: 1 | E11: =Gen!S19 -> 2430.27 | F11: =Gen!T19 -> 6233 | G11: ='Water-Meter'!E14 -> 107 | H11: ='Utility report '!AC14 -> 33 | I11: =Gen!AJ19 -> 284.83
A12: 43748 | B12: =Gen!B20 -> 0.325 | C12: ='Summery Report'!E14 -> 25 | D12: 1 | E12: =Gen!S20 -> 2463.77 | F12: =Gen!T20 -> 6063 | G12: ='Water-Meter'!E15 -> 123 | H12: ='Utility report '!AC15 -> 82 | I12: =Gen!AJ20 -> 106.04
A13: 43749 | B13: =Gen!B21 -> 0.455 | C13: ='Summery Report'!E15 -> 35 | D13: 1 | E13: =Gen!S21 -> 2310.19 | F13: =Gen!T21 -> 5967 | G13: ='Water-Meter'!E16 -> 112 | H13: ='Utility report '!AC16 -> 115 | I13: =Gen!AJ21 -> 263.09
A14: 43750 | B14: =Gen!B22 -> 0.416 | C14: ='Summery Report'!E16 -> 32 | D14: 1 | E14: =Gen!S22 -> 2429.17 | F14: =Gen!T22 -> 5863 | G14: ='Water-Meter'!E17 -> 128 | H14: ='Utility report '!AC17 -> 21 | I14: =Gen!AJ22 -> 309.36
... A33: 43769 | B33: =Gen!B41 -> 0.325 | C33: ='Summery Report'!E35 -> 25 | D33: 1 | E33: =Gen!S41 -> 2126.42 | F33: =Gen!T41 -> 5234 | G33: ='Water-Meter'!E36 -> 111 | H33: ='Utility report '!AC36 -> 45 | I33: =Gen!AJ41 -> 533.66

Sheet Utility summery
A4: Date | B4: Room Occupied | C4: Electricity Units Generated KW | D4: Diseal | G4: Water | J4: Gas | N4: Cost of utilites
D5: Generator | E5: Transport | F5: Total | G5: RO | H5: STP | I5: Total Consumption | J5: 2 ton | K5: 1 Ton | L5: 1 Ton | M5: Total consumption | N5: Electricity /1.4$/liter | O5: Diseal for Transport | P5: Gas /2.38$/Kg | Q5: Total HLP Cost | R5: Electricity Cost/Room $ | S5: cost/Room $
A6: =[1]Gen!A11 -> 43739 | B6: ='Summery Report'!E5 -> 48 | C6: ='Daily report Gen'!AA6 -> 416 | D6: =Gen!S11 -> 2179.48 | E6: =Gen!AJ11 -> 203.28 | F6: =Gen!AR11 -> 2382.76 | G6: ='Utility report '!AC6 -> 26 | H6: ='Utility report '!AE6 -> 41 | I6: ='Water-Meter'!E6 -> 130 | J6: ='Lpg (2)'!B10 -> 85 | K6: ='Lpg (2)'!C10 -> 41 | L6: ='Lpg (2)'!D10 -> 85 | M6: ='Lpg (2)'!G10 -> 95.964 | O6: =E6 -> 203.28 | P6: ='[1]Lpg (2)'!#REF! -> #REF! | Q6: ='[1]Summery Report'!#REF! -> #REF! | R6: =N6/B6 -> 0 | S6: =Q6/B6 -> #REF!
A7: =[1]Gen!A12 -> 43740 | B7: ='Summery Report'!E6 -> 62 | C7: ='Daily report Gen'!AA7 -> 409 | D7: =Gen!S12 -> 2472.85 | E7: =Gen!AJ12 -> 31.45 | F7: =Gen!AR12 -> 2504.3 | G7: ='Utility report '!AC7 -> 177 | H7: ='Utility report '!AE7 -> 44 | I7: ='Water-Meter'!E7 -> 128 | J7: ='Lpg (2)'!B11 -> 85 | K7: ='Lpg (2)'!C11 -> 38 | L7: ='Lpg (2)'!D11 -> 85 | M7: ='Lpg (2)'!G11 -> 112.596 | N7: =D7*1.4 -> 3461.99 | O7: =E7*1.4 -> 44.03 | P7: ='[1]Lpg (2)'!#REF! -> #REF! | Q7: ='[1]Summery Report'!#REF! -> #REF! | R7: =N7/B7 -> 55.838548 | S7: =Q7/B7 -> #REF!
A8: =[1]Gen!A13 -> 43741 | B8: ='Summery Report'!E7 -> 41 | C8: ='Daily report Gen'!AA8 -> 453 | D8: =Gen!S13 -> 2554.39 | E8: =Gen!AJ13 -> 106.26 | F8: =Gen!AR13 -> 2660.65 | G8: ='Utility report '!AC8 -> 128 | H8: ='Utility report '!AE8 -> 41 | I8: ='Water-Meter'!E8 -> 120 | J8: ='Lpg (2)'!B12 -> 85 | K8: ='Lpg (2)'!C12 -> 33 | L8: ='Lpg (2)'!D12 -> 85 | M8: ='Lpg (2)'!G12 -> 116.16 | N8: =D8*1.4 -> 3576.146 | O8: =E8*1.4 -> 148.764 | P8: ='[1]Lpg (2)'!#REF! -> #REF! | Q8: ='[1]Summery Report'!#REF! -> #REF! | R8: =N8/B8 -> 87.223073 | S8: =Q8/B8 -> #REF!
A9: =[1]Gen!A14 -> 43742 | B9: ='Summery Report'!E8 -> 47 | C9: ='Daily report Gen'!AA9 -> 562 | D9: =Gen!S14 -> 2441.42 | E9: =Gen!AJ14 -> 292.31 | F9: =Gen!AR14 -> 2733.73 | G9: ='Utility report '!AC9 -> 115 | H9: ='Utility report '!AE9 -> 69 | I9: ='Water-Meter'!E9 -> 120 | J9: ='Lpg (2)'!B13 -> 85 | K9: ='Lpg (2)'!C13 -> 29 | L9: ='Lpg (2)'!D13 -> 85 | M9: ='Lpg (2)'!G13 -> 117.92 | N9: =D9*1.4 -> 3417.988 | O9: =E9*1.4 -> 409.234 | P9: ='[1]Lpg (2)'!#REF! -> #REF! | Q9: ='[1]Summery Report'!#REF! -> #REF! | R9: =N9/B9 -> 72.723149 | S9: =Q9/B9 -> #REF!
A10: =[1]Gen!A15 -> 43743 | B10: ='Summery Report'!E9 -> 53 | C10: ='Daily report Gen'!AA10 -> 497 | D10: =Gen!S15 -> 2338.36 | E10: =Gen!AJ15 -> 79.16 | F10: =Gen!AR15 -> 2417.52 | G10: ='Utility report '!AC10 -> 86 | H10: ='Utility report '!AE10 -> 44 | I10: ='Water-Meter'!E10 -> 114 | J10: ='Lpg (2)'!B14 -> 85 | K10: ='Lpg (2)'!C14 -> 24 | L10: ='Lpg (2)'!D14 -> 85 | M10: ='Lpg (2)'!G14 -> 121.44 | N10: =D10*1.4 -> 3273.704 | O10: =E10*1.4 -> 110.824 | P10: ='[1]Lpg (2)'!#REF! -> #REF! | Q10: ='[1]Summery Report'!#REF! -> #REF! | R10: =N10/B10 -> 61.768 | S10: =Q10/B10 -> #REF!
A11: =[1]Gen!A16 -> 43744 | B11: ='Summery Report'!E10 -> 41 | C11: ='Daily report Gen'!AA11 -> 498 | D11: =Gen!S16 -> 2478.9 | E11: =Gen!AJ16 -> 115.65 | F11: =Gen!AR16 -> 2594.55 | G11: ='Utility report '!AC11 -> 114 | H11: ='Utility report '!AE11 -> 48 | I11: ='Water-Meter'!E11 -> 126 | J11: ='Lpg (2)'!B15 -> 85 | K11: ='Lpg (2)'!C15 -> 19 | L11: ='Lpg (2)'!D15 -> 85 | M11: ='Lpg (2)'!G15 -> 120.56 | N11: =D11*1.4 -> 3470.46 | O11: =E11*1.4 -> 161.91 | P11: ='[1]Lpg (2)'!#REF! -> #REF! | Q11: ='[1]Summery Report'!#REF! -> #REF! | R11: =N11/B11 -> 84.645366 | S11: =Q11/B11 -> #REF!
A12: =[1]Gen!A17 -> 43745 | B12: ='Summery Report'!E11 -> 58 | C12: ='Daily report Gen'!AA12 -> 496 | D12: =Gen!S17 -> 2276.44 | E12: =Gen!AJ17 -> 74.81 | F12: =Gen!AR17 -> 2351.25 | G12: ='Utility report '!AC12 -> 107 | H12: ='Utility report '!AE12 -> 45 | I12: ='Water-Meter'!E12 -> 116 | J12: ='Lpg (2)'!B16 -> 85 | K12: ='Lpg (2)'!C16 -> 15 | L12: ='Lpg (2)'!D16 -> 85 | M12: ='Lpg (2)'!G16 -> 119.68 | N12: =D12*1.4 -> 3187.016 | O12: =E12*1.4 -> 104.734 | P12: ='[1]Lpg (2)'!#REF! -> #REF! | Q12: ='[1]Summery Report'!#REF! -> #REF! | R12: =N12/B12 -> 54.948552 | S12: =Q12/B12 -> #REF!
A13: =[1]Gen!A18 -> 43746 | B13: ='Summery Report'!E12 -> 12 | C13: ='Daily report Gen'!AA13 -> 498 | D13: =Gen!S18 -> 2242.4 | E13: =Gen!AJ18 -> 94.01 | F13: =Gen!AR18 -> 2336.41 | G13: ='Utility report '!AC13 -> 52 | H13: ='Utility report '!AE13 -> 50 | I13: ='Water-Meter'!E13 -> 120 | J13: ='Lpg (2)'!B17 -> 85 | K13: ='Lpg (2)'!C17 -> 9 | L13: ='Lpg (2)'!D17 -> 85 | M13: ='Lpg (2)'!G17 -> 118.36 | N13: =D13*1.4 -> 3139.36 | O13: =E13*1.4 -> 131.614 | P13: ='[1]Lpg (2)'!#REF! -> #REF! | Q13: ='[1]Summery Report'!#REF! -> #REF! | R13: =N13/B13 -> 261.61333 | S13: =Q13/B13 -> #REF!
A14: =[1]Gen!A19 -> 43747 | B14: ='Summery Report'!E13 -> 34 | C14: ='Daily report Gen'!AA14 -> 486 | D14: =Gen!S19 -> 2430.27 | E14: =Gen!AJ19 -> 284.83 | F14: =Gen!AR19 -> 2715.1 | G14: ='Utility report '!AC14 -> 33 | H14: ='Utility report '!AE14 -> 48 | I14: ='Water-Meter'!E14 -> 107 | J14: ='Lpg (2)'!B18 -> 85 | K14: ='Lpg (2)'!C18 -> 5 | L14: ='Lpg (2)'!D18 -> 76 | M14: ='Lpg (2)'!G18 -> 117.04 | N14: =D14*1.4 -> 3402.378 | O14: =E14*1.4 -> 398.762 | P14: ='[1]Lpg (2)'!#REF! -> #REF! | Q14: ='[1]Summery Report'!#REF! -> #REF! | R14: =N14/B14 -> 100.06994 | S14: =Q14/B14 -> #REF!
A15: =[1]Gen!A20 -> 43748 | B15: ='Summery Report'!E14 -> 25 | C15: ='Daily report Gen'!AA15 -> 490 | D15: =Gen!S20 -> 2463.77 | E15: =Gen!AJ20 -> 106.04 | F15: =Gen!AR20 -> 2569.81 | G15: ='Utility report '!AC15 -> 82 | H15: ='Utility report '!AE15 -> 47 | I15: ='Water-Meter'!E15 -> 123 | J15: ='Lpg (2)'!B19 -> 85 | K15: ='Lpg (2)'!C19 -> 5 | L15: ='Lpg (2)'!D19 -> 74 | M15: ='Lpg (2)'!G19 -> 116.16 | N15: =D15*1.4 -> 3449.278 | O15: =E15*1.4 -> 148.456 | P15: ='[1]Lpg (2)'!#REF! -> #REF! | Q15: ='[1]Summery Report'!#REF! -> #REF! | R15: =N15/B15 -> 137.97112 | S15: =Q15/B15 -> #REF!
A16: =[1]Gen!A21 -> 43749 | B16: ='Summery Report'!E15 -> 35 | C16: ='Daily report Gen'!AA16 -> 498 | D16: =Gen!S21 -> 2310.19 | E16: =Gen!AJ21 -> 263.09 | F16: =Gen!AR21 -> 2573.28 | G16: ='Utility report '!AC16 -> 115 | H16: ='Utility report '!AE16 -> 47 | I16: ='Water-Meter'!E16 -> 112 | J16: ='Lpg (2)'!B20 -> 85 | K16: ='Lpg (2)'!C20 -> 5 | L16: ='Lpg (2)'!D20 -> 72 | M16: ='Lpg (2)'!G20 -> 110.88 | N16: =D16*1.4 -> 3234.266 | O16: =E16*1.4 -> 368.326 | P16: ='[1]Lpg (2)'!#REF! -> #REF! | Q16: ='[1]Summery Report'!#REF! -> #REF! | R16: =N16/B16 -> 92.4076 | S16: =Q16/B16 -> #REF!
A17: =[1]Gen!A22 -> 43750 | B17: ='Summery Report'!E16 -> 32 | C17: ='Daily report Gen'!AA17 -> 503 | D17: =Gen!S22 -> 2429.17 | E17: =Gen!AJ22 -> 309.36 | F17: =Gen!AR22 -> 2738.53 | G17: ='Utility report '!AC17 -> 21 | H17: ='Utility report '!AE17 -> 46 | I17: ='Water-Meter'!E17 -> 128 | J17: ='Lpg (2)'!B21 -> 85 | K17: ='Lpg (2)'!C21 -> 5 | L17: ='Lpg (2)'!D21 -> 68 | M17: ='Lpg (2)'!G21 -> 108.24 | N17: =D17*1.4 -> 3400.838 | O17: =E17*1.4 -> 433.104 | P17: ='[1]Lpg (2)'!#REF! -> #REF! | Q17: ='[1]Summery Report'!#REF! -> #REF! | R17: =N17/B17 -> 106.27619 | S17: =Q17/B17 -> #REF!
A18: =[1]Gen!A23 -> 43751 | B18: ='Summery Report'!E17 -> 30 | C18: ='Daily report Gen'!AA18 -> 498 | D18: =Gen!S23 -> 2249.53 | E18: =Gen!AJ23 -> 63.78 | F18: =Gen!AR23 -> 2313.31 | G18: ='Utility report '!AC18 -> 102 | H18: ='Utility report '!AE18 -> 51 | I18: ='Water-Meter'!E18 -> 114 | J18: ='Lpg (2)'!B22 -> 85 | K18: ='Lpg (2)'!C22 -> 5 | L18: ='Lpg (2)'!D22 -> 65 | M18: ='Lpg (2)'!G22 -> 104.28 | N18: =D18*1.4 -> 3149.342 | O18: =E18*1.4 -> 89.292 | P18: ='[1]Lpg (2)'!#REF! -> #REF! | Q18: ='[1]Summery Report'!#REF! -> #REF! | R18: =N18/B18 -> 104.97807 | S18: =Q18/B18 -> #REF!
... A32: =[1]Gen!A37 -> 43765 | B32: ='Summery Report'!E31 -> 52 | C32: ='Daily report Gen'!AA32 -> 481 | D32: =Gen!S37 -> 2323.74 | E32: =Gen!AJ37 -> 280.63 | F32: =Gen!AR37 -> 2604.37 | G32: ='Utility report '!AC32 -> 117 | H32: ='Utility report '!AE32 -> 30 | I32: ='Water-Meter'!E32 -> 114 | J32: ='Lpg (2)'!B36 -> 80 | K32: ='Lpg (2)'!C36 -> 85 | L32: ='Lpg (2)'!D36 -> 85 | M32: ='Lpg (2)'!G36 -> 115.28 | N32: =D32*1.4 -> 3253.236 | O32: =E32*1.4 -> 392.882 | P32: ='[1]Lpg (2)'!#REF! -> #REF! | Q32: ='[1]Summery Report'!#REF! -> #REF! | R32: =N32/B32 -> 62.562231 | S32: =Q32/B32 -> #REF!
A33: =[1]Gen!A38 -> 43766 | B33: ='Summery Report'!E32 -> 21 | C33: ='Daily report Gen'!AA33 -> 478 | D33: =Gen!S38 -> 2031.83 | E33: =Gen!AJ38 -> 676.29 | F33: =Gen!AR38 -> 2708.12 | G33: ='Utility report '!AC33 -> 118 | H33: ='Utility report '!AE33 -> 44 | I33: ='Water-Meter'!E33 -> 111 | J33: ='Lpg (2)'!B37 -> 78 | K33: ='Lpg (2)'!C37 -> 85 | L33: ='Lpg (2)'!D37 -> 85 | M33: ='Lpg (2)'!G37 -> 110.44 | N33: =D33*1.4 -> 2844.562 | O33: =E33*1.4 -> 946.806 | P33: ='[1]Lpg (2)'!#REF! -> #REF! | Q33: ='[1]Summery Report'!#REF! -> #REF! | R33: =N33/B33 -> 135.45533 | S33: =Q33/B33 -> #REF! | T33: =3124/13 -> 240.30769
A34: =[1]Gen!A39 -> 43767 | B34: ='Summery Report'!E33 -> 32 | C34: ='Daily report Gen'!AA34 -> 405 | D34: =Gen!S39 -> 2131.37 | E34: =Gen!AJ39 -> 120.7 | F34: =Gen!AR39 -> 2252.07 | G34: ='Utility report '!AC34 -> 116 | H34: ='Utility report '!AE34 -> 38 | I34: ='Water-Meter'!E34 -> 100 | J34: ='Lpg (2)'!B38 -> 77 | K34: ='Lpg (2)'!C38 -> 85 | L34: ='Lpg (2)'!D38 -> 85 | M34: ='Lpg (2)'!G38 -> 109.56 | N34: =D34*1.4 -> 2983.918 | O34: =E34*1.4 -> 168.98 | P34: ='[1]Lpg (2)'!#REF! -> #REF! | Q34: ='[1]Summery Report'!#REF! -> #REF! | R34: =N34/B34 -> 93.247437 | S34: =Q34/B34 -> #REF!
A35: =[1]Gen!A40 -> 43768 | B35: ='Summery Report'!E34 -> 32 | C35: ='Daily report Gen'!AA35 -> 417 | D35: =Gen!S40 -> 2033.74 | E35: =Gen!AJ40 -> 25.52 | F35: =Gen!AR40 -> 2059.26 | G35: ='Utility report '!AC35 -> 122 | H35: ='Utility report '!AE35 -> 31 | I35: ='Water-Meter'!E35 -> 99 | J35: ='Lpg (2)'!B39 -> 76 | K35: ='Lpg (2)'!C39 -> 85 | L35: ='Lpg (2)'!D39 -> 85 | M35: ='Lpg (2)'!G39 -> 106.92 | N35: =D35*1.4 -> 2847.236 | O35: =E35*1.4 -> 35.728 | P35: ='[1]Lpg (2)'!#REF! -> #REF! | Q35: ='[1]Summery Report'!#REF! -> #REF! | R35: =N35/B35 -> 88.976125 | S35: =Q35/B35 -> #REF!
A36: =[1]Gen!A41 -> 43769 | B36: ='Summery Report'!E35 -> 25 | C36: ='Daily report Gen'!AA36 -> 430 | D36: =Gen!S41 -> 2126.42 | E36: =Gen!AJ41 -> 533.66 | F36: =Gen!AR41 -> 2660.08 | G36: ='Utility report '!AC36 -> 45 | H36: ='Utility report '!AE36 -> 30 | I36: ='Water-Meter'!E36 -> 111 | J36: ='Lpg (2)'!B40 -> 75 | K36: ='Lpg (2)'!C40 -> 85 | L36: ='Lpg (2)'!D40 -> 85 | M36: ='Lpg (2)'!G40 -> 119.68 | N36: =D36*1.4 -> 2976.988 | O36: =E36*1.4 -> 747.124 | P36: ='[1]Lpg (2)'!#REF! -> #REF! | Q36: ='[1]Summery Report'!#REF! -> #REF! | R36: =N36/B36 -> 119.07952 | S36: =Q36/B36 -> #REF!
A37: =[1]Gen!A42 -> #REF! | B37: ='Summery Report'!E36 -> 0 | D37: =Gen!S42 -> 0 | E37: =Gen!AJ42 -> 0 | F37: =Gen!AR42 -> 0 | G37: ='Utility report '!AC37 -> -15088 | H37: ='Utility report '!AE37 -> -190819 | J37: ='Lpg (2)'!B41 -> 0 | K37: ='Lpg (2)'!C41 -> 0 | L37: ='Lpg (2)'!D41 -> 0 | M37: ='Lpg (2)'!G41 -> -296060.16 | Q37: ='[1]Summery Report'!#REF! -> #REF! | S37: =Q37/B37 -> #REF!
A39: Total | B39: =SUM(B7:B37) -> 1057 | C39: =SUM(C7:C35) -> 13820 | D39: =SUM(D7:D35) -> 67600.34 | E39: =SUM(E7:E35) -> 5969.06 | F39: =SUM(F7:F35) -> 73569.4 | G39: =SUM(G7:G35) -> 2744 | H39: =SUM(H7:H35) -> 1201 | I39: =SUM(I7:I35) -> 3340 | J39: =SUM(J7:J35) -> 2425 | ... S39: =SUM(S7:S35) -> #REF!

Sheet Utility report 
A1: DAILY UTILITY REPORT AUG 2019
A2: Date | B2: Total occupancy | H2: Diesel balance LTS | I2: Diesel Deliveries | J2: Gen.Diesel consumption LTS | L2: Total Diesel consumption LTS | M2: Water Meter reading | N2: Water consumption m³ | O2: R.O WATER PRODUCTION LTRS + TIME | AA2: Total RO production | AB2: RO Meter reading | AD2: 0 | AF2: GAS TANK A | AG2: GAS TANK B | AH2: GAS TANK C | AI2: Total Gas Tanks | AJ2: Kg /day | AK2: TOTAL GAS cons.
A3: Rate Tsh /$ | B3: 1640 | C3: Diesel cost / lits | D3: 2175 | F3: =SUM(D3/B3) -> 1.3262195 | H3: =SUM([1]Gen!C9) -> 35806.65 | K3: Transport consumption | M3: Balance | O3: PLANT NO 1 | S3: PLANT NO 2 | W3: PLANT NO 3 | AA3: /day | AB3: Balance | AC3: Production | AD3: 0 | AE3: Production | AF3: Capacity | AG3: Capacity | AH3: Capacity | AI3: Kg | AJ3: /day | AK3: /day
B4: Rooms OCC | C4: % | D4: Guest Rooms Occ | F4: Electricity Production Cost /Room Occ by guest | G4: All Cost /Room Occ by guest | O4: Flow M3 | P4: Reading Hours Meter | Q4: Hrs | R4: total production M3 | S4: Flow M3 | T4: Reading Hours Meter | U4: Hrs | V4: total production M3 | W4: Flow M3 | Y4: Hrs | Z4: total production M3 | AA4: M3 | AC4: M3 | AE4: M3 | AF4: 2000 | AG4: 1000 | AH4: 1000 | AI4: =SUM([2]Sheet1!$AA$36) -> 950 | AJ4: Kg | AK4: M3
P5: 18502 | T5: 15719 | X5: 20670 | AB5: 12273 | AD5: 189547 | AF5: 0.85 | AG5: 0.85 | AH5: 0.85
A6: =[1]Gen!A11 -> 43739 | B6: ='Summery Report'!E5 -> 48 | C6: =Gen!B11 -> 0.623 | D6: ='Summery Report'!D5 -> 48 | E6: =SUM(F3) -> 1.3262195 | F6: =SUM(J6*E6)/D6 -> 60.218102 | G6: =SUM(L6*E6)/D6 -> 65.834642 | H6: =SUM([1]Gen!C11) -> 47806.65 | I6: =Gen!D11 -> 12000 | J6: =Gen!S11 -> 2179.48 | K6: =Gen!AJ11 -> 203.28 | L6: =SUM(J6:K6) -> 2382.76 | M6: ='Water-Meter'!K46 -> 531.2547 | P6: 18502 | Q6: =SUM(P6-P5) -> 0 | R6: =SUM(Q6*O6) -> 0 | S6: 4.7 | T6: 15719 | U6: =T6-T5 -> 0 | V6: - | W6: 5 | X6: 20685 | Y6: =X6-X5 -> 15 | Z6: =Y6-Y5 -> 15 | AA6: =Z6-Z5 -> 15 | AB6: 12299 | AC6: =AB6-AB5 -> 26 | AD6: 189588 | AE6: =AD6-AD5 -> 41 | AF6: ='Lpg (2)'!B10*2000/85 -> 2000 | AG6: ='Lpg (2)'!C10*1000/85 -> 482.35294 | AH6: ='Lpg (2)'!D10*1000/85 -> 1000 | AI6: =SUM(AF6*2000)+(AG6*1000)+(AH6*1000) -> 5482352.9 | AJ6: =SUM(AI5-AI6) -> -5482352.9
A7: =[1]Gen!A12 -> 43740 | B7: ='Summery Report'!E6 -> 62 | C7: =Gen!B12 -> 0.779 | D7: ='Summery Report'!D6 -> 62 | E7: =SUM(E6) -> 1.3262195 | F7: =SUM(J7*E7)/D7 -> 52.895837 | G7: =SUM(L7*E7)/D7 -> 53.568573 | H7: =Gen!C12 -> 45423.89 | I7: =Gen!D12 -> 0 | J7: =Gen!S12 -> 2472.85 | K7: =Gen!AJ12 -> 31.45 | L7: =SUM(J7:K7) -> 2504.3 | M7: ='Water-Meter'!K47 -> 535.4545 | P7: 18502 | Q7: =SUM(P7-P6) -> 0 | R7: =SUM(Q7*O7) -> 0 | S7: 4.7 | T7: 15719 | U7: =T7-T6 -> 0 | V7: =SUM(U7*S7) -> 0 | X7: 20709 | Y7: =X7-X6 -> 24 | Z7: =SUM(Y7*W7) -> 0 | AA7: =SUM(Z7*X9) -> 0 | AB7: 12476 | AC7: =AB7-AB6 -> 177 | AD7: 189632 | AE7: =AD7-AD6 -> 44 | AF7: ='Lpg (2)'!B11*2000/85 -> 2000 | AG7: ='Lpg (2)'!C11*1000/85 -> 447.05882 | AH7: ='Lpg (2)'!D11*1000/85 -> 1000 | AI7: =SUM(AF6*2000)+(AG7*1000)+(AH7*1000) -> 5447058.8 | AJ7: =SUM(AI6-AI7) -> 35294.118
A8: =[1]Gen!A13 -> 43741 | B8: ='Summery Report'!E7 -> 41 | C8: =Gen!B13 -> 0.532 | D8: ='Summery Report'!D7 -> 41 | E8: =SUM(E7) -> 1.3262195 | F8: =SUM(J8*E8)/D8 -> 82.626387 | G8: =SUM(L8*E8)/D8 -> 86.06356 | H8: =Gen!C13 -> 42919.59 | I8: =Gen!D13 -> 0 | J8: =Gen!S13 -> 2554.39 | K8: =Gen!AJ13 -> 106.26 | L8: =SUM(J8:K8) -> 2660.65 | M8: ='Water-Meter'!K48 -> 481.86559 | P8: 18502 | Q8: =SUM(P8-P7) -> 0 | R8: =SUM(Q8*O8) -> 0 | S8: 4.7 | T8: 15719 | U8: =T8-T7 -> 0 | V8: =SUM(U8*S8) -> 0 | X8: 20734 | Y8: =X8-X7 -> 25 | Z8: =SUM(Y8*W8) -> 0 | AA8: =SUM(Z8*X10) -> 0 | AB8: 12604 | AC8: =AB8-AB7 -> 128 | AD8: 189673 | AE8: =AD8-AD7 -> 41 | AF8: ='Lpg (2)'!B12*2000/85 -> 2000 | AG8: ='Lpg (2)'!C12*1000/85 -> 388.23529 | AH8: ='Lpg (2)'!D12*1000/85 -> 1000 | AI8: =SUM(AF7*2000)+(AG8*1000)+(AH8*1000) -> 5388235.3 | AJ8: =SUM(AI7-AI8) -> 58823.529
A9: =[1]Gen!A14 -> 43742 | B9: ='Summery Report'!E8 -> 47 | C9: =Gen!B14 -> 0.61 | D9: ='Summery Report'!D8 -> 47 | E9: =SUM(E8) -> 1.3262195 | F9: =SUM(J9*E9)/D9 -> 68.890614 | G9: =SUM(L9*E9)/D9 -> 77.138852 | H9: =Gen!C14 -> 40258.94 | I9: =Gen!D14 -> 0 | J9: =Gen!S14 -> 2441.42 | K9: =Gen!AJ14 -> 292.31 | L9: =SUM(J9:K9) -> 2733.73 | M9: ='Water-Meter'!K49 -> 437.09114 | P9: 18502 | Q9: =SUM(P9-P8) -> 0 | R9: =SUM(Q9*O9) -> 0 | S9: 4.7 | T9: 15719 | U9: =T9-T8 -> 0 | V9: =SUM(U9*S9) -> 0 | X9: 20757 | Y9: =X9-X8 -> 23 | Z9: =SUM(Y9*W9) -> 0 | AA9: =SUM(Z9*X11) -> 0 | AB9: 12719 | AC9: =AB9-AB8 -> 115 | AD9: 189742 | AE9: =AD9-AD8 -> 69 | AF9: ='Lpg (2)'!B13*2000/85 -> 2000 | AG9: ='Lpg (2)'!C13*1000/85 -> 341.17647 | AH9: ='Lpg (2)'!D13*1000/85 -> 1000 | AI9: =SUM(AF8*2000)+(AG9*1000)+(AH9*1000) -> 5341176.5 | AJ9: =SUM(AI8-AI9) -> 47058.824
A10: =[1]Gen!A15 -> 43743 | B10: ='Summery Report'!E9 -> 53 | C10: =Gen!B15 -> 0.688 | D10: ='Summery Report'!D9 -> 53 | E10: =SUM(E9) -> 1.3262195 | F10: =SUM(J10*E10)/D10 -> 58.512805 | G10: =SUM(L10*E10)/D10 -> 60.493626 | H10: =Gen!C15 -> 37525.21 | I10: =Gen!D15 -> 0 | J10: =Gen!S15 -> 2338.36 | K10: =Gen!AJ15 -> 79.16 | L10: =SUM(J10:K10) -> 2417.52 | M10: ='Water-Meter'!K50 -> 457.43884 | P10: 18502 | Q10: =SUM(P10-P9) -> 0 | R10: =SUM(Q10*O10) -> 0 | S10: 4.7 | T10: 15719 | U10: =T10-T9 -> 0 | V10: =SUM(U10*S10) -> 0 | W10: 5 | X10: 20776 | Y10: =X10-X9 -> 19 | Z10: =SUM(Y10*W10) -> 95 | AA10: =SUM(Z10*X12) -> 1978280 | AB10: 12805 | AC10: =AB10-AB9 -> 86 | AD10: 189786 | AE10: =AD10-AD9 -> 44 | AF10: ='Lpg (2)'!B14*2000/85 -> 2000 | AG10: ='Lpg (2)'!C14*1000/85 -> 282.35294 | AH10: ='Lpg (2)'!D14*1000/85 -> 1000 | AI10: =SUM(AF9*2000)+(AG10*1000)+(AH10*1000) -> 5282352.9 | AJ10: =SUM(AI9-AI10) -> 58823.529
A11: =[1]Gen!A16 -> 43744 | B11: ='Summery Report'!E10 -> 41 | C11: =Gen!B16 -> 0.532 | D11: ='Summery Report'!D10 -> 41 | E11: =SUM(E10) -> 1.3262195 | F11: =SUM(J11*E11)/D11 -> 80.184526 | G11: =SUM(L11*E11)/D11 -> 83.925435 | H11: =Gen!C16 -> 35107.69 | I11: =Gen!D16 -> 0 | J11: =Gen!S16 -> 2478.9 | K11: =Gen!AJ16 -> 115.65 | L11: =SUM(J11:K11) -> 2594.55 | M11: ='Water-Meter'!K51 -> 440.11465 | P11: 18502 | Q11: =SUM(P11-P10) -> 0 | R11: =SUM(Q11*O11) -> 0 | S11: 4.7 | T11: 15719 | U11: =T11-T10 -> 0 | V11: =SUM(U11*S11) -> 0 | W11: 4.8 | X11: 20801 | Y11: =X11-X10 -> 25 | Z11: =SUM(Y11*W11) -> 120 | AA11: =SUM(Z11*X13) -> 2499240 | AB11: 12919 | AC11: =AB11-AB10 -> 114 | AD11: 189834 | AE11: =AD11-AD10 -> 48 | AF11: ='Lpg (2)'!B15*2000/85 -> 2000 | AG11: ='Lpg (2)'!C15*1000/85 -> 223.52941 | AH11: ='Lpg (2)'!D15*1000/85 -> 1000 | AI11: =SUM(AF10*2000)+(AG11*1000)+(AH11*1000) -> 5223529.4 | AJ11: =SUM(AI10-AI11) -> 58823.529
A12: =[1]Gen!A17 -> 43745 | B12: ='Summery Report'!E11 -> 58 | C12: =Gen!B17 -> 0.753 | D12: ='Summery Report'!D11 -> 58 | E12: =SUM(E11) -> 1.3262195 | F12: =SUM(J12*E12)/D12 -> 52.052744 | G12: =SUM(L12*E12)/D12 -> 53.763338 | H12: =Gen!C17 -> 47513.14 | I12: =Gen!D17 -> 15000 | J12: =Gen!S17 -> 2276.44 | K12: =Gen!AJ17 -> 74.81 | L12: =SUM(J12:K12) -> 2351.25 | M12: ='Water-Meter'!K52 -> 426.40713 | O12: 3.4 | P12: 18502 | Q12: =SUM(P12-P11) -> 0 | R12: =SUM(Q12*O12) -> 0 | S12: 4.7 | T12: 15719 | U12: =T12-T11 -> 0 | V12: =SUM(U12*S12) -> 0 | W12: 5.1 | X12: 20824 | Y12: =X12-X11 -> 23 | Z12: =SUM(Y12*W12) -> 117.3 | AA12: =SUM(Z12*X14) -> 2443007.1 | AB12: 13026 | AC12: =AB12-AB11 -> 107 | AD12: 189879 | AE12: =AD12-AD11 -> 45 | AF12: ='Lpg (2)'!B16*2000/85 -> 2000 | AG12: ='Lpg (2)'!C16*1000/85 -> 176.47059 | AH12: ='Lpg (2)'!D16*1000/85 -> 1000 | AI12: =SUM(AF11*2000)+(AG12*1000)+(AH12*1000) -> 5176470.6 | AJ12: =SUM(AI11-AI12) -> 47058.824
A13: =[1]Gen!A18 -> 43746 | B13: ='Summery Report'!E12 -> 12 | C13: =Gen!B18 -> 0.156 | D13: ='Summery Report'!D12 -> 12 | E13: =SUM(E12) -> 1.3262195 | F13: =SUM(J13*E13)/D13 -> 247.82622 | G13: =SUM(L13*E13)/D13 -> 258.21604 | H13: =Gen!C18 -> 45161.89 | I13: =Gen!D18 -> 0 | J13: =Gen!S18 -> 2242.4 | K13: =Gen!AJ18 -> 94.01 | L13: =SUM(J13:K13) -> 2336.41 | M13: ='Water-Meter'!K53 -> 405.62538 | O13: 2.1 | P13: 18518 | Q13: =SUM(P13-P12) -> 16 | R13: =SUM(Q13*O13) -> 33.6 | S13: 4.7 | T13: 15719 | U13: =T13-T12 -> 0 | V13: =SUM(U13*S13) -> 0 | W13: 5.1 | X13: 20827 | Y13: =X13-X12 -> 3 | Z13: =SUM(Y13*W13) -> 15.3 | AA13: =SUM(Z13*X15) -> 318882.6 | AB13: 13078 | AC13: =AB13-AB12 -> 52 | AD13: 189929 | AE13: =AD13-AD12 -> 50 | AF13: ='Lpg (2)'!B17*2000/85 -> 2000 | AG13: ='Lpg (2)'!C17*1000/85 -> 105.88235 | AH13: ='Lpg (2)'!D17*1000/85 -> 1000 | AI13: =SUM(AF12*2000)+(AG13*1000)+(AH13*1000) -> 5105882.4 | AJ13: =SUM(AI12-AI13) -> 70588.235
A14: =[1]Gen!A19 -> 43747 | B14: ='Summery Report'!E13 -> 34 | C14: =Gen!B19 -> 0.442 | D14: ='Summery Report'!D13 -> 34 | E14: =SUM(E13) -> 1.3262195 | F14: =SUM(J14*E14)/D14 -> 94.79622 | G14: =SUM(L14*E14)/D14 -> 105.90643 | H14: =Gen!C19 -> 42825.48 | I14: =Gen!D19 -> 0 | J14: =Gen!S19 -> 2430.27 | K14: =Gen!AJ19 -> 284.83 | L14: =SUM(J14:K14) -> 2715.1 | M14: ='Water-Meter'!K54 -> 446.72541 | O14: 2.3 | P14: 18532 | Q14: =SUM(P14-P13) -> 14 | R14: =SUM(Q14*O14) -> 32.2 | S14: 4.7 | T14: 15719 | U14: =T14-T13 -> 0 | V14: =SUM(U14*S14) -> 0 | W14: 5.1 | X14: 20827 | Y14: =X14-X13 -> 0 | Z14: =SUM(Y14*W14) -> 0 | AA14: =SUM(Z14*X16) -> 0 | AB14: 13111 | AC14: =AB14-AB13 -> 33 | AD14: 189977 | AE14: =AD14-AD13 -> 48 | AF14: ='Lpg (2)'!B18*2000/85 -> 2000 | AG14: ='Lpg (2)'!C18*1000/85 -> 58.823529 | AH14: ='Lpg (2)'!D18*1000/85 -> 894.11765 | AI14: =SUM(AF13*2000)+(AG14*1000)+(AH14*1000) -> 4952941.2 | AJ14: =SUM(AI13-AI14) -> 152941.18
A15: =[1]Gen!A20 -> 43748 | B15: ='Summery Report'!E14 -> 25 | C15: =Gen!B20 -> 0.325 | D15: ='Summery Report'!D14 -> 25 | E15: =SUM(E14) -> 1.3262195 | F15: =SUM(J15*E15)/D15 -> 130.69999 | G15: =SUM(L15*E15)/D15 -> 136.32529 | H15: =Gen!C20 -> 40110.38 | I15: =Gen!D20 -> 0 | J15: =Gen!S20 -> 2463.77 | K15: =Gen!AJ20 -> 106.04 | L15: =SUM(J15:K15) -> 2569.81 | M15: ='Water-Meter'!K55 -> 451.5578 | O15: 2.3 | P15: 18532 | Q15: =SUM(P15-P14) -> 0 | R15: =SUM(Q15*O15) -> 0 | S15: 4.7 | T15: 15719 | U15: =T15-T14 -> 0 | V15: =SUM(U15*S15) -> 0 | W15: 3.2 | X15: 20842 | Y15: =X15-X14 -> 15 | Z15: =SUM(Y15*W15) -> 48 | AA15: =SUM(Z15*X17) -> 1001760 | AB15: 13193 | AC15: =AB15-AB14 -> 82 | AD15: 190024 | AE15: =AD15-AD14 -> 47 | AF15: ='Lpg (2)'!B19*2000/85 -> 2000 | AG15: ='Lpg (2)'!C19*1000/85 -> 58.823529 | AH15: ='Lpg (2)'!D19*1000/85 -> 870.58824 | AI15: =SUM(AF15*2000)+(AG15*1000)+(AH15*1000) -> 4929411.8 | AJ15: =SUM(AI14-AI15) -> 23529.412
A16: =[1]Gen!A21 -> 43749 | B16: ='Summery Report'!E15 -> 35 | C16: =Gen!B21 -> 0.455 | D16: ='Summery Report'!D15 -> 35 | E16: =SUM(E15) -> 1.3262195 | F16: =SUM(J16*E16)/D16 -> 87.537687 | G16: =SUM(L16*E16)/D16 -> 97.50669 | H16: =Gen!C21 -> 37540.57 | I16: =Gen!D21 -> 0 | J16: =Gen!S21 -> 2310.19 | K16: =Gen!AJ21 -> 263.09 | L16: =SUM(J16:K16) -> 2573.28 | M16: ='Water-Meter'!K56 -> 427.47815 | O16: 2.3 | P16: 18532 | Q16: =SUM(P16-P15) -> 0 | R16: =SUM(Q16*O16) -> 0 | S16: 4.7 | T16: 15719 | U16: =T16-T15 -> 0 | V16: =SUM(U16*S16) -> 0 | W16: 5.1 | X16: 20866 | Y16: =X16-X15 -> 24 | Z16: =SUM(Y16*W16) -> 122.4 | AA16: =SUM(Z16*X18) -> 2557058.4 | AB16: 13308 | AC16: =AB16-AB15 -> 115 | AD16: 190071 | AE16: =AD16-AD15 -> 47 | AF16: ='Lpg (2)'!B20*2000/85 -> 2000 | AG16: ='Lpg (2)'!C20*1000/85 -> 58.823529 | AH16: ='Lpg (2)'!D20*1000/85 -> 847.05882 | AI16: =SUM(AF16*2000)+(AG16*1000)+(AH16*1000) -> 4905882.4 | AJ16: =SUM(AI15-AI16) -> 23529.412
A17: =[1]Gen!A22 -> 43750 | B17: ='Summery Report'!E16 -> 32 | C17: =Gen!B22 -> 0.416 | D17: ='Summery Report'!D16 -> 32 | E17: =SUM(E16) -> 1.3262195 | F17: =SUM(J17*E17)/D17 -> 100.6754 | G17: =SUM(L17*E17)/D17 -> 113.49662 | H17: =Gen!C22 -> 34967.29 | I17: =Gen!D22 -> 0 | J17: =Gen!S22 -> 2429.17 | K17: =Gen!AJ22 -> 309.36 | L17: =SUM(J17:K17) -> 2738.53 | M17: ='Water-Meter'!K57 -> 395.83546 | O17: 2.3 | P17: 18532 | Q17: =SUM(P18-P16) -> 0 | R17: =SUM(Q17*O17) -> 0 | S17: 4.7 | T17: 15719 | U17: =T17-T16 -> 0 | V17: =SUM(U17*S17) -> 0 | W17: 5 | X17: 20870 | Y17: =X17-X16 -> 4 | Z17: =SUM(Y17*W17) -> 20 | AA17: =SUM(Z17*X19) -> 417880 | AB17: 13329 | AC17: =AB17-AB16 -> 21 | AD17: 190117 | AE17: =AD17-AD16 -> 46 | AF17: ='Lpg (2)'!B21*2000/85 -> 2000 | AG17: ='Lpg (2)'!C21*1000/85 -> 58.823529 | AH17: ='Lpg (2)'!D21*1000/85 -> 800 | AI17: =SUM(AF17*2000)+(AG17*1000)+(AH17*1000) -> 4858823.5 | AJ17: =SUM(AI16-AI17) -> 47058.824
A18: =[1]Gen!A23 -> 43751 | B18: ='Summery Report'!E17 -> 30 | C18: =Gen!B23 -> 0.39 | D18: ='Summery Report'!D17 -> 30 | E18: =SUM(E17) -> 1.3262195 | F18: =SUM(J18*E18)/D18 -> 99.445686 | G18: =SUM(L18*E18)/D18 -> 102.26523 | H18: =Gen!C23 -> 32228.76 | I18: =Gen!D23 -> 0 | J18: =Gen!S23 -> 2249.53 | K18: =Gen!AJ23 -> 63.78 | L18: =SUM(J18:K18) -> 2313.31 | M18: ='Water-Meter'!K58 -> 434.03479 | O18: 2.3 | P18: 18532 | R18: =SUM(Q18*O18) -> 0 | S18: 4.7 | T18: 15719 | U18: =T18-T17 -> 0 | V18: =SUM(U18*S18) -> 0 | W18: 5.2 | X18: 20891 | Y18: =X18-X17 -> 21 | Z18: =SUM(Y18*W18) -> 109.2 | AA18: =SUM(Z18*X20) -> 2282716.8 | AB18: 13431 | AC18: =AB18-AB17 -> 102 | AD18: 190168 | AE18: =AD18-AD17 -> 51 | AF18: ='Lpg (2)'!B22*2000/85 -> 2000 | AG18: ='Lpg (2)'!C22*1000/85 -> 58.823529 | AH18: ='Lpg (2)'!D22*1000/85 -> 764.70588 | AI18: =SUM(AF18*2000)+(AG18*1000)+(AH18*1000) -> 4823529.4 | AJ18: =SUM(AI17-AI18) -> 35294.118
A19: =[1]Gen!A24 -> 43752 | B19: ='Summery Report'!E18 -> 49 | C19: =Gen!B24 -> 0.636 | D19: ='Summery Report'!D18 -> 49 | E19: =SUM(E18) -> 1.3262195 | F19: =SUM(J19*E19)/D19 -> 65.619988 | G19: =SUM(L19*E19)/D19 -> 72.299804 | H19: =Gen!C24 -> 29915.45 | I19: =Gen!D24 -> 0 | J19: =Gen!S24 -> 2424.47 | K19: =Gen!AJ24 -> 246.8 | L19: =SUM(J19:K19) -> 2671.27 | M19: ='Water-Meter'!K59 -> 491.18387 | O19: 2.3 | P19: 18532 | R19: =SUM(Q19*O19) -> 0 | S19: 4.7 | T19: 15719 | U19: =T19-T18 -> 0 | V19: =SUM(U19*S19) -> 0 | W19: 5.2 | X19: 20894 | Y19: =X19-X18 -> 3 | Z19: =SUM(Y19*W19) -> 15.6 | AA19: =SUM(Z19*X21) -> 326476.8 | AB19: 13444 | AC19: =AB19-AB18 -> 13 | AD19: 190218 | AE19: =AD19-AD18 -> 50 | AF19: ='Lpg (2)'!B23*2000/85 -> 2000 | AG19: ='Lpg (2)'!C23*1000/85 -> 58.823529 | AH19: ='Lpg (2)'!D23*1000/85 -> 682.35294 | AI19: =SUM(AF19*2000)+(AG19*1000)+(AH19*1000) -> 4741176.5 | AJ19: =SUM(AI18-AI19) -> 82352.941
A20: =[1]Gen!A25 -> 43753 | B20: ='Summery Report'!E19 -> 66 | C20: =Gen!B25 -> 0.844 | D20: ='Summery Report'!D19 -> 66 | E20: =SUM(E19) -> 1.3262195 | F20: =SUM(J20*E20)/D20 -> 53.698025 | G20: =SUM(L20*E20)/D20 -> 55.316817 | H20: =Gen!C25 -> 42244.18 | I20: =Gen!D25 -> 15000 | J20: =Gen!S25 -> 2672.31 | K20: =Gen!AJ25 -> 80.56 | L20: =SUM(J20:K20) -> 2752.87 | M20: ='Water-Meter'!K60 -> 505.79747 | O20: 2.3 | P20: 18532 | Q20: =SUM(P20-P19) -> 0 | R20: =SUM(Q20*O20) -> 0 | S20: 4.7 | T20: 15719 | U20: =T20-T19 -> 0 | V20: =SUM(U20*S20) -> 0 | W20: 5.4 | X20: 20904 | Y20: =X20-X19 -> 10 | Z20: =SUM(Y20*W20) -> 54 | AA20: =SUM(Z20*X22) -> 1130922 | AB20: 13492 | AC20: =AB20-AB19 -> 48 | AD20: 190269 | AE20: =AD20-AD19 -> 51 | AF20: ='Lpg (2)'!B24*2000/85 -> 2000 | AG20: ='Lpg (2)'!C24*1000/85 -> 58.823529 | AH20: ='Lpg (2)'!D24*1000/85 -> 623.52941 | AI20: =SUM(AF20*2000)+(AG20*1000)+(AH20*1000) -> 4682352.9 | AJ20: =SUM(AI19-AI20) -> 58823.529
A21: =[1]Gen!A26 -> 43754 | B21: ='Summery Report'!E20 -> 63 | C21: =Gen!B26 -> 0.818 | D21: ='Summery Report'!D20 -> 63 | E21: =SUM(E20) -> 1.3262195 | F21: =SUM(J21*E21)/D21 -> 57.71581 | G21: =SUM(L21*E21)/D21 -> 59.13297 | H21: =Gen!C26 -> 39491.31 | I21: =Gen!D26 -> 0 | J21: =Gen!S26 -> 2741.7 | K21: =Gen!AJ26 -> 67.32 | L21: =SUM(J21:K21) -> 2809.02 | M21: ='Water-Meter'!K61 -> 466.71867 | O21: 2.3 | P21: 18532 | Q21: =SUM(P21-P20) -> 0 | R21: =SUM(Q21*O21) -> 0 | S21: 4.7 | T21: 15719 | U21: =T21-T20 -> 0 | V21: =SUM(U21*S21) -> 0 | W21: 4.9 | X21: 20928 | Y21: =X21-X20 -> 24 | Z21: =SUM(Y21*W21) -> 117.6 | AA21: =SUM(Z21*X23) -> 2465484 | AB21: 13611 | AC21: =AB21-AB20 -> 119 | AD21: 190318 | AE21: =AD21-AD20 -> 49 | AF21: ='Lpg (2)'!B25*2000/85 -> 2000 | AG21: ='Lpg (2)'!C25*1000/85 -> 58.823529 | AH21: ='Lpg (2)'!D25*1000/85 -> 564.70588 | AI21: =SUM(AF21*2000)+(AG21*1000)+(AH21*1000) -> 4623529.4 | AJ21: =SUM(AI20-AI21) -> 58823.529
A22: =[1]Gen!A27 -> 43755 | B22: ='Summery Report'!E21 -> 16 | C22: =Gen!B27 -> 0.208 | D22: ='Summery Report'!D21 -> 16 | E22: =SUM(E21) -> 1.3262195 | F22: =SUM(J22*E22)/D22 -> 192.39384 | G22: =SUM(L22*E22)/D22 -> 241.953 | H22: =Gen!C27 -> 36682.29 | I22: =Gen!D27 -> 0 | J22: =Gen!S27 -> 2321.11 | K22: =Gen!AJ27 -> 597.9 | L22: =SUM(J22:K22) -> 2919.01 | M22: ='Water-Meter'!K62 -> 489.58383 | O22: 2.3 | P22: 18532 | Q22: =SUM(P22-P21) -> 0 | R22: =SUM(Q22*O22) -> 0 | S22: 4.7 | T22: 15719 | U22: =T22-T21 -> 0 | V22: =SUM(U22*S22) -> 0 | W22: 5.3 | X22: 20943 | Y22: =X22-X21 -> 15 | Z22: =SUM(Y22*W22) -> 79.5 | AA22: =SUM(Z22*X24) -> 1666717.5 | AB22: 13681 | AC22: =AB22-AB21 -> 70 | AD22: 190359 | AE22: =AD22-AD21 -> 41 | AF22: ='Lpg (2)'!B26*2000/85 -> 2000 | AG22: ='Lpg (2)'!C26*1000/85 -> 58.823529 | AH22: ='Lpg (2)'!D26*1000/85 -> 517.64706 | AI22: =SUM(AF22*2000)+(AG22*1000)+(AH22*1000) -> 4576470.6 | AJ22: =SUM(AI21-AI22) -> 47058.824
A23: =[1]Gen!A28 -> 43756 | B23: ='Summery Report'!E22 -> 17 | C23: =Gen!B28 -> 0.221 | D23: ='Summery Report'!D22 -> 17 | E23: =SUM(E22) -> 1.3262195 | F23: =SUM(J23*E23)/D23 -> 172.00599 | G23: =SUM(L23*E23)/D23 -> 189.77187 | H23: =Gen!C28 -> 33763.28 | I23: =Gen!D28 -> 0 | J23: =Gen!S28 -> 2204.84 | K23: =Gen!AJ28 -> 227.73 | L23: =SUM(J23:K23) -> 2432.57 | M23: ='Water-Meter'!K63 -> 511.7188 | O23: 2.3 | P23: 18532 | Q23: =SUM(P23-P22) -> 0 | R23: =SUM(Q23*O23) -> 0 | S23: 4.7 | T23: 15719 | U23: =T23-T22 -> 0 | V23: =SUM(U23*S23) -> 0 | W23: 5.3 | X23: 20965 | Y23: =X23-X22 -> 22 | Z23: =SUM(Y23*W23) -> 116.6 | AA23: =SUM(Z23*X25) -> 2449882.6 | AB23: 13790 | AC23: =AB23-AB22 -> 109 | AD23: 190369 | AE23: =AD23-AD22 -> 10 | AF23: ='Lpg (2)'!B27*2000/85 -> 2000 | AG23: ='Lpg (2)'!C27*1000/85 -> 58.823529 | AH23: ='Lpg (2)'!D27*1000/85 -> 458.82353 | AI23: =SUM(AF23*2000)+(AG23*1000)+(AH23*1000) -> 4517647.1 | AJ23: =SUM(AI22-AI23) -> 58823.529
A24: =[1]Gen!A29 -> 43757 | B24: ='Summery Report'!E23 -> 9 | C24: =Gen!B29 -> 0.117 | D24: ='Summery Report'!D23 -> 9 | E24: =SUM(E23) -> 1.3262195 | F24: =SUM(J24*E24)/D24 -> 271.90152 | G24: =SUM(L24*E24)/D24 -> 284.91174 | H24: =Gen!C29 -> 31330.71 | I24: =Gen!D29 -> 0 | J24: =Gen!S29 -> 1845.18 | K24: =Gen!AJ29 -> 88.29 | L24: =SUM(J24:K24) -> 1933.47 | M24: ='Water-Meter'!K64 -> 514.91402 | O24: 2.3 | P24: 18532 | Q24: =SUM(P24-P23) -> 0 | R24: =SUM(Q24*O24) -> 0 | S24: 4.7 | T24: 15719 | U24: =T24-T23 -> 0 | V24: =SUM(U24*S24) -> 0 | W24: 5 | X24: 20965 | Y24: =X24-X23 -> 0 | Z24: =SUM(Y24*W24) -> 0 | AA24: =SUM(Z24*X26) -> 0 | AB24: 13899 | AC24: =AB24-AB23 -> 109 | AD24: 190376 | AE24: =AD24-AD23 -> 7 | AF24: ='Lpg (2)'!B28*2000/85 -> 2000 | AG24: ='Lpg (2)'!C28*1000/85 -> 58.823529 | AH24: ='Lpg (2)'!D28*1000/85 -> 411.76471 | AI24: =SUM(AF24*2000)+(AG24*1000)+(AH24*1000) -> 4470588.2 | AJ24: =SUM(AI23-AI24) -> 47058.824
A25: =[1]Gen!A30 -> 43758 | B25: ='Summery Report'!E24 -> 44 | C25: =Gen!B30 -> 0.571 | D25: ='Summery Report'!D24 -> 44 | E25: =SUM(E24) -> 1.3262195 | F25: =SUM(J25*E25)/D25 -> 84.305664 | G25: =SUM(L25*E25)/D25 -> 89.849262 | H25: =Gen!C30 -> 29397.24 | I25: =Gen!D30 -> 0 | J25: =Gen!S30 -> 2797.01 | K25: =Gen!AJ30 -> 183.92 | L25: =SUM(J25:K25) -> 2980.93 | M25: ='Water-Meter'!K65 -> 534.97374 | O25: 2.3 | P25: 18532 | Q25: =SUM(P25-P24) -> 0 | R25: =SUM(Q25*O25) -> 0 | S25: 4.7 | T25: 15719 | U25: =T25-T24 -> 0 | V25: =SUM(U25*S25) -> 0 | W25: 5 | X25: 21011 | Y25: =X25-X24 -> 46 | Z25: =SUM(Y25*W25) -> 230 | AA25: =SUM(Z25*X27) -> 4842190 | AB25: 14008 | AC25: =AB25-AB24 -> 109 | AD25: 190426 | AE25: =AD25-AD24 -> 50 | AF25: ='Lpg (2)'!B29*2000/85 -> 2000 | AG25: ='Lpg (2)'!C29*1000/85 -> 58.823529 | AH25: ='Lpg (2)'!D29*1000/85 -> 341.17647 | AI25: =SUM(AF25*2000)+(AG25*1000)+(AH25*1000) -> 4400000 | AJ25: =SUM(AI24-AI25) -> 70588.235
A26: =[1]Gen!A31 -> 43759 | B26: ='Summery Report'!E25 -> 43 | C26: =Gen!B31 -> 0.558 | D26: ='Summery Report'!D25 -> 43 | E26: =SUM(E25) -> 1.3262195 | F26: =SUM(J26*E26)/D26 -> 69.77025 | G26: =SUM(L26*E26)/D26 -> 75.07667 | H26: =Gen!C31 -> 41416.31 | I26: =Gen!D31 -> 15000 | J26: =Gen!S31 -> 2262.16 | K26: =Gen!AJ31 -> 172.05 | L26: =SUM(J26:K26) -> 2434.21 | M26: ='Water-Meter'!K66 -> 501.4901 | O26: 2.3 | P26: 18532 | Q26: =SUM(P26-P25) -> 0 | R26: =SUM(Q26*O26) -> 0 | S26: 4.7 | T26: 15719 | U26: =T26-T25 -> 0 | V26: =SUM(U26*S26) -> 0 | W26: 5 | X26: 21036 | Y26: =X26-X25 -> 25 | Z26: =SUM(Y26*W26) -> 125 | AA26: =SUM(Z26*X28) -> 2633375 | AB26: 14121 | AC26: =AB26-AB25 -> 113 | AD26: 190475 | AE26: =AD26-AD25 -> 49 | AF26: ='Lpg (2)'!B30*2000/85 -> 2000 | AG26: ='Lpg (2)'!C30*1000/85 -> 58.823529 | AH26: ='Lpg (2)'!D30*1000/85 -> 282.35294 | AI26: =SUM(AF26*2000)+(AG26*1000)+(AH26*1000) -> 4341176.5 | AJ26: =SUM(AI25-AI26) -> 58823.529
A27: =[1]Gen!A32 -> 43760 | B27: ='Summery Report'!E26 -> 31 | C27: =Gen!B32 -> 0.403 | D27: ='Summery Report'!D26 -> 31 | E27: =SUM(E26) -> 1.3262195 | F27: =SUM(J27*E27)/D27 -> 97.834786 | G27: =SUM(L27*E27)/D27 -> 98.631801 | H27: =Gen!C32 -> 38982.1 | I27: =Gen!D32 -> 0 | J27: =Gen!S32 -> 2286.86 | K27: =Gen!AJ32 -> 18.63 | L27: =SUM(J27:K27) -> 2305.49 | M27: ='Water-Meter'!K67 -> 596.98933 | O27: 2.3 | P27: 18537 | Q27: =SUM(P27-P26) -> 5 | R27: =SUM(Q27*O27) -> 11.5 | S27: 4.7 | T27: 15719 | U27: =T27-T26 -> 0 | V27: =SUM(U27*S27) -> 0 | W27: 5 | X27: 21053 | Y27: =X27-X26 -> 17 | Z27: =SUM(Y27*W27) -> 85 | AA27: =SUM(Z27*X29) -> 1792650 | AB27: 14208 | AC27: =AB27-AB26 -> 87 | AD27: 190505 | AE27: =AD27-AD26 -> 30 | AF27: ='Lpg (2)'!B31*2000/85 -> 2000 | AG27: ='Lpg (2)'!C31*1000/85 -> 1000 | AH27: ='Lpg (2)'!D31*1000/85 -> 1000 | AI27: =SUM(AF27*2000)+(AG27*1000)+(AH27*1000) -> 6000000 | AJ27: =SUM(AI26-AI27) -> -1658823.5
A28: =[1]Gen!A33 -> 43761 | B28: ='Summery Report'!E27 -> 19 | C28: =Gen!B33 -> 0.24 | D28: ='Summery Report'!D27 -> 19 | E28: =SUM(E27) -> 1.3262195 | F28: =SUM(J28*E28)/D28 -> 149.95355 | G28: =SUM(L28*E28)/D28 -> 171.6854 | H28: =Gen!C33 -> 36676.61 | I28: =Gen!D33 -> 0 | J28: =Gen!S33 -> 2148.3 | K28: =Gen!AJ33 -> 311.34 | L28: =SUM(J28:K28) -> 2459.64 | M28: ='Water-Meter'!K68 -> 512.12688 | O28: 2.3 | P28: 18537 | Q28: =SUM(P28-P27) -> 0 | R28: =SUM(Q28*O28) -> 0 | S28: 4.7 | T28: 15719 | U28: =T28-T27 -> 0 | V28: =SUM(U28*S28) -> 0 | W28: 5 | X28: 21067 | Y28: =X28-X27 -> 14 | Z28: =SUM(Y28*W28) -> 70 | AA28: =SUM(Z28*X30) -> 1477420 | AB28: 14268 | AC28: =SUM(AB28-AB27) -> 60 | AD28: 190519 | AE28: =AD28-AD27 -> 14 | AF28: ='Lpg (2)'!B32*2000/85 -> 1976.4706 | AG28: ='Lpg (2)'!C32*1000/85 -> 1000 | AH28: ='Lpg (2)'!D32*1000/85 -> 1000 | AI28: =SUM(AF28*2000)+(AG28*1000)+(AH28*1000) -> 5952941.2 | AJ28: =SUM(AI27-AI28) -> 47058.824
A29: =[1]Gen!A34 -> 43762 | B29: ='Summery Report'!E28 -> 7 | C29: =Gen!B34 -> 0.09 | D29: ='Summery Report'!D28 -> 7 | E29: =SUM(E28) -> 1.3262195 | F29: =SUM(J29*E29)/D29 -> 400.37999 | G29: =SUM(L29*E29)/D29 -> 472.50738 | H29: =Gen!C34 -> 44216.97 | I29: =Gen!D34 -> 10000 | J29: =Gen!S34 -> 2113.27 | K29: =Gen!AJ34 -> 380.7 | L29: =SUM(J29:K29) -> 2493.97 | M29: ='Water-Meter'!K69 -> 502.84144 | O29: 2.3 | P29: 18537 | Q29: =SUM(P29-P28) -> 0 | R29: =SUM(Q29*O29) -> 0 | S29: 4.7 | T29: 15719 | U29: =T29-T28 -> 0 | V29: =SUM(U29*S29) -> 0 | W29: 5.2 | X29: 21090 | Y29: =X29-X28 -> 23 | Z29: =SUM(Y29*W29) -> 119.6 | AA29: =SUM(Z29*X31) -> 2527267.6 | AB29: 14378 | AC29: =SUM(AB29-AB28) -> 110 | AD29: 190549 | AE29: =AD29-AD28 -> 30 | AF29: ='Lpg (2)'!B33*2000/85 -> 1905.8824 | AG29: ='Lpg (2)'!C33*1000/85 -> 1000 | AH29: ='Lpg (2)'!D33*1000/85 -> 1000 | AI29: =SUM(AF29*2000)+(AG29*1000)+(AH29*1000) -> 5811764.7 | AJ29: =SUM(AI28-AI29) -> 141176.47
A30: =[1]Gen!A35 -> 43763 | B30: ='Summery Report'!E29 -> 19 | C30: =Gen!B35 -> 0.286 | D30: ='Summery Report'!D29 -> 19 | E30: =SUM(E29) -> 1.3262195 | F30: =SUM(J30*E30)/D30 -> 146.89766 | G30: =SUM(L30*E30)/D30 -> 165.97916 | H30: =Gen!C35 -> 41723 | I30: =Gen!D35 -> 0 | J30: =Gen!S35 -> 2104.52 | K30: =Gen!AJ35 -> 273.37 | L30: =SUM(J30:K30) -> 2377.89 | M30: ='Water-Meter'!K70 -> 521.6317 | O30: 2.3 | P30: 18537 | Q30: =SUM(P30-P29) -> 0 | R30: =SUM(Q30*O30) -> 0 | S30: 4.7 | T30: 15719 | U30: =T30-T29 -> 0 | V30: =SUM(U30*S30) -> 0 | W30: 5 | X30: 21106 | Y30: =X30-X29 -> 16 | Z30: =SUM(Y30*W30) -> 80 | AA30: =SUM(Z30*X32) -> 1692400 | AB30: 14454 | AC30: =SUM(AB30-AB29) -> 76 | AD30: 190600 | AE30: =AD30-AD29 -> 51 | AF30: ='Lpg (2)'!B34*2000/85 -> 1952.9412 | AG30: ='Lpg (2)'!C34*1000/85 -> 1000 | AH30: ='Lpg (2)'!D34*1000/85 -> 1000 | AI30: =SUM(AF30*2000)+(AG30*1000)+(AH30*1000) -> 5905882.4 | AJ30: =SUM(AI29-AI30) -> -94117.647
A31: =[1]Gen!A36 -> 43764 | B31: ='Summery Report'!E30 -> 42 | C31: =Gen!B36 -> 0.545 | D31: ='Summery Report'!D30 -> 42 | E31: =SUM(E30) -> 1.3262195 | F31: =SUM(J31*E31)/D31 -> 78.001916 | G31: =SUM(L31*E31)/D31 -> 90.523955 | H31: =Gen!C36 -> 39345.11 | I31: =Gen!D36 -> 0 | J31: =Gen!S36 -> 2470.24 | K31: =Gen!AJ36 -> 396.56 | L31: =SUM(J31:K31) -> 2866.8 | M31: ='Water-Meter'!K71 -> 482.25716 | O31: 2.3 | P31: 18537 | Q31: =SUM(P31-P30) -> 0 | R31: =SUM(Q31*O31) -> 0 | S31: 4.7 | T31: 15719 | U31: =T31-T30 -> 0 | V31: =SUM(U31*S31) -> 0 | W31: 5.3 | X31: 21131 | Y31: =X31-X30 -> 25 | Z31: =SUM(Y31*W31) -> 132.5 | AA31: =SUM(Z31*X33) -> 2806217.5 | AB31: 14570 | AC31: =SUM(AB31-AB30) -> 116 | AD31: 190646 | AE31: =AD31-AD30 -> 46 | AF31: ='Lpg (2)'!B35*2000/85 -> 1905.8824 | AG31: ='Lpg (2)'!C35*1000/85 -> 1000 | AH31: ='Lpg (2)'!D35*1000/85 -> 1000 | AI31: =SUM(AF31*2000)+(AG31*1000)+(AH31*1000) -> 5811764.7 | AJ31: =SUM(AI30-AI31) -> 94117.647
A32: =[1]Gen!A37 -> 43765 | B32: ='Summery Report'!E31 -> 52 | C32: =Gen!B37 -> 0.675 | D32: ='Summery Report'!D31 -> 52 | E32: =SUM(E31) -> 1.3262195 | F32: =SUM(J32*E32)/D32 -> 59.265179 | G32: =SUM(L32*E32)/D32 -> 66.422429 | H32: =Gen!C37 -> 36478.31 | I32: =Gen!D37 -> 0 | J32: =Gen!S37 -> 2323.74 | K32: =Gen!AJ37 -> 280.63 | L32: =SUM(J32:K32) -> 2604.37 | M32: ='Water-Meter'!K72 -> 457.77812 | O32: 2.3 | P32: 18537 | Q32: =SUM(P32-P31) -> 0 | R32: =SUM(Q32*O32) -> 0 | S32: 4.7 | T32: 15719 | U32: =T32-T31 -> 0 | V32: =SUM(U32*S32) -> 0 | W32: 5.3 | X32: 21155 | Y32: =X32-X31 -> 24 | Z32: =SUM(Y32*W32) -> 127.2 | AA32: =SUM(Z32*X34) -> 2696894.4 | AB32: 14687 | AC32: =SUM(AB32-AB31) -> 117 | AD32: 190676 | AE32: =AD32-AD31 -> 30 | AF32: ='Lpg (2)'!B36*2000/85 -> 1882.3529 | AG32: ='Lpg (2)'!C36*1000/85 -> 1000 | AH32: ='Lpg (2)'!D36*1000/85 -> 1000 | AI32: =SUM(AF32*2000)+(AG32*1000)+(AH32*1000) -> 5764705.9 | AJ32: =SUM(AI31-AI32) -> 47058.824
A33: =[1]Gen!A38 -> 43766 | B33: ='Summery Report'!E32 -> 21 | C33: =Gen!B38 -> 0.273 | D33: ='Summery Report'!D32 -> 21 | E33: =SUM(E32) -> 1.3262195 | F33: =SUM(J33*E33)/D33 -> 128.31679 | G33: =SUM(L33*E33)/D33 -> 171.02674 | H33: =Gen!C38 -> 44873.94 | I33: =Gen!D38 -> 11000 | J33: =Gen!S38 -> 2031.83 | K33: =Gen!AJ38 -> 676.29 | L33: =SUM(J33:K33) -> 2708.12 | M33: ='Water-Meter'!K73 -> 478.72679 | O33: 2.3 | P33: 18537 | Q33: =SUM(P33-P32) -> 0 | R33: =SUM(Q33*O33) -> 0 | S33: 4.7 | T33: 15719 | U33: =T33-T32 -> 0 | V33: =SUM(U33*S33) -> 0 | W33: 5.4 | X33: 21179 | Y33: =X33-X32 -> 24 | Z33: =SUM(Y33*W33) -> 129.6 | AA33: =SUM(Z33*X35) -> 2752315.2 | AB33: 14805 | AC33: =SUM(AB33-AB32) -> 118 | AD33: 190720 | AE33: =AD33-AD32 -> 44 | AF33: ='Lpg (2)'!B37*2000/85 -> 1835.2941 | AG33: ='Lpg (2)'!C37*1000/85 -> 1000 | AH33: ='Lpg (2)'!D37*1000/85 -> 1000 | AI33: =SUM(AF33*2000)+(AG33*1000)+(AH33*1000) -> 5670588.2 | AJ33: =SUM(AI32-AI33) -> 94117.647
A34: =[1]Gen!A39 -> 43767 | B34: ='Summery Report'!E33 -> 32 | C34: =Gen!B39 -> 0.416 | D34: ='Summery Report'!D33 -> 32 | E34: =SUM(E33) -> 1.3262195 | F34: =SUM(J34*E34)/D34 -> 88.333265 | G34: =SUM(L34*E34)/D34 -> 93.335599 | H34: =Gen!C39 -> 42165.82 | I34: =Gen!D39 -> 0 | J34: =Gen!S39 -> 2131.37 | K34: =Gen!AJ39 -> 120.7 | L34: =SUM(J34:K34) -> 2252.07 | M34: ='Water-Meter'!K74 -> 469.77865 | N34: ='[1]Water-Meter'!E34 -> 0 | O34: 2.3 | P34: 18537 | Q34: =SUM(P34-P33) -> 0 | R34: =SUM(Q34*O34) -> 0 | S34: 4.7 | T34: 15719 | U34: =T34-T33 -> 0 | V34: =SUM(U34*S34) -> 0 | W34: 5.4 | X34: 21202 | Y34: =X34-X33 -> 23 | Z34: =SUM(Y34*W34) -> 124.2 | AA34: =SUM(Z34*X36) -> 0 | AB34: 14921 | AC34: =SUM(AB34-AB33) -> 116 | AD34: 190758 | AE34: =AD34-AD33 -> 38 | AF34: ='Lpg (2)'!B38*2000/85 -> 1811.7647 | AG34: ='Lpg (2)'!C38*1000/85 -> 1000 | AH34: ='Lpg (2)'!D38*1000/85 -> 1000 | AI34: =SUM(AF34*2000)+(AG34*1000)+(AH34*1000) -> 5623529.4 | AJ34: =SUM(AI33-AI34) -> 47058.824
A35: =[1]Gen!A40 -> 43768 | B35: ='Summery Report'!E34 -> 32 | C35: =Gen!B40 -> 0.429 | D35: ='Summery Report'!D34 -> 32 | E35: =SUM(E34) -> 1.3262195 | F35: =SUM(J35*E35)/D35 -> 84.287052 | G35: =SUM(L35*E35)/D35 -> 85.344712 | H35: =Gen!C40 -> 39913.75 | I35: =Gen!D40 -> 0 | J35: =Gen!S40 -> 2033.74 | K35: =Gen!AJ40 -> 25.52 | L35: =SUM(J35:K35) -> 2059.26 | M35: ='Water-Meter'!K75 -> 441.46816 | N35: ='[1]Water-Meter'!E35 -> 0 | O35: 2.3 | P35: 18537 | Q35: =SUM(P35-P34) -> 0 | R35: =SUM(Q35*O35) -> 0 | S35: 4.7 | T35: 15719 | U35: =T35-T34 -> 0 | V35: =SUM(U35*S35) -> 0 | W35: 5.4 | X35: 21237 | Y35: =X35-X34 -> 35 | Z35: =SUM(Y35*W35) -> 189 | AA35: =SUM(Z35*X37) -> 0 | AB35: 15043 | AC35: =SUM(AB35-AB34) -> 122 | AD35: 190789 | AE35: =AD35-AD34 -> 31 | AF35: ='Lpg (2)'!B39*2000/85 -> 1788.2353 | AG35: ='Lpg (2)'!C39*1000/85 -> 1000 | AH35: ='Lpg (2)'!D39*1000/85 -> 1000 | AI35: =SUM(AF35*2000)+(AG35*1000)+(AH35*1000) -> 5576470.6 | AJ35: =SUM(AI34-AI35) -> 47058.824
A36: =[1]Gen!A41 -> 43769 | B36: ='Summery Report'!E35 -> 25 | C36: =Gen!B41 -> 0.325 | D36: ='Summery Report'!D35 -> 25 | E36: =SUM(E35) -> 1.3262195 | F36: =SUM(J36*E36)/D36 -> 0 | G36: =SUM(L36*E36)/D36 -> 0 | H36: =Gen!C41 -> 37854.49 | I36: =Gen!D41 -> 0 | J36: =SUM([1]Gen!S41) -> 0 | K36: =[1]Gen!AJ41 -> 0 | L36: =SUM(J36:K36) -> 0 | M36: ='Water-Meter'!K76 -> 417.10188 | N36: ='[1]Water-Meter'!E36 -> 0 | Q36: =SUM(P36-P35) -> -18537 | R36: =SUM(Q36*O36) -> 0 | U36: =T36-T35 -> -15719 | V36: =SUM(U36*S36) -> 0 | Y36: =X36-X35 -> -21237 | Z36: =SUM(Y36*W36) -> 0 | AA36: =SUM(Z36*X38) -> 0 | AB36: 15088 | AC36: =SUM(AB36-AB35) -> 45 | AD36: 190819 | AE36: =AD36-AD35 -> 30 | AF36: ='Lpg (2)'!B40*2000/85 -> 1764.7059 | AG36: ='Lpg (2)'!C40*1000/85 -> 1000 | AH36: ='Lpg (2)'!D40*1000/85 -> 1000 | AI36: =SUM(AF36*1000)+(AG36*1000)+(AH36*2000) -> 4764705.9 | AJ36: =SUM(AI35-AI36) -> 811764.71
A37: Nb Day | B37: 0 | J37: =SUM(J6:J36) -> 69779.82 | L37: =SUM(J37:K37) -> 69779.82 | N37: ='[1]Water-Meter'!E37 -> 0 | AC37: =SUM(AB37-AB36) -> -15088 | AE37: =AD37-AD36 -> -190819 | AJ37: =SUM(AJ6:AJ36) -> -4764705.9 | AK37: =SUM(AK6:AK36) -> 0

Sheet Kit report
B1: KITCHEN THREE PHASE KWH METER READING | H1: KITCHEN WATER METER READING | M1: AMANI Restaurant WATER METER READING | T1: LAUNDRY THREE PHASE KWH METER READING | Y1: LAUNDRY WATER METER READING
A2: Occ % | B2: DATE | C2: READING TIME | D2: METER READING OPEN | E2: METER READING ClOSE | F2: UNIT USED Kwh | H2: DATE | I2: READING TIME | J2: METER READING OPEN Cbm | K2: METER READING ClOSE Cbm | L2: UNIT USED Cbm | M2: DATE | N2: READING TIME | O2: METER READING OPEN Cbm | P2: METER READING ClOSE Cbm | Q2: UNIT USED Cbm | R2: Cost Per day Elct+Water $ | S2: % as per the total Lodge consumption | T2: DATE | U2: READING TIME | V2: METER READING OPEN (Kwh) | W2: METER READING ClOSE (Kwh) | X2: UNIT USED Kwh | Y2: DATE | Z2: READING TIME | AA2: METER READING OPEN Cbm | AB2: METER READING ClOSE Cbm | AC2: UNIT USED Cbm
A3: 43070 | B3: Close Last Month | F3: X120 | H3: Close Last Month | K3: ='[1]Water-Meter'!G5 -> 36423 | M3: Close Last Month | P3: ='[1]Water-Meter'!J5 -> 7351 | T3: Close Last Month | X3: =(W3-V3)*200 -> 0 | Y3: Close Last Month | AB3: ='[1]Water-Meter'!P5 -> 18541
A4: =[1]Gen!B11 -> 0.623 | B4: =[1]Gen!A11 -> 43739 | D4: 7909.6 | E4: 7913.1 | F4: =SUM(E4-D4)*120 -> 420 | H4: =B4 -> 43739 | J4: =SUM(K3) -> 36423 | K4: ='Water-Meter'!G6 -> 36434 | L4: =SUM(K4-J4) -> 11 | M4: =H4 -> 43739 | O4: =SUM(P3) -> 7351 | P4: ='Water-Meter'!J6 -> 7353 | Q4: =SUM(P4-O4) -> 2 | R4: =SUM(Q4/1615) -> 0.0012383901 | S4: =SUM(F4/[1]Gen!T10) -> #DIV/0! | T4: =M4 -> 43739 | V4: 7100.4 | W4: 7104.1 | X4: =(W4-V4)*200 -> 740 | Y4: =T4 -> 43739 | AA4: 3397.9 | AB4: ='Water-Meter'!P6 -> 18547 | AC4: =SUM(AB4-AA4) -> 15149.1
A5: =[1]Gen!B12 -> 0.779 | B5: =[1]Gen!A12 -> 43740 | D5: =E4 -> 7913.1 | E5: 7917.1 | F5: =SUM(E5-D5)*120 -> 480 | H5: =B5 -> 43740 | J5: =SUM(K4) -> 36434 | K5: ='Water-Meter'!G7 -> 36454 | L5: =SUM(K5-J5) -> 20 | M5: =H5 -> 43740 | O5: =SUM(P4) -> 7353 | P5: ='Water-Meter'!J7 -> 7357 | Q5: =SUM(P5-O5) -> 4 | R5: =SUM(Q5/1615) -> 0.0024767802 | S5: =SUM(F5/[1]Gen!T11) -> 0.084671018 | T5: =M5 -> 43740 | V5: =W4 -> 7104.1 | W5: 7108.6 | X5: =(W5-V5)*200 -> 900 | Y5: =T5 -> 43740 | AA5: =SUM(AB4) -> 18547 | AB5: ='Water-Meter'!P7 -> 18554 | AC5: =SUM(AB5-AA5) -> 7
A6: =[1]Gen!B13 -> 0.532 | B6: =[1]Gen!A13 -> 43741 | D6: =E5 -> 7917.1 | E6: 7921.3 | F6: =SUM(E6-D6)*120 -> 504 | H6: =B6 -> 43741 | J6: =SUM(K5) -> 36454 | K6: ='Water-Meter'!G8 -> 36472 | L6: =SUM(K6-J6) -> 18 | M6: =H6 -> 43741 | O6: =SUM(P5) -> 7357 | P6: ='Water-Meter'!J8 -> 7360 | Q6: =SUM(P6-O6) -> 3 | R6: =SUM(Q6/1615) -> 0.0018575851 | S6: =SUM(F6/[1]Gen!T12) -> 0.081831466 | T6: =M6 -> 43741 | V6: =W5 -> 7108.6 | W6: 7113.3 | X6: =(W6-V6)*200 -> 940 | Y6: =T6 -> 43741 | AA6: =SUM(AB5) -> 18554 | AB6: ='Water-Meter'!P8 -> 18563 | AC6: =SUM(AB6-AA6) -> 9
A7: =[1]Gen!B14 -> 0.61 | B7: =[1]Gen!A14 -> 43742 | D7: =E6 -> 7921.3 | E7: 7925.6 | F7: =SUM(E7-D7)*120 -> 516 | H7: =B7 -> 43742 | J7: =SUM(K6) -> 36472 | K7: ='Water-Meter'!G9 -> 36485 | L7: =SUM(K7-J7) -> 13 | M7: =H7 -> 43742 | O7: =SUM(P6) -> 7360 | P7: ='Water-Meter'!J9 -> 7364 | Q7: =SUM(P7-O7) -> 4 | R7: =SUM(Q7/1615) -> 0.0024767802 | S7: =SUM(F7/[1]Gen!T13) -> 0.078419453 | T7: =M7 -> 43742 | V7: =W6 -> 7113.3 | W7: 7117.9 | X7: =(W7-V7)*200 -> 920 | Y7: =T7 -> 43742 | AA7: =SUM(AB6) -> 18563 | AB7: ='Water-Meter'!P9 -> 18575 | AC7: =SUM(AB7-AA7) -> 12
A8: =[1]Gen!B15 -> 0.688 | B8: =[1]Gen!A15 -> 43743 | D8: =E7 -> 7925.6 | E8: 7930.1 | F8: =SUM(E8-D8)*120 -> 540 | H8: =B8 -> 43743 | J8: =SUM(K7) -> 36485 | K8: ='Water-Meter'!G10 -> 36500 | L8: =SUM(K8-J8) -> 15 | M8: =H8 -> 43743 | O8: =SUM(P7) -> 7364 | P8: ='Water-Meter'!J10 -> 7367 | Q8: =SUM(P8-O8) -> 3 | R8: =SUM(Q8/1615) -> 0.0018575851 | S8: =SUM(F8/[1]Gen!T14) -> 0.086774867 | T8: =M8 -> 43743 | V8: =W7 -> 7117.9 | W8: 7123.1 | X8: =(W8-V8)*200 -> 1040 | Y8: =T8 -> 43743 | AA8: =SUM(AB7) -> 18575 | AB8: ='Water-Meter'!P10 -> 18586 | AC8: =SUM(AB8-AA8) -> 11
A9: =[1]Gen!B16 -> 0.532 | B9: =[1]Gen!A16 -> 43744 | D9: =E8 -> 7930.1 | E9: 7933.8 | F9: =SUM(E9-D9)*120 -> 444 | H9: =B9 -> 43744 | J9: =SUM(K8) -> 36500 | K9: ='Water-Meter'!G11 -> 36516 | L9: =SUM(K9-J9) -> 16 | M9: =H9 -> 43744 | O9: =SUM(P8) -> 7367 | P9: ='Water-Meter'!J11 -> 7369 | Q9: =SUM(P9-O9) -> 2 | R9: =SUM(Q9/1615) -> 0.0012383901 | S9: =SUM(F9/[1]Gen!T15) -> 0.074197861 | T9: =M9 -> 43744 | V9: =W8 -> 7123.1 | W9: 7128.4 | X9: =(W9-V9)*200 -> 1060 | Y9: =T9 -> 43744 | AA9: =SUM(AB8) -> 18586 | AB9: ='Water-Meter'!P11 -> 18593 | AC9: =SUM(AB9-AA9) -> 7
A10: =[1]Gen!B17 -> 0.753 | B10: =[1]Gen!A17 -> 43745 | D10: =E9 -> 7933.8 | E10: 7938.2 | F10: =SUM(E10-D10)*120 -> 528 | H10: =B10 -> 43745 | J10: =SUM(K9) -> 36516 | K10: ='Water-Meter'!G12 -> 36529 | L10: =SUM(K10-J10) -> 13 | M10: =H10 -> 43745 | O10: =SUM(P9) -> 7369 | P10: ='Water-Meter'!J12 -> 7372 | Q10: =SUM(P10-O10) -> 3 | R10: =SUM(Q10/1615) -> 0.0018575851 | S10: =SUM(F10/[1]Gen!T16) -> 0.086514829 | T10: =M10 -> 43745 | V10: =W9 -> 7128.4 | W10: 7134 | X10: =(W10-V10)*200 -> 1120 | Y10: =T10 -> 43745 | AA10: =SUM(AB9) -> 18593 | AB10: ='Water-Meter'!P12 -> 18606 | AC10: =SUM(AB10-AA10) -> 13 | AH10: 5850
A11: =[1]Gen!B18 -> 0.156 | B11: =[1]Gen!A18 -> 43746 | D11: =E10 -> 7938.2 | E11: 7942.3 | F11: =SUM(E11-D11)*120 -> 492 | H11: =B11 -> 43746 | J11: =SUM(K10) -> 36529 | K11: ='Water-Meter'!G13 -> 36543 | L11: =SUM(K11-J11) -> 14 | M11: =H11 -> 43746 | O11: =SUM(P10) -> 7372 | P11: ='Water-Meter'!J13 -> 7374 | Q11: =SUM(P11-O11) -> 2 | R11: =SUM(Q11/1615) -> 0.0012383901 | S11: =SUM(F11/[1]Gen!T17) -> 0.088235294 | T11: =M11 -> 43746 | V11: =W10 -> 7134 | W11: 7138.5 | X11: =(W11-V11)*200 -> 900 | Y11: =T11 -> 43746 | AA11: =SUM(AB10) -> 18606 | AB11: ='Water-Meter'!P13 -> 18616 | AC11: =SUM(AB11-AA11) -> 10
A12: =[1]Gen!B19 -> 0.442 | B12: =[1]Gen!A19 -> 43747 | D12: =E11 -> 7942.3 | E12: 7946.7 | F12: =SUM(E12-D12)*120 -> 528 | H12: =B12 -> 43747 | J12: =SUM(K11) -> 36543 | K12: ='Water-Meter'!G14 -> 36560 | L12: =SUM(K12-J12) -> 17 | M12: =H12 -> 43747 | O12: =SUM(P11) -> 7374 | P12: ='Water-Meter'!J14 -> 7377 | Q12: =SUM(P12-O12) -> 3 | R12: =SUM(Q12/1615) -> 0.0018575851 | S12: =SUM(F12/[1]Gen!T18) -> 0.095444685 | T12: =M12 -> 43747 | V12: =W11 -> 7138.5 | W12: 7142.8 | X12: =(W12-V12)*200 -> 860 | Y12: =T12 -> 43747 | AA12: =SUM(AB11) -> 18616 | AB12: ='Water-Meter'!P14 -> 18623 | AC12: =SUM(AB12-AA12) -> 7
A13: =[1]Gen!B20 -> 0.325 | B13: =[1]Gen!A20 -> 43748 | D13: =E12 -> 7946.7 | E13: 7951.1 | F13: =SUM(E13-D13)*120 -> 528 | H13: =B13 -> 43748 | J13: =SUM(K12) -> 36560 | K13: ='Water-Meter'!G15 -> 36574 | L13: =SUM(K13-J13) -> 14 | M13: =H13 -> 43748 | O13: =SUM(P12) -> 7377 | P13: ='Water-Meter'!J15 -> 7381 | Q13: =SUM(P13-O13) -> 4 | R13: =SUM(Q13/1615) -> 0.0024767802 | S13: =SUM(F13/[1]Gen!T19) -> 0.084710412 | T13: =M13 -> 43748 | V13: =W12 -> 7142.8 | W13: 7146.7 | X13: =(W13-V13)*200 -> 780 | Y13: =T13 -> 43748 | AA13: =SUM(AB12) -> 18623 | AB13: ='Water-Meter'!P15 -> 18634 | AC13: =SUM(AB13-AA13) -> 11
A14: =[1]Gen!B21 -> 0.455 | B14: =[1]Gen!A21 -> 43749 | D14: =E13 -> 7951.1 | E14: 7955.5 | F14: =SUM(E14-D14)*120 -> 528 | H14: =B14 -> 43749 | J14: =SUM(K13) -> 36574 | K14: ='Water-Meter'!G16 -> 36591 | L14: =SUM(K14-J14) -> 17 | M14: =H14 -> 43749 | O14: =SUM(P13) -> 7381 | P14: ='Water-Meter'!J16 -> 7385 | Q14: =SUM(P14-O14) -> 4 | R14: =SUM(Q14/1615) -> 0.0024767802 | S14: =SUM(F14/[1]Gen!T20) -> 0.087085601 | T14: =M14 -> 43749 | V14: =W13 -> 7146.7 | W14: 7151.2 | X14: =(W14-V14)*200 -> 900 | Y14: =T14 -> 43749 | AA14: =SUM(AB13) -> 18634 | AB14: ='Water-Meter'!P16 -> 18643 | AC14: =SUM(AB14-AA14) -> 9
A15: =[1]Gen!B22 -> 0.416 | B15: =[1]Gen!A22 -> 43750 | D15: =E14 -> 7955.5 | E15: 7960.1 | F15: =SUM(E15-D15)*120 -> 552 | H15: =B15 -> 43750 | J15: =SUM(K14) -> 36591 | K15: ='Water-Meter'!G17 -> 36605 | L15: =SUM(K15-J15) -> 14 | M15: =H15 -> 43750 | O15: =SUM(P14) -> 7385 | P15: ='Water-Meter'!J17 -> 7388 | Q15: =SUM(P15-O15) -> 3 | R15: =SUM(Q15/1615) -> 0.0018575851 | S15: =SUM(F15/[1]Gen!T21) -> 0.092508798 | T15: =M15 -> 43750 | V15: =W14 -> 7151.2 | W15: 7155.5 | X15: =(W15-V15)*200 -> 860 | Y15: =T15 -> 43750 | AA15: =SUM(AB14) -> 18643 | AB15: ='Water-Meter'!P17 -> 18652 | AC15: =SUM(AB15-AA15) -> 9
A16: =[1]Gen!B23 -> 0.39 | B16: =[1]Gen!A23 -> 43751 | D16: =E15 -> 7960.1 | E16: 7964.1 | F16: =SUM(E16-D16)*120 -> 480 | H16: =B16 -> 43751 | J16: =SUM(K15) -> 36605 | K16: ='Water-Meter'!G18 -> 36619 | L16: =SUM(K16-J16) -> 14 | M16: =H16 -> 43751 | O16: =SUM(P15) -> 7388 | P16: ='Water-Meter'!J18 -> 7390 | Q16: =SUM(P16-O16) -> 2 | R16: =SUM(Q16/1615) -> 0.0012383901 | S16: =SUM(F16/[1]Gen!T22) -> 0.08186935 | T16: =M16 -> 43751 | V16: =W15 -> 7155.5 | W16: 7160.7 | X16: =(W16-V16)*200 -> 1040 | Y16: =T16 -> 43751 | AA16: =SUM(AB15) -> 18652 | AB16: ='Water-Meter'!P18 -> 18661 | AC16: =SUM(AB16-AA16) -> 9
A17: =[1]Gen!B24 -> 0.636 | B17: =[1]Gen!A24 -> 43752 | D17: =E16 -> 7964.1 | E17: 7968.6 | F17: =SUM(E17-D17)*120 -> 540 | H17: =B17 -> 43752 | J17: =SUM(K16) -> 36619 | K17: ='Water-Meter'!G19 -> 36632 | L17: =SUM(K17-J17) -> 13 | M17: =H17 -> 43752 | O17: =SUM(P16) -> 7390 | P17: ='Water-Meter'!J19 -> 7393 | Q17: =SUM(P17-O17) -> 3 | R17: =SUM(Q17/1615) -> 0.0018575851 | S17: =SUM(F17/[1]Gen!T23) -> 0.094405594 | T17: =M17 -> 43752 | V17: =W16 -> 7160.7 | W17: 7164.5 | X17: =(W17-V17)*200 -> 760 | Y17: =T17 -> 43752 | AA17: =SUM(AB16) -> 18661 | AB17: ='Water-Meter'!P19 -> 18672 | AC17: =SUM(AB17-AA17) -> 11
A18: =[1]Gen!B25 -> 0.844 | B18: =[1]Gen!A25 -> 43753 | D18: =E17 -> 7968.6 | E18: 7972.9 | F18: =SUM(E18-D18)*120 -> 516 | H18: =B18 -> 43753 | J18: =SUM(K17) -> 36632 | K18: ='Water-Meter'!G20 -> 36651 | L18: =SUM(K18-J18) -> 19 | M18: =H18 -> 43753 | O18: =SUM(P17) -> 7393 | P18: ='Water-Meter'!J20 -> 7396 | Q18: =SUM(P18-O18) -> 3 | R18: =SUM(Q18/1615) -> 0.0018575851 | S18: =SUM(F18/[1]Gen!T24) -> 0.083292978 | T18: =M18 -> 43753 | V18: =W17 -> 7164.5 | W18: 7169.5 | X18: =(W18-V18)*200 -> 1000 | Y18: =T18 -> 43753 | AA18: =SUM(AB17) -> 18672 | AB18: ='Water-Meter'!P20 -> 18680 | AC18: =SUM(AB18-AA18) -> 8
A19: =[1]Gen!B26 -> 0.818 | B19: =[1]Gen!A26 -> 43754 | D19: =E18 -> 7972.9 | E19: 7977.4 | F19: =SUM(E19-D19)*120 -> 540 | H19: =B19 -> 43754 | J19: =SUM(K18) -> 36651 | K19: ='Water-Meter'!G21 -> 36668 | L19: =SUM(K19-J19) -> 17 | M19: =H19 -> 43754 | O19: =SUM(P18) -> 7396 | P19: ='Water-Meter'!J21 -> 7398 | Q19: =SUM(P19-O19) -> 2 | R19: =SUM(Q19/1615) -> 0.0012383901 | S19: =SUM(F19/[1]Gen!T25) -> 0.08372093 | T19: =M19 -> 43754 | V19: =W18 -> 7169.5 | W19: 7173.6 | X19: =(W19-V19)*200 -> 820 | Y19: =T19 -> 43754 | AA19: =SUM(AB18) -> 18680 | AB19: ='Water-Meter'!P21 -> 18689 | AC19: =SUM(AB19-AA19) -> 9
A20: =[1]Gen!B27 -> 0.208 | B20: =[1]Gen!A27 -> 43755 | D20: =E19 -> 7977.4 | E20: 7982.2 | F20: =SUM(E20-D20)*120 -> 576 | H20: =B20 -> 43755 | J20: =SUM(K19) -> 36668 | K20: ='Water-Meter'!G22 -> 36681 | L20: =SUM(K20-J20) -> 13 | M20: =H20 -> 43755 | O20: =SUM(P19) -> 7398 | P20: ='Water-Meter'!J22 -> 7402 | Q20: =SUM(P20-O20) -> 4 | R20: =SUM(Q20/1615) -> 0.0024767802 | S20: =SUM(F20/[1]Gen!T26) -> 0.08329718 | T20: =M20 -> 43755 | V20: =W19 -> 7173.6 | W20: 7178.4 | X20: =(W20-V20)*200 -> 960 | Y20: =T20 -> 43755 | AA20: =SUM(AB19) -> 18689 | AB20: ='Water-Meter'!P22 -> 18701 | AC20: =SUM(AB20-AA20) -> 12
A21: =[1]Gen!B28 -> 0.221 | B21: =[1]Gen!A28 -> 43756 | D21: =E20 -> 7982.2 | E21: 7986.1 | F21: =SUM(E21-D21)*120 -> 468 | H21: =B21 -> 43756 | J21: =SUM(K20) -> 36681 | K21: ='Water-Meter'!G23 -> 36696 | L21: =SUM(K21-J21) -> 15 | M21: =H21 -> 43756 | O21: =SUM(P20) -> 7402 | P21: ='Water-Meter'!J23 -> 7404 | Q21: =SUM(P21-O21) -> 2 | R21: =SUM(Q21/1615) -> 0.0012383901 | S21: =SUM(F21/[1]Gen!T27) -> 0.078497149 | T21: =M21 -> 43756 | V21: =W20 -> 7178.4 | W21: 7186.1 | X21: =(W21-V21)*200 -> 1540 | Y21: =T21 -> 43756 | AA21: =SUM(AB20) -> 18701 | AB21: ='Water-Meter'!P23 -> 18712 | AC21: =SUM(AB21-AA21) -> 11
A22: =[1]Gen!B29 -> 0.117 | B22: =[1]Gen!A29 -> 43757 | D22: =E21 -> 7986.1 | E22: 7990.1 | F22: =SUM(E22-D22)*120 -> 480 | H22: =B22 -> 43757 | J22: =SUM(K21) -> 36696 | K22: ='Water-Meter'!G24 -> 36708 | L22: =SUM(K22-J22) -> 12 | M22: =H22 -> 43757 | O22: =SUM(P21) -> 7404 | P22: ='Water-Meter'!J24 -> 7408 | Q22: =SUM(P22-O22) -> 4 | R22: =SUM(Q22/1615) -> 0.0024767802 | S22: =SUM(F22/[1]Gen!T28) -> 0.091306829 | T22: =M22 -> 43757 | V22: =W21 -> 7186.1 | W22: 7189.1 | X22: =(W22-V22)*200 -> 600 | Y22: =T22 -> 43757 | AA22: =SUM(AB21) -> 18712 | AB22: ='Water-Meter'!P24 -> 18719 | AC22: =SUM(AB22-AA22) -> 7
A23: =[1]Gen!B30 -> 0.571 | B23: =[1]Gen!A30 -> 43758 | D23: =E22 -> 7990.1 | E23: 7993.9 | F23: =SUM(E23-D23)*120 -> 456 | H23: =B23 -> 43758 | J23: =SUM(K22) -> 36708 | K23: ='Water-Meter'!G25 -> 36724 | L23: =SUM(K23-J23) -> 16 | M23: =H23 -> 43758 | O23: =SUM(P22) -> 7408 | P23: ='Water-Meter'!J25 -> 7412 | Q23: =SUM(P23-O23) -> 4 | R23: =SUM(Q23/1615) -> 0.0024767802 | S23: =SUM(F23/[1]Gen!T29) -> 0.097207418 | T23: =M23 -> 43758 | V23: =W22 -> 7189.1 | W23: 7193.6 | X23: =(W23-V23)*200 -> 900 | Y23: =T23 -> 43758 | AA23: =SUM(AB22) -> 18719 | AB23: ='Water-Meter'!P25 -> 18728 | AC23: =SUM(AB23-AA23) -> 9
A24: =[1]Gen!B31 -> 0.558 | B24: =[1]Gen!A31 -> 43759 | D24: =SUM(E23) -> 7993.9 | E24: 7997.9 | F24: =SUM(E24-D24)*120 -> 480 | H24: =B24 -> 43759 | J24: =SUM(K23) -> 36724 | K24: ='Water-Meter'!G26 -> 36740 | L24: =SUM(K24-J24) -> 16 | M24: =H24 -> 43759 | O24: =SUM(P23) -> 7412 | P24: ='Water-Meter'!J26 -> 7415 | Q24: =SUM(P24-O24) -> 3 | R24: =SUM(Q24/1615) -> 0.0018575851 | S24: =SUM(F24/[1]Gen!T30) -> 0.084033613 | T24: 5835.7 | V24: =W23 -> 7193.6 | W24: 7197.1 | X24: =(W24-V24)*200 -> 700 | Y24: =T24 -> 5835.7 | AA24: =SUM(AB23) -> 18728 | AB24: ='Water-Meter'!P26 -> 18737 | AC24: =SUM(AB24-AA24) -> 9
A25: =[1]Gen!B32 -> 0.403 | B25: =[1]Gen!A32 -> 43760 | D25: =SUM(E24) -> 7997.9 | E25: 8001.9 | F25: =SUM(E25-D25)*120 -> 480 | H25: =B25 -> 43760 | J25: =SUM(K24) -> 36740 | K25: ='Water-Meter'!G27 -> 36754 | L25: =SUM(K25-J25) -> 14 | M25: =H25 -> 43760 | O25: =SUM(P24) -> 7415 | P25: ='Water-Meter'!J27 -> 7418 | Q25: =SUM(P25-O25) -> 3 | R25: =SUM(Q25/1615) -> 0.0018575851 | S25: =SUM(F25/[1]Gen!T31) -> 0.080794479 | T25: =M25 -> 43760 | V25: =W24 -> 7197.1 | W25: 7202.1 | X25: =(W25-V25)*200 -> 1000 | Y25: =T25 -> 43760 | AA25: =SUM(AB24) -> 18737 | AB25: ='Water-Meter'!P27 -> 18746 | AC25: =SUM(AB25-AA25) -> 9
A26: =[1]Gen!B33 -> 0.24 | B26: =[1]Gen!A33 -> 43761 | D26: =SUM(E25) -> 8001.9 | E26: 8006.4 | F26: =SUM(E26-D26)*120 -> 540 | H26: =B26 -> 43761 | J26: =SUM(K25) -> 36754 | K26: ='Water-Meter'!G28 -> 36767 | L26: =SUM(K26-J26) -> 13 | M26: =H26 -> 43761 | O26: =SUM(P25) -> 7418 | P26: ='Water-Meter'!J28 -> 7421 | Q26: =SUM(P26-O26) -> 3 | R26: =SUM(Q26/1615) -> 0.0018575851 | S26: =SUM(F26/[1]Gen!T32) -> 0.1 | T26: =M26 -> 43761 | V26: =W25 -> 7202.1 | W26: 7206.1 | X26: =(W26-V26)*200 -> 800 | Y26: =T26 -> 43761 | AA26: =SUM(AB25) -> 18746 | AB26: ='Water-Meter'!P28 -> 18754 | AC26: =SUM(AB26-AA26) -> 8
A27: =[1]Gen!B34 -> 0.09 | B27: =[1]Gen!A34 -> 43762 | D27: =SUM(E26) -> 8006.4 | E27: 8010.9 | F27: =SUM(E27-D27)*120 -> 540 | H27: =B27 -> 43762 | J27: =SUM(K26) -> 36767 | K27: ='Water-Meter'!G29 -> 36779 | L27: =SUM(K27-J27) -> 12 | M27: =H27 -> 43762 | O27: =SUM(P26) -> 7421 | P27: ='Water-Meter'!J29 -> 7423 | Q27: =SUM(P27-O27) -> 2 | R27: =SUM(Q27/1615) -> 0.0012383901 | S27: =SUM(F27/[1]Gen!T33) -> 0.10053994 | T27: =M27 -> 43762 | V27: =W26 -> 7206.1 | W27: 7210.5 | X27: =(W27-V27)*200 -> 880 | Y27: =T27 -> 43762 | AA27: =SUM(AB26) -> 18754 | AB27: ='Water-Meter'!P29 -> 18763 | AC27: =SUM(AB27-AA27) -> 9
A28: =[1]Gen!B35 -> 0.286 | B28: =[1]Gen!A35 -> 43763 | D28: =SUM(E27) -> 8010.9 | E28: 8014.9 | F28: =SUM(E28-D28)*120 -> 480 | H28: =B28 -> 43763 | J28: =SUM(K27) -> 36779 | K28: ='Water-Meter'!G30 -> 36792 | L28: =SUM(K28-J28) -> 13 | M28: =H28 -> 43763 | O28: =SUM(P27) -> 7423 | P28: ='Water-Meter'!J30 -> 7426 | Q28: =SUM(P28-O28) -> 3 | R28: =SUM(Q28/1615) -> 0.0018575851 | S28: =SUM(F28/[1]Gen!T34) -> 0.090634441 | T28: =M28 -> 43763 | V28: =W27 -> 7210.5 | W28: 7214.4 | X28: =(W28-V28)*200 -> 780 | Y28: =T28 -> 43763 | AA28: =SUM(AB27) -> 18763 | AB28: ='Water-Meter'!P30 -> 18773 | AC28: =SUM(AB28-AA28) -> 10
A29: =[1]Gen!B36 -> 0.545 | B29: =[1]Gen!A36 -> 43764 | D29: =SUM(E28) -> 8014.9 | E29: 8019.1 | F29: =SUM(E29-D29)*120 -> 504 | H29: =B29 -> 43764 | J29: =SUM(K28) -> 36792 | K29: ='Water-Meter'!G31 -> 36809 | L29: =SUM(K29-J29) -> 17 | M29: =H29 -> 43764 | O29: =SUM(P28) -> 7426 | P29: ='Water-Meter'!J31 -> 7428 | Q29: =SUM(P29-O29) -> 2 | R29: =SUM(Q29/1615) -> 0.0012383901 | S29: =SUM(F29/[1]Gen!T35) -> 0.096533231 | T29: =M29 -> 43764 | V29: =W28 -> 7214.4 | W29: 7218.1 | X29: =(W29-V29)*200 -> 740 | Y29: =T29 -> 43764 | AA29: =SUM(AB28) -> 18773 | AB29: ='Water-Meter'!P31 -> 18782 | AC29: =SUM(AB29-AA29) -> 9
A30: =[1]Gen!B37 -> 0.675 | B30: =[1]Gen!A37 -> 43765 | D30: =SUM(E29) -> 8019.1 | E30: 8023.1 | F30: =SUM(E30-D30)*120 -> 480 | H30: =B30 -> 43765 | J30: =SUM(K29) -> 36809 | K30: ='Water-Meter'!G32 -> 36825 | L30: =SUM(K30-J30) -> 16 | M30: =H30 -> 43765 | O30: =SUM(P29) -> 7428 | P30: ='Water-Meter'!J32 -> 7432 | Q30: =SUM(P30-O30) -> 4 | R30: =SUM(Q30/1615) -> 0.0024767802 | S30: =SUM(F30/[1]Gen!T36) -> 0.084730803 | T30: =M30 -> 43765 | V30: =W29 -> 7218.1 | W30: 7222.9 | X30: =(W30-V30)*200 -> 960 | Y30: =T30 -> 43765 | AA30: =SUM(AB29) -> 18782 | AB30: ='Water-Meter'!P32 -> 18790 | AC30: =SUM(AB30-AA30) -> 8
A31: =[1]Gen!B38 -> 0.273 | B31: =[1]Gen!A38 -> 43766 | D31: =SUM(E30) -> 8023.1 | E31: 8027.5 | F31: =SUM(E31-D31)*120 -> 528 | H31: =B31 -> 43766 | J31: =SUM(K30) -> 36825 | K31: ='Water-Meter'!G33 -> 36838 | L31: =SUM(K31-J31) -> 13 | M31: =H31 -> 43766 | O31: =SUM(P30) -> 7432 | P31: ='Water-Meter'!J33 -> 7435 | Q31: =SUM(P31-O31) -> 3 | R31: =SUM(Q31/1615) -> 0.0018575851 | S31: =SUM(F31/[1]Gen!T37) -> 0.086429858 | T31: =M31 -> 43766 | V31: =W30 -> 7222.9 | W31: 7226.8 | X31: =(W31-V31)*200 -> 780 | Y31: =T31 -> 43766 | AA31: =SUM(AB30) -> 18790 | AB31: ='Water-Meter'!P33 -> 18800 | AC31: =SUM(AB31-AA31) -> 10
A32: =[1]Gen!B39 -> #REF! | B32: =[1]Gen!A39 -> 43767 | D32: =SUM(E31) -> 8027.5 | E32: 8031.4 | F32: =SUM(E32-D32)*120 -> 468 | H32: =B32 -> 43767 | J32: =SUM(K31) -> 36838 | K32: ='Water-Meter'!G34 -> 36853 | L32: =SUM(K32-J32) -> 15 | M32: =H32 -> 43767 | O32: =SUM(P31) -> 7435 | P32: ='Water-Meter'!J34 -> 7438 | Q32: =SUM(P32-O32) -> 3 | R32: =SUM(Q32/1615) -> 0.0018575851 | S32: =SUM(F32/[1]Gen!T38) -> #DIV/0! | T32: =M32 -> 43767 | V32: =W31 -> 7226.8 | W32: 7230.9 | X32: =(W32-V32)*200 -> 820 | Y32: =T32 -> 43767 | AA32: =SUM(AB31) -> 18800 | AB32: ='Water-Meter'!P34 -> 18811 | AC32: =SUM(AB32-AA32) -> 11
A33: =[1]Gen!B40 -> #REF! | B33: =[1]Gen!A40 -> 43768 | D33: =SUM(E32) -> 8031.4 | E33: 8039.4 | F33: =SUM(E33-D33)*120 -> 960 | H33: =B33 -> 43768 | J33: =SUM(K32) -> 36853 | K33: ='Water-Meter'!G35 -> 36869 | L33: =SUM(K33-J33) -> 16 | M33: =H33 -> 43768 | O33: =SUM(P32) -> 7438 | P33: ='Water-Meter'!J35 -> 7441 | Q33: =SUM(P33-O33) -> 3 | R33: =SUM(Q33/1615) -> 0.0018575851 | S33: =SUM(F33/[1]Gen!T39) -> #DIV/0! | T33: =M33 -> 43768 | V33: =W32 -> 7230.9 | W33: 7240.3 | X33: =(W33-V33)*200 -> 1880 | Y33: =T33 -> 43768 | AA33: =SUM(AB32) -> 18811 | AB33: ='Water-Meter'!P35 -> 18819 | AC33: =SUM(AB33-AA33) -> 8
A34: =[1]Gen!B41 -> #REF! | B34: =[1]Gen!A41 -> 43769 | D34: =SUM(E33) -> 8039.4 | E34: 8043.7 | F34: =SUM(E34-D34)*120 -> 516 | H34: =B34 -> 43769 | J34: =SUM(K33) -> 36869 | K34: ='Water-Meter'!G36 -> 36884 | L34: =SUM(K34-J34) -> 15 | M34: =H34 -> 43769 | O34: =SUM(P33) -> 7441 | P34: ='Water-Meter'!J36 -> 7444 | Q34: =SUM(P34-O34) -> 3 | R34: =SUM(Q34/1615) -> 0.0018575851 | S34: =SUM(F34/[1]Gen!T40) -> #DIV/0! | T34: =M34 -> 43769 | V34: =SUM(W33) -> 7240.3 | W34: 7244.3 | X34: =(W34-V34)*200 -> 800 | Y34: =T34 -> 43769 | AA34: =SUM(AB33) -> 18819 | AB34: ='Water-Meter'!P36 -> 18829 | AC34: =SUM(AB34-AA34) -> 10
A35: =[1]Gen!B42 -> #REF! | B35: =[1]Gen!A42 -> #REF! | D35: =SUM(E34) -> 8043.7 | F35: =SUM(F4:F6) -> 1404 | H35: =B35 -> #REF! | J35: =SUM(K34) -> 36884 | K35: ='Water-Meter'!G37 -> 0 | L35: =SUM(L5:L34) -> 450 | M35: =H35 -> #REF! | O35: =SUM(P34) -> 7444 | P35: ='Water-Meter'!J37 -> 0 | Q35: =SUM(Q5:Q34) -> 91 | R35: =SUM(Q35/1615) -> 0.056346749 | S35: =SUM(F35/[1]Gen!T41) -> #DIV/0! | T35: =M35 -> #REF! | V35: =SUM(W34) -> 7244.3 | X35: =(W35-V35)*200 -> -1448860 | Y35: =T35 -> #REF! | AA35: =SUM(AB34) -> 18829 | AB35: ='Water-Meter'!P37 -> 0 | AC35: =SUM(AC5:AC34) -> 282
E36: 321 | L36: Total Exp | Q36: Total Exp | X36: =SUM(X4:X6) -> 2580 | AC36: Total Exp
B37: Electrical | E37: 321 | H37: Water | T37: Electrical | Y37: Water
B38: Cost | C38: 2856 | D38: =SUM(F35)*0.41 -> 575.64 | E38: 321 | H38: Cost | I38: 985 | J38: =SUM(L35) -> 450 | K38: =SUM(I38*J38) -> 443250 | T38: Cost | U38: 2856 | V38: =SUM(X35)*0.41 -> -594032.6 | W38: =SUM(U38*V38) -> -1.6965571e+09 | Y38: Cost | Z38: 985 | AA38: =SUM(AC35) -> 282 | AB38: =SUM(Z38*AA38) -> 277770
E39: 321
E40: 321
E41: 321
E42: 321 | W42: =SUM(A4:A14)/11 -> 0.53590909 | X42: =SUM(X4:X14)/11 -> 923.63636
E43: 321
E44: 321
E45: 321
E46: 321
E47: 321
E48: 321
E49: 321
E50: 321
E51: 321
E52: 321
E53: 321111

Sheet Summery Report
A2: Generator and Diseal Summry Report 2019
A4: Date | B4: Gen Set Hours Working | C4: Occ% | D4: Total OCC Room | E4: Guest Room Occ | F4: Total Kwh Generated | G4: Diesel consumed by Gen (Ltrs) | H4: Diesel consumed by Vehicle (Ltrs) | I4: Total diesel consumed (Ltrs) | J4: Balance stock of Diesel (Ltrs) | K4: Water consumed | L4: Gas consumed (KG)
A5: =[1]Gen!A11 -> 43739 | B5: ='Daily report Gen'!Z6 -> 57 | C5: =Gen!B11 -> 0.623 | D5: =E5 -> 48 | E5: 48 | F5: =Gen!T11 -> 5669 | G5: =Gen!S11 -> 2179.48 | H5: =Gen!AJ11 -> 203.28 | I5: =SUM(G5:H5) -> 2382.76 | J5: =[1]Gen!AT11 -> 47806.65 | K5: ='Water-Meter'!E6 -> 130 | L5: ='Lpg (2)'!G10 -> 95.964 | M5: =SUM(#REF!-#REF!) -> #REF!
A6: =[1]Gen!A12 -> 43740 | B6: ='Daily report Gen'!Z7 -> 42 | C6: =Gen!B12 -> 0.779 | D6: =E6 -> 62 | E6: 62 | F6: =Gen!T12 -> 6159 | G6: =Gen!S12 -> 2472.85 | H6: =Gen!AJ12 -> 31.45 | I6: =SUM(G6:H6) -> 2504.3 | J6: =[1]Gen!AT12 -> 45423.89 | K6: ='Water-Meter'!E7 -> 128 | L6: ='Lpg (2)'!G11 -> 112.596 | M6: =SUM(#REF!-#REF!) -> #REF!
A7: =[1]Gen!A13 -> 43741 | B7: ='Daily report Gen'!Z8 -> 44 | C7: =Gen!B13 -> 0.532 | D7: =E7 -> 41 | E7: 41 | F7: =Gen!T13 -> 6580 | G7: =Gen!S13 -> 2554.39 | H7: =Gen!AJ13 -> 106.26 | I7: =SUM(G7:H7) -> 2660.65 | J7: =[1]Gen!AT13 -> 42919.59 | K7: ='Water-Meter'!E8 -> 120 | L7: ='Lpg (2)'!G12 -> 116.16 | M7: =SUM(#REF!-#REF!) -> #REF!
A8: =[1]Gen!A14 -> 43742 | B8: ='Daily report Gen'!Z9 -> 43 | C8: =Gen!B14 -> 0.61 | D8: =E8 -> 47 | E8: 47 | F8: =Gen!T14 -> 6223 | G8: =Gen!S14 -> 2441.42 | H8: =Gen!AJ14 -> 292.31 | I8: =SUM(G8:H8) -> 2733.73 | J8: =[1]Gen!AT14 -> 40258.94 | K8: ='Water-Meter'!E9 -> 120 | L8: ='Lpg (2)'!G13 -> 117.92 | M8: =SUM(#REF!-#REF!) -> #REF!
A9: =[1]Gen!A15 -> 43743 | B9: ='Daily report Gen'!Z10 -> 40 | C9: =Gen!B15 -> 0.688 | D9: =E9 -> 53 | E9: 53 | F9: =Gen!T15 -> 5984 | G9: =Gen!S15 -> 2338.36 | H9: =Gen!AJ15 -> 79.16 | I9: =SUM(G9:H9) -> 2417.52 | J9: =[1]Gen!AT15 -> 37525.21 | K9: ='Water-Meter'!E10 -> 114 | L9: ='Lpg (2)'!G14 -> 121.44 | M9: =SUM(#REF!-#REF!) -> #REF!
A10: =[1]Gen!A16 -> 43744 | B10: ='Daily report Gen'!Z11 -> 42 | C10: =Gen!B16 -> 0.532 | D10: =E10 -> 41 | E10: 41 | F10: =Gen!T16 -> 6103 | G10: =Gen!S16 -> 2478.9 | H10: =Gen!AJ16 -> 115.65 | I10: =SUM(G10:H10) -> 2594.55 | J10: =[1]Gen!AT16 -> 35107.69 | K10: ='Water-Meter'!E11 -> 126 | L10: ='Lpg (2)'!G15 -> 120.56 | M10: =SUM(#REF!-#REF!) -> #REF!
A11: =[1]Gen!A17 -> 43745 | B11: ='Daily report Gen'!Z12 -> 43 | C11: =Gen!B17 -> 0.753 | D11: =E11 -> 58 | E11: 58 | F11: =Gen!T17 -> 5576 | G11: =Gen!S17 -> 2276.44 | H11: =Gen!AJ17 -> 74.81 | I11: =SUM(G11:H11) -> 2351.25 | J11: =[1]Gen!AT17 -> 47513.14 | K11: ='Water-Meter'!E12 -> 116 | L11: ='Lpg (2)'!G16 -> 119.68 | M11: =SUM(#REF!-#REF!) -> #REF!
A12: =[1]Gen!A18 -> 43746 | B12: ='Daily report Gen'!Z13 -> 42 | C12: =Gen!B18 -> 0.156 | D12: =E12 -> 12 | E12: 12 | F12: =Gen!T18 -> 5532 | G12: =Gen!S18 -> 2242.4 | H12: =Gen!AJ18 -> 94.01 | I12: =SUM(G12:H12) -> 2336.41 | J12: =[1]Gen!AT18 -> 45161.89 | K12: ='Water-Meter'!E13 -> 120 | L12: ='Lpg (2)'!G17 -> 118.36 | M12: =SUM(#REF!-#REF!) -> #REF!
A13: =[1]Gen!A19 -> 43747 | B13: ='Daily report Gen'!Z14 -> 42 | C13: =Gen!B19 -> 0.442 | D13: =E13 -> 34 | E13: 34 | F13: =Gen!T19 -> 6233 | G13: =Gen!S19 -> 2430.27 | H13: =Gen!AJ19 -> 284.83 | I13: =SUM(G13:H13) -> 2715.1 | J13: =[1]Gen!AT19 -> 42825.48 | K13: ='Water-Meter'!E14 -> 107 | L13: ='Lpg (2)'!G18 -> 117.04 | M13: =SUM(#REF!-#REF!) -> #REF!
A14: =[1]Gen!A20 -> 43748 | B14: ='Daily report Gen'!Z15 -> 42 | C14: =Gen!B20 -> 0.325 | D14: =E14 -> 25 | E14: 25 | F14: =Gen!T20 -> 6063 | G14: =Gen!S20 -> 2463.77 | H14: =Gen!AJ20 -> 106.04 | I14: =SUM(G14:H14) -> 2569.81 | J14: =[1]Gen!AT20 -> 40110.38 | K14: ='Water-Meter'!E15 -> 123 | L14: ='Lpg (2)'!G19 -> 116.16 | M14: =SUM(#REF!-#REF!) -> #REF!
A15: =[1]Gen!A21 -> 43749 | B15: ='Daily report Gen'!Z16 -> 46 | C15: =Gen!B21 -> 0.455 | D15: =E15 -> 35 | E15: 35 | F15: =Gen!T21 -> 5967 | G15: =Gen!S21 -> 2310.19 | H15: =Gen!AJ21 -> 263.09 | I15: =SUM(G15:H15) -> 2573.28 | J15: =[1]Gen!AT21 -> 37540.57 | K15: ='Water-Meter'!E16 -> 112 | L15: ='Lpg (2)'!G20 -> 110.88 | M15: =SUM(#REF!-#REF!) -> #REF!
A16: =[1]Gen!A22 -> 43750 | B16: ='Daily report Gen'!Z17 -> 44 | C16: =Gen!B22 -> 0.416 | D16: =E16 -> 32 | E16: 32 | F16: =Gen!T22 -> 5863 | G16: =Gen!S22 -> 2429.17 | H16: =Gen!AJ22 -> 309.36 | I16: =SUM(G16:H16) -> 2738.53 | J16: =[1]Gen!AT22 -> 34967.29 | K16: ='Water-Meter'!E17 -> 128 | L16: ='Lpg (2)'!G21 -> 108.24 | M16: =SUM(#REF!-#REF!) -> #REF!
... A35: =[1]Gen!A41 -> 43769 | B35: ='Daily report Gen'!Z36 -> 43 | C35: =Gen!B41 -> 0.325 | D35: =E35 -> 25 | E35: 25 | F35: =Gen!T41 -> 5234 | G35: =Gen!S41 -> 2126.42 | H35: =Gen!AJ41 -> 533.66 | I35: =SUM(G35:H35) -> 2660.08 | J35: =[1]Gen!AT41 -> 33780 | K35: ='Water-Meter'!E36 -> 111 | L35: ='Lpg (2)'!G40 -> 119.68 | M35: =SUM(#REF!-#REF!) -> #REF!
C36: =Gen!B42 -> 0 | D36: =E36 -> 0 | K36: ='[1]Water-Meter'!E41 -> #REF!
B38: =SUM(B5:B37)/[1]Gen!A47 -> #REF!
B39: =SUM(B38*[1]Gen!A47) -> #REF! | C39: =SUM(B39/250) -> #REF!

Sheet Daily report Gen
A1: 43739
K3: GENERATOR NO.1 | N3: GENERATOR NO.2 | Q3: GENERATOR NO.4 | T3: GENERATOR NO.5 | W3: GENERATOR NO.6
A4: DATE | B4: OCC% | C4: D-TANK A | D4: D-TANK B | E4: DELIVERY DATE | F4: DELIVERY | G4: ISSUED-VEHICLE | H4: OTHERS | I4: M-R LV PANEL 1. KW-HR | J4: M-R LV PANEL 2. KW-HR | K4: OPEN HRS READING | L4: CLOSE HRS READING | M4: RUNNING HRS | N4: OPEN HRS READING | O4: CLOSE HRS READING | P4: RUNNING HRS | Q4: OPEN HRS READING | R4: CLOSE HRS READING | S4: RUNNING HRS | T4: OPEN HRS READING | U4: CLOSE HRS READING | V4: RUNNING HRS | W4: OPEN HRS READING | Y4: RUNNING HRS | Z4: TOTAL RUNNING HRS | AA4: MAX KW | AB4: MIN-KW | AC4: TOTAL DIESEL CONS.
L5: 33001 | O5: 27710 | R5: 33285 | U5: 30628 | X5: 18157
A6: =[1]Gen!A11 -> 43739 | B6: 0.623 | C6: 24513.14 | D6: 9706.14 | G6: 203.28 | I6: 29001.8 | J6: 19100.1 | K6: ='[4]Daily report Gen'!L37 -> 0 | L6: 33001 | M6: =L6-L5 -> 0 | O6: 27730 | P6: =O6-O5 -> 20 | R6: 33285 | S6: =R6-R5 -> 0 | U6: 30647 | V6: =U6-U5 -> 19 | X6: 18175 | Y6: =X6-X5 -> 18 | Z6: =M6+P6+S6+V6+Y6 -> 57 | AA6: 416 | AB6: 173 | AC6: =Gen!AR11 -> 2382.76
A7: =[1]Gen!A12 -> 43740 | B7: 0.805 | C7: 24513.14 | D7: 19323.38 | G7: 31.45 | I7: 29011.2 | J7: 19106.1 | K7: ='[4]Daily report Gen'!L38 -> 0 | L7: 33001 | M7: =L7-L6 -> 0 | O7: 27747 | P7: =O7-O6 -> 17 | R7: 33285 | S7: =R7-R6 -> 0 | U7: 30665 | V7: =U7-U6 -> 18 | X7: 18182 | Y7: =X7-X6 -> 7 | Z7: =M7+P7+S7+V7+Y7 -> 42 | AA7: 409 | AB7: 181 | AC7: =Gen!AR12 -> 2504.3
A8: =[1]Gen!A13 -> 43741 | B8: 0.532 | C8: 24513.14 | D8: 16819.08 | G8: 106.26 | I8: 29022.1 | J8: 19112.6 | K8: ='[4]Daily report Gen'!L39 -> 0 | L8: 33001 | M8: =L8-L7 -> 0 | O8: 27767 | P8: =O8-O7 -> 20 | R8: 33285 | S8: =R8-R7 -> 0 | U8: 30669 | V8: =U8-U7 -> 4 | X8: 18202 | Y8: =X8-X7 -> 20 | Z8: =M8+P8+S8+V8+Y8 -> 44 | AA8: 453 | AB8: 191 | AC8: =Gen!AR13 -> 2660.65
A9: =[1]Gen!A14 -> 43742 | B9: 0.61 | C9: 24513.14 | D9: 14158.43 | G9: 292.31 | I9: 29032.9 | J9: 19120.1 | K9: ='[4]Daily report Gen'!L40 -> 0 | L9: 33001 | M9: =L9-L8 -> 0 | O9: 27785 | P9: =O9-O8 -> 18 | R9: 33285 | S9: =R9-R8 -> 0 | U9: 30687 | V9: =U9-U8 -> 18 | X9: 18209 | Y9: =X9-X8 -> 7 | Z9: =M9+P9+S9+V9+Y9 -> 43 | AA9: 562 | AB9: 209 | AC9: =Gen!AR14 -> 2733.73
A10: =[1]Gen!A15 -> 43743 | B10: 0.688 | C10: 24513.14 | D10: 11424.7 | G10: 79.16 | I10: 29042.7 | J10: 19126.9 | K10: ='[4]Daily report Gen'!L41 -> 0 | L10: 33001 | M10: =L10-L9 -> 0 | O10: 27800 | P10: =O10-O9 -> 15 | R10: 33285 | S10: =R10-R9 -> 0 | U10: 30694 | V10: =U10-U9 -> 7 | X10: 18227 | Y10: =X10-X9 -> 18 | Z10: =M10+P10+S10+V10+Y10 -> 40 | AA10: 497 | AB10: 211 | AC10: =Gen!AR15 -> 2417.52
A11: =[1]Gen!A16 -> 43744 | B11: 0.41 | C11: 24513.14 | D11: 9007.18 | G11: 115.65 | I11: 29052.9 | J11: 19133.6 | K11: ='[4]Daily report Gen'!L42 -> 0 | L11: 33001 | M11: =L11-L10 -> 0 | O11: 27817 | P11: =O11-O10 -> 17 | R11: 33285 | S11: =R11-R10 -> 0 | U11: 30707 | V11: =U11-U10 -> 13 | X11: 18239 | Y11: =X11-X10 -> 12 | Z11: =M11+P11+S11+V11+Y11 -> 42 | AA11: 498 | AB11: 195 | AC11: =Gen!AR16 -> 2594.55
A12: =[1]Gen!A17 -> 43745 | B12: 0.58 | C12: 24513.14 | D12: 23000.18 | G12: 74.81 | I12: 29063.1 | J12: 19140.7 | K12: ='[4]Daily report Gen'!L43 -> 0 | L12: 33001 | M12: =L12-L11 -> 0 | O12: 27836 | P12: =O12-O11 -> 19 | R12: 33285 | S12: =R12-R11 -> 0 | U12: 30716 | V12: =U12-U11 -> 9 | X12: 18254 | Y12: =X12-X11 -> 15 | Z12: =M12+P12+S12+V12+Y12 -> 43 | AA12: 496 | AB12: 196 | AC12: =Gen!AR17 -> 2351.25
A13: =[1]Gen!A18 -> 43746 | B13: 0.15 | C13: 24513.14 | D13: 20648.75 | G13: 94.01 | I13: 29072.2 | J13: 19147.4 | K13: ='[4]Daily report Gen'!L44 -> 0 | L13: 33001 | M13: =L13-L12 -> 0 | O13: 27853 | P13: =O13-O12 -> 17 | R13: 33285 | S13: =R13-R12 -> 0 | U13: 30729 | V13: =U13-U12 -> 13 | X13: 18266 | Y13: =X13-X12 -> 12 | Z13: =M13+P13+S13+V13+Y13 -> 42 | AA13: 498 | AB13: 198 | AC13: =Gen!AR18 -> 2336.41
A14: =[1]Gen!A19 -> 43747 | B14: 0.442 | C14: 24513.14 | D14: 18312.34 | G14: 284.83 | I14: 29081.5 | J14: 19153.8 | K14: ='[4]Daily report Gen'!L45 -> 0 | L14: 33001 | M14: =L14-L13 -> 0 | O14: 27871 | P14: =O14-O13 -> 18 | R14: 33285 | S14: =R14-R13 -> 0 | U14: 30743 | V14: =U14-U13 -> 14 | X14: 18276 | Y14: =X14-X13 -> 10 | Z14: =M14+P14+S14+V14+Y14 -> 42 | AA14: 486 | AB14: 193 | AC14: =Gen!AR19 -> 2715.1
A15: =[1]Gen!A20 -> 43748 | B15: 0.325 | C15: 24513.14 | D15: 15597.24 | G15: 106.04 | I15: 29091.4 | J15: 1961.3 | K15: ='[4]Daily report Gen'!L46 -> 0 | L15: 33001 | M15: =L15-L14 -> 0 | O15: 27889 | P15: =O15-O14 -> 18 | R15: 33285 | S15: =R15-R14 -> 0 | U15: 30747 | V15: =U15-U14 -> 4 | X15: 18296 | Y15: =X15-X14 -> 20 | Z15: =M15+P15+S15+V15+Y15 -> 42 | AA15: 490 | AB15: 201 | AC15: =Gen!AR20 -> 2569.81
A16: =[1]Gen!A21 -> 43749 | B16: 0.455 | C16: 24513.14 | D16: 13027.43 | G16: 263.09 | I16: 29101.3 | J16: 19168.2 | K16: ='[4]Daily report Gen'!L47 -> 0 | L16: 33001 | M16: =L16-L15 -> 0 | O16: 27912 | P16: =O16-O15 -> 23 | R16: 33285 | S16: =R16-R15 -> 0 | U16: 30747 | V16: =U16-U15 -> 0 | X16: 18319 | Y16: =X16-X15 -> 23 | Z16: =M16+P16+S16+V16+Y16 -> 46 | AA16: 498 | AB16: 203 | AC16: =Gen!AR21 -> 2573.28
A17: =[1]Gen!A22 -> 43750 | B17: 0.42 | C17: 24513.14 | D17: 10454.15 | G17: 309.36 | I17: 29111 | J17: 19175.1 | K17: ='[4]Daily report Gen'!L48 -> 0 | L17: 33008 | M17: =L17-L16 -> 7 | O17: 27925 | P17: =O17-O16 -> 13 | R17: 33285 | S17: =R17-R16 -> 0 | U17: 30764 | V17: =U17-U16 -> 17 | X17: 18326 | Y17: =X17-X16 -> 7 | Z17: =M17+P17+S17+V17+Y17 -> 44 | AA17: 503 | AB17: 210 | AC17: =Gen!AR22 -> 2738.53
... A36: =[1]Gen!A41 -> 43769 | B36: 0.32 | C36: 20081.34 | D36: 17779.21 | G36: 533.66 | I36: 29289.6 | J36: 19296.5 | K36: ='[4]Daily report Gen'!L67 -> 0 | L36: 33195 | M36: =L36-L35 -> 6 | O36: 28092 | P36: =O36-O35 -> 12 | R36: 33409 | S36: =R36-R35 -> 11 | U36: 30928 | V36: =U36-U35 -> 7 | X36: 18511 | Y36: =X36-X35 -> 7 | Z36: =M36+P36+S36+V36+Y36 -> 43 | AA36: 430 | AB36: 196 | AC36: =Gen!AR41 -> 2660.08
A37: =[1]Gen!A42 -> #REF! | C37: 17421.26 | D37: 17779.21 | K37: ='[4]Daily report Gen'!L68 -> 0 | M37: =L37-L36 -> -33195 | S37: =R37-R36 -> -33409 | V37: =U37-U36 -> -30928 | Y37: =X37-X36 -> -18511 | Z37: =M37+P37+S37+V37+Y37 -> -116043 | AC37: =Gen!AR42 -> 0

Sheet Gen
D2: HLP REPORT OCT. 2019
F6: BILILA LODGE INVESTMENT LIMITED | V6: 1 | W6: 2 | X6: 3 | Y6: 4 | Z6: 5 | AA6: 6 | AB6: 7 | AC6: 8 | AD6: 9 | AE6: 10 | AF6: 11
F7: Diesel Consumed by 500KVA Generator | M7: 500KVA Generator KWh | V7: Safari-STAFF | W7: Safari-STAFF | X7: Lc/swg/gust | Y7: Eng pikcup | Z7: VIP Safari Car | AA7: GX Guest | AB7: GX Guest | AC7: T/Hillux/pur | AD7: TATA | AE7: MAN | AF7: F/Truck | AG7: Incenerator | AH7: A&K | AI7: OTHER | AJ7: TOTAL CO
A8: Date | B8: Occupenccy % | C8: OPENING | D8: Received | E8: Schedule delivery | F8: PRICE | G8: 1 | H8: 2 | I8: 3 | J8: 4 | K8: 5 | L8: 6 | M8: 1 | N8: 2 | O8: 3 | P8: 4 | Q8: 5 | R8: 6 | S8: Total Diseal Consumed | T8: Total Kwh generated | U8: Average Diesel/Kwh | V8: T 128 AXJ | W8: T 134 AXJ | X8: T 499 AXG | Y8: T 217 CHV | Z8: T 214 CHV | AA8: T 139 AXE | AB8: T 242 AXN - SABASABA | AC8: T 476 AWZ | AD8: T 226 AUQ | AE8: T 308 CLD | AF8: T 852 AWU | AG8: Machine ENG | AH8: Vehicle | AI8: Vehicle | AR8: Total Diseal Consumed Gen & Vehicle | AS8: Total cost /Day (TSH) | AT8: BALANCE
C9: =[5]Gen!$C$43 -> 35806.65 | S9: =SUM(F9:L9) -> 0 | T9: =SUM(M9:R9) -> 0 | AR9: =SUM(AJ9+S9) -> 0 | AT9: 38784.7
S10: =SUM(F10:L10) -> 0 | T10: =SUM(M10:R10) -> 0 | U10: =SUM(N10:S10) -> 0 | AJ10: =SUM(V10:AI10) -> 0 | AR10: =SUM(AJ10+S10) -> 0
A11: 43739 | B11: 0.623 | C11: =SUM(C9+D11) -> 47806.65 | D11: 12000 | H11: 834.79 | K11: 991.93 | L11: 352.76 | N11: 2241 | Q11: 2406 | R11: 1022 | S11: =SUM(F11:L11) -> 2179.48 | T11: =SUM(M11:R11) -> 5669 | U11: =S11/T11 -> 0.38445581 | V11: 62.64 | W11: 39.99 | X11: 22.41 | AI11: 78.24 | AJ11: =SUM(V11:AI11) -> 203.28 | AR11: =SUM(AJ11+S11) -> 2382.76 | AS11: =AR11*AU11 -> 0 | AT11: =C11 -> 47806.65
A12: 43740 | B12: 0.779 | C12: =SUM(C11-AR11+D12) -> 45423.89 | H12: 1034.87 | K12: 211.48 | L12: 1226.5 | N12: 2811 | Q12: 619 | R12: 2729 | S12: =SUM(F12:L12) -> 2472.85 | T12: =SUM(M12:R12) -> 6159 | U12: =S12/T12 -> 0.40150187 | V12: 11.83 | X12: 19.62 | AJ12: =SUM(V12:AI12) -> 31.45 | AR12: =SUM(AJ12+S12) -> 2504.3 | AS12: =AR12*AU12 -> 0 | AT12: =C12 -> 45423.89
A13: 43741 | B13: 0.532 | C13: =SUM(C12-AR12+D13) -> 42919.59 | H13: 1051.6 | K13: 1104.82 | L13: 397.97 | N13: 2723 | Q13: 2768 | R13: 1089 | S13: =SUM(F13:L13) -> 2554.39 | T13: =SUM(M13:R13) -> 6580 | U13: =S13/T13 -> 0.38820517 | W13: 75.93 | Z13: 30.33 | AJ13: =SUM(V13:AH13) -> 106.26 | AR13: =SUM(AJ13+S13) -> 2660.65 | AS13: =AR13*AU13 -> 0 | AT13: =C13 -> 42919.59
A14: 43742 | B14: 0.61 | C14: =SUM(C13-AR13+D14) -> 40258.94 | H14: 830.76 | K14: 489.44 | L14: 1121.22 | N14: 2289 | Q14: 1122 | R14: 2812 | S14: =SUM(F14:L14) -> 2441.42 | T14: =SUM(M14:R14) -> 6223 | U14: =S14/T14 -> 0.39232203 | V14: 66.1 | W14: 48.58 | X14: 14.3 | Z14: 100.77 | AC14: 62.56 | AJ14: =SUM(V14:AH14) -> 292.31 | AR14: =SUM(AJ14+S14) -> 2733.73 | AS14: =AR14*AU14 -> 0 | AT14: =C14 -> 40258.94
A15: 43743 | B15: 0.688 | C15: =SUM(C14-AR14+D15) -> 37525.21 | H15: 954.3 | K15: 740.15 | L15: 643.91 | N15: 2442 | Q15: 1814 | R15: 1728 | S15: =SUM(F15:L15) -> 2338.36 | T15: =SUM(M15:R15) -> 5984 | U15: =S15/T15 -> 0.39076872 | W15: 43.47 | X15: 35.69 | AJ15: =SUM(V15:AH15) -> 79.16 | AR15: =SUM(AJ15+S15) -> 2417.52 | AS15: =AR15*AU15 -> 0 | AT15: =C15 -> 37525.21
A16: 43744 | B16: 0.532 | C16: =SUM(C15-AR15+D16) -> 35107.69 | H16: 1033.17 | K16: 481.74 | L16: 963.99 | N16: 2593 | Q16: 1187 | R16: 2323 | S16: =SUM(F16:L16) -> 2478.9 | T16: =SUM(M16:R16) -> 6103 | U16: =S16/T16 -> 0.40617729 | V16: 45.95 | W16: 12.7 | AH16: 57 | AJ16: =SUM(V16:AH16) -> 115.65 | AR16: =SUM(AJ16+S16) -> 2594.55 | AS16: =AR16*AU16 -> 0 | AT16: =C16 -> 35107.69
A17: 43745 | B17: 0.753 | C17: =SUM(C16-AR16+D17) -> 47513.14 | D17: 15000 | E17: 15000 | H17: 920.05 | K17: 777.14 | L17: 579.25 | N17: 2324 | Q17: 1904 | R17: 1348 | S17: =SUM(F17:L17) -> 2276.44 | T17: =SUM(M17:R17) -> 5576 | U17: =S17/T17 -> 0.40825681 | Y17: 74.81 | AJ17: =SUM(V17:AI17) -> 74.81 | AR17: =SUM(AJ17+S17) -> 2351.25 | AS17: =AR17*AU17 -> 0 | AT17: =C17 -> 47513.14
A18: 43746 | B18: 0.156 | C18: =SUM(C17-AR17+D18) -> 45161.89 | H18: 892.82 | K18: 781.58 | L18: 568 | N18: 2344 | Q18: 1865 | R18: 1323 | S18: =SUM(F18:L18) -> 2242.4 | T18: =SUM(M18:R18) -> 5532 | U18: =S18/T18 -> 0.40535069 | V18: 31.05 | W18: 33.15 | X18: 29.81 | AJ18: =SUM(V18:AI18) -> 94.01 | AR18: =SUM(AJ18+S18) -> 2336.41 | AS18: =AR18*AU18 -> 0 | AT18: =C18 -> 45161.89
A19: 43747 | B19: 0.442 | C19: =SUM(C18-AR18+D19) -> 42825.48 | H19: 986.09 | K19: 249.3 | L19: 1194.88 | N19: 2575 | Q19: 643 | R19: 3015 | S19: =SUM(F19:L19) -> 2430.27 | T19: =SUM(M19:R19) -> 6233 | U19: =S19/T19 -> 0.38990374 | W19: 11.98 | X19: 8.85 | AH19: 264 | AJ19: =SUM(V19:AI19) -> 284.83 | AR19: =SUM(AJ19+S19) -> 2715.1 | AS19: =AR19*AU19 -> 0 | AT19: =C19 -> 42825.48
A20: 43748 | B20: 0.325 | C20: =SUM(C19-AR19+D20) -> 40110.38 | H20: 1226.72 | L20: 1237.05 | N20: 3112 | R20: 2951 | S20: =SUM(F20:L20) -> 2463.77 | T20: =SUM(M20:R20) -> 6063 | U20: =S20/T20 -> 0.40636154 | V20: 71.87 | W20: 24.48 | X20: 9.69 | AJ20: =SUM(V20:AI20) -> 106.04 | AR20: =SUM(AJ20+S20) -> 2569.81 | AS20: =AR20*AU20 -> 0 | AT20: =C20 -> 40110.38
A21: 43749 | B21: 0.455 | C21: =SUM(C20-AR20+D21) -> 37540.57 | G21: 296.48 | H21: 729.56 | K21: 920.96 | L21: 363.19 | M21: 851 | N21: 1979 | Q21: 2283 | R21: 854 | S21: =SUM(F21:L21) -> 2310.19 | T21: =SUM(M21:R21) -> 5967 | U21: =S21/T21 -> 0.38716105 | W21: 50.13 | X21: 9.96 | AH21: 203 | AJ21: =SUM(V21:AI21) -> 263.09 | AR21: =SUM(AJ21+S21) -> 2573.28 | AS21: =AR21*AU21 -> 0 | AT21: =C21 -> 37540.57
A22: 43750 | B22: 0.416 | C22: =SUM(C21-AR21+D22) -> 34967.29 | G22: 940.35 | H22: 459.15 | K22: 370.76 | L22: 658.91 | M22: 2121 | N22: 1208 | Q22: 883 | R22: 1651 | S22: =SUM(F22:L22) -> 2429.17 | T22: =SUM(M22:R22) -> 5863 | U22: =S22/T22 -> 0.41432202 | V22: 11.51 | W22: 20.37 | Y22: 124.48 | AH22: 153 | AJ22: =SUM(V22:AI22) -> 309.36 | AR22: =SUM(AJ22+S22) -> 2738.53 | AS22: =AR22*AU22 -> 0 | AT22: =C22 -> 34967.29
A23: 43751 | B23: 0.39 | C23: =SUM(C22-AR22+D23) -> 32228.76 | G23: 810.68 | H23: 521.04 | K23: 594.42 | L23: 323.39 | M23: 2040 | N23: 1332 | Q23: 1412 | R23: 936 | S23: =SUM(F23:L23) -> 2249.53 | T23: =SUM(M23:R23) -> 5720 | U23: =S23/T23 -> 0.39327448 | V23: 49.4 | X23: 14.38 | AJ23: =SUM(V23:AI23) -> 63.78 | AR23: =SUM(AJ23+S23) -> 2313.31 | AS23: =AR23*AU23 -> 0 | AT23: =C23 -> 32228.76
A24: 43752 | B24: 0.636 | C24: =SUM(C23-AR23+D24) -> 29915.45 | E24: 18000 | G24: 547.53 | H24: 388.41 | K24: 374.1 | L24: 1114.43 | M24: 1473 | N24: 1217 | Q24: 936 | R24: 2569 | S24: =SUM(F24:L24) -> 2424.47 | T24: =SUM(M24:R24) -> 6195 | U24: =S24/T24 -> 0.39135916 | W24: 28.08 | X24: 32.22 | AC24: 65.5 | AH24: 121 | AJ24: =SUM(V24:AI24) -> 246.8 | AR24: =SUM(AJ24+S24) -> 2671.27 | AS24: =AR24*AU24 -> 0 | AT24: =C24 -> 29915.45
A25: 43753 | B25: 0.844 | C25: =SUM(C24-AR24+D25) -> 42244.18 | D25: 15000 | G25: 723.66 | H25: 660.49 | K25: 693.33 | L25: 594.83 | M25: 1738 | N25: 1782 | Q25: 1415 | R25: 1515 | S25: =SUM(F25:L25) -> 2672.31 | T25: =SUM(M25:R25) -> 6450 | U25: =S25/T25 -> 0.41431163 | X25: 16.25 | Z25: 25.31 | AI25: 39 | AJ25: =SUM(V25:AI25) -> 80.56 | AR25: =SUM(AJ25+S25) -> 2752.87 | AS25: =AR25*AU25 -> 0 | AT25: =C25 -> 42244.18
A26: 43754 | B26: 0.818 | C26: =SUM(C25-AR25+D26) -> 39491.31 | G26: 680.43 | H26: 413.85 | J26: 185.08 | K26: 696.2 | L26: 766.14 | M26: 1759 | N26: 1158 | P26: 283 | Q26: 1739 | R26: 1976 | S26: =SUM(F26:L26) -> 2741.7 | T26: =SUM(M26:R26) -> 6915 | U26: =S26/T26 -> 0.3964859 | AF26: 45.32 | AI26: 22 | AJ26: =SUM(V26:AI26) -> 67.32 | AR26: =SUM(AJ26+S26) -> 2809.02 | AS26: =AR26*AU26 -> 0 | AT26: =C26 -> 39491.31
A27: 43755 | B27: 0.208 | C27: =SUM(C26-AR26+D27) -> 36682.29 | G27: 465.56 | H27: 434.75 | J27: 358 | K27: 200.61 | L27: 862.19 | M27: 1188 | N27: 1138 | P27: 934 | Q27: 469 | R27: 2233 | S27: =SUM(F27:L27) -> 2321.11 | T27: =SUM(M27:R27) -> 5962 | U27: =S27/T27 -> 0.38931734 | X27: 57.69 | Y27: 81.21 | AH27: 249 | AI27: 210 | AJ27: =SUM(V27:AI27) -> 597.9 | AR27: =SUM(AJ27+S27) -> 2919.01 | AS27: =AR27*AU27 -> 0 | AT27: =C27 -> 36682.29
A28: 43756 | B28: 0.221 | C28: =SUM(C27-AR27+D28) -> 33763.28 | G28: 313.9 | H28: 567.41 | J28: 413.78 | K28: 262.55 | L28: 647.2 | M28: 759 | N28: 1359 | P28: 1047 | Q28: 590 | R28: 1502 | S28: =SUM(F28:L28) -> 2204.84 | T28: =SUM(M28:R28) -> 5257 | U28: =S28/T28 -> 0.41941031 | X28: 39.08 | Z28: 66.65 | AH28: 122 | AJ28: =SUM(V28:AI28) -> 227.73 | AR28: =SUM(AJ28+S28) -> 2432.57 | AS28: =AR28*AU28 -> 0 | AT28: =C28 -> 33763.28
A29: 43757 | B29: 0.117 | C29: =SUM(C28-AR28+D29) -> 31330.71 | G29: 424.23 | H29: 286.64 | J29: 335.22 | K29: 363.43 | L29: 435.66 | M29: 1198 | N29: 725 | P29: 828 | Q29: 814 | R29: 1126 | S29: =SUM(F29:L29) -> 1845.18 | T29: =SUM(M29:R29) -> 4691 | U29: =S29/T29 -> 0.3933447 | X29: 22.47 | Z29: 25.82 | AH29: 40 | AJ29: =SUM(V29:AI29) -> 88.29 | AR29: =SUM(AJ29+S29) -> 1933.47 | AS29: =AR29*AU29 -> 0 | AT29: =C29 -> 31330.71
A30: 43758 | B30: 0.571 | C30: =SUM(C29-AR29+D30) -> 29397.24 | G30: 540.28 | H30: 428.27 | I30: 600 | J30: 458.66 | K30: 381.62 | L30: 388.18 | M30: 1229 | N30: 1147 | P30: 1157 | Q30: 1119 | R30: 1060 | S30: =SUM(F30:L30) -> 2797.01 | T30: =SUM(M30:R30) -> 5712 | U30: =S30/T30 -> 0.48967262 | X30: 40.92 | AH30: 143 | AJ30: =SUM(V30:AI30) -> 183.92 | AR30: =SUM(AJ30+S30) -> 2980.93 | AS30: =AR30*AU30 -> 0 | AT30: =C30 -> 29397.24
A31: 43759 | B31: 0.558 | C31: =SUM(C30-AR30+D31) -> 41416.31 | D31: 15000 | E31: 15000 | G31: 750.48 | H31: 379.46 | J31: 381.39 | K31: 334.72 | L31: 416.11 | M31: 1499 | N31: 1029 | P31: 969 | Q31: 1399 | R31: 1045 | S31: =SUM(F31:L31) -> 2262.16 | T31: =SUM(M31:R31) -> 5941 | U31: =S31/T31 -> 0.38077091 | W31: 69.87 | X31: 17.66 | Z31: 35.84 | AC31: 48.68 | AJ31: =SUM(V31:AI31) -> 172.05 | AR31: =SUM(AJ31+S31) -> 2434.21 | AS31: =AR31*AU31 -> 0 | AT31: =C31 -> 41416.31
A32: 43760 | B32: 0.403 | C32: =SUM(C31-AR31+D32) -> 38982.1 | G32: 392.41 | H32: 714.75 | J32: 471.63 | K32: 284.99 | L32: 423.08 | M32: 873 | N32: 1453 | P32: 1238 | Q32: 511 | R32: 1325 | S32: =SUM(F32:L32) -> 2286.86 | T32: =SUM(M32:R32) -> 5400 | U32: =S32/T32 -> 0.42349259 | X32: 18.63 | AJ32: =SUM(V32:AI32) -> 18.63 | AR32: =SUM(AJ32+S32) -> 2305.49 | AS32: =AR32*AU32 -> 0 | AT32: =C32 -> 38982.1
A33: 43761 | B33: 0.24 | C33: =SUM(C32-AR32+D33) -> 36676.61 | G33: 659.46 | H33: 372.64 | J33: 394.2 | K33: 365.55 | L33: 356.45 | M33: 1346 | N33: 857 | P33: 968 | Q33: 1224 | R33: 976 | S33: =SUM(F33:L33) -> 2148.3 | T33: =SUM(M33:R33) -> 5371 | U33: =S33/T33 -> 0.39998138 | Z33: 21.33 | AC33: 30.67 | AH33: 66 | AI33: 193.34 | AJ33: =SUM(V33:AI33) -> 311.34 | AR33: =SUM(AJ33+S33) -> 2459.64 | AS33: =AR33*AU33 -> 0 | AT33: =C33 -> 36676.61 | AU33: =SUM(AU32) -> 0
A34: 43762 | B34: 0.09 | C34: =SUM(C33-AR33+D34) -> 44216.97 | D34: 10000 | G34: 590.81 | H34: 373.45 | J34: 353.12 | K34: 465.7 | L34: 330.19 | M34: 1499 | N34: 917 | P34: 813 | Q34: 1161 | R34: 906 | S34: =SUM(F34:L34) -> 2113.27 | T34: =SUM(M34:R34) -> 5296 | U34: =S34/T34 -> 0.39903134 | W34: 70.07 | Z34: 28.63 | AH34: 103 | AI34: 179 | AJ34: =SUM(V34:AI34) -> 380.7 | AR34: =SUM(AJ34+S34) -> 2493.97 | AS34: =AR34*AU34 -> 0 | AT34: =C34 -> 44216.97 | AU34: =SUM(AU33) -> 0
A35: 43763 | B35: 0.286 | C35: =SUM(C34-AR34+D35) -> 41723 | G35: 568.33 | H35: 356.81 | J35: 339.75 | K35: 364.91 | L35: 474.72 | M35: 1365 | N35: 872 | P35: 866 | Q35: 864 | R35: 1254 | S35: =SUM(F35:L35) -> 2104.52 | T35: =SUM(M35:R35) -> 5221 | U35: =S35/T35 -> 0.40308753 | X35: 37.66 | Y35: 29.16 | Z35: 18.55 | AI35: 188 | AJ35: =SUM(V35:AI35) -> 273.37 | AR35: =SUM(AJ35+S35) -> 2377.89 | AS35: =AR35*AU35 -> 0 | AT35: =C35 -> 41723 | AU35: =SUM(AU34) -> 0
A36: 43764 | B36: 0.545 | C36: =SUM(C35-AR35+D36) -> 39345.11 | G36: 375.76 | H36: 597.46 | J36: 420.31 | K36: 616.83 | L36: 459.88 | M36: 616 | N36: 1549 | P36: 1025 | Q36: 1469 | R36: 1006 | S36: =SUM(F36:L36) -> 2470.24 | T36: =SUM(M36:R36) -> 5665 | U36: =S36/T36 -> 0.43605296 | W36: 46.4 | X36: 9.38 | AD36: 174.05 | AI36: 166.73 | AJ36: =SUM(V36:AI36) -> 396.56 | AR36: =SUM(AJ36+S36) -> 2866.8 | AS36: =AR36*AU36 -> 0 | AT36: =C36 -> 39345.11 | AU36: =SUM(AU35) -> 0
A37: 43765 | B37: 0.675 | C37: =SUM(C36-AR36+D37) -> 36478.31 | G37: 460.53 | H37: 486.95 | J37: 467.04 | K37: 537.99 | L37: 371.23 | M37: 1000 | N37: 1643 | P37: 952 | Q37: 1561 | R37: 953 | S37: =SUM(F37:L37) -> 2323.74 | T37: =SUM(M37:R37) -> 6109 | U37: =S37/T37 -> 0.38037977 | V37: 80.63 | AI37: 200 | AJ37: =SUM(V37:AI37) -> 280.63 | AR37: =SUM(AJ37+S37) -> 2604.37 | AS37: =AR37*AU37 -> 0 | AT37: =C37 -> 36478.31 | AU37: =SUM(AU36) -> 0
A38: 43766 | B38: 0.273 | C38: =SUM(C37-AR37+D38) -> 44873.94 | D38: 11000 | E38: 18000 | H38: 478.88 | J38: 389.78 | K38: 456.14 | L38: 707.03 | N38: 1218 | P38: 953 | Q38: 1169 | R38: 1785 | S38: =SUM(F38:L38) -> 2031.83 | T38: =SUM(M38:R38) -> 5125 | U38: =S38/T38 -> 0.39645463 | V38: 25.52 | W38: 34.95 | X38: 8.67 | Y38: 45.96 | Z38: 37.67 | AH38: 343 | AI38: 180.52 | AJ38: =SUM(V38:AI38) -> 676.29 | AR38: =SUM(AJ38+S38) -> 2708.12 | AS38: =AR38*AU38 -> 0 | AT38: =C38 -> 44873.94 | AU38: =SUM(AU37) -> 0
A39: 43767 | B39: 0.416 | C39: =SUM(C38-AR38+D39) -> 42165.82 | G39: 354.94 | H39: 364.88 | J39: 671.52 | K39: 281.78 | L39: 458.25 | M39: 1364 | N39: 734 | Q39: 693 | R39: 652 | S39: =SUM(F39:L39) -> 2131.37 | T39: =SUM(M39:R39) -> 3443 | U39: =S39/T39 -> 0.61904444 | V39: 11.48 | X39: 9.6 | Y39: 23.51 | Z39: 16.11 | AI39: 60 | AJ39: =SUM(V39:AI39) -> 120.7 | AR39: =SUM(AJ39+S39) -> 2252.07 | AS39: =AR39*AU39 -> 0 | AT39: =C39 -> 42165.82 | AU39: =SUM(AU38) -> 0
A40: 43768 | B40: 0.429 | C40: =SUM(C39-AR39+D40) -> 39913.75 | G40: 320.9 | H40: 442.39 | J40: 625.47 | K40: 349.41 | L40: 295.57 | M40: 775 | N40: 1387 | P40: 1478 | Q40: 798 | R40: 754 | S40: =SUM(F40:L40) -> 2033.74 | T40: =SUM(M40:R40) -> 5192 | U40: =S40/T40 -> 0.39170647 | W40: 12.54 | Z40: 12.98 | AJ40: =SUM(V40:AI40) -> 25.52 | AR40: =SUM(AJ40+S40) -> 2059.26 | AS40: =AR40*AU40 -> 0 | AT40: =C40 -> 39913.75 | AU40: =SUM(AU39) -> 0
A41: 43769 | B41: 0.325 | C41: =SUM(C40-AR40+D41) -> 37854.49 | G41: 213.1 | H41: 362.41 | J41: 588.06 | K41: 687.8 | L41: 275.05 | M41: 743 | N41: 870 | P41: 1502 | Q41: 1383 | R41: 736 | S41: =SUM(F41:L41) -> 2126.42 | T41: =SUM(M41:R41) -> 5234 | U41: =S41/T41 -> 0.40627054 | V41: 67.37 | W41: 24.56 | Z41: 12.73 | AH41: 429 | AJ41: =SUM(V41:AI41) -> 533.66 | AR41: =SUM(AJ41+S41) -> 2660.08 | AS41: =AR41*AU41 -> 0 | AT41: =C41 -> 37854.49 | AU41: =SUM(AU40) -> 0
C42: =SUM(C41-AR41+D42) -> 35194.41 | S42: =SUM(F42:L42) -> 0 | T42: =SUM(M42:R42) -> 0 | AJ42: =SUM(V42:AI42) -> 0 | AR42: =SUM(AJ42+S42) -> 0 | AS42: =AR42*AU42 -> 0 | AT42: =C42 -> 35194.41
A43: BF | C43: =SUM(C42-AR42+D43) -> 35194.41 | S43: =SUM(F43:L43) -> 0 | T43: =SUM(M43:R43) -> 0 | AJ43: =SUM(V43:AI43) -> 0 | AR43: =SUM(AJ43+S43) -> 0 | AS43: =AR43*AU43 -> 0 | AT43: =C43 -> 35194.41
S44: =SUM(F44:L44) -> 0 | AJ44: =SUM(V44:AI44) -> 0 | AR44: =S44+AJ44 -> 0 | AS44: =AR44*AU44 -> 0
D45: =SUM(D11:D44) -> 78000 | E45: =SUM(E11:E42) -> 66000 | F45: =SUM(F11:F44) -> 0 | G45: =SUM(G11:G44) -> 10429.82 | H45: =SUM(H11:H44) -> 19584.82 | I45: =SUM(I11:I44) -> 600 | J45: =SUM(J11:J44) -> 6853.01 | K45: =SUM(K11:K44) -> 15431.38 | L45: =SUM(L11:L44) -> 19007.21 | M45: =SUM(M11:M44) -> 25436 | ... O45: =SUM(O11:O44) -> 0 | P45: =SUM(P11:P43) -> 15013 | Q45: =SUM(Q11:Q44) -> 38220 | R45: =SUM(R11:R44) -> 47154 | S45: =SUM(F45:L45) -> 71906.24 | T45: =SUM(M45:R45) -> 176851 | U45: =SUM(U11:U42) -> 12.698235 | V45: =SUM(V9:V44) -> 535.35 | W45: =SUM(W9:W44) -> 647.25 | X45: =SUM(X9:X44) -> 474.94 | Y45: =SUM(Y9:Y44) -> 379.13 | Z45: =SUM(Z9:Z44) -> 432.72 | AA45: =SUM(AA9:AA44) -> 0 | AB45: =SUM(AB9:AB44) -> 0 | AC45: =SUM(AC10:AC44) -> 207.41 | AD45: =SUM(AD10:AD44) -> 174.05 | AE45: =SUM(AE9:AE44) -> 0 | AF45: =SUM(AF9:AF44) -> 45.32 | AG45: =SUM(AG9:AG44) -> 0 | AH45: =SUM(AH9:AH43) -> 2293 | AI45: =SUM(AI9:AI39) -> 1516.83 | AJ45: =SUM(AJ9:AJ44) -> 6706 | AR45: =SUM(AR11:AR43) -> 78612.24 | AS45: =SUM(AS11:AS44) -> 0
A46: Nb Day | AC46: =SUM(AC44/A47) -> #DIV/0! | AD46: =SUM(AD44/A47) -> #DIV/0! | AJ46: 0 | AQ46: =SUM(AQ45/12) -> 0
R47: =SUM(S47+#REF!) -> #REF! | T47: =S45*2143 -> 1.5409507e+08 | U47: TZS | W47: =SUM(W45/A47) -> #DIV/0! | X47: =SUM(X45/A47) -> #DIV/0! | Y47: =SUM(Y45/A47) -> #DIV/0! | Z47: =SUM(Z45/A47) -> #DIV/0! | AA47: =SUM(AA45/A47) -> #DIV/0! | AB47: =SUM(AB45/A47) -> #DIV/0! | AF47: =SUM(AF45/A47) -> #DIV/0! | AG47: =SUM(AG45/A47) -> #DIV/0! | AQ47: =SUM(AQ45/A47) -> #DIV/0!
A48: Av. Occ | B48: =SUM(B11:B41)/A47 -> #DIV/0! | T48: =T47/2245 -> 68639.23 | U48: USD | AR48: =AVERAGE(AR11:AR24) -> 2540.1764
AJ49: =SUM(AJ10:AJ25)/A47 -> #DIV/0! | AR49: =SUM(AQ45*'[1]Summery Report'!#REF!) -> #REF!
B50: A & K VEHICLES | F50: MAULY VEHICLES | L50: GREENLAND VEHICLE | S50: OTHERS VEHICLES | AJ50: =SUM(#REF!-AI34)/14 -> #REF!
B51: Date | C51: Vehicles | D51: Liters | E51: Driver name | F51: Date | H51: Vehicles | I51: Liters | K51: Driver name | L51: Date | N51: Vehicles | O51: Liters | Q51: Driver name | R51: Authorized Manager | S51: Date | T51: Vehicles | U51: Liters | V51: Driver name | W51: Athorized Manager | X51: Reasons
B52: 43744 | C52: T111CWQ | D52: 57 | E52: Richard | L52: 43755 | N52: T469DPE | O52: 50 | Q52: Stevin | S52: 43740 | T52: T465DJQ | U52: 78.24 | V52: Elisha | W52: P&C
B53: 43747 | C53: T677DND | D53: 80 | E53: George | L53: 43755 | N53: T165DKR | O53: 90 | Q53: Chande | S53: 43753 | T53: T489BHF | U53: 39 | V53: Mudy | W53: Wendo
B54: 43747 | C54: T853DDN | D54: 80 | E54: Othuman | L54: 43755 | N54: T739BRW | O54: 70 | Q54: Naftari | S54: 43754 | T54: T489BHF | U54: 22 | V54: Mudy | W54: Wendo
B55: 43747 | C55: T380DQR | D55: 104 | E55: Mushi | L55: 43767 | N55: 228CRW | O55: 60 | Q55: Charles | S55: 43761 | T55: SU33656 | U55: 193.34 | V55: BHOKE | W55: Wendo
B56: 43749 | C56: T132CWQ | D56: 111 | E56: Baraka | S56: 43762 | T56: SU33656 | U56: 179 | V56: BHOKE | W56: Wendo
B57: 43749 | C57: T840DDW | D57: 92 | E57: Dickson | S57: 43763 | T57: SU33656 | U57: 188 | V57: BHOKE | W57: Wendo
B58: 43750 | C58: T882DKQ | D58: 153 | E58: Joseph | S58: 43764 | T58: SU33656 | U58: 166.73 | V58: BHOKE | W58: Wendo
B59: 43752 | C59: T106CWQ | D59: 121 | E59: Elly | S59: 43765 | T59: SU33657 | U59: 200 | V59: BHOKE | W59: Wendo
B60: 43755 | C60: T840DDW | D60: 114 | E60: Dickson | S60: 43766 | T60: SU33657 | U60: 180.52 | V60: BHOKE | W60: Vedastus
B61: 43755 | C61: T111CWQ | D61: 135 | E61: Richard
B62: 43756 | C62: T132CWQ | D62: 122 | E62: Baraka
B63: 43757 | C63: T389DQR | D63: 40 | E63: Shuma
B64: 43758 | C64: T882DKQ | D64: 143 | E64: Joseph
B65: 43761 | C65: T132CWQ | D65: 66 | E65: Zakayo
B66: 43762 | C66: T111CWQ | D66: 103 | E66: Baraka
B67: 43766 | C67: T111CWQ | D67: 97 | E67: Baraka
B68: 43766 | C68: T880DKQ | D68: 120 | E68: Richard
B69: 43766 | C69: T106CWQ | D69: 126 | E69: Elly
B70: 43769 | C70: T882DKQ | D70: 124 | E70: Joseph
B71: 43769 | C71: T364AHF | D71: 30 | E71: Fadhili
B72: 43769 | C72: T840DDW | D72: 111 | E72: Dickson
... B75: 43769 | C75: T880DKQ | D75: 42 | E75: Kelvin
O77: 67

Sheet Energy Graph
A1: Date | B1: Usage KW | C1: Occ % | D1: Cost per room Total Occ | E1: Cost per room Guest Occ
A2: =SUM([1]Gen!A11) -> 43739 | B2: =SUM('[1]Summery Report'!F5) -> 5669 | C2: =SUM('[1]Summery Report'!C5) -> 0.623 | D2: =SUM('[1]Summery Report'!#REF!) -> #REF! | E2: =SUM('[1]Summery Report'!#REF!) -> #REF! | F2: 0.1
A3: =SUM([1]Gen!A12) -> 43740 | B3: =SUM('[1]Summery Report'!F6) -> 6159 | C3: =SUM('[1]Summery Report'!C6) -> 0.779 | D3: =SUM('[1]Summery Report'!#REF!) -> #REF! | E3: =SUM('[1]Summery Report'!#REF!) -> #REF! | F3: 0.1375
A4: =SUM([1]Gen!A13) -> 43741 | B4: =SUM('[1]Summery Report'!F7) -> 6580 | C4: =SUM('[1]Summery Report'!C7) -> 0.532 | D4: =SUM('[1]Summery Report'!#REF!) -> #REF! | E4: =SUM('[1]Summery Report'!#REF!) -> #REF! | F4: 0.0875
A5: =SUM([1]Gen!A14) -> 43742 | B5: =SUM('[1]Summery Report'!F8) -> 6223 | C5: =SUM('[1]Summery Report'!C8) -> 0.61 | D5: =SUM('[1]Summery Report'!#REF!) -> #REF! | E5: =SUM('[1]Summery Report'!#REF!) -> #REF! | F5: 0.225
A6: =SUM([1]Gen!A15) -> 43743 | B6: =SUM('[1]Summery Report'!F9) -> 5984 | C6: =SUM('[1]Summery Report'!C9) -> 0.688 | D6: =SUM('[1]Summery Report'!#REF!) -> #REF! | E6: =SUM('[1]Summery Report'!#REF!) -> #REF! | F6: 0.2
A7: =SUM([1]Gen!A16) -> 43744 | B7: =SUM('[1]Summery Report'!F10) -> 6103 | C7: =SUM('[1]Summery Report'!C10) -> 0.532 | D7: =SUM('[1]Summery Report'!#REF!) -> #REF! | E7: =SUM('[1]Summery Report'!#REF!) -> #REF! | F7: 0.35
A8: =SUM([1]Gen!A17) -> 43745 | B8: =SUM('[1]Summery Report'!F11) -> 5576 | C8: =SUM('[1]Summery Report'!C11) -> 0.753 | D8: =SUM('[1]Summery Report'!#REF!) -> #REF! | E8: =SUM('[1]Summery Report'!#REF!) -> #REF! | F8: 0.375
A9: =SUM([1]Gen!A18) -> 43746 | B9: =SUM('[1]Summery Report'!F12) -> 5532 | C9: =SUM('[1]Summery Report'!C12) -> 0.156 | D9: =SUM('[1]Summery Report'!#REF!) -> #REF! | E9: =SUM('[1]Summery Report'!#REF!) -> #REF! | F9: 0.325
A10: =SUM([1]Gen!A19) -> 43747 | B10: =SUM('[1]Summery Report'!F13) -> 6233 | C10: =SUM('[1]Summery Report'!C13) -> 0.442 | D10: =SUM('[1]Summery Report'!#REF!) -> #REF! | E10: =SUM('[1]Summery Report'!#REF!) -> #REF! | F10: 0.75
A11: =SUM([1]Gen!A20) -> 43748 | B11: =SUM('[1]Summery Report'!F14) -> 6063 | C11: =SUM('[1]Summery Report'!C14) -> 0.325 | D11: =SUM('[1]Summery Report'!#REF!) -> #REF! | E11: =SUM('[1]Summery Report'!#REF!) -> #REF! | F11: 0.7625
A12: =SUM([1]Gen!A21) -> 43749 | B12: =SUM('[1]Summery Report'!F15) -> 5967 | C12: =SUM('[1]Summery Report'!C15) -> 0.455 | D12: =SUM('[1]Summery Report'!#REF!) -> #REF! | E12: =SUM('[1]Summery Report'!#REF!) -> #REF! | F12: 0.1625
A13: =SUM([1]Gen!A22) -> 43750 | B13: =SUM('[1]Summery Report'!F16) -> 5863 | C13: =SUM('[1]Summery Report'!C16) -> 0.416 | D13: =SUM('[1]Summery Report'!#REF!) -> #REF! | E13: =SUM('[1]Summery Report'!#REF!) -> #REF! | F13: 0.1125
... A32: =SUM([1]Gen!A41) -> 43769 | B32: =SUM('[1]Summery Report'!F35) -> 0 | C32: =SUM('[1]Summery Report'!C35) -> 0 | D32: =SUM('[1]Summery Report'!#REF!) -> #REF! | E32: =SUM('[1]Summery Report'!#REF!) -> #REF! | F32: 0.175
B33: =[1]Gen!S41 -> 0

Sheet Lpg (2)
C3: Four Sasons Safari Lodge Serengeti | H3: =4579-#REF! -> #REF!
G6: VALUE | H6: Cost
A7: DATE | B7: A | C7: B | D7: C | F7: Meter Reading | G7: Total | H7: Occu | I7: No.of | J7: Kg
B8: 2Ton% | C8: 1Ton (%) | D8: 1Ton% | F8: consumption | G8: Consumption Kg | H8: % | I8: pax | J8: per pax
F9: 66501.6
A10: =[1]Gen!A11 -> 43739 | B10: 85 | C10: 41 | D10: 85 | F10: 66523.41 | G10: =(F10-F9)*4.4 -> 95.964 | H10: ='[1]Summery Report'!C5 -> 0.623 | I10: =SUM(F10/H10) -> 106779.15 | J10: =SUM(G10/I10) -> 0.00089871478
A11: =[1]Gen!A12 -> 43740 | B11: 85 | C11: 38 | D11: 85 | F11: 66549 | G11: =(F11-F10)*4.4 -> 112.596 | H11: ='[1]Summery Report'!C6 -> 0.779 | I11: =SUM(F11/H11) -> 85428.755 | J11: =SUM(G11/I11) -> 0.0013180105
A12: =[1]Gen!A13 -> 43741 | B12: 85 | C12: 33 | D12: 85 | F12: 66575.4 | G12: =(F12-F11)*4.4 -> 116.16 | H12: ='[1]Summery Report'!C7 -> 0.532 | I12: =SUM(F12/H12) -> 125141.73 | J12: =SUM(G12/I12) -> 0.00092822754
A13: =[1]Gen!A14 -> 43742 | B13: 85 | C13: 29 | D13: 85 | F13: 66602.2 | G13: =(F13-F12)*4.4 -> 117.92 | H13: ='[1]Summery Report'!C8 -> 0.61 | I13: =SUM(F13/H13) -> 109183.93 | J13: =SUM(G13/I13) -> 0.0010800124
A14: =[1]Gen!A15 -> 43743 | B14: 85 | C14: 24 | D14: 85 | F14: 66629.8 | G14: =(F14-F13)*4.4 -> 121.44 | H14: ='[1]Summery Report'!C9 -> 0.688 | I14: =SUM(F14/H14) -> 96845.64 | J14: =SUM(G14/I14) -> 0.0012539542
A15: =[1]Gen!A16 -> 43744 | B15: 85 | C15: 19 | D15: 85 | F15: 66657.2 | G15: =(F15-F14)*4.4 -> 120.56 | H15: ='[1]Summery Report'!C10 -> 0.532 | I15: =SUM(F15/H15) -> 125295.49 | J15: =SUM(G15/I15) -> 0.00096220543
A16: =[1]Gen!A17 -> 43745 | B16: 85 | C16: 15 | D16: 85 | F16: 66684.4 | G16: =(F16-F15)*4.4 -> 119.68 | H16: ='[1]Summery Report'!C11 -> 0.753 | I16: =SUM(F16/H16) -> 88558.3 | J16: =SUM(G16/I16) -> 0.0013514261
A17: =[1]Gen!A18 -> 43746 | B17: 85 | C17: 9 | D17: 85 | F17: 66711.3 | G17: =(F17-F16)*4.4 -> 118.36 | H17: ='[1]Summery Report'!C12 -> 0.156 | I17: =SUM(F17/H17) -> 427636.54 | J17: =SUM(G17/I17) -> 0.0002767771
A18: =[1]Gen!A19 -> 43747 | B18: 85 | C18: 5 | D18: 76 | F18: 66737.9 | G18: =(F18-F17)*4.4 -> 117.04 | H18: ='[1]Summery Report'!C13 -> 0.442 | I18: =SUM(F18/H18) -> 150990.72 | J18: =SUM(G18/I18) -> 0.00077514696
A19: =[1]Gen!A20 -> 43748 | B19: 85 | C19: 5 | D19: 74 | F19: 66764.3 | G19: =(F19-F18)*4.4 -> 116.16 | H19: ='[1]Summery Report'!C14 -> 0.325 | I19: =SUM(F19/H19) -> 205428.62 | J19: =SUM(G19/I19) -> 0.0005654519
A20: =[1]Gen!A21 -> 43749 | B20: 85 | C20: 5 | D20: 72 | F20: 66789.5 | G20: =(F20-F19)*4.4 -> 110.88 | H20: ='[1]Summery Report'!C15 -> 0.455 | I20: =SUM(F20/H20) -> 146790.11 | J20: =SUM(G20/I20) -> 0.00075536424
A21: =[1]Gen!A22 -> 43750 | B21: 85 | C21: 5 | D21: 68 | F21: 66814.1 | G21: =(F21-F20)*4.4 -> 108.24 | H21: ='[1]Summery Report'!C16 -> 0.416 | I21: =SUM(F21/H21) -> 160610.82 | J21: =SUM(G21/I21) -> 0.00067392721
... A40: =[1]Gen!A41 -> 43769 | B40: 75 | C40: 85 | D40: 85 | F40: 67286.4 | G40: =(F40-F39)*4.4 -> 119.68 | H40: ='[1]Summery Report'!C35 -> 0 | I40: =SUM(F40/H40) -> #DIV/0! | J40: =SUM(G40/I40) -> #DIV/0!
A41: =[1]Gen!A42 -> #REF! | G41: =(F41-F40)*4.4 -> -296060.16 | H41: ='[1]Summery Report'!C36 -> 0 | I41: =SUM(F41/H41) -> #DIV/0! | J41: =SUM(G41/I41) -> #DIV/0!
C42: TOTAL USAGE | E42: =SUM(E10:E40) -> 0 | F42: =SUM(F10:F40) -> 2074144.6 | G42: =SUM(G10:G40) -> 3453.12 | J42: =SUM(G42/I42) -> #DIV/0!
B68: GAS TANK 1 READINGS | H68: GAS TANK 2 READINGS | L68: GAS TANK 3 READINGS

Sheet LPG_Graph
A1: Date | B1: Usage KG | C1: Occ %
A2: =SUM([1]Gen!A11) -> 43739 | B2: ='[1]Lpg (2)'!G10 -> 197.56 | C2: =SUM([1]Gen!B11) -> 0.623
A3: =SUM([1]Gen!A12) -> 43740 | B3: ='[1]Lpg (2)'!G11 -> 131.956 | C3: =SUM([1]Gen!B12) -> 0.779
A4: =SUM([1]Gen!A13) -> 43741 | B4: ='[1]Lpg (2)'!G12 -> 117.48 | C4: =SUM([1]Gen!B13) -> 0.532
A5: =SUM([1]Gen!A14) -> 43742 | B5: ='[1]Lpg (2)'!G13 -> 102.96 | C5: =SUM([1]Gen!B14) -> 0.61
A6: =SUM([1]Gen!A15) -> 43743 | B6: ='[1]Lpg (2)'!G14 -> 101.816 | C6: =SUM([1]Gen!B15) -> 0.688
A7: =SUM([1]Gen!A16) -> 43744 | B7: ='[1]Lpg (2)'!G15 -> 106.92 | C7: =SUM([1]Gen!B16) -> 0.532
A8: =SUM([1]Gen!A17) -> 43745 | B8: ='[1]Lpg (2)'!G16 -> 116.732 | C8: =SUM([1]Gen!B17) -> 0.753
A9: =SUM([1]Gen!A18) -> 43746 | B9: ='[1]Lpg (2)'!G17 -> 105.732 | C9: =SUM([1]Gen!B18) -> 0.156
A10: =SUM([1]Gen!A19) -> 43747 | B10: ='[1]Lpg (2)'!G18 -> 114.4 | C10: =SUM([1]Gen!B19) -> 0.442
A11: =SUM([1]Gen!A20) -> 43748 | B11: ='[1]Lpg (2)'!G19 -> 102.08 | C11: =SUM([1]Gen!B20) -> 0.325
A12: =SUM([1]Gen!A21) -> 43749 | B12: ='[1]Lpg (2)'!G20 -> 105.292 | C12: =SUM([1]Gen!B21) -> 0.455
A13: =SUM([1]Gen!A22) -> 43750 | B13: ='[1]Lpg (2)'!G21 -> 114.664 | C13: =SUM([1]Gen!B22) -> 0.416
... A32: =SUM([1]Gen!A41) -> 43769 | B32: ='[1]Lpg (2)'!G40 -> 0 | C32: =SUM([1]Gen!B41) -> #REF!

Sheet Water-Meter
A1: Four Seasons Safari Lodge Serengeti OCT 2019- Water Report
C2: Main Meter | F2: KITCHEN | I2: Amani café | L2: Main SW POOL | O2: Laundry | S2: BORE HOLE NO.1 METER READING | V2: BORE HOLE NO.2 METER READING | Y2: BORE HOLE NO.3 METER READING | AB2: BORE HOLE NO.4 METER READING | AE2: BORE HOLE NO.5 METER READING | AH2: BORE HOLE NO.6 METER READING | AK2: RAIN WATER - METER READING | AN2: TOTAL WATER PRODUCTION
A3: DATE | C3: Open Bal | D3: Final | E3: consumption | F3: Open Bal | G3: Final | H3: consumption | I3: Open Bal | J3: Final | K3: consumption | L3: Open Bal | M3: Final | N3: consumption | O3: Open Bal | P3: Final | Q3: consumption | R3: Total consumption
S4: OPEN | T4: FINAL | U4: PROD. | V4: OPEN | W4: FINAL | X4: PROD. | Y4: OPEN | Z4: FINAL | AA4: PROD. | AB4: OPEN | AC4: FINAL | AD4: M3 | AE4: OPEN | AF4: FINAL | AG4: M3 | AH4: OPEN | AI4: FINAL | AJ4: M3 | AK4: OPEN | AL4: FINAL | AM4: M3
C5: =D4 -> 0 | D5: 212333 | E5: =D5-D4 -> 212333 | F5: =G4 -> 0 | G5: 36423 | H5: =G5-G4 -> 36423 | I5: =J4 -> 0 | J5: 7351 | K5: =J5-J4 -> 7351 | L5: =M4 -> 0 | M5: 10201 | N5: =M5-M4 -> 10201 | O5: =P4 -> 0 | P5: 18541 | Q5: =P5-P4 -> 18541 | S5: =T4 -> FINAL | T5: 45036 | U5: =V4 -> OPEN | V5: =W4 -> FINAL | W5: 62658 | Y5: =Z4 -> FINAL | Z5: 71806 | AB5: =AC4 -> FINAL | AC5: 11327 | AE5: =AF4 -> FINAL | AF5: 13704 | AH5: =AI4 -> FINAL | AI5: 22158 | AK5: =AL4 -> FINAL | AL5: 15154
A6: =[1]Gen!A11 -> 43739 | C6: =D5 -> 212333 | D6: 212463 | E6: =D6-D5 -> 130 | F6: =G5 -> 36423 | G6: 36434 | H6: =G6-G5 -> 11 | I6: =J5 -> 7351 | J6: 7353 | K6: =J6-J5 -> 2 | L6: =M5 -> 10201 | M6: 10227 | N6: =M6-M5 -> 26 | O6: =P5 -> 18541 | P6: 18547 | Q6: =P6-P5 -> 6 | S6: =T5 -> 45036 | T6: 45061 | U6: =T6-T5 -> 25 | V6: =W5 -> 62658 | W6: 62709 | X6: =W6-W5 -> 51 | Y6: =Z5 -> 71806 | Z6: 71856 | AA6: =Z6-Z5 -> 50 | AB6: =AC5 -> 11327 | AC6: 11327 | AD6: =AC6-AC5 -> 0 | AE6: =AF5 -> 13704 | AF6: 13717 | AG6: =AF6-AF5 -> 13 | AH6: =AI5 -> 22158 | AI6: 22179 | AJ6: =AI6-AI5 -> 21 | AK6: =AL5 -> 15154 | AL6: 15154 | AM6: =AL6-AL5 -> 0 | AN6: =AM6+AJ6+AG6+AD6+AA6+X6+U6 -> 160
A7: =[1]Gen!A12 -> 43740 | C7: =D6 -> 212463 | D7: 212591 | E7: =D7-D6 -> 128 | F7: =G6 -> 36434 | G7: 36454 | H7: =G7-G6 -> 20 | I7: =J6 -> 7353 | J7: 7357 | K7: =J7-J6 -> 4 | L7: =M6 -> 10227 | M7: 10240 | N7: =M7-M6 -> 13 | O7: =P6 -> 18547 | P7: 18554 | Q7: =P7-P6 -> 7 | S7: =T6 -> 45061 | T7: 45090 | U7: =T7-T6 -> 29 | V7: =W6 -> 62709 | W7: 62763 | X7: =W7-W6 -> 54 | Y7: =Z6 -> 71856 | Z7: 71908 | AA7: =Z7-Z6 -> 52 | AB7: =AC6 -> 11327 | AC7: 11327 | AD7: =AC7-AC6 -> 0 | AE7: =AF6 -> 13717 | AF7: 13730 | AG7: =AF7-AF6 -> 13 | AH7: =AI6 -> 22179 | AI7: 22199 | AJ7: =AI7-AI6 -> 20 | AK7: =AL6 -> 15154 | AL7: 15154 | AM7: =AL7-AL6 -> 0 | AN7: =AM7+AJ7+AG7+AD7+AA7+X7+U7 -> 168
A8: =[1]Gen!A13 -> 43741 | C8: =D7 -> 212591 | D8: 212711 | E8: =D8-D7 -> 120 | F8: =G7 -> 36454 | G8: 36472 | H8: =G8-G7 -> 18 | I8: =J7 -> 7357 | J8: 7360 | K8: =J8-J7 -> 3 | L8: =M7 -> 10240 | M8: 10255 | N8: =M8-M7 -> 15 | O8: =P7 -> 18554 | P8: 18563 | Q8: =P8-P7 -> 9 | S8: =T7 -> 45090 | T8: 45120 | U8: =T8-T7 -> 30 | V8: =W7 -> 62763 | W8: 62815 | X8: =W8-W7 -> 52 | Y8: =Z7 -> 71908 | Z8: 71959 | AA8: =Z8-Z7 -> 51 | AB8: =AC7 -> 11327 | AC8: 11327 | AD8: =AC8-AC7 -> 0 | AE8: =AF7 -> 13730 | AF8: 13742 | AG8: =AF8-AF7 -> 12 | AH8: =AI7 -> 22199 | AI8: 22221 | AJ8: =AI8-AI7 -> 22 | AK8: =AL7 -> 15154 | AL8: 15154 | AM8: =AL8-AL7 -> 0 | AN8: =AM8+AJ8+AG8+AD8+AA8+X8+U8 -> 167
A9: =[1]Gen!A14 -> 43742 | C9: =D8 -> 212711 | D9: 212831 | E9: =D9-D8 -> 120 | F9: =G8 -> 36472 | G9: 36485 | H9: =G9-G8 -> 13 | I9: =J8 -> 7360 | J9: 7364 | K9: =J9-J8 -> 4 | L9: =M8 -> 10255 | M9: 10270 | N9: =M9-M8 -> 15 | O9: =P8 -> 18563 | P9: 18575 | Q9: =P9-P8 -> 12 | S9: =T8 -> 45120 | T9: 45161 | U9: =T9-T8 -> 41 | V9: =W8 -> 62815 | W9: 62863 | X9: =W9-W8 -> 48 | Y9: =Z8 -> 71959 | Z9: 72021 | AA9: =Z9-Z8 -> 62 | AB9: =AC8 -> 11327 | AC9: 11342 | AD9: =AC9-AC8 -> 15 | AE9: =AF8 -> 13742 | AF9: 13752 | AG9: =AF9-AF8 -> 10 | AH9: =AI8 -> 22221 | AI9: 22239 | AJ9: =AI9-AI8 -> 18 | AK9: =AL8 -> 15154 | AL9: 15154 | AM9: =AL9-AL8 -> 0 | AN9: =AM9+AJ9+AG9+AD9+AA9+X9+U9 -> 194
A10: =[1]Gen!A15 -> 43743 | C10: =D9 -> 212831 | D10: 212945 | E10: =D10-D9 -> 114 | F10: =G9 -> 36485 | G10: 36500 | H10: =G10-G9 -> 15 | I10: =J9 -> 7364 | J10: 7367 | K10: =J10-J9 -> 3 | L10: =M9 -> 10270 | M10: 10285 | N10: =M10-M9 -> 15 | O10: =P9 -> 18575 | P10: 18586 | Q10: =P10-P9 -> 11 | S10: =T9 -> 45161 | T10: 45190 | U10: =T10-T9 -> 29 | V10: =W9 -> 62863 | W10: 62913 | X10: =W10-W9 -> 50 | Y10: =Z9 -> 72021 | Z10: 72084 | AA10: =Z10-Z9 -> 63 | AB10: =AC9 -> 11342 | AC10: 11351 | AD10: =AC10-AC9 -> 9 | AE10: =AF9 -> 13752 | AF10: 13763 | AG10: =AF10-AF9 -> 11 | AH10: =AI9 -> 22239 | AI10: 22259 | AJ10: =AI10-AI9 -> 20 | AK10: =AL9 -> 15154 | AL10: 15154 | AM10: =AL10-AL9 -> 0 | AN10: =AM10+AJ10+AG10+AD10+AA10+X10+U10 -> 182
A11: =[1]Gen!A16 -> 43744 | C11: =D10 -> 212945 | D11: 213071 | E11: =D11-D10 -> 126 | F11: =G10 -> 36500 | G11: 36516 | H11: =G11-G10 -> 16 | I11: =J10 -> 7367 | J11: 7369 | K11: =J11-J10 -> 2 | M11: 10295 | N11: =M11-M10 -> 10 | O11: =P10 -> 18586 | P11: 18593 | Q11: =P11-P10 -> 7 | S11: =T10 -> 45190 | T11: 45220 | U11: =T11-T10 -> 30 | V11: =W10 -> 62913 | W11: 62964 | X11: =W11-W10 -> 51 | Y11: =Z10 -> 72084 | Z11: 72152 | AA11: =Z11-Z10 -> 68 | AB11: =AC10 -> 11351 | AC11: 11359 | AD11: =AC11-AC10 -> 8 | AE11: =AF10 -> 13763 | AF11: 13774 | AG11: =AF11-AF10 -> 11 | AH11: =AI10 -> 22259 | AI11: 22280 | AJ11: =AI11-AI10 -> 21 | AK11: =AL10 -> 15154 | AL11: 15154 | AM11: =AL11-AL10 -> 0 | AN11: =AM11+AJ11+AG11+AD11+AA11+X11+U11 -> 189
A12: =[1]Gen!A17 -> 43745 | C12: =D11 -> 213071 | D12: 213187 | E12: =D12-D11 -> 116 | F12: =G11 -> 36516 | G12: 36529 | H12: =G12-G11 -> 13 | I12: =J11 -> 7369 | J12: 7372 | K12: =J12-J11 -> 3 | L12: =M11 -> 10295 | M12: 10320 | N12: =M12-M11 -> 25 | O12: =P11 -> 18593 | P12: 18606 | Q12: =P12-P11 -> 13 | S12: =T11 -> 45220 | T12: 45250 | U12: =T12-T11 -> 30 | V12: =W11 -> 62964 | W12: 63013 | X12: =W12-W11 -> 49 | Y12: =Z11 -> 72152 | Z12: 72208 | AA12: =Z12-Z11 -> 56 | AB12: =AC11 -> 11359 | AC12: 11367 | AD12: =AC12-AC11 -> 8 | AE12: =AF11 -> 13774 | AF12: 13780 | AG12: =AF12-AF11 -> 6 | AH12: =AI11 -> 22280 | AI12: 22299 | AJ12: =AI12-AI11 -> 19 | AK12: =AL11 -> 15154 | AL12: 15154 | AM12: =AL12-AL11 -> 0 | AN12: =AM12+AJ12+AG12+AD12+AA12+X12+U12 -> 168
A13: =[1]Gen!A18 -> 43746 | C13: =D12 -> 213187 | D13: 213307 | E13: =D13-D12 -> 120 | F13: =G12 -> 36529 | G13: 36543 | H13: =G13-G12 -> 14 | I13: =J12 -> 7372 | J13: 7374 | K13: =J13-J12 -> 2 | L13: =M12 -> 10320 | M13: 10342 | N13: =M13-M12 -> 22 | O13: =P12 -> 18606 | P13: 18616 | Q13: =P13-P12 -> 10 | S13: =T12 -> 45250 | T13: 45282 | U13: =T13-T12 -> 32 | V13: =W12 -> 63013 | W13: 63063 | X13: =W13-W12 -> 50 | Y13: =Z12 -> 72208 | Z13: 72266 | AA13: =Z13-Z12 -> 58 | AB13: =AC12 -> 11367 | AC13: 11375 | AD13: =AC13-AC12 -> 8 | AE13: =AF12 -> 13780 | AF13: 13794 | AG13: =AF13-AF12 -> 14 | AH13: =AI12 -> 22299 | AI13: 22319 | AJ13: =AI13-AI12 -> 20 | AK13: =AL12 -> 15154 | AL13: 15154 | AM13: =AL13-AL12 -> 0 | AN13: =AM13+AJ13+AG13+AD13+AA13+X13+U13 -> 182
A14: =[1]Gen!A19 -> 43747 | C14: =D13 -> 213307 | D14: 213414 | E14: =D14-D13 -> 107 | F14: =G13 -> 36543 | G14: 36560 | H14: =G14-G13 -> 17 | I14: =J13 -> 7374 | J14: 7377 | K14: =J14-J13 -> 3 | L14: =M13 -> 10342 | M14: 10360 | N14: =M14-M13 -> 18 | O14: =P13 -> 18616 | P14: 18623 | Q14: =P14-P13 -> 7 | S14: =T13 -> 45282 | T14: 45313 | U14: =T14-T13 -> 31 | V14: =W13 -> 63063 | W14: 63112 | X14: =W14-W13 -> 49 | Y14: =Z13 -> 72266 | Z14: 72324 | AA14: =Z14-Z13 -> 58 | AB14: =AC13 -> 11375 | AC14: 11383 | AD14: =AC14-AC13 -> 8 | AE14: =AF13 -> 13794 | AF14: 13804 | AG14: =AF14-AF13 -> 10 | AH14: =AI13 -> 22319 | AI14: 22339 | AJ14: =AI14-AI13 -> 20 | AK14: =AL13 -> 15154 | AL14: 15154 | AM14: =AL14-AL13 -> 0 | AN14: =AM14+AJ14+AG14+AD14+AA14+X14+U14 -> 176
A15: =[1]Gen!A20 -> 43748 | C15: =D14 -> 213414 | D15: 213537 | E15: =D15-D14 -> 123 | F15: =G14 -> 36560 | G15: 36574 | H15: =G15-G14 -> 14 | I15: =J14 -> 7377 | J15: 7381 | K15: =J15-J14 -> 4 | L15: =M14 -> 10360 | M15: 10380 | N15: =M15-M14 -> 20 | O15: =P14 -> 18623 | P15: 18634 | Q15: =P15-P14 -> 11 | S15: =T14 -> 45313 | T15: 45343 | U15: =T15-T14 -> 30 | V15: =W14 -> 63112 | W15: 63162 | X15: =W15-W14 -> 50 | Y15: =Z14 -> 72324 | Z15: 72380 | AA15: =Z15-Z14 -> 56 | AB15: =AC14 -> 11383 | AC15: 11391 | AD15: =AC15-AC14 -> 8 | AE15: =AF14 -> 13804 | AF15: 13804 | AG15: =AF15-AF14 -> 0 | AH15: =AI14 -> 22339 | AI15: 22358 | AJ15: =AI15-AI14 -> 19 | AK15: =AL14 -> 15154 | AL15: 15154 | AM15: =AL15-AL14 -> 0 | AN15: =AM15+AJ15+AG15+AD15+AA15+X15+U15 -> 163
A16: =[1]Gen!A21 -> 43749 | C16: =D15 -> 213537 | D16: 213649 | E16: =D16-D15 -> 112 | F16: =G15 -> 36574 | G16: 36591 | H16: =G16-G15 -> 17 | I16: =J15 -> 7381 | J16: 7385 | K16: =J16-J15 -> 4 | L16: =M15 -> 10380 | M16: 10395 | N16: =M16-M15 -> 15 | O16: =P15 -> 18634 | P16: 18643 | Q16: =P16-P15 -> 9 | S16: =T15 -> 45343 | T16: 45372 | U16: =T16-T15 -> 29 | V16: =W15 -> 63162 | W16: 63214 | X16: =W16-W15 -> 52 | Y16: =Z15 -> 72380 | Z16: 72443 | AA16: =Z16-Z15 -> 63 | AB16: =AC15 -> 11391 | AC16: 11399 | AD16: =AC16-AC15 -> 8 | AE16: =AF15 -> 13804 | AF16: 13804 | AG16: =AF16-AF15 -> 0 | AH16: =AI15 -> 22358 | AI16: 22381 | AJ16: =AI16-AI15 -> 23 | AK16: =AL15 -> 15154 | AL16: 15154 | AM16: =AL16-AL15 -> 0 | AN16: =AM16+AJ16+AG16+AD16+AA16+X16+U16 -> 175
A17: =[1]Gen!A22 -> 43750 | C17: =D16 -> 213649 | D17: 213777 | E17: =D17-D16 -> 128 | F17: =G16 -> 36591 | G17: 36605 | H17: =G17-G16 -> 14 | I17: =J16 -> 7385 | J17: 7388 | K17: =J17-J16 -> 3 | L17: =M16 -> 10395 | M17: 10424 | N17: =M17-M16 -> 29 | O17: =P16 -> 18643 | P17: 18652 | Q17: =P17-P16 -> 9 | S17: =T16 -> 45372 | T17: 45402 | U17: =T17-T16 -> 30 | V17: =W16 -> 63214 | W17: 63265 | X17: =W17-W16 -> 51 | Y17: =Z16 -> 72443 | Z17: 72500 | AA17: =Z17-Z16 -> 57 | AB17: =AC16 -> 11399 | AC17: 11407 | AD17: =AC17-AC16 -> 8 | AE17: =AF16 -> 13804 | AF17: 13804 | AG17: =AF17-AF16 -> 0 | AH17: =AI16 -> 22381 | AI17: 22400 | AJ17: =AI17-AI16 -> 19 | AK17: =AL16 -> 15154 | AL17: 15154 | AM17: =AL17-AL16 -> 0 | AN17: =AM17+AJ17+AG17+AD17+AA17+X17+U17 -> 165
A18: =[1]Gen!A23 -> 43751 | C18: =D17 -> 213777 | D18: 213891 | E18: =D18-D17 -> 114 | F18: =G17 -> 36605 | G18: 36619 | H18: =G18-G17 -> 14 | I18: =J17 -> 7388 | J18: 7390 | K18: =J18-J17 -> 2 | L18: =M17 -> 10424 | M18: 10447 | N18: =M18-M17 -> 23 | O18: =P17 -> 18652 | P18: 18661 | Q18: =P18-P17 -> 9 | S18: =T17 -> 45402 | T18: 45432 | U18: =T18-T17 -> 30 | V18: =W17 -> 63265 | W18: 63309 | X18: =W18-W17 -> 44 | Y18: =Z17 -> 72500 | Z18: 72552 | AA18: =Z18-Z17 -> 52 | AB18: =AC17 -> 11407 | AC18: 11413 | AD18: =AC18-AC17 -> 6 | AE18: =AF17 -> 13804 | AF18: 13816 | AG18: =AF18-AF17 -> 12 | AH18: =AI17 -> 22400 | AI18: 22418 | AJ18: =AI18-AI17 -> 18 | AK18: =AL17 -> 15154 | AL18: 15154 | AM18: =AL18-AL17 -> 0 | AN18: =AM18+AJ18+AG18+AD18+AA18+X18+U18 -> 162
A19: =[1]Gen!A24 -> 43752 | C19: =D18 -> 213891 | D19: 214010 | E19: =D19-D18 -> 119 | F19: =G18 -> 36619 | G19: 36632 | H19: =G19-G18 -> 13 | I19: =J18 -> 7390 | J19: 7393 | K19: =J19-J18 -> 3 | L19: =M18 -> 10447 | M19: 10462 | N19: =M19-M18 -> 15 | O19: =P18 -> 18661 | P19: 18672 | Q19: =P19-P18 -> 11 | S19: =T18 -> 45432 | T19: 45464 | U19: =T19-T18 -> 32 | V19: =W18 -> 63309 | W19: 63358 | X19: =W19-W18 -> 49 | Y19: =Z18 -> 72552 | Z19: 72607 | AA19: =Z19-Z18 -> 55 | AB19: =AC18 -> 11413 | AC19: 11421 | AD19: =AC19-AC18 -> 8 | AE19: =AF18 -> 13816 | AF19: 13833 | AG19: =AF19-AF18 -> 17 | AH19: =AI18 -> 22418 | AI19: 22438 | AJ19: =AI19-AI18 -> 20 | AK19: =AL18 -> 15154 | AL19: 15154 | AM19: =AL19-AL18 -> 0 | AN19: =AM19+AJ19+AG19+AD19+AA19+X19+U19 -> 181
A20: =[1]Gen!A25 -> 43753 | C20: =D19 -> 214010 | D20: 214138 | E20: =D20-D19 -> 128 | F20: =G19 -> 36632 | G20: 36651 | H20: =G20-G19 -> 19 | I20: =J19 -> 7393 | J20: 7396 | K20: =J20-J19 -> 3 | L20: =M19 -> 10462 | M20: 10481 | N20: =M20-M19 -> 19 | O20: =P19 -> 18672 | P20: 18680 | Q20: =P20-P19 -> 8 | S20: =T19 -> 45464 | T20: 45493 | U20: =T20-T19 -> 29 | V20: =W19 -> 63358 | W20: 63407 | X20: =W20-W19 -> 49 | Y20: =Z19 -> 72607 | Z20: 72663 | AA20: =Z20-Z19 -> 56 | AB20: =AC19 -> 11421 | AC20: 11428 | AD20: =AC20-AC19 -> 7 | AE20: =AF19 -> 13833 | AF20: 13850 | AG20: =AF20-AF19 -> 17 | AH20: =AI19 -> 22438 | AI20: 22457 | AJ20: =AI20-AI19 -> 19 | AK20: =AL19 -> 15154 | AL20: 15154 | AM20: =AL20-AL19 -> 0 | AN20: =AM20+AJ20+AG20+AD20+AA20+X20+U20 -> 177
A21: =[1]Gen!A26 -> 43754 | C21: =D20 -> 214138 | D21: 214265 | E21: =D21-D20 -> 127 | F21: =G20 -> 36651 | G21: 36668 | H21: =G21-G20 -> 17 | I21: =J20 -> 7396 | J21: 7398 | K21: =J21-J20 -> 2 | L21: =M20 -> 10481 | M21: 10493 | N21: =M21-M20 -> 12 | O21: =P20 -> 18680 | P21: 18689 | Q21: =P21-P20 -> 9 | S21: =T20 -> 45493 | T21: 45524 | U21: =T21-T20 -> 31 | V21: =W20 -> 63407 | W21: 63457 | X21: =W21-W20 -> 50 | Y21: =Z20 -> 72663 | Z21: 72718 | AA21: =Z21-Z20 -> 55 | AB21: =AC20 -> 11428 | AC21: 11436 | AD21: =AC21-AC20 -> 8 | AE21: =AF20 -> 13850 | AF21: 13865 | AG21: =AF21-AF20 -> 15 | AH21: =AI20 -> 22457 | AI21: 22477 | AJ21: =AI21-AI20 -> 20 | AK21: =AL20 -> 15154 | AL21: 15154 | AM21: =AL21-AL20 -> 0 | AN21: =AM21+AJ21+AG21+AD21+AA21+X21+U21 -> 179
A22: =[1]Gen!A27 -> 43755 | C22: =D21 -> 214265 | D22: 214387 | E22: =D22-D21 -> 122 | F22: =G21 -> 36668 | G22: 36681 | H22: =G22-G21 -> 13 | I22: =J21 -> 7398 | J22: 7402 | K22: =J22-J21 -> 4 | L22: =M21 -> 10493 | M22: 10510 | N22: =M22-M21 -> 17 | O22: =P21 -> 18689 | P22: 18701 | Q22: =P22-P21 -> 12 | S22: =T21 -> 45524 | T22: 45553 | U22: =T22-T21 -> 29 | V22: =W21 -> 63457 | W22: 63507 | X22: =W22-W21 -> 50 | Y22: =Z21 -> 72718 | Z22: 72773 | AA22: =Z22-Z21 -> 55 | AB22: =AC21 -> 11436 | AC22: 11441 | AD22: =AC22-AC21 -> 5 | AE22: =AF21 -> 13865 | AF22: 13882 | AG22: =AF22-AF21 -> 17 | AH22: =AI21 -> 22477 | AI22: 22496 | AJ22: =AI22-AI21 -> 19 | AK22: =AL21 -> 15154 | AL22: 15154 | AM22: =AL22-AL21 -> 0 | AN22: =AM22+AJ22+AG22+AD22+AA22+X22+U22 -> 175
A23: =[1]Gen!A28 -> 43756 | C23: =D22 -> 214387 | D23: 214492 | E23: =D23-D22 -> 105 | F23: =G22 -> 36681 | G23: 36696 | H23: =G23-G22 -> 15 | I23: =J22 -> 7402 | J23: 7404 | K23: =J23-J22 -> 2 | L23: =M22 -> 10510 | M23: 10520 | N23: =M23-M22 -> 10 | O23: =P22 -> 18701 | P23: 18712 | Q23: =P23-P22 -> 11 | S23: =T22 -> 45553 | T23: 45583 | U23: =T23-T22 -> 30 | V23: =W22 -> 63507 | W23: 63559 | X23: =W23-W22 -> 52 | Y23: =Z22 -> 72773 | Z23: 72829 | AA23: =Z23-Z22 -> 56 | AB23: =AC22 -> 11441 | AC23: 11449 | AD23: =AC23-AC22 -> 8 | AE23: =AF22 -> 13882 | AF23: 13897 | AG23: =AF23-AF22 -> 15 | AH23: =AI22 -> 22496 | AI23: 22516 | AJ23: =AI23-AI22 -> 20 | AK23: =AL22 -> 15154 | AL23: 15154 | AM23: =AL23-AL22 -> 0 | AN23: =AM23+AJ23+AG23+AD23+AA23+X23+U23 -> 181
... A31: =[1]Gen!A36 -> 43764 | C31: =D30 -> 215249 | D31: 215379 | E31: =D31-D30 -> 130 | F31: =G30 -> 36792 | G31: 36809 | H31: =G31-G30 -> 17 | I31: =J30 -> 7426 | J31: 7428 | K31: =J31-J30 -> 2 | L31: =M30 -> 10640 | M31: 10646 | N31: =M31-M30 -> 6 | O31: =P30 -> 18773 | P31: 18782 | Q31: =P31-P30 -> 9 | S31: =T30 -> 45792 | T31: 45822 | U31: =T31-T30 -> 30 | V31: =W30 -> 63914 | W31: 63965 | X31: =W31-W30 -> 51 | Y31: =Z30 -> 73214 | Z31: 73269 | AA31: =Z31-Z30 -> 55 | AB31: =AC30 -> 11496 | AC31: 11503 | AD31: =AC31-AC30 -> 7 | AE31: =AF30 -> 14000 | AF31: 14015 | AG31: =AF31-AF30 -> 15 | AH31: =AI30 -> 22652 | AI31: 22671 | AJ31: =AI31-AI30 -> 19 | AK31: =AL30 -> 15154 | AL31: 15154 | AM31: =AL31-AL30 -> 0 | AN31: =AM31+AJ31+AG31+AD31+AA31+X31+U31 -> 177
A32: =[1]Gen!A37 -> 43765 | B32: 10/27//2009 | C32: =D31 -> 215379 | D32: 215493 | E32: =D32-D31 -> 114 | F32: =G31 -> 36809 | G32: 36825 | H32: =G32-G31 -> 16 | I32: =J31 -> 7428 | J32: 7432 | K32: =J32-J31 -> 4 | L32: =M31 -> 10646 | M32: 10675 | N32: =M32-M31 -> 29 | O32: =P31 -> 18782 | P32: 18790 | Q32: =P32-P31 -> 8 | S32: =T31 -> 45822 | T32: 45851 | U32: =T32-T31 -> 29 | V32: =W31 -> 63965 | W32: 64015 | X32: =W32-W31 -> 50 | Y32: =Z31 -> 73269 | Z32: 73324 | AA32: =Z32-Z31 -> 55 | AB32: =AC31 -> 11503 | AC32: 11509 | AD32: =AC32-AC31 -> 6 | AE32: =AF31 -> 14015 | AF32: 14029 | AG32: =AF32-AF31 -> 14 | AH32: =AI31 -> 22671 | AI32: 22690 | AJ32: =AI32-AI31 -> 19 | AK32: =AL31 -> 15154 | AL32: 15154 | AM32: =AL32-AL31 -> 0 | AN32: =AM32+AJ32+AG32+AD32+AA32+X32+U32 -> 173
A33: =[1]Gen!A38 -> 43766 | C33: =D32 -> 215493 | D33: 215604 | E33: =D33-D32 -> 111 | F33: =G32 -> 36825 | G33: 36838 | H33: =G33-G32 -> 13 | I33: =J32 -> 7432 | J33: 7435 | K33: =J33-J32 -> 3 | L33: =M32 -> 10675 | M33: 10688 | N33: =M33-M32 -> 13 | O33: =P32 -> 18790 | P33: 18800 | Q33: =P33-P32 -> 10 | S33: =T32 -> 45851 | T33: 45882 | U33: =T33-T32 -> 31 | V33: =W32 -> 64015 | W33: 64065 | X33: =W33-W32 -> 50 | Y33: =Z32 -> 73324 | Z33: 73379 | AA33: =Z33-Z32 -> 55 | AB33: =AC32 -> 11509 | AC33: 11515 | AD33: =AC33-AC32 -> 6 | AE33: =AF32 -> 14029 | AF33: 14043 | AG33: =AF33-AF32 -> 14 | AH33: =AI32 -> 22690 | AI33: 22709 | AJ33: =AI33-AI32 -> 19 | AK33: =AL32 -> 15154 | AL33: 15154 | AM33: =AL33-AL32 -> 0 | AN33: =AM33+AJ33+AG33+AD33+AA33+X33+U33 -> 175
A34: =[1]Gen!A39 -> 43767 | C34: =D33 -> 215604 | D34: 215704 | E34: =D34-D33 -> 100 | F34: =G33 -> 36838 | G34: 36853 | H34: =G34-G33 -> 15 | I34: =J33 -> 7435 | J34: 7438 | K34: =J34-J33 -> 3 | L34: =M33 -> 10688 | M34: 10688 | N34: =M34-M33 -> 0 | O34: =P33 -> 18800 | P34: 18811 | Q34: =P34-P33 -> 11 | S34: =T33 -> 45882 | T34: 45911 | U34: =T34-T33 -> 29 | V34: =W33 -> 64065 | W34: 64117 | X34: =W34-W33 -> 52 | Y34: =Z33 -> 73379 | Z34: 73435 | AA34: =Z34-Z33 -> 56 | AB34: =AC33 -> 11515 | AC34: 11523 | AD34: =AC34-AC33 -> 8 | AE34: =AF33 -> 14043 | AF34: 14057 | AG34: =AF34-AF33 -> 14 | AH34: =AI33 -> 22709 | AI34: 22729 | AJ34: =AI34-AI33 -> 20 | AK34: =AL33 -> 15154 | AL34: 15154 | AM34: =AL34-AL33 -> 0 | AN34: =AM34+AJ34+AG34+AD34+AA34+X34+U34 -> 179
A35: =[1]Gen!A40 -> 43768 | C35: =D34 -> 215704 | D35: 215803 | E35: =D35-D34 -> 99 | F35: =G34 -> 36853 | G35: 36869 | H35: =G35-G34 -> 16 | I35: =J34 -> 7438 | J35: 7441 | K35: =J35-J34 -> 3 | L35: =M34 -> 10688 | M35: 10688 | N35: =M35-M34 -> 0 | O35: =P34 -> 18811 | P35: 18819 | Q35: =P35-P34 -> 8 | S35: =T34 -> 45911 | T35: 45940 | U35: =T35-T34 -> 29 | V35: =W34 -> 64117 | W35: 64168 | X35: =W35-W34 -> 51 | Y35: =Z34 -> 73435 | Z35: 73491 | AA35: =Z35-Z34 -> 56 | AB35: =AC34 -> 11523 | AC35: 11531 | AD35: =AC35-AC34 -> 8 | AE35: =AF34 -> 14057 | AF35: 14071 | AG35: =AF35-AF34 -> 14 | AH35: =AI34 -> 22729 | AI35: 22748 | AJ35: =AI35-AI34 -> 19 | AK35: =AL34 -> 15154 | AL35: 15154 | AM35: =AL35-AL34 -> 0 | AN35: =AM35+AJ35+AG35+AD35+AA35+X35+U35 -> 177
A36: =[1]Gen!A41 -> 43769 | C36: =D35 -> 215803 | D36: 215914 | E36: =D36-D35 -> 111 | F36: =G35 -> 36869 | G36: 36884 | H36: =G36-G35 -> 15 | I36: =J35 -> 7441 | J36: 7444 | K36: =J36-J35 -> 3 | L36: =M35 -> 10688 | M36: 10700 | N36: =M36-M35 -> 12 | O36: =P35 -> 18819 | P36: 18829 | Q36: =P36-P35 -> 10 | S36: =T35 -> 45940 | T36: 45970 | U36: =T36-T35 -> 30 | V36: =W35 -> 64168 | W36: 64218 | X36: =W36-W35 -> 50 | Y36: =Z35 -> 73491 | Z36: 73536 | AA36: =Z36-Z35 -> 45 | AB36: =AC35 -> 11531 | AC36: 11537 | AD36: =AC36-AC35 -> 6 | AE36: =AF35 -> 14071 | AF36: 14086 | AG36: =AF36-AF35 -> 15 | AH36: =AI35 -> 22748 | AI36: 22768 | AJ36: =AI36-AI35 -> 20 | AK36: =AL35 -> 15154 | AL36: 15154 | AM36: =AL36-AL35 -> 0 | AN36: =AM36+AJ36+AG36+AD36+AA36+X36+U36 -> 166
C37: =D36 -> 215914 | E37: =D37-D36 -> -215914 | F37: =G36 -> 36884 | H37: =G37-G36 -> -36884 | I37: =J36 -> 7444 | K37: =J37-J36 -> -7444 | L37: =M36 -> 10700 | N37: =M37-M36 -> -10700 | O37: =P36 -> 18829 | Q37: =P37-P36 -> -18829 | S37: =T36 -> 45970 | U37: =T37-T36 -> -45970 | V37: =W36 -> 64218 | Y37: =Z36 -> 73536 | AA37: =Z37-Z36 -> -73536 | AB37: =AC36 -> 11537 | AD37: =AC37-AC36 -> -11537 | AE37: =AF36 -> 14086 | AG37: =AF37-AF36 -> -14086 | AH37: =AI36 -> 22768 | AJ37: =AI37-AI36 -> -22768 | AK37: =AL36 -> 15154 | AM37: =AL37-AL36 -> -15154 | AN37: =AM37+AJ37+AG37+AD37+AA37+X37+U37 -> -183051
C38: TOTAL USAGE | E38: =SUM(E6:E36) -> 3581 | F38: KL | H38: =SUM(H6:H37) -> -36423 | K38: =SUM(K6:K37) -> -7351 | N38: =M38-M37 -> 0 | Q38: =P38-O38 -> 0 | R38: =E38 -> 3581 | U38: =SUM(U6:U37) -> -45036 | AN38: =U38+X38+AA38+AD38+AG38+AJ38+AM38 -> -45036
C42: WATER TANK LEVEL
C43: RAW WATER TANK NO.1 | E43: RAW WATER TANK NO.2 | G43: TREATED WATER TANK | I43: TREATED -HILL TANK | K43: TOTAL WATER AVAILABLE
C44: CAPACITY 217 m³ | E44: CAPACITY 92 m³ | G44: CAPACITY 146 m³ | I44: CAPACITY 213 m³
C45: cm | D45: m³ | E45: cm | F45: m³ | H45: m³ | I45: cm | J45: m³ | K45: m³
A46: =[1]Gen!A11 -> 43739 | C46: 275 | D46: =C46*217/300 -> 198.91667 | E46: 230 | F46: =E46*92/305 -> 69.377049 | G46: 200 | H46: =G46*146/383 -> 76.240209 | I46: 270 | J46: =I46*213/308 -> 186.72078 | K46: =D46+F46+H46+J46 -> 531.2547
A47: =[1]Gen!A12 -> 43740 | C47: 240 | D47: =C47*217/300 -> 173.6 | E47: 205 | F47: =E47*92/305 -> 61.836066 | G47: 270 | H47: =G47*146/383 -> 102.92428 | I47: 285 | J47: =I47*213/308 -> 197.09416 | K47: =D47+F47+H47+J47 -> 535.4545
A48: =[1]Gen!A13 -> 43741 | C48: 200 | D48: =C48*217/300 -> 144.66667 | E48: 160 | F48: =E48*92/305 -> 48.262295 | G48: 250 | H48: =G48*146/383 -> 95.300261 | I48: 280 | J48: =I48*213/308 -> 193.63636 | K48: =D48+F48+H48+J48 -> 481.86559
A49: =[1]Gen!A14 -> 43742 | C49: 150 | D49: =C49*217/300 -> 108.5 | E49: 120 | F49: =E49*92/305 -> 36.196721 | G49: 250 | H49: =G49*146/383 -> 95.300261 | I49: 285 | J49: =I49*213/308 -> 197.09416 | K49: =D49+F49+H49+J49 -> 437.09114
A50: =[1]Gen!A15 -> 43743 | C50: 175 | D50: =C50*217/300 -> 126.58333 | E50: 135 | F50: =E50*92/305 -> 40.721311 | G50: 235 | H50: =G50*146/383 -> 89.582245 | I50: 290 | J50: =I50*213/308 -> 200.55195 | K50: =D50+F50+H50+J50 -> 457.43884
A51: =[1]Gen!A16 -> 43744 | C51: 160 | D51: =C51*217/300 -> 115.73333 | E51: 125 | F51: =E51*92/305 -> 37.704918 | G51: 235 | H51: =G51*146/383 -> 89.582245 | I51: 285 | J51: =I51*213/308 -> 197.09416 | K51: =D51+F51+H51+J51 -> 440.11465
A52: =[1]Gen!A17 -> 43745 | C52: 150 | D52: =C52*217/300 -> 108.5 | E52: 115 | F52: =E52*92/305 -> 34.688525 | G52: 235 | H52: =G52*146/383 -> 89.582245 | I52: 280 | J52: =I52*213/308 -> 193.63636 | K52: =D52+F52+H52+J52 -> 426.40713
A53: =[1]Gen!A18 -> 43746 | C53: 200 | D53: =C53*217/300 -> 144.66667 | E53: 160 | F53: =E53*92/305 -> 48.262295 | G53: 50 | H53: =G53*146/383 -> 19.060052 | I53: 280 | J53: =I53*213/308 -> 193.63636 | K53: =D53+F53+H53+J53 -> 405.62538
A54: =[1]Gen!A19 -> 43747 | C54: 210 | D54: =C54*217/300 -> 151.9 | E54: 170 | F54: =E54*92/305 -> 51.278689 | G54: 140 | H54: =G54*146/383 -> 53.368146 | I54: 275 | J54: =I54*213/308 -> 190.17857 | K54: =D54+F54+H54+J54 -> 446.72541
A55: =[1]Gen!A20 -> 43748 | C55: 170 | D55: =C55*217/300 -> 122.96667 | E55: 120 | F55: =E55*92/305 -> 36.196721 | G55: 250 | H55: =G55*146/383 -> 95.300261 | I55: 285 | J55: =I55*213/308 -> 197.09416 | K55: =D55+F55+H55+J55 -> 451.5578
A56: =[1]Gen!A21 -> 43749 | C56: 135 | D56: =C56*217/300 -> 97.65 | E56: 100 | F56: =E56*92/305 -> 30.163934 | G56: 260 | H56: =G56*146/383 -> 99.112272 | I56: 290 | J56: =I56*213/308 -> 200.55195 | K56: =D56+F56+H56+J56 -> 427.47815
A57: =[1]Gen!A22 -> 43750 | C57: 250 | D57: =C57*217/300 -> 180.83333 | E57: 225 | F57: =E57*92/305 -> 67.868852 | G57: 5 | H57: =G57*146/383 -> 1.9060052 | I57: 210 | J57: =I57*213/308 -> 145.22727 | K57: =D57+F57+H57+J57 -> 395.83546
... A59: =[1]Gen!A24 -> 43752 | C59: 187 | D59: =C59*217/300 -> 135.26333 | E59: 152 | F59: =E59*92/305 -> 45.84918 | G59: 300 | H59: =G59*146/383 -> 114.36031 | I59: 283 | J59: =I59*213/308 -> 195.71104 | K59: =D59+F59+H59+J59 -> 491.18387
A60: =[1]Gen!A25 -> 43753 | C60: 200 | D60: =C60*217/300 -> 144.66667 | E60: 165 | F60: =E60*92/305 -> 49.770492 | G60: 300 | H60: =G60*146/383 -> 114.36031 | I60: 280 | J60: 197 | K60: =D60+F60+H60+J60 -> 505.79747
A61: =[1]Gen!A26 -> 43754 | C61: 170 | D61: =C61*217/300 -> 122.96667 | E61: 130 | F61: =E61*92/305 -> 39.213115 | G61: 300 | H61: =G61*146/383 -> 114.36031 | I61: 275 | J61: =I61*213/308 -> 190.17857 | K61: =D61+F61+H61+J61 -> 466.71867
A62: =[1]Gen!A27 -> 43755 | C62: 225 | D62: =C62*217/300 -> 162.75 | E62: 190 | F62: =E62*92/305 -> 57.311475 | G62: 190 | H62: =G62*146/383 -> 72.428198 | I62: 285 | J62: =I62*213/308 -> 197.09416 | K62: =D62+F62+H62+J62 -> 489.58383
A63: =[1]Gen!A28 -> 43756 | C63: 228 | D63: =C63*217/300 -> 164.92 | E63: 193 | F63: =E63*92/305 -> 58.216393 | G63: 240 | H63: =G63*146/383 -> 91.488251 | I63: 285 | J63: =I63*213/308 -> 197.09416 | K63: =D63+F63+H63+J63 -> 511.7188
A64: =[1]Gen!A29 -> 43757 | C64: 227 | D64: =C64*217/300 -> 164.19667 | E64: 192 | F64: =E64*92/305 -> 57.914754 | G64: 242 | H64: =G64*146/383 -> 92.250653 | I64: 290 | J64: =I64*213/308 -> 200.55195 | K64: =D64+F64+H64+J64 -> 514.91402
A65: =[1]Gen!A30 -> 43758 | C65: 225 | D65: =C65*217/300 -> 162.75 | E65: 190 | F65: =E65*92/305 -> 57.311475 | G65: 300 | H65: =G65*146/383 -> 114.36031 | I65: 290 | J65: =I65*213/308 -> 200.55195 | K65: =D65+F65+H65+J65 -> 534.97374
A66: =[1]Gen!A31 -> 43759 | C66: 196 | D66: =C66*217/300 -> 141.77333 | E66: 160 | F66: =E66*92/305 -> 48.262295 | G66: 300 | H66: =G66*146/383 -> 114.36031 | I66: 285 | J66: =I66*213/308 -> 197.09416 | K66: =D66+F66+H66+J66 -> 501.4901
A67: =[1]Gen!A32 -> 43760 | C67: 290 | D67: =C67*217/300 -> 209.76667 | E67: 265 | F67: =E67*92/305 -> 79.934426 | G67: 280 | H67: =G67*146/383 -> 106.73629 | I67: 290 | J67: =I67*213/308 -> 200.55195 | K67: =D67+F67+H67+J67 -> 596.98933
A68: =[1]Gen!A33 -> 43761 | C68: 205 | D68: =C68*217/300 -> 148.28333 | E68: 180 | F68: =E68*92/305 -> 54.295082 | G68: 295 | H68: =G68*146/383 -> 112.45431 | I68: 285 | J68: =I68*213/308 -> 197.09416 | K68: =D68+F68+H68+J68 -> 512.12688
A69: =[1]Gen!A34 -> 43762 | C69: 195 | D69: =C69*217/300 -> 141.05 | E69: 160 | F69: =E69*92/305 -> 48.262295 | G69: 300 | H69: =G69*146/383 -> 114.36031 | I69: 288 | J69: =I69*213/308 -> 199.16883 | K69: =D69+F69+H69+J69 -> 502.84144
A70: =[1]Gen!A35 -> 43763 | C70: 225 | D70: =C70*217/300 -> 162.75 | E70: 190 | F70: =E70*92/305 -> 57.311475 | G70: 265 | H70: =G70*146/383 -> 101.01828 | I70: 290 | J70: =I70*213/308 -> 200.55195 | K70: =D70+F70+H70+J70 -> 521.6317
A71: =[1]Gen!A36 -> 43764 | C71: 200 | D71: =C71*217/300 -> 144.66667 | E71: 165 | F71: =E71*92/305 -> 49.770492 | G71: 238 | H71: =G71*146/383 -> 90.725849 | I71: 285 | J71: =I71*213/308 -> 197.09416 | K71: =D71+F71+H71+J71 -> 482.25716
A72: =[1]Gen!A37 -> 43765 | C72: 172 | D72: =C72*217/300 -> 124.41333 | E72: 137 | F72: =E72*92/305 -> 41.32459 | G72: 240 | H72: =G72*146/383 -> 91.488251 | I72: 290 | J72: =I72*213/308 -> 200.55195 | K72: =D72+F72+H72+J72 -> 457.77812
... A76: =[1]Gen!A41 -> 43769 | C76: 110 | D76: =C76*217/300 -> 79.566667 | E76: 75 | F76: =E76*92/305 -> 22.622951 | G76: 300 | H76: =G76*146/383 -> 114.36031 | I76: 290 | J76: =I76*213/308 -> 200.55195 | K76: =D76+F76+H76+J76 -> 417.10188
A77: =[1]Gen!A42 -> #REF! | D77: =C77*217/300 -> 0 | F77: =E77*92/305 -> 0 | H77: =G77*146/383 -> 0 | J77: =I77*213/308 -> 0 | K77: =D77+F77+H77+J77 -> 0

Sheet Water_Graph 
A1: Date | B1: Usage | C1: Occ %
A2: =SUM([1]Gen!A11) -> 43739 | B2: =SUM('[1]Water-Meter'!R10) -> #REF! | C2: =SUM([1]Gen!B11) -> 0.623
A3: =SUM([1]Gen!A12) -> 43740 | B3: =SUM('[1]Water-Meter'!R11) -> #REF! | C3: =SUM([1]Gen!B12) -> 0.779
A4: =SUM([1]Gen!A13) -> 43741 | B4: =SUM('[1]Water-Meter'!R12) -> #REF! | C4: =SUM([1]Gen!B13) -> 0.532
A5: =SUM([1]Gen!A14) -> 43742 | B5: =SUM('[1]Water-Meter'!R13) -> #REF! | C5: =SUM([1]Gen!B14) -> 0.61
A6: =SUM([1]Gen!A15) -> 43743 | B6: =SUM('[1]Water-Meter'!R14) -> #REF! | C6: =SUM([1]Gen!B15) -> 0.688
A7: =SUM([1]Gen!A16) -> 43744 | B7: =SUM('[1]Water-Meter'!R15) -> #REF! | C7: =SUM([1]Gen!B16) -> 0.532
A8: =SUM([1]Gen!A17) -> 43745 | B8: =SUM('[1]Water-Meter'!R16) -> #REF! | C8: =SUM([1]Gen!B17) -> 0.753
A9: =SUM([1]Gen!A18) -> 43746 | B9: =SUM('[1]Water-Meter'!R17) -> #REF! | C9: =SUM([1]Gen!B18) -> 0.156
A10: =SUM([1]Gen!A19) -> 43747 | B10: =SUM('[1]Water-Meter'!R18) -> #REF! | C10: =SUM([1]Gen!B19) -> 0.442
A11: =SUM([1]Gen!A20) -> 43748 | B11: =SUM('[1]Water-Meter'!R19) -> #REF! | C11: =SUM([1]Gen!B20) -> 0.325
A12: =SUM([1]Gen!A21) -> 43749 | B12: =SUM('[1]Water-Meter'!R20) -> #REF! | C12: =SUM([1]Gen!B21) -> 0.455
A13: =SUM([1]Gen!A22) -> 43750 | B13: =SUM('[1]Water-Meter'!R21) -> #REF! | C13: =SUM([1]Gen!B22) -> 0.416
... A32: =SUM([1]Gen!A41) -> 43769 | B32: =SUM('[1]Water-Meter'!R40) -> #REF! | C32: =SUM([1]Gen!B41) -> #REF!

Sheet Sheet1
A2: Generator and Diseal Summry Report JANUARY 2016 | Q2: 2209.85 | R2: Diesel Cost | S2: Rate$ | T2: 1584
M3: % of Gas balance in Tank | P3: % of Dieasel balance in Tank | Q3: HLP Cost (TSH) | V3: Total Cost (TSH) | W3: Consumption Guest Occ% | AA3: Budget Cost Per Room occ
A4: Date | B4: Gen Set Hours Working | C4: Occ% | D4: Total OCC Room | E4: Guest Room Occ | F4: Total Kwh Generated | G4: Diseal consumed by Gen (Ltrs) | H4: Diseal consumed by Veichel (Ltrs) | I4: Total diseal consumed (Ltrs) | J4: Balance stock of Diseal (Ltrs) | K4: Water consumed | L4: Gas consumed (KG) | M4: 3 | N4: 2 | O4: 1 | Q4: Electricity | R4: Cost per Room Total OOC Usd | S4: Cost per Room Guest OOC Usd | T4: Water | U4: Gas
A5: =SUM([1]Gen!A11) -> 43739 | B5: 0 | C5: =SUM([1]Gen!B11) -> 0.623 | D5: =SUM(77*C5) -> 47.971 | F5: =[1]Gen!T11 -> 5669 | G5: =[1]Gen!S11 -> 2179.48 | H5: =[1]Gen!#REF! -> #REF! | I5: =SUM(G5:H5) -> #REF! | J5: =[1]Gen!AT11 -> 47806.65 | K5: ='[1]Water-Meter'!E10 -> 114 | L5: =#REF! -> #REF! | M5: =#REF! -> #REF! | N5: =#REF! -> #REF! | O5: =#REF! -> #REF! | P5: =J5/52000 -> 0.91935865 | Q5: =I5*Q2 -> #REF! | R5: =SUM(Q5/D5)/X5 -> #REF! | S5: =SUM(Q5/E5)/X5 -> #REF! | T5: =(K5*102)/X5 -> 7.3409091 | U5: =SUM(L5*1963)/X5 -> #REF! | V5: =SUM(Q5+T5+U5) -> #REF! | W5: =SUM(V5/E5)/T2 -> #REF! | X5: =SUM(T2) -> 1584 | Y5: 106 | Z5: =SUM(Y5-S5) -> #REF! | AA5: 106
A6: =SUM([1]Gen!A12) -> 43740 | B6: 0 | C6: =SUM([1]Gen!B12) -> 0.779 | D6: =SUM(77*C6) -> 59.983 | F6: =[1]Gen!T12 -> 6159 | G6: =[1]Gen!S12 -> 2472.85 | H6: =[1]Gen!#REF! -> #REF! | I6: =SUM(G6:H6) -> #REF! | J6: =[1]Gen!AT12 -> 45423.89 | K6: ='[1]Water-Meter'!E11 -> 126 | L6: =#REF! -> #REF! | M6: =#REF! -> #REF! | N6: =#REF! -> #REF! | O6: =#REF! -> #REF! | P6: =J6/52000 -> 0.87353635 | Q6: =I6*Q2 -> #REF! | R6: =SUM(Q6/D6)/X6 -> #REF! | S6: =SUM(Q6/E6)/X6 -> #REF! | T6: =(K6*102)/X6 -> 8.1136364 | U6: =SUM(L6*1963)/X6 -> #REF! | V6: =SUM(Q6+T6+U6) -> #REF! | W6: =SUM(V6/E6)/T2 -> #REF! | X6: =SUM(X5) -> 1584 | Y6: 106 | Z6: =SUM(Y6-S6) -> #REF!
A7: =SUM([1]Gen!A13) -> 43741 | B7: 0 | C7: =SUM([1]Gen!B13) -> 0.532 | D7: =SUM(77*C7) -> 40.964 | F7: =[1]Gen!T13 -> 6580 | G7: =[1]Gen!S13 -> 2554.39 | H7: =[1]Gen!#REF! -> #REF! | I7: =SUM(G7:H7) -> #REF! | J7: =[1]Gen!AT13 -> 42919.59 | K7: ='[1]Water-Meter'!E12 -> 116 | L7: =#REF! -> #REF! | M7: =#REF! -> #REF! | N7: =#REF! -> #REF! | O7: =#REF! -> #REF! | P7: =J7/52000 -> 0.82537673 | Q7: =I7*Q2 -> #REF! | R7: =SUM(Q7/D7)/X7 -> #REF! | S7: =SUM(Q7/E7)/X7 -> #REF! | T7: =(K7*102)/X7 -> 7.469697 | U7: =SUM(L7*1963)/X7 -> #REF! | V7: =SUM(Q7+T7+U7) -> #REF! | W7: =SUM(V7/E7)/T2 -> #REF! | X7: =SUM(X6) -> 1584 | Y7: 106 | Z7: =SUM(Y7-S7) -> #REF!
A8: =SUM([1]Gen!A14) -> 43742 | B8: 0 | C8: =SUM([1]Gen!B14) -> 0.61 | D8: =SUM(77*C8) -> 46.97 | F8: =[1]Gen!T14 -> 6223 | G8: =[1]Gen!S14 -> 2441.42 | H8: =[1]Gen!AJ9 -> #REF! | I8: =SUM(G8:H8) -> #REF! | J8: =[1]Gen!AT14 -> 40258.94 | K8: ='[1]Water-Meter'!E13 -> 120 | L8: =#REF! -> #REF! | M8: =#REF! -> #REF! | N8: =#REF! -> #REF! | O8: =#REF! -> #REF! | P8: =J8/52000 -> 0.77421038 | Q8: =I8*Q2 -> #REF! | R8: =SUM(Q8/D8)/X8 -> #REF! | S8: =SUM(Q8/E8)/X8 -> #REF! | T8: =(K8*102)/X8 -> 7.7272727 | U8: =SUM(L8*1963)/X8 -> #REF! | V8: =SUM(Q8+T8+U8) -> #REF! | W8: =SUM(V8/E8)/T2 -> #REF! | X8: =SUM(X7) -> 1584 | Y8: 106 | Z8: =SUM(Y8-S8) -> #REF!
A9: =SUM([1]Gen!A15) -> 43743 | B9: 0 | C9: =SUM([1]Gen!B15) -> 0.688 | D9: =SUM(77*C9) -> 52.976 | F9: =[1]Gen!T15 -> 5984 | G9: =[1]Gen!S15 -> 2338.36 | H9: =[1]Gen!AJ10 -> 0 | I9: =SUM(G9:H9) -> 2338.36 | J9: =[1]Gen!AT15 -> 37525.21 | K9: ='[1]Water-Meter'!E14 -> 107 | L9: =#REF! -> #REF! | M9: =#REF! -> #REF! | N9: =#REF! -> #REF! | O9: =#REF! -> #REF! | P9: =J9/52000 -> 0.72163865 | Q9: =I9*Q2 -> 5167424.8 | R9: =SUM(Q9/D9)/X9 -> 61.58002 | S9: =SUM(Q9/E9)/X9 -> #DIV/0! | T9: =(K9*102)/X9 -> 6.8901515 | U9: =SUM(L9*1963)/X9 -> #REF! | V9: =SUM(Q9+T9+U9) -> #REF! | W9: =SUM(V9/E9)/T2 -> #REF! | X9: =SUM(X8) -> 1584 | Y9: 106 | Z9: =SUM(Y9-S9) -> #DIV/0!
A10: =SUM([1]Gen!A16) -> 43744 | B10: 0 | C10: =SUM([1]Gen!B16) -> 0.532 | D10: =SUM(77*C10) -> 40.964 | F10: =[1]Gen!T16 -> 6103 | G10: =[1]Gen!S16 -> 2478.9 | H10: =[1]Gen!#REF! -> #REF! | I10: =SUM(G10:H10) -> #REF! | J10: =[1]Gen!AT16 -> 35107.69 | K10: ='[1]Water-Meter'!E15 -> 123 | L10: =#REF! -> #REF! | M10: =#REF! -> #REF! | N10: =#REF! -> #REF! | O10: =#REF! -> #REF! | P10: =J10/52000 -> 0.67514788 | Q10: =I10*Q2 -> #REF! | R10: =SUM(Q10/D10)/X10 -> #REF! | S10: =SUM(Q10/E10)/X10 -> #REF! | T10: =(K10*102)/X10 -> 7.9204545 | U10: =SUM(L10*1963)/X10 -> #REF! | V10: =SUM(Q10+T10+U10) -> #REF! | W10: =SUM(V10/E10)/T2 -> #REF! | X10: =SUM(X9) -> 1584 | Y10: 106 | Z10: =SUM(Y10-S10) -> #REF!
A11: =SUM([1]Gen!A17) -> 43745 | B11: 0 | C11: =SUM([1]Gen!B17) -> 0.753 | D11: =SUM(77*C11) -> 57.981 | F11: =[1]Gen!T17 -> 5576 | G11: =[1]Gen!S17 -> 2276.44 | H11: =[1]Gen!AJ25 -> 80.56 | I11: =SUM(G11:H11) -> 2357 | J11: =[1]Gen!AT17 -> 47513.14 | K11: ='[1]Water-Meter'!E16 -> 112 | L11: =#REF! -> #REF! | M11: =#REF! -> #REF! | N11: =#REF! -> #REF! | O11: =#REF! -> #REF! | P11: =J11/52000 -> 0.91371423 | Q11: =I11*Q2 -> 5208616.5 | R11: =SUM(Q11/D11)/X11 -> 56.712854 | S11: =SUM(Q11/E11)/X11 -> #DIV/0! | T11: =(K11*102)/X11 -> 7.2121212 | U11: =SUM(L11*1963)/X11 -> #REF! | V11: =SUM(Q11+T11+U11) -> #REF! | W11: =SUM(V11/E11)/T2 -> #REF! | X11: =SUM(X10) -> 1584 | Y11: 106 | Z11: =SUM(Y11-S11) -> #DIV/0!
A12: =SUM([1]Gen!A18) -> 43746 | B12: 0 | C12: =SUM([1]Gen!B18) -> 0.156 | D12: =SUM(77*C12) -> 12.012 | F12: =[1]Gen!T18 -> 5532 | G12: =[1]Gen!S18 -> 2242.4 | H12: =[1]Gen!#REF! -> #REF! | I12: =SUM(G12:H12) -> #REF! | J12: =[1]Gen!AT18 -> 45161.89 | K12: ='[1]Water-Meter'!E17 -> 128 | L12: =#REF! -> #REF! | M12: =#REF! -> #REF! | N12: =#REF! -> #REF! | O12: =#REF! -> #REF! | P12: =J12/52000 -> 0.86849788 | Q12: =I12*Q2 -> #REF! | R12: =SUM(Q12/D12)/X12 -> #REF! | S12: =SUM(Q12/E12)/X12 -> #REF! | T12: =(K12*102)/X12 -> 8.2424242 | U12: =SUM(L12*1963)/X12 -> #REF! | V12: =SUM(Q12+T12+U12) -> #REF! | W12: =SUM(V12/E12)/T2 -> #REF! | X12: =SUM(X11) -> 1584 | Y12: 106 | Z12: =SUM(Y12-S12) -> #REF!
A13: =SUM([1]Gen!A19) -> 43747 | B13: 0 | C13: =SUM([1]Gen!B19) -> 0.442 | D13: =SUM(77*C13) -> 34.034 | F13: =[1]Gen!T19 -> 6233 | G13: =[1]Gen!S19 -> 2430.27 | H13: =[1]Gen!#REF! -> #REF! | I13: =SUM(G13:H13) -> #REF! | J13: =[1]Gen!AT19 -> 42825.48 | K13: ='[1]Water-Meter'!E18 -> 114 | L13: =#REF! -> #REF! | M13: =#REF! -> #REF! | N13: =#REF! -> #REF! | O13: =#REF! -> #REF! | P13: =J13/52000 -> 0.82356692 | Q13: =I13*Q2 -> #REF! | R13: =SUM(Q13/D13)/X13 -> #REF! | S13: =SUM(Q13/E13)/X13 -> #REF! | T13: =(K13*102)/X13 -> 7.3409091 | U13: =SUM(L13*1963)/X13 -> #REF! | V13: =SUM(Q13+T13+U13) -> #REF! | W13: =SUM(V13/E13)/T2 -> #REF! | X13: =SUM(X12) -> 1584 | Y13: 106 | Z13: =SUM(Y13-S13) -> #REF!
A14: =SUM([1]Gen!A20) -> 43748 | B14: 0 | C14: =SUM([1]Gen!B20) -> 0.325 | D14: =SUM(77*C14) -> 25.025 | F14: =[1]Gen!T20 -> 6063 | G14: =[1]Gen!S20 -> 2463.77 | H14: =[1]Gen!#REF! -> #REF! | I14: =SUM(G14:H14) -> #REF! | J14: =[1]Gen!AT20 -> 40110.38 | K14: ='[1]Water-Meter'!E19 -> 119 | L14: =#REF! -> #REF! | M14: =#REF! -> #REF! | N14: =#REF! -> #REF! | O14: =#REF! -> #REF! | P14: =J14/52000 -> 0.77135346 | Q14: =I14*Q2 -> #REF! | R14: =SUM(Q14/D14)/X14 -> #REF! | S14: =SUM(Q14/E14)/X14 -> #REF! | T14: =(K14*102)/X14 -> 7.6628788 | U14: =SUM(L14*1963)/X14 -> #REF! | V14: =SUM(Q14+T14+U14) -> #REF! | W14: =SUM(V14/E14)/T2 -> #REF! | X14: =SUM(X13) -> 1584 | Y14: 106 | Z14: =SUM(Y14-S14) -> #REF!
A15: =SUM([1]Gen!A21) -> 43749 | B15: 0 | C15: =SUM([1]Gen!B21) -> 0.455 | D15: =SUM(77*C15) -> 35.035 | F15: =[1]Gen!T21 -> 5967 | G15: =[1]Gen!S21 -> 2310.19 | H15: =[1]Gen!#REF! -> #REF! | I15: =SUM(G15:H15) -> #REF! | J15: =[1]Gen!AT21 -> 37540.57 | K15: ='[1]Water-Meter'!E20 -> 128 | L15: =#REF! -> #REF! | M15: =#REF! -> #REF! | N15: =#REF! -> #REF! | O15: =#REF! -> #REF! | P15: =J15/52000 -> 0.72193404 | Q15: =I15*Q2 -> #REF! | R15: =SUM(Q15/D15)/X15 -> #REF! | S15: =SUM(Q15/E15)/X15 -> #REF! | T15: =(K15*102)/X15 -> 8.2424242 | U15: =SUM(L15*1963)/X15 -> #REF! | V15: =SUM(Q15+T15+U15) -> #REF! | W15: =SUM(V15/E15)/T2 -> #REF! | X15: =SUM(X14) -> 1584 | Y15: 106 | Z15: =SUM(Y15-S15) -> #REF!
A16: =SUM([1]Gen!A22) -> 43750 | B16: 0 | C16: =SUM([1]Gen!B22) -> 0.416 | D16: =SUM(77*C16) -> 32.032 | F16: =[1]Gen!T22 -> 5863 | G16: =[1]Gen!S22 -> 2429.17 | H16: =[1]Gen!#REF! -> #REF! | I16: =SUM(G16:H16) -> #REF! | J16: =[1]Gen!AT22 -> 34967.29 | K16: ='[1]Water-Meter'!E21 -> 127 | L16: =#REF! -> #REF! | M16: =#REF! -> #REF! | N16: =#REF! -> #REF! | O16: =#REF! -> #REF! | P16: =J16/52000 -> 0.67244788 | Q16: =I16*Q2 -> #REF! | R16: =SUM(Q16/D16)/X16 -> #REF! | S16: =SUM(Q16/E16)/X16 -> #REF! | T16: =(K16*102)/X16 -> 8.1780303 | U16: =SUM(L16*1963)/X16 -> #REF! | V16: =SUM(Q16+T16+U16) -> #REF! | W16: =SUM(V16/E16)/T2 -> #REF! | X16: =SUM(X15) -> 1584 | Y16: 106 | Z16: =SUM(Y16-S16) -> #REF!
A17: =SUM([1]Gen!A23) -> 43751 | B17: 0 | C17: =SUM([1]Gen!B23) -> 0.39 | D17: =SUM(77*C17) -> 30.03 | F17: =[1]Gen!T23 -> 5720 | G17: =[1]Gen!S23 -> 2249.53 | H17: =[1]Gen!#REF! -> #REF! | I17: =SUM(G17:H17) -> #REF! | J17: =[1]Gen!AT23 -> 32228.76 | K17: ='[1]Water-Meter'!E22 -> 122 | L17: =#REF! -> #REF! | M17: =#REF! -> #REF! | N17: =#REF! -> #REF! | O17: =#REF! -> #REF! | P17: =J17/52000 -> 0.61978385 | Q17: =I17*Q2 -> #REF! | R17: =SUM(Q17/D17)/X17 -> #REF! | S17: =SUM(Q17/E17)/X17 -> #REF! | T17: =(K17*102)/X17 -> 7.8560606 | U17: =SUM(L17*1963)/X17 -> #REF! | V17: =SUM(Q17+T17+U17) -> #REF! | W17: =SUM(V17/E17)/T2 -> #REF! | X17: =SUM(X16) -> 1584 | Y17: 106 | Z17: =SUM(Y17-S17) -> #REF!
A18: =SUM([1]Gen!A24) -> 43752 | B18: 0 | C18: =SUM([1]Gen!B24) -> 0.636 | D18: =SUM(77*C18) -> 48.972 | F18: =[1]Gen!T24 -> 6195 | G18: =[1]Gen!S24 -> 2420.41 | H18: =[1]Gen!AJ27 -> 597.9 | I18: =SUM(G18:H18) -> 3018.31 | J18: =[1]Gen!AT24 -> 29915.45 | K18: 0 | L18: =#REF! -> #REF! | M18: =#REF! -> #REF! | N18: =#REF! -> #REF! | O18: =#REF! -> #REF! | P18: =J18/52000 -> 0.57529712 | Q18: =I18*Q2 -> 6670012.4 | R18: =SUM(Q18/D18)/X18 -> 85.985183 | S18: =SUM(Q18/E18)/X18 -> #DIV/0! | T18: =(K18*102)/X18 -> 0 | U18: =SUM(L18*1963)/X18 -> #REF! | V18: =SUM(Q18+T18+U18) -> #REF! | W18: =SUM(V18/E18)/T2 -> #REF! | X18: =SUM(X17) -> 1584 | Y18: 106 | Z18: =SUM(Y18-S18) -> #DIV/0!
A19: =SUM([1]Gen!A25) -> 43753 | B19: 0 | C19: =SUM([1]Gen!B25) -> 0.844 | D19: =SUM(77*C19) -> 64.988 | F19: =[1]Gen!T25 -> 6450 | G19: =[1]Gen!S25 -> 2670.31 | H19: =[1]Gen!AJ28 -> 227.73 | I19: =SUM(G19:H19) -> 2898.04 | J19: =[1]Gen!AT25 -> 42248.24 | K19: ='[1]Water-Meter'!E24 -> 104 | L19: =#REF! -> #REF! | M19: =#REF! -> #REF! | N19: =#REF! -> #REF! | O19: =#REF! -> #REF! | P19: =J19/52000 -> 0.81246615 | Q19: =I19*Q2 -> 6404233.7 | R19: =SUM(Q19/D19)/X19 -> 62.212667 | S19: =SUM(Q19/E19)/X19 -> #DIV/0! | T19: =(K19*102)/X19 -> 6.6969697 | U19: =SUM(L19*1963)/X19 -> #REF! | V19: =SUM(Q19+T19+U19) -> #REF! | W19: =SUM(V19/E19)/T2 -> #REF! | X19: =SUM(X18) -> 1584 | Y19: 106 | Z19: =SUM(Y19-S19) -> #DIV/0!
A20: =SUM([1]Gen!A26) -> 43754 | B20: 0 | C20: =SUM([1]Gen!B26) -> 0.818 | D20: =SUM(77*C20) -> 62.986 | F20: =[1]Gen!T26 -> 6915 | G20: =[1]Gen!S26 -> 2741.7 | H20: =[1]Gen!AJ29 -> 88.29 | I20: =SUM(G20:H20) -> 2829.99 | J20: =[1]Gen!AT26 -> 39497.37 | K20: ='[1]Water-Meter'!E25 -> 100 | L20: =#REF! -> #REF! | M20: =#REF! -> #REF! | N20: =#REF! -> #REF! | O20: =#REF! -> #REF! | P20: =J20/52000 -> 0.75956481 | Q20: =I20*Q2 -> 6253853.4 | R20: =SUM(Q20/D20)/X20 -> 62.682815 | S20: =SUM(Q20/E20)/X20 -> #DIV/0! | T20: =(K20*102)/X20 -> 6.4393939 | U20: =SUM(L20*1963)/X20 -> #REF! | V20: =SUM(Q20+T20+U20) -> #REF! | W20: =SUM(V20/E20)/T2 -> #REF! | X20: =SUM(X19) -> 1584 | Y20: 106 | Z20: =SUM(Y20-S20) -> #DIV/0!
A21: =SUM([1]Gen!A27) -> 43755 | B21: 0 | C21: =SUM([1]Gen!B27) -> 0.208 | D21: =SUM(77*C21) -> 16.016 | F21: =[1]Gen!T27 -> 5962 | G21: =[1]Gen!S27 -> 2321.11 | H21: =[1]Gen!AJ30 -> 783.92 | I21: =SUM(G21:H21) -> 3105.03 | J21: =[1]Gen!AT27 -> 36688.35 | K21: ='[1]Water-Meter'!E26 -> 116 | L21: =#REF! -> #REF! | M21: =#REF! -> #REF! | N21: =#REF! -> #REF! | O21: =#REF! -> #REF! | P21: =J21/52000 -> 0.70554519 | Q21: =I21*Q2 -> 6861650.5 | R21: =SUM(Q21/D21)/X21 -> 270.47016 | S21: =SUM(Q21/E21)/X21 -> #DIV/0! | T21: =(K21*102)/X21 -> 7.469697 | U21: =SUM(L21*1963)/X21 -> #REF! | V21: =SUM(Q21+T21+U21) -> #REF! | W21: =SUM(V21/E21)/T2 -> #REF! | X21: =SUM(X20) -> 1584 | Y21: 106 | Z21: =SUM(Y21-S21) -> #DIV/0!
A22: =SUM([1]Gen!A28) -> 43756 | B22: 0 | C22: =SUM([1]Gen!B28) -> 0.221 | D22: =SUM(77*C22) -> 17.017 | F22: =[1]Gen!T28 -> 5257 | G22: =[1]Gen!S28 -> 2204.84 | H22: =[1]Gen!#REF! -> #REF! | I22: =SUM(G22:H22) -> #REF! | J22: =[1]Gen!AT28 -> 33769.34 | K22: ='[1]Water-Meter'!E27 -> 114 | L22: =#REF! -> #REF! | M22: =#REF! -> #REF! | N22: =#REF! -> #REF! | O22: =#REF! -> #REF! | P22: =J22/52000 -> 0.64941038 | Q22: =I22*Q2 -> #REF! | R22: =SUM(Q22/D22)/X22 -> #REF! | S22: =SUM(Q22/E22)/X22 -> #REF! | T22: =(K22*102)/X22 -> 7.3409091 | U22: =SUM(L22*1963)/X22 -> #REF! | V22: =SUM(Q22+T22+U22) -> #REF! | W22: =SUM(V22/E22)/T2 -> #REF! | X22: =SUM(X21) -> 1584 | Y22: 106 | Z22: =SUM(Y22-S22) -> #REF!
A23: =SUM([1]Gen!A29) -> 43757 | B23: 0 | C23: =SUM([1]Gen!B29) -> 0.117 | D23: =SUM(77*C23) -> 9.009 | F23: =[1]Gen!T29 -> 4691 | G23: =[1]Gen!S29 -> 1845.18 | H23: =[1]Gen!#REF! -> #REF! | I23: =SUM(G23:H23) -> #REF! | J23: =[1]Gen!AT29 -> 31336.77 | K23: ='[1]Water-Meter'!E28 -> 113 | L23: =#REF! -> #REF! | M23: =#REF! -> #REF! | N23: =#REF! -> #REF! | O23: =#REF! -> #REF! | P23: =J23/52000 -> 0.60263019 | Q23: =I23*Q2 -> #REF! | R23: =SUM(Q23/D23)/X23 -> #REF! | S23: =SUM(Q23/E23)/X23 -> #REF! | T23: =(K23*102)/X23 -> 7.2765152 | U23: =SUM(L23*1963)/X23 -> #REF! | V23: =SUM(Q23+T23+U23) -> #REF! | W23: =SUM(V23/E23)/T2 -> #REF! | X23: =SUM(X22) -> 1584 | Y23: 106 | Z23: =SUM(Y23-S23) -> #REF!
A24: =SUM([1]Gen!A30) -> 43758 | B24: 0 | C24: =SUM([1]Gen!B30) -> 0.571 | D24: =SUM(77*C24) -> 43.967 | F24: =[1]Gen!T30 -> 5712 | G24: =[1]Gen!S30 -> 2197.01 | H24: =[1]Gen!#REF! -> #REF! | I24: =SUM(G24:H24) -> #REF! | J24: =[1]Gen!AT30 -> 29403.3 | K24: ='[1]Water-Meter'!E29 -> 99 | L24: =#REF! -> #REF! | M24: =#REF! -> #REF! | N24: =#REF! -> #REF! | O24: =#REF! -> #REF! | P24: =J24/52000 -> 0.56544808 | Q24: =I24*Q2 -> #REF! | R24: =SUM(Q24/D24)/X24 -> #REF! | S24: =SUM(Q24/E24)/X24 -> #REF! | T24: =(K24*102)/X24 -> 6.375 | U24: =SUM(L24*1963)/X24 -> #REF! | V24: =SUM(Q24+T24+U24) -> #REF! | W24: =SUM(V24/E24)/T2 -> #REF! | X24: =SUM(X23) -> 1584 | Y24: 106 | Z24: =SUM(Y24-S24) -> #REF!
A25: =SUM([1]Gen!A31) -> 43759 | B25: 0 | C25: =SUM([1]Gen!B31) -> 0.558 | D25: =SUM(77*C25) -> 42.966 | F25: =[1]Gen!T31 -> 5941 | G25: =[1]Gen!S31 -> 2262.16 | H25: =[1]Gen!AJ31 -> 172.05 | I25: =SUM(G25:H25) -> 2434.21 | J25: =[1]Gen!AT31 -> 41422.37 | K25: ='[1]Water-Meter'!E30 -> 111 | L25: =#REF! -> #REF! | M25: =#REF! -> #REF! | N25: =#REF! -> #REF! | O25: =#REF! -> #REF! | P25: =J25/52000 -> 0.79658404 | Q25: =I25*Q2 -> 5379239 | R25: =SUM(Q25/D25)/X25 -> 79.038873 | S25: =SUM(Q25/E25)/X25 -> #DIV/0! | T25: =(K25*102)/X25 -> 7.1477273 | U25: =SUM(L25*1963)/X25 -> #REF! | V25: =SUM(Q25+T25+U25) -> #REF! | W25: =SUM(V25/E25)/T2 -> #REF! | X25: =SUM(X24) -> 1584 | Y25: 106 | Z25: =SUM(Y25-S25) -> #DIV/0!
A26: =SUM([1]Gen!A32) -> 43760 | B26: 0 | C26: =SUM([1]Gen!B32) -> 0.403 | D26: =SUM(77*C26) -> 31.031 | F26: =[1]Gen!T32 -> 5400 | G26: =[1]Gen!S32 -> 2286.86 | H26: =[1]Gen!AJ32 -> 18.63 | I26: =SUM(G26:H26) -> 2305.49 | J26: =[1]Gen!AT32 -> 38988.16 | K26: ='[1]Water-Meter'!E31 -> 130 | L26: =#REF! -> #REF! | M26: =#REF! -> #REF! | N26: =#REF! -> #REF! | O26: =#REF! -> #REF! | P26: =J26/52000 -> 0.74977231 | Q26: =I26*Q2 -> 5094787.1 | R26: =SUM(Q26/D26)/X26 -> 103.65138 | S26: =SUM(Q26/E26)/X26 -> #DIV/0! | T26: =(K26*102)/X26 -> 8.3712121 | U26: =SUM(L26*1963)/X26 -> #REF! | V26: =SUM(Q26+T26+U26) -> #REF! | W26: =SUM(V26/E26)/T2 -> #REF! | X26: =SUM(X25) -> 1584 | Y26: 106 | Z26: =SUM(Y26-S26) -> #DIV/0!
A27: =SUM([1]Gen!A33) -> 43761 | B27: 0 | C27: =SUM([1]Gen!B33) -> 0.24 | D27: =SUM(77*C27) -> 18.48 | F27: =[1]Gen!T33 -> 5371 | G27: =[1]Gen!S33 -> 2148.3 | H27: =[1]Gen!AJ33 -> 311.34 | I27: =SUM(G27:H27) -> 2459.64 | J27: =[1]Gen!AT33 -> 36682.67 | K27: ='[1]Water-Meter'!E32 -> 114 | L27: =#REF! -> #REF! | M27: =#REF! -> #REF! | N27: =#REF! -> #REF! | O27: =#REF! -> #REF! | P27: =J27/52000 -> 0.70543596 | Q27: =I27*Q2 -> 5435435.5 | R27: =SUM(Q27/D27)/X27 -> 185.68516 | S27: =SUM(Q27/E27)/X27 -> #DIV/0! | T27: =(K27*102)/X27 -> 7.3409091 | U27: =SUM(L27*1963)/X27 -> #REF! | V27: =SUM(Q27+T27+U27) -> #REF! | W27: =SUM(V27/E27)/T2 -> #REF! | X27: =SUM(X26) -> 1584 | Y27: 106 | Z27: =SUM(Y27-S27) -> #DIV/0!
A28: =SUM([1]Gen!A34) -> 43762 | B28: 0 | C28: =SUM([1]Gen!B34) -> 0.09 | D28: =SUM(77*C28) -> 6.93 | F28: =[1]Gen!T34 -> 5296 | G28: =[1]Gen!S34 -> 2213.27 | H28: =[1]Gen!AJ34 -> 380.7 | I28: =SUM(G28:H28) -> 2593.97 | J28: =[1]Gen!AT34 -> 44223.03 | K28: ='[1]Water-Meter'!E33 -> -215493 | L28: =#REF! -> #REF! | M28: =#REF! -> #REF! | N28: =#REF! -> #REF! | O28: =#REF! -> #REF! | P28: =J28/52000 -> 0.85044288 | Q28: =I28*Q2 -> 5732284.6 | R28: =SUM(Q28/D28)/X28 -> 522.20296 | S28: =SUM(Q28/E28)/X28 -> #DIV/0! | T28: =(K28*102)/X28 -> -13876.443 | U28: =SUM(L28*1963)/X28 -> #REF! | V28: =SUM(Q28+T28+U28) -> #REF! | W28: =SUM(V28/E28)/T2 -> #REF! | X28: =SUM(X27) -> 1584 | Y28: 106 | Z28: =SUM(Y28-S28) -> #DIV/0!
A29: =SUM([1]Gen!A35) -> 43763 | B29: 0 | C29: =SUM([1]Gen!B35) -> 0.286 | D29: =SUM(77*C29) -> 22.022 | F29: =[1]Gen!T35 -> 5221 | G29: =[1]Gen!S35 -> 2104.52 | H29: =[1]Gen!AJ35 -> 273.37 | I29: =SUM(G29:H29) -> 2377.89 | J29: =[1]Gen!AT35 -> 41629.06 | K29: ='[1]Water-Meter'!E34 -> 0 | L29: =#REF! -> #REF! | M29: =#REF! -> #REF! | N29: =#REF! -> #REF! | O29: =#REF! -> #REF! | P29: =J29/52000 -> 0.80055885 | Q29: =I29*Q2 -> 5254780.2 | R29: =SUM(Q29/D29)/X29 -> 150.6408 | S29: =SUM(Q29/E29)/X29 -> #DIV/0! | T29: =(K29*102)/X29 -> 0 | U29: =SUM(L29*1963)/X29 -> #REF! | V29: =SUM(Q29+T29+U29) -> #REF! | W29: =SUM(V29/E29)/T2 -> #REF! | X29: =SUM(X28) -> 1584 | Y29: 106 | Z29: =SUM(Y29-S29) -> #DIV/0!
A30: =SUM([1]Gen!A36) -> 43764 | B30: 0 | C30: =SUM([1]Gen!B36) -> 0.545 | D30: =SUM(77*C30) -> 41.965 | F30: =[1]Gen!T36 -> 5665 | G30: =[1]Gen!S36 -> 2470.24 | H30: =[1]Gen!AJ36 -> 396.56 | I30: =SUM(G30:H30) -> 2866.8 | J30: =[1]Gen!AT36 -> 39251.17 | K30: ='[1]Water-Meter'!E35 -> 0 | L30: =#REF! -> #REF! | M30: =#REF! -> #REF! | N30: =#REF! -> #REF! | O30: =#REF! -> #REF! | P30: =J30/52000 -> 0.75483019 | Q30: =I30*Q2 -> 6335198 | R30: =SUM(Q30/D30)/X30 -> 95.305461 | S30: =SUM(Q30/E30)/X30 -> #DIV/0! | T30: =(K30*102)/X30 -> 0 | U30: =SUM(L30*1963)/X30 -> #REF! | V30: =SUM(Q30+T30+U30) -> #REF! | W30: =SUM(V30/E30)/T2 -> #REF! | X30: =SUM(X29) -> 1584 | Y30: 106 | Z30: =SUM(Y30-S30) -> #DIV/0!
A31: =SUM([1]Gen!A37) -> 43765 | B31: 0 | C31: =SUM([1]Gen!B37) -> 0.675 | D31: =SUM(77*C31) -> 51.975 | F31: =[1]Gen!T37 -> 6109 | G31: =[1]Gen!S37 -> 2323.74 | H31: =[1]Gen!AJ37 -> 280.63 | I31: =SUM(G31:H31) -> 2604.37 | J31: =[1]Gen!AT37 -> 36384.37 | K31: ='[1]Water-Meter'!E36 -> 0 | L31: =#REF! -> #REF! | M31: =#REF! -> #REF! | N31: =#REF! -> #REF! | O31: =#REF! -> #REF! | P31: =J31/52000 -> 0.69969942 | Q31: =I31*Q2 -> 5755267 | R31: =SUM(Q31/D31)/X31 -> 69.906218 | S31: =SUM(Q31/E31)/X31 -> #DIV/0! | T31: =(K31*102)/X31 -> 0 | U31: =SUM(L31*1963)/X31 -> #REF! | V31: =SUM(Q31+T31+U31) -> #REF! | W31: =SUM(V31/E31)/T2 -> #REF! | X31: =SUM(X30) -> 1584 | Y31: 106 | Z31: =SUM(Y31-S31) -> #DIV/0!
A32: =SUM([1]Gen!A38) -> 43766 | B32: 0 | C32: =SUM([1]Gen!B38) -> 0.273 | D32: =SUM(77*C32) -> 21.021 | F32: =[1]Gen!T38 -> 0 | G32: =[1]Gen!S38 -> 0 | H32: =[1]Gen!AJ38 -> 0 | I32: =SUM(G32:H32) -> 0 | J32: =[1]Gen!AT38 -> 33780 | K32: ='[1]Water-Meter'!E37 -> 0 | L32: =#REF! -> #REF! | M32: =#REF! -> #REF! | N32: =#REF! -> #REF! | O32: =#REF! -> #REF! | P32: =J32/52000 -> 0.64961538 | Q32: =I32*Q2 -> 0 | R32: =SUM(Q32/D32)/X32 -> 0 | S32: =SUM(Q32/E32)/X32 -> #DIV/0! | T32: =(K32*102)/X32 -> 0 | U32: =SUM(L32*1963)/X32 -> #REF! | V32: =SUM(Q32+T32+U32) -> #REF! | W32: =SUM(V32/E32)/T2 -> #REF! | X32: =SUM(X31) -> 1584 | Y32: 106 | Z32: =SUM(Y32-S32) -> #DIV/0!
B33: 0 | C33: =SUM([1]Gen!B39) -> #REF! | D33: =SUM(77*C33) -> #REF! | F33: =[1]Gen!T39 -> 0 | G33: =[1]Gen!S39 -> 0 | H33: =[1]Gen!AJ39 -> 0 | I33: =SUM(G33:H33) -> 0 | J33: =[1]Gen!AT39 -> 33780 | K33: ='[1]Water-Meter'!E38 -> -212333 | L33: =#REF! -> #REF! | M33: =#REF! -> #REF! | N33: =#REF! -> #REF! | O33: =#REF! -> #REF! | P33: =J33/52000 -> 0.64961538 | Q33: =I33*Q2 -> 0 | R33: =SUM(Q33/D33)/X33 -> #REF! | S33: =SUM(Q33/E33)/X33 -> #DIV/0! | T33: =(K33*102)/X33 -> -13672.958 | U33: =SUM(L33*1963)/X33 -> #REF! | V33: =SUM(Q33+T33+U33) -> #REF! | W33: =SUM(V33/E33)/T2 -> #REF! | X33: =SUM(X32) -> 1584 | Y33: 106 | Z33: =SUM(Y33-S33) -> #DIV/0!
B34: 0 | C34: =SUM([1]Gen!B40) -> #REF! | D34: =SUM(77*C34) -> #REF! | F34: =[1]Gen!T40 -> 0 | G34: =[1]Gen!S40 -> 0 | H34: =[1]Gen!AJ40 -> 0 | I34: =SUM(G34:H34) -> 0 | J34: =[1]Gen!AT40 -> 33780 | K34: ='[1]Water-Meter'!E39 -> #REF! | L34: =#REF! -> #REF! | M34: =#REF! -> #REF! | N34: =#REF! -> #REF! | O34: =#REF! -> #REF! | P34: =J34/52000 -> 0.64961538 | Q34: =I34*Q2 -> 0 | R34: =SUM(Q34/D34)/X34 -> #REF! | S34: =SUM(Q34/E34)/X34 -> #DIV/0! | T34: =(K34*102)/X34 -> #REF! | U34: =SUM(L34*1963)/X34 -> #REF! | V34: =SUM(Q34+T34+U34) -> #REF! | W34: =SUM(V34/E34)/T2 -> #REF! | X34: =SUM(X33) -> 1584 | Y34: 106 | Z34: =SUM(Y34-S34) -> #DIV/0!
B35: 0 | C35: =SUM([1]Gen!B41) -> #REF! | D35: =SUM(77*C35) -> #REF! | F35: =[1]Gen!T41 -> 0 | G35: =[1]Gen!S41 -> 0 | H35: =[1]Gen!AJ41 -> 0 | I35: =SUM(G35:H35) -> 0 | J35: =[1]Gen!AT41 -> 33780 | K35: ='[1]Water-Meter'!E40 -> #REF! | L35: =#REF! -> #REF! | M35: =#REF! -> #REF! | N35: =#REF! -> #REF! | O35: =#REF! -> #REF! | P35: =J35/52000 -> 0.64961538 | Q35: =I35*Q2 -> 0 | R35: =SUM(Q35/D35)/X35 -> #REF! | S35: =SUM(Q35/E35)/X35 -> #DIV/0! | T35: =(K35*102)/X35 -> #REF! | U35: =SUM(L35*1963)/X35 -> #REF! | V35: =SUM(Q35+T35+U35) -> #REF! | W35: =SUM(V35/E35)/T2 -> #REF! | X35: =SUM(X34) -> 1584 | Y35: 106 | Z35: =SUM(Y35-S35) -> #DIV/0!
K36: ='[1]Water-Meter'!E41 -> #REF! | Q36: =I36*2057.79 -> 0 | V36: =SUM(Q36+T36+U36) -> 0
S37: =SUM(S5:S16)/[1]Gen!A47 -> #REF!
B38: =SUM(B5:B37)/[1]Gen!A47 -> #REF! | M38: =0.5*2057.79 -> 1028.895
B39: =SUM(B38*[1]Gen!A47) -> #REF! | C39: =SUM(B39/250) -> #REF! | M39: =M38/1500 -> 0.68593 | O39: =(24*2.2)*2 -> 105.6 | P39: =O39*1029 -> 108662.4 | R39: Over budget | S39: =SUM(S37-Y35) -> #REF!
P40: =P39/K5 -> 953.17895

Sheet VODACOM AND AIRTEL
A1: VODACOM AND AIRTEL KWH METER READING
B2: VODACOM TOWER | E2: AIRTEL TOWER
A3: DATE | B3: OPEN METER READING | C3: CLOSE METER READING | D3: UNIT CONSUMED | E3: OPEN METER READING | F3: CLOSE METER READING | G3: UNIT CONSUMED
A4: 42095 | B4: 0 | C4: 193 | D4: =C4-B4 -> 193 | E4: 0 | F4: 0 | G4: =F4-E4 -> 0
A5: 42125 | B5: =C4 -> 193 | C5: 1158 | D5: =C5-B5 -> 965 | E5: 145572 | F5: 145572 | G5: =F5-E5 -> 0
A6: 42156 | B6: =C5 -> 1158 | C6: 2084 | D6: =C6-B6 -> 926 | E6: =F5 -> 145572 | F6: 147984 | G6: =F6-E6 -> 2412
A7: 42186 | B7: =C6 -> 2084 | C7: 3073 | D7: =C7-B7 -> 989 | E7: =F6 -> 147984 | F7: 150507 | G7: =F7-E7 -> 2523
A8: 42217 | B8: =C7 -> 3073 | C8: 4063 | D8: =C8-B8 -> 990 | E8: =F7 -> 150507 | F8: 152986 | G8: =F8-E8 -> 2479
A9: 42248 | B9: =C8 -> 4063 | C9: 5058 | D9: =C9-B9 -> 995 | E9: =F8 -> 152986 | F9: 155468 | G9: =F9-E9 -> 2482
A10: 42278 | B10: =C9 -> 5058 | C10: 6049 | D10: =C10-B10 -> 991 | E10: =F9 -> 155468 | F10: 157962 | G10: =F10-E10 -> 2494
A11: 42309 | B11: =C10 -> 6049 | C11: 7028 | D11: =C11-B11 -> 979 | E11: =F10 -> 157962 | F11: 160323 | G11: =F11-E11 -> 2361
A12: 42339 | B12: =C11 -> 7028 | C12: 7985 | D12: =C12-B12 -> 957 | E12: =F11 -> 160323 | F12: 162813 | G12: =F12-E12 -> 2490
A13: 42370 | B13: =C12 -> 7985 | C13: 8952 | D13: =C13-B13 -> 967 | E13: =F12 -> 162813 | F13: 165317 | G13: =F13-E13 -> 2504
A14: 42401 | B14: =C13 -> 8952 | C14: 9898 | D14: =C14-B14 -> 946 | E14: =F13 -> 165317 | F14: 167679 | G14: =F14-E14 -> 2362
A15: 42430 | B15: =C14 -> 9898 | C15: 10637 | D15: =C15-B15 -> 739 | E15: =F14 -> 167679 | F15: 170134 | G15: =F15-E15 -> 2455
A16: 42461 | B16: =C15 -> 10637 | C16: 11352 | D16: =C16-B16 -> 715 | E16: =F15 -> 170134 | F16: 172562 | G16: =F16-E16 -> 2428
A17: 42491 | B17: =C16 -> 11352 | C17: 12426 | D17: =C17-B17 -> 1074 | E17: =F16 -> 172562 | F17: 175041 | G17: =F17-E17 -> 2479
... A58: 43739 | B58: =C57 -> 87262 | C58: 89489 | D58: =C58-B58 -> 2227 | E58: =F57 -> 261652 | F58: 263905 | G58: =F58-E58 -> 2253
A59: 43770 | B59: =C58 -> 89489 | D59: =C59-B59 -> -89489 | E59: =F58 -> 263905 | G59: =F59-E59 -> -263905
A60: 43800 | B60: =C59 -> 0 | D60: =C60-B60 -> 0 | E60: =F59 -> 0 | G60: =F60-E60 -> 0
A61: 43831 | B61: =C60 -> 0 | D61: =C61-B61 -> 0 | E61: =F60 -> 0 | G61: =F61-E61 -> 0
A62: 43862 | B62: =C61 -> 0 | D62: =C62-B62 -> 0 | E62: =F61 -> 0 | G62: =F62-E62 -> 0
A63: 43891 | B63: =C62 -> 0 | D63: =C63-B63 -> 0 | E63: =F62 -> 0 | G63: =F63-E63 -> 0
A64: 43922 | B64: =C63 -> 0 | D64: =C64-B64 -> 0 | E64: =F63 -> 0 | G64: =F64-E64 -> 0
A65: 43952 | B65: =C64 -> 0 | D65: =C65-B65 -> 0 | E65: =F64 -> 0 | G65: =F65-E65 -> 0
A66: 43983 | B66: =C65 -> 0 | D66: =C66-B66 -> 0 | E66: =F65 -> 0 | G66: =F66-E66 -> 0
A67: 44013 | B67: =C66 -> 0 | D67: =C67-B67 -> 0 | E67: =F66 -> 0 | G67: =F67-E67 -> 0
A68: 44044 | B68: =C67 -> 0 | D68: =C68-B68 -> 0 | E68: =F67 -> 0 | G68: =F68-E68 -> 0
A69: 44075 | B69: =C68 -> 0 | D69: =C69-B69 -> 0 | E69: =F68 -> 0 | G69: =F69-E69 -> 0
A70: 44105 | B70: =C69 -> 0 | D70: =C70-B70 -> 0 | E70: =F69 -> 0 | G70: =F70-E70 -> 0
... A77: 44317 | B77: =C76 -> 0 | D77: =C77-B77 -> 0 | E77: =F76 -> 0 | G77: =F77-E77 -> 0

Sheet FUEL METER READING
A1: FUEL METER 1 READNG | H1: FUEL METER 2 READING
A2: DATE | B2: OPEN METER READING | C2: CLOSE METER READING | D2: Diesel consumed | E2: HLP-GENSETS | F2: DIFFERENCE | G2: OPEN METER | H2: CLOSE METER | I2: DIESEL CONSUMED | J2: HLP-VEHICLES | K2: DIFFERENCE | L2: TOTAL DIESEL CONS.
A3: 42430 | B3: 5000778 | C3: 5057715 | D3: =C3-B3 -> 56937 | G3: =H3 -> 0 | I3: =H3-G3 -> 0 | K3: =I3-J3 -> 0
A4: 42461 | B4: =C3 -> 5057715 | C4: 5111496 | D4: =C4-B4 -> 53781 | G4: =H3 -> 0 | I4: =H4-G4 -> 0 | K4: =I4-J4 -> 0
A5: 42491 | B5: =C4 -> 5111496 | C5: 5169409 | D5: =C5-B5 -> 57913 | G5: =H4 -> 0 | I5: =H5-G5 -> 0 | K5: =I5-J5 -> 0
A6: 42522 | B6: =C5 -> 5169409 | C6: 5232162 | D6: =C6-B6 -> 62753 | G6: =H5 -> 0 | I6: =H6-G6 -> 0 | K6: =I6-J6 -> 0
A7: 42552 | B7: =C6 -> 5232162 | C7: 5310037 | D7: =C7-B7 -> 77875 | G7: =H6 -> 0 | I7: =H7-G7 -> 0 | K7: =I7-J7 -> 0
A8: 42583 | B8: =C7 -> 5310037 | C8: 5382821 | D8: =C8-B8 -> 72784 | E8: =[6]Gen!AR45 -> 72766 | F8: =D8-E8 -> 18 | G8: =H7 -> 0 | I8: =H8-G8 -> 0 | K8: =I8-J8 -> 0
A9: 42614 | B9: =C8 -> 5382821 | C9: 5446740 | D9: =C9-B9 -> 63919 | E9: =[7]Gen!AR45 -> 64036.5 | F9: =D9-E9 -> -117.5 | G9: =H8 -> 0 | I9: =H9-G9 -> 0 | K9: =I9-J9 -> 0
A10: 42644 | B10: =C9 -> 5446740 | C10: 5521440 | D10: =C10-B10 -> 74700 | E10: 76057.09 | F10: =D10-E10 -> -1357.09 | G10: =H9 -> 0 | I10: =H10-G10 -> 0 | K10: =I10-J10 -> 0
A11: 42675 | B11: =C10 -> 5521440 | C11: 5594926 | D11: =C11-B11 -> 73486 | E11: 73462.49 | F11: =D11-E11 -> 23.51 | G11: =H10 -> 0 | I11: =H11-G11 -> 0 | K11: =I11-J11 -> 0
A12: 42705 | B12: =C11 -> 5594926 | C12: 5670348 | D12: =C12-B12 -> 75422 | E12: 75421.2 | F12: =D12-E12 -> 0.8 | G12: =H11 -> 0 | I12: =H12-G12 -> 0 | K12: =I12-J12 -> 0
A13: 42736 | B13: =C12 -> 5670348 | C13: 5735627 | D13: =C13-B13 -> 65279 | E13: 65276.07 | F13: =D13-E13 -> 2.93 | G13: =H12 -> 0 | I13: =H13-G13 -> 0 | K13: =I13-J13 -> 0
A14: 42767 | B14: =C13 -> 5735627 | C14: 5797781 | D14: =C14-B14 -> 62154 | E14: 62154.9 | F14: =D14-E14 -> -0.9 | G14: =H13 -> 0 | I14: =H14-G14 -> 0 | K14: =I14-J14 -> 0
A15: 42795 | B15: =C14 -> 5797781 | C15: 5864602 | D15: =C15-B15 -> 66821 | E15: 66820.89 | F15: =D15-E15 -> 0.11 | G15: =H14 -> 0 | I15: =H15-G15 -> 0 | K15: =I15-J15 -> 0
A16: 42826 | B16: =C15 -> 5864602 | C16: 5927895 | D16: =C16-B16 -> 63293 | E16: 63292.38 | F16: =D16-E16 -> 0.62 | G16: =H15 -> 0 | I16: =H16-G16 -> 0 | K16: =I16-J16 -> 0
A17: 42856 | B17: =C16 -> 5927895 | C17: 5995212 | D17: =C17-B17 -> 67317 | E17: 67313.47 | F17: =D17-E17 -> 3.53 | G17: =H16 -> 0 | I17: =H17-G17 -> 0 | K17: =I17-J17 -> 0
A18: 42887 | B18: =C17 -> 5995212 | C18: 6065754 | D18: =C18-B18 -> 70542 | E18: 70542.6 | F18: =D18-E18 -> -0.6 | G18: =H17 -> 0 | I18: =H18-G18 -> 0 | K18: =I18-J18 -> 0
A19: 42917 | B19: =C18 -> 6065754 | C19: 6141089 | D19: =C19-B19 -> 75335 | E19: 75335 | F19: =D19-E19 -> 0 | G19: 2442 | H19: 15003 | I19: =H19-G19 -> 12561 | K19: =I19-J19 -> 12561
A20: 42948 | B20: =C19 -> 6141089 | C20: 6212470 | D20: =C20-B20 -> 71381 | E20: 71379.9 | F20: =D20-E20 -> 1.1 | G20: =H19 -> 15003 | H20: 25033 | I20: =H20-G20 -> 10030 | J20: 10029.74 | K20: =I20-J20 -> 0.26 | L20: =I20+D20 -> 81411
A21: 42979 | B21: =C20 -> 6212470 | C21: 6276921 | D21: =C21-B21 -> 64451 | E21: 64450.62 | F21: =D21-E21 -> 0.38 | G21: =H20 -> 25033 | H21: 32815 | I21: =H21-G21 -> 7782 | J21: 7781.72 | K21: =I21-J21 -> 0.28 | L21: =I21+D21 -> 72233
A22: 43009 | B22: =C21 -> 6276921 | C22: 6352831 | D22: =C22-B22 -> 75910 | E22: 75906.79 | F22: =D22-E22 -> 3.21 | G22: =H21 -> 32815 | H22: 39587 | I22: =H22-G22 -> 6772 | J22: 6772.04 | K22: =I22-J22 -> -0.04 | L22: =I22+D22 -> 82682
A23: 43040 | B23: =C22 -> 6352831 | C23: 6410003 | D23: =C23-B23 -> 57172 | E23: 57171.51 | F23: =D23-E23 -> 0.49 | G23: =H22 -> 39587 | H23: 45717 | I23: =H23-G23 -> 6130 | J23: 6129.55 | K23: =I23-J23 -> 0.45 | L23: =I23+D23 -> 63302
A24: 43070 | B24: =C23 -> 6410003 | C24: 6476953 | D24: =C24-B24 -> 66950 | E24: 66951.14 | F24: =D24-E24 -> -1.14 | G24: =H23 -> 45717 | H24: 52890 | I24: =H24-G24 -> 7173 | J24: 7173.94 | K24: =I24-J24 -> -0.94 | L24: =I24+D24 -> 74123
A25: 43101 | B25: =C24 -> 6476953 | C25: 6542879 | D25: =C25-B25 -> 65926 | E25: 65927.77 | F25: =D25-E25 -> -1.77 | G25: =H24 -> 52890 | H25: 59763 | I25: =H25-G25 -> 6873 | J25: 6874.87 | K25: =I25-J25 -> -1.87 | L25: =I25+D25 -> 72799
A26: 43132 | B26: =C25 -> 6542879 | C26: 6604433 | D26: =C26-B26 -> 61554 | E26: 61553.03 | F26: =D26-E26 -> 0.97 | G26: =H25 -> 59763 | H26: 66652 | I26: =H26-G26 -> 6889 | J26: 6890.89 | K26: =I26-J26 -> -1.89 | L26: =I26+D26 -> 68443
A27: 43160 | B27: =C26 -> 6604433 | C27: 6660226 | D27: =C27-B27 -> 55793 | E27: 55792.75 | F27: =D27-E27 -> 0.25 | G27: =H26 -> 66652 | H27: 77607 | I27: =H27-G27 -> 10955 | J27: 10955.45 | K27: =I27-J27 -> -0.45 | L27: =I27+D27 -> 66748
A28: 43191 | B28: =C27 -> 6660226 | C28: 6714539 | D28: =C28-B28 -> 54313 | E28: 54312.28 | F28: =D28-E28 -> 0.72 | G28: =H27 -> 77607 | H28: 82271 | I28: =H28-G28 -> 4664 | J28: 4665.22 | K28: =I28-J28 -> -1.22 | L28: =I28+D28 -> 58977
A29: 43221 | B29: =C28 -> 6714539 | C29: 6774547 | D29: =C29-B29 -> 60008 | E29: 60007.47 | F29: =D29-E29 -> 0.53 | G29: =H28 -> 82271 | H29: 88664 | I29: =H29-G29 -> 6393 | J29: 6392.14 | K29: =I29-J29 -> 0.86 | L29: =I29+D29 -> 66401
A30: 43252 | B30: =C29 -> 6774547 | C30: 6845214 | D30: =C30-B30 -> 70667 | E30: 70666.29 | F30: =D30-E30 -> 0.71 | G30: =H29 -> 88664 | H30: 99683 | I30: =H30-G30 -> 11019 | J30: 11020.51 | K30: =I30-J30 -> -1.51 | L30: =I30+D30 -> 81686
A31: 43282 | B31: =C30 -> 6845214 | C31: 6921964 | D31: =C31-B31 -> 76750 | E31: 76750.25 | F31: =D31-E31 -> -0.25 | G31: =H30 -> 99683 | H31: 107936 | I31: =H31-G31 -> 8253 | J31: 8252.24 | K31: =I31-J31 -> 0.76 | L31: =I31+D31 -> 85003
... A42: 43617 | B42: =C41 -> 7635177 | C42: 7705814 | D42: =C42-B42 -> 70637 | E42: 70631.2 | F42: =D42-E42 -> 5.8 | G42: =H41 -> 191580 | H42: 198910 | I42: =H42-G42 -> 7330 | J42: 7352.54 | K42: =I42-J42 -> -22.54 | L42: =I42+D42 -> 77967
A43: 43647 | B43: =C42 -> 7705814 | C43: 7789265 | D43: =C43-B43 -> 83451 | E43: 83450.26 | F43: =D43-E43 -> 0.74 | G43: =H42 -> 198910 | H43: 208208 | I43: =H43-G43 -> 9298 | J43: 8921.51 | K43: =I43-J43 -> 376.49 | L43: =SUM(L20:L42) -> 1748632
A44: 43678 | B44: =C43 -> 7789265 | C44: 7867728 | D44: =C44-B44 -> 78463 | E44: 78463.6 | F44: =D44-E44 -> -0.6 | G44: =H43 -> 208208 | H44: 216205 | I44: =H44-G44 -> 7997 | J44: 7870.33 | K44: =I44-J44 -> 126.67 | L44: =I44+D44 -> 86460
A45: 43709 | B45: =C44 -> 7867728 | C45: 7937278 | D45: =C45-B45 -> 69550 | E45: 69549.31 | F45: =D45-E45 -> 0.69 | G45: =H44 -> 216205 | H45: 223195 | I45: =H45-G45 -> 6990 | J45: 6989.22 | K45: =I45-J45 -> 0.78 | L45: =I45+D45 -> 76540
A46: 43739 | B46: =C45 -> 7937278 | C46: 8009185 | D46: =C46-B46 -> 71907 | E46: 71906.24 | F46: =D46-E46 -> 0.76 | G46: =H45 -> 223195 | H46: 229902 | I46: =H46-G46 -> 6707 | J46: 6706 | K46: =I46-J46 -> 1 | L46: =I46+D46 -> 78614
A47: 43770 | B47: =C46 -> 8009185 | D47: =C47-B47 -> -8009185 | F47: =D47-E47 -> -8009185 | G47: =H46 -> 229902 | I47: =H47-G47 -> -229902 | K47: =I47-J47 -> -229902 | L47: =I47+D47 -> -8239087
A48: 43800 | B48: =C47 -> 0 | D48: =C48-B48 -> 0 | F48: =D48-E48 -> 0 | G48: =H47 -> 0 | I48: =H48-G48 -> 0 | K48: =I48-J48 -> 0 | L48: =I48+D48 -> 0
A49: 43831 | B49: =C48 -> 0 | D49: =C49-B49 -> 0 | F49: =D49-E49 -> 0 | G49: =H48 -> 0 | I49: =H49-G49 -> 0 | K49: =I49-J49 -> 0 | L49: =I49+D49 -> 0
A50: 43862 | B50: =C49 -> 0 | D50: =C50-B50 -> 0 | F50: =D50-E50 -> 0 | G50: =H49 -> 0 | I50: =H50-G50 -> 0 | K50: =I50-J50 -> 0 | L50: =I50+D50 -> 0
A51: 43891 | B51: =C50 -> 0 | D51: =C51-B51 -> 0 | F51: =D51-E51 -> 0 | G51: =H50 -> 0 | I51: =H51-G51 -> 0 | K51: =I51-J51 -> 0 | L51: =I51+D51 -> 0
A52: 43922 | B52: =C51 -> 0 | D52: =C52-B52 -> 0 | F52: =D52-E52 -> 0 | G52: =H51 -> 0 | I52: =H52-G52 -> 0 | K52: =I52-J52 -> 0 | L52: =I52+D52 -> 0
A53: 43586 | B53: =C52 -> 0 | D53: =C53-B53 -> 0 | F53: =D53-E53 -> 0 | G53: =H52 -> 0 | I53: =H53-G53 -> 0 | K53: =I53-J53 -> 0 | L53: =I53+D53 -> 0
A54: 43983 | B54: =C53 -> 0 | D54: =C54-B54 -> 0 | F54: =D54-E54 -> 0 | G54: =H53 -> 0 | I54: =H54-G54 -> 0 | K54: =I54-J54 -> 0 | L54: =I54+D54 -> 0

Sheet Daily utility report 
A1: DAILY UTILITIES REPORT
A2: 43739
A3: DATE | B3: OCC % | D3: GENERATOR FUEL (LTR) | F3: WATER (M³) | I3: ELECTRICAL (Kwh)
C4: VEHICLE CONSUMPTION | D4: CONSUMPTION | E4: BALANCE | F4: CONSUMPTION | G4: BOREHOLE PRODUCTION | H4: RO PRODUCTION | I4: KITCHEN | J4: LAUNDRY
A5: 43739 | B5: =Gen!B11 -> 0.623 | C5: =Gen!AJ11 -> 203.28 | D5: =Gen!S11 -> 2179.48 | E5: =Gen!C11 -> 47806.65 | F5: ='Water-Meter'!E6 -> 130 | G5: ='Water-Meter'!AN5 -> 0 | H5: ='Utility report '!AC6 -> 26 | I5: ='Kit report'!F4 -> 420 | J5: ='Kit report'!X4 -> 740
A6: 43740 | B6: =Gen!B12 -> 0.779 | C6: =Gen!AJ12 -> 31.45 | D6: =Gen!S12 -> 2472.85 | E6: =Gen!C12 -> 45423.89 | F6: ='Water-Meter'!E7 -> 128 | G6: ='Water-Meter'!AN6 -> 160 | H6: ='Utility report '!AC7 -> 177 | I6: ='Kit report'!F5 -> 480 | J6: ='Kit report'!X5 -> 900
A7: 43741 | B7: =Gen!B13 -> 0.532 | C7: =Gen!AJ13 -> 106.26 | D7: =Gen!S13 -> 2554.39 | E7: =Gen!C13 -> 42919.59 | F7: ='Water-Meter'!E8 -> 120 | G7: ='Water-Meter'!AN7 -> 168 | H7: ='Utility report '!AC8 -> 128 | I7: ='Kit report'!F6 -> 504 | J7: ='Kit report'!X6 -> 940
A8: 43742 | B8: =Gen!B14 -> 0.61 | C8: =Gen!AJ14 -> 292.31 | D8: =Gen!S14 -> 2441.42 | E8: =Gen!C14 -> 40258.94 | F8: ='Water-Meter'!E9 -> 120 | G8: ='Water-Meter'!AN8 -> 167 | H8: ='Utility report '!AC9 -> 115 | I8: ='Kit report'!F7 -> 516 | J8: ='Kit report'!X7 -> 920
A9: 43743 | B9: =Gen!B15 -> 0.688 | C9: =Gen!AJ15 -> 79.16 | D9: =Gen!S15 -> 2338.36 | E9: =Gen!C15 -> 37525.21 | F9: ='Water-Meter'!E10 -> 114 | G9: ='Water-Meter'!AN9 -> 194 | H9: ='Utility report '!AC10 -> 86 | I9: ='Kit report'!F8 -> 540 | J9: ='Kit report'!X8 -> 1040
A10: 43744 | B10: =Gen!B16 -> 0.532 | C10: =Gen!AJ16 -> 115.65 | D10: =Gen!S16 -> 2478.9 | E10: =Gen!C16 -> 35107.69 | F10: ='Water-Meter'!E11 -> 126 | G10: ='Water-Meter'!AN10 -> 182 | H10: ='Utility report '!AC11 -> 114 | I10: ='Kit report'!F9 -> 444 | J10: ='Kit report'!X9 -> 1060
A11: 43745 | B11: =Gen!B17 -> 0.753 | C11: =Gen!AJ17 -> 74.81 | D11: =Gen!S17 -> 2276.44 | E11: =Gen!C17 -> 47513.14 | F11: ='Water-Meter'!E12 -> 116 | G11: ='Water-Meter'!AN11 -> 189 | H11: ='Utility report '!AC12 -> 107 | I11: ='Kit report'!F10 -> 528 | J11: ='Kit report'!X10 -> 1120
A12: 43746 | B12: =Gen!B18 -> 0.156 | C12: =Gen!AJ18 -> 94.01 | D12: =Gen!S18 -> 2242.4 | E12: =Gen!C18 -> 45161.89 | F12: ='Water-Meter'!E13 -> 120 | G12: ='Water-Meter'!AN12 -> 168 | H12: ='Utility report '!AC13 -> 52 | I12: ='Kit report'!F11 -> 492 | J12: ='Kit report'!X11 -> 900
A13: 43747 | B13: =Gen!B19 -> 0.442 | C13: =Gen!AJ19 -> 284.83 | D13: =Gen!S19 -> 2430.27 | E13: =Gen!C19 -> 42825.48 | F13: ='Water-Meter'!E14 -> 107 | G13: ='Water-Meter'!AN13 -> 182 | H13: ='Utility report '!AC14 -> 33 | I13: ='Kit report'!F12 -> 528 | J13: ='Kit report'!X12 -> 860
A14: 43748 | B14: =Gen!B20 -> 0.325 | C14: =Gen!AJ20 -> 106.04 | D14: =Gen!S20 -> 2463.77 | E14: =Gen!C20 -> 40110.38 | F14: ='Water-Meter'!E15 -> 123 | G14: ='Water-Meter'!AN14 -> 176 | H14: ='Utility report '!AC15 -> 82 | I14: ='Kit report'!F13 -> 528 | J14: ='Kit report'!X13 -> 780
A15: 43749 | B15: =Gen!B21 -> 0.455 | C15: =Gen!AJ21 -> 263.09 | D15: =Gen!S21 -> 2310.19 | E15: =Gen!C21 -> 37540.57 | F15: ='Water-Meter'!E16 -> 112 | G15: ='Water-Meter'!AN15 -> 163 | H15: ='Utility report '!AC16 -> 115 | I15: ='Kit report'!F14 -> 528 | J15: ='Kit report'!X14 -> 900
A16: 43750 | B16: =Gen!B22 -> 0.416 | C16: =Gen!AJ22 -> 309.36 | D16: =Gen!S22 -> 2429.17 | E16: =Gen!C22 -> 34967.29 | F16: ='Water-Meter'!E17 -> 128 | G16: ='Water-Meter'!AN16 -> 175 | H16: ='Utility report '!AC17 -> 21 | I16: ='Kit report'!F15 -> 552 | J16: ='Kit report'!X15 -> 860
... A27: 43761 | B27: =Gen!B33 -> 0.24 | C27: =Gen!AJ33 -> 311.34 | D27: =Gen!S33 -> 2148.3 | E27: =Gen!C33 -> 36676.61 | F27: ='Water-Meter'!E28 -> 113 | G27: ='Water-Meter'!AN27 -> 176 | H27: ='Utility report '!AC28 -> 60 | I27: ='Kit report'!F26 -> 540 | J27: ='Kit report'!X26 -> 800
A28: 43762 | B28: 0.091 | C28: =Gen!AJ34 -> 380.7 | D28: =Gen!S34 -> 2113.27 | E28: =Gen!C34 -> 44216.97 | F28: ='Water-Meter'!E29 -> 99 | G28: ='Water-Meter'!AN28 -> 180 | H28: ='Utility report '!AC29 -> 110 | I28: ='Kit report'!F27 -> 540 | J28: ='Kit report'!X27 -> 880
A29: 43763 | B29: =Gen!B35 -> 0.286 | C29: =Gen!AJ35 -> 273.37 | D29: =Gen!S35 -> 2104.52 | E29: =Gen!C35 -> 41723 | F29: ='Water-Meter'!E30 -> 111 | G29: ='Water-Meter'!AN29 -> 176 | H29: ='Utility report '!AC30 -> 76 | I29: ='Kit report'!F28 -> 480 | J29: ='Kit report'!X28 -> 780
A30: 43764 | B30: =Gen!B36 -> 0.545 | C30: =Gen!AJ36 -> 396.56 | D30: =Gen!S36 -> 2470.24 | E30: =Gen!C36 -> 39345.11 | F30: ='Water-Meter'!E31 -> 130 | G30: ='Water-Meter'!AN30 -> 174 | H30: ='Utility report '!AC31 -> 116 | I30: ='Kit report'!F29 -> 504 | J30: ='Kit report'!X29 -> 740
A31: 43765 | B31: =Gen!B37 -> 0.675 | C31: =Gen!AJ37 -> 280.63 | D31: =Gen!S37 -> 2323.74 | E31: =Gen!C37 -> 36478.31 | F31: ='Water-Meter'!E32 -> 114 | G31: ='Water-Meter'!AN31 -> 177 | H31: ='Utility report '!AC32 -> 117 | I31: ='Kit report'!F30 -> 480 | J31: ='Kit report'!X30 -> 960
A32: 43766 | B32: =Gen!B38 -> 0.273 | C32: =Gen!AJ38 -> 676.29 | D32: =Gen!S38 -> 2031.83 | E32: =Gen!C38 -> 44873.94 | F32: ='Water-Meter'!E33 -> 111 | G32: ='Water-Meter'!AN32 -> 173 | H32: ='Utility report '!AC33 -> 118 | I32: ='Kit report'!F31 -> 528 | J32: ='Kit report'!X31 -> 780
A33: 43767 | B33: =Gen!B39 -> 0.416 | C33: =Gen!AJ39 -> 120.7 | D33: =Gen!S39 -> 2131.37 | E33: =Gen!C39 -> 42165.82 | F33: ='Water-Meter'!E34 -> 100 | G33: ='Water-Meter'!AN33 -> 175 | H33: ='Utility report '!AC34 -> 116 | I33: ='Kit report'!F32 -> 468 | J33: ='Kit report'!X32 -> 820
A34: 43768 | B34: =Gen!B40 -> 0.429 | C34: =Gen!AJ40 -> 25.52 | D34: =Gen!S40 -> 2033.74 | E34: =Gen!C40 -> 39913.75 | F34: ='Water-Meter'!E35 -> 99 | G34: ='Water-Meter'!AN34 -> 179 | H34: ='Utility report '!AC35 -> 122 | I34: ='Kit report'!F33 -> 960 | J34: ='Kit report'!X33 -> 1880
A35: 43769 | B35: =Gen!B41 -> 0.325 | C35: =Gen!AJ41 -> 533.66 | D35: =Gen!S41 -> 2126.42 | E35: =Gen!C41 -> 37854.49 | F35: ='Water-Meter'!E36 -> 111 | G35: ='Water-Meter'!AN35 -> 177 | H35: ='Utility report '!AC36 -> 45 | I35: ='Kit report'!F34 -> 516 | J35: ='Kit report'!X34 -> 800
A36: 43770 | E36: =Gen!C42 -> 35194.41
