Workbook

Sheet HEP
A1: Site Name | B1: Day | C1: Month | D1: Year | E1: Total Electricity Kwh | F1: Electricity Tariff ($/Kwh) | G1: LPG (Kg) | H1: LPG $/Kg | I1: Water Utility Supply (m3) m3 | J1: Water Utility Supply (m3) $/m3 | K1: Room Nights
A2: Seychelles at Desroches Island | B2: 1 | C2: 11 | D2: 2019 | E2: ='FS Desroches'!F9 -> 11240 | F2: 11.35982 | G2: ='FS Desroches'!G9*0.51 -> 26.52 | H2: =17/0.073 -> 232.87671 | I2: ='FS Desroches'!E9 -> 95 | J2: 117.80822 | K2: ='FS Desroches'!C9 -> 32
A3: Seychelles at Desroches Island | B3: =B2+1 -> 2 | C3: 11 | D3: 2019 | E3: ='FS Desroches'!F10 -> 11490 | F3: =F2 -> 11.35982 | G3: ='FS Desroches'!G10*0.51 -> 26.52 | H3: =H2 -> 232.87671 | I3: ='FS Desroches'!E10 -> 102 | J3: =J2 -> 117.80822 | K3: ='FS Desroches'!C10 -> 37
A4: Seychelles at Desroches Island | B4: =B3+1 -> 3 | C4: 11 | D4: 2019 | E4: ='FS Desroches'!F11 -> 11810 | F4: =F3 -> 11.35982 | G4: ='FS Desroches'!G11*0.51 -> 28.56 | H4: =H3 -> 232.87671 | I4: ='FS Desroches'!E11 -> 97.6 | J4: =J3 -> 117.80822 | K4: ='FS Desroches'!C11 -> 36
A5: Seychelles at Desroches Island | B5: =B4+1 -> 4 | C5: 11 | D5: 2019 | E5: ='FS Desroches'!F12 -> 13210 | F5: =F4 -> 11.35982 | G5: ='FS Desroches'!G12*0.51 -> 34.17 | H5: =H4 -> 232.87671 | I5: ='FS Desroches'!E12 -> 92.6 | J5: =J4 -> 117.80822 | K5: ='FS Desroches'!C12 -> 36
A6: Seychelles at Desroches Island | B6: =B5+1 -> 5 | C6: 11 | D6: 2019 | E6: ='FS Desroches'!F13 -> 12730 | F6: =F5 -> 11.35982 | G6: ='FS Desroches'!G13*0.51 -> 26.52 | H6: =H5 -> 232.87671 | I6: ='FS Desroches'!E13 -> 100.3 | J6: =J5 -> 117.80822 | K6: ='FS Desroches'!C13 -> 42
A7: Seychelles at Desroches Island | B7: =B6+1 -> 6 | C7: 11 | D7: 2019 | E7: ='FS Desroches'!F14 -> 12660 | F7: =F6 -> 11.35982 | G7: ='FS Desroches'!G14*0.51 -> 32.13 | H7: =H6 -> 232.87671 | I7: ='FS Desroches'!E14 -> 88.5 | J7: =J6 -> 117.80822 | K7: ='FS Desroches'!C14 -> 45
A8: Seychelles at Desroches Island | B8: =B7+1 -> 7 | C8: 11 | D8: 2019 | E8: ='FS Desroches'!F15 -> 13530 | F8: =F7 -> 11.35982 | G8: ='FS Desroches'!G15*0.51 -> 26.52 | H8: =H7 -> 232.87671 | I8: ='FS Desroches'!E15 -> 101 | J8: =J7 -> 117.80822 | K8: ='FS Desroches'!C15 -> 50
A9: Seychelles at Desroches Island | B9: =B8+1 -> 8 | C9: 11 | D9: 2019 | E9: ='FS Desroches'!F16 -> 12860 | F9: =F8 -> 11.35982 | G9: ='FS Desroches'!G16*0.51 -> 30.09 | H9: =H8 -> 232.87671 | I9: ='FS Desroches'!E16 -> 95 | J9: =J8 -> 117.80822 | K9: ='FS Desroches'!C16 -> 44
A10: Seychelles at Desroches Island | B10: =B9+1 -> 9 | C10: 11 | D10: 2019 | E10: ='FS Desroches'!F17 -> 10880 | F10: =F9 -> 11.35982 | G10: ='FS Desroches'!G17*0.51 -> 32.13 | H10: =H9 -> 232.87671 | I10: ='FS Desroches'!E17 -> 87 | J10: =J9 -> 117.80822 | K10: ='FS Desroches'!C17 -> 34
A11: Seychelles at Desroches Island | B11: =B10+1 -> 10 | C11: 11 | D11: 2019 | E11: ='FS Desroches'!F18 -> 11880 | F11: =F10 -> 11.35982 | G11: ='FS Desroches'!G18*0.51 -> 32.13 | H11: =H10 -> 232.87671 | I11: ='FS Desroches'!E18 -> 82.4 | J11: =J10 -> 117.80822 | K11: ='FS Desroches'!C18 -> 38
A12: Seychelles at Desroches Island | B12: =B11+1 -> 11 | C12: 11 | D12: 2019 | E12: ='FS Desroches'!F19 -> 12500 | F12: =F11 -> 11.35982 | G12: ='FS Desroches'!G19*0.51 -> 35.7 | H12: =H11 -> 232.87671 | I12: ='FS Desroches'!E19 -> 85.8 | J12: =J11 -> 117.80822 | K12: ='FS Desroches'!C19 -> 36
A13: Seychelles at Desroches Island | B13: =B12+1 -> 12 | C13: 11 | D13: 2019 | E13: ='FS Desroches'!F20 -> 12050 | F13: =F12 -> 11.35982 | G13: ='FS Desroches'!G20*0.51 -> 34.17 | H13: =H12 -> 232.87671 | I13: ='FS Desroches'!E20 -> 95.5 | J13: =J12 -> 117.80822 | K13: ='FS Desroches'!C20 -> 28
A14: Seychelles at Desroches Island | B14: =B13+1 -> 13 | C14: 11 | D14: 2019 | E14: ='FS Desroches'!F21 -> 12590 | F14: =F13 -> 11.35982 | G14: ='FS Desroches'!G21*0.51 -> 28.56 | H14: =H13 -> 232.87671 | I14: ='FS Desroches'!E21 -> 104 | J14: =J13 -> 117.80822 | K14: ='FS Desroches'!C21 -> 41
... A32: Seychelles at Desroches Island | B32: =B31+1 -> 31 | C32: 11 | D32: 2019 | E32: ='FS Desroches'!F39 -> 0 | F32: =F31 -> 11.35982 | G32: ='FS Desroches'!G39*0.51 -> 0 | H32: =H31 -> 232.87671 | I32: ='FS Desroches'!E39 -> 0 | J32: =J31 -> 117.80822 | K32: ='FS Desroches'!C39 -> 0

Sheet FS Desroches
B2: Month | C2: 43739 | D2: Cost | E2: Water/M³ | F2: 8.6 | G2: electricity /kw | H2: 0.65 | I2: Gas/Kg Scr | J2: 15 | M2: Budget | N2: Water $
N3: electricity $
B4: Occ % forecast for the Year : | N4: Gas Scr
A7: Date | B7: Occupancy | E7: Daily consumption | H7: Consumption / Occ .Room | K7: Total consumption Cost | N7: Cost /GN | Q7: weather & Event
B8: Occ % | C8: Room Night | D8: Guest Night | E8: water (m3) | F8: Electricity (kw) | G8: Gas (L) | H8: water (m3) | I8: Electricity (kw) | J8: Gas (L) | K8: water (m3) | L8: Electricity (kw) | M8: Gas (KG) | N8: water (m3) | O8: Electricity (kw) | P8: Gas (KG) | Q8: Temp | R8: Weather | S8: Event
A9: 43770 | B9: 0.39 | C9: 32 | D9: 91 | E9: 95 | F9: 11240 | G9: 52 | H9: =E9/C9 -> 2.96875 | I9: =F9/C9 -> 351.25 | J9: =G9/C9 -> 1.625 | K9: =$F$2*E9 -> 817 | L9: =$H$2*F9 -> 7306 | M9: =$J$2*G9*0.51 -> 397.8 | N9: =K9/D9 -> 8.978022 | O9: =L9/D9 -> 80.285714 | P9: =M9/D9 -> 4.3714286 | Q9: 24.9 | R9: raining
A10: 43771 | B10: 0.45 | C10: 37 | D10: 96 | E10: 102 | F10: 11490 | G10: 52 | H10: =E10/C10 -> 2.7567568 | I10: =F10/C10 -> 310.54054 | J10: =G10/C10 -> 1.4054054 | K10: =$F$2*E10 -> 877.2 | L10: =$H$2*F10 -> 7468.5 | M10: =$J$2*G10*0.51 -> 397.8 | N10: =K10/D10 -> 9.1375 | O10: =L10/D10 -> 77.796875 | P10: =M10/D10 -> 4.14375 | Q10: 25.7 | R10: cloudy
A11: 43772 | B11: 0.41 | C11: 36 | D11: 83 | E11: 97.6 | F11: 11810 | G11: 56 | H11: =E11/C11 -> 2.7111111 | I11: =F11/C11 -> 328.05556 | J11: =G11/C11 -> 1.5555556 | K11: =$F$2*E11 -> 839.36 | L11: =$H$2*F11 -> 7676.5 | M11: =$J$2*G11*0.51 -> 428.4 | N11: =K11/D11 -> 10.112771 | O11: =L11/D11 -> 92.487952 | P11: =M11/D11 -> 5.1614458 | Q11: 27.2 | R11: sunny
A12: 43773 | B12: 0.42 | C12: 36 | D12: 82 | E12: 92.6 | F12: 13210 | G12: 67 | H12: =E12/C12 -> 2.5722222 | I12: =F12/C12 -> 366.94444 | J12: =G12/C12 -> 1.8611111 | K12: =$F$2*E12 -> 796.36 | L12: =$H$2*F12 -> 8586.5 | M12: =$J$2*G12*0.51 -> 512.55 | N12: =K12/D12 -> 9.7117073 | O12: =L12/D12 -> 104.71341 | P12: =M12/D12 -> 6.2506098 | Q12: 26 | R12: sunny
A13: 43774 | B13: 0.52 | C13: 42 | D13: 99 | E13: 100.3 | F13: 12730 | G13: 52 | H13: =E13/C13 -> 2.3880952 | I13: =F13/C13 -> 303.09524 | J13: =G13/C13 -> 1.2380952 | K13: =$F$2*E13 -> 862.58 | L13: =$H$2*F13 -> 8274.5 | M13: =$J$2*G13*0.51 -> 397.8 | N13: =K13/D13 -> 8.7129293 | O13: =L13/D13 -> 83.580808 | P13: =M13/D13 -> 4.0181818 | Q13: 26.6 | R13: sunny
A14: 43775 | B14: 0.55 | C14: 45 | D14: 93 | E14: 88.5 | F14: 12660 | G14: 63 | H14: =E14/C14 -> 1.9666667 | I14: =F14/C14 -> 281.33333 | J14: =G14/C14 -> 1.4 | K14: =$F$2*E14 -> 761.1 | L14: =$H$2*F14 -> 8229 | M14: =$J$2*G14*0.51 -> 481.95 | N14: =K14/D14 -> 8.183871 | O14: =L14/D14 -> 88.483871 | P14: =M14/D14 -> 5.1822581 | Q14: 27.2 | R14: sunny
A15: 43776 | B15: 0.63 | C15: 50 | D15: 107 | E15: 101 | F15: 13530 | G15: 52 | H15: =E15/C15 -> 2.02 | I15: =F15/C15 -> 270.6 | J15: =G15/C15 -> 1.04 | K15: =$F$2*E15 -> 868.6 | L15: =$H$2*F15 -> 8794.5 | M15: =$J$2*G15*0.51 -> 397.8 | N15: =K15/D15 -> 8.117757 | O15: =L15/D15 -> 82.191589 | P15: =M15/D15 -> 3.717757 | Q15: 27.3 | R15: sunny
A16: 43777 | B16: 0.55 | C16: 44 | D16: 99 | E16: 95 | F16: 12860 | G16: 59 | H16: =E16/C16 -> 2.1590909 | I16: =F16/C16 -> 292.27273 | J16: =G16/C16 -> 1.3409091 | K16: =$F$2*E16 -> 817 | L16: =$H$2*F16 -> 8359 | M16: =$J$2*G16*0.51 -> 451.35 | N16: =K16/D16 -> 8.2525253 | O16: =L16/D16 -> 84.434343 | P16: =M16/D16 -> 4.5590909 | Q16: 26.1 | R16: cloudy
A17: 43778 | B17: 0.37 | C17: 34 | D17: 80 | E17: 87 | F17: 10880 | G17: 63 | H17: =E17/C17 -> 2.5588235 | I17: =F17/C17 -> 320 | J17: =G17/C17 -> 1.8529412 | K17: =$F$2*E17 -> 748.2 | L17: =$H$2*F17 -> 7072 | M17: =$J$2*G17*0.51 -> 481.95 | N17: =K17/D17 -> 9.3525 | O17: =L17/D17 -> 88.4 | P17: =M17/D17 -> 6.024375 | Q17: 27.2 | R17: cloudy
A18: 43779 | B18: 0.41 | C18: 38 | D18: 87 | E18: 82.4 | F18: 11880 | G18: 63 | H18: =E18/C18 -> 2.1684211 | I18: =F18/C18 -> 312.63158 | J18: =G18/C18 -> 1.6578947 | K18: =$F$2*E18 -> 708.64 | L18: =$H$2*F18 -> 7722 | M18: =$J$2*G18*0.51 -> 481.95 | N18: =K18/D18 -> 8.1452874 | O18: =L18/D18 -> 88.758621 | P18: =M18/D18 -> 5.5396552 | Q18: 26.8 | R18: cloudy
A19: 43780 | B19: 0.35 | C19: 36 | D19: 83 | E19: 85.8 | F19: 12500 | G19: 70 | H19: =E19/C19 -> 2.3833333 | I19: =F19/C19 -> 347.22222 | J19: =G19/C19 -> 1.9444444 | K19: =$F$2*E19 -> 737.88 | L19: =$H$2*F19 -> 8125 | M19: =$J$2*G19*0.51 -> 535.5 | N19: =K19/D19 -> 8.8901205 | O19: =L19/D19 -> 97.891566 | P19: =M19/D19 -> 6.4518072 | Q19: 26.4 | R19: cloudy
A20: 43781 | B20: 0.28 | C20: 28 | D20: 60 | E20: 95.5 | F20: 12050 | G20: 67 | H20: =E20/C20 -> 3.4107143 | I20: =F20/C20 -> 430.35714 | J20: =G20/C20 -> 2.3928571 | K20: =$F$2*E20 -> 821.3 | L20: =$H$2*F20 -> 7832.5 | M20: =$J$2*G20*0.51 -> 512.55 | N20: =K20/D20 -> 13.688333 | O20: =L20/D20 -> 130.54167 | P20: =M20/D20 -> 8.5425 | Q20: 27.2 | R20: sunny
... A23: 43784 | B23: 0.4 | C23: 39 | D23: 89 | E23: 95.2 | F23: 13010 | G23: 63 | H23: =E23/C23 -> 2.4410256 | I23: =F23/C23 -> 333.58974 | J23: =G23/C23 -> 1.6153846 | K23: =$F$2*E23 -> 818.72 | L23: =$H$2*F23 -> 8456.5 | M23: =$J$2*G23*0.51 -> 481.95 | N23: =K23/D23 -> 9.1991011 | O23: =L23/D23 -> 95.016854 | P23: =M23/D23 -> 5.4151685 | Q23: 27 | R23: sunny
A24: 43785 | H24: =E24/C24 -> #DIV/0! | I24: =F24/C24 -> #DIV/0! | J24: =G24/C24 -> #DIV/0! | K24: =$F$2*E24 -> 0 | L24: =$H$2*F24 -> 0 | M24: =$J$2*G24*0.51 -> 0 | N24: =K24/D24 -> #DIV/0! | O24: =L24/D24 -> #DIV/0! | P24: =M24/D24 -> #DIV/0!
A25: 43786 | H25: =E25/C25 -> #DIV/0! | I25: =F25/C25 -> #DIV/0! | J25: =G25/C25 -> #DIV/0! | K25: =$F$2*E25 -> 0 | L25: =$H$2*F25 -> 0 | M25: =$J$2*G25*0.51 -> 0 | N25: =K25/D25 -> #DIV/0! | O25: =L25/D25 -> #DIV/0! | P25: =M25/D25 -> #DIV/0!
A26: 43787 | H26: =E26/C26 -> #DIV/0! | I26: =F26/C26 -> #DIV/0! | J26: =G26/C26 -> #DIV/0! | K26: =$F$2*E26 -> 0 | L26: =$H$2*F26 -> 0 | M26: =$J$2*G26*0.51 -> 0 | N26: =K26/D26 -> #DIV/0! | O26: =L26/D26 -> #DIV/0! | P26: =M26/D26 -> #DIV/0!
A27: 43788 | H27: =E27/C27 -> #DIV/0! | I27: =F27/C27 -> #DIV/0! | J27: =G27/C27 -> #DIV/0! | K27: =$F$2*E27 -> 0 | L27: =$H$2*F27 -> 0 | M27: =$J$2*G27*0.51 -> 0 | N27: =K27/D27 -> #DIV/0! | O27: =L27/D27 -> #DIV/0! | P27: =M27/D27 -> #DIV/0!
A28: 43789 | H28: =E28/C28 -> #DIV/0! | I28: =F28/C28 -> #DIV/0! | J28: =G28/C28 -> #DIV/0! | K28: =$F$2*E28 -> 0 | L28: =$H$2*F28 -> 0 | M28: =$J$2*G28*0.51 -> 0 | N28: =K28/D28 -> #DIV/0! | O28: =L28/D28 -> #DIV/0! | P28: =M28/D28 -> #DIV/0!
A29: 43790 | H29: =E29/C29 -> #DIV/0! | I29: =F29/C29 -> #DIV/0! | J29: =G29/C29 -> #DIV/0! | K29: =$F$2*E29 -> 0 | L29: =$H$2*F29 -> 0 | M29: =$J$2*G29*0.51 -> 0 | N29: =K29/D29 -> #DIV/0! | O29: =L29/D29 -> #DIV/0! | P29: =M29/D29 -> #DIV/0!
A30: 43791 | H30: =E30/C30 -> #DIV/0! | I30: 297.1 | J30: =G30/C30 -> #DIV/0! | K30: =$F$2*E30 -> 0 | L30: =$H$2*F30 -> 0 | M30: =$J$2*G30*0.51 -> 0 | N30: =K30/D30 -> #DIV/0! | O30: =L30/D30 -> #DIV/0! | P30: =M30/D30 -> #DIV/0!
A31: 43792 | H31: =E31/C31 -> #DIV/0! | I31: 424.07 | J31: =G31/C31 -> #DIV/0! | K31: =$F$2*E31 -> 0 | L31: =$H$2*F31 -> 0 | M31: =$J$2*G31*0.51 -> 0 | N31: =K31/D31 -> #DIV/0! | O31: =L31/D31 -> #DIV/0! | P31: =M31/D31 -> #DIV/0!
A32: 43793 | H32: =E32/C32 -> #DIV/0! | I32: =F32/C32 -> #DIV/0! | J32: =G32/C32 -> #DIV/0! | K32: =$F$2*E32 -> 0 | L32: =$H$2*F32 -> 0 | M32: =$J$2*G32*0.51 -> 0 | N32: =K32/D32 -> #DIV/0! | O32: =L32/D32 -> #DIV/0! | P32: =M32/D32 -> #DIV/0!
A33: 43794 | H33: =E33/C33 -> #DIV/0! | I33: =F33/C33 -> #DIV/0! | J33: =G33/C33 -> #DIV/0! | K33: =$F$2*E33 -> 0 | L33: =$H$2*F33 -> 0 | M33: =$J$2*G33*0.51 -> 0 | N33: =K33/D33 -> #DIV/0! | O33: =L33/D33 -> #DIV/0! | P33: =M33/D33 -> #DIV/0!
A34: 43795 | H34: =E34/C34 -> #DIV/0! | I34: =F34/C34 -> #DIV/0! | J34: =G34/C34 -> #DIV/0! | K34: =$F$2*E34 -> 0 | L34: =$H$2*F34 -> 0 | M34: =$J$2*G34*0.51 -> 0 | N34: =K34/D34 -> #DIV/0! | O34: =L34/D34 -> #DIV/0! | P34: =M34/D34 -> #DIV/0!
A35: 43796 | H35: =E35/C35 -> #DIV/0! | I35: =F35/C35 -> #DIV/0! | J35: =G35/C35 -> #DIV/0! | K35: =$F$2*E35 -> 0 | L35: =$H$2*F35 -> 0 | M35: =$J$2*G35*0.51 -> 0 | N35: =K35/D35 -> #DIV/0! | O35: =L35/D35 -> #DIV/0! | P35: =M35/D35 -> #DIV/0!
A36: 43797 | H36: =E36/C36 -> #DIV/0! | I36: =F36/C36 -> #DIV/0! | J36: =G36/C36 -> #DIV/0! | K36: =$F$2*E36 -> 0 | L36: =$H$2*F36 -> 0 | M36: =$J$2*G36*0.51 -> 0 | N36: =K36/D36 -> #DIV/0! | O36: =L36/D36 -> #DIV/0! | P36: =M36/D36 -> #DIV/0!
A37: 43798 | H37: =E37/C37 -> #DIV/0! | I37: =F37/C37 -> #DIV/0! | J37: =G37/C37 -> #DIV/0! | K37: =$F$2*E37 -> 0 | L37: =$H$2*F37 -> 0 | M37: =$J$2*G37*0.51 -> 0 | N37: =K37/D37 -> #DIV/0! | O37: =L37/D37 -> #DIV/0! | P37: =M37/D37 -> #DIV/0!
A38: 43799 | H38: =E38/C38 -> #DIV/0! | I38: =F38/C38 -> #DIV/0! | J38: =G38/C38 -> #DIV/0! | K38: =$F$2*E38 -> 0 | L38: =$H$2*F38 -> 0 | M38: =$J$2*G38*0.51 -> 0 | N38: =K38/D38 -> #DIV/0! | O38: =L38/D38 -> #DIV/0! | P38: =M38/D38 -> #DIV/0!
H39: =E39/C39 -> #DIV/0! | I39: =F39/C39 -> #DIV/0! | J39: =G39/C39 -> #DIV/0! | K39: =$F$2*E39 -> 0 | L39: =$H$2*F39 -> 0 | M39: =$J$2*G39*0.51 -> 0 | N39: =K39/D39 -> #DIV/0! | O39: =L39/D39 -> #DIV/0! | P39: =M39/D39 -> #DIV/0!
H40: =E40/C40 -> #DIV/0! | I40: =F40/C40 -> #DIV/0! | J40: =G40/C40 -> #DIV/0! | K40: =$F$2*E40 -> 0 | L40: =$H$2*F40 -> 0 | M40: =$J$2*G40*0.51 -> 0 | N40: =K40/D40 -> #DIV/0! | O40: =L40/D40 -> #DIV/0! | P40: =M40/D40 -> #DIV/0!
