Workbook

Sheet Total
A1: Site Name | B1: Day | C1: Month | D1: Year | E1: Total Electricity Kwh | F1: Electricity Tariff ($/Kwh) | G1: LPG (Kg) | H1: LPG $/Kg | I1: Water Utility Supply (m3) m3 | J1: Water Utility Supply (m3) $/m3 | K1: Room Nights | L1: Utilities day cost dh
A2: Serengeti | B2: 1 | C2: 11 | D2: 2019 | E2: ='UTILITY REPORT 1'!F3 -> 5703 | F2: =('UTILITY REPORT 1'!E3*'UTILITY REPORT 1'!D3)/'UTILITY REPORT 1'!F3 -> 0.42050149 | G2: =IF('Utility summery'!M6<0,"0",'Utility summery'!M6) -> 208.34 | H2: 0 | I2: =IF('UTILITY REPORT 1'!G3<0,"0",'UTILITY REPORT 1'!G3) -> 128 | J2: 0 | K2: ='UTILITY REPORT 1'!C3 -> 66 | L2: =E2*F2+G2*H2+#REF!*#REF!+I2*J2 -> #REF!
A3: Serengeti | B3: =B2+1 -> 2 | C3: 11 | D3: 2019 | E3: ='UTILITY REPORT 1'!F4 -> 6052 | F3: =('UTILITY REPORT 1'!E4*'UTILITY REPORT 1'!D4)/'UTILITY REPORT 1'!F4 -> 0.41351124 | G3: =IF('Utility summery'!M7<0,"0",'Utility summery'!M7) -> 101.376 | H3: 0 | I3: =IF('UTILITY REPORT 1'!G4<0,"0",'UTILITY REPORT 1'!G4) -> 139 | J3: 0 | K3: ='UTILITY REPORT 1'!C4 -> 58 | L3: =E3*F3+G3*H3+#REF!*#REF!+I3*J3 -> #REF!
A4: Serengeti | B4: =B3+1 -> 3 | C4: 11 | D4: 2019 | E4: ='UTILITY REPORT 1'!F5 -> 5227 | F4: =('UTILITY REPORT 1'!E5*'UTILITY REPORT 1'!D5)/'UTILITY REPORT 1'!F5 -> 0.39924048 | G4: =IF('Utility summery'!M8<0,"0",'Utility summery'!M8) -> 101.464 | H4: 0 | I4: =IF('UTILITY REPORT 1'!G5<0,"0",'UTILITY REPORT 1'!G5) -> 132 | J4: 0 | K4: ='UTILITY REPORT 1'!C5 -> 9 | L4: =E4*F4+G4*H4+#REF!*#REF!+I4*J4 -> #REF!
A5: Serengeti | B5: =B4+1 -> 4 | C5: 11 | D5: 2019 | E5: ='UTILITY REPORT 1'!F6 -> 4812 | F5: =('UTILITY REPORT 1'!E6*'UTILITY REPORT 1'!D6)/'UTILITY REPORT 1'!F6 -> 0.38117415 | G5: =IF('Utility summery'!M9<0,"0",'Utility summery'!M9) -> 132.616 | H5: 0 | I5: =IF('UTILITY REPORT 1'!G6<0,"0",'UTILITY REPORT 1'!G6) -> 100 | J5: 0 | K5: ='UTILITY REPORT 1'!C6 -> 10 | L5: =E5*F5+G5*H5+#REF!*#REF!+I5*J5 -> #REF!
A6: Serengeti | B6: =B5+1 -> 5 | C6: 11 | D6: 2019 | E6: ='UTILITY REPORT 1'!F7 -> 5035 | F6: =('UTILITY REPORT 1'!E7*'UTILITY REPORT 1'!D7)/'UTILITY REPORT 1'!F7 -> 0.42059583 | G6: =IF('Utility summery'!M10<0,"0",'Utility summery'!M10) -> 147.18 | H6: 0 | I6: =IF('UTILITY REPORT 1'!G7<0,"0",'UTILITY REPORT 1'!G7) -> 119 | J6: 0 | K6: ='UTILITY REPORT 1'!C7 -> 25 | L6: =E6*F6+G6*H6+#REF!*#REF!+I6*J6 -> #REF!
A7: Serengeti | B7: =B6+1 -> 6 | C7: 11 | D7: 2019 | E7: ='UTILITY REPORT 1'!F8 -> 5420 | F7: =('UTILITY REPORT 1'!E8*'UTILITY REPORT 1'!D8)/'UTILITY REPORT 1'!F8 -> 0.44939668 | G7: =IF('Utility summery'!M11<0,"0",'Utility summery'!M11) -> 144.672 | H7: 0 | I7: =IF('UTILITY REPORT 1'!G8<0,"0",'UTILITY REPORT 1'!G8) -> 110 | J7: 0 | K7: ='UTILITY REPORT 1'!C8 -> 24 | L7: =E7*F7+G7*H7+#REF!*#REF!+I7*J7 -> #REF!
A8: Serengeti | B8: =B7+1 -> 7 | C8: 11 | D8: 2019 | E8: ='UTILITY REPORT 1'!F9 -> 5338 | F8: =('UTILITY REPORT 1'!E9*'UTILITY REPORT 1'!D9)/'UTILITY REPORT 1'!F9 -> 0.41775197 | G8: =IF('Utility summery'!M12<0,"0",'Utility summery'!M12) -> 149.072 | H8: 0 | I8: =IF('UTILITY REPORT 1'!G9<0,"0",'UTILITY REPORT 1'!G9) -> 95 | J8: 0 | K8: ='UTILITY REPORT 1'!C9 -> 17 | L8: =E8*F8+G8*H8+#REF!*#REF!+I8*J8 -> #REF!
A9: Serengeti | B9: =B8+1 -> 8 | C9: 11 | D9: 2019 | E9: ='UTILITY REPORT 1'!F10 -> 5670 | F9: =('UTILITY REPORT 1'!E10*'UTILITY REPORT 1'!D10)/'UTILITY REPORT 1'!F10 -> 0.37044974 | G9: =IF('Utility summery'!M13<0,"0",'Utility summery'!M13) -> 152.064 | H9: 0 | I9: =IF('UTILITY REPORT 1'!G10<0,"0",'UTILITY REPORT 1'!G10) -> 120 | J9: 0 | K9: ='UTILITY REPORT 1'!C10 -> 13 | L9: =E9*F9+G9*H9+#REF!*#REF!+I9*J9 -> #REF!
A10: Serengeti | B10: =B9+1 -> 9 | C10: 11 | D10: 2019 | E10: ='UTILITY REPORT 1'!F11 -> 5594 | F10: =('UTILITY REPORT 1'!E11*'UTILITY REPORT 1'!D11)/'UTILITY REPORT 1'!F11 -> 0.3807955 | G10: =IF('Utility summery'!M14<0,"0",'Utility summery'!M14) -> 152.284 | H10: 0 | I10: =IF('UTILITY REPORT 1'!G11<0,"0",'UTILITY REPORT 1'!G11) -> 96 | J10: 0 | K10: ='UTILITY REPORT 1'!C11 -> 13 | L10: =E10*F10+G10*H10+#REF!*#REF!+I10*J10 -> #REF!
A11: Serengeti | B11: =B10+1 -> 10 | C11: 11 | D11: 2019 | E11: ='UTILITY REPORT 1'!F12 -> 5487 | F11: =('UTILITY REPORT 1'!E12*'UTILITY REPORT 1'!D12)/'UTILITY REPORT 1'!F12 -> 0.4085657 | G11: =IF('Utility summery'!M15<0,"0",'Utility summery'!M15) -> 103.488 | H11: 0 | I11: =IF('UTILITY REPORT 1'!G12<0,"0",'UTILITY REPORT 1'!G12) -> 124 | J11: 0 | K11: ='UTILITY REPORT 1'!C12 -> 36 | L11: =E11*F11+G11*H11+#REF!*#REF!+I11*J11 -> #REF!
A12: Serengeti | B12: =B11+1 -> 11 | C12: 11 | D12: 2019 | E12: ='UTILITY REPORT 1'!F13 -> 6542 | F12: =('UTILITY REPORT 1'!E13*'UTILITY REPORT 1'!D13)/'UTILITY REPORT 1'!F13 -> 0.4054494 | G12: =IF('Utility summery'!M16<0,"0",'Utility summery'!M16) -> 101.772 | H12: 0 | I12: =IF('UTILITY REPORT 1'!G13<0,"0",'UTILITY REPORT 1'!G13) -> 131 | J12: 0 | K12: ='UTILITY REPORT 1'!C13 -> 73 | L12: =E12*F12+G12*H12+#REF!*#REF!+I12*J12 -> #REF!
A13: Serengeti | B13: =B12+1 -> 12 | C13: 11 | D13: 2019 | E13: ='UTILITY REPORT 1'!F14 -> 6667 | F13: =('UTILITY REPORT 1'!E14*'UTILITY REPORT 1'!D14)/'UTILITY REPORT 1'!F14 -> 0.3880996 | G13: =IF('Utility summery'!M17<0,"0",'Utility summery'!M17) -> 115.192 | H13: 0 | I13: =IF('UTILITY REPORT 1'!G14<0,"0",'UTILITY REPORT 1'!G14) -> 136 | J13: 0 | K13: ='UTILITY REPORT 1'!C14 -> 73 | L13: =E13*F13+G13*H13+#REF!*#REF!+I13*J13 -> #REF!
A14: Serengeti | B14: =B13+1 -> 13 | C14: 11 | D14: 2019 | E14: ='UTILITY REPORT 1'!F15 -> 5860 | F14: =('UTILITY REPORT 1'!E15*'UTILITY REPORT 1'!D15)/'UTILITY REPORT 1'!F15 -> 0.38045734 | G14: =IF('Utility summery'!M18<0,"0",'Utility summery'!M18) -> 98.472 | H14: 0 | I14: =IF('UTILITY REPORT 1'!G15<0,"0",'UTILITY REPORT 1'!G15) -> 123 | J14: 0 | K14: ='UTILITY REPORT 1'!C15 -> 39 | L14: =E14*F14+G14*H14+#REF!*#REF!+I14*J14 -> #REF!
... A31: Serengeti | B31: =B30+1 -> 30 | C31: 11 | D31: 2019 | E31: ='UTILITY REPORT 1'!F32 -> 0 | F31: =('UTILITY REPORT 1'!E32*'UTILITY REPORT 1'!D32)/'UTILITY REPORT 1'!F32 -> #DIV/0! | G31: =IF('Utility summery'!M35<0,"0",'Utility summery'!M35) -> 0 | H31: 0 | I31: =IF('UTILITY REPORT 1'!G32<0,"0",'UTILITY REPORT 1'!G32) -> 0 | J31: 0 | K31: ='UTILITY REPORT 1'!C32 -> 0 | L31: =E31*F31+G31*H31+#REF!*#REF!+I31*J31 -> #DIV/0!
A32: Serengeti | B32: 1 | C32: 12 | D32: 2019 | E32: ='UTILITY REPORT 1'!F33 -> 0 | F32: =('UTILITY REPORT 1'!E33*'UTILITY REPORT 1'!D33)/'UTILITY REPORT 1'!F33 -> #DIV/0! | G32: =IF('Utility summery'!M36<0,"0",'Utility summery'!M36) -> 0 | H32: 0 | I32: =IF('UTILITY REPORT 1'!G33<0,"0",'UTILITY REPORT 1'!G33) -> 0 | J32: 0 | K32: ='UTILITY REPORT 1'!C33 -> 0

Sheet Submetering
A1: Site Name | B1: Day | C1: Month | D1: Year | E1: Transport Consumption (LT) | F1: Generators Consumption (LT) | G1: Total Electricity Kwh | H1: Kitchen (KWh) | I1: Laundry (KWh) | J1: STP (M3) | K1: RO prodution (M3) | L1: Amani Restaurant (M3) | M1: Kitchen (M3) | N1: Laundry (M3) | O1: Laundry (M3) | P1: Total water Consumption (M3) | Q1: Borehole #1 (M3) | R1: Borehole #2 (M3) | S1: Borehole #3 (M3) | T1: Borehole #4 (M3) | U1: Borehole #5 (M3) | V1: Borehole #6 (M3) | W1: Total Bore holes production (M3) | X1: Room Nights
A2: Serengeti | B2: 1 | C2: 11 | D2: 2019 | E2: ='UTILITY REPORT 1'!I3 -> 69.05 | F2: ='UTILITY REPORT 1'!E3 -> 2398.12 | G2: ='UTILITY REPORT 1'!F3 -> 5703 | H2: =IF('Kit report'!F4<0,"0",'Kit report'!F4) -> 516 | I2: =IF('Kit report'!X4<0,"0",'Kit report'!X4) -> 860 | J2: =IF('Utility summery'!H6<0,"0",'Utility summery'!H6) -> 36 | K2: =IF('UTILITY REPORT 1'!H3<0,"0",'UTILITY REPORT 1'!H3) -> 120 | L2: ='Water-Meter'!K6 -> 3 | M2: ='Water-Meter'!H6 -> 16 | N2: ='Water-Meter'!Q6 -> 13 | O2: =K2*E2+H2*I2+#REF!*#REF!+J2*L2 -> #REF! | P2: ='Water-Meter'!E6 -> 128 | Q2: =IF('Water-Meter'!U6<0,"0",'Water-Meter'!U6) -> 30 | R2: =IF('Water-Meter'!X6<0,"0",'Water-Meter'!X6) -> 50 | S2: =IF('Water-Meter'!AA6<0,"0",'Water-Meter'!AA6) -> 65 | T2: =IF('Water-Meter'!AD6<0,"0",'Water-Meter'!AD6) -> 7 | U2: =IF('Water-Meter'!AG6<0,"0",'Water-Meter'!AG6) -> 14 | V2: =IF('Water-Meter'!AJ6<0,"0",'Water-Meter'!AJ6) -> 19 | W2: ='Water-Meter'!AN6 -> 185 | X2: =Total!K2 -> 66
A3: Serengeti | B3: =B2+1 -> 2 | C3: 11 | D3: 2019 | E3: ='UTILITY REPORT 1'!I4 -> 659.55 | F3: ='UTILITY REPORT 1'!E4 -> 2502.57 | G3: ='UTILITY REPORT 1'!F4 -> 6052 | H3: =IF('Kit report'!F5<0,"0",'Kit report'!F5) -> 516 | I3: =IF('Kit report'!X5<0,"0",'Kit report'!X5) -> 900 | J3: =IF('Utility summery'!H7<0,"0",'Utility summery'!H7) -> 30 | K3: =IF('UTILITY REPORT 1'!H4<0,"0",'UTILITY REPORT 1'!H4) -> 120 | L3: ='Water-Meter'!K7 -> 3 | M3: ='Water-Meter'!H7 -> 23 | N3: ='Water-Meter'!Q7 -> 8 | O3: =K3*E3+H3*I3+#REF!*#REF!+J3*L3 -> #REF! | P3: ='Water-Meter'!E7 -> 139 | Q3: =IF('Water-Meter'!U7<0,"0",'Water-Meter'!U7) -> 29 | R3: =IF('Water-Meter'!X7<0,"0",'Water-Meter'!X7) -> 51 | S3: =IF('Water-Meter'!AA7<0,"0",'Water-Meter'!AA7) -> 55 | T3: =IF('Water-Meter'!AD7<0,"0",'Water-Meter'!AD7) -> 7 | U3: =IF('Water-Meter'!AG7<0,"0",'Water-Meter'!AG7) -> 14 | V3: =IF('Water-Meter'!AJ7<0,"0",'Water-Meter'!AJ7) -> 19 | W3: ='Water-Meter'!AN7 -> 175 | X3: =Total!K3 -> 58
A4: Serengeti | B4: =B3+1 -> 3 | C4: 11 | D4: 2019 | E4: ='UTILITY REPORT 1'!I5 -> 261.5 | F4: ='UTILITY REPORT 1'!E5 -> 2086.83 | G4: ='UTILITY REPORT 1'!F5 -> 5227 | H4: =IF('Kit report'!F6<0,"0",'Kit report'!F6) -> 492 | I4: =IF('Kit report'!X6<0,"0",'Kit report'!X6) -> 820 | J4: =IF('Utility summery'!H8<0,"0",'Utility summery'!H8) -> 38 | K4: =IF('UTILITY REPORT 1'!H5<0,"0",'UTILITY REPORT 1'!H5) -> 125 | L4: ='Water-Meter'!K8 -> 6 | M4: ='Water-Meter'!H8 -> 15 | N4: ='Water-Meter'!Q8 -> 13 | O4: =K4*E4+H4*I4+#REF!*#REF!+J4*L4 -> #REF! | P4: ='Water-Meter'!E8 -> 132 | Q4: =IF('Water-Meter'!U8<0,"0",'Water-Meter'!U8) -> 29 | R4: =IF('Water-Meter'!X8<0,"0",'Water-Meter'!X8) -> 51 | S4: =IF('Water-Meter'!AA8<0,"0",'Water-Meter'!AA8) -> 55 | T4: =IF('Water-Meter'!AD8<0,"0",'Water-Meter'!AD8) -> 7 | U4: =IF('Water-Meter'!AG8<0,"0",'Water-Meter'!AG8) -> 14 | V4: =IF('Water-Meter'!AJ8<0,"0",'Water-Meter'!AJ8) -> 20 | W4: ='Water-Meter'!AN8 -> 176 | X4: =Total!K4 -> 9
A5: Serengeti | B5: =B4+1 -> 4 | C5: 11 | D5: 2019 | E5: ='UTILITY REPORT 1'!I6 -> 17.39 | F5: ='UTILITY REPORT 1'!E6 -> 1834.21 | G5: ='UTILITY REPORT 1'!F6 -> 4812 | H5: =IF('Kit report'!F7<0,"0",'Kit report'!F7) -> 552 | I5: =IF('Kit report'!X7<0,"0",'Kit report'!X7) -> 1060 | J5: =IF('Utility summery'!H9<0,"0",'Utility summery'!H9) -> 40 | K5: =IF('UTILITY REPORT 1'!H6<0,"0",'UTILITY REPORT 1'!H6) -> 32 | L5: ='Water-Meter'!K9 -> 4 | M5: ='Water-Meter'!H9 -> 15 | N5: ='Water-Meter'!Q9 -> 15 | O5: =K5*E5+H5*I5+#REF!*#REF!+J5*L5 -> #REF! | P5: ='Water-Meter'!E9 -> 100 | Q5: =IF('Water-Meter'!U9<0,"0",'Water-Meter'!U9) -> 30 | R5: =IF('Water-Meter'!X9<0,"0",'Water-Meter'!X9) -> 51 | S5: =IF('Water-Meter'!AA9<0,"0",'Water-Meter'!AA9) -> 55 | T5: =IF('Water-Meter'!AD9<0,"0",'Water-Meter'!AD9) -> 6 | U5: =IF('Water-Meter'!AG9<0,"0",'Water-Meter'!AG9) -> 14 | V5: =IF('Water-Meter'!AJ9<0,"0",'Water-Meter'!AJ9) -> 18 | W5: ='Water-Meter'!AN9 -> 174 | X5: =Total!K5 -> 10
A6: Serengeti | B6: =B5+1 -> 5 | C6: 11 | D6: 2019 | E6: ='UTILITY REPORT 1'!I7 -> 18.94 | F6: ='UTILITY REPORT 1'!E7 -> 2117.7 | G6: ='UTILITY REPORT 1'!F7 -> 5035 | H6: =IF('Kit report'!F8<0,"0",'Kit report'!F8) -> 564 | I6: =IF('Kit report'!X8<0,"0",'Kit report'!X8) -> 860 | J6: =IF('Utility summery'!H10<0,"0",'Utility summery'!H10) -> 41 | K6: =IF('UTILITY REPORT 1'!H7<0,"0",'UTILITY REPORT 1'!H7) -> 0 | L6: ='Water-Meter'!K10 -> 1 | M6: ='Water-Meter'!H10 -> 15 | N6: ='Water-Meter'!Q10 -> 2 | O6: =K6*E6+H6*I6+#REF!*#REF!+J6*L6 -> #REF! | P6: ='Water-Meter'!E10 -> 119 | Q6: =IF('Water-Meter'!U10<0,"0",'Water-Meter'!U10) -> 29 | R6: =IF('Water-Meter'!X10<0,"0",'Water-Meter'!X10) -> 50 | S6: =IF('Water-Meter'!AA10<0,"0",'Water-Meter'!AA10) -> 55 | T6: =IF('Water-Meter'!AD10<0,"0",'Water-Meter'!AD10) -> 7 | U6: =IF('Water-Meter'!AG10<0,"0",'Water-Meter'!AG10) -> 14 | V6: =IF('Water-Meter'!AJ10<0,"0",'Water-Meter'!AJ10) -> 19 | W6: ='Water-Meter'!AN10 -> 174 | X6: =Total!K6 -> 25
A7: Serengeti | B7: =B6+1 -> 6 | C7: 11 | D7: 2019 | E7: ='UTILITY REPORT 1'!I8 -> 142.33 | F7: ='UTILITY REPORT 1'!E8 -> 2435.73 | G7: ='UTILITY REPORT 1'!F8 -> 5420 | H7: =IF('Kit report'!F9<0,"0",'Kit report'!F9) -> 504 | I7: =IF('Kit report'!X9<0,"0",'Kit report'!X9) -> 860 | J7: =IF('Utility summery'!H11<0,"0",'Utility summery'!H11) -> 39 | K7: =IF('UTILITY REPORT 1'!H8<0,"0",'UTILITY REPORT 1'!H8) -> 107 | L7: ='Water-Meter'!K11 -> 4 | M7: ='Water-Meter'!H11 -> 13 | N7: ='Water-Meter'!Q11 -> 8 | O7: =K7*E7+H7*I7+#REF!*#REF!+J7*L7 -> #REF! | P7: ='Water-Meter'!E11 -> 110 | Q7: =IF('Water-Meter'!U11<0,"0",'Water-Meter'!U11) -> 30 | R7: =IF('Water-Meter'!X11<0,"0",'Water-Meter'!X11) -> 53 | S7: =IF('Water-Meter'!AA11<0,"0",'Water-Meter'!AA11) -> 54 | T7: =IF('Water-Meter'!AD11<0,"0",'Water-Meter'!AD11) -> 6 | U7: =IF('Water-Meter'!AG11<0,"0",'Water-Meter'!AG11) -> 14 | V7: =IF('Water-Meter'!AJ11<0,"0",'Water-Meter'!AJ11) -> 18 | W7: ='Water-Meter'!AN11 -> 175 | X7: =Total!K7 -> 24
A8: Serengeti | B8: =B7+1 -> 7 | C8: 11 | D8: 2019 | E8: ='UTILITY REPORT 1'!I9 -> 241.32 | F8: ='UTILITY REPORT 1'!E9 -> 2229.96 | G8: ='UTILITY REPORT 1'!F9 -> 5338 | H8: =IF('Kit report'!F10<0,"0",'Kit report'!F10) -> 468 | I8: =IF('Kit report'!X10<0,"0",'Kit report'!X10) -> 700 | J8: =IF('Utility summery'!H12<0,"0",'Utility summery'!H12) -> 30 | K8: =IF('UTILITY REPORT 1'!H9<0,"0",'UTILITY REPORT 1'!H9) -> 112 | L8: ='Water-Meter'!K12 -> 3 | M8: ='Water-Meter'!H12 -> 10 | N8: ='Water-Meter'!Q12 -> 7 | O8: =K8*E8+H8*I8+#REF!*#REF!+J8*L8 -> #REF! | P8: ='Water-Meter'!E12 -> 95 | Q8: =IF('Water-Meter'!U12<0,"0",'Water-Meter'!U12) -> 30 | R8: =IF('Water-Meter'!X12<0,"0",'Water-Meter'!X12) -> 51 | S8: =IF('Water-Meter'!AA12<0,"0",'Water-Meter'!AA12) -> 55 | T8: =IF('Water-Meter'!AD12<0,"0",'Water-Meter'!AD12) -> 7 | U8: =IF('Water-Meter'!AG12<0,"0",'Water-Meter'!AG12) -> 14 | V8: =IF('Water-Meter'!AJ12<0,"0",'Water-Meter'!AJ12) -> 19 | W8: ='Water-Meter'!AN12 -> 176 | X8: =Total!K8 -> 17
A9: Serengeti | B9: =B8+1 -> 8 | C9: 11 | D9: 2019 | E9: ='UTILITY REPORT 1'!I10 -> 159.05 | F9: ='UTILITY REPORT 1'!E10 -> 2100.45 | G9: ='UTILITY REPORT 1'!F10 -> 5670 | H9: =IF('Kit report'!F11<0,"0",'Kit report'!F11) -> 516 | I9: =IF('Kit report'!X11<0,"0",'Kit report'!X11) -> 740 | J9: =IF('Utility summery'!H13<0,"0",'Utility summery'!H13) -> 52 | K9: =IF('UTILITY REPORT 1'!H10<0,"0",'UTILITY REPORT 1'!H10) -> 109 | L9: ='Water-Meter'!K13 -> 3 | M9: ='Water-Meter'!H13 -> 14 | N9: ='Water-Meter'!Q13 -> 10 | O9: =K9*E9+H9*I9+#REF!*#REF!+J9*L9 -> #REF! | P9: ='Water-Meter'!E13 -> 120 | Q9: =IF('Water-Meter'!U13<0,"0",'Water-Meter'!U13) -> 29 | R9: =IF('Water-Meter'!X13<0,"0",'Water-Meter'!X13) -> 52 | S9: =IF('Water-Meter'!AA13<0,"0",'Water-Meter'!AA13) -> 54 | T9: =IF('Water-Meter'!AD13<0,"0",'Water-Meter'!AD13) -> 5 | U9: =IF('Water-Meter'!AG13<0,"0",'Water-Meter'!AG13) -> 14 | V9: =IF('Water-Meter'!AJ13<0,"0",'Water-Meter'!AJ13) -> 18 | W9: ='Water-Meter'!AN13 -> 172 | X9: =Total!K9 -> 13
A10: Serengeti | B10: =B9+1 -> 9 | C10: 11 | D10: 2019 | E10: ='UTILITY REPORT 1'!I11 -> 122.96 | F10: ='UTILITY REPORT 1'!E11 -> 2130.17 | G10: ='UTILITY REPORT 1'!F11 -> 5594 | H10: =IF('Kit report'!F12<0,"0",'Kit report'!F12) -> 492 | I10: =IF('Kit report'!X12<0,"0",'Kit report'!X12) -> 800 | J10: =IF('Utility summery'!H14<0,"0",'Utility summery'!H14) -> 37 | K10: =IF('UTILITY REPORT 1'!H11<0,"0",'UTILITY REPORT 1'!H11) -> 110 | L10: ='Water-Meter'!K14 -> 3 | M10: ='Water-Meter'!H14 -> 20 | N10: ='Water-Meter'!Q14 -> 8 | O10: =K10*E10+H10*I10+#REF!*#REF!+J10*L10 -> #REF! | P10: ='Water-Meter'!E14 -> 96 | Q10: =IF('Water-Meter'!U14<0,"0",'Water-Meter'!U14) -> 31 | R10: =IF('Water-Meter'!X14<0,"0",'Water-Meter'!X14) -> 51 | S10: =IF('Water-Meter'!AA14<0,"0",'Water-Meter'!AA14) -> 55 | T10: =IF('Water-Meter'!AD14<0,"0",'Water-Meter'!AD14) -> 7 | U10: =IF('Water-Meter'!AG14<0,"0",'Water-Meter'!AG14) -> 14 | V10: =IF('Water-Meter'!AJ14<0,"0",'Water-Meter'!AJ14) -> 18 | W10: ='Water-Meter'!AN14 -> 176 | X10: =Total!K10 -> 13
A11: Serengeti | B11: =B10+1 -> 10 | C11: 11 | D11: 2019 | E11: ='UTILITY REPORT 1'!I12 -> 231.5 | F11: ='UTILITY REPORT 1'!E12 -> 2241.8 | G11: ='UTILITY REPORT 1'!F12 -> 5487 | H11: =IF('Kit report'!F13<0,"0",'Kit report'!F13) -> 480 | I11: =IF('Kit report'!X13<0,"0",'Kit report'!X13) -> 720 | J11: =IF('Utility summery'!H15<0,"0",'Utility summery'!H15) -> 35 | K11: =IF('UTILITY REPORT 1'!H12<0,"0",'UTILITY REPORT 1'!H12) -> 81 | L11: ='Water-Meter'!K15 -> 2 | M11: ='Water-Meter'!H15 -> 18 | N11: ='Water-Meter'!Q15 -> 8 | O11: =K11*E11+H11*I11+#REF!*#REF!+J11*L11 -> #REF! | P11: ='Water-Meter'!E15 -> 124 | Q11: =IF('Water-Meter'!U15<0,"0",'Water-Meter'!U15) -> 30 | R11: =IF('Water-Meter'!X15<0,"0",'Water-Meter'!X15) -> 52 | S11: =IF('Water-Meter'!AA15<0,"0",'Water-Meter'!AA15) -> 55 | T11: =IF('Water-Meter'!AD15<0,"0",'Water-Meter'!AD15) -> 6 | U11: =IF('Water-Meter'!AG15<0,"0",'Water-Meter'!AG15) -> 14 | V11: =IF('Water-Meter'!AJ15<0,"0",'Water-Meter'!AJ15) -> 18 | W11: ='Water-Meter'!AN15 -> 175 | X11: =Total!K11 -> 36
A12: Serengeti | B12: =B11+1 -> 11 | C12: 11 | D12: 2019 | E12: ='UTILITY REPORT 1'!I13 -> 0 | F12: ='UTILITY REPORT 1'!E13 -> 2652.45 | G12: ='UTILITY REPORT 1'!F13 -> 6542 | H12: =IF('Kit report'!F14<0,"0",'Kit report'!F14) -> 576 | I12: =IF('Kit report'!X14<0,"0",'Kit report'!X14) -> 980 | J12: =IF('Utility summery'!H16<0,"0",'Utility summery'!H16) -> 30 | K12: =IF('UTILITY REPORT 1'!H13<0,"0",'UTILITY REPORT 1'!H13) -> 117 | L12: ='Water-Meter'!K16 -> 3 | M12: ='Water-Meter'!H16 -> 16 | N12: ='Water-Meter'!Q16 -> 12 | O12: =K12*E12+H12*I12+#REF!*#REF!+J12*L12 -> #REF! | P12: ='Water-Meter'!E16 -> 131 | Q12: =IF('Water-Meter'!U16<0,"0",'Water-Meter'!U16) -> 27 | R12: =IF('Water-Meter'!X16<0,"0",'Water-Meter'!X16) -> 52 | S12: =IF('Water-Meter'!AA16<0,"0",'Water-Meter'!AA16) -> 55 | T12: =IF('Water-Meter'!AD16<0,"0",'Water-Meter'!AD16) -> 7 | U12: =IF('Water-Meter'!AG16<0,"0",'Water-Meter'!AG16) -> 14 | V12: =IF('Water-Meter'!AJ16<0,"0",'Water-Meter'!AJ16) -> 19 | W12: ='Water-Meter'!AN16 -> 174 | X12: =Total!K12 -> 73
A13: Serengeti | B13: =B12+1 -> 12 | C13: 11 | D13: 2019 | E13: ='UTILITY REPORT 1'!I14 -> 187.81 | F13: ='UTILITY REPORT 1'!E14 -> 2587.46 | G13: ='UTILITY REPORT 1'!F14 -> 6667 | H13: =IF('Kit report'!F15<0,"0",'Kit report'!F15) -> 528 | I13: =IF('Kit report'!X15<0,"0",'Kit report'!X15) -> 860 | J13: =IF('Utility summery'!H17<0,"0",'Utility summery'!H17) -> 41 | K13: =IF('UTILITY REPORT 1'!H14<0,"0",'UTILITY REPORT 1'!H14) -> 42 | L13: ='Water-Meter'!K17 -> 2 | M13: ='Water-Meter'!H17 -> 19 | N13: ='Water-Meter'!Q17 -> 10 | O13: =K13*E13+H13*I13+#REF!*#REF!+J13*L13 -> #REF! | P13: ='Water-Meter'!E17 -> 136 | Q13: =IF('Water-Meter'!U17<0,"0",'Water-Meter'!U17) -> 29 | R13: =IF('Water-Meter'!X17<0,"0",'Water-Meter'!X17) -> 49 | S13: =IF('Water-Meter'!AA17<0,"0",'Water-Meter'!AA17) -> 52 | T13: =IF('Water-Meter'!AD17<0,"0",'Water-Meter'!AD17) -> 7 | U13: =IF('Water-Meter'!AG17<0,"0",'Water-Meter'!AG17) -> 14 | V13: =IF('Water-Meter'!AJ17<0,"0",'Water-Meter'!AJ17) -> 18 | W13: ='Water-Meter'!AN17 -> 169 | X13: =Total!K13 -> 73
A14: Serengeti | B14: =B13+1 -> 13 | C14: 11 | D14: 2019 | E14: ='UTILITY REPORT 1'!I15 -> 450.31 | F14: ='UTILITY REPORT 1'!E15 -> 2229.48 | G14: ='UTILITY REPORT 1'!F15 -> 5860 | H14: =IF('Kit report'!F16<0,"0",'Kit report'!F16) -> 504 | I14: =IF('Kit report'!X16<0,"0",'Kit report'!X16) -> 700 | J14: =IF('Utility summery'!H18<0,"0",'Utility summery'!H18) -> 40 | K14: =IF('UTILITY REPORT 1'!H15<0,"0",'UTILITY REPORT 1'!H15) -> 112 | L14: ='Water-Meter'!K18 -> 2 | M14: ='Water-Meter'!H18 -> 19 | N14: ='Water-Meter'!Q18 -> 6 | O14: =K14*E14+H14*I14+#REF!*#REF!+J14*L14 -> #REF! | P14: ='Water-Meter'!E18 -> 123 | Q14: =IF('Water-Meter'!U18<0,"0",'Water-Meter'!U18) -> 29 | R14: =IF('Water-Meter'!X18<0,"0",'Water-Meter'!X18) -> 50 | S14: =IF('Water-Meter'!AA18<0,"0",'Water-Meter'!AA18) -> 53 | T14: =IF('Water-Meter'!AD18<0,"0",'Water-Meter'!AD18) -> 6 | U14: =IF('Water-Meter'!AG18<0,"0",'Water-Meter'!AG18) -> 14 | V14: =IF('Water-Meter'!AJ18<0,"0",'Water-Meter'!AJ18) -> 18 | W14: ='Water-Meter'!AN18 -> 170 | X14: =Total!K14 -> 39
... A31: Serengeti | B31: =B30+1 -> 30 | C31: 11 | D31: 2019 | E31: ='UTILITY REPORT 1'!I32 -> 0 | F31: ='UTILITY REPORT 1'!E32 -> 0 | G31: ='UTILITY REPORT 1'!F32 -> 0 | H31: =IF('Kit report'!F33<0,"0",'Kit report'!F33) -> 0 | I31: =IF('Kit report'!X33<0,"0",'Kit report'!X33) -> 0 | J31: =IF('Utility summery'!H35<0,"0",'Utility summery'!H35) -> 0 | K31: =IF('UTILITY REPORT 1'!H32<0,"0",'UTILITY REPORT 1'!H32) -> 0 | L31: ='Water-Meter'!K35 -> 0 | M31: ='Water-Meter'!H35 -> 0 | N31: ='Water-Meter'!Q35 -> 0 | O31: =K31*E31+H31*I31+#REF!*#REF!+J31*L31 -> #REF! | P31: ='Water-Meter'!E35 -> 0 | Q31: =IF('Water-Meter'!U35<0,"0",'Water-Meter'!U35) -> 0 | R31: =IF('Water-Meter'!X35<0,"0",'Water-Meter'!X35) -> 0 | S31: =IF('Water-Meter'!AA35<0,"0",'Water-Meter'!AA35) -> 0 | T31: =IF('Water-Meter'!AD35<0,"0",'Water-Meter'!AD35) -> 0 | U31: =IF('Water-Meter'!AG35<0,"0",'Water-Meter'!AG35) -> 0 | V31: =IF('Water-Meter'!AJ35<0,"0",'Water-Meter'!AJ35) -> 0 | W31: ='Water-Meter'!AN35 -> 0 | X31: =Total!K31 -> 0
A32: Serengeti | B32: 1 | C32: 12 | D32: 2019 | E32: ='UTILITY REPORT 1'!I33 -> 0 | F32: ='UTILITY REPORT 1'!E33 -> 0 | G32: ='UTILITY REPORT 1'!F33 -> 0 | H32: =IF('Kit report'!F34<0,"0",'Kit report'!F34) -> 0 | I32: =IF('Kit report'!X34<0,"0",'Kit report'!X34) -> 0 | J32: =IF('Utility summery'!H36<0,"0",'Utility summery'!H36) -> 0 | K32: =IF('UTILITY REPORT 1'!H33<0,"0",'UTILITY REPORT 1'!H33) -> 0 | L32: ='Water-Meter'!K36 -> 0 | M32: ='Water-Meter'!H36 -> 0 | N32: ='Water-Meter'!Q36 -> 0 | P32: ='Water-Meter'!E36 -> 0 | Q32: =IF('Water-Meter'!U36<0,"0",'Water-Meter'!U36) -> 0 | R32: =IF('Water-Meter'!X36<0,"0",'Water-Meter'!X36) -> 0 | S32: =IF('Water-Meter'!AA36<0,"0",'Water-Meter'!AA36) -> 0 | T32: =IF('Water-Meter'!AD36<0,"0",'Water-Meter'!AD36) -> 0 | U32: =IF('Water-Meter'!AG36<0,"0",'Water-Meter'!AG36) -> 0 | V32: =IF('Water-Meter'!AJ36<0,"0",'Water-Meter'!AJ36) -> 0 | W32: ='Water-Meter'!AN36 -> 0 | X32: =Total!K32 -> 0

Sheet UTILITY REPORT 1
A1: NOVEMBER UTILITY REPORT
A2: Date | B2: % | C2: Guest Rooms Occupied | D2: Diesel cost Per Liter ($) | E2: Diesel consumption (LT) | F2: Power production (KW) | G2: Water consumption (M3) | H2: RO prodution (M3) | I2: Transport Consupmtion (LT)
A3: 43770 | B3: =Gen!B11 -> 0.87 | C3: ='Summery Report'!E5 -> 66 | D3: 1 | E3: =Gen!S11 -> 2398.12 | F3: =Gen!T11 -> 5703 | G3: ='Water-Meter'!E6 -> 128 | H3: ='Utility report '!AC6 -> 120 | I3: =Gen!AJ11 -> 69.05
A4: 43771 | B4: =Gen!B12 -> 0.766 | C4: ='Summery Report'!E6 -> 58 | D4: 1 | E4: =Gen!S12 -> 2502.57 | F4: =Gen!T12 -> 6052 | G4: ='Water-Meter'!E7 -> 139 | H4: ='Utility report '!AC7 -> 120 | I4: =Gen!AJ12 -> 659.55
A5: 43772 | B5: =Gen!B13 -> 0.11 | C5: ='Summery Report'!E7 -> 9 | D5: 1 | E5: =Gen!S13 -> 2086.83 | F5: =Gen!T13 -> 5227 | G5: ='Water-Meter'!E8 -> 132 | H5: ='Utility report '!AC8 -> 125 | I5: =Gen!AJ13 -> 261.5
A6: 43773 | B6: =Gen!B14 -> 0.13 | C6: ='Summery Report'!E8 -> 10 | D6: 1 | E6: =Gen!S14 -> 1834.21 | F6: =Gen!T14 -> 4812 | G6: ='Water-Meter'!E9 -> 100 | H6: ='Utility report '!AC9 -> 32 | I6: =Gen!AJ14 -> 17.39
A7: 43774 | B7: =Gen!B15 -> 0.506 | C7: ='Summery Report'!E9 -> 25 | D7: 1 | E7: =Gen!S15 -> 2117.7 | F7: =Gen!T15 -> 5035 | G7: ='Water-Meter'!E10 -> 119 | H7: ='Utility report '!AC10 -> 0 | I7: =Gen!AJ15 -> 18.94
A8: 43775 | B8: =Gen!B16 -> 0.312 | C8: ='Summery Report'!E10 -> 24 | D8: 1 | E8: =Gen!S16 -> 2435.73 | F8: =Gen!T16 -> 5420 | G8: ='Water-Meter'!E11 -> 110 | H8: ='Utility report '!AC11 -> 107 | I8: =Gen!AJ16 -> 142.33
A9: 43776 | B9: =Gen!B17 -> 0.195 | C9: ='Summery Report'!E11 -> 17 | D9: 1 | E9: =Gen!S17 -> 2229.96 | F9: =Gen!T17 -> 5338 | G9: ='Water-Meter'!E12 -> 95 | H9: ='Utility report '!AC12 -> 112 | I9: =Gen!AJ17 -> 241.32
A10: 43777 | B10: =Gen!B18 -> 0.169 | C10: ='Summery Report'!E12 -> 13 | D10: 1 | E10: =Gen!S18 -> 2100.45 | F10: =Gen!T18 -> 5670 | G10: ='Water-Meter'!E13 -> 120 | H10: ='Utility report '!AC13 -> 109 | I10: =Gen!AJ18 -> 159.05
A11: 43778 | B11: =Gen!B19 -> 0.169 | C11: ='Summery Report'!E13 -> 13 | D11: 1 | E11: =Gen!S19 -> 2130.17 | F11: =Gen!T19 -> 5594 | G11: ='Water-Meter'!E14 -> 96 | H11: ='Utility report '!AC14 -> 110 | I11: =Gen!AJ19 -> 122.96
A12: 43779 | B12: =Gen!B20 -> 0.468 | C12: ='Summery Report'!E14 -> 36 | D12: 1 | E12: =Gen!S20 -> 2241.8 | F12: =Gen!T20 -> 5487 | G12: ='Water-Meter'!E15 -> 124 | H12: ='Utility report '!AC15 -> 81 | I12: =Gen!AJ20 -> 231.5
A13: 43780 | B13: =Gen!B21 -> 0.948 | C13: ='Summery Report'!E15 -> 73 | D13: 1 | E13: =Gen!S21 -> 2652.45 | F13: =Gen!T21 -> 6542 | G13: ='Water-Meter'!E16 -> 131 | H13: ='Utility report '!AC16 -> 117 | I13: =Gen!AJ21 -> 0
A14: 43781 | B14: =Gen!B22 -> 0.935 | C14: ='Summery Report'!E16 -> 73 | D14: 1 | E14: =Gen!S22 -> 2587.46 | F14: =Gen!T22 -> 6667 | G14: ='Water-Meter'!E17 -> 136 | H14: ='Utility report '!AC17 -> 42 | I14: =Gen!AJ22 -> 187.81
... A33: 43800 | B33: =Gen!B41 -> 0 | C33: ='Summery Report'!E35 -> 0 | D33: 1 | E33: =Gen!S41 -> 0 | F33: =Gen!T41 -> 0 | G33: ='Water-Meter'!E36 -> 0 | H33: ='Utility report '!AC36 -> 0 | I33: =Gen!AJ41 -> 0

Sheet Utility summery
A4: Date | B4: Room Occupied | C4: Electricity Units Generated KW | D4: Diseal | G4: Water | J4: Gas | N4: Cost of utilites
D5: Generator | E5: Transport | F5: Total | G5: RO | H5: STP | I5: Total Consumption | J5: 2 ton | K5: 1 Ton | L5: 1 Ton | M5: Total consumption | N5: Electricity /1.4$/liter | O5: Diseal for Transport | P5: Gas /2.38$/Kg | Q5: Total HLP Cost | R5: Electricity Cost/Room $ | S5: cost/Room $
A6: =Gen!A11 -> 43770 | B6: ='Summery Report'!E5 -> 66 | C6: =Gen!T11 -> 5703 | D6: =Gen!S11 -> 2398.12 | E6: =Gen!AJ11 -> 69.05 | F6: =Gen!AR11 -> 2467.17 | G6: ='Utility report '!AC6 -> 120 | H6: ='Utility report '!AE6 -> 36 | I6: ='Water-Meter'!E6 -> 128 | J6: ='Lpg (2)'!B10 -> 73 | K6: ='Lpg (2)'!C10 -> 85 | L6: ='Lpg (2)'!D10 -> 85 | M6: ='Lpg (2)'!G10 -> 208.34 | O6: =E6 -> 69.05 | P6: ='[1]Lpg (2)'!#REF! -> #REF! | Q6: ='[1]Summery Report'!#REF! -> #REF! | R6: =N6/B6 -> 0 | S6: =Q6/B6 -> #REF!
A7: =Gen!A12 -> 43771 | B7: ='Summery Report'!E6 -> 58 | C7: =Gen!T12 -> 6052 | D7: =Gen!S12 -> 2502.57 | E7: =Gen!AJ12 -> 659.55 | F7: =Gen!AR12 -> 3162.12 | G7: ='Utility report '!AC7 -> 120 | H7: ='Utility report '!AE7 -> 30 | I7: ='Water-Meter'!E7 -> 139 | J7: ='Lpg (2)'!B11 -> 70 | K7: ='Lpg (2)'!C11 -> 85 | L7: ='Lpg (2)'!D11 -> 85 | M7: ='Lpg (2)'!G11 -> 101.376 | N7: =D7*1.4 -> 3503.598 | O7: =E7*1.4 -> 923.37 | P7: ='[1]Lpg (2)'!#REF! -> #REF! | Q7: ='[1]Summery Report'!#REF! -> #REF! | R7: =N7/B7 -> 60.406862 | S7: =Q7/B7 -> #REF!
A8: =Gen!A13 -> 43772 | B8: ='Summery Report'!E7 -> 9 | C8: =Gen!T13 -> 5227 | D8: =Gen!S13 -> 2086.83 | E8: =Gen!AJ13 -> 261.5 | F8: =Gen!AR13 -> 2348.33 | G8: ='Utility report '!AC8 -> 125 | H8: ='Utility report '!AE8 -> 38 | I8: ='Water-Meter'!E8 -> 132 | J8: ='Lpg (2)'!B12 -> 66 | K8: ='Lpg (2)'!C12 -> 85 | L8: ='Lpg (2)'!D12 -> 85 | M8: ='Lpg (2)'!G12 -> 101.464 | N8: =D8*1.4 -> 2921.562 | O8: =E8*1.4 -> 366.1 | P8: ='[1]Lpg (2)'!#REF! -> #REF! | Q8: ='[1]Summery Report'!#REF! -> #REF! | R8: =N8/B8 -> 324.618 | S8: =Q8/B8 -> #REF!
A9: =Gen!A14 -> 43773 | B9: ='Summery Report'!E8 -> 10 | C9: =Gen!T14 -> 4812 | D9: =Gen!S14 -> 1834.21 | E9: =Gen!AJ14 -> 17.39 | F9: =Gen!AR14 -> 1851.6 | G9: ='Utility report '!AC9 -> 32 | H9: ='Utility report '!AE9 -> 40 | I9: ='Water-Meter'!E9 -> 100 | J9: ='Lpg (2)'!B13 -> 62 | K9: ='Lpg (2)'!C13 -> 85 | L9: ='Lpg (2)'!D13 -> 85 | M9: ='Lpg (2)'!G13 -> 132.616 | N9: =D9*1.4 -> 2567.894 | O9: =E9*1.4 -> 24.346 | P9: ='[1]Lpg (2)'!#REF! -> #REF! | Q9: ='[1]Summery Report'!#REF! -> #REF! | R9: =N9/B9 -> 256.7894 | S9: =Q9/B9 -> #REF!
A10: =Gen!A15 -> 43774 | B10: ='Summery Report'!E9 -> 25 | C10: =Gen!T15 -> 5035 | D10: =Gen!S15 -> 2117.7 | E10: =Gen!AJ15 -> 18.94 | F10: =Gen!AR15 -> 2136.64 | G10: ='Utility report '!AC10 -> 0 | H10: ='Utility report '!AE10 -> 41 | I10: ='Water-Meter'!E10 -> 119 | J10: ='Lpg (2)'!B14 -> 60 | K10: ='Lpg (2)'!C14 -> 85 | L10: ='Lpg (2)'!D14 -> 85 | M10: ='Lpg (2)'!G14 -> 147.18 | N10: =D10*1.4 -> 2964.78 | O10: =E10*1.4 -> 26.516 | P10: ='[1]Lpg (2)'!#REF! -> #REF! | Q10: ='[1]Summery Report'!#REF! -> #REF! | R10: =N10/B10 -> 118.5912 | S10: =Q10/B10 -> #REF!
A11: =Gen!A16 -> 43775 | B11: ='Summery Report'!E10 -> 24 | C11: =Gen!T16 -> 5420 | D11: =Gen!S16 -> 2435.73 | E11: =Gen!AJ16 -> 142.33 | F11: =Gen!AR16 -> 2578.06 | G11: ='Utility report '!AC11 -> 107 | H11: ='Utility report '!AE11 -> 39 | I11: ='Water-Meter'!E11 -> 110 | J11: ='Lpg (2)'!B15 -> 56 | K11: ='Lpg (2)'!C15 -> 85 | L11: ='Lpg (2)'!D15 -> 85 | M11: ='Lpg (2)'!G15 -> 144.672 | N11: =D11*1.4 -> 3410.022 | O11: =E11*1.4 -> 199.262 | P11: ='[1]Lpg (2)'!#REF! -> #REF! | Q11: ='[1]Summery Report'!#REF! -> #REF! | R11: =N11/B11 -> 142.08425 | S11: =Q11/B11 -> #REF!
A12: =Gen!A17 -> 43776 | B12: ='Summery Report'!E11 -> 17 | C12: =Gen!T17 -> 5338 | D12: =Gen!S17 -> 2229.96 | E12: =Gen!AJ17 -> 241.32 | F12: =Gen!AR17 -> 2471.28 | G12: ='Utility report '!AC12 -> 112 | H12: ='Utility report '!AE12 -> 30 | I12: ='Water-Meter'!E12 -> 95 | J12: ='Lpg (2)'!B16 -> 54 | K12: ='Lpg (2)'!C16 -> 85 | L12: ='Lpg (2)'!D16 -> 85 | M12: ='Lpg (2)'!G16 -> 149.072 | N12: =D12*1.4 -> 3121.944 | O12: =E12*1.4 -> 337.848 | P12: ='[1]Lpg (2)'!#REF! -> #REF! | Q12: ='[1]Summery Report'!#REF! -> #REF! | R12: =N12/B12 -> 183.64376 | S12: =Q12/B12 -> #REF!
A13: =Gen!A18 -> 43777 | B13: ='Summery Report'!E12 -> 13 | C13: =Gen!T18 -> 5670 | D13: =Gen!S18 -> 2100.45 | E13: =Gen!AJ18 -> 159.05 | F13: =Gen!AR18 -> 2259.5 | G13: ='Utility report '!AC13 -> 109 | H13: ='Utility report '!AE13 -> 52 | I13: ='Water-Meter'!E13 -> 120 | J13: ='Lpg (2)'!B17 -> 50 | K13: ='Lpg (2)'!C17 -> 85 | L13: ='Lpg (2)'!D17 -> 85 | M13: ='Lpg (2)'!G17 -> 152.064 | N13: =D13*1.4 -> 2940.63 | O13: =E13*1.4 -> 222.67 | P13: ='[1]Lpg (2)'!#REF! -> #REF! | Q13: ='[1]Summery Report'!#REF! -> #REF! | R13: =N13/B13 -> 226.20231 | S13: =Q13/B13 -> #REF!
A14: =Gen!A19 -> 43778 | B14: ='Summery Report'!E13 -> 13 | C14: =Gen!T19 -> 5594 | D14: =Gen!S19 -> 2130.17 | E14: =Gen!AJ19 -> 122.96 | F14: =Gen!AR19 -> 2253.13 | G14: ='Utility report '!AC14 -> 110 | H14: ='Utility report '!AE14 -> 37 | I14: ='Water-Meter'!E14 -> 96 | J14: ='Lpg (2)'!B18 -> 47 | K14: ='Lpg (2)'!C18 -> 85 | L14: ='Lpg (2)'!D18 -> 85 | M14: ='Lpg (2)'!G18 -> 152.284 | N14: =D14*1.4 -> 2982.238 | O14: =E14*1.4 -> 172.144 | P14: ='[1]Lpg (2)'!#REF! -> #REF! | Q14: ='[1]Summery Report'!#REF! -> #REF! | R14: =N14/B14 -> 229.40292 | S14: =Q14/B14 -> #REF!
A15: =Gen!A20 -> 43779 | B15: ='Summery Report'!E14 -> 36 | C15: =Gen!T20 -> 5487 | D15: =Gen!S20 -> 2241.8 | E15: =Gen!AJ20 -> 231.5 | F15: =Gen!AR20 -> 2473.3 | G15: ='Utility report '!AC15 -> 81 | H15: ='Utility report '!AE15 -> 35 | I15: ='Water-Meter'!E15 -> 124 | J15: ='Lpg (2)'!B19 -> 45 | K15: ='Lpg (2)'!C19 -> 85 | L15: ='Lpg (2)'!D19 -> 85 | M15: ='Lpg (2)'!G19 -> 103.488 | N15: =D15*1.4 -> 3138.52 | O15: =E15*1.4 -> 324.1 | P15: ='[1]Lpg (2)'!#REF! -> #REF! | Q15: ='[1]Summery Report'!#REF! -> #REF! | R15: =N15/B15 -> 87.181111 | S15: =Q15/B15 -> #REF!
A16: =Gen!A21 -> 43780 | B16: ='Summery Report'!E15 -> 73 | C16: =Gen!T21 -> 6542 | D16: =Gen!S21 -> 2652.45 | E16: =Gen!AJ21 -> 0 | F16: =Gen!AR21 -> 2652.45 | G16: ='Utility report '!AC16 -> 117 | H16: ='Utility report '!AE16 -> 30 | I16: ='Water-Meter'!E16 -> 131 | J16: ='Lpg (2)'!B20 -> 42 | K16: ='Lpg (2)'!C20 -> 85 | L16: ='Lpg (2)'!D20 -> 85 | M16: ='Lpg (2)'!G20 -> 101.772 | N16: =D16*1.4 -> 3713.43 | O16: =E16*1.4 -> 0 | P16: ='[1]Lpg (2)'!#REF! -> #REF! | Q16: ='[1]Summery Report'!#REF! -> #REF! | R16: =N16/B16 -> 50.868904 | S16: =Q16/B16 -> #REF!
A17: =Gen!A22 -> 43781 | B17: ='Summery Report'!E16 -> 73 | C17: =Gen!T22 -> 6667 | D17: =Gen!S22 -> 2587.46 | E17: =Gen!AJ22 -> 187.81 | F17: =Gen!AR22 -> 2775.27 | G17: ='Utility report '!AC17 -> 42 | H17: ='Utility report '!AE17 -> 41 | I17: ='Water-Meter'!E17 -> 136 | J17: ='Lpg (2)'!B21 -> 39 | K17: ='Lpg (2)'!C21 -> 85 | L17: ='Lpg (2)'!D21 -> 85 | M17: ='Lpg (2)'!G21 -> 115.192 | N17: =D17*1.4 -> 3622.444 | O17: =E17*1.4 -> 262.934 | P17: ='[1]Lpg (2)'!#REF! -> #REF! | Q17: ='[1]Summery Report'!#REF! -> #REF! | R17: =N17/B17 -> 49.622521 | S17: =Q17/B17 -> #REF!
A18: =Gen!A23 -> 43782 | B18: ='Summery Report'!E17 -> 39 | C18: =Gen!T23 -> 5860 | D18: =Gen!S23 -> 2229.48 | E18: =Gen!AJ23 -> 450.31 | F18: =Gen!AR23 -> 2679.79 | G18: ='Utility report '!AC18 -> 112 | H18: ='Utility report '!AE18 -> 40 | I18: ='Water-Meter'!E18 -> 123 | J18: ='Lpg (2)'!B22 -> 35 | K18: ='Lpg (2)'!C22 -> 85 | L18: ='Lpg (2)'!D22 -> 85 | M18: ='Lpg (2)'!G22 -> 98.472 | N18: =D18*1.4 -> 3121.272 | O18: =E18*1.4 -> 630.434 | P18: ='[1]Lpg (2)'!#REF! -> #REF! | Q18: ='[1]Summery Report'!#REF! -> #REF! | R18: =N18/B18 -> 80.032615 | S18: =Q18/B18 -> #REF!
... A32: =Gen!A37 -> 43796 | B32: ='Summery Report'!E31 -> 0 | C32: =Gen!T37 -> 0 | D32: =Gen!S37 -> 0 | E32: =Gen!AJ37 -> 0 | F32: =Gen!AR37 -> 0 | G32: ='Utility report '!AC32 -> 0 | H32: ='Utility report '!AE32 -> 0 | I32: ='Water-Meter'!E32 -> 0 | J32: ='Lpg (2)'!B36 -> 0 | K32: ='Lpg (2)'!C36 -> 0 | L32: ='Lpg (2)'!D36 -> 0 | M32: ='Lpg (2)'!G36 -> 0 | N32: =D32*1.4 -> 0 | O32: =E32*1.4 -> 0 | P32: ='[1]Lpg (2)'!#REF! -> #REF! | Q32: ='[1]Summery Report'!#REF! -> #REF! | R32: =N32/B32 -> #DIV/0! | S32: =Q32/B32 -> #REF!
A33: =Gen!A38 -> 43797 | B33: ='Summery Report'!E32 -> 0 | C33: =Gen!T38 -> 0 | D33: =Gen!S38 -> 0 | E33: =Gen!AJ38 -> 0 | F33: =Gen!AR38 -> 0 | G33: ='Utility report '!AC33 -> 0 | H33: ='Utility report '!AE33 -> 0 | I33: ='Water-Meter'!E33 -> 0 | J33: ='Lpg (2)'!B37 -> 0 | K33: ='Lpg (2)'!C37 -> 0 | L33: ='Lpg (2)'!D37 -> 0 | M33: ='Lpg (2)'!G37 -> 0 | N33: =D33*1.4 -> 0 | O33: =E33*1.4 -> 0 | P33: ='[1]Lpg (2)'!#REF! -> #REF! | Q33: ='[1]Summery Report'!#REF! -> #REF! | R33: =N33/B33 -> #DIV/0! | S33: =Q33/B33 -> #REF! | T33: =3124/13 -> 240.30769
A34: =Gen!A39 -> 43798 | B34: ='Summery Report'!E33 -> 0 | C34: =Gen!T39 -> 0 | D34: =Gen!S39 -> 0 | E34: =Gen!AJ39 -> 0 | F34: =Gen!AR39 -> 0 | G34: ='Utility report '!AC34 -> 0 | H34: ='Utility report '!AE34 -> 0 | I34: ='Water-Meter'!E34 -> 0 | J34: ='Lpg (2)'!B38 -> 0 | K34: ='Lpg (2)'!C38 -> 0 | L34: ='Lpg (2)'!D38 -> 0 | M34: ='Lpg (2)'!G38 -> 0 | N34: =D34*1.4 -> 0 | O34: =E34*1.4 -> 0 | P34: ='[1]Lpg (2)'!#REF! -> #REF! | Q34: ='[1]Summery Report'!#REF! -> #REF! | R34: =N34/B34 -> #DIV/0! | S34: =Q34/B34 -> #REF!
A35: =Gen!A40 -> 43799 | B35: ='Summery Report'!E34 -> 0 | C35: =Gen!T40 -> 0 | D35: =Gen!S40 -> 0 | E35: =Gen!AJ40 -> 0 | F35: =Gen!AR40 -> 0 | G35: ='Utility report '!AC35 -> 0 | H35: ='Utility report '!AE35 -> 0 | I35: ='Water-Meter'!E35 -> 0 | J35: ='Lpg (2)'!B39 -> 0 | K35: ='Lpg (2)'!C39 -> 0 | L35: ='Lpg (2)'!D39 -> 0 | M35: ='Lpg (2)'!G39 -> 0 | N35: =D35*1.4 -> 0 | O35: =E35*1.4 -> 0 | P35: ='[1]Lpg (2)'!#REF! -> #REF! | Q35: ='[1]Summery Report'!#REF! -> #REF! | R35: =N35/B35 -> #DIV/0! | S35: =Q35/B35 -> #REF!
A36: =Gen!A41 -> 43800 | B36: ='Summery Report'!E35 -> 0 | C36: =Gen!T41 -> 0 | D36: =Gen!S41 -> 0 | E36: =Gen!AJ41 -> 0 | F36: =Gen!AR41 -> 0 | G36: ='Utility report '!AC36 -> 0 | H36: ='Utility report '!AE36 -> 0 | I36: ='Water-Meter'!E36 -> 0 | J36: ='Lpg (2)'!B40 -> 0 | K36: ='Lpg (2)'!C40 -> 0 | L36: ='Lpg (2)'!D40 -> 0 | M36: ='Lpg (2)'!G40 -> 0 | N36: =D36*1.4 -> 0 | O36: =E36*1.4 -> 0 | P36: ='[1]Lpg (2)'!#REF! -> #REF! | Q36: ='[1]Summery Report'!#REF! -> #REF! | R36: =N36/B36 -> #DIV/0! | S36: =Q36/B36 -> #REF!
A37: =[1]Gen!A42 -> #REF! | B37: ='Summery Report'!E36 -> 0 | C37: =Gen!T42 -> 0 | D37: =Gen!S42 -> 0 | E37: =Gen!AJ42 -> 0 | F37: =Gen!AR42 -> 0 | G37: ='Utility report '!AC37 -> 0 | H37: ='Utility report '!AE37 -> 0 | I37: ='Water-Meter'!E37 -> 0 | J37: ='Lpg (2)'!B41 -> 0 | K37: ='Lpg (2)'!C41 -> 0 | L37: ='Lpg (2)'!D41 -> 0 | M37: ='Lpg (2)'!G41 -> 0 | Q37: ='[1]Summery Report'!#REF! -> #REF! | S37: =Q37/B37 -> #REF!
A39: Total | B39: =SUM(B7:B37) -> 598 | C39: =SUM(C7:C35) -> 113366 | D39: =SUM(D7:D35) -> 45495.04 | E39: =SUM(E7:E35) -> 3815.35 | F39: =SUM(F7:F35) -> 49310.39 | G39: =SUM(G7:G35) -> -15208 | H39: =SUM(H7:H35) -> -190855 | I39: =SUM(I7:I35) -> 2365 | J39: =SUM(J7:J35) -> 846 | ... S39: =SUM(S7:S35) -> #REF!

Sheet Utility report 
A1: DAILY UTILITY REPORT NOV 2019
A2: Date | B2: Total occupancy | H2: Diesel balance LTS | I2: Diesel Deliveries | J2: Gen.Diesel consumption LTS | L2: Total Diesel consumption LTS | M2: Water Meter reading | N2: Water consumption m³ | O2: R.O WATER PRODUCTION LTRS + TIME | AA2: Total RO production | AB2: RO Meter reading | AD2: 0 | AF2: GAS TANK A | AG2: GAS TANK B | AH2: GAS TANK C | AI2: Total Gas Tanks | AJ2: Kg /day | AK2: TOTAL GAS cons.
A3: Rate Tsh /$ | B3: 1640 | C3: Diesel cost / lits | D3: 2175 | F3: =SUM(D3/B3) -> 1.3262195 | H3: =Gen!C11 -> 35194.41 | K3: Transport consumption | M3: Balance | O3: PLANT NO 1 | S3: PLANT NO 2 | W3: PLANT NO 3 | AA3: /day | AB3: Balance | AC3: Production | AD3: 0 | AE3: Production | AF3: Capacity | AG3: Capacity | AH3: Capacity | AI3: Kg | AJ3: /day | AK3: /day
B4: Rooms OCC | C4: % | D4: Guest Rooms Occ | F4: Electricity Production Cost /Room Occ by guest | G4: All Cost /Room Occ by guest | O4: Flow M3 | P4: Reading Hours Meter | Q4: Hrs | R4: total production M3 | S4: Flow M3 | T4: Reading Hours Meter | U4: Hrs | V4: total production M3 | W4: Flow M3 | Y4: Hrs | Z4: total production M3 | AA4: M3 | AC4: M3 | AE4: M3 | AF4: 2000 | AG4: 1000 | AH4: 1000 | AI4: =SUM([2]Sheet1!$AA$36) -> 950 | AJ4: Kg | AK4: M3
P5: 18537 | T5: 15719 | W5: 5.4 | X5: 21237 | AB5: 15088 | AD5: 190819 | AF5: 0.85 | AG5: 0.85 | AH5: 0.85
A6: =Gen!A11 -> 43770 | B6: ='Summery Report'!E5 -> 66 | C6: =Gen!B11 -> 0.87 | D6: ='Summery Report'!E5 -> 66 | E6: =SUM(F3) -> 1.3262195 | F6: =SUM(J6*E6)/D6 -> 48.188387 | G6: =SUM(L6*E6)/D6 -> 49.575894 | H6: =Gen!C11 -> 35194.41 | I6: =Gen!E11 -> 18000 | J6: =Gen!S11 -> 2398.12 | K6: =Gen!AJ11 -> 69.05 | L6: =SUM(J6:K6) -> 2467.17 | M6: ='Water-Meter'!K46 -> 422.72167 | N6: ='Water-Meter'!E6 -> 128 | P6: 18537 | Q6: =SUM(P6-P5) -> 0 | R6: =SUM(Q6*O6) -> 0 | T6: 15719 | U6: =T6-T5 -> 0 | V6: - | X6: 21261 | Y6: =X6-X5 -> 24 | Z6: =Y6-Y5 -> 24 | AA6: =Z6-Z5 -> 24 | AB6: 15208 | AC6: =AB6-AB5 -> 120 | AD6: 190855 | AE6: =AD6-AD5 -> 36 | AF6: ='Lpg (2)'!B10*2000/85 -> 1717.6471 | AG6: ='Lpg (2)'!C10*1000/85 -> 1000 | AH6: ='Lpg (2)'!D10*1000/85 -> 1000 | AI6: =SUM(AF6*2000)+(AG6*1000)+(AH6*1000) -> 5435294.1 | AJ6: =SUM(AI5-AI6) -> -5435294.1
A7: =Gen!A12 -> 43771 | B7: ='Summery Report'!E6 -> 58 | C7: =Gen!B12 -> 0.766 | D7: ='Summery Report'!E6 -> 58 | E7: =SUM(E6) -> 1.3262195 | F7: =SUM(J7*E7)/D7 -> 57.223399 | G7: =SUM(L7*E7)/D7 -> 72.304573 | H7: =Gen!C12 -> 50727.24 | I7: =Gen!E12 -> 0 | J7: =Gen!S12 -> 2502.57 | K7: =Gen!AJ12 -> 659.55 | L7: =SUM(J7:K7) -> 3162.12 | M7: ='Water-Meter'!K47 -> 391.26405 | N7: ='Water-Meter'!E7 -> 139 | P7: 18537 | Q7: =SUM(P7-P6) -> 0 | R7: =SUM(Q7*O7) -> 0 | T7: 15719 | U7: =T7-T6 -> 0 | V7: =SUM(U7*S7) -> 0 | X7: 21284 | Y7: =X7-X6 -> 23 | Z7: =SUM(Y7*W7) -> 0 | AA7: =SUM(Z7*X9) -> 0 | AB7: 15328 | AC7: =AB7-AB6 -> 120 | AD7: 190885 | AE7: =AD7-AD6 -> 30 | AF7: ='Lpg (2)'!B11*2000/85 -> 1647.0588 | AG7: ='Lpg (2)'!C11*1000/85 -> 1000 | AH7: ='Lpg (2)'!D11*1000/85 -> 1000 | AI7: =SUM(AF6*2000)+(AG7*1000)+(AH7*1000) -> 5435294.1 | AJ7: =SUM(AI6-AI7) -> 0
A8: =Gen!A13 -> 43772 | B8: ='Summery Report'!E7 -> 9 | C8: =Gen!B13 -> 0.11 | D8: ='Summery Report'!E7 -> 9 | E8: =SUM(E7) -> 1.3262195 | F8: =SUM(J8*E8)/D8 -> 307.51052 | G8: =SUM(L8*E8)/D8 -> 346.04456 | H8: =Gen!C13 -> 47565.12 | I8: =Gen!E13 -> 0 | J8: =Gen!S13 -> 2086.83 | K8: =Gen!AJ13 -> 261.5 | L8: =SUM(J8:K8) -> 2348.33 | M8: ='Water-Meter'!K48 -> 341.7809 | N8: ='Water-Meter'!E8 -> 132 | P8: 18537 | Q8: =SUM(P8-P7) -> 0 | R8: =SUM(Q8*O8) -> 0 | T8: 15719 | U8: =T8-T7 -> 0 | V8: =SUM(U8*S8) -> 0 | X8: 21287 | Y8: =X8-X7 -> 3 | Z8: =SUM(Y8*W8) -> 0 | AA8: =SUM(Z8*X10) -> 0 | AB8: 15453 | AC8: =AB8-AB7 -> 125 | AD8: 190923 | AE8: =AD8-AD7 -> 38 | AF8: ='Lpg (2)'!B12*2000/85 -> 1552.9412 | AG8: ='Lpg (2)'!C12*1000/85 -> 1000 | AH8: ='Lpg (2)'!D12*1000/85 -> 1000 | AI8: =SUM(AF7*2000)+(AG8*1000)+(AH8*1000) -> 5294117.6 | AJ8: =SUM(AI7-AI8) -> 141176.47
A9: =Gen!A14 -> 43773 | B9: ='Summery Report'!E8 -> 10 | C9: =Gen!B14 -> 0.13 | D9: ='Summery Report'!E8 -> 10 | E9: =SUM(E8) -> 1.3262195 | F9: =SUM(J9*E9)/D9 -> 243.25651 | G9: =SUM(L9*E9)/D9 -> 245.5628 | H9: =Gen!C14 -> 45216.79 | I9: =Gen!E14 -> 0 | J9: =Gen!S14 -> 1834.21 | K9: =Gen!AJ14 -> 17.39 | L9: =SUM(J9:K9) -> 1851.6 | M9: ='Water-Meter'!K49 -> 436.21568 | N9: ='Water-Meter'!E9 -> 100 | P9: 18537 | Q9: =SUM(P9-P8) -> 0 | R9: =SUM(Q9*O9) -> 0 | T9: 15719 | U9: =T9-T8 -> 0 | V9: =SUM(U9*S9) -> 0 | X9: 21287 | Y9: =X9-X8 -> 0 | Z9: =SUM(Y9*W9) -> 0 | AA9: =SUM(Z9*X11) -> 0 | AB9: 15485 | AC9: =AB9-AB8 -> 32 | AD9: 190963 | AE9: =AD9-AD8 -> 40 | AF9: ='Lpg (2)'!B13*2000/85 -> 1458.8235 | AG9: ='Lpg (2)'!C13*1000/85 -> 1000 | AH9: ='Lpg (2)'!D13*1000/85 -> 1000 | AI9: =SUM(AF8*2000)+(AG9*1000)+(AH9*1000) -> 5105882.4 | AJ9: =SUM(AI8-AI9) -> 188235.29
A10: =Gen!A15 -> 43774 | B10: ='Summery Report'!E9 -> 25 | C10: =Gen!B15 -> 0.506 | D10: ='Summery Report'!E9 -> 25 | E10: =SUM(E9) -> 1.3262195 | F10: =SUM(J10*E10)/D10 -> 112.3414 | G10: =SUM(L10*E10)/D10 -> 113.34615 | H10: =Gen!C15 -> 43365.19 | I10: =Gen!E15 -> 0 | J10: =Gen!S15 -> 2117.7 | K10: =Gen!AJ15 -> 18.94 | L10: =SUM(J10:K10) -> 2136.64 | M10: ='Water-Meter'!K50 -> 453.26024 | N10: ='Water-Meter'!E10 -> 119 | P10: 18537 | Q10: =SUM(P10-P9) -> 0 | R10: =SUM(Q10*O10) -> 0 | T10: 15719 | U10: =T10-T9 -> 0 | V10: =SUM(U10*S10) -> 0 | X10: 21287 | Y10: =X10-X9 -> 0 | Z10: =SUM(Y10*W10) -> 0 | AA10: =SUM(Z10*X12) -> 0 | AB10: 15485 | AC10: =AB10-AB9 -> 0 | AD10: 191004 | AE10: =AD10-AD9 -> 41 | AF10: ='Lpg (2)'!B14*2000/85 -> 1411.7647 | AG10: ='Lpg (2)'!C14*1000/85 -> 1000 | AH10: ='Lpg (2)'!D14*1000/85 -> 1000 | AI10: =SUM(AF9*2000)+(AG10*1000)+(AH10*1000) -> 4917647.1 | AJ10: =SUM(AI9-AI10) -> 188235.29
A11: =Gen!A16 -> 43775 | B11: ='Summery Report'!E10 -> 24 | C11: =Gen!B16 -> 0.312 | D11: ='Summery Report'!E10 -> 24 | E11: =SUM(E10) -> 1.3262195 | F11: =SUM(J11*E11)/D11 -> 134.59636 | G11: =SUM(L11*E11)/D11 -> 142.46139 | H11: =Gen!C16 -> 41228.55 | I11: =Gen!E16 -> 0 | J11: =Gen!S16 -> 2435.73 | K11: =Gen!AJ16 -> 142.33 | L11: =SUM(J11:K11) -> 2578.06 | M11: ='Water-Meter'!K51 -> 447.32465 | N11: ='Water-Meter'!E11 -> 110 | P11: 18537 | Q11: =SUM(P11-P10) -> 0 | R11: =SUM(Q11*O11) -> 0 | T11: 15719 | U11: =T11-T10 -> 0 | V11: =SUM(U11*S11) -> 0 | W11: 5 | X11: 21339 | Y11: =X11-X10 -> 52 | Z11: =SUM(Y11*W11) -> 260 | AA11: =SUM(Z11*X13) -> 5560620 | AB11: 15592 | AC11: =AB11-AB10 -> 107 | AD11: 191043 | AE11: =AD11-AD10 -> 39 | AF11: ='Lpg (2)'!B15*2000/85 -> 1317.6471 | AG11: ='Lpg (2)'!C15*1000/85 -> 1000 | AH11: ='Lpg (2)'!D15*1000/85 -> 1000 | AI11: =SUM(AF10*2000)+(AG11*1000)+(AH11*1000) -> 4823529.4 | AJ11: =SUM(AI10-AI11) -> 94117.647
A12: =Gen!A17 -> 43776 | B12: ='Summery Report'!E11 -> 17 | C12: =Gen!B17 -> 0.195 | D12: ='Summery Report'!E11 -> 17 | E12: =SUM(E11) -> 1.3262195 | F12: =SUM(J12*E12)/D12 -> 173.96567 | G12: =SUM(L12*E12)/D12 -> 192.79175 | H12: =Gen!C17 -> 38650.49 | I12: =Gen!E17 -> 0 | J12: =Gen!S17 -> 2229.96 | K12: =Gen!AJ17 -> 241.32 | L12: =SUM(J12:K12) -> 2471.28 | M12: ='Water-Meter'!K52 -> 455.82346 | N12: ='Water-Meter'!E12 -> 95 | P12: 18537 | Q12: =SUM(P12-P11) -> 0 | R12: =SUM(Q12*O12) -> 0 | T12: 15719 | U12: =T12-T11 -> 0 | V12: =SUM(U12*S12) -> 0 | W12: 5 | X12: 21363 | Y12: =X12-X11 -> 24 | Z12: =SUM(Y12*W12) -> 120 | AA12: =SUM(Z12*X14) -> 2569320 | AB12: 15704 | AC12: =AB12-AB11 -> 112 | AD12: 191073 | AE12: =AD12-AD11 -> 30 | AF12: ='Lpg (2)'!B16*2000/85 -> 1270.5882 | AG12: ='Lpg (2)'!C16*1000/85 -> 1000 | AH12: ='Lpg (2)'!D16*1000/85 -> 1000 | AI12: =SUM(AF11*2000)+(AG12*1000)+(AH12*1000) -> 4635294.1 | AJ12: =SUM(AI11-AI12) -> 188235.29
A13: =Gen!A18 -> 43777 | B13: ='Summery Report'!E12 -> 13 | C13: =Gen!B18 -> 0.169 | D13: ='Summery Report'!E12 -> 13 | E13: =SUM(E12) -> 1.3262195 | F13: =SUM(J13*E13)/D13 -> 214.28137 | G13: =SUM(L13*E13)/D13 -> 230.50715 | H13: =Gen!C18 -> 51179.21 | I13: =Gen!E18 -> 15000 | J13: =Gen!S18 -> 2100.45 | K13: =Gen!AJ18 -> 159.05 | L13: =SUM(J13:K13) -> 2259.5 | M13: ='Water-Meter'!K53 -> 434.47053 | N13: ='Water-Meter'!E13 -> 120 | P13: 18537 | Q13: =SUM(P13-P12) -> 0 | R13: =SUM(Q13*O13) -> 0 | T13: 15719 | U13: =T13-T12 -> 0 | V13: =SUM(U13*S13) -> 0 | W13: 5 | X13: 21387 | Y13: =X13-X12 -> 24 | Z13: =SUM(Y13*W13) -> 120 | AA13: =SUM(Z13*X15) -> 2571360 | AB13: 15813 | AC13: =AB13-AB12 -> 109 | AD13: 191125 | AE13: =AD13-AD12 -> 52 | AF13: ='Lpg (2)'!B17*2000/85 -> 1176.4706 | AG13: ='Lpg (2)'!C17*1000/85 -> 1000 | AH13: ='Lpg (2)'!D17*1000/85 -> 1000 | AI13: =SUM(AF12*2000)+(AG13*1000)+(AH13*1000) -> 4541176.5 | AJ13: =SUM(AI12-AI13) -> 94117.647
A14: =Gen!A19 -> 43778 | B14: ='Summery Report'!E13 -> 13 | C14: =Gen!B19 -> 0.169 | D14: ='Summery Report'!E13 -> 13 | E14: =SUM(E13) -> 1.3262195 | F14: =SUM(J14*E14)/D14 -> 217.31331 | G14: =SUM(L14*E14)/D14 -> 229.85731 | H14: =Gen!C19 -> 48919.71 | I14: =Gen!E19 -> 0 | J14: =Gen!S19 -> 2130.17 | K14: =Gen!AJ19 -> 122.96 | L14: =SUM(J14:K14) -> 2253.13 | M14: ='Water-Meter'!K54 -> 428.07494 | N14: ='Water-Meter'!E14 -> 96 | P14: 18537 | Q14: =SUM(P14-P13) -> 0 | R14: =SUM(Q14*O14) -> 0 | T14: 15719 | U14: =T14-T13 -> 0 | V14: =SUM(U14*S14) -> 0 | W14: 5 | X14: 21411 | Y14: =X14-X13 -> 24 | Z14: =SUM(Y14*W14) -> 120 | AA14: =SUM(Z14*X16) -> 2574120 | AB14: 15923 | AC14: =AB14-AB13 -> 110 | AD14: 191162 | AE14: =AD14-AD13 -> 37 | AF14: ='Lpg (2)'!B18*2000/85 -> 1105.8824 | AG14: ='Lpg (2)'!C18*1000/85 -> 1000 | AH14: ='Lpg (2)'!D18*1000/85 -> 1000 | AI14: =SUM(AF13*2000)+(AG14*1000)+(AH14*1000) -> 4352941.2 | AJ14: =SUM(AI13-AI14) -> 188235.29
A15: =Gen!A20 -> 43779 | B15: ='Summery Report'!E14 -> 36 | C15: =Gen!B20 -> 0.468 | D15: ='Summery Report'!E14 -> 36 | E15: =SUM(E14) -> 1.3262195 | F15: =SUM(J15*E15)/D15 -> 82.586636 | G15: =SUM(L15*E15)/D15 -> 91.114964 | H15: =Gen!C20 -> 46666.58 | I15: =Gen!E20 -> 0 | J15: =Gen!S20 -> 2241.8 | K15: =Gen!AJ20 -> 231.5 | L15: =SUM(J15:K15) -> 2473.3 | M15: ='Water-Meter'!K55 -> 426.59128 | N15: ='Water-Meter'!E15 -> 124 | P15: 18537 | Q15: =SUM(P15-P14) -> 0 | R15: =SUM(Q15*O15) -> 0 | T15: 15719 | U15: =T15-T14 -> 0 | V15: =SUM(U15*S15) -> 0 | W15: 5.3 | X15: 21428 | Y15: =X15-X14 -> 17 | Z15: =SUM(Y15*W15) -> 90.1 | AA15: =SUM(Z15*X17) -> 1933546 | AB15: 16004 | AC15: =AB15-AB14 -> 81 | AD15: 191197 | AE15: =AD15-AD14 -> 35 | AF15: ='Lpg (2)'!B19*2000/85 -> 1058.8235 | AG15: ='Lpg (2)'!C19*1000/85 -> 1000 | AH15: ='Lpg (2)'!D19*1000/85 -> 1000 | AI15: =SUM(AF15*2000)+(AG15*1000)+(AH15*1000) -> 4117647.1 | AJ15: =SUM(AI14-AI15) -> 235294.12
A16: =Gen!A21 -> 43780 | B16: ='Summery Report'!E15 -> 73 | C16: =Gen!B21 -> 0.948 | D16: ='Summery Report'!E15 -> 73 | E16: =SUM(E15) -> 1.3262195 | F16: =SUM(J16*E16)/D16 -> 48.188095 | G16: =SUM(L16*E16)/D16 -> 48.188095 | H16: =Gen!C21 -> 44193.28 | I16: =Gen!E21 -> 0 | J16: =Gen!S21 -> 2652.45 | K16: =Gen!AJ21 -> 0 | L16: =SUM(J16:K16) -> 2652.45 | M16: ='Water-Meter'!K56 -> 387.25523 | N16: ='Water-Meter'!E16 -> 131 | P16: 18537 | Q16: =SUM(P16-P15) -> 0 | R16: =SUM(Q16*O16) -> 0 | T16: 15719 | U16: =T16-T15 -> 0 | V16: =SUM(U16*S16) -> 0 | W16: 5.3 | X16: 21451 | Y16: =X16-X15 -> 23 | Z16: =SUM(Y16*W16) -> 121.9 | AA16: =SUM(Z16*X18) -> 2618899.6 | AB16: 16121 | AC16: =AB16-AB15 -> 117 | AD16: 191227 | AE16: =AD16-AD15 -> 30 | AF16: ='Lpg (2)'!B20*2000/85 -> 988.23529 | AG16: ='Lpg (2)'!C20*1000/85 -> 1000 | AH16: ='Lpg (2)'!D20*1000/85 -> 1000 | AI16: =SUM(AF16*2000)+(AG16*1000)+(AH16*1000) -> 3976470.6 | AJ16: =SUM(AI15-AI16) -> 141176.47
A17: =Gen!A22 -> 43781 | B17: ='Summery Report'!E16 -> 73 | C17: =Gen!B22 -> 0.935 | D17: ='Summery Report'!E16 -> 73 | E17: =SUM(E16) -> 1.3262195 | F17: =SUM(J17*E17)/D17 -> 47.007396 | G17: =SUM(L17*E17)/D17 -> 50.419414 | H17: =Gen!C22 -> 41540.83 | I17: =Gen!E22 -> 0 | J17: =Gen!S22 -> 2587.46 | K17: =Gen!AJ22 -> 187.81 | L17: =SUM(J17:K17) -> 2775.27 | M17: ='Water-Meter'!K57 -> 340.02931 | N17: ='Water-Meter'!E17 -> 136 | P17: 18537 | Q17: =SUM(P18-P16) -> 0 | R17: =SUM(Q17*O17) -> 0 | T17: 15719 | U17: =T17-T16 -> 0 | V17: =SUM(U17*S17) -> 0 | X17: 21460 | Y17: =X17-X16 -> 9 | Z17: =SUM(Y17*W17) -> 0 | AA17: =SUM(Z17*X19) -> 0 | AB17: 16163 | AC17: =AB17-AB16 -> 42 | AD17: 191268 | AE17: =AD17-AD16 -> 41 | AF17: ='Lpg (2)'!B21*2000/85 -> 917.64706 | AG17: ='Lpg (2)'!C21*1000/85 -> 1000 | AH17: ='Lpg (2)'!D21*1000/85 -> 1000 | AI17: =SUM(AF17*2000)+(AG17*1000)+(AH17*1000) -> 3835294.1 | AJ17: =SUM(AI16-AI17) -> 141176.47
A18: =Gen!A23 -> 43782 | B18: ='Summery Report'!E17 -> 39 | C18: =Gen!B23 -> 0.481 | D18: ='Summery Report'!E17 -> 39 | E18: =SUM(E17) -> 1.3262195 | F18: =SUM(J18*E18)/D18 -> 75.814869 | G18: =SUM(L18*E18)/D18 -> 91.127943 | H18: =Gen!C23 -> 38765.56 | I18: =Gen!E23 -> 0 | J18: =Gen!S23 -> 2229.48 | K18: =Gen!AJ23 -> 450.31 | L18: =SUM(J18:K18) -> 2679.79 | M18: ='Water-Meter'!K58 -> 413.74011 | N18: ='Water-Meter'!E18 -> 123 | P18: 18537 | R18: =SUM(Q18*O18) -> 0 | T18: 15719 | U18: =T18-T17 -> 0 | V18: =SUM(U18*S18) -> 0 | X18: 21484 | Y18: =X18-X17 -> 24 | Z18: =SUM(Y18*W18) -> 0 | AA18: =SUM(Z18*X20) -> 0 | AB18: 16275 | AC18: =AB18-AB17 -> 112 | AD18: 191308 | AE18: =AD18-AD17 -> 40 | AF18: ='Lpg (2)'!B22*2000/85 -> 823.52941 | AG18: ='Lpg (2)'!C22*1000/85 -> 1000 | AH18: ='Lpg (2)'!D22*1000/85 -> 1000 | AI18: =SUM(AF18*2000)+(AG18*1000)+(AH18*1000) -> 3647058.8 | AJ18: =SUM(AI17-AI18) -> 188235.29
A19: =Gen!A24 -> 43783 | B19: ='Summery Report'!E18 -> 41 | C19: =Gen!B24 -> 0.526 | D19: ='Summery Report'!E18 -> 41 | E19: =SUM(E18) -> 1.3262195 | F19: =SUM(J19*E19)/D19 -> 76.608908 | G19: =SUM(L19*E19)/D19 -> 85.782789 | H19: =Gen!C24 -> 36085.77 | I19: =Gen!E24 -> 0 | J19: =Gen!S24 -> 2368.36 | K19: =Gen!AJ24 -> 283.61 | L19: =SUM(J19:K19) -> 2651.97 | M19: ='Water-Meter'!K59 -> 354.58075 | N19: ='Water-Meter'!E19 -> 118 | P19: 18537 | R19: =SUM(Q19*O19) -> 0 | T19: 15719 | U19: =T19-T18 -> 0 | V19: =SUM(U19*S19) -> 0 | X19: 21508 | Y19: =X19-X18 -> 24 | Z19: =SUM(Y19*W19) -> 0 | AA19: =SUM(Z19*X21) -> 0 | AB19: 16388 | AC19: =AB19-AB18 -> 113 | AD19: 191349 | AE19: =AD19-AD18 -> 41 | AF19: ='Lpg (2)'!B23*2000/85 -> 705.88235 | AG19: ='Lpg (2)'!C23*1000/85 -> 1000 | AH19: ='Lpg (2)'!D23*1000/85 -> 1000 | AI19: =SUM(AF19*2000)+(AG19*1000)+(AH19*1000) -> 3411764.7 | AJ19: =SUM(AI18-AI19) -> 235294.12
A20: =Gen!A25 -> 43784 | B20: ='Summery Report'!E19 -> 17 | C20: =Gen!B25 -> 0.221 | D20: ='Summery Report'!E19 -> 17 | E20: =SUM(E19) -> 1.3262195 | F20: =SUM(J20*E20)/D20 -> 166.45225 | G20: =SUM(L20*E20)/D20 -> 185.97342 | H20: =Gen!C25 -> 33433.8 | I20: =Gen!E25 -> 18000 | J20: =Gen!S25 -> 2133.65 | K20: =Gen!AJ25 -> 250.23 | L20: =SUM(J20:K20) -> 2383.88 | M20: ='Water-Meter'!K60 -> 376.47359 | N20: ='Water-Meter'!E20 -> 107 | P20: 18537 | Q20: =SUM(P20-P19) -> 0 | R20: =SUM(Q20*O20) -> 0 | T20: 15719 | U20: =T20-T19 -> 0 | V20: =SUM(U20*S20) -> 0 | W20: 5 | X20: 21533 | Y20: =X20-X19 -> 25 | Z20: =SUM(Y20*W20) -> 125 | AA20: =SUM(Z20*X22) -> 2697625 | AB20: 16498 | AC20: =AB20-AB19 -> 110 | AD20: 191381 | AE20: =AD20-AD19 -> 32 | AF20: ='Lpg (2)'!B24*2000/85 -> 752.94118 | AG20: ='Lpg (2)'!C24*1000/85 -> 1000 | AH20: ='Lpg (2)'!D24*1000/85 -> 1000 | AI20: =SUM(AF20*2000)+(AG20*1000)+(AH20*1000) -> 3505882.4 | AJ20: =SUM(AI19-AI20) -> -94117.647
A21: =Gen!A26 -> 43785 | B21: ='Summery Report'!E20 -> 12 | C21: =Gen!B26 -> 0.156 | D21: ='Summery Report'!E20 -> 12 | E21: =SUM(E20) -> 1.3262195 | F21: =SUM(J21*E21)/D21 -> 231.99116 | G21: =SUM(L21*E21)/D21 -> 252.17843 | H21: =Gen!C26 -> 49049.92 | I21: =Gen!E26 -> 0 | J21: =Gen!S26 -> 2099.12 | K21: =Gen!AJ26 -> 182.66 | L21: =SUM(J21:K21) -> 2281.78 | M21: ='Water-Meter'!K61 -> 360.88326 | N21: ='Water-Meter'!E21 -> 115 | P21: 18537 | Q21: =SUM(P21-P20) -> 0 | R21: =SUM(Q21*O21) -> 0 | T21: 15719 | U21: =T21-T20 -> 0 | V21: =SUM(U21*S21) -> 0 | W21: 5 | X21: 21557 | Y21: =X21-X20 -> 24 | Z21: =SUM(Y21*W21) -> 120 | AA21: =SUM(Z21*X23) -> 2591640 | AB21: 16608 | AC21: =AB21-AB20 -> 110 | AD21: 191411 | AE21: =AD21-AD20 -> 30 | AF21: ='Lpg (2)'!B25*2000/85 -> 705.88235 | AG21: ='Lpg (2)'!C25*1000/85 -> 1000 | AH21: ='Lpg (2)'!D25*1000/85 -> 1000 | AI21: =SUM(AF21*2000)+(AG21*1000)+(AH21*1000) -> 3411764.7 | AJ21: =SUM(AI20-AI21) -> 94117.647
A22: =Gen!A27 -> 43786 | B22: ='Summery Report'!E21 -> 48 | C22: =Gen!B27 -> 0.623 | D22: ='Summery Report'!E21 -> 48 | E22: =SUM(E21) -> 1.3262195 | F22: =SUM(J22*E22)/D22 -> 66.164263 | G22: =SUM(L22*E22)/D22 -> 69.738977 | H22: =Gen!C27 -> 46768.14 | I22: =Gen!E27 -> 0 | J22: =Gen!S27 -> 2394.69 | K22: =Gen!AJ27 -> 129.38 | L22: =SUM(J22:K22) -> 2524.07 | M22: ='Water-Meter'!K62 -> 315.97577 | N22: ='Water-Meter'!E22 -> 127 | P22: 18537 | Q22: =SUM(P22-P21) -> 0 | R22: =SUM(Q22*O22) -> 0 | T22: 15719 | U22: =T22-T21 -> 0 | V22: =SUM(U22*S22) -> 0 | W22: 5 | X22: 21581 | Y22: =X22-X21 -> 24 | Z22: =SUM(Y22*W22) -> 120 | AA22: =SUM(Z22*X24) -> 2594520 | AB22: 16718 | AC22: =AB22-AB21 -> 110 | AD22: 191458 | AE22: =AD22-AD21 -> 47 | AF22: ='Lpg (2)'!B26*2000/85 -> 635.29412 | AG22: ='Lpg (2)'!C26*1000/85 -> 1000 | AH22: ='Lpg (2)'!D26*1000/85 -> 1000 | AI22: =SUM(AF22*2000)+(AG22*1000)+(AH22*1000) -> 3270588.2 | AJ22: =SUM(AI21-AI22) -> 141176.47
A23: =Gen!A28 -> 43787 | B23: ='Summery Report'!E22 -> 40 | C23: =Gen!B28 -> 0.519 | D23: ='Summery Report'!E22 -> 40 | E23: =SUM(E22) -> 1.3262195 | F23: =SUM(J23*E23)/D23 -> 75.34253 | G23: =SUM(L23*E23)/D23 -> 80.660339 | H23: =Gen!C28 -> 44244.07 | I23: =Gen!E28 -> 0 | J23: =Gen!S28 -> 2272.4 | K23: =Gen!AJ28 -> 160.39 | L23: =SUM(J23:K23) -> 2432.79 | M23: ='Water-Meter'!K63 -> 338.30512 | N23: ='Water-Meter'!E23 -> 106 | P23: 18537 | Q23: =SUM(P23-P22) -> 0 | R23: =SUM(Q23*O23) -> 0 | T23: 15719 | U23: =T23-T22 -> 0 | V23: =SUM(U23*S23) -> 0 | W23: 5 | X23: 21597 | Y23: =X23-X22 -> 16 | Z23: =SUM(Y23*W23) -> 80 | AA23: =SUM(Z23*X25) -> 1730800 | AB23: 16795 | AC23: =AB23-AB22 -> 77 | AD23: 191488 | AE23: =AD23-AD22 -> 30 | AF23: ='Lpg (2)'!B27*2000/85 -> 588.23529 | AG23: ='Lpg (2)'!C27*1000/85 -> 1000 | AH23: ='Lpg (2)'!D27*1000/85 -> 1000 | AI23: =SUM(AF23*2000)+(AG23*1000)+(AH23*1000) -> 3176470.6 | AJ23: =SUM(AI22-AI23) -> 94117.647
A24: =Gen!A29 -> 43788 | B24: ='Summery Report'!E23 -> 7 | C24: =Gen!B29 -> 0.091 | D24: ='Summery Report'!E23 -> 7 | E24: =SUM(E23) -> 1.3262195 | F24: =SUM(J24*E24)/D24 -> 351.12609 | G24: =SUM(L24*E24)/D24 -> 371.53661 | H24: =Gen!C29 -> 41811.28 | I24: =Gen!E29 -> 0 | J24: =Gen!S29 -> 1853.3 | K24: =Gen!AJ29 -> 107.73 | L24: =SUM(J24:K24) -> 1961.03 | M24: ='Water-Meter'!K64 -> 310.06303 | N24: ='Water-Meter'!E24 -> 98 | P24: 18537 | Q24: =SUM(P24-P23) -> 0 | R24: =SUM(Q24*O24) -> 0 | T24: 15719 | U24: =T24-T23 -> 0 | V24: =SUM(U24*S24) -> 0 | W24: 5.1 | X24: 21621 | Y24: =X24-X23 -> 24 | Z24: =SUM(Y24*W24) -> 122.4 | AA24: =SUM(Z24*X26) -> 2651061.6 | AB24: 16908 | AC24: =AB24-AB23 -> 113 | AD24: 191528 | AE24: =AD24-AD23 -> 40 | AF24: ='Lpg (2)'!B28*2000/85 -> 541.17647 | AG24: ='Lpg (2)'!C28*1000/85 -> 1000 | AH24: ='Lpg (2)'!D28*1000/85 -> 1000 | AI24: =SUM(AF24*2000)+(AG24*1000)+(AH24*1000) -> 3082352.9 | AJ24: =SUM(AI23-AI24) -> 94117.647
A25: =Gen!A30 -> 43789 | B25: ='Summery Report'!E24 -> 9 | C25: =Gen!B30 -> 0.117 | D25: ='Summery Report'!E24 -> 9 | E25: =SUM(E24) -> 1.3262195 | F25: =SUM(J25*E25)/D25 -> 271.819 | G25: =SUM(L25*E25)/D25 -> 284.22505 | H25: =Gen!C30 -> 39850.25 | I25: =Gen!E30 -> 0 | J25: =Gen!S30 -> 1844.62 | K25: =Gen!AJ30 -> 84.19 | L25: =SUM(J25:K25) -> 1928.81 | M25: ='Water-Meter'!K65 -> 334.37794 | N25: ='Water-Meter'!E25 -> 79 | P25: 18537 | Q25: =SUM(P25-P24) -> 0 | R25: =SUM(Q25*O25) -> 0 | T25: 15719 | U25: =T25-T24 -> 0 | V25: =SUM(U25*S25) -> 0 | W25: 5 | X25: 21635 | Y25: =X25-X24 -> 14 | Z25: =SUM(Y25*W25) -> 70 | AA25: =SUM(Z25*X27) -> 1517810 | AB25: 16970 | AC25: =AB25-AB24 -> 62 | AD25: 191585 | AE25: =AD25-AD24 -> 57 | AF25: ='Lpg (2)'!B29*2000/85 -> 470.58824 | AG25: ='Lpg (2)'!C29*1000/85 -> 1000 | AH25: ='Lpg (2)'!D29*1000/85 -> 1000 | AI25: =SUM(AF25*2000)+(AG25*1000)+(AH25*1000) -> 2941176.5 | AJ25: =SUM(AI24-AI25) -> 141176.47
A26: =Gen!A31 -> 43790 | B26: ='Summery Report'!E25 -> 10 | C26: =Gen!B31 -> 0.13 | D26: ='Summery Report'!E25 -> 10 | E26: =SUM(E25) -> 1.3262195 | F26: =SUM(J26*E26)/D26 -> 206.5189 | G26: =SUM(L26*E26)/D26 -> 211.57976 | H26: =Gen!C31 -> 37921.44 | I26: =Gen!E31 -> 0 | J26: =Gen!S31 -> 1557.2 | K26: =Gen!AJ31 -> 38.16 | L26: =SUM(J26:K26) -> 1595.36 | M26: ='Water-Meter'!K66 -> 361.96437 | N26: ='Water-Meter'!E26 -> 95 | P26: 18537 | Q26: =SUM(P26-P25) -> 0 | R26: =SUM(Q26*O26) -> 0 | T26: 15719 | U26: =T26-T25 -> 0 | V26: =SUM(U26*S26) -> 0 | W26: 4.9 | X26: 21659 | Y26: =X26-X25 -> 24 | Z26: =SUM(Y26*W26) -> 117.6 | AA26: =SUM(Z26*X28) -> 0 | AB26: 17078 | AC26: =AB26-AB25 -> 108 | AD26: 191627 | AE26: =AD26-AD25 -> 42 | AF26: ='Lpg (2)'!B30*2000/85 -> 423.52941 | AG26: ='Lpg (2)'!C30*1000/85 -> 1000 | AH26: ='Lpg (2)'!D30*1000/85 -> 1000 | AI26: =SUM(AF26*2000)+(AG26*1000)+(AH26*1000) -> 2847058.8 | AJ26: =SUM(AI25-AI26) -> 94117.647
A27: =Gen!A32 -> 43791 | B27: ='Summery Report'!E26 -> 11 | C27: =Gen!B32 -> 0.143 | D27: ='Summery Report'!E26 -> 11 | E27: =SUM(E26) -> 1.3262195 | F27: =SUM(J27*E27)/D27 -> 219.77748 | G27: =SUM(L27*E27)/D27 -> 230.1871 | H27: =Gen!C32 -> 36326.08 | I27: =Gen!E32 -> 0 | J27: =Gen!S32 -> 1822.89 | K27: =Gen!AJ32 -> 86.34 | L27: =SUM(J27:K27) -> 1909.23 | M27: ='Water-Meter'!K67 -> 354.93009 | N27: ='Water-Meter'!E27 -> 95 | P27: 18537 | Q27: =SUM(P27-P26) -> 0 | R27: =SUM(Q27*O27) -> 0 | T27: 15719 | U27: =T27-T26 -> 0 | V27: =SUM(U27*S27) -> 0 | W27: 4.9 | X27: 21683 | Y27: =X27-X26 -> 24 | Z27: =SUM(Y27*W27) -> 117.6 | AA27: =SUM(Z27*X29) -> 0 | AB27: 17186 | AC27: =AB27-AB26 -> 108 | AD27: 191657 | AE27: =AD27-AD26 -> 30 | AF27: ='Lpg (2)'!B31*2000/85 -> 352.94118 | AG27: ='Lpg (2)'!C31*1000/85 -> 1000 | AH27: ='Lpg (2)'!D31*1000/85 -> 1000 | AI27: =SUM(AF27*2000)+(AG27*1000)+(AH27*1000) -> 2705882.4 | AJ27: =SUM(AI26-AI27) -> 141176.47
A28: =Gen!A33 -> 43792 | B28: ='Summery Report'!E27 -> 13 | C28: =Gen!B33 -> 0.169 | D28: ='Summery Report'!E27 -> 13 | E28: =SUM(E27) -> 1.3262195 | F28: =SUM(J28*E28)/D28 -> 0 | G28: =SUM(L28*E28)/D28 -> 0 | H28: =Gen!C33 -> 34416.85 | I28: =Gen!E33 -> 15000 | J28: =Gen!S33 -> 0 | K28: =Gen!AJ33 -> 0 | L28: =SUM(J28:K28) -> 0 | M28: ='Water-Meter'!K68 -> 0 | N28: ='Water-Meter'!E28 -> 0 | Q28: =SUM(P28-P27) -> -18537 | R28: =SUM(Q28*O28) -> 0 | U28: =T28-T27 -> -15719 | V28: =SUM(U28*S28) -> 0 | Y28: =X28-X27 -> -21683 | Z28: =SUM(Y28*W28) -> 0 | AA28: =SUM(Z28*X30) -> 0 | AC28: =SUM(AB28-AB27) -> -17186 | AE28: =AD28-AD27 -> -191657 | AF28: ='Lpg (2)'!B32*2000/85 -> 0 | AG28: ='Lpg (2)'!C32*1000/85 -> 0 | AH28: ='Lpg (2)'!D32*1000/85 -> 0 | AI28: =SUM(AF28*2000)+(AG28*1000)+(AH28*1000) -> 0 | AJ28: =SUM(AI27-AI28) -> 2705882.4
A29: =Gen!A34 -> 43793 | B29: ='Summery Report'!E28 -> 0 | C29: =Gen!B34 -> 0 | D29: ='Summery Report'!E28 -> 0 | E29: =SUM(E28) -> 1.3262195 | F29: =SUM(J29*E29)/D29 -> #DIV/0! | G29: =SUM(L29*E29)/D29 -> #DIV/0! | H29: =Gen!C34 -> 34416.85 | I29: =Gen!E34 -> 0 | J29: =Gen!S34 -> 0 | K29: =Gen!AJ34 -> 0 | L29: =SUM(J29:K29) -> 0 | M29: ='Water-Meter'!K69 -> 0 | N29: ='Water-Meter'!E29 -> 0 | Q29: =SUM(P29-P28) -> 0 | R29: =SUM(Q29*O29) -> 0 | U29: =T29-T28 -> 0 | V29: =SUM(U29*S29) -> 0 | Y29: =X29-X28 -> 0 | Z29: =SUM(Y29*W29) -> 0 | AA29: =SUM(Z29*X31) -> 0 | AC29: =SUM(AB29-AB28) -> 0 | AE29: =AD29-AD28 -> 0 | AF29: ='Lpg (2)'!B33*2000/85 -> 0 | AG29: ='Lpg (2)'!C33*1000/85 -> 0 | AH29: ='Lpg (2)'!D33*1000/85 -> 0 | AI29: =SUM(AF29*2000)+(AG29*1000)+(AH29*1000) -> 0 | AJ29: =SUM(AI28-AI29) -> 0
A30: =Gen!A35 -> 43794 | B30: ='Summery Report'!E29 -> 0 | C30: =Gen!B35 -> 0 | D30: ='Summery Report'!E29 -> 0 | E30: =SUM(E29) -> 1.3262195 | F30: =SUM(J30*E30)/D30 -> #DIV/0! | G30: =SUM(L30*E30)/D30 -> #DIV/0! | H30: =Gen!C35 -> 34416.85 | I30: =Gen!E35 -> 0 | J30: =Gen!S35 -> 0 | K30: =Gen!AJ35 -> 0 | L30: =SUM(J30:K30) -> 0 | M30: ='Water-Meter'!K70 -> 0 | N30: ='Water-Meter'!E30 -> 0 | Q30: =SUM(P30-P29) -> 0 | R30: =SUM(Q30*O30) -> 0 | U30: =T30-T29 -> 0 | V30: =SUM(U30*S30) -> 0 | Y30: =X30-X29 -> 0 | Z30: =SUM(Y30*W30) -> 0 | AA30: =SUM(Z30*X32) -> 0 | AC30: =SUM(AB30-AB29) -> 0 | AE30: =AD30-AD29 -> 0 | AF30: ='Lpg (2)'!B34*2000/85 -> 0 | AG30: ='Lpg (2)'!C34*1000/85 -> 0 | AH30: ='Lpg (2)'!D34*1000/85 -> 0 | AI30: =SUM(AF30*2000)+(AG30*1000)+(AH30*1000) -> 0 | AJ30: =SUM(AI29-AI30) -> 0
A31: =Gen!A36 -> 43795 | B31: ='Summery Report'!E30 -> 0 | C31: =Gen!B36 -> 0 | D31: ='Summery Report'!E30 -> 0 | E31: =SUM(E30) -> 1.3262195 | F31: =SUM(J31*E31)/D31 -> #DIV/0! | G31: =SUM(L31*E31)/D31 -> #DIV/0! | H31: =Gen!C36 -> 34416.85 | I31: =Gen!E36 -> 0 | J31: =Gen!S36 -> 0 | K31: =Gen!AJ36 -> 0 | L31: =SUM(J31:K31) -> 0 | M31: ='Water-Meter'!K71 -> 0 | N31: ='Water-Meter'!E31 -> 0 | Q31: =SUM(P31-P30) -> 0 | R31: =SUM(Q31*O31) -> 0 | U31: =T31-T30 -> 0 | V31: =SUM(U31*S31) -> 0 | Y31: =X31-X30 -> 0 | Z31: =SUM(Y31*W31) -> 0 | AA31: =SUM(Z31*X33) -> 0 | AC31: =SUM(AB31-AB30) -> 0 | AE31: =AD31-AD30 -> 0 | AF31: ='Lpg (2)'!B35*2000/85 -> 0 | AG31: ='Lpg (2)'!C35*1000/85 -> 0 | AH31: ='Lpg (2)'!D35*1000/85 -> 0 | AI31: =SUM(AF31*2000)+(AG31*1000)+(AH31*1000) -> 0 | AJ31: =SUM(AI30-AI31) -> 0
A32: =Gen!A37 -> 43796 | B32: ='Summery Report'!E31 -> 0 | C32: =Gen!B37 -> 0 | D32: ='Summery Report'!E31 -> 0 | E32: =SUM(E31) -> 1.3262195 | F32: =SUM(J32*E32)/D32 -> #DIV/0! | G32: =SUM(L32*E32)/D32 -> #DIV/0! | H32: =Gen!C37 -> 34416.85 | I32: =Gen!E37 -> 0 | J32: =Gen!S37 -> 0 | K32: =Gen!AJ37 -> 0 | L32: =SUM(J32:K32) -> 0 | M32: ='Water-Meter'!K72 -> 0 | N32: ='Water-Meter'!E32 -> 0 | Q32: =SUM(P32-P31) -> 0 | R32: =SUM(Q32*O32) -> 0 | U32: =T32-T31 -> 0 | V32: =SUM(U32*S32) -> 0 | Y32: =X32-X31 -> 0 | Z32: =SUM(Y32*W32) -> 0 | AA32: =SUM(Z32*X34) -> 0 | AC32: =SUM(AB32-AB31) -> 0 | AE32: =AD32-AD31 -> 0 | AF32: ='Lpg (2)'!B36*2000/85 -> 0 | AG32: ='Lpg (2)'!C36*1000/85 -> 0 | AH32: ='Lpg (2)'!D36*1000/85 -> 0 | AI32: =SUM(AF32*2000)+(AG32*1000)+(AH32*1000) -> 0 | AJ32: =SUM(AI31-AI32) -> 0
A33: =Gen!A38 -> 43797 | B33: ='Summery Report'!E32 -> 0 | C33: =Gen!B38 -> 0 | D33: ='Summery Report'!E32 -> 0 | E33: =SUM(E32) -> 1.3262195 | F33: =SUM(J33*E33)/D33 -> #DIV/0! | G33: =SUM(L33*E33)/D33 -> #DIV/0! | H33: =Gen!C38 -> 34416.85 | I33: =Gen!E38 -> 0 | J33: =Gen!S38 -> 0 | K33: =Gen!AJ38 -> 0 | L33: =SUM(J33:K33) -> 0 | M33: ='Water-Meter'!K73 -> 0 | N33: ='Water-Meter'!E33 -> 0 | Q33: =SUM(P33-P32) -> 0 | R33: =SUM(Q33*O33) -> 0 | U33: =T33-T32 -> 0 | V33: =SUM(U33*S33) -> 0 | Y33: =X33-X32 -> 0 | Z33: =SUM(Y33*W33) -> 0 | AA33: =SUM(Z33*X35) -> 0 | AC33: =SUM(AB33-AB32) -> 0 | AE33: =AD33-AD32 -> 0 | AF33: ='Lpg (2)'!B37*2000/85 -> 0 | AG33: ='Lpg (2)'!C37*1000/85 -> 0 | AH33: ='Lpg (2)'!D37*1000/85 -> 0 | AI33: =SUM(AF33*2000)+(AG33*1000)+(AH33*1000) -> 0 | AJ33: =SUM(AI32-AI33) -> 0
A34: =Gen!A39 -> 43798 | B34: ='Summery Report'!E33 -> 0 | C34: =Gen!B39 -> 0 | D34: ='Summery Report'!E33 -> 0 | E34: =SUM(E33) -> 1.3262195 | F34: =SUM(J34*E34)/D34 -> #DIV/0! | G34: =SUM(L34*E34)/D34 -> #DIV/0! | H34: =Gen!C39 -> 34416.85 | I34: =Gen!E39 -> 0 | J34: =Gen!S39 -> 0 | K34: =Gen!AJ39 -> 0 | L34: =SUM(J34:K34) -> 0 | M34: ='Water-Meter'!K74 -> 0 | N34: ='Water-Meter'!E34 -> 0 | Q34: =SUM(P34-P33) -> 0 | R34: =SUM(Q34*O34) -> 0 | U34: =T34-T33 -> 0 | V34: =SUM(U34*S34) -> 0 | Y34: =X34-X33 -> 0 | Z34: =SUM(Y34*W34) -> 0 | AA34: =SUM(Z34*X36) -> 0 | AC34: =SUM(AB34-AB33) -> 0 | AE34: =AD34-AD33 -> 0 | AF34: ='Lpg (2)'!B38*2000/85 -> 0 | AG34: ='Lpg (2)'!C38*1000/85 -> 0 | AH34: ='Lpg (2)'!D38*1000/85 -> 0 | AI34: =SUM(AF34*2000)+(AG34*1000)+(AH34*1000) -> 0 | AJ34: =SUM(AI33-AI34) -> 0
A35: =Gen!A40 -> 43799 | B35: ='Summery Report'!E34 -> 0 | C35: =Gen!B40 -> 0 | D35: ='Summery Report'!E34 -> 0 | E35: =SUM(E34) -> 1.3262195 | F35: =SUM(J35*E35)/D35 -> #DIV/0! | G35: =SUM(L35*E35)/D35 -> #DIV/0! | H35: =Gen!C40 -> 34416.85 | I35: =Gen!E40 -> 18000 | J35: =Gen!S40 -> 0 | K35: =Gen!AJ40 -> 0 | L35: =SUM(J35:K35) -> 0 | M35: ='Water-Meter'!K75 -> 0 | N35: ='Water-Meter'!E35 -> 0 | Q35: =SUM(P35-P34) -> 0 | R35: =SUM(Q35*O35) -> 0 | U35: =T35-T34 -> 0 | V35: =SUM(U35*S35) -> 0 | Y35: =X35-X34 -> 0 | Z35: =SUM(Y35*W35) -> 0 | AA35: =SUM(Z35*X37) -> 0 | AC35: =SUM(AB35-AB34) -> 0 | AE35: =AD35-AD34 -> 0 | AF35: ='Lpg (2)'!B39*2000/85 -> 0 | AG35: ='Lpg (2)'!C39*1000/85 -> 0 | AH35: ='Lpg (2)'!D39*1000/85 -> 0 | AI35: =SUM(AF35*2000)+(AG35*1000)+(AH35*1000) -> 0 | AJ35: =SUM(AI34-AI35) -> 0
A36: =Gen!A41 -> 43800 | B36: ='Summery Report'!E35 -> 0 | C36: =Gen!B41 -> 0 | D36: ='Summery Report'!E35 -> 0 | E36: =SUM(E35) -> 1.3262195 | F36: =SUM(J36*E36)/D36 -> #DIV/0! | G36: =SUM(L36*E36)/D36 -> #DIV/0! | H36: =Gen!C41 -> 34416.85 | I36: =Gen!E41 -> 0 | J36: =Gen!S41 -> 0 | K36: =Gen!AJ41 -> 0 | L36: =SUM(J36:K36) -> 0 | M36: ='Water-Meter'!K76 -> 0 | N36: ='Water-Meter'!E36 -> 0 | Q36: =SUM(P36-P35) -> 0 | R36: =SUM(Q36*O36) -> 0 | U36: =T36-T35 -> 0 | V36: =SUM(U36*S36) -> 0 | Y36: =X36-X35 -> 0 | Z36: =SUM(Y36*W36) -> 0 | AA36: =SUM(Z36*X38) -> 0 | AC36: =SUM(AB36-AB35) -> 0 | AE36: =AD36-AD35 -> 0 | AF36: ='Lpg (2)'!B40*2000/85 -> 0 | AG36: ='Lpg (2)'!C40*1000/85 -> 0 | AH36: ='Lpg (2)'!D40*1000/85 -> 0 | AI36: =SUM(AF36*1000)+(AG36*1000)+(AH36*2000) -> 0 | AJ36: =SUM(AI35-AI36) -> 0
A37: Nb Day | B37: 0 | J37: =SUM(J6:J36) -> 47893.16 | L37: =SUM(J37:K37) -> 47893.16 | N37: ='Water-Meter'!E37 -> 0 | AC37: =SUM(AB37-AB36) -> 0 | AE37: =AD37-AD36 -> 0 | AJ37: =SUM(AJ6:AJ36) -> 0 | AK37: =SUM(AK6:AK36) -> 0

Sheet Kit report
B1: KITCHEN THREE PHASE KWH METER READING | H1: KITCHEN WATER METER READING | M1: AMANI Restaurant WATER METER READING | T1: LAUNDRY THREE PHASE KWH METER READING | Y1: LAUNDRY WATER METER READING
A2: Occ % | B2: DATE | C2: READING TIME | D2: METER READING OPEN | E2: METER READING ClOSE | F2: UNIT USED Kwh | H2: DATE | I2: READING TIME | J2: METER READING OPEN Cbm | K2: METER READING ClOSE Cbm | L2: UNIT USED Cbm | M2: DATE | N2: READING TIME | O2: METER READING OPEN Cbm | P2: METER READING ClOSE Cbm | Q2: UNIT USED Cbm | R2: Cost Per day Elct+Water $ | S2: % as per the total Lodge consumption | T2: DATE | U2: READING TIME | V2: METER READING OPEN (Kwh) | W2: METER READING ClOSE (Kwh) | X2: UNIT USED Kwh | Y2: DATE | Z2: READING TIME | AA2: METER READING OPEN Cbm | AB2: METER READING ClOSE Cbm | AC2: UNIT USED Cbm
A3: 43770 | B3: Close Last Month | F3: X120 | H3: Close Last Month | K3: ='[1]Water-Meter'!G5 -> 36423 | M3: Close Last Month | P3: ='[1]Water-Meter'!J5 -> 7351 | T3: Close Last Month | X3: =(W3-V3)*200 -> 0 | Y3: Close Last Month | AB3: ='[1]Water-Meter'!P5 -> 18541
A4: =Gen!B11 -> 0.87 | B4: =Gen!A11 -> 43770 | D4: 8043.7 | E4: 8048 | F4: =SUM(E4-D4)*120 -> 516 | H4: =B4 -> 43770 | J4: =SUM(K3) -> 36423 | K4: ='[1]Water-Meter'!G6 -> 36434 | L4: =SUM(K4-J4) -> 11 | M4: =H4 -> 43770 | O4: =SUM(P3) -> 7351 | P4: ='[1]Water-Meter'!J6 -> 7353 | Q4: =SUM(P4-O4) -> 2 | R4: =SUM(Q4/1615) -> 0.0012383901 | S4: =SUM(F4/[1]Gen!T10) -> #DIV/0! | T4: =M4 -> 43770 | V4: 7244.3 | W4: 7248.6 | X4: =(W4-V4)*200 -> 860 | Y4: =T4 -> 43770 | AA4: 3397.9 | AB4: ='[1]Water-Meter'!P6 -> 18547 | AC4: =SUM(AB4-AA4) -> 15149.1
A5: =Gen!B12 -> 0.766 | B5: =Gen!A12 -> 43771 | D5: =E4 -> 8048 | E5: 8052.3 | F5: =SUM(E5-D5)*120 -> 516 | H5: =B5 -> 43771 | J5: =SUM(K4) -> 36434 | K5: ='[1]Water-Meter'!G7 -> 36454 | L5: =SUM(K5-J5) -> 20 | M5: =H5 -> 43771 | O5: =SUM(P4) -> 7353 | P5: ='[1]Water-Meter'!J7 -> 7357 | Q5: =SUM(P5-O5) -> 4 | R5: =SUM(Q5/1615) -> 0.0024767802 | S5: =SUM(F5/[1]Gen!T11) -> 0.091021344 | T5: =M5 -> 43771 | V5: =W4 -> 7248.6 | W5: 7253.1 | X5: =(W5-V5)*200 -> 900 | Y5: =T5 -> 43771 | AA5: =SUM(AB4) -> 18547 | AB5: ='[1]Water-Meter'!P7 -> 18554 | AC5: =SUM(AB5-AA5) -> 7
A6: =Gen!B13 -> 0.11 | B6: =Gen!A13 -> 43772 | D6: =E5 -> 8052.3 | E6: 8056.4 | F6: =SUM(E6-D6)*120 -> 492 | H6: =B6 -> 43772 | J6: =SUM(K5) -> 36454 | K6: ='[1]Water-Meter'!G8 -> 36472 | L6: =SUM(K6-J6) -> 18 | M6: =H6 -> 43772 | O6: =SUM(P5) -> 7357 | P6: ='[1]Water-Meter'!J8 -> 7360 | Q6: =SUM(P6-O6) -> 3 | R6: =SUM(Q6/1615) -> 0.0018575851 | S6: =SUM(F6/[1]Gen!T12) -> 0.079883098 | T6: =M6 -> 43772 | V6: =W5 -> 7253.1 | W6: 7257.2 | X6: =(W6-V6)*200 -> 820 | Y6: =T6 -> 43772 | AA6: =SUM(AB5) -> 18554 | AB6: ='[1]Water-Meter'!P8 -> 18563 | AC6: =SUM(AB6-AA6) -> 9
A7: =Gen!B14 -> 0.13 | B7: =Gen!A14 -> 43773 | D7: =E6 -> 8056.4 | E7: 8061 | F7: =SUM(E7-D7)*120 -> 552 | H7: =B7 -> 43773 | J7: =SUM(K6) -> 36472 | K7: ='[1]Water-Meter'!G9 -> 36485 | L7: =SUM(K7-J7) -> 13 | M7: =H7 -> 43773 | O7: =SUM(P6) -> 7360 | P7: ='[1]Water-Meter'!J9 -> 7364 | Q7: =SUM(P7-O7) -> 4 | R7: =SUM(Q7/1615) -> 0.0024767802 | S7: =SUM(F7/[1]Gen!T13) -> 0.083890578 | T7: =M7 -> 43773 | V7: =W6 -> 7257.2 | W7: 7262.5 | X7: =(W7-V7)*200 -> 1060 | Y7: =T7 -> 43773 | AA7: =SUM(AB6) -> 18563 | AB7: ='[1]Water-Meter'!P9 -> 18575 | AC7: =SUM(AB7-AA7) -> 12
A8: =Gen!B15 -> 0.506 | B8: =Gen!A15 -> 43774 | D8: =E7 -> 8061 | E8: 8065.7 | F8: =SUM(E8-D8)*120 -> 564 | H8: =B8 -> 43774 | J8: =SUM(K7) -> 36485 | K8: ='[1]Water-Meter'!G10 -> 36500 | L8: =SUM(K8-J8) -> 15 | M8: =H8 -> 43774 | O8: =SUM(P7) -> 7364 | P8: ='[1]Water-Meter'!J10 -> 7367 | Q8: =SUM(P8-O8) -> 3 | R8: =SUM(Q8/1615) -> 0.0018575851 | S8: =SUM(F8/[1]Gen!T14) -> 0.090631528 | T8: =M8 -> 43774 | V8: =W7 -> 7262.5 | W8: 7266.8 | X8: =(W8-V8)*200 -> 860 | Y8: =T8 -> 43774 | AA8: =SUM(AB7) -> 18575 | AB8: ='[1]Water-Meter'!P10 -> 18586 | AC8: =SUM(AB8-AA8) -> 11
A9: =Gen!B16 -> 0.312 | B9: =Gen!A16 -> 43775 | D9: =E8 -> 8065.7 | E9: 8069.9 | F9: =SUM(E9-D9)*120 -> 504 | H9: =B9 -> 43775 | J9: =SUM(K8) -> 36500 | K9: ='[1]Water-Meter'!G11 -> 36516 | L9: =SUM(K9-J9) -> 16 | M9: =H9 -> 43775 | O9: =SUM(P8) -> 7367 | P9: ='[1]Water-Meter'!J11 -> 7369 | Q9: =SUM(P9-O9) -> 2 | R9: =SUM(Q9/1615) -> 0.0012383901 | S9: =SUM(F9/[1]Gen!T15) -> 0.084224599 | T9: =M9 -> 43775 | V9: =W8 -> 7266.8 | W9: 7271.1 | X9: =(W9-V9)*200 -> 860 | Y9: =T9 -> 43775 | AA9: =SUM(AB8) -> 18586 | AB9: ='[1]Water-Meter'!P11 -> 18593 | AC9: =SUM(AB9-AA9) -> 7
A10: =Gen!B17 -> 0.195 | B10: =Gen!A17 -> 43776 | D10: =E9 -> 8069.9 | E10: 8073.8 | F10: =SUM(E10-D10)*120 -> 468 | H10: =B10 -> 43776 | J10: =SUM(K9) -> 36516 | K10: ='[1]Water-Meter'!G12 -> 36529 | L10: =SUM(K10-J10) -> 13 | M10: =H10 -> 43776 | O10: =SUM(P9) -> 7369 | P10: ='[1]Water-Meter'!J12 -> 7372 | Q10: =SUM(P10-O10) -> 3 | R10: =SUM(Q10/1615) -> 0.0018575851 | S10: =SUM(F10/[1]Gen!T16) -> 0.076683598 | T10: =M10 -> 43776 | V10: =W9 -> 7271.1 | W10: 7274.6 | X10: =(W10-V10)*200 -> 700 | Y10: =T10 -> 43776 | AA10: =SUM(AB9) -> 18593 | AB10: ='[1]Water-Meter'!P12 -> 18606 | AC10: =SUM(AB10-AA10) -> 13 | AH10: 5850
A11: =Gen!B18 -> 0.169 | B11: =Gen!A18 -> 43777 | D11: =E10 -> 8073.8 | E11: 8078.1 | F11: =SUM(E11-D11)*120 -> 516 | H11: =B11 -> 43777 | J11: =SUM(K10) -> 36529 | K11: ='[1]Water-Meter'!G13 -> 36543 | L11: =SUM(K11-J11) -> 14 | M11: =H11 -> 43777 | O11: =SUM(P10) -> 7372 | P11: ='[1]Water-Meter'!J13 -> 7374 | Q11: =SUM(P11-O11) -> 2 | R11: =SUM(Q11/1615) -> 0.0012383901 | S11: =SUM(F11/[1]Gen!T17) -> 0.092539455 | T11: =M11 -> 43777 | V11: =W10 -> 7274.6 | W11: 7278.3 | X11: =(W11-V11)*200 -> 740 | Y11: =T11 -> 43777 | AA11: =SUM(AB10) -> 18606 | AB11: ='[1]Water-Meter'!P13 -> 18616 | AC11: =SUM(AB11-AA11) -> 10
A12: =Gen!B19 -> 0.169 | B12: =Gen!A19 -> 43778 | D12: =E11 -> 8078.1 | E12: 8082.2 | F12: =SUM(E12-D12)*120 -> 492 | H12: =B12 -> 43778 | J12: =SUM(K11) -> 36543 | K12: ='[1]Water-Meter'!G14 -> 36560 | L12: =SUM(K12-J12) -> 17 | M12: =H12 -> 43778 | O12: =SUM(P11) -> 7374 | P12: ='[1]Water-Meter'!J14 -> 7377 | Q12: =SUM(P12-O12) -> 3 | R12: =SUM(Q12/1615) -> 0.0018575851 | S12: =SUM(F12/[1]Gen!T18) -> 0.088937093 | T12: =M12 -> 43778 | V12: =W11 -> 7278.3 | W12: 7282.3 | X12: =(W12-V12)*200 -> 800 | Y12: =T12 -> 43778 | AA12: =SUM(AB11) -> 18616 | AB12: ='[1]Water-Meter'!P14 -> 18623
A13: =Gen!B20 -> 0.468 | B13: =Gen!A20 -> 43779 | D13: =E12 -> 8082.2 | E13: 8086.2 | F13: =SUM(E13-D13)*120 -> 480 | H13: =B13 -> 43779 | J13: =SUM(K12) -> 36560 | K13: ='[1]Water-Meter'!G15 -> 36574 | L13: =SUM(K13-J13) -> 14 | M13: =H13 -> 43779 | O13: =SUM(P12) -> 7377 | P13: ='[1]Water-Meter'!J15 -> 7381 | Q13: =SUM(P13-O13) -> 4 | R13: =SUM(Q13/1615) -> 0.0024767802 | S13: =SUM(F13/[1]Gen!T19) -> 0.077009466 | T13: =M13 -> 43779 | V13: =W12 -> 7282.3 | W13: 7285.9 | X13: =(W13-V13)*200 -> 720 | Y13: =T13 -> 43779 | AA13: =SUM(AB12) -> 18623 | AB13: ='[1]Water-Meter'!P15 -> 18634 | AC13: =SUM(AB13-AA13) -> 11
A14: =Gen!B21 -> 0.948 | B14: =Gen!A21 -> 43780 | D14: =E13 -> 8086.2 | E14: 8091 | F14: =SUM(E14-D14)*120 -> 576 | H14: =B14 -> 43780 | J14: =SUM(K13) -> 36574 | K14: ='[1]Water-Meter'!G16 -> 36591 | L14: =SUM(K14-J14) -> 17 | M14: =H14 -> 43780 | O14: =SUM(P13) -> 7381 | P14: ='[1]Water-Meter'!J16 -> 7385 | Q14: =SUM(P14-O14) -> 4 | R14: =SUM(Q14/1615) -> 0.0024767802 | S14: =SUM(F14/[1]Gen!T20) -> 0.095002474 | T14: =M14 -> 43780 | V14: =W13 -> 7285.9 | W14: 7290.8 | X14: =(W14-V14)*200 -> 980 | Y14: =T14 -> 43780 | AA14: =SUM(AB13) -> 18634 | AB14: ='[1]Water-Meter'!P16 -> 18643 | AC14: =SUM(AB14-AA14) -> 9
A15: =Gen!B22 -> 0.935 | B15: =Gen!A22 -> 43781 | D15: =E14 -> 8091 | E15: 8095.4 | F15: =SUM(E15-D15)*120 -> 528 | H15: =B15 -> 43781 | J15: =SUM(K14) -> 36591 | K15: ='[1]Water-Meter'!G17 -> 36605 | L15: =SUM(K15-J15) -> 14 | M15: =H15 -> 43781 | O15: =SUM(P14) -> 7385 | P15: ='[1]Water-Meter'!J17 -> 7388 | Q15: =SUM(P15-O15) -> 3 | R15: =SUM(Q15/1615) -> 0.0018575851 | S15: =SUM(F15/[1]Gen!T21) -> 0.088486677 | T15: =M15 -> 43781 | V15: =W14 -> 7290.8 | W15: 7295.1 | X15: =(W15-V15)*200 -> 860 | Y15: =T15 -> 43781 | AA15: =SUM(AB14) -> 18643 | AB15: ='[1]Water-Meter'!P17 -> 18652 | AC15: =SUM(AB15-AA15) -> 9
A16: =Gen!B23 -> 0.481 | B16: =Gen!A23 -> 43782 | D16: =E15 -> 8095.4 | E16: 8099.6 | F16: =SUM(E16-D16)*120 -> 504 | H16: =B16 -> 43782 | J16: =SUM(K15) -> 36605 | K16: ='[1]Water-Meter'!G18 -> 36619 | L16: =SUM(K16-J16) -> 14 | M16: =H16 -> 43782 | O16: =SUM(P15) -> 7388 | P16: ='[1]Water-Meter'!J18 -> 7390 | Q16: =SUM(P16-O16) -> 2 | R16: =SUM(Q16/1615) -> 0.0012383901 | S16: =SUM(F16/[1]Gen!T22) -> 0.085962818 | T16: =M16 -> 43782 | V16: =W15 -> 7295.1 | W16: 7298.6 | X16: =(W16-V16)*200 -> 700 | Y16: =T16 -> 43782 | AA16: =SUM(AB15) -> 18652 | AB16: ='[1]Water-Meter'!P18 -> 18661 | AC16: =SUM(AB16-AA16) -> 9
A17: =Gen!B24 -> 0.526 | B17: =Gen!A24 -> 43783 | D17: =E16 -> 8099.6 | E17: 8103.7 | F17: =SUM(E17-D17)*120 -> 492 | H17: =B17 -> 43783 | J17: =SUM(K16) -> 36619 | K17: ='[1]Water-Meter'!G19 -> 36632 | L17: =SUM(K17-J17) -> 13 | M17: =H17 -> 43783 | O17: =SUM(P16) -> 7390 | P17: ='[1]Water-Meter'!J19 -> 7393 | Q17: =SUM(P17-O17) -> 3 | R17: =SUM(Q17/1615) -> 0.0018575851 | S17: =SUM(F17/[1]Gen!T23) -> 0.086013986 | T17: =M17 -> 43783 | V17: =W16 -> 7298.6 | W17: 7303.5 | X17: =(W17-V17)*200 -> 980 | Y17: =T17 -> 43783 | AA17: =SUM(AB16) -> 18661 | AB17: ='[1]Water-Meter'!P19 -> 18672 | AC17: =SUM(AB17-AA17) -> 11
A18: =Gen!B25 -> 0.221 | B18: =Gen!A25 -> 43784 | D18: =E17 -> 8103.7 | E18: 8107.8 | F18: =SUM(E18-D18)*120 -> 492 | H18: =B18 -> 43784 | J18: =SUM(K17) -> 36632 | K18: ='[1]Water-Meter'!G20 -> 36651 | L18: =SUM(K18-J18) -> 19 | M18: =H18 -> 43784 | O18: =SUM(P17) -> 7393 | P18: ='[1]Water-Meter'!J20 -> 7396 | Q18: =SUM(P18-O18) -> 3 | R18: =SUM(Q18/1615) -> 0.0018575851 | S18: =SUM(F18/[1]Gen!T24) -> 0.079418886 | T18: =M18 -> 43784 | V18: =W17 -> 7303.5 | W18: 7307.9 | X18: =(W18-V18)*200 -> 880 | Y18: =T18 -> 43784 | AA18: =SUM(AB17) -> 18672 | AB18: ='[1]Water-Meter'!P20 -> 18680 | AC18: =SUM(AB18-AA18) -> 8
A19: =Gen!B26 -> 0.156 | B19: =Gen!A26 -> 43785 | D19: =E18 -> 8107.8 | E19: 8111.9 | F19: =SUM(E19-D19)*120 -> 492 | H19: =B19 -> 43785 | J19: =SUM(K18) -> 36651 | K19: ='[1]Water-Meter'!G21 -> 36668 | L19: =SUM(K19-J19) -> 17 | M19: =H19 -> 43785 | O19: =SUM(P18) -> 7396 | P19: ='[1]Water-Meter'!J21 -> 7398 | Q19: =SUM(P19-O19) -> 2 | R19: =SUM(Q19/1615) -> 0.0012383901 | S19: =SUM(F19/[1]Gen!T25) -> 0.07627907 | T19: =M19 -> 43785 | V19: =W18 -> 7307.9 | W19: 7313.9 | X19: =(W19-V19)*200 -> 1200 | Y19: =T19 -> 43785 | AA19: =SUM(AB18) -> 18680 | AB19: ='[1]Water-Meter'!P21 -> 18689 | AC19: =SUM(AB19-AA19) -> 9
A20: =Gen!B27 -> 0.623 | B20: =Gen!A27 -> 43786 | D20: =E19 -> 8111.9 | E20: 8116.2 | F20: =SUM(E20-D20)*120 -> 516 | H20: =B20 -> 43786 | J20: =SUM(K19) -> 36668 | K20: ='[1]Water-Meter'!G22 -> 36681 | L20: =SUM(K20-J20) -> 13 | M20: =H20 -> 43786 | O20: =SUM(P19) -> 7398 | P20: ='[1]Water-Meter'!J22 -> 7402 | Q20: =SUM(P20-O20) -> 4 | R20: =SUM(Q20/1615) -> 0.0024767802 | S20: =SUM(F20/[1]Gen!T26) -> 0.07462039 | T20: =M20 -> 43786 | V20: =W19 -> 7313.9 | W20: 7317.9 | X20: =(W20-V20)*200 -> 800 | Y20: =T20 -> 43786 | AA20: =SUM(AB19) -> 18689 | AB20: ='[1]Water-Meter'!P22 -> 18701 | AC20: =SUM(AB20-AA20) -> 12
A21: =Gen!B28 -> 0.519 | B21: =Gen!A28 -> 43787 | D21: =E20 -> 8116.2 | E21: 8120.5 | F21: =SUM(E21-D21)*120 -> 516 | H21: =B21 -> 43787 | J21: =SUM(K20) -> 36681 | K21: ='[1]Water-Meter'!G23 -> 36696 | L21: =SUM(K21-J21) -> 15 | M21: =H21 -> 43787 | O21: =SUM(P20) -> 7402 | P21: ='[1]Water-Meter'!J23 -> 7404 | Q21: =SUM(P21-O21) -> 2 | R21: =SUM(Q21/1615) -> 0.0012383901 | S21: =SUM(F21/[1]Gen!T28) -> 0.098154841 | T21: =M21 -> 43787 | V21: =W20 -> 7317.9 | W21: 7322 | X21: =(W21-V21)*200 -> 820 | Y21: =T21 -> 43787 | AA21: =SUM(AB20) -> 18701 | AB21: ='[1]Water-Meter'!P23 -> 18712 | AC21: =SUM(AB21-AA21) -> 11
A22: =Gen!B29 -> 0.091 | B22: =Gen!A29 -> 43788 | D22: =E21 -> 8120.5 | E22: 8124.6 | F22: =SUM(E22-D22)*120 -> 492 | H22: =B22 -> 43788 | J22: =SUM(K21) -> 36696 | K22: ='[1]Water-Meter'!G24 -> 36708 | L22: =SUM(K22-J22) -> 12 | M22: =H22 -> 43788 | O22: =SUM(P21) -> 7404 | P22: ='[1]Water-Meter'!J24 -> 7408 | Q22: =SUM(P22-O22) -> 4 | R22: =SUM(Q22/1615) -> 0.0024767802 | S22: =SUM(F22/[1]Gen!T29) -> 0.10488169 | T22: =M22 -> 43788 | V22: =W21 -> 7322 | W22: 7326.5 | X22: =(W22-V22)*200 -> 900 | Y22: =T22 -> 43788 | AA22: =SUM(AB21) -> 18712 | AB22: ='[1]Water-Meter'!P24 -> 18719 | AC22: =SUM(AB22-AA22) -> 7
A23: =Gen!B30 -> 0.117 | B23: =Gen!A30 -> 43789 | D23: =E22 -> 8124.6 | E23: 8128.2 | F23: =SUM(E23-D23)*120 -> 432 | H23: =B23 -> 43789 | J23: =SUM(K22) -> 36708 | K23: ='[1]Water-Meter'!G25 -> 36724 | L23: =SUM(K23-J23) -> 16 | M23: =H23 -> 43789 | O23: =SUM(P22) -> 7408 | P23: ='[1]Water-Meter'!J25 -> 7412 | Q23: =SUM(P23-O23) -> 4 | R23: =SUM(Q23/1615) -> 0.0024767802 | S23: =SUM(F23/[1]Gen!T30) -> 0.075630252 | T23: =M23 -> 43789 | V23: =W22 -> 7326.5 | W23: 7329.8 | X23: =(W23-V23)*200 -> 660 | Y23: =T23 -> 43789 | AA23: =SUM(AB22) -> 18719 | AB23: ='[1]Water-Meter'!P25 -> 18728 | AC23: =SUM(AB23-AA23) -> 9
A24: =Gen!B31 -> 0.13 | B24: =Gen!A31 -> 43790 | D24: =SUM(E23) -> 8128.2 | E24: 8131.9 | F24: =SUM(E24-D24)*120 -> 444 | H24: =B24 -> 43790 | J24: =SUM(K23) -> 36724 | K24: ='[1]Water-Meter'!G26 -> 36740 | L24: =SUM(K24-J24) -> 16 | M24: =H24 -> 43790 | O24: =SUM(P23) -> 7412 | P24: ='[1]Water-Meter'!J26 -> 7415 | Q24: =SUM(P24-O24) -> 3 | R24: =SUM(Q24/1615) -> 0.0018575851 | S24: =SUM(F24/[1]Gen!T31) -> 0.074734893 | T24: 5835.7 | V24: =W23 -> 7329.8 | W24: 7332.3 | X24: =(W24-V24)*200 -> 500 | Y24: =T24 -> 5835.7 | AA24: =SUM(AB23) -> 18728 | AB24: ='[1]Water-Meter'!P26 -> 18737 | AC24: =SUM(AB24-AA24) -> 9
A25: =Gen!B32 -> 0.143 | B25: =Gen!A32 -> 43791 | D25: =SUM(E24) -> 8131.9 | E25: 8135.8 | F25: =SUM(E25-D25)*120 -> 468 | H25: =B25 -> 43791 | J25: =SUM(K24) -> 36740 | K25: ='[1]Water-Meter'!G27 -> 36754 | L25: =SUM(K25-J25) -> 14 | M25: =H25 -> 43791 | O25: =SUM(P24) -> 7415 | P25: ='[1]Water-Meter'!J27 -> 7418 | Q25: =SUM(P25-O25) -> 3 | R25: =SUM(Q25/1615) -> 0.0018575851 | S25: =SUM(F25/[1]Gen!T32) -> 0.086666667 | T25: =M25 -> 43791 | V25: =W24 -> 7332.3 | W25: 7334.4 | X25: =(W25-V25)*200 -> 420 | Y25: =T25 -> 43791 | AA25: =SUM(AB24) -> 18737 | AB25: ='[1]Water-Meter'!P27 -> 18746 | AC25: =SUM(AB25-AA25) -> 9
A26: =Gen!B33 -> 0.169 | B26: =Gen!A33 -> 43792 | D26: =SUM(E25) -> 8135.8 | F26: =SUM(E26-D26)*120 -> -976296 | H26: =B26 -> 43792 | J26: =SUM(K25) -> 36754 | K26: ='[1]Water-Meter'!G28 -> 36767 | L26: =SUM(K26-J26) -> 13 | M26: =H26 -> 43792 | O26: =SUM(P25) -> 7418 | P26: ='[1]Water-Meter'!J28 -> 7421 | Q26: =SUM(P26-O26) -> 3 | R26: =SUM(Q26/1615) -> 0.0018575851 | S26: =SUM(F26/[1]Gen!T33) -> -181.77174 | T26: =M26 -> 43792 | V26: =W25 -> 7334.4 | X26: =(W26-V26)*200 -> -1466880 | Y26: =T26 -> 43792 | AA26: =SUM(AB25) -> 18746 | AB26: ='[1]Water-Meter'!P28 -> 18754 | AC26: =SUM(AB26-AA26) -> 8
A27: =Gen!B34 -> 0 | B27: =Gen!A34 -> 43793 | D27: =SUM(E26) -> 0 | F27: =SUM(E27-D27)*120 -> 0 | H27: =B27 -> 43793 | J27: =SUM(K26) -> 36767 | K27: ='[1]Water-Meter'!G29 -> 36779 | L27: =SUM(K27-J27) -> 12 | M27: =H27 -> 43793 | O27: =SUM(P26) -> 7421 | P27: ='[1]Water-Meter'!J29 -> 7423 | Q27: =SUM(P27-O27) -> 2 | R27: =SUM(Q27/1615) -> 0.0012383901 | S27: =SUM(F27/[1]Gen!T34) -> 0 | T27: =M27 -> 43793 | V27: =W26 -> 0 | X27: =(W27-V27)*200 -> 0 | Y27: =T27 -> 43793 | AA27: =SUM(AB26) -> 18754 | AB27: ='[1]Water-Meter'!P29 -> 18763 | AC27: =SUM(AB27-AA27) -> 9
A28: =Gen!B35 -> 0 | B28: =Gen!A35 -> 43794 | D28: =SUM(E27) -> 0 | F28: =SUM(E28-D28)*120 -> 0 | H28: =B28 -> 43794 | J28: =SUM(K27) -> 36779 | K28: ='[1]Water-Meter'!G30 -> 36792 | L28: =SUM(K28-J28) -> 13 | M28: =H28 -> 43794 | O28: =SUM(P27) -> 7423 | P28: ='[1]Water-Meter'!J30 -> 7426 | Q28: =SUM(P28-O28) -> 3 | R28: =SUM(Q28/1615) -> 0.0018575851 | S28: =SUM(F28/[1]Gen!T35) -> 0 | T28: =M28 -> 43794 | V28: =W27 -> 0 | X28: =(W28-V28)*200 -> 0 | Y28: =T28 -> 43794 | AA28: =SUM(AB27) -> 18763 | AB28: ='[1]Water-Meter'!P30 -> 18773 | AC28: =SUM(AB28-AA28) -> 10
A29: =Gen!B36 -> 0 | B29: =Gen!A36 -> 43795 | D29: =SUM(E28) -> 0 | F29: =SUM(E29-D29)*120 -> 0 | H29: =B29 -> 43795 | J29: =SUM(K28) -> 36792 | K29: ='[1]Water-Meter'!G31 -> 36809 | L29: =SUM(K29-J29) -> 17 | M29: =H29 -> 43795 | O29: =SUM(P28) -> 7426 | P29: ='[1]Water-Meter'!J31 -> 7428 | Q29: =SUM(P29-O29) -> 2 | R29: =SUM(Q29/1615) -> 0.0012383901 | S29: =SUM(F29/[1]Gen!T36) -> 0 | T29: =M29 -> 43795 | V29: =W28 -> 0 | X29: =(W29-V29)*200 -> 0 | Y29: =T29 -> 43795 | AA29: =SUM(AB28) -> 18773 | AB29: ='[1]Water-Meter'!P31 -> 18782 | AC29: =SUM(AB29-AA29) -> 9
A30: =Gen!B37 -> 0 | B30: =Gen!A37 -> 43796 | D30: =SUM(E29) -> 0 | F30: =SUM(E30-D30)*120 -> 0 | H30: =B30 -> 43796 | J30: =SUM(K29) -> 36809 | K30: ='[1]Water-Meter'!G32 -> 36825 | L30: =SUM(K30-J30) -> 16 | M30: =H30 -> 43796 | O30: =SUM(P29) -> 7428 | P30: ='[1]Water-Meter'!J32 -> 7432 | Q30: =SUM(P30-O30) -> 4 | R30: =SUM(Q30/1615) -> 0.0024767802 | S30: =SUM(F30/[1]Gen!T37) -> 0 | T30: =M30 -> 43796 | V30: =W29 -> 0 | X30: =(W30-V30)*200 -> 0 | Y30: =T30 -> 43796 | AA30: =SUM(AB29) -> 18782 | AB30: ='[1]Water-Meter'!P32 -> 18790 | AC30: =SUM(AB30-AA30) -> 8
A31: =Gen!B38 -> 0 | B31: =Gen!A38 -> 43797 | D31: =SUM(E30) -> 0 | F31: =SUM(E31-D31)*120 -> 0 | H31: =B31 -> 43797 | J31: =SUM(K30) -> 36825 | K31: ='[1]Water-Meter'!G33 -> #REF! | L31: =SUM(K31-J31) -> #REF! | M31: =H31 -> 43797 | O31: =SUM(P30) -> 7432 | P31: ='[1]Water-Meter'!J33 -> #REF! | Q31: =SUM(P31-O31) -> #REF! | R31: =SUM(Q31/1615) -> #REF! | S31: =SUM(F31/[1]Gen!T38) -> #DIV/0! | T31: =M31 -> 43797 | V31: =W30 -> 0 | X31: =(W31-V31)*200 -> 0 | Y31: =T31 -> 43797 | AA31: =SUM(AB30) -> 18790 | AB31: ='[1]Water-Meter'!P33 -> #REF! | AC31: =SUM(AB31-AA31) -> #REF!
A32: =Gen!B39 -> 0 | B32: =Gen!A39 -> 43798 | D32: =SUM(E31) -> 0 | F32: =SUM(E32-D32)*120 -> 0 | H32: =B32 -> 43798 | J32: =SUM(K31) -> #REF! | K32: ='[1]Water-Meter'!G34 -> #REF! | L32: =SUM(K32-J32) -> #REF! | M32: =H32 -> 43798 | O32: =SUM(P31) -> #REF! | P32: ='[1]Water-Meter'!J34 -> #REF! | Q32: =SUM(P32-O32) -> #REF! | R32: =SUM(Q32/1615) -> #REF! | S32: =SUM(F32/[1]Gen!T39) -> #DIV/0! | T32: =M32 -> 43798 | V32: =W31 -> 0 | X32: =(W32-V32)*200 -> 0 | Y32: =T32 -> 43798 | AA32: =SUM(AB31) -> #REF! | AB32: ='[1]Water-Meter'!P34 -> #REF! | AC32: =SUM(AB32-AA32) -> #REF!
A33: =Gen!B40 -> 0 | B33: =Gen!A40 -> 43799 | D33: =SUM(E32) -> 0 | F33: =SUM(E33-D33)*120 -> 0 | H33: =B33 -> 43799 | J33: =SUM(K32) -> #REF! | K33: ='[1]Water-Meter'!G35 -> #REF! | L33: =SUM(K33-J33) -> #REF! | M33: =H33 -> 43799 | O33: =SUM(P32) -> #REF! | P33: ='[1]Water-Meter'!J35 -> #REF! | Q33: =SUM(P33-O33) -> #REF! | R33: =SUM(Q33/1615) -> #REF! | S33: =SUM(F33/[1]Gen!T40) -> #DIV/0! | T33: =M33 -> 43799 | V33: =W32 -> 0 | X33: =(W33-V33)*200 -> 0 | Y33: =T33 -> 43799 | AA33: =SUM(AB32) -> #REF! | AB33: ='[1]Water-Meter'!P35 -> #REF! | AC33: =SUM(AB33-AA33) -> #REF!
A34: =Gen!B41 -> 0 | B34: =Gen!A41 -> 43800 | D34: =SUM(E33) -> 0 | F34: =SUM(E34-D34)*120 -> 0 | H34: =B34 -> 43800 | J34: =SUM(K33) -> #REF! | K34: ='[1]Water-Meter'!G36 -> #REF! | L34: =SUM(K34-J34) -> #REF! | M34: =H34 -> 43800 | O34: =SUM(P33) -> #REF! | P34: ='[1]Water-Meter'!J36 -> #REF! | Q34: =SUM(P34-O34) -> #REF! | R34: =SUM(Q34/1615) -> #REF! | S34: =SUM(F34/[1]Gen!T41) -> #DIV/0! | T34: =M34 -> 43800 | V34: =SUM(W33) -> 0 | X34: =(W34-V34)*200 -> 0 | Y34: =T34 -> 43800 | AA34: =SUM(AB33) -> #REF! | AB34: ='[1]Water-Meter'!P36 -> #REF! | AC34: =SUM(AB34-AA34) -> #REF!
A35: =[1]Gen!B42 -> #REF! | B35: =[1]Gen!A42 -> #REF! | D35: =SUM(E34) -> 0 | F35: =SUM(F4:F6) -> 1524 | H35: =B35 -> #REF! | J35: =SUM(K34) -> #REF! | K35: ='[1]Water-Meter'!G37 -> #REF! | L35: =SUM(L5:L34) -> #REF! | M35: =H35 -> #REF! | O35: =SUM(P34) -> #REF! | P35: ='[1]Water-Meter'!J37 -> #REF! | Q35: =SUM(Q5:Q34) -> #REF! | R35: =SUM(Q35/1615) -> #REF! | S35: =SUM(F35/[1]Gen!T42) -> #DIV/0! | T35: =M35 -> #REF! | V35: =SUM(W34) -> 0 | X35: =(W35-V35)*200 -> 0 | Y35: =T35 -> #REF! | AA35: =SUM(AB34) -> #REF! | AB35: ='[1]Water-Meter'!P37 -> #REF! | AC35: =SUM(AC5:AC34) -> #REF!
X36: =SUM(X4:X6) -> 2580

Sheet Summery Report
A2: Generator and Diseal Summry Report 2019
A4: Date | B4: Gen Set Hours Working | C4: Occ% | D4: Total OCC Room | E4: Guest Room Occ | F4: Total Kwh Generated | G4: Diesel consumed by Gen (Ltrs) | H4: Diesel consumed by Vehicle (Ltrs) | I4: Total diesel consumed (Ltrs) | J4: Balance stock of Diesel (Ltrs) | K4: Water consumed | L4: Gas consumed (KG)
A5: =Gen!A11 -> 43770 | B5: ='Daily report Gen'!Z6 -> 41 | C5: =Gen!B11 -> 0.87 | D5: =E5 -> 66 | E5: 66 | F5: =Gen!T9 -> 0 | G5: =Gen!S9 -> 0 | H5: =Gen!AJ11 -> 69.05 | I5: =SUM(G5:H5) -> 69.05 | J5: =Gen!C11 -> 35194.41 | K5: ='Water-Meter'!E6 -> 128 | L5: ='Lpg (2)'!G10 -> 208.34 | M5: =SUM(#REF!-#REF!) -> #REF!
A6: =Gen!A12 -> 43771 | B6: ='Daily report Gen'!Z7 -> 46 | C6: =Gen!B12 -> 0.766 | D6: =E6 -> 58 | E6: 58 | F6: =Gen!T10 -> 0 | G6: =Gen!S10 -> 0 | H6: =Gen!AJ12 -> 659.55 | I6: =SUM(G6:H6) -> 659.55 | J6: =Gen!C12 -> 50727.24 | K6: ='Water-Meter'!E7 -> 139 | L6: ='Lpg (2)'!G11 -> 101.376 | M6: =SUM(#REF!-#REF!) -> #REF!
A7: =Gen!A13 -> 43772 | B7: ='Daily report Gen'!Z8 -> 43 | C7: =Gen!B13 -> 0.11 | D7: =E7 -> 9 | E7: 9 | F7: =Gen!T11 -> 5703 | G7: =Gen!S11 -> 2398.12 | H7: =Gen!AJ13 -> 261.5 | I7: =SUM(G7:H7) -> 2659.62 | J7: =Gen!C13 -> 47565.12 | K7: ='Water-Meter'!E8 -> 132 | L7: ='Lpg (2)'!G12 -> 101.464 | M7: =SUM(#REF!-#REF!) -> #REF!
A8: =Gen!A14 -> 43773 | B8: ='Daily report Gen'!Z9 -> 40 | C8: =Gen!B14 -> 0.13 | D8: =E8 -> 10 | E8: 10 | F8: =Gen!T12 -> 6052 | G8: =Gen!S12 -> 2502.57 | H8: =Gen!AJ14 -> 17.39 | I8: =SUM(G8:H8) -> 2519.96 | J8: =Gen!C14 -> 45216.79 | K8: ='Water-Meter'!E9 -> 100 | L8: ='Lpg (2)'!G13 -> 132.616 | M8: =SUM(#REF!-#REF!) -> #REF!
A9: =Gen!A15 -> 43774 | B9: ='Daily report Gen'!Z10 -> 39 | C9: =Gen!B15 -> 0.506 | D9: =E9 -> 25 | E9: 25 | F9: =Gen!T13 -> 5227 | G9: =Gen!S13 -> 2086.83 | H9: =Gen!AJ15 -> 18.94 | I9: =SUM(G9:H9) -> 2105.77 | J9: =Gen!C15 -> 43365.19 | K9: ='Water-Meter'!E10 -> 119 | L9: ='Lpg (2)'!G14 -> 147.18 | M9: =SUM(#REF!-#REF!) -> #REF!
A10: =Gen!A16 -> 43775 | B10: ='Daily report Gen'!Z11 -> 48 | C10: =Gen!B16 -> 0.312 | D10: =E10 -> 24 | E10: 24 | F10: =Gen!T14 -> 4812 | G10: =Gen!S14 -> 1834.21 | H10: =Gen!AJ16 -> 142.33 | I10: =SUM(G10:H10) -> 1976.54 | J10: =Gen!C16 -> 41228.55 | K10: ='Water-Meter'!E11 -> 110 | L10: ='Lpg (2)'!G15 -> 144.672 | M10: =SUM(#REF!-#REF!) -> #REF!
A11: =Gen!A17 -> 43776 | B11: ='Daily report Gen'!Z12 -> 41 | C11: =Gen!B17 -> 0.195 | D11: =E11 -> 17 | E11: 17 | F11: =Gen!T15 -> 5035 | G11: =Gen!S15 -> 2117.7 | H11: =Gen!AJ17 -> 241.32 | I11: =SUM(G11:H11) -> 2359.02 | J11: =Gen!C17 -> 38650.49 | K11: ='Water-Meter'!E12 -> 95 | L11: ='Lpg (2)'!G16 -> 149.072 | M11: =SUM(#REF!-#REF!) -> #REF!
A12: =Gen!A18 -> 43777 | B12: ='Daily report Gen'!Z13 -> 44 | C12: =Gen!B18 -> 0.169 | D12: =E12 -> 13 | E12: 13 | F12: =Gen!T16 -> 5420 | G12: =Gen!S16 -> 2435.73 | H12: =Gen!AJ18 -> 159.05 | I12: =SUM(G12:H12) -> 2594.78 | J12: =Gen!C18 -> 51179.21 | K12: ='Water-Meter'!E13 -> 120 | L12: ='Lpg (2)'!G17 -> 152.064 | M12: =SUM(#REF!-#REF!) -> #REF!
A13: =Gen!A19 -> 43778 | B13: ='Daily report Gen'!Z14 -> 43 | C13: =Gen!B19 -> 0.169 | D13: =E13 -> 13 | E13: 13 | F13: =Gen!T17 -> 5338 | G13: =Gen!S17 -> 2229.96 | H13: =Gen!AJ19 -> 122.96 | I13: =SUM(G13:H13) -> 2352.92 | J13: =Gen!C19 -> 48919.71 | K13: ='Water-Meter'!E14 -> 96 | L13: ='Lpg (2)'!G18 -> 152.284 | M13: =SUM(#REF!-#REF!) -> #REF!
A14: =Gen!A20 -> 43779 | B14: ='Daily report Gen'!Z15 -> 42 | C14: =Gen!B20 -> 0.468 | D14: =E14 -> 36 | E14: 36 | F14: =Gen!T18 -> 5670 | G14: =Gen!S18 -> 2100.45 | H14: =Gen!AJ20 -> 231.5 | I14: =SUM(G14:H14) -> 2331.95 | J14: =Gen!C20 -> 46666.58 | K14: ='Water-Meter'!E15 -> 124 | L14: ='Lpg (2)'!G19 -> 103.488 | M14: =SUM(#REF!-#REF!) -> #REF!
A15: =Gen!A21 -> 43780 | B15: ='Daily report Gen'!Z16 -> 47 | C15: =Gen!B21 -> 0.948 | D15: =E15 -> 73 | E15: 73 | F15: =Gen!T19 -> 5594 | G15: =Gen!S19 -> 2130.17 | H15: =Gen!AJ21 -> 0 | I15: =SUM(G15:H15) -> 2130.17 | J15: =Gen!C21 -> 44193.28 | K15: ='Water-Meter'!E16 -> 131 | L15: ='Lpg (2)'!G20 -> 101.772 | M15: =SUM(#REF!-#REF!) -> #REF!
A16: =Gen!A22 -> 43781 | B16: ='Daily report Gen'!Z17 -> 46 | C16: =Gen!B22 -> 0.935 | D16: =E16 -> 73 | E16: 73 | F16: =Gen!T20 -> 5487 | G16: =Gen!S20 -> 2241.8 | H16: =Gen!AJ22 -> 187.81 | I16: =SUM(G16:H16) -> 2429.61 | J16: =Gen!C22 -> 41540.83 | K16: ='Water-Meter'!E17 -> 136 | L16: ='Lpg (2)'!G21 -> 115.192 | M16: =SUM(#REF!-#REF!) -> #REF!
... A27: =Gen!A33 -> 43792 | B27: ='Daily report Gen'!Z28 -> -145094 | C27: =Gen!B33 -> 0.169 | D27: =E27 -> 13 | E27: 13 | F27: =Gen!T31 -> 4311 | G27: =Gen!S31 -> 1557.2 | H27: =Gen!AJ33 -> 0 | I27: =SUM(G27:H27) -> 1557.2 | J27: =Gen!C33 -> 34416.85 | K27: ='Water-Meter'!E28 -> 0 | L27: ='Lpg (2)'!G32 -> -298772.32 | M27: =SUM(#REF!-#REF!) -> #REF!
A28: =Gen!A34 -> 43793 | B28: ='Daily report Gen'!Z29 -> 0 | C28: =Gen!B34 -> 0 | D28: =E28 -> 0 | F28: =Gen!T32 -> 4323 | G28: =Gen!S32 -> 1822.89 | H28: =Gen!AJ34 -> 0 | I28: =SUM(G28:H28) -> 1822.89 | J28: =Gen!C34 -> 34416.85 | K28: ='Water-Meter'!E29 -> 0 | L28: ='Lpg (2)'!G33 -> 0 | M28: =SUM(#REF!-#REF!) -> #REF!
A29: =Gen!A35 -> 43794 | B29: ='Daily report Gen'!Z30 -> 0 | C29: =Gen!B35 -> 0 | D29: =E29 -> 0 | F29: =Gen!T33 -> 0 | G29: =Gen!S33 -> 0 | H29: =Gen!AJ35 -> 0 | I29: =SUM(G29:H29) -> 0 | J29: =Gen!C35 -> 34416.85 | K29: ='Water-Meter'!E30 -> 0 | L29: ='Lpg (2)'!G34 -> 0 | M29: =SUM(#REF!-#REF!) -> #REF!
A30: =Gen!A36 -> 43795 | B30: ='Daily report Gen'!Z31 -> 0 | C30: =Gen!B36 -> 0 | D30: =E30 -> 0 | F30: =Gen!T34 -> 0 | G30: =Gen!S34 -> 0 | H30: =Gen!AJ36 -> 0 | I30: =SUM(G30:H30) -> 0 | J30: =Gen!C36 -> 34416.85 | K30: ='Water-Meter'!E31 -> 0 | L30: ='Lpg (2)'!G35 -> 0 | M30: =SUM(#REF!-#REF!) -> #REF!
A31: =Gen!A37 -> 43796 | B31: ='Daily report Gen'!Z32 -> 0 | C31: =Gen!B37 -> 0 | D31: =E31 -> 0 | F31: =Gen!T35 -> 0 | G31: =Gen!S35 -> 0 | H31: =Gen!AJ37 -> 0 | I31: =SUM(G31:H31) -> 0 | J31: =Gen!C37 -> 34416.85 | K31: ='Water-Meter'!E32 -> 0 | L31: ='Lpg (2)'!G36 -> 0 | M31: =SUM(#REF!-#REF!) -> #REF!
A32: =Gen!A38 -> 43797 | B32: ='Daily report Gen'!Z33 -> 0 | C32: =Gen!B38 -> 0 | D32: =E32 -> 0 | F32: =Gen!T36 -> 0 | G32: =Gen!S36 -> 0 | H32: =Gen!AJ38 -> 0 | I32: =SUM(G32:H32) -> 0 | J32: =Gen!C38 -> 34416.85 | K32: ='Water-Meter'!E33 -> 0 | L32: ='Lpg (2)'!G37 -> 0 | M32: =SUM(#REF!-#REF!) -> #REF!
A33: =Gen!A39 -> 43798 | B33: ='Daily report Gen'!Z34 -> 0 | C33: =Gen!B39 -> 0 | D33: =E33 -> 0 | F33: =Gen!T37 -> 0 | G33: =Gen!S37 -> 0 | H33: =Gen!AJ39 -> 0 | I33: =SUM(G33:H33) -> 0 | J33: =Gen!C39 -> 34416.85 | K33: ='Water-Meter'!E34 -> 0 | L33: ='Lpg (2)'!G38 -> 0 | M33: =SUM(#REF!-#REF!) -> #REF!
A34: =Gen!A40 -> 43799 | B34: ='Daily report Gen'!Z35 -> 0 | C34: =Gen!B40 -> 0 | D34: =E34 -> 0 | F34: =Gen!T38 -> 0 | G34: =Gen!S38 -> 0 | H34: =Gen!AJ40 -> 0 | I34: =SUM(G34:H34) -> 0 | J34: =Gen!C40 -> 34416.85 | K34: ='Water-Meter'!E35 -> 0 | L34: ='Lpg (2)'!G39 -> 0 | M34: =SUM(#REF!-#REF!) -> #REF!
A35: =Gen!A41 -> 43800 | B35: ='Daily report Gen'!Z36 -> 0 | C35: =Gen!B41 -> 0 | D35: =E35 -> 0 | F35: =Gen!T39 -> 0 | G35: =Gen!S39 -> 0 | H35: =Gen!AJ41 -> 0 | I35: =SUM(G35:H35) -> 0 | J35: =Gen!C41 -> 34416.85 | K35: ='Water-Meter'!E36 -> 0 | L35: ='Lpg (2)'!G40 -> 0 | M35: =SUM(#REF!-#REF!) -> #REF!
A36: =Gen!A42 -> 0 | B36: ='Daily report Gen'!Z37 -> 0 | C36: =Gen!B42 -> 0 | D36: =E36 -> 0 | F36: =Gen!T40 -> 0 | G36: =Gen!S40 -> 0 | H36: =Gen!AJ42 -> 0 | I36: =SUM(G36:H36) -> 0 | J36: =Gen!C42 -> 34416.85 | K36: ='Water-Meter'!E37 -> 0 | L36: ='Lpg (2)'!G41 -> 0
B38: =SUM(B5:B37)/[1]Gen!A47 -> #REF!
B39: =SUM(B38*[1]Gen!A47) -> #REF! | C39: =SUM(B39/250) -> #REF!

Sheet Daily report Gen
A1: 43770
K3: GENERATOR NO.1 | N3: GENERATOR NO.2 | Q3: GENERATOR NO.4 | T3: GENERATOR NO.5 | W3: GENERATOR NO.6
A4: DATE | B4: OCC% | C4: D-TANK A | D4: D-TANK B | E4: DELIVERY DATE | F4: DELIVERY | G4: ISSUED-VEHICLE | H4: OTHERS | I4: M-R LV PANEL 1. KW-HR | J4: M-R LV PANEL 2. KW-HR | K4: OPEN HRS READING | L4: CLOSE HRS READING | M4: RUNNING HRS | N4: OPEN HRS READING | O4: CLOSE HRS READING | P4: RUNNING HRS | Q4: OPEN HRS READING | R4: CLOSE HRS READING | S4: RUNNING HRS | T4: OPEN HRS READING | U4: CLOSE HRS READING | V4: RUNNING HRS | W4: OPEN HRS READING | Y4: RUNNING HRS | Z4: TOTAL RUNNING HRS | AA4: MAX KW | AB4: MIN-KW | AC4: TOTAL DIESEL CONS.
L5: 33200 | O5: 28102 | R5: 33419 | U5: 30941 | X5: 18518
A6: =Gen!A11 -> 43770 | B6: =Gen!B11 -> 0.87 | C6: 17421.26 | D6: 17779.21 | E6: =Gen!D11 -> 0 | G6: 69.05 | I6: 29289.6 | J6: 19296.5 | K6: =L5 -> 33200 | L6: 33210 | M6: =L6-K6 -> 10 | N6: =O5 -> 28102 | O6: 28110 | P6: =O6-N6 -> 8 | Q6: =R5 -> 33419 | R6: 33426 | S6: =R6-Q6 -> 7 | T6: =U5 -> 30941 | U6: 30951 | V6: =U6-T6 -> 10 | W6: =X5 -> 18518 | X6: 18524 | Y6: =X6-W6 -> 6 | Z6: =Y6+V6+S6+P6+M6 -> 41 | AA6: 416 | AB6: 203 | AC6: =Gen!S11 -> 2398.12
A7: =Gen!A12 -> 43771 | B7: =Gen!B12 -> 0.766 | C7: 24259.14 | D7: 25779.21 | E7: =Gen!D12 -> 18000 | G7: 659.55 | I7: 29308.5 | J7: 19308.6 | K7: =L6 -> 33210 | L7: 33218 | M7: =L7-K7 -> 8 | N7: =O6 -> 28110 | O7: 28117 | P7: =O7-N7 -> 7 | Q7: =R6 -> 33426 | R7: 33439 | S7: =R7-Q7 -> 13 | T7: =U6 -> 30951 | U7: 30962 | V7: =U7-T7 -> 11 | W7: =X6 -> 18524 | X7: 18531 | Y7: =X7-W7 -> 7 | Z7: =M7+P7+S7+V7+Y7 -> 46 | AA7: 471 | AB7: 242 | AC7: =Gen!S12 -> 2502.57
A8: =Gen!A13 -> 43772 | B8: =Gen!B13 -> 0.11 | C8: 24259.14 | D8: 20957.65 | E8: =Gen!D13 -> 0 | G8: 261.5 | I8: 29318.6 | J8: 19314.8 | K8: =L7 -> 33218 | L8: 33224 | M8: =L8-K8 -> 6 | N8: =O7 -> 28117 | O8: 28130 | P8: =O8-N8 -> 13 | Q8: =R7 -> 33439 | R8: 33446 | S8: =R8-Q8 -> 7 | T8: =U7 -> 30962 | U8: 30966 | V8: =U8-T8 -> 4 | W8: =X7 -> 18531 | X8: 18544 | Y8: =X8-W8 -> 13 | Z8: =M8+P8+S8+V8+Y8 -> 43 | AA8: 486 | AB8: 220 | AC8: =Gen!S13 -> 2086.83
A9: =Gen!A14 -> 43773 | B9: =Gen!B14 -> 0.13 | C9: 24259.14 | D9: 19106.05 | E9: =Gen!D14 -> 0 | G9: 17.39 | I9: 29328 | J9: 19320.7 | K9: =L8 -> 33224 | L9: 33234 | M9: =L9-K9 -> 10 | N9: =O8 -> 28130 | O9: 28136 | P9: =O9-N9 -> 6 | Q9: =R8 -> 33446 | R9: 33464 | S9: =R9-Q9 -> 18 | T9: =U8 -> 30966 | U9: 30972 | V9: =U9-T9 -> 6 | W9: =X8 -> 18544 | X9: 18544 | Y9: =X9-W9 -> 0 | Z9: =M9+P9+S9+V9+Y9 -> 40 | AA9: 462 | AB9: 215 | AC9: =Gen!S14 -> 1834.21
A10: =Gen!A15 -> 43774 | B10: =Gen!B15 -> 0.506 | C10: 24259.14 | D10: 16969.41 | E10: =Gen!D15 -> 0 | G10: 18.94 | I10: 29336.8 | J10: 19325.8 | K10: =L9 -> 33234 | L10: 33239 | M10: =L10-K10 -> 5 | N10: =O9 -> 28136 | O10: 28149 | P10: =O10-N10 -> 13 | Q10: =R9 -> 33464 | R10: 33470 | S10: =R10-Q10 -> 6 | T10: =U9 -> 30972 | U10: 30987 | V10: =U10-T10 -> 15 | W10: =X9 -> 18544 | X10: 18544 | Y10: =X10-W10 -> 0 | Z10: =M10+P10+S10+V10+Y10 -> 39 | AA10: 468 | AB10: 210 | AC10: =Gen!S15 -> 2117.7
A11: =Gen!A16 -> 43775 | B11: =Gen!B16 -> 0.312 | C11: 24259.14 | D11: 14391.35 | E11: =Gen!D16 -> 0 | G11: 142.33 | I11: 29346.3 | J11: 19331.3 | K11: =L10 -> 33239 | L11: 33252 | M11: =L11-K11 -> 13 | N11: =O10 -> 28149 | O11: 28155 | P11: =O11-N11 -> 6 | Q11: =R10 -> 33470 | R11: 33478 | S11: =R11-Q11 -> 8 | T11: =U10 -> 30987 | U11: 30993 | V11: =U11-T11 -> 6 | W11: =X10 -> 18544 | X11: 18559 | Y11: =X11-W11 -> 15 | Z11: =M11+P11+S11+V11+Y11 -> 48 | AA11: 510 | AB11: 200 | AC11: =Gen!S16 -> 2435.73
A12: =Gen!A17 -> 43776 | B12: =Gen!B17 -> 0.195 | C12: 24259.14 | D12: 11920.07 | E12: =Gen!D17 -> 0 | G12: 241.32 | I12: 29355.4 | J12: 19337.4 | K12: =L11 -> 33252 | L12: 33258 | M12: =L12-K12 -> 6 | N12: =O11 -> 28155 | O12: 28165 | P12: =O12-N12 -> 10 | Q12: =R11 -> 33478 | R12: 33482 | S12: =R12-Q12 -> 4 | T12: =U11 -> 30993 | U12: 31002 | V12: =U12-T12 -> 9 | W12: =X11 -> 18559 | X12: 18571 | Y12: =X12-W12 -> 12 | Z12: =M12+P12+S12+V12+Y12 -> 41 | AA12: 429 | AB12: 197 | AC12: =Gen!S17 -> 2229.96
A13: =Gen!A18 -> 43777 | B13: =Gen!B18 -> 0.169 | C13: 24259.14 | D13: 24660.57 | E13: =Gen!D18 -> 15000 | G13: 159.05 | I13: 29368.6 | J13: 19343.9 | K13: =L12 -> 33258 | L13: 33265 | M13: =L13-K13 -> 7 | N13: =O12 -> 28165 | O13: 28176 | P13: =O13-N13 -> 11 | Q13: =R12 -> 33482 | R13: 33492 | S13: =R13-Q13 -> 10 | T13: =U12 -> 31002 | U13: 31009 | V13: =U13-T13 -> 7 | W13: =X12 -> 18571 | X13: 18580 | Y13: =X13-W13 -> 9 | Z13: =M13+P13+S13+V13+Y13 -> 44 | AA13: 447 | AB13: 200 | AC13: =Gen!S18 -> 2100.45
A14: =Gen!A19 -> 43778 | B14: =Gen!B19 -> 0.169 | C14: 22006.01 | D14: 23100.25 | E14: =Gen!D19 -> 0 | G14: 122.93 | I14: 29372.4 | J14: 19350.5 | K14: =L13 -> 33265 | L14: 33271 | M14: =L14-K14 -> 6 | N14: =O13 -> 28176 | O14: 28188 | P14: =O14-N14 -> 12 | Q14: =R13 -> 33492 | R14: 33498 | S14: =R14-Q14 -> 6 | T14: =U13 -> 31009 | U14: 31022 | V14: =U14-T14 -> 13 | W14: =X13 -> 18580 | X14: 18586 | Y14: =X14-W14 -> 6 | Z14: =M14+P14+S14+V14+Y14 -> 43 | AA14: 468 | AB14: 213 | AC14: =Gen!S19 -> 2130.17
A15: =Gen!A20 -> 43779 | B15: =Gen!B20 -> 0.468 | C15: 21093.03 | D15: 23100.25 | E15: =Gen!D20 -> 0 | G15: 231.5 | I15: 29381.3 | J15: 19387.1 | K15: =L14 -> 33271 | L15: 33284 | M15: =L15-K15 -> 13 | N15: =O14 -> 28188 | O15: 28194 | P15: =O15-N15 -> 6 | Q15: =R14 -> 33498 | R15: 33510 | S15: =R15-Q15 -> 12 | T15: =U14 -> 31022 | U15: 31026 | V15: =U15-T15 -> 4 | W15: =X14 -> 18586 | X15: 18593 | Y15: =X15-W15 -> 7 | Z15: =M15+P15+S15+V15+Y15 -> 42 | AA15: 479 | AB15: 181 | AC15: =Gen!S20 -> 2241.8
A16: =Gen!A21 -> 43780 | B16: =Gen!B21 -> 0.948 | C16: 18440.58 | D16: 23100.25 | E16: =Gen!D21 -> 0 | I16: 29390.2 | J16: 19363.6 | K16: =L15 -> 33284 | L16: 33292 | M16: =L16-K16 -> 8 | N16: =O15 -> 28194 | O16: 28205 | P16: =O16-N16 -> 11 | Q16: =R15 -> 33510 | R16: 33520 | S16: =R16-Q16 -> 10 | T16: =U15 -> 31026 | U16: 31035 | V16: =U16-T16 -> 9 | W16: =X15 -> 18593 | X16: 18602 | Y16: =X16-W16 -> 9 | Z16: =M16+P16+S16+V16+Y16 -> 47 | AA16: 537 | AB16: 216 | AC16: =Gen!S21 -> 2652.45
A17: =Gen!A22 -> 43781 | B17: =Gen!B22 -> 0.935 | C17: 15665.31 | D17: 23100.25 | E17: =Gen!D22 -> 0 | G17: 187.81 | I17: 29401.1 | J17: 19371.1 | K17: =L16 -> 33292 | L17: 33304 | M17: =L17-K17 -> 12 | N17: =O16 -> 28205 | O17: 28214 | P17: =O17-N17 -> 9 | Q17: =R16 -> 33520 | R17: 33531 | S17: =R17-Q17 -> 11 | T17: =U16 -> 31035 | U17: 31042 | V17: =U17-T17 -> 7 | W17: =X16 -> 18602 | X17: 18609 | Y17: =X17-W17 -> 7 | Z17: =M17+P17+S17+V17+Y17 -> 46 | AA17: 614 | AB17: 208 | AC17: =Gen!S22 -> 2587.46
A18: =Gen!A23 -> 43782 | B18: =Gen!B23 -> 0.481 | C18: 12985.52 | D18: 23100.25 | E18: =Gen!D23 -> 0 | G18: 450.31 | I18: 29412.1 | J18: 19378.7 | K18: =L17 -> 33304 | L18: 33315 | M18: =L18-K18 -> 11 | N18: =O17 -> 28214 | O18: 28220 | P18: =O18-N18 -> 6 | Q18: =R17 -> 33531 | R18: 33545 | S18: =R18-Q18 -> 14 | T18: =U17 -> 31042 | U18: 31049 | V18: =U18-T18 -> 7 | W18: =X17 -> 18609 | X18: 18615 | Y18: =X18-W18 -> 6 | Z18: =M18+P18+S18+V18+Y18 -> 44 | AA18: 417 | AB18: 231 | AC18: =Gen!S23 -> 2229.48
A19: =Gen!A24 -> 43783 | B19: =Gen!B24 -> 0.526 | C19: 10333.55 | D19: 23100.25 | E19: =Gen!D24 -> 0 | G19: 283.61 | I19: 29421.4 | J19: 19385.5 | K19: =L18 -> 33315 | L19: 33322 | M19: =L19-K19 -> 7 | N19: =O18 -> 28220 | O19: 28233 | P19: =O19-N19 -> 13 | Q19: =R18 -> 33545 | R19: 33551 | S19: =R19-Q19 -> 6 | T19: =U18 -> 31049 | U19: 31054 | V19: =U19-T19 -> 5 | W19: =X18 -> 18615 | X19: 18628 | Y19: =X19-W19 -> 13 | Z19: =M19+P19+S19+V19+Y19 -> 44 | AA19: 417 | AB19: 231 | AC19: =Gen!S24 -> 2368.36
A20: =Gen!A25 -> 43784 | B20: =Gen!B25 -> 0.221 | C20: 7949.67 | D20: 23100.25 | E20: =Gen!D25 -> 0 | G20: 250.23 | I20: 29431.1 | J20: 19392.1 | K20: =L19 -> 33322 | L20: 33333 | M20: =L20-K20 -> 11 | N20: =O19 -> 28233 | O20: 28240 | P20: =O20-N20 -> 7 | Q20: =R19 -> 33551 | R20: 33563 | S20: =R20-Q20 -> 12 | T20: =U19 -> 31054 | U20: 31061 | V20: =U20-T20 -> 7 | W20: =X19 -> 18628 | X20: 18634 | Y20: =X20-W20 -> 6 | Z20: =M20+P20+S20+V20+Y20 -> 43 | AA20: 436 | AB20: 200 | AC20: =Gen!S25 -> 2133.65
A21: =Gen!A26 -> 43785 | B21: =Gen!B26 -> 0.156 | C21: 25300.57 | D21: 23100.25 | E21: =Gen!D26 -> 18000 | G21: 182.66 | I21: 29439.9 | J21: 19398.1 | K21: =L20 -> 33333 | L21: 33339 | M21: =L21-K21 -> 6 | N21: =O20 -> 28240 | O21: 28252 | P21: =O21-N21 -> 12 | Q21: =R20 -> 33563 | R21: 33569 | S21: =R21-Q21 -> 6 | T21: =U20 -> 31061 | U21: 31068 | V21: =U21-T21 -> 7 | W21: =X20 -> 18634 | X21: 18646 | Y21: =X21-W21 -> 12 | Z21: =M21+P21+S21+V21+Y21 -> 43 | AA21: 435 | AB21: 210 | AC21: =Gen!S26 -> 2099.12
A22: =Gen!A27 -> 43786 | B22: =Gen!B27 -> 0.623 | C22: 23667.89 | D22: 23100.25 | E22: =Gen!D27 -> 0 | G22: 129.38 | I22: 29449.5 | J22: 19403.7 | K22: =L21 -> 33339 | L22: 33347 | M22: =L22-K22 -> 8 | N22: =O21 -> 28252 | O22: 28261 | P22: =O22-N22 -> 9 | Q22: =R21 -> 33569 | R22: 33577 | S22: =R22-Q22 -> 8 | T22: =U21 -> 31068 | U22: 31075 | V22: =U22-T22 -> 7 | W22: =X21 -> 18646 | X22: 18656 | Y22: =X22-W22 -> 10 | Z22: =M22+P22+S22+V22+Y22 -> 42 | AA22: 486 | AB22: 220 | AC22: =Gen!S27 -> 2394.69
A23: =Gen!A28 -> 43787 | B23: =Gen!B28 -> 0.519 | C23: 21143.82 | D23: 23100.25 | E23: =Gen!D28 -> 0 | G23: 160.39 | I23: 29459.5 | J23: 19410.2 | K23: =L22 -> 33347 | L23: 33355 | M23: =L23-K23 -> 8 | N23: =O22 -> 28261 | O23: 28270 | P23: =O23-N23 -> 9 | Q23: =R22 -> 33577 | R23: 33588 | S23: =R23-Q23 -> 11 | T23: =U22 -> 31075 | U23: 31081 | V23: =U23-T23 -> 6 | W23: =X22 -> 18656 | X23: 18665 | Y23: =X23-W23 -> 9 | Z23: =M23+P23+S23+V23+Y23 -> 43 | AA23: 498 | AB23: 230 | AC23: =Gen!S28 -> 2272.4
A24: =Gen!A29 -> 43788 | B24: =Gen!B29 -> 0.091 | C24: 18711.03 | D24: 23100.25 | E24: =Gen!D29 -> 0 | G24: 107.73 | I24: 29468.9 | J24: 19416.2 | K24: =L23 -> 33355 | L24: 33361 | M24: =L24-K24 -> 6 | N24: =O23 -> 28270 | O24: 28280 | P24: =O24-N24 -> 10 | Q24: =R23 -> 33588 | R24: 33594 | S24: =R24-Q24 -> 6 | T24: =U23 -> 31081 | U24: 31091 | V24: =U24-T24 -> 10 | W24: =X23 -> 18665 | X24: 18674 | Y24: =X24-W24 -> 9 | Z24: =M24+P24+S24+V24+Y24 -> 41 | AA24: 473 | AB24: 180 | AC24: =Gen!S29 -> 1853.3
A25: =Gen!A30 -> 43789 | B25: =Gen!B30 -> 0.117 | C25: 16750.04 | D25: 23100.21 | E25: =Gen!D30 -> 0 | G25: 84.19 | I25: 29477.3 | J25: 19421.2 | K25: =L24 -> 33361 | L25: 33365 | M25: =L25-K25 -> 4 | N25: =O24 -> 28280 | O25: 28285 | P25: =O25-N25 -> 5 | Q25: =R24 -> 33594 | R25: 33607 | S25: =R25-Q25 -> 13 | T25: =U24 -> 31091 | U25: 31096 | V25: =U25-T25 -> 5 | W25: =X24 -> 18674 | X25: 18680 | Y25: =X25-W25 -> 6 | Z25: =M25+P25+S25+V25+Y25 -> 33 | AA25: 426 | AB25: 165 | AC25: =Gen!S30 -> 1844.62
A26: =Gen!A31 -> 43790 | B26: =Gen!B31 -> 0.13 | C26: 14821.23 | D26: 23100.21 | E26: =Gen!D31 -> 0 | G26: 38.16 | I26: 29484.6 | J26: 19425.7 | K26: =L25 -> 33365 | L26: 33367 | M26: =L26-K26 -> 2 | N26: =O25 -> 28285 | O26: 28292 | P26: =O26-N26 -> 7 | Q26: =R25 -> 33607 | R26: 33616 | S26: =R26-Q26 -> 9 | T26: =U25 -> 31096 | U26: 31102 | V26: =U26-T26 -> 6 | W26: =X25 -> 18680 | X26: 18685 | Y26: =X26-W26 -> 5 | Z26: =M26+P26+S26+V26+Y26 -> 29 | AA26: 397 | AB26: 172 | AC26: =Gen!S31 -> 1557.2
A27: =Gen!A32 -> 43791 | B27: =Gen!B32 -> 0.143 | C27: 13225.87 | D27: 23100.21 | E27: =Gen!D32 -> 0 | G27: 86.34 | I27: 29491.7 | J27: 19430.8 | K27: =L26 -> 33367 | L27: 33375 | M27: =L27-K27 -> 8 | N27: =O26 -> 28292 | O27: 28299 | P27: =O27-N27 -> 7 | Q27: =R26 -> 33616 | R27: 33619 | S27: =R27-Q27 -> 3 | T27: =U26 -> 31102 | U27: 31108 | V27: =U27-T27 -> 6 | W27: =X26 -> 18685 | X27: 18693 | Y27: =X27-W27 -> 8 | Z27: =M27+P27+S27+V27+Y27 -> 32 | AA27: 399 | AB27: 181 | AC27: =Gen!S32 -> 1822.89
A28: =Gen!A33 -> 43792 | B28: =Gen!B33 -> 0.169 | C28: 11316.64 | D28: 23100.21 | E28: =Gen!D33 -> 0 | I28: 29498.6 | J28: 19436.1 | K28: =L27 -> 33375 | M28: =L28-K28 -> -33375 | N28: =O27 -> 28299 | P28: =O28-N28 -> -28299 | Q28: =R27 -> 33619 | S28: =R28-Q28 -> -33619 | T28: =U27 -> 31108 | V28: =U28-T28 -> -31108 | W28: =X27 -> 18693 | Y28: =X28-W28 -> -18693 | Z28: =M28+P28+S28+V28+Y28 -> -145094 | AC28: =Gen!S33 -> 0
A29: =Gen!A34 -> 43793 | B29: =Gen!B34 -> 0 | E29: =Gen!D34 -> 0 | K29: =L28 -> 0 | M29: =L29-K29 -> 0 | N29: =O28 -> 0 | P29: =O29-N29 -> 0 | Q29: =R28 -> 0 | S29: =R29-Q29 -> 0 | T29: =U28 -> 0 | V29: =U29-T29 -> 0 | W29: =X28 -> 0 | Y29: =X29-W29 -> 0 | Z29: =M29+P29+S29+V29+Y29 -> 0 | AC29: =Gen!S34 -> 0
A30: =Gen!A35 -> 43794 | B30: =Gen!B35 -> 0 | E30: =Gen!D35 -> 0 | K30: =L29 -> 0 | M30: =L30-K30 -> 0 | N30: =O29 -> 0 | P30: =O30-N30 -> 0 | Q30: =R29 -> 0 | S30: =R30-Q30 -> 0 | T30: =U29 -> 0 | V30: =U30-T30 -> 0 | W30: =X29 -> 0 | Y30: =X30-W30 -> 0 | Z30: =M30+P30+S30+V30+Y30 -> 0 | AC30: =Gen!S35 -> 0
A31: =Gen!A36 -> 43795 | B31: =Gen!B36 -> 0 | E31: =Gen!D36 -> 0 | K31: =L30 -> 0 | M31: =L31-K31 -> 0 | N31: =O30 -> 0 | P31: =O31-N31 -> 0 | Q31: =R30 -> 0 | S31: =R31-Q31 -> 0 | T31: =U30 -> 0 | V31: =U31-T31 -> 0 | W31: =X30 -> 0 | Y31: =X31-W31 -> 0 | Z31: =M31+P31+S31+V31+Y31 -> 0 | AC31: =Gen!S36 -> 0
A32: =Gen!A37 -> 43796 | B32: =Gen!B37 -> 0 | E32: =Gen!D37 -> 0 | K32: =L31 -> 0 | M32: =L32-K32 -> 0 | N32: =O31 -> 0 | P32: =O32-N32 -> 0 | Q32: =R31 -> 0 | S32: =R32-Q32 -> 0 | T32: =U31 -> 0 | V32: =U32-T32 -> 0 | W32: =X31 -> 0 | Y32: =X32-W32 -> 0 | Z32: =M32+P32+S32+V32+Y32 -> 0 | AC32: =Gen!S37 -> 0
A33: =Gen!A38 -> 43797 | B33: =Gen!B38 -> 0 | E33: =Gen!D38 -> 0 | K33: =L32 -> 0 | M33: =L33-K33 -> 0 | N33: =O32 -> 0 | P33: =O33-N33 -> 0 | Q33: =R32 -> 0 | S33: =R33-Q33 -> 0 | T33: =U32 -> 0 | V33: =U33-T33 -> 0 | W33: =X32 -> 0 | Y33: =X33-W33 -> 0 | Z33: =M33+P33+S33+V33+Y33 -> 0 | AC33: =Gen!S38 -> 0
A34: =Gen!A39 -> 43798 | B34: =Gen!B39 -> 0 | E34: =Gen!D39 -> 0 | K34: =L33 -> 0 | M34: =L34-K34 -> 0 | N34: =O33 -> 0 | P34: =O34-N34 -> 0 | Q34: =R33 -> 0 | S34: =R34-Q34 -> 0 | T34: =U33 -> 0 | V34: =U34-T34 -> 0 | W34: =X33 -> 0 | Y34: =X34-W34 -> 0 | Z34: =M34+P34+S34+V34+Y34 -> 0 | AC34: =Gen!S39 -> 0
A35: =Gen!A40 -> 43799 | B35: =Gen!B40 -> 0 | E35: =Gen!D40 -> 0 | K35: =L34 -> 0 | M35: =L35-K35 -> 0 | N35: =O34 -> 0 | P35: =O35-N35 -> 0 | Q35: =R34 -> 0 | S35: =R35-Q35 -> 0 | T35: =U34 -> 0 | V35: =U35-T35 -> 0 | W35: =X34 -> 0 | Y35: =X35-W35 -> 0 | Z35: =M35+P35+S35+V35+Y35 -> 0 | AC35: =Gen!S40 -> 0
A36: =Gen!A41 -> 43800 | E36: =Gen!D41 -> 0 | K36: =L35 -> 0 | M36: =L36-K36 -> 0 | N36: =O35 -> 0 | P36: =O36-N36 -> 0 | Q36: =R35 -> 0 | S36: =R36-Q36 -> 0 | T36: =U35 -> 0 | V36: =U36-T36 -> 0 | W36: =X35 -> 0 | Y36: =X36-W36 -> 0 | Z36: =M36+P36+S36+V36+Y36 -> 0 | AC36: =Gen!S41 -> 0
A37: =[1]Gen!A42 -> #REF! | K37: ='[4]Daily report Gen'!L68 -> 0 | M37: =L37-K37 -> 0 | P37: =O37-N37 -> 0 | S37: =R37-Q37 -> 0 | V37: =U37-T37 -> 0 | Y37: =X37-W37 -> 0 | Z37: =M37+P37+S37+V37+Y37 -> 0 | AC37: =Gen!S42 -> 0

Sheet Gen
D2: HLP REPORT NOV. 2019
F6: BILILA LODGE INVESTMENT LIMITED | V6: 1 | W6: 2 | X6: 3 | Y6: 4 | Z6: 5 | AA6: 6 | AB6: 7 | AC6: 8 | AD6: 9 | AE6: 10 | AF6: 11
F7: Diesel Consumed by 500KVA Generator | M7: 500KVA Generator KWh | V7: Safari-STAFF | W7: Safari-STAFF | X7: Lc/swg/gust | Y7: Eng pikcup | Z7: VIP Safari Car | AA7: GX Guest | AB7: GX Guest | AC7: T/Hillux/pur | AD7: TATA | AE7: MAN | AF7: F/Truck | AG7: Incenerator | AH7: A&K | AI7: OTHER | AJ7: TOTAL CO
A8: Date | B8: Occupenccy % | C8: OPENING | D8: Received | E8: Schedule delivery | F8: PRICE | G8: 1 | H8: 2 | I8: 3 | J8: 4 | K8: 5 | L8: 6 | M8: 1 | N8: 2 | O8: 3 | P8: 4 | Q8: 5 | R8: 6 | S8: Total Diseal Consumed | T8: Total Kwh generated | U8: Average Diesel/Kwh | V8: T 128 AXJ | W8: T 134 AXJ | X8: T 499 AXG | Y8: T 217 CHV | Z8: T 214 CHV | AA8: T 139 AXE | AB8: T 242 AXN - SABASABA | AC8: T 476 AWZ | AD8: T 226 AUQ | AE8: T 308 CLD | AF8: T 852 AWU | AG8: Machine ENG | AH8: Vehicle | AI8: Vehicle | AR8: Total Diseal Consumed Gen & Vehicle | AS8: Total cost /Day (TSH) | AT8: BALANCE
C9: =[5]Gen!$C$43 -> 35194.41 | S9: =SUM(F9:L9) -> 0 | T9: =SUM(M9:R9) -> 0 | AR9: =SUM(AJ9+S9) -> 0 | AT9: 38784.7
S10: =SUM(F10:L10) -> 0 | T10: =SUM(M10:R10) -> 0 | U10: =SUM(N10:S10) -> 0 | AJ10: =SUM(V10:AI10) -> 0 | AR10: =SUM(AJ10+S10) -> 0
A11: 43770 | B11: 0.87 | C11: =SUM(C9+D11) -> 35194.41 | E11: 18000 | G11: 416.9 | H11: 365.59 | J11: 351.9 | K11: 828.44 | L11: 435.29 | M11: 970 | N11: 1502 | P11: 938 | Q11: 1400 | R11: 893 | S11: =SUM(F11:L11) -> 2398.12 | T11: =SUM(M11:R11) -> 5703 | U11: =S11/T11 -> 0.42050149 | W11: 45.77 | Z11: 23.28 | AJ11: =SUM(V11:AI11) -> 69.05 | AR11: =SUM(AJ11+S11) -> 2467.17 | AS11: =AR11*AU11 -> 0 | AT11: =C11 -> 35194.41
A12: 43771 | B12: 0.766 | C12: =SUM(C11-AR11+D12) -> 50727.24 | D12: 18000 | G12: 508.61 | H12: 472.97 | J12: 700.12 | K12: 338.72 | L12: 482.15 | M12: 973 | N12: 977 | P12: 1633 | Q12: 1552 | R12: 917 | S12: =SUM(F12:L12) -> 2502.57 | T12: =SUM(M12:R12) -> 6052 | U12: =S12/T12 -> 0.41351124 | X12: 23.51 | AC12: 36.04 | AG12: 600 | AJ12: =SUM(V12:AI12) -> 659.55 | AR12: =SUM(AJ12+S12) -> 3162.12 | AS12: =AR12*AU12 -> 0 | AT12: =C12 -> 50727.24
A13: 43772 | B13: 0.11 | C13: =SUM(C12-AR12+D13) -> 47565.12 | G13: 302.77 | H13: 588.74 | J13: 340.03 | K13: 206.76 | L13: 648.53 | M13: 810 | N13: 1477 | P13: 805 | Q13: 448 | R13: 1687 | S13: =SUM(F13:L13) -> 2086.83 | T13: =SUM(M13:R13) -> 5227 | U13: =S13/T13 -> 0.39924048 | V13: 80.65 | W13: 42.09 | Y13: 35.78 | Z13: 18.24 | AC13: 48.74 | AH13: 36 | AJ13: =SUM(V13:AH13) -> 261.5 | AR13: =SUM(AJ13+S13) -> 2348.33 | AS13: =AR13*AU13 -> 0 | AT13: =C13 -> 47565.12
A14: 43773 | B14: 0.13 | C14: =SUM(C13-AR13+D14) -> 45216.79 | G14: 366.6 | H14: 307.74 | J14: 913.17 | K14: 246.7 | M14: 1101 | N14: 778 | P14: 2255 | Q14: 678 | S14: =SUM(F14:L14) -> 1834.21 | T14: =SUM(M14:R14) -> 4812 | U14: =S14/T14 -> 0.38117415 | Y14: 17.39 | AJ14: =SUM(V14:AH14) -> 17.39 | AR14: =SUM(AJ14+S14) -> 1851.6 | AS14: =AR14*AU14 -> 0 | AT14: =C14 -> 45216.79
A15: 43774 | B15: 0.506 | C15: =SUM(C14-AR14+D15) -> 43365.19 | G15: 347.21 | H15: 613.36 | J15: 329.28 | K15: 827.85 | M15: 666 | N15: 1586 | P15: 785 | Q15: 1998 | S15: =SUM(F15:L15) -> 2117.7 | T15: =SUM(M15:R15) -> 5035 | U15: =S15/T15 -> 0.42059583 | X15: 18.94 | AJ15: =SUM(V15:AH15) -> 18.94 | AR15: =SUM(AJ15+S15) -> 2136.64 | AS15: =AR15*AU15 -> 0 | AT15: =C15 -> 43365.19
A16: 43775 | B16: 0.312 | C16: =SUM(C15-AR15+D16) -> 41228.55 | G16: 658.71 | H16: 259.82 | J16: 364.27 | K16: 343.76 | L16: 809.17 | M16: 1500 | N16: 772 | P16: 886 | Q16: 832 | R16: 1430 | S16: =SUM(F16:L16) -> 2435.73 | T16: =SUM(M16:R16) -> 5420 | U16: =S16/T16 -> 0.44939668 | V16: 77.32 | X16: 14.76 | Y16: 3.14 | Z16: 47.11 | AJ16: =SUM(V16:AH16) -> 142.33 | AR16: =SUM(AJ16+S16) -> 2578.06 | AS16: =AR16*AU16 -> 0 | AT16: =C16 -> 41228.55
A17: 43776 | B17: 0.195 | C17: =SUM(C16-AR16+D17) -> 38650.49 | G17: 333.85 | H17: 544.2 | J17: 227.76 | K17: 439.52 | L17: 684.63 | M17: 843 | N17: 1280 | P17: 568 | Q17: 1027 | R17: 1620 | S17: =SUM(F17:L17) -> 2229.96 | T17: =SUM(M17:R17) -> 5338 | U17: =S17/T17 -> 0.41775197 | W17: 73.36 | X17: 20.06 | Z17: 35.9 | AH17: 112 | AJ17: =SUM(V17:AI17) -> 241.32 | AR17: =SUM(AJ17+S17) -> 2471.28 | AS17: =AR17*AU17 -> 0 | AT17: =C17 -> 38650.49
A18: 43777 | B18: 0.169 | C18: =SUM(C17-AR17+D18) -> 51179.21 | D18: 15000 | E18: 15000 | G18: 346.7 | H18: 486.73 | J18: 456.19 | K18: 352.55 | L18: 458.28 | M18: 933 | N18: 1289 | P18: 1160 | Q18: 861 | R18: 1427 | S18: =SUM(F18:L18) -> 2100.45 | T18: =SUM(M18:R18) -> 5670 | U18: =S18/T18 -> 0.37044974 | V18: 59.93 | X18: 19.87 | Y18: 27.3 | AD18: 51.95 | AJ18: =SUM(V18:AI18) -> 159.05 | AR18: =SUM(AJ18+S18) -> 2259.5 | AS18: =AR18*AU18 -> 0 | AT18: =C18 -> 51179.21
A19: 43778 | B19: 0.169 | C19: =SUM(C18-AR18+D19) -> 48919.71 | G19: 701.5 | H19: 316.46 | J19: 490.37 | K19: 324.83 | L19: 297.01 | M19: 1804 | N19: 810 | P19: 1362 | Q19: 789 | R19: 829 | S19: =SUM(F19:L19) -> 2130.17 | T19: =SUM(M19:R19) -> 5594 | U19: =S19/T19 -> 0.3807955 | W19: 24.92 | X19: 6 | Y19: 3.15 | AF19: 58.89 | AI19: 30 | AJ19: =SUM(V19:AI19) -> 122.96 | AR19: =SUM(AJ19+S19) -> 2253.13 | AS19: =AR19*AU19 -> 0 | AT19: =C19 -> 48919.71
A20: 43779 | B20: 0.468 | C20: =SUM(C19-AR19+D20) -> 46666.58 | G20: 625.66 | H20: 406.99 | J20: 612.95 | K20: 252.38 | L20: 343.82 | M20: 1570 | N20: 925 | P20: 1499 | Q20: 597 | R20: 896 | S20: =SUM(F20:L20) -> 2241.8 | T20: =SUM(M20:R20) -> 5487 | U20: =S20/T20 -> 0.4085657 | W20: 47.53 | X20: 15.84 | Z20: 23.13 | AH20: 145 | AJ20: =SUM(V20:AI20) -> 231.5 | AR20: =SUM(AJ20+S20) -> 2473.3 | AS20: =AR20*AU20 -> 0 | AT20: =C20 -> 46666.58
A21: 43780 | B21: 0.948 | C21: =SUM(C20-AR20+D21) -> 44193.28 | G21: 420.92 | H21: 794.8 | J21: 544.98 | K21: 313.85 | L21: 577.9 | M21: 1027 | N21: 1539 | P21: 1347 | Q21: 1385 | R21: 1244 | S21: =SUM(F21:L21) -> 2652.45 | T21: =SUM(M21:R21) -> 6542 | U21: =S21/T21 -> 0.4054494 | AJ21: =SUM(V21:AI21) -> 0 | AR21: =SUM(AJ21+S21) -> 2652.45 | AS21: =AR21*AU21 -> 0 | AT21: =C21 -> 44193.28
A22: 43781 | B22: 0.935 | C22: =SUM(C21-AR21+D22) -> 41540.83 | G22: 539.74 | H22: 582.75 | J22: 655.75 | K22: 446.35 | L22: 362.87 | M22: 1566 | N22: 1414 | P22: 1734 | Q22: 1101 | R22: 852 | S22: =SUM(F22:L22) -> 2587.46 | T22: =SUM(M22:R22) -> 6667 | U22: =S22/T22 -> 0.3880996 | W22: 1.67 | X22: 23.79 | Z22: 25.35 | AH22: 137 | AJ22: =SUM(V22:AI22) -> 187.81 | AR22: =SUM(AJ22+S22) -> 2775.27 | AS22: =AR22*AU22 -> 0 | AT22: =C22 -> 41540.83
A23: 43782 | B23: 0.481 | C23: =SUM(C22-AR22+D23) -> 38765.56 | G23: 640.34 | H23: 424.4 | J23: 411.89 | K23: 305.57 | L23: 447.28 | M23: 1433 | N23: 859 | P23: 1684 | Q23: 1054 | R23: 830 | S23: =SUM(F23:L23) -> 2229.48 | T23: =SUM(M23:R23) -> 5860 | U23: =S23/T23 -> 0.38045734 | X23: 12.79 | Y23: 48.34 | Z23: 22.18 | AH23: 367 | AJ23: =SUM(V23:AI23) -> 450.31 | AR23: =SUM(AJ23+S23) -> 2679.79 | AS23: =AR23*AU23 -> 0 | AT23: =C23 -> 38765.56
A24: 43783 | B24: 0.526 | C24: =SUM(C23-AR23+D24) -> 36085.77 | G24: 359.79 | H24: 931.51 | J24: 360.47 | K24: 324.06 | L24: 392.53 | M24: 879 | N24: 1678 | P24: 872 | Q24: 860 | R24: 1574 | S24: =SUM(F24:L24) -> 2368.36 | T24: =SUM(M24:R24) -> 5863 | U24: =S24/T24 -> 0.4039502 | W24: 108.51 | X24: 11.2 | Z24: 46.9 | AH24: 117 | AJ24: =SUM(V24:AI24) -> 283.61 | AR24: =SUM(AJ24+S24) -> 2651.97 | AS24: =AR24*AU24 -> 0 | AT24: =C24 -> 36085.77
A25: 43784 | B25: 0.221 | C25: =SUM(C24-AR24+D25) -> 33433.8 | E25: 18000 | G25: 330.65 | H25: 521.84 | J25: 408.51 | K25: 398.92 | L25: 473.73 | M25: 1392 | N25: 803 | P25: 1422 | Q25: 1000 | R25: 773 | S25: =SUM(F25:L25) -> 2133.65 | T25: =SUM(M25:R25) -> 5390 | U25: =S25/T25 -> 0.39585343 | X25: 40.61 | Z25: 17.62 | AH25: 192 | AJ25: =SUM(V25:AI25) -> 250.23 | AR25: =SUM(AJ25+S25) -> 2383.88 | AS25: =AR25*AU25 -> 0 | AT25: =C25 -> 33433.8
A26: 43785 | B26: 0.156 | C26: =SUM(C25-AR25+D26) -> 49049.92 | D26: 18000 | G26: 495.08 | H26: 377.86 | J26: 480.31 | K26: 338.07 | L26: 407.8 | M26: 730 | N26: 1460 | P26: 731 | Q26: 982 | R26: 1438 | S26: =SUM(F26:L26) -> 2099.12 | T26: =SUM(M26:R26) -> 5341 | U26: =S26/T26 -> 0.39302003 | W26: 64.02 | X26: 29.13 | Y26: 16.66 | Z26: 12.85 | AH26: 60 | AJ26: =SUM(V26:AI26) -> 182.66 | AR26: =SUM(AJ26+S26) -> 2281.78 | AS26: =AR26*AU26 -> 0 | AT26: =C26 -> 49049.92
A27: 43786 | B27: 0.623 | C27: =SUM(C26-AR26+D27) -> 46768.14 | G27: 405.97 | H27: 562.37 | J27: 431.95 | K27: 439.29 | L27: 555.11 | M27: 1074 | N27: 1342 | P27: 1015 | Q27: 1143 | R27: 1298 | S27: =SUM(F27:L27) -> 2394.69 | T27: =SUM(M27:R27) -> 5872 | U27: =S27/T27 -> 0.40781505 | X27: 38.38 | AH27: 91 | AJ27: =SUM(V27:AI27) -> 129.38 | AR27: =SUM(AJ27+S27) -> 2524.07 | AS27: =AR27*AU27 -> 0 | AT27: =C27 -> 46768.14
A28: 43787 | B28: 0.519 | C28: =SUM(C27-AR27+D28) -> 44244.07 | G28: 430.07 | H28: 472.35 | J28: 548.03 | K28: 348.64 | L28: 473.31 | M28: 941 | N28: 1146 | P28: 1364 | Q28: 899 | R28: 1127 | S28: =SUM(F28:L28) -> 2272.4 | T28: =SUM(M28:R28) -> 5477 | U28: =S28/T28 -> 0.41489867 | W28: 12.21 | Y28: 33.52 | Z28: 66.66 | AH28: 48 | AJ28: =SUM(V28:AI28) -> 160.39 | AR28: =SUM(AJ28+S28) -> 2432.79 | AS28: =AR28*AU28 -> 0 | AT28: =C28 -> 44244.07
A29: 43788 | B29: 0.091 | C29: =SUM(C28-AR28+D29) -> 41811.28 | G29: 150.24 | H29: 552.05 | J29: 162.24 | K29: 544.33 | L29: 444.44 | M29: 706 | N29: 1092 | P29: 701 | Q29: 1383 | R29: 1010 | S29: =SUM(F29:L29) -> 1853.3 | T29: =SUM(M29:R29) -> 4892 | U29: =S29/T29 -> 0.37884301 | W29: 72.44 | Z29: 35.29 | AJ29: =SUM(V29:AI29) -> 107.73 | AR29: =SUM(AJ29+S29) -> 1961.03 | AS29: =AR29*AU29 -> 0 | AT29: =C29 -> 41811.28
A30: 43789 | B30: 0.117 | C30: =SUM(C29-AR29+D30) -> 39850.25 | G30: 120.14 | H30: 269.44 | J30: 737.4 | K30: 257.21 | L30: 460.43 | M30: 284 | N30: 560 | P30: 1846 | Q30: 603 | R30: 900 | S30: =SUM(F30:L30) -> 1844.62 | T30: =SUM(M30:R30) -> 4193 | U30: =S30/T30 -> 0.43992845 | Z30: 21 | AC30: 63.19 | AJ30: =SUM(V30:AI30) -> 84.19 | AR30: =SUM(AJ30+S30) -> 1928.81 | AS30: =AR30*AU30 -> 0 | AT30: =C30 -> 39850.25
A31: 43790 | B31: 0.13 | C31: =SUM(C30-AR30+D31) -> 37921.44 | G31: 109.83 | H31: 352.04 | J31: 471.39 | K31: 280.01 | L31: 343.93 | M31: 236 | N31: 995 | P31: 1357 | Q31: 781 | R31: 942 | S31: =SUM(F31:L31) -> 1557.2 | T31: =SUM(M31:R31) -> 4311 | U31: =S31/T31 -> 0.3612155 | X31: 38.16 | AJ31: =SUM(V31:AI31) -> 38.16 | AR31: =SUM(AJ31+S31) -> 1595.36 | AS31: =AR31*AU31 -> 0 | AT31: =C31 -> 37921.44
A32: 43791 | B32: 0.143 | C32: =SUM(C31-AR31+D32) -> 36326.08 | G32: 594.06 | H32: 318.87 | J32: 212.62 | K32: 340.4 | L32: 356.94 | M32: 1405 | N32: 773 | P32: 472 | Q32: 804 | R32: 869 | S32: =SUM(F32:L32) -> 1822.89 | T32: =SUM(M32:R32) -> 4323 | U32: =S32/T32 -> 0.42167245 | W32: 73.83 | Y32: 12.51 | AJ32: =SUM(V32:AI32) -> 86.34 | AR32: =SUM(AJ32+S32) -> 1909.23 | AS32: =AR32*AU32 -> 0 | AT32: =C32 -> 36326.08
A33: 43792 | B33: 0.169 | C33: =SUM(C32-AR32+D33) -> 34416.85 | E33: 15000 | S33: =SUM(F33:L33) -> 0 | T33: =SUM(M33:R33) -> 0 | U33: =S33/T33 -> #DIV/0! | AJ33: =SUM(V33:AI33) -> 0 | AR33: =SUM(AJ33+S33) -> 0 | AS33: =AR33*AU33 -> 0 | AT33: =C33 -> 34416.85 | AU33: =SUM(AU32) -> 0
A34: 43793 | C34: =SUM(C33-AR33+D34) -> 34416.85 | S34: =SUM(F34:L34) -> 0 | T34: =SUM(M34:R34) -> 0 | U34: =S34/T34 -> #DIV/0! | AJ34: =SUM(V34:AI34) -> 0 | AR34: =SUM(AJ34+S34) -> 0 | AS34: =AR34*AU34 -> 0 | AT34: =C34 -> 34416.85 | AU34: =SUM(AU33) -> 0
A35: 43794 | C35: =SUM(C34-AR34+D35) -> 34416.85 | S35: =SUM(F35:L35) -> 0 | T35: =SUM(M35:R35) -> 0 | U35: =S35/T35 -> #DIV/0! | AJ35: =SUM(V35:AI35) -> 0 | AR35: =SUM(AJ35+S35) -> 0 | AS35: =AR35*AU35 -> 0 | AT35: =C35 -> 34416.85 | AU35: =SUM(AU34) -> 0
A36: 43795 | C36: =SUM(C35-AR35+D36) -> 34416.85 | S36: =SUM(F36:L36) -> 0 | T36: =SUM(M36:R36) -> 0 | U36: =S36/T36 -> #DIV/0! | AJ36: =SUM(V36:AI36) -> 0 | AR36: =SUM(AJ36+S36) -> 0 | AS36: =AR36*AU36 -> 0 | AT36: =C36 -> 34416.85 | AU36: =SUM(AU35) -> 0
A37: 43796 | C37: =SUM(C36-AR36+D37) -> 34416.85 | S37: =SUM(F37:L37) -> 0 | T37: =SUM(M37:R37) -> 0 | U37: =S37/T37 -> #DIV/0! | AJ37: =SUM(V37:AI37) -> 0 | AR37: =SUM(AJ37+S37) -> 0 | AS37: =AR37*AU37 -> 0 | AT37: =C37 -> 34416.85 | AU37: =SUM(AU36) -> 0
A38: 43797 | C38: =SUM(C37-AR37+D38) -> 34416.85 | S38: =SUM(F38:L38) -> 0 | T38: =SUM(M38:R38) -> 0 | U38: =S38/T38 -> #DIV/0! | AJ38: =SUM(V38:AI38) -> 0 | AR38: =SUM(AJ38+S38) -> 0 | AS38: =AR38*AU38 -> 0 | AT38: =C38 -> 34416.85 | AU38: =SUM(AU37) -> 0
A39: 43798 | C39: =SUM(C38-AR38+D39) -> 34416.85 | S39: =SUM(F39:L39) -> 0 | T39: =SUM(M39:R39) -> 0 | U39: =S39/T39 -> #DIV/0! | AJ39: =SUM(V39:AI39) -> 0 | AR39: =SUM(AJ39+S39) -> 0 | AS39: =AR39*AU39 -> 0 | AT39: =C39 -> 34416.85 | AU39: =SUM(AU38) -> 0
A40: 43799 | C40: =SUM(C39-AR39+D40) -> 34416.85 | E40: 18000 | S40: =SUM(F40:L40) -> 0 | T40: =SUM(M40:R40) -> 0 | U40: =S40/T40 -> #DIV/0! | AJ40: =SUM(V40:AI40) -> 0 | AR40: =SUM(AJ40+S40) -> 0 | AS40: =AR40*AU40 -> 0 | AT40: =C40 -> 34416.85 | AU40: =SUM(AU39) -> 0
A41: 43800 | C41: =SUM(C40-AR40+D41) -> 34416.85 | S41: =SUM(F41:L41) -> 0 | T41: =SUM(M41:R41) -> 0 | U41: =S41/T41 -> #DIV/0! | AJ41: =SUM(V41:AI41) -> 0 | AR41: =SUM(AJ41+S41) -> 0 | AS41: =AR41*AU41 -> 0 | AT41: =C41 -> 34416.85 | AU41: =SUM(AU40) -> 0
C42: =SUM(C41-AR41+D42) -> 34416.85 | S42: =SUM(F42:L42) -> 0 | T42: =SUM(M42:R42) -> 0 | AJ42: =SUM(V42:AI42) -> 0 | AR42: =SUM(AJ42+S42) -> 0 | AS42: =AR42*AU42 -> 0 | AT42: =C42 -> 34416.85
A43: BF | B43: =AVERAGE(B11:B42) -> 0.3806087 | C43: =SUM(C42-AR42+D43) -> 34416.85 | S43: =SUM(F43:L43) -> 0 | T43: =SUM(M43:R43) -> 0 | AJ43: =SUM(V43:AI43) -> 0 | AR43: =SUM(AJ43+S43) -> 0 | AS43: =AR43*AU43 -> 0 | AT43: =C43 -> 34416.85
S44: =SUM(F44:L44) -> 0 | AJ44: =SUM(V44:AI44) -> 0 | AR44: =S44+AJ44 -> 0 | AS44: =AR44*AU44 -> 0
D45: =SUM(D11:D44) -> 51000 | E45: =SUM(E11:E42) -> 84000 | F45: =SUM(F11:F44) -> 0 | G45: =SUM(G11:G44) -> 9205.34 | H45: =SUM(H11:H44) -> 10522.88 | I45: =SUM(I11:I44) -> 0 | J45: =SUM(J11:J44) -> 10211.58 | K45: =SUM(K11:K44) -> 8498.21 | L45: =SUM(L11:L44) -> 9455.15 | M45: =SUM(M11:M44) -> 22843 | ... O45: =SUM(O11:O44) -> 0 | P45: =SUM(P11:P43) -> 26436 | Q45: =SUM(Q11:Q44) -> 22177 | R45: =SUM(R11:R44) -> 22556 | S45: =SUM(F45:L45) -> 47893.16 | T45: =SUM(M45:R45) -> 119069 | U45: =SUM(U11:U42) -> #DIV/0! | V45: =SUM(V9:V44) -> 217.9 | W45: =SUM(W9:W44) -> 566.35 | X45: =SUM(X9:X44) -> 313.04 | Y45: =SUM(Y9:Y44) -> 197.79 | Z45: =SUM(Z9:Z44) -> 395.51 | AA45: =SUM(AA9:AA44) -> 0 | AB45: =SUM(AB9:AB44) -> 0 | AC45: =SUM(AC10:AC44) -> 147.97 | AD45: =SUM(AD10:AD44) -> 51.95 | AE45: =SUM(AE9:AE44) -> 0 | AF45: =SUM(AF9:AF44) -> 58.89 | AG45: =SUM(AG9:AG44) -> 600 | AH45: =SUM(AH9:AH43) -> 1305 | AI45: =SUM(AI9:AI39) -> 30 | AJ45: =SUM(AJ9:AJ44) -> 3884.4 | AR45: =SUM(AR11:AR43) -> 51777.56 | AS45: =SUM(AS11:AS44) -> 0
A46: Nb Day | AC46: =SUM(AC44/A47) -> #DIV/0! | AD46: =SUM(AD44/A47) -> #DIV/0! | AJ46: 0 | AQ46: =SUM(AQ45/12) -> 0
R47: =SUM(S47+#REF!) -> #REF! | T47: =S45*2143 -> 1.0263504e+08 | U47: TZS | W47: =SUM(W45/A47) -> #DIV/0! | X47: =SUM(X45/A47) -> #DIV/0! | Y47: =SUM(Y45/A47) -> #DIV/0! | Z47: =SUM(Z45/A47) -> #DIV/0! | AA47: =SUM(AA45/A47) -> #DIV/0! | AB47: =SUM(AB45/A47) -> #DIV/0! | AF47: =SUM(AF45/A47) -> #DIV/0! | AG47: =SUM(AG45/A47) -> #DIV/0! | AQ47: =SUM(AQ45/A47) -> #DIV/0!
A48: Av. Occ | B48: =SUM(B11:B41)/A47 -> #DIV/0! | T48: =T47/2245 -> 45717.168 | U48: USD | AR48: =AVERAGE(AR11:AR24) -> 2482.9007
AJ49: =SUM(AJ10:AJ25)/A47 -> #DIV/0! | AR49: =SUM(AQ45*'[1]Summery Report'!#REF!) -> #REF!
B50: A & K VEHICLES | F50: MAULY VEHICLES | L50: GREENLAND VEHICLE | S50: OTHERS VEHICLES | AJ50: =SUM(#REF!-AI34)/14 -> #REF!
B51: Date | C51: Vehicles | D51: Liters | E51: Driver name | F51: Date | H51: Vehicles | I51: Liters | K51: Driver name | L51: Date | N51: Vehicles | O51: Liters | Q51: Driver name | R51: Authorized Manager | S51: Date | T51: Vehicles | U51: Liters | V51: Driver name | W51: Athorized Manager | X51: Reasons
B52: 43772 | C52: T106CWQ | D52: 36 | E52: Gurisha | S52: 43778 | T52: T740DIS | U52: 30 | V52: Alphonce | W52: Noel | X52: Paid
B53: 43776 | C53: T882DKQ | D53: 112 | E53: Moses
B54: 43779 | C54: T111CWQ | D54: 145 | E54: Richard
B55: 43781 | C55: T880DKQ | D55: 137 | E55: Dickson
B56: 43782 | C56: T132CWQ | D56: 122 | E56: Zakayo
B57: 43782 | C57: T364AHF | D57: 67 | E57: Zakayo
B58: 43782 | C58: T840DDW | D58: 178 | E58: Kelvin
B59: 43783 | C59: T882DKQ | D59: 117 | E59: Moses
B60: 43784 | C60: T106CWQ | D60: 141 | E60: Priscus
B61: 43784 | C61: T880DKQ | D61: 51 | E61: Dickson
B62: 43785 | C62: T111CWQ | D62: 60 | E62: Richard
B63: 43786 | C63: T132CWQ | D63: 91 | E63: Zakayo
B64: 43787 | C64: 106CWQ | D64: 48 | E64: Priscus

Sheet Energy Graph
A1: Date | B1: Usage KW | C1: Occ % | D1: Cost per room Total Occ | E1: Cost per room Guest Occ
A2: =SUM([1]Gen!A11) -> 43739 | B2: =SUM('[1]Summery Report'!F5) -> 5669 | C2: =SUM('[1]Summery Report'!C5) -> 0.623 | D2: =SUM('[1]Summery Report'!#REF!) -> #REF! | E2: =SUM('[1]Summery Report'!#REF!) -> #REF! | F2: 0.1
A3: =SUM([1]Gen!A12) -> 43740 | B3: =SUM('[1]Summery Report'!F6) -> 6159 | C3: =SUM('[1]Summery Report'!C6) -> 0.779 | D3: =SUM('[1]Summery Report'!#REF!) -> #REF! | E3: =SUM('[1]Summery Report'!#REF!) -> #REF! | F3: 0.1375
A4: =SUM([1]Gen!A13) -> 43741 | B4: =SUM('[1]Summery Report'!F7) -> 6580 | C4: =SUM('[1]Summery Report'!C7) -> 0.532 | D4: =SUM('[1]Summery Report'!#REF!) -> #REF! | E4: =SUM('[1]Summery Report'!#REF!) -> #REF! | F4: 0.0875
A5: =SUM([1]Gen!A14) -> 43742 | B5: =SUM('[1]Summery Report'!F8) -> 6223 | C5: =SUM('[1]Summery Report'!C8) -> 0.61 | D5: =SUM('[1]Summery Report'!#REF!) -> #REF! | E5: =SUM('[1]Summery Report'!#REF!) -> #REF! | F5: 0.225
A6: =SUM([1]Gen!A15) -> 43743 | B6: =SUM('[1]Summery Report'!F9) -> 5984 | C6: =SUM('[1]Summery Report'!C9) -> 0.688 | D6: =SUM('[1]Summery Report'!#REF!) -> #REF! | E6: =SUM('[1]Summery Report'!#REF!) -> #REF! | F6: 0.2
A7: =SUM([1]Gen!A16) -> 43744 | B7: =SUM('[1]Summery Report'!F10) -> 6103 | C7: =SUM('[1]Summery Report'!C10) -> 0.532 | D7: =SUM('[1]Summery Report'!#REF!) -> #REF! | E7: =SUM('[1]Summery Report'!#REF!) -> #REF! | F7: 0.35
A8: =SUM([1]Gen!A17) -> 43745 | B8: =SUM('[1]Summery Report'!F11) -> 5576 | C8: =SUM('[1]Summery Report'!C11) -> 0.753 | D8: =SUM('[1]Summery Report'!#REF!) -> #REF! | E8: =SUM('[1]Summery Report'!#REF!) -> #REF! | F8: 0.375
A9: =SUM([1]Gen!A18) -> 43746 | B9: =SUM('[1]Summery Report'!F12) -> 5532 | C9: =SUM('[1]Summery Report'!C12) -> 0.156 | D9: =SUM('[1]Summery Report'!#REF!) -> #REF! | E9: =SUM('[1]Summery Report'!#REF!) -> #REF! | F9: 0.325
A10: =SUM([1]Gen!A19) -> 43747 | B10: =SUM('[1]Summery Report'!F13) -> 6233 | C10: =SUM('[1]Summery Report'!C13) -> 0.442 | D10: =SUM('[1]Summery Report'!#REF!) -> #REF! | E10: =SUM('[1]Summery Report'!#REF!) -> #REF! | F10: 0.75
A11: =SUM([1]Gen!A20) -> 43748 | B11: =SUM('[1]Summery Report'!F14) -> 6063 | C11: =SUM('[1]Summery Report'!C14) -> 0.325 | D11: =SUM('[1]Summery Report'!#REF!) -> #REF! | E11: =SUM('[1]Summery Report'!#REF!) -> #REF! | F11: 0.7625
A12: =SUM([1]Gen!A21) -> 43749 | B12: =SUM('[1]Summery Report'!F15) -> 5967 | C12: =SUM('[1]Summery Report'!C15) -> 0.455 | D12: =SUM('[1]Summery Report'!#REF!) -> #REF! | E12: =SUM('[1]Summery Report'!#REF!) -> #REF! | F12: 0.1625
A13: =SUM([1]Gen!A22) -> 43750 | B13: =SUM('[1]Summery Report'!F16) -> 5863 | C13: =SUM('[1]Summery Report'!C16) -> 0.416 | D13: =SUM('[1]Summery Report'!#REF!) -> #REF! | E13: =SUM('[1]Summery Report'!#REF!) -> #REF! | F13: 0.1125
... A32: =SUM([1]Gen!A41) -> 43769 | B32: =SUM('[1]Summery Report'!F35) -> 0 | C32: =SUM('[1]Summery Report'!C35) -> 0 | D32: =SUM('[1]Summery Report'!#REF!) -> #REF! | E32: =SUM('[1]Summery Report'!#REF!) -> #REF! | F32: 0.175
B33: =[1]Gen!S41 -> 0

Sheet Lpg (2)
C3: Four Sasons Safari Lodge Serengeti | H3: =4579-#REF! -> #REF!
G6: VALUE | H6: Cost
A7: DATE | B7: A | C7: B | D7: C | F7: Meter Reading | G7: Total | H7: Occu | I7: No.of | J7: Kg
B8: 2Ton% | C8: 1Ton (%) | D8: 1Ton% | F8: consumption | G8: Consumption Kg | H8: % | I8: pax | J8: per pax
B9: 76 | C9: 85 | D9: 85 | F9: 67280.75
A10: =Gen!A11 -> 43770 | B10: 73 | C10: 85 | D10: 85 | F10: 67328.1 | G10: =(F10-F9)*4.4 -> 208.34 | H10: ='[1]Summery Report'!C5 -> 0.623 | I10: =SUM(F10/H10) -> 108070.79 | J10: =SUM(G10/I10) -> 0.0019278105
A11: =Gen!A12 -> 43771 | B11: 70 | C11: 85 | D11: 85 | F11: 67351.14 | G11: =(F11-F10)*4.4 -> 101.376 | H11: ='[1]Summery Report'!C6 -> 0.779 | I11: =SUM(F11/H11) -> 86458.46 | J11: =SUM(G11/I11) -> 0.00117254
A12: =Gen!A13 -> 43772 | B12: 66 | C12: 85 | D12: 85 | F12: 67374.2 | G12: =(F12-F11)*4.4 -> 101.464 | H12: ='[1]Summery Report'!C7 -> 0.532 | I12: =SUM(F12/H12) -> 126643.23 | J12: =SUM(G12/I12) -> 0.0008011798
A13: =Gen!A14 -> 43773 | B13: 62 | C13: 85 | D13: 85 | F13: 67404.34 | G13: =(F13-F12)*4.4 -> 132.616 | H13: ='[1]Summery Report'!C8 -> 0.61 | I13: =SUM(F13/H13) -> 110498.92 | J13: =SUM(G13/I13) -> 0.0012001565
A14: =Gen!A15 -> 43774 | B14: 60 | C14: 85 | D14: 85 | F14: 67437.79 | G14: =(F14-F13)*4.4 -> 147.18 | H14: ='[1]Summery Report'!C9 -> 0.688 | I14: =SUM(F14/H14) -> 98020.044 | J14: =SUM(G14/I14) -> 0.0015015296
A15: =Gen!A16 -> 43775 | B15: 56 | C15: 85 | D15: 85 | F15: 67470.67 | G15: =(F15-F14)*4.4 -> 144.672 | H15: ='[1]Summery Report'!C10 -> 0.532 | I15: =SUM(F15/H15) -> 126824.57 | J15: =SUM(G15/I15) -> 0.0011407254
A16: =Gen!A17 -> 43776 | B16: 54 | C16: 85 | D16: 85 | F16: 67504.55 | G16: =(F16-F15)*4.4 -> 149.072 | H16: ='[1]Summery Report'!C11 -> 0.753 | I16: =SUM(F16/H16) -> 89647.477 | J16: =SUM(G16/I16) -> 0.0016628689
A17: =Gen!A18 -> 43777 | B17: 50 | C17: 85 | D17: 85 | F17: 67539.11 | G17: =(F17-F16)*4.4 -> 152.064 | H17: ='[1]Summery Report'!C12 -> 0.156 | I17: =SUM(F17/H17) -> 432943.01 | J17: =SUM(G17/I17) -> 0.00035123329
A18: =Gen!A19 -> 43778 | B18: 47 | C18: 85 | D18: 85 | F18: 67573.72 | G18: =(F18-F17)*4.4 -> 152.284 | H18: ='[1]Summery Report'!C13 -> 0.442 | I18: =SUM(F18/H18) -> 152881.72 | J18: =SUM(G18/I18) -> 0.00099609031
A19: =Gen!A20 -> 43779 | B19: 45 | C19: 85 | D19: 85 | F19: 67597.24 | G19: =(F19-F18)*4.4 -> 103.488 | H19: ='[1]Summery Report'!C14 -> 0.325 | I19: =SUM(F19/H19) -> 207991.51 | J19: =SUM(G19/I19) -> 0.00049755878
A20: =Gen!A21 -> 43780 | B20: 42 | C20: 85 | D20: 85 | F20: 67620.37 | G20: =(F20-F19)*4.4 -> 101.772 | H20: ='[1]Summery Report'!C15 -> 0.455 | I20: =SUM(F20/H20) -> 148616.2 | J20: =SUM(G20/I20) -> 0.0006847975
A21: =Gen!A22 -> 43781 | B21: 39 | C21: 85 | D21: 85 | F21: 67646.55 | G21: =(F21-F20)*4.4 -> 115.192 | H21: ='[1]Summery Report'!C16 -> 0.416 | I21: =SUM(F21/H21) -> 162611.9 | J21: =SUM(G21/I21) -> 0.00070838604
... A31: =Gen!A32 -> 43791 | B31: 15 | C31: 85 | D31: 85 | F31: 67902.8 | G31: =(F31-F30)*4.4 -> 110.528 | H31: ='[1]Summery Report'!C26 -> 0.403 | I31: =SUM(F31/H31) -> 168493.3 | J31: =SUM(G31/I31) -> 0.0006559786
A32: =Gen!A33 -> 43792 | G32: =(F32-F31)*4.4 -> -298772.32 | H32: ='[1]Summery Report'!C27 -> 0.24 | I32: =SUM(F32/H32) -> 0 | J32: =SUM(G32/I32) -> #DIV/0!
A33: =Gen!A34 -> 43793 | G33: =(F33-F32)*4.4 -> 0 | H33: ='[1]Summery Report'!C28 -> 0.09 | I33: =SUM(F33/H33) -> 0 | J33: =SUM(G33/I33) -> #DIV/0!
A34: =Gen!A35 -> 43794 | G34: =(F34-F33)*4.4 -> 0 | H34: ='[1]Summery Report'!C29 -> 0.286 | I34: =SUM(F34/H34) -> 0 | J34: =SUM(G34/I34) -> #DIV/0!
A35: =Gen!A36 -> 43795 | G35: =(F35-F34)*4.4 -> 0 | H35: ='[1]Summery Report'!C30 -> 0.545 | I35: =SUM(F35/H35) -> 0 | J35: =SUM(G35/I35) -> #DIV/0!
A36: =Gen!A37 -> 43796 | G36: =(F36-F35)*4.4 -> 0 | H36: ='[1]Summery Report'!C31 -> 0.675 | I36: =SUM(F36/H36) -> 0 | J36: =SUM(G36/I36) -> #DIV/0!
A37: =Gen!A38 -> 43797 | G37: =(F37-F36)*4.4 -> 0 | H37: ='[1]Summery Report'!C32 -> 0.273 | I37: =SUM(F37/H37) -> 0 | J37: =SUM(G37/I37) -> #DIV/0!
A38: =Gen!A39 -> 43798 | G38: =(F38-F37)*4.4 -> 0 | H38: ='[1]Summery Report'!C33 -> 0 | I38: =SUM(F38/H38) -> #DIV/0! | J38: =SUM(G38/I38) -> #DIV/0!
A39: =Gen!A40 -> 43799 | G39: =(F39-F38)*4.4 -> 0 | H39: ='[1]Summery Report'!C34 -> 0 | I39: =SUM(F39/H39) -> #DIV/0! | J39: =SUM(G39/I39) -> #DIV/0!
A40: =Gen!A41 -> 43800 | G40: =(F40-F39)*4.4 -> 0 | H40: ='[1]Summery Report'!C35 -> 0 | I40: =SUM(F40/H40) -> #DIV/0! | J40: =SUM(G40/I40) -> #DIV/0!
A41: =[1]Gen!A42 -> #REF! | G41: =(F41-F40)*4.4 -> 0 | H41: ='[1]Summery Report'!C36 -> 0 | I41: =SUM(F41/H41) -> #DIV/0!
C42: TOTAL USAGE | E42: =SUM(E10:E40) -> 0 | F42: =SUM(F10:F40) -> 1487707.8 | G42: =SUM(G10:G40) -> -296035.3
F45: =E12-E11 -> 0 | G45: =F45*4.4 -> 0

Sheet LPG_Graph
A1: Date | B1: Usage KG | C1: Occ %
A2: =SUM([1]Gen!A11) -> 43739 | B2: ='[1]Lpg (2)'!G10 -> 197.56 | C2: =SUM([1]Gen!B11) -> 0.623
A3: =SUM([1]Gen!A12) -> 43740 | B3: ='[1]Lpg (2)'!G11 -> 131.956 | C3: =SUM([1]Gen!B12) -> 0.779
A4: =SUM([1]Gen!A13) -> 43741 | B4: ='[1]Lpg (2)'!G12 -> 117.48 | C4: =SUM([1]Gen!B13) -> 0.532
A5: =SUM([1]Gen!A14) -> 43742 | B5: ='[1]Lpg (2)'!G13 -> 102.96 | C5: =SUM([1]Gen!B14) -> 0.61
A6: =SUM([1]Gen!A15) -> 43743 | B6: ='[1]Lpg (2)'!G14 -> 101.816 | C6: =SUM([1]Gen!B15) -> 0.688
A7: =SUM([1]Gen!A16) -> 43744 | B7: ='[1]Lpg (2)'!G15 -> 106.92 | C7: =SUM([1]Gen!B16) -> 0.532
A8: =SUM([1]Gen!A17) -> 43745 | B8: ='[1]Lpg (2)'!G16 -> 116.732 | C8: =SUM([1]Gen!B17) -> 0.753
A9: =SUM([1]Gen!A18) -> 43746 | B9: ='[1]Lpg (2)'!G17 -> 105.732 | C9: =SUM([1]Gen!B18) -> 0.156
A10: =SUM([1]Gen!A19) -> 43747 | B10: ='[1]Lpg (2)'!G18 -> 114.4 | C10: =SUM([1]Gen!B19) -> 0.442
A11: =SUM([1]Gen!A20) -> 43748 | B11: ='[1]Lpg (2)'!G19 -> 102.08 | C11: =SUM([1]Gen!B20) -> 0.325
A12: =SUM([1]Gen!A21) -> 43749 | B12: ='[1]Lpg (2)'!G20 -> 105.292 | C12: =SUM([1]Gen!B21) -> 0.455
A13: =SUM([1]Gen!A22) -> 43750 | B13: ='[1]Lpg (2)'!G21 -> 114.664 | C13: =SUM([1]Gen!B22) -> 0.416
... A32: =SUM([1]Gen!A41) -> 43769 | B32: ='[1]Lpg (2)'!G40 -> 0 | C32: =SUM([1]Gen!B41) -> #REF!

Sheet Water-Meter
A1: Four Seasons Safari Lodge Serengeti OCT 2019- Water Report
C2: Main Meter | F2: KITCHEN | I2: Amani café | L2: Main SW POOL | O2: Laundry | S2: BORE HOLE NO.1 METER READING | V2: BORE HOLE NO.2 METER READING | Y2: BORE HOLE NO.3 METER READING | AB2: BORE HOLE NO.4 METER READING | AE2: BORE HOLE NO.5 METER READING | AH2: BORE HOLE NO.6 METER READING | AK2: RAIN WATER - METER READING | AN2: TOTAL WATER PRODUCTION
A3: DATE | C3: Open Bal | D3: Final | E3: consumption | F3: Open Bal | G3: Final | H3: consumption | I3: Open Bal | J3: Final | K3: consumption | L3: Open Bal | M3: Final | N3: consumption | O3: Open Bal | P3: Final | Q3: consumption | R3: Total consumption
S4: OPEN | T4: FINAL | U4: PROD. | V4: OPEN | W4: FINAL | X4: PROD. | Y4: OPEN | Z4: FINAL | AA4: PROD. | AB4: OPEN | AC4: FINAL | AD4: M3 | AE4: OPEN | AF4: FINAL | AG4: M3 | AH4: OPEN | AI4: FINAL | AJ4: M3 | AK4: OPEN | AL4: FINAL | AM4: M3
C5: =D4 -> 0 | D5: 215914 | E5: =IF((D5-D4)<0,"0",(D5-D4)) -> 215914 | F5: =G4 -> 0 | G5: 36884 | H5: =IF((G5-G4)<0,"0",(G5-G4)) -> 36884 | I5: =J4 -> 0 | J5: 7444 | K5: =IF((J5-J4)<0,"0",(J5-J4)) -> 7444 | L5: =M4 -> 0 | M5: 10700 | N5: =IF((M5-M4)<0,"0",(M5-M4)) -> 10700 | O5: =P4 -> 0 | P5: 18829 | Q5: =IF((P5-P4)<0,"0",(P5-P4)) -> 18829 | S5: =T4 -> FINAL | T5: 45970 | U5: =V4 -> OPEN | V5: =W4 -> FINAL | W5: 64218 | Y5: =Z4 -> FINAL | Z5: 73536 | AB5: =AC4 -> FINAL | AC5: 11537 | AE5: =AF4 -> FINAL | AF5: 14086 | AH5: =AI4 -> FINAL | AI5: 22768 | AK5: =AL4 -> FINAL | AL5: 15154
A6: =Gen!A11 -> 43770 | C6: =D5 -> 215914 | D6: 216042 | E6: =IF((D6-D5)<0,"0",(D6-D5)) -> 128 | F6: =G5 -> 36884 | G6: 36900 | H6: =IF((G6-G5)<0,"0",(G6-G5)) -> 16 | I6: =J5 -> 7444 | J6: 7447 | K6: =IF((J6-J5)<0,"0",(J6-J5)) -> 3 | L6: =M5 -> 10700 | M6: 10726 | N6: =IF((M6-M5)<0,"0",(M6-M5)) -> 26 | O6: =P5 -> 18829 | P6: 18842 | Q6: =IF((P6-P5)<0,"0",(P6-P5)) -> 13 | S6: =T5 -> 45970 | T6: 46000 | U6: =IF((T6-T5)<0,"0",(T6-T5)) -> 30 | V6: =W5 -> 64218 | W6: 64268 | X6: =IF((W6-W5)<0,"0",(W6-W5)) -> 50 | Y6: =Z5 -> 73536 | Z6: 73601 | AA6: =IF((Z6-Z5)<0,"0",(Z6-Z5)) -> 65 | AB6: =AC5 -> 11537 | AC6: 11544 | AD6: =IF((AC6-AC5)<0,"0",(AC6-AC5)) -> 7 | AE6: =AF5 -> 14086 | AF6: 14100 | AG6: =IF((AF6-AF5)<0,"0",(AF6-AF5)) -> 14 | AH6: =AI5 -> 22768 | AI6: 22787 | AJ6: =IF((AI6-AI5)<0,"0",(AI6-AI5)) -> 19 | AK6: =AL5 -> 15154 | AL6: 15154 | AM6: =IF((AL6-AL5)<0,"0",(AL6-AL5)) -> 0 | AN6: =U6+X6+AA6+AD6+AG6+AJ6+AM6 -> 185
A7: =Gen!A12 -> 43771 | C7: =D6 -> 216042 | D7: 216181 | E7: =IF((D7-D6)<0,"0",(D7-D6)) -> 139 | F7: =G6 -> 36900 | G7: 36923 | H7: =IF((G7-G6)<0,"0",(G7-G6)) -> 23 | I7: =J6 -> 7447 | J7: 7450 | K7: =IF((J7-J6)<0,"0",(J7-J6)) -> 3 | L7: =M6 -> 10726 | M7: 10732 | N7: =IF((M7-M6)<0,"0",(M7-M6)) -> 6 | O7: =P6 -> 18842 | P7: 18850 | Q7: =IF((P7-P6)<0,"0",(P7-P6)) -> 8 | S7: =T6 -> 46000 | T7: 46029 | U7: =IF((T7-T6)<0,"0",(T7-T6)) -> 29 | V7: =W6 -> 64268 | W7: 64319 | X7: =IF((W7-W6)<0,"0",(W7-W6)) -> 51 | Y7: =Z6 -> 73601 | Z7: 73656 | AA7: =IF((Z7-Z6)<0,"0",(Z7-Z6)) -> 55 | AB7: =AC6 -> 11544 | AC7: 11551 | AD7: =IF((AC7-AC6)<0,"0",(AC7-AC6)) -> 7 | AE7: =AF6 -> 14100 | AF7: 14114 | AG7: =IF((AF7-AF6)<0,"0",(AF7-AF6)) -> 14 | AH7: =AI6 -> 22787 | AI7: 22806 | AJ7: =IF((AI7-AI6)<0,"0",(AI7-AI6)) -> 19 | AK7: =AL6 -> 15154 | AL7: 15154 | AM7: =IF((AL7-AL6)<0,"0",(AL7-AL6)) -> 0 | AN7: =U7+X7+AA7+AD7+AG7+AJ7+AM7 -> 175
A8: =Gen!A13 -> 43772 | C8: =D7 -> 216181 | D8: 216313 | E8: =IF((D8-D7)<0,"0",(D8-D7)) -> 132 | F8: =G7 -> 36923 | G8: 36938 | H8: =IF((G8-G7)<0,"0",(G8-G7)) -> 15 | I8: =J7 -> 7450 | J8: 7456 | K8: =IF((J8-J7)<0,"0",(J8-J7)) -> 6 | L8: =M7 -> 10732 | M8: 10740 | N8: =IF((M8-M7)<0,"0",(M8-M7)) -> 8 | O8: =P7 -> 18850 | P8: 18863 | Q8: =IF((P8-P7)<0,"0",(P8-P7)) -> 13 | S8: =T7 -> 46029 | T8: 46058 | U8: =IF((T8-T7)<0,"0",(T8-T7)) -> 29 | V8: =W7 -> 64319 | W8: 64370 | X8: =IF((W8-W7)<0,"0",(W8-W7)) -> 51 | Y8: =Z7 -> 73656 | Z8: 73711 | AA8: =IF((Z8-Z7)<0,"0",(Z8-Z7)) -> 55 | AB8: =AC7 -> 11551 | AC8: 11558 | AD8: =IF((AC8-AC7)<0,"0",(AC8-AC7)) -> 7 | AE8: =AF7 -> 14114 | AF8: 14128 | AG8: =IF((AF8-AF7)<0,"0",(AF8-AF7)) -> 14 | AH8: =AI7 -> 22806 | AI8: 22826 | AJ8: =IF((AI8-AI7)<0,"0",(AI8-AI7)) -> 20 | AK8: =AL7 -> 15154 | AL8: 15154 | AM8: =IF((AL8-AL7)<0,"0",(AL8-AL7)) -> 0 | AN8: =U8+X8+AA8+AD8+AG8+AJ8+AM8 -> 176
A9: =Gen!A14 -> 43773 | C9: =D8 -> 216313 | D9: 216413 | E9: =IF((D9-D8)<0,"0",(D9-D8)) -> 100 | F9: =G8 -> 36938 | G9: 36953 | H9: =IF((G9-G8)<0,"0",(G9-G8)) -> 15 | I9: =J8 -> 7456 | J9: 7460 | K9: =IF((J9-J8)<0,"0",(J9-J8)) -> 4 | L9: =M8 -> 10740 | M9: 10753 | N9: =IF((M9-M8)<0,"0",(M9-M8)) -> 13 | O9: =P8 -> 18863 | P9: 18878 | Q9: =IF((P9-P8)<0,"0",(P9-P8)) -> 15 | S9: =T8 -> 46058 | T9: 46088 | U9: =IF((T9-T8)<0,"0",(T9-T8)) -> 30 | V9: =W8 -> 64370 | W9: 64421 | X9: =IF((W9-W8)<0,"0",(W9-W8)) -> 51 | Y9: =Z8 -> 73711 | Z9: 73766 | AA9: =IF((Z9-Z8)<0,"0",(Z9-Z8)) -> 55 | AB9: =AC8 -> 11558 | AC9: 11564 | AD9: =IF((AC9-AC8)<0,"0",(AC9-AC8)) -> 6 | AE9: =AF8 -> 14128 | AF9: 14142 | AG9: =IF((AF9-AF8)<0,"0",(AF9-AF8)) -> 14 | AH9: =AI8 -> 22826 | AI9: 22844 | AJ9: =IF((AI9-AI8)<0,"0",(AI9-AI8)) -> 18 | AK9: =AL8 -> 15154 | AL9: 15154 | AM9: =IF((AL9-AL8)<0,"0",(AL9-AL8)) -> 0 | AN9: =U9+X9+AA9+AD9+AG9+AJ9+AM9 -> 174
A10: =Gen!A15 -> 43774 | C10: =D9 -> 216413 | D10: 216532 | E10: =IF((D10-D9)<0,"0",(D10-D9)) -> 119 | F10: =G9 -> 36953 | G10: 36968 | H10: =IF((G10-G9)<0,"0",(G10-G9)) -> 15 | I10: =J9 -> 7460 | J10: 7461 | K10: =IF((J10-J9)<0,"0",(J10-J9)) -> 1 | L10: =M9 -> 10753 | M10: 10770 | N10: =IF((M10-M9)<0,"0",(M10-M9)) -> 17 | O10: =P9 -> 18878 | P10: 18880 | Q10: =IF((P10-P9)<0,"0",(P10-P9)) -> 2 | S10: =T9 -> 46088 | T10: 46117 | U10: =IF((T10-T9)<0,"0",(T10-T9)) -> 29 | V10: =W9 -> 64421 | W10: 64471 | X10: =IF((W10-W9)<0,"0",(W10-W9)) -> 50 | Y10: =Z9 -> 73766 | Z10: 73821 | AA10: =IF((Z10-Z9)<0,"0",(Z10-Z9)) -> 55 | AB10: =AC9 -> 11564 | AC10: 11571 | AD10: =IF((AC10-AC9)<0,"0",(AC10-AC9)) -> 7 | AE10: =AF9 -> 14142 | AF10: 14156 | AG10: =IF((AF10-AF9)<0,"0",(AF10-AF9)) -> 14 | AH10: =AI9 -> 22844 | AI10: 22863 | AJ10: =IF((AI10-AI9)<0,"0",(AI10-AI9)) -> 19 | AK10: =AL9 -> 15154 | AL10: 15154 | AM10: =IF((AL10-AL9)<0,"0",(AL10-AL9)) -> 0 | AN10: =U10+X10+AA10+AD10+AG10+AJ10+AM10 -> 174
A11: =Gen!A16 -> 43775 | C11: =D10 -> 216532 | D11: 216642 | E11: =IF((D11-D10)<0,"0",(D11-D10)) -> 110 | F11: =G10 -> 36968 | G11: 36981 | H11: =IF((G11-G10)<0,"0",(G11-G10)) -> 13 | I11: =J10 -> 7461 | J11: 7465 | K11: =IF((J11-J10)<0,"0",(J11-J10)) -> 4 | M11: 10780 | N11: =IF((M11-M10)<0,"0",(M11-M10)) -> 10 | O11: =P10 -> 18880 | P11: 18888 | Q11: =IF((P11-P10)<0,"0",(P11-P10)) -> 8 | S11: =T10 -> 46117 | T11: 46147 | U11: =IF((T11-T10)<0,"0",(T11-T10)) -> 30 | V11: =W10 -> 64471 | W11: 64524 | X11: =IF((W11-W10)<0,"0",(W11-W10)) -> 53 | Y11: =Z10 -> 73821 | Z11: 73875 | AA11: =IF((Z11-Z10)<0,"0",(Z11-Z10)) -> 54 | AB11: =AC10 -> 11571 | AC11: 11577 | AD11: =IF((AC11-AC10)<0,"0",(AC11-AC10)) -> 6 | AE11: =AF10 -> 14156 | AF11: 14170 | AG11: =IF((AF11-AF10)<0,"0",(AF11-AF10)) -> 14 | AH11: =AI10 -> 22863 | AI11: 22881 | AJ11: =IF((AI11-AI10)<0,"0",(AI11-AI10)) -> 18 | AK11: =AL10 -> 15154 | AL11: 15154 | AM11: =IF((AL11-AL10)<0,"0",(AL11-AL10)) -> 0 | AN11: =U11+X11+AA11+AD11+AG11+AJ11+AM11 -> 175
A12: =Gen!A17 -> 43776 | C12: =D11 -> 216642 | D12: 216737 | E12: =IF((D12-D11)<0,"0",(D12-D11)) -> 95 | F12: =G11 -> 36981 | G12: 36991 | H12: =IF((G12-G11)<0,"0",(G12-G11)) -> 10 | I12: =J11 -> 7465 | J12: 7468 | K12: =IF((J12-J11)<0,"0",(J12-J11)) -> 3 | L12: =M11 -> 10780 | M12: 10792 | N12: =IF((M12-M11)<0,"0",(M12-M11)) -> 12 | O12: =P11 -> 18888 | P12: 18895 | Q12: =IF((P12-P11)<0,"0",(P12-P11)) -> 7 | S12: =T11 -> 46147 | T12: 46177 | U12: =IF((T12-T11)<0,"0",(T12-T11)) -> 30 | V12: =W11 -> 64524 | W12: 64575 | X12: =IF((W12-W11)<0,"0",(W12-W11)) -> 51 | Y12: =Z11 -> 73875 | Z12: 73930 | AA12: =IF((Z12-Z11)<0,"0",(Z12-Z11)) -> 55 | AB12: =AC11 -> 11577 | AC12: 11584 | AD12: =IF((AC12-AC11)<0,"0",(AC12-AC11)) -> 7 | AE12: =AF11 -> 14170 | AF12: 14184 | AG12: =IF((AF12-AF11)<0,"0",(AF12-AF11)) -> 14 | AH12: =AI11 -> 22881 | AI12: 22900 | AJ12: =IF((AI12-AI11)<0,"0",(AI12-AI11)) -> 19 | AK12: =AL11 -> 15154 | AL12: 15154 | AM12: =IF((AL12-AL11)<0,"0",(AL12-AL11)) -> 0 | AN12: =U12+X12+AA12+AD12+AG12+AJ12+AM12 -> 176
A13: =Gen!A18 -> 43777 | C13: =D12 -> 216737 | D13: 216857 | E13: =IF((D13-D12)<0,"0",(D13-D12)) -> 120 | F13: =G12 -> 36991 | G13: 37005 | H13: =IF((G13-G12)<0,"0",(G13-G12)) -> 14 | I13: =J12 -> 7468 | J13: 7471 | K13: =IF((J13-J12)<0,"0",(J13-J12)) -> 3 | L13: =M12 -> 10792 | M13: 10810 | N13: =IF((M13-M12)<0,"0",(M13-M12)) -> 18 | O13: =P12 -> 18895 | P13: 18905 | Q13: =IF((P13-P12)<0,"0",(P13-P12)) -> 10 | S13: =T12 -> 46177 | T13: 46206 | U13: =IF((T13-T12)<0,"0",(T13-T12)) -> 29 | V13: =W12 -> 64575 | W13: 64627 | X13: =IF((W13-W12)<0,"0",(W13-W12)) -> 52 | Y13: =Z12 -> 73930 | Z13: 73984 | AA13: =IF((Z13-Z12)<0,"0",(Z13-Z12)) -> 54 | AB13: =AC12 -> 11584 | AC13: 11589 | AD13: =IF((AC13-AC12)<0,"0",(AC13-AC12)) -> 5 | AE13: =AF12 -> 14184 | AF13: 14198 | AG13: =IF((AF13-AF12)<0,"0",(AF13-AF12)) -> 14 | AH13: =AI12 -> 22900 | AI13: 22918 | AJ13: =IF((AI13-AI12)<0,"0",(AI13-AI12)) -> 18 | AK13: =AL12 -> 15154 | AL13: 15154 | AM13: =IF((AL13-AL12)<0,"0",(AL13-AL12)) -> 0 | AN13: =U13+X13+AA13+AD13+AG13+AJ13+AM13 -> 172
A14: =Gen!A19 -> 43778 | C14: =D13 -> 216857 | D14: 216953 | E14: =IF((D14-D13)<0,"0",(D14-D13)) -> 96 | F14: =G13 -> 37005 | G14: 37025 | H14: =IF((G14-G13)<0,"0",(G14-G13)) -> 20 | I14: =J13 -> 7471 | J14: 7474 | K14: =IF((J14-J13)<0,"0",(J14-J13)) -> 3 | L14: =M13 -> 10810 | M14: 10822 | N14: =IF((M14-M13)<0,"0",(M14-M13)) -> 12 | O14: =P13 -> 18905 | P14: 18913 | Q14: =IF((P14-P13)<0,"0",(P14-P13)) -> 8 | S14: =T13 -> 46206 | T14: 46237 | U14: =IF((T14-T13)<0,"0",(T14-T13)) -> 31 | V14: =W13 -> 64627 | W14: 64678 | X14: =IF((W14-W13)<0,"0",(W14-W13)) -> 51 | Y14: =Z13 -> 73984 | Z14: 74039 | AA14: =IF((Z14-Z13)<0,"0",(Z14-Z13)) -> 55 | AB14: =AC13 -> 11589 | AC14: 11596 | AD14: =IF((AC14-AC13)<0,"0",(AC14-AC13)) -> 7 | AE14: =AF13 -> 14198 | AF14: 14212 | AG14: =IF((AF14-AF13)<0,"0",(AF14-AF13)) -> 14 | AH14: =AI13 -> 22918 | AI14: 22936 | AJ14: =IF((AI14-AI13)<0,"0",(AI14-AI13)) -> 18 | AK14: =AL13 -> 15154 | AL14: 15154 | AM14: =IF((AL14-AL13)<0,"0",(AL14-AL13)) -> 0 | AN14: =U14+X14+AA14+AD14+AG14+AJ14+AM14 -> 176
A15: =Gen!A20 -> 43779 | C15: =D14 -> 216953 | D15: 217077 | E15: =IF((D15-D14)<0,"0",(D15-D14)) -> 124 | F15: =G14 -> 37025 | G15: 37043 | H15: =IF((G15-G14)<0,"0",(G15-G14)) -> 18 | I15: =J14 -> 7474 | J15: 7476 | K15: =IF((J15-J14)<0,"0",(J15-J14)) -> 2 | L15: =M14 -> 10822 | M15: 10845 | N15: =IF((M15-M14)<0,"0",(M15-M14)) -> 23 | O15: =P14 -> 18913 | P15: 18921 | Q15: =IF((P15-P14)<0,"0",(P15-P14)) -> 8 | S15: =T14 -> 46237 | T15: 46267 | U15: =IF((T15-T14)<0,"0",(T15-T14)) -> 30 | V15: =W14 -> 64678 | W15: 64730 | X15: =IF((W15-W14)<0,"0",(W15-W14)) -> 52 | Y15: =Z14 -> 74039 | Z15: 74094 | AA15: =IF((Z15-Z14)<0,"0",(Z15-Z14)) -> 55 | AB15: =AC14 -> 11596 | AC15: 11602 | AD15: =IF((AC15-AC14)<0,"0",(AC15-AC14)) -> 6 | AE15: =AF14 -> 14212 | AF15: 14226 | AG15: =IF((AF15-AF14)<0,"0",(AF15-AF14)) -> 14 | AH15: =AI14 -> 22936 | AI15: 22954 | AJ15: =IF((AI15-AI14)<0,"0",(AI15-AI14)) -> 18 | AK15: =AL14 -> 15154 | AL15: 15154 | AM15: =IF((AL15-AL14)<0,"0",(AL15-AL14)) -> 0 | AN15: =U15+X15+AA15+AD15+AG15+AJ15+AM15 -> 175
A16: =Gen!A21 -> 43780 | C16: =D15 -> 217077 | D16: 217208 | E16: =IF((D16-D15)<0,"0",(D16-D15)) -> 131 | F16: =G15 -> 37043 | G16: 37059 | H16: =IF((G16-G15)<0,"0",(G16-G15)) -> 16 | I16: =J15 -> 7476 | J16: 7479 | K16: =IF((J16-J15)<0,"0",(J16-J15)) -> 3 | L16: =M15 -> 10845 | M16: 10857 | N16: =IF((M16-M15)<0,"0",(M16-M15)) -> 12 | O16: =P15 -> 18921 | P16: 18933 | Q16: =IF((P16-P15)<0,"0",(P16-P15)) -> 12 | S16: =T15 -> 46267 | T16: 46294 | U16: =IF((T16-T15)<0,"0",(T16-T15)) -> 27 | V16: =W15 -> 64730 | W16: 64782 | X16: =IF((W16-W15)<0,"0",(W16-W15)) -> 52 | Y16: =Z15 -> 74094 | Z16: 74149 | AA16: =IF((Z16-Z15)<0,"0",(Z16-Z15)) -> 55 | AB16: =AC15 -> 11602 | AC16: 11609 | AD16: =IF((AC16-AC15)<0,"0",(AC16-AC15)) -> 7 | AE16: =AF15 -> 14226 | AF16: 14240 | AG16: =IF((AF16-AF15)<0,"0",(AF16-AF15)) -> 14 | AH16: =AI15 -> 22954 | AI16: 22973 | AJ16: =IF((AI16-AI15)<0,"0",(AI16-AI15)) -> 19 | AK16: =AL15 -> 15154 | AL16: 15154 | AM16: =IF((AL16-AL15)<0,"0",(AL16-AL15)) -> 0 | AN16: =U16+X16+AA16+AD16+AG16+AJ16+AM16 -> 174
A17: =Gen!A22 -> 43781 | C17: =D16 -> 217208 | D17: 217344 | E17: =IF((D17-D16)<0,"0",(D17-D16)) -> 136 | F17: =G16 -> 37059 | G17: 37078 | H17: =IF((G17-G16)<0,"0",(G17-G16)) -> 19 | I17: =J16 -> 7479 | J17: 7481 | K17: =IF((J17-J16)<0,"0",(J17-J16)) -> 2 | L17: =M16 -> 10857 | M17: 10872 | N17: =IF((M17-M16)<0,"0",(M17-M16)) -> 15 | O17: =P16 -> 18933 | P17: 18943 | Q17: =IF((P17-P16)<0,"0",(P17-P16)) -> 10 | S17: =T16 -> 46294 | T17: 46323 | U17: =IF((T17-T16)<0,"0",(T17-T16)) -> 29 | V17: =W16 -> 64782 | W17: 64831 | X17: =IF((W17-W16)<0,"0",(W17-W16)) -> 49 | Y17: =Z16 -> 74149 | Z17: 74201 | AA17: =IF((Z17-Z16)<0,"0",(Z17-Z16)) -> 52 | AB17: =AC16 -> 11609 | AC17: 11616 | AD17: =IF((AC17-AC16)<0,"0",(AC17-AC16)) -> 7 | AE17: =AF16 -> 14240 | AF17: 14254 | AG17: =IF((AF17-AF16)<0,"0",(AF17-AF16)) -> 14 | AH17: =AI16 -> 22973 | AI17: 22991 | AJ17: =IF((AI17-AI16)<0,"0",(AI17-AI16)) -> 18 | AK17: =AL16 -> 15154 | AL17: 15154 | AM17: =IF((AL17-AL16)<0,"0",(AL17-AL16)) -> 0 | AN17: =U17+X17+AA17+AD17+AG17+AJ17+AM17 -> 169
A18: =Gen!A23 -> 43782 | C18: =D17 -> 217344 | D18: 217467 | E18: =IF((D18-D17)<0,"0",(D18-D17)) -> 123 | F18: =G17 -> 37078 | G18: 37097 | H18: =IF((G18-G17)<0,"0",(G18-G17)) -> 19 | I18: =J17 -> 7481 | J18: 7483 | K18: =IF((J18-J17)<0,"0",(J18-J17)) -> 2 | L18: =M17 -> 10872 | M18: 10885 | N18: =IF((M18-M17)<0,"0",(M18-M17)) -> 13 | O18: =P17 -> 18943 | P18: 18949 | Q18: =IF((P18-P17)<0,"0",(P18-P17)) -> 6 | S18: =T17 -> 46323 | T18: 46352 | U18: =IF((T18-T17)<0,"0",(T18-T17)) -> 29 | V18: =W17 -> 64831 | W18: 64881 | X18: =IF((W18-W17)<0,"0",(W18-W17)) -> 50 | Y18: =Z17 -> 74201 | Z18: 74254 | AA18: =IF((Z18-Z17)<0,"0",(Z18-Z17)) -> 53 | AB18: =AC17 -> 11616 | AC18: 11622 | AD18: =IF((AC18-AC17)<0,"0",(AC18-AC17)) -> 6 | AE18: =AF17 -> 14254 | AF18: 14268 | AG18: =IF((AF18-AF17)<0,"0",(AF18-AF17)) -> 14 | AH18: =AI17 -> 22991 | AI18: 23009 | AJ18: =IF((AI18-AI17)<0,"0",(AI18-AI17)) -> 18 | AK18: =AL17 -> 15154 | AL18: 15154 | AM18: =IF((AL18-AL17)<0,"0",(AL18-AL17)) -> 0 | AN18: =U18+X18+AA18+AD18+AG18+AJ18+AM18 -> 170
A19: =Gen!A24 -> 43783 | C19: =D18 -> 217467 | D19: 217585 | E19: =IF((D19-D18)<0,"0",(D19-D18)) -> 118 | F19: =G18 -> 37097 | G19: 37113 | H19: =IF((G19-G18)<0,"0",(G19-G18)) -> 16 | I19: =J18 -> 7483 | J19: 7485 | K19: =IF((J19-J18)<0,"0",(J19-J18)) -> 2 | L19: =M18 -> 10885 | M19: 10885 | N19: =IF((M19-M18)<0,"0",(M19-M18)) -> 0 | O19: =P18 -> 18949 | P19: 18966 | Q19: =IF((P19-P18)<0,"0",(P19-P18)) -> 17 | S19: =T18 -> 46352 | T19: 46381 | U19: =IF((T19-T18)<0,"0",(T19-T18)) -> 29 | V19: =W18 -> 64881 | W19: 64931 | X19: =IF((W19-W18)<0,"0",(W19-W18)) -> 50 | Y19: =Z18 -> 74254 | Z19: 74306 | AA19: =IF((Z19-Z18)<0,"0",(Z19-Z18)) -> 52 | AB19: =AC18 -> 11622 | AC19: 11629 | AD19: =IF((AC19-AC18)<0,"0",(AC19-AC18)) -> 7 | AE19: =AF18 -> 14268 | AF19: 14281 | AG19: =IF((AF19-AF18)<0,"0",(AF19-AF18)) -> 13 | AH19: =AI18 -> 23009 | AI19: 23027 | AJ19: =IF((AI19-AI18)<0,"0",(AI19-AI18)) -> 18 | AK19: =AL18 -> 15154 | AL19: 15154 | AM19: =IF((AL19-AL18)<0,"0",(AL19-AL18)) -> 0 | AN19: =U19+X19+AA19+AD19+AG19+AJ19+AM19 -> 169
A20: =Gen!A25 -> 43784 | C20: =D19 -> 217585 | D20: 217692 | E20: =IF((D20-D19)<0,"0",(D20-D19)) -> 107 | F20: =G19 -> 37113 | G20: 37125 | H20: =IF((G20-G19)<0,"0",(G20-G19)) -> 12 | I20: =J19 -> 7485 | J20: 7488 | K20: =IF((J20-J19)<0,"0",(J20-J19)) -> 3 | L20: =M19 -> 10885 | M20: 10895 | N20: =IF((M20-M19)<0,"0",(M20-M19)) -> 10 | O20: =P19 -> 18966 | P20: 18975 | Q20: =IF((P20-P19)<0,"0",(P20-P19)) -> 9 | S20: =T19 -> 46381 | T20: 46411 | U20: =IF((T20-T19)<0,"0",(T20-T19)) -> 30 | V20: =W19 -> 64931 | W20: 64981 | X20: =IF((W20-W19)<0,"0",(W20-W19)) -> 50 | Y20: =Z19 -> 74306 | Z20: 74359 | AA20: =IF((Z20-Z19)<0,"0",(Z20-Z19)) -> 53 | AB20: =AC19 -> 11629 | AC20: 11635 | AD20: =IF((AC20-AC19)<0,"0",(AC20-AC19)) -> 6 | AE20: =AF19 -> 14281 | AF20: 14295 | AG20: =IF((AF20-AF19)<0,"0",(AF20-AF19)) -> 14 | AH20: =AI19 -> 23027 | AI20: 23044 | AJ20: =IF((AI20-AI19)<0,"0",(AI20-AI19)) -> 17 | AK20: =AL19 -> 15154 | AL20: 15154 | AM20: =IF((AL20-AL19)<0,"0",(AL20-AL19)) -> 0 | AN20: =U20+X20+AA20+AD20+AG20+AJ20+AM20 -> 170
A21: =Gen!A26 -> 43785 | C21: =D20 -> 217692 | D21: 217807 | E21: =IF((D21-D20)<0,"0",(D21-D20)) -> 115 | F21: =G20 -> 37125 | G21: 37139 | H21: =IF((G21-G20)<0,"0",(G21-G20)) -> 14 | I21: =J20 -> 7488 | J21: 7496 | K21: =IF((J21-J20)<0,"0",(J21-J20)) -> 8 | L21: =M20 -> 10895 | M21: 10902 | N21: =IF((M21-M20)<0,"0",(M21-M20)) -> 7 | O21: =P20 -> 18975 | P21: 18987 | Q21: =IF((P21-P20)<0,"0",(P21-P20)) -> 12 | S21: =T20 -> 46411 | T21: 46440 | U21: =IF((T21-T20)<0,"0",(T21-T20)) -> 29 | V21: =W20 -> 64981 | W21: 65031 | X21: =IF((W21-W20)<0,"0",(W21-W20)) -> 50 | Y21: =Z20 -> 74359 | Z21: 74411 | AA21: =IF((Z21-Z20)<0,"0",(Z21-Z20)) -> 52 | AB21: =AC20 -> 11635 | AC21: 11642 | AD21: =IF((AC21-AC20)<0,"0",(AC21-AC20)) -> 7 | AE21: =AF20 -> 14295 | AF21: 14309 | AG21: =IF((AF21-AF20)<0,"0",(AF21-AF20)) -> 14 | AH21: =AI20 -> 23044 | AI21: 23062 | AJ21: =IF((AI21-AI20)<0,"0",(AI21-AI20)) -> 18 | AK21: =AL20 -> 15154 | AL21: 15154 | AM21: =IF((AL21-AL20)<0,"0",(AL21-AL20)) -> 0 | AN21: =U21+X21+AA21+AD21+AG21+AJ21+AM21 -> 170
A22: =Gen!A27 -> 43786 | C22: =D21 -> 217807 | D22: 217934 | E22: =IF((D22-D21)<0,"0",(D22-D21)) -> 127 | F22: =G21 -> 37139 | G22: 37154 | H22: =IF((G22-G21)<0,"0",(G22-G21)) -> 15 | I22: =J21 -> 7496 | J22: 7499 | K22: =IF((J22-J21)<0,"0",(J22-J21)) -> 3 | L22: =M21 -> 10902 | M22: 10917 | N22: =IF((M22-M21)<0,"0",(M22-M21)) -> 15 | O22: =P21 -> 18987 | P22: 18998 | Q22: =IF((P22-P21)<0,"0",(P22-P21)) -> 11 | S22: =T21 -> 46440 | T22: 46469 | U22: =IF((T22-T21)<0,"0",(T22-T21)) -> 29 | V22: =W21 -> 65031 | W22: 65083 | X22: =IF((W22-W21)<0,"0",(W22-W21)) -> 52 | Y22: =Z21 -> 74411 | Z22: 74464 | AA22: =IF((Z22-Z21)<0,"0",(Z22-Z21)) -> 53 | AB22: =AC21 -> 11642 | AC22: 11648 | AD22: =IF((AC22-AC21)<0,"0",(AC22-AC21)) -> 6 | AE22: =AF21 -> 14309 | AF22: 14322 | AG22: =IF((AF22-AF21)<0,"0",(AF22-AF21)) -> 13 | AH22: =AI21 -> 23062 | AI22: 23081 | AJ22: =IF((AI22-AI21)<0,"0",(AI22-AI21)) -> 19 | AK22: =AL21 -> 15154 | AL22: 15154 | AM22: =IF((AL22-AL21)<0,"0",(AL22-AL21)) -> 0 | AN22: =U22+X22+AA22+AD22+AG22+AJ22+AM22 -> 172
A23: =Gen!A28 -> 43787 | C23: =D22 -> 217934 | D23: 218040 | E23: =IF((D23-D22)<0,"0",(D23-D22)) -> 106 | F23: =G22 -> 37154 | G23: 37168 | H23: =IF((G23-G22)<0,"0",(G23-G22)) -> 14 | I23: =J22 -> 7499 | J23: 7503 | K23: =IF((J23-J22)<0,"0",(J23-J22)) -> 4 | L23: =M22 -> 10917 | M23: 10927 | N23: =IF((M23-M22)<0,"0",(M23-M22)) -> 10 | O23: =P22 -> 18998 | P23: 19009 | Q23: =IF((P23-P22)<0,"0",(P23-P22)) -> 11 | S23: =T22 -> 46469 | T23: 46498 | U23: =IF((T23-T22)<0,"0",(T23-T22)) -> 29 | V23: =W22 -> 65083 | W23: 65135 | X23: =IF((W23-W22)<0,"0",(W23-W22)) -> 52 | Y23: =Z22 -> 74464 | Z23: 74517 | AA23: =IF((Z23-Z22)<0,"0",(Z23-Z22)) -> 53 | AB23: =AC22 -> 11648 | AC23: 11655 | AD23: =IF((AC23-AC22)<0,"0",(AC23-AC22)) -> 7 | AE23: =AF22 -> 14322 | AF23: 14336 | AG23: =IF((AF23-AF22)<0,"0",(AF23-AF22)) -> 14 | AH23: =AI22 -> 23081 | AI23: 23100 | AJ23: =IF((AI23-AI22)<0,"0",(AI23-AI22)) -> 19 | AK23: =AL22 -> 15154 | AL23: 15154 | AM23: =IF((AL23-AL22)<0,"0",(AL23-AL22)) -> 0 | AN23: =U23+X23+AA23+AD23+AG23+AJ23+AM23 -> 174
... A26: =Gen!A31 -> 43790 | C26: =D25 -> 218217 | D26: 218312 | E26: =IF((D26-D25)<0,"0",(D26-D25)) -> 95 | F26: =G25 -> 37201 | G26: 37216 | H26: =IF((G26-G25)<0,"0",(G26-G25)) -> 15 | I26: =J25 -> 7511 | J26: 7513 | K26: =IF((J26-J25)<0,"0",(J26-J25)) -> 2 | L26: =M25 -> 10940 | M26: 10952 | N26: =IF((M26-M25)<0,"0",(M26-M25)) -> 12 | O26: =P25 -> 19033 | P26: 19041 | Q26: =IF((P26-P25)<0,"0",(P26-P25)) -> 8 | S26: =T25 -> 46558 | T26: 46587 | U26: =IF((T26-T25)<0,"0",(T26-T25)) -> 29 | V26: =W25 -> 65236 | W26: 65287 | X26: =IF((W26-W25)<0,"0",(W26-W25)) -> 51 | Y26: =Z25 -> 74624 | Z26: 74677 | AA26: =IF((Z26-Z25)<0,"0",(Z26-Z25)) -> 53 | AB26: =AC25 -> 11667 | AC26: 11674 | AD26: =IF((AC26-AC25)<0,"0",(AC26-AC25)) -> 7 | AE26: =AF25 -> 14363 | AF26: 14377 | AG26: =IF((AF26-AF25)<0,"0",(AF26-AF25)) -> 14 | AH26: =AI25 -> 23134 | AI26: 23152 | AJ26: =IF((AI26-AI25)<0,"0",(AI26-AI25)) -> 18 | AK26: =AL25 -> 15154 | AL26: 15154 | AM26: =IF((AL26-AL25)<0,"0",(AL26-AL25)) -> 0 | AN26: =U26+X26+AA26+AD26+AG26+AJ26+AM26 -> 172
A27: =Gen!A32 -> 43791 | C27: =D26 -> 218312 | D27: 218407 | E27: =IF((D27-D26)<0,"0",(D27-D26)) -> 95 | F27: =G26 -> 37216 | G27: 37235 | H27: =IF((G27-G26)<0,"0",(G27-G26)) -> 19 | I27: =J26 -> 7513 | J27: 7516 | K27: =IF((J27-J26)<0,"0",(J27-J26)) -> 3 | L27: =M26 -> 10952 | N27: =IF((M27-M26)<0,"0",(M27-M26)) -> 0 | O27: =P26 -> 19041 | P27: 19050 | Q27: =IF((P27-P26)<0,"0",(P27-P26)) -> 9 | S27: =T26 -> 46587 | T27: 46617 | U27: =IF((T27-T26)<0,"0",(T27-T26)) -> 30 | V27: =W26 -> 65287 | W27: 65339 | X27: =IF((W27-W26)<0,"0",(W27-W26)) -> 52 | Y27: =Z26 -> 74677 | Z27: 74730 | AA27: =IF((Z27-Z26)<0,"0",(Z27-Z26)) -> 53 | AB27: =AC26 -> 11674 | AC27: 11680 | AD27: =IF((AC27-AC26)<0,"0",(AC27-AC26)) -> 6 | AE27: =AF26 -> 14377 | AF27: 14391 | AG27: =IF((AF27-AF26)<0,"0",(AF27-AF26)) -> 14 | AH27: =AI26 -> 23152 | AI27: 23171 | AJ27: =IF((AI27-AI26)<0,"0",(AI27-AI26)) -> 19 | AK27: =AL26 -> 15154 | AL27: 15154 | AM27: =IF((AL27-AL26)<0,"0",(AL27-AL26)) -> 0 | AN27: =U27+X27+AA27+AD27+AG27+AJ27+AM27 -> 174
A28: =Gen!A33 -> 43792 | C28: =D27 -> 218407 | E28: =IF((D28-D27)<0,"0",(D28-D27)) -> 0 | F28: =G27 -> 37235 | H28: =IF((G28-G27)<0,"0",(G28-G27)) -> 0 | I28: =J27 -> 7516 | K28: =IF((J28-J27)<0,"0",(J28-J27)) -> 0 | L28: =M27 -> 0 | N28: =IF((M28-M27)<0,"0",(M28-M27)) -> 0 | O28: =P27 -> 19050 | Q28: =IF((P28-P27)<0,"0",(P28-P27)) -> 0 | S28: =T27 -> 46617 | U28: =IF((T28-T27)<0,"0",(T28-T27)) -> 0 | V28: =W27 -> 65339 | X28: =IF((W28-W27)<0,"0",(W28-W27)) -> 0 | Y28: =Z27 -> 74730 | AA28: =IF((Z28-Z27)<0,"0",(Z28-Z27)) -> 0 | AB28: =AC27 -> 11680 | AD28: =IF((AC28-AC27)<0,"0",(AC28-AC27)) -> 0 | AE28: =AF27 -> 14391 | AG28: =IF((AF28-AF27)<0,"0",(AF28-AF27)) -> 0 | AH28: =AI27 -> 23171 | AJ28: =IF((AI28-AI27)<0,"0",(AI28-AI27)) -> 0 | AK28: =AL27 -> 15154 | AM28: =IF((AL28-AL27)<0,"0",(AL28-AL27)) -> 0 | AN28: =U28+X28+AA28+AD28+AG28+AJ28+AM28 -> 0
A29: =Gen!A34 -> 43793 | C29: =D28 -> 0 | E29: =IF((D29-D28)<0,"0",(D29-D28)) -> 0 | F29: =G28 -> 0 | H29: =IF((G29-G28)<0,"0",(G29-G28)) -> 0 | I29: =J28 -> 0 | K29: =IF((J29-J28)<0,"0",(J29-J28)) -> 0 | L29: =M28 -> 0 | N29: =IF((M29-M28)<0,"0",(M29-M28)) -> 0 | O29: =P28 -> 0 | Q29: =IF((P29-P28)<0,"0",(P29-P28)) -> 0 | S29: =T28 -> 0 | U29: =IF((T29-T28)<0,"0",(T29-T28)) -> 0 | V29: =W28 -> 0 | X29: =IF((W29-W28)<0,"0",(W29-W28)) -> 0 | Y29: =Z28 -> 0 | AA29: =IF((Z29-Z28)<0,"0",(Z29-Z28)) -> 0 | AB29: =AC28 -> 0 | AD29: =IF((AC29-AC28)<0,"0",(AC29-AC28)) -> 0 | AE29: =AF28 -> 0 | AG29: =IF((AF29-AF28)<0,"0",(AF29-AF28)) -> 0 | AH29: =AI28 -> 0 | AJ29: =IF((AI29-AI28)<0,"0",(AI29-AI28)) -> 0 | AK29: =AL28 -> 0 | AM29: =IF((AL29-AL28)<0,"0",(AL29-AL28)) -> 0 | AN29: =U29+X29+AA29+AD29+AG29+AJ29+AM29 -> 0
A30: =Gen!A35 -> 43794 | C30: =D29 -> 0 | E30: =IF((D30-D29)<0,"0",(D30-D29)) -> 0 | F30: =G29 -> 0 | H30: =IF((G30-G29)<0,"0",(G30-G29)) -> 0 | I30: =J29 -> 0 | K30: =IF((J30-J29)<0,"0",(J30-J29)) -> 0 | L30: =M29 -> 0 | N30: =IF((M30-M29)<0,"0",(M30-M29)) -> 0 | O30: =P29 -> 0 | Q30: =IF((P30-P29)<0,"0",(P30-P29)) -> 0 | S30: =T29 -> 0 | U30: =IF((T30-T29)<0,"0",(T30-T29)) -> 0 | V30: =W29 -> 0 | X30: =IF((W30-W29)<0,"0",(W30-W29)) -> 0 | Y30: =Z29 -> 0 | AA30: =IF((Z30-Z29)<0,"0",(Z30-Z29)) -> 0 | AB30: =AC29 -> 0 | AD30: =IF((AC30-AC29)<0,"0",(AC30-AC29)) -> 0 | AE30: =AF29 -> 0 | AG30: =IF((AF30-AF29)<0,"0",(AF30-AF29)) -> 0 | AH30: =AI29 -> 0 | AJ30: =IF((AI30-AI29)<0,"0",(AI30-AI29)) -> 0 | AK30: =AL29 -> 0 | AM30: =IF((AL30-AL29)<0,"0",(AL30-AL29)) -> 0 | AN30: =U30+X30+AA30+AD30+AG30+AJ30+AM30 -> 0
A31: =Gen!A36 -> 43795 | C31: =D30 -> 0 | E31: =IF((D31-D30)<0,"0",(D31-D30)) -> 0 | F31: =G30 -> 0 | H31: =IF((G31-G30)<0,"0",(G31-G30)) -> 0 | I31: =J30 -> 0 | K31: =IF((J31-J30)<0,"0",(J31-J30)) -> 0 | L31: =M30 -> 0 | N31: =IF((M31-M30)<0,"0",(M31-M30)) -> 0 | O31: =P30 -> 0 | Q31: =IF((P31-P30)<0,"0",(P31-P30)) -> 0 | S31: =T30 -> 0 | U31: =IF((T31-T30)<0,"0",(T31-T30)) -> 0 | V31: =W30 -> 0 | X31: =IF((W31-W30)<0,"0",(W31-W30)) -> 0 | Y31: =Z30 -> 0 | AA31: =IF((Z31-Z30)<0,"0",(Z31-Z30)) -> 0 | AB31: =AC30 -> 0 | AD31: =IF((AC31-AC30)<0,"0",(AC31-AC30)) -> 0 | AE31: =AF30 -> 0 | AG31: =IF((AF31-AF30)<0,"0",(AF31-AF30)) -> 0 | AH31: =AI30 -> 0 | AJ31: =IF((AI31-AI30)<0,"0",(AI31-AI30)) -> 0 | AK31: =AL30 -> 0 | AM31: =IF((AL31-AL30)<0,"0",(AL31-AL30)) -> 0 | AN31: =U31+X31+AA31+AD31+AG31+AJ31+AM31 -> 0
A32: =Gen!A37 -> 43796 | B32: 10/27//2009 | C32: =D31 -> 0 | E32: =IF((D32-D31)<0,"0",(D32-D31)) -> 0 | F32: =G31 -> 0 | H32: =IF((G32-G31)<0,"0",(G32-G31)) -> 0 | I32: =J31 -> 0 | K32: =IF((J32-J31)<0,"0",(J32-J31)) -> 0 | L32: =M31 -> 0 | N32: =IF((M32-M31)<0,"0",(M32-M31)) -> 0 | O32: =P31 -> 0 | Q32: =IF((P32-P31)<0,"0",(P32-P31)) -> 0 | S32: =T31 -> 0 | U32: =IF((T32-T31)<0,"0",(T32-T31)) -> 0 | V32: =W31 -> 0 | X32: =IF((W32-W31)<0,"0",(W32-W31)) -> 0 | Y32: =Z31 -> 0 | AA32: =IF((Z32-Z31)<0,"0",(Z32-Z31)) -> 0 | AB32: =AC31 -> 0 | AD32: =IF((AC32-AC31)<0,"0",(AC32-AC31)) -> 0 | AE32: =AF31 -> 0 | AG32: =IF((AF32-AF31)<0,"0",(AF32-AF31)) -> 0 | AH32: =AI31 -> 0 | AJ32: =IF((AI32-AI31)<0,"0",(AI32-AI31)) -> 0 | AK32: =AL31 -> 0 | AM32: =IF((AL32-AL31)<0,"0",(AL32-AL31)) -> 0 | AN32: =U32+X32+AA32+AD32+AG32+AJ32+AM32 -> 0
A33: =Gen!A38 -> 43797 | C33: =D32 -> 0 | E33: =IF((D33-D32)<0,"0",(D33-D32)) -> 0 | F33: =G32 -> 0 | H33: =IF((G33-G32)<0,"0",(G33-G32)) -> 0 | I33: =J32 -> 0 | K33: =IF((J33-J32)<0,"0",(J33-J32)) -> 0 | L33: =M32 -> 0 | N33: =IF((M33-M32)<0,"0",(M33-M32)) -> 0 | O33: =P32 -> 0 | Q33: =IF((P33-P32)<0,"0",(P33-P32)) -> 0 | S33: =T32 -> 0 | U33: =IF((T33-T32)<0,"0",(T33-T32)) -> 0 | V33: =W32 -> 0 | X33: =IF((W33-W32)<0,"0",(W33-W32)) -> 0 | Y33: =Z32 -> 0 | AA33: =IF((Z33-Z32)<0,"0",(Z33-Z32)) -> 0 | AB33: =AC32 -> 0 | AD33: =IF((AC33-AC32)<0,"0",(AC33-AC32)) -> 0 | AE33: =AF32 -> 0 | AG33: =IF((AF33-AF32)<0,"0",(AF33-AF32)) -> 0 | AH33: =AI32 -> 0 | AJ33: =IF((AI33-AI32)<0,"0",(AI33-AI32)) -> 0 | AK33: =AL32 -> 0 | AM33: =IF((AL33-AL32)<0,"0",(AL33-AL32)) -> 0 | AN33: =U33+X33+AA33+AD33+AG33+AJ33+AM33 -> 0
A34: =Gen!A39 -> 43798 | C34: =D33 -> 0 | E34: =IF((D34-D33)<0,"0",(D34-D33)) -> 0 | F34: =G33 -> 0 | H34: =IF((G34-G33)<0,"0",(G34-G33)) -> 0 | I34: =J33 -> 0 | K34: =IF((J34-J33)<0,"0",(J34-J33)) -> 0 | L34: =M33 -> 0 | N34: =IF((M34-M33)<0,"0",(M34-M33)) -> 0 | O34: =P33 -> 0 | Q34: =IF((P34-P33)<0,"0",(P34-P33)) -> 0 | S34: =T33 -> 0 | U34: =IF((T34-T33)<0,"0",(T34-T33)) -> 0 | V34: =W33 -> 0 | X34: =IF((W34-W33)<0,"0",(W34-W33)) -> 0 | Y34: =Z33 -> 0 | AA34: =IF((Z34-Z33)<0,"0",(Z34-Z33)) -> 0 | AB34: =AC33 -> 0 | AD34: =IF((AC34-AC33)<0,"0",(AC34-AC33)) -> 0 | AE34: =AF33 -> 0 | AG34: =IF((AF34-AF33)<0,"0",(AF34-AF33)) -> 0 | AH34: =AI33 -> 0 | AJ34: =IF((AI34-AI33)<0,"0",(AI34-AI33)) -> 0 | AK34: =AL33 -> 0 | AM34: =IF((AL34-AL33)<0,"0",(AL34-AL33)) -> 0 | AN34: =U34+X34+AA34+AD34+AG34+AJ34+AM34 -> 0
A35: =Gen!A40 -> 43799 | C35: =D34 -> 0 | E35: =IF((D35-D34)<0,"0",(D35-D34)) -> 0 | F35: =G34 -> 0 | H35: =IF((G35-G34)<0,"0",(G35-G34)) -> 0 | I35: =J34 -> 0 | K35: =IF((J35-J34)<0,"0",(J35-J34)) -> 0 | L35: =M34 -> 0 | N35: =IF((M35-M34)<0,"0",(M35-M34)) -> 0 | O35: =P34 -> 0 | Q35: =IF((P35-P34)<0,"0",(P35-P34)) -> 0 | S35: =T34 -> 0 | U35: =IF((T35-T34)<0,"0",(T35-T34)) -> 0 | V35: =W34 -> 0 | X35: =IF((W35-W34)<0,"0",(W35-W34)) -> 0 | Y35: =Z34 -> 0 | AA35: =IF((Z35-Z34)<0,"0",(Z35-Z34)) -> 0 | AB35: =AC34 -> 0 | AD35: =IF((AC35-AC34)<0,"0",(AC35-AC34)) -> 0 | AE35: =AF34 -> 0 | AG35: =IF((AF35-AF34)<0,"0",(AF35-AF34)) -> 0 | AH35: =AI34 -> 0 | AJ35: =IF((AI35-AI34)<0,"0",(AI35-AI34)) -> 0 | AK35: =AL34 -> 0 | AM35: =IF((AL35-AL34)<0,"0",(AL35-AL34)) -> 0 | AN35: =U35+X35+AA35+AD35+AG35+AJ35+AM35 -> 0
A36: =Gen!A41 -> 43800 | C36: =D35 -> 0 | E36: =IF((D36-D35)<0,"0",(D36-D35)) -> 0 | F36: =G35 -> 0 | H36: =IF((G36-G35)<0,"0",(G36-G35)) -> 0 | I36: =J35 -> 0 | K36: =IF((J36-J35)<0,"0",(J36-J35)) -> 0 | L36: =M35 -> 0 | N36: =IF((M36-M35)<0,"0",(M36-M35)) -> 0 | O36: =P35 -> 0 | Q36: =IF((P36-P35)<0,"0",(P36-P35)) -> 0 | S36: =T35 -> 0 | U36: =IF((T36-T35)<0,"0",(T36-T35)) -> 0 | V36: =W35 -> 0 | X36: =IF((W36-W35)<0,"0",(W36-W35)) -> 0 | Y36: =Z35 -> 0 | AA36: =IF((Z36-Z35)<0,"0",(Z36-Z35)) -> 0 | AB36: =AC35 -> 0 | AD36: =IF((AC36-AC35)<0,"0",(AC36-AC35)) -> 0 | AE36: =AF35 -> 0 | AG36: =IF((AF36-AF35)<0,"0",(AF36-AF35)) -> 0 | AH36: =AI35 -> 0 | AJ36: =IF((AI36-AI35)<0,"0",(AI36-AI35)) -> 0 | AK36: =AL35 -> 0 | AM36: =IF((AL36-AL35)<0,"0",(AL36-AL35)) -> 0 | AN36: =U36+X36+AA36+AD36+AG36+AJ36+AM36 -> 0
A37: =Gen!A42 -> 0 | C37: =D36 -> 0 | E37: =IF((D37-D36)<0,"0",(D37-D36)) -> 0 | F37: =G36 -> 0 | H37: =IF((G37-G36)<0,"0",(G37-G36)) -> 0 | I37: =J36 -> 0 | K37: =IF((J37-J36)<0,"0",(J37-J36)) -> 0 | L37: =M36 -> 0 | N37: =IF((M37-M36)<0,"0",(M37-M36)) -> 0 | O37: =P36 -> 0 | Q37: =IF((P37-P36)<0,"0",(P37-P36)) -> 0 | S37: =T36 -> 0 | U37: =IF((T37-T36)<0,"0",(T37-T36)) -> 0 | V37: =W36 -> 0 | X37: =IF((W37-W36)<0,"0",(W37-W36)) -> 0 | Y37: =Z36 -> 0 | AA37: =IF((Z37-Z36)<0,"0",(Z37-Z36)) -> 0 | AB37: =AC36 -> 0 | AD37: =IF((AC37-AC36)<0,"0",(AC37-AC36)) -> 0 | AE37: =AF36 -> 0 | AG37: =IF((AF37-AF36)<0,"0",(AF37-AF36)) -> 0 | AH37: =AI36 -> 0 | AJ37: =IF((AI37-AI36)<0,"0",(AI37-AI36)) -> 0 | AK37: =AL36 -> 0 | AM37: =IF((AL37-AL36)<0,"0",(AL37-AL36)) -> 0 | AN37: =U38+X38+AA38+AD38+AG38+AJ38+AM38 -> 647
C38: TOTAL USAGE | E38: =SUM(E6:E36) -> 2493 | F38: KL | H38: =SUM(H6:H37) -> 351 | K38: =SUM(K6:K37) -> 72 | N38: =M38-M37 -> 0 | Q38: =P38-O38 -> 0 | R38: =E38 -> 2493 | U38: =SUM(U6:U37) -> 647 | AN38: =U38+X38+AA38+AD38+AG38+AJ38+AM38 -> 647
C42: WATER TANK LEVEL
C43: RAW WATER TANK NO.1 | E43: RAW WATER TANK NO.2 | G43: TREATED WATER TANK | I43: TREATED -HILL TANK | K43: TOTAL WATER AVAILABLE
C44: CAPACITY 217 m³ | E44: CAPACITY 92 m³ | G44: CAPACITY 146 m³ | I44: CAPACITY 213 m³
C45: cm | D45: m³ | E45: cm | F45: m³ | H45: m³ | I45: cm | J45: m³ | K45: m³
A46: =[1]Gen!A11 -> 43739 | C46: 165 | D46: =C46*217/300 -> 119.35 | E46: 130 | F46: =E46*92/305 -> 39.213115 | G46: 185 | H46: =G46*146/383 -> 70.522193 | I46: 280 | J46: =I46*213/308 -> 193.63636 | K46: =D46+F46+H46+J46 -> 422.72167
A47: =[1]Gen!A12 -> 43740 | C47: 135 | D47: =C47*217/300 -> 97.65 | E47: 100 | F47: =E47*92/305 -> 30.163934 | G47: 165 | H47: =G47*146/383 -> 62.898172 | I47: 290 | J47: =I47*213/308 -> 200.55195 | K47: =D47+F47+H47+J47 -> 391.26405
A48: =[1]Gen!A13 -> 43741 | C48: 95 | D48: =C48*217/300 -> 68.716667 | E48: 60 | F48: =E48*92/305 -> 18.098361 | G48: 150 | H48: =G48*146/383 -> 57.180157 | I48: 286 | J48: =I48*213/308 -> 197.78571 | K48: =D48+F48+H48+J48 -> 341.7809
A49: =[1]Gen!A14 -> 43742 | C49: 225 | D49: =C49*217/300 -> 162.75 | E49: 190 | F49: =E49*92/305 -> 57.311475 | G49: 50 | H49: =G49*146/383 -> 19.060052 | I49: 285 | J49: =I49*213/308 -> 197.09416 | K49: =D49+F49+H49+J49 -> 436.21568
A50: =[1]Gen!A15 -> 43743 | C50: 270 | D50: =C50*217/300 -> 195.3 | E50: 235 | F50: =E50*92/305 -> 70.885246 | G50: 10 | H50: =G50*146/383 -> 3.8120104 | I50: 265 | J50: =I50*213/308 -> 183.26299 | K50: =D50+F50+H50+J50 -> 453.26024
A51: =[1]Gen!A16 -> 43744 | C51: 180 | D51: =C51*217/300 -> 130.2 | E51: 144 | F51: =E51*92/305 -> 43.436066 | G51: 210 | H51: =G51*146/383 -> 80.052219 | I51: 280 | J51: =I51*213/308 -> 193.63636 | K51: =D51+F51+H51+J51 -> 447.32465
A52: =[1]Gen!A17 -> 43745 | C52: 160 | D52: =C52*217/300 -> 115.73333 | E52: 124 | F52: =E52*92/305 -> 37.403279 | G52: 277 | H52: =G52*146/383 -> 105.59269 | I52: 285 | J52: =I52*213/308 -> 197.09416 | K52: =D52+F52+H52+J52 -> 455.82346
A53: =[1]Gen!A18 -> 43746 | C53: 146 | D53: =C53*217/300 -> 105.60667 | E53: 110 | F53: =E53*92/305 -> 33.180328 | G53: 255 | H53: =G53*146/383 -> 97.206266 | I53: 287 | J53: =I53*213/308 -> 198.47727 | K53: =D53+F53+H53+J53 -> 434.47053
A54: =[1]Gen!A19 -> 43747 | C54: 121 | D54: =C54*217/300 -> 87.523333 | E54: 85 | F54: =E54*92/305 -> 25.639344 | G54: 300 | H54: =G54*146/383 -> 114.36031 | I54: 290 | J54: =I54*213/308 -> 200.55195 | K54: =D54+F54+H54+J54 -> 428.07494
A55: =[1]Gen!A20 -> 43748 | C55: 156 | D55: =C55*217/300 -> 112.84 | E55: 120 | F55: =E55*92/305 -> 36.196721 | G55: 202 | H55: =G55*146/383 -> 77.002611 | I55: 290 | J55: =I55*213/308 -> 200.55195 | K55: =D55+F55+H55+J55 -> 426.59128
A56: =[1]Gen!A21 -> 43749 | C56: 125 | D56: =C56*217/300 -> 90.416667 | E56: 90 | F56: =E56*92/305 -> 27.147541 | G56: 185 | H56: =G56*146/383 -> 70.522193 | I56: 288 | J56: =I56*213/308 -> 199.16883 | K56: =D56+F56+H56+J56 -> 387.25523
A57: =[1]Gen!A22 -> 43750 | C57: 135 | D57: =C57*217/300 -> 97.65 | E57: 190 | F57: =E57*92/305 -> 57.311475 | G57: 90 | H57: =G57*146/383 -> 34.308094 | I57: 218 | J57: =I57*213/308 -> 150.75974 | K57: =D57+F57+H57+J57 -> 340.02931
... A67: =[1]Gen!A32 -> 43760 | C67: 166 | D67: =C67*217/300 -> 120.07333 | E67: 130 | F67: =E67*92/305 -> 39.213115 | G67: 125 | H67: =G67*146/383 -> 47.650131 | I67: 214 | J67: =I67*213/308 -> 147.99351 | K67: =D67+F67+H67+J67 -> 354.93009
A68: =[1]Gen!A33 -> 43761 | D68: =C68*217/300 -> 0 | F68: =E68*92/305 -> 0 | H68: =G68*146/383 -> 0 | J68: =I68*213/308 -> 0 | K68: =D68+F68+H68+J68 -> 0
A69: =[1]Gen!A34 -> 43762 | D69: =C69*217/300 -> 0 | F69: =E69*92/305 -> 0 | H69: =G69*146/383 -> 0 | J69: =I69*213/308 -> 0 | K69: =D69+F69+H69+J69 -> 0
A70: =[1]Gen!A35 -> 43763 | D70: =C70*217/300 -> 0 | F70: =E70*92/305 -> 0 | H70: =G70*146/383 -> 0 | J70: =I70*213/308 -> 0 | K70: =D70+F70+H70+J70 -> 0
A71: =[1]Gen!A36 -> 43764 | D71: =C71*217/300 -> 0 | F71: =E71*92/305 -> 0 | H71: =G71*146/383 -> 0 | J71: =I71*213/308 -> 0 | K71: =D71+F71+H71+J71 -> 0
A72: =[1]Gen!A37 -> 43765 | D72: =C72*217/300 -> 0 | F72: =E72*92/305 -> 0 | H72: =G72*146/383 -> 0 | J72: =I72*213/308 -> 0 | K72: =D72+F72+H72+J72 -> 0
A73: =[1]Gen!A38 -> 43766 | D73: =C73*217/300 -> 0 | F73: =E73*92/305 -> 0 | H73: =G73*146/383 -> 0 | J73: =I73*213/308 -> 0 | K73: =D73+F73+H73+J73 -> 0
A74: =[1]Gen!A39 -> 43767 | D74: =C74*217/300 -> 0 | F74: =E74*92/305 -> 0 | H74: =G74*146/383 -> 0 | J74: =I74*213/308 -> 0 | K74: =D74+F74+H74+J74 -> 0
A75: =[1]Gen!A40 -> 43768 | D75: =C75*217/300 -> 0 | F75: =E75*92/305 -> 0 | H75: =G75*146/383 -> 0 | J75: =I75*213/308 -> 0 | K75: =D75+F75+H75+J75 -> 0
A76: =[1]Gen!A41 -> 43769 | D76: =C76*217/300 -> 0 | F76: =E76*92/305 -> 0 | H76: =G76*146/383 -> 0 | J76: =I76*213/308 -> 0 | K76: =D76+F76+H76+J76 -> 0
A77: =[1]Gen!A42 -> #REF! | D77: =C77*217/300 -> 0 | F77: =E77*92/305 -> 0 | H77: =G77*146/383 -> 0 | J77: =I77*213/308 -> 0 | K77: =D77+F77+H77+J77 -> 0

Sheet Water_Graph 
A1: Date | B1: Usage | C1: Occ %
A2: =SUM([1]Gen!A11) -> 43739 | B2: =SUM('[1]Water-Meter'!R10) -> #REF! | C2: =SUM([1]Gen!B11) -> 0.623
A3: =SUM([1]Gen!A12) -> 43740 | B3: =SUM('[1]Water-Meter'!R11) -> #REF! | C3: =SUM([1]Gen!B12) -> 0.779
A4: =SUM([1]Gen!A13) -> 43741 | B4: =SUM('[1]Water-Meter'!R12) -> #REF! | C4: =SUM([1]Gen!B13) -> 0.532
A5: =SUM([1]Gen!A14) -> 43742 | B5: =SUM('[1]Water-Meter'!R13) -> #REF! | C5: =SUM([1]Gen!B14) -> 0.61
A6: =SUM([1]Gen!A15) -> 43743 | B6: =SUM('[1]Water-Meter'!R14) -> #REF! | C6: =SUM([1]Gen!B15) -> 0.688
A7: =SUM([1]Gen!A16) -> 43744 | B7: =SUM('[1]Water-Meter'!R15) -> #REF! | C7: =SUM([1]Gen!B16) -> 0.532
A8: =SUM([1]Gen!A17) -> 43745 | B8: =SUM('[1]Water-Meter'!R16) -> #REF! | C8: =SUM([1]Gen!B17) -> 0.753
A9: =SUM([1]Gen!A18) -> 43746 | B9: =SUM('[1]Water-Meter'!R17) -> #REF! | C9: =SUM([1]Gen!B18) -> 0.156
A10: =SUM([1]Gen!A19) -> 43747 | B10: =SUM('[1]Water-Meter'!R18) -> #REF! | C10: =SUM([1]Gen!B19) -> 0.442
A11: =SUM([1]Gen!A20) -> 43748 | B11: =SUM('[1]Water-Meter'!R19) -> #REF! | C11: =SUM([1]Gen!B20) -> 0.325
A12: =SUM([1]Gen!A21) -> 43749 | B12: =SUM('[1]Water-Meter'!R20) -> #REF! | C12: =SUM([1]Gen!B21) -> 0.455
A13: =SUM([1]Gen!A22) -> 43750 | B13: =SUM('[1]Water-Meter'!R21) -> #REF! | C13: =SUM([1]Gen!B22) -> 0.416
... A32: =SUM([1]Gen!A41) -> 43769 | B32: =SUM('[1]Water-Meter'!R40) -> #REF! | C32: =SUM([1]Gen!B41) -> #REF!

Sheet Sheet1
A2: Generator and Diseal Summry Report JANUARY 2016 | Q2: 2209.85 | R2: Diesel Cost | S2: Rate$ | T2: 1584
M3: % of Gas balance in Tank | P3: % of Dieasel balance in Tank | Q3: HLP Cost (TSH) | V3: Total Cost (TSH) | W3: Consumption Guest Occ% | AA3: Budget Cost Per Room occ
A4: Date | B4: Gen Set Hours Working | C4: Occ% | D4: Total OCC Room | E4: Guest Room Occ | F4: Total Kwh Generated | G4: Diseal consumed by Gen (Ltrs) | H4: Diseal consumed by Veichel (Ltrs) | I4: Total diseal consumed (Ltrs) | J4: Balance stock of Diseal (Ltrs) | K4: Water consumed | L4: Gas consumed (KG) | M4: 3 | N4: 2 | O4: 1 | Q4: Electricity | R4: Cost per Room Total OOC Usd | S4: Cost per Room Guest OOC Usd | T4: Water | U4: Gas
A5: =SUM([1]Gen!A11) -> 43739 | B5: 0 | C5: =SUM([1]Gen!B11) -> 0.623 | D5: =SUM(77*C5) -> 47.971 | F5: =[1]Gen!T11 -> 5669 | G5: =[1]Gen!S11 -> 2179.48 | H5: =[1]Gen!#REF! -> #REF! | I5: =SUM(G5:H5) -> #REF! | J5: =[1]Gen!AT11 -> 47806.65 | K5: ='[1]Water-Meter'!E10 -> 114 | L5: =#REF! -> #REF! | M5: =#REF! -> #REF! | N5: =#REF! -> #REF! | O5: =#REF! -> #REF! | P5: =J5/52000 -> 0.91935865 | Q5: =I5*Q2 -> #REF! | R5: =SUM(Q5/D5)/X5 -> #REF! | S5: =SUM(Q5/E5)/X5 -> #REF! | T5: =(K5*102)/X5 -> 7.3409091 | U5: =SUM(L5*1963)/X5 -> #REF! | V5: =SUM(Q5+T5+U5) -> #REF! | W5: =SUM(V5/E5)/T2 -> #REF! | X5: =SUM(T2) -> 1584 | Y5: 106 | Z5: =SUM(Y5-S5) -> #REF! | AA5: 106
A6: =SUM([1]Gen!A12) -> 43740 | B6: 0 | C6: =SUM([1]Gen!B12) -> 0.779 | D6: =SUM(77*C6) -> 59.983 | F6: =[1]Gen!T12 -> 6159 | G6: =[1]Gen!S12 -> 2472.85 | H6: =[1]Gen!#REF! -> #REF! | I6: =SUM(G6:H6) -> #REF! | J6: =[1]Gen!AT12 -> 45423.89 | K6: ='[1]Water-Meter'!E11 -> 126 | L6: =#REF! -> #REF! | M6: =#REF! -> #REF! | N6: =#REF! -> #REF! | O6: =#REF! -> #REF! | P6: =J6/52000 -> 0.87353635 | Q6: =I6*Q2 -> #REF! | R6: =SUM(Q6/D6)/X6 -> #REF! | S6: =SUM(Q6/E6)/X6 -> #REF! | T6: =(K6*102)/X6 -> 8.1136364 | U6: =SUM(L6*1963)/X6 -> #REF! | V6: =SUM(Q6+T6+U6) -> #REF! | W6: =SUM(V6/E6)/T2 -> #REF! | X6: =SUM(X5) -> 1584 | Y6: 106 | Z6: =SUM(Y6-S6) -> #REF!
A7: =SUM([1]Gen!A13) -> 43741 | B7: 0 | C7: =SUM([1]Gen!B13) -> 0.532 | D7: =SUM(77*C7) -> 40.964 | F7: =[1]Gen!T13 -> 6580 | G7: =[1]Gen!S13 -> 2554.39 | H7: =[1]Gen!#REF! -> #REF! | I7: =SUM(G7:H7) -> #REF! | J7: =[1]Gen!AT13 -> 42919.59 | K7: ='[1]Water-Meter'!E12 -> 116 | L7: =#REF! -> #REF! | M7: =#REF! -> #REF! | N7: =#REF! -> #REF! | O7: =#REF! -> #REF! | P7: =J7/52000 -> 0.82537673 | Q7: =I7*Q2 -> #REF! | R7: =SUM(Q7/D7)/X7 -> #REF! | S7: =SUM(Q7/E7)/X7 -> #REF! | T7: =(K7*102)/X7 -> 7.469697 | U7: =SUM(L7*1963)/X7 -> #REF! | V7: =SUM(Q7+T7+U7) -> #REF! | W7: =SUM(V7/E7)/T2 -> #REF! | X7: =SUM(X6) -> 1584 | Y7: 106 | Z7: =SUM(Y7-S7) -> #REF!
A8: =SUM([1]Gen!A14) -> 43742 | B8: 0 | C8: =SUM([1]Gen!B14) -> 0.61 | D8: =SUM(77*C8) -> 46.97 | F8: =[1]Gen!T14 -> 6223 | G8: =[1]Gen!S14 -> 2441.42 | H8: =[1]Gen!AJ9 -> #REF! | I8: =SUM(G8:H8) -> #REF! | J8: =[1]Gen!AT14 -> 40258.94 | K8: ='[1]Water-Meter'!E13 -> 120 | L8: =#REF! -> #REF! | M8: =#REF! -> #REF! | N8: =#REF! -> #REF! | O8: =#REF! -> #REF! | P8: =J8/52000 -> 0.77421038 | Q8: =I8*Q2 -> #REF! | R8: =SUM(Q8/D8)/X8 -> #REF! | S8: =SUM(Q8/E8)/X8 -> #REF! | T8: =(K8*102)/X8 -> 7.7272727 | U8: =SUM(L8*1963)/X8 -> #REF! | V8: =SUM(Q8+T8+U8) -> #REF! | W8: =SUM(V8/E8)/T2 -> #REF! | X8: =SUM(X7) -> 1584 | Y8: 106 | Z8: =SUM(Y8-S8) -> #REF!
A9: =SUM([1]Gen!A15) -> 43743 | B9: 0 | C9: =SUM([1]Gen!B15) -> 0.688 | D9: =SUM(77*C9) -> 52.976 | F9: =[1]Gen!T15 -> 5984 | G9: =[1]Gen!S15 -> 2338.36 | H9: =[1]Gen!AJ10 -> 0 | I9: =SUM(G9:H9) -> 2338.36 | J9: =[1]Gen!AT15 -> 37525.21 | K9: ='[1]Water-Meter'!E14 -> 107 | L9: =#REF! -> #REF! | M9: =#REF! -> #REF! | N9: =#REF! -> #REF! | O9: =#REF! -> #REF! | P9: =J9/52000 -> 0.72163865 | Q9: =I9*Q2 -> 5167424.8 | R9: =SUM(Q9/D9)/X9 -> 61.58002 | S9: =SUM(Q9/E9)/X9 -> #DIV/0! | T9: =(K9*102)/X9 -> 6.8901515 | U9: =SUM(L9*1963)/X9 -> #REF! | V9: =SUM(Q9+T9+U9) -> #REF! | W9: =SUM(V9/E9)/T2 -> #REF! | X9: =SUM(X8) -> 1584 | Y9: 106 | Z9: =SUM(Y9-S9) -> #DIV/0!
A10: =SUM([1]Gen!A16) -> 43744 | B10: 0 | C10: =SUM([1]Gen!B16) -> 0.532 | D10: =SUM(77*C10) -> 40.964 | F10: =[1]Gen!T16 -> 6103 | G10: =[1]Gen!S16 -> 2478.9 | H10: =[1]Gen!#REF! -> #REF! | I10: =SUM(G10:H10) -> #REF! | J10: =[1]Gen!AT16 -> 35107.69 | K10: ='[1]Water-Meter'!E15 -> 123 | L10: =#REF! -> #REF! | M10: =#REF! -> #REF! | N10: =#REF! -> #REF! | O10: =#REF! -> #REF! | P10: =J10/52000 -> 0.67514788 | Q10: =I10*Q2 -> #REF! | R10: =SUM(Q10/D10)/X10 -> #REF! | S10: =SUM(Q10/E10)/X10 -> #REF! | T10: =(K10*102)/X10 -> 7.9204545 | U10: =SUM(L10*1963)/X10 -> #REF! | V10: =SUM(Q10+T10+U10) -> #REF! | W10: =SUM(V10/E10)/T2 -> #REF! | X10: =SUM(X9) -> 1584 | Y10: 106 | Z10: =SUM(Y10-S10) -> #REF!
A11: =SUM([1]Gen!A17) -> 43745 | B11: 0 | C11: =SUM([1]Gen!B17) -> 0.753 | D11: =SUM(77*C11) -> 57.981 | F11: =[1]Gen!T17 -> 5576 | G11: =[1]Gen!S17 -> 2276.44 | H11: =[1]Gen!AJ25 -> 80.56 | I11: =SUM(G11:H11) -> 2357 | J11: =[1]Gen!AT17 -> 47513.14 | K11: ='[1]Water-Meter'!E16 -> 112 | L11: =#REF! -> #REF! | M11: =#REF! -> #REF! | N11: =#REF! -> #REF! | O11: =#REF! -> #REF! | P11: =J11/52000 -> 0.91371423 | Q11: =I11*Q2 -> 5208616.5 | R11: =SUM(Q11/D11)/X11 -> 56.712854 | S11: =SUM(Q11/E11)/X11 -> #DIV/0! | T11: =(K11*102)/X11 -> 7.2121212 | U11: =SUM(L11*1963)/X11 -> #REF! | V11: =SUM(Q11+T11+U11) -> #REF! | W11: =SUM(V11/E11)/T2 -> #REF! | X11: =SUM(X10) -> 1584 | Y11: 106 | Z11: =SUM(Y11-S11) -> #DIV/0!
A12: =SUM([1]Gen!A18) -> 43746 | B12: 0 | C12: =SUM([1]Gen!B18) -> 0.156 | D12: =SUM(77*C12) -> 12.012 | F12: =[1]Gen!T18 -> 5532 | G12: =[1]Gen!S18 -> 2242.4 | H12: =[1]Gen!#REF! -> #REF! | I12: =SUM(G12:H12) -> #REF! | J12: =[1]Gen!AT18 -> 45161.89 | K12: ='[1]Water-Meter'!E17 -> 128 | L12: =#REF! -> #REF! | M12: =#REF! -> #REF! | N12: =#REF! -> #REF! | O12: =#REF! -> #REF! | P12: =J12/52000 -> 0.86849788 | Q12: =I12*Q2 -> #REF! | R12: =SUM(Q12/D12)/X12 -> #REF! | S12: =SUM(Q12/E12)/X12 -> #REF! | T12: =(K12*102)/X12 -> 8.2424242 | U12: =SUM(L12*1963)/X12 -> #REF! | V12: =SUM(Q12+T12+U12) -> #REF! | W12: =SUM(V12/E12)/T2 -> #REF! | X12: =SUM(X11) -> 1584 | Y12: 106 | Z12: =SUM(Y12-S12) -> #REF!
A13: =SUM([1]Gen!A19) -> 43747 | B13: 0 | C13: =SUM([1]Gen!B19) -> 0.442 | D13: =SUM(77*C13) -> 34.034 | F13: =[1]Gen!T19 -> 6233 | G13: =[1]Gen!S19 -> 2430.27 | H13: =[1]Gen!#REF! -> #REF! | I13: =SUM(G13:H13) -> #REF! | J13: =[1]Gen!AT19 -> 42825.48 | K13: ='[1]Water-Meter'!E18 -> 114 | L13: =#REF! -> #REF! | M13: =#REF! -> #REF! | N13: =#REF! -> #REF! | O13: =#REF! -> #REF! | P13: =J13/52000 -> 0.82356692 | Q13: =I13*Q2 -> #REF! | R13: =SUM(Q13/D13)/X13 -> #REF! | S13: =SUM(Q13/E13)/X13 -> #REF! | T13: =(K13*102)/X13 -> 7.3409091 | U13: =SUM(L13*1963)/X13 -> #REF! | V13: =SUM(Q13+T13+U13) -> #REF! | W13: =SUM(V13/E13)/T2 -> #REF! | X13: =SUM(X12) -> 1584 | Y13: 106 | Z13: =SUM(Y13-S13) -> #REF!
A14: =SUM([1]Gen!A20) -> 43748 | B14: 0 | C14: =SUM([1]Gen!B20) -> 0.325 | D14: =SUM(77*C14) -> 25.025 | F14: =[1]Gen!T20 -> 6063 | G14: =[1]Gen!S20 -> 2463.77 | H14: =[1]Gen!#REF! -> #REF! | I14: =SUM(G14:H14) -> #REF! | J14: =[1]Gen!AT20 -> 40110.38 | K14: ='[1]Water-Meter'!E19 -> 119 | L14: =#REF! -> #REF! | M14: =#REF! -> #REF! | N14: =#REF! -> #REF! | O14: =#REF! -> #REF! | P14: =J14/52000 -> 0.77135346 | Q14: =I14*Q2 -> #REF! | R14: =SUM(Q14/D14)/X14 -> #REF! | S14: =SUM(Q14/E14)/X14 -> #REF! | T14: =(K14*102)/X14 -> 7.6628788 | U14: =SUM(L14*1963)/X14 -> #REF! | V14: =SUM(Q14+T14+U14) -> #REF! | W14: =SUM(V14/E14)/T2 -> #REF! | X14: =SUM(X13) -> 1584 | Y14: 106 | Z14: =SUM(Y14-S14) -> #REF!
A15: =SUM([1]Gen!A21) -> 43749 | B15: 0 | C15: =SUM([1]Gen!B21) -> 0.455 | D15: =SUM(77*C15) -> 35.035 | F15: =[1]Gen!T21 -> 5967 | G15: =[1]Gen!S21 -> 2310.19 | H15: =[1]Gen!#REF! -> #REF! | I15: =SUM(G15:H15) -> #REF! | J15: =[1]Gen!AT21 -> 37540.57 | K15: ='[1]Water-Meter'!E20 -> 128 | L15: =#REF! -> #REF! | M15: =#REF! -> #REF! | N15: =#REF! -> #REF! | O15: =#REF! -> #REF! | P15: =J15/52000 -> 0.72193404 | Q15: =I15*Q2 -> #REF! | R15: =SUM(Q15/D15)/X15 -> #REF! | S15: =SUM(Q15/E15)/X15 -> #REF! | T15: =(K15*102)/X15 -> 8.2424242 | U15: =SUM(L15*1963)/X15 -> #REF! | V15: =SUM(Q15+T15+U15) -> #REF! | W15: =SUM(V15/E15)/T2 -> #REF! | X15: =SUM(X14) -> 1584 | Y15: 106 | Z15: =SUM(Y15-S15) -> #REF!
A16: =SUM([1]Gen!A22) -> 43750 | B16: 0 | C16: =SUM([1]Gen!B22) -> 0.416 | D16: =SUM(77*C16) -> 32.032 | F16: =[1]Gen!T22 -> 5863 | G16: =[1]Gen!S22 -> 2429.17 | H16: =[1]Gen!#REF! -> #REF! | I16: =SUM(G16:H16) -> #REF! | J16: =[1]Gen!AT22 -> 34967.29 | K16: ='[1]Water-Meter'!E21 -> 127 | L16: =#REF! -> #REF! | M16: =#REF! -> #REF! | N16: =#REF! -> #REF! | O16: =#REF! -> #REF! | P16: =J16/52000 -> 0.67244788 | Q16: =I16*Q2 -> #REF! | R16: =SUM(Q16/D16)/X16 -> #REF! | S16: =SUM(Q16/E16)/X16 -> #REF! | T16: =(K16*102)/X16 -> 8.1780303 | U16: =SUM(L16*1963)/X16 -> #REF! | V16: =SUM(Q16+T16+U16) -> #REF! | W16: =SUM(V16/E16)/T2 -> #REF! | X16: =SUM(X15) -> 1584 | Y16: 106 | Z16: =SUM(Y16-S16) -> #REF!
A17: =SUM([1]Gen!A23) -> 43751 | B17: 0 | C17: =SUM([1]Gen!B23) -> 0.39 | D17: =SUM(77*C17) -> 30.03 | F17: =[1]Gen!T23 -> 5720 | G17: =[1]Gen!S23 -> 2249.53 | H17: =[1]Gen!#REF! -> #REF! | I17: =SUM(G17:H17) -> #REF! | J17: =[1]Gen!AT23 -> 32228.76 | K17: ='[1]Water-Meter'!E22 -> 122 | L17: =#REF! -> #REF! | M17: =#REF! -> #REF! | N17: =#REF! -> #REF! | O17: =#REF! -> #REF! | P17: =J17/52000 -> 0.61978385 | Q17: =I17*Q2 -> #REF! | R17: =SUM(Q17/D17)/X17 -> #REF! | S17: =SUM(Q17/E17)/X17 -> #REF! | T17: =(K17*102)/X17 -> 7.8560606 | U17: =SUM(L17*1963)/X17 -> #REF! | V17: =SUM(Q17+T17+U17) -> #REF! | W17: =SUM(V17/E17)/T2 -> #REF! | X17: =SUM(X16) -> 1584 | Y17: 106 | Z17: =SUM(Y17-S17) -> #REF!
A18: =SUM([1]Gen!A24) -> 43752 | B18: 0 | C18: =SUM([1]Gen!B24) -> 0.636 | D18: =SUM(77*C18) -> 48.972 | F18: =[1]Gen!T24 -> 6195 | G18: =[1]Gen!S24 -> 2420.41 | H18: =[1]Gen!AJ27 -> 597.9 | I18: =SUM(G18:H18) -> 3018.31 | J18: =[1]Gen!AT24 -> 29915.45 | K18: 0 | L18: =#REF! -> #REF! | M18: =#REF! -> #REF! | N18: =#REF! -> #REF! | O18: =#REF! -> #REF! | P18: =J18/52000 -> 0.57529712 | Q18: =I18*Q2 -> 6670012.4 | R18: =SUM(Q18/D18)/X18 -> 85.985183 | S18: =SUM(Q18/E18)/X18 -> #DIV/0! | T18: =(K18*102)/X18 -> 0 | U18: =SUM(L18*1963)/X18 -> #REF! | V18: =SUM(Q18+T18+U18) -> #REF! | W18: =SUM(V18/E18)/T2 -> #REF! | X18: =SUM(X17) -> 1584 | Y18: 106 | Z18: =SUM(Y18-S18) -> #DIV/0!
A19: =SUM([1]Gen!A25) -> 43753 | B19: 0 | C19: =SUM([1]Gen!B25) -> 0.844 | D19: =SUM(77*C19) -> 64.988 | F19: =[1]Gen!T25 -> 6450 | G19: =[1]Gen!S25 -> 2670.31 | H19: =[1]Gen!AJ28 -> 227.73 | I19: =SUM(G19:H19) -> 2898.04 | J19: =[1]Gen!AT25 -> 42248.24 | K19: ='[1]Water-Meter'!E24 -> 104 | L19: =#REF! -> #REF! | M19: =#REF! -> #REF! | N19: =#REF! -> #REF! | O19: =#REF! -> #REF! | P19: =J19/52000 -> 0.81246615 | Q19: =I19*Q2 -> 6404233.7 | R19: =SUM(Q19/D19)/X19 -> 62.212667 | S19: =SUM(Q19/E19)/X19 -> #DIV/0! | T19: =(K19*102)/X19 -> 6.6969697 | U19: =SUM(L19*1963)/X19 -> #REF! | V19: =SUM(Q19+T19+U19) -> #REF! | W19: =SUM(V19/E19)/T2 -> #REF! | X19: =SUM(X18) -> 1584 | Y19: 106 | Z19: =SUM(Y19-S19) -> #DIV/0!
A20: =SUM([1]Gen!A26) -> 43754 | B20: 0 | C20: =SUM([1]Gen!B26) -> 0.818 | D20: =SUM(77*C20) -> 62.986 | F20: =[1]Gen!T26 -> 6915 | G20: =[1]Gen!S26 -> 2741.7 | H20: =[1]Gen!AJ29 -> 88.29 | I20: =SUM(G20:H20) -> 2829.99 | J20: =[1]Gen!AT26 -> 39497.37 | K20: ='[1]Water-Meter'!E25 -> 100 | L20: =#REF! -> #REF! | M20: =#REF! -> #REF! | N20: =#REF! -> #REF! | O20: =#REF! -> #REF! | P20: =J20/52000 -> 0.75956481 | Q20: =I20*Q2 -> 6253853.4 | R20: =SUM(Q20/D20)/X20 -> 62.682815 | S20: =SUM(Q20/E20)/X20 -> #DIV/0! | T20: =(K20*102)/X20 -> 6.4393939 | U20: =SUM(L20*1963)/X20 -> #REF! | V20: =SUM(Q20+T20+U20) -> #REF! | W20: =SUM(V20/E20)/T2 -> #REF! | X20: =SUM(X19) -> 1584 | Y20: 106 | Z20: =SUM(Y20-S20) -> #DIV/0!
A21: =SUM([1]Gen!A27) -> 43755 | B21: 0 | C21: =SUM([1]Gen!B27) -> 0.208 | D21: =SUM(77*C21) -> 16.016 | F21: =[1]Gen!T27 -> 5962 | G21: =[1]Gen!S27 -> 2321.11 | H21: =[1]Gen!AJ30 -> 783.92 | I21: =SUM(G21:H21) -> 3105.03 | J21: =[1]Gen!AT27 -> 36688.35 | K21: ='[1]Water-Meter'!E26 -> 116 | L21: =#REF! -> #REF! | M21: =#REF! -> #REF! | N21: =#REF! -> #REF! | O21: =#REF! -> #REF! | P21: =J21/52000 -> 0.70554519 | Q21: =I21*Q2 -> 6861650.5 | R21: =SUM(Q21/D21)/X21 -> 270.47016 | S21: =SUM(Q21/E21)/X21 -> #DIV/0! | T21: =(K21*102)/X21 -> 7.469697 | U21: =SUM(L21*1963)/X21 -> #REF! | V21: =SUM(Q21+T21+U21) -> #REF! | W21: =SUM(V21/E21)/T2 -> #REF! | X21: =SUM(X20) -> 1584 | Y21: 106 | Z21: =SUM(Y21-S21) -> #DIV/0!
A22: =SUM([1]Gen!A28) -> 43756 | B22: 0 | C22: =SUM([1]Gen!B28) -> 0.221 | D22: =SUM(77*C22) -> 17.017 | F22: =[1]Gen!T28 -> 5257 | G22: =[1]Gen!S28 -> 2204.84 | H22: =[1]Gen!#REF! -> #REF! | I22: =SUM(G22:H22) -> #REF! | J22: =[1]Gen!AT28 -> 33769.34 | K22: ='[1]Water-Meter'!E27 -> 114 | L22: =#REF! -> #REF! | M22: =#REF! -> #REF! | N22: =#REF! -> #REF! | O22: =#REF! -> #REF! | P22: =J22/52000 -> 0.64941038 | Q22: =I22*Q2 -> #REF! | R22: =SUM(Q22/D22)/X22 -> #REF! | S22: =SUM(Q22/E22)/X22 -> #REF! | T22: =(K22*102)/X22 -> 7.3409091 | U22: =SUM(L22*1963)/X22 -> #REF! | V22: =SUM(Q22+T22+U22) -> #REF! | W22: =SUM(V22/E22)/T2 -> #REF! | X22: =SUM(X21) -> 1584 | Y22: 106 | Z22: =SUM(Y22-S22) -> #REF!
A23: =SUM([1]Gen!A29) -> 43757 | B23: 0 | C23: =SUM([1]Gen!B29) -> 0.117 | D23: =SUM(77*C23) -> 9.009 | F23: =[1]Gen!T29 -> 4691 | G23: =[1]Gen!S29 -> 1845.18 | H23: =[1]Gen!#REF! -> #REF! | I23: =SUM(G23:H23) -> #REF! | J23: =[1]Gen!AT29 -> 31336.77 | K23: ='[1]Water-Meter'!E28 -> 113 | L23: =#REF! -> #REF! | M23: =#REF! -> #REF! | N23: =#REF! -> #REF! | O23: =#REF! -> #REF! | P23: =J23/52000 -> 0.60263019 | Q23: =I23*Q2 -> #REF! | R23: =SUM(Q23/D23)/X23 -> #REF! | S23: =SUM(Q23/E23)/X23 -> #REF! | T23: =(K23*102)/X23 -> 7.2765152 | U23: =SUM(L23*1963)/X23 -> #REF! | V23: =SUM(Q23+T23+U23) -> #REF! | W23: =SUM(V23/E23)/T2 -> #REF! | X23: =SUM(X22) -> 1584 | Y23: 106 | Z23: =SUM(Y23-S23) -> #REF!
A24: =SUM([1]Gen!A30) -> 43758 | B24: 0 | C24: =SUM([1]Gen!B30) -> 0.571 | D24: =SUM(77*C24) -> 43.967 | F24: =[1]Gen!T30 -> 5712 | G24: =[1]Gen!S30 -> 2197.01 | H24: =[1]Gen!#REF! -> #REF! | I24: =SUM(G24:H24) -> #REF! | J24: =[1]Gen!AT30 -> 29403.3 | K24: ='[1]Water-Meter'!E29 -> 99 | L24: =#REF! -> #REF! | M24: =#REF! -> #REF! | N24: =#REF! -> #REF! | O24: =#REF! -> #REF! | P24: =J24/52000 -> 0.56544808 | Q24: =I24*Q2 -> #REF! | R24: =SUM(Q24/D24)/X24 -> #REF! | S24: =SUM(Q24/E24)/X24 -> #REF! | T24: =(K24*102)/X24 -> 6.375 | U24: =SUM(L24*1963)/X24 -> #REF! | V24: =SUM(Q24+T24+U24) -> #REF! | W24: =SUM(V24/E24)/T2 -> #REF! | X24: =SUM(X23) -> 1584 | Y24: 106 | Z24: =SUM(Y24-S24) -> #REF!
A25: =SUM([1]Gen!A31) -> 43759 | B25: 0 | C25: =SUM([1]Gen!B31) -> 0.558 | D25: =SUM(77*C25) -> 42.966 | F25: =[1]Gen!T31 -> 5941 | G25: =[1]Gen!S31 -> 2262.16 | H25: =[1]Gen!AJ31 -> 172.05 | I25: =SUM(G25:H25) -> 2434.21 | J25: =[1]Gen!AT31 -> 41422.37 | K25: ='[1]Water-Meter'!E30 -> 111 | L25: =#REF! -> #REF! | M25: =#REF! -> #REF! | N25: =#REF! -> #REF! | O25: =#REF! -> #REF! | P25: =J25/52000 -> 0.79658404 | Q25: =I25*Q2 -> 5379239 | R25: =SUM(Q25/D25)/X25 -> 79.038873 | S25: =SUM(Q25/E25)/X25 -> #DIV/0! | T25: =(K25*102)/X25 -> 7.1477273 | U25: =SUM(L25*1963)/X25 -> #REF! | V25: =SUM(Q25+T25+U25) -> #REF! | W25: =SUM(V25/E25)/T2 -> #REF! | X25: =SUM(X24) -> 1584 | Y25: 106 | Z25: =SUM(Y25-S25) -> #DIV/0!
A26: =SUM([1]Gen!A32) -> 43760 | B26: 0 | C26: =SUM([1]Gen!B32) -> 0.403 | D26: =SUM(77*C26) -> 31.031 | F26: =[1]Gen!T32 -> 5400 | G26: =[1]Gen!S32 -> 2286.86 | H26: =[1]Gen!AJ32 -> 18.63 | I26: =SUM(G26:H26) -> 2305.49 | J26: =[1]Gen!AT32 -> 38988.16 | K26: ='[1]Water-Meter'!E31 -> 130 | L26: =#REF! -> #REF! | M26: =#REF! -> #REF! | N26: =#REF! -> #REF! | O26: =#REF! -> #REF! | P26: =J26/52000 -> 0.74977231 | Q26: =I26*Q2 -> 5094787.1 | R26: =SUM(Q26/D26)/X26 -> 103.65138 | S26: =SUM(Q26/E26)/X26 -> #DIV/0! | T26: =(K26*102)/X26 -> 8.3712121 | U26: =SUM(L26*1963)/X26 -> #REF! | V26: =SUM(Q26+T26+U26) -> #REF! | W26: =SUM(V26/E26)/T2 -> #REF! | X26: =SUM(X25) -> 1584 | Y26: 106 | Z26: =SUM(Y26-S26) -> #DIV/0!
A27: =SUM([1]Gen!A33) -> 43761 | B27: 0 | C27: =SUM([1]Gen!B33) -> 0.24 | D27: =SUM(77*C27) -> 18.48 | F27: =[1]Gen!T33 -> 5371 | G27: =[1]Gen!S33 -> 2148.3 | H27: =[1]Gen!AJ33 -> 311.34 | I27: =SUM(G27:H27) -> 2459.64 | J27: =[1]Gen!AT33 -> 36682.67 | K27: ='[1]Water-Meter'!E32 -> 114 | L27: =#REF! -> #REF! | M27: =#REF! -> #REF! | N27: =#REF! -> #REF! | O27: =#REF! -> #REF! | P27: =J27/52000 -> 0.70543596 | Q27: =I27*Q2 -> 5435435.5 | R27: =SUM(Q27/D27)/X27 -> 185.68516 | S27: =SUM(Q27/E27)/X27 -> #DIV/0! | T27: =(K27*102)/X27 -> 7.3409091 | U27: =SUM(L27*1963)/X27 -> #REF! | V27: =SUM(Q27+T27+U27) -> #REF! | W27: =SUM(V27/E27)/T2 -> #REF! | X27: =SUM(X26) -> 1584 | Y27: 106 | Z27: =SUM(Y27-S27) -> #DIV/0!
A28: =SUM([1]Gen!A34) -> 43762 | B28: 0 | C28: =SUM([1]Gen!B34) -> 0.09 | D28: =SUM(77*C28) -> 6.93 | F28: =[1]Gen!T34 -> 5296 | G28: =[1]Gen!S34 -> 2213.27 | H28: =[1]Gen!AJ34 -> 380.7 | I28: =SUM(G28:H28) -> 2593.97 | J28: =[1]Gen!AT34 -> 44223.03 | K28: ='[1]Water-Meter'!E33 -> -215493 | L28: =#REF! -> #REF! | M28: =#REF! -> #REF! | N28: =#REF! -> #REF! | O28: =#REF! -> #REF! | P28: =J28/52000 -> 0.85044288 | Q28: =I28*Q2 -> 5732284.6 | R28: =SUM(Q28/D28)/X28 -> 522.20296 | S28: =SUM(Q28/E28)/X28 -> #DIV/0! | T28: =(K28*102)/X28 -> -13876.443 | U28: =SUM(L28*1963)/X28 -> #REF! | V28: =SUM(Q28+T28+U28) -> #REF! | W28: =SUM(V28/E28)/T2 -> #REF! | X28: =SUM(X27) -> 1584 | Y28: 106 | Z28: =SUM(Y28-S28) -> #DIV/0!
A29: =SUM([1]Gen!A35) -> 43763 | B29: 0 | C29: =SUM([1]Gen!B35) -> 0.286 | D29: =SUM(77*C29) -> 22.022 | F29: =[1]Gen!T35 -> 5221 | G29: =[1]Gen!S35 -> 2104.52 | H29: =[1]Gen!AJ35 -> 273.37 | I29: =SUM(G29:H29) -> 2377.89 | J29: =[1]Gen!AT35 -> 41629.06 | K29: ='[1]Water-Meter'!E34 -> 0 | L29: =#REF! -> #REF! | M29: =#REF! -> #REF! | N29: =#REF! -> #REF! | O29: =#REF! -> #REF! | P29: =J29/52000 -> 0.80055885 | Q29: =I29*Q2 -> 5254780.2 | R29: =SUM(Q29/D29)/X29 -> 150.6408 | S29: =SUM(Q29/E29)/X29 -> #DIV/0! | T29: =(K29*102)/X29 -> 0 | U29: =SUM(L29*1963)/X29 -> #REF! | V29: =SUM(Q29+T29+U29) -> #REF! | W29: =SUM(V29/E29)/T2 -> #REF! | X29: =SUM(X28) -> 1584 | Y29: 106 | Z29: =SUM(Y29-S29) -> #DIV/0!
A30: =SUM([1]Gen!A36) -> 43764 | B30: 0 | C30: =SUM([1]Gen!B36) -> 0.545 | D30: =SUM(77*C30) -> 41.965 | F30: =[1]Gen!T36 -> 5665 | G30: =[1]Gen!S36 -> 2470.24 | H30: =[1]Gen!AJ36 -> 396.56 | I30: =SUM(G30:H30) -> 2866.8 | J30: =[1]Gen!AT36 -> 39251.17 | K30: ='[1]Water-Meter'!E35 -> 0 | L30: =#REF! -> #REF! | M30: =#REF! -> #REF! | N30: =#REF! -> #REF! | O30: =#REF! -> #REF! | P30: =J30/52000 -> 0.75483019 | Q30: =I30*Q2 -> 6335198 | R30: =SUM(Q30/D30)/X30 -> 95.305461 | S30: =SUM(Q30/E30)/X30 -> #DIV/0! | T30: =(K30*102)/X30 -> 0 | U30: =SUM(L30*1963)/X30 -> #REF! | V30: =SUM(Q30+T30+U30) -> #REF! | W30: =SUM(V30/E30)/T2 -> #REF! | X30: =SUM(X29) -> 1584 | Y30: 106 | Z30: =SUM(Y30-S30) -> #DIV/0!
A31: =SUM([1]Gen!A37) -> 43765 | B31: 0 | C31: =SUM([1]Gen!B37) -> 0.675 | D31: =SUM(77*C31) -> 51.975 | F31: =[1]Gen!T37 -> 6109 | G31: =[1]Gen!S37 -> 2323.74 | H31: =[1]Gen!AJ37 -> 280.63 | I31: =SUM(G31:H31) -> 2604.37 | J31: =[1]Gen!AT37 -> 36384.37 | K31: ='[1]Water-Meter'!E36 -> 0 | L31: =#REF! -> #REF! | M31: =#REF! -> #REF! | N31: =#REF! -> #REF! | O31: =#REF! -> #REF! | P31: =J31/52000 -> 0.69969942 | Q31: =I31*Q2 -> 5755267 | R31: =SUM(Q31/D31)/X31 -> 69.906218 | S31: =SUM(Q31/E31)/X31 -> #DIV/0! | T31: =(K31*102)/X31 -> 0 | U31: =SUM(L31*1963)/X31 -> #REF! | V31: =SUM(Q31+T31+U31) -> #REF! | W31: =SUM(V31/E31)/T2 -> #REF! | X31: =SUM(X30) -> 1584 | Y31: 106 | Z31: =SUM(Y31-S31) -> #DIV/0!
A32: =SUM([1]Gen!A38) -> 43766 | B32: 0 | C32: =SUM([1]Gen!B38) -> 0.273 | D32: =SUM(77*C32) -> 21.021 | F32: =[1]Gen!T38 -> 0 | G32: =[1]Gen!S38 -> 0 | H32: =[1]Gen!AJ38 -> 0 | I32: =SUM(G32:H32) -> 0 | J32: =[1]Gen!AT38 -> 33780 | K32: ='[1]Water-Meter'!E37 -> 0 | L32: =#REF! -> #REF! | M32: =#REF! -> #REF! | N32: =#REF! -> #REF! | O32: =#REF! -> #REF! | P32: =J32/52000 -> 0.64961538 | Q32: =I32*Q2 -> 0 | R32: =SUM(Q32/D32)/X32 -> 0 | S32: =SUM(Q32/E32)/X32 -> #DIV/0! | T32: =(K32*102)/X32 -> 0 | U32: =SUM(L32*1963)/X32 -> #REF! | V32: =SUM(Q32+T32+U32) -> #REF! | W32: =SUM(V32/E32)/T2 -> #REF! | X32: =SUM(X31) -> 1584 | Y32: 106 | Z32: =SUM(Y32-S32) -> #DIV/0!
B33: 0 | C33: =SUM([1]Gen!B39) -> #REF! | D33: =SUM(77*C33) -> #REF! | F33: =[1]Gen!T39 -> 0 | G33: =[1]Gen!S39 -> 0 | H33: =[1]Gen!AJ39 -> 0 | I33: =SUM(G33:H33) -> 0 | J33: =[1]Gen!AT39 -> 33780 | K33: ='[1]Water-Meter'!E38 -> -212333 | L33: =#REF! -> #REF! | M33: =#REF! -> #REF! | N33: =#REF! -> #REF! | O33: =#REF! -> #REF! | P33: =J33/52000 -> 0.64961538 | Q33: =I33*Q2 -> 0 | R33: =SUM(Q33/D33)/X33 -> #REF! | S33: =SUM(Q33/E33)/X33 -> #DIV/0! | T33: =(K33*102)/X33 -> -13672.958 | U33: =SUM(L33*1963)/X33 -> #REF! | V33: =SUM(Q33+T33+U33) -> #REF! | W33: =SUM(V33/E33)/T2 -> #REF! | X33: =SUM(X32) -> 1584 | Y33: 106 | Z33: =SUM(Y33-S33) -> #DIV/0!
B34: 0 | C34: =SUM([1]Gen!B40) -> #REF! | D34: =SUM(77*C34) -> #REF! | F34: =[1]Gen!T40 -> 0 | G34: =[1]Gen!S40 -> 0 | H34: =[1]Gen!AJ40 -> 0 | I34: =SUM(G34:H34) -> 0 | J34: =[1]Gen!AT40 -> 33780 | K34: ='[1]Water-Meter'!E39 -> #REF! | L34: =#REF! -> #REF! | M34: =#REF! -> #REF! | N34: =#REF! -> #REF! | O34: =#REF! -> #REF! | P34: =J34/52000 -> 0.64961538 | Q34: =I34*Q2 -> 0 | R34: =SUM(Q34/D34)/X34 -> #REF! | S34: =SUM(Q34/E34)/X34 -> #DIV/0! | T34: =(K34*102)/X34 -> #REF! | U34: =SUM(L34*1963)/X34 -> #REF! | V34: =SUM(Q34+T34+U34) -> #REF! | W34: =SUM(V34/E34)/T2 -> #REF! | X34: =SUM(X33) -> 1584 | Y34: 106 | Z34: =SUM(Y34-S34) -> #DIV/0!
B35: 0 | C35: =SUM([1]Gen!B41) -> #REF! | D35: =SUM(77*C35) -> #REF! | F35: =[1]Gen!T41 -> 0 | G35: =[1]Gen!S41 -> 0 | H35: =[1]Gen!AJ41 -> 0 | I35: =SUM(G35:H35) -> 0 | J35: =[1]Gen!AT41 -> 33780 | K35: ='[1]Water-Meter'!E40 -> #REF! | L35: =#REF! -> #REF! | M35: =#REF! -> #REF! | N35: =#REF! -> #REF! | O35: =#REF! -> #REF! | P35: =J35/52000 -> 0.64961538 | Q35: =I35*Q2 -> 0 | R35: =SUM(Q35/D35)/X35 -> #REF! | S35: =SUM(Q35/E35)/X35 -> #DIV/0! | T35: =(K35*102)/X35 -> #REF! | U35: =SUM(L35*1963)/X35 -> #REF! | V35: =SUM(Q35+T35+U35) -> #REF! | W35: =SUM(V35/E35)/T2 -> #REF! | X35: =SUM(X34) -> 1584 | Y35: 106 | Z35: =SUM(Y35-S35) -> #DIV/0!
K36: ='[1]Water-Meter'!E41 -> #REF! | Q36: =I36*2057.79 -> 0 | V36: =SUM(Q36+T36+U36) -> 0
S37: =SUM(S5:S16)/[1]Gen!A47 -> #REF!
B38: =SUM(B5:B37)/[1]Gen!A47 -> #REF! | M38: =0.5*2057.79 -> 1028.895
B39: =SUM(B38*[1]Gen!A47) -> #REF! | C39: =SUM(B39/250) -> #REF! | M39: =M38/1500 -> 0.68593 | O39: =(24*2.2)*2 -> 105.6 | P39: =O39*1029 -> 108662.4 | R39: Over budget | S39: =SUM(S37-Y35) -> #REF!
P40: =P39/K5 -> 953.17895

Sheet VODACOM AND AIRTEL
A1: VODACOM AND AIRTEL KWH METER READING
B2: VODACOM TOWER | E2: AIRTEL TOWER
A3: DATE | B3: OPEN METER READING | C3: CLOSE METER READING | D3: UNIT CONSUMED | E3: OPEN METER READING | F3: CLOSE METER READING | G3: UNIT CONSUMED
A4: 42095 | B4: 0 | C4: 193 | D4: =C4-B4 -> 193 | E4: 0 | F4: 0 | G4: =F4-E4 -> 0
A5: 42125 | B5: =C4 -> 193 | C5: 1158 | D5: =C5-B5 -> 965 | E5: 145572 | F5: 145572 | G5: =F5-E5 -> 0
A6: 42156 | B6: =C5 -> 1158 | C6: 2084 | D6: =C6-B6 -> 926 | E6: =F5 -> 145572 | F6: 147984 | G6: =F6-E6 -> 2412
A7: 42186 | B7: =C6 -> 2084 | C7: 3073 | D7: =C7-B7 -> 989 | E7: =F6 -> 147984 | F7: 150507 | G7: =F7-E7 -> 2523
A8: 42217 | B8: =C7 -> 3073 | C8: 4063 | D8: =C8-B8 -> 990 | E8: =F7 -> 150507 | F8: 152986 | G8: =F8-E8 -> 2479
A9: 42248 | B9: =C8 -> 4063 | C9: 5058 | D9: =C9-B9 -> 995 | E9: =F8 -> 152986 | F9: 155468 | G9: =F9-E9 -> 2482
A10: 42278 | B10: =C9 -> 5058 | C10: 6049 | D10: =C10-B10 -> 991 | E10: =F9 -> 155468 | F10: 157962 | G10: =F10-E10 -> 2494
A11: 42309 | B11: =C10 -> 6049 | C11: 7028 | D11: =C11-B11 -> 979 | E11: =F10 -> 157962 | F11: 160323 | G11: =F11-E11 -> 2361
A12: 42339 | B12: =C11 -> 7028 | C12: 7985 | D12: =C12-B12 -> 957 | E12: =F11 -> 160323 | F12: 162813 | G12: =F12-E12 -> 2490
A13: 42370 | B13: =C12 -> 7985 | C13: 8952 | D13: =C13-B13 -> 967 | E13: =F12 -> 162813 | F13: 165317 | G13: =F13-E13 -> 2504
A14: 42401 | B14: =C13 -> 8952 | C14: 9898 | D14: =C14-B14 -> 946 | E14: =F13 -> 165317 | F14: 167679 | G14: =F14-E14 -> 2362
A15: 42430 | B15: =C14 -> 9898 | C15: 10637 | D15: =C15-B15 -> 739 | E15: =F14 -> 167679 | F15: 170134 | G15: =F15-E15 -> 2455
A16: 42461 | B16: =C15 -> 10637 | C16: 11352 | D16: =C16-B16 -> 715 | E16: =F15 -> 170134 | F16: 172562 | G16: =F16-E16 -> 2428
A17: 42491 | B17: =C16 -> 11352 | C17: 12426 | D17: =C17-B17 -> 1074 | E17: =F16 -> 172562 | F17: 175041 | G17: =F17-E17 -> 2479
... A45: 43344 | B45: =C44 -> 61427 | C45: 63464 | D45: =C45-B45 -> 2037 | E45: =F44 -> 233548 | F45: 235653 | G45: =F45-E45 -> 2105
A46: 43374 | B46: =C45 -> 63464 | D46: =C46-B46 -> -63464 | E46: =F45 -> 235653 | G46: =F46-E46 -> -235653
A47: 43739 | B47: =C46 -> 0 | D47: =C47-B47 -> 0 | E47: =F46 -> 0 | G47: =F47-E47 -> 0
A48: 43740 | B48: =C47 -> 0 | D48: =C48-B48 -> 0 | E48: =F47 -> 0 | G48: =F48-E48 -> 0
A49: 43741 | B49: =C48 -> 0 | D49: =C49-B49 -> 0 | E49: =F48 -> 0 | G49: =F49-E49 -> 0
A50: 43742 | B50: =C49 -> 0 | D50: =C50-B50 -> 0 | E50: =F49 -> 0 | G50: =F50-E50 -> 0
A51: 43743 | B51: =C50 -> 0 | D51: =C51-B51 -> 0 | E51: =F50 -> 0 | G51: =F51-E51 -> 0
A52: 43744 | B52: =C51 -> 0 | D52: =C52-B52 -> 0 | E52: =F51 -> 0 | G52: =F52-E52 -> 0
A53: 43745 | B53: =C52 -> 0 | D53: =C53-B53 -> 0 | E53: =F52 -> 0 | G53: =F53-E53 -> 0
A54: 43746 | B54: =C53 -> 0 | D54: =C54-B54 -> 0 | E54: =F53 -> 0 | G54: =F54-E54 -> 0
A55: 43747 | B55: =C54 -> 0 | D55: =C55-B55 -> 0 | E55: =F54 -> 0 | G55: =F55-E55 -> 0
A56: 43748 | B56: =C55 -> 0 | D56: =C56-B56 -> 0 | E56: =F55 -> 0 | G56: =F56-E56 -> 0
A57: 43749 | B57: =C56 -> 0 | D57: =C57-B57 -> 0 | E57: =F56 -> 0 | G57: =F57-E57 -> 0
... A77: 43769 | B77: =C76 -> 0 | D77: =C77-B77 -> 0 | E77: =F76 -> 0 | G77: =F77-E77 -> 0

Sheet FUEL METER READING
A1: FUEL METER 1 READNG | H1: FUEL METER 2 READING
A2: DATE | B2: OPEN METER READING | C2: CLOSE METER READING | D2: Diesel consumed | E2: HLP-GENSETS | F2: DIFFERENCE | G2: OPEN METER | H2: CLOSE METER | I2: DIESEL CONSUMED | J2: HLP-VEHICLES | K2: DIFFERENCE | L2: TOTAL DIESEL CONS.
A3: 42430 | B3: 5000778 | C3: 5057715 | D3: =C3-B3 -> 56937 | G3: =H3 -> 0 | I3: =H3-G3 -> 0 | K3: =I3-J3 -> 0
A4: 42461 | B4: =C3 -> 5057715 | C4: 5111496 | D4: =C4-B4 -> 53781 | G4: =H3 -> 0 | I4: =H4-G4 -> 0 | K4: =I4-J4 -> 0
A5: 42491 | B5: =C4 -> 5111496 | C5: 5169409 | D5: =C5-B5 -> 57913 | G5: =H4 -> 0 | I5: =H5-G5 -> 0 | K5: =I5-J5 -> 0
A6: 42522 | B6: =C5 -> 5169409 | C6: 5232162 | D6: =C6-B6 -> 62753 | G6: =H5 -> 0 | I6: =H6-G6 -> 0 | K6: =I6-J6 -> 0
A7: 42552 | B7: =C6 -> 5232162 | C7: 5310037 | D7: =C7-B7 -> 77875 | G7: =H6 -> 0 | I7: =H7-G7 -> 0 | K7: =I7-J7 -> 0
A8: 42583 | B8: =C7 -> 5310037 | C8: 5382821 | D8: =C8-B8 -> 72784 | E8: =[6]Gen!AR45 -> 72766 | F8: =D8-E8 -> 18 | G8: =H7 -> 0 | I8: =H8-G8 -> 0 | K8: =I8-J8 -> 0
A9: 42614 | B9: =C8 -> 5382821 | C9: 5446740 | D9: =C9-B9 -> 63919 | E9: =[7]Gen!AR45 -> 64036.5 | F9: =D9-E9 -> -117.5 | G9: =H8 -> 0 | I9: =H9-G9 -> 0 | K9: =I9-J9 -> 0
A10: 42644 | B10: =C9 -> 5446740 | C10: 5521440 | D10: =C10-B10 -> 74700 | E10: 76057.09 | F10: =D10-E10 -> -1357.09 | G10: =H9 -> 0 | I10: =H10-G10 -> 0 | K10: =I10-J10 -> 0
A11: 42675 | B11: =C10 -> 5521440 | C11: 5594926 | D11: =C11-B11 -> 73486 | E11: 73462.49 | F11: =D11-E11 -> 23.51 | G11: =H10 -> 0 | I11: =H11-G11 -> 0 | K11: =I11-J11 -> 0
A12: 42705 | B12: =C11 -> 5594926 | C12: 5670348 | D12: =C12-B12 -> 75422 | E12: 75421.2 | F12: =D12-E12 -> 0.8 | G12: =H11 -> 0 | I12: =H12-G12 -> 0 | K12: =I12-J12 -> 0
A13: 42736 | B13: =C12 -> 5670348 | C13: 5735627 | D13: =C13-B13 -> 65279 | E13: 65276.07 | F13: =D13-E13 -> 2.93 | G13: =H12 -> 0 | I13: =H13-G13 -> 0 | K13: =I13-J13 -> 0
A14: 42767 | B14: =C13 -> 5735627 | C14: 5797781 | D14: =C14-B14 -> 62154 | E14: 62154.9 | F14: =D14-E14 -> -0.9 | G14: =H13 -> 0 | I14: =H14-G14 -> 0 | K14: =I14-J14 -> 0
A15: 42795 | B15: =C14 -> 5797781 | C15: 5864602 | D15: =C15-B15 -> 66821 | E15: 66820.89 | F15: =D15-E15 -> 0.11 | G15: =H14 -> 0 | I15: =H15-G15 -> 0 | K15: =I15-J15 -> 0
A16: 42826 | B16: =C15 -> 5864602 | C16: 5927895 | D16: =C16-B16 -> 63293 | E16: 63292.38 | F16: =D16-E16 -> 0.62 | G16: =H15 -> 0 | I16: =H16-G16 -> 0 | K16: =I16-J16 -> 0
A17: 42856 | B17: =C16 -> 5927895 | C17: 5995212 | D17: =C17-B17 -> 67317 | E17: 67313.47 | F17: =D17-E17 -> 3.53 | G17: =H16 -> 0 | I17: =H17-G17 -> 0 | K17: =I17-J17 -> 0
A18: 42887 | B18: =C17 -> 5995212 | C18: 6065754 | D18: =C18-B18 -> 70542 | E18: 70542.6 | F18: =D18-E18 -> -0.6 | G18: =H17 -> 0 | I18: =H18-G18 -> 0 | K18: =I18-J18 -> 0
