Workbook

Sheet Total
A1: Site Name | B1: Day | C1: Month | D1: Year | E1: Total Electricity Kwh | F1: Electricity Tariff ($/Kwh) | G1: LPG (Kg) | H1: LPG $/Kg | I1: Water Utility Supply (m3) m3 | J1: Water Utility Supply (m3) $/m3 | K1: Room Nights | L1: Utilities day cost dh
A2: Serengeti | B2: 1 | C2: 12 | D2: 2018 | E2: =Gen!T11 -> 4555 | F2: =Gen!S11/Gen!T11 -> 0.40068716 | G2: =IF('Utility summery'!M6<0,"0",'Utility summery'!M6) -> 149.292 | H2: 2.38 | I2: =IF('Water-Meter'!E6<0,"0",'Water-Meter'!E6) -> 99 | J2: 0 | K2: ='Summery Report'!E5 -> 15 | L2: =E2*F2+G2*H2+#REF!*#REF!+I2*J2 -> #REF!
A3: Serengeti | B3: =B2+1 -> 2 | C3: 12 | D3: 2018 | E3: =Gen!T12 -> 4679 | F3: =Gen!S12/Gen!T12 -> 0.39221842 | G3: =IF('Utility summery'!M7<0,"0",'Utility summery'!M7) -> 78.892 | H3: 2.38 | I3: =IF('Water-Meter'!E7<0,"0",'Water-Meter'!E7) -> 100 | J3: 0 | K3: ='Summery Report'!E6 -> 13 | L3: =E3*F3+G3*H3+#REF!*#REF!+I3*J3 -> #REF!
A4: Serengeti | B4: =B3+1 -> 3 | C4: 12 | D4: 2018 | E4: =Gen!T13 -> 4437 | F4: =Gen!S13/Gen!T13 -> 0.62385621 | G4: =IF('Utility summery'!M8<0,"0",'Utility summery'!M8) -> 126.544 | H4: 2.38 | I4: =IF('Water-Meter'!E8<0,"0",'Water-Meter'!E8) -> 90 | J4: 0 | K4: ='Summery Report'!E7 -> 13 | L4: =E4*F4+G4*H4+#REF!*#REF!+I4*J4 -> #REF!
A5: Serengeti | B5: =B4+1 -> 4 | C5: 12 | D5: 2018 | E5: =Gen!T14 -> 4694 | F5: =Gen!S14/Gen!T14 -> 0.4069983 | G5: =IF('Utility summery'!M9<0,"0",'Utility summery'!M9) -> 101.332 | H5: 2.38 | I5: =IF('Water-Meter'!E9<0,"0",'Water-Meter'!E9) -> 87 | J5: 0 | K5: ='Summery Report'!E8 -> 15 | L5: =E5*F5+G5*H5+#REF!*#REF!+I5*J5 -> #REF!
A6: Serengeti | B6: =B5+1 -> 5 | C6: 12 | D6: 2018 | E6: =Gen!T15 -> 4359 | F6: =Gen!S15/Gen!T15 -> 0.40956183 | G6: =IF('Utility summery'!M10<0,"0",'Utility summery'!M10) -> 111.628 | H6: 2.38 | I6: =IF('Water-Meter'!E10<0,"0",'Water-Meter'!E10) -> 84 | J6: 0 | K6: ='Summery Report'!E9 -> 12 | L6: =E6*F6+G6*H6+#REF!*#REF!+I6*J6 -> #REF!
A7: Serengeti | B7: =B6+1 -> 6 | C7: 12 | D7: 2018 | E7: =Gen!T16 -> 4710 | F7: =Gen!S16/Gen!T16 -> 0.40421656 | G7: =IF('Utility summery'!M11<0,"0",'Utility summery'!M11) -> 105.644 | H7: 2.38 | I7: =IF('Water-Meter'!E11<0,"0",'Water-Meter'!E11) -> 108 | J7: 0 | K7: ='Summery Report'!E10 -> 15 | L7: =E7*F7+G7*H7+#REF!*#REF!+I7*J7 -> #REF!
A8: Serengeti | B8: =B7+1 -> 7 | C8: 12 | D8: 2018 | E8: =Gen!T17 -> 4875 | F8: =Gen!S17/Gen!T17 -> 0.41234667 | G8: =IF('Utility summery'!M12<0,"0",'Utility summery'!M12) -> 116.16 | H8: 2.38 | I8: =IF('Water-Meter'!E12<0,"0",'Water-Meter'!E12) -> 93 | J8: 0 | K8: ='Summery Report'!E11 -> 20 | L8: =E8*F8+G8*H8+#REF!*#REF!+I8*J8 -> #REF!
A9: Serengeti | B9: =B8+1 -> 8 | C9: 12 | D9: 2018 | E9: =Gen!T18 -> 4801 | F9: =Gen!S18/Gen!T18 -> 0.40063737 | G9: =IF('Utility summery'!M13<0,"0",'Utility summery'!M13) -> 149.556 | H9: 2.38 | I9: =IF('Water-Meter'!E13<0,"0",'Water-Meter'!E13) -> 103 | J9: 0 | K9: ='Summery Report'!E12 -> 23 | L9: =E9*F9+G9*H9+#REF!*#REF!+I9*J9 -> #REF!
A10: Serengeti | B10: =B9+1 -> 9 | C10: 12 | D10: 2018 | E10: =Gen!T19 -> 4909 | F10: =Gen!S19/Gen!T19 -> 0.41628845 | G10: =IF('Utility summery'!M14<0,"0",'Utility summery'!M14) -> 158.4 | H10: 2.38 | I10: =IF('Water-Meter'!E14<0,"0",'Water-Meter'!E14) -> 125 | J10: 0 | K10: ='Summery Report'!E13 -> 37 | L10: =E10*F10+G10*H10+#REF!*#REF!+I10*J10 -> #REF!
A11: Serengeti | B11: =B10+1 -> 10 | C11: 12 | D11: 2018 | E11: =Gen!T20 -> 5316 | F11: =Gen!S20/Gen!T20 -> 0.39564146 | G11: =IF('Utility summery'!M15<0,"0",'Utility summery'!M15) -> 197.208 | H11: 2.38 | I11: =IF('Water-Meter'!E15<0,"0",'Water-Meter'!E15) -> 114 | J11: 0 | K11: ='Summery Report'!E14 -> 44 | L11: =E11*F11+G11*H11+#REF!*#REF!+I11*J11 -> #REF!
A12: Serengeti | B12: =B11+1 -> 11 | C12: 12 | D12: 2018 | E12: =Gen!T21 -> 4922 | F12: =Gen!S21/Gen!T21 -> 0.41534539 | G12: =IF('Utility summery'!M16<0,"0",'Utility summery'!M16) -> 121.836 | H12: 2.38 | I12: =IF('Water-Meter'!E16<0,"0",'Water-Meter'!E16) -> 114 | J12: 0 | K12: ='Summery Report'!E15 -> 45 | L12: =E12*F12+G12*H12+#REF!*#REF!+I12*J12 -> #REF!
A13: Serengeti | B13: =B12+1 -> 12 | C13: 12 | D13: 2018 | E13: =Gen!T22 -> 4870 | F13: =Gen!S22/Gen!T22 -> 0.39368378 | G13: =IF('Utility summery'!M17<0,"0",'Utility summery'!M17) -> 127.292 | H13: 2.38 | I13: =IF('Water-Meter'!E17<0,"0",'Water-Meter'!E17) -> 105 | J13: 0 | K13: ='Summery Report'!E16 -> 21 | L13: =E13*F13+G13*H13+#REF!*#REF!+I13*J13 -> #REF!
A14: Serengeti | B14: =B13+1 -> 13 | C14: 12 | D14: 2018 | E14: =Gen!T23 -> 4660 | F14: =Gen!S23/Gen!T23 -> 0.40591845 | G14: =IF('Utility summery'!M18<0,"0",'Utility summery'!M18) -> 119.636 | H14: 2.38 | I14: =IF('Water-Meter'!E18<0,"0",'Water-Meter'!E18) -> 111 | J14: 0 | K14: ='Summery Report'!E17 -> 23 | L14: =E14*F14+G14*H14+#REF!*#REF!+I14*J14 -> #REF!
... A31: Serengeti | B31: =B30+1 -> 30 | C31: 12 | D31: 2018 | E31: =Gen!T40 -> 7378 | F31: =Gen!S40/Gen!T40 -> 0.42999593 | G31: =IF('Utility summery'!M35<0,"0",'Utility summery'!M35) -> 106.568 | H31: 2.38 | I31: =IF('Water-Meter'!E35<0,"0",'Water-Meter'!E35) -> 156 | J31: 0 | K31: ='Summery Report'!E34 -> 61 | L31: =E31*F31+G31*H31+#REF!*#REF!+I31*J31 -> #REF!
A32: Serengeti | B32: =B31+1 -> 31 | C32: 12 | D32: 2018 | E32: =Gen!T41 -> 7255 | F32: =Gen!S41/Gen!T41 -> 0.42160717 | G32: =IF('Utility summery'!M36<0,"0",'Utility summery'!M36) -> 122.54 | H32: 2.38 | I32: =IF('Water-Meter'!E36<0,"0",'Water-Meter'!E36) -> 120 | J32: 0 | K32: ='Summery Report'!E35 -> 66

Sheet Utility summery
A4: Date | B4: Room Occupied | C4: Electricity Units Generated KW | D4: Diseal | G4: Water | J4: Gas | N4: Cost of utilites
D5: Generator | E5: Transport | F5: Total | G5: RO | H5: STP | I5: Total Consumption | J5: 2 ton | K5: 1 Ton | L5: 1 Ton | M5: Total consumption | N5: Electricity /1.4$/liter | O5: Diseal for Transport | P5: Gas /2.38$/Kg | Q5: Total HLP Cost | R5: Electricity Cost/Room $ | S5: cost/Room $
A6: =Gen!A11 -> 43435 | B6: ='Summery Report'!D5 -> 15 | C6: ='Daily report Gen'!AA6 -> 430 | D6: =Gen!S11 -> 1825.13 | E6: =Gen!AJ11 -> 42.79 | F6: =Gen!AR11 -> 1867.92 | G6: ='Utility report'!AA5 -> 0 | H6: ='Utility report'!AF6 -> 65 | I6: ='Utility report'!AE6 -> 0.65656566 | J6: ='Lpg (2)'!B10 -> 85 | K6: ='Lpg (2)'!C12 -> 85 | L6: ='Lpg (2)'!D10 -> 75 | M6: ='Lpg (2)'!N10 -> 149.292 | O6: =E6 -> 42.79 | P6: ='Lpg (2)'!G10 -> 150000 | Q6: ='Summery Report'!Q5 -> 54169.68 | R6: =N6/B6 -> 0 | S6: =Q6/B6 -> 3611.312
A7: =Gen!A12 -> 43436 | B7: ='Summery Report'!D6 -> 13 | C7: ='Daily report Gen'!AA7 -> 410 | D7: =Gen!S12 -> 1835.19 | E7: =Gen!AJ12 -> 90.6 | F7: =SUM(D7+E7) -> 1925.79 | G7: ='Utility report'!AA6 -> #VALUE! | H7: ='Utility report'!AF7 -> 45 | I7: ='Utility report'!AE7 -> 0.45 | J7: ='Lpg (2)'!B11 -> 85 | K7: ='Lpg (2)'!C11 -> 85 | L7: ='Lpg (2)'!D11 -> 61 | M7: ='Lpg (2)'!N11 -> 78.892 | N7: =D7*1.4 -> 2569.266 | O7: =E7*1.4 -> 126.84 | P7: ='Lpg (2)'!G11 -> 122000 | Q7: ='Summery Report'!Q6 -> 55847.91 | R7: =N7/B7 -> 197.63585 | S7: =Q7/B7 -> 4295.9931
A8: =Gen!A13 -> 43437 | B8: ='Summery Report'!D7 -> 13 | C8: ='Daily report Gen'!AA8 -> 421 | D8: =Gen!S13 -> 2768.05 | E8: =Gen!AJ13 -> 108.37 | F8: =SUM(D8+E8) -> 2876.42 | G8: ='Utility report'!AA7 -> 956010 | H8: ='Utility report'!AF8 -> 47 | I8: ='Utility report'!AE8 -> 0.52222222 | J8: ='Lpg (2)'!B12 -> 85 | K8: ='Lpg (2)'!C12 -> 85 | L8: ='Lpg (2)'!D12 -> 52 | M8: ='Lpg (2)'!N12 -> 126.544 | N8: =D8*1.4 -> 3875.27 | O8: =E8*1.4 -> 151.718 | P8: ='Lpg (2)'!G12 -> 104000 | Q8: ='Summery Report'!Q7 -> 83416.18 | R8: =N8/B8 -> 298.09769 | S8: =Q8/B8 -> 6416.6292
A9: =Gen!A14 -> 43438 | B9: ='Summery Report'!D8 -> 15 | C9: ='Daily report Gen'!AA9 -> 417 | D9: =Gen!S14 -> 1910.45 | E9: =Gen!AJ14 -> 110.05 | F9: =SUM(D9+E9) -> 2020.5 | G9: ='Utility report'!AA8 -> 1040878.8 | H9: ='Utility report'!AF9 -> 73 | I9: ='Utility report'!AE9 -> 0.83908046 | J9: ='Lpg (2)'!B13 -> 85 | K9: ='Lpg (2)'!C13 -> 85 | L9: ='Lpg (2)'!D13 -> 45 | M9: ='Lpg (2)'!N13 -> 101.332 | N9: =D9*1.4 -> 2674.63 | O9: =E9*1.4 -> 154.07 | P9: ='Lpg (2)'!G13 -> 90000 | Q9: ='Summery Report'!Q8 -> 58594.5 | R9: =N9/B9 -> 178.30867 | S9: =Q9/B9 -> 3906.3
A10: =Gen!A15 -> 43439 | B10: ='Summery Report'!D9 -> 12 | C10: ='Daily report Gen'!AA10 -> 369 | D10: =Gen!S15 -> 1785.28 | E10: =Gen!AJ15 -> 0 | F10: =SUM(D10+E10) -> 1785.28 | G10: ='Utility report'!AA9 -> 1042314 | H10: ='Utility report'!AF10 -> 53 | I10: ='Utility report'!AE10 -> 0.63095238 | J10: ='Lpg (2)'!B14 -> 85 | K10: ='Lpg (2)'!C14 -> 85 | L10: ='Lpg (2)'!D14 -> 40 | M10: ='Lpg (2)'!N14 -> 111.628 | N10: =D10*1.4 -> 2499.392 | O10: =E10*1.4 -> 0 | P10: ='Lpg (2)'!G14 -> 80000 | Q10: ='Summery Report'!Q9 -> 51773.12 | R10: =N10/B10 -> 208.28267 | S10: =Q10/B10 -> 4314.4267
A11: =Gen!A16 -> 43440 | B11: ='Summery Report'!D10 -> 15 | C11: ='Daily report Gen'!AA11 -> 416 | D11: =Gen!S16 -> 1903.86 | E11: =Gen!AJ16 -> 247.65 | F11: =SUM(D11+E11) -> 2151.51 | G11: ='Utility report'!AA10 -> 1087819.2 | H11: ='Utility report'!AF11 -> 57 | I11: ='Utility report'!AE11 -> 0.52777778 | J11: ='Lpg (2)'!B15 -> 85 | K11: ='Lpg (2)'!C15 -> 85 | L11: ='Lpg (2)'!D15 -> 36 | M11: ='Lpg (2)'!N15 -> 105.644 | N11: =D11*1.4 -> 2665.404 | O11: =E11*1.4 -> 346.71 | P11: ='Lpg (2)'!G15 -> 72000 | Q11: ='Summery Report'!Q10 -> 62393.79 | R11: =N11/B11 -> 177.6936 | S11: =Q11/B11 -> 4159.586
A12: =Gen!A17 -> 43441 | B12: ='Summery Report'!D11 -> 20 | C12: ='Daily report Gen'!AA12 -> 389 | D12: =Gen!S17 -> 2010.19 | E12: =Gen!AJ17 -> 224.17 | F12: =SUM(D12+E12) -> 2234.36 | G12: ='Utility report'!AA11 -> 1089379.2 | H12: ='Utility report'!AF12 -> 53 | I12: ='Utility report'!AE12 -> 0.56989247 | J12: ='Lpg (2)'!B16 -> 85 | K12: ='Lpg (2)'!C16 -> 85 | L12: ='Lpg (2)'!D16 -> 30 | M12: ='Lpg (2)'!N16 -> 116.16 | N12: =D12*1.4 -> 2814.266 | O12: =E12*1.4 -> 313.838 | P12: ='Lpg (2)'!G16 -> 60000 | Q12: ='Summery Report'!Q11 -> 64796.44 | R12: =N12/B12 -> 140.7133 | S12: =Q12/B12 -> 3239.822
A13: =Gen!A18 -> 43442 | B13: ='Summery Report'!D12 -> 23 | C13: ='Daily report Gen'!AA13 -> 410 | D13: =Gen!S18 -> 1923.46 | E13: =Gen!AJ18 -> 114 | F13: =SUM(D13+E13) -> 2037.46 | G13: ='Utility report'!AA12 -> 136258.2 | H13: ='Utility report'!AF13 -> 53 | I13: ='Utility report'!AE13 -> 0.51456311 | J13: ='Lpg (2)'!B17 -> 85 | K13: ='Lpg (2)'!C17 -> 85 | L13: ='Lpg (2)'!D17 -> 23 | M13: ='Lpg (2)'!N17 -> 149.556 | N13: =D13*1.4 -> 2692.844 | O13: =E13*1.4 -> 159.6 | P13: ='Lpg (2)'!G17 -> 46000 | Q13: ='Summery Report'!Q12 -> 59086.34 | R13: =N13/B13 -> 117.08017 | S13: =Q13/B13 -> 2568.9713
A14: =Gen!A19 -> 43443 | B14: ='Summery Report'!D13 -> 37 | C14: ='Daily report Gen'!AA14 -> 426 | D14: =Gen!S19 -> 2043.56 | E14: =Gen!AJ19 -> 534.56 | F14: =SUM(D14+E14) -> 2578.12 | G14: ='Utility report'!AA13 -> 1138540 | H14: ='Utility report'!AF14 -> 59 | I14: ='Utility report'!AE14 -> 0.472 | J14: ='Lpg (2)'!B18 -> 85 | K14: ='Lpg (2)'!C18 -> 85 | L14: ='Lpg (2)'!D18 -> 16 | M14: ='Lpg (2)'!N18 -> 158.4 | N14: =D14*1.4 -> 2860.984 | O14: =E14*1.4 -> 748.384 | P14: ='Lpg (2)'!G18 -> 32000 | Q14: ='Summery Report'!Q13 -> 74765.48 | R14: =N14/B14 -> 77.323892 | S14: =Q14/B14 -> 2020.6886
A15: =Gen!A20 -> 43444 | B15: ='Summery Report'!D14 -> 44 | C15: ='Daily report Gen'!AA15 -> 420 | D15: =Gen!S20 -> 2103.23 | E15: =Gen!AJ20 -> 438 | F15: =SUM(D15+E15) -> 2541.23 | G15: ='Utility report'!AA14 -> 482377.5 | H15: ='Utility report'!AF15 -> 120 | I15: ='Utility report'!AE15 -> 1.0526316 | J15: ='Lpg (2)'!B19 -> 85 | K15: ='Lpg (2)'!C19 -> 85 | L15: ='Lpg (2)'!D19 -> 9 | M15: ='Lpg (2)'!N19 -> 197.208 | N15: =D15*1.4 -> 2944.522 | O15: =E15*1.4 -> 613.2 | P15: ='Lpg (2)'!G19 -> 18000 | Q15: ='Summery Report'!Q14 -> 73695.67 | R15: =N15/B15 -> 66.920955 | S15: =Q15/B15 -> 1674.9016
A16: =Gen!A21 -> 43445 | B16: ='Summery Report'!D15 -> 45 | C16: ='Daily report Gen'!AA16 -> 425 | D16: =Gen!S21 -> 2044.33 | E16: =Gen!AJ21 -> 222.33 | F16: =SUM(D16+E16) -> 2266.66 | G16: ='Utility report'!AA15 -> 1981444.8 | H16: ='Utility report'!AF16 -> 59 | I16: ='Utility report'!AE16 -> 0.51754386 | J16: ='Lpg (2)'!B20 -> 85 | K16: ='Lpg (2)'!C20 -> 85 | L16: ='Lpg (2)'!D20 -> 2 | M16: ='Lpg (2)'!N20 -> 121.836 | N16: =D16*1.4 -> 2862.062 | O16: =E16*1.4 -> 311.262 | P16: ='Lpg (2)'!G20 -> 4000 | Q16: ='Summery Report'!Q15 -> 65733.14 | R16: =N16/B16 -> 63.601378 | S16: =Q16/B16 -> 1460.7364
A17: =Gen!A22 -> 43446 | B17: ='Summery Report'!D16 -> 21 | C17: ='Daily report Gen'!AA17 -> 420 | D17: =Gen!S22 -> 1917.24 | E17: =Gen!AJ22 -> 198.24 | F17: =SUM(D17+E17) -> 2115.48 | G17: ='Utility report'!AA16 -> 1054380 | H17: ='Utility report'!AF17 -> 74 | I17: ='Utility report'!AE17 -> 0.7047619 | J17: ='Lpg (2)'!B21 -> 85 | K17: ='Lpg (2)'!C21 -> 78 | L17: ='Lpg (2)'!D21 -> 0 | M17: ='Lpg (2)'!N21 -> 127.292 | N17: =D17*1.4 -> 2684.136 | O17: =E17*1.4 -> 277.536 | P17: ='Lpg (2)'!G21 -> 0 | Q17: ='Summery Report'!Q16 -> 61348.92 | R17: =N17/B17 -> 127.816 | S17: =Q17/B17 -> 2921.3771
A18: =Gen!A23 -> 43447 | B18: ='Summery Report'!D17 -> 23 | C18: ='Daily report Gen'!AA18 -> 435 | D18: =Gen!S23 -> 1891.58 | E18: =Gen!AJ23 -> 114.1 | F18: =SUM(D18+E18) -> 2005.68 | G18: ='Utility report'!AA17 -> 1055160 | H18: ='Utility report'!AF18 -> 74 | I18: ='Utility report'!AE18 -> 0.66666667 | J18: ='Lpg (2)'!B22 -> 85 | K18: ='Lpg (2)'!C22 -> 66 | L18: ='Lpg (2)'!D22 -> 0 | M18: ='Lpg (2)'!N22 -> 119.636 | N18: =D18*1.4 -> 2648.212 | O18: =E18*1.4 -> 159.74 | P18: ='Lpg (2)'!G22 -> 0 | Q18: ='Summery Report'!Q17 -> 58164.72 | R18: =N18/B18 -> 115.13965 | S18: =Q18/B18 -> 2528.9009
... A32: =Gen!A37 -> 43461 | B32: ='Summery Report'!D31 -> 60 | C32: ='Daily report Gen'!AA32 -> 575 | D32: =Gen!S37 -> 2635.34 | E32: =Gen!AJ37 -> 203.69 | F32: =SUM(D32+E32) -> 2839.03 | G32: ='Utility report'!AA31 -> 0 | H32: ='Utility report'!AF32 -> 74 | I32: ='Utility report'!AE32 -> 0.46540881 | J32: ='Lpg (2)'!B36 -> 83 | K32: ='Lpg (2)'!C36 -> 0 | L32: ='Lpg (2)'!D36 -> 0 | M32: ='Lpg (2)'!N36 -> 108.46 | N32: =D32*1.4 -> 3689.476 | O32: =E32*1.4 -> 285.166 | P32: ='Lpg (2)'!G36 -> 0 | Q32: ='Summery Report'!Q31 -> 82331.87 | R32: =N32/B32 -> 61.491267 | S32: =Q32/B32 -> 1372.1978
A33: =Gen!A38 -> 43462 | B33: ='Summery Report'!D32 -> 62 | C33: ='Daily report Gen'!AA33 -> 630 | D33: =Gen!S38 -> 3043.34 | E33: =Gen!AJ38 -> 321.45 | F33: =SUM(D33+E33) -> 3364.79 | G33: ='Utility report'!AA32 -> 0 | H33: ='Utility report'!AF33 -> 72 | I33: ='Utility report'!AE33 -> 0.43902439 | J33: ='Lpg (2)'!B37 -> 80 | K33: ='Lpg (2)'!C37 -> 0 | L33: ='Lpg (2)'!D37 -> 0 | M33: ='Lpg (2)'!N37 -> 123.024 | N33: =D33*1.4 -> 4260.676 | O33: =E33*1.4 -> 450.03 | P33: ='Lpg (2)'!G37 -> 0 | Q33: ='Summery Report'!Q32 -> 97578.91 | R33: =N33/B33 -> 68.720581 | S33: =Q33/B33 -> 1573.8534 | T33: =3124/13 -> 240.30769
A34: =Gen!A39 -> 43463 | B34: ='Summery Report'!D33 -> 73 | C34: ='Daily report Gen'!AA34 -> 640 | D34: =Gen!S39 -> 2871.98 | E34: =Gen!AJ39 -> 247.04 | F34: =SUM(D34+E34) -> 3119.02 | G34: ='Utility report'!AA33 -> 206352.4 | H34: ='Utility report'!AF34 -> 70 | I34: ='Utility report'!AE34 -> 0.40462428 | J34: ='Lpg (2)'!B38 -> 79 | K34: ='Lpg (2)'!C38 -> 0 | L34: ='Lpg (2)'!D38 -> 0 | M34: ='Lpg (2)'!N38 -> 111.056 | N34: =D34*1.4 -> 4020.772 | O34: =E34*1.4 -> 345.856 | P34: ='Lpg (2)'!G38 -> 0 | Q34: ='Summery Report'!Q33 -> 90451.58 | R34: =N34/B34 -> 55.079068 | S34: =Q34/B34 -> 1239.0627
A35: =Gen!A40 -> 43464 | B35: ='Summery Report'!D34 -> 61 | C35: ='Daily report Gen'!AA35 -> 596 | D35: =Gen!S40 -> 3172.51 | E35: =Gen!AJ40 -> 120.12 | F35: =SUM(D35+E35) -> 3292.63 | G35: ='Utility report'!AA34 -> 0 | H35: ='Utility report'!AF35 -> 71 | I35: ='Utility report'!AE35 -> 0.45512821 | J35: ='Lpg (2)'!B39 -> 76 | K35: ='Lpg (2)'!C39 -> 0 | L35: ='Lpg (2)'!D39 -> 0 | M35: ='Lpg (2)'!N39 -> 106.568 | N35: =D35*1.4 -> 4441.514 | O35: =E35*1.4 -> 168.168 | P35: ='Lpg (2)'!G39 -> 0 | Q35: ='Summery Report'!Q34 -> 95486.27 | R35: =N35/B35 -> 72.811705 | S35: =Q35/B35 -> 1565.3487
A36: =Gen!A41 -> 43465 | B36: ='Summery Report'!D35 -> 66 | C36: ='Daily report Gen'!AA36 -> 568 | D36: =Gen!S41 -> 3058.76 | E36: =Gen!AJ41 -> 1284.14 | F36: =SUM(D36+E36) -> 4342.9 | G36: ='Utility report'!AA35 -> 0 | H36: ='Utility report'!AF36 -> -180052 | I36: ='Utility report'!AE36 -> -1500.4333 | J36: ='Lpg (2)'!B40 -> 72 | K36: ='Lpg (2)'!B39 -> 76 | L36: ='Lpg (2)'!C39 -> 0 | M36: ='Lpg (2)'!N40 -> 122.54 | N36: =D36*1.4 -> 4282.264 | O36: =E36*1.4 -> 1797.796 | P36: ='Lpg (2)'!G40 -> 0 | Q36: ='Summery Report'!Q35 -> 125944.1 | R36: =N36/B36 -> 64.882788 | S36: =Q36/B36 -> 1908.2439
A37: =Gen!A42 -> 0 | B37: ='Summery Report'!D36 -> 55 | E37: ='Utility report'!K34 -> 247.04 | Q37: ='Summery Report'!Q36 -> 0 | S37: =Q37/B37 -> 0
A39: Total | B39: =SUM(B7:B37) -> 1145 | C39: =SUM(C7:C35) -> 13091 | D39: =SUM(D7:D35) -> 66337.33 | E39: =SUM(E7:E35) -> 8369.87 | F39: =SUM(F7:F35) -> 74707.2 | G39: =SUM(G7:G35) -> #VALUE! | H39: =SUM(H7:H35) -> 1898 | I39: =SUM(I7:I35) -> 16.205169 | J39: =SUM(J7:J35) -> 2443 | ... S39: =SUM(S7:S35) -> 78969.616

Sheet Utility report
A1: DAILY UTILITY REPORT OCTOBER 2018
A2: Date | B2: Total occupancy | H2: Diesel balance LTS | I2: Diesel Deliveries | J2: Gen.Diesel consumption LTS | L2: Total Diesel consumption LTS | M2: Water Meter reading | N2: Water consumption m³ | O2: R.O WATER PRODUCTION LTRS + TIME | AA2: Total RO production | AB2: RO Meter reading | AD2: 0 | AE2: STP water production | AG2: GAS TANK A | AH2: GAS TANK B | AI2: GAS TANK C | AJ2: Total Gas Tanks | AK2: Kg /day | AL2: TOTAL GAS cons.
A3: Rate Tsh /$ | B3: 1640 | C3: Diesel cost / lits | D3: 2175 | F3: =SUM(D3/B3) -> 1.3262195 | H3: =SUM(Gen!C9) -> #REF! | K3: Transport consumption | M3: Balance | O3: PLANT NO 1 | S3: PLANT NO 2 | W3: PLANT NO 3 | AA3: /day | AB3: Balance | AC3: Production | AD3: 0 | AE3: % / W cons | AF3: Production | AG3: Capacity | AH3: Capacity | AI3: Capacity | AJ3: Kg | AK3: /day | AL3: /day
B4: Rooms OCC | C4: % | D4: Guest Rooms Occ | F4: Electricity Production Cost /Room Occ by guest | G4: All Cost /Room Occ by guest | O4: Flow M3 | P4: Reading Hours Meter | Q4: Hrs | R4: total production M3 | S4: Flow M3 | T4: Reading Hours Meter | U4: Hrs | V4: total production M3 | W4: Flow M3 | Y4: Hrs | Z4: total production M3 | AA4: M3 | AC4: M3 | AE4: % | AF4: M3 | AG4: 2000 | AH4: 1000 | AI4: 1000 | AJ4: =SUM([1]Sheet1!$AA$36) -> 950 | AK4: Kg | AL4: M3
M5: ='Water-Meter'!D5 -> 173149 | P5: 16896 | T5: 15027 | X5: 17291 | AB5: 96419 | AD5: 178089 | AG5: 0.85 | AH5: 0.85 | AI5: 0.17
A6: =Gen!A11 -> 43435 | B6: ='Summery Report'!E5 -> 15 | C6: =SUM(Gen!B11) -> 0.168 | D6: ='Summery Report'!E5 -> 15 | E6: =SUM(F3) -> 1.3262195 | F6: =SUM(J6*E6)/D6 -> 161.3682 | G6: =SUM(L6*E6)/D6 -> 165.15146 | H6: =SUM(Gen!C11) -> #REF! | I6: =SUM(Gen!D11) -> 0 | J6: =SUM(Gen!S11) -> 1825.13 | K6: =Gen!AJ11 -> 42.79 | L6: =SUM(J6:K6) -> 1867.92 | M6: ='Water-Meter'!D6 -> 173248 | N6: ='Water-Meter'!E6 -> 99 | O6: 2.3 | P6: 16896 | Q6: =SUM(P6-P5) -> 0 | R6: =SUM(Q6*O6) -> 0 | T6: 15027 | U6: =T6-T5 -> 0 | V6: - | W6: 2.7 | X6: 17311 | Y6: =X6-X5 -> 20 | Z6: - | AA6: =SUM(Z6*X8) -> #VALUE! | AB6: 96494 | AC6: =AB6-AB5 -> 75 | AD6: 178154 | AE6: =SUM(AF6/N6) -> 0.65656566 | AF6: =AD6-AD5 -> 65 | AG6: ='Lpg (2)'!B9*2000/85 -> 0 | AH6: ='Lpg (2)'!C9*1000/85 -> 0 | AI6: ='Lpg (2)'!D9*1000/85 -> 0 | AJ6: =SUM(AG6*2000)+(AH6*1000)+(AI6*1000) -> 0 | AK6: =SUM(AJ5-AJ6) -> 0
A7: =Gen!A12 -> 43436 | B7: =SUM(77*C7) -> 11.0033 | C7: =SUM(Gen!B12) -> 0.1429 | D7: =SUM('Summery Report'!E6) -> 13 | E7: =SUM(E6) -> 1.3262195 | F7: =SUM(J7*E7)/D7 -> 187.22037 | G7: =SUM(L7*E7)/D7 -> 196.4631 | H7: =SUM(Gen!C12) -> #REF! | I7: =SUM(Gen!D12) -> 0 | J7: =SUM(Gen!S12) -> 1835.19 | K7: =Gen!AJ12 -> 90.6 | L7: =SUM(J7:K7) -> 1925.79 | M7: ='Water-Meter'!D7 -> 173348 | N7: ='Water-Meter'!E7 -> 100 | O7: 2.3 | P7: 16941 | Q7: =SUM(P7-P6) -> 45 | R7: =SUM(Q7*O7) -> 103.5 | T7: 15027 | U7: =T7-T6 -> 0 | V7: =SUM(U7*S7) -> 0 | W7: 2.2 | X7: 17336 | Y7: =X7-X6 -> 25 | Z7: =SUM(Y7*W7) -> 55 | AA7: =SUM(Z7*X9) -> 956010 | AB7: 96591 | AC7: =SUM(AB7-AB6) -> 97 | AD7: 178199 | AE7: =SUM(AF7/N7) -> 0.45 | AF7: =AD7-AD6 -> 45 | AG7: ='Lpg (2)'!B10*2000/85 -> 2000 | AH7: ='Lpg (2)'!C10*1000/85 -> 1000 | AI7: ='Lpg (2)'!D10*1000/85 -> 882.35294 | AJ7: =SUM(AG6*2000)+(AH7*1000)+(AI7*1000) -> 1882352.9 | AK7: =SUM(AJ6-AJ7) -> -1882352.9
A8: =Gen!A13 -> 43437 | B8: =SUM(77*C8) -> 11.0033 | C8: =SUM(Gen!B13) -> 0.1429 | D8: =SUM('Summery Report'!E7) -> 13 | E8: =SUM(E7) -> 1.3262195 | F8: =SUM(J8*E8)/D8 -> 282.38784 | G8: =SUM(L8*E8)/D8 -> 293.44341 | H8: =SUM(Gen!C13) -> #REF! | I8: =SUM(Gen!D13) -> 0 | J8: =SUM(Gen!S13) -> 2768.05 | K8: =Gen!AJ13 -> 108.37 | L8: =SUM(J8:K8) -> 2876.42 | M8: ='Water-Meter'!D8 -> 173438 | N8: ='Water-Meter'!E8 -> 90 | O8: 1.2 | P8: 16965 | Q8: =SUM(P8-P7) -> 24 | R8: =SUM(Q8*O8) -> 28.8 | T8: 15027 | U8: =T8-T7 -> 0 | V8: =SUM(U8*S8) -> 0 | W8: 2.6 | X8: 17359 | Y8: =X8-X7 -> 23 | Z8: =SUM(Y8*W8) -> 59.8 | AA8: =SUM(Z8*X10) -> 1040878.8 | AB8: 96668 | AC8: =SUM(AB8-AB7) -> 77 | AD8: 178246 | AE8: =SUM(AF8/N8) -> 0.52222222 | AF8: =AD8-AD7 -> 47 | AG8: ='Lpg (2)'!B11*2000/85 -> 2000 | AH8: ='Lpg (2)'!C11*1000/85 -> 1000 | AI8: ='Lpg (2)'!D11*1000/85 -> 717.64706 | AJ8: =SUM(AG7*2000)+(AH8*1000)+(AI8*1000) -> 5717647.1 | AK8: =SUM(AJ7-AJ8) -> -3835294.1
A9: =Gen!A14 -> 43438 | B9: =SUM(77*C9) -> 12.9976 | C9: =SUM(Gen!B14) -> 0.1688 | D9: =SUM('Summery Report'!E8) -> 15 | E9: =SUM(E8) -> 1.3262195 | F9: =SUM(J9*E9)/D9 -> 168.91174 | G9: =SUM(L9*E9)/D9 -> 178.64177 | H9: =SUM(Gen!C14) -> #REF! | I9: =SUM(Gen!D14) -> 17000 | J9: =SUM(Gen!S14) -> 1910.45 | K9: =Gen!AJ14 -> 110.05 | L9: =SUM(J9:K9) -> 2020.5 | M9: ='Water-Meter'!D9 -> 173525 | N9: ='Water-Meter'!E9 -> 87 | O9: 1.2 | P9: 16988 | Q9: =SUM(P9-P8) -> 23 | R9: =SUM(Q9*O9) -> 27.6 | T9: 15027 | U9: =T9-T8 -> 0 | V9: =SUM(U9*S9) -> 0 | W9: 2.6 | X9: 17382 | Y9: =X9-X8 -> 23 | Z9: =SUM(Y9*W9) -> 59.8 | AA9: =SUM(Z9*X11) -> 1042314 | AB9: 96751 | AC9: =SUM(AB9-AB8) -> 83 | AD9: 178319 | AE9: =SUM(AF9/N9) -> 0.83908046 | AF9: =AD9-AD8 -> 73 | AG9: ='Lpg (2)'!B12*2000/85 -> 2000 | AH9: ='Lpg (2)'!C12*1000/85 -> 1000 | AI9: ='Lpg (2)'!D12*1000/85 -> 611.76471 | AJ9: =SUM(AG8*2000)+(AH9*1000)+(AI9*1000) -> 5611764.7 | AK9: =SUM(AJ8-AJ9) -> 105882.35
A10: =Gen!A15 -> 43439 | B10: =SUM(77*C10) -> 16.0006 | C10: =SUM(Gen!B15) -> 0.2078 | D10: =SUM('Summery Report'!E9) -> 12 | E10: =SUM(E9) -> 1.3262195 | F10: =SUM(J10*E10)/D10 -> 197.3061 | G10: =SUM(L10*E10)/D10 -> 197.3061 | H10: =SUM(Gen!C15) -> #REF! | I10: =SUM(Gen!D15) -> 0 | J10: =SUM(Gen!S15) -> 1785.28 | K10: =Gen!AJ15 -> 0 | L10: =SUM(J10:K10) -> 1785.28 | M10: ='Water-Meter'!D10 -> 173609 | N10: ='Water-Meter'!E10 -> 84 | O10: 1.2 | P10: 16994 | Q10: =SUM(P10-P9) -> 6 | R10: =SUM(Q10*O10) -> 7.2 | T10: 15027 | U10: =T10-T9 -> 0 | V10: =SUM(U10*S10) -> 0 | W10: 2.6 | X10: 17406 | Y10: =X10-X9 -> 24 | Z10: =SUM(Y10*W10) -> 62.4 | AA10: =SUM(Z10*X12) -> 1087819.2 | AB10: 96816 | AC10: =SUM(AB10-AB9) -> 65 | AD10: 178372 | AE10: =SUM(AF10/N10) -> 0.63095238 | AF10: =AD10-AD9 -> 53 | AG10: ='Lpg (2)'!B13*2000/85 -> 2000 | AH10: ='Lpg (2)'!C13*1000/85 -> 1000 | AI10: ='Lpg (2)'!D13*1000/85 -> 529.41176 | AJ10: =SUM(AG9*2000)+(AH10*1000)+(AI10*1000) -> 5529411.8 | AK10: =SUM(AJ9-AJ10) -> 82352.941
A11: =Gen!A16 -> 43440 | B11: =SUM(77*C11) -> 22.9999 | C11: =SUM(Gen!B16) -> 0.2987 | D11: =SUM('Summery Report'!E10) -> 15 | E11: =SUM(E10) -> 1.3262195 | F11: =SUM(J11*E11)/D11 -> 168.32909 | G11: =SUM(L11*E11)/D11 -> 190.22497 | H11: =SUM(Gen!C16) -> #REF! | I11: =SUM(Gen!D16) -> 0 | J11: =SUM(Gen!S16) -> 1903.86 | K11: =Gen!AJ16 -> 247.65 | L11: =SUM(J11:K11) -> 2151.51 | M11: ='Water-Meter'!D11 -> 173717 | N11: ='Water-Meter'!E11 -> 108 | O11: 1.2 | P11: 17009 | Q11: =SUM(P11-P10) -> 15 | R11: =SUM(Q11*O11) -> 18 | T11: 15027 | U11: =T11-T10 -> 0 | V11: =SUM(U11*S11) -> 0 | W11: 2.6 | X11: 17430 | Y11: =X11-X10 -> 24 | Z11: =SUM(Y11*W11) -> 62.4 | AA11: =SUM(Z11*X13) -> 1089379.2 | AB11: 96861 | AC11: =SUM(AB11-AB10) -> 45 | AD11: 178429 | AE11: =SUM(AF11/N11) -> 0.52777778 | AF11: =AD11-AD10 -> 57 | AG11: ='Lpg (2)'!B14*2000/85 -> 2000 | AH11: ='Lpg (2)'!C14*1000/85 -> 1000 | AI11: ='Lpg (2)'!D14*1000/85 -> 470.58824 | AJ11: =SUM(AG10*2000)+(AH11*1000)+(AI11*1000) -> 5470588.2 | AK11: =SUM(AJ10-AJ11) -> 58823.529
A12: =Gen!A17 -> 43441 | B12: =SUM(77*C12) -> 19.0036 | C12: =SUM(Gen!B17) -> 0.2468 | D12: =SUM('Summery Report'!E11) -> 20 | E12: =SUM(E11) -> 1.3262195 | F12: =SUM(J12*E12)/D12 -> 133.29766 | G12: =SUM(L12*E12)/D12 -> 148.16259 | H12: =SUM(Gen!C17) -> #REF! | I12: =SUM(Gen!D17) -> 0 | J12: =SUM(Gen!S17) -> 2010.19 | K12: =Gen!AJ17 -> 224.17 | L12: =SUM(J12:K12) -> 2234.36 | M12: ='Water-Meter'!D12 -> 173810 | N12: ='Water-Meter'!E12 -> 93 | P12: 17033 | Q12: =SUM(P12-P11) -> 24 | R12: =SUM(Q12*O12) -> 0 | T12: 15027 | U12: =T12-T11 -> 0 | V12: =SUM(U12*S12) -> 0 | W12: 2.6 | X12: 17433 | Y12: =X12-X11 -> 3 | Z12: =SUM(Y12*W12) -> 7.8 | AA12: =SUM(Z12*X14) -> 136258.2 | AB12: 96973 | AC12: =SUM(AB12-AB11) -> 112 | AD12: 178482 | AE12: =SUM(AF12/N12) -> 0.56989247 | AF12: =AD12-AD11 -> 53 | AG12: ='Lpg (2)'!B15*2000/85 -> 2000 | AH12: ='Lpg (2)'!C15*1000/85 -> 1000 | AI12: ='Lpg (2)'!D15*1000/85 -> 423.52941 | AJ12: =SUM(AG11*2000)+(AH12*1000)+(AI12*1000) -> 5423529.4 | AK12: =SUM(AJ11-AJ12) -> 47058.824
A13: =Gen!A18 -> 43442 | B13: =SUM(77*C13) -> 21.9989 | C13: =SUM(Gen!B18) -> 0.2857 | D13: =SUM('Summery Report'!E12) -> 23 | E13: =SUM(E12) -> 1.3262195 | F13: =SUM(J13*E13)/D13 -> 110.91001 | G13: =SUM(L13*E13)/D13 -> 117.48344 | H13: =SUM(Gen!C18) -> #REF! | I13: =SUM(Gen!D18) -> 0 | J13: =SUM(Gen!S18) -> 1923.46 | K13: =Gen!AJ18 -> 114 | L13: =SUM(J13:K13) -> 2037.46 | M13: ='Water-Meter'!D13 -> 173913 | N13: ='Water-Meter'!E13 -> 103 | P13: 17038 | Q13: =SUM(P13-P12) -> 5 | R13: =SUM(Q13*O13) -> 0 | T13: 15027 | U13: =T13-T12 -> 0 | V13: =SUM(U13*S13) -> 0 | W13: 2.6 | X13: 17458 | Y13: =X13-X12 -> 25 | Z13: =SUM(Y13*W13) -> 65 | AA13: =SUM(Z13*X15) -> 1138540 | AB13: 96993 | AC13: =SUM(AB13-AB12) -> 20 | AD13: 178535 | AE13: =SUM(AF13/N13) -> 0.51456311 | AF13: =AD13-AD12 -> 53 | AG13: ='Lpg (2)'!B16*2000/85 -> 2000 | AH13: ='Lpg (2)'!C16*1000/85 -> 1000 | AI13: ='Lpg (2)'!D16*1000/85 -> 352.94118 | AJ13: =SUM(AG12*2000)+(AH13*1000)+(AI13*1000) -> 5352941.2 | AK13: =SUM(AJ12-AJ13) -> 70588.235
A14: =Gen!A19 -> 43443 | B14: =SUM(77*C14) -> 35.9975 | C14: =SUM(Gen!B19) -> 0.4675 | D14: =SUM('Summery Report'!E13) -> 37 | E14: =SUM(E13) -> 1.3262195 | F14: =SUM(J14*E14)/D14 -> 73.248896 | G14: =SUM(L14*E14)/D14 -> 92.409542 | H14: =SUM(Gen!C19) -> #REF! | I14: =SUM(Gen!D19) -> 0 | J14: =SUM(Gen!S19) -> 2043.56 | K14: =Gen!AJ19 -> 534.56 | L14: =SUM(J14:K14) -> 2578.12 | M14: ='Water-Meter'!D14 -> 174038 | N14: ='Water-Meter'!E14 -> 125 | O14: 1.2 | P14: 17064 | Q14: =SUM(P14-P13) -> 26 | R14: =SUM(Q14*O14) -> 31.2 | T14: 15027 | U14: =T14-T13 -> 0 | V14: =SUM(U14*S14) -> 0 | W14: 2.5 | X14: 17469 | Y14: =X14-X13 -> 11 | Z14: =SUM(Y14*W14) -> 27.5 | AA14: =SUM(Z14*X16) -> 482377.5 | AB14: 97031 | AC14: =SUM(AB14-AB13) -> 38 | AD14: 178594 | AE14: =SUM(AF14/N14) -> 0.472 | AF14: =AD14-AD13 -> 59 | AG14: ='Lpg (2)'!B17*2000/85 -> 2000 | AH14: ='Lpg (2)'!C17*1000/85 -> 1000 | AI14: ='Lpg (2)'!D17*1000/85 -> 270.58824 | AJ14: =SUM(AG13*2000)+(AH14*1000)+(AI14*1000) -> 5270588.2 | AK14: =SUM(AJ13-AJ14) -> 82352.941
A15: =Gen!A20 -> 43444 | B15: =SUM(77*C15) -> 42.9968 | C15: =SUM(Gen!B20) -> 0.5584 | D15: =SUM('Summery Report'!E14) -> 44 | E15: =SUM(E14) -> 1.3262195 | F15: =SUM(J15*E15)/D15 -> 63.394197 | G15: =SUM(L15*E15)/D15 -> 76.596109 | H15: =SUM(Gen!C20) -> #REF! | I15: =SUM(Gen!D20) -> 12000 | J15: =SUM(Gen!S20) -> 2103.23 | K15: =Gen!AJ20 -> 438 | L15: =SUM(J15:K15) -> 2541.23 | M15: ='Water-Meter'!D15 -> 174152 | N15: ='Water-Meter'!E15 -> 114 | O15: 1.2 | P15: 17064 | Q15: =SUM(P15-P14) -> 0 | R15: =SUM(Q15*O15) -> 0 | S15: 2.5 | T15: 15046 | U15: =T15-T14 -> 19 | V15: =SUM(U15*S15) -> 47.5 | W15: 2.4 | X15: 17516 | Y15: =X15-X14 -> 47 | Z15: =SUM(Y15*W15) -> 112.8 | AA15: =SUM(Z15*X17) -> 1981444.8 | AB15: 97126 | AC15: =SUM(AB15-AB14) -> 95 | AD15: 178714 | AE15: =SUM(AF15/N15) -> 1.0526316 | AF15: =AD15-AD14 -> 120 | AG15: ='Lpg (2)'!B18*2000/85 -> 2000 | AH15: ='Lpg (2)'!C18*1000/85 -> 1000 | AI15: ='Lpg (2)'!D18*1000/85 -> 188.23529 | AJ15: =SUM(AG15*2000)+(AH15*1000)+(AI15*1000) -> 5188235.3 | AK15: =SUM(AJ14-AJ15) -> 82352.941
A16: =Gen!A21 -> 43445 | B16: =SUM(77*C16) -> 43.9978 | C16: =SUM(Gen!B21) -> 0.5714 | D16: =SUM('Summery Report'!E15) -> 45 | E16: =SUM(E15) -> 1.3262195 | F16: =SUM(J16*E16)/D16 -> 60.249563 | G16: =SUM(L16*E16)/D16 -> 66.801972 | H16: =SUM(Gen!C21) -> #REF! | I16: =SUM(Gen!D21) -> 0 | J16: =SUM(Gen!S21) -> 2044.33 | K16: =Gen!AJ21 -> 222.33 | L16: =SUM(J16:K16) -> 2266.66 | M16: ='Water-Meter'!D16 -> 174266 | N16: ='Water-Meter'!E16 -> 114 | O16: 1.2 | P16: 17064 | Q16: =SUM(P16-P15) -> 0 | R16: =SUM(Q16*O16) -> 0 | S16: 2.5 | T16: 15071 | U16: =T16-T15 -> 25 | V16: =SUM(U16*S16) -> 62.5 | W16: 2.4 | X16: 17541 | Y16: =X16-X15 -> 25 | Z16: =SUM(Y16*W16) -> 60 | AA16: =SUM(Z16*X18) -> 1054380 | AB16: 97333 | AC16: =SUM(AB16-AB15) -> 207 | AD16: 178773 | AE16: =SUM(AF16/N16) -> 0.51754386 | AF16: =AD16-AD15 -> 59 | AG16: ='Lpg (2)'!B19*2000/85 -> 2000 | AH16: ='Lpg (2)'!C19*1000/85 -> 1000 | AI16: ='Lpg (2)'!D19*1000/85 -> 105.88235 | AJ16: =SUM(AG16*2000)+(AH16*1000)+(AI16*1000) -> 5105882.4 | AK16: =SUM(AJ15-AJ16) -> 82352.941
A17: =Gen!A22 -> 43446 | B17: =SUM(77*C17) -> 18.0026 | C17: =SUM(Gen!B22) -> 0.2338 | D17: =SUM('Summery Report'!E16) -> 21 | E17: =SUM(E16) -> 1.3262195 | F17: =SUM(J17*E17)/D17 -> 121.08005 | G17: =SUM(L17*E17)/D17 -> 133.59956 | H17: =SUM(Gen!C22) -> #REF! | I17: =SUM(Gen!D22) -> 0 | J17: =SUM(Gen!S22) -> 1917.24 | K17: =Gen!AJ22 -> 198.24 | L17: =SUM(J17:K17) -> 2115.48 | M17: ='Water-Meter'!D17 -> 174371 | N17: ='Water-Meter'!E17 -> 105 | O17: 1.2 | P17: 17064 | Q17: =SUM(P17-P16) -> 0 | R17: =SUM(Q17*O17) -> 0 | S17: 2.5 | T17: 15096 | U17: =T17-T16 -> 25 | V17: =SUM(U17*S17) -> 62.5 | W17: 2.4 | X17: 17566 | Y17: =X17-X16 -> 25 | Z17: =SUM(Y17*W17) -> 60 | AA17: =SUM(Z17*X19) -> 1055160 | AB17: 97450 | AC17: =SUM(AB17-AB16) -> 117 | AD17: 178847 | AE17: =SUM(AF17/N17) -> 0.7047619 | AF17: =AD17-AD16 -> 74 | AG17: ='Lpg (2)'!B20*2000/85 -> 2000 | AH17: ='Lpg (2)'!C20*1000/85 -> 1000 | AI17: ='Lpg (2)'!D20*1000/85 -> 23.529412 | AJ17: =SUM(AG17*2000)+(AH17*1000)+(AI17*1000) -> 5023529.4 | AK17: =SUM(AJ16-AJ17) -> 82352.941
A18: =Gen!A23 -> 43447 | B18: =SUM(77*C18) -> 20.9979 | C18: =SUM(Gen!B23) -> 0.2727 | D18: =SUM('Summery Report'!E17) -> 23 | E18: =SUM(E17) -> 1.3262195 | F18: =SUM(J18*E18)/D18 -> 109.07175 | G18: =SUM(L18*E18)/D18 -> 115.65095 | H18: =SUM(Gen!C23) -> #REF! | I18: =SUM(Gen!D23) -> 0 | J18: =SUM(Gen!S23) -> 1891.58 | K18: =Gen!AJ23 -> 114.1 | L18: =SUM(J18:K18) -> 2005.68 | M18: ='Water-Meter'!D18 -> 174482 | N18: ='Water-Meter'!E18 -> 111 | O18: 1.2 | P18: 17064 | Q18: =SUM(P18-P17) -> 0 | R18: =SUM(Q18*O18) -> 0 | S18: 2.5 | T18: 15096 | U18: =T18-T17 -> 0 | V18: =SUM(U18*S18) -> 0 | W18: 2.4 | X18: 17573 | Y18: =X18-X17 -> 7 | Z18: =SUM(Y18*W18) -> 16.8 | AA18: =SUM(Z18*X20) -> 295965.6 | AB18: 97479 | AC18: =SUM(AB18-AB17) -> 29 | AD18: 178921 | AE18: =SUM(AF18/N18) -> 0.66666667 | AF18: =AD18-AD17 -> 74 | AG18: ='Lpg (2)'!B21*2000/85 -> 2000 | AH18: ='Lpg (2)'!C21*1000/85 -> 917.64706 | AI18: ='Lpg (2)'!D21*1000/85 -> 0 | AJ18: =SUM(AG18*2000)+(AH18*1000)+(AI18*1000) -> 4917647.1 | AK18: =SUM(AJ17-AJ18) -> 105882.35
A19: =Gen!A24 -> 43448 | B19: =SUM(77*C19) -> 19.9815 | C19: =SUM(Gen!B24) -> 0.2595 | D19: =SUM('Summery Report'!E18) -> 21 | E19: =SUM(E18) -> 1.3262195 | F19: =SUM(J19*E19)/D19 -> 125.82918 | G19: =SUM(L19*E19)/D19 -> 145.75531 | H19: =SUM(Gen!C24) -> #REF! | I19: =SUM(Gen!D24) -> 0 | J19: =SUM(Gen!S24) -> 1992.44 | K19: =Gen!AJ24 -> 315.52 | L19: =SUM(J19:K19) -> 2307.96 | M19: ='Water-Meter'!D19 -> 174582 | N19: ='Water-Meter'!E19 -> 100 | O19: 1.2 | P19: 17064 | Q19: =SUM(P19-P18) -> 0 | R19: =SUM(Q19*O19) -> 0 | S19: 2.5 | T19: 15096 | U19: =T19-T18 -> 0 | V19: =SUM(U19*S19) -> 0 | W19: 2.4 | X19: 17586 | Y19: =X19-X18 -> 13 | Z19: =SUM(Y19*W19) -> 31.2 | AA19: =SUM(Z19*X21) -> 550399.2 | AB19: 97530 | AC19: =SUM(AB19-AB18) -> 51 | AD19: 178977 | AE19: =SUM(AF19/N19) -> 0.56 | AF19: =AD19-AD18 -> 56 | AG19: ='Lpg (2)'!B22*2000/85 -> 2000 | AH19: ='Lpg (2)'!C22*1000/85 -> 776.47059 | AI19: ='Lpg (2)'!D22*1000/85 -> 0 | AJ19: =SUM(AG19*2000)+(AH19*1000)+(AI19*1000) -> 4776470.6 | AK19: =SUM(AJ18-AJ19) -> 141176.47
A20: =Gen!A25 -> 43449 | B20: =SUM(77*C20) -> 10.0023 | C20: =SUM(Gen!B25) -> 0.1299 | D20: =SUM('Summery Report'!E19) -> 11 | E20: =SUM(E19) -> 1.3262195 | F20: =SUM(J20*E20)/D20 -> 233.65335 | G20: =SUM(L20*E20)/D20 -> 302.53478 | H20: =SUM(Gen!C25) -> #REF! | I20: =SUM(Gen!D25) -> 0 | J20: =SUM(Gen!S25) -> 1937.98 | K20: =Gen!AJ25 -> 571.32 | L20: =SUM(J20:K20) -> 2509.3 | M20: ='Water-Meter'!D20 -> 174669 | N20: ='Water-Meter'!E20 -> 87 | O20: 1.2 | P20: 17064 | Q20: =SUM(P20-P19) -> 0 | R20: =SUM(Q20*O20) -> 0 | S20: 2.5 | T20: 15096 | U20: =T20-T19 -> 0 | V20: =SUM(U20*S20) -> 0 | W20: 2.4 | X20: 17617 | Y20: =X20-X19 -> 31 | Z20: =SUM(Y20*W20) -> 74.4 | AA20: =SUM(Z20*X22) -> 1314127.2 | AB20: 97591 | AC20: =SUM(AB20-AB19) -> 61 | AD20: 179014 | AE20: =SUM(AF20/N20) -> 0.42528736 | AF20: =AD20-AD19 -> 37 | AG20: ='Lpg (2)'!B23*2000/85 -> 2000 | AH20: ='Lpg (2)'!C23*1000/85 -> 705.88235 | AI20: ='Lpg (2)'!D23*1000/85 -> 0 | AJ20: =SUM(AG20*2000)+(AH20*1000)+(AI20*1000) -> 4705882.4 | AK20: =SUM(AJ19-AJ20) -> 70588.235
A21: =Gen!A26 -> 43450 | B21: =SUM(77*C21) -> 19.9969 | C21: =SUM(Gen!B26) -> 0.2597 | D21: =SUM('Summery Report'!E20) -> 21 | E21: =SUM(E20) -> 1.3262195 | F21: =SUM(J21*E21)/D21 -> 128.96727 | G21: =SUM(L21*E21)/D21 -> 150.17036 | H21: =SUM(Gen!C26) -> #REF! | I21: =SUM(Gen!D26) -> 12000 | J21: =SUM(Gen!S26) -> 2042.13 | K21: =Gen!AJ26 -> 335.74 | L21: =SUM(J21:K21) -> 2377.87 | M21: ='Water-Meter'!D21 -> 174774 | N21: ='Water-Meter'!E21 -> 105 | O21: 2.6 | P21: 17097 | Q21: =SUM(P21-P20) -> 33 | R21: =SUM(Q21*O21) -> 85.8 | S21: 2.5 | T21: 15096 | U21: =T21-T20 -> 0 | V21: =SUM(U21*S21) -> 0 | W21: 2.3 | X21: 17641 | Y21: =X21-X20 -> 24 | Z21: =SUM(Y21*W21) -> 55.2 | AA21: =SUM(Z21*X23) -> 976432.8 | AB21: 97691 | AC21: =SUM(AB21-AB20) -> 100 | AD21: 179014 | AE21: =SUM(AF21/N21) -> 0 | AF21: =AD21-AD20 -> 0 | AG21: ='Lpg (2)'!B24*2000/85 -> 2000 | AH21: ='Lpg (2)'!C24*1000/85 -> 658.82353 | AI21: ='Lpg (2)'!D24*1000/85 -> 0 | AJ21: =SUM(AG21*2000)+(AH21*1000)+(AI21*1000) -> 4658823.5 | AK21: =SUM(AJ20-AJ21) -> 47058.824
A22: =Gen!A27 -> 43451 | B22: =SUM(77*C22) -> 22.9999 | C22: =SUM(Gen!B27) -> 0.2987 | D22: =SUM('Summery Report'!E21) -> 24 | E22: =SUM(E21) -> 1.3262195 | F22: =SUM(J22*E22)/D22 -> 115.99226 | G22: =SUM(L22*E22)/D22 -> 148.11496 | H22: =SUM(Gen!C27) -> #REF! | I22: =SUM(Gen!D27) -> 0 | J22: =SUM(Gen!S27) -> 2099.06 | K22: =Gen!AJ27 -> 581.31 | L22: =SUM(J22:K22) -> 2680.37 | M22: ='Water-Meter'!D22 -> 174883 | N22: ='Water-Meter'!E22 -> 109 | O22: 2.6 | P22: 17121 | Q22: =SUM(P22-P21) -> 24 | R22: =SUM(Q22*O22) -> 62.4 | S22: 2.5 | T22: 15096 | U22: =T22-T21 -> 0 | V22: =SUM(U22*S22) -> 0 | W22: 2.3 | X22: 17663 | Y22: =X22-X21 -> 22 | Z22: =SUM(Y22*W22) -> 50.6 | AA22: =SUM(Z22*X24) -> 895822.4 | AB22: 97796 | AC22: =SUM(AB22-AB21) -> 105 | AD22: 179063 | AE22: =SUM(AF22/N22) -> 0.44954128 | AF22: =AD22-AD21 -> 49 | AG22: ='Lpg (2)'!B25*2000/85 -> 2000 | AH22: ='Lpg (2)'!C25*1000/85 -> 611.76471 | AI22: ='Lpg (2)'!D25*1000/85 -> 0 | AJ22: =SUM(AG22*2000)+(AH22*1000)+(AI22*1000) -> 4611764.7 | AK22: =SUM(AJ21-AJ22) -> 47058.824
A23: =Gen!A28 -> 43452 | B23: =SUM(77*C23) -> 39.0005 | C23: =SUM(Gen!B28) -> 0.5065 | D23: =SUM('Summery Report'!E22) -> 41 | E23: =SUM(E22) -> 1.3262195 | F23: =SUM(J23*E23)/D23 -> 76.726004 | G23: =SUM(L23*E23)/D23 -> 82.733131 | H23: =SUM(Gen!C28) -> #REF! | I23: =SUM(Gen!D28) -> 0 | J23: =SUM(Gen!S28) -> 2371.98 | K23: =Gen!AJ28 -> 185.71 | L23: =SUM(J23:K23) -> 2557.69 | M23: ='Water-Meter'!D23 -> 174997 | N23: ='Water-Meter'!E23 -> 114 | O23: 2.6 | P23: 17145 | Q23: =SUM(P23-P22) -> 24 | R23: =SUM(Q23*O23) -> 62.4 | S23: 2.5 | T23: 15096 | U23: =T23-T22 -> 0 | V23: =SUM(U23*S23) -> 0 | W23: 2.3 | X23: 17689 | Y23: =X23-X22 -> 26 | Z23: =SUM(Y23*W23) -> 59.8 | AA23: =SUM(Z23*X25) -> 1058878.6 | AB23: 97900 | AC23: =SUM(AB23-AB22) -> 104 | AD23: 179111 | AE23: =SUM(AF23/N23) -> 0.42105263 | AF23: =AD23-AD22 -> 48 | AG23: ='Lpg (2)'!B26*2000/85 -> 2000 | AH23: ='Lpg (2)'!C26*1000/85 -> 576.47059 | AI23: ='Lpg (2)'!D26*1000/85 -> 0 | AJ23: =SUM(AG23*2000)+(AH23*1000)+(AI23*1000) -> 4576470.6 | AK23: =SUM(AJ22-AJ23) -> 35294.118
A24: =Gen!A29 -> 43453 | B24: =SUM(77*C24) -> 34.0032 | C24: =SUM(Gen!B29) -> 0.4416 | D24: =SUM('Summery Report'!E23) -> 35 | E24: =SUM(E23) -> 1.3262195 | F24: =SUM(J24*E24)/D24 -> 85.588524 | G24: =SUM(L24*E24)/D24 -> 90.059778 | H24: =SUM(Gen!C29) -> #REF! | I24: =SUM(Gen!D29) -> 0 | J24: =SUM(Gen!S29) -> 2258.75 | K24: =Gen!AJ29 -> 118 | L24: =SUM(J24:K24) -> 2376.75 | M24: ='Water-Meter'!D24 -> 175107 | N24: ='Water-Meter'!E24 -> 110 | O24: 2.6 | P24: 17160 | Q24: =SUM(P24-P23) -> 15 | R24: =SUM(Q24*O24) -> 39 | S24: 2.5 | T24: 15096 | U24: =T24-T23 -> 0 | V24: =SUM(U24*S24) -> 0 | W24: 2.3 | X24: 17704 | Y24: =X24-X23 -> 15 | Z24: =SUM(Y24*W24) -> 34.5 | AA24: =SUM(Z24*X26) -> 611719.5 | AB24: 97960 | AC24: =SUM(AB24-AB23) -> 60 | AD24: 179219 | AE24: =SUM(AF24/N24) -> 0.98181818 | AF24: =AD24-AD23 -> 108 | AG24: ='Lpg (2)'!B27*2000/85 -> 2000 | AH24: ='Lpg (2)'!C27*1000/85 -> 435.29412 | AI24: ='Lpg (2)'!D27*1000/85 -> 0 | AJ24: =SUM(AG24*2000)+(AH24*1000)+(AI24*1000) -> 4435294.1 | AK24: =SUM(AJ23-AJ24) -> 141176.47
A25: =Gen!A30 -> 43454 | B25: =SUM(77*C25) -> 31.0002 | C25: =SUM(Gen!B30) -> 0.4026 | D25: =SUM('Summery Report'!E24) -> 34 | E25: =SUM(E24) -> 1.3262195 | F25: =SUM(J25*E25)/D25 -> 91.873077 | G25: =SUM(L25*E25)/D25 -> 118.79104 | H25: =SUM(Gen!C30) -> #REF! | I25: =SUM(Gen!D30) -> 0 | J25: =SUM(Gen!S30) -> 2355.33 | K25: =Gen!AJ30 -> 690.09 | L25: =SUM(J25:K25) -> 3045.42 | M25: ='Water-Meter'!D25 -> 175230 | N25: ='Water-Meter'!E25 -> 123 | O25: 2.6 | P25: 17160 | Q25: =SUM(P25-P24) -> 0 | R25: =SUM(Q25*O25) -> 0 | S25: 2.5 | T25: 15107 | U25: =T25-T24 -> 11 | V25: =SUM(U25*S25) -> 27.5 | W25: 2.3 | X25: 17707 | Y25: =X25-X24 -> 3 | Z25: =SUM(Y25*W25) -> 6.9 | AA25: =SUM(Z25*X27) -> 122392.2 | AB25: 97983 | AC25: =SUM(AB25-AB24) -> 23 | AD25: 179300 | AE25: =SUM(AF25/N25) -> 0.65853659 | AF25: =AD25-AD24 -> 81 | AG25: ='Lpg (2)'!B28*2000/85 -> 2000 | AH25: ='Lpg (2)'!C28*1000/85 -> 341.17647 | AI25: ='Lpg (2)'!D28*1000/85 -> 0 | AJ25: =SUM(AG25*2000)+(AH25*1000)+(AI25*1000) -> 4341176.5 | AK25: =SUM(AJ24-AJ25) -> 94117.647
A26: =Gen!A31 -> 43455 | B26: =SUM(77*C26) -> 37.9995 | C26: =SUM(Gen!B31) -> 0.4935 | D26: =SUM('Summery Report'!E25) -> 41 | E26: =SUM(E25) -> 1.3262195 | F26: =SUM(J26*E26)/D26 -> 69.849717 | G26: =SUM(L26*E26)/D26 -> 87.458678 | H26: =SUM(Gen!C31) -> #REF! | I26: =SUM(Gen!D31) -> 0 | J26: =SUM(Gen!S31) -> 2159.4 | K26: =Gen!AJ31 -> 544.38 | L26: =SUM(J26:K26) -> 2703.78 | M26: ='Water-Meter'!D26 -> 175360 | N26: ='Water-Meter'!E26 -> 130 | O26: 2.5 | P26: 17163 | Q26: =SUM(P26-P25) -> 3 | R26: =SUM(Q26*O26) -> 7.5 | S26: 2.5 | T26: 15128 | U26: =T26-T25 -> 21 | V26: =SUM(U26*S26) -> 52.5 | W26: 2.8 | X26: 17731 | Y26: =X26-X25 -> 24 | Z26: =SUM(Y26*W26) -> 67.2 | AA26: =SUM(Z26*X28) -> 1192732.8 | AB26: 98110 | AC26: =SUM(AB26-AB25) -> 127 | AD26: 179381 | AE26: =SUM(AF26/N26) -> 0.62307692 | AF26: =AD26-AD25 -> 81 | AG26: ='Lpg (2)'!B29*2000/85 -> 2000 | AH26: ='Lpg (2)'!C29*1000/85 -> 235.29412 | AI26: ='Lpg (2)'!D29*1000/85 -> 0 | AJ26: =SUM(AG26*2000)+(AH26*1000)+(AI26*1000) -> 4235294.1 | AK26: =SUM(AJ25-AJ26) -> 105882.35
A27: =Gen!A32 -> 43456 | B27: =SUM(77*C27) -> 37.9995 | C27: =SUM(Gen!B32) -> 0.4935 | D27: =SUM('Summery Report'!E26) -> 41 | E27: =SUM(E26) -> 1.3262195 | F27: =SUM(J27*E27)/D27 -> 80.900037 | G27: =SUM(L27*E27)/D27 -> 91.339326 | H27: =SUM(Gen!C32) -> #REF! | I27: =SUM(Gen!D32) -> 16800 | J27: =SUM(Gen!S32) -> 2501.02 | K27: =Gen!AJ32 -> 322.73 | L27: =SUM(J27:K27) -> 2823.75 | M27: ='Water-Meter'!D27 -> 175490 | N27: ='Water-Meter'!E27 -> 130 | O27: 2.5 | P27: 17164 | Q27: =SUM(P27-P26) -> 1 | R27: =SUM(Q27*O27) -> 2.5 | S27: 2.5 | T27: 15128 | U27: =T27-T26 -> 0 | V27: =SUM(U27*S27) -> 0 | W27: 2.8 | X27: 17738 | Y27: =X27-X26 -> 7 | Z27: =SUM(Y27*W27) -> 19.6 | AA27: =SUM(Z27*X29) -> 347880.4 | AB27: 98145 | AC27: =SUM(AB27-AB26) -> 35 | AD27: 179466 | AE27: =SUM(AF27/N27) -> 0.65384615 | AF27: =AD27-AD26 -> 85 | AG27: ='Lpg (2)'!B30*2000/85 -> 2000 | AH27: ='Lpg (2)'!C30*1000/85 -> 176.47059 | AI27: ='Lpg (2)'!D30*1000/85 -> 0 | AJ27: =SUM(AG27*2000)+(AH27*1000)+(AI27*1000) -> 4176470.6 | AK27: =SUM(AJ26-AJ27) -> 58823.529
A28: =Gen!A33 -> 43457 | B28: =SUM(77*C28) -> 34.3112 | C28: =SUM(Gen!B33) -> 0.4456 | D28: =SUM('Summery Report'!E27) -> 35 | E28: =SUM(E27) -> 1.3262195 | F28: =SUM(J28*E28)/D28 -> 90.011276 | G28: =SUM(L28*E28)/D28 -> 93.569713 | H28: =SUM(Gen!C33) -> #REF! | I28: =SUM(Gen!D33) -> 0 | J28: =SUM(Gen!S33) -> 2375.47 | K28: =Gen!AJ33 -> 93.91 | L28: =SUM(J28:K28) -> 2469.38 | M28: ='Water-Meter'!D28 -> 175621 | N28: ='Water-Meter'!E28 -> 131 | P28: 17164 | Q28: =SUM(P28-P27) -> 0 | R28: =SUM(Q28*O28) -> 0 | T28: 15128 | U28: =T28-T27 -> 0 | V28: =SUM(U28*S28) -> 0 | W28: 2.4 | X28: 17749 | Y28: =X28-X27 -> 11 | Z28: =SUM(Y28*W28) -> 26.4 | AA28: =SUM(Z28*X30) -> 468784.8 | AB28: 98175 | AC28: =SUM(AB28-AB27) -> 30 | AD28: 179541 | AE28: =SUM(AF28/N28) -> 0.57251908 | AF28: =AD28-AD27 -> 75 | AG28: ='Lpg (2)'!B31*2000/85 -> 2000 | AH28: ='Lpg (2)'!C31*1000/85 -> 129.41176 | AI28: ='Lpg (2)'!D31*1000/85 -> 0 | AJ28: =SUM(AG28*2000)+(AH28*1000)+(AI28*1000) -> 4129411.8 | AK28: =SUM(AJ27-AJ28) -> 47058.824
A29: =Gen!A34 -> 43458 | B29: =SUM(77*C29) -> 39.0005 | C29: =SUM(Gen!B34) -> 0.5065 | D29: =SUM('Summery Report'!E28) -> 40 | E29: =SUM(E28) -> 1.3262195 | F29: =SUM(J29*E29)/D29 -> 89.794345 | G29: =SUM(L29*E29)/D29 -> 115.86351 | H29: =SUM(Gen!C34) -> #REF! | I29: =SUM(Gen!D34) -> 0 | J29: =SUM(Gen!S34) -> 2708.28 | K29: =Gen!AJ34 -> 786.27 | L29: =SUM(J29:K29) -> 3494.55 | M29: ='Water-Meter'!D29 -> 175733 | N29: ='Water-Meter'!E29 -> 112 | P29: 17164 | Q29: =SUM(P29-P28) -> 0 | R29: =SUM(Q29*O29) -> 0 | T29: 15128 | U29: =T29-T28 -> 0 | V29: =SUM(U29*S29) -> 0 | X29: 17749 | Y29: =X29-X28 -> 0 | Z29: =SUM(Y29*W29) -> 0 | AA29: =SUM(Z29*X31) -> 0 | AB29: 98175 | AC29: =SUM(AB29-AB28) -> 0 | AD29: 179618 | AE29: =SUM(AF29/N29) -> 0.6875 | AF29: =AD29-AD28 -> 77 | AG29: ='Lpg (2)'!B32*2000/85 -> 2000 | AH29: ='Lpg (2)'!C32*1000/85 -> 82.352941 | AI29: ='Lpg (2)'!D32*1000/85 -> 0 | AJ29: =SUM(AG29*2000)+(AH29*1000)+(AI29*1000) -> 4082352.9 | AK29: =SUM(AJ28-AJ29) -> 47058.824
A30: =Gen!A35 -> 43459 | B30: =SUM(77*C30) -> 73.0037 | C30: =SUM(Gen!B35) -> 0.9481 | D30: =SUM('Summery Report'!E29) -> 73 | E30: =SUM(E29) -> 1.3262195 | F30: =SUM(J30*E30)/D30 -> 51.057634 | G30: =SUM(L30*E30)/D30 -> 54.226754 | H30: =SUM(Gen!C35) -> #REF! | I30: =SUM(Gen!D35) -> 0 | J30: =SUM(Gen!S35) -> 2810.4 | K30: =Gen!AJ35 -> 174.44 | L30: =SUM(J30:K30) -> 2984.84 | M30: ='Water-Meter'!D30 -> 175880 | N30: ='Water-Meter'!E30 -> 147 | P30: 17164 | Q30: =SUM(P30-P29) -> 0 | R30: =SUM(Q30*O30) -> 0 | T30: 15128 | U30: =T30-T29 -> 0 | V30: =SUM(U30*S30) -> 0 | W30: 2.3 | X30: 17757 | Y30: =X30-X29 -> 8 | Z30: =SUM(Y30*W30) -> 18.4 | AA30: =SUM(Z30*X32) -> 326765.6 | AB30: 98196 | AC30: =SUM(AB30-AB29) -> 21 | AD30: 179691 | AE30: =SUM(AF30/N30) -> 0.49659864 | AF30: =AD30-AD29 -> 73 | AG30: ='Lpg (2)'!B33*2000/85 -> 2000 | AH30: ='Lpg (2)'!C33*1000/85 -> 47.058824 | AI30: ='Lpg (2)'!D33*1000/85 -> 0 | AJ30: =SUM(AG30*2000)+(AH30*1000)+(AI30*1000) -> 4047058.8 | AK30: =SUM(AJ29-AJ30) -> 35294.118
A31: =Gen!A36 -> 43460 | B31: =SUM(77*C31) -> 70.0007 | C31: =SUM(Gen!B36) -> 0.9091 | D31: =SUM('Summery Report'!E30) -> 70 | E31: =SUM(E30) -> 1.3262195 | F31: =SUM(J31*E31)/D31 -> 54.289743 | G31: =SUM(L31*E31)/D31 -> 61.036032 | H31: =SUM(Gen!C36) -> #REF! | I31: =SUM(Gen!D36) -> 0 | J31: =SUM(Gen!S36) -> 2865.5 | K31: =Gen!AJ36 -> 356.08 | L31: =SUM(J31:K31) -> 3221.58 | M31: ='Water-Meter'!D31 -> 176047 | N31: ='Water-Meter'!E31 -> 167 | P31: 17164 | Q31: =SUM(P31-P30) -> 0 | R31: =SUM(Q31*O31) -> 0 | T31: 15128 | U31: =T31-T30 -> 0 | V31: =SUM(U31*S31) -> 0 | X31: 17757 | Y31: =X31-X30 -> 0 | Z31: =SUM(Y31*W31) -> 0 | AA31: =SUM(Z31*X33) -> 0 | AB31: 98196 | AC31: =SUM(AB31-AB30) -> 0 | AD31: 179765 | AE31: =SUM(AF31/N31) -> 0.44311377 | AF31: =AD31-AD30 -> 74 | AG31: ='Lpg (2)'!B34*2000/85 -> 2000 | AH31: ='Lpg (2)'!C34*1000/85 -> #VALUE! | AI31: ='Lpg (2)'!D34*1000/85 -> 0 | AJ31: =SUM(AG31*2000)+(AH31*1000)+(AI31*1000) -> #VALUE! | AK31: =SUM(AJ30-AJ31) -> #VALUE!
A32: =Gen!A37 -> 43461 | B32: =SUM(77*C32) -> 58.9974 | C32: =SUM(Gen!B37) -> 0.7662 | D32: =SUM('Summery Report'!E31) -> 60 | E32: =SUM(E31) -> 1.3262195 | F32: =SUM(J32*E32)/D32 -> 58.250655 | G32: =SUM(L32*E32)/D32 -> 62.75295 | H32: =SUM(Gen!C37) -> #REF! | I32: =SUM(Gen!D37) -> 0 | J32: =SUM(Gen!S37) -> 2635.34 | K32: =Gen!AJ37 -> 203.69 | L32: =SUM(J32:K32) -> 2839.03 | M32: ='Water-Meter'!D32 -> 176206 | N32: ='Water-Meter'!E32 -> 159 | P32: 17164 | Q32: =SUM(P32-P31) -> 0 | R32: =SUM(Q32*O32) -> 0 | T32: 15128 | U32: =T32-T31 -> 0 | V32: =SUM(U32*S32) -> 0 | X32: 17759 | Y32: =X32-X31 -> 2 | Z32: =SUM(Y32*W32) -> 0 | AA32: =SUM(Z32*X34) -> 0 | AB32: 98202 | AC32: =SUM(AB32-AB31) -> 6 | AD32: 179839 | AE32: =SUM(AF32/N32) -> 0.46540881 | AF32: =AD32-AD31 -> 74 | AG32: ='Lpg (2)'!B35*2000/85 -> 2000 | AH32: ='Lpg (2)'!C35*1000/85 -> 0 | AI32: ='Lpg (2)'!D35*1000/85 -> 0 | AJ32: =SUM(AG32*2000)+(AH32*1000)+(AI32*1000) -> 4000000 | AK32: =SUM(AJ31-AJ32) -> #VALUE!
A33: =Gen!A38 -> 43462 | B33: =SUM(77*C33) -> 59.9984 | C33: =SUM(Gen!B38) -> 0.7792 | D33: =SUM('Summery Report'!E32) -> 62 | E33: =SUM(E32) -> 1.3262195 | F33: =SUM(J33*E33)/D33 -> 65.098982 | G33: =SUM(L33*E33)/D33 -> 71.975002 | H33: =SUM(Gen!C38) -> #REF! | I33: =SUM(Gen!D38) -> 12000 | J33: =SUM(Gen!S38) -> 3043.34 | K33: =Gen!AJ38 -> 321.45 | L33: =SUM(J33:K33) -> 3364.79 | M33: ='Water-Meter'!D33 -> 176370 | N33: ='Water-Meter'!E33 -> 164 | P33: 17164 | Q33: =SUM(P33-P32) -> 0 | R33: =SUM(Q33*O33) -> 0 | T33: 15128 | U33: =T33-T32 -> 0 | V33: =SUM(U33*S33) -> 0 | W33: 2.9 | X33: 17763 | Y33: =X33-X32 -> 4 | Z33: =SUM(Y33*W33) -> 11.6 | AA33: =SUM(Z33*X35) -> 206352.4 | AB33: 98213 | AC33: =SUM(AB33-AB32) -> 11 | AD33: 179911 | AE33: =SUM(AF33/N33) -> 0.43902439 | AF33: =AD33-AD32 -> 72 | AG33: ='Lpg (2)'!B36*2000/85 -> 1952.9412 | AH33: ='Lpg (2)'!C36*1000/85 -> 0 | AI33: ='Lpg (2)'!D36*1000/85 -> 0 | AJ33: =SUM(AG33*2000)+(AH33*1000)+(AI33*1000) -> 3905882.4 | AK33: =SUM(AJ32-AJ33) -> 94117.647
A34: =Gen!A39 -> 43463 | B34: =SUM(77*C34) -> 71.0017 | C34: =SUM(Gen!B39) -> 0.9221 | D34: =SUM('Summery Report'!E33) -> 73 | E34: =SUM(E33) -> 1.3262195 | F34: =SUM(J34*E34)/D34 -> 52.176382 | G34: =SUM(L34*E34)/D34 -> 56.664455 | H34: =SUM(Gen!C39) -> #REF! | I34: =SUM(Gen!D39) -> 0 | J34: =SUM(Gen!S39) -> 2871.98 | K34: =Gen!AJ39 -> 247.04 | L34: =SUM(J34:K34) -> 3119.02 | M34: ='Water-Meter'!D34 -> 176543 | N34: ='Water-Meter'!E34 -> 173 | P34: 17168 | Q34: =SUM(P34-P33) -> 4 | R34: =SUM(Q34*O34) -> 0 | T34: 15128 | U34: =T34-T33 -> 0 | V34: =SUM(U34*S34) -> 0 | W34: 3 | X34: 17770 | Y34: =X34-X33 -> 7 | Z34: =SUM(Y34*W34) -> 21 | AA34: =SUM(Z34*X36) -> 0 | AB34: 98235 | AC34: =SUM(AB34-AB33) -> 22 | AD34: 179981 | AE34: =SUM(AF34/N34) -> 0.40462428 | AF34: =AD34-AD33 -> 70 | AG34: ='Lpg (2)'!B37*2000/85 -> 1882.3529 | AH34: ='Lpg (2)'!C37*1000/85 -> 0 | AI34: ='Lpg (2)'!D37*1000/85 -> 0 | AJ34: =SUM(AG34*2000)+(AH34*1000)+(AI34*1000) -> 3764705.9 | AK34: =SUM(AJ33-AJ34) -> 141176.47
A35: =Gen!A40 -> 43464 | B35: =SUM(77*C35) -> 59.9984 | C35: =SUM(Gen!B40) -> 0.7792 | D35: =SUM('Summery Report'!E34) -> 61 | E35: =SUM(E34) -> 1.3262195 | F35: =SUM(J35*E35)/D35 -> 68.974503 | G35: =SUM(L35*E35)/D35 -> 71.586068 | H35: =SUM(Gen!C40) -> #REF! | I35: =SUM(Gen!D40) -> 0 | J35: =SUM(Gen!S40) -> 3172.51 | K35: =Gen!AJ40 -> 120.12 | L35: =SUM(J35:K35) -> 3292.63 | M35: ='Water-Meter'!D35 -> 176699 | N35: ='Water-Meter'!E35 -> 156 | Q35: =SUM(P35-P34) -> -17168 | R35: =SUM(Q35*O35) -> 0 | U35: =T35-T34 -> -15128 | V35: =SUM(U35*S35) -> 0 | X35: 17789 | Y35: =X35-X34 -> 19 | Z35: =SUM(Y35*W35) -> 0 | AA35: =SUM(Z35*X37) -> 0 | AB35: 98310 | AC35: =SUM(AB35-AB34) -> 75 | AD35: 180052 | AE35: =SUM(AF35/N35) -> 0.45512821 | AF35: =AD35-AD34 -> 71 | AG35: ='Lpg (2)'!B38*2000/85 -> 1858.8235 | AH35: ='Lpg (2)'!C38*1000/85 -> 0 | AI35: ='Lpg (2)'!D38*1000/85 -> 0 | AJ35: =SUM(AG35*2000)+(AH35*1000)+(AI35*1000) -> 3717647.1 | AK35: =SUM(AJ34-AJ35) -> 47058.824
A36: =Gen!A41 -> 43465 | B36: =SUM(77*C36) -> 65.0034 | C36: =SUM(Gen!B41) -> 0.8442 | D36: =SUM('Summery Report'!E35) -> 66 | E36: =SUM(E35) -> 1.3262195 | F36: =SUM(J36*E36)/D36 -> 61.463442 | G36: =SUM(L36*E36)/D36 -> 87.267253 | H36: =SUM(Gen!C41) -> #REF! | I36: =SUM(Gen!D41) -> 12000 | J36: =SUM(Gen!S41) -> 3058.76 | K36: =Gen!AJ41 -> 1284.14 | L36: =SUM(J36:K36) -> 4342.9 | M36: ='Water-Meter'!D36 -> 176819 | N36: ='Water-Meter'!E36 -> 120 | Q36: =SUM(P36-P35) -> 0 | R36: =SUM(Q36*O36) -> 0 | U36: =T36-T35 -> 0 | V36: =SUM(U36*S36) -> 0 | Y36: =X36-X35 -> -17789 | Z36: =SUM(Y36*W36) -> 0 | AA36: =SUM(Z36*X38) -> 0 | AC36: =SUM(AB36-AB35) -> -98310 | AE36: =SUM(AF36/N36) -> -1500.4333 | AF36: =AD36-AD35 -> -180052 | AG36: ='Lpg (2)'!B39*2000/85 -> 1788.2353 | AH36: ='Lpg (2)'!C39*1000/85 -> 0 | AI36: ='Lpg (2)'!D39*1000/85 -> 0 | AJ36: =SUM(AG36*1000)+(AH36*1000)+(AI36*2000) -> 1788235.3 | AK36: =SUM(AJ35-AJ36) -> 1929411.8
A37: Nb Day | B37: 0 | J37: =SUM(J6:J36) -> 71221.22 | L37: =SUM(J37:K37) -> 71221.22 | N37: ='Water-Meter'!E37 -> -176819 | AC37: =SUM(AB37-AB36) -> 0 | AE37: =SUM(AF37/N37) -> 0 | AF37: =AD37-AD36 -> 0 | AK37: =SUM(AK6:AK36) -> #VALUE! | AL37: =SUM(AL6:AL36) -> 0

Sheet Kit report
B1: KITCHEN THREE PHASE KWH METER READING | H1: KITCHEN WATER METER READING | M1: AMANI Restaurant WATER METER READING | T1: LAUNDRY THREE PHASE KWH METER READING | Y1: LAUNDRY WATER METER READING
A2: Occ % | B2: DATE | C2: READING TIME | D2: METER READING OPEN | E2: METER READING ClOSE | F2: UNIT USED Kwh | H2: DATE | I2: READING TIME | J2: METER READING OPEN Cbm | K2: METER READING ClOSE Cbm | L2: UNIT USED Cbm | M2: DATE | N2: READING TIME | O2: METER READING OPEN Cbm | P2: METER READING ClOSE Cbm | Q2: UNIT USED Cbm | R2: Cost Per day Elct+Water $ | S2: % as per the total Lodge consumption | T2: DATE | U2: READING TIME | V2: METER READING OPEN (Kwh) | W2: METER READING ClOSE (Kwh) | X2: UNIT USED Kwh | Y2: DATE | Z2: READING TIME | AA2: METER READING OPEN Cbm | AB2: METER READING ClOSE Cbm | AC2: UNIT USED Cbm
A3: 43070 | B3: Close Last Month | F3: X120 | H3: Close Last Month | K3: ='Water-Meter'!G5 -> 31114 | M3: Close Last Month | P3: ='Water-Meter'!J5 -> 6197 | T3: Close Last Month | W3: 5758.8 | X3: =(W3-V3)*200 -> 1151760 | Y3: Close Last Month | AB3: ='Water-Meter'!P5 -> 15270
A4: =Gen!B11 -> 0.168 | B4: =Gen!A11 -> 43435 | D4: =E3 -> 0 | E4: 6968.7 | F4: =SUM(E4-D4)*120 -> 836244 | H4: =B4 -> 43435 | J4: =SUM(K3) -> 31114 | K4: ='Water-Meter'!G6 -> 31126 | L4: =SUM(K4-J4) -> 12 | M4: =H4 -> 43435 | O4: =SUM(P3) -> 6197 | P4: ='Water-Meter'!J6 -> 6201 | Q4: =SUM(P4-O4) -> 4 | R4: =SUM(Q4/1615) -> 0.0024767802 | S4: =SUM(F4/Gen!T10) -> #DIV/0! | T4: =M4 -> 43435 | V4: =W3 -> 5758.8 | W4: 5760.4 | X4: =(W4-V4)*200 -> 320 | Y4: =T4 -> 43435 | AA4: 3397.9 | AB4: ='Water-Meter'!P6 -> 15280 | AC4: =SUM(AB4-AA4) -> 11882.1
A5: =Gen!B12 -> 0.1429 | B5: =Gen!A12 -> 43436 | D5: =E4 -> 6968.7 | E5: 6971.2 | F5: =SUM(E5-D5)*120 -> 300 | H5: =B5 -> 43436 | J5: =SUM(K4) -> 31126 | K5: ='Water-Meter'!G7 -> 31137 | L5: =SUM(K5-J5) -> 11 | M5: =H5 -> 43436 | O5: =SUM(P4) -> 6201 | P5: ='Water-Meter'!J7 -> 6204 | Q5: =SUM(P5-O5) -> 3 | R5: =SUM(Q5/1615) -> 0.0018575851 | S5: =SUM(F5/Gen!T11) -> 0.06586169 | T5: =M5 -> 43436 | V5: =W4 -> 5760.4 | W5: 5762.7 | X5: =(W5-V5)*200 -> 460 | Y5: =T5 -> 43436 | AA5: =SUM(AB4) -> 15280 | AB5: ='Water-Meter'!P7 -> 15292 | AC5: =SUM(AB5-AA5) -> 12
A6: =Gen!B13 -> 0.1429 | B6: =Gen!A13 -> 43437 | D6: =E5 -> 6971.2 | E6: 6973.3 | F6: =SUM(E6-D6)*120 -> 252 | H6: =B6 -> 43437 | J6: =SUM(K5) -> 31137 | K6: ='Water-Meter'!G8 -> 31148 | L6: =SUM(K6-J6) -> 11 | M6: =H6 -> 43437 | O6: =SUM(P5) -> 6204 | P6: ='Water-Meter'!J8 -> 6207 | Q6: =SUM(P6-O6) -> 3 | R6: =SUM(Q6/1615) -> 0.0018575851 | S6: =SUM(F6/Gen!T12) -> 0.053857662 | T6: =M6 -> 43437 | V6: =W5 -> 5762.7 | W6: 5764.3 | X6: =(W6-V6)*200 -> 320 | Y6: =T6 -> 43437 | AA6: =SUM(AB5) -> 15292 | AB6: ='Water-Meter'!P8 -> 15305 | AC6: =SUM(AB6-AA6) -> 13
A7: =Gen!B14 -> 0.1688 | B7: =Gen!A14 -> 43438 | D7: =E6 -> 6973.3 | E7: 6975.9 | F7: =SUM(E7-D7)*120 -> 312 | H7: =B7 -> 43438 | J7: =SUM(K6) -> 31148 | K7: ='Water-Meter'!G9 -> 31160 | L7: =SUM(K7-J7) -> 12 | M7: =H7 -> 43438 | O7: =SUM(P6) -> 6207 | P7: ='Water-Meter'!J9 -> 6210 | Q7: =SUM(P7-O7) -> 3 | R7: =SUM(Q7/1615) -> 0.0018575851 | S7: =SUM(F7/Gen!T13) -> 0.070317782 | T7: =M7 -> 43438 | V7: =W6 -> 5764.3 | W7: 5766.9 | X7: =(W7-V7)*200 -> 520 | Y7: =T7 -> 43438 | AA7: =SUM(AB6) -> 15305 | AB7: ='Water-Meter'!P9 -> 15317 | AC7: =SUM(AB7-AA7) -> 12
A8: =Gen!B15 -> 0.2078 | B8: =Gen!A15 -> 43439 | D8: =E7 -> 6975.9 | E8: 6978.5 | F8: =SUM(E8-D8)*120 -> 312 | H8: =B8 -> 43439 | J8: =SUM(K7) -> 31160 | K8: ='Water-Meter'!G10 -> 31172 | L8: =SUM(K8-J8) -> 12 | M8: =H8 -> 43439 | O8: =SUM(P7) -> 6210 | P8: ='Water-Meter'!J10 -> 6213 | Q8: =SUM(P8-O8) -> 3 | R8: =SUM(Q8/1615) -> 0.0018575851 | S8: =SUM(F8/Gen!T14) -> 0.066467831 | T8: =M8 -> 43439 | V8: =W7 -> 5766.9 | W8: 5769.1 | X8: =(W8-V8)*200 -> 440 | Y8: =T8 -> 43439 | AA8: =SUM(AB7) -> 15317 | AB8: ='Water-Meter'!P10 -> 15326 | AC8: =SUM(AB8-AA8) -> 9
A9: =Gen!B16 -> 0.2987 | B9: =Gen!A16 -> 43440 | D9: =E8 -> 6978.5 | E9: 6981.1 | F9: =SUM(E9-D9)*120 -> 312 | H9: =B9 -> 43440 | J9: =SUM(K8) -> 31172 | K9: ='Water-Meter'!G11 -> 31186 | L9: =SUM(K9-J9) -> 14 | M9: =H9 -> 43440 | O9: =SUM(P8) -> 6213 | P9: ='Water-Meter'!J11 -> 6216 | Q9: =SUM(P9-O9) -> 3 | R9: =SUM(Q9/1615) -> 0.0018575851 | S9: =SUM(F9/Gen!T15) -> 0.07157605 | T9: =M9 -> 43440 | V9: =W8 -> 5769.1 | W9: 5771.7 | X9: =(W9-V9)*200 -> 520 | Y9: =T9 -> 43440 | AA9: =SUM(AB8) -> 15326 | AB9: ='Water-Meter'!P11 -> 15336 | AC9: =SUM(AB9-AA9) -> 10
A10: =Gen!B17 -> 0.2468 | B10: =Gen!A17 -> 43441 | D10: =E9 -> 6981.1 | E10: 6983.2 | F10: =SUM(E10-D10)*120 -> 252 | H10: =B10 -> 43441 | J10: =SUM(K9) -> 31186 | K10: ='Water-Meter'!G12 -> 31199 | L10: =SUM(K10-J10) -> 13 | M10: =H10 -> 43441 | O10: =SUM(P9) -> 6216 | P10: ='Water-Meter'!J12 -> 6220 | Q10: =SUM(P10-O10) -> 4 | R10: =SUM(Q10/1615) -> 0.0024767802 | S10: =SUM(F10/Gen!T16) -> 0.053503185 | T10: =M10 -> 43441 | V10: =W9 -> 5771.7 | W10: 5773.8 | X10: =(W10-V10)*200 -> 420 | Y10: =T10 -> 43441 | AA10: =SUM(AB9) -> 15336 | AB10: ='Water-Meter'!P12 -> 15348 | AC10: =SUM(AB10-AA10) -> 12 | AH10: 5850
A11: =Gen!B18 -> 0.2857 | B11: =Gen!A18 -> 43442 | D11: =E10 -> 6983.2 | E11: 6985.5 | F11: =SUM(E11-D11)*120 -> 276 | H11: =B11 -> 43442 | J11: =SUM(K10) -> 31199 | K11: ='Water-Meter'!G13 -> 31213 | L11: =SUM(K11-J11) -> 14 | M11: =H11 -> 43442 | O11: =SUM(P10) -> 6220 | P11: ='Water-Meter'!J13 -> 6223 | Q11: =SUM(P11-O11) -> 3 | R11: =SUM(Q11/1615) -> 0.0018575851 | S11: =SUM(F11/Gen!T17) -> 0.056615385 | T11: =M11 -> 43442 | V11: =W10 -> 5773.8 | W11: 5776.4 | X11: =(W11-V11)*200 -> 520 | Y11: =T11 -> 43442 | AA11: =SUM(AB10) -> 15348 | AB11: ='Water-Meter'!P13 -> 15352 | AC11: =SUM(AB11-AA11) -> 4
A12: =Gen!B19 -> 0.4675 | B12: =Gen!A19 -> 43443 | D12: =E11 -> 6985.5 | E12: 6987.9 | F12: =SUM(E12-D12)*120 -> 288 | H12: =B12 -> 43443 | J12: =SUM(K11) -> 31213 | K12: ='Water-Meter'!G14 -> 31228 | L12: =SUM(K12-J12) -> 15 | M12: =H12 -> 43443 | O12: =SUM(P11) -> 6223 | P12: ='Water-Meter'!J14 -> 6226 | Q12: =SUM(P12-O12) -> 3 | R12: =SUM(Q12/1615) -> 0.0018575851 | S12: =SUM(F12/Gen!T18) -> 0.059987503 | T12: =M12 -> 43443 | V12: =W11 -> 5776.4 | W12: 5779.6 | X12: =(W12-V12)*200 -> 640 | Y12: =T12 -> 43443 | AA12: =SUM(AB11) -> 15352 | AB12: ='Water-Meter'!P14 -> 15361
A13: =Gen!B20 -> 0.5584 | B13: =Gen!A20 -> 43444 | D13: =E12 -> 6987.9 | E13: 6990.1 | F13: =SUM(E13-D13)*120 -> 264 | H13: =B13 -> 43444 | J13: =SUM(K12) -> 31228 | K13: ='Water-Meter'!G15 -> 31244 | L13: =SUM(K13-J13) -> 16 | M13: =H13 -> 43444 | O13: =SUM(P12) -> 6226 | P13: ='Water-Meter'!J15 -> 6235 | Q13: =SUM(P13-O13) -> 9 | R13: =SUM(Q13/1615) -> 0.0055727554 | S13: =SUM(F13/Gen!T19) -> 0.053778774 | T13: =M13 -> 43444 | V13: =W12 -> 5779.6 | W13: 5783.3 | X13: =(W13-V13)*200 -> 740 | Y13: =T13 -> 43444 | AA13: =SUM(AB12) -> 15361 | AB13: ='Water-Meter'!P15 -> 15382 | AC13: =SUM(AB13-AA13) -> 21
A14: =Gen!B21 -> 0.5714 | B14: =Gen!A21 -> 43445 | D14: =E13 -> 6990.1 | E14: 6992.4 | F14: =SUM(E14-D14)*120 -> 276 | H14: =B14 -> 43445 | J14: =SUM(K13) -> 31244 | K14: ='Water-Meter'!G16 -> 31259 | L14: =SUM(K14-J14) -> 15 | M14: =H14 -> 43445 | O14: =SUM(P13) -> 6235 | P14: ='Water-Meter'!J16 -> 6239 | Q14: =SUM(P14-O14) -> 4 | R14: =SUM(Q14/1615) -> 0.0024767802 | S14: =SUM(F14/Gen!T20) -> 0.051918736 | T14: =M14 -> 43445 | V14: =W13 -> 5783.3 | W14: 5787.7 | X14: =(W14-V14)*200 -> 880 | Y14: =T14 -> 43445 | AA14: =SUM(AB13) -> 15382 | AB14: ='Water-Meter'!P16 -> 15395 | AC14: =SUM(AB14-AA14) -> 13
A15: =Gen!B22 -> 0.2338 | B15: =Gen!A22 -> 43446 | D15: =E14 -> 6992.4 | E15: 6994.6 | F15: =SUM(E15-D15)*120 -> 264 | H15: =B15 -> 43446 | J15: =SUM(K14) -> 31259 | K15: ='Water-Meter'!G17 -> 31273 | L15: =SUM(K15-J15) -> 14 | M15: =H15 -> 43446 | O15: =SUM(P14) -> 6239 | P15: ='Water-Meter'!J17 -> 6244 | Q15: =SUM(P15-O15) -> 5 | R15: =SUM(Q15/1615) -> 0.0030959752 | S15: =SUM(F15/Gen!T21) -> 0.053636733 | T15: =M15 -> 43446 | V15: =W14 -> 5787.7 | W15: 5790.7 | X15: =(W15-V15)*200 -> 600 | Y15: =T15 -> 43446 | AA15: =SUM(AB14) -> 15395 | AB15: ='Water-Meter'!P17 -> 15410 | AC15: =SUM(AB15-AA15) -> 15
A16: =Gen!B23 -> 0.2727 | B16: =Gen!A23 -> 43447 | D16: =E15 -> 6994.6 | E16: 6996.9 | F16: =SUM(E16-D16)*120 -> 276 | H16: =B16 -> 43447 | J16: =SUM(K15) -> 31273 | K16: ='Water-Meter'!G18 -> 31288 | L16: =SUM(K16-J16) -> 15 | M16: =H16 -> 43447 | O16: =SUM(P15) -> 6244 | P16: ='Water-Meter'!J18 -> 6246 | Q16: =SUM(P16-O16) -> 2 | R16: =SUM(Q16/1615) -> 0.0012383901 | S16: =SUM(F16/Gen!T22) -> 0.056673511 | T16: =M16 -> 43447 | V16: =W15 -> 5790.7 | W16: 5793.6 | X16: =(W16-V16)*200 -> 580 | Y16: =T16 -> 43447 | AA16: =SUM(AB15) -> 15410 | AB16: ='Water-Meter'!P18 -> 15421 | AC16: =SUM(AB16-AA16) -> 11
A17: =Gen!B24 -> 0.2595 | B17: =Gen!A24 -> 43448 | D17: =E16 -> 6996.9 | E17: 6999.3 | F17: =SUM(E17-D17)*120 -> 288 | H17: =B17 -> 43448 | J17: =SUM(K16) -> 31288 | K17: ='Water-Meter'!G19 -> 31303 | L17: =SUM(K17-J17) -> 15 | M17: =H17 -> 43448 | O17: =SUM(P16) -> 6246 | P17: ='Water-Meter'!J19 -> 6249 | Q17: =SUM(P17-O17) -> 3 | R17: =SUM(Q17/1615) -> 0.0018575851 | S17: =SUM(F17/Gen!T23) -> 0.061802575 | T17: =M17 -> 43448 | V17: =W16 -> 5793.6 | W17: 5797.8 | X17: =(W17-V17)*200 -> 840 | Y17: =T17 -> 43448 | AA17: =SUM(AB16) -> 15421 | AB17: ='Water-Meter'!P19 -> 15442 | AC17: =SUM(AB17-AA17) -> 21
A18: =Gen!B25 -> 0.1299 | B18: =Gen!A25 -> 43449 | D18: =E17 -> 6999.3 | E18: 7001.4 | F18: =SUM(E18-D18)*120 -> 252 | H18: =B18 -> 43449 | J18: =SUM(K17) -> 31303 | K18: ='Water-Meter'!G20 -> 31316 | L18: =SUM(K18-J18) -> 13 | M18: =H18 -> 43449 | O18: =SUM(P17) -> 6249 | P18: ='Water-Meter'!J20 -> 6254 | Q18: =SUM(P18-O18) -> 5 | R18: =SUM(Q18/1615) -> 0.0030959752 | S18: =SUM(F18/Gen!T24) -> 0.053074979 | T18: =M18 -> 43449 | V18: =W17 -> 5797.8 | W18: 5800.9 | X18: =(W18-V18)*200 -> 620 | Y18: =T18 -> 43449 | AA18: =SUM(AB17) -> 15442 | AB18: ='Water-Meter'!P20 -> 15329 | AC18: =SUM(AB18-AA18) -> -113
A19: =Gen!B26 -> 0.2597 | B19: =Gen!A26 -> 43450 | D19: =E18 -> 7001.4 | E19: 7003.7 | F19: =SUM(E19-D19)*120 -> 276 | H19: =B19 -> 43450 | J19: =SUM(K18) -> 31316 | K19: ='Water-Meter'!G21 -> 31330 | L19: =SUM(K19-J19) -> 14 | M19: =H19 -> 43450 | O19: =SUM(P18) -> 6254 | P19: ='Water-Meter'!J21 -> 6257 | Q19: =SUM(P19-O19) -> 3 | R19: =SUM(Q19/1615) -> 0.0018575851 | S19: =SUM(F19/Gen!T25) -> 0.058425064 | T19: =M19 -> 43450 | V19: =W18 -> 5800.9 | W19: 5803.2 | X19: =(W19-V19)*200 -> 460 | Y19: =T19 -> 43450 | AA19: =SUM(AB18) -> 15329 | AB19: ='Water-Meter'!P21 -> 15316 | AC19: =SUM(AB19-AA19) -> -13
A20: =Gen!B27 -> 0.2987 | B20: =Gen!A27 -> 43451 | D20: =E19 -> 7003.7 | E20: 7005.7 | F20: =SUM(E20-D20)*120 -> 240 | H20: =B20 -> 43451 | J20: =SUM(K19) -> 31330 | K20: ='Water-Meter'!G22 -> 31343 | L20: =SUM(K20-J20) -> 13 | M20: =H20 -> 43451 | O20: =SUM(P19) -> 6257 | P20: ='Water-Meter'!J22 -> 6260 | Q20: =SUM(P20-O20) -> 3 | R20: =SUM(Q20/1615) -> 0.0018575851 | S20: =SUM(F20/Gen!T26) -> 0.047952048 | T20: =M20 -> 43451 | V20: =W19 -> 5803.2 | W20: 5806.5 | X20: =(W20-V20)*200 -> 660 | Y20: =T20 -> 43451 | AA20: =SUM(AB19) -> 15316 | AB20: ='Water-Meter'!P22 -> 15328 | AC20: =SUM(AB20-AA20) -> 12
A21: =Gen!B28 -> 0.5065 | B21: =Gen!A28 -> 43452 | D21: =E20 -> 7005.7 | E21: 7008.2 | F21: =SUM(E21-D21)*120 -> 300 | H21: =B21 -> 43452 | J21: =SUM(K20) -> 31343 | K21: ='Water-Meter'!G23 -> 31358 | L21: =SUM(K21-J21) -> 15 | M21: =H21 -> 43452 | O21: =SUM(P20) -> 6260 | P21: ='Water-Meter'!J23 -> 6264 | Q21: =SUM(P21-O21) -> 4 | R21: =SUM(Q21/1615) -> 0.0024767802 | S21: =SUM(F21/Gen!T28) -> 0.050933786 | T21: =M21 -> 43452 | V21: =W20 -> 5806.5 | W21: 5810.5 | X21: =(W21-V21)*200 -> 800 | Y21: =T21 -> 43452 | AA21: =SUM(AB20) -> 15328 | AB21: ='Water-Meter'!P23 -> 15341 | AC21: =SUM(AB21-AA21) -> 13
A22: =Gen!B29 -> 0.4416 | B22: =Gen!A29 -> 43453 | D22: =E21 -> 7008.2 | E22: 7010.2 | F22: =SUM(E22-D22)*120 -> 240 | H22: =B22 -> 43453 | J22: =SUM(K21) -> 31358 | K22: ='Water-Meter'!G24 -> 31384 | L22: =SUM(K22-J22) -> 26 | M22: =H22 -> 43453 | O22: =SUM(P21) -> 6264 | P22: ='Water-Meter'!J24 -> 6269 | Q22: =SUM(P22-O22) -> 5 | R22: =SUM(Q22/1615) -> 0.0030959752 | S22: =SUM(F22/Gen!T29) -> 0.041833711 | T22: =M22 -> 43453 | V22: =W21 -> 5810.5 | W22: 5814.4 | X22: =(W22-V22)*200 -> 780 | Y22: =T22 -> 43453 | AA22: =SUM(AB21) -> 15341 | AB22: ='Water-Meter'!P24 -> 15350 | AC22: =SUM(AB22-AA22) -> 9
A23: =Gen!B30 -> 0.4026 | B23: =Gen!A30 -> 43454 | D23: =E22 -> 7010.2 | E23: 7012.9 | F23: =SUM(E23-D23)*120 -> 324 | H23: =B23 -> 43454 | J23: =SUM(K22) -> 31384 | K23: ='Water-Meter'!G25 -> 31402 | L23: =SUM(K23-J23) -> 18 | M23: =H23 -> 43454 | O23: =SUM(P22) -> 6269 | P23: ='Water-Meter'!J25 -> 6273 | Q23: =SUM(P23-O23) -> 4 | R23: =SUM(Q23/1615) -> 0.0024767802 | S23: =SUM(F23/Gen!T30) -> 0.058043712 | T23: =M23 -> 43454 | V23: =W22 -> 5814.4 | W23: 5818.4 | X23: =(W23-V23)*200 -> 800 | Y23: =T23 -> 43454 | AA23: =SUM(AB22) -> 15350 | AB23: ='Water-Meter'!P25 -> 15367 | AC23: =SUM(AB23-AA23) -> 17
A24: =Gen!B31 -> 0.4935 | B24: =Gen!A31 -> 43455 | D24: =SUM(E23) -> 7012.9 | E24: 7015.4 | F24: =SUM(E24-D24)*120 -> 300 | H24: =B24 -> 43455 | J24: =SUM(K23) -> 31402 | K24: ='Water-Meter'!G26 -> 31420 | L24: =SUM(K24-J24) -> 18 | M24: =H24 -> 43455 | O24: =SUM(P23) -> 6273 | P24: ='Water-Meter'!J26 -> 6278 | Q24: =SUM(P24-O24) -> 5 | R24: =SUM(Q24/1615) -> 0.0030959752 | S24: =SUM(F24/Gen!T31) -> 0.053580997 | T24: 5835.7 | V24: =W23 -> 5818.4 | W24: 5822.4 | X24: =(W24-V24)*200 -> 800 | Y24: =T24 -> 5835.7 | AA24: =SUM(AB23) -> 15367 | AB24: ='Water-Meter'!P26 -> 15373 | AC24: =SUM(AB24-AA24) -> 6
A25: =Gen!B32 -> 0.4935 | B25: =Gen!A32 -> 43456 | D25: =SUM(E24) -> 7015.4 | E25: 7017.9 | F25: =SUM(E25-D25)*120 -> 300 | H25: =B25 -> 43456 | J25: =SUM(K24) -> 31420 | K25: ='Water-Meter'!G27 -> 31441 | L25: =SUM(K25-J25) -> 21 | M25: =H25 -> 43456 | O25: =SUM(P24) -> 6278 | P25: ='Water-Meter'!J27 -> 6282 | Q25: =SUM(P25-O25) -> 4 | R25: =SUM(Q25/1615) -> 0.0024767802 | S25: =SUM(F25/Gen!T32) -> 0.050607287 | T25: =M25 -> 43456 | V25: =W24 -> 5822.4 | W25: 5826.7 | X25: =(W25-V25)*200 -> 860 | Y25: =T25 -> 43456 | AA25: =SUM(AB24) -> 15373 | AB25: ='Water-Meter'!P27 -> 15382 | AC25: =SUM(AB25-AA25) -> 9
A26: =Gen!B33 -> 0.4456 | B26: =Gen!A33 -> 43457 | D26: =SUM(E25) -> 7017.9 | E26: 7020.3 | F26: =SUM(E26-D26)*120 -> 288 | H26: =B26 -> 43457 | J26: =SUM(K25) -> 31441 | K26: ='Water-Meter'!G28 -> 31463 | L26: =SUM(K26-J26) -> 22 | M26: =H26 -> 43457 | O26: =SUM(P25) -> 6282 | P26: ='Water-Meter'!J28 -> 6286 | Q26: =SUM(P26-O26) -> 4 | R26: =SUM(Q26/1615) -> 0.0024767802 | S26: =SUM(F26/Gen!T33) -> 0.049230769 | T26: =M26 -> 43457 | V26: =W25 -> 5826.7 | W26: 5832.2 | X26: =(W26-V26)*200 -> 1100 | Y26: =T26 -> 43457 | AA26: =SUM(AB25) -> 15382 | AB26: ='Water-Meter'!P28 -> 15391 | AC26: =SUM(AB26-AA26) -> 9
A27: =Gen!B34 -> 0.5065 | B27: =Gen!A34 -> 43458 | D27: =SUM(E26) -> 7020.3 | E27: 7022.8 | F27: =SUM(E27-D27)*120 -> 300 | H27: =B27 -> 43458 | J27: =SUM(K26) -> 31463 | K27: ='Water-Meter'!G29 -> 31480 | L27: =SUM(K27-J27) -> 17 | M27: =H27 -> 43458 | O27: =SUM(P26) -> 6286 | P27: ='Water-Meter'!J29 -> 6289 | Q27: =SUM(P27-O27) -> 3 | R27: =SUM(Q27/1615) -> 0.0018575851 | S27: =SUM(F27/Gen!T34) -> 0.048804295 | T27: =M27 -> 43458 | V27: =W26 -> 5832.2 | W27: 5838.1 | X27: =(W27-V27)*200 -> 1180 | Y27: =T27 -> 43458 | AA27: =SUM(AB26) -> 15391 | AB27: ='Water-Meter'!P29 -> 15401 | AC27: =SUM(AB27-AA27) -> 10
A28: =Gen!B35 -> 0.9481 | B28: =Gen!A35 -> 43459 | D28: =SUM(E27) -> 7022.8 | E28: 7025.5 | F28: =SUM(E28-D28)*120 -> 324 | H28: =B28 -> 43459 | J28: =SUM(K27) -> 31480 | K28: ='Water-Meter'!G30 -> 31504 | L28: =SUM(K28-J28) -> 24 | M28: =H28 -> 43459 | O28: =SUM(P27) -> 6289 | P28: ='Water-Meter'!J30 -> 6293 | Q28: =SUM(P28-O28) -> 4 | R28: =SUM(Q28/1615) -> 0.0024767802 | S28: =SUM(F28/Gen!T35) -> 0.050015437 | T28: =M28 -> 43459 | V28: =W27 -> 5838.1 | W28: 5843.6 | X28: =(W28-V28)*200 -> 1100 | Y28: =T28 -> 43459 | AA28: =SUM(AB27) -> 15401 | AB28: ='Water-Meter'!P30 -> 15421 | AC28: =SUM(AB28-AA28) -> 20
A29: =Gen!B36 -> 0.9091 | B29: =Gen!A36 -> 43460 | D29: =SUM(E28) -> 7025.5 | E29: 7028.1 | F29: =SUM(E29-D29)*120 -> 312 | H29: =B29 -> 43460 | J29: =SUM(K28) -> 31504 | K29: ='Water-Meter'!G31 -> 31527 | L29: =SUM(K29-J29) -> 23 | M29: =H29 -> 43460 | O29: =SUM(P28) -> 6293 | P29: ='Water-Meter'!J31 -> 6298 | Q29: =SUM(P29-O29) -> 5 | R29: =SUM(Q29/1615) -> 0.0030959752 | S29: =SUM(F29/Gen!T36) -> 0.047016275 | T29: =M29 -> 43460 | V29: =W28 -> 5843.6 | W29: 5848.8 | X29: =(W29-V29)*200 -> 1040 | Y29: =T29 -> 43460 | AA29: =SUM(AB28) -> 15421 | AB29: ='Water-Meter'!P31 -> 15442 | AC29: =SUM(AB29-AA29) -> 21
A30: =Gen!B37 -> 0.7662 | B30: =Gen!A37 -> 43461 | D30: =SUM(E29) -> 7028.1 | E30: 7030.8 | F30: =SUM(E30-D30)*120 -> 324 | H30: =B30 -> 43461 | J30: =SUM(K29) -> 31527 | K30: ='Water-Meter'!G32 -> 31549 | L30: =SUM(K30-J30) -> 22 | M30: =H30 -> 43461 | O30: =SUM(P29) -> 6298 | P30: ='Water-Meter'!J32 -> 6302 | Q30: =SUM(P30-O30) -> 4 | R30: =SUM(Q30/1615) -> 0.0024767802 | S30: =SUM(F30/Gen!T37) -> 0.049217682 | T30: =M30 -> 43461 | V30: =W29 -> 5848.8 | W30: 5855.3 | X30: =(W30-V30)*200 -> 1300 | Y30: =T30 -> 43461 | AA30: =SUM(AB29) -> 15442 | AB30: ='Water-Meter'!P32 -> 15464 | AC30: =SUM(AB30-AA30) -> 22
A31: =Gen!B38 -> 0.7792 | B31: =Gen!A38 -> 43462 | D31: =SUM(E30) -> 7030.8 | E31: 7033.7 | F31: =SUM(E31-D31)*120 -> 348 | H31: =B31 -> 43462 | J31: =SUM(K30) -> 31549 | K31: ='Water-Meter'!G33 -> 31571 | L31: =SUM(K31-J31) -> 22 | M31: =H31 -> 43462 | O31: =SUM(P30) -> 6302 | P31: ='Water-Meter'!J33 -> 6309 | Q31: =SUM(P31-O31) -> 7 | R31: =SUM(Q31/1615) -> 0.0043343653 | S31: =SUM(F31/Gen!T38) -> 0.04905554 | T31: =M31 -> 43462 | V31: =W30 -> 5855.3 | W31: 5861.2 | X31: =(W31-V31)*200 -> 1180 | Y31: =T31 -> 43462 | AA31: =SUM(AB30) -> 15464 | AB31: ='Water-Meter'!P33 -> 15487 | AC31: =SUM(AB31-AA31) -> 23
A32: =Gen!B39 -> 0.9221 | B32: =Gen!A39 -> 43463 | D32: =SUM(E31) -> 7033.7 | E32: 7036.5 | F32: =SUM(E32-D32)*120 -> 336 | H32: =B32 -> 43463 | J32: =SUM(K31) -> 31571 | K32: ='Water-Meter'!G34 -> 31595 | L32: =SUM(K32-J32) -> 24 | M32: =H32 -> 43463 | O32: =SUM(P31) -> 6309 | P32: ='Water-Meter'!J34 -> 6314 | Q32: =SUM(P32-O32) -> 5 | R32: =SUM(Q32/1615) -> 0.0030959752 | S32: =SUM(F32/Gen!T39) -> 0.044048243 | T32: =M32 -> 43463 | V32: =W31 -> 5861.2 | W32: 5867.3 | X32: =(W32-V32)*200 -> 1220 | Y32: =T32 -> 43463 | AA32: =SUM(AB31) -> 15487 | AB32: ='Water-Meter'!P34 -> 15511 | AC32: =SUM(AB32-AA32) -> 24
A33: =Gen!B40 -> 0.7792 | B33: =Gen!A40 -> 43464 | D33: =SUM(E32) -> 7036.5 | E33: 7039.3 | F33: =SUM(E33-D33)*120 -> 336 | H33: =B33 -> 43464 | J33: =SUM(K32) -> 31595 | K33: ='Water-Meter'!G35 -> 31616 | L33: =SUM(K33-J33) -> 21 | M33: =H33 -> 43464 | O33: =SUM(P32) -> 6314 | P33: ='Water-Meter'!J35 -> 6318 | Q33: =SUM(P33-O33) -> 4 | R33: =SUM(Q33/1615) -> 0.0024767802 | S33: =SUM(F33/Gen!T40) -> 0.045540797 | T33: =M33 -> 43464 | V33: =W32 -> 5867.3 | W33: 5872.5 | X33: =(W33-V33)*200 -> 1040 | Y33: =T33 -> 43464 | AA33: =SUM(AB32) -> 15511 | AB33: ='Water-Meter'!P35 -> 15522 | AC33: =SUM(AB33-AA33) -> 11
A34: =Gen!B41 -> 0.8442 | B34: =Gen!A41 -> 43465 | D34: =SUM(E33) -> 7039.3 | E34: 7042.2 | F34: =SUM(E34-D34)*120 -> 348 | H34: =B34 -> 43465 | J34: =SUM(K33) -> 31616 | K34: ='Water-Meter'!G36 -> 31642 | L34: =SUM(K34-J34) -> 26 | M34: =H34 -> 43465 | O34: =SUM(P33) -> 6318 | P34: ='Water-Meter'!J36 -> 6322 | Q34: =SUM(P34-O34) -> 4 | R34: =SUM(Q34/1615) -> 0.0024767802 | S34: =SUM(F34/Gen!T41) -> 0.047966919 | T34: =M34 -> 43465 | V34: =SUM(W33) -> 5872.5 | W34: 5878.1 | X34: =(W34-V34)*200 -> 1120 | Y34: =T34 -> 43465 | AA34: =SUM(AB33) -> 15522 | AB34: ='Water-Meter'!P36 -> 15533 | AC34: =SUM(AB34-AA34) -> 11
A35: =Gen!B42 -> 0 | B35: =Gen!A42 -> 0 | D35: =SUM(E34) -> 7042.2 | E35: 7045 | F35: =SUM(F5:F34) -> 8820 | H35: =B35 -> 0 | J35: =SUM(K34) -> 31642 | K35: ='Water-Meter'!G37 -> 0 | L35: =SUM(L5:L34) -> 516 | M35: =H35 -> 0 | O35: =SUM(P34) -> 6322 | P35: ='Water-Meter'!J37 -> 0 | Q35: =SUM(Q5:Q34) -> 121 | R35: =SUM(Q35/1615) -> 0.074922601 | S35: =SUM(F35/Gen!T42) -> #DIV/0! | T35: =M35 -> 0 | V35: =SUM(W34) -> 5878.1 | X35: =(W35-V35)*200 -> -1175620 | Y35: =T35 -> 0 | AA35: =SUM(AB34) -> 15533 | AB35: ='Water-Meter'!P37 -> 0 | AC35: =SUM(AC5:AC34) -> 244
L36: Total Exp | Q36: Total Exp | AC36: Total Exp
B37: Electrical | H37: Water | T37: Electrical | Y37: Water
B38: Cost | C38: 2856 | D38: =SUM(F35)*0.41 -> 3616.2 | E38: =SUM(C38*D38) -> 10327867 | H38: Cost | I38: 985 | J38: =SUM(L35) -> 516 | K38: =SUM(I38*J38) -> 508260 | T38: Cost | U38: 2856 | V38: =SUM(X35)*0.41 -> -482004.2 | W38: =SUM(U38*V38) -> -1.376604e+09 | Y38: Cost | Z38: 985 | AA38: =SUM(AC35) -> 244 | AB38: =SUM(Z38*AA38) -> 240340
W42: =SUM(A4:A14)/11 -> 0.29626364 | X42: =SUM(X4:X14)/11 -> 525.45455

Sheet Summery Report
A2: Generator and Diseal Summry Report 2018 | Q2: 29 | R2: Diesel Cost | S2: Rate$ | T2: 1582
M3: % of Gas balance in Tank | P3: % of Diesel balance in Tank | Q3: HLP Cost (TSH) | V3: Total Cost (TSH) | W3: Total utility
A4: Date | B4: Gen Set Hours Working | C4: Occ% | D4: Total OCC Room | E4: Guest Room Occ | F4: Total Kwh Generated | G4: Diesel consumed by Gen (Ltrs) | H4: Diesel consumed by Vehicle (Ltrs) | I4: Total diesel consumed (Ltrs) | J4: Balance stock of Diesel (Ltrs) | K4: Water consumed | L4: Gas consumed (KG) | M4: 3 | N4: 2 | O4: 1 | Q4: Electricity | R4: Cost per Room Total OOC Usd | S4: Cost per Room Guest OOC Usd | T4: Water | U4: Gas | W4: Cost Occ% | Y4: Budget per room Occ
A5: =Gen!A11 -> 43435 | B5: ='Daily report Gen'!Z6 -> 3035 | C5: =Gen!B11 -> 0.168 | D5: =E5 -> 15 | E5: 15 | F5: =Gen!T11 -> 4555 | G5: =Gen!S11 -> 1825.13 | H5: =Gen!AJ11 -> 42.79 | I5: =SUM(G5:H5) -> 1867.92 | J5: =Gen!AT11 -> #REF! | K5: ='Water-Meter'!E6 -> 99 | L5: ='Lpg (2)'!N10 -> 149.292 | M5: =#REF! -> #REF! | N5: =#REF! -> #REF! | O5: =#REF! -> #REF! | P5: =J5/52000 -> #REF! | Q5: =I5*Q2 -> 54169.68 | R5: =SUM(Q5/D5)/X5 -> 2.2827509 | S5: =SUM(Q5/E5)/X5 -> 2.2827509 | T5: =K5*102 -> 10098 | U5: =SUM(L5*1963) -> 293060.2 | V5: =SUM(Q5+T5+U5) -> 357327.88 | W5: =SUM(V5/E5)/T2 -> 15.058065 | X5: =SUM(T2) -> 1582 | Y5: 106 | Z5: =SUM(Y5-S5) -> 103.71725
A6: =Gen!A12 -> 43436 | B6: ='Daily report Gen'!Z7 -> 33 | C6: =Gen!B12 -> 0.1429 | D6: =E6 -> 13 | E6: 13 | F6: =Gen!T12 -> 4679 | G6: =Gen!S12 -> 1835.19 | H6: =Gen!AJ12 -> 90.6 | I6: =SUM(G6:H6) -> 1925.79 | J6: =Gen!AT12 -> #REF! | K6: ='Water-Meter'!E7 -> 100 | L6: ='Lpg (2)'!N11 -> 78.892 | M6: =#REF! -> #REF! | N6: =#REF! -> #REF! | O6: =#REF! -> #REF! | P6: =J6/52000 -> #REF! | Q6: =I6*Q2 -> 55847.91 | R6: =SUM(Q6/D6)/X6 -> 2.7155456 | S6: =SUM(Q6/E6)/X6 -> 2.7155456 | T6: =K6*102 -> 10200 | U6: =SUM(L6*1963) -> 154865 | V6: =SUM(Q6+T6+U6) -> 220912.91 | W6: =SUM(V6/E6)/T3 -> #DIV/0! | X6: =SUM(X5) -> 1582 | Y6: 106 | Z6: =SUM(Y6-S6) -> 103.28445
A7: =Gen!A13 -> 43437 | B7: ='Daily report Gen'!Z8 -> 35 | C7: =Gen!B13 -> 0.1429 | D7: =E7 -> 13 | E7: 13 | F7: =Gen!T13 -> 4437 | G7: =Gen!S13 -> 2768.05 | H7: =Gen!AJ13 -> 108.37 | I7: =SUM(G7:H7) -> 2876.42 | J7: =Gen!AT13 -> #REF! | K7: ='Water-Meter'!E8 -> 90 | L7: ='Lpg (2)'!N12 -> 126.544 | M7: =#REF! -> #REF! | N7: =#REF! -> #REF! | O7: =#REF! -> #REF! | P7: =J7/52000 -> #REF! | Q7: =I7*Q2 -> 83416.18 | R7: =SUM(Q7/D7)/X7 -> 4.0560235 | S7: =SUM(Q7/E7)/X7 -> 4.0560235 | T7: =K7*102 -> 9180 | U7: =SUM(L7*1963) -> 248405.87 | V7: =SUM(Q7+T7+U7) -> 341002.05 | W7: =SUM(V7/E7)/T4 -> #VALUE! | X7: =SUM(X6) -> 1582 | Y7: 106 | Z7: =SUM(Y7-S7) -> 101.94398
A8: =Gen!A14 -> 43438 | B8: ='Daily report Gen'!Z9 -> 38 | C8: =Gen!B14 -> 0.1688 | D8: =E8 -> 15 | E8: 15 | F8: =Gen!T14 -> 4694 | G8: =Gen!S14 -> 1910.45 | H8: =Gen!AJ14 -> 110.05 | I8: =SUM(G8:H8) -> 2020.5 | J8: =Gen!AT14 -> #REF! | K8: ='Water-Meter'!E9 -> 87 | L8: ='Lpg (2)'!N13 -> 101.332 | M8: =#REF! -> #REF! | N8: =#REF! -> #REF! | O8: =#REF! -> #REF! | P8: =J8/52000 -> #REF! | Q8: =I8*Q2 -> 58594.5 | R8: =SUM(Q8/D8)/X8 -> 2.4692162 | S8: =SUM(Q8/E8)/X8 -> 2.4692162 | T8: =K8*102 -> 8874 | U8: =SUM(L8*1963) -> 198914.72 | V8: =SUM(Q8+T8+U8) -> 266383.22 | W8: =SUM(V8/E8)/T5 -> 1.7586533 | X8: =SUM(X7) -> 1582 | Y8: 106 | Z8: =SUM(Y8-S8) -> 103.53078
A9: =Gen!A15 -> 43439 | B9: ='Daily report Gen'!Z10 -> 39 | C9: =Gen!B15 -> 0.2078 | D9: =E9 -> 12 | E9: 12 | F9: =Gen!T15 -> 4359 | G9: =Gen!S15 -> 1785.28 | H9: =Gen!AJ15 -> 0 | I9: =SUM(G9:H9) -> 1785.28 | J9: =Gen!AT15 -> #REF! | K9: ='Water-Meter'!E10 -> 84 | L9: ='Lpg (2)'!N14 -> 111.628 | M9: =#REF! -> #REF! | N9: =#REF! -> #REF! | O9: =#REF! -> #REF! | P9: =J9/52000 -> #REF! | Q9: =I9*Q2 -> 51773.12 | R9: =SUM(Q9/D9)/X9 -> 2.7271976 | S9: =SUM(Q9/E9)/X9 -> 2.7271976 | T9: =K9*102 -> 8568 | U9: =SUM(L9*1963) -> 219125.76 | V9: =SUM(Q9+T9+U9) -> 279466.88 | W9: =SUM(V9/E9)/T6 -> 2.2832262 | X9: =SUM(X8) -> 1582 | Y9: 106 | Z9: =SUM(Y9-S9) -> 103.2728
A10: =Gen!A16 -> 43440 | B10: ='Daily report Gen'!Z11 -> 35 | C10: =Gen!B16 -> 0.2987 | D10: =E10 -> 15 | E10: 15 | F10: =Gen!T16 -> 4710 | G10: =Gen!S16 -> 1903.86 | H10: =Gen!AJ16 -> 247.65 | I10: =SUM(G10:H10) -> 2151.51 | J10: =Gen!AT16 -> #REF! | K10: ='Water-Meter'!E11 -> 108 | L10: ='Lpg (2)'!N15 -> 105.644 | M10: =#REF! -> #REF! | N10: =#REF! -> #REF! | O10: =#REF! -> #REF! | P10: =J10/52000 -> #REF! | Q10: =I10*Q2 -> 62393.79 | R10: =SUM(Q10/D10)/X10 -> 2.6293211 | S10: =SUM(Q10/E10)/X10 -> 2.6293211 | T10: =K10*102 -> 11016 | U10: =SUM(L10*1963) -> 207379.17 | V10: =SUM(Q10+T10+U10) -> 280788.96 | W10: =SUM(V10/E10)/T7 -> 2.0391355 | X10: =SUM(X9) -> 1582 | Y10: 106 | Z10: =SUM(Y10-S10) -> 103.37068
A11: =Gen!A17 -> 43441 | B11: ='Daily report Gen'!Z12 -> 41 | C11: =Gen!B17 -> 0.2468 | D11: =E11 -> 20 | E11: 20 | F11: =Gen!T17 -> 4875 | G11: =Gen!S17 -> 2010.19 | H11: =Gen!AJ17 -> 224.17 | I11: =SUM(G11:H11) -> 2234.36 | J11: =Gen!AT17 -> #REF! | K11: ='Water-Meter'!E12 -> 93 | L11: ='Lpg (2)'!N16 -> 116.16 | M11: =#REF! -> #REF! | N11: =#REF! -> #REF! | O11: =#REF! -> #REF! | P11: =J11/52000 -> #REF! | Q11: =I11*Q2 -> 64796.44 | R11: =SUM(Q11/D11)/X11 -> 2.0479279 | S11: =SUM(Q11/E11)/X11 -> 2.0479279 | T11: =K11*102 -> 9486 | U11: =SUM(L11*1963) -> 228022.08 | V11: =SUM(Q11+T11+U11) -> 302304.52 | W11: =SUM(V11/E11)/T8 -> 1.703316 | X11: =SUM(X10) -> 1582 | Y11: 106 | Z11: =SUM(Y11-S11) -> 103.95207
A12: =Gen!A18 -> 43442 | B12: ='Daily report Gen'!Z13 -> 41 | C12: =Gen!B18 -> 0.2857 | D12: =E12 -> 23 | E12: 23 | F12: =Gen!T18 -> 4801 | G12: =Gen!S18 -> 1923.46 | H12: =Gen!AJ18 -> 114 | I12: =SUM(G12:H12) -> 2037.46 | J12: =Gen!AT18 -> #REF! | K12: ='Water-Meter'!E13 -> 103 | L12: ='Lpg (2)'!N17 -> 149.556 | M12: =#REF! -> #REF! | N12: =#REF! -> #REF! | O12: =#REF! -> #REF! | P12: =J12/52000 -> #REF! | Q12: =I12*Q2 -> 59086.34 | R12: =SUM(Q12/D12)/X12 -> 1.6238757 | S12: =SUM(Q12/E12)/X12 -> 1.6238757 | T12: =K12*102 -> 10506 | U12: =SUM(L12*1963) -> 293578.43 | V12: =SUM(Q12+T12+U12) -> 363170.77 | W12: =SUM(V12/E12)/T9 -> 1.8429077 | X12: =SUM(X11) -> 1582 | Y12: 106 | Z12: =SUM(Y12-S12) -> 104.37612
A13: =Gen!A19 -> 43443 | B13: ='Daily report Gen'!Z14 -> 39 | C13: =Gen!B19 -> 0.4675 | D13: =E13 -> 37 | E13: 37 | F13: =Gen!T19 -> 4909 | G13: =Gen!S19 -> 2043.56 | H13: =Gen!AJ19 -> 534.56 | I13: =SUM(G13:H13) -> 2578.12 | J13: =Gen!AT19 -> #REF! | K13: ='Water-Meter'!E14 -> 125 | L13: ='Lpg (2)'!N18 -> 158.4 | M13: =#REF! -> #REF! | N13: =#REF! -> #REF! | O13: =#REF! -> #REF! | P13: =J13/52000 -> #REF! | Q13: =I13*Q2 -> 74765.48 | R13: =SUM(Q13/D13)/X13 -> 1.2773 | S13: =SUM(Q13/E13)/X13 -> 1.2773 | T13: =K13*102 -> 12750 | U13: =SUM(L13*1963) -> 310939.2 | V13: =SUM(Q13+T13+U13) -> 398454.68 | W13: =SUM(V13/E13)/T4 -> #VALUE! | X13: =SUM(X12) -> 1582 | Y13: 106 | Z13: =SUM(Y13-S13) -> 104.7227
A14: =Gen!A20 -> 43444 | B14: ='Daily report Gen'!Z15 -> 44 | C14: =Gen!B20 -> 0.5584 | D14: =E14 -> 44 | E14: 44 | F14: =Gen!T20 -> 5316 | G14: =Gen!S20 -> 2103.23 | H14: =Gen!AJ20 -> 438 | I14: =SUM(G14:H14) -> 2541.23 | J14: =Gen!AT20 -> #REF! | K14: ='Water-Meter'!E15 -> 114 | L14: ='Lpg (2)'!N19 -> 197.208 | M14: =#REF! -> #REF! | N14: =#REF! -> #REF! | O14: =#REF! -> #REF! | P14: =J14/52000 -> #REF! | Q14: =I14*Q2 -> 73695.67 | R14: =SUM(Q14/D14)/X14 -> 1.0587241 | S14: =SUM(Q14/E14)/X14 -> 1.0587241 | T14: =K14*102 -> 11628 | U14: =SUM(L14*1963) -> 387119.3 | V14: =SUM(Q14+T14+U14) -> 472442.97 | W14: =SUM(V14/E14)/T5 -> 1.0633136 | X14: =SUM(X13) -> 1582 | Y14: 106 | Z14: =SUM(Y14-S14) -> 104.94128
A15: =Gen!A21 -> 43445 | B15: ='Daily report Gen'!Z16 -> 44 | C15: =Gen!B21 -> 0.5714 | D15: =E15 -> 45 | E15: 45 | F15: =Gen!T21 -> 4922 | G15: =Gen!S21 -> 2044.33 | H15: =Gen!AJ21 -> 222.33 | I15: =SUM(G15:H15) -> 2266.66 | J15: =Gen!AT21 -> #REF! | K15: ='Water-Meter'!E16 -> 114 | L15: ='Lpg (2)'!N20 -> 121.836 | M15: =#REF! -> #REF! | N15: =#REF! -> #REF! | O15: =#REF! -> #REF! | P15: =J15/52000 -> #REF! | Q15: =I15*Q2 -> 65733.14 | R15: =SUM(Q15/D15)/X15 -> 0.92334794 | S15: =SUM(Q15/E15)/X15 -> 0.92334794 | T15: =K15*102 -> 11628 | U15: =SUM(L15*1963) -> 239164.07 | V15: =SUM(Q15+T15+U15) -> 316525.21 | W15: =SUM(V15/E15)/T6 -> 0.6895974 | X15: =SUM(X14) -> 1582 | Y15: 106 | Z15: =SUM(Y15-S15) -> 105.07665
A16: =Gen!A22 -> 43446 | B16: ='Daily report Gen'!Z17 -> 42 | C16: =Gen!B22 -> 0.2338 | D16: =E16 -> 21 | E16: 21 | F16: =Gen!T22 -> 4870 | G16: =Gen!S22 -> 1917.24 | H16: =Gen!AJ22 -> 198.24 | I16: =SUM(G16:H16) -> 2115.48 | J16: =Gen!AT22 -> #REF! | K16: ='Water-Meter'!E17 -> 105 | L16: ='Lpg (2)'!N21 -> 127.292 | M16: =#REF! -> #REF! | N16: =#REF! -> #REF! | O16: =#REF! -> #REF! | P16: =J16/52000 -> #REF! | Q16: =I16*Q2 -> 61348.92 | R16: =SUM(Q16/D16)/X16 -> 1.8466354 | S16: =SUM(Q16/E16)/X16 -> 1.8466354 | T16: =K16*102 -> 10710 | U16: =SUM(L16*1963) -> 249874.2 | V16: =SUM(Q16+T16+U16) -> 321933.12 | W16: =SUM(V16/E16)/T7 -> 1.6699508 | X16: =SUM(X15) -> 1582 | Y16: 106 | Z16: =SUM(Y16-S16) -> 104.15336
A17: =Gen!A23 -> 43447 | B17: ='Daily report Gen'!Z18 -> 37 | C17: =Gen!B23 -> 0.2727 | D17: =E17 -> 23 | E17: 23 | F17: =Gen!T23 -> 4660 | G17: =Gen!S23 -> 1891.58 | H17: =Gen!AJ23 -> 114.1 | I17: =SUM(G17:H17) -> 2005.68 | J17: =Gen!AT23 -> #REF! | K17: ='Water-Meter'!E18 -> 111 | L17: ='Lpg (2)'!N22 -> 119.636 | M17: =#REF! -> #REF! | N17: =#REF! -> #REF! | O17: =#REF! -> #REF! | P17: =J17/52000 -> #REF! | Q17: =I17*Q2 -> 58164.72 | R17: =SUM(Q17/D17)/X17 -> 1.5985467 | S17: =SUM(Q17/E17)/X17 -> 1.5985467 | T17: =K17*102 -> 11322 | U17: =SUM(L17*1963) -> 234845.47 | V17: =SUM(Q17+T17+U17) -> 304332.19 | W17: =SUM(V17/E17)/T8 -> 1.4910789 | X17: =SUM(X16) -> 1582 | Y17: 106 | Z17: =SUM(Y17-S17) -> 104.40145
A18: =Gen!A24 -> 43448 | B18: ='Daily report Gen'!Z19 -> 42 | C18: =Gen!B24 -> 0.2595 | D18: =E18 -> 21 | E18: 21 | F18: =Gen!T24 -> 4748 | G18: =Gen!S24 -> 1992.44 | H18: =Gen!AJ24 -> 315.52 | I18: =SUM(G18:H18) -> 2307.96 | J18: =Gen!AT24 -> #REF! | K18: ='Water-Meter'!E19 -> 100 | L18: ='Lpg (2)'!N23 -> 108.504 | M18: =#REF! -> #REF! | N18: =#REF! -> #REF! | O18: =#REF! -> #REF! | P18: =J18/52000 -> #REF! | Q18: =I18*Q2 -> 66930.84 | R18: =SUM(Q18/D18)/X18 -> 2.0146541 | S18: =SUM(Q18/E18)/X18 -> 2.0146541 | T18: =K18*102 -> 10200 | U18: =SUM(L18*1963) -> 212993.35 | V18: =SUM(Q18+T18+U18) -> 290124.19 | W18: =SUM(V18/E18)/T2 -> 8.7328936 | X18: =SUM(X17) -> 1582 | Y18: 106 | Z18: =SUM(Y18-S18) -> 103.98535
A19: =Gen!A25 -> 43449 | B19: ='Daily report Gen'!Z20 -> 41 | C19: =Gen!B25 -> 0.1299 | D19: =E19 -> 11 | E19: 11 | F19: =Gen!T25 -> 4724 | G19: =Gen!S25 -> 1937.98 | H19: =Gen!AJ25 -> 571.32 | I19: =SUM(G19:H19) -> 2509.3 | J19: =Gen!AT25 -> #REF! | K19: ='Water-Meter'!E20 -> 87 | L19: ='Lpg (2)'!N24 -> 117.04 | M19: =#REF! -> #REF! | N19: =#REF! -> #REF! | O19: =#REF! -> #REF! | P19: =J19/52000 -> #REF! | Q19: =I19*Q2 -> 72769.7 | R19: =SUM(Q19/D19)/X19 -> 4.181686 | S19: =SUM(Q19/E19)/X19 -> 4.181686 | T19: =K19*102 -> 8874 | U19: =SUM(L19*1963) -> 229749.52 | V19: =SUM(Q19+T19+U19) -> 311393.22 | W19: =SUM(V19/E19)/T2 -> 17.894105 | X19: =SUM(X18) -> 1582 | Y19: 106 | Z19: =SUM(Y19-S19) -> 101.81831
A20: =Gen!A26 -> 43450 | B20: ='Daily report Gen'!Z21 -> 41 | C20: =Gen!B26 -> 0.2597 | D20: =E20 -> 21 | E20: 21 | F20: =Gen!T26 -> 5005 | G20: =Gen!S26 -> 2042.13 | H20: =Gen!AJ26 -> 335.74 | I20: =SUM(G20:H20) -> 2377.87 | J20: =Gen!AT26 -> #REF! | K20: ='Water-Meter'!E21 -> 105 | L20: ='Lpg (2)'!N25 -> 115.5 | M20: =#REF! -> #REF! | N20: =#REF! -> #REF! | O20: =#REF! -> #REF! | P20: =J20/52000 -> #REF! | Q20: =I20*Q2 -> 68958.23 | R20: =SUM(Q20/D20)/X20 -> 2.0756797 | S20: =SUM(Q20/E20)/X20 -> 2.0756797 | T20: =K20*102 -> 10710 | U20: =SUM(L20*1963) -> 226726.5 | V20: =SUM(Q20+T20+U20) -> 306394.73 | W20: =SUM(V20/E20)/T2 -> 9.2226455 | X20: =SUM(X19) -> 1582 | Y20: 106 | Z20: =SUM(Y20-S20) -> 103.92432
A21: =Gen!A27 -> 43451 | B21: ='Daily report Gen'!Z22 -> 45 | C21: =Gen!B27 -> 0.2987 | D21: =E21 -> 24 | E21: 24 | F21: =Gen!T27 -> 5332 | G21: =Gen!S27 -> 2099.06 | H21: =Gen!AJ27 -> 581.31 | I21: =SUM(G21:H21) -> 2680.37 | J21: =Gen!AT27 -> #REF! | K21: ='Water-Meter'!E22 -> 109 | L21: ='Lpg (2)'!N26 -> 103.268 | M21: =#REF! -> #REF! | N21: =#REF! -> #REF! | O21: =#REF! -> #REF! | P21: =J21/52000 -> #REF! | Q21: =I21*Q2 -> 77730.73 | R21: =SUM(Q21/D21)/X21 -> 2.0472695 | S21: =SUM(Q21/E21)/X21 -> 2.0472695 | T21: =K21*102 -> 11118 | U21: =SUM(L21*1963) -> 202715.08 | V21: =SUM(Q21+T21+U21) -> 291563.81 | W21: =SUM(V21/E21)/T2 -> 7.6791986 | X21: =SUM(X20) -> 1582 | Y21: 106 | Z21: =SUM(Y21-S21) -> 103.95273
A22: =Gen!A28 -> 43452 | B22: ='Daily report Gen'!Z23 -> 44 | C22: =Gen!B28 -> 0.5065 | D22: =E22 -> 41 | E22: 41 | F22: =Gen!T28 -> 5890 | G22: =Gen!S28 -> 2371.98 | H22: =Gen!AJ28 -> 185.71 | I22: =SUM(G22:H22) -> 2557.69 | J22: =Gen!AT28 -> #REF! | K22: ='Water-Meter'!E23 -> 114 | L22: ='Lpg (2)'!N27 -> 116.116 | M22: =#REF! -> #REF! | N22: =#REF! -> #REF! | O22: =#REF! -> #REF! | P22: =J22/52000 -> #REF! | Q22: =I22*Q2 -> 74173.01 | R22: =SUM(Q22/D22)/X22 -> 1.1435511 | S22: =SUM(Q22/E22)/X22 -> 1.1435511 | T22: =K22*102 -> 11628 | U22: =SUM(L22*1963) -> 227935.71 | V22: =SUM(Q22+T22+U22) -> 313736.72 | W22: =SUM(V22/E22)/T2 -> 4.836988 | X22: =SUM(X21) -> 1582 | Y22: 106 | Z22: =SUM(Y22-S22) -> 104.85645
A23: =Gen!A29 -> 43453 | B23: ='Daily report Gen'!Z24 -> 45 | C23: =Gen!B29 -> 0.4416 | D23: =E23 -> 35 | E23: 35 | F23: =Gen!T29 -> 5737 | G23: =Gen!S29 -> 2258.75 | H23: =Gen!AJ29 -> 118 | I23: =SUM(G23:H23) -> 2376.75 | J23: =Gen!AT29 -> #REF! | K23: ='Water-Meter'!E24 -> 110 | L23: ='Lpg (2)'!N28 -> 125.268 | M23: =#REF! -> #REF! | N23: =#REF! -> #REF! | O23: =#REF! -> #REF! | P23: =J23/52000 -> #REF! | Q23: =I23*Q2 -> 68925.75 | R23: =SUM(Q23/D23)/X23 -> 1.2448212 | S23: =SUM(Q23/E23)/X23 -> 1.2448212 | T23: =K23*102 -> 11220 | U23: =SUM(L23*1963) -> 245901.08 | V23: =SUM(Q23+T23+U23) -> 326046.83 | W23: =SUM(V23/E23)/T2 -> 5.8885106 | X23: =SUM(X22) -> 1582 | Y23: 106 | Z23: =SUM(Y23-S23) -> 104.75518
A24: =Gen!A30 -> 43454 | B24: ='Daily report Gen'!Z25 -> 43 | C24: =Gen!B30 -> 0.4026 | D24: =E24 -> 34 | E24: 34 | F24: =Gen!T30 -> 5582 | G24: =Gen!S30 -> 2355.33 | H24: =Gen!AJ30 -> 690.09 | I24: =SUM(G24:H24) -> 3045.42 | J24: =Gen!AT30 -> #REF! | K24: ='Water-Meter'!E25 -> 123 | L24: ='Lpg (2)'!N29 -> 115.368 | M24: =#REF! -> #REF! | N24: =#REF! -> #REF! | O24: =#REF! -> #REF! | P24: =J24/52000 -> #REF! | Q24: =I24*Q2 -> 88317.18 | R24: =SUM(Q24/D24)/X24 -> 1.6419495 | S24: =SUM(Q24/E24)/X24 -> 1.6419495 | T24: =K24*102 -> 12546 | U24: =SUM(L24*1963) -> 226467.38 | V24: =SUM(Q24+T24+U24) -> 327330.56 | W24: =SUM(V24/E24)/T2 -> 6.0855686 | X24: =SUM(X23) -> 1582 | Y24: 106 | Z24: =SUM(Y24-S24) -> 104.35805
A25: =Gen!A31 -> 43455 | B25: ='Daily report Gen'!Z26 -> 45 | C25: =Gen!B31 -> 0.4935 | D25: =E25 -> 41 | E25: 41 | F25: =Gen!T31 -> 5599 | G25: =Gen!S31 -> 2159.4 | H25: =Gen!AJ31 -> 544.38 | I25: =SUM(G25:H25) -> 2703.78 | J25: =Gen!AT31 -> #REF! | K25: ='Water-Meter'!E26 -> 130 | L25: ='Lpg (2)'!N30 -> 128.128 | M25: =#REF! -> #REF! | N25: =#REF! -> #REF! | O25: =#REF! -> #REF! | P25: =J25/52000 -> #REF! | Q25: =I25*Q2 -> 78409.62 | R25: =SUM(Q25/D25)/X25 -> 1.2088684 | S25: =SUM(Q25/E25)/X25 -> 1.2088684 | T25: =K25*102 -> 13260 | U25: =SUM(L25*1963) -> 251515.26 | V25: =SUM(Q25+T25+U25) -> 343184.88 | W25: =SUM(V25/E25)/T2 -> 5.2910006 | X25: =SUM(X24) -> 1582 | Y25: 106 | Z25: =SUM(Y25-S25) -> 104.79113
A26: =Gen!A32 -> 43456 | B26: ='Daily report Gen'!Z27 -> 46 | C26: =Gen!B32 -> 0.4935 | D26: =E26 -> 41 | E26: 41 | F26: =Gen!T32 -> 5928 | G26: =Gen!S32 -> 2501.02 | H26: =Gen!AJ32 -> 322.73 | I26: =SUM(G26:H26) -> 2823.75 | J26: =Gen!AT32 -> #REF! | K26: ='Water-Meter'!E27 -> 130 | L26: ='Lpg (2)'!N31 -> 119.944 | M26: =#REF! -> #REF! | N26: =#REF! -> #REF! | O26: =#REF! -> #REF! | P26: =J26/52000 -> #REF! | Q26: =I26*Q2 -> 81888.75 | R26: =SUM(Q26/D26)/X26 -> 1.2625073 | S26: =SUM(Q26/E26)/X26 -> 1.2625073 | T26: =K26*102 -> 13260 | U26: =SUM(L26*1963) -> 235450.07 | V26: =SUM(Q26+T26+U26) -> 330598.82 | W26: =SUM(V26/E26)/T2 -> 5.096957 | X26: =SUM(X25) -> 1582 | Y26: 106 | Z26: =SUM(Y26-S26) -> 104.73749
A27: =Gen!A33 -> 43457 | B27: ='Daily report Gen'!Z28 -> 49 | C27: =Gen!B33 -> 0.4456 | D27: =E27 -> 35 | E27: 35 | F27: =Gen!T33 -> 5850 | G27: =Gen!S33 -> 2375.47 | H27: =Gen!AJ33 -> 93.91 | I27: =SUM(G27:H27) -> 2469.38 | J27: =Gen!AT33 -> #REF! | K27: ='Water-Meter'!E28 -> 131 | L27: ='Lpg (2)'!N32 -> 106.612 | M27: =#REF! -> #REF! | N27: =#REF! -> #REF! | O27: =#REF! -> #REF! | P27: =J27/52000 -> #REF! | Q27: =I27*Q2 -> 71612.02 | R27: =SUM(Q27/D27)/X27 -> 1.2933361 | S27: =SUM(Q27/E27)/X27 -> 1.2933361 | T27: =K27*102 -> 13362 | U27: =SUM(L27*1963) -> 209279.36 | V27: =SUM(Q27+T27+U27) -> 294253.38 | W27: =SUM(V27/E27)/T2 -> 5.3143106 | X27: =SUM(X26) -> 1582 | Y27: 106 | Z27: =SUM(Y27-S27) -> 104.70666
A28: =Gen!A34 -> 43458 | B28: ='Daily report Gen'!Z29 -> -2952 | C28: =Gen!B34 -> 0.5065 | D28: =E28 -> 40 | E28: 40 | F28: =Gen!T34 -> 6147 | G28: =Gen!S34 -> 2708.28 | H28: =Gen!AJ34 -> 786.27 | I28: =SUM(G28:H28) -> 3494.55 | J28: =Gen!AT34 -> #REF! | K28: ='Water-Meter'!E29 -> 112 | L28: ='Lpg (2)'!N33 -> 119.68 | M28: =#REF! -> #REF! | N28: =#REF! -> #REF! | O28: =#REF! -> #REF! | P28: =J28/52000 -> #REF! | Q28: =I28*Q2 -> 101341.95 | R28: =SUM(Q28/D28)/X28 -> 1.6014847 | S28: =SUM(Q28/E28)/X28 -> 1.6014847 | T28: =K28*102 -> 11424 | U28: =SUM(L28*1963) -> 234931.84 | V28: =SUM(Q28+T28+U28) -> 347697.79 | W28: =SUM(V28/E28)/T2 -> 5.4945921 | X28: =SUM(X27) -> 1582 | Y28: 106 | Z28: =SUM(Y28-S28) -> 104.39852
A29: =Gen!A35 -> 43459 | B29: ='Daily report Gen'!Z30 -> 60 | C29: =Gen!B35 -> 0.9481 | D29: =E29 -> 73 | E29: 73 | F29: =Gen!T35 -> 6478 | G29: =Gen!S35 -> 2810.4 | H29: =Gen!AJ35 -> 174.44 | I29: =SUM(G29:H29) -> 2984.84 | J29: =Gen!AT35 -> #REF! | K29: ='Water-Meter'!E30 -> 147 | L29: ='Lpg (2)'!N34 -> 131.516 | M29: =#REF! -> #REF! | N29: =#REF! -> #REF! | O29: =#REF! -> #REF! | P29: =J29/52000 -> #REF! | Q29: =I29*Q2 -> 86560.36 | R29: =SUM(Q29/D29)/X29 -> 0.7495312 | S29: =SUM(Q29/E29)/X29 -> 0.7495312 | T29: =K29*102 -> 14994 | U29: =SUM(L29*1963) -> 258165.91 | V29: =SUM(Q29+T29+U29) -> 359720.27 | W29: =SUM(V29/E29)/T2 -> 3.1148388 | X29: =SUM(X28) -> 1582 | Y29: 106 | Z29: =SUM(Y29-S29) -> 105.25047
A30: =Gen!A36 -> 43460 | B30: ='Daily report Gen'!Z31 -> 60 | C30: =Gen!B36 -> 0.9091 | D30: =E30 -> 70 | E30: 70 | F30: =Gen!T36 -> 6636 | G30: =Gen!S36 -> 2865.5 | H30: =Gen!AJ36 -> 356.08 | I30: =SUM(G30:H30) -> 3221.58 | J30: =Gen!AT36 -> #REF! | K30: ='Water-Meter'!E31 -> 167 | L30: ='Lpg (2)'!N35 -> 115.192 | M30: =#REF! -> #REF! | N30: =#REF! -> #REF! | O30: =#REF! -> #REF! | P30: =J30/52000 -> #REF! | Q30: =I30*Q2 -> 93425.82 | R30: =SUM(Q30/D30)/X30 -> 0.84365017 | S30: =SUM(Q30/E30)/X30 -> 0.84365017 | T30: =K30*102 -> 17034 | U30: =SUM(L30*1963) -> 226121.9 | V30: =SUM(Q30+T30+U30) -> 336581.72 | W30: =SUM(V30/E30)/T2 -> 3.039387 | X30: =SUM(X29) -> 1582 | Y30: 106 | Z30: =SUM(Y30-S30) -> 105.15635
A31: =Gen!A37 -> 43461 | B31: ='Daily report Gen'!Z32 -> 56 | C31: =Gen!B37 -> 0.7662 | D31: =E31 -> 60 | E31: 60 | F31: =Gen!T37 -> 6583 | G31: =Gen!S37 -> 2635.34 | H31: =Gen!AJ37 -> 203.69 | I31: =SUM(G31:H31) -> 2839.03 | J31: =Gen!AT37 -> #REF! | K31: ='Water-Meter'!E32 -> 159 | L31: ='Lpg (2)'!N36 -> 108.46 | M31: =#REF! -> #REF! | N31: =#REF! -> #REF! | O31: =#REF! -> #REF! | P31: =J31/52000 -> #REF! | Q31: =I31*Q2 -> 82331.87 | R31: =SUM(Q31/D31)/X31 -> 0.86738169 | S31: =SUM(Q31/E31)/X31 -> 0.86738169 | T31: =K31*102 -> 16218 | U31: =SUM(L31*1963) -> 212906.98 | V31: =SUM(Q31+T31+U31) -> 311456.85 | W31: =SUM(V31/E31)/T2 -> 3.2812563 | X31: =SUM(X30) -> 1582 | Y31: 106 | Z31: =SUM(Y31-S31) -> 105.13262
A32: =Gen!A38 -> 43462 | B32: ='Daily report Gen'!Z33 -> 63 | C32: =Gen!B38 -> 0.7792 | D32: =E32 -> 62 | E32: 62 | F32: =Gen!T38 -> 7094 | G32: =Gen!S38 -> 3043.34 | H32: =Gen!AJ38 -> 321.45 | I32: =SUM(G32:H32) -> 3364.79 | J32: =Gen!AT38 -> #REF! | K32: ='Water-Meter'!E33 -> 164 | L32: ='Lpg (2)'!N37 -> 123.024 | M32: =#REF! -> #REF! | N32: =#REF! -> #REF! | O32: =#REF! -> #REF! | P32: =J32/52000 -> #REF! | Q32: =I32*Q2 -> 97578.91 | R32: =SUM(Q32/D32)/X32 -> 0.99485043 | S32: =SUM(Q32/E32)/X32 -> 0.99485043 | T32: =K32*102 -> 16728 | U32: =SUM(L32*1963) -> 241496.11 | V32: =SUM(Q32+T32+U32) -> 355803.02 | W32: =SUM(V32/E32)/T2 -> 3.6275338 | X32: =SUM(X31) -> 1582 | Y32: 106 | Z32: =SUM(Y32-S32) -> 105.00515
A33: =Gen!A39 -> 43463 | B33: ='Daily report Gen'!Z34 -> 61 | C33: =Gen!B39 -> 0.9221 | D33: =E33 -> 73 | E33: 73 | F33: =Gen!T39 -> 7628 | G33: =Gen!S39 -> 2871.98 | H33: =Gen!AJ39 -> 247.04 | I33: =SUM(G33:H33) -> 3119.02 | J33: =Gen!AT39 -> #REF! | K33: ='Water-Meter'!E34 -> 173 | L33: ='Lpg (2)'!N38 -> 111.056 | M33: =#REF! -> #REF! | N33: =#REF! -> #REF! | O33: =#REF! -> #REF! | P33: =J33/52000 -> #REF! | Q33: =I33*Q2 -> 90451.58 | R33: =SUM(Q33/D33)/X33 -> 0.7832255 | S33: =SUM(Q33/E33)/X33 -> 0.7832255 | T33: =K33*102 -> 17646 | U33: =SUM(L33*1963) -> 218002.93 | V33: =SUM(Q33+T33+U33) -> 326100.51 | W33: =SUM(V33/E33)/T2 -> 2.8237233 | X33: =SUM(X32) -> 1582 | Y33: 106 | Z33: =SUM(Y33-S33) -> 105.21677
A34: =Gen!A40 -> 43464 | B34: ='Daily report Gen'!Z35 -> 60 | C34: =Gen!B40 -> 0.7792 | D34: =E34 -> 61 | E34: 61 | F34: =Gen!T40 -> 7378 | G34: =Gen!S40 -> 3172.51 | H34: =Gen!AJ40 -> 120.12 | I34: =SUM(G34:H34) -> 3292.63 | J34: =Gen!AT40 -> #REF! | K34: ='Water-Meter'!E35 -> 156 | L34: ='Lpg (2)'!N39 -> 106.568 | M34: =#REF! -> #REF! | N34: =#REF! -> #REF! | O34: =#REF! -> #REF! | P34: =J34/52000 -> #REF! | Q34: =I34*Q2 -> 95486.27 | R34: =SUM(Q34/D34)/X34 -> 0.98947452 | S34: =SUM(Q34/E34)/X34 -> 0.98947452 | T34: =K34*102 -> 15912 | U34: =SUM(L34*1963) -> 209192.98 | V34: =SUM(Q34+T34+U34) -> 320591.25 | W34: =SUM(V34/E34)/T2 -> 3.3221203 | X34: =SUM(X33) -> 1582 | Y34: 106 | Z34: =SUM(Y34-S34) -> 105.01053
A35: =Gen!A41 -> 43465 | B35: ='Daily report Gen'!Z36 -> 65 | C35: =Gen!B41 -> 0.8442 | D35: =E35 -> 66 | E35: 66 | F35: =Gen!T41 -> 7255 | G35: =Gen!S41 -> 3058.76 | H35: =Gen!AJ41 -> 1284.14 | I35: =SUM(G35:H35) -> 4342.9 | J35: =Gen!AT41 -> #REF! | K35: ='Water-Meter'!E36 -> 120 | L35: ='Lpg (2)'!N40 -> 122.54 | M35: =#REF! -> #REF! | N35: =#REF! -> #REF! | O35: =#REF! -> #REF! | P35: =J35/52000 -> #REF! | Q35: =I35*Q2 -> 125944.1 | R35: =SUM(Q35/D35)/X35 -> 1.2062225 | S35: =SUM(Q35/E35)/X35 -> 1.2062225 | T35: =K35*102 -> 12240 | U35: =SUM(L35*1963) -> 240546.02 | V35: =SUM(Q35+T35+U35) -> 378730.12 | W35: =SUM(V35/E35)/T3 -> #DIV/0! | X35: =SUM(X34) -> 1582 | Y35: 106 | Z35: =SUM(Y35-S35) -> 104.79378
C36: =Gen!B42 -> 0 | D36: =E36 -> 55 | E36: 55 | K36: ='Water-Meter'!E41 -> 0 | Q36: =I36*2057.79 -> 0 | V36: =SUM(Q36+T36+U36) -> 0
S37: =SUM(S5:S17)/Gen!A47 -> 0.87923912
B38: =SUM(B5:B37)/Gen!A47 -> 45.709677 | M38: =0.5*2057.79 -> 1028.895
B39: =SUM(B38*Gen!A47) -> 1417 | C39: =SUM(B39/250) -> 5.668 | M39: =M38/1500 -> 0.68593 | O39: =(24*2.2)*2 -> 105.6 | P39: =O39*1029 -> 108662.4 | R39: Over budget | S39: =SUM(S37-Y35) -> -105.12076
P40: =P39/K5 -> 1097.6

Sheet Daily report Gen
A1: 43374
K3: GENETAOR NO.1 | N3: GENETAOR NO.2 | Q3: GENETAOR NO.4 | T3: GENETAOR NO.5 | W3: GENETAOR NO.6
A4: DATE | B4: OCC% | C4: D-TANK A | D4: D-TANK B | E4: DELIVERY DATE | F4: DELIVERY | G4: ISSUED-VEHICLE | H4: OTHERS | I4: M-R LV PANEL 1. KW-HR | J4: M-R LV PANEL 2. KW-HR | K4: OPEN HRS READING | L4: CLOSE HRS READING | M4: RUNNING HRS | N4: OPEN HRS READING | O4: CLOSE HRS READING | P4: RUNNING HRS | Q4: OPEN HRS READING | R4: CLOSE HRS READING | S4: RUNNING HRS | T4: OPEN HRS READING | U4: CLOSE HRS READING | V4: RUNNING HRS | W4: OPEN HRS READING | X4: CLOSE HRS READING | Y4: RUNNING HRS | Z4: TOTAL RUNNING HRS | AA4: MAX KW | AB4: MIN-KW | AC4: TOTAL DIESEL CONS.
I5: 26209.1 | J5: 16947.2 | L5: 31410 | O5: 24307 | R5: 30484 | U5: 27791 | X5: 15205 | AA5: 413 | AB5: 219
A6: =Gen!A11 -> 43435 | B6: =Gen!B11 -> 0.168 | C6: 25400.01 | D6: 14205.48 | G6: 42.79 | I6: 26215.1 | J6: 16947.2 | K6: =L5 -> 31410 | L6: 31418 | M6: =L6-K6 -> 8 | N6: =O5 -> 24307 | O6: 24314 | P6: =O6-O5 -> 7 | Q6: =R5 -> 30484 | R6: 30495 | S6: =R6-R5 -> 11 | T6: =U5 -> 27791 | U6: 27800 | V6: =U6-T6 -> 9 | W6: =X5 -> 15205 | X6: 18205 | Y6: =X6-X5 -> 3000 | Z6: =Y6+V6+S6+P6+M6 -> 3035 | AA6: 430 | AB6: 209 | AC6: =PRINT!F5 -> 1867.92
A7: =Gen!A12 -> 43436 | B7: =Gen!B12 -> 0.1429 | C7: 25400.01 | D7: 12351.86 | G7: 90.6 | I7: 26221.2 | J7: 16960.1 | K7: =L6 -> 31418 | L7: 31424 | M7: =L7-K7 -> 6 | N7: =O6 -> 24314 | O7: 24328 | P7: =O7-O6 -> 14 | Q7: =R6 -> 30495 | R7: 30502 | S7: =R7-R6 -> 7 | T7: =U6 -> 27800 | U7: 27806 | V7: =U7-T7 -> 6 | W7: =X6 -> 18205 | X7: 18205 | Y7: =X7-X6 -> 0 | Z7: =Y7+V7+S7+P7+M7 -> 33 | AA7: 410 | AB7: 204 | AC7: =PRINT!F6 -> 1925.79
A8: =Gen!A13 -> 43437 | B8: =Gen!B13 -> 0.1429 | C8: 25400.01 | D8: 10426.07 | G8: 108.37 | I8: 26227.5 | J8: 16967.1 | K8: =L7 -> 31424 | L8: 31431 | M8: =L8-K8 -> 7 | N8: =O7 -> 24328 | O8: 24335 | P8: =O8-O7 -> 7 | Q8: =R7 -> 30502 | R8: 30511 | S8: =R8-R7 -> 9 | T8: =U7 -> 27806 | U8: 27818 | V8: =U8-T8 -> 12 | W8: =X7 -> 18205 | X8: 18205 | Y8: =X8-X7 -> 0 | Z8: =Y8+V8+S8+P8+M8 -> 35 | AA8: 421 | AB8: 213 | AC8: =PRINT!F7 -> 2876.42
A9: =Gen!A14 -> 43438 | B9: =Gen!B14 -> 0.1688 | C9: 27000 | D9: 22962.66 | G9: 109.74 | I9: 26234.3 | J9: 16973.5 | K9: =L8 -> 31431 | L9: 31442 | M9: =L9-K9 -> 11 | N9: =O8 -> 24335 | O9: 24348 | P9: =O9-O8 -> 13 | Q9: =R8 -> 30511 | R9: 30520 | S9: =R9-R8 -> 9 | T9: =U8 -> 27818 | U9: 27823 | V9: =U9-T9 -> 5 | W9: =X8 -> 18205 | X9: 18205 | Y9: =X9-X8 -> 0 | Z9: =Y9+V9+S9+P9+M9 -> 38 | AA9: 417 | AB9: 216 | AC9: =PRINT!F8 -> 2020.5
A10: =Gen!A15 -> 43439 | B10: =Gen!B15 -> 0.2078 | C10: 27000 | D10: 20942.16 | I10: 26240.7 | J10: 16979.6 | K10: =L9 -> 31442 | L10: 31453 | M10: =L10-K10 -> 11 | N10: =O9 -> 24348 | O10: 24355 | P10: =O10-O9 -> 7 | Q10: =R9 -> 30520 | R10: 30534 | S10: =R10-R9 -> 14 | T10: =U9 -> 27823 | U10: 27830 | V10: =U10-T10 -> 7 | W10: =X9 -> 18205 | X10: 18205 | Y10: =X10-X9 -> 0 | Z10: =Y10+V10+S10+P10+M10 -> 39 | AA10: 369 | AB10: 154 | AC10: =PRINT!F9 -> 1785.28
A11: =Gen!A16 -> 43440 | B11: =Gen!B16 -> 0.2987 | C11: 27000.01 | D11: 18791.65 | G11: 246.65 | I11: 26247.7 | J11: 16986.1 | K11: =L10 -> 31453 | L11: 31460 | M11: =L11-K11 -> 7 | N11: =O10 -> 24355 | O11: 24362 | P11: =O11-O10 -> 7 | Q11: =R10 -> 30534 | R11: 30542 | S11: =R11-R10 -> 8 | T11: =U10 -> 27830 | U11: 27843 | V11: =U11-T11 -> 13 | W11: =X10 -> 18205 | X11: 18205 | Y11: =X11-X10 -> 0 | Z11: =Y11+V11+S11+P11+M11 -> 35 | AA11: 416 | AB11: 184 | AC11: =PRINT!F10 -> 2151.51
A12: =Gen!A17 -> 43441 | B12: =Gen!B17 -> 0.2468 | C12: 27000.01 | D12: 16558.29 | G12: 223.17 | I12: 26254.6 | J12: 16993.1 | K12: =L11 -> 31460 | L12: 31469 | M12: =L12-K12 -> 9 | N12: =O11 -> 24362 | O12: 24370 | P12: =O12-O11 -> 8 | Q12: =R11 -> 30542 | R12: 30556 | S12: =R12-R11 -> 14 | T12: =U11 -> 27843 | U12: 27853 | V12: =U12-T12 -> 10 | W12: =X11 -> 18205 | X12: 18205 | Y12: =X12-X11 -> 0 | Z12: =Y12+V12+S12+P12+M12 -> 41 | AA12: 389 | AB12: 169
A13: =Gen!A18 -> 43442 | B13: =Gen!B18 -> 0.2857 | C13: 27000.01 | D13: 14634.83 | G13: 114 | I13: 26261.6 | J13: 16999.7 | K13: =L12 -> 31469 | L13: 31479 | M13: =L13-K13 -> 10 | N13: =O12 -> 24370 | O13: 24377 | P13: =O13-O12 -> 7 | Q13: =R12 -> 30556 | R13: 30570 | S13: =R13-R12 -> 14 | T13: =U12 -> 27853 | U13: 27863 | V13: =U13-T13 -> 10 | W13: =X12 -> 18205 | X13: 18205 | Y13: =X13-X12 -> 0 | Z13: =Y13+V13+S13+P13+M13 -> 41 | AA13: 410 | AB13: 187 | AC13: =PRINT!F12 -> 2037.46
A14: =Gen!A19 -> 43443 | B14: =Gen!B19 -> 0.4675 | C14: 27000.01 | D14: 12056.73 | G14: 534.56 | I14: 26269.2 | J14: 17006.2 | K14: =L13 -> 31479 | L14: 31488 | M14: =L14-K14 -> 9 | N14: =O13 -> 24377 | O14: 24383 | P14: =O14-O13 -> 6 | Q14: =R13 -> 30570 | R14: 30580 | S14: =R14-R13 -> 10 | T14: =U13 -> 27863 | U14: 27877 | V14: =U14-T14 -> 14 | W14: =X13 -> 18205 | X14: 18205 | Y14: =X14-X13 -> 0 | Z14: =Y14+V14+S14+P14+M14 -> 39 | AA14: 426 | AB14: 194 | AC14: =PRINT!F13 -> 2578.12
A15: =Gen!A20 -> 43444 | B15: =Gen!B20 -> 0.5584 | C15: 27000.01 | D15: 21058.77 | E15: 43385 | F15: 12000 | G15: 438 | I15: 26277.8 | J15: 17012.8 | K15: =L14 -> 31488 | L15: 31499 | M15: =L15-K15 -> 11 | N15: =O14 -> 24383 | O15: 24396 | P15: =O15-O14 -> 13 | Q15: =R14 -> 30580 | R15: 30590 | S15: =R15-R14 -> 10 | T15: =U14 -> 27877 | U15: 27887 | V15: =U15-T15 -> 10 | W15: =X14 -> 18205 | X15: 18205 | Y15: =X15-X14 -> 0 | Z15: =Y15+V15+S15+P15+M15 -> 44 | AA15: 420 | AB15: 200 | AC15: =PRINT!F14 -> 2541.23
A16: =Gen!A21 -> 43445 | B16: =Gen!B21 -> 0.5714 | C16: 27000.01 | D16: 19616.19 | G16: 222.33 | I16: 26286.1 | J16: 17018.6 | K16: =L15 -> 31499 | L16: 31510 | M16: =L16-K16 -> 11 | N16: =O15 -> 24396 | O16: 24407 | P16: =O16-O15 -> 11 | Q16: =R15 -> 30590 | R16: 30604 | S16: =R16-R15 -> 14 | T16: =U15 -> 27887 | U16: 27895 | V16: =U16-T16 -> 8 | W16: =X15 -> 18205 | X16: 18205 | Y16: =X16-X15 -> 0 | Z16: =Y16+V16+S16+P16+M16 -> 44 | AA16: 425 | AB16: 196 | AC16: =PRINT!F15 -> 2266.66
A17: =Gen!A22 -> 43446 | B17: =Gen!B22 -> 0.2338 | C17: 27000.01 | D17: 17349.53 | G17: 198.24 | I17: 26293.7 | J17: 17024.9 | K17: =L16 -> 31510 | L17: 31521 | M17: =L17-K17 -> 11 | N17: =O16 -> 24407 | O17: 24418 | P17: =O17-O16 -> 11 | Q17: =R16 -> 30604 | R17: 30617 | S17: =R17-R16 -> 13 | T17: =U17 -> 27902 | U17: 27902 | V17: =U17-U16 -> 7 | W17: =X16 -> 18205 | X17: 18205 | Y17: =X17-X16 -> 0 | Z17: =Y17+V17+S17+P17+M17 -> 42 | AA17: 420 | AB17: 200 | AC17: =PRINT!F16 -> 2115.48
A18: =Gen!A23 -> 43447 | B18: =Gen!B23 -> 0.2727 | C18: 27000.01 | D18: 15234.05 | G18: 114.1 | I18: 26300.9 | J18: 17030.9 | K18: =L17 -> 31521 | L18: 31530 | M18: =L18-K18 -> 9 | N18: =O17 -> 24418 | O18: 24431 | P18: =O18-O17 -> 13 | Q18: =R17 -> 30617 | R18: 30627 | S18: =R18-R17 -> 10 | T18: =U18 -> 27907 | U18: 27907 | V18: =U18-U17 -> 5 | W18: =X17 -> 18205 | X18: 18205 | Y18: =X18-X17 -> 0 | Z18: =Y18+V18+S18+P18+M18 -> 37 | AA18: 435 | AB18: 186 | AC18: =PRINT!F17 -> 2005.68
A19: =Gen!A24 -> 43448 | B19: =Gen!B24 -> 0.2595 | C19: 27000.01 | D19: 14228.37 | G19: 315.52 | I19: 26308.7 | J19: 17036.8 | K19: =L18 -> 31530 | L19: 31543 | M19: =L19-K19 -> 13 | N19: =O18 -> 24431 | O19: 24440 | P19: =O19-O18 -> 9 | Q19: =R18 -> 30627 | R19: 30635 | S19: =R19-R18 -> 8 | T19: =U19 -> 27919 | U19: 27919 | V19: =U19-U18 -> 12 | W19: =X18 -> 18205 | X19: 18205 | Y19: =X19-X18 -> 0 | Z19: =Y19+V19+S19+P19+M19 -> 42 | AA19: 421 | AB19: 178 | AC19: =PRINT!F18 -> 2307.96
A20: =Gen!A25 -> 43449 | B20: =Gen!B25 -> 0.1299 | C20: 12919.82 | D20: 25000.6 | G20: 571.31 | I20: 26316.1 | J20: 17042.2 | K20: =L19 -> 31543 | L20: 31554 | M20: =L20-K20 -> 11 | N20: =O19 -> 24440 | O20: 24446 | P20: =O20-O19 -> 6 | Q20: =R19 -> 30635 | R20: 30647 | S20: =R20-R19 -> 12 | T20: =U19 -> 27919 | U20: 27931 | V20: =U20-U19 -> 12 | W20: =X19 -> 18205 | X20: 18205 | Y20: =X20-X19 -> 0 | Z20: =Y20+V20+S20+P20+M20 -> 41 | AA20: 405 | AB20: 180 | AC20: =PRINT!F19 -> 2509.3
A21: =Gen!A26 -> 43450 | B21: =Gen!B26 -> 0.2597 | C21: 22410.52 | D21: 25000.6 | E21: 16/12/2018 | F21: 12000 | G21: 335.94 | I21: 26323.18 | J21: 17049.2 | K21: =L20 -> 31554 | L21: 31565 | M21: =L21-K21 -> 11 | N21: =O20 -> 24446 | O21: 24458 | P21: =O21-O20 -> 12 | Q21: =R20 -> 30647 | R21: 30659 | S21: =R21-R20 -> 12 | T21: =U20 -> 27931 | U21: 27937 | V21: =U21-U20 -> 6 | W21: =X20 -> 18205 | X21: 18205 | Y21: =X21-X20 -> 0 | Z21: =Y21+V21+S21+P21+M21 -> 41 | AA21: 40 | AB21: 195 | AC21: =PRINT!F20 -> 2377.87
A22: =Gen!A27 -> 43451 | B22: =Gen!B27 -> 0.2987 | C22: 20032.65 | D22: 25000.6 | G22: 581.31 | I22: 26331.8 | J22: 17056.2 | K22: =L21 -> 31565 | L22: 31582 | M22: =L22-K22 -> 17 | N22: =O21 -> 24458 | O22: 24468 | P22: =O22-O21 -> 10 | Q22: =R21 -> 30659 | R22: 30672 | S22: =R22-R21 -> 13 | T22: =U21 -> 27937 | U22: 27942 | V22: =U22-U21 -> 5 | W22: =X21 -> 18205 | X22: 18205 | Y22: =X22-X21 -> 0 | Z22: =Y22+V22+S22+P22+M22 -> 45 | AA22: 421 | AB22: 206 | AC22: =PRINT!F21 -> 2680.37
A23: =Gen!A28 -> 43452 | B23: =Gen!B28 -> 0.5065 | C23: 17352.28 | D23: 25000.6 | G23: 185.71 | I23: 26341.1 | J23: 17063.8 | K23: =L22 -> 31582 | L23: 31594 | M23: =L23-K23 -> 12 | N23: =O22 -> 24468 | O23: 24484 | P23: =O23-O22 -> 16 | Q23: =R22 -> 30672 | R23: 30682 | S23: =R23-R22 -> 10 | T23: =U22 -> 27942 | U23: 27948 | V23: =U23-U22 -> 6 | W23: =X22 -> 18205 | X23: 18205 | Y23: =X23-X22 -> 0 | Z23: =Y23+V23+S23+P23+M23 -> 44 | AA23: 457 | AB23: 213 | AC23: =PRINT!F22 -> 2557.69
A24: =Gen!A29 -> 43453 | B24: =Gen!B29 -> 0.4416 | C24: 14794.59 | D24: 25000.6 | G24: 118 | I24: 26349.8 | J24: 17071.3 | K24: =L23 -> 31594 | L24: 31604 | M24: =L24-K24 -> 10 | N24: =O23 -> 24484 | O24: 24494 | P24: =O24-O23 -> 10 | Q24: =R23 -> 30682 | R24: 30691 | S24: =R24-R23 -> 9 | T24: =U23 -> 27948 | U24: 27964 | V24: =U24-U23 -> 16 | W24: =X23 -> 18205 | X24: 18205 | Y24: =X24-X23 -> 0 | Z24: =Y24+V24+S24+P24+M24 -> 45 | AA24: 445 | AB24: 230 | AC24: =PRINT!F23 -> 2376.75
A25: =Gen!A30 -> 43454 | B25: =Gen!B30 -> 0.4026 | C25: 12417.84 | D25: 25000.6 | G25: 690.09 | I25: 26358.6 | J25: 17078.6 | K25: =L24 -> 31604 | L25: 31615 | M25: =L25-K25 -> 11 | N25: =O24 -> 24494 | O25: 24508 | P25: =O25-O24 -> 14 | Q25: =R24 -> 30691 | R25: 30699 | S25: =R25-R24 -> 8 | T25: =U24 -> 27964 | U25: 27974 | V25: =U25-U24 -> 10 | W25: =X24 -> 18205 | X25: 18205 | Y25: =X25-X24 -> 0 | Z25: =Y25+V25+S25+P25+M25 -> 43 | AA25: 468 | AB25: 210 | AC25: =PRINT!F24 -> 3045.42
A26: =Gen!A31 -> 43455 | B26: =Gen!B31 -> 0.4935 | C26: 9372.42 | D26: 25000.6 | G26: 544.38 | I26: 26367.3 | J26: 17085.9 | K26: =L25 -> 31615 | L26: 31624 | M26: =L26-K26 -> 9 | N26: =O25 -> 24508 | O26: 24518 | P26: =O26-O25 -> 10 | Q26: =R25 -> 30699 | R26: 30713 | S26: =R26-R25 -> 14 | T26: =U25 -> 27974 | U26: 27986 | V26: =U26-U25 -> 12 | W26: =X25 -> 18205 | X26: 18205 | Y26: =X26-X25 -> 0 | Z26: =Y26+V26+S26+P26+M26 -> 45 | AA26: 455 | AB26: 220 | AC26: =PRINT!F25 -> 2703.78
A27: =Gen!A32 -> 43456 | B27: =Gen!B32 -> 0.4935 | C27: 6668.64 | D27: 25000.6 | G27: 322.73 | I27: 26376.2 | J27: 17094.1 | K27: =L26 -> 31624 | L27: 31635 | M27: =L27-K27 -> 11 | N27: =O26 -> 24518 | O27: 24528 | P27: =O27-O26 -> 10 | Q27: =R26 -> 30713 | R27: 30729 | S27: =R27-R26 -> 16 | T27: =U26 -> 27986 | U27: 27995 | V27: =U27-U26 -> 9 | W27: =X26 -> 18205 | X27: 18205 | Y27: =X27-X26 -> 0 | Z27: =Y27+V27+S27+P27+M27 -> 46 | AA27: 473 | AB27: 218 | AC27: =PRINT!F26 -> 2823.75
A28: =Gen!A33 -> 43457 | B28: =Gen!B33 -> 0.4456 | C28: 23468.64 | D28: 22176.85 | G28: 93.91 | I28: 26385.1 | J28: 17101.9 | K28: =L27 -> 31635 | L28: 31648 | M28: =L28-K28 -> 13 | N28: =O27 -> 24528 | O28: 24541 | P28: =O28-O27 -> 13 | Q28: =R27 -> 30729 | R28: 30731 | S28: =R28-R27 -> 2 | T28: =U27 -> 27995 | U28: 28004 | V28: =U28-U27 -> 9 | W28: =X27 -> 18205 | X28: 18217 | Y28: =X28-X27 -> 12 | Z28: =Y28+V28+S28+P28+M28 -> 49 | AA28: 481 | AB28: 216 | AC28: =PRINT!F27 -> 2469.38
A29: =Gen!A34 -> 43458 | B29: =Gen!B34 -> 0.5065 | C29: 23468.64 | D29: 19707.47 | G29: 786.27 | I29: 26395.5 | J29: 17109.8 | K29: =L28 -> 31648 | L29: 31661 | M29: =L29-K29 -> 13 | N29: =O28 -> 24541 | O29: 24549 | P29: =O29-O28 -> 8 | Q29: =R28 -> 30731 | R29: 30741 | S29: =R29-R28 -> 10 | T29: =U28 -> 28004 | U29: 28014 | V29: =U29-U28 -> 10 | W29: =X28 -> 18217 | X29: 15224 | Y29: =X29-X28 -> -2993 | Z29: =Y29+V29+S29+P29+M29 -> -2952 | AA29: 468 | AB29: 210 | AC29: =PRINT!F28 -> 3494.55
A30: =Gen!A35 -> 43459 | B30: =Gen!B35 -> 0.9481 | C30: 23468.64 | D30: 16212.97 | G30: 174.44 | I30: 26406.3 | J30: 17117.6 | K30: =L29 -> 31661 | L30: 31672 | M30: =L30-K30 -> 11 | N30: =O29 -> 24549 | O30: 24560 | P30: =O30-O29 -> 11 | Q30: =R29 -> 30741 | R30: 30755 | S30: =R30-R29 -> 14 | T30: =U29 -> 28014 | U30: 28024 | V30: =U30-U29 -> 10 | W30: =X29 -> 15224 | X30: 15238 | Y30: =X30-X29 -> 14 | Z30: =Y30+V30+S30+P30+M30 -> 60 | AA30: 590 | AB30: 246 | AC30: =PRINT!F29 -> 2984.84
A31: =Gen!A36 -> 43460 | B31: =Gen!B36 -> 0.9091 | C31: 23468.64 | D31: 13228.37 | G31: 356..08 | I31: 26417.2 | J31: 17125.5 | K31: =L30 -> 31672 | L31: 31692 | M31: =L31-K31 -> 20 | N31: =O30 -> 24560 | O31: 24578 | P31: =O31-O30 -> 18 | Q31: =R30 -> 30755 | R31: 30763 | S31: =R31-R30 -> 8 | T31: =U30 -> 28024 | U31: 28030 | V31: =U31-U30 -> 6 | W31: =X30 -> 15238 | X31: 15246 | Y31: =X31-X30 -> 8 | Z31: =Y31+V31+S31+P31+M31 -> 60 | AA31: 568 | AB31: 218 | AC31: =PRINT!F30 -> 3221.58
A32: =Gen!A37 -> 43461 | B32: =Gen!B37 -> 0.7662 | C32: 23468.64 | D32: 10006.55 | G32: 203.69 | I32: 26428.7 | J32: 17133.7 | K32: =L31 -> 31692 | L32: 31702 | M32: =L32-K32 -> 10 | N32: =O31 -> 24578 | O32: 24593 | P32: =O32-O31 -> 15 | Q32: =R31 -> 30763 | R32: 30772 | S32: =R32-R31 -> 9 | T32: =U31 -> 28030 | U32: 28045 | V32: =U32-U31 -> 15 | W32: =X31 -> 15246 | X32: 15253 | Y32: =X32-X31 -> 7 | Z32: =Y32+V32+S32+P32+M32 -> 56 | AA32: 575 | AB32: 260 | AC32: =PRINT!F31 -> 2839.03
A33: =Gen!A38 -> 43462 | B33: =Gen!B38 -> 0.7792 | C33: 23468.64 | D33: 19167.52 | E33: 28/12/2018 | F33: 12000 | G33: 321.45 | I33: 26439.9 | J33: 17142.7 | K33: =L32 -> 31702 | L33: 31718 | M33: =L33-K33 -> 16 | N33: =O32 -> 24593 | O33: 24609 | P33: =O33-O32 -> 16 | Q33: =R32 -> 30772 | R33: 30790 | S33: =R33-R32 -> 18 | T33: =U32 -> 28045 | U33: 28052 | V33: =U33-U32 -> 7 | W33: =X32 -> 15253 | X33: 15259 | Y33: =X33-X32 -> 6 | Z33: =Y33+V33+S33+P33+M33 -> 63 | AA33: 630 | AB33: 250 | AC33: =PRINT!F32 -> 3364.79
A34: =Gen!A39 -> 43463 | B34: =Gen!B39 -> 0.9221 | C34: 23468.64 | D34: 15802.73 | G34: 247.04 | I34: 26451.8 | J34: 17152.3 | K34: =L33 -> 31718 | L34: 31728 | M34: =L34-K34 -> 10 | N34: =O33 -> 24609 | O34: 24624 | P34: =O34-O33 -> 15 | Q34: =R33 -> 30790 | R34: 30802 | S34: =R34-R33 -> 12 | T34: =U33 -> 28052 | U34: 28064 | V34: =U34-U33 -> 12 | W34: =X33 -> 15259 | X34: 15271 | Y34: =X34-X33 -> 12 | Z34: =Y34+V34+S34+P34+M34 -> 61 | AA34: 640 | AB34: 260 | AC34: =PRINT!F33 -> 3119.02
A35: =Gen!A40 -> 43464 | B35: =Gen!B40 -> 0.7792 | C35: 23468.64 | D35: 12683.71 | G35: 120.12 | I35: 26463.3 | J35: 17161.6 | K35: =L34 -> 31728 | L35: 31740 | M35: =L35-K35 -> 12 | N35: =O34 -> 24624 | O35: 24638 | P35: =O35-O34 -> 14 | Q35: =R34 -> 30802 | R35: 30813 | S35: =R35-R34 -> 11 | T35: =U34 -> 28064 | U35: 28076 | V35: =U35-U34 -> 12 | W35: =X34 -> 15271 | X35: 15282 | Y35: =X35-X34 -> 11 | Z35: =Y35+V35+S35+P35+M35 -> 60 | AA35: 596 | AB35: 250 | AC35: =PRINT!F34 -> 3292.63
A36: =Gen!A41 -> 43465 | B36: =Gen!B41 -> 0.8442 | C36: 23468.64 | D36: 21391.08 | E36: 31/12/2018 | F36: 12000 | G36: 1284.14 | I36: 26474.8 | J36: 17170.8 | K36: =L35 -> 31740 | L36: 31754 | M36: =L36-K36 -> 14 | N36: =O35 -> 24638 | O36: 24656 | P36: =O36-O35 -> 18 | Q36: =R35 -> 30813 | R36: 30827 | S36: =R36-R35 -> 14 | T36: =U35 -> 28076 | U36: 28088 | V36: =U36-U35 -> 12 | W36: =X35 -> 15282 | X36: 15289 | Y36: =X36-X35 -> 7 | Z36: =Y36+V36+S36+P36+M36 -> 65 | AA36: 568 | AB36: 255 | AC36: =PRINT!F35 -> 4342.9
A37: =Gen!A42 -> 0 | B37: =Gen!B42 -> 0 | C37: 23468.64 | D37: 17046.13 | K37: =L36 -> 31754 | M37: =L37-K37 -> -31754 | N37: =O36 -> 24656 | P37: =O37-O36 -> -24656 | Q37: =R36 -> 30827 | S37: =R37-R36 -> -30827 | T37: =U36 -> 28088 | V37: =U37-T37 -> -28088 | W37: =X36 -> 15289 | Y37: =X37-X36 -> -15289 | Z37: =Y37+V37+S37+P37+M37 -> -130614 | AC37: =PRINT!F36 -> 0

Sheet Gen
D2: HLP REPORT NOVEMBER 2018
F6: BILILA LODGE INVESTMENT LIMITED | V6: 1 | W6: 2 | X6: 3 | Y6: 4 | Z6: 5 | AA6: 6 | AB6: 7 | AC6: 8 | AD6: 9 | AE6: 10 | AF6: 11
F7: Diesel Consumed by 500KVA Generator | M7: 500KVA Generator KWh | V7: Safari-STAFF | W7: Safari-STAFF | X7: Lc/swg/gust | Y7: Eng pikcup | Z7: VIP Safari Car | AA7: GX Guest | AB7: GX Guest | AC7: T/Hillux/pur | AD7: TATA | AE7: MAN | AF7: F/Truck | AG7: Incenerator | AH7: A&K | AI7: OTHER | AJ7: TOTAL CO
A8: Date | B8: Occupenccy % | C8: OPENING | D8: Received | E8: Schedule delivery | F8: PRICE | G8: 1 | H8: 2 | I8: 3 | J8: 4 | K8: 5 | L8: 6 | M8: 1 | N8: 2 | O8: 3 | P8: 4 | Q8: 5 | R8: 6 | S8: Total Diseal Consumed | T8: Total Kwh generated | U8: Average Diesel/Kwh | V8: T 128 AXJ | W8: T 134 AXJ | X8: T 499 AXG | Y8: T 217 CHV | Z8: T 214 CHV | AA8: T 139 AXE | AB8: T 242 AXN - SABASABA | AC8: T 476 AWZ | AD8: T 226 AUQ | AE8: T 308 CLD | AF8: T 852 AWU | AG8: Machine ENG | AH8: Vehicle | AI8: Vehicle | AR8: Total Diseal Consumed Gen & Vehicle | AS8: Total cost /Day (TSH) | AT8: BALANCE
C9: =#REF! -> #REF! | S9: =SUM(F9:L9) -> 0 | T9: =SUM(M9:R9) -> 0 | AR9: =SUM(AJ9+S9) -> 0
S10: =SUM(F10:L10) -> 0 | T10: =SUM(M10:R10) -> 0 | U10: =SUM(N10:S10) -> 0 | AJ10: =SUM(V7:AL7) -> 0 | AR10: =SUM(AJ10+S10) -> 0 | AT10: =C10+D10-AR10 -> 0
A11: 43435 | B11: 0.168 | C11: =SUM(C9+D11) -> #REF! | G11: 411.83 | H11: 420.05 | J11: 529.14 | K11: 464.11 | M11: 999 | N11: 1080 | P11: 1332 | Q11: 1144 | S11: =SUM(F11:L11) -> 1825.13 | T11: =SUM(M11:R11) -> 4555 | U11: =S11/T11 -> 0.40068716 | W11: 22.45 | Z11: 20.34 | AJ11: =SUM(V11:AI11) -> 42.79 | AR11: =SUM(AJ11+S11) -> 1867.92 | AS11: =AR11*AU11 -> 54169.68 | AT11: =C11 -> #REF! | AU11: =SUM('Summery Report'!Q2) -> 29
A12: 43436 | B12: 0.1429 | C12: =SUM(C11-AR11+D12) -> #REF! | E12: 17000 | G12: 275.42 | H12: 810.66 | J12: 325.48 | K12: 423.63 | M12: 709 | N12: 2022 | P12: 829 | Q12: 1119 | S12: =SUM(F12:L12) -> 1835.19 | T12: =SUM(M12:R12) -> 4679 | U12: =S12/T12 -> 0.39221842 | V12: 42.81 | W12: 25.71 | Z12: 22.08 | AJ12: =SUM(V12:AI12) -> 90.6 | AR12: =SUM(AJ12+S12) -> 1925.79 | AS12: =AR12*AU12 -> 55847.91 | AT12: =C12 -> #REF! | AU12: =SUM(AU11) -> 29
A13: 43437 | B13: 0.1429 | C13: =SUM(C12-AR12+D13) -> #REF! | G13: 326.79 | H13: 294.45 | J13: 458.74 | K13: 688.07 | L13: 1000 | M13: 678 | N13: 736 | P13: 1189 | Q13: 1834 | S13: =SUM(F13:L13) -> 2768.05 | T13: =SUM(M13:R13) -> 4437 | U13: =S13/T13 -> 0.62385621 | V13: 9.81 | Z13: 23.1 | AF13: 60.46 | AH13: 15 | AJ13: =SUM(V13:AI13) -> 108.37 | AR13: =SUM(AJ13+S13) -> 2876.42 | AS13: =AR13*AU13 -> 83416.18 | AT13: =C13 -> #REF! | AU13: =SUM(AU12) -> 29
A14: 43438 | B14: 0.1688 | C14: =SUM(C13-AR13+D14) -> #REF! | D14: 17000 | G14: 472.76 | H14: 688.95 | J14: 451.46 | K14: 297.28 | M14: 1265 | N14: 1793 | P14: 1009 | Q14: 627 | S14: =SUM(F14:L14) -> 1910.45 | T14: =SUM(M14:R14) -> 4694 | U14: =S14/T14 -> 0.4069983 | V14: 20.31 | Y14: 89.74 | AJ14: =SUM(V14:AI14) -> 110.05 | AR14: =SUM(AJ14+S14) -> 2020.5 | AS14: =AR14*AU14 -> 58594.5 | AT14: =C14 -> #REF! | AU14: =SUM(AU13) -> 29
A15: 43439 | B15: 0.2078 | C15: =SUM(C14-AR14+D15) -> #REF! | G15: 425.39 | H15: 412.62 | J15: 679.19 | K15: 268.08 | M15: 1042 | N15: 954 | P15: 1749 | Q15: 614 | S15: =SUM(F15:L15) -> 1785.28 | T15: =SUM(M15:R15) -> 4359 | U15: =S15/T15 -> 0.40956183 | AJ15: =SUM(V15:AI15) -> 0 | AR15: =SUM(AJ15+S15) -> 1785.28 | AS15: =AR15*AU15 -> 51773.12 | AT15: =C15 -> #REF! | AU15: =SUM(AU14) -> 29
A16: 43440 | B16: 0.2987 | C16: =SUM(C15-AR15+D16) -> #REF! | G16: 354.62 | H16: 335.11 | J16: 469.05 | K16: 745.08 | M16: 838 | N16: 837 | P16: 1165 | Q16: 1870 | S16: =SUM(F16:L16) -> 1903.86 | T16: =SUM(M16:R16) -> 4710 | U16: =S16/T16 -> 0.40421656 | V16: 67.06 | Y16: 38.25 | Z16: 54.34 | AI16: 88 | AJ16: =SUM(V16:AI16) -> 247.65 | AR16: =SUM(AJ16+S16) -> 2151.51 | AS16: =AR16*AU16 -> 62393.79 | AT16: =C16 -> #REF! | AU16: =SUM(AU15) -> 29
A17: 43441 | B17: 0.2468 | C17: =SUM(C16-AR16+D17) -> #REF! | E17: 12000 | G17: 395.68 | H17: 395.8 | J17: 546.03 | K17: 672.68 | M17: 1042 | N17: 939 | P17: 1501 | Q17: 1393 | S17: =SUM(F17:L17) -> 2010.19 | T17: =SUM(M17:R17) -> 4875 | U17: =S17/T17 -> 0.41234667 | V17: 21.56 | W17: 23.62 | Y17: 23.99 | AI17: 155 | AJ17: =SUM(V17:AI17) -> 224.17 | AR17: =SUM(AJ17+S17) -> 2234.36 | AS17: =AR17*AU17 -> 64796.44 | AT17: =C17 -> #REF! | AU17: =SUM(AU16) -> 29
A18: 43442 | B18: 0.2857 | C18: =SUM(C17-AR17+D18) -> #REF! | G18: 407.47 | H18: 242.76 | J18: 702.49 | K18: 570.74 | M18: 1048 | N18: 693 | P18: 1685 | Q18: 1375 | S18: =SUM(F18:L18) -> 1923.46 | T18: =SUM(M18:R18) -> 4801 | U18: =S18/T18 -> 0.40063737 | AI18: 114 | AJ18: =SUM(V18:AI18) -> 114 | AR18: =SUM(AJ18+S18) -> 2037.46 | AS18: =AR18*AU18 -> 59086.34 | AT18: =C18 -> #REF! | AU18: =SUM(AU17) -> 29
A19: 43443 | B19: 0.4675 | C19: =SUM(C18-AR18+D19) -> #REF! | G19: 430.19 | H19: 369.89 | J19: 528.73 | K19: 714.75 | M19: 1182 | N19: 625 | P19: 1328 | Q19: 1774 | S19: =SUM(F19:L19) -> 2043.56 | T19: =SUM(M19:R19) -> 4909 | U19: =S19/T19 -> 0.41628845 | W19: 28.05 | Y19: 31.77 | Z19: 36.34 | AE19: 20.4 | AH19: 418 | AJ19: =SUM(V19:AI19) -> 534.56 | AR19: =SUM(AJ19+S19) -> 2578.12 | AS19: =AR19*AU19 -> 74765.48 | AT19: =C19 -> #REF! | AU19: =SUM(AU18) -> 29
A20: 43444 | B20: 0.5584 | C20: =SUM(C19-AR19+D20) -> #REF! | D20: 12000 | G20: 480.22 | H20: 623 | J20: 503.76 | K20: 496.25 | M20: 1246 | N20: 1562 | P20: 1226 | Q20: 1282 | S20: =SUM(F20:L20) -> 2103.23 | T20: =SUM(M20:R20) -> 5316 | U20: =S20/T20 -> 0.39564146 | V20: 104.39 | W20: 76.47 | Y20: 22.45 | AC20: 4.69 | AH20: 124 | AI20: 106 | AJ20: =SUM(V20:AI20) -> 438 | AR20: =SUM(AJ20+S20) -> 2541.23 | AS20: =AR20*AU20 -> 73695.67 | AT20: =C20 -> #REF! | AU20: =SUM(AU19) -> 29
A21: 43445 | B21: 0.5714 | C21: =SUM(C20-AR20+D21) -> #REF! | G21: 489.54 | H21: 516.02 | J21: 659.24 | K21: 379.53 | M21: 1153 | N21: 1304 | P21: 1700 | Q21: 765 | S21: =SUM(F21:L21) -> 2044.33 | T21: =SUM(M21:R21) -> 4922 | U21: =S21/T21 -> 0.41534539 | V21: 21.87 | Z21: 45.46 | AI21: 155 | AJ21: =SUM(V21:AI21) -> 222.33 | AR21: =SUM(AJ21+S21) -> 2266.66 | AS21: =AR21*AU21 -> 65733.14 | AT21: =C21 -> #REF! | AU21: =SUM(AU20) -> 29
A22: 43446 | B22: 0.2338 | C22: =SUM(C21-AR21+D22) -> #REF! | G22: 441.34 | H22: 613.96 | J22: 571.09 | K22: 290.85 | M22: 1165 | N22: 1440 | P22: 1474 | Q22: 791 | S22: =SUM(F22:L22) -> 1917.24 | T22: =SUM(M22:R22) -> 4870 | U22: =S22/T22 -> 0.39368378 | W22: 12.64 | Y22: 14.73 | Z22: 19.87 | AH22: 74 | AI22: 77 | AJ22: =SUM(V22:AI22) -> 198.24 | AR22: =SUM(AJ22+S22) -> 2115.48 | AS22: =AR22*AU22 -> 61348.92 | AT22: =C22 -> #REF! | AU22: =SUM(AU21) -> 29
A23: 43447 | B23: 0.2727 | C23: =SUM(C22-AR22+D23) -> #REF! | G23: 445.95 | H23: 724.23 | J23: 467.62 | K23: 253.78 | M23: 1026 | N23: 1851 | P23: 1275 | Q23: 508 | S23: =SUM(F23:L23) -> 1891.58 | T23: =SUM(M23:R23) -> 4660 | U23: =S23/T23 -> 0.40591845 | V23: 67.87 | W23: 27.84 | Z23: 18.39 | AJ23: =SUM(V23:AI23) -> 114.1 | AR23: =SUM(AJ23+S23) -> 2005.68 | AS23: =AR23*AU23 -> 58164.72 | AT23: =C23 -> #REF! | AU23: =SUM(AU22) -> 29
A24: 43448 | B24: 0.2595 | C24: =SUM(C23-AR23+D24) -> #REF! | G24: 642.59 | H24: 387.52 | J24: 411.4 | K24: 550.93 | M24: 1571 | N24: 954 | P24: 925 | Q24: 1298 | S24: =SUM(F24:L24) -> 1992.44 | T24: =SUM(M24:R24) -> 4748 | U24: =S24/T24 -> 0.41963774 | V24: 45.96 | Z24: 25.09 | AF24: 49.47 | AH24: 195 | AJ24: =SUM(V24:AI24) -> 315.52 | AR24: =SUM(AJ24+S24) -> 2307.96 | AS24: =AR24*AU24 -> 66930.84 | AT24: =C24 -> #REF! | AU24: =SUM(AU23) -> 29
A25: 43449 | B25: 0.1299 | C25: =SUM(C24-AR24+D25) -> #REF! | G25: 489.47 | H25: 285.18 | J25: 576.47 | K25: 586.86 | M25: 1208 | N25: 628 | P25: 1488 | Q25: 1400 | S25: =SUM(F25:L25) -> 1937.98 | T25: =SUM(M25:R25) -> 4724 | U25: =S25/T25 -> 0.41024132 | AE25: 263.59 | AF25: 7.73 | AH25: 250 | AI25: 50 | AJ25: =SUM(V25:AI25) -> 571.32 | AR25: =SUM(AJ25+S25) -> 2509.3 | AS25: =AR25*AU25 -> 72769.7 | AT25: =C25 -> #REF! | AU25: =SUM(AU24) -> 29
A26: 43450 | B26: 0.2597 | C26: =SUM(C25-AR25+D26) -> #REF! | D26: 12000 | E26: 12000 | G26: 507.45 | H26: 651.55 | J26: 558.03 | K26: 305.09 | L26: 20.01 | M26: 1218 | N26: 1520 | P26: 1453 | Q26: 814 | S26: =SUM(F26:L26) -> 2042.13 | T26: =SUM(M26:R26) -> 5005 | U26: =S26/T26 -> 0.40801798 | V26: 46.21 | X26: 64.07 | Z26: 19.46 | AH26: 121 | AI26: 85 | AJ26: =SUM(V26:AI26) -> 335.74 | AR26: =SUM(AJ26+S26) -> 2377.87 | AS26: =AR26*AU26 -> 68958.23 | AT26: =C26 -> #REF! | AU26: =SUM(AU25) -> 29
A27: 43451 | B27: 0.2987 | C27: =SUM(C26-AR26+D27) -> #REF! | G27: 787.66 | H27: 481.46 | J27: 645.62 | K27: 184.32 | M27: 2022 | N27: 1197 | P27: 1680 | Q27: 433 | S27: =SUM(F27:L27) -> 2099.06 | T27: =SUM(M27:R27) -> 5332 | U27: =S27/T27 -> 0.39367217 | V27: 23.89 | X27: 29.88 | AD27: 226.54 | AH27: 101 | AI27: 200 | AJ27: =SUM(V27:AI27) -> 581.31 | AR27: =SUM(AJ27+S27) -> 2680.37 | AS27: =AR27*AU27 -> 77730.73 | AT27: =C27 -> #REF! | AU27: =SUM(AU26) -> 29
A28: 43452 | B28: 0.5065 | C28: =SUM(C27-AR27+D28) -> #REF! | G28: 643.39 | H28: 796.21 | J28: 563.28 | K28: 369.1 | M28: 1646 | N28: 2030 | P28: 1304 | Q28: 910 | S28: =SUM(F28:L28) -> 2371.98 | T28: =SUM(M28:R28) -> 5890 | U28: =S28/T28 -> 0.40271307 | V28: 11.71 | AI28: 174 | AJ28: =SUM(V28:AI28) -> 185.71 | AR28: =SUM(AJ28+S28) -> 2557.69 | AS28: =AR28*AU28 -> 74173.01 | AT28: =C28 -> #REF! | AU28: =SUM(AU27) -> 29
A29: 43453 | B29: 0.4416 | C29: =SUM(C28-AR28+D29) -> #REF! | G29: 579.14 | H29: 446.54 | J29: 359.47 | K29: 873.6 | M29: 1304 | N29: 1239 | P29: 996 | Q29: 2198 | S29: =SUM(F29:L29) -> 2258.75 | T29: =SUM(M29:R29) -> 5737 | U29: =S29/T29 -> 0.39371623 | AI29: 118 | AJ29: =SUM(V29:AI29) -> 118 | AR29: =SUM(AJ29+S29) -> 2376.75 | AS29: =AR29*AU29 -> 68925.75 | AT29: =C29 -> #REF! | AU29: =SUM(AU28) -> 29
A30: 43454 | B30: 0.4026 | C30: =SUM(C29-AR29+D30) -> #REF! | G30: 520.6 | H30: 836.04 | J30: 473.81 | K30: 524.88 | M30: 1237 | N30: 2000 | P30: 1103 | Q30: 1242 | S30: =SUM(F30:L30) -> 2355.33 | T30: =SUM(M30:R30) -> 5582 | U30: =S30/T30 -> 0.42195091 | W30: 59.98 | X30: 45.03 | Y30: 46.94 | AE30: 246.41 | AF30: 21.73 | AH30: 64 | AI30: 206 | AJ30: =SUM(V30:AI30) -> 690.09 | AR30: =SUM(AJ30+S30) -> 3045.42 | AS30: =AR30*AU30 -> 88317.18 | AT30: =C30 -> #REF! | AU30: =SUM(AU29) -> 29
A31: 43455 | B31: 0.4935 | C31: =SUM(C30-AR30+D31) -> #REF! | G31: 549.84 | H31: 366.56 | J31: 682.46 | K31: 560.54 | M31: 1267 | N31: 1163 | P31: 1762 | Q31: 1407 | S31: =SUM(F31:L31) -> 2159.4 | T31: =SUM(M31:R31) -> 5599 | U31: =S31/T31 -> 0.38567601 | X31: 40.38 | AI31: 504 | AJ31: =SUM(V31:AI31) -> 544.38 | AR31: =SUM(AJ31+S31) -> 2703.78 | AS31: =AR31*AU31 -> 78409.62 | AT31: =C31 -> #REF! | AU31: =SUM(AU30) -> 29
A32: 43456 | B32: 0.4935 | C32: =SUM(C31-AR31+D32) -> #REF! | D32: 16800 | E32: 17000 | G32: 487.4 | H32: 613.2 | J32: 882.34 | K32: 518.08 | M32: 1195 | N32: 1269 | P32: 2277 | Q32: 1187 | S32: =SUM(F32:L32) -> 2501.02 | T32: =SUM(M32:R32) -> 5928 | U32: =S32/T32 -> 0.42189946 | V32: 49.73 | W32: 29.75 | Z32: 22.25 | AH32: 221 | AJ32: =SUM(V32:AH32) -> 322.73 | AR32: =SUM(AJ32+S32) -> 2823.75 | AS32: =AR32*AU32 -> 81888.75 | AT32: =C32 -> #REF! | AU32: =SUM(AU31) -> 29
A33: 43457 | B33: 0.4456 | C33: =SUM(C32-AR32+D33) -> #REF! | G33: 723.52 | H33: 626.43 | J33: 473.6 | K33: 551.92 | M33: 1693 | N33: 1591 | P33: 1366 | Q33: 1200 | S33: =SUM(F33:L33) -> 2375.47 | T33: =SUM(M33:R33) -> 5850 | U33: =S33/T33 -> 0.40606325 | V33: 54.78 | Y33: 14.13 | AI33: 25 | AJ33: =SUM(V33:AI33) -> 93.91 | AR33: =SUM(AJ33+S33) -> 2469.38 | AS33: =AR33*AU33 -> 71612.02 | AT33: =C33 -> #REF! | AU33: =SUM(AU32) -> 29
A34: 43458 | B34: 0.5065 | C34: =SUM(C33-AR33+D34) -> #REF! | G34: 615.89 | H34: 442.36 | J34: 539.06 | K34: 542.81 | L34: 568.16 | M34: 1518 | N34: 1195 | P34: 1265 | Q34: 1225 | R34: 944 | S34: =SUM(F34:L34) -> 2708.28 | T34: =SUM(M34:R34) -> 6147 | U34: =S34/T34 -> 0.44058565 | W34: 22.97 | X34: 30.3 | AH34: 110 | AI34: 623 | AJ34: =SUM(V34:AI34) -> 786.27 | AR34: =SUM(AJ34+S34) -> 3494.55 | AS34: =AR34*AU34 -> 101341.95 | AT34: =C34 -> #REF! | AU34: =SUM(AU33) -> 29
A35: 43459 | B35: 0.9481 | C35: =SUM(C34-AR34+D35) -> #REF! | G35: 453.71 | H35: 539.32 | J35: 684.88 | K35: 521.76 | L35: 610.73 | M35: 1117 | N35: 1149 | P35: 1494 | Q35: 1210 | R35: 1508 | S35: =SUM(F35:L35) -> 2810.4 | T35: =SUM(M35:R35) -> 6478 | U35: =S35/T35 -> 0.4338376 | W35: 30.04 | X35: 22.5 | Y35: 24.9 | AI35: 97 | AJ35: =SUM(V35:AI35) -> 174.44 | AR35: =SUM(AJ35+S35) -> 2984.84 | AS35: =AR35*AU35 -> 86560.36 | AT35: =C35 -> #REF! | AU35: =SUM(AU34) -> 29
A36: 43460 | B36: 0.9091 | C36: =SUM(C35-AR35+D36) -> #REF! | G36: 1006.77 | H36: 877.35 | J36: 283.78 | K36: 262.24 | L36: 435.36 | M36: 2437 | N36: 2138 | P36: 662 | Q36: 505 | R36: 894 | S36: =SUM(F36:L36) -> 2865.5 | T36: =SUM(M36:R36) -> 6636 | U36: =S36/T36 -> 0.43181133 | Y36: 40.08 | AI36: 316 | AJ36: =SUM(V36:AI36) -> 356.08 | AR36: =SUM(AJ36+S36) -> 3221.58 | AS36: =AR36*AU36 -> 93425.82 | AT36: =C36 -> #REF! | AU36: =SUM(AU35) -> 29
A37: 43461 | B37: 0.7662 | C37: =SUM(C36-AR36+D37) -> #REF! | G37: 422.76 | H37: 724.97 | J37: 443.05 | K37: 757.95 | L37: 286.61 | M37: 1203 | N37: 1763 | P37: 1131 | Q37: 1761 | R37: 725 | S37: =SUM(F37:L37) -> 2635.34 | T37: =SUM(M37:R37) -> 6583 | U37: =S37/T37 -> 0.40032508 | Y37: 32.8 | Z37: 11.89 | AI37: 159 | AJ37: =SUM(V37:AI37) -> 203.69 | AR37: =SUM(AJ37+S37) -> 2839.03 | AS37: =AR37*AU37 -> 82331.87 | AT37: =C37 -> #REF! | AU37: =SUM(AU36) -> 29
A38: 43462 | B38: 0.7792 | C38: =SUM(C37-AR37+D38) -> #REF! | D38: 12000 | E38: 12000 | G38: 817.51 | H38: 666.8 | J38: 964.52 | K38: 308.94 | L38: 285.57 | M38: 1971 | N38: 1641 | P38: 2220 | Q38: 679 | R38: 583 | S38: =SUM(F38:L38) -> 3043.34 | T38: =SUM(M38:R38) -> 7094 | U38: =S38/T38 -> 0.42900197 | V38: 47.5 | W38: 68.95 | Z38: 20 | AH38: 89 | AI38: 96 | AJ38: =SUM(V38:AI38) -> 321.45 | AR38: =SUM(AJ38+S38) -> 3364.79 | AS38: =AR38*AU38 -> 97578.91 | AT38: =C38 -> #REF! | AU38: =SUM(AU37) -> 29
A39: 43463 | B39: 0.9221 | C39: =SUM(C38-AR38+D39) -> #REF! | G39: 511.39 | H39: 697.5 | J39: 639.85 | K39: 563.99 | L39: 459.25 | M39: 1296 | N39: 1774 | P39: 1588 | Q39: 1369 | R39: 1601 | S39: =SUM(F39:L39) -> 2871.98 | T39: =SUM(M39:R39) -> 7628 | U39: =S39/T39 -> 0.37650498 | Z39: 24.04 | AI39: 223 | AJ39: =SUM(V39:AI39) -> 247.04 | AR39: =SUM(AJ39+S39) -> 3119.02 | AS39: =AR39*AU39 -> 90451.58 | AT39: =C39 -> #REF! | AU39: =SUM(AU38) -> 29
A40: 43464 | B40: 0.7792 | C40: =SUM(C39-AR39+D40) -> #REF! | E40: 12000 | G40: 669.58 | H40: 622.13 | J40: 462.12 | K40: 603.15 | L40: 815.53 | M40: 1571 | N40: 1571 | P40: 1336 | Q40: 1402 | R40: 1498 | S40: =SUM(F40:L40) -> 3172.51 | T40: =SUM(M40:R40) -> 7378 | U40: =S40/T40 -> 0.42999593 | Z40: 18.12 | AH40: 102 | AJ40: =SUM(V40:AI40) -> 120.12 | AR40: =SUM(AJ40+S40) -> 3292.63 | AS40: =AR40*AU40 -> 95486.27 | AT40: =C40 -> #REF! | AU40: =SUM(AU39) -> 29
A41: 43465 | B41: 0.8442 | C41: =SUM(C40-AR40+D41) -> #REF! | D41: 12000 | G41: 661.03 | H41: 793.58 | J41: 747.58 | K41: 496.47 | L41: 360.1 | M41: 1557 | N41: 1960 | P41: 1727 | Q41: 1115 | R41: 896 | S41: =SUM(F41:L41) -> 3058.76 | T41: =SUM(M41:R41) -> 7255 | U41: =S41/T41 -> 0.42160717 | W41: 29.62 | Y41: 43.72 | Z41: 11.8 | AH41: 679 | AI41: 520 | AJ41: =SUM(V41:AI41) -> 1284.14 | AR41: =SUM(AJ41+S41) -> 4342.9 | AS41: =AR41*AU41 -> 125944.1 | AT41: =C41 -> #REF! | AU41: =SUM(AU40) -> 29
C42: =SUM(C41-AR41+D42) -> #REF! | S42: =SUM(F42:L42) -> 0 | T42: =SUM(M42:R42) -> 0 | AJ42: =SUM(V42:AI42) -> 0 | AR42: =SUM(AJ42+S42) -> 0 | AS42: =AR42*AU42 -> 0 | AT42: =C42 -> #REF!
A43: BF | C43: =SUM(C42-AR42+D43) -> #REF! | S43: =SUM(F43:L43) -> 0 | T43: =SUM(M43:R43) -> 0 | AJ43: =SUM(V43:AI43) -> 0 | AR43: =SUM(AJ43+S43) -> 0 | AS43: =AR43*AU43 -> 0 | AT43: =C43 -> #REF!
S44: =SUM(F44:L44) -> 0 | AJ44: =SUM(V44:AI44) -> 0 | AR44: =S44+AJ44 -> 0 | AS44: =AR44*AU44 -> 0 | AT44: =C44+D44-AR44 -> 0
D45: =SUM(D11:D44) -> 81800 | E45: =SUM(E11:E42) -> 82000 | F45: =SUM(F11:F44) -> 0 | G45: =SUM(G11:G44) -> 16446.9 | H45: =SUM(H11:H44) -> 17302.2 | I45: =SUM(I12:I44) -> 0 | J45: =SUM(J11:J44) -> 17283.34 | K45: =SUM(K11:K44) -> 15347.46 | L45: =SUM(L11:L44) -> 4841.32 | M45: =SUM(M11:M44) -> 40424 | N45: =SUM(N11:N44) -> 42618 | O45: =SUM(O11:O44) -> 0 | P45: =SUM(P11:P43) -> 43239 | Q45: =SUM(Q11:Q44) -> 36451 | R45: =SUM(R11:R44) -> 8649 | S45: =SUM(F45:L45) -> 71221.22 | T45: =SUM(M45:R45) -> 171381 | U45: =SUM(U11:U42) -> 12.904658 | V45: =SUM(V9:V44) -> 635.46 | W45: =SUM(W9:W44) -> 458.09 | X45: =SUM(X9:X44) -> 232.16 | Y45: =SUM(Y9:Y44) -> 423.5 | Z45: =SUM(Z9:Z44) -> 392.57 | AA45: =SUM(AA9:AA44) -> 0 | AB45: =SUM(AB9:AB44) -> 0 | AC45: =SUM(AC9:AC44) -> 4.69 | ... AH45: =SUM(AH9:AH44) -> 2563 | AI45: =SUM(AI10:AI44) -> 4091 | AJ45: =SUM(AJ9:AJ44) -> 9696.8 | AR45: =SUM(AR11:AR43) -> 80918.02 | AS45: =SUM(AS11:AS44) -> 2346622.6
A46: Nb Day | AJ46: 0 | AQ46: =SUM(AQ45/12) -> 0
A47: 31 | R47: =SUM(S47+#REF!) -> #REF! | T47: =S45*2143 -> 1.5262707e+08 | U47: TZS | W47: =SUM(W45/A47) -> 14.777097 | X47: =SUM(X45/A47) -> 7.4890323 | Y47: =SUM(Y45/A47) -> 13.66129 | Z47: =SUM(Z45/A47) -> 12.663548 | AA47: =SUM(AA45/A47) -> 0 | AB47: =SUM(AB45/A47) -> 0 | AC47: =SUM(AC45/A47) -> 0.15129032 | AD47: =SUM(AD45/A47) -> 7.3077419 | AF47: =SUM(AF45/A47) -> 4.4964516 | AG47: =SUM(AG45/A47) -> 0 | AQ47: =SUM(AQ45/A47) -> 0
A48: Av. Occ | B48: =SUM(B11:B41)/A47 -> 0.45003548 | T48: =T47/2245 -> 67985.334 | U48: USD | AR48: =AVERAGE(AR11:AR24) -> 2193.8836
AJ49: =SUM(AJ10:AJ25)/A47 -> 107.47419 | AR49: =SUM(AQ45*'Summery Report'!Q2) -> 0
B50: A & K VEHICLES | F50: MAULY VEHICLES | L50: GREENLAND VEHICLE | S50: OTHERS VEHICLES | AJ50: =SUM(#REF!-AI41)/14 -> #REF!
B51: Date | C51: Vehicles | D51: Liters | E51: Driver name | F51: Date | H51: Vehicles | I51: Liters | K51: Driver name | L51: Date | N51: Vehicles | O51: Liters | Q51: Driver name | R51: Authorized Manager | S51: Date | T51: Vehicles | U51: Liters | V51: Driver name | W51: Athorized Manager | X51: Reasons
B52: 43171 | C52: T737DCD | D52: 15 | E52: Richard | L52: 43263 | N52: T739BRW | O52: 88 | Q52: Naftari | R52: kimaro | S52: 23/12/2018 | T52: DFP8706 | U52: 25 | V52: Juma said | W52: Joel | X52: Wosha
B53: 43355 | C53: T737DCD | D53: 120 | E53: Dickson | L53: 43293 | N53: T559DLW | O53: 40 | Q53: Fredi | R53: kimaro
B54: 43355 | C54: T880DKQ | D54: 110 | E54: Jackob | L54: 43293 | N54: T494DLP | O54: 115 | Q54: David | R54: kimaro
B55: 43355 | C55: T882DKQ | D55: 93 | E55: Joseph | L55: 43324 | N55: T834CFA | O55: 114 | Q55: Shabani | R55: kimaro
B56: 43355 | C56: T106CWQ | D56: 95 | E56: Emanuel | L56: 43385 | N56: T739BRW | O56: 106 | Q56: Naftari | R56: kimaro
B57: 43385 | C57: T840DDW | D57: 124 | E57: Kimambo | M57: 43416 | N57: T559DLW | P57: 83 | Q57: Fredi | R57: Kimaro
B58: 43446 | C58: T106CWQ | D58: 74 | E58: Emanuel | M58: 43416 | N58: T594DLP | P58: 72 | Q58: Devid | R58: Kimaro
B59: 14/12/2018 | C59: T 840 DDW | D59: 58 | E59: Gurisha | L59: 43446 | N59: T834CFA | O59: 77 | Q59: Shabani | R59: kimaro
B60: 14/12/201 | C60: T 880 DKQ | D60: 137 | E60: Jackobo | L60: 15/12/2010 | N60: T 559 DLW | O60: 50 | Q60: Fredy | R60: kimaro
B61: 15/12/2010 | C61: T 737DCD | D61: 132 | E61: Dickson | M61: 16/12/2018 | N61: T594DLP | P61: 85 | Q61: Devid | R61: kimaro
B62: 15/12/2010 | C62: T 132 CWQ | D62: 118 | E62: Zakayo | L62: 17/12/2011 | N62: T 142 DKQ | O62: 69 | Q62: Comfort | R62: kimaro
B63: 16/12/2018 | C63: T882DKQ | D63: 121 | E63: Joseph | L63: 17/12/2018 | N63: T 755 CJQ | O63: 64 | Q63: Julius | R63: kimaro
B64: 17/12/2018 | C64: T 106 CWQ | D64: 101 | E64: Emanuel | L64: 17/12/2018 | N64: T 726 CCV | O64: 67 | Q64: Karume | R64: kimaro
B65: 20/12/2018 | C65: T882DKQ | D65: 64 | E65: Joseph | L65: 18/12/2018 | N65: T 662 CZG | O65: 68 | Q65: Henry | R65: kimaro
B66: 22/12/2018 | C66: T 111 CWQ | D66: 55 | E66: Sadiki | L66: 18/12/2018 | N66: T 834CFA | O66: 106 | Q66: Shabani | R66: kimaro
B67: 22/12/2018 | C67: T 132 CWQ | D67: 55 | E67: Zakayo | L67: 19/12/2018 | N67: T594DLP | O67: 118 | Q67: David | R67: kimaro
B68: 22/12/2018 | C68: T 737DCD | D68: 72 | E68: Dickson | L68: 20/12/2018 | N68: T928DQJ | O68: 70 | Q68: Michael | R68: kimaro
B69: 22/12/2018 | C69: T 364 AHF | D69: 39 | E69: Gurisha | L69: 20/12/2018 | N69: T165DKR | O69: 79 | Q69: Chande | R69: kimaro
B70: 24/12/2018 | C70: T880DKQ | D70: 110 | E70: Jackson | L70: 20/12/2018 | N70: T755CJQ | O70: 57 | Q70: Julius | R70: kimaro
B71: 28/12/2018 | C71: T882DKQ | D71: 89 | E71: Sadiki | L71: 21/12/2018 | N71: T142DKR | O71: 81 | Q71: Comfort | R71: kimaro
B72: 30/12/2018 | C72: T106CWQ | D72: 102 | E72: Emanuel | L72: 21/12/2018 | N72: T739BRW | O72: 162 | Q72: Naftari | R72: kimaro
B73: 31/12/2018 | C73: T840DDW | D73: 147 | E73: Kelvin | L73: 21/12/2018 | N73: T254DCP | O73: 121 | Q73: Raphael | R73: kimaro
... B76: 31/12/2018 | C76: T132CWQ | D76: 109 | E76: Dickson | L76: 24/12/2018 | N76: T142DKR | O76: 70 | Q76: Comfort | R76: kimaro
L77: 24/12/2018 | N77: T 142 DKR | O77: 70 | Q77: Comfort | R77: kimaro
B78: 31/12/2018 | C78: T880DKQ | D78: 104 | E78: Jackob | L78: 24/12/2018 | N78: T594DLP | O78: 117 | Q78: David | R78: kimaro
B79: 31/12/2018 | C79: T106CWQ | D79: 53 | E79: Emanuel | L79: 24/12/2018 | N79: T928DQJ | O79: 80 | Q79: Michael | R79: kimaro
B80: 31/12/2018 | C80: T675ANT | D80: 45 | E80: Emanuel | L80: 24/12/2018 | N80: T736CCV | O80: 103 | Q80: Karume | R80: kimaro
B81: 31/12/2018 | C81: T882DKQ | D81: 81 | E81: Sadick | L81: 24/12/2018 | N81: T755CJQ | O81: 85 | Q81: Julius | R81: kimaro
L82: 24/12/2018 | N82: T165DKR | O82: 83 | Q82: Chande | R82: kimaro
L83: 25/12/2018 | N83: T739BRW | O83: 97 | Q83: Naftari | R83: kimaro
L84: 26/12/2018 | N84: T834CFA | O84: 122 | Q84: Shabani | R84: kimaro
L85: 26/12/2018 | N85: T594DLP | O85: 81 | Q85: David | R85: kimaro
L86: 26/12/2018 | N86: T714BNE | O86: 113 | Q86: Mmari | R86: kimaro
L87: 27/12/2018 | N87: T254DCP | O87: 134 | Q87: Raphael | R87: kimaro
L88: 27/12/2018 | N88: T142DKR | O88: 25 | Q88: Comfort | R88: kimaro
L89: 28/12/2018 | N89: T142DKR | O89: 96 | Q89: Comfort | R89: kimaro
L90: 29/12/2018 | N90: T662CZG | O90: 85 | Q90: Henry | R90: kimaro
L91: 29/12/2018 | N91: T728CXC | O91: 139 | Q91: Jackson | R91: kimaro
L92: 31/12/2018 | N92: T437AFD | O92: 66 | Q92: Davis | R92: kimaro
L93: 31/12/2018 | N93: T928DQJ | O93: 105 | Q93: Michael | R93: kimaro
... L97: 31/12/2018 | N97: T736CCV | O97: 81 | Q97: Karume | R97: kimaro

Sheet Energy Graph
A1: Date | B1: Usage KWV | C1: Occ % | D1: Cost per room Total Occ | E1: Cost per room Guest Occ
A2: =SUM(Gen!A11) -> 43435 | B2: =SUM('Summery Report'!F5) -> 4555 | C2: =SUM('Summery Report'!C5) -> 0.168 | D2: =SUM('Summery Report'!R5) -> 2.2827509 | E2: =SUM('Summery Report'!S5) -> 2.2827509 | F2: 0.1
A3: =SUM(Gen!A12) -> 43436 | B3: =SUM('Summery Report'!F6) -> 4679 | C3: =SUM('Summery Report'!C6) -> 0.1429 | D3: =SUM('Summery Report'!R6) -> 2.7155456 | E3: =SUM('Summery Report'!S6) -> 2.7155456 | F3: 0.1375
A4: =SUM(Gen!A13) -> 43437 | B4: =SUM('Summery Report'!F7) -> 4437 | C4: =SUM('Summery Report'!C7) -> 0.1429 | D4: =SUM('Summery Report'!R7) -> 4.0560235 | E4: =SUM('Summery Report'!S7) -> 4.0560235 | F4: 0.0875
A5: =SUM(Gen!A14) -> 43438 | B5: =SUM('Summery Report'!F8) -> 4694 | C5: =SUM('Summery Report'!C8) -> 0.1688 | D5: =SUM('Summery Report'!R8) -> 2.4692162 | E5: =SUM('Summery Report'!S8) -> 2.4692162 | F5: 0.225
A6: =SUM(Gen!A15) -> 43439 | B6: =SUM('Summery Report'!F9) -> 4359 | C6: =SUM('Summery Report'!C9) -> 0.2078 | D6: =SUM('Summery Report'!R9) -> 2.7271976 | E6: =SUM('Summery Report'!S9) -> 2.7271976 | F6: 0.2
A7: =SUM(Gen!A16) -> 43440 | B7: =SUM('Summery Report'!F10) -> 4710 | C7: =SUM('Summery Report'!C10) -> 0.2987 | D7: =SUM('Summery Report'!R10) -> 2.6293211 | E7: =SUM('Summery Report'!S10) -> 2.6293211 | F7: 0.35
A8: =SUM(Gen!A17) -> 43441 | B8: =SUM('Summery Report'!F11) -> 4875 | C8: =SUM('Summery Report'!C11) -> 0.2468 | D8: =SUM('Summery Report'!R11) -> 2.0479279 | E8: =SUM('Summery Report'!S11) -> 2.0479279 | F8: 0.375
A9: =SUM(Gen!A18) -> 43442 | B9: =SUM('Summery Report'!F12) -> 4801 | C9: =SUM('Summery Report'!C12) -> 0.2857 | D9: =SUM('Summery Report'!R12) -> 1.6238757 | E9: =SUM('Summery Report'!S12) -> 1.6238757 | F9: 0.325
A10: =SUM(Gen!A19) -> 43443 | B10: =SUM('Summery Report'!F13) -> 4909 | C10: =SUM('Summery Report'!C13) -> 0.4675 | D10: =SUM('Summery Report'!R13) -> 1.2773 | E10: =SUM('Summery Report'!S13) -> 1.2773 | F10: 0.75
A11: =SUM(Gen!A20) -> 43444 | B11: =SUM('Summery Report'!F14) -> 5316 | C11: =SUM('Summery Report'!C14) -> 0.5584 | D11: =SUM('Summery Report'!R14) -> 1.0587241 | E11: =SUM('Summery Report'!S14) -> 1.0587241 | F11: 0.7625
A12: =SUM(Gen!A21) -> 43445 | B12: =SUM('Summery Report'!F15) -> 4922 | C12: =SUM('Summery Report'!C15) -> 0.5714 | D12: =SUM('Summery Report'!R15) -> 0.92334794 | E12: =SUM('Summery Report'!S15) -> 0.92334794 | F12: 0.1625
A13: =SUM(Gen!A22) -> 43446 | B13: =SUM('Summery Report'!F16) -> 4870 | C13: =SUM('Summery Report'!C16) -> 0.2338 | D13: =SUM('Summery Report'!R16) -> 1.8466354 | E13: =SUM('Summery Report'!S16) -> 1.8466354 | F13: 0.1125
... A32: =SUM(Gen!A41) -> 43465 | B32: =SUM('Summery Report'!F35) -> 7255 | C32: =SUM('Summery Report'!C35) -> 0.8442 | D32: =SUM('Summery Report'!R35) -> 1.2062225 | E32: =SUM('Summery Report'!S35) -> 1.2062225 | F32: 0.175
B33: =Gen!S41 -> 3058.76

Sheet Lpg (2)
C3: Four Sasons Safari Lodge Serengeti | O3: =4579-#REF! -> #REF!
G4: 43374
K6: TOTAL & ANALYSIS | N6: VALUE | O6: Cost
A7: DATE | B7: A | C7: B | D7: C | E7: 1T | G7: 2T | K7: Purch | M7: Meter Reading | N7: Total | O7: Occu | P7: No.of | Q7: Kg
B8: 2Ton% | C8: 1Ton (%) | D8: 1Ton% | E8: Consumption% | G8: Consumption% | M8: consumption | N8: Consumption Kg | O8: % | P8: pax | Q8: per pax
E9: =SUM(D9%*1000) -> 0 | F9: =SUM(E9%*1000) -> 0 | G9: =SUM(F9%*2000) -> 0 | M9: 58530.58
A10: =Gen!A11 -> 43435 | B10: 85 | C10: 85 | D10: 75 | E10: =SUM(D10%*1000) -> 750 | F10: =SUM(E10%*1000) -> 7500 | G10: =SUM(F10%*2000) -> 150000 | H10: =SUM(G10%*2000) -> 3000000 | I10: =SUM(F10+H10) -> 3007500 | M10: 58564.51 | N10: =(M10-M9)*4.4 -> 149.292 | O10: ='Summery Report'!C5 -> 0.168 | P10: =SUM(M10/O10) -> 348598.27 | Q10: =SUM(N10/P10) -> 0.00042826374
A11: =Gen!A12 -> 43436 | B11: 85 | C11: 85 | D11: 61 | E11: =SUM(D11%*1000) -> 610 | F11: =SUM(E11%*1000) -> 6100 | G11: =SUM(F11%*2000) -> 122000 | H11: =SUM(G11%*2000) -> 2440000 | I11: =SUM(F11+H11) -> 2446100 | M11: 58582.44 | N11: =(M11-M10)*4.4 -> 78.892 | O11: ='Summery Report'!C6 -> 0.1429 | P11: =SUM(M11/O11) -> 409954.09 | Q11: =SUM(N11/P11) -> 0.00019244106
A12: =Gen!A13 -> 43437 | B12: 85 | C12: 85 | D12: 52 | E12: =SUM(D12%*1000) -> 520 | F12: =SUM(E12%*1000) -> 5200 | G12: =SUM(F12%*2000) -> 104000 | H12: =SUM(G12%*2000) -> 2080000 | I12: =SUM(F12+H12) -> 2085200 | M12: 58611.2 | N12: =(M12-M11)*4.4 -> 126.544 | O12: ='Summery Report'!C7 -> 0.1429 | P12: =SUM(M12/O12) -> 410155.35 | Q12: =SUM(N12/P12) -> 0.000308527
A13: =Gen!A14 -> 43438 | B13: 85 | C13: 85 | D13: 45 | E13: =SUM(D13%*1000) -> 450 | F13: =SUM(E13%*1000) -> 4500 | G13: =SUM(F13%*2000) -> 90000 | H13: =SUM(G13%*2000) -> 1800000 | I13: =SUM(F13+H13) -> 1804500 | M13: 58634.23 | N13: =(M13-M12)*4.4 -> 101.332 | O13: ='Summery Report'!C8 -> 0.1688 | P13: =SUM(M13/O13) -> 347359.18 | Q13: =SUM(N13/P13) -> 0.00029172109
A14: =Gen!A15 -> 43439 | B14: 85 | C14: 85 | D14: 40 | E14: =SUM(D14%*1000) -> 400 | F14: =SUM(E14%*1000) -> 4000 | G14: =SUM(F14%*2000) -> 80000 | H14: =SUM(G14%*2000) -> 1600000 | I14: =SUM(F14+H14) -> 1604000 | M14: 58659.6 | N14: =(M14-M13)*4.4 -> 111.628 | O14: ='Summery Report'!C9 -> 0.2078 | P14: =SUM(M14/O14) -> 282288.74 | Q14: =SUM(N14/P14) -> 0.00039543908
A15: =Gen!A16 -> 43440 | B15: 85 | C15: 85 | D15: 36 | E15: =SUM(D15%*1000) -> 360 | F15: =SUM(E15%*1000) -> 3600 | G15: =SUM(F15%*2000) -> 72000 | H15: =SUM(G15%*2000) -> 1440000 | I15: =SUM(F15+H15) -> 1443600 | M15: 58683.61 | N15: =(M15-M14)*4.4 -> 105.644 | O15: ='Summery Report'!C10 -> 0.2987 | P15: =SUM(M15/O15) -> 196463.37 | Q15: =SUM(N15/P15) -> 0.00053772873
A16: =Gen!A17 -> 43441 | B16: 85 | C16: 85 | D16: 30 | E16: =SUM(D16%*1000) -> 300 | F16: =SUM(E16%*1000) -> 3000 | G16: =SUM(F16%*2000) -> 60000 | H16: =SUM(G16%*2000) -> 1200000 | I16: =SUM(F16+H16) -> 1203000 | M16: 58710.01 | N16: =(M16-M15)*4.4 -> 116.16 | O16: ='Summery Report'!C11 -> 0.2468 | P16: =SUM(M16/O16) -> 237884.97 | Q16: =SUM(N16/P16) -> 0.00048830324
A17: =Gen!A18 -> 43442 | B17: 85 | C17: 85 | D17: 23 | E17: =SUM(D17%*1000) -> 230 | F17: =SUM(E17%*1000) -> 2300 | G17: =SUM(F17%*2000) -> 46000 | H17: =SUM(G17%*2000) -> 920000 | I17: =SUM(F17+H17) -> 922300 | M17: 58744 | N17: =(M17-M16)*4.4 -> 149.556 | O17: ='Summery Report'!C12 -> 0.2857 | P17: =SUM(M17/O17) -> 205614.28 | Q17: =SUM(N17/P17) -> 0.00072736193
A18: =Gen!A19 -> 43443 | B18: 85 | C18: 85 | D18: 16 | E18: =SUM(D18%*1000) -> 160 | F18: =SUM(E18%*1000) -> 1600 | G18: =SUM(F18%*2000) -> 32000 | H18: =SUM(G18%*2000) -> 640000 | I18: =SUM(F18+H18) -> 641600 | M18: 58780 | N18: =(M18-M17)*4.4 -> 158.4 | O18: ='Summery Report'!C13 -> 0.4675 | P18: =SUM(M18/O18) -> 125732.62 | Q18: =SUM(N18/P18) -> 0.0012598163
A19: =Gen!A20 -> 43444 | B19: 85 | C19: 85 | D19: 9 | E19: =SUM(D19%*1000) -> 90 | F19: =SUM(E19%*1000) -> 900 | G19: =SUM(F19%*2000) -> 18000 | H19: =SUM(G19%*2000) -> 360000 | I19: =SUM(F19+H19) -> 360900 | M19: 58824.82 | N19: =(M19-M18)*4.4 -> 197.208 | O19: ='Summery Report'!C14 -> 0.5584 | P19: =SUM(M19/O19) -> 105345.31 | Q19: =SUM(N19/P19) -> 0.001872015
A20: =Gen!A21 -> 43445 | B20: 85 | C20: 85 | D20: 2 | E20: =SUM(D20%*1000) -> 20 | F20: =SUM(E20%*1000) -> 200 | G20: =SUM(F20%*2000) -> 4000 | H20: =SUM(G20%*2000) -> 80000 | I20: =SUM(F20+H20) -> 80200 | M20: 58852.51 | N20: =(M20-M19)*4.4 -> 121.836 | O20: ='Summery Report'!C15 -> 0.5714 | P20: =SUM(M20/O20) -> 102997.04 | Q20: =SUM(N20/P20) -> 0.0011829078
A21: =Gen!A22 -> 43446 | B21: 85 | C21: 78 | D21: 0 | E21: =SUM(D21%*1000) -> 0 | F21: =SUM(E21%*1000) -> 0 | G21: =SUM(F21%*2000) -> 0 | H21: =SUM(G21%*2000) -> 0 | I21: =SUM(F21+H21) -> 0 | M21: 58881.44 | N21: =(M21-M20)*4.4 -> 127.292 | O21: ='Summery Report'!C16 -> 0.2338 | P21: =SUM(M21/O21) -> 251845.34 | Q21: =SUM(N21/P21) -> 0.00050543719
... A33: =Gen!A34 -> 43458 | B33: 85 | C33: 4 | D33: 0 | E33: =SUM(D33%*1000) -> 0 | F33: =SUM(E33%*1000) -> 0 | G33: =SUM(F33%*2000) -> 0 | H33: =SUM(G33%*2000) -> 0 | I33: =SUM(F33+H33) -> 0 | M33: 59198.5 | N33: =(M33-M32)*4.4 -> 119.68 | O33: ='Summery Report'!C28 -> 0.5065 | P33: =SUM(M33/O33) -> 116877.59 | Q33: =SUM(N33/P33) -> 0.0010239773
A34: =Gen!A35 -> 43459 | B34: 85 | C34: o | D34: 0 | E34: =SUM(D34%*1000) -> 0 | F34: =SUM(E34%*1000) -> 0 | G34: =SUM(F34%*2000) -> 0 | H34: =SUM(G34%*2000) -> 0 | I34: =SUM(F34+H34) -> 0 | M34: 59228.39 | N34: =(M34-M33)*4.4 -> 131.516 | O34: ='Summery Report'!C29 -> 0.9481 | P34: =SUM(M34/O34) -> 62470.615 | Q34: =SUM(N34/P34) -> 0.0021052458
A35: =Gen!A36 -> 43460 | B35: 85 | C35: 0 | D35: 0 | E35: =SUM(D35%*1000) -> 0 | F35: =SUM(E35%*1000) -> 0 | G35: =SUM(F35%*2000) -> 0 | H35: =SUM(G35%*2000) -> 0 | I35: =SUM(F35+H35) -> 0 | M35: 59254.57 | N35: =(M35-M34)*4.4 -> 115.192 | O35: ='Summery Report'!C30 -> 0.9091 | P35: =SUM(M35/O35) -> 65179.375 | Q35: =SUM(N35/P35) -> 0.0017673075
A36: =Gen!A37 -> 43461 | B36: 83 | C36: 0 | D36: 0 | E36: =SUM(D36%*1000) -> 0 | F36: =SUM(E36%*1000) -> 0 | G36: =SUM(F36%*2000) -> 0 | H36: =SUM(G36%*2000) -> 0 | I36: =SUM(F36+H36) -> 0 | M36: 59279.22 | N36: =(M36-M35)*4.4 -> 108.46 | O36: ='Summery Report'!C31 -> 0.7662 | P36: =SUM(M36/O36) -> 77367.815 | Q36: =SUM(N36/P36) -> 0.0014018749
A37: =Gen!A38 -> 43462 | B37: 80 | C37: 0 | D37: 0 | E37: =SUM(D37%*1000) -> 0 | F37: =SUM(E37%*1000) -> 0 | G37: =SUM(F37%*2000) -> 0 | H37: =SUM(G37%*2000) -> 0 | I37: =SUM(F37+H37) -> 0 | M37: 59307.18 | N37: =(M37-M36)*4.4 -> 123.024 | O37: ='Summery Report'!C32 -> 0.7792 | P37: =SUM(M37/O37) -> 76112.911 | Q37: =SUM(N37/P37) -> 0.0016163355
A38: =Gen!A39 -> 43463 | B38: 79 | C38: 0 | D38: 0 | E38: =SUM(D38%*1000) -> 0 | F38: =SUM(E38%*1000) -> 0 | G38: =SUM(F38%*2000) -> 0 | H38: =SUM(G38%*2000) -> 0 | I38: =SUM(F38+H38) -> 0 | M38: 59332.42 | N38: =(M38-M37)*4.4 -> 111.056 | O38: ='Summery Report'!C33 -> 0.9221 | P38: =SUM(M38/O38) -> 64344.887 | Q38: =SUM(N38/P38) -> 0.0017259491
A39: =Gen!A40 -> 43464 | B39: 76 | C39: 0 | D39: 0 | E39: =SUM(D39%*1000) -> 0 | F39: =SUM(E39%*1000) -> 0 | G39: =SUM(F39%*2000) -> 0 | H39: =SUM(G39%*2000) -> 0 | I39: =SUM(F39+H39) -> 0 | M39: 59356.64 | N39: =(M39-M38)*4.4 -> 106.568 | O39: ='Summery Report'!C34 -> 0.7792 | P39: =SUM(M39/O39) -> 76176.386 | Q39: =SUM(N39/P39) -> 0.0013989637
A40: =Gen!A41 -> 43465 | B40: 72 | C40: 0 | D40: 0 | E40: =SUM(D40%*1000) -> 0 | F40: =SUM(E40%*1000) -> 0 | G40: =SUM(F40%*2000) -> 0 | H40: =SUM(G40%*2000) -> 0 | I40: =SUM(F40+H40) -> 0 | M40: 59384.49 | N40: =(M40-M39)*4.4 -> 122.54 | O40: ='Summery Report'!C35 -> 0.8442 | P40: =SUM(M40/O40) -> 70344.101 | Q40: =SUM(N40/P40) -> 0.0017420082
A41: =Gen!A42 -> 0 | E41: =SUM(D41%*1000) -> 0 | F41: =SUM(E41%*1000) -> 0 | N41: =(M41-M40)*4.4 -> -261291.76 | O41: ='Summery Report'!C36 -> 0 | P41: =SUM(M41/O41) -> #DIV/0!
C42: TOTAL USAGE | E42: =SUM(D42%*1000) -> 0 | G42: =SUM(G10:G40) -> 778000 | K42: =SUM(K10:K40) -> 0 | N42: =SUM(N10:N40) -> 3757.204
B64: GAS TANK A | G64: GAS TANK B | K64: GAS TANK C

Sheet LPG_Graph
A1: Date | B1: Usage KG | C1: Occ %
A2: =SUM(Gen!A11) -> 43435 | B2: =SUM(#REF!) -> #REF! | C2: =SUM(Gen!B11) -> 0.168
A3: =SUM(Gen!A12) -> 43436 | B3: =#REF! -> #REF! | C3: =SUM(Gen!B12) -> 0.1429
A4: =SUM(Gen!A13) -> 43437 | B4: =#REF! -> #REF! | C4: =SUM(Gen!B13) -> 0.1429
A5: =SUM(Gen!A14) -> 43438 | B5: =#REF! -> #REF! | C5: =SUM(Gen!B14) -> 0.1688
A6: =SUM(Gen!A15) -> 43439 | B6: =#REF! -> #REF! | C6: =SUM(Gen!B15) -> 0.2078
A7: =SUM(Gen!A16) -> 43440 | B7: =#REF! -> #REF! | C7: =SUM(Gen!B16) -> 0.2987
A8: =SUM(Gen!A17) -> 43441 | B8: =#REF! -> #REF! | C8: =SUM(Gen!B17) -> 0.2468
A9: =SUM(Gen!A18) -> 43442 | B9: =#REF! -> #REF! | C9: =SUM(Gen!B18) -> 0.2857
A10: =SUM(Gen!A19) -> 43443 | B10: =#REF! -> #REF! | C10: =SUM(Gen!B19) -> 0.4675
A11: =SUM(Gen!A20) -> 43444 | B11: =#REF! -> #REF! | C11: =SUM(Gen!B20) -> 0.5584
A12: =SUM(Gen!A21) -> 43445 | B12: =#REF! -> #REF! | C12: =SUM(Gen!B21) -> 0.5714
A13: =SUM(Gen!A22) -> 43446 | B13: =#REF! -> #REF! | C13: =SUM(Gen!B22) -> 0.2338
A14: =SUM(Gen!A23) -> 43447 | B14: =#REF! -> #REF! | C14: =SUM(Gen!B23) -> 0.2727
... A32: =SUM(Gen!A41) -> 43465 | B32: =#REF! -> #REF! | C32: =SUM(Gen!B41) -> 0.8442

Sheet Water-Meter
A1: Four Seasons Safari Lodge Serengeti October 2018- Water Report
C2: Main Meter | F2: KITCHEN | I2: Amani café | L2: Main SW POOL | O2: Laundry | S2: BORE HOLE NO.1 METER READING | V2: BORE HOLE NO.2 METER READING | Y2: BORE HOLE NO.3 METER READING | AB2: BORE HOLE NO.4 METER READING | AE2: BORE HOLE NO.5 METER READING | AH2: BORE HOLE NO.6 METER READING | AK2: RAIN WATER - METER READING | AN2: TOTAL WATER PRODUCTION
A3: DATE | C3: Open Bal | D3: Final | E3: consumption | F3: Open Bal | G3: Final | H3: consumption | I3: Open Bal | J3: Final | K3: consumption | L3: Open Bal | M3: Final | N3: consumption | O3: Open Bal | P3: Final | Q3: consumption | R3: Total consumption
S4: OPEN | T4: FINAL | U4: PROD. | V4: OPEN | W4: FINAL | X4: PROD. | Y4: OPEN | Z4: FINAL | AA4: PROD. | AB4: OPEN | AC4: FINAL | AD4: M3 | AE4: OPEN | AF4: FINAL | AG4: M3 | AH4: OPEN | AI4: FINAL | AJ4: M3 | AK4: OPEN | AL4: FINAL | AM4: M3
D5: 173149 | G5: 31114 | J5: 6197 | M5: 6488 | P5: 15270 | T5: 33852 | W5: 47157 | Z5: 57847 | AC5: 9822 | AF5: 8408 | AI5: 12642 | AL5: 1560
A6: =Gen!A11 -> 43435 | C6: =D5 -> 173149 | D6: 173248 | E6: =D6-C6 -> 99 | F6: =G5 -> 31114 | G6: 31126 | H6: =G6-F6 -> 12 | I6: =J5 -> 6197 | J6: 6201 | K6: =J6-I6 -> 4 | L6: =M5 -> 6488 | M6: 6488 | N6: =M6-M5 -> 0 | O6: =P5 -> 15270 | P6: 15280 | Q6: =P6-O6 -> 10 | R6: =SUM(H6+K6+N6+Q6) -> 26 | S6: =T5 -> 33852 | T6: 33892 | U6: =T6-T5 -> 40 | V6: =W5 -> 47157 | W6: 47211 | X6: =W6-W5 -> 54 | Y6: =Z5 -> 57847 | Z6: 57904 | AA6: =Z6-Z5 -> 57 | AB6: =AC5 -> 9822 | AC6: 9833 | AD6: =AC6-AC5 -> 11 | AE6: =AF5 -> 8408 | AF6: 8428 | AG6: =AF6-AF5 -> 20 | AH6: =AI5 -> 12642 | AI6: 12691 | AJ6: =AI6-AI5 -> 49 | AK6: =AL5 -> 1560 | AL6: 1560 | AM6: =AL6-AL5 -> 0 | AN6: =U6+X6+AA6+AD6+AG6+AJ6+AM6 -> 231
A7: =Gen!A12 -> 43436 | C7: =D6 -> 173248 | D7: 173348 | E7: =D7-C7 -> 100 | F7: =G6 -> 31126 | G7: 31137 | H7: =G7-F7 -> 11 | I7: =J6 -> 6201 | J7: 6204 | K7: =J7-I7 -> 3 | L7: =M6 -> 6488 | M7: 6488 | N7: =M7-M6 -> 0 | O7: =P6 -> 15280 | P7: 15292 | Q7: =P7-O7 -> 12 | R7: =SUM(H7+K7+N7+Q7) -> 26 | S7: =T6 -> 33892 | T7: 33934 | U7: =T7-T6 -> 42 | V7: =W6 -> 47211 | W7: 47266 | X7: =W7-W6 -> 55 | Y7: =Z6 -> 57904 | Z7: 57959 | AA7: =Z7-Z6 -> 55 | AB7: =AC6 -> 9833 | AC7: 9845 | AD7: =AC7-AC6 -> 12 | AE7: =AF6 -> 8428 | AF7: 8448 | AG7: =AF7-AF6 -> 20 | AH7: =AI6 -> 12691 | AI7: 12741 | AJ7: =AI7-AI6 -> 50 | AK7: =AL6 -> 1560 | AL7: 1560 | AM7: =AL7-AL6 -> 0 | AN7: =U7+X7+AA7+AD7+AG7+AJ7+AM7 -> 234
A8: =Gen!A13 -> 43437 | C8: =D7 -> 173348 | D8: 173438 | E8: =D8-C8 -> 90 | F8: =G7 -> 31137 | G8: 31148 | H8: =G8-F8 -> 11 | I8: =J7 -> 6204 | J8: 6207 | K8: =J8-I8 -> 3 | L8: =M7 -> 6488 | M8: 6488 | N8: =M8-M7 -> 0 | O8: =P7 -> 15292 | P8: 15305 | Q8: =P8-O8 -> 13 | R8: =SUM(H8+K8+N8+Q8) -> 27 | S8: =T7 -> 33934 | T8: 33974 | U8: =T8-T7 -> 40 | V8: =W7 -> 47266 | W8: 47320 | X8: =W8-W7 -> 54 | Y8: =Z7 -> 57959 | Z8: 58014 | AA8: =Z8-Z7 -> 55 | AB8: =AC7 -> 9845 | AC8: 9856 | AD8: =AC8-AC7 -> 11 | AE8: =AF7 -> 8448 | AF8: 8468 | AG8: =AF8-AF7 -> 20 | AH8: =AI7 -> 12741 | AI8: 12790 | AJ8: =AI8-AI7 -> 49 | AK8: =AL7 -> 1560 | AL8: 1560 | AM8: =AL8-AL7 -> 0 | AN8: =U8+X8+AA8+AD8+AG8+AJ8+AM8 -> 229
A9: =Gen!A14 -> 43438 | C9: =D8 -> 173438 | D9: 173525 | E9: =D9-C9 -> 87 | F9: =G8 -> 31148 | G9: 31160 | H9: =G9-F9 -> 12 | I9: =J8 -> 6207 | J9: 6210 | K9: =J9-I9 -> 3 | L9: =M8 -> 6488 | M9: 6488 | N9: =M9-M8 -> 0 | O9: =P8 -> 15305 | P9: 15317 | Q9: =P9-O9 -> 12 | R9: =SUM(H9+K9+N9+Q9) -> 27 | S9: =T8 -> 33974 | T9: 34013 | U9: =T9-T8 -> 39 | V9: =W8 -> 47320 | W9: 47374 | X9: =W9-W8 -> 54 | Y9: =Z8 -> 58014 | Z9: 58068 | AA9: =Z9-Z8 -> 54 | AB9: =AC8 -> 9856 | AC9: 9867 | AD9: =AC9-AC8 -> 11 | AE9: =AF8 -> 8468 | AF9: 8469 | AG9: =AF9-AF8 -> 1 | AH9: =AI8 -> 12790 | AI9: 12840 | AJ9: =AI9-AI8 -> 50 | AK9: =AL8 -> 1560 | AL9: 1560 | AM9: =AL9-AL8 -> 0 | AN9: =U9+X9+AA9+AD9+AG9+AJ9+AM9 -> 209
A10: =Gen!A15 -> 43439 | C10: =D9 -> 173525 | D10: 173609 | E10: =D10-C10 -> 84 | F10: =G9 -> 31160 | G10: 31172 | H10: =G10-F10 -> 12 | I10: =J9 -> 6210 | J10: 6213 | K10: =J10-I10 -> 3 | M10: 6488 | N10: =M10-M9 -> 0 | O10: =P9 -> 15317 | P10: 15326 | Q10: =P10-O10 -> 9 | R10: =SUM(H10+K10+N10+Q10) -> 24 | S10: =T9 -> 34013 | T10: 34054 | U10: =T10-T9 -> 41 | V10: =W9 -> 47374 | W10: 47429 | X10: =W10-W9 -> 55 | Y10: =Z9 -> 58068 | Z10: 58124 | AA10: =Z10-Z9 -> 56 | AB10: =AC9 -> 9867 | AC10: 9879 | AD10: =AC10-AC9 -> 12 | AE10: =AF9 -> 8469 | AF10: 8470 | AG10: =AF10-AF9 -> 1 | AH10: =AI9 -> 12840 | AI10: 12887 | AJ10: =AI10-AI9 -> 47 | AK10: =AL9 -> 1560 | AL10: 1560 | AM10: =AL10-AL9 -> 0 | AN10: =U10+X10+AA10+AD10+AG10+AJ10+AM10 -> 212
A11: =Gen!A16 -> 43440 | C11: =D10 -> 173609 | D11: 173717 | E11: =D11-C11 -> 108 | F11: =G10 -> 31172 | G11: 31186 | H11: =G11-F11 -> 14 | I11: =J10 -> 6213 | J11: 6216 | K11: =J11-I11 -> 3 | L11: =M11 -> 6488 | M11: 6488 | N11: =M11-M10 -> 0 | O11: =P10 -> 15326 | P11: 15336 | Q11: =P11-O11 -> 10 | R11: =SUM(H11+K11+N11+Q11) -> 27 | S11: =T10 -> 34054 | T11: 34094 | U11: =T11-T10 -> 40 | V11: =W10 -> 47429 | W11: 47482 | X11: =W11-W10 -> 53 | Y11: =Z10 -> 58124 | Z11: 58180 | AA11: =Z11-Z10 -> 56 | AB11: =AC10 -> 9879 | AC11: 9890 | AD11: =AC11-AC10 -> 11 | AE11: =AF10 -> 8470 | AF11: 8470 | AG11: =AF11-AF10 -> 0 | AH11: =AI10 -> 12887 | AI11: 12935 | AJ11: =AI11-AI10 -> 48 | AK11: =AL10 -> 1560 | AL11: 1560 | AM11: =AL11-AL10 -> 0 | AN11: =U11+X11+AA11+AD11+AG11+AJ11+AM11 -> 208
A12: =Gen!A17 -> 43441 | C12: =D11 -> 173717 | D12: 173810 | E12: =D12-C12 -> 93 | F12: =G11 -> 31186 | G12: 31199 | H12: =G12-F12 -> 13 | I12: =J11 -> 6216 | J12: 6220 | K12: =J12-I12 -> 4 | L12: =M12 -> 6488 | M12: 6488 | N12: =M12-M11 -> 0 | O12: =P11 -> 15336 | P12: 15348 | Q12: =P12-O12 -> 12 | R12: =SUM(H12+K12+N12+Q12) -> 29 | S12: =T11 -> 34094 | T12: 34134 | U12: =T12-T11 -> 40 | V12: =W11 -> 47482 | W12: 47537 | X12: =W12-W11 -> 55 | Y12: =Z11 -> 58180 | Z12: 58232 | AA12: =Z12-Z11 -> 52 | AB12: =AC11 -> 9890 | AC12: 9901 | AD12: =AC12-AC11 -> 11 | AE12: =AF11 -> 8470 | AF12: 8470 | AG12: =AF12-AF11 -> 0 | AH12: =AI11 -> 12935 | AI12: 12984 | AJ12: =AI12-AI11 -> 49 | AK12: =AL11 -> 1560 | AL12: 5210 | AN12: =U12+X12+AA12+AD12+AG12+AJ12+AM12 -> 207
A13: =Gen!A18 -> 43442 | C13: =D12 -> 173810 | D13: 173913 | E13: =D13-C13 -> 103 | F13: =G12 -> 31199 | G13: 31213 | H13: =G13-F13 -> 14 | I13: =J12 -> 6220 | J13: 6223 | K13: =J13-I13 -> 3 | L13: =M13 -> 6488 | M13: 6488 | N13: =M13-M12 -> 0 | O13: =P12 -> 15348 | P13: 15352 | Q13: =P13-O13 -> 4 | R13: =SUM(H13+K13+N13+Q13) -> 21 | S13: =T12 -> 34134 | T13: 34174 | U13: =T13-T12 -> 40 | V13: =W12 -> 47537 | W13: 47589 | X13: =W13-W12 -> 52 | Y13: =Z12 -> 58232 | Z13: 58273 | AA13: =Z13-Z12 -> 41 | AB13: =AC12 -> 9901 | AC13: 9912 | AD13: =AC13-AC12 -> 11 | AE13: =AF12 -> 8470 | AF13: 8485 | AG13: =AF13-AF12 -> 15 | AH13: =AI12 -> 12984 | AI13: 13032 | AJ13: =AI13-AI12 -> 48 | AK13: =AL12 -> 5210 | AL13: 5250 | AM13: =AL13-AL12 -> 40 | AN13: =U13+X13+AA13+AD13+AG13+AJ13+AM13 -> 247
A14: =Gen!A19 -> 43443 | C14: =D13 -> 173913 | D14: 174038 | E14: =D14-C14 -> 125 | F14: =G13 -> 31213 | G14: 31228 | H14: =G14-F14 -> 15 | I14: =J13 -> 6223 | J14: 6226 | K14: =J14-I14 -> 3 | L14: =M14 -> 6488 | M14: 6488 | N14: =M14-M13 -> 0 | O14: =P13 -> 15352 | P14: 15361 | Q14: =P14-O14 -> 9 | R14: =SUM(H14+K14+N14+Q14) -> 27 | S14: =T13 -> 34174 | T14: 34215 | U14: =T14-T13 -> 41 | V14: =W13 -> 47589 | W14: 47644 | X14: =W14-W13 -> 55 | Y14: =Z13 -> 58273 | Z14: 58316 | AA14: =Z14-Z13 -> 43 | AB14: =AC13 -> 9912 | AC14: 9924 | AD14: =AC14-AC13 -> 12 | AE14: =AF13 -> 8485 | AF14: 8508 | AG14: =AF14-AF13 -> 23 | AH14: =AI13 -> 13032 | AI14: 13081 | AJ14: =AI14-AI13 -> 49 | AK14: =AL13 -> 5250 | AL14: 5320 | AM14: =AL14-AL13 -> 70 | AN14: =U14+X14+AA14+AD14+AG14+AJ14+AM14 -> 293
A15: =Gen!A20 -> 43444 | C15: =D14 -> 174038 | D15: 174152 | E15: =D15-C15 -> 114 | F15: =G14 -> 31228 | G15: 31244 | H15: =G15-F15 -> 16 | I15: =J14 -> 6226 | J15: 6235 | K15: =J15-I15 -> 9 | L15: =M15 -> 6488 | M15: 6488 | N15: =M15-M14 -> 0 | O15: =P14 -> 15361 | P15: 15382 | Q15: =P15-O15 -> 21 | R15: =SUM(H15+K15+N15+Q15) -> 46 | S15: =T14 -> 34215 | T15: 34255 | U15: =T15-T14 -> 40 | V15: =W14 -> 47644 | W15: 47699 | X15: =W15-W14 -> 55 | Y15: =Z14 -> 58316 | Z15: 58369 | AA15: =Z15-Z14 -> 53 | AB15: =AC14 -> 9924 | AC15: 9935 | AD15: =AC15-AC14 -> 11 | AE15: =AF14 -> 8508 | AF15: 8528 | AG15: =AF15-AF14 -> 20 | AH15: =AI14 -> 13081 | AI15: 13130 | AJ15: =AI15-AI14 -> 49 | AK15: =AL14 -> 5320 | AL15: 5364 | AM15: =AL15-AL14 -> 44 | AN15: =U15+X15+AA15+AD15+AG15+AJ15+AM15 -> 272
A16: =Gen!A21 -> 43445 | C16: =D15 -> 174152 | D16: 174266 | E16: =D16-C16 -> 114 | F16: =G15 -> 31244 | G16: 31259 | H16: =G16-F16 -> 15 | I16: =J15 -> 6235 | J16: 6239 | K16: =J16-I16 -> 4 | L16: =M15 -> 6488 | M16: 6488 | N16: =M16-M15 -> 0 | O16: =P15 -> 15382 | P16: 15395 | Q16: =P16-O16 -> 13 | R16: =SUM(H16+K16+N16+Q16) -> 32 | S16: =T15 -> 34255 | T16: 34295 | U16: =T16-T15 -> 40 | V16: =W15 -> 47699 | W16: 47750 | X16: =W16-W15 -> 51 | Y16: =Z15 -> 58369 | Z16: 58398 | AA16: =Z16-Z15 -> 29 | AB16: =AC15 -> 9935 | AC16: 9944 | AD16: =AC16-AC15 -> 9 | AE16: =AF15 -> 8528 | AF16: 8559 | AG16: =AF16-AF15 -> 31 | AH16: =AI15 -> 13130 | AI16: 13179 | AJ16: =AI16-AI15 -> 49 | AK16: =AL15 -> 5364 | AL16: 5394 | AM16: =AL16-AL15 -> 30 | AN16: =U16+X16+AA16+AD16+AG16+AJ16+AM16 -> 239
A17: =Gen!A22 -> 43446 | C17: =D16 -> 174266 | D17: 174371 | E17: =D17-C17 -> 105 | F17: =G16 -> 31259 | G17: 31273 | H17: =G17-F17 -> 14 | I17: =J16 -> 6239 | J17: 6244 | K17: =J17-I17 -> 5 | L17: =M16 -> 6488 | M17: 6488 | N17: =M17-M16 -> 0 | O17: =P16 -> 15395 | P17: 15410 | Q17: =P17-O17 -> 15 | R17: =SUM(H17+K17+N17+Q17) -> 34 | S17: =T16 -> 34295 | T17: 34335 | U17: =T17-T16 -> 40 | V17: =W16 -> 47750 | W17: 47803 | X17: =W17-W16 -> 53 | Y17: =Z16 -> 58398 | Z17: 58439 | AA17: =Z17-Z16 -> 41 | AB17: =AC16 -> 9944 | AC17: 9953 | AD17: =AC17-AC16 -> 9 | AE17: =AF16 -> 8559 | AF17: 8570 | AG17: =AF17-AF16 -> 11 | AH17: =AI16 -> 13179 | AI17: 13229 | AJ17: =AI17-AI16 -> 50 | AK17: =AL16 -> 5394 | AL17: 5545 | AM17: =AL17-AL16 -> 151 | AN17: =U17+X17+AA17+AD17+AG17+AJ17+AM17 -> 355
A18: =Gen!A23 -> 43447 | C18: =D17 -> 174371 | D18: 174482 | E18: =D18-C18 -> 111 | F18: =G17 -> 31273 | G18: 31288 | H18: =G18-F18 -> 15 | I18: =J17 -> 6244 | J18: 6246 | K18: =J18-I18 -> 2 | L18: =M17 -> 6488 | M18: 6488 | N18: =M18-M17 -> 0 | O18: =P17 -> 15410 | P18: 15421 | Q18: =P18-O18 -> 11 | R18: =SUM(H18+K18+N18+Q18) -> 28 | S18: =T17 -> 34335 | T18: 34374 | U18: =T18-T17 -> 39 | V18: =W17 -> 47803 | W18: 47857 | X18: =W18-W17 -> 54 | Y18: =Z17 -> 58439 | Z18: 58471 | AA18: =Z18-Z17 -> 32 | AB18: =AC17 -> 9953 | AC18: 9962 | AD18: =AC18-AC17 -> 9 | AE18: =AF17 -> 8570 | AF18: 8591 | AG18: =AF18-AF17 -> 21 | AH18: =AI17 -> 13229 | AI18: 13289 | AJ18: =AI18-AI17 -> 60 | AK18: =AL17 -> 5545 | AL18: 5550 | AM18: =AL18-AL17 -> 5 | AN18: =U18+X18+AA18+AD18+AG18+AJ18+AM18 -> 220
A19: =Gen!A24 -> 43448 | C19: =D18 -> 174482 | D19: 174582 | E19: =D19-C19 -> 100 | F19: =G18 -> 31288 | G19: 31303 | H19: =G19-F19 -> 15 | I19: =J18 -> 6246 | J19: 6249 | K19: =J19-I19 -> 3 | L19: =M18 -> 6488 | M19: 6488 | N19: =M19-M18 -> 0 | O19: =P18 -> 15421 | P19: 15442 | Q19: =P19-O19 -> 21 | R19: =SUM(H19+K19+N19+Q19) -> 39 | S19: =T18 -> 34374 | T19: 34416 | U19: =T19-T18 -> 42 | V19: =W18 -> 47857 | W19: 47909 | X19: =W19-W18 -> 52 | Y19: =Z18 -> 58471 | Z19: 58498 | AA19: =Z19-Z18 -> 27 | AB19: =AC18 -> 9962 | AC19: 9971 | AD19: =AC19-AC18 -> 9 | AE19: =AF18 -> 8591 | AF19: 8609 | AG19: =AF19-AF18 -> 18 | AH19: =AI18 -> 13289 | AI19: 13329 | AJ19: =AI19-AI18 -> 40 | AK19: =AL18 -> 5550 | AL19: 5550 | AM19: =AL19-AL18 -> 0 | AN19: =U19+X19+AA19+AD19+AG19+AJ19+AM19 -> 188
A20: =Gen!A25 -> 43449 | C20: =D19 -> 174582 | D20: 174669 | E20: =D20-C20 -> 87 | F20: =G19 -> 31303 | G20: 31316 | H20: =G20-F20 -> 13 | I20: =J19 -> 6249 | J20: 6254 | K20: =J20-I20 -> 5 | L20: =M19 -> 6488 | M20: 6488 | N20: =M20-M19 -> 0 | O20: =P19 -> 15442 | P20: 15329 | Q20: =P20-O20 -> -113 | R20: =SUM(H20+K20+N20+Q20) -> -95 | S20: =T19 -> 34416 | T20: 34455 | U20: =T20-T19 -> 39 | V20: =W19 -> 47909 | W20: 47961 | X20: =W20-W19 -> 52 | Y20: =Z19 -> 58498 | Z20: 58536 | AA20: =Z20-Z19 -> 38 | AB20: =AC19 -> 9971 | AC20: 9980 | AD20: =AC20-AC19 -> 9 | AE20: =AF19 -> 8609 | AF20: 8611 | AG20: =AF20-AF19 -> 2 | AH20: =AI19 -> 13329 | AI20: 13376 | AJ20: =AI20-AI19 -> 47 | AK20: =AL19 -> 5550 | AL20: 5550 | AM20: =AL20-AL19 -> 0 | AN20: =U20+X20+AA20+AD20+AG20+AJ20+AM20 -> 187
A21: =Gen!A26 -> 43450 | C21: =D20 -> 174669 | D21: 174774 | E21: =D21-C21 -> 105 | F21: =G20 -> 31316 | G21: 31330 | H21: =G21-F21 -> 14 | I21: =J20 -> 6254 | J21: 6257 | K21: =J21-I21 -> 3 | L21: =M20 -> 6488 | M21: 6488 | N21: =M21-M20 -> 0 | O21: =P20 -> 15329 | P21: 15316 | Q21: =P21-O21 -> -13 | R21: =SUM(H21+K21+N21+Q21) -> 4 | S21: =T20 -> 34455 | T21: 34495 | U21: =T21-T20 -> 40 | V21: =W20 -> 47961 | W21: 48014 | X21: =W21-W20 -> 53 | Y21: =Z20 -> 58536 | Z21: 58577 | AA21: =Z21-Z20 -> 41 | AB21: =AC20 -> 9980 | AC21: 9991 | AD21: =AC21-AC20 -> 11 | AE21: =AF20 -> 8611 | AF21: 8638 | AG21: =AF21-AF20 -> 27 | AH21: =AI20 -> 13376 | AI21: 13423 | AJ21: =AI21-AI20 -> 47 | AK21: =AL20 -> 5550 | AL21: 5862 | AM21: =AL21-AL20 -> 312 | AN21: =U21+X21+AA21+AD21+AG21+AJ21+AM21 -> 531
A22: =Gen!A27 -> 43451 | C22: =D21 -> 174774 | D22: 174883 | E22: =D22-C22 -> 109 | F22: =G21 -> 31330 | G22: 31343 | H22: =G22-F22 -> 13 | I22: =J21 -> 6257 | J22: 6260 | K22: =J22-I22 -> 3 | L22: =M21 -> 6488 | M22: 6488 | N22: =M22-M21 -> 0 | O22: =P21 -> 15316 | P22: 15328 | Q22: =P22-O22 -> 12 | R22: =SUM(H22+K22+N22+Q22) -> 28 | S22: =T21 -> 34495 | T22: 34535 | U22: =T22-T21 -> 40 | V22: =W21 -> 48014 | W22: 48066 | X22: =W22-W21 -> 52 | Y22: =Z21 -> 58577 | Z22: 58618 | AA22: =Z22-Z21 -> 41 | AB22: =AC21 -> 9991 | AC22: 10001 | AD22: =AC22-AC21 -> 10 | AE22: =AF21 -> 8638 | AF22: 8652 | AG22: =AF22-AF21 -> 14 | AH22: =AI21 -> 13423 | AI22: 13470 | AJ22: =AI22-AI21 -> 47 | AK22: =AL21 -> 5862 | AL22: 5941 | AM22: =AL22-AL21 -> 79 | AN22: =U22+X22+AA22+AD22+AG22+AJ22+AM22 -> 283
A23: =Gen!A28 -> 43452 | C23: =D22 -> 174883 | D23: 174997 | E23: =D23-C23 -> 114 | F23: =G22 -> 31343 | G23: 31358 | H23: =G23-F23 -> 15 | I23: =J22 -> 6260 | J23: 6264 | K23: =J23-I23 -> 4 | L23: =M22 -> 6488 | M23: 6488 | N23: =M23-M22 -> 0 | O23: =P22 -> 15328 | P23: 15341 | Q23: =P23-O23 -> 13 | R23: =SUM(H23+K23+N23+Q23) -> 32 | S23: =T22 -> 34535 | T23: 34574 | U23: =T23-T22 -> 39 | V23: =W22 -> 48066 | W23: 48121 | X23: =W23-W22 -> 55 | Y23: =Z22 -> 58618 | Z23: 58649 | AA23: =Z23-Z22 -> 31 | AB23: =AC22 -> 10001 | AC23: 10014 | AD23: =AC23-AC22 -> 13 | AE23: =AF22 -> 8652 | AF23: 8673 | AG23: =AF23-AF22 -> 21 | AH23: =AI22 -> 13470 | AI23: 13518 | AJ23: =AI23-AI22 -> 48 | AK23: =AL22 -> 5941 | AL23: 6019 | AM23: =AL23-AL22 -> 78 | AN23: =U23+X23+AA23+AD23+AG23+AJ23+AM23 -> 285
A24: =Gen!A29 -> 43453 | C24: =D23 -> 174997 | D24: 175107 | E24: =D24-C24 -> 110 | F24: =G23 -> 31358 | G24: 31384 | H24: =G24-F24 -> 26 | I24: =J23 -> 6264 | J24: 6269 | K24: =J24-I24 -> 5 | L24: =M23 -> 6488 | M24: 6488 | N24: =M24-M23 -> 0 | O24: =P23 -> 15341 | P24: 15350 | Q24: =P24-O24 -> 9 | R24: =SUM(H24+K24+N24+Q24) -> 40 | S24: =T23 -> 34574 | T24: 34612 | U24: =T24-T23 -> 38 | V24: =W23 -> 48121 | W24: 48174 | X24: =W24-W23 -> 53 | Y24: =Z23 -> 58649 | Z24: 58687 | AA24: =Z24-Z23 -> 38 | AB24: =AC23 -> 10014 | AC24: 10026 | AD24: =AC24-AC23 -> 12 | AE24: =AF23 -> 8673 | AF24: 8692 | AG24: =AF24-AF23 -> 19 | AH24: =AI23 -> 13518 | AI24: 13564 | AJ24: =AI24-AI23 -> 46 | AK24: =AL23 -> 6019 | AL24: 6105 | AM24: =AL24-AL23 -> 86 | AN24: =U24+X24+AA24+AD24+AG24+AJ24+AM24 -> 292
A25: =Gen!A30 -> 43454 | C25: =D24 -> 175107 | D25: 175230 | E25: =D25-C25 -> 123 | F25: =G24 -> 31384 | G25: 31402 | H25: =G25-F25 -> 18 | I25: =J25 -> 6273 | J25: 6273 | K25: =J25-J24 -> 4 | L25: =M24 -> 6488 | M25: 6488 | N25: =M25-M24 -> 0 | O25: =P24 -> 15350 | P25: 15367 | Q25: =P25-O25 -> 17 | R25: =SUM(H25+K25+N25+Q25) -> 39 | S25: =T24 -> 34612 | T25: 34652 | U25: =T25-T24 -> 40 | V25: =W24 -> 48174 | W25: 48227 | X25: =W25-W24 -> 53 | Y25: =Z24 -> 58687 | Z25: 58708 | AA25: =Z25-Z24 -> 21 | AB25: =AC24 -> 10026 | AC25: 10034 | AD25: =AC25-AC24 -> 8 | AE25: =AF24 -> 8692 | AF25: 8712 | AG25: =AF25-AF24 -> 20 | AH25: =AI24 -> 13564 | AI25: 13611 | AJ25: =AI25-AI24 -> 47 | AK25: =AL24 -> 6105 | AL25: 6194 | AM25: =AL25-AL24 -> 89 | AN25: =U25+X25+AA25+AD25+AG25+AJ25+AM25 -> 278
A26: =Gen!A31 -> 43455 | C26: =D25 -> 175230 | D26: 175360 | E26: =D26-C26 -> 130 | F26: =G25 -> 31402 | G26: 31420 | H26: =G26-F26 -> 18 | I26: =J26 -> 6278 | J26: 6278 | K26: =J26-J25 -> 5 | L26: =M25 -> 6488 | M26: 6488 | N26: =M26-M25 -> 0 | O26: =P25 -> 15367 | P26: 15373 | Q26: =P26-O26 -> 6 | R26: =SUM(H26+K26+N26+Q26) -> 29 | S26: =T25 -> 34652 | T26: 34691 | U26: =T26-T25 -> 39 | V26: =W25 -> 48227 | W26: 48280 | X26: =W26-W25 -> 53 | Y26: =Z25 -> 58708 | Z26: 58722 | AA26: =Z26-Z25 -> 14 | AB26: =AC25 -> 10034 | AC26: 10037 | AD26: =AC26-AC25 -> 3 | AE26: =AF25 -> 8712 | AF26: 8732 | AG26: =AF26-AF25 -> 20 | AH26: =AI25 -> 13611 | AI26: 13657 | AJ26: =AI26-AI25 -> 46 | AK26: =AL25 -> 6194 | AL26: 6292 | AM26: =AL26-AL25 -> 98 | AN26: =U26+X26+AA26+AD26+AG26+AJ26+AM26 -> 273
A27: =Gen!A32 -> 43456 | C27: =D26 -> 175360 | D27: 175490 | E27: =D27-C27 -> 130 | F27: =G26 -> 31420 | G27: 31441 | H27: =G27-F27 -> 21 | I27: =J27 -> 6282 | J27: 6282 | K27: =J27-J26 -> 4 | L27: =M26 -> 6488 | M27: 6488 | N27: =M27-M26 -> 0 | O27: =P26 -> 15373 | P27: 15382 | Q27: =P27-O27 -> 9 | R27: =SUM(H27+K27+N27+Q27) -> 34 | S27: =T26 -> 34691 | T27: 34733 | U27: =T27-T26 -> 42 | V27: =W26 -> 48280 | W27: 48332 | X27: =W27-W26 -> 52 | Y27: =Z26 -> 58722 | Z27: 58752 | AA27: =Z27-Z26 -> 30 | AB27: =AC26 -> 10037 | AC27: 10043 | AD27: =AC27-AC26 -> 6 | AE27: =AF26 -> 8732 | AF27: 8752 | AG27: =AF27-AF26 -> 20 | AH27: =AI26 -> 13657 | AI27: 13705 | AJ27: =AI27-AI26 -> 48 | AK27: =AL26 -> 6292 | AL27: 6407 | AM27: =AL27-AL26 -> 115 | AN27: =U27+X27+AA27+AD27+AG27+AJ27+AM27 -> 313
A28: =Gen!A33 -> 43457 | C28: =D27 -> 175490 | D28: 175621 | E28: =D28-C28 -> 131 | F28: =G27 -> 31441 | G28: 31463 | H28: =G28-F28 -> 22 | I28: =J28 -> 6286 | J28: 6286 | K28: =J28-J27 -> 4 | L28: =M27 -> 6488 | M28: 6488 | N28: =M28-M27 -> 0 | O28: =P27 -> 15382 | P28: 15391 | Q28: =P28-O28 -> 9 | R28: =SUM(H28+K28+N28+Q28) -> 35 | S28: =T27 -> 34733 | T28: 34772 | U28: =T28-T27 -> 39 | V28: =W27 -> 48332 | W28: 48387 | X28: =W28-W27 -> 55 | Y28: =Z27 -> 58752 | Z28: 58762 | AA28: =Z28-Z27 -> 10 | AB28: =AC27 -> 10043 | AC28: 10047 | AD28: =AC28-AC27 -> 4 | AE28: =AF27 -> 8752 | AF28: 8771 | AG28: =AF28-AF27 -> 19 | AH28: =AI27 -> 13705 | AI28: 13749 | AJ28: =AI28-AI27 -> 44 | AK28: =AL27 -> 6407 | AL28: 6526 | AM28: =AL28-AL27 -> 119 | AN28: =U28+X28+AA28+AD28+AG28+AJ28+AM28 -> 290
A29: =Gen!A34 -> 43458 | C29: =D28 -> 175621 | D29: 175733 | E29: =D29-C29 -> 112 | F29: =G28 -> 31463 | G29: 31480 | H29: =G29-F29 -> 17 | I29: =J29 -> 6289 | J29: 6289 | K29: =J29-J28 -> 3 | L29: =M28 -> 6488 | M29: 6488 | N29: =M29-M28 -> 0 | O29: =P28 -> 15391 | P29: 15401 | Q29: =P29-O29 -> 10 | R29: =SUM(H29+K29+N29+Q29) -> 30 | S29: =T28 -> 34772 | T29: 34802 | U29: =T29-T28 -> 30 | V29: =W28 -> 48387 | W29: 48439 | X29: =W29-W28 -> 52 | Y29: =Z28 -> 58762 | Z29: 58780 | AA29: =Z29-Z28 -> 18 | AB29: =AC28 -> 10047 | AC29: 10052 | AD29: =AC29-AC28 -> 5 | AE29: =AF28 -> 8771 | AF29: 8791 | AG29: =AF29-AF28 -> 20 | AH29: =AI28 -> 13749 | AI29: 13794 | AJ29: =AI29-AI28 -> 45 | AK29: =AL28 -> 6526 | AL29: 6526 | AM29: =AL29-AL28 -> 0 | AN29: =U29+X29+AA29+AD29+AG29+AJ29+AM29 -> 170
A30: =Gen!A35 -> 43459 | C30: =D29 -> 175733 | D30: 175880 | E30: =D30-C30 -> 147 | F30: =G29 -> 31480 | G30: 31504 | H30: =G30-F30 -> 24 | I30: =J29 -> 6289 | J30: 6293 | K30: =J30-J29 -> 4 | L30: =M29 -> 6488 | M30: 6488 | N30: =M30-M29 -> 0 | O30: =P29 -> 15401 | P30: 15421 | Q30: =P30-O30 -> 20 | R30: =SUM(H30+K30+N30+Q30) -> 48 | S30: =T29 -> 34802 | T30: 34851 | U30: =T30-T29 -> 49 | V30: =W29 -> 48439 | W30: 48492 | X30: =W30-W29 -> 53 | Y30: =Z29 -> 58780 | Z30: 58797 | AA30: =Z30-Z29 -> 17 | AB30: =AC29 -> 10052 | AC30: 10056 | AD30: =AC30-AC29 -> 4 | AE30: =AF29 -> 8791 | AF30: 8813 | AG30: =AF30-AF29 -> 22 | AH30: =AI29 -> 13794 | AI30: 13840 | AJ30: =AI30-AI29 -> 46 | AK30: =AL29 -> 6526 | AL30: 6536 | AM30: =AL30-AL29 -> 10 | AN30: =U30+X30+AA30+AD30+AG30+AJ30+AM30 -> 201
A31: =Gen!A36 -> 43460 | C31: =D30 -> 175880 | D31: 176047 | E31: =D31-C31 -> 167 | F31: =G30 -> 31504 | G31: 31527 | H31: =G31-F31 -> 23 | I31: =J30 -> 6293 | J31: 6298 | K31: =J31-J30 -> 5 | L31: =M30 -> 6488 | M31: 6488 | N31: =M31-M30 -> 0 | O31: =P30 -> 15421 | P31: 15442 | Q31: =P31-O31 -> 21 | R31: =SUM(H31+K31+N31+Q31) -> 49 | S31: =T30 -> 34851 | T31: 34890 | U31: =T31-T30 -> 39 | V31: =W30 -> 48492 | W31: 48544 | X31: =W31-W30 -> 52 | Y31: =Z30 -> 58797 | Z31: 58814 | AA31: =Z31-Z30 -> 17 | AC31: 10059 | AD31: =AC31-AC30 -> 3 | AE31: =AF30 -> 8813 | AF31: 8834 | AG31: =AF31-AF30 -> 21 | AH31: =AI30 -> 13840 | AI31: 13883 | AJ31: =AI31-AI30 -> 43 | AK31: =AL30 -> 6536 | AL31: 6536 | AM31: =AL31-AL30 -> 0 | AN31: =U31+X31+AA31+AD31+AG31+AJ31+AM31 -> 175
A32: =Gen!A37 -> 43461 | B32: 10/27//2009 | C32: =D31 -> 176047 | D32: 176206 | E32: =D32-C32 -> 159 | F32: =G31 -> 31527 | G32: 31549 | H32: =G32-F32 -> 22 | I32: =J31 -> 6298 | J32: 6302 | K32: =J32-J31 -> 4 | L32: =M31 -> 6488 | M32: 6488 | N32: =M32-M31 -> 0 | O32: =P31 -> 15442 | P32: 15464 | Q32: =P32-O32 -> 22 | R32: =SUM(H32+K32+N32+Q32) -> 48 | S32: =T31 -> 34890 | T32: 34928 | U32: =T32-T31 -> 38 | V32: =W31 -> 48544 | W32: 48596 | X32: =W32-W31 -> 52 | Y32: =Z31 -> 58814 | Z32: 58837 | AA32: =Z32-Z31 -> 23 | AB32: =AC31 -> 10059 | AC32: 10063 | AD32: =AC32-AC31 -> 4 | AE32: =AF31 -> 8834 | AF32: 8855 | AG32: =AF32-AF31 -> 21 | AH32: =AI31 -> 13883 | AI32: 13926 | AJ32: =AI32-AI31 -> 43 | AK32: =AL31 -> 6536 | AL32: 6536 | AM32: =AL32-AL31 -> 0 | AN32: =U32+X32+AA32+AD32+AG32+AJ32+AM32 -> 181
A33: =Gen!A38 -> 43462 | C33: =D32 -> 176206 | D33: 176370 | E33: =D33-C33 -> 164 | F33: =G32 -> 31549 | G33: 31571 | H33: =G33-F33 -> 22 | I33: =J32 -> 6302 | J33: 6309 | K33: =J33-J32 -> 7 | L33: =M32 -> 6488 | M33: 6488 | N33: =M33-M32 -> 0 | O33: =P32 -> 15464 | P33: 15487 | Q33: =P33-O33 -> 23 | R33: =SUM(H33+K33+N33+Q33) -> 52 | S33: =T32 -> 34928 | T33: 34967 | U33: =T33-T32 -> 39 | V33: =W32 -> 48596 | W33: 48648 | X33: =W33-W32 -> 52 | Y33: =Z32 -> 58837 | Z33: 58862 | AA33: =Z33-Z32 -> 25 | AB33: =AC32 -> 10063 | AC33: 10063 | AD33: =AC33-AC32 -> 0 | AE33: =AF32 -> 8855 | AF33: 8878 | AG33: =AF33-AF32 -> 23 | AH33: =AI32 -> 13926 | AI33: 13970 | AJ33: =AI33-AI32 -> 44 | AK33: =AL32 -> 6536 | AL33: 6536 | AM33: =AL33-AL32 -> 0 | AN33: =U33+X33+AA33+AD33+AG33+AJ33+AM33 -> 183
A34: =Gen!A39 -> 43463 | C34: =D33 -> 176370 | D34: 176543 | E34: =D34-C34 -> 173 | F34: =G33 -> 31571 | G34: 31595 | H34: =G34-F34 -> 24 | I34: =J33 -> 6309 | J34: 6314 | K34: =J34-J33 -> 5 | L34: =M33 -> 6488 | M34: 6488 | N34: =M34-M33 -> 0 | O34: =P33 -> 15487 | P34: 15511 | Q34: =P34-O34 -> 24 | R34: =SUM(H34+K34+N34+Q34) -> 53 | S34: =T33 -> 34967 | T34: 35006 | U34: =T34-T33 -> 39 | V34: =W33 -> 48648 | W34: 48701 | X34: =W34-W33 -> 53 | Y34: =Z33 -> 58862 | Z34: 58887 | AA34: =Z34-Z33 -> 25 | AB34: =AC33 -> 10063 | AC34: 10063 | AD34: =AC34-AC33 -> 0 | AE34: =AF33 -> 8878 | AF34: 8900 | AG34: =AF34-AF33 -> 22 | AH34: =AI33 -> 13970 | AI34: 14013 | AJ34: =AI34-AI33 -> 43 | AK34: =AL33 -> 6536 | AL34: 6536 | AM34: =AL34-AL33 -> 0 | AN34: =U34+X34+AA34+AD34+AG34+AJ34+AM34 -> 182
A35: =Gen!A40 -> 43464 | C35: =D34 -> 176543 | D35: 176699 | E35: =D35-C35 -> 156 | F35: =G34 -> 31595 | G35: 31616 | H35: =G35-F35 -> 21 | I35: =J34 -> 6314 | J35: 6318 | K35: =J35-J34 -> 4 | L35: =M34 -> 6488 | M35: 6488 | N35: =M35-M34 -> 0 | O35: =P34 -> 15511 | P35: 15522 | Q35: =P35-O35 -> 11 | R35: =SUM(H35+K35+N35+Q35) -> 36 | S35: =T34 -> 35006 | T35: 35045 | U35: =T35-T34 -> 39 | V35: =W34 -> 48701 | W35: 48755 | X35: =W35-W34 -> 54 | Y35: =Z34 -> 58887 | Z35: 58913 | AA35: =Z35-Z34 -> 26 | AB35: =AC34 -> 10063 | AC35: 10063 | AD35: =AC35-AC34 -> 0 | AE35: =AF34 -> 8900 | AF35: 8923 | AG35: =AF35-AF34 -> 23 | AH35: =AI34 -> 14013 | AI35: 14057 | AJ35: =AI35-AI34 -> 44 | AK35: =AL34 -> 6536 | AL35: 6536 | AM35: =AL35-AL34 -> 0 | AN35: =U35+X35+AA35+AD35+AG35+AJ35+AM35 -> 186
A36: =Gen!A41 -> 43465 | C36: =D35 -> 176699 | D36: 176819 | E36: =D36-C36 -> 120 | F36: =G35 -> 31616 | G36: 31642 | H36: =G36-F36 -> 26 | I36: =J35 -> 6318 | J36: 6322 | K36: =J36-J35 -> 4 | L36: =M35 -> 6488 | M36: 6488 | N36: =M36-M35 -> 0 | O36: =P35 -> 15522 | P36: 15533 | Q36: =P36-O36 -> 11 | R36: =SUM(H36+K36+N36+Q36) -> 41 | S36: =T35 -> 35045 | T36: 35084 | U36: =T36-T35 -> 39 | V36: =W35 -> 48755 | W36: 48807 | X36: =W36-W35 -> 52 | Y36: =Z35 -> 58913 | Z36: 58939 | AA36: =Z36-Z35 -> 26 | AB36: =AC35 -> 10063 | AC36: 10063 | AD36: =AC36-AC35 -> 0 | AE36: =AF35 -> 8923 | AF36: 8945 | AG36: =AF36-AF35 -> 22 | AH36: =AI35 -> 14057 | AI36: 14098 | AJ36: =AI36-AI35 -> 41 | AK36: =AL35 -> 6536 | AL36: 6536 | AM36: =AL36-AL35 -> 0 | AN36: =U36+X36+AA36+AD36+AG36+AJ36+AM36 -> 180
A37: =Gen!A42 -> 0 | C37: =D36 -> 176819 | E37: =D37-C37 -> -176819 | F37: =G36 -> 31642 | H37: =G37-F37 -> -31642 | I37: =J36 -> 6322 | K37: =J37-J36 -> -6322 | L37: =M36 -> 6488 | N37: =M37-M36 -> -6488 | O37: =P36 -> 15533 | Q37: =P37-O37 -> -15533 | R37: =E37 -> -176819 | S37: =T36 -> 35084 | U37: =T37-T36 -> -35084 | V37: =W36 -> 48807 | X37: =W37-W36 -> -48807 | Y37: =Z36 -> 58939 | AA37: =Z37-Z36 -> -58939 | AB37: =AC36 -> 10063 | AD37: =AC37-AC36 -> -10063 | AE37: =AF36 -> 8945 | AG37: =AF37-AF36 -> -8945 | AH37: =AI36 -> 14098 | AJ37: =AI37-AI36 -> -14098 | AK37: =AL36 -> 6536 | AM37: =AL37-AL36 -> -6536 | AN37: =U37+X37+AA37+AD37+AG37+AJ37+AM37 -> -182472
C38: TOTAL USAGE | E38: =SUM(E6:E36) -> 3670 | F38: KL | H38: =SUM(H6:H37) -> -31114 | K38: =SUM(K6:K37) -> -6197 | Q38: =P38-O38 -> 0 | R38: =E38 -> 3670 | U38: =SUM(U6:U37) -> -33852 | AN38: =U38+X38+AA38+AD38+AG38+AJ38+AM38 -> -33852
C42: WATER TANK LEVEL
C43: RAW WATER TANK NO.1 | E43: RAW WATER TANK NO.2 | G43: TREATED WATER TANK | I43: TREATED -HILL TANK | K43: TOTAL WATER AVAILABLE
C44: CAPACITY 217 m³ | E44: CAPACITY 92 m³ | G44: CAPACITY 146 m³ | I44: CAPACITY 213 m³
C45: cm | D45: m³ | E45: cm | F45: m³ | H45: m³ | I45: cm | J45: m³ | K45: m³
A46: =Gen!A11 -> 43435 | C46: 150 | D46: =C46*217/300 -> 108.5 | E46: 110 | F46: =E46*92/305 -> 33.180328 | G46: 300 | H46: =G46*146/383 -> 114.36031 | I46: 280 | J46: =I46*213/308 -> 193.63636 | K46: =D46+F46+H46+J46 -> 449.677
A47: =Gen!A12 -> 43436 | C47: 175 | D47: =C47*217/300 -> 126.58333 | E47: 140 | F47: =E47*92/305 -> 42.229508 | G47: 220 | H47: =G47*146/383 -> 83.86423 | I47: 275 | J47: =I47*213/308 -> 190.17857 | K47: =D47+F47+H47+J47 -> 442.85564
A48: =Gen!A13 -> 43437 | C48: 186 | D48: =C48*217/300 -> 134.54 | E48: 150 | F48: =E48*92/305 -> 45.245902 | G48: 162 | H48: =G48*146/383 -> 61.754569 | I48: 255 | J48: =I48*213/308 -> 176.3474 | K48: =D48+F48+H48+J48 -> 417.88787
A49: =Gen!A14 -> 43438 | C49: 170 | D49: =C49*217/300 -> 122.96667 | E49: 130 | F49: =E49*92/305 -> 39.213115 | G49: 160 | H49: =G49*146/383 -> 60.992167 | I49: 250 | J49: =I49*213/308 -> 172.88961 | K49: =D49+F49+H49+J49 -> 396.06156
A50: =Gen!A15 -> 43439 | C50: 220 | D50: =C50*217/300 -> 159.13333 | E50: 180 | F50: =E50*92/305 -> 54.295082 | G50: 140 | H50: =G50*146/383 -> 53.368146 | I50: 250 | J50: =I50*213/308 -> 172.88961 | K50: =D50+F50+H50+J50 -> 439.68617
A51: =Gen!A16 -> 43440 | C51: 245 | D51: =C51*217/300 -> 177.21667 | E51: 205 | F51: =E51*92/305 -> 61.836066 | G51: 25 | H51: =G51*146/383 -> 9.5300261 | I51: 240 | J51: =I51*213/308 -> 165.97403 | K51: =D51+F51+H51+J51 -> 414.55678
A52: =Gen!A17 -> 43441 | C52: 160 | D52: =C52*217/300 -> 115.73333 | E52: 100 | F52: =E52*92/305 -> 30.163934 | G52: 185 | H52: =G52*146/383 -> 70.522193 | I52: 220 | J52: =I52*213/308 -> 152.14286 | K52: =D52+F52+H52+J52 -> 368.56232
A53: =Gen!A18 -> 43442 | C53: 185 | D53: =C53*217/300 -> 133.81667 | E53: 145 | F53: =E53*92/305 -> 43.737705 | G53: 240 | H53: =G53*146/383 -> 91.488251 | I53: 240 | J53: =I53*213/308 -> 165.97403 | K53: =D53+F53+H53+J53 -> 435.01665
A54: =Gen!A19 -> 43443 | C54: 171 | D54: =C54*217/300 -> 123.69 | E54: 135 | F54: =E54*92/305 -> 40.721311 | G54: 300 | H54: =G54*146/383 -> 114.36031 | I54: 225 | J54: =I54*213/308 -> 155.60065 | K54: =D54+F54+H54+J54 -> 434.37227
A55: =Gen!A20 -> 43444 | C55: 171 | D55: =C55*217/300 -> 123.69 | E55: 135 | F55: =E55*92/305 -> 40.721311 | G55: 280 | H55: =G55*146/383 -> 106.73629 | I55: 235 | J55: =I55*213/308 -> 162.51623 | K55: =D55+F55+H55+J55 -> 433.66384
A56: =Gen!A21 -> 43445 | C56: 185 | D56: =C56*217/300 -> 133.81667 | E56: 150 | F56: =E56*92/305 -> 45.245902 | G56: 255 | H56: =G56*146/383 -> 97.206266 | I56: 260 | J56: =I56*213/308 -> 179.80519 | K56: =D56+F56+H56+J56 -> 456.07403
A57: =Gen!A22 -> 43446 | C57: 159 | D57: =C57*217/300 -> 115.01 | E57: 123 | F57: =E57*92/305 -> 37.101639 | G57: 205 | H57: =G57*146/383 -> 78.146214 | I57: 280 | J57: =I57*213/308 -> 193.63636 | K57: =D57+F57+H57+J57 -> 423.89422
... A76: =Gen!A41 -> 43465 | C76: 107 | D76: =C76*217/300 -> 77.396667 | E76: 77 | F76: =E76*92/305 -> 23.22623 | G76: 300 | H76: =G76*146/383 -> 114.36031 | I76: 295 | J76: =I76*213/308 -> 204.00974 | K76: =D76+F76+H76+J76 -> 418.99295
A77: =Gen!A42 -> 0 | D77: =C77*217/300 -> 0 | F77: =E77*92/305 -> 0 | H77: =G77*146/383 -> 0 | J77: =I77*213/308 -> 0 | K77: =D77+F77+H77+J77 -> 0

Sheet Water_Graph 
A1: Date | B1: Usage | C1: Occ %
A2: =SUM(Gen!A11) -> 43435 | B2: =SUM('Water-Meter'!R10) -> 24 | C2: =SUM(Gen!B11) -> 0.168
A3: =SUM(Gen!A12) -> 43436 | B3: =SUM('Water-Meter'!R11) -> 27 | C3: =SUM(Gen!B12) -> 0.1429
A4: =SUM(Gen!A13) -> 43437 | B4: =SUM('Water-Meter'!R12) -> 29 | C4: =SUM(Gen!B13) -> 0.1429
A5: =SUM(Gen!A14) -> 43438 | B5: =SUM('Water-Meter'!R13) -> 21 | C5: =SUM(Gen!B14) -> 0.1688
A6: =SUM(Gen!A15) -> 43439 | B6: =SUM('Water-Meter'!R14) -> 27 | C6: =SUM(Gen!B15) -> 0.2078
A7: =SUM(Gen!A16) -> 43440 | B7: =SUM('Water-Meter'!R15) -> 46 | C7: =SUM(Gen!B16) -> 0.2987
A8: =SUM(Gen!A17) -> 43441 | B8: =SUM('Water-Meter'!R16) -> 32 | C8: =SUM(Gen!B17) -> 0.2468
A9: =SUM(Gen!A18) -> 43442 | B9: =SUM('Water-Meter'!R17) -> 34 | C9: =SUM(Gen!B18) -> 0.2857
A10: =SUM(Gen!A19) -> 43443 | B10: =SUM('Water-Meter'!R18) -> 28 | C10: =SUM(Gen!B19) -> 0.4675
A11: =SUM(Gen!A20) -> 43444 | B11: =SUM('Water-Meter'!R19) -> 39 | C11: =SUM(Gen!B20) -> 0.5584
A12: =SUM(Gen!A21) -> 43445 | B12: =SUM('Water-Meter'!R20) -> -95 | C12: =SUM(Gen!B21) -> 0.5714
A13: =SUM(Gen!A22) -> 43446 | B13: =SUM('Water-Meter'!R21) -> 4 | C13: =SUM(Gen!B22) -> 0.2338
... A32: =SUM(Gen!A41) -> 43465 | B32: =SUM('Water-Meter'!R40) -> 0 | C32: =SUM(Gen!B41) -> 0.8442

Sheet WTL-Softner
C4: Four Sasons Safari Lodge Serengeti
C5: WATER TANK LEVELS STP TANKS | I5: PUMPS
A6: DATE | B6: Water Level | C6: Raw water | D6: Hill tank | E6: STP-Hill | F6: STP-Bore | G6: STP | H6: STP-Bore | N6: Bore | O6: Bore | P6: Bore | Q6: Bore | S6: PPM | T6: Water
B7: Raw water | C7: tank | E7: Treated | G7: Condition | H7: tank | I7: Transfer | J7: VSD | K7: Irrigation | L7: Fire | M7: Booster | N7: B-1 | O7: B-2 | P7: B3 | Q7: B-4 | R7: uv | S7: Pre chlorination | T7: Softner-PPM
A9: 0.29166667
A10: 12.noon
A11: 4.00 pm
A12: 10.00 pm
A14: 0.29166667
A15: 12.noon
A16: 4.00 pm
A17: 10.00 pm
A19: 0.29166667
A20: 12.noon
A21: 4.00 pm
A22: 10.00 pm
A24: 0.29166667
A25: 12.noon
A26: 4.00 pm
A27: 10.00 pm
A29: 0.29166667
A30: 12.noon
A31: 4.00 pm
A32: 10.00 pm
A34: 0.29166667
A35: 12.noon
A36: 4.00 pm
A37: 10.00 pm
A39: 0.29166667
A40: 12.noon
A41: 4.00 pm
A42: 10.00 pm

Sheet Sheet1
A2: Generator and Diseal Summry Report JANUARY 2016 | Q2: 2209.85 | R2: Diesel Cost | S2: Rate$ | T2: 1584
M3: % of Gas balance in Tank | P3: % of Dieasel balance in Tank | Q3: HLP Cost (TSH) | V3: Total Cost (TSH) | W3: Consumption Guest Occ% | AA3: Budget Cost Per Room occ
A4: Date | B4: Gen Set Hours Working | C4: Occ% | D4: Total OCC Room | E4: Guest Room Occ | F4: Total Kwh Generated | G4: Diseal consumed by Gen (Ltrs) | H4: Diseal consumed by Veichel (Ltrs) | I4: Total diseal consumed (Ltrs) | J4: Balance stock of Diseal (Ltrs) | K4: Water consumed | L4: Gas consumed (KG) | M4: 3 | N4: 2 | O4: 1 | Q4: Electricity | R4: Cost per Room Total OOC Usd | S4: Cost per Room Guest OOC Usd | T4: Water | U4: Gas
A5: =SUM(Gen!A11) -> 43435 | B5: 0 | C5: =SUM(Gen!B11) -> 0.168 | D5: =SUM(77*C5) -> 12.936 | F5: =Gen!T11 -> 4555 | G5: =Gen!S11 -> 1825.13 | H5: =Gen!#REF! -> #REF! | I5: =SUM(G5:H5) -> #REF! | J5: =Gen!AT11 -> #REF! | K5: ='Water-Meter'!E10 -> 84 | L5: =#REF! -> #REF! | M5: =#REF! -> #REF! | N5: =#REF! -> #REF! | O5: =#REF! -> #REF! | P5: =J5/52000 -> #REF! | Q5: =I5*Q2 -> #REF! | R5: =SUM(Q5/D5)/X5 -> #REF! | S5: =SUM(Q5/E5)/X5 -> #REF! | T5: =(K5*102)/X5 -> 5.4090909 | U5: =SUM(L5*1963)/X5 -> #REF! | V5: =SUM(Q5+T5+U5) -> #REF! | W5: =SUM(V5/E5)/T2 -> #REF! | X5: =SUM(T2) -> 1584 | Y5: 106 | Z5: =SUM(Y5-S5) -> #REF! | AA5: 106
A6: =SUM(Gen!A12) -> 43436 | B6: 0 | C6: =SUM(Gen!B12) -> 0.1429 | D6: =SUM(77*C6) -> 11.0033 | F6: =Gen!T12 -> 4679 | G6: =Gen!S12 -> 1835.19 | H6: =Gen!#REF! -> #REF! | I6: =SUM(G6:H6) -> #REF! | J6: =Gen!AT12 -> #REF! | K6: ='Water-Meter'!E11 -> 108 | L6: =#REF! -> #REF! | M6: =#REF! -> #REF! | N6: =#REF! -> #REF! | O6: =#REF! -> #REF! | P6: =J6/52000 -> #REF! | Q6: =I6*Q2 -> #REF! | R6: =SUM(Q6/D6)/X6 -> #REF! | S6: =SUM(Q6/E6)/X6 -> #REF! | T6: =(K6*102)/X6 -> 6.9545455 | U6: =SUM(L6*1963)/X6 -> #REF! | V6: =SUM(Q6+T6+U6) -> #REF! | W6: =SUM(V6/E6)/T2 -> #REF! | X6: =SUM(X5) -> 1584 | Y6: 106 | Z6: =SUM(Y6-S6) -> #REF!
A7: =SUM(Gen!A13) -> 43437 | B7: 0 | C7: =SUM(Gen!B13) -> 0.1429 | D7: =SUM(77*C7) -> 11.0033 | F7: =Gen!T13 -> 4437 | G7: =Gen!S13 -> 2768.05 | H7: =Gen!#REF! -> #REF! | I7: =SUM(G7:H7) -> #REF! | J7: =Gen!AT13 -> #REF! | K7: ='Water-Meter'!E12 -> 93 | L7: =#REF! -> #REF! | M7: =#REF! -> #REF! | N7: =#REF! -> #REF! | O7: =#REF! -> #REF! | P7: =J7/52000 -> #REF! | Q7: =I7*Q2 -> #REF! | R7: =SUM(Q7/D7)/X7 -> #REF! | S7: =SUM(Q7/E7)/X7 -> #REF! | T7: =(K7*102)/X7 -> 5.9886364 | U7: =SUM(L7*1963)/X7 -> #REF! | V7: =SUM(Q7+T7+U7) -> #REF! | W7: =SUM(V7/E7)/T2 -> #REF! | X7: =SUM(X6) -> 1584 | Y7: 106 | Z7: =SUM(Y7-S7) -> #REF!
A8: =SUM(Gen!A14) -> 43438 | B8: 0 | C8: =SUM(Gen!B14) -> 0.1688 | D8: =SUM(77*C8) -> 12.9976 | F8: =Gen!T14 -> 4694 | G8: =Gen!S14 -> 1910.45 | H8: =Gen!AJ9 -> 0 | I8: =SUM(G8:H8) -> 1910.45 | J8: =Gen!AT14 -> #REF! | K8: ='Water-Meter'!E13 -> 103 | L8: =#REF! -> #REF! | M8: =#REF! -> #REF! | N8: =#REF! -> #REF! | O8: =#REF! -> #REF! | P8: =J8/52000 -> #REF! | Q8: =I8*Q2 -> 4221807.9 | R8: =SUM(Q8/D8)/X8 -> 205.05961 | S8: =SUM(Q8/E8)/X8 -> #DIV/0! | T8: =(K8*102)/X8 -> 6.6325758 | U8: =SUM(L8*1963)/X8 -> #REF! | V8: =SUM(Q8+T8+U8) -> #REF! | W8: =SUM(V8/E8)/T2 -> #REF! | X8: =SUM(X7) -> 1584 | Y8: 106 | Z8: =SUM(Y8-S8) -> #DIV/0!
A9: =SUM(Gen!A15) -> 43439 | B9: 0 | C9: =SUM(Gen!B15) -> 0.2078 | D9: =SUM(77*C9) -> 16.0006 | F9: =Gen!T15 -> 4359 | G9: =Gen!S15 -> 1785.28 | H9: =Gen!AJ10 -> 0 | I9: =SUM(G9:H9) -> 1785.28 | J9: =Gen!AT15 -> #REF! | K9: ='Water-Meter'!E14 -> 125 | L9: =#REF! -> #REF! | M9: =#REF! -> #REF! | N9: =#REF! -> #REF! | O9: =#REF! -> #REF! | P9: =J9/52000 -> #REF! | Q9: =I9*Q2 -> 3945201 | R9: =SUM(Q9/D9)/X9 -> 155.66024 | S9: =SUM(Q9/E9)/X9 -> #DIV/0! | T9: =(K9*102)/X9 -> 8.0492424 | U9: =SUM(L9*1963)/X9 -> #REF! | V9: =SUM(Q9+T9+U9) -> #REF! | W9: =SUM(V9/E9)/T2 -> #REF! | X9: =SUM(X8) -> 1584 | Y9: 106 | Z9: =SUM(Y9-S9) -> #DIV/0!
A10: =SUM(Gen!A16) -> 43440 | B10: 0 | C10: =SUM(Gen!B16) -> 0.2987 | D10: =SUM(77*C10) -> 22.9999 | F10: =Gen!T16 -> 4710 | G10: =Gen!S16 -> 1903.86 | H10: =Gen!#REF! -> #REF! | I10: =SUM(G10:H10) -> #REF! | J10: =Gen!AT16 -> #REF! | K10: ='Water-Meter'!E15 -> 114 | L10: =#REF! -> #REF! | M10: =#REF! -> #REF! | N10: =#REF! -> #REF! | O10: =#REF! -> #REF! | P10: =J10/52000 -> #REF! | Q10: =I10*Q2 -> #REF! | R10: =SUM(Q10/D10)/X10 -> #REF! | S10: =SUM(Q10/E10)/X10 -> #REF! | T10: =(K10*102)/X10 -> 7.3409091 | U10: =SUM(L10*1963)/X10 -> #REF! | V10: =SUM(Q10+T10+U10) -> #REF! | W10: =SUM(V10/E10)/T2 -> #REF! | X10: =SUM(X9) -> 1584 | Y10: 106 | Z10: =SUM(Y10-S10) -> #REF!
A11: =SUM(Gen!A17) -> 43441 | B11: 0 | C11: =SUM(Gen!B17) -> 0.2468 | D11: =SUM(77*C11) -> 19.0036 | F11: =Gen!T17 -> 4875 | G11: =Gen!S17 -> 2010.19 | H11: =Gen!AJ25 -> 571.32 | I11: =SUM(G11:H11) -> 2581.51 | J11: =Gen!AT17 -> #REF! | K11: ='Water-Meter'!E16 -> 114 | L11: =#REF! -> #REF! | M11: =#REF! -> #REF! | N11: =#REF! -> #REF! | O11: =#REF! -> #REF! | P11: =J11/52000 -> #REF! | Q11: =I11*Q2 -> 5704749.9 | R11: =SUM(Q11/D11)/X11 -> 189.51586 | S11: =SUM(Q11/E11)/X11 -> #DIV/0! | T11: =(K11*102)/X11 -> 7.3409091 | U11: =SUM(L11*1963)/X11 -> #REF! | V11: =SUM(Q11+T11+U11) -> #REF! | W11: =SUM(V11/E11)/T2 -> #REF! | X11: =SUM(X10) -> 1584 | Y11: 106 | Z11: =SUM(Y11-S11) -> #DIV/0!
A12: =SUM(Gen!A18) -> 43442 | B12: 0 | C12: =SUM(Gen!B18) -> 0.2857 | D12: =SUM(77*C12) -> 21.9989 | F12: =Gen!T18 -> 4801 | G12: =Gen!S18 -> 1923.46 | H12: =Gen!#REF! -> #REF! | I12: =SUM(G12:H12) -> #REF! | J12: =Gen!AT18 -> #REF! | K12: ='Water-Meter'!E17 -> 105 | L12: =#REF! -> #REF! | M12: =#REF! -> #REF! | N12: =#REF! -> #REF! | O12: =#REF! -> #REF! | P12: =J12/52000 -> #REF! | Q12: =I12*Q2 -> #REF! | R12: =SUM(Q12/D12)/X12 -> #REF! | S12: =SUM(Q12/E12)/X12 -> #REF! | T12: =(K12*102)/X12 -> 6.7613636 | U12: =SUM(L12*1963)/X12 -> #REF! | V12: =SUM(Q12+T12+U12) -> #REF! | W12: =SUM(V12/E12)/T2 -> #REF! | X12: =SUM(X11) -> 1584 | Y12: 106 | Z12: =SUM(Y12-S12) -> #REF!
A13: =SUM(Gen!A19) -> 43443 | B13: 0 | C13: =SUM(Gen!B19) -> 0.4675 | D13: =SUM(77*C13) -> 35.9975 | F13: =Gen!T19 -> 4909 | G13: =Gen!S19 -> 2043.56 | H13: =Gen!#REF! -> #REF! | I13: =SUM(G13:H13) -> #REF! | J13: =Gen!AT19 -> #REF! | K13: ='Water-Meter'!E18 -> 111 | L13: =#REF! -> #REF! | M13: =#REF! -> #REF! | N13: =#REF! -> #REF! | O13: =#REF! -> #REF! | P13: =J13/52000 -> #REF! | Q13: =I13*Q2 -> #REF! | R13: =SUM(Q13/D13)/X13 -> #REF! | S13: =SUM(Q13/E13)/X13 -> #REF! | T13: =(K13*102)/X13 -> 7.1477273 | U13: =SUM(L13*1963)/X13 -> #REF! | V13: =SUM(Q13+T13+U13) -> #REF! | W13: =SUM(V13/E13)/T2 -> #REF! | X13: =SUM(X12) -> 1584 | Y13: 106 | Z13: =SUM(Y13-S13) -> #REF!
A14: =SUM(Gen!A20) -> 43444 | B14: 0 | C14: =SUM(Gen!B20) -> 0.5584 | D14: =SUM(77*C14) -> 42.9968 | F14: =Gen!T20 -> 5316 | G14: =Gen!S20 -> 2103.23 | H14: =Gen!#REF! -> #REF! | I14: =SUM(G14:H14) -> #REF! | J14: =Gen!AT20 -> #REF! | K14: ='Water-Meter'!E19 -> 100 | L14: =#REF! -> #REF! | M14: =#REF! -> #REF! | N14: =#REF! -> #REF! | O14: =#REF! -> #REF! | P14: =J14/52000 -> #REF! | Q14: =I14*Q2 -> #REF! | R14: =SUM(Q14/D14)/X14 -> #REF! | S14: =SUM(Q14/E14)/X14 -> #REF! | T14: =(K14*102)/X14 -> 6.4393939 | U14: =SUM(L14*1963)/X14 -> #REF! | V14: =SUM(Q14+T14+U14) -> #REF! | W14: =SUM(V14/E14)/T2 -> #REF! | X14: =SUM(X13) -> 1584 | Y14: 106 | Z14: =SUM(Y14-S14) -> #REF!
A15: =SUM(Gen!A21) -> 43445 | B15: 0 | C15: =SUM(Gen!B21) -> 0.5714 | D15: =SUM(77*C15) -> 43.9978 | F15: =Gen!T21 -> 4922 | G15: =Gen!S21 -> 2044.33 | H15: =Gen!#REF! -> #REF! | I15: =SUM(G15:H15) -> #REF! | J15: =Gen!AT21 -> #REF! | K15: ='Water-Meter'!E20 -> 87 | L15: =#REF! -> #REF! | M15: =#REF! -> #REF! | N15: =#REF! -> #REF! | O15: =#REF! -> #REF! | P15: =J15/52000 -> #REF! | Q15: =I15*Q2 -> #REF! | R15: =SUM(Q15/D15)/X15 -> #REF! | S15: =SUM(Q15/E15)/X15 -> #REF! | T15: =(K15*102)/X15 -> 5.6022727 | U15: =SUM(L15*1963)/X15 -> #REF! | V15: =SUM(Q15+T15+U15) -> #REF! | W15: =SUM(V15/E15)/T2 -> #REF! | X15: =SUM(X14) -> 1584 | Y15: 106 | Z15: =SUM(Y15-S15) -> #REF!
A16: =SUM(Gen!A22) -> 43446 | B16: 0 | C16: =SUM(Gen!B22) -> 0.2338 | D16: =SUM(77*C16) -> 18.0026 | F16: =Gen!T22 -> 4870 | G16: =Gen!S22 -> 1917.24 | H16: =Gen!#REF! -> #REF! | I16: =SUM(G16:H16) -> #REF! | J16: =Gen!AT22 -> #REF! | K16: ='Water-Meter'!E21 -> 105 | L16: =#REF! -> #REF! | M16: =#REF! -> #REF! | N16: =#REF! -> #REF! | O16: =#REF! -> #REF! | P16: =J16/52000 -> #REF! | Q16: =I16*Q2 -> #REF! | R16: =SUM(Q16/D16)/X16 -> #REF! | S16: =SUM(Q16/E16)/X16 -> #REF! | T16: =(K16*102)/X16 -> 6.7613636 | U16: =SUM(L16*1963)/X16 -> #REF! | V16: =SUM(Q16+T16+U16) -> #REF! | W16: =SUM(V16/E16)/T2 -> #REF! | X16: =SUM(X15) -> 1584 | Y16: 106 | Z16: =SUM(Y16-S16) -> #REF!
A17: =SUM(Gen!A23) -> 43447 | B17: 0 | C17: =SUM(Gen!B23) -> 0.2727 | D17: =SUM(77*C17) -> 20.9979 | F17: =Gen!T23 -> 4660 | G17: =Gen!S23 -> 1891.58 | H17: =Gen!#REF! -> #REF! | I17: =SUM(G17:H17) -> #REF! | J17: =Gen!AT23 -> #REF! | K17: ='Water-Meter'!E22 -> 109 | L17: =#REF! -> #REF! | M17: =#REF! -> #REF! | N17: =#REF! -> #REF! | O17: =#REF! -> #REF! | P17: =J17/52000 -> #REF! | Q17: =I17*Q2 -> #REF! | R17: =SUM(Q17/D17)/X17 -> #REF! | S17: =SUM(Q17/E17)/X17 -> #REF! | T17: =(K17*102)/X17 -> 7.0189394 | U17: =SUM(L17*1963)/X17 -> #REF! | V17: =SUM(Q17+T17+U17) -> #REF! | W17: =SUM(V17/E17)/T2 -> #REF! | X17: =SUM(X16) -> 1584 | Y17: 106 | Z17: =SUM(Y17-S17) -> #REF!
A18: =SUM(Gen!A24) -> 43448 | B18: 0 | C18: =SUM(Gen!B24) -> 0.2595 | D18: =SUM(77*C18) -> 19.9815 | F18: =Gen!T24 -> 4748 | G18: =Gen!S24 -> 1992.44 | H18: =Gen!AJ27 -> 581.31 | I18: =SUM(G18:H18) -> 2573.75 | J18: =Gen!AT24 -> #REF! | K18: 0 | L18: =#REF! -> #REF! | M18: =#REF! -> #REF! | N18: =#REF! -> #REF! | O18: =#REF! -> #REF! | P18: =J18/52000 -> #REF! | Q18: =I18*Q2 -> 5687601.4 | R18: =SUM(Q18/D18)/X18 -> 179.6991 | S18: =SUM(Q18/E18)/X18 -> #DIV/0! | T18: =(K18*102)/X18 -> 0 | U18: =SUM(L18*1963)/X18 -> #REF! | V18: =SUM(Q18+T18+U18) -> #REF! | W18: =SUM(V18/E18)/T2 -> #REF! | X18: =SUM(X17) -> 1584 | Y18: 106 | Z18: =SUM(Y18-S18) -> #DIV/0!
A19: =SUM(Gen!A25) -> 43449 | B19: 0 | C19: =SUM(Gen!B25) -> 0.1299 | D19: =SUM(77*C19) -> 10.0023 | F19: =Gen!T25 -> 4724 | G19: =Gen!S25 -> 1937.98 | H19: =Gen!AJ28 -> 185.71 | I19: =SUM(G19:H19) -> 2123.69 | J19: =Gen!AT25 -> #REF! | K19: ='Water-Meter'!E24 -> 110 | L19: =#REF! -> #REF! | M19: =#REF! -> #REF! | N19: =#REF! -> #REF! | O19: =#REF! -> #REF! | P19: =J19/52000 -> #REF! | Q19: =I19*Q2 -> 4693036.3 | R19: =SUM(Q19/D19)/X19 -> 296.20942 | S19: =SUM(Q19/E19)/X19 -> #DIV/0! | T19: =(K19*102)/X19 -> 7.0833333 | U19: =SUM(L19*1963)/X19 -> #REF! | V19: =SUM(Q19+T19+U19) -> #REF! | W19: =SUM(V19/E19)/T2 -> #REF! | X19: =SUM(X18) -> 1584 | Y19: 106 | Z19: =SUM(Y19-S19) -> #DIV/0!
A20: =SUM(Gen!A26) -> 43450 | B20: 0 | C20: =SUM(Gen!B26) -> 0.2597 | D20: =SUM(77*C20) -> 19.9969 | F20: =Gen!T26 -> 5005 | G20: =Gen!S26 -> 2042.13 | H20: =Gen!AJ29 -> 118 | I20: =SUM(G20:H20) -> 2160.13 | J20: =Gen!AT26 -> #REF! | K20: ='Water-Meter'!E25 -> 123 | L20: =#REF! -> #REF! | M20: =#REF! -> #REF! | N20: =#REF! -> #REF! | O20: =#REF! -> #REF! | P20: =J20/52000 -> #REF! | Q20: =I20*Q2 -> 4773563.3 | R20: =SUM(Q20/D20)/X20 -> 150.70402 | S20: =SUM(Q20/E20)/X20 -> #DIV/0! | T20: =(K20*102)/X20 -> 7.9204545 | U20: =SUM(L20*1963)/X20 -> #REF! | V20: =SUM(Q20+T20+U20) -> #REF! | W20: =SUM(V20/E20)/T2 -> #REF! | X20: =SUM(X19) -> 1584 | Y20: 106 | Z20: =SUM(Y20-S20) -> #DIV/0!
A21: =SUM(Gen!A27) -> 43451 | B21: 0 | C21: =SUM(Gen!B27) -> 0.2987 | D21: =SUM(77*C21) -> 22.9999 | F21: =Gen!T27 -> 5332 | G21: =Gen!S27 -> 2099.06 | H21: =Gen!AJ30 -> 690.09 | I21: =SUM(G21:H21) -> 2789.15 | J21: =Gen!AT27 -> #REF! | K21: ='Water-Meter'!E26 -> 130 | L21: =#REF! -> #REF! | M21: =#REF! -> #REF! | N21: =#REF! -> #REF! | O21: =#REF! -> #REF! | P21: =J21/52000 -> #REF! | Q21: =I21*Q2 -> 6163603.1 | R21: =SUM(Q21/D21)/X21 -> 169.18176 | S21: =SUM(Q21/E21)/X21 -> #DIV/0! | T21: =(K21*102)/X21 -> 8.3712121 | U21: =SUM(L21*1963)/X21 -> #REF! | V21: =SUM(Q21+T21+U21) -> #REF! | W21: =SUM(V21/E21)/T2 -> #REF! | X21: =SUM(X20) -> 1584 | Y21: 106 | Z21: =SUM(Y21-S21) -> #DIV/0!
A22: =SUM(Gen!A28) -> 43452 | B22: 0 | C22: =SUM(Gen!B28) -> 0.5065 | D22: =SUM(77*C22) -> 39.0005 | F22: =Gen!T28 -> 5890 | G22: =Gen!S28 -> 2371.98 | H22: =Gen!#REF! -> #REF! | I22: =SUM(G22:H22) -> #REF! | J22: =Gen!AT28 -> #REF! | K22: ='Water-Meter'!E27 -> 130 | L22: =#REF! -> #REF! | M22: =#REF! -> #REF! | N22: =#REF! -> #REF! | O22: =#REF! -> #REF! | P22: =J22/52000 -> #REF! | Q22: =I22*Q2 -> #REF! | R22: =SUM(Q22/D22)/X22 -> #REF! | S22: =SUM(Q22/E22)/X22 -> #REF! | T22: =(K22*102)/X22 -> 8.3712121 | U22: =SUM(L22*1963)/X22 -> #REF! | V22: =SUM(Q22+T22+U22) -> #REF! | W22: =SUM(V22/E22)/T2 -> #REF! | X22: =SUM(X21) -> 1584 | Y22: 106 | Z22: =SUM(Y22-S22) -> #REF!
A23: =SUM(Gen!A29) -> 43453 | B23: 0 | C23: =SUM(Gen!B29) -> 0.4416 | D23: =SUM(77*C23) -> 34.0032 | F23: =Gen!T29 -> 5737 | G23: =Gen!S29 -> 2258.75 | H23: =Gen!#REF! -> #REF! | I23: =SUM(G23:H23) -> #REF! | J23: =Gen!AT29 -> #REF! | K23: ='Water-Meter'!E28 -> 131 | L23: =#REF! -> #REF! | M23: =#REF! -> #REF! | N23: =#REF! -> #REF! | O23: =#REF! -> #REF! | P23: =J23/52000 -> #REF! | Q23: =I23*Q2 -> #REF! | R23: =SUM(Q23/D23)/X23 -> #REF! | S23: =SUM(Q23/E23)/X23 -> #REF! | T23: =(K23*102)/X23 -> 8.4356061 | U23: =SUM(L23*1963)/X23 -> #REF! | V23: =SUM(Q23+T23+U23) -> #REF! | W23: =SUM(V23/E23)/T2 -> #REF! | X23: =SUM(X22) -> 1584 | Y23: 106 | Z23: =SUM(Y23-S23) -> #REF!
A24: =SUM(Gen!A30) -> 43454 | B24: 0 | C24: =SUM(Gen!B30) -> 0.4026 | D24: =SUM(77*C24) -> 31.0002 | F24: =Gen!T30 -> 5582 | G24: =Gen!S30 -> 2355.33 | H24: =Gen!#REF! -> #REF! | I24: =SUM(G24:H24) -> #REF! | J24: =Gen!AT30 -> #REF! | K24: ='Water-Meter'!E29 -> 112 | L24: =#REF! -> #REF! | M24: =#REF! -> #REF! | N24: =#REF! -> #REF! | O24: =#REF! -> #REF! | P24: =J24/52000 -> #REF! | Q24: =I24*Q2 -> #REF! | R24: =SUM(Q24/D24)/X24 -> #REF! | S24: =SUM(Q24/E24)/X24 -> #REF! | T24: =(K24*102)/X24 -> 7.2121212 | U24: =SUM(L24*1963)/X24 -> #REF! | V24: =SUM(Q24+T24+U24) -> #REF! | W24: =SUM(V24/E24)/T2 -> #REF! | X24: =SUM(X23) -> 1584 | Y24: 106 | Z24: =SUM(Y24-S24) -> #REF!
A25: =SUM(Gen!A31) -> 43455 | B25: 0 | C25: =SUM(Gen!B31) -> 0.4935 | D25: =SUM(77*C25) -> 37.9995 | F25: =Gen!T31 -> 5599 | G25: =Gen!S31 -> 2159.4 | H25: =Gen!AJ31 -> 544.38 | I25: =SUM(G25:H25) -> 2703.78 | J25: =Gen!AT31 -> #REF! | K25: ='Water-Meter'!E30 -> 147 | L25: =#REF! -> #REF! | M25: =#REF! -> #REF! | N25: =#REF! -> #REF! | O25: =#REF! -> #REF! | P25: =J25/52000 -> #REF! | Q25: =I25*Q2 -> 5974948.2 | R25: =SUM(Q25/D25)/X25 -> 99.266129 | S25: =SUM(Q25/E25)/X25 -> #DIV/0! | T25: =(K25*102)/X25 -> 9.4659091 | U25: =SUM(L25*1963)/X25 -> #REF! | V25: =SUM(Q25+T25+U25) -> #REF! | W25: =SUM(V25/E25)/T2 -> #REF! | X25: =SUM(X24) -> 1584 | Y25: 106 | Z25: =SUM(Y25-S25) -> #DIV/0!
A26: =SUM(Gen!A32) -> 43456 | B26: 0 | C26: =SUM(Gen!B32) -> 0.4935 | D26: =SUM(77*C26) -> 37.9995 | F26: =Gen!T32 -> 5928 | G26: =Gen!S32 -> 2501.02 | H26: =Gen!AJ32 -> 322.73 | I26: =SUM(G26:H26) -> 2823.75 | J26: =Gen!AT32 -> #REF! | K26: ='Water-Meter'!E31 -> 167 | L26: =#REF! -> #REF! | M26: =#REF! -> #REF! | N26: =#REF! -> #REF! | O26: =#REF! -> #REF! | P26: =J26/52000 -> #REF! | Q26: =I26*Q2 -> 6240063.9 | R26: =SUM(Q26/D26)/X26 -> 103.67069 | S26: =SUM(Q26/E26)/X26 -> #DIV/0! | T26: =(K26*102)/X26 -> 10.753788 | U26: =SUM(L26*1963)/X26 -> #REF! | V26: =SUM(Q26+T26+U26) -> #REF! | W26: =SUM(V26/E26)/T2 -> #REF! | X26: =SUM(X25) -> 1584 | Y26: 106 | Z26: =SUM(Y26-S26) -> #DIV/0!
A27: =SUM(Gen!A33) -> 43457 | B27: 0 | C27: =SUM(Gen!B33) -> 0.4456 | D27: =SUM(77*C27) -> 34.3112 | F27: =Gen!T33 -> 5850 | G27: =Gen!S33 -> 2375.47 | H27: =Gen!AJ33 -> 93.91 | I27: =SUM(G27:H27) -> 2469.38 | J27: =Gen!AT33 -> #REF! | K27: ='Water-Meter'!E32 -> 159 | L27: =#REF! -> #REF! | M27: =#REF! -> #REF! | N27: =#REF! -> #REF! | O27: =#REF! -> #REF! | P27: =J27/52000 -> #REF! | Q27: =I27*Q2 -> 5456959.4 | R27: =SUM(Q27/D27)/X27 -> 100.40599 | S27: =SUM(Q27/E27)/X27 -> #DIV/0! | T27: =(K27*102)/X27 -> 10.238636 | U27: =SUM(L27*1963)/X27 -> #REF! | V27: =SUM(Q27+T27+U27) -> #REF! | W27: =SUM(V27/E27)/T2 -> #REF! | X27: =SUM(X26) -> 1584 | Y27: 106 | Z27: =SUM(Y27-S27) -> #DIV/0!
A28: =SUM(Gen!A34) -> 43458 | B28: 0 | C28: =SUM(Gen!B34) -> 0.5065 | D28: =SUM(77*C28) -> 39.0005 | F28: =Gen!T34 -> 6147 | G28: =Gen!S34 -> 2708.28 | H28: =Gen!AJ34 -> 786.27 | I28: =SUM(G28:H28) -> 3494.55 | J28: =Gen!AT34 -> #REF! | K28: ='Water-Meter'!E33 -> 164 | L28: =#REF! -> #REF! | M28: =#REF! -> #REF! | N28: =#REF! -> #REF! | O28: =#REF! -> #REF! | P28: =J28/52000 -> #REF! | Q28: =I28*Q2 -> 7722431.3 | R28: =SUM(Q28/D28)/X28 -> 125.00538 | S28: =SUM(Q28/E28)/X28 -> #DIV/0! | T28: =(K28*102)/X28 -> 10.560606 | U28: =SUM(L28*1963)/X28 -> #REF! | V28: =SUM(Q28+T28+U28) -> #REF! | W28: =SUM(V28/E28)/T2 -> #REF! | X28: =SUM(X27) -> 1584 | Y28: 106 | Z28: =SUM(Y28-S28) -> #DIV/0!
A29: =SUM(Gen!A35) -> 43459 | B29: 0 | C29: =SUM(Gen!B35) -> 0.9481 | D29: =SUM(77*C29) -> 73.0037 | F29: =Gen!T35 -> 6478 | G29: =Gen!S35 -> 2810.4 | H29: =Gen!AJ35 -> 174.44 | I29: =SUM(G29:H29) -> 2984.84 | J29: =Gen!AT35 -> #REF! | K29: ='Water-Meter'!E34 -> 173 | L29: =#REF! -> #REF! | M29: =#REF! -> #REF! | N29: =#REF! -> #REF! | O29: =#REF! -> #REF! | P29: =J29/52000 -> #REF! | Q29: =I29*Q2 -> 6596048.7 | R29: =SUM(Q29/D29)/X29 -> 57.040563 | S29: =SUM(Q29/E29)/X29 -> #DIV/0! | T29: =(K29*102)/X29 -> 11.140152 | U29: =SUM(L29*1963)/X29 -> #REF! | V29: =SUM(Q29+T29+U29) -> #REF! | W29: =SUM(V29/E29)/T2 -> #REF! | X29: =SUM(X28) -> 1584 | Y29: 106 | Z29: =SUM(Y29-S29) -> #DIV/0!
A30: =SUM(Gen!A36) -> 43460 | B30: 0 | C30: =SUM(Gen!B36) -> 0.9091 | D30: =SUM(77*C30) -> 70.0007 | F30: =Gen!T36 -> 6636 | G30: =Gen!S36 -> 2865.5 | H30: =Gen!AJ36 -> 356.08 | I30: =SUM(G30:H30) -> 3221.58 | J30: =Gen!AT36 -> #REF! | K30: ='Water-Meter'!E35 -> 156 | L30: =#REF! -> #REF! | M30: =#REF! -> #REF! | N30: =#REF! -> #REF! | O30: =#REF! -> #REF! | P30: =J30/52000 -> #REF! | Q30: =I30*Q2 -> 7119208.6 | R30: =SUM(Q30/D30)/X30 -> 64.205784 | S30: =SUM(Q30/E30)/X30 -> #DIV/0! | T30: =(K30*102)/X30 -> 10.045455 | U30: =SUM(L30*1963)/X30 -> #REF! | V30: =SUM(Q30+T30+U30) -> #REF! | W30: =SUM(V30/E30)/T2 -> #REF! | X30: =SUM(X29) -> 1584 | Y30: 106 | Z30: =SUM(Y30-S30) -> #DIV/0!
A31: =SUM(Gen!A37) -> 43461 | B31: 0 | C31: =SUM(Gen!B37) -> 0.7662 | D31: =SUM(77*C31) -> 58.9974 | F31: =Gen!T37 -> 6583 | G31: =Gen!S37 -> 2635.34 | H31: =Gen!AJ37 -> 203.69 | I31: =SUM(G31:H31) -> 2839.03 | J31: =Gen!AT37 -> #REF! | K31: ='Water-Meter'!E36 -> 120 | L31: =#REF! -> #REF! | M31: =#REF! -> #REF! | N31: =#REF! -> #REF! | O31: =#REF! -> #REF! | P31: =J31/52000 -> #REF! | Q31: =I31*Q2 -> 6273830.4 | R31: =SUM(Q31/D31)/X31 -> 67.134341 | S31: =SUM(Q31/E31)/X31 -> #DIV/0! | T31: =(K31*102)/X31 -> 7.7272727 | U31: =SUM(L31*1963)/X31 -> #REF! | V31: =SUM(Q31+T31+U31) -> #REF! | W31: =SUM(V31/E31)/T2 -> #REF! | X31: =SUM(X30) -> 1584 | Y31: 106 | Z31: =SUM(Y31-S31) -> #DIV/0!
A32: =SUM(Gen!A38) -> 43462 | B32: 0 | C32: =SUM(Gen!B38) -> 0.7792 | D32: =SUM(77*C32) -> 59.9984 | F32: =Gen!T38 -> 7094 | G32: =Gen!S38 -> 3043.34 | H32: =Gen!AJ38 -> 321.45 | I32: =SUM(G32:H32) -> 3364.79 | J32: =Gen!AT38 -> #REF! | K32: ='Water-Meter'!E37 -> -176819 | L32: =#REF! -> #REF! | M32: =#REF! -> #REF! | N32: =#REF! -> #REF! | O32: =#REF! -> #REF! | P32: =J32/52000 -> #REF! | Q32: =I32*Q2 -> 7435681.2 | R32: =SUM(Q32/D32)/X32 -> 78.239473 | S32: =SUM(Q32/E32)/X32 -> #DIV/0! | T32: =(K32*102)/X32 -> -11386.072 | U32: =SUM(L32*1963)/X32 -> #REF! | V32: =SUM(Q32+T32+U32) -> #REF! | W32: =SUM(V32/E32)/T2 -> #REF! | X32: =SUM(X31) -> 1584 | Y32: 106 | Z32: =SUM(Y32-S32) -> #DIV/0!
B33: 0 | C33: =SUM(Gen!B39) -> 0.9221 | D33: =SUM(77*C33) -> 71.0017 | F33: =Gen!T39 -> 7628 | G33: =Gen!S39 -> 2871.98 | H33: =Gen!AJ39 -> 247.04 | I33: =SUM(G33:H33) -> 3119.02 | J33: =Gen!AT39 -> #REF! | K33: ='Water-Meter'!E38 -> 3670 | L33: =#REF! -> #REF! | M33: =#REF! -> #REF! | N33: =#REF! -> #REF! | O33: =#REF! -> #REF! | P33: =J33/52000 -> #REF! | Q33: =I33*Q2 -> 6892566.3 | R33: =SUM(Q33/D33)/X33 -> 61.285401 | S33: =SUM(Q33/E33)/X33 -> #DIV/0! | T33: =(K33*102)/X33 -> 236.32576 | U33: =SUM(L33*1963)/X33 -> #REF! | V33: =SUM(Q33+T33+U33) -> #REF! | W33: =SUM(V33/E33)/T2 -> #REF! | X33: =SUM(X32) -> 1584 | Y33: 106 | Z33: =SUM(Y33-S33) -> #DIV/0!
B34: 0 | C34: =SUM(Gen!B40) -> 0.7792 | D34: =SUM(77*C34) -> 59.9984 | F34: =Gen!T40 -> 7378 | G34: =Gen!S40 -> 3172.51 | H34: =Gen!AJ40 -> 120.12 | I34: =SUM(G34:H34) -> 3292.63 | J34: =Gen!AT40 -> #REF! | K34: ='Water-Meter'!E39 -> 0 | L34: =#REF! -> #REF! | M34: =#REF! -> #REF! | N34: =#REF! -> #REF! | O34: =#REF! -> #REF! | P34: =J34/52000 -> #REF! | Q34: =I34*Q2 -> 7276218.4 | R34: =SUM(Q34/D34)/X34 -> 76.561579 | S34: =SUM(Q34/E34)/X34 -> #DIV/0! | T34: =(K34*102)/X34 -> 0 | U34: =SUM(L34*1963)/X34 -> #REF! | V34: =SUM(Q34+T34+U34) -> #REF! | W34: =SUM(V34/E34)/T2 -> #REF! | X34: =SUM(X33) -> 1584 | Y34: 106 | Z34: =SUM(Y34-S34) -> #DIV/0!
B35: 0 | C35: =SUM(Gen!B41) -> 0.8442 | D35: =SUM(77*C35) -> 65.0034 | F35: =Gen!T41 -> 7255 | G35: =Gen!S41 -> 3058.76 | H35: =Gen!AJ41 -> 1284.14 | I35: =SUM(G35:H35) -> 4342.9 | J35: =Gen!AT41 -> #REF! | K35: ='Water-Meter'!E40 -> 0 | L35: =#REF! -> #REF! | M35: =#REF! -> #REF! | N35: =#REF! -> #REF! | O35: =#REF! -> #REF! | P35: =J35/52000 -> #REF! | Q35: =I35*Q2 -> 9597157.6 | R35: =SUM(Q35/D35)/X35 -> 93.207611 | S35: =SUM(Q35/E35)/X35 -> #DIV/0! | T35: =(K35*102)/X35 -> 0 | U35: =SUM(L35*1963)/X35 -> #REF! | V35: =SUM(Q35+T35+U35) -> #REF! | W35: =SUM(V35/E35)/T2 -> #REF! | X35: =SUM(X34) -> 1584 | Y35: 106 | Z35: =SUM(Y35-S35) -> #DIV/0!
K36: ='Water-Meter'!E41 -> 0 | Q36: =I36*2057.79 -> 0 | V36: =SUM(Q36+T36+U36) -> 0
S37: =SUM(S5:S16)/Gen!A47 -> #REF!
B38: =SUM(B5:B37)/Gen!A47 -> 0 | M38: =0.5*2057.79 -> 1028.895
B39: =SUM(B38*Gen!A47) -> 0 | C39: =SUM(B39/250) -> 0 | M39: =M38/1500 -> 0.68593 | O39: =(24*2.2)*2 -> 105.6 | P39: =O39*1029 -> 108662.4 | R39: Over budget | S39: =SUM(S37-Y35) -> #REF!
P40: =P39/K5 -> 1293.6

Sheet PRINT
A1: UTILITY REPORT OCTOBER 2018
C2: DIESEL | K2: WATER | R2: LPG
B3: GUEST ROOM OCC. | C3: Genset. cons. | E3: Vehicle. Cons. & Incenerator | F3: Total Diesel Cons.Gen&Vehicles | G3: D-TANK A | H3: D-TANK B | I3: Total Diesel Tanks balance | J3: Total Diesel balance | K3: Water cons. | L3: Bore hole water prod. | M3: RO PRODUCTION | Q3: STP prod.m³ | R3: GAS-TANK Kg
A4: DATE | M4: 1 | N4: 2 | O4: 3 | P4: m³ | R4: A | S4: B | T4: C
