Workbook

Sheet Total
A1: Site Name | B1: Day | C1: Month | D1: Year | E1: Total Electricity Kwh | F1: Electricity Tariff ($/Kwh) | G1: Total Fuel Oil (Liters) | H1: Fuel Oil $/Liter | I1: LPG (Kg) | J1: LPG $/Kg | K1: Water Utility Supply (m3) m3 | L1: Water Utility Supply (m3) $/m3 | M1: Irrigation Water (m3) m3 | N1: Irrigation water $/m3 | O1: Room Nights
A2: Beirut | B2: 1 | C2: 12 | D2: 2019 | E2: =ELEC!N3 -> 14340.2 | F2: =SUM('EDl log'!T4) -> 0.033593648 | G2: =-tanks!AW6 -> 229 | H2: =SUM(tanks!AV6) -> 0.5337 | I2: =('B5'!AU5)*0.51 -> 30.6 | J2: ='B5'!AX5/0.51 -> 1.372549 | K2: =WATER!I6 -> 155 | L2: =SUM(WATER!J6) -> 1.5608741 | M2: =WATER!Q6 -> 0 | N2: 0.6 | O2: =ELEC!B3 -> 35.995
A3: Beirut | B3: =B2+1 -> 2 | C3: 12 | D3: 2019 | E3: =ELEC!N4 -> 14840 | F3: =SUM('EDl log'!T5) -> 0.08214287 | G3: =-tanks!AW7 -> 329 | H3: =SUM(tanks!AV7) -> 0.5337 | I3: =('B5'!AU6)*0.51 -> 76.5 | J3: ='B5'!AX6/0.51 -> 1.372549 | K3: =WATER!I7 -> 0 | L3: =SUM(WATER!J7) -> 0 | M3: =WATER!Q7 -> 0 | N3: 0.6 | O3: =ELEC!B4 -> 29.992
A4: Beirut | B4: =B3+1 -> 3 | C4: 12 | D4: 2019 | E4: =ELEC!N5 -> 15111 | F4: =SUM('EDl log'!T6) -> 0.082147141 | G4: =-tanks!AW8 -> 624.7 | H4: =SUM(tanks!AV8) -> 0.5337 | I4: =('B5'!AU7)*0.51 -> 45.9 | J4: ='B5'!AX7/0.51 -> 1.372549 | K4: =WATER!I8 -> 266 | L4: =SUM(WATER!J8) -> 1.4524642 | M4: =WATER!Q8 -> 0 | N4: 0.6 | O4: =ELEC!B5 -> 35.006
A5: Beirut | B5: =B4+1 -> 4 | C5: 12 | D5: 2019 | E5: =ELEC!N6 -> 15739 | F5: =SUM('EDl log'!T7) -> 0.075278175 | G5: =-tanks!AW9 -> 449.9 | H5: =SUM(tanks!AV9) -> 0.5337 | I5: =('B5'!AU8)*0.51 -> 168.3 | J5: ='B5'!AX8/0.51 -> 1.372549 | K5: =WATER!I9 -> 0 | L5: =SUM(WATER!J9) -> 0 | M5: =WATER!Q9 -> 0 | N5: 0.6 | O5: =ELEC!B6 -> 41.009
A6: Beirut | B6: =B5+1 -> 5 | C6: 12 | D6: 2019 | E6: =ELEC!N7 -> 13473 | F6: =SUM('EDl log'!T8) -> 0.093921303 | G6: =-tanks!AW10 -> 498 | H6: =SUM(tanks!AV10) -> 0.5337 | I6: =('B5'!AU9)*0.51 -> 163.2 | J6: ='B5'!AX9/0.51 -> 1.372549 | K6: =WATER!I10 -> 189 | L6: =SUM(WATER!J10) -> 1.2800819 | M6: =WATER!Q10 -> 0 | N6: 0.6 | O6: =ELEC!B7 -> 48.99
A7: Beirut | B7: =B6+1 -> 6 | C7: 12 | D7: 2019 | E7: =ELEC!N8 -> 14010.4 | F7: =SUM('EDl log'!T9) -> 0.093858029 | G7: =-tanks!AW11 -> 705.8 | H7: =SUM(tanks!AV11) -> 0.5337 | I7: =('B5'!AU10)*0.51 -> 15.3 | J7: ='B5'!AX10/0.51 -> 1.372549 | K7: =WATER!I11 -> 0 | L7: =SUM(WATER!J11) -> 0 | M7: =WATER!Q11 -> 0 | N7: 0.6 | O7: =ELEC!B8 -> 40.94
A8: Beirut | B8: =B7+1 -> 7 | C8: 12 | D8: 2019 | E8: =ELEC!N9 -> 15285.6 | F8: =SUM('EDl log'!T10) -> 0.08271187 | G8: =-tanks!AW12 -> 960.3 | H8: =SUM(tanks!AV12) -> 0.5337 | I8: =('B5'!AU11)*0.51 -> 45.9 | J8: ='B5'!AX11/0.51 -> 1.372549 | K8: =WATER!I12 -> 158 | L8: =SUM(WATER!J12) -> 1.5312372 | M8: =WATER!Q12 -> 0 | N8: 0.6 | O8: =ELEC!B9 -> 31.97
A9: Beirut | B9: =B8+1 -> 8 | C9: 12 | D9: 2019 | E9: =ELEC!N10 -> 16664 | F9: =SUM('EDl log'!T11) -> 0.065420619 | G9: =-tanks!AW13 -> 642 | H9: =SUM(tanks!AV13) -> 0.5337 | I9: =('B5'!AU12)*0.51 -> 0 | J9: ='B5'!AX12/0.51 -> 1.372549 | K9: =WATER!I13 -> 80 | L9: =SUM(WATER!J13) -> 4.6841935 | M9: =WATER!Q13 -> 0 | N9: 0.6 | O9: =ELEC!B10 -> 37.306
A10: Beirut | B10: =B9+1 -> 9 | C10: 12 | D10: 2019 | E10: =ELEC!N11 -> 13515 | F10: =SUM('EDl log'!T12) -> 0.087412424 | G10: =-tanks!AW14 -> 624 | H10: =SUM(tanks!AV14) -> 0.5337 | I10: =('B5'!AU13)*0.51 -> 198.9 | J10: ='B5'!AX13/0.51 -> 1.372549 | K10: =WATER!I14 -> 124 | L10: =SUM(WATER!J14) -> 3.0354475 | M10: =WATER!Q14 -> 0 | N10: 0.6 | O10: =ELEC!B11 -> 39.997
A11: Beirut | B11: =B10+1 -> 10 | C11: 12 | D11: 2019 | E11: =ELEC!N12 -> 15465 | F11: =SUM('EDl log'!T13) -> 0.075832705 | G11: =-tanks!AW15 -> 762.2 | H11: =SUM(tanks!AV15) -> 0.5337 | I11: =('B5'!AU14)*0.51 -> 76.5 | J11: ='B5'!AX14/0.51 -> 1.372549 | K11: =WATER!I15 -> 0 | L11: =SUM(WATER!J15) -> 0 | M11: =WATER!Q15 -> 0 | N11: 0.6 | O11: =ELEC!B12 -> 43.01
A12: Beirut | B12: =B11+1 -> 11 | C12: 12 | D12: 2019 | E12: =ELEC!N13 -> 13877 | F12: =SUM('EDl log'!T14) -> 0.086183857 | G12: =-tanks!AW16 -> 838.2 | H12: =SUM(tanks!AV16) -> 0.5337 | I12: =('B5'!AU15)*0.51 -> 91.8 | J12: ='B5'!AX15/0.51 -> 1.372549 | K12: =WATER!I16 -> 0 | L12: =SUM(WATER!J16) -> 0 | M12: =WATER!Q16 -> 0 | N12: 0.6 | O12: =ELEC!B13 -> 35.995
A13: Beirut | B13: =B12+1 -> 12 | C13: 12 | D13: 2019 | E13: =ELEC!N14 -> 14595 | F13: =SUM('EDl log'!T15) -> 0.016696053 | G13: =-tanks!AW17 -> 661 | H13: =SUM(tanks!AV17) -> 0.5271 | I13: =('B5'!AU16)*0.51 -> 163.2 | J13: ='B5'!AX16/0.51 -> 1.372549 | K13: =WATER!I17 -> 0 | L13: =SUM(WATER!J17) -> 0 | M13: =WATER!Q17 -> 0 | N13: 0.6 | O13: =ELEC!B14 -> 50.002
A14: Beirut | B14: =B13+1 -> 13 | C14: 12 | D14: 2019 | E14: =ELEC!N15 -> 15369 | F14: =SUM('EDl log'!T16) -> 0.081696924 | G14: =-tanks!AW18 -> 867 | H14: =SUM(tanks!AV18) -> 0.5271 | I14: =('B5'!AU17)*0.51 -> 137.7 | J14: ='B5'!AX17/0.51 -> 1.372549 | K14: =WATER!I18 -> 0 | L14: =SUM(WATER!J18) -> 0 | M14: =WATER!Q18 -> 0 | N14: 0.6 | O14: =ELEC!B15 -> 54.004
... A32: Beirut | B32: =B31+1 -> 31 | C32: 12 | D32: 2019 | E32: =ELEC!N33 -> 16085 | F32: =SUM('EDl log'!T34) -> 0.14031883 | G32: =-tanks!AW36 -> 1284.8 | H32: =SUM(tanks!AV36) -> 0.5634 | I32: =('B5'!AU35)*0.51 -> 137.7 | J32: ='B5'!AX35/0.51 -> 1.372549 | K32: =WATER!I36 -> 345 | L32: =SUM(WATER!J36) -> 1.3363927 | M32: =WATER!Q36 -> 0 | N32: 0.6 | O32: =ELEC!B33 -> 115

Sheet Submetering
A1: Site Name | B1: Day | C1: Month | D1: Year | E1: ATS1 Kwh | F1: ATS2 Kwh | G1: ATS3 Kwh | H1: ATS4 Kwh | I1: ATS5 Kwh | J1: Guest (m3) | K1: Kitchen & Laundry (m3) | L1: Room Nights
A2: Beirut | B2: 1 | C2: 12 | D2: 2019 | E2: =ELEC!M3 -> 3450 | F2: =ELEC!K3 -> 3210 | G2: =ELEC!I3 -> 2218 | H2: =ELEC!E3 -> 3450 | I2: =ELEC!G3 -> 2012.2 | J2: =WATER!Y6 -> 113 | K2: =WATER!AJ6 -> 35 | L2: =ELEC!B3 -> 35.995
A3: Beirut | B3: =B2+1 -> 2 | C3: 12 | D3: 2019 | E3: =ELEC!M4 -> 4524 | F3: =ELEC!K4 -> 2202 | G3: =ELEC!I4 -> 2244 | H3: =ELEC!E4 -> 3828 | I3: =ELEC!G4 -> 2042 | J3: =WATER!Y7 -> 27 | K3: =WATER!AJ7 -> 21 | L3: =ELEC!B4 -> 29.992
A4: Beirut | B4: =B3+1 -> 3 | C4: 12 | D4: 2019 | E4: =ELEC!M5 -> 4354 | F4: =ELEC!K5 -> 1416 | G4: =ELEC!I5 -> 2516 | H4: =ELEC!E5 -> 4548 | I4: =ELEC!G5 -> 2277 | J4: =WATER!Y8 -> 104 | K4: =WATER!AJ8 -> 78 | L4: =ELEC!B5 -> 35.006
A5: Beirut | B5: =B4+1 -> 4 | C5: 12 | D5: 2019 | E5: =ELEC!M6 -> 3900 | F5: =ELEC!K6 -> 2232 | G5: =ELEC!I6 -> 2650 | H5: =ELEC!E6 -> 4648 | I5: =ELEC!G6 -> 2309 | J5: =WATER!Y9 -> 1 | K5: =WATER!AJ9 -> 0 | L5: =ELEC!B6 -> 41.009
A6: Beirut | B6: =B5+1 -> 5 | C6: 12 | D6: 2019 | E6: =ELEC!M7 -> 3310 | F6: =ELEC!K7 -> 1824 | G6: =ELEC!I7 -> 2222 | H6: =ELEC!E7 -> 4060 | I6: =ELEC!G7 -> 2057 | J6: =WATER!Y10 -> 11 | K6: =WATER!AJ10 -> 38 | L6: =ELEC!B7 -> 48.99
A7: Beirut | B7: =B6+1 -> 6 | C7: 12 | D7: 2019 | E7: =ELEC!M8 -> 3446 | F7: =ELEC!K8 -> 2080 | G7: =ELEC!I8 -> 2504 | H7: =ELEC!E8 -> 3720 | I7: =ELEC!G8 -> 2260.4 | J7: =WATER!Y11 -> 28 | K7: =WATER!AJ11 -> 15 | L7: =ELEC!B8 -> 40.94
A8: Beirut | B8: =B7+1 -> 7 | C8: 12 | D8: 2019 | E8: =ELEC!M9 -> 4540 | F8: =ELEC!K9 -> 2520 | G8: =ELEC!I9 -> 2602 | H8: =ELEC!E9 -> 3377 | I8: =ELEC!G9 -> 2246.6 | J8: =WATER!Y12 -> 33 | K8: =WATER!AJ12 -> 57 | L8: =ELEC!B9 -> 31.97
A9: Beirut | B9: =B8+1 -> 8 | C9: 12 | D9: 2019 | E9: =ELEC!M10 -> 5412 | F9: =ELEC!K10 -> 1704 | G9: =ELEC!I10 -> 2798 | H9: =ELEC!E10 -> 4255 | I9: =ELEC!G10 -> 2495 | J9: =WATER!Y13 -> 80 | K9: =WATER!AJ13 -> 44 | L9: =ELEC!B10 -> 37.306
A10: Beirut | B10: =B9+1 -> 9 | C10: 12 | D10: 2019 | E10: =ELEC!M11 -> 3200 | F10: =ELEC!K11 -> 1756 | G10: =ELEC!I11 -> 2430 | H10: =ELEC!E11 -> 4060 | I10: =ELEC!G11 -> 2069 | J10: =WATER!Y14 -> 78 | K10: =WATER!AJ14 -> 59 | L10: =ELEC!B11 -> 39.997
A11: Beirut | B11: =B10+1 -> 10 | C11: 12 | D11: 2019 | E11: =ELEC!M12 -> 3872 | F11: =ELEC!K12 -> 2888 | G11: =ELEC!I12 -> 2722 | H11: =ELEC!E12 -> 3728 | I11: =ELEC!G12 -> 2255 | J11: =WATER!Y15 -> 19 | K11: =WATER!AJ15 -> 10 | L11: =ELEC!B12 -> 43.01
A12: Beirut | B12: =B11+1 -> 11 | C12: 12 | D12: 2019 | E12: =ELEC!M13 -> 3464 | F12: =ELEC!K13 -> 2582 | G12: =ELEC!I13 -> 2336 | H12: =ELEC!E13 -> 3320 | I12: =ELEC!G13 -> 2175 | J12: =WATER!Y16 -> 130 | K12: =WATER!AJ16 -> 75 | L12: =ELEC!B13 -> 35.995
A13: Beirut | B13: =B12+1 -> 12 | C13: 12 | D13: 2019 | E13: =ELEC!M14 -> 4710 | F13: =ELEC!K14 -> 1540 | G13: =ELEC!I14 -> 2592 | H13: =ELEC!E14 -> 3472 | I13: =ELEC!G14 -> 2281 | J13: =WATER!Y17 -> 0 | K13: =WATER!AJ17 -> 0 | L13: =ELEC!B14 -> 50.002
A14: Beirut | B14: =B13+1 -> 13 | C14: 12 | D14: 2019 | E14: =ELEC!M15 -> 5078 | F14: =ELEC!K15 -> 1666 | G14: =ELEC!I15 -> 2620 | H14: =ELEC!E15 -> 3724 | I14: =ELEC!G15 -> 2281 | J14: =WATER!Y18 -> 100 | K14: =WATER!AJ18 -> 44 | L14: =ELEC!B15 -> 54.004
... A32: Beirut | B32: =B31+1 -> 31 | C32: 12 | D32: 2019 | E32: =ELEC!M33 -> 4076 | F32: =ELEC!K33 -> 3048 | G32: =ELEC!I33 -> 2804 | H32: =ELEC!E33 -> 3678 | I32: =ELEC!G33 -> 2479 | J32: =WATER!Y36 -> 114 | K32: =WATER!AJ36 -> 94 | L32: =ELEC!B33 -> 115

Sheet ELEC
A1: OOC | B1: Room OCC | D1: MDB3 | E1: MDB3/day | F1: EMDB2 | G1: EMDB2/day | H1: EMDB1 | I1: EMDB1/day | J1: MDB2 | K1: mdb2/day | L1: MDB1 | M1: MDB1/Day | N1: Total KWH | O1: KWH/Rooc | P1: Gen MHW | Q1: Gen/Day KWH | R1: EDL KWH | S1: CH1 RH | T1: RH | U1: C1h1 power | V1: CH1 Con KWH | W1: CH2 RH | X1: RH | Y1: Ch2 power | Z1: CH2 Con KWH | AA1: CH3 RH | AB1: RH | AC1: Ch3 power | AD1: CH3 Con KWH | AE1: RH total | AF1: KWH total | AG1: AVG chiller KW/Hr
A2: 0.1391 | B2: 0.1391 | C2: 43799 | D2: =[1]ELEC!D32 -> 31186772 | E2: =[1]ELEC!E32 -> 4138 | F2: =[1]ELEC!F32 -> 3359570.8 | G2: =[1]ELEC!G32 -> 1999.6 | H2: =[1]ELEC!H32 -> 17141916 | I2: =[1]ELEC!I32 -> 2298 | J2: =[1]ELEC!J32 -> 28164866 | K2: =[1]ELEC!K32 -> 2448 | ... AI2: =[1]ELEC!AI32 -> -49039346
A3: ='General information '!F6 -> 0.1565 | B3: =SUM(230*A3) -> 35.995 | C3: 43800 | D3: 31190222 | E3: =D3-D2 -> 3450 | F3: 3361583 | G3: =F3-F2 -> 2012.2 | H3: 17144134 | I3: =H3-H2 -> 2218 | J3: 28168076 | K3: =J3-J2 -> 3210 | L3: 22389572 | M3: =L3-L2 -> 3450 | N3: =M3+K3+I3+G3+E3 -> 14340.2 | O3: =IF(B3>0,N3/B3,0) -> 398.39422 | P3: 15138.832 | Q3: =(P3-P2)*1000 -> 2532 | R3: =+N3-Q3 -> 11808.2 | S3: 8243 | T3: =S3-S2 -> 0 | U3: 997154 | V3: =U3-U2 -> 0 | W3: 31722 | X3: =W3-W2 -> 9 | Y3: 602126 | Z3: =Y3-Y2 -> 1608 | AA3: 34785 | AB3: =AA3-AA2 -> 1 | AC3: 723032 | AD3: =AC3-AC2 -> 172 | AE3: =AB3+X3+T3 -> 10 | AF3: =V3+Z3+AD3 -> 1780 | AG3: =IF(AE3>0,AF3/AE3,0) -> 178
A4: ='General information '!F7 -> 0.1304 | B4: =SUM(230*A4) -> 29.992 | C4: 43801 | D4: 31194050 | E4: =D4-D3 -> 3828 | F4: 3363625 | G4: =F4-F3 -> 2042 | H4: 17146378 | I4: =H4-H3 -> 2244 | J4: 28170278 | K4: =J4-J3 -> 2202 | L4: 22394096 | M4: =L4-L3 -> 4524 | N4: =M4+K4+I4+G4+E4 -> 14840 | O4: =IF(B4>0,N4/B4,0) -> 494.79861 | P4: 15141 | Q4: =(P4-P3)*1000 -> 2168 | R4: =N4-Q4 -> 12672 | S4: 8243 | T4: =S4-S3 -> 0 | U4: 997154 | V4: =U4-U3 -> 0 | W4: 31726 | X4: =W4-W3 -> 4 | Y4: 602797 | Z4: =Y4-Y3 -> 671 | AA4: 34786 | AB4: =AA4-AA3 -> 1 | AC4: 723180 | AD4: =AC4-AC3 -> 148 | AE4: =AB4+X4+T4 -> 5 | AF4: =V4+Z4+AD4 -> 819 | AG4: =IF(AE4>0,AF4/AE4,0) -> 163.8
A5: ='General information '!F8 -> 0.1522 | B5: =SUM(230*A5) -> 35.006 | C5: 43802 | D5: 31198598 | E5: =D5-D4 -> 4548 | F5: 3365902 | G5: =F5-F4 -> 2277 | H5: 17148894 | I5: =H5-H4 -> 2516 | J5: 28171694 | K5: =J5-J4 -> 1416 | L5: 22398450 | M5: =L5-L4 -> 4354 | N5: =M5+K5+I5+G5+E5 -> 15111 | O5: =IF(B5>0,N5/B5,0) -> 431.66886 | P5: 15143 | Q5: =(P5-P4)*1000 -> 2000 | R5: =N5-Q5 -> 13111 | S5: 8250 | T5: =S5-S4 -> 7 | U5: 998610 | V5: =U5-U4 -> 1456 | W5: 31726 | X5: =W5-W4 -> 0 | Y5: 602797 | Z5: =Y5-Y4 -> 0 | AA5: 34790 | AB5: =AA5-AA4 -> 4 | AC5: 723951 | AD5: =AC5-AC4 -> 771 | AE5: =AB5+X5+T5 -> 11 | AF5: =V5+Z5+AD5 -> 2227 | AG5: =IF(AE5>0,AF5/AE5,0) -> 202.45455 | AI5: =R5-'EDl log'!B3 -> -49058311
A6: ='General information '!F9 -> 0.1783 | B6: =SUM(230*A6) -> 41.009 | C6: 43803 | D6: 31203246 | E6: =D6-D5 -> 4648 | F6: 3368211 | G6: =F6-F5 -> 2309 | H6: 17151544 | I6: =H6-H5 -> 2650 | J6: 28173926 | K6: =J6-J5 -> 2232 | L6: 22402350 | M6: =L6-L5 -> 3900 | N6: =M6+K6+I6+G6+E6 -> 15739 | O6: =IF(B6>0,N6/B6,0) -> 383.7938 | P6: 15145.572 | Q6: =(P6-P5)*1000 -> 2572 | R6: =N6-Q6 -> 13167 | S6: 8250 | T6: =S6-S5 -> 0 | U6: 998610 | V6: =U6-U5 -> 0 | W6: 31729 | X6: =W6-W5 -> 3 | Y6: 603353 | Z6: =Y6-Y5 -> 556 | AA6: 34794 | AB6: =AA6-AA5 -> 4 | AC6: 724812 | AD6: =AC6-AC5 -> 861 | AE6: =AB6+X6+T6 -> 7 | AF6: =V6+Z6+AD6 -> 1417 | AG6: =IF(AE6>0,AF6/AE6,0) -> 202.42857 | AI6: =R6-'EDl log'!B4 -> -49064334
A7: ='General information '!F10 -> 0.213 | B7: =SUM(230*A7) -> 48.99 | C7: 43804 | D7: 31207306 | E7: =D7-D6 -> 4060 | F7: 3370268 | G7: =F7-F6 -> 2057 | H7: 17153766 | I7: =H7-H6 -> 2222 | J7: 28175750 | K7: =J7-J6 -> 1824 | L7: 22405660 | M7: =L7-L6 -> 3310 | N7: =M7+K7+I7+G7+E7 -> 13473 | O7: =IF(B7>0,N7/B7,0) -> 275.01531 | P7: 15148.07 | Q7: =(P7-P6)*1000 -> 2498 | R7: =N7-Q24 -> 11459 | S7: 8251 | T7: =S7-S6 -> 1 | U7: 998851 | V7: =U7-U6 -> 241 | W7: 31731 | X7: =W7-W6 -> 2 | Y7: 603870 | Z7: =Y7-Y6 -> 517 | AA7: 34797 | AB7: =AA7-AA6 -> 3 | AC7: 725528 | AD7: =AC7-AC6 -> 716 | AE7: =AB7+X7+T7 -> 6 | AF7: =V7+Z7+AD7 -> 1474 | AG7: =IF(AE7>0,AF7/AE7,0) -> 245.66667 | AI7: =R7-'EDl log'!B5 -> -49072542
A8: ='General information '!F11 -> 0.178 | B8: =SUM(230*A8) -> 40.94 | C8: 43805 | D8: 31211026 | E8: =D8-D7 -> 3720 | F8: 3372528.4 | G8: =F8-F7 -> 2260.4 | H8: 17156270 | I8: =H8-H7 -> 2504 | J8: 28177830 | K8: =J8-J7 -> 2080 | L8: 22409106 | M8: =L8-L7 -> 3446 | N8: =M8+K8+I8+G8+E8 -> 14010.4 | O8: =IF(B8>0,N8/B8,0) -> 342.21788 | P8: 15151.126 | Q8: =(P8-P7)*1000 -> 3056 | R8: =N8-Q8 -> 10954.4 | S8: =S7 -> 8251 | T8: =S8-S7 -> 0 | U8: =U7 -> 998851 | V8: =U8-U7 -> 0 | W8: 31734 | X8: =W8-W7 -> 3 | Y8: 604422 | Z8: =Y8-Y7 -> 552 | AA8: 34800 | AB8: =AA8-AA7 -> 3 | AC8: 726031 | AD8: =AC8-AC7 -> 503 | AE8: =AB8+X8+T8 -> 6 | AF8: =V8+Z8+AD8 -> 1055 | AG8: =IF(AE8>0,AF8/AE8,0) -> 175.83333 | AI8: =R8-'EDl log'!B6 -> -49079680
A9: ='General information '!F12 -> 0.139 | B9: =SUM(230*A9) -> 31.97 | C9: 43806 | D9: 31214403 | E9: =D9-D8 -> 3377 | F9: 3374775 | G9: =F9-F8 -> 2246.6 | H9: 17158872 | I9: =H9-H8 -> 2602 | J9: 28180350 | K9: =J9-J8 -> 2520 | L9: 22413646 | M9: =L9-L8 -> 4540 | N9: =M9+K9+I9+G9+E9 -> 15285.6 | O9: =IF(B9>0,N9/B9,0) -> 478.12324 | P9: 15153 | Q9: =(P9-P8)*1000 -> 1874 | R9: =N9-Q9 -> 13411.6 | S9: 8256 | T9: =S9-S8 -> 5 | U9: 999625 | V9: =U9-U8 -> 774 | W9: 31740 | X9: =W9-W8 -> 6 | Y9: 605454 | Z9: =Y9-Y8 -> 1032 | AA9: =AA8 -> 34800 | AB9: =AA9-AA8 -> 0 | AC9: =AC8 -> 726031 | AD9: =AC9-AC8 -> 0 | AE9: =AB9+X9+T9 -> 11 | AF9: =V9+Z9+AD9 -> 1806 | AG9: =IF(AE9>0,AF9/AE9,0) -> 164.18182 | AI9: =R9-'EDl log'!B7 -> -49084228
A10: ='General information '!F13 -> 0.1622 | B10: =SUM(230*A10) -> 37.306 | C10: 43807 | D10: 31218658 | E10: =D10-D9 -> 4255 | F10: 3377270 | G10: =F10-F9 -> 2495 | H10: 17161670 | I10: =H10-H9 -> 2798 | J10: 28182054 | K10: =J10-J9 -> 1704 | L10: 22419058 | M10: =L10-L9 -> 5412 | N10: =M10+K10+I10+G10+E10 -> 16664 | O10: =IF(B10>0,N10/B10,0) -> 446.68418 | P10: 15155 | Q10: =(P10-P9)*1000 -> 2000 | R10: =N10-Q10 -> 14664 | S10: 8261 | T10: =S10-S9 -> 5 | U10: 1000550 | V10: =U10-U9 -> 925 | W10: =W9 -> 31740 | X10: =W10-W9 -> 0 | Y10: =Y9 -> 605454 | Z10: =Y10-Y9 -> 0 | AA10: =AA9 -> 34800 | AB10: =AA10-AA9 -> 0 | AC10: =AC9 -> 726031 | AD10: =AC10-AC9 -> 0 | AE10: =AB10+X10+T10 -> 5 | AF10: =V10+Z10+AD10 -> 925 | AG10: =IF(AE10>0,AF10/AE10,0) -> 185 | AI10: =R10-'EDl log'!B8 -> -49088646
A11: ='General information '!F14 -> 0.1739 | B11: =SUM(230*A11) -> 39.997 | C11: 43808 | D11: 31222718 | E11: =D11-D10 -> 4060 | F11: 3379339 | G11: =F11-F10 -> 2069 | H11: 17164100 | I11: =H11-H10 -> 2430 | J11: 28183810 | K11: =J11-J10 -> 1756 | L11: 22422258 | M11: =L11-L10 -> 3200 | N11: =M11+K11+I11+G11+E11 -> 13515 | O11: =IF(B11>0,N11/B11,0) -> 337.90034 | P11: 15157.742 | Q11: =(P11-P10)*1000 -> 2742 | R11: =N11-Q11 -> 10773 | S11: 8261 | T11: =S11-S10 -> 0 | U11: 1000550 | V11: =U11-U10 -> 0 | W11: 31741 | X11: =W11-W10 -> 1 | Y11: 605655 | Z11: =Y11-Y10 -> 201 | AA11: 34806 | AB11: =AA11-AA10 -> 6 | AC11: 727030 | AD11: =AC11-AC10 -> 999 | AE11: =AB11+X11+T11 -> 7 | AF11: =V11+Z11+AD11 -> 1200 | AG11: =IF(AE11>0,AF11/AE11,0) -> 171.42857 | AI11: =R11-'EDl log'!B9 -> -49098226
A12: ='General information '!F15 -> 0.187 | B12: =SUM(230*A12) -> 43.01 | C12: 43809 | D12: 31226446 | E12: =D12-D11 -> 3728 | F12: 3381594 | G12: =F12-F11 -> 2255 | H12: 17166822 | I12: =H12-H11 -> 2722 | J12: 28186698 | K12: =J12-J11 -> 2888 | L12: 22426130 | M12: =L12-L11 -> 3872 | N12: =M12+K12+I12+G12+E12 -> 15465 | O12: =IF(B12>0,N12/B12,0) -> 359.56754 | P12: 15159.75 | Q12: =(P12-P11)*1000 -> 2008 | R12: =N12-Q12 -> 13457 | S12: 8261 | T12: =S12-S11 -> 0 | U12: =U11 -> 1000550 | V12: =U12-U11 -> 0 | W12: 31747 | X12: =W12-W11 -> 6 | Y12: 606821 | Z12: =Y12-Y11 -> 1166 | AA12: 34807 | AB12: =AA12-AA11 -> 1 | AC12: 727218 | AD12: =AC12-AC11 -> 188 | AE12: =AB12+X12+T12 -> 7 | AF12: =V12+Z12+AD12 -> 1354 | AG12: =IF(AE12>0,AF12/AE12,0) -> 193.42857 | AI12: =R12-'EDl log'!B10 -> -49102351
A13: ='General information '!F16 -> 0.1565 | B13: =SUM(230*A13) -> 35.995 | C13: 43810 | D13: 31229766 | E13: =D13-D12 -> 3320 | F13: 3383769 | G13: =F13-F12 -> 2175 | H13: 17169158 | I13: =H13-H12 -> 2336 | J13: 28189280 | K13: =J13-J12 -> 2582 | L13: 22429594 | M13: =L13-L12 -> 3464 | N13: =M13+K13+I13+G13+E13 -> 13877 | O13: =IF(B13>0,N13/B13,0) -> 385.52577 | P13: 15162.092 | Q13: =(P13-P12)*1000 -> 2342 | R13: =N13-Q13 -> 11535 | S13: 8263 | T13: =S13-S12 -> 2 | U13: 1000939 | V13: =U13-U12 -> 389 | W13: 31754 | X13: =W13-W12 -> 7 | Y13: 608041 | Z13: =Y13-Y12 -> 1220 | AA13: 34807 | AB13: =AA13-AA12 -> 0 | AC13: 727224 | AD13: =AC13-AC12 -> 6 | AE13: =AB13+X13+T13 -> 9 | AF13: =V13+Z13+AD13 -> 1615 | AG13: =IF(AE13>0,AF13/AE13,0) -> 179.44444 | AI13: =R13-'EDl log'!B11 -> -49111708
A14: ='General information '!F17 -> 0.2174 | B14: =SUM(230*A14) -> 50.002 | C14: 43811 | D14: 31233238 | E14: =D14-D13 -> 3472 | F14: 3386050 | G14: =F14-F13 -> 2281 | H14: 17171750 | I14: =H14-H13 -> 2592 | J14: 28190820 | K14: =J14-J13 -> 1540 | L14: 22434304 | M14: =L14-L13 -> 4710 | N14: =M14+K14+I14+G14+E14 -> 14595 | O14: =IF(B14>0,N14/B14,0) -> 291.88832 | P14: 15164 | Q14: =(P14-P13)*1000 -> 1908 | R14: =N14-Q14 -> 12687 | S14: 8268 | T14: =S14-S13 -> 5 | U14: 1001888 | V14: =U14-U13 -> 949 | W14: =W13 -> 31754 | X14: =W14-W13 -> 0 | Y14: =Y13 -> 608041 | Z14: =Y14-Y13 -> 0 | AA14: 34807 | AB14: =AA14-AA13 -> 0 | AC14: 727224 | AD14: =AC14-AC13 -> 0 | AE14: =AB14+X14+T14 -> 5 | AF14: =V14+Z14+AD14 -> 949 | AG14: =IF(AE14>0,AF14/AE14,0) -> 189.8 | AI14: =R14-'EDl log'!B12 -> -49116423
A15: ='General information '!F18 -> 0.2348 | B15: =SUM(230*A15) -> 54.004 | C15: 43812 | D15: 31236962 | E15: =D15-D14 -> 3724 | F15: 3388331 | G15: =F15-F14 -> 2281 | H15: 17174370 | I15: =H15-H14 -> 2620 | J15: 28192486 | K15: =J15-J14 -> 1666 | L15: 22439382 | M15: =L15-L14 -> 5078 | N15: =M15+K15+I15+G15+E15 -> 15369 | O15: =IF(B15>0,N15/B15,0) -> 284.59003 | P15: 15167.365 | Q15: =(P15-P14)*1000 -> 3365 | R15: =N15-Q15 -> 12004 | S15: 8274 | T15: =S15-S14 -> 6 | U15: 1003357 | V15: =U15-U14 -> 1469 | W15: =W14 -> 31754 | X15: =W15-W14 -> 0 | Y15: =Y14 -> 608041 | Z15: =Y15-Y14 -> 0 | AA15: 34807 | AB15: =AA15-AA14 -> 0 | AC15: 727224 | AD15: =AC15-AC14 -> 0 | AE15: =AB15+X15+T15 -> 6 | AF15: =V15+Z15+AD15 -> 1469 | AG15: =IF(AE15>0,AF15/AE15,0) -> 244.83333 | AI15: =R15-'EDl log'!B13 -> -49124045
A16: ='General information '!F19 -> 0.1696 | B16: =SUM(230*A16) -> 39.008 | C16: 43813 | D16: 31241914 | E16: =D16-D15 -> 4952 | F16: 3390622 | G16: =F16-F15 -> 2291 | H16: 17176926 | I16: =H16-H15 -> 2556 | J16: 28194198 | K16: =J16-J15 -> 1712 | L16: 22443578 | M16: =L16-L15 -> 4196 | N16: =M16+K16+I16+G16+E16 -> 15707 | O16: =IF(B16>0,N16/B16,0) -> 402.66099 | P16: 15170 | Q16: =(P16-P15)*1000 -> 2635 | R16: =N16-Q16 -> 13072 | S16: 8276 | T16: =S16-S15 -> 2 | U16: 1003625 | V16: =U16-U15 -> 268 | W16: =W15 -> 31754 | X16: =W16-W15 -> 0 | Y16: =Y15 -> 608041 | Z16: =Y16-Y15 -> 0 | AA16: 34814 | AB16: =AA16-AA15 -> 7 | AC16: 728587 | AD16: =AC16-AC15 -> 1363 | AE16: =AB16+X16+T16 -> 9 | AF16: =V16+Z16+AD16 -> 1631 | AG16: =IF(AE16>0,AF16/AE16,0) -> 181.22222 | AI16: =R16-'EDl log'!B14 -> -49128902
A17: ='General information '!F20 -> 0.1652 | B17: =SUM(230*A17) -> 37.996 | C17: 43814 | D17: 31244638 | E17: =D17-D16 -> 2724 | F17: 3392505 | G17: =F17-F16 -> 1883 | H17: 17178990 | I17: =H17-H16 -> 2064 | J17: 28195700 | K17: =J17-J16 -> 1502 | L17: 22448270 | M17: =L17-L16 -> 4692 | N17: =M17+K17+I17+G17+E17 -> 12865 | O17: =IF(B17>0,N17/B17,0) -> 338.58827 | P17: 15173.151 | Q17: =(P17-P16)*1000 -> 3151 | R17: =N17-Q17 -> 9714 | S17: 8281 | T17: =S17-S16 -> 5 | U17: 1004738 | V17: =U17-U16 -> 1113 | W17: =W16 -> 31754 | X17: =W17-W16 -> 0 | Y17: =Y16 -> 608041 | Z17: =Y17-Y16 -> 0 | AA17: 34814 | AB17: =AA17-AA16 -> 0 | AC17: 728587 | AD17: =AC17-AC16 -> 0 | AE17: =AB17+X17+T17 -> 5 | AF17: =V17+Z17+AD17 -> 1113 | AG17: =IF(AE17>0,AF17/AE17,0) -> 222.6 | AI17: =R17-'EDl log'!B15 -> -49138374
A18: ='General information '!F21 -> 0.139 | B18: =SUM(230*A18) -> 31.97 | C18: 43815 | D18: 31248006 | E18: =D18-D17 -> 3368 | F18: 3394920 | G18: =F18-F17 -> 2415 | H18: 17181474 | I18: =H18-H17 -> 2484 | J18: 28197594 | K18: =J18-J17 -> 1894 | L18: 22453650 | M18: =L18-L17 -> 5380 | N18: =M18+K18+I18+G18+E18 -> 15541 | O18: =IF(B18>0,N18/B18,0) -> 486.11198 | P18: 15175 | Q18: =(P18-P17)*1000 -> 1849 | R18: =N18-Q18 -> 13692 | S18: 8289 | T18: =S18-S17 -> 8 | U18: 1006290 | V18: =U18-U17 -> 1552 | W18: =W17 -> 31754 | X18: =W18-W17 -> 0 | Y18: =Y17 -> 608041 | Z18: =Y18-Y17 -> 0 | AA18: 34815 | AB18: =AA18-AA17 -> 1 | AC18: 728865 | AD18: =AC18-AC17 -> 278 | AE18: =AB18+X18+T18 -> 9 | AF18: =V18+Z18+AD18 -> 1830 | AG18: =IF(AE18>0,AF18/AE18,0) -> 203.33333 | AI18: =R18-'EDl log'!B16 -> -49141112
A19: ='General information '!F22 -> 0.1522 | B19: =SUM(230*A19) -> 35.006 | C19: 43816 | D19: 31251974 | E19: =D19-D18 -> 3968 | F19: 3397263.6 | G19: =F19-F18 -> 2343.6 | H19: 17183904 | I19: =H19-H18 -> 2430 | J19: 28199448 | K19: =J19-J18 -> 1854 | L19: 22458564 | M19: =L19-L18 -> 4914 | N19: =M19+K19+I19+G19+E19 -> 15509.6 | O19: =IF(B19>0,N19/B19,0) -> 443.05548 | P19: 15178.213 | Q19: =(P19-P18)*1000 -> 3213 | R19: =N19-Q19 -> 12296.6 | S19: 8295 | T19: =S19-S18 -> 6 | U19: 1007268 | V19: =U19-U18 -> 978 | W19: 31756 | X19: =W19-W18 -> 2 | Y19: 608569 | Z19: =Y19-Y18 -> 528 | AA19: 34818 | AB19: =AA19-AA18 -> 3 | AC19: 729401 | AD19: =AC19-AC18 -> 536 | AE19: =AB19+X19+T19 -> 11 | AF19: =V19+Z19+AD19 -> 2042 | AG19: =IF(AE19>0,AF19/AE19,0) -> 185.63636 | AI19: =R19-'EDl log'!B17 -> -49148889
A20: ='General information '!F23 -> 0.1696 | B20: =SUM(230*A20) -> 39.008 | C20: 43817 | D20: 31256188 | E20: =D20-D19 -> 4214 | F20: 3399524 | G20: =F20-F19 -> 2260.4 | H20: 17186358 | I20: =H20-H19 -> 2454 | J20: 28201890 | K20: =J20-J19 -> 2442 | L20: 22462278 | M20: =L20-L19 -> 3714 | N20: =M20+K20+I20+G20+E20 -> 15084.4 | O20: =IF(B20>0,N20/B20,0) -> 386.70016 | P20: 15180.468 | Q20: =(P20-P19)*1000 -> 2255 | R20: =N20-Q20 -> 12829.4 | S20: 8295 | T20: =S20-S19 -> 0 | U20: 1007268 | V20: =U20-U19 -> 0 | W20: 31756 | X20: =W20-W19 -> 0 | Y20: 609395 | Z20: =Y20-Y19 -> 826 | AA20: 34822 | AB20: =AA20-AA19 -> 4 | AC20: 730176 | AD20: =AC20-AC19 -> 775 | AE20: =AB20+X20+T20 -> 4 | AF20: =V20+Z20+AD20 -> 1601 | AG20: =IF(AE20>0,AF20/AE20,0) -> 400.25 | AI20: =R20-'EDl log'!B18 -> -49153814
A21: ='General information '!F24 -> 0.1739 | B21: =SUM(230*A21) -> 39.997 | C21: 43818 | D21: 31260094 | E21: =D21-D20 -> 3906 | F21: 3401960 | G21: =F21-F20 -> 2436 | H21: 17189050 | I21: =H21-H20 -> 2692 | J21: 28204438 | K21: =J21-J20 -> 2548 | L21: 22466890 | M21: =L21-L20 -> 4612 | N21: =M21+K21+I21+G21+E21 -> 16194 | O21: =IF(B21>0,N21/B21,0) -> 404.88037 | P21: 15182.561 | Q21: =(P21-P20)*1000 -> 2093 | R21: =N21-Q21 -> 14101 | S21: 8299 | T21: =S21-S20 -> 4 | U21: 1007937 | V21: =U21-U20 -> 669 | W21: 31764 | X21: =W21-W20 -> 8 | Y21: 610237 | Z21: =Y21-Y20 -> 842 | AA21: 34823 | AB21: =AA21-AA20 -> 1 | AC21: 730342 | AD21: =AC21-AC20 -> 166 | AE21: =AB21+X21+T21 -> 13 | AF21: =V21+Z21+AD21 -> 1677 | AG21: =IF(AE21>0,AF21/AE21,0) -> 129 | AI21: =R21-'EDl log'!B19 -> -49159251
A22: ='General information '!F25 -> 0.2478 | B22: =SUM(230*A22) -> 56.994 | C22: 43819 | D22: 31264518 | E22: =D22-D21 -> 4424 | F22: 3404378 | G22: =F22-F21 -> 2418 | H22: 17191568 | I22: =H22-H21 -> 2518 | J22: 28207352 | K22: =J22-J21 -> 2914 | L22: 22470576 | M22: =L22-L21 -> 3686 | N22: =M22+K22+I22+G22+E22 -> 15960 | O22: =IF(B22>0,N22/B22,0) -> 280.02948 | P22: 15185.235 | Q22: =(P22-P21)*1000 -> 2674 | R22: =N22-Q22 -> 13286 | S22: 8299 | T22: =S22-S21 -> 0 | U22: =U21 -> 1007937 | V22: =U22-U21 -> 0 | W22: 31771 | X22: =W22-W21 -> 7 | Y22: 611383 | Z22: =Y22-Y21 -> 1146 | AA22: 34827 | AB22: =AA22-AA21 -> 4 | AC22: 731256 | AD22: =AC22-AC21 -> 914 | AE22: =AB22+X22+T22 -> 11 | AF22: =V22+Z22+AD22 -> 2060 | AG22: =IF(AE22>0,AF22/AE22,0) -> 187.27273 | AI22: =R22-'EDl log'!B20 -> -49166753
A23: ='General information '!F26 -> 0.1826 | B23: =SUM(230*A23) -> 41.998 | C23: 43820 | D23: 31267894 | E23: =D23-D22 -> 3376 | F23: 3406655.2 | G23: =F23-F22 -> 2277.2 | H23: 17194074 | I23: =H23-H22 -> 2506 | J23: 28209816 | K23: =J23-J22 -> 2464 | L23: 22474218 | M23: =L23-L22 -> 3642 | N23: =M23+K23+I23+G23+E23 -> 14265.2 | O23: =IF(B23>0,N23/B23,0) -> 339.66379 | P23: 15187.7 | Q23: =(P23-P22)*1000 -> 2465 | R23: =N23-Q23 -> 11800.2 | S23: 8300 | T23: =S23-S22 -> 1 | U23: 1008255 | V23: =U23-U22 -> 318 | W23: 31775 | X23: =W23-W22 -> 4 | Y23: 612256 | Z23: =Y23-Y22 -> 873 | AA23: 34828 | AB23: =AA23-AA22 -> 1 | AC23: 731481 | AD23: =AC23-AC22 -> 225 | AE23: =AB23+X23+T23 -> 6 | AF23: =V23+Z23+AD23 -> 1416 | AG23: =IF(AE23>0,AF23/AE23,0) -> 236 | AI23: =R23-'EDl log'!B21 -> -49174888
A24: ='General information '!F27 -> 0.2609 | B24: =SUM(230*A24) -> 60.007 | C24: 43821 | D24: 31272316 | E24: =D24-D23 -> 4422 | F24: 3409014 | G24: =F24-F23 -> 2358.8 | H24: 17196654 | I24: =H24-H23 -> 2580 | J24: 28211594 | K24: =J24-J23 -> 1778 | L24: 22478254 | M24: =L24-L23 -> 4036 | N24: =M24+K24+I24+G24+E24 -> 15174.8 | O24: =IF(B24>0,N24/B24,0) -> 252.88383 | P24: 15189.714 | Q24: =(P24-P23)*1000 -> 2014 | R24: =N24-Q24 -> 13160.8 | S24: 8301 | T24: =S24-S23 -> 1 | U24: 1008471 | V24: =U24-U23 -> 216 | W24: 31775 | X24: =W24-W23 -> 0 | Y24: 612256 | Z24: =Y24-Y23 -> 0 | AA24: 34833 | AB24: =AA24-AA23 -> 5 | AC24: 732546 | AD24: =AC24-AC23 -> 1065 | AE24: =AB24+X24+T24 -> 6 | AF24: =V24+Z24+AD24 -> 1281 | AG24: =IF(AE24>0,AF24/AE24,0) -> 213.5 | AI24: =R24-'EDl log'!B22 -> -49180843
A25: ='General information '!F28 -> 0.2565 | B25: =SUM(230*A25) -> 58.995 | C25: 43822 | D25: 31276616 | E25: =D25-D24 -> 4300 | F25: 3411391.2 | G25: =F25-F24 -> 2377.2 | H25: 17199264 | I25: =H25-H24 -> 2610 | J25: 28213838 | K25: =J25-J24 -> 2244 | L25: 22484236 | M25: =L25-L24 -> 5982 | N25: =M25+K25+I25+G25+E25 -> 17513.2 | O25: =IF(B25>0,N25/B25,0) -> 296.85906 | P25: 15193.016 | Q25: =(P25-P24)*1000 -> 3302 | R25: =N25-Q25 -> 14211.2 | S25: 8308 | T25: =S25-S24 -> 7 | U25: 1010079 | V25: =U25-U24 -> 1608 | W25: 31779 | X25: =W25-W24 -> 4 | Y25: 612978 | Z25: =Y25-Y24 -> 722 | AA25: 34834 | AB25: =AA25-AA24 -> 1 | AC25: 732838 | AD25: =AC25-AC24 -> 292 | AE25: =AB25+X25+T25 -> 12 | AF25: =V25+Z25+AD25 -> 2622 | AG25: =IF(AE25>0,AF25/AE25,0) -> 218.5 | AI25: =R25-'EDl log'!B23 -> -49186639
A26: ='General information '!F29 -> 0.2174 | B26: =SUM(230*A26) -> 50.002 | C26: 43823 | D26: 31280234 | E26: =D26-D25 -> 3618 | F26: 3413858 | G26: =F26-F25 -> 2466.8 | H26: 17201710 | I26: =H26-H25 -> 2446 | J26: 28215286 | K26: =J26-J25 -> 1448 | L26: 22489650 | M26: =L26-L25 -> 5414 | N26: =M26+K26+I26+G26+E26 -> 15392.8 | O26: =IF(B26>0,N26/B26,0) -> 307.84369 | P26: 15195 | Q26: =(P26-P25)*1000 -> 1984 | R26: =N26-Q26 -> 13408.8 | S26: 8315 | T26: =S26-S25 -> 7 | U26: 1011339 | V26: =U26-U25 -> 1260 | W26: =W25 -> 31779 | X26: =W26-W25 -> 0 | Y26: =Y25 -> 612978 | Z26: =Y26-Y25 -> 0 | AA26: =AA25 -> 34834 | AB26: =AA26-AA25 -> 0 | AC26: =AC25 -> 732838 | AD26: =AC26-AC25 -> 0 | AE26: =AB26+X26+T26 -> 7 | AF26: =V26+Z26+AD26 -> 1260 | AG26: =IF(AE26>0,AF26/AE26,0) -> 180 | AI26: =R26-'EDl log'!B24 -> -49193514
A27: ='General information '!F30 -> 0.2043 | B27: =SUM(230*A27) -> 46.989 | C27: 43824 | D27: 31283878 | E27: =D27-D26 -> 3644 | F27: 3416254 | G27: =F27-F26 -> 2396 | H27: 17204112 | I27: =H27-H26 -> 2402 | J27: 28216598 | K27: =J27-J26 -> 1312 | L27: 22493590 | M27: =L27-L26 -> 3940 | N27: =M27+K27+I27+G27+E27 -> 13694 | O27: =IF(B27>0,N27/B27,0) -> 291.42991 | P27: 15198 | Q27: =(P27-P26)*1000 -> 3000 | R27: =N27-Q27 -> 10694 | S27: 8315 | T27: =S27-S26 -> 0 | U27: 1011339 | V27: =U27-U26 -> 0 | W27: 31779 | X27: =W27-W26 -> 0 | Y27: 612978 | Z27: =Y27-Y26 -> 0 | AA27: 34840 | AB27: =AA27-AA26 -> 6 | AC27: 733811 | AD27: =AC27-AC26 -> 973 | AE27: =AB27+X27+T27 -> 6 | AF27: =V27+Z27+AD27 -> 973 | AG27: =IF(AE27>0,AF27/AE27,0) -> 162.16667 | AI27: =R27-'EDl log'!B25 -> -49203082
A28: ='General information '!F31 -> 0.2174 | B28: =SUM(230*A28) -> 50.002 | C28: 43825 | D28: 31286950 | E28: =D28-D27 -> 3072 | F28: 3418544 | G28: =F28-F27 -> 2290 | H28: 17206454 | I28: =H28-H27 -> 2342 | J28: 28218982 | K28: =J28-J27 -> 2384 | L28: 22497322 | M28: =L28-L27 -> 3732 | N28: =M28+K28+I28+G28+E28 -> 13820 | O28: =IF(B28>0,N28/B28,0) -> 276.38894 | P28: 15201.177 | Q28: =(P28-P27)*1000 -> 3177 | R28: =N28-Q28 -> 10643 | S28: 8315 | T28: =S28-S27 -> 0 | U28: 1011339 | V28: =U28-U27 -> 0 | W28: 31783 | X28: =W28-W27 -> 4 | Y28: 613817 | Z28: =Y28-Y27 -> 839 | AA28: 34840 | AB28: =AA28-AA27 -> 0 | AC28: 733811 | AD28: =AC28-AC27 -> 0 | AE28: =AB28+X28+T28 -> 4 | AF28: =V28+Z28+AD28 -> 839 | AG28: =IF(AE28>0,AF28/AE28,0) -> 209.75 | AI28: =R28-'EDl log'!B26 -> -49210466
A29: ='General information '!F32 -> 0.2913 | B29: =SUM(230*A29) -> 66.999 | C29: 43826 | D29: 31290742 | E29: =D29-D28 -> 3792 | F29: 3421098 | G29: =F29-F28 -> 2554 | H29: 17208996 | I29: =H29-H28 -> 2542 | J29: 28220566 | K29: =J29-J28 -> 1584 | L29: 22503438 | M29: =L29-L28 -> 6116 | N29: =M29+K29+I29+G29+E29 -> 16588 | O29: =IF(B29>0,N29/B29,0) -> 247.58578 | P29: 15205 | Q29: =(P29-P28)*1000 -> 3823 | R29: =N29-Q29 -> 12765 | S29: 8322 | T29: =S29-S28 -> 7 | U29: 1012777 | V29: =U29-U28 -> 1438 | W29: 31783 | X29: =W29-W28 -> 0 | Y29: =Y28 -> 613817 | Z29: =Y29-Y28 -> 0 | AA29: =AA28 -> 34840 | AB29: =AA29-AA28 -> 0 | AC29: =AC28 -> 733811 | AD29: =AC29-AC28 -> 0 | AE29: =AB29+X29+T29 -> 7 | AF29: =V29+Z29+AD29 -> 1438 | AG29: =IF(AE29>0,AF29/AE29,0) -> 205.42857 | AI29: =R29-'EDl log'!B27 -> -49214894
A30: ='General information '!F33 -> 0.2913 | B30: =SUM(230*A30) -> 66.999 | C30: 43827 | D30: 31294576 | E30: =D30-D29 -> 3834 | F30: 3423614 | G30: =F30-F29 -> 2516 | H30: 17211568 | I30: =H30-H29 -> 2572 | J30: 28222350 | K30: =J30-J29 -> 1784 | L30: 22508414 | M30: =L30-L29 -> 4976 | N30: =M30+K30+I30+G30+E30 -> 15682 | O30: =IF(B30>0,N30/B30,0) -> 234.06319 | P30: 15208 | Q30: =(P30-P29)*1000 -> 3000 | R30: =N30-Q30 -> 12682 | S30: 8325 | T30: =S30-S29 -> 3 | U30: 1013316 | V30: =U30-U29 -> 539 | W30: 31785 | X30: =W30-W29 -> 2 | Y30: 614104 | Z30: =Y30-Y29 -> 287 | AA30: 34844 | AB30: =AA30-AA29 -> 4 | AC30: 734373 | AD30: =AC30-AC29 -> 562 | AE30: =AB30+X30+T30 -> 9 | AF30: =V30+Z30+AD30 -> 1388 | AG30: =IF(AE30>0,AF30/AE30,0) -> 154.22222 | AI30: =R30-'EDl log'!B28 -> -49220756
A31: ='General information '!F34 -> 0.345 | B31: =SUM(230*A31) -> 79.35 | C31: 43828 | D31: 31299550 | E31: =D31-D30 -> 4974 | F31: 3426257 | G31: =F31-F30 -> 2643 | H31: 17214298 | I31: =H31-H30 -> 2730 | J31: 28224982 | K31: =J31-J30 -> 2632 | L31: 22513108 | M31: =L31-L30 -> 4694 | N31: =M31+K31+I31+G31+E31 -> 17673 | O31: =IF(B31>0,N31/B31,0) -> 222.72212 | P31: 15211.678 | Q31: =(P31-P30)*1000 -> 3678 | R31: =N31-Q31 -> 13995 | S31: 8325 | T31: =S31-S30 -> 0 | U31: 1013316 | V31: =U31-U30 -> 0 | W31: 31790 | X31: =W31-W30 -> 5 | Y31: 615043 | Z31: =Y31-Y30 -> 939 | AA31: 34848 | AB31: =AA31-AA30 -> 4 | AC31: 735114 | AD31: =AC31-AC30 -> 741 | AE31: =AB31+X31+T31 -> 9 | AF31: =V31+Z31+AD31 -> 1680 | AG31: =IF(AE31>0,AF31/AE31,0) -> 186.66667 | AI31: =R31-'EDl log'!B29 -> -49225048
A32: ='General information '!F35 -> 0.345 | B32: =SUM(230*A32) -> 79.35 | C32: 43829 | D32: 31304560 | E32: =D32-D31 -> 5010 | F32: 3428870 | G32: =F32-F31 -> 2613 | H32: 17217114 | I32: =H32-H31 -> 2816 | J32: 28227042 | K32: =J32-J31 -> 2060 | L32: 22518770 | M32: =L32-L31 -> 5662 | N32: =M32+K32+I32+G32+E32 -> 18161 | O32: =IF(B32>0,N32/B32,0) -> 228.87209 | P32: 15214.705 | Q32: =(P32-P31)*1000 -> 3027 | R32: =N32-Q32 -> 15134 | S32: 8334 | T32: =S32-S31 -> 9 | U32: 1014633 | V32: =U32-U31 -> 1317 | W32: 31790 | X32: =W32-W31 -> 0 | Y32: =Y31 -> 615043 | Z32: =Y32-Y31 -> 0 | AA32: 34851 | AB32: =AA32-AA31 -> 3 | AC32: 735699 | AD32: =AC32-AC31 -> 585 | AE32: =AB32+X32+T32 -> 12 | AF32: =V32+Z32+AD32 -> 1902 | AG32: =IF(AE32>0,AF32/AE32,0) -> 158.5 | AI32: =R32-'EDl log'!B30 -> -49230051
A33: ='General information '!F36 -> 0.5 | B33: =SUM(230*A33) -> 115 | C33: 43830 | D33: 31308238 | E33: =D33-D32 -> 3678 | F33: 3431349 | G33: =F33-F32 -> 2479 | H33: 17219918 | I33: =H33-H32 -> 2804 | J33: 28230090 | K33: =J33-J32 -> 3048 | L33: 22522846 | M33: =L33-L32 -> 4076 | N33: =M33+K33+I33+G33+E33 -> 16085 | O33: =IF(B33>0,N33/B33,0) -> 139.86957 | P33: 15218.2 | Q33: =(P33-P32)*1000 -> 3495 | R33: =N33-Q33 -> 12590 | S33: =S32 -> 8334 | T33: =S33-S32 -> 0 | U33: =U32 -> 1014633 | V33: =U33-U32 -> 0 | W33: 31800 | X33: =W33-W32 -> 10 | Y33: 616769 | Z33: =Y33-Y32 -> 1726 | AA33: =AA32 -> 34851 | AB33: =AA33-AA32 -> 0 | AC33: =AC32 -> 735699 | AD33: =AC33-AC32 -> 0 | AE33: =AB33+X33+T33 -> 10 | AF33: =V33+Z33+AD33 -> 1726 | AG33: =IF(AE33>0,AF33/AE33,0) -> 172.6 | AI33: =R33-'EDl log'!B31 -> -49239434

Sheet B5
F1: Boiler A | J1: =J36 -> 76.667478 | K1: Boiler B | P1: Boiler C | V1: Boiler | X1: SteamA | AC1: SteamB | AH1: Steam | AI1: Boiler & steam | AL1: Total Boiler Runing H | AM1: Total Steam Runing H | AN1: GAS1 % | AO1: GAS1/L | AP1: GAS2% | AQ1: Gas2/L | AR1: GAS3% | AS1: GAS3/L | AU1: Gas Cons | AV1: Delivery | AW1: Cost/L
B2: Level Tank Gen | C2: Level tank Boiler | D2: Daily Cons Bo. | E2: Boiler litter | F2: Boiler A | G2: Run Hr a | H2: Boiler A fuel | I2: Daily consumption | J2: AVG | K2: index Run H | L2: Run Hrb | M2: Boiler B Fuel | O2: Daily consumption | P2: Boiler C | S2: Run C | U2: Total RH | V2: Total Fuel | X2: SteamA | Y2: Run SA | Z2: Steam A Conter | AA2: Liters | AC2: SteamB | AD2: Run SteamB | AE2: Steam B Conter | AF2: SB Litters | AG2: Avg | AH2: Total Fuel | AI2: Total Fuel
S3: 0
A4: 43799 | B4: =[1]B5!B34 -> 217 | C4: =[1]B5!C34 -> 223 | D4: =[1]B5!D34 -> 3 | E4: =[1]B5!E34 -> 25.14 | F4: =[1]B5!F34 -> 1192 | G4: =[1]B5!G34 -> 2 | H4: =[1]B5!H34 -> 321489 | I4: =[1]B5!I34 -> 155 | ... AX4: =[1]B5!AX34 -> 0.7
A5: 43800 | B5: 214 | C5: 219 | D5: =C4-C5 -> 4 | E5: =D5*8.38 -> 33.52 | F5: 1192 | G5: =F5-F4 -> 0 | H5: 321489 | I5: =SUM(H5-H4) -> 0 | J5: 1 | K5: 1567 | L5: =K5-K4 -> 1 | M5: 114381 | N5: =M5-M4 -> 108 | O5: =SUM(L5*$J$1) -> 76.667478 | P5: 1410 | Q5: 122817 | R5: =Q5-Q4 -> 121 | S5: =SUM(P5-P4) -> 2 | T5: =SUM(S5*$T$2) -> 0 | U5: =SUM(G5+L5+S5) -> 3 | V5: =R5+N5+I5:I5 -> 229 | W5: =SUM(V5/U5) -> 76.333333 | X5: 2239 | Y5: =X5-X4 -> 0 | Z5: 126340 | AA5: =Z5-Z4 -> 0 | AB5: =SUM(Y5*$AB$2) -> 0 | AC5: 1688 | AD5: =AC5-AC4 -> 0 | AE5: 351848 | AF5: =AE5-AE4 -> 0 | AG5: =IF(AD5>0,AF5/AD5,0) -> 0 | AH5: =AF5+AA5 -> 0 | AI5: =SUM(AH5+V5) -> 229 | AJ5: =-tanks!AW6 -> 229 | AK5: =SUM(AJ5-AI5) -> 0 | AL5: =S5+L5+G5 -> 3 | AM5: =Y5+AD5 -> 0 | AN5: 78 | AO5: =(AN5/100)*3000 -> 2340 | AP5: 77 | AQ5: =(AP5/100)*3000 -> 2310 | AR5: 78 | AS5: =(AR5/100)*3000 -> 2340 | AT5: =SUM(AO5+AQ5+AS5) -> 6990 | AU5: =AT4-AT5+AV5 -> 60 | AX5: =IF(AV5>0,AW5,AX4) -> 0.7
A6: 43801 | B6: 210 | C6: 216 | D6: =C5-C6 -> 3 | E6: =D6*8.38 -> 25.14 | F6: 1194 | G6: =F6-F5 -> 2 | H6: 321606 | I6: =SUM(H6-H5) -> 117 | J6: =IF(G6>0,I6/G6,0) -> 58.5 | K6: 1567 | L6: =K6-K5 -> 0 | M6: 114381 | N6: =M6-M5 -> 0 | O6: =SUM(L6*$J$1) -> 0 | P6: 1411 | Q6: 122915 | R6: =Q6-Q5 -> 98 | S6: =SUM(P6-P5) -> 1 | T6: =SUM(S6*$T$2) -> 0 | U6: =SUM(G6+L6+S6) -> 3 | V6: =R6+N6+I6:I6 -> 215 | W6: =SUM(V6/U6) -> 71.666667 | X6: 2241 | Y6: =X6-X5 -> 2 | Z6: 126454 | AA6: =Z6-Z5 -> 114 | AB6: =SUM(Y6*$AB$2) -> 0 | AC6: 1688 | AD6: =AC6-AC5 -> 0 | AE6: =AE5 -> 351848 | AF6: =AE6-AE5 -> 0 | AG6: =IF(AD6>0,AF6/AD6,0) -> 0 | AH6: =AF6+AA6 -> 114 | AI6: =SUM(AH6+V6) -> 329 | AJ6: =-tanks!AW7 -> 329 | AK6: =SUM(AJ6-AI6) -> 0 | AL6: =S6+L6+G6 -> 3 | AM6: =Y6+AD6 -> 2 | AN6: 75 | AO6: =(AN6/100)*3000 -> 2250 | AP6: 75 | AQ6: =(AP6/100)*3000 -> 2250 | AR6: =AR5 -> 78 | AS6: =(AR6/100)*3000 -> 2340 | AT6: =SUM(AO6+AQ6+AS6) -> 6840 | AU6: =AT5-AT6+AV6 -> 150 | AX6: =IF(AV6>0,AW6,AX5) -> 0.7
A7: 43802 | B7: 205 | C7: 210 | D7: =C6-C7 -> 6 | E7: =D7*8.38 -> 50.28 | F7: 1196 | G7: =F7-F6 -> 2 | H7: 321743 | I7: =SUM(H7-H6) -> 137 | J7: =IF(G7>0,I7/G7,0) -> 68.5 | K7: 1568 | L7: =K7-K6 -> 1 | M7: 114414 | N7: =M7-M6 -> 33 | O7: 1 | P7: 1412 | Q7: 123007 | R7: =Q7-Q6 -> 92 | S7: =SUM(P7-P6) -> 1 | T7: =SUM(S7*$T$2) -> 0 | U7: =SUM(G7+L7+S7) -> 4 | V7: =R7+N7+I7:I7 -> 262 | W7: =SUM(V7/U7) -> 65.5 | X7: 2248 | Y7: =X7-X6 -> 7 | Z7: 126816 | AA7: =Z7-Z6 -> 362 | AB7: =SUM(Y7*$AB$2) -> 0 | AC7: 1688 | AD7: =AC7-AC6 -> 0 | AE7: 351848.7 | AF7: =AE7-AE6 -> 0.7 | AG7: =IF(AD7>0,AF7/AD7,0) -> 0 | AH7: =AF7+AA7 -> 362.7 | AI7: =SUM(AH7+V7) -> 624.7 | AJ7: =-tanks!AW8 -> 624.7 | AK7: =SUM(AJ7-AI7) -> 0 | AL7: =S7+L7+G7 -> 4 | AM7: =Y7+AD7 -> 7 | AN7: 75 | AO7: =(AN7/100)*3000 -> 2250 | AP7: 75 | AQ7: =(AP7/100)*3000 -> 2250 | AR7: 75 | AS7: =(AR7/100)*3000 -> 2250 | AT7: =SUM(AO7+AQ7+AS7) -> 6750 | AU7: =AT6-AT7+AV7 -> 90 | AX7: =IF(AV7>0,AW7,AX6) -> 0.7
A8: 43803 | B8: 201 | C8: 207 | D8: =C7-C8 -> 3 | E8: =D8*8.38 -> 25.14 | F8: 1199 | G8: =F8-F7 -> 3 | H8: 321991 | I8: =SUM(H8-H7) -> 248 | J8: =IF(G8>0,I8/G8,0) -> 82.666667 | K8: 1568 | L8: =K8-K7 -> 0 | M8: 114414 | N8: =M8-M7 -> 0 | O8: =SUM(L8*$J$1) -> 0 | P8: 1414 | Q8: 123208 | R8: =Q8-Q7 -> 201 | S8: =SUM(P8-P7) -> 2 | T8: =SUM(S8*$T$2) -> 0 | U8: =SUM(G8+L8+S8) -> 5 | V8: =R8+N8+I8:I8 -> 449 | W8: =SUM(V8/U8) -> 89.8 | X8: 2248 | Y8: =X8-X7 -> 0 | Z8: 126816.9 | AA8: =Z8-Z7 -> 0.9 | AB8: =SUM(Y8*$AB$2) -> 0 | AC8: 1688 | AD8: =AC8-AC7 -> 0 | AE8: 351848.7 | AF8: =AE8-AE7 -> 0 | AG8: =IF(AD8>0,AF8/AD8,0) -> 0 | AH8: =AF8+AA8 -> 0.9 | AI8: =SUM(AH8+V8) -> 449.9 | AJ8: =-tanks!AW9 -> 449.9 | AK8: =SUM(AJ8-AI8) -> 0 | AL8: =S8+L8+G8 -> 5 | AM8: =Y8+AD8 -> 0 | AN8: 71 | AO8: =(AN8/100)*3000 -> 2130 | AP8: 71 | AQ8: =(AP8/100)*3000 -> 2130 | AR8: 72 | AS8: =(AR8/100)*3000 -> 2160 | AT8: =SUM(AO8+AQ8+AS8) -> 6420 | AU8: =AT7-AT8+AV8 -> 330 | AX8: =IF(AV8>0,AW8,AX7) -> 0.7
A9: 43804 | B9: 196 | C9: 202 | D9: =C8-C9 -> 5 | E9: =D9*8.38 -> 41.9 | F9: 1200 | G9: =F9-F8 -> 1 | H9: 322096 | I9: =SUM(H9-H8) -> 105 | J9: =IF(G9>0,I9/G9,0) -> 105 | K9: 1574 | L9: =K9-K8 -> 6 | M9: 114807 | N9: =M9-M8 -> 393 | O9: =SUM(L9*$J$1) -> 460.00487 | P9: 1414 | Q9: 123208 | R9: =Q9-Q8 -> 0 | S9: =SUM(P9-P8) -> 0 | T9: =SUM(S9*$T$2) -> 0 | U9: =SUM(G9+L9+S9) -> 7 | V9: =R9+N9+I9:I9 -> 498 | W9: =SUM(V9/U9) -> 71.142857 | X9: 2248 | Y9: =X9-X8 -> 0 | Z9: =Z8 -> 126816.9 | AA9: =Z9-Z8 -> 0 | AB9: =SUM(Y9*$AB$2) -> 0 | AC9: 1688 | AD9: =AC9-AC8 -> 0 | AE9: 351848.7 | AF9: =AE9-AE8 -> 0 | AG9: =IF(AD9>0,AF9/AD9,0) -> 0 | AH9: =AF9+AA9 -> 0 | AI9: =SUM(AH9+V9) -> 498 | AJ9: =-tanks!AW10 -> 498 | AK9: =SUM(AJ9-AI9) -> 0 | AL9: =S9+L9+G9 -> 7 | AM9: =Y9+AD9 -> 0 | AN9: 80 | AO9: =(AN9/100)*3000 -> 2400 | AP9: 80 | AQ9: =(AP9/100)*3000 -> 2400 | AR9: 80 | AS9: =(AR9/100)*3000 -> 2400 | AT9: =SUM(AO9+AQ9+AS9) -> 7200 | AU9: =AT8-AT9+AV9 -> 320 | AV9: 1100 | AW9: 0.7 | AX9: =IF(AV9>0,AW9,AX8) -> 0.7
A10: 43805 | B10: 190 | C10: 196 | D10: =C9-C10 -> 6 | E10: =D10*8.38 -> 50.28 | F10: =F9 -> 1200 | G10: =F10-F9 -> 0 | H10: =H9 -> 322096 | I10: =SUM(H10-H9) -> 0 | J10: =IF(G10>0,I10/G10,0) -> 0 | K10: 1578 | L10: =K10-K9 -> 4 | M10: 115056 | N10: =M10-M9 -> 249 | O10: =SUM(L10*$J$1) -> 306.66991 | P10: 1417 | Q10: 123458 | R10: =Q10-Q9 -> 250 | S10: =SUM(P10-P9) -> 3 | T10: =SUM(S10*$T$2) -> 0 | U10: =SUM(G10+L10+S10) -> 7 | V10: =R10+N10+I10:I10 -> 499 | W10: =SUM(V10/U10) -> 71.285714 | X10: 2252 | Y10: =X10-X9 -> 4 | Z10: 127023.7 | AA10: =Z10-Z9 -> 206.8 | AB10: =SUM(Y10*$AB$2) -> 0 | AC10: =AC9 -> 1688 | AD10: =AC10-AC9 -> 0 | AE10: =AE9 -> 351848.7 | AF10: =AE10-AE9 -> 0 | AG10: =IF(AD10>0,AF10/AD10,0) -> 0 | AH10: =AF10+AA10 -> 206.8 | AI10: =SUM(AH10+V10) -> 705.8 | AJ10: =-tanks!AW11 -> 705.8 | AK10: =SUM(AJ10-AI10) -> 0 | AL10: =S10+L10+G10 -> 7 | AM10: =Y10+AD10 -> 4 | AN10: =AN9 -> 80 | AO10: =(AN10/100)*3000 -> 2400 | AP10: 79 | AQ10: =(AP10/100)*3000 -> 2370 | AR10: =AR9 -> 80 | AS10: =(AR10/100)*3000 -> 2400 | AT10: =SUM(AO10+AQ10+AS10) -> 7170 | AU10: =AT9-AT10+AV10 -> 30 | AX10: =IF(AV10>0,AW10,AX9) -> 0.7
A11: 43806 | B11: 184 | C11: 190 | D11: =C10-C11 -> 6 | E11: =D11*8.38 -> 50.28 | F11: 1203 | G11: =F11-F10 -> 3 | H11: 322362 | I11: =SUM(H11-H10) -> 266 | J11: =IF(G11>0,I11/G11,0) -> 88.666667 | K11: 1578 | L11: =K11-K10 -> 0 | M11: =M10 -> 115056 | N11: =M11-M10 -> 0 | O11: =SUM(L11*$J$1) -> 0 | P11: 1421 | Q11: 123775 | R11: =Q11-Q10 -> 317 | S11: =SUM(P11-P10) -> 4 | T11: =SUM(S11*$T$2) -> 0 | U11: =SUM(G11+L11+S11) -> 7 | V11: =R11+N11+I11:I11 -> 583 | W11: =SUM(V11/U11) -> 83.285714 | X11: 2259 | Y11: =X11-X10 -> 7 | Z11: 127401 | AA11: =Z11-Z10 -> 377.3 | AB11: =SUM(Y11*$AB$2) -> 0 | AC11: =AC10 -> 1688 | AD11: =AC11-AC10 -> 0 | AE11: =AE10 -> 351848.7 | AF11: =AE11-AE10 -> 0 | AG11: =IF(AD11>0,AF11/AD11,0) -> 0 | AH11: =AF11+AA11 -> 377.3 | AI11: =SUM(AH11+V11) -> 960.3 | AJ11: =-tanks!AW12 -> 960.3 | AK11: =SUM(AJ11-AI11) -> 0 | AL11: =S11+L11+G11 -> 7 | AM11: =Y11+AD11 -> 7 | AN11: 79 | AO11: =(AN11/100)*3000 -> 2370 | AP11: 78 | AQ11: =(AP11/100)*3000 -> 2340 | AR11: 79 | AS11: =(AR11/100)*3000 -> 2370 | AT11: =SUM(AO11+AQ11+AS11) -> 7080 | AU11: =AT10-AT11+AV11 -> 90 | AX11: =IF(AV11>0,AW11,AX10) -> 0.7
A12: 43807 | B12: 180 | C12: 186 | D12: =C11-C12 -> 4 | E12: =D12*8.38 -> 33.52 | F12: 1208 | G12: =F12-F11 -> 5 | H12: 322713 | I12: =SUM(H12-H11) -> 351 | J12: =IF(G12>0,I12/G12,0) -> 70.2 | K12: 1582 | L12: =K12-K11 -> 4 | M12: 115313 | N12: =M12-M11 -> 257 | O12: =SUM(L12*$J$1) -> 306.66991 | P12: 1422 | Q12: 123809 | R12: =Q12-Q11 -> 34 | S12: =SUM(P12-P11) -> 1 | T12: =SUM(S12*$T$2) -> 0 | U12: =SUM(G12+L12+S12) -> 10 | V12: =R12+N12+I12:I12 -> 642 | W12: =SUM(V12/U12) -> 64.2 | X12: =X11 -> 2259 | Y12: =X12-X11 -> 0 | Z12: =Z11 -> 127401 | AA12: =Z12-Z11 -> 0 | AB12: =SUM(Y12*$AB$2) -> 0 | AC12: =AC11 -> 1688 | AD12: =AC12-AC11 -> 0 | AE12: =AE11 -> 351848.7 | AF12: =AE12-AE11 -> 0 | AG12: =IF(AD12>0,AF12/AD12,0) -> 0 | AH12: =AF12+AA12 -> 0 | AI12: =SUM(AH12+V12) -> 642 | AJ12: =-tanks!AW13 -> 642 | AK12: =SUM(AJ12-AI12) -> 0 | AL12: =S12+L12+G12 -> 10 | AM12: =Y12+AD12 -> 0 | AN12: =AN11 -> 79 | AO12: =(AN12/100)*3000 -> 2370 | AP12: =AP11 -> 78 | AQ12: =(AP12/100)*3000 -> 2340 | AR12: =AR11 -> 79 | AS12: =(AR12/100)*3000 -> 2370 | AT12: =SUM(AO12+AQ12+AS12) -> 7080 | AU12: =AT11-AT12+AV12 -> 0 | AX12: =IF(AV12>0,AW12,AX11) -> 0.7
A13: 43808 | B13: 175 | C13: 181 | D13: =C12-C13 -> 5 | E13: =D13*8.38 -> 41.9 | F13: 1208 | G13: =F13-F12 -> 0 | H13: 322713 | I13: =SUM(H13-H12) -> 0 | J13: =IF(G13>0,I13/G13,0) -> 0 | K13: 1588 | L13: =K13-K12 -> 6 | M13: 115663 | N13: =M13-M12 -> 350 | O13: =SUM(L13*$J$1) -> 460.00487 | P13: 1425 | Q13: 124083 | R13: =Q13-Q12 -> 274 | S13: =SUM(P13-P12) -> 3 | T13: =SUM(S13*$T$2) -> 0 | U13: =SUM(G13+L13+S13) -> 9 | V13: =R13+N13+I13:I13 -> 624 | W13: =SUM(V13/U13) -> 69.333333 | X13: 2259 | Y13: =X13-X12 -> 0 | Z13: 127401 | AA13: =Z13-Z12 -> 0 | AB13: =SUM(Y13*$AB$2) -> 0 | AC13: 1688 | AD13: =AC13-AC12 -> 0 | AE13: 351848.7 | AF13: =AE13-AE12 -> 0 | AG13: =IF(AD13>0,AF13/AD13,0) -> 0 | AH13: =AF13+AA13 -> 0 | AI13: =SUM(AH13+V13) -> 624 | AJ13: =-tanks!AW14 -> 624 | AK13: =SUM(AJ13-AI13) -> 0 | AL13: =S13+L13+G13 -> 9 | AM13: =Y13+AD13 -> 0 | AN13: 74 | AO13: =(AN13/100)*3000 -> 2220 | AP13: 74 | AQ13: =(AP13/100)*3000 -> 2220 | AR13: 75 | AS13: =(AR13/100)*3000 -> 2250 | AT13: =SUM(AO13+AQ13+AS13) -> 6690 | AU13: =AT12-AT13+AV13 -> 390 | AX13: =IF(AV13>0,AW13,AX12) -> 0.7
A14: 43809 | B14: 170 | C14: 176 | D14: =C13-C14 -> 5 | E14: =D14*8.38 -> 41.9 | F14: 1211 | G14: =F14-F13 -> 3 | H14: 322970 | I14: =SUM(H14-H13) -> 257 | J14: =IF(G14>0,I14/G14,0) -> 85.666667 | K14: 1588 | L14: =K14-K13 -> 0 | M14: =M13 -> 115663 | N14: =M14-M13 -> 0 | O14: =SUM(L14*$J$1) -> 0 | P14: 1430 | Q14: 124498 | R14: =Q14-Q13 -> 415 | S14: =SUM(P14-P13) -> 5 | T14: =SUM(S14*$T$2) -> 0 | U14: =SUM(G14+L14+S14) -> 8 | V14: =R14+N14+I14:I14 -> 672 | W14: =SUM(V14/U14) -> 84 | X14: 2261 | Y14: =X14-X13 -> 2 | Z14: 127491.2 | AA14: =Z14-Z13 -> 90.2 | AB14: =SUM(Y14*$AB$2) -> 0 | AC14: 1688 | AD14: =AC14-AC13 -> 0 | AE14: 351848.7 | AF14: =AE14-AE13 -> 0 | AG14: =IF(AD14>0,AF14/AD14,0) -> 0 | AH14: =AF14+AA14 -> 90.2 | AI14: =SUM(AH14+V14) -> 762.2 | AJ14: =-tanks!AW15 -> 762.2 | AK14: =SUM(AJ14-AI14) -> 0 | AL14: =S14+L14+G14 -> 8 | AM14: =Y14+AD14 -> 2 | AN14: 72 | AO14: =(AN14/100)*3000 -> 2160 | AP14: 72 | AQ14: =(AP14/100)*3000 -> 2160 | AR14: 74 | AS14: =(AR14/100)*3000 -> 2220 | AT14: =SUM(AO14+AQ14+AS14) -> 6540 | AU14: =AT13-AT14+AV14 -> 150 | AX14: =IF(AV14>0,AW14,AX13) -> 0.7
A15: 43810 | B15: 164 | C15: 170 | D15: =C14-C15 -> 6 | E15: =D15*8.38 -> 50.28 | F15: 1215 | G15: =F15-F14 -> 4 | H15: 323283 | I15: =SUM(H15-H14) -> 313 | J15: =IF(G15>0,I15/G15,0) -> 78.25 | K15: 1590 | L15: =K15-K14 -> 2 | M15: 115777 | N15: =M15-M14 -> 114 | O15: =SUM(L15*$J$1) -> 153.33496 | P15: 1430 | Q15: 124499 | R15: =Q15-Q14 -> 1 | S15: =SUM(P15-P14) -> 0 | T15: =SUM(S15*$T$2) -> 0 | U15: =SUM(G15+L15+S15) -> 6 | V15: =R15+N15+I15:I15 -> 428 | W15: =SUM(V15/U15) -> 71.333333 | X15: 2269 | Y15: =X15-X14 -> 8 | Z15: 127901.4 | AA15: =Z15-Z14 -> 410.2 | AB15: =SUM(Y15*$AB$2) -> 0 | AC15: 1688 | AD15: =AC15-AC14 -> 0 | AE15: 351848.7 | AF15: =AE15-AE14 -> 0 | AG15: =IF(AD15>0,AF15/AD15,0) -> 0 | AH15: =AF15+AA15 -> 410.2 | AI15: =SUM(AH15+V15) -> 838.2 | AJ15: =-tanks!AW16 -> 838.2 | AK15: =SUM(AJ15-AI15) -> 0 | AL15: =S15+L15+G15 -> 6 | AM15: =Y15+AD15 -> 8 | AN15: 70 | AO15: =(AN15/100)*3000 -> 2100 | AP15: 70 | AQ15: =(AP15/100)*3000 -> 2100 | AR15: 72 | AS15: =(AR15/100)*3000 -> 2160 | AT15: =SUM(AO15+AQ15+AS15) -> 6360 | AU15: =AT14-AT15+AV15 -> 180 | AX15: =IF(AV15>0,AW15,AX14) -> 0.7
A16: 43811 | B16: 202 | C16: 208 | D16: =C15-C16 -> -38 | E16: =D16*8.38 -> -318.44 | F16: 1215 | G16: =F16-F15 -> 0 | H16: 323283 | I16: =SUM(H16-H15) -> 0 | J16: =IF(G16>0,I16/G16,0) -> 0 | K16: 1595 | L16: =K16-K15 -> 5 | M16: 116112 | N16: =M16-M15 -> 335 | O16: =SUM(L16*$J$1) -> 383.33739 | P16: 1434 | Q16: 124825 | R16: =Q16-Q15 -> 326 | S16: =SUM(P16-P15) -> 4 | T16: =SUM(S16*$T$2) -> 0 | U16: =SUM(G16+L16+S16) -> 9 | V16: =R16+N16+I16:I16 -> 661 | W16: =SUM(V16/U16) -> 73.444444 | X16: 2269 | Y16: =X16-X15 -> 0 | Z16: =Z15 -> 127901.4 | AA16: =Z16-Z15 -> 0 | AB16: =SUM(Y16*$AB$2) -> 0 | AC16: 1688 | AD16: =AC16-AC15 -> 0 | AE16: =AE15 -> 351848.7 | AF16: =AE16-AE15 -> 0 | AG16: =IF(AD16>0,AF16/AD16,0) -> 0 | AH16: =AF16+AA16 -> 0 | AI16: =SUM(AH16+V16) -> 661 | AJ16: =-tanks!AW17 -> 661 | AK16: =SUM(AJ16-AI16) -> 0 | AL16: =S16+L16+G16 -> 9 | AM16: =Y16+AD16 -> 0 | AN16: 78 | AO16: =(AN16/100)*3000 -> 2340 | AP16: 78 | AQ16: =(AP16/100)*3000 -> 2340 | AR16: 82 | AS16: =(AR16/100)*3000 -> 2460 | AT16: =SUM(AO16+AQ16+AS16) -> 7140 | AU16: =AT15-AT16+AV16 -> 320 | AV16: 1100 | AW16: 0.7 | AX16: =IF(AV16>0,AW16,AX15) -> 0.7
A17: 43812 | B17: 196 | C17: 203 | D17: =C16-C17 -> 5 | E17: =D17*8.38 -> 41.9 | F17: 1220 | G17: =F17-F16 -> 5 | H17: 323679 | I17: =SUM(H17-H16) -> 396 | J17: =IF(G17>0,I17/G17,0) -> 79.2 | K17: 1595 | L17: =K17-K16 -> 0 | M17: 116112 | N17: =M17-M16 -> 0 | O17: =SUM(L17*$J$1) -> 0 | P17: 1440 | Q17: 125296 | R17: =Q17-Q16 -> 471 | S17: =SUM(P17-P16) -> 6 | T17: =SUM(S17*$T$2) -> 0 | U17: =SUM(G17+L17+S17) -> 11 | V17: =R17+N17+I17:I17 -> 867 | X17: 2269 | Y17: =X17-X16 -> 0 | Z17: 127901.4 | AA17: =Z17-Z16 -> 0 | AB17: =SUM(Y17*$AB$2) -> 0 | AC17: 1688 | AD17: =AC17-AC16 -> 0 | AE17: 351848.7 | AF17: =AE17-AE16 -> 0 | AG17: =IF(AD17>0,AF17/AD17,0) -> 0 | AH17: =AF17+AA17 -> 0 | AI17: =SUM(AH17+V17) -> 867 | AJ17: =-tanks!AW18 -> 867 | AK17: =SUM(AJ17-AI17) -> 0 | AL17: =S17+L17+G17 -> 11 | AM17: =Y17+AD17 -> 0 | AN17: 75 | AO17: =(AN17/100)*3000 -> 2250 | AP17: 75 | AQ17: =(AP17/100)*3000 -> 2250 | AR17: 79 | AS17: =(AR17/100)*3000 -> 2370 | AT17: =SUM(AO17+AQ17+AS17) -> 6870 | AU17: =AT16-AT17+AV17 -> 270 | AX17: =IF(AV17>0,AW17,AX16) -> 0.7
A18: 43813 | B18: 189 | C18: 195 | D18: =C17-C18 -> 8 | E18: =D18*8.38 -> 67.04 | F18: 1225 | G18: =F18-F17 -> 5 | H18: 324117 | I18: =SUM(H18-H17) -> 438 | J18: =IF(G18>0,I18/G18,0) -> 87.6 | K18: 1600 | L18: =K18-K17 -> 5 | M18: 116468 | N18: =M18-M17 -> 356 | O18: =SUM(L18*$J$1) -> 383.33739 | P18: =P17 -> 1440 | Q18: =Q17 -> 125296 | R18: =Q18-Q17 -> 0 | S18: =SUM(P18-P17) -> 0 | T18: =SUM(S18*$T$2) -> 0 | U18: =SUM(G18+L18+S18) -> 10 | V18: =R18+N18+I18:I18 -> 794 | X18: 2271 | Y18: =X18-X17 -> 2 | Z18: 128025.8 | AA18: =Z18-Z17 -> 124.4 | AB18: =SUM(Y18*$AB$2) -> 0 | AC18: =AC17 -> 1688 | AD18: =AC18-AC17 -> 0 | AE18: =AE17 -> 351848.7 | AF18: =AE18-AE17 -> 0 | AG18: =IF(AD18>0,AF18/AD18,0) -> 0 | AH18: =AF18+AA18 -> 124.4 | AI18: =SUM(AH18+V18) -> 918.4 | AJ18: =-tanks!AW19 -> 918.4 | AK18: =SUM(AJ18-AI18) -> 0 | AL18: =S18+L18+G18 -> 10 | AM18: =Y18+AD18 -> 2 | AN18: 74 | AO18: =(AN18/100)*3000 -> 2220 | AP18: 74 | AQ18: =(AP18/100)*3000 -> 2220 | AR18: 78 | AS18: =(AR18/100)*3000 -> 2340 | AT18: =SUM(AO18+AQ18+AS18) -> 6780 | AU18: =AT17-AT18+AV18 -> 90 | AX18: =IF(AV18>0,AW18,AX17) -> 0.7
A19: 43814 | B19: 183 | C19: 189 | D19: =C18-C19 -> 6 | E19: =D19*8.38 -> 50.28 | F19: 1225 | G19: =F19-F18 -> 0 | H19: 324117 | I19: =SUM(H19-H18) -> 0 | J19: =IF(G19>0,I19/G19,0) -> 0 | K19: 1605 | L19: =K19-K18 -> 5 | M19: 116836 | N19: =M19-M18 -> 368 | O19: =SUM(L19*$J$1) -> 383.33739 | P19: 1445 | Q19: 125686 | R19: =Q19-Q18 -> 390 | S19: =SUM(P19-P18) -> 5 | T19: =SUM(S19*$T$2) -> 0 | U19: =SUM(G19+L19+S19) -> 10 | V19: =R19+N19+I19:I19 -> 758 | X19: 2279 | Y19: =X19-X18 -> 8 | Z19: 128431.1 | AA19: =Z19-Z18 -> 405.3 | AB19: =SUM(Y19*$AB$2) -> 0 | AC19: 1688 | AD19: =AC19-AC18 -> 0 | AE19: 351848.7 | AF19: =AE19-AE18 -> 0 | AG19: =IF(AD19>0,AF19/AD19,0) -> 0 | AH19: =AF19+AA19 -> 405.3 | AI19: =SUM(AH19+V19) -> 1163.3 | AJ19: =-tanks!AW20 -> 1163.3 | AK19: =SUM(AJ19-AI19) -> 0 | AL19: =S19+L20+G19 -> 5 | AM19: =Y19+AD19 -> 8 | AN19: 72 | AO19: =(AN19/100)*3000 -> 2160 | AP19: 74 | AQ19: =(AP19/100)*3000 -> 2220 | AR19: 76 | AS19: =(AR19/100)*3000 -> 2280 | AT19: =SUM(AO19+AQ19+AS19) -> 6660 | AU19: =AT18-AT19+AV19 -> 120 | AX19: =IF(AV19>0,AW19,AX18) -> 0.7
A20: 43815 | B20: 177 | C20: 182 | D20: =C19-C20 -> 7 | E20: =D20*8.38 -> 58.66 | F20: 1231 | G20: =F20-F19 -> 6 | H20: 324528 | I20: =SUM(H20-H19) -> 411 | J20: =IF(G20>0,I20/G20,0) -> 68.5 | K20: =K19 -> 1605 | L20: =K20-K19 -> 0 | M20: =M19 -> 116836 | N20: =M20-M19 -> 0 | O20: =SUM(L20*$J$1) -> 0 | P20: 1450 | Q20: 126115 | R20: =Q20-Q19 -> 429 | S20: =SUM(P20-P19) -> 5 | T20: =SUM(S20*$T$2) -> 0 | U20: =SUM(G20+L20+S20) -> 11 | V20: =R20+N20+I20:I20 -> 840 | X20: =X19 -> 2279 | Y20: =X20-X19 -> 0 | Z20: =Z19 -> 128431.1 | AA20: =Z20-Z19 -> 0 | AB20: =SUM(Y20*$AB$2) -> 0 | AC20: =AC19 -> 1688 | AD20: =AC20-AC19 -> 0 | AE20: =AE19 -> 351848.7 | AF20: =AE20-AE19 -> 0 | AG20: =IF(AD20>0,AF20/AD20,0) -> 0 | AH20: =AF20+AA20 -> 0 | AI20: =SUM(AH20+V20) -> 840 | AJ20: =-tanks!AW21 -> 840 | AK20: =SUM(AJ20-AI20) -> 0 | AL20: =S20+L21+G20 -> 16 | AM20: =Y20+AD20 -> 0 | AN20: =AN19 -> 72 | AO20: =(AN20/100)*3000 -> 2160 | AP20: =AP19 -> 74 | AQ20: =(AP20/100)*3000 -> 2220 | AR20: =AR19 -> 76 | AS20: =(AR20/100)*3000 -> 2280 | AT20: =SUM(AO20+AQ20+AS20) -> 6660 | AU20: =AT19-AT20+AV20 -> 0 | AX20: =IF(AV20>0,AW20,AX19) -> 0.7
A21: 43816 | B21: 187 | C21: 193 | D21: =C20-C21 -> -11 | E21: =D21*8.38 -> -92.18 | F21: 1235 | G21: =F21-F20 -> 4 | H21: 324849 | I21: =SUM(H21-H20) -> 321 | J21: =IF(G21>0,I21/G21,0) -> 80.25 | K21: 1610 | L21: =K21-K20 -> 5 | M21: 117178 | N21: =M21-M20 -> 342 | O21: =SUM(L21*$J$1) -> 383.33739 | P21: 1452 | Q21: 126239 | R21: =Q21-Q20 -> 124 | S21: =SUM(P21-P20) -> 2 | T21: =SUM(S21*$T$2) -> 0 | U21: =SUM(G21+L21+S21) -> 11 | V21: =R21+N21+I21:I21 -> 787 | X21: 2279 | Y21: =X21-X20 -> 0 | Z21: 128431.1 | AA21: =Z21-Z20 -> 0 | AB21: =SUM(Y21*$AB$2) -> 0 | AC21: 1688 | AD21: =AC21-AC20 -> 0 | AE21: 351848.7 | AF21: =AE21-AE20 -> 0 | AG21: =IF(AD21>0,AF21/AD21,0) -> 0 | AH21: =AF21+AA21 -> 0 | AI21: =SUM(AH21+V21) -> 787 | AJ21: =-tanks!AW22 -> 787 | AK21: =SUM(AJ21-AI21) -> 0 | AL21: =S21+L21+G21 -> 11 | AM21: =Y21+AD21 -> 0 | AN21: 69 | AO21: =(AN21/100)*3000 -> 2070 | AP21: 70 | AQ21: =(AP21/100)*3000 -> 2100 | AR21: 71 | AS21: =(AR21/100)*3000 -> 2130 | AT21: =SUM(AO21+AQ21+AS21) -> 6300 | AU21: =AT20-AT21+AV21 -> 360 | AX21: =IF(AV21>0,AW21,AX20) -> 0.7
A22: 43817 | B22: 225 | C22: 229 | D22: =C21-C22 -> -36 | E22: =D22*8.38 -> -301.68 | F22: 1238 | G22: =F22-F21 -> 3 | H22: 325131 | I22: =SUM(H22-H21) -> 282 | J22: =IF(G22>0,I22/G22,0) -> 94 | K22: 1615 | L22: =K22-K21 -> 5 | M22: 117578 | N22: =M22-M21 -> 400 | O22: =SUM(L22*$J$1) -> 383.33739 | P22: 1452 | Q22: 126239 | R22: =Q22-Q21 -> 0 | S22: =SUM(P22-P21) -> 0 | T22: =SUM(S22*$T$2) -> 0 | U22: =SUM(G22+L22+S22) -> 8 | V22: =R22+N22+I22:I22 -> 682 | X22: 2281 | Y22: =X22-X21 -> 2 | Z22: 128565.7 | AA22: =Z22-Z21 -> 134.6 | AB22: =SUM(Y22*$AB$2) -> 0 | AC22: 1688 | AD22: =AC22-AC21 -> 0 | AE22: 351848.7 | AF22: =AE22-AE21 -> 0 | AG22: =IF(AD22>0,AF22/AD22,0) -> 0 | AH22: =AF22+AA22 -> 134.6 | AI22: =SUM(AH22+V22) -> 816.6 | AJ22: =-tanks!AW23 -> 816.6 | AK22: =SUM(AJ22-AI22) -> 0 | AL22: =S22+L22+G22 -> 8 | AM22: =Y22+AD22 -> 2 | AN22: 65 | AO22: =(AN22/100)*3000 -> 1950 | AP22: 67 | AQ22: =(AP22/100)*3000 -> 2010 | AR22: 69 | AS22: =(AR22/100)*3000 -> 2070 | AT22: =SUM(AO22+AQ22+AS22) -> 6030 | AU22: =AT21-AT22+AV22 -> 270 | AX22: =IF(AV22>0,AW22,AX21) -> 0.7
A23: 43818 | B23: 222 | C23: 207 | D23: =C22-C23 -> 22 | E23: =D23*8.38 -> 184.36 | F23: 1248 | G23: =F23-F22 -> 10 | H23: 325886 | I23: =SUM(H23-H22) -> 755 | J23: =IF(G23>0,I23/G23,0) -> 75.5 | K23: 1615 | L23: =K23-K22 -> 0 | M23: 117578 | N23: =M23-M22 -> 0 | O23: =SUM(L23*$J$1) -> 0 | P23: 1452 | Q23: 126239 | R23: =Q23-Q22 -> 0 | S23: =SUM(P23-P22) -> 0 | T23: =SUM(S23*$T$2) -> 0 | U23: =SUM(G23+L23+S23) -> 10 | V23: =R23+N23+I23:I23 -> 755 | X23: 2289 | Y23: =X23-X22 -> 8 | Z23: 128954.4 | AA23: =Z23-Z22 -> 388.7 | AB23: =SUM(Y23*$AB$2) -> 0 | AC23: 1688 | AD23: =AC23-AC22 -> 0 | AE23: 351848.7 | AF23: =AE23-AE22 -> 0 | AG23: =IF(AD23>0,AF23/AD23,0) -> 0 | AH23: =AF23+AA23 -> 388.7 | AI23: =SUM(AH23+V23) -> 1143.7 | AJ23: =-tanks!AW24 -> 1143.7 | AK23: =SUM(AJ23-AI23) -> 0 | AL23: =S23+L23+G23 -> 10 | AM23: =Y23+AD23 -> 8 | AN23: 80 | AO23: =(AN23/100)*3000 -> 2400 | AP23: 81 | AQ23: =(AP23/100)*3000 -> 2430 | AR23: 79 | AS23: =(AR23/100)*3000 -> 2370 | AT23: =SUM(AO23+AQ23+AS23) -> 7200 | AU23: =AT22-AT23+AV23 -> 330 | AV23: 1500 | AW23: 0.7 | AX23: =IF(AV23>0,AW23,AX22) -> 0.7
A24: 43819 | B24: 219 | C24: 193 | D24: =C23-C24 -> 14 | E24: =D24*8.38 -> 117.32 | F24: 1256 | G24: =F24-F23 -> 8 | H24: 326591 | I24: =SUM(H24-H23) -> 705 | J24: =IF(G24>0,I24/G24,0) -> 88.125 | K24: 1615 | L24: =K24-K23 -> 0 | M24: 117578 | N24: =M24-M23 -> 0 | O24: =SUM(L24*$J$1) -> 0 | P24: 1452 | Q24: 126239 | R24: =Q24-Q23 -> 0 | S24: =SUM(P24-P23) -> 0 | T24: =SUM(S24*$T$2) -> 0 | U24: =SUM(G24+L24+S24) -> 8 | V24: =R24+N24+I24:I24 -> 705 | X24: 2289 | Y24: =X24-X23 -> 0 | Z24: 128954.4 | AA24: =Z24-Z23 -> 0 | AB24: =SUM(Y24*$AB$2) -> 0 | AC24: 1688 | AD24: =AC24-AC23 -> 0 | AE24: 351848.7 | AF24: =AE24-AE23 -> 0 | AG24: =IF(AD24>0,AF24/AD24,0) -> 0 | AH24: =AF24+AA24 -> 0 | AI24: =SUM(AH24+V24) -> 705 | AJ24: =-tanks!AW25 -> 705 | AK24: =SUM(AJ24-AI24) -> 0 | AL24: =S24+L24+G24 -> 8 | AM24: =Y24+AD24 -> 0 | AN24: 79 | AO24: =(AN24/100)*3000 -> 2370 | AP24: 80 | AQ24: =(AP24/100)*3000 -> 2400 | AR24: 78 | AS24: =(AR24/100)*3000 -> 2340 | AT24: =SUM(AO24+AQ24+AS24) -> 7110 | AU24: =AT23-AT24+AV24 -> 90 | AX24: =IF(AV24>0,AW24,AX23) -> 0.7
A25: 43820 | B25: 216 | C25: 179 | D25: =C24-C25 -> 14 | E25: =D25*8.38 -> 117.32 | F25: 1267 | G25: =F25-F24 -> 11 | H25: 327405 | I25: =SUM(H25-H24) -> 814 | J25: =IF(G25>0,I25/G25,0) -> 74 | K25: =K24 -> 1615 | L25: =K25-K24 -> 0 | M25: =M24 -> 117578 | N25: =M25-M24 -> 0 | O25: =SUM(L25*$J$1) -> 0 | P25: =P24 -> 1452 | Q25: =Q24 -> 126239 | R25: =Q25-Q24 -> 0 | S25: =SUM(P25-P24) -> 0 | T25: =SUM(S25*$T$2) -> 0 | U25: =SUM(G25+L25+S25) -> 11 | V25: =R25+N25+I25:I25 -> 814 | X25: =X24 -> 2289 | Y25: =X25-X24 -> 0 | Z25: =Z24 -> 128954.4 | AA25: =Z25-Z24 -> 0 | AB25: =SUM(Y25*$AB$2) -> 0 | AC25: =AC24 -> 1688 | AD25: =AC25-AC24 -> 0 | AE25: =AE24 -> 351848.7 | AF25: =AE25-AE24 -> 0 | AG25: =IF(AD25>0,AF25/AD25,0) -> 0 | AH25: =AF25+AA25 -> 0 | AI25: =SUM(AH25+V25) -> 814 | AJ25: =-tanks!AW26 -> 814 | AK25: =SUM(AJ25-AI25) -> 0 | AL25: =S25+L25+G25 -> 11 | AM25: =Y25+AD25 -> 0 | AN25: =AN24 -> 79 | AO25: =(AN25/100)*3000 -> 2370 | AP25: 78 | AQ25: =(AP25/100)*3000 -> 2340 | AR25: 76 | AS25: =(AR25/100)*3000 -> 2280 | AT25: =SUM(AO25+AQ25+AS25) -> 6990 | AU25: =AT24-AT25+AV25 -> 120 | AX25: =IF(AV25>0,AW25,AX24) -> 0.7
A26: 43821 | B26: 213 | C26: 166 | D26: =C25-C26 -> 13 | E26: =D26*8.38 -> 108.94 | F26: 1274 | G26: =F26-F25 -> 7 | H26: 328001 | I26: =SUM(H26-H25) -> 596 | J26: =IF(G26>0,I26/G26,0) -> 85.142857 | K26: 1615 | L26: =K26-K25 -> 0 | M26: 117578 | N26: =M26-M25 -> 0 | O26: =SUM(L26*$J$1) -> 0 | P26: 1452 | Q26: 126239 | R26: =Q26-Q25 -> 0 | S26: =SUM(P26-P25) -> 0 | T26: =SUM(S26*$T$2) -> 0 | U26: =SUM(G26+L26+S26) -> 7 | V26: =R26+N26+I26:I26 -> 596 | X26: 2292 | Y26: =X26-X25 -> 3 | Z26: 129117 | AA26: =Z26-Z25 -> 162.6 | AB26: =SUM(Y26*$AB$2) -> 0 | AC26: 1688 | AD26: =AC26-AC25 -> 0 | AE26: 351848.7 | AF26: =AE26-AE25 -> 0 | AG26: =IF(AD26>0,AF26/AD26,0) -> 0 | AH26: =AF26+AA26 -> 162.6 | AI26: =SUM(AH26+V26) -> 758.6 | AJ26: =-tanks!AW27 -> 758.6 | AK26: =SUM(AJ26-AI26) -> 0 | AL26: =S26+L26+G26 -> 7 | AM26: =Y26+AD26 -> 3 | AN26: 73 | AO26: =(AN26/100)*3000 -> 2190 | AP26: 74 | AQ26: =(AP26/100)*3000 -> 2220 | AR26: 73 | AS26: =(AR26/100)*3000 -> 2190 | AT26: =SUM(AO26+AQ26+AS26) -> 6600 | AU26: =AT25-AT26+AV26 -> 390 | AX26: =IF(AV26>0,AW26,AX25) -> 0.7
A27: 43822 | B27: 209 | C27: 145 | D27: =C26-C27 -> 21 | E27: =D27*8.38 -> 175.98 | F27: 1283 | G27: =F27-F26 -> 9 | H27: 328697 | I27: =SUM(H27-H26) -> 696 | J27: =IF(G27>0,I27/G27,0) -> 77.333333 | K27: 1615 | L27: =K27-K26 -> 0 | M27: 117578 | N27: =M27-M26 -> 0 | O27: =SUM(L27*$J$1) -> 0 | P27: 1452 | Q27: 126239 | R27: =Q27-Q26 -> 0 | S27: =SUM(P27-P26) -> 0 | T27: =SUM(S27*$T$2) -> 0 | U27: =SUM(G27+L27+S27) -> 9 | V27: =R27+N27+I27:I27 -> 696 | X27: 2300 | Y27: =X27-X26 -> 8 | Z27: 129516.3 | AA27: =Z27-Z26 -> 399.3 | AB27: =SUM(Y27*$AB$2) -> 0 | AC27: 1688 | AD27: =AC27-AC26 -> 0 | AE27: 351848.7 | AF27: =AE27-AE26 -> 0 | AG27: =IF(AD27>0,AF27/AD27,0) -> 0 | AH27: =AF27+AA27 -> 399.3 | AI27: =SUM(AH27+V27) -> 1095.3 | AJ27: =-tanks!AW28 -> 1095.3 | AK27: =SUM(AJ27-AI27) -> 0 | AL27: =S27+L27+G27 -> 9 | AM27: =Y27+AD27 -> 8 | AN27: 70 | AO27: =(AN27/100)*3000 -> 2100 | AP27: 71 | AQ27: =(AP27/100)*3000 -> 2130 | AR27: 71 | AS27: =(AR27/100)*3000 -> 2130 | AT27: =SUM(AO27+AQ27+AS27) -> 6360 | AU27: =AT26-AT27+AV27 -> 240 | AX27: =IF(AV27>0,AW27,AX26) -> 0.7
A28: 43823 | B28: 206 | C28: 136 | D28: =C27-C28 -> 9 | E28: =D28*8.38 -> 75.42 | F28: 1289 | G28: =F28-F27 -> 6 | H28: 329163 | I28: =SUM(H28-H27) -> 466 | J28: =IF(G28>0,I28/G28,0) -> 77.666667 | K28: =K27 -> 1615 | L28: =K28-K27 -> 0 | M28: =M27 -> 117578 | N28: =M28-M27 -> 0 | O28: =SUM(L28*$J$1) -> 0 | P28: =P27 -> 1452 | Q28: =Q27 -> 126239 | R28: =Q28-Q27 -> 0 | S28: =SUM(P28-P27) -> 0 | T28: =SUM(S28*$T$2) -> 0 | U28: =SUM(G28+L28+S28) -> 6 | V28: =R28+N28+I28:I28 -> 466 | X28: 2301 | Y28: =X28-X27 -> 1 | Z28: 129598.3 | AA28: =Z28-Z27 -> 82 | AB28: =SUM(Y28*$AB$2) -> 0 | AC28: =AC27 -> 1688 | AD28: =AC28-AC27 -> 0 | AE28: =AE27 -> 351848.7 | AF28: =AE28-AE27 -> 0 | AG28: =IF(AD28>0,AF28/AD28,0) -> 0 | AH28: =AF28+AA28 -> 82 | AI28: =SUM(AH28+V28) -> 548 | AJ28: =-tanks!AW29 -> 548 | AK28: =SUM(AJ28-AI28) -> 0 | AL28: =S28+L28+G28 -> 6 | AM28: =Y28+AD28 -> 1 | AN28: 68 | AO28: =(AN28/100)*3000 -> 2040 | AP28: 69 | AQ28: =(AP28/100)*3000 -> 2070 | AR28: 68 | AS28: =(AR28/100)*3000 -> 2040 | AT28: =SUM(AO28+AQ28+AS28) -> 6150 | AU28: =AT27-AT28+AV28 -> 210 | AX28: =IF(AV28>0,AW28,AX27) -> 0.7
A29: 43824 | B29: 202 | C29: 118 | D29: =C28-C29 -> 18 | E29: =D29*8.38 -> 150.84 | F29: 1295 | G29: =F29-F28 -> 6 | H29: 329704 | I29: =SUM(H29-H28) -> 541 | J29: =IF(G29>0,I29/G29,0) -> 90.166667 | K29: 1615 | L29: =K29-K28 -> 0 | M29: 117578 | N29: =M29-M28 -> 0 | O29: =SUM(L29*$J$1) -> 0 | P29: 1452 | Q29: 126239 | R29: =Q29-Q28 -> 0 | S29: =SUM(P29-P28) -> 0 | T29: =SUM(S29*$T$2) -> 0 | U29: =SUM(G29+L29+S29) -> 6 | V29: =R29+N29+I29:I29 -> 541 | X29: 2309 | Y29: =X29-X28 -> 8 | Z29: 130009.7 | AA29: =Z29-Z28 -> 411.4 | AB29: =SUM(Y29*$AB$2) -> 0 | AC29: 1688 | AD29: =AC29-AC28 -> 0 | AE29: 351848.7 | AF29: =AE29-AE28 -> 0 | AG29: =IF(AD29>0,AF29/AD29,0) -> 0 | AH29: =AF29+AA29 -> 411.4 | AI29: =SUM(AH29+V29) -> 952.4 | AJ29: =-tanks!AW30 -> 952.4 | AK29: =SUM(AJ29-AI29) -> 0 | AL29: =S29+L29+G29 -> 6 | AM29: =Y29+AD29 -> 8 | AN29: 65 | AO29: =(AN29/100)*3000 -> 1950 | AP29: 66 | AQ29: =(AP29/100)*3000 -> 1980 | AR29: 65 | AS29: =(AR29/100)*3000 -> 1950 | AT29: =SUM(AO29+AQ29+AS29) -> 5880 | AU29: =AT28-AT29+AV29 -> 270 | AX29: =IF(AV29>0,AW29,AX28) -> 0.7
A30: 43825 | B30: 181 | C30: 162 | D30: =C29-C30 -> -44 | E30: =D30*8.38 -> -368.72 | F30: 1303 | G30: =F30-F29 -> 8 | H30: 330270 | I30: =SUM(H30-H29) -> 566 | J30: =IF(G30>0,I30/G30,0) -> 70.75 | K30: 1621 | L30: =K30-K29 -> 6 | M30: 117953 | N30: =M30-M29 -> 375 | O30: =SUM(L30*$J$1) -> 460.00487 | P30: 1452 | Q30: 126239 | R30: =Q30-Q29 -> 0 | S30: =SUM(P30-P29) -> 0 | T30: =SUM(S30*$T$2) -> 0 | U30: =SUM(G30+L30+S30) -> 14 | V30: =R30+N30+I30:I30 -> 941 | X30: 2310 | Y30: =X30-X29 -> 1 | Z30: 130086.3 | AA30: =Z30-Z29 -> 76.6 | AB30: =SUM(Y30*$AB$2) -> 0 | AC30: 1688 | AD30: =AC30-AC29 -> 0 | AE30: 351848.7 | AF30: =AE30-AE29 -> 0 | AG30: =IF(AD30>0,AF30/AD30,0) -> 0 | AH30: =AF30+AA30 -> 76.6 | AI30: =SUM(AH30+V30) -> 1017.6 | AJ30: =-tanks!AW31 -> 1017.6 | AK30: =SUM(AJ30-AI30) -> 0 | AL30: =S30+L30+G30 -> 14 | AM30: =Y30+AD30 -> 1 | AN30: 80 | AO30: =(AN30/100)*3000 -> 2400 | AP30: 81 | AQ30: =(AP30/100)*3000 -> 2430 | AR30: 82 | AS30: =(AR30/100)*3000 -> 2460 | AT30: =SUM(AO30+AQ30+AS30) -> 7290 | AU30: =AT29-AT30+AV30 -> 390 | AV30: 1800 | AW30: 0.7 | AX30: =IF(AV30>0,AW30,AX29) -> 0.7
A31: 43826 | B31: 213 | C31: 139 | D31: =C30-C31 -> 23 | E31: =D31*8.38 -> 192.74 | F31: =F30 -> 1303 | G31: =F31-F30 -> 0 | H31: =H30 -> 330270 | I31: =SUM(H31-H30) -> 0 | J31: =IF(G31>0,I31/G31,0) -> 0 | K31: 1631 | L31: =K31-K30 -> 10 | M31: 118736 | N31: =M31-M30 -> 783 | O31: =SUM(L31*$J$1) -> 766.67478 | P31: 1452 | Q31: =Q30 -> 126239 | R31: =Q31-Q30 -> 0 | S31: =SUM(P31-P30) -> 0 | T31: =SUM(S31*$T$2) -> 0 | U31: =SUM(G31+L31+S31) -> 10 | V31: =R31+N31+I31:I31 -> 783 | X31: 2319 | Y31: =X31-X30 -> 9 | Z31: 130507 | AA31: =Z31-Z30 -> 420.7 | AB31: =SUM(Y31*$AB$2) -> 0 | AC31: =AC30 -> 1688 | AD31: =AC31-AC30 -> 0 | AE31: =AE30 -> 351848.7 | AF31: =AE31-AE30 -> 0 | AG31: =IF(AD31>0,AF31/AD31,0) -> 0 | AH31: =AF31+AA31 -> 420.7 | AI31: =SUM(AH31+V31) -> 1203.7 | AJ31: =-tanks!AW32 -> 1203.7 | AK31: =SUM(AJ31-AI31) -> 0 | AL31: =S31+L31+G31 -> 10 | AM31: =Y31+AD31 -> 9 | AN31: 79 | AO31: =(AN31/100)*3000 -> 2370 | AP31: 79 | AQ31: =(AP31/100)*3000 -> 2370 | AR31: 80 | AS31: =(AR31/100)*3000 -> 2400 | AT31: =SUM(AO31+AQ31+AS31) -> 7140 | AU31: =AT30-AT31+AV31 -> 150 | AX31: =IF(AV31>0,AW31,AX30) -> 0.7
A32: 43827 | B32: 209 | C32: 120 | D32: =C31-C32 -> 19 | E32: =D32*8.38 -> 159.22 | F32: 1303 | G32: =F32-F31 -> 0 | H32: 330270 | I32: =SUM(H32-H31) -> 0 | J32: =IF(G32>0,I32/G32,0) -> 0 | K32: 1643 | L32: =K32-K31 -> 12 | M32: 119632 | N32: =M32-M31 -> 896 | O32: =SUM(L32*$J$1) -> 920.00974 | P32: 1452 | Q32: 126239 | R32: =Q32-Q31 -> 0 | S32: =SUM(P32-P31) -> 0 | T32: =SUM(S32*$T$2) -> 0 | U32: =SUM(G32+L32+S32) -> 12 | V32: =R32+N32+I32:I32 -> 896 | X32: 2320 | Y32: =X32-X31 -> 1 | Z32: 130593 | AA32: =Z32-Z31 -> 86 | AB32: =SUM(Y32*$AB$2) -> 0 | AC32: 1689 | AD32: =AC32-AC31 -> 1 | AE32: 351940.6 | AF32: =AE32-AE31 -> 91.9 | AG32: =IF(AD32>0,AF32/AD32,0) -> 91.9 | AH32: =AF32+AA32 -> 177.9 | AI32: =SUM(AH32+V32) -> 1073.9 | AJ32: =-tanks!AW33 -> 1073.9 | AK32: =SUM(AJ32-AI32) -> 0 | AL32: =S32+L32+G32 -> 12 | AM32: =Y32+AD32 -> 2 | AN32: 76 | AO32: =(AN32/100)*3000 -> 2280 | AP32: 76 | AQ32: =(AP32/100)*3000 -> 2280 | AR32: 78 | AS32: =(AR32/100)*3000 -> 2340 | AT32: =SUM(AO32+AQ32+AS32) -> 6900 | AU32: =AT31-AT32+AV32 -> 240 | AX32: =IF(AV32>0,AW32,AX31) -> 0.7
A33: 43828 | B33: 205 | C33: 99 | D33: =C32-C33 -> 21 | E33: =D33*8.38 -> 175.98 | F33: 1303 | G33: =F33-F32 -> 0 | H33: 330270 | I33: =SUM(H33-H32) -> 0 | J33: =IF(G33>0,I33/G33,0) -> 0 | K33: 1655 | L33: =K33-K32 -> 12 | M33: 120483 | N33: =M33-M32 -> 851 | O33: =SUM(L33*$J$1) -> 920.00974 | P33: 1452 | Q33: 126239 | R33: =Q33-Q32 -> 0 | S33: =SUM(P33-P32) -> 0 | T33: =SUM(S33*$T$2) -> 0 | U33: =SUM(G33+L33+S33) -> 12 | V33: =R33+N33+I33:I33 -> 851 | X33: 2320 | Y33: =X33-X32 -> 0 | Z33: 130593 | AA33: =Z33-Z32 -> 0 | AB33: =SUM(Y33*$AB$2) -> 0 | AC33: 1696 | AD33: =AC33-AC32 -> 7 | AE33: 352231.8 | AF33: =AE33-AE32 -> 291.2 | AG33: =IF(AD33>0,AF33/AD33,0) -> 41.6 | AH33: =AF33+AA33 -> 291.2 | AI33: =SUM(AH33+V33) -> 1142.2 | AJ33: =-tanks!AW34 -> 1142.2 | AK33: =SUM(AJ33-AI33) -> 0 | AL33: =S33+L33+G33 -> 12 | AM33: =Y33+AD33 -> 7 | AN33: 73 | AO33: =(AN33/100)*3000 -> 2190 | AP33: 73 | AQ33: =(AP33/100)*3000 -> 2190 | AR33: 75 | AS33: =(AR33/100)*3000 -> 2250 | AT33: =SUM(AO33+AQ33+AS33) -> 6630 | AU33: =AT32-AT33+AV33 -> 270 | AX33: =IF(AV33>0,AW33,AX32) -> 0.7
A34: 43495 | B34: 190 | C34: 123 | D34: =C33-C34 -> -24 | E34: =D34*8.38 -> -201.12 | F34: =F33 -> 1303 | G34: =F34-F33 -> 0 | H34: =H33 -> 330270 | I34: =SUM(H34-H33) -> 0 | J34: =IF(G34>0,I34/G34,0) -> 0 | K34: 1666 | L34: =K34-K33 -> 11 | M34: 121321 | N34: =M34-M33 -> 838 | O34: =SUM(L34*$J$1) -> 843.34226 | P34: =P33 -> 1452 | Q34: =Q33 -> 126239 | R34: =Q34-Q33 -> 0 | S34: =SUM(P34-P33) -> 0 | T34: =SUM(S34*$T$2) -> 0 | U34: =SUM(G34+L34+S34) -> 11 | V34: =R34+N34+I34:I34 -> 838 | X34: =X33 -> 2320 | Y34: =X34-X33 -> 0 | Z34: =Z33 -> 130593 | AA34: =Z34-Z33 -> 0 | AB34: =SUM(Y34*$AB$2) -> 0 | AC34: 1697 | AD34: =AC34-AC33 -> 1 | AE34: 352365.2 | AF34: =AE34-AE33 -> 133.4 | AG34: =IF(AD34>0,AF34/AD34,0) -> 133.4 | AH34: =AF34+AA34 -> 133.4 | AI34: =SUM(AH34+V34) -> 971.4 | AJ34: =-tanks!AW35 -> 971.4 | AK34: =SUM(AJ34-AI34) -> 0 | AL34: =S34+L34+G34 -> 11 | AM34: =Y34+AD34 -> 1 | AN34: 69 | AO34: =(AN34/100)*3000 -> 2070 | AP34: 69 | AQ34: =(AP34/100)*3000 -> 2070 | AR34: 71 | AS34: =(AR34/100)*3000 -> 2130 | AT34: =SUM(AO34+AQ34+AS34) -> 6270 | AU34: =AT33-AT34+AV34 -> 360 | AX34: =IF(AV34>0,AW34,AX33) -> 0.7
A35: 43830 | B35: 238 | C35: 98 | D35: =C34-C35 -> 25 | E35: =D35*8.38 -> 209.5 | F35: =F34 -> 1303 | G35: =F35-F34 -> 0 | H35: =H34 -> 330270 | I35: =SUM(H35-H34) -> 0 | J35: =IF(G35>0,I35/G35,0) -> 0 | K35: 1679 | L35: =K35-K34 -> 13 | M35: 122271 | N35: =M35-M34 -> 950 | O35: =SUM(L35*$J$1) -> 996.67722 | P35: =P34 -> 1452 | Q35: =Q34 -> 126239 | R35: =Q35-Q34 -> 0 | S35: =SUM(P35-P34) -> 0 | T35: =SUM(S35*$T$2) -> 0 | U35: =SUM(G35+L35+S35) -> 13 | V35: =R35+N35+I35:I35 -> 950 | X35: =X34 -> 2320 | Y35: =X35-X34 -> 0 | Z35: =Z34 -> 130593 | AA35: =Z35-Z34 -> 0 | AB35: =SUM(Y35*$AB$2) -> 0 | AC35: 1699 | AD35: =AC35-AC34 -> 2 | AE35: 352700 | AF35: =AE35-AE34 -> 334.8 | AG35: =IF(AD35>0,AF35/AD35,0) -> 167.4 | AH35: =AF35+AA35 -> 334.8 | AI35: =SUM(AH35+V35) -> 1284.8 | AJ35: =-tanks!AW36 -> 1284.8 | AK35: =SUM(AJ35-AI35) -> 0 | AL35: =S35+L35+G35 -> 13 | AM35: =Y35+AD35 -> 2 | AN35: 65 | AO35: =(AN35/100)*3000 -> 1950 | AP35: 67 | AQ35: =(AP35/100)*3000 -> 2010 | AR35: 68 | AS35: =(AR35/100)*3000 -> 2040 | AT35: =SUM(AO35+AQ35+AS35) -> 6000 | AU35: =AT34-AT35+AV35 -> 270 | AX35: =IF(AV35>0,AW35,AX34) -> 0.7
J36: =SUM(J5:J34)/(COUNT(J5:J34)-COUNTIF(J5:J34,0)) -> 76.667478 | AE36: . | AR36: Nb Delivery | AS36: =COUNT(AW5:AW35) -> 4 | AU36: =SUM(AU5:AU35) -> 6550 | AV36: =SUM(AV5:AV35) -> 5500 | AW36: =SUM(AW5:AW35)/AS36 -> 0.7
AH37: =AF37+AA37 -> 0 | AI37: =SUM(AI5:AI35) -> 25427
AH38: =AF38+AA38 -> 0 | AU38: =AU36*0.51 -> 3340.5 | AV38: =AV36/0.51 -> 10784.314 | AW38: =SUM(AW5:AW35)/AS36 -> 0.7
AV39: =AV36*0.51 -> 2805

Sheet GEN
B1: GEN1 | C1: RUN HR | D1: Fuel Counter Index | E1: Cons /day | F1: Diesel L/H | H1: next service | I1: ALARM | J1: GEN2 | K1: RUN HR | L1: Fuel Counter Index | M1: Cons /day | N1: Diesel L/H | P1: next service | Q1: ALARM | R1: GEN3 | S1: RUN HR | T1: Fuel Counter Index | U1: Cons /day | V1: Diesel L/H | X1: next service | Y1: ALARM | Z1: RH total | AA1: Gen Con /day | AB1: Total Deisel Cons/day | AC1: H /L | AD1: TOAL KW GEN | AI1: fuel Consuption | AK1: AVG KW/h
A2: =ELEC!C2 -> 43799 | B2: =[1]GEN!B32 -> 8422 | C2: =[1]GEN!C32 -> 1 | D2: =[1]GEN!D32 -> 109619.1 | E2: =[1]GEN!E32 -> 41.1 | F2: =[1]GEN!F32 -> 41.1 | G2: =[1]GEN!G32 -> 0 | H2: =[1]GEN!H32 -> 8497 | I2: =[1]GEN!I32 -> ok | ... AK2: =[1]GEN!AK32 -> 106.9049
A3: =ELEC!C3 -> 43800 | B3: 8422.08 | C3: =B3-B2 -> 0.08 | D3: =D2 -> 109619.1 | E3: =SUM(D3-D2) -> 0 | F3: =IF(C3>0,E3/C3,0) -> 0 | G3: =[2]GEN!G32 -> 0 | H3: =H2 -> 8497 | I3: =IF(B3-H3<=0,"ok","oil change") -> ok | J3: 10553.2 | K3: =J3-J2 -> 0 | L3: 214152 | M3: =SUM(L3-L2) -> 0 | N3: =IF(K3>0,M3/K3,0) -> 0 | O3: =[2]GEN!O32 -> 0 | P3: =P2 -> 10535 | Q3: =IF(J3-P3<=0,"ok","oil change") -> oil change | R3: 10865 | S3: =R3-R2 -> 2.51 | T3: 171471 | U3: =SUM(T3-T2) -> 743.5 | V3: =IF(S3>0,U3/S3,0) -> 296.21514 | W3: =[2]GEN!W32 -> 0 | X3: =X2 -> 10809 | Y3: =IF(R3-X3<=0,"ok","oil change") -> oil change | Z3: =C3+K3+S3 -> 2.59 | AA3: =U3+M3+E3 -> 743.5 | AB3: =V3+N3+F3 -> 296.21514 | AC3: =IF(Z3>0,AA3/Z3,0) -> 287.06564 | AD3: =ELEC!Q3 -> 2532 | AE3: =SUM(AD3/Z3) -> 977.60618 | AF3: =SUM(AE3/1600) -> 0.61100386 | AG3: =SUM(360*AF3) -> 219.96139 | AH3: =SUM(AC3-AG3) -> 67.104247 | AI3: =AD3*AJ3 -> 651.6962 | AJ3: =305/1185 -> 0.25738397 | AK3: =AI3/Z3 -> 251.62016
A4: =ELEC!C4 -> 43801 | B4: 8422 | C4: =B4-B3 -> -0.08 | D4: 109652 | E4: =SUM(D4-D3) -> 32.9 | F4: =IF(C4>0,E4/C4,0) -> 0 | H4: =H3 -> 8497 | I4: =IF(B4-H4<=0,"ok","oil change") -> ok | J4: 10553 | K4: =J4-J3 -> -0.2 | L4: 214152 | M4: =SUM(L4-L3) -> 0 | N4: =IF(K4>0,M4/K4,0) -> 0 | P4: =P3 -> 10535 | Q4: =IF(J4-P4<=0,"ok","oil change") -> oil change | R4: 10868 | S4: =R4-R3 -> 3 | T4: 171680 | U4: =SUM(T4-T3) -> 209 | V4: =IF(S4>0,U4/S4,0) -> 69.666667 | X4: =X3 -> 10809 | Y4: =IF(R4-X4<=0,"ok","oil change") -> oil change | Z4: =C4+K4+S4 -> 2.72 | AA4: =U4+M4+E4 -> 241.9 | AB4: =V4+N4+F4 -> 69.666667 | AC4: =IF(Z4>0,AA4/Z4,0) -> 88.933824 | AD4: =ELEC!Q4 -> 2168 | AE4: =SUM(AD4/Z4) -> 797.05882 | AF4: =SUM(AE4/1600) -> 0.49816176 | AG4: =SUM(360*AF4) -> 179.33824 | AH4: =SUM(AC4-AG4) -> -90.404412 | AI4: =AD4*AJ4 -> 558.00844 | AJ4: =305/1185 -> 0.25738397 | AK4: =AI4/Z4 -> 205.15016
A5: =ELEC!C5 -> 43802 | B5: 8422 | C5: =B5-B4 -> 0 | D5: 109677 | E5: =SUM(D5-D4) -> 25 | F5: =IF(C5>0,E5/C5,0) -> 0 | H5: 8497 | I5: =IF(B5-H5<=0,"ok","oil change") -> ok | J5: 10553 | K5: =J5-J4 -> 0 | L5: 214152 | M5: =SUM(L5-L4) -> 0 | N5: =IF(K5>0,M5/K5,0) -> 0 | P5: =P4 -> 10535 | Q5: =IF(J5-P5<=0,"ok","oil change") -> oil change | R5: 10872 | S5: =R5-R4 -> 4 | T5: 172307.9 | U5: =SUM(T5-T4) -> 627.9 | V5: =IF(S5>0,U5/S5,0) -> 156.975 | X5: =X4 -> 10809 | Y5: =IF(R5-X5<=0,"ok","oil change") -> oil change | Z5: =C5+K5+S5 -> 4 | AA5: =U5+M5+E5 -> 652.9 | AB5: =V5+N5+F5 -> 156.975 | AC5: =IF(Z5>0,AA5/Z5,0) -> 163.225 | AD5: =ELEC!Q5 -> 2000 | AE5: =SUM(AD5/Z5) -> 500 | AF5: =SUM(AE5/1600) -> 0.3125 | AG5: =SUM(320*AF5) -> 100 | AH5: =SUM(AC5-AG5) -> 63.225 | AI5: =AD5*AJ5 -> 514.76793 | AJ5: =305/1185 -> 0.25738397 | AK5: =AI5/Z5 -> 128.69198
A6: =ELEC!C6 -> 43803 | B6: 8425 | C6: =B6-B5 -> 3 | D6: 110237 | E6: =SUM(D6-D5) -> 560 | F6: =IF(C6>0,E6/C6,0) -> 186.66667 | H6: =H5 -> 8497 | I6: =IF(B6-H6<=0,"ok","oil change") -> ok | J6: 10553 | K6: =J6-J5 -> 0 | L6: =L5 -> 214152 | M6: =SUM(L6-L5) -> 0 | N6: =IF(K6>0,M6/K6,0) -> 0 | P6: =P5 -> 10535 | Q6: =IF(J6-P6<=0,"ok","oil change") -> oil change | R6: 10872 | S6: =R6-R5 -> 0 | T6: 172368 | U6: =SUM(T6-T5) -> 60.1 | V6: =IF(S6>0,U6/S6,0) -> 0 | X6: =X5 -> 10809 | Y6: =IF(R6-X6<=0,"ok","oil change") -> oil change | Z6: =C6+K6+S6 -> 3 | AA6: =U6+M6+E6 -> 620.1 | AB6: =V6+N6+F6 -> 186.66667 | AC6: =IF(Z6>0,AA6/Z6,0) -> 206.7 | AD6: =ELEC!Q6 -> 2572 | AE6: =SUM(AD6/Z6) -> 857.33333 | AF6: =SUM(AE6/1600) -> 0.53583333 | AG6: =SUM(320*AF6) -> 171.46667 | AH6: =SUM(AC6-AG6) -> 35.233333 | AI6: =AD6*AJ6 -> 661.99156 | AJ6: =305/1185 -> 0.25738397 | AK6: =AI6/Z6 -> 220.66385
A7: =ELEC!C7 -> 43804 | B7: 8428.4 | C7: =B7-B6 -> 3.4 | D7: 110600 | E7: =SUM(D7-D6) -> 363 | F7: =IF(C7>0,E7/C7,0) -> 106.76471 | H7: =H6 -> 8497 | I7: =IF(B7-H7<=0,"ok","oil change") -> ok | J7: 10553 | K7: =J7-J6 -> 0 | L7: 214152 | M7: =SUM(L7-L6) -> 0 | N7: =IF(K7>0,M7/K7,0) -> 0 | P7: =P6 -> 10535 | Q7: =IF(J7-P7<=0,"ok","oil change") -> oil change | R7: 10872 | S7: =R7-R6 -> 0 | T7: 172430 | U7: =SUM(T7-T6) -> 62 | V7: =IF(S7>0,U7/S7,0) -> 0 | X7: =X6 -> 10809 | Y7: =IF(R7-X7<=0,"ok","oil change") -> oil change | Z7: =C7+K7+S7 -> 3.4 | AA7: =U7+M7+E7 -> 425 | AB7: =V7+N7+F7 -> 106.76471 | AC7: =IF(Z7>0,AA7/Z7,0) -> 125 | AD7: =ELEC!Q7 -> 2498 | AE7: =SUM(AD7/Z7) -> 734.70588 | AF7: =SUM(AE7/1600) -> 0.45919118 | AH7: =SUM(AC7-AG7) -> #VALUE! | AI7: =AD7*AJ7 -> 642.94515 | AJ7: =305/1185 -> 0.25738397 | AK7: =AI7/Z7 -> 189.10151
A8: =ELEC!C8 -> 43805 | B8: 8432.57 | C8: =B8-B7 -> 4.17 | D8: 111185.2 | E8: =SUM(D8-D7) -> 585.2 | F8: =IF(C8>0,E8/C8,0) -> 140.33573 | H8: =H7 -> 8497 | I8: =IF(B8-H8<=0,"ok","oil change") -> ok | J8: =J7 -> 10553 | K8: =J8-J7 -> 0 | L8: =L7 -> 214152 | M8: =SUM(L8-L7) -> 0 | N8: =IF(K8>0,M8/K8,0) -> 0 | P8: =P7 -> 10535 | Q8: =IF(J8-P8<=0,"ok","oil change") -> oil change | R8: 10872 | S8: =R8-R7 -> 0 | T8: 172543 | U8: =SUM(T8-T7) -> 113 | V8: =IF(S8>0,U8/S8,0) -> 0 | X8: =X7 -> 10809 | Y8: =IF(R8-X8<=0,"ok","oil change") -> oil change | Z8: =C8+K8+S8 -> 4.17 | AA8: =U8+M8+E8 -> 698.2 | AB8: =V8+N8+F8 -> 140.33573 | AC8: =IF(Z8>0,AA8/Z8,0) -> 167.43405 | AD8: =ELEC!Q8 -> 3056 | AE8: =SUM(AD8/Z8) -> 732.85372 | AF8: =SUM(AE8/1600) -> 0.45803357 | AG8: =SUM(320*AF8) -> 146.57074 | AH8: =SUM(AC8-AG8) -> 20.863309 | AI8: =AD8*AJ8 -> 786.5654 | AJ8: =305/1185 -> 0.25738397 | AK8: =AI8/Z8 -> 188.6248
A9: =ELEC!C9 -> 43806 | B9: 8436 | C9: =B9-B8 -> 3.43 | D9: 111703 | E9: =SUM(D9-D8) -> 517.8 | F9: =IF(C9>0,E9/C9,0) -> 150.9621 | H9: =H8 -> 8497 | I9: =IF(B9-H9<=0,"ok","oil change") -> ok | J9: 10553 | K9: =J9-J8 -> 0 | L9: =L8 -> 214152 | M9: =SUM(L9-L8) -> 0 | N9: =IF(K9>0,M9/K9,0) -> 0 | P9: =P8 -> 10535 | Q9: =IF(J9-P9<=0,"ok","oil change") -> oil change | R9: 10873 | S9: =R9-R8 -> 1 | T9: 172605 | U9: =SUM(T9-T8) -> 62 | V9: =IF(S9>0,U9/S9,0) -> 62 | X9: =X8 -> 10809 | Y9: =IF(R9-X9<=0,"ok","oil change") -> oil change | Z9: =C9+K9+S9 -> 4.43 | AA9: =U9+M9+E9 -> 579.8 | AB9: =V9+N9+F9 -> 212.9621 | AC9: =IF(Z9>0,AA9/Z9,0) -> 130.88036 | AD9: =ELEC!Q9 -> 1874 | AE9: =SUM(AD9/Z9) -> 423.02483 | AF9: =SUM(AE9/1600) -> 0.26439052 | AG9: =SUM(320*AF9) -> 84.604966 | AH9: =SUM(AC9-AG9) -> 46.275395 | AI9: =AD9*AJ9 -> 482.33755 | AJ9: 0.25738397 | AK9: =IF(Z9>0,AI9/Z9,0) -> 108.87981
A10: =ELEC!C10 -> 43807 | B10: 8439 | C10: =B10-B9 -> 3 | D10: 112292 | E10: =SUM(D10-D9) -> 589 | F10: =IF(C10>0,E10/C10,0) -> 196.33333 | H10: =H9 -> 8497 | I10: =IF(B10-H10<=0,"ok","oil change") -> ok | J10: 10553 | K10: =J10-J9 -> 0 | L10: =L9 -> 214152 | M10: =SUM(L10-L9) -> 0 | N10: =IF(K10>0,M10/K10,0) -> 0 | P10: 10873 | Q10: =IF(J10-P10<=0,"ok","oil change") -> ok | R10: =R9 -> 10873 | S10: =R10-R9 -> 0 | T10: 172667 | U10: =SUM(T10-T9) -> 62 | V10: =IF(S10>0,U10/S10,0) -> 0 | X10: =X9 -> 10809 | Y10: =IF(R10-X10<=0,"ok","oil change") -> oil change | Z10: =C10+K10+S10 -> 3 | AA10: =U10+M10+E10 -> 651 | AB10: =V10+N10+F10 -> 196.33333 | AC10: =IF(Z10>0,AA10/Z10,0) -> 217 | AD10: =ELEC!Q10 -> 2000 | AE10: =SUM(AD10/Z10) -> 666.66667 | AF10: =SUM(AE10/1600) -> 0.41666667 | AG10: =SUM(320*AF10) -> 133.33333 | AH10: =SUM(AC10-AG10) -> 83.666667 | AI10: =AD10*AJ10 -> 514.76793 | AJ10: =305/1185 -> 0.25738397 | AK10: =IF(Z10>0,AI10/Z10,0) -> 171.58931
A11: =ELEC!C11 -> 43808 | B11: 8442 | C11: =B11-B10 -> 3 | D11: 112867.2 | E11: =SUM(D11-D10) -> 575.2 | F11: =IF(C11>0,E11/C11,0) -> 191.73333 | H11: =H10 -> 8497 | I11: =IF(B11-H11<=0,"ok","oil change") -> ok | J11: 10553 | K11: =J11-J10 -> 0 | L11: 214152.3 | M11: =SUM(L11-L10) -> 0.3 | N11: =IF(K11>0,M11/K11,0) -> 0 | P11: =P10 -> 10873 | Q11: =IF(J11-P11<=0,"ok","oil change") -> ok | R11: 10873 | S11: =R11-R10 -> 0 | T11: 172790 | U11: =SUM(T11-T10) -> 123 | V11: =IF(S11>0,U11/S11,0) -> 0 | X11: =X10 -> 10809 | Y11: =IF(R11-X11<=0,"ok","oil change") -> oil change | Z11: =C11+K11+S11 -> 3 | AA11: =U11+M11+E11 -> 698.5 | AB11: =V11+N11+F11 -> 191.73333 | AC11: =IF(Z11>0,AA11/Z11,0) -> 232.83333 | AD11: =ELEC!Q11 -> 2742 | AE11: =SUM(AD11/Z11) -> 914 | AF11: =SUM(AE11/1600) -> 0.57125 | AG11: =SUM(320*AF11) -> 182.8 | AH11: =SUM(AC11-AG11) -> 50.033333 | AI11: =AD11*AJ11 -> 705.74684 | AJ11: =305/1185 -> 0.25738397 | AK11: =IF(Z11>0,AI11/Z11,0) -> 235.24895
A12: =ELEC!C12 -> 43809 | B12: 8445 | C12: =B12-B11 -> 3 | D12: 113351.5 | E12: =SUM(D12-D11) -> 484.3 | F12: =IF(C12>0,E12/C12,0) -> 161.43333 | H12: =H11 -> 8497 | I12: =IF(B12-H12<=0,"ok","oil change") -> ok | J12: 10553 | K12: =J12-J11 -> 0 | L12: 214152 | M12: =SUM(L12-L11) -> -0.3 | N12: =IF(K12>0,M12/K12,0) -> 0 | P12: =P11 -> 10873 | Q12: =IF(J12-P12<=0,"ok","oil change") -> ok | R12: 10874 | S12: =R12-R11 -> 1 | T12: 172845 | U12: =SUM(T12-T11) -> 55 | V12: =IF(S12>0,U12/S12,0) -> 55 | X12: =X11 -> 10809 | Y12: =IF(R12-X12<=0,"ok","oil change") -> oil change | Z12: =C12+K12+S12 -> 4 | AA12: =U12+M12+E12 -> 539 | AB12: =V12+N12+F12 -> 216.43333 | AC12: =IF(Z12>0,AA12/Z12,0) -> 134.75 | AD12: =ELEC!Q12 -> 2008 | AE12: =SUM(AD12/Z12) -> 502 | AF12: =SUM(AE12/1600) -> 0.31375 | AG12: =SUM(320*AF12) -> 100.4 | AH12: =SUM(AC12-AG12) -> 34.35 | AI12: =AD12*AJ12 -> 516.827 | AJ12: =305/1185 -> 0.25738397 | AK12: =IF(Z12>0,AI12/Z12,0) -> 129.20675
A13: =ELEC!C13 -> 43810 | B13: 8448 | C13: =B13-B12 -> 3 | D13: 113740 | E13: =SUM(D13-D12) -> 388.5 | F13: =IF(C13>0,E13/C13,0) -> 129.5 | H13: =H12 -> 8497 | I13: =IF(B13-H13<=0,"ok","oil change") -> ok | J13: 10553 | K13: =J13-J12 -> 0 | L13: 214152 | M13: =SUM(L13-L12) -> 0 | N13: =IF(K13>0,M13/K13,0) -> 0 | P13: =P12 -> 10873 | Q13: =IF(J13-P13<=0,"ok","oil change") -> ok | R13: 10874 | S13: =R13-R12 -> 0 | T13: 172908 | U13: =SUM(T13-T12) -> 63 | V13: =IF(S13>0,U13/S13,0) -> 0 | X13: =X12+180 -> 10989 | Y13: =IF(R13-X13<=0,"ok","oil change") -> ok | Z13: =C13+K13+S13 -> 3 | AA13: =U13+M13+E13 -> 451.5 | AB13: =V13+N13+F13 -> 129.5 | AC13: =IF(Z13>0,AA13/Z13,0) -> 150.5 | AD13: =ELEC!Q13 -> 2342 | AE13: =SUM(AD13/Z13) -> 780.66667 | AF13: =SUM(AE13/1600) -> 0.48791667 | AG13: =SUM(320*AF13) -> 156.13333 | AH13: =SUM(AC13-AG13) -> -5.6333333 | AI13: =AD13*AJ13 -> 602.79325 | AJ13: =305/1185 -> 0.25738397 | AK13: =IF(Z13>0,AI13/Z13,0) -> 200.93108
A14: =ELEC!C14 -> 43811 | B14: 8451 | C14: =B14-B13 -> 3 | D14: 114075 | E14: =SUM(D14-D13) -> 335 | F14: =IF(C14>0,E14/C14,0) -> 111.66667 | H14: =H13 -> 8497 | I14: =IF(B14-H14<=0,"ok","oil change") -> ok | J14: 10553 | K14: =J14-J13 -> 0 | L14: 214152 | M14: =SUM(L14-L13) -> 0 | N14: =IF(K14>0,M14/K14,0) -> 0 | P14: =P13 -> 10873 | Q14: =IF(J14-P14<=0,"ok","oil change") -> ok | R14: 10874 | S14: =R14-R13 -> 0 | T14: 172996 | U14: =SUM(T14-T13) -> 88 | V14: =IF(S14>0,U14/S14,0) -> 0 | X14: =X13 -> 10989 | Y14: =IF(R14-X14<=0,"ok","oil change") -> ok | Z14: =C14+K14+S14 -> 3 | AA14: =U14+M14+E14 -> 423 | AB14: =V14+N14+F14 -> 111.66667 | AC14: =IF(Z14>0,AA14/Z14,0) -> 141 | AD14: =ELEC!Q14 -> 1908 | AE14: =SUM(AD14/Z14) -> 636 | AF14: =SUM(AE14/1600) -> 0.3975 | AG14: =SUM(320*AF14) -> 127.2 | AH14: =SUM(AC14-AG14) -> 13.8 | AI14: =AD14*AJ14 -> 491.08861 | AJ14: =305/1185 -> 0.25738397 | AK14: =IF(Z14>0,AI14/Z14,0) -> 163.6962
A15: =ELEC!C15 -> 43812 | B15: 8453 | C15: =B15-B14 -> 2 | D15: 114305.9 | E15: =SUM(D15-D14) -> 230.9 | F15: =IF(C15>0,E15/C15,0) -> 115.45 | H15: =H14 -> 8497 | I15: =IF(B15-H15<=0,"ok","oil change") -> ok | J15: 10553 | K15: =J15-J14 -> 0 | L15: 214152 | M15: =SUM(L15-L14) -> 0 | N15: =IF(K15>0,M15/K15,0) -> 0 | P15: =P14 -> 10873 | Q15: =IF(J15-P15<=0,"ok","oil change") -> ok | R15: 10876 | S15: =R15-R14 -> 2 | T15: 173343 | U15: =SUM(T15-T14) -> 347 | V15: =IF(S15>0,U15/S15,0) -> 173.5 | X15: =X14 -> 10989 | Y15: =IF(R15-X15<=0,"ok","oil change") -> ok | Z15: =C15+K15+S15 -> 4 | AA15: =U15+M15+E15 -> 577.9 | AB15: =V15+N15+F15 -> 288.95 | AC15: =IF(Z15>0,AA15/Z15,0) -> 144.475 | AD15: =ELEC!Q15 -> 3365 | AE15: =SUM(AD15/Z15) -> 841.25 | AF15: =SUM(AE15/1600) -> 0.52578125 | AG15: =SUM(320*AF15) -> 168.25 | AH15: =SUM(AC15-AG15) -> -23.775 | AI15: =AD15*AJ15 -> 866.09705 | AJ15: =305/1185 -> 0.25738397 | AK15: =IF(Z15>0,AI15/Z15,0) -> 216.52426
A16: =ELEC!C16 -> 43813 | B16: 8456 | C16: =B16-B15 -> 3 | D16: 114679 | E16: =SUM(D16-D15) -> 373.1 | F16: =IF(C16>0,E16/C16,0) -> 124.36667 | H16: =H15 -> 8497 | I16: =IF(B16-H16<=0,"ok","oil change") -> ok | J16: =J15 -> 10553 | K16: =J16-J15 -> 0 | L16: =L15 -> 214152 | M16: =SUM(L16-L15) -> 0 | N16: =IF(K16>0,M16/K16,0) -> 0 | P16: =P15 -> 10873 | Q16: =IF(J16-P16<=0,"ok","oil change") -> ok | R16: 10877 | S16: =R16-R15 -> 1 | T16: 173581.8 | U16: =SUM(T16-T15) -> 238.8 | V16: =IF(S16>0,U16/S16,0) -> 238.8 | X16: =X15 -> 10989 | Y16: =IF(R16-X16<=0,"ok","oil change") -> ok | Z16: =C16+K16+S16 -> 4 | AA16: =U16+M16+E16 -> 611.9 | AB16: =V16+N16+F16 -> 363.16667 | AC16: =IF(Z16>0,AA16/Z16,0) -> 152.975 | AD16: =ELEC!Q16 -> 2635 | AE16: =SUM(AD16/Z16) -> 658.75 | AF16: =SUM(AE16/1600) -> 0.41171875 | AG16: =SUM(320*AF16) -> 131.75 | AH16: =SUM(AC16-AG16) -> 21.225 | AI16: =AD16*AJ16 -> 678.20675 | AJ16: =305/1185 -> 0.25738397 | AK16: =IF(Z16>0,AI16/Z16,0) -> 169.55169
A17: =ELEC!C17 -> 43814 | B17: 8459 | C17: =B17-B16 -> 3 | D17: 115006 | E17: =SUM(D17-D16) -> 327 | F17: =IF(C17>0,E17/C17,0) -> 109 | H17: =H16 -> 8497 | I17: =IF(B17-H17<=0,"ok","oil change") -> ok | J17: 10553 | K17: =J17-J16 -> 0 | L17: 214152 | M17: =SUM(L17-L16) -> 0 | N17: =IF(K17>0,M17/K17,0) -> 0 | P17: =P16 -> 10873 | Q17: =IF(J17-P17<=0,"ok","oil change") -> ok | R17: 10878 | S17: =R17-R16 -> 1 | T17: 173641 | U17: =SUM(T17-T16) -> 59.2 | V17: =IF(S17>0,U17/S17,0) -> 59.2 | X17: =X16 -> 10989 | Y17: =IF(R17-X17<=0,"ok","oil change") -> ok | Z17: =C17+K17+S17 -> 4 | AA17: =U17+M17+E17 -> 386.2 | AB17: =V17+N17+F17 -> 168.2 | AC17: =IF(Z17>0,AA17/Z17,0) -> 96.55 | AD17: =ELEC!Q17 -> 3151 | AE17: =SUM(AD17/Z17) -> 787.75 | AF17: =SUM(AE17/1600) -> 0.49234375 | AG17: =SUM(320*AF17) -> 157.55 | AH17: =SUM(AC17-AG17) -> -61 | AI17: =AD17*AJ17 -> 811.01688 | AJ17: =305/1185 -> 0.25738397 | AK17: =IF(Z17>0,AI17/Z17,0) -> 202.75422
A18: =ELEC!C18 -> 43815 | B18: 8463 | C18: =B18-B17 -> 4 | D18: 115324 | E18: =SUM(D18-D17) -> 318 | F18: =IF(C18>0,E18/C18,0) -> 79.5 | H18: =H17 -> 8497 | I18: =IF(B18-H18<=0,"ok","oil change") -> ok | J18: 10553 | K18: =J18-J17 -> 0 | L18: =L17 -> 214152 | M18: =SUM(L18-L17) -> 0 | N18: =IF(K18>0,M18/K18,0) -> 0 | P18: =P17 -> 10873 | Q18: =IF(J18-P14<=0,"ok","oil change") -> ok | R18: 10878 | S18: =R18-R17 -> 0 | T18: =T17 -> 173641 | U18: =SUM(T18-T17) -> 0 | V18: =IF(S18>0,U18/S18,0) -> 0 | X18: =X17 -> 10989 | Y18: =IF(R18-X18<=0,"ok","oil change") -> ok | Z18: =C18+K18+S18 -> 4 | AA18: =U18+M18+E18 -> 318 | AB18: =V18+N18+F18 -> 79.5 | AC18: =IF(Z18>0,AA18/Z18,0) -> 79.5 | AD18: =ELEC!Q18 -> 1849 | AE18: =SUM(AD18/Z18) -> 462.25 | AF18: =SUM(AE18/1600) -> 0.28890625 | AG18: =SUM(320*AF18) -> 92.45 | AH18: =SUM(AC18-AG18) -> -12.95 | AI18: =AD18*AJ18 -> 475.90295 | AJ18: =305/1185 -> 0.25738397 | AK18: =IF(Z18>0,AI18/Z18,0) -> 118.97574
A19: =ELEC!C19 -> 43816 | B19: 8466 | C19: =B19-B18 -> 3 | D19: 115759 | E19: =SUM(D19-D18) -> 435 | F19: =IF(C19>0,E19/C19,0) -> 145 | H19: =H18 -> 8497 | I19: =IF(B19-H19<=0,"ok","oil change") -> ok | J19: 10553 | K19: =J19-J18 -> 0 | L19: 214152 | M19: =SUM(L19-L18) -> 0 | N19: =IF(K19>0,M19/K19,0) -> 0 | P19: =P18 -> 10873 | Q19: =IF(J19-P19<=0,"ok","oil change") -> ok | R19: 10878 | S19: =R19-R18 -> 0 | T19: 173816 | U19: =SUM(T19-T18) -> 175 | V19: =IF(S19>0,U19/S19,0) -> 0 | X19: =X18 -> 10989 | Y19: =IF(R19-X19<=0,"ok","oil change") -> ok | Z19: =C19+K19+S19 -> 3 | AA19: =U19+M19+E19 -> 610 | AB19: =V19+N19+F19 -> 145 | AC19: =IF(Z19>0,AA19/Z19,0) -> 203.33333 | AD19: =ELEC!Q19 -> 3213 | AE19: =SUM(AD19/Z19) -> 1071 | AF19: =SUM(AE19/1600) -> 0.669375 | AG19: =SUM(320*AF19) -> 214.2 | AH19: =SUM(AC19-AG19) -> -10.866667 | AI19: =AD19*AJ19 -> 826.97468 | AJ19: =305/1185 -> 0.25738397 | AK19: =IF(Z19>0,AI19/Z19,0) -> 275.65823
A20: =ELEC!C20 -> 43817 | B20: 8469 | C20: =B20-B19 -> 3 | D20: 115970 | E20: =SUM(D20-D19) -> 211 | F20: =IF(C20>0,E20/C20,0) -> 70.333333 | H20: =H19 -> 8497 | I20: =IF(B20-H20<=0,"ok","oil change") -> ok | J20: 10553 | K20: =J20-J19 -> 0 | L20: 214152 | M20: =SUM(L20-L19) -> 0 | N20: =IF(K20>0,M20/K20,0) -> 0 | P20: =P19 -> 10873 | Q20: =IF(J20-P20<=0,"ok","oil change") -> ok | R20: 10878 | S20: =R20-R19 -> 0 | T20: 173816 | U20: =SUM(T20-T19) -> 0 | V20: =IF(S20>0,U20/S20,0) -> 0 | X20: =X19 -> 10989 | Y20: =IF(R20-X20<=0,"ok","oil change") -> ok | Z20: =C20+K20+S20 -> 3 | AA20: =U20+M20+E20 -> 211 | AB20: =V20+N20+F20 -> 70.333333 | AC20: =IF(Z20>0,AA20/Z20,0) -> 70.333333 | AD20: =ELEC!Q20 -> 2255 | AE20: =SUM(AD20/Z20) -> 751.66667 | AF20: =SUM(AE20/1600) -> 0.46979167 | AG20: =SUM(320*AF20) -> 150.33333 | AH20: =SUM(AC20-AG20) -> -80 | AI20: =AD20*AJ20 -> 580.40084 | AJ20: =305/1185 -> 0.25738397 | AK20: =IF(Z20>0,AI20/Z20,0) -> 193.46695
A21: =ELEC!C21 -> 43818 | B21: 8472 | C21: =B21-B20 -> 3 | D21: 116568 | E21: =SUM(D21-D20) -> 598 | F21: =IF(C21>0,E21/C21,0) -> 199.33333 | H21: =H20 -> 8497 | I21: =IF(B21-H21<=0,"ok","oil change") -> ok | J21: 10553 | K21: =J21-J20 -> 0 | L21: 214152 | M21: =SUM(L21-L20) -> 0 | N21: =IF(K21>0,M21/K21,0) -> 0 | P21: =P20 -> 10873 | Q21: =IF(J21-P21<=0,"ok","oil change") -> ok | R21: 10879 | S21: =R21-R20 -> 1 | T21: 173882 | U21: =SUM(T21-T20) -> 66 | V21: =IF(S21>0,U21/S21,0) -> 66 | X21: =X20 -> 10989 | Y21: =Y20 -> ok | Z21: =C21+K21+S21 -> 4 | AA21: =U21+M21+E21 -> 664 | AB21: =V21+N21+F21 -> 265.33333 | AC21: =IF(Z21>0,AA21/Z21,0) -> 166 | AD21: =ELEC!Q21 -> 2093 | AE21: =SUM(AD21/Z21) -> 523.25 | AF21: =SUM(AE21/1600) -> 0.32703125 | AG21: =SUM(320*AF21) -> 104.65 | AH21: =SUM(AC21-AG21) -> 61.35 | AI21: =AD21*AJ21 -> 538.70464 | AJ21: =305/1185 -> 0.25738397 | AK21: =IF(Z21>0,AI21/Z21,0) -> 134.67616
A22: =ELEC!C22 -> 43819 | B22: 8475 | C22: =B22-B21 -> 3 | D22: 116865 | E22: =SUM(D22-D21) -> 297 | F22: =IF(C22>0,E22/C22,0) -> 99 | H22: =H21 -> 8497 | I22: =IF(B22-H22<=0,"ok","oil change") -> ok | J22: 10553 | K22: =J22-J21 -> 0 | L22: =L21 -> 214152 | M22: =SUM(L22-L21) -> 0 | N22: =IF(K22>0,M22/K22,0) -> 0 | P22: =P21 -> 10873 | Q22: =IF(J22-P22<=0,"ok","oil change") -> ok | R22: 10879 | S22: =R22-R21 -> 0 | T22: =T21 -> 173882 | U22: =SUM(T22-T21) -> 0 | V22: =IF(S22>0,U22/S22,0) -> 0 | X22: =X21 -> 10989 | Y22: =IF(R22-X22<=0,"ok","oil change") -> ok | Z22: =C22+K22+S22 -> 3 | AA22: =U22+M22+E22 -> 297 | AB22: =V22+N22+F22 -> 99 | AC22: =IF(Z22>0,AA22/Z22,0) -> 99 | AD22: =ELEC!Q22 -> 2674 | AE22: =SUM(AD22/Z22) -> 891.33333 | AF22: =SUM(AE22/1600) -> 0.55708333 | AG22: =SUM(320*AF22) -> 178.26667 | AH22: =SUM(AC22-AG22) -> -79.266667 | AI22: =AD22*AJ22 -> 688.24473 | AJ22: =305/1185 -> 0.25738397 | AK22: =IF(Z22>0,AI22/Z22,0) -> 229.41491
A23: =ELEC!C23 -> 43820 | B23: 8478.32 | C23: =B23-B22 -> 3.32 | D23: 117225.4 | E23: =SUM(D23-D22) -> 360.4 | F23: =IF(C23>0,E23/C23,0) -> 108.55422 | H23: =H22 -> 8497 | I23: =IF(B23-H23<=0,"ok","oil change") -> ok | J23: 10553.2 | K23: =J23-J22 -> 0.2 | L23: 214154.9 | M23: =SUM(L23-L22) -> 2.9 | N23: =IF(K23>0,M23/K23,0) -> 14.5 | P23: =P22 -> 10873 | Q23: =IF(J23-P23<=0,"ok","oil change") -> ok | R23: 10879.31 | S23: =R23-R22 -> 0.31 | T23: 174009.4 | U23: =SUM(T23-T22) -> 127.4 | V23: =IF(S23>0,U23/S23,0) -> 410.96774 | X23: =X22 -> 10989 | Y23: =IF(R23-X23<=0,"ok","oil change") -> ok | Z23: =C23+K23+S23 -> 3.83 | AA23: =U23+M23+E23 -> 490.7 | AB23: =V23+N23+F23 -> 534.02196 | AC23: =IF(Z23>0,AA23/Z23,0) -> 128.1201 | AD23: =ELEC!Q23 -> 2465 | AE23: =SUM(AD23/Z23) -> 643.60313 | AF23: =SUM(AE23/1600) -> 0.40225196 | AG23: =SUM(320*AF23) -> 128.72063 | AH23: =SUM(AC23-AG23) -> -0.60052219 | AI23: =AD23*AJ23 -> 634.45148 | AJ23: =305/1185 -> 0.25738397 | AK23: =IF(Z23>0,AI23/Z23,0) -> 165.65313
A24: =ELEC!C24 -> 43821 | B24: 8481 | C24: =B24-B23 -> 2.68 | D24: 117831.5 | E24: =SUM(D24-D23) -> 606.1 | F24: =IF(C24>0,E24/C24,0) -> 226.15672 | H24: =H23 -> 8497 | I24: =IF(B24-H24<=0,"ok","oil change") -> ok | J24: =J23 -> 10553.2 | K24: =J24-J23 -> 0 | L24: =L23 -> 214154.9 | M24: =SUM(L24-L23) -> 0 | N24: =IF(K24>0,M24/K24,0) -> 0 | P24: =P23 -> 10873 | Q24: =IF(J24-P24<=0,"ok","oil change") -> ok | R24: =R23 -> 10879.31 | S24: =R24-R23 -> 0 | T24: =T23 -> 174009.4 | U24: =SUM(T24-T23) -> 0 | V24: =IF(S24>0,U24/S24,0) -> 0 | X24: =X23 -> 10989 | Y24: =IF(R24-X24<=0,"ok","oil change") -> ok | Z24: =C24+K24+S24 -> 2.68 | AA24: =U24+M24+E24 -> 606.1 | AB24: =V24+N24+F24 -> 226.15672 | AC24: =IF(Z24>0,AA24/Z24,0) -> 226.15672 | AD24: =ELEC!Q24 -> 2014 | AE24: =SUM(AD24/Z24) -> 751.49254 | AF24: =SUM(AE24/1600) -> 0.46968284 | AG24: =SUM(320*AF24) -> 150.29851 | AH24: =SUM(AC24-AG24) -> 75.858209 | AI24: =AD24*AJ24 -> 518.37131 | AJ24: =305/1185 -> 0.25738397 | AK24: =IF(Z24>0,AI24/Z24,0) -> 193.42213
A25: =ELEC!C25 -> 43822 | B25: 8483 | C25: =B25-B24 -> 2 | D25: 118281.3 | E25: =SUM(D25-D24) -> 449.8 | F25: =IF(C25>0,E25/C25,0) -> 224.9 | H25: =H24 -> 8497 | I25: =IF(B25-H25<=0,"ok","oil change") -> ok | J25: 10555 | K25: =J25-J24 -> 1.8 | L25: 214396 | M25: =SUM(L25-L24) -> 241.1 | N25: =IF(K25>0,M25/K25,0) -> 133.94444 | P25: =P24 -> 10873 | Q25: =IF(J25-P25<=0,"ok","oil change") -> ok | R25: 10880 | S25: =R25-R24 -> 0.69 | T25: 174188 | U25: =SUM(T25-T24) -> 178.6 | V25: =IF(S25>0,U25/S25,0) -> 258.84058 | X25: =X24 -> 10989 | Y25: =IF(R25-X25<=0,"ok","oil change") -> ok | Z25: =C25+K25+S25 -> 4.49 | AA25: =U25+M25+E25 -> 869.5 | AB25: =V25+N25+F25 -> 617.68502 | AC25: =IF(Z25>0,AA25/Z25,0) -> 193.65256 | AD25: =ELEC!Q25 -> 3302 | AE25: =SUM(AD25/Z25) -> 735.41203 | AF25: =SUM(AE25/1600) -> 0.45963252 | AG25: =SUM(320*AF25) -> 147.08241 | AH25: =SUM(AC25-AG25) -> 46.570156 | AI25: =AD25*AJ25 -> 849.88186 | AJ25: =305/1185 -> 0.25738397 | AK25: =IF(Z25>0,AI25/Z25,0) -> 189.28326
A26: =ELEC!C26 -> 43823 | B26: 8483 | C26: =B26-B25 -> 0 | D26: 118303.8 | E26: =SUM(D26-D25) -> 22.5 | F26: =IF(C26>0,E26/C26,0) -> 0 | H26: =H25 -> 8497 | I26: =IF(B26-H26<=0,"ok","oil change") -> ok | J26: 10558.21 | K26: =J26-J25 -> 3.21 | L26: 214758.3 | M26: =SUM(L26-L25) -> 362.3 | N26: =IF(K26>0,M26/K26,0) -> 112.86604 | P26: =P25 -> 10873 | Q26: =IF(J26-P26<=0,"ok","oil change") -> ok | R26: =R25 -> 10880 | S26: =R26-R25 -> 0 | T26: =T25 -> 174188 | U26: =SUM(T26-T25) -> 0 | V26: =IF(S26>0,U26/S26,0) -> 0 | X26: =X25 -> 10989 | Y26: =IF(R26-X26<=0,"ok","oil change") -> ok | Z26: =C26+K26+S26 -> 3.21 | AA26: =U26+M26+E26 -> 384.8 | AB26: =V26+N26+F26 -> 112.86604 | AC26: =IF(Z26>0,AA26/Z26,0) -> 119.87539 | AD26: =ELEC!Q26 -> 1984 | AE26: =SUM(AD26/Z26) -> 618.06854 | AF26: =SUM(AE26/1600) -> 0.38629283 | AG26: =SUM(320*AF26) -> 123.61371 | AH26: =SUM(AC26-AG26) -> -3.7383178 | AI26: =AD26*AJ26 -> 510.64979 | AJ26: =305/1185 -> 0.25738397 | AK26: =IF(Z26>0,AI26/Z26,0) -> 159.08093
A27: =ELEC!C27 -> 43824 | B27: 8484.32 | C27: =B27-B26 -> 1.32 | D27: 118364.7 | E27: =SUM(D27-D26) -> 60.9 | F27: =IF(C27>0,E27/C27,0) -> 46.136364 | H27: =H26 -> 8497 | I27: =IF(B27-H27<=0,"ok","oil change") -> ok | J27: 10561 | K27: =J27-J26 -> 2.79 | L27: 215074 | M27: =SUM(L27-L26) -> 315.7 | N27: =IF(K27>0,M27/K27,0) -> 113.15412 | P27: =P26 -> 10873 | Q27: =IF(J27-P27<=0,"ok","oil change") -> ok | R27: 10880 | S27: =R27-R26 -> 0 | T27: =T26 -> 174188 | U27: =SUM(T27-T26) -> 0 | V27: =IF(S27>0,U27/S27,0) -> 0 | X27: =X26 -> 10989 | Y27: =IF(R27-X27<=0,"ok","oil change") -> ok | Z27: =C27+K27+S27 -> 4.11 | AA27: =U27+M27+E27 -> 376.6 | AB27: =V27+N27+F27 -> 159.29049 | AC27: =IF(Z27>0,AA27/Z27,0) -> 91.63017 | AD27: =ELEC!Q27 -> 3000 | AE27: =SUM(AD27/Z27) -> 729.92701 | AF27: =SUM(AE27/1600) -> 0.45620438 | AG27: =SUM(320*AF27) -> 145.9854 | AH27: =SUM(AC27-AG27) -> -54.355231 | AI27: =AD27*AJ27 -> 772.1519 | AJ27: =305/1185 -> 0.25738397 | AK27: =IF(Z27>0,AI27/Z27,0) -> 187.87151
A28: =ELEC!C28 -> 43825 | B28: 8484 | C28: =B28-B27 -> -0.32 | D28: 118411 | E28: =SUM(D28-D27) -> 46.3 | F28: =IF(C28>0,E28/C28,0) -> 0 | H28: =H27 -> 8497 | I28: =IF(B28-H28<=0,"ok","oil change") -> ok | J28: 10565 | K28: =J28-J27 -> 4 | L28: 215628 | M28: =SUM(L28-L27) -> 554 | N28: =IF(K28>0,M28/K28,0) -> 138.5 | P28: =P27 -> 10873 | Q28: =IF(J28-P28<=0,"ok","oil change") -> ok | R28: 10881 | S28: =R28-R27 -> 1 | T28: 174478 | U28: =SUM(T28-T27) -> 290 | V28: =IF(S28>0,U28/S28,0) -> 290 | X28: =X27 -> 10989 | Y28: =IF(R28-X28<=0,"ok","oil change") -> ok | Z28: =C28+K28+S28 -> 4.68 | AA28: =U28+M28+E28 -> 890.3 | AB28: =V28+N28+F28 -> 428.5 | AC28: =IF(Z28>0,AA28/Z28,0) -> 190.23504 | AD28: =ELEC!Q28 -> 3177 | AE28: =SUM(AD28/Z28) -> 678.84615 | AF28: =SUM(AE28/1600) -> 0.42427885 | AG28: =SUM(320*AF28) -> 135.76923 | AH28: =SUM(AC28-AG28) -> 54.465812 | AI28: =AD28*AJ28 -> 817.70886 | AJ28: =305/1185 -> 0.25738397 | AK28: =IF(Z28>0,AI28/Z28,0) -> 174.72412
A29: =ELEC!C29 -> 43826 | B29: 8485 | C29: =B29-B28 -> 1 | D29: 118482 | E29: =SUM(D29-D28) -> 71 | F29: =IF(C29>0,E29/C29,0) -> 71 | H29: =H28 -> 8497 | I29: =IF(B29-H29<=0,"ok","oil change") -> ok | J29: 10571 | K29: =J29-J28 -> 6 | L29: 216723 | M29: =SUM(L29-L28) -> 1095 | N29: =IF(K29>0,M29/K29,0) -> 182.5 | P29: =P28 -> 10873 | Q29: =IF(J29-P29<=0,"ok","oil change") -> ok | R29: 10882.35 | S29: =R29-R28 -> 1.35 | T29: 174781 | U29: =SUM(T29-T28) -> 303 | V29: =IF(S29>0,U29/S29,0) -> 224.44444 | X29: =X28 -> 10989 | Y29: =IF(R29-X29<=0,"ok","oil change") -> ok | Z29: =C29+K29+S29 -> 8.35 | AA29: =U29+M29+E29 -> 1469 | AB29: =V29+N29+F29 -> 477.94444 | AC29: =IF(Z29>0,AA29/Z29,0) -> 175.92814 | AD29: =ELEC!Q29 -> 3823 | AE29: =SUM(AD29/Z29) -> 457.84431 | AF29: =SUM(AE29/1600) -> 0.28615269 | AG29: =SUM(320*AF29) -> 91.568862 | AH29: =SUM(AC29-AG29) -> 84.359281 | AI29: =AD29*AJ29 -> 983.9789 | AJ29: =305/1185 -> 0.25738397 | AK29: =IF(Z29>0,AI29/Z29,0) -> 117.84178
A30: =ELEC!C30 -> 43827 | B30: =B29 -> 8485 | C30: =B30-B29 -> 0 | D30: =D29 -> 118482 | E30: =SUM(D30-D29) -> 0 | F30: =IF(C30>0,E30/C30,0) -> 0 | H30: =H29 -> 8497 | I30: =IF(B30-H30<=0,"ok","oil change") -> ok | J30: 10575 | K30: =J30-J29 -> 4 | L30: 217060.8 | M30: =SUM(L30-L29) -> 337.8 | N30: =IF(K30>0,M30/K30,0) -> 84.45 | P30: =P29 -> 10873 | Q30: =IF(J30-P30<=0,"ok","oil change") -> ok | R30: =R29 -> 10882.35 | S30: =R30-R29 -> 0 | T30: =T29 -> 174781 | U30: =SUM(T30-T29) -> 0 | V30: =IF(S30>0,U30/S30,0) -> 0 | X30: =X29 -> 10989 | Y30: =IF(R30-X30<=0,"ok","oil change") -> ok | Z30: =C30+K30+S30 -> 4 | AA30: =U30+M30+E30 -> 337.8 | AB30: =V30+N30+F30 -> 84.45 | AC30: =IF(Z30>0,AA30/Z30,0) -> 84.45 | AD30: =ELEC!Q30 -> 3000 | AE30: =SUM(AD30/Z30) -> 750 | AF30: =SUM(AE30/1600) -> 0.46875 | AG30: =SUM(320*AF30) -> 150 | AH30: =SUM(AC30-AG30) -> -65.55 | AI30: =AD30*AJ30 -> 772.1519 | AJ30: =305/1185 -> 0.25738397 | AK30: =IF(Z30>0,AI30/Z30,0) -> 193.03797
A31: =ELEC!C31 -> 43828 | B31: 8485 | C31: =B31-B30 -> 0 | D31: 118538 | E31: =SUM(D31-D30) -> 56 | F31: =IF(C31>0,E31/C31,0) -> 0 | H31: =H30 -> 8497 | I31: =IF(B31-H31<=0,"ok","oil change") -> ok | J31: 10579 | K31: =J31-J30 -> 4 | L31: 217642 | M31: =SUM(L31-L30) -> 581.2 | N31: =IF(K31>0,M31/K31,0) -> 145.3 | P31: =P30 -> 10873 | Q31: =IF(J31-P31<=0,"ok","oil change") -> ok | R31: 10883 | S31: =R31-R30 -> 0.65 | T31: 174951.6 | U31: =SUM(T31-T30) -> 170.6 | V31: =IF(S31>0,U31/S31,0) -> 262.46154 | X31: =X30 -> 10989 | Y31: =IF(R31-X31<=0,"ok","oil change") -> ok | Z31: =C31+K31+S31 -> 4.65 | AA31: =U31+M31+E31 -> 807.8 | AB31: =V31+N31+F31 -> 407.76154 | AC31: =IF(Z31>0,AA31/Z31,0) -> 173.72043 | AD31: =ELEC!Q31 -> 3678 | AE31: =SUM(AD31/Z31) -> 790.96774 | AF31: =SUM(AE31/1600) -> 0.49435484 | AG31: =SUM(320*AF31) -> 158.19355 | AH31: =SUM(AC31-AG31) -> 15.526882 | AI31: =AD31*AJ31 -> 946.65823 | AJ31: =305/1185 -> 0.25738397 | AK31: =IF(Z31>0,AI31/Z31,0) -> 203.58241
A32: =ELEC!C32 -> 43829 | B32: =B31 -> 8485 | C32: =B32-B31 -> 0 | D32: =D31 -> 118538 | E32: =SUM(D32-D31) -> 0 | F32: =IF(C32>0,E32/C32,0) -> 0 | H32: =H31 -> 8497 | I32: =IF(B32-H32<=0,"ok","oil change") -> ok | J32: 10583 | K32: =J32-J31 -> 4 | L32: 218125.9 | M32: =SUM(L32-L31) -> 483.9 | N32: =IF(K32>0,M32/K32,0) -> 120.975 | P32: =P31 -> 10873 | Q32: =IF(J32-P32<=0,"ok","oil change") -> ok | R32: =R31 -> 10883 | S32: =R32-R31 -> 0 | T32: =T31 -> 174951.6 | U32: =SUM(T32-T31) -> 0 | V32: =IF(S32>0,U32/S32,0) -> 0 | X32: =X31 -> 10989 | Y32: =IF(R32-X32<=0,"ok","oil change") -> ok | Z32: =C32+K32+S32 -> 4 | AA32: =U32+M32+E32 -> 483.9 | AB32: =V32+N32+F32 -> 120.975 | AC32: =IF(Z32>0,AA32/Z32,0) -> 120.975 | AD32: =ELEC!Q32 -> 3027 | AE32: =SUM(AD32/Z32) -> 756.75 | AF32: =SUM(AE32/1600) -> 0.47296875 | AG32: =SUM(320*AF32) -> 151.35 | AH32: =SUM(AC32-AG32) -> -30.375 | AI32: =AD32*AJ32 -> 779.10127 | AJ32: =305/1185 -> 0.25738397 | AK32: =IF(Z32>0,AI32/Z32,0) -> 194.77532
A33: =ELEC!C33 -> 43830 | B33: 8486 | C33: =B33-B32 -> 1 | D33: 118621.7 | E33: =SUM(D33-D32) -> 83.7 | F33: =IF(C33>0,E33/C33,0) -> 83.7 | H33: =H32 -> 8497 | I33: =IF(B33-H33<=0,"ok","oil change") -> ok | J33: 10588 | K33: =J33-J32 -> 5 | L33: 218633 | M33: =SUM(L33-L32) -> 507.1 | N33: =IF(K33>0,M33/K33,0) -> 101.42 | P33: =P32 -> 10873 | Q33: =IF(J33-P33<=0,"ok","oil change") -> ok | R33: 10884 | S33: =R33-R32 -> 1 | T33: 175184.2 | U33: =SUM(T33-T32) -> 232.6 | V33: =IF(S33>0,U33/S33,0) -> 232.6 | X33: =X32 -> 10989 | Y33: =IF(R33-X33<=0,"ok","oil change") -> ok | Z33: =C33+K33+S33 -> 7 | AA33: =U33+M33+E33 -> 823.4 | AB33: =V33+N33+F33 -> 417.72 | AC33: =IF(Z33>0,AA33/Z33,0) -> 117.62857 | AD33: =ELEC!Q33 -> 3495 | AE33: =SUM(AD33/Z33) -> 499.28571 | AF33: =SUM(AE33/1600) -> 0.31205357 | AG33: =SUM(320*AF33) -> 99.857143 | AH33: =SUM(AC33-AG33) -> 17.771429 | AI33: =AD33*AJ33 -> 899.55696 | AJ33: =305/1185 -> 0.25738397 | AK33: =IF(Z33>0,AI33/Z33,0) -> 128.50814
P34: =+O34/3 -> 0 | U34: =SUM(C35:S35) -> 120.31 | X34: 341 | Z34: =SUM(Z3:Z33) -> 120.31
C35: =SUM(C3:C33) -> 64 | K35: =SUM(K3:K33) -> 34.8 | S35: =SUM(S3:S33) -> 21.51

Sheet WATER
D1: =SUM(G21:G35) -> 8758981 | AR1: Entrance | AT1: Tank 1 | AV1: Tank 2
AR2: Level | AW2: Quantity CM3 | AZ2: Var
A3: Date | B3: Truck | C3: Truck M3/day | D3: N0. Trucks | F3: REQ. # of trucks | G3: City | H3: City/day | I3: Total water delivery | K3: SW | L3: Cosum SW/day | M3: RO Guest/ Liter | O3: RO K&L/ Liter | Q3: TOTAL RO Production | R3: RO 1 RH | S3: RO 2 RH | T3: RO water counter | U3: RO Cons m3 | V3: Steam Boiler | W3: Steam Boiler/day | X3: Softener Guest | Y3: Guest Sotf/day | Z3: Softener K&L | AA3: K&L Soft/Day | AB3: Fire Tank Level | AC3: Fire Tank Counter | AE3: Laundry Hot Water Counter | AF3: Hot Water Cons/day | AG3: Laundry Cold Water Counter | AH3: Cold Water Cons/day | AI3: Laundry Water Total Cons | AJ3: K&L Sotf/day | AK3: Guest / day | AL3: K&L /day | AM3: Avg Outside Temp | AN3: Banquet Activity | AR3: Date | AT3: MainI | AV3: Kitchen and Laundry | AX3: Guest | AY3: Main Tank | AZ3: Kitchen and Laundry | BA3: Guest | BB3: Kitchen and Laundry | BC3: Main | BD3: Guest | BE3: Total VAR | BF3: Hotel Consumption
E4: 1.66 | AN4: Ball R | AO4: Meeting | AP4: outlet | AT4: 180 | AV4: 220 | AX4: 580 | AY4: =SUM(AT4) -> 180 | AZ4: =SUM(AV4) -> 220 | BA4: =SUM(AX4) -> 580
A5: 43769 | B5: 107530 | C5: =[1]WATER!C35 -> 80 | D5: =[1]WATER!D35 -> 2.962963 | E5: =[1]WATER!E35 -> 382.8 | F5: =[1]WATER!F35 -> 3 | G5: =[1]WATER!G35 -> 581929 | H5: =[1]WATER!H35 -> 0 | I5: =[1]WATER!I35 -> 80 | J5: =[1]WATER!J35 -> 4.785 | K5: 0 | L5: =[1]WATER!L35 -> 4 | M5: =[1]WATER!M35 -> 457.44 | N5: =[1]WATER!N35 -> 0 | O5: =[1]WATER!O35 -> 529.52 | P5: =[1]WATER!P35 -> 0 | Q5: =[1]WATER!Q35 -> 0 | R5: =[1]WATER!R35 -> 0 | S5: =[1]WATER!S35 -> 0 | ... BG5: =[1]WATER!BG35 -> -7.1
A6: =ELEC!C3 -> 43800 | B6: 107530 | C6: =B6-B5 -> 0 | D6: =C6/27 -> 0 | E6: =SUM((C6*$E$4)+(7500/'EDl log'!$A$38)) -> 241.93548 | G6: 582084 | H6: =G6-G5 -> 155 | I6: =C6+H6 -> 155 | J6: =IF(I6>0,E6/I6,0) -> 1.5608741 | K6: ='Swimming Pool quality check '!H6 -> 5644 | L6: 0 | M6: =M5 -> 457.44 | N6: =SUM(M6-M5) -> 0 | O6: =O5 -> 529.52 | P6: =SUM(O6-O5) -> 0 | Q6: =P6+N6 -> 0 | T6: 4188 | U6: =SUM(T6-T5) -> 7 | V6: 292 | W6: =+V6-V5 -> 0 | X6: 137041 | Y6: =SUM(X6-X5) -> 113 | Z6: 89400 | AA6: =Z6-Z5 -> 35 | AB6: =AB5 -> 255 | AC6: =AC5 -> 670 | AD6: 0 | AE6: 26.87 | AF6: =AE6-AE5 -> 7.1 | AG6: 661.65 | AH6: =AG6-AG5 -> 2.24 | AI6: =AF6+AH6 -> 9.34 | AJ6: =+Z6-Z5 -> 35 | AK6: =SUM(Y6-L6) -> 113 | AL6: =SUM(AJ6-W6) -> 35 | AM6: ='General information '!D6 -> 17.5 | AN6: ='General information '!H6 -> 0 | AP6: ='General information '!J6 -> 290 | AR6: =A6 -> 43800 | AS6: =AS5 -> 0.9 | AT6: 89 | AU6: =AU5 -> 1.1 | AV6: 66 | AW6: 2.9 | AX6: 69 | AY6: =AS6*AT6 -> 80.1 | AZ6: =AU6*AV6 -> 72.6 | BA6: =AW6*AX6 -> 200.1 | BB6: =AY6-AY5 -> -36.9 | BC6: =AZ6-AZ5 -> 2.2 | BD6: =BA6-BA5 -> 63.8 | BE6: =SUM(BB6:BD6) -> 29.1 | BF6: =SUM(I6-BE6) -> 125.9 | BG6: =SUM(I6-BF6) -> 29.1
A7: =ELEC!C4 -> 43801 | B7: 107530 | C7: =B7-B6 -> 0 | D7: =C7/27 -> 0 | E7: =SUM((C7*$E$4)+(7500/'EDl log'!$A$38)) -> 241.93548 | G7: 582084 | H7: =G7-G6 -> 0 | I7: =C7+H7 -> 0 | J7: =IF(I7>0,E7/I7,0) -> 0 | K7: ='Swimming Pool quality check '!H7 -> 5648 | L7: =K7-K6 -> 4 | M7: =M6 -> 457.44 | N7: =SUM(M7-M6) -> 0 | O7: =O6 -> 529.52 | P7: =SUM(O7-O6) -> 0 | Q7: =P7+N7 -> 0 | T7: 4190 | U7: =SUM(T7-T6) -> 2 | V7: 293 | W7: =+V7-V6 -> 1 | X7: 137068 | Y7: =SUM(X7-X6) -> 27 | Z7: 89421 | AA7: =Z7-Z6 -> 21 | AB7: =AB6 -> 255 | AC7: =AC6 -> 670 | AD7: =AC7-AC6 -> 0 | AE7: 27.48 | AF7: =AE7-AE6 -> 0.61 | AG7: 668.1 | AH7: =AG7-AG6 -> 6.45 | AI7: =AF7+AH7 -> 7.06 | AJ7: =+Z7-Z6 -> 21 | AK7: =SUM(Y7-L7) -> 23 | AL7: =SUM(AJ7-W7) -> 20 | AM7: ='General information '!D7 -> 18.5 | AN7: ='General information '!H7 -> 0 | AP7: ='General information '!J7 -> 145 | AR7: =A7 -> 43801 | AS7: =AS6 -> 0.9 | AT7: 52 | AU7: =AU6 -> 1.1 | AV7: 59 | AW7: 2.9 | AX7: 67 | AY7: =AS7*AT7 -> 46.8 | AZ7: =AU7*AV7 -> 64.9 | BA7: =AW7*AX7 -> 194.3 | BB7: =AY7-AY6 -> -33.3 | BC7: =AZ7-AZ6 -> -7.7 | BD7: =BA7-BA6 -> -5.8 | BE7: =SUM(BB7:BD7) -> -46.8 | BF7: =SUM(I7-BE7) -> 46.8 | BG7: =SUM(I7-BF7) -> -46.8
A8: =ELEC!C5 -> 43802 | B8: 107617 | C8: =B8-B7 -> 87 | D8: =C8/27 -> 3.2222222 | E8: =SUM((C8*$E$4)+(7500/'EDl log'!$A$38)) -> 386.35548 | G8: 582263 | H8: =G8-G7 -> 179 | I8: =C8+H8 -> 266 | J8: =IF(I8>0,E8/I8,0) -> 1.4524642 | K8: ='Swimming Pool quality check '!H8 -> 5651 | L8: =K8-K7 -> 3 | M8: =M7 -> 457.44 | N8: =SUM(M8-M7) -> 0 | O8: =O7 -> 529.52 | P8: =SUM(O8-O7) -> 0 | Q8: =P8+N8 -> 0 | T8: 4194 | U8: =SUM(T8-T7) -> 4 | V8: 293 | W8: =+V8-V7 -> 0 | X8: 137172 | Y8: =SUM(X8-X7) -> 104 | Z8: 89499 | AA8: =Z8-Z7 -> 78 | AB8: =AB7 -> 255 | AC8: =AC7 -> 670 | AD8: =AC8-AC7 -> 0 | AE8: 29.37 | AF8: =AE8-AE7 -> 1.89 | AG8: 692.14 | AH8: =AG8-AG7 -> 24.04 | AI8: =AF8+AH8 -> 25.93 | AJ8: =+Z8-Z7 -> 78 | AK8: =SUM(Y8-L8) -> 101 | AL8: =SUM(AJ8-W8) -> 78 | AM8: ='General information '!D8 -> 19 | AN8: ='General information '!H8 -> 0 | AP8: ='General information '!J8 -> 97 | AR8: =A8 -> 43802 | AS8: =AS7 -> 0.9 | AT8: 40 | AU8: 1.1 | AV8: 78 | AW8: 2.9 | AX8: 84 | AY8: =AS8*AT8 -> 36 | AZ8: =AU8*AV8 -> 85.8 | BA8: =AW8*AX8 -> 243.6 | BB8: =AY8-AY7 -> -10.8 | BC8: =AZ8-AZ7 -> 20.9 | BD8: =BA8-BA7 -> 49.3 | BE8: =SUM(BB8:BD8) -> 59.4 | BF8: =SUM(I8-BE8) -> 206.6 | BG8: =SUM(I8-BF8) -> 59.4
A9: =ELEC!C6 -> 43803 | B9: 107617 | C9: =B9-B8 -> 0 | D9: =C9/27 -> 0 | E9: =SUM((C9*$E$4)+(7500/'EDl log'!$A$38)) -> 241.93548 | G9: 582263 | H9: =G9-G8 -> 0 | I9: =C9+H9 -> 0 | J9: =IF(I9>0,E9/I9,0) -> 0 | K9: ='Swimming Pool quality check '!H9 -> 5653 | L9: =K9-K8 -> 2 | M9: =M8 -> 457.44 | N9: =SUM(M9-M8) -> 0 | O9: =O8 -> 529.52 | P9: =SUM(O9-O8) -> 0 | Q9: =P9+N9 -> 0 | T9: 4198 | U9: =SUM(T9-T8) -> 4 | V9: 293 | W9: =+V9-V8 -> 0 | X9: 137173 | Y9: =SUM(X9-X8) -> 1 | Z9: 89499 | AA9: =Z9-Z8 -> 0 | AB9: =AB8 -> 255 | AC9: =AC8 -> 670 | AD9: =AC9-AC8 -> 0 | AE9: 29.37 | AF9: =AE9-AE8 -> 0 | AG9: 694.61 | AH9: =AG9-AG8 -> 2.47 | AI9: =AF9+AH9 -> 2.47 | AJ9: =+Z9-Z8 -> 0 | AK9: =SUM(Y9-L9) -> -1 | AL9: =SUM(AJ9-W9) -> 0 | AM9: ='General information '!D9 -> 15.5 | AN9: ='General information '!H9 -> 0 | AP9: ='General information '!J9 -> 143 | AR9: =A9 -> 43803 | AS9: =AS8 -> 0.9 | AT9: 26 | AU9: =AU8 -> 1.1 | AV9: 61 | AW9: 2.9 | AX9: 74 | AY9: =AS9*AT9 -> 23.4 | AZ9: =AU9*AV9 -> 67.1 | BA9: =AW9*AX9 -> 214.6 | BB9: =AY9-AY8 -> -12.6 | BC9: =AZ9-AZ8 -> -18.7 | BD9: =BA9-BA8 -> -29 | BE9: =SUM(BB9:BD9) -> -60.3 | BF9: =SUM(I9-BE9) -> 60.3 | BG9: =SUM(I9-BF9) -> -60.3
A10: =ELEC!C7 -> 43804 | B10: 107617 | C10: =B10-B9 -> 0 | D10: =C10/27 -> 0 | E10: =SUM((C10*$E$4)+(7500/'EDl log'!$A$38)) -> 241.93548 | G10: 582452 | H10: =G10-G9 -> 189 | I10: =C10+H10 -> 189 | J10: =IF(I10>0,E10/I10,0) -> 1.2800819 | K10: ='Swimming Pool quality check '!H10 -> 5657 | L10: =K10-K9 -> 4 | M10: =M9 -> 457.44 | N10: =SUM(M10-M9) -> 0 | O10: =O9 -> 529.52 | P10: =SUM(O10-O9) -> 0 | Q10: =P10+N10 -> 0 | T10: 4201 | U10: =SUM(T10-T9) -> 3 | V10: 293 | W10: =+V10-V9 -> 0 | X10: 137184 | Y10: =SUM(X10-X9) -> 11 | Z10: 89537 | AA10: =Z10-Z9 -> 38 | AB10: =AB9 -> 255 | AC10: =AC9 -> 670 | AD10: =AC10-AC9 -> 0 | AE10: 29.37 | AF10: =AE10-AE9 -> 0 | AG10: 696.18 | AH10: =AG10-AG9 -> 1.57 | AI10: =AF10+AH10 -> 1.57 | AJ10: =+Z10-Z9 -> 38 | AK10: =SUM(Y10-L10) -> 7 | AL10: =SUM(AJ10-W10) -> 38 | AM10: ='General information '!D10 -> 14.5 | AN10: ='General information '!H10 -> 0 | AP10: ='General information '!J10 -> 219 | AR10: =A10 -> 43804 | AS10: =AS9 -> 0.9 | AT10: 99 | AU10: =AU9 -> 1.1 | AV10: 77 | AW10: 2.9 | AX10: 65 | AY10: =AS10*AT10 -> 89.1 | AZ10: =AU10*AV10 -> 84.7 | BA10: =AW10*AX10 -> 188.5 | BB10: =AY10-AY9 -> 65.7 | BC10: =AZ10-AZ9 -> 17.6 | BD10: =BA10-BA9 -> -26.1 | BE10: =SUM(BB10:BD10) -> 57.2 | BF10: =SUM(I10-BE10) -> 131.8 | BG10: =SUM(I10-BF10) -> 57.2
A11: =ELEC!C8 -> 43805 | B11: =B10 -> 107617 | C11: =B11-B10 -> 0 | D11: =C11/27 -> 0 | E11: =SUM((C11*$E$4)+(7500/'EDl log'!$A$38)) -> 241.93548 | G11: =G10 -> 582452 | H11: =G11-G10 -> 0 | I11: =C11+H11 -> 0 | J11: =IF(I11>0,E11/I11,0) -> 0 | K11: ='Swimming Pool quality check '!H11 -> 5666 | L11: =K11-K10 -> 9 | M11: =M10 -> 457.44 | N11: =SUM(M11-M10) -> 0 | O11: =O10 -> 529.52 | P11: =SUM(O11-O10) -> 0 | Q11: =SUM(P11+N11) -> 0 | T11: 4205 | U11: =SUM(T11-T10) -> 4 | V11: 294 | W11: =+V11-V10 -> 1 | X11: 137212 | Y11: =SUM(X11-X10) -> 28 | Z11: 89552 | AA11: =Z11-Z10 -> 15 | AB11: 253 | AC11: =AC10 -> 670 | AD11: =AC11-AC10 -> 0 | AE11: 31.02 | AF11: =AE11-AE10 -> 1.65 | AG11: 704.72 | AH11: =AG11-AG10 -> 8.54 | AI11: =AF11+AH11 -> 10.19 | AJ11: =+Z11-Z10 -> 15 | AK11: =SUM(Y11-L11) -> 19 | AL11: =SUM(AJ11-W11) -> 14 | AM11: ='General information '!D11 -> 14.5 | AN11: ='General information '!H11 -> 0 | AP11: ='General information '!J11 -> 300 | AR11: =A11 -> 43805 | AS11: =AS10 -> 0.9 | AT11: 49 | AU11: =AU10 -> 1.1 | AV11: 54 | AW11: 2.9 | AX11: 64 | AY11: =AS11*AT11 -> 44.1 | AZ11: =AU11*AV11 -> 59.4 | BA11: =AW11*AX11 -> 185.6 | BB11: =AY11-AY10 -> -45 | BC11: =AZ11-AZ10 -> -25.3 | BD11: =BA11-BA10 -> -2.9 | BE11: =SUM(BB11:BD11) -> -73.2 | BF11: =SUM(I11-BE11) -> 73.2 | BG11: =SUM(I11-BF11) -> -73.2
A12: =ELEC!C9 -> 43806 | B12: 107617 | C12: =B12-B11 -> 0 | D12: =C12/27 -> 0 | E12: =SUM((C12*$E$4)+(7500/'EDl log'!$A$38)) -> 241.93548 | G12: 582610 | H12: =G12-G11 -> 158 | I12: =C12+H12 -> 158 | J12: =IF(I12>0,E12/I12,0) -> 1.5312372 | K12: ='Swimming Pool quality check '!H12 -> 5669 | L12: =K12-K11 -> 3 | M12: =M11 -> 457.44 | N12: =SUM(M12-M11) -> 0 | O12: =O11 -> 529.52 | P12: =SUM(O12-O11) -> 0 | Q12: =SUM(P12+N12) -> 0 | T12: 4209 | U12: =SUM(T12-T11) -> 4 | V12: =V11 -> 294 | W12: =+V12-V11 -> 0 | X12: 137245 | Y12: =SUM(X12-X11) -> 33 | Z12: 89609 | AA12: =Z12-Z11 -> 57 | AB12: =AB11 -> 253 | AC12: =AC11 -> 670 | AD12: =AC12-AC11 -> 0 | AE12: 33.46 | AF12: =AE12-AE11 -> 2.44 | AG12: 725.6 | AH12: =AG12-AG11 -> 20.88 | AI12: =AF12+AH12 -> 23.32 | AJ12: =+Z12-Z11 -> 57 | AK12: =SUM(Y12-L12) -> 30 | AL12: =SUM(AJ12-W12) -> 57 | AM12: ='General information '!D12 -> 16.5 | AN12: ='General information '!H12 -> 0 | AP12: ='General information '!J12 -> 0 | AR12: =A12 -> 43806 | AS12: =AS11 -> 0.9 | AT12: 75 | AU12: =AU11 -> 1.1 | AV12: 59 | AW12: 2.9 | AX12: 56 | AY12: =AS12*AT12 -> 67.5 | AZ12: =AU12*AV12 -> 64.9 | BA12: =AW12*AX12 -> 162.4 | BB12: =AY12-AY11 -> 23.4 | BC12: =AZ12-AZ11 -> 5.5 | BD12: =BA12-BA11 -> -23.2 | BE12: =SUM(BB12:BD12) -> 5.7 | BF12: =SUM(I12-BE12) -> 152.3 | BG12: =SUM(I12-BF12) -> 5.7
A13: =ELEC!C10 -> 43807 | B13: 107697 | C13: =B13-B12 -> 80 | D13: =C13/27 -> 2.962963 | E13: =SUM((C13*$E$4)+(7500/'EDl log'!$A$38)) -> 374.73548 | G13: =G12 -> 582610 | H13: =G13-G12 -> 0 | I13: =C13+H13 -> 80 | J13: =IF(I13>0,E13/I13,0) -> 4.6841935 | K13: ='Swimming Pool quality check '!H13 -> 5672 | L13: =K13-K12 -> 3 | M13: =M12 -> 457.44 | N13: =SUM(M13-M12) -> 0 | O13: =O12 -> 529.52 | P13: =SUM(O13-O12) -> 0 | Q13: =SUM(P13+N13) -> 0 | T13: 4218 | U13: =SUM(T13-T12) -> 9 | V13: 295 | W13: =+V13-V12 -> 1 | X13: 137325 | Y13: =SUM(X13-X12) -> 80 | Z13: 89653 | AA13: =Z13-Z12 -> 44 | AB13: =AB12 -> 253 | AC13: =AC12 -> 670 | AD13: =AC13-AC12 -> 0 | AE13: =AE12 -> 33.46 | AF13: =AE13-AE12 -> 0 | AG13: 727.54 | AH13: =AG13-AG12 -> 1.94 | AI13: =AF13+AH13 -> 1.94 | AJ13: =+Z13-Z12 -> 44 | AK13: =SUM(Y13-L13) -> 77 | AL13: =SUM(AJ13-W13) -> 43 | AM13: ='General information '!D13 -> 16 | AN13: ='General information '!J13 -> 299 | AP13: ='General information '!J13 -> 299 | AR13: =A13 -> 43807 | AS13: =AS12 -> 0.9 | AT13: 18 | AU13: =AU12 -> 1.1 | AV13: 67 | AW13: 2.9 | AX13: 68 | AY13: =AS13*AT13 -> 16.2 | AZ13: =AU13*AV13 -> 73.7 | BA13: =AW13*AX13 -> 197.2 | BB13: =AY13-AY12 -> -51.3 | BC13: =AZ13-AZ12 -> 8.8 | BD13: =BA13-BA12 -> 34.8 | BE13: =SUM(BB13:BD13) -> -7.7 | BF13: =SUM(I13-BE13) -> 87.7 | BG13: =SUM(I13-BF13) -> -7.7
A14: =ELEC!C11 -> 43808 | B14: 107778 | C14: =B14-B13 -> 81 | D14: =C14/27 -> 3 | E14: =SUM((C14*$E$4)+(7500/'EDl log'!$A$38)) -> 376.39548 | G14: 582653 | H14: =G14-G13 -> 43 | I14: =C14+H14 -> 124 | J14: =IF(I14>0,E14/I14,0) -> 3.0354475 | K14: ='Swimming Pool quality check '!H14 -> 5675 | L14: =K14-K13 -> 3 | M14: =M13 -> 457.44 | N14: =SUM(M14-M13) -> 0 | O14: =O13 -> 529.52 | P14: =SUM(O14-O13) -> 0 | Q14: =SUM(P14+N14) -> 0 | T14: 4222 | U14: =SUM(T14-T13) -> 4 | V14: 295 | W14: =+V14-V13 -> 0 | X14: 137403 | Y14: =SUM(X14-X13) -> 78 | Z14: 89712 | AA14: =Z14-Z13 -> 59 | AB14: =AB13 -> 253 | AC14: =AC13 -> 670 | AD14: =AC14-AC13 -> 0 | AE14: =AE13 -> 33.46 | AF14: =AE14-AE13 -> 0 | AG14: =AG13 -> 727.54 | AH14: =AG14-AG13 -> 0 | AI14: =AF14+AH14 -> 0 | AJ14: =+Z14-Z13 -> 59 | AK14: =SUM(Y14-L14) -> 75 | AL14: =SUM(AJ14-W14) -> 59 | AM14: ='General information '!D14 -> 16 | AN14: ='General information '!H14 -> 0 | AP14: ='General information '!J14 -> 165 | AR14: =A14 -> 43808 | AS14: =AS13 -> 0.9 | AT14: 65 | AU14: =AU13 -> 1.1 | AV14: 95 | AW14: 2.9 | AX14: 79 | AY14: =AS14*AT14 -> 58.5 | AZ14: =AU14*AV14 -> 104.5 | BA14: =AW14*AX14 -> 229.1 | BB14: =AY14-AY13 -> 42.3 | BC14: =AZ14-AZ13 -> 30.8 | BD14: =BA14-BA13 -> 31.9 | BE14: =SUM(BB14:BD14) -> 105 | BF14: =SUM(I14-BE14) -> 19 | BG14: =SUM(I14-BF14) -> 105
A15: =ELEC!C12 -> 43809 | B15: 107778 | C15: =B15-B14 -> 0 | D15: =C15/27 -> 0 | E15: =SUM((C15*$E$4)+(7500/'EDl log'!$A$38)) -> 241.93548 | G15: 582653 | H15: =G15-G14 -> 0 | I15: =C15+H15 -> 0 | J15: =IF(I15>0,E15/I15,0) -> 0 | K15: ='Swimming Pool quality check '!H15 -> 5680 | L15: =K15-K14 -> 5 | M15: =M14 -> 457.44 | N15: =SUM(M15-M14) -> 0 | O15: =O14 -> 529.52 | P15: =SUM(O15-O14) -> 0 | Q15: =SUM(P15+N15) -> 0 | T15: 4228 | U15: =SUM(T15-T14) -> 6 | V15: 298 | W15: =+V15-V14 -> 3 | X15: 137422 | Y15: =SUM(X15-X14) -> 19 | Z15: 89722 | AA15: =Z15-Z14 -> 10 | AB15: =AB14 -> 253 | AC15: =AC14 -> 670 | AD15: =AC15-AC14 -> 0 | AE15: =AE14 -> 33.46 | AF15: =AE15-AE14 -> 0 | AG15: =AG14 -> 727.54 | AH15: =AG15-AG14 -> 0 | AI15: =AF15+AH15 -> 0 | AJ15: =+Z15-Z14 -> 10 | AK15: =SUM(Y15-L15) -> 14 | AL15: =SUM(AJ15-W15) -> 7 | AM15: ='General information '!D15 -> 16 | AN15: ='General information '!H15 -> 0 | AP15: ='General information '!J15 -> 153 | AR15: =A15 -> 43809 | AS15: =AS14 -> 0.9 | AT15: 57 | AU15: =AU14 -> 1.1 | AV15: 85 | AW15: 2.9 | AX15: 75 | AY15: =AS15*AT15 -> 51.3 | AZ15: =AU15*AV15 -> 93.5 | BA15: =AW15*AX15 -> 217.5 | BB15: =AY15-AY14 -> -7.2 | BC15: =AZ15-AZ14 -> -11 | BD15: =BA15-BA14 -> -11.6 | BE15: =SUM(BB15:BD15) -> -29.8 | BF15: =SUM(I15-BE15) -> 29.8 | BG15: =SUM(I15-BF15) -> -29.8
A16: =ELEC!C13 -> 43810 | B16: =B15 -> 107778 | C16: =B16-B15 -> 0 | D16: =C16/27 -> 0 | E16: =SUM((C16*$E$4)+(7500/'EDl log'!$A$38)) -> 241.93548 | G16: =G15 -> 582653 | H16: =G16-G15 -> 0 | I16: =C16+H16 -> 0 | J16: =IF(I16>0,E16/I16,0) -> 0 | K16: ='Swimming Pool quality check '!H16 -> 5683 | L16: =K16-K15 -> 3 | M16: =M15 -> 457.44 | N16: =SUM(M16-M15) -> 0 | O16: =O15 -> 529.52 | P16: =SUM(O16-O15) -> 0 | Q16: =SUM(P16+N16) -> 0 | T16: =T15 -> 4228 | U16: =SUM(T16-T15) -> 0 | V16: =V15 -> 298 | W16: =+V16-V15 -> 0 | X16: 137552 | Y16: =SUM(X16-X15) -> 130 | Z16: 89797 | AA16: =Z16-Z15 -> 75 | AB16: =AB15 -> 253 | AC16: =AC15 -> 670 | AD16: =AC16-AC15 -> 0 | AE16: 36.88 | AF16: =AE16-AE15 -> 3.42 | AG16: =AG15 -> 727.54 | AH16: =AG16-AG15 -> 0 | AI16: =AF16+AH16 -> 3.42 | AJ16: =+Z16-Z15 -> 75 | AK16: =SUM(Y16-L16) -> 127 | AL16: =SUM(AJ16-W16) -> 75 | AM16: ='General information '!D16 -> 16.5 | AN16: ='General information '!H16 -> 0 | AP16: ='General information '!J16 -> 156 | AR16: =A16 -> 43810 | AS16: =AS15 -> 0.9 | AT16: 72 | AU16: =AU15 -> 1.1 | AV16: 101 | AW16: 2.9 | AX16: 100 | AY16: =AS16*AT16 -> 64.8 | AZ16: =AU16*AV16 -> 111.1 | BA16: =AW16*AX16 -> 290 | BB16: =AY16-AY15 -> 13.5 | BC16: =AZ16-AZ15 -> 17.6 | BD16: =BA16-BA15 -> 72.5 | BE16: =SUM(BB16:BD16) -> 103.6 | BF16: =SUM(I16-BE16) -> -103.6 | BG16: =SUM(I16-BF16) -> 103.6
A17: =ELEC!C14 -> 43811 | B17: =B16 -> 107778 | C17: =B17-B16 -> 0 | D17: =C17/27 -> 0 | E17: =SUM((C17*$E$4)+(7500/'EDl log'!$A$38)) -> 241.93548 | G17: 582653 | H17: =G17-G16 -> 0 | I17: =C17+H17 -> 0 | J17: =IF(I17>0,E17/I17,0) -> 0 | K17: ='Swimming Pool quality check '!H17 -> 5690 | L17: =K17-K16 -> 7 | M17: =M16 -> 457.44 | N17: =SUM(M17-M16) -> 0 | O17: =O16 -> 529.52 | P17: =SUM(O17-O16) -> 0 | Q17: =SUM(P17+N17) -> 0 | T17: 4231 | U17: =SUM(T17-T16) -> 3 | V17: 298 | W17: =+V17-V16 -> 0 | X17: 137552 | Y17: =SUM(X17-X16) -> 0 | Z17: 89797 | AA17: =Z17-Z16 -> 0 | AB17: 253 | AC17: 670 | AD17: =AC17-AC16 -> 0 | AE17: 36.88 | AF17: =AE17-AE16 -> 0 | AG17: 757.9 | AH17: =AG17-AG16 -> 30.36 | AI17: =AF17+AH17 -> 30.36 | AJ17: =+Z17-Z16 -> 0 | AK17: =SUM(Y17-L17) -> -7 | AL17: =SUM(AJ17-W17) -> 0 | AM17: ='General information '!D17 -> 17.5 | AN17: ='General information '!H17 -> 0 | AP17: ='General information '!J17 -> 199 | AR17: =A17 -> 43811 | AS17: =AS16 -> 0.9 | AT17: 72 | AU17: =AU16 -> 1.1 | AV17: 82 | AW17: 2.9 | AX17: 87 | AY17: =AS17*AT17 -> 64.8 | AZ17: =AU17*AV17 -> 90.2 | BA17: =AW17*AX17 -> 252.3 | BB17: =AY17-AY16 -> 0 | BC17: =AZ17-AZ16 -> -20.9 | BD17: =BA17-BA16 -> -37.7 | BE17: =SUM(BB17:BD17) -> -58.6 | BF17: =SUM(I17-BE17) -> 58.6 | BG17: =SUM(I17-BF17) -> -58.6
A18: =ELEC!C15 -> 43812 | B18: 107778 | C18: =B18-B17 -> 0 | D18: =C18/27 -> 0 | E18: =SUM((C18*$E$4)+(7500/'EDl log'!$A$38)) -> 241.93548 | G18: 582653 | H18: =G18-G17 -> 0 | I18: =C18+H18 -> 0 | J18: =IF(I18>0,E18/I18,0) -> 0 | K18: ='Swimming Pool quality check '!H18 -> 5693 | L18: =K18-K17 -> 3 | M18: =M17 -> 457.44 | N18: =SUM(M18-M17) -> 0 | O18: =O17 -> 529.52 | P18: =SUM(O18-O17) -> 0 | Q18: =SUM(P18+N18) -> 0 | T18: 4238 | U18: =SUM(T18-T17) -> 7 | V18: 298 | W18: =+V18-V17 -> 0 | X18: 137652 | Y18: =SUM(X18-X17) -> 100 | Z18: 89841 | AA18: =Z18-Z17 -> 44 | AB18: =AB17 -> 253 | AC18: =AC17 -> 670 | AD18: =AC18-AC17 -> 0 | AE18: 36.88 | AF18: =AE18-AE17 -> 0 | AG18: 759.19 | AH18: =AG18-AG17 -> 1.29 | AI18: =AF18+AH18 -> 1.29 | AJ18: =+Z18-Z17 -> 44 | AK18: =SUM(Y18-L18) -> 97 | AL18: =SUM(AJ18-W18) -> 44 | AM18: ='General information '!D18 -> 16.5 | AN18: ='General information '!H18 -> 0 | AP18: ='General information '!J18 -> 276 | AR18: =A18 -> 43812 | AS18: =AS17 -> 0.9 | AT18: 114 | AU18: =AU17 -> 1.1 | AV18: 94 | AW18: 2.9 | AX18: 101 | AY18: =AS18*AT18 -> 102.6 | AZ18: =AU18*AV18 -> 103.4 | BA18: =AW18*AX18 -> 292.9 | BB18: =AY18-AY17 -> 37.8 | BC18: =AZ18-AZ17 -> 13.2 | BD18: =BA18-BA17 -> 40.6 | BE18: =SUM(BB18:BD18) -> 91.6 | BF18: =SUM(I18-BE18) -> -91.6 | BG18: =SUM(I18-BF18) -> 91.6
A19: =ELEC!C16 -> 43813 | B19: =B18 -> 107778 | C19: =B19-B18 -> 0 | D19: =C19/27 -> 0 | E19: =SUM((C19*$E$4)+(7500/'EDl log'!$A$38)) -> 241.93548 | G19: 582653 | H19: =G19-G18 -> 0 | I19: =C19+H19 -> 0 | J19: =IF(I19>0,E19/I19,0) -> 0 | K19: ='Swimming Pool quality check '!H19 -> 5698 | L19: =K19-K18 -> 5 | M19: =M18 -> 457.44 | N19: =SUM(M19-M18) -> 0 | O19: =O18 -> 529.52 | P19: =SUM(O19-O18) -> 0 | Q19: =SUM(P19+N19) -> 0 | T19: 4243 | U19: =SUM(T19-T18) -> 5 | V19: 299 | W19: =+V19-V18 -> 1 | X19: 137695 | Y19: =SUM(X19-X18) -> 43 | Z19: 89872 | AA19: =Z19-Z18 -> 31 | AB19: =AB18 -> 253 | AC19: =AC18 -> 670 | AD19: =AC19-AC18 -> 0 | AE19: 37.82 | AF19: =AE19-AE18 -> 0.94 | AG19: 766.31 | AH19: =AG19-AG18 -> 7.12 | AI19: =AF19+AH19 -> 8.06 | AJ19: =+Z19-Z18 -> 31 | AK19: =SUM(Y19-L19) -> 38 | AL19: =SUM(AJ19-W19) -> 30 | AM19: ='General information '!D19 -> 15 | AN19: ='General information '!H19 -> 150 | AP19: ='General information '!J19 -> 300 | AR19: =A19 -> 43813 | AS19: =AS18 -> 0.9 | AT19: 52 | AU19: =AU18 -> 1.1 | AV19: 92 | AW19: 2.9 | AX19: 100 | AY19: =AS19*AT19 -> 46.8 | AZ19: =AU19*AV19 -> 101.2 | BA19: =AW19*AX19 -> 290 | BB19: =AY19-AY18 -> -55.8 | BC19: =AZ19-AZ18 -> -2.2 | BD19: =BA19-BA18 -> -2.9 | BE19: =SUM(BB19:BD19) -> -60.9 | BF19: =SUM(I19-BE19) -> 60.9 | BG19: =SUM(I19-BF19) -> -60.9
A20: =ELEC!C17 -> 43814 | B20: 107778 | C20: =B20-B19 -> 0 | D20: =C20/27 -> 0 | E20: =SUM((C20*$E$4)+(7500/'EDl log'!$A$38)) -> 241.93548 | G20: 582948 | H20: =G20-G19 -> 295 | I20: =C20+H20 -> 295 | J20: =IF(I20>0,E20/I20,0) -> 0.82012028 | K20: ='Swimming Pool quality check '!H20 -> 5699 | L20: =K20-K19 -> 1 | M20: =M19 -> 457.44 | N20: =SUM(M20-M19) -> 0 | O20: =O19 -> 529.52 | P20: =SUM(O20-O19) -> 0 | Q20: =SUM(P20+N20) -> 0 | T20: 4248 | U20: =SUM(T20-T19) -> 5 | V20: 305 | W20: =+V20-V19 -> 6 | X20: 137837 | Y20: =SUM(X20-X19) -> 142 | Z20: 90003 | AA20: =Z20-Z19 -> 131 | AB20: =AB19 -> 253 | AC20: =AC19 -> 670 | AD20: =AC20-AC19 -> 0 | AE20: 40.52 | AF20: =AE20-AE19 -> 2.7 | AG20: 790.66 | AH20: =AG20-AG19 -> 24.35 | AI20: =AF20+AH20 -> 27.05 | AJ20: =+Z20-Z19 -> 131 | AK20: =SUM(Y20-L20) -> 141 | AL20: =SUM(AJ20-W20) -> 125 | AM20: ='General information '!D20 -> 14.5 | AN20: ='General information '!H20 -> 0 | AP20: ='General information '!J20 -> 448 | AR20: =A20 -> 43814 | AS20: =AS19 -> 0.9 | AT20: 0 | AU20: =AU19 -> 1.1 | AV20: 124 | AW20: 2.9 | AX20: 158 | AY20: =AS20*AT20 -> 0 | AZ20: =AU20*AV20 -> 136.4 | BA20: =AW20*AX20 -> 458.2 | BB20: =AY20-AY19 -> -46.8 | BC20: =AZ20-AZ19 -> 35.2 | BD20: =BA20-BA19 -> 168.2 | BE20: =SUM(BB20:BD20) -> 156.6 | BF20: =SUM(I20-BE20) -> 138.4 | BG20: =SUM(I20-BF20) -> 156.6
A21: =ELEC!C18 -> 43815 | B21: =B20 -> 107778 | C21: =B21-B20 -> 0 | D21: =C21/27 -> 0 | E21: =SUM((C21*$E$4)+(7500/'EDl log'!$A$38)) -> 241.93548 | G21: 582968 | H21: =G21-G20 -> 20 | I21: =C21+H21 -> 20 | J21: =IF(I21>0,E21/I21,0) -> 12.096774 | K21: ='Swimming Pool quality check '!H21 -> 5700 | L21: =K21-K20 -> 1 | M21: =M20 -> 457.44 | N21: =SUM(M21-M20) -> 0 | O21: =O20 -> 529.52 | P21: =SUM(O21-O20) -> 0 | Q21: =SUM(P21+N21) -> 0 | T21: 4253 | U21: =SUM(T21-T20) -> 5 | V21: 306 | W21: =+V21-V20 -> 1 | X21: 137837 | Y21: =SUM(X21-X20) -> 0 | Z21: 90007 | AA21: =Z21-Z20 -> 4 | AB21: =AB20 -> 253 | AC21: =AC20 -> 670 | AD21: =AC21-AC20 -> 0 | AE21: =AE20 -> 40.52 | AF21: =AE21-AE20 -> 0 | AG21: 790.7 | AH21: =AG21-AG20 -> 0.04 | AI21: =AF21+AH21 -> 0.04 | AJ21: =+Z21-Z20 -> 4 | AK21: =SUM(Y21-L21) -> -1 | AL21: =SUM(AJ21-W21) -> 3 | AM21: ='General information '!D21 -> 16.5 | AN21: ='General information '!H21 -> 0 | AP21: ='General information '!J21 -> 0 | AR21: =A21 -> 43815 | AS21: =AS20 -> 0.9 | AT21: =AT20 -> 0 | AU21: =AU20 -> 1.1 | AV21: 132 | AW21: 2.9 | AX21: 110 | AY21: =AS21*AT21 -> 0 | AZ21: =AU21*AV21 -> 145.2 | BA21: =AW21*AX21 -> 319 | BB21: =AY21-AY20 -> 0 | BC21: =AZ21-AZ20 -> 8.8 | BD21: =BA21-BA20 -> -139.2 | BE21: =SUM(BB21:BD21) -> -130.4 | BF21: =SUM(I21-BE21) -> 150.4 | BG21: =SUM(I21-BF21) -> -130.4
A22: =ELEC!C19 -> 43816 | B22: 107778 | C22: =B22-B21 -> 0 | D22: =C22/27 -> 0 | E22: =SUM((C22*$E$4)+(7500/'EDl log'!$A$38)) -> 241.93548 | G22: 583253 | H22: =G22-G21 -> 285 | I22: =C22+H22 -> 285 | J22: =IF(I22>0,E22/I22,0) -> 0.84889643 | K22: ='Swimming Pool quality check '!H22 -> 5708 | L22: =K22-K21 -> 8 | M22: =M21 -> 457.44 | N22: =SUM(M22-M21) -> 0 | O22: =O21 -> 529.52 | P22: =SUM(O22-O21) -> 0 | Q22: =SUM(P22+N22) -> 0 | T22: 4258 | U22: =SUM(T22-T21) -> 5 | V22: 307 | W22: =+V22-V21 -> 1 | X22: 137837 | Y22: =SUM(X22-X21) -> 0 | Z22: 90010 | AA22: =Z22-Z21 -> 3 | AB22: =AB21 -> 253 | AC22: =AC21 -> 670 | AD22: =AC22-AC21 -> 0 | AE22: 40.52 | AF22: =AE22-AE21 -> 0 | AG22: 791.45 | AH22: =AG22-AG21 -> 0.75 | AI22: =AF22+AH22 -> 0.75 | AJ22: =+Z22-Z21 -> 3 | AK22: =SUM(Y22-L22) -> -8 | AL22: =SUM(AJ22-W22) -> 2 | AM22: ='General information '!D22 -> 18 | AN22: ='General information '!H22 -> 0 | AP22: ='General information '!J22 -> 405 | AR22: =A22 -> 43816 | AS22: =AS21 -> 0.9 | AT22: 150 | AU22: =AU21 -> 1.1 | AV22: 112 | AW22: 2.9 | AX22: 98 | AY22: =AS22*AT22 -> 135 | AZ22: =AU22*AV22 -> 123.2 | BA22: =AW22*AX22 -> 284.2 | BB22: =AY22-AY21 -> 135 | BC22: =AZ22-AZ21 -> -22 | BD22: =BA22-BA21 -> -34.8 | BE22: =SUM(BB22:BD22) -> 78.2 | BF22: =SUM(I22-BE22) -> 206.8 | BG22: =SUM(I22-BF22) -> 78.2
A23: =ELEC!C20 -> 43817 | B23: 107778 | C23: =B23-B22 -> 0 | D23: =C23/27 -> 0 | E23: =SUM((C23*$E$4)+(7500/'EDl log'!$A$38)) -> 241.93548 | G23: 583271 | H23: =G23-G22 -> 18 | I23: =C23+H23 -> 18 | J23: =IF(I23>0,E23/I23,0) -> 13.44086 | K23: ='Swimming Pool quality check '!H23 -> 5714 | L23: =K23-K22 -> 6 | M23: =M22 -> 457.44 | N23: =SUM(M23-M22) -> 0 | O23: =O22 -> 529.52 | P23: =SUM(O23-O22) -> 0 | Q23: =SUM(P23+N23) -> 0 | T23: 4262 | U23: =SUM(T23-T22) -> 4 | V23: 307 | W23: =+V23-V22 -> 0 | X23: 137909 | Y23: =SUM(X23-X22) -> 72 | Z23: 90055 | AA23: =Z23-Z22 -> 45 | AB23: =AB22 -> 253 | AC23: =AC22 -> 670 | AD23: =AC23-AC22 -> 0 | AE23: 41.44 | AF23: =AE23-AE22 -> 0.92 | AG23: 797.25 | AH23: =AG23-AG22 -> 5.8 | AI23: =AF23+AH23 -> 6.72 | AJ23: =+Z23-Z22 -> 45 | AK23: =SUM(Y23-L23) -> 66 | AL23: =SUM(AJ23-W23) -> 45 | AM23: ='General information '!D23 -> 18 | AN23: ='General information '!H23 -> 0 | AP23: ='General information '!J23 -> 180 | AR23: =A23 -> 43817 | AS23: =AS22 -> 0.9 | AT23: 38 | AU23: =AU22 -> 1.1 | AV23: 122 | AW23: 2.9 | AX23: 102 | AY23: =AS23*AT23 -> 34.2 | AZ23: =AU23*AV23 -> 134.2 | BA23: =AW23*AX23 -> 295.8 | BB23: =AY23-AY22 -> -100.8 | BC23: =AZ23-AZ22 -> 11 | BD23: =BA23-BA22 -> 11.6 | BE23: =SUM(BB23:BD23) -> -78.2 | BF23: =SUM(I23-BE23) -> 96.2 | BG23: =SUM(I23-BF23) -> -78.2
A24: =ELEC!C21 -> 43818 | B24: 107778 | C24: =B24-B23 -> 0 | D24: =C24/27 -> 0 | E24: =SUM((C24*$E$4)+(7500/'EDl log'!$A$38)) -> 241.93548 | G24: 583577 | H24: =G24-G23 -> 306 | I24: =C24+H24 -> 306 | J24: =IF(I24>0,E24/I24,0) -> 0.79063884 | K24: ='Swimming Pool quality check '!H24 -> 5718 | L24: =K24-K23 -> 4 | M24: =M23 -> 457.44 | N24: =SUM(M24-M23) -> 0 | O24: =O23 -> 529.52 | P24: =SUM(O24-O23) -> 0 | Q24: =SUM(P24+N24) -> 0 | T24: 4267 | U24: =SUM(T24-T23) -> 5 | V24: 309 | W24: =+V24-V23 -> 2 | X24: 138000 | Y24: =SUM(X24-X23) -> 91 | Z24: 90113 | AA24: =Z24-Z23 -> 58 | AB24: =AB23 -> 253 | AC24: =AC23 -> 670 | AD24: =AC24-AC23 -> 0 | AE24: 44.12 | AF24: =AE24-AE23 -> 2.68 | AG24: 819.46 | AH24: =AG24-AG23 -> 22.21 | AI24: =AF24+AH24 -> 24.89 | AJ24: =+Z24-Z23 -> 58 | AK24: =SUM(Y24-L24) -> 87 | AL24: =SUM(AJ24-W24) -> 56 | AM24: ='General information '!D24 -> 18.5 | AN24: ='General information '!H24 -> 0 | AP24: ='General information '!J24 -> 242 | AR24: =A24 -> 43818 | AS24: =AS23 -> 0.9 | AT24: 110 | AU24: =AU23 -> 1.1 | AV24: 128 | AW24: 2.9 | AX24: 110 | AY24: =AS24*AT24 -> 99 | AZ24: =AU24*AV24 -> 140.8 | BA24: =AW24*AX24 -> 319 | BB24: =AY24-AY23 -> 64.8 | BC24: =AZ24-AZ23 -> 6.6 | BD24: =BA24-BA23 -> 23.2 | BE24: =SUM(BB24:BD24) -> 94.6 | BF24: =SUM(I24-BE24) -> 211.4 | BG24: =SUM(I24-BF24) -> 94.6
A25: =ELEC!C22 -> 43819 | B25: 107778 | C25: =B25-B24 -> 0 | D25: =C25/27 -> 0 | E25: =SUM((C25*$E$4)+(7500/'EDl log'!$A$38)) -> 241.93548 | G25: =G24 -> 583577 | H25: =G25-G24 -> 0 | I25: =C25+H25 -> 0 | J25: =IF(I25>0,E25/I25,0) -> 0 | K25: ='Swimming Pool quality check '!H25 -> 5729 | L25: =K25-K24 -> 11 | M25: =M24 -> 457.44 | N25: =SUM(M25-M24) -> 0 | O25: =O24 -> 529.52 | P25: =SUM(O25-O24) -> 0 | Q25: =SUM(P25+N25) -> 0 | T25: 4269 | U25: =SUM(T25-T24) -> 2 | V25: 309 | W25: =+V25-V24 -> 0 | X25: 138055 | Y25: =SUM(X25-X24) -> 55 | Z25: 90126 | AA25: =Z25-Z24 -> 13 | AB25: =AB24 -> 253 | AC25: =AC24 -> 670 | AD25: =AC25-AC24 -> 0 | AE25: 44.12 | AF25: =AE25-AE24 -> 0 | AG25: 820.04 | AH25: =AG25-AG24 -> 0.58 | AI25: =AF25+AH25 -> 0.58 | AJ25: =+Z25-Z24 -> 13 | AK25: =SUM(Y25-L25) -> 44 | AL25: =SUM(AJ25-W25) -> 13 | AM25: ='General information '!D25 -> 17 | AN25: ='General information '!H25 -> 0 | AP25: ='General information '!J25 -> 308 | AR25: =A25 -> 43819 | AS25: =AS24 -> 0.9 | AT25: 20 | AU25: =AU24 -> 1.1 | AV25: 119 | AW25: 2.9 | AX25: 101 | AY25: =AS25*AT25 -> 18 | AZ25: =AU25*AV25 -> 130.9 | BA25: =AW25*AX25 -> 292.9 | BB25: =AY25-AY24 -> -81 | BC25: =AZ25-AZ24 -> -9.9 | BD25: =BA25-BA24 -> -26.1 | BE25: =SUM(BB25:BD25) -> -117 | BF25: =SUM(I25-BE25) -> 117 | BG25: =SUM(I25-BF25) -> -117
A26: =ELEC!C23 -> 43820 | B26: =B25 -> 107778 | C26: =B26-B25 -> 0 | D26: =C26/27 -> 0 | E26: =SUM((C26*$E$4)+(7500/'EDl log'!$A$38)) -> 241.93548 | G26: 583811 | H26: =G26-G25 -> 234 | I26: =C26+H26 -> 234 | J26: =IF(I26>0,E26/I26,0) -> 1.0339123 | K26: ='Swimming Pool quality check '!H26 -> 5732 | L26: =K26-K25 -> 3 | M26: =M25 -> 457.44 | N26: =SUM(M26-M25) -> 0 | O26: =O25 -> 529.52 | P26: =SUM(O26-O25) -> 0 | Q26: =SUM(P26+N26) -> 0 | T26: 4275 | U26: =SUM(T26-T25) -> 6 | V26: =V25 -> 309 | W26: =+V26-V25 -> 0 | X26: 138059 | Y26: =SUM(X26-X25) -> 4 | Z26: 90137 | AA26: =Z26-Z25 -> 11 | AB26: =AB25 -> 253 | AC26: =AC25 -> 670 | AD26: =AC26-AC25 -> 0 | AE26: =AE25 -> 44.12 | AF26: =AE26-AE25 -> 0 | AG26: 821.51 | AH26: =AG26-AG25 -> 1.47 | AI26: =AF26+AH26 -> 1.47 | AJ26: =+Z26-Z25 -> 11 | AK26: =SUM(Y26-L26) -> 1 | AL26: =SUM(AJ26-W26) -> 11 | AM26: ='General information '!D26 -> 17 | AN26: ='General information '!H26 -> 0 | AP26: ='General information '!J26 -> 243 | AR26: =A26 -> 43820 | AS26: =AS25 -> 0.9 | AT26: 140 | AU26: =AU25 -> 1.1 | AV26: 106 | AW26: 2.9 | AX26: 78 | AY26: =AS26*AT26 -> 126 | AZ26: =AU26*AV26 -> 116.6 | BA26: =AW26*AX26 -> 226.2 | BB26: =AY26-AY25 -> 108 | BC26: =AZ26-AZ25 -> -14.3 | BD26: =BA26-BA25 -> -66.7 | BE26: =SUM(BB26:BD26) -> 27 | BF26: =SUM(I26-BE26) -> 207 | BG26: =SUM(I26-BF26) -> 27
A27: =ELEC!C24 -> 43821 | B27: 107778 | C27: =B27-B26 -> 0 | D27: =C27/27 -> 0 | E27: =SUM((C27*$E$4)+(7500/'EDl log'!$A$38)) -> 241.93548 | G27: 583811 | H27: =G27-G26 -> 0 | I27: =C27+H27 -> 0 | J27: =IF(I27>0,E27/I27,0) -> 0 | K27: ='Swimming Pool quality check '!H27 -> 5740 | L27: =K27-K26 -> 8 | M27: =M26 -> 457.44 | N27: =SUM(M27-M26) -> 0 | O27: =O26 -> 529.52 | P27: =SUM(O27-O26) -> 0 | Q27: =SUM(P27+N27) -> 0 | T27: 4283 | U27: =SUM(T27-T26) -> 8 | V27: 310 | W27: =+V27-V26 -> 1 | X27: 138149 | Y27: =SUM(X27-X26) -> 90 | Z27: 90175 | AA27: =Z27-Z26 -> 38 | AB27: =AB26 -> 253 | AC27: =AC26 -> 670 | AD27: =AC27-AC26 -> 0 | AE27: 45.3 | AF27: =AE27-AE26 -> 1.18 | AG27: 830.48 | AH27: =AG27-AG26 -> 8.97 | AI27: =AF27+AH27 -> 10.15 | AJ27: =+Z27-Z26 -> 38 | AK27: =SUM(Y27-L27) -> 82 | AL27: =SUM(AJ27-W27) -> 37 | AM27: ='General information '!D27 -> 17 | AN27: ='General information '!H27 -> 0 | AP27: ='General information '!J27 -> 244 | AR27: =A27 -> 43821 | AS27: =AS26 -> 0.9 | AT27: 23 | AU27: =AU26 -> 1.1 | AV27: 105 | AW27: 2.9 | AX27: 80 | AY27: =AS27*AT27 -> 20.7 | AZ27: =AU27*AV27 -> 115.5 | BA27: =AW27*AX27 -> 232 | BB27: =AY27-AY26 -> -105.3 | BC27: =AZ27-AZ26 -> -1.1 | BD27: =BA27-BA26 -> 5.8 | BE27: =SUM(BB27:BD27) -> -100.6 | BF27: =SUM(I27-BE27) -> 100.6 | BG27: =SUM(I27-BF27) -> -100.6
A28: =ELEC!C25 -> 43822 | B28: 107778 | C28: =B28-B27 -> 0 | D28: =C28/27 -> 0 | E28: =SUM((C28*$E$4)+(7500/'EDl log'!$A$38)) -> 241.93548 | G28: 584073 | H28: =G28-G27 -> 262 | I28: =C28+H28 -> 262 | J28: =IF(I28>0,E28/I28,0) -> 0.92341788 | K28: ='Swimming Pool quality check '!H28 -> 5743 | L28: =K28-K27 -> 3 | M28: =M27 -> 457.44 | N28: =SUM(M28-M27) -> 0 | O28: =O27 -> 529.52 | P28: =SUM(O28-O27) -> 0 | Q28: =SUM(P28+N28) -> 0 | T28: 4290 | U28: =SUM(T28-T27) -> 7 | V28: 312 | W28: =+V28-V27 -> 2 | X28: 138195 | Y28: =SUM(X28-X27) -> 46 | Z28: 90219 | AA28: =Z28-Z27 -> 44 | AB28: =AB27 -> 253 | AC28: =AC27 -> 670 | AD28: =AC28-AC27 -> 0 | AE28: 47.7 | AF28: =AE28-AE27 -> 2.4 | AG28: 851.38 | AH28: =AG28-AG27 -> 20.9 | AI28: =AF28+AH28 -> 23.3 | AJ28: =+Z28-Z27 -> 44 | AK28: =SUM(Y28-L28) -> 43 | AL28: =SUM(AJ28-W28) -> 42 | AM28: ='General information '!D28 -> 17.5 | AN28: ='General information '!H28 -> 0 | AP28: ='General information '!J28 -> 244 | AR28: =A28 -> 43822 | AS28: =AS27 -> 0.9 | AT28: 101 | AU28: =AU27 -> 1.1 | AV28: 97 | AW28: 2.9 | AX28: 77 | AY28: =AS28*AT28 -> 90.9 | AZ28: =AU28*AV28 -> 106.7 | BA28: =AW28*AX28 -> 223.3 | BB28: =AY28-AY27 -> 70.2 | BC28: =AZ28-AZ27 -> -8.8 | BD28: =BA28-BA27 -> -8.7 | BE28: =SUM(BB28:BD28) -> 52.7 | BF28: =SUM(I28-BE28) -> 209.3 | BG28: =SUM(I28-BF28) -> 52.7
A29: =ELEC!C26 -> 43823 | B29: =B28 -> 107778 | C29: =B29-B28 -> 0 | D29: =C29/27 -> 0 | E29: =SUM((C29*$E$4)+(7500/'EDl log'!$A$38)) -> 241.93548 | G29: =G28 -> 584073 | H29: =G29-G28 -> 0 | I29: =C29+H29 -> 0 | J29: =IF(I29>0,E29/I29,0) -> 0 | K29: ='Swimming Pool quality check '!H29 -> 5752 | L29: =K29-K28 -> 9 | M29: =M28 -> 457.44 | N29: =SUM(M29-M28) -> 0 | O29: =O28 -> 529.52 | P29: =SUM(O29-O28) -> 0 | Q29: =SUM(P29+N29) -> 0 | T29: 4298 | U29: =SUM(T29-T28) -> 8 | V29: 313 | W29: =+V29-V28 -> 1 | X29: 138248 | Y29: =SUM(X29-X28) -> 53 | Z29: 90264 | AA29: =Z29-Z28 -> 45 | AB29: 249 | AC29: =AC28 -> 670 | AD29: =AC29-AC28 -> 0 | AE29: 48.62 | AF29: =AE29-AE28 -> 0.92 | AG29: 853.8 | AH29: =AG29-AG28 -> 2.42 | AI29: =AF29+AH29 -> 3.34 | AJ29: =+Z29-Z28 -> 45 | AK29: =SUM(Y29-L29) -> 44 | AL29: =SUM(AJ29-W29) -> 44 | AM29: ='General information '!D29 -> 17 | AN29: ='General information '!H29 -> 0 | AP29: ='General information '!J29 -> 360 | AR29: =A29 -> 43823 | AS29: =AS28 -> 0.9 | AT29: 0 | AU29: =AU28 -> 1.1 | AV29: 99 | AW29: 2.9 | AX29: 76 | AY29: =AS29*AT29 -> 0 | AZ29: =AU29*AV29 -> 108.9 | BA29: =AW29*AX29 -> 220.4 | BB29: =AY29-AY28 -> -90.9 | BC29: =AZ29-AZ28 -> 2.2 | BD29: =BA29-BA28 -> -2.9 | BE29: =SUM(BB29:BD29) -> -91.6 | BF29: =SUM(I29-BE29) -> 91.6 | BG29: =SUM(I29-BF29) -> -91.6
A30: =ELEC!C27 -> 43824 | B30: 107778 | C30: =B30-B29 -> 0 | D30: =C30/27 -> 0 | E30: =SUM((C30*$E$4)+(7500/'EDl log'!$A$38)) -> 241.93548 | G30: 584271 | H30: =G30-G29 -> 198 | I30: =C30+H30 -> 198 | J30: =IF(I30>0,E30/I30,0) -> 1.2218964 | K30: ='Swimming Pool quality check '!H30 -> 5756 | L30: =K30-K29 -> 4 | M30: =M29 -> 457.44 | N30: =SUM(M30-M29) -> 0 | O30: =O29 -> 529.52 | P30: =SUM(O30-O29) -> 0 | Q30: =SUM(P30+N30) -> 0 | T30: 4307 | U30: =SUM(T30-T29) -> 9 | V30: 313 | W30: =+V30-V29 -> 0 | X30: 138317 | Y30: =SUM(X30-X29) -> 69 | Z30: 90331 | AA30: =Z30-Z29 -> 67 | AB30: =AB29 -> 249 | AC30: =AC29 -> 670 | AD30: =AC30-AC29 -> 0 | AE30: 51 | AF30: =AE30-AE29 -> 2.38 | AG30: 878 | AH30: =AG30-AG29 -> 24.2 | AI30: =AF30+AH30 -> 26.58 | AJ30: =+Z30-Z29 -> 67 | AK30: =SUM(Y30-L30) -> 65 | AL30: =SUM(AJ30-W30) -> 67 | AM30: ='General information '!D30 -> 16 | AN30: ='General information '!H30 -> 0 | AP30: ='General information '!J30 -> 540 | AR30: =A30 -> 43824 | AS30: =AS29 -> 0.9 | AT30: 76 | AU30: =AU29 -> 1.1 | AV30: 97 | AW30: 2.9 | AX30: 81 | AY30: =AS30*AT30 -> 68.4 | AZ30: =AU30*AV30 -> 106.7 | BA30: =AW30*AX30 -> 234.9 | BB30: =AY30-AY29 -> 68.4 | BC30: =AZ30-AZ29 -> -2.2 | BD30: =BA30-BA29 -> 14.5 | BE30: =SUM(BB30:BD30) -> 80.7 | BF30: =SUM(I30-BE30) -> 117.3 | BG30: =SUM(I30-BF30) -> 80.7
A31: =ELEC!C28 -> 43825 | B31: 107778 | C31: =B31-B30 -> 0 | D31: =C31/27 -> 0 | E31: =SUM((C31*$E$4)+(7500/'EDl log'!$A$38)) -> 241.93548 | G31: 584271 | H31: =G31-G30 -> 0 | I31: =C31+H31 -> 0 | J31: =IF(I31>0,E31/I31,0) -> 0 | K31: ='Swimming Pool quality check '!H31 -> 5758 | L31: =K31-K30 -> 2 | M31: =M30 -> 457.44 | N31: =SUM(M31-M30) -> 0 | O31: =O30 -> 529.52 | P31: =SUM(O31-O30) -> 0 | Q31: =SUM(P31+N31) -> 0 | T31: 4313 | U31: =SUM(T31-T30) -> 6 | V31: 314 | W31: =+V31-V30 -> 1 | X31: 138321 | Y31: =SUM(X31-X30) -> 4 | Z31: 90358 | AA31: =Z31-Z30 -> 27 | AB31: =AB30 -> 249 | AC31: =AC30 -> 670 | AD31: =AC31-AC30 -> 0 | AE31: 51.6 | AF31: =AE31-AE30 -> 0.6 | AG31: 881 | AH31: =AG31-AG30 -> 3 | AI31: =AF31+AH31 -> 3.6 | AJ31: =+Z31-Z30 -> 27 | AK31: =SUM(Y31-L31) -> 2 | AL31: =SUM(AJ31-W31) -> 26 | AM31: ='General information '!D31 -> 15.5 | AN31: ='General information '!H31 -> 0 | AP31: ='General information '!J31 -> 288 | AR31: =A31 -> 43825 | AS31: =AS30 -> 0.9 | AT31: 26 | AU31: =AU30 -> 1.1 | AV31: 96 | AW31: 2.9 | AX31: 69 | AY31: =AS31*AT31 -> 23.4 | AZ31: =AU31*AV31 -> 105.6 | BA31: =AW31*AX31 -> 200.1 | BB31: =AY31-AY30 -> -45 | BC31: =AZ31-AZ30 -> -1.1 | BD31: =BA31-BA30 -> -34.8 | BE31: =SUM(BB31:BD31) -> -80.9 | BF31: =SUM(I31-BE31) -> 80.9 | BG31: =SUM(I31-BF31) -> -80.9
A32: =ELEC!C29 -> 43826 | B32: 107990 | C32: =B32-B31 -> 212 | D32: =C32/27 -> 7.8518519 | E32: =SUM((C32*$E$4)+(7500/'EDl log'!$A$38)) -> 593.85548 | G32: 584394 | H32: =G32-G31 -> 123 | I32: =C32+H32 -> 335 | J32: =IF(I32>0,E32/I32,0) -> 1.7727029 | K32: ='Swimming Pool quality check '!H32 -> 5758 | L32: =K32-K31 -> 0 | M32: =M31 -> 457.44 | N32: =SUM(M32-M31) -> 0 | O32: =O31 -> 529.52 | P32: =SUM(O32-O31) -> 0 | Q32: =SUM(P32+N32) -> 0 | T32: 4321 | U32: =SUM(T32-T31) -> 8 | V32: 316 | W32: =+V32-V31 -> 2 | X32: 138432 | Y32: =SUM(X32-X31) -> 111 | Z32: 90406 | AA32: =Z32-Z31 -> 48 | AB32: =AB31 -> 249 | AC32: =AC31 -> 670 | AD32: =AC32-AC31 -> 0 | AE32: 54 | AF32: =AE32-AE31 -> 2.4 | AG32: 905 | AH32: =AG32-AG31 -> 24 | AI32: =AF32+AH32 -> 26.4 | AJ32: =+Z32-Z31 -> 48 | AK32: =SUM(Y32-L32) -> 111 | AL32: =SUM(AJ32-W32) -> 46 | AM32: ='General information '!D32 -> 14.5 | AN32: ='General information '!H32 -> 270 | AP32: ='General information '!J32 -> 282 | AR32: =A32 -> 43826 | AS32: =AS31 -> 0.9 | AT32: 79 | AU32: =AU31 -> 1.1 | AV32: 79 | AW32: 2.9 | AX32: 80 | AY32: =AS32*AT32 -> 71.1 | AZ32: =AU32*AV32 -> 86.9 | BA32: =AW32*AX32 -> 232 | BB32: =AY32-AY31 -> 47.7 | BC32: =AZ32-AZ31 -> -18.7 | BD32: =BA32-BA31 -> 31.9 | BE32: =SUM(BB32:BD32) -> 60.9 | BF32: =SUM(I32-BE32) -> 274.1 | BG32: =SUM(I32-BF32) -> 60.9
A33: =ELEC!C30 -> 43827 | B33: 107990 | C33: =B33-B32 -> 0 | D33: =C33/27 -> 0 | E33: =SUM((C33*$E$4)+(7500/'EDl log'!$A$38)) -> 241.93548 | G33: 584394 | H33: =G33-G32 -> 0 | I33: =C33+H33 -> 0 | J33: =IF(I33>0,E33/I33,0) -> 0 | K33: ='Swimming Pool quality check '!H33 -> 5769 | L33: =K33-K32 -> 11 | M33: =M32 -> 457.44 | N33: =SUM(M33-M32) -> 0 | O33: =O32 -> 529.52 | P33: =SUM(O33-O32) -> 0 | Q33: =SUM(P33+N33) -> 0 | T33: 4332 | U33: =SUM(T33-T32) -> 11 | V33: 318 | W33: =+V33-V32 -> 2 | X33: =X32 -> 138432 | Y33: =SUM(X33-X32) -> 0 | Z33: 90407 | AA33: =Z33-Z32 -> 1 | AB33: =AB32 -> 249 | AC33: =AC32 -> 670 | AD33: =AC33-AC32 -> 0 | AE33: 55.2 | AF33: =AE33-AE32 -> 1.2 | AG33: 913 | AH33: =AG33-AG32 -> 8 | AI33: =AF33+AH33 -> 9.2 | AJ33: =+Z33-Z32 -> 1 | AK33: =SUM(Y33-L33) -> -11 | AL33: =SUM(AJ33-W33) -> -1 | AM33: ='General information '!D33 -> 15 | AN33: ='General information '!H33 -> 240 | AP33: ='General information '!J33 -> 766 | AR33: =A33 -> 43827 | AS33: =AS32 -> 0.9 | AT33: 62 | AU33: =AU32 -> 1.1 | AV33: 49 | AW33: 2.9 | AX33: 68 | AY33: =AS33*AT33 -> 55.8 | AZ33: =AU33*AV33 -> 53.9 | BA33: =AW33*AX33 -> 197.2 | BB33: =AY33-AY32 -> -15.3 | BC33: =AZ33-AZ32 -> -33 | BD33: =BA33-BA32 -> -34.8 | BE33: =SUM(BB33:BD33) -> -83.1 | BF33: =SUM(I33-BE33) -> 83.1 | BG33: =SUM(I33-BF33) -> -83.1
A34: =ELEC!C31 -> 43828 | B34: 108070 | C34: =B34-B33 -> 80 | D34: =C34/27 -> 2.962963 | E34: =SUM((C34*$E$4)+(7500/'EDl log'!$A$38)) -> 374.73548 | F34: 3 | G34: 584583 | H34: =G34-G33 -> 189 | I34: =C34+H34 -> 269 | J34: =IF(I34>0,E34/I34,0) -> 1.3930687 | K34: ='Swimming Pool quality check '!H34 -> 5773 | L34: =K34-K33 -> 4 | M34: =M33 -> 457.44 | N34: =SUM(M34-M33) -> 0 | O34: =O33 -> 529.52 | P34: =SUM(O34-O33) -> 0 | Q34: =SUM(P34+N34) -> 0 | T34: 4345 | U34: =SUM(T34-T33) -> 13 | V34: 325 | W34: =+V34-V33 -> 7 | X34: 138516 | Y34: =SUM(X34-X33) -> 84 | Z34: 90504 | AA34: =Z34-Z33 -> 97 | AB34: =AB33 -> 249 | AC34: =AC33 -> 670 | AD34: =AC34-AC33 -> 0 | AE34: 56.9 | AF34: =AE34-AE33 -> 1.7 | AG34: 929.5 | AH34: =AG34-AG33 -> 16.5 | AI34: =AF34+AH34 -> 18.2 | AJ34: =+Z34-Z33 -> 97 | AK34: =SUM(Y34-L34) -> 80 | AL34: =SUM(AJ34-W34) -> 90 | AM34: ='General information '!D34 -> 14.5 | AN34: ='General information '!H34 -> 0 | AP34: ='General information '!J34 -> 746 | AR34: =A34 -> 43828 | AS34: =AS33 -> 0.9 | AT34: 113 | AU34: =AU33 -> 1.1 | AV34: 73 | AW34: 2.9 | AX34: 72 | AY34: =AS34*AT34 -> 101.7 | AZ34: =AU34*AV34 -> 80.3 | BA34: =AW34*AX34 -> 208.8 | BB34: =AY34-AY33 -> 45.9 | BC34: =AZ34-AZ33 -> 26.4 | BD34: =BA34-BA33 -> 11.6 | BE34: =SUM(BB34:BD34) -> 83.9 | BF34: =SUM(I34-BE34) -> 185.1 | BG34: =SUM(I34-BF34) -> 83.9
A35: =ELEC!C32 -> 43829 | B35: =B34 -> 108070 | C35: =B35-B34 -> 0 | D35: =C35/27 -> 0 | E35: =SUM((C35*$E$4)+(7500/'EDl log'!$A$38)) -> 241.93548 | G35: 584654 | H35: =G35-G34 -> 71 | I35: =C35+H35 -> 71 | J35: =IF(I35>0,E35/I35,0) -> 3.407542 | K35: ='Swimming Pool quality check '!H35 -> 5773 | L35: =K35-K34 -> 0 | M35: =M34 -> 457.44 | N35: =SUM(M35-M34) -> 0 | O35: =O34 -> 529.52 | P35: =SUM(O35-O34) -> 0 | Q35: =SUM(P35+N35) -> 0 | T35: 4354 | U35: =SUM(T35-T34) -> 9 | V35: 326 | W35: =+V35-V34 -> 1 | X35: 138557 | Y35: =SUM(X35-X34) -> 41 | Z35: 90527 | AA35: =Z35-Z34 -> 23 | AB35: =AB34 -> 249 | AC35: =AC34 -> 670 | AD35: =AC35-AC34 -> 0 | AE35: 58.21 | AF35: =AE35-AE34 -> 1.31 | AG35: 941.6 | AH35: =AG35-AG34 -> 12.1 | AI35: =AF35+AH35 -> 13.41 | AJ35: =+Z35-Z34 -> 23 | AK35: =SUM(Y35-L35) -> 41 | AL35: =SUM(AJ35-W35) -> 22 | AM35: ='General information '!D35 -> 14 | AN35: ='General information '!H35 -> 0 | AP35: ='General information '!J35 -> 746 | AR35: =A35 -> 43829 | AS35: =AS34 -> 0.9 | AT35: 60 | AU35: =AU34 -> 1.1 | AV35: 66 | AW35: 2.9 | AX35: 47 | AY35: =AS35*AT35 -> 54 | AZ35: =AU35*AV35 -> 72.6 | BA35: =AW35*AX35 -> 136.3 | BB35: =AY35-AY34 -> -47.7 | BC35: =AZ35-AZ34 -> -7.7 | BD35: =BA35-BA34 -> -72.5 | BE35: =SUM(BB35:BD35) -> -127.9 | BF35: =SUM(I35-BE35) -> 198.9 | BG35: =SUM(I35-BF35) -> -127.9
A36: =ELEC!C33 -> 43830 | B36: 108202 | C36: =B36-B35 -> 132 | D36: =C36/27 -> 4.8888889 | E36: =SUM((C36*$E$4)+(7500/'EDl log'!$A$38)) -> 461.05548 | G36: 584867 | H36: =G36-G35 -> 213 | I36: =C36+H36 -> 345 | J36: =IF(I36>0,E36/I36,0) -> 1.3363927 | K36: ='Swimming Pool quality check '!H36 -> 5773 | L36: =K36-K35 -> 0 | M36: =M35 -> 457.44 | N36: =SUM(M36-M35) -> 0 | O36: =O35 -> 529.52 | P36: =SUM(O36-O35) -> 0 | Q36: =SUM(P36+N36) -> 0 | T36: 4363 | U36: =SUM(T36-T35) -> 9 | V36: 332 | W36: =+V36-V35 -> 6 | X36: 138671 | Y36: =SUM(X36-X35) -> 114 | Z36: 90621 | AA36: =Z36-Z35 -> 94 | AB36: =AB35 -> 249 | AC36: =AC35 -> 670 | AD36: =AC36-AC35 -> 0 | AE36: 60.22 | AF36: =AE36-AE35 -> 2.01 | AG36: 961.36 | AH36: =AG36-AG35 -> 19.76 | AI36: =AF36+AH36 -> 21.77 | AJ36: =+Z36-Z35 -> 94 | AK36: =SUM(Y36-L36) -> 114 | AL36: =SUM(AJ36-W36) -> 88 | AM36: ='General information '!D36 -> 13.5 | AN36: ='General information '!H36 -> 0 | AP36: ='General information '!J36 -> 439 | AR36: =A36 -> 43830 | AS36: =AS35 -> 0.9 | AT36: 102 | AU36: =AU35 -> 1.1 | AV36: 71 | AW36: 2.9 | AX36: 76 | AY36: =AS36*AT36 -> 91.8 | AZ36: =AU36*AV36 -> 78.1 | BA36: =AW36*AX36 -> 220.4 | BB36: =AY36-AY35 -> 37.8 | BC36: =AZ36-AZ35 -> 5.5 | BD36: =BA36-BA35 -> 84.1 | BE36: =SUM(BB36:BD36) -> 127.4 | BF36: =SUM(I36-BE36) -> 217.6 | BG36: =SUM(I36-BF36) -> 127.4
B37: =B36-B5 -> 672 | C37: =SUM(C6:C36) -> 672 | D37: =SUM(D6:D36) -> 24.888889 | F37: =SUM(F6:F36) -> 3 | H37: =SUM(H6:H36) -> 2938 | I37: =SUM(I6:I36) -> 3610 | L37: =SUM(L7:L36) -> 129 | Q37: =SUM(Q5:Q35) -> 0 | U37: =SUM(U6:U36) -> 182 | Y37: =SUM(Y35,Y33,Y31,Y29,Y27,Y25,Y23,Y21,Y19,Y17,Y15,Y13,Y11,Y9,Y7+Y36) -> 627 | AJ37: =SUM(AJ6:AJ36) -> 1256 | AK37: =SUM(Y37-L37) -> 498 | AL37: =SUM(AL6:AL36) -> 1216 | AT37: =AT36 -> 102
B38: =B37*1.66 -> 1115.52 | C38: =+C37*1.66 -> 1115.52 | E38: =SUM(E6:E36) -> 8615.52 | F38: =SUM(F6:F36) -> 3 | H38: 7500 | I38: =SUM('General information '!G37/WATER!I37) -> 0.3891651 | O38: =SUM(Q37+I37) -> 3610 | Z38: =SUM(Y37:AJ37) -> 1883 | AK38: =SUM(Y38-L38) -> 0
B39: =9*27 -> 243 | D39: =SUM(D21:D35) -> 10.814815 | F39: =SUM(F6:F36) -> 3 | G39: =SUM(I37) -> 3610 | H39: =SUM(H38+C38) -> 8615.52 | K39: =SUM(H39/G39) -> 2.3865706 | AJ39: =SUM(C38-AK38) -> 1115.52 | AM39: =SUM(AJ39/AO38) -> #DIV/0!

Sheet graphic

Sheet General information 
A1: GENERAL & HOTEL'S INFORMATION SHEET
B4: Max Temp | C4: MIN TEMP | D4: AVE TEMP | E4: AVE Humidity | F4: AVE OCC | G4: # of OCC Rooms | H4: Ball room | I4: Meeting rooms | J4: Outlets | K4: Total covers | L4: # of permenant Emp | M4: # of casuals | N4: Total # of EMP | O4: # of EMP/OCC Room
A5: =ELEC!C2 -> 43799 | B5: ='[1]General information '!B35 -> 22 | C5: ='[1]General information '!C35 -> 15 | D5: ='[1]General information '!D35 -> 18.5 | E5: ='[1]General information '!E35 -> 0.45 | F5: ='[1]General information '!F35 -> 0.113 | G5: ='[1]General information '!G35 -> 25.99 | H5: ='[1]General information '!H35 -> 0 | I5: ='[1]General information '!I35 -> 0 | ... O5: ='[1]General information '!O35 -> 0
A6: =ELEC!C3 -> 43800 | B6: 21 | C6: 14 | D6: =(C6+B6)/2 -> 17.5 | E6: 0.45 | F6: 0.1565 | G6: =F6*230 -> 35.995 | H6: 0 | J6: 290 | K6: =+J6+H6 -> 290
A7: =ELEC!C4 -> 43801 | B7: 22 | C7: 15 | D7: =(C7+B7)/2 -> 18.5 | E7: 0.4 | F7: 0.1304 | G7: =F7*230 -> 29.992 | H7: 0 | I7: 0 | J7: 145 | K7: =+J7+H7 -> 145
A8: =ELEC!C5 -> 43802 | B8: 23 | C8: 15 | D8: =(C8+B8)/2 -> 19 | E8: 0.43 | F8: 0.1522 | G8: =F8*230 -> 35.006 | H8: 0 | J8: 97 | K8: =+J8+H8 -> 97
A9: =ELEC!C6 -> 43803 | B9: 19 | C9: 12 | D9: =(C9+B9)/2 -> 15.5 | E9: 0.65 | F9: 0.1783 | G9: =F9*230 -> 41.009 | H9: 0 | J9: 143 | K9: =+J9+H9 -> 143
A10: =ELEC!C7 -> 43804 | B10: 18 | C10: 11 | D10: =(C10+B10)/2 -> 14.5 | E10: 0.65 | F10: 0.213 | G10: =F10*230 -> 48.99 | H10: 0 | J10: 219 | K10: =+J10+H10 -> 219
A11: =ELEC!C8 -> 43805 | B11: 18 | C11: 11 | D11: =(C11+B11)/2 -> 14.5 | E11: 0.65 | F11: 0.178 | G11: =F11*230 -> 40.94 | H11: 0 | J11: 300 | K11: =+J11+H11 -> 300
A12: =ELEC!C9 -> 43806 | B12: 18 | C12: 15 | D12: =(C12+B12)/2 -> 16.5 | E12: 0.65 | F12: 0.139 | G12: =F12*230 -> 31.97 | H12: 0 | K12: =+J12+H12 -> 0
A13: =ELEC!C10 -> 43807 | B13: 17 | C13: 15 | D13: =(C13+B13)/2 -> 16 | E13: 0.94 | F13: 0.1622 | G13: =F13*230 -> 37.306 | H13: 0 | J13: 299 | K13: =+J13+H13 -> 299
A14: =ELEC!C11 -> 43808 | B14: 17 | C14: 15 | D14: =(C14+B14)/2 -> 16 | E14: 0.65 | F14: 0.1739 | G14: =F14*230 -> 39.997 | H14: 0 | J14: 165 | K14: =+J14+H14 -> 165
A15: =ELEC!C12 -> 43809 | B15: 17 | C15: 15 | D15: =(C15+B15)/2 -> 16 | E15: 0.63 | F15: 0.187 | G15: =F15*230 -> 43.01 | H15: 0 | J15: 153 | K15: =+J15+H15 -> 153
A16: =ELEC!C13 -> 43810 | B16: 18 | C16: 15 | D16: =(C16+B16)/2 -> 16.5 | E16: 0.6 | F16: 0.1565 | G16: =F16*230 -> 35.995 | H16: 0 | J16: 156 | K16: =+J16+H16 -> 156
A17: =ELEC!C14 -> 43811 | B17: 19 | C17: 16 | D17: =(C17+B17)/2 -> 17.5 | E17: 0.6 | F17: 0.2174 | G17: =F17*230 -> 50.002 | J17: 199 | K17: =+J17+H17 -> 199
A18: =ELEC!C15 -> 43812 | B18: 18 | C18: 15 | D18: =(C18+B18)/2 -> 16.5 | E18: 0.55 | F18: 0.2348 | G18: =F18*230 -> 54.004 | H18: 0 | J18: 276 | K18: =+J18+H18 -> 276
A19: =ELEC!C16 -> 43813 | B19: 18 | C19: 12 | D19: =(C19+B19)/2 -> 15 | E19: 0.58 | F19: 0.1696 | G19: =F19*230 -> 39.008 | H19: 150 | J19: 300 | K19: =+J19+H19 -> 450
A20: =ELEC!C17 -> 43814 | B20: 17 | C20: 12 | D20: =(C20+B20)/2 -> 14.5 | E20: 0.55 | F20: 0.1652 | G20: =F20*230 -> 37.996 | H20: 0 | J20: 448 | K20: =+J20+H20 -> 448
A21: =ELEC!C18 -> 43815 | B21: 20 | C21: 13 | D21: =(C21+B21)/2 -> 16.5 | E21: 0.51 | F21: 0.139 | G21: =F21*230 -> 31.97 | H21: 0 | K21: =+J21+H21 -> 0
A22: =ELEC!C19 -> 43816 | B22: 19 | C22: 17 | D22: =(C22+B22)/2 -> 18 | E22: 0.55 | F22: 0.1522 | G22: =F22*230 -> 35.006 | H22: 0 | J22: 405 | K22: =+J22+H22 -> 405
A23: =ELEC!C20 -> 43817 | B23: 19 | C23: 17 | D23: =(C23+B23)/2 -> 18 | E23: 0.6 | F23: 0.1696 | G23: =F23*230 -> 39.008 | H23: 0 | J23: 180 | K23: =+J23+H23 -> 180
A24: =ELEC!C21 -> 43818 | B24: 20 | C24: 17 | D24: =(C24+B24)/2 -> 18.5 | E24: 0.6 | F24: 0.1739 | G24: =F24*230 -> 39.997 | H24: 0 | J24: 242 | K24: =+J24+H24 -> 242
A25: =ELEC!C22 -> 43819 | B25: 20 | C25: 14 | D25: =(C25+B25)/2 -> 17 | E25: 0.58 | F25: 0.2478 | G25: =F25*230 -> 56.994 | H25: 0 | J25: 308 | K25: =+J25+H25 -> 308
A26: =ELEC!C23 -> 43820 | B26: 20 | C26: 14 | D26: =(C26+B26)/2 -> 17 | E26: 0.55 | F26: 0.1826 | G26: =F26*230 -> 41.998 | H26: 0 | J26: 243 | K26: =+J26+H26 -> 243
A27: =ELEC!C24 -> 43821 | B27: 20 | C27: 14 | D27: =(C27+B27)/2 -> 17 | E27: 0.55 | F27: 0.2609 | G27: =F27*230 -> 60.007 | H27: 0 | J27: 244 | K27: =+J27+H27+I27 -> 244
A28: =ELEC!C25 -> 43822 | B28: 19 | C28: 16 | D28: =(C28+B28)/2 -> 17.5 | E28: 0.55 | F28: 0.2565 | G28: =F28*230 -> 58.995 | H28: 0 | J28: 244 | K28: =+J28+H28+I28 -> 244
A29: =ELEC!C26 -> 43823 | B29: 19 | C29: 15 | D29: =(C29+B29)/2 -> 17 | E29: 0.54 | F29: 0.2174 | G29: =F29*230 -> 50.002 | H29: 0 | J29: 360 | K29: =+J29+H29+I29 -> 360
A30: =ELEC!C27 -> 43824 | B30: 18 | C30: 14 | D30: =(C30+B30)/2 -> 16 | E30: 0.55 | F30: 0.2043 | G30: =F30*230 -> 46.989 | H30: 0 | J30: 540 | K30: =+J30+H30+I30 -> 540
A31: =ELEC!C28 -> 43825 | B31: 17 | C31: 14 | D31: =(C31+B31)/2 -> 15.5 | E31: 0.5 | F31: 0.2174 | G31: =F31*230 -> 50.002 | J31: 288 | K31: =+J31+H31+I31 -> 288
A32: =ELEC!C29 -> 43826 | B32: 16 | C32: 13 | D32: =(C32+B32)/2 -> 14.5 | E32: 0.77 | F32: 0.2913 | G32: =F32*230 -> 66.999 | H32: 270 | I32: 30 | J32: 282 | K32: =+J32+H32+I32 -> 582
A33: =ELEC!C30 -> 43827 | B33: 17 | C33: 13 | D33: =(C33+B33)/2 -> 15 | E33: 0.55 | F33: 0.2913 | G33: =F33*230 -> 66.999 | H33: 240 | J33: 766 | K33: =+J33+H33+I33 -> 1006
A34: =ELEC!C31 -> 43828 | B34: 16 | C34: 13 | D34: =(C34+B34)/2 -> 14.5 | E34: 0.55 | F34: 0.345 | G34: =F34*230 -> 79.35 | J34: 746 | K34: =+J34+H34+I34 -> 746
A35: =ELEC!C32 -> 43829 | B35: 16 | C35: 12 | D35: =(C35+B35)/2 -> 14 | E35: 0.85 | F35: 0.345 | G35: =F35*230 -> 79.35 | J35: 746 | K35: =+J35+H35+I35 -> 746
A36: =ELEC!C33 -> 43830 | B36: 16 | C36: 11 | D36: =(C36+B36)/2 -> 13.5 | E36: 0.67 | F36: 0.5 | G36: =F36*230 -> 115 | J36: 439 | K36: =+J36+H36+I36 -> 439
F37: =AVERAGE(F6:F36) -> 0.21316774 | G37: =SUM(G6:G35) -> 1404.886
D38: =SUM(D6:D36)/'EDl log'!A36 -> 16.241935
I41: http://www.accuweather.com/en/lb/lebanon-weather

Sheet tanks
B2: Tank 1 | D2: Tank 2 | F2: Tank 3 | H2: Tank 4 | J2: Tank 5 | L2: Tank 6 | N2: Tank 7 | P2: Tank 8 | R2: Tank 9 | T2: Tank 10 | V2: Tank 11 | Z2: Tank 1 | AB2: Tank 2 | AD2: Tank 3 | AF2: Tank 4 | AH2: Tank 5 | AJ2: Tank 6 | AL2: Tank 7
B3: 6670 | D3: =SUM(B3) -> 6670 | F3: =SUM(D3) -> 6670 | H3: =SUM(F3) -> 6670 | J3: =SUM(H3) -> 6670 | L3: =SUM(J3) -> 6670 | N3: =SUM(L3) -> 6670 | P3: =SUM(N3) -> 6670 | R3: =SUM(P3) -> 6670 | T3: =SUM(R3) -> 6670 | V3: =SUM(T3) -> 6670 | W3: =SUM(B3:V3) -> 73370 | Z3: 2800 | AB3: 2800 | AD3: 2800 | AF3: 2800 | AH3: 2800 | AJ3: 2800 | AL3: 2800 | AM3: =SUM(Z3:AL3) -> 19600 | AO3: =SUM(AM3+W3) -> 92970 | AR3: Total sotck | AS3: Diesel Cons Per day | AT3: Diesel Delivery | BE3: Genset Co | BF3: Steam | BG3: Boil | BH3: Outdoor temperature
B4: =B3/310 -> 21.516129 | D4: =SUM(B4) -> 21.516129 | F4: =SUM(D4) -> 21.516129 | H4: =SUM(F4) -> 21.516129 | J4: =SUM(H4) -> 21.516129 | L4: =SUM(J4) -> 21.516129 | N4: =SUM(L4) -> 21.516129 | P4: =SUM(N4) -> 21.516129 | R4: =SUM(P4) -> 21.516129 | T4: =SUM(R4) -> 21.516129 | V4: =SUM(T4) -> 21.516129 | Z4: =Z3/280 -> 10 | AA4: =AA3/280 -> 0 | AB4: =AB3/280 -> 10 | AC4: =AC3/280 -> 0 | AD4: =AD3/280 -> 10 | AE4: =AE3/280 -> 0 | AF4: =AF3/280 -> 10 | AG4: =AG3/280 -> 0 | ... AL4: =AL3/280 -> 10 | AT4: Delivery | AU4: Cost /L | AW4: Boiler+Steam | AX4: Generator | AZ4: Occupancy | BA4: AVE TEPM | BB4: AVE Humidity
A5: 43769 | B5: 213 | C5: 4582.9355 | D5: 213 | E5: 4582.9355 | F5: 213 | G5: 4582.9355 | H5: 213 | I5: 4582.9355 | J5: 213 | K5: 4582.9355 | L5: 213 | M5: 4582.9355 | N5: 213 | O5: 4582.9355 | P5: 213 | Q5: 4582.9355 | R5: 213 | S5: 4582.9355 | T5: 213 | U5: 4582.9355 | V5: 213 | W5: 4582.9355 | X5: 0.68709677 | Y5: 50412.29 | Z5: 219 | AA5: 2190 | AB5: 219 | AC5: 2190 | AD5: 219 | AE5: 2190 | AF5: 219 | AG5: 2190 | AH5: 219 | AI5: 2190 | AJ5: 219 | AK5: 2190 | AL5: 219 | AM5: 2190 | AN5: 0.78214286 | AO5: 15330 | AP5: 0 | AQ5: 0.70713446 | AR5: 65742.29 | AS5: -616.87097 | AT5: 4297 | AU5: 0.5337 | AV5: 0.5337 | AW5: -436.4 | AX5: -180.47097 | AY5: -616.87097 | AZ5: 0.1391 | BA5: 22.5 | BB5: 0.6 | BC5: 0 | BD5: 19222 | BE5: #REF! | BF5: 0 | BG5: #REF! | BH5: 0
A6: =ELEC!C3 -> 43800 | B6: ='B5'!B5 -> 214 | C6: =B6*$B$4 -> 4604.4516 | D6: =SUM(B6) -> 214 | E6: =D6*$B$4 -> 4604.4516 | F6: =SUM(D6) -> 214 | G6: =F6*$B$4 -> 4604.4516 | H6: =SUM(F6) -> 214 | I6: =H6*$B$4 -> 4604.4516 | J6: =SUM(H6) -> 214 | K6: =J6*$B$4 -> 4604.4516 | L6: =SUM(J6) -> 214 | M6: =L6*$B$4 -> 4604.4516 | N6: =SUM(L6) -> 214 | O6: =N6*$B$4 -> 4604.4516 | P6: =SUM(N6) -> 214 | Q6: =P6*$B$4 -> 4604.4516 | R6: =SUM(P6) -> 214 | S6: =R6*$B$4 -> 4604.4516 | T6: =SUM(R6) -> 214 | U6: =T6*$B$4 -> 4604.4516 | V6: =SUM(T6) -> 214 | W6: =V6*$B$4 -> 4604.4516 | X6: =SUM(Y6/73370) -> 0.69032258 | Y6: =SUM(C6+E6+G6+I6+K6+M6+O6+Q6+S6+U6+W6) -> 50648.968 | Z6: ='B5'!C5 -> 219 | AA6: =SUM(Z6*$Z$4) -> 2190 | AB6: =SUM(Z6) -> 219 | AC6: =SUM(AB6*$Z$4) -> 2190 | AD6: =SUM(AB6) -> 219 | AE6: =SUM(AD6*$Z$4) -> 2190 | AF6: =SUM(AD6) -> 219 | AG6: =SUM(AF6*$Z$4) -> 2190 | AH6: =SUM(AF6) -> 219 | AI6: =SUM(AH6*$Z$4) -> 2190 | AJ6: =SUM(AH6) -> 219 | AK6: =SUM(AJ6*$Z$4) -> 2190 | AL6: =SUM(AJ6) -> 219 | AM6: =SUM(AL6*$Z$4) -> 2190 | AN6: =SUM(AO6/19600) -> 0.78214286 | AO6: =SUM(AA6+AC6+AE6+AG6+AI6+AK6+AM6) -> 15330 | AQ6: =SUM(AR6/92970) -> 0.7096802 | AR6: =SUM(AO6+Y6) -> 65978.968 | AS6: =SUM(AR6-AR5-AT6) -> 236.67742 | AV6: =IF(AT6>0,AU6,AV5) -> 0.5337 | AW6: =-SUM('B5'!AI5) -> -229 | AX6: =-SUM(AW6-AS6) -> 465.67742 | AY6: =SUM(AX6+AW6) -> 236.67742 | AZ6: =ELEC!A3 -> 0.1565 | BA6: ='General information '!D6 -> 17.5 | BB6: =SUM('General information '!E6) -> 0.45 | BC6: =IF(AR3>=AR6,0,1) -> 0 | BD6: 19222 | BE6: =(305/1185)*ELEC!Q4 -> 558.00844 | BG6: =#REF!-BE6 -> #REF! | BH6: 21
A7: =ELEC!C4 -> 43801 | B7: ='B5'!B6 -> 210 | C7: =B7*$B$4 -> 4518.3871 | D7: =SUM(B7) -> 210 | E7: =D7*$B$4 -> 4518.3871 | F7: =SUM(D7) -> 210 | G7: =F7*$B$4 -> 4518.3871 | H7: =SUM(F7) -> 210 | I7: =H7*$B$4 -> 4518.3871 | J7: =SUM(H7) -> 210 | K7: =J7*$B$4 -> 4518.3871 | L7: =SUM(J7) -> 210 | M7: =L7*$B$4 -> 4518.3871 | N7: =SUM(L7) -> 210 | O7: =N7*$B$4 -> 4518.3871 | P7: =SUM(N7) -> 210 | Q7: =P7*$B$4 -> 4518.3871 | R7: =SUM(P7) -> 210 | S7: =R7*$B$4 -> 4518.3871 | T7: =SUM(R7) -> 210 | U7: =T7*$B$4 -> 4518.3871 | V7: =SUM(T7) -> 210 | W7: =V7*$B$4 -> 4518.3871 | X7: =SUM(Y7/73370) -> 0.67741935 | Y7: =SUM(C7+E7+G7+I7+K7+M7+O7+Q7+S7+U7+W7) -> 49702.258 | Z7: ='B5'!C6 -> 216 | AA7: =SUM(Z7*$Z$4) -> 2160 | AB7: =SUM(Z7) -> 216 | AC7: =SUM(AB7*$Z$4) -> 2160 | AD7: =SUM(AB7) -> 216 | AE7: =SUM(AD7*$Z$4) -> 2160 | AF7: =SUM(AD7) -> 216 | AG7: =SUM(AF7*$Z$4) -> 2160 | AH7: =SUM(AF7) -> 216 | AI7: =SUM(AH7*$Z$4) -> 2160 | AJ7: =SUM(AH7) -> 216 | AK7: =SUM(AJ7*$Z$4) -> 2160 | AL7: =SUM(AJ7) -> 216 | AM7: =SUM(AL7*$Z$4) -> 2160 | AN7: =SUM(AO7/19600) -> 0.77142857 | AO7: =SUM(AA7+AC7+AE7+AG7+AI7+AK7+AM7) -> 15120 | AQ7: =SUM(AR7/92970) -> 0.69723844 | AR7: =SUM(AO7+Y7) -> 64822.258 | AS7: =SUM(AR7-AR6-AT7) -> -1156.7097 | AV7: =IF(AT7>0,AU7,AV6) -> 0.5337 | AW7: =-SUM('B5'!AI6) -> -329 | AX7: =-SUM(AW7-AS7) -> -827.70968 | AY7: =SUM(AX7+AW7) -> -1156.7097 | AZ7: =ELEC!A4 -> 0.1304 | BA7: ='General information '!D7 -> 18.5 | BB7: =SUM('General information '!E7) -> 0.4 | BC7: 0 | BD7: 19222 | BE7: =(305/1185)*ELEC!Q5 -> 514.76793 | BG7: =#REF!-BE7 -> #REF! | BH7: 19
A8: =ELEC!C5 -> 43802 | B8: ='B5'!B7 -> 205 | C8: =B8*$B$4 -> 4410.8065 | D8: =SUM(B8) -> 205 | E8: =D8*$B$4 -> 4410.8065 | F8: =SUM(D8) -> 205 | G8: =F8*$B$4 -> 4410.8065 | H8: =SUM(F8) -> 205 | I8: =H8*$B$4 -> 4410.8065 | J8: =SUM(H8) -> 205 | K8: =J8*$B$4 -> 4410.8065 | L8: =SUM(J8) -> 205 | M8: =L8*$B$4 -> 4410.8065 | N8: =SUM(L8) -> 205 | O8: =N8*$B$4 -> 4410.8065 | P8: =SUM(N8) -> 205 | Q8: =P8*$B$4 -> 4410.8065 | R8: =SUM(P8) -> 205 | S8: =R8*$B$4 -> 4410.8065 | T8: =SUM(R8) -> 205 | U8: =T8*$B$4 -> 4410.8065 | V8: =SUM(T8) -> 205 | W8: =V8*$B$4 -> 4410.8065 | X8: =SUM(Y8/73370) -> 0.66129032 | Y8: =SUM(C8+E8+G8+I8+K8+M8+O8+Q8+S8+U8+W8) -> 48518.871 | Z8: ='B5'!C7 -> 210 | AA8: =SUM(Z8*$Z$4) -> 2100 | AB8: =SUM(Z8) -> 210 | AC8: =SUM(AB8*$Z$4) -> 2100 | AD8: =SUM(AB8) -> 210 | AE8: =SUM(AD8*$Z$4) -> 2100 | AF8: =SUM(AD8) -> 210 | AG8: =SUM(AF8*$Z$4) -> 2100 | AH8: =SUM(AF8) -> 210 | AI8: =SUM(AH8*$Z$4) -> 2100 | AJ8: =SUM(AH8) -> 210 | AK8: =SUM(AJ8*$Z$4) -> 2100 | AL8: =SUM(AJ8) -> 210 | AM8: =SUM(AL8*$Z$4) -> 2100 | AN8: =SUM(AO8/19600) -> 0.75 | AO8: =SUM(AA8+AC8+AE8+AG8+AI8+AK8+AM8) -> 14700 | AQ8: =SUM(AR8/92970) -> 0.67999216 | AR8: =SUM(AO8+Y8) -> 63218.871 | AS8: =SUM(AR8-AR7-AT8) -> -1603.3871 | AV8: =IF(AT8>0,AU8,AV7) -> 0.5337 | AW8: =-SUM('B5'!AI7) -> -624.7 | AX8: =-SUM(AW8-AS8) -> -978.6871 | AY8: =SUM(AX8+AW8) -> -1603.3871 | AZ8: =ELEC!A5 -> 0.1522 | BA8: ='General information '!D8 -> 19 | BB8: =SUM('General information '!E8) -> 0.43 | BC8: =IF(AR7>=AR8,0,1) -> 0 | BD8: 19222 | BE8: =(305/1185)*ELEC!Q6 -> 661.99156 | BG8: =#REF!-BE8 -> #REF! | BH8: 16
A9: =ELEC!C6 -> 43803 | B9: ='B5'!B8 -> 201 | C9: =B9*$B$4 -> 4324.7419 | D9: =SUM(B9) -> 201 | E9: =D9*$B$4 -> 4324.7419 | F9: =SUM(D9) -> 201 | G9: =F9*$B$4 -> 4324.7419 | H9: =SUM(F9) -> 201 | I9: =H9*$B$4 -> 4324.7419 | J9: =SUM(H9) -> 201 | K9: =J9*$B$4 -> 4324.7419 | L9: =SUM(J9) -> 201 | M9: =L9*$B$4 -> 4324.7419 | N9: =SUM(L9) -> 201 | O9: =N9*$B$4 -> 4324.7419 | P9: =SUM(N9) -> 201 | Q9: =P9*$B$4 -> 4324.7419 | R9: =SUM(P9) -> 201 | S9: =R9*$B$4 -> 4324.7419 | T9: =SUM(R9) -> 201 | U9: =T9*$B$4 -> 4324.7419 | V9: =SUM(T9) -> 201 | W9: =V9*$B$4 -> 4324.7419 | X9: =SUM(Y9/73370) -> 0.6483871 | Y9: =SUM(C9+E9+G9+I9+K9+M9+O9+Q9+S9+U9+W9) -> 47572.161 | Z9: ='B5'!C8 -> 207 | AA9: =SUM(Z9*$Z$4) -> 2070 | AB9: =SUM(Z9) -> 207 | AC9: =SUM(AB9*$Z$4) -> 2070 | AD9: =SUM(AB9) -> 207 | AE9: =SUM(AD9*$Z$4) -> 2070 | AF9: =SUM(AD9) -> 207 | AG9: =SUM(AF9*$Z$4) -> 2070 | AH9: =SUM(AF9) -> 207 | AI9: =SUM(AH9*$Z$4) -> 2070 | AJ9: =SUM(AH9) -> 207 | AK9: =SUM(AJ9*$Z$4) -> 2070 | AL9: =SUM(AJ9) -> 207 | AM9: =SUM(AL9*$Z$4) -> 2070 | AN9: =SUM(AO9/19600) -> 0.73928571 | AO9: =SUM(AA9+AC9+AE9+AG9+AI9+AK9+AM9) -> 14490 | AQ9: =SUM(AR9/92970) -> 0.66755041 | AR9: =SUM(AO9+Y9) -> 62062.161 | AS9: =SUM(AR9-AR8-AT9) -> -1156.7097 | AV9: =IF(AT9>0,AU9,AV8) -> 0.5337 | AW9: =-SUM('B5'!AI8) -> -449.9 | AX9: =-SUM(AW9-AS9) -> -706.80968 | AY9: =SUM(AX9+AW9) -> -1156.7097 | AZ9: =ELEC!A6 -> 0.1783 | BA9: ='General information '!D9 -> 15.5 | BB9: =SUM('General information '!E9) -> 0.65 | BC9: =IF(AR8>=AR9,0,1) -> 0 | BD9: 19222 | BE9: =(305/1185)*ELEC!Q7 -> 642.94515 | BG9: =#REF!-BE9 -> #REF! | BH9: 18
A10: =ELEC!C7 -> 43804 | B10: ='B5'!B9 -> 196 | C10: =B10*$B$4 -> 4217.1613 | D10: =SUM(B10) -> 196 | E10: =D10*$B$4 -> 4217.1613 | F10: =SUM(D10) -> 196 | G10: =F10*$B$4 -> 4217.1613 | H10: =SUM(F10) -> 196 | I10: =H10*$B$4 -> 4217.1613 | J10: =SUM(H10) -> 196 | K10: =J10*$B$4 -> 4217.1613 | L10: =SUM(J10) -> 196 | M10: =L10*$B$4 -> 4217.1613 | N10: =SUM(L10) -> 196 | O10: =N10*$B$4 -> 4217.1613 | P10: =SUM(N10) -> 196 | Q10: =P10*$B$4 -> 4217.1613 | R10: =SUM(P10) -> 196 | S10: =R10*$B$4 -> 4217.1613 | T10: =SUM(R10) -> 196 | U10: =T10*$B$4 -> 4217.1613 | V10: =SUM(T10) -> 196 | W10: =V10*$B$4 -> 4217.1613 | X10: =SUM(Y10/73370) -> 0.63225806 | Y10: =SUM(C10+E10+G10+I10+K10+M10+O10+Q10+S10+U10+W10) -> 46388.774 | Z10: ='B5'!C9 -> 202 | AA10: =SUM(Z10*$Z$4) -> 2020 | AB10: =SUM(Z10) -> 202 | AC10: =SUM(AB10*$Z$4) -> 2020 | AD10: =SUM(AB10) -> 202 | AE10: =SUM(AD10*$Z$4) -> 2020 | AF10: =SUM(AD10) -> 202 | AG10: =SUM(AF10*$Z$4) -> 2020 | AH10: =SUM(AF10) -> 202 | AI10: =SUM(AH10*$Z$4) -> 2020 | AJ10: =SUM(AH10) -> 202 | AK10: =SUM(AJ10*$Z$4) -> 2020 | AL10: =SUM(AJ10) -> 202 | AM10: =SUM(AL10*$Z$4) -> 2020 | AN10: =SUM(AO10/19600) -> 0.72142857 | AO10: =SUM(AA10+AC10+AE10+AG10+AI10+AK10+AM10) -> 14140 | AQ10: =SUM(AR10/92970) -> 0.65105705 | AR10: =SUM(AO10+Y10) -> 60528.774 | AS10: =SUM(AR10-AR9-AT10) -> -1533.3871 | AV10: =IF(AT10>0,AU10,AV9) -> 0.5337 | AW10: =-SUM('B5'!AI9) -> -498 | AX10: =-SUM(AW10-AS10) -> -1035.3871 | AY10: =SUM(AX10+AW10) -> -1533.3871 | AZ10: =ELEC!A7 -> 0.213 | BA10: ='General information '!D10 -> 14.5 | BB10: =SUM('General information '!E10) -> 0.65 | BC10: =IF(AR9>=AR10,0,1) -> 0 | BD10: 19222 | BE10: =(305/1185)*ELEC!Q8 -> 786.5654 | BG10: =#REF!-BE10 -> #REF! | BH10: 16
A11: =ELEC!C8 -> 43805 | B11: ='B5'!B10 -> 190 | C11: =B11*$B$4 -> 4088.0645 | D11: =SUM(B11) -> 190 | E11: =D11*$B$4 -> 4088.0645 | F11: =SUM(D11) -> 190 | G11: =F11*$B$4 -> 4088.0645 | H11: =SUM(F11) -> 190 | I11: =H11*$B$4 -> 4088.0645 | J11: =SUM(H11) -> 190 | K11: =J11*$B$4 -> 4088.0645 | L11: =SUM(J11) -> 190 | M11: =L11*$B$4 -> 4088.0645 | N11: =SUM(L11) -> 190 | O11: =N11*$B$4 -> 4088.0645 | P11: =SUM(N11) -> 190 | Q11: =P11*$B$4 -> 4088.0645 | R11: =SUM(P11) -> 190 | S11: =R11*$B$4 -> 4088.0645 | T11: =SUM(R11) -> 190 | U11: =T11*$B$4 -> 4088.0645 | V11: =SUM(T11) -> 190 | W11: =V11*$B$4 -> 4088.0645 | X11: =SUM(Y11/73370) -> 0.61290323 | Y11: =SUM(C11+E11+G11+I11+K11+M11+O11+Q11+S11+U11+W11) -> 44968.71 | Z11: ='B5'!C10 -> 196 | AA11: =SUM(Z11*$Z$4) -> 1960 | AB11: =SUM(Z11) -> 196 | AC11: =SUM(AB11*$Z$4) -> 1960 | AD11: =SUM(AB11) -> 196 | AE11: =SUM(AD11*$Z$4) -> 1960 | AF11: =SUM(AD11) -> 196 | AG11: =SUM(AF11*$Z$4) -> 1960 | AH11: =SUM(AF11) -> 196 | AI11: =SUM(AH11*$Z$4) -> 1960 | AJ11: =SUM(AH11) -> 196 | AK11: =SUM(AJ11*$Z$4) -> 1960 | AL11: =SUM(AJ11) -> 196 | AM11: =SUM(AL11*$Z$4) -> 1960 | AN11: =SUM(AO11/19600) -> 0.7 | AO11: =SUM(AA11+AC11+AE11+AG11+AI11+AK11+AM11) -> 13720 | AQ11: =SUM(AR11/92970) -> 0.63126503 | AR11: =SUM(AO11+Y11) -> 58688.71 | AS11: =SUM(AR11-AR10-AT11) -> -1840.0645 | AV11: =IF(AT11>0,AU11,AV10) -> 0.5337 | AW11: =-SUM('B5'!AI10) -> -705.8 | AX11: =-SUM(AW11-AS11) -> -1134.2645 | AY11: =SUM(AX11+AW11) -> -1840.0645 | AZ11: =ELEC!A8 -> 0.178 | BA11: ='General information '!D11 -> 14.5 | BB11: =SUM('General information '!E11) -> 0.65 | BC11: =IF(AR10>=AR11,0,1) -> 0 | BD11: 19222 | BE11: =(305/1185)*ELEC!Q9 -> 482.33755 | BG11: =#REF!-BE11 -> #REF! | BH11: 16.5
A12: =ELEC!C9 -> 43806 | B12: ='B5'!B11 -> 184 | C12: =B12*$B$4 -> 3958.9677 | D12: =SUM(B12) -> 184 | E12: =D12*$B$4 -> 3958.9677 | F12: =SUM(D12) -> 184 | G12: =F12*$B$4 -> 3958.9677 | H12: =SUM(F12) -> 184 | I12: =H12*$B$4 -> 3958.9677 | J12: =SUM(H12) -> 184 | K12: =J12*$B$4 -> 3958.9677 | L12: =SUM(J12) -> 184 | M12: =L12*$B$4 -> 3958.9677 | N12: =SUM(L12) -> 184 | O12: =N12*$B$4 -> 3958.9677 | P12: =SUM(N12) -> 184 | Q12: =P12*$B$4 -> 3958.9677 | R12: =SUM(P12) -> 184 | S12: =R12*$B$4 -> 3958.9677 | T12: =SUM(R12) -> 184 | U12: =T12*$B$4 -> 3958.9677 | V12: =SUM(T12) -> 184 | W12: =V12*$B$4 -> 3958.9677 | X12: =SUM(Y12/73370) -> 0.59354839 | Y12: =SUM(C12+E12+G12+I12+K12+M12+O12+Q12+S12+U12+W12) -> 43548.645 | Z12: ='B5'!C11 -> 190 | AA12: =SUM(Z12*$Z$4) -> 1900 | AB12: =SUM(Z12) -> 190 | AC12: =SUM(AB12*$Z$4) -> 1900 | AD12: =SUM(AB12) -> 190 | AE12: =SUM(AD12*$Z$4) -> 1900 | AF12: =SUM(AD12) -> 190 | AG12: =SUM(AF12*$Z$4) -> 1900 | AH12: =SUM(AF12) -> 190 | AI12: =SUM(AH12*$Z$4) -> 1900 | AJ12: =SUM(AH12) -> 190 | AK12: =SUM(AJ12*$Z$4) -> 1900 | AL12: =SUM(AJ12) -> 190 | AM12: =SUM(AL12*$Z$4) -> 1900 | AN12: =SUM(AO12/19600) -> 0.67857143 | AO12: =SUM(AA12+AC12+AE12+AG12+AI12+AK12+AM12) -> 13300 | AQ12: =SUM(AR12/92970) -> 0.611473 | AR12: =SUM(AO12+Y12) -> 56848.645 | AS12: =SUM(AR12-AR11-AT12) -> -1840.0645 | AV12: =IF(AT12>0,AU12,AV11) -> 0.5337 | AW12: =-SUM('B5'!AI11) -> -960.3 | AX12: =-SUM(AW12-AS12) -> -879.76452 | AY12: =SUM(AX12+AW12) -> -1840.0645 | AZ12: =ELEC!A9 -> 0.139 | BA12: ='General information '!D12 -> 16.5 | BB12: =SUM('General information '!E12) -> 0.65 | BC12: =IF(AR11>=AR12,0,1) -> 0 | BD12: 19222 | BE12: =(305/1185)*ELEC!Q10 -> 514.76793 | BG12: =#REF!-BE12 -> #REF! | BH12: 15.5
A13: =ELEC!C10 -> 43807 | B13: ='B5'!B12 -> 180 | C13: =B13*$B$4 -> 3872.9032 | D13: =SUM(B13) -> 180 | E13: =D13*$B$4 -> 3872.9032 | F13: =SUM(D13) -> 180 | G13: =F13*$B$4 -> 3872.9032 | H13: =SUM(F13) -> 180 | I13: =H13*$B$4 -> 3872.9032 | J13: =SUM(H13) -> 180 | K13: =J13*$B$4 -> 3872.9032 | L13: =SUM(J13) -> 180 | M13: =L13*$B$4 -> 3872.9032 | N13: =SUM(L13) -> 180 | O13: =N13*$B$4 -> 3872.9032 | P13: =SUM(N13) -> 180 | Q13: =P13*$B$4 -> 3872.9032 | R13: =SUM(P13) -> 180 | S13: =R13*$B$4 -> 3872.9032 | T13: =SUM(R13) -> 180 | U13: =T13*$B$4 -> 3872.9032 | V13: =SUM(T13) -> 180 | W13: =V13*$B$4 -> 3872.9032 | X13: =SUM(Y13/73370) -> 0.58064516 | Y13: =SUM(C13+E13+G13+I13+K13+M13+O13+Q13+S13+U13+W13) -> 42601.935 | Z13: ='B5'!C12 -> 186 | AA13: =SUM(Z13*$Z$4) -> 1860 | AB13: =SUM(Z13) -> 186 | AC13: =SUM(AB13*$Z$4) -> 1860 | AD13: =SUM(AB13) -> 186 | AE13: =SUM(AD13*$Z$4) -> 1860 | AF13: =SUM(AD13) -> 186 | AG13: =SUM(AF13*$Z$4) -> 1860 | AH13: =SUM(AF13) -> 186 | AI13: =SUM(AH13*$Z$4) -> 1860 | AJ13: =SUM(AH13) -> 186 | AK13: =SUM(AJ13*$Z$4) -> 1860 | AL13: =SUM(AJ13) -> 186 | AM13: =SUM(AL13*$Z$4) -> 1860 | AN13: =SUM(AO13/19600) -> 0.66428571 | AO13: =SUM(AA13+AC13+AE13+AG13+AI13+AK13+AM13) -> 13020 | AQ13: =SUM(AR13/92970) -> 0.59827832 | AR13: =SUM(AO13+Y13) -> 55621.935 | AS13: =SUM(AR13-AR12-AT13) -> -1226.7097 | AV13: =IF(AT13>0,AU13,AV12) -> 0.5337 | AW13: =-SUM('B5'!AI12) -> -642 | AX13: =-SUM(AW13-AS13) -> -584.70968 | AY13: =SUM(AX13+AW13) -> -1226.7097 | AZ13: =ELEC!A10 -> 0.1622 | BA13: ='General information '!D13 -> 16 | BB13: =SUM('General information '!E13) -> 0.94 | BC13: =IF(AR12>=AR13,0,1) -> 0 | BD13: 19222 | BE13: =(305/1185)*ELEC!Q11 -> 705.74684 | BG13: =#REF!-BE13 -> #REF!
A14: =ELEC!C11 -> 43808 | B14: ='B5'!B13 -> 175 | C14: =B14*$B$4 -> 3765.3226 | D14: =SUM(B14) -> 175 | E14: =D14*$B$4 -> 3765.3226 | F14: =SUM(D14) -> 175 | G14: =F14*$B$4 -> 3765.3226 | H14: =SUM(F14) -> 175 | I14: =H14*$B$4 -> 3765.3226 | J14: =SUM(H14) -> 175 | K14: =J14*$B$4 -> 3765.3226 | L14: =SUM(J14) -> 175 | M14: =L14*$B$4 -> 3765.3226 | N14: =SUM(L14) -> 175 | O14: =N14*$B$4 -> 3765.3226 | P14: =SUM(N14) -> 175 | Q14: =P14*$B$4 -> 3765.3226 | R14: =SUM(P14) -> 175 | S14: =R14*$B$4 -> 3765.3226 | T14: =SUM(R14) -> 175 | U14: =T14*$B$4 -> 3765.3226 | V14: =SUM(T14) -> 175 | W14: =V14*$B$4 -> 3765.3226 | X14: =SUM(Y14/73370) -> 0.56451613 | Y14: =SUM(C14+E14+G14+I14+K14+M14+O14+Q14+S14+U14+W14) -> 41418.548 | Z14: ='B5'!C13 -> 181 | AA14: =SUM(Z14*$Z$4) -> 1810 | AB14: =SUM(Z14) -> 181 | AC14: =SUM(AB14*$Z$4) -> 1810 | AD14: =SUM(AB14) -> 181 | AE14: =SUM(AD14*$Z$4) -> 1810 | AF14: =SUM(AD14) -> 181 | AG14: =SUM(AF14*$Z$4) -> 1810 | AH14: =SUM(AF14) -> 181 | AI14: =SUM(AH14*$Z$4) -> 1810 | AJ14: =SUM(AH14) -> 181 | AK14: =SUM(AJ14*$Z$4) -> 1810 | AL14: =SUM(AJ14) -> 181 | AM14: =SUM(AL14*$Z$4) -> 1810 | AN14: =SUM(AO14/19600) -> 0.64642857 | AO14: =SUM(AA14+AC14+AE14+AG14+AI14+AK14+AM14) -> 12670 | AQ14: =SUM(AR14/92970) -> 0.58178497 | AR14: =SUM(AO14+Y14) -> 54088.548 | AS14: =SUM(AR14-AR13-AT14) -> -1533.3871 | AV14: =IF(AT14>0,AU14,AV13) -> 0.5337 | AW14: =-SUM('B5'!AI13) -> -624 | AX14: =-SUM(AW14-AS14) -> -909.3871 | AY14: =SUM(AX14+AW14) -> -1533.3871 | AZ14: =ELEC!A11 -> 0.1739 | BA14: ='General information '!D14 -> 16 | BB14: =SUM('General information '!E14) -> 0.65 | BC14: =IF(AR13>=AR14,0,1) -> 0 | BD14: 19222 | BE14: =(305/1185)*ELEC!Q12 -> 516.827 | BG14: =#REF!-BE14 -> #REF!
A15: =ELEC!C12 -> 43809 | B15: ='B5'!B14 -> 170 | C15: =B15*$B$4 -> 3657.7419 | D15: =SUM(B15) -> 170 | E15: =D15*$B$4 -> 3657.7419 | F15: =SUM(D15) -> 170 | G15: =F15*$B$4 -> 3657.7419 | H15: =SUM(F15) -> 170 | I15: =H15*$B$4 -> 3657.7419 | J15: =SUM(H15) -> 170 | K15: =J15*$B$4 -> 3657.7419 | L15: =SUM(J15) -> 170 | M15: =L15*$B$4 -> 3657.7419 | N15: =SUM(L15) -> 170 | O15: =N15*$B$4 -> 3657.7419 | P15: =SUM(N15) -> 170 | Q15: =P15*$B$4 -> 3657.7419 | R15: =SUM(P15) -> 170 | S15: =R15*$B$4 -> 3657.7419 | T15: =SUM(R15) -> 170 | U15: =T15*$B$4 -> 3657.7419 | V15: =SUM(T15) -> 170 | W15: =V15*$B$4 -> 3657.7419 | X15: =SUM(Y15/73370) -> 0.5483871 | Y15: =SUM(C15+E15+G15+I15+K15+M15+O15+Q15+S15+U15+W15) -> 40235.161 | Z15: ='B5'!C14 -> 176 | AA15: =SUM(Z15*$Z$4) -> 1760 | AB15: =SUM(Z15) -> 176 | AC15: =SUM(AB15*$Z$4) -> 1760 | AD15: =SUM(AB15) -> 176 | AE15: =SUM(AD15*$Z$4) -> 1760 | AF15: =SUM(AD15) -> 176 | AG15: =SUM(AF15*$Z$4) -> 1760 | AH15: =SUM(AF15) -> 176 | AI15: =SUM(AH15*$Z$4) -> 1760 | AJ15: =SUM(AH15) -> 176 | AK15: =SUM(AJ15*$Z$4) -> 1760 | AL15: =SUM(AJ15) -> 176 | AM15: =SUM(AL15*$Z$4) -> 1760 | AN15: =SUM(AO15/19600) -> 0.62857143 | AO15: =SUM(AA15+AC15+AE15+AG15+AI15+AK15+AM15) -> 12320 | AQ15: =SUM(AR15/92970) -> 0.56529161 | AR15: =SUM(AO15+Y15) -> 52555.161 | AS15: =SUM(AR15-AR14-AT15) -> -1533.3871 | AV15: =IF(AT15>0,AU15,AV14) -> 0.5337 | AW15: =-SUM('B5'!AI14) -> -762.2 | AX15: =-SUM(AW15-AS15) -> -771.1871 | AY15: =SUM(AX15+AW15) -> -1533.3871 | AZ15: =ELEC!A12 -> 0.187 | BA15: ='General information '!D15 -> 16 | BB15: =SUM('General information '!E15) -> 0.63 | BC15: =IF(AR14>=AR15,0,1) -> 0 | BD15: 19222 | BE15: =(305/1185)*ELEC!Q13 -> 602.79325 | BG15: =#REF!-BE15 -> #REF!
A16: =ELEC!C13 -> 43810 | B16: ='B5'!B15 -> 164 | C16: =B16*$B$4 -> 3528.6452 | D16: =SUM(B16) -> 164 | E16: =D16*$B$4 -> 3528.6452 | F16: =SUM(D16) -> 164 | G16: =F16*$B$4 -> 3528.6452 | H16: =SUM(F16) -> 164 | I16: =H16*$B$4 -> 3528.6452 | J16: =SUM(H16) -> 164 | K16: =J16*$B$4 -> 3528.6452 | L16: =SUM(J16) -> 164 | M16: =L16*$B$4 -> 3528.6452 | N16: =SUM(L16) -> 164 | O16: =N16*$B$4 -> 3528.6452 | P16: =SUM(N16) -> 164 | Q16: =P16*$B$4 -> 3528.6452 | R16: =SUM(P16) -> 164 | S16: =R16*$B$4 -> 3528.6452 | T16: =SUM(R16) -> 164 | U16: =T16*$B$4 -> 3528.6452 | V16: =SUM(T16) -> 164 | W16: =V16*$B$4 -> 3528.6452 | X16: =SUM(Y16/73370) -> 0.52903226 | Y16: =SUM(C16+E16+G16+I16+K16+M16+O16+Q16+S16+U16+W16) -> 38815.097 | Z16: ='B5'!C15 -> 170 | AA16: =SUM(Z16*$Z$4) -> 1700 | AB16: =SUM(Z16) -> 170 | AC16: =SUM(AB16*$Z$4) -> 1700 | AD16: =SUM(AB16) -> 170 | AE16: =SUM(AD16*$Z$4) -> 1700 | AF16: =SUM(AD16) -> 170 | AG16: =SUM(AF16*$Z$4) -> 1700 | AH16: =SUM(AF16) -> 170 | AI16: =SUM(AH16*$Z$4) -> 1700 | AJ16: =SUM(AH16) -> 170 | AK16: =SUM(AJ16*$Z$4) -> 1700 | AL16: =SUM(AJ16) -> 170 | AM16: =SUM(AL16*$Z$4) -> 1700 | AN16: =SUM(AO16/19600) -> 0.60714286 | AO16: =SUM(AA16+AC16+AE16+AG16+AI16+AK16+AM16) -> 11900 | AQ16: =SUM(AR16/92970) -> 0.54549959 | AR16: =SUM(AO16+Y16) -> 50715.097 | AS16: =SUM(AR16-AR15-AT16) -> -1840.0645 | AV16: =IF(AT16>0,AU16,AV15) -> 0.5337 | AW16: =-SUM('B5'!AI15) -> -838.2 | AX16: =-SUM(AW16-AS16) -> -1001.8645 | AY16: =SUM(AX16+AW16) -> -1840.0645 | AZ16: =ELEC!A13 -> 0.1565 | BA16: ='General information '!D16 -> 16.5 | BB16: =SUM('General information '!E16) -> 0.6 | BC16: =IF(AR15>=AR16,0,1) -> 0 | BD16: 19222 | BE16: =(305/1185)*ELEC!Q14 -> 491.08861 | BG16: =#REF!-BE16 -> #REF!
A17: =ELEC!C14 -> 43811 | B17: ='B5'!B16 -> 202 | C17: =B17*$B$4 -> 4346.2581 | D17: =SUM(B17) -> 202 | E17: =D17*$B$4 -> 4346.2581 | F17: =SUM(D17) -> 202 | G17: =F17*$B$4 -> 4346.2581 | H17: =SUM(F17) -> 202 | I17: =H17*$B$4 -> 4346.2581 | J17: =SUM(H17) -> 202 | K17: =J17*$B$4 -> 4346.2581 | L17: =SUM(J17) -> 202 | M17: =L17*$B$4 -> 4346.2581 | N17: =SUM(L17) -> 202 | O17: =N17*$B$4 -> 4346.2581 | P17: =SUM(N17) -> 202 | Q17: =P17*$B$4 -> 4346.2581 | R17: =SUM(P17) -> 202 | S17: =R17*$B$4 -> 4346.2581 | T17: =SUM(R17) -> 202 | U17: =T17*$B$4 -> 4346.2581 | V17: =SUM(T17) -> 202 | W17: =V17*$B$4 -> 4346.2581 | X17: =SUM(Y17/73370) -> 0.6516129 | Y17: =SUM(C17+E17+G17+I17+K17+M17+O17+Q17+S17+U17+W17) -> 47808.839 | Z17: ='B5'!C16 -> 208 | AA17: =SUM(Z17*$Z$4) -> 2080 | AB17: =SUM(Z17) -> 208 | AC17: =SUM(AB17*$Z$4) -> 2080 | AD17: =SUM(AB17) -> 208 | AE17: =SUM(AD17*$Z$4) -> 2080 | AF17: =SUM(AD17) -> 208 | AG17: =SUM(AF17*$Z$4) -> 2080 | AH17: =SUM(AF17) -> 208 | AI17: =SUM(AH17*$Z$4) -> 2080 | AJ17: =SUM(AH17) -> 208 | AK17: =SUM(AJ17*$Z$4) -> 2080 | AL17: =SUM(AJ17) -> 208 | AM17: =SUM(AL17*$Z$4) -> 2080 | AN17: =SUM(AO17/19600) -> 0.74285714 | AO17: =SUM(AA17+AC17+AE17+AG17+AI17+AK17+AM17) -> 14560 | AQ17: =SUM(AR17/92970) -> 0.67084908 | AR17: =SUM(AO17+Y17) -> 62368.839 | AS17: =SUM(AR17-AR16-AT17) -> 193.74194 | AT17: 11460 | AU17: 0.5271 | AV17: =IF(AT17>0,AU17,AV16) -> 0.5271 | AW17: =-SUM('B5'!AI16) -> -661 | AX17: =-SUM(AW17-AS17) -> 854.74194 | AY17: =SUM(AX17+AW17) -> 193.74194 | AZ17: =ELEC!A14 -> 0.2174 | BA17: ='General information '!D17 -> 17.5 | BB17: =SUM('General information '!E17) -> 0.6 | BC17: =IF(AR16>=AR17,0,1) -> 1 | BD17: 19222 | BE17: =(305/1185)*ELEC!Q15 -> 866.09705 | BG17: =#REF!-BE17 -> #REF!
A18: =ELEC!C15 -> 43812 | B18: ='B5'!B17 -> 196 | C18: =B18*$B$4 -> 4217.1613 | D18: =SUM(B18) -> 196 | E18: =D18*$B$4 -> 4217.1613 | F18: =SUM(D18) -> 196 | G18: =F18*$B$4 -> 4217.1613 | H18: =SUM(F18) -> 196 | I18: =H18*$B$4 -> 4217.1613 | J18: =SUM(H18) -> 196 | K18: =J18*$B$4 -> 4217.1613 | L18: =SUM(J18) -> 196 | M18: =L18*$B$4 -> 4217.1613 | N18: =SUM(L18) -> 196 | O18: =N18*$B$4 -> 4217.1613 | P18: =SUM(N18) -> 196 | Q18: =P18*$B$4 -> 4217.1613 | R18: =SUM(P18) -> 196 | S18: =R18*$B$4 -> 4217.1613 | T18: =SUM(R18) -> 196 | U18: =T18*$B$4 -> 4217.1613 | V18: =SUM(T18) -> 196 | W18: =V18*$B$4 -> 4217.1613 | X18: =SUM(Y18/73370) -> 0.63225806 | Y18: =SUM(C18+E18+G18+I18+K18+M18+O18+Q18+S18+U18+W18) -> 46388.774 | Z18: ='B5'!C17 -> 203 | AA18: =SUM(Z18*$Z$4) -> 2030 | AB18: =SUM(Z18) -> 203 | AC18: =SUM(AB18*$Z$4) -> 2030 | AD18: =SUM(AB18) -> 203 | AE18: =SUM(AD18*$Z$4) -> 2030 | AF18: =SUM(AD18) -> 203 | AG18: =SUM(AF18*$Z$4) -> 2030 | AH18: =SUM(AF18) -> 203 | AI18: =SUM(AH18*$Z$4) -> 2030 | AJ18: =SUM(AH18) -> 203 | AK18: =SUM(AJ18*$Z$4) -> 2030 | AL18: =SUM(AJ18) -> 203 | AM18: =SUM(AL18*$Z$4) -> 2030 | AN18: =SUM(AO18/19600) -> 0.725 | AO18: =SUM(AA18+AC18+AE18+AG18+AI18+AK18+AM18) -> 14210 | AQ18: =SUM(AR18/92970) -> 0.65180998 | AR18: =SUM(AO18+Y18) -> 60598.774 | AS18: =SUM(AR18-AR17-AT18) -> -1770.0645 | AV18: =IF(AT18>0,AU18,AV17) -> 0.5271 | AW18: =-SUM('B5'!AI17) -> -867 | AX18: =-SUM(AW18-AS18) -> -903.06452 | AY18: =SUM(AX18+AW18) -> -1770.0645 | AZ18: =ELEC!A15 -> 0.2348 | BA18: ='General information '!D18 -> 16.5 | BB18: =SUM('General information '!E18) -> 0.55 | BC18: =IF(AR17>=AR18,0,1) -> 0 | BD18: 19222 | BE18: =(305/1185)*ELEC!Q16 -> 678.20675 | BG18: =#REF!-BE18 -> #REF!
A19: =ELEC!C16 -> 43813 | B19: ='B5'!B18 -> 189 | C19: =B19*$B$4 -> 4066.5484 | D19: =SUM(B19) -> 189 | E19: =D19*$B$4 -> 4066.5484 | F19: =SUM(D19) -> 189 | G19: =F19*$B$4 -> 4066.5484 | H19: =SUM(F19) -> 189 | I19: =H19*$B$4 -> 4066.5484 | J19: =SUM(H19) -> 189 | K19: =J19*$B$4 -> 4066.5484 | L19: =SUM(J19) -> 189 | M19: =L19*$B$4 -> 4066.5484 | N19: =SUM(L19) -> 189 | O19: =N19*$B$4 -> 4066.5484 | P19: =SUM(N19) -> 189 | Q19: =P19*$B$4 -> 4066.5484 | R19: =SUM(P19) -> 189 | S19: =R19*$B$4 -> 4066.5484 | T19: =SUM(R19) -> 189 | U19: =T19*$B$4 -> 4066.5484 | V19: =SUM(T19) -> 189 | W19: =V19*$B$4 -> 4066.5484 | X19: =SUM(Y19/73370) -> 0.60967742 | Y19: =SUM(C19+E19+G19+I19+K19+M19+O19+Q19+S19+U19+W19) -> 44732.032 | Z19: ='B5'!C18 -> 195 | AA19: =SUM(Z19*$Z$4) -> 1950 | AB19: =SUM(Z19) -> 195 | AC19: =SUM(AB19*$Z$4) -> 1950 | AD19: =SUM(AB19) -> 195 | AE19: =SUM(AD19*$Z$4) -> 1950 | AF19: =SUM(AD19) -> 195 | AG19: =SUM(AF19*$Z$4) -> 1950 | AH19: =SUM(AF19) -> 195 | AI19: =SUM(AH19*$Z$4) -> 1950 | AJ19: =SUM(AH19) -> 195 | AK19: =SUM(AJ19*$Z$4) -> 1950 | AL19: =SUM(AJ19) -> 195 | AM19: =SUM(AL19*$Z$4) -> 1950 | AN19: =SUM(AO19/19600) -> 0.69642857 | AO19: =SUM(AA19+AC19+AE19+AG19+AI19+AK19+AM19) -> 13650 | AQ19: =SUM(AR19/92970) -> 0.62796636 | AR19: =SUM(AO19+Y19) -> 58382.032 | AS19: =SUM(AR19-AR18-AT19) -> -2216.7419 | AV19: =IF(AT19>0,AU19,AV18) -> 0.5271 | AW19: =-SUM('B5'!AI18) -> -918.4 | AX19: =-SUM(AW19-AS19) -> -1298.3419 | AY19: =SUM(AX19+AW19) -> -2216.7419 | AZ19: =ELEC!A16 -> 0.1696 | BA19: ='General information '!D19 -> 15 | BB19: =SUM('General information '!E19) -> 0.58 | BC19: =IF(AR18>=AR19,0,1) -> 0 | BD19: 19222 | BE19: =(305/1185)*ELEC!Q17 -> 811.01688 | BG19: =#REF!-BE19 -> #REF!
A20: =ELEC!C17 -> 43814 | B20: ='B5'!B19 -> 183 | C20: =B20*$B$4 -> 3937.4516 | D20: =SUM(B20) -> 183 | E20: =D20*$B$4 -> 3937.4516 | F20: =SUM(D20) -> 183 | G20: =F20*$B$4 -> 3937.4516 | H20: =SUM(F20) -> 183 | I20: =H20*$B$4 -> 3937.4516 | J20: =SUM(H20) -> 183 | K20: =J20*$B$4 -> 3937.4516 | L20: =SUM(J20) -> 183 | M20: =L20*$B$4 -> 3937.4516 | N20: =SUM(L20) -> 183 | O20: =N20*$B$4 -> 3937.4516 | P20: =SUM(N20) -> 183 | Q20: =P20*$B$4 -> 3937.4516 | R20: =SUM(P20) -> 183 | S20: =R20*$B$4 -> 3937.4516 | T20: =SUM(R20) -> 183 | U20: =T20*$B$4 -> 3937.4516 | V20: =SUM(T20) -> 183 | W20: =V20*$B$4 -> 3937.4516 | X20: =SUM(Y20/73370) -> 0.59032258 | Y20: =SUM(C20+E20+G20+I20+K20+M20+O20+Q20+S20+U20+W20) -> 43311.968 | Z20: ='B5'!C19 -> 189 | AA20: =SUM(Z20*$Z$4) -> 1890 | AB20: =SUM(Z20) -> 189 | AC20: =SUM(AB20*$Z$4) -> 1890 | AD20: =SUM(AB20) -> 189 | AE20: =SUM(AD20*$Z$4) -> 1890 | AF20: =SUM(AD20) -> 189 | AG20: =SUM(AF20*$Z$4) -> 1890 | AH20: =SUM(AF20) -> 189 | AI20: =SUM(AH20*$Z$4) -> 1890 | AJ20: =SUM(AH20) -> 189 | AK20: =SUM(AJ20*$Z$4) -> 1890 | AL20: =SUM(AJ20) -> 189 | AM20: =SUM(AL20*$Z$4) -> 1890 | AN20: =SUM(AO20/19600) -> 0.675 | AO20: =SUM(AA20+AC20+AE20+AG20+AI20+AK20+AM20) -> 13230 | AQ20: =SUM(AR20/92970) -> 0.60817433 | AR20: =SUM(AO20+Y20) -> 56541.968 | AS20: =SUM(AR20-AR19-AT20) -> -1840.0645 | AV20: =IF(AT20>0,AU20,AV19) -> 0.5271 | AW20: =-SUM('B5'!AI19) -> -1163.3 | AX20: =-SUM(AW20-AS20) -> -676.76452 | AY20: =SUM(AX20+AW20) -> -1840.0645 | AZ20: =ELEC!A17 -> 0.1652 | BA20: ='General information '!D20 -> 14.5 | BB20: =SUM('General information '!E20) -> 0.55 | BC20: =IF(AR19>=AR20,0,1) -> 0 | BD20: 19222 | BE20: =(305/1185)*ELEC!Q18 -> 475.90295 | BG20: =#REF!-BE20 -> #REF!
A21: =ELEC!C18 -> 43815 | B21: ='B5'!B20 -> 177 | C21: =B21*$B$4 -> 3808.3548 | D21: =SUM(B21) -> 177 | E21: =D21*$B$4 -> 3808.3548 | F21: =SUM(D21) -> 177 | G21: =F21*$B$4 -> 3808.3548 | H21: =SUM(F21) -> 177 | I21: =H21*$B$4 -> 3808.3548 | J21: =SUM(H21) -> 177 | K21: =J21*$B$4 -> 3808.3548 | L21: =SUM(J21) -> 177 | M21: =L21*$B$4 -> 3808.3548 | N21: =SUM(L21) -> 177 | O21: =N21*$B$4 -> 3808.3548 | P21: =SUM(N21) -> 177 | Q21: =P21*$B$4 -> 3808.3548 | R21: =SUM(P21) -> 177 | S21: =R21*$B$4 -> 3808.3548 | T21: =SUM(R21) -> 177 | U21: =T21*$B$4 -> 3808.3548 | V21: =SUM(T21) -> 177 | W21: =V21*$B$4 -> 3808.3548 | X21: =SUM(Y21/73370) -> 0.57096774 | Y21: =SUM(C21+E21+G21+I21+K21+M21+O21+Q21+S21+U21+W21) -> 41891.903 | Z21: ='B5'!C20 -> 182 | AA21: =SUM(Z21*$Z$4) -> 1820 | AB21: =SUM(Z21) -> 182 | AC21: =SUM(AB21*$Z$4) -> 1820 | AD21: =SUM(AB21) -> 182 | AE21: =SUM(AD21*$Z$4) -> 1820 | AF21: =SUM(AD21) -> 182 | AG21: =SUM(AF21*$Z$4) -> 1820 | AH21: =SUM(AF21) -> 182 | AI21: =SUM(AH21*$Z$4) -> 1820 | AJ21: =SUM(AH21) -> 182 | AK21: =SUM(AJ21*$Z$4) -> 1820 | AL21: =SUM(AJ21) -> 182 | AM21: =SUM(AL21*$Z$4) -> 1820 | AN21: =SUM(AO21/19600) -> 0.65 | AO21: =SUM(AA21+AC21+AE21+AG21+AI21+AK21+AM21) -> 12740 | AQ21: =SUM(AR21/92970) -> 0.58762938 | AR21: =SUM(AO21+Y21) -> 54631.903 | AS21: =SUM(AR21-AR20-AT21) -> -1910.0645 | AV21: =IF(AT21>0,AU21,AV20) -> 0.5271 | AW21: =-SUM('B5'!AI20) -> -840 | AX21: =-SUM(AW21-AS21) -> -1070.0645 | AY21: =SUM(AX21+AW21) -> -1910.0645 | AZ21: =ELEC!A18 -> 0.139 | BA21: ='General information '!D21 -> 16.5 | BB21: =SUM('General information '!E21) -> 0.51 | BC21: =IF(AR20>=AR21,0,1) -> 0 | BD21: 19222 | BE21: =(305/1185)*ELEC!Q19 -> 826.97468 | BG21: =#REF!-BE21 -> #REF!
A22: =ELEC!C19 -> 43816 | B22: ='B5'!B21 -> 187 | C22: =B22*$B$4 -> 4023.5161 | D22: =SUM(B22) -> 187 | E22: =D22*$B$4 -> 4023.5161 | F22: =SUM(D22) -> 187 | G22: =F22*$B$4 -> 4023.5161 | H22: =SUM(F22) -> 187 | I22: =H22*$B$4 -> 4023.5161 | J22: =SUM(H22) -> 187 | K22: =J22*$B$4 -> 4023.5161 | L22: =SUM(J22) -> 187 | M22: =L22*$B$4 -> 4023.5161 | N22: =SUM(L22) -> 187 | O22: =N22*$B$4 -> 4023.5161 | P22: =SUM(N22) -> 187 | Q22: =P22*$B$4 -> 4023.5161 | R22: =SUM(P22) -> 187 | S22: =R22*$B$4 -> 4023.5161 | T22: =SUM(R22) -> 187 | U22: =T22*$B$4 -> 4023.5161 | V22: =SUM(T22) -> 187 | W22: =V22*$B$4 -> 4023.5161 | X22: =SUM(Y22/73370) -> 0.60322581 | Y22: =SUM(C22+E22+G22+I22+K22+M22+O22+Q22+S22+U22+W22) -> 44258.677 | Z22: ='B5'!C21 -> 193 | AA22: =SUM(Z22*$Z$4) -> 1930 | AB22: =SUM(Z22) -> 193 | AC22: =SUM(AB22*$Z$4) -> 1930 | AD22: =SUM(AB22) -> 193 | AE22: =SUM(AD22*$Z$4) -> 1930 | AF22: =SUM(AD22) -> 193 | AG22: =SUM(AF22*$Z$4) -> 1930 | AH22: =SUM(AF22) -> 193 | AI22: =SUM(AH22*$Z$4) -> 1930 | AJ22: =SUM(AH22) -> 193 | AK22: =SUM(AJ22*$Z$4) -> 1930 | AL22: =SUM(AJ22) -> 193 | AM22: =SUM(AL22*$Z$4) -> 1930 | AN22: =SUM(AO22/19600) -> 0.68928571 | AO22: =SUM(AA22+AC22+AE22+AG22+AI22+AK22+AM22) -> 13510 | AQ22: =SUM(AR22/92970) -> 0.62136902 | AR22: =SUM(AO22+Y22) -> 57768.677 | AS22: =SUM(AR22-AR21-AT22) -> -1263.2258 | AT22: 4400 | AU22: 0.527 | AV22: =IF(AT22>0,AU22,AV21) -> 0.527 | AW22: =-SUM('B5'!AI21) -> -787 | AX22: =-SUM(AW22-AS22) -> -476.22581 | AY22: =SUM(AX22+AW22) -> -1263.2258 | AZ22: =ELEC!A19 -> 0.1522 | BA22: ='General information '!D22 -> 18 | BB22: =SUM('General information '!E22) -> 0.55 | BC22: =IF(AR21>=AR22,0,1) -> 1 | BD22: 19222 | BE22: =(305/1185)*ELEC!Q20 -> 580.40084 | BG22: =#REF!-BE22 -> #REF!
A23: =ELEC!C20 -> 43817 | B23: ='B5'!B22 -> 225 | C23: =B23*$B$4 -> 4841.129 | D23: =SUM(B23) -> 225 | E23: =D23*$B$4 -> 4841.129 | F23: =SUM(D23) -> 225 | G23: =F23*$B$4 -> 4841.129 | H23: =SUM(F23) -> 225 | I23: =H23*$B$4 -> 4841.129 | J23: =SUM(H23) -> 225 | K23: =J23*$B$4 -> 4841.129 | L23: =SUM(J23) -> 225 | M23: =L23*$B$4 -> 4841.129 | N23: =SUM(L23) -> 225 | O23: =N23*$B$4 -> 4841.129 | P23: =SUM(N23) -> 225 | Q23: =P23*$B$4 -> 4841.129 | R23: =SUM(P23) -> 225 | S23: =R23*$B$4 -> 4841.129 | T23: =SUM(R23) -> 225 | U23: =T23*$B$4 -> 4841.129 | V23: =SUM(T23) -> 225 | W23: =V23*$B$4 -> 4841.129 | X23: =SUM(Y23/73370) -> 0.72580645 | Y23: =SUM(C23+E23+G23+I23+K23+M23+O23+Q23+S23+U23+W23) -> 53252.419 | Z23: ='B5'!C22 -> 229 | AA23: =SUM(Z23*$Z$4) -> 2290 | AB23: =SUM(Z23) -> 229 | AC23: =SUM(AB23*$Z$4) -> 2290 | AD23: =SUM(AB23) -> 229 | AE23: =SUM(AD23*$Z$4) -> 2290 | AF23: =SUM(AD23) -> 229 | AG23: =SUM(AF23*$Z$4) -> 2290 | AH23: =SUM(AF23) -> 229 | AI23: =SUM(AH23*$Z$4) -> 2290 | AJ23: =SUM(AH23) -> 229 | AK23: =SUM(AJ23*$Z$4) -> 2290 | AL23: =SUM(AJ23) -> 229 | AM23: =SUM(AL23*$Z$4) -> 2290 | AN23: =SUM(AO23/19600) -> 0.81785714 | AO23: =SUM(AA23+AC23+AE23+AG23+AI23+AK23+AM23) -> 16030 | AQ23: =SUM(AR23/92970) -> 0.74521264 | AR23: =SUM(AO23+Y23) -> 69282.419 | AS23: =SUM(AR23-AR22-AT23) -> 413.74194 | AT23: 11100 | AU23: 0.53 | AV23: =IF(AT23>0,AU23,AV22) -> 0.53 | AW23: =-SUM('B5'!AI22) -> -816.6 | AX23: =-SUM(AW23-AS23) -> 1230.3419 | AY23: =SUM(AX23+AW23) -> 413.74194 | AZ23: =ELEC!A20 -> 0.1696 | BA23: ='General information '!D23 -> 18 | BB23: =SUM('General information '!E23) -> 0.6 | BC23: =IF(AR22>=AR23,0,1) -> 1 | BD23: 19222 | BE23: =(305/1185)*ELEC!Q21 -> 538.70464 | BG23: =#REF!-BE23 -> #REF!
A24: =ELEC!C21 -> 43818 | B24: ='B5'!B23 -> 222 | C24: =B24*$B$4 -> 4776.5806 | D24: =SUM(B24) -> 222 | E24: =D24*$B$4 -> 4776.5806 | F24: =SUM(D24) -> 222 | G24: =F24*$B$4 -> 4776.5806 | H24: =SUM(F24) -> 222 | I24: =H24*$B$4 -> 4776.5806 | J24: =SUM(H24) -> 222 | K24: =J24*$B$4 -> 4776.5806 | L24: =SUM(J24) -> 222 | M24: =L24*$B$4 -> 4776.5806 | N24: =SUM(L24) -> 222 | O24: =N24*$B$4 -> 4776.5806 | P24: =SUM(N24) -> 222 | Q24: =P24*$B$4 -> 4776.5806 | R24: =SUM(P24) -> 222 | S24: =R24*$B$4 -> 4776.5806 | T24: =SUM(R24) -> 222 | U24: =T24*$B$4 -> 4776.5806 | V24: =SUM(T24) -> 222 | W24: =V24*$B$4 -> 4776.5806 | X24: =SUM(Y24/73370) -> 0.71612903 | Y24: =SUM(C24+E24+G24+I24+K24+M24+O24+Q24+S24+U24+W24) -> 52542.387 | Z24: ='B5'!C23 -> 207 | AA24: =SUM(Z24*$Z$4) -> 2070 | AB24: =SUM(Z24) -> 207 | AC24: =SUM(AB24*$Z$4) -> 2070 | AD24: =SUM(AB24) -> 207 | AE24: =SUM(AD24*$Z$4) -> 2070 | AF24: =SUM(AD24) -> 207 | AG24: =SUM(AF24*$Z$4) -> 2070 | AH24: =SUM(AF24) -> 207 | AI24: =SUM(AH24*$Z$4) -> 2070 | AJ24: =SUM(AH24) -> 207 | AK24: =SUM(AJ24*$Z$4) -> 2070 | AL24: =SUM(AJ24) -> 207 | AM24: =SUM(AL24*$Z$4) -> 2070 | AN24: =SUM(AO24/19600) -> 0.73928571 | AO24: =SUM(AA24+AC24+AE24+AG24+AI24+AK24+AM24) -> 14490 | AQ24: =SUM(AR24/92970) -> 0.72101094 | AR24: =SUM(AO24+Y24) -> 67032.387 | AS24: =SUM(AR24-AR23-AT24) -> -2250.0323 | AV24: =IF(AT24>0,AU24,AV23) -> 0.53 | AW24: =-SUM('B5'!AI23) -> -1143.7 | AX24: =-SUM(AW24-AS24) -> -1106.3323 | AY24: =SUM(AX24+AW24) -> -2250.0323 | AZ24: =ELEC!A21 -> 0.1739 | BA24: ='General information '!D24 -> 18.5 | BB24: =SUM('General information '!E24) -> 0.6 | BC24: =IF(AR23>=AR24,0,1) -> 0 | BD24: 19222 | BE24: =(305/1185)*ELEC!Q22 -> 688.24473 | BG24: =#REF!-BE24 -> #REF!
A25: =ELEC!C22 -> 43819 | B25: ='B5'!B24 -> 219 | C25: =B25*$B$4 -> 4712.0323 | D25: =SUM(B25) -> 219 | E25: =D25*$B$4 -> 4712.0323 | F25: =SUM(D25) -> 219 | G25: =F25*$B$4 -> 4712.0323 | H25: =SUM(F25) -> 219 | I25: =H25*$B$4 -> 4712.0323 | J25: =SUM(H25) -> 219 | K25: =J25*$B$4 -> 4712.0323 | L25: =SUM(J25) -> 219 | M25: =L25*$B$4 -> 4712.0323 | N25: =SUM(L25) -> 219 | O25: =N25*$B$4 -> 4712.0323 | P25: =SUM(N25) -> 219 | Q25: =P25*$B$4 -> 4712.0323 | R25: =SUM(P25) -> 219 | S25: =R25*$B$4 -> 4712.0323 | T25: =SUM(R25) -> 219 | U25: =T25*$B$4 -> 4712.0323 | V25: =SUM(T25) -> 219 | W25: =V25*$B$4 -> 4712.0323 | X25: =SUM(Y25/73370) -> 0.70645161 | Y25: =SUM(C25+E25+G25+I25+K25+M25+O25+Q25+S25+U25+W25) -> 51832.355 | Z25: ='B5'!C24 -> 193 | AA25: =SUM(Z25*$Z$4) -> 1930 | AB25: =SUM(Z25) -> 193 | AC25: =SUM(AB25*$Z$4) -> 1930 | AD25: =SUM(AB25) -> 193 | AE25: =SUM(AD25*$Z$4) -> 1930 | AF25: =SUM(AD25) -> 193 | AG25: =SUM(AF25*$Z$4) -> 1930 | AH25: =SUM(AF25) -> 193 | AI25: =SUM(AH25*$Z$4) -> 1930 | AJ25: =SUM(AH25) -> 193 | AK25: =SUM(AJ25*$Z$4) -> 1930 | AL25: =SUM(AJ25) -> 193 | AM25: =SUM(AL25*$Z$4) -> 1930 | AN25: =SUM(AO25/19600) -> 0.68928571 | AO25: =SUM(AA25+AC25+AE25+AG25+AI25+AK25+AM25) -> 13510 | AQ25: =SUM(AR25/92970) -> 0.70283269 | AR25: =SUM(AO25+Y25) -> 65342.355 | AS25: =SUM(AR25-AR24-AT25) -> -1690.0323 | AV25: =IF(AT25>0,AU25,AV24) -> 0.53 | AW25: =-SUM('B5'!AI24) -> -705 | AX25: =-SUM(AW25-AS25) -> -985.03226 | AY25: =SUM(AX25+AW25) -> -1690.0323 | AZ25: =ELEC!A22 -> 0.2478 | BA25: ='General information '!D25 -> 17 | BB25: =SUM('General information '!E25) -> 0.58 | BC25: =IF(AR24>=AR25,0,1) -> 0 | BD25: 19222 | BE25: =(305/1185)*ELEC!Q23 -> 634.45148 | BG25: =#REF!-BE25 -> #REF!
A26: =ELEC!C23 -> 43820 | B26: ='B5'!B25 -> 216 | C26: =B26*$B$4 -> 4647.4839 | D26: =SUM(B26) -> 216 | E26: =D26*$B$4 -> 4647.4839 | F26: =SUM(D26) -> 216 | G26: =F26*$B$4 -> 4647.4839 | H26: =SUM(F26) -> 216 | I26: =H26*$B$4 -> 4647.4839 | J26: =SUM(H26) -> 216 | K26: =J26*$B$4 -> 4647.4839 | L26: =SUM(J26) -> 216 | M26: =L26*$B$4 -> 4647.4839 | N26: =SUM(L26) -> 216 | O26: =N26*$B$4 -> 4647.4839 | P26: =SUM(N26) -> 216 | Q26: =P26*$B$4 -> 4647.4839 | R26: =SUM(P26) -> 216 | S26: =R26*$B$4 -> 4647.4839 | T26: =SUM(R26) -> 216 | U26: =T26*$B$4 -> 4647.4839 | V26: =SUM(T26) -> 216 | W26: =V26*$B$4 -> 4647.4839 | X26: =SUM(Y26/73370) -> 0.69677419 | Y26: =SUM(C26+E26+G26+I26+K26+M26+O26+Q26+S26+U26+W26) -> 51122.323 | Z26: ='B5'!C25 -> 179 | AA26: =SUM(Z26*$Z$4) -> 1790 | AB26: =SUM(Z26) -> 179 | AC26: =SUM(AB26*$Z$4) -> 1790 | AD26: =SUM(AB26) -> 179 | AE26: =SUM(AD26*$Z$4) -> 1790 | AF26: =SUM(AD26) -> 179 | AG26: =SUM(AF26*$Z$4) -> 1790 | AH26: =SUM(AF26) -> 179 | AI26: =SUM(AH26*$Z$4) -> 1790 | AJ26: =SUM(AH26) -> 179 | AK26: =SUM(AJ26*$Z$4) -> 1790 | AL26: =SUM(AJ26) -> 179 | AM26: =SUM(AL26*$Z$4) -> 1790 | AN26: =SUM(AO26/19600) -> 0.63928571 | AO26: =SUM(AA26+AC26+AE26+AG26+AI26+AK26+AM26) -> 12530 | AQ26: =SUM(AR26/92970) -> 0.68465443 | AR26: =SUM(AO26+Y26) -> 63652.323 | AS26: =SUM(AR26-AR25-AT26) -> -1690.0323 | AV26: =IF(AT26>0,AU26,AV25) -> 0.53 | AW26: =-SUM('B5'!AI25) -> -814 | AX26: =-SUM(AW26-AS26) -> -876.03226 | AY26: =SUM(AX26+AW26) -> -1690.0323 | AZ26: =ELEC!A23 -> 0.1826 | BA26: ='General information '!D26 -> 17 | BB26: =SUM('General information '!E26) -> 0.55 | BC26: =IF(AR25>=AR26,0,1) -> 0 | BD26: 19222 | BE26: =(305/1185)*ELEC!Q24 -> 518.37131 | BG26: =#REF!-BE26 -> #REF!
A27: =ELEC!C24 -> 43821 | B27: ='B5'!B26 -> 213 | C27: =B27*$B$4 -> 4582.9355 | D27: =SUM(B27) -> 213 | E27: =D27*$B$4 -> 4582.9355 | F27: =SUM(D27) -> 213 | G27: =F27*$B$4 -> 4582.9355 | H27: =SUM(F27) -> 213 | I27: =H27*$B$4 -> 4582.9355 | J27: =SUM(H27) -> 213 | K27: =J27*$B$4 -> 4582.9355 | L27: =SUM(J27) -> 213 | M27: =L27*$B$4 -> 4582.9355 | N27: =SUM(L27) -> 213 | O27: =N27*$B$4 -> 4582.9355 | P27: =SUM(N27) -> 213 | Q27: =P27*$B$4 -> 4582.9355 | R27: =SUM(P27) -> 213 | S27: =R27*$B$4 -> 4582.9355 | T27: =SUM(R27) -> 213 | U27: =T27*$B$4 -> 4582.9355 | V27: =SUM(T27) -> 213 | W27: =V27*$B$4 -> 4582.9355 | X27: =SUM(Y27/73370) -> 0.68709677 | Y27: =SUM(C27+E27+G27+I27+K27+M27+O27+Q27+S27+U27+W27) -> 50412.29 | Z27: ='B5'!C26 -> 166 | AA27: =SUM(Z27*$Z$4) -> 1660 | AB27: =SUM(Z27) -> 166 | AC27: =SUM(AB27*$Z$4) -> 1660 | AD27: =SUM(AB27) -> 166 | AE27: =SUM(AD27*$Z$4) -> 1660 | AF27: =SUM(AD27) -> 166 | AG27: =SUM(AF27*$Z$4) -> 1660 | AH27: =SUM(AF27) -> 166 | AI27: =SUM(AH27*$Z$4) -> 1660 | AJ27: =SUM(AH27) -> 166 | AK27: =SUM(AJ27*$Z$4) -> 1660 | AL27: =SUM(AJ27) -> 166 | AM27: =SUM(AL27*$Z$4) -> 1660 | AN27: =SUM(AO27/19600) -> 0.59285714 | AO27: =SUM(AA27+AC27+AE27+AG27+AI27+AK27+AM27) -> 11620 | AQ27: =SUM(AR27/92970) -> 0.66722911 | AR27: =SUM(AO27+Y27) -> 62032.29 | AS27: =SUM(AR27-AR26-AT27) -> -1620.0323 | AV27: =IF(AT27>0,AU27,AV26) -> 0.53 | AW27: =-SUM('B5'!AI26) -> -758.6 | AX27: =-SUM(AW27-AS27) -> -861.43226 | AY27: =SUM(AX27+AW27) -> -1620.0323 | AZ27: =ELEC!A24 -> 0.2609 | BA27: ='General information '!D27 -> 17 | BB27: =SUM('General information '!E27) -> 0.55 | BC27: =IF(AR26>=AR27,0,1) -> 0 | BD27: 19222 | BE27: =(305/1185)*ELEC!Q25 -> 849.88186 | BG27: =#REF!-BE27 -> #REF!
A28: =ELEC!C25 -> 43822 | B28: ='B5'!B27 -> 209 | C28: =B28*$B$4 -> 4496.871 | D28: =SUM(B28) -> 209 | E28: =D28*$B$4 -> 4496.871 | F28: =SUM(D28) -> 209 | G28: =F28*$B$4 -> 4496.871 | H28: =SUM(F28) -> 209 | I28: =H28*$B$4 -> 4496.871 | J28: =SUM(H28) -> 209 | K28: =J28*$B$4 -> 4496.871 | L28: =SUM(J28) -> 209 | M28: =L28*$B$4 -> 4496.871 | N28: =SUM(L28) -> 209 | O28: =N28*$B$4 -> 4496.871 | P28: =SUM(N28) -> 209 | Q28: =P28*$B$4 -> 4496.871 | R28: =SUM(P28) -> 209 | S28: =R28*$B$4 -> 4496.871 | T28: =SUM(R28) -> 209 | U28: =T28*$B$4 -> 4496.871 | V28: =SUM(T28) -> 209 | W28: =V28*$B$4 -> 4496.871 | X28: =SUM(Y28/73370) -> 0.67419355 | Y28: =SUM(C28+E28+G28+I28+K28+M28+O28+Q28+S28+U28+W28) -> 49465.581 | Z28: ='B5'!C27 -> 145 | AA28: =SUM(Z28*$Z$4) -> 1450 | AB28: =SUM(Z28) -> 145 | AC28: =SUM(AB28*$Z$4) -> 1450 | AD28: =SUM(AB28) -> 145 | AE28: =SUM(AD28*$Z$4) -> 1450 | AF28: =SUM(AD28) -> 145 | AG28: =SUM(AF28*$Z$4) -> 1450 | AH28: =SUM(AF28) -> 145 | AI28: =SUM(AH28*$Z$4) -> 1450 | AJ28: =SUM(AH28) -> 145 | AK28: =SUM(AJ28*$Z$4) -> 1450 | AL28: =SUM(AJ28) -> 145 | AM28: =SUM(AL28*$Z$4) -> 1450 | AN28: =SUM(AO28/19600) -> 0.51785714 | AO28: =SUM(AA28+AC28+AE28+AG28+AI28+AK28+AM28) -> 10150 | AQ28: =SUM(AR28/92970) -> 0.6412346 | AR28: =SUM(AO28+Y28) -> 59615.581 | AS28: =SUM(AR28-AR27-AT28) -> -2416.7097 | AV28: =IF(AT28>0,AU28,AV27) -> 0.53 | AW28: =-SUM('B5'!AI27) -> -1095.3 | AX28: =-SUM(AW28-AS28) -> -1321.4097 | AY28: =SUM(AX28+AW28) -> -2416.7097 | AZ28: =ELEC!A25 -> 0.2565 | BA28: ='General information '!D28 -> 17.5 | BB28: =SUM('General information '!E28) -> 0.55 | BC28: =IF(AR27>=AR28,0,1) -> 0 | BD28: 19222 | BE28: =(305/1185)*ELEC!Q26 -> 510.64979 | BG28: =#REF!-BE28 -> #REF!
A29: =ELEC!C26 -> 43823 | B29: ='B5'!B28 -> 206 | C29: =B29*$B$4 -> 4432.3226 | D29: =SUM(B29) -> 206 | E29: =D29*$B$4 -> 4432.3226 | F29: =SUM(D29) -> 206 | G29: =F29*$B$4 -> 4432.3226 | H29: =SUM(F29) -> 206 | I29: =H29*$B$4 -> 4432.3226 | J29: =SUM(H29) -> 206 | K29: =J29*$B$4 -> 4432.3226 | L29: =SUM(J29) -> 206 | M29: =L29*$B$4 -> 4432.3226 | N29: =SUM(L29) -> 206 | O29: =N29*$B$4 -> 4432.3226 | P29: =SUM(N29) -> 206 | Q29: =P29*$B$4 -> 4432.3226 | R29: =SUM(P29) -> 206 | S29: =R29*$B$4 -> 4432.3226 | T29: =SUM(R29) -> 206 | U29: =T29*$B$4 -> 4432.3226 | V29: =SUM(T29) -> 206 | W29: =V29*$B$4 -> 4432.3226 | X29: =SUM(Y29/73370) -> 0.66451613 | Y29: =SUM(C29+E29+G29+I29+K29+M29+O29+Q29+S29+U29+W29) -> 48755.548 | Z29: ='B5'!C28 -> 136 | AA29: =SUM(Z29*$Z$4) -> 1360 | AB29: =SUM(Z29) -> 136 | AC29: =SUM(AB29*$Z$4) -> 1360 | AD29: =SUM(AB29) -> 136 | AE29: =SUM(AD29*$Z$4) -> 1360 | AF29: =SUM(AD29) -> 136 | AG29: =SUM(AF29*$Z$4) -> 1360 | AH29: =SUM(AF29) -> 136 | AI29: =SUM(AH29*$Z$4) -> 1360 | AJ29: =SUM(AH29) -> 136 | AK29: =SUM(AJ29*$Z$4) -> 1360 | AL29: =SUM(AJ29) -> 136 | AM29: =SUM(AL29*$Z$4) -> 1360 | AN29: =SUM(AO29/19600) -> 0.48571429 | AO29: =SUM(AA29+AC29+AE29+AG29+AI29+AK29+AM29) -> 9520 | AQ29: =SUM(AR29/92970) -> 0.626821 | AR29: =SUM(AO29+Y29) -> 58275.548 | AS29: =SUM(AR29-AR28-AT29) -> -1340.0323 | AV29: =IF(AT29>0,AU29,AV28) -> 0.53 | AW29: =-SUM('B5'!AI28) -> -548 | AX29: =-SUM(AW29-AS29) -> -792.03226 | AY29: =SUM(AX29+AW29) -> -1340.0323 | AZ29: =ELEC!A26 -> 0.2174 | BA29: ='General information '!D29 -> 17 | BB29: =SUM('General information '!E29) -> 0.54 | BC29: =IF(AR28>=AR29,0,1) -> 0 | BD29: 19222 | BE29: =(305/1185)*ELEC!Q27 -> 772.1519 | BG29: =#REF!-BE29 -> #REF!
A30: =ELEC!C27 -> 43824 | B30: ='B5'!B29 -> 202 | C30: =B30*$B$4 -> 4346.2581 | D30: =SUM(B30) -> 202 | E30: =D30*$B$4 -> 4346.2581 | F30: =SUM(D30) -> 202 | G30: =F30*$B$4 -> 4346.2581 | H30: =SUM(F30) -> 202 | I30: =H30*$B$4 -> 4346.2581 | J30: =SUM(H30) -> 202 | K30: =J30*$B$4 -> 4346.2581 | L30: =SUM(J30) -> 202 | M30: =L30*$B$4 -> 4346.2581 | N30: =SUM(L30) -> 202 | O30: =N30*$B$4 -> 4346.2581 | P30: =SUM(N30) -> 202 | Q30: =P30*$B$4 -> 4346.2581 | R30: =SUM(P30) -> 202 | S30: =R30*$B$4 -> 4346.2581 | T30: =SUM(R30) -> 202 | U30: =T30*$B$4 -> 4346.2581 | V30: =SUM(T30) -> 202 | W30: =V30*$B$4 -> 4346.2581 | X30: =SUM(Y30/73370) -> 0.6516129 | Y30: =SUM(C30+E30+G30+I30+K30+M30+O30+Q30+S30+U30+W30) -> 47808.839 | Z30: ='B5'!C29 -> 118 | AA30: =SUM(Z30*$Z$4) -> 1180 | AB30: =SUM(Z30) -> 118 | AC30: =SUM(AB30*$Z$4) -> 1180 | AD30: =SUM(AB30) -> 118 | AE30: =SUM(AD30*$Z$4) -> 1180 | AF30: =SUM(AD30) -> 118 | AG30: =SUM(AF30*$Z$4) -> 1180 | AH30: =SUM(AF30) -> 118 | AI30: =SUM(AH30*$Z$4) -> 1180 | AJ30: =SUM(AH30) -> 118 | AK30: =SUM(AJ30*$Z$4) -> 1180 | AL30: =SUM(AJ30) -> 118 | AM30: =SUM(AL30*$Z$4) -> 1180 | AN30: =SUM(AO30/19600) -> 0.42142857 | AO30: =SUM(AA30+AC30+AE30+AG30+AI30+AK30+AM30) -> 8260 | AQ30: =SUM(AR30/92970) -> 0.60308528 | AR30: =SUM(AO30+Y30) -> 56068.839 | AS30: =SUM(AR30-AR29-AT30) -> -2206.7097 | AV30: =IF(AT30>0,AU30,AV29) -> 0.53 | AW30: =-SUM('B5'!AI29) -> -952.4 | AX30: =-SUM(AW30-AS30) -> -1254.3097 | AY30: =SUM(AX30+AW30) -> -2206.7097 | AZ30: =ELEC!A27 -> 0.2043 | BA30: ='General information '!D30 -> 16 | BB30: =SUM('General information '!E30) -> 0.55 | BC30: =IF(AR29>=AR30,0,1) -> 0 | BD30: 19222 | BE30: =(305/1185)*ELEC!Q28 -> 817.70886 | BG30: =#REF!-BE30 -> #REF!
A31: =ELEC!C28 -> 43825 | B31: ='B5'!B30 -> 181 | C31: =B31*$B$4 -> 3894.4194 | D31: =SUM(B31) -> 181 | E31: =D31*$B$4 -> 3894.4194 | F31: =SUM(D31) -> 181 | G31: =F31*$B$4 -> 3894.4194 | H31: =SUM(F31) -> 181 | I31: =H31*$B$4 -> 3894.4194 | J31: =SUM(H31) -> 181 | K31: =J31*$B$4 -> 3894.4194 | L31: =SUM(J31) -> 181 | M31: =L31*$B$4 -> 3894.4194 | N31: =SUM(L31) -> 181 | O31: =N31*$B$4 -> 3894.4194 | P31: =SUM(N31) -> 181 | Q31: =P31*$B$4 -> 3894.4194 | R31: =SUM(P31) -> 181 | S31: =R31*$B$4 -> 3894.4194 | T31: =SUM(R31) -> 181 | U31: =T31*$B$4 -> 3894.4194 | V31: =SUM(T31) -> 181 | W31: =V31*$B$4 -> 3894.4194 | X31: =SUM(Y31/73370) -> 0.58387097 | Y31: =SUM(C31+E31+G31+I31+K31+M31+O31+Q31+S31+U31+W31) -> 42838.613 | Z31: ='B5'!C30 -> 162 | AA31: =SUM(Z31*$Z$4) -> 1620 | AB31: =SUM(Z31) -> 162 | AC31: =SUM(AB31*$Z$4) -> 1620 | AD31: =SUM(AB31) -> 162 | AE31: =SUM(AD31*$Z$4) -> 1620 | AF31: =SUM(AD31) -> 162 | AG31: =SUM(AF31*$Z$4) -> 1620 | AH31: =SUM(AF31) -> 162 | AI31: =SUM(AH31*$Z$4) -> 1620 | AJ31: =SUM(AH31) -> 162 | AK31: =SUM(AJ31*$Z$4) -> 1620 | AL31: =SUM(AJ31) -> 162 | AM31: =SUM(AL31*$Z$4) -> 1620 | AN31: =SUM(AO31/19600) -> 0.57857143 | AO31: =SUM(AA31+AC31+AE31+AG31+AI31+AK31+AM31) -> 11340 | AQ31: =SUM(AR31/92970) -> 0.58275372 | AR31: =SUM(AO31+Y31) -> 54178.613 | AS31: =SUM(AR31-AR30-AT31) -> -1890.2258 | AV31: =IF(AT31>0,AU31,AV30) -> 0.53 | AW31: =-SUM('B5'!AI30) -> -1017.6 | AX31: =-SUM(AW31-AS31) -> -872.62581 | AY31: =SUM(AX31+AW31) -> -1890.2258 | AZ31: =ELEC!A28 -> 0.2174 | BA31: ='General information '!D31 -> 15.5 | BB31: =SUM('General information '!E32) -> 0.77 | BC31: =IF(AR30>=AR31,0,1) -> 0 | BD31: 19222 | BE31: =(305/1185)*ELEC!Q29 -> 983.9789 | BG31: =#REF!-BE31 -> #REF!
A32: =ELEC!C29 -> 43826 | B32: ='B5'!B31 -> 213 | C32: =B32*$B$4 -> 4582.9355 | D32: =SUM(B32) -> 213 | E32: =D32*$B$4 -> 4582.9355 | F32: =SUM(D32) -> 213 | G32: =F32*$B$4 -> 4582.9355 | H32: =SUM(F32) -> 213 | I32: =H32*$B$4 -> 4582.9355 | J32: =SUM(H32) -> 213 | K32: =J32*$B$4 -> 4582.9355 | L32: =SUM(J32) -> 213 | M32: =L32*$B$4 -> 4582.9355 | N32: =SUM(L32) -> 213 | O32: =N32*$B$4 -> 4582.9355 | P32: =SUM(N32) -> 213 | Q32: =P32*$B$4 -> 4582.9355 | R32: =SUM(P32) -> 213 | S32: =R32*$B$4 -> 4582.9355 | T32: =SUM(R32) -> 213 | U32: =T32*$B$4 -> 4582.9355 | V32: =SUM(T32) -> 213 | W32: =V32*$B$4 -> 4582.9355 | X32: =SUM(Y32/73370) -> 0.68709677 | Y32: =SUM(C32+E32+G32+I32+K32+M32+O32+Q32+S32+U32+W32) -> 50412.29 | Z32: ='B5'!C31 -> 139 | AA32: =SUM(Z32*$Z$4) -> 1390 | AB32: =SUM(Z32) -> 139 | AC32: =SUM(AB32*$Z$4) -> 1390 | AD32: =SUM(AB32) -> 139 | AE32: =SUM(AD32*$Z$4) -> 1390 | AF32: =SUM(AD32) -> 139 | AG32: =SUM(AF32*$Z$4) -> 1390 | AH32: =SUM(AF32) -> 139 | AI32: =SUM(AH32*$Z$4) -> 1390 | AJ32: =SUM(AH32) -> 139 | AK32: =SUM(AJ32*$Z$4) -> 1390 | AL32: =SUM(AJ32) -> 139 | AM32: =SUM(AL32*$Z$4) -> 1390 | AN32: =SUM(AO32/19600) -> 0.49642857 | AO32: =SUM(AA32+AC32+AE32+AG32+AI32+AK32+AM32) -> 9730 | AQ32: =SUM(AR32/92970) -> 0.64689997 | AR32: =SUM(AO32+Y32) -> 60142.29 | AS32: =SUM(AR32-AR31-AT32) -> -2916.3226 | AT32: 8880 | AU32: 0.5634 | AV32: =IF(AT32>0,AU32,AV31) -> 0.5634 | AW32: =-SUM('B5'!AI31) -> -1203.7 | AX32: =-SUM(AW32-AS32) -> -1712.6226 | AY32: =SUM(AX32+AW32) -> -2916.3226 | AZ32: =ELEC!A29 -> 0.2913 | BA32: ='General information '!D32 -> 14.5 | BB32: =SUM('General information '!E33) -> 0.55 | BC32: =IF(AR31>=AR32,0,1) -> 1 | BD32: 19222 | BE32: =(305/1185)*ELEC!Q30 -> 772.1519 | BG32: =#REF!-BE32 -> #REF!
A33: =ELEC!C30 -> 43827 | B33: ='B5'!B32 -> 209 | C33: =B33*$B$4 -> 4496.871 | D33: =SUM(B33) -> 209 | E33: =D33*$B$4 -> 4496.871 | F33: =SUM(D33) -> 209 | G33: =F33*$B$4 -> 4496.871 | H33: =SUM(F33) -> 209 | I33: =H33*$B$4 -> 4496.871 | J33: =SUM(H33) -> 209 | K33: =J33*$B$4 -> 4496.871 | L33: =SUM(J33) -> 209 | M33: =L33*$B$4 -> 4496.871 | N33: =SUM(L33) -> 209 | O33: =N33*$B$4 -> 4496.871 | P33: =SUM(N33) -> 209 | Q33: =P33*$B$4 -> 4496.871 | R33: =SUM(P33) -> 209 | S33: =R33*$B$4 -> 4496.871 | T33: =SUM(R33) -> 209 | U33: =T33*$B$4 -> 4496.871 | V33: =SUM(T33) -> 209 | W33: =V33*$B$4 -> 4496.871 | X33: =SUM(Y33/73370) -> 0.67419355 | Y33: =SUM(C33+E33+G33+I33+K33+M33+O33+Q33+S33+U33+W33) -> 49465.581 | Z33: ='B5'!C32 -> 120 | AA33: =SUM(Z33*$Z$4) -> 1200 | AB33: =SUM(Z33) -> 120 | AC33: =SUM(AB33*$Z$4) -> 1200 | AD33: =SUM(AB33) -> 120 | AE33: =SUM(AD33*$Z$4) -> 1200 | AF33: =SUM(AD33) -> 120 | AG33: =SUM(AF33*$Z$4) -> 1200 | AH33: =SUM(AF33) -> 120 | AI33: =SUM(AH33*$Z$4) -> 1200 | AJ33: =SUM(AH33) -> 120 | AK33: =SUM(AJ33*$Z$4) -> 1200 | AL33: =SUM(AJ33) -> 120 | AM33: =SUM(AL33*$Z$4) -> 1200 | AN33: =SUM(AO33/19600) -> 0.42857143 | AO33: =SUM(AA33+AC33+AE33+AG33+AI33+AK33+AM33) -> 8400 | AQ33: =SUM(AR33/92970) -> 0.62241132 | AR33: =SUM(AO33+Y33) -> 57865.581 | AS33: =SUM(AR33-AR32-AT33) -> -2276.7097 | AV33: =IF(AT33>0,AU33,AV32) -> 0.5634 | AW33: =-SUM('B5'!AI32) -> -1073.9 | AX33: =-SUM(AW33-AS33) -> -1202.8097 | AY33: =SUM(AX33+AW33) -> -2276.7097 | AZ33: =ELEC!A30 -> 0.2913 | BA33: ='General information '!D33 -> 15 | BB33: =SUM('General information '!E33) -> 0.55 | BC33: =IF(AR32>=AR33,0,1) -> 0 | BD33: 19222 | BE33: =(305/1185)*ELEC!Q31 -> 946.65823 | BG33: =#REF!-BE33 -> #REF!
