Workbook

Sheet Total
A1: Site Name | B1: Day | C1: Month | D1: Year | E1: Total Electricity Kwh | F1: Electricity Tariff ($/Kwh) | G1: Total Fuel Oil (Liters) | H1: Fuel Oil $/Liter | I1: LPG (Kg) | J1: LPG $/Kg | K1: Water Utility Supply (m3) m3 | L1: Water Utility Supply (m3) $/m3 | M1: Irrigation Water (m3) m3 | N1: Irrigation water $/m3 | O1: Room Nights
A2: Beirut | B2: 1 | C2: 1 | D2: 2020 | E2: =ELEC!N3 -> 14239 | F2: =SUM('EDl log'!T4) -> 0.081556957 | G2: =-tanks!AW6 -> 1458 | H2: =SUM(tanks!AV6) -> 0.5634 | I2: =('B5'!AU5)*0.51 -> 91.8 | J2: ='B5'!AX5/0.51 -> 1.372549 | K2: =WATER!I6 -> 19 | L2: =SUM(WATER!J6) -> 12.733447 | M2: =WATER!Q6 -> 0 | N2: 0.6 | O2: =ELEC!B3 -> 97.98
A3: Beirut | B3: =B2+1 -> 2 | C3: 1 | D3: 2020 | E3: =ELEC!N4 -> 15103 | F3: =SUM('EDl log'!T5) -> 0.082230343 | G3: =-tanks!AW7 -> 1092.3 | H3: =SUM(tanks!AV7) -> 0.5634 | I3: =('B5'!AU6)*0.51 -> 265.2 | J3: ='B5'!AX6/0.51 -> 1.372549 | K3: =WATER!I7 -> 316 | L3: =SUM(WATER!J7) -> 1.1858718 | M3: =WATER!Q7 -> 0 | N3: 0.6 | O3: =ELEC!B4 -> 77.004
A4: Beirut | B4: =B3+1 -> 3 | C4: 1 | D4: 2020 | E4: =ELEC!N5 -> 15173 | F4: =SUM('EDl log'!T6) -> 0.095740939 | G4: =-tanks!AW8 -> 1325.9 | H4: =SUM(tanks!AV8) -> 0.5634 | I4: =('B5'!AU7)*0.51 -> 91.8 | J4: ='B5'!AX7/0.51 -> 1.372549 | K4: =WATER!I8 -> 0 | L4: =SUM(WATER!J8) -> 0 | M4: =WATER!Q8 -> 0 | N4: 0.6 | O4: =ELEC!B5 -> 63.986
A5: Beirut | B5: =B4+1 -> 4 | C5: 1 | D5: 2020 | E5: =ELEC!N6 -> 15817 | F5: =SUM('EDl log'!T7) -> 0.11317896 | G5: =-tanks!AW9 -> 944 | H5: =SUM(tanks!AV9) -> 0.5634 | I5: =('B5'!AU8)*0.51 -> 122.4 | J5: ='B5'!AX8/0.51 -> 1.372549 | K5: =WATER!I9 -> 288 | L5: =SUM(WATER!J9) -> 0.84005376 | M5: =WATER!Q9 -> 0 | N5: 0.6 | O5: =ELEC!B6 -> 48.99
A6: Beirut | B6: =B5+1 -> 5 | C6: 1 | D6: 2020 | E6: =ELEC!N7 -> 12909 | F6: =SUM('EDl log'!T8) -> 0.073554428 | G6: =-tanks!AW10 -> 1107.7 | H6: =SUM(tanks!AV10) -> 0.5634 | I6: =('B5'!AU9)*0.51 -> 137.7 | J6: ='B5'!AX9/0.51 -> 1.372549 | K6: =WATER!I10 -> 0 | L6: =SUM(WATER!J10) -> 0 | M6: =WATER!Q10 -> 0 | N6: 0.6 | O6: =ELEC!B7 -> 37.007
A7: Beirut | B7: =B6+1 -> 6 | C7: 1 | D7: 2020 | E7: =ELEC!N8 -> 13138 | F7: =SUM('EDl log'!T9) -> 0.14193241 | G7: =-tanks!AW11 -> 607 | H7: =SUM(tanks!AV11) -> 0.5634 | I7: =('B5'!AU10)*0.51 -> 91.8 | J7: ='B5'!AX10/0.51 -> 1.372549 | K7: =WATER!I11 -> 179 | L7: =SUM(WATER!J11) -> 1.3515949 | M7: =WATER!Q11 -> 0 | N7: 0.6 | O7: =ELEC!B8 -> 37.996
A8: Beirut | B8: =B7+1 -> 7 | C8: 1 | D8: 2020 | E8: =ELEC!N9 -> 12872 | F8: =SUM('EDl log'!T10) -> 0.082327928 | G8: =-tanks!AW12 -> 1019.3 | H8: =SUM(tanks!AV12) -> 0.5634 | I8: =('B5'!AU11)*0.51 -> 107.1 | J8: ='B5'!AX11/0.51 -> 1.372549 | K8: =WATER!I12 -> 79 | L8: =SUM(WATER!J12) -> 4.7224745 | M8: =WATER!Q12 -> 0 | N8: 0.6 | O8: =ELEC!B9 -> 54.004
A9: Beirut | B9: =B8+1 -> 8 | C9: 1 | D9: 2020 | E9: =ELEC!N10 -> 12536.4 | F9: =SUM('EDl log'!T11) -> 0.16507208 | G9: =-tanks!AW13 -> 816 | H9: =SUM(tanks!AV13) -> 0.5634 | I9: =('B5'!AU12)*0.51 -> 122.4 | J9: ='B5'!AX12/0.51 -> 1.372549 | K9: =WATER!I13 -> 182 | L9: =SUM(WATER!J13) -> 1.3293158 | M9: =WATER!Q13 -> 0 | N9: 0.6 | O9: =ELEC!B10 -> 53.82
A10: Beirut | B10: =B9+1 -> 9 | C10: 1 | D10: 2020 | E10: =ELEC!N11 -> 13631.6 | F10: =SUM('EDl log'!T12) -> 0.17418775 | G10: =-tanks!AW14 -> 853 | H10: =SUM(tanks!AV14) -> 0.5765 | I10: =('B5'!AU13)*0.51 -> 183.6 | J10: ='B5'!AX13/0.51 -> 1.372549 | K10: =WATER!I14 -> 80 | L10: =SUM(WATER!J14) -> 4.6841935 | M10: =WATER!Q14 -> 0 | N10: 0.6 | O10: =ELEC!B11 -> 48.001
A11: Beirut | B11: =B10+1 -> 10 | C11: 1 | D11: 2020 | E11: =ELEC!N12 -> 13062.8 | F11: =SUM('EDl log'!T13) -> 0.060227321 | G11: =-tanks!AW15 -> 1461.8 | H11: =SUM(tanks!AV15) -> 0.5765 | I11: =('B5'!AU14)*0.51 -> 61.2 | J11: ='B5'!AX14/0.51 -> 1.372549 | K11: =WATER!I15 -> 343 | L11: =SUM(WATER!J15) -> 0.70535126 | M11: =WATER!Q15 -> 0 | N11: 0.6 | O11: =ELEC!B12 -> 46
A12: Beirut | B12: =B11+1 -> 11 | C12: 1 | D12: 2020 | E12: =ELEC!N13 -> 14011.2 | F12: =SUM('EDl log'!T14) -> 0.095134534 | G12: =-tanks!AW16 -> 728 | H12: =SUM(tanks!AV16) -> 0.5765 | I12: =('B5'!AU15)*0.51 -> 45.9 | J12: ='B5'!AX15/0.51 -> 1.372549 | K12: =WATER!I16 -> 0 | L12: =SUM(WATER!J16) -> 0 | M12: =WATER!Q16 -> 0 | N12: 0.6 | O12: =ELEC!B13 -> 39.008
A13: Beirut | B13: =B12+1 -> 12 | C13: 1 | D13: 2020 | E13: =ELEC!N14 -> 14175 | F13: =SUM('EDl log'!T15) -> 0.071130652 | G13: =-tanks!AW17 -> 543 | H13: =SUM(tanks!AV17) -> 0.5765 | I13: =('B5'!AU16)*0.51 -> 122.4 | J13: ='B5'!AX16/0.51 -> 1.372549 | K13: =WATER!I17 -> 737 | L13: =SUM(WATER!J17) -> 0.32827067 | M13: =WATER!Q17 -> 0 | N13: 0.6 | O13: =ELEC!B14 -> 39.997
A14: Beirut | B14: =B13+1 -> 13 | C14: 1 | D14: 2020 | E14: =ELEC!N15 -> 12801 | F14: =SUM('EDl log'!T16) -> 0.089701147 | G14: =-tanks!AW18 -> 749 | H14: =SUM(tanks!AV18) -> 0.5765 | I14: =('B5'!AU17)*0.51 -> 122.4 | J14: ='B5'!AX17/0.51 -> 1.372549 | K14: =WATER!I18 -> 0 | L14: =SUM(WATER!J18) -> 0 | M14: =WATER!Q18 -> 0 | N14: 0.6 | O14: =ELEC!B15 -> 41.998
... A32: Beirut | B32: =B31+1 -> 31 | C32: 1 | D32: 2020 | E32: =ELEC!N33 -> 0 | F32: =SUM('EDl log'!T34) -> 0 | G32: =-tanks!AW36 -> 0 | H32: =SUM(tanks!AV36) -> 0.58 | I32: =('B5'!AU35)*0.51 -> 0 | J32: ='B5'!AX35/0.51 -> 1.372549 | K32: =WATER!I36 -> 0 | L32: =SUM(WATER!J36) -> 0 | M32: =WATER!Q36 -> 0 | N32: 0.6 | O32: =ELEC!B33 -> 0

Sheet Submetering
A1: Site Name | B1: Day | C1: Month | D1: Year | E1: ATS1 Kwh | F1: ATS2 Kwh | G1: ATS3 Kwh | H1: ATS4 Kwh | I1: ATS5 Kwh | J1: Guest (m3) | K1: Kitchen & Laundry (m3) | L1: Room Nights
A2: Beirut | B2: 1 | C2: 1 | D2: 2020 | E2: =ELEC!M3 -> 4850 | F2: =ELEC!K3 -> 1588 | G2: =ELEC!I3 -> 2628 | H2: =ELEC!E3 -> 2900 | I2: =ELEC!G3 -> 2273 | J2: =WATER!Y6 -> 48 | K2: =WATER!AJ6 -> 81 | L2: =ELEC!B3 -> 97.98
A3: Beirut | B3: =B2+1 -> 2 | C3: 1 | D3: 2020 | E3: =ELEC!M4 -> 4714 | F3: =ELEC!K4 -> 1882 | G3: =ELEC!I4 -> 2598 | H3: =ELEC!E4 -> 3560 | I3: =ELEC!G4 -> 2349 | J3: =WATER!Y7 -> 88 | K3: =WATER!AJ7 -> 59 | L3: =ELEC!B4 -> 77.004
A4: Beirut | B4: =B3+1 -> 3 | C4: 1 | D4: 2020 | E4: =ELEC!M5 -> 4880 | F4: =ELEC!K5 -> 1846 | G4: =ELEC!I5 -> 2558 | H4: =ELEC!E5 -> 3438 | I4: =ELEC!G5 -> 2451 | J4: =WATER!Y8 -> 20 | K4: =WATER!AJ8 -> 27 | L4: =ELEC!B5 -> 63.986
A5: Beirut | B5: =B4+1 -> 4 | C5: 1 | D5: 2020 | E5: =ELEC!M6 -> 5028 | F5: =ELEC!K6 -> 2324 | G5: =ELEC!I6 -> 2522 | H5: =ELEC!E6 -> 3480 | I5: =ELEC!G6 -> 2463 | J5: =WATER!Y9 -> 98 | K5: =WATER!AJ9 -> 2 | L5: =ELEC!B6 -> 48.99
A6: Beirut | B6: =B5+1 -> 5 | C6: 1 | D6: 2020 | E6: =ELEC!M7 -> 4398 | F6: =ELEC!K7 -> 1702 | G6: =ELEC!I7 -> 2078 | H6: =ELEC!E7 -> 2736 | I6: =ELEC!G7 -> 1995 | J6: =WATER!Y10 -> 4 | K6: =WATER!AJ10 -> 53 | L6: =ELEC!B7 -> 37.007
A7: Beirut | B7: =B6+1 -> 6 | C7: 1 | D7: 2020 | E7: =ELEC!M8 -> 3870 | F7: =ELEC!K8 -> 1900 | G7: =ELEC!I8 -> 2188 | H7: =ELEC!E8 -> 3034 | I7: =ELEC!G8 -> 2146 | J7: =WATER!Y11 -> 54 | K7: =WATER!AJ11 -> 57 | L7: =ELEC!B8 -> 37.996
A8: Beirut | B8: =B7+1 -> 7 | C8: 1 | D8: 2020 | E8: =ELEC!M9 -> 3880 | F8: =ELEC!K9 -> 1810 | G8: =ELEC!I9 -> 2068 | H8: =ELEC!E9 -> 2972 | I8: =ELEC!G9 -> 2142 | J8: =WATER!Y12 -> 0 | K8: =WATER!AJ12 -> 31 | L8: =ELEC!B9 -> 54.004
A9: Beirut | B9: =B8+1 -> 8 | C9: 1 | D9: 2020 | E9: =ELEC!M10 -> 3650 | F9: =ELEC!K10 -> 1850 | G9: =ELEC!I10 -> 2170 | H9: =ELEC!E10 -> 2648 | I9: =ELEC!G10 -> 2218.4 | J9: =WATER!Y13 -> 68 | K9: =WATER!AJ13 -> 58 | L9: =ELEC!B10 -> 53.82
A10: Beirut | B10: =B9+1 -> 9 | C10: 1 | D10: 2020 | E10: =ELEC!M11 -> 4112 | F10: =ELEC!K11 -> 1578 | G10: =ELEC!I11 -> 2178 | H10: =ELEC!E11 -> 3440 | I10: =ELEC!G11 -> 2323.6 | J10: =WATER!Y14 -> 52 | K10: =WATER!AJ14 -> 4 | L10: =ELEC!B11 -> 48.001
A11: Beirut | B11: =B10+1 -> 10 | C11: 1 | D11: 2020 | E11: =ELEC!M12 -> 3938 | F11: =ELEC!K12 -> 1634 | G11: =ELEC!I12 -> 2182 | H11: =ELEC!E12 -> 3044 | I11: =ELEC!G12 -> 2264.8 | J11: =WATER!Y15 -> 140 | K11: =WATER!AJ15 -> 51 | L11: =ELEC!B12 -> 46
A12: Beirut | B12: =B11+1 -> 11 | C12: 1 | D12: 2020 | E12: =ELEC!M13 -> 4798 | F12: =ELEC!K13 -> 1598 | G12: =ELEC!I13 -> 2306 | H12: =ELEC!E13 -> 3078 | I12: =ELEC!G13 -> 2231.2 | J12: =WATER!Y16 -> 67 | K12: =WATER!AJ16 -> 35 | L12: =ELEC!B13 -> 39.008
A13: Beirut | B13: =B12+1 -> 12 | C13: 1 | D13: 2020 | E13: =ELEC!M14 -> 4462 | F13: =ELEC!K14 -> 1534 | G13: =ELEC!I14 -> 2480 | H13: =ELEC!E14 -> 3214 | I13: =ELEC!G14 -> 2485 | J13: =WATER!Y17 -> 101 | K13: =WATER!AJ17 -> 110 | L13: =ELEC!B14 -> 39.997
A14: Beirut | B14: =B13+1 -> 13 | C14: 1 | D14: 2020 | E14: =ELEC!M15 -> 3916 | F14: =ELEC!K15 -> 2088 | G14: =ELEC!I15 -> 2052 | H14: =ELEC!E15 -> 2560 | I14: =ELEC!G15 -> 2185 | J14: =WATER!Y18 -> 75 | K14: =WATER!AJ18 -> 0 | L14: =ELEC!B15 -> 41.998
... A32: Beirut | B32: =B31+1 -> 31 | C32: 1 | D32: 2020 | E32: =ELEC!M33 -> 0 | F32: =ELEC!K33 -> 0 | G32: =ELEC!I33 -> 0 | H32: =ELEC!E33 -> 0 | I32: =ELEC!G33 -> 0 | J32: =WATER!Y36 -> 0 | K32: =WATER!AJ36 -> 0 | L32: =ELEC!B33 -> 0

Sheet ELEC
A1: OOC | B1: Room OCC | D1: MDB3 | E1: MDB3/day | F1: EMDB2 | G1: EMDB2/day | H1: EMDB1 | I1: EMDB1/day | J1: MDB2 | K1: mdb2/day | L1: MDB1 | M1: MDB1/Day | N1: Total KWH | O1: KWH/Rooc | P1: Gen MHW | Q1: Gen/Day KWH | R1: EDL KWH | S1: CH1 RH | T1: RH | U1: C1h1 power | V1: CH1 Con KWH | W1: CH2 RH | X1: RH | Y1: Ch2 power | Z1: CH2 Con KWH | AA1: CH3 RH | AB1: RH | AC1: Ch3 power | AD1: CH3 Con KWH | AE1: RH total | AF1: KWH total | AG1: AVG chiller KW/Hr
A2: 0.1391 | B2: 0.1391 | C2: 31-12-2019 | D2: =[1]ELEC!D33 -> 31308238 | E2: =[1]ELEC!E33 -> 3678 | F2: =[1]ELEC!F33 -> 3431349 | G2: =[1]ELEC!G33 -> 2479 | H2: =[1]ELEC!H33 -> 17219918 | I2: =[1]ELEC!I33 -> 2804 | J2: =[1]ELEC!J33 -> 28230090 | K2: =[1]ELEC!K33 -> 3048 | ... AI2: =[1]ELEC!AI33 -> -49239434
A3: ='General information '!F6 -> 0.426 | B3: =SUM(230*A3) -> 97.98 | C3: 43831 | D3: 31311138 | E3: =D3-D2 -> 2900 | F3: 3433622 | G3: =F3-F2 -> 2273 | H3: 17222546 | I3: =H3-H2 -> 2628 | J3: 28231678 | K3: =J3-J2 -> 1588 | L3: 22527696 | M3: =L3-L2 -> 4850 | N3: =M3+K3+I3+G3+E3 -> 14239 | O3: =IF(B3>0,N3/B3,0) -> 145.32558 | P3: 15220.747 | Q3: =(P3-P2)*1000 -> 2547 | R3: =+N3-Q3 -> 11692 | S3: 8341 | T3: =S3-S2 -> 7 | U3: 1015726 | V3: =U3-U2 -> 1093 | W3: 31800 | X3: =W3-W2 -> 0 | Y3: 616769 | Z3: =Y3-Y2 -> 0 | AA3: 34851 | AB3: =AA3-AA2 -> 0 | AC3: 735699 | AD3: =AC3-AC2 -> 0 | AE3: =AB3+X3+T3 -> 7 | AF3: =V3+Z3+AD3 -> 1093 | AG3: =IF(AE3>0,AF3/AE3,0) -> 156.14286
A4: ='General information '!F7 -> 0.3348 | B4: =SUM(230*A4) -> 77.004 | C4: 43832 | D4: 31314698 | E4: =D4-D3 -> 3560 | F4: 3435971 | G4: =F4-F3 -> 2349 | H4: 17225144 | I4: =H4-H3 -> 2598 | J4: 28233560 | K4: =J4-J3 -> 1882 | L4: 22532410 | M4: =L4-L3 -> 4714 | N4: =M4+K4+I4+G4+E4 -> 15103 | O4: =IF(B4>0,N4/B4,0) -> 196.13267 | P4: 15225.369 | Q4: =(P4-P3)*1000 -> 4622 | R4: =N4-Q4 -> 10481 | S4: 8345 | T4: =S4-S3 -> 4 | U4: 1016381 | V4: =U4-U3 -> 655 | W4: 31802 | X4: =W4-W3 -> 2 | Y4: 617066 | Z4: =Y4-Y3 -> 297 | AA4: 34853 | AB4: =AA4-AA3 -> 2 | AC4: 736029 | AD4: =AC4-AC3 -> 330 | AE4: =AB4+X4+T4 -> 8 | AF4: =V4+Z4+AD4 -> 1282 | AG4: =IF(AE4>0,AF4/AE4,0) -> 160.25
A5: ='General information '!F8 -> 0.2782 | B5: =SUM(230*A5) -> 63.986 | C5: 43833 | D5: 31318136 | E5: =D5-D4 -> 3438 | F5: 3438422 | G5: =F5-F4 -> 2451 | H5: 17227702 | I5: =H5-H4 -> 2558 | J5: 28235406 | K5: =J5-J4 -> 1846 | L5: 22537290 | M5: =L5-L4 -> 4880 | N5: =M5+K5+I5+G5+E5 -> 15173 | O5: =IF(B5>0,N5/B5,0) -> 237.13 | P5: 15230 | Q5: =(P5-P4)*1000 -> 4631 | R5: =N5-Q5 -> 10542 | S5: 8350 | T5: =S5-S4 -> 5 | U5: 1017190 | V5: =U5-U4 -> 809 | W5: 31804 | X5: =W5-W4 -> 2 | Y5: 617292 | Z5: =Y5-Y4 -> 226 | AA5: 34855 | AB5: =AA5-AA4 -> 2 | AC5: 736416 | AD5: =AC5-AC4 -> 387 | AE5: =AB5+X5+T5 -> 9 | AF5: =V5+Z5+AD5 -> 1422 | AG5: =IF(AE5>0,AF5/AE5,0) -> 158 | AI5: =R5-'EDl log'!B3 -> -49262991
A6: ='General information '!F9 -> 0.213 | B6: =SUM(230*A6) -> 48.99 | C6: 43834 | D6: 31321616 | E6: =D6-D5 -> 3480 | F6: 3440885 | G6: =F6-F5 -> 2463 | H6: 17230224 | I6: =H6-H5 -> 2522 | J6: 28237730 | K6: =J6-J5 -> 2324 | L6: 22542318 | M6: =L6-L5 -> 5028 | N6: =M6+K6+I6+G6+E6 -> 15817 | O6: =IF(B6>0,N6/B6,0) -> 322.86181 | P6: 15234 | Q6: =(P6-P5)*1000 -> 4000 | R6: =N6-Q6 -> 11817 | S6: 8352 | T6: =S6-S5 -> 2 | U6: 1017672 | V6: =U6-U5 -> 482 | W6: 31807 | X6: =W6-W5 -> 3 | Y6: 617924 | Z6: =Y6-Y5 -> 632 | AA6: 34855 | AB6: =AA6-AA5 -> 0 | AC6: =AC5 -> 736416 | AD6: =AC6-AC5 -> 0 | AE6: =AB6+X6+T6 -> 5 | AF6: =V6+Z6+AD6 -> 1114 | AG6: =IF(AE6>0,AF6/AE6,0) -> 222.8 | AI6: =R6-'EDl log'!B4 -> -49267868
A7: ='General information '!F10 -> 0.1609 | B7: =SUM(230*A7) -> 37.007 | C7: 43835 | D7: 31324352 | E7: =D7-D6 -> 2736 | F7: 3442880 | G7: =F7-F6 -> 1995 | H7: 17232302 | I7: =H7-H6 -> 2078 | J7: 28239432 | K7: =J7-J6 -> 1702 | L7: 22546716 | M7: =L7-L6 -> 4398 | N7: =M7+K7+I7+G7+E7 -> 12909 | O7: =IF(B7>0,N7/B7,0) -> 348.8259 | P7: 15236.586 | Q7: =(P7-P6)*1000 -> 2586 | R7: =N7-Q24 -> 12909 | S7: 8355 | T7: =S7-S6 -> 3 | U7: 1018314 | V7: =U7-U6 -> 642 | W7: 31810 | X7: =W7-W6 -> 3 | Y7: 618493 | Z7: =Y7-Y6 -> 569 | AA7: 34856 | AB7: =AA7-AA6 -> 1 | AC7: 736573 | AD7: =AC7-AC6 -> 157 | AE7: =AB7+X7+T7 -> 7 | AF7: =V7+Z7+AD7 -> 1368 | AG7: =IF(AE7>0,AF7/AE7,0) -> 195.42857 | AI7: =R7-'EDl log'!B5 -> -49272196
A8: ='General information '!F11 -> 0.1652 | B8: =SUM(230*A8) -> 37.996 | C8: 43836 | D8: 31327386 | E8: =D8-D7 -> 3034 | F8: 3445026 | G8: =F8-F7 -> 2146 | H8: 17234490 | I8: =H8-H7 -> 2188 | J8: 28241332 | K8: =J8-J7 -> 1900 | L8: 22550586 | M8: =L8-L7 -> 3870 | N8: =M8+K8+I8+G8+E8 -> 13138 | O8: =IF(B8>0,N8/B8,0) -> 345.77324 | P8: 15241.82 | Q8: =(P8-P7)*1000 -> 5234 | R8: =N8-Q8 -> 7904 | S8: 8357 | T8: =S8-S7 -> 2 | U8: 1018561 | V8: =U8-U7 -> 247 | W8: 31813 | X8: =W8-W7 -> 3 | Y8: 619036 | Z8: =Y8-Y7 -> 543 | AA8: 34857 | AB8: =AA8-AA7 -> 1 | AC8: 736709 | AD8: =AC8-AC7 -> 136 | AE8: =AB8+X8+T8 -> 6 | AF8: =V8+Z8+AD8 -> 926 | AG8: =IF(AE8>0,AF8/AE8,0) -> 154.33333 | AI8: =R8-'EDl log'!B6 -> -49282366
A9: ='General information '!F12 -> 0.2348 | B9: =SUM(230*A9) -> 54.004 | C9: 43837 | D9: 31330358 | E9: =D9-D8 -> 2972 | F9: 3447168 | G9: =F9-F8 -> 2142 | H9: 17236558 | I9: =H9-H8 -> 2068 | J9: 28243142 | K9: =J9-J8 -> 1810 | L9: 22554466 | M9: =L9-L8 -> 3880 | N9: =M9+K9+I9+G9+E9 -> 12872 | O9: =IF(B9>0,N9/B9,0) -> 238.35271 | P9: 15246.699 | Q9: =(P9-P8)*1000 -> 4879 | R9: =N9-Q9 -> 7993 | S9: 8358 | T9: =S9-S8 -> 1 | U9: 1018775 | V9: =U9-U8 -> 214 | W9: 31816 | X9: =W9-W8 -> 3 | Y9: 619479 | Z9: =Y9-Y8 -> 443 | AA9: 34858 | AB9: =AA9-AA8 -> 1 | AC9: 736958 | AD9: =AC9-AC8 -> 249 | AE9: =AB9+X9+T9 -> 5 | AF9: =V9+Z9+AD9 -> 906 | AG9: =IF(AE9>0,AF9/AE9,0) -> 181.2 | AI9: =R9-'EDl log'!B7 -> -49288394
A10: ='General information '!F13 -> 0.234 | B10: =SUM(230*A10) -> 53.82 | C10: 43838 | D10: 31333006 | E10: =D10-D9 -> 2648 | F10: 3449386.4 | G10: =F10-F9 -> 2218.4 | H10: 17238728 | I10: =H10-H9 -> 2170 | J10: 28244992 | K10: =J10-J9 -> 1850 | L10: 22558116 | M10: =L10-L9 -> 3650 | N10: =M10+K10+I10+G10+E10 -> 12536.4 | O10: =IF(B10>0,N10/B10,0) -> 232.932 | P10: 15253.7 | Q10: =(P10-P9)*1000 -> 7001 | R10: =N10-Q10 -> 5535.4 | S10: =S9 -> 8358 | T10: =S10-S9 -> 0 | U10: =U9 -> 1018775 | V10: =U10-U9 -> 0 | W10: 31819 | X10: =W10-W9 -> 3 | Y10: 619891 | Z10: =Y10-Y9 -> 412 | AA10: 34858 | AB10: =AA10-AA9 -> 0 | AC10: =AC9 -> 736958 | AD10: =AC10-AC9 -> 0 | AE10: =AB10+X10+T10 -> 3 | AF10: =V10+Z10+AD10 -> 412 | AG10: =IF(AE10>0,AF10/AE10,0) -> 137.33333 | AI10: =R10-'EDl log'!B8 -> -49296483
A11: ='General information '!F14 -> 0.2087 | B11: =SUM(230*A11) -> 48.001 | C11: 43839 | D11: 31336446 | E11: =D11-D10 -> 3440 | F11: 3451710 | G11: =F11-F10 -> 2323.6 | H11: 17240906 | I11: =H11-H10 -> 2178 | J11: 28246570 | K11: =J11-J10 -> 1578 | L11: 22562228 | M11: =L11-L10 -> 4112 | N11: =M11+K11+I11+G11+E11 -> 13631.6 | O11: =IF(B11>0,N11/B11,0) -> 283.98575 | P11: 15258.586 | Q11: =(P11-P10)*1000 -> 4886 | R11: =N11-Q11 -> 8745.6 | S11: 8359 | T11: =S11-S10 -> 1 | U11: 1019129 | V11: =U11-U10 -> 354 | W11: 31819 | X11: =W11-W10 -> 0 | Y11: 619891 | Z11: =Y11-Y10 -> 0 | AA11: 34861 | AB11: =AA11-AA10 -> 3 | AC11: 737484 | AD11: =AC11-AC10 -> 526 | AE11: =AB11+X11+T11 -> 4 | AF11: =V11+Z11+AD11 -> 880 | AG11: =IF(AE11>0,AF11/AE11,0) -> 220 | AI11: =R11-'EDl log'!B9 -> -49297371
A12: ='General information '!F15 -> 0.2 | B12: =SUM(230*A12) -> 46 | C12: 43840 | D12: 31339490 | E12: =D12-D11 -> 3044 | F12: 3453974.8 | G12: =F12-F11 -> 2264.8 | H12: 17243088 | I12: =H12-H11 -> 2182 | J12: 28248204 | K12: =J12-J11 -> 1634 | L12: 22566166 | M12: =L12-L11 -> 3938 | N12: =M12+K12+I12+G12+E12 -> 13062.8 | O12: =IF(B12>0,N12/B12,0) -> 283.97391 | P12: 15261 | Q12: =(P12-P11)*1000 -> 2414 | R12: =N12-Q12 -> 10648.8 | S12: 8360 | T12: =S12-S11 -> 1 | U12: 1019198 | V12: =U12-U11 -> 69 | W12: 31820 | X12: =W12-W11 -> 1 | Y12: 620062 | Z12: =Y12-Y11 -> 171 | AA12: 34864 | AB12: =AA12-AA11 -> 3 | AC12: 737985 | AD12: =AC12-AC11 -> 501 | AE12: =AB12+X12+T12 -> 5 | AF12: =V12+Z12+AD12 -> 741 | AG12: =IF(AE12>0,AF12/AE12,0) -> 148.2 | AI12: =R12-'EDl log'!B10 -> -49299637
A13: ='General information '!F16 -> 0.1696 | B13: =SUM(230*A13) -> 39.008 | C13: 43841 | D13: 31342568 | E13: =D13-D12 -> 3078 | F13: 3456206 | G13: =F13-F12 -> 2231.2 | H13: 17245394 | I13: =H13-H12 -> 2306 | J13: 28249802 | K13: =J13-J12 -> 1598 | L13: 22570964 | M13: =L13-L12 -> 4798 | N13: =M13+K13+I13+G13+E13 -> 14011.2 | O13: =IF(B13>0,N13/B13,0) -> 359.18786 | P13: 15262.643 | Q13: =(P13-P12)*1000 -> 1643 | R13: =N13-Q13 -> 12368.2 | S13: 8362 | T13: =S13-S12 -> 2 | U13: 1019557 | V13: =U13-U12 -> 359 | W13: 31821 | X13: =W13-W12 -> 1 | Y13: 620205 | Z13: =Y13-Y12 -> 143 | AA13: 34865 | AB13: =AA13-AA12 -> 1 | AC13: 738305 | AD13: =AC13-AC12 -> 320 | AE13: =AB13+X13+T13 -> 4 | AF13: =V13+Z13+AD13 -> 822 | AG13: =IF(AE13>0,AF13/AE13,0) -> 205.5 | AI13: =R13-'EDl log'!B11 -> -49300715
A14: ='General information '!F17 -> 0.1739 | B14: =SUM(230*A14) -> 39.997 | C14: 43842 | D14: 31345782 | E14: =D14-D13 -> 3214 | F14: 3458691 | G14: =F14-F13 -> 2485 | H14: 17247874 | I14: =H14-H13 -> 2480 | J14: 28251336 | K14: =J14-J13 -> 1534 | L14: 22575426 | M14: =L14-L13 -> 4462 | N14: =M14+K14+I14+G14+E14 -> 14175 | O14: =IF(B14>0,N14/B14,0) -> 354.40158 | P14: 15264.76 | Q14: =(P14-P13)*1000 -> 2117 | R14: =N14-Q14 -> 12058 | S14: 8362 | T14: =S14-S13 -> 0 | U14: 1019557 | V14: =U14-U13 -> 0 | W14: 31821 | X14: =W14-W13 -> 0 | Y14: 620205 | Z14: =Y14-Y13 -> 0 | AA14: 34868 | AB14: =AA14-AA13 -> 3 | AC14: 738769 | AD14: =AC14-AC13 -> 464 | AE14: =AB14+X14+T14 -> 3 | AF14: =V14+Z14+AD14 -> 464 | AG14: =IF(AE14>0,AF14/AE14,0) -> 154.66667 | AI14: =R14-'EDl log'!B12 -> -49305644
A15: ='General information '!F18 -> 0.1826 | B15: =SUM(230*A15) -> 41.998 | C15: 43843 | D15: 31348342 | E15: =D15-D14 -> 2560 | F15: 3460876 | G15: =F15-F14 -> 2185 | H15: 17249926 | I15: =H15-H14 -> 2052 | J15: 28253424 | K15: =J15-J14 -> 2088 | L15: 22579342 | M15: =L15-L14 -> 3916 | N15: =M15+K15+I15+G15+E15 -> 12801 | O15: =IF(B15>0,N15/B15,0) -> 304.80023 | P15: 15267.071 | Q15: =(P15-P14)*1000 -> 2311 | R15: =N15-Q15 -> 10490 | S15: 8362 | T15: =S15-S14 -> 0 | U15: 1019557 | V15: =U15-U14 -> 0 | W15: 31825 | X15: =W15-W14 -> 4 | Y15: 620936 | Z15: =Y15-Y14 -> 731 | AA15: 34868 | AB15: =AA15-AA14 -> 0 | AC15: 738769 | AD15: =AC15-AC14 -> 0 | AE15: =AB15+X15+T15 -> 4 | AF15: =V15+Z15+AD15 -> 731 | AG15: =IF(AE15>0,AF15/AE15,0) -> 182.75 | AI15: =R15-'EDl log'!B13 -> -49312756
A16: ='General information '!F19 -> 0.2087 | B16: =SUM(230*A16) -> 48.001 | C16: 43844 | D16: 31350742 | E16: =D16-D15 -> 2400 | F16: 3462918 | G16: =F16-F15 -> 2042 | H16: 17252062 | I16: =H16-H15 -> 2136 | J16: 28255052 | K16: =J16-J15 -> 1628 | L16: 22583714 | M16: =L16-L15 -> 4372 | N16: =M16+K16+I16+G16+E16 -> 12578 | O16: =IF(B16>0,N16/B16,0) -> 262.03621 | P16: 15269.875 | Q16: =(P16-P15)*1000 -> 2804 | R16: =N16-Q16 -> 9774 | S16: 8363 | T16: =S16-S15 -> 1 | U16: 1019914 | V16: =U16-U15 -> 357 | W16: 31826 | X16: =W16-W15 -> 1 | Y16: 621137 | Z16: =Y16-Y15 -> 201 | AA16: 34868 | AB16: =AA16-AA15 -> 0 | AC16: 738769 | AD16: =AC16-AC15 -> 0 | AE16: =AB16+X16+T16 -> 2 | AF16: =V16+Z16+AD16 -> 558 | AG16: =IF(AE16>0,AF16/AE16,0) -> 279 | AI16: =R16-'EDl log'!B14 -> -49319823
A17: ='General information '!F20 -> 0.2261 | B17: =SUM(230*A17) -> 52.003 | C17: 43845 | D17: 31353438 | E17: =D17-D16 -> 2696 | F17: 3465049 | G17: =F17-F16 -> 2131 | H17: 17254166 | I17: =H17-H16 -> 2104 | J17: 28256730 | K17: =J17-J16 -> 1678 | L17: 22587984 | M17: =L17-L16 -> 4270 | N17: =M17+K17+I17+G17+E17 -> 12879 | O17: =IF(B17>0,N17/B17,0) -> 247.65879 | P17: 15272.521 | Q17: =(P17-P16)*1000 -> 2646 | R17: =N17-Q17 -> 10233 | S17: 8364 | T17: =S17-S16 -> 1 | U17: 1020115 | V17: =U17-U16 -> 201 | W17: 31827 | X17: =W17-W16 -> 1 | Y17: 621317 | Z17: =Y17-Y16 -> 180 | AA17: 34869 | AB17: =AA17-AA16 -> 1 | AC17: 739022 | AD17: =AC17-AC16 -> 253 | AE17: =AB17+X17+T17 -> 3 | AF17: =V17+Z17+AD17 -> 634 | AG17: =IF(AE17>0,AF17/AE17,0) -> 211.33333 | AI17: =R17-'EDl log'!B15 -> -49325513
A18: ='General information '!F21 -> 0.2261 | B18: =SUM(230*A18) -> 52.003 | C18: 43846 | D18: 31355626 | E18: =D18-D17 -> 2188 | F18: 3466916.4 | G18: =F18-F17 -> 1867.4 | H18: 17255862 | I18: =H18-H17 -> 1696 | J18: 28258666 | K18: =J18-J17 -> 1936 | L18: 22591666 | M18: =L18-L17 -> 3682 | N18: =M18+K18+I18+G18+E18 -> 11369.4 | O18: =IF(B18>0,N18/B18,0) -> 218.62969 | P18: 15277.001 | Q18: =(P18-P17)*1000 -> 4480 | R18: =N18-Q18 -> 6889.4 | S18: 8366 | T18: =S18-S17 -> 2 | U18: 1020406 | V18: =U18-U17 -> 291 | W18: 31831 | X18: =W18-W17 -> 4 | Y18: 622008 | Z18: =Y18-Y17 -> 691 | AA18: =AA17 -> 34869 | AB18: =AA18-AA17 -> 0 | AC18: =AC17 -> 739022 | AD18: =AC18-AC17 -> 0 | AE18: =AB18+X18+T18 -> 6 | AF18: =V18+Z18+AD18 -> 982 | AG18: =IF(AE18>0,AF18/AE18,0) -> 163.66667 | AI18: =R18-'EDl log'!B16 -> -49334319
A19: ='General information '!F22 -> 0.1739 | B19: =SUM(230*A19) -> 39.997 | C19: 43847 | D19: 31358932 | E19: =D19-D18 -> 3306 | F19: 3469290 | G19: =F19-F18 -> 2373.6 | H19: 17258222 | I19: =H19-H18 -> 2360 | J19: 28260246 | K19: =J19-J18 -> 1580 | L19: 22596296 | M19: =L19-L18 -> 4630 | N19: =M19+K19+I19+G19+E19 -> 14249.6 | O19: =IF(B19>0,N19/B19,0) -> 356.26672 | P19: 15279.015 | Q19: =(P19-P18)*1000 -> 2014 | R19: =N19-Q19 -> 12235.6 | S19: 8367 | T19: =S19-S18 -> 1 | U19: 1020832 | V19: =U19-U18 -> 426 | W19: =W18 -> 31831 | X19: =W19-W18 -> 0 | Y19: =Y18 -> 622008 | Z19: =Y19-Y18 -> 0 | AA19: 34871 | AB19: =AA19-AA18 -> 2 | AC19: 739336 | AD19: =AC19-AC18 -> 314 | AE19: =AB19+X19+T19 -> 3 | AF19: =V19+Z19+AD19 -> 740 | AG19: =IF(AE19>0,AF19/AE19,0) -> 246.66667 | AI19: =R19-'EDl log'!B17 -> -49333934
A20: ='General information '!F23 -> 0 | B20: =SUM(230*A20) -> 0 | C20: 43848 | D20: =D19 -> 31358932 | E20: =D20-D19 -> 0 | F20: =F19 -> 3469290 | G20: =F20-F19 -> 0 | H20: =H19 -> 17258222 | I20: =H20-H19 -> 0 | J20: =J19 -> 28260246 | K20: =J20-J19 -> 0 | L20: =L19 -> 22596296 | M20: =L20-L19 -> 0 | N20: =M20+K20+I20+G20+E20 -> 0 | O20: =IF(B20>0,N20/B20,0) -> 0 | P20: =P19 -> 15279.015 | Q20: =(P20-P19)*1000 -> 0 | R20: =N20-Q20 -> 0 | S20: =S19 -> 8367 | T20: =S20-S19 -> 0 | U20: =U19 -> 1020832 | V20: =U20-U19 -> 0 | W20: =W19 -> 31831 | X20: =W20-W19 -> 0 | Y20: =Y19 -> 622008 | Z20: =Y20-Y19 -> 0 | AA20: =AA19 -> 34871 | AB20: =AA20-AA19 -> 0 | AC20: =AC19 -> 739336 | AD20: =AC20-AC19 -> 0 | AE20: =AB20+X20+T20 -> 0 | AF20: =V20+Z20+AD20 -> 0 | AG20: =IF(AE20>0,AF20/AE20,0) -> 0 | AI20: =R20-'EDl log'!B18 -> -49351598
A21: ='General information '!F24 -> 0 | B21: =SUM(230*A21) -> 0 | C21: 43849 | D21: =D20 -> 31358932 | E21: =D21-D20 -> 0 | F21: =F20 -> 3469290 | G21: =F21-F20 -> 0 | H21: =H20 -> 17258222 | I21: =H21-H20 -> 0 | J21: =J20 -> 28260246 | K21: =J21-J20 -> 0 | L21: =L20 -> 22596296 | M21: =L21-L20 -> 0 | N21: =M21+K21+I21+G21+E21 -> 0 | O21: =IF(B21>0,N21/B21,0) -> 0 | P21: =P20 -> 15279.015 | Q21: =(P21-P20)*1000 -> 0 | R21: =N21-Q21 -> 0 | S21: =S20 -> 8367 | T21: =S21-S20 -> 0 | U21: =U20 -> 1020832 | V21: =U21-U20 -> 0 | W21: =W20 -> 31831 | X21: =W21-W20 -> 0 | Y21: =Y20 -> 622008 | Z21: =Y21-Y20 -> 0 | AA21: =AA20 -> 34871 | AB21: =AA21-AA20 -> 0 | AC21: =AC20 -> 739336 | AD21: =AC21-AC20 -> 0 | AE21: =AB21+X21+T21 -> 0 | AF21: =V21+Z21+AD21 -> 0 | AG21: =IF(AE21>0,AF21/AE21,0) -> 0 | AI21: =R21-'EDl log'!B19 -> -49355220
A22: ='General information '!F25 -> 0 | B22: =SUM(230*A22) -> 0 | C22: 43850 | D22: =D21 -> 31358932 | E22: =D22-D21 -> 0 | F22: =F21 -> 3469290 | G22: =F22-F21 -> 0 | H22: =H21 -> 17258222 | I22: =H22-H21 -> 0 | J22: =J21 -> 28260246 | K22: =J22-J21 -> 0 | L22: =L21 -> 22596296 | M22: =L22-L21 -> 0 | N22: =M22+K22+I22+G22+E22 -> 0 | O22: =IF(B22>0,N22/B22,0) -> 0 | P22: =P21 -> 15279.015 | Q22: =(P22-P21)*1000 -> 0 | R22: =N22-Q22 -> 0 | S22: =S21 -> 8367 | T22: =S22-S21 -> 0 | U22: =U21 -> 1020832 | V22: =U22-U21 -> 0 | W22: =W21 -> 31831 | X22: =W22-W21 -> 0 | Y22: =Y21 -> 622008 | Z22: =Y22-Y21 -> 0 | AA22: =AA21 -> 34871 | AB22: =AA22-AA21 -> 0 | AC22: =AC21 -> 739336 | AD22: =AC22-AC21 -> 0 | AE22: =AB22+X22+T22 -> 0 | AF22: =V22+Z22+AD22 -> 0 | AG22: =IF(AE22>0,AF22/AE22,0) -> 0 | AI22: =R22-'EDl log'!B20 -> -49361506
A23: ='General information '!F26 -> 0 | B23: =SUM(230*A23) -> 0 | C23: 43851 | D23: =D22 -> 31358932 | E23: =D23-D22 -> 0 | F23: =F22 -> 3469290 | G23: =F23-F22 -> 0 | H23: =H22 -> 17258222 | I23: =H23-H22 -> 0 | J23: =J22 -> 28260246 | K23: =J23-J22 -> 0 | L23: =L22 -> 22596296 | M23: =L23-L22 -> 0 | N23: =M23+K23+I23+G23+E23 -> 0 | O23: =IF(B23>0,N23/B23,0) -> 0 | P23: =P22 -> 15279.015 | Q23: =(P23-P22)*1000 -> 0 | R23: =N23-Q23 -> 0 | S23: =S22 -> 8367 | T23: =S23-S22 -> 0 | U23: =U22 -> 1020832 | V23: =U23-U22 -> 0 | W23: =W22 -> 31831 | X23: =W23-W22 -> 0 | Y23: =Y22 -> 622008 | Z23: =Y23-Y22 -> 0 | AA23: =AA22 -> 34871 | AB23: =AA23-AA22 -> 0 | AC23: =AC22 -> 739336 | AD23: =AC23-AC22 -> 0 | AE23: =AB23+X23+T23 -> 0 | AF23: =V23+Z23+AD23 -> 0 | AG23: =IF(AE23>0,AF23/AE23,0) -> 0 | AI23: =R23-'EDl log'!B21 -> -49361506
A24: ='General information '!F27 -> 0 | B24: =SUM(230*A24) -> 0 | C24: 43852 | D24: =D23 -> 31358932 | E24: =D24-D23 -> 0 | F24: =F23 -> 3469290 | G24: =F24-F23 -> 0 | H24: =H23 -> 17258222 | I24: =H24-H23 -> 0 | J24: =J23 -> 28260246 | K24: =J24-J23 -> 0 | L24: =L23 -> 22596296 | M24: =L24-L23 -> 0 | N24: =M24+K24+I24+G24+E24 -> 0 | O24: =IF(B24>0,N24/B24,0) -> 0 | P24: =P23 -> 15279.015 | Q24: =(P24-P23)*1000 -> 0 | R24: =N24-Q24 -> 0 | S24: =S23 -> 8367 | T24: =S24-S23 -> 0 | U24: =U23 -> 1020832 | V24: =U24-U23 -> 0 | W24: =W23 -> 31831 | X24: =W24-W23 -> 0 | Y24: =Y23 -> 622008 | Z24: =Y24-Y23 -> 0 | AA24: =AA23 -> 34871 | AB24: =AA24-AA23 -> 0 | AC24: =AC23 -> 739336 | AD24: =AC24-AC23 -> 0 | AE24: =AB24+X24+T24 -> 0 | AF24: =V24+Z24+AD24 -> 0 | AG24: =IF(AE24>0,AF24/AE24,0) -> 0 | AI24: =R24-'EDl log'!B22 -> -49361506
A25: ='General information '!F28 -> 0 | B25: =SUM(230*A25) -> 0 | C25: 43853 | D25: =D24 -> 31358932 | E25: =D25-D24 -> 0 | F25: =F24 -> 3469290 | G25: =F25-F24 -> 0 | H25: =H24 -> 17258222 | I25: =H25-H24 -> 0 | J25: =J24 -> 28260246 | K25: =J25-J24 -> 0 | L25: =L24 -> 22596296 | M25: =L25-L24 -> 0 | N25: =M25+K25+I25+G25+E25 -> 0 | O25: =IF(B25>0,N25/B25,0) -> 0 | P25: =P24 -> 15279.015 | Q25: =(P25-P24)*1000 -> 0 | R25: =N25-Q25 -> 0 | S25: =S24 -> 8367 | T25: =S25-S24 -> 0 | U25: =U24 -> 1020832 | V25: =U25-U24 -> 0 | W25: =W24 -> 31831 | X25: =W25-W24 -> 0 | Y25: =Y24 -> 622008 | Z25: =Y25-Y24 -> 0 | AA25: =AA24 -> 34871 | AB25: =AA25-AA24 -> 0 | AC25: =AC24 -> 739336 | AD25: =AC25-AC24 -> 0 | AE25: =AB25+X25+T25 -> 0 | AF25: =V25+Z25+AD25 -> 0 | AG25: =IF(AE25>0,AF25/AE25,0) -> 0 | AI25: =R25-'EDl log'!B23 -> -49361506
A26: ='General information '!F29 -> 0 | B26: =SUM(230*A26) -> 0 | C26: 43854 | D26: =D25 -> 31358932 | E26: =D26-D25 -> 0 | F26: =F25 -> 3469290 | G26: =F26-F25 -> 0 | H26: =H25 -> 17258222 | I26: =H26-H25 -> 0 | J26: =J25 -> 28260246 | K26: =J26-J25 -> 0 | L26: =L25 -> 22596296 | M26: =L26-L25 -> 0 | N26: =M26+K26+I26+G26+E26 -> 0 | O26: =IF(B26>0,N26/B26,0) -> 0 | P26: =P25 -> 15279.015 | Q26: =(P26-P25)*1000 -> 0 | R26: =N26-Q26 -> 0 | S26: =S25 -> 8367 | T26: =S26-S25 -> 0 | U26: =U25 -> 1020832 | V26: =U26-U25 -> 0 | W26: =W25 -> 31831 | X26: =W26-W25 -> 0 | Y26: =Y25 -> 622008 | Z26: =Y26-Y25 -> 0 | AA26: =AA25 -> 34871 | AB26: =AA26-AA25 -> 0 | AC26: =AC25 -> 739336 | AD26: =AC26-AC25 -> 0 | AE26: =AB26+X26+T26 -> 0 | AF26: =V26+Z26+AD26 -> 0 | AG26: =IF(AE26>0,AF26/AE26,0) -> 0 | AI26: =R26-'EDl log'!B24 -> -49361506
A27: ='General information '!F30 -> 0 | B27: =SUM(230*A27) -> 0 | C27: 43855 | D27: =D26 -> 31358932 | E27: =D27-D26 -> 0 | F27: =F26 -> 3469290 | G27: =F27-F26 -> 0 | H27: =H26 -> 17258222 | I27: =H27-H26 -> 0 | J27: =J26 -> 28260246 | K27: =J27-J26 -> 0 | L27: =L26 -> 22596296 | M27: =L27-L26 -> 0 | N27: =M27+K27+I27+G27+E27 -> 0 | O27: =IF(B27>0,N27/B27,0) -> 0 | P27: =P26 -> 15279.015 | Q27: =(P27-P26)*1000 -> 0 | R27: =N27-Q27 -> 0 | S27: =S26 -> 8367 | T27: =S27-S26 -> 0 | U27: =U26 -> 1020832 | V27: =U27-U26 -> 0 | W27: =W26 -> 31831 | X27: =W27-W26 -> 0 | Y27: =Y26 -> 622008 | Z27: =Y27-Y26 -> 0 | AA27: =AA26 -> 34871 | AB27: =AA27-AA26 -> 0 | AC27: =AC26 -> 739336 | AD27: =AC27-AC26 -> 0 | AE27: =AB27+X27+T27 -> 0 | AF27: =V27+Z27+AD27 -> 0 | AG27: =IF(AE27>0,AF27/AE27,0) -> 0 | AI27: =R27-'EDl log'!B25 -> -49361506
A28: ='General information '!F31 -> 0 | B28: =SUM(230*A28) -> 0 | C28: 43856 | D28: =D27 -> 31358932 | E28: =D28-D27 -> 0 | F28: =F27 -> 3469290 | G28: =F28-F27 -> 0 | H28: =H27 -> 17258222 | I28: =H28-H27 -> 0 | J28: =J27 -> 28260246 | K28: =J28-J27 -> 0 | L28: =L27 -> 22596296 | M28: =L28-L27 -> 0 | N28: =M28+K28+I28+G28+E28 -> 0 | O28: =IF(B28>0,N28/B28,0) -> 0 | P28: =P27 -> 15279.015 | Q28: =(P28-P27)*1000 -> 0 | R28: =N28-Q28 -> 0 | S28: =S27 -> 8367 | T28: =S28-S27 -> 0 | U28: =U27 -> 1020832 | V28: =U28-U27 -> 0 | W28: =W27 -> 31831 | X28: =W28-W27 -> 0 | Y28: =Y27 -> 622008 | Z28: =Y28-Y27 -> 0 | AA28: =AA27 -> 34871 | AB28: =AA28-AA27 -> 0 | AC28: =AC27 -> 739336 | AD28: =AC28-AC27 -> 0 | AE28: =AB28+X28+T28 -> 0 | AF28: =V28+Z28+AD28 -> 0 | AG28: =IF(AE28>0,AF28/AE28,0) -> 0 | AI28: =R28-'EDl log'!B26 -> -49361506
A29: ='General information '!F32 -> 0 | B29: =SUM(230*A29) -> 0 | C29: 43857 | D29: =D28 -> 31358932 | E29: =D29-D28 -> 0 | F29: =F28 -> 3469290 | G29: =F29-F28 -> 0 | H29: =H28 -> 17258222 | I29: =H29-H28 -> 0 | J29: =J28 -> 28260246 | K29: =J29-J28 -> 0 | L29: =L28 -> 22596296 | M29: =L29-L28 -> 0 | N29: =M29+K29+I29+G29+E29 -> 0 | O29: =IF(B29>0,N29/B29,0) -> 0 | P29: =P28 -> 15279.015 | Q29: =(P29-P28)*1000 -> 0 | R29: =N29-Q29 -> 0 | S29: =S28 -> 8367 | T29: =S29-S28 -> 0 | U29: =U28 -> 1020832 | V29: =U29-U28 -> 0 | W29: =W28 -> 31831 | X29: =W29-W28 -> 0 | Y29: =Y28 -> 622008 | Z29: =Y29-Y28 -> 0 | AA29: =AA28 -> 34871 | AB29: =AA29-AA28 -> 0 | AC29: =AC28 -> 739336 | AD29: =AC29-AC28 -> 0 | AE29: =AB29+X29+T29 -> 0 | AF29: =V29+Z29+AD29 -> 0 | AG29: =IF(AE29>0,AF29/AE29,0) -> 0 | AI29: =R29-'EDl log'!B27 -> -49361506
A30: ='General information '!F33 -> 0 | B30: =SUM(230*A30) -> 0 | C30: 43858 | D30: =D29 -> 31358932 | E30: =D30-D29 -> 0 | F30: =F29 -> 3469290 | G30: =F30-F29 -> 0 | H30: =H29 -> 17258222 | I30: =H30-H29 -> 0 | J30: =J29 -> 28260246 | K30: =J30-J29 -> 0 | L30: =L29 -> 22596296 | M30: =L30-L29 -> 0 | N30: =M30+K30+I30+G30+E30 -> 0 | O30: =IF(B30>0,N30/B30,0) -> 0 | P30: =P29 -> 15279.015 | Q30: =(P30-P29)*1000 -> 0 | R30: =N30-Q30 -> 0 | S30: =S29 -> 8367 | T30: =S30-S29 -> 0 | U30: =U29 -> 1020832 | V30: =U30-U29 -> 0 | W30: =W29 -> 31831 | X30: =W30-W29 -> 0 | Y30: =Y29 -> 622008 | Z30: =Y30-Y29 -> 0 | AA30: =AA29 -> 34871 | AB30: =AA30-AA29 -> 0 | AC30: =AC29 -> 739336 | AD30: =AC30-AC29 -> 0 | AE30: =AB30+X30+T30 -> 0 | AF30: =V30+Z30+AD30 -> 0 | AG30: =IF(AE30>0,AF30/AE30,0) -> 0 | AI30: =R30-'EDl log'!B28 -> -49361506
A31: ='General information '!F34 -> 0 | B31: =SUM(230*A31) -> 0 | C31: 43859 | D31: =D30 -> 31358932 | E31: =D31-D30 -> 0 | F31: =F30 -> 3469290 | G31: =F31-F30 -> 0 | H31: =H30 -> 17258222 | I31: =H31-H30 -> 0 | J31: =J30 -> 28260246 | K31: =J31-J30 -> 0 | L31: =L30 -> 22596296 | M31: =L31-L30 -> 0 | N31: =M31+K31+I31+G31+E31 -> 0 | O31: =IF(B31>0,N31/B31,0) -> 0 | P31: =P30 -> 15279.015 | Q31: =(P31-P30)*1000 -> 0 | R31: =N31-Q31 -> 0 | S31: =S30 -> 8367 | T31: =S31-S30 -> 0 | U31: =U30 -> 1020832 | V31: =U31-U30 -> 0 | W31: =W30 -> 31831 | X31: =W31-W30 -> 0 | Y31: =Y30 -> 622008 | Z31: =Y31-Y30 -> 0 | AA31: =AA30 -> 34871 | AB31: =AA31-AA30 -> 0 | AC31: =AC30 -> 739336 | AD31: =AC31-AC30 -> 0 | AE31: =AB31+X31+T31 -> 0 | AF31: =V31+Z31+AD31 -> 0 | AG31: =IF(AE31>0,AF31/AE31,0) -> 0 | AI31: =R31-'EDl log'!B29 -> -49361506
... A33: ='General information '!F36 -> 0 | B33: =SUM(230*A33) -> 0 | C33: 43861 | D33: =D32 -> 31358932 | E33: =D33-D32 -> 0 | F33: =F32 -> 3469290 | G33: =F33-F32 -> 0 | H33: =H32 -> 17258222 | I33: =H33-H32 -> 0 | J33: =J32 -> 28260246 | K33: =J33-J32 -> 0 | L33: =L32 -> 22596296 | M33: =L33-L32 -> 0 | N33: =M33+K33+I33+G33+E33 -> 0 | O33: =IF(B33>0,N33/B33,0) -> 0 | P33: =P32 -> 15279.015 | Q33: =(P33-P32)*1000 -> 0 | R33: =N33-Q33 -> 0 | S33: =S32 -> 8367 | T33: =S33-S32 -> 0 | U33: =U32 -> 1020832 | V33: =U33-U32 -> 0 | W33: =W32 -> 31831 | X33: =W33-W32 -> 0 | Y33: =Y32 -> 622008 | Z33: =Y33-Y32 -> 0 | AA33: =AA32 -> 34871 | AB33: =AA33-AA32 -> 0 | AC33: =AC32 -> 739336 | AD33: =AC33-AC32 -> 0 | AE33: =AB33+X33+T33 -> 0 | AF33: =V33+Z33+AD33 -> 0 | AG33: =IF(AE33>0,AF33/AE33,0) -> 0 | AI33: =R33-'EDl log'!B31 -> -49361506

Sheet B5
F1: Boiler A | J1: =J36 -> 68.86875 | K1: Boiler B | P1: Boiler C | V1: Boiler | X1: SteamA | AC1: SteamB | AH1: Steam | AI1: Boiler & steam | AL1: Total Boiler Runing H | AM1: Total Steam Runing H | AN1: GAS1 % | AO1: GAS1/L | AP1: GAS2% | AQ1: Gas2/L | AR1: GAS3% | AS1: GAS3/L | AU1: Gas Cons | AV1: Delivery | AW1: Cost/L
B2: Level Tank Gen | C2: Level tank Boiler | D2: Daily Cons Bo. | E2: Boiler litter | F2: Boiler A | G2: Run Hr a | H2: Boiler A fuel | I2: Daily consumption | J2: AVG | K2: index Run H | L2: Run Hrb | M2: Boiler B Fuel | O2: Daily consumption | P2: Boiler C | S2: Run C | U2: Total RH | V2: Total Fuel | X2: SteamA | Y2: Run SA | Z2: Steam A Conter | AA2: Liters | AC2: SteamB | AD2: Run SteamB | AE2: Steam B Conter | AF2: SB Litters | AG2: Avg | AH2: Total Fuel | AI2: Total Fuel
S3: 0
A4: 31-12-2019 | B4: =[1]B5!B35 -> 238 | C4: =[1]B5!C35 -> 98 | D4: =[1]B5!D35 -> 25 | E4: =[1]B5!E35 -> 209.5 | F4: =[1]B5!F35 -> 1303 | G4: =[1]B5!G35 -> 0 | H4: =[1]B5!H35 -> 330270 | I4: =[1]B5!I35 -> 0 | ... AX4: =[1]B5!AX35 -> 0.7
A5: 43831 | B5: 234 | C5: 78 | D5: =C4-C5 -> 20 | E5: =D5*8.38 -> 167.6 | F5: 1303 | G5: =F5-F4 -> 0 | H5: 330270 | I5: =SUM(H5-H4) -> 0 | J5: 1 | K5: 1693 | L5: =K5-K4 -> 14 | M5: 123329 | N5: =M5-M4 -> 1058 | O5: =SUM(L5*$J$1) -> 964.1625 | P5: 1452 | Q5: 126239 | R5: =Q5-Q4 -> 0 | S5: =SUM(P5-P4) -> 0 | T5: =SUM(S5*$T$2) -> 0 | U5: =SUM(G5+L5+S5) -> 14 | V5: =R5+N5+I5:I5 -> 1058 | W5: =SUM(V5/U5) -> 75.571429 | X5: 2320 | Y5: =X5-X4 -> 0 | Z5: 130593 | AA5: =Z5-Z4 -> 0 | AB5: =SUM(Y5*$AB$2) -> 0 | AC5: 1712 | AD5: =AC5-AC4 -> 9 | AE5: 353100 | AF5: =AE5-AE4 -> 400 | AG5: =IF(AD5>0,AF5/AD5,0) -> 44.444444 | AH5: =AF5+AA5 -> 400 | AI5: =SUM(AH5+V5) -> 1458 | AJ5: =-tanks!AW6 -> 1458 | AK5: =SUM(AJ5-AI5) -> 0 | AL5: =S5+L5+G5 -> 14 | AM5: =Y5+AD5 -> 9 | AN5: 64 | AO5: =(AN5/100)*3000 -> 1920 | AP5: 65 | AQ5: =(AP5/100)*3000 -> 1950 | AR5: 65 | AS5: =(AR5/100)*3000 -> 1950 | AT5: =SUM(AO5+AQ5+AS5) -> 5820 | AU5: =AT4-AT5+AV5 -> 180 | AX5: =IF(AV5>0,AW5,AX4) -> 0.7
A6: 43832 | B6: 205 | C6: 143 | D6: =C5-C6 -> -65 | E6: =D6*8.38 -> -544.7 | F6: 1303 | G6: =F6-F5 -> 0 | H6: 330270 | I6: =SUM(H6-H5) -> 0 | J6: =IF(G6>0,I6/G6,0) -> 0 | K6: 1702 | L6: =K6-K5 -> 9 | M6: 123970 | N6: =M6-M5 -> 641 | O6: =SUM(L6*$J$1) -> 619.81875 | P6: 1456 | Q6: 126593 | R6: =Q6-Q5 -> 354 | S6: =SUM(P6-P5) -> 4 | T6: =SUM(S6*$T$2) -> 0 | U6: =SUM(G6+L6+S6) -> 13 | V6: =R6+N6+I6:I6 -> 995 | W6: =SUM(V6/U6) -> 76.538462 | X6: 2320 | Y6: =X6-X5 -> 0 | Z6: 130593 | AA6: =Z6-Z5 -> 0 | AB6: =SUM(Y6*$AB$2) -> 0 | AC6: 1714 | AD6: =AC6-AC5 -> 2 | AE6: 353197.3 | AF6: =AE6-AE5 -> 97.3 | AG6: =IF(AD6>0,AF6/AD6,0) -> 48.65 | AH6: =AF6+AA6 -> 97.3 | AI6: =SUM(AH6+V6) -> 1092.3 | AJ6: =-tanks!AW7 -> 1092.3 | AK6: =SUM(AJ6-AI6) -> 0 | AL6: =S6+L6+G6 -> 13 | AM6: =Y6+AD6 -> 2 | AN6: 80 | AO6: =(AN6/100)*3000 -> 2400 | AP6: 80 | AQ6: =(AP6/100)*3000 -> 2400 | AR6: 80 | AS6: =(AR6/100)*3000 -> 2400 | AT6: =SUM(AO6+AQ6+AS6) -> 7200 | AU6: =AT5-AT6+AV6 -> 520 | AV6: 1900 | AW6: 0.7 | AX6: =IF(AV6>0,AW6,AX5) -> 0.7
A7: 43833 | B7: 198 | C7: 127 | D7: =C6-C7 -> 16 | E7: =D7*8.38 -> 134.08 | F7: =F6 -> 1303 | G7: =F7-F6 -> 0 | H7: =H6 -> 330270 | I7: =SUM(H7-H6) -> 0 | J7: =IF(G7>0,I7/G7,0) -> 0 | K7: =K6 -> 1702 | L7: =K7-K6 -> 0 | M7: =M6 -> 123970 | N7: =M7-M6 -> 0 | O7: 1 | P7: 1467 | Q7: 127436 | R7: =Q7-Q6 -> 843 | S7: =SUM(P7-P6) -> 11 | T7: =SUM(S7*$T$2) -> 0 | U7: =SUM(G7+L7+S7) -> 11 | V7: =R7+N7+I7:I7 -> 843 | W7: =SUM(V7/U7) -> 76.636364 | X7: =X6 -> 2320 | Y7: =X7-X6 -> 0 | Z7: =Z6 -> 130593 | AA7: =Z7-Z6 -> 0 | AB7: =SUM(Y7*$AB$2) -> 0 | AC7: 1723 | AD7: =AC7-AC6 -> 9 | AE7: 353680.2 | AF7: =AE7-AE6 -> 482.9 | AG7: =IF(AD7>0,AF7/AD7,0) -> 53.655556 | AH7: =AF7+AA7 -> 482.9 | AI7: =SUM(AH7+V7) -> 1325.9 | AJ7: =-tanks!AW8 -> 1325.9 | AK7: =SUM(AJ7-AI7) -> 0 | AL7: =S7+L7+G7 -> 11 | AM7: =Y7+AD7 -> 9 | AN7: 78 | AO7: =(AN7/100)*3000 -> 2340 | AP7: 78 | AQ7: =(AP7/100)*3000 -> 2340 | AR7: 78 | AS7: =(AR7/100)*3000 -> 2340 | AT7: =SUM(AO7+AQ7+AS7) -> 7020 | AU7: =AT6-AT7+AV7 -> 180 | AX7: =IF(AV7>0,AW7,AX6) -> 0.7
A8: 43834 | B8: 193 | C8: 102 | D8: =C7-C8 -> 25 | E8: =D8*8.38 -> 209.5 | F8: =F7 -> 1303 | G8: =F8-F7 -> 0 | H8: =H7 -> 330270 | I8: =SUM(H8-H7) -> 0 | J8: =IF(G8>0,I8/G8,0) -> 0 | K8: =K7 -> 1702 | L8: =K8-K7 -> 0 | M8: =M7 -> 123970 | N8: =M8-M7 -> 0 | O8: 1479 | P8: 1479 | Q8: 128380 | R8: =Q8-Q7 -> 944 | S8: =SUM(P8-P7) -> 12 | T8: =SUM(S8*$T$2) -> 0 | U8: =SUM(G8+L8+S8) -> 12 | V8: =R8+N8+I8:I8 -> 944 | W8: =SUM(V8/U8) -> 78.666667 | X8: 2320 | Y8: =X8-X7 -> 0 | Z8: 130593 | AA8: =Z8-Z7 -> 0 | AB8: =SUM(Y8*$AB$2) -> 0 | AC8: 1723 | AD8: =AC8-AC7 -> 0 | AE8: =AE7 -> 353680.2 | AF8: =AE8-AE7 -> 0 | AG8: =IF(AD8>0,AF8/AD8,0) -> 0 | AH8: =AF8+AA8 -> 0 | AI8: =SUM(AH8+V8) -> 944 | AJ8: =-tanks!AW9 -> 944 | AK8: =SUM(AJ8-AI8) -> 0 | AL8: =S8+L8+G8 -> 12 | AM8: =Y8+AD8 -> 0 | AN8: 75 | AO8: =(AN8/100)*3000 -> 2250 | AP8: 76 | AQ8: =(AP8/100)*3000 -> 2280 | AR8: 75 | AS8: =(AR8/100)*3000 -> 2250 | AT8: =SUM(AO8+AQ8+AS8) -> 6780 | AU8: =AT7-AT8+AV8 -> 240 | AX8: =IF(AV8>0,AW8,AX7) -> 0.7
A9: 43835 | B9: 190 | C9: 88 | D9: =C8-C9 -> 14 | E9: =D9*8.38 -> 117.32 | F9: 1303 | G9: =F9-F8 -> 0 | H9: 330270 | I9: =SUM(H9-H8) -> 0 | J9: =IF(G9>0,I9/G9,0) -> 0 | K9: 1702 | L9: =K9-K8 -> 0 | M9: 123970 | N9: =M9-M8 -> 0 | O9: =SUM(L9*$J$1) -> 0 | P9: 1489 | Q9: 129086 | R9: =Q9-Q8 -> 706 | S9: =SUM(P9-P8) -> 10 | T9: =SUM(S9*$T$2) -> 0 | U9: =SUM(G9+L9+S9) -> 10 | V9: =R9+N9+I9:I9 -> 706 | W9: =SUM(V9/U9) -> 70.6 | X9: 2320 | Y9: =X9-X8 -> 0 | Z9: 130593 | AA9: =Z9-Z8 -> 0 | AB9: =SUM(Y9*$AB$2) -> 0 | AC9: 1732 | AD9: =AC9-AC8 -> 9 | AE9: 354081.9 | AF9: =AE9-AE8 -> 401.7 | AG9: =IF(AD9>0,AF9/AD9,0) -> 44.633333 | AH9: =AF9+AA9 -> 401.7 | AI9: =SUM(AH9+V9) -> 1107.7 | AJ9: =-tanks!AW10 -> 1107.7 | AK9: =SUM(AJ9-AI9) -> 0 | AL9: =S9+L9+G9 -> 10 | AM9: =Y9+AD9 -> 9 | AN9: 71 | AO9: =(AN9/100)*3000 -> 2130 | AP9: 73 | AQ9: =(AP9/100)*3000 -> 2190 | AR9: 73 | AS9: =(AR9/100)*3000 -> 2190 | AT9: =SUM(AO9+AQ9+AS9) -> 6510 | AU9: =AT8-AT9+AV9 -> 270 | AX9: =IF(AV9>0,AW9,AX8) -> 0.7
A10: 43836 | B10: 182 | C10: 70 | D10: =C9-C10 -> 18 | E10: =D10*8.38 -> 150.84 | F10: 1303 | G10: =F10-F9 -> 0 | H10: 330270 | I10: =SUM(H10-H9) -> 0 | J10: =IF(G10>0,I10/G10,0) -> 0 | K10: 1702 | L10: =K10-K9 -> 0 | M10: 123970 | N10: =M10-M9 -> 0 | O10: =SUM(L10*$J$1) -> 0 | P10: 1497 | Q10: 129693 | R10: =Q10-Q9 -> 607 | S10: =SUM(P10-P9) -> 8 | T10: =SUM(S10*$T$2) -> 0 | U10: =SUM(G10+L10+S10) -> 8 | V10: =R10+N10+I10:I10 -> 607 | W10: =SUM(V10/U10) -> 75.875 | X10: 2320 | Y10: =X10-X9 -> 0 | Z10: 130593 | AA10: =Z10-Z9 -> 0 | AB10: =SUM(Y10*$AB$2) -> 0 | AC10: 1732 | AD10: =AC10-AC9 -> 0 | AE10: 354081.9 | AF10: =AE10-AE9 -> 0 | AG10: =IF(AD10>0,AF10/AD10,0) -> 0 | AH10: =AF10+AA10 -> 0 | AI10: =SUM(AH10+V10) -> 607 | AJ10: =-tanks!AW11 -> 607 | AK10: =SUM(AJ10-AI10) -> 0 | AL10: =S10+L10+G10 -> 8 | AM10: =Y10+AD10 -> 0 | AN10: 69 | AO10: =(AN10/100)*3000 -> 2070 | AP10: 71 | AQ10: =(AP10/100)*3000 -> 2130 | AR10: 71 | AS10: =(AR10/100)*3000 -> 2130 | AT10: =SUM(AO10+AQ10+AS10) -> 6330 | AU10: =AT9-AT10+AV10 -> 180 | AX10: =IF(AV10>0,AW10,AX9) -> 0.7
A11: 43837 | B11: 164 | C11: 101 | D11: =C10-C11 -> -31 | E11: =D11*8.38 -> -259.78 | F11: 1303 | G11: =F11-F10 -> 0 | H11: 330270 | I11: =SUM(H11-H10) -> 0 | J11: =IF(G11>0,I11/G11,0) -> 0 | K11: 1702 | L11: =K11-K10 -> 0 | M11: 123970 | N11: =M11-M10 -> 0 | O11: =SUM(L11*$J$1) -> 0 | P11: 1505 | Q11: 130331 | R11: =Q11-Q10 -> 638 | S11: =SUM(P11-P10) -> 8 | T11: =SUM(S11*$T$2) -> 0 | U11: =SUM(G11+L11+S11) -> 8 | V11: =R11+N11+I11:I11 -> 638 | W11: =SUM(V11/U11) -> 79.75 | X11: 2320 | Y11: =X11-X10 -> 0 | Z11: 130593 | AA11: =Z11-Z10 -> 0 | AB11: =SUM(Y11*$AB$2) -> 0 | AC11: 1740 | AD11: =AC11-AC10 -> 8 | AE11: 354463.2 | AF11: =AE11-AE10 -> 381.3 | AG11: =IF(AD11>0,AF11/AD11,0) -> 47.6625 | AH11: =AF11+AA11 -> 381.3 | AI11: =SUM(AH11+V11) -> 1019.3 | AJ11: =-tanks!AW12 -> 1019.3 | AK11: =SUM(AJ11-AI11) -> 0 | AL11: =S11+L11+G11 -> 8 | AM11: =Y11+AD11 -> 8 | AN11: 67 | AO11: =(AN11/100)*3000 -> 2010 | AP11: 68 | AQ11: =(AP11/100)*3000 -> 2040 | AR11: 69 | AS11: =(AR11/100)*3000 -> 2070 | AT11: =SUM(AO11+AQ11+AS11) -> 6120 | AU11: =AT10-AT11+AV11 -> 210 | AX11: =IF(AV11>0,AW11,AX10) -> 0.7
A12: 43838 | B12: 154 | C12: 80 | D12: =C11-C12 -> 21 | E12: =D12*8.38 -> 175.98 | F12: =F11 -> 1303 | G12: =F12-F11 -> 0 | H12: =H11 -> 330270 | I12: =SUM(H12-H11) -> 0 | J12: =IF(G12>0,I12/G12,0) -> 0 | K12: =K11 -> 1702 | L12: =K12-K11 -> 0 | M12: =M11 -> 123970 | N12: =M12-M11 -> 0 | O12: =SUM(L12*$J$1) -> 0 | P12: 1516 | Q12: 131147 | R12: =Q12-Q11 -> 816 | S12: =SUM(P12-P11) -> 11 | T12: =SUM(S12*$T$2) -> 0 | U12: =SUM(G12+L12+S12) -> 11 | V12: =R12+N12+I12:I12 -> 816 | W12: =SUM(V12/U12) -> 74.181818 | X12: 2320 | Y12: =X12-X11 -> 0 | Z12: =Z11 -> 130593 | AA12: =Z12-Z11 -> 0 | AB12: =SUM(Y12*$AB$2) -> 0 | AC12: =AC11 -> 1740 | AD12: =AC12-AC11 -> 0 | AE12: =AE11 -> 354463.2 | AF12: =AE12-AE11 -> 0 | AG12: =IF(AD12>0,AF12/AD12,0) -> 0 | AH12: =AF12+AA12 -> 0 | AI12: =SUM(AH12+V12) -> 816 | AJ12: =-tanks!AW13 -> 816 | AK12: =SUM(AJ12-AI12) -> 0 | AL12: =S12+L12+G12 -> 11 | AM12: =Y12+AD12 -> 0 | AN12: 64 | AO12: =(AN12/100)*3000 -> 1920 | AP12: 66 | AQ12: =(AP12/100)*3000 -> 1980 | AR12: 66 | AS12: =(AR12/100)*3000 -> 1980 | AT12: =SUM(AO12+AQ12+AS12) -> 5880 | AU12: =AT11-AT12+AV12 -> 240 | AX12: =IF(AV12>0,AW12,AX11) -> 0.7
A13: 43839 | B13: 179 | C13: 162 | D13: =C12-C13 -> -82 | E13: =D13*8.38 -> -687.16 | F13: 1303 | G13: =F13-F12 -> 0 | H13: 330270 | I13: =SUM(H13-H12) -> 0 | J13: =IF(G13>0,I13/G13,0) -> 0 | K13: 1702 | L13: =K13-K12 -> 0 | M13: 123970 | N13: =M13-M12 -> 0 | O13: =SUM(L13*$J$1) -> 0 | P13: 1527 | Q13: 132000 | R13: =Q13-Q12 -> 853 | S13: =SUM(P13-P12) -> 11 | T13: =SUM(S13*$T$2) -> 0 | U13: =SUM(G13+L13+S13) -> 11 | V13: =R13+N13+I13:I13 -> 853 | W13: =SUM(V13/U13) -> 77.545455 | X13: 2320 | Y13: =X13-X12 -> 0 | Z13: 130593 | AA13: =Z13-Z12 -> 0 | AB13: =SUM(Y13*$AB$2) -> 0 | AC13: 1740 | AD13: =AC13-AC12 -> 0 | AE13: 354463.2 | AF13: =AE13-AE12 -> 0 | AG13: =IF(AD13>0,AF13/AD13,0) -> 0 | AH13: =AF13+AA13 -> 0 | AI13: =SUM(AH13+V13) -> 853 | AJ13: =-tanks!AW14 -> 853 | AK13: =SUM(AJ13-AI13) -> 0 | AL13: =S13+L13+G13 -> 11 | AM13: =Y13+AD13 -> 0 | AN13: 79 | AO13: =(AN13/100)*3000 -> 2370 | AP13: 79 | AQ13: =(AP13/100)*3000 -> 2370 | AR13: 81 | AS13: =(AR13/100)*3000 -> 2430 | AT13: =SUM(AO13+AQ13+AS13) -> 7170 | AU13: =AT12-AT13+AV13 -> 360 | AV13: 1650 | AW13: 0.7 | AX13: =IF(AV13>0,AW13,AX12) -> 0.7
A14: 43840 | B14: 168 | C14: 174 | D14: =C13-C14 -> -12 | E14: =D14*8.38 -> -100.56 | F14: 1309 | G14: =F14-F13 -> 6 | H14: 330804 | I14: =SUM(H14-H13) -> 534 | J14: =IF(G14>0,I14/G14,0) -> 89 | K14: =K13 -> 1702 | L14: =K14-K13 -> 0 | M14: =M13 -> 123970 | N14: =M14-M13 -> 0 | O14: =SUM(L14*$J$1) -> 0 | P14: 1534 | Q14: 132477 | R14: =Q14-Q13 -> 477 | S14: =SUM(P14-P13) -> 7 | T14: =SUM(S14*$T$2) -> 0 | U14: =SUM(G14+L14+S14) -> 13 | V14: =R14+N14+I14:I14 -> 1011 | W14: =SUM(V14/U14) -> 77.769231 | X14: 2320 | Y14: =X14-X13 -> 0 | Z14: =Z13 -> 130593 | AA14: =Z14-Z13 -> 0 | AB14: =SUM(Y14*$AB$2) -> 0 | AC14: 1749 | AD14: =AC14-AC13 -> 9 | AE14: 354914 | AF14: =AE14-AE13 -> 450.8 | AG14: =IF(AD14>0,AF14/AD14,0) -> 50.088889 | AH14: =AF14+AA14 -> 450.8 | AI14: =SUM(AH14+V14) -> 1461.8 | AJ14: =-tanks!AW15 -> 1461.8 | AK14: =SUM(AJ14-AI14) -> 0 | AL14: =S14+L14+G14 -> 13 | AM14: =Y14+AD14 -> 9 | AN14: 78 | AO14: =(AN14/100)*3000 -> 2340 | AP14: 77 | AQ14: =(AP14/100)*3000 -> 2310 | AR14: 80 | AS14: =(AR14/100)*3000 -> 2400 | AT14: =SUM(AO14+AQ14+AS14) -> 7050 | AU14: =AT13-AT14+AV14 -> 120 | AX14: =IF(AV14>0,AW14,AX13) -> 0.7
A15: 43841 | B15: 162 | C15: 168 | D15: =C14-C15 -> 6 | E15: =D15*8.38 -> 50.28 | F15: 1314 | G15: =F15-F14 -> 5 | H15: 331161 | I15: =SUM(H15-H14) -> 357 | J15: =IF(G15>0,I15/G15,0) -> 71.4 | K15: 1707 | L15: =K15-K14 -> 5 | M15: 124341 | N15: =M15-M14 -> 371 | O15: =SUM(L15*$J$1) -> 344.34375 | P15: =P14 -> 1534 | Q15: =Q14 -> 132477 | R15: =Q15-Q14 -> 0 | S15: =SUM(P15-P14) -> 0 | T15: =SUM(S15*$T$2) -> 0 | U15: =SUM(G15+L15+S15) -> 10 | V15: =R15+N15+I15:I15 -> 728 | W15: =SUM(V15/U15) -> 72.8 | X15: =X14 -> 2320 | Y15: =X15-X14 -> 0 | Z15: =Z14 -> 130593 | AA15: =Z15-Z14 -> 0 | AB15: =SUM(Y15*$AB$2) -> 0 | AC15: =AC14 -> 1749 | AD15: =AC15-AC14 -> 0 | AE15: =AE14 -> 354914 | AF15: =AE15-AE14 -> 0 | AG15: =IF(AD15>0,AF15/AD15,0) -> 0 | AH15: =AF15+AA15 -> 0 | AI15: =SUM(AH15+V15) -> 728 | AJ15: =-tanks!AW16 -> 728 | AK15: =SUM(AJ15-AI15) -> 0 | AL15: =S15+L15+G15 -> 10 | AM15: =Y15+AD15 -> 0 | AN15: 77 | AO15: =(AN15/100)*3000 -> 2310 | AP15: =AP14 -> 77 | AQ15: =(AP15/100)*3000 -> 2310 | AR15: 78 | AS15: =(AR15/100)*3000 -> 2340 | AT15: =SUM(AO15+AQ15+AS15) -> 6960 | AU15: =AT14-AT15+AV15 -> 90 | AX15: =IF(AV15>0,AW15,AX14) -> 0.7
A16: 43842 | B16: 158 | C16: 163 | D16: =C15-C16 -> 5 | E16: =D16*8.38 -> 41.9 | F16: =F15 -> 1314 | G16: =F16-F15 -> 0 | H16: 331161 | I16: =SUM(H16-H15) -> 0 | J16: =IF(G16>0,I16/G16,0) -> 0 | K16: 1711 | L16: =K16-K15 -> 4 | M16: 124632 | N16: =M16-M15 -> 291 | O16: =SUM(L16*$J$1) -> 275.475 | P16: 1537 | Q16: 132729 | R16: =Q16-Q15 -> 252 | S16: =SUM(P16-P15) -> 3 | T16: =SUM(S16*$T$2) -> 0 | U16: =SUM(G16+L16+S16) -> 7 | V16: =R16+N16+I16:I16 -> 543 | W16: =SUM(V16/U16) -> 77.571429 | X16: 2320 | Y16: =X16-X15 -> 0 | Z16: 130593 | AA16: =Z16-Z15 -> 0 | AB16: =SUM(Y16*$AB$2) -> 0 | AC16: 1749 | AD16: =AC16-AC15 -> 0 | AE16: 354914 | AF16: =AE16-AE15 -> 0 | AG16: =IF(AD16>0,AF16/AD16,0) -> 0 | AH16: =AF16+AA16 -> 0 | AI16: =SUM(AH16+V16) -> 543 | AJ16: =-tanks!AW17 -> 543 | AK16: =SUM(AJ16-AI16) -> 0 | AL16: =S16+L16+G16 -> 7 | AM16: =Y16+AD16 -> 0 | AN16: 74 | AO16: =(AN16/100)*3000 -> 2220 | AP16: 74 | AQ16: =(AP16/100)*3000 -> 2220 | AR16: 76 | AS16: =(AR16/100)*3000 -> 2280 | AT16: =SUM(AO16+AQ16+AS16) -> 6720 | AU16: =AT15-AT16+AV16 -> 240 | AX16: =IF(AV16>0,AW16,AX15) -> 0.7
A17: 43843 | B17: 152 | C17: 159 | D17: =C16-C17 -> 4 | E17: =D17*8.38 -> 33.52 | F17: 1319 | G17: =F17-F16 -> 5 | H17: 331585 | I17: =SUM(H17-H16) -> 424 | J17: =IF(G17>0,I17/G17,0) -> 84.8 | K17: 1711 | L17: =K17-K16 -> 0 | M17: 124632 | N17: =M17-M16 -> 0 | O17: =SUM(L17*$J$1) -> 0 | P17: 1541 | Q17: 133054 | R17: =Q17-Q16 -> 325 | S17: =SUM(P17-P16) -> 4 | T17: =SUM(S17*$T$2) -> 0 | U17: =SUM(G17+L17+S17) -> 9 | V17: =R17+N17+I17:I17 -> 749 | X17: 2320 | Y17: =X17-X16 -> 0 | Z17: 130593 | AA17: =Z17-Z16 -> 0 | AB17: =SUM(Y17*$AB$2) -> 0 | AC17: 1749 | AD17: =AC17-AC16 -> 0 | AE17: 354914 | AF17: =AE17-AE16 -> 0 | AG17: =IF(AD17>0,AF17/AD17,0) -> 0 | AH17: =AF17+AA17 -> 0 | AI17: =SUM(AH17+V17) -> 749 | AJ17: =-tanks!AW18 -> 749 | AK17: =SUM(AJ17-AI17) -> 0 | AL17: =S17+L17+G17 -> 9 | AM17: =Y17+AD17 -> 0 | AN17: 71 | AO17: =(AN17/100)*3000 -> 2130 | AP17: 71 | AQ17: =(AP17/100)*3000 -> 2130 | AR17: 74 | AS17: =(AR17/100)*3000 -> 2220 | AT17: =SUM(AO17+AQ17+AS17) -> 6480 | AU17: =AT16-AT17+AV17 -> 240 | AX17: =IF(AV17>0,AW17,AX16) -> 0.7
A18: 43844 | B18: 208 | C18: 214 | D18: =C17-C18 -> -55 | E18: =D18*8.38 -> -460.9 | F18: 1323 | G18: =F18-F17 -> 4 | H18: 331908 | I18: =SUM(H18-H17) -> 323 | J18: =IF(G18>0,I18/G18,0) -> 80.75 | K18: 1712 | L18: =K18-K17 -> 1 | M18: 124752 | N18: =M18-M17 -> 120 | O18: =SUM(L18*$J$1) -> 68.86875 | P18: 1542 | Q18: 133071 | R18: =Q18-Q17 -> 17 | S18: =SUM(P18-P17) -> 1 | T18: =SUM(S18*$T$2) -> 0 | U18: =SUM(G18+L18+S18) -> 6 | V18: =R18+N18+I18:I18 -> 460 | X18: 2320 | Y18: =X18-X17 -> 0 | Z18: 130593 | AA18: =Z18-Z17 -> 0 | AB18: =SUM(Y18*$AB$2) -> 0 | AC18: 1759 | AD18: =AC18-AC17 -> 10 | AE18: 355340.6 | AF18: =AE18-AE17 -> 426.6 | AG18: =IF(AD18>0,AF18/AD18,0) -> 42.66 | AH18: =AF18+AA18 -> 426.6 | AI18: =SUM(AH18+V18) -> 886.6 | AJ18: =-tanks!AW19 -> 886.6 | AK18: =SUM(AJ18-AI18) -> 0 | AL18: =S18+L18+G18 -> 6 | AM18: =Y18+AD18 -> 10 | AN18: 69 | AO18: =(AN18/100)*3000 -> 2070 | AP18: 69 | AQ18: =(AP18/100)*3000 -> 2070 | AR18: 71 | AS18: =(AR18/100)*3000 -> 2130 | AT18: =SUM(AO18+AQ18+AS18) -> 6270 | AU18: =AT17-AT18+AV18 -> 210 | AX18: =IF(AV18>0,AW18,AX17) -> 0.7
A19: 43845 | B19: 201 | C19: 207 | D19: =C18-C19 -> 7 | E19: =D19*8.38 -> 58.66 | F19: 1324 | G19: =F19-F18 -> 1 | H19: 331958 | I19: =SUM(H19-H18) -> 50 | J19: =IF(G19>0,I19/G19,0) -> 50 | K19: 1715 | L19: =K19-K18 -> 3 | M19: 124996 | N19: =M19-M18 -> 244 | O19: =SUM(L19*$J$1) -> 206.60625 | P19: 1545 | Q19: 133365 | R19: =Q19-Q18 -> 294 | S19: =SUM(P19-P18) -> 3 | T19: =SUM(S19*$T$2) -> 0 | U19: =SUM(G19+L19+S19) -> 7 | V19: =R19+N19+I19:I19 -> 588 | X19: 2320 | Y19: =X19-X18 -> 0 | Z19: 130593 | AA19: =Z19-Z18 -> 0 | AB19: =SUM(Y19*$AB$2) -> 0 | AC19: 1762 | AD19: =AC19-AC18 -> 3 | AE19: 355515.2 | AF19: =AE19-AE18 -> 174.6 | AG19: =IF(AD19>0,AF19/AD19,0) -> 58.2 | AH19: =AF19+AA19 -> 174.6 | AI19: =SUM(AH19+V19) -> 762.6 | AJ19: =-tanks!AW20 -> 762.6 | AK19: =SUM(AJ19-AI19) -> 0 | AL19: =S19+L20+G19 -> 4 | AM19: =Y19+AD19 -> 3 | AN19: 67 | AO19: =(AN19/100)*3000 -> 2010 | AP19: 67 | AQ19: =(AP19/100)*3000 -> 2010 | AR19: 69 | AS19: =(AR19/100)*3000 -> 2070 | AT19: =SUM(AO19+AQ19+AS19) -> 6090 | AU19: =AT18-AT19+AV19 -> 180 | AX19: =IF(AV19>0,AW19,AX18) -> 0.7
A20: 43846 | B20: 223 | C20: 229 | D20: =C19-C20 -> -22 | E20: =D20*8.38 -> -184.36 | F20: 1327 | G20: =F20-F19 -> 3 | H20: 332212 | I20: =SUM(H20-H19) -> 254 | J20: =IF(G20>0,I20/G20,0) -> 84.666667 | K20: 1715 | L20: =K20-K19 -> 0 | M20: =M19 -> 124996 | N20: =M20-M19 -> 0 | O20: =SUM(L20*$J$1) -> 0 | P20: 1548 | Q20: 133595 | R20: =Q20-Q19 -> 230 | S20: =SUM(P20-P19) -> 3 | T20: =SUM(S20*$T$2) -> 0 | U20: =SUM(G20+L20+S20) -> 6 | V20: =R20+N20+I20:I20 -> 484 | X20: =X19 -> 2320 | Y20: =X20-X19 -> 0 | Z20: =Z19 -> 130593 | AA20: =Z20-Z19 -> 0 | AB20: =SUM(Y20*$AB$2) -> 0 | AC20: =AC19 -> 1762 | AD20: =AC20-AC19 -> 0 | AE20: =AE19 -> 355515.2 | AF20: =AE20-AE19 -> 0 | AG20: =IF(AD20>0,AF20/AD20,0) -> 0 | AH20: =AF20+AA20 -> 0 | AI20: =SUM(AH20+V20) -> 484 | AJ20: =-tanks!AW21 -> 484 | AK20: =SUM(AJ20-AI20) -> 0 | AL20: =S20+L21+G20 -> 10 | AM20: =Y20+AD20 -> 0 | AN20: 79 | AO20: =(AN20/100)*3000 -> 2370 | AP20: 79 | AQ20: =(AP20/100)*3000 -> 2370 | AR20: 82 | AS20: =(AR20/100)*3000 -> 2460 | AT20: =SUM(AO20+AQ20+AS20) -> 7200 | AU20: =AT19-AT20+AV20 -> 290 | AV20: 1400 | AW20: 0.7 | AX20: =IF(AV20>0,AW20,AX19) -> 0.7
A21: 43847 | B21: 219 | C21: 225 | D21: =C20-C21 -> 4 | E21: =D21*8.38 -> 33.52 | F21: 1330 | G21: =F21-F20 -> 3 | H21: 332480 | I21: =SUM(H21-H20) -> 268 | J21: =IF(G21>0,I21/G21,0) -> 89.333333 | K21: 1719 | L21: =K21-K20 -> 4 | M21: 125236 | N21: =M21-M20 -> 240 | O21: =SUM(L21*$J$1) -> 275.475 | P21: 1549 | Q21: 133617 | R21: =Q21-Q20 -> 22 | S21: =SUM(P21-P20) -> 1 | T21: =SUM(S21*$T$2) -> 0 | U21: =SUM(G21+L21+S21) -> 8 | V21: =R21+N21+I21:I21 -> 530 | X21: =X20 -> 2320 | Y21: =X21-X20 -> 0 | Z21: =Z20 -> 130593 | AA21: =Z21-Z20 -> 0 | AB21: =SUM(Y21*$AB$2) -> 0 | AC21: 1771 | AD21: =AC21-AC20 -> 9 | AE21: 356012.3 | AF21: =AE21-AE20 -> 497.1 | AG21: =IF(AD21>0,AF21/AD21,0) -> 55.233333 | AH21: =AF21+AA21 -> 497.1 | AI21: =SUM(AH21+V21) -> 1027.1 | AJ21: =-tanks!AW22 -> 1027.1 | AK21: =SUM(AJ21-AI21) -> 0 | AL21: =S21+L21+G21 -> 8 | AM21: =Y21+AD21 -> 9 | AN21: 78 | AO21: =(AN21/100)*3000 -> 2340 | AP21: 78 | AQ21: =(AP21/100)*3000 -> 2340 | AR21: 81 | AS21: =(AR21/100)*3000 -> 2430 | AT21: =SUM(AO21+AQ21+AS21) -> 7110 | AU21: =AT20-AT21+AV21 -> 90 | AX21: =IF(AV21>0,AW21,AX20) -> 0.7
A22: 43848 | B22: =B21 -> 219 | C22: =C21 -> 225 | D22: =C21-C22 -> 0 | E22: =D22*8.38 -> 0 | F22: =F21 -> 1330 | G22: =F22-F21 -> 0 | H22: =H21 -> 332480 | I22: =SUM(H22-H21) -> 0 | J22: =IF(G22>0,I22/G22,0) -> 0 | K22: =K21 -> 1719 | L22: =K22-K21 -> 0 | M22: =M21 -> 125236 | N22: =M22-M21 -> 0 | O22: =SUM(L22*$J$1) -> 0 | P22: =P21 -> 1549 | Q22: =Q21 -> 133617 | R22: =Q22-Q21 -> 0 | S22: =SUM(P22-P21) -> 0 | T22: =SUM(S22*$T$2) -> 0 | U22: =SUM(G22+L22+S22) -> 0 | V22: =R22+N22+I22:I22 -> 0 | X22: =X21 -> 2320 | Y22: =X22-X21 -> 0 | Z22: =Z21 -> 130593 | AA22: =Z22-Z21 -> 0 | AB22: =SUM(Y22*$AB$2) -> 0 | AC22: =AC21 -> 1771 | AD22: =AC22-AC21 -> 0 | AE22: =AE21 -> 356012.3 | AF22: =AE22-AE21 -> 0 | AG22: =IF(AD22>0,AF22/AD22,0) -> 0 | AH22: =AF22+AA22 -> 0 | AI22: =SUM(AH22+V22) -> 0 | AJ22: =-tanks!AW23 -> 0 | AK22: =SUM(AJ22-AI22) -> 0 | AL22: =S22+L22+G22 -> 0 | AM22: =Y22+AD22 -> 0 | AN22: =AN21 -> 78 | AO22: =(AN22/100)*3000 -> 2340 | AP22: =AP21 -> 78 | AQ22: =(AP22/100)*3000 -> 2340 | AR22: =AR21 -> 81 | AS22: =(AR22/100)*3000 -> 2430 | AT22: =SUM(AO22+AQ22+AS22) -> 7110 | AU22: =AT21-AT22+AV22 -> 0 | AX22: =IF(AV22>0,AW22,AX21) -> 0.7
A23: 43849 | B23: =B22 -> 219 | C23: =C22 -> 225 | D23: =C22-C23 -> 0 | E23: =D23*8.38 -> 0 | F23: =F22 -> 1330 | G23: =F23-F22 -> 0 | H23: =H22 -> 332480 | I23: =SUM(H23-H22) -> 0 | J23: =IF(G23>0,I23/G23,0) -> 0 | K23: =K22 -> 1719 | L23: =K23-K22 -> 0 | M23: =M22 -> 125236 | N23: =M23-M22 -> 0 | O23: =SUM(L23*$J$1) -> 0 | P23: =P22 -> 1549 | Q23: =Q22 -> 133617 | R23: =Q23-Q22 -> 0 | S23: =SUM(P23-P22) -> 0 | T23: =SUM(S23*$T$2) -> 0 | U23: =SUM(G23+L23+S23) -> 0 | V23: =R23+N23+I23:I23 -> 0 | X23: =X22 -> 2320 | Y23: =X23-X22 -> 0 | Z23: =Z22 -> 130593 | AA23: =Z23-Z22 -> 0 | AB23: =SUM(Y23*$AB$2) -> 0 | AC23: =AC22 -> 1771 | AD23: =AC23-AC22 -> 0 | AE23: =AE22 -> 356012.3 | AF23: =AE23-AE22 -> 0 | AG23: =IF(AD23>0,AF23/AD23,0) -> 0 | AH23: =AF23+AA23 -> 0 | AI23: =SUM(AH23+V23) -> 0 | AJ23: =-tanks!AW24 -> 0 | AK23: =SUM(AJ23-AI23) -> 0 | AL23: =S23+L23+G23 -> 0 | AM23: =Y23+AD23 -> 0 | AN23: =AN22 -> 78 | AO23: =(AN23/100)*3000 -> 2340 | AP23: =AP22 -> 78 | AQ23: =(AP23/100)*3000 -> 2340 | AR23: =AR22 -> 81 | AS23: =(AR23/100)*3000 -> 2430 | AT23: =SUM(AO23+AQ23+AS23) -> 7110 | AU23: =AT22-AT23+AV23 -> 0 | AX23: =IF(AV23>0,AW23,AX22) -> 0.7
A24: 43850 | B24: =B23 -> 219 | C24: =C23 -> 225 | D24: =C23-C24 -> 0 | E24: =D24*8.38 -> 0 | F24: =F23 -> 1330 | G24: =F24-F23 -> 0 | H24: =H23 -> 332480 | I24: =SUM(H24-H23) -> 0 | J24: =IF(G24>0,I24/G24,0) -> 0 | K24: =K23 -> 1719 | L24: =K24-K23 -> 0 | M24: =M23 -> 125236 | N24: =M24-M23 -> 0 | O24: =SUM(L24*$J$1) -> 0 | P24: =P23 -> 1549 | Q24: =Q23 -> 133617 | R24: =Q24-Q23 -> 0 | S24: =SUM(P24-P23) -> 0 | T24: =SUM(S24*$T$2) -> 0 | U24: =SUM(G24+L24+S24) -> 0 | V24: =R24+N24+I24:I24 -> 0 | X24: =X23 -> 2320 | Y24: =X24-X23 -> 0 | Z24: =Z23 -> 130593 | AA24: =Z24-Z23 -> 0 | AB24: =SUM(Y24*$AB$2) -> 0 | AC24: =AC23 -> 1771 | AD24: =AC24-AC23 -> 0 | AE24: =AE23 -> 356012.3 | AF24: =AE24-AE23 -> 0 | AG24: =IF(AD24>0,AF24/AD24,0) -> 0 | AH24: =AF24+AA24 -> 0 | AI24: =SUM(AH24+V24) -> 0 | AJ24: =-tanks!AW25 -> 0 | AK24: =SUM(AJ24-AI24) -> 0 | AL24: =S24+L24+G24 -> 0 | AM24: =Y24+AD24 -> 0 | AN24: =AN23 -> 78 | AO24: =(AN24/100)*3000 -> 2340 | AP24: =AP23 -> 78 | AQ24: =(AP24/100)*3000 -> 2340 | AR24: =AR23 -> 81 | AS24: =(AR24/100)*3000 -> 2430 | AT24: =SUM(AO24+AQ24+AS24) -> 7110 | AU24: =AT23-AT24+AV24 -> 0 | AX24: =IF(AV24>0,AW24,AX23) -> 0.7
A25: 43851 | B25: =B24 -> 219 | C25: =C24 -> 225 | D25: =C24-C25 -> 0 | E25: =D25*8.38 -> 0 | F25: =F24 -> 1330 | G25: =F25-F24 -> 0 | H25: =H24 -> 332480 | I25: =SUM(H25-H24) -> 0 | J25: =IF(G25>0,I25/G25,0) -> 0 | K25: =K24 -> 1719 | L25: =K25-K24 -> 0 | M25: =M24 -> 125236 | N25: =M25-M24 -> 0 | O25: =SUM(L25*$J$1) -> 0 | P25: =P24 -> 1549 | Q25: =Q24 -> 133617 | R25: =Q25-Q24 -> 0 | S25: =SUM(P25-P24) -> 0 | T25: =SUM(S25*$T$2) -> 0 | U25: =SUM(G25+L25+S25) -> 0 | V25: =R25+N25+I25:I25 -> 0 | X25: =X24 -> 2320 | Y25: =X25-X24 -> 0 | Z25: =Z24 -> 130593 | AA25: =Z25-Z24 -> 0 | AB25: =SUM(Y25*$AB$2) -> 0 | AC25: =AC24 -> 1771 | AD25: =AC25-AC24 -> 0 | AE25: =AE24 -> 356012.3 | AF25: =AE25-AE24 -> 0 | AG25: =IF(AD25>0,AF25/AD25,0) -> 0 | AH25: =AF25+AA25 -> 0 | AI25: =SUM(AH25+V25) -> 0 | AJ25: =-tanks!AW26 -> 0 | AK25: =SUM(AJ25-AI25) -> 0 | AL25: =S25+L25+G25 -> 0 | AM25: =Y25+AD25 -> 0 | AN25: =AN24 -> 78 | AO25: =(AN25/100)*3000 -> 2340 | AP25: =AP24 -> 78 | AQ25: =(AP25/100)*3000 -> 2340 | AR25: =AR24 -> 81 | AS25: =(AR25/100)*3000 -> 2430 | AT25: =SUM(AO25+AQ25+AS25) -> 7110 | AU25: =AT24-AT25+AV25 -> 0 | AX25: =IF(AV25>0,AW25,AX24) -> 0.7
A26: 43852 | B26: =B25 -> 219 | C26: =C25 -> 225 | D26: =C25-C26 -> 0 | E26: =D26*8.38 -> 0 | F26: =F25 -> 1330 | G26: =F26-F25 -> 0 | H26: =H25 -> 332480 | I26: =SUM(H26-H25) -> 0 | J26: =IF(G26>0,I26/G26,0) -> 0 | K26: =K25 -> 1719 | L26: =K26-K25 -> 0 | M26: =M25 -> 125236 | N26: =M26-M25 -> 0 | O26: =SUM(L26*$J$1) -> 0 | P26: =P25 -> 1549 | Q26: =Q25 -> 133617 | R26: =Q26-Q25 -> 0 | S26: =SUM(P26-P25) -> 0 | T26: =SUM(S26*$T$2) -> 0 | U26: =SUM(G26+L26+S26) -> 0 | V26: =R26+N26+I26:I26 -> 0 | X26: =X25 -> 2320 | Y26: =X26-X25 -> 0 | Z26: =Z25 -> 130593 | AA26: =Z26-Z25 -> 0 | AB26: =SUM(Y26*$AB$2) -> 0 | AC26: =AC25 -> 1771 | AD26: =AC26-AC25 -> 0 | AE26: =AE25 -> 356012.3 | AF26: =AE26-AE25 -> 0 | AG26: =IF(AD26>0,AF26/AD26,0) -> 0 | AH26: =AF26+AA26 -> 0 | AI26: =SUM(AH26+V26) -> 0 | AJ26: =-tanks!AW27 -> 0 | AK26: =SUM(AJ26-AI26) -> 0 | AL26: =S26+L26+G26 -> 0 | AM26: =Y26+AD26 -> 0 | AN26: =AN25 -> 78 | AO26: =(AN26/100)*3000 -> 2340 | AP26: =AP25 -> 78 | AQ26: =(AP26/100)*3000 -> 2340 | AR26: =AR25 -> 81 | AS26: =(AR26/100)*3000 -> 2430 | AT26: =SUM(AO26+AQ26+AS26) -> 7110 | AU26: =AT25-AT26+AV26 -> 0 | AX26: =IF(AV26>0,AW26,AX25) -> 0.7
A27: 43853 | B27: =B26 -> 219 | C27: =C26 -> 225 | D27: =C26-C27 -> 0 | E27: =D27*8.38 -> 0 | F27: =F26 -> 1330 | G27: =F27-F26 -> 0 | H27: =H26 -> 332480 | I27: =SUM(H27-H26) -> 0 | J27: =IF(G27>0,I27/G27,0) -> 0 | K27: =K26 -> 1719 | L27: =K27-K26 -> 0 | M27: =M26 -> 125236 | N27: =M27-M26 -> 0 | O27: =SUM(L27*$J$1) -> 0 | P27: =P26 -> 1549 | Q27: =Q26 -> 133617 | R27: =Q27-Q26 -> 0 | S27: =SUM(P27-P26) -> 0 | T27: =SUM(S27*$T$2) -> 0 | U27: =SUM(G27+L27+S27) -> 0 | V27: =R27+N27+I27:I27 -> 0 | X27: =X26 -> 2320 | Y27: =X27-X26 -> 0 | Z27: =Z26 -> 130593 | AA27: =Z27-Z26 -> 0 | AB27: =SUM(Y27*$AB$2) -> 0 | AC27: =AC26 -> 1771 | AD27: =AC27-AC26 -> 0 | AE27: =AE26 -> 356012.3 | AF27: =AE27-AE26 -> 0 | AG27: =IF(AD27>0,AF27/AD27,0) -> 0 | AH27: =AF27+AA27 -> 0 | AI27: =SUM(AH27+V27) -> 0 | AJ27: =-tanks!AW28 -> 0 | AK27: =SUM(AJ27-AI27) -> 0 | AL27: =S27+L27+G27 -> 0 | AM27: =Y27+AD27 -> 0 | AN27: =AN26 -> 78 | AO27: =(AN27/100)*3000 -> 2340 | AP27: =AP26 -> 78 | AQ27: =(AP27/100)*3000 -> 2340 | AR27: =AR26 -> 81 | AS27: =(AR27/100)*3000 -> 2430 | AT27: =SUM(AO27+AQ27+AS27) -> 7110 | AU27: =AT26-AT27+AV27 -> 0 | AX27: =IF(AV27>0,AW27,AX26) -> 0.7
A28: 43854 | B28: =B27 -> 219 | C28: =C27 -> 225 | D28: =C27-C28 -> 0 | E28: =D28*8.38 -> 0 | F28: =F27 -> 1330 | G28: =F28-F27 -> 0 | H28: =H27 -> 332480 | I28: =SUM(H28-H27) -> 0 | J28: =IF(G28>0,I28/G28,0) -> 0 | K28: =K27 -> 1719 | L28: =K28-K27 -> 0 | M28: =M27 -> 125236 | N28: =M28-M27 -> 0 | O28: =SUM(L28*$J$1) -> 0 | P28: =P27 -> 1549 | Q28: =Q27 -> 133617 | R28: =Q28-Q27 -> 0 | S28: =SUM(P28-P27) -> 0 | T28: =SUM(S28*$T$2) -> 0 | U28: =SUM(G28+L28+S28) -> 0 | V28: =R28+N28+I28:I28 -> 0 | X28: =X27 -> 2320 | Y28: =X28-X27 -> 0 | Z28: =Z27 -> 130593 | AA28: =Z28-Z27 -> 0 | AB28: =SUM(Y28*$AB$2) -> 0 | AC28: =AC27 -> 1771 | AD28: =AC28-AC27 -> 0 | AE28: =AE27 -> 356012.3 | AF28: =AE28-AE27 -> 0 | AG28: =IF(AD28>0,AF28/AD28,0) -> 0 | AH28: =AF28+AA28 -> 0 | AI28: =SUM(AH28+V28) -> 0 | AJ28: =-tanks!AW29 -> 0 | AK28: =SUM(AJ28-AI28) -> 0 | AL28: =S28+L28+G28 -> 0 | AM28: =Y28+AD28 -> 0 | AN28: =AN27 -> 78 | AO28: =(AN28/100)*3000 -> 2340 | AP28: =AP27 -> 78 | AQ28: =(AP28/100)*3000 -> 2340 | AR28: =AR27 -> 81 | AS28: =(AR28/100)*3000 -> 2430 | AT28: =SUM(AO28+AQ28+AS28) -> 7110 | AU28: =AT27-AT28+AV28 -> 0 | AX28: =IF(AV28>0,AW28,AX27) -> 0.7
A29: 43855 | B29: =B28 -> 219 | C29: =C28 -> 225 | D29: =C28-C29 -> 0 | E29: =D29*8.38 -> 0 | F29: =F28 -> 1330 | G29: =F29-F28 -> 0 | H29: =H28 -> 332480 | I29: =SUM(H29-H28) -> 0 | J29: =IF(G29>0,I29/G29,0) -> 0 | K29: =K28 -> 1719 | L29: =K29-K28 -> 0 | M29: =M28 -> 125236 | N29: =M29-M28 -> 0 | O29: =SUM(L29*$J$1) -> 0 | P29: =P28 -> 1549 | Q29: =Q28 -> 133617 | R29: =Q29-Q28 -> 0 | S29: =SUM(P29-P28) -> 0 | T29: =SUM(S29*$T$2) -> 0 | U29: =SUM(G29+L29+S29) -> 0 | V29: =R29+N29+I29:I29 -> 0 | X29: =X28 -> 2320 | Y29: =X29-X28 -> 0 | Z29: =Z28 -> 130593 | AA29: =Z29-Z28 -> 0 | AB29: =SUM(Y29*$AB$2) -> 0 | AC29: =AC28 -> 1771 | AD29: =AC29-AC28 -> 0 | AE29: =AE28 -> 356012.3 | AF29: =AE29-AE28 -> 0 | AG29: =IF(AD29>0,AF29/AD29,0) -> 0 | AH29: =AF29+AA29 -> 0 | AI29: =SUM(AH29+V29) -> 0 | AJ29: =-tanks!AW30 -> 0 | AK29: =SUM(AJ29-AI29) -> 0 | AL29: =S29+L29+G29 -> 0 | AM29: =Y29+AD29 -> 0 | AN29: =AN28 -> 78 | AO29: =(AN29/100)*3000 -> 2340 | AP29: =AP28 -> 78 | AQ29: =(AP29/100)*3000 -> 2340 | AR29: =AR28 -> 81 | AS29: =(AR29/100)*3000 -> 2430 | AT29: =SUM(AO29+AQ29+AS29) -> 7110 | AU29: =AT28-AT29+AV29 -> 0 | AX29: =IF(AV29>0,AW29,AX28) -> 0.7
A30: 43856 | B30: =B29 -> 219 | C30: =C29 -> 225 | D30: =C29-C30 -> 0 | E30: =D30*8.38 -> 0 | F30: =F29 -> 1330 | G30: =F30-F29 -> 0 | H30: =H29 -> 332480 | I30: =SUM(H30-H29) -> 0 | J30: =IF(G30>0,I30/G30,0) -> 0 | K30: =K29 -> 1719 | L30: =K30-K29 -> 0 | M30: =M29 -> 125236 | N30: =M30-M29 -> 0 | O30: =SUM(L30*$J$1) -> 0 | P30: =P29 -> 1549 | Q30: =Q29 -> 133617 | R30: =Q30-Q29 -> 0 | S30: =SUM(P30-P29) -> 0 | T30: =SUM(S30*$T$2) -> 0 | U30: =SUM(G30+L30+S30) -> 0 | V30: =R30+N30+I30:I30 -> 0 | X30: =X29 -> 2320 | Y30: =X30-X29 -> 0 | Z30: =Z29 -> 130593 | AA30: =Z30-Z29 -> 0 | AB30: =SUM(Y30*$AB$2) -> 0 | AC30: =AC29 -> 1771 | AD30: =AC30-AC29 -> 0 | AE30: =AE29 -> 356012.3 | AF30: =AE30-AE29 -> 0 | AG30: =IF(AD30>0,AF30/AD30,0) -> 0 | AH30: =AF30+AA30 -> 0 | AI30: =SUM(AH30+V30) -> 0 | AJ30: =-tanks!AW31 -> 0 | AK30: =SUM(AJ30-AI30) -> 0 | AL30: =S30+L30+G30 -> 0 | AM30: =Y30+AD30 -> 0 | AN30: =AN29 -> 78 | AO30: =(AN30/100)*3000 -> 2340 | AP30: =AP29 -> 78 | AQ30: =(AP30/100)*3000 -> 2340 | AR30: =AR29 -> 81 | AS30: =(AR30/100)*3000 -> 2430 | AT30: =SUM(AO30+AQ30+AS30) -> 7110 | AU30: =AT29-AT30+AV30 -> 0 | AX30: =IF(AV30>0,AW30,AX29) -> 0.7
A31: 43857 | B31: =B30 -> 219 | C31: =C30 -> 225 | D31: =C30-C31 -> 0 | E31: =D31*8.38 -> 0 | F31: =F30 -> 1330 | G31: =F31-F30 -> 0 | H31: =H30 -> 332480 | I31: =SUM(H31-H30) -> 0 | J31: =IF(G31>0,I31/G31,0) -> 0 | K31: =K30 -> 1719 | L31: =K31-K30 -> 0 | M31: =M30 -> 125236 | N31: =M31-M30 -> 0 | O31: =SUM(L31*$J$1) -> 0 | P31: =P30 -> 1549 | Q31: =Q30 -> 133617 | R31: =Q31-Q30 -> 0 | S31: =SUM(P31-P30) -> 0 | T31: =SUM(S31*$T$2) -> 0 | U31: =SUM(G31+L31+S31) -> 0 | V31: =R31+N31+I31:I31 -> 0 | X31: =X30 -> 2320 | Y31: =X31-X30 -> 0 | Z31: =Z30 -> 130593 | AA31: =Z31-Z30 -> 0 | AB31: =SUM(Y31*$AB$2) -> 0 | AC31: =AC30 -> 1771 | AD31: =AC31-AC30 -> 0 | AE31: =AE30 -> 356012.3 | AF31: =AE31-AE30 -> 0 | AG31: =IF(AD31>0,AF31/AD31,0) -> 0 | AH31: =AF31+AA31 -> 0 | AI31: =SUM(AH31+V31) -> 0 | AJ31: =-tanks!AW32 -> 0 | AK31: =SUM(AJ31-AI31) -> 0 | AL31: =S31+L31+G31 -> 0 | AM31: =Y31+AD31 -> 0 | AN31: =AN30 -> 78 | AO31: =(AN31/100)*3000 -> 2340 | AP31: =AP30 -> 78 | AQ31: =(AP31/100)*3000 -> 2340 | AR31: =AR30 -> 81 | AS31: =(AR31/100)*3000 -> 2430 | AT31: =SUM(AO31+AQ31+AS31) -> 7110 | AU31: =AT30-AT31+AV31 -> 0 | AX31: =IF(AV31>0,AW31,AX30) -> 0.7
A32: 43858 | B32: =B31 -> 219 | C32: =C31 -> 225 | D32: =C31-C32 -> 0 | E32: =D32*8.38 -> 0 | F32: =F31 -> 1330 | G32: =F32-F31 -> 0 | H32: =H31 -> 332480 | I32: =SUM(H32-H31) -> 0 | J32: =IF(G32>0,I32/G32,0) -> 0 | K32: =K31 -> 1719 | L32: =K32-K31 -> 0 | M32: =M31 -> 125236 | N32: =M32-M31 -> 0 | O32: =SUM(L32*$J$1) -> 0 | P32: =P31 -> 1549 | Q32: =Q31 -> 133617 | R32: =Q32-Q31 -> 0 | S32: =SUM(P32-P31) -> 0 | T32: =SUM(S32*$T$2) -> 0 | U32: =SUM(G32+L32+S32) -> 0 | V32: =R32+N32+I32:I32 -> 0 | X32: =X31 -> 2320 | Y32: =X32-X31 -> 0 | Z32: =Z31 -> 130593 | AA32: =Z32-Z31 -> 0 | AB32: =SUM(Y32*$AB$2) -> 0 | AC32: =AC31 -> 1771 | AD32: =AC32-AC31 -> 0 | AE32: =AE31 -> 356012.3 | AF32: =AE32-AE31 -> 0 | AG32: =IF(AD32>0,AF32/AD32,0) -> 0 | AH32: =AF32+AA32 -> 0 | AI32: =SUM(AH32+V32) -> 0 | AJ32: =-tanks!AW33 -> 0 | AK32: =SUM(AJ32-AI32) -> 0 | AL32: =S32+L32+G32 -> 0 | AM32: =Y32+AD32 -> 0 | AN32: =AN31 -> 78 | AO32: =(AN32/100)*3000 -> 2340 | AP32: =AP31 -> 78 | AQ32: =(AP32/100)*3000 -> 2340 | AR32: =AR31 -> 81 | AS32: =(AR32/100)*3000 -> 2430 | AT32: =SUM(AO32+AQ32+AS32) -> 7110 | AU32: =AT31-AT32+AV32 -> 0 | AX32: =IF(AV32>0,AW32,AX31) -> 0.7
A33: 43859 | B33: =B32 -> 219 | C33: =C32 -> 225 | D33: =C32-C33 -> 0 | E33: =D33*8.38 -> 0 | F33: =F32 -> 1330 | G33: =F33-F32 -> 0 | H33: =H32 -> 332480 | I33: =SUM(H33-H32) -> 0 | J33: =IF(G33>0,I33/G33,0) -> 0 | K33: =K32 -> 1719 | L33: =K33-K32 -> 0 | M33: =M32 -> 125236 | N33: =M33-M32 -> 0 | O33: =SUM(L33*$J$1) -> 0 | P33: =P32 -> 1549 | Q33: =Q32 -> 133617 | R33: =Q33-Q32 -> 0 | S33: =SUM(P33-P32) -> 0 | T33: =SUM(S33*$T$2) -> 0 | U33: =SUM(G33+L33+S33) -> 0 | V33: =R33+N33+I33:I33 -> 0 | X33: =X32 -> 2320 | Y33: =X33-X32 -> 0 | Z33: =Z32 -> 130593 | AA33: =Z33-Z32 -> 0 | AB33: =SUM(Y33*$AB$2) -> 0 | AC33: =AC32 -> 1771 | AD33: =AC33-AC32 -> 0 | AE33: =AE32 -> 356012.3 | AF33: =AE33-AE32 -> 0 | AG33: =IF(AD33>0,AF33/AD33,0) -> 0 | AH33: =AF33+AA33 -> 0 | AI33: =SUM(AH33+V33) -> 0 | AJ33: =-tanks!AW34 -> 0 | AK33: =SUM(AJ33-AI33) -> 0 | AL33: =S33+L33+G33 -> 0 | AM33: =Y33+AD33 -> 0 | AN33: =AN32 -> 78 | AO33: =(AN33/100)*3000 -> 2340 | AP33: =AP32 -> 78 | AQ33: =(AP33/100)*3000 -> 2340 | AR33: =AR32 -> 81 | AS33: =(AR33/100)*3000 -> 2430 | AT33: =SUM(AO33+AQ33+AS33) -> 7110 | AU33: =AT32-AT33+AV33 -> 0 | AX33: =IF(AV33>0,AW33,AX32) -> 0.7
... A35: 43861 | B35: =B34 -> 219 | C35: =C34 -> 225 | D35: =C34-C35 -> 0 | E35: =D35*8.38 -> 0 | F35: =F34 -> 1330 | G35: =F35-F34 -> 0 | H35: =H34 -> 332480 | I35: =SUM(H35-H34) -> 0 | J35: =IF(G35>0,I35/G35,0) -> 0 | K35: =K34 -> 1719 | L35: =K35-K34 -> 0 | M35: =M34 -> 125236 | N35: =M35-M34 -> 0 | O35: =SUM(L35*$J$1) -> 0 | P35: =P34 -> 1549 | Q35: =Q34 -> 133617 | R35: =Q35-Q34 -> 0 | S35: =SUM(P35-P34) -> 0 | T35: =SUM(S35*$T$2) -> 0 | U35: =SUM(G35+L35+S35) -> 0 | V35: =R35+N35+I35:I35 -> 0 | X35: =X34 -> 2320 | Y35: =X35-X34 -> 0 | Z35: =Z34 -> 130593 | AA35: =Z35-Z34 -> 0 | AB35: =SUM(Y35*$AB$2) -> 0 | AC35: =AC34 -> 1771 | AD35: =AC35-AC34 -> 0 | AE35: =AE34 -> 356012.3 | AF35: =AE35-AE34 -> 0 | AG35: =IF(AD35>0,AF35/AD35,0) -> 0 | AH35: =AF35+AA35 -> 0 | AI35: =SUM(AH35+V35) -> 0 | AJ35: =-tanks!AW36 -> 0 | AK35: =SUM(AJ35-AI35) -> 0 | AL35: =S35+L35+G35 -> 0 | AM35: =Y35+AD35 -> 0 | AN35: =AN34 -> 78 | AO35: =(AN35/100)*3000 -> 2340 | AP35: =AP34 -> 78 | AQ35: =(AP35/100)*3000 -> 2340 | AR35: =AR34 -> 81 | AS35: =(AR35/100)*3000 -> 2430 | AT35: =SUM(AO35+AQ35+AS35) -> 7110 | AU35: =AT34-AT35+AV35 -> 0 | AX35: =IF(AV35>0,AW35,AX34) -> 0.7
J36: =SUM(J5:J34)/(COUNT(J5:J34)-COUNTIF(J5:J34,0)) -> 68.86875 | AE36: . | AR36: Nb Delivery | AS36: =COUNT(AW5:AW35) -> 3 | AU36: =SUM(AU5:AU35) -> 3840 | AV36: =SUM(AV5:AV35) -> 4950 | AW36: =SUM(AW5:AW35)/AS36 -> 0.7
AH37: =AF37+AA37 -> 0 | AI37: =SUM(AI5:AI35) -> 15865.3
AH38: =AF38+AA38 -> 0 | AU38: =AU36*0.51 -> 1958.4 | AV38: =AV36/0.51 -> 9705.8824 | AW38: =SUM(AW5:AW35)/AS36 -> 0.7
AV39: =AV36*0.51 -> 2524.5

Sheet WATER
D1: =SUM(G21:G35) -> 8809245 | AR1: Entrance | AT1: Tank 1 | AV1: Tank 2
AR2: Level | AW2: Quantity CM3 | AZ2: Var
A3: Date | B3: Truck | C3: Truck M3/day | D3: N0. Trucks | F3: REQ. # of trucks | G3: City | H3: City/day | I3: Total water delivery | K3: SW | L3: Cosum SW/day | M3: RO Guest/ Liter | O3: RO K&L/ Liter | Q3: TOTAL RO Production | R3: RO 1 RH | S3: RO 2 RH | T3: RO water counter | U3: RO Cons m3 | V3: Steam Boiler | W3: Steam Boiler/day | X3: Softener Guest | Y3: Guest Sotf/day | Z3: Softener K&L | AA3: K&L Soft/Day | AB3: Fire Tank Level | AC3: Fire Tank Counter | AE3: Laundry Hot Water Counter | AF3: Hot Water Cons/day | AG3: Laundry Cold Water Counter | AH3: Cold Water Cons/day | AI3: Laundry Water Total Cons | AJ3: K&L Sotf/day | AK3: Guest / day | AL3: K&L /day | AM3: Avg Outside Temp | AN3: Banquet Activity | AR3: Date | AT3: MainI | AV3: Kitchen and Laundry | AX3: Guest | AY3: Main Tank | AZ3: Kitchen and Laundry | BA3: Guest | BB3: Kitchen and Laundry | BC3: Main | BD3: Guest | BE3: Total VAR | BF3: Hotel Consumption
E4: 1.66 | AN4: Ball R | AO4: Meeting | AP4: outlet | AT4: 180 | AV4: 220 | AX4: 580 | AY4: =SUM(AT4) -> 180 | AZ4: =SUM(AV4) -> 220 | BA4: =SUM(AX4) -> 580
A5: 43769 | B5: =[1]WATER!B36 -> 108202 | C5: =[1]WATER!C36 -> 132 | D5: =[1]WATER!D36 -> 4.8888889 | E5: =[1]WATER!E36 -> 461.05548 | F5: =[1]WATER!F36 -> 0 | G5: =[1]WATER!G36 -> 584867 | H5: =[1]WATER!H36 -> 213 | I5: =[1]WATER!I36 -> 345 | ... BG5: =[1]WATER!BG36 -> 127.4
A6: =ELEC!C3 -> 43831 | B6: 108202 | C6: =B6-B5 -> 0 | D6: =C6/27 -> 0 | E6: =SUM((C6*$E$4)+(7500/'EDl log'!$A$38)) -> 241.93548 | G6: 584886 | H6: =G6-G5 -> 19 | I6: =C6+H6 -> 19 | J6: =IF(I6>0,E6/I6,0) -> 12.733447 | K6: ='Swimming Pool quality check '!H6 -> 5783 | L6: 0 | M6: =M5 -> 457.44 | N6: =SUM(M6-M5) -> 0 | O6: =O5 -> 529.52 | P6: =SUM(O6-O5) -> 0 | Q6: =P6+N6 -> 0 | T6: 4371 | U6: =SUM(T6-T5) -> 8 | V6: 336 | W6: =+V6-V5 -> 4 | X6: 138719 | Y6: =SUM(X6-X5) -> 48 | Z6: 90702 | AA6: =Z6-Z5 -> 81 | AB6: 249 | AC6: =AC5 -> 670 | AD6: 0 | AE6: 61.38 | AF6: =AE6-AE5 -> 1.16 | AG6: 970.45 | AH6: =AG6-AG5 -> 9.09 | AI6: =AF6+AH6 -> 10.25 | AJ6: =+Z6-Z5 -> 81 | AK6: =SUM(Y6-L6) -> 48 | AL6: =SUM(AJ6-W6) -> 77 | AM6: ='General information '!D6 -> 13.5 | AN6: ='General information '!H6 -> 0 | AP6: ='General information '!J6 -> 549 | AR6: =A6 -> 43831 | AS6: =AS5 -> 0.9 | AT6: 0 | AU6: =AU5 -> 1.1 | AV6: 80 | AW6: 2.9 | AX6: 72 | AY6: =AS6*AT6 -> 0 | AZ6: =AU6*AV6 -> 88 | BA6: =AW6*AX6 -> 208.8 | BB6: =AY6-AY5 -> -91.8 | BC6: =AZ6-AZ5 -> 9.9 | BD6: =BA6-BA5 -> -11.6 | BE6: =SUM(BB6:BD6) -> -93.5 | BF6: =SUM(I6-BE6) -> 112.5 | BG6: =SUM(I6-BF6) -> -93.5
A7: =ELEC!C4 -> 43832 | B7: 108282 | C7: =B7-B6 -> 80 | D7: =C7/27 -> 2.962963 | E7: =SUM((C7*$E$4)+(7500/'EDl log'!$A$38)) -> 374.73548 | F7: 3 | G7: 585122 | H7: =G7-G6 -> 236 | I7: =C7+H7 -> 316 | J7: =IF(I7>0,E7/I7,0) -> 1.1858718 | K7: ='Swimming Pool quality check '!H7 -> 5790 | L7: =K7-K6 -> 7 | M7: =M6 -> 457.44 | N7: =SUM(M7-M6) -> 0 | O7: =O6 -> 529.52 | P7: =SUM(O7-O6) -> 0 | Q7: =P7+N7 -> 0 | T7: 4376 | U7: =SUM(T7-T6) -> 5 | V7: 338 | W7: =+V7-V6 -> 2 | X7: 138807 | Y7: =SUM(X7-X6) -> 88 | Z7: 90761 | AA7: =Z7-Z6 -> 59 | AB7: =AB6 -> 249 | AC7: =AC6 -> 670 | AD7: =AC7-AC6 -> 0 | AE7: 63.34 | AF7: =AE7-AE6 -> 1.96 | AG7: 991.8 | AH7: =AG7-AG6 -> 21.35 | AI7: =AF7+AH7 -> 23.31 | AJ7: =+Z7-Z6 -> 59 | AK7: =SUM(Y7-L7) -> 81 | AL7: =SUM(AJ7-W7) -> 57 | AM7: ='General information '!D7 -> 14.5 | AN7: ='General information '!H7 -> 0 | AP7: ='General information '!J7 -> 371 | AR7: =A7 -> 43832 | AS7: =AS6 -> 0.9 | AT7: 57 | AU7: =AU6 -> 1.1 | AV7: 106 | AW7: 2.9 | AX7: 70 | AY7: =AS7*AT7 -> 51.3 | AZ7: =AU7*AV7 -> 116.6 | BA7: =AW7*AX7 -> 203 | BB7: =AY7-AY6 -> 51.3 | BC7: =AZ7-AZ6 -> 28.6 | BD7: =BA7-BA6 -> -5.8 | BE7: =SUM(BB7:BD7) -> 74.1 | BF7: =SUM(I7-BE7) -> 241.9 | BG7: =SUM(I7-BF7) -> 74.1
A8: =ELEC!C5 -> 43833 | B8: 108282 | C8: =B8-B7 -> 0 | D8: =C8/27 -> 0 | E8: =SUM((C8*$E$4)+(7500/'EDl log'!$A$38)) -> 241.93548 | G8: =G7 -> 585122 | H8: =G8-G7 -> 0 | I8: =C8+H8 -> 0 | J8: =IF(I8>0,E8/I8,0) -> 0 | K8: ='Swimming Pool quality check '!H8 -> 5791 | L8: =K8-K7 -> 1 | M8: =M7 -> 457.44 | N8: =SUM(M8-M7) -> 0 | O8: =O7 -> 529.52 | P8: =SUM(O8-O7) -> 0 | Q8: =P8+N8 -> 0 | T8: 4381 | U8: =SUM(T8-T7) -> 5 | V8: 339 | W8: =+V8-V7 -> 1 | X8: 138827 | Y8: =SUM(X8-X7) -> 20 | Z8: 90788 | AA8: =Z8-Z7 -> 27 | AB8: 246 | AC8: =AC7 -> 670 | AD8: =AC8-AC7 -> 0 | AE8: =AE7 -> 63.34 | AF8: =AE8-AE7 -> 0 | AG8: 993.36 | AH8: =AG8-AG7 -> 1.56 | AI8: =AF8+AH8 -> 1.56 | AJ8: =+Z8-Z7 -> 27 | AK8: =SUM(Y8-L8) -> 19 | AL8: =SUM(AJ8-W8) -> 26 | AM8: ='General information '!D8 -> 14 | AN8: ='General information '!H8 -> 157 | AP8: ='General information '!J8 -> 535 | AR8: =A8 -> 43833 | AS8: =AS7 -> 0.9 | AT8: 7 | AU8: 1.1 | AV8: 100 | AW8: 2.9 | AX8: 59 | AY8: =AS8*AT8 -> 6.3 | AZ8: =AU8*AV8 -> 110 | BA8: =AW8*AX8 -> 171.1 | BB8: =AY8-AY7 -> -45 | BC8: =AZ8-AZ7 -> -6.6 | BD8: =BA8-BA7 -> -31.9 | BE8: =SUM(BB8:BD8) -> -83.5 | BF8: =SUM(I8-BE8) -> 83.5 | BG8: =SUM(I8-BF8) -> -83.5
A9: =ELEC!C6 -> 43834 | B9: 108282 | C9: =B9-B8 -> 0 | D9: =C9/27 -> 0 | E9: =SUM((C9*$E$4)+(7500/'EDl log'!$A$38)) -> 241.93548 | G9: 585410 | H9: =G9-G8 -> 288 | I9: =C9+H9 -> 288 | J9: =IF(I9>0,E9/I9,0) -> 0.84005376 | K9: ='Swimming Pool quality check '!H9 -> 5794 | L9: =K9-K8 -> 3 | M9: =M8 -> 457.44 | N9: =SUM(M9-M8) -> 0 | O9: =O8 -> 529.52 | P9: =SUM(O9-O8) -> 0 | Q9: =P9+N9 -> 0 | T9: 4388 | U9: =SUM(T9-T8) -> 7 | V9: 339 | W9: =+V9-V8 -> 0 | X9: 138925 | Y9: =SUM(X9-X8) -> 98 | Z9: 90790 | AA9: =Z9-Z8 -> 2 | AB9: =AB8 -> 246 | AC9: =AC8 -> 670 | AD9: =AC9-AC8 -> 0 | AE9: 67.05 | AF9: =AE9-AE8 -> 3.71 | AG9: 1020.78 | AH9: =AG9-AG8 -> 27.42 | AI9: =AF9+AH9 -> 31.13 | AJ9: =+Z9-Z8 -> 2 | AK9: =SUM(Y9-L9) -> 95 | AL9: =SUM(AJ9-W9) -> 2 | AM9: ='General information '!D9 -> 13 | AN9: ='General information '!H9 -> 260 | AP9: ='General information '!J9 -> 650 | AR9: =A9 -> 43834 | AS9: =AS8 -> 0.9 | AT9: 79 | AU9: =AU8 -> 1.1 | AV9: 54 | AW9: 2.9 | AX9: 69 | AY9: =AS9*AT9 -> 71.1 | AZ9: =AU9*AV9 -> 59.4 | BA9: =AW9*AX9 -> 200.1 | BB9: =AY9-AY8 -> 64.8 | BC9: =AZ9-AZ8 -> -50.6 | BD9: =BA9-BA8 -> 29 | BE9: =SUM(BB9:BD9) -> 43.2 | BF9: =SUM(I9-BE9) -> 244.8 | BG9: =SUM(I9-BF9) -> 43.2
A10: =ELEC!C7 -> 43835 | B10: 108282 | C10: =B10-B9 -> 0 | D10: =C10/27 -> 0 | E10: =SUM((C10*$E$4)+(7500/'EDl log'!$A$38)) -> 241.93548 | G10: 585410 | H10: =G10-G9 -> 0 | I10: =C10+H10 -> 0 | J10: =IF(I10>0,E10/I10,0) -> 0 | K10: ='Swimming Pool quality check '!H10 -> 5796 | L10: =K10-K9 -> 2 | M10: =M9 -> 457.44 | N10: =SUM(M10-M9) -> 0 | O10: =O9 -> 529.52 | P10: =SUM(O10-O9) -> 0 | Q10: =P10+N10 -> 0 | T10: 4396 | U10: =SUM(T10-T9) -> 8 | V10: 342 | W10: =+V10-V9 -> 3 | X10: 138929 | Y10: =SUM(X10-X9) -> 4 | Z10: 90843 | AA10: =Z10-Z9 -> 53 | AB10: 246 | AC10: =AC9 -> 670 | AD10: =AC10-AC9 -> 0 | AE10: 67.54 | AF10: =AE10-AE9 -> 0.49 | AG10: 1025.94 | AH10: =AG10-AG9 -> 5.16 | AI10: =AF10+AH10 -> 5.65 | AJ10: =+Z10-Z9 -> 53 | AK10: =SUM(Y10-L10) -> 2 | AL10: =SUM(AJ10-W10) -> 50 | AM10: ='General information '!D10 -> 13 | AN10: ='General information '!H10 -> 0 | AP10: ='General information '!J10 -> 287 | AR10: =A10 -> 43835 | AS10: =AS9 -> 0.9 | AT10: 23 | AU10: =AU9 -> 1.1 | AV10: 67 | AW10: 2.9 | AX10: 60 | AY10: =AS10*AT10 -> 20.7 | AZ10: =AU10*AV10 -> 73.7 | BA10: =AW10*AX10 -> 174 | BB10: =AY10-AY9 -> -50.4 | BC10: =AZ10-AZ9 -> 14.3 | BD10: =BA10-BA9 -> -26.1 | BE10: =SUM(BB10:BD10) -> -62.2 | BF10: =SUM(I10-BE10) -> 62.2 | BG10: =SUM(I10-BF10) -> -62.2
A11: =ELEC!C8 -> 43836 | B11: 108282 | C11: =B11-B10 -> 0 | D11: =C11/27 -> 0 | E11: =SUM((C11*$E$4)+(7500/'EDl log'!$A$38)) -> 241.93548 | G11: 585589 | H11: =G11-G10 -> 179 | I11: =C11+H11 -> 179 | J11: =IF(I11>0,E11/I11,0) -> 1.3515949 | K11: ='Swimming Pool quality check '!H11 -> 5800 | L11: =K11-K10 -> 4 | M11: =M10 -> 457.44 | N11: =SUM(M11-M10) -> 0 | O11: =O10 -> 529.52 | P11: =SUM(O11-O10) -> 0 | Q11: =SUM(P11+N11) -> 0 | T11: 4400 | U11: =SUM(T11-T10) -> 4 | V11: 342 | W11: =+V11-V10 -> 0 | X11: 138983 | Y11: =SUM(X11-X10) -> 54 | Z11: 90900 | AA11: =Z11-Z10 -> 57 | AB11: =AB10 -> 246 | AC11: =AC10 -> 670 | AD11: =AC11-AC10 -> 0 | AE11: 69.8 | AF11: =AE11-AE10 -> 2.26 | AG11: 1046.25 | AH11: =AG11-AG10 -> 20.31 | AI11: =AF11+AH11 -> 22.57 | AJ11: =+Z11-Z10 -> 57 | AK11: =SUM(Y11-L11) -> 50 | AL11: =SUM(AJ11-W11) -> 57 | AM11: ='General information '!D11 -> 14 | AN11: ='General information '!H11 -> 0 | AP11: ='General information '!J11 -> 186 | AR11: =A11 -> 43836 | AS11: =AS10 -> 0.9 | AT11: 20 | AU11: =AU10 -> 1.1 | AV11: 75 | AW11: 2.9 | AX11: 63 | AY11: =AS11*AT11 -> 18 | AZ11: =AU11*AV11 -> 82.5 | BA11: =AW11*AX11 -> 182.7 | BB11: =AY11-AY10 -> -2.7 | BC11: =AZ11-AZ10 -> 8.8 | BD11: =BA11-BA10 -> 8.7 | BE11: =SUM(BB11:BD11) -> 14.8 | BF11: =SUM(I11-BE11) -> 164.2 | BG11: =SUM(I11-BF11) -> 14.8
A12: =ELEC!C9 -> 43837 | B12: 108361 | C12: =B12-B11 -> 79 | D12: =C12/27 -> 2.9259259 | E12: =SUM((C12*$E$4)+(7500/'EDl log'!$A$38)) -> 373.07548 | G12: 585589 | H12: =G12-G11 -> 0 | I12: =C12+H12 -> 79 | J12: =IF(I12>0,E12/I12,0) -> 4.7224745 | K12: ='Swimming Pool quality check '!H12 -> 5803 | L12: =K12-K11 -> 3 | M12: =M11 -> 457.44 | N12: =SUM(M12-M11) -> 0 | O12: =O11 -> 529.52 | P12: =SUM(O12-O11) -> 0 | Q12: =SUM(P12+N12) -> 0 | T12: 4405 | U12: =SUM(T12-T11) -> 5 | V12: 343 | W12: =+V12-V11 -> 1 | X12: 138983 | Y12: =SUM(X12-X11) -> 0 | Z12: 90931 | AA12: =Z12-Z11 -> 31 | AB12: =AB11 -> 246 | AC12: =AC11 -> 670 | AD12: =AC12-AC11 -> 0 | AE12: 70.28 | AF12: =AE12-AE11 -> 0.48 | AG12: 1053.3 | AH12: =AG12-AG11 -> 7.05 | AI12: =AF12+AH12 -> 7.53 | AJ12: =+Z12-Z11 -> 31 | AK12: =SUM(Y12-L12) -> -3 | AL12: =SUM(AJ12-W12) -> 30 | AM12: ='General information '!D12 -> 14 | AN12: ='General information '!H12 -> 0 | AP12: ='General information '!J12 -> 269 | AR12: =A12 -> 43837 | AS12: =AS11 -> 0.9 | AT12: 60 | AU12: =AU11 -> 1.1 | AV12: 71 | AW12: 2.9 | AX12: 52 | AY12: =AS12*AT12 -> 54 | AZ12: =AU12*AV12 -> 78.1 | BA12: =AW12*AX12 -> 150.8 | BB12: =AY12-AY11 -> 36 | BC12: =AZ12-AZ11 -> -4.4 | BD12: =BA12-BA11 -> -31.9 | BE12: =SUM(BB12:BD12) -> -0.3 | BF12: =SUM(I12-BE12) -> 79.3 | BG12: =SUM(I12-BF12) -> -0.3
A13: =ELEC!C10 -> 43838 | B13: 108361 | C13: =B13-B12 -> 0 | D13: =C13/27 -> 0 | E13: =SUM((C13*$E$4)+(7500/'EDl log'!$A$38)) -> 241.93548 | G13: 585771 | H13: =G13-G12 -> 182 | I13: =C13+H13 -> 182 | J13: =IF(I13>0,E13/I13,0) -> 1.3293158 | K13: ='Swimming Pool quality check '!H13 -> 5803 | L13: =K13-K12 -> 0 | M13: =M12 -> 457.44 | N13: =SUM(M13-M12) -> 0 | O13: =O12 -> 529.52 | P13: =SUM(O13-O12) -> 0 | Q13: =SUM(P13+N13) -> 0 | T13: 4410 | U13: =SUM(T13-T12) -> 5 | V13: =V12 -> 343 | W13: =+V13-V12 -> 0 | X13: 139051 | Y13: =SUM(X13-X12) -> 68 | Z13: 90989 | AA13: =Z13-Z12 -> 58 | AB13: =AB12 -> 246 | AC13: =AC12 -> 670 | AD13: =AC13-AC12 -> 0 | AE13: 71.52 | AF13: =AE13-AE12 -> 1.24 | AG13: 1065.07 | AH13: =AG13-AG12 -> 11.77 | AI13: =AF13+AH13 -> 13.01 | AJ13: =+Z13-Z12 -> 58 | AK13: =SUM(Y13-L13) -> 68 | AL13: =SUM(AJ13-W13) -> 58 | AM13: ='General information '!D13 -> 12.5 | AN13: ='General information '!J13 -> 0 | AP13: ='General information '!J13 -> 0 | AR13: =A13 -> 43838 | AS13: =AS12 -> 0.9 | AT13: 49 | AU13: =AU12 -> 1.1 | AV13: 84 | AW13: 2.9 | AX13: 61 | AY13: =AS13*AT13 -> 44.1 | AZ13: =AU13*AV13 -> 92.4 | BA13: =AW13*AX13 -> 176.9 | BB13: =AY13-AY12 -> -9.9 | BC13: =AZ13-AZ12 -> 14.3 | BD13: =BA13-BA12 -> 26.1 | BE13: =SUM(BB13:BD13) -> 30.5 | BF13: =SUM(I13-BE13) -> 151.5 | BG13: =SUM(I13-BF13) -> 30.5
A14: =ELEC!C11 -> 43839 | B14: 108441 | C14: =B14-B13 -> 80 | D14: =C14/27 -> 2.962963 | E14: =SUM((C14*$E$4)+(7500/'EDl log'!$A$38)) -> 374.73548 | G14: 585771 | H14: =G14-G13 -> 0 | I14: =C14+H14 -> 80 | J14: =IF(I14>0,E14/I14,0) -> 4.6841935 | K14: ='Swimming Pool quality check '!H14 -> 5805 | L14: =K14-K13 -> 2 | M14: =M13 -> 457.44 | N14: =SUM(M14-M13) -> 0 | O14: =O13 -> 529.52 | P14: =SUM(O14-O13) -> 0 | Q14: =SUM(P14+N14) -> 0 | T14: 4415 | U14: =SUM(T14-T13) -> 5 | V14: 347 | W14: =+V14-V13 -> 4 | X14: 139103 | Y14: =SUM(X14-X13) -> 52 | Z14: 90993 | AA14: =Z14-Z13 -> 4 | AB14: =AB13 -> 246 | AC14: =AC13 -> 670 | AD14: =AC14-AC13 -> 0 | AE14: 71.52 | AF14: =AE14-AE13 -> 0 | AG14: 1065.68 | AH14: =AG14-AG13 -> 0.61 | AI14: =AF14+AH14 -> 0.61 | AJ14: =+Z14-Z13 -> 4 | AK14: =SUM(Y14-L14) -> 50 | AL14: =SUM(AJ14-W14) -> 0 | AM14: ='General information '!D14 -> 12.5 | AN14: ='General information '!H14 -> 0 | AP14: ='General information '!J14 -> 258 | AR14: =A14 -> 43839 | AS14: =AS13 -> 0.9 | AT14: 48 | AU14: =AU13 -> 1.1 | AV14: 68 | AW14: 2.9 | AX14: 64 | AY14: =AS14*AT14 -> 43.2 | AZ14: =AU14*AV14 -> 74.8 | BA14: =AW14*AX14 -> 185.6 | BB14: =AY14-AY13 -> -0.9 | BC14: =AZ14-AZ13 -> -17.6 | BD14: =BA14-BA13 -> 8.7 | BE14: =SUM(BB14:BD14) -> -9.8 | BF14: =SUM(I14-BE14) -> 89.8 | BG14: =SUM(I14-BF14) -> -9.8
A15: =ELEC!C12 -> 43840 | B15: =B14 -> 108441 | C15: =B15-B14 -> 0 | D15: =C15/27 -> 0 | E15: =SUM((C15*$E$4)+(7500/'EDl log'!$A$38)) -> 241.93548 | G15: 586114 | H15: =G15-G14 -> 343 | I15: =C15+H15 -> 343 | J15: =IF(I15>0,E15/I15,0) -> 0.70535126 | K15: ='Swimming Pool quality check '!H15 -> 5805 | L15: =K15-K14 -> 0 | M15: =M14 -> 457.44 | N15: =SUM(M15-M14) -> 0 | O15: =O14 -> 529.52 | P15: =SUM(O15-O14) -> 0 | Q15: =SUM(P15+N15) -> 0 | T15: 4420 | U15: =SUM(T15-T14) -> 5 | V15: 348 | W15: =+V15-V14 -> 1 | X15: 139243 | Y15: =SUM(X15-X14) -> 140 | Z15: 91044 | AA15: =Z15-Z14 -> 51 | AB15: =AB14 -> 246 | AC15: =AC14 -> 670 | AD15: =AC15-AC14 -> 0 | AE15: 72.71 | AF15: =AE15-AE14 -> 1.19 | AG15: 1073.65 | AH15: =AG15-AG14 -> 7.97 | AI15: =AF15+AH15 -> 9.16 | AJ15: =+Z15-Z14 -> 51 | AK15: =SUM(Y15-L15) -> 140 | AL15: =SUM(AJ15-W15) -> 50 | AM15: ='General information '!D15 -> 14.5 | AN15: ='General information '!H15 -> 0 | AP15: ='General information '!J15 -> 276 | AR15: =A15 -> 43840 | AS15: =AS14 -> 0.9 | AT15: 122 | AU15: =AU14 -> 1.1 | AV15: 79 | AW15: 2.9 | AX15: 88 | AY15: =AS15*AT15 -> 109.8 | AZ15: =AU15*AV15 -> 86.9 | BA15: =AW15*AX15 -> 255.2 | BB15: =AY15-AY14 -> 66.6 | BC15: =AZ15-AZ14 -> 12.1 | BD15: =BA15-BA14 -> 69.6 | BE15: =SUM(BB15:BD15) -> 148.3 | BF15: =SUM(I15-BE15) -> 194.7 | BG15: =SUM(I15-BF15) -> 148.3
A16: =ELEC!C13 -> 43841 | B16: =B15 -> 108441 | C16: =B16-B15 -> 0 | D16: =C16/27 -> 0 | E16: =SUM((C16*$E$4)+(7500/'EDl log'!$A$38)) -> 241.93548 | G16: =G15 -> 586114 | H16: =G16-G15 -> 0 | I16: =C16+H16 -> 0 | J16: =IF(I16>0,E16/I16,0) -> 0 | K16: ='Swimming Pool quality check '!H16 -> 5813 | L16: =K16-K15 -> 8 | M16: =M15 -> 457.44 | N16: =SUM(M16-M15) -> 0 | O16: =O15 -> 529.52 | P16: =SUM(O16-O15) -> 0 | Q16: =SUM(P16+N16) -> 0 | T16: 4427 | U16: =SUM(T16-T15) -> 7 | V16: 348 | W16: =+V16-V15 -> 0 | X16: 139310 | Y16: =SUM(X16-X15) -> 67 | Z16: 91079 | AA16: =Z16-Z15 -> 35 | AB16: 244 | AC16: =AC15 -> 670 | AD16: =AC16-AC15 -> 0 | AE16: 74.26 | AF16: =AE16-AE15 -> 1.55 | AG16: 1089.47 | AH16: =AG16-AG15 -> 15.82 | AI16: =AF16+AH16 -> 17.37 | AJ16: =+Z16-Z15 -> 35 | AK16: =SUM(Y16-L16) -> 59 | AL16: =SUM(AJ16-W16) -> 35 | AM16: ='General information '!D16 -> 15 | AN16: ='General information '!H16 -> 180 | AP16: ='General information '!J16 -> 536 | AR16: =A16 -> 43841 | AS16: =AS15 -> 0.9 | AT16: 47 | AU16: =AU15 -> 1.1 | AV16: 70 | AW16: 2.9 | AX16: 92 | AY16: =AS16*AT16 -> 42.3 | AZ16: =AU16*AV16 -> 77 | BA16: =AW16*AX16 -> 266.8 | BB16: =AY16-AY15 -> -67.5 | BC16: =AZ16-AZ15 -> -9.9 | BD16: =BA16-BA15 -> 11.6 | BE16: =SUM(BB16:BD16) -> -65.8 | BF16: =SUM(I16-BE16) -> 65.8 | BG16: =SUM(I16-BF16) -> -65.8
A17: =ELEC!C14 -> 43842 | B17: 108441 | C17: =B17-B16 -> 0 | D17: =C17/27 -> 0 | E17: =SUM((C17*$E$4)+(7500/'EDl log'!$A$38)) -> 241.93548 | G17: 586851 | H17: =G17-G16 -> 737 | I17: =C17+H17 -> 737 | J17: =IF(I17>0,E17/I17,0) -> 0.32827067 | K17: ='Swimming Pool quality check '!H17 -> 5819 | L17: =K17-K16 -> 6 | M17: =M16 -> 457.44 | N17: =SUM(M17-M16) -> 0 | O17: =O16 -> 529.52 | P17: =SUM(O17-O16) -> 0 | Q17: =SUM(P17+N17) -> 0 | T17: 4434 | U17: =SUM(T17-T16) -> 7 | V17: 348 | W17: =+V17-V16 -> 0 | X17: 139411 | Y17: =SUM(X17-X16) -> 101 | Z17: 91189 | AA17: =Z17-Z16 -> 110 | AB17: =AB16 -> 244 | AC17: =AC16 -> 670 | AD17: =AC17-AC16 -> 0 | AE17: 74.26 | AF17: =AE17-AE16 -> 0 | AG17: 1090.3 | AH17: =AG17-AG16 -> 0.83 | AI17: =AF17+AH17 -> 0.83 | AJ17: =+Z17-Z16 -> 110 | AK17: =SUM(Y17-L17) -> 95 | AL17: =SUM(AJ17-W17) -> 110 | AM17: ='General information '!D17 -> 14 | AN17: ='General information '!H17 -> 0 | AP17: ='General information '!J17 -> 233 | AR17: =A17 -> 43842 | AS17: =AS16 -> 0.9 | AT17: 36 | AU17: =AU16 -> 1.1 | AV17: 120 | AW17: 2.9 | AX17: 109 | AY17: =AS17*AT17 -> 32.4 | AZ17: =AU17*AV17 -> 132 | BA17: =AW17*AX17 -> 316.1 | BB17: =AY17-AY16 -> -9.9 | BC17: =AZ17-AZ16 -> 55 | BD17: =BA17-BA16 -> 49.3 | BE17: =SUM(BB17:BD17) -> 94.4 | BF17: =SUM(I17-BE17) -> 642.6 | BG17: =SUM(I17-BF17) -> 94.4
A18: =ELEC!C15 -> 43843 | B18: 108441 | C18: =B18-B17 -> 0 | D18: =C18/27 -> 0 | E18: =SUM((C18*$E$4)+(7500/'EDl log'!$A$38)) -> 241.93548 | G18: 586851 | H18: =G18-G17 -> 0 | I18: =C18+H18 -> 0 | J18: =IF(I18>0,E18/I18,0) -> 0 | K18: ='Swimming Pool quality check '!H18 -> 5822 | L18: =K18-K17 -> 3 | M18: =M17 -> 457.44 | N18: =SUM(M18-M17) -> 0 | O18: =O17 -> 529.52 | P18: =SUM(O18-O17) -> 0 | Q18: =SUM(P18+N18) -> 0 | T18: 4443 | U18: =SUM(T18-T17) -> 9 | V18: 348 | W18: =+V18-V17 -> 0 | X18: 139486 | Y18: =SUM(X18-X17) -> 75 | Z18: 91189 | AA18: =Z18-Z17 -> 0 | AB18: 244 | AC18: =AC17 -> 670 | AD18: =AC18-AC17 -> 0 | AE18: 74.26 | AF18: =AE18-AE17 -> 0 | AG18: 1090.83 | AH18: =AG18-AG17 -> 0.53 | AI18: =AF18+AH18 -> 0.53 | AJ18: =+Z18-Z17 -> 0 | AK18: =SUM(Y18-L18) -> 72 | AL18: =SUM(AJ18-W18) -> 0 | AM18: ='General information '!D18 -> 15 | AN18: ='General information '!H18 -> 0 | AP18: ='General information '!J18 -> 540 | AR18: =A18 -> 43843 | AS18: =AS17 -> 0.9 | AT18: 73 | AU18: =AU17 -> 1.1 | AV18: 107 | AW18: 2.9 | AX18: 115 | AY18: =AS18*AT18 -> 65.7 | AZ18: =AU18*AV18 -> 117.7 | BA18: =AW18*AX18 -> 333.5 | BB18: =AY18-AY17 -> 33.3 | BC18: =AZ18-AZ17 -> -14.3 | BD18: =BA18-BA17 -> 17.4 | BE18: =SUM(BB18:BD18) -> 36.4 | BF18: =SUM(I18-BE18) -> -36.4 | BG18: =SUM(I18-BF18) -> 36.4
A19: =ELEC!C16 -> 43844 | B19: 108441 | C19: =B19-B18 -> 0 | D19: =C19/27 -> 0 | E19: =SUM((C19*$E$4)+(7500/'EDl log'!$A$38)) -> 241.93548 | G19: 586940 | H19: =G19-G18 -> 89 | I19: =C19+H19 -> 89 | J19: =IF(I19>0,E19/I19,0) -> 2.7183762 | K19: ='Swimming Pool quality check '!H19 -> 5826 | L19: =K19-K18 -> 4 | M19: =M18 -> 457.44 | N19: =SUM(M19-M18) -> 0 | O19: =O18 -> 529.52 | P19: =SUM(O19-O18) -> 0 | Q19: =SUM(P19+N19) -> 0 | T19: 4446 | U19: =SUM(T19-T18) -> 3 | V19: 349 | W19: =+V19-V18 -> 1 | X19: 139576 | Y19: =SUM(X19-X18) -> 90 | Z19: 91246 | AA19: =Z19-Z18 -> 57 | AB19: =AB18 -> 244 | AC19: =AC18 -> 670 | AD19: =AC19-AC18 -> 0 | AE19: 74.28 | AF19: =AE19-AE18 -> 0.02 | AG19: 1091.76 | AH19: =AG19-AG18 -> 0.93 | AI19: =AF19+AH19 -> 0.95 | AJ19: =+Z19-Z18 -> 57 | AK19: =SUM(Y19-L19) -> 86 | AL19: =SUM(AJ19-W19) -> 56 | AM19: ='General information '!D19 -> 14 | AN19: ='General information '!H19 -> 0 | AP19: ='General information '!J19 -> 184 | AR19: =A19 -> 43844 | AS19: =AS18 -> 0.9 | AT19: 133 | AU19: =AU18 -> 1.1 | AV19: 59 | AW19: 2.9 | AX19: 131 | AY19: =AS19*AT19 -> 119.7 | AZ19: =AU19*AV19 -> 64.9 | BA19: =AW19*AX19 -> 379.9 | BB19: =AY19-AY18 -> 54 | BC19: =AZ19-AZ18 -> -52.8 | BD19: =BA19-BA18 -> 46.4 | BE19: =SUM(BB19:BD19) -> 47.6 | BF19: =SUM(I19-BE19) -> 41.4 | BG19: =SUM(I19-BF19) -> 47.6
A20: =ELEC!C17 -> 43845 | B20: 108441 | C20: =B20-B19 -> 0 | D20: =C20/27 -> 0 | E20: =SUM((C20*$E$4)+(7500/'EDl log'!$A$38)) -> 241.93548 | G20: 586940 | H20: =G20-G19 -> 0 | I20: =C20+H20 -> 0 | J20: =IF(I20>0,E20/I20,0) -> 0 | K20: ='Swimming Pool quality check '!H20 -> 5832 | L20: =K20-K19 -> 6 | M20: =M19 -> 457.44 | N20: =SUM(M20-M19) -> 0 | O20: =O19 -> 529.52 | P20: =SUM(O20-O19) -> 0 | Q20: =SUM(P20+N20) -> 0 | T20: 4450 | U20: =SUM(T20-T19) -> 4 | V20: 350 | W20: =+V20-V19 -> 1 | X20: 139578 | Y20: =SUM(X20-X19) -> 2 | Z20: 91246 | AA20: =Z20-Z19 -> 0 | AB20: =AB19 -> 244 | AC20: =AC19 -> 670 | AD20: =AC20-AC19 -> 0 | AE20: 78.03 | AF20: =AE20-AE19 -> 3.75 | AG20: 1117.74 | AH20: =AG20-AG19 -> 25.98 | AI20: =AF20+AH20 -> 29.73 | AJ20: =+Z20-Z19 -> 0 | AK20: =SUM(Y20-L20) -> -4 | AL20: =SUM(AJ20-W20) -> -1 | AM20: ='General information '!D20 -> 15 | AN20: ='General information '!H20 -> 0 | AP20: ='General information '!J20 -> 345 | AR20: =A20 -> 43845 | AS20: =AS19 -> 0.9 | AT20: 62 | AU20: =AU19 -> 1.1 | AV20: 95 | AW20: 2.9 | AX20: 117 | AY20: =AS20*AT20 -> 55.8 | AZ20: =AU20*AV20 -> 104.5 | BA20: =AW20*AX20 -> 339.3 | BB20: =AY20-AY19 -> -63.9 | BC20: =AZ20-AZ19 -> 39.6 | BD20: =BA20-BA19 -> -40.6 | BE20: =SUM(BB20:BD20) -> -64.9 | BF20: =SUM(I20-BE20) -> 64.9 | BG20: =SUM(I20-BF20) -> -64.9
A21: =ELEC!C18 -> 43846 | B21: =B20 -> 108441 | C21: =B21-B20 -> 0 | D21: =C21/27 -> 0 | E21: =SUM((C21*$E$4)+(7500/'EDl log'!$A$38)) -> 241.93548 | G21: 587283 | H21: =G21-G20 -> 343 | I21: =C21+H21 -> 343 | J21: =IF(I21>0,E21/I21,0) -> 0.70535126 | K21: ='Swimming Pool quality check '!H21 -> 5834 | L21: =K21-K20 -> 2 | M21: =M20 -> 457.44 | N21: =SUM(M21-M20) -> 0 | O21: =O20 -> 529.52 | P21: =SUM(O21-O20) -> 0 | Q21: =SUM(P21+N21) -> 0 | T21: 4456 | U21: =SUM(T21-T20) -> 6 | V21: =V20 -> 350 | W21: =+V21-V20 -> 0 | X21: 139647 | Y21: =SUM(X21-X20) -> 69 | Z21: 91335 | AA21: =Z21-Z20 -> 89 | AB21: =AB20 -> 244 | AC21: =AC20 -> 670 | AD21: =AC21-AC20 -> 0 | AE21: =AE20 -> 78.03 | AF21: =AE21-AE20 -> 0 | AG21: 1122.72 | AH21: =AG21-AG20 -> 4.98 | AI21: =AF21+AH21 -> 4.98 | AJ21: =+Z21-Z20 -> 89 | AK21: =SUM(Y21-L21) -> 67 | AL21: =SUM(AJ21-W21) -> 89 | AM21: ='General information '!D21 -> 16 | AN21: ='General information '!H21 -> 107 | AP21: ='General information '!J21 -> 331 | AR21: =A21 -> 43846 | AS21: =AS20 -> 0.9 | AT21: 118 | AU21: =AU20 -> 1.1 | AV21: 140 | AW21: 2.9 | AX21: 125 | AY21: =AS21*AT21 -> 106.2 | AZ21: =AU21*AV21 -> 154 | BA21: =AW21*AX21 -> 362.5 | BB21: =AY21-AY20 -> 50.4 | BC21: =AZ21-AZ20 -> 49.5 | BD21: =BA21-BA20 -> 23.2 | BE21: =SUM(BB21:BD21) -> 123.1 | BF21: =SUM(I21-BE21) -> 219.9 | BG21: =SUM(I21-BF21) -> 123.1
A22: =ELEC!C19 -> 43847 | B22: =B21 -> 108441 | C22: =B22-B21 -> 0 | D22: =C22/27 -> 0 | E22: =SUM((C22*$E$4)+(7500/'EDl log'!$A$38)) -> 241.93548 | G22: =G21 -> 587283 | H22: =G22-G21 -> 0 | I22: =C22+H22 -> 0 | J22: =IF(I22>0,E22/I22,0) -> 0 | K22: ='Swimming Pool quality check '!H22 -> 5834 | L22: =K22-K21 -> 0 | M22: =M21 -> 457.44 | N22: =SUM(M22-M21) -> 0 | O22: =O21 -> 529.52 | P22: =SUM(O22-O21) -> 0 | Q22: =SUM(P22+N22) -> 0 | T22: 4460 | U22: =SUM(T22-T21) -> 4 | V22: 353 | W22: =+V22-V21 -> 3 | X22: 139647 | Y22: =SUM(X22-X21) -> 0 | Z22: =Z21 -> 91335 | AA22: =Z22-Z21 -> 0 | AB22: =AB21 -> 244 | AC22: =AC21 -> 670 | AD22: =AC22-AC21 -> 0 | AE22: 81.78 | AF22: =AE22-AE21 -> 3.75 | AG22: 1126.61 | AH22: =AG22-AG21 -> 3.89 | AI22: =AF22+AH22 -> 7.64 | AJ22: =+Z22-Z21 -> 0 | AK22: =SUM(Y22-L22) -> 0 | AL22: =SUM(AJ22-W22) -> -3 | AM22: ='General information '!D22 -> 16.5 | AN22: ='General information '!H22 -> 100 | AP22: ='General information '!J22 -> 340 | AR22: =A22 -> 43847 | AS22: =AS21 -> 0.9 | AT22: 127 | AU22: =AU21 -> 1.1 | AV22: 120 | AW22: 2.9 | AX22: 113 | AY22: =AS22*AT22 -> 114.3 | AZ22: =AU22*AV22 -> 132 | BA22: =AW22*AX22 -> 327.7 | BB22: =AY22-AY21 -> 8.1 | BC22: =AZ22-AZ21 -> -22 | BD22: =BA22-BA21 -> -34.8 | BE22: =SUM(BB22:BD22) -> -48.7 | BF22: =SUM(I22-BE22) -> 48.7 | BG22: =SUM(I22-BF22) -> -48.7
A23: =ELEC!C20 -> 43848 | B23: =B22 -> 108441 | C23: =B23-B22 -> 0 | D23: =C23/27 -> 0 | E23: =SUM((C23*$E$4)+(7500/'EDl log'!$A$38)) -> 241.93548 | G23: =G22 -> 587283 | H23: =G23-G22 -> 0 | I23: =C23+H23 -> 0 | J23: =IF(I23>0,E23/I23,0) -> 0 | K23: ='Swimming Pool quality check '!H23 -> 5834 | L23: =K23-K22 -> 0 | M23: =M22 -> 457.44 | N23: =SUM(M23-M22) -> 0 | O23: =O22 -> 529.52 | P23: =SUM(O23-O22) -> 0 | Q23: =SUM(P23+N23) -> 0 | T23: =T22 -> 4460 | U23: =SUM(T23-T22) -> 0 | V23: =V22 -> 353 | W23: =+V23-V22 -> 0 | X23: =X22 -> 139647 | Y23: =SUM(X23-X22) -> 0 | Z23: =Z22 -> 91335 | AA23: =Z23-Z22 -> 0 | AB23: =AB22 -> 244 | AC23: =AC22 -> 670 | AD23: =AC23-AC22 -> 0 | AE23: =AE22 -> 81.78 | AF23: =AE23-AE22 -> 0 | AG23: =AG22 -> 1126.61 | AH23: =AG23-AG22 -> 0 | AI23: =AF23+AH23 -> 0 | AJ23: =+Z23-Z22 -> 0 | AK23: =SUM(Y23-L23) -> 0 | AL23: =SUM(AJ23-W23) -> 0 | AM23: ='General information '!D23 -> 0 | AN23: ='General information '!H23 -> 0 | AP23: ='General information '!J23 -> 0 | AR23: =A23 -> 43848 | AS23: =AS22 -> 0.9 | AT23: =AT22 -> 127 | AU23: =AU22 -> 1.1 | AV23: =AV22 -> 120 | AW23: 2.9 | AX23: =AX22 -> 113 | AY23: =AS23*AT23 -> 114.3 | AZ23: =AU23*AV23 -> 132 | BA23: =AW23*AX23 -> 327.7 | BB23: =AY23-AY22 -> 0 | BC23: =AZ23-AZ22 -> 0 | BD23: =BA23-BA22 -> 0 | BE23: =SUM(BB23:BD23) -> 0 | BF23: =SUM(I23-BE23) -> 0 | BG23: =SUM(I23-BF23) -> 0
A24: =ELEC!C21 -> 43849 | B24: =B23 -> 108441 | C24: =B24-B23 -> 0 | D24: =C24/27 -> 0 | E24: =SUM((C24*$E$4)+(7500/'EDl log'!$A$38)) -> 241.93548 | G24: =G23 -> 587283 | H24: =G24-G23 -> 0 | I24: =C24+H24 -> 0 | J24: =IF(I24>0,E24/I24,0) -> 0 | K24: ='Swimming Pool quality check '!H24 -> 5834 | L24: =K24-K23 -> 0 | M24: =M23 -> 457.44 | N24: =SUM(M24-M23) -> 0 | O24: =O23 -> 529.52 | P24: =SUM(O24-O23) -> 0 | Q24: =SUM(P24+N24) -> 0 | T24: =T23 -> 4460 | U24: =SUM(T24-T23) -> 0 | V24: =V23 -> 353 | W24: =+V24-V23 -> 0 | X24: =X23 -> 139647 | Y24: =SUM(X24-X23) -> 0 | Z24: =Z23 -> 91335 | AA24: =Z24-Z23 -> 0 | AB24: =AB23 -> 244 | AC24: =AC23 -> 670 | AD24: =AC24-AC23 -> 0 | AE24: =AE23 -> 81.78 | AF24: =AE24-AE23 -> 0 | AG24: =AG23 -> 1126.61 | AH24: =AG24-AG23 -> 0 | AI24: =AF24+AH24 -> 0 | AJ24: =+Z24-Z23 -> 0 | AK24: =SUM(Y24-L24) -> 0 | AL24: =SUM(AJ24-W24) -> 0 | AM24: ='General information '!D24 -> 0 | AN24: ='General information '!H24 -> 0 | AP24: ='General information '!J24 -> 0 | AR24: =A24 -> 43849 | AS24: =AS23 -> 0.9 | AT24: =AT23 -> 127 | AU24: =AU23 -> 1.1 | AV24: =AV23 -> 120 | AW24: 2.9 | AX24: =AX23 -> 113 | AY24: =AS24*AT24 -> 114.3 | AZ24: =AU24*AV24 -> 132 | BA24: =AW24*AX24 -> 327.7 | BB24: =AY24-AY23 -> 0 | BC24: =AZ24-AZ23 -> 0 | BD24: =BA24-BA23 -> 0 | BE24: =SUM(BB24:BD24) -> 0 | BF24: =SUM(I24-BE24) -> 0 | BG24: =SUM(I24-BF24) -> 0
A25: =ELEC!C22 -> 43850 | B25: =B24 -> 108441 | C25: =B25-B24 -> 0 | D25: =C25/27 -> 0 | E25: =SUM((C25*$E$4)+(7500/'EDl log'!$A$38)) -> 241.93548 | G25: =G24 -> 587283 | H25: =G25-G24 -> 0 | I25: =C25+H25 -> 0 | J25: =IF(I25>0,E25/I25,0) -> 0 | K25: ='Swimming Pool quality check '!H25 -> 5834 | L25: =K25-K24 -> 0 | M25: =M24 -> 457.44 | N25: =SUM(M25-M24) -> 0 | O25: =O24 -> 529.52 | P25: =SUM(O25-O24) -> 0 | Q25: =SUM(P25+N25) -> 0 | T25: =T24 -> 4460 | U25: =SUM(T25-T24) -> 0 | V25: =V24 -> 353 | W25: =+V25-V24 -> 0 | X25: =X24 -> 139647 | Y25: =SUM(X25-X24) -> 0 | Z25: =Z24 -> 91335 | AA25: =Z25-Z24 -> 0 | AB25: =AB24 -> 244 | AC25: =AC24 -> 670 | AD25: =AC25-AC24 -> 0 | AE25: =AE24 -> 81.78 | AF25: =AE25-AE24 -> 0 | AG25: =AG24 -> 1126.61 | AH25: =AG25-AG24 -> 0 | AI25: =AF25+AH25 -> 0 | AJ25: =+Z25-Z24 -> 0 | AK25: =SUM(Y25-L25) -> 0 | AL25: =SUM(AJ25-W25) -> 0 | AM25: ='General information '!D25 -> 0 | AN25: ='General information '!H25 -> 0 | AP25: ='General information '!J25 -> 0 | AR25: =A25 -> 43850 | AS25: =AS24 -> 0.9 | AT25: =AT24 -> 127 | AU25: =AU24 -> 1.1 | AV25: =AV24 -> 120 | AW25: 2.9 | AX25: =AX24 -> 113 | AY25: =AS25*AT25 -> 114.3 | AZ25: =AU25*AV25 -> 132 | BA25: =AW25*AX25 -> 327.7 | BB25: =AY25-AY24 -> 0 | BC25: =AZ25-AZ24 -> 0 | BD25: =BA25-BA24 -> 0 | BE25: =SUM(BB25:BD25) -> 0 | BF25: =SUM(I25-BE25) -> 0 | BG25: =SUM(I25-BF25) -> 0
A26: =ELEC!C23 -> 43851 | B26: =B25 -> 108441 | C26: =B26-B25 -> 0 | D26: =C26/27 -> 0 | E26: =SUM((C26*$E$4)+(7500/'EDl log'!$A$38)) -> 241.93548 | G26: =G25 -> 587283 | H26: =G26-G25 -> 0 | I26: =C26+H26 -> 0 | J26: =IF(I26>0,E26/I26,0) -> 0 | K26: ='Swimming Pool quality check '!H26 -> 5834 | L26: =K26-K25 -> 0 | M26: =M25 -> 457.44 | N26: =SUM(M26-M25) -> 0 | O26: =O25 -> 529.52 | P26: =SUM(O26-O25) -> 0 | Q26: =SUM(P26+N26) -> 0 | T26: =T25 -> 4460 | U26: =SUM(T26-T25) -> 0 | V26: =V25 -> 353 | W26: =+V26-V25 -> 0 | X26: =X25 -> 139647 | Y26: =SUM(X26-X25) -> 0 | Z26: =Z25 -> 91335 | AA26: =Z26-Z25 -> 0 | AB26: =AB25 -> 244 | AC26: =AC25 -> 670 | AD26: =AC26-AC25 -> 0 | AE26: =AE25 -> 81.78 | AF26: =AE26-AE25 -> 0 | AG26: =AG25 -> 1126.61 | AH26: =AG26-AG25 -> 0 | AI26: =AF26+AH26 -> 0 | AJ26: =+Z26-Z25 -> 0 | AK26: =SUM(Y26-L26) -> 0 | AL26: =SUM(AJ26-W26) -> 0 | AM26: ='General information '!D26 -> 0 | AN26: ='General information '!H26 -> 0 | AP26: ='General information '!J26 -> 0 | AR26: =A26 -> 43851 | AS26: =AS25 -> 0.9 | AT26: =AT25 -> 127 | AU26: =AU25 -> 1.1 | AV26: =AV25 -> 120 | AW26: 2.9 | AX26: =AX25 -> 113 | AY26: =AS26*AT26 -> 114.3 | AZ26: =AU26*AV26 -> 132 | BA26: =AW26*AX26 -> 327.7 | BB26: =AY26-AY25 -> 0 | BC26: =AZ26-AZ25 -> 0 | BD26: =BA26-BA25 -> 0 | BE26: =SUM(BB26:BD26) -> 0 | BF26: =SUM(I26-BE26) -> 0 | BG26: =SUM(I26-BF26) -> 0
A27: =ELEC!C24 -> 43852 | B27: =B26 -> 108441 | C27: =B27-B26 -> 0 | D27: =C27/27 -> 0 | E27: =SUM((C27*$E$4)+(7500/'EDl log'!$A$38)) -> 241.93548 | G27: =G26 -> 587283 | H27: =G27-G26 -> 0 | I27: =C27+H27 -> 0 | J27: =IF(I27>0,E27/I27,0) -> 0 | K27: ='Swimming Pool quality check '!H27 -> 5834 | L27: =K27-K26 -> 0 | M27: =M26 -> 457.44 | N27: =SUM(M27-M26) -> 0 | O27: =O26 -> 529.52 | P27: =SUM(O27-O26) -> 0 | Q27: =SUM(P27+N27) -> 0 | T27: =T26 -> 4460 | U27: =SUM(T27-T26) -> 0 | V27: =V26 -> 353 | W27: =+V27-V26 -> 0 | X27: =X26 -> 139647 | Y27: =SUM(X27-X26) -> 0 | Z27: =Z26 -> 91335 | AA27: =Z27-Z26 -> 0 | AB27: =AB26 -> 244 | AC27: =AC26 -> 670 | AD27: =AC27-AC26 -> 0 | AE27: =AE26 -> 81.78 | AF27: =AE27-AE26 -> 0 | AG27: =AG26 -> 1126.61 | AH27: =AG27-AG26 -> 0 | AI27: =AF27+AH27 -> 0 | AJ27: =+Z27-Z26 -> 0 | AK27: =SUM(Y27-L27) -> 0 | AL27: =SUM(AJ27-W27) -> 0 | AM27: ='General information '!D27 -> 0 | AN27: ='General information '!H27 -> 0 | AP27: ='General information '!J27 -> 0 | AR27: =A27 -> 43852 | AS27: =AS26 -> 0.9 | AT27: =AT26 -> 127 | AU27: =AU26 -> 1.1 | AV27: =AV26 -> 120 | AW27: 2.9 | AX27: =AX26 -> 113 | AY27: =AS27*AT27 -> 114.3 | AZ27: =AU27*AV27 -> 132 | BA27: =AW27*AX27 -> 327.7 | BB27: =AY27-AY26 -> 0 | BC27: =AZ27-AZ26 -> 0 | BD27: =BA27-BA26 -> 0 | BE27: =SUM(BB27:BD27) -> 0 | BF27: =SUM(I27-BE27) -> 0 | BG27: =SUM(I27-BF27) -> 0
A28: =ELEC!C25 -> 43853 | B28: =B27 -> 108441 | C28: =B28-B27 -> 0 | D28: =C28/27 -> 0 | E28: =SUM((C28*$E$4)+(7500/'EDl log'!$A$38)) -> 241.93548 | G28: =G27 -> 587283 | H28: =G28-G27 -> 0 | I28: =C28+H28 -> 0 | J28: =IF(I28>0,E28/I28,0) -> 0 | K28: ='Swimming Pool quality check '!H28 -> 5834 | L28: =K28-K27 -> 0 | M28: =M27 -> 457.44 | N28: =SUM(M28-M27) -> 0 | O28: =O27 -> 529.52 | P28: =SUM(O28-O27) -> 0 | Q28: =SUM(P28+N28) -> 0 | T28: =T27 -> 4460 | U28: =SUM(T28-T27) -> 0 | V28: =V27 -> 353 | W28: =+V28-V27 -> 0 | X28: =X27 -> 139647 | Y28: =SUM(X28-X27) -> 0 | Z28: =Z27 -> 91335 | AA28: =Z28-Z27 -> 0 | AB28: =AB27 -> 244 | AC28: =AC27 -> 670 | AD28: =AC28-AC27 -> 0 | AE28: =AE27 -> 81.78 | AF28: =AE28-AE27 -> 0 | AG28: =AG27 -> 1126.61 | AH28: =AG28-AG27 -> 0 | AI28: =AF28+AH28 -> 0 | AJ28: =+Z28-Z27 -> 0 | AK28: =SUM(Y28-L28) -> 0 | AL28: =SUM(AJ28-W28) -> 0 | AM28: ='General information '!D28 -> 0 | AN28: ='General information '!H28 -> 0 | AP28: ='General information '!J28 -> 0 | AR28: =A28 -> 43853 | AS28: =AS27 -> 0.9 | AT28: =AT27 -> 127 | AU28: =AU27 -> 1.1 | AV28: =AV27 -> 120 | AW28: 2.9 | AX28: =AX27 -> 113 | AY28: =AS28*AT28 -> 114.3 | AZ28: =AU28*AV28 -> 132 | BA28: =AW28*AX28 -> 327.7 | BB28: =AY28-AY27 -> 0 | BC28: =AZ28-AZ27 -> 0 | BD28: =BA28-BA27 -> 0 | BE28: =SUM(BB28:BD28) -> 0 | BF28: =SUM(I28-BE28) -> 0 | BG28: =SUM(I28-BF28) -> 0
A29: =ELEC!C26 -> 43854 | B29: =B28 -> 108441 | C29: =B29-B28 -> 0 | D29: =C29/27 -> 0 | E29: =SUM((C29*$E$4)+(7500/'EDl log'!$A$38)) -> 241.93548 | G29: =G28 -> 587283 | H29: =G29-G28 -> 0 | I29: =C29+H29 -> 0 | J29: =IF(I29>0,E29/I29,0) -> 0 | K29: ='Swimming Pool quality check '!H29 -> 5834 | L29: =K29-K28 -> 0 | M29: =M28 -> 457.44 | N29: =SUM(M29-M28) -> 0 | O29: =O28 -> 529.52 | P29: =SUM(O29-O28) -> 0 | Q29: =SUM(P29+N29) -> 0 | T29: =T28 -> 4460 | U29: =SUM(T29-T28) -> 0 | V29: =V28 -> 353 | W29: =+V29-V28 -> 0 | X29: =X28 -> 139647 | Y29: =SUM(X29-X28) -> 0 | Z29: =Z28 -> 91335 | AA29: =Z29-Z28 -> 0 | AB29: =AB28 -> 244 | AC29: =AC28 -> 670 | AD29: =AC29-AC28 -> 0 | AE29: =AE28 -> 81.78 | AF29: =AE29-AE28 -> 0 | AG29: =AG28 -> 1126.61 | AH29: =AG29-AG28 -> 0 | AI29: =AF29+AH29 -> 0 | AJ29: =+Z29-Z28 -> 0 | AK29: =SUM(Y29-L29) -> 0 | AL29: =SUM(AJ29-W29) -> 0 | AM29: ='General information '!D29 -> 0 | AN29: ='General information '!H29 -> 0 | AP29: ='General information '!J29 -> 0 | AR29: =A29 -> 43854 | AS29: =AS28 -> 0.9 | AT29: =AT28 -> 127 | AU29: =AU28 -> 1.1 | AV29: =AV28 -> 120 | AW29: 2.9 | AX29: =AX28 -> 113 | AY29: =AS29*AT29 -> 114.3 | AZ29: =AU29*AV29 -> 132 | BA29: =AW29*AX29 -> 327.7 | BB29: =AY29-AY28 -> 0 | BC29: =AZ29-AZ28 -> 0 | BD29: =BA29-BA28 -> 0 | BE29: =SUM(BB29:BD29) -> 0 | BF29: =SUM(I29-BE29) -> 0 | BG29: =SUM(I29-BF29) -> 0
A30: =ELEC!C27 -> 43855 | B30: =B29 -> 108441 | C30: =B30-B29 -> 0 | D30: =C30/27 -> 0 | E30: =SUM((C30*$E$4)+(7500/'EDl log'!$A$38)) -> 241.93548 | G30: =G29 -> 587283 | H30: =G30-G29 -> 0 | I30: =C30+H30 -> 0 | J30: =IF(I30>0,E30/I30,0) -> 0 | K30: ='Swimming Pool quality check '!H30 -> 5834 | L30: =K30-K29 -> 0 | M30: =M29 -> 457.44 | N30: =SUM(M30-M29) -> 0 | O30: =O29 -> 529.52 | P30: =SUM(O30-O29) -> 0 | Q30: =SUM(P30+N30) -> 0 | T30: =T29 -> 4460 | U30: =SUM(T30-T29) -> 0 | V30: =V29 -> 353 | W30: =+V30-V29 -> 0 | X30: =X29 -> 139647 | Y30: =SUM(X30-X29) -> 0 | Z30: =Z29 -> 91335 | AA30: =Z30-Z29 -> 0 | AB30: =AB29 -> 244 | AC30: =AC29 -> 670 | AD30: =AC30-AC29 -> 0 | AE30: =AE29 -> 81.78 | AF30: =AE30-AE29 -> 0 | AG30: =AG29 -> 1126.61 | AH30: =AG30-AG29 -> 0 | AI30: =AF30+AH30 -> 0 | AJ30: =+Z30-Z29 -> 0 | AK30: =SUM(Y30-L30) -> 0 | AL30: =SUM(AJ30-W30) -> 0 | AM30: ='General information '!D30 -> 0 | AN30: ='General information '!H30 -> 0 | AP30: ='General information '!J30 -> 0 | AR30: =A30 -> 43855 | AS30: =AS29 -> 0.9 | AT30: =AT29 -> 127 | AU30: =AU29 -> 1.1 | AV30: =AV29 -> 120 | AW30: 2.9 | AX30: =AX29 -> 113 | AY30: =AS30*AT30 -> 114.3 | AZ30: =AU30*AV30 -> 132 | BA30: =AW30*AX30 -> 327.7 | BB30: =AY30-AY29 -> 0 | BC30: =AZ30-AZ29 -> 0 | BD30: =BA30-BA29 -> 0 | BE30: =SUM(BB30:BD30) -> 0 | BF30: =SUM(I30-BE30) -> 0 | BG30: =SUM(I30-BF30) -> 0
A31: =ELEC!C28 -> 43856 | B31: =B30 -> 108441 | C31: =B31-B30 -> 0 | D31: =C31/27 -> 0 | E31: =SUM((C31*$E$4)+(7500/'EDl log'!$A$38)) -> 241.93548 | G31: =G30 -> 587283 | H31: =G31-G30 -> 0 | I31: =C31+H31 -> 0 | J31: =IF(I31>0,E31/I31,0) -> 0 | K31: ='Swimming Pool quality check '!H31 -> 5834 | L31: =K31-K30 -> 0 | M31: =M30 -> 457.44 | N31: =SUM(M31-M30) -> 0 | O31: =O30 -> 529.52 | P31: =SUM(O31-O30) -> 0 | Q31: =SUM(P31+N31) -> 0 | T31: =T30 -> 4460 | U31: =SUM(T31-T30) -> 0 | V31: =V30 -> 353 | W31: =+V31-V30 -> 0 | X31: =X30 -> 139647 | Y31: =SUM(X31-X30) -> 0 | Z31: =Z30 -> 91335 | AA31: =Z31-Z30 -> 0 | AB31: =AB30 -> 244 | AC31: =AC30 -> 670 | AD31: =AC31-AC30 -> 0 | AE31: =AE30 -> 81.78 | AF31: =AE31-AE30 -> 0 | AG31: =AG30 -> 1126.61 | AH31: =AG31-AG30 -> 0 | AI31: =AF31+AH31 -> 0 | AJ31: =+Z31-Z30 -> 0 | AK31: =SUM(Y31-L31) -> 0 | AL31: =SUM(AJ31-W31) -> 0 | AM31: ='General information '!D31 -> 0 | AN31: ='General information '!H31 -> 0 | AP31: ='General information '!J31 -> 0 | AR31: =A31 -> 43856 | AS31: =AS30 -> 0.9 | AT31: =AT30 -> 127 | AU31: =AU30 -> 1.1 | AV31: =AV30 -> 120 | AW31: 2.9 | AX31: =AX30 -> 113 | AY31: =AS31*AT31 -> 114.3 | AZ31: =AU31*AV31 -> 132 | BA31: =AW31*AX31 -> 327.7 | BB31: =AY31-AY30 -> 0 | BC31: =AZ31-AZ30 -> 0 | BD31: =BA31-BA30 -> 0 | BE31: =SUM(BB31:BD31) -> 0 | BF31: =SUM(I31-BE31) -> 0 | BG31: =SUM(I31-BF31) -> 0
A32: =ELEC!C29 -> 43857 | B32: =B31 -> 108441 | C32: =B32-B31 -> 0 | D32: =C32/27 -> 0 | E32: =SUM((C32*$E$4)+(7500/'EDl log'!$A$38)) -> 241.93548 | G32: =G31 -> 587283 | H32: =G32-G31 -> 0 | I32: =C32+H32 -> 0 | J32: =IF(I32>0,E32/I32,0) -> 0 | K32: ='Swimming Pool quality check '!H32 -> 5834 | L32: =K32-K31 -> 0 | M32: =M31 -> 457.44 | N32: =SUM(M32-M31) -> 0 | O32: =O31 -> 529.52 | P32: =SUM(O32-O31) -> 0 | Q32: =SUM(P32+N32) -> 0 | T32: =T31 -> 4460 | U32: =SUM(T32-T31) -> 0 | V32: =V31 -> 353 | W32: =+V32-V31 -> 0 | X32: =X31 -> 139647 | Y32: =SUM(X32-X31) -> 0 | Z32: =Z31 -> 91335 | AA32: =Z32-Z31 -> 0 | AB32: =AB31 -> 244 | AC32: =AC31 -> 670 | AD32: =AC32-AC31 -> 0 | AE32: =AE31 -> 81.78 | AF32: =AE32-AE31 -> 0 | AG32: =AG31 -> 1126.61 | AH32: =AG32-AG31 -> 0 | AI32: =AF32+AH32 -> 0 | AJ32: =+Z32-Z31 -> 0 | AK32: =SUM(Y32-L32) -> 0 | AL32: =SUM(AJ32-W32) -> 0 | AM32: ='General information '!D32 -> 0 | AN32: ='General information '!H32 -> 0 | AP32: ='General information '!J32 -> 0 | AR32: =A32 -> 43857 | AS32: =AS31 -> 0.9 | AT32: =AT31 -> 127 | AU32: =AU31 -> 1.1 | AV32: =AV31 -> 120 | AW32: 2.9 | AX32: =AX31 -> 113 | AY32: =AS32*AT32 -> 114.3 | AZ32: =AU32*AV32 -> 132 | BA32: =AW32*AX32 -> 327.7 | BB32: =AY32-AY31 -> 0 | BC32: =AZ32-AZ31 -> 0 | BD32: =BA32-BA31 -> 0 | BE32: =SUM(BB32:BD32) -> 0 | BF32: =SUM(I32-BE32) -> 0 | BG32: =SUM(I32-BF32) -> 0
A33: =ELEC!C30 -> 43858 | B33: =B32 -> 108441 | C33: =B33-B32 -> 0 | D33: =C33/27 -> 0 | E33: =SUM((C33*$E$4)+(7500/'EDl log'!$A$38)) -> 241.93548 | G33: =G32 -> 587283 | H33: =G33-G32 -> 0 | I33: =C33+H33 -> 0 | J33: =IF(I33>0,E33/I33,0) -> 0 | K33: ='Swimming Pool quality check '!H33 -> 5834 | L33: =K33-K32 -> 0 | M33: =M32 -> 457.44 | N33: =SUM(M33-M32) -> 0 | O33: =O32 -> 529.52 | P33: =SUM(O33-O32) -> 0 | Q33: =SUM(P33+N33) -> 0 | T33: =T32 -> 4460 | U33: =SUM(T33-T32) -> 0 | V33: =V32 -> 353 | W33: =+V33-V32 -> 0 | X33: =X32 -> 139647 | Y33: =SUM(X33-X32) -> 0 | Z33: =Z32 -> 91335 | AA33: =Z33-Z32 -> 0 | AB33: =AB32 -> 244 | AC33: =AC32 -> 670 | AD33: =AC33-AC32 -> 0 | AE33: =AE32 -> 81.78 | AF33: =AE33-AE32 -> 0 | AG33: =AG32 -> 1126.61 | AH33: =AG33-AG32 -> 0 | AI33: =AF33+AH33 -> 0 | AJ33: =+Z33-Z32 -> 0 | AK33: =SUM(Y33-L33) -> 0 | AL33: =SUM(AJ33-W33) -> 0 | AM33: ='General information '!D33 -> 0 | AN33: ='General information '!H33 -> 0 | AP33: ='General information '!J33 -> 0 | AR33: =A33 -> 43858 | AS33: =AS32 -> 0.9 | AT33: =AT32 -> 127 | AU33: =AU32 -> 1.1 | AV33: =AV32 -> 120 | AW33: 2.9 | AX33: =AX32 -> 113 | AY33: =AS33*AT33 -> 114.3 | AZ33: =AU33*AV33 -> 132 | BA33: =AW33*AX33 -> 327.7 | BB33: =AY33-AY32 -> 0 | BC33: =AZ33-AZ32 -> 0 | BD33: =BA33-BA32 -> 0 | BE33: =SUM(BB33:BD33) -> 0 | BF33: =SUM(I33-BE33) -> 0 | BG33: =SUM(I33-BF33) -> 0
A34: =ELEC!C31 -> 43859 | B34: =B33 -> 108441 | C34: =B34-B33 -> 0 | D34: =C34/27 -> 0 | E34: =SUM((C34*$E$4)+(7500/'EDl log'!$A$38)) -> 241.93548 | G34: =G33 -> 587283 | H34: =G34-G33 -> 0 | I34: =C34+H34 -> 0 | J34: =IF(I34>0,E34/I34,0) -> 0 | K34: ='Swimming Pool quality check '!H34 -> 5834 | L34: =K34-K33 -> 0 | M34: =M33 -> 457.44 | N34: =SUM(M34-M33) -> 0 | O34: =O33 -> 529.52 | P34: =SUM(O34-O33) -> 0 | Q34: =SUM(P34+N34) -> 0 | T34: =T33 -> 4460 | U34: =SUM(T34-T33) -> 0 | V34: =V33 -> 353 | W34: =+V34-V33 -> 0 | X34: =X33 -> 139647 | Y34: =SUM(X34-X33) -> 0 | Z34: =Z33 -> 91335 | AA34: =Z34-Z33 -> 0 | AB34: =AB33 -> 244 | AC34: =AC33 -> 670 | AD34: =AC34-AC33 -> 0 | AE34: =AE33 -> 81.78 | AF34: =AE34-AE33 -> 0 | AG34: =AG33 -> 1126.61 | AH34: =AG34-AG33 -> 0 | AI34: =AF34+AH34 -> 0 | AJ34: =+Z34-Z33 -> 0 | AK34: =SUM(Y34-L34) -> 0 | AL34: =SUM(AJ34-W34) -> 0 | AM34: ='General information '!D34 -> 0 | AN34: ='General information '!H34 -> 0 | AP34: ='General information '!J34 -> 0 | AR34: =A34 -> 43859 | AS34: =AS33 -> 0.9 | AT34: =AT33 -> 127 | AU34: =AU33 -> 1.1 | AV34: =AV33 -> 120 | AW34: 2.9 | AX34: =AX33 -> 113 | AY34: =AS34*AT34 -> 114.3 | AZ34: =AU34*AV34 -> 132 | BA34: =AW34*AX34 -> 327.7 | BB34: =AY34-AY33 -> 0 | BC34: =AZ34-AZ33 -> 0 | BD34: =BA34-BA33 -> 0 | BE34: =SUM(BB34:BD34) -> 0 | BF34: =SUM(I34-BE34) -> 0 | BG34: =SUM(I34-BF34) -> 0
... A36: =ELEC!C33 -> 43861 | B36: =B35 -> 108441 | C36: =B36-B35 -> 0 | D36: =C36/27 -> 0 | E36: =SUM((C36*$E$4)+(7500/'EDl log'!$A$38)) -> 241.93548 | G36: =G35 -> 587283 | H36: =G36-G35 -> 0 | I36: =C36+H36 -> 0 | J36: =IF(I36>0,E36/I36,0) -> 0 | K36: ='Swimming Pool quality check '!H36 -> 5834 | L36: =K36-K35 -> 0 | M36: =M35 -> 457.44 | N36: =SUM(M36-M35) -> 0 | O36: =O35 -> 529.52 | P36: =SUM(O36-O35) -> 0 | Q36: =SUM(P36+N36) -> 0 | T36: =T35 -> 4460 | U36: =SUM(T36-T35) -> 0 | V36: =V35 -> 353 | W36: =+V36-V35 -> 0 | X36: =X35 -> 139647 | Y36: =SUM(X36-X35) -> 0 | Z36: =Z35 -> 91335 | AA36: =Z36-Z35 -> 0 | AB36: =AB35 -> 244 | AC36: =AC35 -> 670 | AD36: =AC36-AC35 -> 0 | AE36: =AE35 -> 81.78 | AF36: =AE36-AE35 -> 0 | AG36: =AG35 -> 1126.61 | AH36: =AG36-AG35 -> 0 | AI36: =AF36+AH36 -> 0 | AJ36: =+Z36-Z35 -> 0 | AK36: =SUM(Y36-L36) -> 0 | AL36: =SUM(AJ36-W36) -> 0 | AM36: ='General information '!D36 -> 0 | AN36: ='General information '!H36 -> 0 | AP36: ='General information '!J36 -> 0 | AR36: =A36 -> 43861 | AS36: =AS35 -> 0.9 | AT36: =AT35 -> 127 | AU36: =AU35 -> 1.1 | AV36: =AV35 -> 120 | AW36: 2.9 | AX36: =AX35 -> 113 | AY36: =AS36*AT36 -> 114.3 | AZ36: =AU36*AV36 -> 132 | BA36: =AW36*AX36 -> 327.7 | BB36: =AY36-AY35 -> 0 | BC36: =AZ36-AZ35 -> 0 | BD36: =BA36-BA35 -> 0 | BE36: =SUM(BB36:BD36) -> 0 | BF36: =SUM(I36-BE36) -> 0 | BG36: =SUM(I36-BF36) -> 0
C37: =SUM(C6:C36) -> 239 | D37: =SUM(D6:D36) -> 8.8518519 | F37: =SUM(F6:F36) -> 3 | H37: =SUM(H6:H36) -> 2416 | I37: =SUM(I6:I36) -> 2655 | L37: =SUM(L7:L36) -> 51 | Q37: =SUM(Q5:Q35) -> 0 | U37: =SUM(U6:U36) -> 97 | Y37: =SUM(Y35,Y33,Y31,Y29,Y27,Y25,Y23,Y21,Y19,Y17,Y15,Y13,Y11,Y9,Y7+Y36) -> 708 | AJ37: =SUM(AJ6:AJ36) -> 714 | AK37: =SUM(Y37-L37) -> 657 | AL37: =SUM(AL6:AL36) -> 693 | AT37: =AT36 -> 127
C38: =+C37*1.66 -> 396.74 | E38: =SUM(E6:E36) -> 7896.74 | F38: =SUM(F6:F36) -> 3 | H38: 7500 | I38: =SUM('General information '!G37/WATER!I37) -> 0.33061959 | O38: =SUM(Q37+I37) -> 2655 | Z38: =SUM(Y37:AJ37) -> 1422 | AK38: =SUM(Y38-L38) -> 0
B39: =9*27 -> 243 | D39: =SUM(D21:D35) -> 0 | F39: =SUM(F6:F36) -> 3 | G39: =SUM(I37) -> 2655 | H39: =SUM(H38+C38) -> 7896.74 | K39: =SUM(H39/G39) -> 2.97429 | AJ39: =SUM(C38-AK38) -> 396.74 | AM39: =SUM(AJ39/AO38) -> #DIV/0!

Sheet graphic

Sheet General information 
A1: GENERAL & HOTEL'S INFORMATION SHEET
B4: Max Temp | C4: MIN TEMP | D4: AVE TEMP | E4: AVE Humidity | F4: AVE OCC | G4: # of OCC Rooms | H4: Ball room | I4: Meeting rooms | J4: Outlets | K4: Total covers | L4: # of permenant Emp | M4: # of casuals | N4: Total # of EMP | O4: # of EMP/OCC Room
A5: =ELEC!C2 -> 31-12-2019 | B5: ='[1]General information '!B36 -> 16 | C5: ='[1]General information '!C36 -> 11 | D5: ='[1]General information '!D36 -> 13.5 | E5: ='[1]General information '!E36 -> 0.67 | F5: ='[1]General information '!F36 -> 0.5 | G5: ='[1]General information '!G36 -> 115 | H5: ='[1]General information '!H36 -> 0 | I5: ='[1]General information '!I36 -> 0 | ... O5: ='[1]General information '!O36 -> 0
A6: =ELEC!C3 -> 43831 | B6: 16 | C6: 11 | D6: =(C6+B6)/2 -> 13.5 | E6: 0.55 | F6: 0.426 | G6: =F6*230 -> 97.98 | H6: 0 | J6: 549 | K6: =+J6+H6 -> 549
A7: =ELEC!C4 -> 43832 | B7: 17 | C7: 12 | D7: =(C7+B7)/2 -> 14.5 | E7: 0.55 | F7: 0.3348 | G7: =F7*230 -> 77.004 | H7: 0 | I7: 0 | J7: 371 | K7: =+J7+H7 -> 371
A8: =ELEC!C5 -> 43833 | B8: 16 | C8: 12 | D8: =(C8+B8)/2 -> 14 | E8: 0.54 | F8: 0.2782 | G8: =F8*230 -> 63.986 | H8: 157 | J8: 535 | K8: =+J8+H8 -> 692
A9: =ELEC!C6 -> 43834 | B9: 15 | C9: 11 | D9: =(C9+B9)/2 -> 13 | E9: 0.55 | F9: 0.213 | G9: =F9*230 -> 48.99 | H9: 260 | J9: 650 | K9: =+J9+H9 -> 910
A10: =ELEC!C7 -> 43835 | B10: 15 | C10: 11 | D10: =(C10+B10)/2 -> 13 | E10: 0.55 | F10: 0.1609 | G10: =F10*230 -> 37.007 | H10: 0 | J10: 287 | K10: =+J10+H10 -> 287
A11: =ELEC!C8 -> 43836 | B11: 16 | C11: 12 | D11: =(C11+B11)/2 -> 14 | E11: 0.58 | F11: 0.1652 | G11: =F11*230 -> 37.996 | H11: 0 | J11: 186 | K11: =+J11+H11 -> 186
A12: =ELEC!C9 -> 43837 | B12: 16 | C12: 12 | D12: =(C12+B12)/2 -> 14 | E12: 0.5 | F12: 0.2348 | G12: =F12*230 -> 54.004 | H12: 0 | J12: 269 | K12: =+J12+H12 -> 269
A13: =ELEC!C10 -> 43838 | B13: 14 | C13: 11 | D13: =(C13+B13)/2 -> 12.5 | E13: 0.72 | F13: 0.234 | G13: =F13*230 -> 53.82 | H13: 0 | K13: 269
A14: =ELEC!C11 -> 43839 | B14: 14 | C14: 11 | D14: =(C14+B14)/2 -> 12.5 | E14: 0.6 | F14: 0.2087 | G14: =F14*230 -> 48.001 | H14: 0 | J14: 258 | K14: =+J14+H14 -> 258
A15: =ELEC!C12 -> 43840 | B15: 17 | C15: 12 | D15: =(C15+B15)/2 -> 14.5 | E15: 0.5 | F15: 0.2 | G15: =F15*230 -> 46 | H15: 0 | J15: 276 | K15: =+J15+H15 -> 276
A16: =ELEC!C13 -> 43841 | B16: 17 | C16: 13 | D16: =(C16+B16)/2 -> 15 | E16: 0.5 | F16: 0.1696 | G16: =F16*230 -> 39.008 | H16: 180 | J16: 536 | K16: =+J16+H16 -> 716
A17: =ELEC!C14 -> 43842 | B17: 16 | C17: 12 | D17: =(C17+B17)/2 -> 14 | E17: 0.55 | F17: 0.1739 | G17: =F17*230 -> 39.997 | H17: 0 | J17: 233 | K17: =+J17+H17 -> 233
A18: =ELEC!C15 -> 43843 | B18: 17 | C18: 13 | D18: =(C18+B18)/2 -> 15 | E18: 0.55 | F18: 0.1826 | G18: =F18*230 -> 41.998 | H18: 0 | J18: 540 | K18: =+J18+H18 -> 540
A19: =ELEC!C16 -> 43844 | B19: 16 | C19: 12 | D19: =(C19+B19)/2 -> 14 | E19: 0.55 | F19: 0.2087 | G19: =F19*230 -> 48.001 | H19: 0 | J19: 184 | K19: =+J19+H19 -> 184
A20: =ELEC!C17 -> 43845 | B20: 17 | C20: 13 | D20: =(C20+B20)/2 -> 15 | E20: 0.55 | F20: 0.2261 | G20: =F20*230 -> 52.003 | H20: 0 | J20: 345 | K20: =+J20+H20 -> 345
A21: =ELEC!C18 -> 43846 | B21: 19 | C21: 13 | D21: =(C21+B21)/2 -> 16 | E21: 0.6 | F21: 0.2261 | G21: =F21*230 -> 52.003 | H21: 107 | J21: 331 | K21: =+J21+H21 -> 438
A22: =ELEC!C19 -> 43847 | B22: 20 | C22: 13 | D22: =(C22+B22)/2 -> 16.5 | E22: 0.57 | F22: 0.1739 | G22: =F22*230 -> 39.997 | H22: 100 | J22: 340 | K22: =+J22+H22 -> 440
A23: =ELEC!C20 -> 43848 | D23: =(C23+B23)/2 -> 0 | G23: =F23*230 -> 0 | H23: 0 | K23: =+J23+H23 -> 0
A24: =ELEC!C21 -> 43849 | D24: =(C24+B24)/2 -> 0 | G24: =F24*230 -> 0 | H24: 0 | K24: =+J24+H24 -> 0
A25: =ELEC!C22 -> 43850 | D25: =(C25+B25)/2 -> 0 | G25: =F25*230 -> 0 | H25: 0 | K25: =+J25+H25 -> 0
A26: =ELEC!C23 -> 43851 | D26: =(C26+B26)/2 -> 0 | G26: =F26*230 -> 0 | H26: 0 | K26: =+J26+H26 -> 0
A27: =ELEC!C24 -> 43852 | D27: =(C27+B27)/2 -> 0 | G27: =F27*230 -> 0 | H27: 0 | K27: =+J27+H27+I27 -> 0
A28: =ELEC!C25 -> 43853 | D28: =(C28+B28)/2 -> 0 | G28: =F28*230 -> 0 | H28: 0 | K28: =+J28+H28+I28 -> 0
A29: =ELEC!C26 -> 43854 | D29: =(C29+B29)/2 -> 0 | G29: =F29*230 -> 0 | H29: 0 | K29: =+J29+H29+I29 -> 0
A30: =ELEC!C27 -> 43855 | D30: =(C30+B30)/2 -> 0 | G30: =F30*230 -> 0 | H30: 0 | K30: =+J30+H30+I30 -> 0
A31: =ELEC!C28 -> 43856 | D31: =(C31+B31)/2 -> 0 | G31: =F31*230 -> 0 | K31: =+J31+H31+I31 -> 0
A32: =ELEC!C29 -> 43857 | D32: =(C32+B32)/2 -> 0 | G32: =F32*230 -> 0 | K32: =+J32+H32+I32 -> 0
A33: =ELEC!C30 -> 43858 | D33: =(C33+B33)/2 -> 0 | G33: =F33*230 -> 0 | K33: =+J33+H33+I33 -> 0
A34: =ELEC!C31 -> 43859 | D34: =(C34+B34)/2 -> 0 | G34: =F34*230 -> 0 | K34: =+J34+H34+I34 -> 0
A35: =ELEC!C32 -> 43860 | D35: =(C35+B35)/2 -> 0 | G35: =F35*230 -> 0 | K35: =+J35+H35+I35 -> 0
A36: =ELEC!C33 -> 43861 | D36: =(C36+B36)/2 -> 0 | G36: =F36*230 -> 0 | K36: =+J36+H36+I36 -> 0
F37: =AVERAGE(F6:F36) -> 0.2245 | G37: =SUM(G6:G35) -> 877.795
D38: =SUM(D6:D36)/'EDl log'!A36 -> 14.176471
I41: http://www.accuweather.com/en/lb/lebanon-weather

Sheet tanks
B2: Tank 1 | D2: Tank 2 | F2: Tank 3 | H2: Tank 4 | J2: Tank 5 | L2: Tank 6 | N2: Tank 7 | P2: Tank 8 | R2: Tank 9 | T2: Tank 10 | V2: Tank 11 | Z2: Tank 1 | AB2: Tank 2 | AD2: Tank 3 | AF2: Tank 4 | AH2: Tank 5 | AJ2: Tank 6 | AL2: Tank 7
B3: 6670 | D3: =SUM(B3) -> 6670 | F3: =SUM(D3) -> 6670 | H3: =SUM(F3) -> 6670 | J3: =SUM(H3) -> 6670 | L3: =SUM(J3) -> 6670 | N3: =SUM(L3) -> 6670 | P3: =SUM(N3) -> 6670 | R3: =SUM(P3) -> 6670 | T3: =SUM(R3) -> 6670 | V3: =SUM(T3) -> 6670 | W3: =SUM(B3:V3) -> 73370 | Z3: 2800 | AB3: 2800 | AD3: 2800 | AF3: 2800 | AH3: 2800 | AJ3: 2800 | AL3: 2800 | AM3: =SUM(Z3:AL3) -> 19600 | AO3: =SUM(AM3+W3) -> 92970 | AR3: Total sotck | AS3: Diesel Cons Per day | AT3: Diesel Delivery | BE3: Genset Co | BF3: Steam | BG3: Boil | BH3: Outdoor temperature
B4: =B3/310 -> 21.516129 | D4: =SUM(B4) -> 21.516129 | F4: =SUM(D4) -> 21.516129 | H4: =SUM(F4) -> 21.516129 | J4: =SUM(H4) -> 21.516129 | L4: =SUM(J4) -> 21.516129 | N4: =SUM(L4) -> 21.516129 | P4: =SUM(N4) -> 21.516129 | R4: =SUM(P4) -> 21.516129 | T4: =SUM(R4) -> 21.516129 | V4: =SUM(T4) -> 21.516129 | Z4: =Z3/280 -> 10 | AA4: =AA3/280 -> 0 | AB4: =AB3/280 -> 10 | AC4: =AC3/280 -> 0 | AD4: =AD3/280 -> 10 | AE4: =AE3/280 -> 0 | AF4: =AF3/280 -> 10 | AG4: =AG3/280 -> 0 | ... AL4: =AL3/280 -> 10 | AT4: Delivery | AU4: Cost /L | AW4: Boiler+Steam | AX4: Generator | AZ4: Occupancy | BA4: AVE TEPM | BB4: AVE Humidity
A5: =ELEC!C2 -> 31-12-2019 | B5: =[1]tanks!B36 -> 238 | C5: =[1]tanks!C36 -> 5120.8387 | D5: =[1]tanks!D36 -> 238 | E5: =[1]tanks!E36 -> 5120.8387 | F5: =[1]tanks!F36 -> 238 | G5: =[1]tanks!G36 -> 5120.8387 | H5: =[1]tanks!H36 -> 238 | I5: =[1]tanks!I36 -> 5120.8387 | ... BH5: =[1]tanks!BH36 -> 0
A6: =ELEC!C3 -> 43831 | B6: ='B5'!B5 -> 234 | C6: =B6*$B$4 -> 5034.7742 | D6: =SUM(B6) -> 234 | E6: =D6*$B$4 -> 5034.7742 | F6: =SUM(D6) -> 234 | G6: =F6*$B$4 -> 5034.7742 | H6: =SUM(F6) -> 234 | I6: =H6*$B$4 -> 5034.7742 | J6: =SUM(H6) -> 234 | K6: =J6*$B$4 -> 5034.7742 | L6: =SUM(J6) -> 234 | M6: =L6*$B$4 -> 5034.7742 | N6: =SUM(L6) -> 234 | O6: =N6*$B$4 -> 5034.7742 | P6: =SUM(N6) -> 234 | Q6: =P6*$B$4 -> 5034.7742 | R6: =SUM(P6) -> 234 | S6: =R6*$B$4 -> 5034.7742 | T6: =SUM(R6) -> 234 | U6: =T6*$B$4 -> 5034.7742 | V6: =SUM(T6) -> 234 | W6: =V6*$B$4 -> 5034.7742 | X6: =SUM(Y6/73370) -> 0.75483871 | Y6: =SUM(C6+E6+G6+I6+K6+M6+O6+Q6+S6+U6+W6) -> 55382.516 | Z6: ='B5'!C5 -> 78 | AA6: =SUM(Z6*$Z$4) -> 780 | AB6: =SUM(Z6) -> 78 | AC6: =SUM(AB6*$Z$4) -> 780 | AD6: =SUM(AB6) -> 78 | AE6: =SUM(AD6*$Z$4) -> 780 | AF6: =SUM(AD6) -> 78 | AG6: =SUM(AF6*$Z$4) -> 780 | AH6: =SUM(AF6) -> 78 | AI6: =SUM(AH6*$Z$4) -> 780 | AJ6: =SUM(AH6) -> 78 | AK6: =SUM(AJ6*$Z$4) -> 780 | AL6: =SUM(AJ6) -> 78 | AM6: =SUM(AL6*$Z$4) -> 780 | AN6: =SUM(AO6/19600) -> 0.27857143 | AO6: =SUM(AA6+AC6+AE6+AG6+AI6+AK6+AM6) -> 5460 | AQ6: =SUM(AR6/92970) -> 0.65443171 | AR6: =SUM(AO6+Y6) -> 60842.516 | AS6: =SUM(AR6-AR5-AT6) -> -2346.7097 | AV6: =IF(AT6>0,AU6,AV5) -> 0.5634 | AW6: =-SUM('B5'!AI5) -> -1458 | AX6: =-SUM(AW6-AS6) -> -888.70968 | AY6: =SUM(AX6+AW6) -> -2346.7097 | AZ6: =ELEC!A3 -> 0.426 | BA6: ='General information '!D6 -> 13.5 | BB6: =SUM('General information '!E6) -> 0.55 | BC6: =IF(AR3>=AR6,0,1) -> 0 | BD6: 19222 | BE6: =(305/1185)*ELEC!Q4 -> 1189.6287 | BG6: =#REF!-BE6 -> #REF! | BH6: 21
A7: =ELEC!C4 -> 43832 | B7: ='B5'!B6 -> 205 | C7: =B7*$B$4 -> 4410.8065 | D7: =SUM(B7) -> 205 | E7: =D7*$B$4 -> 4410.8065 | F7: =SUM(D7) -> 205 | G7: =F7*$B$4 -> 4410.8065 | H7: =SUM(F7) -> 205 | I7: =H7*$B$4 -> 4410.8065 | J7: =SUM(H7) -> 205 | K7: =J7*$B$4 -> 4410.8065 | L7: =SUM(J7) -> 205 | M7: =L7*$B$4 -> 4410.8065 | N7: =SUM(L7) -> 205 | O7: =N7*$B$4 -> 4410.8065 | P7: =SUM(N7) -> 205 | Q7: =P7*$B$4 -> 4410.8065 | R7: =SUM(P7) -> 205 | S7: =R7*$B$4 -> 4410.8065 | T7: =SUM(R7) -> 205 | U7: =T7*$B$4 -> 4410.8065 | V7: =SUM(T7) -> 205 | W7: =V7*$B$4 -> 4410.8065 | X7: =SUM(Y7/73370) -> 0.66129032 | Y7: =SUM(C7+E7+G7+I7+K7+M7+O7+Q7+S7+U7+W7) -> 48518.871 | Z7: ='B5'!C6 -> 143 | AA7: =SUM(Z7*$Z$4) -> 1430 | AB7: =SUM(Z7) -> 143 | AC7: =SUM(AB7*$Z$4) -> 1430 | AD7: =SUM(AB7) -> 143 | AE7: =SUM(AD7*$Z$4) -> 1430 | AF7: =SUM(AD7) -> 143 | AG7: =SUM(AF7*$Z$4) -> 1430 | AH7: =SUM(AF7) -> 143 | AI7: =SUM(AH7*$Z$4) -> 1430 | AJ7: =SUM(AH7) -> 143 | AK7: =SUM(AJ7*$Z$4) -> 1430 | AL7: =SUM(AJ7) -> 143 | AM7: =SUM(AL7*$Z$4) -> 1430 | AN7: =SUM(AO7/19600) -> 0.51071429 | AO7: =SUM(AA7+AC7+AE7+AG7+AI7+AK7+AM7) -> 10010 | AQ7: =SUM(AR7/92970) -> 0.62954578 | AR7: =SUM(AO7+Y7) -> 58528.871 | AS7: =SUM(AR7-AR6-AT7) -> -2313.6452 | AV7: =IF(AT7>0,AU7,AV6) -> 0.5634 | AW7: =-SUM('B5'!AI6) -> -1092.3 | AX7: =-SUM(AW7-AS7) -> -1221.3452 | AY7: =SUM(AX7+AW7) -> -2313.6452 | AZ7: =ELEC!A4 -> 0.3348 | BA7: ='General information '!D7 -> 14.5 | BB7: =SUM('General information '!E7) -> 0.55 | BC7: 0 | BD7: 19222 | BE7: =(305/1185)*ELEC!Q5 -> 1191.9451 | BG7: =#REF!-BE7 -> #REF! | BH7: 19
A8: =ELEC!C5 -> 43833 | B8: ='B5'!B7 -> 198 | C8: =B8*$B$4 -> 4260.1935 | D8: =SUM(B8) -> 198 | E8: =D8*$B$4 -> 4260.1935 | F8: =SUM(D8) -> 198 | G8: =F8*$B$4 -> 4260.1935 | H8: =SUM(F8) -> 198 | I8: =H8*$B$4 -> 4260.1935 | J8: =SUM(H8) -> 198 | K8: =J8*$B$4 -> 4260.1935 | L8: =SUM(J8) -> 198 | M8: =L8*$B$4 -> 4260.1935 | N8: =SUM(L8) -> 198 | O8: =N8*$B$4 -> 4260.1935 | P8: =SUM(N8) -> 198 | Q8: =P8*$B$4 -> 4260.1935 | R8: =SUM(P8) -> 198 | S8: =R8*$B$4 -> 4260.1935 | T8: =SUM(R8) -> 198 | U8: =T8*$B$4 -> 4260.1935 | V8: =SUM(T8) -> 198 | W8: =V8*$B$4 -> 4260.1935 | X8: =SUM(Y8/73370) -> 0.63870968 | Y8: =SUM(C8+E8+G8+I8+K8+M8+O8+Q8+S8+U8+W8) -> 46862.129 | Z8: ='B5'!C7 -> 127 | AA8: =SUM(Z8*$Z$4) -> 1270 | AB8: =SUM(Z8) -> 127 | AC8: =SUM(AB8*$Z$4) -> 1270 | AD8: =SUM(AB8) -> 127 | AE8: =SUM(AD8*$Z$4) -> 1270 | AF8: =SUM(AD8) -> 127 | AG8: =SUM(AF8*$Z$4) -> 1270 | AH8: =SUM(AF8) -> 127 | AI8: =SUM(AH8*$Z$4) -> 1270 | AJ8: =SUM(AH8) -> 127 | AK8: =SUM(AJ8*$Z$4) -> 1270 | AL8: =SUM(AJ8) -> 127 | AM8: =SUM(AL8*$Z$4) -> 1270 | AN8: =SUM(AO8/19600) -> 0.45357143 | AO8: =SUM(AA8+AC8+AE8+AG8+AI8+AK8+AM8) -> 8890 | AQ8: =SUM(AR8/92970) -> 0.5996787 | AR8: =SUM(AO8+Y8) -> 55752.129 | AS8: =SUM(AR8-AR7-AT8) -> -2776.7419 | AV8: =IF(AT8>0,AU8,AV7) -> 0.5634 | AW8: =-SUM('B5'!AI7) -> -1325.9 | AX8: =-SUM(AW8-AS8) -> -1450.8419 | AY8: =SUM(AX8+AW8) -> -2776.7419 | AZ8: =ELEC!A5 -> 0.2782 | BA8: ='General information '!D8 -> 14 | BB8: =SUM('General information '!E8) -> 0.54 | BC8: =IF(AR7>=AR8,0,1) -> 0 | BD8: 19222 | BE8: =(305/1185)*ELEC!Q6 -> 1029.5359 | BG8: =#REF!-BE8 -> #REF! | BH8: 16
A9: =ELEC!C6 -> 43834 | B9: ='B5'!B8 -> 193 | C9: =B9*$B$4 -> 4152.6129 | D9: =SUM(B9) -> 193 | E9: =D9*$B$4 -> 4152.6129 | F9: =SUM(D9) -> 193 | G9: =F9*$B$4 -> 4152.6129 | H9: =SUM(F9) -> 193 | I9: =H9*$B$4 -> 4152.6129 | J9: =SUM(H9) -> 193 | K9: =J9*$B$4 -> 4152.6129 | L9: =SUM(J9) -> 193 | M9: =L9*$B$4 -> 4152.6129 | N9: =SUM(L9) -> 193 | O9: =N9*$B$4 -> 4152.6129 | P9: =SUM(N9) -> 193 | Q9: =P9*$B$4 -> 4152.6129 | R9: =SUM(P9) -> 193 | S9: =R9*$B$4 -> 4152.6129 | T9: =SUM(R9) -> 193 | U9: =T9*$B$4 -> 4152.6129 | V9: =SUM(T9) -> 193 | W9: =V9*$B$4 -> 4152.6129 | X9: =SUM(Y9/73370) -> 0.62258065 | Y9: =SUM(C9+E9+G9+I9+K9+M9+O9+Q9+S9+U9+W9) -> 45678.742 | Z9: ='B5'!C8 -> 102 | AA9: =SUM(Z9*$Z$4) -> 1020 | AB9: =SUM(Z9) -> 102 | AC9: =SUM(AB9*$Z$4) -> 1020 | AD9: =SUM(AB9) -> 102 | AE9: =SUM(AD9*$Z$4) -> 1020 | AF9: =SUM(AD9) -> 102 | AG9: =SUM(AF9*$Z$4) -> 1020 | AH9: =SUM(AF9) -> 102 | AI9: =SUM(AH9*$Z$4) -> 1020 | AJ9: =SUM(AH9) -> 102 | AK9: =SUM(AJ9*$Z$4) -> 1020 | AL9: =SUM(AJ9) -> 102 | AM9: =SUM(AL9*$Z$4) -> 1020 | AN9: =SUM(AO9/19600) -> 0.36428571 | AO9: =SUM(AA9+AC9+AE9+AG9+AI9+AK9+AM9) -> 7140 | AQ9: =SUM(AR9/92970) -> 0.56812673 | AR9: =SUM(AO9+Y9) -> 52818.742 | AS9: =SUM(AR9-AR8-AT9) -> -2933.3871 | AV9: =IF(AT9>0,AU9,AV8) -> 0.5634 | AW9: =-SUM('B5'!AI8) -> -944 | AX9: =-SUM(AW9-AS9) -> -1989.3871 | AY9: =SUM(AX9+AW9) -> -2933.3871 | AZ9: =ELEC!A6 -> 0.213 | BA9: ='General information '!D9 -> 13 | BB9: =SUM('General information '!E9) -> 0.55 | BC9: =IF(AR8>=AR9,0,1) -> 0 | BD9: 19222 | BE9: =(305/1185)*ELEC!Q7 -> 665.59494 | BG9: =#REF!-BE9 -> #REF! | BH9: 18
A10: =ELEC!C7 -> 43835 | B10: ='B5'!B9 -> 190 | C10: =B10*$B$4 -> 4088.0645 | D10: =SUM(B10) -> 190 | E10: =D10*$B$4 -> 4088.0645 | F10: =SUM(D10) -> 190 | G10: =F10*$B$4 -> 4088.0645 | H10: =SUM(F10) -> 190 | I10: =H10*$B$4 -> 4088.0645 | J10: =SUM(H10) -> 190 | K10: =J10*$B$4 -> 4088.0645 | L10: =SUM(J10) -> 190 | M10: =L10*$B$4 -> 4088.0645 | N10: =SUM(L10) -> 190 | O10: =N10*$B$4 -> 4088.0645 | P10: =SUM(N10) -> 190 | Q10: =P10*$B$4 -> 4088.0645 | R10: =SUM(P10) -> 190 | S10: =R10*$B$4 -> 4088.0645 | T10: =SUM(R10) -> 190 | U10: =T10*$B$4 -> 4088.0645 | V10: =SUM(T10) -> 190 | W10: =V10*$B$4 -> 4088.0645 | X10: =SUM(Y10/73370) -> 0.61290323 | Y10: =SUM(C10+E10+G10+I10+K10+M10+O10+Q10+S10+U10+W10) -> 44968.71 | Z10: ='B5'!C9 -> 88 | AA10: =SUM(Z10*$Z$4) -> 880 | AB10: =SUM(Z10) -> 88 | AC10: =SUM(AB10*$Z$4) -> 880 | AD10: =SUM(AB10) -> 88 | AE10: =SUM(AD10*$Z$4) -> 880 | AF10: =SUM(AD10) -> 88 | AG10: =SUM(AF10*$Z$4) -> 880 | AH10: =SUM(AF10) -> 88 | AI10: =SUM(AH10*$Z$4) -> 880 | AJ10: =SUM(AH10) -> 88 | AK10: =SUM(AJ10*$Z$4) -> 880 | AL10: =SUM(AJ10) -> 88 | AM10: =SUM(AL10*$Z$4) -> 880 | AN10: =SUM(AO10/19600) -> 0.31428571 | AO10: =SUM(AA10+AC10+AE10+AG10+AI10+AK10+AM10) -> 6160 | AQ10: =SUM(AR10/92970) -> 0.54994847 | AR10: =SUM(AO10+Y10) -> 51128.71 | AS10: =SUM(AR10-AR9-AT10) -> -1690.0323 | AV10: =IF(AT10>0,AU10,AV9) -> 0.5634 | AW10: =-SUM('B5'!AI9) -> -1107.7 | AX10: =-SUM(AW10-AS10) -> -582.33226 | AY10: =SUM(AX10+AW10) -> -1690.0323 | AZ10: =ELEC!A7 -> 0.1609 | BA10: ='General information '!D10 -> 13 | BB10: =SUM('General information '!E10) -> 0.55 | BC10: =IF(AR9>=AR10,0,1) -> 0 | BD10: 19222 | BE10: =(305/1185)*ELEC!Q8 -> 1347.1477 | BG10: =#REF!-BE10 -> #REF! | BH10: 16
A11: =ELEC!C8 -> 43836 | B11: ='B5'!B10 -> 182 | C11: =B11*$B$4 -> 3915.9355 | D11: =SUM(B11) -> 182 | E11: =D11*$B$4 -> 3915.9355 | F11: =SUM(D11) -> 182 | G11: =F11*$B$4 -> 3915.9355 | H11: =SUM(F11) -> 182 | I11: =H11*$B$4 -> 3915.9355 | J11: =SUM(H11) -> 182 | K11: =J11*$B$4 -> 3915.9355 | L11: =SUM(J11) -> 182 | M11: =L11*$B$4 -> 3915.9355 | N11: =SUM(L11) -> 182 | O11: =N11*$B$4 -> 3915.9355 | P11: =SUM(N11) -> 182 | Q11: =P11*$B$4 -> 3915.9355 | R11: =SUM(P11) -> 182 | S11: =R11*$B$4 -> 3915.9355 | T11: =SUM(R11) -> 182 | U11: =T11*$B$4 -> 3915.9355 | V11: =SUM(T11) -> 182 | W11: =V11*$B$4 -> 3915.9355 | X11: =SUM(Y11/73370) -> 0.58709677 | Y11: =SUM(C11+E11+G11+I11+K11+M11+O11+Q11+S11+U11+W11) -> 43075.29 | Z11: ='B5'!C10 -> 70 | AA11: =SUM(Z11*$Z$4) -> 700 | AB11: =SUM(Z11) -> 70 | AC11: =SUM(AB11*$Z$4) -> 700 | AD11: =SUM(AB11) -> 70 | AE11: =SUM(AD11*$Z$4) -> 700 | AF11: =SUM(AD11) -> 70 | AG11: =SUM(AF11*$Z$4) -> 700 | AH11: =SUM(AF11) -> 70 | AI11: =SUM(AH11*$Z$4) -> 700 | AJ11: =SUM(AH11) -> 70 | AK11: =SUM(AJ11*$Z$4) -> 700 | AL11: =SUM(AJ11) -> 70 | AM11: =SUM(AL11*$Z$4) -> 700 | AN11: =SUM(AO11/19600) -> 0.25 | AO11: =SUM(AA11+AC11+AE11+AG11+AI11+AK11+AM11) -> 4900 | AQ11: =SUM(AR11/92970) -> 0.5160298 | AR11: =SUM(AO11+Y11) -> 47975.29 | AS11: =SUM(AR11-AR10-AT11) -> -3153.4194 | AV11: =IF(AT11>0,AU11,AV10) -> 0.5634 | AW11: =-SUM('B5'!AI10) -> -607 | AX11: =-SUM(AW11-AS11) -> -2546.4194 | AY11: =SUM(AX11+AW11) -> -3153.4194 | AZ11: =ELEC!A8 -> 0.1652 | BA11: ='General information '!D11 -> 14 | BB11: =SUM('General information '!E11) -> 0.58 | BC11: =IF(AR10>=AR11,0,1) -> 0 | BD11: 19222 | BE11: =(305/1185)*ELEC!Q9 -> 1255.7764 | BG11: =#REF!-BE11 -> #REF! | BH11: 16.5
A12: =ELEC!C9 -> 43837 | B12: ='B5'!B11 -> 164 | C12: =B12*$B$4 -> 3528.6452 | D12: =SUM(B12) -> 164 | E12: =D12*$B$4 -> 3528.6452 | F12: =SUM(D12) -> 164 | G12: =F12*$B$4 -> 3528.6452 | H12: =SUM(F12) -> 164 | I12: =H12*$B$4 -> 3528.6452 | J12: =SUM(H12) -> 164 | K12: =J12*$B$4 -> 3528.6452 | L12: =SUM(J12) -> 164 | M12: =L12*$B$4 -> 3528.6452 | N12: =SUM(L12) -> 164 | O12: =N12*$B$4 -> 3528.6452 | P12: =SUM(N12) -> 164 | Q12: =P12*$B$4 -> 3528.6452 | R12: =SUM(P12) -> 164 | S12: =R12*$B$4 -> 3528.6452 | T12: =SUM(R12) -> 164 | U12: =T12*$B$4 -> 3528.6452 | V12: =SUM(T12) -> 164 | W12: =V12*$B$4 -> 3528.6452 | X12: =SUM(Y12/73370) -> 0.52903226 | Y12: =SUM(C12+E12+G12+I12+K12+M12+O12+Q12+S12+U12+W12) -> 38815.097 | Z12: ='B5'!C11 -> 101 | AA12: =SUM(Z12*$Z$4) -> 1010 | AB12: =SUM(Z12) -> 101 | AC12: =SUM(AB12*$Z$4) -> 1010 | AD12: =SUM(AB12) -> 101 | AE12: =SUM(AD12*$Z$4) -> 1010 | AF12: =SUM(AD12) -> 101 | AG12: =SUM(AF12*$Z$4) -> 1010 | AH12: =SUM(AF12) -> 101 | AI12: =SUM(AH12*$Z$4) -> 1010 | AJ12: =SUM(AH12) -> 101 | AK12: =SUM(AJ12*$Z$4) -> 1010 | AL12: =SUM(AJ12) -> 101 | AM12: =SUM(AL12*$Z$4) -> 1010 | AN12: =SUM(AO12/19600) -> 0.36071429 | AO12: =SUM(AA12+AC12+AE12+AG12+AI12+AK12+AM12) -> 7070 | AQ12: =SUM(AR12/92970) -> 0.49354735 | AR12: =SUM(AO12+Y12) -> 45885.097 | AS12: =SUM(AR12-AR11-AT12) -> -2090.1935 | AV12: =IF(AT12>0,AU12,AV11) -> 0.5634 | AW12: =-SUM('B5'!AI11) -> -1019.3 | AX12: =-SUM(AW12-AS12) -> -1070.8935 | AY12: =SUM(AX12+AW12) -> -2090.1935 | AZ12: =ELEC!A9 -> 0.2348 | BA12: ='General information '!D12 -> 14 | BB12: =SUM('General information '!E12) -> 0.5 | BC12: =IF(AR11>=AR12,0,1) -> 0 | BD12: 19222 | BE12: =(305/1185)*ELEC!Q10 -> 1801.9451 | BG12: =#REF!-BE12 -> #REF! | BH12: 15.5
A13: =ELEC!C10 -> 43838 | B13: ='B5'!B12 -> 154 | C13: =B13*$B$4 -> 3313.4839 | D13: =SUM(B13) -> 154 | E13: =D13*$B$4 -> 3313.4839 | F13: =SUM(D13) -> 154 | G13: =F13*$B$4 -> 3313.4839 | H13: =SUM(F13) -> 154 | I13: =H13*$B$4 -> 3313.4839 | J13: =SUM(H13) -> 154 | K13: =J13*$B$4 -> 3313.4839 | L13: =SUM(J13) -> 154 | M13: =L13*$B$4 -> 3313.4839 | N13: =SUM(L13) -> 154 | O13: =N13*$B$4 -> 3313.4839 | P13: =SUM(N13) -> 154 | Q13: =P13*$B$4 -> 3313.4839 | R13: =SUM(P13) -> 154 | S13: =R13*$B$4 -> 3313.4839 | T13: =SUM(R13) -> 154 | U13: =T13*$B$4 -> 3313.4839 | V13: =SUM(T13) -> 154 | W13: =V13*$B$4 -> 3313.4839 | X13: =SUM(Y13/73370) -> 0.49677419 | Y13: =SUM(C13+E13+G13+I13+K13+M13+O13+Q13+S13+U13+W13) -> 36448.323 | Z13: ='B5'!C12 -> 80 | AA13: =SUM(Z13*$Z$4) -> 800 | AB13: =SUM(Z13) -> 80 | AC13: =SUM(AB13*$Z$4) -> 800 | AD13: =SUM(AB13) -> 80 | AE13: =SUM(AD13*$Z$4) -> 800 | AF13: =SUM(AD13) -> 80 | AG13: =SUM(AF13*$Z$4) -> 800 | AH13: =SUM(AF13) -> 80 | AI13: =SUM(AH13*$Z$4) -> 800 | AJ13: =SUM(AH13) -> 80 | AK13: =SUM(AJ13*$Z$4) -> 800 | AL13: =SUM(AJ13) -> 80 | AM13: =SUM(AL13*$Z$4) -> 800 | AN13: =SUM(AO13/19600) -> 0.28571429 | AO13: =SUM(AA13+AC13+AE13+AG13+AI13+AK13+AM13) -> 5600 | AQ13: =SUM(AR13/92970) -> 0.4522784 | AR13: =SUM(AO13+Y13) -> 42048.323 | AS13: =SUM(AR13-AR12-AT13) -> -3836.7742 | AV13: =IF(AT13>0,AU13,AV12) -> 0.5634 | AW13: =-SUM('B5'!AI12) -> -816 | AX13: =-SUM(AW13-AS13) -> -3020.7742 | AY13: =SUM(AX13+AW13) -> -3836.7742 | AZ13: =ELEC!A10 -> 0.234 | BA13: ='General information '!D13 -> 12.5 | BB13: =SUM('General information '!E13) -> 0.72 | BC13: =IF(AR12>=AR13,0,1) -> 0 | BD13: 19222 | BE13: =(305/1185)*ELEC!Q11 -> 1257.5781 | BG13: =#REF!-BE13 -> #REF!
A14: =ELEC!C11 -> 43839 | B14: ='B5'!B13 -> 179 | C14: =B14*$B$4 -> 3851.3871 | D14: =SUM(B14) -> 179 | E14: =D14*$B$4 -> 3851.3871 | F14: =SUM(D14) -> 179 | G14: =F14*$B$4 -> 3851.3871 | H14: =SUM(F14) -> 179 | I14: =H14*$B$4 -> 3851.3871 | J14: =SUM(H14) -> 179 | K14: =J14*$B$4 -> 3851.3871 | L14: =SUM(J14) -> 179 | M14: =L14*$B$4 -> 3851.3871 | N14: =SUM(L14) -> 179 | O14: =N14*$B$4 -> 3851.3871 | P14: =SUM(N14) -> 179 | Q14: =P14*$B$4 -> 3851.3871 | R14: =SUM(P14) -> 179 | S14: =R14*$B$4 -> 3851.3871 | T14: =SUM(R14) -> 179 | U14: =T14*$B$4 -> 3851.3871 | V14: =SUM(T14) -> 179 | W14: =V14*$B$4 -> 3851.3871 | X14: =SUM(Y14/73370) -> 0.57741935 | Y14: =SUM(C14+E14+G14+I14+K14+M14+O14+Q14+S14+U14+W14) -> 42365.258 | Z14: ='B5'!C13 -> 162 | AA14: =SUM(Z14*$Z$4) -> 1620 | AB14: =SUM(Z14) -> 162 | AC14: =SUM(AB14*$Z$4) -> 1620 | AD14: =SUM(AB14) -> 162 | AE14: =SUM(AD14*$Z$4) -> 1620 | AF14: =SUM(AD14) -> 162 | AG14: =SUM(AF14*$Z$4) -> 1620 | AH14: =SUM(AF14) -> 162 | AI14: =SUM(AH14*$Z$4) -> 1620 | AJ14: =SUM(AH14) -> 162 | AK14: =SUM(AJ14*$Z$4) -> 1620 | AL14: =SUM(AJ14) -> 162 | AM14: =SUM(AL14*$Z$4) -> 1620 | AN14: =SUM(AO14/19600) -> 0.57857143 | AO14: =SUM(AA14+AC14+AE14+AG14+AI14+AK14+AM14) -> 11340 | AQ14: =SUM(AR14/92970) -> 0.57766224 | AR14: =SUM(AO14+Y14) -> 53705.258 | AS14: =SUM(AR14-AR13-AT14) -> -4135.0645 | AT14: 15792 | AU14: 0.5765 | AV14: =IF(AT14>0,AU14,AV13) -> 0.5765 | AW14: =-SUM('B5'!AI13) -> -853 | AX14: =-SUM(AW14-AS14) -> -3282.0645 | AY14: =SUM(AX14+AW14) -> -4135.0645 | AZ14: =ELEC!A11 -> 0.2087 | BA14: ='General information '!D14 -> 12.5 | BB14: =SUM('General information '!E14) -> 0.6 | BC14: =IF(AR13>=AR14,0,1) -> 1 | BD14: 19222 | BE14: =(305/1185)*ELEC!Q12 -> 621.32489 | BG14: =#REF!-BE14 -> #REF!
A15: =ELEC!C12 -> 43840 | B15: ='B5'!B14 -> 168 | C15: =B15*$B$4 -> 3614.7097 | D15: =SUM(B15) -> 168 | E15: =D15*$B$4 -> 3614.7097 | F15: =SUM(D15) -> 168 | G15: =F15*$B$4 -> 3614.7097 | H15: =SUM(F15) -> 168 | I15: =H15*$B$4 -> 3614.7097 | J15: =SUM(H15) -> 168 | K15: =J15*$B$4 -> 3614.7097 | L15: =SUM(J15) -> 168 | M15: =L15*$B$4 -> 3614.7097 | N15: =SUM(L15) -> 168 | O15: =N15*$B$4 -> 3614.7097 | P15: =SUM(N15) -> 168 | Q15: =P15*$B$4 -> 3614.7097 | R15: =SUM(P15) -> 168 | S15: =R15*$B$4 -> 3614.7097 | T15: =SUM(R15) -> 168 | U15: =T15*$B$4 -> 3614.7097 | V15: =SUM(T15) -> 168 | W15: =V15*$B$4 -> 3614.7097 | X15: =SUM(Y15/73370) -> 0.54193548 | Y15: =SUM(C15+E15+G15+I15+K15+M15+O15+Q15+S15+U15+W15) -> 39761.806 | Z15: ='B5'!C14 -> 174 | AA15: =SUM(Z15*$Z$4) -> 1740 | AB15: =SUM(Z15) -> 174 | AC15: =SUM(AB15*$Z$4) -> 1740 | AD15: =SUM(AB15) -> 174 | AE15: =SUM(AD15*$Z$4) -> 1740 | AF15: =SUM(AD15) -> 174 | AG15: =SUM(AF15*$Z$4) -> 1740 | AH15: =SUM(AF15) -> 174 | AI15: =SUM(AH15*$Z$4) -> 1740 | AJ15: =SUM(AH15) -> 174 | AK15: =SUM(AJ15*$Z$4) -> 1740 | AL15: =SUM(AJ15) -> 174 | AM15: =SUM(AL15*$Z$4) -> 1740 | AN15: =SUM(AO15/19600) -> 0.62142857 | AO15: =SUM(AA15+AC15+AE15+AG15+AI15+AK15+AM15) -> 12180 | AQ15: =SUM(AR15/92970) -> 0.55869427 | AR15: =SUM(AO15+Y15) -> 51941.806 | AS15: =SUM(AR15-AR14-AT15) -> -1763.4516 | AV15: =IF(AT15>0,AU15,AV14) -> 0.5765 | AW15: =-SUM('B5'!AI14) -> -1461.8 | AX15: =-SUM(AW15-AS15) -> -301.65161 | AY15: =SUM(AX15+AW15) -> -1763.4516 | AZ15: =ELEC!A12 -> 0.2 | BA15: ='General information '!D15 -> 14.5 | BB15: =SUM('General information '!E15) -> 0.5 | BC15: =IF(AR14>=AR15,0,1) -> 0 | BD15: 19222 | BE15: =(305/1185)*ELEC!Q13 -> 422.88186 | BG15: =#REF!-BE15 -> #REF!
A16: =ELEC!C13 -> 43841 | B16: ='B5'!B15 -> 162 | C16: =B16*$B$4 -> 3485.6129 | D16: =SUM(B16) -> 162 | E16: =D16*$B$4 -> 3485.6129 | F16: =SUM(D16) -> 162 | G16: =F16*$B$4 -> 3485.6129 | H16: =SUM(F16) -> 162 | I16: =H16*$B$4 -> 3485.6129 | J16: =SUM(H16) -> 162 | K16: =J16*$B$4 -> 3485.6129 | L16: =SUM(J16) -> 162 | M16: =L16*$B$4 -> 3485.6129 | N16: =SUM(L16) -> 162 | O16: =N16*$B$4 -> 3485.6129 | P16: =SUM(N16) -> 162 | Q16: =P16*$B$4 -> 3485.6129 | R16: =SUM(P16) -> 162 | S16: =R16*$B$4 -> 3485.6129 | T16: =SUM(R16) -> 162 | U16: =T16*$B$4 -> 3485.6129 | V16: =SUM(T16) -> 162 | W16: =V16*$B$4 -> 3485.6129 | X16: =SUM(Y16/73370) -> 0.52258065 | Y16: =SUM(C16+E16+G16+I16+K16+M16+O16+Q16+S16+U16+W16) -> 38341.742 | Z16: ='B5'!C15 -> 168 | AA16: =SUM(Z16*$Z$4) -> 1680 | AB16: =SUM(Z16) -> 168 | AC16: =SUM(AB16*$Z$4) -> 1680 | AD16: =SUM(AB16) -> 168 | AE16: =SUM(AD16*$Z$4) -> 1680 | AF16: =SUM(AD16) -> 168 | AG16: =SUM(AF16*$Z$4) -> 1680 | AH16: =SUM(AF16) -> 168 | AI16: =SUM(AH16*$Z$4) -> 1680 | AJ16: =SUM(AH16) -> 168 | AK16: =SUM(AJ16*$Z$4) -> 1680 | AL16: =SUM(AJ16) -> 168 | AM16: =SUM(AL16*$Z$4) -> 1680 | AN16: =SUM(AO16/19600) -> 0.6 | AO16: =SUM(AA16+AC16+AE16+AG16+AI16+AK16+AM16) -> 11760 | AQ16: =SUM(AR16/92970) -> 0.53890225 | AR16: =SUM(AO16+Y16) -> 50101.742 | AS16: =SUM(AR16-AR15-AT16) -> -1840.0645 | AV16: =IF(AT16>0,AU16,AV15) -> 0.5765 | AW16: =-SUM('B5'!AI15) -> -728 | AX16: =-SUM(AW16-AS16) -> -1112.0645 | AY16: =SUM(AX16+AW16) -> -1840.0645 | AZ16: =ELEC!A13 -> 0.1696 | BA16: ='General information '!D16 -> 15 | BB16: =SUM('General information '!E16) -> 0.5 | BC16: =IF(AR15>=AR16,0,1) -> 0 | BD16: 19222 | BE16: =(305/1185)*ELEC!Q14 -> 544.88186 | BG16: =#REF!-BE16 -> #REF!
A17: =ELEC!C14 -> 43842 | B17: ='B5'!B16 -> 158 | C17: =B17*$B$4 -> 3399.5484 | D17: =SUM(B17) -> 158 | E17: =D17*$B$4 -> 3399.5484 | F17: =SUM(D17) -> 158 | G17: =F17*$B$4 -> 3399.5484 | H17: =SUM(F17) -> 158 | I17: =H17*$B$4 -> 3399.5484 | J17: =SUM(H17) -> 158 | K17: =J17*$B$4 -> 3399.5484 | L17: =SUM(J17) -> 158 | M17: =L17*$B$4 -> 3399.5484 | N17: =SUM(L17) -> 158 | O17: =N17*$B$4 -> 3399.5484 | P17: =SUM(N17) -> 158 | Q17: =P17*$B$4 -> 3399.5484 | R17: =SUM(P17) -> 158 | S17: =R17*$B$4 -> 3399.5484 | T17: =SUM(R17) -> 158 | U17: =T17*$B$4 -> 3399.5484 | V17: =SUM(T17) -> 158 | W17: =V17*$B$4 -> 3399.5484 | X17: =SUM(Y17/73370) -> 0.50967742 | Y17: =SUM(C17+E17+G17+I17+K17+M17+O17+Q17+S17+U17+W17) -> 37395.032 | Z17: ='B5'!C16 -> 163 | AA17: =SUM(Z17*$Z$4) -> 1630 | AB17: =SUM(Z17) -> 163 | AC17: =SUM(AB17*$Z$4) -> 1630 | AD17: =SUM(AB17) -> 163 | AE17: =SUM(AD17*$Z$4) -> 1630 | AF17: =SUM(AD17) -> 163 | AG17: =SUM(AF17*$Z$4) -> 1630 | AH17: =SUM(AF17) -> 163 | AI17: =SUM(AH17*$Z$4) -> 1630 | AJ17: =SUM(AH17) -> 163 | AK17: =SUM(AJ17*$Z$4) -> 1630 | AL17: =SUM(AJ17) -> 163 | AM17: =SUM(AL17*$Z$4) -> 1630 | AN17: =SUM(AO17/19600) -> 0.58214286 | AO17: =SUM(AA17+AC17+AE17+AG17+AI17+AK17+AM17) -> 11410 | AQ17: =SUM(AR17/92970) -> 0.52495463 | AR17: =SUM(AO17+Y17) -> 48805.032 | AS17: =SUM(AR17-AR16-AT17) -> -1296.7097 | AV17: =IF(AT17>0,AU17,AV16) -> 0.5765 | AW17: =-SUM('B5'!AI16) -> -543 | AX17: =-SUM(AW17-AS17) -> -753.70968 | AY17: =SUM(AX17+AW17) -> -1296.7097 | AZ17: =ELEC!A14 -> 0.1739 | BA17: ='General information '!D17 -> 14 | BB17: =SUM('General information '!E17) -> 0.55 | BC17: =IF(AR16>=AR17,0,1) -> 0 | BD17: 19222 | BE17: =(305/1185)*ELEC!Q15 -> 594.81435 | BG17: =#REF!-BE17 -> #REF!
A18: =ELEC!C15 -> 43843 | B18: ='B5'!B17 -> 152 | C18: =B18*$B$4 -> 3270.4516 | D18: =SUM(B18) -> 152 | E18: =D18*$B$4 -> 3270.4516 | F18: =SUM(D18) -> 152 | G18: =F18*$B$4 -> 3270.4516 | H18: =SUM(F18) -> 152 | I18: =H18*$B$4 -> 3270.4516 | J18: =SUM(H18) -> 152 | K18: =J18*$B$4 -> 3270.4516 | L18: =SUM(J18) -> 152 | M18: =L18*$B$4 -> 3270.4516 | N18: =SUM(L18) -> 152 | O18: =N18*$B$4 -> 3270.4516 | P18: =SUM(N18) -> 152 | Q18: =P18*$B$4 -> 3270.4516 | R18: =SUM(P18) -> 152 | S18: =R18*$B$4 -> 3270.4516 | T18: =SUM(R18) -> 152 | U18: =T18*$B$4 -> 3270.4516 | V18: =SUM(T18) -> 152 | W18: =V18*$B$4 -> 3270.4516 | X18: =SUM(Y18/73370) -> 0.49032258 | Y18: =SUM(C18+E18+G18+I18+K18+M18+O18+Q18+S18+U18+W18) -> 35974.968 | Z18: ='B5'!C17 -> 159 | AA18: =SUM(Z18*$Z$4) -> 1590 | AB18: =SUM(Z18) -> 159 | AC18: =SUM(AB18*$Z$4) -> 1590 | AD18: =SUM(AB18) -> 159 | AE18: =SUM(AD18*$Z$4) -> 1590 | AF18: =SUM(AD18) -> 159 | AG18: =SUM(AF18*$Z$4) -> 1590 | AH18: =SUM(AF18) -> 159 | AI18: =SUM(AH18*$Z$4) -> 1590 | AJ18: =SUM(AH18) -> 159 | AK18: =SUM(AJ18*$Z$4) -> 1590 | AL18: =SUM(AJ18) -> 159 | AM18: =SUM(AL18*$Z$4) -> 1590 | AN18: =SUM(AO18/19600) -> 0.56785714 | AO18: =SUM(AA18+AC18+AE18+AG18+AI18+AK18+AM18) -> 11130 | AQ18: =SUM(AR18/92970) -> 0.50666847 | AR18: =SUM(AO18+Y18) -> 47104.968 | AS18: =SUM(AR18-AR17-AT18) -> -1700.0645 | AV18: =IF(AT18>0,AU18,AV17) -> 0.5765 | AW18: =-SUM('B5'!AI17) -> -749 | AX18: =-SUM(AW18-AS18) -> -951.06452 | AY18: =SUM(AX18+AW18) -> -1700.0645 | AZ18: =ELEC!A15 -> 0.1826 | BA18: ='General information '!D18 -> 15 | BB18: =SUM('General information '!E18) -> 0.55 | BC18: =IF(AR17>=AR18,0,1) -> 0 | BD18: 19222 | BE18: =(305/1185)*ELEC!Q16 -> 721.70464 | BG18: =#REF!-BE18 -> #REF!
A19: =ELEC!C16 -> 43844 | B19: ='B5'!B18 -> 208 | C19: =B19*$B$4 -> 4475.3548 | D19: =SUM(B19) -> 208 | E19: =D19*$B$4 -> 4475.3548 | F19: =SUM(D19) -> 208 | G19: =F19*$B$4 -> 4475.3548 | H19: =SUM(F19) -> 208 | I19: =H19*$B$4 -> 4475.3548 | J19: =SUM(H19) -> 208 | K19: =J19*$B$4 -> 4475.3548 | L19: =SUM(J19) -> 208 | M19: =L19*$B$4 -> 4475.3548 | N19: =SUM(L19) -> 208 | O19: =N19*$B$4 -> 4475.3548 | P19: =SUM(N19) -> 208 | Q19: =P19*$B$4 -> 4475.3548 | R19: =SUM(P19) -> 208 | S19: =R19*$B$4 -> 4475.3548 | T19: =SUM(R19) -> 208 | U19: =T19*$B$4 -> 4475.3548 | V19: =SUM(T19) -> 208 | W19: =V19*$B$4 -> 4475.3548 | X19: =SUM(Y19/73370) -> 0.67096774 | Y19: =SUM(C19+E19+G19+I19+K19+M19+O19+Q19+S19+U19+W19) -> 49228.903 | Z19: ='B5'!C18 -> 214 | AA19: =SUM(Z19*$Z$4) -> 2140 | AB19: =SUM(Z19) -> 214 | AC19: =SUM(AB19*$Z$4) -> 2140 | AD19: =SUM(AB19) -> 214 | AE19: =SUM(AD19*$Z$4) -> 2140 | AF19: =SUM(AD19) -> 214 | AG19: =SUM(AF19*$Z$4) -> 2140 | AH19: =SUM(AF19) -> 214 | AI19: =SUM(AH19*$Z$4) -> 2140 | AJ19: =SUM(AH19) -> 214 | AK19: =SUM(AJ19*$Z$4) -> 2140 | AL19: =SUM(AJ19) -> 214 | AM19: =SUM(AL19*$Z$4) -> 2140 | AN19: =SUM(AO19/19600) -> 0.76428571 | AO19: =SUM(AA19+AC19+AE19+AG19+AI19+AK19+AM19) -> 14980 | AQ19: =SUM(AR19/92970) -> 0.6906411 | AR19: =SUM(AO19+Y19) -> 64208.903 | AS19: =SUM(AR19-AR18-AT19) -> 1179.9355 | AT19: 15924 | AU19: 0.5765 | AV19: =IF(AT19>0,AU19,AV18) -> 0.5765 | AW19: =-SUM('B5'!AI18) -> -886.6 | AX19: =-SUM(AW19-AS19) -> 2066.5355 | AY19: =SUM(AX19+AW19) -> 1179.9355 | AZ19: =ELEC!A16 -> 0.2087 | BA19: ='General information '!D19 -> 14 | BB19: =SUM('General information '!E19) -> 0.55 | BC19: =IF(AR18>=AR19,0,1) -> 1 | BD19: 19222 | BE19: =(305/1185)*ELEC!Q17 -> 681.03797 | BG19: =#REF!-BE19 -> #REF!
A20: =ELEC!C17 -> 43845 | B20: ='B5'!B19 -> 201 | C20: =B20*$B$4 -> 4324.7419 | D20: =SUM(B20) -> 201 | E20: =D20*$B$4 -> 4324.7419 | F20: =SUM(D20) -> 201 | G20: =F20*$B$4 -> 4324.7419 | H20: =SUM(F20) -> 201 | I20: =H20*$B$4 -> 4324.7419 | J20: =SUM(H20) -> 201 | K20: =J20*$B$4 -> 4324.7419 | L20: =SUM(J20) -> 201 | M20: =L20*$B$4 -> 4324.7419 | N20: =SUM(L20) -> 201 | O20: =N20*$B$4 -> 4324.7419 | P20: =SUM(N20) -> 201 | Q20: =P20*$B$4 -> 4324.7419 | R20: =SUM(P20) -> 201 | S20: =R20*$B$4 -> 4324.7419 | T20: =SUM(R20) -> 201 | U20: =T20*$B$4 -> 4324.7419 | V20: =SUM(T20) -> 201 | W20: =V20*$B$4 -> 4324.7419 | X20: =SUM(Y20/73370) -> 0.6483871 | Y20: =SUM(C20+E20+G20+I20+K20+M20+O20+Q20+S20+U20+W20) -> 47572.161 | Z20: ='B5'!C19 -> 207 | AA20: =SUM(Z20*$Z$4) -> 2070 | AB20: =SUM(Z20) -> 207 | AC20: =SUM(AB20*$Z$4) -> 2070 | AD20: =SUM(AB20) -> 207 | AE20: =SUM(AD20*$Z$4) -> 2070 | AF20: =SUM(AD20) -> 207 | AG20: =SUM(AF20*$Z$4) -> 2070 | AH20: =SUM(AF20) -> 207 | AI20: =SUM(AH20*$Z$4) -> 2070 | AJ20: =SUM(AH20) -> 207 | AK20: =SUM(AJ20*$Z$4) -> 2070 | AL20: =SUM(AJ20) -> 207 | AM20: =SUM(AL20*$Z$4) -> 2070 | AN20: =SUM(AO20/19600) -> 0.73928571 | AO20: =SUM(AA20+AC20+AE20+AG20+AI20+AK20+AM20) -> 14490 | AQ20: =SUM(AR20/92970) -> 0.66755041 | AR20: =SUM(AO20+Y20) -> 62062.161 | AS20: =SUM(AR20-AR19-AT20) -> -2146.7419 | AV20: =IF(AT20>0,AU20,AV19) -> 0.5765 | AW20: =-SUM('B5'!AI19) -> -762.6 | AX20: =-SUM(AW20-AS20) -> -1384.1419 | AY20: =SUM(AX20+AW20) -> -2146.7419 | AZ20: =ELEC!A17 -> 0.2261 | BA20: ='General information '!D20 -> 15 | BB20: =SUM('General information '!E20) -> 0.55 | BC20: =IF(AR19>=AR20,0,1) -> 0 | BD20: 19222 | BE20: =(305/1185)*ELEC!Q18 -> 1153.0802 | BG20: =#REF!-BE20 -> #REF!
A21: =ELEC!C18 -> 43846 | B21: ='B5'!B20 -> 223 | C21: =B21*$B$4 -> 4798.0968 | D21: =SUM(B21) -> 223 | E21: =D21*$B$4 -> 4798.0968 | F21: =SUM(D21) -> 223 | G21: =F21*$B$4 -> 4798.0968 | H21: =SUM(F21) -> 223 | I21: =H21*$B$4 -> 4798.0968 | J21: =SUM(H21) -> 223 | K21: =J21*$B$4 -> 4798.0968 | L21: =SUM(J21) -> 223 | M21: =L21*$B$4 -> 4798.0968 | N21: =SUM(L21) -> 223 | O21: =N21*$B$4 -> 4798.0968 | P21: =SUM(N21) -> 223 | Q21: =P21*$B$4 -> 4798.0968 | R21: =SUM(P21) -> 223 | S21: =R21*$B$4 -> 4798.0968 | T21: =SUM(R21) -> 223 | U21: =T21*$B$4 -> 4798.0968 | V21: =SUM(T21) -> 223 | W21: =V21*$B$4 -> 4798.0968 | X21: =SUM(Y21/73370) -> 0.71935484 | Y21: =SUM(C21+E21+G21+I21+K21+M21+O21+Q21+S21+U21+W21) -> 52779.065 | Z21: ='B5'!C20 -> 229 | AA21: =SUM(Z21*$Z$4) -> 2290 | AB21: =SUM(Z21) -> 229 | AC21: =SUM(AB21*$Z$4) -> 2290 | AD21: =SUM(AB21) -> 229 | AE21: =SUM(AD21*$Z$4) -> 2290 | AF21: =SUM(AD21) -> 229 | AG21: =SUM(AF21*$Z$4) -> 2290 | AH21: =SUM(AF21) -> 229 | AI21: =SUM(AH21*$Z$4) -> 2290 | AJ21: =SUM(AH21) -> 229 | AK21: =SUM(AJ21*$Z$4) -> 2290 | AL21: =SUM(AJ21) -> 229 | AM21: =SUM(AL21*$Z$4) -> 2290 | AN21: =SUM(AO21/19600) -> 0.81785714 | AO21: =SUM(AA21+AC21+AE21+AG21+AI21+AK21+AM21) -> 16030 | AQ21: =SUM(AR21/92970) -> 0.74012116 | AR21: =SUM(AO21+Y21) -> 68809.065 | AS21: =SUM(AR21-AR20-AT21) -> -1707.0968 | AT21: 8454 | AU21: 0.58 | AV21: =IF(AT21>0,AU21,AV20) -> 0.58 | AW21: =-SUM('B5'!AI20) -> -484 | AX21: =-SUM(AW21-AS21) -> -1223.0968 | AY21: =SUM(AX21+AW21) -> -1707.0968 | AZ21: =ELEC!A18 -> 0.2261 | BA21: ='General information '!D21 -> 16 | BB21: =SUM('General information '!E21) -> 0.6 | BC21: =IF(AR20>=AR21,0,1) -> 1 | BD21: 19222 | BE21: =(305/1185)*ELEC!Q19 -> 518.37131 | BG21: =#REF!-BE21 -> #REF!
A22: =ELEC!C19 -> 43847 | B22: ='B5'!B21 -> 219 | C22: =B22*$B$4 -> 4712.0323 | D22: =SUM(B22) -> 219 | E22: =D22*$B$4 -> 4712.0323 | F22: =SUM(D22) -> 219 | G22: =F22*$B$4 -> 4712.0323 | H22: =SUM(F22) -> 219 | I22: =H22*$B$4 -> 4712.0323 | J22: =SUM(H22) -> 219 | K22: =J22*$B$4 -> 4712.0323 | L22: =SUM(J22) -> 219 | M22: =L22*$B$4 -> 4712.0323 | N22: =SUM(L22) -> 219 | O22: =N22*$B$4 -> 4712.0323 | P22: =SUM(N22) -> 219 | Q22: =P22*$B$4 -> 4712.0323 | R22: =SUM(P22) -> 219 | S22: =R22*$B$4 -> 4712.0323 | T22: =SUM(R22) -> 219 | U22: =T22*$B$4 -> 4712.0323 | V22: =SUM(T22) -> 219 | W22: =V22*$B$4 -> 4712.0323 | X22: =SUM(Y22/73370) -> 0.70645161 | Y22: =SUM(C22+E22+G22+I22+K22+M22+O22+Q22+S22+U22+W22) -> 51832.355 | Z22: ='B5'!C21 -> 225 | AA22: =SUM(Z22*$Z$4) -> 2250 | AB22: =SUM(Z22) -> 225 | AC22: =SUM(AB22*$Z$4) -> 2250 | AD22: =SUM(AB22) -> 225 | AE22: =SUM(AD22*$Z$4) -> 2250 | AF22: =SUM(AD22) -> 225 | AG22: =SUM(AF22*$Z$4) -> 2250 | AH22: =SUM(AF22) -> 225 | AI22: =SUM(AH22*$Z$4) -> 2250 | AJ22: =SUM(AH22) -> 225 | AK22: =SUM(AJ22*$Z$4) -> 2250 | AL22: =SUM(AJ22) -> 225 | AM22: =SUM(AL22*$Z$4) -> 2250 | AN22: =SUM(AO22/19600) -> 0.80357143 | AO22: =SUM(AA22+AC22+AE22+AG22+AI22+AK22+AM22) -> 15750 | AQ22: =SUM(AR22/92970) -> 0.72692648 | AR22: =SUM(AO22+Y22) -> 67582.355 | AS22: =SUM(AR22-AR21-AT22) -> -1226.7097 | AV22: =IF(AT22>0,AU22,AV21) -> 0.58 | AW22: =-SUM('B5'!AI21) -> -1027.1 | AX22: =-SUM(AW22-AS22) -> -199.60968 | AY22: =SUM(AX22+AW22) -> -1226.7097 | AZ22: =ELEC!A19 -> 0.1739 | BA22: ='General information '!D22 -> 16.5 | BB22: =SUM('General information '!E22) -> 0.57 | BC22: =IF(AR21>=AR22,0,1) -> 0 | BD22: 19222 | BE22: =(305/1185)*ELEC!Q20 -> 0 | BG22: =#REF!-BE22 -> #REF!
A23: =ELEC!C20 -> 43848 | B23: ='B5'!B22 -> 219 | C23: =B23*$B$4 -> 4712.0323 | D23: =SUM(B23) -> 219 | E23: =D23*$B$4 -> 4712.0323 | F23: =SUM(D23) -> 219 | G23: =F23*$B$4 -> 4712.0323 | H23: =SUM(F23) -> 219 | I23: =H23*$B$4 -> 4712.0323 | J23: =SUM(H23) -> 219 | K23: =J23*$B$4 -> 4712.0323 | L23: =SUM(J23) -> 219 | M23: =L23*$B$4 -> 4712.0323 | N23: =SUM(L23) -> 219 | O23: =N23*$B$4 -> 4712.0323 | P23: =SUM(N23) -> 219 | Q23: =P23*$B$4 -> 4712.0323 | R23: =SUM(P23) -> 219 | S23: =R23*$B$4 -> 4712.0323 | T23: =SUM(R23) -> 219 | U23: =T23*$B$4 -> 4712.0323 | V23: =SUM(T23) -> 219 | W23: =V23*$B$4 -> 4712.0323 | X23: =SUM(Y23/73370) -> 0.70645161 | Y23: =SUM(C23+E23+G23+I23+K23+M23+O23+Q23+S23+U23+W23) -> 51832.355 | Z23: ='B5'!C22 -> 225 | AA23: =SUM(Z23*$Z$4) -> 2250 | AB23: =SUM(Z23) -> 225 | AC23: =SUM(AB23*$Z$4) -> 2250 | AD23: =SUM(AB23) -> 225 | AE23: =SUM(AD23*$Z$4) -> 2250 | AF23: =SUM(AD23) -> 225 | AG23: =SUM(AF23*$Z$4) -> 2250 | AH23: =SUM(AF23) -> 225 | AI23: =SUM(AH23*$Z$4) -> 2250 | AJ23: =SUM(AH23) -> 225 | AK23: =SUM(AJ23*$Z$4) -> 2250 | AL23: =SUM(AJ23) -> 225 | AM23: =SUM(AL23*$Z$4) -> 2250 | AN23: =SUM(AO23/19600) -> 0.80357143 | AO23: =SUM(AA23+AC23+AE23+AG23+AI23+AK23+AM23) -> 15750 | AQ23: =SUM(AR23/92970) -> 0.72692648 | AR23: =SUM(AO23+Y23) -> 67582.355 | AS23: =SUM(AR23-AR22-AT23) -> 0 | AV23: =IF(AT23>0,AU23,AV22) -> 0.58 | AW23: =-SUM('B5'!AI22) -> 0 | AX23: =-SUM(AW23-AS23) -> 0 | AY23: =SUM(AX23+AW23) -> 0 | AZ23: =ELEC!A20 -> 0 | BA23: ='General information '!D23 -> 0 | BB23: =SUM('General information '!E23) -> 0 | BC23: =IF(AR22>=AR23,0,1) -> 0 | BD23: 19222 | BE23: =(305/1185)*ELEC!Q21 -> 0 | BG23: =#REF!-BE23 -> #REF!
A24: =ELEC!C21 -> 43849 | B24: ='B5'!B23 -> 219 | C24: =B24*$B$4 -> 4712.0323 | D24: =SUM(B24) -> 219 | E24: =D24*$B$4 -> 4712.0323 | F24: =SUM(D24) -> 219 | G24: =F24*$B$4 -> 4712.0323 | H24: =SUM(F24) -> 219 | I24: =H24*$B$4 -> 4712.0323 | J24: =SUM(H24) -> 219 | K24: =J24*$B$4 -> 4712.0323 | L24: =SUM(J24) -> 219 | M24: =L24*$B$4 -> 4712.0323 | N24: =SUM(L24) -> 219 | O24: =N24*$B$4 -> 4712.0323 | P24: =SUM(N24) -> 219 | Q24: =P24*$B$4 -> 4712.0323 | R24: =SUM(P24) -> 219 | S24: =R24*$B$4 -> 4712.0323 | T24: =SUM(R24) -> 219 | U24: =T24*$B$4 -> 4712.0323 | V24: =SUM(T24) -> 219 | W24: =V24*$B$4 -> 4712.0323 | X24: =SUM(Y24/73370) -> 0.70645161 | Y24: =SUM(C24+E24+G24+I24+K24+M24+O24+Q24+S24+U24+W24) -> 51832.355 | Z24: ='B5'!C23 -> 225 | AA24: =SUM(Z24*$Z$4) -> 2250 | AB24: =SUM(Z24) -> 225 | AC24: =SUM(AB24*$Z$4) -> 2250 | AD24: =SUM(AB24) -> 225 | AE24: =SUM(AD24*$Z$4) -> 2250 | AF24: =SUM(AD24) -> 225 | AG24: =SUM(AF24*$Z$4) -> 2250 | AH24: =SUM(AF24) -> 225 | AI24: =SUM(AH24*$Z$4) -> 2250 | AJ24: =SUM(AH24) -> 225 | AK24: =SUM(AJ24*$Z$4) -> 2250 | AL24: =SUM(AJ24) -> 225 | AM24: =SUM(AL24*$Z$4) -> 2250 | AN24: =SUM(AO24/19600) -> 0.80357143 | AO24: =SUM(AA24+AC24+AE24+AG24+AI24+AK24+AM24) -> 15750 | AQ24: =SUM(AR24/92970) -> 0.72692648 | AR24: =SUM(AO24+Y24) -> 67582.355 | AS24: =SUM(AR24-AR23-AT24) -> 0 | AV24: =IF(AT24>0,AU24,AV23) -> 0.58 | AW24: =-SUM('B5'!AI23) -> 0 | AX24: =-SUM(AW24-AS24) -> 0 | AY24: =SUM(AX24+AW24) -> 0 | AZ24: =ELEC!A21 -> 0 | BA24: ='General information '!D24 -> 0 | BB24: =SUM('General information '!E24) -> 0 | BC24: =IF(AR23>=AR24,0,1) -> 0 | BD24: 19222 | BE24: =(305/1185)*ELEC!Q22 -> 0 | BG24: =#REF!-BE24 -> #REF!
A25: =ELEC!C22 -> 43850 | B25: ='B5'!B24 -> 219 | C25: =B25*$B$4 -> 4712.0323 | D25: =SUM(B25) -> 219 | E25: =D25*$B$4 -> 4712.0323 | F25: =SUM(D25) -> 219 | G25: =F25*$B$4 -> 4712.0323 | H25: =SUM(F25) -> 219 | I25: =H25*$B$4 -> 4712.0323 | J25: =SUM(H25) -> 219 | K25: =J25*$B$4 -> 4712.0323 | L25: =SUM(J25) -> 219 | M25: =L25*$B$4 -> 4712.0323 | N25: =SUM(L25) -> 219 | O25: =N25*$B$4 -> 4712.0323 | P25: =SUM(N25) -> 219 | Q25: =P25*$B$4 -> 4712.0323 | R25: =SUM(P25) -> 219 | S25: =R25*$B$4 -> 4712.0323 | T25: =SUM(R25) -> 219 | U25: =T25*$B$4 -> 4712.0323 | V25: =SUM(T25) -> 219 | W25: =V25*$B$4 -> 4712.0323 | X25: =SUM(Y25/73370) -> 0.70645161 | Y25: =SUM(C25+E25+G25+I25+K25+M25+O25+Q25+S25+U25+W25) -> 51832.355 | Z25: ='B5'!C24 -> 225 | AA25: =SUM(Z25*$Z$4) -> 2250 | AB25: =SUM(Z25) -> 225 | AC25: =SUM(AB25*$Z$4) -> 2250 | AD25: =SUM(AB25) -> 225 | AE25: =SUM(AD25*$Z$4) -> 2250 | AF25: =SUM(AD25) -> 225 | AG25: =SUM(AF25*$Z$4) -> 2250 | AH25: =SUM(AF25) -> 225 | AI25: =SUM(AH25*$Z$4) -> 2250 | AJ25: =SUM(AH25) -> 225 | AK25: =SUM(AJ25*$Z$4) -> 2250 | AL25: =SUM(AJ25) -> 225 | AM25: =SUM(AL25*$Z$4) -> 2250 | AN25: =SUM(AO25/19600) -> 0.80357143 | AO25: =SUM(AA25+AC25+AE25+AG25+AI25+AK25+AM25) -> 15750 | AQ25: =SUM(AR25/92970) -> 0.72692648 | AR25: =SUM(AO25+Y25) -> 67582.355 | AS25: =SUM(AR25-AR24-AT25) -> 0 | AV25: =IF(AT25>0,AU25,AV24) -> 0.58 | AW25: =-SUM('B5'!AI24) -> 0 | AX25: =-SUM(AW25-AS25) -> 0 | AY25: =SUM(AX25+AW25) -> 0 | AZ25: =ELEC!A22 -> 0 | BA25: ='General information '!D25 -> 0 | BB25: =SUM('General information '!E25) -> 0 | BC25: =IF(AR24>=AR25,0,1) -> 0 | BD25: 19222 | BE25: =(305/1185)*ELEC!Q23 -> 0 | BG25: =#REF!-BE25 -> #REF!
A26: =ELEC!C23 -> 43851 | B26: ='B5'!B25 -> 219 | C26: =B26*$B$4 -> 4712.0323 | D26: =SUM(B26) -> 219 | E26: =D26*$B$4 -> 4712.0323 | F26: =SUM(D26) -> 219 | G26: =F26*$B$4 -> 4712.0323 | H26: =SUM(F26) -> 219 | I26: =H26*$B$4 -> 4712.0323 | J26: =SUM(H26) -> 219 | K26: =J26*$B$4 -> 4712.0323 | L26: =SUM(J26) -> 219 | M26: =L26*$B$4 -> 4712.0323 | N26: =SUM(L26) -> 219 | O26: =N26*$B$4 -> 4712.0323 | P26: =SUM(N26) -> 219 | Q26: =P26*$B$4 -> 4712.0323 | R26: =SUM(P26) -> 219 | S26: =R26*$B$4 -> 4712.0323 | T26: =SUM(R26) -> 219 | U26: =T26*$B$4 -> 4712.0323 | V26: =SUM(T26) -> 219 | W26: =V26*$B$4 -> 4712.0323 | X26: =SUM(Y26/73370) -> 0.70645161 | Y26: =SUM(C26+E26+G26+I26+K26+M26+O26+Q26+S26+U26+W26) -> 51832.355 | Z26: ='B5'!C25 -> 225 | AA26: =SUM(Z26*$Z$4) -> 2250 | AB26: =SUM(Z26) -> 225 | AC26: =SUM(AB26*$Z$4) -> 2250 | AD26: =SUM(AB26) -> 225 | AE26: =SUM(AD26*$Z$4) -> 2250 | AF26: =SUM(AD26) -> 225 | AG26: =SUM(AF26*$Z$4) -> 2250 | AH26: =SUM(AF26) -> 225 | AI26: =SUM(AH26*$Z$4) -> 2250 | AJ26: =SUM(AH26) -> 225 | AK26: =SUM(AJ26*$Z$4) -> 2250 | AL26: =SUM(AJ26) -> 225 | AM26: =SUM(AL26*$Z$4) -> 2250 | AN26: =SUM(AO26/19600) -> 0.80357143 | AO26: =SUM(AA26+AC26+AE26+AG26+AI26+AK26+AM26) -> 15750 | AQ26: =SUM(AR26/92970) -> 0.72692648 | AR26: =SUM(AO26+Y26) -> 67582.355 | AS26: =SUM(AR26-AR25-AT26) -> 0 | AV26: =IF(AT26>0,AU26,AV25) -> 0.58 | AW26: =-SUM('B5'!AI25) -> 0 | AX26: =-SUM(AW26-AS26) -> 0 | AY26: =SUM(AX26+AW26) -> 0 | AZ26: =ELEC!A23 -> 0 | BA26: ='General information '!D26 -> 0 | BB26: =SUM('General information '!E26) -> 0 | BC26: =IF(AR25>=AR26,0,1) -> 0 | BD26: 19222 | BE26: =(305/1185)*ELEC!Q24 -> 0 | BG26: =#REF!-BE26 -> #REF!
A27: =ELEC!C24 -> 43852 | B27: ='B5'!B26 -> 219 | C27: =B27*$B$4 -> 4712.0323 | D27: =SUM(B27) -> 219 | E27: =D27*$B$4 -> 4712.0323 | F27: =SUM(D27) -> 219 | G27: =F27*$B$4 -> 4712.0323 | H27: =SUM(F27) -> 219 | I27: =H27*$B$4 -> 4712.0323 | J27: =SUM(H27) -> 219 | K27: =J27*$B$4 -> 4712.0323 | L27: =SUM(J27) -> 219 | M27: =L27*$B$4 -> 4712.0323 | N27: =SUM(L27) -> 219 | O27: =N27*$B$4 -> 4712.0323 | P27: =SUM(N27) -> 219 | Q27: =P27*$B$4 -> 4712.0323 | R27: =SUM(P27) -> 219 | S27: =R27*$B$4 -> 4712.0323 | T27: =SUM(R27) -> 219 | U27: =T27*$B$4 -> 4712.0323 | V27: =SUM(T27) -> 219 | W27: =V27*$B$4 -> 4712.0323 | X27: =SUM(Y27/73370) -> 0.70645161 | Y27: =SUM(C27+E27+G27+I27+K27+M27+O27+Q27+S27+U27+W27) -> 51832.355 | Z27: ='B5'!C26 -> 225 | AA27: =SUM(Z27*$Z$4) -> 2250 | AB27: =SUM(Z27) -> 225 | AC27: =SUM(AB27*$Z$4) -> 2250 | AD27: =SUM(AB27) -> 225 | AE27: =SUM(AD27*$Z$4) -> 2250 | AF27: =SUM(AD27) -> 225 | AG27: =SUM(AF27*$Z$4) -> 2250 | AH27: =SUM(AF27) -> 225 | AI27: =SUM(AH27*$Z$4) -> 2250 | AJ27: =SUM(AH27) -> 225 | AK27: =SUM(AJ27*$Z$4) -> 2250 | AL27: =SUM(AJ27) -> 225 | AM27: =SUM(AL27*$Z$4) -> 2250 | AN27: =SUM(AO27/19600) -> 0.80357143 | AO27: =SUM(AA27+AC27+AE27+AG27+AI27+AK27+AM27) -> 15750 | AQ27: =SUM(AR27/92970) -> 0.72692648 | AR27: =SUM(AO27+Y27) -> 67582.355 | AS27: =SUM(AR27-AR26-AT27) -> 0 | AV27: =IF(AT27>0,AU27,AV26) -> 0.58 | AW27: =-SUM('B5'!AI26) -> 0 | AX27: =-SUM(AW27-AS27) -> 0 | AY27: =SUM(AX27+AW27) -> 0 | AZ27: =ELEC!A24 -> 0 | BA27: ='General information '!D27 -> 0 | BB27: =SUM('General information '!E27) -> 0 | BC27: =IF(AR26>=AR27,0,1) -> 0 | BD27: 19222 | BE27: =(305/1185)*ELEC!Q25 -> 0 | BG27: =#REF!-BE27 -> #REF!
A28: =ELEC!C25 -> 43853 | B28: ='B5'!B27 -> 219 | C28: =B28*$B$4 -> 4712.0323 | D28: =SUM(B28) -> 219 | E28: =D28*$B$4 -> 4712.0323 | F28: =SUM(D28) -> 219 | G28: =F28*$B$4 -> 4712.0323 | H28: =SUM(F28) -> 219 | I28: =H28*$B$4 -> 4712.0323 | J28: =SUM(H28) -> 219 | K28: =J28*$B$4 -> 4712.0323 | L28: =SUM(J28) -> 219 | M28: =L28*$B$4 -> 4712.0323 | N28: =SUM(L28) -> 219 | O28: =N28*$B$4 -> 4712.0323 | P28: =SUM(N28) -> 219 | Q28: =P28*$B$4 -> 4712.0323 | R28: =SUM(P28) -> 219 | S28: =R28*$B$4 -> 4712.0323 | T28: =SUM(R28) -> 219 | U28: =T28*$B$4 -> 4712.0323 | V28: =SUM(T28) -> 219 | W28: =V28*$B$4 -> 4712.0323 | X28: =SUM(Y28/73370) -> 0.70645161 | Y28: =SUM(C28+E28+G28+I28+K28+M28+O28+Q28+S28+U28+W28) -> 51832.355 | Z28: ='B5'!C27 -> 225 | AA28: =SUM(Z28*$Z$4) -> 2250 | AB28: =SUM(Z28) -> 225 | AC28: =SUM(AB28*$Z$4) -> 2250 | AD28: =SUM(AB28) -> 225 | AE28: =SUM(AD28*$Z$4) -> 2250 | AF28: =SUM(AD28) -> 225 | AG28: =SUM(AF28*$Z$4) -> 2250 | AH28: =SUM(AF28) -> 225 | AI28: =SUM(AH28*$Z$4) -> 2250 | AJ28: =SUM(AH28) -> 225 | AK28: =SUM(AJ28*$Z$4) -> 2250 | AL28: =SUM(AJ28) -> 225 | AM28: =SUM(AL28*$Z$4) -> 2250 | AN28: =SUM(AO28/19600) -> 0.80357143 | AO28: =SUM(AA28+AC28+AE28+AG28+AI28+AK28+AM28) -> 15750 | AQ28: =SUM(AR28/92970) -> 0.72692648 | AR28: =SUM(AO28+Y28) -> 67582.355 | AS28: =SUM(AR28-AR27-AT28) -> 0 | AV28: =IF(AT28>0,AU28,AV27) -> 0.58 | AW28: =-SUM('B5'!AI27) -> 0 | AX28: =-SUM(AW28-AS28) -> 0 | AY28: =SUM(AX28+AW28) -> 0 | AZ28: =ELEC!A25 -> 0 | BA28: ='General information '!D28 -> 0 | BB28: =SUM('General information '!E28) -> 0 | BC28: =IF(AR27>=AR28,0,1) -> 0 | BD28: 19222 | BE28: =(305/1185)*ELEC!Q26 -> 0 | BG28: =#REF!-BE28 -> #REF!
A29: =ELEC!C26 -> 43854 | B29: ='B5'!B28 -> 219 | C29: =B29*$B$4 -> 4712.0323 | D29: =SUM(B29) -> 219 | E29: =D29*$B$4 -> 4712.0323 | F29: =SUM(D29) -> 219 | G29: =F29*$B$4 -> 4712.0323 | H29: =SUM(F29) -> 219 | I29: =H29*$B$4 -> 4712.0323 | J29: =SUM(H29) -> 219 | K29: =J29*$B$4 -> 4712.0323 | L29: =SUM(J29) -> 219 | M29: =L29*$B$4 -> 4712.0323 | N29: =SUM(L29) -> 219 | O29: =N29*$B$4 -> 4712.0323 | P29: =SUM(N29) -> 219 | Q29: =P29*$B$4 -> 4712.0323 | R29: =SUM(P29) -> 219 | S29: =R29*$B$4 -> 4712.0323 | T29: =SUM(R29) -> 219 | U29: =T29*$B$4 -> 4712.0323 | V29: =SUM(T29) -> 219 | W29: =V29*$B$4 -> 4712.0323 | X29: =SUM(Y29/73370) -> 0.70645161 | Y29: =SUM(C29+E29+G29+I29+K29+M29+O29+Q29+S29+U29+W29) -> 51832.355 | Z29: ='B5'!C28 -> 225 | AA29: =SUM(Z29*$Z$4) -> 2250 | AB29: =SUM(Z29) -> 225 | AC29: =SUM(AB29*$Z$4) -> 2250 | AD29: =SUM(AB29) -> 225 | AE29: =SUM(AD29*$Z$4) -> 2250 | AF29: =SUM(AD29) -> 225 | AG29: =SUM(AF29*$Z$4) -> 2250 | AH29: =SUM(AF29) -> 225 | AI29: =SUM(AH29*$Z$4) -> 2250 | AJ29: =SUM(AH29) -> 225 | AK29: =SUM(AJ29*$Z$4) -> 2250 | AL29: =SUM(AJ29) -> 225 | AM29: =SUM(AL29*$Z$4) -> 2250 | AN29: =SUM(AO29/19600) -> 0.80357143 | AO29: =SUM(AA29+AC29+AE29+AG29+AI29+AK29+AM29) -> 15750 | AQ29: =SUM(AR29/92970) -> 0.72692648 | AR29: =SUM(AO29+Y29) -> 67582.355 | AS29: =SUM(AR29-AR28-AT29) -> 0 | AV29: =IF(AT29>0,AU29,AV28) -> 0.58 | AW29: =-SUM('B5'!AI28) -> 0 | AX29: =-SUM(AW29-AS29) -> 0 | AY29: =SUM(AX29+AW29) -> 0 | AZ29: =ELEC!A26 -> 0 | BA29: ='General information '!D29 -> 0 | BB29: =SUM('General information '!E29) -> 0 | BC29: =IF(AR28>=AR29,0,1) -> 0 | BD29: 19222 | BE29: =(305/1185)*ELEC!Q27 -> 0 | BG29: =#REF!-BE29 -> #REF!
A30: =ELEC!C27 -> 43855 | B30: ='B5'!B29 -> 219 | C30: =B30*$B$4 -> 4712.0323 | D30: =SUM(B30) -> 219 | E30: =D30*$B$4 -> 4712.0323 | F30: =SUM(D30) -> 219 | G30: =F30*$B$4 -> 4712.0323 | H30: =SUM(F30) -> 219 | I30: =H30*$B$4 -> 4712.0323 | J30: =SUM(H30) -> 219 | K30: =J30*$B$4 -> 4712.0323 | L30: =SUM(J30) -> 219 | M30: =L30*$B$4 -> 4712.0323 | N30: =SUM(L30) -> 219 | O30: =N30*$B$4 -> 4712.0323 | P30: =SUM(N30) -> 219 | Q30: =P30*$B$4 -> 4712.0323 | R30: =SUM(P30) -> 219 | S30: =R30*$B$4 -> 4712.0323 | T30: =SUM(R30) -> 219 | U30: =T30*$B$4 -> 4712.0323 | V30: =SUM(T30) -> 219 | W30: =V30*$B$4 -> 4712.0323 | X30: =SUM(Y30/73370) -> 0.70645161 | Y30: =SUM(C30+E30+G30+I30+K30+M30+O30+Q30+S30+U30+W30) -> 51832.355 | Z30: ='B5'!C29 -> 225 | AA30: =SUM(Z30*$Z$4) -> 2250 | AB30: =SUM(Z30) -> 225 | AC30: =SUM(AB30*$Z$4) -> 2250 | AD30: =SUM(AB30) -> 225 | AE30: =SUM(AD30*$Z$4) -> 2250 | AF30: =SUM(AD30) -> 225 | AG30: =SUM(AF30*$Z$4) -> 2250 | AH30: =SUM(AF30) -> 225 | AI30: =SUM(AH30*$Z$4) -> 2250 | AJ30: =SUM(AH30) -> 225 | AK30: =SUM(AJ30*$Z$4) -> 2250 | AL30: =SUM(AJ30) -> 225 | AM30: =SUM(AL30*$Z$4) -> 2250 | AN30: =SUM(AO30/19600) -> 0.80357143 | AO30: =SUM(AA30+AC30+AE30+AG30+AI30+AK30+AM30) -> 15750 | AQ30: =SUM(AR30/92970) -> 0.72692648 | AR30: =SUM(AO30+Y30) -> 67582.355 | AS30: =SUM(AR30-AR29-AT30) -> 0 | AV30: =IF(AT30>0,AU30,AV29) -> 0.58 | AW30: =-SUM('B5'!AI29) -> 0 | AX30: =-SUM(AW30-AS30) -> 0 | AY30: =SUM(AX30+AW30) -> 0 | AZ30: =ELEC!A27 -> 0 | BA30: ='General information '!D30 -> 0 | BB30: =SUM('General information '!E30) -> 0 | BC30: =IF(AR29>=AR30,0,1) -> 0 | BD30: 19222 | BE30: =(305/1185)*ELEC!Q28 -> 0 | BG30: =#REF!-BE30 -> #REF!
A31: =ELEC!C28 -> 43856 | B31: ='B5'!B30 -> 219 | C31: =B31*$B$4 -> 4712.0323 | D31: =SUM(B31) -> 219 | E31: =D31*$B$4 -> 4712.0323 | F31: =SUM(D31) -> 219 | G31: =F31*$B$4 -> 4712.0323 | H31: =SUM(F31) -> 219 | I31: =H31*$B$4 -> 4712.0323 | J31: =SUM(H31) -> 219 | K31: =J31*$B$4 -> 4712.0323 | L31: =SUM(J31) -> 219 | M31: =L31*$B$4 -> 4712.0323 | N31: =SUM(L31) -> 219 | O31: =N31*$B$4 -> 4712.0323 | P31: =SUM(N31) -> 219 | Q31: =P31*$B$4 -> 4712.0323 | R31: =SUM(P31) -> 219 | S31: =R31*$B$4 -> 4712.0323 | T31: =SUM(R31) -> 219 | U31: =T31*$B$4 -> 4712.0323 | V31: =SUM(T31) -> 219 | W31: =V31*$B$4 -> 4712.0323 | X31: =SUM(Y31/73370) -> 0.70645161 | Y31: =SUM(C31+E31+G31+I31+K31+M31+O31+Q31+S31+U31+W31) -> 51832.355 | Z31: ='B5'!C30 -> 225 | AA31: =SUM(Z31*$Z$4) -> 2250 | AB31: =SUM(Z31) -> 225 | AC31: =SUM(AB31*$Z$4) -> 2250 | AD31: =SUM(AB31) -> 225 | AE31: =SUM(AD31*$Z$4) -> 2250 | AF31: =SUM(AD31) -> 225 | AG31: =SUM(AF31*$Z$4) -> 2250 | AH31: =SUM(AF31) -> 225 | AI31: =SUM(AH31*$Z$4) -> 2250 | AJ31: =SUM(AH31) -> 225 | AK31: =SUM(AJ31*$Z$4) -> 2250 | AL31: =SUM(AJ31) -> 225 | AM31: =SUM(AL31*$Z$4) -> 2250 | AN31: =SUM(AO31/19600) -> 0.80357143 | AO31: =SUM(AA31+AC31+AE31+AG31+AI31+AK31+AM31) -> 15750 | AQ31: =SUM(AR31/92970) -> 0.72692648 | AR31: =SUM(AO31+Y31) -> 67582.355 | AS31: =SUM(AR31-AR30-AT31) -> 0 | AV31: =IF(AT31>0,AU31,AV30) -> 0.58 | AW31: =-SUM('B5'!AI30) -> 0 | AX31: =-SUM(AW31-AS31) -> 0 | AY31: =SUM(AX31+AW31) -> 0 | AZ31: =ELEC!A28 -> 0 | BA31: ='General information '!D31 -> 0 | BB31: =SUM('General information '!E32) -> 0 | BC31: =IF(AR30>=AR31,0,1) -> 0 | BD31: 19222 | BE31: =(305/1185)*ELEC!Q29 -> 0 | BG31: =#REF!-BE31 -> #REF!
A32: =ELEC!C29 -> 43857 | B32: ='B5'!B31 -> 219 | C32: =B32*$B$4 -> 4712.0323 | D32: =SUM(B32) -> 219 | E32: =D32*$B$4 -> 4712.0323 | F32: =SUM(D32) -> 219 | G32: =F32*$B$4 -> 4712.0323 | H32: =SUM(F32) -> 219 | I32: =H32*$B$4 -> 4712.0323 | J32: =SUM(H32) -> 219 | K32: =J32*$B$4 -> 4712.0323 | L32: =SUM(J32) -> 219 | M32: =L32*$B$4 -> 4712.0323 | N32: =SUM(L32) -> 219 | O32: =N32*$B$4 -> 4712.0323 | P32: =SUM(N32) -> 219 | Q32: =P32*$B$4 -> 4712.0323 | R32: =SUM(P32) -> 219 | S32: =R32*$B$4 -> 4712.0323 | T32: =SUM(R32) -> 219 | U32: =T32*$B$4 -> 4712.0323 | V32: =SUM(T32) -> 219 | W32: =V32*$B$4 -> 4712.0323 | X32: =SUM(Y32/73370) -> 0.70645161 | Y32: =SUM(C32+E32+G32+I32+K32+M32+O32+Q32+S32+U32+W32) -> 51832.355 | Z32: ='B5'!C31 -> 225 | AA32: =SUM(Z32*$Z$4) -> 2250 | AB32: =SUM(Z32) -> 225 | AC32: =SUM(AB32*$Z$4) -> 2250 | AD32: =SUM(AB32) -> 225 | AE32: =SUM(AD32*$Z$4) -> 2250 | AF32: =SUM(AD32) -> 225 | AG32: =SUM(AF32*$Z$4) -> 2250 | AH32: =SUM(AF32) -> 225 | AI32: =SUM(AH32*$Z$4) -> 2250 | AJ32: =SUM(AH32) -> 225 | AK32: =SUM(AJ32*$Z$4) -> 2250 | AL32: =SUM(AJ32) -> 225 | AM32: =SUM(AL32*$Z$4) -> 2250 | AN32: =SUM(AO32/19600) -> 0.80357143 | AO32: =SUM(AA32+AC32+AE32+AG32+AI32+AK32+AM32) -> 15750 | AQ32: =SUM(AR32/92970) -> 0.72692648 | AR32: =SUM(AO32+Y32) -> 67582.355 | AS32: =SUM(AR32-AR31-AT32) -> 0 | AV32: =IF(AT32>0,AU32,AV31) -> 0.58 | AW32: =-SUM('B5'!AI31) -> 0 | AX32: =-SUM(AW32-AS32) -> 0 | AY32: =SUM(AX32+AW32) -> 0 | AZ32: =ELEC!A29 -> 0 | BA32: ='General information '!D32 -> 0 | BB32: =SUM('General information '!E33) -> 0 | BC32: =IF(AR31>=AR32,0,1) -> 0 | BD32: 19222 | BE32: =(305/1185)*ELEC!Q30 -> 0 | BG32: =#REF!-BE32 -> #REF!
A33: =ELEC!C30 -> 43858 | B33: ='B5'!B32 -> 219 | C33: =B33*$B$4 -> 4712.0323 | D33: =SUM(B33) -> 219 | E33: =D33*$B$4 -> 4712.0323 | F33: =SUM(D33) -> 219 | G33: =F33*$B$4 -> 4712.0323 | H33: =SUM(F33) -> 219 | I33: =H33*$B$4 -> 4712.0323 | J33: =SUM(H33) -> 219 | K33: =J33*$B$4 -> 4712.0323 | L33: =SUM(J33) -> 219 | M33: =L33*$B$4 -> 4712.0323 | N33: =SUM(L33) -> 219 | O33: =N33*$B$4 -> 4712.0323 | P33: =SUM(N33) -> 219 | Q33: =P33*$B$4 -> 4712.0323 | R33: =SUM(P33) -> 219 | S33: =R33*$B$4 -> 4712.0323 | T33: =SUM(R33) -> 219 | U33: =T33*$B$4 -> 4712.0323 | V33: =SUM(T33) -> 219 | W33: =V33*$B$4 -> 4712.0323 | X33: =SUM(Y33/73370) -> 0.70645161 | Y33: =SUM(C33+E33+G33+I33+K33+M33+O33+Q33+S33+U33+W33) -> 51832.355 | Z33: ='B5'!C32 -> 225 | AA33: =SUM(Z33*$Z$4) -> 2250 | AB33: =SUM(Z33) -> 225 | AC33: =SUM(AB33*$Z$4) -> 2250 | AD33: =SUM(AB33) -> 225 | AE33: =SUM(AD33*$Z$4) -> 2250 | AF33: =SUM(AD33) -> 225 | AG33: =SUM(AF33*$Z$4) -> 2250 | AH33: =SUM(AF33) -> 225 | AI33: =SUM(AH33*$Z$4) -> 2250 | AJ33: =SUM(AH33) -> 225 | AK33: =SUM(AJ33*$Z$4) -> 2250 | AL33: =SUM(AJ33) -> 225 | AM33: =SUM(AL33*$Z$4) -> 2250 | AN33: =SUM(AO33/19600) -> 0.80357143 | AO33: =SUM(AA33+AC33+AE33+AG33+AI33+AK33+AM33) -> 15750 | AQ33: =SUM(AR33/92970) -> 0.72692648 | AR33: =SUM(AO33+Y33) -> 67582.355 | AS33: =SUM(AR33-AR32-AT33) -> 0 | AV33: =IF(AT33>0,AU33,AV32) -> 0.58 | AW33: =-SUM('B5'!AI32) -> 0 | AX33: =-SUM(AW33-AS33) -> 0 | AY33: =SUM(AX33+AW33) -> 0 | AZ33: =ELEC!A30 -> 0 | BA33: ='General information '!D33 -> 0 | BB33: =SUM('General information '!E33) -> 0 | BC33: =IF(AR32>=AR33,0,1) -> 0 | BD33: 19222 | BE33: =(305/1185)*ELEC!Q31 -> 0 | BG33: =#REF!-BE33 -> #REF!
A34: =ELEC!C31 -> 43859 | B34: ='B5'!B33 -> 219 | C34: =B34*$B$4 -> 4712.0323 | D34: =SUM(B34) -> 219 | E34: =D34*$B$4 -> 4712.0323 | F34: =SUM(D34) -> 219 | G34: =F34*$B$4 -> 4712.0323 | H34: =SUM(F34) -> 219 | I34: =H34*$B$4 -> 4712.0323 | J34: =SUM(H34) -> 219 | K34: =J34*$B$4 -> 4712.0323 | L34: =SUM(J34) -> 219 | M34: =L34*$B$4 -> 4712.0323 | N34: =SUM(L34) -> 219 | O34: =N34*$B$4 -> 4712.0323 | P34: =SUM(N34) -> 219 | Q34: =P34*$B$4 -> 4712.0323 | R34: =SUM(P34) -> 219 | S34: =R34*$B$4 -> 4712.0323 | T34: =SUM(R34) -> 219 | U34: =T34*$B$4 -> 4712.0323 | V34: =SUM(T34) -> 219 | W34: =V34*$B$4 -> 4712.0323 | X34: =SUM(Y34/73370) -> 0.70645161 | Y34: =SUM(C34+E34+G34+I34+K34+M34+O34+Q34+S34+U34+W34) -> 51832.355 | Z34: ='B5'!C33 -> 225 | AA34: =SUM(Z34*$Z$4) -> 2250 | AB34: =SUM(Z34) -> 225 | AC34: =SUM(AB34*$Z$4) -> 2250 | AD34: =SUM(AB34) -> 225 | AE34: =SUM(AD34*$Z$4) -> 2250 | AF34: =SUM(AD34) -> 225 | AG34: =SUM(AF34*$Z$4) -> 2250 | AH34: =SUM(AF34) -> 225 | AI34: =SUM(AH34*$Z$4) -> 2250 | AJ34: =SUM(AH34) -> 225 | AK34: =SUM(AJ34*$Z$4) -> 2250 | AL34: =SUM(AJ34) -> 225 | AM34: =SUM(AL34*$Z$4) -> 2250 | AN34: =SUM(AO34/19600) -> 0.80357143 | AO34: =SUM(AA34+AC34+AE34+AG34+AI34+AK34+AM34) -> 15750 | AQ34: =SUM(AR34/92970) -> 0.72692648 | AR34: =SUM(AO34+Y34) -> 67582.355 | AS34: =SUM(AR34-AR33-AT34) -> 0 | AV34: =IF(AT34>0,AU34,AV33) -> 0.58 | AW34: =-SUM('B5'!AI33) -> 0 | AX34: =-SUM(AW34-AS34) -> 0 | AY34: =SUM(AX34+AW34) -> 0 | AZ34: =ELEC!A31 -> 0 | BA34: ='General information '!D34 -> 0 | BB34: =SUM('General information '!E34) -> 0 | BC34: =IF(AR33>=AR34,0,1) -> 0 | BD34: 19222 | BE34: =(305/1185)*ELEC!#REF! -> #REF! | BG34: =#REF!-BE34 -> #REF!
A35: =ELEC!C32 -> 43860 | B35: ='B5'!B34 -> 219 | C35: =B35*$B$4 -> 4712.0323 | D35: =SUM(B35) -> 219 | E35: =D35*$B$4 -> 4712.0323 | F35: =SUM(D35) -> 219 | G35: =F35*$B$4 -> 4712.0323 | H35: =SUM(F35) -> 219 | I35: =H35*$B$4 -> 4712.0323 | J35: =SUM(H35) -> 219 | K35: =J35*$B$4 -> 4712.0323 | L35: =SUM(J35) -> 219 | M35: =L35*$B$4 -> 4712.0323 | N35: =SUM(L35) -> 219 | O35: =N35*$B$4 -> 4712.0323 | P35: =SUM(N35) -> 219 | Q35: =P35*$B$4 -> 4712.0323 | R35: =SUM(P35) -> 219 | S35: =R35*$B$4 -> 4712.0323 | T35: =SUM(R35) -> 219 | U35: =T35*$B$4 -> 4712.0323 | V35: =SUM(T35) -> 219 | W35: =V35*$B$4 -> 4712.0323 | X35: =SUM(Y35/73370) -> 0.70645161 | Y35: =SUM(C35+E35+G35+I35+K35+M35+O35+Q35+S35+U35+W35) -> 51832.355 | Z35: ='B5'!C34 -> 225 | AA35: =SUM(Z35*$Z$4) -> 2250 | AB35: =SUM(Z35) -> 225 | AC35: =SUM(AB35*$Z$4) -> 2250 | AD35: =SUM(AB35) -> 225 | AE35: =SUM(AD35*$Z$4) -> 2250 | AF35: =SUM(AD35) -> 225 | AG35: =SUM(AF35*$Z$4) -> 2250 | AH35: =SUM(AF35) -> 225 | AI35: =SUM(AH35*$Z$4) -> 2250 | AJ35: =SUM(AH35) -> 225 | AK35: =SUM(AJ35*$Z$4) -> 2250 | AL35: =SUM(AJ35) -> 225 | AM35: =SUM(AL35*$Z$4) -> 2250 | AN35: =SUM(AO35/19600) -> 0.80357143 | AO35: =SUM(AA35+AC35+AE35+AG35+AI35+AK35+AM35) -> 15750 | AQ35: =SUM(AR35/92970) -> 0.72692648 | AR35: =SUM(AO35+Y35) -> 67582.355 | AS35: =SUM(AR35-AR34-AT35) -> 0 | AV35: =IF(AT35>0,AU35,AV34) -> 0.58 | AW35: =-SUM('B5'!AI34) -> 0 | AX35: =-SUM(AW35-AS35) -> 0 | AY35: =SUM(AX35+AW35) -> 0 | AZ35: =ELEC!A32 -> 0 | BA35: ='General information '!D35 -> 0 | BB35: =SUM('General information '!E35) -> 0 | BC35: =IF(AR34>=AR35,0,1) -> 0 | BD35: 19222 | BE35: =(305/1185)*ELEC!#REF! -> #REF! | BG35: =#REF!-BE35 -> #REF!
A36: =ELEC!C33 -> 43861 | B36: ='B5'!B35 -> 219 | C36: =B36*$B$4 -> 4712.0323 | D36: =SUM(B36) -> 219 | E36: =D36*$B$4 -> 4712.0323 | F36: =SUM(D36) -> 219 | G36: =F36*$B$4 -> 4712.0323 | H36: =SUM(F36) -> 219 | I36: =H36*$B$4 -> 4712.0323 | J36: =SUM(H36) -> 219 | K36: =J36*$B$4 -> 4712.0323 | L36: =SUM(J36) -> 219 | M36: =L36*$B$4 -> 4712.0323 | N36: =SUM(L36) -> 219 | O36: =N36*$B$4 -> 4712.0323 | P36: =SUM(N36) -> 219 | Q36: =P36*$B$4 -> 4712.0323 | R36: =SUM(P36) -> 219 | S36: =R36*$B$4 -> 4712.0323 | T36: =SUM(R36) -> 219 | U36: =T36*$B$4 -> 4712.0323 | V36: =SUM(T36) -> 219 | W36: =V36*$B$4 -> 4712.0323 | X36: =SUM(Y36/73370) -> 0.70645161 | Y36: =SUM(C36+E36+G36+I36+K36+M36+O36+Q36+S36+U36+W36) -> 51832.355 | Z36: ='B5'!C35 -> 225 | AA36: =SUM(Z36*$Z$4) -> 2250 | AB36: =SUM(Z36) -> 225 | AC36: =SUM(AB36*$Z$4) -> 2250 | AD36: =SUM(AB36) -> 225 | AE36: =SUM(AD36*$Z$4) -> 2250 | AF36: =SUM(AD36) -> 225 | AG36: =SUM(AF36*$Z$4) -> 2250 | AH36: =SUM(AF36) -> 225 | AI36: =SUM(AH36*$Z$4) -> 2250 | AJ36: =SUM(AH36) -> 225 | AK36: =SUM(AJ36*$Z$4) -> 2250 | AL36: =SUM(AJ36) -> 225 | AM36: =SUM(AL36*$Z$4) -> 2250 | AN36: =SUM(AO36/19600) -> 0.80357143 | AO36: =SUM(AA36+AC36+AE36+AG36+AI36+AK36+AM36) -> 15750 | AQ36: =SUM(AR36/92970) -> 0.72692648 | AR36: =SUM(AO36+Y36) -> 67582.355 | AS36: =SUM(AR36-AR35-AT36) -> 0 | AV36: =IF(AT36>0,AU36,AV35) -> 0.58 | AW36: =-SUM('B5'!AI35) -> 0 | AX36: =-SUM(AW36-AS36) -> 0 | AY36: =SUM(AX36+AW36) -> 0 | AZ36: =ELEC!A33 -> 0 | BA36: ='General information '!D36 -> 0 | BB36: =SUM('General information '!E36) -> 0
AR37: NB delivery | AS37: =COUNT(AT6:AT36) -> 3 | AT37: =SUM(AT6:AT36) -> 40170 | AU37: =SUM(AU6:AU36)/AS37 -> 0.57766667 | AX37: =SUM(AX6:AX36) -> -19911.571 | AY37: =SUM(AY6:AY36) -> -35776.871
AT38: =+AT37*AU37 -> 23204.87
AS40: =SUM(AS6:AS36)/'EDl log'!A36 -> -2104.5218

Sheet GEN
B1: GEN1 | C1: RUN HR | D1: Fuel Counter Index | E1: Cons /day | F1: Diesel L/H | H1: next service | I1: ALARM | J1: GEN2 | K1: RUN HR | L1: Fuel Counter Index | M1: Cons /day | N1: Diesel L/H | P1: next service | Q1: ALARM | R1: GEN3 | S1: RUN HR | T1: Fuel Counter Index | U1: Cons /day | V1: Diesel L/H | X1: next service | Y1: ALARM | Z1: RH total | AA1: Gen Con /day | AB1: Total Deisel Cons/day | AC1: H /L | AD1: TOAL KW GEN | AI1: fuel Consuption | AK1: AVG KW/h
A2: =ELEC!C2 -> 31-12-2019 | B2: =[1]GEN!B33 -> 8486 | C2: =[1]GEN!C33 -> 1 | D2: =[1]GEN!D33 -> 118621.7 | E2: =[1]GEN!E33 -> 83.7 | F2: =[1]GEN!F33 -> 83.7 | G2: =[1]GEN!G33 -> 0 | H2: =[1]GEN!H33 -> 8497 | I2: =[1]GEN!I33 -> ok | ... AK2: =[1]GEN!AK33 -> 128.50814
A3: =ELEC!C3 -> 43831 | B3: 8486 | C3: =B3-B2 -> 0 | D3: 118644 | E3: =SUM(D3-D2) -> 22.3 | F3: =IF(C3>0,E3/C3,0) -> 0 | G3: =[2]GEN!G32 -> 0 | H3: =H2 -> 8497 | I3: =IF(B3-H3<=0,"ok","oil change") -> ok | J3: 10591 | K3: =J3-J2 -> 3 | L3: 219030.1 | M3: =SUM(L3-L2) -> 397.1 | N3: =IF(K3>0,M3/K3,0) -> 132.36667 | O3: =[2]GEN!O32 -> 0 | P3: =P2 -> 10873 | Q3: =IF(J3-P3<=0,"ok","oil change") -> ok | R3: 10884 | S3: =R3-R2 -> 0 | T3: 175258 | U3: =SUM(T3-T2) -> 73.8 | V3: =IF(S3>0,U3/S3,0) -> 0 | W3: =[2]GEN!W32 -> 0 | X3: =X2 -> 10989 | Y3: =IF(R3-X3<=0,"ok","oil change") -> ok | Z3: =C3+K3+S3 -> 3 | AA3: =U3+M3+E3 -> 493.2 | AB3: =V3+N3+F3 -> 132.36667 | AC3: =IF(Z3>0,AA3/Z3,0) -> 164.4 | AD3: =ELEC!Q3 -> 2547 | AE3: =SUM(AD3/Z3) -> 849 | AF3: =SUM(AE3/1600) -> 0.530625 | AG3: =SUM(360*AF3) -> 191.025 | AH3: =SUM(AC3-AG3) -> -26.625 | AI3: =AD3*AJ3 -> 655.55696 | AJ3: =305/1185 -> 0.25738397 | AK3: =AI3/Z3 -> 218.51899
A4: =ELEC!C4 -> 43832 | B4: 8486 | C4: =B4-B3 -> 0 | D4: 118701 | E4: =SUM(D4-D3) -> 57 | F4: =IF(C4>0,E4/C4,0) -> 0 | H4: =H3 -> 8497 | I4: =IF(B4-H4<=0,"ok","oil change") -> ok | J4: 10597 | K4: =J4-J3 -> 6 | L4: 219814 | M4: =SUM(L4-L3) -> 783.9 | N4: =IF(K4>0,M4/K4,0) -> 130.65 | P4: =P3 -> 10873 | Q4: =IF(J4-P4<=0,"ok","oil change") -> ok | R4: 10885 | S4: =R4-R3 -> 1 | T4: 175393.1 | U4: =SUM(T4-T3) -> 135.1 | V4: =IF(S4>0,U4/S4,0) -> 135.1 | X4: =X3 -> 10989 | Y4: =IF(R4-X4<=0,"ok","oil change") -> ok | Z4: =C4+K4+S4 -> 7 | AA4: =U4+M4+E4 -> 976 | AB4: =V4+N4+F4 -> 265.75 | AC4: =IF(Z4>0,AA4/Z4,0) -> 139.42857 | AD4: =ELEC!Q4 -> 4622 | AE4: =SUM(AD4/Z4) -> 660.28571 | AF4: =SUM(AE4/1600) -> 0.41267857 | AG4: =SUM(360*AF4) -> 148.56429 | AH4: =SUM(AC4-AG4) -> -9.1357143 | AI4: =AD4*AJ4 -> 1189.6287 | AJ4: =305/1185 -> 0.25738397 | AK4: =AI4/Z4 -> 169.94696
A5: =ELEC!C5 -> 43833 | B5: =B4 -> 8486 | C5: =B5-B4 -> 0 | D5: 118732.4 | E5: =SUM(D5-D4) -> 31.4 | F5: =IF(C5>0,E5/C5,0) -> 0 | H5: 8497 | I5: =IF(B5-H5<=0,"ok","oil change") -> ok | J5: 10603 | K5: =J5-J4 -> 6 | L5: 220473.1 | M5: =SUM(L5-L4) -> 659.1 | N5: =IF(K5>0,M5/K5,0) -> 109.85 | P5: =P4 -> 10873 | Q5: =IF(J5-P5<=0,"ok","oil change") -> ok | R5: 10885 | S5: =R5-R4 -> 0 | T5: 175498.8 | U5: =SUM(T5-T4) -> 105.7 | V5: =IF(S5>0,U5/S5,0) -> 0 | X5: =X4 -> 10989 | Y5: =IF(R5-X5<=0,"ok","oil change") -> ok | Z5: =C5+K5+S5 -> 6 | AA5: =U5+M5+E5 -> 796.2 | AB5: =V5+N5+F5 -> 109.85 | AC5: =IF(Z5>0,AA5/Z5,0) -> 132.7 | AD5: =ELEC!Q5 -> 4631 | AE5: =SUM(AD5/Z5) -> 771.83333 | AF5: =SUM(AE5/1600) -> 0.48239583 | AG5: =SUM(320*AF5) -> 154.36667 | AH5: =SUM(AC5-AG5) -> -21.666667 | AI5: =AD5*AJ5 -> 1191.9451 | AJ5: =305/1185 -> 0.25738397 | AK5: =AI5/Z5 -> 198.65752
A6: =ELEC!C6 -> 43834 | B6: =B5 -> 8486 | C6: =B6-B5 -> 0 | D6: 118765.8 | E6: =SUM(D6-D5) -> 33.4 | F6: =IF(C6>0,E6/C6,0) -> 0 | H6: =H5 -> 8497 | I6: =IF(B6-H6<=0,"ok","oil change") -> ok | J6: 10608 | K6: =J6-J5 -> 5 | L6: 221194.7 | M6: =SUM(L6-L5) -> 721.6 | N6: =IF(K6>0,M6/K6,0) -> 144.32 | P6: =P5 -> 10873 | Q6: =IF(J6-P6<=0,"ok","oil change") -> ok | R6: 10886 | S6: =R6-R5 -> 1 | T6: 175723.2 | U6: =SUM(T6-T5) -> 224.4 | V6: =IF(S6>0,U6/S6,0) -> 224.4 | X6: =X5 -> 10989 | Y6: =IF(R6-X6<=0,"ok","oil change") -> ok | Z6: =C6+K6+S6 -> 6 | AA6: =U6+M6+E6 -> 979.4 | AB6: =V6+N6+F6 -> 368.72 | AC6: =IF(Z6>0,AA6/Z6,0) -> 163.23333 | AD6: =ELEC!Q6 -> 4000 | AE6: =SUM(AD6/Z6) -> 666.66667 | AF6: =SUM(AE6/1600) -> 0.41666667 | AG6: =SUM(320*AF6) -> 133.33333 | AH6: =SUM(AC6-AG6) -> 29.9 | AI6: =AD6*AJ6 -> 1029.5359 | AJ6: =305/1185 -> 0.25738397 | AK6: =AI6/Z6 -> 171.58931
A7: =ELEC!C7 -> 43835 | B7: 8486 | C7: =B7-B6 -> 0 | D7: 118781 | E7: =SUM(D7-D6) -> 15.2 | F7: =IF(C7>0,E7/C7,0) -> 0 | H7: =H6 -> 8497 | I7: =IF(B7-H7<=0,"ok","oil change") -> ok | J7: 10611 | K7: =J7-J6 -> 3 | L7: 221540 | M7: =SUM(L7-L6) -> 345.3 | N7: =IF(K7>0,M7/K7,0) -> 115.1 | P7: =P6 -> 10873 | Q7: =IF(J7-P7<=0,"ok","oil change") -> ok | R7: 10886 | S7: =R7-R6 -> 0 | T7: 175776.5 | U7: =SUM(T7-T6) -> 53.3 | V7: =IF(S7>0,U7/S7,0) -> 0 | X7: =X6 -> 10989 | Y7: =IF(R7-X7<=0,"ok","oil change") -> ok | Z7: =C7+K7+S7 -> 3 | AA7: =U7+M7+E7 -> 413.8 | AB7: =V7+N7+F7 -> 115.1 | AC7: =IF(Z7>0,AA7/Z7,0) -> 137.93333 | AD7: =ELEC!Q7 -> 2586 | AE7: =SUM(AD7/Z7) -> 862 | AF7: =SUM(AE7/1600) -> 0.53875 | AH7: =SUM(AC7-AG7) -> #VALUE! | AI7: =AD7*AJ7 -> 665.59494 | AJ7: =305/1185 -> 0.25738397 | AK7: =AI7/Z7 -> 221.86498
A8: =ELEC!C8 -> 43836 | B8: 8487 | C8: =B8-B7 -> 1 | D8: 118823 | E8: =SUM(D8-D7) -> 42 | F8: =IF(C8>0,E8/C8,0) -> 42 | H8: =H7 -> 8497 | I8: =IF(B8-H8<=0,"ok","oil change") -> ok | J8: 10619 | K8: =J8-J7 -> 8 | L8: 222802 | M8: =SUM(L8-L7) -> 1262 | N8: =IF(K8>0,M8/K8,0) -> 157.75 | P8: =P7 -> 10873 | Q8: =IF(J8-P8<=0,"ok","oil change") -> ok | R8: 10887 | S8: =R8-R7 -> 1 | T8: 175937.9 | U8: =SUM(T8-T7) -> 161.4 | V8: =IF(S8>0,U8/S8,0) -> 161.4 | X8: =X7 -> 10989 | Y8: =IF(R8-X8<=0,"ok","oil change") -> ok | Z8: =C8+K8+S8 -> 10 | AA8: =U8+M8+E8 -> 1465.4 | AB8: =V8+N8+F8 -> 361.15 | AC8: =IF(Z8>0,AA8/Z8,0) -> 146.54 | AD8: =ELEC!Q8 -> 5234 | AE8: =SUM(AD8/Z8) -> 523.4 | AF8: =SUM(AE8/1600) -> 0.327125 | AG8: =SUM(320*AF8) -> 104.68 | AH8: =SUM(AC8-AG8) -> 41.86 | AI8: =AD8*AJ8 -> 1347.1477 | AJ8: =305/1185 -> 0.25738397 | AK8: =AI8/Z8 -> 134.71477
A9: =ELEC!C9 -> 43837 | B9: 8487 | C9: =B9-B8 -> 0 | D9: 118878 | E9: =SUM(D9-D8) -> 55 | F9: =IF(C9>0,E9/C9,0) -> 0 | H9: =H8 -> 8497 | I9: =IF(B9-H9<=0,"ok","oil change") -> ok | J9: 10628 | K9: =J9-J8 -> 9 | L9: 224521 | M9: =SUM(L9-L8) -> 1719 | N9: =IF(K9>0,M9/K9,0) -> 191 | P9: =P8 -> 10873 | Q9: =IF(J9-P9<=0,"ok","oil change") -> ok | R9: 10887 | S9: =R9-R8 -> 0 | T9: 176085 | U9: =SUM(T9-T8) -> 147.1 | V9: =IF(S9>0,U9/S9,0) -> 0 | X9: =X8 -> 10989 | Y9: =IF(R9-X9<=0,"ok","oil change") -> ok | Z9: =C9+K9+S9 -> 9 | AA9: =U9+M9+E9 -> 1921.1 | AB9: =V9+N9+F9 -> 191 | AC9: =IF(Z9>0,AA9/Z9,0) -> 213.45556 | AD9: =ELEC!Q9 -> 4879 | AE9: =SUM(AD9/Z9) -> 542.11111 | AF9: =SUM(AE9/1600) -> 0.33881944 | AG9: =SUM(320*AF9) -> 108.42222 | AH9: =SUM(AC9-AG9) -> 105.03333 | AI9: =AD9*AJ9 -> 1255.7764 | AJ9: 0.25738397 | AK9: =IF(Z9>0,AI9/Z9,0) -> 139.53071
A10: =ELEC!C10 -> 43838 | B10: =B9 -> 8487 | C10: =B10-B9 -> 0 | D10: =D9 -> 118878 | E10: =SUM(D10-D9) -> 0 | F10: =IF(C10>0,E10/C10,0) -> 0 | H10: =H9 -> 8497 | I10: =IF(B10-H10<=0,"ok","oil change") -> ok | J10: 10642 | K10: =J10-J9 -> 14 | L10: 227914.9 | M10: =SUM(L10-L9) -> 3393.9 | N10: =IF(K10>0,M10/K10,0) -> 242.42143 | P10: 10873 | Q10: =IF(J10-P10<=0,"ok","oil change") -> ok | R10: 10889 | S10: =R10-R9 -> 2 | T10: 176482.2 | U10: =SUM(T10-T9) -> 397.2 | V10: =IF(S10>0,U10/S10,0) -> 198.6 | X10: =X9 -> 10989 | Y10: =IF(R10-X10<=0,"ok","oil change") -> ok | Z10: =C10+K10+S10 -> 16 | AA10: =U10+M10+E10 -> 3791.1 | AB10: =V10+N10+F10 -> 441.02143 | AC10: =IF(Z10>0,AA10/Z10,0) -> 236.94375 | AD10: =ELEC!Q10 -> 7001 | AE10: =SUM(AD10/Z10) -> 437.5625 | AF10: =SUM(AE10/1600) -> 0.27347656 | AG10: =SUM(320*AF10) -> 87.5125 | AH10: =SUM(AC10-AG10) -> 149.43125 | AI10: =AD10*AJ10 -> 1801.9451 | AJ10: =305/1185 -> 0.25738397 | AK10: =IF(Z10>0,AI10/Z10,0) -> 112.62157
A11: =ELEC!C11 -> 43839 | B11: 8487 | C11: =B11-B10 -> 0 | D11: 118922.3 | E11: =SUM(D11-D10) -> 44.3 | F11: =IF(C11>0,E11/C11,0) -> 0 | H11: =H10 -> 8497 | I11: =IF(B11-H11<=0,"ok","oil change") -> ok | J11: 10649 | K11: =J11-J10 -> 7 | L11: 229412.3 | M11: =SUM(L11-L10) -> 1497.4 | N11: =IF(K11>0,M11/K11,0) -> 213.91429 | P11: =P10 -> 10873 | Q11: =IF(J11-P11<=0,"ok","oil change") -> ok | R11: 10889 | S11: =R11-R10 -> 0 | T11: 176646 | U11: =SUM(T11-T10) -> 163.8 | V11: =IF(S11>0,U11/S11,0) -> 0 | X11: =X10 -> 10989 | Y11: =IF(R11-X11<=0,"ok","oil change") -> ok | Z11: =C11+K11+S11 -> 7 | AA11: =U11+M11+E11 -> 1705.5 | AB11: =V11+N11+F11 -> 213.91429 | AC11: =IF(Z11>0,AA11/Z11,0) -> 243.64286 | AD11: =ELEC!Q11 -> 4886 | AE11: =SUM(AD11/Z11) -> 698 | AF11: =SUM(AE11/1600) -> 0.43625 | AG11: =SUM(320*AF11) -> 139.6 | AH11: =SUM(AC11-AG11) -> 104.04286 | AI11: =AD11*AJ11 -> 1257.5781 | AJ11: =305/1185 -> 0.25738397 | AK11: =IF(Z11>0,AI11/Z11,0) -> 179.65401
A12: =ELEC!C12 -> 43840 | B12: 8487 | C12: =B12-B11 -> 0 | D12: 118922.4 | E12: =SUM(D12-D11) -> 0.1 | F12: =IF(C12>0,E12/C12,0) -> 0 | H12: =H11 -> 8497 | I12: =IF(B12-H12<=0,"ok","oil change") -> ok | J12: 10652 | K12: =J12-J11 -> 3 | L12: 229782 | M12: =SUM(L12-L11) -> 369.7 | N12: =IF(K12>0,M12/K12,0) -> 123.23333 | P12: =P11 -> 10873 | Q12: =IF(J12-P12<=0,"ok","oil change") -> ok | R12: 10890 | S12: =R12-R11 -> 1 | T12: 176663 | U12: =SUM(T12-T11) -> 17 | V12: =IF(S12>0,U12/S12,0) -> 17 | X12: =X11 -> 10989 | Y12: =IF(R12-X12<=0,"ok","oil change") -> ok | Z12: =C12+K12+S12 -> 4 | AA12: =U12+M12+E12 -> 386.8 | AB12: =V12+N12+F12 -> 140.23333 | AC12: =IF(Z12>0,AA12/Z12,0) -> 96.7 | AD12: =ELEC!Q12 -> 2414 | AE12: =SUM(AD12/Z12) -> 603.5 | AF12: =SUM(AE12/1600) -> 0.3771875 | AG12: =SUM(320*AF12) -> 120.7 | AH12: =SUM(AC12-AG12) -> -24 | AI12: =AD12*AJ12 -> 621.32489 | AJ12: =305/1185 -> 0.25738397 | AK12: =IF(Z12>0,AI12/Z12,0) -> 155.33122
A13: =ELEC!C13 -> 43841 | B13: =B12 -> 8487 | C13: =B13-B12 -> 0 | D13: 118922.4 | E13: =SUM(D13-D12) -> 0 | F13: =IF(C13>0,E13/C13,0) -> 0 | H13: =H12 -> 8497 | I13: =IF(B13-H13<=0,"ok","oil change") -> ok | J13: 10656 | K13: =J13-J12 -> 4 | L13: 230579.6 | M13: =SUM(L13-L12) -> 797.6 | N13: =IF(K13>0,M13/K13,0) -> 199.4 | P13: =P12 -> 10873 | Q13: =IF(J13-P13<=0,"ok","oil change") -> ok | R13: =R12 -> 10890 | S13: =R13-R12 -> 0 | T13: 176718.7 | U13: =SUM(T13-T12) -> 55.7 | V13: =IF(S13>0,U13/S13,0) -> 0 | X13: =X12+180 -> 11169 | Y13: =IF(R13-X13<=0,"ok","oil change") -> ok | Z13: =C13+K13+S13 -> 4 | AA13: =U13+M13+E13 -> 853.3 | AB13: =V13+N13+F13 -> 199.4 | AC13: =IF(Z13>0,AA13/Z13,0) -> 213.325 | AD13: =ELEC!Q13 -> 1643 | AE13: =SUM(AD13/Z13) -> 410.75 | AF13: =SUM(AE13/1600) -> 0.25671875 | AG13: =SUM(320*AF13) -> 82.15 | AH13: =SUM(AC13-AG13) -> 131.175 | AI13: =AD13*AJ13 -> 422.88186 | AJ13: =305/1185 -> 0.25738397 | AK13: =IF(Z13>0,AI13/Z13,0) -> 105.72046
A14: =ELEC!C14 -> 43842 | B14: 8487 | C14: =B14-B13 -> 0 | D14: 118922 | E14: =SUM(D14-D13) -> -0.4 | F14: =IF(C14>0,E14/C14,0) -> 0 | H14: =H13 -> 8497 | I14: =IF(B14-H14<=0,"ok","oil change") -> ok | J14: 10659 | K14: =J14-J13 -> 3 | L14: 231104 | M14: =SUM(L14-L13) -> 524.4 | N14: =IF(K14>0,M14/K14,0) -> 174.8 | P14: =P13 -> 10873 | Q14: =IF(J14-P14<=0,"ok","oil change") -> ok | R14: 10890 | S14: =R14-R13 -> 0 | T14: =T13 -> 176718.7 | U14: =SUM(T14-T13) -> 0 | V14: =IF(S14>0,U14/S14,0) -> 0 | X14: =X13 -> 11169 | Y14: =IF(R14-X14<=0,"ok","oil change") -> ok | Z14: =C14+K14+S14 -> 3 | AA14: =U14+M14+E14 -> 524 | AB14: =V14+N14+F14 -> 174.8 | AC14: =IF(Z14>0,AA14/Z14,0) -> 174.66667 | AD14: =ELEC!Q14 -> 2117 | AE14: =SUM(AD14/Z14) -> 705.66667 | AF14: =SUM(AE14/1600) -> 0.44104167 | AG14: =SUM(320*AF14) -> 141.13333 | AH14: =SUM(AC14-AG14) -> 33.533333 | AI14: =AD14*AJ14 -> 544.88186 | AJ14: =305/1185 -> 0.25738397 | AK14: =IF(Z14>0,AI14/Z14,0) -> 181.62729
A15: =ELEC!C15 -> 43843 | B15: 8487 | C15: =B15-B14 -> 0 | D15: 118922.5 | E15: =SUM(D15-D14) -> 0.5 | F15: =IF(C15>0,E15/C15,0) -> 0 | H15: =H14 -> 8497 | I15: =IF(B15-H15<=0,"ok","oil change") -> ok | J15: 10662 | K15: =J15-J14 -> 3 | L15: 231479 | M15: =SUM(L15-L14) -> 375 | N15: =IF(K15>0,M15/K15,0) -> 125 | P15: =P14 -> 10873 | Q15: =IF(J15-P15<=0,"ok","oil change") -> ok | R15: 10890 | S15: =R15-R14 -> 0 | T15: =T14 -> 176718.7 | U15: =SUM(T15-T14) -> 0 | V15: =IF(S15>0,U15/S15,0) -> 0 | X15: =X14 -> 11169 | Y15: =IF(R15-X15<=0,"ok","oil change") -> ok | Z15: =C15+K15+S15 -> 3 | AA15: =U15+M15+E15 -> 375.5 | AB15: =V15+N15+F15 -> 125 | AC15: =IF(Z15>0,AA15/Z15,0) -> 125.16667 | AD15: =ELEC!Q15 -> 2311 | AE15: =SUM(AD15/Z15) -> 770.33333 | AF15: =SUM(AE15/1600) -> 0.48145833 | AG15: =SUM(320*AF15) -> 154.06667 | AH15: =SUM(AC15-AG15) -> -28.9 | AI15: =AD15*AJ15 -> 594.81435 | AJ15: =305/1185 -> 0.25738397 | AK15: =IF(Z15>0,AI15/Z15,0) -> 198.27145
A16: =ELEC!C16 -> 43844 | B16: 8487 | C16: =B16-B15 -> 0 | D16: =D15 -> 118922.5 | E16: =SUM(D16-D15) -> 0 | F16: =IF(C16>0,E16/C16,0) -> 0 | H16: =H15 -> 8497 | I16: =IF(B16-H16<=0,"ok","oil change") -> ok | J16: 10666 | K16: =J16-J15 -> 4 | L16: 232349 | M16: =SUM(L16-L15) -> 870 | N16: =IF(K16>0,M16/K16,0) -> 217.5 | P16: =P15 -> 10873 | Q16: =IF(J16-P16<=0,"ok","oil change") -> ok | R16: 10890 | S16: =R16-R15 -> 0 | T16: 176718.7 | U16: =SUM(T16-T15) -> 0 | V16: =IF(S16>0,U16/S16,0) -> 0 | X16: =X15 -> 11169 | Y16: =IF(R16-X16<=0,"ok","oil change") -> ok | Z16: =C16+K16+S16 -> 4 | AA16: =U16+M16+E16 -> 870 | AB16: =V16+N16+F16 -> 217.5 | AC16: =IF(Z16>0,AA16/Z16,0) -> 217.5 | AD16: =ELEC!Q16 -> 2804 | AE16: =SUM(AD16/Z16) -> 701 | AF16: =SUM(AE16/1600) -> 0.438125 | AG16: =SUM(320*AF16) -> 140.2 | AH16: =SUM(AC16-AG16) -> 77.3 | AI16: =AD16*AJ16 -> 721.70464 | AJ16: =305/1185 -> 0.25738397 | AK16: =IF(Z16>0,AI16/Z16,0) -> 180.42616
A17: =ELEC!C17 -> 43845 | B17: 8487 | C17: =B17-B16 -> 0 | D17: 118922.6 | E17: =SUM(D17-D16) -> 0.1 | F17: =IF(C17>0,E17/C17,0) -> 0 | H17: =H16 -> 8497 | I17: =IF(B17-H17<=0,"ok","oil change") -> ok | J17: 10671 | K17: =J17-J16 -> 5 | L17: 233233.3 | M17: =SUM(L17-L16) -> 884.3 | N17: =IF(K17>0,M17/K17,0) -> 176.86 | P17: =P16 -> 10873 | Q17: =IF(J17-P17<=0,"ok","oil change") -> ok | R17: 10890 | S17: =R17-R16 -> 0 | T17: 176718.7 | U17: =SUM(T17-T16) -> 0 | V17: =IF(S17>0,U17/S17,0) -> 0 | X17: =X16 -> 11169 | Y17: =IF(R17-X17<=0,"ok","oil change") -> ok | Z17: =C17+K17+S17 -> 5 | AA17: =U17+M17+E17 -> 884.4 | AB17: =V17+N17+F17 -> 176.86 | AC17: =IF(Z17>0,AA17/Z17,0) -> 176.88 | AD17: =ELEC!Q17 -> 2646 | AE17: =SUM(AD17/Z17) -> 529.2 | AF17: =SUM(AE17/1600) -> 0.33075 | AG17: =SUM(320*AF17) -> 105.84 | AH17: =SUM(AC17-AG17) -> 71.04 | AI17: =AD17*AJ17 -> 681.03797 | AJ17: =305/1185 -> 0.25738397 | AK17: =IF(Z17>0,AI17/Z17,0) -> 136.20759
A18: =ELEC!C18 -> 43846 | B18: =B17 -> 8487 | C18: =B18-B17 -> 0 | D18: =D17 -> 118922.6 | E18: =SUM(D18-D17) -> 0 | F18: =IF(C18>0,E18/C18,0) -> 0 | H18: =H17 -> 8497 | I18: =IF(B18-H18<=0,"ok","oil change") -> ok | J18: 10677 | K18: =J18-J17 -> 6 | L18: 234033.6 | M18: =SUM(L18-L17) -> 800.3 | N18: =IF(K18>0,M18/K18,0) -> 133.38333 | P18: =P17 -> 10873 | Q18: =IF(J18-P14<=0,"ok","oil change") -> ok | R18: =R17 -> 10890 | S18: =R18-R17 -> 0 | T18: =T17 -> 176718.7 | U18: =SUM(T18-T17) -> 0 | V18: =IF(S18>0,U18/S18,0) -> 0 | X18: =X17 -> 11169 | Y18: =IF(R18-X18<=0,"ok","oil change") -> ok | Z18: =C18+K18+S18 -> 6 | AA18: =U18+M18+E18 -> 800.3 | AB18: =V18+N18+F18 -> 133.38333 | AC18: =IF(Z18>0,AA18/Z18,0) -> 133.38333 | AD18: =ELEC!Q18 -> 4480 | AE18: =SUM(AD18/Z18) -> 746.66667 | AF18: =SUM(AE18/1600) -> 0.46666667 | AG18: =SUM(320*AF18) -> 149.33333 | AH18: =SUM(AC18-AG18) -> -15.95 | AI18: =AD18*AJ18 -> 1153.0802 | AJ18: =305/1185 -> 0.25738397 | AK18: =IF(Z18>0,AI18/Z18,0) -> 192.18003
A19: =ELEC!C19 -> 43847 | B19: =B18 -> 8487 | C19: =B19-B18 -> 0 | D19: =D18 -> 118922.6 | E19: =SUM(D19-D18) -> 0 | F19: =IF(C19>0,E19/C19,0) -> 0 | H19: =H18 -> 8497 | I19: =IF(B19-H19<=0,"ok","oil change") -> ok | J19: 10680 | K19: =J19-J18 -> 3 | L19: 234681.6 | M19: =SUM(L19-L18) -> 648 | N19: =IF(K19>0,M19/K19,0) -> 216 | P19: =P18 -> 10873 | Q19: =IF(J19-P19<=0,"ok","oil change") -> ok | R19: =R18 -> 10890 | S19: =R19-R18 -> 0 | T19: =T18 -> 176718.7 | U19: =SUM(T19-T18) -> 0 | V19: =IF(S19>0,U19/S19,0) -> 0 | X19: =X18 -> 11169 | Y19: =IF(R19-X19<=0,"ok","oil change") -> ok | Z19: =C19+K19+S19 -> 3 | AA19: =U19+M19+E19 -> 648 | AB19: =V19+N19+F19 -> 216 | AC19: =IF(Z19>0,AA19/Z19,0) -> 216 | AD19: =ELEC!Q19 -> 2014 | AE19: =SUM(AD19/Z19) -> 671.33333 | AF19: =SUM(AE19/1600) -> 0.41958333 | AG19: =SUM(320*AF19) -> 134.26667 | AH19: =SUM(AC19-AG19) -> 81.733333 | AI19: =AD19*AJ19 -> 518.37131 | AJ19: =305/1185 -> 0.25738397 | AK19: =IF(Z19>0,AI19/Z19,0) -> 172.79044
A20: =ELEC!C20 -> 43848 | B20: =B19 -> 8487 | C20: =B20-B19 -> 0 | D20: =D19 -> 118922.6 | E20: =SUM(D20-D19) -> 0 | F20: =IF(C20>0,E20/C20,0) -> 0 | H20: =H19 -> 8497 | I20: =IF(B20-H20<=0,"ok","oil change") -> ok | J20: =J19 -> 10680 | K20: =J20-J19 -> 0 | L20: =L19 -> 234681.6 | M20: =SUM(L20-L19) -> 0 | N20: =IF(K20>0,M20/K20,0) -> 0 | P20: =P19 -> 10873 | Q20: =IF(J20-P20<=0,"ok","oil change") -> ok | R20: =R19 -> 10890 | S20: =R20-R19 -> 0 | T20: =T19 -> 176718.7 | U20: =SUM(T20-T19) -> 0 | V20: =IF(S20>0,U20/S20,0) -> 0 | X20: =X19 -> 11169 | Y20: =IF(R20-X20<=0,"ok","oil change") -> ok | Z20: =C20+K20+S20 -> 0 | AA20: =U20+M20+E20 -> 0 | AB20: =V20+N20+F20 -> 0 | AC20: =IF(Z20>0,AA20/Z20,0) -> 0 | AD20: =ELEC!Q20 -> 0 | AE20: =SUM(AD20/Z20) -> #DIV/0! | AF20: =SUM(AE20/1600) -> #DIV/0! | AG20: =SUM(320*AF20) -> #DIV/0! | AH20: =SUM(AC20-AG20) -> #DIV/0! | AI20: =AD20*AJ20 -> 0 | AJ20: =305/1185 -> 0.25738397 | AK20: =IF(Z20>0,AI20/Z20,0) -> 0
A21: =ELEC!C21 -> 43849 | B21: =B20 -> 8487 | C21: =B21-B20 -> 0 | D21: =D20 -> 118922.6 | E21: =SUM(D21-D20) -> 0 | F21: =IF(C21>0,E21/C21,0) -> 0 | H21: =H20 -> 8497 | I21: =IF(B21-H21<=0,"ok","oil change") -> ok | J21: =J20 -> 10680 | K21: =J21-J20 -> 0 | L21: =L20 -> 234681.6 | M21: =SUM(L21-L20) -> 0 | N21: =IF(K21>0,M21/K21,0) -> 0 | P21: =P20 -> 10873 | Q21: =IF(J21-P21<=0,"ok","oil change") -> ok | R21: =R20 -> 10890 | S21: =R21-R20 -> 0 | T21: =T20 -> 176718.7 | U21: =SUM(T21-T20) -> 0 | V21: =IF(S21>0,U21/S21,0) -> 0 | X21: =X20 -> 11169 | Y21: =Y20 -> ok | Z21: =C21+K21+S21 -> 0 | AA21: =U21+M21+E21 -> 0 | AB21: =V21+N21+F21 -> 0 | AC21: =IF(Z21>0,AA21/Z21,0) -> 0 | AD21: =ELEC!Q21 -> 0 | AE21: =SUM(AD21/Z21) -> #DIV/0! | AF21: =SUM(AE21/1600) -> #DIV/0! | AG21: =SUM(320*AF21) -> #DIV/0! | AH21: =SUM(AC21-AG21) -> #DIV/0! | AI21: =AD21*AJ21 -> 0 | AJ21: =305/1185 -> 0.25738397 | AK21: =IF(Z21>0,AI21/Z21,0) -> 0
A22: =ELEC!C22 -> 43850 | B22: =B21 -> 8487 | C22: =B22-B21 -> 0 | D22: =D21 -> 118922.6 | E22: =SUM(D22-D21) -> 0 | F22: =IF(C22>0,E22/C22,0) -> 0 | H22: =H21 -> 8497 | I22: =IF(B22-H22<=0,"ok","oil change") -> ok | J22: =J21 -> 10680 | K22: =J22-J21 -> 0 | L22: =L21 -> 234681.6 | M22: =SUM(L22-L21) -> 0 | N22: =IF(K22>0,M22/K22,0) -> 0 | P22: =P21 -> 10873 | Q22: =IF(J22-P22<=0,"ok","oil change") -> ok | R22: =R21 -> 10890 | S22: =R22-R21 -> 0 | T22: =T21 -> 176718.7 | U22: =SUM(T22-T21) -> 0 | V22: =IF(S22>0,U22/S22,0) -> 0 | X22: =X21 -> 11169 | Y22: =IF(R22-X22<=0,"ok","oil change") -> ok | Z22: =C22+K22+S22 -> 0 | AA22: =U22+M22+E22 -> 0 | AB22: =V22+N22+F22 -> 0 | AC22: =IF(Z22>0,AA22/Z22,0) -> 0 | AD22: =ELEC!Q22 -> 0 | AE22: =SUM(AD22/Z22) -> #DIV/0! | AF22: =SUM(AE22/1600) -> #DIV/0! | AG22: =SUM(320*AF22) -> #DIV/0! | AH22: =SUM(AC22-AG22) -> #DIV/0! | AI22: =AD22*AJ22 -> 0 | AJ22: =305/1185 -> 0.25738397 | AK22: =IF(Z22>0,AI22/Z22,0) -> 0
A23: =ELEC!C23 -> 43851 | B23: =B22 -> 8487 | C23: =B23-B22 -> 0 | D23: =D22 -> 118922.6 | E23: =SUM(D23-D22) -> 0 | F23: =IF(C23>0,E23/C23,0) -> 0 | H23: =H22 -> 8497 | I23: =IF(B23-H23<=0,"ok","oil change") -> ok | J23: =J22 -> 10680 | K23: =J23-J22 -> 0 | L23: =L22 -> 234681.6 | M23: =SUM(L23-L22) -> 0 | N23: =IF(K23>0,M23/K23,0) -> 0 | P23: =P22 -> 10873 | Q23: =IF(J23-P23<=0,"ok","oil change") -> ok | R23: =R22 -> 10890 | S23: =R23-R22 -> 0 | T23: =T22 -> 176718.7 | U23: =SUM(T23-T22) -> 0 | V23: =IF(S23>0,U23/S23,0) -> 0 | X23: =X22 -> 11169 | Y23: =IF(R23-X23<=0,"ok","oil change") -> ok | Z23: =C23+K23+S23 -> 0 | AA23: =U23+M23+E23 -> 0 | AB23: =V23+N23+F23 -> 0 | AC23: =IF(Z23>0,AA23/Z23,0) -> 0 | AD23: =ELEC!Q23 -> 0 | AE23: =SUM(AD23/Z23) -> #DIV/0! | AF23: =SUM(AE23/1600) -> #DIV/0! | AG23: =SUM(320*AF23) -> #DIV/0! | AH23: =SUM(AC23-AG23) -> #DIV/0! | AI23: =AD23*AJ23 -> 0 | AJ23: =305/1185 -> 0.25738397 | AK23: =IF(Z23>0,AI23/Z23,0) -> 0
A24: =ELEC!C24 -> 43852 | B24: =B23 -> 8487 | C24: =B24-B23 -> 0 | D24: =D23 -> 118922.6 | E24: =SUM(D24-D23) -> 0 | F24: =IF(C24>0,E24/C24,0) -> 0 | H24: =H23 -> 8497 | I24: =IF(B24-H24<=0,"ok","oil change") -> ok | J24: =J23 -> 10680 | K24: =J24-J23 -> 0 | L24: =L23 -> 234681.6 | M24: =SUM(L24-L23) -> 0 | N24: =IF(K24>0,M24/K24,0) -> 0 | P24: =P23 -> 10873 | Q24: =IF(J24-P24<=0,"ok","oil change") -> ok | R24: =R23 -> 10890 | S24: =R24-R23 -> 0 | T24: =T23 -> 176718.7 | U24: =SUM(T24-T23) -> 0 | V24: =IF(S24>0,U24/S24,0) -> 0 | X24: =X23 -> 11169 | Y24: =IF(R24-X24<=0,"ok","oil change") -> ok | Z24: =C24+K24+S24 -> 0 | AA24: =U24+M24+E24 -> 0 | AB24: =V24+N24+F24 -> 0 | AC24: =IF(Z24>0,AA24/Z24,0) -> 0 | AD24: =ELEC!Q24 -> 0 | AE24: =SUM(AD24/Z24) -> #DIV/0! | AF24: =SUM(AE24/1600) -> #DIV/0! | AG24: =SUM(320*AF24) -> #DIV/0! | AH24: =SUM(AC24-AG24) -> #DIV/0! | AI24: =AD24*AJ24 -> 0 | AJ24: =305/1185 -> 0.25738397 | AK24: =IF(Z24>0,AI24/Z24,0) -> 0
A25: =ELEC!C25 -> 43853 | B25: =B24 -> 8487 | C25: =B25-B24 -> 0 | D25: =D24 -> 118922.6 | E25: =SUM(D25-D24) -> 0 | F25: =IF(C25>0,E25/C25,0) -> 0 | H25: =H24 -> 8497 | I25: =IF(B25-H25<=0,"ok","oil change") -> ok | J25: =J24 -> 10680 | K25: =J25-J24 -> 0 | L25: =L24 -> 234681.6 | M25: =SUM(L25-L24) -> 0 | N25: =IF(K25>0,M25/K25,0) -> 0 | P25: =P24 -> 10873 | Q25: =IF(J25-P25<=0,"ok","oil change") -> ok | R25: =R24 -> 10890 | S25: =R25-R24 -> 0 | T25: =T24 -> 176718.7 | U25: =SUM(T25-T24) -> 0 | V25: =IF(S25>0,U25/S25,0) -> 0 | X25: =X24 -> 11169 | Y25: =IF(R25-X25<=0,"ok","oil change") -> ok | Z25: =C25+K25+S25 -> 0 | AA25: =U25+M25+E25 -> 0 | AB25: =V25+N25+F25 -> 0 | AC25: =IF(Z25>0,AA25/Z25,0) -> 0 | AD25: =ELEC!Q25 -> 0 | AE25: =SUM(AD25/Z25) -> #DIV/0! | AF25: =SUM(AE25/1600) -> #DIV/0! | AG25: =SUM(320*AF25) -> #DIV/0! | AH25: =SUM(AC25-AG25) -> #DIV/0! | AI25: =AD25*AJ25 -> 0 | AJ25: =305/1185 -> 0.25738397 | AK25: =IF(Z25>0,AI25/Z25,0) -> 0
A26: =ELEC!C26 -> 43854 | B26: =B25 -> 8487 | C26: =B26-B25 -> 0 | D26: =D25 -> 118922.6 | E26: =SUM(D26-D25) -> 0 | F26: =IF(C26>0,E26/C26,0) -> 0 | H26: =H25 -> 8497 | I26: =IF(B26-H26<=0,"ok","oil change") -> ok | J26: =J25 -> 10680 | K26: =J26-J25 -> 0 | L26: =L25 -> 234681.6 | M26: =SUM(L26-L25) -> 0 | N26: =IF(K26>0,M26/K26,0) -> 0 | P26: =P25 -> 10873 | Q26: =IF(J26-P26<=0,"ok","oil change") -> ok | R26: =R25 -> 10890 | S26: =R26-R25 -> 0 | T26: =T25 -> 176718.7 | U26: =SUM(T26-T25) -> 0 | V26: =IF(S26>0,U26/S26,0) -> 0 | X26: =X25 -> 11169 | Y26: =IF(R26-X26<=0,"ok","oil change") -> ok | Z26: =C26+K26+S26 -> 0 | AA26: =U26+M26+E26 -> 0 | AB26: =V26+N26+F26 -> 0 | AC26: =IF(Z26>0,AA26/Z26,0) -> 0 | AD26: =ELEC!Q26 -> 0 | AE26: =SUM(AD26/Z26) -> #DIV/0! | AF26: =SUM(AE26/1600) -> #DIV/0! | AG26: =SUM(320*AF26) -> #DIV/0! | AH26: =SUM(AC26-AG26) -> #DIV/0! | AI26: =AD26*AJ26 -> 0 | AJ26: =305/1185 -> 0.25738397 | AK26: =IF(Z26>0,AI26/Z26,0) -> 0
A27: =ELEC!C27 -> 43855 | B27: =B26 -> 8487 | C27: =B27-B26 -> 0 | D27: =D26 -> 118922.6 | E27: =SUM(D27-D26) -> 0 | F27: =IF(C27>0,E27/C27,0) -> 0 | H27: =H26 -> 8497 | I27: =IF(B27-H27<=0,"ok","oil change") -> ok | J27: =J26 -> 10680 | K27: =J27-J26 -> 0 | L27: =L26 -> 234681.6 | M27: =SUM(L27-L26) -> 0 | N27: =IF(K27>0,M27/K27,0) -> 0 | P27: =P26 -> 10873 | Q27: =IF(J27-P27<=0,"ok","oil change") -> ok | R27: =R26 -> 10890 | S27: =R27-R26 -> 0 | T27: =T26 -> 176718.7 | U27: =SUM(T27-T26) -> 0 | V27: =IF(S27>0,U27/S27,0) -> 0 | X27: =X26 -> 11169 | Y27: =IF(R27-X27<=0,"ok","oil change") -> ok | Z27: =C27+K27+S27 -> 0 | AA27: =U27+M27+E27 -> 0 | AB27: =V27+N27+F27 -> 0 | AC27: =IF(Z27>0,AA27/Z27,0) -> 0 | AD27: =ELEC!Q27 -> 0 | AE27: =SUM(AD27/Z27) -> #DIV/0! | AF27: =SUM(AE27/1600) -> #DIV/0! | AG27: =SUM(320*AF27) -> #DIV/0! | AH27: =SUM(AC27-AG27) -> #DIV/0! | AI27: =AD27*AJ27 -> 0 | AJ27: =305/1185 -> 0.25738397 | AK27: =IF(Z27>0,AI27/Z27,0) -> 0
A28: =ELEC!C28 -> 43856 | B28: =B27 -> 8487 | C28: =B28-B27 -> 0 | D28: =D27 -> 118922.6 | E28: =SUM(D28-D27) -> 0 | F28: =IF(C28>0,E28/C28,0) -> 0 | H28: =H27 -> 8497 | I28: =IF(B28-H28<=0,"ok","oil change") -> ok | J28: =J27 -> 10680 | K28: =J28-J27 -> 0 | L28: =L27 -> 234681.6 | M28: =SUM(L28-L27) -> 0 | N28: =IF(K28>0,M28/K28,0) -> 0 | P28: =P27 -> 10873 | Q28: =IF(J28-P28<=0,"ok","oil change") -> ok | R28: =R27 -> 10890 | S28: =R28-R27 -> 0 | T28: =T27 -> 176718.7 | U28: =SUM(T28-T27) -> 0 | V28: =IF(S28>0,U28/S28,0) -> 0 | X28: =X27 -> 11169 | Y28: =IF(R28-X28<=0,"ok","oil change") -> ok | Z28: =C28+K28+S28 -> 0 | AA28: =U28+M28+E28 -> 0 | AB28: =V28+N28+F28 -> 0 | AC28: =IF(Z28>0,AA28/Z28,0) -> 0 | AD28: =ELEC!Q28 -> 0 | AE28: =SUM(AD28/Z28) -> #DIV/0! | AF28: =SUM(AE28/1600) -> #DIV/0! | AG28: =SUM(320*AF28) -> #DIV/0! | AH28: =SUM(AC28-AG28) -> #DIV/0! | AI28: =AD28*AJ28 -> 0 | AJ28: =305/1185 -> 0.25738397 | AK28: =IF(Z28>0,AI28/Z28,0) -> 0
A29: =ELEC!C29 -> 43857 | B29: =B28 -> 8487 | C29: =B29-B28 -> 0 | D29: =D28 -> 118922.6 | E29: =SUM(D29-D28) -> 0 | F29: =IF(C29>0,E29/C29,0) -> 0 | H29: =H28 -> 8497 | I29: =IF(B29-H29<=0,"ok","oil change") -> ok | J29: =J28 -> 10680 | K29: =J29-J28 -> 0 | L29: =L28 -> 234681.6 | M29: =SUM(L29-L28) -> 0 | N29: =IF(K29>0,M29/K29,0) -> 0 | P29: =P28 -> 10873 | Q29: =IF(J29-P29<=0,"ok","oil change") -> ok | R29: =R28 -> 10890 | S29: =R29-R28 -> 0 | T29: =T28 -> 176718.7 | U29: =SUM(T29-T28) -> 0 | V29: =IF(S29>0,U29/S29,0) -> 0 | X29: =X28 -> 11169 | Y29: =IF(R29-X29<=0,"ok","oil change") -> ok | Z29: =C29+K29+S29 -> 0 | AA29: =U29+M29+E29 -> 0 | AB29: =V29+N29+F29 -> 0 | AC29: =IF(Z29>0,AA29/Z29,0) -> 0 | AD29: =ELEC!Q29 -> 0 | AE29: =SUM(AD29/Z29) -> #DIV/0! | AF29: =SUM(AE29/1600) -> #DIV/0! | AG29: =SUM(320*AF29) -> #DIV/0! | AH29: =SUM(AC29-AG29) -> #DIV/0! | AI29: =AD29*AJ29 -> 0 | AJ29: =305/1185 -> 0.25738397 | AK29: =IF(Z29>0,AI29/Z29,0) -> 0
A30: =ELEC!C30 -> 43858 | B30: =B29 -> 8487 | C30: =B30-B29 -> 0 | D30: =D29 -> 118922.6 | E30: =SUM(D30-D29) -> 0 | F30: =IF(C30>0,E30/C30,0) -> 0 | H30: =H29 -> 8497 | I30: =IF(B30-H30<=0,"ok","oil change") -> ok | J30: =J29 -> 10680 | K30: =J30-J29 -> 0 | L30: =L29 -> 234681.6 | M30: =SUM(L30-L29) -> 0 | N30: =IF(K30>0,M30/K30,0) -> 0 | P30: =P29 -> 10873 | Q30: =IF(J30-P30<=0,"ok","oil change") -> ok | R30: =R29 -> 10890 | S30: =R30-R29 -> 0 | T30: =T29 -> 176718.7 | U30: =SUM(T30-T29) -> 0 | V30: =IF(S30>0,U30/S30,0) -> 0 | X30: =X29 -> 11169 | Y30: =IF(R30-X30<=0,"ok","oil change") -> ok | Z30: =C30+K30+S30 -> 0 | AA30: =U30+M30+E30 -> 0 | AB30: =V30+N30+F30 -> 0 | AC30: =IF(Z30>0,AA30/Z30,0) -> 0 | AD30: =ELEC!Q30 -> 0 | AE30: =SUM(AD30/Z30) -> #DIV/0! | AF30: =SUM(AE30/1600) -> #DIV/0! | AG30: =SUM(320*AF30) -> #DIV/0! | AH30: =SUM(AC30-AG30) -> #DIV/0! | AI30: =AD30*AJ30 -> 0 | AJ30: =305/1185 -> 0.25738397 | AK30: =IF(Z30>0,AI30/Z30,0) -> 0
A31: =ELEC!C31 -> 43859 | B31: =B30 -> 8487 | C31: =B31-B30 -> 0 | D31: =D30 -> 118922.6 | E31: =SUM(D31-D30) -> 0 | F31: =IF(C31>0,E31/C31,0) -> 0 | H31: =H30 -> 8497 | I31: =IF(B31-H31<=0,"ok","oil change") -> ok | J31: =J30 -> 10680 | K31: =J31-J30 -> 0 | L31: =L30 -> 234681.6 | M31: =SUM(L31-L30) -> 0 | N31: =IF(K31>0,M31/K31,0) -> 0 | P31: =P30 -> 10873 | Q31: =IF(J31-P31<=0,"ok","oil change") -> ok | R31: =R30 -> 10890 | S31: =R31-R30 -> 0 | T31: =T30 -> 176718.7 | U31: =SUM(T31-T30) -> 0 | V31: =IF(S31>0,U31/S31,0) -> 0 | X31: =X30 -> 11169 | Y31: =IF(R31-X31<=0,"ok","oil change") -> ok | Z31: =C31+K31+S31 -> 0 | AA31: =U31+M31+E31 -> 0 | AB31: =V31+N31+F31 -> 0 | AC31: =IF(Z31>0,AA31/Z31,0) -> 0 | AD31: =ELEC!Q31 -> 0 | AE31: =SUM(AD31/Z31) -> #DIV/0! | AF31: =SUM(AE31/1600) -> #DIV/0! | AG31: =SUM(320*AF31) -> #DIV/0! | AH31: =SUM(AC31-AG31) -> #DIV/0! | AI31: =AD31*AJ31 -> 0 | AJ31: =305/1185 -> 0.25738397 | AK31: =IF(Z31>0,AI31/Z31,0) -> 0
A32: =ELEC!C32 -> 43860 | B32: =B31 -> 8487 | C32: =B32-B31 -> 0 | D32: =D31 -> 118922.6 | E32: =SUM(D32-D31) -> 0 | F32: =IF(C32>0,E32/C32,0) -> 0 | H32: =H31 -> 8497 | I32: =IF(B32-H32<=0,"ok","oil change") -> ok | J32: =J31 -> 10680 | K32: =J32-J31 -> 0 | L32: =L31 -> 234681.6 | M32: =SUM(L32-L31) -> 0 | N32: =IF(K32>0,M32/K32,0) -> 0 | P32: =P31 -> 10873 | Q32: =IF(J32-P32<=0,"ok","oil change") -> ok | R32: =R31 -> 10890 | S32: =R32-R31 -> 0 | T32: =T31 -> 176718.7 | U32: =SUM(T32-T31) -> 0 | V32: =IF(S32>0,U32/S32,0) -> 0 | X32: =X31 -> 11169 | Y32: =IF(R32-X32<=0,"ok","oil change") -> ok | Z32: =C32+K32+S32 -> 0 | AA32: =U32+M32+E32 -> 0 | AB32: =V32+N32+F32 -> 0 | AC32: =IF(Z32>0,AA32/Z32,0) -> 0 | AD32: =ELEC!Q32 -> 0 | AE32: =SUM(AD32/Z32) -> #DIV/0! | AF32: =SUM(AE32/1600) -> #DIV/0! | AG32: =SUM(320*AF32) -> #DIV/0! | AH32: =SUM(AC32-AG32) -> #DIV/0! | AI32: =AD32*AJ32 -> 0 | AJ32: =305/1185 -> 0.25738397 | AK32: =IF(Z32>0,AI32/Z32,0) -> 0
