Workbook

Sheet Total
A1: Site Name | B1: Day | C1: Month | D1: Year | E1: Total Electricity Kwh | F1: Electricity Tariff ($/Kwh) | G1: LPG (Kg) | H1: LPG $/Kg | I1: Water Utility Supply (m3) m3 | J1: Water Utility Supply (m3) $/m3 | K1: Room Nights | L1: Utilities day cost dh
A2: Serengeti | B2: 1 | C2: 2 | D2: 2020 | E2: ='UTILITY REPORT 1'!F3 -> 4580 | F2: =('UTILITY REPORT 1'!E3*'UTILITY REPORT 1'!D3)/'UTILITY REPORT 1'!F3 -> 0.39841703 | G2: =IF('Utility summery'!M6<0,"0",'Utility summery'!M6) -> 94.512 | H2: 0 | I2: =IF('UTILITY REPORT 1'!G3<0,"0",'UTILITY REPORT 1'!G3) -> 113 | J2: 0 | K2: ='UTILITY REPORT 1'!C3 -> 18 | L2: =E2*F2+G2*H2+#REF!*#REF!+I2*J2 -> #REF!
A3: Serengeti | B3: =B2+1 -> 2 | C3: 2 | D3: 2020 | E3: ='UTILITY REPORT 1'!F4 -> 4303 | F3: =('UTILITY REPORT 1'!E4*'UTILITY REPORT 1'!D4)/'UTILITY REPORT 1'!F4 -> 0.41897513 | G3: =IF('Utility summery'!M7<0,"0",'Utility summery'!M7) -> 104.632 | H3: 0 | I3: =IF('UTILITY REPORT 1'!G4<0,"0",'UTILITY REPORT 1'!G4) -> 97 | J3: 0 | K3: ='UTILITY REPORT 1'!C4 -> 18 | L3: =E3*F3+G3*H3+#REF!*#REF!+I3*J3 -> #REF!
A4: Serengeti | B4: =B3+1 -> 3 | C4: 2 | D4: 2020 | E4: ='UTILITY REPORT 1'!F5 -> 4514 | F4: =('UTILITY REPORT 1'!E5*'UTILITY REPORT 1'!D5)/'UTILITY REPORT 1'!F5 -> 0.42554719 | G4: =IF('Utility summery'!M8<0,"0",'Utility summery'!M8) -> 0 | H4: 0 | I4: =IF('UTILITY REPORT 1'!G5<0,"0",'UTILITY REPORT 1'!G5) -> 107 | J4: 0 | K4: ='UTILITY REPORT 1'!C5 -> 8 | L4: =E4*F4+G4*H4+#REF!*#REF!+I4*J4 -> #REF!
A5: Serengeti | B5: =B4+1 -> 4 | C5: 2 | D5: 2020 | E5: ='UTILITY REPORT 1'!F6 -> 5690 | F5: =('UTILITY REPORT 1'!E6*'UTILITY REPORT 1'!D6)/'UTILITY REPORT 1'!F6 -> 0.41460808 | G5: =IF('Utility summery'!M9<0,"0",'Utility summery'!M9) -> 112.728 | H5: 0 | I5: =IF('UTILITY REPORT 1'!G6<0,"0",'UTILITY REPORT 1'!G6) -> 139 | J5: 0 | K5: ='UTILITY REPORT 1'!C6 -> 77 | L5: =E5*F5+G5*H5+#REF!*#REF!+I5*J5 -> #REF!
A6: Serengeti | B6: =B5+1 -> 5 | C6: 2 | D6: 2020 | E6: ='UTILITY REPORT 1'!F7 -> 5866 | F6: =('UTILITY REPORT 1'!E7*'UTILITY REPORT 1'!D7)/'UTILITY REPORT 1'!F7 -> 0.3847136 | G6: =IF('Utility summery'!M10<0,"0",'Utility summery'!M10) -> 106.92 | H6: 0 | I6: =IF('UTILITY REPORT 1'!G7<0,"0",'UTILITY REPORT 1'!G7) -> 141 | J6: 0 | K6: ='UTILITY REPORT 1'!C7 -> 77 | L6: =E6*F6+G6*H6+#REF!*#REF!+I6*J6 -> #REF!
A7: Serengeti | B7: =B6+1 -> 6 | C7: 2 | D7: 2020 | E7: ='UTILITY REPORT 1'!F8 -> 5875 | F7: =('UTILITY REPORT 1'!E8*'UTILITY REPORT 1'!D8)/'UTILITY REPORT 1'!F8 -> 0.42408681 | G7: =IF('Utility summery'!M11<0,"0",'Utility summery'!M11) -> 102.124 | H7: 0 | I7: =IF('UTILITY REPORT 1'!G8<0,"0",'UTILITY REPORT 1'!G8) -> 129 | J7: 0 | K7: ='UTILITY REPORT 1'!C8 -> 77 | L7: =E7*F7+G7*H7+#REF!*#REF!+I7*J7 -> #REF!
A8: Serengeti | B8: =B7+1 -> 7 | C8: 2 | D8: 2020 | E8: ='UTILITY REPORT 1'!F9 -> 5952 | F8: =('UTILITY REPORT 1'!E9*'UTILITY REPORT 1'!D9)/'UTILITY REPORT 1'!F9 -> 0.37714046 | G8: =IF('Utility summery'!M12<0,"0",'Utility summery'!M12) -> 108.196 | H8: 0 | I8: =IF('UTILITY REPORT 1'!G9<0,"0",'UTILITY REPORT 1'!G9) -> 129 | J8: 0 | K8: ='UTILITY REPORT 1'!C9 -> 77 | L8: =E8*F8+G8*H8+#REF!*#REF!+I8*J8 -> #REF!
A9: Serengeti | B9: =B8+1 -> 8 | C9: 2 | D9: 2020 | E9: ='UTILITY REPORT 1'!F10 -> 5988 | F9: =('UTILITY REPORT 1'!E10*'UTILITY REPORT 1'!D10)/'UTILITY REPORT 1'!F10 -> 0.42909987 | G9: =IF('Utility summery'!M13<0,"0",'Utility summery'!M13) -> 112.156 | H9: 0 | I9: =IF('UTILITY REPORT 1'!G10<0,"0",'UTILITY REPORT 1'!G10) -> 128 | J9: 0 | K9: ='UTILITY REPORT 1'!C10 -> 13 | L9: =E9*F9+G9*H9+#REF!*#REF!+I9*J9 -> #REF!
A10: Serengeti | B10: =B9+1 -> 9 | C10: 2 | D10: 2020 | E10: ='UTILITY REPORT 1'!F11 -> 5209 | F10: =('UTILITY REPORT 1'!E11*'UTILITY REPORT 1'!D11)/'UTILITY REPORT 1'!F11 -> 0.39159532 | G10: =IF('Utility summery'!M14<0,"0",'Utility summery'!M14) -> 103.444 | H10: 0 | I10: =IF('UTILITY REPORT 1'!G11<0,"0",'UTILITY REPORT 1'!G11) -> 96 | J10: 0 | K10: ='UTILITY REPORT 1'!C11 -> 16 | L10: =E10*F10+G10*H10+#REF!*#REF!+I10*J10 -> #REF!
A11: Serengeti | B11: =B10+1 -> 10 | C11: 2 | D11: 2020 | E11: ='UTILITY REPORT 1'!F12 -> 0 | F11: =('UTILITY REPORT 1'!E12*'UTILITY REPORT 1'!D12)/'UTILITY REPORT 1'!F12 -> #DIV/0! | G11: =IF('Utility summery'!M15<0,"0",'Utility summery'!M15) -> 0 | H11: 0 | I11: =IF('UTILITY REPORT 1'!G12<0,"0",'UTILITY REPORT 1'!G12) -> 0 | J11: 0 | K11: ='UTILITY REPORT 1'!C12 -> 15 | L11: =E11*F11+G11*H11+#REF!*#REF!+I11*J11 -> #DIV/0!
A12: Serengeti | B12: =B11+1 -> 11 | C12: 2 | D12: 2020 | E12: ='UTILITY REPORT 1'!F13 -> 0 | F12: =('UTILITY REPORT 1'!E13*'UTILITY REPORT 1'!D13)/'UTILITY REPORT 1'!F13 -> #DIV/0! | G12: =IF('Utility summery'!M16<0,"0",'Utility summery'!M16) -> 0 | H12: 0 | I12: =IF('UTILITY REPORT 1'!G13<0,"0",'UTILITY REPORT 1'!G13) -> 0 | J12: 0 | K12: ='UTILITY REPORT 1'!C13 -> 0 | L12: =E12*F12+G12*H12+#REF!*#REF!+I12*J12 -> #DIV/0!
A13: Serengeti | B13: =B12+1 -> 12 | C13: 2 | D13: 2020 | E13: ='UTILITY REPORT 1'!F14 -> 0 | F13: =('UTILITY REPORT 1'!E14*'UTILITY REPORT 1'!D14)/'UTILITY REPORT 1'!F14 -> #DIV/0! | G13: =IF('Utility summery'!M17<0,"0",'Utility summery'!M17) -> 0 | H13: 0 | I13: =IF('UTILITY REPORT 1'!G14<0,"0",'UTILITY REPORT 1'!G14) -> 0 | J13: 0 | K13: ='UTILITY REPORT 1'!C14 -> 0 | L13: =E13*F13+G13*H13+#REF!*#REF!+I13*J13 -> #DIV/0!
A14: Serengeti | B14: =B13+1 -> 13 | C14: 2 | D14: 2020 | E14: ='UTILITY REPORT 1'!F15 -> 0 | F14: =('UTILITY REPORT 1'!E15*'UTILITY REPORT 1'!D15)/'UTILITY REPORT 1'!F15 -> #DIV/0! | G14: =IF('Utility summery'!M18<0,"0",'Utility summery'!M18) -> 0 | H14: 0 | I14: =IF('UTILITY REPORT 1'!G15<0,"0",'UTILITY REPORT 1'!G15) -> 0 | J14: 0 | K14: ='UTILITY REPORT 1'!C15 -> 0 | L14: =E14*F14+G14*H14+#REF!*#REF!+I14*J14 -> #DIV/0!
... A30: Serengeti | B30: =B29+1 -> 29 | C30: 2 | D30: 2020 | E30: ='UTILITY REPORT 1'!F31 -> 0 | F30: =('UTILITY REPORT 1'!E31*'UTILITY REPORT 1'!D31)/'UTILITY REPORT 1'!F31 -> #DIV/0! | G30: =IF('Utility summery'!M34<0,"0",'Utility summery'!M34) -> 0 | H30: 0 | I30: =IF('UTILITY REPORT 1'!G31<0,"0",'UTILITY REPORT 1'!G31) -> 0 | J30: 0 | K30: ='UTILITY REPORT 1'!C31 -> 0 | L30: =E30*F30+G30*H30+#REF!*#REF!+I30*J30 -> #DIV/0!
A31: Serengeti | B31: 1 | C31: 3 | D31: 2020 | E31: ='UTILITY REPORT 1'!F32 -> 0 | F31: =('UTILITY REPORT 1'!E32*'UTILITY REPORT 1'!D32)/'UTILITY REPORT 1'!F32 -> #DIV/0! | G31: =IF('Utility summery'!M35<0,"0",'Utility summery'!M35) -> 0 | H31: 0 | I31: =IF('UTILITY REPORT 1'!G32<0,"0",'UTILITY REPORT 1'!G32) -> 0 | J31: 0 | K31: ='UTILITY REPORT 1'!C32 -> 0 | L31: =E31*F31+G31*H31+#REF!*#REF!+I31*J31 -> #DIV/0!
A32: Serengeti | B32: 2 | C32: 3 | D32: 2020 | E32: ='UTILITY REPORT 1'!F33 -> 0 | F32: =('UTILITY REPORT 1'!E33*'UTILITY REPORT 1'!D33)/'UTILITY REPORT 1'!F33 -> #DIV/0! | G32: =IF('Utility summery'!M36<0,"0",'Utility summery'!M36) -> 0 | H32: 0 | I32: =IF('UTILITY REPORT 1'!G33<0,"0",'UTILITY REPORT 1'!G33) -> 0 | J32: 0 | K32: ='UTILITY REPORT 1'!C33 -> 0

Sheet Submetering
A1: Site Name | B1: Day | C1: Month | D1: Year | E1: Transport Consumption (LT) | F1: Generators Consumption (LT) | G1: Total Electricity Kwh | H1: Kitchen (KWh) | I1: Laundry (KWh) | J1: STP (M3) | K1: RO prodution (M3) | L1: Amani Restaurant (M3) | M1: Kitchen (M3) | N1: Laundry (M3) | O1: Laundry (M3) | P1: Total water Consumption (M3) | Q1: Borehole #1 (M3) | R1: Borehole #2 (M3) | S1: Borehole #3 (M3) | T1: Borehole #4 (M3) | U1: Borehole #5 (M3) | V1: Borehole #6 (M3) | W1: Total Bore holes production (M3) | X1: Room Nights
A2: Serengeti | B2: 1 | C2: 2 | D2: 2020 | E2: ='UTILITY REPORT 1'!I3 -> 83.21 | F2: ='UTILITY REPORT 1'!E3 -> 1824.75 | G2: ='UTILITY REPORT 1'!F3 -> 4580 | H2: =IF('Kit report'!F4<0,"0",'Kit report'!F4) -> 444 | I2: =IF('Kit report'!X4<0,"0",'Kit report'!X4) -> 700 | J2: =IF('Utility summery'!H6<0,"0",'Utility summery'!H6) -> 53 | K2: =IF('UTILITY REPORT 1'!H3<0,"0",'UTILITY REPORT 1'!H3) -> 115 | L2: ='Water-Meter'!K6 -> 3 | M2: ='Water-Meter'!H6 -> 0 | N2: ='Water-Meter'!Q6 -> 9 | O2: =K2*E2+H2*I2+#REF!*#REF!+J2*L2 -> #REF! | P2: ='Water-Meter'!E6 -> 113 | Q2: =IF('Water-Meter'!U6<0,"0",'Water-Meter'!U6) -> 49 | R2: =IF('Water-Meter'!X6<0,"0",'Water-Meter'!X6) -> 62 | S2: =IF('Water-Meter'!AA6<0,"0",'Water-Meter'!AA6) -> 50 | T2: =IF('Water-Meter'!AD6<0,"0",'Water-Meter'!AD6) -> 15 | U2: =IF('Water-Meter'!AG6<0,"0",'Water-Meter'!AG6) -> 24 | V2: =IF('Water-Meter'!AJ6<0,"0",'Water-Meter'!AJ6) -> 0 | W2: ='Water-Meter'!AN6 -> 200 | X2: =Total!K2 -> 18
A3: Serengeti | B3: =B2+1 -> 2 | C3: 2 | D3: 2020 | E3: ='UTILITY REPORT 1'!I4 -> 130.39 | F3: ='UTILITY REPORT 1'!E4 -> 1802.85 | G3: ='UTILITY REPORT 1'!F4 -> 4303 | H3: =IF('Kit report'!F5<0,"0",'Kit report'!F5) -> 468 | I3: =IF('Kit report'!X5<0,"0",'Kit report'!X5) -> 700 | J3: =IF('Utility summery'!H7<0,"0",'Utility summery'!H7) -> 63 | K3: =IF('UTILITY REPORT 1'!H4<0,"0",'UTILITY REPORT 1'!H4) -> 101 | L3: ='Water-Meter'!K7 -> 2 | M3: ='Water-Meter'!H7 -> 0 | N3: ='Water-Meter'!Q7 -> 8 | O3: =K3*E3+H3*I3+#REF!*#REF!+J3*L3 -> #REF! | P3: ='Water-Meter'!E7 -> 97 | Q3: =IF('Water-Meter'!U7<0,"0",'Water-Meter'!U7) -> 19 | R3: =IF('Water-Meter'!X7<0,"0",'Water-Meter'!X7) -> 30 | S3: =IF('Water-Meter'!AA7<0,"0",'Water-Meter'!AA7) -> 50 | T3: =IF('Water-Meter'!AD7<0,"0",'Water-Meter'!AD7) -> 16 | U3: =IF('Water-Meter'!AG7<0,"0",'Water-Meter'!AG7) -> 25 | V3: =IF('Water-Meter'!AJ7<0,"0",'Water-Meter'!AJ7) -> 0 | W3: ='Water-Meter'!AN7 -> 140 | X3: =Total!K3 -> 18
A4: Serengeti | B4: =B3+1 -> 3 | C4: 2 | D4: 2020 | E4: ='UTILITY REPORT 1'!I5 -> 178.75 | F4: ='UTILITY REPORT 1'!E5 -> 1920.92 | G4: ='UTILITY REPORT 1'!F5 -> 4514 | H4: =IF('Kit report'!F6<0,"0",'Kit report'!F6) -> 516 | I4: =IF('Kit report'!X6<0,"0",'Kit report'!X6) -> 960 | J4: =IF('Utility summery'!H8<0,"0",'Utility summery'!H8) -> 60 | K4: =IF('UTILITY REPORT 1'!H5<0,"0",'UTILITY REPORT 1'!H5) -> 81 | L4: ='Water-Meter'!K8 -> 3 | M4: ='Water-Meter'!H8 -> 0 | N4: ='Water-Meter'!Q8 -> 10 | O4: =K4*E4+H4*I4+#REF!*#REF!+J4*L4 -> #REF! | P4: ='Water-Meter'!E8 -> 107 | Q4: =IF('Water-Meter'!U8<0,"0",'Water-Meter'!U8) -> 0 | R4: =IF('Water-Meter'!X8<0,"0",'Water-Meter'!X8) -> 0 | S4: =IF('Water-Meter'!AA8<0,"0",'Water-Meter'!AA8) -> 50 | T4: =IF('Water-Meter'!AD8<0,"0",'Water-Meter'!AD8) -> 17 | U4: =IF('Water-Meter'!AG8<0,"0",'Water-Meter'!AG8) -> 26 | V4: =IF('Water-Meter'!AJ8<0,"0",'Water-Meter'!AJ8) -> 0 | W4: ='Water-Meter'!AN8 -> 93 | X4: =Total!K4 -> 8
A5: Serengeti | B5: =B4+1 -> 4 | C5: 2 | D5: 2020 | E5: ='UTILITY REPORT 1'!I6 -> 89.65 | F5: ='UTILITY REPORT 1'!E6 -> 2359.12 | G5: ='UTILITY REPORT 1'!F6 -> 5690 | H5: =IF('Kit report'!F7<0,"0",'Kit report'!F7) -> 492 | I5: =IF('Kit report'!X7<0,"0",'Kit report'!X7) -> 1060 | J5: =IF('Utility summery'!H9<0,"0",'Utility summery'!H9) -> 63 | K5: =IF('UTILITY REPORT 1'!H6<0,"0",'UTILITY REPORT 1'!H6) -> 100 | L5: ='Water-Meter'!K9 -> 4 | M5: ='Water-Meter'!H9 -> 0 | N5: ='Water-Meter'!Q9 -> 5 | O5: =K5*E5+H5*I5+#REF!*#REF!+J5*L5 -> #REF! | P5: ='Water-Meter'!E9 -> 139 | Q5: =IF('Water-Meter'!U9<0,"0",'Water-Meter'!U9) -> 0 | R5: =IF('Water-Meter'!X9<0,"0",'Water-Meter'!X9) -> 0 | S5: =IF('Water-Meter'!AA9<0,"0",'Water-Meter'!AA9) -> 52 | T5: =IF('Water-Meter'!AD9<0,"0",'Water-Meter'!AD9) -> 17 | U5: =IF('Water-Meter'!AG9<0,"0",'Water-Meter'!AG9) -> 25 | V5: =IF('Water-Meter'!AJ9<0,"0",'Water-Meter'!AJ9) -> 0 | W5: ='Water-Meter'!AN9 -> 94 | X5: =Total!K5 -> 77
A6: Serengeti | B6: =B5+1 -> 5 | C6: 2 | D6: 2020 | E6: ='UTILITY REPORT 1'!I7 -> 129.27 | F6: ='UTILITY REPORT 1'!E7 -> 2256.73 | G6: ='UTILITY REPORT 1'!F7 -> 5866 | H6: =IF('Kit report'!F8<0,"0",'Kit report'!F8) -> 552 | I6: =IF('Kit report'!X8<0,"0",'Kit report'!X8) -> 840 | J6: =IF('Utility summery'!H10<0,"0",'Utility summery'!H10) -> 63 | K6: =IF('UTILITY REPORT 1'!H7<0,"0",'UTILITY REPORT 1'!H7) -> 98 | L6: ='Water-Meter'!K10 -> 5 | M6: ='Water-Meter'!H10 -> 0 | N6: ='Water-Meter'!Q10 -> 4 | O6: =K6*E6+H6*I6+#REF!*#REF!+J6*L6 -> #REF! | P6: ='Water-Meter'!E10 -> 141 | Q6: =IF('Water-Meter'!U10<0,"0",'Water-Meter'!U10) -> 49 | R6: =IF('Water-Meter'!X10<0,"0",'Water-Meter'!X10) -> 55 | S6: =IF('Water-Meter'!AA10<0,"0",'Water-Meter'!AA10) -> 39 | T6: =IF('Water-Meter'!AD10<0,"0",'Water-Meter'!AD10) -> 12 | U6: =IF('Water-Meter'!AG10<0,"0",'Water-Meter'!AG10) -> 23 | V6: =IF('Water-Meter'!AJ10<0,"0",'Water-Meter'!AJ10) -> 0 | W6: ='Water-Meter'!AN10 -> 178 | X6: =Total!K6 -> 77
A7: Serengeti | B7: =B6+1 -> 6 | C7: 2 | D7: 2020 | E7: ='UTILITY REPORT 1'!I8 -> 187.64 | F7: ='UTILITY REPORT 1'!E8 -> 2491.51 | G7: ='UTILITY REPORT 1'!F8 -> 5875 | H7: =IF('Kit report'!F9<0,"0",'Kit report'!F9) -> 540 | I7: =IF('Kit report'!X9<0,"0",'Kit report'!X9) -> 1060 | J7: =IF('Utility summery'!H11<0,"0",'Utility summery'!H11) -> 56 | K7: =IF('UTILITY REPORT 1'!H8<0,"0",'UTILITY REPORT 1'!H8) -> 83 | L7: ='Water-Meter'!K11 -> 4 | M7: ='Water-Meter'!H11 -> 0 | N7: ='Water-Meter'!Q11 -> 15 | O7: =K7*E7+H7*I7+#REF!*#REF!+J7*L7 -> #REF! | P7: ='Water-Meter'!E11 -> 129 | Q7: =IF('Water-Meter'!U11<0,"0",'Water-Meter'!U11) -> 53 | R7: =IF('Water-Meter'!X11<0,"0",'Water-Meter'!X11) -> 65 | S7: =IF('Water-Meter'!AA11<0,"0",'Water-Meter'!AA11) -> 33 | T7: =IF('Water-Meter'!AD11<0,"0",'Water-Meter'!AD11) -> 13 | U7: =IF('Water-Meter'!AG11<0,"0",'Water-Meter'!AG11) -> 24 | V7: =IF('Water-Meter'!AJ11<0,"0",'Water-Meter'!AJ11) -> 0 | W7: ='Water-Meter'!AN11 -> 188 | X7: =Total!K7 -> 77
A8: Serengeti | B8: =B7+1 -> 7 | C8: 2 | D8: 2020 | E8: ='UTILITY REPORT 1'!I9 -> 203.15 | F8: ='UTILITY REPORT 1'!E9 -> 2244.74 | G8: ='UTILITY REPORT 1'!F9 -> 5952 | H8: =IF('Kit report'!F10<0,"0",'Kit report'!F10) -> 564 | I8: =IF('Kit report'!X10<0,"0",'Kit report'!X10) -> 1200 | J8: =IF('Utility summery'!H12<0,"0",'Utility summery'!H12) -> 0 | K8: =IF('UTILITY REPORT 1'!H9<0,"0",'UTILITY REPORT 1'!H9) -> 103 | L8: ='Water-Meter'!K12 -> 4 | M8: ='Water-Meter'!H12 -> 0 | N8: ='Water-Meter'!Q12 -> 11 | O8: =K8*E8+H8*I8+#REF!*#REF!+J8*L8 -> #REF! | P8: ='Water-Meter'!E12 -> 129 | Q8: =IF('Water-Meter'!U12<0,"0",'Water-Meter'!U12) -> 52 | R8: =IF('Water-Meter'!X12<0,"0",'Water-Meter'!X12) -> 60 | S8: =IF('Water-Meter'!AA12<0,"0",'Water-Meter'!AA12) -> 30 | T8: =IF('Water-Meter'!AD12<0,"0",'Water-Meter'!AD12) -> 13 | U8: =IF('Water-Meter'!AG12<0,"0",'Water-Meter'!AG12) -> 23 | V8: =IF('Water-Meter'!AJ12<0,"0",'Water-Meter'!AJ12) -> 0 | W8: ='Water-Meter'!AN12 -> 178 | X8: =Total!K8 -> 77
A9: Serengeti | B9: =B8+1 -> 8 | C9: 2 | D9: 2020 | E9: ='UTILITY REPORT 1'!I10 -> 56.74 | F9: ='UTILITY REPORT 1'!E10 -> 2569.45 | G9: ='UTILITY REPORT 1'!F10 -> 5988 | H9: =IF('Kit report'!F11<0,"0",'Kit report'!F11) -> 564 | I9: =IF('Kit report'!X11<0,"0",'Kit report'!X11) -> 1220 | J9: =IF('Utility summery'!H13<0,"0",'Utility summery'!H13) -> 0 | K9: =IF('UTILITY REPORT 1'!H10<0,"0",'UTILITY REPORT 1'!H10) -> 105 | L9: ='Water-Meter'!K13 -> 4 | M9: ='Water-Meter'!H13 -> 0 | N9: ='Water-Meter'!Q13 -> 13 | O9: =K9*E9+H9*I9+#REF!*#REF!+J9*L9 -> #REF! | P9: ='Water-Meter'!E13 -> 128 | Q9: =IF('Water-Meter'!U13<0,"0",'Water-Meter'!U13) -> 53 | R9: =IF('Water-Meter'!X13<0,"0",'Water-Meter'!X13) -> 55 | S9: =IF('Water-Meter'!AA13<0,"0",'Water-Meter'!AA13) -> 40 | T9: =IF('Water-Meter'!AD13<0,"0",'Water-Meter'!AD13) -> 14 | U9: =IF('Water-Meter'!AG13<0,"0",'Water-Meter'!AG13) -> 22 | V9: =IF('Water-Meter'!AJ13<0,"0",'Water-Meter'!AJ13) -> 0 | W9: ='Water-Meter'!AN13 -> 184 | X9: =Total!K9 -> 13
A10: Serengeti | B10: =B9+1 -> 9 | C10: 2 | D10: 2020 | E10: ='UTILITY REPORT 1'!I11 -> 162.68 | F10: ='UTILITY REPORT 1'!E11 -> 2039.82 | G10: ='UTILITY REPORT 1'!F11 -> 5209 | H10: =IF('Kit report'!F12<0,"0",'Kit report'!F12) -> 552 | I10: =IF('Kit report'!X12<0,"0",'Kit report'!X12) -> 1060 | J10: =IF('Utility summery'!H14<0,"0",'Utility summery'!H14) -> 0 | K10: =IF('UTILITY REPORT 1'!H11<0,"0",'UTILITY REPORT 1'!H11) -> 136 | L10: ='Water-Meter'!K14 -> 3 | M10: ='Water-Meter'!H14 -> 0 | N10: ='Water-Meter'!Q14 -> 14 | O10: =K10*E10+H10*I10+#REF!*#REF!+J10*L10 -> #REF! | P10: ='Water-Meter'!E14 -> 96 | Q10: =IF('Water-Meter'!U14<0,"0",'Water-Meter'!U14) -> 55 | R10: =IF('Water-Meter'!X14<0,"0",'Water-Meter'!X14) -> 62 | S10: =IF('Water-Meter'!AA14<0,"0",'Water-Meter'!AA14) -> 78 | T10: =IF('Water-Meter'!AD14<0,"0",'Water-Meter'!AD14) -> 22 | U10: =IF('Water-Meter'!AG14<0,"0",'Water-Meter'!AG14) -> 22 | V10: =IF('Water-Meter'!AJ14<0,"0",'Water-Meter'!AJ14) -> 0 | W10: ='Water-Meter'!AN14 -> 239 | X10: =Total!K10 -> 16
A11: Serengeti | B11: =B10+1 -> 10 | C11: 2 | D11: 2020 | E11: ='UTILITY REPORT 1'!I12 -> 0 | F11: ='UTILITY REPORT 1'!E12 -> 0 | G11: ='UTILITY REPORT 1'!F12 -> 0 | H11: =IF('Kit report'!F13<0,"0",'Kit report'!F13) -> 0 | I11: =IF('Kit report'!X13<0,"0",'Kit report'!X13) -> 0 | J11: =IF('Utility summery'!H15<0,"0",'Utility summery'!H15) -> 49 | K11: =IF('UTILITY REPORT 1'!H12<0,"0",'UTILITY REPORT 1'!H12) -> 121 | L11: ='Water-Meter'!K15 -> 0 | M11: ='Water-Meter'!H15 -> 0 | N11: ='Water-Meter'!Q15 -> 0 | O11: =K11*E11+H11*I11+#REF!*#REF!+J11*L11 -> #REF! | P11: ='Water-Meter'!E15 -> 0 | Q11: =IF('Water-Meter'!U15<0,"0",'Water-Meter'!U15) -> 0 | R11: =IF('Water-Meter'!X15<0,"0",'Water-Meter'!X15) -> 0 | S11: =IF('Water-Meter'!AA15<0,"0",'Water-Meter'!AA15) -> 0 | T11: =IF('Water-Meter'!AD15<0,"0",'Water-Meter'!AD15) -> 0 | U11: =IF('Water-Meter'!AG15<0,"0",'Water-Meter'!AG15) -> 0 | V11: =IF('Water-Meter'!AJ15<0,"0",'Water-Meter'!AJ15) -> 0 | W11: ='Water-Meter'!AN15 -> 0 | X11: =Total!K11 -> 15
A12: Serengeti | B12: =B11+1 -> 11 | C12: 2 | D12: 2020 | E12: ='UTILITY REPORT 1'!I13 -> 0 | F12: ='UTILITY REPORT 1'!E13 -> 0 | G12: ='UTILITY REPORT 1'!F13 -> 0 | H12: =IF('Kit report'!F14<0,"0",'Kit report'!F14) -> 0 | I12: =IF('Kit report'!X14<0,"0",'Kit report'!X14) -> 0 | J12: =IF('Utility summery'!H16<0,"0",'Utility summery'!H16) -> 0 | K12: =IF('UTILITY REPORT 1'!H13<0,"0",'UTILITY REPORT 1'!H13) -> 0 | L12: ='Water-Meter'!K16 -> 0 | M12: ='Water-Meter'!H16 -> 0 | N12: ='Water-Meter'!Q16 -> 0 | O12: =K12*E12+H12*I12+#REF!*#REF!+J12*L12 -> #REF! | P12: ='Water-Meter'!E16 -> 0 | Q12: =IF('Water-Meter'!U16<0,"0",'Water-Meter'!U16) -> 0 | R12: =IF('Water-Meter'!X16<0,"0",'Water-Meter'!X16) -> 0 | S12: =IF('Water-Meter'!AA16<0,"0",'Water-Meter'!AA16) -> 0 | T12: =IF('Water-Meter'!AD16<0,"0",'Water-Meter'!AD16) -> 0 | U12: =IF('Water-Meter'!AG16<0,"0",'Water-Meter'!AG16) -> 0 | V12: =IF('Water-Meter'!AJ16<0,"0",'Water-Meter'!AJ16) -> 0 | W12: ='Water-Meter'!AN16 -> 0 | X12: =Total!K12 -> 0
A13: Serengeti | B13: =B12+1 -> 12 | C13: 2 | D13: 2020 | E13: ='UTILITY REPORT 1'!I14 -> 0 | F13: ='UTILITY REPORT 1'!E14 -> 0 | G13: ='UTILITY REPORT 1'!F14 -> 0 | H13: =IF('Kit report'!F15<0,"0",'Kit report'!F15) -> 0 | I13: =IF('Kit report'!X15<0,"0",'Kit report'!X15) -> 0 | J13: =IF('Utility summery'!H17<0,"0",'Utility summery'!H17) -> 0 | K13: =IF('UTILITY REPORT 1'!H14<0,"0",'UTILITY REPORT 1'!H14) -> 0 | L13: ='Water-Meter'!K17 -> 0 | M13: ='Water-Meter'!H17 -> 0 | N13: ='Water-Meter'!Q17 -> 0 | O13: =K13*E13+H13*I13+#REF!*#REF!+J13*L13 -> #REF! | P13: ='Water-Meter'!E17 -> 0 | Q13: =IF('Water-Meter'!U17<0,"0",'Water-Meter'!U17) -> 0 | R13: =IF('Water-Meter'!X17<0,"0",'Water-Meter'!X17) -> 0 | S13: =IF('Water-Meter'!AA17<0,"0",'Water-Meter'!AA17) -> 0 | T13: =IF('Water-Meter'!AD17<0,"0",'Water-Meter'!AD17) -> 0 | U13: =IF('Water-Meter'!AG17<0,"0",'Water-Meter'!AG17) -> 0 | V13: =IF('Water-Meter'!AJ17<0,"0",'Water-Meter'!AJ17) -> 0 | W13: ='Water-Meter'!AN17 -> 0 | X13: =Total!K13 -> 0
A14: Serengeti | B14: =B13+1 -> 13 | C14: 2 | D14: 2020 | E14: ='UTILITY REPORT 1'!I15 -> 0 | F14: ='UTILITY REPORT 1'!E15 -> 0 | G14: ='UTILITY REPORT 1'!F15 -> 0 | H14: =IF('Kit report'!F16<0,"0",'Kit report'!F16) -> 0 | I14: =IF('Kit report'!X16<0,"0",'Kit report'!X16) -> 0 | J14: =IF('Utility summery'!H18<0,"0",'Utility summery'!H18) -> 0 | K14: =IF('UTILITY REPORT 1'!H15<0,"0",'UTILITY REPORT 1'!H15) -> 0 | L14: ='Water-Meter'!K18 -> 0 | M14: ='Water-Meter'!H18 -> 0 | N14: ='Water-Meter'!Q18 -> 0 | O14: =K14*E14+H14*I14+#REF!*#REF!+J14*L14 -> #REF! | P14: ='Water-Meter'!E18 -> 0 | Q14: =IF('Water-Meter'!U18<0,"0",'Water-Meter'!U18) -> 0 | R14: =IF('Water-Meter'!X18<0,"0",'Water-Meter'!X18) -> 0 | S14: =IF('Water-Meter'!AA18<0,"0",'Water-Meter'!AA18) -> 0 | T14: =IF('Water-Meter'!AD18<0,"0",'Water-Meter'!AD18) -> 0 | U14: =IF('Water-Meter'!AG18<0,"0",'Water-Meter'!AG18) -> 0 | V14: =IF('Water-Meter'!AJ18<0,"0",'Water-Meter'!AJ18) -> 0 | W14: ='Water-Meter'!AN18 -> 0 | X14: =Total!K14 -> 0
... A30: Serengeti | B30: =B29+1 -> 29 | C30: 2 | D30: 2020 | E30: ='UTILITY REPORT 1'!I31 -> 0 | F30: ='UTILITY REPORT 1'!E31 -> 0 | G30: ='UTILITY REPORT 1'!F31 -> 0 | H30: =IF('Kit report'!F32<0,"0",'Kit report'!F32) -> 0 | I30: =IF('Kit report'!X32<0,"0",'Kit report'!X32) -> 0 | J30: =IF('Utility summery'!H34<0,"0",'Utility summery'!H34) -> 0 | K30: =IF('UTILITY REPORT 1'!H31<0,"0",'UTILITY REPORT 1'!H31) -> 0 | L30: ='Water-Meter'!K34 -> 0 | M30: ='Water-Meter'!H34 -> 0 | N30: ='Water-Meter'!Q34 -> 0 | O30: =K30*E30+H30*I30+#REF!*#REF!+J30*L30 -> #REF! | P30: ='Water-Meter'!E34 -> 0 | Q30: =IF('Water-Meter'!U34<0,"0",'Water-Meter'!U34) -> 0 | R30: =IF('Water-Meter'!X34<0,"0",'Water-Meter'!X34) -> 0 | S30: =IF('Water-Meter'!AA34<0,"0",'Water-Meter'!AA34) -> 0 | T30: =IF('Water-Meter'!AD34<0,"0",'Water-Meter'!AD34) -> 0 | U30: =IF('Water-Meter'!AG34<0,"0",'Water-Meter'!AG34) -> 0 | V30: =IF('Water-Meter'!AJ34<0,"0",'Water-Meter'!AJ34) -> 0 | W30: ='Water-Meter'!AN34 -> 0 | X30: =Total!K30 -> 0
A31: Serengeti | B31: 1 | C31: 3 | D31: 2020 | E31: ='UTILITY REPORT 1'!I32 -> 0 | F31: ='UTILITY REPORT 1'!E32 -> 0 | G31: ='UTILITY REPORT 1'!F32 -> 0 | H31: =IF('Kit report'!F33<0,"0",'Kit report'!F33) -> 0 | I31: =IF('Kit report'!X33<0,"0",'Kit report'!X33) -> 0 | J31: =IF('Utility summery'!H35<0,"0",'Utility summery'!H35) -> 0 | K31: =IF('UTILITY REPORT 1'!H32<0,"0",'UTILITY REPORT 1'!H32) -> 0 | L31: ='Water-Meter'!K35 -> 0 | M31: ='Water-Meter'!H35 -> 0 | N31: ='Water-Meter'!Q35 -> 0 | O31: =K31*E31+H31*I31+#REF!*#REF!+J31*L31 -> #REF! | P31: ='Water-Meter'!E35 -> 0 | Q31: =IF('Water-Meter'!U35<0,"0",'Water-Meter'!U35) -> 0 | R31: =IF('Water-Meter'!X35<0,"0",'Water-Meter'!X35) -> 0 | S31: =IF('Water-Meter'!AA35<0,"0",'Water-Meter'!AA35) -> 0 | T31: =IF('Water-Meter'!AD35<0,"0",'Water-Meter'!AD35) -> 0 | U31: =IF('Water-Meter'!AG35<0,"0",'Water-Meter'!AG35) -> 0 | V31: =IF('Water-Meter'!AJ35<0,"0",'Water-Meter'!AJ35) -> 0 | W31: ='Water-Meter'!AN35 -> 0 | X31: =Total!K31 -> 0
A32: Serengeti | B32: 2 | C32: 3 | D32: 2020 | E32: ='UTILITY REPORT 1'!I33 -> 0 | F32: ='UTILITY REPORT 1'!E33 -> 0 | G32: ='UTILITY REPORT 1'!F33 -> 0 | H32: =IF('Kit report'!F34<0,"0",'Kit report'!F34) -> 0 | I32: =IF('Kit report'!X34<0,"0",'Kit report'!X34) -> 0 | J32: =IF('Utility summery'!H36<0,"0",'Utility summery'!H36) -> 0 | K32: =IF('UTILITY REPORT 1'!H33<0,"0",'UTILITY REPORT 1'!H33) -> 0 | L32: ='Water-Meter'!K36 -> 0 | M32: ='Water-Meter'!H36 -> 0 | N32: ='Water-Meter'!Q36 -> 0 | P32: ='Water-Meter'!E36 -> 0 | Q32: =IF('Water-Meter'!U36<0,"0",'Water-Meter'!U36) -> 0 | R32: =IF('Water-Meter'!X36<0,"0",'Water-Meter'!X36) -> 0 | S32: =IF('Water-Meter'!AA36<0,"0",'Water-Meter'!AA36) -> 0 | T32: =IF('Water-Meter'!AD36<0,"0",'Water-Meter'!AD36) -> 0 | U32: =IF('Water-Meter'!AG36<0,"0",'Water-Meter'!AG36) -> 0 | V32: =IF('Water-Meter'!AJ36<0,"0",'Water-Meter'!AJ36) -> 0 | W32: ='Water-Meter'!AN36 -> 0 | X32: =Total!K32 -> 0

Sheet UTILITY REPORT 1
A1: NOVEMBER UTILITY REPORT
A2: Date | B2: % | C2: Guest Rooms Occupied | D2: Diesel cost Per Liter ($) | E2: Diesel consumption (LT) | F2: Power production (KW) | G2: Water consumption (M3) | H2: RO prodution (M3) | I2: Transport Consupmtion (LT)
A3: 43862 | B3: =Gen!B11 -> 0.2338 | C3: ='Summery Report'!E5 -> 18 | D3: 1 | E3: =Gen!S11 -> 1824.75 | F3: =Gen!T11 -> 4580 | G3: ='Water-Meter'!E6 -> 113 | H3: ='Utility report '!AC6 -> 115 | I3: =Gen!AJ11 -> 83.21
A4: 43863 | B4: =Gen!B12 -> 0.234 | C4: ='Summery Report'!E6 -> 18 | D4: 1 | E4: =Gen!S12 -> 1802.85 | F4: =Gen!T12 -> 4303 | G4: ='Water-Meter'!E7 -> 97 | H4: ='Utility report '!AC7 -> 101 | I4: =Gen!AJ12 -> 130.39
A5: 43864 | B5: =Gen!B13 -> 0.104 | C5: ='Summery Report'!E7 -> 8 | D5: 1 | E5: =Gen!S13 -> 1920.92 | F5: =Gen!T13 -> 4514 | G5: ='Water-Meter'!E8 -> 107 | H5: ='Utility report '!AC8 -> 81 | I5: =Gen!AJ13 -> 178.75
A6: 43865 | B6: =Gen!B14 -> 1 | C6: ='Summery Report'!E8 -> 77 | D6: 1 | E6: =Gen!S14 -> 2359.12 | F6: =Gen!T14 -> 5690 | G6: ='Water-Meter'!E9 -> 139 | H6: ='Utility report '!AC9 -> 100 | I6: =Gen!AJ14 -> 89.65
A7: 43866 | B7: =Gen!B15 -> 1 | C7: ='Summery Report'!E9 -> 77 | D7: 1 | E7: =Gen!S15 -> 2256.73 | F7: =Gen!T15 -> 5866 | G7: ='Water-Meter'!E10 -> 141 | H7: ='Utility report '!AC10 -> 98 | I7: =Gen!AJ15 -> 129.27
A8: 43867 | B8: =Gen!B16 -> 1 | C8: ='Summery Report'!E10 -> 77 | D8: 1 | E8: =Gen!S16 -> 2491.51 | F8: =Gen!T16 -> 5875 | G8: ='Water-Meter'!E11 -> 129 | H8: ='Utility report '!AC11 -> 83 | I8: =Gen!AJ16 -> 187.64
A9: 43868 | B9: =Gen!B17 -> 1 | C9: ='Summery Report'!E11 -> 77 | D9: 1 | E9: =Gen!S17 -> 2244.74 | F9: =Gen!T17 -> 5952 | G9: ='Water-Meter'!E12 -> 129 | H9: ='Utility report '!AC12 -> 103 | I9: =Gen!AJ17 -> 203.15
A10: 43869 | B10: =Gen!B18 -> 0.1429 | C10: ='Summery Report'!E12 -> 13 | D10: 1 | E10: =Gen!S18 -> 2569.45 | F10: =Gen!T18 -> 5988 | G10: ='Water-Meter'!E13 -> 128 | H10: ='Utility report '!AC13 -> 105 | I10: =Gen!AJ18 -> 56.74
A11: 43870 | B11: =Gen!B19 -> 0.195 | C11: ='Summery Report'!E13 -> 16 | D11: 1 | E11: =Gen!S19 -> 2039.82 | F11: =Gen!T19 -> 5209 | G11: ='Water-Meter'!E14 -> 96 | H11: ='Utility report '!AC14 -> 136 | I11: =Gen!AJ19 -> 162.68
A12: 43871 | B12: =Gen!B20 -> 0.1818 | C12: ='Summery Report'!E14 -> 15 | D12: 1 | E12: =Gen!S20 -> 0 | F12: =Gen!T20 -> 0 | G12: ='Water-Meter'!E15 -> 0 | H12: ='Utility report '!AC15 -> 121 | I12: =Gen!AJ20 -> 0
A13: 43872 | B13: =Gen!B21 -> 0 | C13: ='Summery Report'!E15 -> 0 | D13: 1 | E13: =Gen!S21 -> 0 | F13: =Gen!T21 -> 0 | G13: ='Water-Meter'!E16 -> 0 | H13: ='Utility report '!AC16 -> -24878 | I13: =Gen!AJ21 -> 0
A14: 43873 | B14: =Gen!B22 -> 0 | C14: ='Summery Report'!E16 -> 0 | D14: 1 | E14: =Gen!S22 -> 0 | F14: =Gen!T22 -> 0 | G14: ='Water-Meter'!E17 -> 0 | H14: ='Utility report '!AC17 -> 0 | I14: =Gen!AJ22 -> 0
... A34: 43893 | B34: =Gen!B42 -> 0 | C34: ='Summery Report'!E36 -> 0 | D34: 2 | E34: =Gen!S42 -> 0 | F34: =Gen!T42 -> 0 | G34: ='Water-Meter'!E37 -> 0 | H34: ='Utility report '!AC37 -> 0 | I34: =Gen!AJ42 -> 0

Sheet Utility summery
A4: Date | B4: Room Occupied | C4: Electricity Units Generated KW | D4: Diseal | G4: Water | J4: Gas | N4: Cost of utilites
D5: Generator | E5: Transport | F5: Total | G5: RO | H5: STP | I5: Total Consumption | J5: 2 ton | K5: 1 Ton | L5: 1 Ton | M5: Total consumption | N5: Electricity /1.4$/liter | O5: Diseal for Transport | P5: Gas /2.38$/Kg | Q5: Total HLP Cost | R5: Electricity Cost/Room $ | S5: cost/Room $
A6: =Gen!A11 -> 43862 | B6: ='Summery Report'!E5 -> 18 | C6: =Gen!T11 -> 4580 | D6: =Gen!S11 -> 1824.75 | E6: =Gen!AJ11 -> 83.21 | F6: =Gen!AR11 -> 1907.96 | G6: ='Utility report '!AC6 -> 115 | H6: ='Utility report '!AE6 -> 53 | I6: ='Water-Meter'!E6 -> 113 | J6: ='Lpg (2)'!B10 -> 85 | K6: ='Lpg (2)'!C10 -> 85 | L6: ='Lpg (2)'!D10 -> 18 | M6: ='Lpg (2)'!G10 -> 94.512 | O6: =E6 -> 83.21 | P6: ='[1]Lpg (2)'!#REF! -> #REF! | Q6: ='[1]Summery Report'!#REF! -> #REF! | R6: =N6/B6 -> 0 | S6: =Q6/B6 -> #REF!
A7: =Gen!A12 -> 43863 | B7: ='Summery Report'!E6 -> 18 | C7: =Gen!T12 -> 4303 | D7: =Gen!S12 -> 1802.85 | E7: =Gen!AJ12 -> 130.39 | F7: =Gen!AR12 -> 1933.24 | G7: ='Utility report '!AC7 -> 101 | H7: ='Utility report '!AE7 -> 63 | I7: ='Water-Meter'!E7 -> 97 | J7: ='Lpg (2)'!B11 -> 85 | K7: ='Lpg (2)'!C11 -> 85 | L7: ='Lpg (2)'!D11 -> 10 | M7: ='Lpg (2)'!G11 -> 104.632 | N7: =D7*1.4 -> 2523.99 | O7: =E7*1.4 -> 182.546 | P7: ='[1]Lpg (2)'!#REF! -> #REF! | Q7: ='[1]Summery Report'!#REF! -> #REF! | R7: =N7/B7 -> 140.22167 | S7: =Q7/B7 -> #REF!
A8: =Gen!A13 -> 43864 | B8: ='Summery Report'!E7 -> 8 | C8: =Gen!T13 -> 4514 | D8: =Gen!S13 -> 1920.92 | E8: =Gen!AJ13 -> 178.75 | F8: =Gen!AR13 -> 2099.67 | G8: ='Utility report '!AC8 -> 81 | H8: ='Utility report '!AE8 -> 60 | I8: ='Water-Meter'!E8 -> 107 | J8: ='Lpg (2)'!B12 -> 85 | K8: ='Lpg (2)'!C12 -> 85 | L8: ='Lpg (2)'!D12 -> 7 | M8: ='Lpg (2)'!G12 -> -783.948 | N8: =D8*1.4 -> 2689.288 | O8: =E8*1.4 -> 250.25 | P8: ='[1]Lpg (2)'!#REF! -> #REF! | Q8: ='[1]Summery Report'!#REF! -> #REF! | R8: =N8/B8 -> 336.161 | S8: =Q8/B8 -> #REF!
A9: =Gen!A14 -> 43865 | B9: ='Summery Report'!E8 -> 77 | C9: =Gen!T14 -> 5690 | D9: =Gen!S14 -> 2359.12 | E9: =Gen!AJ14 -> 89.65 | F9: =Gen!AR14 -> 2448.77 | G9: ='Utility report '!AC9 -> 100 | H9: ='Utility report '!AE9 -> 63 | I9: ='Water-Meter'!E9 -> 139 | J9: ='Lpg (2)'!B13 -> 85 | K9: ='Lpg (2)'!C13 -> 85 | L9: ='Lpg (2)'!D13 -> 5 | M9: ='Lpg (2)'!G13 -> 112.728 | N9: =D9*1.4 -> 3302.768 | O9: =E9*1.4 -> 125.51 | P9: ='[1]Lpg (2)'!#REF! -> #REF! | Q9: ='[1]Summery Report'!#REF! -> #REF! | R9: =N9/B9 -> 42.893091 | S9: =Q9/B9 -> #REF!
A10: =Gen!A15 -> 43866 | B10: ='Summery Report'!E9 -> 77 | C10: =Gen!T15 -> 5866 | D10: =Gen!S15 -> 2256.73 | E10: =Gen!AJ15 -> 129.27 | F10: =Gen!AR15 -> 2386 | G10: ='Utility report '!AC10 -> 98 | H10: ='Utility report '!AE10 -> 63 | I10: ='Water-Meter'!E10 -> 141 | J10: ='Lpg (2)'!B14 -> 85 | K10: ='Lpg (2)'!C14 -> 76 | L10: ='Lpg (2)'!D14 -> 0 | M10: ='Lpg (2)'!G14 -> 106.92 | N10: =D10*1.4 -> 3159.422 | O10: =E10*1.4 -> 180.978 | P10: ='[1]Lpg (2)'!#REF! -> #REF! | Q10: ='[1]Summery Report'!#REF! -> #REF! | R10: =N10/B10 -> 41.031455 | S10: =Q10/B10 -> #REF!
A11: =Gen!A16 -> 43867 | B11: ='Summery Report'!E10 -> 77 | C11: =Gen!T16 -> 5875 | D11: =Gen!S16 -> 2491.51 | E11: =Gen!AJ16 -> 187.64 | F11: =Gen!AR16 -> 2679.15 | G11: ='Utility report '!AC11 -> 83 | H11: ='Utility report '!AE11 -> 56 | I11: ='Water-Meter'!E11 -> 129 | J11: ='Lpg (2)'!B15 -> 85 | K11: ='Lpg (2)'!C15 -> 70 | L11: ='Lpg (2)'!D15 -> 0 | M11: ='Lpg (2)'!G15 -> 102.124 | N11: =D11*1.4 -> 3488.114 | O11: =E11*1.4 -> 262.696 | P11: ='[1]Lpg (2)'!#REF! -> #REF! | Q11: ='[1]Summery Report'!#REF! -> #REF! | R11: =N11/B11 -> 45.300182 | S11: =Q11/B11 -> #REF!
A12: =Gen!A17 -> 43868 | B12: ='Summery Report'!E11 -> 77 | C12: =Gen!T17 -> 5952 | D12: =Gen!S17 -> 2244.74 | E12: =Gen!AJ17 -> 203.15 | F12: =Gen!AR17 -> 2447.89 | G12: ='Utility report '!AC12 -> 103 | H12: ='Utility report '!AE12 -> 0 | I12: ='Water-Meter'!E12 -> 129 | J12: ='Lpg (2)'!B16 -> 85 | K12: ='Lpg (2)'!C16 -> 60 | L12: ='Lpg (2)'!D16 -> 0 | M12: ='Lpg (2)'!G16 -> 108.196 | N12: =D12*1.4 -> 3142.636 | O12: =E12*1.4 -> 284.41 | P12: ='[1]Lpg (2)'!#REF! -> #REF! | Q12: ='[1]Summery Report'!#REF! -> #REF! | R12: =N12/B12 -> 40.813455 | S12: =Q12/B12 -> #REF!
A13: =Gen!A18 -> 43869 | B13: ='Summery Report'!E12 -> 13 | C13: =Gen!T18 -> 5988 | D13: =Gen!S18 -> 2569.45 | E13: =Gen!AJ18 -> 56.74 | F13: =Gen!AR18 -> 2626.19 | G13: ='Utility report '!AC13 -> 105 | H13: ='Utility report '!AE13 -> 0 | I13: ='Water-Meter'!E13 -> 128 | J13: ='Lpg (2)'!B17 -> 85 | K13: ='Lpg (2)'!C17 -> 55 | L13: ='Lpg (2)'!D17 -> 0 | M13: ='Lpg (2)'!G17 -> 112.156 | N13: =D13*1.4 -> 3597.23 | O13: =E13*1.4 -> 79.436 | P13: ='[1]Lpg (2)'!#REF! -> #REF! | Q13: ='[1]Summery Report'!#REF! -> #REF! | R13: =N13/B13 -> 276.71 | S13: =Q13/B13 -> #REF!
A14: =Gen!A19 -> 43870 | B14: ='Summery Report'!E13 -> 16 | C14: =Gen!T19 -> 5209 | D14: =Gen!S19 -> 2039.82 | E14: =Gen!AJ19 -> 162.68 | F14: =Gen!AR19 -> 2202.5 | G14: ='Utility report '!AC14 -> 136 | H14: ='Utility report '!AE14 -> 0 | I14: ='Water-Meter'!E14 -> 96 | J14: ='Lpg (2)'!B18 -> 85 | K14: ='Lpg (2)'!C18 -> 49 | L14: ='Lpg (2)'!D18 -> 0 | M14: ='Lpg (2)'!G18 -> 103.444 | N14: =D14*1.4 -> 2855.748 | O14: =E14*1.4 -> 227.752 | P14: ='[1]Lpg (2)'!#REF! -> #REF! | Q14: ='[1]Summery Report'!#REF! -> #REF! | R14: =N14/B14 -> 178.48425 | S14: =Q14/B14 -> #REF!
A15: =Gen!A20 -> 43871 | B15: ='Summery Report'!E14 -> 15 | C15: =Gen!T20 -> 0 | D15: =Gen!S20 -> 0 | E15: =Gen!AJ20 -> 0 | F15: =Gen!AR20 -> 0 | G15: ='Utility report '!AC15 -> 121 | H15: ='Utility report '!AE15 -> 49 | I15: ='Water-Meter'!E15 -> 0 | J15: ='Lpg (2)'!B19 -> 0 | K15: ='Lpg (2)'!C19 -> 0 | L15: ='Lpg (2)'!D19 -> 0 | M15: ='Lpg (2)'!G19 -> -307317.16 | N15: =D15*1.4 -> 0 | O15: =E15*1.4 -> 0 | P15: ='[1]Lpg (2)'!#REF! -> #REF! | Q15: ='[1]Summery Report'!#REF! -> #REF! | R15: =N15/B15 -> 0 | S15: =Q15/B15 -> #REF!
A16: =Gen!A21 -> 43872 | B16: ='Summery Report'!E15 -> 0 | C16: =Gen!T21 -> 0 | D16: =Gen!S21 -> 0 | E16: =Gen!AJ21 -> 0 | F16: =Gen!AR21 -> 0 | G16: ='Utility report '!AC16 -> -24878 | H16: ='Utility report '!AE16 -> -195532 | I16: ='Water-Meter'!E16 -> 0 | J16: ='Lpg (2)'!B20 -> 0 | K16: ='Lpg (2)'!C20 -> 0 | L16: ='Lpg (2)'!D20 -> 0 | M16: ='Lpg (2)'!G20 -> 0 | N16: =D16*1.4 -> 0 | O16: =E16*1.4 -> 0 | P16: ='[1]Lpg (2)'!#REF! -> #REF! | Q16: ='[1]Summery Report'!#REF! -> #REF! | R16: =N16/B16 -> #DIV/0! | S16: =Q16/B16 -> #REF!
A17: =Gen!A22 -> 43873 | B17: ='Summery Report'!E16 -> 0 | C17: =Gen!T22 -> 0 | D17: =Gen!S22 -> 0 | E17: =Gen!AJ22 -> 0 | F17: =Gen!AR22 -> 0 | G17: ='Utility report '!AC17 -> 0 | H17: ='Utility report '!AE17 -> 0 | I17: ='Water-Meter'!E17 -> 0 | J17: ='Lpg (2)'!B21 -> 0 | K17: ='Lpg (2)'!C21 -> 0 | L17: ='Lpg (2)'!D21 -> 0 | M17: ='Lpg (2)'!G21 -> 0 | N17: =D17*1.4 -> 0 | O17: =E17*1.4 -> 0 | P17: ='[1]Lpg (2)'!#REF! -> #REF! | Q17: ='[1]Summery Report'!#REF! -> #REF! | R17: =N17/B17 -> #DIV/0! | S17: =Q17/B17 -> #REF!
A18: =Gen!A23 -> 43874 | B18: ='Summery Report'!E17 -> 0 | C18: =Gen!T23 -> 0 | D18: =Gen!S23 -> 0 | E18: =Gen!AJ23 -> 0 | F18: =Gen!AR23 -> 0 | G18: ='Utility report '!AC18 -> 0 | H18: ='Utility report '!AE18 -> 0 | I18: ='Water-Meter'!E18 -> 0 | J18: ='Lpg (2)'!B22 -> 0 | K18: ='Lpg (2)'!C22 -> 0 | L18: ='Lpg (2)'!D22 -> 0 | M18: ='Lpg (2)'!G22 -> 0 | N18: =D18*1.4 -> 0 | O18: =E18*1.4 -> 0 | P18: ='[1]Lpg (2)'!#REF! -> #REF! | Q18: ='[1]Summery Report'!#REF! -> #REF! | R18: =N18/B18 -> #DIV/0! | S18: =Q18/B18 -> #REF!
... A32: =Gen!A37 -> 43888 | B32: ='Summery Report'!E31 -> 0 | C32: =Gen!T37 -> 0 | D32: =Gen!S37 -> 0 | E32: =Gen!AJ37 -> 0 | F32: =Gen!AR37 -> 0 | G32: ='Utility report '!AC32 -> 0 | H32: ='Utility report '!AE32 -> 0 | I32: ='Water-Meter'!E32 -> 0 | J32: ='Lpg (2)'!B36 -> 0 | K32: ='Lpg (2)'!C36 -> 0 | L32: ='Lpg (2)'!D36 -> 0 | M32: ='Lpg (2)'!G36 -> 0 | N32: =D32*1.4 -> 0 | O32: =E32*1.4 -> 0 | P32: ='[1]Lpg (2)'!#REF! -> #REF! | Q32: ='[1]Summery Report'!#REF! -> #REF! | R32: =N32/B32 -> #DIV/0! | S32: =Q32/B32 -> #REF!
A33: =Gen!A38 -> 43889 | B33: ='Summery Report'!E32 -> 0 | C33: =Gen!T38 -> 0 | D33: =Gen!S38 -> 0 | E33: =Gen!AJ38 -> 0 | F33: =Gen!AR38 -> 0 | G33: ='Utility report '!AC33 -> 0 | H33: ='Utility report '!AE33 -> 0 | I33: ='Water-Meter'!E33 -> 0 | J33: ='Lpg (2)'!B37 -> 0 | K33: ='Lpg (2)'!C37 -> 0 | L33: ='Lpg (2)'!D37 -> 0 | M33: ='Lpg (2)'!G37 -> 0 | N33: =D33*1.4 -> 0 | O33: =E33*1.4 -> 0 | P33: ='[1]Lpg (2)'!#REF! -> #REF! | Q33: ='[1]Summery Report'!#REF! -> #REF! | R33: =N33/B33 -> #DIV/0! | S33: =Q33/B33 -> #REF! | T33: =3124/13 -> 240.30769
A34: =Gen!A39 -> 43890 | B34: ='Summery Report'!E33 -> 0 | C34: =Gen!T39 -> 0 | D34: =Gen!S39 -> 0 | E34: =Gen!AJ39 -> 0 | F34: =Gen!AR39 -> 0 | G34: ='Utility report '!AC34 -> 0 | H34: ='Utility report '!AE34 -> 0 | I34: ='Water-Meter'!E34 -> 0 | J34: ='Lpg (2)'!B38 -> 0 | K34: ='Lpg (2)'!C38 -> 0 | L34: ='Lpg (2)'!D38 -> 0 | M34: ='Lpg (2)'!G38 -> 0 | N34: =D34*1.4 -> 0 | O34: =E34*1.4 -> 0 | P34: ='[1]Lpg (2)'!#REF! -> #REF! | Q34: ='[1]Summery Report'!#REF! -> #REF! | R34: =N34/B34 -> #DIV/0! | S34: =Q34/B34 -> #REF!
A35: =Gen!A40 -> 43891 | B35: ='Summery Report'!E34 -> 0 | C35: =Gen!T40 -> 0 | D35: =Gen!S40 -> 0 | E35: =Gen!AJ40 -> 0 | F35: =Gen!AR40 -> 0 | G35: ='Utility report '!AC35 -> 0 | H35: ='Utility report '!AE35 -> 0 | I35: ='Water-Meter'!E35 -> 0 | J35: ='Lpg (2)'!B39 -> 0 | K35: ='Lpg (2)'!C39 -> 0 | L35: ='Lpg (2)'!D39 -> 0 | M35: ='Lpg (2)'!G39 -> 0 | N35: =D35*1.4 -> 0 | O35: =E35*1.4 -> 0 | P35: ='[1]Lpg (2)'!#REF! -> #REF! | Q35: ='[1]Summery Report'!#REF! -> #REF! | R35: =N35/B35 -> #DIV/0! | S35: =Q35/B35 -> #REF!
A36: =Gen!A41 -> 43892 | B36: ='Summery Report'!E35 -> 0 | C36: =Gen!T41 -> 0 | D36: =Gen!S41 -> 0 | E36: =Gen!AJ41 -> 0 | F36: =Gen!AR41 -> 0 | G36: ='Utility report '!AC36 -> 0 | H36: ='Utility report '!AE36 -> 0 | I36: ='Water-Meter'!E36 -> 0 | J36: ='Lpg (2)'!B40 -> 0 | K36: ='Lpg (2)'!C40 -> 0 | L36: ='Lpg (2)'!D40 -> 0 | M36: ='Lpg (2)'!G40 -> 0 | N36: =D36*1.4 -> 0 | O36: =E36*1.4 -> 0 | P36: ='[1]Lpg (2)'!#REF! -> #REF! | Q36: ='[1]Summery Report'!#REF! -> #REF! | R36: =N36/B36 -> #DIV/0! | S36: =Q36/B36 -> #REF!
A37: =[1]Gen!A42 -> #REF! | B37: ='Summery Report'!E36 -> 0 | C37: =Gen!T42 -> 0 | D37: =Gen!S42 -> 0 | E37: =Gen!AJ42 -> 0 | F37: =Gen!AR42 -> 0 | G37: ='Utility report '!AC37 -> 0 | H37: ='Utility report '!AE37 -> 0 | I37: ='Water-Meter'!E37 -> 0 | J37: ='Lpg (2)'!B41 -> 0 | K37: ='Lpg (2)'!C41 -> 0 | L37: ='Lpg (2)'!D41 -> 0 | M37: ='Lpg (2)'!G41 -> 0 | Q37: ='[1]Summery Report'!#REF! -> #REF! | R37: =N37/B37 -> #DIV/0! | S37: =Q37/B37 -> #REF!
A39: Total | B39: =SUM(B7:B37) -> 378 | C39: =SUM(C7:C35) -> 43397 | D39: =SUM(D7:D35) -> 17685.14 | E39: =SUM(E7:E35) -> 1138.27 | F39: =SUM(F7:F35) -> 18823.41 | G39: =SUM(G7:G35) -> -23950 | H39: =SUM(H7:H35) -> -195178 | I39: =SUM(I7:I35) -> 966 | J39: =SUM(J7:J35) -> 680 | ... S39: =SUM(S7:S35) -> #REF!

Sheet Utility report 
A1: DAILY UTILITY REPORT FEBRUARY 2020
A2: Date | B2: Total occupancy | H2: Diesel balance LTS | I2: Diesel Deliveries | J2: Gen.Diesel consumption LTS | L2: Total Diesel consumption LTS | M2: Water Meter reading | N2: Water consumption m³ | O2: R.O WATER PRODUCTION LTRS + TIME | AA2: Total RO production | AB2: RO Meter reading | AD2: 0 | AF2: GAS TANK A | AG2: GAS TANK B | AH2: GAS TANK C | AI2: Total Gas Tanks | AJ2: Kg /day | AK2: TOTAL GAS cons.
A3: Rate Tsh /$ | B3: 1640 | C3: Diesel cost / lits | D3: 2175 | F3: =SUM(D3/B3) -> 1.3262195 | H3: =Gen!C11 -> 30982.31 | K3: Transport consumption | M3: Balance | O3: PLANT NO 1 | S3: PLANT NO 2 | W3: PLANT NO 3 | AA3: /day | AB3: Balance | AC3: Production | AD3: 0 | AE3: Production | AF3: Capacity | AG3: Capacity | AH3: Capacity | AI3: Kg | AJ3: /day | AK3: /day
B4: Rooms OCC | C4: % | D4: Guest Rooms Occ | F4: Electricity Production Cost /Room Occ by guest | G4: All Cost /Room Occ by guest | O4: Flow M3 | P4: Reading Hours Meter | Q4: Hrs | R4: total production M3 | S4: Flow M3 | T4: Reading Hours Meter | U4: Hrs | V4: total production M3 | W4: Flow M3 | X4: READING HOURS METER | Y4: Hrs | Z4: total production M3 | AA4: M3 | AC4: M3 | AE4: M3 | AF4: 2000 | AG4: 1000 | AH4: 1000 | AI4: =SUM([2]Sheet1!$AA$36) -> 950 | AJ4: Kg | AK4: M3
X5: 23125 | AB5: 23835 | AD5: 195125 | AF5: 0.85 | AG5: 0.85 | AH5: 0.85
A6: =Gen!A11 -> 43862 | B6: ='Summery Report'!E5 -> 18 | C6: =Gen!B11 -> 0.2338 | D6: ='Summery Report'!E5 -> 18 | E6: =SUM(F3) -> 1.3262195 | F6: =SUM(J6*E6)/D6 -> 134.4455 | G6: =SUM(L6*E6)/D6 -> 140.57632 | H6: =Gen!C11 -> 30982.31 | I6: =Gen!E11 -> 0 | J6: =Gen!S11 -> 1824.75 | K6: =Gen!AJ11 -> 83.21 | L6: =SUM(J6:K6) -> 1907.96 | M6: ='Water-Meter'!K46 -> 574.19311 | N6: ='Water-Meter'!E6 -> 113 | Q6: =SUM(P6-P5) -> 0 | R6: =SUM(Q6*O6) -> 0 | T6: 15719 | U6: =T6-T5 -> 15719 | V6: - | X6: 23143 | Y6: =X6-X5 -> 18 | Z6: =Y6-Y5 -> 18 | AA6: =Z6-Z5 -> 18 | AB6: 23950 | AC6: =AB6-AB5 -> 115 | AD6: 195178 | AE6: =AD6-AD5 -> 53 | AF6: ='Lpg (2)'!B10*2000/85 -> 2000 | AG6: ='Lpg (2)'!C10*1000/85 -> 1000 | AH6: ='Lpg (2)'!D10*1000/85 -> 211.76471 | AI6: =SUM(AF6*2000)+(AG6*1000)+(AH6*1000) -> 5211764.7 | AJ6: =SUM(AI5-AI6) -> -5211764.7
A7: =Gen!A12 -> 43863 | B7: ='Summery Report'!E6 -> 18 | C7: =Gen!B12 -> 0.234 | D7: ='Summery Report'!E6 -> 18 | E7: =SUM(E6) -> 1.3262195 | F7: =SUM(J7*E7)/D7 -> 132.83194 | G7: =SUM(L7*E7)/D7 -> 142.43892 | H7: =Gen!C12 -> 29074.35 | I7: =Gen!E12 -> 18000 | J7: =Gen!S12 -> 1802.85 | K7: =Gen!AJ12 -> 130.39 | L7: =SUM(J7:K7) -> 1933.24 | M7: ='Water-Meter'!K47 -> 533.64272 | N7: ='Water-Meter'!E7 -> 97 | P7: 18665 | Q7: =SUM(P7-P6) -> 18665 | R7: =SUM(Q7*O7) -> 0 | T7: 15719 | U7: =T7-T6 -> 0 | V7: =SUM(U7*S7) -> 0 | X7: 23167 | Y7: =X7-X6 -> 24 | Z7: =SUM(Y7*W7) -> 0 | AA7: =SUM(Z7*X9) -> 0 | AB7: 24051 | AC7: =AB7-AB6 -> 101 | AD7: 195241 | AE7: =AD7-AD6 -> 63 | AF7: ='Lpg (2)'!B11*2000/85 -> 2000 | AG7: ='Lpg (2)'!C11*1000/85 -> 1000 | AH7: ='Lpg (2)'!D11*1000/85 -> 117.64706 | AI7: =SUM(AF6*2000)+(AG7*1000)+(AH7*1000) -> 5117647.1 | AJ7: =SUM(AI6-AI7) -> 94117.647
A8: =Gen!A13 -> 43864 | B8: ='Summery Report'!E7 -> 8 | C8: =Gen!B13 -> 0.104 | D8: ='Summery Report'!E7 -> 8 | E8: =SUM(E7) -> 1.3262195 | F8: =SUM(J8*E8)/D8 -> 318.4452 | G8: =SUM(L8*E8)/D8 -> 348.07792 | H8: =Gen!C13 -> 27141.11 | I8: =Gen!E13 -> 0 | J8: =Gen!S13 -> 1920.92 | K8: =Gen!AJ13 -> 178.75 | L8: =SUM(J8:K8) -> 2099.67 | M8: ='Water-Meter'!K48 -> 440.34108 | N8: ='Water-Meter'!E8 -> 107 | P8: 18665 | Q8: =SUM(P8-P7) -> 0 | R8: =SUM(Q8*O8) -> 0 | T8: 15719 | U8: =T8-T7 -> 0 | V8: =SUM(U8*S8) -> 0 | X8: 23184.3 | Y8: =X8-X7 -> 17.3 | Z8: =SUM(Y8*W8) -> 0 | AA8: =SUM(Z8*X10) -> 0 | AB8: 24132 | AC8: =AB8-AB7 -> 81 | AD8: 195301 | AE8: =AD8-AD7 -> 60 | AF8: ='Lpg (2)'!B12*2000/85 -> 2000 | AG8: ='Lpg (2)'!C12*1000/85 -> 1000 | AH8: ='Lpg (2)'!D12*1000/85 -> 82.352941 | AI8: =SUM(AF7*2000)+(AG8*1000)+(AH8*1000) -> 5082352.9 | AJ8: =SUM(AI7-AI8) -> 35294.118
A9: =Gen!A14 -> 43865 | B9: ='Summery Report'!E8 -> 77 | C9: =Gen!B14 -> 1 | D9: ='Summery Report'!E8 -> 77 | E9: =SUM(E8) -> 1.3262195 | F9: =SUM(J9*E9)/D9 -> 40.63261 | G9: =SUM(L9*E9)/D9 -> 42.176709 | H9: =Gen!C14 -> 43041.44 | I9: =Gen!E14 -> 0 | J9: =Gen!S14 -> 2359.12 | K9: =Gen!AJ14 -> 89.65 | L9: =SUM(J9:K9) -> 2448.77 | M9: ='Water-Meter'!K49 -> 339.08585 | N9: ='Water-Meter'!E9 -> 139 | P9: 18665 | Q9: =SUM(P9-P8) -> 0 | R9: =SUM(Q9*O9) -> 0 | T9: 15719 | U9: =T9-T8 -> 0 | V9: =SUM(U9*S9) -> 0 | X9: 23208 | Y9: =X9-X8 -> 23.7 | Z9: =SUM(Y9*W9) -> 0 | AA9: =SUM(Z9*X11) -> 0 | AB9: 24232 | AC9: =AB9-AB8 -> 100 | AD9: 195364 | AE9: =AD9-AD8 -> 63 | AF9: ='Lpg (2)'!B13*2000/85 -> 2000 | AG9: ='Lpg (2)'!C13*1000/85 -> 1000 | AH9: ='Lpg (2)'!D13*1000/85 -> 58.823529 | AI9: =SUM(AF8*2000)+(AG9*1000)+(AH9*1000) -> 5058823.5 | AJ9: =SUM(AI8-AI9) -> 23529.412
A10: =Gen!A15 -> 43866 | B10: ='Summery Report'!E9 -> 77 | C10: =Gen!B15 -> 1 | D10: ='Summery Report'!E9 -> 77 | E10: =SUM(E9) -> 1.3262195 | F10: =SUM(J10*E10)/D10 -> 38.869083 | G10: =SUM(L10*E10)/D10 -> 41.095581 | H10: =Gen!C15 -> 40592.67 | I10: =Gen!E15 -> 0 | J10: =Gen!S15 -> 2256.73 | K10: =Gen!AJ15 -> 129.27 | L10: =SUM(J10:K10) -> 2386 | M10: ='Water-Meter'!K50 -> 383.76819 | N10: ='Water-Meter'!E10 -> 141 | P10: 18665 | Q10: =SUM(P10-P9) -> 0 | R10: =SUM(Q10*O10) -> 0 | T10: 15719 | U10: =T10-T9 -> 0 | V10: =SUM(U10*S10) -> 0 | W10: 4.8 | X10: 23251 | Y10: =X10-X9 -> 43 | Z10: =SUM(Y10*W10) -> 206.4 | AA10: =SUM(Z10*X12) -> 4807881.6 | AB10: 24330 | AC10: =AB10-AB9 -> 98 | AD10: 195427 | AE10: =AD10-AD9 -> 63 | AF10: ='Lpg (2)'!B14*2000/85 -> 2000 | AG10: ='Lpg (2)'!C14*1000/85 -> 894.11765 | AH10: ='Lpg (2)'!D14*1000/85 -> 0 | AI10: =SUM(AF9*2000)+(AG10*1000)+(AH10*1000) -> 4894117.6 | AJ10: =SUM(AI9-AI10) -> 164705.88
A11: =Gen!A16 -> 43867 | B11: ='Summery Report'!E10 -> 77 | C11: =Gen!B16 -> 1 | D11: ='Summery Report'!E10 -> 77 | E11: =SUM(E10) -> 1.3262195 | F11: =SUM(J11*E11)/D11 -> 42.912846 | G11: =SUM(L11*E11)/D11 -> 46.144688 | H11: =Gen!C16 -> 38206.67 | I11: =Gen!E16 -> 0 | J11: =Gen!S16 -> 2491.51 | K11: =Gen!AJ16 -> 187.64 | L11: =SUM(J11:K11) -> 2679.15 | M11: ='Water-Meter'!K51 -> 370.15578 | N11: ='Water-Meter'!E11 -> 129 | P11: 18665 | Q11: =SUM(P11-P10) -> 0 | R11: =SUM(Q11*O11) -> 0 | T11: 15719 | U11: =T11-T10 -> 0 | V11: =SUM(U11*S11) -> 0 | W11: 4.8 | X11: 23274 | Y11: =X11-X10 -> 23 | Z11: =SUM(Y11*W11) -> 110.4 | AA11: =SUM(Z11*X13) -> 2574196.8 | AB11: 24413 | AC11: =AB11-AB10 -> 83 | AD11: 195483 | AE11: =AD11-AD10 -> 56 | AF11: ='Lpg (2)'!B15*2000/85 -> 2000 | AG11: ='Lpg (2)'!C15*1000/85 -> 823.52941 | AH11: ='Lpg (2)'!D15*1000/85 -> 0 | AI11: =SUM(AF10*2000)+(AG11*1000)+(AH11*1000) -> 4823529.4 | AJ11: =SUM(AI10-AI11) -> 70588.235
A12: =Gen!A17 -> 43868 | B12: ='Summery Report'!E11 -> 77 | C12: =Gen!B17 -> 1 | D12: ='Summery Report'!E11 -> 77 | E12: =SUM(E11) -> 1.3262195 | F12: =SUM(J12*E12)/D12 -> 38.662571 | G12: =SUM(L12*E12)/D12 -> 42.161552 | H12: =Gen!C17 -> 35527.52 | I12: =Gen!E17 -> 0 | J12: =Gen!S17 -> 2244.74 | K12: =Gen!AJ17 -> 203.15 | L12: =SUM(J12:K12) -> 2447.89 | M12: ='Water-Meter'!K52 -> 390.1632 | N12: ='Water-Meter'!E12 -> 129 | O12: 2.5 | P12: 18674 | Q12: =SUM(P12-P11) -> 9 | R12: =SUM(Q12*O12) -> 22.5 | T12: 15719 | U12: =T12-T11 -> 0 | V12: =SUM(U12*S12) -> 0 | W12: 4.7 | X12: 23294 | Y12: =X12-X11 -> 20 | Z12: =SUM(Y12*W12) -> 94 | AA12: =SUM(Z12*X14) -> 2194054 | AB12: 24516 | AC12: =AB12-AB11 -> 103 | AD12: 195483 | AE12: =AD12-AD11 -> 0 | AF12: ='Lpg (2)'!B16*2000/85 -> 2000 | AG12: ='Lpg (2)'!C16*1000/85 -> 705.88235 | AH12: ='Lpg (2)'!D16*1000/85 -> 0 | AI12: =SUM(AF11*2000)+(AG12*1000)+(AH12*1000) -> 4705882.4 | AJ12: =SUM(AI11-AI12) -> 117647.06
A13: =Gen!A18 -> 43869 | B13: ='Summery Report'!E12 -> 13 | C13: =Gen!B18 -> 0.1429 | D13: ='Summery Report'!E12 -> 13 | E13: =SUM(E12) -> 1.3262195 | F13: =SUM(J13*E13)/D13 -> 262.12729 | G13: =SUM(L13*E13)/D13 -> 267.91572 | H13: =Gen!C18 -> 33079.63 | I13: =Gen!E18 -> 0 | J13: =Gen!S18 -> 2569.45 | K13: =Gen!AJ18 -> 56.74 | L13: =SUM(J13:K13) -> 2626.19 | M13: ='Water-Meter'!K53 -> 329.199 | N13: ='Water-Meter'!E13 -> 128 | O13: 2.5 | P13: 18687 | Q13: =SUM(P13-P12) -> 13 | R13: =SUM(Q13*O13) -> 32.5 | T13: 15719 | U13: =T13-T12 -> 0 | V13: =SUM(U13*S13) -> 0 | W13: 5 | X13: 23317 | Y13: =X13-X12 -> 23 | Z13: =SUM(Y13*W13) -> 115 | AA13: =SUM(Z13*X15) -> 0 | AB13: 24621 | AC13: =AB13-AB12 -> 105 | AD13: 195483 | AE13: =AD13-AD12 -> 0 | AF13: ='Lpg (2)'!B17*2000/85 -> 2000 | AG13: ='Lpg (2)'!C17*1000/85 -> 647.05882 | AH13: ='Lpg (2)'!D17*1000/85 -> 0 | AI13: =SUM(AF12*2000)+(AG13*1000)+(AH13*1000) -> 4647058.8 | AJ13: =SUM(AI12-AI13) -> 58823.529
A14: =Gen!A19 -> 43870 | B14: ='Summery Report'!E13 -> 16 | C14: =Gen!B19 -> 0.195 | D14: ='Summery Report'!E13 -> 16 | E14: =SUM(E13) -> 1.3262195 | F14: =SUM(J14*E14)/D14 -> 169.07807 | G14: =SUM(L14*E14)/D14 -> 182.5624 | H14: =Gen!C19 -> 45453.44 | I14: =Gen!E19 -> 15000 | J14: =Gen!S19 -> 2039.82 | K14: =Gen!AJ19 -> 162.68 | L14: =SUM(J14:K14) -> 2202.5 | M14: ='Water-Meter'!K54 -> 382.48232 | N14: ='Water-Meter'!E14 -> 96 | P14: 18687 | Q14: =SUM(P14-P13) -> 0 | R14: =SUM(Q14*O14) -> 0 | T14: 15719 | U14: =T14-T13 -> 0 | V14: =SUM(U14*S14) -> 0 | W14: 5.2 | X14: 23341 | Y14: =X14-X13 -> 24 | Z14: =SUM(Y14*W14) -> 124.8 | AA14: =SUM(Z14*X16) -> 0 | AB14: 24757 | AC14: =AB14-AB13 -> 136 | AD14: 195483 | AE14: =AD14-AD13 -> 0 | AF14: ='Lpg (2)'!B18*2000/85 -> 2000 | AG14: ='Lpg (2)'!C18*1000/85 -> 576.47059 | AH14: ='Lpg (2)'!D18*1000/85 -> 0 | AI14: =SUM(AF13*2000)+(AG14*1000)+(AH14*1000) -> 4576470.6 | AJ14: =SUM(AI13-AI14) -> 70588.235
A15: =Gen!A20 -> 43871 | B15: ='Summery Report'!E14 -> 15 | C15: =Gen!B20 -> 0.1818 | D15: ='Summery Report'!E14 -> 15 | E15: =SUM(E14) -> 1.3262195 | F15: =SUM(J15*E15)/D15 -> 0 | G15: =SUM(L15*E15)/D15 -> 0 | H15: =Gen!C20 -> 43250.94 | I15: =Gen!E20 -> 0 | J15: =Gen!S20 -> 0 | K15: =Gen!AJ20 -> 0 | L15: =SUM(J15:K15) -> 0 | M15: ='Water-Meter'!K55 -> 0 | N15: ='Water-Meter'!E15 -> 0 | Q15: =SUM(P15-P14) -> -18687 | R15: =SUM(Q15*O15) -> 0 | U15: =T15-T14 -> -15719 | V15: =SUM(U15*S15) -> 0 | Y15: =X15-X14 -> -23341 | Z15: =SUM(Y15*W15) -> 0 | AA15: =SUM(Z15*X17) -> 0 | AB15: 24878 | AC15: =AB15-AB14 -> 121 | AD15: 195532 | AE15: =AD15-AD14 -> 49 | AF15: ='Lpg (2)'!B19*2000/85 -> 0 | AG15: ='Lpg (2)'!C19*1000/85 -> 0 | AH15: ='Lpg (2)'!D19*1000/85 -> 0 | AI15: =SUM(AF15*2000)+(AG15*1000)+(AH15*1000) -> 0 | AJ15: =SUM(AI14-AI15) -> 4576470.6
A16: =Gen!A21 -> 43872 | B16: ='Summery Report'!E15 -> 0 | C16: =Gen!B21 -> 0 | D16: ='Summery Report'!E15 -> 0 | E16: =SUM(E15) -> 1.3262195 | F16: =SUM(J16*E16)/D16 -> #DIV/0! | G16: =SUM(L16*E16)/D16 -> #DIV/0! | H16: =Gen!C21 -> 43250.94 | I16: =Gen!E21 -> 0 | J16: =Gen!S21 -> 0 | K16: =Gen!AJ21 -> 0 | L16: =SUM(J16:K16) -> 0 | M16: ='Water-Meter'!K56 -> 0 | N16: ='Water-Meter'!E16 -> 0 | Q16: =SUM(P16-P15) -> 0 | R16: =SUM(Q16*O16) -> 0 | U16: =T16-T15 -> 0 | V16: =SUM(U16*S16) -> 0 | Y16: =X16-X15 -> 0 | Z16: =SUM(Y16*W16) -> 0 | AA16: =SUM(Z16*X18) -> 0 | AC16: =AB16-AB15 -> -24878 | AE16: =AD16-AD15 -> -195532 | AF16: ='Lpg (2)'!B20*2000/85 -> 0 | AG16: ='Lpg (2)'!C20*1000/85 -> 0 | AH16: ='Lpg (2)'!D20*1000/85 -> 0 | AI16: =SUM(AF16*2000)+(AG16*1000)+(AH16*1000) -> 0 | AJ16: =SUM(AI15-AI16) -> 0
A17: =Gen!A22 -> 43873 | B17: ='Summery Report'!E16 -> 0 | C17: =Gen!B22 -> 0 | D17: ='Summery Report'!E16 -> 0 | E17: =SUM(E16) -> 1.3262195 | F17: =SUM(J17*E17)/D17 -> #DIV/0! | G17: =SUM(L17*E17)/D17 -> #DIV/0! | H17: =Gen!C22 -> 43250.94 | I17: =Gen!E22 -> 0 | J17: =Gen!S22 -> 0 | K17: =Gen!AJ22 -> 0 | L17: =SUM(J17:K17) -> 0 | M17: ='Water-Meter'!K57 -> 0 | N17: ='Water-Meter'!E17 -> 0 | Q17: =SUM(P18-P16) -> 0 | R17: =SUM(Q17*O17) -> 0 | U17: =T17-T16 -> 0 | V17: =SUM(U17*S17) -> 0 | Y17: =X17-X16 -> 0 | Z17: =SUM(Y17*W17) -> 0 | AA17: =SUM(Z17*X19) -> 0 | AC17: =AB17-AB16 -> 0 | AE17: =AD17-AD16 -> 0 | AF17: ='Lpg (2)'!B21*2000/85 -> 0 | AG17: ='Lpg (2)'!C21*1000/85 -> 0 | AH17: ='Lpg (2)'!D21*1000/85 -> 0 | AI17: =SUM(AF17*2000)+(AG17*1000)+(AH17*1000) -> 0 | AJ17: =SUM(AI16-AI17) -> 0
A18: =Gen!A23 -> 43874 | B18: ='Summery Report'!E17 -> 0 | C18: =Gen!B23 -> 0 | D18: ='Summery Report'!E17 -> 0 | E18: =SUM(E17) -> 1.3262195 | F18: =SUM(J18*E18)/D18 -> #DIV/0! | G18: =SUM(L18*E18)/D18 -> #DIV/0! | H18: =Gen!C23 -> 43250.94 | I18: =Gen!E23 -> 0 | J18: =Gen!S23 -> 0 | K18: =Gen!AJ23 -> 0 | L18: =SUM(J18:K18) -> 0 | M18: ='Water-Meter'!K58 -> 0 | N18: ='Water-Meter'!E18 -> 0 | R18: =SUM(Q18*O18) -> 0 | U18: =T18-T17 -> 0 | V18: =SUM(U18*S18) -> 0 | Y18: =X18-X17 -> 0 | Z18: =SUM(Y18*W18) -> 0 | AA18: =SUM(Z18*X20) -> 0 | AC18: =AB18-AB17 -> 0 | AE18: =AD18-AD17 -> 0 | AF18: ='Lpg (2)'!B22*2000/85 -> 0 | AG18: ='Lpg (2)'!C22*1000/85 -> 0 | AH18: ='Lpg (2)'!D22*1000/85 -> 0 | AI18: =SUM(AF18*2000)+(AG18*1000)+(AH18*1000) -> 0 | AJ18: =SUM(AI17-AI18) -> 0
A19: =Gen!A24 -> 43875 | B19: ='Summery Report'!E18 -> 0 | C19: =Gen!B24 -> 0 | D19: ='Summery Report'!E18 -> 0 | E19: =SUM(E18) -> 1.3262195 | F19: =SUM(J19*E19)/D19 -> #DIV/0! | G19: =SUM(L19*E19)/D19 -> #DIV/0! | H19: =Gen!C24 -> 43250.94 | I19: =Gen!E24 -> 0 | J19: =Gen!S24 -> 0 | K19: =Gen!AJ24 -> 0 | L19: =SUM(J19:K19) -> 0 | M19: ='Water-Meter'!K59 -> 0 | N19: ='Water-Meter'!E19 -> 0 | R19: =SUM(Q19*O19) -> 0 | U19: =T19-T18 -> 0 | V19: =SUM(U19*S19) -> 0 | Y19: =X19-X18 -> 0 | Z19: =SUM(Y19*W19) -> 0 | AA19: =SUM(Z19*X21) -> 0 | AC19: =AB19-AB18 -> 0 | AE19: =AD19-AD18 -> 0 | AF19: ='Lpg (2)'!B23*2000/85 -> 0 | AG19: ='Lpg (2)'!C23*1000/85 -> 0 | AH19: ='Lpg (2)'!D23*1000/85 -> 0 | AI19: =SUM(AF19*2000)+(AG19*1000)+(AH19*1000) -> 0 | AJ19: =SUM(AI18-AI19) -> 0
A20: =Gen!A25 -> 43876 | B20: ='Summery Report'!E19 -> 0 | C20: =Gen!B25 -> 0 | D20: ='Summery Report'!E19 -> 0 | E20: =SUM(E19) -> 1.3262195 | F20: =SUM(J20*E20)/D20 -> #DIV/0! | G20: =SUM(L20*E20)/D20 -> #DIV/0! | H20: =Gen!C25 -> 43250.94 | I20: =Gen!E25 -> 0 | J20: =Gen!S25 -> 0 | K20: =Gen!AJ25 -> 0 | L20: =SUM(J20:K20) -> 0 | M20: ='Water-Meter'!K60 -> 0 | N20: ='Water-Meter'!E20 -> 0 | Q20: =SUM(P20-P19) -> 0 | R20: =SUM(Q20*O20) -> 0 | U20: =T20-T19 -> 0 | V20: =SUM(U20*S20) -> 0 | Y20: =X20-X19 -> 0 | Z20: =SUM(Y20*W20) -> 0 | AA20: =SUM(Z20*X22) -> 0 | AC20: =AB20-AB19 -> 0 | AE20: =AD20-AD19 -> 0 | AF20: ='Lpg (2)'!B24*2000/85 -> 0 | AG20: ='Lpg (2)'!C24*1000/85 -> 0 | AH20: ='Lpg (2)'!D24*1000/85 -> 0 | AI20: =SUM(AF20*2000)+(AG20*1000)+(AH20*1000) -> 0 | AJ20: =SUM(AI19-AI20) -> 0
A21: =Gen!A26 -> 43877 | B21: ='Summery Report'!E20 -> 0 | C21: =Gen!B26 -> 0 | D21: ='Summery Report'!E20 -> 0 | E21: =SUM(E20) -> 1.3262195 | F21: =SUM(J21*E21)/D21 -> #DIV/0! | G21: =SUM(L21*E21)/D21 -> #DIV/0! | H21: =Gen!C26 -> 43250.94 | I21: =Gen!E26 -> 18000 | J21: =Gen!S26 -> 0 | K21: =Gen!AJ26 -> 0 | L21: =SUM(J21:K21) -> 0 | M21: ='Water-Meter'!K61 -> 0 | N21: ='Water-Meter'!E21 -> 0 | Q21: =SUM(P21-P20) -> 0 | R21: =SUM(Q21*O21) -> 0 | U21: =T21-T20 -> 0 | V21: =SUM(U21*S21) -> 0 | Y21: =X21-X20 -> 0 | Z21: =SUM(Y21*W21) -> 0 | AA21: =SUM(Z21*X23) -> 0 | AC21: =AB21-AB20 -> 0 | AE21: =AD21-AD20 -> 0 | AF21: ='Lpg (2)'!B25*2000/85 -> 0 | AG21: ='Lpg (2)'!C25*1000/85 -> 0 | AH21: ='Lpg (2)'!D25*1000/85 -> 0 | AI21: =SUM(AF21*2000)+(AG21*1000)+(AH21*1000) -> 0 | AJ21: =SUM(AI20-AI21) -> 0
A22: =Gen!A27 -> 43878 | B22: ='Summery Report'!E21 -> 0 | C22: =Gen!B27 -> 0 | D22: ='Summery Report'!E21 -> 0 | E22: =SUM(E21) -> 1.3262195 | F22: =SUM(J22*E22)/D22 -> #DIV/0! | G22: =SUM(L22*E22)/D22 -> #DIV/0! | H22: =Gen!C27 -> 43250.94 | I22: =Gen!E27 -> 0 | J22: =Gen!S27 -> 0 | K22: =Gen!AJ27 -> 0 | L22: =SUM(J22:K22) -> 0 | M22: ='Water-Meter'!K62 -> 0 | N22: ='Water-Meter'!E22 -> 0 | Q22: =SUM(P22-P21) -> 0 | R22: =SUM(Q22*O22) -> 0 | U22: =T22-T21 -> 0 | V22: =SUM(U22*S22) -> 0 | Y22: =X22-X21 -> 0 | Z22: =SUM(Y22*W22) -> 0 | AA22: =SUM(Z22*X24) -> 0 | AC22: =AB22-AB21 -> 0 | AE22: =AD22-AD21 -> 0 | AF22: ='Lpg (2)'!B26*2000/85 -> 0 | AG22: ='Lpg (2)'!C26*1000/85 -> 0 | AH22: ='Lpg (2)'!D26*1000/85 -> 0 | AI22: =SUM(AF22*2000)+(AG22*1000)+(AH22*1000) -> 0 | AJ22: =SUM(AI21-AI22) -> 0
A23: =Gen!A28 -> 43879 | B23: ='Summery Report'!E22 -> 0 | C23: =Gen!B28 -> 0 | D23: ='Summery Report'!E22 -> 0 | E23: =SUM(E22) -> 1.3262195 | F23: =SUM(J23*E23)/D23 -> #DIV/0! | G23: =SUM(L23*E23)/D23 -> #DIV/0! | H23: =Gen!C28 -> 43250.94 | I23: =Gen!E28 -> 0 | J23: =Gen!S28 -> 0 | K23: =Gen!AJ28 -> 0 | L23: =SUM(J23:K23) -> 0 | M23: ='Water-Meter'!K63 -> 0 | N23: ='Water-Meter'!E23 -> 0 | Q23: =SUM(P23-P22) -> 0 | R23: =SUM(Q23*O23) -> 0 | U23: =T23-T22 -> 0 | V23: =SUM(U23*S23) -> 0 | Y23: =X23-X22 -> 0 | Z23: =SUM(Y23*W23) -> 0 | AA23: =SUM(Z23*X25) -> 0 | AC23: =AB23-AB22 -> 0 | AE23: =AD23-AD22 -> 0 | AF23: ='Lpg (2)'!B27*2000/85 -> 0 | AG23: ='Lpg (2)'!C27*1000/85 -> 0 | AH23: ='Lpg (2)'!D27*1000/85 -> 0 | AI23: =SUM(AF23*2000)+(AG23*1000)+(AH23*1000) -> 0 | AJ23: =SUM(AI22-AI23) -> 0
A24: =Gen!A29 -> 43880 | B24: ='Summery Report'!E23 -> 0 | C24: =Gen!B29 -> 0 | D24: ='Summery Report'!E23 -> 0 | E24: =SUM(E23) -> 1.3262195 | F24: =SUM(J24*E24)/D24 -> #DIV/0! | G24: =SUM(L24*E24)/D24 -> #DIV/0! | H24: =Gen!C29 -> 43250.94 | I24: =Gen!E29 -> 0 | J24: =Gen!S29 -> 0 | K24: =Gen!AJ29 -> 0 | L24: =SUM(J24:K24) -> 0 | M24: ='Water-Meter'!K64 -> 0 | N24: ='Water-Meter'!E24 -> 0 | Q24: =SUM(P24-P23) -> 0 | R24: =SUM(Q24*O24) -> 0 | U24: =T24-T23 -> 0 | V24: =SUM(U24*S24) -> 0 | Y24: =X24-X23 -> 0 | Z24: =SUM(Y24*W24) -> 0 | AA24: =SUM(Z24*X26) -> 0 | AC24: =AB24-AB23 -> 0 | AE24: =AD24-AD23 -> 0 | AF24: ='Lpg (2)'!B28*2000/85 -> 0 | AG24: ='Lpg (2)'!C28*1000/85 -> 0 | AH24: ='Lpg (2)'!D28*1000/85 -> 0 | AI24: =SUM(AF24*2000)+(AG24*1000)+(AH24*1000) -> 0 | AJ24: =SUM(AI23-AI24) -> 0
A25: =Gen!A30 -> 43881 | B25: ='Summery Report'!E24 -> 0 | C25: =Gen!B30 -> 0 | D25: ='Summery Report'!E24 -> 0 | E25: =SUM(E24) -> 1.3262195 | F25: =SUM(J25*E25)/D25 -> #DIV/0! | G25: =SUM(L25*E25)/D25 -> #DIV/0! | H25: =Gen!C30 -> 43250.94 | I25: =Gen!E30 -> 0 | J25: =Gen!S30 -> 0 | K25: =Gen!AJ30 -> 0 | L25: =SUM(J25:K25) -> 0 | M25: ='Water-Meter'!K65 -> 0 | N25: ='Water-Meter'!E25 -> 0 | Q25: =SUM(P25-P24) -> 0 | R25: =SUM(Q25*O25) -> 0 | U25: =T25-T24 -> 0 | V25: =SUM(U25*S25) -> 0 | Y25: =X25-X24 -> 0 | Z25: =SUM(Y25*W25) -> 0 | AA25: =SUM(Z25*X27) -> 0 | AC25: =AB25-AB24 -> 0 | AE25: =AD25-AD24 -> 0 | AF25: ='Lpg (2)'!B29*2000/85 -> 0 | AG25: ='Lpg (2)'!C29*1000/85 -> 0 | AH25: ='Lpg (2)'!D29*1000/85 -> 0 | AI25: =SUM(AF25*2000)+(AG25*1000)+(AH25*1000) -> 0 | AJ25: =SUM(AI24-AI25) -> 0
A26: =Gen!A31 -> 43882 | B26: ='Summery Report'!E25 -> 0 | C26: =Gen!B31 -> 0 | D26: ='Summery Report'!E25 -> 0 | E26: =SUM(E25) -> 1.3262195 | F26: =SUM(J26*E26)/D26 -> #DIV/0! | G26: =SUM(L26*E26)/D26 -> #DIV/0! | H26: =Gen!C31 -> 43250.94 | I26: =Gen!E31 -> 0 | J26: =Gen!S31 -> 0 | K26: =Gen!AJ31 -> 0 | L26: =SUM(J26:K26) -> 0 | M26: ='Water-Meter'!K66 -> 0 | N26: ='Water-Meter'!E26 -> 0 | Q26: =SUM(P26-P25) -> 0 | R26: =SUM(Q26*O26) -> 0 | U26: =T26-T25 -> 0 | V26: =SUM(U26*S26) -> 0 | Y26: =X26-X25 -> 0 | Z26: =SUM(Y26*W26) -> 0 | AA26: =SUM(Z26*X28) -> 0 | AC26: =AB26-AB25 -> 0 | AE26: =AD26-AD25 -> 0 | AF26: ='Lpg (2)'!B30*2000/85 -> 0 | AG26: ='Lpg (2)'!C30*1000/85 -> 0 | AH26: ='Lpg (2)'!D30*1000/85 -> 0 | AI26: =SUM(AF26*2000)+(AG26*1000)+(AH26*1000) -> 0 | AJ26: =SUM(AI25-AI26) -> 0
A27: =Gen!A32 -> 43883 | B27: ='Summery Report'!E26 -> 0 | C27: =Gen!B32 -> 0 | D27: ='Summery Report'!E26 -> 0 | E27: =SUM(E26) -> 1.3262195 | F27: =SUM(J27*E27)/D27 -> #DIV/0! | G27: =SUM(L27*E27)/D27 -> #DIV/0! | H27: =Gen!C32 -> 43250.94 | I27: =Gen!E32 -> 0 | J27: =Gen!S32 -> 0 | K27: =Gen!AJ32 -> 0 | L27: =SUM(J27:K27) -> 0 | M27: ='Water-Meter'!K67 -> 0 | N27: ='Water-Meter'!E27 -> 0 | Q27: =SUM(P27-P26) -> 0 | R27: =SUM(Q27*O27) -> 0 | U27: =T27-T26 -> 0 | V27: =SUM(U27*S27) -> 0 | Y27: =X27-X26 -> 0 | Z27: =SUM(Y27*W27) -> 0 | AA27: =SUM(Z27*X29) -> 0 | AC27: =AB27-AB26 -> 0 | AE27: =AD27-AD26 -> 0 | AF27: ='Lpg (2)'!B31*2000/85 -> 0 | AG27: ='Lpg (2)'!C31*1000/85 -> 0 | AH27: ='Lpg (2)'!D31*1000/85 -> 0 | AI27: =SUM(AF27*2000)+(AG27*1000)+(AH27*1000) -> 0 | AJ27: =SUM(AI26-AI27) -> 0
A28: =Gen!A33 -> 43884 | B28: ='Summery Report'!E27 -> 0 | C28: =Gen!B33 -> 0 | D28: ='Summery Report'!E27 -> 0 | E28: =SUM(E27) -> 1.3262195 | F28: =SUM(J28*E28)/D28 -> #DIV/0! | G28: =SUM(L28*E28)/D28 -> #DIV/0! | H28: =Gen!C33 -> 43250.94 | I28: =Gen!E33 -> 0 | J28: =Gen!S33 -> 0 | K28: =Gen!AJ33 -> 0 | L28: =SUM(J28:K28) -> 0 | M28: ='Water-Meter'!K68 -> 0 | N28: ='Water-Meter'!E28 -> 0 | Q28: =SUM(P28-P27) -> 0 | R28: =SUM(Q28*O28) -> 0 | U28: =T28-T27 -> 0 | V28: =SUM(U28*S28) -> 0 | Y28: =X28-X27 -> 0 | Z28: =SUM(Y28*W28) -> 0 | AA28: =SUM(Z28*X30) -> 0 | AC28: =SUM(AB28-AB27) -> 0 | AE28: =AD28-AD27 -> 0 | AF28: ='Lpg (2)'!B32*2000/85 -> 0 | AG28: ='Lpg (2)'!C32*1000/85 -> 0 | AH28: ='Lpg (2)'!D32*1000/85 -> 0 | AI28: =SUM(AF28*2000)+(AG28*1000)+(AH28*1000) -> 0 | AJ28: =SUM(AI27-AI28) -> 0
A29: =Gen!A34 -> 43885 | B29: ='Summery Report'!E28 -> 0 | C29: =Gen!B34 -> 0 | D29: ='Summery Report'!E28 -> 0 | E29: =SUM(E28) -> 1.3262195 | F29: =SUM(J29*E29)/D29 -> #DIV/0! | G29: =SUM(L29*E29)/D29 -> #DIV/0! | H29: =Gen!C34 -> 43250.94 | I29: =Gen!E34 -> 0 | J29: =Gen!S34 -> 0 | K29: =Gen!AJ34 -> 0 | L29: =SUM(J29:K29) -> 0 | M29: ='Water-Meter'!K69 -> 0 | N29: ='Water-Meter'!E29 -> 0 | Q29: =SUM(P29-P28) -> 0 | R29: =SUM(Q29*O29) -> 0 | U29: =T29-T28 -> 0 | V29: =SUM(U29*S29) -> 0 | Y29: =X29-X28 -> 0 | Z29: =SUM(Y29*W29) -> 0 | AA29: =SUM(Z29*X31) -> 0 | AC29: =SUM(AB29-AB28) -> 0 | AE29: =AD29-AD28 -> 0 | AF29: ='Lpg (2)'!B33*2000/85 -> 0 | AG29: ='Lpg (2)'!C33*1000/85 -> 0 | AH29: ='Lpg (2)'!D33*1000/85 -> 0 | AI29: =SUM(AF29*2000)+(AG29*1000)+(AH29*1000) -> 0 | AJ29: =SUM(AI28-AI29) -> 0
A30: =Gen!A35 -> 43886 | B30: ='Summery Report'!E29 -> 0 | C30: =Gen!B35 -> 0 | D30: ='Summery Report'!E29 -> 0 | E30: =SUM(E29) -> 1.3262195 | F30: =SUM(J30*E30)/D30 -> #DIV/0! | G30: =SUM(L30*E30)/D30 -> #DIV/0! | H30: =Gen!C35 -> 43250.94 | I30: =Gen!E35 -> 15000 | J30: =Gen!S35 -> 0 | K30: =Gen!AJ35 -> 0 | L30: =SUM(J30:K30) -> 0 | M30: ='Water-Meter'!K70 -> 0 | N30: ='Water-Meter'!E30 -> 0 | Q30: =SUM(P30-P29) -> 0 | R30: =SUM(Q30*O30) -> 0 | U30: =T30-T29 -> 0 | V30: =SUM(U30*S30) -> 0 | Y30: =X30-X29 -> 0 | Z30: =SUM(Y30*W30) -> 0 | AA30: =SUM(Z30*X32) -> 0 | AC30: =SUM(AB30-AB29) -> 0 | AE30: =AD30-AD29 -> 0 | AF30: ='Lpg (2)'!B34*2000/85 -> 0 | AG30: ='Lpg (2)'!C34*1000/85 -> 0 | AH30: ='Lpg (2)'!D34*1000/85 -> 0 | AI30: =SUM(AF30*2000)+(AG30*1000)+(AH30*1000) -> 0 | AJ30: =SUM(AI29-AI30) -> 0
A31: =Gen!A36 -> 43887 | B31: ='Summery Report'!E30 -> 0 | C31: =Gen!B36 -> 0 | D31: ='Summery Report'!E30 -> 0 | E31: =SUM(E30) -> 1.3262195 | F31: =SUM(J31*E31)/D31 -> #DIV/0! | G31: =SUM(L31*E31)/D31 -> #DIV/0! | H31: =Gen!C36 -> 43250.94 | I31: =Gen!E36 -> 0 | J31: =Gen!S36 -> 0 | K31: =Gen!AJ36 -> 0 | L31: =SUM(J31:K31) -> 0 | M31: ='Water-Meter'!K71 -> 0 | N31: ='Water-Meter'!E31 -> 0 | Q31: =SUM(P31-P30) -> 0 | R31: =SUM(Q31*O31) -> 0 | U31: =T31-T30 -> 0 | V31: =SUM(U31*S31) -> 0 | Y31: =X31-X30 -> 0 | Z31: =SUM(Y31*W31) -> 0 | AA31: =SUM(Z31*X33) -> 0 | AC31: =SUM(AB31-AB30) -> 0 | AE31: =AD31-AD30 -> 0 | AF31: ='Lpg (2)'!B35*2000/85 -> 0 | AG31: ='Lpg (2)'!C35*1000/85 -> 0 | AH31: ='Lpg (2)'!D35*1000/85 -> 0 | AI31: =SUM(AF31*2000)+(AG31*1000)+(AH31*1000) -> 0 | AJ31: =SUM(AI30-AI31) -> 0
A32: =Gen!A37 -> 43888 | B32: ='Summery Report'!E31 -> 0 | C32: =Gen!B37 -> 0 | D32: ='Summery Report'!E31 -> 0 | E32: =SUM(E31) -> 1.3262195 | F32: =SUM(J32*E32)/D32 -> #DIV/0! | G32: =SUM(L32*E32)/D32 -> #DIV/0! | H32: =Gen!C37 -> 43250.94 | I32: =Gen!E37 -> 0 | J32: =Gen!S37 -> 0 | K32: =Gen!AJ37 -> 0 | L32: =SUM(J32:K32) -> 0 | M32: ='Water-Meter'!K72 -> 0 | N32: ='Water-Meter'!E32 -> 0 | Q32: =SUM(P32-P31) -> 0 | R32: =SUM(Q32*O32) -> 0 | U32: =T32-T31 -> 0 | V32: =SUM(U32*S32) -> 0 | Y32: =X32-X31 -> 0 | Z32: =SUM(Y32*W32) -> 0 | AA32: =SUM(Z32*X34) -> 0 | AC32: =SUM(AB32-AB31) -> 0 | AE32: =AD32-AD31 -> 0 | AF32: ='Lpg (2)'!B36*2000/85 -> 0 | AG32: ='Lpg (2)'!C36*1000/85 -> 0 | AH32: ='Lpg (2)'!D36*1000/85 -> 0 | AI32: =SUM(AF32*2000)+(AG32*1000)+(AH32*1000) -> 0 | AJ32: =SUM(AI31-AI32) -> 0
A33: =Gen!A38 -> 43889 | B33: ='Summery Report'!E32 -> 0 | C33: =Gen!B38 -> 0 | D33: ='Summery Report'!E32 -> 0 | E33: =SUM(E32) -> 1.3262195 | F33: =SUM(J33*E33)/D33 -> #DIV/0! | G33: =SUM(L33*E33)/D33 -> #DIV/0! | H33: =Gen!C38 -> 43250.94 | I33: =Gen!E38 -> 0 | J33: =Gen!S38 -> 0 | K33: =Gen!AJ38 -> 0 | L33: =SUM(J33:K33) -> 0 | M33: ='Water-Meter'!K73 -> 0 | N33: ='Water-Meter'!E33 -> 0 | Q33: =SUM(P33-P32) -> 0 | R33: =SUM(Q33*O33) -> 0 | U33: =T33-T32 -> 0 | V33: =SUM(U33*S33) -> 0 | Y33: =X33-X32 -> 0 | Z33: =SUM(Y33*W33) -> 0 | AA33: =SUM(Z33*X35) -> 0 | AC33: =SUM(AB33-AB32) -> 0 | AE33: =AD33-AD32 -> 0 | AF33: ='Lpg (2)'!B37*2000/85 -> 0 | AG33: ='Lpg (2)'!C37*1000/85 -> 0 | AH33: ='Lpg (2)'!D37*1000/85 -> 0 | AI33: =SUM(AF33*2000)+(AG33*1000)+(AH33*1000) -> 0 | AJ33: =SUM(AI32-AI33) -> 0
A34: =Gen!A39 -> 43890 | B34: ='Summery Report'!E33 -> 0 | C34: =Gen!B39 -> 0 | D34: ='Summery Report'!E33 -> 0 | E34: =SUM(E33) -> 1.3262195 | F34: =SUM(J34*E34)/D34 -> #DIV/0! | G34: =SUM(L34*E34)/D34 -> #DIV/0! | H34: =Gen!C39 -> 43250.94 | I34: =Gen!E39 -> 0 | J34: =Gen!S39 -> 0 | K34: =Gen!AJ39 -> 0 | L34: =SUM(J34:K34) -> 0 | M34: ='Water-Meter'!K74 -> 0 | N34: ='Water-Meter'!E34 -> 0 | Q34: =SUM(P34-P33) -> 0 | R34: =SUM(Q34*O34) -> 0 | U34: =T34-T33 -> 0 | V34: =SUM(U34*S34) -> 0 | Y34: =X34-X33 -> 0 | Z34: =SUM(Y34*W34) -> 0 | AA34: =SUM(Z34*X36) -> 0 | AC34: =SUM(AB34-AB33) -> 0 | AE34: =AD34-AD33 -> 0 | AF34: ='Lpg (2)'!B38*2000/85 -> 0 | AG34: ='Lpg (2)'!C38*1000/85 -> 0 | AH34: ='Lpg (2)'!D38*1000/85 -> 0 | AI34: =SUM(AF34*2000)+(AG34*1000)+(AH34*1000) -> 0 | AJ34: =SUM(AI33-AI34) -> 0
A35: =Gen!A40 -> 43891 | B35: ='Summery Report'!E34 -> 0 | C35: =Gen!B40 -> 0 | D35: ='Summery Report'!E34 -> 0 | E35: =SUM(E34) -> 1.3262195 | F35: =SUM(J35*E35)/D35 -> #DIV/0! | G35: =SUM(L35*E35)/D35 -> #DIV/0! | H35: =Gen!C40 -> 43250.94 | I35: =Gen!E40 -> 0 | J35: =Gen!S40 -> 0 | K35: =Gen!AJ40 -> 0 | L35: =SUM(J35:K35) -> 0 | M35: ='Water-Meter'!K75 -> 0 | N35: ='Water-Meter'!E35 -> 0 | Q35: =SUM(P35-P34) -> 0 | R35: =SUM(Q35*O35) -> 0 | U35: =T35-T34 -> 0 | V35: =SUM(U35*S35) -> 0 | Y35: =X35-X34 -> 0 | Z35: =SUM(Y35*W35) -> 0 | AA35: =SUM(Z35*X37) -> 0 | AC35: =SUM(AB35-AB34) -> 0 | AE35: =AD35-AD34 -> 0 | AF35: ='Lpg (2)'!B39*2000/85 -> 0 | AG35: ='Lpg (2)'!C39*1000/85 -> 0 | AH35: ='Lpg (2)'!D39*1000/85 -> 0 | AI35: =SUM(AF35*2000)+(AG35*1000)+(AH35*1000) -> 0 | AJ35: =SUM(AI34-AI35) -> 0
A36: =Gen!A41 -> 43892 | B36: ='Summery Report'!E35 -> 0 | C36: =Gen!B41 -> 0 | D36: ='Summery Report'!E35 -> 0 | E36: =SUM(E35) -> 1.3262195 | F36: =SUM(J36*E36)/D36 -> #DIV/0! | G36: =SUM(L36*E36)/D36 -> #DIV/0! | H36: =Gen!C41 -> 43250.94 | I36: =Gen!E41 -> 0 | J36: =Gen!S41 -> 0 | K36: =Gen!AJ41 -> 0 | L36: =SUM(J36:K36) -> 0 | M36: ='Water-Meter'!K76 -> 0 | N36: ='Water-Meter'!E36 -> 0 | Q36: =SUM(P36-P35) -> 0 | R36: =SUM(Q36*O36) -> 0 | U36: =T36-T35 -> 0 | V36: =SUM(U36*S36) -> 0 | Y36: =X36-X35 -> 0 | Z36: =SUM(Y36*W36) -> 0 | AA36: =SUM(Z36*X38) -> 0 | AC36: =SUM(AB36-AB35) -> 0 | AE36: =AD36-AD35 -> 0 | AF36: ='Lpg (2)'!B40*2000/85 -> 0 | AG36: ='Lpg (2)'!C40*1000/85 -> 0 | AH36: ='Lpg (2)'!D40*1000/85 -> 0 | AI36: =SUM(AF36*1000)+(AG36*1000)+(AH36*2000) -> 0 | AJ36: =SUM(AI35-AI36) -> 0
A37: =Gen!A42 -> 43893 | B37: 0 | J37: =SUM(J6:J36) -> 19509.89 | L37: =SUM(J37:K37) -> 19509.89 | N37: ='Water-Meter'!E37 -> 0 | AC37: =SUM(AB37-AB36) -> 0 | AE37: =AD37-AD36 -> 0 | AJ37: =SUM(AJ6:AJ36) -> 0 | AK37: =SUM(AK6:AK36) -> 0

Sheet Kit report
B1: KITCHEN THREE PHASE KWH METER READING | H1: KITCHEN WATER METER READING | M1: AMANI Restaurant WATER METER READING | T1: LAUNDRY THREE PHASE KWH METER READING | Y1: LAUNDRY WATER METER READING
A2: Occ % | B2: DATE | C2: READING TIME | D2: METER READING OPEN | E2: METER READING ClOSE | F2: UNIT USED Kwh | H2: DATE | I2: READING TIME | J2: METER READING OPEN Cbm | K2: METER READING ClOSE Cbm | L2: UNIT USED Cbm | M2: DATE | N2: READING TIME | O2: METER READING OPEN Cbm | P2: METER READING ClOSE Cbm | Q2: UNIT USED Cbm | R2: Cost Per day Elct+Water $ | S2: % as per the total Lodge consumption | T2: DATE | U2: READING TIME | V2: METER READING OPEN (Kwh) | W2: METER READING ClOSE (Kwh) | X2: UNIT USED Kwh | Y2: DATE | Z2: READING TIME | AA2: METER READING OPEN Cbm | AB2: METER READING ClOSE Cbm | AC2: UNIT USED Cbm
A3: 43770 | B3: Close Last Month | E3: 8420.8 | F3: X120 | H3: Close Last Month | K3: ='[1]Water-Meter'!G5 -> 36423 | M3: Close Last Month | P3: ='[1]Water-Meter'!J5 -> 7351 | T3: Close Last Month | W3: 7597.7 | X3: =(W3-V3)*200 -> 1519540 | Y3: Close Last Month | AB3: ='[1]Water-Meter'!P5 -> 18541
A4: =Gen!B11 -> 0.2338 | B4: =Gen!A11 -> 43862 | D4: =E3 -> 8420.8 | E4: 8424.5 | F4: =SUM(E4-D4)*120 -> 444 | H4: =B4 -> 43862 | J4: =SUM(K3) -> 36423 | K4: ='[1]Water-Meter'!G6 -> 36434 | L4: =SUM(K4-J4) -> 11 | M4: =H4 -> 43862 | O4: =SUM(P3) -> 7351 | P4: ='[1]Water-Meter'!J6 -> 7353 | Q4: =SUM(P4-O4) -> 2 | R4: =SUM(Q4/1615) -> 0.0012383901 | S4: =SUM(F4/[1]Gen!T10) -> #DIV/0! | T4: =M4 -> 43862 | V4: =W3 -> 7597.7 | W4: 7601.2 | X4: =(W4-V4)*200 -> 700 | Y4: =T4 -> 43862 | AA4: 3397.9 | AB4: ='[1]Water-Meter'!P6 -> 18547 | AC4: =SUM(AB4-AA4) -> 15149.1
A5: =Gen!B12 -> 0.234 | B5: =Gen!A12 -> 43863 | D5: =E4 -> 8424.5 | E5: 8428.4 | F5: =SUM(E5-D5)*120 -> 468 | H5: =B5 -> 43863 | J5: =SUM(K4) -> 36434 | K5: ='[1]Water-Meter'!G7 -> 36454 | L5: =SUM(K5-J5) -> 20 | M5: =H5 -> 43863 | O5: =SUM(P4) -> 7353 | P5: ='[1]Water-Meter'!J7 -> 7357 | Q5: =SUM(P5-O5) -> 4 | R5: =SUM(Q5/1615) -> 0.0024767802 | S5: =SUM(F5/[1]Gen!T11) -> 0.082554242 | T5: =M5 -> 43863 | V5: =W4 -> 7601.2 | W5: 7604.7 | X5: =(W5-V5)*200 -> 700 | Y5: =T5 -> 43863 | AA5: =SUM(AB4) -> 18547 | AB5: ='[1]Water-Meter'!P7 -> 18554 | AC5: =SUM(AB5-AA5) -> 7
A6: =Gen!B13 -> 0.104 | B6: =Gen!A13 -> 43864 | D6: =E5 -> 8428.4 | E6: 8432.7 | F6: =SUM(E6-D6)*120 -> 516 | H6: =B6 -> 43864 | J6: =SUM(K5) -> 36454 | K6: ='[1]Water-Meter'!G8 -> 36472 | L6: =SUM(K6-J6) -> 18 | M6: =H6 -> 43864 | O6: =SUM(P5) -> 7357 | P6: ='[1]Water-Meter'!J8 -> 7360 | Q6: =SUM(P6-O6) -> 3 | R6: =SUM(Q6/1615) -> 0.0018575851 | S6: =SUM(F6/[1]Gen!T12) -> 0.083779834 | T6: =M6 -> 43864 | V6: =W5 -> 7604.7 | W6: 7609.5 | X6: =(W6-V6)*200 -> 960 | Y6: =T6 -> 43864 | AA6: =SUM(AB5) -> 18554 | AB6: ='[1]Water-Meter'!P8 -> 18563 | AC6: =SUM(AB6-AA6) -> 9
A7: =Gen!B14 -> 1 | B7: =Gen!A14 -> 43865 | D7: =E6 -> 8432.7 | E7: 8436.8 | F7: =SUM(E7-D7)*120 -> 492 | H7: =B7 -> 43865 | J7: =SUM(K6) -> 36472 | K7: ='[1]Water-Meter'!G9 -> 36485 | L7: =SUM(K7-J7) -> 13 | M7: =H7 -> 43865 | O7: =SUM(P6) -> 7360 | P7: ='[1]Water-Meter'!J9 -> 7364 | Q7: =SUM(P7-O7) -> 4 | R7: =SUM(Q7/1615) -> 0.0024767802 | S7: =SUM(F7/[1]Gen!T13) -> 0.074772036 | T7: =M7 -> 43865 | V7: =W6 -> 7609.5 | W7: 7614.8 | X7: =(W7-V7)*200 -> 1060 | Y7: =T7 -> 43865 | AA7: =SUM(AB6) -> 18563 | AB7: ='[1]Water-Meter'!P9 -> 18575 | AC7: =SUM(AB7-AA7) -> 12
A8: =Gen!B15 -> 1 | B8: =Gen!A15 -> 43866 | D8: =E7 -> 8436.8 | E8: 8441.4 | F8: =SUM(E8-D8)*120 -> 552 | H8: =B8 -> 43866 | J8: =SUM(K7) -> 36485 | K8: ='[1]Water-Meter'!G10 -> 36500 | L8: =SUM(K8-J8) -> 15 | M8: =H8 -> 43866 | O8: =SUM(P7) -> 7364 | P8: ='[1]Water-Meter'!J10 -> 7367 | Q8: =SUM(P8-O8) -> 3 | R8: =SUM(Q8/1615) -> 0.0018575851 | S8: =SUM(F8/[1]Gen!T14) -> 0.088703198 | T8: =M8 -> 43866 | V8: =W7 -> 7614.8 | W8: 7619 | X8: =(W8-V8)*200 -> 840 | Y8: =T8 -> 43866 | AA8: =SUM(AB7) -> 18575 | AB8: ='[1]Water-Meter'!P10 -> 18586 | AC8: =SUM(AB8-AA8) -> 11
A9: =Gen!B16 -> 1 | B9: =Gen!A16 -> 43867 | D9: =E8 -> 8441.4 | E9: 8445.9 | F9: =SUM(E9-D9)*120 -> 540 | H9: =B9 -> 43867 | J9: =SUM(K8) -> 36500 | K9: ='[1]Water-Meter'!G11 -> 36516 | L9: =SUM(K9-J9) -> 16 | M9: =H9 -> 43867 | O9: =SUM(P8) -> 7367 | P9: ='[1]Water-Meter'!J11 -> 7369 | Q9: =SUM(P9-O9) -> 2 | R9: =SUM(Q9/1615) -> 0.0012383901 | S9: =SUM(F9/[1]Gen!T15) -> 0.090240642 | T9: =M9 -> 43867 | V9: =W8 -> 7619 | W9: 7624.3 | X9: =(W9-V9)*200 -> 1060 | Y9: =T9 -> 43867 | AA9: =SUM(AB8) -> 18586 | AB9: ='[1]Water-Meter'!P11 -> 18593 | AC9: =SUM(AB9-AA9) -> 7
A10: =Gen!B17 -> 1 | B10: =Gen!A17 -> 43868 | D10: =E9 -> 8445.9 | E10: 8450.6 | F10: =SUM(E10-D10)*120 -> 564 | H10: =B10 -> 43868 | J10: =SUM(K9) -> 36516 | K10: ='[1]Water-Meter'!G12 -> 36529 | L10: =SUM(K10-J10) -> 13 | M10: =H10 -> 43868 | O10: =SUM(P9) -> 7369 | P10: ='[1]Water-Meter'!J12 -> 7372 | Q10: =SUM(P10-O10) -> 3 | R10: =SUM(Q10/1615) -> 0.0018575851 | S10: =SUM(F10/[1]Gen!T16) -> 0.092413567 | T10: =M10 -> 43868 | V10: =W9 -> 7624.3 | W10: 7630.3 | X10: =(W10-V10)*200 -> 1200 | Y10: =T10 -> 43868 | AA10: =SUM(AB9) -> 18593 | AB10: ='[1]Water-Meter'!P12 -> 18606 | AC10: =SUM(AB10-AA10) -> 13 | AH10: 5850
A11: =Gen!B18 -> 0.1429 | B11: =Gen!A18 -> 43869 | D11: =E10 -> 8450.6 | E11: 8455.3 | F11: =SUM(E11-D11)*120 -> 564 | H11: =B11 -> 43869 | J11: =SUM(K10) -> 36529 | K11: ='[1]Water-Meter'!G13 -> 36543 | L11: =SUM(K11-J11) -> 14 | M11: =H11 -> 43869 | O11: =SUM(P10) -> 7372 | P11: ='[1]Water-Meter'!J13 -> 7374 | Q11: =SUM(P11-O11) -> 2 | R11: =SUM(Q11/1615) -> 0.0012383901 | S11: =SUM(F11/[1]Gen!T17) -> 0.10114778 | T11: =M11 -> 43869 | V11: =W10 -> 7630.3 | W11: 7636.4 | X11: =(W11-V11)*200 -> 1220 | Y11: =T11 -> 43869 | AA11: =SUM(AB10) -> 18606 | AB11: ='[1]Water-Meter'!P13 -> 18616 | AC11: =SUM(AB11-AA11) -> 10
A12: =Gen!B19 -> 0.195 | B12: =Gen!A19 -> 43870 | D12: =E11 -> 8455.3 | E12: 8459.9 | F12: =SUM(E12-D12)*120 -> 552 | H12: =B12 -> 43870 | J12: =SUM(K11) -> 36543 | K12: ='[1]Water-Meter'!G14 -> 36560 | L12: =SUM(K12-J12) -> 17 | M12: =H12 -> 43870 | O12: =SUM(P11) -> 7374 | P12: ='[1]Water-Meter'!J14 -> 7377 | Q12: =SUM(P12-O12) -> 3 | R12: =SUM(Q12/1615) -> 0.0018575851 | S12: =SUM(F12/[1]Gen!T18) -> 0.09978308 | T12: =M12 -> 43870 | V12: =W11 -> 7636.4 | W12: 7641.7 | X12: =(W12-V12)*200 -> 1060 | Y12: =T12 -> 43870 | AA12: =SUM(AB11) -> 18616 | AB12: ='[1]Water-Meter'!P14 -> 18623
A13: =Gen!B20 -> 0.1818 | B13: =Gen!A20 -> 43871 | D13: =E12 -> 8459.9 | F13: =SUM(E13-D13)*120 -> -1015188 | H13: =B13 -> 43871 | J13: =SUM(K12) -> 36560 | K13: ='[1]Water-Meter'!G15 -> 36574 | L13: =SUM(K13-J13) -> 14 | M13: =H13 -> 43871 | O13: =SUM(P12) -> 7377 | P13: ='[1]Water-Meter'!J15 -> 7381 | Q13: =SUM(P13-O13) -> 4 | R13: =SUM(Q13/1615) -> 0.0024767802 | S13: =SUM(F13/[1]Gen!T19) -> -162.87309 | T13: =M13 -> 43871 | V13: =W12 -> 7641.7 | X13: =(W13-V13)*200 -> -1528340 | Y13: =T13 -> 43871 | AA13: =SUM(AB12) -> 18623 | AB13: ='[1]Water-Meter'!P15 -> 18634 | AC13: =SUM(AB13-AA13) -> 11
A14: =Gen!B21 -> 0 | B14: =Gen!A21 -> 43872 | D14: =E13 -> 0 | F14: =SUM(E14-D14)*120 -> 0 | H14: =B14 -> 43872 | J14: =SUM(K13) -> 36574 | K14: ='[1]Water-Meter'!G16 -> 36591 | L14: =SUM(K14-J14) -> 17 | M14: =H14 -> 43872 | O14: =SUM(P13) -> 7381 | P14: ='[1]Water-Meter'!J16 -> 7385 | Q14: =SUM(P14-O14) -> 4 | R14: =SUM(Q14/1615) -> 0.0024767802 | S14: =SUM(F14/[1]Gen!T20) -> 0 | T14: =M14 -> 43872 | V14: =W13 -> 0 | X14: =(W14-V14)*200 -> 0 | Y14: =T14 -> 43872 | AA14: =SUM(AB13) -> 18634 | AB14: ='[1]Water-Meter'!P16 -> 18643 | AC14: =SUM(AB14-AA14) -> 9
A15: =Gen!B22 -> 0 | B15: =Gen!A22 -> 43873 | D15: =E14 -> 0 | F15: =SUM(E15-D15)*120 -> 0 | H15: =B15 -> 43873 | J15: =SUM(K14) -> 36591 | K15: ='[1]Water-Meter'!G17 -> 36605 | L15: =SUM(K15-J15) -> 14 | M15: =H15 -> 43873 | O15: =SUM(P14) -> 7385 | P15: ='[1]Water-Meter'!J17 -> 7388 | Q15: =SUM(P15-O15) -> 3 | R15: =SUM(Q15/1615) -> 0.0018575851 | S15: =SUM(F15/[1]Gen!T21) -> 0 | T15: =M15 -> 43873 | V15: =W14 -> 0 | X15: =(W15-V15)*200 -> 0 | Y15: =T15 -> 43873 | AA15: =SUM(AB14) -> 18643 | AB15: ='[1]Water-Meter'!P17 -> 18652 | AC15: =SUM(AB15-AA15) -> 9
A16: =Gen!B23 -> 0 | B16: =Gen!A23 -> 43874 | D16: =E15 -> 0 | F16: =SUM(E16-D16)*120 -> 0 | H16: =B16 -> 43874 | J16: =SUM(K15) -> 36605 | K16: ='[1]Water-Meter'!G18 -> 36619 | L16: =SUM(K16-J16) -> 14 | M16: =H16 -> 43874 | O16: =SUM(P15) -> 7388 | P16: ='[1]Water-Meter'!J18 -> 7390 | Q16: =SUM(P16-O16) -> 2 | R16: =SUM(Q16/1615) -> 0.0012383901 | S16: =SUM(F16/[1]Gen!T22) -> 0 | T16: =M16 -> 43874 | V16: =W15 -> 0 | X16: =(W16-V16)*200 -> 0 | Y16: =T16 -> 43874 | AA16: =SUM(AB15) -> 18652 | AB16: ='[1]Water-Meter'!P18 -> 18661 | AC16: =SUM(AB16-AA16) -> 9
A17: =Gen!B24 -> 0 | B17: =Gen!A24 -> 43875 | D17: =E16 -> 0 | F17: =SUM(E17-D17)*120 -> 0 | H17: =B17 -> 43875 | J17: =SUM(K16) -> 36619 | K17: ='[1]Water-Meter'!G19 -> 36632 | L17: =SUM(K17-J17) -> 13 | M17: =H17 -> 43875 | O17: =SUM(P16) -> 7390 | P17: ='[1]Water-Meter'!J19 -> 7393 | Q17: =SUM(P17-O17) -> 3 | R17: =SUM(Q17/1615) -> 0.0018575851 | S17: =SUM(F17/[1]Gen!T23) -> 0 | T17: =M17 -> 43875 | V17: =W16 -> 0 | X17: =(W17-V17)*200 -> 0 | Y17: =T17 -> 43875 | AA17: =SUM(AB16) -> 18661 | AB17: ='[1]Water-Meter'!P19 -> 18672 | AC17: =SUM(AB17-AA17) -> 11
A18: =Gen!B25 -> 0 | B18: =Gen!A25 -> 43876 | D18: =E17 -> 0 | F18: =SUM(E18-D18)*120 -> 0 | H18: =B18 -> 43876 | J18: =SUM(K17) -> 36632 | K18: ='[1]Water-Meter'!G20 -> 36651 | L18: =SUM(K18-J18) -> 19 | M18: =H18 -> 43876 | O18: =SUM(P17) -> 7393 | P18: ='[1]Water-Meter'!J20 -> 7396 | Q18: =SUM(P18-O18) -> 3 | R18: =SUM(Q18/1615) -> 0.0018575851 | S18: =SUM(F18/[1]Gen!T24) -> 0 | T18: =M18 -> 43876 | V18: =W17 -> 0 | X18: =(W18-V18)*200 -> 0 | Y18: =T18 -> 43876 | AA18: =SUM(AB17) -> 18672 | AB18: ='[1]Water-Meter'!P20 -> 18680 | AC18: =SUM(AB18-AA18) -> 8
A19: =Gen!B26 -> 0 | B19: =Gen!A26 -> 43877 | D19: =E18 -> 0 | F19: =SUM(E19-D19)*120 -> 0 | H19: =B19 -> 43877 | J19: =SUM(K18) -> 36651 | K19: ='[1]Water-Meter'!G21 -> 36668 | L19: =SUM(K19-J19) -> 17 | M19: =H19 -> 43877 | O19: =SUM(P18) -> 7396 | P19: ='[1]Water-Meter'!J21 -> 7398 | Q19: =SUM(P19-O19) -> 2 | R19: =SUM(Q19/1615) -> 0.0012383901 | S19: =SUM(F19/[1]Gen!T25) -> 0 | T19: =M19 -> 43877 | V19: =W18 -> 0 | X19: =(W19-V19)*200 -> 0 | Y19: =T19 -> 43877 | AA19: =SUM(AB18) -> 18680 | AB19: ='[1]Water-Meter'!P21 -> 18689 | AC19: =SUM(AB19-AA19) -> 9
A20: =Gen!B27 -> 0 | B20: =Gen!A27 -> 43878 | D20: =E19 -> 0 | F20: =SUM(E20-D20)*120 -> 0 | H20: =B20 -> 43878 | J20: =SUM(K19) -> 36668 | K20: ='[1]Water-Meter'!G22 -> 36681 | L20: =SUM(K20-J20) -> 13 | M20: =H20 -> 43878 | O20: =SUM(P19) -> 7398 | P20: ='[1]Water-Meter'!J22 -> 7402 | Q20: =SUM(P20-O20) -> 4 | R20: =SUM(Q20/1615) -> 0.0024767802 | S20: =SUM(F20/[1]Gen!T26) -> 0 | T20: =M20 -> 43878 | V20: =W19 -> 0 | X20: =(W20-V20)*200 -> 0 | Y20: =T20 -> 43878 | AA20: =SUM(AB19) -> 18689 | AB20: ='[1]Water-Meter'!P22 -> 18701 | AC20: =SUM(AB20-AA20) -> 12
A21: =Gen!B28 -> 0 | B21: =Gen!A28 -> 43879 | D21: =E20 -> 0 | F21: =SUM(E21-D21)*120 -> 0 | H21: =B21 -> 43879 | J21: =SUM(K20) -> 36681 | K21: ='[1]Water-Meter'!G23 -> 36696 | L21: =SUM(K21-J21) -> 15 | M21: =H21 -> 43879 | O21: =SUM(P20) -> 7402 | P21: ='[1]Water-Meter'!J23 -> 7404 | Q21: =SUM(P21-O21) -> 2 | R21: =SUM(Q21/1615) -> 0.0012383901 | S21: =SUM(F21/[1]Gen!T28) -> 0 | T21: =M21 -> 43879 | V21: =W20 -> 0 | X21: =(W21-V21)*200 -> 0 | Y21: =T21 -> 43879 | AA21: =SUM(AB20) -> 18701 | AB21: ='[1]Water-Meter'!P23 -> 18712 | AC21: =SUM(AB21-AA21) -> 11
A22: =Gen!B29 -> 0 | B22: =Gen!A29 -> 43880 | D22: =E21 -> 0 | F22: =SUM(E22-D22)*120 -> 0 | H22: =B22 -> 43880 | J22: =SUM(K21) -> 36696 | K22: ='[1]Water-Meter'!G24 -> 36708 | L22: =SUM(K22-J22) -> 12 | M22: =H22 -> 43880 | O22: =SUM(P21) -> 7404 | P22: ='[1]Water-Meter'!J24 -> 7408 | Q22: =SUM(P22-O22) -> 4 | R22: =SUM(Q22/1615) -> 0.0024767802 | S22: =SUM(F22/[1]Gen!T29) -> 0 | T22: =M22 -> 43880 | V22: =W21 -> 0 | X22: =(W22-V22)*200 -> 0 | Y22: =T22 -> 43880 | AA22: =SUM(AB21) -> 18712 | AB22: ='[1]Water-Meter'!P24 -> 18719 | AC22: =SUM(AB22-AA22) -> 7
A23: =Gen!B30 -> 0 | B23: =Gen!A30 -> 43881 | D23: =E22 -> 0 | F23: =SUM(E23-D23)*120 -> 0 | H23: =B23 -> 43881 | J23: =SUM(K22) -> 36708 | K23: ='[1]Water-Meter'!G25 -> 36724 | L23: =SUM(K23-J23) -> 16 | M23: =H23 -> 43881 | O23: =SUM(P22) -> 7408 | P23: ='[1]Water-Meter'!J25 -> 7412 | Q23: =SUM(P23-O23) -> 4 | R23: =SUM(Q23/1615) -> 0.0024767802 | S23: =SUM(F23/[1]Gen!T30) -> 0 | T23: =M23 -> 43881 | V23: =W22 -> 0 | X23: =(W23-V23)*200 -> 0 | Y23: =T23 -> 43881 | AA23: =SUM(AB22) -> 18719 | AB23: ='[1]Water-Meter'!P25 -> 18728 | AC23: =SUM(AB23-AA23) -> 9
A24: =Gen!B31 -> 0 | B24: =Gen!A31 -> 43882 | D24: =SUM(E23) -> 0 | F24: =SUM(E24-D24)*120 -> 0 | H24: =B24 -> 43882 | J24: =SUM(K23) -> 36724 | K24: ='[1]Water-Meter'!G26 -> 36740 | L24: =SUM(K24-J24) -> 16 | M24: =H24 -> 43882 | O24: =SUM(P23) -> 7412 | P24: ='[1]Water-Meter'!J26 -> 7415 | Q24: =SUM(P24-O24) -> 3 | R24: =SUM(Q24/1615) -> 0.0018575851 | S24: =SUM(F24/[1]Gen!T31) -> 0 | T24: 5835.7 | V24: =W23 -> 0 | X24: =(W24-V24)*200 -> 0 | Y24: =T24 -> 5835.7 | AA24: =SUM(AB23) -> 18728 | AB24: ='[1]Water-Meter'!P26 -> 18737 | AC24: =SUM(AB24-AA24) -> 9
A25: =Gen!B32 -> 0 | B25: =Gen!A32 -> 43883 | D25: =SUM(E24) -> 0 | F25: =SUM(E25-D25)*120 -> 0 | H25: =B25 -> 43883 | J25: =SUM(K24) -> 36740 | K25: ='[1]Water-Meter'!G27 -> 36754 | L25: =SUM(K25-J25) -> 14 | M25: =H25 -> 43883 | O25: =SUM(P24) -> 7415 | P25: ='[1]Water-Meter'!J27 -> 7418 | Q25: =SUM(P25-O25) -> 3 | R25: =SUM(Q25/1615) -> 0.0018575851 | S25: =SUM(F25/[1]Gen!T32) -> 0 | T25: =M25 -> 43883 | V25: =W24 -> 0 | X25: =(W25-V25)*200 -> 0 | Y25: =T25 -> 43883 | AA25: =SUM(AB24) -> 18737 | AB25: ='[1]Water-Meter'!P27 -> 18746 | AC25: =SUM(AB25-AA25) -> 9
A26: =Gen!B33 -> 0 | B26: =Gen!A33 -> 43884 | D26: =SUM(E25) -> 0 | F26: =SUM(E26-D26)*120 -> 0 | H26: =B26 -> 43884 | J26: =SUM(K25) -> 36754 | K26: ='[1]Water-Meter'!G28 -> 36767 | L26: =SUM(K26-J26) -> 13 | M26: =H26 -> 43884 | O26: =SUM(P25) -> 7418 | P26: ='[1]Water-Meter'!J28 -> 7421 | Q26: =SUM(P26-O26) -> 3 | R26: =SUM(Q26/1615) -> 0.0018575851 | S26: =SUM(F26/[1]Gen!T33) -> 0 | T26: =M26 -> 43884 | V26: =W25 -> 0 | X26: =(W26-V26)*200 -> 0 | Y26: =T26 -> 43884 | AA26: =SUM(AB25) -> 18746 | AB26: ='[1]Water-Meter'!P28 -> 18754 | AC26: =SUM(AB26-AA26) -> 8
A27: =Gen!B34 -> 0 | B27: =Gen!A34 -> 43885 | D27: =SUM(E26) -> 0 | F27: =SUM(E27-D27)*120 -> 0 | H27: =B27 -> 43885 | J27: =SUM(K26) -> 36767 | K27: ='[1]Water-Meter'!G29 -> 36779 | L27: =SUM(K27-J27) -> 12 | M27: =H27 -> 43885 | O27: =SUM(P26) -> 7421 | P27: ='[1]Water-Meter'!J29 -> 7423 | Q27: =SUM(P27-O27) -> 2 | R27: =SUM(Q27/1615) -> 0.0012383901 | S27: =SUM(F27/[1]Gen!T34) -> 0 | T27: =M27 -> 43885 | V27: =W26 -> 0 | X27: =(W27-V27)*200 -> 0 | Y27: =T27 -> 43885 | AA27: =SUM(AB26) -> 18754 | AB27: ='[1]Water-Meter'!P29 -> 18763 | AC27: =SUM(AB27-AA27) -> 9
A28: =Gen!B35 -> 0 | B28: =Gen!A35 -> 43886 | D28: =SUM(E27) -> 0 | F28: =SUM(E28-D28)*120 -> 0 | H28: =B28 -> 43886 | J28: =SUM(K27) -> 36779 | K28: ='[1]Water-Meter'!G30 -> 36792 | L28: =SUM(K28-J28) -> 13 | M28: =H28 -> 43886 | O28: =SUM(P27) -> 7423 | P28: ='[1]Water-Meter'!J30 -> 7426 | Q28: =SUM(P28-O28) -> 3 | R28: =SUM(Q28/1615) -> 0.0018575851 | S28: =SUM(F28/[1]Gen!T35) -> 0 | T28: =M28 -> 43886 | V28: =W27 -> 0 | X28: =(W28-V28)*200 -> 0 | Y28: =T28 -> 43886 | AA28: =SUM(AB27) -> 18763 | AB28: ='[1]Water-Meter'!P30 -> 18773 | AC28: =SUM(AB28-AA28) -> 10
A29: =Gen!B36 -> 0 | B29: =Gen!A36 -> 43887 | D29: =SUM(E28) -> 0 | F29: =SUM(E29-D29)*120 -> 0 | H29: =B29 -> 43887 | J29: =SUM(K28) -> 36792 | K29: ='[1]Water-Meter'!G31 -> 36809 | L29: =SUM(K29-J29) -> 17 | M29: =H29 -> 43887 | O29: =SUM(P28) -> 7426 | P29: ='[1]Water-Meter'!J31 -> 7428 | Q29: =SUM(P29-O29) -> 2 | R29: =SUM(Q29/1615) -> 0.0012383901 | S29: =SUM(F29/[1]Gen!T36) -> 0 | T29: =M29 -> 43887 | V29: =W28 -> 0 | X29: =(W29-V29)*200 -> 0 | Y29: =T29 -> 43887 | AA29: =SUM(AB28) -> 18773 | AB29: ='[1]Water-Meter'!P31 -> 18782 | AC29: =SUM(AB29-AA29) -> 9
A30: =Gen!B37 -> 0 | B30: =Gen!A37 -> 43888 | D30: =SUM(E29) -> 0 | F30: =SUM(E30-D30)*120 -> 0 | H30: =B30 -> 43888 | J30: =SUM(K29) -> 36809 | K30: ='[1]Water-Meter'!G32 -> 36825 | L30: =SUM(K30-J30) -> 16 | M30: =H30 -> 43888 | O30: =SUM(P29) -> 7428 | P30: ='[1]Water-Meter'!J32 -> 7432 | Q30: =SUM(P30-O30) -> 4 | R30: =SUM(Q30/1615) -> 0.0024767802 | S30: =SUM(F30/[1]Gen!T37) -> 0 | T30: =M30 -> 43888 | V30: =W29 -> 0 | X30: =(W30-V30)*200 -> 0 | Y30: =T30 -> 43888 | AA30: =SUM(AB29) -> 18782 | AB30: ='[1]Water-Meter'!P32 -> 18790 | AC30: =SUM(AB30-AA30) -> 8
A31: =Gen!B38 -> 0 | B31: =Gen!A38 -> 43889 | D31: =SUM(E30) -> 0 | F31: =SUM(E31-D31)*120 -> 0 | H31: =B31 -> 43889 | J31: =SUM(K30) -> 36825 | K31: ='[1]Water-Meter'!G33 -> #REF! | L31: =SUM(K31-J31) -> #REF! | M31: =H31 -> 43889 | O31: =SUM(P30) -> 7432 | P31: ='[1]Water-Meter'!J33 -> #REF! | Q31: =SUM(P31-O31) -> #REF! | R31: =SUM(Q31/1615) -> #REF! | S31: =SUM(F31/[1]Gen!T38) -> #DIV/0! | T31: =M31 -> 43889 | V31: =W30 -> 0 | X31: =(W31-V31)*200 -> 0 | Y31: =T31 -> 43889 | AA31: =SUM(AB30) -> 18790 | AB31: ='[1]Water-Meter'!P33 -> #REF! | AC31: =SUM(AB31-AA31) -> #REF!
A32: =Gen!B39 -> 0 | B32: =Gen!A39 -> 43890 | D32: =SUM(E31) -> 0 | F32: =SUM(E32-D32)*120 -> 0 | H32: =B32 -> 43890 | J32: =SUM(K31) -> #REF! | K32: ='[1]Water-Meter'!G34 -> #REF! | L32: =SUM(K32-J32) -> #REF! | M32: =H32 -> 43890 | O32: =SUM(P31) -> #REF! | P32: ='[1]Water-Meter'!J34 -> #REF! | Q32: =SUM(P32-O32) -> #REF! | R32: =SUM(Q32/1615) -> #REF! | S32: =SUM(F32/[1]Gen!T39) -> #DIV/0! | T32: =M32 -> 43890 | V32: =W31 -> 0 | X32: =(W32-V32)*200 -> 0 | Y32: =T32 -> 43890 | AA32: =SUM(AB31) -> #REF! | AB32: ='[1]Water-Meter'!P34 -> #REF! | AC32: =SUM(AB32-AA32) -> #REF!
A33: =Gen!B40 -> 0 | B33: =Gen!A40 -> 43891 | D33: =SUM(E32) -> 0 | F33: =SUM(E33-D33)*120 -> 0 | H33: =B33 -> 43891 | J33: =SUM(K32) -> #REF! | K33: ='[1]Water-Meter'!G35 -> #REF! | L33: =SUM(K33-J33) -> #REF! | M33: =H33 -> 43891 | O33: =SUM(P32) -> #REF! | P33: ='[1]Water-Meter'!J35 -> #REF! | Q33: =SUM(P33-O33) -> #REF! | R33: =SUM(Q33/1615) -> #REF! | S33: =SUM(F33/[1]Gen!T40) -> #DIV/0! | T33: =M33 -> 43891 | V33: =W32 -> 0 | X33: =(W33-V33)*200 -> 0 | Y33: =T33 -> 43891 | AA33: =SUM(AB32) -> #REF! | AB33: ='[1]Water-Meter'!P35 -> #REF! | AC33: =SUM(AB33-AA33) -> #REF!
A34: =Gen!B41 -> 0 | B34: =Gen!A41 -> 43892 | D34: =SUM(E33) -> 0 | F34: =SUM(E34-D34)*120 -> 0 | H34: =B34 -> 43892 | J34: =SUM(K33) -> #REF! | K34: ='[1]Water-Meter'!G36 -> #REF! | L34: =SUM(K34-J34) -> #REF! | M34: =H34 -> 43892 | O34: =SUM(P33) -> #REF! | P34: ='[1]Water-Meter'!J36 -> #REF! | Q34: =SUM(P34-O34) -> #REF! | R34: =SUM(Q34/1615) -> #REF! | S34: =SUM(F34/[1]Gen!T41) -> #DIV/0! | T34: =M34 -> 43892 | V34: =SUM(W33) -> 0 | X34: =(W34-V34)*200 -> 0 | Y34: =T34 -> 43892 | AA34: =SUM(AB33) -> #REF! | AB34: ='[1]Water-Meter'!P36 -> #REF! | AC34: =SUM(AB34-AA34) -> #REF!
A35: =[1]Gen!B42 -> #REF! | B35: =[1]Gen!A42 -> #REF! | D35: =SUM(E34) -> 0 | F35: =SUM(F4:F6) -> 1428 | H35: =B35 -> #REF! | J35: =SUM(K34) -> #REF! | K35: ='[1]Water-Meter'!G37 -> #REF! | L35: =SUM(L5:L34) -> #REF! | M35: =H35 -> #REF! | O35: =SUM(P34) -> #REF! | P35: ='[1]Water-Meter'!J37 -> #REF! | Q35: =SUM(Q5:Q34) -> #REF! | R35: =SUM(Q35/1615) -> #REF! | S35: =SUM(F35/[1]Gen!T42) -> #DIV/0! | T35: =M35 -> #REF! | V35: =SUM(W34) -> 0 | X35: =(W35-V35)*200 -> 0 | Y35: =T35 -> #REF! | AA35: =SUM(AB34) -> #REF! | AB35: ='[1]Water-Meter'!P37 -> #REF! | AC35: =SUM(AC5:AC34) -> #REF!
X36: =SUM(X4:X6) -> 2360

Sheet Summery Report
A2: Generator and Diseal Summry Report January 2020
A4: Date | B4: Gen Set Hours Working | C4: Occ% | D4: Total OCC Room | E4: Guest Room Occ | F4: Total Kwh Generated | G4: Diesel consumed by Gen (Ltrs) | H4: Diesel consumed by Vehicle (Ltrs) | I4: Total diesel consumed (Ltrs) | J4: Balance stock of Diesel (Ltrs) | K4: Water consumed | L4: Gas consumed (KG)
A5: =Gen!A11 -> 43862 | B5: ='Daily report Gen'!Z6 -> 37 | C5: =Gen!B11 -> 0.2338 | D5: =E5 -> 18 | E5: 18 | F5: =Gen!T9 -> 0 | G5: =Gen!S9 -> 0 | H5: =Gen!AJ11 -> 83.21 | I5: =SUM(G5:H5) -> 83.21 | J5: =Gen!C11 -> 30982.31 | K5: ='Water-Meter'!E6 -> 113 | L5: ='Lpg (2)'!G10 -> 94.512 | M5: =SUM(#REF!-#REF!) -> #REF!
A6: =Gen!A12 -> 43863 | B6: ='Daily report Gen'!Z7 -> 12 | C6: =Gen!B12 -> 0.234 | D6: =E6 -> 18 | E6: 18 | F6: =Gen!T10 -> 0 | G6: =Gen!S10 -> 0 | H6: =Gen!AJ12 -> 130.39 | I6: =SUM(G6:H6) -> 130.39 | J6: =Gen!C12 -> 29074.35 | K6: ='Water-Meter'!E7 -> 97 | L6: ='Lpg (2)'!G11 -> 104.632 | M6: =SUM(#REF!-#REF!) -> #REF!
A7: =Gen!A13 -> 43864 | B7: ='Daily report Gen'!Z8 -> 71 | C7: =Gen!B13 -> 0.104 | D7: =E7 -> 8 | E7: 8 | F7: =Gen!T11 -> 4580 | G7: =Gen!S11 -> 1824.75 | H7: =Gen!AJ13 -> 178.75 | I7: =SUM(G7:H7) -> 2003.5 | J7: =Gen!C13 -> 27141.11 | K7: ='Water-Meter'!E8 -> 107 | L7: ='Lpg (2)'!G12 -> -783.948 | M7: =SUM(#REF!-#REF!) -> #REF!
A8: =Gen!A14 -> 43865 | B8: ='Daily report Gen'!Z9 -> 43 | C8: =Gen!B14 -> 1 | D8: =E8 -> 77 | E8: 77 | F8: =Gen!T12 -> 4303 | G8: =Gen!S12 -> 1802.85 | H8: =Gen!AJ14 -> 89.65 | I8: =SUM(G8:H8) -> 1892.5 | J8: =Gen!C14 -> 43041.44 | K8: ='Water-Meter'!E9 -> 139 | L8: ='Lpg (2)'!G13 -> 112.728 | M8: =SUM(#REF!-#REF!) -> #REF!
A9: =Gen!A15 -> 43866 | B9: ='Daily report Gen'!Z10 -> 45 | C9: =Gen!B15 -> 1 | D9: =E9 -> 77 | E9: 77 | F9: =Gen!T13 -> 4514 | G9: =Gen!S13 -> 1920.92 | H9: =Gen!AJ15 -> 129.27 | I9: =SUM(G9:H9) -> 2050.19 | J9: =Gen!C15 -> 40592.67 | K9: ='Water-Meter'!E10 -> 141 | L9: ='Lpg (2)'!G14 -> 106.92 | M9: =SUM(#REF!-#REF!) -> #REF!
A10: =Gen!A16 -> 43867 | B10: ='Daily report Gen'!Z11 -> 45 | C10: =Gen!B16 -> 1 | D10: =E10 -> 77 | E10: 77 | F10: =Gen!T14 -> 5690 | G10: =Gen!S14 -> 2359.12 | H10: =Gen!AJ16 -> 187.64 | I10: =SUM(G10:H10) -> 2546.76 | J10: =Gen!C16 -> 38206.67 | K10: ='Water-Meter'!E11 -> 129 | L10: ='Lpg (2)'!G15 -> 102.124 | M10: =SUM(#REF!-#REF!) -> #REF!
A11: =Gen!A17 -> 43868 | B11: ='Daily report Gen'!Z12 -> 42 | C11: =Gen!B17 -> 1 | D11: =E11 -> 77 | E11: 77 | F11: =Gen!T15 -> 5866 | G11: =Gen!S15 -> 2256.73 | H11: =Gen!AJ17 -> 203.15 | I11: =SUM(G11:H11) -> 2459.88 | J11: =Gen!C17 -> 35527.52 | K11: ='Water-Meter'!E12 -> 129 | L11: ='Lpg (2)'!G16 -> 108.196 | M11: =SUM(#REF!-#REF!) -> #REF!
A12: =Gen!A18 -> 43869 | B12: ='Daily report Gen'!Z13 -> 46 | C12: =Gen!B18 -> 0.1429 | D12: =E12 -> 13 | E12: 13 | F12: =Gen!T16 -> 5875 | G12: =Gen!S16 -> 2491.51 | H12: =Gen!AJ18 -> 56.74 | I12: =SUM(G12:H12) -> 2548.25 | J12: =Gen!C18 -> 33079.63 | K12: ='Water-Meter'!E13 -> 128 | L12: ='Lpg (2)'!G17 -> 112.156 | M12: =SUM(#REF!-#REF!) -> #REF!
A13: =Gen!A19 -> 43870 | B13: ='Daily report Gen'!Z14 -> 41 | C13: =Gen!B19 -> 0.195 | D13: =E13 -> 16 | E13: 16 | F13: =Gen!T17 -> 5952 | G13: =Gen!S17 -> 2244.74 | H13: =Gen!AJ19 -> 162.68 | I13: =SUM(G13:H13) -> 2407.42 | J13: =Gen!C19 -> 45453.44 | K13: ='Water-Meter'!E14 -> 96 | L13: ='Lpg (2)'!G18 -> 103.444 | M13: =SUM(#REF!-#REF!) -> #REF!
A14: =Gen!A20 -> 43871 | B14: ='Daily report Gen'!Z15 -> -148058 | C14: =Gen!B20 -> 0.1818 | D14: =E14 -> 15 | E14: 15 | F14: =Gen!T18 -> 5988 | G14: =Gen!S18 -> 2569.45 | H14: =Gen!AJ20 -> 0 | I14: =SUM(G14:H14) -> 2569.45 | J14: =Gen!C20 -> 43250.94 | K14: ='Water-Meter'!E15 -> 0 | L14: ='Lpg (2)'!G19 -> -307317.16 | M14: =SUM(#REF!-#REF!) -> #REF!
A15: =Gen!A21 -> 43872 | B15: ='Daily report Gen'!Z16 -> 0 | C15: =Gen!B21 -> 0 | D15: =E15 -> 0 | F15: =Gen!T19 -> 5209 | G15: =Gen!S19 -> 2039.82 | H15: =Gen!AJ21 -> 0 | I15: =SUM(G15:H15) -> 2039.82 | J15: =Gen!C21 -> 43250.94 | K15: ='Water-Meter'!E16 -> 0 | L15: ='Lpg (2)'!G20 -> 0 | M15: =SUM(#REF!-#REF!) -> #REF!
A16: =Gen!A22 -> 43873 | B16: ='Daily report Gen'!Z17 -> 0 | C16: =Gen!B22 -> 0 | D16: =E16 -> 0 | F16: =Gen!T20 -> 0 | G16: =Gen!S20 -> 0 | H16: =Gen!AJ22 -> 0 | I16: =SUM(G16:H16) -> 0 | J16: =Gen!C22 -> 43250.94 | K16: ='Water-Meter'!E17 -> 0 | L16: ='Lpg (2)'!G21 -> 0 | M16: =SUM(#REF!-#REF!) -> #REF!
A17: =Gen!A23 -> 43874 | B17: ='Daily report Gen'!Z18 -> 0 | C17: =Gen!B23 -> 0 | D17: =E17 -> 0 | F17: =Gen!T21 -> 0 | G17: =Gen!S21 -> 0 | H17: =Gen!AJ23 -> 0 | I17: =SUM(G17:H17) -> 0 | J17: =Gen!C23 -> 43250.94 | K17: ='Water-Meter'!E18 -> 0 | L17: ='Lpg (2)'!G22 -> 0 | M17: =SUM(#REF!-#REF!) -> #REF!
A18: =Gen!A24 -> 43875 | B18: ='Daily report Gen'!Z19 -> 0 | C18: =Gen!B24 -> 0 | D18: =E18 -> 0 | F18: =Gen!T22 -> 0 | G18: =Gen!S22 -> 0 | H18: =Gen!AJ24 -> 0 | I18: =SUM(G18:H18) -> 0 | J18: =Gen!C24 -> 43250.94 | K18: ='Water-Meter'!E19 -> 0 | L18: ='Lpg (2)'!G23 -> 0 | M18: =SUM(#REF!-#REF!) -> #REF!
A19: =Gen!A25 -> 43876 | B19: ='Daily report Gen'!Z20 -> 0 | C19: =Gen!B25 -> 0 | D19: =E19 -> 0 | F19: =Gen!T23 -> 0 | G19: =Gen!S23 -> 0 | H19: =Gen!AJ25 -> 0 | I19: =SUM(G19:H19) -> 0 | J19: =Gen!C25 -> 43250.94 | K19: ='Water-Meter'!E20 -> 0 | L19: ='Lpg (2)'!G24 -> 0 | M19: =SUM(#REF!-#REF!) -> #REF!
A20: =Gen!A26 -> 43877 | B20: ='Daily report Gen'!Z21 -> 0 | C20: =Gen!B26 -> 0 | D20: =E20 -> 0 | F20: =Gen!T24 -> 0 | G20: =Gen!S24 -> 0 | H20: =Gen!AJ26 -> 0 | I20: =SUM(G20:H20) -> 0 | J20: =Gen!C26 -> 43250.94 | K20: ='Water-Meter'!E21 -> 0 | L20: ='Lpg (2)'!G25 -> 0 | M20: =SUM(#REF!-#REF!) -> #REF!
A21: =Gen!A27 -> 43878 | B21: ='Daily report Gen'!Z22 -> 0 | C21: =Gen!B27 -> 0 | D21: =E21 -> 0 | F21: =Gen!T25 -> 0 | G21: =Gen!S25 -> 0 | H21: =Gen!AJ27 -> 0 | I21: =SUM(G21:H21) -> 0 | J21: =Gen!C27 -> 43250.94 | K21: ='Water-Meter'!E22 -> 0 | L21: ='Lpg (2)'!G26 -> 0 | M21: =SUM(#REF!-#REF!) -> #REF!
A22: =Gen!A28 -> 43879 | B22: ='Daily report Gen'!Z23 -> 0 | C22: =Gen!B28 -> 0 | D22: =E22 -> 0 | F22: =Gen!T26 -> 0 | G22: =Gen!S26 -> 0 | H22: =Gen!AJ28 -> 0 | I22: =SUM(G22:H22) -> 0 | J22: =Gen!C28 -> 43250.94 | K22: ='Water-Meter'!E23 -> 0 | L22: ='Lpg (2)'!G27 -> 0 | M22: =SUM(#REF!-#REF!) -> #REF!
A23: =Gen!A29 -> 43880 | B23: ='Daily report Gen'!Z24 -> 0 | C23: =Gen!B29 -> 0 | D23: =E23 -> 0 | F23: =Gen!T27 -> 0 | G23: =Gen!S27 -> 0 | H23: =Gen!AJ29 -> 0 | I23: =SUM(G23:H23) -> 0 | J23: =Gen!C29 -> 43250.94 | K23: ='Water-Meter'!E24 -> 0 | L23: ='Lpg (2)'!G28 -> 0 | M23: =SUM(#REF!-#REF!) -> #REF!
A24: =Gen!A30 -> 43881 | B24: ='Daily report Gen'!Z25 -> 0 | C24: =Gen!B30 -> 0 | D24: =E24 -> 0 | F24: =Gen!T28 -> 0 | G24: =Gen!S28 -> 0 | H24: =Gen!AJ30 -> 0 | I24: =SUM(G24:H24) -> 0 | J24: =Gen!C30 -> 43250.94 | K24: ='Water-Meter'!E25 -> 0 | L24: ='Lpg (2)'!G29 -> 0 | M24: =SUM(#REF!-#REF!) -> #REF!
A25: =Gen!A31 -> 43882 | B25: ='Daily report Gen'!Z26 -> 0 | C25: =Gen!B31 -> 0 | D25: =E25 -> 0 | F25: =Gen!T29 -> 0 | G25: =Gen!S29 -> 0 | H25: =Gen!AJ31 -> 0 | I25: =SUM(G25:H25) -> 0 | J25: =Gen!C31 -> 43250.94 | K25: ='Water-Meter'!E26 -> 0 | L25: ='Lpg (2)'!G30 -> 0 | M25: =SUM(#REF!-#REF!) -> #REF!
A26: =Gen!A32 -> 43883 | B26: ='Daily report Gen'!Z27 -> 0 | C26: =Gen!B32 -> 0 | D26: =E26 -> 0 | F26: =Gen!T30 -> 0 | G26: =Gen!S30 -> 0 | H26: =Gen!AJ32 -> 0 | I26: =SUM(G26:H26) -> 0 | J26: =Gen!C32 -> 43250.94 | K26: ='Water-Meter'!E27 -> 0 | L26: ='Lpg (2)'!G31 -> 0 | M26: =SUM(#REF!-#REF!) -> #REF!
... A35: =Gen!A41 -> 43892 | B35: ='Daily report Gen'!Z36 -> 0 | C35: =Gen!B41 -> 0 | D35: =E35 -> 0 | F35: =Gen!T39 -> 0 | G35: =Gen!S39 -> 0 | H35: =Gen!AJ41 -> 0 | I35: =SUM(G35:H35) -> 0 | J35: =Gen!C41 -> 43250.94 | K35: ='Water-Meter'!E36 -> 0 | L35: ='Lpg (2)'!G40 -> 0 | M35: =SUM(#REF!-#REF!) -> #REF!
A36: =Gen!A42 -> 43893 | B36: ='Daily report Gen'!Z37 -> 0 | C36: =Gen!B42 -> 0 | D36: =E36 -> 0 | F36: =Gen!T40 -> 0 | G36: =Gen!S40 -> 0 | H36: =Gen!AJ42 -> 0 | I36: =SUM(G36:H36) -> 0 | J36: =Gen!C42 -> 43250.94 | K36: ='Water-Meter'!E37 -> 0 | L36: ='Lpg (2)'!G41 -> 0

Sheet Daily report Gen
A1: 43862
K3: GENERATOR NO.1 | N3: GENERATOR NO.2 | Q3: GENERATOR NO.4 | T3: GENERATOR NO.5 | W3: GENERATOR NO.6
A4: DATE | B4: OCC% | C4: D-TANK A | D4: D-TANK B | E4: DELIVERY DATE | F4: DELIVERY | G4: ISSUED-VEHICLE | H4: OTHERS | I4: M-R LV PANEL 1. KW-HR | J4: M-R LV PANEL 2. KW-HR | K4: OPEN HRS READING | L4: CLOSE HRS READING | M4: RUNNING HRS | N4: OPEN HRS READING | O4: CLOSE HRS READING | P4: RUNNING HRS | Q4: OPEN HRS READING | R4: CLOSE HRS READING | S4: RUNNING HRS | T4: OPEN HRS READING | U4: CLOSE HRS READING | V4: RUNNING HRS | W4: OPEN HRS READING | X4: CLOSE HRS READING | Y4: RUNNING HRS | Z4: TOTAL RUNNING HRS | AA4: MAX KW | AB4: MIN-KW | AC4: TOTAL DIESEL CONS.
L5: 33915 | O5: 28805 | R5: 34173 | U5: 31560 | X5: 19223
A6: =Gen!A11 -> 43862 | B6: =Gen!B11 -> 0.2338 | C6: 20133.2 | D6: 10849.11 | G6: 83.21 | I6: 30102.1 | J6: 19855.8 | K6: =L5 -> 33915 | L6: 33918 | M6: =L6-K6 -> 3 | N6: =O5 -> 28805 | O6: 28812 | P6: =O6-N6 -> 7 | Q6: =R5 -> 34173 | R6: 34180 | S6: =R6-Q6 -> 7 | T6: =U5 -> 31560 | U6: 31571 | V6: =U6-T6 -> 11 | W6: =X5 -> 19223 | X6: 19232 | Y6: =X6-W6 -> 9 | Z6: =Y6+V6+S6+P6+M6 -> 37 | AA6: 383 | AB6: 181 | AC6: =Gen!S11 -> 1824.75
A7: =Gen!A12 -> 43863 | B7: =Gen!B12 -> 0.234 | C7: 20133.2 | D7: 8941.15 | G7: 130.39 | I7: 30109.6 | J7: 19860.7 | K7: =L6 -> 33918 | L7: 33926 | M7: =L7-K7 -> 8 | N7: =O6 -> 28812 | O7: 28821 | P7: =O7-N7 -> 9 | Q7: =R6 -> 34180 | R7: 34188 | S7: =R7-Q7 -> 8 | T7: =U6 -> 31571 | U7: 31578 | V7: =U7-T7 -> 7 | W7: =X6 -> 19232 | X7: 19212 | Y7: =X7-W7 -> -20 | Z7: =Y7+V7+S7+P7+M7 -> 12 | AA7: 389 | AB7: 192 | AC7: =Gen!S12 -> 1802.85
A8: =Gen!A13 -> 43864 | B8: =Gen!B13 -> 0.104 | C8: 20133.2 | D8: 6841.48 | G8: 178.75 | I8: 30117.6 | J8: 19865.7 | K8: =L7 -> 33926 | L8: 33932 | M8: =L8-K8 -> 6 | N8: =O7 -> 28821 | O8: 28831 | P8: =O8-N8 -> 10 | Q8: =R7 -> 34188 | R8: 34194 | S8: =R8-Q8 -> 6 | T8: =U7 -> 31578 | U8: 31586 | V8: =U8-T8 -> 8 | W8: =X7 -> 19212 | X8: 19253 | Y8: =X8-W8 -> 41 | Z8: =Y8+V8+S8+P8+M8 -> 71 | AA8: 402 | AB8: 179 | AC8: =Gen!S13 -> 1920.92
A9: =Gen!A14 -> 43865 | B9: =Gen!B14 -> 1 | C9: 20133.2 | D9: 22908.24 | F9: 18000 | G9: 89.65 | I9: 30127.5 | J9: 19872.4 | K9: =L8 -> 33932 | L9: 33941 | M9: =L9-K9 -> 9 | N9: =O8 -> 28831 | O9: 28840 | P9: =O9-N9 -> 9 | Q9: =R8 -> 34194 | R9: 34203 | S9: =R9-Q9 -> 9 | T9: =U8 -> 31586 | U9: 31591 | V9: =U9-T9 -> 5 | W9: =X8 -> 19253 | X9: 19264 | Y9: =X9-W9 -> 11 | Z9: =Y9+V9+S9+P9+M9 -> 43 | AA9: 498 | AB9: 230 | AC9: =Gen!S14 -> 2359.12
A10: =Gen!A15 -> 43866 | B10: =Gen!B15 -> 1 | C10: 20133.2 | D10: 20459.47 | G10: 129.27 | I10: 30137 | J10: 19879.6 | K10: =L9 -> 33941 | L10: 33949 | M10: =L10-K10 -> 8 | N10: =O9 -> 28840 | O10: 28850 | P10: =O10-N10 -> 10 | Q10: =R9 -> 34203 | R10: 34213 | S10: =R10-Q10 -> 10 | T10: =U9 -> 31591 | U10: 31600 | V10: =U10-T10 -> 9 | W10: =X9 -> 19264 | X10: 19272 | Y10: =X10-W10 -> 8 | Z10: =Y10+V10+S10+P10+M10 -> 45 | AA10: 595 | AB10: 240 | AC10: =Gen!S15 -> 2256.73
A11: =Gen!A16 -> 43867 | B11: =Gen!B16 -> 1 | C11: 20133.2 | D11: 18073.47 | G11: 187.64 | I11: 30146.9 | J11: 19886.5 | K11: =L10 -> 33949 | L11: 33954 | M11: =L11-K11 -> 5 | N11: =O10 -> 28850 | O11: 28864 | P11: =O11-N11 -> 14 | Q11: =R10 -> 34213 | R11: 34226 | S11: =R11-Q11 -> 13 | T11: =U10 -> 31600 | U11: 31606 | V11: =U11-T11 -> 6 | W11: =X10 -> 19272 | X11: 19279 | Y11: =X11-W11 -> 7 | Z11: =Y11+V11+S11+P11+M11 -> 45 | AA11: 586 | AB11: 240 | AC11: =Gen!S16 -> 2491.51
A12: =Gen!A17 -> 43868 | B12: =Gen!B17 -> 1 | C12: 20133.2 | D12: 15394.32 | G12: 203.15 | I12: 30157.3 | J12: 19893.3 | K12: =L11 -> 33954 | L12: 33962 | M12: =L12-K12 -> 8 | N12: =O11 -> 28864 | O12: 28874 | P12: =O12-N12 -> 10 | Q12: =R11 -> 34226 | R12: 34237 | S12: =R12-Q12 -> 11 | T12: =U11 -> 31606 | U12: 31612 | V12: =U12-T12 -> 6 | W12: =X11 -> 19279 | X12: 19286 | Y12: =X12-W12 -> 7 | Z12: =Y12+V12+S12+P12+M12 -> 42 | AC12: =Gen!S17 -> 2244.74
A13: =Gen!A18 -> 43869 | B13: =Gen!B18 -> 0.1429 | C13: 20133.2 | D13: 12946.43 | G13: 56.74 | I13: 30167.6 | J13: 19900.2 | K13: =L12 -> 33962 | L13: 33969 | M13: =L13-K13 -> 7 | N13: =O12 -> 28874 | O13: 28888 | P13: =O13-N13 -> 14 | Q13: =R12 -> 34237 | R13: 34250 | S13: =R13-Q13 -> 13 | T13: =U12 -> 31612 | U13: 31620 | V13: =U13-T13 -> 8 | W13: =X12 -> 19286 | X13: 19290 | Y13: =X13-W13 -> 4 | Z13: =Y13+V13+S13+P13+M13 -> 46 | AA13: 576 | AB13: 209 | AC13: =Gen!S18 -> 2569.45
A14: =Gen!A19 -> 43870 | B14: =Gen!B19 -> 0.195 | C14: 20133.2 | D14: 10320.24 | G14: 162.68 | I14: 30176.4 | J14: 19906.1 | K14: =L13 -> 33969 | L14: 33976 | M14: =L14-K14 -> 7 | N14: =O13 -> 28888 | O14: 28896 | P14: =O14-N14 -> 8 | Q14: =R13 -> 34250 | R14: 34261 | S14: =R14-Q14 -> 11 | T14: =U13 -> 31620 | U14: 31625 | V14: =U14-T14 -> 5 | W14: =X13 -> 19290 | X14: 19300 | Y14: =X14-W14 -> 10 | Z14: =Y14+V14+S14+P14+M14 -> 41 | AA14: 491 | AB14: 213 | AC14: =Gen!S19 -> 2039.82
A15: =Gen!A20 -> 43871 | B15: =Gen!B20 -> 0.1818 | C15: 20133.2 | D15: 23117.74 | K15: =L14 -> 33976 | M15: =L15-K15 -> -33976 | N15: =O14 -> 28896 | P15: =O15-N15 -> -28896 | Q15: =R14 -> 34261 | S15: =R15-Q15 -> -34261 | T15: =U14 -> 31625 | V15: =U15-T15 -> -31625 | W15: =X14 -> 19300 | Y15: =X15-W15 -> -19300 | Z15: =Y15+V15+S15+P15+M15 -> -148058 | AC15: =Gen!S20 -> 0
A16: =Gen!A21 -> 43872 | B16: =Gen!B21 -> 0 | K16: =L15 -> 0 | M16: =L16-K16 -> 0 | N16: =O15 -> 0 | P16: =O16-N16 -> 0 | Q16: =R15 -> 0 | S16: =R16-Q16 -> 0 | T16: =U15 -> 0 | V16: =U16-T16 -> 0 | W16: =X15 -> 0 | Y16: =X16-W16 -> 0 | Z16: =Y16+V16+S16+P16+M16 -> 0 | AC16: =Gen!S21 -> 0
A17: =Gen!A22 -> 43873 | B17: =Gen!B22 -> 0 | K17: =L16 -> 0 | M17: =L17-K17 -> 0 | N17: =O16 -> 0 | P17: =O17-N17 -> 0 | Q17: =R16 -> 0 | S17: =R17-Q17 -> 0 | T17: =U16 -> 0 | V17: =U17-T17 -> 0 | W17: =X16 -> 0 | Y17: =X17-W17 -> 0 | Z17: =Y17+V17+S17+P17+M17 -> 0 | AC17: =Gen!S22 -> 0
A18: =Gen!A23 -> 43874 | B18: =Gen!B23 -> 0 | K18: =L17 -> 0 | M18: =L18-K18 -> 0 | N18: =O17 -> 0 | P18: =O18-N18 -> 0 | Q18: =R17 -> 0 | S18: =R18-Q18 -> 0 | T18: =U17 -> 0 | V18: =U18-T18 -> 0 | W18: =X17 -> 0 | Y18: =X18-W18 -> 0 | Z18: =Y18+V18+S18+P18+M18 -> 0 | AC18: =Gen!S23 -> 0
A19: =Gen!A24 -> 43875 | B19: =Gen!B24 -> 0 | K19: =L18 -> 0 | M19: =L19-K19 -> 0 | N19: =O18 -> 0 | P19: =O19-N19 -> 0 | Q19: =R18 -> 0 | S19: =R19-Q19 -> 0 | T19: =U18 -> 0 | V19: =U19-T19 -> 0 | W19: =X18 -> 0 | Y19: =X19-W19 -> 0 | Z19: =Y19+V19+S19+P19+M19 -> 0 | AC19: =Gen!S24 -> 0
A20: =Gen!A25 -> 43876 | B20: =Gen!B25 -> 0 | K20: =L19 -> 0 | M20: =L20-K20 -> 0 | N20: =O19 -> 0 | P20: =O20-N20 -> 0 | Q20: =R19 -> 0 | S20: =R20-Q20 -> 0 | T20: =U19 -> 0 | V20: =U20-T20 -> 0 | W20: =X19 -> 0 | Y20: =X20-W20 -> 0 | Z20: =Y20+V20+S20+P20+M20 -> 0 | AC20: =Gen!S25 -> 0
A21: =Gen!A26 -> 43877 | B21: =Gen!B26 -> 0 | K21: =L20 -> 0 | M21: =L21-K21 -> 0 | N21: =O20 -> 0 | P21: =O21-N21 -> 0 | Q21: =R20 -> 0 | S21: =R21-Q21 -> 0 | T21: =U20 -> 0 | V21: =U21-T21 -> 0 | W21: =X20 -> 0 | Y21: =X21-W21 -> 0 | Z21: =Y21+V21+S21+P21+M21 -> 0 | AC21: =Gen!S26 -> 0
A22: =Gen!A27 -> 43878 | B22: =Gen!B27 -> 0 | K22: =L21 -> 0 | M22: =L22-K22 -> 0 | N22: =O21 -> 0 | P22: =O22-N22 -> 0 | Q22: =R21 -> 0 | S22: =R22-Q22 -> 0 | T22: =U21 -> 0 | V22: =U22-T22 -> 0 | W22: =X21 -> 0 | Y22: =X22-W22 -> 0 | Z22: =Y22+V22+S22+P22+M22 -> 0 | AC22: =Gen!S27 -> 0
A23: =Gen!A28 -> 43879 | B23: =Gen!B28 -> 0 | K23: =L22 -> 0 | M23: =L23-K23 -> 0 | N23: =O22 -> 0 | P23: =O23-N23 -> 0 | Q23: =R22 -> 0 | S23: =R23-Q23 -> 0 | T23: =U22 -> 0 | V23: =U23-T23 -> 0 | W23: =X22 -> 0 | Y23: =X23-W23 -> 0 | Z23: =Y23+V23+S23+P23+M23 -> 0 | AC23: =Gen!S28 -> 0
A24: =Gen!A29 -> 43880 | B24: =Gen!B29 -> 0 | K24: =L23 -> 0 | M24: =L24-K24 -> 0 | N24: =O23 -> 0 | P24: =O24-N24 -> 0 | Q24: =R23 -> 0 | S24: =R24-Q24 -> 0 | T24: =U23 -> 0 | V24: =U24-T24 -> 0 | W24: =X23 -> 0 | Y24: =X24-W24 -> 0 | Z24: =Y24+V24+S24+P24+M24 -> 0 | AC24: =Gen!S29 -> 0
A25: =Gen!A30 -> 43881 | B25: =Gen!B30 -> 0 | K25: =L24 -> 0 | M25: =L25-K25 -> 0 | N25: =O24 -> 0 | P25: =O25-N25 -> 0 | Q25: =R24 -> 0 | S25: =R25-Q25 -> 0 | T25: =U24 -> 0 | V25: =U25-T25 -> 0 | W25: =X24 -> 0 | Y25: =X25-W25 -> 0 | Z25: =Y25+V25+S25+P25+M25 -> 0 | AC25: =Gen!S30 -> 0
A26: =Gen!A31 -> 43882 | B26: =Gen!B31 -> 0 | K26: =L25 -> 0 | M26: =L26-K26 -> 0 | N26: =O25 -> 0 | P26: =O26-N26 -> 0 | Q26: =R25 -> 0 | S26: =R26-Q26 -> 0 | T26: =U25 -> 0 | V26: =U26-T26 -> 0 | W26: =X25 -> 0 | Y26: =X26-W26 -> 0 | Z26: =Y26+V26+S26+P26+M26 -> 0 | AC26: =Gen!S31 -> 0
A27: =Gen!A32 -> 43883 | B27: =Gen!B32 -> 0 | K27: =L26 -> 0 | M27: =L27-K27 -> 0 | N27: =O26 -> 0 | P27: =O27-N27 -> 0 | Q27: =R26 -> 0 | S27: =R27-Q27 -> 0 | T27: =U26 -> 0 | V27: =U27-T27 -> 0 | W27: =X26 -> 0 | Y27: =X27-W27 -> 0 | Z27: =Y27+V27+S27+P27+M27 -> 0 | AC27: =Gen!S32 -> 0
... A37: =Gen!A42 -> 43893 | B37: =Gen!B42 -> 0 | K37: =L36 -> 0 | M37: =L37-K37 -> 0 | N37: =O36 -> 0 | P37: =O37-N37 -> 0 | Q37: =R36 -> 0 | S37: =R37-Q37 -> 0 | T37: =U36 -> 0 | V37: =U37-T37 -> 0 | W37: =X36 -> 0 | Y37: =X37-W37 -> 0 | Z37: =Y37+V37+S37+P37+M37 -> 0 | AC37: =Gen!S42 -> 0

Sheet Gen
D2: HLP REPORT FEBRUARY 2020
F6: BILILA LODGE INVESTMENT LIMITED | V6: 1 | W6: 2 | X6: 3 | Y6: 4 | Z6: 5 | AA6: 6 | AB6: 7 | AC6: 8 | AD6: 9 | AE6: 10 | AF6: 11
F7: Diesel Consumed by 500KVA Generator | M7: 500KVA Generator KWh | V7: Safari-STAFF | W7: Safari-STAFF | X7: Lc/swg/gust | Y7: Eng pikcup | Z7: VIP Safari Car | AA7: GX Guest | AB7: GX Guest | AC7: T/Hillux/pur | AD7: TATA | AE7: MAN | AF7: F/Truck | AG7: Incenerator | AH7: A&K | AI7: OTHER | AJ7: TOTAL CO
A8: Date | B8: Occupenccy % | C8: OPENING | D8: Received | E8: Schedule delivery | F8: Company | G8: 1 | H8: 2 | I8: 3 | J8: 4 | K8: 5 | L8: 6 | M8: 1 | N8: 2 | O8: 3 | P8: 4 | Q8: 5 | R8: 6 | S8: Total Diseal Consumed | T8: Total Kwh generated | U8: Average Diesel/Kwh | V8: T 128 AXJ | W8: T 134 AXJ | X8: T 499 AXG | Y8: T 217 CHV | Z8: T 214 CHV | AA8: T 139 AXE | AB8: T 242 AXN - SABASABA | AC8: T 476 AWZ | AD8: T 226 AUQ | AE8: T 308 CLD | AF8: T 852 AWU | AG8: Machine ENG | AH8: Vehicle | AI8: Vehicle | AR8: Total Diseal Consumed Gen & Vehicle | AS8: Total cost /Day (TSH) | AT8: BALANCE
C9: 30982.31 | S9: =SUM(F9:L9) -> 0 | T9: =SUM(M9:R9) -> 0 | AR9: =SUM(AJ9+S9) -> 0 | AT9: 38784.7
S10: =SUM(F10:L10) -> 0 | T10: =SUM(M10:R10) -> 0 | U10: =SUM(N10:S10) -> 0 | AJ10: =SUM(V10:AI10) -> 0 | AR10: =SUM(AJ10+S10) -> 0
A11: 43862 | B11: 0.2338 | C11: =SUM(C9+D11) -> 30982.31 | G11: 221.91 | H11: 313.61 | J11: 407.27 | K11: 409.57 | L11: 472.39 | M11: 250 | N11: 763 | P11: 1094 | Q11: 1324 | R11: 1149 | S11: =SUM(F11:L11) -> 1824.75 | T11: =SUM(M11:R11) -> 4580 | U11: =S11/T11 -> 0.39841703 | Z11: 83.21 | AJ11: =SUM(V11:AI11) -> 83.21 | AR11: =SUM(AJ11+S11) -> 1907.96 | AS11: =AR11*AU11 -> 0 | AT11: =C11 -> 30982.31
A12: 43863 | B12: 0.234 | C12: =SUM(C11-AR11+D12) -> 29074.35 | E12: 18000 | F12: PUMA | G12: 390.28 | H12: 322.89 | J12: 352.73 | K12: 308.88 | L12: 428.07 | M12: 812 | N12: 795 | P12: 807 | Q12: 907 | R12: 982 | S12: =SUM(F12:L12) -> 1802.85 | T12: =SUM(M12:R12) -> 4303 | U12: =S12/T12 -> 0.41897513 | Z12: 47.65 | AC12: 41.74 | AH12: 41 | AJ12: =SUM(V12:AI12) -> 130.39 | AR12: =SUM(AJ12+S12) -> 1933.24 | AS12: =AR12*AU12 -> 0 | AT12: =C12 -> 29074.35
A13: 43864 | B13: 0.104 | C13: =SUM(C12-AR12+D13) -> 27141.11 | G13: 285.8 | H13: 447.48 | J13: 287.73 | K13: 355.52 | L13: 544.39 | M13: 764 | N13: 1072 | P13: 699 | Q13: 809 | R13: 1170 | S13: =SUM(F13:L13) -> 1920.92 | T13: =SUM(M13:R13) -> 4514 | U13: =S13/T13 -> 0.42554719 | W13: 57.39 | X13: 10.88 | Y13: 100.52 | Z13: 9.96 | AJ13: =SUM(V13:AI13) -> 178.75 | AR13: =SUM(AJ13+S13) -> 2099.67 | AS13: =AR13*AU13 -> 0 | AT13: =C13 -> 27141.11
A14: 43865 | B14: 1 | C14: =SUM(C13-AR13+D14) -> 43041.44 | D14: 18000 | G14: 529.7 | H14: 437.57 | J14: 508.68 | K14: 298.02 | L14: 585.15 | M14: 1298 | N14: 794 | P14: 1220 | Q14: 1128 | R14: 1250 | S14: =SUM(F14:L14) -> 2359.12 | T14: =SUM(M14:R14) -> 5690 | U14: =S14/T14 -> 0.41460808 | Z14: 13.58 | AC14: 16.82 | AF14: 59.25 | AJ14: =SUM(V14:AI14) -> 89.65 | AR14: =SUM(AJ14+S14) -> 2448.77 | AS14: =AR14*AU14 -> 0 | AT14: =C14 -> 43041.44
A15: 43866 | B15: 1 | C15: =SUM(C14-AR14+D15) -> 40592.67 | G15: 458.42 | H15: 448.4 | J15: 406.69 | K15: 467.7 | L15: 475.52 | M15: 1182 | N15: 1270 | P15: 1121 | Q15: 1131 | R15: 1162 | S15: =SUM(F15:L15) -> 2256.73 | T15: =SUM(M15:R15) -> 5866 | U15: =S15/T15 -> 0.3847136 | W15: 38.51 | X15: 21.51 | Z15: 69.25 | AJ15: =SUM(V15:AI15) -> 129.27 | AR15: =SUM(AJ15+S15) -> 2386 | AS15: =AR15*AU15 -> 0 | AT15: =C15 -> 40592.67
A16: 43867 | B16: 1 | C16: =SUM(C15-AR15+D16) -> 38206.67 | G16: 217.14 | H16: 797.5 | J16: 763.55 | K16: 341.26 | L16: 372.06 | M16: 494 | N16: 1835 | P16: 1734 | Q16: 867 | R16: 945 | S16: =SUM(F16:L16) -> 2491.51 | T16: =SUM(M16:R16) -> 5875 | U16: =S16/T16 -> 0.42408681 | W16: 68.62 | X16: 28.64 | Y16: 90.38 | AJ16: =SUM(V16:AI16) -> 187.64 | AR16: =SUM(AJ16+S16) -> 2679.15 | AS16: =AR16*AU16 -> 0 | AT16: =C16 -> 38206.67
A17: 43868 | B17: 1 | C17: =SUM(C16-AR16+D17) -> 35527.52 | G17: 469.45 | H17: 484.11 | J17: 353.56 | K17: 349.16 | L17: 588.46 | M17: 1008 | N17: 1512 | P17: 1572 | Q17: 952 | R17: 908 | S17: =SUM(F17:L17) -> 2244.74 | T17: =SUM(M17:R17) -> 5952 | U17: =S17/T17 -> 0.37714046 | X17: 22.75 | Z17: 47.4 | AH17: 73 | AI17: 60 | AJ17: =SUM(V17:AI17) -> 203.15 | AR17: =SUM(AJ17+S17) -> 2447.89 | AS17: =AR17*AU17 -> 0 | AT17: =C17 -> 35527.52
A18: 43869 | B18: 0.1429 | C18: =SUM(C17-AR17+D18) -> 33079.63 | G18: 606.39 | H18: 666.11 | J18: 492.65 | K18: 328.68 | L18: 475.62 | M18: 932 | N18: 1690 | P18: 1554 | Q18: 956 | R18: 856 | S18: =SUM(F18:L18) -> 2569.45 | T18: =SUM(M18:R18) -> 5988 | U18: =S18/T18 -> 0.42909987 | X18: 20.14 | Z18: 36.6 | AJ18: =SUM(V18:AI18) -> 56.74 | AR18: =SUM(AJ18+S18) -> 2626.19 | AS18: =AR18*AU18 -> 0 | AT18: =C18 -> 33079.63
A19: 43870 | B19: 0.195 | C19: =SUM(C18-AR18+D19) -> 45453.44 | D19: 15000 | E19: 15000 | F19: RAHA | G19: 401.93 | H19: 411.39 | J19: 491.94 | K19: 334.47 | L19: 400.09 | M19: 806 | N19: 1375 | P19: 1366 | Q19: 874 | R19: 788 | S19: =SUM(F19:L19) -> 2039.82 | T19: =SUM(M19:R19) -> 5209 | U19: =S19/T19 -> 0.39159532 | W19: 31.95 | X19: 43.41 | Y19: 26.48 | Z19: 26.24 | AC19: 34.6 | AJ19: =SUM(V19:AI19) -> 162.68 | AR19: =SUM(AJ19+S19) -> 2202.5 | AS19: =AR19*AU19 -> 0 | AT19: =C19 -> 45453.44
A20: 43871 | B20: 0.1818 | C20: =SUM(C19-AR19+D20) -> 43250.94 | S20: =SUM(F20:L20) -> 0 | T20: =SUM(M20:R20) -> 0 | U20: =S20/T20 -> #DIV/0! | AJ20: =SUM(V20:AI20) -> 0 | AR20: =SUM(AJ20+S20) -> 0 | AS20: =AR20*AU20 -> 0 | AT20: =C20 -> 43250.94
A21: 43872 | C21: =SUM(C20-AR20+D21) -> 43250.94 | S21: =SUM(F21:L21) -> 0 | T21: =SUM(M21:R21) -> 0 | U21: =S21/T21 -> #DIV/0! | AJ21: =SUM(V21:AI21) -> 0 | AR21: =SUM(AJ21+S21) -> 0 | AS21: =AR21*AU21 -> 0 | AT21: =C21 -> 43250.94
A22: 43873 | C22: =SUM(C21-AR21+D22) -> 43250.94 | S22: =SUM(F22:L22) -> 0 | T22: =SUM(M22:R22) -> 0 | U22: =S22/T22 -> #DIV/0! | AJ22: =SUM(V22:AI22) -> 0 | AR22: =SUM(AJ22+S22) -> 0 | AS22: =AR22*AU22 -> 0 | AT22: =C22 -> 43250.94
A23: 43874 | C23: =SUM(C22-AR22+D23) -> 43250.94 | S23: =SUM(F23:L23) -> 0 | T23: =SUM(M23:R23) -> 0 | U23: =S23/T23 -> #DIV/0! | AJ23: =SUM(V23:AI23) -> 0 | AR23: =SUM(AJ23+S23) -> 0 | AS23: =AR23*AU23 -> 0 | AT23: =C23 -> 43250.94
A24: 43875 | C24: =SUM(C23-AR23+D24) -> 43250.94 | S24: =SUM(F24:L24) -> 0 | T24: =SUM(M24:R24) -> 0 | U24: =S24/T24 -> #DIV/0! | AJ24: =SUM(V24:AI24) -> 0 | AR24: =SUM(AJ24+S24) -> 0 | AS24: =AR24*AU24 -> 0 | AT24: =C24 -> 43250.94
A25: 43876 | C25: =SUM(C24-AR24+D25) -> 43250.94 | S25: =SUM(F25:L25) -> 0 | T25: =SUM(M25:R25) -> 0 | U25: =S25/T25 -> #DIV/0! | AJ25: =SUM(V25:AI25) -> 0 | AR25: =SUM(AJ25+S25) -> 0 | AS25: =AR25*AU25 -> 0 | AT25: =C25 -> 43250.94
A26: 43877 | C26: =SUM(C25-AR25+D26) -> 43250.94 | E26: 18000 | F26: PUMA | S26: =SUM(F26:L26) -> 0 | T26: =SUM(M26:R26) -> 0 | U26: =S26/T26 -> #DIV/0! | AJ26: =SUM(V26:AI26) -> 0 | AR26: =SUM(AJ26+S26) -> 0 | AS26: =AR26*AU26 -> 0 | AT26: =C26 -> 43250.94
A27: 43878 | C27: =SUM(C26-AR26+D27) -> 43250.94 | S27: =SUM(F27:L27) -> 0 | T27: =SUM(M27:R27) -> 0 | U27: =S27/T27 -> #DIV/0! | AJ27: =SUM(V27:AI27) -> 0 | AR27: =SUM(AJ27+S27) -> 0 | AS27: =AR27*AU27 -> 0 | AT27: =C27 -> 43250.94
A28: 43879 | C28: =SUM(C27-AR27+D28) -> 43250.94 | S28: =SUM(F28:L28) -> 0 | T28: =SUM(M28:R28) -> 0 | U28: =S28/T28 -> #DIV/0! | AJ28: =SUM(V28:AI28) -> 0 | AR28: =SUM(AJ28+S28) -> 0 | AS28: =AR28*AU28 -> 0 | AT28: =C28 -> 43250.94
A29: 43880 | C29: =SUM(C28-AR28+D29) -> 43250.94 | S29: =SUM(F29:L29) -> 0 | T29: =SUM(M29:R29) -> 0 | U29: =S29/T29 -> #DIV/0! | AJ29: =SUM(V29:AI29) -> 0 | AR29: =SUM(AJ29+S29) -> 0 | AS29: =AR29*AU29 -> 0 | AT29: =C29 -> 43250.94
A30: 43881 | C30: =SUM(C29-AR29+D30) -> 43250.94 | S30: =SUM(F30:L30) -> 0 | T30: =SUM(M30:R30) -> 0 | U30: =S30/T30 -> #DIV/0! | AJ30: =SUM(V30:AI30) -> 0 | AR30: =SUM(AJ30+S30) -> 0 | AS30: =AR30*AU30 -> 0 | AT30: =C30 -> 43250.94
A31: 43882 | C31: =SUM(C30-AR30+D31) -> 43250.94 | S31: =SUM(F31:L31) -> 0 | T31: =SUM(M31:R31) -> 0 | U31: =S31/T31 -> #DIV/0! | AJ31: =SUM(V31:AI31) -> 0 | AR31: =SUM(AJ31+S31) -> 0 | AS31: =AR31*AU31 -> 0 | AT31: =C31 -> 43250.94
A32: 43883 | C32: =SUM(C31-AR31+D32) -> 43250.94 | S32: =SUM(F32:L32) -> 0 | T32: =SUM(M32:R32) -> 0 | U32: =S32/T32 -> #DIV/0! | AJ32: =SUM(V32:AI32) -> 0 | AR32: =SUM(AJ32+S32) -> 0 | AS32: =AR32*AU32 -> 0 | AT32: =C32 -> 43250.94
A33: 43884 | C33: =SUM(C32-AR32+D33) -> 43250.94 | S33: =SUM(F33:L33) -> 0 | T33: =SUM(M33:R33) -> 0 | U33: =S33/T33 -> #DIV/0! | AJ33: =SUM(V33:AI33) -> 0 | AR33: =SUM(AJ33+S33) -> 0 | AS33: =AR33*AU33 -> 0 | AT33: =C33 -> 43250.94 | AU33: =SUM(AU32) -> 0
A34: 43885 | C34: =SUM(C33-AR33+D34) -> 43250.94 | S34: =SUM(F34:L34) -> 0 | T34: =SUM(M34:R34) -> 0 | U34: =S34/T34 -> #DIV/0! | AJ34: =SUM(V34:AI34) -> 0 | AR34: =SUM(AJ34+S34) -> 0 | AS34: =AR34*AU34 -> 0 | AT34: =C34 -> 43250.94 | AU34: =SUM(AU33) -> 0
A35: 43886 | C35: =SUM(C34-AR34+D35) -> 43250.94 | E35: 15000 | F35: RAHA | S35: =SUM(F35:L35) -> 0 | T35: =SUM(M35:R35) -> 0 | U35: =S35/T35 -> #DIV/0! | AJ35: =SUM(V35:AI35) -> 0 | AR35: =SUM(AJ35+S35) -> 0 | AS35: =AR35*AU35 -> 0 | AT35: =C35 -> 43250.94 | AU35: =SUM(AU34) -> 0
A36: 43887 | C36: =SUM(C35-AR35+D36) -> 43250.94 | S36: =SUM(F36:L36) -> 0 | T36: =SUM(M36:R36) -> 0 | U36: =S36/T36 -> #DIV/0! | AJ36: =SUM(V36:AI36) -> 0 | AR36: =SUM(AJ36+S36) -> 0 | AS36: =AR36*AU36 -> 0 | AT36: =C36 -> 43250.94 | AU36: =SUM(AU35) -> 0
A37: 43888 | C37: =SUM(C36-AR36+D37) -> 43250.94 | S37: =SUM(F37:L37) -> 0 | T37: =SUM(M37:R37) -> 0 | U37: =S37/T37 -> #DIV/0! | AJ37: =SUM(V37:AI37) -> 0 | AR37: =SUM(AJ37+S37) -> 0 | AS37: =AR37*AU37 -> 0 | AT37: =C37 -> 43250.94 | AU37: =SUM(AU36) -> 0
A38: 43889 | C38: =SUM(C37-AR37+D38) -> 43250.94 | S38: =SUM(F38:L38) -> 0 | T38: =SUM(M38:R38) -> 0 | U38: =S38/T38 -> #DIV/0! | AJ38: =SUM(V38:AI38) -> 0 | AR38: =SUM(AJ38+S38) -> 0 | AS38: =AR38*AU38 -> 0 | AT38: =C38 -> 43250.94 | AU38: =SUM(AU37) -> 0
A39: 43890 | C39: =SUM(C38-AR38+D39) -> 43250.94 | S39: =SUM(F39:L39) -> 0 | T39: =SUM(M39:R39) -> 0 | U39: =S39/T39 -> #DIV/0! | AJ39: =SUM(V39:AI39) -> 0 | AR39: =SUM(AJ39+S39) -> 0 | AS39: =AR39*AU39 -> 0 | AT39: =C39 -> 43250.94 | AU39: =SUM(AU38) -> 0
A40: 43891 | C40: =SUM(C39-AR39+D40) -> 43250.94 | S40: =SUM(F40:L40) -> 0 | T40: =SUM(M40:R40) -> 0 | U40: =S40/T40 -> #DIV/0! | AJ40: =SUM(V40:AI40) -> 0 | AR40: =SUM(AJ40+S40) -> 0 | AS40: =AR40*AU40 -> 0 | AT40: =C40 -> 43250.94 | AU40: =SUM(AU39) -> 0
A41: 43892 | C41: =SUM(C40-AR40+D41) -> 43250.94 | S41: =SUM(F41:L41) -> 0 | T41: =SUM(M41:R41) -> 0 | U41: =S41/T41 -> #DIV/0! | AJ41: =SUM(V41:AI41) -> 0 | AR41: =SUM(AJ41+S41) -> 0 | AS41: =AR41*AU41 -> 0 | AT41: =C41 -> 43250.94 | AU41: =SUM(AU40) -> 0
A42: 43893 | C42: =SUM(C41-AR41+D42) -> 43250.94 | S42: =SUM(F42:L42) -> 0 | T42: =SUM(M42:R42) -> 0 | AJ42: =SUM(V42:AI42) -> 0 | AR42: =SUM(AJ42+S42) -> 0 | AS42: =AR42*AU42 -> 0 | AT42: =C42 -> 43250.94
A43: BF | B43: =AVERAGE(B11:B42) -> 0.50915 | C43: =SUM(C42-AR42+D43) -> 43250.94 | S43: =SUM(F43:L43) -> 0 | T43: =SUM(M43:R43) -> 0 | AJ43: =SUM(V43:AI43) -> 0 | AR43: =SUM(AJ43+S43) -> 0 | AS43: =AR43*AU43 -> 0 | AT43: =C43 -> 43250.94
S44: =SUM(F44:L44) -> 0 | AJ44: =SUM(V44:AI44) -> 0 | AR44: =S44+AJ44 -> 0 | AS44: =AR44*AU44 -> 0
D45: =SUM(D11:D44) -> 33000 | E45: =SUM(E11:E42) -> 66000 | F45: =SUM(F11:F44) -> 0 | G45: =SUM(G11:G44) -> 3581.02 | H45: =SUM(H11:H44) -> 4329.06 | I45: =SUM(I11:I44) -> 0 | J45: =SUM(J11:J44) -> 4064.8 | K45: =SUM(K11:K44) -> 3193.26 | L45: =SUM(L11:L44) -> 4341.75 | M45: =SUM(M11:M44) -> 7546 | ... O45: =SUM(O11:O44) -> 0 | P45: =SUM(P11:P43) -> 11167 | Q45: =SUM(Q11:Q44) -> 8948 | R45: =SUM(R11:R44) -> 9210 | S45: =SUM(F45:L45) -> 19509.89 | T45: =SUM(M45:R45) -> 47977 | U45: =SUM(U11:U42) -> #DIV/0! | V45: =SUM(V9:V44) -> 0 | W45: =SUM(W9:W44) -> 196.47 | X45: =SUM(X9:X44) -> 147.33 | Y45: =SUM(Y9:Y44) -> 217.38 | Z45: =SUM(Z9:Z44) -> 333.89 | AA45: =SUM(AA9:AA44) -> 0 | AB45: =SUM(AB9:AB44) -> 0 | AC45: =SUM(AC10:AC44) -> 93.16 | AD45: =SUM(AD10:AD44) -> 0 | AE45: =SUM(AE9:AE44) -> 0 | AF45: =SUM(AF9:AF44) -> 59.25 | AG45: =SUM(AG9:AG44) -> 0 | AH45: =SUM(AH9:AH43) -> 114 | AI45: =SUM(AI9:AI39) -> 60 | AJ45: =SUM(AJ9:AJ44) -> 1221.48 | AR45: =SUM(AR11:AR43) -> 20731.37 | AS45: =SUM(AS11:AS44) -> 0
A46: Nb Day
T47: =S45*2143 -> 41809694 | U47: TZS
A48: Av. Occ | T48: =T47/2245 -> 18623.472 | U48: USD
B50: A & K VEHICLES | H50: MAULY VEHICLES | N50: GREEN LAND VEHICLES | S50: OTHERS VEHICLES
B51: Date | C51: Vehicles | D51: Liters | E51: Driver name | F51: Authority manager | H51: Date | I51: Vehicles | J51: Liters | K51: Driver name | L51: Authority manager | N51: Date | O51: Vehicles | P51: Liters | Q51: Driver name | R51: Authorized Manager | S51: Date | T51: Vehicles | U51: Liters | V51: Driver name | W51: Athorized Manager | X51: Reasons
B52: 43863 | C52: T880DKQ | D52: 41 | E52: Andrew | F52: huruma | H52: 43868 | I52: T740DCS | J52: 60 | K52: Alphonse
B53: 43868 | C53: T106CWQ | D53: 73 | E53: Richard | F53: huruma

Sheet Energy Graph
A1: Date | B1: Usage KW | C1: Occ % | D1: Cost per room Total Occ | E1: Cost per room Guest Occ
A2: =Gen!A11 -> 43862 | B2: =SUM('[1]Summery Report'!F5) -> 5669 | C2: =SUM('[1]Summery Report'!C5) -> 0.623 | D2: =SUM('[1]Summery Report'!#REF!) -> #REF! | E2: =SUM('[1]Summery Report'!#REF!) -> #REF! | F2: 0.1
A3: =Gen!A12 -> 43863 | B3: =SUM('[1]Summery Report'!F6) -> 6159 | C3: =SUM('[1]Summery Report'!C6) -> 0.779 | D3: =SUM('[1]Summery Report'!#REF!) -> #REF! | E3: =SUM('[1]Summery Report'!#REF!) -> #REF! | F3: 0.1375
A4: =Gen!A13 -> 43864 | B4: =SUM('[1]Summery Report'!F7) -> 6580 | C4: =SUM('[1]Summery Report'!C7) -> 0.532 | D4: =SUM('[1]Summery Report'!#REF!) -> #REF! | E4: =SUM('[1]Summery Report'!#REF!) -> #REF! | F4: 0.0875
A5: =Gen!A14 -> 43865 | B5: =SUM('[1]Summery Report'!F8) -> 6223 | C5: =SUM('[1]Summery Report'!C8) -> 0.61 | D5: =SUM('[1]Summery Report'!#REF!) -> #REF! | E5: =SUM('[1]Summery Report'!#REF!) -> #REF! | F5: 0.225
A6: =Gen!A15 -> 43866 | B6: =SUM('[1]Summery Report'!F9) -> 5984 | C6: =SUM('[1]Summery Report'!C9) -> 0.688 | D6: =SUM('[1]Summery Report'!#REF!) -> #REF! | E6: =SUM('[1]Summery Report'!#REF!) -> #REF! | F6: 0.2
A7: =Gen!A16 -> 43867 | B7: =SUM('[1]Summery Report'!F10) -> 6103 | C7: =SUM('[1]Summery Report'!C10) -> 0.532 | D7: =SUM('[1]Summery Report'!#REF!) -> #REF! | E7: =SUM('[1]Summery Report'!#REF!) -> #REF! | F7: 0.35
A8: =Gen!A17 -> 43868 | B8: =SUM('[1]Summery Report'!F11) -> 5576 | C8: =SUM('[1]Summery Report'!C11) -> 0.753 | D8: =SUM('[1]Summery Report'!#REF!) -> #REF! | E8: =SUM('[1]Summery Report'!#REF!) -> #REF! | F8: 0.375
A9: =Gen!A18 -> 43869 | B9: =SUM('[1]Summery Report'!F12) -> 5532 | C9: =SUM('[1]Summery Report'!C12) -> 0.156 | D9: =SUM('[1]Summery Report'!#REF!) -> #REF! | E9: =SUM('[1]Summery Report'!#REF!) -> #REF! | F9: 0.325
A10: =Gen!A19 -> 43870 | B10: =SUM('[1]Summery Report'!F13) -> 6233 | C10: =SUM('[1]Summery Report'!C13) -> 0.442 | D10: =SUM('[1]Summery Report'!#REF!) -> #REF! | E10: =SUM('[1]Summery Report'!#REF!) -> #REF! | F10: 0.75
A11: =Gen!A20 -> 43871 | B11: =SUM('[1]Summery Report'!F14) -> 6063 | C11: =SUM('[1]Summery Report'!C14) -> 0.325 | D11: =SUM('[1]Summery Report'!#REF!) -> #REF! | E11: =SUM('[1]Summery Report'!#REF!) -> #REF! | F11: 0.7625
A12: =Gen!A21 -> 43872 | B12: =SUM('[1]Summery Report'!F15) -> 5967 | C12: =SUM('[1]Summery Report'!C15) -> 0.455 | D12: =SUM('[1]Summery Report'!#REF!) -> #REF! | E12: =SUM('[1]Summery Report'!#REF!) -> #REF! | F12: 0.1625
A13: =Gen!A22 -> 43873 | B13: =SUM('[1]Summery Report'!F16) -> 5863 | C13: =SUM('[1]Summery Report'!C16) -> 0.416 | D13: =SUM('[1]Summery Report'!#REF!) -> #REF! | E13: =SUM('[1]Summery Report'!#REF!) -> #REF! | F13: 0.1125
... A32: =Gen!A41 -> 43892 | B32: =SUM('[1]Summery Report'!F35) -> 0 | C32: =SUM('[1]Summery Report'!C35) -> 0 | D32: =SUM('[1]Summery Report'!#REF!) -> #REF! | E32: =SUM('[1]Summery Report'!#REF!) -> #REF! | F32: 0.175
A33: =Gen!A42 -> 43893 | B33: =[1]Gen!S41 -> 0

Sheet Lpg (2)
C3: Four Sasons Safari Lodge Serengeti
G6: VALUE | H6: Cost
A7: DATE | B7: A | C7: B | D7: C | F7: Meter Reading | G7: Total | H7: Occu | I7: No.of | J7: Kg
B8: 2Ton% | C8: 1Ton (%) | D8: 1Ton% | F8: consumption | G8: Consumption Kg | H8: % | I8: pax | J8: per pax
B9: 85 | C9: 85 | D9: 25 | F9: 69831
A10: =Gen!A11 -> 43862 | B10: 85 | C10: 85 | D10: 18 | F10: 69852.48 | G10: =(F10-F9)*4.4 -> 94.512 | H10: =Gen!B11 -> 0.2338 | I10: =SUM(F10/H10) -> 298770.23 | J10: =SUM(G10/I10) -> 0.00031633674
A11: =Gen!A12 -> 43863 | B11: 85 | C11: 85 | D11: 10 | F11: 69876.26 | G11: =(F11-F10)*4.4 -> 104.632 | H11: =Gen!B12 -> 0.234 | I11: =SUM(F11/H11) -> 298616.5 | J11: =SUM(G11/I11) -> 0.00035038922
A12: =Gen!A13 -> 43864 | B12: 85 | C12: 85 | D12: 7 | F12: 69698.09 | G12: =(F12-F11)*4.4 -> -783.948 | H12: =Gen!B13 -> 0.104 | I12: =SUM(F12/H12) -> 670173.94 | J12: =SUM(G12/I12) -> -0.001169768
A13: =Gen!A14 -> 43865 | B13: 85 | C13: 85 | D13: 5 | F13: 69723.71 | G13: =(F13-F12)*4.4 -> 112.728 | H13: =Gen!B14 -> 1 | I13: =SUM(F13/H13) -> 69723.71 | J13: =SUM(G13/I13) -> 0.0016167814
A14: =Gen!A15 -> 43866 | B14: 85 | C14: 76 | D14: 0 | F14: 69748.01 | G14: =(F14-F13)*4.4 -> 106.92 | H14: =Gen!B15 -> 1 | I14: =SUM(F14/H14) -> 69748.01 | J14: =SUM(G14/I14) -> 0.001532947
A15: =Gen!A16 -> 43867 | B15: 85 | C15: 70 | D15: 0 | F15: 69771.22 | G15: =(F15-F14)*4.4 -> 102.124 | H15: =Gen!B16 -> 1 | I15: =SUM(F15/H15) -> 69771.22 | J15: =SUM(G15/I15) -> 0.0014636981
A16: =Gen!A17 -> 43868 | B16: 85 | C16: 60 | D16: 0 | F16: 69795.81 | G16: =(F16-F15)*4.4 -> 108.196 | H16: =Gen!B17 -> 1 | I16: =SUM(F16/H16) -> 69795.81 | J16: =SUM(G16/I16) -> 0.001550179
A17: =Gen!A18 -> 43869 | B17: 85 | C17: 55 | D17: 0 | F17: 69821.3 | G17: =(F17-F16)*4.4 -> 112.156 | H17: =Gen!B18 -> 0.1429 | I17: =SUM(F17/H17) -> 488602.52 | J17: =SUM(G17/I17) -> 0.00022954446
A18: =Gen!A19 -> 43870 | B18: 85 | C18: 49 | D18: 0 | F18: 69844.81 | G18: =(F18-F17)*4.4 -> 103.444 | H18: =Gen!B19 -> 0.195 | I18: =SUM(F18/H18) -> 358178.51 | J18: =SUM(G18/I18) -> 0.00028880571
A19: =Gen!A20 -> 43871 | G19: =(F19-F18)*4.4 -> -307317.16 | H19: =Gen!B20 -> 0.1818 | I19: =SUM(F19/H19) -> 0 | J19: =SUM(G19/I19) -> #DIV/0!
A20: =Gen!A21 -> 43872 | G20: =(F20-F19)*4.4 -> 0 | H20: =Gen!B21 -> 0 | I20: =SUM(F20/H20) -> #DIV/0! | J20: =SUM(G20/I20) -> #DIV/0!
A21: =Gen!A22 -> 43873 | G21: =(F21-F20)*4.4 -> 0 | H21: =Gen!B22 -> 0 | I21: =SUM(F21/H21) -> #DIV/0! | J21: =SUM(G21/I21) -> #DIV/0!
A22: =Gen!A23 -> 43874 | G22: =(F22-F21)*4.4 -> 0 | H22: =Gen!B23 -> 0 | I22: =SUM(F22/H22) -> #DIV/0! | J22: =SUM(G22/I22) -> #DIV/0!
A23: =Gen!A24 -> 43875 | G23: =(F23-F22)*4.4 -> 0 | H23: =Gen!B24 -> 0 | I23: =SUM(F23/H23) -> #DIV/0! | J23: =SUM(G23/I23) -> #DIV/0!
A24: =Gen!A25 -> 43876 | G24: =(F24-F23)*4.4 -> 0 | H24: =Gen!B25 -> 0 | I24: =SUM(F24/H24) -> #DIV/0! | J24: =SUM(G24/I24) -> #DIV/0!
A25: =Gen!A26 -> 43877 | G25: =(F25-F24)*4.4 -> 0 | H25: =Gen!B26 -> 0 | I25: =SUM(F25/H25) -> #DIV/0! | J25: =SUM(G25/I25) -> #DIV/0!
A26: =Gen!A27 -> 43878 | G26: =(F26-F25)*4.4 -> 0 | H26: =Gen!B27 -> 0 | I26: =SUM(F26/H26) -> #DIV/0! | J26: =SUM(G26/I26) -> #DIV/0!
A27: =Gen!A28 -> 43879 | G27: =(F27-F26)*4.4 -> 0 | H27: =Gen!B28 -> 0 | I27: =SUM(F27/H27) -> #DIV/0! | J27: =SUM(G27/I27) -> #DIV/0!
A28: =Gen!A29 -> 43880 | G28: =(F28-F27)*4.4 -> 0 | H28: =Gen!B29 -> 0 | I28: =SUM(F28/H28) -> #DIV/0! | J28: =SUM(G28/I28) -> #DIV/0!
A29: =Gen!A30 -> 43881 | G29: =(F29-F28)*4.4 -> 0 | H29: =Gen!B30 -> 0 | I29: =SUM(F29/H29) -> #DIV/0! | J29: =SUM(G29/I29) -> #DIV/0!
A30: =Gen!A31 -> 43882 | G30: =(F30-F29)*4.4 -> 0 | H30: =Gen!B31 -> 0 | I30: =SUM(F30/H30) -> #DIV/0! | J30: =SUM(G30/I30) -> #DIV/0!
... A40: =Gen!A41 -> 43892 | G40: =(F40-F39)*4.4 -> 0 | H40: =Gen!B41 -> 0 | I40: =SUM(F40/H40) -> #DIV/0! | J40: =SUM(G40/I40) -> #DIV/0!
A41: =Gen!A42 -> 43893 | H41: =Gen!B42 -> 0 | I41: =SUM(F41/H41) -> #DIV/0!
C42: TOTAL USAGE | E42: =SUM(E10:E40) -> 0 | F42: =SUM(F10:F40) -> 628131.69 | G42: =SUM(G10:G40) -> -307256.4
F45: =E12-E11 -> 0 | G45: =F45*4.4 -> 0

Sheet LPG_Graph
A1: Date | B1: Usage KG | C1: Occ %
A2: =SUM([1]Gen!A11) -> 43739 | B2: ='[1]Lpg (2)'!G10 -> 197.56 | C2: =SUM([1]Gen!B11) -> 0.623
A3: =SUM([1]Gen!A12) -> 43740 | B3: ='[1]Lpg (2)'!G11 -> 131.956 | C3: =SUM([1]Gen!B12) -> 0.779
A4: =SUM([1]Gen!A13) -> 43741 | B4: ='[1]Lpg (2)'!G12 -> 117.48 | C4: =SUM([1]Gen!B13) -> 0.532
A5: =SUM([1]Gen!A14) -> 43742 | B5: ='[1]Lpg (2)'!G13 -> 102.96 | C5: =SUM([1]Gen!B14) -> 0.61
A6: =SUM([1]Gen!A15) -> 43743 | B6: ='[1]Lpg (2)'!G14 -> 101.816 | C6: =SUM([1]Gen!B15) -> 0.688
A7: =SUM([1]Gen!A16) -> 43744 | B7: ='[1]Lpg (2)'!G15 -> 106.92 | C7: =SUM([1]Gen!B16) -> 0.532
A8: =SUM([1]Gen!A17) -> 43745 | B8: ='[1]Lpg (2)'!G16 -> 116.732 | C8: =SUM([1]Gen!B17) -> 0.753
A9: =SUM([1]Gen!A18) -> 43746 | B9: ='[1]Lpg (2)'!G17 -> 105.732 | C9: =SUM([1]Gen!B18) -> 0.156
A10: =SUM([1]Gen!A19) -> 43747 | B10: ='[1]Lpg (2)'!G18 -> 114.4 | C10: =SUM([1]Gen!B19) -> 0.442
A11: =SUM([1]Gen!A20) -> 43748 | B11: ='[1]Lpg (2)'!G19 -> 102.08 | C11: =SUM([1]Gen!B20) -> 0.325
A12: =SUM([1]Gen!A21) -> 43749 | B12: ='[1]Lpg (2)'!G20 -> 105.292 | C12: =SUM([1]Gen!B21) -> 0.455
A13: =SUM([1]Gen!A22) -> 43750 | B13: ='[1]Lpg (2)'!G21 -> 114.664 | C13: =SUM([1]Gen!B22) -> 0.416
... A32: =SUM([1]Gen!A41) -> 43769 | B32: ='[1]Lpg (2)'!G40 -> 0 | C32: =SUM([1]Gen!B41) -> #REF!

Sheet Water-Meter
A1: Four Seasons Safari Lodge Serengeti February 2020- Water Report
C2: Main Meter | F2: KITCHEN | I2: Amani café | L2: Main SW POOL | O2: Laundry | S2: BORE HOLE NO.1 METER READING | V2: BORE HOLE NO.2 METER READING | Y2: BORE HOLE NO.3 METER READING | AB2: BORE HOLE NO.4 METER READING | AE2: BORE HOLE NO.5 METER READING | AH2: BORE HOLE NO.6 METER READING | AK2: RAIN WATER - METER READING | AN2: TOTAL WATER PRODUCTION
A3: DATE | C3: Open Bal | D3: Final | E3: consumption | F3: Open Bal | G3: Final | H3: consumption | I3: Open Bal | J3: Final | K3: consumption | L3: Open Bal | M3: Final | N3: consumption | O3: Open Bal | P3: Final | Q3: consumption | R3: Total consumption
S4: OPEN | T4: FINAL | U4: PROD. | V4: OPEN | W4: FINAL | X4: PROD. | Y4: OPEN | Z4: FINAL | AA4: PROD. | AB4: OPEN | AC4: FINAL | AD4: M3 | AE4: OPEN | AF4: FINAL | AG4: M3 | AH4: OPEN | AI4: FINAL | AJ4: M3 | AK4: OPEN | AL4: FINAL | AM4: M3
C5: =D4 -> 0 | D5: 226136 | E5: =IF((D5-D4)<0,"0",(D5-D4)) -> 226136 | F5: =G4 -> 0 | G5: 38000 | H5: =IF((G5-G4)<0,"0",(G5-G4)) -> 38000 | I5: =J4 -> 0 | J5: 7712 | K5: =IF((J5-J4)<0,"0",(J5-J4)) -> 7712 | L5: =M4 -> 0 | M5: 11630 | N5: =IF((M5-M4)<0,"0",(M5-M4)) -> 11630 | O5: =P4 -> 0 | P5: 19637 | Q5: =IF((P5-P4)<0,"0",(P5-P4)) -> 19637 | T5: 48536 | U5: =V4 -> OPEN | V5: =W4 -> FINAL | W5: 69032 | Y5: =Z4 -> FINAL | Z5: 78136 | AB5: =AC4 -> FINAL | AC5: 12539 | AE5: =AF4 -> FINAL | AF5: 15965 | AH5: =AI4 -> FINAL | AI5: 24347 | AK5: =AL4 -> FINAL | AL5: 15154
A6: =Gen!A11 -> 43862 | C6: =D5 -> 226136 | D6: 226249 | E6: =IF((D6-D5)<0,"0",(D6-D5)) -> 113 | F6: =G5 -> 38000 | G6: 38000 | H6: =IF((G6-G5)<0,"0",(G6-G5)) -> 0 | I6: =J5 -> 7712 | J6: 7715 | K6: =IF((J6-J5)<0,"0",(J6-J5)) -> 3 | L6: =M5 -> 11630 | N6: =IF((M6-M5)<0,"0",(M6-M5)) -> 0 | O6: =P5 -> 19637 | P6: 19646 | Q6: =IF((P6-P5)<0,"0",(P6-P5)) -> 9 | S6: =T5 -> 48536 | T6: 48585 | U6: =IF((T6-T5)<0,"0",(T6-T5)) -> 49 | V6: =W5 -> 69032 | W6: 69094 | X6: =IF((W6-W5)<0,"0",(W6-W5)) -> 62 | Y6: =Z5 -> 78136 | Z6: 78186 | AA6: =IF((Z6-Z5)<0,"0",(Z6-Z5)) -> 50 | AB6: =AC5 -> 12539 | AC6: 12554 | AD6: =IF((AC6-AC5)<0,"0",(AC6-AC5)) -> 15 | AE6: =AF5 -> 15965 | AF6: 15989 | AG6: =IF((AF6-AF5)<0,"0",(AF6-AF5)) -> 24 | AH6: =AI5 -> 24347 | AI6: 24347 | AJ6: =IF((AI6-AI5)<0,"0",(AI6-AI5)) -> 0 | AK6: =AL5 -> 15154 | AL6: 15154 | AM6: =IF((AL6-AL5)<0,"0",(AL6-AL5)) -> 0 | AN6: =U6+X6+AA6+AD6+AG6+AJ6+AM6 -> 200
A7: =Gen!A12 -> 43863 | C7: =D6 -> 226249 | D7: 226346 | E7: =IF((D7-D6)<0,"0",(D7-D6)) -> 97 | F7: =G6 -> 38000 | G7: 38000 | H7: =IF((G7-G6)<0,"0",(G7-G6)) -> 0 | I7: =J6 -> 7715 | J7: 7717 | K7: =IF((J7-J6)<0,"0",(J7-J6)) -> 2 | L7: =M6 -> 0 | N7: =IF((M7-M6)<0,"0",(M7-M6)) -> 0 | O7: =P6 -> 19646 | P7: 19654 | Q7: =IF((P7-P6)<0,"0",(P7-P6)) -> 8 | S7: =T6 -> 48585 | T7: 48604 | U7: =IF((T7-T6)<0,"0",(T7-T6)) -> 19 | V7: =W6 -> 69094 | W7: 69124 | X7: =IF((W7-W6)<0,"0",(W7-W6)) -> 30 | Y7: =Z6 -> 78186 | Z7: 78236 | AA7: =IF((Z7-Z6)<0,"0",(Z7-Z6)) -> 50 | AB7: =AC6 -> 12554 | AC7: 12570 | AD7: =IF((AC7-AC6)<0,"0",(AC7-AC6)) -> 16 | AE7: =AF6 -> 15989 | AF7: 16014 | AG7: =IF((AF7-AF6)<0,"0",(AF7-AF6)) -> 25 | AH7: =AI6 -> 24347 | AI7: 24347 | AJ7: =IF((AI7-AI6)<0,"0",(AI7-AI6)) -> 0 | AK7: =AL6 -> 15154 | AL7: 15154 | AM7: =IF((AL7-AL6)<0,"0",(AL7-AL6)) -> 0 | AN7: =U7+X7+AA7+AD7+AG7+AJ7+AM7 -> 140
A8: =Gen!A13 -> 43864 | C8: =D7 -> 226346 | D8: 226453 | E8: =IF((D8-D7)<0,"0",(D8-D7)) -> 107 | F8: =G7 -> 38000 | G8: 38000 | H8: =IF((G8-G7)<0,"0",(G8-G7)) -> 0 | I8: =J7 -> 7717 | J8: 7720 | K8: =IF((J8-J7)<0,"0",(J8-J7)) -> 3 | L8: =M7 -> 0 | N8: =IF((M8-M7)<0,"0",(M8-M7)) -> 0 | O8: =P7 -> 19654 | P8: 19664 | Q8: =IF((P8-P7)<0,"0",(P8-P7)) -> 10 | S8: =T7 -> 48604 | T8: 48604 | U8: =IF((T8-T7)<0,"0",(T8-T7)) -> 0 | V8: =W7 -> 69124 | W8: 69124 | X8: =IF((W8-W7)<0,"0",(W8-W7)) -> 0 | Y8: =Z7 -> 78236 | Z8: 78286 | AA8: =IF((Z8-Z7)<0,"0",(Z8-Z7)) -> 50 | AB8: =AC7 -> 12570 | AC8: 12587 | AD8: =IF((AC8-AC7)<0,"0",(AC8-AC7)) -> 17 | AE8: =AF7 -> 16014 | AF8: 16040 | AG8: =IF((AF8-AF7)<0,"0",(AF8-AF7)) -> 26 | AH8: =AI7 -> 24347 | AI8: 24347 | AJ8: =IF((AI8-AI7)<0,"0",(AI8-AI7)) -> 0 | AK8: =AL7 -> 15154 | AL8: 15154 | AM8: =IF((AL8-AL7)<0,"0",(AL8-AL7)) -> 0 | AN8: =U8+X8+AA8+AD8+AG8+AJ8+AM8 -> 93
A9: =Gen!A14 -> 43865 | C9: =D8 -> 226453 | D9: 226592 | E9: =IF((D9-D8)<0,"0",(D9-D8)) -> 139 | F9: =G8 -> 38000 | G9: 38000 | H9: =IF((G9-G8)<0,"0",(G9-G8)) -> 0 | I9: =J8 -> 7720 | J9: 7724 | K9: =IF((J9-J8)<0,"0",(J9-J8)) -> 4 | L9: =M8 -> 0 | N9: =IF((M9-M8)<0,"0",(M9-M8)) -> 0 | O9: =P8 -> 19664 | P9: 19669 | Q9: =IF((P9-P8)<0,"0",(P9-P8)) -> 5 | S9: =T8 -> 48604 | T9: 48604 | U9: =IF((T9-T8)<0,"0",(T9-T8)) -> 0 | V9: =W8 -> 69124 | W9: 69124 | X9: =IF((W9-W8)<0,"0",(W9-W8)) -> 0 | Y9: =Z8 -> 78286 | Z9: 78338 | AA9: =IF((Z9-Z8)<0,"0",(Z9-Z8)) -> 52 | AB9: =AC8 -> 12587 | AC9: 12604 | AD9: =IF((AC9-AC8)<0,"0",(AC9-AC8)) -> 17 | AE9: =AF8 -> 16040 | AF9: 16065 | AG9: =IF((AF9-AF8)<0,"0",(AF9-AF8)) -> 25 | AH9: =AI8 -> 24347 | AI9: 24347 | AJ9: =IF((AI9-AI8)<0,"0",(AI9-AI8)) -> 0 | AK9: =AL8 -> 15154 | AL9: 15154 | AM9: =IF((AL9-AL8)<0,"0",(AL9-AL8)) -> 0 | AN9: =U9+X9+AA9+AD9+AG9+AJ9+AM9 -> 94
A10: =Gen!A15 -> 43866 | C10: =D9 -> 226592 | D10: 226733 | E10: =IF((D10-D9)<0,"0",(D10-D9)) -> 141 | F10: =G9 -> 38000 | G10: 38000 | H10: =IF((G10-G9)<0,"0",(G10-G9)) -> 0 | I10: =J9 -> 7724 | J10: 7729 | K10: =IF((J10-J9)<0,"0",(J10-J9)) -> 5 | L10: =M9 -> 0 | N10: =IF((M10-M9)<0,"0",(M10-M9)) -> 0 | O10: =P9 -> 19669 | P10: 19673 | Q10: =IF((P10-P9)<0,"0",(P10-P9)) -> 4 | S10: =T9 -> 48604 | T10: 48653 | U10: =IF((T10-T9)<0,"0",(T10-T9)) -> 49 | V10: =W9 -> 69124 | W10: 69179 | X10: =IF((W10-W9)<0,"0",(W10-W9)) -> 55 | Y10: =Z9 -> 78338 | Z10: 78377 | AA10: =IF((Z10-Z9)<0,"0",(Z10-Z9)) -> 39 | AB10: =AC9 -> 12604 | AC10: 12616 | AD10: =IF((AC10-AC9)<0,"0",(AC10-AC9)) -> 12 | AE10: =AF9 -> 16065 | AF10: 16088 | AG10: =IF((AF10-AF9)<0,"0",(AF10-AF9)) -> 23 | AH10: =AI9 -> 24347 | AI10: 24347 | AJ10: =IF((AI10-AI9)<0,"0",(AI10-AI9)) -> 0 | AK10: =AL9 -> 15154 | AL10: 15154 | AM10: =IF((AL10-AL9)<0,"0",(AL10-AL9)) -> 0 | AN10: =U10+X10+AA10+AD10+AG10+AJ10+AM10 -> 178
A11: =Gen!A16 -> 43867 | C11: =D10 -> 226733 | D11: 226862 | E11: =IF((D11-D10)<0,"0",(D11-D10)) -> 129 | F11: =G10 -> 38000 | G11: 38000 | H11: =IF((G11-G10)<0,"0",(G11-G10)) -> 0 | I11: =J10 -> 7729 | J11: 7733 | K11: =IF((J11-J10)<0,"0",(J11-J10)) -> 4 | L11: =M10 -> 0 | N11: =IF((M11-M10)<0,"0",(M11-M10)) -> 0 | O11: =P10 -> 19673 | P11: 19688 | Q11: =IF((P11-P10)<0,"0",(P11-P10)) -> 15 | S11: =T10 -> 48653 | T11: 48706 | U11: =IF((T11-T10)<0,"0",(T11-T10)) -> 53 | V11: =W10 -> 69179 | W11: 69244 | X11: =IF((W11-W10)<0,"0",(W11-W10)) -> 65 | Y11: =Z10 -> 78377 | Z11: 78410 | AA11: =IF((Z11-Z10)<0,"0",(Z11-Z10)) -> 33 | AB11: =AC10 -> 12616 | AC11: 12629 | AD11: =IF((AC11-AC10)<0,"0",(AC11-AC10)) -> 13 | AE11: =AF10 -> 16088 | AF11: 16112 | AG11: =IF((AF11-AF10)<0,"0",(AF11-AF10)) -> 24 | AH11: =AI10 -> 24347 | AI11: 24347 | AJ11: =IF((AI11-AI10)<0,"0",(AI11-AI10)) -> 0 | AK11: =AL10 -> 15154 | AL11: 15154 | AM11: =IF((AL11-AL10)<0,"0",(AL11-AL10)) -> 0 | AN11: =U11+X11+AA11+AD11+AG11+AJ11+AM11 -> 188
A12: =Gen!A17 -> 43868 | C12: =D11 -> 226862 | D12: 226991 | E12: =IF((D12-D11)<0,"0",(D12-D11)) -> 129 | F12: =G11 -> 38000 | G12: 38000 | H12: =IF((G12-G11)<0,"0",(G12-G11)) -> 0 | I12: =J11 -> 7733 | J12: 7737 | K12: =IF((J12-J11)<0,"0",(J12-J11)) -> 4 | L12: =M11 -> 0 | N12: =IF((M12-M11)<0,"0",(M12-M11)) -> 0 | O12: =P11 -> 19688 | P12: 19699 | Q12: =IF((P12-P11)<0,"0",(P12-P11)) -> 11 | S12: =T11 -> 48706 | T12: 48758 | U12: =IF((T12-T11)<0,"0",(T12-T11)) -> 52 | V12: =W11 -> 69244 | W12: 69304 | X12: =IF((W12-W11)<0,"0",(W12-W11)) -> 60 | Y12: =Z11 -> 78410 | Z12: 78440 | AA12: =IF((Z12-Z11)<0,"0",(Z12-Z11)) -> 30 | AB12: =AC11 -> 12629 | AC12: 12642 | AD12: =IF((AC12-AC11)<0,"0",(AC12-AC11)) -> 13 | AE12: =AF11 -> 16112 | AF12: 16135 | AG12: =IF((AF12-AF11)<0,"0",(AF12-AF11)) -> 23 | AH12: =AI11 -> 24347 | AI12: 24347 | AJ12: =IF((AI12-AI11)<0,"0",(AI12-AI11)) -> 0 | AK12: =AL11 -> 15154 | AL12: 15154 | AM12: =IF((AL12-AL11)<0,"0",(AL12-AL11)) -> 0 | AN12: =U12+X12+AA12+AD12+AG12+AJ12+AM12 -> 178
A13: =Gen!A18 -> 43869 | C13: =D12 -> 226991 | D13: 227119 | E13: =IF((D13-D12)<0,"0",(D13-D12)) -> 128 | F13: =G12 -> 38000 | G13: 38000 | H13: =IF((G13-G12)<0,"0",(G13-G12)) -> 0 | I13: =J12 -> 7737 | J13: 7741 | K13: =IF((J13-J12)<0,"0",(J13-J12)) -> 4 | L13: =M12 -> 0 | N13: =IF((M13-M12)<0,"0",(M13-M12)) -> 0 | O13: =P12 -> 19699 | P13: 19712 | Q13: =IF((P13-P12)<0,"0",(P13-P12)) -> 13 | S13: =T12 -> 48758 | T13: 48811 | U13: =IF((T13-T12)<0,"0",(T13-T12)) -> 53 | V13: =W12 -> 69304 | W13: 69359 | X13: =IF((W13-W12)<0,"0",(W13-W12)) -> 55 | Y13: =Z12 -> 78440 | Z13: 78480 | AA13: =IF((Z13-Z12)<0,"0",(Z13-Z12)) -> 40 | AB13: =AC12 -> 12642 | AC13: 12656 | AD13: =IF((AC13-AC12)<0,"0",(AC13-AC12)) -> 14 | AE13: =AF12 -> 16135 | AF13: 16157 | AG13: =IF((AF13-AF12)<0,"0",(AF13-AF12)) -> 22 | AH13: =AI12 -> 24347 | AI13: 24347 | AJ13: =IF((AI13-AI12)<0,"0",(AI13-AI12)) -> 0 | AK13: =AL12 -> 15154 | AL13: 15154 | AM13: =IF((AL13-AL12)<0,"0",(AL13-AL12)) -> 0 | AN13: =U13+X13+AA13+AD13+AG13+AJ13+AM13 -> 184
A14: =Gen!A19 -> 43870 | C14: =D13 -> 227119 | D14: 227215 | E14: =IF((D14-D13)<0,"0",(D14-D13)) -> 96 | F14: =G13 -> 38000 | G14: 38000 | H14: =IF((G14-G13)<0,"0",(G14-G13)) -> 0 | I14: =J13 -> 7741 | J14: 7744 | K14: =IF((J14-J13)<0,"0",(J14-J13)) -> 3 | L14: =M13 -> 0 | N14: =IF((M14-M13)<0,"0",(M14-M13)) -> 0 | O14: =P13 -> 19712 | P14: 19726 | Q14: =IF((P14-P13)<0,"0",(P14-P13)) -> 14 | S14: =T13 -> 48811 | T14: 48866 | U14: =IF((T14-T13)<0,"0",(T14-T13)) -> 55 | V14: =W13 -> 69359 | W14: 69421 | X14: =IF((W14-W13)<0,"0",(W14-W13)) -> 62 | Y14: =Z13 -> 78480 | Z14: 78558 | AA14: =IF((Z14-Z13)<0,"0",(Z14-Z13)) -> 78 | AB14: =AC13 -> 12656 | AC14: 12678 | AD14: =IF((AC14-AC13)<0,"0",(AC14-AC13)) -> 22 | AE14: =AF13 -> 16157 | AF14: 16179 | AG14: =IF((AF14-AF13)<0,"0",(AF14-AF13)) -> 22 | AH14: =AI13 -> 24347 | AI14: 24347 | AJ14: =IF((AI14-AI13)<0,"0",(AI14-AI13)) -> 0 | AK14: =AL13 -> 15154 | AL14: 15154 | AM14: =IF((AL14-AL13)<0,"0",(AL14-AL13)) -> 0 | AN14: =U14+X14+AA14+AD14+AG14+AJ14+AM14 -> 239
A15: =Gen!A20 -> 43871 | C15: =D14 -> 227215 | E15: =IF((D15-D14)<0,"0",(D15-D14)) -> 0 | F15: =G14 -> 38000 | H15: =IF((G15-G14)<0,"0",(G15-G14)) -> 0 | I15: =J14 -> 7744 | K15: =IF((J15-J14)<0,"0",(J15-J14)) -> 0 | L15: =M14 -> 0 | N15: =IF((M15-M14)<0,"0",(M15-M14)) -> 0 | O15: =P14 -> 19726 | Q15: =IF((P15-P14)<0,"0",(P15-P14)) -> 0 | S15: =T14 -> 48866 | U15: =IF((T15-T14)<0,"0",(T15-T14)) -> 0 | V15: =W14 -> 69421 | X15: =IF((W15-W14)<0,"0",(W15-W14)) -> 0 | Y15: =Z14 -> 78558 | AA15: =IF((Z15-Z14)<0,"0",(Z15-Z14)) -> 0 | AB15: =AC14 -> 12678 | AD15: =IF((AC15-AC14)<0,"0",(AC15-AC14)) -> 0 | AE15: =AF14 -> 16179 | AG15: =IF((AF15-AF14)<0,"0",(AF15-AF14)) -> 0 | AH15: =AI14 -> 24347 | AJ15: =IF((AI15-AI14)<0,"0",(AI15-AI14)) -> 0 | AK15: =AL14 -> 15154 | AM15: =IF((AL15-AL14)<0,"0",(AL15-AL14)) -> 0 | AN15: =U15+X15+AA15+AD15+AG15+AJ15+AM15 -> 0
A16: =Gen!A21 -> 43872 | C16: =D15 -> 0 | E16: =IF((D16-D15)<0,"0",(D16-D15)) -> 0 | F16: =G15 -> 0 | H16: =IF((G16-G15)<0,"0",(G16-G15)) -> 0 | I16: =J15 -> 0 | K16: =IF((J16-J15)<0,"0",(J16-J15)) -> 0 | N16: =IF((M16-M15)<0,"0",(M16-M15)) -> 0 | O16: =P15 -> 0 | Q16: =IF((P16-P15)<0,"0",(P16-P15)) -> 0 | S16: =T15 -> 0 | U16: =IF((T16-T15)<0,"0",(T16-T15)) -> 0 | V16: =W15 -> 0 | X16: =IF((W16-W15)<0,"0",(W16-W15)) -> 0 | Y16: =Z15 -> 0 | AA16: =IF((Z16-Z15)<0,"0",(Z16-Z15)) -> 0 | AB16: =AC15 -> 0 | AD16: =IF((AC16-AC15)<0,"0",(AC16-AC15)) -> 0 | AE16: =AF15 -> 0 | AG16: =IF((AF16-AF15)<0,"0",(AF16-AF15)) -> 0 | AH16: =AI15 -> 0 | AJ16: =IF((AI16-AI15)<0,"0",(AI16-AI15)) -> 0 | AK16: =AL15 -> 0 | AM16: =IF((AL16-AL15)<0,"0",(AL16-AL15)) -> 0 | AN16: =U16+X16+AA16+AD16+AG16+AJ16+AM16 -> 0
A17: =Gen!A22 -> 43873 | C17: =D16 -> 0 | E17: =IF((D17-D16)<0,"0",(D17-D16)) -> 0 | F17: =G16 -> 0 | H17: =IF((G17-G16)<0,"0",(G17-G16)) -> 0 | I17: =J16 -> 0 | K17: =IF((J17-J16)<0,"0",(J17-J16)) -> 0 | N17: =IF((M17-M16)<0,"0",(M17-M16)) -> 0 | O17: =P16 -> 0 | Q17: =IF((P17-P16)<0,"0",(P17-P16)) -> 0 | S17: =T16 -> 0 | U17: =IF((T17-T16)<0,"0",(T17-T16)) -> 0 | V17: =W16 -> 0 | X17: =IF((W17-W16)<0,"0",(W17-W16)) -> 0 | Y17: =Z16 -> 0 | AA17: =IF((Z17-Z16)<0,"0",(Z17-Z16)) -> 0 | AB17: =AC16 -> 0 | AD17: =IF((AC17-AC16)<0,"0",(AC17-AC16)) -> 0 | AE17: =AF16 -> 0 | AG17: =IF((AF17-AF16)<0,"0",(AF17-AF16)) -> 0 | AH17: =AI16 -> 0 | AJ17: =IF((AI17-AI16)<0,"0",(AI17-AI16)) -> 0 | AK17: =AL16 -> 0 | AM17: =IF((AL17-AL16)<0,"0",(AL17-AL16)) -> 0 | AN17: =U17+X17+AA17+AD17+AG17+AJ17+AM17 -> 0
A18: =Gen!A23 -> 43874 | C18: =D17 -> 0 | E18: =IF((D18-D17)<0,"0",(D18-D17)) -> 0 | F18: =G17 -> 0 | H18: =IF((G18-G17)<0,"0",(G18-G17)) -> 0 | K18: =IF((J18-J17)<0,"0",(J18-J17)) -> 0 | L18: =M17 -> 0 | N18: =IF((M18-M17)<0,"0",(M18-M17)) -> 0 | O18: =P17 -> 0 | Q18: =IF((P18-P17)<0,"0",(P18-P17)) -> 0 | S18: =T17 -> 0 | U18: =IF((T18-T17)<0,"0",(T18-T17)) -> 0 | V18: =W17 -> 0 | X18: =IF((W18-W17)<0,"0",(W18-W17)) -> 0 | Y18: =Z17 -> 0 | AA18: =IF((Z18-Z17)<0,"0",(Z18-Z17)) -> 0 | AB18: =AC17 -> 0 | AD18: =IF((AC18-AC17)<0,"0",(AC18-AC17)) -> 0 | AE18: =AF17 -> 0 | AG18: =IF((AF18-AF17)<0,"0",(AF18-AF17)) -> 0 | AH18: =AI17 -> 0 | AJ18: =IF((AI18-AI17)<0,"0",(AI18-AI17)) -> 0 | AK18: =AL17 -> 0 | AM18: =IF((AL18-AL17)<0,"0",(AL18-AL17)) -> 0 | AN18: =U18+X18+AA18+AD18+AG18+AJ18+AM18 -> 0
A19: =Gen!A24 -> 43875 | C19: =D18 -> 0 | E19: =IF((D19-D18)<0,"0",(D19-D18)) -> 0 | F19: =G18 -> 0 | H19: =IF((G19-G18)<0,"0",(G19-G18)) -> 0 | I19: =J18 -> 0 | K19: =IF((J19-J18)<0,"0",(J19-J18)) -> 0 | L19: =M18 -> 0 | N19: =IF((M19-M18)<0,"0",(M19-M18)) -> 0 | O19: =P18 -> 0 | Q19: =IF((P19-P18)<0,"0",(P19-P18)) -> 0 | S19: =T18 -> 0 | U19: =IF((T19-T18)<0,"0",(T19-T18)) -> 0 | V19: =W18 -> 0 | X19: =IF((W19-W18)<0,"0",(W19-W18)) -> 0 | Y19: =Z18 -> 0 | AA19: =IF((Z19-Z18)<0,"0",(Z19-Z18)) -> 0 | AB19: =AC18 -> 0 | AD19: =IF((AC19-AC18)<0,"0",(AC19-AC18)) -> 0 | AE19: =AF18 -> 0 | AG19: =IF((AF19-AF18)<0,"0",(AF19-AF18)) -> 0 | AH19: =AI18 -> 0 | AJ19: =IF((AI19-AI18)<0,"0",(AI19-AI18)) -> 0 | AK19: =AL18 -> 0 | AM19: =IF((AL19-AL18)<0,"0",(AL19-AL18)) -> 0 | AN19: =U19+X19+AA19+AD19+AG19+AJ19+AM19 -> 0
A20: =Gen!A25 -> 43876 | C20: =D19 -> 0 | E20: =IF((D20-D19)<0,"0",(D20-D19)) -> 0 | F20: =G19 -> 0 | H20: =IF((G20-G19)<0,"0",(G20-G19)) -> 0 | I20: =J19 -> 0 | K20: =IF((J20-J19)<0,"0",(J20-J19)) -> 0 | L20: =M19 -> 0 | N20: =IF((M20-M19)<0,"0",(M20-M19)) -> 0 | O20: =P19 -> 0 | Q20: =IF((P20-P19)<0,"0",(P20-P19)) -> 0 | S20: =T19 -> 0 | U20: =IF((T20-T19)<0,"0",(T20-T19)) -> 0 | V20: =W19 -> 0 | X20: =IF((W20-W19)<0,"0",(W20-W19)) -> 0 | Y20: =Z19 -> 0 | AA20: =IF((Z20-Z19)<0,"0",(Z20-Z19)) -> 0 | AB20: =AC19 -> 0 | AD20: =IF((AC20-AC19)<0,"0",(AC20-AC19)) -> 0 | AE20: =AF19 -> 0 | AG20: =IF((AF20-AF19)<0,"0",(AF20-AF19)) -> 0 | AH20: =AI19 -> 0 | AJ20: =IF((AI20-AI19)<0,"0",(AI20-AI19)) -> 0 | AK20: =AL19 -> 0 | AM20: =IF((AL20-AL19)<0,"0",(AL20-AL19)) -> 0 | AN20: =U20+X20+AA20+AD20+AG20+AJ20+AM20 -> 0
A21: =Gen!A26 -> 43877 | C21: =D20 -> 0 | E21: =IF((D21-D20)<0,"0",(D21-D20)) -> 0 | F21: =G20 -> 0 | H21: =IF((G21-G20)<0,"0",(G21-G20)) -> 0 | I21: =J20 -> 0 | K21: =IF((J21-J20)<0,"0",(J21-J20)) -> 0 | L21: =M20 -> 0 | N21: =IF((M21-M20)<0,"0",(M21-M20)) -> 0 | O21: =P20 -> 0 | Q21: =IF((P21-P20)<0,"0",(P21-P20)) -> 0 | S21: =T20 -> 0 | U21: =IF((T21-T20)<0,"0",(T21-T20)) -> 0 | V21: =W20 -> 0 | X21: =IF((W21-W20)<0,"0",(W21-W20)) -> 0 | Y21: =Z20 -> 0 | AA21: =IF((Z21-Z20)<0,"0",(Z21-Z20)) -> 0 | AB21: =AC20 -> 0 | AD21: =IF((AC21-AC20)<0,"0",(AC21-AC20)) -> 0 | AE21: =AF20 -> 0 | AG21: =IF((AF21-AF20)<0,"0",(AF21-AF20)) -> 0 | AH21: =AI20 -> 0 | AJ21: =IF((AI21-AI20)<0,"0",(AI21-AI20)) -> 0 | AK21: =AL20 -> 0 | AM21: =IF((AL21-AL20)<0,"0",(AL21-AL20)) -> 0 | AN21: =U21+X21+AA21+AD21+AG21+AJ21+AM21 -> 0
A22: =Gen!A27 -> 43878 | C22: =D21 -> 0 | E22: =IF((D22-D21)<0,"0",(D22-D21)) -> 0 | F22: =G21 -> 0 | H22: =IF((G22-G21)<0,"0",(G22-G21)) -> 0 | I22: =J21 -> 0 | K22: =IF((J22-J21)<0,"0",(J22-J21)) -> 0 | L22: =M21 -> 0 | N22: =IF((M22-M21)<0,"0",(M22-M21)) -> 0 | O22: =P21 -> 0 | Q22: =IF((P22-P21)<0,"0",(P22-P21)) -> 0 | S22: =T21 -> 0 | U22: =IF((T22-T21)<0,"0",(T22-T21)) -> 0 | V22: =W21 -> 0 | X22: =IF((W22-W21)<0,"0",(W22-W21)) -> 0 | Y22: =Z21 -> 0 | AA22: =IF((Z22-Z21)<0,"0",(Z22-Z21)) -> 0 | AB22: =AC21 -> 0 | AD22: =IF((AC22-AC21)<0,"0",(AC22-AC21)) -> 0 | AE22: =AF21 -> 0 | AG22: =IF((AF22-AF21)<0,"0",(AF22-AF21)) -> 0 | AH22: =AI21 -> 0 | AJ22: =IF((AI22-AI21)<0,"0",(AI22-AI21)) -> 0 | AK22: =AL21 -> 0 | AM22: =IF((AL22-AL21)<0,"0",(AL22-AL21)) -> 0 | AN22: =U22+X22+AA22+AD22+AG22+AJ22+AM22 -> 0
A23: =Gen!A28 -> 43879 | C23: =D22 -> 0 | E23: =IF((D23-D22)<0,"0",(D23-D22)) -> 0 | F23: =G22 -> 0 | H23: =IF((G23-G22)<0,"0",(G23-G22)) -> 0 | I23: =J22 -> 0 | K23: =IF((J23-J22)<0,"0",(J23-J22)) -> 0 | L23: =M22 -> 0 | N23: =IF((M23-M22)<0,"0",(M23-M22)) -> 0 | O23: =P22 -> 0 | Q23: =IF((P23-P22)<0,"0",(P23-P22)) -> 0 | S23: =T22 -> 0 | U23: =IF((T23-T22)<0,"0",(T23-T22)) -> 0 | V23: =W22 -> 0 | X23: =IF((W23-W22)<0,"0",(W23-W22)) -> 0 | Y23: =Z22 -> 0 | AA23: =IF((Z23-Z22)<0,"0",(Z23-Z22)) -> 0 | AB23: =AC22 -> 0 | AD23: =IF((AC23-AC22)<0,"0",(AC23-AC22)) -> 0 | AE23: =AF22 -> 0 | AG23: =IF((AF23-AF22)<0,"0",(AF23-AF22)) -> 0 | AH23: =AI22 -> 0 | AJ23: =IF((AI23-AI22)<0,"0",(AI23-AI22)) -> 0 | AK23: =AL22 -> 0 | AM23: =IF((AL23-AL22)<0,"0",(AL23-AL22)) -> 0 | AN23: =U23+X23+AA23+AD23+AG23+AJ23+AM23 -> 0
A24: =Gen!A29 -> 43880 | C24: =D23 -> 0 | E24: =IF((D24-D23)<0,"0",(D24-D23)) -> 0 | F24: =G23 -> 0 | H24: =IF((G24-G23)<0,"0",(G24-G23)) -> 0 | I24: =J23 -> 0 | K24: =IF((J24-J23)<0,"0",(J24-J23)) -> 0 | L24: =M23 -> 0 | N24: =IF((M24-M23)<0,"0",(M24-M23)) -> 0 | O24: =P23 -> 0 | Q24: =IF((P24-P23)<0,"0",(P24-P23)) -> 0 | S24: =T23 -> 0 | U24: =IF((T24-T23)<0,"0",(T24-T23)) -> 0 | V24: =W23 -> 0 | X24: =IF((W24-W23)<0,"0",(W24-W23)) -> 0 | Y24: =Z23 -> 0 | AA24: =IF((Z24-Z23)<0,"0",(Z24-Z23)) -> 0 | AB24: =AC23 -> 0 | AD24: =IF((AC24-AC23)<0,"0",(AC24-AC23)) -> 0 | AE24: =AF23 -> 0 | AG24: =IF((AF24-AF23)<0,"0",(AF24-AF23)) -> 0 | AH24: =AI23 -> 0 | AJ24: =IF((AI24-AI23)<0,"0",(AI24-AI23)) -> 0 | AK24: =AL23 -> 0 | AM24: =IF((AL24-AL23)<0,"0",(AL24-AL23)) -> 0 | AN24: =U24+X24+AA24+AD24+AG24+AJ24+AM24 -> 0
A25: =Gen!A30 -> 43881 | C25: =D24 -> 0 | E25: =IF((D25-D24)<0,"0",(D25-D24)) -> 0 | F25: =G24 -> 0 | H25: =IF((G25-G24)<0,"0",(G25-G24)) -> 0 | I25: =J24 -> 0 | K25: =IF((J25-J24)<0,"0",(J25-J24)) -> 0 | L25: =M24 -> 0 | N25: =IF((M25-M24)<0,"0",(M25-M24)) -> 0 | O25: =P24 -> 0 | Q25: =IF((P25-P24)<0,"0",(P25-P24)) -> 0 | S25: =T24 -> 0 | U25: =IF((T25-T24)<0,"0",(T25-T24)) -> 0 | V25: =W24 -> 0 | X25: =IF((W25-W24)<0,"0",(W25-W24)) -> 0 | Y25: =Z24 -> 0 | AA25: =IF((Z25-Z24)<0,"0",(Z25-Z24)) -> 0 | AB25: =AC24 -> 0 | AD25: =IF((AC25-AC24)<0,"0",(AC25-AC24)) -> 0 | AE25: =AF24 -> 0 | AG25: =IF((AF25-AF24)<0,"0",(AF25-AF24)) -> 0 | AH25: =AI24 -> 0 | AJ25: =IF((AI25-AI24)<0,"0",(AI25-AI24)) -> 0 | AK25: =AL24 -> 0 | AM25: =IF((AL25-AL24)<0,"0",(AL25-AL24)) -> 0 | AN25: =U25+X25+AA25+AD25+AG25+AJ25+AM25 -> 0
A26: =Gen!A31 -> 43882 | C26: =D25 -> 0 | E26: =IF((D26-D25)<0,"0",(D26-D25)) -> 0 | F26: =G25 -> 0 | H26: =IF((G26-G25)<0,"0",(G26-G25)) -> 0 | I26: =J25 -> 0 | K26: =IF((J26-J25)<0,"0",(J26-J25)) -> 0 | L26: =M25 -> 0 | N26: =IF((M26-M25)<0,"0",(M26-M25)) -> 0 | O26: =P25 -> 0 | Q26: =IF((P26-P25)<0,"0",(P26-P25)) -> 0 | S26: =T25 -> 0 | U26: =IF((T26-T25)<0,"0",(T26-T25)) -> 0 | V26: =W25 -> 0 | X26: =IF((W26-W25)<0,"0",(W26-W25)) -> 0 | Y26: =Z25 -> 0 | AA26: =IF((Z26-Z25)<0,"0",(Z26-Z25)) -> 0 | AB26: =AC25 -> 0 | AD26: =IF((AC26-AC25)<0,"0",(AC26-AC25)) -> 0 | AE26: =AF25 -> 0 | AG26: =IF((AF26-AF25)<0,"0",(AF26-AF25)) -> 0 | AH26: =AI25 -> 0 | AJ26: =IF((AI26-AI25)<0,"0",(AI26-AI25)) -> 0 | AK26: =AL25 -> 0 | AM26: =IF((AL26-AL25)<0,"0",(AL26-AL25)) -> 0 | AN26: =U26+X26+AA26+AD26+AG26+AJ26+AM26 -> 0
A27: =Gen!A32 -> 43883 | C27: =D26 -> 0 | E27: =IF((D27-D26)<0,"0",(D27-D26)) -> 0 | F27: =G26 -> 0 | H27: =IF((G27-G26)<0,"0",(G27-G26)) -> 0 | I27: =J26 -> 0 | K27: =IF((J27-J26)<0,"0",(J27-J26)) -> 0 | L27: =M26 -> 0 | N27: =IF((M27-M26)<0,"0",(M27-M26)) -> 0 | O27: =P26 -> 0 | Q27: =IF((P27-P26)<0,"0",(P27-P26)) -> 0 | S27: =T26 -> 0 | U27: =IF((T27-T26)<0,"0",(T27-T26)) -> 0 | V27: =W26 -> 0 | X27: =IF((W27-W26)<0,"0",(W27-W26)) -> 0 | Y27: =Z26 -> 0 | AA27: =IF((Z27-Z26)<0,"0",(Z27-Z26)) -> 0 | AB27: =AC26 -> 0 | AD27: =IF((AC27-AC26)<0,"0",(AC27-AC26)) -> 0 | AE27: =AF26 -> 0 | AG27: =IF((AF27-AF26)<0,"0",(AF27-AF26)) -> 0 | AH27: =AI26 -> 0 | AJ27: =IF((AI27-AI26)<0,"0",(AI27-AI26)) -> 0 | AK27: =AL26 -> 0 | AM27: =IF((AL27-AL26)<0,"0",(AL27-AL26)) -> 0 | AN27: =U27+X27+AA27+AD27+AG27+AJ27+AM27 -> 0
A28: =Gen!A33 -> 43884 | C28: =D27 -> 0 | E28: =IF((D28-D27)<0,"0",(D28-D27)) -> 0 | F28: =G27 -> 0 | H28: =IF((G28-G27)<0,"0",(G28-G27)) -> 0 | I28: =J27 -> 0 | K28: =IF((J28-J27)<0,"0",(J28-J27)) -> 0 | L28: =M27 -> 0 | N28: =IF((M28-M27)<0,"0",(M28-M27)) -> 0 | O28: =P27 -> 0 | Q28: =IF((P28-P27)<0,"0",(P28-P27)) -> 0 | S28: =T27 -> 0 | U28: =IF((T28-T27)<0,"0",(T28-T27)) -> 0 | V28: =W27 -> 0 | X28: =IF((W28-W27)<0,"0",(W28-W27)) -> 0 | Y28: =Z27 -> 0 | AA28: =IF((Z28-Z27)<0,"0",(Z28-Z27)) -> 0 | AB28: =AC27 -> 0 | AD28: =IF((AC28-AC27)<0,"0",(AC28-AC27)) -> 0 | AE28: =AF27 -> 0 | AG28: =IF((AF28-AF27)<0,"0",(AF28-AF27)) -> 0 | AH28: =AI27 -> 0 | AJ28: =IF((AI28-AI27)<0,"0",(AI28-AI27)) -> 0 | AK28: =AL27 -> 0 | AM28: =IF((AL28-AL27)<0,"0",(AL28-AL27)) -> 0 | AN28: =U28+X28+AA28+AD28+AG28+AJ28+AM28 -> 0
A29: =Gen!A34 -> 43885 | C29: =D28 -> 0 | E29: =IF((D29-D28)<0,"0",(D29-D28)) -> 0 | F29: =G28 -> 0 | H29: =IF((G29-G28)<0,"0",(G29-G28)) -> 0 | I29: =J28 -> 0 | K29: =IF((J29-J28)<0,"0",(J29-J28)) -> 0 | L29: =M28 -> 0 | N29: =IF((M29-M28)<0,"0",(M29-M28)) -> 0 | O29: =P28 -> 0 | Q29: =IF((P29-P28)<0,"0",(P29-P28)) -> 0 | S29: =T28 -> 0 | U29: =IF((T29-T28)<0,"0",(T29-T28)) -> 0 | V29: =W28 -> 0 | X29: =IF((W29-W28)<0,"0",(W29-W28)) -> 0 | Y29: =Z28 -> 0 | AA29: =IF((Z29-Z28)<0,"0",(Z29-Z28)) -> 0 | AB29: =AC28 -> 0 | AD29: =IF((AC29-AC28)<0,"0",(AC29-AC28)) -> 0 | AE29: =AF28 -> 0 | AG29: =IF((AF29-AF28)<0,"0",(AF29-AF28)) -> 0 | AH29: =AI28 -> 0 | AJ29: =IF((AI29-AI28)<0,"0",(AI29-AI28)) -> 0 | AK29: =AL28 -> 0 | AM29: =IF((AL29-AL28)<0,"0",(AL29-AL28)) -> 0 | AN29: =U29+X29+AA29+AD29+AG29+AJ29+AM29 -> 0
A30: =Gen!A35 -> 43886 | C30: =D29 -> 0 | E30: =IF((D30-D29)<0,"0",(D30-D29)) -> 0 | F30: =G29 -> 0 | H30: =IF((G30-G29)<0,"0",(G30-G29)) -> 0 | I30: =J29 -> 0 | K30: =IF((J30-J29)<0,"0",(J30-J29)) -> 0 | L30: =M29 -> 0 | N30: =IF((M30-M29)<0,"0",(M30-M29)) -> 0 | O30: =P29 -> 0 | Q30: =IF((P30-P29)<0,"0",(P30-P29)) -> 0 | S30: =T29 -> 0 | U30: =IF((T30-T29)<0,"0",(T30-T29)) -> 0 | V30: =W29 -> 0 | X30: =IF((W30-W29)<0,"0",(W30-W29)) -> 0 | Y30: =Z29 -> 0 | AA30: =IF((Z30-Z29)<0,"0",(Z30-Z29)) -> 0 | AB30: =AC29 -> 0 | AD30: =IF((AC30-AC29)<0,"0",(AC30-AC29)) -> 0 | AE30: =AF29 -> 0 | AG30: =IF((AF30-AF29)<0,"0",(AF30-AF29)) -> 0 | AH30: =AI29 -> 0 | AJ30: =IF((AI30-AI29)<0,"0",(AI30-AI29)) -> 0 | AK30: =AL29 -> 0 | AM30: =IF((AL30-AL29)<0,"0",(AL30-AL29)) -> 0 | AN30: =U30+X30+AA30+AD30+AG30+AJ30+AM30 -> 0
A31: =Gen!A36 -> 43887 | C31: =D30 -> 0 | E31: =IF((D31-D30)<0,"0",(D31-D30)) -> 0 | F31: =G30 -> 0 | H31: =IF((G31-G30)<0,"0",(G31-G30)) -> 0 | I31: =J30 -> 0 | K31: =IF((J31-J30)<0,"0",(J31-J30)) -> 0 | L31: =M30 -> 0 | N31: =IF((M31-M30)<0,"0",(M31-M30)) -> 0 | O31: =P30 -> 0 | Q31: =IF((P31-P30)<0,"0",(P31-P30)) -> 0 | S31: =T30 -> 0 | U31: =IF((T31-T30)<0,"0",(T31-T30)) -> 0 | V31: =W30 -> 0 | X31: =IF((W31-W30)<0,"0",(W31-W30)) -> 0 | Y31: =Z30 -> 0 | AA31: =IF((Z31-Z30)<0,"0",(Z31-Z30)) -> 0 | AB31: =AC30 -> 0 | AD31: =IF((AC31-AC30)<0,"0",(AC31-AC30)) -> 0 | AE31: =AF30 -> 0 | AG31: =IF((AF31-AF30)<0,"0",(AF31-AF30)) -> 0 | AH31: =AI30 -> 0 | AJ31: =IF((AI31-AI30)<0,"0",(AI31-AI30)) -> 0 | AK31: =AL30 -> 0 | AM31: =IF((AL31-AL30)<0,"0",(AL31-AL30)) -> 0 | AN31: =U31+X31+AA31+AD31+AG31+AJ31+AM31 -> 0
A32: =Gen!A37 -> 43888 | B32: 10/27//2009 | C32: =D31 -> 0 | E32: =IF((D32-D31)<0,"0",(D32-D31)) -> 0 | F32: =G31 -> 0 | H32: =IF((G32-G31)<0,"0",(G32-G31)) -> 0 | I32: =J31 -> 0 | K32: =IF((J32-J31)<0,"0",(J32-J31)) -> 0 | L32: =M31 -> 0 | N32: =IF((M32-M31)<0,"0",(M32-M31)) -> 0 | O32: =P31 -> 0 | Q32: =IF((P32-P31)<0,"0",(P32-P31)) -> 0 | S32: =T31 -> 0 | U32: =IF((T32-T31)<0,"0",(T32-T31)) -> 0 | V32: =W31 -> 0 | X32: =IF((W32-W31)<0,"0",(W32-W31)) -> 0 | Y32: =Z31 -> 0 | AA32: =IF((Z32-Z31)<0,"0",(Z32-Z31)) -> 0 | AB32: =AC31 -> 0 | AD32: =IF((AC32-AC31)<0,"0",(AC32-AC31)) -> 0 | AE32: =AF31 -> 0 | AG32: =IF((AF32-AF31)<0,"0",(AF32-AF31)) -> 0 | AH32: =AI31 -> 0 | AJ32: =IF((AI32-AI31)<0,"0",(AI32-AI31)) -> 0 | AK32: =AL31 -> 0 | AM32: =IF((AL32-AL31)<0,"0",(AL32-AL31)) -> 0 | AN32: =U32+X32+AA32+AD32+AG32+AJ32+AM32 -> 0
A33: =Gen!A38 -> 43889 | C33: =D32 -> 0 | E33: =IF((D33-D32)<0,"0",(D33-D32)) -> 0 | F33: =G32 -> 0 | H33: =IF((G33-G32)<0,"0",(G33-G32)) -> 0 | I33: =J32 -> 0 | K33: =IF((J33-J32)<0,"0",(J33-J32)) -> 0 | L33: =M32 -> 0 | N33: =IF((M33-M32)<0,"0",(M33-M32)) -> 0 | O33: =P32 -> 0 | Q33: =IF((P33-P32)<0,"0",(P33-P32)) -> 0 | S33: =T32 -> 0 | U33: =IF((T33-T32)<0,"0",(T33-T32)) -> 0 | V33: =W32 -> 0 | X33: =IF((W33-W32)<0,"0",(W33-W32)) -> 0 | Y33: =Z32 -> 0 | AA33: =IF((Z33-Z32)<0,"0",(Z33-Z32)) -> 0 | AB33: =AC32 -> 0 | AD33: =IF((AC33-AC32)<0,"0",(AC33-AC32)) -> 0 | AE33: =AF32 -> 0 | AG33: =IF((AF33-AF32)<0,"0",(AF33-AF32)) -> 0 | AH33: =AI32 -> 0 | AJ33: =IF((AI33-AI32)<0,"0",(AI33-AI32)) -> 0 | AK33: =AL32 -> 0 | AM33: =IF((AL33-AL32)<0,"0",(AL33-AL32)) -> 0 | AN33: =U33+X33+AA33+AD33+AG33+AJ33+AM33 -> 0
A34: =Gen!A39 -> 43890 | C34: =D33 -> 0 | E34: =IF((D34-D33)<0,"0",(D34-D33)) -> 0 | F34: =G33 -> 0 | H34: =IF((G34-G33)<0,"0",(G34-G33)) -> 0 | I34: =J33 -> 0 | K34: =IF((J34-J33)<0,"0",(J34-J33)) -> 0 | L34: =M33 -> 0 | N34: =IF((M34-M33)<0,"0",(M34-M33)) -> 0 | O34: =P33 -> 0 | Q34: =IF((P34-P33)<0,"0",(P34-P33)) -> 0 | S34: =T33 -> 0 | U34: =IF((T34-T33)<0,"0",(T34-T33)) -> 0 | V34: =W33 -> 0 | X34: =IF((W34-W33)<0,"0",(W34-W33)) -> 0 | Y34: =Z33 -> 0 | AA34: =IF((Z34-Z33)<0,"0",(Z34-Z33)) -> 0 | AB34: =AC33 -> 0 | AD34: =IF((AC34-AC33)<0,"0",(AC34-AC33)) -> 0 | AE34: =AF33 -> 0 | AG34: =IF((AF34-AF33)<0,"0",(AF34-AF33)) -> 0 | AH34: =AI33 -> 0 | AJ34: =IF((AI34-AI33)<0,"0",(AI34-AI33)) -> 0 | AK34: =AL33 -> 0 | AM34: =IF((AL34-AL33)<0,"0",(AL34-AL33)) -> 0 | AN34: =U34+X34+AA34+AD34+AG34+AJ34+AM34 -> 0
A35: =Gen!A40 -> 43891 | C35: =D34 -> 0 | E35: =IF((D35-D34)<0,"0",(D35-D34)) -> 0 | F35: =G34 -> 0 | H35: =IF((G35-G34)<0,"0",(G35-G34)) -> 0 | I35: =J34 -> 0 | K35: =IF((J35-J34)<0,"0",(J35-J34)) -> 0 | L35: =M34 -> 0 | N35: =IF((M35-M34)<0,"0",(M35-M34)) -> 0 | O35: =P34 -> 0 | Q35: =IF((P35-P34)<0,"0",(P35-P34)) -> 0 | S35: =T34 -> 0 | U35: =IF((T35-T34)<0,"0",(T35-T34)) -> 0 | V35: =W34 -> 0 | X35: =IF((W35-W34)<0,"0",(W35-W34)) -> 0 | Y35: =Z34 -> 0 | AA35: =IF((Z35-Z34)<0,"0",(Z35-Z34)) -> 0 | AB35: =AC34 -> 0 | AD35: =IF((AC35-AC34)<0,"0",(AC35-AC34)) -> 0 | AE35: =AF34 -> 0 | AG35: =IF((AF35-AF34)<0,"0",(AF35-AF34)) -> 0 | AH35: =AI34 -> 0 | AJ35: =IF((AI35-AI34)<0,"0",(AI35-AI34)) -> 0 | AK35: =AL34 -> 0 | AM35: =IF((AL35-AL34)<0,"0",(AL35-AL34)) -> 0 | AN35: =U35+X35+AA35+AD35+AG35+AJ35+AM35 -> 0
A36: =Gen!A41 -> 43892 | C36: =D35 -> 0 | E36: =IF((D36-D35)<0,"0",(D36-D35)) -> 0 | F36: =G35 -> 0 | H36: =IF((G36-G35)<0,"0",(G36-G35)) -> 0 | I36: =J35 -> 0 | K36: =IF((J36-J35)<0,"0",(J36-J35)) -> 0 | L36: =M35 -> 0 | N36: =IF((M36-M35)<0,"0",(M36-M35)) -> 0 | O36: =P35 -> 0 | Q36: =IF((P36-P35)<0,"0",(P36-P35)) -> 0 | S36: =T35 -> 0 | U36: =IF((T36-T35)<0,"0",(T36-T35)) -> 0 | V36: =W35 -> 0 | X36: =IF((W36-W35)<0,"0",(W36-W35)) -> 0 | Y36: =Z35 -> 0 | AA36: =IF((Z36-Z35)<0,"0",(Z36-Z35)) -> 0 | AB36: =AC35 -> 0 | AD36: =IF((AC36-AC35)<0,"0",(AC36-AC35)) -> 0 | AE36: =AF35 -> 0 | AG36: =IF((AF36-AF35)<0,"0",(AF36-AF35)) -> 0 | AH36: =AI35 -> 0 | AJ36: =IF((AI36-AI35)<0,"0",(AI36-AI35)) -> 0 | AK36: =AL35 -> 0 | AM36: =IF((AL36-AL35)<0,"0",(AL36-AL35)) -> 0 | AN36: =U36+X36+AA36+AD36+AG36+AJ36+AM36 -> 0
A37: =Gen!A42 -> 43893 | C37: =D36 -> 0 | E37: =IF((D37-D36)<0,"0",(D37-D36)) -> 0 | F37: =G36 -> 0 | H37: =IF((G37-G36)<0,"0",(G37-G36)) -> 0 | I37: =J36 -> 0 | K37: =IF((J37-J36)<0,"0",(J37-J36)) -> 0 | L37: =M36 -> 0 | N37: =IF((M37-M36)<0,"0",(M37-M36)) -> 0 | O37: =P36 -> 0 | Q37: =IF((P37-P36)<0,"0",(P37-P36)) -> 0 | S37: =T36 -> 0 | U37: =IF((T37-T36)<0,"0",(T37-T36)) -> 0 | V37: =W36 -> 0 | X37: =IF((W37-W36)<0,"0",(W37-W36)) -> 0 | Y37: =Z36 -> 0 | AA37: =IF((Z37-Z36)<0,"0",(Z37-Z36)) -> 0 | AB37: =AC36 -> 0 | AD37: =IF((AC37-AC36)<0,"0",(AC37-AC36)) -> 0 | AE37: =AF36 -> 0 | AG37: =IF((AF37-AF36)<0,"0",(AF37-AF36)) -> 0 | AH37: =AI36 -> 0 | AJ37: =IF((AI37-AI36)<0,"0",(AI37-AI36)) -> 0 | AK37: =AL36 -> 0 | AM37: =IF((AL37-AL36)<0,"0",(AL37-AL36)) -> 0 | AN37: =U38+X38+AA38+AD38+AG38+AJ38+AM38 -> 330
C38: TOTAL USAGE | E38: =SUM(E6:E36) -> 1079 | F38: KL | H38: =SUM(H6:H37) -> 0 | K38: =SUM(K6:K37) -> 32 | N38: =M38-M37 -> 0 | Q38: =P38-O38 -> 0 | R38: =E38 -> 1079 | U38: =SUM(U6:U37) -> 330 | AN38: =U38+X38+AA38+AD38+AG38+AJ38+AM38 -> 330
C42: WATER TANK LEVEL
C43: RAW WATER TANK NO.1 | E43: RAW WATER TANK NO.2 | G43: TREATED WATER TANK | I43: TREATED -HILL TANK | K43: TOTAL WATER AVAILABLE
C44: CAPACITY 217 m³ | E44: CAPACITY 92 m³ | G44: CAPACITY 146 m³ | I44: CAPACITY 213 m³
C45: cm | D45: m³ | E45: cm | F45: m³ | H45: m³ | I45: cm | J45: m³ | K45: m³
A46: =Gen!A11 -> 43862 | C46: 295 | D46: =C46*217/300 -> 213.38333 | E46: 290 | F46: =E46*92/305 -> 87.47541 | G46: 200 | H46: =G46*146/383 -> 76.240209 | I46: 285 | J46: =I46*213/308 -> 197.09416 | K46: =D46+F46+H46+J46 -> 574.19311
A47: =Gen!A12 -> 43863 | C47: 265 | D47: =C47*217/300 -> 191.68333 | E47: 235 | F47: =E47*92/305 -> 70.885246 | G47: 185 | H47: =G47*146/383 -> 70.522193 | I47: 290 | J47: =I47*213/308 -> 200.55195 | K47: =D47+F47+H47+J47 -> 533.64272
A48: =Gen!A13 -> 43864 | C48: 195 | D48: =C48*217/300 -> 141.05 | E48: 155 | F48: =E48*92/305 -> 46.754098 | G48: 140 | H48: =G48*146/383 -> 53.368146 | I48: 288 | J48: =I48*213/308 -> 199.16883 | K48: =D48+F48+H48+J48 -> 440.34108
A49: =Gen!A14 -> 43865 | C49: 116 | D49: =C49*217/300 -> 83.906667 | E49: 80 | F49: =E49*92/305 -> 24.131148 | G49: 80 | H49: =G49*146/383 -> 30.496084 | I49: 290 | J49: =I49*213/308 -> 200.55195 | K49: =D49+F49+H49+J49 -> 339.08585
A50: =Gen!A15 -> 43866 | C50: 181 | D50: =C50*217/300 -> 130.92333 | E50: 145 | F50: =E50*92/305 -> 43.737705 | G50: 222 | H50: =G50*146/383 -> 84.626632 | I50: 180 | J50: =I50*213/308 -> 124.48052 | K50: =D50+F50+H50+J50 -> 383.76819
A51: =Gen!A16 -> 43867 | C51: 206 | D51: =C51*217/300 -> 149.00667 | E51: 170 | F51: =E51*92/305 -> 51.278689 | G51: 110 | H51: =G51*146/383 -> 41.932115 | I51: 185 | J51: =I51*213/308 -> 127.93831 | K51: =D51+F51+H51+J51 -> 370.15578
A52: =Gen!A17 -> 43868 | C52: 201 | D52: =C52*217/300 -> 145.39 | E52: 165 | F52: =E52*92/305 -> 49.770492 | G52: 185 | H52: =G52*146/383 -> 70.522193 | I52: 180 | J52: =I52*213/308 -> 124.48052 | K52: =D52+F52+H52+J52 -> 390.1632
A53: =Gen!A18 -> 43869 | C53: 151 | D53: =C53*217/300 -> 109.22333 | E53: 115 | F53: =E53*92/305 -> 34.688525 | G53: 145 | H53: =G53*146/383 -> 55.274151 | I53: 188 | J53: =I53*213/308 -> 130.01299 | K53: =D53+F53+H53+J53 -> 329.199
A54: =Gen!A19 -> 43870 | C54: 176 | D54: =C54*217/300 -> 127.30667 | E54: 140 | F54: =E54*92/305 -> 42.229508 | G54: 223 | H54: =G54*146/383 -> 85.007833 | I54: 185 | J54: =I54*213/308 -> 127.93831 | K54: =D54+F54+H54+J54 -> 382.48232
A55: =Gen!A20 -> 43871 | D55: =C55*217/300 -> 0 | F55: =E55*92/305 -> 0 | H55: =G55*146/383 -> 0 | J55: =I55*213/308 -> 0 | K55: =D55+F55+H55+J55 -> 0
A56: =Gen!A21 -> 43872 | D56: =C56*217/300 -> 0 | F56: =E56*92/305 -> 0 | H56: =G56*146/383 -> 0 | J56: =I56*213/308 -> 0 | K56: =D56+F56+H56+J56 -> 0
A57: =Gen!A22 -> 43873 | D57: =C57*217/300 -> 0 | F57: =E57*92/305 -> 0 | H57: =G57*146/383 -> 0 | J57: =I57*213/308 -> 0 | K57: =D57+F57+H57+J57 -> 0
A58: =Gen!A23 -> 43874 | D58: =C58*217/300 -> 0 | F58: =E58*92/305 -> 0 | H58: =G58*146/383 -> 0 | J58: =I58*213/308 -> 0 | K58: =D58+F58+H58+J58 -> 0
A59: =Gen!A24 -> 43875 | D59: =C59*217/300 -> 0 | F59: =E59*92/305 -> 0 | H59: =G59*146/383 -> 0 | J59: =I59*213/308 -> 0 | K59: =D59+F59+H59+J59 -> 0
A60: =Gen!A25 -> 43876 | D60: =C60*217/300 -> 0 | F60: =E60*92/305 -> 0 | H60: =G60*146/383 -> 0 | J60: =I60*213/308 -> 0 | K60: =D60+F60+H60+J60 -> 0
A61: =Gen!A26 -> 43877 | D61: =C61*217/300 -> 0 | F61: =E61*92/305 -> 0 | H61: =G61*146/383 -> 0 | J61: =I61*213/308 -> 0 | K61: =D61+F61+H61+J61 -> 0
A62: =Gen!A27 -> 43878 | D62: =C62*217/300 -> 0 | F62: =E62*92/305 -> 0 | H62: =G62*146/383 -> 0 | J62: =I62*213/308 -> 0 | K62: =D62+F62+H62+J62 -> 0
A63: =Gen!A28 -> 43879 | D63: =C63*217/300 -> 0 | F63: =E63*92/305 -> 0 | H63: =G63*146/383 -> 0 | J63: =I63*213/308 -> 0 | K63: =D63+F63+H63+J63 -> 0
A64: =Gen!A29 -> 43880 | D64: =C64*217/300 -> 0 | F64: =E64*92/305 -> 0 | H64: =G64*146/383 -> 0 | J64: =I64*213/308 -> 0 | K64: =D64+F64+H64+J64 -> 0
A65: =Gen!A30 -> 43881 | D65: =C65*217/300 -> 0 | F65: =E65*92/305 -> 0 | H65: =G65*146/383 -> 0 | J65: =I65*213/308 -> 0 | K65: =D65+F65+H65+J65 -> 0
A66: =Gen!A31 -> 43882 | D66: =C66*217/300 -> 0 | F66: =E66*92/305 -> 0 | H66: =G66*146/383 -> 0 | J66: =I66*213/308 -> 0 | K66: =D66+F66+H66+J66 -> 0
... A77: =Gen!A42 -> 43893 | D77: =C77*217/300 -> 0 | F77: =E77*92/305 -> 0 | H77: =G77*146/383 -> 0 | J77: =I77*213/308 -> 0 | K77: =D77+F77+H77+J77 -> 0
A78: =Gen!A43 -> BF

Sheet Water_Graph 
A1: Date | B1: Usage | C1: Occ %
A2: =SUM([1]Gen!A11) -> 43739 | B2: =SUM('[1]Water-Meter'!R10) -> #REF! | C2: =SUM([1]Gen!B11) -> 0.623
A3: =SUM([1]Gen!A12) -> 43740 | B3: =SUM('[1]Water-Meter'!R11) -> #REF! | C3: =SUM([1]Gen!B12) -> 0.779
A4: =SUM([1]Gen!A13) -> 43741 | B4: =SUM('[1]Water-Meter'!R12) -> #REF! | C4: =SUM([1]Gen!B13) -> 0.532
A5: =SUM([1]Gen!A14) -> 43742 | B5: =SUM('[1]Water-Meter'!R13) -> #REF! | C5: =SUM([1]Gen!B14) -> 0.61
A6: =SUM([1]Gen!A15) -> 43743 | B6: =SUM('[1]Water-Meter'!R14) -> #REF! | C6: =SUM([1]Gen!B15) -> 0.688
A7: =SUM([1]Gen!A16) -> 43744 | B7: =SUM('[1]Water-Meter'!R15) -> #REF! | C7: =SUM([1]Gen!B16) -> 0.532
A8: =SUM([1]Gen!A17) -> 43745 | B8: =SUM('[1]Water-Meter'!R16) -> #REF! | C8: =SUM([1]Gen!B17) -> 0.753
A9: =SUM([1]Gen!A18) -> 43746 | B9: =SUM('[1]Water-Meter'!R17) -> #REF! | C9: =SUM([1]Gen!B18) -> 0.156
A10: =SUM([1]Gen!A19) -> 43747 | B10: =SUM('[1]Water-Meter'!R18) -> #REF! | C10: =SUM([1]Gen!B19) -> 0.442
A11: =SUM([1]Gen!A20) -> 43748 | B11: =SUM('[1]Water-Meter'!R19) -> #REF! | C11: =SUM([1]Gen!B20) -> 0.325
A12: =SUM([1]Gen!A21) -> 43749 | B12: =SUM('[1]Water-Meter'!R20) -> #REF! | C12: =SUM([1]Gen!B21) -> 0.455
A13: =SUM([1]Gen!A22) -> 43750 | B13: =SUM('[1]Water-Meter'!R21) -> #REF! | C13: =SUM([1]Gen!B22) -> 0.416
... A32: =SUM([1]Gen!A41) -> 43769 | B32: =SUM('[1]Water-Meter'!R40) -> #REF! | C32: =SUM([1]Gen!B41) -> #REF!

Sheet Sheet1
A2: Generator and Diseal Summry Report JANUARY 2016 | Q2: 2209.85 | R2: Diesel Cost | S2: Rate$ | T2: 1584
M3: % of Gas balance in Tank | P3: % of Dieasel balance in Tank | Q3: HLP Cost (TSH) | V3: Total Cost (TSH) | W3: Consumption Guest Occ% | AA3: Budget Cost Per Room occ
A4: Date | B4: Gen Set Hours Working | C4: Occ% | D4: Total OCC Room | E4: Guest Room Occ | F4: Total Kwh Generated | G4: Diseal consumed by Gen (Ltrs) | H4: Diseal consumed by Veichel (Ltrs) | I4: Total diseal consumed (Ltrs) | J4: Balance stock of Diseal (Ltrs) | K4: Water consumed | L4: Gas consumed (KG) | M4: 3 | N4: 2 | O4: 1 | Q4: Electricity | R4: Cost per Room Total OOC Usd | S4: Cost per Room Guest OOC Usd | T4: Water | U4: Gas
A5: =SUM([1]Gen!A11) -> 43739 | B5: 0 | C5: =SUM([1]Gen!B11) -> 0.623 | D5: =SUM(77*C5) -> 47.971 | F5: =[1]Gen!T11 -> 5669 | G5: =[1]Gen!S11 -> 2179.48 | H5: =[1]Gen!#REF! -> #REF! | I5: =SUM(G5:H5) -> #REF! | J5: =[1]Gen!AT11 -> 47806.65 | K5: ='[1]Water-Meter'!E10 -> 114 | L5: =#REF! -> #REF! | M5: =#REF! -> #REF! | N5: =#REF! -> #REF! | O5: =#REF! -> #REF! | P5: =J5/52000 -> 0.91935865 | Q5: =I5*Q2 -> #REF! | R5: =SUM(Q5/D5)/X5 -> #REF! | S5: =SUM(Q5/E5)/X5 -> #REF! | T5: =(K5*102)/X5 -> 7.3409091 | U5: =SUM(L5*1963)/X5 -> #REF! | V5: =SUM(Q5+T5+U5) -> #REF! | W5: =SUM(V5/E5)/T2 -> #REF! | X5: =SUM(T2) -> 1584 | Y5: 106 | Z5: =SUM(Y5-S5) -> #REF! | AA5: 106
A6: =SUM([1]Gen!A12) -> 43740 | B6: 0 | C6: =SUM([1]Gen!B12) -> 0.779 | D6: =SUM(77*C6) -> 59.983 | F6: =[1]Gen!T12 -> 6159 | G6: =[1]Gen!S12 -> 2472.85 | H6: =[1]Gen!#REF! -> #REF! | I6: =SUM(G6:H6) -> #REF! | J6: =[1]Gen!AT12 -> 45423.89 | K6: ='[1]Water-Meter'!E11 -> 126 | L6: =#REF! -> #REF! | M6: =#REF! -> #REF! | N6: =#REF! -> #REF! | O6: =#REF! -> #REF! | P6: =J6/52000 -> 0.87353635 | Q6: =I6*Q2 -> #REF! | R6: =SUM(Q6/D6)/X6 -> #REF! | S6: =SUM(Q6/E6)/X6 -> #REF! | T6: =(K6*102)/X6 -> 8.1136364 | U6: =SUM(L6*1963)/X6 -> #REF! | V6: =SUM(Q6+T6+U6) -> #REF! | W6: =SUM(V6/E6)/T2 -> #REF! | X6: =SUM(X5) -> 1584 | Y6: 106 | Z6: =SUM(Y6-S6) -> #REF!
A7: =SUM([1]Gen!A13) -> 43741 | B7: 0 | C7: =SUM([1]Gen!B13) -> 0.532 | D7: =SUM(77*C7) -> 40.964 | F7: =[1]Gen!T13 -> 6580 | G7: =[1]Gen!S13 -> 2554.39 | H7: =[1]Gen!#REF! -> #REF! | I7: =SUM(G7:H7) -> #REF! | J7: =[1]Gen!AT13 -> 42919.59 | K7: ='[1]Water-Meter'!E12 -> 116 | L7: =#REF! -> #REF! | M7: =#REF! -> #REF! | N7: =#REF! -> #REF! | O7: =#REF! -> #REF! | P7: =J7/52000 -> 0.82537673 | Q7: =I7*Q2 -> #REF! | R7: =SUM(Q7/D7)/X7 -> #REF! | S7: =SUM(Q7/E7)/X7 -> #REF! | T7: =(K7*102)/X7 -> 7.469697 | U7: =SUM(L7*1963)/X7 -> #REF! | V7: =SUM(Q7+T7+U7) -> #REF! | W7: =SUM(V7/E7)/T2 -> #REF! | X7: =SUM(X6) -> 1584 | Y7: 106 | Z7: =SUM(Y7-S7) -> #REF!
A8: =SUM([1]Gen!A14) -> 43742 | B8: 0 | C8: =SUM([1]Gen!B14) -> 0.61 | D8: =SUM(77*C8) -> 46.97 | F8: =[1]Gen!T14 -> 6223 | G8: =[1]Gen!S14 -> 2441.42 | H8: =[1]Gen!AJ9 -> #REF! | I8: =SUM(G8:H8) -> #REF! | J8: =[1]Gen!AT14 -> 40258.94 | K8: ='[1]Water-Meter'!E13 -> 120 | L8: =#REF! -> #REF! | M8: =#REF! -> #REF! | N8: =#REF! -> #REF! | O8: =#REF! -> #REF! | P8: =J8/52000 -> 0.77421038 | Q8: =I8*Q2 -> #REF! | R8: =SUM(Q8/D8)/X8 -> #REF! | S8: =SUM(Q8/E8)/X8 -> #REF! | T8: =(K8*102)/X8 -> 7.7272727 | U8: =SUM(L8*1963)/X8 -> #REF! | V8: =SUM(Q8+T8+U8) -> #REF! | W8: =SUM(V8/E8)/T2 -> #REF! | X8: =SUM(X7) -> 1584 | Y8: 106 | Z8: =SUM(Y8-S8) -> #REF!
A9: =SUM([1]Gen!A15) -> 43743 | B9: 0 | C9: =SUM([1]Gen!B15) -> 0.688 | D9: =SUM(77*C9) -> 52.976 | F9: =[1]Gen!T15 -> 5984 | G9: =[1]Gen!S15 -> 2338.36 | H9: =[1]Gen!AJ10 -> 0 | I9: =SUM(G9:H9) -> 2338.36 | J9: =[1]Gen!AT15 -> 37525.21 | K9: ='[1]Water-Meter'!E14 -> 107 | L9: =#REF! -> #REF! | M9: =#REF! -> #REF! | N9: =#REF! -> #REF! | O9: =#REF! -> #REF! | P9: =J9/52000 -> 0.72163865 | Q9: =I9*Q2 -> 5167424.8 | R9: =SUM(Q9/D9)/X9 -> 61.58002 | S9: =SUM(Q9/E9)/X9 -> #DIV/0! | T9: =(K9*102)/X9 -> 6.8901515 | U9: =SUM(L9*1963)/X9 -> #REF! | V9: =SUM(Q9+T9+U9) -> #REF! | W9: =SUM(V9/E9)/T2 -> #REF! | X9: =SUM(X8) -> 1584 | Y9: 106 | Z9: =SUM(Y9-S9) -> #DIV/0!
A10: =SUM([1]Gen!A16) -> 43744 | B10: 0 | C10: =SUM([1]Gen!B16) -> 0.532 | D10: =SUM(77*C10) -> 40.964 | F10: =[1]Gen!T16 -> 6103 | G10: =[1]Gen!S16 -> 2478.9 | H10: =[1]Gen!#REF! -> #REF! | I10: =SUM(G10:H10) -> #REF! | J10: =[1]Gen!AT16 -> 35107.69 | K10: ='[1]Water-Meter'!E15 -> 123 | L10: =#REF! -> #REF! | M10: =#REF! -> #REF! | N10: =#REF! -> #REF! | O10: =#REF! -> #REF! | P10: =J10/52000 -> 0.67514788 | Q10: =I10*Q2 -> #REF! | R10: =SUM(Q10/D10)/X10 -> #REF! | S10: =SUM(Q10/E10)/X10 -> #REF! | T10: =(K10*102)/X10 -> 7.9204545 | U10: =SUM(L10*1963)/X10 -> #REF! | V10: =SUM(Q10+T10+U10) -> #REF! | W10: =SUM(V10/E10)/T2 -> #REF! | X10: =SUM(X9) -> 1584 | Y10: 106 | Z10: =SUM(Y10-S10) -> #REF!
A11: =SUM([1]Gen!A17) -> 43745 | B11: 0 | C11: =SUM([1]Gen!B17) -> 0.753 | D11: =SUM(77*C11) -> 57.981 | F11: =[1]Gen!T17 -> 5576 | G11: =[1]Gen!S17 -> 2276.44 | H11: =[1]Gen!AJ25 -> 80.56 | I11: =SUM(G11:H11) -> 2357 | J11: =[1]Gen!AT17 -> 47513.14 | K11: ='[1]Water-Meter'!E16 -> 112 | L11: =#REF! -> #REF! | M11: =#REF! -> #REF! | N11: =#REF! -> #REF! | O11: =#REF! -> #REF! | P11: =J11/52000 -> 0.91371423 | Q11: =I11*Q2 -> 5208616.5 | R11: =SUM(Q11/D11)/X11 -> 56.712854 | S11: =SUM(Q11/E11)/X11 -> #DIV/0! | T11: =(K11*102)/X11 -> 7.2121212 | U11: =SUM(L11*1963)/X11 -> #REF! | V11: =SUM(Q11+T11+U11) -> #REF! | W11: =SUM(V11/E11)/T2 -> #REF! | X11: =SUM(X10) -> 1584 | Y11: 106 | Z11: =SUM(Y11-S11) -> #DIV/0!
A12: =SUM([1]Gen!A18) -> 43746 | B12: 0 | C12: =SUM([1]Gen!B18) -> 0.156 | D12: =SUM(77*C12) -> 12.012 | F12: =[1]Gen!T18 -> 5532 | G12: =[1]Gen!S18 -> 2242.4 | H12: =[1]Gen!#REF! -> #REF! | I12: =SUM(G12:H12) -> #REF! | J12: =[1]Gen!AT18 -> 45161.89 | K12: ='[1]Water-Meter'!E17 -> 128 | L12: =#REF! -> #REF! | M12: =#REF! -> #REF! | N12: =#REF! -> #REF! | O12: =#REF! -> #REF! | P12: =J12/52000 -> 0.86849788 | Q12: =I12*Q2 -> #REF! | R12: =SUM(Q12/D12)/X12 -> #REF! | S12: =SUM(Q12/E12)/X12 -> #REF! | T12: =(K12*102)/X12 -> 8.2424242 | U12: =SUM(L12*1963)/X12 -> #REF! | V12: =SUM(Q12+T12+U12) -> #REF! | W12: =SUM(V12/E12)/T2 -> #REF! | X12: =SUM(X11) -> 1584 | Y12: 106 | Z12: =SUM(Y12-S12) -> #REF!
A13: =SUM([1]Gen!A19) -> 43747 | B13: 0 | C13: =SUM([1]Gen!B19) -> 0.442 | D13: =SUM(77*C13) -> 34.034 | F13: =[1]Gen!T19 -> 6233 | G13: =[1]Gen!S19 -> 2430.27 | H13: =[1]Gen!#REF! -> #REF! | I13: =SUM(G13:H13) -> #REF! | J13: =[1]Gen!AT19 -> 42825.48 | K13: ='[1]Water-Meter'!E18 -> 114 | L13: =#REF! -> #REF! | M13: =#REF! -> #REF! | N13: =#REF! -> #REF! | O13: =#REF! -> #REF! | P13: =J13/52000 -> 0.82356692 | Q13: =I13*Q2 -> #REF! | R13: =SUM(Q13/D13)/X13 -> #REF! | S13: =SUM(Q13/E13)/X13 -> #REF! | T13: =(K13*102)/X13 -> 7.3409091 | U13: =SUM(L13*1963)/X13 -> #REF! | V13: =SUM(Q13+T13+U13) -> #REF! | W13: =SUM(V13/E13)/T2 -> #REF! | X13: =SUM(X12) -> 1584 | Y13: 106 | Z13: =SUM(Y13-S13) -> #REF!
A14: =SUM([1]Gen!A20) -> 43748 | B14: 0 | C14: =SUM([1]Gen!B20) -> 0.325 | D14: =SUM(77*C14) -> 25.025 | F14: =[1]Gen!T20 -> 6063 | G14: =[1]Gen!S20 -> 2463.77 | H14: =[1]Gen!#REF! -> #REF! | I14: =SUM(G14:H14) -> #REF! | J14: =[1]Gen!AT20 -> 40110.38 | K14: ='[1]Water-Meter'!E19 -> 119 | L14: =#REF! -> #REF! | M14: =#REF! -> #REF! | N14: =#REF! -> #REF! | O14: =#REF! -> #REF! | P14: =J14/52000 -> 0.77135346 | Q14: =I14*Q2 -> #REF! | R14: =SUM(Q14/D14)/X14 -> #REF! | S14: =SUM(Q14/E14)/X14 -> #REF! | T14: =(K14*102)/X14 -> 7.6628788 | U14: =SUM(L14*1963)/X14 -> #REF! | V14: =SUM(Q14+T14+U14) -> #REF! | W14: =SUM(V14/E14)/T2 -> #REF! | X14: =SUM(X13) -> 1584 | Y14: 106 | Z14: =SUM(Y14-S14) -> #REF!
A15: =SUM([1]Gen!A21) -> 43749 | B15: 0 | C15: =SUM([1]Gen!B21) -> 0.455 | D15: =SUM(77*C15) -> 35.035 | F15: =[1]Gen!T21 -> 5967 | G15: =[1]Gen!S21 -> 2310.19 | H15: =[1]Gen!#REF! -> #REF! | I15: =SUM(G15:H15) -> #REF! | J15: =[1]Gen!AT21 -> 37540.57 | K15: ='[1]Water-Meter'!E20 -> 128 | L15: =#REF! -> #REF! | M15: =#REF! -> #REF! | N15: =#REF! -> #REF! | O15: =#REF! -> #REF! | P15: =J15/52000 -> 0.72193404 | Q15: =I15*Q2 -> #REF! | R15: =SUM(Q15/D15)/X15 -> #REF! | S15: =SUM(Q15/E15)/X15 -> #REF! | T15: =(K15*102)/X15 -> 8.2424242 | U15: =SUM(L15*1963)/X15 -> #REF! | V15: =SUM(Q15+T15+U15) -> #REF! | W15: =SUM(V15/E15)/T2 -> #REF! | X15: =SUM(X14) -> 1584 | Y15: 106 | Z15: =SUM(Y15-S15) -> #REF!
A16: =SUM([1]Gen!A22) -> 43750 | B16: 0 | C16: =SUM([1]Gen!B22) -> 0.416 | D16: =SUM(77*C16) -> 32.032 | F16: =[1]Gen!T22 -> 5863 | G16: =[1]Gen!S22 -> 2429.17 | H16: =[1]Gen!#REF! -> #REF! | I16: =SUM(G16:H16) -> #REF! | J16: =[1]Gen!AT22 -> 34967.29 | K16: ='[1]Water-Meter'!E21 -> 127 | L16: =#REF! -> #REF! | M16: =#REF! -> #REF! | N16: =#REF! -> #REF! | O16: =#REF! -> #REF! | P16: =J16/52000 -> 0.67244788 | Q16: =I16*Q2 -> #REF! | R16: =SUM(Q16/D16)/X16 -> #REF! | S16: =SUM(Q16/E16)/X16 -> #REF! | T16: =(K16*102)/X16 -> 8.1780303 | U16: =SUM(L16*1963)/X16 -> #REF! | V16: =SUM(Q16+T16+U16) -> #REF! | W16: =SUM(V16/E16)/T2 -> #REF! | X16: =SUM(X15) -> 1584 | Y16: 106 | Z16: =SUM(Y16-S16) -> #REF!
A17: =SUM([1]Gen!A23) -> 43751 | B17: 0 | C17: =SUM([1]Gen!B23) -> 0.39 | D17: =SUM(77*C17) -> 30.03 | F17: =[1]Gen!T23 -> 5720 | G17: =[1]Gen!S23 -> 2249.53 | H17: =[1]Gen!#REF! -> #REF! | I17: =SUM(G17:H17) -> #REF! | J17: =[1]Gen!AT23 -> 32228.76 | K17: ='[1]Water-Meter'!E22 -> 122 | L17: =#REF! -> #REF! | M17: =#REF! -> #REF! | N17: =#REF! -> #REF! | O17: =#REF! -> #REF! | P17: =J17/52000 -> 0.61978385 | Q17: =I17*Q2 -> #REF! | R17: =SUM(Q17/D17)/X17 -> #REF! | S17: =SUM(Q17/E17)/X17 -> #REF! | T17: =(K17*102)/X17 -> 7.8560606 | U17: =SUM(L17*1963)/X17 -> #REF! | V17: =SUM(Q17+T17+U17) -> #REF! | W17: =SUM(V17/E17)/T2 -> #REF! | X17: =SUM(X16) -> 1584 | Y17: 106 | Z17: =SUM(Y17-S17) -> #REF!
A18: =SUM([1]Gen!A24) -> 43752 | B18: 0 | C18: =SUM([1]Gen!B24) -> 0.636 | D18: =SUM(77*C18) -> 48.972 | F18: =[1]Gen!T24 -> 6195 | G18: =[1]Gen!S24 -> 2420.41 | H18: =[1]Gen!AJ27 -> 597.9 | I18: =SUM(G18:H18) -> 3018.31 | J18: =[1]Gen!AT24 -> 29915.45 | K18: 0 | L18: =#REF! -> #REF! | M18: =#REF! -> #REF! | N18: =#REF! -> #REF! | O18: =#REF! -> #REF! | P18: =J18/52000 -> 0.57529712 | Q18: =I18*Q2 -> 6670012.4 | R18: =SUM(Q18/D18)/X18 -> 85.985183 | S18: =SUM(Q18/E18)/X18 -> #DIV/0! | T18: =(K18*102)/X18 -> 0 | U18: =SUM(L18*1963)/X18 -> #REF! | V18: =SUM(Q18+T18+U18) -> #REF! | W18: =SUM(V18/E18)/T2 -> #REF! | X18: =SUM(X17) -> 1584 | Y18: 106 | Z18: =SUM(Y18-S18) -> #DIV/0!
A19: =SUM([1]Gen!A25) -> 43753 | B19: 0 | C19: =SUM([1]Gen!B25) -> 0.844 | D19: =SUM(77*C19) -> 64.988 | F19: =[1]Gen!T25 -> 6450 | G19: =[1]Gen!S25 -> 2670.31 | H19: =[1]Gen!AJ28 -> 227.73 | I19: =SUM(G19:H19) -> 2898.04 | J19: =[1]Gen!AT25 -> 42248.24 | K19: ='[1]Water-Meter'!E24 -> 104 | L19: =#REF! -> #REF! | M19: =#REF! -> #REF! | N19: =#REF! -> #REF! | O19: =#REF! -> #REF! | P19: =J19/52000 -> 0.81246615 | Q19: =I19*Q2 -> 6404233.7 | R19: =SUM(Q19/D19)/X19 -> 62.212667 | S19: =SUM(Q19/E19)/X19 -> #DIV/0! | T19: =(K19*102)/X19 -> 6.6969697 | U19: =SUM(L19*1963)/X19 -> #REF! | V19: =SUM(Q19+T19+U19) -> #REF! | W19: =SUM(V19/E19)/T2 -> #REF! | X19: =SUM(X18) -> 1584 | Y19: 106 | Z19: =SUM(Y19-S19) -> #DIV/0!
A20: =SUM([1]Gen!A26) -> 43754 | B20: 0 | C20: =SUM([1]Gen!B26) -> 0.818 | D20: =SUM(77*C20) -> 62.986 | F20: =[1]Gen!T26 -> 6915 | G20: =[1]Gen!S26 -> 2741.7 | H20: =[1]Gen!AJ29 -> 88.29 | I20: =SUM(G20:H20) -> 2829.99 | J20: =[1]Gen!AT26 -> 39497.37 | K20: ='[1]Water-Meter'!E25 -> 100 | L20: =#REF! -> #REF! | M20: =#REF! -> #REF! | N20: =#REF! -> #REF! | O20: =#REF! -> #REF! | P20: =J20/52000 -> 0.75956481 | Q20: =I20*Q2 -> 6253853.4 | R20: =SUM(Q20/D20)/X20 -> 62.682815 | S20: =SUM(Q20/E20)/X20 -> #DIV/0! | T20: =(K20*102)/X20 -> 6.4393939 | U20: =SUM(L20*1963)/X20 -> #REF! | V20: =SUM(Q20+T20+U20) -> #REF! | W20: =SUM(V20/E20)/T2 -> #REF! | X20: =SUM(X19) -> 1584 | Y20: 106 | Z20: =SUM(Y20-S20) -> #DIV/0!
A21: =SUM([1]Gen!A27) -> 43755 | B21: 0 | C21: =SUM([1]Gen!B27) -> 0.208 | D21: =SUM(77*C21) -> 16.016 | F21: =[1]Gen!T27 -> 5962 | G21: =[1]Gen!S27 -> 2321.11 | H21: =[1]Gen!AJ30 -> 783.92 | I21: =SUM(G21:H21) -> 3105.03 | J21: =[1]Gen!AT27 -> 36688.35 | K21: ='[1]Water-Meter'!E26 -> 116 | L21: =#REF! -> #REF! | M21: =#REF! -> #REF! | N21: =#REF! -> #REF! | O21: =#REF! -> #REF! | P21: =J21/52000 -> 0.70554519 | Q21: =I21*Q2 -> 6861650.5 | R21: =SUM(Q21/D21)/X21 -> 270.47016 | S21: =SUM(Q21/E21)/X21 -> #DIV/0! | T21: =(K21*102)/X21 -> 7.469697 | U21: =SUM(L21*1963)/X21 -> #REF! | V21: =SUM(Q21+T21+U21) -> #REF! | W21: =SUM(V21/E21)/T2 -> #REF! | X21: =SUM(X20) -> 1584 | Y21: 106 | Z21: =SUM(Y21-S21) -> #DIV/0!
A22: =SUM([1]Gen!A28) -> 43756 | B22: 0 | C22: =SUM([1]Gen!B28) -> 0.221 | D22: =SUM(77*C22) -> 17.017 | F22: =[1]Gen!T28 -> 5257 | G22: =[1]Gen!S28 -> 2204.84 | H22: =[1]Gen!#REF! -> #REF! | I22: =SUM(G22:H22) -> #REF! | J22: =[1]Gen!AT28 -> 33769.34 | K22: ='[1]Water-Meter'!E27 -> 114 | L22: =#REF! -> #REF! | M22: =#REF! -> #REF! | N22: =#REF! -> #REF! | O22: =#REF! -> #REF! | P22: =J22/52000 -> 0.64941038 | Q22: =I22*Q2 -> #REF! | R22: =SUM(Q22/D22)/X22 -> #REF! | S22: =SUM(Q22/E22)/X22 -> #REF! | T22: =(K22*102)/X22 -> 7.3409091 | U22: =SUM(L22*1963)/X22 -> #REF! | V22: =SUM(Q22+T22+U22) -> #REF! | W22: =SUM(V22/E22)/T2 -> #REF! | X22: =SUM(X21) -> 1584 | Y22: 106 | Z22: =SUM(Y22-S22) -> #REF!
A23: =SUM([1]Gen!A29) -> 43757 | B23: 0 | C23: =SUM([1]Gen!B29) -> 0.117 | D23: =SUM(77*C23) -> 9.009 | F23: =[1]Gen!T29 -> 4691 | G23: =[1]Gen!S29 -> 1845.18 | H23: =[1]Gen!#REF! -> #REF! | I23: =SUM(G23:H23) -> #REF! | J23: =[1]Gen!AT29 -> 31336.77 | K23: ='[1]Water-Meter'!E28 -> 113 | L23: =#REF! -> #REF! | M23: =#REF! -> #REF! | N23: =#REF! -> #REF! | O23: =#REF! -> #REF! | P23: =J23/52000 -> 0.60263019 | Q23: =I23*Q2 -> #REF! | R23: =SUM(Q23/D23)/X23 -> #REF! | S23: =SUM(Q23/E23)/X23 -> #REF! | T23: =(K23*102)/X23 -> 7.2765152 | U23: =SUM(L23*1963)/X23 -> #REF! | V23: =SUM(Q23+T23+U23) -> #REF! | W23: =SUM(V23/E23)/T2 -> #REF! | X23: =SUM(X22) -> 1584 | Y23: 106 | Z23: =SUM(Y23-S23) -> #REF!
A24: =SUM([1]Gen!A30) -> 43758 | B24: 0 | C24: =SUM([1]Gen!B30) -> 0.571 | D24: =SUM(77*C24) -> 43.967 | F24: =[1]Gen!T30 -> 5712 | G24: =[1]Gen!S30 -> 2197.01 | H24: =[1]Gen!#REF! -> #REF! | I24: =SUM(G24:H24) -> #REF! | J24: =[1]Gen!AT30 -> 29403.3 | K24: ='[1]Water-Meter'!E29 -> 99 | L24: =#REF! -> #REF! | M24: =#REF! -> #REF! | N24: =#REF! -> #REF! | O24: =#REF! -> #REF! | P24: =J24/52000 -> 0.56544808 | Q24: =I24*Q2 -> #REF! | R24: =SUM(Q24/D24)/X24 -> #REF! | S24: =SUM(Q24/E24)/X24 -> #REF! | T24: =(K24*102)/X24 -> 6.375 | U24: =SUM(L24*1963)/X24 -> #REF! | V24: =SUM(Q24+T24+U24) -> #REF! | W24: =SUM(V24/E24)/T2 -> #REF! | X24: =SUM(X23) -> 1584 | Y24: 106 | Z24: =SUM(Y24-S24) -> #REF!
A25: =SUM([1]Gen!A31) -> 43759 | B25: 0 | C25: =SUM([1]Gen!B31) -> 0.558 | D25: =SUM(77*C25) -> 42.966 | F25: =[1]Gen!T31 -> 5941 | G25: =[1]Gen!S31 -> 2262.16 | H25: =[1]Gen!AJ31 -> 172.05 | I25: =SUM(G25:H25) -> 2434.21 | J25: =[1]Gen!AT31 -> 41422.37 | K25: ='[1]Water-Meter'!E30 -> 111 | L25: =#REF! -> #REF! | M25: =#REF! -> #REF! | N25: =#REF! -> #REF! | O25: =#REF! -> #REF! | P25: =J25/52000 -> 0.79658404 | Q25: =I25*Q2 -> 5379239 | R25: =SUM(Q25/D25)/X25 -> 79.038873 | S25: =SUM(Q25/E25)/X25 -> #DIV/0! | T25: =(K25*102)/X25 -> 7.1477273 | U25: =SUM(L25*1963)/X25 -> #REF! | V25: =SUM(Q25+T25+U25) -> #REF! | W25: =SUM(V25/E25)/T2 -> #REF! | X25: =SUM(X24) -> 1584 | Y25: 106 | Z25: =SUM(Y25-S25) -> #DIV/0!
A26: =SUM([1]Gen!A32) -> 43760 | B26: 0 | C26: =SUM([1]Gen!B32) -> 0.403 | D26: =SUM(77*C26) -> 31.031 | F26: =[1]Gen!T32 -> 5400 | G26: =[1]Gen!S32 -> 2286.86 | H26: =[1]Gen!AJ32 -> 18.63 | I26: =SUM(G26:H26) -> 2305.49 | J26: =[1]Gen!AT32 -> 38988.16 | K26: ='[1]Water-Meter'!E31 -> 130 | L26: =#REF! -> #REF! | M26: =#REF! -> #REF! | N26: =#REF! -> #REF! | O26: =#REF! -> #REF! | P26: =J26/52000 -> 0.74977231 | Q26: =I26*Q2 -> 5094787.1 | R26: =SUM(Q26/D26)/X26 -> 103.65138 | S26: =SUM(Q26/E26)/X26 -> #DIV/0! | T26: =(K26*102)/X26 -> 8.3712121 | U26: =SUM(L26*1963)/X26 -> #REF! | V26: =SUM(Q26+T26+U26) -> #REF! | W26: =SUM(V26/E26)/T2 -> #REF! | X26: =SUM(X25) -> 1584 | Y26: 106 | Z26: =SUM(Y26-S26) -> #DIV/0!
A27: =SUM([1]Gen!A33) -> 43761 | B27: 0 | C27: =SUM([1]Gen!B33) -> 0.24 | D27: =SUM(77*C27) -> 18.48 | F27: =[1]Gen!T33 -> 5371 | G27: =[1]Gen!S33 -> 2148.3 | H27: =[1]Gen!AJ33 -> 311.34 | I27: =SUM(G27:H27) -> 2459.64 | J27: =[1]Gen!AT33 -> 36682.67 | K27: ='[1]Water-Meter'!E32 -> 114 | L27: =#REF! -> #REF! | M27: =#REF! -> #REF! | N27: =#REF! -> #REF! | O27: =#REF! -> #REF! | P27: =J27/52000 -> 0.70543596 | Q27: =I27*Q2 -> 5435435.5 | R27: =SUM(Q27/D27)/X27 -> 185.68516 | S27: =SUM(Q27/E27)/X27 -> #DIV/0! | T27: =(K27*102)/X27 -> 7.3409091 | U27: =SUM(L27*1963)/X27 -> #REF! | V27: =SUM(Q27+T27+U27) -> #REF! | W27: =SUM(V27/E27)/T2 -> #REF! | X27: =SUM(X26) -> 1584 | Y27: 106 | Z27: =SUM(Y27-S27) -> #DIV/0!
A28: =SUM([1]Gen!A34) -> 43762 | B28: 0 | C28: =SUM([1]Gen!B34) -> 0.09 | D28: =SUM(77*C28) -> 6.93 | F28: =[1]Gen!T34 -> 5296 | G28: =[1]Gen!S34 -> 2213.27 | H28: =[1]Gen!AJ34 -> 380.7 | I28: =SUM(G28:H28) -> 2593.97 | J28: =[1]Gen!AT34 -> 44223.03 | K28: ='[1]Water-Meter'!E33 -> -215493 | L28: =#REF! -> #REF! | M28: =#REF! -> #REF! | N28: =#REF! -> #REF! | O28: =#REF! -> #REF! | P28: =J28/52000 -> 0.85044288 | Q28: =I28*Q2 -> 5732284.6 | R28: =SUM(Q28/D28)/X28 -> 522.20296 | S28: =SUM(Q28/E28)/X28 -> #DIV/0! | T28: =(K28*102)/X28 -> -13876.443 | U28: =SUM(L28*1963)/X28 -> #REF! | V28: =SUM(Q28+T28+U28) -> #REF! | W28: =SUM(V28/E28)/T2 -> #REF! | X28: =SUM(X27) -> 1584 | Y28: 106 | Z28: =SUM(Y28-S28) -> #DIV/0!
A29: =SUM([1]Gen!A35) -> 43763 | B29: 0 | C29: =SUM([1]Gen!B35) -> 0.286 | D29: =SUM(77*C29) -> 22.022 | F29: =[1]Gen!T35 -> 5221 | G29: =[1]Gen!S35 -> 2104.52 | H29: =[1]Gen!AJ35 -> 273.37 | I29: =SUM(G29:H29) -> 2377.89 | J29: =[1]Gen!AT35 -> 41629.06 | K29: ='[1]Water-Meter'!E34 -> 0 | L29: =#REF! -> #REF! | M29: =#REF! -> #REF! | N29: =#REF! -> #REF! | O29: =#REF! -> #REF! | P29: =J29/52000 -> 0.80055885 | Q29: =I29*Q2 -> 5254780.2 | R29: =SUM(Q29/D29)/X29 -> 150.6408 | S29: =SUM(Q29/E29)/X29 -> #DIV/0! | T29: =(K29*102)/X29 -> 0 | U29: =SUM(L29*1963)/X29 -> #REF! | V29: =SUM(Q29+T29+U29) -> #REF! | W29: =SUM(V29/E29)/T2 -> #REF! | X29: =SUM(X28) -> 1584 | Y29: 106 | Z29: =SUM(Y29-S29) -> #DIV/0!
A30: =SUM([1]Gen!A36) -> 43764 | B30: 0 | C30: =SUM([1]Gen!B36) -> 0.545 | D30: =SUM(77*C30) -> 41.965 | F30: =[1]Gen!T36 -> 5665 | G30: =[1]Gen!S36 -> 2470.24 | H30: =[1]Gen!AJ36 -> 396.56 | I30: =SUM(G30:H30) -> 2866.8 | J30: =[1]Gen!AT36 -> 39251.17 | K30: ='[1]Water-Meter'!E35 -> 0 | L30: =#REF! -> #REF! | M30: =#REF! -> #REF! | N30: =#REF! -> #REF! | O30: =#REF! -> #REF! | P30: =J30/52000 -> 0.75483019 | Q30: =I30*Q2 -> 6335198 | R30: =SUM(Q30/D30)/X30 -> 95.305461 | S30: =SUM(Q30/E30)/X30 -> #DIV/0! | T30: =(K30*102)/X30 -> 0 | U30: =SUM(L30*1963)/X30 -> #REF! | V30: =SUM(Q30+T30+U30) -> #REF! | W30: =SUM(V30/E30)/T2 -> #REF! | X30: =SUM(X29) -> 1584 | Y30: 106 | Z30: =SUM(Y30-S30) -> #DIV/0!
A31: =SUM([1]Gen!A37) -> 43765 | B31: 0 | C31: =SUM([1]Gen!B37) -> 0.675 | D31: =SUM(77*C31) -> 51.975 | F31: =[1]Gen!T37 -> 6109 | G31: =[1]Gen!S37 -> 2323.74 | H31: =[1]Gen!AJ37 -> 280.63 | I31: =SUM(G31:H31) -> 2604.37 | J31: =[1]Gen!AT37 -> 36384.37 | K31: ='[1]Water-Meter'!E36 -> 0 | L31: =#REF! -> #REF! | M31: =#REF! -> #REF! | N31: =#REF! -> #REF! | O31: =#REF! -> #REF! | P31: =J31/52000 -> 0.69969942 | Q31: =I31*Q2 -> 5755267 | R31: =SUM(Q31/D31)/X31 -> 69.906218 | S31: =SUM(Q31/E31)/X31 -> #DIV/0! | T31: =(K31*102)/X31 -> 0 | U31: =SUM(L31*1963)/X31 -> #REF! | V31: =SUM(Q31+T31+U31) -> #REF! | W31: =SUM(V31/E31)/T2 -> #REF! | X31: =SUM(X30) -> 1584 | Y31: 106 | Z31: =SUM(Y31-S31) -> #DIV/0!
A32: =SUM([1]Gen!A38) -> 43766 | B32: 0 | C32: =SUM([1]Gen!B38) -> 0.273 | D32: =SUM(77*C32) -> 21.021 | F32: =[1]Gen!T38 -> 0 | G32: =[1]Gen!S38 -> 0 | H32: =[1]Gen!AJ38 -> 0 | I32: =SUM(G32:H32) -> 0 | J32: =[1]Gen!AT38 -> 33780 | K32: ='[1]Water-Meter'!E37 -> 0 | L32: =#REF! -> #REF! | M32: =#REF! -> #REF! | N32: =#REF! -> #REF! | O32: =#REF! -> #REF! | P32: =J32/52000 -> 0.64961538 | Q32: =I32*Q2 -> 0 | R32: =SUM(Q32/D32)/X32 -> 0 | S32: =SUM(Q32/E32)/X32 -> #DIV/0! | T32: =(K32*102)/X32 -> 0 | U32: =SUM(L32*1963)/X32 -> #REF! | V32: =SUM(Q32+T32+U32) -> #REF! | W32: =SUM(V32/E32)/T2 -> #REF! | X32: =SUM(X31) -> 1584 | Y32: 106 | Z32: =SUM(Y32-S32) -> #DIV/0!
B33: 0 | C33: =SUM([1]Gen!B39) -> #REF! | D33: =SUM(77*C33) -> #REF! | F33: =[1]Gen!T39 -> 0 | G33: =[1]Gen!S39 -> 0 | H33: =[1]Gen!AJ39 -> 0 | I33: =SUM(G33:H33) -> 0 | J33: =[1]Gen!AT39 -> 33780 | K33: ='[1]Water-Meter'!E38 -> -212333 | L33: =#REF! -> #REF! | M33: =#REF! -> #REF! | N33: =#REF! -> #REF! | O33: =#REF! -> #REF! | P33: =J33/52000 -> 0.64961538 | Q33: =I33*Q2 -> 0 | R33: =SUM(Q33/D33)/X33 -> #REF! | S33: =SUM(Q33/E33)/X33 -> #DIV/0! | T33: =(K33*102)/X33 -> -13672.958 | U33: =SUM(L33*1963)/X33 -> #REF! | V33: =SUM(Q33+T33+U33) -> #REF! | W33: =SUM(V33/E33)/T2 -> #REF! | X33: =SUM(X32) -> 1584 | Y33: 106 | Z33: =SUM(Y33-S33) -> #DIV/0!
B34: 0 | C34: =SUM([1]Gen!B40) -> #REF! | D34: =SUM(77*C34) -> #REF! | F34: =[1]Gen!T40 -> 0 | G34: =[1]Gen!S40 -> 0 | H34: =[1]Gen!AJ40 -> 0 | I34: =SUM(G34:H34) -> 0 | J34: =[1]Gen!AT40 -> 33780 | K34: ='[1]Water-Meter'!E39 -> #REF! | L34: =#REF! -> #REF! | M34: =#REF! -> #REF! | N34: =#REF! -> #REF! | O34: =#REF! -> #REF! | P34: =J34/52000 -> 0.64961538 | Q34: =I34*Q2 -> 0 | R34: =SUM(Q34/D34)/X34 -> #REF! | S34: =SUM(Q34/E34)/X34 -> #DIV/0! | T34: =(K34*102)/X34 -> #REF! | U34: =SUM(L34*1963)/X34 -> #REF! | V34: =SUM(Q34+T34+U34) -> #REF! | W34: =SUM(V34/E34)/T2 -> #REF! | X34: =SUM(X33) -> 1584 | Y34: 106 | Z34: =SUM(Y34-S34) -> #DIV/0!
B35: 0 | C35: =SUM([1]Gen!B41) -> #REF! | D35: =SUM(77*C35) -> #REF! | F35: =[1]Gen!T41 -> 0 | G35: =[1]Gen!S41 -> 0 | H35: =[1]Gen!AJ41 -> 0 | I35: =SUM(G35:H35) -> 0 | J35: =[1]Gen!AT41 -> 33780 | K35: ='[1]Water-Meter'!E40 -> #REF! | L35: =#REF! -> #REF! | M35: =#REF! -> #REF! | N35: =#REF! -> #REF! | O35: =#REF! -> #REF! | P35: =J35/52000 -> 0.64961538 | Q35: =I35*Q2 -> 0 | R35: =SUM(Q35/D35)/X35 -> #REF! | S35: =SUM(Q35/E35)/X35 -> #DIV/0! | T35: =(K35*102)/X35 -> #REF! | U35: =SUM(L35*1963)/X35 -> #REF! | V35: =SUM(Q35+T35+U35) -> #REF! | W35: =SUM(V35/E35)/T2 -> #REF! | X35: =SUM(X34) -> 1584 | Y35: 106 | Z35: =SUM(Y35-S35) -> #DIV/0!
K36: ='[1]Water-Meter'!E41 -> #REF! | Q36: =I36*2057.79 -> 0 | V36: =SUM(Q36+T36+U36) -> 0
S37: =SUM(S5:S16)/[1]Gen!A47 -> #REF!
B38: =SUM(B5:B37)/[1]Gen!A47 -> #REF! | M38: =0.5*2057.79 -> 1028.895
B39: =SUM(B38*[1]Gen!A47) -> #REF! | C39: =SUM(B39/250) -> #REF! | M39: =M38/1500 -> 0.68593 | O39: =(24*2.2)*2 -> 105.6 | P39: =O39*1029 -> 108662.4 | R39: Over budget | S39: =SUM(S37-Y35) -> #REF!
P40: =P39/K5 -> 953.17895

Sheet VODACOM AND AIRTEL
A1: VODACOM AND AIRTEL KWH METER READING
B2: VODACOM TOWER | E2: AIRTEL TOWER
A3: DATE | B3: OPEN METER READING | C3: CLOSE METER READING | D3: UNIT CONSUMED | E3: OPEN METER READING | F3: CLOSE METER READING | G3: UNIT CONSUMED
A4: 42095 | B4: 0 | C4: 193 | D4: =C4-B4 -> 193 | E4: 0 | F4: 0 | G4: =F4-E4 -> 0
A5: 42125 | B5: =C4 -> 193 | C5: 1158 | D5: =C5-B5 -> 965 | E5: 145572 | F5: 145572 | G5: =F5-E5 -> 0
A6: 42156 | B6: =C5 -> 1158 | C6: 2084 | D6: =C6-B6 -> 926 | E6: =F5 -> 145572 | F6: 147984 | G6: =F6-E6 -> 2412
A7: 42186 | B7: =C6 -> 2084 | C7: 3073 | D7: =C7-B7 -> 989 | E7: =F6 -> 147984 | F7: 150507 | G7: =F7-E7 -> 2523
A8: 42217 | B8: =C7 -> 3073 | C8: 4063 | D8: =C8-B8 -> 990 | E8: =F7 -> 150507 | F8: 152986 | G8: =F8-E8 -> 2479
A9: 42248 | B9: =C8 -> 4063 | C9: 5058 | D9: =C9-B9 -> 995 | E9: =F8 -> 152986 | F9: 155468 | G9: =F9-E9 -> 2482
A10: 42278 | B10: =C9 -> 5058 | C10: 6049 | D10: =C10-B10 -> 991 | E10: =F9 -> 155468 | F10: 157962 | G10: =F10-E10 -> 2494
A11: 42309 | B11: =C10 -> 6049 | C11: 7028 | D11: =C11-B11 -> 979 | E11: =F10 -> 157962 | F11: 160323 | G11: =F11-E11 -> 2361
A12: 42339 | B12: =C11 -> 7028 | C12: 7985 | D12: =C12-B12 -> 957 | E12: =F11 -> 160323 | F12: 162813 | G12: =F12-E12 -> 2490
A13: 42370 | B13: =C12 -> 7985 | C13: 8952 | D13: =C13-B13 -> 967 | E13: =F12 -> 162813 | F13: 165317 | G13: =F13-E13 -> 2504
A14: 42401 | B14: =C13 -> 8952 | C14: 9898 | D14: =C14-B14 -> 946 | E14: =F13 -> 165317 | F14: 167679 | G14: =F14-E14 -> 2362
A15: 42430 | B15: =C14 -> 9898 | C15: 10637 | D15: =C15-B15 -> 739 | E15: =F14 -> 167679 | F15: 170134 | G15: =F15-E15 -> 2455
A16: 42461 | B16: =C15 -> 10637 | C16: 11352 | D16: =C16-B16 -> 715 | E16: =F15 -> 170134 | F16: 172562 | G16: =F16-E16 -> 2428
A17: 42491 | B17: =C16 -> 11352 | C17: 12426 | D17: =C17-B17 -> 1074 | E17: =F16 -> 172562 | F17: 175041 | G17: =F17-E17 -> 2479
... A59: 43770 | B59: =C58 -> 89489 | C59: 91615 | D59: =C59-B59 -> 2126 | E59: =F58 -> 263905 | F59: 265969 | G59: =F59-E59 -> 2064
A60: 43800 | B60: =C59 -> 91615 | D60: =C60-B60 -> -91615 | E60: =F59 -> 265969 | G60: =F60-E60 -> -265969
A61: 43831 | B61: =C60 -> 0 | D61: =C61-B61 -> 0 | E61: =F60 -> 0 | G61: =F61-E61 -> 0
A62: 43862 | B62: =C61 -> 0 | D62: =C62-B62 -> 0 | E62: =F61 -> 0 | G62: =F62-E62 -> 0
A63: 43891 | B63: =C62 -> 0 | D63: =C63-B63 -> 0 | E63: =F62 -> 0 | G63: =F63-E63 -> 0
A64: 43922 | B64: =C63 -> 0 | D64: =C64-B64 -> 0 | E64: =F63 -> 0 | G64: =F64-E64 -> 0
A65: 43952 | B65: =C64 -> 0 | D65: =C65-B65 -> 0 | E65: =F64 -> 0 | G65: =F65-E65 -> 0
A66: 43983 | B66: =C65 -> 0 | D66: =C66-B66 -> 0 | E66: =F65 -> 0 | G66: =F66-E66 -> 0
A67: 44013 | B67: =C66 -> 0 | D67: =C67-B67 -> 0 | E67: =F66 -> 0 | G67: =F67-E67 -> 0
A68: 44044 | B68: =C67 -> 0 | D68: =C68-B68 -> 0 | E68: =F67 -> 0 | G68: =F68-E68 -> 0
A69: 44075 | B69: =C68 -> 0 | D69: =C69-B69 -> 0 | E69: =F68 -> 0 | G69: =F69-E69 -> 0
A70: 44105 | B70: =C69 -> 0 | D70: =C70-B70 -> 0 | E70: =F69 -> 0 | G70: =F70-E70 -> 0
A71: 44136 | B71: =C70 -> 0 | D71: =C71-B71 -> 0 | E71: =F70 -> 0 | G71: =F71-E71 -> 0
... A99: 44986 | B99: =C98 -> 0 | D99: =C99-B99 -> 0 | E99: =F98 -> 0 | G99: =F99-E99 -> 0

Sheet FUEL METER READING
A1: FUEL METER 1 READNG | H1: FUEL METER 2 READING
A2: DATE | B2: OPEN METER READING | C2: CLOSE METER READING | D2: Diesel consumed | E2: HLP-GENSETS | F2: DIFFERENCE | G2: OPEN METER | H2: CLOSE METER | I2: DIESEL CONSUMED | J2: HLP-VEHICLES | K2: DIFFERENCE | L2: TOTAL DIESEL CONS.
A3: 42430 | B3: 5000778 | C3: 5057715 | D3: =C3-B3 -> 56937 | G3: =H3 -> 0 | I3: =H3-G3 -> 0 | K3: =I3-J3 -> 0
A4: 42461 | B4: =C3 -> 5057715 | C4: 5111496 | D4: =C4-B4 -> 53781 | G4: =H3 -> 0 | I4: =H4-G4 -> 0 | K4: =I4-J4 -> 0
A5: 42491 | B5: =C4 -> 5111496 | C5: 5169409 | D5: =C5-B5 -> 57913 | G5: =H4 -> 0 | I5: =H5-G5 -> 0 | K5: =I5-J5 -> 0
A6: 42522 | B6: =C5 -> 5169409 | C6: 5232162 | D6: =C6-B6 -> 62753 | G6: =H5 -> 0 | I6: =H6-G6 -> 0 | K6: =I6-J6 -> 0
A7: 42552 | B7: =C6 -> 5232162 | C7: 5310037 | D7: =C7-B7 -> 77875 | G7: =H6 -> 0 | I7: =H7-G7 -> 0 | K7: =I7-J7 -> 0
A8: 42583 | B8: =C7 -> 5310037 | C8: 5382821 | D8: =C8-B8 -> 72784 | E8: =[4]Gen!AR45 -> 72766 | F8: =D8-E8 -> 18 | G8: =H7 -> 0 | I8: =H8-G8 -> 0 | K8: =I8-J8 -> 0
A9: 42614 | B9: =C8 -> 5382821 | C9: 5446740 | D9: =C9-B9 -> 63919 | E9: =[5]Gen!AR45 -> 64036.5 | F9: =D9-E9 -> -117.5 | G9: =H8 -> 0 | I9: =H9-G9 -> 0 | K9: =I9-J9 -> 0
A10: 42644 | B10: =C9 -> 5446740 | C10: 5521440 | D10: =C10-B10 -> 74700 | E10: 76057.09 | F10: =D10-E10 -> -1357.09 | G10: =H9 -> 0 | I10: =H10-G10 -> 0 | K10: =I10-J10 -> 0
A11: 42675 | B11: =C10 -> 5521440 | C11: 5594926 | D11: =C11-B11 -> 73486 | E11: 73462.49 | F11: =D11-E11 -> 23.51 | G11: =H10 -> 0 | I11: =H11-G11 -> 0 | K11: =I11-J11 -> 0
A12: 42705 | B12: =C11 -> 5594926 | C12: 5670348 | D12: =C12-B12 -> 75422 | E12: 75421.2 | F12: =D12-E12 -> 0.8 | G12: =H11 -> 0 | I12: =H12-G12 -> 0 | K12: =I12-J12 -> 0
A13: 42736 | B13: =C12 -> 5670348 | C13: 5735627 | D13: =C13-B13 -> 65279 | E13: 65276.07 | F13: =D13-E13 -> 2.93 | G13: =H12 -> 0 | I13: =H13-G13 -> 0 | K13: =I13-J13 -> 0
A14: 42767 | B14: =C13 -> 5735627 | C14: 5797781 | D14: =C14-B14 -> 62154 | E14: 62154.9 | F14: =D14-E14 -> -0.9 | G14: =H13 -> 0 | I14: =H14-G14 -> 0 | K14: =I14-J14 -> 0
A15: 42795 | B15: =C14 -> 5797781 | C15: 5864602 | D15: =C15-B15 -> 66821 | E15: 66820.89 | F15: =D15-E15 -> 0.11 | G15: =H14 -> 0 | I15: =H15-G15 -> 0 | K15: =I15-J15 -> 0
A16: 42826 | B16: =C15 -> 5864602 | C16: 5927895 | D16: =C16-B16 -> 63293 | E16: 63292.38 | F16: =D16-E16 -> 0.62 | G16: =H15 -> 0 | I16: =H16-G16 -> 0 | K16: =I16-J16 -> 0
A17: 42856 | B17: =C16 -> 5927895 | C17: 5995212 | D17: =C17-B17 -> 67317 | E17: 67313.47 | F17: =D17-E17 -> 3.53 | G17: =H16 -> 0 | I17: =H17-G17 -> 0 | K17: =I17-J17 -> 0
A18: 42887 | B18: =C17 -> 5995212 | C18: 6065754 | D18: =C18-B18 -> 70542 | E18: 70542.6 | F18: =D18-E18 -> -0.6 | G18: =H17 -> 0 | I18: =H18-G18 -> 0 | K18: =I18-J18 -> 0
A19: 42917 | B19: =C18 -> 6065754 | C19: 6141089 | D19: =C19-B19 -> 75335 | E19: 75335 | F19: =D19-E19 -> 0 | G19: 2442 | H19: 15003 | I19: =H19-G19 -> 12561 | K19: =I19-J19 -> 12561
A20: 42948 | B20: =C19 -> 6141089 | C20: 6212470 | D20: =C20-B20 -> 71381 | E20: 71379.9 | F20: =D20-E20 -> 1.1 | G20: =H19 -> 15003 | H20: 25033 | I20: =H20-G20 -> 10030 | J20: 10029.74 | K20: =I20-J20 -> 0.26 | L20: =I20+D20 -> 81411
A21: 42979 | B21: =C20 -> 6212470 | C21: 6276921 | D21: =C21-B21 -> 64451 | E21: 64450.62 | F21: =D21-E21 -> 0.38 | G21: =H20 -> 25033 | H21: 32815 | I21: =H21-G21 -> 7782 | J21: 7781.72 | K21: =I21-J21 -> 0.28 | L21: =I21+D21 -> 72233
A22: 43009 | B22: =C21 -> 6276921 | C22: 6352831 | D22: =C22-B22 -> 75910 | E22: 75906.79 | F22: =D22-E22 -> 3.21 | G22: =H21 -> 32815 | H22: 39587 | I22: =H22-G22 -> 6772 | J22: 6772.04 | K22: =I22-J22 -> -0.04 | L22: =I22+D22 -> 82682
A23: 43040 | B23: =C22 -> 6352831 | C23: 6410003 | D23: =C23-B23 -> 57172 | E23: 57171.51 | F23: =D23-E23 -> 0.49 | G23: =H22 -> 39587 | H23: 45717 | I23: =H23-G23 -> 6130 | J23: 6129.55 | K23: =I23-J23 -> 0.45 | L23: =I23+D23 -> 63302
A24: 43070 | B24: =C23 -> 6410003 | C24: 6476953 | D24: =C24-B24 -> 66950 | E24: 66951.14 | F24: =D24-E24 -> -1.14 | G24: =H23 -> 45717 | H24: 52890 | I24: =H24-G24 -> 7173 | J24: 7173.94 | K24: =I24-J24 -> -0.94 | L24: =I24+D24 -> 74123
A25: 43101 | B25: =C24 -> 6476953 | C25: 6542879 | D25: =C25-B25 -> 65926 | E25: 65927.77 | F25: =D25-E25 -> -1.77 | G25: =H24 -> 52890 | H25: 59763 | I25: =H25-G25 -> 6873 | J25: 6874.87 | K25: =I25-J25 -> -1.87 | L25: =I25+D25 -> 72799
A26: 43132 | B26: =C25 -> 6542879 | C26: 6604433 | D26: =C26-B26 -> 61554 | E26: 61553.03 | F26: =D26-E26 -> 0.97 | G26: =H25 -> 59763 | H26: 66652 | I26: =H26-G26 -> 6889 | J26: 6890.89 | K26: =I26-J26 -> -1.89 | L26: =I26+D26 -> 68443
A27: 43160 | B27: =C26 -> 6604433 | C27: 6660226 | D27: =C27-B27 -> 55793 | E27: 55792.75 | F27: =D27-E27 -> 0.25 | G27: =H26 -> 66652 | H27: 77607 | I27: =H27-G27 -> 10955 | J27: 10955.45 | K27: =I27-J27 -> -0.45 | L27: =I27+D27 -> 66748
A28: 43191 | B28: =C27 -> 6660226 | C28: 6714539 | D28: =C28-B28 -> 54313 | E28: 54312.28 | F28: =D28-E28 -> 0.72 | G28: =H27 -> 77607 | H28: 82271 | I28: =H28-G28 -> 4664 | J28: 4665.22 | K28: =I28-J28 -> -1.22 | L28: =I28+D28 -> 58977
A29: 43221 | B29: =C28 -> 6714539 | C29: 6774547 | D29: =C29-B29 -> 60008 | E29: 60007.47 | F29: =D29-E29 -> 0.53 | G29: =H28 -> 82271 | H29: 88664 | I29: =H29-G29 -> 6393 | J29: 6392.14 | K29: =I29-J29 -> 0.86 | L29: =I29+D29 -> 66401
A30: 43252 | B30: =C29 -> 6774547 | C30: 6845214 | D30: =C30-B30 -> 70667 | E30: 70666.29 | F30: =D30-E30 -> 0.71 | G30: =H29 -> 88664 | H30: 99683 | I30: =H30-G30 -> 11019 | J30: 11020.51 | K30: =I30-J30 -> -1.51 | L30: =I30+D30 -> 81686
A31: 43282 | B31: =C30 -> 6845214 | C31: 6921964 | D31: =C31-B31 -> 76750 | E31: 76750.25 | F31: =D31-E31 -> -0.25 | G31: =H30 -> 99683 | H31: 107936 | I31: =H31-G31 -> 8253 | J31: 8252.24 | K31: =I31-J31 -> 0.76 | L31: =I31+D31 -> 85003
... A48: 43800 | B48: =C47 -> 8069975 | C48: 8103174 | D48: =C48-B48 -> 33199 | E48: 33228.35 | F48: =D48-E48 -> -29.35 | G48: =H47 -> 235486 | H48: 241845 | I48: =H48-G48 -> 6359 | J48: 6359.28 | K48: =I48-J48 -> -0.28 | L48: =I48+D48 -> 39558
A49: 43831 | B49: =C48 -> 8103174 | D49: =C49-B49 -> -8103174 | F49: =D49-E49 -> -8103174 | G49: =H48 -> 241845 | I49: =H49-G49 -> -241845 | K49: =I49-J49 -> -241845 | L49: =I49+D49 -> -8345019
A50: 43862 | B50: =C49 -> 0 | D50: =C50-B50 -> 0 | F50: =D50-E50 -> 0 | G50: =H49 -> 0 | I50: =H50-G50 -> 0 | K50: =I50-J50 -> 0 | L50: =I50+D50 -> 0
A51: 43891 | B51: =C50 -> 0 | D51: =C51-B51 -> 0 | F51: =D51-E51 -> 0 | G51: =H50 -> 0 | I51: =H51-G51 -> 0 | K51: =I51-J51 -> 0 | L51: =I51+D51 -> 0
A52: 43922 | B52: =C51 -> 0 | D52: =C52-B52 -> 0 | F52: =D52-E52 -> 0 | G52: =H51 -> 0 | I52: =H52-G52 -> 0 | K52: =I52-J52 -> 0 | L52: =I52+D52 -> 0
A53: 43952 | B53: =C52 -> 0 | D53: =C53-B53 -> 0 | F53: =D53-E53 -> 0 | G53: =H52 -> 0 | I53: =H53-G53 -> 0 | K53: =I53-J53 -> 0 | L53: =I53+D53 -> 0
A54: 43983 | B54: =C53 -> 0 | D54: =C54-B54 -> 0 | F54: =D54-E54 -> 0 | G54: =H53 -> 0 | I54: =H54-G54 -> 0 | K54: =I54-J54 -> 0 | L54: =I54+D54 -> 0
A55: 44013 | B55: =C54 -> 0 | D55: =C55-B55 -> 0 | F55: =D55-E55 -> 0 | G55: =H54 -> 0 | I55: =H55-G55 -> 0 | K55: =I55-J55 -> 0 | L55: =I55+D55 -> 0
A56: 44044 | B56: =C55 -> 0 | D56: =C56-B56 -> 0 | F56: =D56-E56 -> 0 | G56: =H55 -> 0 | I56: =H56-G56 -> 0 | K56: =I56-J56 -> 0 | L56: =I56+D56 -> 0
A57: 44075 | B57: =C56 -> 0 | D57: =C57-B57 -> 0 | F57: =D57-E57 -> 0 | G57: =H56 -> 0 | I57: =H57-G57 -> 0 | K57: =I57-J57 -> 0 | L57: =I57+D57 -> 0
A58: 44105 | B58: =C57 -> 0 | D58: =C58-B58 -> 0 | F58: =D58-E58 -> 0 | G58: =H57 -> 0 | I58: =H58-G58 -> 0 | K58: =I58-J58 -> 0 | L58: =I58+D58 -> 0
A59: 44136 | B59: =C58 -> 0 | D59: =C59-B59 -> 0 | F59: =D59-E59 -> 0 | G59: =H58 -> 0 | I59: =H59-G59 -> 0 | K59: =I59-J59 -> 0 | L59: =I59+D59 -> 0
A60: 44166 | B60: =C59 -> 0 | D60: =C60-B60 -> 0 | F60: =D60-E60 -> 0 | G60: =H59 -> 0 | I60: =H60-G60 -> 0 | K60: =I60-J60 -> 0 | L60: =I60+D60 -> 0
... A86: 44958 | B86: =C85 -> 0 | D86: =C86-B86 -> 0 | F86: =D86-E86 -> 0 | G86: =H85 -> 0 | I86: =H86-G86 -> 0 | K86: =I86-J86 -> 0 | L86: =I86+D86 -> 0

Sheet Daily utility report 
A1: DAILY UTILITIES REPORT
A2: 43831
A3: DATE | B3: OCC % | D3: GENERATOR FUEL (LTR) | F3: WATER (M³) | I3: ELECTRICAL (Kwh)
C4: VEHICLE CONSUMPTION | D4: CONSUMPTION | E4: BALANCE | F4: CONSUMPTION | G4: BOREHOLE PRODUCTION | H4: RO PRODUCTION | I4: KITCHEN | J4: LAUNDRY
A5: 43862 | B5: =Gen!B11 -> 0.2338 | C5: =Gen!AJ11 -> 83.21 | D5: =Gen!S11 -> 1824.75 | E5: =Gen!C11 -> 30982.31 | F5: ='Water-Meter'!E6 -> 113 | G5: ='Water-Meter'!AN6 -> 200 | H5: ='Utility report '!AC6 -> 115 | I5: ='Kit report'!F4 -> 444 | J5: ='Kit report'!X4 -> 700
A6: 43863 | B6: =Gen!B12 -> 0.234 | C6: =Gen!AJ12 -> 130.39 | D6: =Gen!S12 -> 1802.85 | E6: =Gen!C12 -> 29074.35 | F6: ='Water-Meter'!E7 -> 97 | G6: ='Water-Meter'!AN7 -> 140 | H6: ='Utility report '!AC7 -> 101 | I6: ='Kit report'!F5 -> 468 | J6: ='Kit report'!X5 -> 700
A7: 43864 | B7: =Gen!B13 -> 0.104 | C7: =Gen!AJ13 -> 178.75 | D7: =Gen!S13 -> 1920.92 | E7: =Gen!C13 -> 27141.11 | F7: ='Water-Meter'!E8 -> 107 | G7: ='Water-Meter'!AN8 -> 93 | H7: ='Utility report '!AC8 -> 81 | I7: ='Kit report'!F6 -> 516 | J7: ='Kit report'!X6 -> 960
A8: 43865 | B8: =Gen!B14 -> 1 | C8: =Gen!AJ14 -> 89.65 | D8: =Gen!S14 -> 2359.12 | E8: =Gen!C14 -> 43041.44 | F8: ='Water-Meter'!E9 -> 139 | G8: ='Water-Meter'!AN9 -> 94 | H8: ='Utility report '!AC9 -> 100 | I8: ='Kit report'!F7 -> 492 | J8: ='Kit report'!X7 -> 1060
A9: 43866 | B9: =Gen!B15 -> 1 | C9: =Gen!AJ15 -> 129.27 | D9: =Gen!S15 -> 2256.73 | E9: =Gen!C15 -> 40592.67 | F9: ='Water-Meter'!E10 -> 141 | G9: ='Water-Meter'!AN10 -> 178 | H9: ='Utility report '!AC10 -> 98 | I9: ='Kit report'!F8 -> 552 | J9: ='Kit report'!X8 -> 840
A10: 43867 | B10: =Gen!B16 -> 1 | C10: =Gen!AJ16 -> 187.64 | D10: =Gen!S16 -> 2491.51 | E10: =Gen!C16 -> 38206.67 | F10: ='Water-Meter'!E11 -> 129 | G10: ='Water-Meter'!AN11 -> 188 | H10: ='Utility report '!AC11 -> 83 | I10: ='Kit report'!F9 -> 540 | J10: ='Kit report'!X9 -> 1060
A11: 43868 | B11: =Gen!B17 -> 1 | C11: =Gen!AJ17 -> 203.15 | D11: =Gen!S17 -> 2244.74 | E11: =Gen!C17 -> 35527.52 | F11: ='Water-Meter'!E12 -> 129 | G11: ='Water-Meter'!AN12 -> 178 | H11: ='Utility report '!AC12 -> 103 | I11: ='Kit report'!F10 -> 564 | J11: ='Kit report'!X10 -> 1200
A12: 43869 | B12: =Gen!B18 -> 0.1429 | C12: =Gen!AJ18 -> 56.74 | D12: =Gen!S18 -> 2569.45 | E12: =Gen!C18 -> 33079.63 | F12: ='Water-Meter'!E13 -> 128 | G12: ='Water-Meter'!AN13 -> 184 | H12: ='Utility report '!AC13 -> 105 | I12: ='Kit report'!F11 -> 564 | J12: ='Kit report'!X11 -> 1220
A13: 43870 | B13: =Gen!B19 -> 0.195 | C13: =Gen!AJ19 -> 162.68 | D13: =Gen!S19 -> 2039.82 | E13: =Gen!C19 -> 45453.44 | F13: ='Water-Meter'!E14 -> 96 | G13: ='Water-Meter'!AN14 -> 239 | H13: ='Utility report '!AC14 -> 136 | I13: ='Kit report'!F12 -> 552 | J13: ='Kit report'!X12 -> 1060
A14: 43871 | B14: =Gen!B20 -> 0.1818 | C14: =Gen!AJ20 -> 0 | D14: =Gen!S20 -> 0 | E14: =Gen!C20 -> 43250.94 | F14: ='Water-Meter'!E15 -> 0 | G14: ='Water-Meter'!AN15 -> 0 | H14: ='Utility report '!AC15 -> 121 | I14: ='Kit report'!F13 -> -1015188 | J14: ='Kit report'!X13 -> -1528340
A15: 43872 | B15: =Gen!B21 -> 0 | C15: =Gen!AJ21 -> 0 | D15: =Gen!S21 -> 0 | E15: =Gen!C21 -> 43250.94 | F15: ='Water-Meter'!E16 -> 0 | G15: ='Water-Meter'!AN16 -> 0 | H15: ='Utility report '!AC16 -> -24878 | I15: ='Kit report'!F14 -> 0 | J15: ='Kit report'!X14 -> 0
A16: 43873 | B16: =Gen!B22 -> 0 | C16: =Gen!AJ22 -> 0 | D16: =Gen!S22 -> 0 | E16: =Gen!C22 -> 43250.94 | F16: ='Water-Meter'!E17 -> 0 | G16: ='Water-Meter'!AN17 -> 0 | H16: ='Utility report '!AC17 -> 0 | I16: ='Kit report'!F15 -> 0 | J16: ='Kit report'!X15 -> 0
... A27: 43884 | B27: =Gen!B33 -> 0 | C27: =Gen!AJ33 -> 0 | D27: =Gen!S33 -> 0 | E27: =Gen!C33 -> 43250.94 | F27: ='Water-Meter'!E28 -> 0 | G27: ='Water-Meter'!AN28 -> 0 | H27: ='Utility report '!AC28 -> 0 | I27: ='Kit report'!F26 -> 0 | J27: ='Kit report'!X26 -> 0
A28: 43885 | B28: 0.091 | C28: =Gen!AJ34 -> 0 | D28: =Gen!S34 -> 0 | E28: =Gen!C34 -> 43250.94 | F28: ='Water-Meter'!E29 -> 0 | G28: ='Water-Meter'!AN29 -> 0 | H28: ='Utility report '!AC29 -> 0 | I28: ='Kit report'!F27 -> 0 | J28: ='Kit report'!X27 -> 0
A29: 43886 | B29: =Gen!B35 -> 0 | C29: =Gen!AJ35 -> 0 | D29: =Gen!S35 -> 0 | E29: =Gen!C35 -> 43250.94 | F29: ='Water-Meter'!E30 -> 0 | G29: ='Water-Meter'!AN30 -> 0 | H29: ='Utility report '!AC30 -> 0 | I29: ='Kit report'!F28 -> 0 | J29: ='Kit report'!X28 -> 0
A30: 43887 | B30: =Gen!B36 -> 0 | C30: =Gen!AJ36 -> 0 | D30: =Gen!S36 -> 0 | E30: =Gen!C36 -> 43250.94 | F30: ='Water-Meter'!E31 -> 0 | G30: ='Water-Meter'!AN31 -> 0 | H30: ='Utility report '!AC31 -> 0 | I30: ='Kit report'!F29 -> 0 | J30: ='Kit report'!X29 -> 0
A31: 43888 | B31: =Gen!B37 -> 0 | C31: =Gen!AJ37 -> 0 | D31: =Gen!S37 -> 0 | E31: =Gen!C37 -> 43250.94 | F31: ='Water-Meter'!E32 -> 0 | G31: ='Water-Meter'!AN32 -> 0 | H31: ='Utility report '!AC32 -> 0 | I31: ='Kit report'!F30 -> 0 | J31: ='Kit report'!X30 -> 0
A32: 43889 | B32: =Gen!B38 -> 0 | C32: =Gen!AJ38 -> 0 | D32: =Gen!S38 -> 0 | E32: =Gen!C38 -> 43250.94 | F32: ='Water-Meter'!E33 -> 0 | G32: ='Water-Meter'!AN33 -> 0 | H32: ='Utility report '!AC33 -> 0 | I32: ='Kit report'!F31 -> 0 | J32: ='Kit report'!X31 -> 0
A33: 43890 | B33: =Gen!B39 -> 0 | C33: =Gen!AJ39 -> 0 | D33: =Gen!S39 -> 0 | E33: =Gen!C39 -> 43250.94 | F33: ='Water-Meter'!E34 -> 0 | G33: ='Water-Meter'!AN34 -> 0 | H33: ='Utility report '!AC34 -> 0 | I33: ='Kit report'!F32 -> 0 | J33: ='Kit report'!X32 -> 0
A34: 43891 | B34: =Gen!B40 -> 0 | C34: =Gen!AJ40 -> 0 | D34: =Gen!S40 -> 0 | E34: =Gen!C40 -> 43250.94 | F34: ='Water-Meter'!E35 -> 0 | G34: ='Water-Meter'!AN35 -> 0 | H34: ='Utility report '!AC35 -> 0 | I34: ='Kit report'!F33 -> 0 | J34: ='Kit report'!X33 -> 0
A35: 43892 | B35: =Gen!B41 -> 0 | C35: =Gen!AJ41 -> 0 | D35: =Gen!S41 -> 0 | E35: =Gen!C41 -> 43250.94 | F35: ='Water-Meter'!E36 -> 0 | G35: ='Water-Meter'!AN36 -> 0 | H35: ='Utility report '!AC36 -> 0 | I35: ='Kit report'!F34 -> 0 | J35: ='Kit report'!X34 -> 0
A36: 43893 | C36: =Gen!AJ42 -> 0 | D36: =Gen!S42 -> 0 | E36: =Gen!C42 -> 43250.94 | F36: ='Water-Meter'!E37 -> 0 | G36: ='Water-Meter'!AN37 -> 330 | H36: ='Utility report '!AC37 -> 0 | I36: ='Kit report'!F35 -> 1428 | J36: ='Kit report'!X35 -> 0
