Workbook

Sheet Total
A1: Site Name | B1: Day | C1: Month | D1: Year | E1: Total Electricity Kwh | F1: Electricity Tariff ($/Kwh) | G1: Total Fuel Oil (Liters) | H1: Fuel Oil $/Liter | I1: LPG (Kg) | J1: LPG $/Kg | K1: Water Utility Supply (m3) m3 | L1: Water Utility Supply (m3) $/m3 | M1: Irrigation Water (m3) m3 | N1: Irrigation water $/m3 | O1: Room Nights
A2: Beirut | B2: 1 | C2: 2 | D2: 2020 | E2: =ELEC!N3 -> 11338 | F2: =SUM('EDl log'!T4) -> 0.10069059 | G2: =-tanks!AW6 -> 530 | H2: =SUM(tanks!AV6) -> 0.5835 | I2: =('B5'!AU5)*0.51 -> 45.9 | J2: ='B5'!AX5/0.51 -> 1.372549 | K2: =WATER!I6 -> 320 | L2: =SUM(WATER!J6) -> 0.80818966 | M2: =WATER!Q6 -> 0 | N2: 0.6 | O2: =ELEC!B3 -> 33.994
A3: Beirut | B3: =B2+1 -> 2 | C3: 2 | D3: 2020 | E3: =ELEC!N4 -> 13781 | F3: =SUM('EDl log'!T5) -> 0.08047306 | G3: =-tanks!AW7 -> 606 | H3: =SUM(tanks!AV7) -> 0.5835 | I3: =('B5'!AU6)*0.51 -> 107.1 | J3: ='B5'!AX6/0.51 -> 1.372549 | K3: =WATER!I7 -> 40 | L3: =SUM(WATER!J7) -> 6.4655172 | M3: =WATER!Q7 -> 0 | N3: 0.6 | O3: =ELEC!B4 -> 25.001
A4: Beirut | B4: =B3+1 -> 3 | C4: 2 | D4: 2020 | E4: =ELEC!N5 -> 10327 | F4: =SUM('EDl log'!T6) -> 0.099326823 | G4: =-tanks!AW8 -> 655 | H4: =SUM(tanks!AV8) -> 0.5835 | I4: =('B5'!AU7)*0.51 -> 45.9 | J4: ='B5'!AX7/0.51 -> 1.372549 | K4: =WATER!I8 -> 118 | L4: =SUM(WATER!J8) -> 2.1917008 | M4: =WATER!Q8 -> 0 | N4: 0.6 | O4: =ELEC!B5 -> 27.002
A5: Beirut | B5: =B4+1 -> 4 | C5: 2 | D5: 2020 | E5: =ELEC!N6 -> 12214 | F5: =SUM('EDl log'!T7) -> 0.080064763 | G5: =-tanks!AW9 -> 1137.7 | H5: =SUM(tanks!AV9) -> 0.5835 | I5: =('B5'!AU8)*0.51 -> 91.8 | J5: ='B5'!AX8/0.51 -> 1.372549 | K5: =WATER!I9 -> 0 | L5: =SUM(WATER!J9) -> 0 | M5: =WATER!Q9 -> 0 | N5: 0.6 | O5: =ELEC!B6 -> 27.002
A6: Beirut | B6: =B5+1 -> 5 | C6: 2 | D6: 2020 | E6: =ELEC!N7 -> 13334 | F6: =SUM('EDl log'!T8) -> 0.089794305 | G6: =-tanks!AW10 -> 617 | H6: =SUM(tanks!AV10) -> 0.5835 | I6: =('B5'!AU9)*0.51 -> 91.8 | J6: ='B5'!AX9/0.51 -> 1.372549 | K6: =WATER!I10 -> 311 | L6: =SUM(WATER!J10) -> 0.83157778 | M6: =WATER!Q10 -> 0 | N6: 0.6 | O6: =ELEC!B7 -> 33.994
A7: Beirut | B7: =B6+1 -> 6 | C7: 2 | D7: 2020 | E7: =ELEC!N8 -> 11008 | F7: =SUM('EDl log'!T9) -> 0.091261957 | G7: =-tanks!AW11 -> 453 | H7: =SUM(tanks!AV11) -> 0.5835 | I7: =('B5'!AU10)*0.51 -> 163.2 | J7: ='B5'!AX10/0.51 -> 1.372549 | K7: =WATER!I11 -> 0 | L7: =SUM(WATER!J11) -> 0 | M7: =WATER!Q11 -> 0 | N7: 0.6 | O7: =ELEC!B8 -> 46
A8: Beirut | B8: =B7+1 -> 7 | C8: 2 | D8: 2020 | E8: =ELEC!N9 -> 12629 | F8: =SUM('EDl log'!T10) -> 0.012386308 | G8: =-tanks!AW12 -> 906.9 | H8: =SUM(tanks!AV12) -> 0.54 | I8: =('B5'!AU11)*0.51 -> 61.2 | J8: ='B5'!AX11/0.51 -> 1.372549 | K8: =WATER!I12 -> 334 | L8: =SUM(WATER!J12) -> 0.77431344 | M8: =WATER!Q12 -> 0 | N8: 0.6 | O8: =ELEC!B9 -> 45.011
A9: Beirut | B9: =B8+1 -> 8 | C9: 2 | D9: 2020 | E9: =ELEC!N10 -> 12830 | F9: =SUM('EDl log'!T11) -> 0.082024837 | G9: =-tanks!AW13 -> 669.8 | H9: =SUM(tanks!AV13) -> 0.54 | I9: =('B5'!AU12)*0.51 -> 45.9 | J9: ='B5'!AX12/0.51 -> 1.372549 | K9: =WATER!I13 -> 0 | L9: =SUM(WATER!J13) -> 0 | M9: =WATER!Q13 -> 0 | N9: 0.6 | O9: =ELEC!B10 -> 31.97
A10: Beirut | B10: =B9+1 -> 9 | C10: 2 | D10: 2020 | E10: =ELEC!N11 -> 10890 | F10: =SUM('EDl log'!T12) -> 0.094138036 | G10: =-tanks!AW14 -> 828 | H10: =SUM(tanks!AV14) -> 0.54 | I10: =('B5'!AU13)*0.51 -> 137.7 | J10: ='B5'!AX13/0.51 -> 1.372549 | K10: =WATER!I14 -> 0 | L10: =SUM(WATER!J14) -> 0 | M10: =WATER!Q14 -> 0 | N10: 0.6 | O10: =ELEC!B11 -> 35.006
A11: Beirut | B11: =B10+1 -> 10 | C11: 2 | D11: 2020 | E11: =ELEC!N12 -> 10518 | F11: =SUM('EDl log'!T13) -> 0.093357235 | G11: =-tanks!AW15 -> 1098.6 | H11: =SUM(tanks!AV15) -> 0.54 | I11: =('B5'!AU14)*0.51 -> 137.7 | J11: ='B5'!AX14/0.51 -> 1.372549 | K11: =WATER!I15 -> 324 | L11: =SUM(WATER!J15) -> 0.79821201 | M11: =WATER!Q15 -> 0 | N11: 0.6 | O11: =ELEC!B12 -> 37.007
A12: Beirut | B12: =B11+1 -> 11 | C12: 2 | D12: 2020 | E12: =ELEC!N13 -> 10923 | F12: =SUM('EDl log'!T14) -> 0.072704071 | G12: =-tanks!AW16 -> 1468.1 | H12: =SUM(tanks!AV16) -> 0.54 | I12: =('B5'!AU15)*0.51 -> 45.9 | J12: ='B5'!AX15/0.51 -> 1.372549 | K12: =WATER!I16 -> 141 | L12: =SUM(WATER!J16) -> 1.8341893 | M12: =WATER!Q16 -> 0 | N12: 0.6 | O12: =ELEC!B13 -> 33.994
A13: Beirut | B13: =B12+1 -> 12 | C13: 2 | D13: 2020 | E13: =ELEC!N14 -> 11363.4 | F13: =SUM('EDl log'!T15) -> 0.10545805 | G13: =-tanks!AW17 -> 880 | H13: =SUM(tanks!AV17) -> 0.54 | I13: =('B5'!AU16)*0.51 -> 61.2 | J13: ='B5'!AX16/0.51 -> 1.372549 | K13: =WATER!I17 -> 0 | L13: =SUM(WATER!J17) -> 0 | M13: =WATER!Q17 -> 0 | N13: 0.6 | O13: =ELEC!B14 -> 46.989
A14: Beirut | B14: =B13+1 -> 13 | C14: 2 | D14: 2020 | E14: =ELEC!N15 -> 11590.6 | F14: =SUM('EDl log'!T16) -> 0.071227716 | G14: =-tanks!AW18 -> 735 | H14: =SUM(tanks!AV18) -> 0.54 | I14: =('B5'!AU17)*0.51 -> 193.8 | J14: ='B5'!AX17/0.51 -> 1.372549 | K14: =WATER!I18 -> 0 | L14: =SUM(WATER!J18) -> 0 | M14: =WATER!Q18 -> 0 | N14: 0.6 | O14: =ELEC!B15 -> 79.994
... A30: Beirut | B30: =B29+1 -> 29 | C30: 2 | D30: 2020 | E30: =ELEC!N31 -> 0 | F30: =SUM('EDl log'!T32) -> 0 | G30: =-tanks!AW34 -> 0 | H30: =SUM(tanks!AV34) -> 0.5165 | I30: =('B5'!AU33)*0.51 -> 0 | J30: ='B5'!AX33/0.51 -> 1.372549 | K30: =WATER!I34 -> 0 | L30: =SUM(WATER!J34) -> 0 | M30: =WATER!Q34 -> 0 | N30: 0.6 | O30: =ELEC!B31 -> 0
A31: Beirut | E31: =ELEC!N32 -> 0
A32: Beirut | E32: =ELEC!N33 -> 0

Sheet Submetering
A1: Site Name | B1: Day | C1: Month | D1: Year | E1: ATS1 Kwh | F1: ATS2 Kwh | G1: ATS3 Kwh | H1: ATS4 Kwh | I1: ATS5 Kwh | J1: Guest (m3) | K1: Kitchen & Laundry (m3) | L1: Room Nights
A2: Beirut | B2: 1 | C2: 2 | D2: 2020 | E2: =ELEC!M3 -> 3520 | F2: =ELEC!K3 -> 1372 | G2: =ELEC!I3 -> 1962 | H2: =ELEC!E3 -> 2503 | I2: =ELEC!G3 -> 1981 | J2: =WATER!Y6 -> 168 | K2: =WATER!AJ6 -> 58 | L2: =ELEC!B3 -> 33.994
A3: Beirut | B3: =B2+1 -> 2 | C3: 2 | D3: 2020 | E3: =ELEC!M4 -> 4766 | F3: =ELEC!K4 -> 1798 | G3: =ELEC!I4 -> 2192 | H3: =ELEC!E4 -> 2791 | I3: =ELEC!G4 -> 2234 | J3: =WATER!Y7 -> 0 | K3: =WATER!AJ7 -> 0 | L3: =ELEC!B4 -> 25.001
A4: Beirut | B4: =B3+1 -> 3 | C4: 2 | D4: 2020 | E4: =ELEC!M5 -> 3236 | F4: =ELEC!K5 -> 1446 | G4: =ELEC!I5 -> 1588 | H4: =ELEC!E5 -> 2364 | I4: =ELEC!G5 -> 1693 | J4: =WATER!Y8 -> 24 | K4: =WATER!AJ8 -> 43 | L4: =ELEC!B5 -> 27.002
A5: Beirut | B5: =B4+1 -> 4 | C5: 2 | D5: 2020 | E5: =ELEC!M6 -> 3902 | F5: =ELEC!K6 -> 1680 | G5: =ELEC!I6 -> 1948 | H5: =ELEC!E6 -> 2740 | I5: =ELEC!G6 -> 1944 | J5: =WATER!Y9 -> 2 | K5: =WATER!AJ9 -> 2 | L5: =ELEC!B6 -> 27.002
A6: Beirut | B6: =B5+1 -> 5 | C6: 2 | D6: 2020 | E6: =ELEC!M7 -> 4024 | F6: =ELEC!K7 -> 2528 | G6: =ELEC!I7 -> 1964 | H6: =ELEC!E7 -> 2836 | I6: =ELEC!G7 -> 1982 | J6: =WATER!Y10 -> 118 | K6: =WATER!AJ10 -> 79 | L6: =ELEC!B7 -> 33.994
A7: Beirut | B7: =B6+1 -> 6 | C7: 2 | D7: 2020 | E7: =ELEC!M8 -> 3578 | F7: =ELEC!K8 -> 1468 | G7: =ELEC!I8 -> 1744 | H7: =ELEC!E8 -> 2352 | I7: =ELEC!G8 -> 1866 | J7: =WATER!Y11 -> 101 | K7: =WATER!AJ11 -> 42 | L7: =ELEC!B8 -> 46
A8: Beirut | B8: =B7+1 -> 7 | C8: 2 | D8: 2020 | E8: =ELEC!M9 -> 4492 | F8: =ELEC!K9 -> 1532 | G8: =ELEC!I9 -> 1972 | H8: =ELEC!E9 -> 2488 | I8: =ELEC!G9 -> 2145 | J8: =WATER!Y12 -> 46 | K8: =WATER!AJ12 -> 67 | L8: =ELEC!B9 -> 45.011
A9: Beirut | B9: =B8+1 -> 8 | C9: 2 | D9: 2020 | E9: =ELEC!M10 -> 4476 | F9: =ELEC!K10 -> 1540 | G9: =ELEC!I10 -> 1836 | H9: =ELEC!E10 -> 2884 | I9: =ELEC!G10 -> 2094 | J9: =WATER!Y13 -> 0 | K9: =WATER!AJ13 -> 0 | L9: =ELEC!B10 -> 31.97
A10: Beirut | B10: =B9+1 -> 9 | C10: 2 | D10: 2020 | E10: =ELEC!M11 -> 3672 | F10: =ELEC!K11 -> 1226 | G10: =ELEC!I11 -> 1668 | H10: =ELEC!E11 -> 1838 | I10: =ELEC!G11 -> 2486 | J10: =WATER!Y14 -> 121 | K10: =WATER!AJ14 -> 99 | L10: =ELEC!B11 -> 35.006
A11: Beirut | B11: =B10+1 -> 10 | C11: 2 | D11: 2020 | E11: =ELEC!M12 -> 4204 | F11: =ELEC!K12 -> 1442 | G11: =ELEC!I12 -> 1990 | H11: =ELEC!E12 -> 1626 | I11: =ELEC!G12 -> 1256 | J11: =WATER!Y15 -> 0 | K11: =WATER!AJ15 -> 0 | L11: =ELEC!B12 -> 37.007
A12: Beirut | B12: =B11+1 -> 11 | C12: 2 | D12: 2020 | E12: =ELEC!M13 -> 3388 | F12: =ELEC!K13 -> 1748 | G12: =ELEC!I13 -> 2082 | H12: =ELEC!E13 -> 1812 | I12: =ELEC!G13 -> 1893 | J12: =WATER!Y16 -> 3 | K12: =WATER!AJ16 -> 1 | L12: =ELEC!B13 -> 33.994
A13: Beirut | B13: =B12+1 -> 12 | C13: 2 | D13: 2020 | E13: =ELEC!M14 -> 3704 | F13: =ELEC!K14 -> 1416 | G13: =ELEC!I14 -> 2220 | H13: =ELEC!E14 -> 2052 | I13: =ELEC!G14 -> 1971.4 | J13: =WATER!Y17 -> 0 | K13: =WATER!AJ17 -> 0 | L13: =ELEC!B14 -> 46.989
A14: Beirut | B14: =B13+1 -> 13 | C14: 2 | D14: 2020 | E14: =ELEC!M15 -> 3592 | F14: =ELEC!K15 -> 1374 | G14: =ELEC!I15 -> 2192 | H14: =ELEC!E15 -> 2308 | I14: =ELEC!G15 -> 2124.6 | J14: =WATER!Y18 -> 0 | K14: =WATER!AJ18 -> 0 | L14: =ELEC!B15 -> 79.994
... A30: Beirut | B30: =B29+1 -> 29 | C30: 2 | D30: 2020 | E30: =ELEC!M31 -> 0 | F30: =ELEC!K31 -> 0 | G30: =ELEC!I31 -> 0 | H30: =ELEC!E31 -> 0 | I30: =ELEC!G31 -> 0 | J30: =WATER!Y34 -> 0 | K30: =WATER!AJ34 -> 0 | L30: =ELEC!B31 -> 0
A31: Beirut
A32: Beirut

Sheet ELEC
A1: OOC | B1: Room OCC | D1: MDB3 | E1: MDB3/day | F1: EMDB2 | G1: EMDB2/day | H1: EMDB1 | I1: EMDB1/day | J1: MDB2 | K1: mdb2/day | L1: MDB1 | M1: MDB1/Day | N1: Total KWH | O1: KWH/Rooc | P1: Gen MHW | Q1: Gen/Day KWH | R1: EDL KWH | S1: CH1 RH | T1: RH | U1: C1h1 power | V1: CH1 Con KWH | W1: CH2 RH | X1: RH | Y1: Ch2 power | Z1: CH2 Con KWH | AA1: CH3 RH | AB1: RH | AC1: Ch3 power | AD1: CH3 Con KWH | AE1: RH total | AF1: KWH total | AG1: AVG chiller KW/Hr
A2: =[1]ELEC!$A$33 -> 0.1478 | B2: =[1]ELEC!$B$33 -> 33.994 | C2: 31-01-2020 | D2: 31388876 | E2: =[1]ELEC!E33 -> 1958 | F2: 3496407 | G2: =[1]ELEC!G33 -> 1865.8 | H2: 17285396 | I2: =[1]ELEC!I33 -> 1934 | J2: =[1]ELEC!J33 -> 28279902 | K2: =[1]ELEC!K33 -> 1240 | L2: =[1]ELEC!L33 -> 22645064 | M2: =[1]ELEC!M33 -> 3350 | N2: =[1]ELEC!N33 -> 10347.8 | O2: =[1]ELEC!O33 -> 304.40078 | P2: =[1]ELEC!P33 -> 15304.848 | ... AJ2: =[1]ELEC!AJ33 -> 0
A3: ='General information '!F6 -> 0.1478 | B3: =SUM(230*A3) -> 33.994 | C3: 43862 | D3: 31391379 | E3: =D3-D2 -> 2503 | F3: 3498388 | G3: =F3-F2 -> 1981 | H3: 17287358 | I3: =H3-H2 -> 1962 | J3: 28281274 | K3: =J3-J2 -> 1372 | L3: 22648584 | M3: =L3-L2 -> 3520 | N3: =M3+K3+I3+G3+E3 -> 11338 | O3: =IF(B3>0,N3/B3,0) -> 333.52945 | P3: 15307.274 | Q3: =(P3-P2)*1000 -> 2426 | R3: =+N3-Q3 -> 8912 | S3: 8373 | T3: =S3-S2 -> 2 | U3: 1022099 | V3: =U3-U2 -> 469 | W3: =W2 -> 31840 | X3: =W3-W2 -> 0 | Y3: =Y2 -> 623360 | Z3: =Y3-Y2 -> 0 | AA3: =AA2 -> 34877 | AB3: =AA3-AA2 -> 0 | AC3: =AC2 -> 740427 | AD3: =AC3-AC2 -> 0 | AE3: =AB3+X3+T3 -> 2 | AF3: =V3+Z3+AD3 -> 469 | AG3: =IF(AE3>0,AF3/AE3,0) -> 234.5
A4: ='General information '!F7 -> 0.1087 | B4: =SUM(230*A4) -> 25.001 | C4: 43863 | D4: 31394170 | E4: =D4-D3 -> 2791 | F4: 3500622 | G4: =F4-F3 -> 2234 | H4: 17289550 | I4: =H4-H3 -> 2192 | J4: 28283072 | K4: =J4-J3 -> 1798 | L4: 22653350 | M4: =L4-L3 -> 4766 | N4: =M4+K4+I4+G4+E4 -> 13781 | O4: =IF(B4>0,N4/B4,0) -> 551.21795 | P4: 15309.206 | Q4: =(P4-P3)*1000 -> 1932 | R4: =N4-Q4 -> 11849 | S4: 8378 | T4: =S4-S3 -> 5 | U4: 1023028 | V4: =U4-U3 -> 929 | W4: 31840 | X4: =W4-W3 -> 0 | Y4: =Y3 -> 623360 | Z4: =Y4-Y3 -> 0 | AA4: 34878 | AB4: =AA4-AA3 -> 1 | AC4: 740548 | AD4: =AC4-AC3 -> 121 | AE4: =AB4+X4+T4 -> 6 | AF4: =V4+Z4+AD4 -> 1050 | AG4: =IF(AE4>0,AF4/AE4,0) -> 175
A5: ='General information '!F8 -> 0.1174 | B5: =SUM(230*A5) -> 27.002 | C5: 43864 | D5: 31396534 | E5: =D5-D4 -> 2364 | F5: 3502315 | G5: =F5-F4 -> 1693 | H5: 17291138 | I5: =H5-H4 -> 1588 | J5: 28284518 | K5: =J5-J4 -> 1446 | L5: 22656586 | M5: =L5-L4 -> 3236 | N5: =M5+K5+I5+G5+E5 -> 10327 | O5: =IF(B5>0,N5/B5,0) -> 382.45315 | P5: 15312.064 | Q5: =(P5-P4)*1000 -> 2858 | R5: =N5-Q5 -> 7469 | S5: 8379 | T5: =S5-S4 -> 1 | U5: 1023092 | V5: =U5-U4 -> 64 | W5: 31841 | X5: =W5-W4 -> 1 | Y5: 623507 | Z5: =Y5-Y4 -> 147 | AA5: 34879 | AB5: =AA5-AA4 -> 1 | AC5: 740830 | AD5: =AC5-AC4 -> 282 | AE5: =AB5+X5+T5 -> 3 | AF5: =V5+Z5+AD5 -> 493 | AG5: =IF(AE5>0,AF5/AE5,0) -> 164.33333 | AI5: =R5-'EDl log'!B3 -> -49419805
A6: ='General information '!F9 -> 0.1174 | B6: =SUM(230*A6) -> 27.002 | C6: 43865 | D6: 31399274 | E6: =D6-D5 -> 2740 | F6: 3504259 | G6: =F6-F5 -> 1944 | H6: 17293086 | I6: =H6-H5 -> 1948 | J6: 28286198 | K6: =J6-J5 -> 1680 | L6: 22660488 | M6: =L6-L5 -> 3902 | N6: =M6+K6+I6+G6+E6 -> 12214 | O6: =IF(B6>0,N6/B6,0) -> 452.33686 | P6: 15314.842 | Q6: =(P6-P5)*1000 -> 2778 | R6: =N6-Q6 -> 9436 | S6: =S5 -> 8379 | T6: =S6-S5 -> 0 | U6: =U5 -> 1023092 | V6: =U6-U5 -> 0 | W6: =W5 -> 31841 | X6: =W6-W5 -> 0 | Y6: =Y5 -> 623507 | Z6: =Y6-Y5 -> 0 | AA6: 34882 | AB6: =AA6-AA5 -> 3 | AC6: 741247 | AD6: =AC6-AC5 -> 417 | AE6: =AB6+X6+T6 -> 3 | AF6: =V6+Z6+AD6 -> 417 | AG6: =IF(AE6>0,AF6/AE6,0) -> 139 | AI6: =R6-'EDl log'!B4 -> -49422471
A7: ='General information '!F10 -> 0.1478 | B7: =SUM(230*A7) -> 33.994 | C7: 43866 | D7: 31402110 | E7: =D7-D6 -> 2836 | F7: 3506241 | G7: =F7-F6 -> 1982 | H7: 17295050 | I7: =H7-H6 -> 1964 | J7: 28288726 | K7: =J7-J6 -> 2528 | L7: 22664512 | M7: =L7-L6 -> 4024 | N7: =M7+K7+I7+G7+E7 -> 13334 | O7: =IF(B7>0,N7/B7,0) -> 392.24569 | P7: 15317.023 | Q7: =(P7-P6)*1000 -> 2181 | R7: =N7-Q24 -> 10670 | S7: 8379 | T7: =S7-S6 -> 0 | U7: 1023092 | V7: =U7-U6 -> 0 | W7: 31843 | X7: =W7-W6 -> 2 | Y7: 624129 | Z7: =Y7-Y6 -> 622 | AA7: 34882 | AB7: =AA7-AA6 -> 0 | AC7: 741247 | AD7: =AC7-AC6 -> 0 | AE7: =AB7+X7+T7 -> 2 | AF7: =V7+Z7+AD7 -> 622 | AG7: =IF(AE7>0,AF7/AE7,0) -> 311 | AI7: =R7-'EDl log'!B5 -> -49427349
A8: ='General information '!F11 -> 0.2 | B8: =SUM(230*A8) -> 46 | C8: 43867 | D8: 31404462 | E8: =D8-D7 -> 2352 | F8: 3508107 | G8: =F8-F7 -> 1866 | H8: 17296794 | I8: =H8-H7 -> 1744 | J8: 28290194 | K8: =J8-J7 -> 1468 | L8: 22668090 | M8: =L8-L7 -> 3578 | N8: =M8+K8+I8+G8+E8 -> 11008 | O8: =IF(B8>0,N8/B8,0) -> 239.30435 | P8: 15318.894 | Q8: =(P8-P7)*1000 -> 1871 | R8: =N8-Q8 -> 9137 | S8: =S7 -> 8379 | T8: =S8-S7 -> 0 | U8: =U7 -> 1023092 | V8: =U8-U7 -> 0 | W8: 31845 | X8: =W8-W7 -> 2 | Y8: 624369 | Z8: =Y8-Y7 -> 240 | AA8: 34883 | AB8: =AA8-AA7 -> 1 | AC8: 741440 | AD8: =AC8-AC7 -> 193 | AE8: =AB8+X8+T8 -> 3 | AF8: =V8+Z8+AD8 -> 433 | AG8: =IF(AE8>0,AF8/AE8,0) -> 144.33333 | AI8: =R8-'EDl log'!B6 -> -49432747
A9: ='General information '!F12 -> 0.1957 | B9: =SUM(230*A9) -> 45.011 | C9: 43868 | D9: 31406950 | E9: =D9-D8 -> 2488 | F9: 3510252 | G9: =F9-F8 -> 2145 | H9: 17298766 | I9: =H9-H8 -> 1972 | J9: 28291726 | K9: =J9-J8 -> 1532 | L9: 22672582 | M9: =L9-L8 -> 4492 | N9: =M9+K9+I9+G9+E9 -> 12629 | O9: =IF(B9>0,N9/B9,0) -> 280.57586 | P9: 15321.643 | Q9: =(P9-P8)*1000 -> 2749 | R9: =N9-Q9 -> 9880 | S9: 8380 | T9: =S9-S8 -> 1 | U9: 1023424 | V9: =U9-U8 -> 332 | W9: =W8 -> 31845 | X9: =W9-W8 -> 0 | Y9: =Y8 -> 624369 | Z9: =Y9-Y8 -> 0 | AA9: =AA8 -> 34883 | AB9: =AA9-AA8 -> 0 | AC9: =AC8 -> 741440 | AD9: =AC9-AC8 -> 0 | AE9: =AB9+X9+T9 -> 1 | AF9: =V9+Z9+AD9 -> 332 | AG9: =IF(AE9>0,AF9/AE9,0) -> 332 | AI9: =R9-'EDl log'!B7 -> -49436888
A10: ='General information '!F13 -> 0.139 | B10: =SUM(230*A10) -> 31.97 | C10: 43869 | D10: 31409834 | E10: =D10-D9 -> 2884 | F10: 3512346 | G10: =F10-F9 -> 2094 | H10: 17300602 | I10: =H10-H9 -> 1836 | J10: 28293266 | K10: =J10-J9 -> 1540 | L10: 22677058 | M10: =L10-L9 -> 4476 | N10: =M10+K10+I10+G10+E10 -> 12830 | O10: =IF(B10>0,N10/B10,0) -> 401.31373 | P10: 15323.08 | Q10: =(P10-P9)*1000 -> 1437 | R10: =N10-Q10 -> 11393 | S10: 8382 | T10: =S10-S9 -> 2 | U10: 1023764 | V10: =U10-U9 -> 340 | W10: 31845 | X10: =W10-W9 -> 0 | Y10: 624440 | Z10: =Y10-Y9 -> 71 | AA10: 34883 | AB10: =AA10-AA9 -> 0 | AC10: 741441 | AD10: =AC10-AC9 -> 1 | AE10: =AB10+X10+T10 -> 2 | AF10: =V10+Z10+AD10 -> 412 | AG10: =IF(AE10>0,AF10/AE10,0) -> 206 | AI10: =R10-'EDl log'!B8 -> -49440422
A11: ='General information '!F14 -> 0.1522 | B11: =SUM(230*A11) -> 35.006 | C11: 43870 | D11: 31411672 | E11: =D11-D10 -> 1838 | F11: 3514832 | G11: =F11-F10 -> 2486 | H11: 17302270 | I11: =H11-H10 -> 1668 | J11: 28294492 | K11: =J11-J10 -> 1226 | L11: 22680730 | M11: =L11-L10 -> 3672 | N11: =M11+K11+I11+G11+E11 -> 10890 | O11: =IF(B11>0,N11/B11,0) -> 311.08953 | P11: 15325.17 | Q11: =(P11-P10)*1000 -> 2090 | R11: =N11-Q11 -> 8800 | S11: 8382 | T11: =S11-S10 -> 0 | U11: =U10 -> 1023764 | V11: =U11-U10 -> 0 | W11: =W10 -> 31845 | X11: =W11-W10 -> 0 | Y11: =Y10 -> 624440 | Z11: =Y11-Y10 -> 0 | AA11: 34887 | AB11: =AA11-AA10 -> 4 | AC11: 742049 | AD11: =AC11-AC10 -> 608 | AE11: =AB11+X11+T11 -> 4 | AF11: =V11+Z11+AD11 -> 608 | AG11: =IF(AE11>0,AF11/AE11,0) -> 152 | AI11: =R11-'EDl log'!B9 -> -49448459
A12: ='General information '!F15 -> 0.1609 | B12: =SUM(230*A12) -> 37.007 | C12: 43871 | D12: 31413298 | E12: =D12-D11 -> 1626 | F12: 3516088 | G12: =F12-F11 -> 1256 | H12: 17304260 | I12: =H12-H11 -> 1990 | J12: 28295934 | K12: =J12-J11 -> 1442 | L12: 22684934 | M12: =L12-L11 -> 4204 | N12: =M12+K12+I12+G12+E12 -> 10518 | O12: =IF(B12>0,N12/B12,0) -> 284.2165 | P12: 15326.76 | Q12: =(P12-P11)*1000 -> 1590 | R12: =N12-Q12 -> 8928 | S12: 8382 | T12: =S12-S11 -> 0 | U12: 1023764 | V12: =U12-U11 -> 0 | W12: 31845 | X12: =W12-W11 -> 0 | Y12: 624440 | Z12: =Y12-Y11 -> 0 | AA12: 34888 | AB12: =AA12-AA11 -> 1 | AC12: 742070 | AD12: =AC12-AC11 -> 21 | AE12: =AB12+X12+T12 -> 1 | AF12: =V12+Z12+AD12 -> 21 | AG12: =IF(AE12>0,AF12/AE12,0) -> 21 | AI12: =R12-'EDl log'!B10 -> -49453440
A13: ='General information '!F16 -> 0.1478 | B13: =SUM(230*A13) -> 33.994 | C13: 43872 | D13: 31415110 | E13: =D13-D12 -> 1812 | F13: 3517981 | G13: =F13-F12 -> 1893 | H13: 17306342 | I13: =H13-H12 -> 2082 | J13: 28297682 | K13: =J13-J12 -> 1748 | L13: 22688322 | M13: =L13-L12 -> 3388 | N13: =M13+K13+I13+G13+E13 -> 10923 | O13: =IF(B13>0,N13/B13,0) -> 321.32141 | P13: 15328.411 | Q13: =(P13-P12)*1000 -> 1651 | R13: =N13-Q13 -> 9272 | S13: 8382 | T13: =S13-S12 -> 0 | U13: 1023769 | V13: =U13-U12 -> 5 | W13: 31845 | X13: =W13-W12 -> 0 | Y13: 624440 | Z13: =Y13-Y12 -> 0 | AA13: 34888 | AB13: =AA13-AA12 -> 0 | AC13: 742070 | AD13: =AC13-AC12 -> 0 | AE13: =AB13+X13+T13 -> 0 | AF13: =V13+Z13+AD13 -> 5 | AG13: =IF(AE13>0,AF13/AE13,0) -> 0 | AI13: =R13-'EDl log'!B11 -> -49459020
A14: ='General information '!F17 -> 0.2043 | B14: =SUM(230*A14) -> 46.989 | C14: 43873 | D14: 31417162 | E14: =D14-D13 -> 2052 | F14: 3519952.4 | G14: =F14-F13 -> 1971.4 | H14: 17308562 | I14: =H14-H13 -> 2220 | J14: 28299098 | K14: =J14-J13 -> 1416 | L14: 22692026 | M14: =L14-L13 -> 3704 | N14: =M14+K14+I14+G14+E14 -> 11363.4 | O14: =IF(B14>0,N14/B14,0) -> 241.83107 | P14: 15330.121 | Q14: =(P14-P13)*1000 -> 1710 | R14: =N14-Q14 -> 9653.4 | S14: 8383 | T14: =S14-S13 -> 1 | U14: 1023979 | V14: =U14-U13 -> 210 | W14: =W13 -> 31845 | X14: =W14-W13 -> 0 | Y14: =Y13 -> 624440 | Z14: =Y14-Y13 -> 0 | AA14: =AA13 -> 34888 | AB14: =AA14-AA13 -> 0 | AC14: 742158 | AD14: =AC14-AC13 -> 88 | AE14: =AB14+X14+T14 -> 1 | AF14: =V14+Z14+AD14 -> 298 | AG14: =IF(AE14>0,AF14/AE14,0) -> 298 | AI14: =R14-'EDl log'!B12 -> -49462867
A15: ='General information '!F18 -> 0.3478 | B15: =SUM(230*A15) -> 79.994 | C15: 43874 | D15: 31419470 | E15: =D15-D14 -> 2308 | F15: 3522077 | G15: =F15-F14 -> 2124.6 | H15: 17310754 | I15: =H15-H14 -> 2192 | J15: 28300472 | K15: =J15-J14 -> 1374 | L15: 22695618 | M15: =L15-L14 -> 3592 | N15: =M15+K15+I15+G15+E15 -> 11590.6 | O15: =IF(B15>0,N15/B15,0) -> 144.89337 | P15: 15332.234 | Q15: =(P15-P14)*1000 -> 2113 | R15: =N15-Q15 -> 9477.6 | S15: 8383 | T15: =S15-S14 -> 0 | U15: 1023979 | V15: =U15-U14 -> 0 | W15: 31845 | X15: =W15-W14 -> 0 | Y15: 624440 | Z15: =Y15-Y14 -> 0 | AA15: 34890 | AB15: =AA15-AA14 -> 2 | AC15: 742464 | AD15: =AC15-AC14 -> 306 | AE15: =AB15+X15+T15 -> 2 | AF15: =V15+Z15+AD15 -> 306 | AG15: =IF(AE15>0,AF15/AE15,0) -> 153 | AI15: =R15-'EDl log'!B13 -> -49467996
A16: ='General information '!F19 -> 0.3826 | B16: =SUM(230*A16) -> 87.998 | C16: 43875 | D16: 31423330 | E16: =D16-D15 -> 3860 | F16: 3524322 | G16: =F16-F15 -> 2245 | H16: 17312988 | I16: =H16-H15 -> 2234 | J16: 28302050 | K16: =J16-J15 -> 1578 | L16: 22699674 | M16: =L16-L15 -> 4056 | N16: =M16+K16+I16+G16+E16 -> 13973 | O16: =IF(B16>0,N16/B16,0) -> 158.7877 | P16: 15334.331 | Q16: =(P16-P15)*1000 -> 2097 | R16: =N16-Q16 -> 11876 | S16: 8384 | T16: =S16-S15 -> 1 | U16: 1024343 | V16: =U16-U15 -> 364 | W16: =W15 -> 31845 | X16: =W16-W15 -> 0 | Y16: =Y15 -> 624440 | Z16: =Y16-Y15 -> 0 | AA16: 34895 | AB16: =AA16-AA15 -> 5 | AC16: 743301 | AD16: =AC16-AC15 -> 837 | AE16: =AB16+X16+T16 -> 6 | AF16: =V16+Z16+AD16 -> 1201 | AG16: =IF(AE16>0,AF16/AE16,0) -> 200.16667 | AI16: =R16-'EDl log'!B14 -> -49470408
A17: ='General information '!F20 -> 0.247 | B17: =SUM(230*A17) -> 56.81 | C17: 43876 | D17: 31426858 | E17: =D17-D16 -> 3528 | F17: 3526558.8 | G17: =F17-F16 -> 2236.8 | H17: 17315262 | I17: =H17-H16 -> 2274 | J17: 28303566 | K17: =J17-J16 -> 1516 | L17: 22703290 | M17: =L17-L16 -> 3616 | N17: =M17+K17+I17+G17+E17 -> 13170.8 | O17: =IF(B17>0,N17/B17,0) -> 231.83946 | P17: 15336.825 | Q17: =(P17-P16)*1000 -> 2494 | R17: =N17-Q17 -> 10676.8 | S17: =S16 -> 8384 | T17: =S17-S16 -> 0 | U17: =U16 -> 1024343 | V17: =U17-U16 -> 0 | W17: =W16 -> 31845 | X17: =W17-W16 -> 0 | Y17: =Y16 -> 624440 | Z17: =Y17-Y16 -> 0 | AA17: 34900 | AB17: =AA17-AA16 -> 5 | AC17: 744360 | AD17: =AC17-AC16 -> 1059 | AE17: =AB17+X17+T17 -> 5 | AF17: =V17+Z17+AD17 -> 1059 | AG17: =IF(AE17>0,AF17/AE17,0) -> 211.8 | AI17: =R17-'EDl log'!B15 -> -49476609
A18: ='General information '!F21 -> 0.1696 | B18: =SUM(230*A18) -> 39.008 | C18: 43877 | D18: 31430446 | E18: =D18-D17 -> 3588 | F18: 3528846 | G18: =F18-F17 -> 2287.2 | H18: 17317582 | I18: =H18-H17 -> 2320 | J18: 28305092 | K18: =J18-J17 -> 1526 | L18: 22707034 | M18: =L18-L17 -> 3744 | N18: =M18+K18+I18+G18+E18 -> 13465.2 | O18: =IF(B18>0,N18/B18,0) -> 345.19073 | P18: 15337.7 | Q18: =(P18-P17)*1000 -> 875 | R18: =N18-Q18 -> 12590.2 | S18: =S17 -> 8384 | T18: =S18-S17 -> 0 | U18: =U17 -> 1024343 | V18: =U18-U17 -> 0 | W18: =W17 -> 31845 | X18: =W18-W17 -> 0 | Y18: =Y17 -> 624440 | Z18: =Y18-Y17 -> 0 | AA18: 34903 | AB18: =AA18-AA17 -> 3 | AC18: 744994 | AD18: =AC18-AC17 -> 634 | AE18: =AB18+X18+T18 -> 3 | AF18: =V18+Z18+AD18 -> 634 | AG18: =IF(AE18>0,AF18/AE18,0) -> 211.33333 | AI18: =R18-'EDl log'!B16 -> -49479605
A19: ='General information '!F22 -> 0.2304 | B19: =SUM(230*A19) -> 52.992 | C19: 43878 | D19: 31434710 | E19: =D19-D18 -> 4264 | F19: 3530950 | G19: =F19-F18 -> 2104 | H19: 17319762 | I19: =H19-H18 -> 2180 | J19: 28306616 | K19: =J19-J18 -> 1524 | L19: 22710454 | M19: =L19-L18 -> 3420 | N19: =M19+K19+I19+G19+E19 -> 13492 | O19: =IF(B19>0,N19/B19,0) -> 254.60447 | P19: 15339.919 | Q19: =(P19-P18)*1000 -> 2219 | R19: =N19-Q19 -> 11273 | S19: 8384 | T19: =S19-S18 -> 0 | U19: 1024343 | V19: =U19-U18 -> 0 | W19: 31845 | X19: =W19-W18 -> 0 | Y19: 624440 | Z19: =Y19-Y18 -> 0 | AA19: 34907 | AB19: =AA19-AA18 -> 4 | AC19: 745923 | AD19: =AC19-AC18 -> 929 | AE19: =AB19+X19+T19 -> 4 | AF19: =V19+Z19+AD19 -> 929 | AG19: =IF(AE19>0,AF19/AE19,0) -> 232.25 | AI19: =R19-'EDl log'!B17 -> -49487057
A20: ='General information '!F23 -> 0.2348 | B20: =SUM(230*A20) -> 54.004 | C20: 43879 | D20: 31438132 | E20: =D20-D19 -> 3422 | F20: 3532897 | G20: =F20-F19 -> 1947 | H20: 17321730 | I20: =H20-H19 -> 1968 | J20: 28308028 | K20: =J20-J19 -> 1412 | L20: 22713590 | M20: =L20-L19 -> 3136 | N20: =M20+K20+I20+G20+E20 -> 11885 | O20: =IF(B20>0,N20/B20,0) -> 220.07629 | P20: 15342.182 | Q20: =(P20-P19)*1000 -> 2263 | R20: =N20-Q20 -> 9622 | S20: 8384 | T20: =S20-S19 -> 0 | U20: 1024343 | V20: =U20-U19 -> 0 | W20: 31845 | X20: =W20-W19 -> 0 | Y20: 624440 | Z20: =Y20-Y19 -> 0 | AA20: 34911 | AB20: =AA20-AA19 -> 4 | AC20: 746724 | AD20: =AC20-AC19 -> 801 | AE20: =AB20+X20+T20 -> 4 | AF20: =V20+Z20+AD20 -> 801 | AG20: =IF(AE20>0,AF20/AE20,0) -> 200.25 | AI20: =R20-'EDl log'!B18 -> -49494226
A21: ='General information '!F24 -> 0.2304 | B21: =SUM(230*A21) -> 52.992 | C21: 43880 | D21: 31441234 | E21: =D21-D20 -> 3102 | F21: 3534911 | G21: =F21-F20 -> 2014 | H21: 17323880 | I21: =H21-H20 -> 2150 | J21: 28309470 | K21: =J21-J20 -> 1442 | L21: 22716958 | M21: =L21-L20 -> 3368 | N21: =M21+K21+I21+G21+E21 -> 12076 | O21: =IF(B21>0,N21/B21,0) -> 227.88345 | P21: 15344.795 | Q21: =(P21-P20)*1000 -> 2613 | R21: =N21-Q21 -> 9463 | S21: 8384 | T21: =S21-S20 -> 0 | U21: 1024343 | V21: =U21-U20 -> 0 | W21: 31845 | X21: =W21-W20 -> 0 | Y21: 624440 | Z21: =Y21-Y20 -> 0 | AA21: 34913 | AB21: =AA21-AA20 -> 2 | AC21: 747174 | AD21: =AC21-AC20 -> 450 | AE21: =AB21+X21+T21 -> 2 | AF21: =V21+Z21+AD21 -> 450 | AG21: =IF(AE21>0,AF21/AE21,0) -> 225 | AI21: =R21-'EDl log'!B19 -> -49500889
A22: ='General information '!F25 -> 0.2261 | B22: =SUM(230*A22) -> 52.003 | C22: 43881 | D22: 31444914 | E22: =D22-D21 -> 3680 | F22: 3536916 | G22: =F22-F21 -> 2005 | H22: 17325874 | I22: =H22-H21 -> 1994 | J22: 28310926 | K22: =J22-J21 -> 1456 | L22: 22720206 | M22: =L22-L21 -> 3248 | N22: =M22+K22+I22+G22+E22 -> 12383 | O22: =IF(B22>0,N22/B22,0) -> 238.12088 | P22: 15346.83 | Q22: =(P22-P21)*1000 -> 2035 | R22: =N22-Q22 -> 10348 | S22: 8384 | T22: =S22-S21 -> 0 | U22: 1024343 | V22: =U22-U21 -> 0 | W22: 31845 | X22: =W22-W21 -> 0 | Y22: 624440 | Z22: =Y22-Y21 -> 0 | AA22: 34918 | AB22: =AA22-AA21 -> 5 | AC22: 748034 | AD22: =AC22-AC21 -> 860 | AE22: =AB22+X22+T22 -> 5 | AF22: =V22+Z22+AD22 -> 860 | AG22: =IF(AE22>0,AF22/AE22,0) -> 172 | AI22: =R22-'EDl log'!B20 -> -49505865
A23: ='General information '!F26 -> 0.2478 | B23: =SUM(230*A23) -> 56.994 | C23: 43882 | D23: 31449362 | E23: =D23-D22 -> 4448 | F23: 3538936 | G23: =F23-F22 -> 2020 | H23: 17327918 | I23: =H23-H22 -> 2044 | J23: 28312595 | K23: =J23-J22 -> 1669 | L23: 22723562 | M23: =L23-L22 -> 3356 | N23: =M23+K23+I23+G23+E23 -> 13537 | O23: =IF(B23>0,N23/B23,0) -> 237.51623 | P23: 15349.098 | Q23: =(P23-P22)*1000 -> 2268 | R23: =N23-Q23 -> 11269 | S23: 8384 | T23: =S23-S22 -> 0 | U23: =U22 -> 1024343 | V23: =U23-U22 -> 0 | W23: =W22 -> 31845 | X23: =W23-W22 -> 0 | Y23: =Y22 -> 624440 | Z23: =Y23-Y22 -> 0 | AA23: 34924 | AB23: =AA23-AA22 -> 6 | AC23: 749155 | AD23: =AC23-AC22 -> 1121 | AE23: =AB23+X23+T23 -> 6 | AF23: =V23+Z23+AD23 -> 1121 | AG23: =IF(AE23>0,AF23/AE23,0) -> 186.83333 | AI23: =R23-'EDl log'!B21 -> -49509924
A24: ='General information '!F27 -> 0.1826 | B24: =SUM(230*A24) -> 41.998 | C24: 43883 | D24: 31453650 | E24: =D24-D23 -> 4288 | F24: 3541037 | G24: =F24-F23 -> 2101 | H24: 17330058 | I24: =H24-H23 -> 2140 | J24: 28314274 | K24: =J24-J23 -> 1679 | L24: 22727126 | M24: =L24-L23 -> 3564 | N24: =M24+K24+I24+G24+E24 -> 13772 | O24: =IF(B24>0,N24/B24,0) -> 327.92038 | P24: 15351.762 | Q24: =(P24-P23)*1000 -> 2664 | R24: =N24-Q24 -> 11108 | S24: =S23 -> 8384 | T24: =S24-S23 -> 0 | U24: =U23 -> 1024343 | V24: =U24-U23 -> 0 | W24: =W23 -> 31845 | X24: =W24-W23 -> 0 | Y24: =Y23 -> 624440 | Z24: =Y24-Y23 -> 0 | AA24: 34929 | AB24: =AA24-AA23 -> 5 | AC24: 750150 | AD24: =AC24-AC23 -> 995 | AE24: =AB24+X24+T24 -> 5 | AF24: =V24+Z24+AD24 -> 995 | AG24: =IF(AE24>0,AF24/AE24,0) -> 199 | AI24: =R24-'EDl log'!B22 -> -49514934
A25: ='General information '!F28 -> 0.1391 | B25: =SUM(230*A25) -> 31.993 | C25: 43884 | D25: 31458170 | E25: =D25-D24 -> 4520 | F25: 3543226 | G25: =F25-F24 -> 2189 | H25: 17332322 | I25: =H25-H24 -> 2264 | J25: 28316014 | K25: =J25-J24 -> 1740 | L25: 22730712 | M25: =L25-L24 -> 3586 | N25: =M25+K25+I25+G25+E25 -> 14299 | O25: =IF(B25>0,N25/B25,0) -> 446.94152 | P25: 15355.608 | Q25: =(P25-P24)*1000 -> 3846 | R25: =N25-Q25 -> 10453 | S25: 8384 | T25: =S25-S24 -> 0 | U25: 1024343 | V25: =U25-U24 -> 0 | W25: 31845 | X25: =W25-W24 -> 0 | Y25: 624440 | Z25: =Y25-Y24 -> 0 | AA25: 34936 | AB25: =AA25-AA24 -> 7 | AC25: 751223 | AD25: =AC25-AC24 -> 1073 | AE25: =AB25+X25+T25 -> 7 | AF25: =V25+Z25+AD25 -> 1073 | AG25: =IF(AE25>0,AF25/AE25,0) -> 153.28571 | AI25: =R25-'EDl log'!B23 -> -49520999
A26: ='General information '!F29 -> 0 | B26: =SUM(230*A26) -> 0 | C26: 43885 | D26: =D25 -> 31458170 | E26: =D26-D25 -> 0 | F26: =F25 -> 3543226 | G26: =F26-F25 -> 0 | H26: =H25 -> 17332322 | I26: =H26-H25 -> 0 | J26: =J25 -> 28316014 | K26: =J26-J25 -> 0 | L26: =L25 -> 22730712 | M26: =L26-L25 -> 0 | N26: =M26+K26+I26+G26+E26 -> 0 | O26: =IF(B26>0,N26/B26,0) -> 0 | P26: =P25 -> 15355.608 | Q26: =(P26-P25)*1000 -> 0 | R26: =N26-Q26 -> 0 | S26: =S25 -> 8384 | T26: =S26-S25 -> 0 | U26: =U25 -> 1024343 | V26: =U26-U25 -> 0 | W26: =W25 -> 31845 | X26: =W26-W25 -> 0 | Y26: =Y25 -> 624440 | Z26: =Y26-Y25 -> 0 | AA26: =AA25 -> 34936 | AB26: =AA26-AA25 -> 0 | AC26: =AC25 -> 751223 | AD26: =AC26-AC25 -> 0 | AE26: =AB26+X26+T26 -> 0 | AF26: =V26+Z26+AD26 -> 0 | AG26: =IF(AE26>0,AF26/AE26,0) -> 0 | AI26: =R26-'EDl log'!B24 -> -49537279
A27: ='General information '!F30 -> 0 | B27: =SUM(230*A27) -> 0 | C27: 43886 | D27: =D26 -> 31458170 | E27: =D27-D26 -> 0 | F27: =F26 -> 3543226 | G27: =F27-F26 -> 0 | H27: =H26 -> 17332322 | I27: =H27-H26 -> 0 | J27: =J26 -> 28316014 | K27: =J27-J26 -> 0 | L27: =L26 -> 22730712 | M27: =L27-L26 -> 0 | N27: =M27+K27+I27+G27+E27 -> 0 | O27: =IF(B27>0,N27/B27,0) -> 0 | P27: =P26 -> 15355.608 | Q27: =(P27-P26)*1000 -> 0 | R27: =N27-Q27 -> 0 | S27: =S26 -> 8384 | T27: =S27-S26 -> 0 | U27: =U26 -> 1024343 | V27: =U27-U26 -> 0 | W27: =W26 -> 31845 | X27: =W27-W26 -> 0 | Y27: =Y26 -> 624440 | Z27: =Y27-Y26 -> 0 | AA27: =AA26 -> 34936 | AB27: =AA27-AA26 -> 0 | AC27: =AC26 -> 751223 | AD27: =AC27-AC26 -> 0 | AE27: =AB27+X27+T27 -> 0 | AF27: =V27+Z27+AD27 -> 0 | AG27: =IF(AE27>0,AF27/AE27,0) -> 0 | AI27: =R27-'EDl log'!B25 -> -49543046
A28: ='General information '!F31 -> 0 | B28: =SUM(230*A28) -> 0 | C28: 43887 | D28: =D27 -> 31458170 | E28: =D28-D27 -> 0 | F28: =F27 -> 3543226 | G28: =F28-F27 -> 0 | H28: =H27 -> 17332322 | I28: =H28-H27 -> 0 | J28: =J27 -> 28316014 | K28: =J28-J27 -> 0 | L28: =L27 -> 22730712 | M28: =L28-L27 -> 0 | N28: =M28+K28+I28+G28+E28 -> 0 | O28: =IF(B28>0,N28/B28,0) -> 0 | P28: =P27 -> 15355.608 | Q28: =(P28-P27)*1000 -> 0 | R28: =N28-Q28 -> 0 | S28: =S27 -> 8384 | T28: =S28-S27 -> 0 | U28: =U27 -> 1024343 | V28: =U28-U27 -> 0 | W28: =W27 -> 31845 | X28: =W28-W27 -> 0 | Y28: =Y27 -> 624440 | Z28: =Y28-Y27 -> 0 | AA28: =AA27 -> 34936 | AB28: =AA28-AA27 -> 0 | AC28: =AC27 -> 751223 | AD28: =AC28-AC27 -> 0 | AE28: =AB28+X28+T28 -> 0 | AF28: =V28+Z28+AD28 -> 0 | AG28: =IF(AE28>0,AF28/AE28,0) -> 0 | AI28: =R28-'EDl log'!B26 -> -49548451
A29: ='General information '!F32 -> 0 | B29: =SUM(230*A29) -> 0 | C29: 43888 | D29: =D28 -> 31458170 | E29: =D29-D28 -> 0 | F29: =F28 -> 3543226 | G29: =F29-F28 -> 0 | H29: =H28 -> 17332322 | I29: =H29-H28 -> 0 | J29: =J28 -> 28316014 | K29: =J29-J28 -> 0 | L29: =L28 -> 22730712 | M29: =L29-L28 -> 0 | N29: =M29+K29+I29+G29+E29 -> 0 | O29: =IF(B29>0,N29/B29,0) -> 0 | P29: =P28 -> 15355.608 | Q29: =(P29-P28)*1000 -> 0 | R29: =N29-Q29 -> 0 | S29: =S28 -> 8384 | T29: =S29-S28 -> 0 | U29: =U28 -> 1024343 | V29: =U29-U28 -> 0 | W29: =W28 -> 31845 | X29: =W29-W28 -> 0 | Y29: =Y28 -> 624440 | Z29: =Y29-Y28 -> 0 | AA29: =AA28 -> 34936 | AB29: =AA29-AA28 -> 0 | AC29: =AC28 -> 751223 | AD29: =AC29-AC28 -> 0 | AE29: =AB29+X29+T29 -> 0 | AF29: =V29+Z29+AD29 -> 0 | AG29: =IF(AE29>0,AF29/AE29,0) -> 0 | AI29: =R29-'EDl log'!B27 -> -49548451
A30: ='General information '!F33 -> 0 | B30: =SUM(230*A30) -> 0 | C30: 43889 | D30: =D29 -> 31458170 | E30: =D30-D29 -> 0 | F30: =F29 -> 3543226 | G30: =F30-F29 -> 0 | H30: =H29 -> 17332322 | I30: =H30-H29 -> 0 | J30: =J29 -> 28316014 | K30: =J30-J29 -> 0 | L30: =L29 -> 22730712 | M30: =L30-L29 -> 0 | N30: =M30+K30+I30+G30+E30 -> 0 | O30: =IF(B30>0,N30/B30,0) -> 0 | P30: =P29 -> 15355.608 | Q30: =(P30-P29)*1000 -> 0 | R30: =N30-Q30 -> 0 | S30: =S29 -> 8384 | T30: =S30-S29 -> 0 | U30: =U29 -> 1024343 | V30: =U30-U29 -> 0 | W30: =W29 -> 31845 | X30: =W30-W29 -> 0 | Y30: =Y29 -> 624440 | Z30: =Y30-Y29 -> 0 | AA30: =AA29 -> 34936 | AB30: =AA30-AA29 -> 0 | AC30: =AC29 -> 751223 | AD30: =AC30-AC29 -> 0 | AE30: =AB30+X30+T30 -> 0 | AF30: =V30+Z30+AD30 -> 0 | AG30: =IF(AE30>0,AF30/AE30,0) -> 0 | AI30: =R30-'EDl log'!B28 -> -49548451
A31: ='General information '!F34 -> 0 | B31: =SUM(230*A31) -> 0 | C31: 43890 | D31: =D30 -> 31458170 | E31: =D31-D30 -> 0 | F31: =F30 -> 3543226 | G31: =F31-F30 -> 0 | H31: =H30 -> 17332322 | I31: =H31-H30 -> 0 | J31: =J30 -> 28316014 | K31: =J31-J30 -> 0 | L31: =L30 -> 22730712 | M31: =L31-L30 -> 0 | N31: =M31+K31+I31+G31+E31 -> 0 | O31: =IF(B31>0,N31/B31,0) -> 0 | P31: =P30 -> 15355.608 | Q31: =(P31-P30)*1000 -> 0 | R31: =N31-Q31 -> 0 | S31: =S30 -> 8384 | T31: =S31-S30 -> 0 | U31: =U30 -> 1024343 | V31: =U31-U30 -> 0 | W31: =W30 -> 31845 | X31: =W31-W30 -> 0 | Y31: =Y30 -> 624440 | Z31: =Y31-Y30 -> 0 | AA31: =AA30 -> 34936 | AB31: =AA31-AA30 -> 0 | AC31: =AC30 -> 751223 | AD31: =AC31-AC30 -> 0 | AE31: =AB31+X31+T31 -> 0 | AF31: =V31+Z31+AD31 -> 0 | AG31: =IF(AE31>0,AF31/AE31,0) -> 0 | AI31: =R31-'EDl log'!B29 -> -49548451
A32: ='General information '!F35 -> 0 | B32: =SUM(230*A32) -> 0 | D32: =D31 -> 31458170 | E32: =D32-D31 -> 0 | F32: =F31 -> 3543226 | G32: =F32-F31 -> 0 | H32: =H31 -> 17332322 | I32: =H32-H31 -> 0 | J32: =J31 -> 28316014 | K32: =J32-J31 -> 0 | L32: =L31 -> 22730712 | M32: =L32-L31 -> 0 | N32: =M32+K32+I32+G32+E32 -> 0 | O32: =IF(B32>0,N32/B32,0) -> 0 | P32: =P31 -> 15355.608 | Q32: =(P32-P31)*1000 -> 0 | R32: =N32-Q32 -> 0 | S32: =S31 -> 8384 | T32: =S32-S31 -> 0 | U32: =U31 -> 1024343 | V32: =U32-U31 -> 0 | W32: =W31 -> 31845 | X32: =W32-W31 -> 0 | Y32: =Y31 -> 624440 | Z32: =Y32-Y31 -> 0 | AA32: =AA31 -> 34936 | AB32: =AA32-AA31 -> 0 | AC32: =AC31 -> 751223 | AD32: =AC32-AC31 -> 0 | AE32: =AB32+X32+T32 -> 0 | AF32: =V32+Z32+AD32 -> 0 | AG32: =IF(AE32>0,AF32/AE32,0) -> 0 | AI32: =R32-'EDl log'!B30 -> -49548451
A33: ='General information '!F36 -> 0 | B33: =SUM(230*A33) -> 0 | D33: =D32 -> 31458170 | E33: =D33-D32 -> 0 | F33: =F32 -> 3543226 | G33: =F33-F32 -> 0 | H33: =H32 -> 17332322 | I33: =H33-H32 -> 0 | J33: =J32 -> 28316014 | K33: =J33-J32 -> 0 | L33: =L32 -> 22730712 | M33: =L33-L32 -> 0 | N33: =M33+K33+I33+G33+E33 -> 0 | O33: =IF(B33>0,N33/B33,0) -> 0 | P33: =P32 -> 15355.608 | Q33: =(P33-P32)*1000 -> 0 | R33: =N33-Q33 -> 0 | S33: =S32 -> 8384 | T33: =S33-S32 -> 0 | U33: =U32 -> 1024343 | V33: =U33-U32 -> 0 | W33: =W32 -> 31845 | X33: =W33-W32 -> 0 | Y33: =Y32 -> 624440 | Z33: =Y33-Y32 -> 0 | AA33: =AA32 -> 34936 | AB33: =AA33-AA32 -> 0 | AC33: =AC32 -> 751223 | AD33: =AC33-AC32 -> 0 | AE33: =AB33+X33+T33 -> 0 | AF33: =V33+Z33+AD33 -> 0 | AG33: =IF(AE33>0,AF33/AE33,0) -> 0 | AI33: =R33-'EDl log'!B31 -> -49548451

Sheet B5
F1: Boiler A | J1: =J36 -> 76.638542 | K1: Boiler B | P1: Boiler C | V1: Boiler | X1: SteamA | AC1: SteamB | AH1: Steam | AI1: Boiler & steam | AL1: Total Boiler Runing H | AM1: Total Steam Runing H | AN1: GAS1 % | AO1: GAS1/L | AP1: GAS2% | AQ1: Gas2/L | AR1: GAS3% | AS1: GAS3/L | AU1: Gas Cons | AV1: Delivery | AW1: Cost/L
B2: Level Tank Gen | C2: Level tank Boiler | D2: Daily Cons Bo. | E2: Boiler litter | F2: Boiler A | G2: Run Hr a | H2: Boiler A fuel | I2: Daily consumption | J2: AVG | K2: index Run H | L2: Run Hrb | M2: Boiler B Fuel | O2: Daily consumption | P2: Boiler C | S2: Run C | U2: Total RH | V2: Total Fuel | X2: SteamA | Y2: Run SA | Z2: Steam A Conter | AA2: Liters | AC2: SteamB | AD2: Run SteamB | AE2: Steam B Conter | AF2: SB Litters | AG2: Avg | AH2: Total Fuel | AI2: Total Fuel
S3: 0
A4: =ELEC!C2 -> 31-01-2020 | B4: =[1]B5!B35 -> 242.4 | C4: =[1]B5!C35 -> 248 | D4: =[1]B5!D35 -> 5.1 | E4: =[1]B5!E35 -> 42.738 | F4: =[1]B5!F35 -> 1365 | G4: =[1]B5!G35 -> 4 | H4: =[1]B5!H35 -> 335279 | I4: =[1]B5!I35 -> 270 | ... AX4: =[1]B5!AX35 -> 0.7
A5: =ELEC!C3 -> 43862 | B5: 237 | C5: 242 | D5: =C4-C5 -> 6 | E5: =D5*8.38 -> 50.28 | F5: 1368 | G5: =F5-F4 -> 3 | H5: 335533 | I5: =SUM(H5-H4) -> 254 | J5: 1 | K5: 1760 | L5: =K5-K4 -> 4 | M5: 128367 | N5: =M5-M4 -> 276 | O5: =SUM(L5*$J$1) -> 306.55417 | P5: =P4 -> 1590 | Q5: =Q4 -> 136769 | R5: =Q5-Q4 -> 0 | S5: =SUM(P5-P4) -> 0 | T5: =SUM(S5*$T$2) -> 0 | U5: =SUM(G5+L5+S5) -> 7 | V5: =R5+N5+I5:I5 -> 530 | W5: =SUM(V5/U5) -> 75.714286 | X5: =X4 -> 2320 | Y5: =X5-X4 -> 0 | Z5: =Z4 -> 130593 | AA5: =Z5-Z4 -> 0 | AB5: =SUM(Y5*$AB$2) -> 0 | AC5: =AC4 -> 1800 | AD5: =AC5-AC4 -> 0 | AE5: =AE4 -> 357647.9 | AF5: =AE5-AE4 -> 0 | AG5: =IF(AD5>0,AF5/AD5,0) -> 0 | AH5: =AF5+AA5 -> 0 | AI5: =SUM(AH5+V5) -> 530 | AJ5: =-tanks!AW6 -> 530 | AK5: =SUM(AJ5-AI5) -> 0 | AL5: =S5+L5+G5 -> 7 | AM5: =Y5+AD5 -> 0 | AN5: 78 | AO5: =(AN5/100)*3000 -> 2340 | AP5: 78 | AQ5: =(AP5/100)*3000 -> 2340 | AR5: 78 | AS5: =(AR5/100)*3000 -> 2340 | AT5: =SUM(AO5+AQ5+AS5) -> 7020 | AU5: =AT4-AT5+AV5 -> 90 | AX5: =IF(AV5>0,AW5,AX4) -> 0.7
A6: =ELEC!C4 -> 43863 | B6: 232 | C6: 238 | D6: =C5-C6 -> 4 | E6: =D6*8.38 -> 33.52 | F6: 1368 | G6: =F6-F5 -> 0 | H6: 335533 | I6: =SUM(H6-H5) -> 0 | J6: =IF(G6>0,I6/G6,0) -> 0 | K6: 1763 | L6: =K6-K5 -> 3 | M6: 128639 | N6: =M6-M5 -> 272 | O6: =SUM(L6*$J$1) -> 229.91563 | P6: 1595 | Q6: 137103 | R6: =Q6-Q5 -> 334 | S6: =SUM(P6-P5) -> 5 | T6: =SUM(S6*$T$2) -> 0 | U6: =SUM(G6+L6+S6) -> 8 | V6: =R6+N6+I6:I6 -> 606 | W6: =SUM(V6/U6) -> 75.75 | X6: 2320 | Y6: =X6-X5 -> 0 | Z6: 130593 | AA6: =Z6-Z5 -> 0 | AB6: =SUM(Y6*$AB$2) -> 0 | AC6: 1800 | AD6: =AC6-AC5 -> 0 | AE6: 357647.9 | AF6: =AE6-AE5 -> 0 | AG6: =IF(AD6>0,AF6/AD6,0) -> 0 | AH6: =AF6+AA6 -> 0 | AI6: =SUM(AH6+V6) -> 606 | AJ6: =-tanks!AW7 -> 606 | AK6: =SUM(AJ6-AI6) -> 0 | AL6: =S6+L6+G6 -> 8 | AM6: =Y6+AD6 -> 0 | AN6: 77 | AO6: =(AN6/100)*3000 -> 2310 | AP6: 75 | AQ6: =(AP6/100)*3000 -> 2250 | AR6: 75 | AS6: =(AR6/100)*3000 -> 2250 | AT6: =SUM(AO6+AQ6+AS6) -> 6810 | AU6: =AT5-AT6+AV6 -> 210 | AX6: =IF(AV6>0,AW6,AX5) -> 0.7
A7: =ELEC!C5 -> 43864 | B7: 226.4 | C7: 232.2 | D7: =C6-C7 -> 5.8 | E7: =D7*8.38 -> 48.604 | F7: 1373 | G7: =F7-F6 -> 5 | H7: 335970 | I7: =SUM(H7-H6) -> 437 | J7: =IF(G7>0,I7/G7,0) -> 87.4 | K7: 1763 | L7: =K7-K6 -> 0 | M7: 128639 | N7: =M7-M6 -> 0 | O7: 1 | P7: 1597 | Q7: 137321 | R7: =Q7-Q6 -> 218 | S7: =SUM(P7-P6) -> 2 | T7: =SUM(S7*$T$2) -> 0 | U7: =SUM(G7+L7+S7) -> 7 | V7: =R7+N7+I7:I7 -> 655 | W7: =SUM(V7/U7) -> 93.571429 | X7: 2320 | Y7: =X7-X6 -> 0 | Z7: 130593 | AA7: =Z7-Z6 -> 0 | AB7: =SUM(Y7*$AB$2) -> 0 | AC7: 1800 | AD7: =AC7-AC6 -> 0 | AE7: 357647.9 | AF7: =AE7-AE6 -> 0 | AG7: =IF(AD7>0,AF7/AD7,0) -> 0 | AH7: =AF7+AA7 -> 0 | AI7: =SUM(AH7+V7) -> 655 | AJ7: =-tanks!AW8 -> 655 | AK7: =SUM(AJ7-AI7) -> 0 | AL7: =S7+L7+G7 -> 7 | AM7: =Y7+AD7 -> 0 | AN7: 76 | AO7: =(AN7/100)*3000 -> 2280 | AP7: 74 | AQ7: =(AP7/100)*3000 -> 2220 | AR7: 74 | AS7: =(AR7/100)*3000 -> 2220 | AT7: =SUM(AO7+AQ7+AS7) -> 6720 | AU7: =AT6-AT7+AV7 -> 90 | AX7: =IF(AV7>0,AW7,AX6) -> 0.7
A8: =ELEC!C6 -> 43865 | B8: 220 | C8: 226 | D8: =C7-C8 -> 6.2 | E8: =D8*8.38 -> 51.956 | F8: 1377 | G8: =F8-F7 -> 4 | H8: 336311 | I8: =SUM(H8-H7) -> 341 | J8: =IF(G8>0,I8/G8,0) -> 85.25 | K8: 1767 | L8: =K8-K7 -> 4 | M8: 128883 | N8: =M8-M7 -> 244 | O8: 1479 | P8: 1599 | Q8: 137447 | R8: =Q8-Q7 -> 126 | S8: =SUM(P8-P7) -> 2 | T8: =SUM(S8*$T$2) -> 0 | U8: =SUM(G8+L8+S8) -> 10 | V8: =R8+N8+I8:I8 -> 711 | W8: =SUM(V8/U8) -> 71.1 | X8: 2328 | Y8: =X8-X7 -> 8 | Z8: 131019.7 | AA8: =Z8-Z7 -> 426.7 | AB8: =SUM(Y8*$AB$2) -> 0 | AC8: =AC7 -> 1800 | AD8: =AC8-AC7 -> 0 | AE8: =AE7 -> 357647.9 | AF8: =AE8-AE7 -> 0 | AG8: =IF(AD8>0,AF8/AD8,0) -> 0 | AH8: =AF8+AA8 -> 426.7 | AI8: =SUM(AH8+V8) -> 1137.7 | AJ8: =-tanks!AW9 -> 1137.7 | AK8: =SUM(AJ8-AI8) -> 0 | AL8: =S8+L8+G8 -> 10 | AM8: =Y8+AD8 -> 8 | AN8: 74 | AO8: =(AN8/100)*3000 -> 2220 | AP8: 72 | AQ8: =(AP8/100)*3000 -> 2160 | AR8: 72 | AS8: =(AR8/100)*3000 -> 2160 | AT8: =SUM(AO8+AQ8+AS8) -> 6540 | AU8: =AT7-AT8+AV8 -> 180 | AX8: =IF(AV8>0,AW8,AX7) -> 0.7
A9: =ELEC!C7 -> 43866 | B9: 214.2 | C9: 220 | D9: =C8-C9 -> 6 | E9: =D9*8.38 -> 50.28 | F9: 1377 | G9: =F9-F8 -> 0 | H9: 336311 | I9: =SUM(H9-H8) -> 0 | J9: =IF(G9>0,I9/G9,0) -> 0 | K9: 1771 | L9: =K9-K8 -> 4 | M9: 129199 | N9: =M9-M8 -> 316 | O9: =SUM(L9*$J$1) -> 306.55417 | P9: 1603 | Q9: 137748 | R9: =Q9-Q8 -> 301 | S9: =SUM(P9-P8) -> 4 | T9: =SUM(S9*$T$2) -> 0 | U9: =SUM(G9+L9+S9) -> 8 | V9: =R9+N9+I9:I9 -> 617 | W9: =SUM(V9/U9) -> 77.125 | X9: 2328 | Y9: =X9-X8 -> 0 | Z9: 131019.7 | AA9: =Z9-Z8 -> 0 | AB9: =SUM(Y9*$AB$2) -> 0 | AC9: 1800 | AD9: =AC9-AC8 -> 0 | AE9: 357647.9 | AF9: =AE9-AE8 -> 0 | AG9: =IF(AD9>0,AF9/AD9,0) -> 0 | AH9: =AF9+AA9 -> 0 | AI9: =SUM(AH9+V9) -> 617 | AJ9: =-tanks!AW10 -> 617 | AK9: =SUM(AJ9-AI9) -> 0 | AL9: =S9+L9+G9 -> 8 | AM9: =Y9+AD9 -> 0 | AN9: 72 | AO9: =(AN9/100)*3000 -> 2160 | AP9: 70 | AQ9: =(AP9/100)*3000 -> 2100 | AR9: 70 | AS9: =(AR9/100)*3000 -> 2100 | AT9: =SUM(AO9+AQ9+AS9) -> 6360 | AU9: =AT8-AT9+AV9 -> 180 | AX9: =IF(AV9>0,AW9,AX8) -> 0.7
A10: =ELEC!C8 -> 43867 | B10: 210.3 | C10: 216.4 | D10: =C9-C10 -> 3.6 | E10: =D10*8.38 -> 30.168 | F10: 1380 | G10: =F10-F9 -> 3 | H10: 336523 | I10: =SUM(H10-H9) -> 212 | J10: =IF(G10>0,I10/G10,0) -> 70.666667 | K10: =K9 -> 1771 | L10: =K10-K9 -> 0 | M10: =M9 -> 129199 | N10: =M10-M9 -> 0 | O10: =SUM(L10*$J$1) -> 0 | P10: 1606 | Q10: 137989 | R10: =Q10-Q9 -> 241 | S10: =SUM(P10-P9) -> 3 | T10: =SUM(S10*$T$2) -> 0 | U10: =SUM(G10+L10+S10) -> 6 | V10: =R10+N10+I10:I10 -> 453 | W10: =SUM(V10/U10) -> 75.5 | X10: =X9 -> 2328 | Y10: =X10-X9 -> 0 | Z10: =Z9 -> 131019.7 | AA10: =Z10-Z9 -> 0 | AB10: =SUM(Y10*$AB$2) -> 0 | AC10: =AC9 -> 1800 | AD10: =AC10-AC9 -> 0 | AE10: =AE9 -> 357647.9 | AF10: =AE10-AE9 -> 0 | AG10: =IF(AD10>0,AF10/AD10,0) -> 0 | AH10: =AF10+AA10 -> 0 | AI10: =SUM(AH10+V10) -> 453 | AJ10: =-tanks!AW11 -> 453 | AK10: =SUM(AJ10-AI10) -> 0 | AL10: =S10+L10+G10 -> 6 | AM10: =Y10+AD10 -> 0 | AN10: 80 | AO10: =(AN10/100)*3000 -> 2400 | AP10: 79 | AQ10: =(AP10/100)*3000 -> 2370 | AR10: 79 | AS10: =(AR10/100)*3000 -> 2370 | AT10: =SUM(AO10+AQ10+AS10) -> 7140 | AU10: =AT9-AT10+AV10 -> 320 | AV10: 1100 | AW10: 0.7 | AX10: =IF(AV10>0,AW10,AX9) -> 0.7
A11: =ELEC!C9 -> 43868 | B11: 252 | C11: 259 | D11: =C10-C11 -> -42.6 | E11: =D11*8.38 -> -356.988 | F11: 1383 | G11: =F11-F10 -> 3 | H11: 336745 | I11: =SUM(H11-H10) -> 222 | J11: =IF(G11>0,I11/G11,0) -> 74 | K11: 1775 | L11: =K11-K10 -> 4 | M11: 129531 | N11: =M11-M10 -> 332 | O11: =SUM(L11*$J$1) -> 306.55417 | P11: =P10 -> 1606 | Q11: =Q10 -> 137989 | R11: =Q11-Q10 -> 0 | S11: =SUM(P11-P10) -> 0 | T11: =SUM(S11*$T$2) -> 0 | U11: =SUM(G11+L11+S11) -> 7 | V11: =R11+N11+I11:I11 -> 554 | W11: =SUM(V11/U11) -> 79.142857 | X11: 2335 | Y11: =X11-X10 -> 7 | Z11: 131372.6 | AA11: =Z11-Z10 -> 352.9 | AB11: =SUM(Y11*$AB$2) -> 0 | AC11: =AC10 -> 1800 | AD11: =AC11-AC10 -> 0 | AE11: =AE10 -> 357647.9 | AF11: =AE11-AE10 -> 0 | AG11: =IF(AD11>0,AF11/AD11,0) -> 0 | AH11: =AF11+AA11 -> 352.9 | AI11: =SUM(AH11+V11) -> 906.9 | AJ11: =-tanks!AW12 -> 906.9 | AK11: =SUM(AJ11-AI11) -> 0 | AL11: =S11+L11+G11 -> 7 | AM11: =Y11+AD11 -> 7 | AN11: 78 | AO11: =(AN11/100)*3000 -> 2340 | AP11: 78 | AQ11: =(AP11/100)*3000 -> 2340 | AR11: 78 | AS11: =(AR11/100)*3000 -> 2340 | AT11: =SUM(AO11+AQ11+AS11) -> 7020 | AU11: =AT10-AT11+AV11 -> 120 | AX11: =IF(AV11>0,AW11,AX10) -> 0.7
A12: =ELEC!C10 -> 43869 | B12: 248 | C12: 253.4 | D12: =C11-C12 -> 5.6 | E12: =D12*8.38 -> 46.928 | F12: =F11 -> 1383 | G12: =F12-F11 -> 0 | H12: =H11 -> 336745 | I12: =SUM(H12-H11) -> 0 | J12: =IF(G12>0,I12/G12,0) -> 0 | K12: 1779 | L12: =K12-K11 -> 4 | M12: 129837 | N12: =M12-M11 -> 306 | O12: =SUM(L12*$J$1) -> 306.55417 | P12: 1610 | Q12: 138263 | R12: =Q12-Q11 -> 274 | S12: =SUM(P12-P11) -> 4 | T12: =SUM(S12*$T$2) -> 0 | U12: =SUM(G12+L12+S12) -> 8 | V12: =R12+N12+I12:I12 -> 580 | W12: =SUM(V12/U12) -> 72.5 | X12: =X11 -> 2335 | Y12: =X12-X11 -> 0 | Z12: 131398.9 | AA12: =Z12-Z11 -> 26.3 | AB12: =SUM(Y12*$AB$2) -> 0 | AC12: 1801 | AD12: =AC12-AC11 -> 1 | AE12: 357711.4 | AF12: =AE12-AE11 -> 63.5 | AG12: =IF(AD12>0,AF12/AD12,0) -> 63.5 | AH12: =AF12+AA12 -> 89.8 | AI12: =SUM(AH12+V12) -> 669.8 | AJ12: =-tanks!AW13 -> 669.8 | AK12: =SUM(AJ12-AI12) -> 0 | AL12: =S12+L12+G12 -> 8 | AM12: =Y12+AD12 -> 1 | AN12: 77 | AO12: =(AN12/100)*3000 -> 2310 | AP12: 77 | AQ12: =(AP12/100)*3000 -> 2310 | AR12: 77 | AS12: =(AR12/100)*3000 -> 2310 | AT12: =SUM(AO12+AQ12+AS12) -> 6930 | AU12: =AT11-AT12+AV12 -> 90 | AX12: =IF(AV12>0,AW12,AX11) -> 0.7
A13: =ELEC!C11 -> 43870 | B13: 242 | C13: 248 | D13: =C12-C13 -> 5.4 | E13: =D13*8.38 -> 45.252 | F13: 1387 | G13: =F13-F12 -> 4 | H13: 337106 | I13: =SUM(H13-H12) -> 361 | J13: =IF(G13>0,I13/G13,0) -> 90.25 | K13: =K12 -> 1779 | L13: =K13-K12 -> 0 | M13: =M12 -> 129837 | N13: =M13-M12 -> 0 | O13: =SUM(L13*$J$1) -> 0 | P13: 1616 | Q13: 138730 | R13: =Q13-Q12 -> 467 | S13: =SUM(P13-P12) -> 6 | T13: =SUM(S13*$T$2) -> 0 | U13: =SUM(G13+L13+S13) -> 10 | V13: =R13+N13+I13:I13 -> 828 | W13: =SUM(V13/U13) -> 82.8 | X13: =X12 -> 2335 | Y13: =X13-X12 -> 0 | Z13: =Z12 -> 131398.9 | AA13: =Z13-Z12 -> 0 | AB13: =SUM(Y13*$AB$2) -> 0 | AC13: =AC12 -> 1801 | AD13: =AC13-AC12 -> 0 | AE13: =AE12 -> 357711.4 | AF13: =AE13-AE12 -> 0 | AG13: =IF(AD13>0,AF13/AD13,0) -> 0 | AH13: =AF13+AA13 -> 0 | AI13: =SUM(AH13+V13) -> 828 | AJ13: =-tanks!AW14 -> 828 | AK13: =SUM(AJ13-AI13) -> 0 | AL13: =S13+L13+G13 -> 10 | AM13: =Y13+AD13 -> 0 | AN13: 74 | AO13: =(AN13/100)*3000 -> 2220 | AP13: 74 | AQ13: =(AP13/100)*3000 -> 2220 | AR13: 74 | AS13: =(AR13/100)*3000 -> 2220 | AT13: =SUM(AO13+AQ13+AS13) -> 6660 | AU13: =AT12-AT13+AV13 -> 270 | AX13: =IF(AV13>0,AW13,AX12) -> 0.7
A14: =ELEC!C12 -> 43871 | B14: 236.1 | C14: 241.4 | D14: =C13-C14 -> 6.6 | E14: =D14*8.38 -> 55.308 | F14: 1394 | G14: =F14-F13 -> 7 | H14: 337680 | I14: =SUM(H14-H13) -> 574 | J14: =IF(G14>0,I14/G14,0) -> 82 | K14: 1784 | L14: =K14-K13 -> 5 | M14: 130244 | N14: =M14-M13 -> 407 | O14: =SUM(L14*$J$1) -> 383.19271 | P14: 1617 | Q14: 138848 | R14: =Q14-Q13 -> 118 | S14: =SUM(P14-P13) -> 1 | T14: =SUM(S14*$T$2) -> 0 | U14: =SUM(G14+L14+S14) -> 13 | V14: =R14+N14+I14:I14 -> 1099 | W14: =SUM(V14/U14) -> 84.538462 | X14: 2335 | Y14: =X14-X13 -> 0 | Z14: 131398.9 | AA14: =Z14-Z13 -> 0 | AB14: =SUM(Y14*$AB$2) -> 0 | AC14: 1801 | AD14: =AC14-AC13 -> 0 | AE14: 357711 | AF14: =AE14-AE13 -> -0.4 | AG14: =IF(AD14>0,AF14/AD14,0) -> 0 | AH14: =AF14+AA14 -> -0.4 | AI14: =SUM(AH14+V14) -> 1098.6 | AJ14: =-tanks!AW15 -> 1098.6 | AK14: =SUM(AJ14-AI14) -> 0 | AL14: =S14+L14+G14 -> 13 | AM14: =Y14+AD14 -> 0 | AN14: 71 | AO14: =(AN14/100)*3000 -> 2130 | AP14: 71 | AQ14: =(AP14/100)*3000 -> 2130 | AR14: 71 | AS14: =(AR14/100)*3000 -> 2130 | AT14: =SUM(AO14+AQ14+AS14) -> 6390 | AU14: =AT13-AT14+AV14 -> 270 | AX14: =IF(AV14>0,AW14,AX13) -> 0.7
A15: =ELEC!C13 -> 43872 | B15: 230 | C15: 235.4 | D15: =C14-C15 -> 6 | E15: =D15*8.38 -> 50.28 | F15: 1394 | G15: =F15-F14 -> 0 | H15: 337680 | I15: =SUM(H15-H14) -> 0 | J15: =IF(G15>0,I15/G15,0) -> 0 | K15: 1792 | L15: =K15-K14 -> 8 | M15: 130802 | N15: =M15-M14 -> 558 | O15: =SUM(L15*$J$1) -> 613.10833 | P15: 1623 | Q15: 139294 | R15: =Q15-Q14 -> 446 | S15: =SUM(P15-P14) -> 6 | T15: =SUM(S15*$T$2) -> 0 | U15: =SUM(G15+L15+S15) -> 14 | V15: =R15+N15+I15:I15 -> 1004 | W15: =SUM(V15/U15) -> 71.714286 | X15: 2344 | Y15: =X15-X14 -> 9 | Z15: 131862.6 | AA15: =Z15-Z14 -> 463.7 | AB15: =SUM(Y15*$AB$2) -> 0 | AC15: 1801 | AD15: =AC15-AC14 -> 0 | AE15: 357711.4 | AF15: =AE15-AE14 -> 0.4 | AG15: =IF(AD15>0,AF15/AD15,0) -> 0 | AH15: =AF15+AA15 -> 464.1 | AI15: =SUM(AH15+V15) -> 1468.1 | AJ15: =-tanks!AW16 -> 1468.1 | AK15: =SUM(AJ15-AI15) -> 0 | AL15: =S15+L15+G15 -> 14 | AM15: =Y15+AD15 -> 9 | AN15: 70 | AO15: =(AN15/100)*3000 -> 2100 | AP15: 70 | AQ15: =(AP15/100)*3000 -> 2100 | AR15: 70 | AS15: =(AR15/100)*3000 -> 2100 | AT15: =SUM(AO15+AQ15+AS15) -> 6300 | AU15: =AT14-AT15+AV15 -> 90 | AX15: =IF(AV15>0,AW15,AX14) -> 0.7
A16: =ELEC!C14 -> 43873 | B16: 223 | C16: 229.5 | D16: =C15-C16 -> 5.9 | E16: =D16*8.38 -> 49.442 | F16: 1399 | G16: =F16-F15 -> 5 | H16: 338058 | I16: =SUM(H16-H15) -> 378 | J16: =IF(G16>0,I16/G16,0) -> 75.6 | K16: =K15 -> 1792 | L16: =K16-K15 -> 0 | M16: =M15 -> 130802 | N16: =M16-M15 -> 0 | O16: =SUM(L16*$J$1) -> 0 | P16: 1630 | Q16: 139796 | R16: =Q16-Q15 -> 502 | S16: =SUM(P16-P15) -> 7 | T16: =SUM(S16*$T$2) -> 0 | U16: =SUM(G16+L16+S16) -> 12 | V16: =R16+N16+I16:I16 -> 880 | W16: =SUM(V16/U16) -> 73.333333 | X16: =X15 -> 2344 | Y16: =X16-X15 -> 0 | Z16: =Z15 -> 131862.6 | AA16: =Z16-Z15 -> 0 | AB16: =SUM(Y16*$AB$2) -> 0 | AC16: =AC15 -> 1801 | AD16: =AC16-AC15 -> 0 | AE16: =AE15 -> 357711.4 | AF16: =AE16-AE15 -> 0 | AG16: =IF(AD16>0,AF16/AD16,0) -> 0 | AH16: =AF16+AA16 -> 0 | AI16: =SUM(AH16+V16) -> 880 | AJ16: =-tanks!AW17 -> 880 | AK16: =SUM(AJ16-AI16) -> 0 | AL16: =S16+L16+G16 -> 12 | AM16: =Y16+AD16 -> 0 | AN16: 69 | AO16: =(AN16/100)*3000 -> 2070 | AP16: 69 | AQ16: =(AP16/100)*3000 -> 2070 | AR16: 68 | AS16: =(AR16/100)*3000 -> 2040 | AT16: =SUM(AO16+AQ16+AS16) -> 6180 | AU16: =AT15-AT16+AV16 -> 120 | AX16: =IF(AV16>0,AW16,AX15) -> 0.7
A17: =ELEC!C15 -> 43874 | B17: 219 | C17: 225 | D17: =C16-C17 -> 4.5 | E17: =D17*8.38 -> 37.71 | F17: 1403 | G17: =F17-F16 -> 4 | H17: 338387 | I17: =SUM(H17-H16) -> 329 | J17: =IF(G17>0,I17/G17,0) -> 82.25 | K17: 1793 | L17: =K17-K16 -> 1 | M17: 130929 | N17: =M17-M16 -> 127 | O17: =SUM(L17*$J$1) -> 76.638542 | P17: 1634 | Q17: 140075 | R17: =Q17-Q16 -> 279 | S17: =SUM(P17-P16) -> 4 | T17: =SUM(S17*$T$2) -> 0 | U17: =SUM(G17+L17+S17) -> 9 | V17: =R17+N17+I17:I17 -> 735 | X17: 2344 | Y17: =X17-X16 -> 0 | Z17: 131862.6 | AA17: =Z17-Z16 -> 0 | AB17: =SUM(Y17*$AB$2) -> 0 | AC17: 1801 | AD17: =AC17-AC16 -> 0 | AE17: 357711.4 | AF17: =AE17-AE16 -> 0 | AG17: =IF(AD17>0,AF17/AD17,0) -> 0 | AH17: =AF17+AA17 -> 0 | AI17: =SUM(AH17+V17) -> 735 | AJ17: =-tanks!AW18 -> 735 | AK17: =SUM(AJ17-AI17) -> 0 | AL17: =S17+L17+G17 -> 9 | AM17: =Y17+AD17 -> 0 | AN17: 80 | AO17: =(AN17/100)*3000 -> 2400 | AP17: 80 | AQ17: =(AP17/100)*3000 -> 2400 | AR17: 80 | AS17: =(AR17/100)*3000 -> 2400 | AT17: =SUM(AO17+AQ17+AS17) -> 7200 | AU17: =AT16-AT17+AV17 -> 380 | AV17: 1400 | AW17: 0.7 | AX17: =IF(AV17>0,AW17,AX16) -> 0.7
A18: =ELEC!C16 -> 43875 | B18: 213.2 | C18: 219 | D18: =C17-C18 -> 6 | E18: =D18*8.38 -> 50.28 | F18: =F17 -> 1403 | G18: =F18-F17 -> 0 | H18: =H17 -> 338387 | I18: =SUM(H18-H17) -> 0 | J18: =IF(G18>0,I18/G18,0) -> 0 | K18: =K17 -> 1793 | L18: =K18-K17 -> 0 | M18: =M17 -> 130929 | N18: =M18-M17 -> 0 | O18: =SUM(L18*$J$1) -> 0 | P18: 1643 | Q18: 140820 | R18: =Q18-Q17 -> 745 | S18: =SUM(P18-P17) -> 9 | T18: =SUM(S18*$T$2) -> 0 | U18: =SUM(G18+L18+S18) -> 9 | V18: =R18+N18+I18:I18 -> 745 | X18: 2353 | Y18: =X18-X17 -> 9 | Z18: 132298.7 | AA18: =Z18-Z17 -> 436.1 | AB18: =SUM(Y18*$AB$2) -> 0 | AC18: =AC17 -> 1801 | AD18: =AC18-AC17 -> 0 | AE18: 357717.4 | AF18: =AE18-AE17 -> 6 | AG18: =IF(AD18>0,AF18/AD18,0) -> 0 | AH18: =AF18+AA18 -> 442.1 | AI18: =SUM(AH18+V18) -> 1187.1 | AJ18: =-tanks!AW19 -> 1187.1 | AK18: =SUM(AJ18-AI18) -> 0 | AL18: =S18+L18+G18 -> 9 | AM18: =Y18+AD18 -> 9 | AN18: 78 | AO18: =(AN18/100)*3000 -> 2340 | AP18: 79 | AQ18: =(AP18/100)*3000 -> 2370 | AR18: 79 | AS18: =(AR18/100)*3000 -> 2370 | AT18: =SUM(AO18+AQ18+AS18) -> 7080 | AU18: =AT17-AT18+AV18 -> 120 | AX18: =IF(AV18>0,AW18,AX17) -> 0.7
A19: =ELEC!C17 -> 43876 | B19: 206.1 | C19: 212 | D19: =C18-C19 -> 7 | E19: =D19*8.38 -> 58.66 | F19: 1408 | G19: =F19-F18 -> 5 | H19: 338776 | I19: =SUM(H19-H18) -> 389 | J19: =IF(G19>0,I19/G19,0) -> 77.8 | K19: =K18 -> 1793 | L19: =K19-K18 -> 0 | M19: =M18 -> 130929 | N19: =M19-M18 -> 0 | O19: =SUM(L19*$J$1) -> 0 | P19: 1648 | Q19: 141150 | R19: =Q19-Q18 -> 330 | S19: =SUM(P19-P18) -> 5 | T19: =SUM(S19*$T$2) -> 0 | U19: =SUM(G19+L19+S19) -> 10 | V19: =R19+N19+I19:I19 -> 719 | X19: =X18 -> 2353 | Y19: =X19-X18 -> 0 | Z19: 132325.7 | AA19: =Z19-Z18 -> 27 | AB19: =SUM(Y19*$AB$2) -> 0 | AC19: =AC18 -> 1801 | AD19: =AC19-AC18 -> 0 | AE19: 357717.4 | AF19: =AE19-AE18 -> 0 | AG19: =IF(AD19>0,AF19/AD19,0) -> 0 | AH19: =AF19+AA19 -> 27 | AI19: =SUM(AH19+V19) -> 746 | AJ19: =-tanks!AW20 -> 746 | AK19: =SUM(AJ19-AI19) -> 0 | AL19: =S19+L20+G19 -> 15 | AM19: =Y19+AD19 -> 0 | AN19: 76 | AO19: =(AN19/100)*3000 -> 2280 | AP19: 78 | AQ19: =(AP19/100)*3000 -> 2340 | AR19: 78 | AS19: =(AR19/100)*3000 -> 2340 | AT19: =SUM(AO19+AQ19+AS19) -> 6960 | AU19: =AT18-AT19+AV19 -> 120 | AX19: =IF(AV19>0,AW19,AX18) -> 0.7
A20: =ELEC!C18 -> 43877 | B20: 202.3 | C20: 208.1 | D20: =C19-C20 -> 3.9 | E20: =D20*8.38 -> 32.682 | F20: 1411 | G20: =F20-F19 -> 3 | H20: 339042 | I20: =SUM(H20-H19) -> 266 | J20: =IF(G20>0,I20/G20,0) -> 88.666667 | K20: 1798 | L20: =K20-K19 -> 5 | M20: 131307 | N20: =M20-M19 -> 378 | O20: =SUM(L20*$J$1) -> 383.19271 | P20: =P19 -> 1648 | Q20: =Q19 -> 141150 | R20: =Q20-Q19 -> 0 | S20: =SUM(P20-P19) -> 0 | T20: =SUM(S20*$T$2) -> 0 | U20: =SUM(G20+L20+S20) -> 8 | V20: =R20+N20+I20:I20 -> 644 | X20: =X19 -> 2353 | Y20: =X20-X19 -> 0 | Z20: 132325.7 | AA20: =Z20-Z19 -> 0 | AB20: =SUM(Y20*$AB$2) -> 0 | AC20: =AC19 -> 1801 | AD20: =AC20-AC19 -> 0 | AE20: =AE19 -> 357717.4 | AF20: =AE20-AE19 -> 0 | AG20: =IF(AD20>0,AF20/AD20,0) -> 0 | AH20: =AF20+AA20 -> 0 | AI20: =SUM(AH20+V20) -> 644 | AJ20: =-tanks!AW21 -> 644 | AK20: =SUM(AJ20-AI20) -> 0 | AL20: =S20+L21+G20 -> 7 | AM20: =Y20+AD20 -> 0 | AN20: 74 | AO20: =(AN20/100)*3000 -> 2220 | AP20: 76 | AQ20: =(AP20/100)*3000 -> 2280 | AR20: 76 | AS20: =(AR20/100)*3000 -> 2280 | AT20: =SUM(AO20+AQ20+AS20) -> 6780 | AU20: =AT19-AT20+AV20 -> 180 | AX20: =IF(AV20>0,AW20,AX19) -> 0.7
A21: =ELEC!C19 -> 43878 | B21: 198 | C21: 203.3 | D21: =C20-C21 -> 4.8 | E21: =D21*8.38 -> 40.224 | F21: 1411 | G21: =F21-F20 -> 0 | H21: 339042 | I21: =SUM(H21-H20) -> 0 | J21: =IF(G21>0,I21/G21,0) -> 0 | K21: 1802 | L21: =K21-K20 -> 4 | M21: 131602 | N21: =M21-M20 -> 295 | O21: =SUM(L21*$J$1) -> 306.55417 | P21: 1652 | Q21: 141485 | R21: =Q21-Q20 -> 335 | S21: =SUM(P21-P20) -> 4 | T21: =SUM(S21*$T$2) -> 0 | U21: =SUM(G21+L21+S21) -> 8 | V21: =R21+N21+I21:I21 -> 630 | X21: 2353 | Y21: =X21-X20 -> 0 | Z21: 132325.7 | AA21: =Z21-Z20 -> 0 | AB21: =SUM(Y21*$AB$2) -> 0 | AC21: 1801 | AD21: =AC21-AC20 -> 0 | AE21: 357717.4 | AF21: =AE21-AE20 -> 0 | AG21: =IF(AD21>0,AF21/AD21,0) -> 0 | AH21: =AF21+AA21 -> 0 | AI21: =SUM(AH21+V21) -> 630 | AJ21: =-tanks!AW22 -> 630 | AK21: =SUM(AJ21-AI21) -> 0 | AL21: =S21+L21+G21 -> 8 | AM21: =Y21+AD21 -> 0 | AN21: 71 | AO21: =(AN21/100)*3000 -> 2130 | AP21: 73 | AQ21: =(AP21/100)*3000 -> 2190 | AR21: 73 | AS21: =(AR21/100)*3000 -> 2190 | AT21: =SUM(AO21+AQ21+AS21) -> 6510 | AU21: =AT20-AT21+AV21 -> 270 | AX21: =IF(AV21>0,AW21,AX20) -> 0.7
A22: =ELEC!C20 -> 43879 | B22: 251.2 | C22: 256.4 | D22: =C21-C22 -> -53.1 | E22: =D22*8.38 -> -444.978 | F22: 1415 | G22: =F22-F21 -> 4 | H22: 339352 | I22: =SUM(H22-H21) -> 310 | J22: =IF(G22>0,I22/G22,0) -> 77.5 | K22: 1802 | L22: =K22-K21 -> 0 | M22: 131602 | N22: =M22-M21 -> 0 | O22: =SUM(L22*$J$1) -> 0 | P22: 1656 | Q22: 141745 | R22: =Q22-Q21 -> 260 | S22: =SUM(P22-P21) -> 4 | T22: =SUM(S22*$T$2) -> 0 | U22: =SUM(G22+L22+S22) -> 8 | V22: =R22+N22+I22:I22 -> 570 | X22: 2363 | Y22: =X22-X21 -> 10 | Z22: 132877.7 | AA22: =Z22-Z21 -> 552 | AB22: =SUM(Y22*$AB$2) -> 0 | AC22: =AC21 -> 1801 | AD22: =AC22-AC21 -> 0 | AE22: =AE21 -> 357717.4 | AF22: =AE22-AE21 -> 0 | AG22: =IF(AD22>0,AF22/AD22,0) -> 0 | AH22: =AF22+AA22 -> 552 | AI22: =SUM(AH22+V22) -> 1122 | AJ22: =-tanks!AW23 -> 1122 | AK22: =SUM(AJ22-AI22) -> 0 | AL22: =S22+L22+G22 -> 8 | AM22: =Y22+AD22 -> 10 | AN22: 69 | AO22: =(AN22/100)*3000 -> 2070 | AP22: 71 | AQ22: =(AP22/100)*3000 -> 2130 | AR22: 72 | AS22: =(AR22/100)*3000 -> 2160 | AT22: =SUM(AO22+AQ22+AS22) -> 6360 | AU22: =AT21-AT22+AV22 -> 150 | AX22: =IF(AV22>0,AW22,AX21) -> 0.7
A23: =ELEC!C21 -> 43880 | B23: 245 | C23: 249.4 | D23: =C22-C23 -> 7 | E23: =D23*8.38 -> 58.66 | F23: 1418 | G23: =F23-F22 -> 3 | H23: 339608 | I23: =SUM(H23-H22) -> 256 | J23: =IF(G23>0,I23/G23,0) -> 85.333333 | K23: 1805 | L23: =K23-K22 -> 3 | M23: 131845 | N23: =M23-M22 -> 243 | O23: =SUM(L23*$J$1) -> 229.91563 | P23: 1656 | Q23: 141745 | R23: =Q23-Q22 -> 0 | S23: =SUM(P23-P22) -> 0 | T23: =SUM(S23*$T$2) -> 0 | U23: =SUM(G23+L23+S23) -> 6 | V23: =R23+N23+I23:I23 -> 499 | X23: 2363 | Y23: =X23-X22 -> 0 | Z23: 132877.7 | AA23: =Z23-Z22 -> 0 | AB23: =SUM(Y23*$AB$2) -> 0 | AC23: 1801 | AD23: =AC23-AC22 -> 0 | AE23: 357717.4 | AF23: =AE23-AE22 -> 0 | AG23: =IF(AD23>0,AF23/AD23,0) -> 0 | AH23: =AF23+AA23 -> 0 | AI23: =SUM(AH23+V23) -> 499 | AJ23: =-tanks!AW24 -> 499 | AK23: =SUM(AJ23-AI23) -> 0 | AL23: =S23+L23+G23 -> 6 | AM23: =Y23+AD23 -> 0 | AN23: 67 | AO23: =(AN23/100)*3000 -> 2010 | AP23: 69 | AQ23: =(AP23/100)*3000 -> 2070 | AR23: 70 | AS23: =(AR23/100)*3000 -> 2100 | AT23: =SUM(AO23+AQ23+AS23) -> 6180 | AU23: =AT22-AT23+AV23 -> 180 | AX23: =IF(AV23>0,AW23,AX22) -> 0.7
A24: =ELEC!C22 -> 43881 | B24: 241 | C24: 246.5 | D24: =C23-C24 -> 2.9 | E24: =D24*8.38 -> 24.302 | F24: 1418 | G24: =F24-F23 -> 0 | H24: 339608 | I24: =SUM(H24-H23) -> 0 | J24: =IF(G24>0,I24/G24,0) -> 0 | K24: 1809 | L24: =K24-K23 -> 4 | M24: 132120 | N24: =M24-M23 -> 275 | O24: =SUM(L24*$J$1) -> 306.55417 | P24: 1659 | Q24: 142011 | R24: =Q24-Q23 -> 266 | S24: =SUM(P24-P23) -> 3 | T24: =SUM(S24*$T$2) -> 0 | U24: =SUM(G24+L24+S24) -> 7 | V24: =R24+N24+I24:I24 -> 541 | X24: 2363 | Y24: =X24-X23 -> 0 | Z24: 132877.7 | AA24: =Z24-Z23 -> 0 | AB24: =SUM(Y24*$AB$2) -> 0 | AC24: 1801 | AD24: =AC24-AC23 -> 0 | AE24: 357717.4 | AF24: =AE24-AE23 -> 0 | AG24: =IF(AD24>0,AF24/AD24,0) -> 0 | AH24: =AF24+AA24 -> 0 | AI24: =SUM(AH24+V24) -> 541 | AJ24: =-tanks!AW25 -> 541 | AK24: =SUM(AJ24-AI24) -> 0 | AL24: =S24+L24+G24 -> 7 | AM24: =Y24+AD24 -> 0 | AN24: 79 | AO24: =(AN24/100)*3000 -> 2370 | AP24: 79 | AQ24: =(AP24/100)*3000 -> 2370 | AR24: 81 | AS24: =(AR24/100)*3000 -> 2430 | AT24: =SUM(AO24+AQ24+AS24) -> 7170 | AU24: =AT23-AT24+AV24 -> 410 | AV24: 1400 | AW24: 0.7 | AX24: =IF(AV24>0,AW24,AX23) -> 0.7
A25: =ELEC!C23 -> 43882 | B25: 237 | C25: 241 | D25: =C24-C25 -> 5.5 | E25: =D25*8.38 -> 46.09 | F25: 1422 | G25: =F25-F24 -> 4 | H25: 339923 | I25: =SUM(H25-H24) -> 315 | J25: =IF(G25>0,I25/G25,0) -> 78.75 | K25: =K24 -> 1809 | L25: =K25-K24 -> 0 | M25: =M24 -> 132120 | N25: =M25-M24 -> 0 | O25: =SUM(L25*$J$1) -> 0 | P25: 1662 | Q25: 142265 | R25: =Q25-Q24 -> 254 | S25: =SUM(P25-P24) -> 3 | T25: =SUM(S25*$T$2) -> 0 | U25: =SUM(G25+L25+S25) -> 7 | V25: =R25+N25+I25:I25 -> 569 | X25: 2372 | Y25: =X25-X24 -> 9 | Z25: 133353 | AA25: =Z25-Z24 -> 475.3 | AB25: =SUM(Y25*$AB$2) -> 0 | AC25: =AC24 -> 1801 | AD25: =AC25-AC24 -> 0 | AE25: =AE24 -> 357717.4 | AF25: =AE25-AE24 -> 0 | AG25: =IF(AD25>0,AF25/AD25,0) -> 0 | AH25: =AF25+AA25 -> 475.3 | AI25: =SUM(AH25+V25) -> 1044.3 | AJ25: =-tanks!AW26 -> 1044.3 | AK25: =SUM(AJ25-AI25) -> 0 | AL25: =S25+L25+G25 -> 7 | AM25: =Y25+AD25 -> 9 | AN25: =AN24 -> 79 | AO25: =(AN25/100)*3000 -> 2370 | AP25: =AP24 -> 79 | AQ25: =(AP25/100)*3000 -> 2370 | AR25: 80 | AS25: =(AR25/100)*3000 -> 2400 | AT25: =SUM(AO25+AQ25+AS25) -> 7140 | AU25: =AT24-AT25+AV25 -> 30 | AX25: =IF(AV25>0,AW25,AX24) -> 0.7
A26: =ELEC!C24 -> 43883 | B26: 229 | C26: 234.3 | D26: =C25-C26 -> 6.7 | E26: =D26*8.38 -> 56.146 | F26: 1426 | G26: =F26-F25 -> 4 | H26: 340262 | I26: =SUM(H26-H25) -> 339 | J26: =IF(G26>0,I26/G26,0) -> 84.75 | K26: 1814 | L26: =K26-K25 -> 5 | M26: 132475 | N26: =M26-M25 -> 355 | O26: =SUM(L26*$J$1) -> 383.19271 | P26: 1662 | Q26: 142270 | R26: =Q26-Q25 -> 5 | S26: =SUM(P26-P25) -> 0 | T26: =SUM(S26*$T$2) -> 0 | U26: =SUM(G26+L26+S26) -> 9 | V26: =R26+N26+I26:I26 -> 699 | X26: 2374 | Y26: =X26-X25 -> 2 | Z26: 133402 | AA26: =Z26-Z25 -> 49 | AB26: =SUM(Y26*$AB$2) -> 0 | AC26: =AC25 -> 1801 | AD26: =AC26-AC25 -> 0 | AE26: =AE25 -> 357717.4 | AF26: =AE26-AE25 -> 0 | AG26: =IF(AD26>0,AF26/AD26,0) -> 0 | AH26: =AF26+AA26 -> 49 | AI26: =SUM(AH26+V26) -> 748 | AJ26: =-tanks!AW27 -> 748 | AK26: =SUM(AJ26-AI26) -> 0 | AL26: =S26+L26+G26 -> 9 | AM26: =Y26+AD26 -> 2 | AN26: 77 | AO26: =(AN26/100)*3000 -> 2310 | AP26: 78 | AQ26: =(AP26/100)*3000 -> 2340 | AR26: 79 | AS26: =(AR26/100)*3000 -> 2370 | AT26: =SUM(AO26+AQ26+AS26) -> 7020 | AU26: =AT25-AT26+AV26 -> 120 | AX26: =IF(AV26>0,AW26,AX25) -> 0.7
A27: =ELEC!C25 -> 43884 | B27: 222 | C27: 228.1 | D27: =C26-C27 -> 6.2 | E27: =D27*8.38 -> 51.956 | F27: 1430 | G27: =F27-F26 -> 4 | H27: 340602 | I27: =SUM(H27-H26) -> 340 | J27: =IF(G27>0,I27/G27,0) -> 85 | K27: 1818 | L27: =K27-K26 -> 4 | M27: 132812 | N27: =M27-M26 -> 337 | O27: =SUM(L27*$J$1) -> 306.55417 | P27: 1662 | Q27: 142270 | R27: =Q27-Q26 -> 0 | S27: =SUM(P27-P26) -> 0 | T27: =SUM(S27*$T$2) -> 0 | U27: =SUM(G27+L27+S27) -> 8 | V27: =R27+N27+I27:I27 -> 677 | X27: 2374 | Y27: =X27-X26 -> 0 | Z27: 133402.3 | AA27: =Z27-Z26 -> 0.3 | AB27: =SUM(Y27*$AB$2) -> 0 | AC27: 1801 | AD27: =AC27-AC26 -> 0 | AE27: 357717.4 | AF27: =AE27-AE26 -> 0 | AG27: =IF(AD27>0,AF27/AD27,0) -> 0 | AH27: =AF27+AA27 -> 0.3 | AI27: =SUM(AH27+V27) -> 677.3 | AJ27: =-tanks!AW28 -> 677.3 | AK27: =SUM(AJ27-AI27) -> 0 | AL27: =S27+L27+G27 -> 8 | AM27: =Y27+AD27 -> 0 | AN27: 75 | AO27: =(AN27/100)*3000 -> 2250 | AP27: 75 | AQ27: =(AP27/100)*3000 -> 2250 | AR27: 77 | AS27: =(AR27/100)*3000 -> 2310 | AT27: =SUM(AO27+AQ27+AS27) -> 6810 | AU27: =AT26-AT27+AV27 -> 210 | AX27: =IF(AV27>0,AW27,AX26) -> 0.7
A28: =ELEC!C26 -> 43885 | B28: =B27 -> 222 | C28: =C27 -> 228.1 | D28: =C27-C28 -> 0 | E28: =D28*8.38 -> 0 | F28: =F27 -> 1430 | G28: =F28-F27 -> 0 | H28: =H27 -> 340602 | I28: =SUM(H28-H27) -> 0 | J28: =IF(G28>0,I28/G28,0) -> 0 | K28: =K27 -> 1818 | L28: =K28-K27 -> 0 | M28: =M27 -> 132812 | N28: =M28-M27 -> 0 | O28: =SUM(L28*$J$1) -> 0 | P28: 1662 | Q28: =Q27 -> 142270 | R28: =Q28-Q27 -> 0 | S28: =SUM(P28-P27) -> 0 | T28: =SUM(S28*$T$2) -> 0 | U28: =SUM(G28+L28+S28) -> 0 | V28: =R28+N28+I28:I28 -> 0 | X28: =X27 -> 2374 | Y28: =X28-X27 -> 0 | Z28: =Z27 -> 133402.3 | AA28: =Z28-Z27 -> 0 | AB28: =SUM(Y28*$AB$2) -> 0 | AC28: =AC27 -> 1801 | AD28: =AC28-AC27 -> 0 | AE28: =AE27 -> 357717.4 | AF28: =AE28-AE27 -> 0 | AG28: =IF(AD28>0,AF28/AD28,0) -> 0 | AH28: =AF28+AA28 -> 0 | AI28: =SUM(AH28+V28) -> 0 | AJ28: =-tanks!AW29 -> 0 | AK28: =SUM(AJ28-AI28) -> 0 | AL28: =S28+L28+G28 -> 0 | AM28: =Y28+AD28 -> 0 | AN28: =AN27 -> 75 | AO28: =(AN28/100)*3000 -> 2250 | AP28: =AP27 -> 75 | AQ28: =(AP28/100)*3000 -> 2250 | AR28: =AR27 -> 77 | AS28: =(AR28/100)*3000 -> 2310 | AT28: =SUM(AO28+AQ28+AS28) -> 6810 | AU28: =AT27-AT28+AV28 -> 0 | AX28: =IF(AV28>0,AW28,AX27) -> 0.7
A29: =ELEC!C27 -> 43886 | B29: =B28 -> 222 | C29: =C28 -> 228.1 | D29: =C28-C29 -> 0 | E29: =D29*8.38 -> 0 | F29: =F28 -> 1430 | G29: =F29-F28 -> 0 | H29: =H28 -> 340602 | I29: =SUM(H29-H28) -> 0 | J29: =IF(G29>0,I29/G29,0) -> 0 | K29: =K28 -> 1818 | L29: =K29-K28 -> 0 | M29: =M28 -> 132812 | N29: =M29-M28 -> 0 | O29: =SUM(L29*$J$1) -> 0 | P29: =P28 -> 1662 | Q29: =Q28 -> 142270 | R29: =Q29-Q28 -> 0 | S29: =SUM(P29-P28) -> 0 | T29: =SUM(S29*$T$2) -> 0 | U29: =SUM(G29+L29+S29) -> 0 | V29: =R29+N29+I29:I29 -> 0 | X29: =X28 -> 2374 | Y29: =X29-X28 -> 0 | Z29: =Z28 -> 133402.3 | AA29: =Z29-Z28 -> 0 | AB29: =SUM(Y29*$AB$2) -> 0 | AC29: =AC28 -> 1801 | AD29: =AC29-AC28 -> 0 | AE29: =AE28 -> 357717.4 | AF29: =AE29-AE28 -> 0 | AG29: =IF(AD29>0,AF29/AD29,0) -> 0 | AH29: =AF29+AA29 -> 0 | AI29: =SUM(AH29+V29) -> 0 | AJ29: =-tanks!AW30 -> 0 | AK29: =SUM(AJ29-AI29) -> 0 | AL29: =S29+L29+G29 -> 0 | AM29: =Y29+AD29 -> 0 | AN29: =AN28 -> 75 | AO29: =(AN29/100)*3000 -> 2250 | AP29: =AP28 -> 75 | AQ29: =(AP29/100)*3000 -> 2250 | AR29: =AR28 -> 77 | AS29: =(AR29/100)*3000 -> 2310 | AT29: =SUM(AO29+AQ29+AS29) -> 6810 | AU29: =AT28-AT29+AV29 -> 0 | AX29: =IF(AV29>0,AW29,AX28) -> 0.7
A30: =ELEC!C28 -> 43887 | B30: =B29 -> 222 | C30: =C29 -> 228.1 | D30: =C29-C30 -> 0 | E30: =D30*8.38 -> 0 | F30: =F29 -> 1430 | G30: =F30-F29 -> 0 | H30: =H29 -> 340602 | I30: =SUM(H30-H29) -> 0 | J30: =IF(G30>0,I30/G30,0) -> 0 | K30: =K29 -> 1818 | L30: =K30-K29 -> 0 | M30: =M29 -> 132812 | N30: =M30-M29 -> 0 | O30: =SUM(L30*$J$1) -> 0 | P30: =P29 -> 1662 | Q30: =Q29 -> 142270 | R30: =Q30-Q29 -> 0 | S30: =SUM(P30-P29) -> 0 | T30: =SUM(S30*$T$2) -> 0 | U30: =SUM(G30+L30+S30) -> 0 | V30: =R30+N30+I30:I30 -> 0 | X30: =X29 -> 2374 | Y30: =X30-X29 -> 0 | Z30: =Z29 -> 133402.3 | AA30: =Z30-Z29 -> 0 | AB30: =SUM(Y30*$AB$2) -> 0 | AC30: =AC29 -> 1801 | AD30: =AC30-AC29 -> 0 | AE30: =AE29 -> 357717.4 | AF30: =AE30-AE29 -> 0 | AG30: =IF(AD30>0,AF30/AD30,0) -> 0 | AH30: =AF30+AA30 -> 0 | AI30: =SUM(AH30+V30) -> 0 | AJ30: =-tanks!AW31 -> 0 | AK30: =SUM(AJ30-AI30) -> 0 | AL30: =S30+L30+G30 -> 0 | AM30: =Y30+AD30 -> 0 | AN30: =AN29 -> 75 | AO30: =(AN30/100)*3000 -> 2250 | AP30: =AP29 -> 75 | AQ30: =(AP30/100)*3000 -> 2250 | AR30: =AR29 -> 77 | AS30: =(AR30/100)*3000 -> 2310 | AT30: =SUM(AO30+AQ30+AS30) -> 6810 | AU30: =AT29-AT30+AV30 -> 0 | AX30: =IF(AV30>0,AW30,AX29) -> 0.7
A31: =ELEC!C29 -> 43888 | B31: =B30 -> 222 | C31: =C30 -> 228.1 | D31: =C30-C31 -> 0 | E31: =D31*8.38 -> 0 | F31: =F30 -> 1430 | G31: =F31-F30 -> 0 | H31: =H30 -> 340602 | I31: =SUM(H31-H30) -> 0 | J31: =IF(G31>0,I31/G31,0) -> 0 | K31: =K30 -> 1818 | L31: =K31-K30 -> 0 | M31: =M30 -> 132812 | N31: =M31-M30 -> 0 | O31: =SUM(L31*$J$1) -> 0 | P31: =P30 -> 1662 | Q31: =Q30 -> 142270 | R31: =Q31-Q30 -> 0 | S31: =SUM(P31-P30) -> 0 | T31: =SUM(S31*$T$2) -> 0 | U31: =SUM(G31+L31+S31) -> 0 | V31: =R31+N31+I31:I31 -> 0 | X31: =X30 -> 2374 | Y31: =X31-X30 -> 0 | Z31: =Z30 -> 133402.3 | AA31: =Z31-Z30 -> 0 | AB31: =SUM(Y31*$AB$2) -> 0 | AC31: =AC30 -> 1801 | AD31: =AC31-AC30 -> 0 | AE31: =AE30 -> 357717.4 | AF31: =AE31-AE30 -> 0 | AG31: =IF(AD31>0,AF31/AD31,0) -> 0 | AH31: =AF31+AA31 -> 0 | AI31: =SUM(AH31+V31) -> 0 | AJ31: =-tanks!AW32 -> 0 | AK31: =SUM(AJ31-AI31) -> 0 | AL31: =S31+L31+G31 -> 0 | AM31: =Y31+AD31 -> 0 | AN31: =AN30 -> 75 | AO31: =(AN31/100)*3000 -> 2250 | AP31: =AP30 -> 75 | AQ31: =(AP31/100)*3000 -> 2250 | AR31: =AR30 -> 77 | AS31: =(AR31/100)*3000 -> 2310 | AT31: =SUM(AO31+AQ31+AS31) -> 6810 | AU31: =AT30-AT31+AV31 -> 0 | AX31: =IF(AV31>0,AW31,AX30) -> 0.7
A32: =ELEC!C30 -> 43889 | B32: =B31 -> 222 | C32: =C31 -> 228.1 | D32: =C31-C32 -> 0 | E32: =D32*8.38 -> 0 | F32: =F31 -> 1430 | G32: =F32-F31 -> 0 | H32: =H31 -> 340602 | I32: =SUM(H32-H31) -> 0 | J32: =IF(G32>0,I32/G32,0) -> 0 | K32: =K31 -> 1818 | L32: =K32-K31 -> 0 | M32: =M31 -> 132812 | N32: =M32-M31 -> 0 | O32: =SUM(L32*$J$1) -> 0 | P32: =P31 -> 1662 | Q32: =Q31 -> 142270 | R32: =Q32-Q31 -> 0 | S32: =SUM(P32-P31) -> 0 | T32: =SUM(S32*$T$2) -> 0 | U32: =SUM(G32+L32+S32) -> 0 | V32: =R32+N32+I32:I32 -> 0 | X32: =X31 -> 2374 | Y32: =X32-X31 -> 0 | Z32: =Z31 -> 133402.3 | AA32: =Z32-Z31 -> 0 | AB32: =SUM(Y32*$AB$2) -> 0 | AC32: =AC31 -> 1801 | AD32: =AC32-AC31 -> 0 | AE32: =AE31 -> 357717.4 | AF32: =AE32-AE31 -> 0 | AG32: =IF(AD32>0,AF32/AD32,0) -> 0 | AH32: =AF32+AA32 -> 0 | AI32: =SUM(AH32+V32) -> 0 | AJ32: =-tanks!AW33 -> 0 | AK32: =SUM(AJ32-AI32) -> 0 | AL32: =S32+L32+G32 -> 0 | AM32: =Y32+AD32 -> 0 | AN32: =AN31 -> 75 | AO32: =(AN32/100)*3000 -> 2250 | AP32: =AP31 -> 75 | AQ32: =(AP32/100)*3000 -> 2250 | AR32: =AR31 -> 77 | AS32: =(AR32/100)*3000 -> 2310 | AT32: =SUM(AO32+AQ32+AS32) -> 6810 | AU32: =AT31-AT32+AV32 -> 0 | AX32: =IF(AV32>0,AW32,AX31) -> 0.7
A33: =ELEC!C31 -> 43890 | B33: =B32 -> 222 | C33: =C32 -> 228.1 | D33: =C32-C33 -> 0 | E33: =D33*8.38 -> 0 | F33: =F32 -> 1430 | G33: =F33-F32 -> 0 | H33: =H32 -> 340602 | I33: =SUM(H33-H32) -> 0 | J33: =IF(G33>0,I33/G33,0) -> 0 | K33: =K32 -> 1818 | L33: =K33-K32 -> 0 | M33: =M32 -> 132812 | N33: =M33-M32 -> 0 | O33: =SUM(L33*$J$1) -> 0 | P33: =P32 -> 1662 | Q33: =Q32 -> 142270 | R33: =Q33-Q32 -> 0 | S33: =SUM(P33-P32) -> 0 | T33: =SUM(S33*$T$2) -> 0 | U33: =SUM(G33+L33+S33) -> 0 | V33: =R33+N33+I33:I33 -> 0 | X33: =X32 -> 2374 | Y33: =X33-X32 -> 0 | Z33: =Z32 -> 133402.3 | AA33: =Z33-Z32 -> 0 | AB33: =SUM(Y33*$AB$2) -> 0 | AC33: =AC32 -> 1801 | AD33: =AC33-AC32 -> 0 | AE33: =AE32 -> 357717.4 | AF33: =AE33-AE32 -> 0 | AG33: =IF(AD33>0,AF33/AD33,0) -> 0 | AH33: =AF33+AA33 -> 0 | AI33: =SUM(AH33+V33) -> 0 | AJ33: =-tanks!AW34 -> 0 | AK33: =SUM(AJ33-AI33) -> 0 | AL33: =S33+L33+G33 -> 0 | AM33: =Y33+AD33 -> 0 | AN33: =AN32 -> 75 | AO33: =(AN33/100)*3000 -> 2250 | AP33: =AP32 -> 75 | AQ33: =(AP33/100)*3000 -> 2250 | AR33: =AR32 -> 77 | AS33: =(AR33/100)*3000 -> 2310 | AT33: =SUM(AO33+AQ33+AS33) -> 6810 | AU33: =AT32-AT33+AV33 -> 0 | AX33: =IF(AV33>0,AW33,AX32) -> 0.7
B34: =B33 -> 222 | C34: =C33 -> 228.1 | D34: =C33-C34 -> 0 | E34: =D34*8.38 -> 0 | F34: =F33 -> 1430 | G34: =F34-F33 -> 0 | H34: =H33 -> 340602 | I34: =SUM(H34-H33) -> 0 | J34: =IF(G34>0,I34/G34,0) -> 0 | K34: =K33 -> 1818 | L34: =K34-K33 -> 0 | M34: =M33 -> 132812 | N34: =M34-M33 -> 0 | O34: =SUM(L34*$J$1) -> 0 | P34: =P33 -> 1662 | Q34: =Q33 -> 142270 | R34: =Q34-Q33 -> 0 | S34: =SUM(P34-P33) -> 0 | T34: =SUM(S34*$T$2) -> 0 | U34: =SUM(G34+L34+S34) -> 0 | V34: =R34+N34+I34:I34 -> 0 | X34: =X33 -> 2374 | Y34: =X34-X33 -> 0 | Z34: =Z33 -> 133402.3 | AA34: =Z34-Z33 -> 0 | AB34: =SUM(Y34*$AB$2) -> 0 | AC34: =AC33 -> 1801 | AD34: =AC34-AC33 -> 0 | AE34: =AE33 -> 357717.4 | AF34: =AE34-AE33 -> 0 | AG34: =IF(AD34>0,AF34/AD34,0) -> 0 | AH34: =AF34+AA34 -> 0 | AI34: =SUM(AH34+V34) -> 0 | AJ34: =-tanks!AW35 -> 0 | AK34: =SUM(AJ34-AI34) -> 0 | AL34: =S34+L34+G34 -> 0 | AM34: =Y34+AD34 -> 0 | AN34: =AN33 -> 75 | AO34: =(AN34/100)*3000 -> 2250 | AP34: =AP33 -> 75 | AQ34: =(AP34/100)*3000 -> 2250 | AR34: =AR33 -> 77 | AS34: =(AR34/100)*3000 -> 2310 | AT34: =SUM(AO34+AQ34+AS34) -> 6810 | AU34: =AT33-AT34+AV34 -> 0 | AX34: =IF(AV34>0,AW34,AX33) -> 0.7
B35: =B34 -> 222 | C35: =C34 -> 228.1 | D35: =C34-C35 -> 0 | E35: =D35*8.38 -> 0 | F35: =F34 -> 1430 | G35: =F35-F34 -> 0 | H35: =H34 -> 340602 | I35: =SUM(H35-H34) -> 0 | J35: =IF(G35>0,I35/G35,0) -> 0 | K35: =K34 -> 1818 | L35: =K35-K34 -> 0 | M35: =M34 -> 132812 | N35: =M35-M34 -> 0 | O35: =SUM(L35*$J$1) -> 0 | P35: =P34 -> 1662 | Q35: =Q34 -> 142270 | R35: =Q35-Q34 -> 0 | S35: =SUM(P35-P34) -> 0 | T35: =SUM(S35*$T$2) -> 0 | U35: =SUM(G35+L35+S35) -> 0 | V35: =R35+N35+I35:I35 -> 0 | X35: =X34 -> 2374 | Y35: =X35-X34 -> 0 | Z35: =Z34 -> 133402.3 | AA35: =Z35-Z34 -> 0 | AB35: =SUM(Y35*$AB$2) -> 0 | AC35: =AC34 -> 1801 | AD35: =AC35-AC34 -> 0 | AE35: =AE34 -> 357717.4 | AF35: =AE35-AE34 -> 0 | AG35: =IF(AD35>0,AF35/AD35,0) -> 0 | AH35: =AF35+AA35 -> 0 | AI35: =SUM(AH35+V35) -> 0 | AJ35: =-tanks!AW36 -> 0 | AK35: =SUM(AJ35-AI35) -> 0 | AL35: =S35+L35+G35 -> 0 | AM35: =Y35+AD35 -> 0 | AN35: =AN34 -> 75 | AO35: =(AN35/100)*3000 -> 2250 | AP35: =AP34 -> 75 | AQ35: =(AP35/100)*3000 -> 2250 | AR35: =AR34 -> 77 | AS35: =(AR35/100)*3000 -> 2310 | AT35: =SUM(AO35+AQ35+AS35) -> 6810 | AU35: =AT34-AT35+AV35 -> 0 | AX35: =IF(AV35>0,AW35,AX34) -> 0.7
J36: =SUM(J5:J34)/(COUNT(J5:J34)-COUNTIF(J5:J34,0)) -> 76.638542 | AE36: . | AR36: Nb Delivery | AS36: =COUNT(AW5:AW35) -> 3 | AU36: =SUM(AU5:AU35) -> 4200 | AV36: =SUM(AV5:AV35) -> 3900 | AW36: =SUM(AW5:AW35)/AS36 -> 0.7
AH37: =AF37+AA37 -> 0 | AI37: =SUM(AI5:AI35) -> 18423.8
AH38: =AF38+AA38 -> 0 | AU38: =AU36*0.51 -> 2142 | AV38: =AV36/0.51 -> 7647.0588 | AW38: =SUM(AW5:AW35)/AS36 -> 0.7
AV39: =AV36*0.51 -> 1989

Sheet WATER
D1: =SUM(G21:G35) -> 8872145 | AR1: Entrance | AT1: Tank 1 | AV1: Tank 2
AR2: Level | AW2: Quantity CM3 | AZ2: Var
A3: Date | B3: Truck | C3: Truck M3/day | D3: N0. Trucks | F3: REQ. # of trucks | G3: City | H3: City/day | I3: Total water delivery | K3: SW | L3: Cosum SW/day | M3: RO Guest/ Liter | O3: RO K&L/ Liter | Q3: TOTAL RO Production | R3: RO 1 RH | S3: RO 2 RH | T3: RO water counter | U3: RO Cons m3 | V3: Steam Boiler | W3: Steam Boiler/day | X3: Softener Guest | Y3: Guest Sotf/day | Z3: Softener K&L | AA3: K&L Soft/Day | AB3: Fire Tank Level | AC3: Fire Tank Counter | AE3: Laundry Hot Water Counter | AF3: Hot Water Cons/day | AG3: Laundry Cold Water Counter | AH3: Cold Water Cons/day | AI3: Laundry Water Total Cons | AJ3: K&L Sotf/day | AK3: Guest / day | AL3: K&L /day | AM3: Avg Outside Temp | AN3: Banquet Activity | AR3: Date | AT3: MainI | AV3: Kitchen and Laundry | AX3: Guest | AY3: Main Tank | AZ3: Kitchen and Laundry | BA3: Guest | BB3: Kitchen and Laundry | BC3: Main | BD3: Guest | BE3: Total VAR | BF3: Hotel Consumption
E4: 1.66 | AN4: Ball R | AO4: Meeting | AP4: outlet | AT4: 180 | AV4: 220 | AX4: 580 | AY4: =SUM(AT4) -> 180 | AZ4: =SUM(AV4) -> 220 | BA4: =SUM(AX4) -> 580
A5: 43769 | B5: =[1]WATER!B36 -> 108441 | C5: =[1]WATER!C36 -> 0 | D5: =[1]WATER!D36 -> 0 | E5: =[1]WATER!E36 -> 241.93548 | F5: =[1]WATER!F36 -> 0 | G5: =[1]WATER!G36 -> 589336 | H5: =[1]WATER!H36 -> 0 | I5: =[1]WATER!I36 -> 0 | ... BG5: =[1]WATER!BG36 -> -80
A6: =ELEC!C3 -> 43862 | B6: 108441 | C6: =B6-B5 -> 0 | D6: =C6/27 -> 0 | E6: =SUM((C6*$E$4)+(7500/'EDl log'!$A$36)) -> 258.62069 | G6: 589656 | H6: =G6-G5 -> 320 | I6: =C6+H6 -> 320 | J6: =IF(I6>0,E6/I6,0) -> 0.80818966 | K6: ='Swimming Pool quality check '!H6 -> 5897 | L6: 0 | M6: =M5 -> 457.44 | N6: =SUM(M6-M5) -> 0 | O6: =O5 -> 529.52 | P6: =SUM(O6-O5) -> 0 | Q6: =P6+N6 -> 0 | T6: 4524 | U6: =SUM(T6-T5) -> 5 | V6: 363 | W6: =+V6-V5 -> 0 | X6: 140535 | Y6: =SUM(X6-X5) -> 168 | Z6: 92018 | AA6: =Z6-Z5 -> 58 | AB6: =AB5 -> 261 | AC6: =AC5 -> 671 | AD6: 0 | AE6: 94.46 | AF6: =AE6-AE5 -> 2.08 | AG6: 1236.52 | AH6: =AG6-AG5 -> 15.51 | AI6: =AF6+AH6 -> 17.59 | AJ6: =+Z6-Z5 -> 58 | AK6: =SUM(Y6-L6) -> 168 | AL6: =SUM(AJ6-W6) -> 58 | AM6: ='General information '!D6 -> 14.5 | AN6: ='General information '!H6 -> 0 | AP6: ='General information '!J6 -> 210 | AR6: =A6 -> 43862 | AS6: =AS5 -> 0.9 | AT6: 87 | AU6: =AU5 -> 1.1 | AV6: 147 | AW6: 2.9 | AX6: 161 | AY6: =AS6*AT6 -> 78.3 | AZ6: =AU6*AV6 -> 161.7 | BA6: =AW6*AX6 -> 466.9 | BB6: =AY6-AY5 -> -9.9 | BC6: =AZ6-AZ5 -> 14.3 | BD6: =BA6-BA5 -> 92.8 | BE6: =SUM(BB6:BD6) -> 97.2 | BF6: =SUM(I6-BE6) -> 222.8 | BG6: =SUM(I6-BF6) -> 97.2
A7: =ELEC!C4 -> 43863 | B7: 108441 | C7: =B7-B6 -> 0 | D7: =C7/27 -> 0 | E7: =SUM((C7*$E$4)+(7500/'EDl log'!$A$36)) -> 258.62069 | G7: 589696 | H7: =G7-G6 -> 40 | I7: =C7+H7 -> 40 | J7: =IF(I7>0,E7/I7,0) -> 6.4655172 | K7: ='Swimming Pool quality check '!H7 -> 5898 | L7: =K7-K6 -> 1 | M7: =M6 -> 457.44 | N7: =SUM(M7-M6) -> 0 | O7: =O6 -> 529.52 | P7: =SUM(O7-O6) -> 0 | Q7: =P7+N7 -> 0 | T7: 4532 | U7: =SUM(T7-T6) -> 8 | V7: =V6 -> 363 | W7: =+V7-V6 -> 0 | X7: 140535 | Y7: =SUM(X7-X6) -> 0 | Z7: 92018 | AA7: =Z7-Z6 -> 0 | AB7: =AB6 -> 261 | AC7: =AC6 -> 671 | AD7: =AC7-AC6 -> 0 | AE7: 94.46 | AF7: =AE7-AE6 -> 0 | AG7: 1236.82 | AH7: =AG7-AG6 -> 0.3 | AI7: =AF7+AH7 -> 0.3 | AJ7: =+Z7-Z6 -> 0 | AK7: =SUM(Y7-L7) -> -1 | AL7: =SUM(AJ7-W7) -> 0 | AM7: ='General information '!D7 -> 14 | AN7: ='General information '!H7 -> 0 | AP7: ='General information '!J7 -> 258 | AR7: =A7 -> 43863 | AS7: =AS6 -> 0.9 | AT7: 87 | AU7: =AU6 -> 1.1 | AV7: 123 | AW7: 2.9 | AX7: 154 | AY7: =AS7*AT7 -> 78.3 | AZ7: =AU7*AV7 -> 135.3 | BA7: =AW7*AX7 -> 446.6 | BB7: =AY7-AY6 -> 0 | BC7: =AZ7-AZ6 -> -26.4 | BD7: =BA7-BA6 -> -20.3 | BE7: =SUM(BB7:BD7) -> -46.7 | BF7: =SUM(I7-BE7) -> 86.7 | BG7: =SUM(I7-BF7) -> -46.7
A8: =ELEC!C5 -> 43864 | B8: 108441 | C8: =B8-B7 -> 0 | D8: =C8/27 -> 0 | E8: =SUM((C8*$E$4)+(7500/'EDl log'!$A$36)) -> 258.62069 | G8: 589814 | H8: =G8-G7 -> 118 | I8: =C8+H8 -> 118 | J8: =IF(I8>0,E8/I8,0) -> 2.1917008 | K8: ='Swimming Pool quality check '!H8 -> 5901 | L8: =K8-K7 -> 3 | M8: =M7 -> 457.44 | N8: =SUM(M8-M7) -> 0 | O8: =O7 -> 529.52 | P8: =SUM(O8-O7) -> 0 | Q8: =P8+N8 -> 0 | T8: 4535 | U8: =SUM(T8-T7) -> 3 | V8: 363 | W8: =+V8-V7 -> 0 | X8: 140559 | Y8: =SUM(X8-X7) -> 24 | Z8: 92061 | AA8: =Z8-Z7 -> 43 | AB8: =AB7 -> 261 | AC8: =AC7 -> 671 | AD8: =AC8-AC7 -> 0 | AE8: 94.46 | AF8: =AE8-AE7 -> 0 | AG8: 1237.2 | AH8: =AG8-AG7 -> 0.38 | AI8: =AF8+AH8 -> 0.38 | AJ8: =+Z8-Z7 -> 43 | AK8: =SUM(Y8-L8) -> 21 | AL8: =SUM(AJ8-W8) -> 43 | AM8: ='General information '!D8 -> 13 | AN8: ='General information '!H8 -> 0 | AP8: ='General information '!J8 -> 134 | AR8: =A8 -> 43864 | AS8: =AS7 -> 0.9 | AT8: 196 | AU8: 1.1 | AV8: 142 | AW8: 2.9 | AX8: 148 | AY8: =AS8*AT8 -> 176.4 | AZ8: =AU8*AV8 -> 156.2 | BA8: =AW8*AX8 -> 429.2 | BB8: =AY8-AY7 -> 98.1 | BC8: =AZ8-AZ7 -> 20.9 | BD8: =BA8-BA7 -> -17.4 | BE8: =SUM(BB8:BD8) -> 101.6 | BF8: =SUM(I8-BE8) -> 16.4 | BG8: =SUM(I8-BF8) -> 101.6
A9: =ELEC!C6 -> 43865 | B9: =B8 -> 108441 | C9: =B9-B8 -> 0 | D9: =C9/27 -> 0 | E9: =SUM((C9*$E$4)+(7500/'EDl log'!$A$36)) -> 258.62069 | G9: =G8 -> 589814 | H9: =G9-G8 -> 0 | I9: =C9+H9 -> 0 | J9: =IF(I9>0,E9/I9,0) -> 0 | K9: ='Swimming Pool quality check '!H9 -> 5902 | L9: =K9-K8 -> 1 | M9: =M8 -> 457.44 | N9: =SUM(M9-M8) -> 0 | O9: =O8 -> 529.52 | P9: =SUM(O9-O8) -> 0 | Q9: =P9+N9 -> 0 | T9: 4538 | U9: =SUM(T9-T8) -> 3 | V9: 366 | W9: =+V9-V8 -> 3 | X9: 140561 | Y9: =SUM(X9-X8) -> 2 | Z9: 92063 | AA9: =Z9-Z8 -> 2 | AB9: =AB8 -> 261 | AC9: =AC8 -> 671 | AD9: =AC9-AC8 -> 0 | AE9: 95.27 | AF9: =AE9-AE8 -> 0.81 | AG9: 1243.09 | AH9: =AG9-AG8 -> 5.89 | AI9: =AF9+AH9 -> 6.7 | AJ9: =+Z9-Z8 -> 2 | AK9: =SUM(Y9-L9) -> 1 | AL9: =SUM(AJ9-W9) -> -1 | AM9: ='General information '!D9 -> 15 | AN9: ='General information '!H9 -> 0 | AP9: ='General information '!J9 -> 155 | AR9: =A9 -> 43865 | AS9: =AS8 -> 0.9 | AT9: 190 | AU9: =AU8 -> 1.1 | AV9: 123 | AW9: 2.9 | AX9: 139 | AY9: =AS9*AT9 -> 171 | AZ9: =AU9*AV9 -> 135.3 | BA9: =AW9*AX9 -> 403.1 | BB9: =AY9-AY8 -> -5.4 | BC9: =AZ9-AZ8 -> -20.9 | BD9: =BA9-BA8 -> -26.1 | BE9: =SUM(BB9:BD9) -> -52.4 | BF9: =SUM(I9-BE9) -> 52.4 | BG9: =SUM(I9-BF9) -> -52.4
A10: =ELEC!C7 -> 43866 | B10: 108441 | C10: =B10-B9 -> 0 | D10: =C10/27 -> 0 | E10: =SUM((C10*$E$4)+(7500/'EDl log'!$A$36)) -> 258.62069 | G10: 590125 | H10: =G10-G9 -> 311 | I10: =C10+H10 -> 311 | J10: =IF(I10>0,E10/I10,0) -> 0.83157778 | K10: ='Swimming Pool quality check '!H10 -> 5902 | L10: =K10-K9 -> 0 | M10: =M9 -> 457.44 | N10: =SUM(M10-M9) -> 0 | O10: =O9 -> 529.52 | P10: =SUM(O10-O9) -> 0 | Q10: =P10+N10 -> 0 | T10: 4541 | U10: =SUM(T10-T9) -> 3 | V10: 366 | W10: =+V10-V9 -> 0 | X10: 140679 | Y10: =SUM(X10-X9) -> 118 | Z10: 92142 | AA10: =Z10-Z9 -> 79 | AB10: =AB9 -> 261 | AC10: =AC9 -> 671 | AD10: =AC10-AC9 -> 0 | AE10: 97.28 | AF10: =AE10-AE9 -> 2.01 | AG10: 1263.16 | AH10: =AG10-AG9 -> 20.07 | AI10: =AF10+AH10 -> 22.08 | AJ10: =+Z10-Z9 -> 79 | AK10: =SUM(Y10-L10) -> 118 | AL10: =SUM(AJ10-W10) -> 79 | AM10: ='General information '!D10 -> 17.5 | AN10: ='General information '!H10 -> 0 | AP10: ='General information '!J10 -> 175 | AR10: =A10 -> 43866 | AS10: =AS9 -> 0.9 | AT10: 150 | AU10: =AU9 -> 1.1 | AV10: 136 | AW10: 2.9 | AX10: 155 | AY10: =AS10*AT10 -> 135 | AZ10: =AU10*AV10 -> 149.6 | BA10: =AW10*AX10 -> 449.5 | BB10: =AY10-AY9 -> -36 | BC10: =AZ10-AZ9 -> 14.3 | BD10: =BA10-BA9 -> 46.4 | BE10: =SUM(BB10:BD10) -> 24.7 | BF10: =SUM(I10-BE10) -> 286.3 | BG10: =SUM(I10-BF10) -> 24.7
A11: =ELEC!C8 -> 43867 | B11: =B10 -> 108441 | C11: =B11-B10 -> 0 | D11: =C11/27 -> 0 | E11: =SUM((C11*$E$4)+(7500/'EDl log'!$A$36)) -> 258.62069 | G11: =G10 -> 590125 | H11: =G11-G10 -> 0 | I11: =C11+H11 -> 0 | J11: =IF(I11>0,E11/I11,0) -> 0 | K11: ='Swimming Pool quality check '!H11 -> 5902 | L11: =K11-K10 -> 0 | M11: =M10 -> 457.44 | N11: =SUM(M11-M10) -> 0 | O11: =O10 -> 529.52 | P11: =SUM(O11-O10) -> 0 | Q11: =SUM(P11+N11) -> 0 | T11: 4544 | U11: =SUM(T11-T10) -> 3 | V11: =V10 -> 366 | W11: =+V11-V10 -> 0 | X11: 140780 | Y11: =SUM(X11-X10) -> 101 | Z11: 92184 | AA11: =Z11-Z10 -> 42 | AB11: =AB10 -> 261 | AC11: =AC10 -> 671 | AD11: =AC11-AC10 -> 0 | AE11: =AE10 -> 97.28 | AF11: =AE11-AE10 -> 0 | AG11: 1264.24 | AH11: =AG11-AG10 -> 1.08 | AI11: =AF11+AH11 -> 1.08 | AJ11: =+Z11-Z10 -> 42 | AK11: =SUM(Y11-L11) -> 101 | AL11: =SUM(AJ11-W11) -> 42 | AM11: ='General information '!D11 -> 19 | AN11: ='General information '!H11 -> 0 | AP11: ='General information '!J11 -> 162 | AR11: =A11 -> 43867 | AS11: =AS10 -> 0.9 | AT11: 36 | AU11: =AU10 -> 1.1 | AV11: 150 | AW11: 2.9 | AX11: 176 | AY11: =AS11*AT11 -> 32.4 | AZ11: =AU11*AV11 -> 165 | BA11: =AW11*AX11 -> 510.4 | BB11: =AY11-AY10 -> -102.6 | BC11: =AZ11-AZ10 -> 15.4 | BD11: =BA11-BA10 -> 60.9 | BE11: =SUM(BB11:BD11) -> -26.3 | BF11: =SUM(I11-BE11) -> 26.3 | BG11: =SUM(I11-BF11) -> -26.3
A12: =ELEC!C9 -> 43868 | B12: =B11 -> 108441 | C12: =B12-B11 -> 0 | D12: =C12/27 -> 0 | E12: =SUM((C12*$E$4)+(7500/'EDl log'!$A$36)) -> 258.62069 | G12: 590459 | H12: =G12-G11 -> 334 | I12: =C12+H12 -> 334 | J12: =IF(I12>0,E12/I12,0) -> 0.77431344 | K12: ='Swimming Pool quality check '!H12 -> 5903 | L12: =K12-K11 -> 1 | M12: =M11 -> 457.44 | N12: =SUM(M12-M11) -> 0 | O12: =O11 -> 529.52 | P12: =SUM(O12-O11) -> 0 | Q12: =SUM(P12+N12) -> 0 | T12: 4550 | U12: =SUM(T12-T11) -> 6 | V12: 373 | W12: =+V12-V11 -> 7 | X12: 140826 | Y12: =SUM(X12-X11) -> 46 | Z12: 92251 | AA12: =Z12-Z11 -> 67 | AB12: =AB11 -> 261 | AC12: =AC11 -> 671 | AD12: =AC12-AC11 -> 0 | AE12: 98.77 | AF12: =AE12-AE11 -> 1.49 | AG12: 1270 | AH12: =AG12-AG11 -> 5.76 | AI12: =AF12+AH12 -> 7.25 | AJ12: =+Z12-Z11 -> 67 | AK12: =SUM(Y12-L12) -> 45 | AL12: =SUM(AJ12-W12) -> 60 | AM12: ='General information '!D12 -> 13 | AN12: ='General information '!H12 -> 0 | AP12: ='General information '!J12 -> 304 | AR12: =A12 -> 43868 | AS12: =AS11 -> 0.9 | AT12: 130 | AU12: =AU11 -> 1.1 | AV12: 180 | AW12: 2.9 | AX12: 183 | AY12: =AS12*AT12 -> 117 | AZ12: =AU12*AV12 -> 198 | BA12: =AW12*AX12 -> 530.7 | BB12: =AY12-AY11 -> 84.6 | BC12: =AZ12-AZ11 -> 33 | BD12: =BA12-BA11 -> 20.3 | BE12: =SUM(BB12:BD12) -> 137.9 | BF12: =SUM(I12-BE12) -> 196.1 | BG12: =SUM(I12-BF12) -> 137.9
A13: =ELEC!C10 -> 43869 | B13: =B12 -> 108441 | C13: =B13-B12 -> 0 | D13: =C13/27 -> 0 | E13: =SUM((C13*$E$4)+(7500/'EDl log'!$A$36)) -> 258.62069 | G13: =G12 -> 590459 | H13: =G13-G12 -> 0 | I13: =C13+H13 -> 0 | J13: =IF(I13>0,E13/I13,0) -> 0 | K13: ='Swimming Pool quality check '!H13 -> 5904 | L13: =K13-K12 -> 1 | M13: =M12 -> 457.44 | N13: =SUM(M13-M12) -> 0 | O13: =O12 -> 529.52 | P13: =SUM(O13-O12) -> 0 | Q13: =SUM(P13+N13) -> 0 | T13: 4556 | U13: =SUM(T13-T12) -> 6 | V13: 374 | W13: =+V13-V12 -> 1 | X13: =X12 -> 140826 | Y13: =SUM(X13-X12) -> 0 | Z13: =Z12 -> 92251 | AA13: =Z13-Z12 -> 0 | AB13: =AB12 -> 261 | AC13: =AC12 -> 671 | AD13: =AC13-AC12 -> 0 | AE13: 101.54 | AF13: =AE13-AE12 -> 2.77 | AG13: 1287.42 | AH13: =AG13-AG12 -> 17.42 | AI13: =AF13+AH13 -> 20.19 | AJ13: =+Z13-Z12 -> 0 | AK13: =SUM(Y13-L13) -> -1 | AL13: =SUM(AJ13-W13) -> -1 | AM13: ='General information '!D13 -> 11.5 | AN13: ='General information '!H13 -> 0 | AP13: ='General information '!J13 -> 445 | AR13: =A13 -> 43869 | AS13: =AS12 -> 0.9 | AT13: 116 | AU13: =AU12 -> 1.1 | AV13: 146 | AW13: 2.9 | AX13: 173 | AY13: =AS13*AT13 -> 104.4 | AZ13: =AU13*AV13 -> 160.6 | BA13: =AW13*AX13 -> 501.7 | BB13: =AY13-AY12 -> -12.6 | BC13: =AZ13-AZ12 -> -37.4 | BD13: =BA13-BA12 -> -29 | BE13: =SUM(BB13:BD13) -> -79 | BF13: =SUM(I13-BE13) -> 79 | BG13: =SUM(I13-BF13) -> -79
A14: =ELEC!C11 -> 43870 | B14: =B13 -> 108441 | C14: =B14-B13 -> 0 | D14: =C14/27 -> 0 | E14: =SUM((C14*$E$4)+(7500/'EDl log'!$A$36)) -> 258.62069 | G14: =G13 -> 590459 | H14: =G14-G13 -> 0 | I14: =C14+H14 -> 0 | J14: =IF(I14>0,E14/I14,0) -> 0 | K14: ='Swimming Pool quality check '!H14 -> 5904 | L14: =K14-K13 -> 0 | M14: =M13 -> 457.44 | N14: =SUM(M14-M13) -> 0 | O14: =O13 -> 529.52 | P14: =SUM(O14-O13) -> 0 | Q14: =SUM(P14+N14) -> 0 | T14: 4564 | U14: =SUM(T14-T13) -> 8 | V14: =V13 -> 374 | W14: =+V14-V13 -> 0 | X14: 140947 | Y14: =SUM(X14-X13) -> 121 | Z14: 92350 | AA14: =Z14-Z13 -> 99 | AB14: =AB13 -> 261 | AC14: =AC13 -> 671 | AD14: =AC14-AC13 -> 0 | AE14: 101.54 | AF14: =AE14-AE13 -> 0 | AG14: 1288 | AH14: =AG14-AG13 -> 0.58 | AI14: =AF14+AH14 -> 0.58 | AJ14: =+Z14-Z13 -> 99 | AK14: =SUM(Y14-L14) -> 121 | AL14: =SUM(AJ14-W14) -> 99 | AM14: ='General information '!D14 -> 8.5 | AN14: ='General information '!H14 -> 0 | AP14: ='General information '!J14 -> 376 | AR14: =A14 -> 43870 | AS14: =AS13 -> 0.9 | AT14: 110 | AU14: =AU13 -> 1.1 | AV14: 194 | AW14: 2.9 | AX14: 195 | AY14: =AS14*AT14 -> 99 | AZ14: =AU14*AV14 -> 213.4 | BA14: =AW14*AX14 -> 565.5 | BB14: =AY14-AY13 -> -5.4 | BC14: =AZ14-AZ13 -> 52.8 | BD14: =BA14-BA13 -> 63.8 | BE14: =SUM(BB14:BD14) -> 111.2 | BF14: =SUM(I14-BE14) -> -111.2 | BG14: =SUM(I14-BF14) -> 111.2
A15: =ELEC!C12 -> 43871 | B15: 108441 | C15: =B15-B14 -> 0 | D15: =C15/27 -> 0 | E15: =SUM((C15*$E$4)+(7500/'EDl log'!$A$36)) -> 258.62069 | G15: 590783 | H15: =G15-G14 -> 324 | I15: =C15+H15 -> 324 | J15: =IF(I15>0,E15/I15,0) -> 0.79821201 | K15: ='Swimming Pool quality check '!H15 -> 5905 | L15: =K15-K14 -> 1 | M15: =M14 -> 457.44 | N15: =SUM(M15-M14) -> 0 | O15: =O14 -> 529.52 | P15: =SUM(O15-O14) -> 0 | Q15: =SUM(P15+N15) -> 0 | T15: 4571 | U15: =SUM(T15-T14) -> 7 | V15: 374 | W15: =+V15-V14 -> 0 | X15: 140947 | Y15: =SUM(X15-X14) -> 0 | Z15: 92350 | AA15: =Z15-Z14 -> 0 | AB15: =AB14 -> 261 | AC15: =AC14 -> 671 | AD15: =AC15-AC14 -> 0 | AE15: 101.54 | AF15: =AE15-AE14 -> 0 | AG15: 1288.3 | AH15: =AG15-AG14 -> 0.3 | AI15: =AF15+AH15 -> 0.3 | AJ15: =+Z15-Z14 -> 0 | AK15: =SUM(Y15-L15) -> -1 | AL15: =SUM(AJ15-W15) -> 0 | AM15: ='General information '!D15 -> 8.5 | AN15: ='General information '!H15 -> 0 | AP15: ='General information '!J15 -> 206 | AR15: =A15 -> 43871 | AS15: =AS14 -> 0.9 | AT15: 110 | AU15: =AU14 -> 1.1 | AV15: 175 | AW15: 2.9 | AX15: 185 | AY15: =AS15*AT15 -> 99 | AZ15: =AU15*AV15 -> 192.5 | BA15: =AW15*AX15 -> 536.5 | BB15: =AY15-AY14 -> 0 | BC15: =AZ15-AZ14 -> -20.9 | BD15: =BA15-BA14 -> -29 | BE15: =SUM(BB15:BD15) -> -49.9 | BF15: =SUM(I15-BE15) -> 373.9 | BG15: =SUM(I15-BF15) -> -49.9
A16: =ELEC!C13 -> 43872 | B16: 108441 | C16: =B16-B15 -> 0 | D16: =C16/27 -> 0 | E16: =SUM((C16*$E$4)+(7500/'EDl log'!$A$36)) -> 258.62069 | G16: 590924 | H16: =G16-G15 -> 141 | I16: =C16+H16 -> 141 | J16: =IF(I16>0,E16/I16,0) -> 1.8341893 | K16: ='Swimming Pool quality check '!H16 -> 5905 | L16: =K16-K15 -> 0 | M16: =M15 -> 457.44 | N16: =SUM(M16-M15) -> 0 | O16: =O15 -> 529.52 | P16: =SUM(O16-O15) -> 0 | Q16: =SUM(P16+N16) -> 0 | T16: 4576 | U16: =SUM(T16-T15) -> 5 | V16: 375 | W16: =+V16-V15 -> 1 | X16: 140950 | Y16: =SUM(X16-X15) -> 3 | Z16: 92351 | AA16: =Z16-Z15 -> 1 | AB16: 261 | AC16: =AC15 -> 671 | AD16: =AC16-AC15 -> 0 | AE16: 101.54 | AF16: =AE16-AE15 -> 0 | AG16: 1288.58 | AH16: =AG16-AG15 -> 0.28 | AI16: =AF16+AH16 -> 0.28 | AJ16: =+Z16-Z15 -> 1 | AK16: =SUM(Y16-L16) -> 3 | AL16: =SUM(AJ16-W16) -> 0 | AM16: ='General information '!D16 -> 11 | AN16: ='General information '!H16 -> 0 | AP16: ='General information '!J16 -> 199 | AR16: =A16 -> 43872 | AS16: =AS15 -> 0.9 | AT16: 194 | AU16: =AU15 -> 1.1 | AV16: 155 | AW16: 2.9 | AX16: 174 | AY16: =AS16*AT16 -> 174.6 | AZ16: =AU16*AV16 -> 170.5 | BA16: =AW16*AX16 -> 504.6 | BB16: =AY16-AY15 -> 75.6 | BC16: =AZ16-AZ15 -> -22 | BD16: =BA16-BA15 -> -31.9 | BE16: =SUM(BB16:BD16) -> 21.7 | BF16: =SUM(I16-BE16) -> 119.3 | BG16: =SUM(I16-BF16) -> 21.7
A17: =ELEC!C14 -> 43873 | B17: =B16 -> 108441 | C17: =B17-B16 -> 0 | D17: =C17/27 -> 0 | E17: =SUM((C17*$E$4)+(7500/'EDl log'!$A$36)) -> 258.62069 | G17: =G16 -> 590924 | H17: =G17-G16 -> 0 | I17: =C17+H17 -> 0 | J17: =IF(I17>0,E17/I17,0) -> 0 | K17: ='Swimming Pool quality check '!H17 -> 5905 | L17: =K17-K16 -> 0 | M17: =M16 -> 457.44 | N17: =SUM(M17-M16) -> 0 | O17: =O16 -> 529.52 | P17: =SUM(O17-O16) -> 0 | Q17: =SUM(P17+N17) -> 0 | T17: 4580 | U17: =SUM(T17-T16) -> 4 | V17: =V16 -> 375 | W17: =+V17-V16 -> 0 | X17: =X16 -> 140950 | Y17: =SUM(X17-X16) -> 0 | Z17: =Z16 -> 92351 | AA17: =Z17-Z16 -> 0 | AB17: =AB16 -> 261 | AC17: =AC16 -> 671 | AD17: =AC17-AC16 -> 0 | AE17: 105.45 | AF17: =AE17-AE16 -> 3.91 | AG17: 1313.82 | AH17: =AG17-AG16 -> 25.24 | AI17: =AF17+AH17 -> 29.15 | AJ17: =+Z17-Z16 -> 0 | AK17: =SUM(Y17-L17) -> 0 | AL17: =SUM(AJ17-W17) -> 0 | AM17: ='General information '!D17 -> 14.5 | AN17: ='General information '!H17 -> 0 | AP17: ='General information '!J17 -> 136 | AR17: =A17 -> 43873 | AS17: =AS16 -> 0.9 | AT17: =AT16 -> 194 | AU17: =AU16 -> 1.1 | AV17: 115 | AW17: 2.9 | AX17: 170 | AY17: =AS17*AT17 -> 174.6 | AZ17: =AU17*AV17 -> 126.5 | BA17: =AW17*AX17 -> 493 | BB17: =AY17-AY16 -> 0 | BC17: =AZ17-AZ16 -> -44 | BD17: =BA17-BA16 -> -11.6 | BE17: =SUM(BB17:BD17) -> -55.6 | BF17: =SUM(I17-BE17) -> 55.6 | BG17: =SUM(I17-BF17) -> -55.6
A18: =ELEC!C15 -> 43874 | B18: 108441 | C18: =B18-B17 -> 0 | D18: =C18/27 -> 0 | E18: =SUM((C18*$E$4)+(7500/'EDl log'!$A$36)) -> 258.62069 | G18: 590924 | H18: =G18-G17 -> 0 | I18: =C18+H18 -> 0 | J18: =IF(I18>0,E18/I18,0) -> 0 | K18: ='Swimming Pool quality check '!H18 -> 5907 | L18: =K18-K17 -> 2 | M18: =M17 -> 457.44 | N18: =SUM(M18-M17) -> 0 | O18: =O17 -> 529.52 | P18: =SUM(O18-O17) -> 0 | Q18: =SUM(P18+N18) -> 0 | T18: 4584 | U18: =SUM(T18-T17) -> 4 | V18: 380 | W18: =+V18-V17 -> 5 | X18: 140950 | Y18: =SUM(X18-X17) -> 0 | Z18: 92351 | AA18: =Z18-Z17 -> 0 | AB18: =AB17 -> 261 | AC18: =AC17 -> 671 | AD18: =AC18-AC17 -> 0 | AE18: 105.47 | AF18: =AE18-AE17 -> 0.02 | AG18: 1314.29 | AH18: =AG18-AG17 -> 0.47 | AI18: =AF18+AH18 -> 0.49 | AJ18: =+Z18-Z17 -> 0 | AK18: =SUM(Y18-L18) -> -2 | AL18: =SUM(AJ18-W18) -> -5 | AM18: ='General information '!D18 -> 15.5 | AN18: ='General information '!H18 -> 0 | AP18: ='General information '!J18 -> 284 | AR18: =A18 -> 43874 | AS18: =AS17 -> 0.9 | AT18: 182 | AU18: =AU17 -> 1.1 | AV18: 95 | AW18: 2.9 | AX18: 158 | AY18: =AS18*AT18 -> 163.8 | AZ18: =AU18*AV18 -> 104.5 | BA18: =AW18*AX18 -> 458.2 | BB18: =AY18-AY17 -> -10.8 | BC18: =AZ18-AZ17 -> -22 | BD18: =BA18-BA17 -> -34.8 | BE18: =SUM(BB18:BD18) -> -67.6 | BF18: =SUM(I18-BE18) -> 67.6 | BG18: =SUM(I18-BF18) -> -67.6
A19: =ELEC!C16 -> 43875 | B19: =B18 -> 108441 | C19: =B19-B18 -> 0 | D19: =C19/27 -> 0 | E19: =SUM((C19*$E$4)+(7500/'EDl log'!$A$36)) -> 258.62069 | G19: =G18 -> 590924 | H19: =G19-G18 -> 0 | I19: =C19+H19 -> 0 | J19: =IF(I19>0,E19/I19,0) -> 0 | K19: ='Swimming Pool quality check '!H19 -> 5907 | L19: =K19-K18 -> 0 | M19: =M18 -> 457.44 | N19: =SUM(M19-M18) -> 0 | O19: =O18 -> 529.52 | P19: =SUM(O19-O18) -> 0 | Q19: =SUM(P19+N19) -> 0 | T19: 4589 | U19: =SUM(T19-T18) -> 5 | V19: 383 | W19: =+V19-V18 -> 3 | X19: 140950 | Y19: =SUM(X19-X18) -> 0 | Z19: 92352 | AA19: =Z19-Z18 -> 1 | AB19: =AB18 -> 261 | AC19: =AC18 -> 671 | AD19: =AC19-AC18 -> 0 | AE19: 106.94 | AF19: =AE19-AE18 -> 1.47 | AG19: 1320.43 | AH19: =AG19-AG18 -> 6.14 | AI19: =AF19+AH19 -> 7.61 | AJ19: =+Z19-Z18 -> 1 | AK19: =SUM(Y19-L19) -> 0 | AL19: =SUM(AJ19-W19) -> -2 | AM19: ='General information '!D19 -> 14 | AN19: ='General information '!H19 -> 0 | AP19: ='General information '!J19 -> 477 | AR19: =A19 -> 43875 | AS19: =AS18 -> 0.9 | AT19: 181 | AU19: =AU18 -> 1.1 | AV19: 66 | AW19: 2.9 | AX19: 141 | AY19: =AS19*AT19 -> 162.9 | AZ19: =AU19*AV19 -> 72.6 | BA19: =AW19*AX19 -> 408.9 | BB19: =AY19-AY18 -> -0.9 | BC19: =AZ19-AZ18 -> -31.9 | BD19: =BA19-BA18 -> -49.3 | BE19: =SUM(BB19:BD19) -> -82.1 | BF19: =SUM(I19-BE19) -> 82.1 | BG19: =SUM(I19-BF19) -> -82.1
A20: =ELEC!C17 -> 43876 | B20: =B19 -> 108441 | C20: =B20-B19 -> 0 | D20: =C20/27 -> 0 | E20: =SUM((C20*$E$4)+(7500/'EDl log'!$A$36)) -> 258.62069 | G20: =G19 -> 590924 | H20: =G20-G19 -> 0 | I20: =C20+H20 -> 0 | J20: =IF(I20>0,E20/I20,0) -> 0 | K20: ='Swimming Pool quality check '!H20 -> 5908 | L20: =K20-K19 -> 1 | M20: =M19 -> 457.44 | N20: =SUM(M20-M19) -> 0 | O20: =O19 -> 529.52 | P20: =SUM(O20-O19) -> 0 | Q20: =SUM(P20+N20) -> 0 | T20: 4594 | U20: =SUM(T20-T19) -> 5 | V20: =V19 -> 383 | W20: =+V20-V19 -> 0 | X20: =X19 -> 140950 | Y20: =SUM(X20-X19) -> 0 | Z20: =Z19 -> 92352 | AA20: =Z20-Z19 -> 0 | AB20: =AB19 -> 261 | AC20: =AC19 -> 671 | AD20: =AC20-AC19 -> 0 | AE20: 109.33 | AF20: =AE20-AE19 -> 2.39 | AG20: 1342.7 | AH20: =AG20-AG19 -> 22.27 | AI20: =AF20+AH20 -> 24.66 | AJ20: =+Z20-Z19 -> 0 | AK20: =SUM(Y20-L20) -> -1 | AL20: =SUM(AJ20-W20) -> 0 | AM20: ='General information '!D20 -> 14.5 | AN20: ='General information '!H20 -> 0 | AP20: ='General information '!J20 -> 396 | AR20: =A20 -> 43876 | AS20: =AS19 -> 0.9 | AT20: 159 | AU20: =AU19 -> 1.1 | AV20: 58 | AW20: 2.9 | AX20: 128 | AY20: =AS20*AT20 -> 143.1 | AZ20: =AU20*AV20 -> 63.8 | BA20: =AW20*AX20 -> 371.2 | BB20: =AY20-AY19 -> -19.8 | BC20: =AZ20-AZ19 -> -8.8 | BD20: =BA20-BA19 -> -37.7 | BE20: =SUM(BB20:BD20) -> -66.3 | BF20: =SUM(I20-BE20) -> 66.3 | BG20: =SUM(I20-BF20) -> -66.3
A21: =ELEC!C18 -> 43877 | B21: =B20 -> 108441 | C21: =B21-B20 -> 0 | D21: =C21/27 -> 0 | E21: =SUM((C21*$E$4)+(7500/'EDl log'!$A$36)) -> 258.62069 | G21: =G20 -> 590924 | H21: =G21-G20 -> 0 | I21: =C21+H21 -> 0 | J21: =IF(I21>0,E21/I21,0) -> 0 | K21: ='Swimming Pool quality check '!H21 -> 5909 | L21: =K21-K20 -> 1 | M21: =M20 -> 457.44 | N21: =SUM(M21-M20) -> 0 | O21: =O20 -> 529.52 | P21: =SUM(O21-O20) -> 0 | Q21: =SUM(P21+N21) -> 0 | T21: 4599 | U21: =SUM(T21-T20) -> 5 | V21: 383 | W21: =+V21-V20 -> 0 | X21: 140950 | Y21: =SUM(X21-X20) -> 0 | Z21: 92417 | AA21: =Z21-Z20 -> 65 | AB21: =AB20 -> 261 | AC21: =AC20 -> 671 | AD21: =AC21-AC20 -> 0 | AE21: =AE20 -> 109.33 | AF21: =AE21-AE20 -> 0 | AG21: 1343.06 | AH21: =AG21-AG20 -> 0.36 | AI21: =AF21+AH21 -> 0.36 | AJ21: =+Z21-Z20 -> 65 | AK21: =SUM(Y21-L21) -> -1 | AL21: =SUM(AJ21-W21) -> 65 | AM21: ='General information '!D21 -> 14 | AN21: ='General information '!H21 -> 0 | AP21: ='General information '!J21 -> 305 | AR21: =A21 -> 43877 | AS21: =AS20 -> 0.9 | AT21: 126 | AU21: =AU20 -> 1.1 | AV21: 54 | AW21: 2.9 | AX21: 117 | AY21: =AS21*AT21 -> 113.4 | AZ21: =AU21*AV21 -> 59.4 | BA21: =AW21*AX21 -> 339.3 | BB21: =AY21-AY20 -> -29.7 | BC21: =AZ21-AZ20 -> -4.4 | BD21: =BA21-BA20 -> -31.9 | BE21: =SUM(BB21:BD21) -> -66 | BF21: =SUM(I21-BE21) -> 66 | BG21: =SUM(I21-BF21) -> -66
A22: =ELEC!C19 -> 43878 | B22: 108473 | C22: =B22-B21 -> 32 | D22: =C22/27 -> 1.1851852 | E22: =SUM((C22*$E$4)+(7500/'EDl log'!$A$36)) -> 311.74069 | G22: 591131 | H22: =G22-G21 -> 207 | I22: =C22+H22 -> 239 | J22: =IF(I22>0,E22/I22,0) -> 1.3043544 | K22: ='Swimming Pool quality check '!H22 -> 5909 | L22: =K22-K21 -> 0 | M22: =M21 -> 457.44 | N22: =SUM(M22-M21) -> 0 | O22: =O21 -> 529.52 | P22: =SUM(O22-O21) -> 0 | Q22: =SUM(P22+N22) -> 0 | T22: 4604 | U22: =SUM(T22-T21) -> 5 | V22: 383 | W22: =+V22-V21 -> 0 | X22: 140950 | Y22: =SUM(X22-X21) -> 0 | Z22: 92452 | AA22: =Z22-Z21 -> 35 | AB22: 261 | AC22: =AC21 -> 671 | AD22: =AC22-AC21 -> 0 | AE22: 109.33 | AF22: =AE22-AE21 -> 0 | AG22: 1343.38 | AH22: =AG22-AG21 -> 0.32 | AI22: =AF22+AH22 -> 0.32 | AJ22: =+Z22-Z21 -> 35 | AK22: =SUM(Y22-L22) -> 0 | AL22: =SUM(AJ22-W22) -> 35 | AM22: ='General information '!D22 -> 14 | AN22: ='General information '!H22 -> 0 | AP22: ='General information '!J22 -> 178 | AR22: =A22 -> 43878 | AS22: =AS21 -> 0.9 | AT22: 180 | AU22: =AU21 -> 1.1 | AV22: 62 | AW22: 2.9 | AX22: 108 | AY22: =AS22*AT22 -> 162 | AZ22: =AU22*AV22 -> 68.2 | BA22: =AW22*AX22 -> 313.2 | BB22: =AY22-AY21 -> 48.6 | BC22: =AZ22-AZ21 -> 8.8 | BD22: =BA22-BA21 -> -26.1 | BE22: =SUM(BB22:BD22) -> 31.3 | BF22: =SUM(I22-BE22) -> 207.7 | BG22: =SUM(I22-BF22) -> 31.3
A23: =ELEC!C20 -> 43879 | B23: 108473 | C23: =B23-B22 -> 0 | D23: =C23/27 -> 0 | E23: =SUM((C23*$E$4)+(7500/'EDl log'!$A$36)) -> 258.62069 | G23: 591131 | H23: =G23-G22 -> 0 | I23: =C23+H23 -> 0 | J23: =IF(I23>0,E23/I23,0) -> 0 | K23: ='Swimming Pool quality check '!H23 -> 5910 | L23: =K23-K22 -> 1 | M23: =M22 -> 457.44 | N23: =SUM(M23-M22) -> 0 | O23: =O22 -> 529.52 | P23: =SUM(O23-O22) -> 0 | Q23: =SUM(P23+N23) -> 0 | T23: 4609 | U23: =SUM(T23-T22) -> 5 | V23: 386 | W23: =+V23-V22 -> 3 | X23: 140950 | Y23: =SUM(X23-X22) -> 0 | Z23: 92486 | AA23: =Z23-Z22 -> 34 | AB23: =AB22 -> 261 | AC23: =AC22 -> 671 | AD23: =AC23-AC22 -> 0 | AE23: 110.36 | AF23: =AE23-AE22 -> 1.03 | AG23: 1350.8 | AH23: =AG23-AG22 -> 7.42 | AI23: =AF23+AH23 -> 8.45 | AJ23: =+Z23-Z22 -> 34 | AK23: =SUM(Y23-L23) -> -1 | AL23: =SUM(AJ23-W23) -> 31 | AM23: ='General information '!D23 -> 14 | AN23: ='General information '!H23 -> 0 | AP23: ='General information '!J23 -> 179 | AR23: =A23 -> 43879 | AS23: =AS22 -> 0.9 | AT23: 146 | AU23: =AU22 -> 1.1 | AV23: 64 | AW23: 2.9 | AX23: 100 | AY23: =AS23*AT23 -> 131.4 | AZ23: =AU23*AV23 -> 70.4 | BA23: =AW23*AX23 -> 290 | BB23: =AY23-AY22 -> -30.6 | BC23: =AZ23-AZ22 -> 2.2 | BD23: =BA23-BA22 -> -23.2 | BE23: =SUM(BB23:BD23) -> -51.6 | BF23: =SUM(I23-BE23) -> 51.6 | BG23: =SUM(I23-BF23) -> -51.6
A24: =ELEC!C21 -> 43880 | B24: 108473 | C24: =B24-B23 -> 0 | D24: =C24/27 -> 0 | E24: =SUM((C24*$E$4)+(7500/'EDl log'!$A$36)) -> 258.62069 | G24: 591244 | H24: =G24-G23 -> 113 | I24: =C24+H24 -> 113 | J24: =IF(I24>0,E24/I24,0) -> 2.2886787 | K24: ='Swimming Pool quality check '!H24 -> 5911 | L24: =K24-K23 -> 1 | M24: =M23 -> 457.44 | N24: =SUM(M24-M23) -> 0 | O24: =O23 -> 529.52 | P24: =SUM(O24-O23) -> 0 | Q24: =SUM(P24+N24) -> 0 | T24: 4614 | U24: =SUM(T24-T23) -> 5 | V24: 386 | W24: =+V24-V23 -> 0 | X24: 140950 | Y24: =SUM(X24-X23) -> 0 | Z24: 92561 | AA24: =Z24-Z23 -> 75 | AB24: =AB23 -> 261 | AC24: =AC23 -> 671 | AD24: =AC24-AC23 -> 0 | AE24: 113.66 | AF24: =AE24-AE23 -> 3.3 | AG24: 1376.36 | AH24: =AG24-AG23 -> 25.56 | AI24: =AF24+AH24 -> 28.86 | AJ24: =+Z24-Z23 -> 75 | AK24: =SUM(Y24-L24) -> -1 | AL24: =SUM(AJ24-W24) -> 75 | AM24: ='General information '!D24 -> 15.5 | AN24: ='General information '!H24 -> 0 | AP24: ='General information '!J24 -> 173 | AR24: =A24 -> 43880 | AS24: =AS23 -> 0.9 | AT24: 150 | AU24: =AU23 -> 1.1 | AV24: 75 | AW24: 2.9 | AX24: 89 | AY24: =AS24*AT24 -> 135 | AZ24: =AU24*AV24 -> 82.5 | BA24: =AW24*AX24 -> 258.1 | BB24: =AY24-AY23 -> 3.6 | BC24: =AZ24-AZ23 -> 12.1 | BD24: =BA24-BA23 -> -31.9 | BE24: =SUM(BB24:BD24) -> -16.2 | BF24: =SUM(I24-BE24) -> 129.2 | BG24: =SUM(I24-BF24) -> -16.2
A25: =ELEC!C22 -> 43881 | B25: 108473 | C25: =B25-B24 -> 0 | D25: =C25/27 -> 0 | E25: =SUM((C25*$E$4)+(7500/'EDl log'!$A$36)) -> 258.62069 | G25: 591244 | H25: =G25-G24 -> 0 | I25: =C25+H25 -> 0 | J25: =IF(I25>0,E25/I25,0) -> 0 | K25: ='Swimming Pool quality check '!H25 -> 5911 | L25: =K25-K24 -> 0 | M25: =M24 -> 457.44 | N25: =SUM(M25-M24) -> 0 | O25: =O24 -> 529.52 | P25: =SUM(O25-O24) -> 0 | Q25: =SUM(P25+N25) -> 0 | T25: 4618 | U25: =SUM(T25-T24) -> 4 | V25: 386 | W25: =+V25-V24 -> 0 | X25: 140950 | Y25: =SUM(X25-X24) -> 0 | Z25: 92563 | AA25: =Z25-Z24 -> 2 | AB25: =AB24 -> 261 | AC25: =AC24 -> 671 | AD25: =AC25-AC24 -> 0 | AE25: 113.66 | AF25: =AE25-AE24 -> 0 | AG25: 1377.54 | AH25: =AG25-AG24 -> 1.18 | AI25: =AF25+AH25 -> 1.18 | AJ25: =+Z25-Z24 -> 2 | AK25: =SUM(Y25-L25) -> 0 | AL25: =SUM(AJ25-W25) -> 2 | AM25: ='General information '!D25 -> 15.5 | AN25: ='General information '!H25 -> 0 | AP25: ='General information '!J25 -> 266 | AR25: =A25 -> 43881 | AS25: =AS24 -> 0.9 | AT25: 145 | AU25: =AU24 -> 1.1 | AV25: 64 | AW25: 2.9 | AX25: 83 | AY25: =AS25*AT25 -> 130.5 | AZ25: =AU25*AV25 -> 70.4 | BA25: =AW25*AX25 -> 240.7 | BB25: =AY25-AY24 -> -4.5 | BC25: =AZ25-AZ24 -> -12.1 | BD25: =BA25-BA24 -> -17.4 | BE25: =SUM(BB25:BD25) -> -34 | BF25: =SUM(I25-BE25) -> 34 | BG25: =SUM(I25-BF25) -> -34
A26: =ELEC!C23 -> 43882 | B26: 108473 | C26: =B26-B25 -> 0 | D26: =C26/27 -> 0 | E26: =SUM((C26*$E$4)+(7500/'EDl log'!$A$36)) -> 258.62069 | G26: 591368 | H26: =G26-G25 -> 124 | I26: =C26+H26 -> 124 | J26: =IF(I26>0,E26/I26,0) -> 2.0856507 | K26: ='Swimming Pool quality check '!H26 -> 5912 | L26: =K26-K25 -> 1 | M26: =M25 -> 457.44 | N26: =SUM(M26-M25) -> 0 | O26: =O25 -> 529.52 | P26: =SUM(O26-O25) -> 0 | Q26: =SUM(P26+N26) -> 0 | T26: 4623 | U26: =SUM(T26-T25) -> 5 | V26: 387 | W26: =+V26-V25 -> 1 | X26: =X25 -> 140950 | Y26: =SUM(X26-X25) -> 0 | Z26: 92618 | AA26: =Z26-Z25 -> 55 | AB26: =AB25 -> 261 | AC26: =AC25 -> 671 | AD26: =AC26-AC25 -> 0 | AE26: 114.86 | AF26: =AE26-AE25 -> 1.2 | AG26: 1383.82 | AH26: =AG26-AG25 -> 6.28 | AI26: =AF26+AH26 -> 7.48 | AJ26: =+Z26-Z25 -> 55 | AK26: =SUM(Y26-L26) -> -1 | AL26: =SUM(AJ26-W26) -> 54 | AM26: ='General information '!D26 -> 14 | AN26: ='General information '!H26 -> 0 | AP26: ='General information '!J26 -> 208 | AR26: =A26 -> 43882 | AS26: =AS25 -> 0.9 | AT26: 165 | AU26: =AU25 -> 1.1 | AV26: 80 | AW26: 2.9 | AX26: 75 | AY26: =AS26*AT26 -> 148.5 | AZ26: =AU26*AV26 -> 88 | BA26: =AW26*AX26 -> 217.5 | BB26: =AY26-AY25 -> 18 | BC26: =AZ26-AZ25 -> 17.6 | BD26: =BA26-BA25 -> -23.2 | BE26: =SUM(BB26:BD26) -> 12.4 | BF26: =SUM(I26-BE26) -> 111.6 | BG26: =SUM(I26-BF26) -> 12.4
A27: =ELEC!C24 -> 43883 | B27: =B26 -> 108473 | C27: =B27-B26 -> 0 | D27: =C27/27 -> 0 | E27: =SUM((C27*$E$4)+(7500/'EDl log'!$A$36)) -> 258.62069 | G27: 591391 | H27: =G27-G26 -> 23 | I27: =C27+H27 -> 23 | J27: =IF(I27>0,E27/I27,0) -> 11.244378 | K27: ='Swimming Pool quality check '!H27 -> 5913 | L27: =K27-K26 -> 1 | M27: =M26 -> 457.44 | N27: =SUM(M27-M26) -> 0 | O27: =O26 -> 529.52 | P27: =SUM(O27-O26) -> 0 | Q27: =SUM(P27+N27) -> 0 | T27: 4628 | U27: =SUM(T27-T26) -> 5 | V27: 389 | W27: =+V27-V26 -> 2 | X27: 141019 | Y27: =SUM(X27-X26) -> 69 | Z27: 92651 | AA27: =Z27-Z26 -> 33 | AB27: =AB26 -> 261 | AC27: =AC26 -> 671 | AD27: =AC27-AC26 -> 0 | AE27: 117.52 | AF27: =AE27-AE26 -> 2.66 | AG27: 1406.45 | AH27: =AG27-AG26 -> 22.63 | AI27: =AF27+AH27 -> 25.29 | AJ27: =+Z27-Z26 -> 33 | AK27: =SUM(Y27-L27) -> 68 | AL27: =SUM(AJ27-W27) -> 31 | AM27: ='General information '!D27 -> 14.5 | AN27: ='General information '!H27 -> 0 | AP27: ='General information '!J27 -> 264 | AR27: =A27 -> 43883 | AS27: =AS26 -> 0.9 | AT27: 96 | AU27: =AU26 -> 1.1 | AV27: 62 | AW27: 2.9 | AX27: 77 | AY27: =AS27*AT27 -> 86.4 | AZ27: =AU27*AV27 -> 68.2 | BA27: =AW27*AX27 -> 223.3 | BB27: =AY27-AY26 -> -62.1 | BC27: =AZ27-AZ26 -> -19.8 | BD27: =BA27-BA26 -> 5.8 | BE27: =SUM(BB27:BD27) -> -76.1 | BF27: =SUM(I27-BE27) -> 99.1 | BG27: =SUM(I27-BF27) -> -76.1
A28: =ELEC!C25 -> 43884 | B28: 108473 | C28: =B28-B27 -> 0 | D28: =C28/27 -> 0 | E28: =SUM((C28*$E$4)+(7500/'EDl log'!$A$36)) -> 258.62069 | G28: 591714 | H28: =G28-G27 -> 323 | I28: =C28+H28 -> 323 | J28: =IF(I28>0,E28/I28,0) -> 0.80068325 | K28: ='Swimming Pool quality check '!H28 -> 5913 | L28: =K28-K27 -> 0 | M28: =M27 -> 457.44 | N28: =SUM(M28-M27) -> 0 | O28: =O27 -> 529.52 | P28: =SUM(O28-O27) -> 0 | Q28: =SUM(P28+N28) -> 0 | T28: 4635 | U28: =SUM(T28-T27) -> 7 | V28: 389 | W28: =+V28-V27 -> 0 | X28: 141112 | Y28: =SUM(X28-X27) -> 93 | Z28: 92717 | AA28: =Z28-Z27 -> 66 | AB28: =AB27 -> 261 | AC28: =AC27 -> 671 | AD28: =AC28-AC27 -> 0 | AE28: 117.52 | AF28: =AE28-AE27 -> 0 | AG28: 1407.32 | AH28: =AG28-AG27 -> 0.87 | AI28: =AF28+AH28 -> 0.87 | AJ28: =+Z28-Z27 -> 66 | AK28: =SUM(Y28-L28) -> 93 | AL28: =SUM(AJ28-W28) -> 66 | AM28: ='General information '!D28 -> 15 | AN28: ='General information '!H28 -> 0 | AP28: ='General information '!J28 -> 209 | AR28: =A28 -> 43884 | AS28: =AS27 -> 0.9 | AT28: 165 | AU28: =AU27 -> 1.1 | AV28: 77 | AW28: 2.9 | AX28: 90 | AY28: =AS28*AT28 -> 148.5 | AZ28: =AU28*AV28 -> 84.7 | BA28: =AW28*AX28 -> 261 | BB28: =AY28-AY27 -> 62.1 | BC28: =AZ28-AZ27 -> 16.5 | BD28: =BA28-BA27 -> 37.7 | BE28: =SUM(BB28:BD28) -> 116.3 | BF28: =SUM(I28-BE28) -> 206.7 | BG28: =SUM(I28-BF28) -> 116.3
A29: =ELEC!C26 -> 43885 | B29: =B28 -> 108473 | C29: =B29-B28 -> 0 | D29: =C29/27 -> 0 | E29: =SUM((C29*$E$4)+(7500/'EDl log'!$A$36)) -> 258.62069 | G29: =G28 -> 591714 | H29: =G29-G28 -> 0 | I29: =C29+H29 -> 0 | J29: =IF(I29>0,E29/I29,0) -> 0 | K29: ='Swimming Pool quality check '!H29 -> 5913 | L29: =K29-K28 -> 0 | M29: =M28 -> 457.44 | N29: =SUM(M29-M28) -> 0 | O29: =O28 -> 529.52 | P29: =SUM(O29-O28) -> 0 | Q29: =SUM(P29+N29) -> 0 | T29: =T28 -> 4635 | U29: =SUM(T29-T28) -> 0 | V29: =V28 -> 389 | W29: =+V29-V28 -> 0 | X29: =X28 -> 141112 | Y29: =SUM(X29-X28) -> 0 | Z29: =Z28 -> 92717 | AA29: =Z29-Z28 -> 0 | AB29: =AB28 -> 261 | AC29: =AC28 -> 671 | AD29: =AC29-AC28 -> 0 | AE29: =AE28 -> 117.52 | AF29: =AE29-AE28 -> 0 | AG29: =AG28 -> 1407.32 | AH29: =AG29-AG28 -> 0 | AI29: =AF29+AH29 -> 0 | AJ29: =+Z29-Z28 -> 0 | AK29: =SUM(Y29-L29) -> 0 | AL29: =SUM(AJ29-W29) -> 0 | AM29: ='General information '!D29 -> 0 | AN29: ='General information '!H29 -> 0 | AP29: ='General information '!J29 -> 0 | AR29: =A29 -> 43885 | AS29: =AS28 -> 0.9 | AT29: =AT28 -> 165 | AU29: =AU28 -> 1.1 | AV29: =AV28 -> 77 | AW29: 2.9 | AX29: =AX28 -> 90 | AY29: =AS29*AT29 -> 148.5 | AZ29: =AU29*AV29 -> 84.7 | BA29: =AW29*AX29 -> 261 | BB29: =AY29-AY28 -> 0 | BC29: =AZ29-AZ28 -> 0 | BD29: =BA29-BA28 -> 0 | BE29: =SUM(BB29:BD29) -> 0 | BF29: =SUM(I29-BE29) -> 0 | BG29: =SUM(I29-BF29) -> 0
A30: =ELEC!C27 -> 43886 | B30: =B29 -> 108473 | C30: =B30-B29 -> 0 | D30: =C30/27 -> 0 | E30: =SUM((C30*$E$4)+(7500/'EDl log'!$A$36)) -> 258.62069 | G30: =G29 -> 591714 | H30: =G30-G29 -> 0 | I30: =C30+H30 -> 0 | J30: =IF(I30>0,E30/I30,0) -> 0 | K30: ='Swimming Pool quality check '!H30 -> 5913 | L30: =K30-K29 -> 0 | M30: =M29 -> 457.44 | N30: =SUM(M30-M29) -> 0 | O30: =O29 -> 529.52 | P30: =SUM(O30-O29) -> 0 | Q30: =SUM(P30+N30) -> 0 | T30: =T29 -> 4635 | U30: =SUM(T30-T29) -> 0 | V30: =V29 -> 389 | W30: =+V30-V29 -> 0 | X30: =X29 -> 141112 | Y30: =SUM(X30-X29) -> 0 | Z30: =Z29 -> 92717 | AA30: =Z30-Z29 -> 0 | AB30: =AB29 -> 261 | AC30: =AC29 -> 671 | AD30: =AC30-AC29 -> 0 | AE30: =AE29 -> 117.52 | AF30: =AE30-AE29 -> 0 | AG30: =AG29 -> 1407.32 | AH30: =AG30-AG29 -> 0 | AI30: =AF30+AH30 -> 0 | AJ30: =+Z30-Z29 -> 0 | AK30: =SUM(Y30-L30) -> 0 | AL30: =SUM(AJ30-W30) -> 0 | AM30: ='General information '!D30 -> 0 | AN30: ='General information '!H30 -> 0 | AP30: ='General information '!J30 -> 0 | AR30: =A30 -> 43886 | AS30: =AS29 -> 0.9 | AT30: =AT29 -> 165 | AU30: =AU29 -> 1.1 | AV30: =AV29 -> 77 | AW30: 2.9 | AX30: =AX29 -> 90 | AY30: =AS30*AT30 -> 148.5 | AZ30: =AU30*AV30 -> 84.7 | BA30: =AW30*AX30 -> 261 | BB30: =AY30-AY29 -> 0 | BC30: =AZ30-AZ29 -> 0 | BD30: =BA30-BA29 -> 0 | BE30: =SUM(BB30:BD30) -> 0 | BF30: =SUM(I30-BE30) -> 0 | BG30: =SUM(I30-BF30) -> 0
A31: =ELEC!C28 -> 43887 | B31: =B30 -> 108473 | C31: =B31-B30 -> 0 | D31: =C31/27 -> 0 | E31: =SUM((C31*$E$4)+(7500/'EDl log'!$A$36)) -> 258.62069 | G31: =G30 -> 591714 | H31: =G31-G30 -> 0 | I31: =C31+H31 -> 0 | J31: =IF(I31>0,E31/I31,0) -> 0 | K31: ='Swimming Pool quality check '!H31 -> 5913 | L31: =K31-K30 -> 0 | M31: =M30 -> 457.44 | N31: =SUM(M31-M30) -> 0 | O31: =O30 -> 529.52 | P31: =SUM(O31-O30) -> 0 | Q31: =SUM(P31+N31) -> 0 | T31: =T30 -> 4635 | U31: =SUM(T31-T30) -> 0 | V31: =V30 -> 389 | W31: =+V31-V30 -> 0 | X31: =X30 -> 141112 | Y31: =SUM(X31-X30) -> 0 | Z31: =Z30 -> 92717 | AA31: =Z31-Z30 -> 0 | AB31: =AB30 -> 261 | AC31: =AC30 -> 671 | AD31: =AC31-AC30 -> 0 | AE31: =AE30 -> 117.52 | AF31: =AE31-AE30 -> 0 | AG31: =AG30 -> 1407.32 | AH31: =AG31-AG30 -> 0 | AI31: =AF31+AH31 -> 0 | AJ31: =+Z31-Z30 -> 0 | AK31: =SUM(Y31-L31) -> 0 | AL31: =SUM(AJ31-W31) -> 0 | AM31: ='General information '!D31 -> 0 | AN31: ='General information '!H31 -> 0 | AP31: ='General information '!J31 -> 0 | AR31: =A31 -> 43887 | AS31: =AS30 -> 0.9 | AT31: =AT30 -> 165 | AU31: =AU30 -> 1.1 | AV31: =AV30 -> 77 | AW31: 2.9 | AX31: =AX30 -> 90 | AY31: =AS31*AT31 -> 148.5 | AZ31: =AU31*AV31 -> 84.7 | BA31: =AW31*AX31 -> 261 | BB31: =AY31-AY30 -> 0 | BC31: =AZ31-AZ30 -> 0 | BD31: =BA31-BA30 -> 0 | BE31: =SUM(BB31:BD31) -> 0 | BF31: =SUM(I31-BE31) -> 0 | BG31: =SUM(I31-BF31) -> 0
A32: =ELEC!C29 -> 43888 | B32: =B31 -> 108473 | C32: =B32-B31 -> 0 | D32: =C32/27 -> 0 | E32: =SUM((C32*$E$4)+(7500/'EDl log'!$A$36)) -> 258.62069 | G32: =G31 -> 591714 | H32: =G32-G31 -> 0 | I32: =C32+H32 -> 0 | J32: =IF(I32>0,E32/I32,0) -> 0 | K32: ='Swimming Pool quality check '!H32 -> 5913 | L32: =K32-K31 -> 0 | M32: =M31 -> 457.44 | N32: =SUM(M32-M31) -> 0 | O32: =O31 -> 529.52 | P32: =SUM(O32-O31) -> 0 | Q32: =SUM(P32+N32) -> 0 | T32: =T31 -> 4635 | U32: =SUM(T32-T31) -> 0 | V32: =V31 -> 389 | W32: =+V32-V31 -> 0 | X32: =X31 -> 141112 | Y32: =SUM(X32-X31) -> 0 | Z32: =Z31 -> 92717 | AA32: =Z32-Z31 -> 0 | AB32: =AB31 -> 261 | AC32: =AC31 -> 671 | AD32: =AC32-AC31 -> 0 | AE32: =AE31 -> 117.52 | AF32: =AE32-AE31 -> 0 | AG32: =AG31 -> 1407.32 | AH32: =AG32-AG31 -> 0 | AI32: =AF32+AH32 -> 0 | AJ32: =+Z32-Z31 -> 0 | AK32: =SUM(Y32-L32) -> 0 | AL32: =SUM(AJ32-W32) -> 0 | AM32: ='General information '!D32 -> 0 | AN32: ='General information '!H32 -> 0 | AP32: ='General information '!J32 -> 0 | AR32: =A32 -> 43888 | AS32: =AS31 -> 0.9 | AT32: =AT31 -> 165 | AU32: =AU31 -> 1.1 | AV32: =AV31 -> 77 | AW32: 2.9 | AX32: =AX31 -> 90 | AY32: =AS32*AT32 -> 148.5 | AZ32: =AU32*AV32 -> 84.7 | BA32: =AW32*AX32 -> 261 | BB32: =AY32-AY31 -> 0 | BC32: =AZ32-AZ31 -> 0 | BD32: =BA32-BA31 -> 0 | BE32: =SUM(BB32:BD32) -> 0 | BF32: =SUM(I32-BE32) -> 0 | BG32: =SUM(I32-BF32) -> 0
A33: =ELEC!C30 -> 43889 | B33: =B32 -> 108473 | C33: =B33-B32 -> 0 | D33: =C33/27 -> 0 | E33: =SUM((C33*$E$4)+(7500/'EDl log'!$A$36)) -> 258.62069 | G33: =G32 -> 591714 | H33: =G33-G32 -> 0 | I33: =C33+H33 -> 0 | J33: =IF(I33>0,E33/I33,0) -> 0 | K33: ='Swimming Pool quality check '!H33 -> 5913 | L33: =K33-K32 -> 0 | M33: =M32 -> 457.44 | N33: =SUM(M33-M32) -> 0 | O33: =O32 -> 529.52 | P33: =SUM(O33-O32) -> 0 | Q33: =SUM(P33+N33) -> 0 | T33: =T32 -> 4635 | U33: =SUM(T33-T32) -> 0 | V33: =V32 -> 389 | W33: =+V33-V32 -> 0 | X33: =X32 -> 141112 | Y33: =SUM(X33-X32) -> 0 | Z33: =Z32 -> 92717 | AA33: =Z33-Z32 -> 0 | AB33: =AB32 -> 261 | AC33: =AC32 -> 671 | AD33: =AC33-AC32 -> 0 | AE33: =AE32 -> 117.52 | AF33: =AE33-AE32 -> 0 | AG33: =AG32 -> 1407.32 | AH33: =AG33-AG32 -> 0 | AI33: =AF33+AH33 -> 0 | AJ33: =+Z33-Z32 -> 0 | AK33: =SUM(Y33-L33) -> 0 | AL33: =SUM(AJ33-W33) -> 0 | AM33: ='General information '!D33 -> 0 | AN33: ='General information '!H33 -> 0 | AP33: ='General information '!J33 -> 0 | AR33: =A33 -> 43889 | AS33: =AS32 -> 0.9 | AT33: =AT32 -> 165 | AU33: =AU32 -> 1.1 | AV33: =AV32 -> 77 | AW33: 2.9 | AX33: =AX32 -> 90 | AY33: =AS33*AT33 -> 148.5 | AZ33: =AU33*AV33 -> 84.7 | BA33: =AW33*AX33 -> 261 | BB33: =AY33-AY32 -> 0 | BC33: =AZ33-AZ32 -> 0 | BD33: =BA33-BA32 -> 0 | BE33: =SUM(BB33:BD33) -> 0 | BF33: =SUM(I33-BE33) -> 0 | BG33: =SUM(I33-BF33) -> 0
A34: =ELEC!C31 -> 43890 | B34: =B33 -> 108473 | C34: =B34-B33 -> 0 | D34: =C34/27 -> 0 | E34: =SUM((C34*$E$4)+(7500/'EDl log'!$A$36)) -> 258.62069 | G34: =G33 -> 591714 | H34: =G34-G33 -> 0 | I34: =C34+H34 -> 0 | J34: =IF(I34>0,E34/I34,0) -> 0 | K34: ='Swimming Pool quality check '!H34 -> 5913 | L34: =K34-K33 -> 0 | M34: =M33 -> 457.44 | N34: =SUM(M34-M33) -> 0 | O34: =O33 -> 529.52 | P34: =SUM(O34-O33) -> 0 | Q34: =SUM(P34+N34) -> 0 | T34: =T33 -> 4635 | U34: =SUM(T34-T33) -> 0 | V34: =V33 -> 389 | W34: =+V34-V33 -> 0 | X34: =X33 -> 141112 | Y34: =SUM(X34-X33) -> 0 | Z34: =Z33 -> 92717 | AA34: =Z34-Z33 -> 0 | AB34: =AB33 -> 261 | AC34: =AC33 -> 671 | AD34: =AC34-AC33 -> 0 | AE34: =AE33 -> 117.52 | AF34: =AE34-AE33 -> 0 | AG34: =AG33 -> 1407.32 | AH34: =AG34-AG33 -> 0 | AI34: =AF34+AH34 -> 0 | AJ34: =+Z34-Z33 -> 0 | AK34: =SUM(Y34-L34) -> 0 | AL34: =SUM(AJ34-W34) -> 0 | AM34: ='General information '!D34 -> 0 | AN34: ='General information '!H34 -> 0 | AP34: ='General information '!J34 -> 0 | AR34: =A34 -> 43890 | AS34: =AS33 -> 0.9 | AT34: =AT33 -> 165 | AU34: =AU33 -> 1.1 | AV34: =AV33 -> 77 | AW34: 2.9 | AX34: =AX33 -> 90 | AY34: =AS34*AT34 -> 148.5 | AZ34: =AU34*AV34 -> 84.7 | BA34: =AW34*AX34 -> 261 | BB34: =AY34-AY33 -> 0 | BC34: =AZ34-AZ33 -> 0 | BD34: =BA34-BA33 -> 0 | BE34: =SUM(BB34:BD34) -> 0 | BF34: =SUM(I34-BE34) -> 0 | BG34: =SUM(I34-BF34) -> 0
B35: =B34 -> 108473 | C35: =B35-B34 -> 0 | D35: =C35/27 -> 0 | E35: =SUM((C35*$E$4)+(7500/'EDl log'!$A$36)) -> 258.62069 | G35: =G34 -> 591714 | H35: =G35-G34 -> 0 | I35: =C35+H35 -> 0 | J35: =IF(I35>0,E35/I35,0) -> 0 | K35: ='Swimming Pool quality check '!H35 -> 5913 | L35: =K35-K34 -> 0 | M35: =M34 -> 457.44 | N35: =SUM(M35-M34) -> 0 | O35: =O34 -> 529.52 | P35: =SUM(O35-O34) -> 0 | Q35: =SUM(P35+N35) -> 0 | T35: =T34 -> 4635 | U35: =SUM(T35-T34) -> 0 | V35: =V34 -> 389 | W35: =+V35-V34 -> 0 | X35: =X34 -> 141112 | Y35: =SUM(X35-X34) -> 0 | Z35: =Z34 -> 92717 | AA35: =Z35-Z34 -> 0 | AB35: =AB34 -> 261 | AC35: =AC34 -> 671 | AD35: =AC35-AC34 -> 0 | AE35: =AE34 -> 117.52 | AF35: =AE35-AE34 -> 0 | AG35: =AG34 -> 1407.32 | AH35: =AG35-AG34 -> 0 | AI35: =AF35+AH35 -> 0 | AJ35: =+Z35-Z34 -> 0 | AK35: =SUM(Y35-L35) -> 0 | AL35: =SUM(AJ35-W35) -> 0 | AM35: ='General information '!D35 -> 0 | AN35: ='General information '!H35 -> 0 | AP35: ='General information '!J35 -> 0 | AS35: =AS34 -> 0.9 | AT35: =AT34 -> 165 | AU35: =AU34 -> 1.1 | AV35: =AV34 -> 77 | AW35: 2.9 | AX35: =AX34 -> 90 | AY35: =AS35*AT35 -> 148.5 | AZ35: =AU35*AV35 -> 84.7 | BA35: =AW35*AX35 -> 261 | BB35: =AY35-AY34 -> 0 | BC35: =AZ35-AZ34 -> 0 | BD35: =BA35-BA34 -> 0 | BE35: =SUM(BB35:BD35) -> 0 | BF35: =SUM(I35-BE35) -> 0 | BG35: =SUM(I35-BF35) -> 0
B36: =B35 -> 108473 | C36: =B36-B35 -> 0 | D36: =C36/27 -> 0 | E36: =SUM((C36*$E$4)+(7500/'EDl log'!$A$36)) -> 258.62069 | G36: =G35 -> 591714 | H36: =G36-G35 -> 0 | I36: =C36+H36 -> 0 | J36: =IF(I36>0,E36/I36,0) -> 0 | K36: ='Swimming Pool quality check '!H36 -> 5913 | L36: =K36-K35 -> 0 | M36: =M35 -> 457.44 | N36: =SUM(M36-M35) -> 0 | O36: =O35 -> 529.52 | P36: =SUM(O36-O35) -> 0 | Q36: =SUM(P36+N36) -> 0 | T36: =T35 -> 4635 | U36: =SUM(T36-T35) -> 0 | V36: =V35 -> 389 | W36: =+V36-V35 -> 0 | X36: =X35 -> 141112 | Y36: =SUM(X36-X35) -> 0 | Z36: =Z35 -> 92717 | AA36: =Z36-Z35 -> 0 | AB36: =AB35 -> 261 | AC36: =AC35 -> 671 | AD36: =AC36-AC35 -> 0 | AE36: =AE35 -> 117.52 | AF36: =AE36-AE35 -> 0 | AG36: =AG35 -> 1407.32 | AH36: =AG36-AG35 -> 0 | AI36: =AF36+AH36 -> 0 | AJ36: =+Z36-Z35 -> 0 | AK36: =SUM(Y36-L36) -> 0 | AL36: =SUM(AJ36-W36) -> 0 | AM36: ='General information '!D36 -> 0 | AN36: ='General information '!H36 -> 0 | AP36: ='General information '!J36 -> 0 | AS36: =AS35 -> 0.9 | AT36: =AT35 -> 165 | AU36: =AU35 -> 1.1 | AV36: =AV35 -> 77 | AW36: 2.9 | AX36: =AX35 -> 90 | AY36: =AS36*AT36 -> 148.5 | AZ36: =AU36*AV36 -> 84.7 | BA36: =AW36*AX36 -> 261 | BB36: =AY36-AY35 -> 0 | BC36: =AZ36-AZ35 -> 0 | BD36: =BA36-BA35 -> 0 | BE36: =SUM(BB36:BD36) -> 0 | BF36: =SUM(I36-BE36) -> 0 | BG36: =SUM(I36-BF36) -> 0
C37: =SUM(C6:C36) -> 32 | D37: =SUM(D6:D36) -> 1.1851852 | F37: =SUM(F6:F36) -> 0 | H37: =SUM(H6:H36) -> 2378 | I37: =SUM(I6:I36) -> 2410 | L37: =SUM(L7:L36) -> 16 | Q37: =SUM(Q5:Q35) -> 0 | U37: =SUM(U6:U36) -> 116 | Y37: =SUM(Y35,Y33,Y31,Y29,Y27,Y25,Y23,Y21,Y19,Y17,Y15,Y13,Y11,Y9,Y7+Y36) -> 172 | AJ37: =SUM(AJ6:AJ36) -> 757 | AK37: =SUM(Y37-L37) -> 156 | AL37: =SUM(AL6:AL36) -> 731
C38: =+C37*1.66 -> 53.12 | E38: =SUM(E6:E36) -> 8070.3614 | F38: =SUM(F6:F36) -> 0 | H38: 7500 | I38: =SUM('General information '!G37/WATER!I37) -> 0.42728465 | O38: =SUM(Q37+I37) -> 2410 | Z38: =SUM(Y37:AJ37) -> 929 | AK38: =SUM(Y38-L38) -> 0
B39: =9*27 -> 243 | D39: =SUM(D21:D35) -> 1.1851852 | F39: =SUM(F6:F36) -> 0 | G39: =SUM(I37) -> 2410 | H39: =SUM(H38+C38) -> 7553.12 | K39: =SUM(H39/G39) -> 3.1340747 | AJ39: =SUM(C38-AK38) -> 53.12 | AM39: =SUM(AJ39/AO38) -> #DIV/0!

Sheet graphic

Sheet General information 
A1: GENERAL & HOTEL'S INFORMATION SHEET
B4: Max Temp | C4: MIN TEMP | D4: AVE TEMP | E4: AVE Humidity | F4: AVE OCC | G4: # of OCC Rooms | H4: Ball room | I4: Meeting rooms | J4: Outlets | K4: Total covers | L4: # of permenant Emp | M4: # of casuals | N4: Total # of EMP | O4: # of EMP/OCC Room
A5: =ELEC!C2 -> 31-01-2020 | B5: ='[1]General information '!B36 -> 17 | C5: ='[1]General information '!C36 -> 13 | D5: ='[1]General information '!D36 -> 15 | E5: ='[1]General information '!E36 -> 0.64 | F5: ='[1]General information '!F36 -> 0.1478 | G5: ='[1]General information '!G36 -> 33.994 | H5: ='[1]General information '!H36 -> 0 | I5: ='[1]General information '!I36 -> 0 | ... O5: ='[1]General information '!O36 -> 0
A6: =ELEC!C3 -> 43862 | B6: 17 | C6: 12 | D6: =(C6+B6)/2 -> 14.5 | E6: 0.56 | F6: 0.1478 | G6: =F6*230 -> 33.994 | J6: 210 | K6: =+J6+H6 -> 210
A7: =ELEC!C4 -> 43863 | B7: 17 | C7: 11 | D7: =(C7+B7)/2 -> 14 | E7: 0.6 | F7: 0.1087 | G7: =F7*230 -> 25.001 | J7: 258 | K7: =+J7+H7 -> 258
A8: =ELEC!C5 -> 43864 | B8: 16 | C8: 10 | D8: =(C8+B8)/2 -> 13 | E8: 0.65 | F8: 0.1174 | G8: =F8*230 -> 27.002 | J8: 134 | K8: =+J8+H8 -> 134
A9: =ELEC!C6 -> 43865 | B9: 17 | C9: 13 | D9: =(C9+B9)/2 -> 15 | E9: 0.71 | F9: 0.1174 | G9: =F9*230 -> 27.002 | I9: 0 | J9: 155 | K9: =+J9+H9 -> 155
A10: =ELEC!C7 -> 43866 | B10: 20 | C10: 15 | D10: =(C10+B10)/2 -> 17.5 | E10: 0.65 | F10: 0.1478 | G10: =F10*230 -> 33.994 | J10: 175 | K10: =+J10+H10 -> 175
A11: =ELEC!C8 -> 43867 | B11: 22 | C11: 16 | D11: =(C11+B11)/2 -> 19 | E11: 0.61 | F11: 0.2 | G11: =F11*230 -> 46 | I11: 0 | J11: 162 | K11: =+J11+H11 -> 162
A12: =ELEC!C9 -> 43868 | B12: 16 | C12: 10 | D12: =(C12+B12)/2 -> 13 | E12: 0.61 | F12: 0.1957 | G12: =F12*230 -> 45.011 | J12: 304 | K12: =+J12+H12 -> 304
A13: =ELEC!C10 -> 43869 | B13: 14 | C13: 9 | D13: =(C13+B13)/2 -> 11.5 | E13: 0.46 | F13: 0.139 | G13: =F13*230 -> 31.97 | J13: 445 | K13: =+J13+H13 -> 445
A14: =ELEC!C11 -> 43870 | B14: 9 | C14: 8 | D14: =(C14+B14)/2 -> 8.5 | E14: 0.52 | F14: 0.1522 | G14: =F14*230 -> 35.006 | I14: 0 | J14: 376 | K14: =+J14+H14 -> 376
A15: =ELEC!C12 -> 43871 | B15: 10 | C15: 7 | D15: =(C15+B15)/2 -> 8.5 | E15: 0.55 | F15: 0.1609 | G15: =F15*230 -> 37.007 | J15: 206 | K15: =+J15+H15 -> 206
A16: =ELEC!C13 -> 43872 | B16: 14 | C16: 8 | D16: =(C16+B16)/2 -> 11 | E16: 0.5 | F16: 0.1478 | G16: =F16*230 -> 33.994 | J16: 199 | K16: =+J16+H16 -> 199
A17: =ELEC!C14 -> 43873 | B17: 16 | C17: 13 | D17: =(C17+B17)/2 -> 14.5 | E17: 0.6 | F17: 0.2043 | G17: =F17*230 -> 46.989 | I17: 0 | J17: 136 | K17: =+J17+H17 -> 136
A18: =ELEC!C15 -> 43874 | B18: 17 | C18: 14 | D18: =(C18+B18)/2 -> 15.5 | E18: 0.65 | F18: 0.3478 | G18: =F18*230 -> 79.994 | J18: 284 | K18: =+J18+H18 -> 284
A19: =ELEC!C16 -> 43875 | B19: 17 | C19: 11 | D19: =(C19+B19)/2 -> 14 | E19: 0.78 | F19: 0.3826 | G19: =F19*230 -> 87.998 | I19: 0 | J19: 477 | K19: =+J19+H19 -> 477
A20: =ELEC!C17 -> 43876 | B20: 17 | C20: 12 | D20: =(C20+B20)/2 -> 14.5 | E20: 0.59 | F20: 0.247 | G20: =F20*230 -> 56.81 | J20: 396 | K20: =+J20+H20 -> 396
A21: =ELEC!C18 -> 43877 | B21: 17 | C21: 11 | D21: =(C21+B21)/2 -> 14 | E21: 0.58 | F21: 0.1696 | G21: =F21*230 -> 39.008 | J21: 305 | K21: =+J21+H21 -> 305
A22: =ELEC!C19 -> 43878 | B22: 16 | C22: 12 | D22: =(C22+B22)/2 -> 14 | E22: 0.6 | F22: 0.2304 | G22: =F22*230 -> 52.992 | J22: 178 | K22: =+J22+H22 -> 178
A23: =ELEC!C20 -> 43879 | B23: 17 | C23: 11 | D23: =(C23+B23)/2 -> 14 | E23: 0.62 | F23: 0.2348 | G23: =F23*230 -> 54.004 | J23: 179 | K23: =+J23+H23 -> 179
A24: =ELEC!C21 -> 43880 | B24: 17 | C24: 14 | D24: =(C24+B24)/2 -> 15.5 | E24: 0.6 | F24: 0.2304 | G24: =F24*230 -> 52.992 | J24: 173 | K24: =+J24+H24 -> 173
A25: =ELEC!C22 -> 43881 | B25: 17 | C25: 14 | D25: =(C25+B25)/2 -> 15.5 | E25: 0.59 | F25: 0.2261 | G25: =F25*230 -> 52.003 | J25: 266 | K25: =+J25+H25 -> 266
A26: =ELEC!C23 -> 43882 | B26: 16 | C26: 12 | D26: =(C26+B26)/2 -> 14 | E26: 0.82 | F26: 0.2478 | G26: =F26*230 -> 56.994 | J26: 208 | K26: =+J26+H26 -> 208
A27: =ELEC!C24 -> 43883 | B27: 17 | C27: 12 | D27: =(C27+B27)/2 -> 14.5 | E27: 0.65 | F27: 0.1826 | G27: =F27*230 -> 41.998 | J27: 264 | K27: =+J27+H27+I27 -> 264
A28: =ELEC!C25 -> 43884 | B28: 16 | C28: 14 | D28: =(C28+B28)/2 -> 15 | E28: 0.66 | F28: 0.1391 | G28: =F28*230 -> 31.993 | J28: 209 | K28: =+J28+H28+I28 -> 209
A29: =ELEC!C26 -> 43885 | D29: =(C29+B29)/2 -> 0 | G29: =F29*230 -> 0 | K29: =+J29+H29+I29 -> 0
A30: =ELEC!C27 -> 43886 | D30: =(C30+B30)/2 -> 0 | G30: =F30*230 -> 0 | K30: =+J30+H30+I30 -> 0
A31: =ELEC!C28 -> 43887 | D31: =(C31+B31)/2 -> 0 | G31: =F31*230 -> 0 | K31: =+J31+H31+I31 -> 0
A32: =ELEC!C29 -> 43888 | D32: =(C32+B32)/2 -> 0 | G32: =F32*230 -> 0 | K32: =+J32+H32+I32 -> 0
A33: =ELEC!C30 -> 43889 | D33: =(C33+B33)/2 -> 0 | G33: =F33*230 -> 0 | K33: =+J33+H33+I33 -> 0
A34: =ELEC!C31 -> 43890 | D34: =(C34+B34)/2 -> 0 | G34: =F34*230 -> 0 | K34: =+J34+H34+I34 -> 0
A35: =ELEC!C32 -> 0 | D35: =(C35+B35)/2 -> 0 | G35: =F35*230 -> 0 | K35: =+J35+H35+I35 -> 0
A36: =ELEC!C33 -> 0 | D36: =(C36+B36)/2 -> 0 | G36: =F36*230 -> 0 | K36: =+J36+H36+I36 -> 0
F37: =AVERAGE(F6:F36) -> 0.19466087 | G37: =SUM(G6:G35) -> 1029.756
D38: =SUM(D6:D36)/'EDl log'!A34 -> 13.934783
I41: http://www.accuweather.com/en/lb/lebanon-weather

Sheet tanks
B2: Tank 1 | D2: Tank 2 | F2: Tank 3 | H2: Tank 4 | J2: Tank 5 | L2: Tank 6 | N2: Tank 7 | P2: Tank 8 | R2: Tank 9 | T2: Tank 10 | V2: Tank 11 | Z2: Tank 1 | AB2: Tank 2 | AD2: Tank 3 | AF2: Tank 4 | AH2: Tank 5 | AJ2: Tank 6 | AL2: Tank 7
B3: 6670 | D3: =SUM(B3) -> 6670 | F3: =SUM(D3) -> 6670 | H3: =SUM(F3) -> 6670 | J3: =SUM(H3) -> 6670 | L3: =SUM(J3) -> 6670 | N3: =SUM(L3) -> 6670 | P3: =SUM(N3) -> 6670 | R3: =SUM(P3) -> 6670 | T3: =SUM(R3) -> 6670 | V3: =SUM(T3) -> 6670 | W3: =SUM(B3:V3) -> 73370 | Z3: 2800 | AB3: 2800 | AD3: 2800 | AF3: 2800 | AH3: 2800 | AJ3: 2800 | AL3: 2800 | AM3: =SUM(Z3:AL3) -> 19600 | AO3: =SUM(AM3+W3) -> 92970 | AR3: Total sotck | AS3: Diesel Cons Per day | AT3: Diesel Delivery | BE3: Genset Co | BF3: Steam | BG3: Boil | BH3: Outdoor temperature
B4: =B3/310 -> 21.516129 | D4: =SUM(B4) -> 21.516129 | F4: =SUM(D4) -> 21.516129 | H4: =SUM(F4) -> 21.516129 | J4: =SUM(H4) -> 21.516129 | L4: =SUM(J4) -> 21.516129 | N4: =SUM(L4) -> 21.516129 | P4: =SUM(N4) -> 21.516129 | R4: =SUM(P4) -> 21.516129 | T4: =SUM(R4) -> 21.516129 | V4: =SUM(T4) -> 21.516129 | Z4: =Z3/280 -> 10 | AA4: =AA3/280 -> 0 | AB4: =AB3/280 -> 10 | AC4: =AC3/280 -> 0 | AD4: =AD3/280 -> 10 | AE4: =AE3/280 -> 0 | AF4: =AF3/280 -> 10 | AG4: =AG3/280 -> 0 | ... AL4: =AL3/280 -> 10 | AT4: Delivery | AU4: Cost /L | AW4: Boiler+Steam | AX4: Generator | AZ4: Occupancy | BA4: AVE TEPM | BB4: AVE Humidity
A5: =ELEC!C2 -> 31-01-2020 | B5: =[1]tanks!B36 -> 242.4 | C5: =[1]tanks!C36 -> 5215.5097 | D5: =[1]tanks!D36 -> 242.4 | E5: =[1]tanks!E36 -> 5215.5097 | F5: =[1]tanks!F36 -> 242.4 | G5: =[1]tanks!G36 -> 5215.5097 | H5: =[1]tanks!H36 -> 242.4 | I5: =[1]tanks!I36 -> 5215.5097 | ... AO5: =[1]tanks!AO36 -> 17360 | AP5: =[2]tanks!AP36 -> 0 | AQ5: =[1]tanks!AQ36 -> 0.8038142 | AR5: =[1]tanks!AR36 -> 74730.606 | AS5: =[1]tanks!AS36 -> -1493.0516 | AT5: =[1]tanks!AT36 -> 0 | AU5: =[1]tanks!AU36 -> 0 | AV5: =[1]tanks!AV36 -> 0.5835 | AW5: =[1]tanks!AW36 -> -877.9 | AX5: =[1]tanks!AX36 -> -615.15161 | ... BB5: =[1]tanks!BB36 -> 0.64 | BC5: =[2]tanks!BC36 -> 0 | BD5: =[2]tanks!BD36 -> 0 | BE5: =[2]tanks!BE36 -> 0 | BF5: =[2]tanks!BF36 -> 0 | BG5: =[2]tanks!BG36 -> 0 | BH5: =[2]tanks!BH36 -> 0
A6: =ELEC!C3 -> 43862 | B6: ='B5'!B5 -> 237 | C6: =B6*$B$4 -> 5099.3226 | D6: =SUM(B6) -> 237 | E6: =D6*$B$4 -> 5099.3226 | F6: =SUM(D6) -> 237 | G6: =F6*$B$4 -> 5099.3226 | H6: =SUM(F6) -> 237 | I6: =H6*$B$4 -> 5099.3226 | J6: =SUM(H6) -> 237 | K6: =J6*$B$4 -> 5099.3226 | L6: =SUM(J6) -> 237 | M6: =L6*$B$4 -> 5099.3226 | N6: =SUM(L6) -> 237 | O6: =N6*$B$4 -> 5099.3226 | P6: =SUM(N6) -> 237 | Q6: =P6*$B$4 -> 5099.3226 | R6: =SUM(P6) -> 237 | S6: =R6*$B$4 -> 5099.3226 | T6: =SUM(R6) -> 237 | U6: =T6*$B$4 -> 5099.3226 | V6: =SUM(T6) -> 237 | W6: =V6*$B$4 -> 5099.3226 | X6: =SUM(Y6/73370) -> 0.76451613 | Y6: =SUM(C6+E6+G6+I6+K6+M6+O6+Q6+S6+U6+W6) -> 56092.548 | Z6: ='B5'!C5 -> 242 | AA6: =SUM(Z6*$Z$4) -> 2420 | AB6: =SUM(Z6) -> 242 | AC6: =SUM(AB6*$Z$4) -> 2420 | AD6: =SUM(AB6) -> 242 | AE6: =SUM(AD6*$Z$4) -> 2420 | AF6: =SUM(AD6) -> 242 | AG6: =SUM(AF6*$Z$4) -> 2420 | AH6: =SUM(AF6) -> 242 | AI6: =SUM(AH6*$Z$4) -> 2420 | AJ6: =SUM(AH6) -> 242 | AK6: =SUM(AJ6*$Z$4) -> 2420 | AL6: =SUM(AJ6) -> 242 | AM6: =SUM(AL6*$Z$4) -> 2420 | AN6: =SUM(AO6/19600) -> 0.86428571 | AO6: =SUM(AA6+AC6+AE6+AG6+AI6+AK6+AM6) -> 16940 | AQ6: =SUM(AR6/92970) -> 0.78554962 | AR6: =SUM(AO6+Y6) -> 73032.548 | AS6: =SUM(AR6-AR5-AT6) -> -1698.0581 | AV6: =IF(AT6>0,AU6,AV5) -> 0.5835 | AW6: =-SUM('B5'!AI5) -> -530 | AX6: =-SUM(AW6-AS6) -> -1168.0581 | AY6: =SUM(AX6+AW6) -> -1698.0581 | AZ6: =ELEC!A3 -> 0.1478 | BA6: ='General information '!D6 -> 14.5 | BB6: =SUM('General information '!E6) -> 0.56 | BC6: =IF(AR3>=AR6,0,1) -> 0 | BD6: 19222 | BE6: =(305/1185)*ELEC!Q4 -> 497.26582 | BG6: =#REF!-BE6 -> #REF! | BH6: 21
A7: =ELEC!C4 -> 43863 | B7: ='B5'!B6 -> 232 | C7: =B7*$B$4 -> 4991.7419 | D7: =SUM(B7) -> 232 | E7: =D7*$B$4 -> 4991.7419 | F7: =SUM(D7) -> 232 | G7: =F7*$B$4 -> 4991.7419 | H7: =SUM(F7) -> 232 | I7: =H7*$B$4 -> 4991.7419 | J7: =SUM(H7) -> 232 | K7: =J7*$B$4 -> 4991.7419 | L7: =SUM(J7) -> 232 | M7: =L7*$B$4 -> 4991.7419 | N7: =SUM(L7) -> 232 | O7: =N7*$B$4 -> 4991.7419 | P7: =SUM(N7) -> 232 | Q7: =P7*$B$4 -> 4991.7419 | R7: =SUM(P7) -> 232 | S7: =R7*$B$4 -> 4991.7419 | T7: =SUM(R7) -> 232 | U7: =T7*$B$4 -> 4991.7419 | V7: =SUM(T7) -> 232 | W7: =V7*$B$4 -> 4991.7419 | X7: =SUM(Y7/73370) -> 0.7483871 | Y7: =SUM(C7+E7+G7+I7+K7+M7+O7+Q7+S7+U7+W7) -> 54909.161 | Z7: ='B5'!C6 -> 238 | AA7: =SUM(Z7*$Z$4) -> 2380 | AB7: =SUM(Z7) -> 238 | AC7: =SUM(AB7*$Z$4) -> 2380 | AD7: =SUM(AB7) -> 238 | AE7: =SUM(AD7*$Z$4) -> 2380 | AF7: =SUM(AD7) -> 238 | AG7: =SUM(AF7*$Z$4) -> 2380 | AH7: =SUM(AF7) -> 238 | AI7: =SUM(AH7*$Z$4) -> 2380 | AJ7: =SUM(AH7) -> 238 | AK7: =SUM(AJ7*$Z$4) -> 2380 | AL7: =SUM(AJ7) -> 238 | AM7: =SUM(AL7*$Z$4) -> 2380 | AN7: =SUM(AO7/19600) -> 0.85 | AO7: =SUM(AA7+AC7+AE7+AG7+AI7+AK7+AM7) -> 16660 | AQ7: =SUM(AR7/92970) -> 0.7698092 | AR7: =SUM(AO7+Y7) -> 71569.161 | AS7: =SUM(AR7-AR6-AT7) -> -1463.3871 | AV7: =IF(AT7>0,AU7,AV6) -> 0.5835 | AW7: =-SUM('B5'!AI6) -> -606 | AX7: =-SUM(AW7-AS7) -> -857.3871 | AY7: =SUM(AX7+AW7) -> -1463.3871 | AZ7: =ELEC!A4 -> 0.1087 | BA7: ='General information '!D7 -> 14 | BB7: =SUM('General information '!E7) -> 0.6 | BC7: 0 | BD7: 19222 | BE7: =(305/1185)*ELEC!Q5 -> 735.60338 | BG7: =#REF!-BE7 -> #REF! | BH7: 19
A8: =ELEC!C5 -> 43864 | B8: ='B5'!B7 -> 226.4 | C8: =B8*$B$4 -> 4871.2516 | D8: =SUM(B8) -> 226.4 | E8: =D8*$B$4 -> 4871.2516 | F8: =SUM(D8) -> 226.4 | G8: =F8*$B$4 -> 4871.2516 | H8: =SUM(F8) -> 226.4 | I8: =H8*$B$4 -> 4871.2516 | J8: =SUM(H8) -> 226.4 | K8: =J8*$B$4 -> 4871.2516 | L8: =SUM(J8) -> 226.4 | M8: =L8*$B$4 -> 4871.2516 | N8: =SUM(L8) -> 226.4 | O8: =N8*$B$4 -> 4871.2516 | P8: =SUM(N8) -> 226.4 | Q8: =P8*$B$4 -> 4871.2516 | R8: =SUM(P8) -> 226.4 | S8: =R8*$B$4 -> 4871.2516 | T8: =SUM(R8) -> 226.4 | U8: =T8*$B$4 -> 4871.2516 | V8: =SUM(T8) -> 226.4 | W8: =V8*$B$4 -> 4871.2516 | X8: =SUM(Y8/73370) -> 0.73032258 | Y8: =SUM(C8+E8+G8+I8+K8+M8+O8+Q8+S8+U8+W8) -> 53583.768 | Z8: ='B5'!C7 -> 232.2 | AA8: =SUM(Z8*$Z$4) -> 2322 | AB8: =SUM(Z8) -> 232.2 | AC8: =SUM(AB8*$Z$4) -> 2322 | AD8: =SUM(AB8) -> 232.2 | AE8: =SUM(AD8*$Z$4) -> 2322 | AF8: =SUM(AD8) -> 232.2 | AG8: =SUM(AF8*$Z$4) -> 2322 | AH8: =SUM(AF8) -> 232.2 | AI8: =SUM(AH8*$Z$4) -> 2322 | AJ8: =SUM(AH8) -> 232.2 | AK8: =SUM(AJ8*$Z$4) -> 2322 | AL8: =SUM(AJ8) -> 232.2 | AM8: =SUM(AL8*$Z$4) -> 2322 | AN8: =SUM(AO8/19600) -> 0.82928571 | AO8: =SUM(AA8+AC8+AE8+AG8+AI8+AK8+AM8) -> 16254 | AQ8: =SUM(AR8/92970) -> 0.75118606 | AR8: =SUM(AO8+Y8) -> 69837.768 | AS8: =SUM(AR8-AR7-AT8) -> -1731.3935 | AV8: =IF(AT8>0,AU8,AV7) -> 0.5835 | AW8: =-SUM('B5'!AI7) -> -655 | AX8: =-SUM(AW8-AS8) -> -1076.3935 | AY8: =SUM(AX8+AW8) -> -1731.3935 | AZ8: =ELEC!A5 -> 0.1174 | BA8: ='General information '!D8 -> 13 | BB8: =SUM('General information '!E8) -> 0.65 | BC8: =IF(AR7>=AR8,0,1) -> 0 | BD8: 19222 | BE8: =(305/1185)*ELEC!Q6 -> 715.01266 | BG8: =#REF!-BE8 -> #REF! | BH8: 16
A9: =ELEC!C6 -> 43865 | B9: ='B5'!B8 -> 220 | C9: =B9*$B$4 -> 4733.5484 | D9: =SUM(B9) -> 220 | E9: =D9*$B$4 -> 4733.5484 | F9: =SUM(D9) -> 220 | G9: =F9*$B$4 -> 4733.5484 | H9: =SUM(F9) -> 220 | I9: =H9*$B$4 -> 4733.5484 | J9: =SUM(H9) -> 220 | K9: =J9*$B$4 -> 4733.5484 | L9: =SUM(J9) -> 220 | M9: =L9*$B$4 -> 4733.5484 | N9: =SUM(L9) -> 220 | O9: =N9*$B$4 -> 4733.5484 | P9: =SUM(N9) -> 220 | Q9: =P9*$B$4 -> 4733.5484 | R9: =SUM(P9) -> 220 | S9: =R9*$B$4 -> 4733.5484 | T9: =SUM(R9) -> 220 | U9: =T9*$B$4 -> 4733.5484 | V9: =SUM(T9) -> 220 | W9: =V9*$B$4 -> 4733.5484 | X9: =SUM(Y9/73370) -> 0.70967742 | Y9: =SUM(C9+E9+G9+I9+K9+M9+O9+Q9+S9+U9+W9) -> 52069.032 | Z9: ='B5'!C8 -> 226 | AA9: =SUM(Z9*$Z$4) -> 2260 | AB9: =SUM(Z9) -> 226 | AC9: =SUM(AB9*$Z$4) -> 2260 | AD9: =SUM(AB9) -> 226 | AE9: =SUM(AD9*$Z$4) -> 2260 | AF9: =SUM(AD9) -> 226 | AG9: =SUM(AF9*$Z$4) -> 2260 | AH9: =SUM(AF9) -> 226 | AI9: =SUM(AH9*$Z$4) -> 2260 | AJ9: =SUM(AH9) -> 226 | AK9: =SUM(AJ9*$Z$4) -> 2260 | AL9: =SUM(AJ9) -> 226 | AM9: =SUM(AL9*$Z$4) -> 2260 | AN9: =SUM(AO9/19600) -> 0.80714286 | AO9: =SUM(AA9+AC9+AE9+AG9+AI9+AK9+AM9) -> 15820 | AQ9: =SUM(AR9/92970) -> 0.73022515 | AR9: =SUM(AO9+Y9) -> 67889.032 | AS9: =SUM(AR9-AR8-AT9) -> -1948.7355 | AV9: =IF(AT9>0,AU9,AV8) -> 0.5835 | AW9: =-SUM('B5'!AI8) -> -1137.7 | AX9: =-SUM(AW9-AS9) -> -811.03548 | AY9: =SUM(AX9+AW9) -> -1948.7355 | AZ9: =ELEC!A6 -> 0.1174 | BA9: ='General information '!D9 -> 15 | BB9: =SUM('General information '!E9) -> 0.71 | BC9: =IF(AR8>=AR9,0,1) -> 0 | BD9: 19222 | BE9: =(305/1185)*ELEC!Q7 -> 561.35443 | BG9: =#REF!-BE9 -> #REF! | BH9: 18
A10: =ELEC!C7 -> 43866 | B10: ='B5'!B9 -> 214.2 | C10: =B10*$B$4 -> 4608.7548 | D10: =SUM(B10) -> 214.2 | E10: =D10*$B$4 -> 4608.7548 | F10: =SUM(D10) -> 214.2 | G10: =F10*$B$4 -> 4608.7548 | H10: =SUM(F10) -> 214.2 | I10: =H10*$B$4 -> 4608.7548 | J10: =SUM(H10) -> 214.2 | K10: =J10*$B$4 -> 4608.7548 | L10: =SUM(J10) -> 214.2 | M10: =L10*$B$4 -> 4608.7548 | N10: =SUM(L10) -> 214.2 | O10: =N10*$B$4 -> 4608.7548 | P10: =SUM(N10) -> 214.2 | Q10: =P10*$B$4 -> 4608.7548 | R10: =SUM(P10) -> 214.2 | S10: =R10*$B$4 -> 4608.7548 | T10: =SUM(R10) -> 214.2 | U10: =T10*$B$4 -> 4608.7548 | V10: =SUM(T10) -> 214.2 | W10: =V10*$B$4 -> 4608.7548 | X10: =SUM(Y10/73370) -> 0.69096774 | Y10: =SUM(C10+E10+G10+I10+K10+M10+O10+Q10+S10+U10+W10) -> 50696.303 | Z10: ='B5'!C9 -> 220 | AA10: =SUM(Z10*$Z$4) -> 2200 | AB10: =SUM(Z10) -> 220 | AC10: =SUM(AB10*$Z$4) -> 2200 | AD10: =SUM(AB10) -> 220 | AE10: =SUM(AD10*$Z$4) -> 2200 | AF10: =SUM(AD10) -> 220 | AG10: =SUM(AF10*$Z$4) -> 2200 | AH10: =SUM(AF10) -> 220 | AI10: =SUM(AH10*$Z$4) -> 2200 | AJ10: =SUM(AH10) -> 220 | AK10: =SUM(AJ10*$Z$4) -> 2200 | AL10: =SUM(AJ10) -> 220 | AM10: =SUM(AL10*$Z$4) -> 2200 | AN10: =SUM(AO10/19600) -> 0.78571429 | AO10: =SUM(AA10+AC10+AE10+AG10+AI10+AK10+AM10) -> 15400 | AQ10: =SUM(AR10/92970) -> 0.71094227 | AR10: =SUM(AO10+Y10) -> 66096.303 | AS10: =SUM(AR10-AR9-AT10) -> -1792.729 | AV10: =IF(AT10>0,AU10,AV9) -> 0.5835 | AW10: =-SUM('B5'!AI9) -> -617 | AX10: =-SUM(AW10-AS10) -> -1175.729 | AY10: =SUM(AX10+AW10) -> -1792.729 | AZ10: =ELEC!A7 -> 0.1478 | BA10: ='General information '!D10 -> 17.5 | BB10: =SUM('General information '!E10) -> 0.65 | BC10: =IF(AR9>=AR10,0,1) -> 0 | BD10: 19222 | BE10: =(305/1185)*ELEC!Q8 -> 481.5654 | BG10: =#REF!-BE10 -> #REF! | BH10: 16
A11: =ELEC!C8 -> 43867 | B11: ='B5'!B10 -> 210.3 | C11: =B11*$B$4 -> 4524.8419 | D11: =SUM(B11) -> 210.3 | E11: =D11*$B$4 -> 4524.8419 | F11: =SUM(D11) -> 210.3 | G11: =F11*$B$4 -> 4524.8419 | H11: =SUM(F11) -> 210.3 | I11: =H11*$B$4 -> 4524.8419 | J11: =SUM(H11) -> 210.3 | K11: =J11*$B$4 -> 4524.8419 | L11: =SUM(J11) -> 210.3 | M11: =L11*$B$4 -> 4524.8419 | N11: =SUM(L11) -> 210.3 | O11: =N11*$B$4 -> 4524.8419 | P11: =SUM(N11) -> 210.3 | Q11: =P11*$B$4 -> 4524.8419 | R11: =SUM(P11) -> 210.3 | S11: =R11*$B$4 -> 4524.8419 | T11: =SUM(R11) -> 210.3 | U11: =T11*$B$4 -> 4524.8419 | V11: =SUM(T11) -> 210.3 | W11: =V11*$B$4 -> 4524.8419 | X11: =SUM(Y11/73370) -> 0.6783871 | Y11: =SUM(C11+E11+G11+I11+K11+M11+O11+Q11+S11+U11+W11) -> 49773.261 | Z11: ='B5'!C10 -> 216.4 | AA11: =SUM(Z11*$Z$4) -> 2164 | AB11: =SUM(Z11) -> 216.4 | AC11: =SUM(AB11*$Z$4) -> 2164 | AD11: =SUM(AB11) -> 216.4 | AE11: =SUM(AD11*$Z$4) -> 2164 | AF11: =SUM(AD11) -> 216.4 | AG11: =SUM(AF11*$Z$4) -> 2164 | AH11: =SUM(AF11) -> 216.4 | AI11: =SUM(AH11*$Z$4) -> 2164 | AJ11: =SUM(AH11) -> 216.4 | AK11: =SUM(AJ11*$Z$4) -> 2164 | AL11: =SUM(AJ11) -> 216.4 | AM11: =SUM(AL11*$Z$4) -> 2164 | AN11: =SUM(AO11/19600) -> 0.77285714 | AO11: =SUM(AA11+AC11+AE11+AG11+AI11+AK11+AM11) -> 15148 | AQ11: =SUM(AR11/92970) -> 0.69830334 | AR11: =SUM(AO11+Y11) -> 64921.261 | AS11: =SUM(AR11-AR10-AT11) -> -1175.0419 | AV11: =IF(AT11>0,AU11,AV10) -> 0.5835 | AW11: =-SUM('B5'!AI10) -> -453 | AX11: =-SUM(AW11-AS11) -> -722.04194 | AY11: =SUM(AX11+AW11) -> -1175.0419 | AZ11: =ELEC!A8 -> 0.2 | BA11: ='General information '!D11 -> 19 | BB11: =SUM('General information '!E11) -> 0.61 | BC11: =IF(AR10>=AR11,0,1) -> 0 | BD11: 19222 | BE11: =(305/1185)*ELEC!Q9 -> 707.54852 | BG11: =#REF!-BE11 -> #REF! | BH11: 16.5
A12: =ELEC!C9 -> 43868 | B12: ='B5'!B11 -> 252 | C12: =B12*$B$4 -> 5422.0645 | D12: =SUM(B12) -> 252 | E12: =D12*$B$4 -> 5422.0645 | F12: =SUM(D12) -> 252 | G12: =F12*$B$4 -> 5422.0645 | H12: =SUM(F12) -> 252 | I12: =H12*$B$4 -> 5422.0645 | J12: =SUM(H12) -> 252 | K12: =J12*$B$4 -> 5422.0645 | L12: =SUM(J12) -> 252 | M12: =L12*$B$4 -> 5422.0645 | N12: =SUM(L12) -> 252 | O12: =N12*$B$4 -> 5422.0645 | P12: =SUM(N12) -> 252 | Q12: =P12*$B$4 -> 5422.0645 | R12: =SUM(P12) -> 252 | S12: =R12*$B$4 -> 5422.0645 | T12: =SUM(R12) -> 252 | U12: =T12*$B$4 -> 5422.0645 | V12: =SUM(T12) -> 252 | W12: =V12*$B$4 -> 5422.0645 | X12: =SUM(Y12/73370) -> 0.81290323 | Y12: =SUM(C12+E12+G12+I12+K12+M12+O12+Q12+S12+U12+W12) -> 59642.71 | Z12: ='B5'!C11 -> 259 | AA12: =SUM(Z12*$Z$4) -> 2590 | AB12: =SUM(Z12) -> 259 | AC12: =SUM(AB12*$Z$4) -> 2590 | AD12: =SUM(AB12) -> 259 | AE12: =SUM(AD12*$Z$4) -> 2590 | AF12: =SUM(AD12) -> 259 | AG12: =SUM(AF12*$Z$4) -> 2590 | AH12: =SUM(AF12) -> 259 | AI12: =SUM(AH12*$Z$4) -> 2590 | AJ12: =SUM(AH12) -> 259 | AK12: =SUM(AJ12*$Z$4) -> 2590 | AL12: =SUM(AJ12) -> 259 | AM12: =SUM(AL12*$Z$4) -> 2590 | AN12: =SUM(AO12/19600) -> 0.925 | AO12: =SUM(AA12+AC12+AE12+AG12+AI12+AK12+AM12) -> 18130 | AQ12: =SUM(AR12/92970) -> 0.83653555 | AR12: =SUM(AO12+Y12) -> 77772.71 | AS12: =SUM(AR12-AR11-AT12) -> -132.55161 | AT12: 12984 | AU12: 0.54 | AV12: =IF(AT12>0,AU12,AV11) -> 0.54 | AW12: =-SUM('B5'!AI11) -> -906.9 | AX12: =-SUM(AW12-AS12) -> 774.34839 | AY12: =SUM(AX12+AW12) -> -132.55161 | AZ12: =ELEC!A9 -> 0.1957 | BA12: ='General information '!D12 -> 13 | BB12: =SUM('General information '!E12) -> 0.61 | BC12: =IF(AR11>=AR12,0,1) -> 1 | BD12: 19222 | BE12: =(305/1185)*ELEC!Q10 -> 369.86076 | BG12: =#REF!-BE12 -> #REF! | BH12: 15.5
A13: =ELEC!C10 -> 43869 | B13: ='B5'!B12 -> 248 | C13: =B13*$B$4 -> 5336 | D13: =SUM(B13) -> 248 | E13: =D13*$B$4 -> 5336 | F13: =SUM(D13) -> 248 | G13: =F13*$B$4 -> 5336 | H13: =SUM(F13) -> 248 | I13: =H13*$B$4 -> 5336 | J13: =SUM(H13) -> 248 | K13: =J13*$B$4 -> 5336 | L13: =SUM(J13) -> 248 | M13: =L13*$B$4 -> 5336 | N13: =SUM(L13) -> 248 | O13: =N13*$B$4 -> 5336 | P13: =SUM(N13) -> 248 | Q13: =P13*$B$4 -> 5336 | R13: =SUM(P13) -> 248 | S13: =R13*$B$4 -> 5336 | T13: =SUM(R13) -> 248 | U13: =T13*$B$4 -> 5336 | V13: =SUM(T13) -> 248 | W13: =V13*$B$4 -> 5336 | X13: =SUM(Y13/73370) -> 0.8 | Y13: =SUM(C13+E13+G13+I13+K13+M13+O13+Q13+S13+U13+W13) -> 58696 | Z13: ='B5'!C12 -> 253.4 | AA13: =SUM(Z13*$Z$4) -> 2534 | AB13: =SUM(Z13) -> 253.4 | AC13: =SUM(AB13*$Z$4) -> 2534 | AD13: =SUM(AB13) -> 253.4 | AE13: =SUM(AD13*$Z$4) -> 2534 | AF13: =SUM(AD13) -> 253.4 | AG13: =SUM(AF13*$Z$4) -> 2534 | AH13: =SUM(AF13) -> 253.4 | AI13: =SUM(AH13*$Z$4) -> 2534 | AJ13: =SUM(AH13) -> 253.4 | AK13: =SUM(AJ13*$Z$4) -> 2534 | AL13: =SUM(AJ13) -> 253.4 | AM13: =SUM(AL13*$Z$4) -> 2534 | AN13: =SUM(AO13/19600) -> 0.905 | AO13: =SUM(AA13+AC13+AE13+AG13+AI13+AK13+AM13) -> 17738 | AQ13: =SUM(AR13/92970) -> 0.82213617 | AR13: =SUM(AO13+Y13) -> 76434 | AS13: =SUM(AR13-AR12-AT13) -> -1338.7097 | AV13: =IF(AT13>0,AU13,AV12) -> 0.54 | AW13: =-SUM('B5'!AI12) -> -669.8 | AX13: =-SUM(AW13-AS13) -> -668.90968 | AY13: =SUM(AX13+AW13) -> -1338.7097 | AZ13: =ELEC!A10 -> 0.139 | BA13: ='General information '!D13 -> 11.5 | BB13: =SUM('General information '!E13) -> 0.46 | BC13: =IF(AR12>=AR13,0,1) -> 0 | BD13: 19222 | BE13: =(305/1185)*ELEC!Q11 -> 537.93249 | BG13: =#REF!-BE13 -> #REF!
A14: =ELEC!C11 -> 43870 | B14: ='B5'!B13 -> 242 | C14: =B14*$B$4 -> 5206.9032 | D14: =SUM(B14) -> 242 | E14: =D14*$B$4 -> 5206.9032 | F14: =SUM(D14) -> 242 | G14: =F14*$B$4 -> 5206.9032 | H14: =SUM(F14) -> 242 | I14: =H14*$B$4 -> 5206.9032 | J14: =SUM(H14) -> 242 | K14: =J14*$B$4 -> 5206.9032 | L14: =SUM(J14) -> 242 | M14: =L14*$B$4 -> 5206.9032 | N14: =SUM(L14) -> 242 | O14: =N14*$B$4 -> 5206.9032 | P14: =SUM(N14) -> 242 | Q14: =P14*$B$4 -> 5206.9032 | R14: =SUM(P14) -> 242 | S14: =R14*$B$4 -> 5206.9032 | T14: =SUM(R14) -> 242 | U14: =T14*$B$4 -> 5206.9032 | V14: =SUM(T14) -> 242 | W14: =V14*$B$4 -> 5206.9032 | X14: =SUM(Y14/73370) -> 0.78064516 | Y14: =SUM(C14+E14+G14+I14+K14+M14+O14+Q14+S14+U14+W14) -> 57275.935 | Z14: ='B5'!C13 -> 248 | AA14: =SUM(Z14*$Z$4) -> 2480 | AB14: =SUM(Z14) -> 248 | AC14: =SUM(AB14*$Z$4) -> 2480 | AD14: =SUM(AB14) -> 248 | AE14: =SUM(AD14*$Z$4) -> 2480 | AF14: =SUM(AD14) -> 248 | AG14: =SUM(AF14*$Z$4) -> 2480 | AH14: =SUM(AF14) -> 248 | AI14: =SUM(AH14*$Z$4) -> 2480 | AJ14: =SUM(AH14) -> 248 | AK14: =SUM(AJ14*$Z$4) -> 2480 | AL14: =SUM(AJ14) -> 248 | AM14: =SUM(AL14*$Z$4) -> 2480 | AN14: =SUM(AO14/19600) -> 0.88571429 | AO14: =SUM(AA14+AC14+AE14+AG14+AI14+AK14+AM14) -> 17360 | AQ14: =SUM(AR14/92970) -> 0.80279591 | AR14: =SUM(AO14+Y14) -> 74635.935 | AS14: =SUM(AR14-AR13-AT14) -> -1798.0645 | AV14: =IF(AT14>0,AU14,AV13) -> 0.54 | AW14: =-SUM('B5'!AI13) -> -828 | AX14: =-SUM(AW14-AS14) -> -970.06452 | AY14: =SUM(AX14+AW14) -> -1798.0645 | AZ14: =ELEC!A11 -> 0.1522 | BA14: ='General information '!D14 -> 8.5 | BB14: =SUM('General information '!E14) -> 0.52 | BC14: =IF(AR13>=AR14,0,1) -> 0 | BD14: 19222 | BE14: =(305/1185)*ELEC!Q12 -> 409.24051 | BG14: =#REF!-BE14 -> #REF!
A15: =ELEC!C12 -> 43871 | B15: ='B5'!B14 -> 236.1 | C15: =B15*$B$4 -> 5079.9581 | D15: =SUM(B15) -> 236.1 | E15: =D15*$B$4 -> 5079.9581 | F15: =SUM(D15) -> 236.1 | G15: =F15*$B$4 -> 5079.9581 | H15: =SUM(F15) -> 236.1 | I15: =H15*$B$4 -> 5079.9581 | J15: =SUM(H15) -> 236.1 | K15: =J15*$B$4 -> 5079.9581 | L15: =SUM(J15) -> 236.1 | M15: =L15*$B$4 -> 5079.9581 | N15: =SUM(L15) -> 236.1 | O15: =N15*$B$4 -> 5079.9581 | P15: =SUM(N15) -> 236.1 | Q15: =P15*$B$4 -> 5079.9581 | R15: =SUM(P15) -> 236.1 | S15: =R15*$B$4 -> 5079.9581 | T15: =SUM(R15) -> 236.1 | U15: =T15*$B$4 -> 5079.9581 | V15: =SUM(T15) -> 236.1 | W15: =V15*$B$4 -> 5079.9581 | X15: =SUM(Y15/73370) -> 0.7616129 | Y15: =SUM(C15+E15+G15+I15+K15+M15+O15+Q15+S15+U15+W15) -> 55879.539 | Z15: ='B5'!C14 -> 241.4 | AA15: =SUM(Z15*$Z$4) -> 2414 | AB15: =SUM(Z15) -> 241.4 | AC15: =SUM(AB15*$Z$4) -> 2414 | AD15: =SUM(AB15) -> 241.4 | AE15: =SUM(AD15*$Z$4) -> 2414 | AF15: =SUM(AD15) -> 241.4 | AG15: =SUM(AF15*$Z$4) -> 2414 | AH15: =SUM(AF15) -> 241.4 | AI15: =SUM(AH15*$Z$4) -> 2414 | AJ15: =SUM(AH15) -> 241.4 | AK15: =SUM(AJ15*$Z$4) -> 2414 | AL15: =SUM(AJ15) -> 241.4 | AM15: =SUM(AL15*$Z$4) -> 2414 | AN15: =SUM(AO15/19600) -> 0.86214286 | AO15: =SUM(AA15+AC15+AE15+AG15+AI15+AK15+AM15) -> 16898 | AQ15: =SUM(AR15/92970) -> 0.7828067 | AR15: =SUM(AO15+Y15) -> 72777.539 | AS15: =SUM(AR15-AR14-AT15) -> -1858.3968 | AV15: =IF(AT15>0,AU15,AV14) -> 0.54 | AW15: =-SUM('B5'!AI14) -> -1098.6 | AX15: =-SUM(AW15-AS15) -> -759.79677 | AY15: =SUM(AX15+AW15) -> -1858.3968 | AZ15: =ELEC!A12 -> 0.1609 | BA15: ='General information '!D15 -> 8.5 | BB15: =SUM('General information '!E15) -> 0.55 | BC15: =IF(AR14>=AR15,0,1) -> 0 | BD15: 19222 | BE15: =(305/1185)*ELEC!Q13 -> 424.94093 | BG15: =#REF!-BE15 -> #REF!
A16: =ELEC!C13 -> 43872 | B16: ='B5'!B15 -> 230 | C16: =B16*$B$4 -> 4948.7097 | D16: =SUM(B16) -> 230 | E16: =D16*$B$4 -> 4948.7097 | F16: =SUM(D16) -> 230 | G16: =F16*$B$4 -> 4948.7097 | H16: =SUM(F16) -> 230 | I16: =H16*$B$4 -> 4948.7097 | J16: =SUM(H16) -> 230 | K16: =J16*$B$4 -> 4948.7097 | L16: =SUM(J16) -> 230 | M16: =L16*$B$4 -> 4948.7097 | N16: =SUM(L16) -> 230 | O16: =N16*$B$4 -> 4948.7097 | P16: =SUM(N16) -> 230 | Q16: =P16*$B$4 -> 4948.7097 | R16: =SUM(P16) -> 230 | S16: =R16*$B$4 -> 4948.7097 | T16: =SUM(R16) -> 230 | U16: =T16*$B$4 -> 4948.7097 | V16: =SUM(T16) -> 230 | W16: =V16*$B$4 -> 4948.7097 | X16: =SUM(Y16/73370) -> 0.74193548 | Y16: =SUM(C16+E16+G16+I16+K16+M16+O16+Q16+S16+U16+W16) -> 54435.806 | Z16: ='B5'!C15 -> 235.4 | AA16: =SUM(Z16*$Z$4) -> 2354 | AB16: =SUM(Z16) -> 235.4 | AC16: =SUM(AB16*$Z$4) -> 2354 | AD16: =SUM(AB16) -> 235.4 | AE16: =SUM(AD16*$Z$4) -> 2354 | AF16: =SUM(AD16) -> 235.4 | AG16: =SUM(AF16*$Z$4) -> 2354 | AH16: =SUM(AF16) -> 235.4 | AI16: =SUM(AH16*$Z$4) -> 2354 | AJ16: =SUM(AH16) -> 235.4 | AK16: =SUM(AJ16*$Z$4) -> 2354 | AL16: =SUM(AJ16) -> 235.4 | AM16: =SUM(AL16*$Z$4) -> 2354 | AN16: =SUM(AO16/19600) -> 0.84071429 | AO16: =SUM(AA16+AC16+AE16+AG16+AI16+AK16+AM16) -> 16478 | AQ16: =SUM(AR16/92970) -> 0.7627601 | AR16: =SUM(AO16+Y16) -> 70913.806 | AS16: =SUM(AR16-AR15-AT16) -> -1863.7323 | AV16: =IF(AT16>0,AU16,AV15) -> 0.54 | AW16: =-SUM('B5'!AI15) -> -1468.1 | AX16: =-SUM(AW16-AS16) -> -395.63226 | AY16: =SUM(AX16+AW16) -> -1863.7323 | AZ16: =ELEC!A13 -> 0.1478 | BA16: ='General information '!D16 -> 11 | BB16: =SUM('General information '!E16) -> 0.5 | BC16: =IF(AR15>=AR16,0,1) -> 0 | BD16: 19222 | BE16: =(305/1185)*ELEC!Q14 -> 440.12658 | BG16: =#REF!-BE16 -> #REF!
A17: =ELEC!C14 -> 43873 | B17: ='B5'!B16 -> 223 | C17: =B17*$B$4 -> 4798.0968 | D17: =SUM(B17) -> 223 | E17: =D17*$B$4 -> 4798.0968 | F17: =SUM(D17) -> 223 | G17: =F17*$B$4 -> 4798.0968 | H17: =SUM(F17) -> 223 | I17: =H17*$B$4 -> 4798.0968 | J17: =SUM(H17) -> 223 | K17: =J17*$B$4 -> 4798.0968 | L17: =SUM(J17) -> 223 | M17: =L17*$B$4 -> 4798.0968 | N17: =SUM(L17) -> 223 | O17: =N17*$B$4 -> 4798.0968 | P17: =SUM(N17) -> 223 | Q17: =P17*$B$4 -> 4798.0968 | R17: =SUM(P17) -> 223 | S17: =R17*$B$4 -> 4798.0968 | T17: =SUM(R17) -> 223 | U17: =T17*$B$4 -> 4798.0968 | V17: =SUM(T17) -> 223 | W17: =V17*$B$4 -> 4798.0968 | X17: =SUM(Y17/73370) -> 0.71935484 | Y17: =SUM(C17+E17+G17+I17+K17+M17+O17+Q17+S17+U17+W17) -> 52779.065 | Z17: ='B5'!C16 -> 229.5 | AA17: =SUM(Z17*$Z$4) -> 2295 | AB17: =SUM(Z17) -> 229.5 | AC17: =SUM(AB17*$Z$4) -> 2295 | AD17: =SUM(AB17) -> 229.5 | AE17: =SUM(AD17*$Z$4) -> 2295 | AF17: =SUM(AD17) -> 229.5 | AG17: =SUM(AF17*$Z$4) -> 2295 | AH17: =SUM(AF17) -> 229.5 | AI17: =SUM(AH17*$Z$4) -> 2295 | AJ17: =SUM(AH17) -> 229.5 | AK17: =SUM(AJ17*$Z$4) -> 2295 | AL17: =SUM(AJ17) -> 229.5 | AM17: =SUM(AL17*$Z$4) -> 2295 | AN17: =SUM(AO17/19600) -> 0.81964286 | AO17: =SUM(AA17+AC17+AE17+AG17+AI17+AK17+AM17) -> 16065 | AQ17: =SUM(AR17/92970) -> 0.74049763 | AR17: =SUM(AO17+Y17) -> 68844.065 | AS17: =SUM(AR17-AR16-AT17) -> -2069.7419 | AV17: =IF(AT17>0,AU17,AV16) -> 0.54 | AW17: =-SUM('B5'!AI16) -> -880 | AX17: =-SUM(AW17-AS17) -> -1189.7419 | AY17: =SUM(AX17+AW17) -> -2069.7419 | AZ17: =ELEC!A14 -> 0.2043 | BA17: ='General information '!D17 -> 14.5 | BB17: =SUM('General information '!E17) -> 0.6 | BC17: =IF(AR16>=AR17,0,1) -> 0 | BD17: 19222 | BE17: =(305/1185)*ELEC!Q15 -> 543.85232 | BG17: =#REF!-BE17 -> #REF!
A18: =ELEC!C15 -> 43874 | B18: ='B5'!B17 -> 219 | C18: =B18*$B$4 -> 4712.0323 | D18: =SUM(B18) -> 219 | E18: =D18*$B$4 -> 4712.0323 | F18: =SUM(D18) -> 219 | G18: =F18*$B$4 -> 4712.0323 | H18: =SUM(F18) -> 219 | I18: =H18*$B$4 -> 4712.0323 | J18: =SUM(H18) -> 219 | K18: =J18*$B$4 -> 4712.0323 | L18: =SUM(J18) -> 219 | M18: =L18*$B$4 -> 4712.0323 | N18: =SUM(L18) -> 219 | O18: =N18*$B$4 -> 4712.0323 | P18: =SUM(N18) -> 219 | Q18: =P18*$B$4 -> 4712.0323 | R18: =SUM(P18) -> 219 | S18: =R18*$B$4 -> 4712.0323 | T18: =SUM(R18) -> 219 | U18: =T18*$B$4 -> 4712.0323 | V18: =SUM(T18) -> 219 | W18: =V18*$B$4 -> 4712.0323 | X18: =SUM(Y18/73370) -> 0.70645161 | Y18: =SUM(C18+E18+G18+I18+K18+M18+O18+Q18+S18+U18+W18) -> 51832.355 | Z18: ='B5'!C17 -> 225 | AA18: =SUM(Z18*$Z$4) -> 2250 | AB18: =SUM(Z18) -> 225 | AC18: =SUM(AB18*$Z$4) -> 2250 | AD18: =SUM(AB18) -> 225 | AE18: =SUM(AD18*$Z$4) -> 2250 | AF18: =SUM(AD18) -> 225 | AG18: =SUM(AF18*$Z$4) -> 2250 | AH18: =SUM(AF18) -> 225 | AI18: =SUM(AH18*$Z$4) -> 2250 | AJ18: =SUM(AH18) -> 225 | AK18: =SUM(AJ18*$Z$4) -> 2250 | AL18: =SUM(AJ18) -> 225 | AM18: =SUM(AL18*$Z$4) -> 2250 | AN18: =SUM(AO18/19600) -> 0.80357143 | AO18: =SUM(AA18+AC18+AE18+AG18+AI18+AK18+AM18) -> 15750 | AQ18: =SUM(AR18/92970) -> 0.72692648 | AR18: =SUM(AO18+Y18) -> 67582.355 | AS18: =SUM(AR18-AR17-AT18) -> -1261.7097 | AV18: =IF(AT18>0,AU18,AV17) -> 0.54 | AW18: =-SUM('B5'!AI17) -> -735 | AX18: =-SUM(AW18-AS18) -> -526.70968 | AY18: =SUM(AX18+AW18) -> -1261.7097 | AZ18: =ELEC!A15 -> 0.3478 | BA18: ='General information '!D18 -> 15.5 | BB18: =SUM('General information '!E18) -> 0.65 | BC18: =IF(AR17>=AR18,0,1) -> 0 | BD18: 19222 | BE18: =(305/1185)*ELEC!Q16 -> 539.73418 | BG18: =#REF!-BE18 -> #REF!
A19: =ELEC!C16 -> 43875 | B19: ='B5'!B18 -> 213.2 | C19: =B19*$B$4 -> 4587.2387 | D19: =SUM(B19) -> 213.2 | E19: =D19*$B$4 -> 4587.2387 | F19: =SUM(D19) -> 213.2 | G19: =F19*$B$4 -> 4587.2387 | H19: =SUM(F19) -> 213.2 | I19: =H19*$B$4 -> 4587.2387 | J19: =SUM(H19) -> 213.2 | K19: =J19*$B$4 -> 4587.2387 | L19: =SUM(J19) -> 213.2 | M19: =L19*$B$4 -> 4587.2387 | N19: =SUM(L19) -> 213.2 | O19: =N19*$B$4 -> 4587.2387 | P19: =SUM(N19) -> 213.2 | Q19: =P19*$B$4 -> 4587.2387 | R19: =SUM(P19) -> 213.2 | S19: =R19*$B$4 -> 4587.2387 | T19: =SUM(R19) -> 213.2 | U19: =T19*$B$4 -> 4587.2387 | V19: =SUM(T19) -> 213.2 | W19: =V19*$B$4 -> 4587.2387 | X19: =SUM(Y19/73370) -> 0.68774194 | Y19: =SUM(C19+E19+G19+I19+K19+M19+O19+Q19+S19+U19+W19) -> 50459.626 | Z19: ='B5'!C18 -> 219 | AA19: =SUM(Z19*$Z$4) -> 2190 | AB19: =SUM(Z19) -> 219 | AC19: =SUM(AB19*$Z$4) -> 2190 | AD19: =SUM(AB19) -> 219 | AE19: =SUM(AD19*$Z$4) -> 2190 | AF19: =SUM(AD19) -> 219 | AG19: =SUM(AF19*$Z$4) -> 2190 | AH19: =SUM(AF19) -> 219 | AI19: =SUM(AH19*$Z$4) -> 2190 | AJ19: =SUM(AH19) -> 219 | AK19: =SUM(AJ19*$Z$4) -> 2190 | AL19: =SUM(AJ19) -> 219 | AM19: =SUM(AL19*$Z$4) -> 2190 | AN19: =SUM(AO19/19600) -> 0.78214286 | AO19: =SUM(AA19+AC19+AE19+AG19+AI19+AK19+AM19) -> 15330 | AQ19: =SUM(AR19/92970) -> 0.7076436 | AR19: =SUM(AO19+Y19) -> 65789.626 | AS19: =SUM(AR19-AR18-AT19) -> -1792.729 | AV19: =IF(AT19>0,AU19,AV18) -> 0.54 | AW19: =-SUM('B5'!AI18) -> -1187.1 | AX19: =-SUM(AW19-AS19) -> -605.62903 | AY19: =SUM(AX19+AW19) -> -1792.729 | AZ19: =ELEC!A16 -> 0.3826 | BA19: ='General information '!D19 -> 14 | BB19: =SUM('General information '!E19) -> 0.78 | BC19: =IF(AR18>=AR19,0,1) -> 0 | BD19: 19222 | BE19: =(305/1185)*ELEC!Q17 -> 641.91561 | BG19: =#REF!-BE19 -> #REF!
A20: =ELEC!C17 -> 43876 | B20: ='B5'!B19 -> 206.1 | C20: =B20*$B$4 -> 4434.4742 | D20: =SUM(B20) -> 206.1 | E20: =D20*$B$4 -> 4434.4742 | F20: =SUM(D20) -> 206.1 | G20: =F20*$B$4 -> 4434.4742 | H20: =SUM(F20) -> 206.1 | I20: =H20*$B$4 -> 4434.4742 | J20: =SUM(H20) -> 206.1 | K20: =J20*$B$4 -> 4434.4742 | L20: =SUM(J20) -> 206.1 | M20: =L20*$B$4 -> 4434.4742 | N20: =SUM(L20) -> 206.1 | O20: =N20*$B$4 -> 4434.4742 | P20: =SUM(N20) -> 206.1 | Q20: =P20*$B$4 -> 4434.4742 | R20: =SUM(P20) -> 206.1 | S20: =R20*$B$4 -> 4434.4742 | T20: =SUM(R20) -> 206.1 | U20: =T20*$B$4 -> 4434.4742 | V20: =SUM(T20) -> 206.1 | W20: =V20*$B$4 -> 4434.4742 | X20: =SUM(Y20/73370) -> 0.66483871 | Y20: =SUM(C20+E20+G20+I20+K20+M20+O20+Q20+S20+U20+W20) -> 48779.216 | Z20: ='B5'!C19 -> 212 | AA20: =SUM(Z20*$Z$4) -> 2120 | AB20: =SUM(Z20) -> 212 | AC20: =SUM(AB20*$Z$4) -> 2120 | AD20: =SUM(AB20) -> 212 | AE20: =SUM(AD20*$Z$4) -> 2120 | AF20: =SUM(AD20) -> 212 | AG20: =SUM(AF20*$Z$4) -> 2120 | AH20: =SUM(AF20) -> 212 | AI20: =SUM(AH20*$Z$4) -> 2120 | AJ20: =SUM(AH20) -> 212 | AK20: =SUM(AJ20*$Z$4) -> 2120 | AL20: =SUM(AJ20) -> 212 | AM20: =SUM(AL20*$Z$4) -> 2120 | AN20: =SUM(AO20/19600) -> 0.75714286 | AO20: =SUM(AA20+AC20+AE20+AG20+AI20+AK20+AM20) -> 14840 | AQ20: =SUM(AR20/92970) -> 0.68429833 | AR20: =SUM(AO20+Y20) -> 63619.216 | AS20: =SUM(AR20-AR19-AT20) -> -2170.4097 | AV20: =IF(AT20>0,AU20,AV19) -> 0.54 | AW20: =-SUM('B5'!AI19) -> -746 | AX20: =-SUM(AW20-AS20) -> -1424.4097 | AY20: =SUM(AX20+AW20) -> -2170.4097 | AZ20: =ELEC!A17 -> 0.247 | BA20: ='General information '!D20 -> 14.5 | BB20: =SUM('General information '!E20) -> 0.59 | BC20: =IF(AR19>=AR20,0,1) -> 0 | BD20: 19222 | BE20: =(305/1185)*ELEC!Q18 -> 225.21097 | BG20: =#REF!-BE20 -> #REF!
A21: =ELEC!C18 -> 43877 | B21: ='B5'!B20 -> 202.3 | C21: =B21*$B$4 -> 4352.7129 | D21: =SUM(B21) -> 202.3 | E21: =D21*$B$4 -> 4352.7129 | F21: =SUM(D21) -> 202.3 | G21: =F21*$B$4 -> 4352.7129 | H21: =SUM(F21) -> 202.3 | I21: =H21*$B$4 -> 4352.7129 | J21: =SUM(H21) -> 202.3 | K21: =J21*$B$4 -> 4352.7129 | L21: =SUM(J21) -> 202.3 | M21: =L21*$B$4 -> 4352.7129 | N21: =SUM(L21) -> 202.3 | O21: =N21*$B$4 -> 4352.7129 | P21: =SUM(N21) -> 202.3 | Q21: =P21*$B$4 -> 4352.7129 | R21: =SUM(P21) -> 202.3 | S21: =R21*$B$4 -> 4352.7129 | T21: =SUM(R21) -> 202.3 | U21: =T21*$B$4 -> 4352.7129 | V21: =SUM(T21) -> 202.3 | W21: =V21*$B$4 -> 4352.7129 | X21: =SUM(Y21/73370) -> 0.65258065 | Y21: =SUM(C21+E21+G21+I21+K21+M21+O21+Q21+S21+U21+W21) -> 47879.842 | Z21: ='B5'!C20 -> 208.1 | AA21: =SUM(Z21*$Z$4) -> 2081 | AB21: =SUM(Z21) -> 208.1 | AC21: =SUM(AB21*$Z$4) -> 2081 | AD21: =SUM(AB21) -> 208.1 | AE21: =SUM(AD21*$Z$4) -> 2081 | AF21: =SUM(AD21) -> 208.1 | AG21: =SUM(AF21*$Z$4) -> 2081 | AH21: =SUM(AF21) -> 208.1 | AI21: =SUM(AH21*$Z$4) -> 2081 | AJ21: =SUM(AH21) -> 208.1 | AK21: =SUM(AJ21*$Z$4) -> 2081 | AL21: =SUM(AJ21) -> 208.1 | AM21: =SUM(AL21*$Z$4) -> 2081 | AN21: =SUM(AO21/19600) -> 0.74321429 | AO21: =SUM(AA21+AC21+AE21+AG21+AI21+AK21+AM21) -> 14567 | AQ21: =SUM(AR21/92970) -> 0.67168809 | AR21: =SUM(AO21+Y21) -> 62446.842 | AS21: =SUM(AR21-AR20-AT21) -> -1172.3742 | AV21: =IF(AT21>0,AU21,AV20) -> 0.54 | AW21: =-SUM('B5'!AI20) -> -644 | AX21: =-SUM(AW21-AS21) -> -528.37419 | AY21: =SUM(AX21+AW21) -> -1172.3742 | AZ21: =ELEC!A18 -> 0.1696 | BA21: ='General information '!D21 -> 14 | BB21: =SUM('General information '!E21) -> 0.58 | BC21: =IF(AR20>=AR21,0,1) -> 0 | BD21: 19222 | BE21: =(305/1185)*ELEC!Q19 -> 571.13502 | BG21: =#REF!-BE21 -> #REF!
A22: =ELEC!C19 -> 43878 | B22: ='B5'!B21 -> 198 | C22: =B22*$B$4 -> 4260.1935 | D22: =SUM(B22) -> 198 | E22: =D22*$B$4 -> 4260.1935 | F22: =SUM(D22) -> 198 | G22: =F22*$B$4 -> 4260.1935 | H22: =SUM(F22) -> 198 | I22: =H22*$B$4 -> 4260.1935 | J22: =SUM(H22) -> 198 | K22: =J22*$B$4 -> 4260.1935 | L22: =SUM(J22) -> 198 | M22: =L22*$B$4 -> 4260.1935 | N22: =SUM(L22) -> 198 | O22: =N22*$B$4 -> 4260.1935 | P22: =SUM(N22) -> 198 | Q22: =P22*$B$4 -> 4260.1935 | R22: =SUM(P22) -> 198 | S22: =R22*$B$4 -> 4260.1935 | T22: =SUM(R22) -> 198 | U22: =T22*$B$4 -> 4260.1935 | V22: =SUM(T22) -> 198 | W22: =V22*$B$4 -> 4260.1935 | X22: =SUM(Y22/73370) -> 0.63870968 | Y22: =SUM(C22+E22+G22+I22+K22+M22+O22+Q22+S22+U22+W22) -> 46862.129 | Z22: ='B5'!C21 -> 203.3 | AA22: =SUM(Z22*$Z$4) -> 2033 | AB22: =SUM(Z22) -> 203.3 | AC22: =SUM(AB22*$Z$4) -> 2033 | AD22: =SUM(AB22) -> 203.3 | AE22: =SUM(AD22*$Z$4) -> 2033 | AF22: =SUM(AD22) -> 203.3 | AG22: =SUM(AF22*$Z$4) -> 2033 | AH22: =SUM(AF22) -> 203.3 | AI22: =SUM(AH22*$Z$4) -> 2033 | AJ22: =SUM(AH22) -> 203.3 | AK22: =SUM(AJ22*$Z$4) -> 2033 | AL22: =SUM(AJ22) -> 203.3 | AM22: =SUM(AL22*$Z$4) -> 2033 | AN22: =SUM(AO22/19600) -> 0.72607143 | AO22: =SUM(AA22+AC22+AE22+AG22+AI22+AK22+AM22) -> 14231 | AQ22: =SUM(AR22/92970) -> 0.65712734 | AR22: =SUM(AO22+Y22) -> 61093.129 | AS22: =SUM(AR22-AR21-AT22) -> -1353.7129 | AV22: =IF(AT22>0,AU22,AV21) -> 0.54 | AW22: =-SUM('B5'!AI21) -> -630 | AX22: =-SUM(AW22-AS22) -> -723.7129 | AY22: =SUM(AX22+AW22) -> -1353.7129 | AZ22: =ELEC!A19 -> 0.2304 | BA22: ='General information '!D22 -> 14 | BB22: =SUM('General information '!E22) -> 0.6 | BC22: =IF(AR21>=AR22,0,1) -> 0 | BD22: 19222 | BE22: =(305/1185)*ELEC!Q20 -> 582.45992 | BG22: =#REF!-BE22 -> #REF!
A23: =ELEC!C20 -> 43879 | B23: ='B5'!B22 -> 251.2 | C23: =B23*$B$4 -> 5404.8516 | D23: =SUM(B23) -> 251.2 | E23: =D23*$B$4 -> 5404.8516 | F23: =SUM(D23) -> 251.2 | G23: =F23*$B$4 -> 5404.8516 | H23: =SUM(F23) -> 251.2 | I23: =H23*$B$4 -> 5404.8516 | J23: =SUM(H23) -> 251.2 | K23: =J23*$B$4 -> 5404.8516 | L23: =SUM(J23) -> 251.2 | M23: =L23*$B$4 -> 5404.8516 | N23: =SUM(L23) -> 251.2 | O23: =N23*$B$4 -> 5404.8516 | P23: =SUM(N23) -> 251.2 | Q23: =P23*$B$4 -> 5404.8516 | R23: =SUM(P23) -> 251.2 | S23: =R23*$B$4 -> 5404.8516 | T23: =SUM(R23) -> 251.2 | U23: =T23*$B$4 -> 5404.8516 | V23: =SUM(T23) -> 251.2 | W23: =V23*$B$4 -> 5404.8516 | X23: =SUM(Y23/73370) -> 0.81032258 | Y23: =SUM(C23+E23+G23+I23+K23+M23+O23+Q23+S23+U23+W23) -> 59453.368 | Z23: ='B5'!C22 -> 256.4 | AA23: =SUM(Z23*$Z$4) -> 2564 | AB23: =SUM(Z23) -> 256.4 | AC23: =SUM(AB23*$Z$4) -> 2564 | AD23: =SUM(AB23) -> 256.4 | AE23: =SUM(AD23*$Z$4) -> 2564 | AF23: =SUM(AD23) -> 256.4 | AG23: =SUM(AF23*$Z$4) -> 2564 | AH23: =SUM(AF23) -> 256.4 | AI23: =SUM(AH23*$Z$4) -> 2564 | AJ23: =SUM(AH23) -> 256.4 | AK23: =SUM(AJ23*$Z$4) -> 2564 | AL23: =SUM(AJ23) -> 256.4 | AM23: =SUM(AL23*$Z$4) -> 2564 | AN23: =SUM(AO23/19600) -> 0.91571429 | AO23: =SUM(AA23+AC23+AE23+AG23+AI23+AK23+AM23) -> 17948 | AQ23: =SUM(AR23/92970) -> 0.83254133 | AR23: =SUM(AO23+Y23) -> 77401.368 | AS23: =SUM(AR23-AR22-AT23) -> 425.23871 | AT23: 15883 | AU23: 0.5165 | AV23: =IF(AT23>0,AU23,AV22) -> 0.5165 | AW23: =-SUM('B5'!AI22) -> -1122 | AX23: =-SUM(AW23-AS23) -> 1547.2387 | AY23: =SUM(AX23+AW23) -> 425.23871 | AZ23: =ELEC!A20 -> 0.2348 | BA23: ='General information '!D23 -> 14 | BB23: =SUM('General information '!E23) -> 0.62 | BC23: =IF(AR22>=AR23,0,1) -> 1 | BD23: 19222 | BE23: =(305/1185)*ELEC!Q21 -> 672.5443 | BG23: =#REF!-BE23 -> #REF!
A24: =ELEC!C21 -> 43880 | B24: ='B5'!B23 -> 245 | C24: =B24*$B$4 -> 5271.4516 | D24: =SUM(B24) -> 245 | E24: =D24*$B$4 -> 5271.4516 | F24: =SUM(D24) -> 245 | G24: =F24*$B$4 -> 5271.4516 | H24: =SUM(F24) -> 245 | I24: =H24*$B$4 -> 5271.4516 | J24: =SUM(H24) -> 245 | K24: =J24*$B$4 -> 5271.4516 | L24: =SUM(J24) -> 245 | M24: =L24*$B$4 -> 5271.4516 | N24: =SUM(L24) -> 245 | O24: =N24*$B$4 -> 5271.4516 | P24: =SUM(N24) -> 245 | Q24: =P24*$B$4 -> 5271.4516 | R24: =SUM(P24) -> 245 | S24: =R24*$B$4 -> 5271.4516 | T24: =SUM(R24) -> 245 | U24: =T24*$B$4 -> 5271.4516 | V24: =SUM(T24) -> 245 | W24: =V24*$B$4 -> 5271.4516 | X24: =SUM(Y24/73370) -> 0.79032258 | Y24: =SUM(C24+E24+G24+I24+K24+M24+O24+Q24+S24+U24+W24) -> 57985.968 | Z24: ='B5'!C23 -> 249.4 | AA24: =SUM(Z24*$Z$4) -> 2494 | AB24: =SUM(Z24) -> 249.4 | AC24: =SUM(AB24*$Z$4) -> 2494 | AD24: =SUM(AB24) -> 249.4 | AE24: =SUM(AD24*$Z$4) -> 2494 | AF24: =SUM(AD24) -> 249.4 | AG24: =SUM(AF24*$Z$4) -> 2494 | AH24: =SUM(AF24) -> 249.4 | AI24: =SUM(AH24*$Z$4) -> 2494 | AJ24: =SUM(AH24) -> 249.4 | AK24: =SUM(AJ24*$Z$4) -> 2494 | AL24: =SUM(AJ24) -> 249.4 | AM24: =SUM(AL24*$Z$4) -> 2494 | AN24: =SUM(AO24/19600) -> 0.89071429 | AO24: =SUM(AA24+AC24+AE24+AG24+AI24+AK24+AM24) -> 17458 | AQ24: =SUM(AR24/92970) -> 0.81148723 | AR24: =SUM(AO24+Y24) -> 75443.968 | AS24: =SUM(AR24-AR23-AT24) -> -1957.4 | AV24: =IF(AT24>0,AU24,AV23) -> 0.5165 | AW24: =-SUM('B5'!AI23) -> -499 | AX24: =-SUM(AW24-AS24) -> -1458.4 | AY24: =SUM(AX24+AW24) -> -1957.4 | AZ24: =ELEC!A21 -> 0.2304 | BA24: ='General information '!D24 -> 15.5 | BB24: =SUM('General information '!E24) -> 0.6 | BC24: =IF(AR23>=AR24,0,1) -> 0 | BD24: 19222 | BE24: =(305/1185)*ELEC!Q22 -> 523.77637 | BG24: =#REF!-BE24 -> #REF!
A25: =ELEC!C22 -> 43881 | B25: ='B5'!B24 -> 241 | C25: =B25*$B$4 -> 5185.3871 | D25: =SUM(B25) -> 241 | E25: =D25*$B$4 -> 5185.3871 | F25: =SUM(D25) -> 241 | G25: =F25*$B$4 -> 5185.3871 | H25: =SUM(F25) -> 241 | I25: =H25*$B$4 -> 5185.3871 | J25: =SUM(H25) -> 241 | K25: =J25*$B$4 -> 5185.3871 | L25: =SUM(J25) -> 241 | M25: =L25*$B$4 -> 5185.3871 | N25: =SUM(L25) -> 241 | O25: =N25*$B$4 -> 5185.3871 | P25: =SUM(N25) -> 241 | Q25: =P25*$B$4 -> 5185.3871 | R25: =SUM(P25) -> 241 | S25: =R25*$B$4 -> 5185.3871 | T25: =SUM(R25) -> 241 | U25: =T25*$B$4 -> 5185.3871 | V25: =SUM(T25) -> 241 | W25: =V25*$B$4 -> 5185.3871 | X25: =SUM(Y25/73370) -> 0.77741935 | Y25: =SUM(C25+E25+G25+I25+K25+M25+O25+Q25+S25+U25+W25) -> 57039.258 | Z25: ='B5'!C24 -> 246.5 | AA25: =SUM(Z25*$Z$4) -> 2465 | AB25: =SUM(Z25) -> 246.5 | AC25: =SUM(AB25*$Z$4) -> 2465 | AD25: =SUM(AB25) -> 246.5 | AE25: =SUM(AD25*$Z$4) -> 2465 | AF25: =SUM(AD25) -> 246.5 | AG25: =SUM(AF25*$Z$4) -> 2465 | AH25: =SUM(AF25) -> 246.5 | AI25: =SUM(AH25*$Z$4) -> 2465 | AJ25: =SUM(AH25) -> 246.5 | AK25: =SUM(AJ25*$Z$4) -> 2465 | AL25: =SUM(AJ25) -> 246.5 | AM25: =SUM(AL25*$Z$4) -> 2465 | AN25: =SUM(AO25/19600) -> 0.88035714 | AO25: =SUM(AA25+AC25+AE25+AG25+AI25+AK25+AM25) -> 17255 | AQ25: =SUM(AR25/92970) -> 0.79912077 | AR25: =SUM(AO25+Y25) -> 74294.258 | AS25: =SUM(AR25-AR24-AT25) -> -1149.7097 | AV25: =IF(AT25>0,AU25,AV24) -> 0.5165 | AW25: =-SUM('B5'!AI24) -> -541 | AX25: =-SUM(AW25-AS25) -> -608.70968 | AY25: =SUM(AX25+AW25) -> -1149.7097 | AZ25: =ELEC!A22 -> 0.2261 | BA25: ='General information '!D25 -> 15.5 | BB25: =SUM('General information '!E25) -> 0.59 | BC25: =IF(AR24>=AR25,0,1) -> 0 | BD25: 19222 | BE25: =(305/1185)*ELEC!Q23 -> 583.74684 | BG25: =#REF!-BE25 -> #REF!
A26: =ELEC!C23 -> 43882 | B26: ='B5'!B25 -> 237 | C26: =B26*$B$4 -> 5099.3226 | D26: =SUM(B26) -> 237 | E26: =D26*$B$4 -> 5099.3226 | F26: =SUM(D26) -> 237 | G26: =F26*$B$4 -> 5099.3226 | H26: =SUM(F26) -> 237 | I26: =H26*$B$4 -> 5099.3226 | J26: =SUM(H26) -> 237 | K26: =J26*$B$4 -> 5099.3226 | L26: =SUM(J26) -> 237 | M26: =L26*$B$4 -> 5099.3226 | N26: =SUM(L26) -> 237 | O26: =N26*$B$4 -> 5099.3226 | P26: =SUM(N26) -> 237 | Q26: =P26*$B$4 -> 5099.3226 | R26: =SUM(P26) -> 237 | S26: =R26*$B$4 -> 5099.3226 | T26: =SUM(R26) -> 237 | U26: =T26*$B$4 -> 5099.3226 | V26: =SUM(T26) -> 237 | W26: =V26*$B$4 -> 5099.3226 | X26: =SUM(Y26/73370) -> 0.76451613 | Y26: =SUM(C26+E26+G26+I26+K26+M26+O26+Q26+S26+U26+W26) -> 56092.548 | Z26: ='B5'!C25 -> 241 | AA26: =SUM(Z26*$Z$4) -> 2410 | AB26: =SUM(Z26) -> 241 | AC26: =SUM(AB26*$Z$4) -> 2410 | AD26: =SUM(AB26) -> 241 | AE26: =SUM(AD26*$Z$4) -> 2410 | AF26: =SUM(AD26) -> 241 | AG26: =SUM(AF26*$Z$4) -> 2410 | AH26: =SUM(AF26) -> 241 | AI26: =SUM(AH26*$Z$4) -> 2410 | AJ26: =SUM(AH26) -> 241 | AK26: =SUM(AJ26*$Z$4) -> 2410 | AL26: =SUM(AJ26) -> 241 | AM26: =SUM(AL26*$Z$4) -> 2410 | AN26: =SUM(AO26/19600) -> 0.86071429 | AO26: =SUM(AA26+AC26+AE26+AG26+AI26+AK26+AM26) -> 16870 | AQ26: =SUM(AR26/92970) -> 0.78479669 | AR26: =SUM(AO26+Y26) -> 72962.548 | AS26: =SUM(AR26-AR25-AT26) -> -1331.7097 | AV26: =IF(AT26>0,AU26,AV25) -> 0.5165 | AW26: =-SUM('B5'!AI25) -> -1044.3 | AX26: =-SUM(AW26-AS26) -> -287.40968 | AY26: =SUM(AX26+AW26) -> -1331.7097 | AZ26: =ELEC!A23 -> 0.2478 | BA26: ='General information '!D26 -> 14 | BB26: =SUM('General information '!E26) -> 0.82 | BC26: =IF(AR25>=AR26,0,1) -> 0 | BD26: 19222 | BE26: =(305/1185)*ELEC!Q24 -> 685.67089 | BG26: =#REF!-BE26 -> #REF!
A27: =ELEC!C24 -> 43883 | B27: ='B5'!B26 -> 229 | C27: =B27*$B$4 -> 4927.1935 | D27: =SUM(B27) -> 229 | E27: =D27*$B$4 -> 4927.1935 | F27: =SUM(D27) -> 229 | G27: =F27*$B$4 -> 4927.1935 | H27: =SUM(F27) -> 229 | I27: =H27*$B$4 -> 4927.1935 | J27: =SUM(H27) -> 229 | K27: =J27*$B$4 -> 4927.1935 | L27: =SUM(J27) -> 229 | M27: =L27*$B$4 -> 4927.1935 | N27: =SUM(L27) -> 229 | O27: =N27*$B$4 -> 4927.1935 | P27: =SUM(N27) -> 229 | Q27: =P27*$B$4 -> 4927.1935 | R27: =SUM(P27) -> 229 | S27: =R27*$B$4 -> 4927.1935 | T27: =SUM(R27) -> 229 | U27: =T27*$B$4 -> 4927.1935 | V27: =SUM(T27) -> 229 | W27: =V27*$B$4 -> 4927.1935 | X27: =SUM(Y27/73370) -> 0.73870968 | Y27: =SUM(C27+E27+G27+I27+K27+M27+O27+Q27+S27+U27+W27) -> 54199.129 | Z27: ='B5'!C26 -> 234.3 | AA27: =SUM(Z27*$Z$4) -> 2343 | AB27: =SUM(Z27) -> 234.3 | AC27: =SUM(AB27*$Z$4) -> 2343 | AD27: =SUM(AB27) -> 234.3 | AE27: =SUM(AD27*$Z$4) -> 2343 | AF27: =SUM(AD27) -> 234.3 | AG27: =SUM(AF27*$Z$4) -> 2343 | AH27: =SUM(AF27) -> 234.3 | AI27: =SUM(AH27*$Z$4) -> 2343 | AJ27: =SUM(AH27) -> 234.3 | AK27: =SUM(AJ27*$Z$4) -> 2343 | AL27: =SUM(AJ27) -> 234.3 | AM27: =SUM(AL27*$Z$4) -> 2343 | AN27: =SUM(AO27/19600) -> 0.83678571 | AO27: =SUM(AA27+AC27+AE27+AG27+AI27+AK27+AM27) -> 16401 | AQ27: =SUM(AR27/92970) -> 0.75938614 | AR27: =SUM(AO27+Y27) -> 70600.129 | AS27: =SUM(AR27-AR26-AT27) -> -2362.4194 | AV27: =IF(AT27>0,AU27,AV26) -> 0.5165 | AW27: =-SUM('B5'!AI26) -> -748 | AX27: =-SUM(AW27-AS27) -> -1614.4194 | AY27: =SUM(AX27+AW27) -> -2362.4194 | AZ27: =ELEC!A24 -> 0.1826 | BA27: ='General information '!D27 -> 14.5 | BB27: =SUM('General information '!E27) -> 0.65 | BC27: =IF(AR26>=AR27,0,1) -> 0 | BD27: 19222 | BE27: =(305/1185)*ELEC!Q25 -> 989.89873 | BG27: =#REF!-BE27 -> #REF!
A28: =ELEC!C25 -> 43884 | B28: ='B5'!B27 -> 222 | C28: =B28*$B$4 -> 4776.5806 | D28: =SUM(B28) -> 222 | E28: =D28*$B$4 -> 4776.5806 | F28: =SUM(D28) -> 222 | G28: =F28*$B$4 -> 4776.5806 | H28: =SUM(F28) -> 222 | I28: =H28*$B$4 -> 4776.5806 | J28: =SUM(H28) -> 222 | K28: =J28*$B$4 -> 4776.5806 | L28: =SUM(J28) -> 222 | M28: =L28*$B$4 -> 4776.5806 | N28: =SUM(L28) -> 222 | O28: =N28*$B$4 -> 4776.5806 | P28: =SUM(N28) -> 222 | Q28: =P28*$B$4 -> 4776.5806 | R28: =SUM(P28) -> 222 | S28: =R28*$B$4 -> 4776.5806 | T28: =SUM(R28) -> 222 | U28: =T28*$B$4 -> 4776.5806 | V28: =SUM(T28) -> 222 | W28: =V28*$B$4 -> 4776.5806 | X28: =SUM(Y28/73370) -> 0.71612903 | Y28: =SUM(C28+E28+G28+I28+K28+M28+O28+Q28+S28+U28+W28) -> 52542.387 | Z28: ='B5'!C27 -> 228.1 | AA28: =SUM(Z28*$Z$4) -> 2281 | AB28: =SUM(Z28) -> 228.1 | AC28: =SUM(AB28*$Z$4) -> 2281 | AD28: =SUM(AB28) -> 228.1 | AE28: =SUM(AD28*$Z$4) -> 2281 | AF28: =SUM(AD28) -> 228.1 | AG28: =SUM(AF28*$Z$4) -> 2281 | AH28: =SUM(AF28) -> 228.1 | AI28: =SUM(AH28*$Z$4) -> 2281 | AJ28: =SUM(AH28) -> 228.1 | AK28: =SUM(AJ28*$Z$4) -> 2281 | AL28: =SUM(AJ28) -> 228.1 | AM28: =SUM(AL28*$Z$4) -> 2281 | AN28: =SUM(AO28/19600) -> 0.81464286 | AO28: =SUM(AA28+AC28+AE28+AG28+AI28+AK28+AM28) -> 15967 | AQ28: =SUM(AR28/92970) -> 0.73689779 | AR28: =SUM(AO28+Y28) -> 68509.387 | AS28: =SUM(AR28-AR27-AT28) -> -2090.7419 | AV28: =IF(AT28>0,AU28,AV27) -> 0.5165 | AW28: =-SUM('B5'!AI27) -> -677.3 | AX28: =-SUM(AW28-AS28) -> -1413.4419 | AY28: =SUM(AX28+AW28) -> -2090.7419 | AZ28: =ELEC!A25 -> 0.1391 | BA28: ='General information '!D28 -> 15 | BB28: =SUM('General information '!E28) -> 0.66 | BC28: =IF(AR27>=AR28,0,1) -> 0 | BD28: 19222 | BE28: =(305/1185)*ELEC!Q26 -> 0 | BG28: =#REF!-BE28 -> #REF!
A29: =ELEC!C26 -> 43885 | B29: ='B5'!B28 -> 222 | C29: =B29*$B$4 -> 4776.5806 | D29: =SUM(B29) -> 222 | E29: =D29*$B$4 -> 4776.5806 | F29: =SUM(D29) -> 222 | G29: =F29*$B$4 -> 4776.5806 | H29: =SUM(F29) -> 222 | I29: =H29*$B$4 -> 4776.5806 | J29: =SUM(H29) -> 222 | K29: =J29*$B$4 -> 4776.5806 | L29: =SUM(J29) -> 222 | M29: =L29*$B$4 -> 4776.5806 | N29: =SUM(L29) -> 222 | O29: =N29*$B$4 -> 4776.5806 | P29: =SUM(N29) -> 222 | Q29: =P29*$B$4 -> 4776.5806 | R29: =SUM(P29) -> 222 | S29: =R29*$B$4 -> 4776.5806 | T29: =SUM(R29) -> 222 | U29: =T29*$B$4 -> 4776.5806 | V29: =SUM(T29) -> 222 | W29: =V29*$B$4 -> 4776.5806 | X29: =SUM(Y29/73370) -> 0.71612903 | Y29: =SUM(C29+E29+G29+I29+K29+M29+O29+Q29+S29+U29+W29) -> 52542.387 | Z29: ='B5'!C28 -> 228.1 | AA29: =SUM(Z29*$Z$4) -> 2281 | AB29: =SUM(Z29) -> 228.1 | AC29: =SUM(AB29*$Z$4) -> 2281 | AD29: =SUM(AB29) -> 228.1 | AE29: =SUM(AD29*$Z$4) -> 2281 | AF29: =SUM(AD29) -> 228.1 | AG29: =SUM(AF29*$Z$4) -> 2281 | AH29: =SUM(AF29) -> 228.1 | AI29: =SUM(AH29*$Z$4) -> 2281 | AJ29: =SUM(AH29) -> 228.1 | AK29: =SUM(AJ29*$Z$4) -> 2281 | AL29: =SUM(AJ29) -> 228.1 | AM29: =SUM(AL29*$Z$4) -> 2281 | AN29: =SUM(AO29/19600) -> 0.81464286 | AO29: =SUM(AA29+AC29+AE29+AG29+AI29+AK29+AM29) -> 15967 | AQ29: =SUM(AR29/92970) -> 0.73689779 | AR29: =SUM(AO29+Y29) -> 68509.387 | AS29: =SUM(AR29-AR28-AT29) -> 0 | AV29: =IF(AT29>0,AU29,AV28) -> 0.5165 | AW29: =-SUM('B5'!AI28) -> 0 | AX29: =-SUM(AW29-AS29) -> 0 | AY29: =SUM(AX29+AW29) -> 0 | AZ29: =ELEC!A26 -> 0 | BA29: ='General information '!D29 -> 0 | BB29: =SUM('General information '!E29) -> 0 | BC29: =IF(AR28>=AR29,0,1) -> 0 | BD29: 19222 | BE29: =(305/1185)*ELEC!Q27 -> 0 | BG29: =#REF!-BE29 -> #REF!
A30: =ELEC!C27 -> 43886 | B30: ='B5'!B29 -> 222 | C30: =B30*$B$4 -> 4776.5806 | D30: =SUM(B30) -> 222 | E30: =D30*$B$4 -> 4776.5806 | F30: =SUM(D30) -> 222 | G30: =F30*$B$4 -> 4776.5806 | H30: =SUM(F30) -> 222 | I30: =H30*$B$4 -> 4776.5806 | J30: =SUM(H30) -> 222 | K30: =J30*$B$4 -> 4776.5806 | L30: =SUM(J30) -> 222 | M30: =L30*$B$4 -> 4776.5806 | N30: =SUM(L30) -> 222 | O30: =N30*$B$4 -> 4776.5806 | P30: =SUM(N30) -> 222 | Q30: =P30*$B$4 -> 4776.5806 | R30: =SUM(P30) -> 222 | S30: =R30*$B$4 -> 4776.5806 | T30: =SUM(R30) -> 222 | U30: =T30*$B$4 -> 4776.5806 | V30: =SUM(T30) -> 222 | W30: =V30*$B$4 -> 4776.5806 | X30: =SUM(Y30/73370) -> 0.71612903 | Y30: =SUM(C30+E30+G30+I30+K30+M30+O30+Q30+S30+U30+W30) -> 52542.387 | Z30: ='B5'!C29 -> 228.1 | AA30: =SUM(Z30*$Z$4) -> 2281 | AB30: =SUM(Z30) -> 228.1 | AC30: =SUM(AB30*$Z$4) -> 2281 | AD30: =SUM(AB30) -> 228.1 | AE30: =SUM(AD30*$Z$4) -> 2281 | AF30: =SUM(AD30) -> 228.1 | AG30: =SUM(AF30*$Z$4) -> 2281 | AH30: =SUM(AF30) -> 228.1 | AI30: =SUM(AH30*$Z$4) -> 2281 | AJ30: =SUM(AH30) -> 228.1 | AK30: =SUM(AJ30*$Z$4) -> 2281 | AL30: =SUM(AJ30) -> 228.1 | AM30: =SUM(AL30*$Z$4) -> 2281 | AN30: =SUM(AO30/19600) -> 0.81464286 | AO30: =SUM(AA30+AC30+AE30+AG30+AI30+AK30+AM30) -> 15967 | AQ30: =SUM(AR30/92970) -> 0.73689779 | AR30: =SUM(AO30+Y30) -> 68509.387 | AS30: =SUM(AR30-AR29-AT30) -> 0 | AV30: =IF(AT30>0,AU30,AV29) -> 0.5165 | AW30: =-SUM('B5'!AI29) -> 0 | AX30: =-SUM(AW30-AS30) -> 0 | AY30: =SUM(AX30+AW30) -> 0 | AZ30: =ELEC!A27 -> 0 | BA30: ='General information '!D30 -> 0 | BB30: =SUM('General information '!E30) -> 0 | BC30: =IF(AR29>=AR30,0,1) -> 0 | BD30: 19222 | BE30: =(305/1185)*ELEC!Q28 -> 0 | BG30: =#REF!-BE30 -> #REF!
A31: =ELEC!C28 -> 43887 | B31: ='B5'!B30 -> 222 | C31: =B31*$B$4 -> 4776.5806 | D31: =SUM(B31) -> 222 | E31: =D31*$B$4 -> 4776.5806 | F31: =SUM(D31) -> 222 | G31: =F31*$B$4 -> 4776.5806 | H31: =SUM(F31) -> 222 | I31: =H31*$B$4 -> 4776.5806 | J31: =SUM(H31) -> 222 | K31: =J31*$B$4 -> 4776.5806 | L31: =SUM(J31) -> 222 | M31: =L31*$B$4 -> 4776.5806 | N31: =SUM(L31) -> 222 | O31: =N31*$B$4 -> 4776.5806 | P31: =SUM(N31) -> 222 | Q31: =P31*$B$4 -> 4776.5806 | R31: =SUM(P31) -> 222 | S31: =R31*$B$4 -> 4776.5806 | T31: =SUM(R31) -> 222 | U31: =T31*$B$4 -> 4776.5806 | V31: =SUM(T31) -> 222 | W31: =V31*$B$4 -> 4776.5806 | X31: =SUM(Y31/73370) -> 0.71612903 | Y31: =SUM(C31+E31+G31+I31+K31+M31+O31+Q31+S31+U31+W31) -> 52542.387 | Z31: ='B5'!C30 -> 228.1 | AA31: =SUM(Z31*$Z$4) -> 2281 | AB31: =SUM(Z31) -> 228.1 | AC31: =SUM(AB31*$Z$4) -> 2281 | AD31: =SUM(AB31) -> 228.1 | AE31: =SUM(AD31*$Z$4) -> 2281 | AF31: =SUM(AD31) -> 228.1 | AG31: =SUM(AF31*$Z$4) -> 2281 | AH31: =SUM(AF31) -> 228.1 | AI31: =SUM(AH31*$Z$4) -> 2281 | AJ31: =SUM(AH31) -> 228.1 | AK31: =SUM(AJ31*$Z$4) -> 2281 | AL31: =SUM(AJ31) -> 228.1 | AM31: =SUM(AL31*$Z$4) -> 2281 | AN31: =SUM(AO31/19600) -> 0.81464286 | AO31: =SUM(AA31+AC31+AE31+AG31+AI31+AK31+AM31) -> 15967 | AQ31: =SUM(AR31/92970) -> 0.73689779 | AR31: =SUM(AO31+Y31) -> 68509.387 | AS31: =SUM(AR31-AR30-AT31) -> 0 | AV31: =IF(AT31>0,AU31,AV30) -> 0.5165 | AW31: =-SUM('B5'!AI30) -> 0 | AX31: =-SUM(AW31-AS31) -> 0 | AY31: =SUM(AX31+AW31) -> 0 | AZ31: =ELEC!A28 -> 0 | BA31: ='General information '!D31 -> 0 | BB31: =SUM('General information '!E31) -> 0 | BC31: =IF(AR30>=AR31,0,1) -> 0 | BD31: 19222 | BE31: =(305/1185)*ELEC!Q29 -> 0 | BG31: =#REF!-BE31 -> #REF!
A32: =ELEC!C29 -> 43888 | B32: ='B5'!B31 -> 222 | C32: =B32*$B$4 -> 4776.5806 | D32: =SUM(B32) -> 222 | E32: =D32*$B$4 -> 4776.5806 | F32: =SUM(D32) -> 222 | G32: =F32*$B$4 -> 4776.5806 | H32: =SUM(F32) -> 222 | I32: =H32*$B$4 -> 4776.5806 | J32: =SUM(H32) -> 222 | K32: =J32*$B$4 -> 4776.5806 | L32: =SUM(J32) -> 222 | M32: =L32*$B$4 -> 4776.5806 | N32: =SUM(L32) -> 222 | O32: =N32*$B$4 -> 4776.5806 | P32: =SUM(N32) -> 222 | Q32: =P32*$B$4 -> 4776.5806 | R32: =SUM(P32) -> 222 | S32: =R32*$B$4 -> 4776.5806 | T32: =SUM(R32) -> 222 | U32: =T32*$B$4 -> 4776.5806 | V32: =SUM(T32) -> 222 | W32: =V32*$B$4 -> 4776.5806 | X32: =SUM(Y32/73370) -> 0.71612903 | Y32: =SUM(C32+E32+G32+I32+K32+M32+O32+Q32+S32+U32+W32) -> 52542.387 | Z32: ='B5'!C31 -> 228.1 | AA32: =SUM(Z32*$Z$4) -> 2281 | AB32: =SUM(Z32) -> 228.1 | AC32: =SUM(AB32*$Z$4) -> 2281 | AD32: =SUM(AB32) -> 228.1 | AE32: =SUM(AD32*$Z$4) -> 2281 | AF32: =SUM(AD32) -> 228.1 | AG32: =SUM(AF32*$Z$4) -> 2281 | AH32: =SUM(AF32) -> 228.1 | AI32: =SUM(AH32*$Z$4) -> 2281 | AJ32: =SUM(AH32) -> 228.1 | AK32: =SUM(AJ32*$Z$4) -> 2281 | AL32: =SUM(AJ32) -> 228.1 | AM32: =SUM(AL32*$Z$4) -> 2281 | AN32: =SUM(AO32/19600) -> 0.81464286 | AO32: =SUM(AA32+AC32+AE32+AG32+AI32+AK32+AM32) -> 15967 | AQ32: =SUM(AR32/92970) -> 0.73689779 | AR32: =SUM(AO32+Y32) -> 68509.387 | AS32: =SUM(AR32-AR31-AT32) -> 0 | AV32: =IF(AT32>0,AU32,AV31) -> 0.5165 | AW32: =-SUM('B5'!AI31) -> 0 | AX32: =-SUM(AW32-AS32) -> 0 | AY32: =SUM(AX32+AW32) -> 0 | AZ32: =ELEC!A29 -> 0 | BA32: ='General information '!D32 -> 0 | BB32: =SUM('General information '!E32) -> 0 | BC32: =IF(AR31>=AR32,0,1) -> 0 | BD32: 19222 | BE32: =(305/1185)*ELEC!Q30 -> 0 | BG32: =#REF!-BE32 -> #REF!
A33: =ELEC!C30 -> 43889 | B33: ='B5'!B32 -> 222 | C33: =B33*$B$4 -> 4776.5806 | D33: =SUM(B33) -> 222 | E33: =D33*$B$4 -> 4776.5806 | F33: =SUM(D33) -> 222 | G33: =F33*$B$4 -> 4776.5806 | H33: =SUM(F33) -> 222 | I33: =H33*$B$4 -> 4776.5806 | J33: =SUM(H33) -> 222 | K33: =J33*$B$4 -> 4776.5806 | L33: =SUM(J33) -> 222 | M33: =L33*$B$4 -> 4776.5806 | N33: =SUM(L33) -> 222 | O33: =N33*$B$4 -> 4776.5806 | P33: =SUM(N33) -> 222 | Q33: =P33*$B$4 -> 4776.5806 | R33: =SUM(P33) -> 222 | S33: =R33*$B$4 -> 4776.5806 | T33: =SUM(R33) -> 222 | U33: =T33*$B$4 -> 4776.5806 | V33: =SUM(T33) -> 222 | W33: =V33*$B$4 -> 4776.5806 | X33: =SUM(Y33/73370) -> 0.71612903 | Y33: =SUM(C33+E33+G33+I33+K33+M33+O33+Q33+S33+U33+W33) -> 52542.387 | Z33: ='B5'!C32 -> 228.1 | AA33: =SUM(Z33*$Z$4) -> 2281 | AB33: =SUM(Z33) -> 228.1 | AC33: =SUM(AB33*$Z$4) -> 2281 | AD33: =SUM(AB33) -> 228.1 | AE33: =SUM(AD33*$Z$4) -> 2281 | AF33: =SUM(AD33) -> 228.1 | AG33: =SUM(AF33*$Z$4) -> 2281 | AH33: =SUM(AF33) -> 228.1 | AI33: =SUM(AH33*$Z$4) -> 2281 | AJ33: =SUM(AH33) -> 228.1 | AK33: =SUM(AJ33*$Z$4) -> 2281 | AL33: =SUM(AJ33) -> 228.1 | AM33: =SUM(AL33*$Z$4) -> 2281 | AN33: =SUM(AO33/19600) -> 0.81464286 | AO33: =SUM(AA33+AC33+AE33+AG33+AI33+AK33+AM33) -> 15967 | AQ33: =SUM(AR33/92970) -> 0.73689779 | AR33: =SUM(AO33+Y33) -> 68509.387 | AS33: =SUM(AR33-AR32-AT33) -> 0 | AV33: =IF(AT33>0,AU33,AV32) -> 0.5165 | AW33: =-SUM('B5'!AI32) -> 0 | AX33: =-SUM(AW33-AS33) -> 0 | AY33: =SUM(AX33+AW33) -> 0 | AZ33: =ELEC!A30 -> 0 | BA33: ='General information '!D33 -> 0 | BB33: =SUM('General information '!E33) -> 0 | BC33: =IF(AR32>=AR33,0,1) -> 0 | BD33: 19222 | BE33: =(305/1185)*ELEC!Q31 -> 0 | BG33: =#REF!-BE33 -> #REF!
A34: =ELEC!C31 -> 43890 | B34: ='B5'!B33 -> 222 | C34: =B34*$B$4 -> 4776.5806 | D34: =SUM(B34) -> 222 | E34: =D34*$B$4 -> 4776.5806 | F34: =SUM(D34) -> 222 | G34: =F34*$B$4 -> 4776.5806 | H34: =SUM(F34) -> 222 | I34: =H34*$B$4 -> 4776.5806 | J34: =SUM(H34) -> 222 | K34: =J34*$B$4 -> 4776.5806 | L34: =SUM(J34) -> 222 | M34: =L34*$B$4 -> 4776.5806 | N34: =SUM(L34) -> 222 | O34: =N34*$B$4 -> 4776.5806 | P34: =SUM(N34) -> 222 | Q34: =P34*$B$4 -> 4776.5806 | R34: =SUM(P34) -> 222 | S34: =R34*$B$4 -> 4776.5806 | T34: =SUM(R34) -> 222 | U34: =T34*$B$4 -> 4776.5806 | V34: =SUM(T34) -> 222 | W34: =V34*$B$4 -> 4776.5806 | X34: =SUM(Y34/73370) -> 0.71612903 | Y34: =SUM(C34+E34+G34+I34+K34+M34+O34+Q34+S34+U34+W34) -> 52542.387 | Z34: ='B5'!C33 -> 228.1 | AA34: =SUM(Z34*$Z$4) -> 2281 | AB34: =SUM(Z34) -> 228.1 | AC34: =SUM(AB34*$Z$4) -> 2281 | AD34: =SUM(AB34) -> 228.1 | AE34: =SUM(AD34*$Z$4) -> 2281 | AF34: =SUM(AD34) -> 228.1 | AG34: =SUM(AF34*$Z$4) -> 2281 | AH34: =SUM(AF34) -> 228.1 | AI34: =SUM(AH34*$Z$4) -> 2281 | AJ34: =SUM(AH34) -> 228.1 | AK34: =SUM(AJ34*$Z$4) -> 2281 | AL34: =SUM(AJ34) -> 228.1 | AM34: =SUM(AL34*$Z$4) -> 2281 | AN34: =SUM(AO34/19600) -> 0.81464286 | AO34: =SUM(AA34+AC34+AE34+AG34+AI34+AK34+AM34) -> 15967 | AQ34: =SUM(AR34/92970) -> 0.73689779 | AR34: =SUM(AO34+Y34) -> 68509.387 | AS34: =SUM(AR34-AR33-AT34) -> 0 | AV34: =IF(AT34>0,AU34,AV33) -> 0.5165 | AW34: =-SUM('B5'!AI33) -> 0 | AX34: =-SUM(AW34-AS34) -> 0 | AY34: =SUM(AX34+AW34) -> 0 | AZ34: =ELEC!A31 -> 0 | BA34: ='General information '!D34 -> 0 | BB34: =SUM('General information '!E34) -> 0 | BC34: =IF(AR33>=AR34,0,1) -> 0 | BD34: 19222 | BE34: =(305/1185)*ELEC!#REF! -> #REF! | BG34: =#REF!-BE34 -> #REF!
A35: =ELEC!C32 -> 0 | B35: ='B5'!B34 -> 222 | C35: =B35*$B$4 -> 4776.5806 | D35: =SUM(B35) -> 222 | E35: =D35*$B$4 -> 4776.5806 | F35: =SUM(D35) -> 222 | G35: =F35*$B$4 -> 4776.5806 | H35: =SUM(F35) -> 222 | I35: =H35*$B$4 -> 4776.5806 | J35: =SUM(H35) -> 222 | K35: =J35*$B$4 -> 4776.5806 | L35: =SUM(J35) -> 222 | M35: =L35*$B$4 -> 4776.5806 | N35: =SUM(L35) -> 222 | O35: =N35*$B$4 -> 4776.5806 | P35: =SUM(N35) -> 222 | Q35: =P35*$B$4 -> 4776.5806 | R35: =SUM(P35) -> 222 | S35: =R35*$B$4 -> 4776.5806 | T35: =SUM(R35) -> 222 | U35: =T35*$B$4 -> 4776.5806 | V35: =SUM(T35) -> 222 | W35: =V35*$B$4 -> 4776.5806 | X35: =SUM(Y35/73370) -> 0.71612903 | Y35: =SUM(C35+E35+G35+I35+K35+M35+O35+Q35+S35+U35+W35) -> 52542.387 | Z35: ='B5'!C34 -> 228.1 | AA35: =SUM(Z35*$Z$4) -> 2281 | AB35: =SUM(Z35) -> 228.1 | AC35: =SUM(AB35*$Z$4) -> 2281 | AD35: =SUM(AB35) -> 228.1 | AE35: =SUM(AD35*$Z$4) -> 2281 | AF35: =SUM(AD35) -> 228.1 | AG35: =SUM(AF35*$Z$4) -> 2281 | AH35: =SUM(AF35) -> 228.1 | AI35: =SUM(AH35*$Z$4) -> 2281 | AJ35: =SUM(AH35) -> 228.1 | AK35: =SUM(AJ35*$Z$4) -> 2281 | AL35: =SUM(AJ35) -> 228.1 | AM35: =SUM(AL35*$Z$4) -> 2281 | AN35: =SUM(AO35/19600) -> 0.81464286 | AO35: =SUM(AA35+AC35+AE35+AG35+AI35+AK35+AM35) -> 15967 | AQ35: =SUM(AR35/92970) -> 0.73689779 | AR35: =SUM(AO35+Y35) -> 68509.387 | AS35: =SUM(AR35-AR34-AT35) -> 0 | AV35: =IF(AT35>0,AU35,AV34) -> 0.5165 | AW35: =-SUM('B5'!AI34) -> 0 | AX35: =-SUM(AW35-AS35) -> 0 | AY35: =SUM(AX35+AW35) -> 0 | AZ35: =ELEC!A32 -> 0 | BA35: ='General information '!D35 -> 0 | BB35: =SUM('General information '!E35) -> 0 | BC35: =IF(AR34>=AR35,0,1) -> 0 | BD35: 19222 | BE35: =(305/1185)*ELEC!#REF! -> #REF! | BG35: =#REF!-BE35 -> #REF!
A36: =ELEC!C33 -> 0 | B36: ='B5'!B35 -> 222 | C36: =B36*$B$4 -> 4776.5806 | D36: =SUM(B36) -> 222 | E36: =D36*$B$4 -> 4776.5806 | F36: =SUM(D36) -> 222 | G36: =F36*$B$4 -> 4776.5806 | H36: =SUM(F36) -> 222 | I36: =H36*$B$4 -> 4776.5806 | J36: =SUM(H36) -> 222 | K36: =J36*$B$4 -> 4776.5806 | L36: =SUM(J36) -> 222 | M36: =L36*$B$4 -> 4776.5806 | N36: =SUM(L36) -> 222 | O36: =N36*$B$4 -> 4776.5806 | P36: =SUM(N36) -> 222 | Q36: =P36*$B$4 -> 4776.5806 | R36: =SUM(P36) -> 222 | S36: =R36*$B$4 -> 4776.5806 | T36: =SUM(R36) -> 222 | U36: =T36*$B$4 -> 4776.5806 | V36: =SUM(T36) -> 222 | W36: =V36*$B$4 -> 4776.5806 | X36: =SUM(Y36/73370) -> 0.71612903 | Y36: =SUM(C36+E36+G36+I36+K36+M36+O36+Q36+S36+U36+W36) -> 52542.387 | Z36: ='B5'!C35 -> 228.1 | AA36: =SUM(Z36*$Z$4) -> 2281 | AB36: =SUM(Z36) -> 228.1 | AC36: =SUM(AB36*$Z$4) -> 2281 | AD36: =SUM(AB36) -> 228.1 | AE36: =SUM(AD36*$Z$4) -> 2281 | AF36: =SUM(AD36) -> 228.1 | AG36: =SUM(AF36*$Z$4) -> 2281 | AH36: =SUM(AF36) -> 228.1 | AI36: =SUM(AH36*$Z$4) -> 2281 | AJ36: =SUM(AH36) -> 228.1 | AK36: =SUM(AJ36*$Z$4) -> 2281 | AL36: =SUM(AJ36) -> 228.1 | AM36: =SUM(AL36*$Z$4) -> 2281 | AN36: =SUM(AO36/19600) -> 0.81464286 | AO36: =SUM(AA36+AC36+AE36+AG36+AI36+AK36+AM36) -> 15967 | AQ36: =SUM(AR36/92970) -> 0.73689779 | AR36: =SUM(AO36+Y36) -> 68509.387 | AS36: =SUM(AR36-AR35-AT36) -> 0 | AV36: =IF(AT36>0,AU36,AV35) -> 0.5165 | AW36: =-SUM('B5'!AI35) -> 0 | AX36: =-SUM(AW36-AS36) -> 0 | AY36: =SUM(AX36+AW36) -> 0 | AZ36: =ELEC!A33 -> 0 | BA36: ='General information '!D36 -> 0 | BB36: =SUM('General information '!E36) -> 0
AR37: NB delivery | AS37: =COUNT(AT6:AT36) -> 2 | AT37: =SUM(AT6:AT36) -> 28867 | AU37: =SUM(AU6:AU36)/AS37 -> 0.52825 | AX37: =SUM(AX6:AX36) -> -16664.419 | AY37: =SUM(AY6:AY36) -> -35088.219
AT38: =+AT37*AU37 -> 15248.993
AS40: =SUM(AS6:AS36)/'EDl log'!A34 -> -1525.5748

Sheet GEN
B1: GEN1 | C1: RUN HR | D1: Fuel Counter Index | E1: Cons /day | F1: Diesel L/H | H1: next service | I1: ALARM | J1: GEN2 | K1: RUN HR | L1: Fuel Counter Index | M1: Cons /day | N1: Diesel L/H | P1: next service | Q1: ALARM | R1: GEN3 | S1: RUN HR | T1: Fuel Counter Index | U1: Cons /day | V1: Diesel L/H | X1: next service | Y1: ALARM | Z1: RH total | AA1: Gen Con /day | AB1: Total Deisel Cons/day | AC1: H /L | AD1: TOAL KW GEN | AI1: fuel Consuption | AK1: AVG KW/h
A2: =ELEC!C2 -> 31-01-2020 | B2: =[1]GEN!B33 -> 8505 | C2: =[1]GEN!C33 -> 0 | D2: =[1]GEN!D33 -> 123672.5 | E2: =[1]GEN!E33 -> 0 | F2: =[1]GEN!F33 -> 0 | G2: =[1]GEN!G33 -> 0 | H2: =[1]GEN!H33 -> 8497 | I2: =[1]GEN!I33 -> oil change | ... AK2: =[1]GEN!AK33 -> 0
A3: =ELEC!C3 -> 43862 | B3: =B2 -> 8505 | C3: =B3-B2 -> 0 | D3: =D2 -> 123672.5 | E3: =SUM(D3-D2) -> 0 | F3: =IF(C3>0,E3/C3,0) -> 0 | G3: =[3]GEN!G32 -> 0 | H3: =H2 -> 8497 | I3: =IF(B3-H3<=0,"ok","oil change") -> oil change | J3: =J2 -> 10689 | K3: =J3-J2 -> 0 | L3: =L2 -> 237067.1 | M3: =SUM(L3-L2) -> 0 | N3: =IF(K3>0,M3/K3,0) -> 0 | O3: =[3]GEN!O32 -> 0 | P3: =P2 -> 10873 | Q3: =IF(J3-P3<=0,"ok","oil change") -> ok | R3: 10920 | S3: =R3-R2 -> 5 | T3: 184775.9 | U3: =T3-T2 -> 1436.9 | V3: =IF(S3>0,U3/S3,0) -> 287.38 | W3: =[3]GEN!W32 -> 0 | X3: =X2 -> 11169 | Y3: =IF(R3-X3<=0,"ok","oil change") -> ok | Z3: =C3+K3+S3 -> 5 | AA3: =U3+M3+E3 -> 1436.9 | AB3: =V3+N3+F3 -> 287.38 | AC3: =IF(Z3>0,AA3/Z3,0) -> 287.38 | AD3: =ELEC!Q3 -> 2426 | AE3: =SUM(AD3/Z3) -> 485.2 | AF3: =SUM(AE3/1600) -> 0.30325 | AG3: =SUM(360*AF3) -> 109.17 | AH3: =SUM(AC3-AG3) -> 178.21 | AI3: =AD3*AJ3 -> 624.4135 | AJ3: =305/1185 -> 0.25738397 | AK3: =AI3/Z3 -> 124.8827
A4: =ELEC!C4 -> 43863 | B4: 8505 | C4: =B4-B3 -> 0 | D4: 123673 | E4: =SUM(D4-D3) -> 0.5 | F4: =IF(C4>0,E4/C4,0) -> 0 | H4: =H3 -> 8497 | I4: =IF(B4-H4<=0,"ok","oil change") -> oil change | J4: 10689 | K4: =J4-J3 -> 0 | L4: 237067 | M4: =SUM(L4-L3) -> -0.1 | N4: =IF(K4>0,M4/K4,0) -> 0 | P4: =P3 -> 10873 | Q4: =IF(J4-P4<=0,"ok","oil change") -> ok | R4: 10923 | S4: =R4-R3 -> 3 | T4: 185422 | U4: =T4-T3 -> 646.1 | V4: =IF(S4>0,U4/S4,0) -> 215.36667 | X4: =X3 -> 11169 | Y4: =IF(R4-X4<=0,"ok","oil change") -> ok | Z4: =C4+K4+S4 -> 3 | AA4: =U4+M4+E4 -> 646.5 | AB4: =V4+N4+F4 -> 215.36667 | AC4: =IF(Z4>0,AA4/Z4,0) -> 215.5 | AD4: =ELEC!Q4 -> 1932 | AE4: =SUM(AD4/Z4) -> 644 | AF4: =SUM(AE4/1600) -> 0.4025 | AG4: =SUM(360*AF4) -> 144.9 | AH4: =SUM(AC4-AG4) -> 70.6 | AI4: =AD4*AJ4 -> 497.26582 | AJ4: =305/1185 -> 0.25738397 | AK4: =AI4/Z4 -> 165.75527
A5: =ELEC!C5 -> 43864 | B5: 8505 | C5: =B5-B4 -> 0 | D5: 123673 | E5: =SUM(D5-D4) -> 0 | F5: =IF(C5>0,E5/C5,0) -> 0 | H5: 8497 | I5: =IF(B5-H5<=0,"ok","oil change") -> oil change | J5: 10689 | K5: =J5-J4 -> 0 | L5: 237067 | M5: =SUM(L5-L4) -> 0 | N5: =IF(K5>0,M5/K5,0) -> 0 | P5: =P4 -> 10873 | Q5: =IF(J5-P5<=0,"ok","oil change") -> ok | R5: 10929 | S5: =R5-R4 -> 6 | T5: 186761 | U5: =T5-T4 -> 1339 | V5: =IF(S5>0,U5/S5,0) -> 223.16667 | X5: =X4 -> 11169 | Y5: =IF(R5-X5<=0,"ok","oil change") -> ok | Z5: =C5+K5+S5 -> 6 | AA5: =U5+M5+E5 -> 1339 | AB5: =V5+N5+F5 -> 223.16667 | AC5: =IF(Z5>0,AA5/Z5,0) -> 223.16667 | AD5: =ELEC!Q5 -> 2858 | AE5: =SUM(AD5/Z5) -> 476.33333 | AF5: =SUM(AE5/1600) -> 0.29770833 | AG5: =SUM(320*AF5) -> 95.266667 | AH5: =SUM(AC5-AG5) -> 127.9 | AI5: =AD5*AJ5 -> 735.60338 | AJ5: =305/1185 -> 0.25738397 | AK5: =AI5/Z5 -> 122.60056
A6: =ELEC!C6 -> 43865 | B6: =B5 -> 8505 | C6: =B6-B5 -> 0 | D6: =D5 -> 123673 | E6: =SUM(D6-D5) -> 0 | F6: =IF(C6>0,E6/C6,0) -> 0 | H6: =H5 -> 8497 | I6: =IF(B6-H6<=0,"ok","oil change") -> oil change | J6: =J5 -> 10689 | K6: =J6-J5 -> 0 | L6: =L5 -> 237067 | M6: =SUM(L6-L5) -> 0 | N6: =IF(K6>0,M6/K6,0) -> 0 | P6: =P5 -> 10873 | Q6: =IF(J6-P6<=0,"ok","oil change") -> ok | R6: 10934 | S6: =R6-R5 -> 5 | T6: 187849 | U6: =T6-T5 -> 1088 | V6: =IF(S6>0,U6/S6,0) -> 217.6 | X6: =X5 -> 11169 | Y6: =IF(R6-X6<=0,"ok","oil change") -> ok | Z6: =C6+K6+S6 -> 5 | AA6: =U6+M6+E6 -> 1088 | AB6: =V6+N6+F6 -> 217.6 | AC6: =IF(Z6>0,AA6/Z6,0) -> 217.6 | AD6: =ELEC!Q6 -> 2778 | AE6: =SUM(AD6/Z6) -> 555.6 | AF6: =SUM(AE6/1600) -> 0.34725 | AG6: =SUM(320*AF6) -> 111.12 | AH6: =SUM(AC6-AG6) -> 106.48 | AI6: =AD6*AJ6 -> 715.01266 | AJ6: =305/1185 -> 0.25738397 | AK6: =AI6/Z6 -> 143.00253
A7: =ELEC!C7 -> 43866 | B7: 8505 | C7: =B7-B6 -> 0 | D7: 123673 | E7: =SUM(D7-D6) -> 0 | F7: =IF(C7>0,E7/C7,0) -> 0 | H7: =H6 -> 8497 | I7: =IF(B7-H7<=0,"ok","oil change") -> oil change | J7: 10689 | K7: =J7-J6 -> 0 | L7: 237068 | M7: =SUM(L7-L6) -> 1 | N7: =IF(K7>0,M7/K7,0) -> 0 | P7: =P6 -> 10873 | Q7: =IF(J7-P7<=0,"ok","oil change") -> ok | R7: 10937 | S7: =R7-R6 -> 3 | T7: 188444 | U7: =T7-T6 -> 595 | V7: =IF(S7>0,U7/S7,0) -> 198.33333 | X7: =X6 -> 11169 | Y7: =IF(R7-X7<=0,"ok","oil change") -> ok | Z7: =C7+K7+S7 -> 3 | AA7: =U7+M7+E7 -> 596 | AB7: =V7+N7+F7 -> 198.33333 | AC7: =IF(Z7>0,AA7/Z7,0) -> 198.66667 | AD7: =ELEC!Q7 -> 2181 | AE7: =SUM(AD7/Z7) -> 727 | AF7: =SUM(AE7/1600) -> 0.454375 | AH7: =SUM(AC7-AG7) -> #VALUE! | AI7: =AD7*AJ7 -> 561.35443 | AJ7: =305/1185 -> 0.25738397 | AK7: =AI7/Z7 -> 187.11814
A8: =ELEC!C8 -> 43867 | B8: =B7 -> 8505 | C8: =B8-B7 -> 0 | D8: =D7 -> 123673 | E8: =SUM(D8-D7) -> 0 | F8: =IF(C8>0,E8/C8,0) -> 0 | H8: =H7 -> 8497 | I8: =IF(B8-H8<=0,"ok","oil change") -> oil change | J8: =J7 -> 10689 | K8: =J8-J7 -> 0 | L8: =L7 -> 237068 | M8: =SUM(L8-L7) -> 0 | N8: =IF(K8>0,M8/K8,0) -> 0 | P8: =P7 -> 10873 | Q8: =IF(J8-P8<=0,"ok","oil change") -> ok | R8: 10940 | S8: =R8-R7 -> 3 | T8: 189127 | U8: =T8-T7 -> 683 | V8: =IF(S8>0,U8/S8,0) -> 227.66667 | X8: =X7 -> 11169 | Y8: =IF(R8-X8<=0,"ok","oil change") -> ok | Z8: =C8+K8+S8 -> 3 | AA8: =U8+M8+E8 -> 683 | AB8: =V8+N8+F8 -> 227.66667 | AC8: =IF(Z8>0,AA8/Z8,0) -> 227.66667 | AD8: =ELEC!Q8 -> 1871 | AE8: =SUM(AD8/Z8) -> 623.66667 | AF8: =SUM(AE8/1600) -> 0.38979167 | AG8: =SUM(320*AF8) -> 124.73333 | AH8: =SUM(AC8-AG8) -> 102.93333 | AI8: =AD8*AJ8 -> 481.5654 | AJ8: =305/1185 -> 0.25738397 | AK8: =AI8/Z8 -> 160.5218
A9: =ELEC!C9 -> 43868 | B9: =B8 -> 8505 | C9: =B9-B8 -> 0 | D9: =D8 -> 123673 | E9: =SUM(D9-D8) -> 0 | F9: =IF(C9>0,E9/C9,0) -> 0 | H9: =H8 -> 8497 | I9: =IF(B9-H9<=0,"ok","oil change") -> oil change | J9: =J8 -> 10689 | K9: =J9-J8 -> 0 | L9: =L8 -> 237068 | M9: =SUM(L9-L8) -> 0 | N9: =IF(K9>0,M9/K9,0) -> 0 | P9: =P8 -> 10873 | Q9: =IF(J9-P9<=0,"ok","oil change") -> ok | R9: 10945 | S9: =R9-R8 -> 5 | T9: 190428 | U9: =T9-T8 -> 1301 | V9: =IF(S9>0,U9/S9,0) -> 260.2 | X9: =X8 -> 11169 | Y9: =IF(R9-X9<=0,"ok","oil change") -> ok | Z9: =C9+K9+S9 -> 5 | AA9: =U9+M9+E9 -> 1301 | AB9: =V9+N9+F9 -> 260.2 | AC9: =IF(Z9>0,AA9/Z9,0) -> 260.2 | AD9: =ELEC!Q9 -> 2749 | AE9: =SUM(AD9/Z9) -> 549.8 | AF9: =SUM(AE9/1600) -> 0.343625 | AG9: =SUM(320*AF9) -> 109.96 | AH9: =SUM(AC9-AG9) -> 150.24 | AI9: =AD9*AJ9 -> 707.54852 | AJ9: 0.25738397 | AK9: =IF(Z9>0,AI9/Z9,0) -> 141.5097
A10: =ELEC!C10 -> 43869 | B10: =B9 -> 8505 | C10: =B10-B9 -> 0 | D10: =D9 -> 123673 | E10: =SUM(D10-D9) -> 0 | F10: =IF(C10>0,E10/C10,0) -> 0 | H10: =H9 -> 8497 | I10: =IF(B10-H10<=0,"ok","oil change") -> oil change | J10: =J9 -> 10689 | K10: =J10-J9 -> 0 | L10: =L9 -> 237068 | M10: =SUM(L10-L9) -> 0 | N10: =IF(K10>0,M10/K10,0) -> 0 | P10: 10873 | Q10: =IF(J10-P10<=0,"ok","oil change") -> ok | R10: 10948 | S10: =R10-R9 -> 3 | T10: 191262 | U10: =T10-T9 -> 834 | V10: =IF(S10>0,U10/S10,0) -> 278 | X10: =X9 -> 11169 | Y10: =IF(R10-X10<=0,"ok","oil change") -> ok | Z10: =C10+K10+S10 -> 3 | AA10: =U10+M10+E10 -> 834 | AB10: =V10+N10+F10 -> 278 | AC10: =IF(Z10>0,AA10/Z10,0) -> 278 | AD10: =ELEC!Q10 -> 1437 | AE10: =SUM(AD10/Z10) -> 479 | AF10: =SUM(AE10/1600) -> 0.299375 | AG10: =SUM(320*AF10) -> 95.8 | AH10: =SUM(AC10-AG10) -> 182.2 | AI10: =AD10*AJ10 -> 369.86076 | AJ10: =305/1185 -> 0.25738397 | AK10: =IF(Z10>0,AI10/Z10,0) -> 123.28692
A11: =ELEC!C11 -> 43870 | B11: =B10 -> 8505 | C11: =B11-B10 -> 0 | D11: =D10 -> 123673 | E11: =SUM(D11-D10) -> 0 | F11: =IF(C11>0,E11/C11,0) -> 0 | H11: =H10 -> 8497 | I11: =IF(B11-H11<=0,"ok","oil change") -> oil change | J11: =J10 -> 10689 | K11: =J11-J10 -> 0 | L11: =L10 -> 237068 | M11: =SUM(L11-L10) -> 0 | N11: =IF(K11>0,M11/K11,0) -> 0 | P11: =P10 -> 10873 | Q11: =IF(J11-P11<=0,"ok","oil change") -> ok | R11: 10951 | S11: =R11-R10 -> 3 | T11: 191835 | U11: =T11-T10 -> 573 | V11: =IF(S11>0,U11/S11,0) -> 191 | X11: =X10 -> 11169 | Y11: =IF(R11-X11<=0,"ok","oil change") -> ok | Z11: =C11+K11+S11 -> 3 | AA11: =U11+M11+E11 -> 573 | AB11: =V11+N11+F11 -> 191 | AC11: =IF(Z11>0,AA11/Z11,0) -> 191 | AD11: =ELEC!Q11 -> 2090 | AE11: =SUM(AD11/Z11) -> 696.66667 | AF11: =SUM(AE11/1600) -> 0.43541667 | AG11: =SUM(320*AF11) -> 139.33333 | AH11: =SUM(AC11-AG11) -> 51.666667 | AI11: =AD11*AJ11 -> 537.93249 | AJ11: =305/1185 -> 0.25738397 | AK11: =IF(Z11>0,AI11/Z11,0) -> 179.31083
A12: =ELEC!C12 -> 43871 | B12: 8505 | C12: =B12-B11 -> 0 | D12: 123673 | E12: =SUM(D12-D11) -> 0 | F12: =IF(C12>0,E12/C12,0) -> 0 | H12: =H11 -> 8497 | I12: =IF(B12-H12<=0,"ok","oil change") -> oil change | J12: 10689 | K12: =J12-J11 -> 0 | L12: =L11 -> 237068 | M12: =SUM(L12-L11) -> 0 | N12: =IF(K12>0,M12/K12,0) -> 0 | P12: =P11 -> 10873 | Q12: =IF(J12-P12<=0,"ok","oil change") -> ok | R12: 10954.58 | S12: =R12-R11 -> 3.58 | T12: 192680.6 | U12: =T12-T11 -> 845.6 | V12: =IF(S12>0,U12/S12,0) -> 236.20112 | X12: =X11 -> 11169 | Y12: =IF(R12-X12<=0,"ok","oil change") -> ok | Z12: =C12+K12+S12 -> 3.58 | AA12: =U12+M12+E12 -> 845.6 | AB12: =V12+N12+F12 -> 236.20112 | AC12: =IF(Z12>0,AA12/Z12,0) -> 236.20112 | AD12: =ELEC!Q12 -> 1590 | AE12: =SUM(AD12/Z12) -> 444.13408 | AF12: =SUM(AE12/1600) -> 0.2775838 | AG12: =SUM(320*AF12) -> 88.826816 | AH12: =SUM(AC12-AG12) -> 147.3743 | AI12: =AD12*AJ12 -> 409.24051 | AJ12: =305/1185 -> 0.25738397 | AK12: =IF(Z12>0,AI12/Z12,0) -> 114.31299
A13: =ELEC!C13 -> 43872 | B13: 8505 | C13: =B13-B12 -> 0 | D13: 123673.4 | E13: =SUM(D13-D12) -> 0.4 | F13: =IF(C13>0,E13/C13,0) -> 0 | H13: =H12 -> 8497 | I13: =IF(B13-H13<=0,"ok","oil change") -> oil change | J13: 10689.42 | K13: =J13-J12 -> 0.42 | L13: 237068.2 | M13: =SUM(L13-L12) -> 0.2 | N13: =IF(K13>0,M13/K13,0) -> 0.47619048 | P13: =P12 -> 10873 | Q13: =IF(J13-P13<=0,"ok","oil change") -> ok | R13: 10958.04 | S13: =R13-R12 -> 3.46 | T13: 193505 | U13: =T13-T12 -> 824.4 | V13: =IF(S13>0,U13/S13,0) -> 238.2659 | X13: =X12+180 -> 11349 | Y13: =IF(R13-X13<=0,"ok","oil change") -> ok | Z13: =C13+K13+S13 -> 3.88 | AA13: =U13+M13+E13 -> 825 | AB13: =V13+N13+F13 -> 238.74209 | AC13: =IF(Z13>0,AA13/Z13,0) -> 212.62887 | AD13: =ELEC!Q13 -> 1651 | AE13: =SUM(AD13/Z13) -> 425.51546 | AF13: =SUM(AE13/1600) -> 0.26594716 | AG13: =SUM(320*AF13) -> 85.103093 | AH13: =SUM(AC13-AG13) -> 127.52577 | AI13: =AD13*AJ13 -> 424.94093 | AJ13: =305/1185 -> 0.25738397 | AK13: =IF(Z13>0,AI13/Z13,0) -> 109.52086
A14: =ELEC!C14 -> 43873 | B14: =B13 -> 8505 | C14: =B14-B13 -> 0 | D14: =D13 -> 123673.4 | E14: =SUM(D14-D13) -> 0 | F14: =IF(C14>0,E14/C14,0) -> 0 | H14: =H13 -> 8497 | I14: =IF(B14-H14<=0,"ok","oil change") -> oil change | J14: =J13 -> 10689.42 | K14: =J14-J13 -> 0 | L14: =L13 -> 237068.2 | M14: =SUM(L14-L13) -> 0 | N14: =IF(K14>0,M14/K14,0) -> 0 | P14: =P13 -> 10873 | Q14: =IF(J14-P14<=0,"ok","oil change") -> ok | R14: 10961.53 | S14: =R14-R13 -> 3.49 | T14: 194583.1 | U14: =T14-T13 -> 1078.1 | V14: =IF(S14>0,U14/S14,0) -> 308.91117 | X14: =X13 -> 11349 | Y14: =IF(R14-X14<=0,"ok","oil change") -> ok | Z14: =C14+K14+S14 -> 3.49 | AA14: =U14+M14+E14 -> 1078.1 | AB14: =V14+N14+F14 -> 308.91117 | AC14: =IF(Z14>0,AA14/Z14,0) -> 308.91117 | AD14: =ELEC!Q14 -> 1710 | AE14: =SUM(AD14/Z14) -> 489.97135 | AF14: =SUM(AE14/1600) -> 0.30623209 | AG14: =SUM(320*AF14) -> 97.994269 | AH14: =SUM(AC14-AG14) -> 210.91691 | AI14: =AD14*AJ14 -> 440.12658 | AJ14: =305/1185 -> 0.25738397 | AK14: =IF(Z14>0,AI14/Z14,0) -> 126.11077
A15: =ELEC!C15 -> 43874 | B15: 8505.41 | C15: =B15-B14 -> 0.41 | D15: 123673 | E15: =SUM(D15-D14) -> -0.4 | F15: =IF(C15>0,E15/C15,0) -> -0.97560976 | H15: =H14 -> 8497 | I15: =IF(B15-H15<=0,"ok","oil change") -> oil change | J15: 10689.42 | K15: =J15-J14 -> 0 | L15: 237068 | M15: =SUM(L15-L14) -> -0.2 | N15: =IF(K15>0,M15/K15,0) -> 0 | P15: =P14 -> 10873 | Q15: =IF(J15-P15<=0,"ok","oil change") -> ok | R15: 10965 | S15: =R15-R14 -> 3.47 | T15: 195298 | U15: =T15-T14 -> 714.9 | V15: =IF(S15>0,U15/S15,0) -> 206.02305 | X15: =X14 -> 11349 | Y15: =IF(R15-X15<=0,"ok","oil change") -> ok | Z15: =C15+K15+S15 -> 3.88 | AA15: =U15+M15+E15 -> 714.3 | AB15: =V15+N15+F15 -> 205.04744 | AC15: =IF(Z15>0,AA15/Z15,0) -> 184.09794 | AD15: =ELEC!Q15 -> 2113 | AE15: =SUM(AD15/Z15) -> 544.58763 | AF15: =SUM(AE15/1600) -> 0.34036727 | AG15: =SUM(320*AF15) -> 108.91753 | AH15: =SUM(AC15-AG15) -> 75.180412 | AI15: =AD15*AJ15 -> 543.85232 | AJ15: =305/1185 -> 0.25738397 | AK15: =IF(Z15>0,AI15/Z15,0) -> 140.16812
A16: =ELEC!C16 -> 43875 | B16: =B15 -> 8505.41 | C16: =B16-B15 -> 0 | D16: =D15 -> 123673 | E16: =SUM(D16-D15) -> 0 | F16: =IF(C16>0,E16/C16,0) -> 0 | H16: =H15 -> 8497 | I16: =IF(B16-H16<=0,"ok","oil change") -> oil change | J16: =J15 -> 10689.42 | K16: =J16-J15 -> 0 | L16: =L15 -> 237068 | M16: =SUM(L16-L15) -> 0 | N16: =IF(K16>0,M16/K16,0) -> 0 | P16: =P15 -> 10873 | Q16: =IF(J16-P16<=0,"ok","oil change") -> ok | R16: 10968 | S16: =R16-R15 -> 3 | T16: 195896.8 | U16: =T16-T15 -> 598.8 | V16: =IF(S16>0,U16/S16,0) -> 199.6 | X16: =X15 -> 11349 | Y16: =IF(R16-X16<=0,"ok","oil change") -> ok | Z16: =C16+K16+S16 -> 3 | AA16: =U16+M16+E16 -> 598.8 | AB16: =V16+N16+F16 -> 199.6 | AC16: =IF(Z16>0,AA16/Z16,0) -> 199.6 | AD16: =ELEC!Q16 -> 2097 | AE16: =SUM(AD16/Z16) -> 699 | AF16: =SUM(AE16/1600) -> 0.436875 | AG16: =SUM(320*AF16) -> 139.8 | AH16: =SUM(AC16-AG16) -> 59.8 | AI16: =AD16*AJ16 -> 539.73418 | AJ16: =305/1185 -> 0.25738397 | AK16: =IF(Z16>0,AI16/Z16,0) -> 179.91139
A17: =ELEC!C17 -> 43876 | B17: =B16 -> 8505.41 | C17: =B17-B16 -> 0 | D17: =D16 -> 123673 | E17: =SUM(D17-D16) -> 0 | F17: =IF(C17>0,E17/C17,0) -> 0 | H17: =H16 -> 8497 | I17: =IF(B17-H17<=0,"ok","oil change") -> oil change | J17: =J16 -> 10689.42 | K17: =J17-J16 -> 0 | L17: =L16 -> 237068 | M17: =SUM(L17-L16) -> 0 | N17: =IF(K17>0,M17/K17,0) -> 0 | P17: =P16 -> 10873 | Q17: =IF(J17-P17<=0,"ok","oil change") -> ok | R17: 10972.18 | S17: =R17-R16 -> 4.18 | T17: 196777.7 | U17: =T17-T16 -> 880.9 | V17: =IF(S17>0,U17/S17,0) -> 210.74163 | X17: =X16 -> 11349 | Y17: =IF(R17-X17<=0,"ok","oil change") -> ok | Z17: =C17+K17+S17 -> 4.18 | AA17: =U17+M17+E17 -> 880.9 | AB17: =V17+N17+F17 -> 210.74163 | AC17: =IF(Z17>0,AA17/Z17,0) -> 210.74163 | AD17: =ELEC!Q17 -> 2494 | AE17: =SUM(AD17/Z17) -> 596.65072 | AF17: =SUM(AE17/1600) -> 0.3729067 | AG17: =SUM(320*AF17) -> 119.33014 | AH17: =SUM(AC17-AG17) -> 91.411483 | AI17: =AD17*AJ17 -> 641.91561 | AJ17: =305/1185 -> 0.25738397 | AK17: =IF(Z17>0,AI17/Z17,0) -> 153.56833
A18: =ELEC!C18 -> 43877 | B18: =B17 -> 8505.41 | C18: =B18-B17 -> 0 | D18: =D17 -> 123673 | E18: =SUM(D18-D17) -> 0 | F18: =IF(C18>0,E18/C18,0) -> 0 | H18: =H17 -> 8497 | I18: =IF(B18-H18<=0,"ok","oil change") -> oil change | J18: =J17 -> 10689.42 | K18: =J18-J17 -> 0 | L18: =L17 -> 237068 | M18: =SUM(L18-L17) -> 0 | N18: =IF(K18>0,M18/K18,0) -> 0 | P18: =P17 -> 10873 | Q18: =IF(J18-P14<=0,"ok","oil change") -> ok | R18: 10974 | S18: =R18-R17 -> 1.82 | T18: 197351.6 | U18: =T18-T17 -> 573.9 | V18: =IF(S18>0,U18/S18,0) -> 315.32967 | X18: =X17 -> 11349 | Y18: =IF(R18-X18<=0,"ok","oil change") -> ok | Z18: =C18+K18+S18 -> 1.82 | AA18: =U18+M18+E18 -> 573.9 | AB18: =V18+N18+F18 -> 315.32967 | AC18: =IF(Z18>0,AA18/Z18,0) -> 315.32967 | AD18: =ELEC!Q18 -> 875 | AE18: =SUM(AD18/Z18) -> 480.76923 | AF18: =SUM(AE18/1600) -> 0.30048077 | AG18: =SUM(320*AF18) -> 96.153846 | AH18: =SUM(AC18-AG18) -> 219.17582 | AI18: =AD18*AJ18 -> 225.21097 | AJ18: =305/1185 -> 0.25738397 | AK18: =IF(Z18>0,AI18/Z18,0) -> 123.74229
A19: =ELEC!C19 -> 43878 | B19: 8505 | C19: =B19-B18 -> -0.41 | D19: 123673.7 | E19: =SUM(D19-D18) -> 0.7 | F19: =IF(C19>0,E19/C19,0) -> 0 | H19: =H18 -> 8497 | I19: =IF(B19-H19<=0,"ok","oil change") -> oil change | J19: 10689 | K19: 0 | L19: 237068 | M19: =SUM(L19-L18) -> 0 | N19: =IF(K19>0,M19/K19,0) -> 0 | P19: =P18 -> 10873 | Q19: =IF(J19-P19<=0,"ok","oil change") -> ok | R19: 10977 | S19: =R19-R18 -> 3 | T19: 198004.2 | U19: =T19-T18 -> 652.6 | V19: =IF(S19>0,U19/S19,0) -> 217.53333 | X19: =X18 -> 11349 | Y19: =IF(R19-X19<=0,"ok","oil change") -> ok | Z19: =C19+K19+S19 -> 2.59 | AA19: =U19+M19+E19 -> 653.3 | AB19: =V19+N19+F19 -> 217.53333 | AC19: =IF(Z19>0,AA19/Z19,0) -> 252.23938 | AD19: =ELEC!Q19 -> 2219 | AE19: =SUM(AD19/Z19) -> 856.75676 | AF19: =SUM(AE19/1600) -> 0.53547297 | AG19: =SUM(320*AF19) -> 171.35135 | AH19: =SUM(AC19-AG19) -> 80.888031 | AI19: =AD19*AJ19 -> 571.13502 | AJ19: =305/1185 -> 0.25738397 | AK19: =IF(Z19>0,AI19/Z19,0) -> 220.51545
A20: =ELEC!C20 -> 43879 | B20: 8505 | C20: =B20-B19 -> 0 | D20: 123674 | E20: =SUM(D20-D19) -> 0.3 | F20: =IF(C20>0,E20/C20,0) -> 0 | H20: =H19 -> 8497 | I20: =IF(B20-H20<=0,"ok","oil change") -> oil change | J20: 10689 | K20: =J20-J19 -> 0 | L20: 237068 | M20: =SUM(L20-L19) -> 0 | N20: =IF(K20>0,M20/K20,0) -> 0 | P20: =P19 -> 10873 | Q20: =IF(J20-P20<=0,"ok","oil change") -> ok | R20: 10980 | S20: =R20-R19 -> 3 | T20: 198620 | U20: =T20-T19 -> 615.8 | V20: =IF(S20>0,U20/S20,0) -> 205.26667 | X20: =X19 -> 11349 | Y20: =IF(R20-X20<=0,"ok","oil change") -> ok | Z20: =C20+K20+S20 -> 3 | AA20: =U20+M20+E20 -> 616.1 | AB20: =V20+N20+F20 -> 205.26667 | AC20: =IF(Z20>0,AA20/Z20,0) -> 205.36667 | AD20: =ELEC!Q20 -> 2263 | AE20: =SUM(AD20/Z20) -> 754.33333 | AF20: =SUM(AE20/1600) -> 0.47145833 | AG20: =SUM(320*AF20) -> 150.86667 | AH20: =SUM(AC20-AG20) -> 54.5 | AI20: =AD20*AJ20 -> 582.45992 | AJ20: =305/1185 -> 0.25738397 | AK20: =IF(Z20>0,AI20/Z20,0) -> 194.15331
A21: =ELEC!C21 -> 43880 | B21: 8505 | C21: =B21-B20 -> 0 | D21: 123673.9 | E21: =SUM(D21-D20) -> -0.1 | F21: =IF(C21>0,E21/C21,0) -> 0 | H21: =H20 -> 8497 | I21: =IF(B21-H21<=0,"ok","oil change") -> oil change | J21: 10689 | K21: =J21-J20 -> 0 | L21: 237068.7 | M21: =SUM(L21-L20) -> 0.7 | N21: =IF(K21>0,M21/K21,0) -> 0 | P21: =P20 -> 10873 | Q21: =IF(J21-P21<=0,"ok","oil change") -> ok | R21: 10984 | S21: =R21-R20 -> 4 | T21: 199438.6 | U21: =T21-T20 -> 818.6 | V21: =IF(S21>0,U21/S21,0) -> 204.65 | X21: =X20 -> 11349 | Y21: =Y20 -> ok | Z21: =C21+K21+S21 -> 4 | AA21: =U21+M21+E21 -> 819.2 | AB21: =V21+N21+F21 -> 204.65 | AC21: =IF(Z21>0,AA21/Z21,0) -> 204.8 | AD21: =ELEC!Q21 -> 2613 | AE21: =SUM(AD21/Z21) -> 653.25 | AF21: =SUM(AE21/1600) -> 0.40828125 | AG21: =SUM(320*AF21) -> 130.65 | AH21: =SUM(AC21-AG21) -> 74.15 | AI21: =AD21*AJ21 -> 672.5443 | AJ21: =305/1185 -> 0.25738397 | AK21: =IF(Z21>0,AI21/Z21,0) -> 168.13608
A22: =ELEC!C22 -> 43881 | B22: 8505 | C22: =B22-B21 -> 0 | D22: =D21 -> 123673.9 | E22: =SUM(D22-D21) -> 0 | F22: =IF(C22>0,E22/C22,0) -> 0 | H22: =H21 -> 8497 | I22: =IF(B22-H22<=0,"ok","oil change") -> oil change | J22: 10689 | K22: =J22-J21 -> 0 | L22: =L21 -> 237068.7 | M22: =SUM(L22-L21) -> 0 | N22: =IF(K22>0,M22/K22,0) -> 0 | P22: =P21 -> 10873 | Q22: =IF(J22-P22<=0,"ok","oil change") -> ok | R22: 10988 | S22: =R22-R21 -> 4 | T22: 200436.3 | U22: =T22-T21 -> 997.7 | V22: =IF(S22>0,U22/S22,0) -> 249.425 | X22: =X21 -> 11349 | Y22: =IF(R22-X22<=0,"ok","oil change") -> ok | Z22: =C22+K22+S22 -> 4 | AA22: =U22+M22+E22 -> 997.7 | AB22: =V22+N22+F22 -> 249.425 | AC22: =IF(Z22>0,AA22/Z22,0) -> 249.425 | AD22: =ELEC!Q22 -> 2035 | AE22: =SUM(AD22/Z22) -> 508.75 | AF22: =SUM(AE22/1600) -> 0.31796875 | AG22: =SUM(320*AF22) -> 101.75 | AH22: =SUM(AC22-AG22) -> 147.675 | AI22: =AD22*AJ22 -> 523.77637 | AJ22: =305/1185 -> 0.25738397 | AK22: =IF(Z22>0,AI22/Z22,0) -> 130.94409
A23: =ELEC!C23 -> 43882 | B23: =B22 -> 8505 | C23: =B23-B22 -> 0 | D23: =D22 -> 123673.9 | E23: =SUM(D23-D22) -> 0 | F23: =IF(C23>0,E23/C23,0) -> 0 | H23: =H22 -> 8497 | I23: =IF(B23-H23<=0,"ok","oil change") -> oil change | J23: =J22 -> 10689 | K23: =J23-J22 -> 0 | L23: =L22 -> 237068.7 | M23: =SUM(L23-L22) -> 0 | N23: =IF(K23>0,M23/K23,0) -> 0 | P23: =P22 -> 10873 | Q23: =IF(J23-P23<=0,"ok","oil change") -> ok | R23: 10992 | S23: =R23-R22 -> 4 | T23: 201136.8 | U23: =T23-T22 -> 700.5 | V23: =IF(S23>0,U23/S23,0) -> 175.125 | X23: =X22 -> 11349 | Y23: =IF(R23-X23<=0,"ok","oil change") -> ok | Z23: =C23+K23+S23 -> 4 | AA23: =U23+M23+E23 -> 700.5 | AB23: =V23+N23+F23 -> 175.125 | AC23: =IF(Z23>0,AA23/Z23,0) -> 175.125 | AD23: =ELEC!Q23 -> 2268 | AE23: =SUM(AD23/Z23) -> 567 | AF23: =SUM(AE23/1600) -> 0.354375 | AG23: =SUM(320*AF23) -> 113.4 | AH23: =SUM(AC23-AG23) -> 61.725 | AI23: =AD23*AJ23 -> 583.74684 | AJ23: =305/1185 -> 0.25738397 | AK23: =IF(Z23>0,AI23/Z23,0) -> 145.93671
A24: =ELEC!C24 -> 43883 | B24: 8509 | C24: =B24-B23 -> 4 | D24: 124172.8 | E24: =SUM(D24-D23) -> 498.9 | F24: =IF(C24>0,E24/C24,0) -> 124.725 | H24: =H23 -> 8497 | I24: =IF(B24-H24<=0,"ok","oil change") -> oil change | J24: =J23 -> 10689 | K24: =J24-J23 -> 0 | L24: 237069 | M24: =SUM(L24-L23) -> 0.3 | N24: =IF(K24>0,M24/K24,0) -> 0 | P24: =P23 -> 10873 | Q24: =IF(J24-P24<=0,"ok","oil change") -> ok | R24: =R23 -> 10992 | S24: =R24-R23 -> 0 | T24: 201242.5 | U24: =T24-T23 -> 105.7 | V24: =IF(S24>0,U24/S24,0) -> 0 | X24: =X23 -> 11349 | Y24: =IF(R24-X24<=0,"ok","oil change") -> ok | Z24: =C24+K24+S24 -> 4 | AA24: =U24+M24+E24 -> 604.9 | AB24: =V24+N24+F24 -> 124.725 | AC24: =IF(Z24>0,AA24/Z24,0) -> 151.225 | AD24: =ELEC!Q24 -> 2664 | AE24: =SUM(AD24/Z24) -> 666 | AF24: =SUM(AE24/1600) -> 0.41625 | AG24: =SUM(320*AF24) -> 133.2 | AH24: =SUM(AC24-AG24) -> 18.025 | AI24: =AD24*AJ24 -> 685.67089 | AJ24: =305/1185 -> 0.25738397 | AK24: =IF(Z24>0,AI24/Z24,0) -> 171.41772
A25: =ELEC!C25 -> 43884 | B25: 8514 | C25: =B25-B24 -> 5 | D25: 125193 | E25: =SUM(D25-D24) -> 1020.2 | F25: =IF(C25>0,E25/C25,0) -> 204.04 | H25: =H24 -> 8497 | I25: =IF(B25-H25<=0,"ok","oil change") -> oil change | J25: 10689 | K25: =J25-J24 -> 0 | L25: 237069 | M25: =SUM(L25-L24) -> 0 | N25: =IF(K25>0,M25/K25,0) -> 0 | P25: =P24 -> 10873 | Q25: =IF(J25-P25<=0,"ok","oil change") -> ok | R25: 10992 | S25: =R25-R24 -> 0 | T25: 201242.5 | U25: =T25-T24 -> 0 | V25: =IF(S25>0,U25/S25,0) -> 0 | X25: =X24 -> 11349 | Y25: =IF(R25-X25<=0,"ok","oil change") -> ok | Z25: =C25+K25+S25 -> 5 | AA25: =U25+M25+E25 -> 1020.2 | AB25: =V25+N25+F25 -> 204.04 | AC25: =IF(Z25>0,AA25/Z25,0) -> 204.04 | AD25: =ELEC!Q25 -> 3846 | AE25: =SUM(AD25/Z25) -> 769.2 | AF25: =SUM(AE25/1600) -> 0.48075 | AG25: =SUM(320*AF25) -> 153.84 | AH25: =SUM(AC25-AG25) -> 50.2 | AI25: =AD25*AJ25 -> 989.89873 | AJ25: =305/1185 -> 0.25738397 | AK25: =IF(Z25>0,AI25/Z25,0) -> 197.97975
A26: =ELEC!C26 -> 43885 | B26: =B25 -> 8514 | C26: =B26-B25 -> 0 | D26: =D25 -> 125193 | E26: =SUM(D26-D25) -> 0 | F26: =IF(C26>0,E26/C26,0) -> 0 | H26: =H25 -> 8497 | I26: =IF(B26-H26<=0,"ok","oil change") -> oil change | J26: =J25 -> 10689 | K26: =J26-J25 -> 0 | L26: =L25 -> 237069 | M26: =SUM(L26-L25) -> 0 | N26: =IF(K26>0,M26/K26,0) -> 0 | P26: =P25 -> 10873 | Q26: =IF(J26-P26<=0,"ok","oil change") -> ok | R26: =R25 -> 10992 | S26: =R26-R25 -> 0 | T26: =T25 -> 201242.5 | U26: =T26-T25 -> 0 | V26: =IF(S26>0,U26/S26,0) -> 0 | X26: =X25 -> 11349 | Y26: =IF(R26-X26<=0,"ok","oil change") -> ok | Z26: =C26+K26+S26 -> 0 | AA26: =U26+M26+E26 -> 0 | AB26: =V26+N26+F26 -> 0 | AC26: =IF(Z26>0,AA26/Z26,0) -> 0 | AD26: =ELEC!Q26 -> 0 | AE26: =SUM(AD26/Z26) -> #DIV/0! | AF26: =SUM(AE26/1600) -> #DIV/0! | AG26: =SUM(320*AF26) -> #DIV/0! | AH26: =SUM(AC26-AG26) -> #DIV/0! | AI26: =AD26*AJ26 -> 0 | AJ26: =305/1185 -> 0.25738397 | AK26: =IF(Z26>0,AI26/Z26,0) -> 0
A27: =ELEC!C27 -> 43886 | B27: =B26 -> 8514 | C27: =B27-B26 -> 0 | D27: =D26 -> 125193 | E27: =SUM(D27-D26) -> 0 | F27: =IF(C27>0,E27/C27,0) -> 0 | H27: =H26 -> 8497 | I27: =IF(B27-H27<=0,"ok","oil change") -> oil change | J27: =J26 -> 10689 | K27: =J27-J26 -> 0 | L27: =L26 -> 237069 | M27: =SUM(L27-L26) -> 0 | N27: =IF(K27>0,M27/K27,0) -> 0 | P27: =P26 -> 10873 | Q27: =IF(J27-P27<=0,"ok","oil change") -> ok | R27: =R26 -> 10992 | S27: =R27-R26 -> 0 | T27: =T26 -> 201242.5 | U27: =T27-T26 -> 0 | V27: =IF(S27>0,U27/S27,0) -> 0 | X27: =X26 -> 11349 | Y27: =IF(R27-X27<=0,"ok","oil change") -> ok | Z27: =C27+K27+S27 -> 0 | AA27: =U27+M27+E27 -> 0 | AB27: =V27+N27+F27 -> 0 | AC27: =IF(Z27>0,AA27/Z27,0) -> 0 | AD27: =ELEC!Q27 -> 0 | AE27: =SUM(AD27/Z27) -> #DIV/0! | AF27: =SUM(AE27/1600) -> #DIV/0! | AG27: =SUM(320*AF27) -> #DIV/0! | AH27: =SUM(AC27-AG27) -> #DIV/0! | AI27: =AD27*AJ27 -> 0 | AJ27: =305/1185 -> 0.25738397 | AK27: =IF(Z27>0,AI27/Z27,0) -> 0
