Workbook

Sheet Total
A1: Site Name | B1: Day | C1: Month | D1: Year | E1: Total Electricity Kwh | F1: Electricity Tariff ($/Kwh) | G1: Total Fuel Oil (Liters) | H1: Fuel Oil $/Liter | I1: LPG (Kg) | J1: LPG $/Kg | K1: Water Utility Supply (m3) m3 | L1: Water Utility Supply (m3) $/m3 | M1: Irrigation Water (m3) m3 | N1: Irrigation water $/m3 | O1: Room Nights
A2: Beirut | B2: 1 | C2: 3 | D2: 2020 | E2: =ELEC!N3 -> 10658 | F2: =SUM('EDl log'!T4) -> 0.048038828 | G2: =-tanks!AW6 -> 580 | H2: =SUM(tanks!AV6) -> 0.1 | I2: =('B5'!AU5)*0.51 -> 122.451 | J2: ='B5'!AX5/0.51 -> 0.19607843 | K2: =WATER!I6 -> 0 | L2: =SUM(WATER!J6) -> 0 | M2: =WATER!Q6 -> 0 | N2: 0.6 | O2: =ELEC!B3 -> 35.006
A3: Beirut | B3: =B2+1 -> 2 | C3: 3 | D3: 2020 | E3: =ELEC!N4 -> 12173 | F3: =SUM('EDl log'!T5) -> 0.048140417 | G3: =-tanks!AW7 -> 567 | H3: =SUM(tanks!AV7) -> 0.1 | I3: =('B5'!AU6)*0.51 -> 30.6 | J3: ='B5'!AX6/0.51 -> 0.19607843 | K3: =WATER!I7 -> 454 | L3: =SUM(WATER!J7) -> 0.53289754 | M3: =WATER!Q7 -> 0 | N3: 0.6 | O3: =ELEC!B4 -> 25.99
A4: Beirut | B4: =B3+1 -> 3 | C4: 3 | D4: 2020 | E4: =ELEC!N5 -> 11827.6 | F4: =SUM('EDl log'!T6) -> 0.044792755 | G4: =-tanks!AW8 -> 1061.4 | H4: =SUM(tanks!AV8) -> 0.1 | I4: =('B5'!AU7)*0.51 -> 45.9 | J4: ='B5'!AX7/0.51 -> 0.19607843 | K4: =WATER!I8 -> 0 | L4: =SUM(WATER!J8) -> 0 | M4: =WATER!Q8 -> 0 | N4: 0.6 | O4: =ELEC!B5 -> 27.991
A5: Beirut | B5: =B4+1 -> 4 | C5: 3 | D5: 2020 | E5: =ELEC!N6 -> 12688.8 | F5: =SUM('EDl log'!T7) -> 0.05022043 | G5: =-tanks!AW9 -> 276.7 | H5: =SUM(tanks!AV9) -> 0.1 | I5: =('B5'!AU8)*0.51 -> 107.1 | J5: ='B5'!AX8/0.51 -> 0.19607843 | K5: =WATER!I9 -> 341 | L5: =SUM(WATER!J9) -> 0.70948822 | M5: =WATER!Q9 -> 0 | N5: 0.6 | O5: =ELEC!B6 -> 29.003
A6: Beirut | B6: =B5+1 -> 5 | C6: 3 | D6: 2020 | E6: =ELEC!N7 -> 0 | F6: =SUM('EDl log'!T8) -> 0 | G6: =-tanks!AW10 -> 0 | H6: =SUM(tanks!AV10) -> 0.1 | I6: =('B5'!AU9)*0.51 -> 0 | J6: ='B5'!AX9/0.51 -> 0.19607843 | K6: =WATER!I10 -> 0 | L6: =SUM(WATER!J10) -> 0 | M6: =WATER!Q10 -> 0 | N6: 0.6 | O6: =ELEC!B7 -> 0
A7: Beirut | B7: =B6+1 -> 6 | C7: 3 | D7: 2020 | E7: =ELEC!N8 -> 0 | F7: =SUM('EDl log'!T9) -> 0 | G7: =-tanks!AW11 -> 0 | H7: =SUM(tanks!AV11) -> 0.1 | I7: =('B5'!AU10)*0.51 -> 0 | J7: ='B5'!AX10/0.51 -> 0.19607843 | K7: =WATER!I11 -> 0 | L7: =SUM(WATER!J11) -> 0 | M7: =WATER!Q11 -> 0 | N7: 0.6 | O7: =ELEC!B8 -> 0
A8: Beirut | B8: =B7+1 -> 7 | C8: 3 | D8: 2020 | E8: =ELEC!N9 -> 0 | F8: =SUM('EDl log'!T10) -> 0 | G8: =-tanks!AW12 -> 0 | H8: =SUM(tanks!AV12) -> 0.1 | I8: =('B5'!AU11)*0.51 -> 0 | J8: ='B5'!AX11/0.51 -> 0.19607843 | K8: =WATER!I12 -> 0 | L8: =SUM(WATER!J12) -> 0 | M8: =WATER!Q12 -> 0 | N8: 0.6 | O8: =ELEC!B9 -> 0
A9: Beirut | B9: =B8+1 -> 8 | C9: 3 | D9: 2020 | E9: =ELEC!N10 -> 0 | F9: =SUM('EDl log'!T11) -> 0 | G9: =-tanks!AW13 -> 0 | H9: =SUM(tanks!AV13) -> 0.1 | I9: =('B5'!AU12)*0.51 -> 0 | J9: ='B5'!AX12/0.51 -> 0.19607843 | K9: =WATER!I13 -> 0 | L9: =SUM(WATER!J13) -> 0 | M9: =WATER!Q13 -> 0 | N9: 0.6 | O9: =ELEC!B10 -> 0
A10: Beirut | B10: =B9+1 -> 9 | C10: 3 | D10: 2020 | E10: =ELEC!N11 -> 0 | F10: =SUM('EDl log'!T12) -> 0 | G10: =-tanks!AW14 -> 0 | H10: =SUM(tanks!AV14) -> 0.1 | I10: =('B5'!AU13)*0.51 -> 0 | J10: ='B5'!AX13/0.51 -> 0.19607843 | K10: =WATER!I14 -> 0 | L10: =SUM(WATER!J14) -> 0 | M10: =WATER!Q14 -> 0 | N10: 0.6 | O10: =ELEC!B11 -> 0
A11: Beirut | B11: =B10+1 -> 10 | C11: 3 | D11: 2020 | E11: =ELEC!N12 -> 0 | F11: =SUM('EDl log'!T13) -> 0 | G11: =-tanks!AW15 -> 0 | H11: =SUM(tanks!AV15) -> 0.1 | I11: =('B5'!AU14)*0.51 -> 0 | J11: ='B5'!AX14/0.51 -> 0.19607843 | K11: =WATER!I15 -> 0 | L11: =SUM(WATER!J15) -> 0 | M11: =WATER!Q15 -> 0 | N11: 0.6 | O11: =ELEC!B12 -> 0
A12: Beirut | B12: =B11+1 -> 11 | C12: 3 | D12: 2020 | E12: =ELEC!N13 -> 0 | F12: =SUM('EDl log'!T14) -> 0 | G12: =-tanks!AW16 -> 0 | H12: =SUM(tanks!AV16) -> 0.1 | I12: =('B5'!AU15)*0.51 -> 0 | J12: ='B5'!AX15/0.51 -> 0.19607843 | K12: =WATER!I16 -> 0 | L12: =SUM(WATER!J16) -> 0 | M12: =WATER!Q16 -> 0 | N12: 0.6 | O12: =ELEC!B13 -> 0
A13: Beirut | B13: =B12+1 -> 12 | C13: 3 | D13: 2020 | E13: =ELEC!N14 -> 0 | F13: =SUM('EDl log'!T15) -> 0 | G13: =-tanks!AW17 -> 0 | H13: =SUM(tanks!AV17) -> 0.1 | I13: =('B5'!AU16)*0.51 -> 0 | J13: ='B5'!AX16/0.51 -> 0.19607843 | K13: =WATER!I17 -> 0 | L13: =SUM(WATER!J17) -> 0 | M13: =WATER!Q17 -> 0 | N13: 0.6 | O13: =ELEC!B14 -> 0
A14: Beirut | B14: =B13+1 -> 13 | C14: 3 | D14: 2020 | E14: =ELEC!N15 -> 0 | F14: =SUM('EDl log'!T16) -> 0 | G14: =-tanks!AW18 -> 0 | H14: =SUM(tanks!AV18) -> 0.1 | I14: =('B5'!AU17)*0.51 -> 0 | J14: ='B5'!AX17/0.51 -> 0.19607843 | K14: =WATER!I18 -> 0 | L14: =SUM(WATER!J18) -> 0 | M14: =WATER!Q18 -> 0 | N14: 0.6 | O14: =ELEC!B15 -> 0
... A32: Beirut | B32: =B31+1 -> 31 | C32: 3 | D32: 2020 | E32: =ELEC!N33 -> 0 | F32: =SUM('EDl log'!T34) -> 0 | G32: =-tanks!AW36 -> 0 | H32: =SUM(tanks!AV36) -> 0.1 | I32: =('B5'!AU35)*0.51 -> 0 | J32: ='B5'!AX35/0.51 -> 0.19607843 | K32: =WATER!I36 -> 0 | L32: =SUM(WATER!J36) -> 0 | M32: =WATER!Q36 -> 0 | N32: 0.6 | O32: =ELEC!B33 -> 0

Sheet Submetering
A1: Site Name | B1: Day | C1: Month | D1: Year | E1: ATS1 Kwh | F1: ATS2 Kwh | G1: ATS3 Kwh | H1: ATS4 Kwh | I1: ATS5 Kwh | J1: Guest (m3) | K1: Kitchen & Laundry (m3) | L1: Room Nights
A2: Beirut | B2: 1 | C2: 3 | D2: 2020 | E2: =ELEC!M3 -> 3180 | F2: =ELEC!K3 -> 1116 | G2: =ELEC!I3 -> 1704 | H2: =ELEC!E3 -> 2808 | I2: =ELEC!G3 -> 1850 | J2: =WATER!Y6 -> 26 | K2: =WATER!AJ6 -> 11 | L2: =ELEC!B3 -> 35.006
A3: Beirut | B3: =B2+1 -> 2 | C3: 3 | D3: 2020 | E3: =ELEC!M4 -> 3284 | F3: =ELEC!K4 -> 1684 | G3: =ELEC!I4 -> 1910 | H3: =ELEC!E4 -> 3246 | I3: =ELEC!G4 -> 2049 | J3: =WATER!Y7 -> 152 | K3: =WATER!AJ7 -> 66 | L3: =ELEC!B4 -> 25.99
A4: Beirut | B4: =B3+1 -> 3 | C4: 3 | D4: 2020 | E4: =ELEC!M5 -> 3232 | F4: =ELEC!K5 -> 1468 | G4: =ELEC!I5 -> 1798 | H4: =ELEC!E5 -> 3364 | I4: =ELEC!G5 -> 1965.6 | J4: =WATER!Y8 -> 0 | K4: =WATER!AJ8 -> 0 | L4: =ELEC!B5 -> 27.991
A5: Beirut | B5: =B4+1 -> 4 | C5: 3 | D5: 2020 | E5: =ELEC!M6 -> 3424 | F5: =ELEC!K6 -> 1488 | G5: =ELEC!I6 -> 2038 | H5: =ELEC!E6 -> 3630 | I5: =ELEC!G6 -> 2108.8 | J5: =WATER!Y9 -> 93 | K5: =WATER!AJ9 -> 90 | L5: =ELEC!B6 -> 29.003
A6: Beirut | B6: =B5+1 -> 5 | C6: 3 | D6: 2020 | E6: =ELEC!M7 -> 0 | F6: =ELEC!K7 -> 0 | G6: =ELEC!I7 -> 0 | H6: =ELEC!E7 -> 0 | I6: =ELEC!G7 -> 0 | J6: =WATER!Y10 -> 0 | K6: =WATER!AJ10 -> 0 | L6: =ELEC!B7 -> 0
A7: Beirut | B7: =B6+1 -> 6 | C7: 3 | D7: 2020 | E7: =ELEC!M8 -> 0 | F7: =ELEC!K8 -> 0 | G7: =ELEC!I8 -> 0 | H7: =ELEC!E8 -> 0 | I7: =ELEC!G8 -> 0 | J7: =WATER!Y11 -> 0 | K7: =WATER!AJ11 -> 0 | L7: =ELEC!B8 -> 0
A8: Beirut | B8: =B7+1 -> 7 | C8: 3 | D8: 2020 | E8: =ELEC!M9 -> 0 | F8: =ELEC!K9 -> 0 | G8: =ELEC!I9 -> 0 | H8: =ELEC!E9 -> 0 | I8: =ELEC!G9 -> 0 | J8: =WATER!Y12 -> 0 | K8: =WATER!AJ12 -> 0 | L8: =ELEC!B9 -> 0
A9: Beirut | B9: =B8+1 -> 8 | C9: 3 | D9: 2020 | E9: =ELEC!M10 -> 0 | F9: =ELEC!K10 -> 0 | G9: =ELEC!I10 -> 0 | H9: =ELEC!E10 -> 0 | I9: =ELEC!G10 -> 0 | J9: =WATER!Y13 -> 0 | K9: =WATER!AJ13 -> 0 | L9: =ELEC!B10 -> 0
A10: Beirut | B10: =B9+1 -> 9 | C10: 3 | D10: 2020 | E10: =ELEC!M11 -> 0 | F10: =ELEC!K11 -> 0 | G10: =ELEC!I11 -> 0 | H10: =ELEC!E11 -> 0 | I10: =ELEC!G11 -> 0 | J10: =WATER!Y14 -> 0 | K10: =WATER!AJ14 -> 0 | L10: =ELEC!B11 -> 0
A11: Beirut | B11: =B10+1 -> 10 | C11: 3 | D11: 2020 | E11: =ELEC!M12 -> 0 | F11: =ELEC!K12 -> 0 | G11: =ELEC!I12 -> 0 | H11: =ELEC!E12 -> 0 | I11: =ELEC!G12 -> 0 | J11: =WATER!Y15 -> 0 | K11: =WATER!AJ15 -> 0 | L11: =ELEC!B12 -> 0
A12: Beirut | B12: =B11+1 -> 11 | C12: 3 | D12: 2020 | E12: =ELEC!M13 -> 0 | F12: =ELEC!K13 -> 0 | G12: =ELEC!I13 -> 0 | H12: =ELEC!E13 -> 0 | I12: =ELEC!G13 -> 0 | J12: =WATER!Y16 -> 0 | K12: =WATER!AJ16 -> 0 | L12: =ELEC!B13 -> 0
A13: Beirut | B13: =B12+1 -> 12 | C13: 3 | D13: 2020 | E13: =ELEC!M14 -> 0 | F13: =ELEC!K14 -> 0 | G13: =ELEC!I14 -> 0 | H13: =ELEC!E14 -> 0 | I13: =ELEC!G14 -> 0 | J13: =WATER!Y17 -> 0 | K13: =WATER!AJ17 -> 0 | L13: =ELEC!B14 -> 0
A14: Beirut | B14: =B13+1 -> 13 | C14: 3 | D14: 2020 | E14: =ELEC!M15 -> 0 | F14: =ELEC!K15 -> 0 | G14: =ELEC!I15 -> 0 | H14: =ELEC!E15 -> 0 | I14: =ELEC!G15 -> 0 | J14: =WATER!Y18 -> 0 | K14: =WATER!AJ18 -> 0 | L14: =ELEC!B15 -> 0
... A32: Beirut | B32: =B31+1 -> 31 | C32: 3 | D32: 2020 | E32: =ELEC!M33 -> 0 | F32: =ELEC!K33 -> 0 | G32: =ELEC!I33 -> 0 | H32: =ELEC!E33 -> 0 | I32: =ELEC!G33 -> 0 | J32: =WATER!Y36 -> 0 | K32: =WATER!AJ36 -> 0 | L32: =ELEC!B33 -> 0

Sheet ELEC
A1: OOC | B1: Room OCC | D1: MDB3 | E1: MDB3/day | F1: EMDB2 | G1: EMDB2/day | H1: EMDB1 | I1: EMDB1/day | J1: MDB2 | K1: mdb2/day | L1: MDB1 | M1: MDB1/Day | N1: Total KWH | O1: KWH/Rooc | P1: Gen MHW | Q1: Gen/Day KWH | R1: EDL KWH | S1: CH1 RH | T1: RH | U1: C1h1 power | V1: CH1 Con KWH | W1: CH2 RH | X1: RH | Y1: Ch2 power | Z1: CH2 Con KWH | AA1: CH3 RH | AB1: RH | AC1: Ch3 power | AD1: CH3 Con KWH | AE1: RH total | AF1: KWH total | AG1: AVG chiller KW/Hr
A2: 0.1391 | B2: 0.1391 | C2: 43890 | D2: =[1]ELEC!D31 -> 31482720 | E2: =[1]ELEC!E31 -> 3634 | F2: =[1]ELEC!F31 -> 3556171 | G2: =[1]ELEC!G31 -> 2226 | H2: =[1]ELEC!H31 -> 17345006 | I2: =[1]ELEC!I31 -> 2064 | J2: =[1]ELEC!J31 -> 28330034 | K2: =[1]ELEC!K31 -> 2096 | ... AI2: =[1]ELEC!AI31 -> -49556526
A3: ='General information '!F6 -> 0.1522 | B3: =SUM(230*A3) -> 35.006 | C3: 43891 | D3: 31485528 | E3: =D3-D2 -> 2808 | F3: 3558021 | G3: =F3-F2 -> 1850 | H3: 17346710 | I3: =H3-H2 -> 1704 | J3: 28331150 | K3: =J3-J2 -> 1116 | L3: 22755778 | M3: =L3-L2 -> 3180 | N3: =M3+K3+I3+G3+E3 -> 10658 | O3: =IF(B3>0,N3/B3,0) -> 304.46209 | P3: 15381 | Q3: =(P3-P2)*1000 -> 4100 | R3: =+N3-Q3 -> 6558 | S3: 8384 | T3: =S3-S2 -> 0 | U3: 1024343 | V3: =U3-U2 -> 0 | W3: 31845 | X3: =W3-W2 -> 0 | Y3: 624440 | Z3: =Y3-Y2 -> 0 | AA3: 34971 | AB3: =AA3-AA2 -> 4 | AC3: 757660 | AD3: =AC3-AC2 -> 681 | AE3: =AB3+X3+T3 -> 4 | AF3: =V3+Z3+AD3 -> 681 | AG3: =IF(AE3>0,AF3/AE3,0) -> 170.25
A4: ='General information '!F7 -> 0.113 | B4: =SUM(230*A4) -> 25.99 | C4: 43892 | D4: 31488774 | E4: =D4-D3 -> 3246 | F4: 3560070 | G4: =F4-F3 -> 2049 | H4: 17348620 | I4: =H4-H3 -> 1910 | J4: 28332834 | K4: =J4-J3 -> 1684 | L4: 22759062 | M4: =L4-L3 -> 3284 | N4: =M4+K4+I4+G4+E4 -> 12173 | O4: =IF(B4>0,N4/B4,0) -> 468.37245 | P4: 15381.849 | Q4: =(P4-P3)*1000 -> 849 | R4: =N4-Q4 -> 11324 | S4: =S3 -> 8384 | T4: =S4-S3 -> 0 | U4: =U3 -> 1024343 | V4: =U4-U3 -> 0 | W4: =W3 -> 31845 | X4: =W4-W3 -> 0 | Y4: =Y3 -> 624440 | Z4: =Y4-Y3 -> 0 | AA4: 34974 | AB4: =AA4-AA3 -> 3 | AC4: 758247 | AD4: =AC4-AC3 -> 587 | AE4: =AB4+X4+T4 -> 3 | AF4: =V4+Z4+AD4 -> 587 | AG4: =IF(AE4>0,AF4/AE4,0) -> 195.66667
A5: ='General information '!F8 -> 0.1217 | B5: =SUM(230*A5) -> 27.991 | C5: 43893 | D5: 31492138 | E5: =D5-D4 -> 3364 | F5: 3562035.6 | G5: =F5-F4 -> 1965.6 | H5: 17350418 | I5: =H5-H4 -> 1798 | J5: 28334302 | K5: =J5-J4 -> 1468 | L5: 22762294 | M5: =L5-L4 -> 3232 | N5: =M5+K5+I5+G5+E5 -> 11827.6 | O5: =IF(B5>0,N5/B5,0) -> 422.55011 | P5: 15383.715 | Q5: =(P5-P4)*1000 -> 1866 | R5: =N5-Q5 -> 9961.6 | S5: 8384 | T5: =S5-S4 -> 0 | U5: 1024343 | V5: =U5-U4 -> 0 | W5: 31845 | X5: =W5-W4 -> 0 | Y5: 624440 | Z5: =Y5-Y4 -> 0 | AA5: 34978 | AB5: =AA5-AA4 -> 4 | AC5: 759035 | AD5: =AC5-AC4 -> 788 | AE5: =AB5+X5+T5 -> 4 | AF5: =V5+Z5+AD5 -> 788 | AG5: =IF(AE5>0,AF5/AE5,0) -> 197 | AI5: =R5-'EDl log'!B3 -> -49572080
A6: ='General information '!F9 -> 0.1261 | B6: =SUM(230*A6) -> 29.003 | C6: 43894 | D6: 31495768 | E6: =D6-D5 -> 3630 | F6: 3564144.4 | G6: =F6-F5 -> 2108.8 | H6: 17352456 | I6: =H6-H5 -> 2038 | J6: 28335790 | K6: =J6-J5 -> 1488 | L6: 22765718 | M6: =L6-L5 -> 3424 | N6: =M6+K6+I6+G6+E6 -> 12688.8 | O6: =IF(B6>0,N6/B6,0) -> 437.49957 | P6: 15386.126 | Q6: =(P6-P5)*1000 -> 2411 | R6: =N6-Q6 -> 10277.8 | S6: 8384 | T6: =S6-S5 -> 0 | U6: 1024343 | V6: =U6-U5 -> 0 | W6: 31845 | X6: =W6-W5 -> 0 | Y6: 624440 | Z6: =Y6-Y5 -> 0 | AA6: 34982 | AB6: =AA6-AA5 -> 4 | AC6: 759837 | AD6: =AC6-AC5 -> 802 | AE6: =AB6+X6+T6 -> 4 | AF6: =V6+Z6+AD6 -> 802 | AG6: =IF(AE6>0,AF6/AE6,0) -> 200.5 | AI6: =R6-'EDl log'!B4 -> -49576134
A7: ='General information '!F10 -> 0 | B7: =SUM(230*A7) -> 0 | C7: 43895 | D7: =D6 -> 31495768 | E7: =D7-D6 -> 0 | F7: =F6 -> 3564144.4 | G7: =F7-F6 -> 0 | H7: =H6 -> 17352456 | I7: =H7-H6 -> 0 | J7: =J6 -> 28335790 | K7: =J7-J6 -> 0 | L7: =L6 -> 22765718 | M7: =L7-L6 -> 0 | N7: =M7+K7+I7+G7+E7 -> 0 | O7: =IF(B7>0,N7/B7,0) -> 0 | P7: =P6 -> 15386.126 | Q7: =(P7-P6)*1000 -> 0 | R7: =N7-Q7 -> 0 | S7: =S6 -> 8384 | T7: =S7-S6 -> 0 | U7: =U6 -> 1024343 | V7: =U7-U6 -> 0 | W7: =W6 -> 31845 | X7: =W7-W6 -> 0 | Y7: =Y6 -> 624440 | Z7: =Y7-Y6 -> 0 | AA7: =AA6 -> 34982 | AB7: =AA7-AA6 -> 0 | AC7: =AC6 -> 759837 | AD7: =AC7-AC6 -> 0 | AE7: =AB7+X7+T7 -> 0 | AF7: =V7+Z7+AD7 -> 0 | AG7: =IF(AE7>0,AF7/AE7,0) -> 0 | AI7: =R7-'EDl log'!B5 -> -49591340
A8: ='General information '!F11 -> 0 | B8: =SUM(230*A8) -> 0 | C8: 43896 | D8: =D7 -> 31495768 | E8: =D8-D7 -> 0 | F8: =F7 -> 3564144.4 | G8: =F8-F7 -> 0 | H8: =H7 -> 17352456 | I8: =H8-H7 -> 0 | J8: =J7 -> 28335790 | K8: =J8-J7 -> 0 | L8: =L7 -> 22765718 | M8: =L8-L7 -> 0 | N8: =M8+K8+I8+G8+E8 -> 0 | O8: =IF(B8>0,N8/B8,0) -> 0 | P8: =P7 -> 15386.126 | Q8: =(P8-P7)*1000 -> 0 | R8: =N8-Q8 -> 0 | S8: =S7 -> 8384 | T8: =S8-S7 -> 0 | U8: =U7 -> 1024343 | V8: =U8-U7 -> 0 | W8: =W7 -> 31845 | X8: =W8-W7 -> 0 | Y8: =Y7 -> 624440 | Z8: =Y8-Y7 -> 0 | AA8: =AA7 -> 34982 | AB8: =AA8-AA7 -> 0 | AC8: =AC7 -> 759837 | AD8: =AC8-AC7 -> 0 | AE8: =AB8+X8+T8 -> 0 | AF8: =V8+Z8+AD8 -> 0 | AG8: =IF(AE8>0,AF8/AE8,0) -> 0 | AI8: =R8-'EDl log'!B6 -> -49596500
A9: ='General information '!F12 -> 0 | B9: =SUM(230*A9) -> 0 | C9: 43897 | D9: =D8 -> 31495768 | E9: =D9-D8 -> 0 | F9: =F8 -> 3564144.4 | G9: =F9-F8 -> 0 | H9: =H8 -> 17352456 | I9: =H9-H8 -> 0 | J9: =J8 -> 28335790 | K9: =J9-J8 -> 0 | L9: =L8 -> 22765718 | M9: =L9-L8 -> 0 | N9: =M9+K9+I9+G9+E9 -> 0 | O9: =IF(B9>0,N9/B9,0) -> 0 | P9: =P8 -> 15386.126 | Q9: =(P9-P8)*1000 -> 0 | R9: =N9-Q9 -> 0 | S9: =S8 -> 8384 | T9: =S9-S8 -> 0 | U9: =U8 -> 1024343 | V9: =U9-U8 -> 0 | W9: =W8 -> 31845 | X9: =W9-W8 -> 0 | Y9: =Y8 -> 624440 | Z9: =Y9-Y8 -> 0 | AA9: =AA8 -> 34982 | AB9: =AA9-AA8 -> 0 | AC9: =AC8 -> 759837 | AD9: =AC9-AC8 -> 0 | AE9: =AB9+X9+T9 -> 0 | AF9: =V9+Z9+AD9 -> 0 | AG9: =IF(AE9>0,AF9/AE9,0) -> 0 | AI9: =R9-'EDl log'!B7 -> -49601831
A10: ='General information '!F13 -> 0 | B10: =SUM(230*A10) -> 0 | C10: 43898 | D10: =D9 -> 31495768 | E10: =D10-D9 -> 0 | F10: =F9 -> 3564144.4 | G10: =F10-F9 -> 0 | H10: =H9 -> 17352456 | I10: =H10-H9 -> 0 | J10: =J9 -> 28335790 | K10: =J10-J9 -> 0 | L10: =L9 -> 22765718 | M10: =L10-L9 -> 0 | N10: =M10+K10+I10+G10+E10 -> 0 | O10: =IF(B10>0,N10/B10,0) -> 0 | P10: =P9 -> 15386.126 | Q10: =(P10-P9)*1000 -> 0 | R10: =N10-Q10 -> 0 | S10: =S9 -> 8384 | T10: =S10-S9 -> 0 | U10: =U9 -> 1024343 | V10: =U10-U9 -> 0 | W10: =W9 -> 31845 | X10: =W10-W9 -> 0 | Y10: =Y9 -> 624440 | Z10: =Y10-Y9 -> 0 | AA10: =AA9 -> 34982 | AB10: =AA10-AA9 -> 0 | AC10: =AC9 -> 759837 | AD10: =AC10-AC9 -> 0 | AE10: =AB10+X10+T10 -> 0 | AF10: =V10+Z10+AD10 -> 0 | AG10: =IF(AE10>0,AF10/AE10,0) -> 0 | AI10: =R10-'EDl log'!B8 -> -49601831
A11: ='General information '!F14 -> 0 | B11: =SUM(230*A11) -> 0 | C11: 43899 | D11: =D10 -> 31495768 | E11: =D11-D10 -> 0 | F11: =F10 -> 3564144.4 | G11: =F11-F10 -> 0 | H11: =H10 -> 17352456 | I11: =H11-H10 -> 0 | J11: =J10 -> 28335790 | K11: =J11-J10 -> 0 | L11: =L10 -> 22765718 | M11: =L11-L10 -> 0 | N11: =M11+K11+I11+G11+E11 -> 0 | O11: =IF(B11>0,N11/B11,0) -> 0 | P11: =P10 -> 15386.126 | Q11: =(P11-P10)*1000 -> 0 | R11: =N11-Q11 -> 0 | S11: =S10 -> 8384 | T11: =S11-S10 -> 0 | U11: =U10 -> 1024343 | V11: =U11-U10 -> 0 | W11: =W10 -> 31845 | X11: =W11-W10 -> 0 | Y11: =Y10 -> 624440 | Z11: =Y11-Y10 -> 0 | AA11: =AA10 -> 34982 | AB11: =AA11-AA10 -> 0 | AC11: =AC10 -> 759837 | AD11: =AC11-AC10 -> 0 | AE11: =AB11+X11+T11 -> 0 | AF11: =V11+Z11+AD11 -> 0 | AG11: =IF(AE11>0,AF11/AE11,0) -> 0 | AI11: =R11-'EDl log'!B9 -> -49601831
A12: ='General information '!F15 -> 0 | B12: =SUM(230*A12) -> 0 | C12: 43900 | D12: =D11 -> 31495768 | E12: =D12-D11 -> 0 | F12: =F11 -> 3564144.4 | G12: =F12-F11 -> 0 | H12: =H11 -> 17352456 | I12: =H12-H11 -> 0 | J12: =J11 -> 28335790 | K12: =J12-J11 -> 0 | L12: =L11 -> 22765718 | M12: =L12-L11 -> 0 | N12: =M12+K12+I12+G12+E12 -> 0 | O12: =IF(B12>0,N12/B12,0) -> 0 | P12: =P11 -> 15386.126 | Q12: =(P12-P11)*1000 -> 0 | R12: =N12-Q12 -> 0 | S12: =S11 -> 8384 | T12: =S12-S11 -> 0 | U12: =U11 -> 1024343 | V12: =U12-U11 -> 0 | W12: =W11 -> 31845 | X12: =W12-W11 -> 0 | Y12: =Y11 -> 624440 | Z12: =Y12-Y11 -> 0 | AA12: =AA11 -> 34982 | AB12: =AA12-AA11 -> 0 | AC12: =AC11 -> 759837 | AD12: =AC12-AC11 -> 0 | AE12: =AB12+X12+T12 -> 0 | AF12: =V12+Z12+AD12 -> 0 | AG12: =IF(AE12>0,AF12/AE12,0) -> 0 | AI12: =R12-'EDl log'!B10 -> -49601831
A13: ='General information '!F16 -> 0 | B13: =SUM(230*A13) -> 0 | C13: 43901 | D13: =D12 -> 31495768 | E13: =D13-D12 -> 0 | F13: =F12 -> 3564144.4 | G13: =F13-F12 -> 0 | H13: =H12 -> 17352456 | I13: =H13-H12 -> 0 | J13: =J12 -> 28335790 | K13: =J13-J12 -> 0 | L13: =L12 -> 22765718 | M13: =L13-L12 -> 0 | N13: =M13+K13+I13+G13+E13 -> 0 | O13: =IF(B13>0,N13/B13,0) -> 0 | P13: =P12 -> 15386.126 | Q13: =(P13-P12)*1000 -> 0 | R13: =N13-Q13 -> 0 | S13: =S12 -> 8384 | T13: =S13-S12 -> 0 | U13: =U12 -> 1024343 | V13: =U13-U12 -> 0 | W13: =W12 -> 31845 | X13: =W13-W12 -> 0 | Y13: =Y12 -> 624440 | Z13: =Y13-Y12 -> 0 | AA13: =AA12 -> 34982 | AB13: =AA13-AA12 -> 0 | AC13: =AC12 -> 759837 | AD13: =AC13-AC12 -> 0 | AE13: =AB13+X13+T13 -> 0 | AF13: =V13+Z13+AD13 -> 0 | AG13: =IF(AE13>0,AF13/AE13,0) -> 0 | AI13: =R13-'EDl log'!B11 -> -49601831
A14: ='General information '!F17 -> 0 | B14: =SUM(230*A14) -> 0 | C14: 43902 | D14: =D13 -> 31495768 | E14: =D14-D13 -> 0 | F14: =F13 -> 3564144.4 | G14: =F14-F13 -> 0 | H14: =H13 -> 17352456 | I14: =H14-H13 -> 0 | J14: =J13 -> 28335790 | K14: =J14-J13 -> 0 | L14: =L13 -> 22765718 | M14: =L14-L13 -> 0 | N14: =M14+K14+I14+G14+E14 -> 0 | O14: =IF(B14>0,N14/B14,0) -> 0 | P14: =P13 -> 15386.126 | Q14: =(P14-P13)*1000 -> 0 | R14: =N14-Q14 -> 0 | S14: =S13 -> 8384 | T14: =S14-S13 -> 0 | U14: =U13 -> 1024343 | V14: =U14-U13 -> 0 | W14: =W13 -> 31845 | X14: =W14-W13 -> 0 | Y14: =Y13 -> 624440 | Z14: =Y14-Y13 -> 0 | AA14: =AA13 -> 34982 | AB14: =AA14-AA13 -> 0 | AC14: =AC13 -> 759837 | AD14: =AC14-AC13 -> 0 | AE14: =AB14+X14+T14 -> 0 | AF14: =V14+Z14+AD14 -> 0 | AG14: =IF(AE14>0,AF14/AE14,0) -> 0 | AI14: =R14-'EDl log'!B12 -> -49601831
A15: ='General information '!F18 -> 0 | B15: =SUM(230*A15) -> 0 | C15: 43903 | D15: =D14 -> 31495768 | E15: =D15-D14 -> 0 | F15: =F14 -> 3564144.4 | G15: =F15-F14 -> 0 | H15: =H14 -> 17352456 | I15: =H15-H14 -> 0 | J15: =J14 -> 28335790 | K15: =J15-J14 -> 0 | L15: =L14 -> 22765718 | M15: =L15-L14 -> 0 | N15: =M15+K15+I15+G15+E15 -> 0 | O15: =IF(B15>0,N15/B15,0) -> 0 | P15: =P14 -> 15386.126 | Q15: =(P15-P14)*1000 -> 0 | R15: =N15-Q15 -> 0 | S15: =S14 -> 8384 | T15: =S15-S14 -> 0 | U15: =U14 -> 1024343 | V15: =U15-U14 -> 0 | W15: =W14 -> 31845 | X15: =W15-W14 -> 0 | Y15: =Y14 -> 624440 | Z15: =Y15-Y14 -> 0 | AA15: =AA14 -> 34982 | AB15: =AA15-AA14 -> 0 | AC15: =AC14 -> 759837 | AD15: =AC15-AC14 -> 0 | AE15: =AB15+X15+T15 -> 0 | AF15: =V15+Z15+AD15 -> 0 | AG15: =IF(AE15>0,AF15/AE15,0) -> 0 | AI15: =R15-'EDl log'!B13 -> -49601831
A16: ='General information '!F19 -> 0 | B16: =SUM(230*A16) -> 0 | C16: 43904 | D16: =D15 -> 31495768 | E16: =D16-D15 -> 0 | F16: =F15 -> 3564144.4 | G16: =F16-F15 -> 0 | H16: =H15 -> 17352456 | I16: =H16-H15 -> 0 | J16: =J15 -> 28335790 | K16: =J16-J15 -> 0 | L16: =L15 -> 22765718 | M16: =L16-L15 -> 0 | N16: =M16+K16+I16+G16+E16 -> 0 | O16: =IF(B16>0,N16/B16,0) -> 0 | P16: =P15 -> 15386.126 | Q16: =(P16-P15)*1000 -> 0 | R16: =N16-Q16 -> 0 | S16: =S15 -> 8384 | T16: =S16-S15 -> 0 | U16: =U15 -> 1024343 | V16: =U16-U15 -> 0 | W16: =W15 -> 31845 | X16: =W16-W15 -> 0 | Y16: =Y15 -> 624440 | Z16: =Y16-Y15 -> 0 | AA16: =AA15 -> 34982 | AB16: =AA16-AA15 -> 0 | AC16: =AC15 -> 759837 | AD16: =AC16-AC15 -> 0 | AE16: =AB16+X16+T16 -> 0 | AF16: =V16+Z16+AD16 -> 0 | AG16: =IF(AE16>0,AF16/AE16,0) -> 0 | AI16: =R16-'EDl log'!B14 -> -49601831
A17: ='General information '!F20 -> 0 | B17: =SUM(230*A17) -> 0 | C17: 43905 | D17: =D16 -> 31495768 | E17: =D17-D16 -> 0 | F17: =F16 -> 3564144.4 | G17: =F17-F16 -> 0 | H17: =H16 -> 17352456 | I17: =H17-H16 -> 0 | J17: =J16 -> 28335790 | K17: =J17-J16 -> 0 | L17: =L16 -> 22765718 | M17: =L17-L16 -> 0 | N17: =M17+K17+I17+G17+E17 -> 0 | O17: =IF(B17>0,N17/B17,0) -> 0 | P17: =P16 -> 15386.126 | Q17: =(P17-P16)*1000 -> 0 | R17: =N17-Q17 -> 0 | S17: =S16 -> 8384 | T17: =S17-S16 -> 0 | U17: =U16 -> 1024343 | V17: =U17-U16 -> 0 | W17: =W16 -> 31845 | X17: =W17-W16 -> 0 | Y17: =Y16 -> 624440 | Z17: =Y17-Y16 -> 0 | AA17: =AA16 -> 34982 | AB17: =AA17-AA16 -> 0 | AC17: =AC16 -> 759837 | AD17: =AC17-AC16 -> 0 | AE17: =AB17+X17+T17 -> 0 | AF17: =V17+Z17+AD17 -> 0 | AG17: =IF(AE17>0,AF17/AE17,0) -> 0 | AI17: =R17-'EDl log'!B15 -> -49601831
A18: ='General information '!F21 -> 0 | B18: =SUM(230*A18) -> 0 | C18: 43906 | D18: =D17 -> 31495768 | E18: =D18-D17 -> 0 | F18: =F17 -> 3564144.4 | G18: =F18-F17 -> 0 | H18: =H17 -> 17352456 | I18: =H18-H17 -> 0 | J18: =J17 -> 28335790 | K18: =J18-J17 -> 0 | L18: =L17 -> 22765718 | M18: =L18-L17 -> 0 | N18: =M18+K18+I18+G18+E18 -> 0 | O18: =IF(B18>0,N18/B18,0) -> 0 | P18: =P17 -> 15386.126 | Q18: =(P18-P17)*1000 -> 0 | R18: =N18-Q18 -> 0 | S18: =S17 -> 8384 | T18: =S18-S17 -> 0 | U18: =U17 -> 1024343 | V18: =U18-U17 -> 0 | W18: =W17 -> 31845 | X18: =W18-W17 -> 0 | Y18: =Y17 -> 624440 | Z18: =Y18-Y17 -> 0 | AA18: =AA17 -> 34982 | AB18: =AA18-AA17 -> 0 | AC18: =AC17 -> 759837 | AD18: =AC18-AC17 -> 0 | AE18: =AB18+X18+T18 -> 0 | AF18: =V18+Z18+AD18 -> 0 | AG18: =IF(AE18>0,AF18/AE18,0) -> 0 | AI18: =R18-'EDl log'!B16 -> -49601831
... A33: ='General information '!F36 -> 0 | B33: =SUM(230*A33) -> 0 | C33: 43921 | D33: =D32 -> 31495768 | E33: =D33-D32 -> 0 | F33: =F32 -> 3564144.4 | G33: =F33-F32 -> 0 | H33: =H32 -> 17352456 | I33: =H33-H32 -> 0 | J33: =J32 -> 28335790 | K33: =J33-J32 -> 0 | L33: =L32 -> 22765718 | M33: =L33-L32 -> 0 | N33: =M33+K33+I33+G33+E33 -> 0 | O33: =IF(B33>0,N33/B33,0) -> 0 | P33: =P32 -> 15386.126 | Q33: =(P33-P32)*1000 -> 0 | R33: =N33-Q33 -> 0 | S33: =S32 -> 8384 | T33: =S33-S32 -> 0 | U33: =U32 -> 1024343 | V33: =U33-U32 -> 0 | W33: =W32 -> 31845 | X33: =W33-W32 -> 0 | Y33: =Y32 -> 624440 | Z33: =Y33-Y32 -> 0 | AA33: =AA32 -> 34982 | AB33: =AA33-AA32 -> 0 | AC33: =AC32 -> 759837 | AD33: =AC33-AC32 -> 0 | AE33: =AB33+X33+T33 -> 0 | AF33: =V33+Z33+AD33 -> 0 | AG33: =IF(AE33>0,AF33/AE33,0) -> 0 | AI33: =R33-'EDl log'!B31 -> -49601831

Sheet B5
F1: Boiler A | J1: =J36 -> 51.888889 | K1: Boiler B | P1: Boiler C | V1: Boiler | X1: SteamA | AC1: SteamB | AH1: Steam | AI1: Boiler & steam | AL1: Total Boiler Runing H | AM1: Total Steam Runing H | AN1: GAS1 % | AO1: GAS1/L | AP1: GAS2% | AQ1: Gas2/L | AR1: GAS3% | AS1: GAS3/L | AU1: Gas Cons | AV1: Delivery | AW1: Cost/L
B2: Level Tank Gen | C2: Level tank Boiler | D2: Daily Cons Bo. | E2: Boiler litter | F2: Boiler A | G2: Run Hr a | H2: Boiler A fuel | I2: Daily consumption | J2: AVG | K2: index Run H | L2: Run Hrb | M2: Boiler B Fuel | O2: Daily consumption | P2: Boiler C | S2: Run C | U2: Total RH | V2: Total Fuel | X2: SteamA | Y2: Run SA | Z2: Steam A Conter | AA2: Liters | AC2: SteamB | AD2: Run SteamB | AE2: Steam B Conter | AF2: SB Litters | AG2: Avg | AH2: Total Fuel | AI2: Total Fuel
S3: 0
A4: =ELEC!C2 -> 43890 | B4: =[1]B5!B33 -> 233.3 | C4: =[1]B5!C33 -> 239.1 | D4: =[1]B5!D33 -> 8.9 | E4: =[1]B5!E33 -> 74.582 | F4: =[1]B5!F33 -> 1448 | G4: =[1]B5!G33 -> 1 | H4: =[1]B5!H33 -> 342051 | I4: =[1]B5!I33 -> 93 | ... AX4: =[1]B5!AX33 -> 0.7
A5: =ELEC!C3 -> 43891 | B5: 229 | C5: 234.4 | D5: =C4-C5 -> 4.7 | E5: =D5*8.38 -> 39.386 | F5: 1452 | G5: =F5-F4 -> 4 | H5: 342342 | I5: =SUM(H5-H4) -> 291 | J5: 1 | K5: 1836 | L5: =K5-K4 -> 0 | M5: 134157 | N5: =M5-M4 -> 0 | O5: =SUM(L5*$J$1) -> 0 | P5: 1680 | Q5: 143596 | R5: =Q5-Q4 -> 289 | S5: =SUM(P5-P4) -> 4 | T5: =SUM(S5*$T$2) -> 0 | U5: =SUM(G5+L5+S5) -> 8 | V5: =R5+N5+I5:I5 -> 580 | W5: =SUM(V5/U5) -> 72.5 | X5: 2392 | Y5: =X5-X4 -> 0 | Z5: 134406.8 | AA5: =Z5-Z4 -> 0 | AB5: =SUM(Y5*$AB$2) -> 0 | AC5: 1801 | AD5: =AC5-AC4 -> 0 | AE5: 357717.5 | AF5: =AE5-AE4 -> 0 | AG5: =IF(AD5>0,AF5/AD5,0) -> 0 | AH5: =AF5+AA5 -> 0 | AI5: =SUM(AH5+V5) -> 580 | AJ5: =-tanks!AW6 -> 580 | AK5: =SUM(AJ5-AI5) -> 0 | AL5: =S5+L5+G5 -> 8 | AM5: =Y5+AD5 -> 0 | AN5: 75 | AO5: =(AN5/100)*3000 -> 2250 | AP5: 75 | AQ5: =(AP5/100)*3000 -> 2250 | AR5: 76 | AS5: =(AR5/100)*3000 -> 2280 | AT5: =SUM(AO5+AQ5+AS5) -> 6780 | AU5: =AT4-AT5+AV5 -> 240.1 | AV5: 0.1 | AW5: 0.1 | AX5: =IF(AV5>0,AW5,AX4) -> 0.1
A6: =ELEC!C4 -> 43892 | B6: 224 | C6: 230 | D6: =C5-C6 -> 4.4 | E6: =D6*8.38 -> 36.872 | F6: 1456 | G6: =F6-F5 -> 4 | H6: 342630 | I6: =SUM(H6-H5) -> 288 | J6: =IF(G6>0,I6/G6,0) -> 72 | K6: 1839 | L6: =K6-K5 -> 3 | M6: 134436 | N6: =M6-M5 -> 279 | O6: =SUM(L6*$J$1) -> 155.66667 | P6: =P5 -> 1680 | Q6: =Q5 -> 143596 | R6: =Q6-Q5 -> 0 | S6: =SUM(P6-P5) -> 0 | T6: =SUM(S6*$T$2) -> 0 | U6: =SUM(G6+L6+S6) -> 7 | V6: =R6+N6+I6:I6 -> 567 | W6: =SUM(V6/U6) -> 81 | X6: =X5 -> 2392 | Y6: =X6-X5 -> 0 | Z6: =Z5 -> 134406.8 | AA6: =Z6-Z5 -> 0 | AB6: =SUM(Y6*$AB$2) -> 0 | AC6: =AC5 -> 1801 | AD6: =AC6-AC5 -> 0 | AE6: =AE5 -> 357717.5 | AF6: =AE6-AE5 -> 0 | AG6: =IF(AD6>0,AF6/AD6,0) -> 0 | AH6: =AF6+AA6 -> 0 | AI6: =SUM(AH6+V6) -> 567 | AJ6: =-tanks!AW7 -> 567 | AK6: =SUM(AJ6-AI6) -> 0 | AL6: =S6+L6+G6 -> 7 | AM6: =Y6+AD6 -> 0 | AN6: =AN5 -> 75 | AO6: =(AN6/100)*3000 -> 2250 | AP6: 74 | AQ6: =(AP6/100)*3000 -> 2220 | AR6: 75 | AS6: =(AR6/100)*3000 -> 2250 | AT6: =SUM(AO6+AQ6+AS6) -> 6720 | AU6: =AT5-AT6+AV6 -> 60 | AX6: =IF(AV6>0,AW6,AX5) -> 0.1
A7: =ELEC!C5 -> 43893 | B7: 220 | C7: 225.4 | D7: =C6-C7 -> 4.6 | E7: =D7*8.38 -> 38.548 | F7: 1459 | G7: =F7-F6 -> 3 | H7: 342878 | I7: =SUM(H7-H6) -> 248 | J7: =IF(G7>0,I7/G7,0) -> 82.666667 | K7: 1843 | L7: =K7-K6 -> 4 | M7: 134733 | N7: =M7-M6 -> 297 | O7: 1 | P7: 1680 | Q7: 143604 | R7: =Q7-Q6 -> 8 | S7: =SUM(P7-P6) -> 0 | T7: =SUM(S7*$T$2) -> 0 | U7: =SUM(G7+L7+S7) -> 7 | V7: =R7+N7+I7:I7 -> 553 | W7: =SUM(V7/U7) -> 79 | X7: 2400 | Y7: =X7-X6 -> 8 | Z7: 134915.2 | AA7: =Z7-Z6 -> 508.4 | AB7: =SUM(Y7*$AB$2) -> 0 | AC7: 1801 | AD7: =AC7-AC6 -> 0 | AE7: 357717.5 | AF7: =AE7-AE6 -> 0 | AG7: =IF(AD7>0,AF7/AD7,0) -> 0 | AH7: =AF7+AA7 -> 508.4 | AI7: =SUM(AH7+V7) -> 1061.4 | AJ7: =-tanks!AW8 -> 1061.4 | AK7: =SUM(AJ7-AI7) -> 0 | AL7: =S7+L7+G7 -> 7 | AM7: =Y7+AD7 -> 8 | AN7: 72 | AO7: =(AN7/100)*3000 -> 2160 | AP7: 74 | AQ7: =(AP7/100)*3000 -> 2220 | AR7: =AR6 -> 75 | AS7: =(AR7/100)*3000 -> 2250 | AT7: =SUM(AO7+AQ7+AS7) -> 6630 | AU7: =AT6-AT7+AV7 -> 90 | AX7: =IF(AV7>0,AW7,AX6) -> 0.1
A8: =ELEC!C6 -> 43894 | B8: 213.3 | C8: 219.2 | D8: =C7-C8 -> 6.2 | E8: =D8*8.38 -> 51.956 | F8: 1459 | G8: =F8-F7 -> 0 | H8: 342878 | I8: =SUM(H8-H7) -> 0 | J8: =IF(G8>0,I8/G8,0) -> 0 | K8: 1846 | L8: =K8-K7 -> 3 | M8: 134906 | N8: =M8-M7 -> 173 | O8: 1479 | P8: 1681 | Q8: 143671 | R8: =Q8-Q7 -> 67 | S8: =SUM(P8-P7) -> 1 | T8: =SUM(S8*$T$2) -> 0 | U8: =SUM(G8+L8+S8) -> 4 | V8: =R8+N8+I8:I8 -> 240 | W8: =SUM(V8/U8) -> 60 | X8: 2401 | Y8: =X8-X7 -> 1 | Z8: 134951.9 | AA8: =Z8-Z7 -> 36.7 | AB8: =SUM(Y8*$AB$2) -> 0 | AC8: 1801 | AD8: =AC8-AC7 -> 0 | AE8: 357717.5 | AF8: =AE8-AE7 -> 0 | AG8: =IF(AD8>0,AF8/AD8,0) -> 0 | AH8: =AF8+AA8 -> 36.7 | AI8: =SUM(AH8+V8) -> 276.7 | AJ8: =-tanks!AW9 -> 276.7 | AK8: =SUM(AJ8-AI8) -> 0 | AL8: =S8+L8+G8 -> 4 | AM8: =Y8+AD8 -> 1 | AN8: 71 | AO8: =(AN8/100)*3000 -> 2130 | AP8: 71 | AQ8: =(AP8/100)*3000 -> 2130 | AR8: 72 | AS8: =(AR8/100)*3000 -> 2160 | AT8: =SUM(AO8+AQ8+AS8) -> 6420 | AU8: =AT7-AT8+AV8 -> 210 | AX8: =IF(AV8>0,AW8,AX7) -> 0.1
A9: =ELEC!C7 -> 43895 | B9: =B8 -> 213.3 | C9: =C8 -> 219.2 | D9: =C8-C9 -> 0 | E9: =D9*8.38 -> 0 | F9: =F8 -> 1459 | G9: =F9-F8 -> 0 | H9: =H8 -> 342878 | I9: =SUM(H9-H8) -> 0 | J9: =IF(G9>0,I9/G9,0) -> 0 | K9: =K8 -> 1846 | L9: =K9-K8 -> 0 | M9: =M8 -> 134906 | N9: =M9-M8 -> 0 | O9: =SUM(L9*$J$1) -> 0 | P9: =P8 -> 1681 | Q9: =Q8 -> 143671 | R9: =Q9-Q8 -> 0 | S9: =SUM(P9-P8) -> 0 | T9: =SUM(S9*$T$2) -> 0 | U9: =SUM(G9+L9+S9) -> 0 | V9: =R9+N9+I9:I9 -> 0 | W9: =SUM(V9/U9) -> #DIV/0! | X9: =X8 -> 2401 | Y9: =X9-X8 -> 0 | Z9: =Z8 -> 134951.9 | AA9: =Z9-Z8 -> 0 | AB9: =SUM(Y9*$AB$2) -> 0 | AC9: =AC8 -> 1801 | AD9: =AC9-AC8 -> 0 | AE9: =AE8 -> 357717.5 | AF9: =AE9-AE8 -> 0 | AG9: =IF(AD9>0,AF9/AD9,0) -> 0 | AH9: =AF9+AA9 -> 0 | AI9: =SUM(AH9+V9) -> 0 | AJ9: =-tanks!AW10 -> 0 | AK9: =SUM(AJ9-AI9) -> 0 | AL9: =S9+L9+G9 -> 0 | AM9: =Y9+AD9 -> 0 | AN9: =AN8 -> 71 | AO9: =(AN9/100)*3000 -> 2130 | AP9: =AP8 -> 71 | AQ9: =(AP9/100)*3000 -> 2130 | AR9: =AR8 -> 72 | AS9: =(AR9/100)*3000 -> 2160 | AT9: =SUM(AO9+AQ9+AS9) -> 6420 | AU9: =AT8-AT9+AV9 -> 0 | AX9: =IF(AV9>0,AW9,AX8) -> 0.1
A10: =ELEC!C8 -> 43896 | B10: =B9 -> 213.3 | C10: =C9 -> 219.2 | D10: =C9-C10 -> 0 | E10: =D10*8.38 -> 0 | F10: =F9 -> 1459 | G10: =F10-F9 -> 0 | H10: =H9 -> 342878 | I10: =SUM(H10-H9) -> 0 | J10: =IF(G10>0,I10/G10,0) -> 0 | K10: =K9 -> 1846 | L10: =K10-K9 -> 0 | M10: =M9 -> 134906 | N10: =M10-M9 -> 0 | O10: =SUM(L10*$J$1) -> 0 | P10: =P9 -> 1681 | Q10: =Q9 -> 143671 | R10: =Q10-Q9 -> 0 | S10: =SUM(P10-P9) -> 0 | T10: =SUM(S10*$T$2) -> 0 | U10: =SUM(G10+L10+S10) -> 0 | V10: =R10+N10+I10:I10 -> 0 | W10: =SUM(V10/U10) -> #DIV/0! | X10: =X9 -> 2401 | Y10: =X10-X9 -> 0 | Z10: =Z9 -> 134951.9 | AA10: =Z10-Z9 -> 0 | AB10: =SUM(Y10*$AB$2) -> 0 | AC10: =AC9 -> 1801 | AD10: =AC10-AC9 -> 0 | AE10: =AE9 -> 357717.5 | AF10: =AE10-AE9 -> 0 | AG10: =IF(AD10>0,AF10/AD10,0) -> 0 | AH10: =AF10+AA10 -> 0 | AI10: =SUM(AH10+V10) -> 0 | AJ10: =-tanks!AW11 -> 0 | AK10: =SUM(AJ10-AI10) -> 0 | AL10: =S10+L10+G10 -> 0 | AM10: =Y10+AD10 -> 0 | AN10: =AN9 -> 71 | AO10: =(AN10/100)*3000 -> 2130 | AP10: =AP9 -> 71 | AQ10: =(AP10/100)*3000 -> 2130 | AR10: =AR9 -> 72 | AS10: =(AR10/100)*3000 -> 2160 | AT10: =SUM(AO10+AQ10+AS10) -> 6420 | AU10: =AT9-AT10+AV10 -> 0 | AX10: =IF(AV10>0,AW10,AX9) -> 0.1
A11: =ELEC!C9 -> 43897 | B11: =B10 -> 213.3 | C11: =C10 -> 219.2 | D11: =C10-C11 -> 0 | E11: =D11*8.38 -> 0 | F11: =F10 -> 1459 | G11: =F11-F10 -> 0 | H11: =H10 -> 342878 | I11: =SUM(H11-H10) -> 0 | J11: =IF(G11>0,I11/G11,0) -> 0 | K11: =K10 -> 1846 | L11: =K11-K10 -> 0 | M11: =M10 -> 134906 | N11: =M11-M10 -> 0 | O11: =SUM(L11*$J$1) -> 0 | P11: =P10 -> 1681 | Q11: =Q10 -> 143671 | R11: =Q11-Q10 -> 0 | S11: =SUM(P11-P10) -> 0 | T11: =SUM(S11*$T$2) -> 0 | U11: =SUM(G11+L11+S11) -> 0 | V11: =R11+N11+I11:I11 -> 0 | W11: =SUM(V11/U11) -> #DIV/0! | X11: =X10 -> 2401 | Y11: =X11-X10 -> 0 | Z11: =Z10 -> 134951.9 | AA11: =Z11-Z10 -> 0 | AB11: =SUM(Y11*$AB$2) -> 0 | AC11: =AC10 -> 1801 | AD11: =AC11-AC10 -> 0 | AE11: =AE10 -> 357717.5 | AF11: =AE11-AE10 -> 0 | AG11: =IF(AD11>0,AF11/AD11,0) -> 0 | AH11: =AF11+AA11 -> 0 | AI11: =SUM(AH11+V11) -> 0 | AJ11: =-tanks!AW12 -> 0 | AK11: =SUM(AJ11-AI11) -> 0 | AL11: =S11+L11+G11 -> 0 | AM11: =Y11+AD11 -> 0 | AN11: =AN10 -> 71 | AO11: =(AN11/100)*3000 -> 2130 | AP11: =AP10 -> 71 | AQ11: =(AP11/100)*3000 -> 2130 | AR11: =AR10 -> 72 | AS11: =(AR11/100)*3000 -> 2160 | AT11: =SUM(AO11+AQ11+AS11) -> 6420 | AU11: =AT10-AT11+AV11 -> 0 | AX11: =IF(AV11>0,AW11,AX10) -> 0.1
A12: =ELEC!C10 -> 43898 | B12: =B11 -> 213.3 | C12: =C11 -> 219.2 | D12: =C11-C12 -> 0 | E12: =D12*8.38 -> 0 | F12: =F11 -> 1459 | G12: =F12-F11 -> 0 | H12: =H11 -> 342878 | I12: =SUM(H12-H11) -> 0 | J12: =IF(G12>0,I12/G12,0) -> 0 | K12: =K11 -> 1846 | L12: =K12-K11 -> 0 | M12: =M11 -> 134906 | N12: =M12-M11 -> 0 | O12: =SUM(L12*$J$1) -> 0 | P12: =P11 -> 1681 | Q12: =Q11 -> 143671 | R12: =Q12-Q11 -> 0 | S12: =SUM(P12-P11) -> 0 | T12: =SUM(S12*$T$2) -> 0 | U12: =SUM(G12+L12+S12) -> 0 | V12: =R12+N12+I12:I12 -> 0 | W12: =SUM(V12/U12) -> #DIV/0! | X12: =X11 -> 2401 | Y12: =X12-X11 -> 0 | Z12: =Z11 -> 134951.9 | AA12: =Z12-Z11 -> 0 | AB12: =SUM(Y12*$AB$2) -> 0 | AC12: =AC11 -> 1801 | AD12: =AC12-AC11 -> 0 | AE12: =AE11 -> 357717.5 | AF12: =AE12-AE11 -> 0 | AG12: =IF(AD12>0,AF12/AD12,0) -> 0 | AH12: =AF12+AA12 -> 0 | AI12: =SUM(AH12+V12) -> 0 | AJ12: =-tanks!AW13 -> 0 | AK12: =SUM(AJ12-AI12) -> 0 | AL12: =S12+L12+G12 -> 0 | AM12: =Y12+AD12 -> 0 | AN12: =AN11 -> 71 | AO12: =(AN12/100)*3000 -> 2130 | AP12: =AP11 -> 71 | AQ12: =(AP12/100)*3000 -> 2130 | AR12: =AR11 -> 72 | AS12: =(AR12/100)*3000 -> 2160 | AT12: =SUM(AO12+AQ12+AS12) -> 6420 | AU12: =AT11-AT12+AV12 -> 0 | AX12: =IF(AV12>0,AW12,AX11) -> 0.1
A13: =ELEC!C11 -> 43899 | B13: =B12 -> 213.3 | C13: =C12 -> 219.2 | D13: =C12-C13 -> 0 | E13: =D13*8.38 -> 0 | F13: =F12 -> 1459 | G13: =F13-F12 -> 0 | H13: =H12 -> 342878 | I13: =SUM(H13-H12) -> 0 | J13: =IF(G13>0,I13/G13,0) -> 0 | K13: =K12 -> 1846 | L13: =K13-K12 -> 0 | M13: =M12 -> 134906 | N13: =M13-M12 -> 0 | O13: =SUM(L13*$J$1) -> 0 | P13: =P12 -> 1681 | Q13: =Q12 -> 143671 | R13: =Q13-Q12 -> 0 | S13: =SUM(P13-P12) -> 0 | T13: =SUM(S13*$T$2) -> 0 | U13: =SUM(G13+L13+S13) -> 0 | V13: =R13+N13+I13:I13 -> 0 | W13: =SUM(V13/U13) -> #DIV/0! | X13: =X12 -> 2401 | Y13: =X13-X12 -> 0 | Z13: =Z12 -> 134951.9 | AA13: =Z13-Z12 -> 0 | AB13: =SUM(Y13*$AB$2) -> 0 | AC13: =AC12 -> 1801 | AD13: =AC13-AC12 -> 0 | AE13: =AE12 -> 357717.5 | AF13: =AE13-AE12 -> 0 | AG13: =IF(AD13>0,AF13/AD13,0) -> 0 | AH13: =AF13+AA13 -> 0 | AI13: =SUM(AH13+V13) -> 0 | AJ13: =-tanks!AW14 -> 0 | AK13: =SUM(AJ13-AI13) -> 0 | AL13: =S13+L13+G13 -> 0 | AM13: =Y13+AD13 -> 0 | AN13: =AN12 -> 71 | AO13: =(AN13/100)*3000 -> 2130 | AP13: =AP12 -> 71 | AQ13: =(AP13/100)*3000 -> 2130 | AR13: =AR12 -> 72 | AS13: =(AR13/100)*3000 -> 2160 | AT13: =SUM(AO13+AQ13+AS13) -> 6420 | AU13: =AT12-AT13+AV13 -> 0 | AX13: =IF(AV13>0,AW13,AX12) -> 0.1
A14: =ELEC!C12 -> 43900 | B14: =B13 -> 213.3 | C14: =C13 -> 219.2 | D14: =C13-C14 -> 0 | E14: =D14*8.38 -> 0 | F14: =F13 -> 1459 | G14: =F14-F13 -> 0 | H14: =H13 -> 342878 | I14: =SUM(H14-H13) -> 0 | J14: =IF(G14>0,I14/G14,0) -> 0 | K14: =K13 -> 1846 | L14: =K14-K13 -> 0 | M14: =M13 -> 134906 | N14: =M14-M13 -> 0 | O14: =SUM(L14*$J$1) -> 0 | P14: =P13 -> 1681 | Q14: =Q13 -> 143671 | R14: =Q14-Q13 -> 0 | S14: =SUM(P14-P13) -> 0 | T14: =SUM(S14*$T$2) -> 0 | U14: =SUM(G14+L14+S14) -> 0 | V14: =R14+N14+I14:I14 -> 0 | W14: =SUM(V14/U14) -> #DIV/0! | X14: =X13 -> 2401 | Y14: =X14-X13 -> 0 | Z14: =Z13 -> 134951.9 | AA14: =Z14-Z13 -> 0 | AB14: =SUM(Y14*$AB$2) -> 0 | AC14: =AC13 -> 1801 | AD14: =AC14-AC13 -> 0 | AE14: =AE13 -> 357717.5 | AF14: =AE14-AE13 -> 0 | AG14: =IF(AD14>0,AF14/AD14,0) -> 0 | AH14: =AF14+AA14 -> 0 | AI14: =SUM(AH14+V14) -> 0 | AJ14: =-tanks!AW15 -> 0 | AK14: =SUM(AJ14-AI14) -> 0 | AL14: =S14+L14+G14 -> 0 | AM14: =Y14+AD14 -> 0 | AN14: =AN13 -> 71 | AO14: =(AN14/100)*3000 -> 2130 | AP14: =AP13 -> 71 | AQ14: =(AP14/100)*3000 -> 2130 | AR14: =AR13 -> 72 | AS14: =(AR14/100)*3000 -> 2160 | AT14: =SUM(AO14+AQ14+AS14) -> 6420 | AU14: =AT13-AT14+AV14 -> 0 | AX14: =IF(AV14>0,AW14,AX13) -> 0.1
A15: =ELEC!C13 -> 43901 | B15: =B14 -> 213.3 | C15: =C14 -> 219.2 | D15: =C14-C15 -> 0 | E15: =D15*8.38 -> 0 | F15: =F14 -> 1459 | G15: =F15-F14 -> 0 | H15: =H14 -> 342878 | I15: =SUM(H15-H14) -> 0 | J15: =IF(G15>0,I15/G15,0) -> 0 | K15: =K14 -> 1846 | L15: =K15-K14 -> 0 | M15: =M14 -> 134906 | N15: =M15-M14 -> 0 | O15: =SUM(L15*$J$1) -> 0 | P15: =P14 -> 1681 | Q15: =Q14 -> 143671 | R15: =Q15-Q14 -> 0 | S15: =SUM(P15-P14) -> 0 | T15: =SUM(S15*$T$2) -> 0 | U15: =SUM(G15+L15+S15) -> 0 | V15: =R15+N15+I15:I15 -> 0 | W15: =SUM(V15/U15) -> #DIV/0! | X15: =X14 -> 2401 | Y15: =X15-X14 -> 0 | Z15: =Z14 -> 134951.9 | AA15: =Z15-Z14 -> 0 | AB15: =SUM(Y15*$AB$2) -> 0 | AC15: =AC14 -> 1801 | AD15: =AC15-AC14 -> 0 | AE15: =AE14 -> 357717.5 | AF15: =AE15-AE14 -> 0 | AG15: =IF(AD15>0,AF15/AD15,0) -> 0 | AH15: =AF15+AA15 -> 0 | AI15: =SUM(AH15+V15) -> 0 | AJ15: =-tanks!AW16 -> 0 | AK15: =SUM(AJ15-AI15) -> 0 | AL15: =S15+L15+G15 -> 0 | AM15: =Y15+AD15 -> 0 | AN15: =AN14 -> 71 | AO15: =(AN15/100)*3000 -> 2130 | AP15: =AP14 -> 71 | AQ15: =(AP15/100)*3000 -> 2130 | AR15: =AR14 -> 72 | AS15: =(AR15/100)*3000 -> 2160 | AT15: =SUM(AO15+AQ15+AS15) -> 6420 | AU15: =AT14-AT15+AV15 -> 0 | AX15: =IF(AV15>0,AW15,AX14) -> 0.1
A16: =ELEC!C14 -> 43902 | B16: =B15 -> 213.3 | C16: =C15 -> 219.2 | D16: =C15-C16 -> 0 | E16: =D16*8.38 -> 0 | F16: =F15 -> 1459 | G16: =F16-F15 -> 0 | H16: =H15 -> 342878 | I16: =SUM(H16-H15) -> 0 | J16: =IF(G16>0,I16/G16,0) -> 0 | K16: =K15 -> 1846 | L16: =K16-K15 -> 0 | M16: =M15 -> 134906 | N16: =M16-M15 -> 0 | O16: =SUM(L16*$J$1) -> 0 | P16: =P15 -> 1681 | Q16: =Q15 -> 143671 | R16: =Q16-Q15 -> 0 | S16: =SUM(P16-P15) -> 0 | T16: =SUM(S16*$T$2) -> 0 | U16: =SUM(G16+L16+S16) -> 0 | V16: =R16+N16+I16:I16 -> 0 | W16: =SUM(V16/U16) -> #DIV/0! | X16: =X15 -> 2401 | Y16: =X16-X15 -> 0 | Z16: =Z15 -> 134951.9 | AA16: =Z16-Z15 -> 0 | AB16: =SUM(Y16*$AB$2) -> 0 | AC16: =AC15 -> 1801 | AD16: =AC16-AC15 -> 0 | AE16: =AE15 -> 357717.5 | AF16: =AE16-AE15 -> 0 | AG16: =IF(AD16>0,AF16/AD16,0) -> 0 | AH16: =AF16+AA16 -> 0 | AI16: =SUM(AH16+V16) -> 0 | AJ16: =-tanks!AW17 -> 0 | AK16: =SUM(AJ16-AI16) -> 0 | AL16: =S16+L16+G16 -> 0 | AM16: =Y16+AD16 -> 0 | AN16: =AN15 -> 71 | AO16: =(AN16/100)*3000 -> 2130 | AP16: =AP15 -> 71 | AQ16: =(AP16/100)*3000 -> 2130 | AR16: =AR15 -> 72 | AS16: =(AR16/100)*3000 -> 2160 | AT16: =SUM(AO16+AQ16+AS16) -> 6420 | AU16: =AT15-AT16+AV16 -> 0 | AX16: =IF(AV16>0,AW16,AX15) -> 0.1
A17: =ELEC!C15 -> 43903 | B17: =B16 -> 213.3 | C17: =C16 -> 219.2 | D17: =C16-C17 -> 0 | E17: =D17*8.38 -> 0 | F17: =F16 -> 1459 | G17: =F17-F16 -> 0 | H17: =H16 -> 342878 | I17: =SUM(H17-H16) -> 0 | J17: =IF(G17>0,I17/G17,0) -> 0 | K17: =K16 -> 1846 | L17: =K17-K16 -> 0 | M17: =M16 -> 134906 | N17: =M17-M16 -> 0 | O17: =SUM(L17*$J$1) -> 0 | P17: =P16 -> 1681 | Q17: =Q16 -> 143671 | R17: =Q17-Q16 -> 0 | S17: =SUM(P17-P16) -> 0 | T17: =SUM(S17*$T$2) -> 0 | U17: =SUM(G17+L17+S17) -> 0 | V17: =R17+N17+I17:I17 -> 0 | X17: =X16 -> 2401 | Y17: =X17-X16 -> 0 | Z17: =Z16 -> 134951.9 | AA17: =Z17-Z16 -> 0 | AB17: =SUM(Y17*$AB$2) -> 0 | AC17: =AC16 -> 1801 | AD17: =AC17-AC16 -> 0 | AE17: =AE16 -> 357717.5 | AF17: =AE17-AE16 -> 0 | AG17: =IF(AD17>0,AF17/AD17,0) -> 0 | AH17: =AF17+AA17 -> 0 | AI17: =SUM(AH17+V17) -> 0 | AJ17: =-tanks!AW18 -> 0 | AK17: =SUM(AJ17-AI17) -> 0 | AL17: =S17+L17+G17 -> 0 | AM17: =Y17+AD17 -> 0 | AN17: =AN16 -> 71 | AO17: =(AN17/100)*3000 -> 2130 | AP17: =AP16 -> 71 | AQ17: =(AP17/100)*3000 -> 2130 | AR17: =AR16 -> 72 | AS17: =(AR17/100)*3000 -> 2160 | AT17: =SUM(AO17+AQ17+AS17) -> 6420 | AU17: =AT16-AT17+AV17 -> 0 | AX17: =IF(AV17>0,AW17,AX16) -> 0.1
A18: =ELEC!C16 -> 43904 | B18: =B17 -> 213.3 | C18: =C17 -> 219.2 | D18: =C17-C18 -> 0 | E18: =D18*8.38 -> 0 | F18: =F17 -> 1459 | G18: =F18-F17 -> 0 | H18: =H17 -> 342878 | I18: =SUM(H18-H17) -> 0 | J18: =IF(G18>0,I18/G18,0) -> 0 | K18: =K17 -> 1846 | L18: =K18-K17 -> 0 | M18: =M17 -> 134906 | N18: =M18-M17 -> 0 | O18: =SUM(L18*$J$1) -> 0 | P18: =P17 -> 1681 | Q18: =Q17 -> 143671 | R18: =Q18-Q17 -> 0 | S18: =SUM(P18-P17) -> 0 | T18: =SUM(S18*$T$2) -> 0 | U18: =SUM(G18+L18+S18) -> 0 | V18: =R18+N18+I18:I18 -> 0 | X18: =X17 -> 2401 | Y18: =X18-X17 -> 0 | Z18: =Z17 -> 134951.9 | AA18: =Z18-Z17 -> 0 | AB18: =SUM(Y18*$AB$2) -> 0 | AC18: =AC17 -> 1801 | AD18: =AC18-AC17 -> 0 | AE18: =AE17 -> 357717.5 | AF18: =AE18-AE17 -> 0 | AG18: =IF(AD18>0,AF18/AD18,0) -> 0 | AH18: =AF18+AA18 -> 0 | AI18: =SUM(AH18+V18) -> 0 | AJ18: =-tanks!AW19 -> 0 | AK18: =SUM(AJ18-AI18) -> 0 | AL18: =S18+L18+G18 -> 0 | AM18: =Y18+AD18 -> 0 | AN18: =AN17 -> 71 | AO18: =(AN18/100)*3000 -> 2130 | AP18: =AP17 -> 71 | AQ18: =(AP18/100)*3000 -> 2130 | AR18: =AR17 -> 72 | AS18: =(AR18/100)*3000 -> 2160 | AT18: =SUM(AO18+AQ18+AS18) -> 6420 | AU18: =AT17-AT18+AV18 -> 0 | AX18: =IF(AV18>0,AW18,AX17) -> 0.1
A19: =ELEC!C17 -> 43905 | B19: =B18 -> 213.3 | C19: =C18 -> 219.2 | D19: =C18-C19 -> 0 | E19: =D19*8.38 -> 0 | F19: =F18 -> 1459 | G19: =F19-F18 -> 0 | H19: =H18 -> 342878 | I19: =SUM(H19-H18) -> 0 | J19: =IF(G19>0,I19/G19,0) -> 0 | K19: =K18 -> 1846 | L19: =K19-K18 -> 0 | M19: =M18 -> 134906 | N19: =M19-M18 -> 0 | O19: =SUM(L19*$J$1) -> 0 | P19: =P18 -> 1681 | Q19: =Q18 -> 143671 | R19: =Q19-Q18 -> 0 | S19: =SUM(P19-P18) -> 0 | T19: =SUM(S19*$T$2) -> 0 | U19: =SUM(G19+L19+S19) -> 0 | V19: =R19+N19+I19:I19 -> 0 | X19: =X18 -> 2401 | Y19: =X19-X18 -> 0 | Z19: =Z18 -> 134951.9 | AA19: =Z19-Z18 -> 0 | AB19: =SUM(Y19*$AB$2) -> 0 | AC19: =AC18 -> 1801 | AD19: =AC19-AC18 -> 0 | AE19: =AE18 -> 357717.5 | AF19: =AE19-AE18 -> 0 | AG19: =IF(AD19>0,AF19/AD19,0) -> 0 | AH19: =AF19+AA19 -> 0 | AI19: =SUM(AH19+V19) -> 0 | AJ19: =-tanks!AW20 -> 0 | AK19: =SUM(AJ19-AI19) -> 0 | AL19: =S19+L20+G19 -> 0 | AM19: =Y19+AD19 -> 0 | AN19: =AN18 -> 71 | AO19: =(AN19/100)*3000 -> 2130 | AP19: =AP18 -> 71 | AQ19: =(AP19/100)*3000 -> 2130 | AR19: =AR18 -> 72 | AS19: =(AR19/100)*3000 -> 2160 | AT19: =SUM(AO19+AQ19+AS19) -> 6420 | AU19: =AT18-AT19+AV19 -> 0 | AX19: =IF(AV19>0,AW19,AX18) -> 0.1
A20: =ELEC!C18 -> 43906 | B20: =B19 -> 213.3 | C20: =C19 -> 219.2 | D20: =C19-C20 -> 0 | E20: =D20*8.38 -> 0 | F20: =F19 -> 1459 | G20: =F20-F19 -> 0 | H20: =H19 -> 342878 | I20: =SUM(H20-H19) -> 0 | J20: =IF(G20>0,I20/G20,0) -> 0 | K20: =K19 -> 1846 | L20: =K20-K19 -> 0 | M20: =M19 -> 134906 | N20: =M20-M19 -> 0 | O20: =SUM(L20*$J$1) -> 0 | P20: =P19 -> 1681 | Q20: =Q19 -> 143671 | R20: =Q20-Q19 -> 0 | S20: =SUM(P20-P19) -> 0 | T20: =SUM(S20*$T$2) -> 0 | U20: =SUM(G20+L20+S20) -> 0 | V20: =R20+N20+I20:I20 -> 0 | X20: =X19 -> 2401 | Y20: =X20-X19 -> 0 | Z20: =Z19 -> 134951.9 | AA20: =Z20-Z19 -> 0 | AB20: =SUM(Y20*$AB$2) -> 0 | AC20: =AC19 -> 1801 | AD20: =AC20-AC19 -> 0 | AE20: =AE19 -> 357717.5 | AF20: =AE20-AE19 -> 0 | AG20: =IF(AD20>0,AF20/AD20,0) -> 0 | AH20: =AF20+AA20 -> 0 | AI20: =SUM(AH20+V20) -> 0 | AJ20: =-tanks!AW21 -> 0 | AK20: =SUM(AJ20-AI20) -> 0 | AL20: =S20+L21+G20 -> 0 | AM20: =Y20+AD20 -> 0 | AN20: =AN19 -> 71 | AO20: =(AN20/100)*3000 -> 2130 | AP20: =AP19 -> 71 | AQ20: =(AP20/100)*3000 -> 2130 | AR20: =AR19 -> 72 | AS20: =(AR20/100)*3000 -> 2160 | AT20: =SUM(AO20+AQ20+AS20) -> 6420 | AU20: =AT19-AT20+AV20 -> 0 | AX20: =IF(AV20>0,AW20,AX19) -> 0.1
A21: =ELEC!C19 -> 43907 | B21: =B20 -> 213.3 | C21: =C20 -> 219.2 | D21: =C20-C21 -> 0 | E21: =D21*8.38 -> 0 | F21: =F20 -> 1459 | G21: =F21-F20 -> 0 | H21: =H20 -> 342878 | I21: =SUM(H21-H20) -> 0 | J21: =IF(G21>0,I21/G21,0) -> 0 | K21: =K20 -> 1846 | L21: =K21-K20 -> 0 | M21: =M20 -> 134906 | N21: =M21-M20 -> 0 | O21: =SUM(L21*$J$1) -> 0 | P21: =P20 -> 1681 | Q21: =Q20 -> 143671 | R21: =Q21-Q20 -> 0 | S21: =SUM(P21-P20) -> 0 | T21: =SUM(S21*$T$2) -> 0 | U21: =SUM(G21+L21+S21) -> 0 | V21: =R21+N21+I21:I21 -> 0 | X21: =X20 -> 2401 | Y21: =X21-X20 -> 0 | Z21: =Z20 -> 134951.9 | AA21: =Z21-Z20 -> 0 | AB21: =SUM(Y21*$AB$2) -> 0 | AC21: =AC20 -> 1801 | AD21: =AC21-AC20 -> 0 | AE21: =AE20 -> 357717.5 | AF21: =AE21-AE20 -> 0 | AG21: =IF(AD21>0,AF21/AD21,0) -> 0 | AH21: =AF21+AA21 -> 0 | AI21: =SUM(AH21+V21) -> 0 | AJ21: =-tanks!AW22 -> 0 | AK21: =SUM(AJ21-AI21) -> 0 | AL21: =S21+L21+G21 -> 0 | AM21: =Y21+AD21 -> 0 | AN21: =AN20 -> 71 | AO21: =(AN21/100)*3000 -> 2130 | AP21: =AP20 -> 71 | AQ21: =(AP21/100)*3000 -> 2130 | AR21: =AR20 -> 72 | AS21: =(AR21/100)*3000 -> 2160 | AT21: =SUM(AO21+AQ21+AS21) -> 6420 | AU21: =AT20-AT21+AV21 -> 0 | AX21: =IF(AV21>0,AW21,AX20) -> 0.1
A22: =ELEC!C20 -> 43908 | B22: =B21 -> 213.3 | C22: =C21 -> 219.2 | D22: =C21-C22 -> 0 | E22: =D22*8.38 -> 0 | F22: =F21 -> 1459 | G22: =F22-F21 -> 0 | H22: =H21 -> 342878 | I22: =SUM(H22-H21) -> 0 | J22: =IF(G22>0,I22/G22,0) -> 0 | K22: =K21 -> 1846 | L22: =K22-K21 -> 0 | M22: =M21 -> 134906 | N22: =M22-M21 -> 0 | O22: =SUM(L22*$J$1) -> 0 | P22: =P21 -> 1681 | Q22: =Q21 -> 143671 | R22: =Q22-Q21 -> 0 | S22: =SUM(P22-P21) -> 0 | T22: =SUM(S22*$T$2) -> 0 | U22: =SUM(G22+L22+S22) -> 0 | V22: =R22+N22+I22:I22 -> 0 | X22: =X21 -> 2401 | Y22: =X22-X21 -> 0 | Z22: =Z21 -> 134951.9 | AA22: =Z22-Z21 -> 0 | AB22: =SUM(Y22*$AB$2) -> 0 | AC22: =AC21 -> 1801 | AD22: =AC22-AC21 -> 0 | AE22: =AE21 -> 357717.5 | AF22: =AE22-AE21 -> 0 | AG22: =IF(AD22>0,AF22/AD22,0) -> 0 | AH22: =AF22+AA22 -> 0 | AI22: =SUM(AH22+V22) -> 0 | AJ22: =-tanks!AW23 -> 0 | AK22: =SUM(AJ22-AI22) -> 0 | AL22: =S22+L22+G22 -> 0 | AM22: =Y22+AD22 -> 0 | AN22: =AN21 -> 71 | AO22: =(AN22/100)*3000 -> 2130 | AP22: =AP21 -> 71 | AQ22: =(AP22/100)*3000 -> 2130 | AR22: =AR21 -> 72 | AS22: =(AR22/100)*3000 -> 2160 | AT22: =SUM(AO22+AQ22+AS22) -> 6420 | AU22: =AT21-AT22+AV22 -> 0 | AX22: =IF(AV22>0,AW22,AX21) -> 0.1
A23: =ELEC!C21 -> 43909 | B23: =B22 -> 213.3 | C23: =C22 -> 219.2 | D23: =C22-C23 -> 0 | E23: =D23*8.38 -> 0 | F23: =F22 -> 1459 | G23: =F23-F22 -> 0 | H23: =H22 -> 342878 | I23: =SUM(H23-H22) -> 0 | J23: =IF(G23>0,I23/G23,0) -> 0 | K23: =K22 -> 1846 | L23: =K23-K22 -> 0 | M23: =M22 -> 134906 | N23: =M23-M22 -> 0 | O23: =SUM(L23*$J$1) -> 0 | P23: =P22 -> 1681 | Q23: =Q22 -> 143671 | R23: =Q23-Q22 -> 0 | S23: =SUM(P23-P22) -> 0 | T23: =SUM(S23*$T$2) -> 0 | U23: =SUM(G23+L23+S23) -> 0 | V23: =R23+N23+I23:I23 -> 0 | X23: =X22 -> 2401 | Y23: =X23-X22 -> 0 | Z23: =Z22 -> 134951.9 | AA23: =Z23-Z22 -> 0 | AB23: =SUM(Y23*$AB$2) -> 0 | AC23: =AC22 -> 1801 | AD23: =AC23-AC22 -> 0 | AE23: =AE22 -> 357717.5 | AF23: =AE23-AE22 -> 0 | AG23: =IF(AD23>0,AF23/AD23,0) -> 0 | AH23: =AF23+AA23 -> 0 | AI23: =SUM(AH23+V23) -> 0 | AJ23: =-tanks!AW24 -> 0 | AK23: =SUM(AJ23-AI23) -> 0 | AL23: =S23+L23+G23 -> 0 | AM23: =Y23+AD23 -> 0 | AN23: =AN22 -> 71 | AO23: =(AN23/100)*3000 -> 2130 | AP23: =AP22 -> 71 | AQ23: =(AP23/100)*3000 -> 2130 | AR23: =AR22 -> 72 | AS23: =(AR23/100)*3000 -> 2160 | AT23: =SUM(AO23+AQ23+AS23) -> 6420 | AU23: =AT22-AT23+AV23 -> 0 | AX23: =IF(AV23>0,AW23,AX22) -> 0.1
A24: =ELEC!C22 -> 43910 | B24: =B23 -> 213.3 | C24: =C23 -> 219.2 | D24: =C23-C24 -> 0 | E24: =D24*8.38 -> 0 | F24: =F23 -> 1459 | G24: =F24-F23 -> 0 | H24: =H23 -> 342878 | I24: =SUM(H24-H23) -> 0 | J24: =IF(G24>0,I24/G24,0) -> 0 | K24: =K23 -> 1846 | L24: =K24-K23 -> 0 | M24: =M23 -> 134906 | N24: =M24-M23 -> 0 | O24: =SUM(L24*$J$1) -> 0 | P24: =P23 -> 1681 | Q24: =Q23 -> 143671 | R24: =Q24-Q23 -> 0 | S24: =SUM(P24-P23) -> 0 | T24: =SUM(S24*$T$2) -> 0 | U24: =SUM(G24+L24+S24) -> 0 | V24: =R24+N24+I24:I24 -> 0 | X24: =X23 -> 2401 | Y24: =X24-X23 -> 0 | Z24: =Z23 -> 134951.9 | AA24: =Z24-Z23 -> 0 | AB24: =SUM(Y24*$AB$2) -> 0 | AC24: =AC23 -> 1801 | AD24: =AC24-AC23 -> 0 | AE24: =AE23 -> 357717.5 | AF24: =AE24-AE23 -> 0 | AG24: =IF(AD24>0,AF24/AD24,0) -> 0 | AH24: =AF24+AA24 -> 0 | AI24: =SUM(AH24+V24) -> 0 | AJ24: =-tanks!AW25 -> 0 | AK24: =SUM(AJ24-AI24) -> 0 | AL24: =S24+L24+G24 -> 0 | AM24: =Y24+AD24 -> 0 | AN24: =AN23 -> 71 | AO24: =(AN24/100)*3000 -> 2130 | AP24: =AP23 -> 71 | AQ24: =(AP24/100)*3000 -> 2130 | AR24: =AR23 -> 72 | AS24: =(AR24/100)*3000 -> 2160 | AT24: =SUM(AO24+AQ24+AS24) -> 6420 | AU24: =AT23-AT24+AV24 -> 0 | AX24: =IF(AV24>0,AW24,AX23) -> 0.1
A25: =ELEC!C23 -> 43911 | B25: =B24 -> 213.3 | C25: =C24 -> 219.2 | D25: =C24-C25 -> 0 | E25: =D25*8.38 -> 0 | F25: =F24 -> 1459 | G25: =F25-F24 -> 0 | H25: =H24 -> 342878 | I25: =SUM(H25-H24) -> 0 | J25: =IF(G25>0,I25/G25,0) -> 0 | K25: =K24 -> 1846 | L25: =K25-K24 -> 0 | M25: =M24 -> 134906 | N25: =M25-M24 -> 0 | O25: =SUM(L25*$J$1) -> 0 | P25: =P24 -> 1681 | Q25: =Q24 -> 143671 | R25: =Q25-Q24 -> 0 | S25: =SUM(P25-P24) -> 0 | T25: =SUM(S25*$T$2) -> 0 | U25: =SUM(G25+L25+S25) -> 0 | V25: =R25+N25+I25:I25 -> 0 | X25: =X24 -> 2401 | Y25: =X25-X24 -> 0 | Z25: =Z24 -> 134951.9 | AA25: =Z25-Z24 -> 0 | AB25: =SUM(Y25*$AB$2) -> 0 | AC25: =AC24 -> 1801 | AD25: =AC25-AC24 -> 0 | AE25: =AE24 -> 357717.5 | AF25: =AE25-AE24 -> 0 | AG25: =IF(AD25>0,AF25/AD25,0) -> 0 | AH25: =AF25+AA25 -> 0 | AI25: =SUM(AH25+V25) -> 0 | AJ25: =-tanks!AW26 -> 0 | AK25: =SUM(AJ25-AI25) -> 0 | AL25: =S25+L25+G25 -> 0 | AM25: =Y25+AD25 -> 0 | AN25: =AN24 -> 71 | AO25: =(AN25/100)*3000 -> 2130 | AP25: =AP24 -> 71 | AQ25: =(AP25/100)*3000 -> 2130 | AR25: =AR24 -> 72 | AS25: =(AR25/100)*3000 -> 2160 | AT25: =SUM(AO25+AQ25+AS25) -> 6420 | AU25: =AT24-AT25+AV25 -> 0 | AX25: =IF(AV25>0,AW25,AX24) -> 0.1
A26: =ELEC!C24 -> 43912 | B26: =B25 -> 213.3 | C26: =C25 -> 219.2 | D26: =C25-C26 -> 0 | E26: =D26*8.38 -> 0 | F26: =F25 -> 1459 | G26: =F26-F25 -> 0 | H26: =H25 -> 342878 | I26: =SUM(H26-H25) -> 0 | J26: =IF(G26>0,I26/G26,0) -> 0 | K26: =K25 -> 1846 | L26: =K26-K25 -> 0 | M26: =M25 -> 134906 | N26: =M26-M25 -> 0 | O26: =SUM(L26*$J$1) -> 0 | P26: =P25 -> 1681 | Q26: =Q25 -> 143671 | R26: =Q26-Q25 -> 0 | S26: =SUM(P26-P25) -> 0 | T26: =SUM(S26*$T$2) -> 0 | U26: =SUM(G26+L26+S26) -> 0 | V26: =R26+N26+I26:I26 -> 0 | X26: =X25 -> 2401 | Y26: =X26-X25 -> 0 | Z26: =Z25 -> 134951.9 | AA26: =Z26-Z25 -> 0 | AB26: =SUM(Y26*$AB$2) -> 0 | AC26: =AC25 -> 1801 | AD26: =AC26-AC25 -> 0 | AE26: =AE25 -> 357717.5 | AF26: =AE26-AE25 -> 0 | AG26: =IF(AD26>0,AF26/AD26,0) -> 0 | AH26: =AF26+AA26 -> 0 | AI26: =SUM(AH26+V26) -> 0 | AJ26: =-tanks!AW27 -> 0 | AK26: =SUM(AJ26-AI26) -> 0 | AL26: =S26+L26+G26 -> 0 | AM26: =Y26+AD26 -> 0 | AN26: =AN25 -> 71 | AO26: =(AN26/100)*3000 -> 2130 | AP26: =AP25 -> 71 | AQ26: =(AP26/100)*3000 -> 2130 | AR26: =AR25 -> 72 | AS26: =(AR26/100)*3000 -> 2160 | AT26: =SUM(AO26+AQ26+AS26) -> 6420 | AU26: =AT25-AT26+AV26 -> 0 | AX26: =IF(AV26>0,AW26,AX25) -> 0.1
A27: =ELEC!C25 -> 43913 | B27: =B26 -> 213.3 | C27: =C26 -> 219.2 | D27: =C26-C27 -> 0 | E27: =D27*8.38 -> 0 | F27: =F26 -> 1459 | G27: =F27-F26 -> 0 | H27: =H26 -> 342878 | I27: =SUM(H27-H26) -> 0 | J27: =IF(G27>0,I27/G27,0) -> 0 | K27: =K26 -> 1846 | L27: =K27-K26 -> 0 | M27: =M26 -> 134906 | N27: =M27-M26 -> 0 | O27: =SUM(L27*$J$1) -> 0 | P27: =P26 -> 1681 | Q27: =Q26 -> 143671 | R27: =Q27-Q26 -> 0 | S27: =SUM(P27-P26) -> 0 | T27: =SUM(S27*$T$2) -> 0 | U27: =SUM(G27+L27+S27) -> 0 | V27: =R27+N27+I27:I27 -> 0 | X27: =X26 -> 2401 | Y27: =X27-X26 -> 0 | Z27: =Z26 -> 134951.9 | AA27: =Z27-Z26 -> 0 | AB27: =SUM(Y27*$AB$2) -> 0 | AC27: =AC26 -> 1801 | AD27: =AC27-AC26 -> 0 | AE27: =AE26 -> 357717.5 | AF27: =AE27-AE26 -> 0 | AG27: =IF(AD27>0,AF27/AD27,0) -> 0 | AH27: =AF27+AA27 -> 0 | AI27: =SUM(AH27+V27) -> 0 | AJ27: =-tanks!AW28 -> 0 | AK27: =SUM(AJ27-AI27) -> 0 | AL27: =S27+L27+G27 -> 0 | AM27: =Y27+AD27 -> 0 | AN27: =AN26 -> 71 | AO27: =(AN27/100)*3000 -> 2130 | AP27: =AP26 -> 71 | AQ27: =(AP27/100)*3000 -> 2130 | AR27: =AR26 -> 72 | AS27: =(AR27/100)*3000 -> 2160 | AT27: =SUM(AO27+AQ27+AS27) -> 6420 | AU27: =AT26-AT27+AV27 -> 0 | AX27: =IF(AV27>0,AW27,AX26) -> 0.1
A28: =ELEC!C26 -> 43914 | B28: =B27 -> 213.3 | C28: =C27 -> 219.2 | D28: =C27-C28 -> 0 | E28: =D28*8.38 -> 0 | F28: =F27 -> 1459 | G28: =F28-F27 -> 0 | H28: =H27 -> 342878 | I28: =SUM(H28-H27) -> 0 | J28: =IF(G28>0,I28/G28,0) -> 0 | K28: =K27 -> 1846 | L28: =K28-K27 -> 0 | M28: =M27 -> 134906 | N28: =M28-M27 -> 0 | O28: =SUM(L28*$J$1) -> 0 | P28: =P27 -> 1681 | Q28: =Q27 -> 143671 | R28: =Q28-Q27 -> 0 | S28: =SUM(P28-P27) -> 0 | T28: =SUM(S28*$T$2) -> 0 | U28: =SUM(G28+L28+S28) -> 0 | V28: =R28+N28+I28:I28 -> 0 | X28: =X27 -> 2401 | Y28: =X28-X27 -> 0 | Z28: =Z27 -> 134951.9 | AA28: =Z28-Z27 -> 0 | AB28: =SUM(Y28*$AB$2) -> 0 | AC28: =AC27 -> 1801 | AD28: =AC28-AC27 -> 0 | AE28: =AE27 -> 357717.5 | AF28: =AE28-AE27 -> 0 | AG28: =IF(AD28>0,AF28/AD28,0) -> 0 | AH28: =AF28+AA28 -> 0 | AI28: =SUM(AH28+V28) -> 0 | AJ28: =-tanks!AW29 -> 0 | AK28: =SUM(AJ28-AI28) -> 0 | AL28: =S28+L28+G28 -> 0 | AM28: =Y28+AD28 -> 0 | AN28: =AN27 -> 71 | AO28: =(AN28/100)*3000 -> 2130 | AP28: =AP27 -> 71 | AQ28: =(AP28/100)*3000 -> 2130 | AR28: =AR27 -> 72 | AS28: =(AR28/100)*3000 -> 2160 | AT28: =SUM(AO28+AQ28+AS28) -> 6420 | AU28: =AT27-AT28+AV28 -> 0 | AX28: =IF(AV28>0,AW28,AX27) -> 0.1
A29: =ELEC!C27 -> 43915 | B29: =B28 -> 213.3 | C29: =C28 -> 219.2 | D29: =C28-C29 -> 0 | E29: =D29*8.38 -> 0 | F29: =F28 -> 1459 | G29: =F29-F28 -> 0 | H29: =H28 -> 342878 | I29: =SUM(H29-H28) -> 0 | J29: =IF(G29>0,I29/G29,0) -> 0 | K29: =K28 -> 1846 | L29: =K29-K28 -> 0 | M29: =M28 -> 134906 | N29: =M29-M28 -> 0 | O29: =SUM(L29*$J$1) -> 0 | P29: =P28 -> 1681 | Q29: =Q28 -> 143671 | R29: =Q29-Q28 -> 0 | S29: =SUM(P29-P28) -> 0 | T29: =SUM(S29*$T$2) -> 0 | U29: =SUM(G29+L29+S29) -> 0 | V29: =R29+N29+I29:I29 -> 0 | X29: =X28 -> 2401 | Y29: =X29-X28 -> 0 | Z29: =Z28 -> 134951.9 | AA29: =Z29-Z28 -> 0 | AB29: =SUM(Y29*$AB$2) -> 0 | AC29: =AC28 -> 1801 | AD29: =AC29-AC28 -> 0 | AE29: =AE28 -> 357717.5 | AF29: =AE29-AE28 -> 0 | AG29: =IF(AD29>0,AF29/AD29,0) -> 0 | AH29: =AF29+AA29 -> 0 | AI29: =SUM(AH29+V29) -> 0 | AJ29: =-tanks!AW30 -> 0 | AK29: =SUM(AJ29-AI29) -> 0 | AL29: =S29+L29+G29 -> 0 | AM29: =Y29+AD29 -> 0 | AN29: =AN28 -> 71 | AO29: =(AN29/100)*3000 -> 2130 | AP29: =AP28 -> 71 | AQ29: =(AP29/100)*3000 -> 2130 | AR29: =AR28 -> 72 | AS29: =(AR29/100)*3000 -> 2160 | AT29: =SUM(AO29+AQ29+AS29) -> 6420 | AU29: =AT28-AT29+AV29 -> 0 | AX29: =IF(AV29>0,AW29,AX28) -> 0.1
A30: =ELEC!C28 -> 43916 | B30: =B29 -> 213.3 | C30: =C29 -> 219.2 | D30: =C29-C30 -> 0 | E30: =D30*8.38 -> 0 | F30: =F29 -> 1459 | G30: =F30-F29 -> 0 | H30: =H29 -> 342878 | I30: =SUM(H30-H29) -> 0 | J30: =IF(G30>0,I30/G30,0) -> 0 | K30: =K29 -> 1846 | L30: =K30-K29 -> 0 | M30: =M29 -> 134906 | N30: =M30-M29 -> 0 | O30: =SUM(L30*$J$1) -> 0 | P30: =P29 -> 1681 | Q30: =Q29 -> 143671 | R30: =Q30-Q29 -> 0 | S30: =SUM(P30-P29) -> 0 | T30: =SUM(S30*$T$2) -> 0 | U30: =SUM(G30+L30+S30) -> 0 | V30: =R30+N30+I30:I30 -> 0 | X30: =X29 -> 2401 | Y30: =X30-X29 -> 0 | Z30: =Z29 -> 134951.9 | AA30: =Z30-Z29 -> 0 | AB30: =SUM(Y30*$AB$2) -> 0 | AC30: =AC29 -> 1801 | AD30: =AC30-AC29 -> 0 | AE30: =AE29 -> 357717.5 | AF30: =AE30-AE29 -> 0 | AG30: =IF(AD30>0,AF30/AD30,0) -> 0 | AH30: =AF30+AA30 -> 0 | AI30: =SUM(AH30+V30) -> 0 | AJ30: =-tanks!AW31 -> 0 | AK30: =SUM(AJ30-AI30) -> 0 | AL30: =S30+L30+G30 -> 0 | AM30: =Y30+AD30 -> 0 | AN30: =AN29 -> 71 | AO30: =(AN30/100)*3000 -> 2130 | AP30: =AP29 -> 71 | AQ30: =(AP30/100)*3000 -> 2130 | AR30: =AR29 -> 72 | AS30: =(AR30/100)*3000 -> 2160 | AT30: =SUM(AO30+AQ30+AS30) -> 6420 | AU30: =AT29-AT30+AV30 -> 0 | AX30: =IF(AV30>0,AW30,AX29) -> 0.1
A31: =ELEC!C29 -> 43917 | B31: =B30 -> 213.3 | C31: =C30 -> 219.2 | D31: =C30-C31 -> 0 | E31: =D31*8.38 -> 0 | F31: =F30 -> 1459 | G31: =F31-F30 -> 0 | H31: =H30 -> 342878 | I31: =SUM(H31-H30) -> 0 | J31: =IF(G31>0,I31/G31,0) -> 0 | K31: =K30 -> 1846 | L31: =K31-K30 -> 0 | M31: =M30 -> 134906 | N31: =M31-M30 -> 0 | O31: =SUM(L31*$J$1) -> 0 | P31: =P30 -> 1681 | Q31: =Q30 -> 143671 | R31: =Q31-Q30 -> 0 | S31: =SUM(P31-P30) -> 0 | T31: =SUM(S31*$T$2) -> 0 | U31: =SUM(G31+L31+S31) -> 0 | V31: =R31+N31+I31:I31 -> 0 | X31: =X30 -> 2401 | Y31: =X31-X30 -> 0 | Z31: =Z30 -> 134951.9 | AA31: =Z31-Z30 -> 0 | AB31: =SUM(Y31*$AB$2) -> 0 | AC31: =AC30 -> 1801 | AD31: =AC31-AC30 -> 0 | AE31: =AE30 -> 357717.5 | AF31: =AE31-AE30 -> 0 | AG31: =IF(AD31>0,AF31/AD31,0) -> 0 | AH31: =AF31+AA31 -> 0 | AI31: =SUM(AH31+V31) -> 0 | AJ31: =-tanks!AW32 -> 0 | AK31: =SUM(AJ31-AI31) -> 0 | AL31: =S31+L31+G31 -> 0 | AM31: =Y31+AD31 -> 0 | AN31: =AN30 -> 71 | AO31: =(AN31/100)*3000 -> 2130 | AP31: =AP30 -> 71 | AQ31: =(AP31/100)*3000 -> 2130 | AR31: =AR30 -> 72 | AS31: =(AR31/100)*3000 -> 2160 | AT31: =SUM(AO31+AQ31+AS31) -> 6420 | AU31: =AT30-AT31+AV31 -> 0 | AX31: =IF(AV31>0,AW31,AX30) -> 0.1
A32: =ELEC!C30 -> 43918 | B32: =B31 -> 213.3 | C32: =C31 -> 219.2 | D32: =C31-C32 -> 0 | E32: =D32*8.38 -> 0 | F32: =F31 -> 1459 | G32: =F32-F31 -> 0 | H32: =H31 -> 342878 | I32: =SUM(H32-H31) -> 0 | J32: =IF(G32>0,I32/G32,0) -> 0 | K32: =K31 -> 1846 | L32: =K32-K31 -> 0 | M32: =M31 -> 134906 | N32: =M32-M31 -> 0 | O32: =SUM(L32*$J$1) -> 0 | P32: =P31 -> 1681 | Q32: =Q31 -> 143671 | R32: =Q32-Q31 -> 0 | S32: =SUM(P32-P31) -> 0 | T32: =SUM(S32*$T$2) -> 0 | U32: =SUM(G32+L32+S32) -> 0 | V32: =R32+N32+I32:I32 -> 0 | X32: =X31 -> 2401 | Y32: =X32-X31 -> 0 | Z32: =Z31 -> 134951.9 | AA32: =Z32-Z31 -> 0 | AB32: =SUM(Y32*$AB$2) -> 0 | AC32: =AC31 -> 1801 | AD32: =AC32-AC31 -> 0 | AE32: =AE31 -> 357717.5 | AF32: =AE32-AE31 -> 0 | AG32: =IF(AD32>0,AF32/AD32,0) -> 0 | AH32: =AF32+AA32 -> 0 | AI32: =SUM(AH32+V32) -> 0 | AJ32: =-tanks!AW33 -> 0 | AK32: =SUM(AJ32-AI32) -> 0 | AL32: =S32+L32+G32 -> 0 | AM32: =Y32+AD32 -> 0 | AN32: =AN31 -> 71 | AO32: =(AN32/100)*3000 -> 2130 | AP32: =AP31 -> 71 | AQ32: =(AP32/100)*3000 -> 2130 | AR32: =AR31 -> 72 | AS32: =(AR32/100)*3000 -> 2160 | AT32: =SUM(AO32+AQ32+AS32) -> 6420 | AU32: =AT31-AT32+AV32 -> 0 | AX32: =IF(AV32>0,AW32,AX31) -> 0.1
... A35: =ELEC!C33 -> 43921 | B35: =B34 -> 213.3 | C35: =C34 -> 219.2 | D35: =C34-C35 -> 0 | E35: =D35*8.38 -> 0 | F35: =F34 -> 1459 | G35: =F35-F34 -> 0 | H35: =H34 -> 342878 | I35: =SUM(H35-H34) -> 0 | J35: =IF(G35>0,I35/G35,0) -> 0 | K35: =K34 -> 1846 | L35: =K35-K34 -> 0 | M35: =M34 -> 134906 | N35: =M35-M34 -> 0 | O35: =SUM(L35*$J$1) -> 0 | P35: =P34 -> 1681 | Q35: =Q34 -> 143671 | R35: =Q35-Q34 -> 0 | S35: =SUM(P35-P34) -> 0 | T35: =SUM(S35*$T$2) -> 0 | U35: =SUM(G35+L35+S35) -> 0 | V35: =R35+N35+I35:I35 -> 0 | X35: =X34 -> 2401 | Y35: =X35-X34 -> 0 | Z35: =Z34 -> 134951.9 | AA35: =Z35-Z34 -> 0 | AB35: =SUM(Y35*$AB$2) -> 0 | AC35: =AC34 -> 1801 | AD35: =AC35-AC34 -> 0 | AE35: =AE34 -> 357717.5 | AF35: =AE35-AE34 -> 0 | AG35: =IF(AD35>0,AF35/AD35,0) -> 0 | AH35: =AF35+AA35 -> 0 | AI35: =SUM(AH35+V35) -> 0 | AJ35: =-tanks!AW36 -> 0 | AK35: =SUM(AJ35-AI35) -> 0 | AL35: =S35+L35+G35 -> 0 | AM35: =Y35+AD35 -> 0 | AN35: =AN34 -> 71 | AO35: =(AN35/100)*3000 -> 2130 | AP35: =AP34 -> 71 | AQ35: =(AP35/100)*3000 -> 2130 | AR35: =AR34 -> 72 | AS35: =(AR35/100)*3000 -> 2160 | AT35: =SUM(AO35+AQ35+AS35) -> 6420 | AU35: =AT34-AT35+AV35 -> 0 | AX35: =IF(AV35>0,AW35,AX34) -> 0.1
J36: =SUM(J5:J34)/(COUNT(J5:J34)-COUNTIF(J5:J34,0)) -> 51.888889 | AE36: . | AR36: Nb Delivery | AS36: =COUNT(AW5:AW35) -> 1 | AU36: =SUM(AU5:AU35) -> 600.1 | AV36: =SUM(AV5:AV35) -> 0.1 | AW36: =SUM(AW5:AW35)/AS36 -> 0.1
AH37: =AF37+AA37 -> 0 | AI37: =SUM(AI5:AI35) -> 2485.1
AH38: =AF38+AA38 -> 0 | AU38: =AU36*0.51 -> 306.051 | AV38: =AV36/0.51 -> 0.19607843 | AW38: =SUM(AW5:AW35)/AS36 -> 0.1
AV39: =AV36*0.51 -> 0.051

Sheet WATER
D1: =SUM(G21:G35) -> 8895720 | AR1: Entrance | AT1: Tank 1 | AV1: Tank 2
AR2: Level | AW2: Quantity CM3 | AZ2: Var
A3: Date | B3: Truck | C3: Truck M3/day | D3: N0. Trucks | F3: REQ. # of trucks | G3: City | H3: City/day | I3: Total water delivery | K3: SW | L3: Cosum SW/day | M3: RO Guest/ Liter | O3: RO K&L/ Liter | Q3: TOTAL RO Production | R3: RO 1 RH | S3: RO 2 RH | T3: RO water counter | U3: RO Cons m3 | V3: Steam Boiler | W3: Steam Boiler/day | X3: Softener Guest | Y3: Guest Sotf/day | Z3: Softener K&L | AA3: K&L Soft/Day | AB3: Fire Tank Level | AC3: Fire Tank Counter | AE3: Laundry Hot Water Counter | AF3: Hot Water Cons/day | AG3: Laundry Cold Water Counter | AH3: Cold Water Cons/day | AI3: Laundry Water Total Cons | AJ3: K&L Sotf/day | AK3: Guest / day | AL3: K&L /day | AM3: Avg Outside Temp | AN3: Banquet Activity | AR3: Date | AT3: MainI | AV3: Kitchen and Laundry | AX3: Guest | AY3: Main Tank | AZ3: Kitchen and Laundry | BA3: Guest | BB3: Kitchen and Laundry | BC3: Main | BD3: Guest | BE3: Total VAR | BF3: Hotel Consumption
E4: 1.66 | AN4: Ball R | AO4: Meeting | AP4: outlet | AT4: 180 | AV4: 220 | AX4: 580 | AY4: =SUM(AT4) -> 180 | AZ4: =SUM(AV4) -> 220 | BA4: =SUM(AX4) -> 580
A5: 43890 | B5: =[1]WATER!B34 -> 108473 | C5: =[1]WATER!C34 -> 0 | D5: =[1]WATER!D34 -> 0 | E5: =[1]WATER!E34 -> 258.62069 | F5: =[1]WATER!F34 -> 0 | G5: =[1]WATER!G34 -> 592253 | H5: =[1]WATER!H34 -> 160 | I5: =[1]WATER!I34 -> 160 | ... AQ5: =[1]WATER!AQ34 -> 0 | AR5: =A5 -> 43890 | AS5: =[1]WATER!AS34 -> 0.9 | AT5: =[1]WATER!AT34 -> 93 | AU5: =[1]WATER!AU34 -> 1.1 | AV5: =[1]WATER!AV34 -> 95 | AW5: =[1]WATER!AW34 -> 2.9 | AX5: =[1]WATER!AX34 -> 68 | AY5: =[1]WATER!AY34 -> 83.7 | AZ5: =[1]WATER!AZ34 -> 104.5 | ... BG5: =[1]WATER!BG34 -> 68.8
A6: =ELEC!C3 -> 43891 | B6: 108473 | C6: =B6-B5 -> 0 | D6: =C6/27 -> 0 | E6: =SUM((C6*$E$4)+(7500/'EDl log'!$A$38)) -> 241.93548 | G6: 592253 | H6: =G6-G5 -> 0 | I6: =C6+H6 -> 0 | J6: =IF(I6>0,E6/I6,0) -> 0 | K6: ='Swimming Pool quality check '!H6 -> 5921 | L6: 0 | M6: =M5 -> 457.44 | N6: =SUM(M6-M5) -> 0 | O6: =O5 -> 529.52 | P6: =SUM(O6-O5) -> 0 | Q6: =P6+N6 -> 0 | T6: 4668 | U6: =SUM(T6-T5) -> 4 | V6: 392 | W6: =+V6-V5 -> 0 | X6: 141371 | Y6: =SUM(X6-X5) -> 26 | Z6: 93020 | AA6: =Z6-Z5 -> 11 | AB6: 249 | AC6: =AC5 -> 671 | AD6: 0 | AE6: 124.74 | AF6: =AE6-AE5 -> 0 | AG6: 1444.08 | AH6: =AG6-AG5 -> 0.62 | AI6: =AF6+AH6 -> 0.62 | AJ6: =+Z6-Z5 -> 11 | AK6: =SUM(Y6-L6) -> 26 | AL6: =SUM(AJ6-W6) -> 11 | AM6: ='General information '!D6 -> 13.5 | AN6: ='General information '!H6 -> 248 | AP6: ='General information '!J6 -> 0 | AR6: =A6 -> 43891 | AS6: =AS5 -> 0.9 | AT6: 58 | AU6: =AU5 -> 1.1 | AV6: 78 | AW6: 2.9 | AX6: 67 | AY6: =AS6*AT6 -> 52.2 | AZ6: =AU6*AV6 -> 85.8 | BA6: =AW6*AX6 -> 194.3 | BB6: =AY6-AY5 -> -31.5 | BC6: =AZ6-AZ5 -> -18.7 | BD6: =BA6-BA5 -> -2.9 | BE6: =SUM(BB6:BD6) -> -53.1 | BF6: =SUM(I6-BE6) -> 53.1 | BG6: =SUM(I6-BF6) -> -53.1
A7: =ELEC!C4 -> 43892 | B7: =B6 -> 108473 | C7: =B7-B6 -> 0 | D7: =C7/27 -> 0 | E7: =SUM((C7*$E$4)+(7500/'EDl log'!$A$38)) -> 241.93548 | G7: 592707 | H7: =G7-G6 -> 454 | I7: =C7+H7 -> 454 | J7: =IF(I7>0,E7/I7,0) -> 0.53289754 | K7: ='Swimming Pool quality check '!H7 -> 5921 | L7: =K7-K6 -> 0 | M7: =M6 -> 457.44 | N7: =SUM(M7-M6) -> 0 | O7: =O6 -> 529.52 | P7: =SUM(O7-O6) -> 0 | Q7: =P7+N7 -> 0 | T7: 4673 | U7: =SUM(T7-T6) -> 5 | V7: 392 | W7: =+V7-V6 -> 0 | X7: 141523 | Y7: =SUM(X7-X6) -> 152 | Z7: 93086 | AA7: =Z7-Z6 -> 66 | AB7: 260 | AC7: =AC6 -> 671 | AD7: =AC7-AC6 -> 0 | AE7: 124.74 | AF7: =AE7-AE6 -> 0 | AG7: 1444.36 | AH7: =AG7-AG6 -> 0.28 | AI7: =AF7+AH7 -> 0.28 | AJ7: =+Z7-Z6 -> 66 | AK7: =SUM(Y7-L7) -> 152 | AL7: =SUM(AJ7-W7) -> 66 | AM7: ='General information '!D7 -> 14.5 | AN7: ='General information '!H7 -> 0 | AP7: ='General information '!J7 -> 170 | AR7: =A7 -> 43892 | AS7: =AS6 -> 0.9 | AT7: 40 | AU7: =AU6 -> 1.1 | AV7: 108 | AW7: 2.9 | AX7: 97 | AY7: =AS7*AT7 -> 36 | AZ7: =AU7*AV7 -> 118.8 | BA7: =AW7*AX7 -> 281.3 | BB7: =AY7-AY6 -> -16.2 | BC7: =AZ7-AZ6 -> 33 | BD7: =BA7-BA6 -> 87 | BE7: =SUM(BB7:BD7) -> 103.8 | BF7: =SUM(I7-BE7) -> 350.2 | BG7: =SUM(I7-BF7) -> 103.8
A8: =ELEC!C5 -> 43893 | B8: 108473 | C8: =B8-B7 -> 0 | D8: =C8/27 -> 0 | E8: =SUM((C8*$E$4)+(7500/'EDl log'!$A$38)) -> 241.93548 | G8: 592707 | H8: =G8-G7 -> 0 | I8: =C8+H8 -> 0 | J8: =IF(I8>0,E8/I8,0) -> 0 | K8: ='Swimming Pool quality check '!H8 -> 5921 | L8: =K8-K7 -> 0 | M8: =M7 -> 457.44 | N8: =SUM(M8-M7) -> 0 | O8: =O7 -> 529.52 | P8: =SUM(O8-O7) -> 0 | Q8: =P8+N8 -> 0 | T8: 4677 | U8: =SUM(T8-T7) -> 4 | V8: 393 | W8: =+V8-V7 -> 1 | X8: 141523 | Y8: =SUM(X8-X7) -> 0 | Z8: 93086 | AA8: =Z8-Z7 -> 0 | AB8: 246 | AC8: =AC7 -> 671 | AD8: =AC8-AC7 -> 0 | AE8: 129.92 | AF8: =AE8-AE7 -> 5.18 | AG8: 1444.46 | AH8: =AG8-AG7 -> 0.1 | AI8: =AF8+AH8 -> 5.28 | AJ8: =+Z8-Z7 -> 0 | AK8: =SUM(Y8-L8) -> 0 | AL8: =SUM(AJ8-W8) -> -1 | AM8: ='General information '!D8 -> 15.5 | AN8: ='General information '!H8 -> 0 | AP8: ='General information '!J8 -> 168 | AR8: =A8 -> 43893 | AS8: =AS7 -> 0.9 | AT8: 52 | AU8: 1.1 | AV8: 89 | AW8: 2.9 | AX8: 90 | AY8: =AS8*AT8 -> 46.8 | AZ8: =AU8*AV8 -> 97.9 | BA8: =AW8*AX8 -> 261 | BB8: =AY8-AY7 -> 10.8 | BC8: =AZ8-AZ7 -> -20.9 | BD8: =BA8-BA7 -> -20.3 | BE8: =SUM(BB8:BD8) -> -30.4 | BF8: =SUM(I8-BE8) -> 30.4 | BG8: =SUM(I8-BF8) -> -30.4
A9: =ELEC!C6 -> 43894 | B9: 108473 | C9: =B9-B8 -> 0 | D9: =C9/27 -> 0 | E9: =SUM((C9*$E$4)+(7500/'EDl log'!$A$38)) -> 241.93548 | G9: 593048 | H9: =G9-G8 -> 341 | I9: =C9+H9 -> 341 | J9: =IF(I9>0,E9/I9,0) -> 0.70948822 | K9: ='Swimming Pool quality check '!H9 -> 5921 | L9: =K9-K8 -> 0 | M9: =M8 -> 457.44 | N9: =SUM(M9-M8) -> 0 | O9: =O8 -> 529.52 | P9: =SUM(O9-O8) -> 0 | Q9: =P9+N9 -> 0 | T9: 4679 | U9: =SUM(T9-T8) -> 2 | V9: 394 | W9: =+V9-V8 -> 1 | X9: 141616 | Y9: =SUM(X9-X8) -> 93 | Z9: 93176 | AA9: =Z9-Z8 -> 90 | AB9: 246 | AC9: =AC8 -> 671 | AD9: =AC9-AC8 -> 0 | AE9: 131.84 | AF9: =AE9-AE8 -> 1.92 | AG9: 1445.01 | AH9: =AG9-AG8 -> 0.55 | AI9: =AF9+AH9 -> 2.47 | AJ9: =+Z9-Z8 -> 90 | AK9: =SUM(Y9-L9) -> 93 | AL9: =SUM(AJ9-W9) -> 89 | AM9: ='General information '!D9 -> 15.5 | AN9: ='General information '!H9 -> 0 | AP9: ='General information '!J9 -> 189 | AR9: =A9 -> 43894 | AS9: =AS8 -> 0.9 | AT9: 80 | AU9: =AU8 -> 1.1 | AV9: 107 | AW9: 2.9 | AX9: 108 | AY9: =AS9*AT9 -> 72 | AZ9: =AU9*AV9 -> 117.7 | BA9: =AW9*AX9 -> 313.2 | BB9: =AY9-AY8 -> 25.2 | BC9: =AZ9-AZ8 -> 19.8 | BD9: =BA9-BA8 -> 52.2 | BE9: =SUM(BB9:BD9) -> 97.2 | BF9: =SUM(I9-BE9) -> 243.8 | BG9: =SUM(I9-BF9) -> 97.2
A10: =ELEC!C7 -> 43895 | B10: =B9 -> 108473 | C10: =B10-B9 -> 0 | D10: =C10/27 -> 0 | E10: =SUM((C10*$E$4)+(7500/'EDl log'!$A$38)) -> 241.93548 | G10: =G9 -> 593048 | H10: =G10-G9 -> 0 | I10: =C10+H10 -> 0 | J10: =IF(I10>0,E10/I10,0) -> 0 | K10: ='Swimming Pool quality check '!H10 -> 5921 | L10: =K10-K9 -> 0 | M10: =M9 -> 457.44 | N10: =SUM(M10-M9) -> 0 | O10: =O9 -> 529.52 | P10: =SUM(O10-O9) -> 0 | Q10: =P10+N10 -> 0 | T10: =T9 -> 4679 | U10: =SUM(T10-T9) -> 0 | V10: =V9 -> 394 | W10: =+V10-V9 -> 0 | X10: =X9 -> 141616 | Y10: =SUM(X10-X9) -> 0 | Z10: =Z9 -> 93176 | AA10: =Z10-Z9 -> 0 | AB10: 246 | AC10: =AC9 -> 671 | AD10: =AC10-AC9 -> 0 | AE10: =AE9 -> 131.84 | AF10: =AE10-AE9 -> 0 | AG10: =AG9 -> 1445.01 | AH10: =AG10-AG9 -> 0 | AI10: =AF10+AH10 -> 0 | AJ10: =+Z10-Z9 -> 0 | AK10: =SUM(Y10-L10) -> 0 | AL10: =SUM(AJ10-W10) -> 0 | AM10: ='General information '!D10 -> 0 | AN10: ='General information '!H10 -> 0 | AP10: ='General information '!J10 -> 0 | AR10: =A10 -> 43895 | AS10: =AS9 -> 0.9 | AT10: =AT9 -> 80 | AU10: =AU9 -> 1.1 | AV10: =AV9 -> 107 | AW10: 2.9 | AX10: =AX9 -> 108 | AY10: =AS10*AT10 -> 72 | AZ10: =AU10*AV10 -> 117.7 | BA10: =AW10*AX10 -> 313.2 | BB10: =AY10-AY9 -> 0 | BC10: =AZ10-AZ9 -> 0 | BD10: =BA10-BA9 -> 0 | BE10: =SUM(BB10:BD10) -> 0 | BF10: =SUM(I10-BE10) -> 0 | BG10: =SUM(I10-BF10) -> 0
A11: =ELEC!C8 -> 43896 | B11: =B10 -> 108473 | C11: =B11-B10 -> 0 | D11: =C11/27 -> 0 | E11: =SUM((C11*$E$4)+(7500/'EDl log'!$A$38)) -> 241.93548 | G11: =G10 -> 593048 | H11: =G11-G10 -> 0 | I11: =C11+H11 -> 0 | J11: =IF(I11>0,E11/I11,0) -> 0 | K11: ='Swimming Pool quality check '!H11 -> 5921 | L11: =K11-K10 -> 0 | M11: =M10 -> 457.44 | N11: =SUM(M11-M10) -> 0 | O11: =O10 -> 529.52 | P11: =SUM(O11-O10) -> 0 | Q11: =SUM(P11+N11) -> 0 | T11: =T10 -> 4679 | U11: =SUM(T11-T10) -> 0 | V11: =V10 -> 394 | W11: =+V11-V10 -> 0 | X11: =X10 -> 141616 | Y11: =SUM(X11-X10) -> 0 | Z11: =Z10 -> 93176 | AA11: =Z11-Z10 -> 0 | AB11: =AB10 -> 246 | AC11: =AC10 -> 671 | AD11: =AC11-AC10 -> 0 | AE11: =AE10 -> 131.84 | AF11: =AE11-AE10 -> 0 | AG11: =AG10 -> 1445.01 | AH11: =AG11-AG10 -> 0 | AI11: =AF11+AH11 -> 0 | AJ11: =+Z11-Z10 -> 0 | AK11: =SUM(Y11-L11) -> 0 | AL11: =SUM(AJ11-W11) -> 0 | AM11: ='General information '!D11 -> 0 | AN11: ='General information '!H11 -> 0 | AP11: ='General information '!J11 -> 0 | AR11: =A11 -> 43896 | AS11: =AS10 -> 0.9 | AT11: =AT10 -> 80 | AU11: =AU10 -> 1.1 | AV11: =AV10 -> 107 | AW11: 2.9 | AX11: =AX10 -> 108 | AY11: =AS11*AT11 -> 72 | AZ11: =AU11*AV11 -> 117.7 | BA11: =AW11*AX11 -> 313.2 | BB11: =AY11-AY10 -> 0 | BC11: =AZ11-AZ10 -> 0 | BD11: =BA11-BA10 -> 0 | BE11: =SUM(BB11:BD11) -> 0 | BF11: =SUM(I11-BE11) -> 0 | BG11: =SUM(I11-BF11) -> 0
A12: =ELEC!C9 -> 43897 | B12: =B11 -> 108473 | C12: =B12-B11 -> 0 | D12: =C12/27 -> 0 | E12: =SUM((C12*$E$4)+(7500/'EDl log'!$A$38)) -> 241.93548 | G12: =G11 -> 593048 | H12: =G12-G11 -> 0 | I12: =C12+H12 -> 0 | J12: =IF(I12>0,E12/I12,0) -> 0 | K12: ='Swimming Pool quality check '!H12 -> 5921 | L12: =K12-K11 -> 0 | M12: =M11 -> 457.44 | N12: =SUM(M12-M11) -> 0 | O12: =O11 -> 529.52 | P12: =SUM(O12-O11) -> 0 | Q12: =SUM(P12+N12) -> 0 | T12: =T11 -> 4679 | U12: =SUM(T12-T11) -> 0 | V12: =V11 -> 394 | W12: =+V12-V11 -> 0 | X12: =X11 -> 141616 | Y12: =SUM(X12-X11) -> 0 | Z12: =Z11 -> 93176 | AA12: =Z12-Z11 -> 0 | AB12: =AB11 -> 246 | AC12: =AC11 -> 671 | AD12: =AC12-AC11 -> 0 | AE12: =AE11 -> 131.84 | AF12: =AE12-AE11 -> 0 | AG12: =AG11 -> 1445.01 | AH12: =AG12-AG11 -> 0 | AI12: =AF12+AH12 -> 0 | AJ12: =+Z12-Z11 -> 0 | AK12: =SUM(Y12-L12) -> 0 | AL12: =SUM(AJ12-W12) -> 0 | AM12: ='General information '!D12 -> 0 | AN12: ='General information '!H12 -> 0 | AP12: ='General information '!J12 -> 0 | AR12: =A12 -> 43897 | AS12: =AS11 -> 0.9 | AT12: =AT11 -> 80 | AU12: =AU11 -> 1.1 | AV12: =AV11 -> 107 | AW12: 2.9 | AX12: =AX11 -> 108 | AY12: =AS12*AT12 -> 72 | AZ12: =AU12*AV12 -> 117.7 | BA12: =AW12*AX12 -> 313.2 | BB12: =AY12-AY11 -> 0 | BC12: =AZ12-AZ11 -> 0 | BD12: =BA12-BA11 -> 0 | BE12: =SUM(BB12:BD12) -> 0 | BF12: =SUM(I12-BE12) -> 0 | BG12: =SUM(I12-BF12) -> 0
A13: =ELEC!C10 -> 43898 | B13: =B12 -> 108473 | C13: =B13-B12 -> 0 | D13: =C13/27 -> 0 | E13: =SUM((C13*$E$4)+(7500/'EDl log'!$A$38)) -> 241.93548 | G13: =G12 -> 593048 | H13: =G13-G12 -> 0 | I13: =C13+H13 -> 0 | J13: =IF(I13>0,E13/I13,0) -> 0 | K13: ='Swimming Pool quality check '!H13 -> 5921 | L13: =K13-K12 -> 0 | M13: =M12 -> 457.44 | N13: =SUM(M13-M12) -> 0 | O13: =O12 -> 529.52 | P13: =SUM(O13-O12) -> 0 | Q13: =SUM(P13+N13) -> 0 | T13: =T12 -> 4679 | U13: =SUM(T13-T12) -> 0 | V13: =V12 -> 394 | W13: =+V13-V12 -> 0 | X13: =X12 -> 141616 | Y13: =SUM(X13-X12) -> 0 | Z13: =Z12 -> 93176 | AA13: =Z13-Z12 -> 0 | AB13: =AB12 -> 246 | AC13: =AC12 -> 671 | AD13: =AC13-AC12 -> 0 | AE13: =AE12 -> 131.84 | AF13: =AE13-AE12 -> 0 | AG13: =AG12 -> 1445.01 | AH13: =AG13-AG12 -> 0 | AI13: =AF13+AH13 -> 0 | AJ13: =+Z13-Z12 -> 0 | AK13: =SUM(Y13-L13) -> 0 | AL13: =SUM(AJ13-W13) -> 0 | AM13: ='General information '!D13 -> 0 | AN13: ='General information '!J13 -> 0 | AP13: ='General information '!J13 -> 0 | AR13: =A13 -> 43898 | AS13: =AS12 -> 0.9 | AT13: =AT12 -> 80 | AU13: =AU12 -> 1.1 | AV13: =AV12 -> 107 | AW13: 2.9 | AX13: =AX12 -> 108 | AY13: =AS13*AT13 -> 72 | AZ13: =AU13*AV13 -> 117.7 | BA13: =AW13*AX13 -> 313.2 | BB13: =AY13-AY12 -> 0 | BC13: =AZ13-AZ12 -> 0 | BD13: =BA13-BA12 -> 0 | BE13: =SUM(BB13:BD13) -> 0 | BF13: =SUM(I13-BE13) -> 0 | BG13: =SUM(I13-BF13) -> 0
A14: =ELEC!C11 -> 43899 | B14: =B13 -> 108473 | C14: =B14-B13 -> 0 | D14: =C14/27 -> 0 | E14: =SUM((C14*$E$4)+(7500/'EDl log'!$A$38)) -> 241.93548 | G14: =G13 -> 593048 | H14: =G14-G13 -> 0 | I14: =C14+H14 -> 0 | J14: =IF(I14>0,E14/I14,0) -> 0 | K14: ='Swimming Pool quality check '!H14 -> 5921 | L14: =K14-K13 -> 0 | M14: =M13 -> 457.44 | N14: =SUM(M14-M13) -> 0 | O14: =O13 -> 529.52 | P14: =SUM(O14-O13) -> 0 | Q14: =SUM(P14+N14) -> 0 | T14: =T13 -> 4679 | U14: =SUM(T14-T13) -> 0 | V14: =V13 -> 394 | W14: =+V14-V13 -> 0 | X14: =X13 -> 141616 | Y14: =SUM(X14-X13) -> 0 | Z14: =Z13 -> 93176 | AA14: =Z14-Z13 -> 0 | AB14: =AB13 -> 246 | AC14: =AC13 -> 671 | AD14: =AC14-AC13 -> 0 | AE14: =AE13 -> 131.84 | AF14: =AE14-AE13 -> 0 | AG14: =AG13 -> 1445.01 | AH14: =AG14-AG13 -> 0 | AI14: =AF14+AH14 -> 0 | AJ14: =+Z14-Z13 -> 0 | AK14: =SUM(Y14-L14) -> 0 | AL14: =SUM(AJ14-W14) -> 0 | AM14: ='General information '!D14 -> 0 | AN14: ='General information '!H14 -> 0 | AP14: ='General information '!J14 -> 0 | AR14: =A14 -> 43899 | AS14: =AS13 -> 0.9 | AT14: =AT13 -> 80 | AU14: =AU13 -> 1.1 | AV14: =AV13 -> 107 | AW14: 2.9 | AX14: =AX13 -> 108 | AY14: =AS14*AT14 -> 72 | AZ14: =AU14*AV14 -> 117.7 | BA14: =AW14*AX14 -> 313.2 | BB14: =AY14-AY13 -> 0 | BC14: =AZ14-AZ13 -> 0 | BD14: =BA14-BA13 -> 0 | BE14: =SUM(BB14:BD14) -> 0 | BF14: =SUM(I14-BE14) -> 0 | BG14: =SUM(I14-BF14) -> 0
A15: =ELEC!C12 -> 43900 | B15: =B14 -> 108473 | C15: =B15-B14 -> 0 | D15: =C15/27 -> 0 | E15: =SUM((C15*$E$4)+(7500/'EDl log'!$A$38)) -> 241.93548 | G15: =G14 -> 593048 | H15: =G15-G14 -> 0 | I15: =C15+H15 -> 0 | J15: =IF(I15>0,E15/I15,0) -> 0 | K15: ='Swimming Pool quality check '!H15 -> 5921 | L15: =K15-K14 -> 0 | M15: =M14 -> 457.44 | N15: =SUM(M15-M14) -> 0 | O15: =O14 -> 529.52 | P15: =SUM(O15-O14) -> 0 | Q15: =SUM(P15+N15) -> 0 | T15: =T14 -> 4679 | U15: =SUM(T15-T14) -> 0 | V15: =V14 -> 394 | W15: =+V15-V14 -> 0 | X15: =X14 -> 141616 | Y15: =SUM(X15-X14) -> 0 | Z15: =Z14 -> 93176 | AA15: =Z15-Z14 -> 0 | AB15: =AB14 -> 246 | AC15: =AC14 -> 671 | AD15: =AC15-AC14 -> 0 | AE15: =AE14 -> 131.84 | AF15: =AE15-AE14 -> 0 | AG15: =AG14 -> 1445.01 | AH15: =AG15-AG14 -> 0 | AI15: =AF15+AH15 -> 0 | AJ15: =+Z15-Z14 -> 0 | AK15: =SUM(Y15-L15) -> 0 | AL15: =SUM(AJ15-W15) -> 0 | AM15: ='General information '!D15 -> 0 | AN15: ='General information '!H15 -> 0 | AP15: ='General information '!J15 -> 0 | AR15: =A15 -> 43900 | AS15: =AS14 -> 0.9 | AT15: =AT14 -> 80 | AU15: =AU14 -> 1.1 | AV15: =AV14 -> 107 | AW15: 2.9 | AX15: =AX14 -> 108 | AY15: =AS15*AT15 -> 72 | AZ15: =AU15*AV15 -> 117.7 | BA15: =AW15*AX15 -> 313.2 | BB15: =AY15-AY14 -> 0 | BC15: =AZ15-AZ14 -> 0 | BD15: =BA15-BA14 -> 0 | BE15: =SUM(BB15:BD15) -> 0 | BF15: =SUM(I15-BE15) -> 0 | BG15: =SUM(I15-BF15) -> 0
A16: =ELEC!C13 -> 43901 | B16: =B15 -> 108473 | C16: =B16-B15 -> 0 | D16: =C16/27 -> 0 | E16: =SUM((C16*$E$4)+(7500/'EDl log'!$A$38)) -> 241.93548 | G16: =G15 -> 593048 | H16: =G16-G15 -> 0 | I16: =C16+H16 -> 0 | J16: =IF(I16>0,E16/I16,0) -> 0 | K16: ='Swimming Pool quality check '!H16 -> 5921 | L16: =K16-K15 -> 0 | M16: =M15 -> 457.44 | N16: =SUM(M16-M15) -> 0 | O16: =O15 -> 529.52 | P16: =SUM(O16-O15) -> 0 | Q16: =SUM(P16+N16) -> 0 | T16: =T15 -> 4679 | U16: =SUM(T16-T15) -> 0 | V16: =V15 -> 394 | W16: =+V16-V15 -> 0 | X16: =X15 -> 141616 | Y16: =SUM(X16-X15) -> 0 | Z16: =Z15 -> 93176 | AA16: =Z16-Z15 -> 0 | AB16: 244 | AC16: =AC15 -> 671 | AD16: =AC16-AC15 -> 0 | AE16: =AE15 -> 131.84 | AF16: =AE16-AE15 -> 0 | AG16: =AG15 -> 1445.01 | AH16: =AG16-AG15 -> 0 | AI16: =AF16+AH16 -> 0 | AJ16: =+Z16-Z15 -> 0 | AK16: =SUM(Y16-L16) -> 0 | AL16: =SUM(AJ16-W16) -> 0 | AM16: ='General information '!D16 -> 0 | AN16: ='General information '!H16 -> 0 | AP16: ='General information '!J16 -> 0 | AR16: =A16 -> 43901 | AS16: =AS15 -> 0.9 | AT16: =AT15 -> 80 | AU16: =AU15 -> 1.1 | AV16: =AV15 -> 107 | AW16: 2.9 | AX16: =AX15 -> 108 | AY16: =AS16*AT16 -> 72 | AZ16: =AU16*AV16 -> 117.7 | BA16: =AW16*AX16 -> 313.2 | BB16: =AY16-AY15 -> 0 | BC16: =AZ16-AZ15 -> 0 | BD16: =BA16-BA15 -> 0 | BE16: =SUM(BB16:BD16) -> 0 | BF16: =SUM(I16-BE16) -> 0 | BG16: =SUM(I16-BF16) -> 0
A17: =ELEC!C14 -> 43902 | B17: =B16 -> 108473 | C17: =B17-B16 -> 0 | D17: =C17/27 -> 0 | E17: =SUM((C17*$E$4)+(7500/'EDl log'!$A$38)) -> 241.93548 | G17: =G16 -> 593048 | H17: =G17-G16 -> 0 | I17: =C17+H17 -> 0 | J17: =IF(I17>0,E17/I17,0) -> 0 | K17: ='Swimming Pool quality check '!H17 -> 5921 | L17: =K17-K16 -> 0 | M17: =M16 -> 457.44 | N17: =SUM(M17-M16) -> 0 | O17: =O16 -> 529.52 | P17: =SUM(O17-O16) -> 0 | Q17: =SUM(P17+N17) -> 0 | T17: =T16 -> 4679 | U17: =SUM(T17-T16) -> 0 | V17: =V16 -> 394 | W17: =+V17-V16 -> 0 | X17: =X16 -> 141616 | Y17: =SUM(X17-X16) -> 0 | Z17: =Z16 -> 93176 | AA17: =Z17-Z16 -> 0 | AB17: =AB16 -> 244 | AC17: =AC16 -> 671 | AD17: =AC17-AC16 -> 0 | AE17: =AE16 -> 131.84 | AF17: =AE17-AE16 -> 0 | AG17: =AG16 -> 1445.01 | AH17: =AG17-AG16 -> 0 | AI17: =AF17+AH17 -> 0 | AJ17: =+Z17-Z16 -> 0 | AK17: =SUM(Y17-L17) -> 0 | AL17: =SUM(AJ17-W17) -> 0 | AM17: ='General information '!D17 -> 0 | AN17: ='General information '!H17 -> 0 | AP17: ='General information '!J17 -> 0 | AR17: =A17 -> 43902 | AS17: =AS16 -> 0.9 | AT17: =AT16 -> 80 | AU17: =AU16 -> 1.1 | AV17: =AV16 -> 107 | AW17: 2.9 | AX17: =AX16 -> 108 | AY17: =AS17*AT17 -> 72 | AZ17: =AU17*AV17 -> 117.7 | BA17: =AW17*AX17 -> 313.2 | BB17: =AY17-AY16 -> 0 | BC17: =AZ17-AZ16 -> 0 | BD17: =BA17-BA16 -> 0 | BE17: =SUM(BB17:BD17) -> 0 | BF17: =SUM(I17-BE17) -> 0 | BG17: =SUM(I17-BF17) -> 0
A18: =ELEC!C15 -> 43903 | B18: =B17 -> 108473 | C18: =B18-B17 -> 0 | D18: =C18/27 -> 0 | E18: =SUM((C18*$E$4)+(7500/'EDl log'!$A$38)) -> 241.93548 | G18: =G17 -> 593048 | H18: =G18-G17 -> 0 | I18: =C18+H18 -> 0 | J18: =IF(I18>0,E18/I18,0) -> 0 | K18: ='Swimming Pool quality check '!H18 -> 5921 | L18: =K18-K17 -> 0 | M18: =M17 -> 457.44 | N18: =SUM(M18-M17) -> 0 | O18: =O17 -> 529.52 | P18: =SUM(O18-O17) -> 0 | Q18: =SUM(P18+N18) -> 0 | T18: =T17 -> 4679 | U18: =SUM(T18-T17) -> 0 | V18: =V17 -> 394 | W18: =+V18-V17 -> 0 | X18: =X17 -> 141616 | Y18: =SUM(X18-X17) -> 0 | Z18: =Z17 -> 93176 | AA18: =Z18-Z17 -> 0 | AB18: 244 | AC18: =AC17 -> 671 | AD18: =AC18-AC17 -> 0 | AE18: =AE17 -> 131.84 | AF18: =AE18-AE17 -> 0 | AG18: =AG17 -> 1445.01 | AH18: =AG18-AG17 -> 0 | AI18: =AF18+AH18 -> 0 | AJ18: =+Z18-Z17 -> 0 | AK18: =SUM(Y18-L18) -> 0 | AL18: =SUM(AJ18-W18) -> 0 | AM18: ='General information '!D18 -> 0 | AN18: ='General information '!H18 -> 0 | AP18: ='General information '!J18 -> 0 | AR18: =A18 -> 43903 | AS18: =AS17 -> 0.9 | AT18: =AT17 -> 80 | AU18: =AU17 -> 1.1 | AV18: =AV17 -> 107 | AW18: 2.9 | AX18: =AX17 -> 108 | AY18: =AS18*AT18 -> 72 | AZ18: =AU18*AV18 -> 117.7 | BA18: =AW18*AX18 -> 313.2 | BB18: =AY18-AY17 -> 0 | BC18: =AZ18-AZ17 -> 0 | BD18: =BA18-BA17 -> 0 | BE18: =SUM(BB18:BD18) -> 0 | BF18: =SUM(I18-BE18) -> 0 | BG18: =SUM(I18-BF18) -> 0
A19: =ELEC!C16 -> 43904 | B19: =B18 -> 108473 | C19: =B19-B18 -> 0 | D19: =C19/27 -> 0 | E19: =SUM((C19*$E$4)+(7500/'EDl log'!$A$38)) -> 241.93548 | G19: =G18 -> 593048 | H19: =G19-G18 -> 0 | I19: =C19+H19 -> 0 | J19: =IF(I19>0,E19/I19,0) -> 0 | K19: ='Swimming Pool quality check '!H19 -> 5921 | L19: =K19-K18 -> 0 | M19: =M18 -> 457.44 | N19: =SUM(M19-M18) -> 0 | O19: =O18 -> 529.52 | P19: =SUM(O19-O18) -> 0 | Q19: =SUM(P19+N19) -> 0 | T19: =T18 -> 4679 | U19: =SUM(T19-T18) -> 0 | V19: =V18 -> 394 | W19: =+V19-V18 -> 0 | X19: =X18 -> 141616 | Y19: =SUM(X19-X18) -> 0 | Z19: =Z18 -> 93176 | AA19: =Z19-Z18 -> 0 | AB19: =AB18 -> 244 | AC19: =AC18 -> 671 | AD19: =AC19-AC18 -> 0 | AE19: =AE18 -> 131.84 | AF19: =AE19-AE18 -> 0 | AG19: =AG18 -> 1445.01 | AH19: =AG19-AG18 -> 0 | AI19: =AF19+AH19 -> 0 | AJ19: =+Z19-Z18 -> 0 | AK19: =SUM(Y19-L19) -> 0 | AL19: =SUM(AJ19-W19) -> 0 | AM19: ='General information '!D19 -> 0 | AN19: ='General information '!H19 -> 0 | AP19: ='General information '!J19 -> 0 | AR19: =A19 -> 43904 | AS19: =AS18 -> 0.9 | AT19: =AT18 -> 80 | AU19: =AU18 -> 1.1 | AV19: =AV18 -> 107 | AW19: 2.9 | AX19: =AX18 -> 108 | AY19: =AS19*AT19 -> 72 | AZ19: =AU19*AV19 -> 117.7 | BA19: =AW19*AX19 -> 313.2 | BB19: =AY19-AY18 -> 0 | BC19: =AZ19-AZ18 -> 0 | BD19: =BA19-BA18 -> 0 | BE19: =SUM(BB19:BD19) -> 0 | BF19: =SUM(I19-BE19) -> 0 | BG19: =SUM(I19-BF19) -> 0
A20: =ELEC!C17 -> 43905 | B20: =B19 -> 108473 | C20: =B20-B19 -> 0 | D20: =C20/27 -> 0 | E20: =SUM((C20*$E$4)+(7500/'EDl log'!$A$38)) -> 241.93548 | G20: =G19 -> 593048 | H20: =G20-G19 -> 0 | I20: =C20+H20 -> 0 | J20: =IF(I20>0,E20/I20,0) -> 0 | K20: ='Swimming Pool quality check '!H20 -> 5921 | L20: =K20-K19 -> 0 | M20: =M19 -> 457.44 | N20: =SUM(M20-M19) -> 0 | O20: =O19 -> 529.52 | P20: =SUM(O20-O19) -> 0 | Q20: =SUM(P20+N20) -> 0 | T20: =T19 -> 4679 | U20: =SUM(T20-T19) -> 0 | V20: =V19 -> 394 | W20: =+V20-V19 -> 0 | X20: =X19 -> 141616 | Y20: =SUM(X20-X19) -> 0 | Z20: =Z19 -> 93176 | AA20: =Z20-Z19 -> 0 | AB20: 262 | AC20: =AC19 -> 671 | AD20: =AC20-AC19 -> 0 | AE20: =AE19 -> 131.84 | AF20: =AE20-AE19 -> 0 | AG20: =AG19 -> 1445.01 | AH20: =AG20-AG19 -> 0 | AI20: =AF20+AH20 -> 0 | AJ20: =+Z20-Z19 -> 0 | AK20: =SUM(Y20-L20) -> 0 | AL20: =SUM(AJ20-W20) -> 0 | AM20: ='General information '!D20 -> 0 | AN20: ='General information '!H20 -> 0 | AP20: ='General information '!J20 -> 0 | AR20: =A20 -> 43905 | AS20: =AS19 -> 0.9 | AT20: =AT19 -> 80 | AU20: =AU19 -> 1.1 | AV20: =AV19 -> 107 | AW20: 2.9 | AX20: =AX19 -> 108 | AY20: =AS20*AT20 -> 72 | AZ20: =AU20*AV20 -> 117.7 | BA20: =AW20*AX20 -> 313.2 | BB20: =AY20-AY19 -> 0 | BC20: =AZ20-AZ19 -> 0 | BD20: =BA20-BA19 -> 0 | BE20: =SUM(BB20:BD20) -> 0 | BF20: =SUM(I20-BE20) -> 0 | BG20: =SUM(I20-BF20) -> 0
A21: =ELEC!C18 -> 43906 | B21: =B20 -> 108473 | C21: =B21-B20 -> 0 | D21: =C21/27 -> 0 | E21: =SUM((C21*$E$4)+(7500/'EDl log'!$A$38)) -> 241.93548 | G21: =G20 -> 593048 | H21: =G21-G20 -> 0 | I21: =C21+H21 -> 0 | J21: =IF(I21>0,E21/I21,0) -> 0 | K21: ='Swimming Pool quality check '!H21 -> 5921 | L21: =K21-K20 -> 0 | M21: =M20 -> 457.44 | N21: =SUM(M21-M20) -> 0 | O21: =O20 -> 529.52 | P21: =SUM(O21-O20) -> 0 | Q21: =SUM(P21+N21) -> 0 | T21: =T20 -> 4679 | U21: =SUM(T21-T20) -> 0 | V21: =V20 -> 394 | W21: =+V21-V20 -> 0 | X21: =X20 -> 141616 | Y21: =SUM(X21-X20) -> 0 | Z21: =Z20 -> 93176 | AA21: =Z21-Z20 -> 0 | AB21: 262 | AC21: =AC20 -> 671 | AD21: =AC21-AC20 -> 0 | AE21: =AE20 -> 131.84 | AF21: =AE21-AE20 -> 0 | AG21: =AG20 -> 1445.01 | AH21: =AG21-AG20 -> 0 | AI21: =AF21+AH21 -> 0 | AJ21: =+Z21-Z20 -> 0 | AK21: =SUM(Y21-L21) -> 0 | AL21: =SUM(AJ21-W21) -> 0 | AM21: ='General information '!D21 -> 0 | AN21: ='General information '!H21 -> 0 | AP21: ='General information '!J21 -> 0 | AR21: =A21 -> 43906 | AS21: =AS20 -> 0.9 | AT21: =AT20 -> 80 | AU21: =AU20 -> 1.1 | AV21: =AV20 -> 107 | AW21: 2.9 | AX21: =AX20 -> 108 | AY21: =AS21*AT21 -> 72 | AZ21: =AU21*AV21 -> 117.7 | BA21: =AW21*AX21 -> 313.2 | BB21: =AY21-AY20 -> 0 | BC21: =AZ21-AZ20 -> 0 | BD21: =BA21-BA20 -> 0 | BE21: =SUM(BB21:BD21) -> 0 | BF21: =SUM(I21-BE21) -> 0 | BG21: =SUM(I21-BF21) -> 0
A22: =ELEC!C19 -> 43907 | B22: =B21 -> 108473 | C22: =B22-B21 -> 0 | D22: =C22/27 -> 0 | E22: =SUM((C22*$E$4)+(7500/'EDl log'!$A$38)) -> 241.93548 | G22: =G21 -> 593048 | H22: =G22-G21 -> 0 | I22: =C22+H22 -> 0 | J22: =IF(I22>0,E22/I22,0) -> 0 | K22: ='Swimming Pool quality check '!H22 -> 5921 | L22: =K22-K21 -> 0 | M22: =M21 -> 457.44 | N22: =SUM(M22-M21) -> 0 | O22: =O21 -> 529.52 | P22: =SUM(O22-O21) -> 0 | Q22: =SUM(P22+N22) -> 0 | T22: =T21 -> 4679 | U22: =SUM(T22-T21) -> 0 | V22: =V21 -> 394 | W22: =+V22-V21 -> 0 | X22: =X21 -> 141616 | Y22: =SUM(X22-X21) -> 0 | Z22: =Z21 -> 93176 | AA22: =Z22-Z21 -> 0 | AB22: 262 | AC22: =AC21 -> 671 | AD22: =AC22-AC21 -> 0 | AE22: =AE21 -> 131.84 | AF22: =AE22-AE21 -> 0 | AG22: =AG21 -> 1445.01 | AH22: =AG22-AG21 -> 0 | AI22: =AF22+AH22 -> 0 | AJ22: =+Z22-Z21 -> 0 | AK22: =SUM(Y22-L22) -> 0 | AL22: =SUM(AJ22-W22) -> 0 | AM22: ='General information '!D22 -> 0 | AN22: ='General information '!H22 -> 0 | AP22: ='General information '!J22 -> 0 | AR22: =A22 -> 43907 | AS22: =AS21 -> 0.9 | AT22: =AT21 -> 80 | AU22: =AU21 -> 1.1 | AV22: =AV21 -> 107 | AW22: 2.9 | AX22: =AX21 -> 108 | AY22: =AS22*AT22 -> 72 | AZ22: =AU22*AV22 -> 117.7 | BA22: =AW22*AX22 -> 313.2 | BB22: =AY22-AY21 -> 0 | BC22: =AZ22-AZ21 -> 0 | BD22: =BA22-BA21 -> 0 | BE22: =SUM(BB22:BD22) -> 0 | BF22: =SUM(I22-BE22) -> 0 | BG22: =SUM(I22-BF22) -> 0
A23: =ELEC!C20 -> 43908 | B23: =B22 -> 108473 | C23: =B23-B22 -> 0 | D23: =C23/27 -> 0 | E23: =SUM((C23*$E$4)+(7500/'EDl log'!$A$38)) -> 241.93548 | G23: =G22 -> 593048 | H23: =G23-G22 -> 0 | I23: =C23+H23 -> 0 | J23: =IF(I23>0,E23/I23,0) -> 0 | K23: ='Swimming Pool quality check '!H23 -> 5921 | L23: =K23-K22 -> 0 | M23: =M22 -> 457.44 | N23: =SUM(M23-M22) -> 0 | O23: =O22 -> 529.52 | P23: =SUM(O23-O22) -> 0 | Q23: =SUM(P23+N23) -> 0 | T23: =T22 -> 4679 | U23: =SUM(T23-T22) -> 0 | V23: =V22 -> 394 | W23: =+V23-V22 -> 0 | X23: =X22 -> 141616 | Y23: =SUM(X23-X22) -> 0 | Z23: =Z22 -> 93176 | AA23: =Z23-Z22 -> 0 | AB23: 262 | AC23: 671 | AD23: =AC23-AC22 -> 0 | AE23: =AE22 -> 131.84 | AF23: =AE23-AE22 -> 0 | AG23: =AG22 -> 1445.01 | AH23: =AG23-AG22 -> 0 | AI23: =AF23+AH23 -> 0 | AJ23: =+Z23-Z22 -> 0 | AK23: =SUM(Y23-L23) -> 0 | AL23: =SUM(AJ23-W23) -> 0 | AM23: ='General information '!D23 -> 0 | AN23: ='General information '!H23 -> 0 | AP23: ='General information '!J23 -> 0 | AR23: =A23 -> 43908 | AS23: =AS22 -> 0.9 | AT23: =AT22 -> 80 | AU23: =AU22 -> 1.1 | AV23: =AV22 -> 107 | AW23: 2.9 | AX23: =AX22 -> 108 | AY23: =AS23*AT23 -> 72 | AZ23: =AU23*AV23 -> 117.7 | BA23: =AW23*AX23 -> 313.2 | BB23: =AY23-AY22 -> 0 | BC23: =AZ23-AZ22 -> 0 | BD23: =BA23-BA22 -> 0 | BE23: =SUM(BB23:BD23) -> 0 | BF23: =SUM(I23-BE23) -> 0 | BG23: =SUM(I23-BF23) -> 0
A24: =ELEC!C21 -> 43909 | B24: =B23 -> 108473 | C24: =B24-B23 -> 0 | D24: =C24/27 -> 0 | E24: =SUM((C24*$E$4)+(7500/'EDl log'!$A$38)) -> 241.93548 | G24: =G23 -> 593048 | H24: =G24-G23 -> 0 | I24: =C24+H24 -> 0 | J24: =IF(I24>0,E24/I24,0) -> 0 | K24: ='Swimming Pool quality check '!H24 -> 5921 | L24: =K24-K23 -> 0 | M24: =M23 -> 457.44 | N24: =SUM(M24-M23) -> 0 | O24: =O23 -> 529.52 | P24: =SUM(O24-O23) -> 0 | Q24: =SUM(P24+N24) -> 0 | T24: =T23 -> 4679 | U24: =SUM(T24-T23) -> 0 | V24: =V23 -> 394 | W24: =+V24-V23 -> 0 | X24: =X23 -> 141616 | Y24: =SUM(X24-X23) -> 0 | Z24: =Z23 -> 93176 | AA24: =Z24-Z23 -> 0 | AB24: =AB23 -> 262 | AC24: =AC23 -> 671 | AD24: =AC24-AC23 -> 0 | AE24: =AE23 -> 131.84 | AF24: =AE24-AE23 -> 0 | AG24: =AG23 -> 1445.01 | AH24: =AG24-AG23 -> 0 | AI24: =AF24+AH24 -> 0 | AJ24: =+Z24-Z23 -> 0 | AK24: =SUM(Y24-L24) -> 0 | AL24: =SUM(AJ24-W24) -> 0 | AM24: ='General information '!D24 -> 0 | AN24: ='General information '!H24 -> 0 | AP24: ='General information '!J24 -> 0 | AR24: =A24 -> 43909 | AS24: =AS23 -> 0.9 | AT24: =AT23 -> 80 | AU24: =AU23 -> 1.1 | AV24: =AV23 -> 107 | AW24: 2.9 | AX24: =AX23 -> 108 | AY24: =AS24*AT24 -> 72 | AZ24: =AU24*AV24 -> 117.7 | BA24: =AW24*AX24 -> 313.2 | BB24: =AY24-AY23 -> 0 | BC24: =AZ24-AZ23 -> 0 | BD24: =BA24-BA23 -> 0 | BE24: =SUM(BB24:BD24) -> 0 | BF24: =SUM(I24-BE24) -> 0 | BG24: =SUM(I24-BF24) -> 0
A25: =ELEC!C22 -> 43910 | B25: =B24 -> 108473 | C25: =B25-B24 -> 0 | D25: =C25/27 -> 0 | E25: =SUM((C25*$E$4)+(7500/'EDl log'!$A$38)) -> 241.93548 | G25: =G24 -> 593048 | H25: =G25-G24 -> 0 | I25: =C25+H25 -> 0 | J25: =IF(I25>0,E25/I25,0) -> 0 | K25: ='Swimming Pool quality check '!H25 -> 5921 | L25: =K25-K24 -> 0 | M25: =M24 -> 457.44 | N25: =SUM(M25-M24) -> 0 | O25: =O24 -> 529.52 | P25: =SUM(O25-O24) -> 0 | Q25: =SUM(P25+N25) -> 0 | T25: =T24 -> 4679 | U25: =SUM(T25-T24) -> 0 | V25: =V24 -> 394 | W25: =+V25-V24 -> 0 | X25: =X24 -> 141616 | Y25: =SUM(X25-X24) -> 0 | Z25: =Z24 -> 93176 | AA25: =Z25-Z24 -> 0 | AB25: =AB24 -> 262 | AC25: =AC24 -> 671 | AD25: =AC25-AC24 -> 0 | AE25: =AE24 -> 131.84 | AF25: =AE25-AE24 -> 0 | AG25: =AG24 -> 1445.01 | AH25: =AG25-AG24 -> 0 | AI25: =AF25+AH25 -> 0 | AJ25: =+Z25-Z24 -> 0 | AK25: =SUM(Y25-L25) -> 0 | AL25: =SUM(AJ25-W25) -> 0 | AM25: ='General information '!D25 -> 0 | AN25: ='General information '!H25 -> 0 | AP25: ='General information '!J25 -> 0 | AR25: =A25 -> 43910 | AS25: =AS24 -> 0.9 | AT25: =AT24 -> 80 | AU25: =AU24 -> 1.1 | AV25: =AV24 -> 107 | AW25: 2.9 | AX25: =AX24 -> 108 | AY25: =AS25*AT25 -> 72 | AZ25: =AU25*AV25 -> 117.7 | BA25: =AW25*AX25 -> 313.2 | BB25: =AY25-AY24 -> 0 | BC25: =AZ25-AZ24 -> 0 | BD25: =BA25-BA24 -> 0 | BE25: =SUM(BB25:BD25) -> 0 | BF25: =SUM(I25-BE25) -> 0 | BG25: =SUM(I25-BF25) -> 0
A26: =ELEC!C23 -> 43911 | B26: =B25 -> 108473 | C26: =B26-B25 -> 0 | D26: =C26/27 -> 0 | E26: =SUM((C26*$E$4)+(7500/'EDl log'!$A$38)) -> 241.93548 | G26: =G25 -> 593048 | H26: =G26-G25 -> 0 | I26: =C26+H26 -> 0 | J26: =IF(I26>0,E26/I26,0) -> 0 | K26: ='Swimming Pool quality check '!H26 -> 5921 | L26: =K26-K25 -> 0 | M26: =M25 -> 457.44 | N26: =SUM(M26-M25) -> 0 | O26: =O25 -> 529.52 | P26: =SUM(O26-O25) -> 0 | Q26: =SUM(P26+N26) -> 0 | T26: =T25 -> 4679 | U26: =SUM(T26-T25) -> 0 | V26: =V25 -> 394 | W26: =+V26-V25 -> 0 | X26: =X25 -> 141616 | Y26: =SUM(X26-X25) -> 0 | Z26: =Z25 -> 93176 | AA26: =Z26-Z25 -> 0 | AB26: =AB25 -> 262 | AC26: =AC25 -> 671 | AD26: =AC26-AC25 -> 0 | AE26: =AE25 -> 131.84 | AF26: =AE26-AE25 -> 0 | AG26: =AG25 -> 1445.01 | AH26: =AG26-AG25 -> 0 | AI26: =AF26+AH26 -> 0 | AJ26: =+Z26-Z25 -> 0 | AK26: =SUM(Y26-L26) -> 0 | AL26: =SUM(AJ26-W26) -> 0 | AM26: ='General information '!D26 -> 0 | AN26: ='General information '!H26 -> 0 | AP26: ='General information '!J26 -> 0 | AR26: =A26 -> 43911 | AS26: =AS25 -> 0.9 | AT26: =AT25 -> 80 | AU26: =AU25 -> 1.1 | AV26: =AV25 -> 107 | AW26: 2.9 | AX26: =AX25 -> 108 | AY26: =AS26*AT26 -> 72 | AZ26: =AU26*AV26 -> 117.7 | BA26: =AW26*AX26 -> 313.2 | BB26: =AY26-AY25 -> 0 | BC26: =AZ26-AZ25 -> 0 | BD26: =BA26-BA25 -> 0 | BE26: =SUM(BB26:BD26) -> 0 | BF26: =SUM(I26-BE26) -> 0 | BG26: =SUM(I26-BF26) -> 0
A27: =ELEC!C24 -> 43912 | B27: =B26 -> 108473 | C27: =B27-B26 -> 0 | D27: =C27/27 -> 0 | E27: =SUM((C27*$E$4)+(7500/'EDl log'!$A$38)) -> 241.93548 | G27: =G26 -> 593048 | H27: =G27-G26 -> 0 | I27: =C27+H27 -> 0 | J27: =IF(I27>0,E27/I27,0) -> 0 | K27: ='Swimming Pool quality check '!H27 -> 5921 | L27: =K27-K26 -> 0 | M27: =M26 -> 457.44 | N27: =SUM(M27-M26) -> 0 | O27: =O26 -> 529.52 | P27: =SUM(O27-O26) -> 0 | Q27: =SUM(P27+N27) -> 0 | T27: =T26 -> 4679 | U27: =SUM(T27-T26) -> 0 | V27: =V26 -> 394 | W27: =+V27-V26 -> 0 | X27: =X26 -> 141616 | Y27: =SUM(X27-X26) -> 0 | Z27: =Z26 -> 93176 | AA27: =Z27-Z26 -> 0 | AB27: =AB26 -> 262 | AC27: =AC26 -> 671 | AD27: =AC27-AC26 -> 0 | AE27: =AE26 -> 131.84 | AF27: =AE27-AE26 -> 0 | AG27: =AG26 -> 1445.01 | AH27: =AG27-AG26 -> 0 | AI27: =AF27+AH27 -> 0 | AJ27: =+Z27-Z26 -> 0 | AK27: =SUM(Y27-L27) -> 0 | AL27: =SUM(AJ27-W27) -> 0 | AM27: ='General information '!D27 -> 0 | AN27: ='General information '!H27 -> 0 | AP27: ='General information '!J27 -> 0 | AR27: =A27 -> 43912 | AS27: =AS26 -> 0.9 | AT27: =AT26 -> 80 | AU27: =AU26 -> 1.1 | AV27: =AV26 -> 107 | AW27: 2.9 | AX27: =AX26 -> 108 | AY27: =AS27*AT27 -> 72 | AZ27: =AU27*AV27 -> 117.7 | BA27: =AW27*AX27 -> 313.2 | BB27: =AY27-AY26 -> 0 | BC27: =AZ27-AZ26 -> 0 | BD27: =BA27-BA26 -> 0 | BE27: =SUM(BB27:BD27) -> 0 | BF27: =SUM(I27-BE27) -> 0 | BG27: =SUM(I27-BF27) -> 0
A28: =ELEC!C25 -> 43913 | B28: =B27 -> 108473 | C28: =B28-B27 -> 0 | D28: =C28/27 -> 0 | E28: =SUM((C28*$E$4)+(7500/'EDl log'!$A$38)) -> 241.93548 | G28: =G27 -> 593048 | H28: =G28-G27 -> 0 | I28: =C28+H28 -> 0 | J28: =IF(I28>0,E28/I28,0) -> 0 | K28: ='Swimming Pool quality check '!H28 -> 5921 | L28: =K28-K27 -> 0 | M28: =M27 -> 457.44 | N28: =SUM(M28-M27) -> 0 | O28: =O27 -> 529.52 | P28: =SUM(O28-O27) -> 0 | Q28: =SUM(P28+N28) -> 0 | T28: =T27 -> 4679 | U28: =SUM(T28-T27) -> 0 | V28: =V27 -> 394 | W28: =+V28-V27 -> 0 | X28: =X27 -> 141616 | Y28: =SUM(X28-X27) -> 0 | Z28: =Z27 -> 93176 | AA28: =Z28-Z27 -> 0 | AB28: =AB27 -> 262 | AC28: =AC27 -> 671 | AD28: =AC28-AC27 -> 0 | AE28: =AE27 -> 131.84 | AF28: =AE28-AE27 -> 0 | AG28: =AG27 -> 1445.01 | AH28: =AG28-AG27 -> 0 | AI28: =AF28+AH28 -> 0 | AJ28: =+Z28-Z27 -> 0 | AK28: =SUM(Y28-L28) -> 0 | AL28: =SUM(AJ28-W28) -> 0 | AM28: ='General information '!D28 -> 0 | AN28: ='General information '!H28 -> 0 | AP28: ='General information '!J28 -> 0 | AR28: =A28 -> 43913 | AS28: =AS27 -> 0.9 | AT28: =AT27 -> 80 | AU28: =AU27 -> 1.1 | AV28: =AV27 -> 107 | AW28: 2.9 | AX28: =AX27 -> 108 | AY28: =AS28*AT28 -> 72 | AZ28: =AU28*AV28 -> 117.7 | BA28: =AW28*AX28 -> 313.2 | BB28: =AY28-AY27 -> 0 | BC28: =AZ28-AZ27 -> 0 | BD28: =BA28-BA27 -> 0 | BE28: =SUM(BB28:BD28) -> 0 | BF28: =SUM(I28-BE28) -> 0 | BG28: =SUM(I28-BF28) -> 0
A29: =ELEC!C26 -> 43914 | B29: =B28 -> 108473 | C29: =B29-B28 -> 0 | D29: =C29/27 -> 0 | E29: =SUM((C29*$E$4)+(7500/'EDl log'!$A$38)) -> 241.93548 | G29: =G28 -> 593048 | H29: =G29-G28 -> 0 | I29: =C29+H29 -> 0 | J29: =IF(I29>0,E29/I29,0) -> 0 | K29: ='Swimming Pool quality check '!H29 -> 5921 | L29: =K29-K28 -> 0 | M29: =M28 -> 457.44 | N29: =SUM(M29-M28) -> 0 | O29: =O28 -> 529.52 | P29: =SUM(O29-O28) -> 0 | Q29: =SUM(P29+N29) -> 0 | T29: =T28 -> 4679 | U29: =SUM(T29-T28) -> 0 | V29: =V28 -> 394 | W29: =+V29-V28 -> 0 | X29: =X28 -> 141616 | Y29: =SUM(X29-X28) -> 0 | Z29: =Z28 -> 93176 | AA29: =Z29-Z28 -> 0 | AB29: =AB28 -> 262 | AC29: =AC28 -> 671 | AD29: =AC29-AC28 -> 0 | AE29: =AE28 -> 131.84 | AF29: =AE29-AE28 -> 0 | AG29: =AG28 -> 1445.01 | AH29: =AG29-AG28 -> 0 | AI29: =AF29+AH29 -> 0 | AJ29: =+Z29-Z28 -> 0 | AK29: =SUM(Y29-L29) -> 0 | AL29: =SUM(AJ29-W29) -> 0 | AM29: ='General information '!D29 -> 0 | AN29: ='General information '!H29 -> 0 | AP29: ='General information '!J29 -> 0 | AR29: =A29 -> 43914 | AS29: =AS28 -> 0.9 | AT29: =AT28 -> 80 | AU29: =AU28 -> 1.1 | AV29: =AV28 -> 107 | AW29: 2.9 | AX29: =AX28 -> 108 | AY29: =AS29*AT29 -> 72 | AZ29: =AU29*AV29 -> 117.7 | BA29: =AW29*AX29 -> 313.2 | BB29: =AY29-AY28 -> 0 | BC29: =AZ29-AZ28 -> 0 | BD29: =BA29-BA28 -> 0 | BE29: =SUM(BB29:BD29) -> 0 | BF29: =SUM(I29-BE29) -> 0 | BG29: =SUM(I29-BF29) -> 0
A30: =ELEC!C27 -> 43915 | B30: =B29 -> 108473 | C30: =B30-B29 -> 0 | D30: =C30/27 -> 0 | E30: =SUM((C30*$E$4)+(7500/'EDl log'!$A$38)) -> 241.93548 | G30: =G29 -> 593048 | H30: =G30-G29 -> 0 | I30: =C30+H30 -> 0 | J30: =IF(I30>0,E30/I30,0) -> 0 | K30: ='Swimming Pool quality check '!H30 -> 5921 | L30: =K30-K29 -> 0 | M30: =M29 -> 457.44 | N30: =SUM(M30-M29) -> 0 | O30: =O29 -> 529.52 | P30: =SUM(O30-O29) -> 0 | Q30: =SUM(P30+N30) -> 0 | T30: =T29 -> 4679 | U30: =SUM(T30-T29) -> 0 | V30: =V29 -> 394 | W30: =+V30-V29 -> 0 | X30: =X29 -> 141616 | Y30: =SUM(X30-X29) -> 0 | Z30: =Z29 -> 93176 | AA30: =Z30-Z29 -> 0 | AB30: =AB29 -> 262 | AC30: =AC29 -> 671 | AD30: =AC30-AC29 -> 0 | AE30: =AE29 -> 131.84 | AF30: =AE30-AE29 -> 0 | AG30: =AG29 -> 1445.01 | AH30: =AG30-AG29 -> 0 | AI30: =AF30+AH30 -> 0 | AJ30: =+Z30-Z29 -> 0 | AK30: =SUM(Y30-L30) -> 0 | AL30: =SUM(AJ30-W30) -> 0 | AM30: ='General information '!D30 -> 0 | AN30: ='General information '!H30 -> 0 | AP30: ='General information '!J30 -> 0 | AR30: =A30 -> 43915 | AS30: =AS29 -> 0.9 | AT30: =AT29 -> 80 | AU30: =AU29 -> 1.1 | AV30: =AV29 -> 107 | AW30: 2.9 | AX30: =AX29 -> 108 | AY30: =AS30*AT30 -> 72 | AZ30: =AU30*AV30 -> 117.7 | BA30: =AW30*AX30 -> 313.2 | BB30: =AY30-AY29 -> 0 | BC30: =AZ30-AZ29 -> 0 | BD30: =BA30-BA29 -> 0 | BE30: =SUM(BB30:BD30) -> 0 | BF30: =SUM(I30-BE30) -> 0 | BG30: =SUM(I30-BF30) -> 0
A31: =ELEC!C28 -> 43916 | B31: =B30 -> 108473 | C31: =B31-B30 -> 0 | D31: =C31/27 -> 0 | E31: =SUM((C31*$E$4)+(7500/'EDl log'!$A$38)) -> 241.93548 | G31: =G30 -> 593048 | H31: =G31-G30 -> 0 | I31: =C31+H31 -> 0 | J31: =IF(I31>0,E31/I31,0) -> 0 | K31: ='Swimming Pool quality check '!H31 -> 5921 | L31: =K31-K30 -> 0 | M31: =M30 -> 457.44 | N31: =SUM(M31-M30) -> 0 | O31: =O30 -> 529.52 | P31: =SUM(O31-O30) -> 0 | Q31: =SUM(P31+N31) -> 0 | T31: =T30 -> 4679 | U31: =SUM(T31-T30) -> 0 | V31: =V30 -> 394 | W31: =+V31-V30 -> 0 | X31: =X30 -> 141616 | Y31: =SUM(X31-X30) -> 0 | Z31: =Z30 -> 93176 | AA31: =Z31-Z30 -> 0 | AB31: =AB30 -> 262 | AC31: =AC30 -> 671 | AD31: =AC31-AC30 -> 0 | AE31: =AE30 -> 131.84 | AF31: =AE31-AE30 -> 0 | AG31: =AG30 -> 1445.01 | AH31: =AG31-AG30 -> 0 | AI31: =AF31+AH31 -> 0 | AJ31: =+Z31-Z30 -> 0 | AK31: =SUM(Y31-L31) -> 0 | AL31: =SUM(AJ31-W31) -> 0 | AM31: ='General information '!D31 -> 0 | AN31: ='General information '!H31 -> 0 | AP31: ='General information '!J31 -> 0 | AR31: =A31 -> 43916 | AS31: =AS30 -> 0.9 | AT31: =AT30 -> 80 | AU31: =AU30 -> 1.1 | AV31: =AV30 -> 107 | AW31: 2.9 | AX31: =AX30 -> 108 | AY31: =AS31*AT31 -> 72 | AZ31: =AU31*AV31 -> 117.7 | BA31: =AW31*AX31 -> 313.2 | BB31: =AY31-AY30 -> 0 | BC31: =AZ31-AZ30 -> 0 | BD31: =BA31-BA30 -> 0 | BE31: =SUM(BB31:BD31) -> 0 | BF31: =SUM(I31-BE31) -> 0 | BG31: =SUM(I31-BF31) -> 0
A32: =ELEC!C29 -> 43917 | B32: =B31 -> 108473 | C32: =B32-B31 -> 0 | D32: =C32/27 -> 0 | E32: =SUM((C32*$E$4)+(7500/'EDl log'!$A$38)) -> 241.93548 | G32: =G31 -> 593048 | H32: =G32-G31 -> 0 | I32: =C32+H32 -> 0 | J32: =IF(I32>0,E32/I32,0) -> 0 | K32: ='Swimming Pool quality check '!H32 -> 5921 | L32: =K32-K31 -> 0 | M32: =M31 -> 457.44 | N32: =SUM(M32-M31) -> 0 | O32: =O31 -> 529.52 | P32: =SUM(O32-O31) -> 0 | Q32: =SUM(P32+N32) -> 0 | T32: =T31 -> 4679 | U32: =SUM(T32-T31) -> 0 | V32: =V31 -> 394 | W32: =+V32-V31 -> 0 | X32: =X31 -> 141616 | Y32: =SUM(X32-X31) -> 0 | Z32: =Z31 -> 93176 | AA32: =Z32-Z31 -> 0 | AB32: =AB31 -> 262 | AC32: =AC31 -> 671 | AD32: =AC32-AC31 -> 0 | AE32: =AE31 -> 131.84 | AF32: =AE32-AE31 -> 0 | AG32: =AG31 -> 1445.01 | AH32: =AG32-AG31 -> 0 | AI32: =AF32+AH32 -> 0 | AJ32: =+Z32-Z31 -> 0 | AK32: =SUM(Y32-L32) -> 0 | AL32: =SUM(AJ32-W32) -> 0 | AM32: ='General information '!D32 -> 0 | AN32: ='General information '!H32 -> 0 | AP32: ='General information '!J32 -> 0 | AR32: =A32 -> 43917 | AS32: =AS31 -> 0.9 | AT32: =AT31 -> 80 | AU32: =AU31 -> 1.1 | AV32: =AV31 -> 107 | AW32: 2.9 | AX32: =AX31 -> 108 | AY32: =AS32*AT32 -> 72 | AZ32: =AU32*AV32 -> 117.7 | BA32: =AW32*AX32 -> 313.2 | BB32: =AY32-AY31 -> 0 | BC32: =AZ32-AZ31 -> 0 | BD32: =BA32-BA31 -> 0 | BE32: =SUM(BB32:BD32) -> 0 | BF32: =SUM(I32-BE32) -> 0 | BG32: =SUM(I32-BF32) -> 0
A33: =ELEC!C30 -> 43918 | B33: =B32 -> 108473 | C33: =B33-B32 -> 0 | D33: =C33/27 -> 0 | E33: =SUM((C33*$E$4)+(7500/'EDl log'!$A$38)) -> 241.93548 | G33: =G32 -> 593048 | H33: =G33-G32 -> 0 | I33: =C33+H33 -> 0 | J33: =IF(I33>0,E33/I33,0) -> 0 | K33: ='Swimming Pool quality check '!H33 -> 5921 | L33: =K33-K32 -> 0 | M33: =M32 -> 457.44 | N33: =SUM(M33-M32) -> 0 | O33: =O32 -> 529.52 | P33: =SUM(O33-O32) -> 0 | Q33: =SUM(P33+N33) -> 0 | T33: =T32 -> 4679 | U33: =SUM(T33-T32) -> 0 | V33: =V32 -> 394 | W33: =+V33-V32 -> 0 | X33: =X32 -> 141616 | Y33: =SUM(X33-X32) -> 0 | Z33: =Z32 -> 93176 | AA33: =Z33-Z32 -> 0 | AB33: =AB32 -> 262 | AC33: =AC32 -> 671 | AD33: =AC33-AC32 -> 0 | AE33: =AE32 -> 131.84 | AF33: =AE33-AE32 -> 0 | AG33: =AG32 -> 1445.01 | AH33: =AG33-AG32 -> 0 | AI33: =AF33+AH33 -> 0 | AJ33: =+Z33-Z32 -> 0 | AK33: =SUM(Y33-L33) -> 0 | AL33: =SUM(AJ33-W33) -> 0 | AM33: ='General information '!D33 -> 0 | AN33: ='General information '!H33 -> 0 | AP33: ='General information '!J33 -> 0 | AR33: =A33 -> 43918 | AS33: =AS32 -> 0.9 | AT33: =AT32 -> 80 | AU33: =AU32 -> 1.1 | AV33: =AV32 -> 107 | AW33: 2.9 | AX33: =AX32 -> 108 | AY33: =AS33*AT33 -> 72 | AZ33: =AU33*AV33 -> 117.7 | BA33: =AW33*AX33 -> 313.2 | BB33: =AY33-AY32 -> 0 | BC33: =AZ33-AZ32 -> 0 | BD33: =BA33-BA32 -> 0 | BE33: =SUM(BB33:BD33) -> 0 | BF33: =SUM(I33-BE33) -> 0 | BG33: =SUM(I33-BF33) -> 0
A34: =ELEC!C31 -> 43919 | B34: =B33 -> 108473 | C34: =B34-B33 -> 0 | D34: =C34/27 -> 0 | E34: =SUM((C34*$E$4)+(7500/'EDl log'!$A$38)) -> 241.93548 | G34: =G33 -> 593048 | H34: =G34-G33 -> 0 | I34: =C34+H34 -> 0 | J34: =IF(I34>0,E34/I34,0) -> 0 | K34: ='Swimming Pool quality check '!H34 -> 5921 | L34: =K34-K33 -> 0 | M34: =M33 -> 457.44 | N34: =SUM(M34-M33) -> 0 | O34: =O33 -> 529.52 | P34: =SUM(O34-O33) -> 0 | Q34: =SUM(P34+N34) -> 0 | T34: =T33 -> 4679 | U34: =SUM(T34-T33) -> 0 | V34: =V33 -> 394 | W34: =+V34-V33 -> 0 | X34: =X33 -> 141616 | Y34: =SUM(X34-X33) -> 0 | Z34: =Z33 -> 93176 | AA34: =Z34-Z33 -> 0 | AB34: =AB33 -> 262 | AC34: =AC33 -> 671 | AD34: =AC34-AC33 -> 0 | AE34: =AE33 -> 131.84 | AF34: =AE34-AE33 -> 0 | AG34: =AG33 -> 1445.01 | AH34: =AG34-AG33 -> 0 | AI34: =AF34+AH34 -> 0 | AJ34: =+Z34-Z33 -> 0 | AK34: =SUM(Y34-L34) -> 0 | AL34: =SUM(AJ34-W34) -> 0 | AM34: ='General information '!D34 -> 0 | AN34: ='General information '!H34 -> 0 | AP34: ='General information '!J34 -> 0 | AR34: =A34 -> 43919 | AS34: =AS33 -> 0.9 | AT34: =AT33 -> 80 | AU34: =AU33 -> 1.1 | AV34: =AV33 -> 107 | AW34: 2.9 | AX34: =AX33 -> 108 | AY34: =AS34*AT34 -> 72 | AZ34: =AU34*AV34 -> 117.7 | BA34: =AW34*AX34 -> 313.2 | BB34: =AY34-AY33 -> 0 | BC34: =AZ34-AZ33 -> 0 | BD34: =BA34-BA33 -> 0 | BE34: =SUM(BB34:BD34) -> 0 | BF34: =SUM(I34-BE34) -> 0 | BG34: =SUM(I34-BF34) -> 0
A35: =ELEC!C32 -> 43920 | B35: =B34 -> 108473 | C35: =B35-B34 -> 0 | D35: =C35/27 -> 0 | E35: =SUM((C35*$E$4)+(7500/'EDl log'!$A$38)) -> 241.93548 | G35: =G34 -> 593048 | H35: =G35-G34 -> 0 | I35: =C35+H35 -> 0 | J35: =IF(I35>0,E35/I35,0) -> 0 | K35: ='Swimming Pool quality check '!H35 -> 5921 | L35: =K35-K34 -> 0 | M35: =M34 -> 457.44 | N35: =SUM(M35-M34) -> 0 | O35: =O34 -> 529.52 | P35: =SUM(O35-O34) -> 0 | Q35: =SUM(P35+N35) -> 0 | T35: =T34 -> 4679 | U35: =SUM(T35-T34) -> 0 | V35: =V34 -> 394 | W35: =+V35-V34 -> 0 | X35: =X34 -> 141616 | Y35: =SUM(X35-X34) -> 0 | Z35: =Z34 -> 93176 | AA35: =Z35-Z34 -> 0 | AB35: 261 | AC35: =AC34 -> 671 | AD35: =AC35-AC34 -> 0 | AE35: =AE34 -> 131.84 | AF35: =AE35-AE34 -> 0 | AG35: =AG34 -> 1445.01 | AH35: =AG35-AG34 -> 0 | AI35: =AF35+AH35 -> 0 | AJ35: =+Z35-Z34 -> 0 | AK35: =SUM(Y35-L35) -> 0 | AL35: =SUM(AJ35-W35) -> 0 | AM35: ='General information '!D35 -> 0 | AN35: ='General information '!H35 -> 0 | AP35: ='General information '!J35 -> 0 | AR35: =A35 -> 43920 | AS35: =AS34 -> 0.9 | AT35: =AT34 -> 80 | AU35: =AU34 -> 1.1 | AV35: =AV34 -> 107 | AW35: 2.9 | AX35: =AX34 -> 108 | AY35: =AS35*AT35 -> 72 | AZ35: =AU35*AV35 -> 117.7 | BA35: =AW35*AX35 -> 313.2 | BB35: =AY35-AY34 -> 0 | BC35: =AZ35-AZ34 -> 0 | BD35: =BA35-BA34 -> 0 | BE35: =SUM(BB35:BD35) -> 0 | BF35: =SUM(I35-BE35) -> 0 | BG35: =SUM(I35-BF35) -> 0
A36: =ELEC!C33 -> 43921 | B36: =B35 -> 108473 | C36: =B36-B35 -> 0 | D36: =C36/27 -> 0 | E36: =SUM((C36*$E$4)+(7500/'EDl log'!$A$38)) -> 241.93548 | G36: =G35 -> 593048 | H36: =G36-G35 -> 0 | I36: =C36+H36 -> 0 | J36: =IF(I36>0,E36/I36,0) -> 0 | K36: ='Swimming Pool quality check '!H36 -> 5921 | L36: =K36-K35 -> 0 | M36: =M35 -> 457.44 | N36: =SUM(M36-M35) -> 0 | O36: =O35 -> 529.52 | P36: =SUM(O36-O35) -> 0 | Q36: =SUM(P36+N36) -> 0 | T36: =T35 -> 4679 | U36: =SUM(T36-T35) -> 0 | V36: =V35 -> 394 | W36: =+V36-V35 -> 0 | X36: =X35 -> 141616 | Y36: =SUM(X36-X35) -> 0 | Z36: =Z35 -> 93176 | AA36: =Z36-Z35 -> 0 | AB36: =AB35 -> 261 | AC36: =AC35 -> 671 | AD36: =AC36-AC35 -> 0 | AE36: =AE35 -> 131.84 | AF36: =AE36-AE35 -> 0 | AG36: =AG35 -> 1445.01 | AH36: =AG36-AG35 -> 0 | AI36: =AF36+AH36 -> 0 | AJ36: =+Z36-Z35 -> 0 | AK36: =SUM(Y36-L36) -> 0 | AL36: =SUM(AJ36-W36) -> 0 | AM36: ='General information '!D36 -> 0 | AN36: ='General information '!H36 -> 0 | AP36: ='General information '!J36 -> 0 | AR36: =A36 -> 43921 | AS36: =AS35 -> 0.9 | AT36: =AT35 -> 80 | AU36: =AU35 -> 1.1 | AV36: =AV35 -> 107 | AW36: 2.9 | AX36: =AX35 -> 108 | AY36: =AS36*AT36 -> 72 | AZ36: =AU36*AV36 -> 117.7 | BA36: =AW36*AX36 -> 313.2 | BB36: =AY36-AY35 -> 0 | BC36: =AZ36-AZ35 -> 0 | BD36: =BA36-BA35 -> 0 | BE36: =SUM(BB36:BD36) -> 0 | BF36: =SUM(I36-BE36) -> 0 | BG36: =SUM(I36-BF36) -> 0
C37: =SUM(C6:C36) -> 0 | D37: =SUM(D6:D36) -> 0 | F37: =SUM(F6:F36) -> 0 | H37: =SUM(H6:H36) -> 795 | I37: =SUM(I6:I36) -> 795 | L37: =SUM(L7:L36) -> 0 | Q37: =SUM(Q5:Q35) -> 0 | U37: =SUM(U6:U36) -> 15 | Y37: =SUM(Y35,Y33,Y31,Y29,Y27,Y25,Y23,Y21,Y19,Y17,Y15,Y13,Y11,Y9,Y7+Y36) -> 245 | AJ37: =SUM(AJ6:AJ36) -> 167 | AK37: =SUM(Y37-L37) -> 245 | AL37: =SUM(AL6:AL36) -> 165 | AT37: =AT36 -> 80
C38: =+C37*1.66 -> 0 | E38: =SUM(E6:E36) -> 7500 | F38: =SUM(F6:F36) -> 0 | H38: 7500 | I38: =SUM('General information '!G37/WATER!I37) -> 0.14841509 | O38: =SUM(Q37+I37) -> 795 | Z38: =SUM(Y37:AJ37) -> 412 | AK38: =SUM(Y38-L38) -> 0
B39: =9*27 -> 243 | D39: =SUM(D21:D35) -> 0 | F39: =SUM(F6:F36) -> 0 | G39: =SUM(I37) -> 795 | H39: =SUM(H38+C38) -> 7500 | K39: =SUM(H39/G39) -> 9.4339623 | AJ39: =SUM(C38-AK38) -> 0 | AM39: =SUM(AJ39/AO38) -> #DIV/0!

Sheet graphic

Sheet General information 
A1: GENERAL & HOTEL'S INFORMATION SHEET
B4: Max Temp | C4: MIN TEMP | D4: AVE TEMP | E4: AVE Humidity | F4: AVE OCC | G4: # of OCC Rooms | H4: Ball room | I4: Meeting rooms | J4: Outlets | K4: Total covers | L4: # of permenant Emp | M4: # of casuals | N4: Total # of EMP | O4: # of EMP/OCC Room
A5: =ELEC!C2 -> 43890 | B5: ='[1]General information '!B34 -> 18 | C5: ='[1]General information '!C34 -> 13 | D5: ='[1]General information '!D34 -> 15.5 | E5: ='[1]General information '!E34 -> 0.65 | F5: ='[1]General information '!F34 -> 0.1826 | G5: ='[1]General information '!G34 -> 41.998 | H5: ='[1]General information '!H34 -> 150 | I5: ='[1]General information '!I34 -> 0 | ... O5: ='[1]General information '!O34 -> 0
A6: =ELEC!C3 -> 43891 | B6: 17 | C6: 10 | D6: =(C6+B6)/2 -> 13.5 | E6: 0.65 | F6: 0.1522 | G6: =F6*230 -> 35.006 | H6: 248 | K6: =+J6+H6 -> 248
A7: =ELEC!C4 -> 43892 | B7: 18 | C7: 11 | D7: =(C7+B7)/2 -> 14.5 | E7: 0.66 | F7: 0.113 | G7: =F7*230 -> 25.99 | H7: 0 | I7: 0 | J7: 170 | K7: =+J7+H7 -> 170
A8: =ELEC!C5 -> 43893 | B8: 19 | C8: 12 | D8: =(C8+B8)/2 -> 15.5 | E8: 0.65 | F8: 0.1217 | G8: =F8*230 -> 27.991 | J8: 168 | K8: =+J8+H8 -> 168
A9: =ELEC!C6 -> 43894 | B9: 19 | C9: 12 | D9: =(C9+B9)/2 -> 15.5 | E9: 0.6 | F9: 0.1261 | G9: =F9*230 -> 29.003 | J9: 189 | K9: =+J9+H9 -> 189
A10: =ELEC!C7 -> 43895 | D10: =(C10+B10)/2 -> 0 | G10: =F10*230 -> 0 | K10: =+J10+H10 -> 0
A11: =ELEC!C8 -> 43896 | D11: =(C11+B11)/2 -> 0 | G11: =F11*230 -> 0 | K11: =+J11+H11 -> 0
A12: =ELEC!C9 -> 43897 | D12: =(C12+B12)/2 -> 0 | G12: =F12*230 -> 0 | K12: =+J12+H12 -> 0
A13: =ELEC!C10 -> 43898 | D13: =(C13+B13)/2 -> 0 | G13: =F13*230 -> 0 | K13: =+J13+H13 -> 0
A14: =ELEC!C11 -> 43899 | D14: =(C14+B14)/2 -> 0 | G14: =F14*230 -> 0 | K14: =+J14+H14 -> 0
A15: =ELEC!C12 -> 43900 | D15: =(C15+B15)/2 -> 0 | G15: =F15*230 -> 0 | K15: =+J15+H15 -> 0
A16: =ELEC!C13 -> 43901 | D16: =(C16+B16)/2 -> 0 | G16: =F16*230 -> 0 | K16: =+J16+H16 -> 0
A17: =ELEC!C14 -> 43902 | D17: =(C17+B17)/2 -> 0 | G17: =F17*230 -> 0 | K17: =+J17+H17 -> 0
A18: =ELEC!C15 -> 43903 | D18: =(C18+B18)/2 -> 0 | G18: =F18*230 -> 0 | K18: =+J18+H18 -> 0
A19: =ELEC!C16 -> 43904 | D19: =(C19+B19)/2 -> 0 | G19: =F19*230 -> 0 | K19: =+J19+H19 -> 0
A20: =ELEC!C17 -> 43905 | D20: =(C20+B20)/2 -> 0 | G20: =F20*230 -> 0 | K20: =+J20+H20 -> 0
A21: =ELEC!C18 -> 43906 | D21: =(C21+B21)/2 -> 0 | G21: =F21*230 -> 0 | K21: =+J21+H21 -> 0
... A26: =ELEC!C23 -> 43911 | D26: =(C26+B26)/2 -> 0 | G26: =F26*230 -> 0 | K26: =+J26+H26 -> 0
A27: =ELEC!C24 -> 43912 | D27: =(C27+B27)/2 -> 0 | G27: =F27*230 -> 0 | K27: =+J27+H27+I27 -> 0
A28: =ELEC!C25 -> 43913 | D28: =(C28+B28)/2 -> 0 | G28: =F28*230 -> 0 | K28: =+J28+H28+I28 -> 0
A29: =ELEC!C26 -> 43914 | D29: =(C29+B29)/2 -> 0 | G29: =F29*230 -> 0 | K29: =+J29+H29+I29 -> 0
A30: =ELEC!C27 -> 43915 | D30: =(C30+B30)/2 -> 0 | G30: =F30*230 -> 0 | K30: =+J30+H30+I30 -> 0
A31: =ELEC!C28 -> 43916 | D31: =(C31+B31)/2 -> 0 | G31: =F31*230 -> 0 | K31: =+J31+H31+I31 -> 0
A32: =ELEC!C29 -> 43917 | D32: =(C32+B32)/2 -> 0 | G32: =F32*230 -> 0 | K32: =+J32+H32+I32 -> 0
A33: =ELEC!C30 -> 43918 | D33: =(C33+B33)/2 -> 0 | G33: =F33*230 -> 0 | K33: =+J33+H33+I33 -> 0
A34: =ELEC!C31 -> 43919 | D34: =(C34+B34)/2 -> 0 | G34: =F34*230 -> 0 | K34: =+J34+H34+I34 -> 0
A35: =ELEC!C32 -> 43920 | D35: =(C35+B35)/2 -> 0 | G35: =F35*230 -> 0 | K35: =+J35+H35+I35 -> 0
A36: =ELEC!C33 -> 43921 | D36: =(C36+B36)/2 -> 0 | G36: =F36*230 -> 0 | K36: =+J36+H36+I36 -> 0
F37: =AVERAGE(F6:F36) -> 0.12825 | G37: =SUM(G6:G35) -> 117.99
D38: =SUM(D6:D36)/'EDl log'!A36 -> 14.75
I41: http://www.accuweather.com/en/lb/lebanon-weather

Sheet tanks
B2: Tank 1 | D2: Tank 2 | F2: Tank 3 | H2: Tank 4 | J2: Tank 5 | L2: Tank 6 | N2: Tank 7 | P2: Tank 8 | R2: Tank 9 | T2: Tank 10 | V2: Tank 11 | Z2: Tank 1 | AB2: Tank 2 | AD2: Tank 3 | AF2: Tank 4 | AH2: Tank 5 | AJ2: Tank 6 | AL2: Tank 7
B3: 6670 | D3: =SUM(B3) -> 6670 | F3: =SUM(D3) -> 6670 | H3: =SUM(F3) -> 6670 | J3: =SUM(H3) -> 6670 | L3: =SUM(J3) -> 6670 | N3: =SUM(L3) -> 6670 | P3: =SUM(N3) -> 6670 | R3: =SUM(P3) -> 6670 | T3: =SUM(R3) -> 6670 | V3: =SUM(T3) -> 6670 | W3: =SUM(B3:V3) -> 73370 | Z3: 2800 | AB3: 2800 | AD3: 2800 | AF3: 2800 | AH3: 2800 | AJ3: 2800 | AL3: 2800 | AM3: =SUM(Z3:AL3) -> 19600 | AO3: =SUM(AM3+W3) -> 92970 | AR3: Total sotck | AS3: Diesel Cons Per day | AT3: Diesel Delivery | BE3: Genset Co | BF3: Steam | BG3: Boil | BH3: Outdoor temperature
B4: =B3/310 -> 21.516129 | D4: =SUM(B4) -> 21.516129 | F4: =SUM(D4) -> 21.516129 | H4: =SUM(F4) -> 21.516129 | J4: =SUM(H4) -> 21.516129 | L4: =SUM(J4) -> 21.516129 | N4: =SUM(L4) -> 21.516129 | P4: =SUM(N4) -> 21.516129 | R4: =SUM(P4) -> 21.516129 | T4: =SUM(R4) -> 21.516129 | V4: =SUM(T4) -> 21.516129 | Z4: =Z3/280 -> 10 | AA4: =AA3/280 -> 0 | AB4: =AB3/280 -> 10 | AC4: =AC3/280 -> 0 | AD4: =AD3/280 -> 10 | AE4: =AE3/280 -> 0 | AF4: =AF3/280 -> 10 | AG4: =AG3/280 -> 0 | ... AL4: =AL3/280 -> 10 | AT4: Delivery | AU4: Cost /L | AW4: Boiler+Steam | AX4: Generator | AZ4: Occupancy | BA4: AVE TEPM | BB4: AVE Humidity
A5: =ELEC!C2 -> 43890 | B5: =[1]tanks!B34 -> 233.3 | C5: =[1]tanks!C34 -> 5019.7129 | D5: =[1]tanks!D34 -> 233.3 | E5: =[1]tanks!E34 -> 5019.7129 | F5: =[1]tanks!F34 -> 233.3 | G5: =[1]tanks!G34 -> 5019.7129 | H5: =[1]tanks!H34 -> 233.3 | I5: =[1]tanks!I34 -> 5019.7129 | ... BH5: =[1]tanks!BH34 -> 0
A6: =ELEC!C3 -> 43891 | B6: ='B5'!B5 -> 229 | C6: =B6*$B$4 -> 4927.1935 | D6: =SUM(B6) -> 229 | E6: =D6*$B$4 -> 4927.1935 | F6: =SUM(D6) -> 229 | G6: =F6*$B$4 -> 4927.1935 | H6: =SUM(F6) -> 229 | I6: =H6*$B$4 -> 4927.1935 | J6: =SUM(H6) -> 229 | K6: =J6*$B$4 -> 4927.1935 | L6: =SUM(J6) -> 229 | M6: =L6*$B$4 -> 4927.1935 | N6: =SUM(L6) -> 229 | O6: =N6*$B$4 -> 4927.1935 | P6: =SUM(N6) -> 229 | Q6: =P6*$B$4 -> 4927.1935 | R6: =SUM(P6) -> 229 | S6: =R6*$B$4 -> 4927.1935 | T6: =SUM(R6) -> 229 | U6: =T6*$B$4 -> 4927.1935 | V6: =SUM(T6) -> 229 | W6: =V6*$B$4 -> 4927.1935 | X6: =SUM(Y6/73370) -> 0.73870968 | Y6: =SUM(C6+E6+G6+I6+K6+M6+O6+Q6+S6+U6+W6) -> 54199.129 | Z6: ='B5'!C5 -> 234.4 | AA6: =SUM(Z6*$Z$4) -> 2344 | AB6: =SUM(Z6) -> 234.4 | AC6: =SUM(AB6*$Z$4) -> 2344 | AD6: =SUM(AB6) -> 234.4 | AE6: =SUM(AD6*$Z$4) -> 2344 | AF6: =SUM(AD6) -> 234.4 | AG6: =SUM(AF6*$Z$4) -> 2344 | AH6: =SUM(AF6) -> 234.4 | AI6: =SUM(AH6*$Z$4) -> 2344 | AJ6: =SUM(AH6) -> 234.4 | AK6: =SUM(AJ6*$Z$4) -> 2344 | AL6: =SUM(AJ6) -> 234.4 | AM6: =SUM(AL6*$Z$4) -> 2344 | AN6: =SUM(AO6/19600) -> 0.83714286 | AO6: =SUM(AA6+AC6+AE6+AG6+AI6+AK6+AM6) -> 16408 | AQ6: =SUM(AR6/92970) -> 0.75946143 | AR6: =SUM(AO6+Y6) -> 70607.129 | AS6: =SUM(AR6-AR5-AT6) -> -1346.8129 | AT6: 0.1 | AU6: 0.1 | AV6: =IF(AT6>0,AU6,AV5) -> 0.1 | AW6: =-SUM('B5'!AI5) -> -580 | AX6: =-SUM(AW6-AS6) -> -766.8129 | AY6: =SUM(AX6+AW6) -> -1346.8129 | AZ6: =ELEC!A3 -> 0.1522 | BA6: ='General information '!D6 -> 13.5 | BB6: =SUM('General information '!E6) -> 0.65 | BC6: =IF(AR3>=AR6,0,1) -> 0 | BD6: 19222 | BE6: =(305/1185)*ELEC!Q4 -> 218.51899 | BG6: =#REF!-BE6 -> #REF! | BH6: 21
A7: =ELEC!C4 -> 43892 | B7: ='B5'!B6 -> 224 | C7: =B7*$B$4 -> 4819.6129 | D7: =SUM(B7) -> 224 | E7: =D7*$B$4 -> 4819.6129 | F7: =SUM(D7) -> 224 | G7: =F7*$B$4 -> 4819.6129 | H7: =SUM(F7) -> 224 | I7: =H7*$B$4 -> 4819.6129 | J7: =SUM(H7) -> 224 | K7: =J7*$B$4 -> 4819.6129 | L7: =SUM(J7) -> 224 | M7: =L7*$B$4 -> 4819.6129 | N7: =SUM(L7) -> 224 | O7: =N7*$B$4 -> 4819.6129 | P7: =SUM(N7) -> 224 | Q7: =P7*$B$4 -> 4819.6129 | R7: =SUM(P7) -> 224 | S7: =R7*$B$4 -> 4819.6129 | T7: =SUM(R7) -> 224 | U7: =T7*$B$4 -> 4819.6129 | V7: =SUM(T7) -> 224 | W7: =V7*$B$4 -> 4819.6129 | X7: =SUM(Y7/73370) -> 0.72258065 | Y7: =SUM(C7+E7+G7+I7+K7+M7+O7+Q7+S7+U7+W7) -> 53015.742 | Z7: ='B5'!C6 -> 230 | AA7: =SUM(Z7*$Z$4) -> 2300 | AB7: =SUM(Z7) -> 230 | AC7: =SUM(AB7*$Z$4) -> 2300 | AD7: =SUM(AB7) -> 230 | AE7: =SUM(AD7*$Z$4) -> 2300 | AF7: =SUM(AD7) -> 230 | AG7: =SUM(AF7*$Z$4) -> 2300 | AH7: =SUM(AF7) -> 230 | AI7: =SUM(AH7*$Z$4) -> 2300 | AJ7: =SUM(AH7) -> 230 | AK7: =SUM(AJ7*$Z$4) -> 2300 | AL7: =SUM(AJ7) -> 230 | AM7: =SUM(AL7*$Z$4) -> 2300 | AN7: =SUM(AO7/19600) -> 0.82142857 | AO7: =SUM(AA7+AC7+AE7+AG7+AI7+AK7+AM7) -> 16100 | AQ7: =SUM(AR7/92970) -> 0.74341983 | AR7: =SUM(AO7+Y7) -> 69115.742 | AS7: =SUM(AR7-AR6-AT7) -> -1491.3871 | AV7: =IF(AT7>0,AU7,AV6) -> 0.1 | AW7: =-SUM('B5'!AI6) -> -567 | AX7: =-SUM(AW7-AS7) -> -924.3871 | AY7: =SUM(AX7+AW7) -> -1491.3871 | AZ7: =ELEC!A4 -> 0.113 | BA7: ='General information '!D7 -> 14.5 | BB7: =SUM('General information '!E7) -> 0.66 | BC7: 0 | BD7: 19222 | BE7: =(305/1185)*ELEC!Q5 -> 480.27848 | BG7: =#REF!-BE7 -> #REF! | BH7: 19
A8: =ELEC!C5 -> 43893 | B8: ='B5'!B7 -> 220 | C8: =B8*$B$4 -> 4733.5484 | D8: =SUM(B8) -> 220 | E8: =D8*$B$4 -> 4733.5484 | F8: =SUM(D8) -> 220 | G8: =F8*$B$4 -> 4733.5484 | H8: =SUM(F8) -> 220 | I8: =H8*$B$4 -> 4733.5484 | J8: =SUM(H8) -> 220 | K8: =J8*$B$4 -> 4733.5484 | L8: =SUM(J8) -> 220 | M8: =L8*$B$4 -> 4733.5484 | N8: =SUM(L8) -> 220 | O8: =N8*$B$4 -> 4733.5484 | P8: =SUM(N8) -> 220 | Q8: =P8*$B$4 -> 4733.5484 | R8: =SUM(P8) -> 220 | S8: =R8*$B$4 -> 4733.5484 | T8: =SUM(R8) -> 220 | U8: =T8*$B$4 -> 4733.5484 | V8: =SUM(T8) -> 220 | W8: =V8*$B$4 -> 4733.5484 | X8: =SUM(Y8/73370) -> 0.70967742 | Y8: =SUM(C8+E8+G8+I8+K8+M8+O8+Q8+S8+U8+W8) -> 52069.032 | Z8: ='B5'!C7 -> 225.4 | AA8: =SUM(Z8*$Z$4) -> 2254 | AB8: =SUM(Z8) -> 225.4 | AC8: =SUM(AB8*$Z$4) -> 2254 | AD8: =SUM(AB8) -> 225.4 | AE8: =SUM(AD8*$Z$4) -> 2254 | AF8: =SUM(AD8) -> 225.4 | AG8: =SUM(AF8*$Z$4) -> 2254 | AH8: =SUM(AF8) -> 225.4 | AI8: =SUM(AH8*$Z$4) -> 2254 | AJ8: =SUM(AH8) -> 225.4 | AK8: =SUM(AJ8*$Z$4) -> 2254 | AL8: =SUM(AJ8) -> 225.4 | AM8: =SUM(AL8*$Z$4) -> 2254 | AN8: =SUM(AO8/19600) -> 0.805 | AO8: =SUM(AA8+AC8+AE8+AG8+AI8+AK8+AM8) -> 15778 | AQ8: =SUM(AR8/92970) -> 0.72977339 | AR8: =SUM(AO8+Y8) -> 67847.032 | AS8: =SUM(AR8-AR7-AT8) -> -1268.7097 | AV8: =IF(AT8>0,AU8,AV7) -> 0.1 | AW8: =-SUM('B5'!AI7) -> -1061.4 | AX8: =-SUM(AW8-AS8) -> -207.30968 | AY8: =SUM(AX8+AW8) -> -1268.7097 | AZ8: =ELEC!A5 -> 0.1217 | BA8: ='General information '!D8 -> 15.5 | BB8: =SUM('General information '!E8) -> 0.65 | BC8: =IF(AR7>=AR8,0,1) -> 0 | BD8: 19222 | BE8: =(305/1185)*ELEC!Q6 -> 620.55274 | BG8: =#REF!-BE8 -> #REF! | BH8: 16
A9: =ELEC!C6 -> 43894 | B9: ='B5'!B8 -> 213.3 | C9: =B9*$B$4 -> 4589.3903 | D9: =SUM(B9) -> 213.3 | E9: =D9*$B$4 -> 4589.3903 | F9: =SUM(D9) -> 213.3 | G9: =F9*$B$4 -> 4589.3903 | H9: =SUM(F9) -> 213.3 | I9: =H9*$B$4 -> 4589.3903 | J9: =SUM(H9) -> 213.3 | K9: =J9*$B$4 -> 4589.3903 | L9: =SUM(J9) -> 213.3 | M9: =L9*$B$4 -> 4589.3903 | N9: =SUM(L9) -> 213.3 | O9: =N9*$B$4 -> 4589.3903 | P9: =SUM(N9) -> 213.3 | Q9: =P9*$B$4 -> 4589.3903 | R9: =SUM(P9) -> 213.3 | S9: =R9*$B$4 -> 4589.3903 | T9: =SUM(R9) -> 213.3 | U9: =T9*$B$4 -> 4589.3903 | V9: =SUM(T9) -> 213.3 | W9: =V9*$B$4 -> 4589.3903 | X9: =SUM(Y9/73370) -> 0.68806452 | Y9: =SUM(C9+E9+G9+I9+K9+M9+O9+Q9+S9+U9+W9) -> 50483.294 | Z9: ='B5'!C8 -> 219.2 | AA9: =SUM(Z9*$Z$4) -> 2192 | AB9: =SUM(Z9) -> 219.2 | AC9: =SUM(AB9*$Z$4) -> 2192 | AD9: =SUM(AB9) -> 219.2 | AE9: =SUM(AD9*$Z$4) -> 2192 | AF9: =SUM(AD9) -> 219.2 | AG9: =SUM(AF9*$Z$4) -> 2192 | AH9: =SUM(AF9) -> 219.2 | AI9: =SUM(AH9*$Z$4) -> 2192 | AJ9: =SUM(AH9) -> 219.2 | AK9: =SUM(AJ9*$Z$4) -> 2192 | AL9: =SUM(AJ9) -> 219.2 | AM9: =SUM(AL9*$Z$4) -> 2192 | AN9: =SUM(AO9/19600) -> 0.78285714 | AO9: =SUM(AA9+AC9+AE9+AG9+AI9+AK9+AM9) -> 15344 | AQ9: =SUM(AR9/92970) -> 0.70804876 | AR9: =SUM(AO9+Y9) -> 65827.294 | AS9: =SUM(AR9-AR8-AT9) -> -2019.7387 | AV9: =IF(AT9>0,AU9,AV8) -> 0.1 | AW9: =-SUM('B5'!AI8) -> -276.7 | AX9: =-SUM(AW9-AS9) -> -1743.0387 | AY9: =SUM(AX9+AW9) -> -2019.7387 | AZ9: =ELEC!A6 -> 0.1261 | BA9: ='General information '!D9 -> 15.5 | BB9: =SUM('General information '!E9) -> 0.6 | BC9: =IF(AR8>=AR9,0,1) -> 0 | BD9: 19222 | BE9: =(305/1185)*ELEC!Q7 -> 0 | BG9: =#REF!-BE9 -> #REF! | BH9: 18
A10: =ELEC!C7 -> 43895 | B10: ='B5'!B9 -> 213.3 | C10: =B10*$B$4 -> 4589.3903 | D10: =SUM(B10) -> 213.3 | E10: =D10*$B$4 -> 4589.3903 | F10: =SUM(D10) -> 213.3 | G10: =F10*$B$4 -> 4589.3903 | H10: =SUM(F10) -> 213.3 | I10: =H10*$B$4 -> 4589.3903 | J10: =SUM(H10) -> 213.3 | K10: =J10*$B$4 -> 4589.3903 | L10: =SUM(J10) -> 213.3 | M10: =L10*$B$4 -> 4589.3903 | N10: =SUM(L10) -> 213.3 | O10: =N10*$B$4 -> 4589.3903 | P10: =SUM(N10) -> 213.3 | Q10: =P10*$B$4 -> 4589.3903 | R10: =SUM(P10) -> 213.3 | S10: =R10*$B$4 -> 4589.3903 | T10: =SUM(R10) -> 213.3 | U10: =T10*$B$4 -> 4589.3903 | V10: =SUM(T10) -> 213.3 | W10: =V10*$B$4 -> 4589.3903 | X10: =SUM(Y10/73370) -> 0.68806452 | Y10: =SUM(C10+E10+G10+I10+K10+M10+O10+Q10+S10+U10+W10) -> 50483.294 | Z10: ='B5'!C9 -> 219.2 | AA10: =SUM(Z10*$Z$4) -> 2192 | AB10: =SUM(Z10) -> 219.2 | AC10: =SUM(AB10*$Z$4) -> 2192 | AD10: =SUM(AB10) -> 219.2 | AE10: =SUM(AD10*$Z$4) -> 2192 | AF10: =SUM(AD10) -> 219.2 | AG10: =SUM(AF10*$Z$4) -> 2192 | AH10: =SUM(AF10) -> 219.2 | AI10: =SUM(AH10*$Z$4) -> 2192 | AJ10: =SUM(AH10) -> 219.2 | AK10: =SUM(AJ10*$Z$4) -> 2192 | AL10: =SUM(AJ10) -> 219.2 | AM10: =SUM(AL10*$Z$4) -> 2192 | AN10: =SUM(AO10/19600) -> 0.78285714 | AO10: =SUM(AA10+AC10+AE10+AG10+AI10+AK10+AM10) -> 15344 | AQ10: =SUM(AR10/92970) -> 0.70804876 | AR10: =SUM(AO10+Y10) -> 65827.294 | AS10: =SUM(AR10-AR9-AT10) -> 0 | AV10: =IF(AT10>0,AU10,AV9) -> 0.1 | AW10: =-SUM('B5'!AI9) -> 0 | AX10: =-SUM(AW10-AS10) -> 0 | AY10: =SUM(AX10+AW10) -> 0 | AZ10: =ELEC!A7 -> 0 | BA10: ='General information '!D10 -> 0 | BB10: =SUM('General information '!E10) -> 0 | BC10: =IF(AR9>=AR10,0,1) -> 0 | BD10: 19222 | BE10: =(305/1185)*ELEC!Q8 -> 0 | BG10: =#REF!-BE10 -> #REF! | BH10: 16
A11: =ELEC!C8 -> 43896 | B11: ='B5'!B10 -> 213.3 | C11: =B11*$B$4 -> 4589.3903 | D11: =SUM(B11) -> 213.3 | E11: =D11*$B$4 -> 4589.3903 | F11: =SUM(D11) -> 213.3 | G11: =F11*$B$4 -> 4589.3903 | H11: =SUM(F11) -> 213.3 | I11: =H11*$B$4 -> 4589.3903 | J11: =SUM(H11) -> 213.3 | K11: =J11*$B$4 -> 4589.3903 | L11: =SUM(J11) -> 213.3 | M11: =L11*$B$4 -> 4589.3903 | N11: =SUM(L11) -> 213.3 | O11: =N11*$B$4 -> 4589.3903 | P11: =SUM(N11) -> 213.3 | Q11: =P11*$B$4 -> 4589.3903 | R11: =SUM(P11) -> 213.3 | S11: =R11*$B$4 -> 4589.3903 | T11: =SUM(R11) -> 213.3 | U11: =T11*$B$4 -> 4589.3903 | V11: =SUM(T11) -> 213.3 | W11: =V11*$B$4 -> 4589.3903 | X11: =SUM(Y11/73370) -> 0.68806452 | Y11: =SUM(C11+E11+G11+I11+K11+M11+O11+Q11+S11+U11+W11) -> 50483.294 | Z11: ='B5'!C10 -> 219.2 | AA11: =SUM(Z11*$Z$4) -> 2192 | AB11: =SUM(Z11) -> 219.2 | AC11: =SUM(AB11*$Z$4) -> 2192 | AD11: =SUM(AB11) -> 219.2 | AE11: =SUM(AD11*$Z$4) -> 2192 | AF11: =SUM(AD11) -> 219.2 | AG11: =SUM(AF11*$Z$4) -> 2192 | AH11: =SUM(AF11) -> 219.2 | AI11: =SUM(AH11*$Z$4) -> 2192 | AJ11: =SUM(AH11) -> 219.2 | AK11: =SUM(AJ11*$Z$4) -> 2192 | AL11: =SUM(AJ11) -> 219.2 | AM11: =SUM(AL11*$Z$4) -> 2192 | AN11: =SUM(AO11/19600) -> 0.78285714 | AO11: =SUM(AA11+AC11+AE11+AG11+AI11+AK11+AM11) -> 15344 | AQ11: =SUM(AR11/92970) -> 0.70804876 | AR11: =SUM(AO11+Y11) -> 65827.294 | AS11: =SUM(AR11-AR10-AT11) -> 0 | AV11: =IF(AT11>0,AU11,AV10) -> 0.1 | AW11: =-SUM('B5'!AI10) -> 0 | AX11: =-SUM(AW11-AS11) -> 0 | AY11: =SUM(AX11+AW11) -> 0 | AZ11: =ELEC!A8 -> 0 | BA11: ='General information '!D11 -> 0 | BB11: =SUM('General information '!E11) -> 0 | BC11: =IF(AR10>=AR11,0,1) -> 0 | BD11: 19222 | BE11: =(305/1185)*ELEC!Q9 -> 0 | BG11: =#REF!-BE11 -> #REF! | BH11: 16.5
A12: =ELEC!C9 -> 43897 | B12: ='B5'!B11 -> 213.3 | C12: =B12*$B$4 -> 4589.3903 | D12: =SUM(B12) -> 213.3 | E12: =D12*$B$4 -> 4589.3903 | F12: =SUM(D12) -> 213.3 | G12: =F12*$B$4 -> 4589.3903 | H12: =SUM(F12) -> 213.3 | I12: =H12*$B$4 -> 4589.3903 | J12: =SUM(H12) -> 213.3 | K12: =J12*$B$4 -> 4589.3903 | L12: =SUM(J12) -> 213.3 | M12: =L12*$B$4 -> 4589.3903 | N12: =SUM(L12) -> 213.3 | O12: =N12*$B$4 -> 4589.3903 | P12: =SUM(N12) -> 213.3 | Q12: =P12*$B$4 -> 4589.3903 | R12: =SUM(P12) -> 213.3 | S12: =R12*$B$4 -> 4589.3903 | T12: =SUM(R12) -> 213.3 | U12: =T12*$B$4 -> 4589.3903 | V12: =SUM(T12) -> 213.3 | W12: =V12*$B$4 -> 4589.3903 | X12: =SUM(Y12/73370) -> 0.68806452 | Y12: =SUM(C12+E12+G12+I12+K12+M12+O12+Q12+S12+U12+W12) -> 50483.294 | Z12: ='B5'!C11 -> 219.2 | AA12: =SUM(Z12*$Z$4) -> 2192 | AB12: =SUM(Z12) -> 219.2 | AC12: =SUM(AB12*$Z$4) -> 2192 | AD12: =SUM(AB12) -> 219.2 | AE12: =SUM(AD12*$Z$4) -> 2192 | AF12: =SUM(AD12) -> 219.2 | AG12: =SUM(AF12*$Z$4) -> 2192 | AH12: =SUM(AF12) -> 219.2 | AI12: =SUM(AH12*$Z$4) -> 2192 | AJ12: =SUM(AH12) -> 219.2 | AK12: =SUM(AJ12*$Z$4) -> 2192 | AL12: =SUM(AJ12) -> 219.2 | AM12: =SUM(AL12*$Z$4) -> 2192 | AN12: =SUM(AO12/19600) -> 0.78285714 | AO12: =SUM(AA12+AC12+AE12+AG12+AI12+AK12+AM12) -> 15344 | AQ12: =SUM(AR12/92970) -> 0.70804876 | AR12: =SUM(AO12+Y12) -> 65827.294 | AS12: =SUM(AR12-AR11-AT12) -> 0 | AV12: =IF(AT12>0,AU12,AV11) -> 0.1 | AW12: =-SUM('B5'!AI11) -> 0 | AX12: =-SUM(AW12-AS12) -> 0 | AY12: =SUM(AX12+AW12) -> 0 | AZ12: =ELEC!A9 -> 0 | BA12: ='General information '!D12 -> 0 | BB12: =SUM('General information '!E12) -> 0 | BC12: =IF(AR11>=AR12,0,1) -> 0 | BD12: 19222 | BE12: =(305/1185)*ELEC!Q10 -> 0 | BG12: =#REF!-BE12 -> #REF! | BH12: 15.5
A13: =ELEC!C10 -> 43898 | B13: ='B5'!B12 -> 213.3 | C13: =B13*$B$4 -> 4589.3903 | D13: =SUM(B13) -> 213.3 | E13: =D13*$B$4 -> 4589.3903 | F13: =SUM(D13) -> 213.3 | G13: =F13*$B$4 -> 4589.3903 | H13: =SUM(F13) -> 213.3 | I13: =H13*$B$4 -> 4589.3903 | J13: =SUM(H13) -> 213.3 | K13: =J13*$B$4 -> 4589.3903 | L13: =SUM(J13) -> 213.3 | M13: =L13*$B$4 -> 4589.3903 | N13: =SUM(L13) -> 213.3 | O13: =N13*$B$4 -> 4589.3903 | P13: =SUM(N13) -> 213.3 | Q13: =P13*$B$4 -> 4589.3903 | R13: =SUM(P13) -> 213.3 | S13: =R13*$B$4 -> 4589.3903 | T13: =SUM(R13) -> 213.3 | U13: =T13*$B$4 -> 4589.3903 | V13: =SUM(T13) -> 213.3 | W13: =V13*$B$4 -> 4589.3903 | X13: =SUM(Y13/73370) -> 0.68806452 | Y13: =SUM(C13+E13+G13+I13+K13+M13+O13+Q13+S13+U13+W13) -> 50483.294 | Z13: ='B5'!C12 -> 219.2 | AA13: =SUM(Z13*$Z$4) -> 2192 | AB13: =SUM(Z13) -> 219.2 | AC13: =SUM(AB13*$Z$4) -> 2192 | AD13: =SUM(AB13) -> 219.2 | AE13: =SUM(AD13*$Z$4) -> 2192 | AF13: =SUM(AD13) -> 219.2 | AG13: =SUM(AF13*$Z$4) -> 2192 | AH13: =SUM(AF13) -> 219.2 | AI13: =SUM(AH13*$Z$4) -> 2192 | AJ13: =SUM(AH13) -> 219.2 | AK13: =SUM(AJ13*$Z$4) -> 2192 | AL13: =SUM(AJ13) -> 219.2 | AM13: =SUM(AL13*$Z$4) -> 2192 | AN13: =SUM(AO13/19600) -> 0.78285714 | AO13: =SUM(AA13+AC13+AE13+AG13+AI13+AK13+AM13) -> 15344 | AQ13: =SUM(AR13/92970) -> 0.70804876 | AR13: =SUM(AO13+Y13) -> 65827.294 | AS13: =SUM(AR13-AR12-AT13) -> 0 | AV13: =IF(AT13>0,AU13,AV12) -> 0.1 | AW13: =-SUM('B5'!AI12) -> 0 | AX13: =-SUM(AW13-AS13) -> 0 | AY13: =SUM(AX13+AW13) -> 0 | AZ13: =ELEC!A10 -> 0 | BA13: ='General information '!D13 -> 0 | BB13: =SUM('General information '!E13) -> 0 | BC13: =IF(AR12>=AR13,0,1) -> 0 | BD13: 19222 | BE13: =(305/1185)*ELEC!Q11 -> 0 | BG13: =#REF!-BE13 -> #REF!
A14: =ELEC!C11 -> 43899 | B14: ='B5'!B13 -> 213.3 | C14: =B14*$B$4 -> 4589.3903 | D14: =SUM(B14) -> 213.3 | E14: =D14*$B$4 -> 4589.3903 | F14: =SUM(D14) -> 213.3 | G14: =F14*$B$4 -> 4589.3903 | H14: =SUM(F14) -> 213.3 | I14: =H14*$B$4 -> 4589.3903 | J14: =SUM(H14) -> 213.3 | K14: =J14*$B$4 -> 4589.3903 | L14: =SUM(J14) -> 213.3 | M14: =L14*$B$4 -> 4589.3903 | N14: =SUM(L14) -> 213.3 | O14: =N14*$B$4 -> 4589.3903 | P14: =SUM(N14) -> 213.3 | Q14: =P14*$B$4 -> 4589.3903 | R14: =SUM(P14) -> 213.3 | S14: =R14*$B$4 -> 4589.3903 | T14: =SUM(R14) -> 213.3 | U14: =T14*$B$4 -> 4589.3903 | V14: =SUM(T14) -> 213.3 | W14: =V14*$B$4 -> 4589.3903 | X14: =SUM(Y14/73370) -> 0.68806452 | Y14: =SUM(C14+E14+G14+I14+K14+M14+O14+Q14+S14+U14+W14) -> 50483.294 | Z14: ='B5'!C13 -> 219.2 | AA14: =SUM(Z14*$Z$4) -> 2192 | AB14: =SUM(Z14) -> 219.2 | AC14: =SUM(AB14*$Z$4) -> 2192 | AD14: =SUM(AB14) -> 219.2 | AE14: =SUM(AD14*$Z$4) -> 2192 | AF14: =SUM(AD14) -> 219.2 | AG14: =SUM(AF14*$Z$4) -> 2192 | AH14: =SUM(AF14) -> 219.2 | AI14: =SUM(AH14*$Z$4) -> 2192 | AJ14: =SUM(AH14) -> 219.2 | AK14: =SUM(AJ14*$Z$4) -> 2192 | AL14: =SUM(AJ14) -> 219.2 | AM14: =SUM(AL14*$Z$4) -> 2192 | AN14: =SUM(AO14/19600) -> 0.78285714 | AO14: =SUM(AA14+AC14+AE14+AG14+AI14+AK14+AM14) -> 15344 | AQ14: =SUM(AR14/92970) -> 0.70804876 | AR14: =SUM(AO14+Y14) -> 65827.294 | AS14: =SUM(AR14-AR13-AT14) -> 0 | AV14: =IF(AT14>0,AU14,AV13) -> 0.1 | AW14: =-SUM('B5'!AI13) -> 0 | AX14: =-SUM(AW14-AS14) -> 0 | AY14: =SUM(AX14+AW14) -> 0 | AZ14: =ELEC!A11 -> 0 | BA14: ='General information '!D14 -> 0 | BB14: =SUM('General information '!E14) -> 0 | BC14: =IF(AR13>=AR14,0,1) -> 0 | BD14: 19222 | BE14: =(305/1185)*ELEC!Q12 -> 0 | BG14: =#REF!-BE14 -> #REF!
A15: =ELEC!C12 -> 43900 | B15: ='B5'!B14 -> 213.3 | C15: =B15*$B$4 -> 4589.3903 | D15: =SUM(B15) -> 213.3 | E15: =D15*$B$4 -> 4589.3903 | F15: =SUM(D15) -> 213.3 | G15: =F15*$B$4 -> 4589.3903 | H15: =SUM(F15) -> 213.3 | I15: =H15*$B$4 -> 4589.3903 | J15: =SUM(H15) -> 213.3 | K15: =J15*$B$4 -> 4589.3903 | L15: =SUM(J15) -> 213.3 | M15: =L15*$B$4 -> 4589.3903 | N15: =SUM(L15) -> 213.3 | O15: =N15*$B$4 -> 4589.3903 | P15: =SUM(N15) -> 213.3 | Q15: =P15*$B$4 -> 4589.3903 | R15: =SUM(P15) -> 213.3 | S15: =R15*$B$4 -> 4589.3903 | T15: =SUM(R15) -> 213.3 | U15: =T15*$B$4 -> 4589.3903 | V15: =SUM(T15) -> 213.3 | W15: =V15*$B$4 -> 4589.3903 | X15: =SUM(Y15/73370) -> 0.68806452 | Y15: =SUM(C15+E15+G15+I15+K15+M15+O15+Q15+S15+U15+W15) -> 50483.294 | Z15: ='B5'!C14 -> 219.2 | AA15: =SUM(Z15*$Z$4) -> 2192 | AB15: =SUM(Z15) -> 219.2 | AC15: =SUM(AB15*$Z$4) -> 2192 | AD15: =SUM(AB15) -> 219.2 | AE15: =SUM(AD15*$Z$4) -> 2192 | AF15: =SUM(AD15) -> 219.2 | AG15: =SUM(AF15*$Z$4) -> 2192 | AH15: =SUM(AF15) -> 219.2 | AI15: =SUM(AH15*$Z$4) -> 2192 | AJ15: =SUM(AH15) -> 219.2 | AK15: =SUM(AJ15*$Z$4) -> 2192 | AL15: =SUM(AJ15) -> 219.2 | AM15: =SUM(AL15*$Z$4) -> 2192 | AN15: =SUM(AO15/19600) -> 0.78285714 | AO15: =SUM(AA15+AC15+AE15+AG15+AI15+AK15+AM15) -> 15344 | AQ15: =SUM(AR15/92970) -> 0.70804876 | AR15: =SUM(AO15+Y15) -> 65827.294 | AS15: =SUM(AR15-AR14-AT15) -> 0 | AV15: =IF(AT15>0,AU15,AV14) -> 0.1 | AW15: =-SUM('B5'!AI14) -> 0 | AX15: =-SUM(AW15-AS15) -> 0 | AY15: =SUM(AX15+AW15) -> 0 | AZ15: =ELEC!A12 -> 0 | BA15: ='General information '!D15 -> 0 | BB15: =SUM('General information '!E15) -> 0 | BC15: =IF(AR14>=AR15,0,1) -> 0 | BD15: 19222 | BE15: =(305/1185)*ELEC!Q13 -> 0 | BG15: =#REF!-BE15 -> #REF!
A16: =ELEC!C13 -> 43901 | B16: ='B5'!B15 -> 213.3 | C16: =B16*$B$4 -> 4589.3903 | D16: =SUM(B16) -> 213.3 | E16: =D16*$B$4 -> 4589.3903 | F16: =SUM(D16) -> 213.3 | G16: =F16*$B$4 -> 4589.3903 | H16: =SUM(F16) -> 213.3 | I16: =H16*$B$4 -> 4589.3903 | J16: =SUM(H16) -> 213.3 | K16: =J16*$B$4 -> 4589.3903 | L16: =SUM(J16) -> 213.3 | M16: =L16*$B$4 -> 4589.3903 | N16: =SUM(L16) -> 213.3 | O16: =N16*$B$4 -> 4589.3903 | P16: =SUM(N16) -> 213.3 | Q16: =P16*$B$4 -> 4589.3903 | R16: =SUM(P16) -> 213.3 | S16: =R16*$B$4 -> 4589.3903 | T16: =SUM(R16) -> 213.3 | U16: =T16*$B$4 -> 4589.3903 | V16: =SUM(T16) -> 213.3 | W16: =V16*$B$4 -> 4589.3903 | X16: =SUM(Y16/73370) -> 0.68806452 | Y16: =SUM(C16+E16+G16+I16+K16+M16+O16+Q16+S16+U16+W16) -> 50483.294 | Z16: ='B5'!C15 -> 219.2 | AA16: =SUM(Z16*$Z$4) -> 2192 | AB16: =SUM(Z16) -> 219.2 | AC16: =SUM(AB16*$Z$4) -> 2192 | AD16: =SUM(AB16) -> 219.2 | AE16: =SUM(AD16*$Z$4) -> 2192 | AF16: =SUM(AD16) -> 219.2 | AG16: =SUM(AF16*$Z$4) -> 2192 | AH16: =SUM(AF16) -> 219.2 | AI16: =SUM(AH16*$Z$4) -> 2192 | AJ16: =SUM(AH16) -> 219.2 | AK16: =SUM(AJ16*$Z$4) -> 2192 | AL16: =SUM(AJ16) -> 219.2 | AM16: =SUM(AL16*$Z$4) -> 2192 | AN16: =SUM(AO16/19600) -> 0.78285714 | AO16: =SUM(AA16+AC16+AE16+AG16+AI16+AK16+AM16) -> 15344 | AQ16: =SUM(AR16/92970) -> 0.70804876 | AR16: =SUM(AO16+Y16) -> 65827.294 | AS16: =SUM(AR16-AR15-AT16) -> 0 | AV16: =IF(AT16>0,AU16,AV15) -> 0.1 | AW16: =-SUM('B5'!AI15) -> 0 | AX16: =-SUM(AW16-AS16) -> 0 | AY16: =SUM(AX16+AW16) -> 0 | AZ16: =ELEC!A13 -> 0 | BA16: ='General information '!D16 -> 0 | BB16: =SUM('General information '!E16) -> 0 | BC16: =IF(AR15>=AR16,0,1) -> 0 | BD16: 19222 | BE16: =(305/1185)*ELEC!Q14 -> 0 | BG16: =#REF!-BE16 -> #REF!
A17: =ELEC!C14 -> 43902 | B17: ='B5'!B16 -> 213.3 | C17: =B17*$B$4 -> 4589.3903 | D17: =SUM(B17) -> 213.3 | E17: =D17*$B$4 -> 4589.3903 | F17: =SUM(D17) -> 213.3 | G17: =F17*$B$4 -> 4589.3903 | H17: =SUM(F17) -> 213.3 | I17: =H17*$B$4 -> 4589.3903 | J17: =SUM(H17) -> 213.3 | K17: =J17*$B$4 -> 4589.3903 | L17: =SUM(J17) -> 213.3 | M17: =L17*$B$4 -> 4589.3903 | N17: =SUM(L17) -> 213.3 | O17: =N17*$B$4 -> 4589.3903 | P17: =SUM(N17) -> 213.3 | Q17: =P17*$B$4 -> 4589.3903 | R17: =SUM(P17) -> 213.3 | S17: =R17*$B$4 -> 4589.3903 | T17: =SUM(R17) -> 213.3 | U17: =T17*$B$4 -> 4589.3903 | V17: =SUM(T17) -> 213.3 | W17: =V17*$B$4 -> 4589.3903 | X17: =SUM(Y17/73370) -> 0.68806452 | Y17: =SUM(C17+E17+G17+I17+K17+M17+O17+Q17+S17+U17+W17) -> 50483.294 | Z17: ='B5'!C16 -> 219.2 | AA17: =SUM(Z17*$Z$4) -> 2192 | AB17: =SUM(Z17) -> 219.2 | AC17: =SUM(AB17*$Z$4) -> 2192 | AD17: =SUM(AB17) -> 219.2 | AE17: =SUM(AD17*$Z$4) -> 2192 | AF17: =SUM(AD17) -> 219.2 | AG17: =SUM(AF17*$Z$4) -> 2192 | AH17: =SUM(AF17) -> 219.2 | AI17: =SUM(AH17*$Z$4) -> 2192 | AJ17: =SUM(AH17) -> 219.2 | AK17: =SUM(AJ17*$Z$4) -> 2192 | AL17: =SUM(AJ17) -> 219.2 | AM17: =SUM(AL17*$Z$4) -> 2192 | AN17: =SUM(AO17/19600) -> 0.78285714 | AO17: =SUM(AA17+AC17+AE17+AG17+AI17+AK17+AM17) -> 15344 | AQ17: =SUM(AR17/92970) -> 0.70804876 | AR17: =SUM(AO17+Y17) -> 65827.294 | AS17: =SUM(AR17-AR16-AT17) -> 0 | AV17: =IF(AT17>0,AU17,AV16) -> 0.1 | AW17: =-SUM('B5'!AI16) -> 0 | AX17: =-SUM(AW17-AS17) -> 0 | AY17: =SUM(AX17+AW17) -> 0 | AZ17: =ELEC!A14 -> 0 | BA17: ='General information '!D17 -> 0 | BB17: =SUM('General information '!E17) -> 0 | BC17: =IF(AR16>=AR17,0,1) -> 0 | BD17: 19222 | BE17: =(305/1185)*ELEC!Q15 -> 0 | BG17: =#REF!-BE17 -> #REF!
A18: =ELEC!C15 -> 43903 | B18: ='B5'!B17 -> 213.3 | C18: =B18*$B$4 -> 4589.3903 | D18: =SUM(B18) -> 213.3 | E18: =D18*$B$4 -> 4589.3903 | F18: =SUM(D18) -> 213.3 | G18: =F18*$B$4 -> 4589.3903 | H18: =SUM(F18) -> 213.3 | I18: =H18*$B$4 -> 4589.3903 | J18: =SUM(H18) -> 213.3 | K18: =J18*$B$4 -> 4589.3903 | L18: =SUM(J18) -> 213.3 | M18: =L18*$B$4 -> 4589.3903 | N18: =SUM(L18) -> 213.3 | O18: =N18*$B$4 -> 4589.3903 | P18: =SUM(N18) -> 213.3 | Q18: =P18*$B$4 -> 4589.3903 | R18: =SUM(P18) -> 213.3 | S18: =R18*$B$4 -> 4589.3903 | T18: =SUM(R18) -> 213.3 | U18: =T18*$B$4 -> 4589.3903 | V18: =SUM(T18) -> 213.3 | W18: =V18*$B$4 -> 4589.3903 | X18: =SUM(Y18/73370) -> 0.68806452 | Y18: =SUM(C18+E18+G18+I18+K18+M18+O18+Q18+S18+U18+W18) -> 50483.294 | Z18: ='B5'!C17 -> 219.2 | AA18: =SUM(Z18*$Z$4) -> 2192 | AB18: =SUM(Z18) -> 219.2 | AC18: =SUM(AB18*$Z$4) -> 2192 | AD18: =SUM(AB18) -> 219.2 | AE18: =SUM(AD18*$Z$4) -> 2192 | AF18: =SUM(AD18) -> 219.2 | AG18: =SUM(AF18*$Z$4) -> 2192 | AH18: =SUM(AF18) -> 219.2 | AI18: =SUM(AH18*$Z$4) -> 2192 | AJ18: =SUM(AH18) -> 219.2 | AK18: =SUM(AJ18*$Z$4) -> 2192 | AL18: =SUM(AJ18) -> 219.2 | AM18: =SUM(AL18*$Z$4) -> 2192 | AN18: =SUM(AO18/19600) -> 0.78285714 | AO18: =SUM(AA18+AC18+AE18+AG18+AI18+AK18+AM18) -> 15344 | AQ18: =SUM(AR18/92970) -> 0.70804876 | AR18: =SUM(AO18+Y18) -> 65827.294 | AS18: =SUM(AR18-AR17-AT18) -> 0 | AV18: =IF(AT18>0,AU18,AV17) -> 0.1 | AW18: =-SUM('B5'!AI17) -> 0 | AX18: =-SUM(AW18-AS18) -> 0 | AY18: =SUM(AX18+AW18) -> 0 | AZ18: =ELEC!A15 -> 0 | BA18: ='General information '!D18 -> 0 | BB18: =SUM('General information '!E18) -> 0 | BC18: =IF(AR17>=AR18,0,1) -> 0 | BD18: 19222 | BE18: =(305/1185)*ELEC!Q16 -> 0 | BG18: =#REF!-BE18 -> #REF!
A19: =ELEC!C16 -> 43904 | B19: ='B5'!B18 -> 213.3 | C19: =B19*$B$4 -> 4589.3903 | D19: =SUM(B19) -> 213.3 | E19: =D19*$B$4 -> 4589.3903 | F19: =SUM(D19) -> 213.3 | G19: =F19*$B$4 -> 4589.3903 | H19: =SUM(F19) -> 213.3 | I19: =H19*$B$4 -> 4589.3903 | J19: =SUM(H19) -> 213.3 | K19: =J19*$B$4 -> 4589.3903 | L19: =SUM(J19) -> 213.3 | M19: =L19*$B$4 -> 4589.3903 | N19: =SUM(L19) -> 213.3 | O19: =N19*$B$4 -> 4589.3903 | P19: =SUM(N19) -> 213.3 | Q19: =P19*$B$4 -> 4589.3903 | R19: =SUM(P19) -> 213.3 | S19: =R19*$B$4 -> 4589.3903 | T19: =SUM(R19) -> 213.3 | U19: =T19*$B$4 -> 4589.3903 | V19: =SUM(T19) -> 213.3 | W19: =V19*$B$4 -> 4589.3903 | X19: =SUM(Y19/73370) -> 0.68806452 | Y19: =SUM(C19+E19+G19+I19+K19+M19+O19+Q19+S19+U19+W19) -> 50483.294 | Z19: ='B5'!C18 -> 219.2 | AA19: =SUM(Z19*$Z$4) -> 2192 | AB19: =SUM(Z19) -> 219.2 | AC19: =SUM(AB19*$Z$4) -> 2192 | AD19: =SUM(AB19) -> 219.2 | AE19: =SUM(AD19*$Z$4) -> 2192 | AF19: =SUM(AD19) -> 219.2 | AG19: =SUM(AF19*$Z$4) -> 2192 | AH19: =SUM(AF19) -> 219.2 | AI19: =SUM(AH19*$Z$4) -> 2192 | AJ19: =SUM(AH19) -> 219.2 | AK19: =SUM(AJ19*$Z$4) -> 2192 | AL19: =SUM(AJ19) -> 219.2 | AM19: =SUM(AL19*$Z$4) -> 2192 | AN19: =SUM(AO19/19600) -> 0.78285714 | AO19: =SUM(AA19+AC19+AE19+AG19+AI19+AK19+AM19) -> 15344 | AQ19: =SUM(AR19/92970) -> 0.70804876 | AR19: =SUM(AO19+Y19) -> 65827.294 | AS19: =SUM(AR19-AR18-AT19) -> 0 | AV19: =IF(AT19>0,AU19,AV18) -> 0.1 | AW19: =-SUM('B5'!AI18) -> 0 | AX19: =-SUM(AW19-AS19) -> 0 | AY19: =SUM(AX19+AW19) -> 0 | AZ19: =ELEC!A16 -> 0 | BA19: ='General information '!D19 -> 0 | BB19: =SUM('General information '!E19) -> 0 | BC19: =IF(AR18>=AR19,0,1) -> 0 | BD19: 19222 | BE19: =(305/1185)*ELEC!Q17 -> 0 | BG19: =#REF!-BE19 -> #REF!
A20: =ELEC!C17 -> 43905 | B20: ='B5'!B19 -> 213.3 | C20: =B20*$B$4 -> 4589.3903 | D20: =SUM(B20) -> 213.3 | E20: =D20*$B$4 -> 4589.3903 | F20: =SUM(D20) -> 213.3 | G20: =F20*$B$4 -> 4589.3903 | H20: =SUM(F20) -> 213.3 | I20: =H20*$B$4 -> 4589.3903 | J20: =SUM(H20) -> 213.3 | K20: =J20*$B$4 -> 4589.3903 | L20: =SUM(J20) -> 213.3 | M20: =L20*$B$4 -> 4589.3903 | N20: =SUM(L20) -> 213.3 | O20: =N20*$B$4 -> 4589.3903 | P20: =SUM(N20) -> 213.3 | Q20: =P20*$B$4 -> 4589.3903 | R20: =SUM(P20) -> 213.3 | S20: =R20*$B$4 -> 4589.3903 | T20: =SUM(R20) -> 213.3 | U20: =T20*$B$4 -> 4589.3903 | V20: =SUM(T20) -> 213.3 | W20: =V20*$B$4 -> 4589.3903 | X20: =SUM(Y20/73370) -> 0.68806452 | Y20: =SUM(C20+E20+G20+I20+K20+M20+O20+Q20+S20+U20+W20) -> 50483.294 | Z20: ='B5'!C19 -> 219.2 | AA20: =SUM(Z20*$Z$4) -> 2192 | AB20: =SUM(Z20) -> 219.2 | AC20: =SUM(AB20*$Z$4) -> 2192 | AD20: =SUM(AB20) -> 219.2 | AE20: =SUM(AD20*$Z$4) -> 2192 | AF20: =SUM(AD20) -> 219.2 | AG20: =SUM(AF20*$Z$4) -> 2192 | AH20: =SUM(AF20) -> 219.2 | AI20: =SUM(AH20*$Z$4) -> 2192 | AJ20: =SUM(AH20) -> 219.2 | AK20: =SUM(AJ20*$Z$4) -> 2192 | AL20: =SUM(AJ20) -> 219.2 | AM20: =SUM(AL20*$Z$4) -> 2192 | AN20: =SUM(AO20/19600) -> 0.78285714 | AO20: =SUM(AA20+AC20+AE20+AG20+AI20+AK20+AM20) -> 15344 | AQ20: =SUM(AR20/92970) -> 0.70804876 | AR20: =SUM(AO20+Y20) -> 65827.294 | AS20: =SUM(AR20-AR19-AT20) -> 0 | AV20: =IF(AT20>0,AU20,AV19) -> 0.1 | AW20: =-SUM('B5'!AI19) -> 0 | AX20: =-SUM(AW20-AS20) -> 0 | AY20: =SUM(AX20+AW20) -> 0 | AZ20: =ELEC!A17 -> 0 | BA20: ='General information '!D20 -> 0 | BB20: =SUM('General information '!E20) -> 0 | BC20: =IF(AR19>=AR20,0,1) -> 0 | BD20: 19222 | BE20: =(305/1185)*ELEC!Q18 -> 0 | BG20: =#REF!-BE20 -> #REF!
A21: =ELEC!C18 -> 43906 | B21: ='B5'!B20 -> 213.3 | C21: =B21*$B$4 -> 4589.3903 | D21: =SUM(B21) -> 213.3 | E21: =D21*$B$4 -> 4589.3903 | F21: =SUM(D21) -> 213.3 | G21: =F21*$B$4 -> 4589.3903 | H21: =SUM(F21) -> 213.3 | I21: =H21*$B$4 -> 4589.3903 | J21: =SUM(H21) -> 213.3 | K21: =J21*$B$4 -> 4589.3903 | L21: =SUM(J21) -> 213.3 | M21: =L21*$B$4 -> 4589.3903 | N21: =SUM(L21) -> 213.3 | O21: =N21*$B$4 -> 4589.3903 | P21: =SUM(N21) -> 213.3 | Q21: =P21*$B$4 -> 4589.3903 | R21: =SUM(P21) -> 213.3 | S21: =R21*$B$4 -> 4589.3903 | T21: =SUM(R21) -> 213.3 | U21: =T21*$B$4 -> 4589.3903 | V21: =SUM(T21) -> 213.3 | W21: =V21*$B$4 -> 4589.3903 | X21: =SUM(Y21/73370) -> 0.68806452 | Y21: =SUM(C21+E21+G21+I21+K21+M21+O21+Q21+S21+U21+W21) -> 50483.294 | Z21: ='B5'!C20 -> 219.2 | AA21: =SUM(Z21*$Z$4) -> 2192 | AB21: =SUM(Z21) -> 219.2 | AC21: =SUM(AB21*$Z$4) -> 2192 | AD21: =SUM(AB21) -> 219.2 | AE21: =SUM(AD21*$Z$4) -> 2192 | AF21: =SUM(AD21) -> 219.2 | AG21: =SUM(AF21*$Z$4) -> 2192 | AH21: =SUM(AF21) -> 219.2 | AI21: =SUM(AH21*$Z$4) -> 2192 | AJ21: =SUM(AH21) -> 219.2 | AK21: =SUM(AJ21*$Z$4) -> 2192 | AL21: =SUM(AJ21) -> 219.2 | AM21: =SUM(AL21*$Z$4) -> 2192 | AN21: =SUM(AO21/19600) -> 0.78285714 | AO21: =SUM(AA21+AC21+AE21+AG21+AI21+AK21+AM21) -> 15344 | AQ21: =SUM(AR21/92970) -> 0.70804876 | AR21: =SUM(AO21+Y21) -> 65827.294 | AS21: =SUM(AR21-AR20-AT21) -> 0 | AV21: =IF(AT21>0,AU21,AV20) -> 0.1 | AW21: =-SUM('B5'!AI20) -> 0 | AX21: =-SUM(AW21-AS21) -> 0 | AY21: =SUM(AX21+AW21) -> 0 | AZ21: =ELEC!A18 -> 0 | BA21: ='General information '!D21 -> 0 | BB21: =SUM('General information '!E21) -> 0 | BC21: =IF(AR20>=AR21,0,1) -> 0 | BD21: 19222 | BE21: =(305/1185)*ELEC!Q19 -> 0 | BG21: =#REF!-BE21 -> #REF!
A22: =ELEC!C19 -> 43907 | B22: ='B5'!B21 -> 213.3 | C22: =B22*$B$4 -> 4589.3903 | D22: =SUM(B22) -> 213.3 | E22: =D22*$B$4 -> 4589.3903 | F22: =SUM(D22) -> 213.3 | G22: =F22*$B$4 -> 4589.3903 | H22: =SUM(F22) -> 213.3 | I22: =H22*$B$4 -> 4589.3903 | J22: =SUM(H22) -> 213.3 | K22: =J22*$B$4 -> 4589.3903 | L22: =SUM(J22) -> 213.3 | M22: =L22*$B$4 -> 4589.3903 | N22: =SUM(L22) -> 213.3 | O22: =N22*$B$4 -> 4589.3903 | P22: =SUM(N22) -> 213.3 | Q22: =P22*$B$4 -> 4589.3903 | R22: =SUM(P22) -> 213.3 | S22: =R22*$B$4 -> 4589.3903 | T22: =SUM(R22) -> 213.3 | U22: =T22*$B$4 -> 4589.3903 | V22: =SUM(T22) -> 213.3 | W22: =V22*$B$4 -> 4589.3903 | X22: =SUM(Y22/73370) -> 0.68806452 | Y22: =SUM(C22+E22+G22+I22+K22+M22+O22+Q22+S22+U22+W22) -> 50483.294 | Z22: ='B5'!C21 -> 219.2 | AA22: =SUM(Z22*$Z$4) -> 2192 | AB22: =SUM(Z22) -> 219.2 | AC22: =SUM(AB22*$Z$4) -> 2192 | AD22: =SUM(AB22) -> 219.2 | AE22: =SUM(AD22*$Z$4) -> 2192 | AF22: =SUM(AD22) -> 219.2 | AG22: =SUM(AF22*$Z$4) -> 2192 | AH22: =SUM(AF22) -> 219.2 | AI22: =SUM(AH22*$Z$4) -> 2192 | AJ22: =SUM(AH22) -> 219.2 | AK22: =SUM(AJ22*$Z$4) -> 2192 | AL22: =SUM(AJ22) -> 219.2 | AM22: =SUM(AL22*$Z$4) -> 2192 | AN22: =SUM(AO22/19600) -> 0.78285714 | AO22: =SUM(AA22+AC22+AE22+AG22+AI22+AK22+AM22) -> 15344 | AQ22: =SUM(AR22/92970) -> 0.70804876 | AR22: =SUM(AO22+Y22) -> 65827.294 | AS22: =SUM(AR22-AR21-AT22) -> 0 | AV22: =IF(AT22>0,AU22,AV21) -> 0.1 | AW22: =-SUM('B5'!AI21) -> 0 | AX22: =-SUM(AW22-AS22) -> 0 | AY22: =SUM(AX22+AW22) -> 0 | AZ22: =ELEC!A19 -> 0 | BA22: ='General information '!D22 -> 0 | BB22: =SUM('General information '!E22) -> 0 | BC22: =IF(AR21>=AR22,0,1) -> 0 | BD22: 19222 | BE22: =(305/1185)*ELEC!Q20 -> 0 | BG22: =#REF!-BE22 -> #REF!
A23: =ELEC!C20 -> 43908 | B23: ='B5'!B22 -> 213.3 | C23: =B23*$B$4 -> 4589.3903 | D23: =SUM(B23) -> 213.3 | E23: =D23*$B$4 -> 4589.3903 | F23: =SUM(D23) -> 213.3 | G23: =F23*$B$4 -> 4589.3903 | H23: =SUM(F23) -> 213.3 | I23: =H23*$B$4 -> 4589.3903 | J23: =SUM(H23) -> 213.3 | K23: =J23*$B$4 -> 4589.3903 | L23: =SUM(J23) -> 213.3 | M23: =L23*$B$4 -> 4589.3903 | N23: =SUM(L23) -> 213.3 | O23: =N23*$B$4 -> 4589.3903 | P23: =SUM(N23) -> 213.3 | Q23: =P23*$B$4 -> 4589.3903 | R23: =SUM(P23) -> 213.3 | S23: =R23*$B$4 -> 4589.3903 | T23: =SUM(R23) -> 213.3 | U23: =T23*$B$4 -> 4589.3903 | V23: =SUM(T23) -> 213.3 | W23: =V23*$B$4 -> 4589.3903 | X23: =SUM(Y23/73370) -> 0.68806452 | Y23: =SUM(C23+E23+G23+I23+K23+M23+O23+Q23+S23+U23+W23) -> 50483.294 | Z23: ='B5'!C22 -> 219.2 | AA23: =SUM(Z23*$Z$4) -> 2192 | AB23: =SUM(Z23) -> 219.2 | AC23: =SUM(AB23*$Z$4) -> 2192 | AD23: =SUM(AB23) -> 219.2 | AE23: =SUM(AD23*$Z$4) -> 2192 | AF23: =SUM(AD23) -> 219.2 | AG23: =SUM(AF23*$Z$4) -> 2192 | AH23: =SUM(AF23) -> 219.2 | AI23: =SUM(AH23*$Z$4) -> 2192 | AJ23: =SUM(AH23) -> 219.2 | AK23: =SUM(AJ23*$Z$4) -> 2192 | AL23: =SUM(AJ23) -> 219.2 | AM23: =SUM(AL23*$Z$4) -> 2192 | AN23: =SUM(AO23/19600) -> 0.78285714 | AO23: =SUM(AA23+AC23+AE23+AG23+AI23+AK23+AM23) -> 15344 | AQ23: =SUM(AR23/92970) -> 0.70804876 | AR23: =SUM(AO23+Y23) -> 65827.294 | AS23: =SUM(AR23-AR22-AT23) -> 0 | AV23: =IF(AT23>0,AU23,AV22) -> 0.1 | AW23: =-SUM('B5'!AI22) -> 0 | AX23: =-SUM(AW23-AS23) -> 0 | AY23: =SUM(AX23+AW23) -> 0 | AZ23: =ELEC!A20 -> 0 | BA23: ='General information '!D23 -> 0 | BB23: =SUM('General information '!E23) -> 0 | BC23: =IF(AR22>=AR23,0,1) -> 0 | BD23: 19222 | BE23: =(305/1185)*ELEC!Q21 -> 0 | BG23: =#REF!-BE23 -> #REF!
A24: =ELEC!C21 -> 43909 | B24: ='B5'!B23 -> 213.3 | C24: =B24*$B$4 -> 4589.3903 | D24: =SUM(B24) -> 213.3 | E24: =D24*$B$4 -> 4589.3903 | F24: =SUM(D24) -> 213.3 | G24: =F24*$B$4 -> 4589.3903 | H24: =SUM(F24) -> 213.3 | I24: =H24*$B$4 -> 4589.3903 | J24: =SUM(H24) -> 213.3 | K24: =J24*$B$4 -> 4589.3903 | L24: =SUM(J24) -> 213.3 | M24: =L24*$B$4 -> 4589.3903 | N24: =SUM(L24) -> 213.3 | O24: =N24*$B$4 -> 4589.3903 | P24: =SUM(N24) -> 213.3 | Q24: =P24*$B$4 -> 4589.3903 | R24: =SUM(P24) -> 213.3 | S24: =R24*$B$4 -> 4589.3903 | T24: =SUM(R24) -> 213.3 | U24: =T24*$B$4 -> 4589.3903 | V24: =SUM(T24) -> 213.3 | W24: =V24*$B$4 -> 4589.3903 | X24: =SUM(Y24/73370) -> 0.68806452 | Y24: =SUM(C24+E24+G24+I24+K24+M24+O24+Q24+S24+U24+W24) -> 50483.294 | Z24: ='B5'!C23 -> 219.2 | AA24: =SUM(Z24*$Z$4) -> 2192 | AB24: =SUM(Z24) -> 219.2 | AC24: =SUM(AB24*$Z$4) -> 2192 | AD24: =SUM(AB24) -> 219.2 | AE24: =SUM(AD24*$Z$4) -> 2192 | AF24: =SUM(AD24) -> 219.2 | AG24: =SUM(AF24*$Z$4) -> 2192 | AH24: =SUM(AF24) -> 219.2 | AI24: =SUM(AH24*$Z$4) -> 2192 | AJ24: =SUM(AH24) -> 219.2 | AK24: =SUM(AJ24*$Z$4) -> 2192 | AL24: =SUM(AJ24) -> 219.2 | AM24: =SUM(AL24*$Z$4) -> 2192 | AN24: =SUM(AO24/19600) -> 0.78285714 | AO24: =SUM(AA24+AC24+AE24+AG24+AI24+AK24+AM24) -> 15344 | AQ24: =SUM(AR24/92970) -> 0.70804876 | AR24: =SUM(AO24+Y24) -> 65827.294 | AS24: =SUM(AR24-AR23-AT24) -> 0 | AV24: =IF(AT24>0,AU24,AV23) -> 0.1 | AW24: =-SUM('B5'!AI23) -> 0 | AX24: =-SUM(AW24-AS24) -> 0 | AY24: =SUM(AX24+AW24) -> 0 | AZ24: =ELEC!A21 -> 0 | BA24: ='General information '!D24 -> 0 | BB24: =SUM('General information '!E24) -> 0 | BC24: =IF(AR23>=AR24,0,1) -> 0 | BD24: 19222 | BE24: =(305/1185)*ELEC!Q22 -> 0 | BG24: =#REF!-BE24 -> #REF!
... A33: =ELEC!C30 -> 43918 | B33: ='B5'!B32 -> 213.3 | C33: =B33*$B$4 -> 4589.3903 | D33: =SUM(B33) -> 213.3 | E33: =D33*$B$4 -> 4589.3903 | F33: =SUM(D33) -> 213.3 | G33: =F33*$B$4 -> 4589.3903 | H33: =SUM(F33) -> 213.3 | I33: =H33*$B$4 -> 4589.3903 | J33: =SUM(H33) -> 213.3 | K33: =J33*$B$4 -> 4589.3903 | L33: =SUM(J33) -> 213.3 | M33: =L33*$B$4 -> 4589.3903 | N33: =SUM(L33) -> 213.3 | O33: =N33*$B$4 -> 4589.3903 | P33: =SUM(N33) -> 213.3 | Q33: =P33*$B$4 -> 4589.3903 | R33: =SUM(P33) -> 213.3 | S33: =R33*$B$4 -> 4589.3903 | T33: =SUM(R33) -> 213.3 | U33: =T33*$B$4 -> 4589.3903 | V33: =SUM(T33) -> 213.3 | W33: =V33*$B$4 -> 4589.3903 | X33: =SUM(Y33/73370) -> 0.68806452 | Y33: =SUM(C33+E33+G33+I33+K33+M33+O33+Q33+S33+U33+W33) -> 50483.294 | Z33: ='B5'!C32 -> 219.2 | AA33: =SUM(Z33*$Z$4) -> 2192 | AB33: =SUM(Z33) -> 219.2 | AC33: =SUM(AB33*$Z$4) -> 2192 | AD33: =SUM(AB33) -> 219.2 | AE33: =SUM(AD33*$Z$4) -> 2192 | AF33: =SUM(AD33) -> 219.2 | AG33: =SUM(AF33*$Z$4) -> 2192 | AH33: =SUM(AF33) -> 219.2 | AI33: =SUM(AH33*$Z$4) -> 2192 | AJ33: =SUM(AH33) -> 219.2 | AK33: =SUM(AJ33*$Z$4) -> 2192 | AL33: =SUM(AJ33) -> 219.2 | AM33: =SUM(AL33*$Z$4) -> 2192 | AN33: =SUM(AO33/19600) -> 0.78285714 | AO33: =SUM(AA33+AC33+AE33+AG33+AI33+AK33+AM33) -> 15344 | AQ33: =SUM(AR33/92970) -> 0.70804876 | AR33: =SUM(AO33+Y33) -> 65827.294 | AS33: =SUM(AR33-AR32-AT33) -> 0 | AV33: =IF(AT33>0,AU33,AV32) -> 0.1 | AW33: =-SUM('B5'!AI32) -> 0 | AX33: =-SUM(AW33-AS33) -> 0 | AY33: =SUM(AX33+AW33) -> 0 | AZ33: =ELEC!A30 -> 0 | BA33: ='General information '!D33 -> 0 | BB33: =SUM('General information '!E33) -> 0 | BC33: =IF(AR32>=AR33,0,1) -> 0 | BD33: 19222 | BE33: =(305/1185)*ELEC!Q31 -> 0 | BG33: =#REF!-BE33 -> #REF!
A34: =ELEC!C31 -> 43919 | B34: ='B5'!B33 -> 213.3 | C34: =B34*$B$4 -> 4589.3903 | D34: =SUM(B34) -> 213.3 | E34: =D34*$B$4 -> 4589.3903 | F34: =SUM(D34) -> 213.3 | G34: =F34*$B$4 -> 4589.3903 | H34: =SUM(F34) -> 213.3 | I34: =H34*$B$4 -> 4589.3903 | J34: =SUM(H34) -> 213.3 | K34: =J34*$B$4 -> 4589.3903 | L34: =SUM(J34) -> 213.3 | M34: =L34*$B$4 -> 4589.3903 | N34: =SUM(L34) -> 213.3 | O34: =N34*$B$4 -> 4589.3903 | P34: =SUM(N34) -> 213.3 | Q34: =P34*$B$4 -> 4589.3903 | R34: =SUM(P34) -> 213.3 | S34: =R34*$B$4 -> 4589.3903 | T34: =SUM(R34) -> 213.3 | U34: =T34*$B$4 -> 4589.3903 | V34: =SUM(T34) -> 213.3 | W34: =V34*$B$4 -> 4589.3903 | X34: =SUM(Y34/73370) -> 0.68806452 | Y34: =SUM(C34+E34+G34+I34+K34+M34+O34+Q34+S34+U34+W34) -> 50483.294 | Z34: ='B5'!C33 -> 219.2 | AA34: =SUM(Z34*$Z$4) -> 2192 | AB34: =SUM(Z34) -> 219.2 | AC34: =SUM(AB34*$Z$4) -> 2192 | AD34: =SUM(AB34) -> 219.2 | AE34: =SUM(AD34*$Z$4) -> 2192 | AF34: =SUM(AD34) -> 219.2 | AG34: =SUM(AF34*$Z$4) -> 2192 | AH34: =SUM(AF34) -> 219.2 | AI34: =SUM(AH34*$Z$4) -> 2192 | AJ34: =SUM(AH34) -> 219.2 | AK34: =SUM(AJ34*$Z$4) -> 2192 | AL34: =SUM(AJ34) -> 219.2 | AM34: =SUM(AL34*$Z$4) -> 2192 | AN34: =SUM(AO34/19600) -> 0.78285714 | AO34: =SUM(AA34+AC34+AE34+AG34+AI34+AK34+AM34) -> 15344 | AQ34: =SUM(AR34/92970) -> 0.70804876 | AR34: =SUM(AO34+Y34) -> 65827.294 | AS34: =SUM(AR34-AR33-AT34) -> 0 | AV34: =IF(AT34>0,AU34,AV33) -> 0.1 | AW34: =-SUM('B5'!AI33) -> 0 | AX34: =-SUM(AW34-AS34) -> 0 | AY34: =SUM(AX34+AW34) -> 0 | AZ34: =ELEC!A31 -> 0 | BA34: ='General information '!D34 -> 0 | BB34: =SUM('General information '!E34) -> 0 | BC34: =IF(AR33>=AR34,0,1) -> 0 | BD34: 19222 | BE34: =(305/1185)*ELEC!#REF! -> #REF! | BG34: =#REF!-BE34 -> #REF!
A35: =ELEC!C32 -> 43920 | B35: ='B5'!B34 -> 213.3 | C35: =B35*$B$4 -> 4589.3903 | D35: =SUM(B35) -> 213.3 | E35: =D35*$B$4 -> 4589.3903 | F35: =SUM(D35) -> 213.3 | G35: =F35*$B$4 -> 4589.3903 | H35: =SUM(F35) -> 213.3 | I35: =H35*$B$4 -> 4589.3903 | J35: =SUM(H35) -> 213.3 | K35: =J35*$B$4 -> 4589.3903 | L35: =SUM(J35) -> 213.3 | M35: =L35*$B$4 -> 4589.3903 | N35: =SUM(L35) -> 213.3 | O35: =N35*$B$4 -> 4589.3903 | P35: =SUM(N35) -> 213.3 | Q35: =P35*$B$4 -> 4589.3903 | R35: =SUM(P35) -> 213.3 | S35: =R35*$B$4 -> 4589.3903 | T35: =SUM(R35) -> 213.3 | U35: =T35*$B$4 -> 4589.3903 | V35: =SUM(T35) -> 213.3 | W35: =V35*$B$4 -> 4589.3903 | X35: =SUM(Y35/73370) -> 0.68806452 | Y35: =SUM(C35+E35+G35+I35+K35+M35+O35+Q35+S35+U35+W35) -> 50483.294 | Z35: ='B5'!C34 -> 219.2 | AA35: =SUM(Z35*$Z$4) -> 2192 | AB35: =SUM(Z35) -> 219.2 | AC35: =SUM(AB35*$Z$4) -> 2192 | AD35: =SUM(AB35) -> 219.2 | AE35: =SUM(AD35*$Z$4) -> 2192 | AF35: =SUM(AD35) -> 219.2 | AG35: =SUM(AF35*$Z$4) -> 2192 | AH35: =SUM(AF35) -> 219.2 | AI35: =SUM(AH35*$Z$4) -> 2192 | AJ35: =SUM(AH35) -> 219.2 | AK35: =SUM(AJ35*$Z$4) -> 2192 | AL35: =SUM(AJ35) -> 219.2 | AM35: =SUM(AL35*$Z$4) -> 2192 | AN35: =SUM(AO35/19600) -> 0.78285714 | AO35: =SUM(AA35+AC35+AE35+AG35+AI35+AK35+AM35) -> 15344 | AQ35: =SUM(AR35/92970) -> 0.70804876 | AR35: =SUM(AO35+Y35) -> 65827.294 | AS35: =SUM(AR35-AR34-AT35) -> 0 | AV35: =IF(AT35>0,AU35,AV34) -> 0.1 | AW35: =-SUM('B5'!AI34) -> 0 | AX35: =-SUM(AW35-AS35) -> 0 | AY35: =SUM(AX35+AW35) -> 0 | AZ35: =ELEC!A32 -> 0 | BA35: ='General information '!D35 -> 0 | BB35: =SUM('General information '!E35) -> 0 | BC35: =IF(AR34>=AR35,0,1) -> 0 | BD35: 19222 | BE35: =(305/1185)*ELEC!#REF! -> #REF! | BG35: =#REF!-BE35 -> #REF!
A36: =ELEC!C33 -> 43921 | B36: ='B5'!B35 -> 213.3 | C36: =B36*$B$4 -> 4589.3903 | D36: =SUM(B36) -> 213.3 | E36: =D36*$B$4 -> 4589.3903 | F36: =SUM(D36) -> 213.3 | G36: =F36*$B$4 -> 4589.3903 | H36: =SUM(F36) -> 213.3 | I36: =H36*$B$4 -> 4589.3903 | J36: =SUM(H36) -> 213.3 | K36: =J36*$B$4 -> 4589.3903 | L36: =SUM(J36) -> 213.3 | M36: =L36*$B$4 -> 4589.3903 | N36: =SUM(L36) -> 213.3 | O36: =N36*$B$4 -> 4589.3903 | P36: =SUM(N36) -> 213.3 | Q36: =P36*$B$4 -> 4589.3903 | R36: =SUM(P36) -> 213.3 | S36: =R36*$B$4 -> 4589.3903 | T36: =SUM(R36) -> 213.3 | U36: =T36*$B$4 -> 4589.3903 | V36: =SUM(T36) -> 213.3 | W36: =V36*$B$4 -> 4589.3903 | X36: =SUM(Y36/73370) -> 0.68806452 | Y36: =SUM(C36+E36+G36+I36+K36+M36+O36+Q36+S36+U36+W36) -> 50483.294 | Z36: ='B5'!C35 -> 219.2 | AA36: =SUM(Z36*$Z$4) -> 2192 | AB36: =SUM(Z36) -> 219.2 | AC36: =SUM(AB36*$Z$4) -> 2192 | AD36: =SUM(AB36) -> 219.2 | AE36: =SUM(AD36*$Z$4) -> 2192 | AF36: =SUM(AD36) -> 219.2 | AG36: =SUM(AF36*$Z$4) -> 2192 | AH36: =SUM(AF36) -> 219.2 | AI36: =SUM(AH36*$Z$4) -> 2192 | AJ36: =SUM(AH36) -> 219.2 | AK36: =SUM(AJ36*$Z$4) -> 2192 | AL36: =SUM(AJ36) -> 219.2 | AM36: =SUM(AL36*$Z$4) -> 2192 | AN36: =SUM(AO36/19600) -> 0.78285714 | AO36: =SUM(AA36+AC36+AE36+AG36+AI36+AK36+AM36) -> 15344 | AQ36: =SUM(AR36/92970) -> 0.70804876 | AR36: =SUM(AO36+Y36) -> 65827.294 | AS36: =SUM(AR36-AR35-AT36) -> 0 | AV36: =IF(AT36>0,AU36,AV35) -> 0.1 | AW36: =-SUM('B5'!AI35) -> 0 | AX36: =-SUM(AW36-AS36) -> 0 | AY36: =SUM(AX36+AW36) -> 0 | AZ36: =ELEC!A33 -> 0 | BA36: ='General information '!D36 -> 0 | BB36: =SUM('General information '!E36) -> 0
AR37: NB delivery | AS37: =COUNT(AT6:AT36) -> 1 | AT37: =SUM(AT6:AT36) -> 0.1 | AU37: =SUM(AU6:AU36)/AS37 -> 0.1 | AX37: =SUM(AX6:AX36) -> -3641.5484 | AY37: =SUM(AY6:AY36) -> -6126.6484
AT38: =+AT37*AU37 -> 0.01
AS40: =SUM(AS6:AS36)/'EDl log'!A36 -> -1531.6621

Sheet GEN
B1: GEN1 | C1: RUN HR | D1: Fuel Counter Index | E1: Cons /day | F1: Diesel L/H | H1: next service | I1: ALARM | J1: GEN2 | K1: RUN HR | L1: Fuel Counter Index | M1: Cons /day | N1: Diesel L/H | P1: next service | Q1: ALARM | R1: GEN3 | S1: RUN HR | T1: Fuel Counter Index | U1: Cons /day | V1: Diesel L/H | X1: next service | Y1: ALARM | Z1: RH total | AA1: Gen Con /day | AB1: Total Deisel Cons/day | AC1: H /L | AD1: TOAL KW GEN | AI1: fuel Consuption | AK1: AVG KW/h
A2: =ELEC!C2 -> 43890 | B2: =[1]GEN!B31 -> 8543 | C2: =[1]GEN!C31 -> 6 | D2: =[1]GEN!D31 -> 129830.6 | E2: =[1]GEN!E31 -> 1004.7 | F2: =[1]GEN!F31 -> 167.45 | G2: =[1]GEN!G31 -> 0 | H2: =[1]GEN!H31 -> 8497 | I2: =[1]GEN!I31 -> oil change | ... AK2: =[1]GEN!AK31 -> 210.19691
A3: =ELEC!C3 -> 43891 | B3: 8547.09 | C3: =B3-B2 -> 4.09 | D3: 130317.1 | E3: =SUM(D3-D2) -> 486.5 | F3: =IF(C3>0,E3/C3,0) -> 118.94866 | G3: =[2]GEN!G32 -> 0 | H3: =H2 -> 8497 | I3: =IF(B3-H3<=0,"ok","oil change") -> oil change | J3: 10689.42 | K3: =J3-J2 -> 0.42 | L3: 237069.6 | M3: =SUM(L3-L2) -> 0.1 | N3: =IF(K3>0,M3/K3,0) -> 0.23809524 | O3: =[2]GEN!O32 -> 0 | P3: =P2 -> 10873 | Q3: =IF(J3-P3<=0,"ok","oil change") -> ok | R3: 10992.51 | S3: =R3-R2 -> 0.51 | T3: 201286.1 | U3: =SUM(T3-T2) -> 0 | V3: =IF(S3>0,U3/S3,0) -> 0 | W3: =[2]GEN!W32 -> 0 | X3: =X2 -> 11349 | Y3: =IF(R3-X3<=0,"ok","oil change") -> ok | Z3: =C3+K3+S3 -> 5.02 | AA3: =U3+M3+E3 -> 486.6 | AB3: =V3+N3+F3 -> 119.18675 | AC3: =IF(Z3>0,AA3/Z3,0) -> 96.932271 | AD3: =ELEC!Q3 -> 4100 | AE3: =SUM(AD3/Z3) -> 816.73307 | AF3: =SUM(AE3/1600) -> 0.51045817 | AG3: =SUM(360*AF3) -> 183.76494 | AH3: =SUM(AC3-AG3) -> -86.832669 | AI3: =AD3*AJ3 -> 1055.2743 | AJ3: =305/1185 -> 0.25738397 | AK3: =AI3/Z3 -> 210.214
A4: =ELEC!C4 -> 43892 | B4: 8550 | C4: =B4-B3 -> 2.91 | D4: 131218.9 | E4: =SUM(D4-D3) -> 901.8 | F4: =IF(C4>0,E4/C4,0) -> 309.89691 | H4: =H3 -> 8497 | I4: =IF(B4-H4<=0,"ok","oil change") -> oil change | J4: 10689 | K4: =J4-J3 -> -0.42 | L4: 237069.6 | M4: =SUM(L4-L3) -> 0 | N4: =IF(K4>0,M4/K4,0) -> 0 | P4: =P3 -> 10873 | Q4: =IF(J4-P4<=0,"ok","oil change") -> ok | R4: 10992 | S4: =R4-R3 -> -0.51 | T4: 201286.1 | U4: =SUM(T4-T3) -> 0 | V4: =IF(S4>0,U4/S4,0) -> 0 | X4: =X3 -> 11349 | Y4: =IF(R4-X4<=0,"ok","oil change") -> ok | Z4: =C4+K4+S4 -> 1.98 | AA4: =U4+M4+E4 -> 901.8 | AB4: =V4+N4+F4 -> 309.89691 | AC4: =IF(Z4>0,AA4/Z4,0) -> 455.45455 | AD4: =ELEC!Q4 -> 849 | AE4: =SUM(AD4/Z4) -> 428.78788 | AF4: =SUM(AE4/1600) -> 0.26799242 | AG4: =SUM(360*AF4) -> 96.477273 | AH4: =SUM(AC4-AG4) -> 358.97727 | AI4: =AD4*AJ4 -> 218.51899 | AJ4: =305/1185 -> 0.25738397 | AK4: =AI4/Z4 -> 110.36312
A5: =ELEC!C5 -> 43893 | B5: 8553.45 | C5: =B5-B4 -> 3.45 | D5: 131421 | E5: =SUM(D5-D4) -> 202.1 | F5: =IF(C5>0,E5/C5,0) -> 58.57971 | H5: 8497 | I5: =IF(B5-H5<=0,"ok","oil change") -> oil change | J5: =J4 -> 10689 | K5: =J5-J4 -> 0 | L5: =L4 -> 237069.6 | M5: =SUM(L5-L4) -> 0 | N5: =IF(K5>0,M5/K5,0) -> 0 | P5: =P4 -> 10873 | Q5: =IF(J5-P5<=0,"ok","oil change") -> ok | R5: =R4 -> 10992 | S5: =R5-R4 -> 0 | T5: =T4 -> 201286.1 | U5: =SUM(T5-T4) -> 0 | V5: =IF(S5>0,U5/S5,0) -> 0 | X5: =X4 -> 11349 | Y5: =IF(R5-X5<=0,"ok","oil change") -> ok | Z5: =C5+K5+S5 -> 3.45 | AA5: =U5+M5+E5 -> 202.1 | AB5: =V5+N5+F5 -> 58.57971 | AC5: =IF(Z5>0,AA5/Z5,0) -> 58.57971 | AD5: =ELEC!Q5 -> 1866 | AE5: =SUM(AD5/Z5) -> 540.86957 | AF5: =SUM(AE5/1600) -> 0.33804348 | AG5: =SUM(320*AF5) -> 108.17391 | AH5: =SUM(AC5-AG5) -> -49.594203 | AI5: =AD5*AJ5 -> 480.27848 | AJ5: =305/1185 -> 0.25738397 | AK5: =AI5/Z5 -> 139.21115
A6: =ELEC!C6 -> 43894 | B6: 8556.55 | C6: =B6-B5 -> 3.1 | D6: 131971.3 | E6: =SUM(D6-D5) -> 550.3 | F6: =IF(C6>0,E6/C6,0) -> 177.51613 | H6: =H5 -> 8497 | I6: =IF(B6-H6<=0,"ok","oil change") -> oil change | J6: 10689.42 | K6: =J6-J5 -> 0.42 | L6: 237071 | M6: =SUM(L6-L5) -> 1.4 | N6: =IF(K6>0,M6/K6,0) -> 3.3333333 | P6: =P5 -> 10873 | Q6: =IF(J6-P6<=0,"ok","oil change") -> ok | R6: 10992.51 | S6: =R6-R5 -> 0.51 | T6: =T5 -> 201286.1 | U6: =SUM(T6-T5) -> 0 | V6: =IF(S6>0,U6/S6,0) -> 0 | X6: =X5 -> 11349 | Y6: =IF(R6-X6<=0,"ok","oil change") -> ok | Z6: =C6+K6+S6 -> 4.03 | AA6: =U6+M6+E6 -> 551.7 | AB6: =V6+N6+F6 -> 180.84946 | AC6: =IF(Z6>0,AA6/Z6,0) -> 136.89826 | AD6: =ELEC!Q6 -> 2411 | AE6: =SUM(AD6/Z6) -> 598.26303 | AF6: =SUM(AE6/1600) -> 0.37391439 | AG6: =SUM(320*AF6) -> 119.65261 | AH6: =SUM(AC6-AG6) -> 17.245658 | AI6: =AD6*AJ6 -> 620.55274 | AJ6: =305/1185 -> 0.25738397 | AK6: =AI6/Z6 -> 153.98331
A7: =ELEC!C7 -> 43895 | B7: =B6 -> 8556.55 | C7: =B7-B6 -> 0 | D7: =D6 -> 131971.3 | E7: =SUM(D7-D6) -> 0 | F7: =IF(C7>0,E7/C7,0) -> 0 | H7: =H6 -> 8497 | I7: =IF(B7-H7<=0,"ok","oil change") -> oil change | J7: =J6 -> 10689.42 | K7: =J7-J6 -> 0 | L7: =L6 -> 237071 | M7: =SUM(L7-L6) -> 0 | N7: =IF(K7>0,M7/K7,0) -> 0 | P7: =P6 -> 10873 | Q7: =IF(J7-P7<=0,"ok","oil change") -> ok | R7: =R6 -> 10992.51 | S7: =R7-R6 -> 0 | T7: =T6 -> 201286.1 | U7: =SUM(T7-T6) -> 0 | V7: =IF(S7>0,U7/S7,0) -> 0 | X7: =X6 -> 11349 | Y7: =IF(R7-X7<=0,"ok","oil change") -> ok | Z7: =C7+K7+S7 -> 0 | AA7: =U7+M7+E7 -> 0 | AB7: =V7+N7+F7 -> 0 | AC7: =IF(Z7>0,AA7/Z7,0) -> 0 | AD7: =ELEC!Q7 -> 0 | AE7: =SUM(AD7/Z7) -> #DIV/0! | AF7: =SUM(AE7/1600) -> #DIV/0! | AH7: =SUM(AC7-AG7) -> #VALUE! | AI7: =AD7*AJ7 -> 0 | AJ7: =305/1185 -> 0.25738397 | AK7: =AI7/Z7 -> #DIV/0!
A8: =ELEC!C8 -> 43896 | B8: =B7 -> 8556.55 | C8: =B8-B7 -> 0 | D8: =D7 -> 131971.3 | E8: =SUM(D8-D7) -> 0 | F8: =IF(C8>0,E8/C8,0) -> 0 | H8: =H7 -> 8497 | I8: =IF(B8-H8<=0,"ok","oil change") -> oil change | J8: =J7 -> 10689.42 | K8: =J8-J7 -> 0 | L8: =L7 -> 237071 | M8: =SUM(L8-L7) -> 0 | N8: =IF(K8>0,M8/K8,0) -> 0 | P8: =P7 -> 10873 | Q8: =IF(J8-P8<=0,"ok","oil change") -> ok | R8: =R7 -> 10992.51 | S8: =R8-R7 -> 0 | T8: =T7 -> 201286.1 | U8: =SUM(T8-T7) -> 0 | V8: =IF(S8>0,U8/S8,0) -> 0 | X8: =X7 -> 11349 | Y8: =IF(R8-X8<=0,"ok","oil change") -> ok | Z8: =C8+K8+S8 -> 0 | AA8: =U8+M8+E8 -> 0 | AB8: =V8+N8+F8 -> 0 | AC8: =IF(Z8>0,AA8/Z8,0) -> 0 | AD8: =ELEC!Q8 -> 0 | AE8: =SUM(AD8/Z8) -> #DIV/0! | AF8: =SUM(AE8/1600) -> #DIV/0! | AG8: =SUM(320*AF8) -> #DIV/0! | AH8: =SUM(AC8-AG8) -> #DIV/0! | AI8: =AD8*AJ8 -> 0 | AJ8: =305/1185 -> 0.25738397 | AK8: =AI8/Z8 -> #DIV/0!
A9: =ELEC!C9 -> 43897 | B9: =B8 -> 8556.55 | C9: =B9-B8 -> 0 | D9: =D8 -> 131971.3 | E9: =SUM(D9-D8) -> 0 | F9: =IF(C9>0,E9/C9,0) -> 0 | H9: =H8 -> 8497 | I9: =IF(B9-H9<=0,"ok","oil change") -> oil change | J9: =J8 -> 10689.42 | K9: =J9-J8 -> 0 | L9: =L8 -> 237071 | M9: =SUM(L9-L8) -> 0 | N9: =IF(K9>0,M9/K9,0) -> 0 | P9: =P8 -> 10873 | Q9: =IF(J9-P9<=0,"ok","oil change") -> ok | R9: =R8 -> 10992.51 | S9: =R9-R8 -> 0 | T9: =T8 -> 201286.1 | U9: =SUM(T9-T8) -> 0 | V9: =IF(S9>0,U9/S9,0) -> 0 | X9: =X8 -> 11349 | Y9: =IF(R9-X9<=0,"ok","oil change") -> ok | Z9: =C9+K9+S9 -> 0 | AA9: =U9+M9+E9 -> 0 | AB9: =V9+N9+F9 -> 0 | AC9: =IF(Z9>0,AA9/Z9,0) -> 0 | AD9: =ELEC!Q9 -> 0 | AE9: =SUM(AD9/Z9) -> #DIV/0! | AF9: =SUM(AE9/1600) -> #DIV/0! | AG9: =SUM(320*AF9) -> #DIV/0! | AH9: =SUM(AC9-AG9) -> #DIV/0! | AI9: =AD9*AJ9 -> 0 | AJ9: 0.25738397 | AK9: =IF(Z9>0,AI9/Z9,0) -> 0
A10: =ELEC!C10 -> 43898 | B10: =B9 -> 8556.55 | C10: =B10-B9 -> 0 | D10: =D9 -> 131971.3 | E10: =SUM(D10-D9) -> 0 | F10: =IF(C10>0,E10/C10,0) -> 0 | H10: =H9 -> 8497 | I10: =IF(B10-H10<=0,"ok","oil change") -> oil change | J10: =J9 -> 10689.42 | K10: =J10-J9 -> 0 | L10: =L9 -> 237071 | M10: =SUM(L10-L9) -> 0 | N10: =IF(K10>0,M10/K10,0) -> 0 | P10: 10873 | Q10: =IF(J10-P10<=0,"ok","oil change") -> ok | R10: =R9 -> 10992.51 | S10: =R10-R9 -> 0 | T10: =T9 -> 201286.1 | U10: =SUM(T10-T9) -> 0 | V10: =IF(S10>0,U10/S10,0) -> 0 | X10: =X9 -> 11349 | Y10: =IF(R10-X10<=0,"ok","oil change") -> ok | Z10: =C10+K10+S10 -> 0 | AA10: =U10+M10+E10 -> 0 | AB10: =V10+N10+F10 -> 0 | AC10: =IF(Z10>0,AA10/Z10,0) -> 0 | AD10: =ELEC!Q10 -> 0 | AE10: =SUM(AD10/Z10) -> #DIV/0! | AF10: =SUM(AE10/1600) -> #DIV/0! | AG10: =SUM(320*AF10) -> #DIV/0! | AH10: =SUM(AC10-AG10) -> #DIV/0! | AI10: =AD10*AJ10 -> 0 | AJ10: =305/1185 -> 0.25738397 | AK10: =IF(Z10>0,AI10/Z10,0) -> 0
A11: =ELEC!C11 -> 43899 | B11: =B10 -> 8556.55 | C11: =B11-B10 -> 0 | D11: =D10 -> 131971.3 | E11: =SUM(D11-D10) -> 0 | F11: =IF(C11>0,E11/C11,0) -> 0 | H11: =H10 -> 8497 | I11: =IF(B11-H11<=0,"ok","oil change") -> oil change | J11: =J10 -> 10689.42 | K11: =J11-J10 -> 0 | L11: =L10 -> 237071 | M11: =SUM(L11-L10) -> 0 | N11: =IF(K11>0,M11/K11,0) -> 0 | P11: =P10 -> 10873 | Q11: =IF(J11-P11<=0,"ok","oil change") -> ok | R11: =R10 -> 10992.51 | S11: =R11-R10 -> 0 | T11: =T10 -> 201286.1 | U11: =SUM(T11-T10) -> 0 | V11: =IF(S11>0,U11/S11,0) -> 0 | X11: =X10 -> 11349 | Y11: =IF(R11-X11<=0,"ok","oil change") -> ok | Z11: =C11+K11+S11 -> 0 | AA11: =U11+M11+E11 -> 0 | AB11: =V11+N11+F11 -> 0 | AC11: =IF(Z11>0,AA11/Z11,0) -> 0 | AD11: =ELEC!Q11 -> 0 | AE11: =SUM(AD11/Z11) -> #DIV/0! | AF11: =SUM(AE11/1600) -> #DIV/0! | AG11: =SUM(320*AF11) -> #DIV/0! | AH11: =SUM(AC11-AG11) -> #DIV/0! | AI11: =AD11*AJ11 -> 0 | AJ11: =305/1185 -> 0.25738397 | AK11: =IF(Z11>0,AI11/Z11,0) -> 0
A12: =ELEC!C12 -> 43900 | B12: =B11 -> 8556.55 | C12: =B12-B11 -> 0 | D12: =D11 -> 131971.3 | E12: =SUM(D12-D11) -> 0 | F12: =IF(C12>0,E12/C12,0) -> 0 | H12: =H11 -> 8497 | I12: =IF(B12-H12<=0,"ok","oil change") -> oil change | J12: =J11 -> 10689.42 | K12: =J12-J11 -> 0 | L12: =L11 -> 237071 | M12: =SUM(L12-L11) -> 0 | N12: =IF(K12>0,M12/K12,0) -> 0 | P12: =P11 -> 10873 | Q12: =IF(J12-P12<=0,"ok","oil change") -> ok | R12: =R11 -> 10992.51 | S12: =R12-R11 -> 0 | T12: =T11 -> 201286.1 | U12: =SUM(T12-T11) -> 0 | V12: =IF(S12>0,U12/S12,0) -> 0 | X12: =X11 -> 11349 | Y12: =IF(R12-X12<=0,"ok","oil change") -> ok | Z12: =C12+K12+S12 -> 0 | AA12: =U12+M12+E12 -> 0 | AB12: =V12+N12+F12 -> 0 | AC12: =IF(Z12>0,AA12/Z12,0) -> 0 | AD12: =ELEC!Q12 -> 0 | AE12: =SUM(AD12/Z12) -> #DIV/0! | AF12: =SUM(AE12/1600) -> #DIV/0! | AG12: =SUM(320*AF12) -> #DIV/0! | AH12: =SUM(AC12-AG12) -> #DIV/0! | AI12: =AD12*AJ12 -> 0 | AJ12: =305/1185 -> 0.25738397 | AK12: =IF(Z12>0,AI12/Z12,0) -> 0
A13: =ELEC!C13 -> 43901 | B13: =B12 -> 8556.55 | C13: =B13-B12 -> 0 | D13: =D12 -> 131971.3 | E13: =SUM(D13-D12) -> 0 | F13: =IF(C13>0,E13/C13,0) -> 0 | H13: =H12 -> 8497 | I13: =IF(B13-H13<=0,"ok","oil change") -> oil change | J13: =J12 -> 10689.42 | K13: =J13-J12 -> 0 | L13: =L12 -> 237071 | M13: =SUM(L13-L12) -> 0 | N13: =IF(K13>0,M13/K13,0) -> 0 | P13: =P12 -> 10873 | Q13: =IF(J13-P13<=0,"ok","oil change") -> ok | R13: =R12 -> 10992.51 | S13: =R13-R12 -> 0 | T13: =T12 -> 201286.1 | U13: =SUM(T13-T12) -> 0 | V13: =IF(S13>0,U13/S13,0) -> 0 | X13: =X12+180 -> 11529 | Y13: =IF(R13-X13<=0,"ok","oil change") -> ok | Z13: =C13+K13+S13 -> 0 | AA13: =U13+M13+E13 -> 0 | AB13: =V13+N13+F13 -> 0 | AC13: =IF(Z13>0,AA13/Z13,0) -> 0 | AD13: =ELEC!Q13 -> 0 | AE13: =SUM(AD13/Z13) -> #DIV/0! | AF13: =SUM(AE13/1600) -> #DIV/0! | AG13: =SUM(320*AF13) -> #DIV/0! | AH13: =SUM(AC13-AG13) -> #DIV/0! | AI13: =AD13*AJ13 -> 0 | AJ13: =305/1185 -> 0.25738397 | AK13: =IF(Z13>0,AI13/Z13,0) -> 0
A14: =ELEC!C14 -> 43902 | B14: =B13 -> 8556.55 | C14: =B14-B13 -> 0 | D14: =D13 -> 131971.3 | E14: =SUM(D14-D13) -> 0 | F14: =IF(C14>0,E14/C14,0) -> 0 | H14: =H13 -> 8497 | I14: =IF(B14-H14<=0,"ok","oil change") -> oil change | J14: =J13 -> 10689.42 | K14: =J14-J13 -> 0 | L14: =L13 -> 237071 | M14: =SUM(L14-L13) -> 0 | N14: =IF(K14>0,M14/K14,0) -> 0 | P14: =P13 -> 10873 | Q14: =IF(J14-P14<=0,"ok","oil change") -> ok | R14: =R13 -> 10992.51 | S14: =R14-R13 -> 0 | T14: =T13 -> 201286.1 | U14: =SUM(T14-T13) -> 0 | V14: =IF(S14>0,U14/S14,0) -> 0 | X14: =X13 -> 11529 | Y14: =IF(R14-X14<=0,"ok","oil change") -> ok | Z14: =C14+K14+S14 -> 0 | AA14: =U14+M14+E14 -> 0 | AB14: =V14+N14+F14 -> 0 | AC14: =IF(Z14>0,AA14/Z14,0) -> 0 | AD14: =ELEC!Q14 -> 0 | AE14: =SUM(AD14/Z14) -> #DIV/0! | AF14: =SUM(AE14/1600) -> #DIV/0! | AG14: =SUM(320*AF14) -> #DIV/0! | AH14: =SUM(AC14-AG14) -> #DIV/0! | AI14: =AD14*AJ14 -> 0 | AJ14: =305/1185 -> 0.25738397 | AK14: =IF(Z14>0,AI14/Z14,0) -> 0
A15: =ELEC!C15 -> 43903 | B15: =B14 -> 8556.55 | C15: =B15-B14 -> 0 | D15: =D14 -> 131971.3 | E15: =SUM(D15-D14) -> 0 | F15: =IF(C15>0,E15/C15,0) -> 0 | H15: =H14 -> 8497 | I15: =IF(B15-H15<=0,"ok","oil change") -> oil change | J15: =J14 -> 10689.42 | K15: =J15-J14 -> 0 | L15: =L14 -> 237071 | M15: =SUM(L15-L14) -> 0 | N15: =IF(K15>0,M15/K15,0) -> 0 | P15: =P14 -> 10873 | Q15: =IF(J15-P15<=0,"ok","oil change") -> ok | R15: =R14 -> 10992.51 | S15: =R15-R14 -> 0 | T15: =T14 -> 201286.1 | U15: =SUM(T15-T14) -> 0 | V15: =IF(S15>0,U15/S15,0) -> 0 | X15: =X14 -> 11529 | Y15: =IF(R15-X15<=0,"ok","oil change") -> ok | Z15: =C15+K15+S15 -> 0 | AA15: =U15+M15+E15 -> 0 | AB15: =V15+N15+F15 -> 0 | AC15: =IF(Z15>0,AA15/Z15,0) -> 0 | AD15: =ELEC!Q15 -> 0 | AE15: =SUM(AD15/Z15) -> #DIV/0! | AF15: =SUM(AE15/1600) -> #DIV/0! | AG15: =SUM(320*AF15) -> #DIV/0! | AH15: =SUM(AC15-AG15) -> #DIV/0! | AI15: =AD15*AJ15 -> 0 | AJ15: =305/1185 -> 0.25738397 | AK15: =IF(Z15>0,AI15/Z15,0) -> 0
A16: =ELEC!C16 -> 43904 | B16: =B15 -> 8556.55 | C16: =B16-B15 -> 0 | D16: =D15 -> 131971.3 | E16: =SUM(D16-D15) -> 0 | F16: =IF(C16>0,E16/C16,0) -> 0 | H16: =H15 -> 8497 | I16: =IF(B16-H16<=0,"ok","oil change") -> oil change | J16: =J15 -> 10689.42 | K16: =J16-J15 -> 0 | L16: =L15 -> 237071 | M16: =SUM(L16-L15) -> 0 | N16: =IF(K16>0,M16/K16,0) -> 0 | P16: =P15 -> 10873 | Q16: =IF(J16-P16<=0,"ok","oil change") -> ok | R16: =R15 -> 10992.51 | S16: =R16-R15 -> 0 | T16: =T15 -> 201286.1 | U16: =SUM(T16-T15) -> 0 | V16: =IF(S16>0,U16/S16,0) -> 0 | X16: =X15 -> 11529 | Y16: =IF(R16-X16<=0,"ok","oil change") -> ok | Z16: =C16+K16+S16 -> 0 | AA16: =U16+M16+E16 -> 0 | AB16: =V16+N16+F16 -> 0 | AC16: =IF(Z16>0,AA16/Z16,0) -> 0 | AD16: =ELEC!Q16 -> 0 | AE16: =SUM(AD16/Z16) -> #DIV/0! | AF16: =SUM(AE16/1600) -> #DIV/0! | AG16: =SUM(320*AF16) -> #DIV/0! | AH16: =SUM(AC16-AG16) -> #DIV/0! | AI16: =AD16*AJ16 -> 0 | AJ16: =305/1185 -> 0.25738397 | AK16: =IF(Z16>0,AI16/Z16,0) -> 0
A17: =ELEC!C17 -> 43905 | B17: =B16 -> 8556.55 | C17: =B17-B16 -> 0 | D17: =D16 -> 131971.3 | E17: =SUM(D17-D16) -> 0 | F17: =IF(C17>0,E17/C17,0) -> 0 | H17: =H16 -> 8497 | I17: =IF(B17-H17<=0,"ok","oil change") -> oil change | J17: =J16 -> 10689.42 | K17: =J17-J16 -> 0 | L17: =L16 -> 237071 | M17: =SUM(L17-L16) -> 0 | N17: =IF(K17>0,M17/K17,0) -> 0 | P17: =P16 -> 10873 | Q17: =IF(J17-P17<=0,"ok","oil change") -> ok | R17: =R16 -> 10992.51 | S17: =R17-R16 -> 0 | T17: =T16 -> 201286.1 | U17: =SUM(T17-T16) -> 0 | V17: =IF(S17>0,U17/S17,0) -> 0 | X17: =X16 -> 11529 | Y17: =IF(R17-X17<=0,"ok","oil change") -> ok | Z17: =C17+K17+S17 -> 0 | AA17: =U17+M17+E17 -> 0 | AB17: =V17+N17+F17 -> 0 | AC17: =IF(Z17>0,AA17/Z17,0) -> 0 | AD17: =ELEC!Q17 -> 0 | AE17: =SUM(AD17/Z17) -> #DIV/0! | AF17: =SUM(AE17/1600) -> #DIV/0! | AG17: =SUM(320*AF17) -> #DIV/0! | AH17: =SUM(AC17-AG17) -> #DIV/0! | AI17: =AD17*AJ17 -> 0 | AJ17: =305/1185 -> 0.25738397 | AK17: =IF(Z17>0,AI17/Z17,0) -> 0
A18: =ELEC!C18 -> 43906 | B18: =B17 -> 8556.55 | C18: =B18-B17 -> 0 | D18: =D17 -> 131971.3 | E18: =SUM(D18-D17) -> 0 | F18: =IF(C18>0,E18/C18,0) -> 0 | H18: =H17 -> 8497 | I18: =IF(B18-H18<=0,"ok","oil change") -> oil change | J18: =J17 -> 10689.42 | K18: =J18-J17 -> 0 | L18: =L17 -> 237071 | M18: =SUM(L18-L17) -> 0 | N18: =IF(K18>0,M18/K18,0) -> 0 | P18: =P17 -> 10873 | Q18: =IF(J18-P14<=0,"ok","oil change") -> ok | R18: =R17 -> 10992.51 | S18: =R18-R17 -> 0 | T18: =T17 -> 201286.1 | U18: =SUM(T18-T17) -> 0 | V18: =IF(S18>0,U18/S18,0) -> 0 | X18: =X17 -> 11529 | Y18: =IF(R18-X18<=0,"ok","oil change") -> ok | Z18: =C18+K18+S18 -> 0 | AA18: =U18+M18+E18 -> 0 | AB18: =V18+N18+F18 -> 0 | AC18: =IF(Z18>0,AA18/Z18,0) -> 0 | AD18: =ELEC!Q18 -> 0 | AE18: =SUM(AD18/Z18) -> #DIV/0! | AF18: =SUM(AE18/1600) -> #DIV/0! | AG18: =SUM(320*AF18) -> #DIV/0! | AH18: =SUM(AC18-AG18) -> #DIV/0! | AI18: =AD18*AJ18 -> 0 | AJ18: =305/1185 -> 0.25738397 | AK18: =IF(Z18>0,AI18/Z18,0) -> 0
A19: =ELEC!C19 -> 43907 | B19: =B18 -> 8556.55 | C19: =B19-B18 -> 0 | D19: =D18 -> 131971.3 | E19: =SUM(D19-D18) -> 0 | F19: =IF(C19>0,E19/C19,0) -> 0 | H19: =H18 -> 8497 | I19: =IF(B19-H19<=0,"ok","oil change") -> oil change | J19: =J18 -> 10689.42 | K19: =J19-J18 -> 0 | L19: =L18 -> 237071 | M19: =SUM(L19-L18) -> 0 | N19: =IF(K19>0,M19/K19,0) -> 0 | P19: =P18 -> 10873 | Q19: =IF(J19-P19<=0,"ok","oil change") -> ok | R19: =R18 -> 10992.51 | S19: =R19-R18 -> 0 | T19: =T18 -> 201286.1 | U19: =SUM(T19-T18) -> 0 | V19: =IF(S19>0,U19/S19,0) -> 0 | X19: =X18 -> 11529 | Y19: =IF(R19-X19<=0,"ok","oil change") -> ok | Z19: =C19+K19+S19 -> 0 | AA19: =U19+M19+E19 -> 0 | AB19: =V19+N19+F19 -> 0 | AC19: =IF(Z19>0,AA19/Z19,0) -> 0 | AD19: =ELEC!Q19 -> 0 | AE19: =SUM(AD19/Z19) -> #DIV/0! | AF19: =SUM(AE19/1600) -> #DIV/0! | AG19: =SUM(320*AF19) -> #DIV/0! | AH19: =SUM(AC19-AG19) -> #DIV/0! | AI19: =AD19*AJ19 -> 0 | AJ19: =305/1185 -> 0.25738397 | AK19: =IF(Z19>0,AI19/Z19,0) -> 0
A20: =ELEC!C20 -> 43908 | B20: =B19 -> 8556.55 | C20: =B20-B19 -> 0 | D20: =D19 -> 131971.3 | E20: =SUM(D20-D19) -> 0 | F20: =IF(C20>0,E20/C20,0) -> 0 | H20: =H19 -> 8497 | I20: =IF(B20-H20<=0,"ok","oil change") -> oil change | J20: =J19 -> 10689.42 | K20: =J20-J19 -> 0 | L20: =L19 -> 237071 | M20: =SUM(L20-L19) -> 0 | N20: =IF(K20>0,M20/K20,0) -> 0 | P20: =P19 -> 10873 | Q20: =IF(J20-P20<=0,"ok","oil change") -> ok | R20: =R19 -> 10992.51 | S20: =R20-R19 -> 0 | T20: =T19 -> 201286.1 | U20: =SUM(T20-T19) -> 0 | V20: =IF(S20>0,U20/S20,0) -> 0 | X20: =X19 -> 11529 | Y20: =IF(R20-X20<=0,"ok","oil change") -> ok | Z20: =C20+K20+S20 -> 0 | AA20: =U20+M20+E20 -> 0 | AB20: =V20+N20+F20 -> 0 | AC20: =IF(Z20>0,AA20/Z20,0) -> 0 | AD20: =ELEC!Q20 -> 0 | AE20: =SUM(AD20/Z20) -> #DIV/0! | AF20: =SUM(AE20/1600) -> #DIV/0! | AG20: =SUM(320*AF20) -> #DIV/0! | AH20: =SUM(AC20-AG20) -> #DIV/0! | AI20: =AD20*AJ20 -> 0 | AJ20: =305/1185 -> 0.25738397 | AK20: =IF(Z20>0,AI20/Z20,0) -> 0
A21: =ELEC!C21 -> 43909 | B21: =B20 -> 8556.55 | C21: =B21-B20 -> 0 | D21: =D20 -> 131971.3 | E21: =SUM(D21-D20) -> 0 | F21: =IF(C21>0,E21/C21,0) -> 0 | H21: =H20 -> 8497 | I21: =IF(B21-H21<=0,"ok","oil change") -> oil change | J21: =J20 -> 10689.42 | K21: =J21-J20 -> 0 | L21: =L20 -> 237071 | M21: =SUM(L21-L20) -> 0 | N21: =IF(K21>0,M21/K21,0) -> 0 | P21: =P20 -> 10873 | Q21: =IF(J21-P21<=0,"ok","oil change") -> ok | R21: =R20 -> 10992.51 | S21: =R21-R20 -> 0 | T21: =T20 -> 201286.1 | U21: =SUM(T21-T20) -> 0 | V21: =IF(S21>0,U21/S21,0) -> 0 | X21: =X20 -> 11529 | Y21: =Y20 -> ok | Z21: =C21+K21+S21 -> 0 | AA21: =U21+M21+E21 -> 0 | AB21: =V21+N21+F21 -> 0 | AC21: =IF(Z21>0,AA21/Z21,0) -> 0 | AD21: =ELEC!Q21 -> 0 | AE21: =SUM(AD21/Z21) -> #DIV/0! | AF21: =SUM(AE21/1600) -> #DIV/0! | AG21: =SUM(320*AF21) -> #DIV/0! | AH21: =SUM(AC21-AG21) -> #DIV/0! | AI21: =AD21*AJ21 -> 0 | AJ21: =305/1185 -> 0.25738397 | AK21: =IF(Z21>0,AI21/Z21,0) -> 0
A22: =ELEC!C22 -> 43910 | B22: =B21 -> 8556.55 | C22: =B22-B21 -> 0 | D22: =D21 -> 131971.3 | E22: =SUM(D22-D21) -> 0 | F22: =IF(C22>0,E22/C22,0) -> 0 | H22: =H21 -> 8497 | I22: =IF(B22-H22<=0,"ok","oil change") -> oil change | J22: =J21 -> 10689.42 | K22: =J22-J21 -> 0 | L22: =L21 -> 237071 | M22: =SUM(L22-L21) -> 0 | N22: =IF(K22>0,M22/K22,0) -> 0 | P22: =P21 -> 10873 | Q22: =IF(J22-P22<=0,"ok","oil change") -> ok | R22: =R21 -> 10992.51 | S22: =R22-R21 -> 0 | T22: =T21 -> 201286.1 | U22: =SUM(T22-T21) -> 0 | V22: =IF(S22>0,U22/S22,0) -> 0 | X22: =X21 -> 11529 | Y22: =IF(R22-X22<=0,"ok","oil change") -> ok | Z22: =C22+K22+S22 -> 0 | AA22: =U22+M22+E22 -> 0 | AB22: =V22+N22+F22 -> 0 | AC22: =IF(Z22>0,AA22/Z22,0) -> 0 | AD22: =ELEC!Q22 -> 0 | AE22: =SUM(AD22/Z22) -> #DIV/0! | AF22: =SUM(AE22/1600) -> #DIV/0! | AG22: =SUM(320*AF22) -> #DIV/0! | AH22: =SUM(AC22-AG22) -> #DIV/0! | AI22: =AD22*AJ22 -> 0 | AJ22: =305/1185 -> 0.25738397 | AK22: =IF(Z22>0,AI22/Z22,0) -> 0
A23: =ELEC!C23 -> 43911 | B23: =B22 -> 8556.55 | C23: =B23-B22 -> 0 | D23: =D22 -> 131971.3 | E23: =SUM(D23-D22) -> 0 | F23: =IF(C23>0,E23/C23,0) -> 0 | H23: =H22 -> 8497 | I23: =IF(B23-H23<=0,"ok","oil change") -> oil change | J23: =J22 -> 10689.42 | K23: =J23-J22 -> 0 | L23: =L22 -> 237071 | M23: =SUM(L23-L22) -> 0 | N23: =IF(K23>0,M23/K23,0) -> 0 | P23: =P22 -> 10873 | Q23: =IF(J23-P23<=0,"ok","oil change") -> ok | R23: =R22 -> 10992.51 | S23: =R23-R22 -> 0 | T23: =T22 -> 201286.1 | U23: =SUM(T23-T22) -> 0 | V23: =IF(S23>0,U23/S23,0) -> 0 | X23: =X22 -> 11529 | Y23: =IF(R23-X23<=0,"ok","oil change") -> ok | Z23: =C23+K23+S23 -> 0 | AA23: =U23+M23+E23 -> 0 | AB23: =V23+N23+F23 -> 0 | AC23: =IF(Z23>0,AA23/Z23,0) -> 0 | AD23: =ELEC!Q23 -> 0 | AE23: =SUM(AD23/Z23) -> #DIV/0! | AF23: =SUM(AE23/1600) -> #DIV/0! | AG23: =SUM(320*AF23) -> #DIV/0! | AH23: =SUM(AC23-AG23) -> #DIV/0! | AI23: =AD23*AJ23 -> 0 | AJ23: =305/1185 -> 0.25738397 | AK23: =IF(Z23>0,AI23/Z23,0) -> 0
A24: =ELEC!C24 -> 43912 | B24: =B23 -> 8556.55 | C24: =B24-B23 -> 0 | D24: =D23 -> 131971.3 | E24: =SUM(D24-D23) -> 0 | F24: =IF(C24>0,E24/C24,0) -> 0 | H24: =H23 -> 8497 | I24: =IF(B24-H24<=0,"ok","oil change") -> oil change | J24: =J23 -> 10689.42 | K24: =J24-J23 -> 0 | L24: =L23 -> 237071 | M24: =SUM(L24-L23) -> 0 | N24: =IF(K24>0,M24/K24,0) -> 0 | P24: =P23 -> 10873 | Q24: =IF(J24-P24<=0,"ok","oil change") -> ok | R24: =R23 -> 10992.51 | S24: =R24-R23 -> 0 | T24: =T23 -> 201286.1 | U24: =SUM(T24-T23) -> 0 | V24: =IF(S24>0,U24/S24,0) -> 0 | X24: =X23 -> 11529 | Y24: =IF(R24-X24<=0,"ok","oil change") -> ok | Z24: =C24+K24+S24 -> 0 | AA24: =U24+M24+E24 -> 0 | AB24: =V24+N24+F24 -> 0 | AC24: =IF(Z24>0,AA24/Z24,0) -> 0 | AD24: =ELEC!Q24 -> 0 | AE24: =SUM(AD24/Z24) -> #DIV/0! | AF24: =SUM(AE24/1600) -> #DIV/0! | AG24: =SUM(320*AF24) -> #DIV/0! | AH24: =SUM(AC24-AG24) -> #DIV/0! | AI24: =AD24*AJ24 -> 0 | AJ24: =305/1185 -> 0.25738397 | AK24: =IF(Z24>0,AI24/Z24,0) -> 0
A25: =ELEC!C25 -> 43913 | B25: =B24 -> 8556.55 | C25: =B25-B24 -> 0 | D25: =D24 -> 131971.3 | E25: =SUM(D25-D24) -> 0 | F25: =IF(C25>0,E25/C25,0) -> 0 | H25: =H24 -> 8497 | I25: =IF(B25-H25<=0,"ok","oil change") -> oil change | J25: =J24 -> 10689.42 | K25: =J25-J24 -> 0 | L25: =L24 -> 237071 | M25: =SUM(L25-L24) -> 0 | N25: =IF(K25>0,M25/K25,0) -> 0 | P25: =P24 -> 10873 | Q25: =IF(J25-P25<=0,"ok","oil change") -> ok | R25: =R24 -> 10992.51 | S25: =R25-R24 -> 0 | T25: =T24 -> 201286.1 | U25: =SUM(T25-T24) -> 0 | V25: =IF(S25>0,U25/S25,0) -> 0 | X25: =X24 -> 11529 | Y25: =IF(R25-X25<=0,"ok","oil change") -> ok | Z25: =C25+K25+S25 -> 0 | AA25: =U25+M25+E25 -> 0 | AB25: =V25+N25+F25 -> 0 | AC25: =IF(Z25>0,AA25/Z25,0) -> 0 | AD25: =ELEC!Q25 -> 0 | AE25: =SUM(AD25/Z25) -> #DIV/0! | AF25: =SUM(AE25/1600) -> #DIV/0! | AG25: =SUM(320*AF25) -> #DIV/0! | AH25: =SUM(AC25-AG25) -> #DIV/0! | AI25: =AD25*AJ25 -> 0 | AJ25: =305/1185 -> 0.25738397 | AK25: =IF(Z25>0,AI25/Z25,0) -> 0
A26: =ELEC!C26 -> 43914 | B26: =B25 -> 8556.55 | C26: =B26-B25 -> 0 | D26: =D25 -> 131971.3 | E26: =SUM(D26-D25) -> 0 | F26: =IF(C26>0,E26/C26,0) -> 0 | H26: =H25 -> 8497 | I26: =IF(B26-H26<=0,"ok","oil change") -> oil change | J26: =J25 -> 10689.42 | K26: =J26-J25 -> 0 | L26: =L25 -> 237071 | M26: =SUM(L26-L25) -> 0 | N26: =IF(K26>0,M26/K26,0) -> 0 | P26: =P25 -> 10873 | Q26: =IF(J26-P26<=0,"ok","oil change") -> ok | R26: =R25 -> 10992.51 | S26: =R26-R25 -> 0 | T26: =T25 -> 201286.1 | U26: =SUM(T26-T25) -> 0 | V26: =IF(S26>0,U26/S26,0) -> 0 | X26: =X25 -> 11529 | Y26: =IF(R26-X26<=0,"ok","oil change") -> ok | Z26: =C26+K26+S26 -> 0 | AA26: =U26+M26+E26 -> 0 | AB26: =V26+N26+F26 -> 0 | AC26: =IF(Z26>0,AA26/Z26,0) -> 0 | AD26: =ELEC!Q26 -> 0 | AE26: =SUM(AD26/Z26) -> #DIV/0! | AF26: =SUM(AE26/1600) -> #DIV/0! | AG26: =SUM(320*AF26) -> #DIV/0! | AH26: =SUM(AC26-AG26) -> #DIV/0! | AI26: =AD26*AJ26 -> 0 | AJ26: =305/1185 -> 0.25738397 | AK26: =IF(Z26>0,AI26/Z26,0) -> 0
A27: =ELEC!C27 -> 43915 | B27: =B26 -> 8556.55 | C27: =B27-B26 -> 0 | D27: =D26 -> 131971.3 | E27: =SUM(D27-D26) -> 0 | F27: =IF(C27>0,E27/C27,0) -> 0 | H27: =H26 -> 8497 | I27: =IF(B27-H27<=0,"ok","oil change") -> oil change | J27: =J26 -> 10689.42 | K27: =J27-J26 -> 0 | L27: =L26 -> 237071 | M27: =SUM(L27-L26) -> 0 | N27: =IF(K27>0,M27/K27,0) -> 0 | P27: =P26 -> 10873 | Q27: =IF(J27-P27<=0,"ok","oil change") -> ok | R27: =R26 -> 10992.51 | S27: =R27-R26 -> 0 | T27: =T26 -> 201286.1 | U27: =SUM(T27-T26) -> 0 | V27: =IF(S27>0,U27/S27,0) -> 0 | X27: =X26 -> 11529 | Y27: =IF(R27-X27<=0,"ok","oil change") -> ok | Z27: =C27+K27+S27 -> 0 | AA27: =U27+M27+E27 -> 0 | AB27: =V27+N27+F27 -> 0 | AC27: =IF(Z27>0,AA27/Z27,0) -> 0 | AD27: =ELEC!Q27 -> 0 | AE27: =SUM(AD27/Z27) -> #DIV/0! | AF27: =SUM(AE27/1600) -> #DIV/0! | AG27: =SUM(320*AF27) -> #DIV/0! | AH27: =SUM(AC27-AG27) -> #DIV/0! | AI27: =AD27*AJ27 -> 0 | AJ27: =305/1185 -> 0.25738397 | AK27: =IF(Z27>0,AI27/Z27,0) -> 0
A28: =ELEC!C28 -> 43916 | B28: =B27 -> 8556.55 | C28: =B28-B27 -> 0 | D28: =D27 -> 131971.3 | E28: =SUM(D28-D27) -> 0 | F28: =IF(C28>0,E28/C28,0) -> 0 | H28: =H27 -> 8497 | I28: =IF(B28-H28<=0,"ok","oil change") -> oil change | J28: =J27 -> 10689.42 | K28: =J28-J27 -> 0 | L28: =L27 -> 237071 | M28: =SUM(L28-L27) -> 0 | N28: =IF(K28>0,M28/K28,0) -> 0 | P28: =P27 -> 10873 | Q28: =IF(J28-P28<=0,"ok","oil change") -> ok | R28: =R27 -> 10992.51 | S28: =R28-R27 -> 0 | T28: =T27 -> 201286.1 | U28: =SUM(T28-T27) -> 0 | V28: =IF(S28>0,U28/S28,0) -> 0 | X28: =X27 -> 11529 | Y28: =IF(R28-X28<=0,"ok","oil change") -> ok | Z28: =C28+K28+S28 -> 0 | AA28: =U28+M28+E28 -> 0 | AB28: =V28+N28+F28 -> 0 | AC28: =IF(Z28>0,AA28/Z28,0) -> 0 | AD28: =ELEC!Q28 -> 0 | AE28: =SUM(AD28/Z28) -> #DIV/0! | AF28: =SUM(AE28/1600) -> #DIV/0! | AG28: =SUM(320*AF28) -> #DIV/0! | AH28: =SUM(AC28-AG28) -> #DIV/0! | AI28: =AD28*AJ28 -> 0 | AJ28: =305/1185 -> 0.25738397 | AK28: =IF(Z28>0,AI28/Z28,0) -> 0
A29: =ELEC!C29 -> 43917 | B29: =B28 -> 8556.55 | C29: =B29-B28 -> 0 | D29: =D28 -> 131971.3 | E29: =SUM(D29-D28) -> 0 | F29: =IF(C29>0,E29/C29,0) -> 0 | H29: =H28 -> 8497 | I29: =IF(B29-H29<=0,"ok","oil change") -> oil change | J29: =J28 -> 10689.42 | K29: =J29-J28 -> 0 | L29: =L28 -> 237071 | M29: =SUM(L29-L28) -> 0 | N29: =IF(K29>0,M29/K29,0) -> 0 | P29: =P28 -> 10873 | Q29: =IF(J29-P29<=0,"ok","oil change") -> ok | R29: =R28 -> 10992.51 | S29: =R29-R28 -> 0 | T29: =T28 -> 201286.1 | U29: =SUM(T29-T28) -> 0 | V29: =IF(S29>0,U29/S29,0) -> 0 | X29: =X28 -> 11529 | Y29: =IF(R29-X29<=0,"ok","oil change") -> ok | Z29: =C29+K29+S29 -> 0 | AA29: =U29+M29+E29 -> 0 | AB29: =V29+N29+F29 -> 0 | AC29: =IF(Z29>0,AA29/Z29,0) -> 0 | AD29: =ELEC!Q29 -> 0 | AE29: =SUM(AD29/Z29) -> #DIV/0! | AF29: =SUM(AE29/1600) -> #DIV/0! | AG29: =SUM(320*AF29) -> #DIV/0! | AH29: =SUM(AC29-AG29) -> #DIV/0! | AI29: =AD29*AJ29 -> 0 | AJ29: =305/1185 -> 0.25738397 | AK29: =IF(Z29>0,AI29/Z29,0) -> 0
A30: =ELEC!C30 -> 43918 | B30: =B29 -> 8556.55 | C30: =B30-B29 -> 0 | D30: =D29 -> 131971.3 | E30: =SUM(D30-D29) -> 0 | F30: =IF(C30>0,E30/C30,0) -> 0 | H30: =H29 -> 8497 | I30: =IF(B30-H30<=0,"ok","oil change") -> oil change | J30: =J29 -> 10689.42 | K30: =J30-J29 -> 0 | L30: =L29 -> 237071 | M30: =SUM(L30-L29) -> 0 | N30: =IF(K30>0,M30/K30,0) -> 0 | P30: =P29 -> 10873 | Q30: =IF(J30-P30<=0,"ok","oil change") -> ok | R30: =R29 -> 10992.51 | S30: =R30-R29 -> 0 | T30: =T29 -> 201286.1 | U30: =SUM(T30-T29) -> 0 | V30: =IF(S30>0,U30/S30,0) -> 0 | X30: =X29 -> 11529 | Y30: =IF(R30-X30<=0,"ok","oil change") -> ok | Z30: =C30+K30+S30 -> 0 | AA30: =U30+M30+E30 -> 0 | AB30: =V30+N30+F30 -> 0 | AC30: =IF(Z30>0,AA30/Z30,0) -> 0 | AD30: =ELEC!Q30 -> 0 | AE30: =SUM(AD30/Z30) -> #DIV/0! | AF30: =SUM(AE30/1600) -> #DIV/0! | AG30: =SUM(320*AF30) -> #DIV/0! | AH30: =SUM(AC30-AG30) -> #DIV/0! | AI30: =AD30*AJ30 -> 0 | AJ30: =305/1185 -> 0.25738397 | AK30: =IF(Z30>0,AI30/Z30,0) -> 0
A31: =ELEC!C31 -> 43919 | B31: =B30 -> 8556.55 | C31: =B31-B30 -> 0 | D31: =D30 -> 131971.3 | E31: =SUM(D31-D30) -> 0 | F31: =IF(C31>0,E31/C31,0) -> 0 | H31: =H30 -> 8497 | I31: =IF(B31-H31<=0,"ok","oil change") -> oil change | J31: =J30 -> 10689.42 | K31: =J31-J30 -> 0 | L31: =L30 -> 237071 | M31: =SUM(L31-L30) -> 0 | N31: =IF(K31>0,M31/K31,0) -> 0 | P31: =P30 -> 10873 | Q31: =IF(J31-P31<=0,"ok","oil change") -> ok | R31: =R30 -> 10992.51 | S31: =R31-R30 -> 0 | T31: =T30 -> 201286.1 | U31: =SUM(T31-T30) -> 0 | V31: =IF(S31>0,U31/S31,0) -> 0 | X31: =X30 -> 11529 | Y31: =IF(R31-X31<=0,"ok","oil change") -> ok | Z31: =C31+K31+S31 -> 0 | AA31: =U31+M31+E31 -> 0 | AB31: =V31+N31+F31 -> 0 | AC31: =IF(Z31>0,AA31/Z31,0) -> 0 | AD31: =ELEC!Q31 -> 0 | AE31: =SUM(AD31/Z31) -> #DIV/0! | AF31: =SUM(AE31/1600) -> #DIV/0! | AG31: =SUM(320*AF31) -> #DIV/0! | AH31: =SUM(AC31-AG31) -> #DIV/0! | AI31: =AD31*AJ31 -> 0 | AJ31: =305/1185 -> 0.25738397 | AK31: =IF(Z31>0,AI31/Z31,0) -> 0
A32: =ELEC!C32 -> 43920 | B32: =B31 -> 8556.55 | C32: =B32-B31 -> 0 | D32: =D31 -> 131971.3 | E32: =SUM(D32-D31) -> 0 | F32: =IF(C32>0,E32/C32,0) -> 0 | H32: =H31 -> 8497 | I32: =IF(B32-H32<=0,"ok","oil change") -> oil change | J32: =J31 -> 10689.42 | K32: =J32-J31 -> 0 | L32: =L31 -> 237071 | M32: =SUM(L32-L31) -> 0 | N32: =IF(K32>0,M32/K32,0) -> 0 | P32: =P31 -> 10873 | Q32: =IF(J32-P32<=0,"ok","oil change") -> ok | R32: =R31 -> 10992.51 | S32: =R32-R31 -> 0 | T32: =T31 -> 201286.1 | U32: =SUM(T32-T31) -> 0 | V32: =IF(S32>0,U32/S32,0) -> 0 | X32: =X31 -> 11529 | Y32: =IF(R32-X32<=0,"ok","oil change") -> ok | Z32: =C32+K32+S32 -> 0 | AA32: =U32+M32+E32 -> 0 | AB32: =V32+N32+F32 -> 0 | AC32: =IF(Z32>0,AA32/Z32,0) -> 0 | AD32: =ELEC!Q32 -> 0 | AE32: =SUM(AD32/Z32) -> #DIV/0! | AF32: =SUM(AE32/1600) -> #DIV/0! | AG32: =SUM(320*AF32) -> #DIV/0! | AH32: =SUM(AC32-AG32) -> #DIV/0! | AI32: =AD32*AJ32 -> 0 | AJ32: =305/1185 -> 0.25738397 | AK32: =IF(Z32>0,AI32/Z32,0) -> 0
A33: =ELEC!C33 -> 43921 | B33: =B32 -> 8556.55 | C33: =B33-B32 -> 0 | D33: =D32 -> 131971.3 | E33: =SUM(D33-D32) -> 0 | F33: =IF(C33>0,E33/C33,0) -> 0 | H33: =H32 -> 8497 | I33: =IF(B33-H33<=0,"ok","oil change") -> oil change | J33: =J32 -> 10689.42 | K33: =J33-J32 -> 0 | L33: =L32 -> 237071 | M33: =SUM(L33-L32) -> 0 | N33: =IF(K33>0,M33/K33,0) -> 0 | P33: =P32 -> 10873 | Q33: =IF(J33-P33<=0,"ok","oil change") -> ok | R33: =R32 -> 10992.51 | S33: =R33-R32 -> 0 | T33: =T32 -> 201286.1 | U33: =SUM(T33-T32) -> 0 | V33: =IF(S33>0,U33/S33,0) -> 0 | X33: =X32 -> 11529 | Y33: =IF(R33-X33<=0,"ok","oil change") -> ok | Z33: =C33+K33+S33 -> 0 | AA33: =U33+M33+E33 -> 0 | AB33: =V33+N33+F33 -> 0 | AC33: =IF(Z33>0,AA33/Z33,0) -> 0 | AD33: =ELEC!Q33 -> 0 | AE33: =SUM(AD33/Z33) -> #DIV/0! | AF33: =SUM(AE33/1600) -> #DIV/0! | AG33: =SUM(320*AF33) -> #DIV/0! | AH33: =SUM(AC33-AG33) -> #DIV/0!
P34: =+O34/3 -> 0 | U34: =SUM(C35:S35) -> 14.48 | X34: 341 | Z34: =SUM(Z3:Z33) -> 14.48
C35: =SUM(C3:C33) -> 13.55 | K35: =SUM(K3:K33) -> 0.42 | S35: =SUM(S3:S33) -> 0.51

Sheet Sheet1
A1: TOTAL CH RH | B1: TOTAL CH cons KW | C1: TOTAL ELIC KW | D1: TOTAL EDL | E1: TOTAL GEN KW | F1: GEN HR | G1: WATER IN | H1: TOTAL CT | I1: TOTAL WATER | J1: Date
A2: =ELEC!T3+ELEC!X1+ELEC!AB3 -> #VALUE! | B2: =ELEC!AF3 -> 681 | C2: =ELEC!N3 -> 10658 | D2: =C2-E2 -> 6558 | E2: =ELEC!Q3 -> 4100 | F2: =GEN!Z2 -> 6 | G2: =WATER!C5+WATER!H5 -> 160 | H2: =WATER!L5 -> 2 | I2: =WATER!BC5+WATER!BD5+WATER!BE6-Sheet1!G2 -> -170.4 | J2: ='B5'!A4 -> 43890
A3: =ELEC!T4+ELEC!X2+ELEC!AB4 -> 3 | B3: =ELEC!AF4 -> 587 | C3: =ELEC!N4 -> 12173 | D3: =C3-E3 -> 11324 | E3: =ELEC!Q4 -> 849 | F3: =GEN!Z3 -> 5.02 | G3: =WATER!C6+WATER!H6 -> 0 | H3: =WATER!L6 -> 0 | I3: =WATER!BC6+WATER!BD6+WATER!BE7-Sheet1!G3 -> 82.2 | J3: ='B5'!A5 -> 43891
A4: =ELEC!T5+ELEC!X5+ELEC!AB5 -> 4 | B4: =ELEC!AF5 -> 788 | C4: =ELEC!N5 -> 11827.6 | D4: =C4-E4 -> 9961.6 | E4: =ELEC!Q5 -> 1866 | F4: =GEN!Z4 -> 1.98 | G4: =WATER!C7+WATER!H7 -> 454 | H4: =WATER!L7 -> 0 | I4: =WATER!BC7+WATER!BD7+WATER!BE8-Sheet1!G4 -> -364.4 | J4: ='B5'!A6 -> 43892
A5: =ELEC!T6+ELEC!X6+ELEC!AB6 -> 4 | B5: =ELEC!AF6 -> 802 | C5: =ELEC!N6 -> 12688.8 | D5: =C5-E5 -> 10277.8 | E5: =ELEC!Q6 -> 2411 | F5: =GEN!Z5 -> 3.45 | G5: =WATER!C8+WATER!H8 -> 0 | H5: =WATER!L8 -> 0 | I5: =WATER!BC8+WATER!BD8+WATER!BE9-Sheet1!G5 -> 56 | J5: ='B5'!A7 -> 43893
A6: =ELEC!T7+ELEC!X7+ELEC!AB7 -> 0 | B6: =ELEC!AF7 -> 0 | C6: =ELEC!N7 -> 0 | D6: =C6-E6 -> 0 | E6: =ELEC!Q24 -> 0 | F6: =GEN!Z6 -> 4.03 | G6: =WATER!C9+WATER!H9 -> 341 | H6: =WATER!L9 -> 0 | I6: =WATER!BC9+WATER!BD9+WATER!BE10-Sheet1!G6 -> -269 | J6: ='B5'!A8 -> 43894
A7: =ELEC!T8+ELEC!X8+ELEC!AB8 -> 0 | B7: =ELEC!AF8 -> 0 | C7: =ELEC!N8 -> 0 | D7: =C7-E7 -> 0 | E7: =ELEC!Q8 -> 0 | F7: =GEN!Z7 -> 0 | G7: =WATER!C10+WATER!H10 -> 0 | H7: =WATER!L10 -> 0 | I7: =WATER!BC10+WATER!BD10+WATER!BE11-Sheet1!G7 -> 0 | J7: ='B5'!A9 -> 43895
A8: =ELEC!T9+ELEC!X9+ELEC!AB9 -> 0 | B8: =ELEC!AF9 -> 0 | C8: =ELEC!N9 -> 0 | D8: =C8-E8 -> 0 | E8: =ELEC!Q9 -> 0 | F8: =GEN!Z8 -> 0 | G8: =WATER!C11+WATER!H11 -> 0 | H8: =WATER!L11 -> 0 | I8: =WATER!BC11+WATER!BD11+WATER!BE12-Sheet1!G8 -> 0 | J8: ='B5'!A10 -> 43896
A9: =ELEC!T10+ELEC!X10+ELEC!AB10 -> 0 | B9: =ELEC!AF10 -> 0 | C9: =ELEC!N10 -> 0 | D9: =C9-E9 -> 0 | E9: =ELEC!Q10 -> 0 | F9: =GEN!Z9 -> 0 | G9: =WATER!C12+WATER!H12 -> 0 | H9: =WATER!L12 -> 0 | I9: =WATER!BC12+WATER!BD12+WATER!BE13-Sheet1!G9 -> 0 | J9: ='B5'!A11 -> 43897
A10: =ELEC!T11+ELEC!X11+ELEC!AB11 -> 0 | B10: =ELEC!AF11 -> 0 | C10: =ELEC!N11 -> 0 | D10: =C10-E10 -> 0 | E10: =ELEC!Q11 -> 0 | F10: =GEN!Z10 -> 0 | G10: =WATER!C13+WATER!H13 -> 0 | H10: =WATER!L13 -> 0 | I10: =WATER!BC13+WATER!BD13+WATER!BE14-Sheet1!G10 -> 0 | J10: ='B5'!A12 -> 43898
A11: =ELEC!T12+ELEC!X12+ELEC!AB12 -> 0 | B11: =ELEC!AF12 -> 0 | C11: =ELEC!N12 -> 0 | D11: =C11-E11 -> 0 | E11: =ELEC!Q12 -> 0 | F11: =GEN!Z11 -> 0 | G11: =WATER!C14+WATER!H14 -> 0 | H11: =WATER!L14 -> 0 | I11: =WATER!BC14+WATER!BD14+WATER!BE15-Sheet1!G11 -> 0 | J11: ='B5'!A13 -> 43899
A12: =ELEC!T13+ELEC!X13+ELEC!AB13 -> 0 | B12: =ELEC!AF13 -> 0 | C12: =ELEC!N13 -> 0 | D12: =C12-E12 -> 0 | E12: =ELEC!Q13 -> 0 | F12: =GEN!Z12 -> 0 | G12: =WATER!C15+WATER!H15 -> 0 | H12: =WATER!L15 -> 0 | I12: =WATER!BC15+WATER!BD15+WATER!BE16-Sheet1!G12 -> 0 | J12: ='B5'!A14 -> 43900
A13: =ELEC!T14+ELEC!X14+ELEC!AB14 -> 0 | B13: =ELEC!AF14 -> 0 | C13: =ELEC!N14 -> 0 | D13: =C13-E13 -> 0 | E13: =ELEC!Q14 -> 0 | F13: =GEN!Z13 -> 0 | G13: =WATER!C16+WATER!H16 -> 0 | H13: =WATER!L16 -> 0 | I13: =WATER!BC16+WATER!BD16+WATER!BE17-Sheet1!G13 -> 0 | J13: ='B5'!A15 -> 43901
A14: =ELEC!T15+ELEC!X15+ELEC!AB15 -> 0 | B14: =ELEC!AF15 -> 0 | C14: =ELEC!N15 -> 0 | D14: =C14-E14 -> 0 | E14: =ELEC!Q15 -> 0 | F14: =GEN!Z14 -> 0 | G14: =WATER!C17+WATER!H17 -> 0 | H14: =WATER!L17 -> 0 | I14: =WATER!BC17+WATER!BD17+WATER!BE18-Sheet1!G14 -> 0 | J14: ='B5'!A16 -> 43902
A15: =ELEC!T16+ELEC!X16+ELEC!AB16 -> 0 | B15: =ELEC!AF16 -> 0 | C15: =ELEC!N16 -> 0 | D15: =C15-E15 -> 0 | E15: =ELEC!Q16 -> 0 | F15: =GEN!Z15 -> 0 | G15: =WATER!C18+WATER!H18 -> 0 | H15: =WATER!L18 -> 0 | I15: =WATER!BC18+WATER!BD18+WATER!BE19-Sheet1!G15 -> 0 | J15: ='B5'!A17 -> 43903
A16: =ELEC!T17+ELEC!X17+ELEC!AB17 -> 0 | B16: =ELEC!AF17 -> 0 | C16: =ELEC!N17 -> 0 | D16: =C16-E16 -> 0 | E16: =ELEC!Q17 -> 0 | F16: =GEN!Z16 -> 0 | G16: =WATER!C19+WATER!H19 -> 0 | H16: =WATER!L19 -> 0 | I16: =WATER!BC19+WATER!BD19+WATER!BE20-Sheet1!G16 -> 0 | J16: ='B5'!A18 -> 43904
A17: =ELEC!T18+ELEC!X18+ELEC!AB18 -> 0 | B17: =ELEC!AF18 -> 0 | C17: =ELEC!N18 -> 0 | D17: =C17-E17 -> 0 | E17: =ELEC!Q18 -> 0 | F17: =GEN!Z17 -> 0 | G17: =WATER!C20+WATER!H20 -> 0 | H17: =WATER!L20 -> 0 | I17: =WATER!BC20+WATER!BD20+WATER!BE21-Sheet1!G17 -> 0 | J17: ='B5'!A19 -> 43905
A18: =ELEC!T19+ELEC!X19+ELEC!AB19 -> 0 | B18: =ELEC!AF19 -> 0 | C18: =ELEC!N19 -> 0 | D18: =C18-E18 -> 0 | E18: =ELEC!Q19 -> 0 | F18: =GEN!Z18 -> 0 | G18: =WATER!C21+WATER!H21 -> 0 | H18: =WATER!L21 -> 0 | I18: =WATER!BC21+WATER!BD21+WATER!BE22-Sheet1!G18 -> 0 | J18: ='B5'!A20 -> 43906
... A29: =ELEC!T30+ELEC!X30+ELEC!AB30 -> 0 | B29: =ELEC!AF30 -> 0 | C29: =ELEC!N30 -> 0 | D29: =C29-E29 -> 0 | E29: =ELEC!Q30 -> 0 | F29: =GEN!Z29 -> 0 | G29: =WATER!C32+WATER!H32 -> 0 | H29: =WATER!L32 -> 0 | I29: =WATER!BC32+WATER!BD32+WATER!BE33-Sheet1!G29 -> 0 | J29: ='B5'!A31 -> 43917
A30: =ELEC!T31+ELEC!X31+ELEC!#REF! -> #REF! | B30: =ELEC!AF31 -> 0 | C30: =ELEC!N31 -> 0 | D30: =C30-E30 -> 0 | E30: =ELEC!Q31 -> 0 | F30: =GEN!Z30 -> 0 | G30: =WATER!C33+WATER!H33 -> 0 | H30: =WATER!L33 -> 0 | I30: =WATER!BC33+WATER!BD33+WATER!BE34-Sheet1!G30 -> 0 | J30: ='B5'!A32 -> 43918
A31: =ELEC!T32+ELEC!X32+ELEC!AB31 -> 0 | B31: =ELEC!AF32 -> 0 | C31: =ELEC!N32 -> 0 | D31: =C31-E31 -> 0 | E31: =ELEC!Q32 -> 0 | F31: =GEN!Z31 -> 0 | G31: =WATER!C34+WATER!H34 -> 0 | H31: =WATER!L34 -> 0 | I31: =WATER!BC34+WATER!BD34+WATER!BE35-Sheet1!G31 -> 0 | J31: ='B5'!A33 -> 43919
A32: =ELEC!#REF!+ELEC!#REF!+ELEC!#REF! -> #REF! | B32: =ELEC!#REF! -> #REF! | C32: =ELEC!#REF! -> #REF! | D32: =C32-E32 -> #REF! | E32: =ELEC!#REF! -> #REF! | F32: =GEN!#REF! -> #REF! | G32: =WATER!#REF!+WATER!#REF! -> #REF! | H32: =WATER!#REF! -> #REF! | I32: =WATER!#REF!+WATER!#REF!+WATER!BE37-Sheet1!G32 -> #REF!

Sheet Report
B1: Boiler Fuel | C1: Steam Fuel | D1: GEN FUEL | E1: FUEL TOTAL | F1: CT/mᶾ | G1: Water Consumption | H1: Chiller KW | I1: GEN KW | J1: EDL KW | K1: occ | L1: covers | M1: temp. C⁰ | N1: RH %
B3: ='B5'!V3 -> 0 | C3: ='B5'!AH3 -> 0 | E3: =B3+C3+D3 -> 0
A4: 42704 | B4: 810 | C4: -606.1 | D4: 1420.5021 | E4: 1624.4021 | F4: 106 | G4: -58.4 | H4: 6284 | I4: 2399 | J4: 23932 | K4: 0 | L4: 0 | M4: 0 | N4: 0
A5: ='B5'!A5 -> 43891 | B5: ='B5'!V5 -> 580 | C5: ='B5'!AH5 -> 0 | D5: =GEN!AI3 -> 1055.2743 | E5: =B5+C5+D5 -> 1635.2743 | F5: =WATER!L5 -> 2 | G5: =WATER!BG5 -> 68.8 | H5: =ELEC!AF3 -> 681 | I5: =ELEC!Q3 -> 4100 | J5: =ELEC!R3 -> 6558
A6: ='B5'!A6 -> 43892 | B6: ='B5'!V6 -> 567 | C6: ='B5'!AH6 -> 0 | D6: =GEN!AI4 -> 218.51899 | E6: =B6+C6+D6 -> 785.51899 | F6: =WATER!L6 -> 0 | G6: =WATER!BG6 -> -53.1 | H6: =ELEC!AF4 -> 587 | I6: =ELEC!Q4 -> 849 | J6: =ELEC!R4 -> 11324
A7: ='B5'!A7 -> 43893 | B7: ='B5'!V7 -> 553 | C7: ='B5'!AH7 -> 508.4 | D7: =GEN!AI5 -> 480.27848 | E7: =B7+C7+D7 -> 1541.6785 | F7: =WATER!L7 -> 0 | G7: =WATER!BG7 -> 103.8 | H7: =ELEC!AF5 -> 788 | I7: =ELEC!Q5 -> 1866 | J7: =ELEC!R5 -> 9961.6
A8: ='B5'!A8 -> 43894 | B8: ='B5'!V8 -> 240 | C8: ='B5'!AH8 -> 36.7 | D8: =GEN!AI6 -> 620.55274 | E8: =B8+C8+D8 -> 897.25274 | F8: =WATER!L8 -> 0 | G8: =WATER!BG8 -> -30.4 | H8: =ELEC!AF6 -> 802 | I8: =ELEC!Q6 -> 2411 | J8: =ELEC!R6 -> 10277.8
A9: ='B5'!A9 -> 43895 | B9: ='B5'!V9 -> 0 | C9: ='B5'!AH9 -> 0 | D9: =GEN!AI7 -> 0 | E9: =B9+C9+D9 -> 0 | F9: =WATER!L9 -> 0 | G9: =WATER!BG9 -> 97.2 | H9: =ELEC!AF7 -> 0 | I9: =ELEC!Q7 -> 0 | J9: =ELEC!R7 -> 0
A10: ='B5'!A10 -> 43896 | B10: ='B5'!V10 -> 0 | C10: ='B5'!AH10 -> 0 | D10: =GEN!AI8 -> 0 | E10: =B10+C10+D10 -> 0 | F10: =WATER!L10 -> 0 | G10: =WATER!BG10 -> 0 | H10: =ELEC!AF8 -> 0 | I10: =ELEC!Q8 -> 0 | J10: =ELEC!R8 -> 0
A11: ='B5'!A11 -> 43897 | B11: ='B5'!V11 -> 0 | C11: ='B5'!AH11 -> 0 | D11: =GEN!AI9 -> 0 | E11: =B11+C11+D11 -> 0 | F11: =WATER!L11 -> 0 | G11: =WATER!BG11 -> 0 | H11: =ELEC!AF9 -> 0 | I11: =ELEC!Q9 -> 0 | J11: =ELEC!R9 -> 0
A12: ='B5'!A12 -> 43898 | B12: ='B5'!V12 -> 0 | C12: ='B5'!AH12 -> 0 | D12: =GEN!AI10 -> 0 | E12: =B12+C12+D12 -> 0 | F12: =WATER!L12 -> 0 | G12: =WATER!BG12 -> 0 | H12: =ELEC!AF10 -> 0 | I12: =ELEC!Q10 -> 0 | J12: =ELEC!R10 -> 0
A13: ='B5'!A13 -> 43899 | B13: ='B5'!V13 -> 0 | C13: ='B5'!AH13 -> 0 | D13: =GEN!AI11 -> 0 | E13: =B13+C13+D13 -> 0 | F13: =WATER!L13 -> 0 | G13: =WATER!BG13 -> 0 | H13: =ELEC!AF11 -> 0 | I13: =ELEC!Q11 -> 0 | J13: =ELEC!R11 -> 0
A14: ='B5'!A14 -> 43900 | B14: ='B5'!V14 -> 0 | C14: ='B5'!AH14 -> 0 | D14: =GEN!AI12 -> 0 | E14: =B14+C14+D14 -> 0 | F14: =WATER!L14 -> 0 | G14: =WATER!BG14 -> 0 | H14: =ELEC!AF12 -> 0 | I14: =ELEC!Q12 -> 0 | J14: =ELEC!R12 -> 0
A15: ='B5'!A15 -> 43901 | B15: ='B5'!V15 -> 0 | C15: ='B5'!AH15 -> 0 | D15: =GEN!AI13 -> 0 | E15: =B15+C15+D15 -> 0 | F15: =WATER!L15 -> 0 | G15: =WATER!BG15 -> 0 | H15: =ELEC!AF13 -> 0 | I15: =ELEC!Q13 -> 0 | J15: =ELEC!R13 -> 0
A16: ='B5'!A16 -> 43902 | B16: ='B5'!V16 -> 0 | C16: ='B5'!AH16 -> 0 | D16: =GEN!AI14 -> 0 | E16: =B16+C16+D16 -> 0 | F16: =WATER!L16 -> 0 | G16: =WATER!BG16 -> 0 | H16: =ELEC!AF14 -> 0 | I16: =ELEC!Q14 -> 0 | J16: =ELEC!R14 -> 0
... A33: ='B5'!A33 -> 43919 | B33: ='B5'!V33 -> 0 | C33: ='B5'!AH33 -> 0 | D33: =GEN!AI31 -> 0 | E33: =B33+C33+D33 -> 0 | F33: =WATER!L33 -> 0 | G33: =WATER!BG33 -> 0 | H33: =ELEC!AF31 -> 0 | I33: =ELEC!Q31 -> 0 | J33: =ELEC!R31 -> 0
A34: ='B5'!A34 -> 43920 | B34: ='B5'!V34 -> 0 | C34: ='B5'!AH34 -> 0 | D34: =GEN!AI32 -> 0 | E34: =B34+C34+D34 -> 0 | F34: =WATER!L34 -> 0 | G34: =WATER!BG34 -> 0 | H34: =ELEC!#REF! -> #REF! | I34: =ELEC!#REF! -> #REF! | J34: =ELEC!#REF! -> #REF!

Sheet Sheet5
T3: Outdoor conditions
C4: Date | D4: Total Boiler running H | E4: AVE CONSUM | F4: Total Steam running H | G4: AVE CONSUM | H4: Total GEN running H | I4: AVE CONSUM | J4: Actual Diesel Consumption | K4: Actual Gas Consumption | L4: Total ELEC power | M4: Gen ELEC power | N4: EDL ELEC power | O4: Chillers running H | P4: Total Water delivery | Q4: Total water consumption | R4: Total water in tanks | S4: Occupancy | T4: AVE TEPM | U4: AVE Humidity
C5: 42429 | D5: ='B5'!AL4 -> 9 | E5: =D5*90 -> 810 | F5: ='B5'!AM4 -> 1 | G5: =F5*107 -> 107 | H5: =GEN!Z3 -> 5.02
C6: 42430 | D6: ='B5'!AL5 -> 8 | E6: =D6*90 -> 720 | F6: ='B5'!AM5 -> 0 | G6: =F6*107 -> 0
C7: 42431 | D7: ='B5'!AL6 -> 7 | E7: =D7*90 -> 630 | F7: ='B5'!AM6 -> 0 | G7: =F7*107 -> 0
C8: 42432 | D8: ='B5'!AL7 -> 7 | E8: =D8*90 -> 630 | F8: ='B5'!AM7 -> 8 | G8: =F8*107 -> 856
C9: 42433 | D9: ='B5'!AL8 -> 4 | E9: =D9*90 -> 360 | F9: ='B5'!AM8 -> 1 | G9: =F9*107 -> 107
C10: 42434 | D10: ='B5'!AL9 -> 0 | E10: =D10*90 -> 0 | F10: ='B5'!AM9 -> 0 | G10: =F10*107 -> 0
C11: 42435 | D11: ='B5'!AL10 -> 0 | E11: =D11*90 -> 0 | F11: ='B5'!AM10 -> 0 | G11: =F11*107 -> 0
C12: 42436 | D12: ='B5'!AL11 -> 0 | E12: =D12*90 -> 0 | F12: ='B5'!AM11 -> 0 | G12: =F12*107 -> 0
C13: 42437 | D13: ='B5'!AL12 -> 0 | E13: =D13*90 -> 0 | F13: ='B5'!AM12 -> 0 | G13: =F13*107 -> 0
C14: 42438 | D14: ='B5'!AL13 -> 0 | E14: =D14*90 -> 0 | F14: ='B5'!AM13 -> 0 | G14: =F14*107 -> 0
C15: 42439 | D15: ='B5'!AL14 -> 0 | E15: =D15*90 -> 0 | F15: ='B5'!AM14 -> 0 | G15: =F15*107 -> 0
C16: 42440 | D16: ='B5'!AL15 -> 0 | E16: =D16*90 -> 0 | F16: ='B5'!AM15 -> 0 | G16: =F16*107 -> 0
C17: 42441 | D17: ='B5'!AL16 -> 0 | E17: =D17*90 -> 0 | F17: ='B5'!AM16 -> 0 | G17: =F17*107 -> 0
... C35: 42459 | D35: ='B5'!AL34 -> 0 | E35: =D35*90 -> 0 | F35: ='B5'!AM34 -> 0 | G35: =F35*107 -> 0
C36: 42460 | D36: ='B5'!#REF! -> #REF! | E36: =D36*90 -> #REF! | F36: ='B5'!#REF! -> #REF! | G36: =F36*107 -> #REF!
C37: 42461 | D37: ='B5'!#REF! -> #REF! | E37: =D37*90 -> #REF! | F37: ='B5'!#REF! -> #REF! | G37: =F37*107 -> #REF!

Sheet EDl log
A1: Date | B1: EDL | C1: Conso EDL KW | F1: Peak | G1: 320 | H1: Day | I1: 112 | J1: Night | K1: 80
L2: P | M2: D | N2: N | O2: fee | P2: T EDL | Q2: Gen | R2: Elc C
A3: =ELEC!C2 -> 43890 | B3: ='[1]EDl log'!B32 -> 49582042 | C3: ='[1]EDl log'!C32 -> 5344 | D3: ='[1]EDl log'!D32 -> 5342 | E3: ='[1]EDl log'!E32 -> 49582040 | F3: ='[1]EDl log'!F32 -> 7969132 | G3: ='[1]EDl log'!G32 -> 830 | H3: ='[1]EDl log'!H32 -> 24415638 | I3: ='[1]EDl log'!I32 -> 2199 | ... T3: ='[1]EDl log'!T32 -> 0.11876476 | Z3: VAT | AA3: 0.1
A4: =ELEC!C3 -> 43891 | B4: 49586412 | C4: =SUM(B4-B3) -> 4370 | D4: =SUM(G4+I4+K4) -> 4372 | E4: =B3+D4 -> 49586414 | F4: 7970021 | G4: =F4-F3 -> 889 | H4: 24417607 | I4: =H4-H3 -> 1969 | J4: 17198786 | K4: =J4-J3 -> 1514 | L4: =SUM(G4*$Y$28)/1507.5 -> 188.70978 | M4: =SUM(I4*$Y$27)/1507.5 -> 146.28723 | N4: =SUM(K4*$Y$26)/1507.5 -> 80.344942 | O4: =($AC$31/$A$38)/1507.5 -> 19.974586 | P4: =SUM(L4:O4) -> 435.31654 | Q4: =SUM(-tanks!AX6*tanks!$AU$37) -> 76.68129 | R4: =SUM(P4:Q4) -> 511.99783 | S4: =SUM(ELEC!N3) -> 10658 | T4: =IF(S4>0,R4/S4,0) -> 0.048038828 | V4: ='[3]EDl log'!V21 -> EDL | W4: 43881 | Z4: Subscription
A5: =ELEC!C4 -> 43892 | B5: 49591340 | C5: =SUM(B5-B4) -> 4928 | D5: =SUM(G5+I5+K5) -> 4927 | E5: =B4+D5 -> 49591339 | F5: 7971060 | G5: =F5-F4 -> 1039 | H5: 24419808 | I5: =H5-H4 -> 2201 | J5: 17200473 | K5: =J5-J4 -> 1687 | L5: =SUM(G5*$Y$28)/1507.5 -> 220.55058 | M5: =SUM(I5*$Y$27)/1507.5 -> 163.52371 | N5: =SUM(K5*$Y$26)/1507.5 -> 89.525705 | O5: =($AC$31/$A$38)/1507.5 -> 19.974586 | P5: =SUM(L5:O5) -> 493.57459 | Q5: =SUM(-tanks!AX7*tanks!$AU$37) -> 92.43871 | R5: =SUM(P5:Q5) -> 586.0133 | S5: =SUM(ELEC!N4) -> 12173 | T5: =IF(S5>0,R5/S5,0) -> 0.048140417 | Z5: KVA | AA5: ='[4]EDl log'!AA5 -> 5000
A6: =ELEC!C5 -> 43893 | B6: 49596500 | C6: =SUM(B6-B5) -> 5160 | D6: =SUM(G6+I6+K6) -> 5160 | E6: =B5+D6 -> 49596500 | F6: 7972051 | G6: =F6-F5 -> 991 | H6: 24422516 | I6: =H6-H5 -> 2708 | J6: 17201934 | K6: =J6-J5 -> 1461 | L6: =SUM(G6*$Y$28)/1507.5 -> 210.36153 | M6: =SUM(I6*$Y$27)/1507.5 -> 201.19138 | N6: =SUM(K6*$Y$26)/1507.5 -> 77.532338 | O6: =($AC$31/$A$38)/1507.5 -> 19.974586 | P6: =SUM(L6:O6) -> 509.05983 | Q6: =SUM(-tanks!AX8*tanks!$AU$37) -> 20.730968 | R6: =SUM(P6:Q6) -> 529.79079 | S6: =SUM(ELEC!N5) -> 11827.6 | T6: =IF(S6>0,R6/S6,0) -> 0.044792755
A7: =ELEC!C6 -> 43894 | B7: 49601831 | C7: =SUM(B7-B6) -> 5331 | D7: =SUM(G7+I7+K7) -> 5331 | E7: =B6+D7 -> 49601831 | F7: 7972695 | G7: =F7-F6 -> 644 | H7: 24425226 | I7: =H7-H6 -> 2710 | J7: 17203911 | K7: =J7-J6 -> 1977 | L7: =SUM(G7*$Y$28)/1507.5 -> 136.70315 | M7: =SUM(I7*$Y$27)/1507.5 -> 201.33997 | N7: =SUM(K7*$Y$26)/1507.5 -> 104.91542 | O7: =($AC$31/$A$38)/1507.5 -> 19.974586 | P7: =SUM(L7:O7) -> 462.93313 | Q7: =SUM(-tanks!AX9*tanks!$AU$37) -> 174.30387 | R7: =SUM(P7:Q7) -> 637.237 | S7: =SUM(ELEC!N6) -> 12688.8 | T7: =IF(S7>0,R7/S7,0) -> 0.05022043 | V7: Electricity consumption | X7: Price LL
A8: =ELEC!C7 -> 43895 | B8: =B7 -> 49601831 | C8: =SUM(B8-B7) -> 0 | D8: =SUM(G8+I8+K8) -> 0 | E8: =B7+D8 -> 49601831 | F8: =F7 -> 7972695 | G8: =F8-F7 -> 0 | H8: =H7 -> 24425226 | I8: =H8-H7 -> 0 | J8: =J7 -> 17203911 | K8: =J8-J7 -> 0 | L8: =SUM(G8*$Y$28)/1507.5 -> 0 | M8: =SUM(I8*$Y$27)/1507.5 -> 0 | N8: =SUM(K8*$Y$26)/1507.5 -> 0 | O8: =($AC$31/$A$38)/1507.5 -> 19.974586 | P8: =SUM(L8:O8) -> 19.974586 | Q8: =SUM(-tanks!AX10*tanks!$AU$37) -> 0 | R8: =SUM(P8:Q8) -> 19.974586 | S8: =SUM(ELEC!N7) -> 0 | T8: =IF(S8>0,R8/S8,0) -> 0 | V8: Index in | W8: Index Out | Y8: Kwh Cost | Z8: K | AA8: Kwh | AB8: Total cost LL | AC8: Fees
A9: =ELEC!C8 -> 43896 | B9: =B8 -> 49601831 | C9: =SUM(B9-B8) -> 0 | D9: =SUM(G9+I9+K9) -> 0 | E9: =B8+D9 -> 49601831 | F9: =F8 -> 7972695 | G9: =F9-F8 -> 0 | H9: =H8 -> 24425226 | I9: =H9-H8 -> 0 | J9: =J8 -> 17203911 | K9: =J9-J8 -> 0 | L9: =SUM(G9*$Y$28)/1507.5 -> 0 | M9: =SUM(I9*$Y$27)/1507.5 -> 0 | N9: =SUM(K9*$Y$26)/1507.5 -> 0 | O9: =($AC$31/$A$38)/1507.5 -> 19.974586 | P9: =SUM(L9:O9) -> 19.974586 | Q9: =SUM(-tanks!AX11*tanks!$AU$37) -> 0 | R9: =SUM(P9:Q9) -> 19.974586 | S9: =SUM(ELEC!N8) -> 0 | T9: =IF(S9>0,R9/S9,0) -> 0 | V9: ='[1]EDl log'!V26 -> 17141733 | W9: ='[1]EDl log'!W26 -> 17197272 | X9: ='[5]EDl log'!X26 -> Night | Y9: ='[1]EDl log'!Y26 -> 80 | Z9: ='[1]EDl log'!Z26 -> 1 | AA9: ='[1]EDl log'!AA26 -> 55539 | AB9: ='[1]EDl log'!AB26 -> 4443120 | AC9: ='[1]EDl log'!AC26 -> 1033333 | AD9: ='[1]EDl log'!AD26 -> 0.35885325
A10: =ELEC!C9 -> 43897 | B10: =B9 -> 49601831 | C10: =SUM(B10-B9) -> 0 | D10: =SUM(G10+I10+K10) -> 0 | E10: =B9+D10 -> 49601831 | F10: =F9 -> 7972695 | G10: =F10-F9 -> 0 | H10: =H9 -> 24425226 | I10: =H10-H9 -> 0 | J10: =J9 -> 17203911 | K10: =J10-J9 -> 0 | L10: =SUM(G10*$Y$28)/1507.5 -> 0 | M10: =SUM(I10*$Y$27)/1507.5 -> 0 | N10: =SUM(K10*$Y$26)/1507.5 -> 0 | O10: =($AC$31/$A$38)/1507.5 -> 19.974586 | P10: =SUM(L10:O10) -> 19.974586 | Q10: =SUM(-tanks!AX12*tanks!$AU$37) -> 0 | R10: =SUM(P10:Q10) -> 19.974586 | S10: =SUM(ELEC!N9) -> 0 | T10: =IF(S10>0,R10/S10,0) -> 0 | V10: ='[1]EDl log'!V27 -> 24340859 | W10: ='[1]EDl log'!W27 -> 24415638 | X10: ='[5]EDl log'!X27 -> day | Y10: ='[1]EDl log'!Y27 -> 112 | Z10: ='[1]EDl log'!Z27 -> 1 | AA10: ='[1]EDl log'!AA27 -> 74779 | AB10: ='[1]EDl log'!AB27 -> 8375248 | AC10: ='[1]EDl log'!AC27 -> 6200000 | AD10: ='[1]EDl log'!AD27 -> 0.48316836
A11: =ELEC!C10 -> 43898 | B11: =B10 -> 49601831 | C11: =SUM(B11-B10) -> 0 | D11: =SUM(G11+I11+K11) -> 0 | E11: =B10+D11 -> 49601831 | F11: =F10 -> 7972695 | G11: =F11-F10 -> 0 | H11: =H10 -> 24425226 | I11: =H11-H10 -> 0 | J11: =J10 -> 17203911 | K11: =J11-J10 -> 0 | L11: =SUM(G11*$Y$28)/1507.5 -> 0 | M11: =SUM(I11*$Y$27)/1507.5 -> 0 | N11: =SUM(K11*$Y$26)/1507.5 -> 0 | O11: =($AC$31/$A$38)/1507.5 -> 19.974586 | P11: =SUM(L11:O11) -> 19.974586 | Q11: =SUM(-tanks!AX13*tanks!$AU$37) -> 0 | R11: =SUM(P11:Q11) -> 19.974586 | S11: =SUM(ELEC!N10) -> 0 | T11: =IF(S11>0,R11/S11,0) -> 0 | V11: ='[1]EDl log'!V28 -> 7944681 | W11: ='[1]EDl log'!W28 -> 7969132 | X11: ='[5]EDl log'!X28 -> Peak | Y11: ='[1]EDl log'!Y28 -> 320 | Z11: ='[1]EDl log'!Z28 -> 1 | AA11: ='[1]EDl log'!AA28 -> 24451 | AB11: ='[1]EDl log'!AB28 -> 7824320 | AC11: ='[1]EDl log'!AC28 -> 1000 | AD11: ='[1]EDl log'!AD28 -> 0.15798485
A12: =ELEC!C11 -> 43899 | B12: =B11 -> 49601831 | C12: =SUM(B12-B11) -> 0 | D12: =SUM(G12+I12+K12) -> 0 | E12: =B11+D12 -> 49601831 | F12: =F11 -> 7972695 | G12: =F12-F11 -> 0 | H12: =H11 -> 24425226 | I12: =H12-H11 -> 0 | J12: =J11 -> 17203911 | K12: =J12-J11 -> 0 | L12: =SUM(G12*$Y$28)/1507.5 -> 0 | M12: =SUM(I12*$Y$27)/1507.5 -> 0 | N12: =SUM(K12*$Y$26)/1507.5 -> 0 | O12: =($AC$31/$A$38)/1507.5 -> 19.974586 | P12: =SUM(L12:O12) -> 19.974586 | Q12: =SUM(-tanks!AX14*tanks!$AU$37) -> 0 | R12: =SUM(P12:Q12) -> 19.974586 | S12: =SUM(ELEC!N11) -> 0 | T12: =IF(S12>0,R12/S12,0) -> 0 | V12: ='[6]EDl log'!V29 -> 0 | W12: ='[6]EDl log'!W29 -> 0 | Y12: ='[7]EDl log'!Y29 -> 0 | AA12: ='[1]EDl log'!AA29 -> 154769 | AB12: ='[5]EDl log'!AB29 -> #REF! | AC12: ='[6]EDl log'!AC29 -> 0
A13: =ELEC!C12 -> 43900 | B13: =B12 -> 49601831 | C13: =SUM(B13-B12) -> 0 | D13: =SUM(G13+I13+K13) -> 0 | E13: =B12+D13 -> 49601831 | F13: =F12 -> 7972695 | G13: =F13-F12 -> 0 | H13: =H12 -> 24425226 | I13: =H13-H12 -> 0 | J13: =J12 -> 17203911 | K13: =J13-J12 -> 0 | L13: =SUM(G13*$Y$28)/1507.5 -> 0 | M13: =SUM(I13*$Y$27)/1507.5 -> 0 | N13: =SUM(K13*$Y$26)/1507.5 -> 0 | O13: =($AC$31/$A$38)/1507.5 -> 19.974586 | P13: =SUM(L13:O13) -> 19.974586 | Q13: =SUM(-tanks!AX15*tanks!$AU$37) -> 0 | R13: =SUM(P13:Q13) -> 19.974586 | S13: =SUM(ELEC!N12) -> 0 | T13: =IF(S13>0,R13/S13,0) -> 0 | V13: ='[5]EDl log'!V30 -> Occ % | W13: ='[1]EDl log'!W30 -> 0.20819655 | X13: ='[8]EDl log'!X30 -> 0 | Y13: ='[8]EDl log'!Y30 -> Per G | AB13: ='[1]EDl log'!AB30 -> 20642688 | AC13: ='[1]EDl log'!AC30 -> 7234333
A14: =ELEC!C13 -> 43901 | B14: =B13 -> 49601831 | C14: =SUM(B14-B13) -> 0 | D14: =SUM(G14+I14+K14) -> 0 | E14: =B13+D14 -> 49601831 | F14: =F13 -> 7972695 | G14: =F14-F13 -> 0 | H14: =H13 -> 24425226 | I14: =H14-H13 -> 0 | J14: =J13 -> 17203911 | K14: =J14-J13 -> 0 | L14: =SUM(G14*$Y$28)/1507.5 -> 0 | M14: =SUM(I14*$Y$27)/1507.5 -> 0 | N14: =SUM(K14*$Y$26)/1507.5 -> 0 | O14: =($AC$31/$A$38)/1507.5 -> 19.974586 | P14: =SUM(L14:O14) -> 19.974586 | Q14: =SUM(-tanks!AX16*tanks!$AU$37) -> 0 | R14: =SUM(P14:Q14) -> 19.974586 | S14: =SUM(ELEC!N13) -> 0 | T14: =IF(S14>0,R14/S14,0) -> 0 | V14: ='[5]EDl log'!V31 -> Gen RH | W14: ='[1]EDl log'!W31 -> 115.42 | X14: ='[1]EDl log'!X31 -> 3.98 | Y14: ='[1]EDl log'!Y31 -> 1.99 | AB14: ='[1]EDl log'!AB31 -> 27877021 | AC14: ='[1]EDl log'!AC31 -> 7234333
A15: =ELEC!C14 -> 43902 | B15: =B14 -> 49601831 | C15: =SUM(B15-B14) -> 0 | D15: =SUM(G15+I15+K15) -> 0 | E15: =B14+D15 -> 49601831 | F15: =F14 -> 7972695 | G15: =F15-F14 -> 0 | H15: =H14 -> 24425226 | I15: =H15-H14 -> 0 | J15: =J14 -> 17203911 | K15: =J15-J14 -> 0 | L15: =SUM(G15*$Y$28)/1507.5 -> 0 | M15: =SUM(I15*$Y$27)/1507.5 -> 0 | N15: =SUM(K15*$Y$26)/1507.5 -> 0 | O15: =($AC$31/$A$38)/1507.5 -> 19.974586 | P15: =SUM(L15:O15) -> 19.974586 | Q15: =SUM(-tanks!AX17*tanks!$AU$37) -> 0 | R15: =SUM(P15:Q15) -> 19.974586 | S15: =SUM(ELEC!N14) -> 0 | T15: =IF(S15>0,R15/S15,0) -> 0 | V15: ='[5]EDl log'!V32 -> H Deg | W15: ='[1]EDl log'!W32 -> -549 | X15: ='[7]EDl log'!X32 -> 0 | Y15: ='[7]EDl log'!Y32 -> 0 | AB15: ='[6]EDl log'!AB32 -> 0 | AC15: ='[5]EDl log'!AC32 -> #REF!
A16: =ELEC!C15 -> 43903 | B16: =B15 -> 49601831 | C16: =SUM(B16-B15) -> 0 | D16: =SUM(G16+I16+K16) -> 0 | E16: =B15+D16 -> 49601831 | F16: =F15 -> 7972695 | G16: =F16-F15 -> 0 | H16: =H15 -> 24425226 | I16: =H16-H15 -> 0 | J16: =J15 -> 17203911 | K16: =J16-J15 -> 0 | L16: =SUM(G16*$Y$28)/1507.5 -> 0 | M16: =SUM(I16*$Y$27)/1507.5 -> 0 | N16: =SUM(K16*$Y$26)/1507.5 -> 0 | O16: =($AC$31/$A$38)/1507.5 -> 19.974586 | P16: =SUM(L16:O16) -> 19.974586 | Q16: =SUM(-tanks!AX18*tanks!$AU$37) -> 0 | R16: =SUM(P16:Q16) -> 19.974586 | S16: =SUM(ELEC!N15) -> 0 | T16: =IF(S16>0,R16/S16,0) -> 0 | V16: ='[5]EDl log'!V33 -> C Deg | W16: ='[1]EDl log'!W33 -> 2.3 | X16: ='[7]EDl log'!X33 -> 0 | Y16: ='[7]EDl log'!Y33 -> 0 | AB16: ='[6]EDl log'!AB33 -> 0 | AC16: ='[6]EDl log'!AC33 -> 0
