Workbook

Sheet Total
A1: Site Name | B1: Day | C1: Month | D1: Year | E1: Total Electricity Kwh | F1: Electricity Tariff ($/Kwh) | G1: LPG (Kg) | H1: LPG $/Kg | I1: Water Utility Supply (m3) m3 | J1: Water Utility Supply (m3) $/m3 | K1: Room Nights | L1: Utilities day cost dh
A2: Serengeti | B2: 1 | C2: 4 | D2: 2020 | E2: ='UTILITY REPORT 1'!F3 -> 2051 | F2: =('UTILITY REPORT 1'!E3*'UTILITY REPORT 1'!D3)/'UTILITY REPORT 1'!F3 -> 0.41490005 | G2: =IF('Utility summery'!M6<0,"0",'Utility summery'!M6) -> 61.6 | H2: 0 | I2: =IF('UTILITY REPORT 1'!G3<0,"0",'UTILITY REPORT 1'!G3) -> 38 | J2: 0 | K2: ='UTILITY REPORT 1'!C3 -> 0 | L2: =E2*F2+G2*H2+#REF!*#REF!+I2*J2 -> #REF!
A3: Serengeti | B3: =B2+1 -> 2 | C3: 4 | D3: 2020 | E3: ='UTILITY REPORT 1'!F4 -> 2088 | F3: =('UTILITY REPORT 1'!E4*'UTILITY REPORT 1'!D4)/'UTILITY REPORT 1'!F4 -> 0.41487069 | G3: =IF('Utility summery'!M7<0,"0",'Utility summery'!M7) -> 66 | H3: 0 | I3: =IF('UTILITY REPORT 1'!G4<0,"0",'UTILITY REPORT 1'!G4) -> 52 | J3: 0 | K3: ='UTILITY REPORT 1'!C4 -> 0 | L3: =E3*F3+G3*H3+#REF!*#REF!+I3*J3 -> #REF!
A4: Serengeti | B4: =B3+1 -> 3 | C4: 4 | D4: 2020 | E4: ='UTILITY REPORT 1'!F5 -> 1898 | F4: =('UTILITY REPORT 1'!E5*'UTILITY REPORT 1'!D5)/'UTILITY REPORT 1'!F5 -> 0.43884089 | G4: =IF('Utility summery'!M8<0,"0",'Utility summery'!M8) -> 37.532 | H4: 0 | I4: =IF('UTILITY REPORT 1'!G5<0,"0",'UTILITY REPORT 1'!G5) -> 26 | J4: 0 | K4: ='UTILITY REPORT 1'!C5 -> 0 | L4: =E4*F4+G4*H4+#REF!*#REF!+I4*J4 -> #REF!
A5: Serengeti | B5: =B4+1 -> 4 | C5: 4 | D5: 2020 | E5: ='UTILITY REPORT 1'!F6 -> 1815 | F5: =('UTILITY REPORT 1'!E6*'UTILITY REPORT 1'!D6)/'UTILITY REPORT 1'!F6 -> 0.43501377 | G5: =IF('Utility summery'!M9<0,"0",'Utility summery'!M9) -> 31.46 | H5: 0 | I5: =IF('UTILITY REPORT 1'!G6<0,"0",'UTILITY REPORT 1'!G6) -> 34 | J5: 0 | K5: ='UTILITY REPORT 1'!C6 -> 0 | L5: =E5*F5+G5*H5+#REF!*#REF!+I5*J5 -> #REF!
A6: Serengeti | B6: =B5+1 -> 5 | C6: 4 | D6: 2020 | E6: ='UTILITY REPORT 1'!F7 -> 1841 | F6: =('UTILITY REPORT 1'!E7*'UTILITY REPORT 1'!D7)/'UTILITY REPORT 1'!F7 -> 0.4417925 | G6: =IF('Utility summery'!M10<0,"0",'Utility summery'!M10) -> 27.808 | H6: 0 | I6: =IF('UTILITY REPORT 1'!G7<0,"0",'UTILITY REPORT 1'!G7) -> 42 | J6: 0 | K6: ='UTILITY REPORT 1'!C7 -> 0 | L6: =E6*F6+G6*H6+#REF!*#REF!+I6*J6 -> #REF!
A7: Serengeti | B7: =B6+1 -> 6 | C7: 4 | D7: 2020 | E7: ='UTILITY REPORT 1'!F8 -> 1789 | F7: =('UTILITY REPORT 1'!E8*'UTILITY REPORT 1'!D8)/'UTILITY REPORT 1'!F8 -> 0.42343767 | G7: =IF('Utility summery'!M11<0,"0",'Utility summery'!M11) -> 14.608 | H7: 0 | I7: =IF('UTILITY REPORT 1'!G8<0,"0",'UTILITY REPORT 1'!G8) -> 41 | J7: 0 | K7: ='UTILITY REPORT 1'!C8 -> 0 | L7: =E7*F7+G7*H7+#REF!*#REF!+I7*J7 -> #REF!
A8: Serengeti | B8: =B7+1 -> 7 | C8: 4 | D8: 2020 | E8: ='UTILITY REPORT 1'!F9 -> 1867 | F8: =('UTILITY REPORT 1'!E9*'UTILITY REPORT 1'!D9)/'UTILITY REPORT 1'!F9 -> 0.41968399 | G8: =IF('Utility summery'!M12<0,"0",'Utility summery'!M12) -> 25.212 | H8: 0 | I8: =IF('UTILITY REPORT 1'!G9<0,"0",'UTILITY REPORT 1'!G9) -> 47 | J8: 0 | K8: ='UTILITY REPORT 1'!C9 -> 0 | L8: =E8*F8+G8*H8+#REF!*#REF!+I8*J8 -> #REF!
A9: Serengeti | B9: =B8+1 -> 8 | C9: 4 | D9: 2020 | E9: ='UTILITY REPORT 1'!F10 -> 1940 | F9: =('UTILITY REPORT 1'!E10*'UTILITY REPORT 1'!D10)/'UTILITY REPORT 1'!F10 -> 0.42848969 | G9: =IF('Utility summery'!M13<0,"0",'Utility summery'!M13) -> 36.3 | H9: 0 | I9: =IF('UTILITY REPORT 1'!G10<0,"0",'UTILITY REPORT 1'!G10) -> 36 | J9: 0 | K9: ='UTILITY REPORT 1'!C10 -> 0 | L9: =E9*F9+G9*H9+#REF!*#REF!+I9*J9 -> #REF!
A10: Serengeti | B10: =B9+1 -> 9 | C10: 4 | D10: 2020 | E10: ='UTILITY REPORT 1'!F11 -> 1882 | F10: =('UTILITY REPORT 1'!E11*'UTILITY REPORT 1'!D11)/'UTILITY REPORT 1'!F11 -> 0.42843783 | G10: =IF('Utility summery'!M14<0,"0",'Utility summery'!M14) -> 25.916 | H10: 0 | I10: =IF('UTILITY REPORT 1'!G11<0,"0",'UTILITY REPORT 1'!G11) -> 33 | J10: 0 | K10: ='UTILITY REPORT 1'!C11 -> 0 | L10: =E10*F10+G10*H10+#REF!*#REF!+I10*J10 -> #REF!
A11: Serengeti | B11: =B10+1 -> 10 | C11: 4 | D11: 2020 | E11: ='UTILITY REPORT 1'!F12 -> 1935 | F11: =('UTILITY REPORT 1'!E12*'UTILITY REPORT 1'!D12)/'UTILITY REPORT 1'!F12 -> 0.42571059 | G11: =IF('Utility summery'!M15<0,"0",'Utility summery'!M15) -> 34.54 | H11: 0 | I11: =IF('UTILITY REPORT 1'!G12<0,"0",'UTILITY REPORT 1'!G12) -> 55 | J11: 0 | K11: ='UTILITY REPORT 1'!C12 -> 0 | L11: =E11*F11+G11*H11+#REF!*#REF!+I11*J11 -> #REF!
A12: Serengeti | B12: =B11+1 -> 11 | C12: 4 | D12: 2020 | E12: ='UTILITY REPORT 1'!F13 -> 1883 | F12: =('UTILITY REPORT 1'!E13*'UTILITY REPORT 1'!D13)/'UTILITY REPORT 1'!F13 -> 0.41565056 | G12: =IF('Utility summery'!M16<0,"0",'Utility summery'!M16) -> 38.412 | H12: 0 | I12: =IF('UTILITY REPORT 1'!G13<0,"0",'UTILITY REPORT 1'!G13) -> 56 | J12: 0 | K12: ='UTILITY REPORT 1'!C13 -> 0 | L12: =E12*F12+G12*H12+#REF!*#REF!+I12*J12 -> #REF!
A13: Serengeti | B13: =B12+1 -> 12 | C13: 4 | D13: 2020 | E13: ='UTILITY REPORT 1'!F14 -> 1877 | F13: =('UTILITY REPORT 1'!E14*'UTILITY REPORT 1'!D14)/'UTILITY REPORT 1'!F14 -> 0.41385189 | G13: =IF('Utility summery'!M17<0,"0",'Utility summery'!M17) -> 35.2 | H13: 0 | I13: =IF('UTILITY REPORT 1'!G14<0,"0",'UTILITY REPORT 1'!G14) -> 41 | J13: 0 | K13: ='UTILITY REPORT 1'!C14 -> 0 | L13: =E13*F13+G13*H13+#REF!*#REF!+I13*J13 -> #REF!
A14: Serengeti | B14: =B13+1 -> 13 | C14: 4 | D14: 2020 | E14: ='UTILITY REPORT 1'!F15 -> 1796 | F14: =('UTILITY REPORT 1'!E15*'UTILITY REPORT 1'!D15)/'UTILITY REPORT 1'!F15 -> 0.4296882 | G14: =IF('Utility summery'!M18<0,"0",'Utility summery'!M18) -> 36.036 | H14: 0 | I14: =IF('UTILITY REPORT 1'!G15<0,"0",'UTILITY REPORT 1'!G15) -> 45 | J14: 0 | K14: ='UTILITY REPORT 1'!C15 -> 0 | L14: =E14*F14+G14*H14+#REF!*#REF!+I14*J14 -> #REF!
... A30: Serengeti | B30: =B29+1 -> 29 | C30: 4 | D30: 2020 | E30: ='UTILITY REPORT 1'!F31 -> 1644 | F30: =('UTILITY REPORT 1'!E31*'UTILITY REPORT 1'!D31)/'UTILITY REPORT 1'!F31 -> 0.42037105 | G30: =IF('Utility summery'!M34<0,"0",'Utility summery'!M34) -> 40.92 | H30: 0 | I30: =IF('UTILITY REPORT 1'!G31<0,"0",'UTILITY REPORT 1'!G31) -> 29 | J30: 0 | K30: ='UTILITY REPORT 1'!C31 -> 0 | L30: =E30*F30+G30*H30+#REF!*#REF!+I30*J30 -> #REF!
A31: Serengeti | B31: 30 | C31: 4 | D31: 2020 | E31: ='UTILITY REPORT 1'!F32 -> 1564 | F31: =('UTILITY REPORT 1'!E32*'UTILITY REPORT 1'!D32)/'UTILITY REPORT 1'!F32 -> 0.42248082 | G31: =IF('Utility summery'!M35<0,"0",'Utility summery'!M35) -> 17.424 | H31: 0 | I31: =IF('UTILITY REPORT 1'!G32<0,"0",'UTILITY REPORT 1'!G32) -> 29 | J31: 0 | K31: ='UTILITY REPORT 1'!C32 -> 0 | L31: =E31*F31+G31*H31+#REF!*#REF!+I31*J31 -> #REF!
A32: Serengeti | B32: 31 | C32: 4 | D32: 2020 | E32: ='UTILITY REPORT 1'!F33 -> 0 | F32: =('UTILITY REPORT 1'!E33*'UTILITY REPORT 1'!D33)/'UTILITY REPORT 1'!F33 -> #DIV/0! | G32: =IF('Utility summery'!M36<0,"0",'Utility summery'!M36) -> 27.852 | H32: 0 | I32: =IF('UTILITY REPORT 1'!G33<0,"0",'UTILITY REPORT 1'!G33) -> 0 | J32: 0 | K32: ='UTILITY REPORT 1'!C33 -> 0

Sheet Submetering
A1: Site Name | B1: Day | C1: Month | D1: Year | E1: Transport Consumption (LT) | F1: Generators Consumption (LT) | G1: Total Electricity Kwh | H1: Kitchen (KWh) | I1: Laundry (KWh) | J1: STP (M3) | K1: RO prodution (M3) | L1: Amani Restaurant (M3) | M1: Kitchen (M3) | N1: Laundry (M3) | O1: Laundry (M3) | P1: Total water Consumption (M3) | Q1: Borehole #1 (M3) | R1: Borehole #2 (M3) | S1: Borehole #3 (M3) | T1: Borehole #4 (M3) | U1: Borehole #5 (M3) | V1: Borehole #6 (M3) | W1: Total Bore holes production (M3) | X1: Room Nights
A2: Serengeti | B2: 1 | C2: 4 | D2: 2020 | E2: ='UTILITY REPORT 1'!I3 -> 49.37 | F2: ='UTILITY REPORT 1'!E3 -> 850.96 | G2: ='UTILITY REPORT 1'!F3 -> 2051 | H2: =IF('Kit report'!F4<0,"0",'Kit report'!F4) -> 156 | I2: =IF('Kit report'!X4<0,"0",'Kit report'!X4) -> 20 | J2: =IF('Utility summery'!H6<0,"0",'Utility summery'!H6) -> 28 | K2: =IF('UTILITY REPORT 1'!H3<0,"0",'UTILITY REPORT 1'!H3) -> 0 | L2: ='Water-Meter'!K6 -> 1 | M2: ='Water-Meter'!H6 -> 0 | N2: ='Water-Meter'!Q6 -> 1 | O2: =K2*E2+H2*I2+#REF!*#REF!+J2*L2 -> #REF! | P2: ='Water-Meter'!E6 -> 38 | Q2: =IF('Water-Meter'!U6<0,"0",'Water-Meter'!U6) -> 75 | R2: =IF('Water-Meter'!X6<0,"0",'Water-Meter'!X6) -> 0 | S2: =IF('Water-Meter'!AA6<0,"0",'Water-Meter'!AA6) -> 0 | T2: =IF('Water-Meter'!AD6<0,"0",'Water-Meter'!AD6) -> 0 | U2: =IF('Water-Meter'!AG6<0,"0",'Water-Meter'!AG6) -> 24 | V2: =IF('Water-Meter'!AJ6<0,"0",'Water-Meter'!AJ6) -> 0 | W2: ='Water-Meter'!AN6 -> 99 | X2: =Total!K2 -> 0
A3: Serengeti | B3: =B2+1 -> 2 | C3: 4 | D3: 2020 | E3: ='UTILITY REPORT 1'!I4 -> 9.39 | F3: ='UTILITY REPORT 1'!E4 -> 866.25 | G3: ='UTILITY REPORT 1'!F4 -> 2088 | H3: =IF('Kit report'!F5<0,"0",'Kit report'!F5) -> 132 | I3: =IF('Kit report'!X5<0,"0",'Kit report'!X5) -> 20 | J3: =IF('Utility summery'!H7<0,"0",'Utility summery'!H7) -> 29 | K3: =IF('UTILITY REPORT 1'!H4<0,"0",'UTILITY REPORT 1'!H4) -> 48 | L3: ='Water-Meter'!K7 -> 1 | M3: ='Water-Meter'!H7 -> 0 | N3: ='Water-Meter'!Q7 -> 2 | O3: =K3*E3+H3*I3+#REF!*#REF!+J3*L3 -> #REF! | P3: ='Water-Meter'!E7 -> 52 | Q3: =IF('Water-Meter'!U7<0,"0",'Water-Meter'!U7) -> 65 | R3: =IF('Water-Meter'!X7<0,"0",'Water-Meter'!X7) -> 0 | S3: =IF('Water-Meter'!AA7<0,"0",'Water-Meter'!AA7) -> 0 | T3: =IF('Water-Meter'!AD7<0,"0",'Water-Meter'!AD7) -> 0 | U3: =IF('Water-Meter'!AG7<0,"0",'Water-Meter'!AG7) -> 24 | V3: =IF('Water-Meter'!AJ7<0,"0",'Water-Meter'!AJ7) -> 0 | W3: ='Water-Meter'!AN7 -> 89 | X3: =Total!K3 -> 0
A4: Serengeti | B4: =B3+1 -> 3 | C4: 4 | D4: 2020 | E4: ='UTILITY REPORT 1'!I5 -> 18.02 | F4: ='UTILITY REPORT 1'!E5 -> 832.92 | G4: ='UTILITY REPORT 1'!F5 -> 1898 | H4: =IF('Kit report'!F6<0,"0",'Kit report'!F6) -> 144 | I4: =IF('Kit report'!X6<0,"0",'Kit report'!X6) -> 40 | J4: =IF('Utility summery'!H8<0,"0",'Utility summery'!H8) -> 19 | K4: =IF('UTILITY REPORT 1'!H5<0,"0",'UTILITY REPORT 1'!H5) -> 59 | L4: ='Water-Meter'!K8 -> 1 | M4: ='Water-Meter'!H8 -> 0 | N4: ='Water-Meter'!Q8 -> 1 | O4: =K4*E4+H4*I4+#REF!*#REF!+J4*L4 -> #REF! | P4: ='Water-Meter'!E8 -> 26 | Q4: =IF('Water-Meter'!U8<0,"0",'Water-Meter'!U8) -> 60 | R4: =IF('Water-Meter'!X8<0,"0",'Water-Meter'!X8) -> 0 | S4: =IF('Water-Meter'!AA8<0,"0",'Water-Meter'!AA8) -> 0 | T4: =IF('Water-Meter'!AD8<0,"0",'Water-Meter'!AD8) -> 0 | U4: =IF('Water-Meter'!AG8<0,"0",'Water-Meter'!AG8) -> 24 | V4: =IF('Water-Meter'!AJ8<0,"0",'Water-Meter'!AJ8) -> 0 | W4: ='Water-Meter'!AN8 -> 84 | X4: =Total!K4 -> 0
A5: Serengeti | B5: =B4+1 -> 4 | C5: 4 | D5: 2020 | E5: ='UTILITY REPORT 1'!I6 -> 660.37 | F5: ='UTILITY REPORT 1'!E6 -> 789.55 | G5: ='UTILITY REPORT 1'!F6 -> 1815 | H5: =IF('Kit report'!F7<0,"0",'Kit report'!F7) -> 132 | I5: =IF('Kit report'!X7<0,"0",'Kit report'!X7) -> 40 | J5: =IF('Utility summery'!H9<0,"0",'Utility summery'!H9) -> 0 | K5: =IF('UTILITY REPORT 1'!H6<0,"0",'UTILITY REPORT 1'!H6) -> 57 | L5: ='Water-Meter'!K9 -> 1 | M5: ='Water-Meter'!H9 -> 0 | N5: ='Water-Meter'!Q9 -> 2 | O5: =K5*E5+H5*I5+#REF!*#REF!+J5*L5 -> #REF! | P5: ='Water-Meter'!E9 -> 34 | Q5: =IF('Water-Meter'!U9<0,"0",'Water-Meter'!U9) -> 52 | R5: =IF('Water-Meter'!X9<0,"0",'Water-Meter'!X9) -> 0 | S5: =IF('Water-Meter'!AA9<0,"0",'Water-Meter'!AA9) -> 0 | T5: =IF('Water-Meter'!AD9<0,"0",'Water-Meter'!AD9) -> 0 | U5: =IF('Water-Meter'!AG9<0,"0",'Water-Meter'!AG9) -> 24 | V5: =IF('Water-Meter'!AJ9<0,"0",'Water-Meter'!AJ9) -> 0 | W5: ='Water-Meter'!AN9 -> 76 | X5: =Total!K5 -> 0
A6: Serengeti | B6: =B5+1 -> 5 | C6: 4 | D6: 2020 | E6: ='UTILITY REPORT 1'!I7 -> 34.28 | F6: ='UTILITY REPORT 1'!E7 -> 813.34 | G6: ='UTILITY REPORT 1'!F7 -> 1841 | H6: =IF('Kit report'!F8<0,"0",'Kit report'!F8) -> 108 | I6: =IF('Kit report'!X8<0,"0",'Kit report'!X8) -> 40 | J6: =IF('Utility summery'!H10<0,"0",'Utility summery'!H10) -> 48 | K6: =IF('UTILITY REPORT 1'!H7<0,"0",'UTILITY REPORT 1'!H7) -> 57 | L6: ='Water-Meter'!K10 -> 0 | M6: ='Water-Meter'!H10 -> 0 | N6: ='Water-Meter'!Q10 -> 1 | O6: =K6*E6+H6*I6+#REF!*#REF!+J6*L6 -> #REF! | P6: ='Water-Meter'!E10 -> 42 | Q6: =IF('Water-Meter'!U10<0,"0",'Water-Meter'!U10) -> 82 | R6: =IF('Water-Meter'!X10<0,"0",'Water-Meter'!X10) -> 0 | S6: =IF('Water-Meter'!AA10<0,"0",'Water-Meter'!AA10) -> 0 | T6: =IF('Water-Meter'!AD10<0,"0",'Water-Meter'!AD10) -> 11 | U6: =IF('Water-Meter'!AG10<0,"0",'Water-Meter'!AG10) -> 0 | V6: =IF('Water-Meter'!AJ10<0,"0",'Water-Meter'!AJ10) -> 0 | W6: ='Water-Meter'!AN10 -> 93 | X6: =Total!K6 -> 0
A7: Serengeti | B7: =B6+1 -> 6 | C7: 4 | D7: 2020 | E7: ='UTILITY REPORT 1'!I8 -> 0 | F7: ='UTILITY REPORT 1'!E8 -> 757.53 | G7: ='UTILITY REPORT 1'!F8 -> 1789 | H7: =IF('Kit report'!F9<0,"0",'Kit report'!F9) -> 132 | I7: =IF('Kit report'!X9<0,"0",'Kit report'!X9) -> 40 | J7: =IF('Utility summery'!H11<0,"0",'Utility summery'!H11) -> 18 | K7: =IF('UTILITY REPORT 1'!H8<0,"0",'UTILITY REPORT 1'!H8) -> 38 | L7: ='Water-Meter'!K11 -> 0 | M7: ='Water-Meter'!H11 -> 0 | N7: ='Water-Meter'!Q11 -> 1 | O7: =K7*E7+H7*I7+#REF!*#REF!+J7*L7 -> #REF! | P7: ='Water-Meter'!E11 -> 41 | Q7: =IF('Water-Meter'!U11<0,"0",'Water-Meter'!U11) -> 65 | R7: =IF('Water-Meter'!X11<0,"0",'Water-Meter'!X11) -> 0 | S7: =IF('Water-Meter'!AA11<0,"0",'Water-Meter'!AA11) -> 0 | T7: =IF('Water-Meter'!AD11<0,"0",'Water-Meter'!AD11) -> 11 | U7: =IF('Water-Meter'!AG11<0,"0",'Water-Meter'!AG11) -> 0 | V7: =IF('Water-Meter'!AJ11<0,"0",'Water-Meter'!AJ11) -> 0 | W7: ='Water-Meter'!AN11 -> 76 | X7: =Total!K7 -> 0
A8: Serengeti | B8: =B7+1 -> 7 | C8: 4 | D8: 2020 | E8: ='UTILITY REPORT 1'!I9 -> 108.2 | F8: ='UTILITY REPORT 1'!E9 -> 783.55 | G8: ='UTILITY REPORT 1'!F9 -> 1867 | H8: =IF('Kit report'!F10<0,"0",'Kit report'!F10) -> 108 | I8: =IF('Kit report'!X10<0,"0",'Kit report'!X10) -> 40 | J8: =IF('Utility summery'!H12<0,"0",'Utility summery'!H12) -> 32 | K8: =IF('UTILITY REPORT 1'!H9<0,"0",'UTILITY REPORT 1'!H9) -> 53 | L8: ='Water-Meter'!K12 -> 0 | M8: ='Water-Meter'!H12 -> 0 | N8: ='Water-Meter'!Q12 -> 2 | O8: =K8*E8+H8*I8+#REF!*#REF!+J8*L8 -> #REF! | P8: ='Water-Meter'!E12 -> 47 | Q8: =IF('Water-Meter'!U12<0,"0",'Water-Meter'!U12) -> 49 | R8: =IF('Water-Meter'!X12<0,"0",'Water-Meter'!X12) -> 0 | S8: =IF('Water-Meter'!AA12<0,"0",'Water-Meter'!AA12) -> 44 | T8: =IF('Water-Meter'!AD12<0,"0",'Water-Meter'!AD12) -> 10 | U8: =IF('Water-Meter'!AG12<0,"0",'Water-Meter'!AG12) -> 0 | V8: =IF('Water-Meter'!AJ12<0,"0",'Water-Meter'!AJ12) -> 0 | W8: ='Water-Meter'!AN12 -> 103 | X8: =Total!K8 -> 0
A9: Serengeti | B9: =B8+1 -> 8 | C9: 4 | D9: 2020 | E9: ='UTILITY REPORT 1'!I10 -> 0 | F9: ='UTILITY REPORT 1'!E10 -> 831.27 | G9: ='UTILITY REPORT 1'!F10 -> 1940 | H9: =IF('Kit report'!F11<0,"0",'Kit report'!F11) -> 120 | I9: =IF('Kit report'!X11<0,"0",'Kit report'!X11) -> 40 | J9: =IF('Utility summery'!H13<0,"0",'Utility summery'!H13) -> 28 | K9: =IF('UTILITY REPORT 1'!H10<0,"0",'UTILITY REPORT 1'!H10) -> 50 | L9: ='Water-Meter'!K13 -> 0 | M9: ='Water-Meter'!H13 -> 0 | N9: ='Water-Meter'!Q13 -> 1 | O9: =K9*E9+H9*I9+#REF!*#REF!+J9*L9 -> #REF! | P9: ='Water-Meter'!E13 -> 36 | Q9: =IF('Water-Meter'!U13<0,"0",'Water-Meter'!U13) -> 66 | R9: =IF('Water-Meter'!X13<0,"0",'Water-Meter'!X13) -> 0 | S9: =IF('Water-Meter'!AA13<0,"0",'Water-Meter'!AA13) -> 52 | T9: =IF('Water-Meter'!AD13<0,"0",'Water-Meter'!AD13) -> 11 | U9: =IF('Water-Meter'!AG13<0,"0",'Water-Meter'!AG13) -> 0 | V9: =IF('Water-Meter'!AJ13<0,"0",'Water-Meter'!AJ13) -> 0 | W9: ='Water-Meter'!AN13 -> 129 | X9: =Total!K9 -> 0
A10: Serengeti | B10: =B9+1 -> 9 | C10: 4 | D10: 2020 | E10: ='UTILITY REPORT 1'!I11 -> 0 | F10: ='UTILITY REPORT 1'!E11 -> 806.32 | G10: ='UTILITY REPORT 1'!F11 -> 1882 | H10: =IF('Kit report'!F12<0,"0",'Kit report'!F12) -> 120 | I10: =IF('Kit report'!X12<0,"0",'Kit report'!X12) -> 20 | J10: =IF('Utility summery'!H14<0,"0",'Utility summery'!H14) -> 26 | K10: =IF('UTILITY REPORT 1'!H11<0,"0",'UTILITY REPORT 1'!H11) -> 7 | L10: ='Water-Meter'!K14 -> 0 | M10: ='Water-Meter'!H14 -> 0 | N10: ='Water-Meter'!Q14 -> 1 | O10: =K10*E10+H10*I10+#REF!*#REF!+J10*L10 -> #REF! | P10: ='Water-Meter'!E14 -> 33 | Q10: =IF('Water-Meter'!U14<0,"0",'Water-Meter'!U14) -> 65 | R10: =IF('Water-Meter'!X14<0,"0",'Water-Meter'!X14) -> 0 | S10: =IF('Water-Meter'!AA14<0,"0",'Water-Meter'!AA14) -> 53 | T10: =IF('Water-Meter'!AD14<0,"0",'Water-Meter'!AD14) -> 17 | U10: =IF('Water-Meter'!AG14<0,"0",'Water-Meter'!AG14) -> 0 | V10: =IF('Water-Meter'!AJ14<0,"0",'Water-Meter'!AJ14) -> 0 | W10: ='Water-Meter'!AN14 -> 135 | X10: =Total!K10 -> 0
A11: Serengeti | B11: =B10+1 -> 10 | C11: 4 | D11: 2020 | E11: ='UTILITY REPORT 1'!I12 -> 0 | F11: ='UTILITY REPORT 1'!E12 -> 823.75 | G11: ='UTILITY REPORT 1'!F12 -> 1935 | H11: =IF('Kit report'!F13<0,"0",'Kit report'!F13) -> 108 | I11: =IF('Kit report'!X13<0,"0",'Kit report'!X13) -> 60 | J11: =IF('Utility summery'!H15<0,"0",'Utility summery'!H15) -> 26 | K11: =IF('UTILITY REPORT 1'!H12<0,"0",'UTILITY REPORT 1'!H12) -> 44 | L11: ='Water-Meter'!K15 -> 0 | M11: ='Water-Meter'!H15 -> 0 | N11: ='Water-Meter'!Q15 -> 2 | O11: =K11*E11+H11*I11+#REF!*#REF!+J11*L11 -> #REF! | P11: ='Water-Meter'!E15 -> 55 | Q11: =IF('Water-Meter'!U15<0,"0",'Water-Meter'!U15) -> 1 | R11: =IF('Water-Meter'!X15<0,"0",'Water-Meter'!X15) -> 0 | S11: =IF('Water-Meter'!AA15<0,"0",'Water-Meter'!AA15) -> 53 | T11: =IF('Water-Meter'!AD15<0,"0",'Water-Meter'!AD15) -> 17 | U11: =IF('Water-Meter'!AG15<0,"0",'Water-Meter'!AG15) -> 20 | V11: =IF('Water-Meter'!AJ15<0,"0",'Water-Meter'!AJ15) -> 0 | W11: ='Water-Meter'!AN15 -> 91 | X11: =Total!K11 -> 0
A12: Serengeti | B12: =B11+1 -> 11 | C12: 4 | D12: 2020 | E12: ='UTILITY REPORT 1'!I13 -> 0 | F12: ='UTILITY REPORT 1'!E13 -> 782.67 | G12: ='UTILITY REPORT 1'!F13 -> 1883 | H12: =IF('Kit report'!F14<0,"0",'Kit report'!F14) -> 132 | I12: =IF('Kit report'!X14<0,"0",'Kit report'!X14) -> 20 | J12: =IF('Utility summery'!H16<0,"0",'Utility summery'!H16) -> 28 | K12: =IF('UTILITY REPORT 1'!H13<0,"0",'UTILITY REPORT 1'!H13) -> 75 | L12: ='Water-Meter'!K16 -> 0 | M12: ='Water-Meter'!H16 -> 0 | N12: ='Water-Meter'!Q16 -> 1 | O12: =K12*E12+H12*I12+#REF!*#REF!+J12*L12 -> #REF! | P12: ='Water-Meter'!E16 -> 56 | Q12: =IF('Water-Meter'!U16<0,"0",'Water-Meter'!U16) -> 0 | R12: =IF('Water-Meter'!X16<0,"0",'Water-Meter'!X16) -> 0 | S12: =IF('Water-Meter'!AA16<0,"0",'Water-Meter'!AA16) -> 4 | T12: =IF('Water-Meter'!AD16<0,"0",'Water-Meter'!AD16) -> 17 | U12: =IF('Water-Meter'!AG16<0,"0",'Water-Meter'!AG16) -> 25 | V12: =IF('Water-Meter'!AJ16<0,"0",'Water-Meter'!AJ16) -> 0 | W12: ='Water-Meter'!AN16 -> 46 | X12: =Total!K12 -> 0
A13: Serengeti | B13: =B12+1 -> 12 | C13: 4 | D13: 2020 | E13: ='UTILITY REPORT 1'!I14 -> 0 | F13: ='UTILITY REPORT 1'!E14 -> 776.8 | G13: ='UTILITY REPORT 1'!F14 -> 1877 | H13: =IF('Kit report'!F15<0,"0",'Kit report'!F15) -> 132 | I13: =IF('Kit report'!X15<0,"0",'Kit report'!X15) -> 20 | J13: =IF('Utility summery'!H17<0,"0",'Utility summery'!H17) -> 24 | K13: =IF('UTILITY REPORT 1'!H14<0,"0",'UTILITY REPORT 1'!H14) -> 49 | L13: ='Water-Meter'!K17 -> 1 | M13: ='Water-Meter'!H17 -> 0 | N13: ='Water-Meter'!Q17 -> 1 | O13: =K13*E13+H13*I13+#REF!*#REF!+J13*L13 -> #REF! | P13: ='Water-Meter'!E17 -> 41 | Q13: =IF('Water-Meter'!U17<0,"0",'Water-Meter'!U17) -> 0 | R13: =IF('Water-Meter'!X17<0,"0",'Water-Meter'!X17) -> 0 | S13: =IF('Water-Meter'!AA17<0,"0",'Water-Meter'!AA17) -> 0 | T13: =IF('Water-Meter'!AD17<0,"0",'Water-Meter'!AD17) -> 16 | U13: =IF('Water-Meter'!AG17<0,"0",'Water-Meter'!AG17) -> 25 | V13: =IF('Water-Meter'!AJ17<0,"0",'Water-Meter'!AJ17) -> 0 | W13: ='Water-Meter'!AN17 -> 41 | X13: =Total!K13 -> 0
A14: Serengeti | B14: =B13+1 -> 13 | C14: 4 | D14: 2020 | E14: ='UTILITY REPORT 1'!I15 -> 19.86 | F14: ='UTILITY REPORT 1'!E15 -> 771.72 | G14: ='UTILITY REPORT 1'!F15 -> 1796 | H14: =IF('Kit report'!F16<0,"0",'Kit report'!F16) -> 132 | I14: =IF('Kit report'!X16<0,"0",'Kit report'!X16) -> 20 | J14: =IF('Utility summery'!H18<0,"0",'Utility summery'!H18) -> 31 | K14: =IF('UTILITY REPORT 1'!H15<0,"0",'UTILITY REPORT 1'!H15) -> 50 | L14: ='Water-Meter'!K18 -> 0 | M14: ='Water-Meter'!H18 -> 0 | N14: ='Water-Meter'!Q18 -> 1 | O14: =K14*E14+H14*I14+#REF!*#REF!+J14*L14 -> #REF! | P14: ='Water-Meter'!E18 -> 45 | Q14: =IF('Water-Meter'!U18<0,"0",'Water-Meter'!U18) -> 0 | R14: =IF('Water-Meter'!X18<0,"0",'Water-Meter'!X18) -> 0 | S14: =IF('Water-Meter'!AA18<0,"0",'Water-Meter'!AA18) -> 0 | T14: =IF('Water-Meter'!AD18<0,"0",'Water-Meter'!AD18) -> 16 | U14: =IF('Water-Meter'!AG18<0,"0",'Water-Meter'!AG18) -> 25 | V14: =IF('Water-Meter'!AJ18<0,"0",'Water-Meter'!AJ18) -> 0 | W14: ='Water-Meter'!AN18 -> 41 | X14: =Total!K14 -> 0
... A30: Serengeti | B30: =B29+1 -> 29 | C30: 4 | D30: 2020 | E30: ='UTILITY REPORT 1'!I31 -> 38.11 | F30: ='UTILITY REPORT 1'!E31 -> 691.09 | G30: ='UTILITY REPORT 1'!F31 -> 1644 | H30: =IF('Kit report'!F32<0,"0",'Kit report'!F32) -> 108 | I30: =IF('Kit report'!X32<0,"0",'Kit report'!X32) -> 0 | J30: =IF('Utility summery'!H34<0,"0",'Utility summery'!H34) -> 42 | K30: =IF('UTILITY REPORT 1'!H31<0,"0",'UTILITY REPORT 1'!H31) -> 83 | L30: ='Water-Meter'!K34 -> 1 | M30: ='Water-Meter'!H34 -> 0 | N30: ='Water-Meter'!Q34 -> 1 | O30: =K30*E30+H30*I30+#REF!*#REF!+J30*L30 -> #REF! | P30: ='Water-Meter'!E34 -> 29 | Q30: =IF('Water-Meter'!U34<0,"0",'Water-Meter'!U34) -> 0 | R30: =IF('Water-Meter'!X34<0,"0",'Water-Meter'!X34) -> 0 | S30: =IF('Water-Meter'!AA34<0,"0",'Water-Meter'!AA34) -> 0 | T30: =IF('Water-Meter'!AD34<0,"0",'Water-Meter'!AD34) -> 20 | U30: =IF('Water-Meter'!AG34<0,"0",'Water-Meter'!AG34) -> 25 | V30: =IF('Water-Meter'!AJ34<0,"0",'Water-Meter'!AJ34) -> 0 | W30: ='Water-Meter'!AN34 -> 45 | X30: =Total!K30 -> 0
A31: Serengeti | B31: 30 | C31: 4 | D31: 2020 | E31: ='UTILITY REPORT 1'!I32 -> 0 | F31: ='UTILITY REPORT 1'!E32 -> 660.76 | G31: ='UTILITY REPORT 1'!F32 -> 1564 | H31: =IF('Kit report'!F33<0,"0",'Kit report'!F33) -> 96 | I31: =IF('Kit report'!X33<0,"0",'Kit report'!X33) -> 20 | J31: =IF('Utility summery'!H35<0,"0",'Utility summery'!H35) -> 70 | K31: =IF('UTILITY REPORT 1'!H32<0,"0",'UTILITY REPORT 1'!H32) -> 0 | L31: ='Water-Meter'!K35 -> 0 | M31: ='Water-Meter'!H35 -> 0 | N31: ='Water-Meter'!Q35 -> 1 | O31: =K31*E31+H31*I31+#REF!*#REF!+J31*L31 -> #REF! | P31: ='Water-Meter'!E35 -> 29 | Q31: =IF('Water-Meter'!U35<0,"0",'Water-Meter'!U35) -> 0 | R31: =IF('Water-Meter'!X35<0,"0",'Water-Meter'!X35) -> 0 | S31: =IF('Water-Meter'!AA35<0,"0",'Water-Meter'!AA35) -> 0 | T31: =IF('Water-Meter'!AD35<0,"0",'Water-Meter'!AD35) -> 21 | U31: =IF('Water-Meter'!AG35<0,"0",'Water-Meter'!AG35) -> 25 | V31: =IF('Water-Meter'!AJ35<0,"0",'Water-Meter'!AJ35) -> 0 | W31: ='Water-Meter'!AN35 -> 46 | X31: =Total!K31 -> 0
A32: Serengeti | B32: 31 | C32: 4 | D32: 2020 | E32: ='UTILITY REPORT 1'!I33 -> 0 | F32: ='UTILITY REPORT 1'!E33 -> 0 | G32: ='UTILITY REPORT 1'!F33 -> 0 | H32: =IF('Kit report'!F34<0,"0",'Kit report'!F34) -> 0 | I32: =IF('Kit report'!X34<0,"0",'Kit report'!X34) -> 0 | J32: =IF('Utility summery'!H36<0,"0",'Utility summery'!H36) -> 0 | K32: =IF('UTILITY REPORT 1'!H33<0,"0",'UTILITY REPORT 1'!H33) -> 0 | L32: ='Water-Meter'!K36 -> 0 | M32: ='Water-Meter'!H36 -> 0 | N32: ='Water-Meter'!Q36 -> 0 | P32: ='Water-Meter'!E36 -> 0 | Q32: =IF('Water-Meter'!U36<0,"0",'Water-Meter'!U36) -> 0 | R32: =IF('Water-Meter'!X36<0,"0",'Water-Meter'!X36) -> 0 | S32: =IF('Water-Meter'!AA36<0,"0",'Water-Meter'!AA36) -> 0 | T32: =IF('Water-Meter'!AD36<0,"0",'Water-Meter'!AD36) -> 0 | U32: =IF('Water-Meter'!AG36<0,"0",'Water-Meter'!AG36) -> 0 | V32: =IF('Water-Meter'!AJ36<0,"0",'Water-Meter'!AJ36) -> 0 | W32: ='Water-Meter'!AN36 -> 0 | X32: =Total!K32 -> 0

Sheet UTILITY REPORT 1
A1: APRIL UTILITY REPORT
A2: Date | B2: % | C2: Guest Rooms Occupied | D2: Diesel cost Per Liter ($) | E2: Diesel consumption (LT) | F2: Power production (KW) | G2: Water consumption (M3) | H2: RO prodution (M3) | I2: Transport Consupmtion (LT)
A3: =Gen!B11 -> 43922 | B3: =Gen!C11 -> 0 | C3: ='Summery Report'!E5 -> 0 | D3: 1 | E3: =Gen!T11 -> 850.96 | F3: =Gen!U11 -> 2051 | G3: ='Water-Meter'!E6 -> 38 | H3: ='Utility report '!AC6 -> 0 | I3: =Gen!AK11 -> 49.37
A4: =Gen!B12 -> 43923 | B4: =Gen!C12 -> 0 | C4: ='Summery Report'!E6 -> 0 | D4: 1 | E4: =Gen!T12 -> 866.25 | F4: =Gen!U12 -> 2088 | G4: ='Water-Meter'!E7 -> 52 | H4: ='Utility report '!AC7 -> 48 | I4: =Gen!AK12 -> 9.39
A5: =Gen!B13 -> 43924 | B5: =Gen!C13 -> 0 | C5: ='Summery Report'!E7 -> 0 | D5: 1 | E5: =Gen!T13 -> 832.92 | F5: =Gen!U13 -> 1898 | G5: ='Water-Meter'!E8 -> 26 | H5: ='Utility report '!AC8 -> 59 | I5: =Gen!AK13 -> 18.02
A6: =Gen!B14 -> 43925 | B6: =Gen!C14 -> 0 | C6: ='Summery Report'!E8 -> 0 | D6: 1 | E6: =Gen!T14 -> 789.55 | F6: =Gen!U14 -> 1815 | G6: ='Water-Meter'!E9 -> 34 | H6: ='Utility report '!AC9 -> 57 | I6: =Gen!AK14 -> 660.37
A7: =Gen!B15 -> 43926 | B7: =Gen!C15 -> 0 | C7: ='Summery Report'!E9 -> 0 | D7: 1 | E7: =Gen!T15 -> 813.34 | F7: =Gen!U15 -> 1841 | G7: ='Water-Meter'!E10 -> 42 | H7: ='Utility report '!AC10 -> 57 | I7: =Gen!AK15 -> 34.28
A8: =Gen!B16 -> 43927 | B8: =Gen!C16 -> 0 | C8: ='Summery Report'!E10 -> 0 | D8: 1 | E8: =Gen!T16 -> 757.53 | F8: =Gen!U16 -> 1789 | G8: ='Water-Meter'!E11 -> 41 | H8: ='Utility report '!AC11 -> 38 | I8: =Gen!AK16 -> 0
A9: =Gen!B17 -> 43928 | B9: =Gen!C17 -> 0 | C9: ='Summery Report'!E11 -> 0 | D9: 1 | E9: =Gen!T17 -> 783.55 | F9: =Gen!U17 -> 1867 | G9: ='Water-Meter'!E12 -> 47 | H9: ='Utility report '!AC12 -> 53 | I9: =Gen!AK17 -> 108.2
A10: =Gen!B18 -> 43929 | B10: =Gen!C18 -> 0 | C10: ='Summery Report'!E12 -> 0 | D10: 1 | E10: =Gen!T18 -> 831.27 | F10: =Gen!U18 -> 1940 | G10: ='Water-Meter'!E13 -> 36 | H10: ='Utility report '!AC13 -> 50 | I10: =Gen!AK18 -> 0
A11: =Gen!B19 -> 43930 | B11: =Gen!C19 -> 0 | C11: ='Summery Report'!E13 -> 0 | D11: 1 | E11: =Gen!T19 -> 806.32 | F11: =Gen!U19 -> 1882 | G11: ='Water-Meter'!E14 -> 33 | H11: ='Utility report '!AC14 -> 7 | I11: =Gen!AK19 -> 0
A12: =Gen!B20 -> 43931 | B12: =Gen!C20 -> 0 | C12: ='Summery Report'!E14 -> 0 | D12: 1 | E12: =Gen!T20 -> 823.75 | F12: =Gen!U20 -> 1935 | G12: ='Water-Meter'!E15 -> 55 | H12: ='Utility report '!AC15 -> 44 | I12: =Gen!AK20 -> 0
A13: =Gen!B21 -> 43932 | B13: =Gen!C21 -> 0 | C13: ='Summery Report'!E15 -> 0 | D13: 1 | E13: =Gen!T21 -> 782.67 | F13: =Gen!U21 -> 1883 | G13: ='Water-Meter'!E16 -> 56 | H13: ='Utility report '!AC16 -> 75 | I13: =Gen!AK21 -> 0
A14: =Gen!B22 -> 43933 | B14: =Gen!C22 -> 0 | C14: ='Summery Report'!E16 -> 0 | D14: 1 | E14: =Gen!T22 -> 776.8 | F14: =Gen!U22 -> 1877 | G14: ='Water-Meter'!E17 -> 41 | H14: ='Utility report '!AC17 -> 49 | I14: =Gen!AK22 -> 0
... A34: =Gen!B42 -> 0 | B34: =Gen!C42 -> 0 | C34: ='Summery Report'!E36 -> 0 | D34: 2 | E34: =Gen!T42 -> 0 | F34: =Gen!U42 -> 0 | G34: ='Water-Meter'!E37 -> 0 | H34: ='Utility report '!AC37 -> 0 | I34: =Gen!AK42 -> 0

Sheet Utility summery
A4: Date | B4: Room Occupied | C4: Electricity Units Generated KW | D4: Diseal | G4: Water | J4: Gas | N4: Cost of utilites
D5: Generator | E5: Transport | F5: Total | G5: RO | H5: STP | I5: Total Consumption | J5: 2 ton | K5: 1 Ton | L5: 1 Ton | M5: Total consumption | N5: Electricity /1.4$/liter | O5: Diseal for Transport | P5: Gas /2.38$/Kg | Q5: Total HLP Cost | R5: Electricity Cost/Room $ | S5: cost/Room $
A6: =Gen!B11 -> 43922 | B6: ='Summery Report'!E5 -> 0 | C6: =Gen!U11 -> 2051 | D6: =Gen!T11 -> 850.96 | E6: =Gen!AK11 -> 49.37 | F6: =Gen!AS11 -> 900.33 | G6: ='Utility report '!AC6 -> 0 | H6: ='Utility report '!AE6 -> 28 | I6: ='Water-Meter'!E6 -> 38 | J6: ='Lpg (2)'!B10 -> 16 | K6: ='Lpg (2)'!C10 -> 85 | L6: ='Lpg (2)'!D10 -> 66 | M6: ='Lpg (2)'!G10 -> 61.6 | O6: =E6 -> 49.37 | P6: ='[1]Lpg (2)'!#REF! -> #REF! | Q6: ='[1]Summery Report'!#REF! -> #REF! | R6: =N6/B6 -> #DIV/0! | S6: =Q6/B6 -> #REF!
A7: =Gen!B12 -> 43923 | B7: ='Summery Report'!E6 -> 0 | C7: =Gen!U12 -> 2088 | D7: =Gen!T12 -> 866.25 | E7: =Gen!AK12 -> 9.39 | F7: =Gen!AS12 -> 875.64 | G7: ='Utility report '!AC7 -> 48 | H7: ='Utility report '!AE7 -> 29 | I7: ='Water-Meter'!E7 -> 52 | J7: ='Lpg (2)'!B11 -> 16 | K7: ='Lpg (2)'!C11 -> 85 | L7: ='Lpg (2)'!D11 -> 66 | M7: ='Lpg (2)'!G11 -> 66 | N7: =D7*1.4 -> 1212.75 | O7: =E7*1.4 -> 13.146 | P7: ='[1]Lpg (2)'!#REF! -> #REF! | Q7: ='[1]Summery Report'!#REF! -> #REF! | R7: =N7/B7 -> #DIV/0! | S7: =Q7/B7 -> #REF!
A8: =Gen!B13 -> 43924 | B8: ='Summery Report'!E7 -> 0 | C8: =Gen!U13 -> 1898 | D8: =Gen!T13 -> 832.92 | E8: =Gen!AK13 -> 18.02 | F8: =Gen!AS13 -> 850.94 | G8: ='Utility report '!AC8 -> 59 | H8: ='Utility report '!AE8 -> 19 | I8: ='Water-Meter'!E8 -> 26 | J8: ='Lpg (2)'!B12 -> 15 | K8: ='Lpg (2)'!C12 -> 85 | L8: ='Lpg (2)'!D12 -> 66 | M8: ='Lpg (2)'!G12 -> 37.532 | N8: =D8*1.4 -> 1166.088 | O8: =E8*1.4 -> 25.228 | P8: ='[1]Lpg (2)'!#REF! -> #REF! | Q8: ='[1]Summery Report'!#REF! -> #REF! | R8: =N8/B8 -> #DIV/0! | S8: =Q8/B8 -> #REF!
A9: =Gen!B14 -> 43925 | B9: ='Summery Report'!E8 -> 0 | C9: =Gen!U14 -> 1815 | D9: =Gen!T14 -> 789.55 | E9: =Gen!AK14 -> 660.37 | F9: =Gen!AS14 -> 1449.92 | G9: ='Utility report '!AC9 -> 57 | H9: ='Utility report '!AE9 -> 0 | I9: ='Water-Meter'!E9 -> 34 | J9: ='Lpg (2)'!B13 -> 14 | K9: ='Lpg (2)'!C13 -> 85 | L9: ='Lpg (2)'!D13 -> 66 | M9: ='Lpg (2)'!G13 -> 31.46 | N9: =D9*1.4 -> 1105.37 | O9: =E9*1.4 -> 924.518 | P9: ='[1]Lpg (2)'!#REF! -> #REF! | Q9: ='[1]Summery Report'!#REF! -> #REF! | R9: =N9/B9 -> #DIV/0! | S9: =Q9/B9 -> #REF!
A10: =Gen!B15 -> 43926 | B10: ='Summery Report'!E9 -> 0 | C10: =Gen!U15 -> 1841 | D10: =Gen!T15 -> 813.34 | E10: =Gen!AK15 -> 34.28 | F10: =Gen!AS15 -> 847.62 | G10: ='Utility report '!AC10 -> 57 | H10: ='Utility report '!AE10 -> 48 | I10: ='Water-Meter'!E10 -> 42 | J10: ='Lpg (2)'!B14 -> 13 | K10: ='Lpg (2)'!C14 -> 85 | L10: ='Lpg (2)'!D14 -> 66 | M10: ='Lpg (2)'!G14 -> 27.808 | N10: =D10*1.4 -> 1138.676 | O10: =E10*1.4 -> 47.992 | P10: ='[1]Lpg (2)'!#REF! -> #REF! | Q10: ='[1]Summery Report'!#REF! -> #REF! | R10: =N10/B10 -> #DIV/0! | S10: =Q10/B10 -> #REF!
A11: =Gen!B16 -> 43927 | B11: ='Summery Report'!E10 -> 0 | C11: =Gen!U16 -> 1789 | D11: =Gen!T16 -> 757.53 | E11: =Gen!AK16 -> 0 | F11: =Gen!AS16 -> 757.53 | G11: ='Utility report '!AC11 -> 38 | H11: ='Utility report '!AE11 -> 18 | I11: ='Water-Meter'!E11 -> 41 | J11: ='Lpg (2)'!B15 -> 13 | K11: ='Lpg (2)'!C15 -> 85 | L11: ='Lpg (2)'!D15 -> 66 | M11: ='Lpg (2)'!G15 -> 14.608 | N11: =D11*1.4 -> 1060.542 | O11: =E11*1.4 -> 0 | P11: ='[1]Lpg (2)'!#REF! -> #REF! | Q11: ='[1]Summery Report'!#REF! -> #REF! | R11: =N11/B11 -> #DIV/0! | S11: =Q11/B11 -> #REF!
A12: =Gen!B17 -> 43928 | B12: ='Summery Report'!E11 -> 0 | C12: =Gen!U17 -> 1867 | D12: =Gen!T17 -> 783.55 | E12: =Gen!AK17 -> 108.2 | F12: =Gen!AS17 -> 891.75 | G12: ='Utility report '!AC12 -> 53 | H12: ='Utility report '!AE12 -> 32 | I12: ='Water-Meter'!E12 -> 47 | J12: ='Lpg (2)'!B16 -> 13 | K12: ='Lpg (2)'!C16 -> 85 | L12: ='Lpg (2)'!D16 -> 66 | M12: ='Lpg (2)'!G16 -> 25.212 | N12: =D12*1.4 -> 1096.97 | O12: =E12*1.4 -> 151.48 | P12: ='[1]Lpg (2)'!#REF! -> #REF! | Q12: ='[1]Summery Report'!#REF! -> #REF! | R12: =N12/B12 -> #DIV/0! | S12: =Q12/B12 -> #REF!
A13: =Gen!B18 -> 43929 | B13: ='Summery Report'!E12 -> 0 | C13: =Gen!U18 -> 1940 | D13: =Gen!T18 -> 831.27 | E13: =Gen!AK18 -> 0 | F13: =Gen!AS18 -> 831.27 | G13: ='Utility report '!AC13 -> 50 | H13: ='Utility report '!AE13 -> 28 | I13: ='Water-Meter'!E13 -> 36 | J13: ='Lpg (2)'!B17 -> 13 | K13: ='Lpg (2)'!C17 -> 85 | L13: ='Lpg (2)'!D17 -> 66 | M13: ='Lpg (2)'!G17 -> 36.3 | N13: =D13*1.4 -> 1163.778 | O13: =E13*1.4 -> 0 | P13: ='[1]Lpg (2)'!#REF! -> #REF! | Q13: ='[1]Summery Report'!#REF! -> #REF! | R13: =N13/B13 -> #DIV/0! | S13: =Q13/B13 -> #REF!
A14: =Gen!B19 -> 43930 | B14: ='Summery Report'!E13 -> 0 | C14: =Gen!U19 -> 1882 | D14: =Gen!T19 -> 806.32 | E14: =Gen!AK19 -> 0 | F14: =Gen!AS19 -> 806.32 | G14: ='Utility report '!AC14 -> 7 | H14: ='Utility report '!AE14 -> 26 | I14: ='Water-Meter'!E14 -> 33 | J14: ='Lpg (2)'!B18 -> 13 | K14: ='Lpg (2)'!C18 -> 85 | L14: ='Lpg (2)'!D18 -> 66 | M14: ='Lpg (2)'!G18 -> 25.916 | N14: =D14*1.4 -> 1128.848 | O14: =E14*1.4 -> 0 | P14: ='[1]Lpg (2)'!#REF! -> #REF! | Q14: ='[1]Summery Report'!#REF! -> #REF! | R14: =N14/B14 -> #DIV/0! | S14: =Q14/B14 -> #REF!
A15: =Gen!B20 -> 43931 | B15: ='Summery Report'!E14 -> 0 | C15: =Gen!U20 -> 1935 | D15: =Gen!T20 -> 823.75 | E15: =Gen!AK20 -> 0 | F15: =Gen!AS20 -> 823.75 | G15: ='Utility report '!AC15 -> 44 | H15: ='Utility report '!AE15 -> 26 | I15: ='Water-Meter'!E15 -> 55 | J15: ='Lpg (2)'!B19 -> 12 | K15: ='Lpg (2)'!C19 -> 85 | L15: ='Lpg (2)'!D19 -> 66 | M15: ='Lpg (2)'!G19 -> 34.54 | N15: =D15*1.4 -> 1153.25 | O15: =E15*1.4 -> 0 | P15: ='[1]Lpg (2)'!#REF! -> #REF! | Q15: ='[1]Summery Report'!#REF! -> #REF! | R15: =N15/B15 -> #DIV/0! | S15: =Q15/B15 -> #REF!
A16: =Gen!B21 -> 43932 | B16: ='Summery Report'!E15 -> 0 | C16: =Gen!U21 -> 1883 | D16: =Gen!T21 -> 782.67 | E16: =Gen!AK21 -> 0 | F16: =Gen!AS21 -> 782.67 | G16: ='Utility report '!AC16 -> 75 | H16: ='Utility report '!AE16 -> 28 | I16: ='Water-Meter'!E16 -> 56 | J16: ='Lpg (2)'!B20 -> 12 | K16: ='Lpg (2)'!C20 -> 85 | L16: ='Lpg (2)'!D20 -> 66 | M16: ='Lpg (2)'!G20 -> 38.412 | N16: =D16*1.4 -> 1095.738 | O16: =E16*1.4 -> 0 | P16: ='[1]Lpg (2)'!#REF! -> #REF! | Q16: ='[1]Summery Report'!#REF! -> #REF! | R16: =N16/B16 -> #DIV/0! | S16: =Q16/B16 -> #REF!
A17: =Gen!B22 -> 43933 | B17: ='Summery Report'!E16 -> 0 | C17: =Gen!U22 -> 1877 | D17: =Gen!T22 -> 776.8 | E17: =Gen!AK22 -> 0 | F17: =Gen!AS22 -> 776.8 | G17: ='Utility report '!AC17 -> 49 | H17: ='Utility report '!AE17 -> 24 | I17: ='Water-Meter'!E17 -> 41 | J17: ='Lpg (2)'!B21 -> 8 | K17: ='Lpg (2)'!C21 -> 85 | L17: ='Lpg (2)'!D21 -> 66 | M17: ='Lpg (2)'!G21 -> 35.2 | N17: =D17*1.4 -> 1087.52 | O17: =E17*1.4 -> 0 | P17: ='[1]Lpg (2)'!#REF! -> #REF! | Q17: ='[1]Summery Report'!#REF! -> #REF! | R17: =N17/B17 -> #DIV/0! | S17: =Q17/B17 -> #REF!
A18: =Gen!B23 -> 43934 | B18: ='Summery Report'!E17 -> 0 | C18: =Gen!U23 -> 1796 | D18: =Gen!T23 -> 771.72 | E18: =Gen!AK23 -> 19.86 | F18: =Gen!AS23 -> 791.58 | G18: ='Utility report '!AC18 -> 50 | H18: ='Utility report '!AE18 -> 31 | I18: ='Water-Meter'!E18 -> 45 | J18: ='Lpg (2)'!B22 -> 8 | K18: ='Lpg (2)'!C22 -> 85 | L18: ='Lpg (2)'!D22 -> 66 | M18: ='Lpg (2)'!G22 -> 36.036 | N18: =D18*1.4 -> 1080.408 | O18: =E18*1.4 -> 27.804 | P18: ='[1]Lpg (2)'!#REF! -> #REF! | Q18: ='[1]Summery Report'!#REF! -> #REF! | R18: =N18/B18 -> #DIV/0! | S18: =Q18/B18 -> #REF!
... A32: =Gen!B37 -> 43948 | B32: ='Summery Report'!E31 -> 0 | C32: =Gen!U37 -> 1721 | D32: =Gen!T37 -> 716.78 | E32: =Gen!AK37 -> 7.38 | F32: =Gen!AS37 -> 724.16 | G32: ='Utility report '!AC32 -> 58 | H32: ='Utility report '!AE32 -> 52 | I32: ='Water-Meter'!E32 -> 30 | J32: ='Lpg (2)'!B36 -> 85 | K32: ='Lpg (2)'!C36 -> 85 | L32: ='Lpg (2)'!D36 -> 55 | M32: ='Lpg (2)'!G36 -> 28.6 | N32: =D32*1.4 -> 1003.492 | O32: =E32*1.4 -> 10.332 | P32: ='[1]Lpg (2)'!#REF! -> #REF! | Q32: ='[1]Summery Report'!#REF! -> #REF! | R32: =N32/B32 -> #DIV/0! | S32: =Q32/B32 -> #REF!
A33: =Gen!B38 -> 43949 | B33: ='Summery Report'!E32 -> 0 | C33: =Gen!U38 -> 1637 | D33: =Gen!T38 -> 690.55 | E33: =Gen!AK38 -> 100 | F33: =Gen!AS38 -> 790.55 | G33: ='Utility report '!AC33 -> 0 | H33: ='Utility report '!AE33 -> 47 | I33: ='Water-Meter'!E33 -> 31 | J33: ='Lpg (2)'!B37 -> 85 | K33: ='Lpg (2)'!C37 -> 85 | L33: ='Lpg (2)'!D37 -> 53 | M33: ='Lpg (2)'!G37 -> 31.24 | N33: =D33*1.4 -> 966.77 | O33: =E33*1.4 -> 140 | P33: ='[1]Lpg (2)'!#REF! -> #REF! | Q33: ='[1]Summery Report'!#REF! -> #REF! | R33: =N33/B33 -> #DIV/0! | S33: =Q33/B33 -> #REF! | T33: =3124/13 -> 240.30769
A34: =Gen!B39 -> 43950 | B34: ='Summery Report'!E33 -> 0 | C34: =Gen!U39 -> 1644 | D34: =Gen!T39 -> 691.09 | E34: =Gen!AK39 -> 38.11 | F34: =Gen!AS39 -> 729.2 | G34: ='Utility report '!AC34 -> 83 | H34: ='Utility report '!AE34 -> 42 | I34: ='Water-Meter'!E34 -> 29 | J34: ='Lpg (2)'!B38 -> 85 | K34: ='Lpg (2)'!C38 -> 85 | L34: ='Lpg (2)'!D38 -> 50 | M34: ='Lpg (2)'!G38 -> 40.92 | N34: =D34*1.4 -> 967.526 | O34: =E34*1.4 -> 53.354 | P34: ='[1]Lpg (2)'!#REF! -> #REF! | Q34: ='[1]Summery Report'!#REF! -> #REF! | R34: =N34/B34 -> #DIV/0! | S34: =Q34/B34 -> #REF!
A35: =Gen!B40 -> 43951 | B35: ='Summery Report'!E34 -> 0 | C35: =Gen!U40 -> 1564 | D35: =Gen!T40 -> 660.76 | E35: =Gen!AK40 -> 0 | F35: =Gen!AS40 -> 660.76 | G35: ='Utility report '!AC35 -> 0 | H35: ='Utility report '!AE35 -> 70 | I35: ='Water-Meter'!E35 -> 29 | J35: ='Lpg (2)'!B39 -> 85 | K35: ='Lpg (2)'!C39 -> 85 | L35: ='Lpg (2)'!D39 -> 48 | M35: ='Lpg (2)'!G39 -> 17.424 | N35: =D35*1.4 -> 925.064 | O35: =E35*1.4 -> 0 | P35: ='[1]Lpg (2)'!#REF! -> #REF! | Q35: ='[1]Summery Report'!#REF! -> #REF! | R35: =N35/B35 -> #DIV/0! | S35: =Q35/B35 -> #REF!
A36: =Gen!B41 -> 0 | B36: ='Summery Report'!E35 -> 0 | C36: =Gen!U41 -> 0 | D36: =Gen!T41 -> 0 | E36: =Gen!AK41 -> 0 | F36: =Gen!AS41 -> 0 | G36: ='Utility report '!AC36 -> -31534 | H36: ='Utility report '!AE36 -> -200738 | I36: ='Water-Meter'!E36 -> 0 | J36: ='Lpg (2)'!B40 -> 85 | K36: ='Lpg (2)'!C40 -> 85 | L36: ='Lpg (2)'!D40 -> 45 | M36: ='Lpg (2)'!G40 -> 27.852 | N36: =D36*1.4 -> 0 | O36: =E36*1.4 -> 0 | P36: ='[1]Lpg (2)'!#REF! -> #REF! | Q36: ='[1]Summery Report'!#REF! -> #REF! | R36: =N36/B36 -> #DIV/0! | S36: =Q36/B36 -> #REF!
A37: =Gen!B42 -> 0 | B37: ='Summery Report'!E36 -> 0 | C37: =Gen!U42 -> 0 | D37: =Gen!T42 -> 0 | E37: =Gen!AK42 -> 0 | F37: =Gen!AS42 -> 0 | G37: ='Utility report '!AC37 -> 0 | H37: ='Utility report '!AE37 -> 0 | I37: ='Water-Meter'!E37 -> 0 | J37: ='Lpg (2)'!B41 -> 0 | K37: ='Lpg (2)'!C41 -> 0 | L37: ='Lpg (2)'!D41 -> 0 | M37: ='Lpg (2)'!G41 -> 0 | Q37: ='[1]Summery Report'!#REF! -> #REF! | R37: =N37/B37 -> #DIV/0! | S37: =Q37/B37 -> #REF!
A39: Total | B39: =SUM(B7:B37) -> 0 | C39: =SUM(C7:C35) -> 51720 | D39: =SUM(D7:D35) -> 21971.81 | E39: =SUM(E7:E35) -> 1809.04 | F39: =SUM(F7:F35) -> 23780.85 | G39: =SUM(G7:G35) -> 1285 | H39: =SUM(H7:H35) -> 1245 | I39: =SUM(I7:I35) -> 1122 | J39: =SUM(J7:J35) -> 946 | ... S39: =SUM(S7:S35) -> #REF!

Sheet Utility report 
A1: DAILY UTILITY REPORT March 2020
A2: Date | B2: Total occupancy | H2: Diesel balance LTS | I2: Diesel Deliveries | J2: Gen.Diesel consumption LTS | L2: Total Diesel consumption LTS | M2: Water Meter reading | N2: Water consumption m³ | O2: R.O WATER PRODUCTION LTRS + TIME | AA2: Total RO production | AB2: RO Meter reading | AD2: 0 | AE2: STP | AF2: GAS TANK A | AG2: GAS TANK B | AH2: GAS TANK C | AI2: Total Gas Tanks | AJ2: Kg /day | AK2: TOTAL GAS cons.
A3: Rate Tsh /$ | B3: 1640 | C3: Diesel cost / lits | D3: 2175 | F3: =SUM(D3/B3) -> 1.3262195 | H3: =Gen!D11 -> 41048.87 | K3: Transport consumption | M3: Balance | O3: PLANT NO 1 | S3: PLANT NO 2 | W3: PLANT NO 3 | AA3: /day | AB3: Balance | AC3: Production | AD3: 0 | AE3: Production | AF3: Capacity | AG3: Capacity | AH3: Capacity | AI3: Kg | AJ3: /day | AK3: /day
B4: Rooms OCC | C4: % | D4: Guest Rooms Occ | F4: Electricity Production Cost /Room Occ by guest | G4: All Cost /Room Occ by guest | O4: Flow M3 | P4: Reading Hours Meter | Q4: Hrs | R4: total production M3 | S4: Flow M3 | T4: Reading Hours Meter | U4: Hrs | V4: total production M3 | W4: Flow M3 | X4: READING HOURS METER | Y4: Hrs | Z4: total production M3 | AA4: M3 | AC4: M3 | AE4: M3 | AF4: 2000 | AG4: 1000 | AH4: 1000 | AI4: =SUM([2]Sheet1!$AA$36) -> 950 | AJ4: Kg | AK4: M3
P5: 19027 | T5: 16086 | X5: 24240 | AB5: 30249 | AD5: 199465 | AF5: 0.85 | AG5: 0.85 | AH5: 0.85
A6: =Gen!B11 -> 43922 | B6: ='Summery Report'!E5 -> 0 | C6: =Gen!C11 -> 0 | D6: ='Summery Report'!E5 -> 0 | E6: =SUM(F3) -> 1.3262195 | F6: =SUM(J6*E6)/D6 -> #DIV/0! | G6: =SUM(L6*E6)/D6 -> #DIV/0! | H6: =Gen!D11 -> 41048.87 | I6: =Gen!F11 -> 0 | J6: =Gen!T11 -> 850.96 | K6: =Gen!AK11 -> 49.37 | L6: =SUM(J6:K6) -> 900.33 | M6: ='Water-Meter'!K46 -> 434.92781 | N6: ='Water-Meter'!E6 -> 38 | P6: 19027 | Q6: =SUM(P6-P5) -> 0 | R6: =SUM(Q6*O6) -> 0 | T6: 16086 | U6: =T6-T5 -> 0 | V6: - | X6: 24240 | Y6: =X6-X5 -> 0 | Z6: =Y6-Y5 -> 0 | AA6: =Z6-Z5 -> 0 | AB6: 30249 | AC6: =AB6-AB5 -> 0 | AD6: 199493 | AE6: =AD6-AD5 -> 28 | AF6: ='Lpg (2)'!B10*2000/85 -> 376.47059 | AG6: ='Lpg (2)'!C10*1000/85 -> 1000 | AH6: ='Lpg (2)'!D10*1000/85 -> 776.47059 | AI6: =SUM(AF6*2000)+(AG6*1000)+(AH6*1000) -> 2529411.8 | AJ6: =SUM(AI5-AI6) -> -2529411.8
A7: =Gen!B12 -> 43923 | B7: ='Summery Report'!E6 -> 0 | C7: =Gen!C12 -> 0 | D7: ='Summery Report'!E6 -> 0 | E7: =SUM(E6) -> 1.3262195 | F7: =SUM(J7*E7)/D7 -> #DIV/0! | G7: =SUM(L7*E7)/D7 -> #DIV/0! | H7: =Gen!D12 -> 40148.54 | I7: =Gen!F12 -> 0 | J7: =Gen!T12 -> 866.25 | K7: =Gen!AK12 -> 9.39 | L7: =SUM(J7:K7) -> 875.64 | M7: ='Water-Meter'!K47 -> 503.07762 | N7: ='Water-Meter'!E7 -> 52 | O7: 2.3 | P7: 19029 | Q7: =SUM(P7-P6) -> 2 | R7: =SUM(Q7*O7) -> 4.6 | T7: 16086 | U7: =T7-T6 -> 0 | V7: =SUM(U7*S7) -> 0 | W7: 2.4 | X7: 24259 | Y7: =X7-X6 -> 19 | Z7: =SUM(Y7*W7) -> 45.6 | AA7: =SUM(Z7*X9) -> 1108399.2 | AB7: 30297 | AC7: =AB7-AB6 -> 48 | AD7: 199522 | AE7: =AD7-AD6 -> 29 | AF7: ='Lpg (2)'!B11*2000/85 -> 376.47059 | AG7: ='Lpg (2)'!C11*1000/85 -> 1000 | AH7: ='Lpg (2)'!D11*1000/85 -> 776.47059 | AI7: =SUM(AF6*2000)+(AG7*1000)+(AH7*1000) -> 2529411.8 | AJ7: =SUM(AI6-AI7) -> 0
A8: =Gen!B13 -> 43924 | B8: ='Summery Report'!E7 -> 0 | C8: =Gen!C13 -> 0 | D8: ='Summery Report'!E7 -> 0 | E8: =SUM(E7) -> 1.3262195 | F8: =SUM(J8*E8)/D8 -> #DIV/0! | G8: =SUM(L8*E8)/D8 -> #DIV/0! | H8: =Gen!D13 -> 39272.9 | I8: =Gen!F13 -> 0 | J8: =Gen!T13 -> 832.92 | K8: =Gen!AK13 -> 18.02 | L8: =SUM(J8:K8) -> 850.94 | M8: ='Water-Meter'!K48 -> 507.01618 | N8: ='Water-Meter'!E8 -> 26 | P8: 19029 | Q8: =SUM(P8-P7) -> 0 | R8: =SUM(Q8*O8) -> 0 | T8: 16086 | U8: =T8-T7 -> 0 | V8: =SUM(U8*S8) -> 0 | W8: 2.5 | X8: 24283 | Y8: =X8-X7 -> 24 | Z8: =SUM(Y8*W8) -> 60 | AA8: =SUM(Z8*X10) -> 1459860 | AB8: 30356 | AC8: =AB8-AB7 -> 59 | AD8: 199541 | AE8: =AD8-AD7 -> 19 | AF8: ='Lpg (2)'!B12*2000/85 -> 352.94118 | AG8: ='Lpg (2)'!C12*1000/85 -> 1000 | AH8: ='Lpg (2)'!D12*1000/85 -> 776.47059 | AI8: =SUM(AF7*2000)+(AG8*1000)+(AH8*1000) -> 2529411.8 | AJ8: =SUM(AI7-AI8) -> 0
A9: =Gen!B14 -> 43925 | B9: ='Summery Report'!E8 -> 0 | C9: =Gen!C14 -> 0 | D9: ='Summery Report'!E8 -> 0 | E9: =SUM(E8) -> 1.3262195 | F9: =SUM(J9*E9)/D9 -> #DIV/0! | G9: =SUM(L9*E9)/D9 -> #DIV/0! | H9: =Gen!D14 -> 38421.96 | I9: =Gen!F14 -> 0 | J9: =Gen!T14 -> 789.55 | K9: =Gen!AK14 -> 660.37 | L9: =SUM(J9:K9) -> 1449.92 | M9: ='Water-Meter'!K49 -> 518.72347 | N9: ='Water-Meter'!E9 -> 34 | P9: 19029 | Q9: =SUM(P9-P8) -> 0 | R9: =SUM(Q9*O9) -> 0 | T9: 16086 | U9: =T9-T8 -> 0 | V9: =SUM(U9*S9) -> 0 | W9: 2.6 | X9: 24307 | Y9: =X9-X8 -> 24 | Z9: =SUM(Y9*W9) -> 62.4 | AA9: =SUM(Z9*X11) -> 1519315.2 | AB9: 30413 | AC9: =AB9-AB8 -> 57 | AD9: 199541 | AE9: =AD9-AD8 -> 0 | AF9: ='Lpg (2)'!B13*2000/85 -> 329.41176 | AG9: ='Lpg (2)'!C13*1000/85 -> 1000 | AH9: ='Lpg (2)'!D13*1000/85 -> 776.47059 | AI9: =SUM(AF8*2000)+(AG9*1000)+(AH9*1000) -> 2482352.9 | AJ9: =SUM(AI8-AI9) -> 47058.824
A10: =Gen!B15 -> 43926 | B10: ='Summery Report'!E9 -> 0 | C10: =Gen!C15 -> 0 | D10: ='Summery Report'!E9 -> 0 | E10: =SUM(E9) -> 1.3262195 | F10: =SUM(J10*E10)/D10 -> #DIV/0! | G10: =SUM(L10*E10)/D10 -> #DIV/0! | H10: =Gen!D15 -> 36972.04 | I10: =Gen!F15 -> 0 | J10: =Gen!T15 -> 813.34 | K10: =Gen!AK15 -> 34.28 | L10: =SUM(J10:K10) -> 847.62 | M10: ='Water-Meter'!K50 -> 497.30897 | N10: ='Water-Meter'!E10 -> 42 | P10: 19029 | Q10: =SUM(P10-P9) -> 0 | R10: =SUM(Q10*O10) -> 0 | T10: 16086 | U10: =T10-T9 -> 0 | V10: =SUM(U10*S10) -> 0 | W10: 2.6 | X10: 24331 | Y10: =X10-X9 -> 24 | Z10: =SUM(Y10*W10) -> 62.4 | AA10: =SUM(Z10*X12) -> 1520812.8 | AB10: 30470 | AC10: =AB10-AB9 -> 57 | AD10: 199589 | AE10: =AD10-AD9 -> 48 | AF10: ='Lpg (2)'!B14*2000/85 -> 305.88235 | AG10: ='Lpg (2)'!C14*1000/85 -> 1000 | AH10: ='Lpg (2)'!D14*1000/85 -> 776.47059 | AI10: =SUM(AF9*2000)+(AG10*1000)+(AH10*1000) -> 2435294.1 | AJ10: =SUM(AI9-AI10) -> 47058.824
A11: =Gen!B16 -> 43927 | B11: ='Summery Report'!E10 -> 0 | C11: =Gen!C16 -> 0 | D11: ='Summery Report'!E10 -> 0 | E11: =SUM(E10) -> 1.3262195 | F11: =SUM(J11*E11)/D11 -> #DIV/0! | G11: =SUM(L11*E11)/D11 -> #DIV/0! | H11: =Gen!D16 -> 36124.42 | I11: =Gen!F16 -> 15000 | J11: =Gen!T16 -> 757.53 | K11: =Gen!AK16 -> 0 | L11: =SUM(J11:K11) -> 757.53 | M11: ='Water-Meter'!K51 -> 469.85871 | N11: ='Water-Meter'!E11 -> 41 | P11: 19029 | Q11: =SUM(P11-P10) -> 0 | R11: =SUM(Q11*O11) -> 0 | T11: 16086 | U11: =T11-T10 -> 0 | V11: =SUM(U11*S11) -> 0 | W11: 2.7 | X11: 24348 | Y11: =X11-X10 -> 17 | Z11: =SUM(Y11*W11) -> 45.9 | AA11: =SUM(Z11*X13) -> 1119730.5 | AB11: 30508 | AC11: =AB11-AB10 -> 38 | AD11: 199607 | AE11: =AD11-AD10 -> 18 | AF11: ='Lpg (2)'!B15*2000/85 -> 305.88235 | AG11: ='Lpg (2)'!C15*1000/85 -> 1000 | AH11: ='Lpg (2)'!D15*1000/85 -> 776.47059 | AI11: =SUM(AF10*2000)+(AG11*1000)+(AH11*1000) -> 2388235.3 | AJ11: =SUM(AI10-AI11) -> 47058.824
A12: =Gen!B17 -> 43928 | B12: ='Summery Report'!E11 -> 0 | C12: =Gen!C17 -> 0 | D12: ='Summery Report'!E11 -> 0 | E12: =SUM(E11) -> 1.3262195 | F12: =SUM(J12*E12)/D12 -> #DIV/0! | G12: =SUM(L12*E12)/D12 -> #DIV/0! | H12: =Gen!D17 -> 50366.89 | I12: =Gen!F17 -> 0 | J12: =Gen!T17 -> 783.55 | K12: =Gen!AK17 -> 108.2 | L12: =SUM(J12:K12) -> 891.75 | M12: ='Water-Meter'!K52 -> 471.68466 | N12: ='Water-Meter'!E12 -> 47 | P12: 19029 | Q12: =SUM(P12-P11) -> 0 | R12: =SUM(Q12*O12) -> 0 | T12: 16086 | U12: =T12-T11 -> 0 | V12: =SUM(U12*S12) -> 0 | W12: 2.2 | X12: 24372 | Y12: =X12-X11 -> 24 | Z12: =SUM(Y12*W12) -> 52.8 | AA12: =SUM(Z12*X14) -> 1288267.2 | AB12: 30561 | AC12: =AB12-AB11 -> 53 | AD12: 199639 | AE12: =AD12-AD11 -> 32 | AF12: ='Lpg (2)'!B16*2000/85 -> 305.88235 | AG12: ='Lpg (2)'!C16*1000/85 -> 1000 | AH12: ='Lpg (2)'!D16*1000/85 -> 776.47059 | AI12: =SUM(AF11*2000)+(AG12*1000)+(AH12*1000) -> 2388235.3 | AJ12: =SUM(AI11-AI12) -> 0
A13: =Gen!B18 -> 43929 | B13: ='Summery Report'!E12 -> 0 | C13: =Gen!C18 -> 0 | D13: ='Summery Report'!E12 -> 0 | E13: =SUM(E12) -> 1.3262195 | F13: =SUM(J13*E13)/D13 -> #DIV/0! | G13: =SUM(L13*E13)/D13 -> #DIV/0! | H13: =Gen!D18 -> 49475.14 | I13: =Gen!F18 -> 0 | J13: =Gen!T18 -> 831.27 | K13: =Gen!AK18 -> 0 | L13: =SUM(J13:K13) -> 831.27 | M13: ='Water-Meter'!K53 -> 483.60145 | N13: ='Water-Meter'!E13 -> 36 | O13: 2.4 | P13: 19030 | Q13: =SUM(P13-P12) -> 1 | R13: =SUM(Q13*O13) -> 2.4 | T13: 16086 | U13: =T13-T12 -> 0 | V13: =SUM(U13*S13) -> 0 | W13: 2.3 | X13: 24395 | Y13: =X13-X12 -> 23 | Z13: =SUM(Y13*W13) -> 52.9 | AA13: =SUM(Z13*X15) -> 1291818 | AB13: 30611 | AC13: =AB13-AB12 -> 50 | AD13: 199667 | AE13: =AD13-AD12 -> 28 | AF13: ='Lpg (2)'!B17*2000/85 -> 305.88235 | AG13: ='Lpg (2)'!C17*1000/85 -> 1000 | AH13: ='Lpg (2)'!D17*1000/85 -> 776.47059 | AI13: =SUM(AF12*2000)+(AG13*1000)+(AH13*1000) -> 2388235.3 | AJ13: =SUM(AI12-AI13) -> 0
A14: =Gen!B19 -> 43930 | B14: ='Summery Report'!E13 -> 0 | C14: =Gen!C19 -> 0 | D14: ='Summery Report'!E13 -> 0 | E14: =SUM(E13) -> 1.3262195 | F14: =SUM(J14*E14)/D14 -> #DIV/0! | G14: =SUM(L14*E14)/D14 -> #DIV/0! | H14: =Gen!D19 -> 48643.87 | I14: =Gen!F19 -> 0 | J14: =Gen!T19 -> 806.32 | K14: =Gen!AK19 -> 0 | L14: =SUM(J14:K14) -> 806.32 | M14: ='Water-Meter'!K54 -> 541.48315 | N14: ='Water-Meter'!E14 -> 33 | P14: 19030 | Q14: =SUM(P14-P13) -> 0 | R14: =SUM(Q14*O14) -> 0 | T14: 16086 | U14: =T14-T13 -> 0 | V14: =SUM(U14*S14) -> 0 | W14: 2.3 | X14: 24399 | Y14: =X14-X13 -> 4 | Z14: =SUM(Y14*W14) -> 9.2 | AA14: =SUM(Z14*X16) -> 224664 | AB14: 30618 | AC14: =AB14-AB13 -> 7 | AD14: 199693 | AE14: =AD14-AD13 -> 26 | AF14: ='Lpg (2)'!B18*2000/85 -> 305.88235 | AG14: ='Lpg (2)'!C18*1000/85 -> 1000 | AH14: ='Lpg (2)'!D18*1000/85 -> 776.47059 | AI14: =SUM(AF13*2000)+(AG14*1000)+(AH14*1000) -> 2388235.3 | AJ14: =SUM(AI13-AI14) -> 0
A15: =Gen!B20 -> 43931 | B15: ='Summery Report'!E14 -> 0 | C15: =Gen!C20 -> 0 | D15: ='Summery Report'!E14 -> 0 | E15: =SUM(E14) -> 1.3262195 | F15: =SUM(J15*E15)/D15 -> #DIV/0! | G15: =SUM(L15*E15)/D15 -> #DIV/0! | H15: =Gen!D20 -> 47837.55 | I15: =Gen!F20 -> 0 | J15: =Gen!T20 -> 823.75 | K15: =Gen!AK20 -> 0 | L15: =SUM(J15:K15) -> 823.75 | M15: ='Water-Meter'!K55 -> 600.59466 | N15: ='Water-Meter'!E15 -> 55 | P15: 19030 | Q15: =SUM(P15-P14) -> 0 | R15: =SUM(Q15*O15) -> 0 | T15: 16086 | U15: =T15-T14 -> 0 | V15: =SUM(U15*S15) -> 0 | W15: 2.3 | X15: 24420 | Y15: =X15-X14 -> 21 | Z15: =SUM(Y15*W15) -> 48.3 | AA15: =SUM(Z15*X17) -> 1179727.5 | AB15: 30662 | AC15: =AB15-AB14 -> 44 | AD15: 199719 | AE15: =AD15-AD14 -> 26 | AF15: ='Lpg (2)'!B19*2000/85 -> 282.35294 | AG15: ='Lpg (2)'!C19*1000/85 -> 1000 | AH15: ='Lpg (2)'!D19*1000/85 -> 776.47059 | AI15: =SUM(AF15*2000)+(AG15*1000)+(AH15*1000) -> 2341176.5 | AJ15: =SUM(AI14-AI15) -> 47058.824
A16: =Gen!B21 -> 43932 | B16: ='Summery Report'!E15 -> 0 | C16: =Gen!C21 -> 0 | D16: ='Summery Report'!E15 -> 0 | E16: =SUM(E15) -> 1.3262195 | F16: =SUM(J16*E16)/D16 -> #DIV/0! | G16: =SUM(L16*E16)/D16 -> #DIV/0! | H16: =Gen!D21 -> 47013.8 | I16: =Gen!F21 -> 0 | J16: =Gen!T21 -> 782.67 | K16: =Gen!AK21 -> 0 | L16: =SUM(J16:K16) -> 782.67 | M16: ='Water-Meter'!K56 -> 588.54041 | N16: ='Water-Meter'!E16 -> 56 | P16: 19030 | Q16: =SUM(P16-P15) -> 0 | R16: =SUM(Q16*O16) -> 0 | S16: 8.1 | T16: 16095 | U16: =T16-T15 -> 9 | V16: =SUM(U16*S16) -> 72.9 | X16: 24420 | Y16: =X16-X15 -> 0 | Z16: =SUM(Y16*W16) -> 0 | AA16: =SUM(Z16*X18) -> 0 | AB16: 30737 | AC16: =AB16-AB15 -> 75 | AD16: 199747 | AE16: =AD16-AD15 -> 28 | AF16: ='Lpg (2)'!B20*2000/85 -> 282.35294 | AG16: ='Lpg (2)'!C20*1000/85 -> 1000 | AH16: ='Lpg (2)'!D20*1000/85 -> 776.47059 | AI16: =SUM(AF16*2000)+(AG16*1000)+(AH16*1000) -> 2341176.5 | AJ16: =SUM(AI15-AI16) -> 0
A17: =Gen!B22 -> 43933 | B17: ='Summery Report'!E16 -> 0 | C17: =Gen!C22 -> 0 | D17: ='Summery Report'!E16 -> 0 | E17: =SUM(E16) -> 1.3262195 | F17: =SUM(J17*E17)/D17 -> #DIV/0! | G17: =SUM(L17*E17)/D17 -> #DIV/0! | H17: =Gen!D22 -> 46231.13 | I17: =Gen!F22 -> 0 | J17: =Gen!T22 -> 776.8 | K17: =Gen!AK22 -> 0 | L17: =SUM(J17:K17) -> 776.8 | M17: ='Water-Meter'!K57 -> 557.22322 | N17: ='Water-Meter'!E17 -> 41 | P17: 19030 | Q17: =SUM(P18-P16) -> 0 | R17: =SUM(Q17*O17) -> 0 | S17: 8.2 | T17: 16101 | U17: =T17-T16 -> 6 | V17: =SUM(U17*S17) -> 49.2 | X17: 24425 | Y17: =X17-X16 -> 5 | Z17: =SUM(Y17*W17) -> 0 | AA17: =SUM(Z17*X19) -> 0 | AB17: 30786 | AC17: =AB17-AB16 -> 49 | AD17: 199771 | AE17: =AD17-AD16 -> 24 | AF17: ='Lpg (2)'!B21*2000/85 -> 188.23529 | AG17: ='Lpg (2)'!C21*1000/85 -> 1000 | AH17: ='Lpg (2)'!D21*1000/85 -> 776.47059 | AI17: =SUM(AF17*2000)+(AG17*1000)+(AH17*1000) -> 2152941.2 | AJ17: =SUM(AI16-AI17) -> 188235.29
A18: =Gen!B23 -> 43934 | B18: ='Summery Report'!E17 -> 0 | C18: =Gen!C23 -> 0 | D18: ='Summery Report'!E17 -> 0 | E18: =SUM(E17) -> 1.3262195 | F18: =SUM(J18*E18)/D18 -> #DIV/0! | G18: =SUM(L18*E18)/D18 -> #DIV/0! | H18: =Gen!D23 -> 45454.33 | I18: =Gen!F23 -> 0 | J18: =Gen!T23 -> 771.72 | K18: =Gen!AK23 -> 19.86 | L18: =SUM(J18:K18) -> 791.58 | M18: ='Water-Meter'!K58 -> 543.27387 | N18: ='Water-Meter'!E18 -> 45 | P18: 19030 | R18: =SUM(Q18*O18) -> 0 | S18: 7.9 | T18: 16107 | U18: =T18-T17 -> 6 | V18: =SUM(U18*S18) -> 47.4 | X18: 24425 | Y18: =X18-X17 -> 0 | Z18: =SUM(Y18*W18) -> 0 | AA18: =SUM(Z18*X20) -> 0 | AB18: 30836 | AC18: =AB18-AB17 -> 50 | AD18: 199802 | AE18: =AD18-AD17 -> 31 | AF18: ='Lpg (2)'!B22*2000/85 -> 188.23529 | AG18: ='Lpg (2)'!C22*1000/85 -> 1000 | AH18: ='Lpg (2)'!D22*1000/85 -> 776.47059 | AI18: =SUM(AF18*2000)+(AG18*1000)+(AH18*1000) -> 2152941.2 | AJ18: =SUM(AI17-AI18) -> 0
A19: =Gen!B24 -> 43935 | B19: ='Summery Report'!E18 -> 0 | C19: =Gen!C24 -> 0 | D19: ='Summery Report'!E18 -> 0 | E19: =SUM(E18) -> 1.3262195 | F19: =SUM(J19*E19)/D19 -> #DIV/0! | G19: =SUM(L19*E19)/D19 -> #DIV/0! | H19: =Gen!D24 -> 44662.75 | I19: =Gen!F24 -> 0 | J19: =Gen!T24 -> 760.62 | K19: =Gen!AK24 -> 0 | L19: =SUM(J19:K19) -> 760.62 | M19: ='Water-Meter'!K59 -> 543.43274 | N19: ='Water-Meter'!E19 -> 51 | P19: 19030 | R19: =SUM(Q19*O19) -> 0 | S19: 8.2 | T19: 16112 | U19: =T19-T18 -> 5 | V19: =SUM(U19*S19) -> 41 | X19: 24425 | Y19: =X19-X18 -> 0 | Z19: =SUM(Y19*W19) -> 0 | AA19: =SUM(Z19*X21) -> 0 | AB19: 30871 | AC19: =AB19-AB18 -> 35 | AD19: 199828 | AE19: =AD19-AD18 -> 26 | AF19: ='Lpg (2)'!B23*2000/85 -> 141.17647 | AG19: ='Lpg (2)'!C23*1000/85 -> 1000 | AH19: ='Lpg (2)'!D23*1000/85 -> 776.47059 | AI19: =SUM(AF19*2000)+(AG19*1000)+(AH19*1000) -> 2058823.5 | AJ19: =SUM(AI18-AI19) -> 94117.647
A20: =Gen!B25 -> 43936 | B20: ='Summery Report'!E19 -> 0 | C20: =Gen!C25 -> 0 | D20: ='Summery Report'!E19 -> 0 | E20: =SUM(E19) -> 1.3262195 | F20: =SUM(J20*E20)/D20 -> #DIV/0! | G20: =SUM(L20*E20)/D20 -> #DIV/0! | H20: =Gen!D25 -> 43902.13 | I20: =Gen!F25 -> 0 | J20: =Gen!T25 -> 786.19 | K20: =Gen!AK25 -> 0 | L20: =SUM(J20:K20) -> 786.19 | M20: ='Water-Meter'!K60 -> 536.76736 | N20: ='Water-Meter'!E20 -> 54 | P20: 19030 | Q20: =SUM(P20-P19) -> 0 | R20: =SUM(Q20*O20) -> 0 | S20: 8.4 | T20: 16118 | U20: =T20-T19 -> 6 | V20: =SUM(U20*S20) -> 50.4 | X20: 24425 | Y20: =X20-X19 -> 0 | Z20: =SUM(Y20*W20) -> 0 | AA20: =SUM(Z20*X22) -> 0 | AB20: 30928 | AC20: =AB20-AB19 -> 57 | AD20: 199872 | AE20: =AD20-AD19 -> 44 | AF20: ='Lpg (2)'!B24*2000/85 -> 117.64706 | AG20: ='Lpg (2)'!C24*1000/85 -> 1000 | AH20: ='Lpg (2)'!D24*1000/85 -> 776.47059 | AI20: =SUM(AF20*2000)+(AG20*1000)+(AH20*1000) -> 2011764.7 | AJ20: =SUM(AI19-AI20) -> 47058.824
A21: =Gen!B26 -> 43937 | B21: ='Summery Report'!E20 -> 0 | C21: =Gen!C26 -> 0 | D21: ='Summery Report'!E20 -> 0 | E21: =SUM(E20) -> 1.3262195 | F21: =SUM(J21*E21)/D21 -> #DIV/0! | G21: =SUM(L21*E21)/D21 -> #DIV/0! | H21: =Gen!D26 -> 43115.94 | I21: =Gen!F26 -> 0 | J21: =Gen!T26 -> 754.27 | K21: =Gen!AK26 -> 0 | L21: =SUM(J21:K21) -> 754.27 | M21: ='Water-Meter'!K61 -> 513.8488 | N21: ='Water-Meter'!E21 -> 54 | P21: 19030 | Q21: =SUM(P21-P20) -> 0 | R21: =SUM(Q21*O21) -> 0 | S21: 8.2 | T21: 16124 | U21: =T21-T20 -> 6 | V21: =SUM(U21*S21) -> 49.2 | X21: 24425 | Y21: =X21-X20 -> 0 | Z21: =SUM(Y21*W21) -> 0 | AA21: =SUM(Z21*X23) -> 0 | AB21: 30972 | AC21: =AB21-AB20 -> 44 | AD21: 199900 | AE21: =AD21-AD20 -> 28 | AF21: ='Lpg (2)'!B25*2000/85 -> 117.64706 | AG21: ='Lpg (2)'!C25*1000/85 -> 1000 | AH21: ='Lpg (2)'!D25*1000/85 -> 776.47059 | AI21: =SUM(AF21*2000)+(AG21*1000)+(AH21*1000) -> 2011764.7 | AJ21: =SUM(AI20-AI21) -> 0
A22: =Gen!B27 -> 43938 | B22: ='Summery Report'!E21 -> 0 | C22: =Gen!C27 -> 0 | D22: ='Summery Report'!E21 -> 0 | E22: =SUM(E21) -> 1.3262195 | F22: =SUM(J22*E22)/D22 -> #DIV/0! | G22: =SUM(L22*E22)/D22 -> #DIV/0! | H22: =Gen!D27 -> 42361.67 | I22: =Gen!F27 -> 0 | J22: =Gen!T27 -> 781.93 | K22: =Gen!AK27 -> 18.45 | L22: =SUM(J22:K22) -> 800.38 | M22: ='Water-Meter'!K62 -> 494.06905 | N22: ='Water-Meter'!E22 -> 42 | P22: 19030 | Q22: =SUM(P22-P21) -> 0 | R22: =SUM(Q22*O22) -> 0 | S22: 8.1 | T22: 16133 | U22: =T22-T21 -> 9 | V22: =SUM(U22*S22) -> 72.9 | X22: 24425 | Y22: =X22-X21 -> 0 | Z22: =SUM(Y22*W22) -> 0 | AA22: =SUM(Z22*X24) -> 0 | AB22: 31040 | AC22: =AB22-AB21 -> 68 | AD22: 199939 | AE22: =AD22-AD21 -> 39 | AF22: ='Lpg (2)'!B26*2000/85 -> 117.64706 | AG22: ='Lpg (2)'!C26*1000/85 -> 1000 | AH22: ='Lpg (2)'!D26*1000/85 -> 776.47059 | AI22: =SUM(AF22*2000)+(AG22*1000)+(AH22*1000) -> 2011764.7 | AJ22: =SUM(AI21-AI22) -> 0
A23: =Gen!B28 -> 43939 | B23: ='Summery Report'!E22 -> 0 | C23: =Gen!C28 -> 0 | D23: ='Summery Report'!E22 -> 0 | E23: =SUM(E22) -> 1.3262195 | F23: =SUM(J23*E23)/D23 -> #DIV/0! | G23: =SUM(L23*E23)/D23 -> #DIV/0! | H23: =Gen!D28 -> 41561.29 | I23: =Gen!F28 -> 0 | J23: =Gen!T28 -> 744.22 | K23: =Gen!AK28 -> 0 | L23: =SUM(J23:K23) -> 744.22 | M23: ='Water-Meter'!K63 -> 481.0404 | N23: ='Water-Meter'!E23 -> 30 | P23: 19030 | Q23: =SUM(P23-P22) -> 0 | R23: =SUM(Q23*O23) -> 0 | S23: 8.3 | T23: 16139 | U23: =T23-T22 -> 6 | V23: =SUM(U23*S23) -> 49.8 | X23: 24425 | Y23: =X23-X22 -> 0 | Z23: =SUM(Y23*W23) -> 0 | AA23: =SUM(Z23*X25) -> 0 | AB23: 31087 | AC23: =AB23-AB22 -> 47 | AD23: 200001 | AE23: =AD23-AD22 -> 62 | AF23: ='Lpg (2)'!B27*2000/85 -> 94.117647 | AG23: ='Lpg (2)'!C27*1000/85 -> 1000 | AH23: ='Lpg (2)'!D27*1000/85 -> 776.47059 | AI23: =SUM(AF23*2000)+(AG23*1000)+(AH23*1000) -> 1964705.9 | AJ23: =SUM(AI22-AI23) -> 47058.824
A24: =Gen!B29 -> 43940 | B24: ='Summery Report'!E23 -> 0 | C24: =Gen!C29 -> 0 | D24: ='Summery Report'!E23 -> 0 | E24: =SUM(E23) -> 1.3262195 | F24: =SUM(J24*E24)/D24 -> #DIV/0! | G24: =SUM(L24*E24)/D24 -> #DIV/0! | H24: =Gen!D29 -> 40817.07 | I24: =Gen!F29 -> 0 | J24: =Gen!T29 -> 740.05 | K24: =Gen!AK29 -> 52.04 | L24: =SUM(J24:K24) -> 792.09 | M24: ='Water-Meter'!K64 -> 493.97483 | N24: ='Water-Meter'!E24 -> 51 | P24: 19030 | Q24: =SUM(P24-P23) -> 0 | R24: =SUM(Q24*O24) -> 0 | T24: 16139 | U24: =T24-T23 -> 0 | V24: =SUM(U24*S24) -> 0 | X24: 24425 | Y24: =X24-X23 -> 0 | Z24: =SUM(Y24*W24) -> 0 | AA24: =SUM(Z24*X26) -> 0 | AB24: 31087 | AC24: =AB24-AB23 -> 0 | AD24: 200070 | AE24: =AD24-AD23 -> 69 | AF24: ='Lpg (2)'!B28*2000/85 -> 47.058824 | AG24: ='Lpg (2)'!C28*1000/85 -> 1000 | AH24: ='Lpg (2)'!D28*1000/85 -> 776.47059 | AI24: =SUM(AF24*2000)+(AG24*1000)+(AH24*1000) -> 1870588.2 | AJ24: =SUM(AI23-AI24) -> 94117.647
A25: =Gen!B30 -> 43941 | B25: ='Summery Report'!E24 -> 0 | C25: =Gen!C30 -> 0 | D25: ='Summery Report'!E24 -> 0 | E25: =SUM(E24) -> 1.3262195 | F25: =SUM(J25*E25)/D25 -> #DIV/0! | G25: =SUM(L25*E25)/D25 -> #DIV/0! | H25: =Gen!D30 -> 40024.98 | I25: =Gen!F30 -> 0 | J25: =Gen!T30 -> 731.47 | K25: =Gen!AK30 -> 0 | L25: =SUM(J25:K25) -> 731.47 | M25: ='Water-Meter'!K65 -> 506.27127 | N25: ='Water-Meter'!E25 -> 35 | P25: 19030 | Q25: =SUM(P25-P24) -> 0 | R25: =SUM(Q25*O25) -> 0 | T25: 16139 | U25: =T25-T24 -> 0 | V25: =SUM(U25*S25) -> 0 | W25: 2.2 | X25: 24445 | Y25: =X25-X24 -> 20 | Z25: =SUM(Y25*W25) -> 44 | AA25: =SUM(Z25*X27) -> 1076944 | AB25: 31133 | AC25: =AB25-AB24 -> 46 | AD25: 200121 | AE25: =AD25-AD24 -> 51 | AF25: ='Lpg (2)'!B29*2000/85 -> 47.058824 | AG25: ='Lpg (2)'!C29*1000/85 -> 1000 | AH25: ='Lpg (2)'!D29*1000/85 -> 776.47059 | AI25: =SUM(AF25*2000)+(AG25*1000)+(AH25*1000) -> 1870588.2 | AJ25: =SUM(AI24-AI25) -> 0
A26: =Gen!B31 -> 43942 | B26: ='Summery Report'!E25 -> 0 | C26: =Gen!C31 -> 0 | D26: ='Summery Report'!E25 -> 0 | E26: =SUM(E25) -> 1.3262195 | F26: =SUM(J26*E26)/D26 -> #DIV/0! | G26: =SUM(L26*E26)/D26 -> #DIV/0! | H26: =Gen!D31 -> 39293.51 | I26: =Gen!F31 -> 0 | J26: =Gen!T31 -> 747.27 | K26: =Gen!AK31 -> 180 | L26: =SUM(J26:K26) -> 927.27 | M26: ='Water-Meter'!K66 -> 484.18481 | N26: ='Water-Meter'!E26 -> 27 | P26: 19030 | Q26: =SUM(P26-P25) -> 0 | R26: =SUM(Q26*O26) -> 0 | T26: 16139 | U26: =T26-T25 -> 0 | V26: =SUM(U26*S26) -> 0 | W26: 2.3 | X26: 24469 | Y26: =X26-X25 -> 24 | Z26: =SUM(Y26*W26) -> 55.2 | AA26: =SUM(Z26*X28) -> 1351075.2 | AB26: 31182 | AC26: =AB26-AB25 -> 49 | AD26: 200162 | AE26: =AD26-AD25 -> 41 | AF26: ='Lpg (2)'!B30*2000/85 -> 47.058824 | AG26: ='Lpg (2)'!C30*1000/85 -> 1000 | AH26: ='Lpg (2)'!D30*1000/85 -> 776.47059 | AI26: =SUM(AF26*2000)+(AG26*1000)+(AH26*1000) -> 1870588.2 | AJ26: =SUM(AI25-AI26) -> 0
A27: =Gen!B32 -> 43943 | B27: ='Summery Report'!E26 -> 0 | C27: =Gen!C32 -> 0 | D27: ='Summery Report'!E26 -> 0 | E27: =SUM(E26) -> 1.3262195 | F27: =SUM(J27*E27)/D27 -> #DIV/0! | G27: =SUM(L27*E27)/D27 -> #DIV/0! | H27: =Gen!D32 -> 38366.24 | I27: =Gen!F32 -> 0 | J27: =Gen!T32 -> 709.13 | K27: =Gen!AK32 -> 123.51 | L27: =SUM(J27:K27) -> 832.64 | M27: ='Water-Meter'!K67 -> 460.25989 | N27: ='Water-Meter'!E27 -> 28 | P27: 19030 | Q27: =SUM(P27-P26) -> 0 | R27: =SUM(Q27*O27) -> 0 | S27: 8.2 | T27: 16145 | U27: =T27-T26 -> 6 | V27: =SUM(U27*S27) -> 49.2 | W27: 2.3 | X27: 24476 | Y27: =X27-X26 -> 7 | Z27: =SUM(Y27*W27) -> 16.1 | AA27: =SUM(Z27*X29) -> 394063.6 | AB27: 31247 | AC27: =AB27-AB26 -> 65 | AD27: 200203 | AE27: =AD27-AD26 -> 41 | AF27: ='Lpg (2)'!B31*2000/85 -> 2000 | AG27: ='Lpg (2)'!C31*1000/85 -> 1000 | AH27: ='Lpg (2)'!D31*1000/85 -> 752.94118 | AI27: =SUM(AF27*2000)+(AG27*1000)+(AH27*1000) -> 5752941.2 | AJ27: =SUM(AI26-AI27) -> -3882352.9
A28: =Gen!B33 -> 43944 | B28: ='Summery Report'!E27 -> 0 | C28: =Gen!C33 -> 0 | D28: ='Summery Report'!E27 -> 0 | E28: =SUM(E27) -> 1.3262195 | F28: =SUM(J28*E28)/D28 -> #DIV/0! | G28: =SUM(L28*E28)/D28 -> #DIV/0! | H28: =Gen!D33 -> 49533.6 | I28: =Gen!F33 -> 12000 | J28: =Gen!T33 -> 670.85 | K28: =Gen!AK33 -> 0 | L28: =SUM(J28:K28) -> 670.85 | M28: ='Water-Meter'!K68 -> 439.2684 | N28: ='Water-Meter'!E28 -> 29 | P28: 19030 | Q28: =SUM(P28-P27) -> 0 | R28: =SUM(Q28*O28) -> 0 | T28: 16145 | U28: =T28-T27 -> 0 | V28: =SUM(U28*S28) -> 0 | X28: 24476 | Y28: =X28-X27 -> 0 | Z28: =SUM(Y28*W28) -> 0 | AA28: =SUM(Z28*X30) -> 0 | AB28: 31247 | AC28: =SUM(AB28-AB27) -> 0 | AD28: 200293 | AE28: =AD28-AD27 -> 90 | AF28: ='Lpg (2)'!B32*2000/85 -> 2000 | AG28: ='Lpg (2)'!C32*1000/85 -> 1000 | AH28: ='Lpg (2)'!D32*1000/85 -> 729.41176 | AI28: =SUM(AF28*2000)+(AG28*1000)+(AH28*1000) -> 5729411.8 | AJ28: =SUM(AI27-AI28) -> 23529.412
A29: =Gen!B34 -> 43945 | B29: ='Summery Report'!E28 -> 0 | C29: =Gen!C34 -> 0 | D29: ='Summery Report'!E28 -> 0 | E29: =SUM(E28) -> 1.3262195 | F29: =SUM(J29*E29)/D29 -> #DIV/0! | G29: =SUM(L29*E29)/D29 -> #DIV/0! | H29: =Gen!D34 -> 48862.75 | I29: =Gen!F34 -> 0 | J29: =Gen!T34 -> 734.77 | K29: =Gen!AK34 -> 254.15 | L29: =SUM(J29:K29) -> 988.92 | M29: ='Water-Meter'!K69 -> 489.05947 | N29: ='Water-Meter'!E29 -> 31 | P29: 19030 | Q29: =SUM(P29-P28) -> 0 | R29: =SUM(Q29*O29) -> 0 | S29: 8.2 | T29: 16153 | U29: =T29-T28 -> 8 | V29: =SUM(U29*S29) -> 65.6 | X29: 24476 | Y29: =X29-X28 -> 0 | Z29: =SUM(Y29*W29) -> 0 | AA29: =SUM(Z29*X31) -> 0 | AB29: 31336 | AC29: =SUM(AB29-AB28) -> 89 | AD29: 200383 | AE29: =AD29-AD28 -> 90 | AF29: ='Lpg (2)'!B33*2000/85 -> 2000 | AG29: ='Lpg (2)'!C33*1000/85 -> 1000 | AH29: ='Lpg (2)'!D33*1000/85 -> 705.88235 | AI29: =SUM(AF29*2000)+(AG29*1000)+(AH29*1000) -> 5705882.4 | AJ29: =SUM(AI28-AI29) -> 23529.412
A30: =Gen!B35 -> 43946 | B30: ='Summery Report'!E29 -> 0 | C30: =Gen!C35 -> 0 | D30: ='Summery Report'!E29 -> 0 | E30: =SUM(E29) -> 1.3262195 | F30: =SUM(J30*E30)/D30 -> #DIV/0! | G30: =SUM(L30*E30)/D30 -> #DIV/0! | H30: =Gen!D35 -> 47873.83 | I30: =Gen!F35 -> 0 | J30: =Gen!T35 -> 708.25 | K30: =Gen!AK35 -> 133.02 | L30: =SUM(J30:K30) -> 841.27 | M30: ='Water-Meter'!K70 -> 452.81705 | N30: ='Water-Meter'!E30 -> 32 | P30: 19030 | Q30: =SUM(P30-P29) -> 0 | R30: =SUM(Q30*O30) -> 0 | S30: 8.2 | T30: 16158 | U30: =T30-T29 -> 5 | V30: =SUM(U30*S30) -> 41 | X30: 24476 | Y30: =X30-X29 -> 0 | Z30: =SUM(Y30*W30) -> 0 | AA30: =SUM(Z30*X32) -> 0 | AB30: 31388 | AC30: =SUM(AB30-AB29) -> 52 | AD30: 200466 | AE30: =AD30-AD29 -> 83 | AF30: ='Lpg (2)'!B34*2000/85 -> 2000 | AG30: ='Lpg (2)'!C34*1000/85 -> 1000 | AH30: ='Lpg (2)'!D34*1000/85 -> 682.35294 | AI30: =SUM(AF30*2000)+(AG30*1000)+(AH30*1000) -> 5682352.9 | AJ30: =SUM(AI29-AI30) -> 23529.412
A31: =Gen!B36 -> 43947 | B31: ='Summery Report'!E30 -> 0 | C31: =Gen!C36 -> 0 | D31: ='Summery Report'!E30 -> 0 | E31: =SUM(E30) -> 1.3262195 | F31: =SUM(J31*E31)/D31 -> #DIV/0! | G31: =SUM(L31*E31)/D31 -> #DIV/0! | H31: =Gen!D36 -> 47032.56 | I31: =Gen!F36 -> 0 | J31: =Gen!T36 -> 707.94 | K31: =Gen!AK36 -> 52.26 | L31: =SUM(J31:K31) -> 760.2 | M31: ='Water-Meter'!K71 -> 442.56732 | N31: ='Water-Meter'!E31 -> 31 | P31: 19030 | Q31: =SUM(P31-P30) -> 0 | R31: =SUM(Q31*O31) -> 0 | S31: 8.2 | T31: 16160 | U31: =T31-T30 -> 2 | V31: =SUM(U31*S31) -> 16.4 | X31: 24476 | Y31: =X31-X30 -> 0 | Z31: =SUM(Y31*W31) -> 0 | AA31: =SUM(Z31*X33) -> 0 | AB31: 31393 | AC31: =SUM(AB31-AB30) -> 5 | AD31: 200527 | AE31: =AD31-AD30 -> 61 | AF31: ='Lpg (2)'!B35*2000/85 -> 2000 | AG31: ='Lpg (2)'!C35*1000/85 -> 1000 | AH31: ='Lpg (2)'!D35*1000/85 -> 658.82353 | AI31: =SUM(AF31*2000)+(AG31*1000)+(AH31*1000) -> 5658823.5 | AJ31: =SUM(AI30-AI31) -> 23529.412
A32: =Gen!B37 -> 43948 | B32: ='Summery Report'!E31 -> 0 | C32: =Gen!C37 -> 0 | D32: ='Summery Report'!E31 -> 0 | E32: =SUM(E31) -> 1.3262195 | F32: =SUM(J32*E32)/D32 -> #DIV/0! | G32: =SUM(L32*E32)/D32 -> #DIV/0! | H32: =Gen!D37 -> 46272.36 | I32: =Gen!F37 -> 0 | J32: =Gen!T37 -> 716.78 | K32: =Gen!AK37 -> 7.38 | L32: =SUM(J32:K32) -> 724.16 | M32: ='Water-Meter'!K72 -> 547.97572 | N32: ='Water-Meter'!E32 -> 30 | P32: 19030 | Q32: =SUM(P32-P31) -> 0 | R32: =SUM(Q32*O32) -> 0 | S32: 8.1 | T32: 16166 | U32: =T32-T31 -> 6 | V32: =SUM(U32*S32) -> 48.6 | X32: 24476 | Y32: =X32-X31 -> 0 | Z32: =SUM(Y32*W32) -> 0 | AA32: =SUM(Z32*X34) -> 0 | AB32: 31451 | AC32: =SUM(AB32-AB31) -> 58 | AD32: 200579 | AE32: =AD32-AD31 -> 52 | AF32: ='Lpg (2)'!B36*2000/85 -> 2000 | AG32: ='Lpg (2)'!C36*1000/85 -> 1000 | AH32: ='Lpg (2)'!D36*1000/85 -> 647.05882 | AI32: =SUM(AF32*2000)+(AG32*1000)+(AH32*1000) -> 5647058.8 | AJ32: =SUM(AI31-AI32) -> 11764.706
A33: =Gen!B38 -> 43949 | B33: ='Summery Report'!E32 -> 0 | C33: =Gen!C38 -> 0 | D33: ='Summery Report'!E32 -> 0 | E33: =SUM(E32) -> 1.3262195 | F33: =SUM(J33*E33)/D33 -> #DIV/0! | G33: =SUM(L33*E33)/D33 -> #DIV/0! | H33: =Gen!D38 -> 45548.2 | I33: =Gen!F38 -> 0 | J33: =Gen!T38 -> 690.55 | K33: =Gen!AK38 -> 100 | L33: =SUM(J33:K33) -> 790.55 | M33: ='Water-Meter'!K73 -> 609.60146 | N33: ='Water-Meter'!E33 -> 31 | P33: 19030 | Q33: =SUM(P33-P32) -> 0 | R33: =SUM(Q33*O33) -> 0 | T33: 16166 | U33: =T33-T32 -> 0 | V33: =SUM(U33*S33) -> 0 | X33: 24476 | Y33: =X33-X32 -> 0 | Z33: =SUM(Y33*W33) -> 0 | AA33: =SUM(Z33*X35) -> 0 | AB33: 31451 | AC33: =SUM(AB33-AB32) -> 0 | AD33: 200626 | AE33: =AD33-AD32 -> 47 | AF33: ='Lpg (2)'!B37*2000/85 -> 2000 | AG33: ='Lpg (2)'!C37*1000/85 -> 1000 | AH33: ='Lpg (2)'!D37*1000/85 -> 623.52941 | AI33: =SUM(AF33*2000)+(AG33*1000)+(AH33*1000) -> 5623529.4 | AJ33: =SUM(AI32-AI33) -> 23529.412
A34: =Gen!B39 -> 43950 | B34: ='Summery Report'!E33 -> 0 | C34: =Gen!C39 -> 0 | D34: ='Summery Report'!E33 -> 0 | E34: =SUM(E33) -> 1.3262195 | F34: =SUM(J34*E34)/D34 -> #DIV/0! | G34: =SUM(L34*E34)/D34 -> #DIV/0! | H34: =Gen!D39 -> 44757.65 | I34: =Gen!F39 -> 0 | J34: =Gen!T39 -> 691.09 | K34: =Gen!AK39 -> 38.11 | L34: =SUM(J34:K34) -> 729.2 | M34: ='Water-Meter'!K74 -> 588.45019 | N34: ='Water-Meter'!E34 -> 29 | P34: 19030 | Q34: =SUM(P34-P33) -> 0 | R34: =SUM(Q34*O34) -> 0 | S34: 8.1 | T34: 16177 | U34: =T34-T33 -> 11 | V34: =SUM(U34*S34) -> 89.1 | X34: 24476 | Y34: =X34-X33 -> 0 | Z34: =SUM(Y34*W34) -> 0 | AA34: =SUM(Z34*X36) -> 0 | AB34: 31534 | AC34: =SUM(AB34-AB33) -> 83 | AD34: 200668 | AE34: =AD34-AD33 -> 42 | AF34: ='Lpg (2)'!B38*2000/85 -> 2000 | AG34: ='Lpg (2)'!C38*1000/85 -> 1000 | AH34: ='Lpg (2)'!D38*1000/85 -> 588.23529 | AI34: =SUM(AF34*2000)+(AG34*1000)+(AH34*1000) -> 5588235.3 | AJ34: =SUM(AI33-AI34) -> 35294.118
A35: =Gen!B40 -> 43951 | B35: ='Summery Report'!E34 -> 0 | C35: =Gen!C40 -> 0 | D35: ='Summery Report'!E34 -> 0 | E35: =SUM(E34) -> 1.3262195 | F35: =SUM(J35*E35)/D35 -> #DIV/0! | G35: =SUM(L35*E35)/D35 -> #DIV/0! | H35: =Gen!D40 -> 44028.45 | I35: =Gen!F40 -> 0 | J35: =Gen!T40 -> 660.76 | K35: =Gen!AK40 -> 0 | L35: =SUM(J35:K35) -> 660.76 | M35: ='Water-Meter'!K75 -> 555.47319 | N35: ='Water-Meter'!E35 -> 29 | P35: 19030 | Q35: =SUM(P35-P34) -> 0 | R35: =SUM(Q35*O35) -> 0 | T35: 16177 | U35: =T35-T34 -> 0 | V35: =SUM(U35*S35) -> 0 | X35: 24476 | Y35: =X35-X34 -> 0 | Z35: =SUM(Y35*W35) -> 0 | AA35: =SUM(Z35*X37) -> 0 | AB35: 31534 | AC35: =SUM(AB35-AB34) -> 0 | AD35: 200738 | AE35: =AD35-AD34 -> 70 | AF35: ='Lpg (2)'!B39*2000/85 -> 2000 | AG35: ='Lpg (2)'!C39*1000/85 -> 1000 | AH35: ='Lpg (2)'!D39*1000/85 -> 564.70588 | AI35: =SUM(AF35*2000)+(AG35*1000)+(AH35*1000) -> 5564705.9 | AJ35: =SUM(AI34-AI35) -> 23529.412
A36: =Gen!B41 -> 0 | B36: ='Summery Report'!E35 -> 0 | C36: =Gen!C41 -> 0 | D36: ='Summery Report'!E35 -> 0 | E36: =SUM(E35) -> 1.3262195 | F36: =SUM(J36*E36)/D36 -> #DIV/0! | G36: =SUM(L36*E36)/D36 -> #DIV/0! | H36: =Gen!D41 -> 43367.69 | I36: =Gen!F41 -> 0 | J36: =Gen!T41 -> 0 | K36: =Gen!AK41 -> 0 | L36: =SUM(J36:K36) -> 0 | M36: ='Water-Meter'!K76 -> 573.91481 | N36: ='Water-Meter'!E36 -> 0 | Q36: =SUM(P36-P35) -> -19030 | R36: =SUM(Q36*O36) -> 0 | U36: =T36-T35 -> -16177 | V36: =SUM(U36*S36) -> 0 | Y36: =X36-X35 -> -24476 | Z36: =SUM(Y36*W36) -> 0 | AA36: =SUM(Z36*X38) -> 0 | AC36: =SUM(AB36-AB35) -> -31534 | AE36: =AD36-AD35 -> -200738 | AF36: ='Lpg (2)'!B40*2000/85 -> 2000 | AG36: ='Lpg (2)'!C40*1000/85 -> 1000 | AH36: ='Lpg (2)'!D40*1000/85 -> 529.41176 | AI36: =SUM(AF36*1000)+(AG36*1000)+(AH36*2000) -> 4058823.5 | AJ36: =SUM(AI35-AI36) -> 1505882.4
A37: =Gen!B42 -> 0 | B37: 0 | J37: =SUM(J6:J36) -> 22822.77 | L37: =SUM(J37:K37) -> 22822.77 | N37: ='Water-Meter'!E37 -> 0 | AC37: =SUM(AB37-AB36) -> 0 | AE37: =AD37-AD36 -> 0 | AJ37: =SUM(AJ6:AJ36) -> -4058823.5 | AK37: =SUM(AK6:AK36) -> 0

Sheet Kit report
B1: KITCHEN THREE PHASE KWH METER READING | H1: KITCHEN WATER METER READING | M1: AMANI Restaurant WATER METER READING | T1: LAUNDRY THREE PHASE KWH METER READING | Y1: LAUNDRY WATER METER READING
A2: Occ % | B2: DATE | C2: READING TIME | D2: METER READING OPEN | E2: METER READING ClOSE | F2: UNIT USED Kwh | H2: DATE | I2: READING TIME | J2: METER READING OPEN Cbm | K2: METER READING ClOSE Cbm | L2: UNIT USED Cbm | M2: DATE | N2: READING TIME | O2: METER READING OPEN Cbm | P2: METER READING ClOSE Cbm | Q2: UNIT USED Cbm | R2: Cost Per day Elct+Water $ | S2: % as per the total Lodge consumption | T2: DATE | U2: READING TIME | V2: METER READING OPEN (Kwh) | W2: METER READING ClOSE (Kwh) | X2: UNIT USED Kwh | Y2: DATE | Z2: READING TIME | AA2: METER READING OPEN Cbm | AB2: METER READING ClOSE Cbm | AC2: UNIT USED Cbm
A3: 43770 | B3: Close Last Month | E3: 8637.1 | F3: X120 | H3: Close Last Month | K3: ='Water-Meter'!H5 -> 38000 | M3: Close Last Month | P3: ='[1]Water-Meter'!J5 -> 7351 | T3: Close Last Month | W3: 7800.7 | X3: =(W3-V3)*200 -> 1560140 | Y3: Close Last Month | AB3: ='[1]Water-Meter'!P5 -> 18541
A4: =Gen!C11 -> 0 | B4: =Gen!B11 -> 43922 | D4: =E3 -> 8637.1 | E4: 8638.4 | F4: =SUM(E4-D4)*120 -> 156 | H4: =B4 -> 43922 | J4: =SUM(K3) -> 38000 | K4: ='[1]Water-Meter'!G6 -> 36434 | L4: =SUM(K4-J4) -> -1566 | M4: =H4 -> 43922 | O4: =SUM(P3) -> 7351 | P4: ='[1]Water-Meter'!J6 -> 7353 | Q4: =SUM(P4-O4) -> 2 | R4: =SUM(Q4/1615) -> 0.0012383901 | S4: =SUM(F4/[1]Gen!T10) -> #DIV/0! | T4: =M4 -> 43922 | V4: =W3 -> 7800.7 | W4: 7800.8 | X4: =(W4-V4)*200 -> 20 | Y4: =T4 -> 43922 | AA4: 3397.9 | AB4: ='[1]Water-Meter'!P6 -> 18547 | AC4: =SUM(AB4-AA4) -> 15149.1
A5: =Gen!C12 -> 0 | B5: =Gen!B12 -> 43923 | D5: =E4 -> 8638.4 | E5: 8639.5 | F5: =SUM(E5-D5)*120 -> 132 | H5: =B5 -> 43923 | J5: =SUM(K4) -> 36434 | K5: ='[1]Water-Meter'!G7 -> 36454 | L5: =SUM(K5-J5) -> 20 | M5: =H5 -> 43923 | O5: =SUM(P4) -> 7353 | P5: ='[1]Water-Meter'!J7 -> 7357 | Q5: =SUM(P5-O5) -> 4 | R5: =SUM(Q5/1615) -> 0.0024767802 | S5: =SUM(F5/[1]Gen!T11) -> 0.02328453 | T5: =M5 -> 43923 | V5: =W4 -> 7800.8 | W5: 7800.9 | X5: =(W5-V5)*200 -> 20 | Y5: =T5 -> 43923 | AA5: =SUM(AB4) -> 18547 | AB5: ='[1]Water-Meter'!P7 -> 18554 | AC5: =SUM(AB5-AA5) -> 7
A6: =Gen!C13 -> 0 | B6: =Gen!B13 -> 43924 | D6: =E5 -> 8639.5 | E6: 8640.7 | F6: =SUM(E6-D6)*120 -> 144 | H6: =B6 -> 43924 | J6: =SUM(K5) -> 36454 | K6: ='[1]Water-Meter'!G8 -> 36472 | L6: =SUM(K6-J6) -> 18 | M6: =H6 -> 43924 | O6: =SUM(P5) -> 7357 | P6: ='[1]Water-Meter'!J8 -> 7360 | Q6: =SUM(P6-O6) -> 3 | R6: =SUM(Q6/1615) -> 0.0018575851 | S6: =SUM(F6/[1]Gen!T12) -> 0.023380419 | T6: =M6 -> 43924 | V6: =W5 -> 7800.9 | W6: 7801.1 | X6: =(W6-V6)*200 -> 40 | Y6: =T6 -> 43924 | AA6: =SUM(AB5) -> 18554 | AB6: ='[1]Water-Meter'!P8 -> 18563 | AC6: =SUM(AB6-AA6) -> 9
A7: =Gen!C14 -> 0 | B7: =Gen!B14 -> 43925 | D7: =E6 -> 8640.7 | E7: 8641.8 | F7: =SUM(E7-D7)*120 -> 132 | H7: =B7 -> 43925 | J7: =SUM(K6) -> 36472 | K7: ='[1]Water-Meter'!G9 -> 36485 | L7: =SUM(K7-J7) -> 13 | M7: =H7 -> 43925 | O7: =SUM(P6) -> 7360 | P7: ='[1]Water-Meter'!J9 -> 7364 | Q7: =SUM(P7-O7) -> 4 | R7: =SUM(Q7/1615) -> 0.0024767802 | S7: =SUM(F7/[1]Gen!T13) -> 0.02006079 | T7: =M7 -> 43925 | V7: =W6 -> 7801.1 | W7: 7801.3 | X7: =(W7-V7)*200 -> 40 | Y7: =T7 -> 43925 | AA7: =SUM(AB6) -> 18563 | AB7: ='[1]Water-Meter'!P9 -> 18575 | AC7: =SUM(AB7-AA7) -> 12
A8: =Gen!C15 -> 0 | B8: =Gen!B15 -> 43926 | D8: =E7 -> 8641.8 | E8: 8642.7 | F8: =SUM(E8-D8)*120 -> 108 | H8: =B8 -> 43926 | J8: =SUM(K7) -> 36485 | K8: ='[1]Water-Meter'!G10 -> 36500 | L8: =SUM(K8-J8) -> 15 | M8: =H8 -> 43926 | O8: =SUM(P7) -> 7364 | P8: ='[1]Water-Meter'!J10 -> 7367 | Q8: =SUM(P8-O8) -> 3 | R8: =SUM(Q8/1615) -> 0.0018575851 | S8: =SUM(F8/[1]Gen!T14) -> 0.017354973 | T8: =M8 -> 43926 | V8: =W7 -> 7801.3 | W8: 7801.5 | X8: =(W8-V8)*200 -> 40 | Y8: =T8 -> 43926 | AA8: =SUM(AB7) -> 18575 | AB8: ='[1]Water-Meter'!P10 -> 18586 | AC8: =SUM(AB8-AA8) -> 11
A9: =Gen!C16 -> 0 | B9: =Gen!B16 -> 43927 | D9: =E8 -> 8642.7 | E9: 8643.8 | F9: =SUM(E9-D9)*120 -> 132 | H9: =B9 -> 43927 | J9: =SUM(K8) -> 36500 | K9: ='[1]Water-Meter'!G11 -> 36516 | L9: =SUM(K9-J9) -> 16 | M9: =H9 -> 43927 | O9: =SUM(P8) -> 7367 | P9: ='[1]Water-Meter'!J11 -> 7369 | Q9: =SUM(P9-O9) -> 2 | R9: =SUM(Q9/1615) -> 0.0012383901 | S9: =SUM(F9/[1]Gen!T15) -> 0.022058824 | T9: =M9 -> 43927 | V9: =W8 -> 7801.5 | W9: 7801.7 | X9: =(W9-V9)*200 -> 40 | Y9: =T9 -> 43927 | AA9: =SUM(AB8) -> 18586 | AB9: ='[1]Water-Meter'!P11 -> 18593 | AC9: =SUM(AB9-AA9) -> 7
A10: =Gen!C17 -> 0 | B10: =Gen!B17 -> 43928 | D10: =E9 -> 8643.8 | E10: 8644.7 | F10: =SUM(E10-D10)*120 -> 108 | H10: =B10 -> 43928 | J10: =SUM(K9) -> 36516 | K10: ='[1]Water-Meter'!G12 -> 36529 | L10: =SUM(K10-J10) -> 13 | M10: =H10 -> 43928 | O10: =SUM(P9) -> 7369 | P10: ='[1]Water-Meter'!J12 -> 7372 | Q10: =SUM(P10-O10) -> 3 | R10: =SUM(Q10/1615) -> 0.0018575851 | S10: =SUM(F10/[1]Gen!T16) -> 0.017696215 | T10: =M10 -> 43928 | V10: =W9 -> 7801.7 | W10: 7801.9 | X10: =(W10-V10)*200 -> 40 | Y10: =T10 -> 43928 | AA10: =SUM(AB9) -> 18593 | AB10: ='[1]Water-Meter'!P12 -> 18606 | AC10: =SUM(AB10-AA10) -> 13 | AH10: 5850
A11: =Gen!C18 -> 0 | B11: =Gen!B18 -> 43929 | D11: =E10 -> 8644.7 | E11: 8645.7 | F11: =SUM(E11-D11)*120 -> 120 | H11: =B11 -> 43929 | J11: =SUM(K10) -> 36529 | K11: ='[1]Water-Meter'!G13 -> 36543 | L11: =SUM(K11-J11) -> 14 | M11: =H11 -> 43929 | O11: =SUM(P10) -> 7372 | P11: ='[1]Water-Meter'!J13 -> 7374 | Q11: =SUM(P11-O11) -> 2 | R11: =SUM(Q11/1615) -> 0.0012383901 | S11: =SUM(F11/[1]Gen!T17) -> 0.021520803 | T11: =M11 -> 43929 | V11: =W10 -> 7801.9 | W11: 7802.1 | X11: =(W11-V11)*200 -> 40 | Y11: =T11 -> 43929 | AA11: =SUM(AB10) -> 18606 | AB11: ='[1]Water-Meter'!P13 -> 18616 | AC11: =SUM(AB11-AA11) -> 10
A12: =Gen!C19 -> 0 | B12: =Gen!B19 -> 43930 | D12: =E11 -> 8645.7 | E12: 8646.7 | F12: =SUM(E12-D12)*120 -> 120 | H12: =B12 -> 43930 | J12: =SUM(K11) -> 36543 | K12: ='[1]Water-Meter'!G14 -> 36560 | L12: =SUM(K12-J12) -> 17 | M12: =H12 -> 43930 | O12: =SUM(P11) -> 7374 | P12: ='[1]Water-Meter'!J14 -> 7377 | Q12: =SUM(P12-O12) -> 3 | R12: =SUM(Q12/1615) -> 0.0018575851 | S12: =SUM(F12/[1]Gen!T18) -> 0.021691974 | T12: =M12 -> 43930 | V12: =W11 -> 7802.1 | W12: 7802.2 | X12: =(W12-V12)*200 -> 20 | Y12: =T12 -> 43930 | AA12: =SUM(AB11) -> 18616 | AB12: ='[1]Water-Meter'!P14 -> 18623
A13: =Gen!C20 -> 0 | B13: =Gen!B20 -> 43931 | D13: =E12 -> 8646.7 | E13: 8647.6 | F13: =SUM(E13-D13)*120 -> 108 | H13: =B13 -> 43931 | J13: =SUM(K12) -> 36560 | K13: ='[1]Water-Meter'!G15 -> 36574 | L13: =SUM(K13-J13) -> 14 | M13: =H13 -> 43931 | O13: =SUM(P12) -> 7377 | P13: ='[1]Water-Meter'!J15 -> 7381 | Q13: =SUM(P13-O13) -> 4 | R13: =SUM(Q13/1615) -> 0.0024767802 | S13: =SUM(F13/[1]Gen!T19) -> 0.01732713 | T13: =M13 -> 43931 | V13: =W12 -> 7802.2 | W13: 7802.5 | X13: =(W13-V13)*200 -> 60 | Y13: =T13 -> 43931 | AA13: =SUM(AB12) -> 18623 | AB13: ='[1]Water-Meter'!P15 -> 18634 | AC13: =SUM(AB13-AA13) -> 11
A14: =Gen!C21 -> 0 | B14: =Gen!B21 -> 43932 | D14: =E13 -> 8647.6 | E14: 8648.7 | F14: =SUM(E14-D14)*120 -> 132 | H14: =B14 -> 43932 | J14: =SUM(K13) -> 36574 | K14: ='[1]Water-Meter'!G16 -> 36591 | L14: =SUM(K14-J14) -> 17 | M14: =H14 -> 43932 | O14: =SUM(P13) -> 7381 | P14: ='[1]Water-Meter'!J16 -> 7385 | Q14: =SUM(P14-O14) -> 4 | R14: =SUM(Q14/1615) -> 0.0024767802 | S14: =SUM(F14/[1]Gen!T20) -> 0.0217714 | T14: =M14 -> 43932 | V14: =W13 -> 7802.5 | W14: 7802.6 | X14: =(W14-V14)*200 -> 20 | Y14: =T14 -> 43932 | AA14: =SUM(AB13) -> 18634 | AB14: ='[1]Water-Meter'!P16 -> 18643 | AC14: =SUM(AB14-AA14) -> 9
A15: =Gen!C22 -> 0 | B15: =Gen!B22 -> 43933 | D15: =E14 -> 8648.7 | E15: 8649.8 | F15: =SUM(E15-D15)*120 -> 132 | H15: =B15 -> 43933 | J15: =SUM(K14) -> 36591 | K15: ='[1]Water-Meter'!G17 -> 36605 | L15: =SUM(K15-J15) -> 14 | M15: =H15 -> 43933 | O15: =SUM(P14) -> 7385 | P15: ='[1]Water-Meter'!J17 -> 7388 | Q15: =SUM(P15-O15) -> 3 | R15: =SUM(Q15/1615) -> 0.0018575851 | S15: =SUM(F15/[1]Gen!T21) -> 0.022121669 | T15: =M15 -> 43933 | V15: =W14 -> 7802.6 | W15: 7802.7 | X15: =(W15-V15)*200 -> 20 | Y15: =T15 -> 43933 | AA15: =SUM(AB14) -> 18643 | AB15: ='[1]Water-Meter'!P17 -> 18652 | AC15: =SUM(AB15-AA15) -> 9
A16: =Gen!C23 -> 0 | B16: =Gen!B23 -> 43934 | D16: =E15 -> 8649.8 | E16: 8650.9 | F16: =SUM(E16-D16)*120 -> 132 | H16: =B16 -> 43934 | J16: =SUM(K15) -> 36605 | K16: ='[1]Water-Meter'!G18 -> 36619 | L16: =SUM(K16-J16) -> 14 | M16: =H16 -> 43934 | O16: =SUM(P15) -> 7388 | P16: ='[1]Water-Meter'!J18 -> 7390 | Q16: =SUM(P16-O16) -> 2 | R16: =SUM(Q16/1615) -> 0.0012383901 | S16: =SUM(F16/[1]Gen!T22) -> 0.022514071 | T16: =M16 -> 43934 | V16: =W15 -> 7802.7 | W16: 7802.8 | X16: =(W16-V16)*200 -> 20 | Y16: =T16 -> 43934 | AA16: =SUM(AB15) -> 18652 | AB16: ='[1]Water-Meter'!P18 -> 18661 | AC16: =SUM(AB16-AA16) -> 9
A17: =Gen!C24 -> 0 | B17: =Gen!B24 -> 43935 | D17: =E16 -> 8650.9 | E17: 8651.9 | F17: =SUM(E17-D17)*120 -> 120 | H17: =B17 -> 43935 | J17: =SUM(K16) -> 36619 | K17: ='[1]Water-Meter'!G19 -> 36632 | L17: =SUM(K17-J17) -> 13 | M17: =H17 -> 43935 | O17: =SUM(P16) -> 7390 | P17: ='[1]Water-Meter'!J19 -> 7393 | Q17: =SUM(P17-O17) -> 3 | R17: =SUM(Q17/1615) -> 0.0018575851 | S17: =SUM(F17/[1]Gen!T23) -> 0.020979021 | T17: =M17 -> 43935 | V17: =W16 -> 7802.8 | W17: 7803 | X17: =(W17-V17)*200 -> 40 | Y17: =T17 -> 43935 | AA17: =SUM(AB16) -> 18661 | AB17: ='[1]Water-Meter'!P19 -> 18672 | AC17: =SUM(AB17-AA17) -> 11
A18: =Gen!C25 -> 0 | B18: =Gen!B25 -> 43936 | D18: =E17 -> 8651.9 | E18: 8652.9 | F18: =SUM(E18-D18)*120 -> 120 | H18: =B18 -> 43936 | J18: =SUM(K17) -> 36632 | K18: ='[1]Water-Meter'!G20 -> 36651 | L18: =SUM(K18-J18) -> 19 | M18: =H18 -> 43936 | O18: =SUM(P17) -> 7393 | P18: ='[1]Water-Meter'!J20 -> 7396 | Q18: =SUM(P18-O18) -> 3 | R18: =SUM(Q18/1615) -> 0.0018575851 | S18: =SUM(F18/[1]Gen!T24) -> 0.01937046 | T18: =M18 -> 43936 | V18: =W17 -> 7803 | W18: 7803.1 | X18: =(W18-V18)*200 -> 20 | Y18: =T18 -> 43936 | AA18: =SUM(AB17) -> 18672 | AB18: ='[1]Water-Meter'!P20 -> 18680 | AC18: =SUM(AB18-AA18) -> 8
A19: =Gen!C26 -> 0 | B19: =Gen!B26 -> 43937 | D19: =E18 -> 8652.9 | E19: 8653.9 | F19: =SUM(E19-D19)*120 -> 120 | H19: =B19 -> 43937 | J19: =SUM(K18) -> 36651 | K19: ='[1]Water-Meter'!G21 -> 36668 | L19: =SUM(K19-J19) -> 17 | M19: =H19 -> 43937 | O19: =SUM(P18) -> 7396 | P19: ='[1]Water-Meter'!J21 -> 7398 | Q19: =SUM(P19-O19) -> 2 | R19: =SUM(Q19/1615) -> 0.0012383901 | S19: =SUM(F19/[1]Gen!T25) -> 0.018604651 | T19: =M19 -> 43937 | V19: =W18 -> 7803.1 | W19: 7803.2 | X19: =(W19-V19)*200 -> 20 | Y19: =T19 -> 43937 | AA19: =SUM(AB18) -> 18680 | AB19: ='[1]Water-Meter'!P21 -> 18689 | AC19: =SUM(AB19-AA19) -> 9
A20: =Gen!C27 -> 0 | B20: =Gen!B27 -> 43938 | D20: =E19 -> 8653.9 | E20: 8654.9 | F20: =SUM(E20-D20)*120 -> 120 | H20: =B20 -> 43938 | J20: =SUM(K19) -> 36668 | K20: ='[1]Water-Meter'!G22 -> 36681 | L20: =SUM(K20-J20) -> 13 | M20: =H20 -> 43938 | O20: =SUM(P19) -> 7398 | P20: ='[1]Water-Meter'!J22 -> 7402 | Q20: =SUM(P20-O20) -> 4 | R20: =SUM(Q20/1615) -> 0.0024767802 | S20: =SUM(F20/[1]Gen!T26) -> 0.017353579 | T20: =M20 -> 43938 | V20: =W19 -> 7803.2 | W20: 7803.4 | X20: =(W20-V20)*200 -> 40 | Y20: =T20 -> 43938 | AA20: =SUM(AB19) -> 18689 | AB20: ='[1]Water-Meter'!P22 -> 18701 | AC20: =SUM(AB20-AA20) -> 12
A21: =Gen!C28 -> 0 | B21: =Gen!B28 -> 43939 | D21: =E20 -> 8654.9 | E21: 8655.7 | F21: =SUM(E21-D21)*120 -> 96 | H21: =B21 -> 43939 | J21: =SUM(K20) -> 36681 | K21: ='[1]Water-Meter'!G23 -> 36696 | L21: =SUM(K21-J21) -> 15 | M21: =H21 -> 43939 | O21: =SUM(P20) -> 7402 | P21: ='[1]Water-Meter'!J23 -> 7404 | Q21: =SUM(P21-O21) -> 2 | R21: =SUM(Q21/1615) -> 0.0012383901 | S21: =SUM(F21/[1]Gen!T28) -> 0.018261366 | T21: =M21 -> 43939 | V21: =W20 -> 7803.4 | W21: 7803.5 | X21: =(W21-V21)*200 -> 20 | Y21: =T21 -> 43939 | AA21: =SUM(AB20) -> 18701 | AB21: ='[1]Water-Meter'!P23 -> 18712 | AC21: =SUM(AB21-AA21) -> 11
A22: =Gen!C29 -> 0 | B22: =Gen!B29 -> 43940 | D22: =E21 -> 8655.7 | E22: 8656.6 | F22: =SUM(E22-D22)*120 -> 108 | H22: =B22 -> 43940 | J22: =SUM(K21) -> 36696 | K22: ='[1]Water-Meter'!G24 -> 36708 | L22: =SUM(K22-J22) -> 12 | M22: =H22 -> 43940 | O22: =SUM(P21) -> 7404 | P22: ='[1]Water-Meter'!J24 -> 7408 | Q22: =SUM(P22-O22) -> 4 | R22: =SUM(Q22/1615) -> 0.0024767802 | S22: =SUM(F22/[1]Gen!T29) -> 0.02302281 | T22: =M22 -> 43940 | V22: =W21 -> 7803.5 | W22: 7803.6 | X22: =(W22-V22)*200 -> 20 | Y22: =T22 -> 43940 | AA22: =SUM(AB21) -> 18712 | AB22: ='[1]Water-Meter'!P24 -> 18719 | AC22: =SUM(AB22-AA22) -> 7
A23: =Gen!C30 -> 0 | B23: =Gen!B30 -> 43941 | D23: =E22 -> 8656.6 | E23: 8657.5 | F23: =SUM(E23-D23)*120 -> 108 | H23: =B23 -> 43941 | J23: =SUM(K22) -> 36708 | K23: ='[1]Water-Meter'!G25 -> 36724 | L23: =SUM(K23-J23) -> 16 | M23: =H23 -> 43941 | O23: =SUM(P22) -> 7408 | P23: ='[1]Water-Meter'!J25 -> 7412 | Q23: =SUM(P23-O23) -> 4 | R23: =SUM(Q23/1615) -> 0.0024767802 | S23: =SUM(F23/[1]Gen!T30) -> 0.018907563 | T23: =M23 -> 43941 | V23: =W22 -> 7803.6 | W23: 7803.7 | X23: =(W23-V23)*200 -> 20 | Y23: =T23 -> 43941 | AA23: =SUM(AB22) -> 18719 | AB23: ='[1]Water-Meter'!P25 -> 18728 | AC23: =SUM(AB23-AA23) -> 9
A24: =Gen!C31 -> 0 | B24: =Gen!B31 -> 43942 | D24: =SUM(E23) -> 8657.5 | E24: 8658.4 | F24: =SUM(E24-D24)*120 -> 108 | H24: =B24 -> 43942 | J24: =SUM(K23) -> 36724 | K24: ='[1]Water-Meter'!G26 -> 36740 | L24: =SUM(K24-J24) -> 16 | M24: =H24 -> 43942 | O24: =SUM(P23) -> 7412 | P24: ='[1]Water-Meter'!J26 -> 7415 | Q24: =SUM(P24-O24) -> 3 | R24: =SUM(Q24/1615) -> 0.0018575851 | S24: =SUM(F24/[1]Gen!T31) -> 0.018178758 | T24: 5835.7 | V24: =W23 -> 7803.7 | W24: 7803.8 | X24: =(W24-V24)*200 -> 20 | Y24: =T24 -> 5835.7 | AA24: =SUM(AB23) -> 18728 | AB24: ='[1]Water-Meter'!P26 -> 18737 | AC24: =SUM(AB24-AA24) -> 9
A25: =Gen!C32 -> 0 | B25: =Gen!B32 -> 43943 | D25: =SUM(E24) -> 8658.4 | E25: 8659.2 | F25: =SUM(E25-D25)*120 -> 96 | H25: =B25 -> 43943 | J25: =SUM(K24) -> 36740 | K25: ='[1]Water-Meter'!G27 -> 36754 | L25: =SUM(K25-J25) -> 14 | M25: =H25 -> 43943 | O25: =SUM(P24) -> 7415 | P25: ='[1]Water-Meter'!J27 -> 7418 | Q25: =SUM(P25-O25) -> 3 | R25: =SUM(Q25/1615) -> 0.0018575851 | S25: =SUM(F25/[1]Gen!T32) -> 0.017777778 | T25: =M25 -> 43943 | V25: =W24 -> 7803.8 | W25: 7803.9 | X25: =(W25-V25)*200 -> 20 | Y25: =T25 -> 43943 | AA25: =SUM(AB24) -> 18737 | AB25: ='[1]Water-Meter'!P27 -> 18746 | AC25: =SUM(AB25-AA25) -> 9
A26: =Gen!C33 -> 0 | B26: =Gen!B33 -> 43944 | D26: =SUM(E25) -> 8659.2 | E26: 8660.1 | F26: =SUM(E26-D26)*120 -> 108 | H26: =B26 -> 43944 | J26: =SUM(K25) -> 36754 | K26: ='[1]Water-Meter'!G28 -> 36767 | L26: =SUM(K26-J26) -> 13 | M26: =H26 -> 43944 | O26: =SUM(P25) -> 7418 | P26: ='[1]Water-Meter'!J28 -> 7421 | Q26: =SUM(P26-O26) -> 3 | R26: =SUM(Q26/1615) -> 0.0018575851 | S26: =SUM(F26/[1]Gen!T33) -> 0.020107987 | T26: =M26 -> 43944 | V26: =W25 -> 7803.9 | W26: 7804 | X26: =(W26-V26)*200 -> 20 | Y26: =T26 -> 43944 | AA26: =SUM(AB25) -> 18746 | AB26: ='[1]Water-Meter'!P28 -> 18754 | AC26: =SUM(AB26-AA26) -> 8
A27: =Gen!C34 -> 0 | B27: =Gen!B34 -> 43945 | D27: =SUM(E26) -> 8660.1 | E27: 8661.1 | F27: =SUM(E27-D27)*120 -> 120 | H27: =B27 -> 43945 | J27: =SUM(K26) -> 36767 | K27: ='[1]Water-Meter'!G29 -> 36779 | L27: =SUM(K27-J27) -> 12 | M27: =H27 -> 43945 | O27: =SUM(P26) -> 7421 | P27: ='[1]Water-Meter'!J29 -> 7423 | Q27: =SUM(P27-O27) -> 2 | R27: =SUM(Q27/1615) -> 0.0012383901 | S27: =SUM(F27/[1]Gen!T34) -> 0.02265861 | T27: =M27 -> 43945 | V27: =W26 -> 7804 | W27: 7804 | X27: =(W27-V27)*200 -> 0 | Y27: =T27 -> 43945 | AA27: =SUM(AB26) -> 18754 | AB27: ='[1]Water-Meter'!P29 -> 18763 | AC27: =SUM(AB27-AA27) -> 9
A28: =Gen!C35 -> 0 | B28: =Gen!B35 -> 43946 | D28: =SUM(E27) -> 8661.1 | E28: 8662 | F28: =SUM(E28-D28)*120 -> 108 | H28: =B28 -> 43946 | J28: =SUM(K27) -> 36779 | K28: ='[1]Water-Meter'!G30 -> 36792 | L28: =SUM(K28-J28) -> 13 | M28: =H28 -> 43946 | O28: =SUM(P27) -> 7423 | P28: ='[1]Water-Meter'!J30 -> 7426 | Q28: =SUM(P28-O28) -> 3 | R28: =SUM(Q28/1615) -> 0.0018575851 | S28: =SUM(F28/[1]Gen!T35) -> 0.020685692 | T28: =M28 -> 43946 | V28: =W27 -> 7804 | W28: 7804.1 | X28: =(W28-V28)*200 -> 20 | Y28: =T28 -> 43946 | AA28: =SUM(AB27) -> 18763 | AB28: ='[1]Water-Meter'!P30 -> 18773 | AC28: =SUM(AB28-AA28) -> 10
A29: =Gen!C36 -> 0 | B29: =Gen!B36 -> 43947 | D29: =SUM(E28) -> 8662 | E29: 8662.9 | F29: =SUM(E29-D29)*120 -> 108 | H29: =B29 -> 43947 | J29: =SUM(K28) -> 36792 | K29: ='[1]Water-Meter'!G31 -> 36809 | L29: =SUM(K29-J29) -> 17 | M29: =H29 -> 43947 | O29: =SUM(P28) -> 7426 | P29: ='[1]Water-Meter'!J31 -> 7428 | Q29: =SUM(P29-O29) -> 2 | R29: =SUM(Q29/1615) -> 0.0012383901 | S29: =SUM(F29/[1]Gen!T36) -> 0.019064431 | T29: =M29 -> 43947 | V29: =W28 -> 7804.1 | W29: 7804.2 | X29: =(W29-V29)*200 -> 20 | Y29: =T29 -> 43947 | AA29: =SUM(AB28) -> 18773 | AB29: ='[1]Water-Meter'!P31 -> 18782 | AC29: =SUM(AB29-AA29) -> 9
A30: =Gen!C37 -> 0 | B30: =Gen!B37 -> 43948 | D30: =SUM(E29) -> 8662.9 | E30: 8664 | F30: =SUM(E30-D30)*120 -> 132 | H30: =B30 -> 43948 | J30: =SUM(K29) -> 36809 | K30: ='[1]Water-Meter'!G32 -> 36825 | L30: =SUM(K30-J30) -> 16 | M30: =H30 -> 43948 | O30: =SUM(P29) -> 7428 | P30: ='[1]Water-Meter'!J32 -> 7432 | Q30: =SUM(P30-O30) -> 4 | R30: =SUM(Q30/1615) -> 0.0024767802 | S30: =SUM(F30/[1]Gen!T37) -> 0.021607464 | T30: =M30 -> 43948 | V30: =W29 -> 7804.2 | W30: 7804.3 | X30: =(W30-V30)*200 -> 20 | Y30: =T30 -> 43948 | AA30: =SUM(AB29) -> 18782 | AB30: ='[1]Water-Meter'!P32 -> 18790 | AC30: =SUM(AB30-AA30) -> 8
A31: =Gen!C38 -> 0 | B31: =Gen!B38 -> 43949 | D31: =SUM(E30) -> 8664 | E31: 8664.9 | F31: =SUM(E31-D31)*120 -> 108 | H31: =B31 -> 43949 | J31: =SUM(K30) -> 36825 | K31: ='[1]Water-Meter'!G33 -> #REF! | L31: =SUM(K31-J31) -> #REF! | M31: =H31 -> 43949 | O31: =SUM(P30) -> 7432 | P31: ='[1]Water-Meter'!J33 -> #REF! | Q31: =SUM(P31-O31) -> #REF! | R31: =SUM(Q31/1615) -> #REF! | S31: =SUM(F31/[1]Gen!T38) -> #DIV/0! | T31: =M31 -> 43949 | V31: =W30 -> 7804.3 | W31: 7804.4 | X31: =(W31-V31)*200 -> 20 | Y31: =T31 -> 43949 | AA31: =SUM(AB30) -> 18790 | AB31: ='[1]Water-Meter'!P33 -> #REF! | AC31: =SUM(AB31-AA31) -> #REF!
A32: =Gen!C39 -> 0 | B32: =Gen!B39 -> 43950 | D32: =SUM(E31) -> 8664.9 | E32: 8665.8 | F32: =SUM(E32-D32)*120 -> 108 | H32: =B32 -> 43950 | J32: =SUM(K31) -> #REF! | K32: ='[1]Water-Meter'!G34 -> #REF! | L32: =SUM(K32-J32) -> #REF! | M32: =H32 -> 43950 | O32: =SUM(P31) -> #REF! | P32: ='[1]Water-Meter'!J34 -> #REF! | Q32: =SUM(P32-O32) -> #REF! | R32: =SUM(Q32/1615) -> #REF! | S32: =SUM(F32/[1]Gen!T39) -> #DIV/0! | T32: =M32 -> 43950 | V32: =W31 -> 7804.4 | W32: 7804.4 | X32: =(W32-V32)*200 -> 0 | Y32: =T32 -> 43950 | AA32: =SUM(AB31) -> #REF! | AB32: ='[1]Water-Meter'!P34 -> #REF! | AC32: =SUM(AB32-AA32) -> #REF!
A33: =Gen!C40 -> 0 | B33: =Gen!B40 -> 43951 | D33: =SUM(E32) -> 8665.8 | E33: 8666.6 | F33: =SUM(E33-D33)*120 -> 96 | H33: =B33 -> 43951 | J33: =SUM(K32) -> #REF! | K33: ='[1]Water-Meter'!G35 -> #REF! | L33: =SUM(K33-J33) -> #REF! | M33: =H33 -> 43951 | O33: =SUM(P32) -> #REF! | P33: ='[1]Water-Meter'!J35 -> #REF! | Q33: =SUM(P33-O33) -> #REF! | R33: =SUM(Q33/1615) -> #REF! | S33: =SUM(F33/[1]Gen!T40) -> #DIV/0! | T33: =M33 -> 43951 | V33: =W32 -> 7804.4 | W33: 7804.5 | X33: =(W33-V33)*200 -> 20 | Y33: =T33 -> 43951 | AA33: =SUM(AB32) -> #REF! | AB33: ='[1]Water-Meter'!P35 -> #REF! | AC33: =SUM(AB33-AA33) -> #REF!
A34: =Gen!C41 -> 0 | B34: =Gen!B41 -> 0 | D34: =SUM(E33) -> 8666.6 | F34: =SUM(E34-D34)*120 -> -1039992 | H34: =B34 -> 0 | J34: =SUM(K33) -> #REF! | K34: ='[1]Water-Meter'!G36 -> #REF! | L34: =SUM(K34-J34) -> #REF! | M34: =H34 -> 0 | O34: =SUM(P33) -> #REF! | P34: ='[1]Water-Meter'!J36 -> #REF! | Q34: =SUM(P34-O34) -> #REF! | R34: =SUM(Q34/1615) -> #REF! | S34: =SUM(F34/[1]Gen!T41) -> #DIV/0! | T34: =M34 -> 0 | V34: =SUM(W33) -> 7804.5 | X34: =(W34-V34)*200 -> -1560900 | Y34: =T34 -> 0 | AA34: =SUM(AB33) -> #REF! | AB34: ='[1]Water-Meter'!P36 -> #REF! | AC34: =SUM(AB34-AA34) -> #REF!
A35: =[1]Gen!B42 -> #REF! | B35: =[1]Gen!A42 -> #REF! | D35: =SUM(E34) -> 0 | F35: =SUM(F4:F6) -> 432 | H35: =B35 -> #REF! | J35: =SUM(K34) -> #REF! | K35: ='[1]Water-Meter'!G37 -> #REF! | L35: =SUM(L5:L34) -> #REF! | M35: =H35 -> #REF! | O35: =SUM(P34) -> #REF! | P35: ='[1]Water-Meter'!J37 -> #REF! | Q35: =SUM(Q5:Q34) -> #REF! | R35: =SUM(Q35/1615) -> #REF! | S35: =SUM(F35/[1]Gen!T42) -> #DIV/0! | T35: =M35 -> #REF! | V35: =SUM(W34) -> 0 | X35: =(W35-V35)*200 -> 0 | Y35: =T35 -> #REF! | AA35: =SUM(AB34) -> #REF! | AB35: ='[1]Water-Meter'!P37 -> #REF! | AC35: =SUM(AC5:AC34) -> #REF!
X36: =SUM(X4:X6) -> 80

Sheet Summery Report
A2: Generator and Diseal Summry Report March 2020
A4: Date | B4: Gen Set Hours Working | C4: Occ% | D4: Total OCC Room | E4: Guest Room Occ | F4: Total Kwh Generated | G4: Diesel consumed by Gen (Ltrs) | H4: Diesel consumed by Vehicle (Ltrs) | I4: Total diesel consumed (Ltrs) | J4: Balance stock of Diesel (Ltrs) | K4: Water consumed | L4: Gas consumed (KG)
A5: =Gen!B11 -> 43922 | B5: ='Daily report Gen'!Z6 -> 24 | C5: =Gen!C11 -> 0 | D5: =E5 -> 0 | F5: =Gen!U9 -> 0 | G5: =Gen!T9 -> 0 | H5: =Gen!AK11 -> 49.37 | I5: =SUM(G5:H5) -> 49.37 | J5: =Gen!D11 -> 41048.87 | K5: ='Water-Meter'!E6 -> 38 | L5: ='Lpg (2)'!G10 -> 61.6 | M5: =SUM(#REF!-#REF!) -> #REF!
A6: =Gen!B12 -> 43923 | B6: ='Daily report Gen'!Z7 -> 25 | C6: =Gen!C12 -> 0 | D6: =E6 -> 0 | F6: =Gen!U10 -> 0 | G6: =Gen!T10 -> 0 | H6: =Gen!AK12 -> 9.39 | I6: =SUM(G6:H6) -> 9.39 | J6: =Gen!D12 -> 40148.54 | K6: ='Water-Meter'!E7 -> 52 | L6: ='Lpg (2)'!G11 -> 66 | M6: =SUM(#REF!-#REF!) -> #REF!
A7: =Gen!B13 -> 43924 | B7: ='Daily report Gen'!Z8 -> 24 | C7: =Gen!C13 -> 0 | D7: =E7 -> 0 | F7: =Gen!U11 -> 2051 | G7: =Gen!T11 -> 850.96 | H7: =Gen!AK13 -> 18.02 | I7: =SUM(G7:H7) -> 868.98 | J7: =Gen!D13 -> 39272.9 | K7: ='Water-Meter'!E8 -> 26 | L7: ='Lpg (2)'!G12 -> 37.532 | M7: =SUM(#REF!-#REF!) -> #REF!
A8: =Gen!B14 -> 43925 | B8: ='Daily report Gen'!Z9 -> 26 | C8: =Gen!C14 -> 0 | D8: =E8 -> 0 | F8: =Gen!U12 -> 2088 | G8: =Gen!T12 -> 866.25 | H8: =Gen!AK14 -> 660.37 | I8: =SUM(G8:H8) -> 1526.62 | J8: =Gen!D14 -> 38421.96 | K8: ='Water-Meter'!E9 -> 34 | L8: ='Lpg (2)'!G13 -> 31.46 | M8: =SUM(#REF!-#REF!) -> #REF!
A9: =Gen!B15 -> 43926 | B9: ='Daily report Gen'!Z10 -> 24 | C9: =Gen!C15 -> 0 | D9: =E9 -> 0 | F9: =Gen!U13 -> 1898 | G9: =Gen!T13 -> 832.92 | H9: =Gen!AK15 -> 34.28 | I9: =SUM(G9:H9) -> 867.2 | J9: =Gen!D15 -> 36972.04 | K9: ='Water-Meter'!E10 -> 42 | L9: ='Lpg (2)'!G14 -> 27.808 | M9: =SUM(#REF!-#REF!) -> #REF!
A10: =Gen!B16 -> 43927 | B10: ='Daily report Gen'!Z11 -> 24 | C10: =Gen!C16 -> 0 | D10: =E10 -> 0 | F10: =Gen!U14 -> 1815 | G10: =Gen!T14 -> 789.55 | H10: =Gen!AK16 -> 0 | I10: =SUM(G10:H10) -> 789.55 | J10: =Gen!D16 -> 36124.42 | K10: ='Water-Meter'!E11 -> 41 | L10: ='Lpg (2)'!G15 -> 14.608 | M10: =SUM(#REF!-#REF!) -> #REF!
A11: =Gen!B17 -> 43928 | B11: ='Daily report Gen'!Z12 -> 24 | C11: =Gen!C17 -> 0 | D11: =E11 -> 0 | F11: =Gen!U15 -> 1841 | G11: =Gen!T15 -> 813.34 | H11: =Gen!AK17 -> 108.2 | I11: =SUM(G11:H11) -> 921.54 | J11: =Gen!D17 -> 50366.89 | K11: ='Water-Meter'!E12 -> 47 | L11: ='Lpg (2)'!G16 -> 25.212 | M11: =SUM(#REF!-#REF!) -> #REF!
A12: =Gen!B18 -> 43929 | B12: ='Daily report Gen'!Z13 -> 24 | C12: =Gen!C18 -> 0 | D12: =E12 -> 0 | F12: =Gen!U16 -> 1789 | G12: =Gen!T16 -> 757.53 | H12: =Gen!AK18 -> 0 | I12: =SUM(G12:H12) -> 757.53 | J12: =Gen!D18 -> 49475.14 | K12: ='Water-Meter'!E13 -> 36 | L12: ='Lpg (2)'!G17 -> 36.3 | M12: =SUM(#REF!-#REF!) -> #REF!
A13: =Gen!B19 -> 43930 | B13: ='Daily report Gen'!Z14 -> 25 | C13: =Gen!C19 -> 0 | D13: =E13 -> 0 | F13: =Gen!U17 -> 1867 | G13: =Gen!T17 -> 783.55 | H13: =Gen!AK19 -> 0 | I13: =SUM(G13:H13) -> 783.55 | J13: =Gen!D19 -> 48643.87 | K13: ='Water-Meter'!E14 -> 33 | L13: ='Lpg (2)'!G18 -> 25.916 | M13: =SUM(#REF!-#REF!) -> #REF!
A14: =Gen!B20 -> 43931 | B14: ='Daily report Gen'!Z15 -> 24 | C14: =Gen!C20 -> 0 | D14: =E14 -> 0 | F14: =Gen!U18 -> 1940 | G14: =Gen!T18 -> 831.27 | H14: =Gen!AK20 -> 0 | I14: =SUM(G14:H14) -> 831.27 | J14: =Gen!D20 -> 47837.55 | K14: ='Water-Meter'!E15 -> 55 | L14: ='Lpg (2)'!G19 -> 34.54 | M14: =SUM(#REF!-#REF!) -> #REF!
A15: =Gen!B21 -> 43932 | B15: ='Daily report Gen'!Z16 -> 25 | C15: =Gen!C21 -> 0 | D15: =E15 -> 0 | F15: =Gen!U19 -> 1882 | G15: =Gen!T19 -> 806.32 | H15: =Gen!AK21 -> 0 | I15: =SUM(G15:H15) -> 806.32 | J15: =Gen!D21 -> 47013.8 | K15: ='Water-Meter'!E16 -> 56 | L15: ='Lpg (2)'!G20 -> 38.412 | M15: =SUM(#REF!-#REF!) -> #REF!
A16: =Gen!B22 -> 43933 | B16: ='Daily report Gen'!Z17 -> 25 | C16: =Gen!C22 -> 0 | D16: =E16 -> 0 | F16: =Gen!U20 -> 1935 | G16: =Gen!T20 -> 823.75 | H16: =Gen!AK22 -> 0 | I16: =SUM(G16:H16) -> 823.75 | J16: =Gen!D22 -> 46231.13 | K16: ='Water-Meter'!E17 -> 41 | L16: ='Lpg (2)'!G21 -> 35.2 | M16: =SUM(#REF!-#REF!) -> #REF!
... A35: =Gen!B41 -> 0 | B35: ='Daily report Gen'!Z36 -> -150621 | C35: =Gen!C41 -> 0 | D35: =E35 -> 0 | F35: =Gen!U39 -> 1644 | G35: =Gen!T39 -> 691.09 | H35: =Gen!AK41 -> 0 | I35: =SUM(G35:H35) -> 691.09 | J35: =Gen!D41 -> 43367.69 | K35: ='Water-Meter'!E36 -> 0 | L35: ='Lpg (2)'!G40 -> 27.852 | M35: =SUM(#REF!-#REF!) -> #REF!
A36: =Gen!B42 -> 0 | B36: ='Daily report Gen'!Z37 -> 0 | C36: =Gen!C42 -> 0 | D36: =E36 -> 0 | F36: =Gen!U40 -> 1564 | G36: =Gen!T40 -> 660.76 | H36: =Gen!AK42 -> 0 | I36: =SUM(G36:H36) -> 660.76 | J36: =Gen!D42 -> 43367.69 | K36: ='Water-Meter'!E37 -> 0 | L36: ='Lpg (2)'!G41 -> 0

Sheet Daily report Gen
A1: 43922
K3: GENERATOR NO.1 | N3: GENERATOR NO.2 | Q3: GENERATOR NO.4 | T3: GENERATOR NO.5 | W3: GENERATOR NO.6
A4: DATE | B4: OCC% | C4: D-TANK A | D4: D-TANK B | E4: DELIVERY DATE | F4: DELIVERY | G4: ISSUED-VEHICLE | H4: OTHERS | I4: M-R LV PANEL 1. KW-HR | J4: M-R LV PANEL 2. KW-HR | K4: OPEN HRS READING | L4: CLOSE HRS READING | M4: RUNNING HRS | N4: OPEN HRS READING | O4: CLOSE HRS READING | P4: RUNNING HRS | Q4: OPEN HRS READING | R4: CLOSE HRS READING | S4: RUNNING HRS | T4: OPEN HRS READING | U4: CLOSE HRS READING | V4: RUNNING HRS | W4: OPEN HRS READING | X4: CLOSE HRS READING | Y4: RUNNING HRS | Z4: TOTAL RUNNING HRS | AA4: MAX KW | AB4: MIN-KW | AC4: TOTAL DIESEL CONS.
L5: ='[4]Daily report Gen'!$L$36 -> 34275 | O5: ='[4]Daily report Gen'!$O$36 -> 29189 | R5: ='[4]Daily report Gen'!$R$36 -> 34669 | U5: ='[4]Daily report Gen'!$U$36 -> 32019 | X5: ='[4]Daily report Gen'!$X$36 -> 19736
A6: =Gen!B11 -> 43922 | B6: =Gen!C11 -> 0 | C6: 19057.67 | D6: 21996.2 | G6: 49.37 | I6: 30552.9 | J6: 20198.6 | K6: =L5 -> 34275 | L6: ='[4]Daily report Gen'!$L$36 -> 34275 | M6: =L6-K6 -> 0 | N6: =O5 -> 29189 | O6: 29198 | P6: =O6-N6 -> 9 | Q6: =R5 -> 34669 | R6: 34677 | S6: =R6-Q6 -> 8 | T6: =U5 -> 32019 | U6: ='[4]Daily report Gen'!$U$36 -> 32019 | V6: =U6-T6 -> 0 | W6: =X5 -> 19736 | X6: 19743 | Y6: =X6-W6 -> 7 | Z6: =Y6+V6+S6+P6+M6 -> 24 | AA6: 240 | AB6: 90 | AC6: =Gen!T11 -> 850.96
A7: =Gen!B12 -> 43923 | B7: =Gen!C12 -> 0 | C7: 18201.71 | D7: 21996.2 | G7: 9.39 | I7: 30556.1 | J7: 20201.2 | K7: =L6 -> 34275 | L7: ='[4]Daily report Gen'!$L$36 -> 34275 | M7: =L7-K7 -> 0 | N7: =O6 -> 29198 | O7: 29199 | P7: =O7-N7 -> 1 | Q7: =R6 -> 34677 | R7: 34683 | S7: =R7-Q7 -> 6 | T7: =U6 -> 32019 | U7: 32027 | V7: =U7-T7 -> 8 | W7: =X6 -> 19743 | X7: 19753 | Y7: =X7-W7 -> 10 | Z7: =Y7+V7+S7+P7+M7 -> 25 | AA7: 220 | AB7: 90 | AC7: =Gen!T12 -> 866.25
A8: =Gen!B13 -> 43924 | B8: =Gen!C13 -> 0 | C8: 17276.7 | D8: 21996.2 | G8: 18.02 | I8: 30559 | J8: 20203.7 | K8: =L7 -> 34275 | L8: ='[4]Daily report Gen'!$L$36 -> 34275 | M8: =L8-K8 -> 0 | N8: =O7 -> 29199 | O8: 29207 | P8: =O8-N8 -> 8 | Q8: =R7 -> 34683 | R8: 34691 | S8: =R8-Q8 -> 8 | T8: =U7 -> 32027 | U8: 32034 | V8: =U8-T8 -> 7 | W8: =X7 -> 19753 | X8: 19754 | Y8: =X8-W8 -> 1 | Z8: =Y8+V8+S8+P8+M8 -> 24 | AA8: 198 | AB8: 88 | AC8: =Gen!T13 -> 832.92
A9: =Gen!B14 -> 43925 | B9: =Gen!C14 -> 0 | C9: 16425.76 | D9: 21996.2 | G9: 660.37 | I9: 30561.8 | J9: 20206.9 | K9: =L8 -> 34275 | L9: ='[4]Daily report Gen'!$L$36 -> 34275 | M9: =L9-K9 -> 0 | N9: =O8 -> 29207 | O9: 29214 | P9: =O9-N9 -> 7 | Q9: =R8 -> 34691 | R9: 34692 | S9: =R9-Q9 -> 1 | T9: =U8 -> 32034 | U9: 32043 | V9: =U9-T9 -> 9 | W9: =X8 -> 19754 | X9: 19763 | Y9: =X9-W9 -> 9 | Z9: =Y9+V9+S9+P9+M9 -> 26 | AA9: 197 | AB9: 90 | AC9: =Gen!T14 -> 789.55
A10: =Gen!B15 -> 43926 | B10: =Gen!C15 -> 0 | C10: 14975.84 | D10: 21996.2 | G10: 34.28 | I10: 30564.4 | J10: 20208.4 | K10: =L9 -> 34275 | L10: ='[4]Daily report Gen'!$L$36 -> 34275 | M10: =L10-K10 -> 0 | N10: =O9 -> 29214 | O10: 29222 | P10: =O10-N10 -> 8 | Q10: =R9 -> 34692 | R10: 34701 | S10: =R10-Q10 -> 9 | T10: =U9 -> 32043 | U10: 32050 | V10: =U10-T10 -> 7 | W10: =X9 -> 19763 | X10: 19763 | Y10: =X10-W10 -> 0 | Z10: =Y10+V10+S10+P10+M10 -> 24 | AA10: 198 | AB10: 90 | AC10: =Gen!T15 -> 813.34
A11: =Gen!B16 -> 43927 | B11: =Gen!C16 -> 0 | C11: 14128.22 | D11: 21996.2 | I11: 30567 | J11: 20210.7 | K11: =L10 -> 34275 | L11: ='[4]Daily report Gen'!$L$36 -> 34275 | M11: =L11-K11 -> 0 | N11: =O10 -> 29222 | O11: 29223 | P11: =O11-N11 -> 1 | Q11: =R10 -> 34701 | R11: 34711 | S11: =R11-Q11 -> 10 | T11: =U10 -> 32050 | U11: 32056 | V11: =U11-T11 -> 6 | W11: =X10 -> 19763 | X11: 19770 | Y11: =X11-W11 -> 7 | Z11: =Y11+V11+S11+P11+M11 -> 24 | AA11: 189 | AB11: 90 | AC11: =Gen!T16 -> 757.53
A12: =Gen!B17 -> 43928 | B12: =Gen!C17 -> 0 | C12: 24370.69 | D12: 25996.2 | E12: 15000 | G12: 108.2 | I12: 30569.6 | J12: 20213.2 | K12: =L11 -> 34275 | L12: 34275 | M12: =L12-K12 -> 0 | N12: =O11 -> 29223 | O12: 29231 | P12: =O12-N12 -> 8 | Q12: =R11 -> 34711 | R12: 34718 | S12: =R12-Q12 -> 7 | T12: =U11 -> 32056 | U12: 32056 | V12: =U12-T12 -> 0 | W12: =X11 -> 19770 | X12: 19779 | Y12: =X12-W12 -> 9 | Z12: =Y12+V12+S12+P12+M12 -> 24 | AA12: 178 | AB12: 86 | AC12: =Gen!T17 -> 783.55
A13: =Gen!B18 -> 43929 | B13: =Gen!C18 -> 0 | C13: 23478.94 | D13: 25996.2 | I13: 30572.2 | J13: 20215.9 | K13: =L12 -> 34275 | L13: 34275 | M13: =L13-K13 -> 0 | N13: =O12 -> 29231 | O13: 29231 | P13: =O13-N13 -> 0 | Q13: =R12 -> 34718 | R13: 34723 | S13: =R13-Q13 -> 5 | T13: =U12 -> 32056 | U13: 32065 | V13: =U13-T13 -> 9 | W13: =X12 -> 19779 | X13: 19789 | Y13: =X13-W13 -> 10 | Z13: =Y13+V13+S13+P13+M13 -> 24 | AA13: 198 | AB13: 90 | AC13: =Gen!T18 -> 831.27
A14: =Gen!B19 -> 43930 | B14: =Gen!C19 -> 0 | C14: 22647.67 | D14: 25996.2 | I14: 30574.8 | J14: 20218.4 | K14: =L13 -> 34275 | L14: 34275 | M14: =L14-K14 -> 0 | N14: =O13 -> 29231 | O14: 29238 | P14: =O14-N14 -> 7 | Q14: =R13 -> 34723 | R14: 34723 | S14: =R14-Q14 -> 0 | T14: =U13 -> 32065 | U14: 32073 | V14: =U14-T14 -> 8 | W14: =X13 -> 19789 | X14: 19799 | Y14: =X14-W14 -> 10 | Z14: =Y14+V14+S14+P14+M14 -> 25 | AA14: 195 | AB14: 90 | AC14: =Gen!T19 -> 806.32
A15: =Gen!B20 -> 43931 | B15: =Gen!C20 -> 0 | C15: 21841.35 | D15: 25996.2 | I15: 30577.5 | J15: 20221 | K15: =L14 -> 34275 | L15: 34275 | M15: =L15-K15 -> 0 | N15: =O14 -> 29238 | O15: 29248 | P15: =O15-N15 -> 10 | Q15: =R14 -> 34723 | R15: 34723 | S15: =R15-Q15 -> 0 | T15: =U14 -> 32073 | U15: 32078 | V15: =U15-T15 -> 5 | W15: =X14 -> 19799 | X15: 19808 | Y15: =X15-W15 -> 9 | Z15: =Y15+V15+S15+P15+M15 -> 24 | AA15: 145 | AB15: 80 | AC15: =Gen!T20 -> 823.75
A16: =Gen!B21 -> 43932 | B16: =Gen!C21 -> 0 | C16: 21017.6 | D16: 25996.2 | I16: 30580.1 | J16: 20223.4 | K16: =L15 -> 34275 | L16: 34275 | M16: =L16-K16 -> 0 | N16: =O15 -> 29248 | O16: 29257 | P16: =O16-N16 -> 9 | Q16: =R15 -> 34723 | R16: 34723 | S16: =R16-Q16 -> 0 | T16: =U15 -> 32078 | U16: 32085 | V16: =U16-T16 -> 7 | W16: =X15 -> 19808 | X16: 19817 | Y16: =X16-W16 -> 9 | Z16: =Y16+V16+S16+P16+M16 -> 25 | AA16: 189 | AB16: 85 | AC16: =Gen!T21 -> 782.67
A17: =Gen!B22 -> 43933 | B17: =Gen!C22 -> 0 | C17: 20234.93 | D17: 25996.2 | I17: 30582.8 | J17: 20225.8 | K17: =L16 -> 34275 | L17: 34275 | M17: =L17-K17 -> 0 | N17: =O16 -> 29257 | O17: 29270 | P17: =O17-N17 -> 13 | Q17: =R16 -> 34723 | R17: 34723 | S17: =R17-Q17 -> 0 | T17: =U16 -> 32085 | U17: 32085 | V17: =U17-T17 -> 0 | W17: =X16 -> 19817 | X17: 19829 | Y17: =X17-W17 -> 12 | Z17: =Y17+V17+S17+P17+M17 -> 25 | AA17: 176 | AB17: 113 | AC17: =Gen!T22 -> 776.8
A18: =Gen!B23 -> 43934 | B18: =Gen!C23 -> 0 | C18: 19458.13 | D18: 25996.2 | G18: 19.86 | I18: 30585.3 | J18: 20228.1 | K18: =L17 -> 34275 | L18: 34275 | M18: =L18-K18 -> 0 | N18: =O17 -> 29270 | O18: 29281 | P18: =O18-N18 -> 11 | Q18: =R17 -> 34723 | R18: 34723 | S18: =R18-Q18 -> 0 | T18: =U17 -> 32085 | U18: 32097 | V18: =U18-T18 -> 12 | W18: =X17 -> 19829 | X18: 19829 | Y18: =X18-W18 -> 0 | Z18: =Y18+V18+S18+P18+M18 -> 23 | AA18: 178 | AB18: 90 | AC18: =Gen!T23 -> 771.72
A19: =Gen!B24 -> 43935 | B19: =Gen!C24 -> 0 | C19: 18666.55 | D19: 25996.2 | I19: 30587.9 | J19: 20230.3 | K19: =L18 -> 34275 | L19: 34275 | M19: =L19-K19 -> 0 | N19: =O18 -> 29281 | O19: 29293 | P19: =O19-N19 -> 12 | Q19: =R18 -> 34723 | R19: 34723 | S19: =R19-Q19 -> 0 | T19: =U18 -> 32097 | U19: 32097 | V19: =U19-T19 -> 0 | W19: =X18 -> 19829 | X19: 19842 | Y19: =X19-W19 -> 13 | Z19: =Y19+V19+S19+P19+M19 -> 25 | AA19: 179 | AB19: 80 | AC19: =Gen!T24 -> 760.62
A20: =Gen!B25 -> 43936 | B20: =Gen!C25 -> 0 | C20: 17905.93 | D20: 25996.2 | I20: 30590.5 | J20: 20232.7 | K20: =L19 -> 34275 | L20: 34275 | M20: =L20-K20 -> 0 | N20: =O19 -> 29293 | O20: 29293 | P20: =O20-N20 -> 0 | Q20: =R19 -> 34723 | R20: 34734 | S20: =R20-Q20 -> 11 | T20: =U19 -> 32097 | U20: 32110 | V20: =U20-T20 -> 13 | W20: =X19 -> 19842 | X20: 19842 | Y20: =X20-W20 -> 0 | Z20: =Y20+V20+S20+P20+M20 -> 24 | AA20: 178 | AB20: 80 | AC20: =Gen!T25 -> 786.19
A21: =Gen!B26 -> 43937 | B21: =Gen!C26 -> 0 | C21: 17119.74 | D21: 25996.2 | I21: 30593 | J21: 20235.1 | K21: =L20 -> 34275 | L21: 34275 | M21: =L21-K21 -> 0 | N21: =O20 -> 29293 | O21: 29304 | P21: =O21-N21 -> 11 | Q21: =R20 -> 34734 | R21: 34735 | S21: =R21-Q21 -> 1 | T21: =U20 -> 32110 | U21: 32110 | V21: =U21-T21 -> 0 | W21: =X20 -> 19842 | X21: 19855 | Y21: =X21-W21 -> 13 | Z21: =Y21+V21+S21+P21+M21 -> 25 | AA21: 176 | AB21: 80 | AC21: =Gen!T26 -> 754.27
A22: =Gen!B27 -> 43938 | B22: =Gen!C27 -> 0 | C22: 16365.47 | D22: 25996.2 | G22: 18.45 | I22: 30595.7 | J22: 20237.4 | K22: =L21 -> 34275 | L22: 34275 | M22: =L22-K22 -> 0 | N22: =O21 -> 29304 | O22: 29304 | P22: =O22-N22 -> 0 | Q22: =R21 -> 34735 | R22: 34748 | S22: =R22-Q22 -> 13 | T22: =U21 -> 32110 | U22: 32121 | V22: =U22-T22 -> 11 | W22: =X21 -> 19855 | X22: 19855 | Y22: =X22-W22 -> 0 | Z22: =Y22+V22+S22+P22+M22 -> 24 | AA22: 169 | AB22: 80 | AC22: =Gen!T27 -> 781.93
A23: =Gen!B28 -> 43939 | B23: =Gen!C28 -> 0 | C23: 15565.09 | D23: 25996.2 | I23: 30598.2 | J23: 20239.7 | K23: =L22 -> 34275 | L23: 34275 | M23: =L23-K23 -> 0 | N23: =O22 -> 29304 | O23: 29317 | P23: =O23-N23 -> 13 | Q23: =R22 -> 34748 | R23: 34748 | S23: =R23-Q23 -> 0 | T23: =U22 -> 32121 | U23: 32122 | V23: =U23-T23 -> 1 | W23: =X22 -> 19855 | X23: 19866 | Y23: =X23-W23 -> 11 | Z23: =Y23+V23+S23+P23+M23 -> 25 | AA23: 168 | AB23: 80 | AC23: =Gen!T28 -> 744.22
A24: =Gen!B29 -> 43940 | B24: =Gen!C29 -> 0 | C24: 14820.87 | D24: 25996.2 | G24: 52.04 | I24: 30600.7 | J24: 20242 | K24: =L23 -> 34275 | L24: 34275 | M24: =L24-K24 -> 0 | N24: =O23 -> 29317 | O24: 29317 | P24: =O24-N24 -> 0 | Q24: =R23 -> 34748 | R24: 34760 | S24: =R24-Q24 -> 12 | T24: =U23 -> 32122 | U24: 32134 | V24: =U24-T24 -> 12 | W24: =X23 -> 19866 | X24: 19866 | Y24: =X24-W24 -> 0 | Z24: =Y24+V24+S24+P24+M24 -> 24 | AA24: 166 | AB24: 70 | AC24: =Gen!T29 -> 740.05
A25: =Gen!B30 -> 43941 | B25: =Gen!C30 -> 0 | C25: 14028.78 | D25: 25996.2 | I25: 30603.1 | J25: 20244.3 | K25: =L24 -> 34275 | L25: 34275 | M25: =L25-K25 -> 0 | N25: =O24 -> 29317 | O25: 29330 | P25: =O25-N25 -> 13 | Q25: =R24 -> 34760 | R25: 34760 | S25: =R25-Q25 -> 0 | T25: =U24 -> 32134 | U25: 32134 | V25: =U25-T25 -> 0 | W25: =X24 -> 19866 | X25: 19878 | Y25: =X25-W25 -> 12 | Z25: =Y25+V25+S25+P25+M25 -> 25 | AA25: 167 | AB25: 70 | AC25: =Gen!T30 -> 731.47
A26: =Gen!B31 -> 43942 | B26: =Gen!C31 -> 0 | C26: 13297.31 | D26: 25996.2 | G26: 180 | I26: 30605.5 | J26: 20246.7 | K26: =L25 -> 34275 | L26: 34275 | M26: =L26-K26 -> 0 | N26: =O25 -> 29330 | O26: 29330 | P26: =O26-N26 -> 0 | Q26: =R25 -> 34760 | R26: 34772 | S26: =R26-Q26 -> 12 | T26: =U25 -> 32134 | U26: 32146 | V26: =U26-T26 -> 12 | W26: =X25 -> 19878 | X26: 19878 | Y26: =X26-W26 -> 0 | Z26: =Y26+V26+S26+P26+M26 -> 24 | AA26: 168 | AB26: 75 | AC26: =Gen!T31 -> 747.27
A27: =Gen!B32 -> 43943 | B27: =Gen!C32 -> 0 | C27: 12370.04 | D27: 25996.2 | G27: 123.51 | I27: 30607.7 | J27: 20248.9 | K27: =L26 -> 34275 | L27: 34275 | M27: =L27-K27 -> 0 | N27: =O26 -> 29330 | O27: 29342 | P27: =O27-N27 -> 12 | Q27: =R26 -> 34772 | R27: 34772 | S27: =R27-Q27 -> 0 | T27: =U26 -> 32146 | U27: 32146 | V27: =U27-T27 -> 0 | W27: =X26 -> 19878 | X27: 19890 | Y27: =X27-W27 -> 12 | Z27: =Y27+V27+S27+P27+M27 -> 24 | AA27: 166 | AB27: 75 | AC27: =Gen!T32 -> 709.13
A28: =Gen!B33 -> 43944 | B28: =Gen!C33 -> 0 | C28: 23537.4 | D28: 25996.2 | I28: 30610 | J28: 20251 | K28: =L27 -> 34275 | L28: 34275 | M28: =L28-K28 -> 0 | N28: =O27 -> 29342 | O28: 29342 | P28: =O28-N28 -> 0 | Q28: =R27 -> 34772 | R28: 34784 | S28: =R28-Q28 -> 12 | T28: =U27 -> 32146 | U28: 32158 | V28: =U28-T28 -> 12 | W28: =X27 -> 19890 | X28: 19891 | Y28: =X28-W28 -> 1 | Z28: =Y28+V28+S28+P28+M28 -> 25 | AA28: 165 | AB28: 70 | AC28: =Gen!T33 -> 670.85
A29: =Gen!B34 -> 43945 | B29: =Gen!C34 -> 0 | C29: 22866.55 | D29: 25996.2 | G29: 254.15 | I29: 30612.4 | J29: 20253.2 | K29: =L28 -> 34275 | L29: 34275 | M29: =L29-K29 -> 0 | N29: =O28 -> 29342 | O29: 29354 | P29: =O29-N29 -> 12 | Q29: =R28 -> 34784 | R29: 34784 | S29: =R29-Q29 -> 0 | T29: =U28 -> 32158 | U29: 32159 | V29: =U29-T29 -> 1 | W29: =X28 -> 19891 | X29: 19903 | Y29: =X29-W29 -> 12 | Z29: =Y29+V29+S29+P29+M29 -> 25 | AA29: 168 | AB29: 75 | AC29: =Gen!T34 -> 734.77
A30: =Gen!B35 -> 43946 | B30: =Gen!C35 -> 0 | C30: 21877.63 | D30: 25996.2 | G30: 133.02 | I30: 30614.7 | J30: 20255.3 | K30: =L29 -> 34275 | L30: 34275 | M30: =L30-K30 -> 0 | N30: =O29 -> 29354 | O30: 29354 | P30: =O30-N30 -> 0 | Q30: =R29 -> 34784 | R30: 34796 | S30: =R30-Q30 -> 12 | T30: =U29 -> 32159 | U30: 32171 | V30: =U30-T30 -> 12 | W30: =X29 -> 19903 | X30: 19904 | Y30: =X30-W30 -> 1 | Z30: =Y30+V30+S30+P30+M30 -> 25 | AA30: 198 | AB30: 75 | AC30: =Gen!T35 -> 708.25
A31: =Gen!B36 -> 43947 | B31: =Gen!C36 -> 0 | C31: 21036.36 | D31: 25996.2 | G31: 52.26 | I31: 30617.1 | J31: 20257.4 | K31: =L30 -> 34275 | L31: 34275 | M31: =L31-K31 -> 0 | N31: =O30 -> 29354 | O31: 29366 | P31: =O31-N31 -> 12 | Q31: =R30 -> 34796 | R31: 34796 | S31: =R31-Q31 -> 0 | T31: =U30 -> 32171 | U31: 32171 | V31: =U31-T31 -> 0 | W31: =X30 -> 19904 | X31: 19915 | Y31: =X31-W31 -> 11 | Z31: =Y31+V31+S31+P31+M31 -> 23 | AA31: 167 | AB31: 75 | AC31: =Gen!T36 -> 707.94
A32: =Gen!B37 -> 43948 | B32: =Gen!C37 -> 0 | C32: 20276.16 | D32: 25996.2 | G32: 7.38 | I32: 30619.5 | J32: 20259.8 | K32: =L31 -> 34275 | L32: 34275 | M32: =L32-K32 -> 0 | N32: =O31 -> 29366 | O32: 29366 | P32: =O32-N32 -> 0 | Q32: =R31 -> 34796 | R32: 34808 | S32: =R32-Q32 -> 12 | T32: =U31 -> 32171 | U32: 32182 | V32: =U32-T32 -> 11 | W32: =X31 -> 19915 | X32: 19916 | Y32: =X32-W32 -> 1 | Z32: =Y32+V32+S32+P32+M32 -> 24 | AA32: 168 | AB32: 70 | AC32: =Gen!T37 -> 716.78
A33: =Gen!B38 -> 43949 | B33: =Gen!C38 -> 0 | C33: 19552 | D33: 25996.2 | G33: 100 | I33: 30621.9 | J33: 20261.4 | K33: =L32 -> 34275 | L33: 34275 | M33: =L33-K33 -> 0 | N33: =O32 -> 29366 | O33: 29379 | P33: =O33-N33 -> 13 | Q33: =R32 -> 34808 | R33: 34808 | S33: =R33-Q33 -> 0 | T33: =U32 -> 32182 | U33: 32182 | V33: =U33-T33 -> 0 | W33: =X32 -> 19916 | X33: 19928 | Y33: =X33-W33 -> 12 | Z33: =Y33+V33+S33+P33+M33 -> 25 | AA33: 167 | AB33: 70 | AC33: =Gen!T38 -> 690.55
A34: =Gen!B39 -> 43950 | B34: =Gen!C39 -> 0 | C34: 18761.45 | D34: 25996.2 | G34: 38.11 | I34: 30624.2 | J34: 20263.4 | K34: =L33 -> 34275 | L34: 34288 | M34: =L34-K34 -> 13 | N34: =O33 -> 29379 | O34: 29391 | P34: =O34-N34 -> 12 | Q34: =R33 -> 34808 | R34: 34808 | S34: =R34-Q34 -> 0 | T34: =U33 -> 32182 | U34: 32182 | V34: =U34-T34 -> 0 | W34: =X33 -> 19928 | X34: 19928 | Y34: =X34-W34 -> 0 | Z34: =Y34+V34+S34+P34+M34 -> 25 | AA34: 167 | AB34: 70 | AC34: =Gen!T39 -> 691.09
A35: =Gen!B40 -> 43951 | B35: =Gen!C40 -> 0 | C35: 18032.25 | D35: 25996.2 | I35: 30626.4 | J35: 20265.5 | K35: =L34 -> 34288 | L35: 34300 | M35: =L35-K35 -> 12 | N35: =O34 -> 29391 | O35: 29391 | P35: =O35-N35 -> 0 | Q35: =R34 -> 34808 | R35: 34808 | S35: =R35-Q35 -> 0 | T35: =U34 -> 32182 | U35: 32182 | V35: =U35-T35 -> 0 | W35: =X34 -> 19928 | X35: 19940 | Y35: =X35-W35 -> 12 | Z35: =Y35+V35+S35+P35+M35 -> 24 | AA35: 168 | AB35: 75 | AC35: =Gen!T40 -> 660.76
A36: =Gen!B41 -> 0 | B36: =Gen!C41 -> 0 | C36: 17371.49 | D36: 25996.2 | K36: =L35 -> 34300 | M36: =L36-K36 -> -34300 | N36: =O35 -> 29391 | P36: =O36-N36 -> -29391 | Q36: =R35 -> 34808 | S36: =R36-Q36 -> -34808 | T36: =U35 -> 32182 | V36: =U36-T36 -> -32182 | W36: =X35 -> 19940 | Y36: =X36-W36 -> -19940 | Z36: =Y36+V36+S36+P36+M36 -> -150621 | AC36: =Gen!T41 -> 0
A37: =Gen!B42 -> 0 | B37: =Gen!C42 -> 0 | K37: =L36 -> 0 | M37: =L37-K37 -> 0 | N37: =O36 -> 0 | P37: =O37-N37 -> 0 | Q37: =R36 -> 0 | S37: =R37-Q37 -> 0 | T37: =U36 -> 0 | V37: =U37-T37 -> 0 | W37: =X36 -> 0 | Y37: =X37-W37 -> 0 | Z37: =Y37+V37+S37+P37+M37 -> 0 | AC37: =Gen!T42 -> 0

Sheet Gen
E2: HLP REPORT APRIL 2020
G6: BILILA LODGE INVESTMENT LIMITED | W6: 1 | X6: 2 | Y6: 3 | Z6: 4 | AA6: 5 | AB6: 6 | AC6: 7 | AD6: 8 | AE6: 9 | AF6: 10 | AG6: 11
G7: Diesel Consumed by 500KVA Generator | N7: 500KVA Generator KWh | W7: Safari-STAFF | X7: Safari-STAFF | Y7: Lc/swg/gust | Z7: Eng pikcup | AA7: VIP Safari Car | AB7: GX Guest | AC7: GX Guest | AD7: T/Hillux/pur | AE7: TATA | AF7: MAN | AG7: F/Truck | AH7: Incenerator | AI7: A&K | AJ7: OTHER | AK7: TOTAL CO
B8: Date | C8: Occupancy % | D8: OPENING | E8: Received | F8: Schedule delivery | G8: Company | H8: 1 | I8: 2 | J8: 3 | K8: 4 | L8: 5 | M8: 6 | N8: 1 | O8: 2 | P8: 3 | Q8: 4 | R8: 5 | S8: 6 | T8: Total Diseal Consumed | U8: Total Kwh generated | V8: Average Diesel/Kwh | W8: T 128 AXJ | X8: T 134 AXJ | Y8: T 499 AXG | Z8: T 217 CHV | AA8: T 214 CHV | AB8: T 139 AXE | AC8: T 242 AXN - SABASABA | AD8: T 476 AWZ | AE8: T 226 AUQ | AF8: T 308 CLD | AG8: T 852 AWU | AH8: Machine ENG | AI8: Vehicle | AJ8: Vehicle | AS8: Total Diseal Consumed Gen & Vehicle | AT8: Total cost /Day (TSH) | AU8: BALANCE
D9: =[5]Gen!$D$43 -> 41048.87 | T9: =SUM(G9:M9) -> 0 | U9: =SUM(N9:S9) -> 0 | AS9: =SUM(AK9+T9) -> 0 | AU9: 38784.7
T10: =SUM(G10:M10) -> 0 | U10: =SUM(N10:S10) -> 0 | V10: =SUM(O10:T10) -> 0 | AK10: =SUM(W10:AJ10) -> 0 | AS10: =SUM(AK10+T10) -> 0
B11: 43922 | D11: =SUM(D9+E11) -> 41048.87 | I11: 289.75 | K11: 291 | M11: 270.21 | O11: 656 | Q11: 727 | S11: 668 | T11: =SUM(G11:M11) -> 850.96 | U11: =SUM(N11:S11) -> 2051 | V11: =T11/U11 -> 0.41490005 | Y11: 49.37 | AK11: =SUM(W11:AJ11) -> 49.37 | AS11: =SUM(AK11+T11) -> 900.33 | AT11: =AS11*AV11 -> 0 | AU11: =D11 -> 41048.87
B12: 43923 | D12: =SUM(D11-AS11+E12) -> 40148.54 | K12: 212.16 | L12: 302.41 | M12: 351.68 | Q12: 582 | R12: 715 | S12: 791 | T12: =SUM(G12:M12) -> 866.25 | U12: =SUM(N12:S12) -> 2088 | V12: =T12/U12 -> 0.41487069 | AA12: 9.39 | AK12: =SUM(W12:AJ12) -> 9.39 | AS12: =SUM(AK12+T12) -> 875.64 | AT12: =AS12*AV12 -> 0 | AU12: =D12 -> 40148.54
B13: 43924 | D13: =SUM(D12-AS12+E13) -> 39272.9 | I13: 330.06 | K13: 304.46 | L13: 198.4 | O13: 716 | Q13: 632 | R13: 550 | T13: =SUM(G13:M13) -> 832.92 | U13: =SUM(N13:S13) -> 1898 | V13: =T13/U13 -> 0.43884089 | X13: 18.02 | AK13: =SUM(W13:AJ13) -> 18.02 | AS13: =SUM(AK13+T13) -> 850.94 | AT13: =AS13*AV13 -> 0 | AU13: =D13 -> 39272.9
B14: 43925 | D14: =SUM(D13-AS13+E14) -> 38421.96 | I14: 219.03 | L14: 276.5 | M14: 294.02 | O14: 537 | R14: 627 | S14: 651 | T14: =SUM(G14:M14) -> 789.55 | U14: =SUM(N14:S14) -> 1815 | V14: =T14/U14 -> 0.43501377 | Z14: 35.53 | AA14: 24.84 | AH14: 600 | AK14: =SUM(W14:AJ14) -> 660.37 | AS14: =SUM(AK14+T14) -> 1449.92 | AT14: =AS14*AV14 -> 0 | AU14: =D14 -> 38421.96
B15: 43926 | D15: =SUM(D14-AS14+E15) -> 36972.04 | I15: 299.84 | K15: 290.92 | L15: 222.58 | O15: 601 | Q15: 664 | R15: 576 | T15: =SUM(G15:M15) -> 813.34 | U15: =SUM(N15:S15) -> 1841 | V15: =T15/U15 -> 0.4417925 | AA15: 34.28 | AK15: =SUM(W15:AJ15) -> 34.28 | AS15: =SUM(AK15+T15) -> 847.62 | AT15: =AS15*AV15 -> 0 | AU15: =D15 -> 36972.04
B16: 43927 | D16: =SUM(D15-AS15+E16) -> 36124.42 | F16: 15000 | G16: RAHA | K16: 303.21 | L16: 236.21 | M16: 218.11 | Q16: 691 | R16: 493 | S16: 605 | T16: =SUM(G16:M16) -> 757.53 | U16: =SUM(N16:S16) -> 1789 | V16: =T16/U16 -> 0.42343767 | AK16: =SUM(W16:AJ16) -> 0 | AS16: =SUM(AK16+T16) -> 757.53 | AT16: =AS16*AV16 -> 0 | AU16: =D16 -> 36124.42
B17: 43928 | D17: =SUM(D16-AS16+E17) -> 50366.89 | E17: 15000 | I17: 282.75 | K17: 195.24 | M17: 305.56 | O17: 655 | Q17: 568 | S17: 644 | T17: =SUM(G17:M17) -> 783.55 | U17: =SUM(N17:S17) -> 1867 | V17: =T17/U17 -> 0.41968399 | X17: 24.64 | AA17: 83.56 | AK17: =SUM(W17:AJ17) -> 108.2 | AS17: =SUM(AK17+T17) -> 891.75 | AT17: =AS17*AV17 -> 0 | AU17: =D17 -> 50366.89
B18: 43929 | D18: =SUM(D17-AS17+E18) -> 49475.14 | K18: 217.14 | L18: 295.59 | M18: 318.54 | Q18: 480 | R18: 705 | S18: 755 | T18: =SUM(G18:M18) -> 831.27 | U18: =SUM(N18:S18) -> 1940 | V18: =T18/U18 -> 0.42848969 | AK18: =SUM(W18:AJ18) -> 0 | AS18: =SUM(AK18+T18) -> 831.27 | AT18: =AS18*AV18 -> 0 | AU18: =D18 -> 49475.14
B19: 43930 | D19: =SUM(D18-AS18+E19) -> 48643.87 | I19: 242.98 | L19: 258.63 | M19: 304.71 | O19: 564 | R19: 613 | S19: 705 | T19: =SUM(G19:M19) -> 806.32 | U19: =SUM(N19:S19) -> 1882 | V19: =T19/U19 -> 0.42843783 | AK19: =SUM(W19:AJ19) -> 0 | AS19: =SUM(AK19+T19) -> 806.32 | AT19: =AS19*AV19 -> 0 | AU19: =D19 -> 48643.87
B20: 43931 | D20: =SUM(D19-AS19+E20) -> 47837.55 | I20: 361.49 | L20: 165.05 | M20: 297.21 | O20: 791 | R20: 462 | S20: 682 | T20: =SUM(G20:M20) -> 823.75 | U20: =SUM(N20:S20) -> 1935 | V20: =T20/U20 -> 0.42571059 | AK20: =SUM(W20:AJ20) -> 0 | AS20: =SUM(AK20+T20) -> 823.75 | AT20: =AS20*AV20 -> 0 | AU20: =D20 -> 47837.55
B21: 43932 | D21: =SUM(D20-AS20+E21) -> 47013.8 | I21: 291.7 | L21: 231.87 | M21: 259.1 | O21: 714 | R21: 555 | S21: 614 | T21: =SUM(G21:M21) -> 782.67 | U21: =SUM(N21:S21) -> 1883 | V21: =T21/U21 -> 0.41565056 | AK21: =SUM(W21:AJ21) -> 0 | AS21: =SUM(AK21+T21) -> 782.67 | AT21: =AS21*AV21 -> 0 | AU21: =D21 -> 47013.8
B22: 43933 | D22: =SUM(D21-AS21+E22) -> 46231.13 | I22: 417.51 | M22: 359.29 | O22: 1018 | S22: 859 | T22: =SUM(G22:M22) -> 776.8 | U22: =SUM(N22:S22) -> 1877 | V22: =T22/U22 -> 0.41385189 | AK22: =SUM(W22:AJ22) -> 0 | AS22: =SUM(AK22+T22) -> 776.8 | AT22: =AS22*AV22 -> 0 | AU22: =D22 -> 46231.13
B23: 43934 | D23: =SUM(D22-AS22+E23) -> 45454.33 | I23: 395.24 | L23: 376.48 | O23: 929 | R23: 867 | T23: =SUM(G23:M23) -> 771.72 | U23: =SUM(N23:S23) -> 1796 | V23: =T23/U23 -> 0.4296882 | AA23: 19.86 | AK23: =SUM(W23:AJ23) -> 19.86 | AS23: =SUM(AK23+T23) -> 791.58 | AT23: =AS23*AV23 -> 0 | AU23: =D23 -> 45454.33
B24: 43935 | D24: =SUM(D23-AS23+E24) -> 44662.75 | I24: 344.04 | M24: 416.58 | O24: 828 | S24: 961 | T24: =SUM(G24:M24) -> 760.62 | U24: =SUM(N24:S24) -> 1789 | V24: =T24/U24 -> 0.4251649 | AK24: =SUM(W24:AJ24) -> 0 | AS24: =SUM(AK24+T24) -> 760.62 | AT24: =AS24*AV24 -> 0 | AU24: =D24 -> 44662.75
B25: 43936 | D25: =SUM(D24-AS24+E25) -> 43902.13 | K25: 356.88 | L25: 429.31 | Q25: 817 | R25: 1006 | T25: =SUM(G25:M25) -> 786.19 | U25: =SUM(N25:S25) -> 1823 | V25: =T25/U25 -> 0.43126166 | AK25: =SUM(W25:AJ25) -> 0 | AS25: =SUM(AK25+T25) -> 786.19 | AT25: =AS25*AV25 -> 0 | AU25: =D25 -> 43902.13
B26: 43937 | D26: =SUM(D25-AS25+E26) -> 43115.94 | I26: 321.24 | M26: 433.03 | O26: 745 | S26: 1037 | T26: =SUM(G26:M26) -> 754.27 | U26: =SUM(N26:S26) -> 1782 | V26: =T26/U26 -> 0.4232716 | AK26: =SUM(W26:AJ26) -> 0 | AS26: =SUM(AK26+T26) -> 754.27 | AT26: =AS26*AV26 -> 0 | AU26: =D26 -> 43115.94
B27: 43938 | D27: =SUM(D26-AS26+E27) -> 42361.67 | K27: 441.25 | L27: 340.68 | Q27: 1042 | R27: 815 | T27: =SUM(G27:M27) -> 781.93 | U27: =SUM(N27:S27) -> 1857 | V27: =T27/U27 -> 0.42107162 | AA27: 18.45 | AK27: =SUM(W27:AJ27) -> 18.45 | AS27: =SUM(AK27+T27) -> 800.38 | AT27: =AS27*AV27 -> 0 | AU27: =D27 -> 42361.67
B28: 43939 | D28: =SUM(D27-AS27+E28) -> 41561.29 | I28: 408.61 | M28: 335.61 | O28: 963 | S28: 793 | T28: =SUM(G28:M28) -> 744.22 | U28: =SUM(N28:S28) -> 1756 | V28: =T28/U28 -> 0.42381549 | AK28: =SUM(W28:AJ28) -> 0 | AS28: =SUM(AK28+T28) -> 744.22 | AT28: =AS28*AV28 -> 0 | AU28: =D28 -> 41561.29
B29: 43940 | D29: =SUM(D28-AS28+E29) -> 40817.07 | K29: 369.03 | L29: 371.02 | Q29: 890 | R29: 838 | T29: =SUM(G29:M29) -> 740.05 | U29: =SUM(N29:S29) -> 1728 | V29: =T29/U29 -> 0.42826968 | Y29: 32.55 | AA29: 19.49 | AK29: =SUM(W29:AJ29) -> 52.04 | AS29: =SUM(AK29+T29) -> 792.09 | AT29: =AS29*AV29 -> 0 | AU29: =D29 -> 40817.07
B30: 43941 | D30: =SUM(D29-AS29+E30) -> 40024.98 | I30: 368.39 | M30: 363.08 | O30: 884 | S30: 809 | T30: =SUM(G30:M30) -> 731.47 | U30: =SUM(N30:S30) -> 1693 | V30: =T30/U30 -> 0.43205552 | AK30: =SUM(W30:AJ30) -> 0 | AS30: =SUM(AK30+T30) -> 731.47 | AT30: =AS30*AV30 -> 0 | AU30: =D30 -> 40024.98
B31: 43942 | D31: =SUM(D30-AS30+E31) -> 39293.51 | K31: 376.22 | L31: 371.05 | Q31: 870 | R31: 857 | T31: =SUM(G31:M31) -> 747.27 | U31: =SUM(N31:S31) -> 1727 | V31: =T31/U31 -> 0.43269832 | AJ31: 180 | AK31: =SUM(W31:AJ31) -> 180 | AS31: =SUM(AK31+T31) -> 927.27 | AT31: =AS31*AV31 -> 0 | AU31: =D31 -> 39293.51
B32: 43943 | D32: =SUM(D31-AS31+E32) -> 38366.24 | I32: 362.98 | M32: 346.15 | O32: 895 | S32: 825 | T32: =SUM(G32:M32) -> 709.13 | U32: =SUM(N32:S32) -> 1720 | V32: =T32/U32 -> 0.41228488 | Y32: 23.51 | AJ32: 100 | AK32: =SUM(W32:AJ32) -> 123.51 | AS32: =SUM(AK32+T32) -> 832.64 | AT32: =AS32*AV32 -> 0 | AU32: =D32 -> 38366.24
B33: 43944 | D33: =SUM(D32-AS32+E33) -> 49533.6 | E33: 12000 | F33: 12000 | G33: PUMA | K33: 319.12 | L33: 351.73 | Q33: 739 | R33: 815 | T33: =SUM(G33:M33) -> 670.85 | U33: =SUM(N33:S33) -> 1554 | V33: =T33/U33 -> 0.43169241 | AK33: =SUM(W33:AJ33) -> 0 | AS33: =SUM(AK33+T33) -> 670.85 | AT33: =AS33*AV33 -> 0 | AU33: =D33 -> 49533.6 | AV33: =SUM(AV32) -> 0
B34: 43945 | D34: =SUM(D33-AS33+E34) -> 48862.75 | I34: 356.44 | M34: 378.33 | O34: 889 | S34: 833 | T34: =SUM(G34:M34) -> 734.77 | U34: =SUM(N34:S34) -> 1722 | V34: =T34/U34 -> 0.4266957 | AA34: 74.15 | AJ34: 180 | AK34: =SUM(W34:AJ34) -> 254.15 | AS34: =SUM(AK34+T34) -> 988.92 | AT34: =AS34*AV34 -> 0 | AU34: =D34 -> 48862.75 | AV34: =SUM(AV33) -> 0
B35: 43946 | D35: =SUM(D34-AS34+E35) -> 47873.83 | K35: 350.48 | L35: 357.77 | Q35: 854 | R35: 858 | T35: =SUM(G35:M35) -> 708.25 | U35: =SUM(N35:S35) -> 1712 | V35: =T35/U35 -> 0.41369743 | AJ35: 133.02 | AK35: =SUM(W35:AJ35) -> 133.02 | AS35: =SUM(AK35+T35) -> 841.27 | AT35: =AS35*AV35 -> 0 | AU35: =D35 -> 47873.83 | AV35: =SUM(AV34) -> 0
B36: 43947 | D36: =SUM(D35-AS35+E36) -> 47032.56 | I36: 351.88 | M36: 356.06 | O36: 884 | S36: 796 | T36: =SUM(G36:M36) -> 707.94 | U36: =SUM(N36:S36) -> 1680 | V36: =T36/U36 -> 0.42139286 | Z36: 52.26 | AK36: =SUM(W36:AJ36) -> 52.26 | AS36: =SUM(AK36+T36) -> 760.2 | AT36: =AS36*AV36 -> 0 | AU36: =D36 -> 47032.56 | AV36: =SUM(AV35) -> 0
B37: 43948 | D37: =SUM(D36-AS36+E37) -> 46272.36 | K37: 372.38 | L37: 344.4 | Q37: 897 | R37: 824 | T37: =SUM(G37:M37) -> 716.78 | U37: =SUM(N37:S37) -> 1721 | V37: =T37/U37 -> 0.41649041 | AA37: 7.38 | AK37: =SUM(W37:AJ37) -> 7.38 | AS37: =SUM(AK37+T37) -> 724.16 | AT37: =AS37*AV37 -> 0 | AU37: =D37 -> 46272.36 | AV37: =SUM(AV36) -> 0
B38: 43949 | D38: =SUM(D37-AS37+E38) -> 45548.2 | I38: 339.69 | M38: 350.86 | O38: 835 | S38: 802 | T38: =SUM(G38:M38) -> 690.55 | U38: =SUM(N38:S38) -> 1637 | V38: =T38/U38 -> 0.42183873 | AJ38: 100 | AK38: =SUM(W38:AJ38) -> 100 | AS38: =SUM(AK38+T38) -> 790.55 | AT38: =AS38*AV38 -> 0 | AU38: =D38 -> 45548.2 | AV38: =SUM(AV37) -> 0
B39: 43950 | D39: =SUM(D38-AS38+E39) -> 44757.65 | H39: 352.6 | I39: 338.49 | N39: 816 | O39: 828 | T39: =SUM(G39:M39) -> 691.09 | U39: =SUM(N39:S39) -> 1644 | V39: =T39/U39 -> 0.42037105 | X39: 38.11 | AK39: =SUM(W39:AJ39) -> 38.11 | AS39: =SUM(AK39+T39) -> 729.2 | AT39: =AS39*AV39 -> 0 | AU39: =D39 -> 44757.65 | AV39: =SUM(AV38) -> 0
B40: 43951 | D40: =SUM(D39-AS39+E40) -> 44028.45 | H40: 326.31 | M40: 334.45 | N40: 778 | S40: 786 | T40: =SUM(G40:M40) -> 660.76 | U40: =SUM(N40:S40) -> 1564 | V40: =T40/U40 -> 0.42248082 | AK40: =SUM(W40:AJ40) -> 0 | AS40: =SUM(AK40+T40) -> 660.76 | AT40: =AS40*AV40 -> 0 | AU40: =D40 -> 44028.45 | AV40: =SUM(AV39) -> 0
D41: =SUM(D40-AS40+E41) -> 43367.69 | T41: =SUM(G41:M41) -> 0 | U41: =SUM(N41:S41) -> 0 | V41: =T41/U41 -> #DIV/0! | AK41: =SUM(W41:AJ41) -> 0 | AS41: =SUM(AK41+T41) -> 0 | AT41: =AS41*AV41 -> 0 | AU41: =D41 -> 43367.69 | AV41: =SUM(AV40) -> 0
D42: =SUM(D41-AS41+E42) -> 43367.69 | T42: =SUM(G42:M42) -> 0 | U42: =SUM(N42:S42) -> 0 | AK42: =SUM(W42:AJ42) -> 0 | AS42: =SUM(AK42+T42) -> 0 | AT42: =AS42*AV42 -> 0 | AU42: =D42 -> 43367.69
B43: BF | C43: =AVERAGE(C11:C42) -> #DIV/0! | D43: =SUM(D42-AS42+E43) -> 43367.69 | T43: =SUM(G43:M43) -> 0 | U43: =SUM(N43:S43) -> 0 | AK43: =SUM(W43:AJ43) -> 0 | AS43: =SUM(AK43+T43) -> 0 | AT43: =AS43*AV43 -> 0 | AU43: =D43 -> 43367.69
T44: =SUM(G44:M44) -> 0 | AK44: =SUM(W44:AJ44) -> 0 | AS44: =T44+AK44 -> 0 | AT44: =AS44*AV44 -> 0
E45: =SUM(E11:E44) -> 27000 | F45: =SUM(F11:F42) -> 27000 | G45: =SUM(G11:G44) -> 0 | H45: =SUM(H11:H44) -> 678.91 | I45: =SUM(I11:I44) -> 6322.11 | J45: =SUM(J11:J44) -> 0 | K45: =SUM(K11:K44) -> 4399.49 | L45: =SUM(L11:L44) -> 5129.68 | M45: =SUM(M11:M44) -> 6292.58 | N45: =SUM(N11:N44) -> 1594 | ... P45: =SUM(P11:P44) -> 0 | Q45: =SUM(Q11:Q43) -> 10453 | R45: =SUM(R11:R44) -> 12176 | S45: =SUM(S11:S44) -> 14616 | T45: =SUM(G45:M45) -> 22822.77 | U45: =SUM(N45:S45) -> 53771 | V45: =SUM(V11:V42) -> #DIV/0! | W45: =SUM(W9:W44) -> 0 | X45: =SUM(X9:X44) -> 80.77 | Y45: =SUM(Y9:Y44) -> 105.43 | Z45: =SUM(Z9:Z44) -> 87.79 | AA45: =SUM(AA9:AA44) -> 291.4 | AB45: =SUM(AB9:AB44) -> 0 | AC45: =SUM(AC9:AC44) -> 0 | AD45: =SUM(AD10:AD44) -> 0 | AE45: =SUM(AE10:AE44) -> 0 | AF45: =SUM(AF9:AF44) -> 0 | AG45: =SUM(AG9:AG44) -> 0 | AH45: =SUM(AH9:AH44) -> 600 | AI45: =SUM(AI9:AI43) -> 0 | AJ45: =SUM(AJ9:AJ39) -> 693.02 | AK45: =SUM(AK9:AK44) -> 1858.41 | AS45: =SUM(AS11:AS43) -> 24681.18 | AT45: =SUM(AT11:AT44) -> 0
B46: Nb Day
U47: =T45*2315 -> 52834713 | V47: TZS | AS47: =AS45*2143 -> 52891769 | AT47: TZS
B48: Av. Occ | U48: =U47/2289 -> 23082.006 | V48: USD | AS48: =AS47/2289 -> 23106.933 | AT48: USD
C50: A & K VEHICLES | I50: MAULY VEHICLES | O50: GREEN LAND VEHICLES | U50: OTHERS VEHICLES
C51: Date | D51: Vehicles | E51: Liters | F51: Driver name | G51: Authority manager | I51: Date | J51: Vehicles | K51: Liters | L51: Driver name | M51: Authority manager | O51: Date | P51: Vehicles | Q51: Liters | R51: Driver name | S51: Authorized Manager | U51: Date | V51: Vehicles | W51: Liters | X51: Driver name | Y51: Athorized Manager | Z51: Reasons
U52: 43942 | V52: SU35656 | W52: 180 | X52: Kenedi | Y52: vedastus | Z52: road repair
U53: 43943 | V53: SU35657 | W53: 100 | X53: Kenedi | Y53: vedastus | Z53: road repair
U54: 43945 | V54: SU35656 | W54: 180 | X54: Kenedi | Y54: vedastus | Z54: road repair
U55: 43946 | V55: SU35657 | W55: 133.02 | X55: Kenedi | Y55: vedastus | Z55: road repair
U56: 43949 | V56: SU35658 | W56: 100 | X56: Kenedi | Y56: vedastus | Z56: road repair

Sheet Energy Graph
A1: Date | B1: Usage KW | C1: Occ % | D1: Cost per room Total Occ | E1: Cost per room Guest Occ
A2: =Gen!B11 -> 43922 | B2: =Gen!U11 -> 2051 | C2: =Gen!C11 -> 0 | D2: =SUM('[1]Summery Report'!#REF!) -> #REF! | E2: =SUM('[1]Summery Report'!#REF!) -> #REF! | F2: 0.1
A3: =Gen!B12 -> 43923 | B3: =Gen!U12 -> 2088 | C3: =Gen!C12 -> 0 | D3: =SUM('[1]Summery Report'!#REF!) -> #REF! | E3: =SUM('[1]Summery Report'!#REF!) -> #REF! | F3: 0.1375
A4: =Gen!B13 -> 43924 | B4: =Gen!U13 -> 1898 | C4: =Gen!C13 -> 0 | D4: =SUM('[1]Summery Report'!#REF!) -> #REF! | E4: =SUM('[1]Summery Report'!#REF!) -> #REF! | F4: 0.0875
A5: =Gen!B14 -> 43925 | B5: =Gen!U14 -> 1815 | C5: =Gen!C14 -> 0 | D5: =SUM('[1]Summery Report'!#REF!) -> #REF! | E5: =SUM('[1]Summery Report'!#REF!) -> #REF! | F5: 0.225
A6: =Gen!B15 -> 43926 | B6: =Gen!U15 -> 1841 | C6: =Gen!C15 -> 0 | D6: =SUM('[1]Summery Report'!#REF!) -> #REF! | E6: =SUM('[1]Summery Report'!#REF!) -> #REF! | F6: 0.2
A7: =Gen!B16 -> 43927 | B7: =Gen!U16 -> 1789 | C7: =Gen!C16 -> 0 | D7: =SUM('[1]Summery Report'!#REF!) -> #REF! | E7: =SUM('[1]Summery Report'!#REF!) -> #REF! | F7: 0.35
A8: =Gen!B17 -> 43928 | B8: =Gen!U17 -> 1867 | C8: =Gen!C17 -> 0 | D8: =SUM('[1]Summery Report'!#REF!) -> #REF! | E8: =SUM('[1]Summery Report'!#REF!) -> #REF! | F8: 0.375
A9: =Gen!B18 -> 43929 | B9: =Gen!U18 -> 1940 | C9: =Gen!C18 -> 0 | D9: =SUM('[1]Summery Report'!#REF!) -> #REF! | E9: =SUM('[1]Summery Report'!#REF!) -> #REF! | F9: 0.325
A10: =Gen!B19 -> 43930 | B10: =Gen!U19 -> 1882 | C10: =Gen!C19 -> 0 | D10: =SUM('[1]Summery Report'!#REF!) -> #REF! | E10: =SUM('[1]Summery Report'!#REF!) -> #REF! | F10: 0.75
A11: =Gen!B20 -> 43931 | B11: =Gen!U20 -> 1935 | C11: =Gen!C20 -> 0 | D11: =SUM('[1]Summery Report'!#REF!) -> #REF! | E11: =SUM('[1]Summery Report'!#REF!) -> #REF! | F11: 0.7625
A12: =Gen!B21 -> 43932 | B12: =Gen!U21 -> 1883 | C12: =Gen!C21 -> 0 | D12: =SUM('[1]Summery Report'!#REF!) -> #REF! | E12: =SUM('[1]Summery Report'!#REF!) -> #REF! | F12: 0.1625
A13: =Gen!B22 -> 43933 | B13: =Gen!U22 -> 1877 | C13: =Gen!C22 -> 0 | D13: =SUM('[1]Summery Report'!#REF!) -> #REF! | E13: =SUM('[1]Summery Report'!#REF!) -> #REF! | F13: 0.1125
... A32: =Gen!B41 -> 0 | B32: =Gen!U41 -> 0 | C32: =Gen!C41 -> 0 | D32: =SUM('[1]Summery Report'!#REF!) -> #REF! | E32: =SUM('[1]Summery Report'!#REF!) -> #REF! | F32: 0.175
A33: =Gen!B42 -> 0 | B33: =Gen!U42 -> 0 | C33: =Gen!C42 -> 0

Sheet Lpg (2)
C3: Four Sasons Safari Lodge Serengeti
G6: VALUE | H6: Cost
A7: DATE | B7: A | C7: B | D7: C | F7: Meter Reading | G7: Total | H7: Occu | I7: No.of | J7: Kg
B8: 2Ton 85% | C8: 1Ton 85(%) | D8: 1Ton 85% | F8: consumption | G8: Consumption Kg | H8: % | I8: pax | J8: per pax
F9: 70924
A10: =Gen!B11 -> 43922 | B10: 16 | C10: 85 | D10: 66 | F10: 70938 | G10: =(F10-F9)*4.4 -> 61.6 | H10: =Gen!C11 -> 0 | I10: =SUM(F10/H10) -> #DIV/0! | J10: =SUM(G10/I10) -> #DIV/0!
A11: =Gen!B12 -> 43923 | B11: 16 | C11: 85 | D11: 66 | F11: 70953 | G11: =(F11-F10)*4.4 -> 66 | H11: =Gen!C12 -> 0 | I11: =SUM(F11/H11) -> #DIV/0! | J11: =SUM(G11/I11) -> #DIV/0!
A12: =Gen!B13 -> 43924 | B12: 15 | C12: 85 | D12: 66 | F12: 70961.53 | G12: =(F12-F11)*4.4 -> 37.532 | H12: =Gen!C13 -> 0 | I12: =SUM(F12/H12) -> #DIV/0! | J12: =SUM(G12/I12) -> #DIV/0!
A13: =Gen!B14 -> 43925 | B13: 14 | C13: 85 | D13: 66 | E13: 85 | F13: 70968.68 | G13: =(F13-F12)*4.4 -> 31.46 | H13: =Gen!C14 -> 0 | I13: =SUM(F13/H13) -> #DIV/0! | J13: =SUM(G13/I13) -> #DIV/0!
A14: =Gen!B15 -> 43926 | B14: 13 | C14: 85 | D14: 66 | E14: 85 | F14: 70975 | G14: =(F14-F13)*4.4 -> 27.808 | H14: =Gen!C15 -> 0 | I14: =SUM(F14/H14) -> #DIV/0! | J14: =SUM(G14/I14) -> #DIV/0!
A15: =Gen!B16 -> 43927 | B15: 13 | C15: 85 | D15: 66 | F15: 70978.32 | G15: =(F15-F14)*4.4 -> 14.608 | H15: =Gen!C16 -> 0 | I15: =SUM(F15/H15) -> #DIV/0! | J15: =SUM(G15/I15) -> #DIV/0!
A16: =Gen!B17 -> 43928 | B16: 13 | C16: 85 | D16: 66 | F16: 70984.05 | G16: =(F16-F15)*4.4 -> 25.212 | H16: =Gen!C17 -> 0 | I16: =SUM(F16/H16) -> #DIV/0! | J16: =SUM(G16/I16) -> #DIV/0!
A17: =Gen!B18 -> 43929 | B17: 13 | C17: 85 | D17: 66 | F17: 70992.3 | G17: =(F17-F16)*4.4 -> 36.3 | H17: =Gen!C18 -> 0 | I17: =SUM(F17/H17) -> #DIV/0! | J17: =SUM(G17/I17) -> #DIV/0!
A18: =Gen!B19 -> 43930 | B18: 13 | C18: 85 | D18: 66 | F18: 70998.19 | G18: =(F18-F17)*4.4 -> 25.916 | H18: =Gen!C19 -> 0 | I18: =SUM(F18/H18) -> #DIV/0! | J18: =SUM(G18/I18) -> #DIV/0!
A19: =Gen!B20 -> 43931 | B19: 12 | C19: 85 | D19: 66 | F19: 71006.04 | G19: =(F19-F18)*4.4 -> 34.54 | H19: =Gen!C20 -> 0 | I19: =SUM(F19/H19) -> #DIV/0! | J19: =SUM(G19/I19) -> #DIV/0!
A20: =Gen!B21 -> 43932 | B20: 12 | C20: 85 | D20: 66 | F20: 71014.77 | G20: =(F20-F19)*4.4 -> 38.412 | H20: =Gen!C21 -> 0 | I20: =SUM(F20/H20) -> #DIV/0! | J20: =SUM(G20/I20) -> #DIV/0!
A21: =Gen!B22 -> 43933 | B21: 8 | C21: 85 | D21: 66 | F21: 71022.77 | G21: =(F21-F20)*4.4 -> 35.2 | H21: =Gen!C22 -> 0 | I21: =SUM(F21/H21) -> #DIV/0! | J21: =SUM(G21/I21) -> #DIV/0!
A22: =Gen!B23 -> 43934 | B22: 8 | C22: 85 | D22: 66 | E22: 75 | F22: 71030.96 | G22: =(F22-F21)*4.4 -> 36.036 | H22: =Gen!C23 -> 0 | I22: =SUM(F22/H22) -> #DIV/0! | J22: =SUM(G22/I22) -> #DIV/0!
A23: =Gen!B24 -> 43935 | B23: 6 | C23: 85 | D23: 66 | E23: 75 | F23: 71039 | G23: =(F23-F22)*4.4 -> 35.376 | H23: =Gen!C24 -> 0 | I23: =SUM(F23/H23) -> #DIV/0! | J23: =SUM(G23/I23) -> #DIV/0!
A24: =Gen!B25 -> 43936 | B24: 5 | C24: 85 | D24: 66 | F24: 71047.09 | G24: =(F24-F23)*4.4 -> 35.596 | H24: =Gen!C25 -> 0 | I24: =SUM(F24/H24) -> #DIV/0! | J24: =SUM(G24/I24) -> #DIV/0!
A25: =Gen!B26 -> 43937 | B25: 5 | C25: 85 | D25: 66 | F25: 71054.03 | G25: =(F25-F24)*4.4 -> 30.536 | H25: =Gen!C26 -> 0 | I25: =SUM(F25/H25) -> #DIV/0! | J25: =SUM(G25/I25) -> #DIV/0!
A26: =Gen!B27 -> 43938 | B26: 5 | C26: 85 | D26: 66 | F26: 71061.09 | G26: =(F26-F25)*4.4 -> 31.064 | H26: =Gen!C27 -> 0 | I26: =SUM(F26/H26) -> #DIV/0! | J26: =SUM(G26/I26) -> #DIV/0!
A27: =Gen!B28 -> 43939 | B27: 4 | C27: 85 | D27: 66 | F27: 71068.5 | G27: =(F27-F26)*4.4 -> 32.604 | H27: =Gen!C28 -> 0 | I27: =SUM(F27/H27) -> #DIV/0! | J27: =SUM(G27/I27) -> #DIV/0!
A28: =Gen!B29 -> 43940 | B28: 2 | C28: 85 | D28: 66 | F28: 71075.57 | G28: =(F28-F27)*4.4 -> 31.108 | H28: =Gen!C29 -> 0 | I28: =SUM(F28/H28) -> #DIV/0! | J28: =SUM(G28/I28) -> #DIV/0!
A29: =Gen!B30 -> 43941 | B29: 2 | C29: 85 | D29: 66 | F29: 71082.21 | G29: =(F29-F28)*4.4 -> 29.216 | H29: =Gen!C30 -> 0 | I29: =SUM(F29/H29) -> #DIV/0! | J29: =SUM(G29/I29) -> #DIV/0!
A30: =Gen!B31 -> 43942 | B30: 2 | C30: 85 | D30: 66 | F30: 71089.81 | G30: =(F30-F29)*4.4 -> 33.44 | H30: =Gen!C31 -> 0 | I30: =SUM(F30/H30) -> #DIV/0! | J30: =SUM(G30/I30) -> #DIV/0!
A31: =Gen!B32 -> 43943 | B31: 85 | C31: 85 | D31: 64 | F31: 71096.26 | G31: =(F31-F30)*4.4 -> 28.38 | H31: =Gen!C32 -> 0 | I31: =SUM(F31/H31) -> #DIV/0! | J31: =SUM(G31/I31) -> #DIV/0!
A32: =Gen!B33 -> 43944 | B32: 85 | C32: 85 | D32: 62 | F32: 71104.26 | G32: =(F32-F31)*4.4 -> 35.2 | H32: =Gen!C33 -> 0 | I32: =SUM(F32/H32) -> #DIV/0! | J32: =SUM(G32/I32) -> #DIV/0!
A33: =Gen!B34 -> 43945 | B33: 85 | C33: 85 | D33: 60 | F33: 71112.92 | G33: =(F33-F32)*4.4 -> 38.104 | H33: =Gen!C34 -> 0 | I33: =SUM(F33/H33) -> #DIV/0! | J33: =SUM(G33/I33) -> #DIV/0!
A34: =Gen!B35 -> 43946 | B34: 85 | C34: 85 | D34: 58 | F34: 71119.36 | G34: =(F34-F33)*4.4 -> 28.336 | H34: =Gen!C35 -> 0 | I34: =SUM(F34/H34) -> #DIV/0! | J34: =SUM(G34/I34) -> #DIV/0!
A35: =Gen!B36 -> 43947 | B35: 85 | C35: 85 | D35: 56 | F35: 71126.79 | G35: =(F35-F34)*4.4 -> 32.692 | H35: =Gen!C36 -> 0 | I35: =SUM(F35/H35) -> #DIV/0! | J35: =SUM(G35/I35) -> #DIV/0!
... A40: =Gen!B41 -> 0 | B40: 85 | C40: 85 | D40: 45 | F40: 71159.98 | G40: =(F40-F39)*4.4 -> 27.852 | H40: =Gen!C41 -> 0 | I40: =SUM(F40/H40) -> #DIV/0! | J40: =SUM(G40/I40) -> #DIV/0!
A41: =Gen!B42 -> 0 | H41: =Gen!C42 -> 0 | I41: =SUM(F41/H41) -> #DIV/0!
C42: TOTAL USAGE | E42: =SUM(E10:E40) -> 320 | F42: =SUM(F10:F40) -> 2202637.5 | G42: =SUM(G10:G40) -> 1038.312
F45: =E12-E11 -> 0 | G45: =F45*4.4 -> 0

Sheet LPG_Graph
A1: Date | B1: Usage KG | C1: =Gen!C11 -> 0
A2: =Gen!B11 -> 43922 | B2: ='Lpg (2)'!G10 -> 61.6 | C2: =Gen!C11 -> 0
A3: =Gen!B12 -> 43923 | B3: ='Lpg (2)'!G11 -> 66 | C3: =Gen!C12 -> 0
A4: =Gen!B13 -> 43924 | B4: ='Lpg (2)'!G12 -> 37.532 | C4: =Gen!C13 -> 0
A5: =Gen!B14 -> 43925 | B5: ='Lpg (2)'!G13 -> 31.46 | C5: =Gen!C14 -> 0
A6: =Gen!B15 -> 43926 | B6: ='Lpg (2)'!G14 -> 27.808 | C6: =Gen!C15 -> 0
A7: =Gen!B16 -> 43927 | B7: ='Lpg (2)'!G15 -> 14.608 | C7: =Gen!C16 -> 0
A8: =Gen!B17 -> 43928 | B8: ='Lpg (2)'!G16 -> 25.212 | C8: =Gen!C17 -> 0
A9: =Gen!B18 -> 43929 | B9: ='Lpg (2)'!G17 -> 36.3 | C9: =Gen!C18 -> 0
A10: =Gen!B19 -> 43930 | B10: ='Lpg (2)'!G18 -> 25.916 | C10: =Gen!C19 -> 0
A11: =Gen!B20 -> 43931 | B11: ='Lpg (2)'!G19 -> 34.54 | C11: =Gen!C20 -> 0
A12: =Gen!B21 -> 43932 | B12: ='Lpg (2)'!G20 -> 38.412 | C12: =Gen!C21 -> 0
A13: =Gen!B22 -> 43933 | B13: ='Lpg (2)'!G21 -> 35.2 | C13: =Gen!C22 -> 0
... A32: =Gen!B41 -> 0 | B32: ='Lpg (2)'!G40 -> 27.852 | C32: =Gen!C41 -> 0

Sheet Water-Meter
A1: Four Seasons Safari Lodge Serengeti April 2020- Water Report
C2: Main Meter | F2: KITCHEN | I2: Amani café | L2: Main SW POOL | O2: Laundry | S2: BORE HOLE NO.1 METER READING | V2: BORE HOLE NO.2 METER READING | Y2: BORE HOLE NO.3 METER READING | AB2: BORE HOLE NO.4 METER READING | AE2: BORE HOLE NO.5 METER READING | AH2: BORE HOLE NO.6 METER READING | AK2: RAIN WATER - METER READING | AN2: TOTAL WATER PRODUCTION
A3: DATE | C3: Open Bal | D3: Final | E3: consumption | F3: Open Bal | G3: Final | H3: consumption | I3: Open Bal | J3: Final | K3: consumption | L3: Open Bal | M3: Final | N3: consumption | O3: Open Bal | P3: Final | Q3: consumption | R3: Total consumption
S4: OPEN | T4: FINAL | U4: PROD. | V4: OPEN | W4: FINAL | X4: PROD. | Y4: OPEN | Z4: FINAL | AA4: PROD. | AB4: OPEN | AC4: FINAL | AD4: M3 | AE4: OPEN | AF4: FINAL | AG4: M3 | AH4: OPEN | AI4: FINAL | AJ4: M3 | AK4: OPEN | AL4: FINAL | AM4: M3
C5: =D4 -> 0 | D5: ='[4]Water-Meter'!$D$36 -> 232607 | E5: =IF((D5-D4)<0,"0",(D5-D4)) -> 232607 | F5: =G4 -> 0 | G5: ='[4]Water-Meter'!$G$36 -> 38000 | H5: =IF((G5-G4)<0,"0",(G5-G4)) -> 38000 | I5: =J4 -> 0 | J5: ='[4]Water-Meter'!$J$36 -> 7890 | K5: =IF((J5-J4)<0,"0",(J5-J4)) -> 7890 | L5: =M4 -> 0 | M5: ='[4]Water-Meter'!$M$36 -> 11978 | N5: =IF((M5-M4)<0,"0",(M5-M4)) -> 11978 | O5: =P4 -> 0 | P5: 20100 | Q5: =IF((P5-P4)<0,"0",(P5-P4)) -> 20100 | T5: ='[4]Water-Meter'!$T$36 -> 51712 | U5: =V4 -> OPEN | V5: =W4 -> FINAL | W5: ='[4]Water-Meter'!$W$36 -> 71260 | Y5: =Z4 -> FINAL | Z5: ='[4]Water-Meter'!$Z$36 -> 80332 | AB5: =AC4 -> FINAL | AC5: ='[4]Water-Meter'!$AC$36 -> 13184 | AE5: =AF4 -> FINAL | AF5: ='[4]Water-Meter'!$AF$36 -> 17313 | AH5: =AI4 -> FINAL | AI5: ='[4]Water-Meter'!$AI$36 -> 24546 | AK5: =AL4 -> FINAL | AL5: ='[4]Water-Meter'!$AL$36 -> 15154
A6: =Gen!B11 -> 43922 | C6: =D5 -> 232607 | D6: 232645 | E6: =IF((D6-D5)<0,"0",(D6-D5)) -> 38 | F6: =G5 -> 38000 | G6: 38000 | H6: =IF((G6-G5)<0,"0",(G6-G5)) -> 0 | I6: =J5 -> 7890 | J6: 7891 | K6: =IF((J6-J5)<0,"0",(J6-J5)) -> 1 | L6: =M5 -> 11978 | M6: ='[4]Water-Meter'!$M$36 -> 11978 | N6: =IF((M6-M5)<0,"0",(M6-M5)) -> 0 | O6: =P5 -> 20100 | P6: 20101 | Q6: =IF((P6-P5)<0,"0",(P6-P5)) -> 1 | S6: =T5 -> 51712 | T6: 51787 | U6: =IF((T6-T5)<0,"0",(T6-T5)) -> 75 | V6: =W5 -> 71260 | W6: 71260 | X6: =IF((W6-W5)<0,"0",(W6-W5)) -> 0 | Y6: =Z5 -> 80332 | Z6: 80332 | AA6: =IF((Z6-Z5)<0,"0",(Z6-Z5)) -> 0 | AB6: =AC5 -> 13184 | AC6: 13184 | AD6: =IF((AC6-AC5)<0,"0",(AC6-AC5)) -> 0 | AE6: =AF5 -> 17313 | AF6: 17337 | AG6: =IF((AF6-AF5)<0,"0",(AF6-AF5)) -> 24 | AH6: =AI5 -> 24546 | AI6: 24546 | AJ6: =IF((AI7-AI5)<0,"0",(AI7-AI5)) -> 0 | AK6: =AL5 -> 15154 | AL6: 15154 | AM6: =IF((AL6-AL5)<0,"0",(AL6-AL5)) -> 0 | AN6: =U6+X6+AA6+AD6+AG6+AJ6+AM6 -> 99
A7: =Gen!B12 -> 43923 | C7: =D6 -> 232645 | D7: 232697 | E7: =IF((D7-D6)<0,"0",(D7-D6)) -> 52 | F7: =G6 -> 38000 | G7: 38000 | H7: =IF((G7-G6)<0,"0",(G7-G6)) -> 0 | I7: =J6 -> 7891 | J7: 7892 | K7: =IF((J7-J6)<0,"0",(J7-J6)) -> 1 | L7: =M6 -> 11978 | M7: 11978 | N7: =IF((M7-M6)<0,"0",(M7-M6)) -> 0 | O7: =P6 -> 20101 | P7: 20103 | Q7: =IF((P7-P6)<0,"0",(P7-P6)) -> 2 | S7: =T6 -> 51787 | T7: 51852 | U7: =IF((T7-T6)<0,"0",(T7-T6)) -> 65 | V7: =W6 -> 71260 | W7: 71260 | X7: =IF((W7-W6)<0,"0",(W7-W6)) -> 0 | Y7: =Z6 -> 80332 | Z7: 80332 | AA7: =IF((Z7-Z6)<0,"0",(Z7-Z6)) -> 0 | AB7: =AC6 -> 13184 | AC7: 13184 | AD7: =IF((AC7-AC6)<0,"0",(AC7-AC6)) -> 0 | AE7: =AF6 -> 17337 | AF7: 17361 | AG7: =IF((AF7-AF6)<0,"0",(AF7-AF6)) -> 24 | AH7: =AI6 -> 24546 | AI7: 24546 | AJ7: =IF((AI8-AI6)<0,"0",(AI8-AI6)) -> 0 | AK7: =AL6 -> 15154 | AL7: 15154 | AM7: =IF((AL7-AL6)<0,"0",(AL7-AL6)) -> 0 | AN7: =U7+X7+AA7+AD7+AG7+AJ7+AM7 -> 89
A8: =Gen!B13 -> 43924 | C8: =D7 -> 232697 | D8: 232723 | E8: =IF((D8-D7)<0,"0",(D8-D7)) -> 26 | F8: =G7 -> 38000 | G8: 38000 | H8: =IF((G8-G7)<0,"0",(G8-G7)) -> 0 | I8: =J7 -> 7892 | J8: 7893 | K8: =IF((J8-J7)<0,"0",(J8-J7)) -> 1 | L8: =M7 -> 11978 | M8: 11978 | N8: =IF((M8-M7)<0,"0",(M8-M7)) -> 0 | O8: =P7 -> 20103 | P8: 20104 | Q8: =IF((P8-P7)<0,"0",(P8-P7)) -> 1 | S8: =T7 -> 51852 | T8: 51912 | U8: =IF((T8-T7)<0,"0",(T8-T7)) -> 60 | V8: =W7 -> 71260 | W8: 71260 | X8: =IF((W8-W7)<0,"0",(W8-W7)) -> 0 | Y8: =Z7 -> 80332 | Z8: 80332 | AA8: =IF((Z8-Z7)<0,"0",(Z8-Z7)) -> 0 | AB8: =AC7 -> 13184 | AC8: 13184 | AD8: =IF((AC8-AC7)<0,"0",(AC8-AC7)) -> 0 | AE8: =AF7 -> 17361 | AF8: 17385 | AG8: =IF((AF8-AF7)<0,"0",(AF8-AF7)) -> 24 | AH8: =AI7 -> 24546 | AI8: 24546 | AJ8: =IF((AI9-AI7)<0,"0",(AI9-AI7)) -> 0 | AK8: =AL7 -> 15154 | AL8: 15154 | AM8: =IF((AL8-AL7)<0,"0",(AL8-AL7)) -> 0 | AN8: =U8+X8+AA8+AD8+AG8+AJ8+AM8 -> 84
A9: =Gen!B14 -> 43925 | C9: =D8 -> 232723 | D9: 232757 | E9: =IF((D9-D8)<0,"0",(D9-D8)) -> 34 | F9: =G8 -> 38000 | G9: 38000 | H9: =IF((G9-G8)<0,"0",(G9-G8)) -> 0 | I9: =J8 -> 7893 | J9: 7894 | K9: =IF((J9-J8)<0,"0",(J9-J8)) -> 1 | L9: =M8 -> 11978 | M9: 11978 | N9: =IF((M9-M8)<0,"0",(M9-M8)) -> 0 | O9: =P8 -> 20104 | P9: 20106 | Q9: =IF((P9-P8)<0,"0",(P9-P8)) -> 2 | S9: =T8 -> 51912 | T9: 51964 | U9: =IF((T9-T8)<0,"0",(T9-T8)) -> 52 | V9: =W8 -> 71260 | W9: 71260 | X9: =IF((W9-W8)<0,"0",(W9-W8)) -> 0 | Y9: =Z8 -> 80332 | Z9: 80332 | AA9: =IF((Z9-Z8)<0,"0",(Z9-Z8)) -> 0 | AB9: =AC8 -> 13184 | AC9: 13184 | AD9: =IF((AC9-AC8)<0,"0",(AC9-AC8)) -> 0 | AE9: =AF8 -> 17385 | AF9: 17409 | AG9: =IF((AF9-AF8)<0,"0",(AF9-AF8)) -> 24 | AH9: =AI9 -> 24546 | AI9: 24546 | AJ9: =IF((AI10-AI8)<0,"0",(AI10-AI8)) -> 0 | AK9: =AL8 -> 15154 | AL9: 15154 | AM9: =IF((AL9-AL8)<0,"0",(AL9-AL8)) -> 0 | AN9: =U9+X9+AA9+AD9+AG9+AJ9+AM9 -> 76
A10: =Gen!B15 -> 43926 | C10: =D9 -> 232757 | D10: 232799 | E10: =IF((D10-D9)<0,"0",(D10-D9)) -> 42 | F10: =G9 -> 38000 | G10: 38000 | H10: =IF((G10-G9)<0,"0",(G10-G9)) -> 0 | I10: =J9 -> 7894 | J10: 7894 | K10: =IF((J10-J9)<0,"0",(J10-J9)) -> 0 | L10: =M9 -> 11978 | M10: 11978 | N10: =IF((M10-M9)<0,"0",(M10-M9)) -> 0 | O10: =P9 -> 20106 | P10: 20107 | Q10: =IF((P10-P9)<0,"0",(P10-P9)) -> 1 | S10: =T9 -> 51964 | T10: 52046 | U10: =IF((T10-T9)<0,"0",(T10-T9)) -> 82 | V10: =W9 -> 71260 | W10: 71260 | X10: =IF((W10-W9)<0,"0",(W10-W9)) -> 0 | Y10: =Z9 -> 80332 | Z10: 80332 | AA10: =IF((Z10-Z9)<0,"0",(Z10-Z9)) -> 0 | AB10: =AC9 -> 13184 | AC10: 13195 | AD10: =IF((AC10-AC9)<0,"0",(AC10-AC9)) -> 11 | AE10: =AF9 -> 17409 | AF10: 17365 | AG10: =IF((AF10-AF9)<0,"0",(AF10-AF9)) -> 0 | AH10: =AI9 -> 24546 | AI10: 24546 | AJ10: =IF((AI11-AI9)<0,"0",(AI11-AI9)) -> 0 | AK10: =AL9 -> 15154 | AL10: 15154 | AM10: =IF((AL10-AL9)<0,"0",(AL10-AL9)) -> 0 | AN10: =U10+X10+AA10+AD10+AG10+AJ10+AM10 -> 93
A11: =Gen!B16 -> 43927 | C11: =D10 -> 232799 | D11: 232840 | E11: =IF((D11-D10)<0,"0",(D11-D10)) -> 41 | F11: =G10 -> 38000 | G11: 38000 | H11: =IF((G11-G10)<0,"0",(G11-G10)) -> 0 | I11: =J10 -> 7894 | J11: 7894 | K11: =IF((J11-J10)<0,"0",(J11-J10)) -> 0 | L11: =M10 -> 11978 | M11: 11978 | N11: =IF((M11-M10)<0,"0",(M11-M10)) -> 0 | O11: =P10 -> 20107 | P11: 20108 | Q11: =IF((P11-P10)<0,"0",(P11-P10)) -> 1 | S11: =T10 -> 52046 | T11: 52111 | U11: =IF((T11-T10)<0,"0",(T11-T10)) -> 65 | V11: =W10 -> 71260 | W11: 71260 | X11: =IF((W11-W10)<0,"0",(W11-W10)) -> 0 | Y11: =Z10 -> 80332 | Z11: 80332 | AA11: =IF((Z11-Z10)<0,"0",(Z11-Z10)) -> 0 | AB11: =AC10 -> 13195 | AC11: 13206 | AD11: =IF((AC11-AC10)<0,"0",(AC11-AC10)) -> 11 | AE11: =AF10 -> 17365 | AF11: 17365 | AG11: =IF((AF11-AF10)<0,"0",(AF11-AF10)) -> 0 | AH11: =AI10 -> 24546 | AI11: 24546 | AJ11: =IF((AI12-AI10)<0,"0",(AI12-AI10)) -> 0 | AK11: =AL10 -> 15154 | AL11: 15154 | AM11: =IF((AL11-AL10)<0,"0",(AL11-AL10)) -> 0 | AN11: =U11+X11+AA11+AD11+AG11+AJ11+AM11 -> 76
A12: =Gen!B17 -> 43928 | C12: =D11 -> 232840 | D12: 232887 | E12: =IF((D12-D11)<0,"0",(D12-D11)) -> 47 | F12: =G11 -> 38000 | G12: 38000 | H12: =IF((G12-G11)<0,"0",(G12-G11)) -> 0 | I12: =J11 -> 7894 | J12: 7894 | K12: =IF((J12-J11)<0,"0",(J12-J11)) -> 0 | L12: =M11 -> 11978 | M12: 11978 | N12: =IF((M12-M11)<0,"0",(M12-M11)) -> 0 | O12: =P11 -> 20108 | P12: 20110 | Q12: =IF((P12-P11)<0,"0",(P12-P11)) -> 2 | S12: =T11 -> 52111 | T12: 52160 | U12: =IF((T12-T11)<0,"0",(T12-T11)) -> 49 | V12: =W11 -> 71260 | W12: 71260 | X12: =IF((W12-W11)<0,"0",(W12-W11)) -> 0 | Y12: =Z11 -> 80332 | Z12: 80376 | AA12: =IF((Z12-Z11)<0,"0",(Z12-Z11)) -> 44 | AB12: =AC11 -> 13206 | AC12: 13216 | AD12: =IF((AC12-AC11)<0,"0",(AC12-AC11)) -> 10 | AE12: =AF11 -> 17365 | AF12: 17365 | AG12: =IF((AF12-AF11)<0,"0",(AF12-AF11)) -> 0 | AH12: =AI11 -> 24546 | AI12: 24546 | AJ12: =IF((AI13-AI11)<0,"0",(AI13-AI11)) -> 0 | AK12: =AL11 -> 15154 | AL12: 15154 | AM12: =IF((AL12-AL11)<0,"0",(AL12-AL11)) -> 0 | AN12: =U12+X12+AA12+AD12+AG12+AJ12+AM12 -> 103
A13: =Gen!B18 -> 43929 | C13: =D12 -> 232887 | D13: 232923 | E13: =IF((D13-D12)<0,"0",(D13-D12)) -> 36 | F13: =G12 -> 38000 | G13: 38000 | H13: =IF((G13-G12)<0,"0",(G13-G12)) -> 0 | I13: =J12 -> 7894 | J13: 7894 | K13: =IF((J13-J12)<0,"0",(J13-J12)) -> 0 | L13: =M12 -> 11978 | M13: 11978 | N13: =IF((M13-M12)<0,"0",(M13-M12)) -> 0 | O13: =P12 -> 20110 | P13: 20111 | Q13: =IF((P13-P12)<0,"0",(P13-P12)) -> 1 | S13: =T12 -> 52160 | T13: 52226 | U13: =IF((T13-T12)<0,"0",(T13-T12)) -> 66 | V13: =W12 -> 71260 | W13: 71260 | X13: =IF((W13-W12)<0,"0",(W13-W12)) -> 0 | Y13: =Z12 -> 80376 | Z13: 80428 | AA13: =IF((Z13-Z12)<0,"0",(Z13-Z12)) -> 52 | AB13: =AC12 -> 13216 | AC13: 13227 | AD13: =IF((AC13-AC12)<0,"0",(AC13-AC12)) -> 11 | AE13: =AF12 -> 17365 | AF13: 17365 | AG13: =IF((AF13-AF12)<0,"0",(AF13-AF12)) -> 0 | AH13: =AI12 -> 24546 | AI13: 24546 | AJ13: =IF((AI14-AI12)<0,"0",(AI14-AI12)) -> 0 | AK13: =AL12 -> 15154 | AL13: 15154 | AM13: =IF((AL13-AL12)<0,"0",(AL13-AL12)) -> 0 | AN13: =U13+X13+AA13+AD13+AG13+AJ13+AM13 -> 129
A14: =Gen!B19 -> 43930 | C14: =D13 -> 232923 | D14: 232956 | E14: =IF((D14-D13)<0,"0",(D14-D13)) -> 33 | F14: =G13 -> 38000 | G14: 38000 | H14: =IF((G14-G13)<0,"0",(G14-G13)) -> 0 | I14: =J13 -> 7894 | J14: 7894 | K14: =IF((J14-J13)<0,"0",(J14-J13)) -> 0 | L14: =M13 -> 11978 | M14: 11978 | N14: =IF((M14-M13)<0,"0",(M14-M13)) -> 0 | O14: =P13 -> 20111 | P14: 20112 | Q14: =IF((P14-P13)<0,"0",(P14-P13)) -> 1 | S14: =T13 -> 52226 | T14: 52291 | U14: =IF((T14-T13)<0,"0",(T14-T13)) -> 65 | V14: =W13 -> 71260 | W14: 71260 | X14: =IF((W14-W13)<0,"0",(W14-W13)) -> 0 | Y14: =Z13 -> 80428 | Z14: 80481 | AA14: =IF((Z14-Z13)<0,"0",(Z14-Z13)) -> 53 | AB14: =AC13 -> 13227 | AC14: 13244 | AD14: =IF((AC14-AC13)<0,"0",(AC14-AC13)) -> 17 | AE14: =AF13 -> 17365 | AF14: 17365 | AG14: =IF((AF14-AF13)<0,"0",(AF14-AF13)) -> 0 | AH14: =AI13 -> 24546 | AI14: 24546 | AJ14: =IF((AI15-AI13)<0,"0",(AI15-AI13)) -> 0 | AK14: =AL13 -> 15154 | AL14: 15154 | AM14: =IF((AL14-AL13)<0,"0",(AL14-AL13)) -> 0 | AN14: =U14+X14+AA14+AD14+AG14+AJ14+AM14 -> 135
A15: =Gen!B20 -> 43931 | C15: =D14 -> 232956 | D15: 233011 | E15: =IF((D15-D14)<0,"0",(D15-D14)) -> 55 | F15: =G14 -> 38000 | G15: 38000 | H15: =IF((G15-G14)<0,"0",(G15-G14)) -> 0 | I15: =J14 -> 7894 | J15: 7894 | K15: =IF((J15-J14)<0,"0",(J15-J14)) -> 0 | L15: =M14 -> 11978 | M15: 11978 | N15: =IF((M15-M14)<0,"0",(M15-M14)) -> 0 | O15: =P14 -> 20112 | P15: 20114 | Q15: =IF((P15-P14)<0,"0",(P15-P14)) -> 2 | S15: =T14 -> 52291 | T15: 52292 | U15: =IF((T15-T14)<0,"0",(T15-T14)) -> 1 | V15: =W14 -> 71260 | W15: 71260 | X15: =IF((W15-W14)<0,"0",(W15-W14)) -> 0 | Y15: =Z14 -> 80481 | Z15: 80534 | AA15: =IF((Z15-Z14)<0,"0",(Z15-Z14)) -> 53 | AB15: =AC14 -> 13244 | AC15: 13261 | AD15: =IF((AC15-AC14)<0,"0",(AC15-AC14)) -> 17 | AE15: =AF14 -> 17365 | AF15: 17385 | AG15: =IF((AF15-AF14)<0,"0",(AF15-AF14)) -> 20 | AH15: =AI14 -> 24546 | AI15: 24546 | AJ15: =IF((AI16-AI14)<0,"0",(AI16-AI14)) -> 0 | AK15: =AL14 -> 15154 | AL15: 15154 | AM15: =IF((AL15-AL14)<0,"0",(AL15-AL14)) -> 0 | AN15: =U15+X15+AA15+AD15+AG15+AJ15+AM15 -> 91
A16: =Gen!B21 -> 43932 | C16: =D15 -> 233011 | D16: 233067 | E16: =IF((D16-D15)<0,"0",(D16-D15)) -> 56 | F16: =G15 -> 38000 | G16: 38000 | H16: =IF((G16-G15)<0,"0",(G16-G15)) -> 0 | I16: =J15 -> 7894 | J16: 7894 | K16: =IF((J16-J15)<0,"0",(J16-J15)) -> 0 | M16: 11978 | N16: =IF((M16-M15)<0,"0",(M16-M15)) -> 0 | O16: =P15 -> 20114 | P16: 20115 | Q16: =IF((P16-P15)<0,"0",(P16-P15)) -> 1 | S16: =T15 -> 52292 | T16: 52292 | U16: =IF((T16-T15)<0,"0",(T16-T15)) -> 0 | V16: =W15 -> 71260 | W16: 71260 | X16: =IF((W16-W15)<0,"0",(W16-W15)) -> 0 | Y16: =Z15 -> 80534 | Z16: 80538 | AA16: =IF((Z16-Z15)<0,"0",(Z16-Z15)) -> 4 | AB16: =AC15 -> 13261 | AC16: 13278 | AD16: =IF((AC16-AC15)<0,"0",(AC16-AC15)) -> 17 | AE16: =AF15 -> 17385 | AF16: 17410 | AG16: =IF((AF16-AF15)<0,"0",(AF16-AF15)) -> 25 | AH16: =AI15 -> 24546 | AI16: 24546 | AJ16: =IF((AI17-AI15)<0,"0",(AI17-AI15)) -> 0 | AK16: =AL15 -> 15154 | AL16: 15154 | AM16: =IF((AL16-AL15)<0,"0",(AL16-AL15)) -> 0 | AN16: =U16+X16+AA16+AD16+AG16+AJ16+AM16 -> 46
A17: =Gen!B22 -> 43933 | C17: =D16 -> 233067 | D17: 233108 | E17: =IF((D17-D16)<0,"0",(D17-D16)) -> 41 | F17: =G16 -> 38000 | G17: 38000 | H17: =IF((G17-G16)<0,"0",(G17-G16)) -> 0 | I17: =J16 -> 7894 | J17: 7895 | K17: =IF((J17-J16)<0,"0",(J17-J16)) -> 1 | M17: 11978 | N17: =IF((M17-M16)<0,"0",(M17-M16)) -> 0 | O17: =P16 -> 20115 | P17: 20116 | Q17: =IF((P17-P16)<0,"0",(P17-P16)) -> 1 | S17: =T16 -> 52292 | T17: 52292 | U17: =IF((T17-T16)<0,"0",(T17-T16)) -> 0 | V17: =W16 -> 71260 | W17: 71260 | X17: =IF((W17-W16)<0,"0",(W17-W16)) -> 0 | Y17: =Z16 -> 80538 | Z17: 80538 | AA17: =IF((Z17-Z16)<0,"0",(Z17-Z16)) -> 0 | AB17: =AC16 -> 13278 | AC17: 13294 | AD17: =IF((AC17-AC16)<0,"0",(AC17-AC16)) -> 16 | AE17: =AF16 -> 17410 | AF17: 17435 | AG17: =IF((AF17-AF16)<0,"0",(AF17-AF16)) -> 25 | AH17: =AI16 -> 24546 | AI17: 24546 | AJ17: =IF((AI18-AI16)<0,"0",(AI18-AI16)) -> 0 | AK17: =AL16 -> 15154 | AL17: 15154 | AM17: =IF((AL17-AL16)<0,"0",(AL17-AL16)) -> 0 | AN17: =U17+X17+AA17+AD17+AG17+AJ17+AM17 -> 41
A18: =Gen!B23 -> 43934 | C18: =D17 -> 233108 | D18: 233153 | E18: =IF((D18-D17)<0,"0",(D18-D17)) -> 45 | F18: =G17 -> 38000 | G18: 38000 | H18: =IF((G18-G17)<0,"0",(G18-G17)) -> 0 | J18: 7895 | K18: =IF((J18-J17)<0,"0",(J18-J17)) -> 0 | L18: =M17 -> 11978 | M18: 11978 | N18: =IF((M18-M17)<0,"0",(M18-M17)) -> 0 | O18: =P17 -> 20116 | P18: 20117 | Q18: =IF((P18-P17)<0,"0",(P18-P17)) -> 1 | S18: =T17 -> 52292 | T18: 52292 | U18: =IF((T18-T17)<0,"0",(T18-T17)) -> 0 | V18: =W17 -> 71260 | W18: 71260 | X18: =IF((W18-W17)<0,"0",(W18-W17)) -> 0 | Y18: =Z17 -> 80538 | Z18: 80538 | AA18: =IF((Z18-Z17)<0,"0",(Z18-Z17)) -> 0 | AB18: =AC17 -> 13294 | AC18: 13310 | AD18: =IF((AC18-AC17)<0,"0",(AC18-AC17)) -> 16 | AE18: =AF17 -> 17435 | AF18: 17460 | AG18: =IF((AF18-AF17)<0,"0",(AF18-AF17)) -> 25 | AH18: =AI17 -> 24546 | AI18: 24546 | AJ18: =IF((AI19-AI17)<0,"0",(AI19-AI17)) -> 0 | AK18: =AL17 -> 15154 | AL18: 15154 | AM18: =IF((AL18-AL17)<0,"0",(AL18-AL17)) -> 0 | AN18: =U18+X18+AA18+AD18+AG18+AJ18+AM18 -> 41
A19: =Gen!B24 -> 43935 | C19: =D18 -> 233153 | D19: 233204 | E19: =IF((D19-D18)<0,"0",(D19-D18)) -> 51 | F19: =G18 -> 38000 | G19: 38000 | H19: =IF((G19-G18)<0,"0",(G19-G18)) -> 0 | I19: =J18 -> 7895 | J19: 7896 | K19: =IF((J19-J18)<0,"0",(J19-J18)) -> 1 | L19: =M18 -> 11978 | M19: 11978 | N19: =IF((M19-M18)<0,"0",(M19-M18)) -> 0 | O19: =P18 -> 20117 | P19: 20118 | Q19: =IF((P19-P18)<0,"0",(P19-P18)) -> 1 | S19: =T18 -> 52292 | T19: 52292 | U19: =IF((T19-T18)<0,"0",(T19-T18)) -> 0 | V19: =W18 -> 71260 | W19: 71260 | X19: =IF((W19-W18)<0,"0",(W19-W18)) -> 0 | Y19: =Z18 -> 80538 | Z19: 80538 | AA19: =IF((Z19-Z18)<0,"0",(Z19-Z18)) -> 0 | AB19: =AC18 -> 13310 | AC19: 13327 | AD19: =IF((AC19-AC18)<0,"0",(AC19-AC18)) -> 17 | AE19: =AF18 -> 17460 | AF19: 17484 | AG19: =IF((AF19-AF18)<0,"0",(AF19-AF18)) -> 24 | AH19: =AI18 -> 24546 | AI19: 24546 | AJ19: =IF((AI20-AI18)<0,"0",(AI20-AI18)) -> 0 | AK19: =AL18 -> 15154 | AL19: 15154 | AM19: =IF((AL19-AL18)<0,"0",(AL19-AL18)) -> 0 | AN19: =U19+X19+AA19+AD19+AG19+AJ19+AM19 -> 41
A20: =Gen!B25 -> 43936 | C20: =D19 -> 233204 | D20: 233258 | E20: =IF((D20-D19)<0,"0",(D20-D19)) -> 54 | F20: =G19 -> 38000 | G20: 38000 | H20: =IF((G20-G19)<0,"0",(G20-G19)) -> 0 | I20: =J19 -> 7896 | J20: 7896 | K20: =IF((J20-J19)<0,"0",(J20-J19)) -> 0 | L20: =M19 -> 11978 | M20: 11978 | N20: =IF((M20-M19)<0,"0",(M20-M19)) -> 0 | O20: =P19 -> 20118 | P20: 20119 | Q20: =IF((P20-P19)<0,"0",(P20-P19)) -> 1 | S20: =T19 -> 52292 | T20: 52292 | U20: =IF((T20-T19)<0,"0",(T20-T19)) -> 0 | V20: =W19 -> 71260 | W20: 71260 | X20: =IF((W20-W19)<0,"0",(W20-W19)) -> 0 | Y20: =Z19 -> 80538 | Z20: 80538 | AA20: =IF((Z20-Z19)<0,"0",(Z20-Z19)) -> 0 | AB20: =AC19 -> 13327 | AC20: 13344 | AD20: =IF((AC20-AC19)<0,"0",(AC20-AC19)) -> 17 | AE20: =AF19 -> 17484 | AF20: 17509 | AG20: =IF((AF20-AF19)<0,"0",(AF20-AF19)) -> 25 | AH20: =AI19 -> 24546 | AI20: 24546 | AJ20: =IF((AI21-AI19)<0,"0",(AI21-AI19)) -> 0 | AK20: =AL19 -> 15154 | AL20: 15154 | AM20: =IF((AL20-AL19)<0,"0",(AL20-AL19)) -> 0 | AN20: =U20+X20+AA20+AD20+AG20+AJ20+AM20 -> 42
A21: =Gen!B26 -> 43937 | C21: =D20 -> 233258 | D21: 233312 | E21: =IF((D21-D20)<0,"0",(D21-D20)) -> 54 | F21: =G20 -> 38000 | G21: 38000 | H21: =IF((G21-G20)<0,"0",(G21-G20)) -> 0 | I21: =J20 -> 7896 | J21: 7897 | K21: =IF((J21-J20)<0,"0",(J21-J20)) -> 1 | L21: =M20 -> 11978 | M21: 11978 | N21: =IF((M21-M20)<0,"0",(M21-M20)) -> 0 | O21: =P20 -> 20119 | P21: 20119 | Q21: =IF((P21-P20)<0,"0",(P21-P20)) -> 0 | S21: =T20 -> 52292 | T21: 52292 | U21: =IF((T21-T20)<0,"0",(T21-T20)) -> 0 | V21: =W20 -> 71260 | W21: 71260 | X21: =IF((W21-W20)<0,"0",(W21-W20)) -> 0 | Y21: =Z20 -> 80538 | Z21: 80538 | AA21: =IF((Z21-Z20)<0,"0",(Z21-Z20)) -> 0 | AB21: =AC20 -> 13344 | AC21: 13361 | AD21: =IF((AC21-AC20)<0,"0",(AC21-AC20)) -> 17 | AE21: =AF20 -> 17509 | AF21: 17533 | AG21: =IF((AF21-AF20)<0,"0",(AF21-AF20)) -> 24 | AH21: =AI20 -> 24546 | AI21: 24546 | AJ21: =IF((AI22-AI20)<0,"0",(AI22-AI20)) -> 0 | AK21: =AL20 -> 15154 | AL21: 15154 | AM21: =IF((AL21-AL20)<0,"0",(AL21-AL20)) -> 0 | AN21: =U21+X21+AA21+AD21+AG21+AJ21+AM21 -> 41
A22: =Gen!B27 -> 43938 | C22: =D21 -> 233312 | D22: 233354 | E22: =IF((D22-D21)<0,"0",(D22-D21)) -> 42 | F22: =G21 -> 38000 | G22: 38000 | H22: =IF((G22-G21)<0,"0",(G22-G21)) -> 0 | I22: =J21 -> 7897 | J22: 7897 | K22: =IF((J22-J21)<0,"0",(J22-J21)) -> 0 | L22: =M21 -> 11978 | M22: 11978 | N22: =IF((M22-M21)<0,"0",(M22-M21)) -> 0 | O22: =P21 -> 20119 | P22: 20121 | Q22: =IF((P22-P21)<0,"0",(P22-P21)) -> 2 | S22: =T21 -> 52292 | T22: 52292 | U22: =IF((T22-T21)<0,"0",(T22-T21)) -> 0 | V22: =W21 -> 71260 | W22: 71260 | X22: =IF((W22-W21)<0,"0",(W22-W21)) -> 0 | Y22: =Z21 -> 80538 | Z22: 80538 | AA22: =IF((Z22-Z21)<0,"0",(Z22-Z21)) -> 0 | AB22: =AC21 -> 13361 | AC22: 13377 | AD22: =IF((AC22-AC21)<0,"0",(AC22-AC21)) -> 16 | AE22: =AF21 -> 17533 | AF22: 17557 | AG22: =IF((AF22-AF21)<0,"0",(AF22-AF21)) -> 24 | AH22: =AI21 -> 24546 | AI22: 24546 | AJ22: =IF((AI23-AI21)<0,"0",(AI23-AI21)) -> 0 | AK22: =AL21 -> 15154 | AL22: 15154 | AM22: =IF((AL22-AL21)<0,"0",(AL22-AL21)) -> 0 | AN22: =U22+X22+AA22+AD22+AG22+AJ22+AM22 -> 40
A23: =Gen!B28 -> 43939 | C23: =D22 -> 233354 | D23: 233384 | E23: =IF((D23-D22)<0,"0",(D23-D22)) -> 30 | F23: =G22 -> 38000 | G23: 38000 | H23: =IF((G23-G22)<0,"0",(G23-G22)) -> 0 | I23: =J22 -> 7897 | J23: 7898 | K23: =IF((J23-J22)<0,"0",(J23-J22)) -> 1 | L23: =M22 -> 11978 | M23: 11978 | N23: =IF((M23-M22)<0,"0",(M23-M22)) -> 0 | O23: =P22 -> 20121 | P23: 20122 | Q23: =IF((P23-P22)<0,"0",(P23-P22)) -> 1 | S23: =T22 -> 52292 | T23: 52292 | U23: =IF((T23-T22)<0,"0",(T23-T22)) -> 0 | V23: =W22 -> 71260 | W23: 71260 | X23: =IF((W23-W22)<0,"0",(W23-W22)) -> 0 | Y23: =Z22 -> 80538 | Z23: 80538 | AA23: =IF((Z23-Z22)<0,"0",(Z23-Z22)) -> 0 | AB23: =AC22 -> 13377 | AC23: 13393 | AD23: =IF((AC23-AC22)<0,"0",(AC23-AC22)) -> 16 | AE23: =AF22 -> 17557 | AF23: 17582 | AG23: =IF((AF23-AF22)<0,"0",(AF23-AF22)) -> 25 | AH23: =AI22 -> 24546 | AI23: 24546 | AJ23: =IF((AI24-AI22)<0,"0",(AI24-AI22)) -> 0 | AK23: =AL22 -> 15154 | AL23: 15154 | AM23: =IF((AL23-AL22)<0,"0",(AL23-AL22)) -> 0 | AN23: =U23+X23+AA23+AD23+AG23+AJ23+AM23 -> 41
A24: =Gen!B29 -> 43940 | C24: =D23 -> 233384 | D24: 233435 | E24: =IF((D24-D23)<0,"0",(D24-D23)) -> 51 | F24: =G23 -> 38000 | G24: 38000 | H24: =IF((G24-G23)<0,"0",(G24-G23)) -> 0 | I24: =J23 -> 7898 | J24: 7898 | K24: =IF((J24-J23)<0,"0",(J24-J23)) -> 0 | L24: =M23 -> 11978 | M24: 11978 | N24: =IF((M24-M23)<0,"0",(M24-M23)) -> 0 | O24: =P23 -> 20122 | P24: 20123 | Q24: =IF((P24-P23)<0,"0",(P24-P23)) -> 1 | S24: =T23 -> 52292 | T24: 52292 | U24: =IF((T24-T23)<0,"0",(T24-T23)) -> 0 | V24: =W23 -> 71260 | W24: 71260 | X24: =IF((W24-W23)<0,"0",(W24-W23)) -> 0 | Y24: =Z23 -> 80538 | Z24: 80538 | AA24: =IF((Z24-Z23)<0,"0",(Z24-Z23)) -> 0 | AB24: =AC23 -> 13393 | AC24: 13412 | AD24: =IF((AC24-AC23)<0,"0",(AC24-AC23)) -> 19 | AE24: =AF23 -> 17582 | AF24: 17606 | AG24: =IF((AF24-AF23)<0,"0",(AF24-AF23)) -> 24 | AH24: =AI23 -> 24546 | AI24: 24546 | AJ24: =IF((AI25-AI23)<0,"0",(AI25-AI23)) -> 0 | AK24: =AL23 -> 15154 | AL24: 15154 | AM24: =IF((AL24-AL23)<0,"0",(AL24-AL23)) -> 0 | AN24: =U24+X24+AA24+AD24+AG24+AJ24+AM24 -> 43
A25: =Gen!B30 -> 43941 | C25: =D24 -> 233435 | D25: 233470 | E25: =IF((D25-D24)<0,"0",(D25-D24)) -> 35 | F25: =G24 -> 38000 | G25: 38000 | H25: =IF((G25-G24)<0,"0",(G25-G24)) -> 0 | I25: =J24 -> 7898 | J25: 7899 | K25: =IF((J25-J24)<0,"0",(J25-J24)) -> 1 | L25: =M24 -> 11978 | M25: 11978 | N25: =IF((M25-M24)<0,"0",(M25-M24)) -> 0 | O25: =P24 -> 20123 | P25: 20123 | Q25: =IF((P25-P24)<0,"0",(P25-P24)) -> 0 | S25: =T24 -> 52292 | T25: 52292 | U25: =IF((T25-T24)<0,"0",(T25-T24)) -> 0 | V25: =W24 -> 71260 | W25: 71260 | X25: =IF((W25-W24)<0,"0",(W25-W24)) -> 0 | Y25: =Z24 -> 80538 | Z25: 80538 | AA25: =IF((Z25-Z24)<0,"0",(Z25-Z24)) -> 0 | AB25: =AC24 -> 13412 | AC25: 13429 | AD25: =IF((AC25-AC24)<0,"0",(AC25-AC24)) -> 17 | AE25: =AF24 -> 17606 | AF25: 17631 | AG25: =IF((AF25-AF24)<0,"0",(AF25-AF24)) -> 25 | AH25: =AI24 -> 24546 | AI25: 24546 | AJ25: =IF((AI26-AI24)<0,"0",(AI26-AI24)) -> 0 | AK25: =AL24 -> 15154 | AL25: 15154 | AM25: =IF((AL25-AL24)<0,"0",(AL25-AL24)) -> 0 | AN25: =U25+X25+AA25+AD25+AG25+AJ25+AM25 -> 42
A26: =Gen!B31 -> 43942 | C26: =D25 -> 233470 | D26: 233497 | E26: =IF((D26-D25)<0,"0",(D26-D25)) -> 27 | F26: =G25 -> 38000 | G26: 38000 | H26: =IF((G26-G25)<0,"0",(G26-G25)) -> 0 | I26: =J25 -> 7899 | J26: 7899 | K26: =IF((J26-J25)<0,"0",(J26-J25)) -> 0 | L26: =M25 -> 11978 | M26: 11978 | N26: =IF((M26-M25)<0,"0",(M26-M25)) -> 0 | O26: =P25 -> 20123 | P26: 20124 | Q26: =IF((P26-P25)<0,"0",(P26-P25)) -> 1 | S26: =T25 -> 52292 | T26: 52292 | U26: =IF((T26-T25)<0,"0",(T26-T25)) -> 0 | V26: =W25 -> 71260 | W26: 71260 | X26: =IF((W26-W25)<0,"0",(W26-W25)) -> 0 | Y26: =Z25 -> 80538 | Z26: 80538 | AA26: =IF((Z26-Z25)<0,"0",(Z26-Z25)) -> 0 | AB26: =AC25 -> 13429 | AC26: 13447 | AD26: =IF((AC26-AC25)<0,"0",(AC26-AC25)) -> 18 | AE26: =AF25 -> 17631 | AF26: 17655 | AG26: =IF((AF26-AF25)<0,"0",(AF26-AF25)) -> 24 | AH26: =AI25 -> 24546 | AI26: 24546 | AJ26: =IF((AI27-AI25)<0,"0",(AI27-AI25)) -> 0 | AK26: =AL25 -> 15154 | AL26: 15154 | AM26: =IF((AL26-AL25)<0,"0",(AL26-AL25)) -> 0 | AN26: =U26+X26+AA26+AD26+AG26+AJ26+AM26 -> 42
A27: =Gen!B32 -> 43943 | C27: =D26 -> 233497 | D27: 233525 | E27: =IF((D27-D26)<0,"0",(D27-D26)) -> 28 | F27: =G26 -> 38000 | G27: 38000 | H27: =IF((G27-G26)<0,"0",(G27-G26)) -> 0 | I27: =J26 -> 7899 | J27: 7899 | K27: =IF((J27-J26)<0,"0",(J27-J26)) -> 0 | L27: =M26 -> 11978 | M27: 11978 | N27: =IF((M27-M26)<0,"0",(M27-M26)) -> 0 | O27: =P26 -> 20124 | P27: 20125 | Q27: =IF((P27-P26)<0,"0",(P27-P26)) -> 1 | S27: =T26 -> 52292 | T27: 52292 | U27: =IF((T27-T26)<0,"0",(T27-T26)) -> 0 | V27: =W26 -> 71260 | W27: 71260 | X27: =IF((W27-W26)<0,"0",(W27-W26)) -> 0 | Y27: =Z26 -> 80538 | Z27: 80538 | AA27: =IF((Z27-Z26)<0,"0",(Z27-Z26)) -> 0 | AB27: =AC26 -> 13447 | AC27: 13464 | AD27: =IF((AC27-AC26)<0,"0",(AC27-AC26)) -> 17 | AE27: =AF26 -> 17655 | AF27: 17680 | AG27: =IF((AF27-AF26)<0,"0",(AF27-AF26)) -> 25 | AH27: =AI26 -> 24546 | AI27: 24546 | AJ27: =IF((AI28-AI26)<0,"0",(AI28-AI26)) -> 0 | AK27: =AL26 -> 15154 | AL27: 15154 | AM27: =IF((AL27-AL26)<0,"0",(AL27-AL26)) -> 0 | AN27: =U27+X27+AA27+AD27+AG27+AJ27+AM27 -> 42
A28: =Gen!B33 -> 43944 | C28: =D27 -> 233525 | D28: 233554 | E28: =IF((D28-D27)<0,"0",(D28-D27)) -> 29 | F28: =G27 -> 38000 | G28: 38000 | H28: =IF((G28-G27)<0,"0",(G28-G27)) -> 0 | I28: =J27 -> 7899 | J28: 7899 | K28: =IF((J28-J27)<0,"0",(J28-J27)) -> 0 | L28: =M27 -> 11978 | M28: 11978 | N28: =IF((M28-M27)<0,"0",(M28-M27)) -> 0 | O28: =P27 -> 20125 | P28: 20125 | Q28: =IF((P28-P27)<0,"0",(P28-P27)) -> 0 | S28: =T27 -> 52292 | T28: 52292 | U28: =IF((T28-T27)<0,"0",(T28-T27)) -> 0 | V28: =W27 -> 71260 | W28: 71260 | X28: =IF((W28-W27)<0,"0",(W28-W27)) -> 0 | Y28: =Z27 -> 80538 | Z28: 80538 | AA28: =IF((Z28-Z27)<0,"0",(Z28-Z27)) -> 0 | AB28: =AC27 -> 13464 | AC28: 13483 | AD28: =IF((AC28-AC27)<0,"0",(AC28-AC27)) -> 19 | AE28: =AF27 -> 17680 | AF28: 17705 | AG28: =IF((AF28-AF27)<0,"0",(AF28-AF27)) -> 25 | AH28: =AI27 -> 24546 | AI28: 24546 | AJ28: =IF((AI29-AI27)<0,"0",(AI29-AI27)) -> 0 | AK28: =AL27 -> 15154 | AL28: 15154 | AM28: =IF((AL28-AL27)<0,"0",(AL28-AL27)) -> 0 | AN28: =U28+X28+AA28+AD28+AG28+AJ28+AM28 -> 44
A29: =Gen!B34 -> 43945 | C29: =D28 -> 233554 | D29: 233585 | E29: =IF((D29-D28)<0,"0",(D29-D28)) -> 31 | F29: =G28 -> 38000 | G29: 38000 | H29: =IF((G29-G28)<0,"0",(G29-G28)) -> 0 | I29: =J28 -> 7899 | J29: 7900 | K29: =IF((J29-J28)<0,"0",(J29-J28)) -> 1 | L29: =M28 -> 11978 | M29: 11978 | N29: =IF((M29-M28)<0,"0",(M29-M28)) -> 0 | O29: =P28 -> 20125 | P29: 20126 | Q29: =IF((P29-P28)<0,"0",(P29-P28)) -> 1 | S29: =T28 -> 52292 | T29: 52292 | U29: =IF((T29-T28)<0,"0",(T29-T28)) -> 0 | V29: =W28 -> 71260 | W29: 71260 | X29: =IF((W29-W28)<0,"0",(W29-W28)) -> 0 | Y29: =Z28 -> 80538 | Z29: 80538 | AA29: =IF((Z29-Z28)<0,"0",(Z29-Z28)) -> 0 | AB29: =AC28 -> 13483 | AC29: 13502 | AD29: =IF((AC29-AC28)<0,"0",(AC29-AC28)) -> 19 | AE29: =AF28 -> 17705 | AF29: 17730 | AG29: =IF((AF29-AF28)<0,"0",(AF29-AF28)) -> 25 | AH29: =AI28 -> 24546 | AI29: 24546 | AJ29: =IF((AI30-AI28)<0,"0",(AI30-AI28)) -> 0 | AK29: =AL28 -> 15154 | AL29: 15154 | AM29: =IF((AL29-AL28)<0,"0",(AL29-AL28)) -> 0 | AN29: =U29+X29+AA29+AD29+AG29+AJ29+AM29 -> 44
A30: =Gen!B35 -> 43946 | C30: =D29 -> 233585 | D30: 233617 | E30: =IF((D30-D29)<0,"0",(D30-D29)) -> 32 | F30: =G29 -> 38000 | G30: 38000 | H30: =IF((G30-G29)<0,"0",(G30-G29)) -> 0 | I30: =J29 -> 7900 | J30: 7900 | K30: =IF((J30-J29)<0,"0",(J30-J29)) -> 0 | L30: =M29 -> 11978 | M30: 11978 | N30: =IF((M30-M29)<0,"0",(M30-M29)) -> 0 | O30: =P29 -> 20126 | P30: 20127 | Q30: =IF((P30-P29)<0,"0",(P30-P29)) -> 1 | S30: =T29 -> 52292 | T30: 52292 | U30: =IF((T30-T29)<0,"0",(T30-T29)) -> 0 | V30: =W29 -> 71260 | W30: 71260 | X30: =IF((W30-W29)<0,"0",(W30-W29)) -> 0 | Y30: =Z29 -> 80538 | Z30: 80538 | AA30: =IF((Z30-Z29)<0,"0",(Z30-Z29)) -> 0 | AB30: =AC29 -> 13502 | AC30: 13522 | AD30: =IF((AC30-AC29)<0,"0",(AC30-AC29)) -> 20 | AE30: =AF29 -> 17730 | AF30: 17752 | AG30: =IF((AF30-AF29)<0,"0",(AF30-AF29)) -> 22 | AH30: =AI29 -> 24546 | AI30: 24546 | AJ30: =IF((AI31-AI29)<0,"0",(AI31-AI29)) -> 0 | AK30: =AL29 -> 15154 | AL30: 15154 | AM30: =IF((AL30-AL29)<0,"0",(AL30-AL29)) -> 0 | AN30: =U30+X30+AA30+AD30+AG30+AJ30+AM30 -> 42
A31: =Gen!B36 -> 43947 | C31: =D30 -> 233617 | D31: 233648 | E31: =IF((D31-D30)<0,"0",(D31-D30)) -> 31 | F31: =G30 -> 38000 | G31: 38000 | H31: =IF((G31-G30)<0,"0",(G31-G30)) -> 0 | I31: =J30 -> 7900 | J31: 7901 | K31: =IF((J31-J30)<0,"0",(J31-J30)) -> 1 | L31: =M30 -> 11978 | M31: 11978 | N31: =IF((M31-M30)<0,"0",(M31-M30)) -> 0 | O31: =P30 -> 20127 | P31: 20128 | Q31: =IF((P31-P30)<0,"0",(P31-P30)) -> 1 | S31: =T30 -> 52292 | T31: 52370 | U31: =IF((T31-T30)<0,"0",(T31-T30)) -> 78 | V31: =W30 -> 71260 | W31: 71260 | X31: =IF((W31-W30)<0,"0",(W31-W30)) -> 0 | Y31: =Z30 -> 80538 | Z31: 80538 | AA31: =IF((Z31-Z30)<0,"0",(Z31-Z30)) -> 0 | AB31: =AC30 -> 13522 | AC31: 13547 | AD31: =IF((AC31-AC30)<0,"0",(AC31-AC30)) -> 25 | AE31: =AF30 -> 17752 | AF31: 17780 | AG31: =IF((AF31-AF30)<0,"0",(AF31-AF30)) -> 28 | AH31: =AI30 -> 24546 | AI31: 24546 | AJ31: =IF((AI32-AI30)<0,"0",(AI32-AI30)) -> 0 | AK31: =AL30 -> 15154 | AL31: 15154 | AM31: =IF((AL31-AL30)<0,"0",(AL31-AL30)) -> 0 | AN31: =U31+X31+AA31+AD31+AG31+AJ31+AM31 -> 131
A32: =Gen!B37 -> 43948 | B32: 10/27//2009 | C32: =D31 -> 233648 | D32: 233678 | E32: =IF((D32-D31)<0,"0",(D32-D31)) -> 30 | F32: =G31 -> 38000 | G32: 38000 | H32: =IF((G32-G31)<0,"0",(G32-G31)) -> 0 | I32: =J31 -> 7901 | J32: 7902 | K32: =IF((J32-J31)<0,"0",(J32-J31)) -> 1 | L32: =M31 -> 11978 | M32: 11978 | N32: =IF((M32-M31)<0,"0",(M32-M31)) -> 0 | O32: =P31 -> 20128 | P32: 20129 | Q32: =IF((P32-P31)<0,"0",(P32-P31)) -> 1 | S32: =T31 -> 52370 | T32: 52447 | U32: =IF((T32-T31)<0,"0",(T32-T31)) -> 77 | V32: =W31 -> 71260 | W32: 71260 | X32: =IF((W32-W31)<0,"0",(W32-W31)) -> 0 | Y32: =Z31 -> 80538 | Z32: 80538 | AA32: =IF((Z32-Z31)<0,"0",(Z32-Z31)) -> 0 | AB32: =AC31 -> 13547 | AC32: 13562 | AD32: =IF((AC32-AC31)<0,"0",(AC32-AC31)) -> 15 | AE32: =AF31 -> 17780 | AF32: 17805 | AG32: =IF((AF32-AF31)<0,"0",(AF32-AF31)) -> 25 | AH32: =AI31 -> 24546 | AI32: 24546 | AJ32: =IF((AI33-AI31)<0,"0",(AI33-AI31)) -> 0 | AK32: =AL31 -> 15154 | AL32: 15154 | AM32: =IF((AL32-AL31)<0,"0",(AL32-AL31)) -> 0 | AN32: =U32+X32+AA32+AD32+AG32+AJ32+AM32 -> 117
A33: =Gen!B38 -> 43949 | C33: =D32 -> 233678 | D33: 233709 | E33: =IF((D33-D32)<0,"0",(D33-D32)) -> 31 | F33: =G32 -> 38000 | G33: 38000 | H33: =IF((G33-G32)<0,"0",(G33-G32)) -> 0 | I33: =J32 -> 7902 | J33: 7902 | K33: =IF((J33-J32)<0,"0",(J33-J32)) -> 0 | L33: =M32 -> 11978 | M33: 11978 | N33: =IF((M33-M32)<0,"0",(M33-M32)) -> 0 | O33: =P32 -> 20129 | P33: 20129 | Q33: =IF((P33-P32)<0,"0",(P33-P32)) -> 0 | S33: =T32 -> 52447 | T33: 52462 | U33: =IF((T33-T32)<0,"0",(T33-T32)) -> 15 | V33: =W32 -> 71260 | W33: 71260 | X33: =IF((W33-W32)<0,"0",(W33-W32)) -> 0 | Y33: =Z32 -> 80538 | Z33: 80538 | AA33: =IF((Z33-Z32)<0,"0",(Z33-Z32)) -> 0 | AB33: =AC32 -> 13562 | AC33: 13583 | AD33: =IF((AC33-AC32)<0,"0",(AC33-AC32)) -> 21 | AE33: =AF32 -> 17805 | AF33: 17830 | AG33: =IF((AF33-AF32)<0,"0",(AF33-AF32)) -> 25 | AH33: =AI32 -> 24546 | AI33: 24546 | AJ33: =IF((AI34-AI32)<0,"0",(AI34-AI32)) -> 0 | AK33: =AL32 -> 15154 | AL33: 15154 | AM33: =IF((AL33-AL32)<0,"0",(AL33-AL32)) -> 0 | AN33: =U33+X33+AA33+AD33+AG33+AJ33+AM33 -> 61
A34: =Gen!B39 -> 43950 | C34: =D33 -> 233709 | D34: 233738 | E34: =IF((D34-D33)<0,"0",(D34-D33)) -> 29 | F34: =G33 -> 38000 | G34: 38000 | H34: =IF((G34-G33)<0,"0",(G34-G33)) -> 0 | I34: =J33 -> 7902 | J34: 7903 | K34: =IF((J34-J33)<0,"0",(J34-J33)) -> 1 | L34: =M33 -> 11978 | M34: 11978 | N34: =IF((M34-M33)<0,"0",(M34-M33)) -> 0 | O34: =P33 -> 20129 | P34: 20130 | Q34: =IF((P34-P33)<0,"0",(P34-P33)) -> 1 | S34: =T33 -> 52462 | T34: 52462 | U34: =IF((T34-T33)<0,"0",(T34-T33)) -> 0 | V34: =W33 -> 71260 | W34: 71260 | X34: =IF((W34-W33)<0,"0",(W34-W33)) -> 0 | Y34: =Z33 -> 80538 | Z34: 80538 | AA34: =IF((Z34-Z33)<0,"0",(Z34-Z33)) -> 0 | AB34: =AC33 -> 13583 | AC34: 13603 | AD34: =IF((AC34-AC33)<0,"0",(AC34-AC33)) -> 20 | AE34: =AF33 -> 17830 | AF34: 17855 | AG34: =IF((AF34-AF33)<0,"0",(AF34-AF33)) -> 25 | AH34: =AI33 -> 24546 | AI34: 24546 | AJ34: =IF((AI35-AI33)<0,"0",(AI35-AI33)) -> 0 | AK34: =AL33 -> 15154 | AL34: 15154 | AM34: =IF((AL34-AL33)<0,"0",(AL34-AL33)) -> 0 | AN34: =U34+X34+AA34+AD34+AG34+AJ34+AM34 -> 45
A35: =Gen!B40 -> 43951 | C35: =D34 -> 233738 | D35: 233767 | E35: =IF((D35-D34)<0,"0",(D35-D34)) -> 29 | F35: =G34 -> 38000 | G35: 38000 | H35: =IF((G35-G34)<0,"0",(G35-G34)) -> 0 | I35: =J34 -> 7903 | J35: 7903 | K35: =IF((J35-J34)<0,"0",(J35-J34)) -> 0 | L35: =M34 -> 11978 | M35: 11978 | N35: =IF((M35-M34)<0,"0",(M35-M34)) -> 0 | O35: =P34 -> 20130 | P35: 20131 | Q35: =IF((P35-P34)<0,"0",(P35-P34)) -> 1 | S35: =T34 -> 52462 | T35: 52462 | U35: =IF((T35-T34)<0,"0",(T35-T34)) -> 0 | V35: =W34 -> 71260 | W35: 71260 | X35: =IF((W35-W34)<0,"0",(W35-W34)) -> 0 | Y35: =Z34 -> 80538 | Z35: 80538 | AA35: =IF((Z35-Z34)<0,"0",(Z35-Z34)) -> 0 | AB35: =AC34 -> 13603 | AC35: 13624 | AD35: =IF((AC35-AC34)<0,"0",(AC35-AC34)) -> 21 | AE35: =AF34 -> 17855 | AF35: 17880 | AG35: =IF((AF35-AF34)<0,"0",(AF35-AF34)) -> 25 | AH35: =AI34 -> 24546 | AI35: 24546 | AJ35: =IF((AI36-AI34)<0,"0",(AI36-AI34)) -> 0 | AK35: =AL34 -> 15154 | AL35: 15154 | AM35: =IF((AL35-AL34)<0,"0",(AL35-AL34)) -> 0 | AN35: =U35+X35+AA35+AD35+AG35+AJ35+AM35 -> 46
A36: =Gen!B41 -> 0 | C36: =D35 -> 233767 | E36: =IF((D36-D35)<0,"0",(D36-D35)) -> 0 | F36: =G35 -> 38000 | H36: =IF((G36-G35)<0,"0",(G36-G35)) -> 0 | I36: =J35 -> 7903 | K36: =IF((J36-J35)<0,"0",(J36-J35)) -> 0 | L36: =M35 -> 11978 | N36: =IF((M36-M35)<0,"0",(M36-M35)) -> 0 | O36: =P35 -> 20131 | Q36: =IF((P36-P35)<0,"0",(P36-P35)) -> 0 | S36: =T35 -> 52462 | U36: =IF((T36-T35)<0,"0",(T36-T35)) -> 0 | V36: =W35 -> 71260 | X36: =IF((W36-W35)<0,"0",(W36-W35)) -> 0 | Y36: =Z35 -> 80538 | AA36: =IF((Z36-Z35)<0,"0",(Z36-Z35)) -> 0 | AB36: =AC35 -> 13624 | AD36: =IF((AC36-AC35)<0,"0",(AC36-AC35)) -> 0 | AE36: =AF35 -> 17880 | AG36: =IF((AF36-AF35)<0,"0",(AF36-AF35)) -> 0 | AH36: =AI35 -> 24546 | AJ36: =IF((AI37-AI35)<0,"0",(AI37-AI35)) -> 0 | AK36: =AL35 -> 15154 | AM36: =IF((AL36-AL35)<0,"0",(AL36-AL35)) -> 0 | AN36: =U36+X36+AA36+AD36+AG36+AJ36+AM36 -> 0
A37: =Gen!B42 -> 0 | C37: =D36 -> 0 | E37: =IF((D37-D36)<0,"0",(D37-D36)) -> 0 | F37: =G36 -> 0 | H37: =IF((G37-G36)<0,"0",(G37-G36)) -> 0 | I37: =J36 -> 0 | K37: =IF((J37-J36)<0,"0",(J37-J36)) -> 0 | L37: =M36 -> 0 | N37: =IF((M37-M36)<0,"0",(M37-M36)) -> 0 | O37: =P36 -> 0 | Q37: =IF((P37-P36)<0,"0",(P37-P36)) -> 0 | S37: =T36 -> 0 | U37: =IF((T37-T36)<0,"0",(T37-T36)) -> 0 | V37: =W36 -> 0 | X37: =IF((W37-W36)<0,"0",(W37-W36)) -> 0 | Y37: =Z36 -> 0 | AA37: =IF((Z37-Z36)<0,"0",(Z37-Z36)) -> 0 | AB37: =AC36 -> 0 | AD37: =IF((AC37-AC36)<0,"0",(AC37-AC36)) -> 0 | AE37: =AF36 -> 0 | AG37: =IF((AF37-AF36)<0,"0",(AF37-AF36)) -> 0 | AH37: =AI36 -> 0 | AJ37: =IF((AI38-AI36)<0,"0",(AI38-AI36)) -> 0 | AK37: =AL36 -> 0 | AM37: =IF((AL37-AL36)<0,"0",(AL37-AL36)) -> 0 | AN37: =U38+X38+AA38+AD38+AG38+AJ38+AM38 -> 750
C38: TOTAL USAGE | E38: =SUM(E6:E36) -> 1160 | F38: KL | H38: =SUM(H6:H37) -> 0 | K38: =SUM(K6:K37) -> 13 | N38: =M38-M37 -> 0 | Q38: =P38-O38 -> 0 | R38: =E38 -> 1160 | U38: =SUM(U6:U37) -> 750 | AN38: =U38+X38+AA38+AD38+AG38+AJ38+AM38 -> 750
C42: WATER TANK LEVEL
C43: RAW WATER TANK NO.1 | E43: RAW WATER TANK NO.2 | G43: TREATED WATER TANK | I43: TREATED -HILL TANK | K43: TOTAL WATER AVAILABLE
C44: CAPACITY 217 m³ | E44: CAPACITY 92 m³ | G44: CAPACITY 146 m³ | I44: CAPACITY 213 m³
C45: cm | D45: m³ | E45: cm | F45: m³ | H45: m³ | I45: cm | J45: m³ | K45: m³
A46: =Gen!B11 -> 43922 | C46: 135 | D46: =C46*217/300 -> 97.65 | E46: 120 | F46: =E46*92/305 -> 36.196721 | G46: 300 | H46: =G46*146/383 -> 114.36031 | I46: 270 | J46: =I46*213/308 -> 186.72078 | K46: =D46+F46+H46+J46 -> 434.92781
A47: =Gen!B12 -> 43923 | C47: 220 | D47: =C47*217/300 -> 159.13333 | E47: 195 | F47: =E47*92/305 -> 58.819672 | G47: 240 | H47: =G47*146/383 -> 91.488251 | I47: 280 | J47: =I47*213/308 -> 193.63636 | K47: =D47+F47+H47+J47 -> 503.07762
A48: =Gen!B13 -> 43924 | C48: 235 | D48: =C48*217/300 -> 169.98333 | E48: 210 | F48: =E48*92/305 -> 63.344262 | G48: 210 | H48: =G48*146/383 -> 80.052219 | I48: 280 | J48: =I48*213/308 -> 193.63636 | K48: =D48+F48+H48+J48 -> 507.01618
A49: =Gen!B14 -> 43925 | C49: 220 | D49: =C49*217/300 -> 159.13333 | E49: 190 | F49: =E49*92/305 -> 57.311475 | G49: 285 | H49: =G49*146/383 -> 108.6423 | I49: 280 | J49: =I49*213/308 -> 193.63636 | K49: =D49+F49+H49+J49 -> 518.72347
A50: =Gen!B15 -> 43926 | C50: 195 | D50: =C50*217/300 -> 141.05 | E50: 160 | F50: =E50*92/305 -> 48.262295 | G50: 300 | H50: =G50*146/383 -> 114.36031 | I50: 280 | J50: =I50*213/308 -> 193.63636 | K50: =D50+F50+H50+J50 -> 497.30897
A51: =Gen!B16 -> 43927 | C51: 160 | D51: =C51*217/300 -> 115.73333 | E51: 130 | F51: =E51*92/305 -> 39.213115 | G51: 300 | H51: =G51*146/383 -> 114.36031 | I51: 290 | J51: =I51*213/308 -> 200.55195 | K51: =D51+F51+H51+J51 -> 469.85871
A52: =Gen!B17 -> 43928 | C52: 170 | D52: =C52*217/300 -> 122.96667 | E52: 135 | F52: =E52*92/305 -> 40.721311 | G52: 300 | H52: =G52*146/383 -> 114.36031 | I52: 280 | J52: =I52*213/308 -> 193.63636 | K52: =D52+F52+H52+J52 -> 471.68466
A53: =Gen!B18 -> 43929 | C53: 185 | D53: =C53*217/300 -> 133.81667 | E53: 150 | F53: =E53*92/305 -> 45.245902 | G53: 300 | H53: =G53*146/383 -> 114.36031 | I53: 275 | J53: =I53*213/308 -> 190.17857 | K53: =D53+F53+H53+J53 -> 483.60145
A54: =Gen!B19 -> 43930 | C54: 240 | D54: =C54*217/300 -> 173.6 | E54: 210 | F54: =E54*92/305 -> 63.344262 | G54: 300 | H54: =G54*146/383 -> 114.36031 | I54: 275 | J54: =I54*213/308 -> 190.17857 | K54: =D54+F54+H54+J54 -> 541.48315
A55: =Gen!B20 -> 43931 | C55: 300 | D55: =C55*217/300 -> 217 | E55: 300 | F55: =E55*92/305 -> 90.491803 | G55: 270 | H55: =G55*146/383 -> 102.92428 | I55: 275 | J55: =I55*213/308 -> 190.17857 | K55: =D55+F55+H55+J55 -> 600.59466
A56: =Gen!B21 -> 43932 | C56: 297 | D56: =C56*217/300 -> 214.83 | E56: 300 | F56: =E56*92/305 -> 90.491803 | G56: 235 | H56: =G56*146/383 -> 89.582245 | I56: 280 | J56: =I56*213/308 -> 193.63636 | K56: =D56+F56+H56+J56 -> 588.54041
A57: =Gen!B22 -> 43933 | C57: 265 | D57: =C57*217/300 -> 191.68333 | E57: 235 | F57: =E57*92/305 -> 70.885246 | G57: 265 | H57: =G57*146/383 -> 101.01828 | I57: 280 | J57: =I57*213/308 -> 193.63636 | K57: =D57+F57+H57+J57 -> 557.22322
... A76: =Gen!B41 -> 0 | C76: 285 | D76: =C76*217/300 -> 206.15 | E76: 270 | F76: =E76*92/305 -> 81.442623 | G76: 225 | H76: =G76*146/383 -> 85.770235 | I76: 290 | J76: =I76*213/308 -> 200.55195 | K76: =D76+F76+H76+J76 -> 573.91481
A77: =Gen!B42 -> 0 | D77: =C77*217/300 -> 0 | F77: =E77*92/305 -> 0 | H77: =G77*146/383 -> 0 | J77: =I77*213/308 -> 0 | K77: =D77+F77+H77+J77 -> 0
A78: =Gen!B43 -> BF

Sheet Water_Graph 
A1: Date | B1: Usage | C1: Occ %
A2: =Gen!B11 -> 43922 | B2: ='Water-Meter'!E6 -> 38 | C2: =Gen!C11 -> 0
A3: =Gen!B12 -> 43923 | B3: ='Water-Meter'!E7 -> 52 | C3: =Gen!C12 -> 0
A4: =Gen!B13 -> 43924 | B4: ='Water-Meter'!E8 -> 26 | C4: =Gen!C13 -> 0
A5: =Gen!B14 -> 43925 | B5: ='Water-Meter'!E9 -> 34 | C5: =Gen!C14 -> 0
A6: =Gen!B15 -> 43926 | B6: ='Water-Meter'!E10 -> 42 | C6: =Gen!C15 -> 0
A7: =Gen!B16 -> 43927 | B7: ='Water-Meter'!E11 -> 41 | C7: =Gen!C16 -> 0
A8: =Gen!B17 -> 43928 | B8: ='Water-Meter'!E12 -> 47 | C8: =Gen!C17 -> 0
A9: =Gen!B18 -> 43929 | B9: ='Water-Meter'!E13 -> 36 | C9: =Gen!C18 -> 0
A10: =Gen!B19 -> 43930 | B10: ='Water-Meter'!E14 -> 33 | C10: =Gen!C19 -> 0
A11: =Gen!B20 -> 43931 | B11: ='Water-Meter'!E15 -> 55 | C11: =Gen!C20 -> 0
A12: =Gen!B21 -> 43932 | B12: ='Water-Meter'!E16 -> 56 | C12: =Gen!C21 -> 0
A13: =Gen!B22 -> 43933 | B13: ='Water-Meter'!E17 -> 41 | C13: =Gen!C22 -> 0
... A32: =Gen!B41 -> 0 | B32: ='Water-Meter'!E36 -> 0 | C32: =Gen!C41 -> 0

Sheet VODACOM AND AIRTEL
A1: VODACOM AND AIRTEL KWH METER READING
B2: VODACOM TOWER | E2: AIRTEL TOWER
A3: DATE | B3: OPEN METER READING | C3: CLOSE METER READING | D3: UNIT CONSUMED | E3: OPEN METER READING | F3: CLOSE METER READING | G3: UNIT CONSUMED
A4: 42095 | B4: 0 | C4: 193 | D4: =C4-B4 -> 193 | E4: 0 | F4: 0 | G4: =F4-E4 -> 0
A5: 42125 | B5: =C4 -> 193 | C5: 1158 | D5: =C5-B5 -> 965 | E5: 145572 | F5: 145572 | G5: =F5-E5 -> 0
A6: 42156 | B6: =C5 -> 1158 | C6: 2084 | D6: =C6-B6 -> 926 | E6: =F5 -> 145572 | F6: 147984 | G6: =F6-E6 -> 2412
A7: 42186 | B7: =C6 -> 2084 | C7: 3073 | D7: =C7-B7 -> 989 | E7: =F6 -> 147984 | F7: 150507 | G7: =F7-E7 -> 2523
A8: 42217 | B8: =C7 -> 3073 | C8: 4063 | D8: =C8-B8 -> 990 | E8: =F7 -> 150507 | F8: 152986 | G8: =F8-E8 -> 2479
A9: 42248 | B9: =C8 -> 4063 | C9: 5058 | D9: =C9-B9 -> 995 | E9: =F8 -> 152986 | F9: 155468 | G9: =F9-E9 -> 2482
A10: 42278 | B10: =C9 -> 5058 | C10: 6049 | D10: =C10-B10 -> 991 | E10: =F9 -> 155468 | F10: 157962 | G10: =F10-E10 -> 2494
A11: 42309 | B11: =C10 -> 6049 | C11: 7028 | D11: =C11-B11 -> 979 | E11: =F10 -> 157962 | F11: 160323 | G11: =F11-E11 -> 2361
A12: 42339 | B12: =C11 -> 7028 | C12: 7985 | D12: =C12-B12 -> 957 | E12: =F11 -> 160323 | F12: 162813 | G12: =F12-E12 -> 2490
A13: 42370 | B13: =C12 -> 7985 | C13: 8952 | D13: =C13-B13 -> 967 | E13: =F12 -> 162813 | F13: 165317 | G13: =F13-E13 -> 2504
A14: 42401 | B14: =C13 -> 8952 | C14: 9898 | D14: =C14-B14 -> 946 | E14: =F13 -> 165317 | F14: 167679 | G14: =F14-E14 -> 2362
A15: 42430 | B15: =C14 -> 9898 | C15: 10637 | D15: =C15-B15 -> 739 | E15: =F14 -> 167679 | F15: 170134 | G15: =F15-E15 -> 2455
A16: 42461 | B16: =C15 -> 10637 | C16: 11352 | D16: =C16-B16 -> 715 | E16: =F15 -> 170134 | F16: 172562 | G16: =F16-E16 -> 2428
A17: 42491 | B17: =C16 -> 11352 | C17: 12426 | D17: =C17-B17 -> 1074 | E17: =F16 -> 172562 | F17: 175041 | G17: =F17-E17 -> 2479
... A63: 43891 | B63: =C62 -> 98070 | C63: 100381 | D63: =C63-B63 -> 2311 | E63: =F62 -> 272554 | F63: 274788 | G63: =F63-E63 -> 2234
A64: 43922 | B64: =C63 -> 100381 | D64: =C64-B64 -> -100381 | E64: =F63 -> 274788 | G64: =F64-E64 -> -274788
A65: 43952 | B65: =C64 -> 0 | D65: =C65-B65 -> 0 | E65: =F64 -> 0 | G65: =F65-E65 -> 0
A66: 43983 | B66: =C65 -> 0 | D66: =C66-B66 -> 0 | E66: =F65 -> 0 | G66: =F66-E66 -> 0
A67: 44013 | B67: =C66 -> 0 | D67: =C67-B67 -> 0 | E67: =F66 -> 0 | G67: =F67-E67 -> 0
A68: 44044 | B68: =C67 -> 0 | D68: =C68-B68 -> 0 | E68: =F67 -> 0 | G68: =F68-E68 -> 0
A69: 44075 | B69: =C68 -> 0 | D69: =C69-B69 -> 0 | E69: =F68 -> 0 | G69: =F69-E69 -> 0
A70: 44105 | B70: =C69 -> 0 | D70: =C70-B70 -> 0 | E70: =F69 -> 0 | G70: =F70-E70 -> 0
A71: 44136 | B71: =C70 -> 0 | D71: =C71-B71 -> 0 | E71: =F70 -> 0 | G71: =F71-E71 -> 0
A72: 44166 | B72: =C71 -> 0 | D72: =C72-B72 -> 0 | E72: =F71 -> 0 | G72: =F72-E72 -> 0
A73: 44197 | B73: =C72 -> 0 | D73: =C73-B73 -> 0 | E73: =F72 -> 0 | G73: =F73-E73 -> 0
A74: 44228 | B74: =C73 -> 0 | D74: =C74-B74 -> 0 | E74: =F73 -> 0 | G74: =F74-E74 -> 0
A75: 44256 | B75: =C74 -> 0 | D75: =C75-B75 -> 0 | E75: =F74 -> 0 | G75: =F75-E75 -> 0
... A99: 44986 | B99: =C98 -> 0 | D99: =C99-B99 -> 0 | E99: =F98 -> 0 | G99: =F99-E99 -> 0

Sheet FUEL METER READING
A1: FUEL METER 1 READNG | H1: FUEL METER 2 READING
A2: DATE | B2: OPEN METER READING | C2: CLOSE METER READING | D2: Diesel consumed | E2: HLP-GENSETS | F2: DIFFERENCE | G2: OPEN METER | H2: CLOSE METER | I2: DIESEL CONSUMED | J2: HLP-VEHICLES | K2: DIFFERENCE | L2: TOTAL DIESEL CONS.
A3: 42430 | B3: 5000778 | C3: 5057715 | D3: =C3-B3 -> 56937 | G3: =H3 -> 0 | I3: =H3-G3 -> 0 | K3: =I3-J3 -> 0
A4: 42461 | B4: =C3 -> 5057715 | C4: 5111496 | D4: =C4-B4 -> 53781 | G4: =H3 -> 0 | I4: =H4-G4 -> 0 | K4: =I4-J4 -> 0
A5: 42491 | B5: =C4 -> 5111496 | C5: 5169409 | D5: =C5-B5 -> 57913 | G5: =H4 -> 0 | I5: =H5-G5 -> 0 | K5: =I5-J5 -> 0
A6: 42522 | B6: =C5 -> 5169409 | C6: 5232162 | D6: =C6-B6 -> 62753 | G6: =H5 -> 0 | I6: =H6-G6 -> 0 | K6: =I6-J6 -> 0
A7: 42552 | B7: =C6 -> 5232162 | C7: 5310037 | D7: =C7-B7 -> 77875 | G7: =H6 -> 0 | I7: =H7-G7 -> 0 | K7: =I7-J7 -> 0
A8: 42583 | B8: =C7 -> 5310037 | C8: 5382821 | D8: =C8-B8 -> 72784 | E8: =[6]Gen!AR45 -> 72766 | F8: =D8-E8 -> 18 | G8: =H7 -> 0 | I8: =H8-G8 -> 0 | K8: =I8-J8 -> 0
A9: 42614 | B9: =C8 -> 5382821 | C9: 5446740 | D9: =C9-B9 -> 63919 | E9: =[7]Gen!AR45 -> 64036.5 | F9: =D9-E9 -> -117.5 | G9: =H8 -> 0 | I9: =H9-G9 -> 0 | K9: =I9-J9 -> 0
A10: 42644 | B10: =C9 -> 5446740 | C10: 5521440 | D10: =C10-B10 -> 74700 | E10: 76057.09 | F10: =D10-E10 -> -1357.09 | G10: =H9 -> 0 | I10: =H10-G10 -> 0 | K10: =I10-J10 -> 0
A11: 42675 | B11: =C10 -> 5521440 | C11: 5594926 | D11: =C11-B11 -> 73486 | E11: 73462.49 | F11: =D11-E11 -> 23.51 | G11: =H10 -> 0 | I11: =H11-G11 -> 0 | K11: =I11-J11 -> 0
A12: 42705 | B12: =C11 -> 5594926 | C12: 5670348 | D12: =C12-B12 -> 75422 | E12: 75421.2 | F12: =D12-E12 -> 0.8 | G12: =H11 -> 0 | I12: =H12-G12 -> 0 | K12: =I12-J12 -> 0
A13: 42736 | B13: =C12 -> 5670348 | C13: 5735627 | D13: =C13-B13 -> 65279 | E13: 65276.07 | F13: =D13-E13 -> 2.93 | G13: =H12 -> 0 | I13: =H13-G13 -> 0 | K13: =I13-J13 -> 0
A14: 42767 | B14: =C13 -> 5735627 | C14: 5797781 | D14: =C14-B14 -> 62154 | E14: 62154.9 | F14: =D14-E14 -> -0.9 | G14: =H13 -> 0 | I14: =H14-G14 -> 0 | K14: =I14-J14 -> 0
A15: 42795 | B15: =C14 -> 5797781 | C15: 5864602 | D15: =C15-B15 -> 66821 | E15: 66820.89 | F15: =D15-E15 -> 0.11 | G15: =H14 -> 0 | I15: =H15-G15 -> 0 | K15: =I15-J15 -> 0
A16: 42826 | B16: =C15 -> 5864602 | C16: 5927895 | D16: =C16-B16 -> 63293 | E16: 63292.38 | F16: =D16-E16 -> 0.62 | G16: =H15 -> 0 | I16: =H16-G16 -> 0 | K16: =I16-J16 -> 0
A17: 42856 | B17: =C16 -> 5927895 | C17: 5995212 | D17: =C17-B17 -> 67317 | E17: 67313.47 | F17: =D17-E17 -> 3.53 | G17: =H16 -> 0 | I17: =H17-G17 -> 0 | K17: =I17-J17 -> 0
A18: 42887 | B18: =C17 -> 5995212 | C18: 6065754 | D18: =C18-B18 -> 70542 | E18: 70542.6 | F18: =D18-E18 -> -0.6 | G18: =H17 -> 0 | I18: =H18-G18 -> 0 | K18: =I18-J18 -> 0
A19: 42917 | B19: =C18 -> 6065754 | C19: 6141089 | D19: =C19-B19 -> 75335 | E19: 75335 | F19: =D19-E19 -> 0 | G19: 2442 | H19: 15003 | I19: =H19-G19 -> 12561 | K19: =I19-J19 -> 12561
A20: 42948 | B20: =C19 -> 6141089 | C20: 6212470 | D20: =C20-B20 -> 71381 | E20: 71379.9 | F20: =D20-E20 -> 1.1 | G20: =H19 -> 15003 | H20: 25033 | I20: =H20-G20 -> 10030 | J20: 10029.74 | K20: =I20-J20 -> 0.26 | L20: =I20+D20 -> 81411
A21: 42979 | B21: =C20 -> 6212470 | C21: 6276921 | D21: =C21-B21 -> 64451 | E21: 64450.62 | F21: =D21-E21 -> 0.38 | G21: =H20 -> 25033 | H21: 32815 | I21: =H21-G21 -> 7782 | J21: 7781.72 | K21: =I21-J21 -> 0.28 | L21: =I21+D21 -> 72233
A22: 43009 | B22: =C21 -> 6276921 | C22: 6352831 | D22: =C22-B22 -> 75910 | E22: 75906.79 | F22: =D22-E22 -> 3.21 | G22: =H21 -> 32815 | H22: 39587 | I22: =H22-G22 -> 6772 | J22: 6772.04 | K22: =I22-J22 -> -0.04 | L22: =I22+D22 -> 82682
A23: 43040 | B23: =C22 -> 6352831 | C23: 6410003 | D23: =C23-B23 -> 57172 | E23: 57171.51 | F23: =D23-E23 -> 0.49 | G23: =H22 -> 39587 | H23: 45717 | I23: =H23-G23 -> 6130 | J23: 6129.55 | K23: =I23-J23 -> 0.45 | L23: =I23+D23 -> 63302
A24: 43070 | B24: =C23 -> 6410003 | C24: 6476953 | D24: =C24-B24 -> 66950 | E24: 66951.14 | F24: =D24-E24 -> -1.14 | G24: =H23 -> 45717 | H24: 52890 | I24: =H24-G24 -> 7173 | J24: 7173.94 | K24: =I24-J24 -> -0.94 | L24: =I24+D24 -> 74123
A25: 43101 | B25: =C24 -> 6476953 | C25: 6542879 | D25: =C25-B25 -> 65926 | E25: 65927.77 | F25: =D25-E25 -> -1.77 | G25: =H24 -> 52890 | H25: 59763 | I25: =H25-G25 -> 6873 | J25: 6874.87 | K25: =I25-J25 -> -1.87 | L25: =I25+D25 -> 72799
A26: 43132 | B26: =C25 -> 6542879 | C26: 6604433 | D26: =C26-B26 -> 61554 | E26: 61553.03 | F26: =D26-E26 -> 0.97 | G26: =H25 -> 59763 | H26: 66652 | I26: =H26-G26 -> 6889 | J26: 6890.89 | K26: =I26-J26 -> -1.89 | L26: =I26+D26 -> 68443
A27: 43160 | B27: =C26 -> 6604433 | C27: 6660226 | D27: =C27-B27 -> 55793 | E27: 55792.75 | F27: =D27-E27 -> 0.25 | G27: =H26 -> 66652 | H27: 77607 | I27: =H27-G27 -> 10955 | J27: 10955.45 | K27: =I27-J27 -> -0.45 | L27: =I27+D27 -> 66748
A28: 43191 | B28: =C27 -> 6660226 | C28: 6714539 | D28: =C28-B28 -> 54313 | E28: 54312.28 | F28: =D28-E28 -> 0.72 | G28: =H27 -> 77607 | H28: 82271 | I28: =H28-G28 -> 4664 | J28: 4665.22 | K28: =I28-J28 -> -1.22 | L28: =I28+D28 -> 58977
A29: 43221 | B29: =C28 -> 6714539 | C29: 6774547 | D29: =C29-B29 -> 60008 | E29: 60007.47 | F29: =D29-E29 -> 0.53 | G29: =H28 -> 82271 | H29: 88664 | I29: =H29-G29 -> 6393 | J29: 6392.14 | K29: =I29-J29 -> 0.86 | L29: =I29+D29 -> 66401
A30: 43252 | B30: =C29 -> 6774547 | C30: 6845214 | D30: =C30-B30 -> 70667 | E30: 70666.29 | F30: =D30-E30 -> 0.71 | G30: =H29 -> 88664 | H30: 99683 | I30: =H30-G30 -> 11019 | J30: 11020.51 | K30: =I30-J30 -> -1.51 | L30: =I30+D30 -> 81686
A31: 43282 | B31: =C30 -> 6845214 | C31: 6921964 | D31: =C31-B31 -> 76750 | E31: 76750.25 | F31: =D31-E31 -> -0.25 | G31: =H30 -> 99683 | H31: 107936 | I31: =H31-G31 -> 8253 | J31: 8252.24 | K31: =I31-J31 -> 0.76 | L31: =I31+D31 -> 85003
... A52: 43951 | B52: =C51 -> 8316467 | C52: 8337939 | D52: =C52-B52 -> 21472 | E52: 21470.92 | F52: =D52-E52 -> 1.08 | G52: =H51 -> 262770 | H52: 264590 | I52: =H52-G52 -> 1820 | J52: 1820.3 | K52: =I52-J52 -> -0.3 | L52: =I52+D52 -> 23292
A53: 43952 | B53: =C52 -> 8337939 | D53: =C53-B53 -> -8337939 | F53: =D53-E53 -> -8337939 | G53: =H52 -> 264590 | I53: =H53-G53 -> -264590 | K53: =I53-J53 -> -264590 | L53: =I53+D53 -> -8602529
A54: 43983 | B54: =C53 -> 0 | D54: =C54-B54 -> 0 | F54: =D54-E54 -> 0 | G54: =H53 -> 0 | I54: =H54-G54 -> 0 | K54: =I54-J54 -> 0 | L54: =I54+D54 -> 0
A55: 44013 | B55: =C54 -> 0 | D55: =C55-B55 -> 0 | F55: =D55-E55 -> 0 | G55: =H54 -> 0 | I55: =H55-G55 -> 0 | K55: =I55-J55 -> 0 | L55: =I55+D55 -> 0
A56: 44044 | B56: =C55 -> 0 | D56: =C56-B56 -> 0 | F56: =D56-E56 -> 0 | G56: =H55 -> 0 | I56: =H56-G56 -> 0 | K56: =I56-J56 -> 0 | L56: =I56+D56 -> 0
A57: 44075 | B57: =C56 -> 0 | D57: =C57-B57 -> 0 | F57: =D57-E57 -> 0 | G57: =H56 -> 0 | I57: =H57-G57 -> 0 | K57: =I57-J57 -> 0 | L57: =I57+D57 -> 0
A58: 44105 | B58: =C57 -> 0 | D58: =C58-B58 -> 0 | F58: =D58-E58 -> 0 | G58: =H57 -> 0 | I58: =H58-G58 -> 0 | K58: =I58-J58 -> 0 | L58: =I58+D58 -> 0
A59: 44136 | B59: =C58 -> 0 | D59: =C59-B59 -> 0 | F59: =D59-E59 -> 0 | G59: =H58 -> 0 | I59: =H59-G59 -> 0 | K59: =I59-J59 -> 0 | L59: =I59+D59 -> 0
A60: 44166 | B60: =C59 -> 0 | D60: =C60-B60 -> 0 | F60: =D60-E60 -> 0 | G60: =H59 -> 0 | I60: =H60-G60 -> 0 | K60: =I60-J60 -> 0 | L60: =I60+D60 -> 0
A61: 44197 | B61: =C60 -> 0 | D61: =C61-B61 -> 0 | F61: =D61-E61 -> 0 | G61: =H60 -> 0 | I61: =H61-G61 -> 0 | K61: =I61-J61 -> 0 | L61: =I61+D61 -> 0
A62: 44228 | B62: =C61 -> 0 | D62: =C62-B62 -> 0 | F62: =D62-E62 -> 0 | G62: =H61 -> 0 | I62: =H62-G62 -> 0 | K62: =I62-J62 -> 0 | L62: =I62+D62 -> 0
A63: 44256 | B63: =C62 -> 0 | D63: =C63-B63 -> 0 | F63: =D63-E63 -> 0 | G63: =H62 -> 0 | I63: =H63-G63 -> 0 | K63: =I63-J63 -> 0 | L63: =I63+D63 -> 0
A64: 44287 | B64: =C63 -> 0 | D64: =C64-B64 -> 0 | F64: =D64-E64 -> 0 | G64: =H63 -> 0 | I64: =H64-G64 -> 0 | K64: =I64-J64 -> 0 | L64: =I64+D64 -> 0
... A87: 44986 | B87: =C86 -> 0 | D87: =C87-B87 -> 0 | F87: =D87-E87 -> 0 | G87: =H86 -> 0 | I87: =H87-G87 -> 0 | K87: =I87-J87 -> 0 | L87: =I87+D87 -> 0

Sheet Daily utility report 
A1: DAILY UTILITIES REPORT
A2: 43922
A3: DATE | B3: OCC % | D3: GENERATOR FUEL (LTR) | F3: WATER (M³) | I3: ELECTRICAL (Kwh)
C4: VEHICLE CONSUMPTION | D4: CONSUMPTION | E4: BALANCE | F4: CONSUMPTION | G4: BOREHOLE PRODUCTION | H4: RO PRODUCTION | I4: KITCHEN | J4: LAUNDRY
A5: 43922 | B5: =Gen!C11 -> 0 | C5: =Gen!AK11 -> 49.37 | D5: =Gen!T11 -> 850.96 | E5: =Gen!D11 -> 41048.87 | F5: ='Water-Meter'!E6 -> 38 | G5: ='Water-Meter'!AN6 -> 99 | H5: ='Utility report '!AC6 -> 0 | I5: ='Kit report'!F4 -> 156 | J5: ='Kit report'!X4 -> 20
A6: 43923 | B6: =Gen!C12 -> 0 | C6: =Gen!AK12 -> 9.39 | D6: =Gen!T12 -> 866.25 | E6: =Gen!D12 -> 40148.54 | F6: ='Water-Meter'!E7 -> 52 | G6: ='Water-Meter'!AN7 -> 89 | H6: ='Utility report '!AC7 -> 48 | I6: ='Kit report'!F5 -> 132 | J6: ='Kit report'!X5 -> 20
A7: 43924 | B7: =Gen!C13 -> 0 | C7: =Gen!AK13 -> 18.02 | D7: =Gen!T13 -> 832.92 | E7: =Gen!D13 -> 39272.9 | F7: ='Water-Meter'!E8 -> 26 | G7: ='Water-Meter'!AN8 -> 84 | H7: ='Utility report '!AC8 -> 59 | I7: ='Kit report'!F6 -> 144 | J7: ='Kit report'!X6 -> 40
A8: 43925 | B8: =Gen!C14 -> 0 | C8: =Gen!AK14 -> 660.37 | D8: =Gen!T14 -> 789.55 | E8: =Gen!D14 -> 38421.96 | F8: ='Water-Meter'!E9 -> 34 | G8: ='Water-Meter'!AN9 -> 76 | H8: ='Utility report '!AC9 -> 57 | I8: ='Kit report'!F7 -> 132 | J8: ='Kit report'!X7 -> 40
A9: 43926 | B9: =Gen!C15 -> 0 | C9: =Gen!AK15 -> 34.28 | D9: =Gen!T15 -> 813.34 | E9: =Gen!D15 -> 36972.04 | F9: ='Water-Meter'!E10 -> 42 | G9: ='Water-Meter'!AN10 -> 93 | H9: ='Utility report '!AC10 -> 57 | I9: ='Kit report'!F8 -> 108 | J9: ='Kit report'!X8 -> 40
A10: 43927 | B10: =Gen!C16 -> 0 | C10: =Gen!AK16 -> 0 | D10: =Gen!T16 -> 757.53 | E10: =Gen!D16 -> 36124.42 | F10: ='Water-Meter'!E11 -> 41 | G10: ='Water-Meter'!AN11 -> 76 | H10: ='Utility report '!AC11 -> 38 | I10: ='Kit report'!F9 -> 132 | J10: ='Kit report'!X9 -> 40
A11: 43928 | B11: =Gen!C17 -> 0 | C11: =Gen!AK17 -> 108.2 | D11: =Gen!T17 -> 783.55 | E11: =Gen!D17 -> 50366.89 | F11: ='Water-Meter'!E12 -> 47 | G11: ='Water-Meter'!AN12 -> 103 | H11: ='Utility report '!AC12 -> 53 | I11: ='Kit report'!F10 -> 108 | J11: ='Kit report'!X10 -> 40
A12: 43929 | B12: =Gen!C18 -> 0 | C12: =Gen!AK18 -> 0 | D12: =Gen!T18 -> 831.27 | E12: =Gen!D18 -> 49475.14 | F12: ='Water-Meter'!E13 -> 36 | G12: ='Water-Meter'!AN13 -> 129 | H12: ='Utility report '!AC13 -> 50 | I12: ='Kit report'!F11 -> 120 | J12: ='Kit report'!X11 -> 40
A13: 43930 | B13: =Gen!C19 -> 0 | C13: =Gen!AK19 -> 0 | D13: =Gen!T19 -> 806.32 | E13: =Gen!D19 -> 48643.87 | F13: ='Water-Meter'!E14 -> 33 | G13: ='Water-Meter'!AN14 -> 135 | H13: ='Utility report '!AC14 -> 7 | I13: ='Kit report'!F12 -> 120 | J13: ='Kit report'!X12 -> 20
A14: 43931 | B14: =Gen!C20 -> 0 | C14: =Gen!AK20 -> 0 | D14: =Gen!T20 -> 823.75 | E14: =Gen!D20 -> 47837.55 | F14: ='Water-Meter'!E15 -> 55 | G14: ='Water-Meter'!AN15 -> 91 | H14: ='Utility report '!AC15 -> 44 | I14: ='Kit report'!F13 -> 108 | J14: ='Kit report'!X13 -> 60
A15: 43932 | B15: =Gen!C21 -> 0 | C15: =Gen!AK21 -> 0 | D15: =Gen!T21 -> 782.67 | E15: =Gen!D21 -> 47013.8 | F15: ='Water-Meter'!E16 -> 56 | G15: ='Water-Meter'!AN16 -> 46 | H15: ='Utility report '!AC16 -> 75 | I15: ='Kit report'!F14 -> 132 | J15: ='Kit report'!X14 -> 20
A16: 43933 | B16: =Gen!C22 -> 0 | C16: =Gen!AK22 -> 0 | D16: =Gen!T22 -> 776.8 | E16: =Gen!D22 -> 46231.13 | F16: ='Water-Meter'!E17 -> 41 | G16: ='Water-Meter'!AN17 -> 41 | H16: ='Utility report '!AC17 -> 49 | I16: ='Kit report'!F15 -> 132 | J16: ='Kit report'!X15 -> 20
... A35: 43952 | B35: =Gen!C41 -> 0 | C35: =Gen!AK41 -> 0 | D35: =Gen!T41 -> 0 | E35: =Gen!D41 -> 43367.69 | F35: ='Water-Meter'!E36 -> 0 | G35: ='Water-Meter'!AN36 -> 0 | H35: ='Utility report '!AC36 -> -31534 | I35: ='Kit report'!F34 -> -1039992 | J35: ='Kit report'!X34 -> -1560900
A36: 43922 | C36: =Gen!AK42 -> 0 | D36: =Gen!T42 -> 0 | E36: =Gen!D42 -> 43367.69 | F36: ='Water-Meter'!E37 -> 0 | G36: ='Water-Meter'!AN37 -> 750 | H36: ='Utility report '!AC37 -> 0 | I36: ='Kit report'!F35 -> 432 | J36: ='Kit report'!X35 -> 0
