Workbook

Sheet Total
A1: Site Name | B1: Day | C1: Month | D1: Year | E1: Total Electricity Kwh | F1: Electricity Tariff ($/Kwh) | G1: Total Fuel Oil (Liters) | H1: Fuel Oil $/Liter | I1: LPG (Kg) | J1: LPG $/Kg | K1: Water Utility Supply (m3) m3 | L1: Water Utility Supply (m3) $/m3 | M1: Irrigation Water (m3) m3 | N1: Irrigation water $/m3 | O1: Room Nights
A2: Beirut | B2: 1 | C2: 4 | D2: 2020 | E2: =ELEC!N3 -> 7662.2 | F2: =SUM('EDl log'!T4) -> 0.10830399 | G2: =-tanks!AW6 -> 267 | H2: =SUM(tanks!AV6) -> 0.3845 | I2: =('B5'!AU5)*0.51 -> 30.6 | J2: ='B5'!AX5/0.51 -> 1.372549 | K2: =WATER!I6 -> 107 | L2: =SUM(WATER!J6) -> 2.3364486 | M2: =WATER!Q6 -> 0 | N2: 0.6 | O2: =ELEC!B3 -> 4.002
A3: Beirut | B3: =B2+1 -> 2 | C3: 4 | D3: 2020 | E3: =ELEC!N4 -> 7437.6 | F3: =SUM('EDl log'!T5) -> 0.093088556 | G3: =-tanks!AW7 -> 307 | H3: =SUM(tanks!AV7) -> 0.3845 | I3: =('B5'!AU6)*0.51 -> 91.8 | J3: ='B5'!AX6/0.51 -> 1.372549 | K3: =WATER!I7 -> 0 | L3: =SUM(WATER!J7) -> 0 | M3: =WATER!Q7 -> 0 | N3: 0.6 | O3: =ELEC!B4 -> 2.001
A4: Beirut | B4: =B3+1 -> 3 | C4: 4 | D4: 2020 | E4: =ELEC!N5 -> 8665.2 | F4: =SUM('EDl log'!T6) -> 0.069733051 | G4: =-tanks!AW8 -> 351 | H4: =SUM(tanks!AV8) -> 0.3845 | I4: =('B5'!AU7)*0.51 -> 30.6 | J4: ='B5'!AX7/0.51 -> 1.372549 | K4: =WATER!I8 -> 300 | L4: =SUM(WATER!J8) -> 0.83333333 | M4: =WATER!Q8 -> 0 | N4: 0.6 | O4: =ELEC!B5 -> 2.001
A5: Beirut | B5: =B4+1 -> 4 | C5: 4 | D5: 2020 | E5: =ELEC!N6 -> 7670.4 | F5: =SUM('EDl log'!T7) -> 0.071592309 | G5: =-tanks!AW9 -> 271 | H5: =SUM(tanks!AV9) -> 0.3845 | I5: =('B5'!AU8)*0.51 -> 61.2 | J5: ='B5'!AX8/0.51 -> 1.372549 | K5: =WATER!I9 -> 0 | L5: =SUM(WATER!J9) -> 0 | M5: =WATER!Q9 -> 0 | N5: 0.6 | O5: =ELEC!B6 -> 2.99
A6: Beirut | B6: =B5+1 -> 5 | C6: 4 | D6: 2020 | E6: =ELEC!N7 -> 8538.8 | F6: =SUM('EDl log'!T8) -> 0.086834101 | G6: =-tanks!AW10 -> 252 | H6: =SUM(tanks!AV10) -> 0.3845 | I6: =('B5'!AU9)*0.51 -> 15.3 | J6: ='B5'!AX9/0.51 -> 1.372549 | K6: =WATER!I10 -> 166 | L6: =SUM(WATER!J10) -> 1.5060241 | M6: =WATER!Q10 -> 0 | N6: 0.6 | O6: =ELEC!B7 -> 6.992
A7: Beirut | B7: =B6+1 -> 6 | C7: 4 | D7: 2020 | E7: =ELEC!N8 -> 10057.8 | F7: =SUM('EDl log'!T9) -> 0.057249517 | G7: =-tanks!AW11 -> 444 | H7: =SUM(tanks!AV11) -> 0.3845 | I7: =('B5'!AU10)*0.51 -> 30.6 | J7: ='B5'!AX10/0.51 -> 1.372549 | K7: =WATER!I11 -> 19 | L7: =SUM(WATER!J11) -> 13.157895 | M7: =WATER!Q11 -> 0 | N7: 0.6 | O7: =ELEC!B8 -> 2.001
A8: Beirut | B8: =B7+1 -> 7 | C8: 4 | D8: 2020 | E8: =ELEC!N9 -> 7909.4 | F8: =SUM('EDl log'!T10) -> 0.063332284 | G8: =-tanks!AW12 -> 164 | H8: =SUM(tanks!AV12) -> 0.3845 | I8: =('B5'!AU11)*0.51 -> 15.3 | J8: ='B5'!AX11/0.51 -> 1.372549 | K8: =WATER!I12 -> 0 | L8: =SUM(WATER!J12) -> 0 | M8: =WATER!Q12 -> 0 | N8: 0.6 | O8: =ELEC!B9 -> 2.001
A9: Beirut | B9: =B8+1 -> 8 | C9: 4 | D9: 2020 | E9: =ELEC!N10 -> 10815.6 | F9: =SUM('EDl log'!T11) -> 0.068925058 | G9: =-tanks!AW13 -> 305 | H9: =SUM(tanks!AV13) -> 0.3845 | I9: =('B5'!AU12)*0.51 -> 61.2 | J9: ='B5'!AX12/0.51 -> 1.372549 | K9: =WATER!I13 -> 29 | L9: =SUM(WATER!J13) -> 8.6206897 | M9: =WATER!Q13 -> 0 | N9: 0.6 | O9: =ELEC!B10 -> 10.994
A10: Beirut | B10: =B9+1 -> 9 | C10: 4 | D10: 2020 | E10: =ELEC!N11 -> 9103 | F10: =SUM('EDl log'!T12) -> 0.073464034 | G10: =-tanks!AW14 -> 615.7 | H10: =SUM(tanks!AV14) -> 0.3845 | I10: =('B5'!AU13)*0.51 -> 158.1 | J10: ='B5'!AX13/0.51 -> 1.372549 | K10: =WATER!I14 -> 287 | L10: =SUM(WATER!J14) -> 0.87108014 | M10: =WATER!Q14 -> 0 | N10: 0.6 | O10: =ELEC!B11 -> 4.991
A11: Beirut | B11: =B10+1 -> 10 | C11: 4 | D11: 2020 | E11: =ELEC!N12 -> 8022.6 | F11: =SUM('EDl log'!T13) -> 0.082986374 | G11: =-tanks!AW15 -> 426 | H11: =SUM(tanks!AV15) -> 0.3845 | I11: =('B5'!AU14)*0.51 -> 45.9 | J11: ='B5'!AX14/0.51 -> 1.372549 | K11: =WATER!I15 -> 0 | L11: =SUM(WATER!J15) -> 0 | M11: =WATER!Q15 -> 0 | N11: 0.6 | O11: =ELEC!B12 -> 2.001
A12: Beirut | B12: =B11+1 -> 11 | C12: 4 | D12: 2020 | E12: =ELEC!N13 -> 8603.4 | F12: =SUM('EDl log'!T14) -> 0.067763691 | G12: =-tanks!AW16 -> 194 | H12: =SUM(tanks!AV16) -> 0.3845 | I12: =('B5'!AU15)*0.51 -> 30.6 | J12: ='B5'!AX15/0.51 -> 1.372549 | K12: =WATER!I16 -> 0 | L12: =SUM(WATER!J16) -> 0 | M12: =WATER!Q16 -> 0 | N12: 0.6 | O12: =ELEC!B13 -> 4.002
A13: Beirut | B13: =B12+1 -> 12 | C13: 4 | D13: 2020 | E13: =ELEC!N14 -> 8743 | F13: =SUM('EDl log'!T15) -> 0.079652111 | G13: =-tanks!AW17 -> 308 | H13: =SUM(tanks!AV17) -> 0.3845 | I13: =('B5'!AU16)*0.51 -> 61.2 | J13: ='B5'!AX16/0.51 -> 1.372549 | K13: =WATER!I17 -> 0 | L13: =SUM(WATER!J17) -> 0 | M13: =WATER!Q17 -> 0 | N13: 0.6 | O13: =ELEC!B14 -> 2.99
A14: Beirut | B14: =B13+1 -> 13 | C14: 4 | D14: 2020 | E14: =ELEC!N15 -> 8764 | F14: =SUM('EDl log'!T16) -> 0.083829721 | G14: =-tanks!AW18 -> 411 | H14: =SUM(tanks!AV18) -> 0.3845 | I14: =('B5'!AU17)*0.51 -> 30.6 | J14: ='B5'!AX17/0.51 -> 1.372549 | K14: =WATER!I18 -> 45 | L14: =SUM(WATER!J18) -> 5.5555556 | M14: =WATER!Q18 -> 0 | N14: 0.6 | O14: =ELEC!B15 -> 8.004
... A31: Beirut | B31: =B30+1 -> 30 | C31: 4 | D31: 2020 | E31: =ELEC!N32 -> 10173.2 | F31: =SUM('EDl log'!T33) -> 0.066615024 | G31: =-tanks!AW35 -> 281 | H31: =SUM(tanks!AV35) -> 0.284 | I31: =('B5'!AU34)*0.51 -> 224.4 | J31: ='B5'!AX34/0.51 -> 1.372549 | K31: =WATER!I35 -> 0 | L31: =SUM(WATER!J35) -> 0 | M31: =WATER!Q35 -> 0 | N31: 0.6 | O31: =ELEC!B32 -> 2.99

Sheet Submetering
A1: Site Name | B1: Day | C1: Month | D1: Year | E1: ATS1 Kwh | F1: ATS2 Kwh | G1: ATS3 Kwh | H1: ATS4 Kwh | I1: ATS5 Kwh | J1: Guest (m3) | K1: Kitchen & Laundry (m3) | L1: Room Nights
A2: Beirut | B2: 1 | C2: 4 | D2: 2020 | E2: =ELEC!M3 -> 2880 | F2: =ELEC!K3 -> 740 | G2: =ELEC!I3 -> 1112 | H2: =ELEC!E3 -> 1668 | I2: =ELEC!G3 -> 1262.2 | J2: =WATER!Y6 -> 99 | K2: =WATER!AJ6 -> 0 | L2: =ELEC!B3 -> 4.002
A3: Beirut | B3: =B2+1 -> 2 | C3: 4 | D3: 2020 | E3: =ELEC!M4 -> 2800 | F3: =ELEC!K4 -> 776 | G3: =ELEC!I4 -> 1056 | H3: =ELEC!E4 -> 1572 | I3: =ELEC!G4 -> 1233.6 | J3: =WATER!Y7 -> 72 | K3: =WATER!AJ7 -> 20 | L3: =ELEC!B4 -> 2.001
A4: Beirut | B4: =B3+1 -> 3 | C4: 4 | D4: 2020 | E4: =ELEC!M5 -> 3270 | F4: =ELEC!K5 -> 918 | G4: =ELEC!I5 -> 1130 | H4: =ELEC!E5 -> 2056 | I4: =ELEC!G5 -> 1291.2 | J4: =WATER!Y8 -> 60 | K4: =WATER!AJ8 -> 34 | L4: =ELEC!B5 -> 2.001
A5: Beirut | B5: =B4+1 -> 4 | C5: 4 | D5: 2020 | E5: =ELEC!M6 -> 2810 | F5: =ELEC!K6 -> 774 | G5: =ELEC!I6 -> 1112 | H5: =ELEC!E6 -> 1784 | I5: =ELEC!G6 -> 1190.4 | J5: =WATER!Y9 -> 10 | K5: =WATER!AJ9 -> 0 | L5: =ELEC!B6 -> 2.99
A6: Beirut | B6: =B5+1 -> 5 | C6: 4 | D6: 2020 | E6: =ELEC!M7 -> 2492 | F6: =ELEC!K7 -> 888 | G6: =ELEC!I7 -> 1086 | H6: =ELEC!E7 -> 2924 | I6: =ELEC!G7 -> 1148.8 | J6: =WATER!Y10 -> 0 | K6: =WATER!AJ10 -> 70 | L6: =ELEC!B7 -> 6.992
A7: Beirut | B7: =B6+1 -> 6 | C7: 4 | D7: 2020 | E7: =ELEC!M8 -> 3192 | F7: =ELEC!K8 -> 1022 | G7: =ELEC!I8 -> 1192 | H7: =ELEC!E8 -> 3300 | I7: =ELEC!G8 -> 1351.8 | J7: =WATER!Y11 -> 4 | K7: =WATER!AJ11 -> 0 | L7: =ELEC!B8 -> 2.001
A8: Beirut | B8: =B7+1 -> 7 | C8: 4 | D8: 2020 | E8: =ELEC!M9 -> 2542 | F8: =ELEC!K9 -> 832 | G8: =ELEC!I9 -> 1086 | H8: =ELEC!E9 -> 2178 | I8: =ELEC!G9 -> 1271.4 | J8: =WATER!Y12 -> 0 | K8: =WATER!AJ12 -> 37 | L8: =ELEC!B9 -> 2.001
A9: Beirut | B9: =B8+1 -> 8 | C9: 4 | D9: 2020 | E9: =ELEC!M10 -> 2910 | F9: =ELEC!K10 -> 1174 | G9: =ELEC!I10 -> 1352 | H9: =ELEC!E10 -> 3866 | I9: =ELEC!G10 -> 1513.6 | J9: =WATER!Y13 -> 81 | K9: =WATER!AJ13 -> 0 | L9: =ELEC!B10 -> 10.994
A10: Beirut | B10: =B9+1 -> 9 | C10: 4 | D10: 2020 | E10: =ELEC!M11 -> 2356 | F10: =ELEC!K11 -> 972 | G10: =ELEC!I11 -> 1158 | H10: =ELEC!E11 -> 3330 | I10: =ELEC!G11 -> 1287 | J10: =WATER!Y14 -> 78 | K10: =WATER!AJ14 -> 24 | L10: =ELEC!B11 -> 4.991
A11: Beirut | B11: =B10+1 -> 10 | C11: 4 | D11: 2020 | E11: =ELEC!M12 -> 2392 | F11: =ELEC!K12 -> 954 | G11: =ELEC!I12 -> 1200 | H11: =ELEC!E12 -> 2186 | I11: =ELEC!G12 -> 1290.6 | J11: =WATER!Y15 -> 0 | K11: =WATER!AJ15 -> 0 | L11: =ELEC!B12 -> 2.001
A12: Beirut | B12: =B11+1 -> 11 | C12: 4 | D12: 2020 | E12: =ELEC!M13 -> 2612 | F12: =ELEC!K13 -> 978 | G12: =ELEC!I13 -> 1300 | H12: =ELEC!E13 -> 2336 | I12: =ELEC!G13 -> 1377.4 | J12: =WATER!Y16 -> 0 | K12: =WATER!AJ16 -> 5 | L12: =ELEC!B13 -> 4.002
A13: Beirut | B13: =B12+1 -> 12 | C13: 4 | D13: 2020 | E13: =ELEC!M14 -> 2468 | F13: =ELEC!K14 -> 958 | G13: =ELEC!I14 -> 1268 | H13: =ELEC!E14 -> 2796 | I13: =ELEC!G14 -> 1253 | J13: =WATER!Y17 -> 0 | K13: =WATER!AJ17 -> 0 | L13: =ELEC!B14 -> 2.99
A14: Beirut | B14: =B13+1 -> 13 | C14: 4 | D14: 2020 | E14: =ELEC!M15 -> 2532 | F14: =ELEC!K15 -> 924 | G14: =ELEC!I15 -> 1316 | H14: =ELEC!E15 -> 2660 | I14: =ELEC!G15 -> 1332 | J14: =WATER!Y18 -> 3 | K14: =WATER!AJ18 -> 0 | L14: =ELEC!B15 -> 8.004
... A31: Beirut | B31: =B30+1 -> 30 | C31: 4 | D31: 2020 | E31: =ELEC!M32 -> 3506 | F31: =ELEC!K32 -> 1094 | G31: =ELEC!I32 -> 1518 | H31: =ELEC!E32 -> 2376 | I31: =ELEC!G32 -> 1679.2 | J31: =WATER!Y35 -> 0 | K31: =WATER!AJ35 -> 0 | L31: =ELEC!B32 -> 2.99

Sheet ELEC
A1: OOC | B1: Room OCC | D1: MDB3 | E1: MDB3/day | F1: EMDB2 | G1: EMDB2/day | H1: EMDB1 | I1: EMDB1/day | J1: MDB2 | K1: mdb2/day | L1: MDB1 | M1: MDB1/Day | N1: Total KWH | O1: KWH/Rooc | P1: Gen MHW | Q1: Gen/Day KWH | R1: EDL KWH | S1: CH1 RH | T1: RH | U1: C1h1 power | V1: CH1 Con KWH | W1: CH2 RH | X1: RH | Y1: Ch2 power | Z1: CH2 Con KWH | AA1: CH3 RH | AB1: RH | AC1: Ch3 power | AD1: CH3 Con KWH | AE1: RH total | AF1: KWH total | AG1: AVG chiller KW/Hr
A2: =[1]ELEC!$A$33 -> 0.0087 | B2: =[1]ELEC!$B$33 -> 2.001 | C2: 43921 | D2: =[1]ELEC!D33 -> 31561298 | E2: =[1]ELEC!E33 -> 2012 | F2: =[1]ELEC!F33 -> 3605675 | G2: =[1]ELEC!G33 -> 1309 | H2: =[1]ELEC!H33 -> 17390434 | I2: =[1]ELEC!I33 -> 1104 | J2: =[1]ELEC!J33 -> 28361182 | K2: =[1]ELEC!K33 -> 772 | ... T2: =[1]ELEC!T33 -> 2 | U2: 29956 | V2: =[1]ELEC!V33 -> 319 | W2: =[1]ELEC!W33 -> 31845 | X2: =[1]ELEC!X33 -> 0 | Y2: =[1]ELEC!Y33 -> 624440 | Z2: =[1]ELEC!Z33 -> 0 | AA2: =[1]ELEC!AA33 -> 35018 | AB2: =[1]ELEC!AB33 -> 1 | AC2: =[1]ELEC!AC33 -> 767207 | ... AI2: =[1]ELEC!AI33 -> -49692041
A3: ='General information '!F6 -> 0.0174 | B3: =SUM(230*A3) -> 4.002 | C3: 43922 | D3: 31562966 | E3: =D3-D2 -> 1668 | F3: 3606937.2 | G3: =F3-F2 -> 1262.2 | H3: 17391546 | I3: =H3-H2 -> 1112 | J3: 28361922 | K3: =J3-J2 -> 740 | L3: 22854318 | M3: =L3-L2 -> 2880 | N3: =M3+K3+I3+G3+E3 -> 7662.2 | O3: =IF(B3>0,N3/B3,0) -> 1914.5927 | P3: 15437.157 | Q3: =(P3-P2)*1000 -> 2431 | R3: =+N3-Q3 -> 5231.2 | S3: 8410 | T3: =S3-S2 -> 1 | U3: 30202 | V3: =U3-U2 -> 246 | W3: 31845 | X3: =W3-W2 -> 0 | Y3: 624440 | Z3: =Y3-Y2 -> 0 | AA3: =AA2 -> 35018 | AB3: =AA3-AA2 -> 0 | AC3: =AC2 -> 767207 | AD3: =AC3-AC2 -> 0 | AE3: =AB3+X3+T3 -> 1 | AF3: =V3+Z3+AD3 -> 246 | AG3: =IF(AE3>0,AF3/AE3,0) -> 246
A4: ='General information '!F7 -> 0.0087 | B4: =SUM(230*A4) -> 2.001 | C4: 43923 | D4: 31564538 | E4: =D4-D3 -> 1572 | F4: 3608170.8 | G4: =F4-F3 -> 1233.6 | H4: 17392602 | I4: =H4-H3 -> 1056 | J4: 28362698 | K4: =J4-J3 -> 776 | L4: 22857118 | M4: =L4-L3 -> 2800 | N4: =M4+K4+I4+G4+E4 -> 7437.6 | O4: =IF(B4>0,N4/B4,0) -> 3716.9415 | P4: 15438.738 | Q4: =(P4-P3)*1000 -> 1581 | R4: =N4-Q4 -> 5856.6 | S4: 8411 | T4: =S4-S3 -> 1 | U4: 30510 | V4: =U4-U3 -> 308 | W4: =W3 -> 31845 | X4: =W4-W3 -> 0 | Y4: =Y3 -> 624440 | Z4: =Y4-Y3 -> 0 | AA4: =AA3 -> 35018 | AB4: =AA4-AA3 -> 0 | AC4: =AC3 -> 767207 | AD4: =AC4-AC3 -> 0 | AE4: =AB4+X4+T4 -> 1 | AF4: =V4+Z4+AD4 -> 308 | AG4: =IF(AE4>0,AF4/AE4,0) -> 308
A5: ='General information '!F8 -> 0.0087 | B5: =SUM(230*A5) -> 2.001 | C5: 43924 | D5: 31566594 | E5: =D5-D4 -> 2056 | F5: 3609462 | G5: =F5-F4 -> 1291.2 | H5: 17393732 | I5: =H5-H4 -> 1130 | J5: 28363616 | K5: =J5-J4 -> 918 | L5: 22860388 | M5: =L5-L4 -> 3270 | N5: =M5+K5+I5+G5+E5 -> 8665.2 | O5: =IF(B5>0,N5/B5,0) -> 4330.4348 | P5: 15440 | Q5: =(P5-P4)*1000 -> 1262 | R5: =N5-Q5 -> 7403.2 | S5: 8413 | T5: =S5-S4 -> 2 | U5: 31029 | V5: =U5-U4 -> 519 | W5: =W4 -> 31845 | X5: =W5-W4 -> 0 | Y5: =Y4 -> 624440 | Z5: =Y5-Y4 -> 0 | AA5: =AA4 -> 35018 | AB5: =AA5-AA4 -> 0 | AC5: =AC4 -> 767207 | AD5: =AC5-AC4 -> 0 | AE5: =AB5+X5+T5 -> 2 | AF5: =V5+Z5+AD5 -> 519 | AG5: =IF(AE5>0,AF5/AE5,0) -> 259.5 | AI5: =R5-'EDl log'!B3 -> -49702331
A6: ='General information '!F9 -> 0.013 | B6: =SUM(230*A6) -> 2.99 | C6: 43925 | D6: 31568378 | E6: =D6-D5 -> 1784 | F6: 3610652.4 | G6: =F6-F5 -> 1190.4 | H6: 17394844 | I6: =H6-H5 -> 1112 | J6: 28364390 | K6: =J6-J5 -> 774 | L6: 22863198 | M6: =L6-L5 -> 2810 | N6: =M6+K6+I6+G6+E6 -> 7670.4 | O6: =IF(B6>0,N6/B6,0) -> 2565.3512 | P6: 15441.642 | Q6: =(P6-P5)*1000 -> 1642 | R6: =N6-Q6 -> 6028.4 | S6: 8414 | T6: =S6-S5 -> 1 | U6: 31272 | V6: =U6-U5 -> 243 | W6: =W5 -> 31845 | X6: =W6-W5 -> 0 | Y6: =Y5 -> 624440 | Z6: =Y6-Y5 -> 0 | AA6: =AA5 -> 35018 | AB6: =AA6-AA5 -> 0 | AC6: =AC5 -> 767207 | AD6: =AC6-AC5 -> 0 | AE6: =AB6+X6+T6 -> 1 | AF6: =V6+Z6+AD6 -> 243 | AG6: =IF(AE6>0,AF6/AE6,0) -> 243 | AI6: =R6-'EDl log'!B4 -> -49706937
A7: ='General information '!F10 -> 0.0304 | B7: =SUM(230*A7) -> 6.992 | C7: 43926 | D7: 31571302 | E7: =D7-D6 -> 2924 | F7: 3611801.2 | G7: =F7-F6 -> 1148.8 | H7: 17395930 | I7: =H7-H6 -> 1086 | J7: 28365278 | K7: =J7-J6 -> 888 | L7: 22865690 | M7: =L7-L6 -> 2492 | N7: =M7+K7+I7+G7+E7 -> 8538.8 | O7: =IF(B7>0,N7/B7,0) -> 1221.2243 | P7: 15443.333 | Q7: =(P7-P6)*1000 -> 1691 | R7: =N7-Q7 -> 6847.8 | S7: 8416 | T7: =S7-S6 -> 2 | U7: 31598 | V7: =U7-U6 -> 326 | W7: 31845 | X7: =W7-W6 -> 0 | Y7: 624440 | Z7: =Y7-Y6 -> 0 | AA7: 35025 | AB7: =AA7-AA6 -> 7 | AC7: 768802 | AD7: =AC7-AC6 -> 1595 | AE7: =AB7+X7+T7 -> 9 | AF7: =V7+Z7+AD7 -> 1921 | AG7: =IF(AE7>0,AF7/AE7,0) -> 213.44444 | AI7: =R7-'EDl log'!B5 -> -49709193
A8: ='General information '!F11 -> 0.0087 | B8: =SUM(230*A8) -> 2.001 | C8: 43927 | D8: 31574602 | E8: =D8-D7 -> 3300 | F8: 3613153 | G8: =F8-F7 -> 1351.8 | H8: 17397122 | I8: =H8-H7 -> 1192 | J8: 28366300 | K8: =J8-J7 -> 1022 | L8: 22868882 | M8: =L8-L7 -> 3192 | N8: =M8+K8+I8+G8+E8 -> 10057.8 | O8: =IF(B8>0,N8/B8,0) -> 5026.3868 | P8: 15445.123 | Q8: =(P8-P7)*1000 -> 1790 | R8: =N8-Q8 -> 8267.8 | S8: 8416 | T8: =S8-S7 -> 0 | U8: 31598 | V8: =U8-U7 -> 0 | W8: 31845 | X8: =W8-W7 -> 0 | Y8: 624440 | Z8: =Y8-Y7 -> 0 | AA8: 35025 | AB8: =AA8-AA7 -> 0 | AC8: 768802 | AD8: =AC8-AC7 -> 0 | AE8: =AB8+X8+T8 -> 0 | AF8: =V8+Z8+AD8 -> 0 | AG8: =IF(AE8>0,AF8/AE8,0) -> 0 | AI8: =R8-'EDl log'!B6 -> -49711486
A9: ='General information '!F12 -> 0.0087 | B9: =SUM(230*A9) -> 2.001 | C9: 43928 | D9: 31576780 | E9: =D9-D8 -> 2178 | F9: 3614424.4 | G9: =F9-F8 -> 1271.4 | H9: 17398208 | I9: =H9-H8 -> 1086 | J9: 28367132 | K9: =J9-J8 -> 832 | L9: 22871424 | M9: =L9-L8 -> 2542 | N9: =M9+K9+I9+G9+E9 -> 7909.4 | O9: =IF(B9>0,N9/B9,0) -> 3952.7236 | P9: 15446.522 | Q9: =(P9-P8)*1000 -> 1399 | R9: =N9-Q9 -> 6510.4 | S9: 8416 | T9: =S9-S8 -> 0 | U9: 31598 | V9: =U9-U8 -> 0 | W9: 31845 | X9: =W9-W8 -> 0 | Y9: 624440 | Z9: =Y9-Y8 -> 0 | AA9: 35026 | AB9: =AA9-AA8 -> 1 | AC9: 769112 | AD9: =AC9-AC8 -> 310 | AE9: =AB9+X9+T9 -> 1 | AF9: =V9+Z9+AD9 -> 310 | AG9: =IF(AE9>0,AF9/AE9,0) -> 310 | AI9: =R9-'EDl log'!B7 -> -49716573
A10: ='General information '!F13 -> 0.0478 | B10: =SUM(230*A10) -> 10.994 | C10: 43929 | D10: 31580646 | E10: =D10-D9 -> 3866 | F10: 3615938 | G10: =F10-F9 -> 1513.6 | H10: 17399560 | I10: =H10-H9 -> 1352 | J10: 28368306 | K10: =J10-J9 -> 1174 | L10: 22874334 | M10: =L10-L9 -> 2910 | N10: =M10+K10+I10+G10+E10 -> 10815.6 | O10: =IF(B10>0,N10/B10,0) -> 983.77297 | P10: 15448.133 | Q10: =(P10-P9)*1000 -> 1611 | R10: =N10-Q10 -> 9204.6 | S10: 8416 | T10: =S10-S9 -> 0 | U10: 31598 | V10: =U10-U9 -> 0 | W10: 31845 | X10: =W10-W9 -> 0 | Y10: 624440 | Z10: =Y10-Y9 -> 0 | AA10: 35030 | AB10: =AA10-AA9 -> 4 | AC10: 770135 | AD10: =AC10-AC9 -> 1023 | AE10: =AB10+X10+T10 -> 4 | AF10: =V10+Z10+AD10 -> 1023 | AG10: =IF(AE10>0,AF10/AE10,0) -> 255.75 | AI10: =R10-'EDl log'!B8 -> -49717461
A11: ='General information '!F14 -> 0.0217 | B11: =SUM(230*A11) -> 4.991 | C11: 43930 | D11: 31583976 | E11: =D11-D10 -> 3330 | F11: 3617225 | G11: =F11-F10 -> 1287 | H11: 17400718 | I11: =H11-H10 -> 1158 | J11: 28369278 | K11: =J11-J10 -> 972 | L11: 22876690 | M11: =L11-L10 -> 2356 | N11: =M11+K11+I11+G11+E11 -> 9103 | O11: =IF(B11>0,N11/B11,0) -> 1823.883 | P11: 15450 | Q11: =(P11-P10)*1000 -> 1867 | R11: =N11-Q11 -> 7236 | S11: =S10 -> 8416 | T11: =S11-S10 -> 0 | U11: =U10 -> 31598 | V11: =U11-U10 -> 0 | W11: =W10 -> 31845 | X11: =W11-W10 -> 0 | Y11: =Y10 -> 624440 | Z11: =Y11-Y10 -> 0 | AA11: 35032 | AB11: =AA11-AA10 -> 2 | AC11: 770886 | AD11: =AC11-AC10 -> 751 | AE11: =AB11+X11+T11 -> 2 | AF11: =V11+Z11+AD11 -> 751 | AG11: =IF(AE11>0,AF11/AE11,0) -> 375.5 | AI11: =R11-'EDl log'!B9 -> -49723744
A12: ='General information '!F15 -> 0.0087 | B12: =SUM(230*A12) -> 2.001 | C12: 43931 | D12: 31586162 | E12: =D12-D11 -> 2186 | F12: 3618515.6 | G12: =F12-F11 -> 1290.6 | H12: 17401918 | I12: =H12-H11 -> 1200 | J12: 28370232 | K12: =J12-J11 -> 954 | L12: 22879082 | M12: =L12-L11 -> 2392 | N12: =M12+K12+I12+G12+E12 -> 8022.6 | O12: =IF(B12>0,N12/B12,0) -> 4009.2954 | P12: 15451 | Q12: =(P12-P11)*1000 -> 1000 | R12: =N12-Q12 -> 7022.6 | S12: =S11 -> 8416 | T12: =S12-S11 -> 0 | U12: =U11 -> 31598 | V12: =U12-U11 -> 0 | W12: =W11 -> 31845 | X12: =W12-W11 -> 0 | Y12: =Y11 -> 624440 | Z12: =Y12-Y11 -> 0 | AA12: 35034 | AB12: =AA12-AA11 -> 2 | AC12: 771312 | AD12: =AC12-AC11 -> 426 | AE12: =AB12+X12+T12 -> 2 | AF12: =V12+Z12+AD12 -> 426 | AG12: =IF(AE12>0,AF12/AE12,0) -> 213 | AI12: =R12-'EDl log'!B10 -> -49727414
A13: ='General information '!F16 -> 0.0174 | B13: =SUM(230*A13) -> 4.002 | C13: 43932 | D13: 31588498 | E13: =D13-D12 -> 2336 | F13: 3619893 | G13: =F13-F12 -> 1377.4 | H13: 17403218 | I13: =H13-H12 -> 1300 | J13: 28371210 | K13: =J13-J12 -> 978 | L13: 22881694 | M13: =L13-L12 -> 2612 | N13: =M13+K13+I13+G13+E13 -> 8603.4 | O13: =IF(B13>0,N13/B13,0) -> 2149.7751 | P13: 15453 | Q13: =(P13-P12)*1000 -> 2000 | R13: =N13-Q13 -> 6603.4 | S13: =S12 -> 8416 | T13: =S13-S12 -> 0 | U13: =U12 -> 31598 | V13: =U13-U12 -> 0 | W13: =W12 -> 31845 | X13: =W13-W12 -> 0 | Y13: =Y12 -> 624440 | Z13: =Y13-Y12 -> 0 | AA13: 35035 | AB13: =AA13-AA12 -> 1 | AC13: 771620 | AD13: =AC13-AC12 -> 308 | AE13: =AB13+X13+T13 -> 1 | AF13: =V13+Z13+AD13 -> 308 | AG13: =IF(AE13>0,AF13/AE13,0) -> 308 | AI13: =R13-'EDl log'!B11 -> -49732572
A14: ='General information '!F17 -> 0.013 | B14: =SUM(230*A14) -> 2.99 | C14: 43933 | D14: 31591294 | E14: =D14-D13 -> 2796 | F14: 3621146 | G14: =F14-F13 -> 1253 | H14: 17404486 | I14: =H14-H13 -> 1268 | J14: 28372168 | K14: =J14-J13 -> 958 | L14: 22884162 | M14: =L14-L13 -> 2468 | N14: =M14+K14+I14+G14+E14 -> 8743 | O14: =IF(B14>0,N14/B14,0) -> 2924.0803 | P14: 15454 | Q14: =(P14-P13)*1000 -> 1000 | R14: =N14-Q14 -> 7743 | S14: =S13 -> 8416 | T14: =S14-S13 -> 0 | U14: =U13 -> 31598 | V14: =U14-U13 -> 0 | W14: =W13 -> 31845 | X14: =W14-W13 -> 0 | Y14: =Y13 -> 624440 | Z14: =Y14-Y13 -> 0 | AA14: 35037 | AB14: =AA14-AA13 -> 2 | AC14: 772092 | AD14: =AC14-AC13 -> 472 | AE14: =AB14+X14+T14 -> 2 | AF14: =V14+Z14+AD14 -> 472 | AG14: =IF(AE14>0,AF14/AE14,0) -> 236 | AI14: =R14-'EDl log'!B12 -> -49735109
A15: ='General information '!F18 -> 0.0348 | B15: =SUM(230*A15) -> 8.004 | C15: 43934 | D15: 31593954 | E15: =D15-D14 -> 2660 | F15: 3622478 | G15: =F15-F14 -> 1332 | H15: 17405802 | I15: =H15-H14 -> 1316 | J15: 28373092 | K15: =J15-J14 -> 924 | L15: 22886694 | M15: =L15-L14 -> 2532 | N15: =M15+K15+I15+G15+E15 -> 8764 | O15: =IF(B15>0,N15/B15,0) -> 1094.9525 | P15: 15455 | Q15: =(P15-P14)*1000 -> 1000 | R15: =N15-Q15 -> 7764 | S15: =S14 -> 8416 | T15: =S15-S14 -> 0 | U15: =U14 -> 31598 | V15: =U15-U14 -> 0 | W15: =W14 -> 31845 | X15: =W15-W14 -> 0 | Y15: =Y14 -> 624440 | Z15: =Y15-Y14 -> 0 | AA15: =AA14 -> 35037 | AB15: =AA15-AA14 -> 0 | AC15: 772288 | AD15: =AC15-AC14 -> 196 | AE15: =AB15+X15+T15 -> 0 | AF15: =V15+Z15+AD15 -> 196 | AG15: =IF(AE15>0,AF15/AE15,0) -> 0 | AI15: =R15-'EDl log'!B13 -> -49738477
A16: ='General information '!F19 -> 0.0217 | B16: =SUM(230*A16) -> 4.991 | C16: 43935 | D16: 31596054 | E16: =D16-D15 -> 2100 | F16: 3623964.4 | G16: =F16-F15 -> 1486.4 | H16: 17407190 | I16: =H16-H15 -> 1388 | J16: 28374102 | K16: =J16-J15 -> 1010 | L16: 22889398 | M16: =L16-L15 -> 2704 | N16: =M16+K16+I16+G16+E16 -> 8688.4 | O16: =IF(B16>0,N16/B16,0) -> 1740.8135 | P16: 15457.114 | Q16: =(P16-P15)*1000 -> 2114 | R16: =N16-Q16 -> 6574.4 | S16: 8416 | T16: =S16-S15 -> 0 | U16: 31598 | V16: =U16-U15 -> 0 | W16: 31845 | X16: =W16-W15 -> 0 | Y16: 624440 | Z16: =Y16-Y15 -> 0 | AA16: 35038 | AB16: =AA16-AA15 -> 1 | AC16: 772525 | AD16: =AC16-AC15 -> 237 | AE16: =AB16+X16+T16 -> 1 | AF16: =V16+Z16+AD16 -> 237 | AG16: =IF(AE16>0,AF16/AE16,0) -> 237 | AI16: =R16-'EDl log'!B14 -> -49743158
A17: ='General information '!F20 -> 0.013 | B17: =SUM(230*A17) -> 2.99 | C17: 43936 | D17: 31598968 | E17: =D17-D16 -> 2914 | F17: 3625348.4 | G17: =F17-F16 -> 1384 | H17: 17408506 | I17: =H17-H16 -> 1316 | J17: 28375126 | K17: =J17-J16 -> 1024 | L17: 22892042 | M17: =L17-L16 -> 2644 | N17: =M17+K17+I17+G17+E17 -> 9282 | O17: =IF(B17>0,N17/B17,0) -> 3104.3478 | P17: 15458.864 | Q17: =(P17-P16)*1000 -> 1750 | R17: =N17-Q17 -> 7532 | S17: 8416 | T17: =S17-S16 -> 0 | U17: 31598 | V17: =U17-U16 -> 0 | W17: 31845 | X17: =W17-W16 -> 0 | Y17: 624440 | Z17: =Y17-Y16 -> 0 | AA17: 35041 | AB17: =AA17-AA16 -> 3 | AC17: 773141 | AD17: =AC17-AC16 -> 616 | AE17: =AB17+X17+T17 -> 3 | AF17: =V17+Z17+AD17 -> 616 | AG17: =IF(AE17>0,AF17/AE17,0) -> 205.33333 | AI17: =R17-'EDl log'!B15 -> -49746497
A18: ='General information '!F21 -> 0.01 | B18: =SUM(230*A18) -> 2.3 | C18: 43937 | D18: 31601698 | E18: =D18-D17 -> 2730 | F18: 3627030 | G18: =F18-F17 -> 1681.6 | H18: 17410024 | I18: =H18-H17 -> 1518 | J18: 28376340 | K18: =J18-J17 -> 1214 | L18: 22895670 | M18: =L18-L17 -> 3628 | N18: =M18+K18+I18+G18+E18 -> 10771.6 | O18: =IF(B18>0,N18/B18,0) -> 4683.3043 | P18: 15459.5 | Q18: =(P18-P17)*1000 -> 636 | R18: =N18-Q18 -> 10135.6 | S18: 8418 | T18: =S18-S17 -> 2 | U18: 32172 | V18: =U18-U17 -> 574 | W18: 31845 | X18: =W18-W17 -> 0 | Y18: =Y17 -> 624440 | Z18: =Y18-Y17 -> 0 | AA18: 35042 | AB18: =AA18-AA17 -> 1 | AC18: 773343 | AD18: =AC18-AC17 -> 202 | AE18: =AB18+X18+T18 -> 3 | AF18: =V18+Z18+AD18 -> 776 | AG18: =IF(AE18>0,AF18/AE18,0) -> 258.66667 | AI18: =R18-'EDl log'!B16 -> -49747767
A19: ='General information '!F22 -> 0.0087 | B19: =SUM(230*A19) -> 2.001 | C19: 43938 | D19: 31603542 | E19: =D19-D18 -> 1844 | F19: 3628364 | G19: =F19-F18 -> 1334 | H19: 17411118 | I19: =H19-H18 -> 1094 | J19: 28377274 | K19: =J19-J18 -> 934 | L19: 22898710 | M19: =L19-L18 -> 3040 | N19: =M19+K19+I19+G19+E19 -> 8246 | O19: =IF(B19>0,N19/B19,0) -> 4120.9395 | P19: 15461.289 | Q19: =(P19-P18)*1000 -> 1789 | R19: =N19-Q19 -> 6457 | S19: 8420 | T19: =S19-S18 -> 2 | U19: 32720 | V19: =U19-U18 -> 548 | W19: 31845 | X19: =W19-W18 -> 0 | Y19: =Y18 -> 624440 | Z19: =Y19-Y18 -> 0 | AA19: =AA18 -> 35042 | AB19: =AA19-AA18 -> 0 | AC19: =AC18 -> 773343 | AD19: =AC19-AC18 -> 0 | AE19: =AB19+X19+T19 -> 2 | AF19: =V19+Z19+AD19 -> 548 | AG19: =IF(AE19>0,AF19/AE19,0) -> 274 | AI19: =R19-'EDl log'!B17 -> -49755146
A20: ='General information '!F23 -> 0.013 | B20: =SUM(230*A20) -> 2.99 | C20: 43939 | D20: 31605926 | E20: =D20-D19 -> 2384 | F20: 3629837 | G20: =F20-F19 -> 1473 | H20: 17412422 | I20: =H20-H19 -> 1304 | J20: 28378316 | K20: =J20-J19 -> 1042 | L20: 22902130 | M20: =L20-L19 -> 3420 | N20: =M20+K20+I20+G20+E20 -> 9623 | O20: =IF(B20>0,N20/B20,0) -> 3218.3946 | P20: 15462.976 | Q20: =(P20-P19)*1000 -> 1687 | R20: =N20-Q20 -> 7936 | S20: 8423 | T20: =S20-S19 -> 3 | U20: 33208 | V20: =U20-U19 -> 488 | W20: =W19 -> 31845 | X20: =W20-W19 -> 0 | Y20: =Y19 -> 624440 | Z20: =Y20-Y19 -> 0 | AA20: =AA19 -> 35042 | AB20: =AA20-AA19 -> 0 | AC20: =AC19 -> 773343 | AD20: =AC20-AC19 -> 0 | AE20: =AB20+X20+T20 -> 3 | AF20: =V20+Z20+AD20 -> 488 | AG20: =IF(AE20>0,AF20/AE20,0) -> 162.66667 | AI20: =R20-'EDl log'!B18 -> -49757589
A21: ='General information '!F24 -> 0.0217 | B21: =SUM(230*A21) -> 4.991 | C21: 43940 | D21: 31608186 | E21: =D21-D20 -> 2260 | F21: 3631079 | G21: =F21-F20 -> 1242 | H21: 17413568 | I21: =H21-H20 -> 1146 | J21: 28379406 | K21: =J21-J20 -> 1090 | L21: 22905442 | M21: =L21-L20 -> 3312 | N21: =M21+K21+I21+G21+E21 -> 9050 | O21: =IF(B21>0,N21/B21,0) -> 1813.2639 | P21: 15463.334 | Q21: =(P21-P20)*1000 -> 358 | R21: =N21-Q21 -> 8692 | S21: 8425 | T21: =S21-S20 -> 2 | U21: 33943 | V21: =U21-U20 -> 735 | W21: =W20 -> 31845 | X21: =W21-W20 -> 0 | Y21: =Y20 -> 624440 | Z21: =Y21-Y20 -> 0 | AA21: =AA20 -> 35042 | AB21: =AA21-AA20 -> 0 | AC21: =AC20 -> 773343 | AD21: =AC21-AC20 -> 0 | AE21: =AB21+X21+T21 -> 2 | AF21: =V21+Z21+AD21 -> 735 | AG21: =IF(AE21>0,AF21/AE21,0) -> 367.5 | AI21: =R21-'EDl log'!B19 -> -49762137
A22: ='General information '!F25 -> 0.0087 | B22: =SUM(230*A22) -> 2.001 | C22: 43941 | D22: 31610498 | E22: =D22-D21 -> 2312 | F22: 3632435 | G22: =F22-F21 -> 1356 | H22: 17414834 | I22: =H22-H21 -> 1266 | J22: 28380474 | K22: =J22-J21 -> 1068 | L22: 22909138 | M22: =L22-L21 -> 3696 | N22: =M22+K22+I22+G22+E22 -> 9698 | O22: =IF(B22>0,N22/B22,0) -> 4846.5767 | P22: 15463.334 | Q22: =(P22-P21)*1000 -> 0 | R22: =N22-Q22 -> 9698 | S22: 8429 | T22: =S22-S21 -> 4 | U22: 34834 | V22: =U22-U21 -> 891 | W22: =W21 -> 31845 | X22: =W22-W21 -> 0 | Y22: =Y21 -> 624440 | Z22: =Y22-Y21 -> 0 | AA22: =AA21 -> 35042 | AB22: =AA22-AA21 -> 0 | AC22: =AC21 -> 773343 | AD22: =AC22-AC21 -> 0 | AE22: =AB22+X22+T22 -> 4 | AF22: =V22+Z22+AD22 -> 891 | AG22: =IF(AE22>0,AF22/AE22,0) -> 222.75 | AI22: =R22-'EDl log'!B20 -> -49764486
A23: ='General information '!F26 -> 0.0087 | B23: =SUM(230*A23) -> 2.001 | C23: 43942 | D23: 31612378 | E23: =D23-D22 -> 1880 | F23: 3633753 | G23: =F23-F22 -> 1318 | H23: 17415986 | I23: =H23-H22 -> 1152 | J23: 28381450 | K23: =J23-J22 -> 976 | L23: 22912266 | M23: =L23-L22 -> 3128 | N23: =M23+K23+I23+G23+E23 -> 8454 | O23: =IF(B23>0,N23/B23,0) -> 4224.8876 | P23: 15464.986 | Q23: =(P23-P22)*1000 -> 1652 | R23: =N23-Q23 -> 6802 | S23: 8432 | T23: =S23-S22 -> 3 | U23: 35423 | V23: =U23-U22 -> 589 | W23: 31845 | X23: =W23-W22 -> 0 | Y23: 624440 | Z23: =Y23-Y22 -> 0 | AA23: 35042 | AB23: =AA23-AA22 -> 0 | AC23: 773343 | AD23: =AC23-AC22 -> 0 | AE23: =AB23+X23+T23 -> 3 | AF23: =V23+Z23+AD23 -> 589 | AG23: =IF(AE23>0,AF23/AE23,0) -> 196.33333 | AI23: =R23-'EDl log'!B21 -> -49771537
A24: ='General information '!F27 -> 0.0087 | B24: =SUM(230*A24) -> 2.001 | C24: 43943 | D24: 31614590 | E24: =D24-D23 -> 2212 | F24: 3635325 | G24: =F24-F23 -> 1572 | H24: 17417342 | I24: =H24-H23 -> 1356 | J24: 28382546 | K24: =J24-J23 -> 1096 | L24: 22915870 | M24: =L24-L23 -> 3604 | N24: =M24+K24+I24+G24+E24 -> 9840 | O24: =IF(B24>0,N24/B24,0) -> 4917.5412 | P24: 15467.004 | Q24: =(P24-P23)*1000 -> 2018 | R24: =N24-Q24 -> 7822 | S24: 8434 | T24: =S24-S23 -> 2 | U24: 35999 | V24: =U24-U23 -> 576 | W24: 31845 | X24: =W24-W23 -> 0 | Y24: 624440 | Z24: =Y24-Y23 -> 0 | AA24: 35042 | AB24: =AA24-AA23 -> 0 | AC24: 773343 | AD24: =AC24-AC23 -> 0 | AE24: =AB24+X24+T24 -> 2 | AF24: =V24+Z24+AD24 -> 576 | AG24: =IF(AE24>0,AF24/AE24,0) -> 288 | AI24: =R24-'EDl log'!B22 -> -49775041
A25: ='General information '!F28 -> 0.0087 | B25: =SUM(230*A25) -> 2.001 | C25: 43944 | D25: 31616650 | E25: =D25-D24 -> 2060 | F25: 3636670 | G25: =F25-F24 -> 1345 | H25: 17418468 | I25: =H25-H24 -> 1126 | J25: 28383382 | K25: =J25-J24 -> 836 | L25: 22918890 | M25: =L25-L24 -> 3020 | N25: =M25+K25+I25+G25+E25 -> 8387 | O25: =IF(B25>0,N25/B25,0) -> 4191.4043 | P25: 15468 | Q25: =(P25-P24)*1000 -> 996 | R25: =N25-Q25 -> 7391 | S25: 8437 | T25: =S25-S24 -> 3 | U25: 36455 | V25: =U25-U24 -> 456 | W25: =W24 -> 31845 | X25: =W25-W24 -> 0 | Y25: =Y24 -> 624440 | Z25: =Y25-Y24 -> 0 | AA25: =AA24 -> 35042 | AB25: =AA25-AA24 -> 0 | AC25: =AC24 -> 773343 | AD25: =AC25-AC24 -> 0 | AE25: =AB25+X25+T25 -> 3 | AF25: =V25+Z25+AD25 -> 456 | AG25: =IF(AE25>0,AF25/AE25,0) -> 152 | AI25: =R25-'EDl log'!B23 -> -49780505
A26: ='General information '!F29 -> 0.0087 | B26: =SUM(230*A26) -> 2.001 | C26: 43945 | D26: 31619370 | E26: =D26-D25 -> 2720 | F26: 3638044.4 | G26: =F26-F25 -> 1374.4 | H26: 17419674 | I26: =H26-H25 -> 1206 | J26: 28384482 | K26: =J26-J25 -> 1100 | L26: 22922712 | M26: =L26-L25 -> 3822 | N26: =M26+K26+I26+G26+E26 -> 10222.4 | O26: =IF(B26>0,N26/B26,0) -> 5108.6457 | P26: 15469.98 | Q26: =(P26-P25)*1000 -> 1980 | R26: =N26-Q26 -> 8242.4 | S26: 8441 | T26: =S26-S25 -> 4 | U26: 37459 | V26: =U26-U25 -> 1004 | W26: =W25 -> 31845 | X26: =W26-W25 -> 0 | Y26: =Y25 -> 624440 | Z26: =Y26-Y25 -> 0 | AA26: =AA25 -> 35042 | AB26: =AA26-AA25 -> 0 | AC26: =AC25 -> 773343 | AD26: =AC26-AC25 -> 0 | AE26: =AB26+X26+T26 -> 4 | AF26: =V26+Z26+AD26 -> 1004 | AG26: =IF(AE26>0,AF26/AE26,0) -> 251 | AI26: =R26-'EDl log'!B24 -> -49783217
A27: ='General information '!F30 -> 0.0174 | B27: =SUM(230*A27) -> 4.002 | C27: 43946 | D27: 31621706 | E27: =D27-D26 -> 2336 | F27: 3639346 | G27: =F27-F26 -> 1301.6 | H27: 17420866 | I27: =H27-H26 -> 1192 | J27: 28385472 | K27: =J27-J26 -> 990 | L27: 22926062 | M27: =L27-L26 -> 3350 | N27: =M27+K27+I27+G27+E27 -> 9169.6 | O27: =IF(B27>0,N27/B27,0) -> 2291.2544 | P27: 15471.5 | Q27: =(P27-P26)*1000 -> 1520 | R27: =N27-Q27 -> 7649.6 | S27: 8444 | T27: =S27-S26 -> 3 | U27: 38088 | V27: =U27-U26 -> 629 | W27: =W26 -> 31845 | X27: =W27-W26 -> 0 | Y27: =Y26 -> 624440 | Z27: =Y27-Y26 -> 0 | AA27: =AA26 -> 35042 | AB27: =AA27-AA26 -> 0 | AC27: =AC26 -> 773343 | AD27: =AC27-AC26 -> 0 | AE27: =AB27+X27+T27 -> 3 | AF27: =V27+Z27+AD27 -> 629 | AG27: =IF(AE27>0,AF27/AE27,0) -> 209.66667 | AI27: =R27-'EDl log'!B25 -> -49787896
A28: ='General information '!F31 -> 0.0348 | B28: =SUM(230*A28) -> 8.004 | C28: 43947 | D28: 31623718 | E28: =D28-D27 -> 2012 | F28: 3640592 | G28: =F28-F27 -> 1246 | H28: 17422066 | I28: =H28-H27 -> 1200 | J28: 28386398 | K28: =J28-J27 -> 926 | L28: 22929078 | M28: =L28-L27 -> 3016 | N28: =M28+K28+I28+G28+E28 -> 8400 | O28: =IF(B28>0,N28/B28,0) -> 1049.4753 | P28: 15473 | Q28: =(P28-P27)*1000 -> 1500 | R28: =N28-Q28 -> 6900 | S28: 8446 | T28: =S28-S27 -> 2 | U28: 38539 | V28: =U28-U27 -> 451 | W28: =W27 -> 31845 | X28: =W28-W27 -> 0 | Y28: =Y27 -> 624440 | Z28: =Y28-Y27 -> 0 | AA28: =AA27 -> 35042 | AB28: =AA28-AA27 -> 0 | AC28: =AC27 -> 773343 | AD28: =AC28-AC27 -> 0 | AE28: =AB28+X28+T28 -> 2 | AF28: =V28+Z28+AD28 -> 451 | AG28: =IF(AE28>0,AF28/AE28,0) -> 225.5 | AI28: =R28-'EDl log'!B26 -> -49792018
A29: ='General information '!F32 -> 0.0087 | B29: =SUM(230*A29) -> 2.001 | C29: 43948 | D29: 31625998 | E29: =D29-D28 -> 2280 | F29: 3642080 | G29: =F29-F28 -> 1488 | H29: 17423448 | I29: =H29-H28 -> 1382 | J29: 28387428 | K29: =J29-J28 -> 1030 | L29: 22932548 | M29: =L29-L28 -> 3470 | N29: =M29+K29+I29+G29+E29 -> 9650 | O29: =IF(B29>0,N29/B29,0) -> 4822.5887 | P29: 15475.513 | Q29: =(P29-P28)*1000 -> 2513 | R29: =N29-Q29 -> 7137 | S29: 8449 | T29: =S29-S28 -> 3 | U29: 39033 | V29: =U29-U28 -> 494 | W29: 31845 | X29: =W29-W28 -> 0 | Y29: 624440 | Z29: =Y29-Y28 -> 0 | AA29: 35042 | AB29: =AA29-AA28 -> 0 | AC29: 773343 | AD29: =AC29-AC28 -> 0 | AE29: =AB29+X29+T29 -> 3 | AF29: =V29+Z29+AD29 -> 494 | AG29: =IF(AE29>0,AF29/AE29,0) -> 164.66667 | AI29: =R29-'EDl log'!B27 -> -49796566
A30: ='General information '!F33 -> 0.0174 | B30: =SUM(230*A30) -> 4.002 | C30: 43949 | D30: 31628282 | E30: =D30-D29 -> 2284 | F30: 3643444 | G30: =F30-F29 -> 1364 | H30: 17424726 | I30: =H30-H29 -> 1278 | J30: 28388330 | K30: =J30-J29 -> 902 | L30: 22935484 | M30: =L30-L29 -> 2936 | N30: =M30+K30+I30+G30+E30 -> 8764 | O30: =IF(B30>0,N30/B30,0) -> 2189.905 | P30: 15476.532 | Q30: =(P30-P29)*1000 -> 1019 | R30: =N30-Q30 -> 7745 | S30: 8450 | T30: =S30-S29 -> 1 | U30: 39179 | V30: =U30-U29 -> 146 | W30: 31845 | X30: =W30-W29 -> 0 | Y30: 624440 | Z30: =Y30-Y29 -> 0 | AA30: 35042 | AB30: =AA30-AA29 -> 0 | AC30: 773343 | AD30: =AC30-AC29 -> 0 | AE30: =AB30+X30+T30 -> 1 | AF30: =V30+Z30+AD30 -> 146 | AG30: =IF(AE30>0,AF30/AE30,0) -> 146 | AI30: =R30-'EDl log'!B28 -> -49799895
A31: ='General information '!F34 -> 0.0174 | B31: =SUM(230*A31) -> 4.002 | C31: 43950 | D31: 31630714 | E31: =D31-D30 -> 2432 | F31: 3644716.4 | G31: =F31-F30 -> 1272.4 | H31: 17425898 | I31: =H31-H30 -> 1172 | J31: 28389326 | K31: =J31-J30 -> 996 | L31: 22938680 | M31: =L31-L30 -> 3196 | N31: =M31+K31+I31+G31+E31 -> 9068.4 | O31: =IF(B31>0,N31/B31,0) -> 2265.967 | P31: 15477.83 | Q31: =(P31-P30)*1000 -> 1298 | R31: =N31-Q31 -> 7770.4 | S31: 8452 | T31: =S31-S30 -> 2 | U31: 39860 | V31: =U31-U30 -> 681 | W31: 31845 | X31: =W31-W30 -> 0 | Y31: 624440 | Z31: =Y31-Y30 -> 0 | AA31: 35042 | AB31: =AA31-AA30 -> 0 | AC31: 773343 | AD31: =AC31-AC30 -> 0 | AE31: =AB31+X31+T31 -> 2 | AF31: =V31+Z31+AD31 -> 681 | AG31: =IF(AE31>0,AF31/AE31,0) -> 340.5 | AI31: =R31-'EDl log'!B29 -> -49803311
A32: ='General information '!F35 -> 0.013 | B32: =SUM(230*A32) -> 2.99 | C32: 43951 | D32: 31633090 | E32: =D32-D31 -> 2376 | F32: 3646395.6 | G32: =F32-F31 -> 1679.2 | H32: 17427416 | I32: =H32-H31 -> 1518 | J32: 28390420 | K32: =J32-J31 -> 1094 | L32: 22942186 | M32: =L32-L31 -> 3506 | N32: =M32+K32+I32+G32+E32 -> 10173.2 | O32: =IF(B32>0,N32/B32,0) -> 3402.408 | P32: 15479.6 | Q32: =(P32-P31)*1000 -> 1770 | R32: =N32-Q32 -> 8403.2 | S32: 8454 | T32: =S32-S31 -> 2 | U32: 40221 | V32: =U32-U31 -> 361 | W32: =W31 -> 31845 | X32: =W32-W31 -> 0 | Y32: =Y31 -> 624440 | Z32: =Y32-Y31 -> 0 | AA32: =AA31 -> 35042 | AB32: =AA32-AA31 -> 0 | AC32: =AC31 -> 773343 | AD32: =AC32-AC31 -> 0 | AE32: =AB32+X32+T32 -> 2 | AF32: =V32+Z32+AD32 -> 361 | AG32: =IF(AE32>0,AF32/AE32,0) -> 180.5 | AI32: =R32-'EDl log'!B30 -> -49806640

Sheet B5
F1: Boiler A | J1: =J35 -> 82.769841 | K1: Boiler B | P1: Boiler C | V1: Boiler | X1: SteamA | AC1: SteamB | AH1: Steam | AI1: Boiler & steam | AL1: Total Boiler Runing H | AM1: Total Steam Runing H | AN1: GAS1 % | AO1: GAS1/L | AP1: GAS2% | AQ1: Gas2/L | AR1: GAS3% | AS1: GAS3/L | AU1: Gas Cons | AV1: Delivery | AW1: Cost/L
B2: Level Tank Gen | C2: Level tank Boiler | D2: Daily Cons Bo. | E2: Boiler litter | F2: Boiler A | G2: Run Hr a | H2: Boiler A fuel | I2: Daily consumption | J2: AVG | K2: index Run H | L2: Run Hrb | M2: Boiler B Fuel | O2: Daily consumption | P2: Boiler C | S2: Run C | U2: Total RH | V2: Total Fuel | X2: SteamA | Y2: Run SA | Z2: Steam A Conter | AA2: Liters | AC2: SteamB | AD2: Run SteamB | AE2: Steam B Conter | AF2: SB Litters | AG2: Avg | AH2: Total Fuel | AI2: Total Fuel
S3: 0
A4: =ELEC!C2 -> 43921 | B4: =[1]B5!B35 -> 252 | C4: =[1]B5!C35 -> 258 | D4: =[1]B5!D35 -> -34 | E4: =[1]B5!E35 -> -284.92 | F4: =[1]B5!F35 -> 1498 | G4: =[1]B5!G35 -> 1 | H4: =[1]B5!H35 -> 346077 | I4: =[1]B5!I35 -> 84 | ... AX4: =[1]B5!AX35 -> 0.7
A5: =ELEC!C3 -> 43922 | B5: 247 | C5: 253 | D5: =C4-C5 -> 5 | E5: =D5*8.38 -> 41.9 | F5: 1499 | G5: =F5-F4 -> 1 | H5: 346155 | I5: =SUM(H5-H4) -> 78 | J5: 1 | K5: 1883 | L5: =K5-K4 -> 4 | M5: 137637 | N5: =M5-M4 -> 189 | O5: =SUM(L5*$J$1) -> 331.07937 | P5: =P4 -> 1727 | Q5: =Q4 -> 147146 | R5: =Q5-Q4 -> 0 | S5: =SUM(P5-P4) -> 0 | T5: =SUM(S5*$T$2) -> 0 | U5: =SUM(G5+L5+S5) -> 5 | V5: =R5+N5+I5:I5 -> 267 | W5: =SUM(V5/U5) -> 53.4 | X5: =X4 -> 2404 | Y5: =X5-X4 -> 0 | Z5: =Z4 -> 135129.3 | AA5: =Z5-Z4 -> 0 | AB5: =SUM(Y5*$AB$2) -> 0 | AC5: =AC4 -> 1824 | AD5: =AC5-AC4 -> 0 | AE5: =AE4 -> 358857.5 | AF5: =AE5-AE4 -> 0 | AG5: =IF(AD5>0,AF5/AD5,0) -> 0 | AH5: =AF5+AA5 -> 0 | AI5: =SUM(AH5+V5) -> 267 | AJ5: =-tanks!AW6 -> 267 | AK5: =SUM(AJ5-AI5) -> 0 | AL5: =S5+L5+G5 -> 5 | AM5: =Y5+AD5 -> 0 | AN5: 71 | AO5: =(AN5/100)*3000 -> 2130 | AP5: 68 | AQ5: =(AP5/100)*3000 -> 2040 | AR5: 65 | AS5: =(AR5/100)*3000 -> 1950 | AT5: =SUM(AO5+AQ5+AS5) -> 6120 | AU5: =AT4-AT5+AV5 -> 60 | AX5: =IF(AV5>0,AW5,AX4) -> 0.7
A6: =ELEC!C4 -> 43923 | B6: 243 | C6: 249 | D6: =C5-C6 -> 4 | E6: =D6*8.38 -> 33.52 | F6: 1499 | G6: =F6-F5 -> 0 | H6: =H5 -> 346155 | I6: =SUM(H6-H5) -> 0 | J6: =IF(G6>0,I6/G6,0) -> 0 | K6: 1883 | L6: =K6-K5 -> 0 | M6: 137775 | N6: =M6-M5 -> 138 | O6: =SUM(L6*$J$1) -> 0 | P6: 1729 | Q6: 147315 | R6: =Q6-Q5 -> 169 | S6: =SUM(P6-P5) -> 2 | T6: =SUM(S6*$T$2) -> 0 | U6: =SUM(G6+L6+S6) -> 2 | V6: =R6+N6+I6:I6 -> 307 | W6: =SUM(V6/U6) -> 153.5 | X6: =X5 -> 2404 | Y6: =X6-X5 -> 0 | Z6: =Z5 -> 135129.3 | AA6: =Z6-Z5 -> 0 | AB6: =SUM(Y6*$AB$2) -> 0 | AC6: =AC5 -> 1824 | AD6: =AC6-AC5 -> 0 | AE6: =AE5 -> 358857.5 | AF6: =AE6-AE5 -> 0 | AG6: =IF(AD6>0,AF6/AD6,0) -> 0 | AH6: =AF6+AA6 -> 0 | AI6: =SUM(AH6+V6) -> 307 | AJ6: =-tanks!AW7 -> 307 | AK6: =SUM(AJ6-AI6) -> 0 | AL6: =S6+L6+G6 -> 2 | AM6: =Y6+AD6 -> 0 | AN6: 68 | AO6: =(AN6/100)*3000 -> 2040 | AP6: 66 | AQ6: =(AP6/100)*3000 -> 1980 | AR6: 64 | AS6: =(AR6/100)*3000 -> 1920 | AT6: =SUM(AO6+AQ6+AS6) -> 5940 | AU6: =AT5-AT6+AV6 -> 180 | AX6: =IF(AV6>0,AW6,AX5) -> 0.7
A7: =ELEC!C5 -> 43924 | B7: 241 | C7: 246 | D7: =C6-C7 -> 3 | E7: =D7*8.38 -> 25.14 | F7: 1502 | G7: =F7-F6 -> 3 | H7: 346351 | I7: =SUM(H7-H6) -> 196 | J7: =IF(G7>0,I7/G7,0) -> 65.333333 | K7: =K6 -> 1883 | L7: =K7-K6 -> 0 | M7: =M6 -> 137775 | N7: =M7-M6 -> 0 | O7: 1 | P7: 1731 | Q7: 147470 | R7: =Q7-Q6 -> 155 | S7: =SUM(P7-P6) -> 2 | T7: =SUM(S7*$T$2) -> 0 | U7: =SUM(G7+L7+S7) -> 5 | V7: =R7+N7+I7:I7 -> 351 | W7: =SUM(V7/U7) -> 70.2 | X7: =X6 -> 2404 | Y7: =X7-X6 -> 0 | Z7: =Z6 -> 135129.3 | AA7: =Z7-Z6 -> 0 | AB7: =SUM(Y7*$AB$2) -> 0 | AC7: =AC6 -> 1824 | AD7: =AC7-AC6 -> 0 | AE7: =AE6 -> 358857.5 | AF7: =AE7-AE6 -> 0 | AG7: =IF(AD7>0,AF7/AD7,0) -> 0 | AH7: =AF7+AA7 -> 0 | AI7: =SUM(AH7+V7) -> 351 | AJ7: =-tanks!AW8 -> 351 | AK7: =SUM(AJ7-AI7) -> 0 | AL7: =S7+L7+G7 -> 5 | AM7: =Y7+AD7 -> 0 | AN7: =AN6 -> 68 | AO7: =(AN7/100)*3000 -> 2040 | AP7: =AP6 -> 66 | AQ7: =(AP7/100)*3000 -> 1980 | AR7: 62 | AS7: =(AR7/100)*3000 -> 1860 | AT7: =SUM(AO7+AQ7+AS7) -> 5880 | AU7: =AT6-AT7+AV7 -> 60 | AX7: =IF(AV7>0,AW7,AX6) -> 0.7
A8: =ELEC!C6 -> 43925 | B8: 239 | C8: 244 | D8: =C7-C8 -> 2 | E8: =D8*8.38 -> 16.76 | F8: 1503 | G8: =F8-F7 -> 1 | H8: 346462 | I8: =SUM(H8-H7) -> 111 | J8: =IF(G8>0,I8/G8,0) -> 111 | K8: 1884 | L8: =K8-K7 -> 1 | M8: 137882 | N8: =M8-M7 -> 107 | O8: 1479 | P8: 1732 | Q8: 147523 | R8: =Q8-Q7 -> 53 | S8: =SUM(P8-P7) -> 1 | T8: =SUM(S8*$T$2) -> 0 | U8: =SUM(G8+L8+S8) -> 3 | V8: =R8+N8+I8:I8 -> 271 | W8: =SUM(V8/U8) -> 90.333333 | X8: 2404 | Y8: =X8-X7 -> 0 | Z8: =Z7 -> 135129.3 | AA8: =Z8-Z7 -> 0 | AB8: =SUM(Y8*$AB$2) -> 0 | AC8: =AC7 -> 1824 | AD8: =AC8-AC7 -> 0 | AE8: =AE7 -> 358857.5 | AF8: =AE8-AE7 -> 0 | AG8: =IF(AD8>0,AF8/AD8,0) -> 0 | AH8: =AF8+AA8 -> 0 | AI8: =SUM(AH8+V8) -> 271 | AJ8: =-tanks!AW9 -> 271 | AK8: =SUM(AJ8-AI8) -> 0 | AL8: =S8+L8+G8 -> 3 | AM8: =Y8+AD8 -> 0 | AN8: 66 | AO8: =(AN8/100)*3000 -> 1980 | AP8: 65 | AQ8: =(AP8/100)*3000 -> 1950 | AR8: 61 | AS8: =(AR8/100)*3000 -> 1830 | AT8: =SUM(AO8+AQ8+AS8) -> 5760 | AU8: =AT7-AT8+AV8 -> 120 | AX8: =IF(AV8>0,AW8,AX7) -> 0.7
A9: =ELEC!C7 -> 43926 | B9: 235 | C9: 241 | D9: =C8-C9 -> 3 | E9: =D9*8.38 -> 25.14 | F9: =F8 -> 1503 | G9: =F9-F8 -> 0 | H9: =H8 -> 346462 | I9: =SUM(H9-H8) -> 0 | J9: =IF(G9>0,I9/G9,0) -> 0 | K9: =K8 -> 1884 | L9: =K9-K8 -> 0 | M9: =M8 -> 137882 | N9: =M9-M8 -> 0 | O9: =SUM(L9*$J$1) -> 0 | P9: 1734 | Q9: 147775 | R9: =Q9-Q8 -> 252 | S9: =SUM(P9-P8) -> 2 | T9: =SUM(S9*$T$2) -> 0 | U9: =SUM(G9+L9+S9) -> 2 | V9: =R9+N9+I9:I9 -> 252 | W9: =SUM(V9/U9) -> 126 | X9: =X8 -> 2404 | Y9: =X9-X8 -> 0 | Z9: =Z8 -> 135129.3 | AA9: =Z9-Z8 -> 0 | AB9: =SUM(Y9*$AB$2) -> 0 | AC9: =AC8 -> 1824 | AD9: =AC9-AC8 -> 0 | AE9: =AE8 -> 358857.5 | AF9: =AE9-AE8 -> 0 | AG9: =IF(AD9>0,AF9/AD9,0) -> 0 | AH9: =AF9+AA9 -> 0 | AI9: =SUM(AH9+V9) -> 252 | AJ9: =-tanks!AW10 -> 252 | AK9: =SUM(AJ9-AI9) -> 0 | AL9: =S9+L9+G9 -> 2 | AM9: =Y9+AD9 -> 0 | AN9: 66 | AO9: =(AN9/100)*3000 -> 1980 | AP9: 65 | AQ9: =(AP9/100)*3000 -> 1950 | AR9: 60 | AS9: =(AR9/100)*3000 -> 1800 | AT9: =SUM(AO9+AQ9+AS9) -> 5730 | AU9: =AT8-AT9+AV9 -> 30 | AX9: =IF(AV9>0,AW9,AX8) -> 0.7
A10: =ELEC!C8 -> 43927 | B10: 233 | C10: 239 | D10: =C9-C10 -> 2 | E10: =D10*8.38 -> 16.76 | F10: 1507 | G10: =F10-F9 -> 4 | H10: 346758 | I10: =SUM(H10-H9) -> 296 | J10: =IF(G10>0,I10/G10,0) -> 74 | K10: 1884 | L10: =K10-K9 -> 0 | M10: 137884 | N10: =M10-M9 -> 2 | O10: =SUM(L10*$J$1) -> 0 | P10: 1737 | Q10: 147921 | R10: =Q10-Q9 -> 146 | S10: =SUM(P10-P9) -> 3 | T10: =SUM(S10*$T$2) -> 0 | U10: =SUM(G10+L10+S10) -> 7 | V10: =R10+N10+I10:I10 -> 444 | W10: =SUM(V10/U10) -> 63.428571 | X10: 2404 | Y10: =X10-X9 -> 0 | Z10: 135129.3 | AA10: =Z10-Z9 -> 0 | AB10: =SUM(Y10*$AB$2) -> 0 | AC10: 1824 | AD10: =AC10-AC9 -> 0 | AE10: 358857.5 | AF10: =AE10-AE9 -> 0 | AG10: =IF(AD10>0,AF10/AD10,0) -> 0 | AH10: =AF10+AA10 -> 0 | AI10: =SUM(AH10+V10) -> 444 | AJ10: =-tanks!AW11 -> 444 | AK10: =SUM(AJ10-AI10) -> 0 | AL10: =S10+L10+G10 -> 7 | AM10: =Y10+AD10 -> 0 | AN10: 65 | AO10: =(AN10/100)*3000 -> 1950 | AP10: 64 | AQ10: =(AP10/100)*3000 -> 1920 | AR10: 60 | AS10: =(AR10/100)*3000 -> 1800 | AT10: =SUM(AO10+AQ10+AS10) -> 5670 | AU10: =AT9-AT10+AV10 -> 60 | AX10: =IF(AV10>0,AW10,AX9) -> 0.7
A11: =ELEC!C9 -> 43928 | B11: 232 | C11: 238 | D11: =C10-C11 -> 1 | E11: =D11*8.38 -> 8.38 | F11: 1507 | G11: =F11-F10 -> 0 | H11: 346759 | I11: =SUM(H11-H10) -> 1 | J11: =IF(G11>0,I11/G11,0) -> 0 | K11: 1886 | L11: =K11-K10 -> 2 | M11: 138047 | N11: =M11-M10 -> 163 | O11: =SUM(L11*$J$1) -> 165.53968 | P11: 1737 | Q11: 147921 | R11: =Q11-Q10 -> 0 | S11: =SUM(P11-P10) -> 0 | T11: =SUM(S11*$T$2) -> 0 | U11: =SUM(G11+L11+S11) -> 2 | V11: =R11+N11+I11:I11 -> 164 | W11: =SUM(V11/U11) -> 82 | X11: 2404 | Y11: =X11-X10 -> 0 | Z11: 135129.3 | AA11: =Z11-Z10 -> 0 | AB11: =SUM(Y11*$AB$2) -> 0 | AC11: 1824 | AD11: =AC11-AC10 -> 0 | AE11: 358857.5 | AF11: =AE11-AE10 -> 0 | AG11: =IF(AD11>0,AF11/AD11,0) -> 0 | AH11: =AF11+AA11 -> 0 | AI11: =SUM(AH11+V11) -> 164 | AJ11: =-tanks!AW12 -> 164 | AK11: =SUM(AJ11-AI11) -> 0 | AL11: =S11+L11+G11 -> 2 | AM11: =Y11+AD11 -> 0 | AN11: =AN10 -> 65 | AO11: =(AN11/100)*3000 -> 1950 | AP11: =AP10 -> 64 | AQ11: =(AP11/100)*3000 -> 1920 | AR11: 59 | AS11: =(AR11/100)*3000 -> 1770 | AT11: =SUM(AO11+AQ11+AS11) -> 5640 | AU11: =AT10-AT11+AV11 -> 30 | AX11: =IF(AV11>0,AW11,AX10) -> 0.7
A12: =ELEC!C10 -> 43929 | B12: 229 | C12: 235 | D12: =C11-C12 -> 3 | E12: =D12*8.38 -> 25.14 | F12: 1507 | G12: =F12-F11 -> 0 | H12: 346759 | I12: =SUM(H12-H11) -> 0 | J12: =IF(G12>0,I12/G12,0) -> 0 | K12: 1888 | L12: =K12-K11 -> 2 | M12: 138172 | N12: =M12-M11 -> 125 | O12: =SUM(L12*$J$1) -> 165.53968 | P12: 1739 | Q12: 148101 | R12: =Q12-Q11 -> 180 | S12: =SUM(P12-P11) -> 2 | T12: =SUM(S12*$T$2) -> 0 | U12: =SUM(G12+L12+S12) -> 4 | V12: =R12+N12+I12:I12 -> 305 | W12: =SUM(V12/U12) -> 76.25 | X12: 2404 | Y12: =X12-X11 -> 0 | Z12: 135129.3 | AA12: =Z12-Z11 -> 0 | AB12: =SUM(Y12*$AB$2) -> 0 | AC12: 1824 | AD12: =AC12-AC11 -> 0 | AE12: 358857.5 | AF12: =AE12-AE11 -> 0 | AG12: =IF(AD12>0,AF12/AD12,0) -> 0 | AH12: =AF12+AA12 -> 0 | AI12: =SUM(AH12+V12) -> 305 | AJ12: =-tanks!AW13 -> 305 | AK12: =SUM(AJ12-AI12) -> 0 | AL12: =S12+L12+G12 -> 4 | AM12: =Y12+AD12 -> 0 | AN12: 64 | AO12: =(AN12/100)*3000 -> 1920 | AP12: 62 | AQ12: =(AP12/100)*3000 -> 1860 | AR12: 58 | AS12: =(AR12/100)*3000 -> 1740 | AT12: =SUM(AO12+AQ12+AS12) -> 5520 | AU12: =AT11-AT12+AV12 -> 120 | AX12: =IF(AV12>0,AW12,AX11) -> 0.7
A13: =ELEC!C11 -> 43930 | B13: 225 | C13: 231 | D13: =C12-C13 -> 4 | E13: =D13*8.38 -> 33.52 | F13: 1509 | G13: =F13-F12 -> 2 | H13: 346954 | I13: =SUM(H13-H12) -> 195 | J13: =IF(G13>0,I13/G13,0) -> 97.5 | K13: =K12 -> 1888 | L13: =K13-K12 -> 0 | M13: =M12 -> 138172 | N13: =M13-M12 -> 0 | O13: =SUM(L13*$J$1) -> 0 | P13: 1742 | Q13: 148290 | R13: =Q13-Q12 -> 189 | S13: =SUM(P13-P12) -> 3 | T13: =SUM(S13*$T$2) -> 0 | U13: =SUM(G13+L13+S13) -> 5 | V13: =R13+N13+I13:I13 -> 384 | W13: =SUM(V13/U13) -> 76.8 | X13: 2408 | Y13: =X13-X12 -> 4 | Z13: 135361 | AA13: =Z13-Z12 -> 231.7 | AB13: =SUM(Y13*$AB$2) -> 0 | AC13: =AC12 -> 1824 | AD13: =AC13-AC12 -> 0 | AE13: =AE12 -> 358857.5 | AF13: =AE13-AE12 -> 0 | AG13: =IF(AD13>0,AF13/AD13,0) -> 0 | AH13: =AF13+AA13 -> 231.7 | AI13: =SUM(AH13+V13) -> 615.7 | AJ13: =-tanks!AW14 -> 615.7 | AK13: =SUM(AJ13-AI13) -> 0 | AL13: =S13+L13+G13 -> 5 | AM13: =Y13+AD13 -> 4 | AN13: 80 | AO13: =(AN13/100)*3000 -> 2400 | AP13: 68 | AQ13: =(AP13/100)*3000 -> 2040 | AR13: 59 | AS13: =(AR13/100)*3000 -> 1770 | AT13: =SUM(AO13+AQ13+AS13) -> 6210 | AU13: =AT12-AT13+AV13 -> 310 | AV13: 1000 | AW13: 0.7 | AX13: =IF(AV13>0,AW13,AX12) -> 0.7
A14: =ELEC!C12 -> 43931 | B14: 221 | C14: 228 | D14: =C13-C14 -> 3 | E14: =D14*8.38 -> 25.14 | F14: 1511 | G14: =F14-F13 -> 2 | H14: 347085 | I14: =SUM(H14-H13) -> 131 | J14: =IF(G14>0,I14/G14,0) -> 65.5 | K14: 1892 | L14: =K14-K13 -> 4 | M14: 138467 | N14: =M14-M13 -> 295 | O14: =SUM(L14*$J$1) -> 331.07937 | P14: =P13 -> 1742 | Q14: =Q13 -> 148290 | R14: =Q14-Q13 -> 0 | S14: =SUM(P14-P13) -> 0 | T14: =SUM(S14*$T$2) -> 0 | U14: =SUM(G14+L14+S14) -> 6 | V14: =R14+N14+I14:I14 -> 426 | W14: =SUM(V14/U14) -> 71 | X14: =X13 -> 2408 | Y14: =X14-X13 -> 0 | Z14: =Z13 -> 135361 | AA14: =Z14-Z13 -> 0 | AB14: =SUM(Y14*$AB$2) -> 0 | AC14: =AC13 -> 1824 | AD14: =AC14-AC13 -> 0 | AE14: =AE13 -> 358857.5 | AF14: =AE14-AE13 -> 0 | AG14: =IF(AD14>0,AF14/AD14,0) -> 0 | AH14: =AF14+AA14 -> 0 | AI14: =SUM(AH14+V14) -> 426 | AJ14: =-tanks!AW15 -> 426 | AK14: =SUM(AJ14-AI14) -> 0 | AL14: =S14+L14+G14 -> 6 | AM14: =Y14+AD14 -> 0 | AN14: 79 | AO14: =(AN14/100)*3000 -> 2370 | AP14: 67 | AQ14: =(AP14/100)*3000 -> 2010 | AR14: 58 | AS14: =(AR14/100)*3000 -> 1740 | AT14: =SUM(AO14+AQ14+AS14) -> 6120 | AU14: =AT13-AT14+AV14 -> 90 | AX14: =IF(AV14>0,AW14,AX13) -> 0.7
A15: =ELEC!C13 -> 43932 | B15: 219 | C15: 225 | D15: =C14-C15 -> 3 | E15: =D15*8.38 -> 25.14 | F15: =F14 -> 1511 | G15: =F15-F14 -> 0 | H15: =H14 -> 347085 | I15: =SUM(H15-H14) -> 0 | J15: =IF(G15>0,I15/G15,0) -> 0 | K15: 1893 | L15: =K15-K14 -> 1 | M15: 138552 | N15: =M15-M14 -> 85 | O15: =SUM(L15*$J$1) -> 82.769841 | P15: 1743 | Q15: 148399 | R15: =Q15-Q14 -> 109 | S15: =SUM(P15-P14) -> 1 | T15: =SUM(S15*$T$2) -> 0 | U15: =SUM(G15+L15+S15) -> 2 | V15: =R15+N15+I15:I15 -> 194 | W15: =SUM(V15/U15) -> 97 | X15: =X14 -> 2408 | Y15: =X15-X14 -> 0 | Z15: =Z14 -> 135361 | AA15: =Z15-Z14 -> 0 | AB15: =SUM(Y15*$AB$2) -> 0 | AC15: =AC14 -> 1824 | AD15: =AC15-AC14 -> 0 | AE15: =AE14 -> 358857.5 | AF15: =AE15-AE14 -> 0 | AG15: =IF(AD15>0,AF15/AD15,0) -> 0 | AH15: =AF15+AA15 -> 0 | AI15: =SUM(AH15+V15) -> 194 | AJ15: =-tanks!AW16 -> 194 | AK15: =SUM(AJ15-AI15) -> 0 | AL15: =S15+L15+G15 -> 2 | AM15: =Y15+AD15 -> 0 | AN15: 79 | AO15: =(AN15/100)*3000 -> 2370 | AP15: 66 | AQ15: =(AP15/100)*3000 -> 1980 | AR15: 57 | AS15: =(AR15/100)*3000 -> 1710 | AT15: =SUM(AO15+AQ15+AS15) -> 6060 | AU15: =AT14-AT15+AV15 -> 60 | AX15: =IF(AV15>0,AW15,AX14) -> 0.7
A16: =ELEC!C14 -> 43933 | B16: 216 | C16: 223 | D16: =C15-C16 -> 2 | E16: =D16*8.38 -> 16.76 | F16: 1512 | G16: =F16-F15 -> 1 | H16: 347211 | I16: =SUM(H16-H15) -> 126 | J16: =IF(G16>0,I16/G16,0) -> 126 | K16: =K15 -> 1893 | L16: =K16-K15 -> 0 | M16: =M15 -> 138552 | N16: =M16-M15 -> 0 | O16: =SUM(L16*$J$1) -> 0 | P16: 1745 | Q16: 148581 | R16: =Q16-Q15 -> 182 | S16: =SUM(P16-P15) -> 2 | T16: =SUM(S16*$T$2) -> 0 | U16: =SUM(G16+L16+S16) -> 3 | V16: =R16+N16+I16:I16 -> 308 | W16: =SUM(V16/U16) -> 102.66667 | X16: =X15 -> 2408 | Y16: =X16-X15 -> 0 | Z16: =Z15 -> 135361 | AA16: =Z16-Z15 -> 0 | AB16: =SUM(Y16*$AB$2) -> 0 | AC16: =AC15 -> 1824 | AD16: =AC16-AC15 -> 0 | AE16: =AE15 -> 358857.5 | AF16: =AE16-AE15 -> 0 | AG16: =IF(AD16>0,AF16/AD16,0) -> 0 | AH16: =AF16+AA16 -> 0 | AI16: =SUM(AH16+V16) -> 308 | AJ16: =-tanks!AW17 -> 308 | AK16: =SUM(AJ16-AI16) -> 0 | AL16: =S16+L16+G16 -> 3 | AM16: =Y16+AD16 -> 0 | AN16: 78 | AO16: =(AN16/100)*3000 -> 2340 | AP16: 65 | AQ16: =(AP16/100)*3000 -> 1950 | AR16: 55 | AS16: =(AR16/100)*3000 -> 1650 | AT16: =SUM(AO16+AQ16+AS16) -> 5940 | AU16: =AT15-AT16+AV16 -> 120 | AX16: =IF(AV16>0,AW16,AX15) -> 0.7
A17: =ELEC!C15 -> 43934 | B17: 212 | C17: 219 | D17: =C16-C17 -> 4 | E17: =D17*8.38 -> 33.52 | F17: 1515 | G17: =F17-F16 -> 3 | H17: 347403 | I17: =SUM(H17-H16) -> 192 | J17: =IF(G17>0,I17/G17,0) -> 64 | K17: 1896 | L17: =K17-K16 -> 3 | M17: 138771 | N17: =M17-M16 -> 219 | O17: =SUM(L17*$J$1) -> 248.30952 | P17: =P16 -> 1745 | Q17: =Q16 -> 148581 | R17: =Q17-Q16 -> 0 | S17: =SUM(P17-P16) -> 0 | T17: =SUM(S17*$T$2) -> 0 | U17: =SUM(G17+L17+S17) -> 6 | V17: =R17+N17+I17:I17 -> 411 | X17: =X16 -> 2408 | Y17: =X17-X16 -> 0 | Z17: =Z16 -> 135361 | AA17: =Z17-Z16 -> 0 | AB17: =SUM(Y17*$AB$2) -> 0 | AC17: =AC16 -> 1824 | AD17: =AC17-AC16 -> 0 | AE17: =AE16 -> 358857.5 | AF17: =AE17-AE16 -> 0 | AG17: =IF(AD17>0,AF17/AD17,0) -> 0 | AH17: =AF17+AA17 -> 0 | AI17: =SUM(AH17+V17) -> 411 | AJ17: =-tanks!AW18 -> 411 | AK17: =SUM(AJ17-AI17) -> 0 | AL17: =S17+L17+G17 -> 6 | AM17: =Y17+AD17 -> 0 | AN17: 76 | AO17: =(AN17/100)*3000 -> 2280 | AP17: =AP16 -> 65 | AQ17: =(AP17/100)*3000 -> 1950 | AR17: =AR16 -> 55 | AS17: =(AR17/100)*3000 -> 1650 | AT17: =SUM(AO17+AQ17+AS17) -> 5880 | AU17: =AT16-AT17+AV17 -> 60 | AX17: =IF(AV17>0,AW17,AX16) -> 0.7
A18: =ELEC!C16 -> 43935 | B18: 210 | C18: 216.4 | D18: =C17-C18 -> 2.6 | E18: =D18*8.38 -> 21.788 | F18: 1517 | G18: =F18-F17 -> 2 | H18: 347551 | I18: =SUM(H18-H17) -> 148 | J18: =IF(G18>0,I18/G18,0) -> 74 | K18: 1897 | L18: =K18-K17 -> 1 | M18: 138858 | N18: =M18-M17 -> 87 | O18: =SUM(L18*$J$1) -> 82.769841 | P18: 1745 | Q18: 148581 | R18: =Q18-Q17 -> 0 | S18: =SUM(P18-P17) -> 0 | T18: =SUM(S18*$T$2) -> 0 | U18: =SUM(G18+L18+S18) -> 3 | V18: =R18+N18+I18:I18 -> 235 | X18: 2408 | Y18: =X18-X17 -> 0 | Z18: 135361 | AA18: =Z18-Z17 -> 0 | AB18: =SUM(Y18*$AB$2) -> 0 | AC18: 1824 | AD18: =AC18-AC17 -> 0 | AE18: 358857.5 | AF18: =AE18-AE17 -> 0 | AG18: =IF(AD18>0,AF18/AD18,0) -> 0 | AH18: =AF18+AA18 -> 0 | AI18: =SUM(AH18+V18) -> 235 | AJ18: =-tanks!AW19 -> 235 | AK18: =SUM(AJ18-AI18) -> 0 | AL18: =S18+L18+G18 -> 3 | AM18: =Y18+AD18 -> 0 | AN18: 74 | AO18: =(AN18/100)*3000 -> 2220 | AP18: 65 | AQ18: =(AP18/100)*3000 -> 1950 | AR18: 55 | AS18: =(AR18/100)*3000 -> 1650 | AT18: =SUM(AO18+AQ18+AS18) -> 5820 | AU18: =AT17-AT18+AV18 -> 60 | AX18: =IF(AV18>0,AW18,AX17) -> 0.7
A19: =ELEC!C17 -> 43936 | B19: 243 | C19: 249 | D19: =C18-C19 -> -32.6 | E19: =D19*8.38 -> -273.188 | F19: 1518 | G19: =F19-F18 -> 1 | H19: 347688 | I19: =SUM(H19-H18) -> 137 | J19: =IF(G19>0,I19/G19,0) -> 137 | K19: 1899 | L19: =K19-K18 -> 2 | M19: 139036 | N19: =M19-M18 -> 178 | O19: =SUM(L19*$J$1) -> 165.53968 | P19: 1745 | Q19: 148581 | R19: =Q19-Q18 -> 0 | S19: =SUM(P19-P18) -> 0 | T19: =SUM(S19*$T$2) -> 0 | U19: =SUM(G19+L19+S19) -> 3 | V19: =R19+N19+I19:I19 -> 315 | X19: 2412 | Y19: =X19-X18 -> 4 | Z19: 135583 | AA19: =Z19-Z18 -> 222 | AB19: =SUM(Y19*$AB$2) -> 0 | AC19: 1824 | AD19: =AC19-AC18 -> 0 | AE19: 358857.5 | AF19: =AE19-AE18 -> 0 | AG19: =IF(AD19>0,AF19/AD19,0) -> 0 | AH19: =AF19+AA19 -> 222 | AI19: =SUM(AH19+V19) -> 537 | AJ19: =-tanks!AW20 -> 537 | AK19: =SUM(AJ19-AI19) -> 0 | AL19: =S19+L20+G19 -> 3 | AM19: =Y19+AD19 -> 4 | AN19: 72 | AO19: =(AN19/100)*3000 -> 2160 | AP19: 64 | AQ19: =(AP19/100)*3000 -> 1920 | AR19: 55 | AS19: =(AR19/100)*3000 -> 1650 | AT19: =SUM(AO19+AQ19+AS19) -> 5730 | AU19: =AT18-AT19+AV19 -> 90 | AX19: =IF(AV19>0,AW19,AX18) -> 0.7
A20: =ELEC!C18 -> 43937 | B20: 241 | C20: 247 | D20: =C19-C20 -> 2 | E20: =D20*8.38 -> 16.76 | F20: 1518 | G20: =F20-F19 -> 0 | H20: =H19 -> 347688 | I20: =SUM(H20-H19) -> 0 | J20: =IF(G20>0,I20/G20,0) -> 0 | K20: 1901 | L20: =K20-K19 -> 2 | M20: 139183 | N20: =M20-M19 -> 147 | O20: =SUM(L20*$J$1) -> 165.53968 | P20: 1748 | Q20: 148774 | R20: =Q20-Q19 -> 193 | S20: =SUM(P20-P19) -> 3 | T20: =SUM(S20*$T$2) -> 0 | U20: =SUM(G20+L20+S20) -> 5 | V20: =R20+N20+I20:I20 -> 340 | X20: =X19 -> 2412 | Y20: =X20-X19 -> 0 | Z20: =Z19 -> 135583 | AA20: =Z20-Z19 -> 0 | AB20: =SUM(Y20*$AB$2) -> 0 | AC20: =AC19 -> 1824 | AD20: =AC20-AC19 -> 0 | AE20: =AE19 -> 358857.5 | AF20: =AE20-AE19 -> 0 | AG20: =IF(AD20>0,AF20/AD20,0) -> 0 | AH20: =AF20+AA20 -> 0 | AI20: =SUM(AH20+V20) -> 340 | AJ20: =-tanks!AW21 -> 340 | AK20: =SUM(AJ20-AI20) -> 0 | AL20: =S20+L21+G20 -> 3 | AM20: =Y20+AD20 -> 0 | AN20: 81 | AO20: =(AN20/100)*3000 -> 2430 | AP20: 65 | AQ20: =(AP20/100)*3000 -> 1950 | AR20: 71 | AS20: =(AR20/100)*3000 -> 2130 | AT20: =SUM(AO20+AQ20+AS20) -> 6510 | AU20: =AT19-AT20+AV20 -> 220 | AV20: 1000 | AW20: 0.7 | AX20: =IF(AV20>0,AW20,AX19) -> 0.7
A21: =ELEC!C19 -> 43938 | B21: 238 | C21: 244 | D21: =C20-C21 -> 3 | E21: =D21*8.38 -> 25.14 | F21: 1520 | G21: =F21-F20 -> 2 | H21: 347826 | I21: =SUM(H21-H20) -> 138 | J21: =IF(G21>0,I21/G21,0) -> 69 | K21: =K20 -> 1901 | L21: =K21-K20 -> 0 | M21: =M20 -> 139183 | N21: =M21-M20 -> 0 | O21: =SUM(L21*$J$1) -> 0 | P21: 1749 | Q21: 148883 | R21: =Q21-Q20 -> 109 | S21: =SUM(P21-P20) -> 1 | T21: =SUM(S21*$T$2) -> 0 | U21: =SUM(G21+L21+S21) -> 3 | V21: =R21+N21+I21:I21 -> 247 | X21: =X20 -> 2412 | Y21: =X21-X20 -> 0 | Z21: =Z20 -> 135583 | AA21: =Z21-Z20 -> 0 | AB21: =SUM(Y21*$AB$2) -> 0 | AC21: =AC20 -> 1824 | AD21: =AC21-AC20 -> 0 | AE21: =AE20 -> 358857.5 | AF21: =AE21-AE20 -> 0 | AG21: =IF(AD21>0,AF21/AD21,0) -> 0 | AH21: =AF21+AA21 -> 0 | AI21: =SUM(AH21+V21) -> 247 | AJ21: =-tanks!AW22 -> 247 | AK21: =SUM(AJ21-AI21) -> 0 | AL21: =S21+L21+G21 -> 3 | AM21: =Y21+AD21 -> 0 | AN21: 80 | AO21: =(AN21/100)*3000 -> 2400 | AP21: 65 | AQ21: =(AP21/100)*3000 -> 1950 | AR21: 70 | AS21: =(AR21/100)*3000 -> 2100 | AT21: =SUM(AO21+AQ21+AS21) -> 6450 | AU21: =AT20-AT21+AV21 -> 60 | AX21: =IF(AV21>0,AW21,AX20) -> 0.7
A22: =ELEC!C20 -> 43939 | B22: 235 | C22: 241 | D22: =C21-C22 -> 3 | E22: =D22*8.38 -> 25.14 | F22: 1522 | G22: =F22-F21 -> 2 | H22: 347921 | I22: =SUM(H22-H21) -> 95 | J22: =IF(G22>0,I22/G22,0) -> 47.5 | K22: 1904 | L22: =K22-K21 -> 3 | M22: 139383 | N22: =M22-M21 -> 200 | O22: =SUM(L22*$J$1) -> 248.30952 | P22: 1749 | Q22: =Q21 -> 148883 | R22: =Q22-Q21 -> 0 | S22: =SUM(P22-P21) -> 0 | T22: =SUM(S22*$T$2) -> 0 | U22: =SUM(G22+L22+S22) -> 5 | V22: =R22+N22+I22:I22 -> 295 | X22: =X21 -> 2412 | Y22: =X22-X21 -> 0 | Z22: =Z21 -> 135583 | AA22: =Z22-Z21 -> 0 | AB22: =SUM(Y22*$AB$2) -> 0 | AC22: =AC21 -> 1824 | AD22: =AC22-AC21 -> 0 | AE22: =AE21 -> 358857.5 | AF22: =AE22-AE21 -> 0 | AG22: =IF(AD22>0,AF22/AD22,0) -> 0 | AH22: =AF22+AA22 -> 0 | AI22: =SUM(AH22+V22) -> 295 | AJ22: =-tanks!AW23 -> 295 | AK22: =SUM(AJ22-AI22) -> 0 | AL22: =S22+L22+G22 -> 5 | AM22: =Y22+AD22 -> 0 | AN22: 78 | AO22: =(AN22/100)*3000 -> 2340 | AP22: 64 | AQ22: =(AP22/100)*3000 -> 1920 | AR22: 69 | AS22: =(AR22/100)*3000 -> 2070 | AT22: =SUM(AO22+AQ22+AS22) -> 6330 | AU22: =AT21-AT22+AV22 -> 120 | AX22: =IF(AV22>0,AW22,AX21) -> 0.7
A23: =ELEC!C21 -> 43940 | B23: 233 | C23: 239 | D23: =C22-C23 -> 2 | E23: =D23*8.38 -> 16.76 | F23: 1523 | G23: =F23-F22 -> 1 | H23: 348083 | I23: =SUM(H23-H22) -> 162 | J23: =IF(G23>0,I23/G23,0) -> 162 | K23: 1905 | L23: =K23-K22 -> 1 | M23: 139447 | N23: =M23-M22 -> 64 | O23: =SUM(L23*$J$1) -> 82.769841 | P23: 1751 | Q23: 148980 | R23: =Q23-Q22 -> 97 | S23: =SUM(P23-P22) -> 2 | T23: =SUM(S23*$T$2) -> 0 | U23: =SUM(G23+L23+S23) -> 4 | V23: =R23+N23+I23:I23 -> 323 | X23: =X22 -> 2412 | Y23: =X23-X22 -> 0 | Z23: =Z22 -> 135583 | AA23: =Z23-Z22 -> 0 | AB23: =SUM(Y23*$AB$2) -> 0 | AC23: =AC22 -> 1824 | AD23: =AC23-AC22 -> 0 | AE23: =AE22 -> 358857.5 | AF23: =AE23-AE22 -> 0 | AG23: =IF(AD23>0,AF23/AD23,0) -> 0 | AH23: =AF23+AA23 -> 0 | AI23: =SUM(AH23+V23) -> 323 | AJ23: =-tanks!AW24 -> 323 | AK23: =SUM(AJ23-AI23) -> 0 | AL23: =S23+L23+G23 -> 4 | AM23: =Y23+AD23 -> 0 | AN23: 77 | AO23: =(AN23/100)*3000 -> 2310 | AP23: 63 | AQ23: =(AP23/100)*3000 -> 1890 | AR23: 68 | AS23: =(AR23/100)*3000 -> 2040 | AT23: =SUM(AO23+AQ23+AS23) -> 6240 | AU23: =AT22-AT23+AV23 -> 90 | AX23: =IF(AV23>0,AW23,AX22) -> 0.7
A24: =ELEC!C22 -> 43941 | B24: 231 | C24: 238 | D24: =C23-C24 -> 1 | E24: =D24*8.38 -> 8.38 | F24: 1526 | G24: =F24-F23 -> 3 | H24: 348336 | I24: =SUM(H24-H23) -> 253 | J24: =IF(G24>0,I24/G24,0) -> 84.333333 | K24: 1905 | L24: =K24-K23 -> 0 | M24: =M23 -> 139447 | N24: =M24-M23 -> 0 | O24: =SUM(L24*$J$1) -> 0 | P24: 1752 | Q24: 149093 | R24: =Q24-Q23 -> 113 | S24: =SUM(P24-P23) -> 1 | T24: =SUM(S24*$T$2) -> 0 | U24: =SUM(G24+L24+S24) -> 4 | V24: =R24+N24+I24:I24 -> 366 | X24: 2412 | Y24: =X24-X23 -> 0 | Z24: =Z23 -> 135583 | AA24: =Z24-Z23 -> 0 | AB24: =SUM(Y24*$AB$2) -> 0 | AC24: =AC23 -> 1824 | AD24: =AC24-AC23 -> 0 | AE24: =AE23 -> 358857.5 | AF24: =AE24-AE23 -> 0 | AG24: =IF(AD24>0,AF24/AD24,0) -> 0 | AH24: =AF24+AA24 -> 0 | AI24: =SUM(AH24+V24) -> 366 | AJ24: =-tanks!AW25 -> 366 | AK24: =SUM(AJ24-AI24) -> 0 | AL24: =S24+L24+G24 -> 4 | AM24: =Y24+AD24 -> 0 | AN24: 75 | AO24: =(AN24/100)*3000 -> 2250 | AP24: =AP23 -> 63 | AQ24: =(AP24/100)*3000 -> 1890 | AR24: =AR23 -> 68 | AS24: =(AR24/100)*3000 -> 2040 | AT24: =SUM(AO24+AQ24+AS24) -> 6180 | AU24: =AT23-AT24+AV24 -> 60 | AX24: =IF(AV24>0,AW24,AX23) -> 0.7
A25: =ELEC!C23 -> 43942 | B25: 229 | C25: 235 | D25: =C24-C25 -> 3 | E25: =D25*8.38 -> 25.14 | F25: 1527 | G25: =F25-F24 -> 1 | H25: 348382 | I25: =SUM(H25-H24) -> 46 | J25: =IF(G25>0,I25/G25,0) -> 46 | K25: 1907 | L25: =K25-K24 -> 2 | M25: 139626 | N25: =M25-M24 -> 179 | O25: =SUM(L25*$J$1) -> 165.53968 | P25: =P24 -> 1752 | Q25: 149093 | R25: =Q25-Q24 -> 0 | S25: =SUM(P25-P24) -> 0 | T25: =SUM(S25*$T$2) -> 0 | U25: =SUM(G25+L25+S25) -> 3 | V25: =R25+N25+I25:I25 -> 225 | X25: 2412 | Y25: =X25-X24 -> 0 | Z25: 135583 | AA25: =Z25-Z24 -> 0 | AB25: =SUM(Y25*$AB$2) -> 0 | AC25: 1824 | AD25: =AC25-AC24 -> 0 | AE25: =AE24 -> 358857.5 | AF25: =AE25-AE24 -> 0 | AG25: =IF(AD25>0,AF25/AD25,0) -> 0 | AH25: =AF25+AA25 -> 0 | AI25: =SUM(AH25+V25) -> 225 | AJ25: =-tanks!AW26 -> 225 | AK25: =SUM(AJ25-AI25) -> 0 | AL25: =S25+L25+G25 -> 3 | AM25: =Y25+AD25 -> 0 | AN25: 74 | AO25: =(AN25/100)*3000 -> 2220 | AP25: 63 | AQ25: =(AP25/100)*3000 -> 1890 | AR25: 68 | AS25: =(AR25/100)*3000 -> 2040 | AT25: =SUM(AO25+AQ25+AS25) -> 6150 | AU25: =AT24-AT25+AV25 -> 30 | AX25: =IF(AV25>0,AW25,AX24) -> 0.7
A26: =ELEC!C24 -> 43943 | B26: 226 | C26: 232 | D26: =C25-C26 -> 3 | E26: =D26*8.38 -> 25.14 | F26: 1527 | G26: =F26-F25 -> 0 | H26: 348382 | I26: =SUM(H26-H25) -> 0 | J26: =IF(G26>0,I26/G26,0) -> 0 | K26: 1909 | L26: =K26-K25 -> 2 | M26: 139745 | N26: =M26-M25 -> 119 | O26: =SUM(L26*$J$1) -> 165.53968 | P26: 1755 | Q26: 149319 | R26: =Q26-Q25 -> 226 | S26: =SUM(P26-P25) -> 3 | T26: =SUM(S26*$T$2) -> 0 | U26: =SUM(G26+L26+S26) -> 5 | V26: =R26+N26+I26:I26 -> 345 | X26: 2412 | Y26: =X26-X25 -> 0 | Z26: 135583 | AA26: =Z26-Z25 -> 0 | AB26: =SUM(Y26*$AB$2) -> 0 | AC26: 1824 | AD26: =AC26-AC25 -> 0 | AE26: 358857.5 | AF26: =AE26-AE25 -> 0 | AG26: =IF(AD26>0,AF26/AD26,0) -> 0 | AH26: =AF26+AA26 -> 0 | AI26: =SUM(AH26+V26) -> 345 | AJ26: =-tanks!AW27 -> 345 | AK26: =SUM(AJ26-AI26) -> 0 | AL26: =S26+L26+G26 -> 5 | AM26: =Y26+AD26 -> 0 | AN26: 71 | AO26: =(AN26/100)*3000 -> 2130 | AP26: 62 | AQ26: =(AP26/100)*3000 -> 1860 | AR26: 67 | AS26: =(AR26/100)*3000 -> 2010 | AT26: =SUM(AO26+AQ26+AS26) -> 6000 | AU26: =AT25-AT26+AV26 -> 150 | AX26: =IF(AV26>0,AW26,AX25) -> 0.7
A27: =ELEC!C25 -> 43944 | B27: 221 | C27: 227 | D27: =C26-C27 -> 5 | E27: =D27*8.38 -> 41.9 | F27: 1529 | G27: =F27-F26 -> 2 | H27: 348527 | I27: =SUM(H27-H26) -> 145 | J27: =IF(G27>0,I27/G27,0) -> 72.5 | K27: =K26 -> 1909 | L27: =K27-K26 -> 0 | M27: =M26 -> 139745 | N27: =M27-M26 -> 0 | O27: =SUM(L27*$J$1) -> 0 | P27: 1756 | Q27: 149373 | R27: =Q27-Q26 -> 54 | S27: =SUM(P27-P26) -> 1 | T27: =SUM(S27*$T$2) -> 0 | U27: =SUM(G27+L27+S27) -> 3 | V27: =R27+N27+I27:I27 -> 199 | X27: 2417 | Y27: =X27-X26 -> 5 | Z27: 135840 | AA27: =Z27-Z26 -> 257 | AB27: =SUM(Y27*$AB$2) -> 0 | AC27: =AC26 -> 1824 | AD27: =AC27-AC26 -> 0 | AE27: =AE26 -> 358857.5 | AF27: =AE27-AE26 -> 0 | AG27: =IF(AD27>0,AF27/AD27,0) -> 0 | AH27: =AF27+AA27 -> 257 | AI27: =SUM(AH27+V27) -> 456 | AJ27: =-tanks!AW28 -> 456 | AK27: =SUM(AJ27-AI27) -> 0 | AL27: =S27+L27+G27 -> 3 | AM27: =Y27+AD27 -> 5 | AN27: 68 | AO27: =(AN27/100)*3000 -> 2040 | AP27: 61 | AQ27: =(AP27/100)*3000 -> 1830 | AR27: 65 | AS27: =(AR27/100)*3000 -> 1950 | AT27: =SUM(AO27+AQ27+AS27) -> 5820 | AU27: =AT26-AT27+AV27 -> 180 | AX27: =IF(AV27>0,AW27,AX26) -> 0.7
A28: =ELEC!C26 -> 43945 | B28: 219 | C28: 225 | D28: =C27-C28 -> 2 | E28: =D28*8.38 -> 16.76 | F28: 1530 | G28: =F28-F27 -> 1 | H28: 348646 | I28: =SUM(H28-H27) -> 119 | J28: =IF(G28>0,I28/G28,0) -> 119 | K28: 1911 | L28: =K28-K27 -> 2 | M28: 139945 | N28: =M28-M27 -> 200 | O28: =SUM(L28*$J$1) -> 165.53968 | P28: =P27 -> 1756 | Q28: =Q27 -> 149373 | R28: =Q28-Q27 -> 0 | S28: =SUM(P28-P27) -> 0 | T28: =SUM(S28*$T$2) -> 0 | U28: =SUM(G28+L28+S28) -> 3 | V28: =R28+N28+I28:I28 -> 319 | X28: =X27 -> 2417 | Y28: =X28-X27 -> 0 | Z28: =Z27 -> 135840 | AA28: =Z28-Z27 -> 0 | AB28: =SUM(Y28*$AB$2) -> 0 | AC28: =AC27 -> 1824 | AD28: =AC28-AC27 -> 0 | AE28: =AE27 -> 358857.5 | AF28: =AE28-AE27 -> 0 | AG28: =IF(AD28>0,AF28/AD28,0) -> 0 | AH28: =AF28+AA28 -> 0 | AI28: =SUM(AH28+V28) -> 319 | AJ28: =-tanks!AW29 -> 319 | AK28: =SUM(AJ28-AI28) -> 0 | AL28: =S28+L28+G28 -> 3 | AM28: =Y28+AD28 -> 0 | AN28: 66 | AO28: =(AN28/100)*3000 -> 1980 | AP28: 60 | AQ28: =(AP28/100)*3000 -> 1800 | AR28: =AR27 -> 65 | AS28: =(AR28/100)*3000 -> 1950 | AT28: =SUM(AO28+AQ28+AS28) -> 5730 | AU28: =AT27-AT28+AV28 -> 90 | AX28: =IF(AV28>0,AW28,AX27) -> 0.7
A29: =ELEC!C27 -> 43946 | B29: 216 | C29: 220.5 | D29: =C28-C29 -> 4.5 | E29: =D29*8.38 -> 37.71 | F29: =F28 -> 1530 | G29: =F29-F28 -> 0 | H29: =H28 -> 348646 | I29: =SUM(H29-H28) -> 0 | J29: =IF(G29>0,I29/G29,0) -> 0 | K29: 1913 | L29: =K29-K28 -> 2 | M29: 140091 | N29: =M29-M28 -> 146 | O29: =SUM(L29*$J$1) -> 165.53968 | P29: 1758 | Q29: 149564 | R29: =Q29-Q28 -> 191 | S29: =SUM(P29-P28) -> 2 | T29: =SUM(S29*$T$2) -> 0 | U29: =SUM(G29+L29+S29) -> 4 | V29: =R29+N29+I29:I29 -> 337 | X29: =X28 -> 2417 | Y29: =X29-X28 -> 0 | Z29: =Z28 -> 135840 | AA29: =Z29-Z28 -> 0 | AB29: =SUM(Y29*$AB$2) -> 0 | AC29: =AC28 -> 1824 | AD29: =AC29-AC28 -> 0 | AE29: =AE28 -> 358857.5 | AF29: =AE29-AE28 -> 0 | AG29: =IF(AD29>0,AF29/AD29,0) -> 0 | AH29: =AF29+AA29 -> 0 | AI29: =SUM(AH29+V29) -> 337 | AJ29: =-tanks!AW30 -> 337 | AK29: =SUM(AJ29-AI29) -> 0 | AL29: =S29+L29+G29 -> 4 | AM29: =Y29+AD29 -> 0 | AN29: 65 | AO29: =(AN29/100)*3000 -> 1950 | AP29: =AP28 -> 60 | AQ29: =(AP29/100)*3000 -> 1800 | AR29: =AR28 -> 65 | AS29: =(AR29/100)*3000 -> 1950 | AT29: =SUM(AO29+AQ29+AS29) -> 5700 | AU29: =AT28-AT29+AV29 -> 30 | AX29: =IF(AV29>0,AW29,AX28) -> 0.7
A30: =ELEC!C28 -> 43947 | B30: 213 | C30: 219 | D30: =C29-C30 -> 1.5 | E30: =D30*8.38 -> 12.57 | F30: 1532 | G30: =F30-F29 -> 2 | H30: 348813 | I30: =SUM(H30-H29) -> 167 | J30: =IF(G30>0,I30/G30,0) -> 83.5 | K30: =K29 -> 1913 | L30: =K30-K29 -> 0 | M30: =M29 -> 140091 | N30: =M30-M29 -> 0 | O30: =SUM(L30*$J$1) -> 0 | P30: 1760 | Q30: 149674 | R30: =Q30-Q29 -> 110 | S30: =SUM(P30-P29) -> 2 | T30: =SUM(S30*$T$2) -> 0 | U30: =SUM(G30+L30+S30) -> 4 | V30: =R30+N30+I30:I30 -> 277 | X30: =X29 -> 2417 | Y30: =X30-X29 -> 0 | Z30: =Z29 -> 135840 | AA30: =Z30-Z29 -> 0 | AB30: =SUM(Y30*$AB$2) -> 0 | AC30: =AC29 -> 1824 | AD30: =AC30-AC29 -> 0 | AE30: =AE29 -> 358857.5 | AF30: =AE30-AE29 -> 0 | AG30: =IF(AD30>0,AF30/AD30,0) -> 0 | AH30: =AF30+AA30 -> 0 | AI30: =SUM(AH30+V30) -> 277 | AJ30: =-tanks!AW31 -> 277 | AK30: =SUM(AJ30-AI30) -> 0 | AL30: =S30+L30+G30 -> 4 | AM30: =Y30+AD30 -> 0 | AN30: 64 | AO30: =(AN30/100)*3000 -> 1920 | AP30: =AP29 -> 60 | AQ30: =(AP30/100)*3000 -> 1800 | AR30: =AR29 -> 65 | AS30: =(AR30/100)*3000 -> 1950 | AT30: =SUM(AO30+AQ30+AS30) -> 5670 | AU30: =AT29-AT30+AV30 -> 30 | AX30: =IF(AV30>0,AW30,AX29) -> 0.7
A31: =ELEC!C29 -> 43948 | B31: 209 | C31: 215 | D31: =C30-C31 -> 4 | E31: =D31*8.38 -> 33.52 | F31: 1534 | G31: =F31-F30 -> 2 | H31: 348910 | I31: =SUM(H31-H30) -> 97 | J31: =IF(G31>0,I31/G31,0) -> 48.5 | K31: 1916 | L31: =K31-K30 -> 3 | M31: 140316 | N31: =M31-M30 -> 225 | O31: =SUM(L31*$J$1) -> 248.30952 | P31: 1760 | Q31: 149674 | R31: =Q31-Q30 -> 0 | S31: =SUM(P31-P30) -> 0 | T31: =SUM(S31*$T$2) -> 0 | U31: =SUM(G31+L31+S31) -> 5 | V31: =R31+N31+I31:I31 -> 322 | X31: 2417 | Y31: =X31-X30 -> 0 | Z31: 135840 | AA31: =Z31-Z30 -> 0 | AB31: =SUM(Y31*$AB$2) -> 0 | AC31: 1824 | AD31: =AC31-AC30 -> 0 | AE31: 358857.5 | AF31: =AE31-AE30 -> 0 | AG31: =IF(AD31>0,AF31/AD31,0) -> 0 | AH31: =AF31+AA31 -> 0 | AI31: =SUM(AH31+V31) -> 322 | AJ31: =-tanks!AW32 -> 322 | AK31: =SUM(AJ31-AI31) -> 0 | AL31: =S31+L31+G31 -> 5 | AM31: =Y31+AD31 -> 0 | AN31: 64 | AO31: =(AN31/100)*3000 -> 1920 | AP31: 60 | AQ31: =(AP31/100)*3000 -> 1800 | AR31: 63 | AS31: =(AR31/100)*3000 -> 1890 | AT31: =SUM(AO31+AQ31+AS31) -> 5610 | AU31: =AT30-AT31+AV31 -> 60 | AX31: =IF(AV31>0,AW31,AX30) -> 0.7
A32: =ELEC!C30 -> 43949 | B32: 207 | C32: 213 | D32: =C31-C32 -> 2 | E32: =D32*8.38 -> 16.76 | F32: 1534 | G32: =F32-F31 -> 0 | H32: 348925 | I32: =SUM(H32-H31) -> 15 | J32: =IF(G32>0,I32/G32,0) -> 0 | K32: 1917 | L32: =K32-K31 -> 1 | M32: 140390 | N32: =M32-M31 -> 74 | O32: =SUM(L32*$J$1) -> 82.769841 | P32: 1762 | Q32: 149815 | R32: =Q32-Q31 -> 141 | S32: =SUM(P32-P31) -> 2 | T32: =SUM(S32*$T$2) -> 0 | U32: =SUM(G32+L32+S32) -> 3 | V32: =R32+N32+I32:I32 -> 230 | X32: 2417 | Y32: =X32-X31 -> 0 | Z32: 135840 | AA32: =Z32-Z31 -> 0 | AB32: =SUM(Y32*$AB$2) -> 0 | AC32: 1824 | AD32: =AC32-AC31 -> 0 | AE32: 358857.5 | AF32: =AE32-AE31 -> 0 | AG32: =IF(AD32>0,AF32/AD32,0) -> 0 | AH32: =AF32+AA32 -> 0 | AI32: =SUM(AH32+V32) -> 230 | AJ32: =-tanks!AW33 -> 230 | AK32: =SUM(AJ32-AI32) -> 0 | AL32: =S32+L32+G32 -> 3 | AM32: =Y32+AD32 -> 0 | AN32: 63 | AO32: =(AN32/100)*3000 -> 1890 | AP32: 60 | AQ32: =(AP32/100)*3000 -> 1800 | AR32: 62 | AS32: =(AR32/100)*3000 -> 1860 | AT32: =SUM(AO32+AQ32+AS32) -> 5550 | AU32: =AT31-AT32+AV32 -> 60 | AX32: =IF(AV32>0,AW32,AX31) -> 0.7
A33: =ELEC!C31 -> 43950 | B33: 248 | C33: 254 | D33: =C32-C33 -> -41 | E33: =D33*8.38 -> -343.58 | F33: 1536 | G33: =F33-F32 -> 2 | H33: 349090 | I33: =SUM(H33-H32) -> 165 | J33: =IF(G33>0,I33/G33,0) -> 82.5 | K33: 1917 | L33: =K33-K32 -> 0 | M33: 140390 | N33: =M33-M32 -> 0 | O33: =SUM(L33*$J$1) -> 0 | P33: 1763 | Q33: 149940 | R33: =Q33-Q32 -> 125 | S33: =SUM(P33-P32) -> 1 | T33: =SUM(S33*$T$2) -> 0 | U33: =SUM(G33+L33+S33) -> 3 | V33: =R33+N33+I33:I33 -> 290 | X33: 2417 | Y33: =X33-X32 -> 0 | Z33: 135845.1 | AA33: =Z33-Z32 -> 5.1 | AB33: =SUM(Y33*$AB$2) -> 0 | AC33: 1824 | AD33: =AC33-AC32 -> 0 | AE33: 358865.2 | AF33: =AE33-AE32 -> 7.7 | AG33: =IF(AD33>0,AF33/AD33,0) -> 0 | AH33: =AF33+AA33 -> 12.8 | AI33: =SUM(AH33+V33) -> 302.8 | AJ33: =-tanks!AW34 -> 302.8 | AK33: =SUM(AJ33-AI33) -> 0 | AL33: =S33+L33+G33 -> 3 | AM33: =Y33+AD33 -> 0 | AN33: 61 | AO33: =(AN33/100)*3000 -> 1830 | AP33: 59 | AQ33: =(AP33/100)*3000 -> 1770 | AR33: 60 | AS33: =(AR33/100)*3000 -> 1800 | AT33: =SUM(AO33+AQ33+AS33) -> 5400 | AU33: =AT32-AT33+AV33 -> 150 | AX33: =IF(AV33>0,AW33,AX32) -> 0.7
A34: =ELEC!C32 -> 43951 | B34: 245.5 | C34: 251 | D34: =C33-C34 -> 3 | E34: =D34*8.38 -> 25.14 | F34: 1537 | G34: =F34-F33 -> 1 | H34: 349198 | I34: =SUM(H34-H33) -> 108 | J34: =IF(G34>0,I34/G34,0) -> 108 | K34: 1919 | L34: =K34-K33 -> 2 | M34: 140563 | N34: =M34-M33 -> 173 | O34: =SUM(L34*$J$1) -> 165.53968 | P34: =P33 -> 1763 | Q34: =Q33 -> 149940 | R34: =Q34-Q33 -> 0 | S34: =SUM(P34-P33) -> 0 | T34: =SUM(S34*$T$2) -> 0 | U34: =SUM(G34+L34+S34) -> 3 | V34: =R34+N34+I34:I34 -> 281 | X34: =X33 -> 2417 | Y34: =X34-X33 -> 0 | Z34: =Z33 -> 135845.1 | AA34: =Z34-Z33 -> 0 | AB34: =SUM(Y34*$AB$2) -> 0 | AC34: =AC33 -> 1824 | AD34: =AC34-AC33 -> 0 | AE34: =AE33 -> 358865.2 | AF34: =AE34-AE33 -> 0 | AG34: =IF(AD34>0,AF34/AD34,0) -> 0 | AH34: =AF34+AA34 -> 0 | AI34: =SUM(AH34+V34) -> 281 | AJ34: =-tanks!AW35 -> 281 | AK34: =SUM(AJ34-AI34) -> 0 | AL34: =S34+L34+G34 -> 3 | AM34: =Y34+AD34 -> 0 | AN34: 81 | AO34: =(AN34/100)*3000 -> 2430 | AP34: 80 | AQ34: =(AP34/100)*3000 -> 2400 | AR34: 61 | AS34: =(AR34/100)*3000 -> 1830 | AT34: =SUM(AO34+AQ34+AS34) -> 6660 | AU34: =AT33-AT34+AV34 -> 440 | AV34: 1700 | AW34: 0.7 | AX34: =IF(AV34>0,AW34,AX33) -> 0.7
J35: =SUM(J5:J34)/(COUNT(J5:J34)-COUNTIF(J5:J34,0)) -> 82.769841 | AE35: . | AR35: Nb Delivery | AS35: =COUNT(AW5:AW34) -> 3 | AU35: =SUM(AU5:AU34) -> 3220 | AV35: =SUM(AV5:AV34) -> 3700 | AW35: =SUM(AW5:AW34)/AS35 -> 0.7
AH36: =AF36+AA36 -> 0 | AI36: =SUM(AI5:AI34) -> 9753.5
AH37: =AF37+AA37 -> 0 | AU37: =AU35*0.51 -> 1642.2 | AV37: =AV35/0.51 -> 7254.902 | AW37: =SUM(AW5:AW34)/AS35 -> 0.7
AV38: =AV35*0.51 -> 1887

Sheet WATER
D1: =SUM(G21:G35) -> 8945789 | AR1: Entrance | AT1: Tank 1 | AV1: Tank 2
AR2: Level | AW2: Quantity CM3 | AZ2: Var
A3: Date | B3: Truck | C3: Truck M3/day | D3: N0. Trucks | F3: REQ. # of trucks | G3: City | H3: City/day | I3: Total water delivery | K3: SW | L3: Cosum SW/day | M3: RO Guest/ Liter | O3: RO K&L/ Liter | Q3: TOTAL RO Production | R3: RO 1 RH | S3: RO 2 RH | T3: RO water counter | U3: RO Cons m3 | V3: Steam Boiler | W3: Steam Boiler/day | X3: Softener Guest | Y3: Guest Sotf/day | Z3: Softener K&L | AA3: K&L Soft/Day | AB3: Fire Tank Level | AC3: Fire Tank Counter | AE3: Laundry Hot Water Counter | AF3: Hot Water Cons/day | AG3: Laundry Cold Water Counter | AH3: Cold Water Cons/day | AI3: Laundry Water Total Cons | AJ3: K&L Sotf/day | AK3: Guest / day | AL3: K&L /day | AM3: Avg Outside Temp | AN3: Banquet Activity | AR3: Date | AT3: MainI | AV3: Kitchen and Laundry | AX3: Guest | AY3: Main Tank | AZ3: Kitchen and Laundry | BA3: Guest | BB3: Kitchen and Laundry | BC3: Main | BD3: Guest | BE3: Total VAR | BF3: Hotel Consumption
E4: 1.66 | AN4: Ball R | AO4: Meeting | AP4: outlet | AT4: 180 | AV4: 220 | AX4: 580 | AY4: =SUM(AT4) -> 180 | AZ4: =SUM(AV4) -> 220 | BA4: =SUM(AX4) -> 580
A5: 43921 | B5: =[1]WATER!B36 -> 108473 | C5: =[1]WATER!C36 -> 0 | D5: =[1]WATER!D36 -> 0 | E5: =[1]WATER!E36 -> 241.93548 | F5: =[1]WATER!F36 -> 0 | G5: =[1]WATER!G36 -> 595093 | H5: =[1]WATER!H36 -> 0 | I5: =[1]WATER!I36 -> 0 | ... AP5: =[1]WATER!AP36 -> 41 | AR5: 43921 | AS5: =[1]WATER!AS36 -> 0.9 | AT5: =[1]WATER!AT36 -> 105 | AU5: =[1]WATER!AU36 -> 1.1 | AV5: =[1]WATER!AV36 -> 79 | AW5: =[1]WATER!AW36 -> 2.9 | AX5: =[1]WATER!AX36 -> 123 | AY5: =[1]WATER!AY36 -> 94.5 | AZ5: =[1]WATER!AZ36 -> 86.9 | ... BG5: =[1]WATER!BG36 -> -36.1
A6: =ELEC!C3 -> 43922 | B6: =B5 -> 108473 | C6: =B6-B5 -> 0 | D6: =C6/27 -> 0 | E6: =SUM((C6*$E$4)+(7500/'EDl log'!$A$37)) -> 250 | G6: 595200 | H6: =G6-G5 -> 107 | I6: =C6+H6 -> 107 | J6: =IF(I6>0,E6/I6,0) -> 2.3364486 | K6: ='Swimming Pool quality check '!H6 -> 5274 | L6: 0 | M6: =M5 -> 457.44 | N6: =SUM(M6-M5) -> 0 | O6: =O5 -> 529.52 | P6: =SUM(O6-O5) -> 0 | Q6: =P6+N6 -> 0 | T6: 4744 | U6: =SUM(T6-T5) -> 2 | V6: =V5 -> 401 | W6: =+V6-V5 -> 0 | X6: 142399 | Y6: =SUM(X6-X5) -> 99 | Z6: =Z5 -> 93723 | AA6: =Z6-Z5 -> 0 | AB6: 258 | AC6: =AC5 -> 671 | AD6: 0 | AE6: =AE5 -> 144.23 | AF6: =AE6-AE5 -> 0 | AG6: =AG5 -> 1467.64 | AH6: =AG6-AG5 -> 0 | AI6: =AF6+AH6 -> 0 | AJ6: =+Z6-Z5 -> 0 | AK6: =SUM(Y6-L6) -> 99 | AL6: =SUM(AJ6-W6) -> 0 | AM6: ='General information '!D6 -> 16.5 | AN6: ='General information '!H6 -> 0 | AP6: ='General information '!J6 -> 25 | AR6: =A6 -> 43922 | AS6: =AS5 -> 0.9 | AT6: 175 | AU6: =AU5 -> 1.1 | AV6: 80 | AW6: 2.9 | AX6: 145 | AY6: =AS6*AT6 -> 157.5 | AZ6: =AU6*AV6 -> 88 | BA6: =AW6*AX6 -> 420.5 | BB6: =AY6-AY5 -> 63 | BC6: =AZ6-AZ5 -> 1.1 | BD6: =BA6-BA5 -> 63.8 | BE6: =SUM(BB6:BD6) -> 127.9 | BF6: =SUM(I6-BE6) -> -20.9 | BG6: =SUM(I6-BF6) -> 127.9
A7: =ELEC!C4 -> 43923 | B7: 108473 | C7: =B7-B6 -> 0 | D7: =C7/27 -> 0 | E7: =SUM((C7*$E$4)+(7500/'EDl log'!$A$37)) -> 250 | G7: 595200 | H7: =G7-G6 -> 0 | I7: =C7+H7 -> 0 | J7: =IF(I7>0,E7/I7,0) -> 0 | K7: ='Swimming Pool quality check '!H7 -> 5274 | L7: =K7-K6 -> 0 | M7: =M6 -> 457.44 | N7: =SUM(M7-M6) -> 0 | O7: =O6 -> 529.52 | P7: =SUM(O7-O6) -> 0 | Q7: =P7+N7 -> 0 | T7: 4745 | U7: =SUM(T7-T6) -> 1 | V7: =V6 -> 401 | W7: =+V7-V6 -> 0 | X7: 142471 | Y7: =SUM(X7-X6) -> 72 | Z7: 93743 | AA7: =Z7-Z6 -> 20 | AB7: 258 | AC7: =AC6 -> 671 | AD7: =AC7-AC6 -> 0 | AE7: 144.23 | AF7: =AE7-AE6 -> 0 | AG7: 1468.24 | AH7: =AG7-AG6 -> 0.6 | AI7: =AF7+AH7 -> 0.6 | AJ7: =+Z7-Z6 -> 20 | AK7: =SUM(Y7-L7) -> 72 | AL7: =SUM(AJ7-W7) -> 20 | AM7: ='General information '!D7 -> 17 | AN7: ='General information '!H7 -> 0 | AP7: ='General information '!J7 -> 37 | AR7: =A7 -> 43923 | AS7: =AS6 -> 0.9 | AT7: 80 | AU7: =AU6 -> 1.1 | AV7: 75 | AW7: 2.9 | AX7: 160 | AY7: =AS7*AT7 -> 72 | AZ7: =AU7*AV7 -> 82.5 | BA7: =AW7*AX7 -> 464 | BB7: =AY7-AY6 -> -85.5 | BC7: =AZ7-AZ6 -> -5.5 | BD7: =BA7-BA6 -> 43.5 | BE7: =SUM(BB7:BD7) -> -47.5 | BF7: =SUM(I7-BE7) -> 47.5 | BG7: =SUM(I7-BF7) -> -47.5
A8: =ELEC!C5 -> 43924 | B8: 108473 | C8: =B8-B7 -> 0 | D8: =C8/27 -> 0 | E8: =SUM((C8*$E$4)+(7500/'EDl log'!$A$37)) -> 250 | G8: 595500 | H8: =G8-G7 -> 300 | I8: =C8+H8 -> 300 | J8: =IF(I8>0,E8/I8,0) -> 0.83333333 | K8: ='Swimming Pool quality check '!H8 -> 5274 | L8: =K8-K7 -> 0 | M8: =M7 -> 457.44 | N8: =SUM(M8-M7) -> 0 | O8: =O7 -> 529.52 | P8: =SUM(O8-O7) -> 0 | Q8: =P8+N8 -> 0 | T8: 4747 | U8: =SUM(T8-T7) -> 2 | V8: =V7 -> 401 | W8: =+V8-V7 -> 0 | X8: 142531 | Y8: =SUM(X8-X7) -> 60 | Z8: 93777 | AA8: =Z8-Z7 -> 34 | AB8: 265 | AC8: =AC7 -> 671 | AD8: =AC8-AC7 -> 0 | AE8: 144.23 | AF8: =AE8-AE7 -> 0 | AG8: 1468.6 | AH8: =AG8-AG7 -> 0.36 | AI8: =AF8+AH8 -> 0.36 | AJ8: =+Z8-Z7 -> 34 | AK8: =SUM(Y8-L8) -> 60 | AL8: =SUM(AJ8-W8) -> 34 | AM8: ='General information '!D8 -> 17 | AN8: ='General information '!H8 -> 0 | AP8: ='General information '!J8 -> 33 | AR8: =A8 -> 43924 | AS8: =AS7 -> 0.9 | AT8: 192 | AU8: 1.1 | AV8: 97 | AW8: 2.9 | AX8: 169 | AY8: =AS8*AT8 -> 172.8 | AZ8: =AU8*AV8 -> 106.7 | BA8: =AW8*AX8 -> 490.1 | BB8: =AY8-AY7 -> 100.8 | BC8: =AZ8-AZ7 -> 24.2 | BD8: =BA8-BA7 -> 26.1 | BE8: =SUM(BB8:BD8) -> 151.1 | BF8: =SUM(I8-BE8) -> 148.9 | BG8: =SUM(I8-BF8) -> 151.1
A9: =ELEC!C6 -> 43925 | B9: 108473 | C9: =B9-B8 -> 0 | D9: =C9/27 -> 0 | E9: =SUM((C9*$E$4)+(7500/'EDl log'!$A$37)) -> 250 | G9: =G8 -> 595500 | H9: =G9-G8 -> 0 | I9: =C9+H9 -> 0 | J9: =IF(I9>0,E9/I9,0) -> 0 | K9: ='Swimming Pool quality check '!H9 -> 5983 | L9: =K9-K8 -> 709 | M9: =M8 -> 457.44 | N9: =SUM(M9-M8) -> 0 | O9: =O8 -> 529.52 | P9: =SUM(O9-O8) -> 0 | Q9: =P9+N9 -> 0 | T9: 4748 | U9: =SUM(T9-T8) -> 1 | V9: =V8 -> 401 | W9: =+V9-V8 -> 0 | X9: 142541 | Y9: =SUM(X9-X8) -> 10 | Z9: 93777 | AA9: =Z9-Z8 -> 0 | AB9: 265 | AC9: =AC8 -> 671 | AD9: =AC9-AC8 -> 0 | AE9: =AE8 -> 144.23 | AF9: =AE9-AE8 -> 0 | AG9: =AG8 -> 1468.6 | AH9: =AG9-AG8 -> 0 | AI9: =AF9+AH9 -> 0 | AJ9: =+Z9-Z8 -> 0 | AK9: =SUM(Y9-L9) -> -699 | AL9: =SUM(AJ9-W9) -> 0 | AM9: ='General information '!D9 -> 18.5 | AN9: ='General information '!H9 -> 0 | AP9: ='General information '!J9 -> 39 | AR9: =A9 -> 43925 | AS9: =AS8 -> 0.9 | AT9: 185 | AU9: =AU8 -> 1.1 | AV9: 82 | AW9: 2.9 | AX9: 165 | AY9: =AS9*AT9 -> 166.5 | AZ9: =AU9*AV9 -> 90.2 | BA9: =AW9*AX9 -> 478.5 | BB9: =AY9-AY8 -> -6.3 | BC9: =AZ9-AZ8 -> -16.5 | BD9: =BA9-BA8 -> -11.6 | BE9: =SUM(BB9:BD9) -> -34.4 | BF9: =SUM(I9-BE9) -> 34.4 | BG9: =SUM(I9-BF9) -> -34.4
A10: =ELEC!C7 -> 43926 | B10: =B9 -> 108473 | C10: =B10-B9 -> 0 | D10: =C10/27 -> 0 | E10: =SUM((C10*$E$4)+(7500/'EDl log'!$A$37)) -> 250 | G10: 595666 | H10: =G10-G9 -> 166 | I10: =C10+H10 -> 166 | J10: =IF(I10>0,E10/I10,0) -> 1.5060241 | K10: ='Swimming Pool quality check '!H10 -> 5985 | L10: =K10-K9 -> 2 | M10: =M9 -> 457.44 | N10: =SUM(M10-M9) -> 0 | O10: =O9 -> 529.52 | P10: =SUM(O10-O9) -> 0 | Q10: =P10+N10 -> 0 | T10: 4749 | U10: =SUM(T10-T9) -> 1 | V10: =V9 -> 401 | W10: =+V10-V9 -> 0 | X10: =X9 -> 142541 | Y10: =SUM(X10-X9) -> 0 | Z10: 93847 | AA10: =Z10-Z9 -> 70 | AB10: =AB9 -> 265 | AC10: =AC9 -> 671 | AD10: =AC10-AC9 -> 0 | AE10: 144.52 | AF10: =AE10-AE9 -> 0.29 | AG10: 1473.72 | AH10: =AG10-AG9 -> 5.12 | AI10: =AF10+AH10 -> 5.41 | AJ10: =+Z10-Z9 -> 70 | AK10: =SUM(Y10-L10) -> -2 | AL10: =SUM(AJ10-W10) -> 70 | AM10: ='General information '!D10 -> 25.5 | AN10: ='General information '!H10 -> 0 | AP10: ='General information '!J10 -> 68 | AR10: =A10 -> 43926 | AS10: =AS9 -> 0.9 | AT10: 175 | AU10: =AU9 -> 1.1 | AV10: 90 | AW10: 2.9 | AX10: 160 | AY10: =AS10*AT10 -> 157.5 | AZ10: =AU10*AV10 -> 99 | BA10: =AW10*AX10 -> 464 | BB10: =AY10-AY9 -> -9 | BC10: =AZ10-AZ9 -> 8.8 | BD10: =BA10-BA9 -> -14.5 | BE10: =SUM(BB10:BD10) -> -14.7 | BF10: =SUM(I10-BE10) -> 180.7 | BG10: =SUM(I10-BF10) -> -14.7
A11: =ELEC!C8 -> 43927 | B11: 108473 | C11: =B11-B10 -> 0 | D11: =C11/27 -> 0 | E11: =SUM((C11*$E$4)+(7500/'EDl log'!$A$37)) -> 250 | G11: 595685 | H11: =G11-G10 -> 19 | I11: =C11+H11 -> 19 | J11: =IF(I11>0,E11/I11,0) -> 13.157895 | K11: ='Swimming Pool quality check '!H11 -> 6006 | L11: =K11-K10 -> 21 | M11: =M10 -> 457.44 | N11: =SUM(M11-M10) -> 0 | O11: =O10 -> 529.52 | P11: =SUM(O11-O10) -> 0 | Q11: =SUM(P11+N11) -> 0 | T11: 4750 | U11: =SUM(T11-T10) -> 1 | V11: =V10 -> 401 | W11: =+V11-V10 -> 0 | X11: 142545 | Y11: =SUM(X11-X10) -> 4 | Z11: 93847 | AA11: =Z11-Z10 -> 0 | AB11: 265 | AC11: =AC10 -> 671 | AD11: =AC11-AC10 -> 0 | AE11: =AE10 -> 144.52 | AF11: =AE11-AE10 -> 0 | AG11: 1474.06 | AH11: =AG11-AG10 -> 0.34 | AI11: =AF11+AH11 -> 0.34 | AJ11: =+Z11-Z10 -> 0 | AK11: =SUM(Y11-L11) -> -17 | AL11: =SUM(AJ11-W11) -> 0 | AM11: ='General information '!D11 -> 18 | AN11: ='General information '!H11 -> 0 | AP11: ='General information '!J11 -> 31 | AR11: =A11 -> 43927 | AS11: =AS10 -> 0.9 | AT11: 170 | AU11: =AU10 -> 1.1 | AV11: 120 | AW11: 2.9 | AX11: 157 | AY11: =AS11*AT11 -> 153 | AZ11: =AU11*AV11 -> 132 | BA11: =AW11*AX11 -> 455.3 | BB11: =AY11-AY10 -> -4.5 | BC11: =AZ11-AZ10 -> 33 | BD11: =BA11-BA10 -> -8.7 | BE11: =SUM(BB11:BD11) -> 19.8 | BF11: =SUM(I11-BE11) -> -0.8 | BG11: =SUM(I11-BF11) -> 19.8
A12: =ELEC!C9 -> 43928 | B12: 108473 | C12: =B12-B11 -> 0 | D12: =C12/27 -> 0 | E12: =SUM((C12*$E$4)+(7500/'EDl log'!$A$37)) -> 250 | G12: 595685 | H12: =G12-G11 -> 0 | I12: =C12+H12 -> 0 | J12: =IF(I12>0,E12/I12,0) -> 0 | K12: ='Swimming Pool quality check '!H12 -> 6007 | L12: =K12-K11 -> 1 | M12: =M11 -> 457.44 | N12: =SUM(M12-M11) -> 0 | O12: =O11 -> 529.52 | P12: =SUM(O12-O11) -> 0 | Q12: =SUM(P12+N12) -> 0 | T12: 4751 | U12: =SUM(T12-T11) -> 1 | V12: =V11 -> 401 | W12: =+V12-V11 -> 0 | X12: 142545 | Y12: =SUM(X12-X11) -> 0 | Z12: 93884 | AA12: =Z12-Z11 -> 37 | AB12: 266 | AC12: =AC11 -> 671 | AD12: =AC12-AC11 -> 0 | AE12: 144.52 | AF12: =AE12-AE11 -> 0 | AG12: 1474.34 | AH12: =AG12-AG11 -> 0.28 | AI12: =AF12+AH12 -> 0.28 | AJ12: =+Z12-Z11 -> 37 | AK12: =SUM(Y12-L12) -> -1 | AL12: =SUM(AJ12-W12) -> 37 | AM12: ='General information '!D12 -> 18 | AN12: ='General information '!H12 -> 0 | AP12: ='General information '!J12 -> 31 | AR12: =A12 -> 43928 | AS12: =AS11 -> 0.9 | AT12: 161 | AU12: =AU11 -> 1.1 | AV12: 133 | AW12: 2.9 | AX12: 146 | AY12: =AS12*AT12 -> 144.9 | AZ12: =AU12*AV12 -> 146.3 | BA12: =AW12*AX12 -> 423.4 | BB12: =AY12-AY11 -> -8.1 | BC12: =AZ12-AZ11 -> 14.3 | BD12: =BA12-BA11 -> -31.9 | BE12: =SUM(BB12:BD12) -> -25.7 | BF12: =SUM(I12-BE12) -> 25.7 | BG12: =SUM(I12-BF12) -> -25.7
A13: =ELEC!C10 -> 43929 | B13: 108473 | C13: =B13-B12 -> 0 | D13: =C13/27 -> 0 | E13: =SUM((C13*$E$4)+(7500/'EDl log'!$A$37)) -> 250 | G13: 595714 | H13: =G13-G12 -> 29 | I13: =C13+H13 -> 29 | J13: =IF(I13>0,E13/I13,0) -> 8.6206897 | K13: ='Swimming Pool quality check '!H13 -> 6013 | L13: =K13-K12 -> 6 | M13: =M12 -> 457.44 | N13: =SUM(M13-M12) -> 0 | O13: =O12 -> 529.52 | P13: =SUM(O13-O12) -> 0 | Q13: =SUM(P13+N13) -> 0 | T13: 4751 | U13: =SUM(T13-T12) -> 0 | V13: 401 | W13: =+V13-V12 -> 0 | X13: 142626 | Y13: =SUM(X13-X12) -> 81 | Z13: 93884 | AA13: =Z13-Z12 -> 0 | AB13: 266 | AC13: =AC12 -> 671 | AD13: =AC13-AC12 -> 0 | AE13: 144.52 | AF13: =AE13-AE12 -> 0 | AG13: 1474.62 | AH13: =AG13-AG12 -> 0.28 | AI13: =AF13+AH13 -> 0.28 | AJ13: =+Z13-Z12 -> 0 | AK13: =SUM(Y13-L13) -> 75 | AL13: =SUM(AJ13-W13) -> 0 | AM13: ='General information '!D13 -> 17 | AN13: ='General information '!J13 -> 48 | AP13: ='General information '!J13 -> 48 | AR13: =A13 -> 43929 | AS13: =AS12 -> 0.9 | AT13: 80 | AU13: =AU12 -> 1.1 | AV13: 124 | AW13: 2.9 | AX13: 163 | AY13: =AS13*AT13 -> 72 | AZ13: =AU13*AV13 -> 136.4 | BA13: =AW13*AX13 -> 472.7 | BB13: =AY13-AY12 -> -72.9 | BC13: =AZ13-AZ12 -> -9.9 | BD13: =BA13-BA12 -> 49.3 | BE13: =SUM(BB13:BD13) -> -33.5 | BF13: =SUM(I13-BE13) -> 62.5 | BG13: =SUM(I13-BF13) -> -33.5
A14: =ELEC!C11 -> 43930 | B14: =B13 -> 108473 | C14: =B14-B13 -> 0 | D14: =C14/27 -> 0 | E14: =SUM((C14*$E$4)+(7500/'EDl log'!$A$37)) -> 250 | G14: 596001 | H14: =G14-G13 -> 287 | I14: =C14+H14 -> 287 | J14: =IF(I14>0,E14/I14,0) -> 0.87108014 | K14: ='Swimming Pool quality check '!H14 -> 6017 | L14: =K14-K13 -> 4 | M14: =M13 -> 457.44 | N14: =SUM(M14-M13) -> 0 | O14: =O13 -> 529.52 | P14: =SUM(O14-O13) -> 0 | Q14: =SUM(P14+N14) -> 0 | T14: 4753 | U14: =SUM(T14-T13) -> 2 | V14: 402 | W14: =+V14-V13 -> 1 | X14: 142704 | Y14: =SUM(X14-X13) -> 78 | Z14: 93908 | AA14: =Z14-Z13 -> 24 | AB14: 266 | AC14: =AC13 -> 671 | AD14: =AC14-AC13 -> 0 | AE14: 146.14 | AF14: =AE14-AE13 -> 1.62 | AG14: 1485.52 | AH14: =AG14-AG13 -> 10.9 | AI14: =AF14+AH14 -> 12.52 | AJ14: =+Z14-Z13 -> 24 | AK14: =SUM(Y14-L14) -> 74 | AL14: =SUM(AJ14-W14) -> 23 | AM14: ='General information '!D14 -> 16.5 | AN14: ='General information '!H14 -> 0 | AP14: ='General information '!J14 -> 25 | AR14: =A14 -> 43930 | AS14: =AS13 -> 0.9 | AT14: 176 | AU14: =AU13 -> 1.1 | AV14: 133 | AW14: 2.9 | AX14: 180 | AY14: =AS14*AT14 -> 158.4 | AZ14: =AU14*AV14 -> 146.3 | BA14: =AW14*AX14 -> 522 | BB14: =AY14-AY13 -> 86.4 | BC14: =AZ14-AZ13 -> 9.9 | BD14: =BA14-BA13 -> 49.3 | BE14: =SUM(BB14:BD14) -> 145.6 | BF14: =SUM(I14-BE14) -> 141.4 | BG14: =SUM(I14-BF14) -> 145.6
A15: =ELEC!C12 -> 43931 | B15: 108473 | C15: =B15-B14 -> 0 | D15: =C15/27 -> 0 | E15: =SUM((C15*$E$4)+(7500/'EDl log'!$A$37)) -> 250 | G15: =G14 -> 596001 | H15: =G15-G14 -> 0 | I15: =C15+H15 -> 0 | J15: =IF(I15>0,E15/I15,0) -> 0 | K15: ='Swimming Pool quality check '!H15 -> 6020 | L15: =K15-K14 -> 3 | M15: =M14 -> 457.44 | N15: =SUM(M15-M14) -> 0 | O15: =O14 -> 529.52 | P15: =SUM(O15-O14) -> 0 | Q15: =SUM(P15+N15) -> 0 | T15: 4754 | U15: =SUM(T15-T14) -> 1 | V15: =V14 -> 402 | W15: =+V15-V14 -> 0 | X15: =X14 -> 142704 | Y15: =SUM(X15-X14) -> 0 | Z15: =Z14 -> 93908 | AA15: =Z15-Z14 -> 0 | AB15: 266 | AC15: =AC14 -> 671 | AD15: =AC15-AC14 -> 0 | AE15: =AE14 -> 146.14 | AF15: =AE15-AE14 -> 0 | AG15: =AG14 -> 1485.52 | AH15: =AG15-AG14 -> 0 | AI15: =AF15+AH15 -> 0 | AJ15: =+Z15-Z14 -> 0 | AK15: =SUM(Y15-L15) -> -3 | AL15: =SUM(AJ15-W15) -> 0 | AM15: ='General information '!D15 -> 14.5 | AN15: ='General information '!H15 -> 0 | AP15: ='General information '!J15 -> 52 | AR15: =A15 -> 43931 | AS15: =AS14 -> 0.9 | AT15: =AT14 -> 176 | AU15: =AU14 -> 1.1 | AV15: 121 | AW15: 2.9 | AX15: 179 | AY15: =AS15*AT15 -> 158.4 | AZ15: =AU15*AV15 -> 133.1 | BA15: =AW15*AX15 -> 519.1 | BB15: =AY15-AY14 -> 0 | BC15: =AZ15-AZ14 -> -13.2 | BD15: =BA15-BA14 -> -2.9 | BE15: =SUM(BB15:BD15) -> -16.1 | BF15: =SUM(I15-BE15) -> 16.1 | BG15: =SUM(I15-BF15) -> -16.1
A16: =ELEC!C13 -> 43932 | B16: 108473 | C16: =B16-B15 -> 0 | D16: =C16/27 -> 0 | E16: =SUM((C16*$E$4)+(7500/'EDl log'!$A$37)) -> 250 | G16: =G15 -> 596001 | H16: =G16-G15 -> 0 | I16: =C16+H16 -> 0 | J16: =IF(I16>0,E16/I16,0) -> 0 | K16: ='Swimming Pool quality check '!H16 -> 6021 | L16: =K16-K15 -> 1 | M16: =M15 -> 457.44 | N16: =SUM(M16-M15) -> 0 | O16: =O15 -> 529.52 | P16: =SUM(O16-O15) -> 0 | Q16: =SUM(P16+N16) -> 0 | T16: 4755 | U16: =SUM(T16-T15) -> 1 | V16: =V15 -> 402 | W16: =+V16-V15 -> 0 | X16: =X15 -> 142704 | Y16: =SUM(X16-X15) -> 0 | Z16: 93913 | AA16: =Z16-Z15 -> 5 | AB16: 266 | AC16: =AC15 -> 671 | AD16: =AC16-AC15 -> 0 | AE16: =AE15 -> 146.14 | AF16: =AE16-AE15 -> 0 | AG16: 1486.22 | AH16: =AG16-AG15 -> 0.7 | AI16: =AF16+AH16 -> 0.7 | AJ16: =+Z16-Z15 -> 5 | AK16: =SUM(Y16-L16) -> -1 | AL16: =SUM(AJ16-W16) -> 5 | AM16: ='General information '!D16 -> 15.5 | AN16: ='General information '!H16 -> 0 | AP16: ='General information '!J16 -> 60 | AR16: =A16 -> 43932 | AS16: =AS15 -> 0.9 | AT16: 172 | AU16: =AU15 -> 1.1 | AV16: 114 | AW16: 2.9 | AX16: 176 | AY16: =AS16*AT16 -> 154.8 | AZ16: =AU16*AV16 -> 125.4 | BA16: =AW16*AX16 -> 510.4 | BB16: =AY16-AY15 -> -3.6 | BC16: =AZ16-AZ15 -> -7.7 | BD16: =BA16-BA15 -> -8.7 | BE16: =SUM(BB16:BD16) -> -20 | BF16: =SUM(I16-BE16) -> 20 | BG16: =SUM(I16-BF16) -> -20
A17: =ELEC!C14 -> 43933 | B17: 108473 | C17: =B17-B16 -> 0 | D17: =C17/27 -> 0 | E17: =SUM((C17*$E$4)+(7500/'EDl log'!$A$37)) -> 250 | G17: =G16 -> 596001 | H17: =G17-G16 -> 0 | I17: =C17+H17 -> 0 | J17: =IF(I17>0,E17/I17,0) -> 0 | K17: ='Swimming Pool quality check '!H17 -> 6022 | L17: =K17-K16 -> 1 | M17: =M16 -> 457.44 | N17: =SUM(M17-M16) -> 0 | O17: =O16 -> 529.52 | P17: =SUM(O17-O16) -> 0 | Q17: =SUM(P17+N17) -> 0 | T17: 4756 | U17: =SUM(T17-T16) -> 1 | V17: =V16 -> 402 | W17: =+V17-V16 -> 0 | X17: =X16 -> 142704 | Y17: =SUM(X17-X16) -> 0 | Z17: =Z16 -> 93913 | AA17: =Z17-Z16 -> 0 | AB17: 266 | AC17: =AC16 -> 671 | AD17: =AC17-AC16 -> 0 | AE17: =AE16 -> 146.14 | AF17: =AE17-AE16 -> 0 | AG17: =AG16 -> 1486.22 | AH17: =AG17-AG16 -> 0 | AI17: =AF17+AH17 -> 0 | AJ17: =+Z17-Z16 -> 0 | AK17: =SUM(Y17-L17) -> -1 | AL17: =SUM(AJ17-W17) -> 0 | AM17: ='General information '!D17 -> 17 | AN17: ='General information '!H17 -> 0 | AP17: ='General information '!J17 -> 71 | AR17: =A17 -> 43933 | AS17: =AS16 -> 0.9 | AT17: =AT16 -> 172 | AU17: =AU16 -> 1.1 | AV17: 94 | AW17: 2.9 | AX17: 166 | AY17: =AS17*AT17 -> 154.8 | AZ17: =AU17*AV17 -> 103.4 | BA17: =AW17*AX17 -> 481.4 | BB17: =AY17-AY16 -> 0 | BC17: =AZ17-AZ16 -> -22 | BD17: =BA17-BA16 -> -29 | BE17: =SUM(BB17:BD17) -> -51 | BF17: =SUM(I17-BE17) -> 51 | BG17: =SUM(I17-BF17) -> -51
A18: =ELEC!C15 -> 43934 | B18: =B17 -> 108473 | C18: =B18-B17 -> 0 | D18: =C18/27 -> 0 | E18: =SUM((C18*$E$4)+(7500/'EDl log'!$A$37)) -> 250 | G18: 596046 | H18: =G18-G17 -> 45 | I18: =C18+H18 -> 45 | J18: =IF(I18>0,E18/I18,0) -> 5.5555556 | K18: ='Swimming Pool quality check '!H18 -> 6026 | L18: =K18-K17 -> 4 | M18: =M17 -> 457.44 | N18: =SUM(M18-M17) -> 0 | O18: =O17 -> 529.52 | P18: =SUM(O18-O17) -> 0 | Q18: =SUM(P18+N18) -> 0 | T18: 4758 | U18: =SUM(T18-T17) -> 2 | V18: =V17 -> 402 | W18: =+V18-V17 -> 0 | X18: 142707 | Y18: =SUM(X18-X17) -> 3 | Z18: =Z17 -> 93913 | AA18: =Z18-Z17 -> 0 | AB18: 266 | AC18: =AC17 -> 671 | AD18: =AC18-AC17 -> 0 | AE18: =AE17 -> 146.14 | AF18: =AE18-AE17 -> 0 | AG18: =AG17 -> 1486.22 | AH18: =AG18-AG17 -> 0 | AI18: =AF18+AH18 -> 0 | AJ18: =+Z18-Z17 -> 0 | AK18: =SUM(Y18-L18) -> -1 | AL18: =SUM(AJ18-W18) -> 0 | AM18: ='General information '!D18 -> 18 | AN18: ='General information '!H18 -> 0 | AP18: ='General information '!J18 -> 58 | AR18: =A18 -> 43934 | AS18: =AS17 -> 0.9 | AT18: 190 | AU18: =AU17 -> 1.1 | AV18: 82 | AW18: 2.9 | AX18: 158 | AY18: =AS18*AT18 -> 171 | AZ18: =AU18*AV18 -> 90.2 | BA18: =AW18*AX18 -> 458.2 | BB18: =AY18-AY17 -> 16.2 | BC18: =AZ18-AZ17 -> -13.2 | BD18: =BA18-BA17 -> -23.2 | BE18: =SUM(BB18:BD18) -> -20.2 | BF18: =SUM(I18-BE18) -> 65.2 | BG18: =SUM(I18-BF18) -> -20.2
A19: =ELEC!C16 -> 43935 | B19: 108473 | C19: =B19-B18 -> 0 | D19: =C19/27 -> 0 | E19: =SUM((C19*$E$4)+(7500/'EDl log'!$A$37)) -> 250 | G19: 596046 | H19: =G19-G18 -> 0 | I19: =C19+H19 -> 0 | J19: =IF(I19>0,E19/I19,0) -> 0 | K19: ='Swimming Pool quality check '!H19 -> 6028 | L19: =K19-K18 -> 2 | M19: =M18 -> 457.44 | N19: =SUM(M19-M18) -> 0 | O19: =O18 -> 529.52 | P19: =SUM(O19-O18) -> 0 | Q19: =SUM(P19+N19) -> 0 | T19: 4760 | U19: =SUM(T19-T18) -> 2 | V19: 402 | W19: =+V19-V18 -> 0 | X19: 142707 | Y19: =SUM(X19-X18) -> 0 | Z19: 93953 | AA19: =Z19-Z18 -> 40 | AB19: =AB18 -> 266 | AC19: =AC18 -> 671 | AD19: =AC19-AC18 -> 0 | AE19: 146.14 | AF19: =AE19-AE18 -> 0 | AG19: 1487.6 | AH19: =AG19-AG18 -> 1.38 | AI19: =AF19+AH19 -> 1.38 | AJ19: =+Z19-Z18 -> 40 | AK19: =SUM(Y19-L19) -> -2 | AL19: =SUM(AJ19-W19) -> 40 | AM19: ='General information '!D19 -> 19 | AN19: ='General information '!H19 -> 0 | AP19: ='General information '!J19 -> 91 | AR19: =A19 -> 43935 | AS19: =AS18 -> 0.9 | AT19: 154 | AU19: =AU18 -> 1.1 | AV19: 112 | AW19: 2.9 | AX19: 154 | AY19: =AS19*AT19 -> 138.6 | AZ19: =AU19*AV19 -> 123.2 | BA19: =AW19*AX19 -> 446.6 | BB19: =AY19-AY18 -> -32.4 | BC19: =AZ19-AZ18 -> 33 | BD19: =BA19-BA18 -> -11.6 | BE19: =SUM(BB19:BD19) -> -11 | BF19: =SUM(I19-BE19) -> 11 | BG19: =SUM(I19-BF19) -> -11
A20: =ELEC!C17 -> 43936 | B20: 108473 | C20: =B20-B19 -> 0 | D20: =C20/27 -> 0 | E20: =SUM((C20*$E$4)+(7500/'EDl log'!$A$37)) -> 250 | G20: 596065 | H20: =G20-G19 -> 19 | I20: =C20+H20 -> 19 | J20: =IF(I20>0,E20/I20,0) -> 13.157895 | K20: ='Swimming Pool quality check '!H20 -> 6033 | L20: =K20-K19 -> 5 | M20: =M19 -> 457.44 | N20: =SUM(M20-M19) -> 0 | O20: =O19 -> 529.52 | P20: =SUM(O20-O19) -> 0 | Q20: =SUM(P20+N20) -> 0 | T20: 4762 | U20: =SUM(T20-T19) -> 2 | V20: 403 | W20: =+V20-V19 -> 1 | X20: 142707 | Y20: =SUM(X20-X19) -> 0 | Z20: 93953 | AA20: =Z20-Z19 -> 0 | AB20: =AB19 -> 266 | AC20: =AC19 -> 671 | AD20: =AC20-AC19 -> 0 | AE20: 147.84 | AF20: =AE20-AE19 -> 1.7 | AG20: 1499.91 | AH20: =AG20-AG19 -> 12.31 | AI20: =AF20+AH20 -> 14.01 | AJ20: =+Z20-Z19 -> 0 | AK20: =SUM(Y20-L20) -> -5 | AL20: =SUM(AJ20-W20) -> -1 | AM20: ='General information '!D20 -> 18 | AN20: ='General information '!H20 -> 0 | AP20: ='General information '!J20 -> 50 | AR20: =A20 -> 43936 | AS20: =AS19 -> 0.9 | AT20: 117 | AU20: =AU19 -> 1.1 | AV20: 92 | AW20: 2.9 | AX20: 150 | AY20: =AS20*AT20 -> 105.3 | AZ20: =AU20*AV20 -> 101.2 | BA20: =AW20*AX20 -> 435 | BB20: =AY20-AY19 -> -33.3 | BC20: =AZ20-AZ19 -> -22 | BD20: =BA20-BA19 -> -11.6 | BE20: =SUM(BB20:BD20) -> -66.9 | BF20: =SUM(I20-BE20) -> 85.9 | BG20: =SUM(I20-BF20) -> -66.9
A21: =ELEC!C18 -> 43937 | B21: =B20 -> 108473 | C21: =B21-B20 -> 0 | D21: =C21/27 -> 0 | E21: =SUM((C21*$E$4)+(7500/'EDl log'!$A$37)) -> 250 | G21: 596115 | H21: =G21-G20 -> 50 | I21: =C21+H21 -> 50 | J21: =IF(I21>0,E21/I21,0) -> 5 | K21: ='Swimming Pool quality check '!H21 -> 6033 | L21: =K21-K20 -> 0 | M21: =M20 -> 457.44 | N21: =SUM(M21-M20) -> 0 | O21: =O20 -> 529.52 | P21: =SUM(O21-O20) -> 0 | Q21: =SUM(P21+N21) -> 0 | T21: 4764 | U21: =SUM(T21-T20) -> 2 | V21: =V20 -> 403 | W21: =+V21-V20 -> 0 | X21: =X20 -> 142707 | Y21: =SUM(X21-X20) -> 0 | Z21: 93964 | AA21: =Z21-Z20 -> 11 | AB21: =AB20 -> 266 | AC21: =AC20 -> 671 | AD21: =AC21-AC20 -> 0 | AE21: =AE20 -> 147.84 | AF21: =AE21-AE20 -> 0 | AG21: 1500 | AH21: =AG21-AG20 -> 0.09 | AI21: =AF21+AH21 -> 0.09 | AJ21: =+Z21-Z20 -> 11 | AK21: =SUM(Y21-L21) -> 0 | AL21: =SUM(AJ21-W21) -> 11 | AM21: ='General information '!D21 -> 17.5 | AN21: ='General information '!H21 -> 0 | AP21: ='General information '!J21 -> 61 | AR21: =A21 -> 43937 | AS21: =AS20 -> 0.9 | AT21: 136 | AU21: =AU20 -> 1.1 | AV21: 76 | AW21: 2.9 | AX21: 141 | AY21: =AS21*AT21 -> 122.4 | AZ21: =AU21*AV21 -> 83.6 | BA21: =AW21*AX21 -> 408.9 | BB21: =AY21-AY20 -> 17.1 | BC21: =AZ21-AZ20 -> -17.6 | BD21: =BA21-BA20 -> -26.1 | BE21: =SUM(BB21:BD21) -> -26.6 | BF21: =SUM(I21-BE21) -> 76.6 | BG21: =SUM(I21-BF21) -> -26.6
A22: =ELEC!C19 -> 43938 | B22: 108473 | C22: =B22-B21 -> 0 | D22: =C22/27 -> 0 | E22: =SUM((C22*$E$4)+(7500/'EDl log'!$A$37)) -> 250 | G22: 596369 | H22: =G22-G21 -> 254 | I22: =C22+H22 -> 254 | J22: =IF(I22>0,E22/I22,0) -> 0.98425197 | K22: ='Swimming Pool quality check '!H22 -> 6033 | L22: =K22-K21 -> 0 | M22: =M21 -> 457.44 | N22: =SUM(M22-M21) -> 0 | O22: =O21 -> 529.52 | P22: =SUM(O22-O21) -> 0 | Q22: =SUM(P22+N22) -> 0 | T22: 4765 | U22: =SUM(T22-T21) -> 1 | V22: 403 | W22: =+V22-V21 -> 0 | X22: =X21 -> 142707 | Y22: =SUM(X22-X21) -> 0 | Z22: 94037 | AA22: =Z22-Z21 -> 73 | AB22: =AB21 -> 266 | AC22: =AC21 -> 671 | AD22: =AC22-AC21 -> 0 | AE22: =AE21 -> 147.84 | AF22: =AE22-AE21 -> 0 | AG22: =AG21 -> 1500 | AH22: =AG22-AG21 -> 0 | AI22: =AF22+AH22 -> 0 | AJ22: =+Z22-Z21 -> 73 | AK22: =SUM(Y22-L22) -> 0 | AL22: =SUM(AJ22-W22) -> 73 | AM22: ='General information '!D22 -> 19.5 | AN22: ='General information '!H22 -> 0 | AP22: ='General information '!J22 -> 83 | AR22: =A22 -> 43938 | AS22: =AS21 -> 0.9 | AT22: 200 | AU22: =AU21 -> 1.1 | AV22: 124 | AW22: 2.9 | AX22: 136 | AY22: =AS22*AT22 -> 180 | AZ22: =AU22*AV22 -> 136.4 | BA22: =AW22*AX22 -> 394.4 | BB22: =AY22-AY21 -> 57.6 | BC22: =AZ22-AZ21 -> 52.8 | BD22: =BA22-BA21 -> -14.5 | BE22: =SUM(BB22:BD22) -> 95.9 | BF22: =SUM(I22-BE22) -> 158.1 | BG22: =SUM(I22-BF22) -> 95.9
A23: =ELEC!C20 -> 43939 | B23: =B22 -> 108473 | C23: =B23-B22 -> 0 | D23: =C23/27 -> 0 | E23: =SUM((C23*$E$4)+(7500/'EDl log'!$A$37)) -> 250 | G23: 596369 | H23: =G23-G22 -> 0 | I23: =C23+H23 -> 0 | J23: =IF(I23>0,E23/I23,0) -> 0 | K23: ='Swimming Pool quality check '!H23 -> 6033 | L23: =K23-K22 -> 0 | M23: =M22 -> 457.44 | N23: =SUM(M23-M22) -> 0 | O23: =O22 -> 529.52 | P23: =SUM(O23-O22) -> 0 | Q23: =SUM(P23+N23) -> 0 | T23: 4769 | U23: =SUM(T23-T22) -> 4 | V23: 403 | W23: =+V23-V22 -> 0 | X23: 142707 | Y23: =SUM(X23-X22) -> 0 | Z23: =Z22 -> 94037 | AA23: =Z23-Z22 -> 0 | AB23: =AB22 -> 266 | AC23: =AC22 -> 671 | AD23: =AC23-AC22 -> 0 | AE23: =AE22 -> 147.84 | AF23: =AE23-AE22 -> 0 | AG23: 1500.67 | AH23: =AG23-AG22 -> 0.67 | AI23: =AF23+AH23 -> 0.67 | AJ23: =+Z23-Z22 -> 0 | AK23: =SUM(Y23-L23) -> 0 | AL23: =SUM(AJ23-W23) -> 0 | AM23: ='General information '!D23 -> 20.5 | AN23: ='General information '!H23 -> 0 | AP23: ='General information '!J23 -> 68 | AR23: =A23 -> 43939 | AS23: =AS22 -> 0.9 | AT23: 193 | AU23: =AU22 -> 1.1 | AV23: 125 | AW23: 2.9 | AX23: 135 | AY23: =AS23*AT23 -> 173.7 | AZ23: =AU23*AV23 -> 137.5 | BA23: =AW23*AX23 -> 391.5 | BB23: =AY23-AY22 -> -6.3 | BC23: =AZ23-AZ22 -> 1.1 | BD23: =BA23-BA22 -> -2.9 | BE23: =SUM(BB23:BD23) -> -8.1 | BF23: =SUM(I23-BE23) -> 8.1 | BG23: =SUM(I23-BF23) -> -8.1
A24: =ELEC!C21 -> 43940 | B24: =B23 -> 108473 | C24: =B24-B23 -> 0 | D24: =C24/27 -> 0 | E24: =SUM((C24*$E$4)+(7500/'EDl log'!$A$37)) -> 250 | G24: 596369 | H24: =G24-G23 -> 0 | I24: =C24+H24 -> 0 | J24: =IF(I24>0,E24/I24,0) -> 0 | K24: ='Swimming Pool quality check '!H24 -> 6044 | L24: =K24-K23 -> 11 | M24: =M23 -> 457.44 | N24: =SUM(M24-M23) -> 0 | O24: =O23 -> 529.52 | P24: =SUM(O24-O23) -> 0 | Q24: =SUM(P24+N24) -> 0 | T24: 4771 | U24: =SUM(T24-T23) -> 2 | V24: =V23 -> 403 | W24: =+V24-V23 -> 0 | X24: 142712 | Y24: =SUM(X24-X23) -> 5 | Z24: 94040 | AA24: =Z24-Z23 -> 3 | AB24: =AB23 -> 266 | AC24: =AC23 -> 671 | AD24: =AC24-AC23 -> 0 | AE24: =AE23 -> 147.84 | AF24: =AE24-AE23 -> 0 | AG24: =AG23 -> 1500.67 | AH24: =AG24-AG23 -> 0 | AI24: =AF24+AH24 -> 0 | AJ24: =+Z24-Z23 -> 3 | AK24: =SUM(Y24-L24) -> -6 | AL24: =SUM(AJ24-W24) -> 3 | AM24: ='General information '!D24 -> 20.5 | AN24: ='General information '!H24 -> 0 | AP24: ='General information '!J24 -> 41 | AR24: =A24 -> 43940 | AS24: =AS23 -> 0.9 | AT24: =AT23 -> 193 | AU24: =AU23 -> 1.1 | AV24: 107 | AW24: 2.9 | AX24: 130 | AY24: =AS24*AT24 -> 173.7 | AZ24: =AU24*AV24 -> 117.7 | BA24: =AW24*AX24 -> 377 | BB24: =AY24-AY23 -> 0 | BC24: =AZ24-AZ23 -> -19.8 | BD24: =BA24-BA23 -> -14.5 | BE24: =SUM(BB24:BD24) -> -34.3 | BF24: =SUM(I24-BE24) -> 34.3 | BG24: =SUM(I24-BF24) -> -34.3
A25: =ELEC!C22 -> 43941 | B25: =B24 -> 108473 | C25: =B25-B24 -> 0 | D25: =C25/27 -> 0 | E25: =SUM((C25*$E$4)+(7500/'EDl log'!$A$37)) -> 250 | G25: 596369 | H25: =G25-G24 -> 0 | I25: =C25+H25 -> 0 | J25: =IF(I25>0,E25/I25,0) -> 0 | K25: ='Swimming Pool quality check '!H25 -> 6048 | L25: =K25-K24 -> 4 | M25: =M24 -> 457.44 | N25: =SUM(M25-M24) -> 0 | O25: =O24 -> 529.52 | P25: =SUM(O25-O24) -> 0 | Q25: =SUM(P25+N25) -> 0 | T25: 4773 | U25: =SUM(T25-T24) -> 2 | V25: =V24 -> 403 | W25: =+V25-V24 -> 0 | X25: =X24 -> 142712 | Y25: =SUM(X25-X24) -> 0 | Z25: =Z24 -> 94040 | AA25: =Z25-Z24 -> 0 | AB25: =AB24 -> 266 | AC25: =AC24 -> 671 | AD25: =AC25-AC24 -> 0 | AE25: 147.54 | AF25: =AE25-AE24 -> -0.3 | AG25: 1501.13 | AH25: =AG25-AG24 -> 0.46 | AI25: =AF25+AH25 -> 0.16 | AJ25: =+Z25-Z24 -> 0 | AK25: =SUM(Y25-L25) -> -4 | AL25: =SUM(AJ25-W25) -> 0 | AM25: ='General information '!D25 -> 20.5 | AN25: ='General information '!H25 -> 0 | AP25: ='General information '!J25 -> 34 | AR25: =A25 -> 43941 | AS25: =AS24 -> 0.9 | AT25: 180 | AU25: =AU24 -> 1.1 | AV25: 102 | AW25: 2.9 | AX25: 126 | AY25: =AS25*AT25 -> 162 | AZ25: =AU25*AV25 -> 112.2 | BA25: =AW25*AX25 -> 365.4 | BB25: =AY25-AY24 -> -11.7 | BC25: =AZ25-AZ24 -> -5.5 | BD25: =BA25-BA24 -> -11.6 | BE25: =SUM(BB25:BD25) -> -28.8 | BF25: =SUM(I25-BE25) -> 28.8 | BG25: =SUM(I25-BF25) -> -28.8
A26: =ELEC!C23 -> 43942 | B26: 108473 | C26: =B26-B25 -> 0 | D26: =C26/27 -> 0 | E26: =SUM((C26*$E$4)+(7500/'EDl log'!$A$37)) -> 250 | G26: 596369 | H26: =G26-G25 -> 0 | I26: =C26+H26 -> 0 | J26: =IF(I26>0,E26/I26,0) -> 0 | K26: ='Swimming Pool quality check '!H26 -> 6050 | L26: =K26-K25 -> 2 | M26: =M25 -> 457.44 | N26: =SUM(M26-M25) -> 0 | O26: =O25 -> 529.52 | P26: =SUM(O26-O25) -> 0 | Q26: =SUM(P26+N26) -> 0 | T26: 4775 | U26: =SUM(T26-T25) -> 2 | V26: 403 | W26: =+V26-V25 -> 0 | X26: 142712 | Y26: =SUM(X26-X25) -> 0 | Z26: 94040 | AA26: =Z26-Z25 -> 0 | AB26: =AB25 -> 266 | AC26: =AC25 -> 671 | AD26: =AC26-AC25 -> 0 | AE26: 147.54 | AF26: =AE26-AE25 -> 0 | AG26: 1501.42 | AH26: =AG26-AG25 -> 0.29 | AI26: =AF26+AH26 -> 0.29 | AJ26: =+Z26-Z25 -> 0 | AK26: =SUM(Y26-L26) -> -2 | AL26: =SUM(AJ26-W26) -> 0 | AM26: ='General information '!D26 -> 21 | AN26: ='General information '!H26 -> 0 | AP26: ='General information '!J26 -> 58 | AR26: =A26 -> 43942 | AS26: =AS25 -> 0.9 | AT26: 180 | AU26: =AU25 -> 1.1 | AV26: 94 | AW26: 2.9 | AX26: 123 | AY26: =AS26*AT26 -> 162 | AZ26: =AU26*AV26 -> 103.4 | BA26: =AW26*AX26 -> 356.7 | BB26: =AY26-AY25 -> 0 | BC26: =AZ26-AZ25 -> -8.8 | BD26: =BA26-BA25 -> -8.7 | BE26: =SUM(BB26:BD26) -> -17.5 | BF26: =SUM(I26-BE26) -> 17.5 | BG26: =SUM(I26-BF26) -> -17.5
A27: =ELEC!C24 -> 43943 | B27: 108473 | C27: =B27-B26 -> 0 | D27: =C27/27 -> 0 | E27: =SUM((C27*$E$4)+(7500/'EDl log'!$A$37)) -> 250 | G27: 596369 | H27: =G27-G26 -> 0 | I27: =C27+H27 -> 0 | J27: =IF(I27>0,E27/I27,0) -> 0 | K27: ='Swimming Pool quality check '!H27 -> 6061 | L27: =K27-K26 -> 11 | M27: =M26 -> 457.44 | N27: =SUM(M27-M26) -> 0 | O27: =O26 -> 529.52 | P27: =SUM(O27-O26) -> 0 | Q27: =SUM(P27+N27) -> 0 | T27: 4776 | U27: =SUM(T27-T26) -> 1 | V27: 403 | W27: =+V27-V26 -> 0 | X27: 142712 | Y27: =SUM(X27-X26) -> 0 | Z27: 94084 | AA27: =Z27-Z26 -> 44 | AB27: =AB26 -> 266 | AC27: =AC26 -> 671 | AD27: =AC27-AC26 -> 0 | AE27: 147.99 | AF27: =AE27-AE26 -> 0.45 | AG27: 1502.06 | AH27: =AG27-AG26 -> 0.64 | AI27: =AF27+AH27 -> 1.09 | AJ27: =+Z27-Z26 -> 44 | AK27: =SUM(Y27-L27) -> -11 | AL27: =SUM(AJ27-W27) -> 44 | AM27: ='General information '!D27 -> 21.5 | AN27: ='General information '!H27 -> 0 | AP27: ='General information '!J27 -> 85 | AR27: =A27 -> 43943 | AS27: =AS26 -> 0.9 | AT27: 168 | AU27: =AU26 -> 1.1 | AV27: 110 | AW27: 2.9 | AX27: 117 | AY27: =AS27*AT27 -> 151.2 | AZ27: =AU27*AV27 -> 121 | BA27: =AW27*AX27 -> 339.3 | BB27: =AY27-AY26 -> -10.8 | BC27: =AZ27-AZ26 -> 17.6 | BD27: =BA27-BA26 -> -17.4 | BE27: =SUM(BB27:BD27) -> -10.6 | BF27: =SUM(I27-BE27) -> 10.6 | BG27: =SUM(I27-BF27) -> -10.6
A28: =ELEC!C25 -> 43944 | B28: =B27 -> 108473 | C28: =B28-B27 -> 0 | D28: =C28/27 -> 0 | E28: =SUM((C28*$E$4)+(7500/'EDl log'!$A$37)) -> 250 | G28: 596432 | H28: =G28-G27 -> 63 | I28: =C28+H28 -> 63 | J28: =IF(I28>0,E28/I28,0) -> 3.968254 | K28: ='Swimming Pool quality check '!H28 -> 6066 | L28: =K28-K27 -> 5 | M28: =M27 -> 457.44 | N28: =SUM(M28-M27) -> 0 | O28: =O27 -> 529.52 | P28: =SUM(O28-O27) -> 0 | Q28: =SUM(P28+N28) -> 0 | T28: 4778 | U28: =SUM(T28-T27) -> 2 | V28: 404 | W28: =+V28-V27 -> 1 | X28: 142818 | Y28: =SUM(X28-X27) -> 106 | Z28: 94101 | AA28: =Z28-Z27 -> 17 | AB28: =AB27 -> 266 | AC28: =AC27 -> 671 | AD28: =AC28-AC27 -> 0 | AE28: 149.46 | AF28: =AE28-AE27 -> 1.47 | AG28: 1515.36 | AH28: =AG28-AG27 -> 13.3 | AI28: =AF28+AH28 -> 14.77 | AJ28: =+Z28-Z27 -> 17 | AK28: =SUM(Y28-L28) -> 101 | AL28: =SUM(AJ28-W28) -> 16 | AM28: ='General information '!D28 -> 19 | AN28: ='General information '!H28 -> 0 | AP28: ='General information '!J28 -> 0 | AR28: =A28 -> 43944 | AS28: =AS27 -> 0.9 | AT28: 173 | AU28: =AU27 -> 1.1 | AV28: 96 | AW28: 2.9 | AX28: 140 | AY28: =AS28*AT28 -> 155.7 | AZ28: =AU28*AV28 -> 105.6 | BA28: =AW28*AX28 -> 406 | BB28: =AY28-AY27 -> 4.5 | BC28: =AZ28-AZ27 -> -15.4 | BD28: =BA28-BA27 -> 66.7 | BE28: =SUM(BB28:BD28) -> 55.8 | BF28: =SUM(I28-BE28) -> 7.2 | BG28: =SUM(I28-BF28) -> 55.8
A29: =ELEC!C26 -> 43945 | B29: =B28 -> 108473 | C29: =B29-B28 -> 0 | D29: =C29/27 -> 0 | E29: =SUM((C29*$E$4)+(7500/'EDl log'!$A$37)) -> 250 | G29: 596432 | H29: =G29-G28 -> 0 | I29: =C29+H29 -> 0 | J29: =IF(I29>0,E29/I29,0) -> 0 | K29: ='Swimming Pool quality check '!H29 -> 6068 | L29: =K29-K28 -> 2 | M29: =M28 -> 457.44 | N29: =SUM(M29-M28) -> 0 | O29: =O28 -> 529.52 | P29: =SUM(O29-O28) -> 0 | Q29: =SUM(P29+N29) -> 0 | T29: =T28 -> 4778 | U29: =SUM(T29-T28) -> 0 | V29: =V28 -> 404 | W29: =+V29-V28 -> 0 | X29: 142820 | Y29: =SUM(X29-X28) -> 2 | Z29: =Z28 -> 94101 | AA29: =Z29-Z28 -> 0 | AB29: =AB28 -> 266 | AC29: =AC28 -> 671 | AD29: =AC29-AC28 -> 0 | AE29: =AE28 -> 149.46 | AF29: =AE29-AE28 -> 0 | AG29: 1515.86 | AH29: =AG29-AG28 -> 0.5 | AI29: =AF29+AH29 -> 0.5 | AJ29: =+Z29-Z28 -> 0 | AK29: =SUM(Y29-L29) -> 0 | AL29: =SUM(AJ29-W29) -> 0 | AM29: ='General information '!D29 -> 19.5 | AN29: ='General information '!H29 -> 0 | AP29: ='General information '!J29 -> 53 | AR29: =A29 -> 43945 | AS29: =AS28 -> 0.9 | AT29: 200 | AU29: =AU28 -> 1.1 | AV29: 82 | AW29: 2.9 | AX29: 133 | AY29: =AS29*AT29 -> 180 | AZ29: =AU29*AV29 -> 90.2 | BA29: =AW29*AX29 -> 385.7 | BB29: =AY29-AY28 -> 24.3 | BC29: =AZ29-AZ28 -> -15.4 | BD29: =BA29-BA28 -> -20.3 | BE29: =SUM(BB29:BD29) -> -11.4 | BF29: =SUM(I29-BE29) -> 11.4 | BG29: =SUM(I29-BF29) -> -11.4
A30: =ELEC!C27 -> 43946 | B30: 108473 | C30: =B30-B29 -> 0 | D30: =C30/27 -> 0 | E30: =SUM((C30*$E$4)+(7500/'EDl log'!$A$37)) -> 250 | G30: 596432 | H30: =G30-G29 -> 0 | I30: =C30+H30 -> 0 | J30: =IF(I30>0,E30/I30,0) -> 0 | K30: ='Swimming Pool quality check '!H30 -> 6068 | L30: =K30-K29 -> 0 | M30: =M29 -> 457.44 | N30: =SUM(M30-M29) -> 0 | O30: =O29 -> 529.52 | P30: =SUM(O30-O29) -> 0 | Q30: =SUM(P30+N30) -> 0 | T30: 4781 | U30: =SUM(T30-T29) -> 3 | V30: =V29 -> 404 | W30: =+V30-V29 -> 0 | X30: =X29 -> 142820 | Y30: =SUM(X30-X29) -> 0 | Z30: 94131 | AA30: =Z30-Z29 -> 30 | AB30: =AB29 -> 266 | AC30: =AC29 -> 671 | AD30: =AC30-AC29 -> 0 | AE30: =AE29 -> 149.46 | AF30: =AE30-AE29 -> 0 | AG30: 1516.46 | AH30: =AG30-AG29 -> 0.6 | AI30: =AF30+AH30 -> 0.6 | AJ30: =+Z30-Z29 -> 30 | AK30: =SUM(Y30-L30) -> 0 | AL30: =SUM(AJ30-W30) -> 30 | AM30: ='General information '!D30 -> 18 | AN30: ='General information '!H30 -> 0 | AP30: ='General information '!J30 -> 78 | AR30: =A30 -> 43946 | AS30: =AS29 -> 0.9 | AT30: 160 | AU30: =AU29 -> 1.1 | AV30: 91 | AW30: 2.9 | AX30: 128 | AY30: =AS30*AT30 -> 144 | AZ30: =AU30*AV30 -> 100.1 | BA30: =AW30*AX30 -> 371.2 | BB30: =AY30-AY29 -> -36 | BC30: =AZ30-AZ29 -> 9.9 | BD30: =BA30-BA29 -> -14.5 | BE30: =SUM(BB30:BD30) -> -40.6 | BF30: =SUM(I30-BE30) -> 40.6 | BG30: =SUM(I30-BF30) -> -40.6
A31: =ELEC!C28 -> 43947 | B31: =B30 -> 108473 | C31: =B31-B30 -> 0 | D31: =C31/27 -> 0 | E31: =SUM((C31*$E$4)+(7500/'EDl log'!$A$37)) -> 250 | G31: 596432 | H31: =G31-G30 -> 0 | I31: =C31+H31 -> 0 | J31: =IF(I31>0,E31/I31,0) -> 0 | K31: ='Swimming Pool quality check '!H31 -> 6070 | L31: =K31-K30 -> 2 | M31: =M30 -> 457.44 | N31: =SUM(M31-M30) -> 0 | O31: =O30 -> 529.52 | P31: =SUM(O31-O30) -> 0 | Q31: =SUM(P31+N31) -> 0 | T31: =T30 -> 4781 | U31: =SUM(T31-T30) -> 0 | V31: =V30 -> 404 | W31: =+V31-V30 -> 0 | X31: 142821 | Y31: =SUM(X31-X30) -> 1 | Z31: 94140 | AA31: =Z31-Z30 -> 9 | AB31: =AB30 -> 266 | AC31: =AC30 -> 671 | AD31: =AC31-AC30 -> 0 | AE31: =AE30 -> 149.46 | AF31: =AE31-AE30 -> 0 | AG31: =AG30 -> 1516.46 | AH31: =AG31-AG30 -> 0 | AI31: =AF31+AH31 -> 0 | AJ31: =+Z31-Z30 -> 9 | AK31: =SUM(Y31-L31) -> -1 | AL31: =SUM(AJ31-W31) -> 9 | AM31: ='General information '!D31 -> 19 | AN31: ='General information '!H31 -> 0 | AP31: ='General information '!J31 -> 59 | AR31: =A31 -> 43947 | AS31: =AS30 -> 0.9 | AT31: 142 | AU31: =AU30 -> 1.1 | AV31: 108 | AW31: 2.9 | AX31: 125.5 | AY31: =AS31*AT31 -> 127.8 | AZ31: =AU31*AV31 -> 118.8 | BA31: =AW31*AX31 -> 363.95 | BB31: =AY31-AY30 -> -16.2 | BC31: =AZ31-AZ30 -> 18.7 | BD31: =BA31-BA30 -> -7.25 | BE31: =SUM(BB31:BD31) -> -4.75 | BF31: =SUM(I31-BE31) -> 4.75 | BG31: =SUM(I31-BF31) -> -4.75
A32: =ELEC!C29 -> 43948 | B32: 108473 | C32: =B32-B31 -> 0 | D32: =C32/27 -> 0 | E32: =SUM((C32*$E$4)+(7500/'EDl log'!$A$37)) -> 250 | G32: 596433 | H32: =G32-G31 -> 1 | I32: =C32+H32 -> 1 | J32: =IF(I32>0,E32/I32,0) -> 250 | K32: ='Swimming Pool quality check '!H32 -> 6070 | L32: =K32-K31 -> 0 | M32: =M31 -> 457.44 | N32: =SUM(M32-M31) -> 0 | O32: =O31 -> 529.52 | P32: =SUM(O32-O31) -> 0 | Q32: =SUM(P32+N32) -> 0 | T32: 4782 | U32: =SUM(T32-T31) -> 1 | V32: 404 | W32: =+V32-V31 -> 0 | X32: 142821 | Y32: =SUM(X32-X31) -> 0 | Z32: 94140 | AA32: =Z32-Z31 -> 0 | AB32: =AB31 -> 266 | AC32: =AC31 -> 671 | AD32: =AC32-AC31 -> 0 | AE32: 149.46 | AF32: =AE32-AE31 -> 0 | AG32: 1516.96 | AH32: =AG32-AG31 -> 0.5 | AI32: =AF32+AH32 -> 0.5 | AJ32: =+Z32-Z31 -> 0 | AK32: =SUM(Y32-L32) -> 0 | AL32: =SUM(AJ32-W32) -> 0 | AM32: ='General information '!D32 -> 18 | AN32: ='General information '!H32 -> 0 | AP32: ='General information '!J32 -> 55 | AR32: =A32 -> 43948 | AS32: =AS31 -> 0.9 | AT32: 155 | AU32: =AU31 -> 1.1 | AV32: 86 | AW32: 2.9 | AX32: 116 | AY32: =AS32*AT32 -> 139.5 | AZ32: =AU32*AV32 -> 94.6 | BA32: =AW32*AX32 -> 336.4 | BB32: =AY32-AY31 -> 11.7 | BC32: =AZ32-AZ31 -> -24.2 | BD32: =BA32-BA31 -> -27.55 | BE32: =SUM(BB32:BD32) -> -40.05 | BF32: =SUM(I32-BE32) -> 41.05 | BG32: =SUM(I32-BF32) -> -40.05
A33: =ELEC!C30 -> 43949 | B33: 108473 | C33: =B33-B32 -> 0 | D33: =C33/27 -> 0 | E33: =SUM((C33*$E$4)+(7500/'EDl log'!$A$37)) -> 250 | G33: 596433 | H33: =G33-G32 -> 0 | I33: =C33+H33 -> 0 | J33: =IF(I33>0,E33/I33,0) -> 0 | K33: ='Swimming Pool quality check '!H33 -> 6072 | L33: =K33-K32 -> 2 | M33: =M32 -> 457.44 | N33: =SUM(M33-M32) -> 0 | O33: =O32 -> 529.52 | P33: =SUM(O33-O32) -> 0 | Q33: =SUM(P33+N33) -> 0 | T33: 4784 | U33: =SUM(T33-T32) -> 2 | V33: =V32 -> 404 | W33: =+V33-V32 -> 0 | X33: 142861 | Y33: =SUM(X33-X32) -> 40 | Z33: 94174 | AA33: =Z33-Z32 -> 34 | AB33: =AB32 -> 266 | AC33: =AC32 -> 671 | AD33: =AC33-AC32 -> 0 | AE33: 149.46 | AF33: =AE33-AE32 -> 0 | AG33: 1517.41 | AH33: =AG33-AG32 -> 0.45 | AI33: =AF33+AH33 -> 0.45 | AJ33: =+Z33-Z32 -> 34 | AK33: =SUM(Y33-L33) -> 38 | AL33: =SUM(AJ33-W33) -> 34 | AM33: ='General information '!D33 -> 18.5 | AN33: ='General information '!H33 -> 0 | AP33: ='General information '!J33 -> 54 | AR33: =A33 -> 43949 | AS33: =AS32 -> 0.9 | AT33: 96 | AU33: =AU32 -> 1.1 | AV33: 95 | AW33: 2.9 | AX33: 122 | AY33: =AS33*AT33 -> 86.4 | AZ33: =AU33*AV33 -> 104.5 | BA33: =AW33*AX33 -> 353.8 | BB33: =AY33-AY32 -> -53.1 | BC33: =AZ33-AZ32 -> 9.9 | BD33: =BA33-BA32 -> 17.4 | BE33: =SUM(BB33:BD33) -> -25.8 | BF33: =SUM(I33-BE33) -> 25.8 | BG33: =SUM(I33-BF33) -> -25.8
A34: =ELEC!C31 -> 43950 | B34: 108473 | C34: =B34-B33 -> 0 | D34: =C34/27 -> 0 | E34: =SUM((C34*$E$4)+(7500/'EDl log'!$A$37)) -> 250 | G34: 596433 | H34: =G34-G33 -> 0 | I34: =C34+H34 -> 0 | J34: =IF(I34>0,E34/I34,0) -> 0 | K34: ='Swimming Pool quality check '!H34 -> 6083 | L34: =K34-K33 -> 11 | M34: =M33 -> 457.44 | N34: =SUM(M34-M33) -> 0 | O34: =O33 -> 529.52 | P34: =SUM(O34-O33) -> 0 | Q34: =SUM(P34+N34) -> 0 | T34: 4784 | U34: =SUM(T34-T33) -> 0 | V34: 404 | W34: =+V34-V33 -> 0 | X34: 142861 | Y34: =SUM(X34-X33) -> 0 | Z34: 94174 | AA34: =Z34-Z33 -> 0 | AB34: =AB33 -> 266 | AC34: =AC33 -> 671 | AD34: =AC34-AC33 -> 0 | AE34: 149.46 | AF34: =AE34-AE33 -> 0 | AG34: 1517.44 | AH34: =AG34-AG33 -> 0.03 | AI34: =AF34+AH34 -> 0.03 | AJ34: =+Z34-Z33 -> 0 | AK34: =SUM(Y34-L34) -> -11 | AL34: =SUM(AJ34-W34) -> 0 | AM34: ='General information '!D34 -> 19 | AN34: ='General information '!H34 -> 0 | AP34: ='General information '!J34 -> 98 | AR34: =A34 -> 43950 | AS34: =AS33 -> 0.9 | AT34: 189 | AU34: =AU33 -> 1.1 | AV34: 87 | AW34: 2.9 | AX34: 118 | AY34: =AS34*AT34 -> 170.1 | AZ34: =AU34*AV34 -> 95.7 | BA34: =AW34*AX34 -> 342.2 | BB34: =AY34-AY33 -> 83.7 | BC34: =AZ34-AZ33 -> -8.8 | BD34: =BA34-BA33 -> -11.6 | BE34: =SUM(BB34:BD34) -> 63.3 | BF34: =SUM(I34-BE34) -> -63.3 | BG34: =SUM(I34-BF34) -> 63.3
A35: =ELEC!C32 -> 43951 | B35: =B34 -> 108473 | C35: =B35-B34 -> 0 | D35: =C35/27 -> 0 | E35: =SUM((C35*$E$4)+(7500/'EDl log'!$A$37)) -> 250 | G35: =G34 -> 596433 | H35: =G35-G34 -> 0 | I35: =C35+H35 -> 0 | J35: =IF(I35>0,E35/I35,0) -> 0 | K35: ='Swimming Pool quality check '!H35 -> 6084 | L35: =K35-K34 -> 1 | M35: =M34 -> 457.44 | N35: =SUM(M35-M34) -> 0 | O35: =O34 -> 529.52 | P35: =SUM(O35-O34) -> 0 | Q35: =SUM(P35+N35) -> 0 | T35: 4785 | U35: =SUM(T35-T34) -> 1 | V35: =V34 -> 404 | W35: =+V35-V34 -> 0 | X35: =X34 -> 142861 | Y35: =SUM(X35-X34) -> 0 | Z35: =Z34 -> 94174 | AA35: =Z35-Z34 -> 0 | AB35: =AB34 -> 266 | AC35: =AC34 -> 671 | AD35: =AC35-AC34 -> 0 | AE35: =AE34 -> 149.46 | AF35: =AE35-AE34 -> 0 | AG35: 1517.45 | AH35: =AG35-AG34 -> 0.01 | AI35: =AF35+AH35 -> 0.01 | AJ35: =+Z35-Z34 -> 0 | AK35: =SUM(Y35-L35) -> -1 | AL35: =SUM(AJ35-W35) -> 0 | AM35: ='General information '!D35 -> 21 | AN35: ='General information '!H35 -> 0 | AP35: ='General information '!J35 -> 78 | AR35: =A35 -> 43951 | AS35: =AS34 -> 0.9 | AT35: =AT34 -> 189 | AU35: =AU34 -> 1.1 | AV35: 75 | AW35: 2.9 | AX35: 117 | AY35: =AS35*AT35 -> 170.1 | AZ35: =AU35*AV35 -> 82.5 | BA35: =AW35*AX35 -> 339.3 | BB35: =AY35-AY34 -> 0 | BC35: =AZ35-AZ34 -> -13.2 | BD35: =BA35-BA34 -> -2.9 | BE35: =SUM(BB35:BD35) -> -16.1 | BF35: =SUM(I35-BE35) -> 16.1 | BG35: =SUM(I35-BF35) -> -16.1
C36: =SUM(C6:C35) -> 0 | D36: =SUM(D6:D35) -> 0 | F36: =SUM(F6:F35) -> 0 | H36: =SUM(H6:H35) -> 1340 | I36: =SUM(I6:I35) -> 1340 | L36: =SUM(L7:L35) -> 810 | Q36: =SUM(Q5:Q35) -> 0 | U36: =SUM(U6:U35) -> 43 | Y36: =SUM(Y35,Y33,Y31,Y29,Y27,Y25,Y23,Y21,Y19,Y17,Y15,Y13,Y11,Y9,Y7+#REF!) -> #REF! | AJ36: =SUM(AJ6:AJ35) -> 451 | AK36: =SUM(Y36-L36) -> #REF! | AL36: =SUM(AL6:AL35) -> 448 | AT36: =#REF! -> #REF!
C37: =+C36*1.66 -> 0 | E37: =SUM(E6:E35) -> 7500 | F37: =SUM(F6:F35) -> 0 | H37: 7500 | I37: =SUM('General information '!G36/WATER!I36) -> 0.080773134 | O37: =SUM(Q36+I36) -> 1340 | Z37: =SUM(Y36:AJ36) -> #REF! | AK37: =SUM(Y37-L37) -> 0
B38: =9*27 -> 243 | D38: =SUM(D21:D35) -> 0 | F38: =SUM(F6:F35) -> 0 | G38: =SUM(I36) -> 1340 | H38: =SUM(H37+C37) -> 7500 | K38: =SUM(H38/G38) -> 5.5970149 | AJ38: =SUM(C37-AK37) -> 0 | AM38: =SUM(AJ38/AO37) -> #DIV/0!

Sheet graphic

Sheet General information 
A1: GENERAL & HOTEL'S INFORMATION SHEET
B4: Max Temp | C4: MIN TEMP | D4: AVE TEMP | E4: AVE Humidity | F4: AVE OCC | G4: # of OCC Rooms | H4: Ball room | I4: Meeting rooms | J4: Outlets | K4: Total covers | L4: # of permenant Emp | M4: # of casuals | N4: Total # of EMP | O4: # of EMP/OCC Room
A5: =ELEC!C2 -> 43921 | B5: ='[1]General information '!B36 -> 30 | C5: ='[1]General information '!C36 -> 18 | D5: ='[1]General information '!D36 -> 24 | E5: ='[1]General information '!E36 -> 0.46 | F5: ='[1]General information '!F36 -> 0.0087 | G5: ='[1]General information '!G36 -> 2.001 | H5: ='[1]General information '!H36 -> 0 | I5: ='[1]General information '!I36 -> 0 | ... O5: ='[1]General information '!O36 -> 0
A6: =ELEC!C3 -> 43922 | B6: 19 | C6: 14 | D6: =(B6+C6)/2 -> 16.5 | E6: 0.68 | F6: 0.0174 | G6: 2 | H6: 0 | J6: 25 | K6: =+J6+H6 -> 25
A7: =ELEC!C4 -> 43923 | B7: 19 | C7: 15 | D7: =(B7+C7)/2 -> 17 | E7: 0.68 | F7: 0.0087 | G7: 2 | H7: 0 | J7: 37 | K7: =+J7+H7 -> 37
A8: =ELEC!C5 -> 43924 | B8: 20 | C8: 14 | D8: =(B8+C8)/2 -> 17 | E8: 0.65 | F8: 0.0087 | G8: =F8*230 -> 2.001 | H8: 0 | J8: 33 | K8: =+J8+H8 -> 33
A9: =ELEC!C6 -> 43925 | B9: 23 | C9: 14 | D9: =(B9+C9)/2 -> 18.5 | E9: 0.31 | F9: 0.013 | G9: =F9*230 -> 2.99 | J9: 39 | K9: =+J9+H9 -> 39
A10: =ELEC!C7 -> 43926 | B10: 34 | C10: 17 | D10: =(B10+C10)/2 -> 25.5 | E10: 0.43 | F10: 0.0304 | G10: =F10*230 -> 6.992 | H10: 0 | J10: 68 | K10: =+J10+H10 -> 68
A11: =ELEC!C8 -> 43927 | B11: 19 | C11: 17 | D11: =(B11+C11)/2 -> 18 | E11: 0.5 | F11: 0.0087 | G11: =F11*230 -> 2.001 | J11: 31 | K11: =+J11+H11 -> 31
A12: =ELEC!C9 -> 43928 | B12: 20 | C12: 16 | D12: =(B12+C12)/2 -> 18 | E12: 0.5 | F12: 0.0087 | G12: =F12*230 -> 2.001 | J12: 31 | K12: =+J12+H12 -> 31
A13: =ELEC!C10 -> 43929 | B13: 19 | C13: 15 | D13: =(B13+C13)/2 -> 17 | E13: 0.55 | F13: 0.0478 | G13: =F13*230 -> 10.994 | J13: 48 | K13: =+J13+H13 -> 48
A14: =ELEC!C11 -> 43930 | B14: 18 | C14: 15 | D14: =(B14+C14)/2 -> 16.5 | E14: 0.87 | F14: 0.0217 | G14: =F14*230 -> 4.991 | J14: 25 | K14: =+J14+H14 -> 25
A15: =ELEC!C12 -> 43931 | B15: 16 | C15: 13 | D15: =(B15+C15)/2 -> 14.5 | E15: 0.85 | F15: 0.0087 | G15: =F15*230 -> 2.001 | H15: 0 | J15: 52 | K15: =+J15+H15 -> 52
A16: =ELEC!C13 -> 43932 | B16: 17 | C16: 14 | D16: =(B16+C16)/2 -> 15.5 | E16: 0.8 | F16: 0.0174 | G16: =F16*230 -> 4.002 | H16: 0 | J16: 60 | K16: =+J16+H16 -> 60
A17: =ELEC!C14 -> 43933 | B17: 20 | C17: 14 | D17: =(B17+C17)/2 -> 17 | E17: 0.72 | F17: 0.013 | G17: =F17*230 -> 2.99 | H17: 0 | J17: 71 | K17: =+J17+H17 -> 71
A18: =ELEC!C15 -> 43934 | B18: 21 | C18: 15 | D18: =(B18+C18)/2 -> 18 | E18: 0.68 | F18: 0.0348 | G18: =F18*230 -> 8.004 | H18: 0 | J18: 58 | K18: =+J18+H18 -> 58
A19: =ELEC!C16 -> 43935 | B19: 22 | C19: 16 | D19: =(B19+C19)/2 -> 19 | E19: 0.65 | F19: 0.0217 | G19: =F19*230 -> 4.991 | J19: 91 | K19: =+J19+H19 -> 91
A20: =ELEC!C17 -> 43936 | B20: 20 | C20: 16 | D20: =(B20+C20)/2 -> 18 | E20: 0.63 | F20: 0.013 | G20: =F20*230 -> 2.99 | J20: 50 | K20: =+J20+H20 -> 50
A21: =ELEC!C18 -> 43937 | B21: 20 | C21: 15 | D21: =(B21+C21)/2 -> 17.5 | E21: 0.84 | F21: 0.01 | G21: =F21*230 -> 2.3 | J21: 61 | K21: =+J21+H21 -> 61
A22: =ELEC!C19 -> 43938 | B22: 22 | C22: 17 | D22: =(B22+C22)/2 -> 19.5 | E22: 0.73 | F22: 0.0087 | G22: =F22*230 -> 2.001 | J22: 83 | K22: =+J22+H22 -> 83
A23: =ELEC!C20 -> 43939 | B23: 24 | C23: 17 | D23: =(B23+C23)/2 -> 20.5 | E23: 0.72 | F23: 0.013 | G23: =F23*230 -> 2.99 | J23: 68 | K23: =+J23+H23 -> 68
A24: =ELEC!C21 -> 43940 | B24: 24 | C24: 17 | D24: =(B24+C24)/2 -> 20.5 | E24: 0.65 | F24: 0.0217 | G24: =F24*230 -> 4.991 | H24: 0 | J24: 41 | K24: =+J24+H24 -> 41
A25: =ELEC!C22 -> 43941 | B25: 23 | C25: 18 | D25: =(B25+C25)/2 -> 20.5 | E25: 0.83 | F25: 0.0087 | G25: =F25*230 -> 2.001 | J25: 34 | K25: =+J25+H25 -> 34
A26: =ELEC!C23 -> 43942 | B26: 24 | C26: 18 | D26: =(B26+C26)/2 -> 21 | E26: 0.7 | F26: 0.0087 | G26: =F26*230 -> 2.001 | J26: 58 | K26: =+J26+H26 -> 58
A27: =ELEC!C24 -> 43943 | B27: 25 | C27: 18 | D27: =(B27+C27)/2 -> 21.5 | E27: 0.8 | F27: 0.0087 | G27: =F27*230 -> 2.001 | J27: 85 | K27: =+J27+H27+I27 -> 85
A28: =ELEC!C25 -> 43944 | B28: 23 | C28: 15 | D28: =(B28+C28)/2 -> 19 | E28: 0.8 | F28: 0.0087 | G28: =F28*230 -> 2.001 | H28: 0 | K28: =+J28+H28+I28 -> 0
A29: =ELEC!C26 -> 43945 | B29: 23 | C29: 16 | D29: =(B29+C29)/2 -> 19.5 | E29: 0.83 | F29: 0.0087 | G29: =F29*230 -> 2.001 | H29: 0 | J29: 53 | K29: =+J29+H29+I29 -> 53
A30: =ELEC!C27 -> 43946 | B30: 22 | C30: 14 | D30: =(B30+C30)/2 -> 18 | E30: 0.85 | F30: 0.0174 | G30: =F30*230 -> 4.002 | H30: 0 | J30: 78 | K30: =+J30+H30+I30 -> 78
A31: =ELEC!C28 -> 43947 | B31: 21 | C31: 17 | D31: =(B31+C31)/2 -> 19 | E31: 0.67 | F31: 0.0348 | G31: =F31*230 -> 8.004 | H31: 0 | J31: 59 | K31: =+J31+H31+I31 -> 59
A32: =ELEC!C29 -> 43948 | B32: 20 | C32: 16 | D32: =(B32+C32)/2 -> 18 | E32: 0.68 | F32: 0.0087 | G32: =F32*230 -> 2.001 | J32: 55 | K32: =+J32+H32+I32 -> 55
A33: =ELEC!C30 -> 43949 | B33: 21 | C33: 16 | D33: =(B33+C33)/2 -> 18.5 | E33: 0.7 | F33: 0.0174 | G33: =F33*230 -> 4.002 | J33: 54 | K33: =+J33+H33+I33 -> 54
A34: =ELEC!C31 -> 43950 | B34: 21 | C34: 17 | D34: =(B34+C34)/2 -> 19 | E34: 0.69 | F34: 0.0174 | G34: =F34*230 -> 4.002 | J34: 98 | K34: =+J34+H34+I34 -> 98
A35: =ELEC!C32 -> 43951 | B35: 23 | C35: 19 | D35: =(B35+C35)/2 -> 21 | E35: 0.75 | F35: 0.013 | G35: =F35*230 -> 2.99 | H35: 0 | J35: 78 | K35: =+J35+H35+I35 -> 78
F36: =AVERAGE(F6:F35) -> 0.015976667 | G36: =SUM(G6:G35) -> 108.236
D37: =SUM(D6:D35)/'EDl log'!A35 -> 18.633333
I40: http://www.accuweather.com/en/lb/lebanon-weather

Sheet tanks
B2: Tank 1 | D2: Tank 2 | F2: Tank 3 | H2: Tank 4 | J2: Tank 5 | L2: Tank 6 | N2: Tank 7 | P2: Tank 8 | R2: Tank 9 | T2: Tank 10 | V2: Tank 11 | Z2: Tank 1 | AB2: Tank 2 | AD2: Tank 3 | AF2: Tank 4 | AH2: Tank 5 | AJ2: Tank 6 | AL2: Tank 7
B3: 6670 | D3: =SUM(B3) -> 6670 | F3: =SUM(D3) -> 6670 | H3: =SUM(F3) -> 6670 | J3: =SUM(H3) -> 6670 | L3: =SUM(J3) -> 6670 | N3: =SUM(L3) -> 6670 | P3: =SUM(N3) -> 6670 | R3: =SUM(P3) -> 6670 | T3: =SUM(R3) -> 6670 | V3: =SUM(T3) -> 6670 | W3: =SUM(B3:V3) -> 73370 | Z3: 2800 | AB3: 2800 | AD3: 2800 | AF3: 2800 | AH3: 2800 | AJ3: 2800 | AL3: 2800 | AM3: =SUM(Z3:AL3) -> 19600 | AO3: =SUM(AM3+W3) -> 92970 | AR3: Total sotck | AS3: Diesel Cons Per day | AT3: Diesel Delivery | BE3: Genset Co | BF3: Steam | BG3: Boil | BH3: Outdoor temperature
B4: =B3/310 -> 21.516129 | D4: =SUM(B4) -> 21.516129 | F4: =SUM(D4) -> 21.516129 | H4: =SUM(F4) -> 21.516129 | J4: =SUM(H4) -> 21.516129 | L4: =SUM(J4) -> 21.516129 | N4: =SUM(L4) -> 21.516129 | P4: =SUM(N4) -> 21.516129 | R4: =SUM(P4) -> 21.516129 | T4: =SUM(R4) -> 21.516129 | V4: =SUM(T4) -> 21.516129 | Z4: =Z3/280 -> 10 | AA4: =AA3/280 -> 0 | AB4: =AB3/280 -> 10 | AC4: =AC3/280 -> 0 | AD4: =AD3/280 -> 10 | AE4: =AE3/280 -> 0 | AF4: =AF3/280 -> 10 | AG4: =AG3/280 -> 0 | ... AL4: =AL3/280 -> 10 | AT4: Delivery | AU4: Cost /L | AW4: Boiler+Steam | AX4: Generator | AZ4: Occupancy | BA4: AVE TEPM | BB4: AVE Humidity
A5: =ELEC!C2 -> 43921 | B5: =[1]tanks!B36 -> 252 | C5: =[1]tanks!C36 -> 5422.0645 | D5: =[1]tanks!D36 -> 252 | E5: =[1]tanks!E36 -> 5422.0645 | F5: =[1]tanks!F36 -> 252 | G5: =[1]tanks!G36 -> 5422.0645 | H5: =[1]tanks!H36 -> 252 | I5: =[1]tanks!I36 -> 5422.0645 | ... AO5: =[1]tanks!AO36 -> 18060 | AP5: =[2]tanks!AP34 -> 0 | AQ5: =[1]tanks!AQ36 -> 0.83578261 | AR5: =[1]tanks!AR36 -> 77702.71 | AS5: =[1]tanks!AS36 -> 387.03226 | AT5: =[1]tanks!AT36 -> 10040 | AU5: =[1]tanks!AU36 -> 0.3845 | AV5: =[1]tanks!AV36 -> 0.3845 | AW5: =[1]tanks!AW36 -> -197 | AX5: =[1]tanks!AX36 -> 584.03226 | ... BH5: =[1]tanks!BH36 -> 0
A6: =ELEC!C3 -> 43922 | B6: ='B5'!B5 -> 247 | C6: =B6*$B$4 -> 5314.4839 | D6: =SUM(B6) -> 247 | E6: =D6*$B$4 -> 5314.4839 | F6: =SUM(D6) -> 247 | G6: =F6*$B$4 -> 5314.4839 | H6: =SUM(F6) -> 247 | I6: =H6*$B$4 -> 5314.4839 | J6: =SUM(H6) -> 247 | K6: =J6*$B$4 -> 5314.4839 | L6: =SUM(J6) -> 247 | M6: =L6*$B$4 -> 5314.4839 | N6: =SUM(L6) -> 247 | O6: =N6*$B$4 -> 5314.4839 | P6: =SUM(N6) -> 247 | Q6: =P6*$B$4 -> 5314.4839 | R6: =SUM(P6) -> 247 | S6: =R6*$B$4 -> 5314.4839 | T6: =SUM(R6) -> 247 | U6: =T6*$B$4 -> 5314.4839 | V6: =SUM(T6) -> 247 | W6: =V6*$B$4 -> 5314.4839 | X6: =SUM(Y6/73370) -> 0.79677419 | Y6: =SUM(C6+E6+G6+I6+K6+M6+O6+Q6+S6+U6+W6) -> 58459.323 | Z6: ='B5'!C5 -> 253 | AA6: =SUM(Z6*$Z$4) -> 2530 | AB6: =SUM(Z6) -> 253 | AC6: =SUM(AB6*$Z$4) -> 2530 | AD6: =SUM(AB6) -> 253 | AE6: =SUM(AD6*$Z$4) -> 2530 | AF6: =SUM(AD6) -> 253 | AG6: =SUM(AF6*$Z$4) -> 2530 | AH6: =SUM(AF6) -> 253 | AI6: =SUM(AH6*$Z$4) -> 2530 | AJ6: =SUM(AH6) -> 253 | AK6: =SUM(AJ6*$Z$4) -> 2530 | AL6: =SUM(AJ6) -> 253 | AM6: =SUM(AL6*$Z$4) -> 2530 | AN6: =SUM(AO6/19600) -> 0.90357143 | AO6: =SUM(AA6+AC6+AE6+AG6+AI6+AK6+AM6) -> 17710 | AQ6: =SUM(AR6/92970) -> 0.81928926 | AR6: =SUM(AO6+Y6) -> 76169.323 | AS6: =SUM(AR6-AR5-AT6) -> -1533.3871 | AV6: =IF(AT6>0,AU6,AV5) -> 0.3845 | AW6: =-SUM('B5'!AI5) -> -267 | AX6: =-SUM(AW6-AS6) -> -1266.3871 | AY6: =SUM(AX6+AW6) -> -1533.3871 | AZ6: =ELEC!A3 -> 0.0174 | BA6: ='General information '!D6 -> 16.5 | BB6: =SUM('General information '!E6) -> 0.68 | BC6: =IF(AR3>=AR6,0,1) -> 0 | BD6: 19222 | BE6: =(305/1185)*ELEC!Q4 -> 406.92405 | BG6: =#REF!-BE6 -> #REF! | BH6: 21
A7: =ELEC!C4 -> 43923 | B7: ='B5'!B6 -> 243 | C7: =B7*$B$4 -> 5228.4194 | D7: =SUM(B7) -> 243 | E7: =D7*$B$4 -> 5228.4194 | F7: =SUM(D7) -> 243 | G7: =F7*$B$4 -> 5228.4194 | H7: =SUM(F7) -> 243 | I7: =H7*$B$4 -> 5228.4194 | J7: =SUM(H7) -> 243 | K7: =J7*$B$4 -> 5228.4194 | L7: =SUM(J7) -> 243 | M7: =L7*$B$4 -> 5228.4194 | N7: =SUM(L7) -> 243 | O7: =N7*$B$4 -> 5228.4194 | P7: =SUM(N7) -> 243 | Q7: =P7*$B$4 -> 5228.4194 | R7: =SUM(P7) -> 243 | S7: =R7*$B$4 -> 5228.4194 | T7: =SUM(R7) -> 243 | U7: =T7*$B$4 -> 5228.4194 | V7: =SUM(T7) -> 243 | W7: =V7*$B$4 -> 5228.4194 | X7: =SUM(Y7/73370) -> 0.78387097 | Y7: =SUM(C7+E7+G7+I7+K7+M7+O7+Q7+S7+U7+W7) -> 57512.613 | Z7: ='B5'!C6 -> 249 | AA7: =SUM(Z7*$Z$4) -> 2490 | AB7: =SUM(Z7) -> 249 | AC7: =SUM(AB7*$Z$4) -> 2490 | AD7: =SUM(AB7) -> 249 | AE7: =SUM(AD7*$Z$4) -> 2490 | AF7: =SUM(AD7) -> 249 | AG7: =SUM(AF7*$Z$4) -> 2490 | AH7: =SUM(AF7) -> 249 | AI7: =SUM(AH7*$Z$4) -> 2490 | AJ7: =SUM(AH7) -> 249 | AK7: =SUM(AJ7*$Z$4) -> 2490 | AL7: =SUM(AJ7) -> 249 | AM7: =SUM(AL7*$Z$4) -> 2490 | AN7: =SUM(AO7/19600) -> 0.88928571 | AO7: =SUM(AA7+AC7+AE7+AG7+AI7+AK7+AM7) -> 17430 | AQ7: =SUM(AR7/92970) -> 0.80609458 | AR7: =SUM(AO7+Y7) -> 74942.613 | AS7: =SUM(AR7-AR6-AT7) -> -1226.7097 | AV7: =IF(AT7>0,AU7,AV6) -> 0.3845 | AW7: =-SUM('B5'!AI6) -> -307 | AX7: =-SUM(AW7-AS7) -> -919.70968 | AY7: =SUM(AX7+AW7) -> -1226.7097 | AZ7: =ELEC!A4 -> 0.0087 | BA7: ='General information '!D7 -> 17 | BB7: =SUM('General information '!E7) -> 0.68 | BC7: 0 | BD7: 19222 | BE7: =(305/1185)*ELEC!Q5 -> 324.81857 | BG7: =#REF!-BE7 -> #REF! | BH7: 19
A8: =ELEC!C5 -> 43924 | B8: ='B5'!B7 -> 241 | C8: =B8*$B$4 -> 5185.3871 | D8: =SUM(B8) -> 241 | E8: =D8*$B$4 -> 5185.3871 | F8: =SUM(D8) -> 241 | G8: =F8*$B$4 -> 5185.3871 | H8: =SUM(F8) -> 241 | I8: =H8*$B$4 -> 5185.3871 | J8: =SUM(H8) -> 241 | K8: =J8*$B$4 -> 5185.3871 | L8: =SUM(J8) -> 241 | M8: =L8*$B$4 -> 5185.3871 | N8: =SUM(L8) -> 241 | O8: =N8*$B$4 -> 5185.3871 | P8: =SUM(N8) -> 241 | Q8: =P8*$B$4 -> 5185.3871 | R8: =SUM(P8) -> 241 | S8: =R8*$B$4 -> 5185.3871 | T8: =SUM(R8) -> 241 | U8: =T8*$B$4 -> 5185.3871 | V8: =SUM(T8) -> 241 | W8: =V8*$B$4 -> 5185.3871 | X8: =SUM(Y8/73370) -> 0.77741935 | Y8: =SUM(C8+E8+G8+I8+K8+M8+O8+Q8+S8+U8+W8) -> 57039.258 | Z8: ='B5'!C7 -> 246 | AA8: =SUM(Z8*$Z$4) -> 2460 | AB8: =SUM(Z8) -> 246 | AC8: =SUM(AB8*$Z$4) -> 2460 | AD8: =SUM(AB8) -> 246 | AE8: =SUM(AD8*$Z$4) -> 2460 | AF8: =SUM(AD8) -> 246 | AG8: =SUM(AF8*$Z$4) -> 2460 | AH8: =SUM(AF8) -> 246 | AI8: =SUM(AH8*$Z$4) -> 2460 | AJ8: =SUM(AH8) -> 246 | AK8: =SUM(AJ8*$Z$4) -> 2460 | AL8: =SUM(AJ8) -> 246 | AM8: =SUM(AL8*$Z$4) -> 2460 | AN8: =SUM(AO8/19600) -> 0.87857143 | AO8: =SUM(AA8+AC8+AE8+AG8+AI8+AK8+AM8) -> 17220 | AQ8: =SUM(AR8/92970) -> 0.79874431 | AR8: =SUM(AO8+Y8) -> 74259.258 | AS8: =SUM(AR8-AR7-AT8) -> -683.35484 | AV8: =IF(AT8>0,AU8,AV7) -> 0.3845 | AW8: =-SUM('B5'!AI7) -> -351 | AX8: =-SUM(AW8-AS8) -> -332.35484 | AY8: =SUM(AX8+AW8) -> -683.35484 | AZ8: =ELEC!A5 -> 0.0087 | BA8: ='General information '!D8 -> 17 | BB8: =SUM('General information '!E8) -> 0.65 | BC8: =IF(AR7>=AR8,0,1) -> 0 | BD8: 19222 | BE8: =(305/1185)*ELEC!Q6 -> 422.62447 | BG8: =#REF!-BE8 -> #REF! | BH8: 16
A9: =ELEC!C6 -> 43925 | B9: ='B5'!B8 -> 239 | C9: =B9*$B$4 -> 5142.3548 | D9: =SUM(B9) -> 239 | E9: =D9*$B$4 -> 5142.3548 | F9: =SUM(D9) -> 239 | G9: =F9*$B$4 -> 5142.3548 | H9: =SUM(F9) -> 239 | I9: =H9*$B$4 -> 5142.3548 | J9: =SUM(H9) -> 239 | K9: =J9*$B$4 -> 5142.3548 | L9: =SUM(J9) -> 239 | M9: =L9*$B$4 -> 5142.3548 | N9: =SUM(L9) -> 239 | O9: =N9*$B$4 -> 5142.3548 | P9: =SUM(N9) -> 239 | Q9: =P9*$B$4 -> 5142.3548 | R9: =SUM(P9) -> 239 | S9: =R9*$B$4 -> 5142.3548 | T9: =SUM(R9) -> 239 | U9: =T9*$B$4 -> 5142.3548 | V9: =SUM(T9) -> 239 | W9: =V9*$B$4 -> 5142.3548 | X9: =SUM(Y9/73370) -> 0.77096774 | Y9: =SUM(C9+E9+G9+I9+K9+M9+O9+Q9+S9+U9+W9) -> 56565.903 | Z9: ='B5'!C8 -> 244 | AA9: =SUM(Z9*$Z$4) -> 2440 | AB9: =SUM(Z9) -> 244 | AC9: =SUM(AB9*$Z$4) -> 2440 | AD9: =SUM(AB9) -> 244 | AE9: =SUM(AD9*$Z$4) -> 2440 | AF9: =SUM(AD9) -> 244 | AG9: =SUM(AF9*$Z$4) -> 2440 | AH9: =SUM(AF9) -> 244 | AI9: =SUM(AH9*$Z$4) -> 2440 | AJ9: =SUM(AH9) -> 244 | AK9: =SUM(AJ9*$Z$4) -> 2440 | AL9: =SUM(AJ9) -> 244 | AM9: =SUM(AL9*$Z$4) -> 2440 | AN9: =SUM(AO9/19600) -> 0.87142857 | AO9: =SUM(AA9+AC9+AE9+AG9+AI9+AK9+AM9) -> 17080 | AQ9: =SUM(AR9/92970) -> 0.79214696 | AR9: =SUM(AO9+Y9) -> 73645.903 | AS9: =SUM(AR9-AR8-AT9) -> -613.35484 | AV9: =IF(AT9>0,AU9,AV8) -> 0.3845 | AW9: =-SUM('B5'!AI8) -> -271 | AX9: =-SUM(AW9-AS9) -> -342.35484 | AY9: =SUM(AX9+AW9) -> -613.35484 | AZ9: =ELEC!A6 -> 0.013 | BA9: ='General information '!D9 -> 18.5 | BB9: =SUM('General information '!E9) -> 0.31 | BC9: =IF(AR8>=AR9,0,1) -> 0 | BD9: 19222 | BE9: =(305/1185)*ELEC!Q7 -> 435.23629 | BG9: =#REF!-BE9 -> #REF! | BH9: 18
A10: =ELEC!C7 -> 43926 | B10: ='B5'!B9 -> 235 | C10: =B10*$B$4 -> 5056.2903 | D10: =SUM(B10) -> 235 | E10: =D10*$B$4 -> 5056.2903 | F10: =SUM(D10) -> 235 | G10: =F10*$B$4 -> 5056.2903 | H10: =SUM(F10) -> 235 | I10: =H10*$B$4 -> 5056.2903 | J10: =SUM(H10) -> 235 | K10: =J10*$B$4 -> 5056.2903 | L10: =SUM(J10) -> 235 | M10: =L10*$B$4 -> 5056.2903 | N10: =SUM(L10) -> 235 | O10: =N10*$B$4 -> 5056.2903 | P10: =SUM(N10) -> 235 | Q10: =P10*$B$4 -> 5056.2903 | R10: =SUM(P10) -> 235 | S10: =R10*$B$4 -> 5056.2903 | T10: =SUM(R10) -> 235 | U10: =T10*$B$4 -> 5056.2903 | V10: =SUM(T10) -> 235 | W10: =V10*$B$4 -> 5056.2903 | X10: =SUM(Y10/73370) -> 0.75806452 | Y10: =SUM(C10+E10+G10+I10+K10+M10+O10+Q10+S10+U10+W10) -> 55619.194 | Z10: ='B5'!C9 -> 241 | AA10: =SUM(Z10*$Z$4) -> 2410 | AB10: =SUM(Z10) -> 241 | AC10: =SUM(AB10*$Z$4) -> 2410 | AD10: =SUM(AB10) -> 241 | AE10: =SUM(AD10*$Z$4) -> 2410 | AF10: =SUM(AD10) -> 241 | AG10: =SUM(AF10*$Z$4) -> 2410 | AH10: =SUM(AF10) -> 241 | AI10: =SUM(AH10*$Z$4) -> 2410 | AJ10: =SUM(AH10) -> 241 | AK10: =SUM(AJ10*$Z$4) -> 2410 | AL10: =SUM(AJ10) -> 241 | AM10: =SUM(AL10*$Z$4) -> 2410 | AN10: =SUM(AO10/19600) -> 0.86071429 | AO10: =SUM(AA10+AC10+AE10+AG10+AI10+AK10+AM10) -> 16870 | AQ10: =SUM(AR10/92970) -> 0.77970521 | AR10: =SUM(AO10+Y10) -> 72489.194 | AS10: =SUM(AR10-AR9-AT10) -> -1156.7097 | AV10: =IF(AT10>0,AU10,AV9) -> 0.3845 | AW10: =-SUM('B5'!AI9) -> -252 | AX10: =-SUM(AW10-AS10) -> -904.70968 | AY10: =SUM(AX10+AW10) -> -1156.7097 | AZ10: =ELEC!A7 -> 0.0304 | BA10: ='General information '!D10 -> 25.5 | BB10: =SUM('General information '!E10) -> 0.43 | BC10: =IF(AR9>=AR10,0,1) -> 0 | BD10: 19222 | BE10: =(305/1185)*ELEC!Q8 -> 460.7173 | BG10: =#REF!-BE10 -> #REF! | BH10: 16
A11: =ELEC!C8 -> 43927 | B11: ='B5'!B10 -> 233 | C11: =B11*$B$4 -> 5013.2581 | D11: =SUM(B11) -> 233 | E11: =D11*$B$4 -> 5013.2581 | F11: =SUM(D11) -> 233 | G11: =F11*$B$4 -> 5013.2581 | H11: =SUM(F11) -> 233 | I11: =H11*$B$4 -> 5013.2581 | J11: =SUM(H11) -> 233 | K11: =J11*$B$4 -> 5013.2581 | L11: =SUM(J11) -> 233 | M11: =L11*$B$4 -> 5013.2581 | N11: =SUM(L11) -> 233 | O11: =N11*$B$4 -> 5013.2581 | P11: =SUM(N11) -> 233 | Q11: =P11*$B$4 -> 5013.2581 | R11: =SUM(P11) -> 233 | S11: =R11*$B$4 -> 5013.2581 | T11: =SUM(R11) -> 233 | U11: =T11*$B$4 -> 5013.2581 | V11: =SUM(T11) -> 233 | W11: =V11*$B$4 -> 5013.2581 | X11: =SUM(Y11/73370) -> 0.7516129 | Y11: =SUM(C11+E11+G11+I11+K11+M11+O11+Q11+S11+U11+W11) -> 55145.839 | Z11: ='B5'!C10 -> 239 | AA11: =SUM(Z11*$Z$4) -> 2390 | AB11: =SUM(Z11) -> 239 | AC11: =SUM(AB11*$Z$4) -> 2390 | AD11: =SUM(AB11) -> 239 | AE11: =SUM(AD11*$Z$4) -> 2390 | AF11: =SUM(AD11) -> 239 | AG11: =SUM(AF11*$Z$4) -> 2390 | AH11: =SUM(AF11) -> 239 | AI11: =SUM(AH11*$Z$4) -> 2390 | AJ11: =SUM(AH11) -> 239 | AK11: =SUM(AJ11*$Z$4) -> 2390 | AL11: =SUM(AJ11) -> 239 | AM11: =SUM(AL11*$Z$4) -> 2390 | AN11: =SUM(AO11/19600) -> 0.85357143 | AO11: =SUM(AA11+AC11+AE11+AG11+AI11+AK11+AM11) -> 16730 | AQ11: =SUM(AR11/92970) -> 0.77310787 | AR11: =SUM(AO11+Y11) -> 71875.839 | AS11: =SUM(AR11-AR10-AT11) -> -613.35484 | AV11: =IF(AT11>0,AU11,AV10) -> 0.3845 | AW11: =-SUM('B5'!AI10) -> -444 | AX11: =-SUM(AW11-AS11) -> -169.35484 | AY11: =SUM(AX11+AW11) -> -613.35484 | AZ11: =ELEC!A8 -> 0.0087 | BA11: ='General information '!D11 -> 18 | BB11: =SUM('General information '!E11) -> 0.5 | BC11: =IF(AR10>=AR11,0,1) -> 0 | BD11: 19222 | BE11: =(305/1185)*ELEC!Q9 -> 360.08017 | BG11: =#REF!-BE11 -> #REF! | BH11: 16.5
A12: =ELEC!C9 -> 43928 | B12: ='B5'!B11 -> 232 | C12: =B12*$B$4 -> 4991.7419 | D12: =SUM(B12) -> 232 | E12: =D12*$B$4 -> 4991.7419 | F12: =SUM(D12) -> 232 | G12: =F12*$B$4 -> 4991.7419 | H12: =SUM(F12) -> 232 | I12: =H12*$B$4 -> 4991.7419 | J12: =SUM(H12) -> 232 | K12: =J12*$B$4 -> 4991.7419 | L12: =SUM(J12) -> 232 | M12: =L12*$B$4 -> 4991.7419 | N12: =SUM(L12) -> 232 | O12: =N12*$B$4 -> 4991.7419 | P12: =SUM(N12) -> 232 | Q12: =P12*$B$4 -> 4991.7419 | R12: =SUM(P12) -> 232 | S12: =R12*$B$4 -> 4991.7419 | T12: =SUM(R12) -> 232 | U12: =T12*$B$4 -> 4991.7419 | V12: =SUM(T12) -> 232 | W12: =V12*$B$4 -> 4991.7419 | X12: =SUM(Y12/73370) -> 0.7483871 | Y12: =SUM(C12+E12+G12+I12+K12+M12+O12+Q12+S12+U12+W12) -> 54909.161 | Z12: ='B5'!C11 -> 238 | AA12: =SUM(Z12*$Z$4) -> 2380 | AB12: =SUM(Z12) -> 238 | AC12: =SUM(AB12*$Z$4) -> 2380 | AD12: =SUM(AB12) -> 238 | AE12: =SUM(AD12*$Z$4) -> 2380 | AF12: =SUM(AD12) -> 238 | AG12: =SUM(AF12*$Z$4) -> 2380 | AH12: =SUM(AF12) -> 238 | AI12: =SUM(AH12*$Z$4) -> 2380 | AJ12: =SUM(AH12) -> 238 | AK12: =SUM(AJ12*$Z$4) -> 2380 | AL12: =SUM(AJ12) -> 238 | AM12: =SUM(AL12*$Z$4) -> 2380 | AN12: =SUM(AO12/19600) -> 0.85 | AO12: =SUM(AA12+AC12+AE12+AG12+AI12+AK12+AM12) -> 16660 | AQ12: =SUM(AR12/92970) -> 0.7698092 | AR12: =SUM(AO12+Y12) -> 71569.161 | AS12: =SUM(AR12-AR11-AT12) -> -306.67742 | AV12: =IF(AT12>0,AU12,AV11) -> 0.3845 | AW12: =-SUM('B5'!AI11) -> -164 | AX12: =-SUM(AW12-AS12) -> -142.67742 | AY12: =SUM(AX12+AW12) -> -306.67742 | AZ12: =ELEC!A9 -> 0.0087 | BA12: ='General information '!D12 -> 18 | BB12: =SUM('General information '!E12) -> 0.5 | BC12: =IF(AR11>=AR12,0,1) -> 0 | BD12: 19222 | BE12: =(305/1185)*ELEC!Q10 -> 414.64557 | BG12: =#REF!-BE12 -> #REF! | BH12: 15.5
A13: =ELEC!C10 -> 43929 | B13: ='B5'!B12 -> 229 | C13: =B13*$B$4 -> 4927.1935 | D13: =SUM(B13) -> 229 | E13: =D13*$B$4 -> 4927.1935 | F13: =SUM(D13) -> 229 | G13: =F13*$B$4 -> 4927.1935 | H13: =SUM(F13) -> 229 | I13: =H13*$B$4 -> 4927.1935 | J13: =SUM(H13) -> 229 | K13: =J13*$B$4 -> 4927.1935 | L13: =SUM(J13) -> 229 | M13: =L13*$B$4 -> 4927.1935 | N13: =SUM(L13) -> 229 | O13: =N13*$B$4 -> 4927.1935 | P13: =SUM(N13) -> 229 | Q13: =P13*$B$4 -> 4927.1935 | R13: =SUM(P13) -> 229 | S13: =R13*$B$4 -> 4927.1935 | T13: =SUM(R13) -> 229 | U13: =T13*$B$4 -> 4927.1935 | V13: =SUM(T13) -> 229 | W13: =V13*$B$4 -> 4927.1935 | X13: =SUM(Y13/73370) -> 0.73870968 | Y13: =SUM(C13+E13+G13+I13+K13+M13+O13+Q13+S13+U13+W13) -> 54199.129 | Z13: ='B5'!C12 -> 235 | AA13: =SUM(Z13*$Z$4) -> 2350 | AB13: =SUM(Z13) -> 235 | AC13: =SUM(AB13*$Z$4) -> 2350 | AD13: =SUM(AB13) -> 235 | AE13: =SUM(AD13*$Z$4) -> 2350 | AF13: =SUM(AD13) -> 235 | AG13: =SUM(AF13*$Z$4) -> 2350 | AH13: =SUM(AF13) -> 235 | AI13: =SUM(AH13*$Z$4) -> 2350 | AJ13: =SUM(AH13) -> 235 | AK13: =SUM(AJ13*$Z$4) -> 2350 | AL13: =SUM(AJ13) -> 235 | AM13: =SUM(AL13*$Z$4) -> 2350 | AN13: =SUM(AO13/19600) -> 0.83928571 | AO13: =SUM(AA13+AC13+AE13+AG13+AI13+AK13+AM13) -> 16450 | AQ13: =SUM(AR13/92970) -> 0.75991319 | AR13: =SUM(AO13+Y13) -> 70649.129 | AS13: =SUM(AR13-AR12-AT13) -> -920.03226 | AV13: =IF(AT13>0,AU13,AV12) -> 0.3845 | AW13: =-SUM('B5'!AI12) -> -305 | AX13: =-SUM(AW13-AS13) -> -615.03226 | AY13: =SUM(AX13+AW13) -> -920.03226 | AZ13: =ELEC!A10 -> 0.0478 | BA13: ='General information '!D13 -> 17 | BB13: =SUM('General information '!E13) -> 0.55 | BC13: =IF(AR12>=AR13,0,1) -> 0 | BD13: 19222 | BE13: =(305/1185)*ELEC!Q11 -> 480.53586 | BG13: =#REF!-BE13 -> #REF!
A14: =ELEC!C11 -> 43930 | B14: ='B5'!B13 -> 225 | C14: =B14*$B$4 -> 4841.129 | D14: =SUM(B14) -> 225 | E14: =D14*$B$4 -> 4841.129 | F14: =SUM(D14) -> 225 | G14: =F14*$B$4 -> 4841.129 | H14: =SUM(F14) -> 225 | I14: =H14*$B$4 -> 4841.129 | J14: =SUM(H14) -> 225 | K14: =J14*$B$4 -> 4841.129 | L14: =SUM(J14) -> 225 | M14: =L14*$B$4 -> 4841.129 | N14: =SUM(L14) -> 225 | O14: =N14*$B$4 -> 4841.129 | P14: =SUM(N14) -> 225 | Q14: =P14*$B$4 -> 4841.129 | R14: =SUM(P14) -> 225 | S14: =R14*$B$4 -> 4841.129 | T14: =SUM(R14) -> 225 | U14: =T14*$B$4 -> 4841.129 | V14: =SUM(T14) -> 225 | W14: =V14*$B$4 -> 4841.129 | X14: =SUM(Y14/73370) -> 0.72580645 | Y14: =SUM(C14+E14+G14+I14+K14+M14+O14+Q14+S14+U14+W14) -> 53252.419 | Z14: ='B5'!C13 -> 231 | AA14: =SUM(Z14*$Z$4) -> 2310 | AB14: =SUM(Z14) -> 231 | AC14: =SUM(AB14*$Z$4) -> 2310 | AD14: =SUM(AB14) -> 231 | AE14: =SUM(AD14*$Z$4) -> 2310 | AF14: =SUM(AD14) -> 231 | AG14: =SUM(AF14*$Z$4) -> 2310 | AH14: =SUM(AF14) -> 231 | AI14: =SUM(AH14*$Z$4) -> 2310 | AJ14: =SUM(AH14) -> 231 | AK14: =SUM(AJ14*$Z$4) -> 2310 | AL14: =SUM(AJ14) -> 231 | AM14: =SUM(AL14*$Z$4) -> 2310 | AN14: =SUM(AO14/19600) -> 0.825 | AO14: =SUM(AA14+AC14+AE14+AG14+AI14+AK14+AM14) -> 16170 | AQ14: =SUM(AR14/92970) -> 0.7467185 | AR14: =SUM(AO14+Y14) -> 69422.419 | AS14: =SUM(AR14-AR13-AT14) -> -1226.7097 | AV14: =IF(AT14>0,AU14,AV13) -> 0.3845 | AW14: =-SUM('B5'!AI13) -> -615.7 | AX14: =-SUM(AW14-AS14) -> -611.00968 | AY14: =SUM(AX14+AW14) -> -1226.7097 | AZ14: =ELEC!A11 -> 0.0217 | BA14: ='General information '!D14 -> 16.5 | BB14: =SUM('General information '!E14) -> 0.87 | BC14: =IF(AR13>=AR14,0,1) -> 0 | BD14: 19222 | BE14: =(305/1185)*ELEC!Q12 -> 257.38397 | BG14: =#REF!-BE14 -> #REF!
A15: =ELEC!C12 -> 43931 | B15: ='B5'!B14 -> 221 | C15: =B15*$B$4 -> 4755.0645 | D15: =SUM(B15) -> 221 | E15: =D15*$B$4 -> 4755.0645 | F15: =SUM(D15) -> 221 | G15: =F15*$B$4 -> 4755.0645 | H15: =SUM(F15) -> 221 | I15: =H15*$B$4 -> 4755.0645 | J15: =SUM(H15) -> 221 | K15: =J15*$B$4 -> 4755.0645 | L15: =SUM(J15) -> 221 | M15: =L15*$B$4 -> 4755.0645 | N15: =SUM(L15) -> 221 | O15: =N15*$B$4 -> 4755.0645 | P15: =SUM(N15) -> 221 | Q15: =P15*$B$4 -> 4755.0645 | R15: =SUM(P15) -> 221 | S15: =R15*$B$4 -> 4755.0645 | T15: =SUM(R15) -> 221 | U15: =T15*$B$4 -> 4755.0645 | V15: =SUM(T15) -> 221 | W15: =V15*$B$4 -> 4755.0645 | X15: =SUM(Y15/73370) -> 0.71290323 | Y15: =SUM(C15+E15+G15+I15+K15+M15+O15+Q15+S15+U15+W15) -> 52305.71 | Z15: ='B5'!C14 -> 228 | AA15: =SUM(Z15*$Z$4) -> 2280 | AB15: =SUM(Z15) -> 228 | AC15: =SUM(AB15*$Z$4) -> 2280 | AD15: =SUM(AB15) -> 228 | AE15: =SUM(AD15*$Z$4) -> 2280 | AF15: =SUM(AD15) -> 228 | AG15: =SUM(AF15*$Z$4) -> 2280 | AH15: =SUM(AF15) -> 228 | AI15: =SUM(AH15*$Z$4) -> 2280 | AJ15: =SUM(AH15) -> 228 | AK15: =SUM(AJ15*$Z$4) -> 2280 | AL15: =SUM(AJ15) -> 228 | AM15: =SUM(AL15*$Z$4) -> 2280 | AN15: =SUM(AO15/19600) -> 0.81428571 | AO15: =SUM(AA15+AC15+AE15+AG15+AI15+AK15+AM15) -> 15960 | AQ15: =SUM(AR15/92970) -> 0.73427675 | AR15: =SUM(AO15+Y15) -> 68265.71 | AS15: =SUM(AR15-AR14-AT15) -> -1156.7097 | AV15: =IF(AT15>0,AU15,AV14) -> 0.3845 | AW15: =-SUM('B5'!AI14) -> -426 | AX15: =-SUM(AW15-AS15) -> -730.70968 | AY15: =SUM(AX15+AW15) -> -1156.7097 | AZ15: =ELEC!A12 -> 0.0087 | BA15: ='General information '!D15 -> 14.5 | BB15: =SUM('General information '!E15) -> 0.85 | BC15: =IF(AR14>=AR15,0,1) -> 0 | BD15: 19222 | BE15: =(305/1185)*ELEC!Q13 -> 514.76793 | BG15: =#REF!-BE15 -> #REF!
A16: =ELEC!C13 -> 43932 | B16: ='B5'!B15 -> 219 | C16: =B16*$B$4 -> 4712.0323 | D16: =SUM(B16) -> 219 | E16: =D16*$B$4 -> 4712.0323 | F16: =SUM(D16) -> 219 | G16: =F16*$B$4 -> 4712.0323 | H16: =SUM(F16) -> 219 | I16: =H16*$B$4 -> 4712.0323 | J16: =SUM(H16) -> 219 | K16: =J16*$B$4 -> 4712.0323 | L16: =SUM(J16) -> 219 | M16: =L16*$B$4 -> 4712.0323 | N16: =SUM(L16) -> 219 | O16: =N16*$B$4 -> 4712.0323 | P16: =SUM(N16) -> 219 | Q16: =P16*$B$4 -> 4712.0323 | R16: =SUM(P16) -> 219 | S16: =R16*$B$4 -> 4712.0323 | T16: =SUM(R16) -> 219 | U16: =T16*$B$4 -> 4712.0323 | V16: =SUM(T16) -> 219 | W16: =V16*$B$4 -> 4712.0323 | X16: =SUM(Y16/73370) -> 0.70645161 | Y16: =SUM(C16+E16+G16+I16+K16+M16+O16+Q16+S16+U16+W16) -> 51832.355 | Z16: ='B5'!C15 -> 225 | AA16: =SUM(Z16*$Z$4) -> 2250 | AB16: =SUM(Z16) -> 225 | AC16: =SUM(AB16*$Z$4) -> 2250 | AD16: =SUM(AB16) -> 225 | AE16: =SUM(AD16*$Z$4) -> 2250 | AF16: =SUM(AD16) -> 225 | AG16: =SUM(AF16*$Z$4) -> 2250 | AH16: =SUM(AF16) -> 225 | AI16: =SUM(AH16*$Z$4) -> 2250 | AJ16: =SUM(AH16) -> 225 | AK16: =SUM(AJ16*$Z$4) -> 2250 | AL16: =SUM(AJ16) -> 225 | AM16: =SUM(AL16*$Z$4) -> 2250 | AN16: =SUM(AO16/19600) -> 0.80357143 | AO16: =SUM(AA16+AC16+AE16+AG16+AI16+AK16+AM16) -> 15750 | AQ16: =SUM(AR16/92970) -> 0.72692648 | AR16: =SUM(AO16+Y16) -> 67582.355 | AS16: =SUM(AR16-AR15-AT16) -> -683.35484 | AV16: =IF(AT16>0,AU16,AV15) -> 0.3845 | AW16: =-SUM('B5'!AI15) -> -194 | AX16: =-SUM(AW16-AS16) -> -489.35484 | AY16: =SUM(AX16+AW16) -> -683.35484 | AZ16: =ELEC!A13 -> 0.0174 | BA16: ='General information '!D16 -> 15.5 | BB16: =SUM('General information '!E16) -> 0.8 | BC16: =IF(AR15>=AR16,0,1) -> 0 | BD16: 19222 | BE16: =(305/1185)*ELEC!Q14 -> 257.38397 | BG16: =#REF!-BE16 -> #REF!
A17: =ELEC!C14 -> 43933 | B17: ='B5'!B16 -> 216 | C17: =B17*$B$4 -> 4647.4839 | D17: =SUM(B17) -> 216 | E17: =D17*$B$4 -> 4647.4839 | F17: =SUM(D17) -> 216 | G17: =F17*$B$4 -> 4647.4839 | H17: =SUM(F17) -> 216 | I17: =H17*$B$4 -> 4647.4839 | J17: =SUM(H17) -> 216 | K17: =J17*$B$4 -> 4647.4839 | L17: =SUM(J17) -> 216 | M17: =L17*$B$4 -> 4647.4839 | N17: =SUM(L17) -> 216 | O17: =N17*$B$4 -> 4647.4839 | P17: =SUM(N17) -> 216 | Q17: =P17*$B$4 -> 4647.4839 | R17: =SUM(P17) -> 216 | S17: =R17*$B$4 -> 4647.4839 | T17: =SUM(R17) -> 216 | U17: =T17*$B$4 -> 4647.4839 | V17: =SUM(T17) -> 216 | W17: =V17*$B$4 -> 4647.4839 | X17: =SUM(Y17/73370) -> 0.69677419 | Y17: =SUM(C17+E17+G17+I17+K17+M17+O17+Q17+S17+U17+W17) -> 51122.323 | Z17: ='B5'!C16 -> 223 | AA17: =SUM(Z17*$Z$4) -> 2230 | AB17: =SUM(Z17) -> 223 | AC17: =SUM(AB17*$Z$4) -> 2230 | AD17: =SUM(AB17) -> 223 | AE17: =SUM(AD17*$Z$4) -> 2230 | AF17: =SUM(AD17) -> 223 | AG17: =SUM(AF17*$Z$4) -> 2230 | AH17: =SUM(AF17) -> 223 | AI17: =SUM(AH17*$Z$4) -> 2230 | AJ17: =SUM(AH17) -> 223 | AK17: =SUM(AJ17*$Z$4) -> 2230 | AL17: =SUM(AJ17) -> 223 | AM17: =SUM(AL17*$Z$4) -> 2230 | AN17: =SUM(AO17/19600) -> 0.79642857 | AO17: =SUM(AA17+AC17+AE17+AG17+AI17+AK17+AM17) -> 15610 | AQ17: =SUM(AR17/92970) -> 0.7177834 | AR17: =SUM(AO17+Y17) -> 66732.323 | AS17: =SUM(AR17-AR16-AT17) -> -850.03226 | AV17: =IF(AT17>0,AU17,AV16) -> 0.3845 | AW17: =-SUM('B5'!AI16) -> -308 | AX17: =-SUM(AW17-AS17) -> -542.03226 | AY17: =SUM(AX17+AW17) -> -850.03226 | AZ17: =ELEC!A14 -> 0.013 | BA17: ='General information '!D17 -> 17 | BB17: =SUM('General information '!E17) -> 0.72 | BC17: =IF(AR16>=AR17,0,1) -> 0 | BD17: 19222 | BE17: =(305/1185)*ELEC!Q15 -> 257.38397 | BG17: =#REF!-BE17 -> #REF!
A18: =ELEC!C15 -> 43934 | B18: ='B5'!B17 -> 212 | C18: =B18*$B$4 -> 4561.4194 | D18: =SUM(B18) -> 212 | E18: =D18*$B$4 -> 4561.4194 | F18: =SUM(D18) -> 212 | G18: =F18*$B$4 -> 4561.4194 | H18: =SUM(F18) -> 212 | I18: =H18*$B$4 -> 4561.4194 | J18: =SUM(H18) -> 212 | K18: =J18*$B$4 -> 4561.4194 | L18: =SUM(J18) -> 212 | M18: =L18*$B$4 -> 4561.4194 | N18: =SUM(L18) -> 212 | O18: =N18*$B$4 -> 4561.4194 | P18: =SUM(N18) -> 212 | Q18: =P18*$B$4 -> 4561.4194 | R18: =SUM(P18) -> 212 | S18: =R18*$B$4 -> 4561.4194 | T18: =SUM(R18) -> 212 | U18: =T18*$B$4 -> 4561.4194 | V18: =SUM(T18) -> 212 | W18: =V18*$B$4 -> 4561.4194 | X18: =SUM(Y18/73370) -> 0.68387097 | Y18: =SUM(C18+E18+G18+I18+K18+M18+O18+Q18+S18+U18+W18) -> 50175.613 | Z18: ='B5'!C17 -> 219 | AA18: =SUM(Z18*$Z$4) -> 2190 | AB18: =SUM(Z18) -> 219 | AC18: =SUM(AB18*$Z$4) -> 2190 | AD18: =SUM(AB18) -> 219 | AE18: =SUM(AD18*$Z$4) -> 2190 | AF18: =SUM(AD18) -> 219 | AG18: =SUM(AF18*$Z$4) -> 2190 | AH18: =SUM(AF18) -> 219 | AI18: =SUM(AH18*$Z$4) -> 2190 | AJ18: =SUM(AH18) -> 219 | AK18: =SUM(AJ18*$Z$4) -> 2190 | AL18: =SUM(AJ18) -> 219 | AM18: =SUM(AL18*$Z$4) -> 2190 | AN18: =SUM(AO18/19600) -> 0.78214286 | AO18: =SUM(AA18+AC18+AE18+AG18+AI18+AK18+AM18) -> 15330 | AQ18: =SUM(AR18/92970) -> 0.70458872 | AR18: =SUM(AO18+Y18) -> 65505.613 | AS18: =SUM(AR18-AR17-AT18) -> -1226.7097 | AV18: =IF(AT18>0,AU18,AV17) -> 0.3845 | AW18: =-SUM('B5'!AI17) -> -411 | AX18: =-SUM(AW18-AS18) -> -815.70968 | AY18: =SUM(AX18+AW18) -> -1226.7097 | AZ18: =ELEC!A15 -> 0.0348 | BA18: ='General information '!D18 -> 18 | BB18: =SUM('General information '!E18) -> 0.68 | BC18: =IF(AR17>=AR18,0,1) -> 0 | BD18: 19222 | BE18: =(305/1185)*ELEC!Q16 -> 544.1097 | BG18: =#REF!-BE18 -> #REF!
A19: =ELEC!C16 -> 43935 | B19: ='B5'!B18 -> 210 | C19: =B19*$B$4 -> 4518.3871 | D19: =SUM(B19) -> 210 | E19: =D19*$B$4 -> 4518.3871 | F19: =SUM(D19) -> 210 | G19: =F19*$B$4 -> 4518.3871 | H19: =SUM(F19) -> 210 | I19: =H19*$B$4 -> 4518.3871 | J19: =SUM(H19) -> 210 | K19: =J19*$B$4 -> 4518.3871 | L19: =SUM(J19) -> 210 | M19: =L19*$B$4 -> 4518.3871 | N19: =SUM(L19) -> 210 | O19: =N19*$B$4 -> 4518.3871 | P19: =SUM(N19) -> 210 | Q19: =P19*$B$4 -> 4518.3871 | R19: =SUM(P19) -> 210 | S19: =R19*$B$4 -> 4518.3871 | T19: =SUM(R19) -> 210 | U19: =T19*$B$4 -> 4518.3871 | V19: =SUM(T19) -> 210 | W19: =V19*$B$4 -> 4518.3871 | X19: =SUM(Y19/73370) -> 0.67741935 | Y19: =SUM(C19+E19+G19+I19+K19+M19+O19+Q19+S19+U19+W19) -> 49702.258 | Z19: ='B5'!C18 -> 216.4 | AA19: =SUM(Z19*$Z$4) -> 2164 | AB19: =SUM(Z19) -> 216.4 | AC19: =SUM(AB19*$Z$4) -> 2164 | AD19: =SUM(AB19) -> 216.4 | AE19: =SUM(AD19*$Z$4) -> 2164 | AF19: =SUM(AD19) -> 216.4 | AG19: =SUM(AF19*$Z$4) -> 2164 | AH19: =SUM(AF19) -> 216.4 | AI19: =SUM(AH19*$Z$4) -> 2164 | AJ19: =SUM(AH19) -> 216.4 | AK19: =SUM(AJ19*$Z$4) -> 2164 | AL19: =SUM(AJ19) -> 216.4 | AM19: =SUM(AL19*$Z$4) -> 2164 | AN19: =SUM(AO19/19600) -> 0.77285714 | AO19: =SUM(AA19+AC19+AE19+AG19+AI19+AK19+AM19) -> 15148 | AQ19: =SUM(AR19/92970) -> 0.69753962 | AR19: =SUM(AO19+Y19) -> 64850.258 | AS19: =SUM(AR19-AR18-AT19) -> -655.35484 | AV19: =IF(AT19>0,AU19,AV18) -> 0.3845 | AW19: =-SUM('B5'!AI18) -> -235 | AX19: =-SUM(AW19-AS19) -> -420.35484 | AY19: =SUM(AX19+AW19) -> -655.35484 | AZ19: =ELEC!A16 -> 0.0217 | BA19: ='General information '!D19 -> 19 | BB19: =SUM('General information '!E19) -> 0.65 | BC19: =IF(AR18>=AR19,0,1) -> 0 | BD19: 19222 | BE19: =(305/1185)*ELEC!Q17 -> 450.42194 | BG19: =#REF!-BE19 -> #REF!
A20: =ELEC!C17 -> 43936 | B20: ='B5'!B19 -> 243 | C20: =B20*$B$4 -> 5228.4194 | D20: =SUM(B20) -> 243 | E20: =D20*$B$4 -> 5228.4194 | F20: =SUM(D20) -> 243 | G20: =F20*$B$4 -> 5228.4194 | H20: =SUM(F20) -> 243 | I20: =H20*$B$4 -> 5228.4194 | J20: =SUM(H20) -> 243 | K20: =J20*$B$4 -> 5228.4194 | L20: =SUM(J20) -> 243 | M20: =L20*$B$4 -> 5228.4194 | N20: =SUM(L20) -> 243 | O20: =N20*$B$4 -> 5228.4194 | P20: =SUM(N20) -> 243 | Q20: =P20*$B$4 -> 5228.4194 | R20: =SUM(P20) -> 243 | S20: =R20*$B$4 -> 5228.4194 | T20: =SUM(R20) -> 243 | U20: =T20*$B$4 -> 5228.4194 | V20: =SUM(T20) -> 243 | W20: =V20*$B$4 -> 5228.4194 | X20: =SUM(Y20/73370) -> 0.78387097 | Y20: =SUM(C20+E20+G20+I20+K20+M20+O20+Q20+S20+U20+W20) -> 57512.613 | Z20: ='B5'!C19 -> 249 | AA20: =SUM(Z20*$Z$4) -> 2490 | AB20: =SUM(Z20) -> 249 | AC20: =SUM(AB20*$Z$4) -> 2490 | AD20: =SUM(AB20) -> 249 | AE20: =SUM(AD20*$Z$4) -> 2490 | AF20: =SUM(AD20) -> 249 | AG20: =SUM(AF20*$Z$4) -> 2490 | AH20: =SUM(AF20) -> 249 | AI20: =SUM(AH20*$Z$4) -> 2490 | AJ20: =SUM(AH20) -> 249 | AK20: =SUM(AJ20*$Z$4) -> 2490 | AL20: =SUM(AJ20) -> 249 | AM20: =SUM(AL20*$Z$4) -> 2490 | AN20: =SUM(AO20/19600) -> 0.88928571 | AO20: =SUM(AA20+AC20+AE20+AG20+AI20+AK20+AM20) -> 17430 | AQ20: =SUM(AR20/92970) -> 0.80609458 | AR20: =SUM(AO20+Y20) -> 74942.613 | AS20: =SUM(AR20-AR19-AT20) -> -517.64516 | AT20: 10610 | AU20: 0.326667 | AV20: =IF(AT20>0,AU20,AV19) -> 0.326667 | AW20: =-SUM('B5'!AI19) -> -537 | AX20: =-SUM(AW20-AS20) -> 19.354839 | AY20: =SUM(AX20+AW20) -> -517.64516 | AZ20: =ELEC!A17 -> 0.013 | BA20: ='General information '!D20 -> 18 | BB20: =SUM('General information '!E20) -> 0.63 | BC20: =IF(AR19>=AR20,0,1) -> 1 | BD20: 19222 | BE20: =(305/1185)*ELEC!Q18 -> 163.6962 | BG20: =#REF!-BE20 -> #REF!
A21: =ELEC!C18 -> 43937 | B21: ='B5'!B20 -> 241 | C21: =B21*$B$4 -> 5185.3871 | D21: =SUM(B21) -> 241 | E21: =D21*$B$4 -> 5185.3871 | F21: =SUM(D21) -> 241 | G21: =F21*$B$4 -> 5185.3871 | H21: =SUM(F21) -> 241 | I21: =H21*$B$4 -> 5185.3871 | J21: =SUM(H21) -> 241 | K21: =J21*$B$4 -> 5185.3871 | L21: =SUM(J21) -> 241 | M21: =L21*$B$4 -> 5185.3871 | N21: =SUM(L21) -> 241 | O21: =N21*$B$4 -> 5185.3871 | P21: =SUM(N21) -> 241 | Q21: =P21*$B$4 -> 5185.3871 | R21: =SUM(P21) -> 241 | S21: =R21*$B$4 -> 5185.3871 | T21: =SUM(R21) -> 241 | U21: =T21*$B$4 -> 5185.3871 | V21: =SUM(T21) -> 241 | W21: =V21*$B$4 -> 5185.3871 | X21: =SUM(Y21/73370) -> 0.77741935 | Y21: =SUM(C21+E21+G21+I21+K21+M21+O21+Q21+S21+U21+W21) -> 57039.258 | Z21: ='B5'!C20 -> 247 | AA21: =SUM(Z21*$Z$4) -> 2470 | AB21: =SUM(Z21) -> 247 | AC21: =SUM(AB21*$Z$4) -> 2470 | AD21: =SUM(AB21) -> 247 | AE21: =SUM(AD21*$Z$4) -> 2470 | AF21: =SUM(AD21) -> 247 | AG21: =SUM(AF21*$Z$4) -> 2470 | AH21: =SUM(AF21) -> 247 | AI21: =SUM(AH21*$Z$4) -> 2470 | AJ21: =SUM(AH21) -> 247 | AK21: =SUM(AJ21*$Z$4) -> 2470 | AL21: =SUM(AJ21) -> 247 | AM21: =SUM(AL21*$Z$4) -> 2470 | AN21: =SUM(AO21/19600) -> 0.88214286 | AO21: =SUM(AA21+AC21+AE21+AG21+AI21+AK21+AM21) -> 17290 | AQ21: =SUM(AR21/92970) -> 0.79949724 | AR21: =SUM(AO21+Y21) -> 74329.258 | AS21: =SUM(AR21-AR20-AT21) -> -613.35484 | AV21: =IF(AT21>0,AU21,AV20) -> 0.326667 | AW21: =-SUM('B5'!AI20) -> -340 | AX21: =-SUM(AW21-AS21) -> -273.35484 | AY21: =SUM(AX21+AW21) -> -613.35484 | AZ21: =ELEC!A18 -> 0.01 | BA21: ='General information '!D21 -> 17.5 | BB21: =SUM('General information '!E21) -> 0.84 | BC21: =IF(AR20>=AR21,0,1) -> 0 | BD21: 19222 | BE21: =(305/1185)*ELEC!Q19 -> 460.45992 | BG21: =#REF!-BE21 -> #REF!
A22: =ELEC!C19 -> 43938 | B22: ='B5'!B21 -> 238 | C22: =B22*$B$4 -> 5120.8387 | D22: =SUM(B22) -> 238 | E22: =D22*$B$4 -> 5120.8387 | F22: =SUM(D22) -> 238 | G22: =F22*$B$4 -> 5120.8387 | H22: =SUM(F22) -> 238 | I22: =H22*$B$4 -> 5120.8387 | J22: =SUM(H22) -> 238 | K22: =J22*$B$4 -> 5120.8387 | L22: =SUM(J22) -> 238 | M22: =L22*$B$4 -> 5120.8387 | N22: =SUM(L22) -> 238 | O22: =N22*$B$4 -> 5120.8387 | P22: =SUM(N22) -> 238 | Q22: =P22*$B$4 -> 5120.8387 | R22: =SUM(P22) -> 238 | S22: =R22*$B$4 -> 5120.8387 | T22: =SUM(R22) -> 238 | U22: =T22*$B$4 -> 5120.8387 | V22: =SUM(T22) -> 238 | W22: =V22*$B$4 -> 5120.8387 | X22: =SUM(Y22/73370) -> 0.76774194 | Y22: =SUM(C22+E22+G22+I22+K22+M22+O22+Q22+S22+U22+W22) -> 56329.226 | Z22: ='B5'!C21 -> 244 | AA22: =SUM(Z22*$Z$4) -> 2440 | AB22: =SUM(Z22) -> 244 | AC22: =SUM(AB22*$Z$4) -> 2440 | AD22: =SUM(AB22) -> 244 | AE22: =SUM(AD22*$Z$4) -> 2440 | AF22: =SUM(AD22) -> 244 | AG22: =SUM(AF22*$Z$4) -> 2440 | AH22: =SUM(AF22) -> 244 | AI22: =SUM(AH22*$Z$4) -> 2440 | AJ22: =SUM(AH22) -> 244 | AK22: =SUM(AJ22*$Z$4) -> 2440 | AL22: =SUM(AJ22) -> 244 | AM22: =SUM(AL22*$Z$4) -> 2440 | AN22: =SUM(AO22/19600) -> 0.87142857 | AO22: =SUM(AA22+AC22+AE22+AG22+AI22+AK22+AM22) -> 17080 | AQ22: =SUM(AR22/92970) -> 0.78960122 | AR22: =SUM(AO22+Y22) -> 73409.226 | AS22: =SUM(AR22-AR21-AT22) -> -920.03226 | AV22: =IF(AT22>0,AU22,AV21) -> 0.326667 | AW22: =-SUM('B5'!AI21) -> -247 | AX22: =-SUM(AW22-AS22) -> -673.03226 | AY22: =SUM(AX22+AW22) -> -920.03226 | AZ22: =ELEC!A19 -> 0.0087 | BA22: ='General information '!D22 -> 19.5 | BB22: =SUM('General information '!E22) -> 0.73 | BC22: =IF(AR21>=AR22,0,1) -> 0 | BD22: 19222 | BE22: =(305/1185)*ELEC!Q20 -> 434.20675 | BG22: =#REF!-BE22 -> #REF!
A23: =ELEC!C20 -> 43939 | B23: ='B5'!B22 -> 235 | C23: =B23*$B$4 -> 5056.2903 | D23: =SUM(B23) -> 235 | E23: =D23*$B$4 -> 5056.2903 | F23: =SUM(D23) -> 235 | G23: =F23*$B$4 -> 5056.2903 | H23: =SUM(F23) -> 235 | I23: =H23*$B$4 -> 5056.2903 | J23: =SUM(H23) -> 235 | K23: =J23*$B$4 -> 5056.2903 | L23: =SUM(J23) -> 235 | M23: =L23*$B$4 -> 5056.2903 | N23: =SUM(L23) -> 235 | O23: =N23*$B$4 -> 5056.2903 | P23: =SUM(N23) -> 235 | Q23: =P23*$B$4 -> 5056.2903 | R23: =SUM(P23) -> 235 | S23: =R23*$B$4 -> 5056.2903 | T23: =SUM(R23) -> 235 | U23: =T23*$B$4 -> 5056.2903 | V23: =SUM(T23) -> 235 | W23: =V23*$B$4 -> 5056.2903 | X23: =SUM(Y23/73370) -> 0.75806452 | Y23: =SUM(C23+E23+G23+I23+K23+M23+O23+Q23+S23+U23+W23) -> 55619.194 | Z23: ='B5'!C22 -> 241 | AA23: =SUM(Z23*$Z$4) -> 2410 | AB23: =SUM(Z23) -> 241 | AC23: =SUM(AB23*$Z$4) -> 2410 | AD23: =SUM(AB23) -> 241 | AE23: =SUM(AD23*$Z$4) -> 2410 | AF23: =SUM(AD23) -> 241 | AG23: =SUM(AF23*$Z$4) -> 2410 | AH23: =SUM(AF23) -> 241 | AI23: =SUM(AH23*$Z$4) -> 2410 | AJ23: =SUM(AH23) -> 241 | AK23: =SUM(AJ23*$Z$4) -> 2410 | AL23: =SUM(AJ23) -> 241 | AM23: =SUM(AL23*$Z$4) -> 2410 | AN23: =SUM(AO23/19600) -> 0.86071429 | AO23: =SUM(AA23+AC23+AE23+AG23+AI23+AK23+AM23) -> 16870 | AQ23: =SUM(AR23/92970) -> 0.77970521 | AR23: =SUM(AO23+Y23) -> 72489.194 | AS23: =SUM(AR23-AR22-AT23) -> -920.03226 | AV23: =IF(AT23>0,AU23,AV22) -> 0.326667 | AW23: =-SUM('B5'!AI22) -> -295 | AX23: =-SUM(AW23-AS23) -> -625.03226 | AY23: =SUM(AX23+AW23) -> -920.03226 | AZ23: =ELEC!A20 -> 0.013 | BA23: ='General information '!D23 -> 20.5 | BB23: =SUM('General information '!E23) -> 0.72 | BC23: =IF(AR22>=AR23,0,1) -> 0 | BD23: 19222 | BE23: =(305/1185)*ELEC!Q21 -> 92.14346 | BG23: =#REF!-BE23 -> #REF!
A24: =ELEC!C21 -> 43940 | B24: ='B5'!B23 -> 233 | C24: =B24*$B$4 -> 5013.2581 | D24: =SUM(B24) -> 233 | E24: =D24*$B$4 -> 5013.2581 | F24: =SUM(D24) -> 233 | G24: =F24*$B$4 -> 5013.2581 | H24: =SUM(F24) -> 233 | I24: =H24*$B$4 -> 5013.2581 | J24: =SUM(H24) -> 233 | K24: =J24*$B$4 -> 5013.2581 | L24: =SUM(J24) -> 233 | M24: =L24*$B$4 -> 5013.2581 | N24: =SUM(L24) -> 233 | O24: =N24*$B$4 -> 5013.2581 | P24: =SUM(N24) -> 233 | Q24: =P24*$B$4 -> 5013.2581 | R24: =SUM(P24) -> 233 | S24: =R24*$B$4 -> 5013.2581 | T24: =SUM(R24) -> 233 | U24: =T24*$B$4 -> 5013.2581 | V24: =SUM(T24) -> 233 | W24: =V24*$B$4 -> 5013.2581 | X24: =SUM(Y24/73370) -> 0.7516129 | Y24: =SUM(C24+E24+G24+I24+K24+M24+O24+Q24+S24+U24+W24) -> 55145.839 | Z24: ='B5'!C23 -> 239 | AA24: =SUM(Z24*$Z$4) -> 2390 | AB24: =SUM(Z24) -> 239 | AC24: =SUM(AB24*$Z$4) -> 2390 | AD24: =SUM(AB24) -> 239 | AE24: =SUM(AD24*$Z$4) -> 2390 | AF24: =SUM(AD24) -> 239 | AG24: =SUM(AF24*$Z$4) -> 2390 | AH24: =SUM(AF24) -> 239 | AI24: =SUM(AH24*$Z$4) -> 2390 | AJ24: =SUM(AH24) -> 239 | AK24: =SUM(AJ24*$Z$4) -> 2390 | AL24: =SUM(AJ24) -> 239 | AM24: =SUM(AL24*$Z$4) -> 2390 | AN24: =SUM(AO24/19600) -> 0.85357143 | AO24: =SUM(AA24+AC24+AE24+AG24+AI24+AK24+AM24) -> 16730 | AQ24: =SUM(AR24/92970) -> 0.77310787 | AR24: =SUM(AO24+Y24) -> 71875.839 | AS24: =SUM(AR24-AR23-AT24) -> -613.35484 | AV24: =IF(AT24>0,AU24,AV23) -> 0.326667 | AW24: =-SUM('B5'!AI23) -> -323 | AX24: =-SUM(AW24-AS24) -> -290.35484 | AY24: =SUM(AX24+AW24) -> -613.35484 | AZ24: =ELEC!A21 -> 0.0217 | BA24: ='General information '!D24 -> 20.5 | BB24: =SUM('General information '!E24) -> 0.65 | BC24: =IF(AR23>=AR24,0,1) -> 0 | BD24: 19222 | BE24: =(305/1185)*ELEC!Q22 -> 0 | BG24: =#REF!-BE24 -> #REF!
A25: =ELEC!C22 -> 43941 | B25: ='B5'!B24 -> 231 | C25: =B25*$B$4 -> 4970.2258 | D25: =SUM(B25) -> 231 | E25: =D25*$B$4 -> 4970.2258 | F25: =SUM(D25) -> 231 | G25: =F25*$B$4 -> 4970.2258 | H25: =SUM(F25) -> 231 | I25: =H25*$B$4 -> 4970.2258 | J25: =SUM(H25) -> 231 | K25: =J25*$B$4 -> 4970.2258 | L25: =SUM(J25) -> 231 | M25: =L25*$B$4 -> 4970.2258 | N25: =SUM(L25) -> 231 | O25: =N25*$B$4 -> 4970.2258 | P25: =SUM(N25) -> 231 | Q25: =P25*$B$4 -> 4970.2258 | R25: =SUM(P25) -> 231 | S25: =R25*$B$4 -> 4970.2258 | T25: =SUM(R25) -> 231 | U25: =T25*$B$4 -> 4970.2258 | V25: =SUM(T25) -> 231 | W25: =V25*$B$4 -> 4970.2258 | X25: =SUM(Y25/73370) -> 0.74516129 | Y25: =SUM(C25+E25+G25+I25+K25+M25+O25+Q25+S25+U25+W25) -> 54672.484 | Z25: ='B5'!C24 -> 238 | AA25: =SUM(Z25*$Z$4) -> 2380 | AB25: =SUM(Z25) -> 238 | AC25: =SUM(AB25*$Z$4) -> 2380 | AD25: =SUM(AB25) -> 238 | AE25: =SUM(AD25*$Z$4) -> 2380 | AF25: =SUM(AD25) -> 238 | AG25: =SUM(AF25*$Z$4) -> 2380 | AH25: =SUM(AF25) -> 238 | AI25: =SUM(AH25*$Z$4) -> 2380 | AJ25: =SUM(AH25) -> 238 | AK25: =SUM(AJ25*$Z$4) -> 2380 | AL25: =SUM(AJ25) -> 238 | AM25: =SUM(AL25*$Z$4) -> 2380 | AN25: =SUM(AO25/19600) -> 0.85 | AO25: =SUM(AA25+AC25+AE25+AG25+AI25+AK25+AM25) -> 16660 | AQ25: =SUM(AR25/92970) -> 0.76726346 | AR25: =SUM(AO25+Y25) -> 71332.484 | AS25: =SUM(AR25-AR24-AT25) -> -543.35484 | AV25: =IF(AT25>0,AU25,AV24) -> 0.326667 | AW25: =-SUM('B5'!AI24) -> -366 | AX25: =-SUM(AW25-AS25) -> -177.35484 | AY25: =SUM(AX25+AW25) -> -543.35484 | AZ25: =ELEC!A22 -> 0.0087 | BA25: ='General information '!D25 -> 20.5 | BB25: =SUM('General information '!E25) -> 0.83 | BC25: =IF(AR24>=AR25,0,1) -> 0 | BD25: 19222 | BE25: =(305/1185)*ELEC!Q23 -> 425.19831 | BG25: =#REF!-BE25 -> #REF!
A26: =ELEC!C23 -> 43942 | B26: ='B5'!B25 -> 229 | C26: =B26*$B$4 -> 4927.1935 | D26: =SUM(B26) -> 229 | E26: =D26*$B$4 -> 4927.1935 | F26: =SUM(D26) -> 229 | G26: =F26*$B$4 -> 4927.1935 | H26: =SUM(F26) -> 229 | I26: =H26*$B$4 -> 4927.1935 | J26: =SUM(H26) -> 229 | K26: =J26*$B$4 -> 4927.1935 | L26: =SUM(J26) -> 229 | M26: =L26*$B$4 -> 4927.1935 | N26: =SUM(L26) -> 229 | O26: =N26*$B$4 -> 4927.1935 | P26: =SUM(N26) -> 229 | Q26: =P26*$B$4 -> 4927.1935 | R26: =SUM(P26) -> 229 | S26: =R26*$B$4 -> 4927.1935 | T26: =SUM(R26) -> 229 | U26: =T26*$B$4 -> 4927.1935 | V26: =SUM(T26) -> 229 | W26: =V26*$B$4 -> 4927.1935 | X26: =SUM(Y26/73370) -> 0.73870968 | Y26: =SUM(C26+E26+G26+I26+K26+M26+O26+Q26+S26+U26+W26) -> 54199.129 | Z26: ='B5'!C25 -> 235 | AA26: =SUM(Z26*$Z$4) -> 2350 | AB26: =SUM(Z26) -> 235 | AC26: =SUM(AB26*$Z$4) -> 2350 | AD26: =SUM(AB26) -> 235 | AE26: =SUM(AD26*$Z$4) -> 2350 | AF26: =SUM(AD26) -> 235 | AG26: =SUM(AF26*$Z$4) -> 2350 | AH26: =SUM(AF26) -> 235 | AI26: =SUM(AH26*$Z$4) -> 2350 | AJ26: =SUM(AH26) -> 235 | AK26: =SUM(AJ26*$Z$4) -> 2350 | AL26: =SUM(AJ26) -> 235 | AM26: =SUM(AL26*$Z$4) -> 2350 | AN26: =SUM(AO26/19600) -> 0.83928571 | AO26: =SUM(AA26+AC26+AE26+AG26+AI26+AK26+AM26) -> 16450 | AQ26: =SUM(AR26/92970) -> 0.75991319 | AR26: =SUM(AO26+Y26) -> 70649.129 | AS26: =SUM(AR26-AR25-AT26) -> -683.35484 | AV26: =IF(AT26>0,AU26,AV25) -> 0.326667 | AW26: =-SUM('B5'!AI25) -> -225 | AX26: =-SUM(AW26-AS26) -> -458.35484 | AY26: =SUM(AX26+AW26) -> -683.35484 | AZ26: =ELEC!A23 -> 0.0087 | BA26: ='General information '!D26 -> 21 | BB26: =SUM('General information '!E26) -> 0.7 | BC26: =IF(AR25>=AR26,0,1) -> 0 | BD26: 19222 | BE26: =(305/1185)*ELEC!Q24 -> 519.40084 | BG26: =#REF!-BE26 -> #REF!
A27: =ELEC!C24 -> 43943 | B27: ='B5'!B26 -> 226 | C27: =B27*$B$4 -> 4862.6452 | D27: =SUM(B27) -> 226 | E27: =D27*$B$4 -> 4862.6452 | F27: =SUM(D27) -> 226 | G27: =F27*$B$4 -> 4862.6452 | H27: =SUM(F27) -> 226 | I27: =H27*$B$4 -> 4862.6452 | J27: =SUM(H27) -> 226 | K27: =J27*$B$4 -> 4862.6452 | L27: =SUM(J27) -> 226 | M27: =L27*$B$4 -> 4862.6452 | N27: =SUM(L27) -> 226 | O27: =N27*$B$4 -> 4862.6452 | P27: =SUM(N27) -> 226 | Q27: =P27*$B$4 -> 4862.6452 | R27: =SUM(P27) -> 226 | S27: =R27*$B$4 -> 4862.6452 | T27: =SUM(R27) -> 226 | U27: =T27*$B$4 -> 4862.6452 | V27: =SUM(T27) -> 226 | W27: =V27*$B$4 -> 4862.6452 | X27: =SUM(Y27/73370) -> 0.72903226 | Y27: =SUM(C27+E27+G27+I27+K27+M27+O27+Q27+S27+U27+W27) -> 53489.097 | Z27: ='B5'!C26 -> 232 | AA27: =SUM(Z27*$Z$4) -> 2320 | AB27: =SUM(Z27) -> 232 | AC27: =SUM(AB27*$Z$4) -> 2320 | AD27: =SUM(AB27) -> 232 | AE27: =SUM(AD27*$Z$4) -> 2320 | AF27: =SUM(AD27) -> 232 | AG27: =SUM(AF27*$Z$4) -> 2320 | AH27: =SUM(AF27) -> 232 | AI27: =SUM(AH27*$Z$4) -> 2320 | AJ27: =SUM(AH27) -> 232 | AK27: =SUM(AJ27*$Z$4) -> 2320 | AL27: =SUM(AJ27) -> 232 | AM27: =SUM(AL27*$Z$4) -> 2320 | AN27: =SUM(AO27/19600) -> 0.82857143 | AO27: =SUM(AA27+AC27+AE27+AG27+AI27+AK27+AM27) -> 16240 | AQ27: =SUM(AR27/92970) -> 0.75001718 | AR27: =SUM(AO27+Y27) -> 69729.097 | AS27: =SUM(AR27-AR26-AT27) -> -920.03226 | AV27: =IF(AT27>0,AU27,AV26) -> 0.326667 | AW27: =-SUM('B5'!AI26) -> -345 | AX27: =-SUM(AW27-AS27) -> -575.03226 | AY27: =SUM(AX27+AW27) -> -920.03226 | AZ27: =ELEC!A24 -> 0.0087 | BA27: ='General information '!D27 -> 21.5 | BB27: =SUM('General information '!E27) -> 0.8 | BC27: =IF(AR26>=AR27,0,1) -> 0 | BD27: 19222 | BE27: =(305/1185)*ELEC!Q25 -> 256.35443 | BG27: =#REF!-BE27 -> #REF!
A28: =ELEC!C25 -> 43944 | B28: ='B5'!B27 -> 221 | C28: =B28*$B$4 -> 4755.0645 | D28: =SUM(B28) -> 221 | E28: =D28*$B$4 -> 4755.0645 | F28: =SUM(D28) -> 221 | G28: =F28*$B$4 -> 4755.0645 | H28: =SUM(F28) -> 221 | I28: =H28*$B$4 -> 4755.0645 | J28: =SUM(H28) -> 221 | K28: =J28*$B$4 -> 4755.0645 | L28: =SUM(J28) -> 221 | M28: =L28*$B$4 -> 4755.0645 | N28: =SUM(L28) -> 221 | O28: =N28*$B$4 -> 4755.0645 | P28: =SUM(N28) -> 221 | Q28: =P28*$B$4 -> 4755.0645 | R28: =SUM(P28) -> 221 | S28: =R28*$B$4 -> 4755.0645 | T28: =SUM(R28) -> 221 | U28: =T28*$B$4 -> 4755.0645 | V28: =SUM(T28) -> 221 | W28: =V28*$B$4 -> 4755.0645 | X28: =SUM(Y28/73370) -> 0.71290323 | Y28: =SUM(C28+E28+G28+I28+K28+M28+O28+Q28+S28+U28+W28) -> 52305.71 | Z28: ='B5'!C27 -> 227 | AA28: =SUM(Z28*$Z$4) -> 2270 | AB28: =SUM(Z28) -> 227 | AC28: =SUM(AB28*$Z$4) -> 2270 | AD28: =SUM(AB28) -> 227 | AE28: =SUM(AD28*$Z$4) -> 2270 | AF28: =SUM(AD28) -> 227 | AG28: =SUM(AF28*$Z$4) -> 2270 | AH28: =SUM(AF28) -> 227 | AI28: =SUM(AH28*$Z$4) -> 2270 | AJ28: =SUM(AH28) -> 227 | AK28: =SUM(AJ28*$Z$4) -> 2270 | AL28: =SUM(AJ28) -> 227 | AM28: =SUM(AL28*$Z$4) -> 2270 | AN28: =SUM(AO28/19600) -> 0.81071429 | AO28: =SUM(AA28+AC28+AE28+AG28+AI28+AK28+AM28) -> 15890 | AQ28: =SUM(AR28/92970) -> 0.73352382 | AR28: =SUM(AO28+Y28) -> 68195.71 | AS28: =SUM(AR28-AR27-AT28) -> -1533.3871 | AV28: =IF(AT28>0,AU28,AV27) -> 0.326667 | AW28: =-SUM('B5'!AI27) -> -456 | AX28: =-SUM(AW28-AS28) -> -1077.3871 | AY28: =SUM(AX28+AW28) -> -1533.3871 | AZ28: =ELEC!A25 -> 0.0087 | BA28: ='General information '!D28 -> 19 | BB28: =SUM('General information '!E28) -> 0.8 | BC28: =IF(AR27>=AR28,0,1) -> 0 | BD28: 19222 | BE28: =(305/1185)*ELEC!Q26 -> 509.62025 | BG28: =#REF!-BE28 -> #REF!
A29: =ELEC!C26 -> 43945 | B29: ='B5'!B28 -> 219 | C29: =B29*$B$4 -> 4712.0323 | D29: =SUM(B29) -> 219 | E29: =D29*$B$4 -> 4712.0323 | F29: =SUM(D29) -> 219 | G29: =F29*$B$4 -> 4712.0323 | H29: =SUM(F29) -> 219 | I29: =H29*$B$4 -> 4712.0323 | J29: =SUM(H29) -> 219 | K29: =J29*$B$4 -> 4712.0323 | L29: =SUM(J29) -> 219 | M29: =L29*$B$4 -> 4712.0323 | N29: =SUM(L29) -> 219 | O29: =N29*$B$4 -> 4712.0323 | P29: =SUM(N29) -> 219 | Q29: =P29*$B$4 -> 4712.0323 | R29: =SUM(P29) -> 219 | S29: =R29*$B$4 -> 4712.0323 | T29: =SUM(R29) -> 219 | U29: =T29*$B$4 -> 4712.0323 | V29: =SUM(T29) -> 219 | W29: =V29*$B$4 -> 4712.0323 | X29: =SUM(Y29/73370) -> 0.70645161 | Y29: =SUM(C29+E29+G29+I29+K29+M29+O29+Q29+S29+U29+W29) -> 51832.355 | Z29: ='B5'!C28 -> 225 | AA29: =SUM(Z29*$Z$4) -> 2250 | AB29: =SUM(Z29) -> 225 | AC29: =SUM(AB29*$Z$4) -> 2250 | AD29: =SUM(AB29) -> 225 | AE29: =SUM(AD29*$Z$4) -> 2250 | AF29: =SUM(AD29) -> 225 | AG29: =SUM(AF29*$Z$4) -> 2250 | AH29: =SUM(AF29) -> 225 | AI29: =SUM(AH29*$Z$4) -> 2250 | AJ29: =SUM(AH29) -> 225 | AK29: =SUM(AJ29*$Z$4) -> 2250 | AL29: =SUM(AJ29) -> 225 | AM29: =SUM(AL29*$Z$4) -> 2250 | AN29: =SUM(AO29/19600) -> 0.80357143 | AO29: =SUM(AA29+AC29+AE29+AG29+AI29+AK29+AM29) -> 15750 | AQ29: =SUM(AR29/92970) -> 0.72692648 | AR29: =SUM(AO29+Y29) -> 67582.355 | AS29: =SUM(AR29-AR28-AT29) -> -613.35484 | AV29: =IF(AT29>0,AU29,AV28) -> 0.326667 | AW29: =-SUM('B5'!AI28) -> -319 | AX29: =-SUM(AW29-AS29) -> -294.35484 | AY29: =SUM(AX29+AW29) -> -613.35484 | AZ29: =ELEC!A26 -> 0.0087 | BA29: ='General information '!D29 -> 19.5 | BB29: =SUM('General information '!E29) -> 0.83 | BC29: =IF(AR28>=AR29,0,1) -> 0 | BD29: 19222 | BE29: =(305/1185)*ELEC!Q27 -> 391.22363 | BG29: =#REF!-BE29 -> #REF!
A30: =ELEC!C27 -> 43946 | B30: ='B5'!B29 -> 216 | C30: =B30*$B$4 -> 4647.4839 | D30: =SUM(B30) -> 216 | E30: =D30*$B$4 -> 4647.4839 | F30: =SUM(D30) -> 216 | G30: =F30*$B$4 -> 4647.4839 | H30: =SUM(F30) -> 216 | I30: =H30*$B$4 -> 4647.4839 | J30: =SUM(H30) -> 216 | K30: =J30*$B$4 -> 4647.4839 | L30: =SUM(J30) -> 216 | M30: =L30*$B$4 -> 4647.4839 | N30: =SUM(L30) -> 216 | O30: =N30*$B$4 -> 4647.4839 | P30: =SUM(N30) -> 216 | Q30: =P30*$B$4 -> 4647.4839 | R30: =SUM(P30) -> 216 | S30: =R30*$B$4 -> 4647.4839 | T30: =SUM(R30) -> 216 | U30: =T30*$B$4 -> 4647.4839 | V30: =SUM(T30) -> 216 | W30: =V30*$B$4 -> 4647.4839 | X30: =SUM(Y30/73370) -> 0.69677419 | Y30: =SUM(C30+E30+G30+I30+K30+M30+O30+Q30+S30+U30+W30) -> 51122.323 | Z30: ='B5'!C29 -> 220.5 | AA30: =SUM(Z30*$Z$4) -> 2205 | AB30: =SUM(Z30) -> 220.5 | AC30: =SUM(AB30*$Z$4) -> 2205 | AD30: =SUM(AB30) -> 220.5 | AE30: =SUM(AD30*$Z$4) -> 2205 | AF30: =SUM(AD30) -> 220.5 | AG30: =SUM(AF30*$Z$4) -> 2205 | AH30: =SUM(AF30) -> 220.5 | AI30: =SUM(AH30*$Z$4) -> 2205 | AJ30: =SUM(AH30) -> 220.5 | AK30: =SUM(AJ30*$Z$4) -> 2205 | AL30: =SUM(AJ30) -> 220.5 | AM30: =SUM(AL30*$Z$4) -> 2205 | AN30: =SUM(AO30/19600) -> 0.7875 | AO30: =SUM(AA30+AC30+AE30+AG30+AI30+AK30+AM30) -> 15435 | AQ30: =SUM(AR30/92970) -> 0.71590107 | AR30: =SUM(AO30+Y30) -> 66557.323 | AS30: =SUM(AR30-AR29-AT30) -> -1025.0323 | AV30: =IF(AT30>0,AU30,AV29) -> 0.326667 | AW30: =-SUM('B5'!AI29) -> -337 | AX30: =-SUM(AW30-AS30) -> -688.03226 | AY30: =SUM(AX30+AW30) -> -1025.0323 | AZ30: =ELEC!A27 -> 0.0174 | BA30: ='General information '!D30 -> 18 | BB30: =SUM('General information '!E30) -> 0.85 | BC30: =IF(AR29>=AR30,0,1) -> 0 | BD30: 19222 | BE30: =(305/1185)*ELEC!Q28 -> 386.07595 | BG30: =#REF!-BE30 -> #REF!
A31: =ELEC!C28 -> 43947 | B31: ='B5'!B30 -> 213 | C31: =B31*$B$4 -> 4582.9355 | D31: =SUM(B31) -> 213 | E31: =D31*$B$4 -> 4582.9355 | F31: =SUM(D31) -> 213 | G31: =F31*$B$4 -> 4582.9355 | H31: =SUM(F31) -> 213 | I31: =H31*$B$4 -> 4582.9355 | J31: =SUM(H31) -> 213 | K31: =J31*$B$4 -> 4582.9355 | L31: =SUM(J31) -> 213 | M31: =L31*$B$4 -> 4582.9355 | N31: =SUM(L31) -> 213 | O31: =N31*$B$4 -> 4582.9355 | P31: =SUM(N31) -> 213 | Q31: =P31*$B$4 -> 4582.9355 | R31: =SUM(P31) -> 213 | S31: =R31*$B$4 -> 4582.9355 | T31: =SUM(R31) -> 213 | U31: =T31*$B$4 -> 4582.9355 | V31: =SUM(T31) -> 213 | W31: =V31*$B$4 -> 4582.9355 | X31: =SUM(Y31/73370) -> 0.68709677 | Y31: =SUM(C31+E31+G31+I31+K31+M31+O31+Q31+S31+U31+W31) -> 50412.29 | Z31: ='B5'!C30 -> 219 | AA31: =SUM(Z31*$Z$4) -> 2190 | AB31: =SUM(Z31) -> 219 | AC31: =SUM(AB31*$Z$4) -> 2190 | AD31: =SUM(AB31) -> 219 | AE31: =SUM(AD31*$Z$4) -> 2190 | AF31: =SUM(AD31) -> 219 | AG31: =SUM(AF31*$Z$4) -> 2190 | AH31: =SUM(AF31) -> 219 | AI31: =SUM(AH31*$Z$4) -> 2190 | AJ31: =SUM(AH31) -> 219 | AK31: =SUM(AJ31*$Z$4) -> 2190 | AL31: =SUM(AJ31) -> 219 | AM31: =SUM(AL31*$Z$4) -> 2190 | AN31: =SUM(AO31/19600) -> 0.78214286 | AO31: =SUM(AA31+AC31+AE31+AG31+AI31+AK31+AM31) -> 15330 | AQ31: =SUM(AR31/92970) -> 0.70713446 | AR31: =SUM(AO31+Y31) -> 65742.29 | AS31: =SUM(AR31-AR30-AT31) -> -815.03226 | AV31: =IF(AT31>0,AU31,AV30) -> 0.326667 | AW31: =-SUM('B5'!AI30) -> -277 | AX31: =-SUM(AW31-AS31) -> -538.03226 | AY31: =SUM(AX31+AW31) -> -815.03226 | AZ31: =ELEC!A28 -> 0.0348 | BA31: ='General information '!D31 -> 19 | BB31: =SUM('General information '!E31) -> 0.67 | BC31: =IF(AR30>=AR31,0,1) -> 0 | BD31: 19222 | BE31: =(305/1185)*ELEC!Q29 -> 646.80591 | BG31: =#REF!-BE31 -> #REF!
A32: =ELEC!C29 -> 43948 | B32: ='B5'!B31 -> 209 | C32: =B32*$B$4 -> 4496.871 | D32: =SUM(B32) -> 209 | E32: =D32*$B$4 -> 4496.871 | F32: =SUM(D32) -> 209 | G32: =F32*$B$4 -> 4496.871 | H32: =SUM(F32) -> 209 | I32: =H32*$B$4 -> 4496.871 | J32: =SUM(H32) -> 209 | K32: =J32*$B$4 -> 4496.871 | L32: =SUM(J32) -> 209 | M32: =L32*$B$4 -> 4496.871 | N32: =SUM(L32) -> 209 | O32: =N32*$B$4 -> 4496.871 | P32: =SUM(N32) -> 209 | Q32: =P32*$B$4 -> 4496.871 | R32: =SUM(P32) -> 209 | S32: =R32*$B$4 -> 4496.871 | T32: =SUM(R32) -> 209 | U32: =T32*$B$4 -> 4496.871 | V32: =SUM(T32) -> 209 | W32: =V32*$B$4 -> 4496.871 | X32: =SUM(Y32/73370) -> 0.67419355 | Y32: =SUM(C32+E32+G32+I32+K32+M32+O32+Q32+S32+U32+W32) -> 49465.581 | Z32: ='B5'!C31 -> 215 | AA32: =SUM(Z32*$Z$4) -> 2150 | AB32: =SUM(Z32) -> 215 | AC32: =SUM(AB32*$Z$4) -> 2150 | AD32: =SUM(AB32) -> 215 | AE32: =SUM(AD32*$Z$4) -> 2150 | AF32: =SUM(AD32) -> 215 | AG32: =SUM(AF32*$Z$4) -> 2150 | AH32: =SUM(AF32) -> 215 | AI32: =SUM(AH32*$Z$4) -> 2150 | AJ32: =SUM(AH32) -> 215 | AK32: =SUM(AJ32*$Z$4) -> 2150 | AL32: =SUM(AJ32) -> 215 | AM32: =SUM(AL32*$Z$4) -> 2150 | AN32: =SUM(AO32/19600) -> 0.76785714 | AO32: =SUM(AA32+AC32+AE32+AG32+AI32+AK32+AM32) -> 15050 | AQ32: =SUM(AR32/92970) -> 0.69393977 | AR32: =SUM(AO32+Y32) -> 64515.581 | AS32: =SUM(AR32-AR31-AT32) -> -1226.7097 | AV32: =IF(AT32>0,AU32,AV31) -> 0.326667 | AW32: =-SUM('B5'!AI31) -> -322 | AX32: =-SUM(AW32-AS32) -> -904.70968 | AY32: =SUM(AX32+AW32) -> -1226.7097 | AZ32: =ELEC!A29 -> 0.0087 | BA32: ='General information '!D32 -> 18 | BB32: =SUM('General information '!E32) -> 0.68 | BC32: =IF(AR31>=AR32,0,1) -> 0 | BD32: 19222 | BE32: =(305/1185)*ELEC!Q30 -> 262.27426 | BG32: =#REF!-BE32 -> #REF!
A33: =ELEC!C30 -> 43949 | B33: ='B5'!B32 -> 207 | C33: =B33*$B$4 -> 4453.8387 | D33: =SUM(B33) -> 207 | E33: =D33*$B$4 -> 4453.8387 | F33: =SUM(D33) -> 207 | G33: =F33*$B$4 -> 4453.8387 | H33: =SUM(F33) -> 207 | I33: =H33*$B$4 -> 4453.8387 | J33: =SUM(H33) -> 207 | K33: =J33*$B$4 -> 4453.8387 | L33: =SUM(J33) -> 207 | M33: =L33*$B$4 -> 4453.8387 | N33: =SUM(L33) -> 207 | O33: =N33*$B$4 -> 4453.8387 | P33: =SUM(N33) -> 207 | Q33: =P33*$B$4 -> 4453.8387 | R33: =SUM(P33) -> 207 | S33: =R33*$B$4 -> 4453.8387 | T33: =SUM(R33) -> 207 | U33: =T33*$B$4 -> 4453.8387 | V33: =SUM(T33) -> 207 | W33: =V33*$B$4 -> 4453.8387 | X33: =SUM(Y33/73370) -> 0.66774194 | Y33: =SUM(C33+E33+G33+I33+K33+M33+O33+Q33+S33+U33+W33) -> 48992.226 | Z33: ='B5'!C32 -> 213 | AA33: =SUM(Z33*$Z$4) -> 2130 | AB33: =SUM(Z33) -> 213 | AC33: =SUM(AB33*$Z$4) -> 2130 | AD33: =SUM(AB33) -> 213 | AE33: =SUM(AD33*$Z$4) -> 2130 | AF33: =SUM(AD33) -> 213 | AG33: =SUM(AF33*$Z$4) -> 2130 | AH33: =SUM(AF33) -> 213 | AI33: =SUM(AH33*$Z$4) -> 2130 | AJ33: =SUM(AH33) -> 213 | AK33: =SUM(AJ33*$Z$4) -> 2130 | AL33: =SUM(AJ33) -> 213 | AM33: =SUM(AL33*$Z$4) -> 2130 | AN33: =SUM(AO33/19600) -> 0.76071429 | AO33: =SUM(AA33+AC33+AE33+AG33+AI33+AK33+AM33) -> 14910 | AQ33: =SUM(AR33/92970) -> 0.68734243 | AR33: =SUM(AO33+Y33) -> 63902.226 | AS33: =SUM(AR33-AR32-AT33) -> -613.35484 | AV33: =IF(AT33>0,AU33,AV32) -> 0.326667 | AW33: =-SUM('B5'!AI32) -> -230 | AX33: =-SUM(AW33-AS33) -> -383.35484 | AY33: =SUM(AX33+AW33) -> -613.35484 | AZ33: =ELEC!A30 -> 0.0174 | BA33: ='General information '!D33 -> 18.5 | BB33: =SUM('General information '!E33) -> 0.7 | BC33: =IF(AR32>=AR33,0,1) -> 0 | BD33: 19222 | BE33: =(305/1185)*ELEC!Q31 -> 334.08439 | BG33: =#REF!-BE33 -> #REF!
A34: =ELEC!C31 -> 43950 | B34: ='B5'!B33 -> 248 | C34: =B34*$B$4 -> 5336 | D34: =SUM(B34) -> 248 | E34: =D34*$B$4 -> 5336 | F34: =SUM(D34) -> 248 | G34: =F34*$B$4 -> 5336 | H34: =SUM(F34) -> 248 | I34: =H34*$B$4 -> 5336 | J34: =SUM(H34) -> 248 | K34: =J34*$B$4 -> 5336 | L34: =SUM(J34) -> 248 | M34: =L34*$B$4 -> 5336 | N34: =SUM(L34) -> 248 | O34: =N34*$B$4 -> 5336 | P34: =SUM(N34) -> 248 | Q34: =P34*$B$4 -> 5336 | R34: =SUM(P34) -> 248 | S34: =R34*$B$4 -> 5336 | T34: =SUM(R34) -> 248 | U34: =T34*$B$4 -> 5336 | V34: =SUM(T34) -> 248 | W34: =V34*$B$4 -> 5336 | X34: =SUM(Y34/73370) -> 0.8 | Y34: =SUM(C34+E34+G34+I34+K34+M34+O34+Q34+S34+U34+W34) -> 58696 | Z34: ='B5'!C33 -> 254 | AA34: =SUM(Z34*$Z$4) -> 2540 | AB34: =SUM(Z34) -> 254 | AC34: =SUM(AB34*$Z$4) -> 2540 | AD34: =SUM(AB34) -> 254 | AE34: =SUM(AD34*$Z$4) -> 2540 | AF34: =SUM(AD34) -> 254 | AG34: =SUM(AF34*$Z$4) -> 2540 | AH34: =SUM(AF34) -> 254 | AI34: =SUM(AH34*$Z$4) -> 2540 | AJ34: =SUM(AH34) -> 254 | AK34: =SUM(AJ34*$Z$4) -> 2540 | AL34: =SUM(AJ34) -> 254 | AM34: =SUM(AL34*$Z$4) -> 2540 | AN34: =SUM(AO34/19600) -> 0.90714286 | AO34: =SUM(AA34+AC34+AE34+AG34+AI34+AK34+AM34) -> 17780 | AQ34: =SUM(AR34/92970) -> 0.82258793 | AR34: =SUM(AO34+Y34) -> 76476 | AS34: =SUM(AR34-AR33-AT34) -> 168.77419 | AT34: 12405 | AU34: 0.284 | AV34: =IF(AT34>0,AU34,AV33) -> 0.284 | AW34: =-SUM('B5'!AI33) -> -302.8 | AX34: =-SUM(AW34-AS34) -> 471.57419 | AY34: =SUM(AX34+AW34) -> 168.77419 | AZ34: =ELEC!A31 -> 0.0174 | BA34: ='General information '!D34 -> 19 | BB34: =SUM('General information '!E34) -> 0.69 | BC34: =IF(AR33>=AR34,0,1) -> 1 | BD34: 19222 | BE34: =(305/1185)*ELEC!#REF! -> #REF! | BG34: =#REF!-BE34 -> #REF!
A35: =ELEC!C32 -> 43951 | B35: ='B5'!B34 -> 245.5 | C35: =B35*$B$4 -> 5282.2097 | D35: =SUM(B35) -> 245.5 | E35: =D35*$B$4 -> 5282.2097 | F35: =SUM(D35) -> 245.5 | G35: =F35*$B$4 -> 5282.2097 | H35: =SUM(F35) -> 245.5 | I35: =H35*$B$4 -> 5282.2097 | J35: =SUM(H35) -> 245.5 | K35: =J35*$B$4 -> 5282.2097 | L35: =SUM(J35) -> 245.5 | M35: =L35*$B$4 -> 5282.2097 | N35: =SUM(L35) -> 245.5 | O35: =N35*$B$4 -> 5282.2097 | P35: =SUM(N35) -> 245.5 | Q35: =P35*$B$4 -> 5282.2097 | R35: =SUM(P35) -> 245.5 | S35: =R35*$B$4 -> 5282.2097 | T35: =SUM(R35) -> 245.5 | U35: =T35*$B$4 -> 5282.2097 | V35: =SUM(T35) -> 245.5 | W35: =V35*$B$4 -> 5282.2097 | X35: =SUM(Y35/73370) -> 0.79193548 | Y35: =SUM(C35+E35+G35+I35+K35+M35+O35+Q35+S35+U35+W35) -> 58104.306 | Z35: ='B5'!C34 -> 251 | AA35: =SUM(Z35*$Z$4) -> 2510 | AB35: =SUM(Z35) -> 251 | AC35: =SUM(AB35*$Z$4) -> 2510 | AD35: =SUM(AB35) -> 251 | AE35: =SUM(AD35*$Z$4) -> 2510 | AF35: =SUM(AD35) -> 251 | AG35: =SUM(AF35*$Z$4) -> 2510 | AH35: =SUM(AF35) -> 251 | AI35: =SUM(AH35*$Z$4) -> 2510 | AJ35: =SUM(AH35) -> 251 | AK35: =SUM(AJ35*$Z$4) -> 2510 | AL35: =SUM(AJ35) -> 251 | AM35: =SUM(AL35*$Z$4) -> 2510 | AN35: =SUM(AO35/19600) -> 0.89642857 | AO35: =SUM(AA35+AC35+AE35+AG35+AI35+AK35+AM35) -> 17570 | AQ35: =SUM(AR35/92970) -> 0.81396479 | AR35: =SUM(AO35+Y35) -> 75674.306 | AS35: =SUM(AR35-AR34-AT35) -> -801.69355 | AV35: =IF(AT35>0,AU35,AV34) -> 0.284 | AW35: =-SUM('B5'!AI34) -> -281 | AX35: =-SUM(AW35-AS35) -> -520.69355 | AY35: =SUM(AX35+AW35) -> -801.69355 | AZ35: =ELEC!A32 -> 0.013 | BA35: ='General information '!D35 -> 21 | BB35: =SUM('General information '!E35) -> 0.75 | BC35: =IF(AR34>=AR35,0,1) -> 0 | BD35: 19222 | BE35: =(305/1185)*ELEC!#REF! -> #REF! | BG35: =#REF!-BE35 -> #REF!
AR36: NB delivery | AS36: =COUNT(AT6:AT35) -> 2 | AT36: =SUM(AT6:AT35) -> 23015 | AU36: =SUM(AU6:AU35)/AS36 -> 0.3053335 | AX36: =SUM(AX6:AX35) -> -15289.903 | AY36: =SUM(AY6:AY35) -> -25043.403
AT37: =+AT36*AU36 -> 7027.2505
AS39: =SUM(AS6:AS35)/'EDl log'!A35 -> -834.78011

Sheet Sheet1
A1: TOTAL CH RH | B1: TOTAL CH cons KW | C1: TOTAL ELIC KW | D1: TOTAL EDL | E1: TOTAL GEN KW | F1: GEN HR | G1: WATER IN | H1: TOTAL CT | I1: TOTAL WATER | J1: Date
A2: =ELEC!T3+ELEC!X1+ELEC!AB3 -> #VALUE! | B2: =ELEC!AF3 -> 246 | C2: =ELEC!N3 -> 7662.2 | D2: =C2-E2 -> 5231.2 | E2: =ELEC!Q3 -> 2431 | F2: =GEN!Z2 -> 4 | G2: =WATER!C5+WATER!H5 -> 0 | H2: =WATER!L5 -> 5 | I2: =WATER!BC5+WATER!BD5+WATER!BE6-Sheet1!G2 -> 103.5 | J2: ='B5'!A4 -> 43921
A3: =ELEC!T4+ELEC!X2+ELEC!AB4 -> 1 | B3: =ELEC!AF4 -> 308 | C3: =ELEC!N4 -> 7437.6 | D3: =C3-E3 -> 5856.6 | E3: =ELEC!Q4 -> 1581 | F3: =GEN!Z3 -> 3 | G3: =WATER!C6+WATER!H6 -> 107 | H3: =WATER!L6 -> 0 | I3: =WATER!BC6+WATER!BD6+WATER!BE7-Sheet1!G3 -> -89.6 | J3: ='B5'!A5 -> 43922
A4: =ELEC!T5+ELEC!X5+ELEC!AB5 -> 2 | B4: =ELEC!AF5 -> 519 | C4: =ELEC!N5 -> 8665.2 | D4: =C4-E4 -> 7403.2 | E4: =ELEC!Q5 -> 1262 | F4: =GEN!Z4 -> 3 | G4: =WATER!C7+WATER!H7 -> 0 | H4: =WATER!L7 -> 0 | I4: =WATER!BC7+WATER!BD7+WATER!BE8-Sheet1!G4 -> 189.1 | J4: ='B5'!A6 -> 43923
A5: =ELEC!T6+ELEC!X6+ELEC!AB6 -> 1 | B5: =ELEC!AF6 -> 243 | C5: =ELEC!N6 -> 7670.4 | D5: =C5-E5 -> 6028.4 | E5: =ELEC!Q6 -> 1642 | F5: =GEN!Z5 -> 3 | G5: =WATER!C8+WATER!H8 -> 300 | H5: =WATER!L8 -> 0 | I5: =WATER!BC8+WATER!BD8+WATER!BE9-Sheet1!G5 -> -284.1 | J5: ='B5'!A7 -> 43924
A6: =ELEC!T7+ELEC!X7+ELEC!AB7 -> 9 | B6: =ELEC!AF7 -> 1921 | C6: =ELEC!N7 -> 8538.8 | D6: =C6-E6 -> 6520.8 | E6: =ELEC!Q24 -> 2018 | F6: =GEN!Z6 -> 3.5 | G6: =WATER!C9+WATER!H9 -> 0 | H6: =WATER!L9 -> 709 | I6: =WATER!BC9+WATER!BD9+WATER!BE10-Sheet1!G6 -> -42.8 | J6: ='B5'!A8 -> 43925
A7: =ELEC!T8+ELEC!X8+ELEC!AB8 -> 0 | B7: =ELEC!AF8 -> 0 | C7: =ELEC!N8 -> 10057.8 | D7: =C7-E7 -> 8267.8 | E7: =ELEC!Q8 -> 1790 | F7: =GEN!Z7 -> 2.5 | G7: =WATER!C10+WATER!H10 -> 166 | H7: =WATER!L10 -> 2 | I7: =WATER!BC10+WATER!BD10+WATER!BE11-Sheet1!G7 -> -151.9 | J7: ='B5'!A9 -> 43926
A8: =ELEC!T9+ELEC!X9+ELEC!AB9 -> 1 | B8: =ELEC!AF9 -> 310 | C8: =ELEC!N9 -> 7909.4 | D8: =C8-E8 -> 6510.4 | E8: =ELEC!Q9 -> 1399 | F8: =GEN!Z8 -> 3 | G8: =WATER!C11+WATER!H11 -> 19 | H8: =WATER!L11 -> 21 | I8: =WATER!BC11+WATER!BD11+WATER!BE12-Sheet1!G8 -> -20.4 | J8: ='B5'!A10 -> 43927
A9: =ELEC!T10+ELEC!X10+ELEC!AB10 -> 4 | B9: =ELEC!AF10 -> 1023 | C9: =ELEC!N10 -> 10815.6 | D9: =C9-E9 -> 9204.6 | E9: =ELEC!Q10 -> 1611 | F9: =GEN!Z9 -> 3.48 | G9: =WATER!C12+WATER!H12 -> 0 | H9: =WATER!L12 -> 1 | I9: =WATER!BC12+WATER!BD12+WATER!BE13-Sheet1!G9 -> -51.1 | J9: ='B5'!A11 -> 43928
A10: =ELEC!T11+ELEC!X11+ELEC!AB11 -> 2 | B10: =ELEC!AF11 -> 751 | C10: =ELEC!N11 -> 9103 | D10: =C10-E10 -> 7236 | E10: =ELEC!Q11 -> 1867 | F10: =GEN!Z10 -> 3.52 | G10: =WATER!C13+WATER!H13 -> 29 | H10: =WATER!L13 -> 6 | I10: =WATER!BC13+WATER!BD13+WATER!BE14-Sheet1!G10 -> 156 | J10: ='B5'!A12 -> 43929
A11: =ELEC!T12+ELEC!X12+ELEC!AB12 -> 2 | B11: =ELEC!AF12 -> 426 | C11: =ELEC!N12 -> 8022.6 | D11: =C11-E11 -> 7022.6 | E11: =ELEC!Q12 -> 1000 | F11: =GEN!Z11 -> 3 | G11: =WATER!C14+WATER!H14 -> 287 | H11: =WATER!L14 -> 4 | I11: =WATER!BC14+WATER!BD14+WATER!BE15-Sheet1!G11 -> -243.9 | J11: ='B5'!A13 -> 43930
A12: =ELEC!T13+ELEC!X13+ELEC!AB13 -> 1 | B12: =ELEC!AF13 -> 308 | C12: =ELEC!N13 -> 8603.4 | D12: =C12-E12 -> 6603.4 | E12: =ELEC!Q13 -> 2000 | F12: =GEN!Z12 -> 3 | G12: =WATER!C15+WATER!H15 -> 0 | H12: =WATER!L15 -> 3 | I12: =WATER!BC15+WATER!BD15+WATER!BE16-Sheet1!G12 -> -36.1 | J12: ='B5'!A14 -> 43931
A13: =ELEC!T14+ELEC!X14+ELEC!AB14 -> 2 | B13: =ELEC!AF14 -> 472 | C13: =ELEC!N14 -> 8743 | D13: =C13-E13 -> 7743 | E13: =ELEC!Q14 -> 1000 | F13: =GEN!Z13 -> 5 | G13: =WATER!C16+WATER!H16 -> 0 | H13: =WATER!L16 -> 1 | I13: =WATER!BC16+WATER!BD16+WATER!BE17-Sheet1!G13 -> -67.4 | J13: ='B5'!A15 -> 43932
A14: =ELEC!T15+ELEC!X15+ELEC!AB15 -> 0 | B14: =ELEC!AF15 -> 196 | C14: =ELEC!N15 -> 8764 | D14: =C14-E14 -> 7764 | E14: =ELEC!Q15 -> 1000 | F14: =GEN!Z14 -> 1 | G14: =WATER!C17+WATER!H17 -> 0 | H14: =WATER!L17 -> 1 | I14: =WATER!BC17+WATER!BD17+WATER!BE18-Sheet1!G14 -> -71.2 | J14: ='B5'!A16 -> 43933
A15: =ELEC!T16+ELEC!X16+ELEC!AB16 -> 1 | B15: =ELEC!AF16 -> 237 | C15: =ELEC!N16 -> 8688.4 | D15: =C15-E15 -> 6574.4 | E15: =ELEC!Q16 -> 2114 | F15: =GEN!Z15 -> 3 | G15: =WATER!C18+WATER!H18 -> 45 | H15: =WATER!L18 -> 4 | I15: =WATER!BC18+WATER!BD18+WATER!BE19-Sheet1!G15 -> -92.4 | J15: ='B5'!A17 -> 43934
A16: =ELEC!T17+ELEC!X17+ELEC!AB17 -> 3 | B16: =ELEC!AF17 -> 616 | C16: =ELEC!N17 -> 9282 | D16: =C16-E16 -> 7532 | E16: =ELEC!Q17 -> 1750 | F16: =GEN!Z16 -> 4.9 | G16: =WATER!C19+WATER!H19 -> 0 | H16: =WATER!L19 -> 2 | I16: =WATER!BC19+WATER!BD19+WATER!BE20-Sheet1!G16 -> -45.5 | J16: ='B5'!A18 -> 43935
A17: =ELEC!T18+ELEC!X18+ELEC!AB18 -> 3 | B17: =ELEC!AF18 -> 776 | C17: =ELEC!N18 -> 10771.6 | D17: =C17-E17 -> 10135.6 | E17: =ELEC!Q18 -> 636 | F17: =GEN!Z17 -> 2.6 | G17: =WATER!C20+WATER!H20 -> 19 | H17: =WATER!L20 -> 5 | I17: =WATER!BC20+WATER!BD20+WATER!BE21-Sheet1!G17 -> -79.2 | J17: ='B5'!A19 -> 43936
A18: =ELEC!T19+ELEC!X19+ELEC!AB19 -> 2 | B18: =ELEC!AF19 -> 548 | C18: =ELEC!N19 -> 8246 | D18: =C18-E18 -> 6457 | E18: =ELEC!Q19 -> 1789 | F18: =GEN!Z18 -> 1 | G18: =WATER!C21+WATER!H21 -> 50 | H18: =WATER!L21 -> 0 | I18: =WATER!BC21+WATER!BD21+WATER!BE22-Sheet1!G18 -> 2.2 | J18: ='B5'!A20 -> 43937
... A29: =ELEC!T30+ELEC!X30+ELEC!AB30 -> 1 | B29: =ELEC!AF30 -> 146 | C29: =ELEC!N30 -> 8764 | D29: =C29-E29 -> 7745 | E29: =ELEC!Q30 -> 1019 | F29: =GEN!Z29 -> 3.5 | G29: =WATER!C32+WATER!H32 -> 1 | H29: =WATER!L32 -> 0 | I29: =WATER!BC32+WATER!BD32+WATER!BE33-Sheet1!G29 -> -78.55 | J29: ='B5'!A31 -> 43948
A30: =ELEC!T31+ELEC!X31+ELEC!#REF! -> #REF! | B30: =ELEC!AF31 -> 681 | C30: =ELEC!N31 -> 9068.4 | D30: =C30-E30 -> 7770.4 | E30: =ELEC!Q31 -> 1298 | F30: =GEN!Z30 -> 2.42 | G30: =WATER!C33+WATER!H33 -> 0 | H30: =WATER!L33 -> 2 | I30: =WATER!BC33+WATER!BD33+WATER!BE34-Sheet1!G30 -> 90.6 | J30: ='B5'!A32 -> 43949
A31: =ELEC!T32+ELEC!X32+ELEC!AB31 -> 2 | B31: =ELEC!AF32 -> 361 | C31: =ELEC!N32 -> 10173.2 | D31: =C31-E31 -> 8403.2 | E31: =ELEC!Q32 -> 1770 | F31: =GEN!Z31 -> 3.22 | G31: =WATER!C34+WATER!H34 -> 0 | H31: =WATER!L34 -> 11 | I31: =WATER!BC34+WATER!BD34+WATER!BE35-Sheet1!G31 -> -36.5 | J31: ='B5'!A33 -> 43950
A32: =ELEC!#REF!+ELEC!#REF!+ELEC!#REF! -> #REF! | B32: =ELEC!#REF! -> #REF! | C32: =ELEC!#REF! -> #REF! | D32: =C32-E32 -> #REF! | E32: =ELEC!#REF! -> #REF! | F32: =GEN!#REF! -> #REF! | G32: =WATER!#REF!+WATER!#REF! -> #REF! | H32: =WATER!#REF! -> #REF! | I32: =WATER!#REF!+WATER!#REF!+WATER!BE36-Sheet1!G32 -> #REF!

Sheet Report
B1: Boiler Fuel | C1: Steam Fuel | D1: GEN FUEL | E1: FUEL TOTAL | F1: CT/mᶾ | G1: Water Consumption | H1: Chiller KW | I1: GEN KW | J1: EDL KW | K1: occ | L1: covers | M1: temp. C⁰ | N1: RH %
B3: ='B5'!V3 -> 0 | C3: ='B5'!AH3 -> 0 | E3: =B3+C3+D3 -> 0
A4: 42704 | B4: 810 | C4: -606.1 | D4: 1420.5021 | E4: 1624.4021 | F4: 106 | G4: -58.4 | H4: 6284 | I4: 2399 | J4: 23932 | K4: 0 | L4: 0 | M4: 0 | N4: 0
A5: ='B5'!A5 -> 43922 | B5: ='B5'!V5 -> 267 | C5: ='B5'!AH5 -> 0 | D5: =GEN!AI3 -> 625.70042 | E5: =B5+C5+D5 -> 892.70042 | F5: =WATER!L5 -> 5 | G5: =WATER!BG5 -> -36.1 | H5: =ELEC!AF3 -> 246 | I5: =ELEC!Q3 -> 2431 | J5: =ELEC!R3 -> 5231.2
A6: ='B5'!A6 -> 43923 | B6: ='B5'!V6 -> 307 | C6: ='B5'!AH6 -> 0 | D6: =GEN!AI4 -> 406.92405 | E6: =B6+C6+D6 -> 713.92405 | F6: =WATER!L6 -> 0 | G6: =WATER!BG6 -> 127.9 | H6: =ELEC!AF4 -> 308 | I6: =ELEC!Q4 -> 1581 | J6: =ELEC!R4 -> 5856.6
A7: ='B5'!A7 -> 43924 | B7: ='B5'!V7 -> 351 | C7: ='B5'!AH7 -> 0 | D7: =GEN!AI5 -> 324.81857 | E7: =B7+C7+D7 -> 675.81857 | F7: =WATER!L7 -> 0 | G7: =WATER!BG7 -> -47.5 | H7: =ELEC!AF5 -> 519 | I7: =ELEC!Q5 -> 1262 | J7: =ELEC!R5 -> 7403.2
A8: ='B5'!A8 -> 43925 | B8: ='B5'!V8 -> 271 | C8: ='B5'!AH8 -> 0 | D8: =GEN!AI6 -> 422.62447 | E8: =B8+C8+D8 -> 693.62447 | F8: =WATER!L8 -> 0 | G8: =WATER!BG8 -> 151.1 | H8: =ELEC!AF6 -> 243 | I8: =ELEC!Q6 -> 1642 | J8: =ELEC!R6 -> 6028.4
A9: ='B5'!A9 -> 43926 | B9: ='B5'!V9 -> 252 | C9: ='B5'!AH9 -> 0 | D9: =GEN!AI7 -> 435.23629 | E9: =B9+C9+D9 -> 687.23629 | F9: =WATER!L9 -> 709 | G9: =WATER!BG9 -> -34.4 | H9: =ELEC!AF7 -> 1921 | I9: =ELEC!Q7 -> 1691 | J9: =ELEC!R7 -> 6847.8
A10: ='B5'!A10 -> 43927 | B10: ='B5'!V10 -> 444 | C10: ='B5'!AH10 -> 0 | D10: =GEN!AI8 -> 460.7173 | E10: =B10+C10+D10 -> 904.7173 | F10: =WATER!L10 -> 2 | G10: =WATER!BG10 -> -14.7 | H10: =ELEC!AF8 -> 0 | I10: =ELEC!Q8 -> 1790 | J10: =ELEC!R8 -> 8267.8
A11: ='B5'!A11 -> 43928 | B11: ='B5'!V11 -> 164 | C11: ='B5'!AH11 -> 0 | D11: =GEN!AI9 -> 360.08017 | E11: =B11+C11+D11 -> 524.08017 | F11: =WATER!L11 -> 21 | G11: =WATER!BG11 -> 19.8 | H11: =ELEC!AF9 -> 310 | I11: =ELEC!Q9 -> 1399 | J11: =ELEC!R9 -> 6510.4
A12: ='B5'!A12 -> 43929 | B12: ='B5'!V12 -> 305 | C12: ='B5'!AH12 -> 0 | D12: =GEN!AI10 -> 414.64557 | E12: =B12+C12+D12 -> 719.64557 | F12: =WATER!L12 -> 1 | G12: =WATER!BG12 -> -25.7 | H12: =ELEC!AF10 -> 1023 | I12: =ELEC!Q10 -> 1611 | J12: =ELEC!R10 -> 9204.6
A13: ='B5'!A13 -> 43930 | B13: ='B5'!V13 -> 384 | C13: ='B5'!AH13 -> 231.7 | D13: =GEN!AI11 -> 480.53586 | E13: =B13+C13+D13 -> 1096.2359 | F13: =WATER!L13 -> 6 | G13: =WATER!BG13 -> -33.5 | H13: =ELEC!AF11 -> 751 | I13: =ELEC!Q11 -> 1867 | J13: =ELEC!R11 -> 7236
A14: ='B5'!A14 -> 43931 | B14: ='B5'!V14 -> 426 | C14: ='B5'!AH14 -> 0 | D14: =GEN!AI12 -> 257.38397 | E14: =B14+C14+D14 -> 683.38397 | F14: =WATER!L14 -> 4 | G14: =WATER!BG14 -> 145.6 | H14: =ELEC!AF12 -> 426 | I14: =ELEC!Q12 -> 1000 | J14: =ELEC!R12 -> 7022.6
A15: ='B5'!A15 -> 43932 | B15: ='B5'!V15 -> 194 | C15: ='B5'!AH15 -> 0 | D15: =GEN!AI13 -> 514.76793 | E15: =B15+C15+D15 -> 708.76793 | F15: =WATER!L15 -> 3 | G15: =WATER!BG15 -> -16.1 | H15: =ELEC!AF13 -> 308 | I15: =ELEC!Q13 -> 2000 | J15: =ELEC!R13 -> 6603.4
A16: ='B5'!A16 -> 43933 | B16: ='B5'!V16 -> 308 | C16: ='B5'!AH16 -> 0 | D16: =GEN!AI14 -> 257.38397 | E16: =B16+C16+D16 -> 565.38397 | F16: =WATER!L16 -> 1 | G16: =WATER!BG16 -> -20 | H16: =ELEC!AF14 -> 472 | I16: =ELEC!Q14 -> 1000 | J16: =ELEC!R14 -> 7743
... A33: ='B5'!A33 -> 43950 | B33: ='B5'!V33 -> 290 | C33: ='B5'!AH33 -> 12.8 | D33: =GEN!AI31 -> 334.08439 | E33: =B33+C33+D33 -> 636.88439 | F33: =WATER!L33 -> 2 | G33: =WATER!BG33 -> -25.8 | H33: =ELEC!AF31 -> 681 | I33: =ELEC!Q31 -> 1298 | J33: =ELEC!R31 -> 7770.4
A34: ='B5'!A34 -> 43951 | B34: ='B5'!V34 -> 281 | C34: ='B5'!AH34 -> 0 | D34: =GEN!AI32 -> 455.56962 | E34: =B34+C34+D34 -> 736.56962 | F34: =WATER!L34 -> 11 | G34: =WATER!BG34 -> 63.3 | H34: =ELEC!#REF! -> #REF! | I34: =ELEC!#REF! -> #REF! | J34: =ELEC!#REF! -> #REF!

Sheet Sheet5
T3: Outdoor conditions
C4: Date | D4: Total Boiler running H | E4: AVE CONSUM | F4: Total Steam running H | G4: AVE CONSUM | H4: Total GEN running H | I4: AVE CONSUM | J4: Actual Diesel Consumption | K4: Actual Gas Consumption | L4: Total ELEC power | M4: Gen ELEC power | N4: EDL ELEC power | O4: Chillers running H | P4: Total Water delivery | Q4: Total water consumption | R4: Total water in tanks | S4: Occupancy | T4: AVE TEPM | U4: AVE Humidity
C5: 42429 | D5: ='B5'!AL4 -> 3 | E5: =D5*90 -> 270 | F5: ='B5'!AM4 -> 0 | G5: =F5*107 -> 0 | H5: =GEN!Z3 -> 3
C6: 42430 | D6: ='B5'!AL5 -> 5 | E6: =D6*90 -> 450 | F6: ='B5'!AM5 -> 0 | G6: =F6*107 -> 0
C7: 42431 | D7: ='B5'!AL6 -> 2 | E7: =D7*90 -> 180 | F7: ='B5'!AM6 -> 0 | G7: =F7*107 -> 0
C8: 42432 | D8: ='B5'!AL7 -> 5 | E8: =D8*90 -> 450 | F8: ='B5'!AM7 -> 0 | G8: =F8*107 -> 0
C9: 42433 | D9: ='B5'!AL8 -> 3 | E9: =D9*90 -> 270 | F9: ='B5'!AM8 -> 0 | G9: =F9*107 -> 0
C10: 42434 | D10: ='B5'!AL9 -> 2 | E10: =D10*90 -> 180 | F10: ='B5'!AM9 -> 0 | G10: =F10*107 -> 0
C11: 42435 | D11: ='B5'!AL10 -> 7 | E11: =D11*90 -> 630 | F11: ='B5'!AM10 -> 0 | G11: =F11*107 -> 0
C12: 42436 | D12: ='B5'!AL11 -> 2 | E12: =D12*90 -> 180 | F12: ='B5'!AM11 -> 0 | G12: =F12*107 -> 0
C13: 42437 | D13: ='B5'!AL12 -> 4 | E13: =D13*90 -> 360 | F13: ='B5'!AM12 -> 0 | G13: =F13*107 -> 0
C14: 42438 | D14: ='B5'!AL13 -> 5 | E14: =D14*90 -> 450 | F14: ='B5'!AM13 -> 4 | G14: =F14*107 -> 428
C15: 42439 | D15: ='B5'!AL14 -> 6 | E15: =D15*90 -> 540 | F15: ='B5'!AM14 -> 0 | G15: =F15*107 -> 0
C16: 42440 | D16: ='B5'!AL15 -> 2 | E16: =D16*90 -> 180 | F16: ='B5'!AM15 -> 0 | G16: =F16*107 -> 0
C17: 42441 | D17: ='B5'!AL16 -> 3 | E17: =D17*90 -> 270 | F17: ='B5'!AM16 -> 0 | G17: =F17*107 -> 0
... C35: 42459 | D35: ='B5'!AL34 -> 3 | E35: =D35*90 -> 270 | F35: ='B5'!AM34 -> 0 | G35: =F35*107 -> 0
C36: 42460 | D36: ='B5'!#REF! -> #REF! | E36: =D36*90 -> #REF! | F36: ='B5'!#REF! -> #REF! | G36: =F36*107 -> #REF!
C37: 42461 | D37: ='B5'!#REF! -> #REF! | E37: =D37*90 -> #REF! | F37: ='B5'!#REF! -> #REF! | G37: =F37*107 -> #REF!

Sheet GEN
B1: GEN1 | C1: RUN HR | D1: Fuel Counter Index | E1: Cons /day | F1: Diesel L/H | H1: next service | I1: ALARM | J1: GEN2 | K1: RUN HR | L1: Fuel Counter Index | M1: Cons /day | N1: Diesel L/H | P1: next service | Q1: ALARM | R1: GEN3 | S1: RUN HR | T1: Fuel Counter Index | U1: Cons /day | V1: Diesel L/H | X1: next service | Y1: ALARM | Z1: RH total | AA1: Gen Con /day | AB1: Total Deisel Cons/day | AC1: H /L | AD1: TOAL KW GEN | AI1: fuel Consuption | AK1: AVG KW/h
A2: =ELEC!C2 -> 43921 | B2: 8621 | C2: 0 | D2: =[1]GEN!D33 -> 146464 | E2: =[1]GEN!E33 -> 0 | F2: =[1]GEN!F33 -> 0 | G2: =[1]GEN!G33 -> #REF! | H2: =[1]GEN!H33 -> 8497 | I2: =[1]GEN!I33 -> oil change | J2: =[1]GEN!J33 -> 10689 | K2: =[1]GEN!K33 -> 0 | ... AK2: =[1]GEN!AK33 -> #REF!
A3: =ELEC!C3 -> 43922 | B3: 8621 | C3: =B3-B2 -> 0 | D3: =D2 -> 146464 | E3: =SUM(D3-D2) -> 0 | F3: =IF(C3>0,E3/C3,0) -> 0 | G3: =[3]GEN!G32 -> 0 | H3: =H2 -> 8497 | I3: =IF(B3-H3<=0,"ok","oil change") -> oil change | J3: =J2 -> 10689 | K3: =J3-J2 -> 0 | L3: =L2 -> 237072.3 | M3: =SUM(L3-L2) -> 0 | N3: =IF(K3>0,M3/K3,0) -> 0 | O3: =[3]GEN!O32 -> 0 | P3: =P2 -> 10873 | Q3: =IF(J3-P3<=0,"ok","oil change") -> ok | R3: 11033 | S3: =R3-R2 -> 3 | T3: 213766.9 | U3: =SUM(T3-T2) -> 849.9 | V3: =IF(S3>0,U3/S3,0) -> 283.3 | W3: =[3]GEN!W32 -> 0 | X3: =X2 -> 11529 | Y3: =IF(R3-X3<=0,"ok","oil change") -> ok | Z3: =C3+K3+S3 -> 3 | AA3: =U3+M3+E3 -> 849.9 | AB3: =V3+N3+F3 -> 283.3 | AC3: =IF(Z3>0,AA3/Z3,0) -> 283.3 | AD3: =ELEC!Q3 -> 2431 | AE3: =SUM(AD3/Z3) -> 810.33333 | AF3: =SUM(AE3/1600) -> 0.50645833 | AG3: =SUM(360*AF3) -> 182.325 | AH3: =SUM(AC3-AG3) -> 100.975 | AI3: =AD3*AJ3 -> 625.70042 | AJ3: =305/1185 -> 0.25738397 | AK3: =AI3/Z3 -> 208.56681
A4: =ELEC!C4 -> 43923 | B4: =B3 -> 8621 | C4: =B4-B3 -> 0 | D4: =D3 -> 146464 | E4: =SUM(D4-D3) -> 0 | F4: =IF(C4>0,E4/C4,0) -> 0 | H4: =H3 -> 8497 | I4: =IF(B4-H4<=0,"ok","oil change") -> oil change | J4: =J3 -> 10689 | K4: =J4-J3 -> 0 | L4: =L3 -> 237072.3 | M4: =SUM(L4-L3) -> 0 | N4: =IF(K4>0,M4/K4,0) -> 0 | P4: =P3 -> 10873 | Q4: =IF(J4-P4<=0,"ok","oil change") -> ok | R4: 11036 | S4: =R4-R3 -> 3 | T4: 214642 | U4: =SUM(T4-T3) -> 875.1 | V4: =IF(S4>0,U4/S4,0) -> 291.7 | X4: =X3 -> 11529 | Y4: =IF(R4-X4<=0,"ok","oil change") -> ok | Z4: =C4+K4+S4 -> 3 | AA4: =U4+M4+E4 -> 875.1 | AB4: =V4+N4+F4 -> 291.7 | AC4: =IF(Z4>0,AA4/Z4,0) -> 291.7 | AD4: =ELEC!Q4 -> 1581 | AE4: =SUM(AD4/Z4) -> 527 | AF4: =SUM(AE4/1600) -> 0.329375 | AG4: =SUM(360*AF4) -> 118.575 | AH4: =SUM(AC4-AG4) -> 173.125 | AI4: =AD4*AJ4 -> 406.92405 | AJ4: =305/1185 -> 0.25738397 | AK4: =AI4/Z4 -> 135.64135
A5: =ELEC!C5 -> 43924 | B5: =B4 -> 8621 | C5: =B5-B4 -> 0 | D5: =D4 -> 146464 | E5: =SUM(D5-D4) -> 0 | F5: =IF(C5>0,E5/C5,0) -> 0 | H5: 8497 | I5: =IF(B5-H5<=0,"ok","oil change") -> oil change | J5: =J4 -> 10689 | K5: =J5-J4 -> 0 | L5: =L4 -> 237072.3 | M5: =SUM(L5-L4) -> 0 | N5: =IF(K5>0,M5/K5,0) -> 0 | P5: =P4 -> 10873 | Q5: =IF(J5-P5<=0,"ok","oil change") -> ok | R5: 11039 | S5: =R5-R4 -> 3 | T5: 215521 | U5: =SUM(T5-T4) -> 879 | V5: =IF(S5>0,U5/S5,0) -> 293 | X5: =X4 -> 11529 | Y5: =IF(R5-X5<=0,"ok","oil change") -> ok | Z5: =C5+K5+S5 -> 3 | AA5: =U5+M5+E5 -> 879 | AB5: =V5+N5+F5 -> 293 | AC5: =IF(Z5>0,AA5/Z5,0) -> 293 | AD5: =ELEC!Q5 -> 1262 | AE5: =SUM(AD5/Z5) -> 420.66667 | AF5: =SUM(AE5/1600) -> 0.26291667 | AG5: =SUM(320*AF5) -> 84.133333 | AH5: =SUM(AC5-AG5) -> 208.86667 | AI5: =AD5*AJ5 -> 324.81857 | AJ5: =305/1185 -> 0.25738397 | AK5: =AI5/Z5 -> 108.27286
A6: =ELEC!C6 -> 43925 | B6: =B5 -> 8621 | C6: =B6-B5 -> 0 | D6: =D5 -> 146464 | E6: =SUM(D6-D5) -> 0 | F6: =IF(C6>0,E6/C6,0) -> 0 | H6: =H5 -> 8497 | I6: =IF(B6-H6<=0,"ok","oil change") -> oil change | J6: =J5 -> 10689 | K6: =J6-J5 -> 0 | L6: =L5 -> 237072.3 | M6: =SUM(L6-L5) -> 0 | N6: =IF(K6>0,M6/K6,0) -> 0 | P6: =P5 -> 10873 | Q6: =IF(J6-P6<=0,"ok","oil change") -> ok | R6: 11042.5 | S6: =R6-R5 -> 3.5 | T6: 216304 | U6: =SUM(T6-T5) -> 783 | V6: =IF(S6>0,U6/S6,0) -> 223.71429 | X6: =X5 -> 11529 | Y6: =IF(R6-X6<=0,"ok","oil change") -> ok | Z6: =C6+K6+S6 -> 3.5 | AA6: =U6+M6+E6 -> 783 | AB6: =V6+N6+F6 -> 223.71429 | AC6: =IF(Z6>0,AA6/Z6,0) -> 223.71429 | AD6: =ELEC!Q6 -> 1642 | AE6: =SUM(AD6/Z6) -> 469.14286 | AF6: =SUM(AE6/1600) -> 0.29321429 | AG6: =SUM(320*AF6) -> 93.828571 | AH6: =SUM(AC6-AG6) -> 129.88571 | AI6: =AD6*AJ6 -> 422.62447 | AJ6: =305/1185 -> 0.25738397 | AK6: =AI6/Z6 -> 120.74985
A7: =ELEC!C7 -> 43926 | B7: =B6 -> 8621 | C7: =B7-B6 -> 0 | D7: =D6 -> 146464 | E7: =SUM(D7-D6) -> 0 | F7: =IF(C7>0,E7/C7,0) -> 0 | H7: =H6 -> 8497 | I7: =IF(B7-H7<=0,"ok","oil change") -> oil change | J7: =J6 -> 10689 | K7: =J7-J6 -> 0 | L7: =L6 -> 237072.3 | M7: =SUM(L7-L6) -> 0 | N7: =IF(K7>0,M7/K7,0) -> 0 | P7: =P6 -> 10873 | Q7: =IF(J7-P7<=0,"ok","oil change") -> ok | R7: 11045 | S7: =R7-R6 -> 2.5 | T7: 216853.1 | U7: =SUM(T7-T6) -> 549.1 | V7: =IF(S7>0,U7/S7,0) -> 219.64 | X7: =X6 -> 11529 | Y7: =IF(R7-X7<=0,"ok","oil change") -> ok | Z7: =C7+K7+S7 -> 2.5 | AA7: =U7+M7+E7 -> 549.1 | AB7: =V7+N7+F7 -> 219.64 | AC7: =IF(Z7>0,AA7/Z7,0) -> 219.64 | AD7: =ELEC!Q7 -> 1691 | AE7: =SUM(AD7/Z7) -> 676.4 | AF7: =SUM(AE7/1600) -> 0.42275 | AH7: =SUM(AC7-AG7) -> #VALUE! | AI7: =AD7*AJ7 -> 435.23629 | AJ7: =305/1185 -> 0.25738397 | AK7: =AI7/Z7 -> 174.09451
A8: =ELEC!C8 -> 43927 | B8: 8621 | C8: =B8-B7 -> 0 | D8: 146465 | E8: =SUM(D8-D7) -> 1 | F8: =IF(C8>0,E8/C8,0) -> 0 | H8: =H7 -> 8497 | I8: =IF(B8-H8<=0,"ok","oil change") -> oil change | J8: 10689 | K8: =J8-J7 -> 0 | L8: 237073.6 | M8: =SUM(L8-L7) -> 1.3 | N8: =IF(K8>0,M8/K8,0) -> 0 | P8: =P7 -> 10873 | Q8: =IF(J8-P8<=0,"ok","oil change") -> ok | R8: 11048 | S8: =R8-R7 -> 3 | T8: 217517.1 | U8: =SUM(T8-T7) -> 664 | V8: =IF(S8>0,U8/S8,0) -> 221.33333 | X8: =X7 -> 11529 | Y8: =IF(R8-X8<=0,"ok","oil change") -> ok | Z8: =C8+K8+S8 -> 3 | AA8: =U8+M8+E8 -> 666.3 | AB8: =V8+N8+F8 -> 221.33333 | AC8: =IF(Z8>0,AA8/Z8,0) -> 222.1 | AD8: =ELEC!Q8 -> 1790 | AE8: =SUM(AD8/Z8) -> 596.66667 | AF8: =SUM(AE8/1600) -> 0.37291667 | AG8: =SUM(320*AF8) -> 119.33333 | AH8: =SUM(AC8-AG8) -> 102.76667 | AI8: =AD8*AJ8 -> 460.7173 | AJ8: =305/1185 -> 0.25738397 | AK8: =AI8/Z8 -> 153.57243
A9: =ELEC!C9 -> 43928 | B9: 8621.06 | C9: =B9-B8 -> 0.06 | D9: 146465.1 | E9: =SUM(D9-D8) -> 0.1 | F9: =IF(C9>0,E9/C9,0) -> 1.6666667 | H9: =H8 -> 8497 | I9: =IF(B9-H9<=0,"ok","oil change") -> oil change | J9: 10689.42 | K9: =J9-J8 -> 0.42 | L9: 237073.7 | M9: =SUM(L9-L8) -> 0.1 | N9: =IF(K9>0,M9/K9,0) -> 0.23809524 | P9: =P8 -> 10873 | Q9: =IF(J9-P9<=0,"ok","oil change") -> ok | R9: 11051 | S9: =R9-R8 -> 3 | T9: 218286.9 | U9: =SUM(T9-T8) -> 769.8 | V9: =IF(S9>0,U9/S9,0) -> 256.6 | X9: =X8 -> 11529 | Y9: =IF(R9-X9<=0,"ok","oil change") -> ok | Z9: =C9+K9+S9 -> 3.48 | AA9: =U9+M9+E9 -> 770 | AB9: =V9+N9+F9 -> 258.50476 | AC9: =IF(Z9>0,AA9/Z9,0) -> 221.26437 | AD9: =ELEC!Q9 -> 1399 | AE9: =SUM(AD9/Z9) -> 402.01149 | AF9: =SUM(AE9/1600) -> 0.25125718 | AG9: =SUM(320*AF9) -> 80.402299 | AH9: =SUM(AC9-AG9) -> 140.86207 | AI9: =AD9*AJ9 -> 360.08017 | AJ9: 0.25738397 | AK9: =IF(Z9>0,AI9/Z9,0) -> 103.47131
A10: =ELEC!C10 -> 43929 | B10: 8621 | C10: =B10-B9 -> -0.06 | D10: 146465 | E10: =SUM(D10-D9) -> -0.1 | F10: =IF(C10>0,E10/C10,0) -> 0 | H10: =H9 -> 8497 | I10: =IF(B10-H10<=0,"ok","oil change") -> oil change | J10: 10689 | K10: =J10-J9 -> -0.42 | L10: =L9 -> 237073.7 | M10: =SUM(L10-L9) -> 0 | N10: =IF(K10>0,M10/K10,0) -> 0 | P10: 10873 | Q10: =IF(J10-P10<=0,"ok","oil change") -> ok | R10: 11055 | S10: =R10-R9 -> 4 | T10: 219084 | U10: =SUM(T10-T9) -> 797.1 | V10: =IF(S10>0,U10/S10,0) -> 199.275 | X10: =X9 -> 11529 | Y10: =IF(R10-X10<=0,"ok","oil change") -> ok | Z10: =C10+K10+S10 -> 3.52 | AA10: =U10+M10+E10 -> 797 | AB10: =V10+N10+F10 -> 199.275 | AC10: =IF(Z10>0,AA10/Z10,0) -> 226.42045 | AD10: =ELEC!Q10 -> 1611 | AE10: =SUM(AD10/Z10) -> 457.67045 | AF10: =SUM(AE10/1600) -> 0.28604403 | AG10: =SUM(320*AF10) -> 91.534091 | AH10: =SUM(AC10-AG10) -> 134.88636 | AI10: =AD10*AJ10 -> 414.64557 | AJ10: =305/1185 -> 0.25738397 | AK10: =IF(Z10>0,AI10/Z10,0) -> 117.79704
A11: =ELEC!C11 -> 43930 | B11: =B10 -> 8621 | C11: =B11-B10 -> 0 | D11: =D10 -> 146465 | E11: =SUM(D11-D10) -> 0 | F11: =IF(C11>0,E11/C11,0) -> 0 | H11: =H10 -> 8497 | I11: =IF(B11-H11<=0,"ok","oil change") -> oil change | J11: =J10 -> 10689 | K11: =J11-J10 -> 0 | L11: =L10 -> 237073.7 | M11: =SUM(L11-L10) -> 0 | N11: =IF(K11>0,M11/K11,0) -> 0 | P11: =P10 -> 10873 | Q11: =IF(J11-P11<=0,"ok","oil change") -> ok | R11: 11058 | S11: =R11-R10 -> 3 | T11: 219869 | U11: =SUM(T11-T10) -> 785 | V11: =IF(S11>0,U11/S11,0) -> 261.66667 | X11: =X10 -> 11529 | Y11: =IF(R11-X11<=0,"ok","oil change") -> ok | Z11: =C11+K11+S11 -> 3 | AA11: =U11+M11+E11 -> 785 | AB11: =V11+N11+F11 -> 261.66667 | AC11: =IF(Z11>0,AA11/Z11,0) -> 261.66667 | AD11: =ELEC!Q11 -> 1867 | AE11: =SUM(AD11/Z11) -> 622.33333 | AF11: =SUM(AE11/1600) -> 0.38895833 | AG11: =SUM(320*AF11) -> 124.46667 | AH11: =SUM(AC11-AG11) -> 137.2 | AI11: =AD11*AJ11 -> 480.53586 | AJ11: =305/1185 -> 0.25738397 | AK11: =IF(Z11>0,AI11/Z11,0) -> 160.17862
A12: =ELEC!C12 -> 43931 | B12: =B11 -> 8621 | C12: =B12-B11 -> 0 | D12: =D11 -> 146465 | E12: =SUM(D12-D11) -> 0 | F12: =IF(C12>0,E12/C12,0) -> 0 | H12: =H11 -> 8497 | I12: =IF(B12-H12<=0,"ok","oil change") -> oil change | J12: =J11 -> 10689 | K12: =J12-J11 -> 0 | L12: =L11 -> 237073.7 | M12: =SUM(L12-L11) -> 0 | N12: =IF(K12>0,M12/K12,0) -> 0 | P12: =P11 -> 10873 | Q12: =IF(J12-P12<=0,"ok","oil change") -> ok | R12: 11061 | S12: =R12-R11 -> 3 | T12: 220678 | U12: =SUM(T12-T11) -> 809 | V12: =IF(S12>0,U12/S12,0) -> 269.66667 | X12: =X11 -> 11529 | Y12: =IF(R12-X12<=0,"ok","oil change") -> ok | Z12: =C12+K12+S12 -> 3 | AA12: =U12+M12+E12 -> 809 | AB12: =V12+N12+F12 -> 269.66667 | AC12: =IF(Z12>0,AA12/Z12,0) -> 269.66667 | AD12: =ELEC!Q12 -> 1000 | AE12: =SUM(AD12/Z12) -> 333.33333 | AF12: =SUM(AE12/1600) -> 0.20833333 | AG12: =SUM(320*AF12) -> 66.666667 | AH12: =SUM(AC12-AG12) -> 203 | AI12: =AD12*AJ12 -> 257.38397 | AJ12: =305/1185 -> 0.25738397 | AK12: =IF(Z12>0,AI12/Z12,0) -> 85.794655
A13: =ELEC!C13 -> 43932 | B13: =B12 -> 8621 | C13: =B13-B12 -> 0 | D13: =D12 -> 146465 | E13: =SUM(D13-D12) -> 0 | F13: =IF(C13>0,E13/C13,0) -> 0 | H13: =H12 -> 8497 | I13: =IF(B13-H13<=0,"ok","oil change") -> oil change | J13: =J12 -> 10689 | K13: =J13-J12 -> 0 | L13: =L12 -> 237073.7 | M13: =SUM(L13-L12) -> 0 | N13: =IF(K13>0,M13/K13,0) -> 0 | P13: =P12 -> 10873 | Q13: =IF(J13-P13<=0,"ok","oil change") -> ok | R13: 11066 | S13: =R13-R12 -> 5 | T13: 222252 | U13: =SUM(T13-T12) -> 1574 | V13: =IF(S13>0,U13/S13,0) -> 314.8 | X13: =X12+180 -> 11709 | Y13: =IF(R13-X13<=0,"ok","oil change") -> ok | Z13: =C13+K13+S13 -> 5 | AA13: =U13+M13+E13 -> 1574 | AB13: =V13+N13+F13 -> 314.8 | AC13: =IF(Z13>0,AA13/Z13,0) -> 314.8 | AD13: =ELEC!Q13 -> 2000 | AE13: =SUM(AD13/Z13) -> 400 | AF13: =SUM(AE13/1600) -> 0.25 | AG13: =SUM(320*AF13) -> 80 | AH13: =SUM(AC13-AG13) -> 234.8 | AI13: =AD13*AJ13 -> 514.76793 | AJ13: =305/1185 -> 0.25738397 | AK13: =IF(Z13>0,AI13/Z13,0) -> 102.95359
A14: =ELEC!C14 -> 43933 | B14: =B13 -> 8621 | C14: =B14-B13 -> 0 | D14: =D13 -> 146465 | E14: =SUM(D14-D13) -> 0 | F14: =IF(C14>0,E14/C14,0) -> 0 | H14: =H13 -> 8497 | I14: =IF(B14-H14<=0,"ok","oil change") -> oil change | J14: =J13 -> 10689 | K14: =J14-J13 -> 0 | L14: =L13 -> 237073.7 | M14: =SUM(L14-L13) -> 0 | N14: =IF(K14>0,M14/K14,0) -> 0 | P14: =P13 -> 10873 | Q14: =IF(J14-P14<=0,"ok","oil change") -> ok | R14: 11067 | S14: =R14-R13 -> 1 | T14: 222748 | U14: =SUM(T14-T13) -> 496 | V14: =IF(S14>0,U14/S14,0) -> 496 | X14: =X13 -> 11709 | Y14: =IF(R14-X14<=0,"ok","oil change") -> ok | Z14: =C14+K14+S14 -> 1 | AA14: =U14+M14+E14 -> 496 | AB14: =V14+N14+F14 -> 496 | AC14: =IF(Z14>0,AA14/Z14,0) -> 496 | AD14: =ELEC!Q14 -> 1000 | AE14: =SUM(AD14/Z14) -> 1000 | AF14: =SUM(AE14/1600) -> 0.625 | AG14: =SUM(320*AF14) -> 200 | AH14: =SUM(AC14-AG14) -> 296 | AI14: =AD14*AJ14 -> 257.38397 | AJ14: =305/1185 -> 0.25738397 | AK14: =IF(Z14>0,AI14/Z14,0) -> 257.38397
A15: =ELEC!C15 -> 43934 | B15: =B14 -> 8621 | C15: =B15-B14 -> 0 | D15: =D14 -> 146465 | E15: =SUM(D15-D14) -> 0 | F15: =IF(C15>0,E15/C15,0) -> 0 | H15: =H14 -> 8497 | I15: =IF(B15-H15<=0,"ok","oil change") -> oil change | J15: =J14 -> 10689 | K15: =J15-J14 -> 0 | L15: =L14 -> 237073.7 | M15: =SUM(L15-L14) -> 0 | N15: =IF(K15>0,M15/K15,0) -> 0 | P15: =P14 -> 10873 | Q15: =IF(J15-P15<=0,"ok","oil change") -> ok | R15: 11070 | S15: =R15-R14 -> 3 | T15: 223552 | U15: =SUM(T15-T14) -> 804 | V15: =IF(S15>0,U15/S15,0) -> 268 | X15: =X14 -> 11709 | Y15: =IF(R15-X15<=0,"ok","oil change") -> ok | Z15: =C15+K15+S15 -> 3 | AA15: =U15+M15+E15 -> 804 | AB15: =V15+N15+F15 -> 268 | AC15: =IF(Z15>0,AA15/Z15,0) -> 268 | AD15: =ELEC!Q15 -> 1000 | AE15: =SUM(AD15/Z15) -> 333.33333 | AF15: =SUM(AE15/1600) -> 0.20833333 | AG15: =SUM(320*AF15) -> 66.666667 | AH15: =SUM(AC15-AG15) -> 201.33333 | AI15: =AD15*AJ15 -> 257.38397 | AJ15: =305/1185 -> 0.25738397 | AK15: =IF(Z15>0,AI15/Z15,0) -> 85.794655
A16: =ELEC!C16 -> 43935 | B16: 8621.08 | C16: =B16-B15 -> 0.08 | D16: 146465.6 | E16: =SUM(D16-D15) -> 0.6 | F16: =IF(C16>0,E16/C16,0) -> 7.5 | H16: =H15 -> 8497 | I16: =IF(B16-H16<=0,"ok","oil change") -> oil change | J16: 10689.42 | K16: =J16-J15 -> 0.42 | L16: 237074.02 | M16: =SUM(L16-L15) -> 0.32 | N16: =IF(K16>0,M16/K16,0) -> 0.76190476 | P16: =P15 -> 10873 | Q16: =IF(J16-P16<=0,"ok","oil change") -> ok | R16: 11074.4 | S16: =R16-R15 -> 4.4 | T16: 224558.9 | U16: =SUM(T16-T15) -> 1006.9 | V16: =IF(S16>0,U16/S16,0) -> 228.84091 | X16: =X15 -> 11709 | Y16: =IF(R16-X16<=0,"ok","oil change") -> ok | Z16: =C16+K16+S16 -> 4.9 | AA16: =U16+M16+E16 -> 1007.82 | AB16: =V16+N16+F16 -> 237.10281 | AC16: =IF(Z16>0,AA16/Z16,0) -> 205.67755 | AD16: =ELEC!Q16 -> 2114 | AE16: =SUM(AD16/Z16) -> 431.42857 | AF16: =SUM(AE16/1600) -> 0.26964286 | AG16: =SUM(320*AF16) -> 86.285714 | AH16: =SUM(AC16-AG16) -> 119.39184 | AI16: =AD16*AJ16 -> 544.1097 | AJ16: =305/1185 -> 0.25738397 | AK16: =IF(Z16>0,AI16/Z16,0) -> 111.0428
A17: =ELEC!C17 -> 43936 | B17: =B16 -> 8621.08 | C17: =B17-B16 -> 0 | D17: 146479 | E17: =SUM(D17-D16) -> 13.4 | F17: =IF(C17>0,E17/C17,0) -> 0 | H17: =H16+180 -> 8677 | I17: =IF(B17-H17<=0,"ok","oil change") -> ok | J17: =J16 -> 10689.42 | K17: =J17-J16 -> 0 | L17: 237074.2 | M17: =SUM(L17-L16) -> 0.18 | N17: =IF(K17>0,M17/K17,0) -> 0 | P17: =P16 -> 10873 | Q17: =IF(J17-P17<=0,"ok","oil change") -> ok | R17: 11077 | S17: =R17-R16 -> 2.6 | T17: 225305.5 | U17: =SUM(T17-T16) -> 746.6 | V17: =IF(S17>0,U17/S17,0) -> 287.15385 | X17: =X16 -> 11709 | Y17: =IF(R17-X17<=0,"ok","oil change") -> ok | Z17: =C17+K17+S17 -> 2.6 | AA17: =U17+M17+E17 -> 760.18 | AB17: =V17+N17+F17 -> 287.15385 | AC17: =IF(Z17>0,AA17/Z17,0) -> 292.37692 | AD17: =ELEC!Q17 -> 1750 | AE17: =SUM(AD17/Z17) -> 673.07692 | AF17: =SUM(AE17/1600) -> 0.42067308 | AG17: =SUM(320*AF17) -> 134.61538 | AH17: =SUM(AC17-AG17) -> 157.76154 | AI17: =AD17*AJ17 -> 450.42194 | AJ17: =305/1185 -> 0.25738397 | AK17: =IF(Z17>0,AI17/Z17,0) -> 173.23921
A18: =ELEC!C18 -> 43937 | B18: =B17 -> 8621.08 | C18: =B18-B17 -> 0 | D18: =D17 -> 146479 | E18: =SUM(D18-D17) -> 0 | F18: =IF(C18>0,E18/C18,0) -> 0 | H18: =H17 -> 8677 | I18: =IF(B18-H18<=0,"ok","oil change") -> ok | J18: =J17 -> 10689.42 | K18: =J18-J17 -> 0 | L18: =L17 -> 237074.2 | M18: =SUM(L18-L17) -> 0 | N18: =IF(K18>0,M18/K18,0) -> 0 | P18: =P17 -> 10873 | Q18: =IF(J18-P14<=0,"ok","oil change") -> ok | R18: 11078 | S18: =R18-R17 -> 1 | T18: 225501.7 | U18: =SUM(T18-T17) -> 196.2 | V18: =IF(S18>0,U18/S18,0) -> 196.2 | X18: =X17 -> 11709 | Y18: =IF(R18-X18<=0,"ok","oil change") -> ok | Z18: =C18+K18+S18 -> 1 | AA18: =U18+M18+E18 -> 196.2 | AB18: =V18+N18+F18 -> 196.2 | AC18: =IF(Z18>0,AA18/Z18,0) -> 196.2 | AD18: =ELEC!Q18 -> 636 | AE18: =SUM(AD18/Z18) -> 636 | AF18: =SUM(AE18/1600) -> 0.3975 | AG18: =SUM(320*AF18) -> 127.2 | AH18: =SUM(AC18-AG18) -> 69 | AI18: =AD18*AJ18 -> 163.6962 | AJ18: =305/1185 -> 0.25738397 | AK18: =IF(Z18>0,AI18/Z18,0) -> 163.6962
A19: =ELEC!C19 -> 43938 | B19: =B18 -> 8621.08 | C19: =B19-B18 -> 0 | D19: =D18 -> 146479 | E19: =SUM(D19-D18) -> 0 | F19: =IF(C19>0,E19/C19,0) -> 0 | H19: =H18 -> 8677 | I19: =IF(B19-H19<=0,"ok","oil change") -> ok | J19: =J18 -> 10689.42 | K19: =J19-J18 -> 0 | L19: =L18 -> 237074.2 | M19: =SUM(L19-L18) -> 0 | N19: =IF(K19>0,M19/K19,0) -> 0 | P19: =P18 -> 10873 | Q19: =IF(J19-P19<=0,"ok","oil change") -> ok | R19: 11081 | S19: =R19-R18 -> 3 | T19: 226191 | U19: =SUM(T19-T18) -> 689.3 | V19: =IF(S19>0,U19/S19,0) -> 229.76667 | X19: =X18 -> 11709 | Y19: =IF(R19-X19<=0,"ok","oil change") -> ok | Z19: =C19+K19+S19 -> 3 | AA19: =U19+M19+E19 -> 689.3 | AB19: =V19+N19+F19 -> 229.76667 | AC19: =IF(Z19>0,AA19/Z19,0) -> 229.76667 | AD19: =ELEC!Q19 -> 1789 | AE19: =SUM(AD19/Z19) -> 596.33333 | AF19: =SUM(AE19/1600) -> 0.37270833 | AG19: =SUM(320*AF19) -> 119.26667 | AH19: =SUM(AC19-AG19) -> 110.5 | AI19: =AD19*AJ19 -> 460.45992 | AJ19: =305/1185 -> 0.25738397 | AK19: =IF(Z19>0,AI19/Z19,0) -> 153.48664
