Workbook

Sheet Total
A1: Site Name | B1: Day | C1: Month | D1: Year | E1: Total Electricity Kwh | F1: Electricity Tariff ($/Kwh) | G1: Total Fuel Oil (Liters) | H1: Fuel Oil $/Liter | I1: LPG (Kg) | J1: LPG $/Kg | K1: Water Utility Supply (m3) m3 | L1: Water Utility Supply (m3) $/m3 | M1: Irrigation Water (m3) m3 | N1: Irrigation water $/m3 | O1: Room Nights
A2: Beirut | B2: 1 | C2: 5 | D2: 2020 | E2: =ELEC!N3 -> 8802.4 | F2: =SUM('EDl log'!T4) -> 0.042144973 | G2: =-tanks!AW6 -> 349 | H2: =SUM(tanks!AV6) -> 0 | I2: =('B5'!AU5)*0.51 -> 30.6 | J2: ='B5'!AX5/0.51 -> 1.372549 | K2: =WATER!I6 -> 0 | L2: =SUM(WATER!J6) -> 0 | M2: =WATER!Q6 -> 0 | N2: 0.6 | O2: =ELEC!B3 -> 10.005
A3: Beirut | B3: =B2+1 -> 2 | C3: 5 | D3: 2020 | E3: =ELEC!N4 -> 8701.6 | F3: =SUM('EDl log'!T5) -> 0.042124556 | G3: =-tanks!AW7 -> 249 | H3: =SUM(tanks!AV7) -> 0 | I3: =('B5'!AU6)*0.51 -> 0 | J3: ='B5'!AX6/0.51 -> 1.372549 | K3: =WATER!I7 -> 0 | L3: =SUM(WATER!J7) -> 0 | M3: =WATER!Q7 -> 0 | N3: 0.6 | O3: =ELEC!B4 -> 8.97
A4: Beirut | B4: =B3+1 -> 3 | C4: 5 | D4: 2020 | E4: =ELEC!N5 -> 11338.4 | F4: =SUM('EDl log'!T6) -> 0.040860614 | G4: =-tanks!AW8 -> 288.5 | H4: =SUM(tanks!AV8) -> 0 | I4: =('B5'!AU7)*0.51 -> 76.5 | J4: ='B5'!AX7/0.51 -> 1.372549 | K4: =WATER!I8 -> 340 | L4: =SUM(WATER!J8) -> 0.71157495 | M4: =WATER!Q8 -> 0 | N4: 0.6 | O4: =ELEC!B5 -> 6.003
A5: Beirut | B5: =B4+1 -> 4 | C5: 5 | D5: 2020 | E5: =ELEC!N6 -> 10592 | F5: =SUM('EDl log'!T7) -> 0.038565461 | G5: =-tanks!AW9 -> 657.9 | H5: =SUM(tanks!AV9) -> 0 | I5: =('B5'!AU8)*0.51 -> 122.4 | J5: ='B5'!AX8/0.51 -> 1.372549 | K5: =WATER!I9 -> 0 | L5: =SUM(WATER!J9) -> 0 | M5: =WATER!Q9 -> 0 | N5: 0.6 | O5: =ELEC!B6 -> 2.001
A6: Beirut | B6: =B5+1 -> 5 | C6: 5 | D6: 2020 | E6: =ELEC!N7 -> 0 | F6: =SUM('EDl log'!T8) -> 0 | G6: =-tanks!AW10 -> 0 | H6: =SUM(tanks!AV10) -> 0 | I6: =('B5'!AU9)*0.51 -> 0 | J6: ='B5'!AX9/0.51 -> 1.372549 | K6: =WATER!I10 -> 0 | L6: =SUM(WATER!J10) -> 0 | M6: =WATER!Q10 -> 0 | N6: 0.6 | O6: =ELEC!B7 -> 0
A7: Beirut | B7: =B6+1 -> 6 | C7: 5 | D7: 2020 | E7: =ELEC!N8 -> 0 | F7: =SUM('EDl log'!T9) -> 0 | G7: =-tanks!AW11 -> 0 | H7: =SUM(tanks!AV11) -> 0 | I7: =('B5'!AU10)*0.51 -> 0 | J7: ='B5'!AX10/0.51 -> 1.372549 | K7: =WATER!I11 -> 0 | L7: =SUM(WATER!J11) -> 0 | M7: =WATER!Q11 -> 0 | N7: 0.6 | O7: =ELEC!B8 -> 0
A8: Beirut | B8: =B7+1 -> 7 | C8: 5 | D8: 2020 | E8: =ELEC!N9 -> 0 | F8: =SUM('EDl log'!T10) -> 0 | G8: =-tanks!AW12 -> 0 | H8: =SUM(tanks!AV12) -> 0 | I8: =('B5'!AU11)*0.51 -> 0 | J8: ='B5'!AX11/0.51 -> 1.372549 | K8: =WATER!I12 -> 0 | L8: =SUM(WATER!J12) -> 0 | M8: =WATER!Q12 -> 0 | N8: 0.6 | O8: =ELEC!B9 -> 0
A9: Beirut | B9: =B8+1 -> 8 | C9: 5 | D9: 2020 | E9: =ELEC!N10 -> 0 | F9: =SUM('EDl log'!T11) -> 0 | G9: =-tanks!AW13 -> 0 | H9: =SUM(tanks!AV13) -> 0 | I9: =('B5'!AU12)*0.51 -> 0 | J9: ='B5'!AX12/0.51 -> 1.372549 | K9: =WATER!I13 -> 0 | L9: =SUM(WATER!J13) -> 0 | M9: =WATER!Q13 -> 0 | N9: 0.6 | O9: =ELEC!B10 -> 0
A10: Beirut | B10: =B9+1 -> 9 | C10: 5 | D10: 2020 | E10: =ELEC!N11 -> 0 | F10: =SUM('EDl log'!T12) -> 0 | G10: =-tanks!AW14 -> 0 | H10: =SUM(tanks!AV14) -> 0 | I10: =('B5'!AU13)*0.51 -> 0 | J10: ='B5'!AX13/0.51 -> 1.372549 | K10: =WATER!I14 -> 0 | L10: =SUM(WATER!J14) -> 0 | M10: =WATER!Q14 -> 0 | N10: 0.6 | O10: =ELEC!B11 -> 0
A11: Beirut | B11: =B10+1 -> 10 | C11: 5 | D11: 2020 | E11: =ELEC!N12 -> 0 | F11: =SUM('EDl log'!T13) -> 0 | G11: =-tanks!AW15 -> 0 | H11: =SUM(tanks!AV15) -> 0 | I11: =('B5'!AU14)*0.51 -> 0 | J11: ='B5'!AX14/0.51 -> 1.372549 | K11: =WATER!I15 -> 0 | L11: =SUM(WATER!J15) -> 0 | M11: =WATER!Q15 -> 0 | N11: 0.6 | O11: =ELEC!B12 -> 0
A12: Beirut | B12: =B11+1 -> 11 | C12: 5 | D12: 2020 | E12: =ELEC!N13 -> 0 | F12: =SUM('EDl log'!T14) -> 0 | G12: =-tanks!AW16 -> 0 | H12: =SUM(tanks!AV16) -> 0 | I12: =('B5'!AU15)*0.51 -> 0 | J12: ='B5'!AX15/0.51 -> 1.372549 | K12: =WATER!I16 -> 0 | L12: =SUM(WATER!J16) -> 0 | M12: =WATER!Q16 -> 0 | N12: 0.6 | O12: =ELEC!B13 -> 0
A13: Beirut | B13: =B12+1 -> 12 | C13: 5 | D13: 2020 | E13: =ELEC!N14 -> 0 | F13: =SUM('EDl log'!T15) -> 0 | G13: =-tanks!AW17 -> 0 | H13: =SUM(tanks!AV17) -> 0 | I13: =('B5'!AU16)*0.51 -> 0 | J13: ='B5'!AX16/0.51 -> 1.372549 | K13: =WATER!I17 -> 0 | L13: =SUM(WATER!J17) -> 0 | M13: =WATER!Q17 -> 0 | N13: 0.6 | O13: =ELEC!B14 -> 0
A14: Beirut | B14: =B13+1 -> 13 | C14: 5 | D14: 2020 | E14: =ELEC!N15 -> 0 | F14: =SUM('EDl log'!T16) -> 0 | G14: =-tanks!AW18 -> 0 | H14: =SUM(tanks!AV18) -> 0 | I14: =('B5'!AU17)*0.51 -> 0 | J14: ='B5'!AX17/0.51 -> 1.372549 | K14: =WATER!I18 -> 0 | L14: =SUM(WATER!J18) -> 0 | M14: =WATER!Q18 -> 0 | N14: 0.6 | O14: =ELEC!B15 -> 0
... A32: Beirut | B32: =B31+1 -> 31 | C32: 5 | D32: 2020 | E32: =ELEC!N33 -> 0 | F32: =SUM('EDl log'!T34) -> 0 | G32: =-tanks!AW36 -> 0 | H32: =SUM(tanks!AV36) -> 0 | I32: =('B5'!AU35)*0.51 -> 0 | J32: ='B5'!AX35/0.51 -> 1.372549 | K32: =WATER!I36 -> 0 | L32: =SUM(WATER!J36) -> 0 | M32: =WATER!Q36 -> 0 | N32: 0.6 | O32: =ELEC!B33 -> 0

Sheet Submetering
A1: Site Name | B1: Day | C1: Month | D1: Year | E1: ATS1 Kwh | F1: ATS2 Kwh | G1: ATS3 Kwh | H1: ATS4 Kwh | I1: ATS5 Kwh | J1: Guest (m3) | K1: Kitchen & Laundry (m3) | L1: Room Nights
A2: Beirut | B2: 1 | C2: 5 | D2: 2020 | E2: =ELEC!M3 -> 2580 | F2: =ELEC!K3 -> 996 | G2: =ELEC!I3 -> 1146 | H2: =ELEC!E3 -> 2824 | I2: =ELEC!G3 -> 1256.4 | J2: =WATER!Y6 -> 2 | K2: =WATER!AJ6 -> 1 | L2: =ELEC!B3 -> 10.005
A3: Beirut | B3: =B2+1 -> 2 | C3: 5 | D3: 2020 | E3: =ELEC!M4 -> 2628 | F3: =ELEC!K4 -> 930 | G3: =ELEC!I4 -> 1188 | H3: =ELEC!E4 -> 2628 | I3: =ELEC!G4 -> 1327.6 | J3: =WATER!Y7 -> 66 | K3: =WATER!AJ7 -> 45 | L3: =ELEC!B4 -> 8.97
A4: Beirut | B4: =B3+1 -> 3 | C4: 5 | D4: 2020 | E4: =ELEC!M5 -> 2892 | F4: =ELEC!K5 -> 940 | G4: =ELEC!I5 -> 1376 | H4: =ELEC!E5 -> 4672 | I4: =ELEC!G5 -> 1458.4 | J4: =WATER!Y8 -> 82 | K4: =WATER!AJ8 -> 13 | L4: =ELEC!B5 -> 6.003
A5: Beirut | B5: =B4+1 -> 4 | C5: 5 | D5: 2020 | E5: =ELEC!M6 -> 2872 | F5: =ELEC!K6 -> 1572 | G5: =ELEC!I6 -> 1320 | H5: =ELEC!E6 -> 3434 | I5: =ELEC!G6 -> 1394 | J5: =WATER!Y9 -> 2 | K5: =WATER!AJ9 -> 21 | L5: =ELEC!B6 -> 2.001
A6: Beirut | B6: =B5+1 -> 5 | C6: 5 | D6: 2020 | E6: =ELEC!M7 -> 0 | F6: =ELEC!K7 -> 0 | G6: =ELEC!I7 -> 0 | H6: =ELEC!E7 -> 0 | I6: =ELEC!G7 -> 0 | J6: =WATER!Y10 -> 0 | K6: =WATER!AJ10 -> 0 | L6: =ELEC!B7 -> 0
A7: Beirut | B7: =B6+1 -> 6 | C7: 5 | D7: 2020 | E7: =ELEC!M8 -> 0 | F7: =ELEC!K8 -> 0 | G7: =ELEC!I8 -> 0 | H7: =ELEC!E8 -> 0 | I7: =ELEC!G8 -> 0 | J7: =WATER!Y11 -> 0 | K7: =WATER!AJ11 -> 0 | L7: =ELEC!B8 -> 0
A8: Beirut | B8: =B7+1 -> 7 | C8: 5 | D8: 2020 | E8: =ELEC!M9 -> 0 | F8: =ELEC!K9 -> 0 | G8: =ELEC!I9 -> 0 | H8: =ELEC!E9 -> 0 | I8: =ELEC!G9 -> 0 | J8: =WATER!Y12 -> 0 | K8: =WATER!AJ12 -> 0 | L8: =ELEC!B9 -> 0
A9: Beirut | B9: =B8+1 -> 8 | C9: 5 | D9: 2020 | E9: =ELEC!M10 -> 0 | F9: =ELEC!K10 -> 0 | G9: =ELEC!I10 -> 0 | H9: =ELEC!E10 -> 0 | I9: =ELEC!G10 -> 0 | J9: =WATER!Y13 -> 0 | K9: =WATER!AJ13 -> 0 | L9: =ELEC!B10 -> 0
A10: Beirut | B10: =B9+1 -> 9 | C10: 5 | D10: 2020 | E10: =ELEC!M11 -> 0 | F10: =ELEC!K11 -> 0 | G10: =ELEC!I11 -> 0 | H10: =ELEC!E11 -> 0 | I10: =ELEC!G11 -> 0 | J10: =WATER!Y14 -> 0 | K10: =WATER!AJ14 -> 0 | L10: =ELEC!B11 -> 0
A11: Beirut | B11: =B10+1 -> 10 | C11: 5 | D11: 2020 | E11: =ELEC!M12 -> 0 | F11: =ELEC!K12 -> 0 | G11: =ELEC!I12 -> 0 | H11: =ELEC!E12 -> 0 | I11: =ELEC!G12 -> 0 | J11: =WATER!Y15 -> 0 | K11: =WATER!AJ15 -> 0 | L11: =ELEC!B12 -> 0
A12: Beirut | B12: =B11+1 -> 11 | C12: 5 | D12: 2020 | E12: =ELEC!M13 -> 0 | F12: =ELEC!K13 -> 0 | G12: =ELEC!I13 -> 0 | H12: =ELEC!E13 -> 0 | I12: =ELEC!G13 -> 0 | J12: =WATER!Y16 -> 0 | K12: =WATER!AJ16 -> 0 | L12: =ELEC!B13 -> 0
A13: Beirut | B13: =B12+1 -> 12 | C13: 5 | D13: 2020 | E13: =ELEC!M14 -> 0 | F13: =ELEC!K14 -> 0 | G13: =ELEC!I14 -> 0 | H13: =ELEC!E14 -> 0 | I13: =ELEC!G14 -> 0 | J13: =WATER!Y17 -> 0 | K13: =WATER!AJ17 -> 0 | L13: =ELEC!B14 -> 0
A14: Beirut | B14: =B13+1 -> 13 | C14: 5 | D14: 2020 | E14: =ELEC!M15 -> 0 | F14: =ELEC!K15 -> 0 | G14: =ELEC!I15 -> 0 | H14: =ELEC!E15 -> 0 | I14: =ELEC!G15 -> 0 | J14: =WATER!Y18 -> 0 | K14: =WATER!AJ18 -> 0 | L14: =ELEC!B15 -> 0
... A32: Beirut | B32: =B31+1 -> 31 | C32: 5 | D32: 2020 | E32: =ELEC!M33 -> 0 | F32: =ELEC!K33 -> 0 | G32: =ELEC!I33 -> 0 | H32: =ELEC!E33 -> 0 | I32: =ELEC!G33 -> 0 | J32: =WATER!Y36 -> 0 | K32: =WATER!AJ36 -> 0 | L32: =ELEC!B33 -> 0

Sheet ELEC
A1: OOC | B1: Room OCC | D1: MDB3 | E1: MDB3/day | F1: EMDB2 | G1: EMDB2/day | H1: EMDB1 | I1: EMDB1/day | J1: MDB2 | K1: mdb2/day | L1: MDB1 | M1: MDB1/Day | N1: Total KWH | O1: KWH/Rooc | P1: Gen MHW | Q1: Gen/Day KWH | R1: EDL KWH | S1: CH1 RH | T1: RH | U1: C1h1 power | V1: CH1 Con KWH | W1: CH2 RH | X1: RH | Y1: Ch2 power | Z1: CH2 Con KWH | AA1: CH3 RH | AB1: RH | AC1: Ch3 power | AD1: CH3 Con KWH | AE1: RH total | AF1: KWH total | AG1: AVG chiller KW/Hr
A2: =[1]ELEC!A32 -> 0.013 | B2: 0.0299 | C2: 43951 | D2: =[1]ELEC!D32 -> 31633090 | E2: =[1]ELEC!E32 -> 2376 | F2: =[1]ELEC!F32 -> 3646395.6 | G2: =[1]ELEC!G32 -> 1679.2 | H2: =[1]ELEC!H32 -> 17427416 | I2: =[1]ELEC!I32 -> 1518 | J2: =[1]ELEC!J32 -> 28390420 | K2: =[1]ELEC!K32 -> 1094 | ... AI2: =[1]ELEC!AI32 -> -49806640
A3: ='General information '!F6 -> 0.0435 | B3: =SUM(230*A3) -> 10.005 | C3: 43952 | D3: 31635914 | E3: =D3-D2 -> 2824 | F3: 3647652 | G3: =F3-F2 -> 1256.4 | H3: 17428562 | I3: =H3-H2 -> 1146 | J3: 28391416 | K3: =J3-J2 -> 996 | L3: 22944766 | M3: =L3-L2 -> 2580 | N3: =M3+K3+I3+G3+E3 -> 8802.4 | O3: =IF(B3>0,N3/B3,0) -> 879.8001 | P3: 15481 | Q3: =(P3-P2)*1000 -> 1400 | R3: =+N3-Q3 -> 7402.4 | S3: =S2 -> 8454 | T3: =S3-S2 -> 0 | U3: =U2 -> 40221 | V3: =U3-U2 -> 0 | W3: 31845 | X3: =W3-W2 -> 0 | Y3: 624440 | Z3: =Y3-Y2 -> 0 | AA3: 35046 | AB3: =AA3-AA2 -> 4 | AC3: 774178 | AD3: =AC3-AC2 -> 835 | AE3: =AB3+X3+T3 -> 4 | AF3: =V3+Z3+AD3 -> 835 | AG3: =IF(AE3>0,AF3/AE3,0) -> 208.75
A4: ='General information '!F7 -> 0.039 | B4: =SUM(230*A4) -> 8.97 | C4: 43953 | D4: 31638542 | E4: =D4-D3 -> 2628 | F4: 3648979.6 | G4: =F4-F3 -> 1327.6 | H4: 17429750 | I4: =H4-H3 -> 1188 | J4: 28392346 | K4: =J4-J3 -> 930 | L4: 22947394 | M4: =L4-L3 -> 2628 | N4: =M4+K4+I4+G4+E4 -> 8701.6 | O4: =IF(B4>0,N4/B4,0) -> 970.07804 | P4: 15482.534 | Q4: =(P4-P3)*1000 -> 1534 | R4: =N4-Q4 -> 7167.6 | S4: =S3 -> 8454 | T4: =S4-S3 -> 0 | U4: =U3 -> 40221 | V4: =U4-U3 -> 0 | W4: =W3 -> 31845 | X4: =W4-W3 -> 0 | Y4: =Y3 -> 624440 | Z4: =Y4-Y3 -> 0 | AA4: 35049 | AB4: =AA4-AA3 -> 3 | AC4: 774785 | AD4: =AC4-AC3 -> 607 | AE4: =AB4+X4+T4 -> 3 | AF4: =V4+Z4+AD4 -> 607 | AG4: =IF(AE4>0,AF4/AE4,0) -> 202.33333
A5: ='General information '!F8 -> 0.0261 | B5: =SUM(230*A5) -> 6.003 | C5: 43954 | D5: 31643214 | E5: =D5-D4 -> 4672 | F5: 3650438 | G5: =F5-F4 -> 1458.4 | H5: 17431126 | I5: =H5-H4 -> 1376 | J5: 28393286 | K5: =J5-J4 -> 940 | L5: 22950286 | M5: =L5-L4 -> 2892 | N5: =M5+K5+I5+G5+E5 -> 11338.4 | O5: =IF(B5>0,N5/B5,0) -> 1888.7889 | P5: 15484 | Q5: =(P5-P4)*1000 -> 1466 | R5: =N5-Q5 -> 9872.4 | S5: =S4 -> 8454 | T5: =S5-S4 -> 0 | U5: =U4 -> 40221 | V5: =U5-U4 -> 0 | W5: 31845 | X5: =W5-W4 -> 0 | Y5: 624440 | Z5: =Y5-Y4 -> 0 | AA5: 35057 | AB5: =AA5-AA4 -> 8 | AC5: 776180 | AD5: =AC5-AC4 -> 1395 | AE5: =AB5+X5+T5 -> 8 | AF5: =V5+Z5+AD5 -> 1395 | AG5: =IF(AE5>0,AF5/AE5,0) -> 174.375 | AI5: =R5-'EDl log'!B3 -> -49817698
A6: ='General information '!F9 -> 0.0087 | B6: =SUM(230*A6) -> 2.001 | C6: 43955 | D6: 31646648 | E6: =D6-D5 -> 3434 | F6: 3651832 | G6: =F6-F5 -> 1394 | H6: 17432446 | I6: =H6-H5 -> 1320 | J6: 28394858 | K6: =J6-J5 -> 1572 | L6: 22953158 | M6: =L6-L5 -> 2872 | N6: =M6+K6+I6+G6+E6 -> 10592 | O6: =IF(B6>0,N6/B6,0) -> 5293.3533 | P6: 15485 | Q6: =(P6-P5)*1000 -> 1000 | R6: =N6-Q6 -> 9592 | S6: =S5 -> 8454 | T6: =S6-S5 -> 0 | U6: =U5 -> 40221 | V6: =U6-U5 -> 0 | W6: 31845 | X6: =W6-W5 -> 0 | Y6: 624440 | Z6: =Y6-Y5 -> 0 | AA6: 35061 | AB6: =AA6-AA5 -> 4 | AC6: 777210 | AD6: =AC6-AC5 -> 1030 | AE6: =AB6+X6+T6 -> 4 | AF6: =V6+Z6+AD6 -> 1030 | AG6: =IF(AE6>0,AF6/AE6,0) -> 257.5 | AI6: =R6-'EDl log'!B4 -> -49821551
A7: ='General information '!F10 -> 0 | B7: =SUM(230*A7) -> 0 | C7: 43956 | D7: =D6 -> 31646648 | E7: =D7-D6 -> 0 | F7: =F6 -> 3651832 | G7: =F7-F6 -> 0 | H7: =H6 -> 17432446 | I7: =H7-H6 -> 0 | J7: =J6 -> 28394858 | K7: =J7-J6 -> 0 | L7: =L6 -> 22953158 | M7: =L7-L6 -> 0 | N7: =M7+K7+I7+G7+E7 -> 0 | O7: =IF(B7>0,N7/B7,0) -> 0 | P7: =P6 -> 15485 | Q7: =(P7-P6)*1000 -> 0 | R7: =N7-Q7 -> 0 | S7: =S6 -> 8454 | T7: =S7-S6 -> 0 | U7: =U6 -> 40221 | V7: =U7-U6 -> 0 | W7: =W6 -> 31845 | X7: =W7-W6 -> 0 | Y7: =Y6 -> 624440 | Z7: =Y7-Y6 -> 0 | AA7: =AA6 -> 35061 | AB7: 6 | AC7: =AC6 -> 777210 | AD7: =AC7-AC6 -> 0 | AE7: =AB7+X7+T7 -> 6 | AF7: =V7+Z7+AD7 -> 0 | AG7: =IF(AE7>0,AF7/AE7,0) -> 0 | AI7: =R7-'EDl log'!B5 -> -49835173
A8: ='General information '!F11 -> 0 | B8: =SUM(230*A8) -> 0 | C8: 43957 | D8: =D7 -> 31646648 | E8: =D8-D7 -> 0 | F8: =F7 -> 3651832 | G8: =F8-F7 -> 0 | H8: =H7 -> 17432446 | I8: =H8-H7 -> 0 | J8: =J7 -> 28394858 | K8: =J8-J7 -> 0 | L8: =L7 -> 22953158 | M8: =L8-L7 -> 0 | N8: =M8+K8+I8+G8+E8 -> 0 | O8: =IF(B8>0,N8/B8,0) -> 0 | P8: =P7 -> 15485 | Q8: =(P8-P7)*1000 -> 0 | R8: =N8-Q8 -> 0 | S8: =S7 -> 8454 | T8: =S8-S7 -> 0 | U8: =U7 -> 40221 | V8: =U8-U7 -> 0 | W8: 31845 | X8: =W8-W7 -> 0 | Y8: 624440 | Z8: =Y8-Y7 -> 0 | AA8: =AA7 -> 35061 | AB8: =AA8-AA7 -> 0 | AC8: =AC7 -> 777210 | AD8: =AC8-AC7 -> 0 | AE8: =AB8+X8+T8 -> 0 | AF8: =V8+Z8+AD8 -> 0 | AG8: =IF(AE8>0,AF8/AE8,0) -> 0 | AI8: =R8-'EDl log'!B6 -> -49840476
A9: ='General information '!F12 -> 0 | B9: =SUM(230*A9) -> 0 | C9: 43958 | D9: =D8 -> 31646648 | E9: =D9-D8 -> 0 | F9: =F8 -> 3651832 | G9: =F9-F8 -> 0 | H9: =H8 -> 17432446 | I9: =H9-H8 -> 0 | J9: =J8 -> 28394858 | K9: =J9-J8 -> 0 | L9: =L8 -> 22953158 | M9: =L9-L8 -> 0 | N9: =M9+K9+I9+G9+E9 -> 0 | O9: =IF(B9>0,N9/B9,0) -> 0 | P9: =P8 -> 15485 | Q9: =(P9-P8)*1000 -> 0 | R9: =N9-Q9 -> 0 | S9: =S8 -> 8454 | T9: =S9-S8 -> 0 | U9: =U8 -> 40221 | V9: =U9-U8 -> 0 | W9: =W8 -> 31845 | X9: =W9-W8 -> 0 | Y9: =Y8 -> 624440 | Z9: =Y9-Y8 -> 0 | AA9: =AA8 -> 35061 | AB9: =AA9-AA8 -> 0 | AC9: =AC8 -> 777210 | AD9: =AC9-AC8 -> 0 | AE9: =AB9+X9+T9 -> 0 | AF9: =V9+Z9+AD9 -> 0 | AG9: =IF(AE9>0,AF9/AE9,0) -> 0 | AI9: =R9-'EDl log'!B7 -> -49844850
A10: ='General information '!F13 -> 0 | B10: =SUM(230*A10) -> 0 | C10: 43959 | D10: =D9 -> 31646648 | E10: =D10-D9 -> 0 | F10: =F9 -> 3651832 | G10: =F10-F9 -> 0 | H10: =H9 -> 17432446 | I10: =H10-H9 -> 0 | J10: =J9 -> 28394858 | K10: =J10-J9 -> 0 | L10: =L9 -> 22953158 | M10: =L10-L9 -> 0 | N10: =M10+K10+I10+G10+E10 -> 0 | O10: =IF(B10>0,N10/B10,0) -> 0 | P10: =P9 -> 15485 | Q10: =(P10-P9)*1000 -> 0 | R10: =N10-Q10 -> 0 | S10: =S9 -> 8454 | T10: =S10-S9 -> 0 | U10: =U9 -> 40221 | V10: =U10-U9 -> 0 | W10: 31845 | X10: =W10-W9 -> 0 | Y10: 624440 | Z10: =Y10-Y9 -> 0 | AA10: =AA9 -> 35061 | AB10: =AA10-AA9 -> 0 | AC10: =AC9 -> 777210 | AD10: =AC10-AC9 -> 0 | AE10: =AB10+X10+T10 -> 0 | AF10: =V10+Z10+AD10 -> 0 | AG10: =IF(AE10>0,AF10/AE10,0) -> 0 | AI10: =R10-'EDl log'!B8 -> -49844850
A11: ='General information '!F14 -> 0 | B11: =SUM(230*A11) -> 0 | C11: 43960 | D11: =D10 -> 31646648 | E11: =D11-D10 -> 0 | F11: =F10 -> 3651832 | G11: =F11-F10 -> 0 | H11: =H10 -> 17432446 | I11: =H11-H10 -> 0 | J11: =J10 -> 28394858 | K11: =J11-J10 -> 0 | L11: =L10 -> 22953158 | M11: =L11-L10 -> 0 | N11: =M11+K11+I11+G11+E11 -> 0 | O11: =IF(B11>0,N11/B11,0) -> 0 | P11: =P10 -> 15485 | Q11: =(P11-P10)*1000 -> 0 | R11: =N11-Q11 -> 0 | S11: =S10 -> 8454 | T11: =S11-S10 -> 0 | U11: =U10 -> 40221 | V11: =U11-U10 -> 0 | W11: =W10 -> 31845 | X11: =W11-W10 -> 0 | Y11: =Y10 -> 624440 | Z11: =Y11-Y10 -> 0 | AA11: =AA10 -> 35061 | AB11: =AA11-AA10 -> 0 | AC11: =AC10 -> 777210 | AD11: =AC11-AC10 -> 0 | AE11: =AB11+X11+T11 -> 0 | AF11: =V11+Z11+AD11 -> 0 | AG11: =IF(AE11>0,AF11/AE11,0) -> 0 | AI11: =R11-'EDl log'!B9 -> -49844850
A12: ='General information '!F15 -> 0 | B12: =SUM(230*A12) -> 0 | C12: 43961 | D12: =D11 -> 31646648 | E12: =D12-D11 -> 0 | F12: =F11 -> 3651832 | G12: =F12-F11 -> 0 | H12: =H11 -> 17432446 | I12: =H12-H11 -> 0 | J12: =J11 -> 28394858 | K12: =J12-J11 -> 0 | L12: =L11 -> 22953158 | M12: =L12-L11 -> 0 | N12: =M12+K12+I12+G12+E12 -> 0 | O12: =IF(B12>0,N12/B12,0) -> 0 | P12: =P11 -> 15485 | Q12: =(P12-P11)*1000 -> 0 | R12: =N12-Q12 -> 0 | S12: =S11 -> 8454 | T12: =S12-S11 -> 0 | U12: =U11 -> 40221 | V12: =U12-U11 -> 0 | W12: 31845 | X12: =W12-W11 -> 0 | Y12: 624440 | Z12: =Y12-Y11 -> 0 | AA12: =AA11 -> 35061 | AB12: =AA12-AA11 -> 0 | AC12: =AC11 -> 777210 | AD12: =AC12-AC11 -> 0 | AE12: =AB12+X12+T12 -> 0 | AF12: =V12+Z12+AD12 -> 0 | AG12: =IF(AE12>0,AF12/AE12,0) -> 0 | AI12: =R12-'EDl log'!B10 -> -49844850
A13: ='General information '!F16 -> 0 | B13: =SUM(230*A13) -> 0 | C13: 43962 | D13: =D12 -> 31646648 | E13: =D13-D12 -> 0 | F13: =F12 -> 3651832 | G13: =F13-F12 -> 0 | H13: =H12 -> 17432446 | I13: =H13-H12 -> 0 | J13: =J12 -> 28394858 | K13: =J13-J12 -> 0 | L13: =L12 -> 22953158 | M13: =L13-L12 -> 0 | N13: =M13+K13+I13+G13+E13 -> 0 | O13: =IF(B13>0,N13/B13,0) -> 0 | P13: =P12 -> 15485 | Q13: =(P13-P12)*1000 -> 0 | R13: =N13-Q13 -> 0 | S13: =S12 -> 8454 | T13: =S13-S12 -> 0 | U13: =U12 -> 40221 | V13: =U13-U12 -> 0 | W13: 31845 | X13: =W13-W12 -> 0 | Y13: 624440 | Z13: =Y13-Y12 -> 0 | AA13: =AA12 -> 35061 | AB13: =AA13-AA12 -> 0 | AC13: =AC12 -> 777210 | AD13: =AC13-AC12 -> 0 | AE13: =AB13+X13+T13 -> 0 | AF13: =V13+Z13+AD13 -> 0 | AG13: =IF(AE13>0,AF13/AE13,0) -> 0 | AI13: =R13-'EDl log'!B11 -> -49844850
A14: ='General information '!F17 -> 0 | B14: =SUM(230*A14) -> 0 | C14: 43963 | D14: =D13 -> 31646648 | E14: =D14-D13 -> 0 | F14: =F13 -> 3651832 | G14: =F14-F13 -> 0 | H14: =H13 -> 17432446 | I14: =H14-H13 -> 0 | J14: =J13 -> 28394858 | K14: =J14-J13 -> 0 | L14: =L13 -> 22953158 | M14: =L14-L13 -> 0 | N14: =M14+K14+I14+G14+E14 -> 0 | O14: =IF(B14>0,N14/B14,0) -> 0 | P14: =P13 -> 15485 | Q14: =(P14-P13)*1000 -> 0 | R14: =N14-Q14 -> 0 | S14: =S13 -> 8454 | T14: =S14-S13 -> 0 | U14: =U13 -> 40221 | V14: =U14-U13 -> 0 | W14: 31845 | X14: =W14-W13 -> 0 | Y14: 624440 | Z14: =Y14-Y13 -> 0 | AA14: =AA13 -> 35061 | AB14: =AA14-AA13 -> 0 | AC14: =AC13 -> 777210 | AD14: =AC14-AC13 -> 0 | AE14: =AB14+X14+T14 -> 0 | AF14: =V14+Z14+AD14 -> 0 | AG14: =IF(AE14>0,AF14/AE14,0) -> 0 | AI14: =R14-'EDl log'!B12 -> -49844850
A15: ='General information '!F18 -> 0 | B15: =SUM(230*A15) -> 0 | C15: 43964 | D15: =D14 -> 31646648 | E15: =D15-D14 -> 0 | F15: =F14 -> 3651832 | G15: =F15-F14 -> 0 | H15: =H14 -> 17432446 | I15: =H15-H14 -> 0 | J15: =J14 -> 28394858 | K15: =J15-J14 -> 0 | L15: =L14 -> 22953158 | M15: =L15-L14 -> 0 | N15: =M15+K15+I15+G15+E15 -> 0 | O15: =IF(B15>0,N15/B15,0) -> 0 | P15: =P14 -> 15485 | Q15: =(P15-P14)*1000 -> 0 | R15: =N15-Q15 -> 0 | S15: =S14 -> 8454 | T15: =S15-S14 -> 0 | U15: =U14 -> 40221 | V15: =U15-U14 -> 0 | W15: =W14 -> 31845 | X15: =W15-W14 -> 0 | Y15: =Y14 -> 624440 | Z15: =Y15-Y14 -> 0 | AA15: =AA14 -> 35061 | AB15: =AA15-AA14 -> 0 | AC15: =AC14 -> 777210 | AD15: =AC15-AC14 -> 0 | AE15: =AB15+X15+T15 -> 0 | AF15: =V15+Z15+AD15 -> 0 | AG15: =IF(AE15>0,AF15/AE15,0) -> 0 | AI15: =R15-'EDl log'!B13 -> -49844850
A16: ='General information '!F19 -> 0 | B16: =SUM(230*A16) -> 0 | C16: 43965 | D16: =D15 -> 31646648 | E16: =D16-D15 -> 0 | F16: =F15 -> 3651832 | G16: =F16-F15 -> 0 | H16: =H15 -> 17432446 | I16: =H16-H15 -> 0 | J16: =J15 -> 28394858 | K16: =J16-J15 -> 0 | L16: =L15 -> 22953158 | M16: =L16-L15 -> 0 | N16: =M16+K16+I16+G16+E16 -> 0 | O16: =IF(B16>0,N16/B16,0) -> 0 | P16: =P15 -> 15485 | Q16: =(P16-P15)*1000 -> 0 | R16: =N16-Q16 -> 0 | S16: =S15 -> 8454 | T16: =S16-S15 -> 0 | U16: =U15 -> 40221 | V16: =U16-U15 -> 0 | W16: =W15 -> 31845 | X16: =W16-W15 -> 0 | Y16: =Y15 -> 624440 | Z16: =Y16-Y15 -> 0 | AA16: =AA15 -> 35061 | AB16: =AA16-AA15 -> 0 | AC16: =AC15 -> 777210 | AD16: =AC16-AC15 -> 0 | AE16: =AB16+X16+T16 -> 0 | AF16: =V16+Z16+AD16 -> 0 | AG16: =IF(AE16>0,AF16/AE16,0) -> 0 | AI16: =R16-'EDl log'!B14 -> -49844850
A17: ='General information '!F20 -> 0 | B17: =SUM(230*A17) -> 0 | C17: 43966 | D17: =D16 -> 31646648 | E17: =D17-D16 -> 0 | F17: =F16 -> 3651832 | G17: =F17-F16 -> 0 | H17: =H16 -> 17432446 | I17: =H17-H16 -> 0 | J17: =J16 -> 28394858 | K17: =J17-J16 -> 0 | L17: =L16 -> 22953158 | M17: =L17-L16 -> 0 | N17: =M17+K17+I17+G17+E17 -> 0 | O17: =IF(B17>0,N17/B17,0) -> 0 | P17: =P16 -> 15485 | Q17: =(P17-P16)*1000 -> 0 | R17: =N17-Q17 -> 0 | S17: =S16 -> 8454 | T17: =S17-S16 -> 0 | U17: =U16 -> 40221 | V17: =U17-U16 -> 0 | W17: =W16 -> 31845 | X17: =W17-W16 -> 0 | Y17: =Y16 -> 624440 | Z17: =Y17-Y16 -> 0 | AA17: =AA16 -> 35061 | AB17: =AA17-AA16 -> 0 | AC17: =AC16 -> 777210 | AD17: =AC17-AC16 -> 0 | AE17: =AB17+X17+T17 -> 0 | AF17: =V17+Z17+AD17 -> 0 | AG17: =IF(AE17>0,AF17/AE17,0) -> 0 | AI17: =R17-'EDl log'!B15 -> -49844850
A18: ='General information '!F21 -> 0 | B18: =SUM(230*A18) -> 0 | C18: 43967 | D18: =D17 -> 31646648 | E18: =D18-D17 -> 0 | F18: =F17 -> 3651832 | G18: =F18-F17 -> 0 | H18: =H17 -> 17432446 | I18: =H18-H17 -> 0 | J18: =J17 -> 28394858 | K18: =J18-J17 -> 0 | L18: =L17 -> 22953158 | M18: =L18-L17 -> 0 | N18: =M18+K18+I18+G18+E18 -> 0 | O18: =IF(B18>0,N18/B18,0) -> 0 | P18: =P17 -> 15485 | Q18: =(P18-P17)*1000 -> 0 | R18: =N18-Q18 -> 0 | S18: =S17 -> 8454 | T18: =S18-S17 -> 0 | U18: =U17 -> 40221 | V18: =U18-U17 -> 0 | W18: =[2]ELEC!K18 -> 31845 | X18: =W18-W17 -> 0 | Y18: =[2]ELEC!L18 -> 624440 | Z18: =Y18-Y17 -> 0 | AA18: =AA17 -> 35061 | AB18: =AA18-AA17 -> 0 | AC18: =AC17 -> 777210 | AD18: =AC18-AC17 -> 0 | AE18: =AB18+X18+T18 -> 0 | AF18: =V18+Z18+AD18 -> 0 | AG18: =IF(AE18>0,AF18/AE18,0) -> 0 | AI18: =R18-'EDl log'!B16 -> -49844850
A19: ='General information '!F22 -> 0 | B19: =SUM(230*A19) -> 0 | C19: 43968 | D19: =D18 -> 31646648 | E19: =D19-D18 -> 0 | F19: =F18 -> 3651832 | G19: =F19-F18 -> 0 | H19: =H18 -> 17432446 | I19: =H19-H18 -> 0 | J19: =J18 -> 28394858 | K19: =J19-J18 -> 0 | L19: =L18 -> 22953158 | M19: =L19-L18 -> 0 | N19: =M19+K19+I19+G19+E19 -> 0 | O19: =IF(B19>0,N19/B19,0) -> 0 | P19: =P18 -> 15485 | Q19: =(P19-P18)*1000 -> 0 | R19: =N19-Q19 -> 0 | S19: =S18 -> 8454 | T19: =S19-S18 -> 0 | U19: =U18 -> 40221 | V19: =U19-U18 -> 0 | W19: =[2]ELEC!K19 -> 31845 | X19: =W19-W18 -> 0 | Y19: =[2]ELEC!L19 -> 624440 | Z19: =Y19-Y18 -> 0 | AA19: =AA18 -> 35061 | AB19: =AA19-AA18 -> 0 | AC19: =AC18 -> 777210 | AD19: =AC19-AC18 -> 0 | AE19: =AB19+X19+T19 -> 0 | AF19: =V19+Z19+AD19 -> 0 | AG19: =IF(AE19>0,AF19/AE19,0) -> 0 | AI19: =R19-'EDl log'!B17 -> -49844850
A20: ='General information '!F23 -> 0 | B20: =SUM(230*A20) -> 0 | C20: 43969 | D20: =D19 -> 31646648 | E20: =D20-D19 -> 0 | F20: =F19 -> 3651832 | G20: =F20-F19 -> 0 | H20: =H19 -> 17432446 | I20: =H20-H19 -> 0 | J20: =J19 -> 28394858 | K20: =J20-J19 -> 0 | L20: =L19 -> 22953158 | M20: =L20-L19 -> 0 | N20: =M20+K20+I20+G20+E20 -> 0 | O20: =IF(B20>0,N20/B20,0) -> 0 | P20: =P19 -> 15485 | Q20: =(P20-P19)*1000 -> 0 | R20: =N20-Q20 -> 0 | S20: =S19 -> 8454 | T20: =S20-S19 -> 0 | U20: =U19 -> 40221 | V20: =U20-U19 -> 0 | W20: 31845 | X20: =W20-W19 -> 0 | Y20: 624440 | Z20: =Y20-Y19 -> 0 | AA20: =AA19 -> 35061 | AB20: =AA20-AA19 -> 0 | AC20: =AC19 -> 777210 | AD20: =AC20-AC19 -> 0 | AE20: =AB20+X20+T20 -> 0 | AF20: =V20+Z20+AD20 -> 0 | AG20: =IF(AE20>0,AF20/AE20,0) -> 0 | AI20: =R20-'EDl log'!B18 -> -49844850
A21: ='General information '!F24 -> 0 | B21: =SUM(230*A21) -> 0 | C21: 43970 | D21: =D20 -> 31646648 | E21: =D21-D20 -> 0 | F21: =F20 -> 3651832 | G21: =F21-F20 -> 0 | H21: =H20 -> 17432446 | I21: =H21-H20 -> 0 | J21: =J20 -> 28394858 | K21: =J21-J20 -> 0 | L21: =L20 -> 22953158 | M21: =L21-L20 -> 0 | N21: =M21+K21+I21+G21+E21 -> 0 | O21: =IF(B21>0,N21/B21,0) -> 0 | P21: =P20 -> 15485 | Q21: =(P21-P20)*1000 -> 0 | R21: =N21-Q21 -> 0 | S21: =S20 -> 8454 | T21: =S21-S20 -> 0 | U21: =U20 -> 40221 | V21: =U21-U20 -> 0 | W21: =W20 -> 31845 | X21: =W21-W20 -> 0 | Y21: =Y20 -> 624440 | Z21: =Y21-Y20 -> 0 | AA21: =AA20 -> 35061 | AB21: =AA21-AA20 -> 0 | AC21: =AC20 -> 777210 | AD21: =AC21-AC20 -> 0 | AE21: =AB21+X21+T21 -> 0 | AF21: =V21+Z21+AD21 -> 0 | AG21: =IF(AE21>0,AF21/AE21,0) -> 0 | AI21: =R21-'EDl log'!B19 -> -49844850
A22: ='General information '!F25 -> 0 | B22: =SUM(230*A22) -> 0 | C22: 43971 | D22: =D21 -> 31646648 | E22: =D22-D21 -> 0 | F22: =F21 -> 3651832 | G22: =F22-F21 -> 0 | H22: =H21 -> 17432446 | I22: =H22-H21 -> 0 | J22: =J21 -> 28394858 | K22: =J22-J21 -> 0 | L22: =L21 -> 22953158 | M22: =L22-L21 -> 0 | N22: =M22+K22+I22+G22+E22 -> 0 | O22: =IF(B22>0,N22/B22,0) -> 0 | P22: =P21 -> 15485 | Q22: =(P22-P21)*1000 -> 0 | R22: =N22-Q22 -> 0 | S22: =S21 -> 8454 | T22: =S22-S21 -> 0 | U22: =U21 -> 40221 | V22: =U22-U21 -> 0 | W22: =W21 -> 31845 | X22: =W22-W21 -> 0 | Y22: =Y21 -> 624440 | Z22: =Y22-Y21 -> 0 | AA22: =AA21 -> 35061 | AB22: =AA22-AA21 -> 0 | AC22: =AC21 -> 777210 | AD22: =AC22-AC21 -> 0 | AE22: =AB22+X22+T22 -> 0 | AF22: =V22+Z22+AD22 -> 0 | AG22: =IF(AE22>0,AF22/AE22,0) -> 0 | AI22: =R22-'EDl log'!B20 -> -49844850
A23: ='General information '!F26 -> 0 | B23: =SUM(230*A23) -> 0 | C23: 43972 | D23: =D22 -> 31646648 | E23: =D23-D22 -> 0 | F23: =F22 -> 3651832 | G23: =F23-F22 -> 0 | H23: =H22 -> 17432446 | I23: =H23-H22 -> 0 | J23: =J22 -> 28394858 | K23: =J23-J22 -> 0 | L23: =L22 -> 22953158 | M23: =L23-L22 -> 0 | N23: =M23+K23+I23+G23+E23 -> 0 | O23: =IF(B23>0,N23/B23,0) -> 0 | P23: =P22 -> 15485 | Q23: =(P23-P22)*1000 -> 0 | R23: =N23-Q23 -> 0 | S23: =S22 -> 8454 | T23: =S23-S22 -> 0 | U23: =U22 -> 40221 | V23: =U23-U22 -> 0 | W23: =W22 -> 31845 | X23: =W23-W22 -> 0 | Y23: =Y22 -> 624440 | Z23: =Y23-Y22 -> 0 | AA23: =AA22 -> 35061 | AB23: =AA23-AA22 -> 0 | AC23: =AC22 -> 777210 | AD23: =AC23-AC22 -> 0 | AE23: =AB23+X23+T23 -> 0 | AF23: =V23+Z23+AD23 -> 0 | AG23: =IF(AE23>0,AF23/AE23,0) -> 0 | AI23: =R23-'EDl log'!B21 -> -49844850
A24: ='General information '!F27 -> 0 | B24: =SUM(230*A24) -> 0 | C24: 43973 | D24: =D23 -> 31646648 | E24: =D24-D23 -> 0 | F24: =F23 -> 3651832 | G24: =F24-F23 -> 0 | H24: =H23 -> 17432446 | I24: =H24-H23 -> 0 | J24: =J23 -> 28394858 | K24: =J24-J23 -> 0 | L24: =L23 -> 22953158 | M24: =L24-L23 -> 0 | N24: =M24+K24+I24+G24+E24 -> 0 | O24: =IF(B24>0,N24/B24,0) -> 0 | P24: =P23 -> 15485 | Q24: =(P24-P23)*1000 -> 0 | R24: =N24-Q24 -> 0 | S24: =S23 -> 8454 | T24: =S24-S23 -> 0 | U24: =U23 -> 40221 | V24: =U24-U23 -> 0 | W24: =W23 -> 31845 | X24: =W24-W23 -> 0 | Y24: =Y23 -> 624440 | Z24: =Y24-Y23 -> 0 | AA24: =AA23 -> 35061 | AB24: =AA24-AA23 -> 0 | AC24: =AC23 -> 777210 | AD24: =AC24-AC23 -> 0 | AE24: =AB24+X24+T24 -> 0 | AF24: =V24+Z24+AD24 -> 0 | AG24: =IF(AE24>0,AF24/AE24,0) -> 0 | AI24: =R24-'EDl log'!B22 -> -49844850
A25: ='General information '!F28 -> 0 | B25: =SUM(230*A25) -> 0 | C25: 43974 | D25: =D24 -> 31646648 | E25: =D25-D24 -> 0 | F25: =F24 -> 3651832 | G25: =F25-F24 -> 0 | H25: =H24 -> 17432446 | I25: =H25-H24 -> 0 | J25: =J24 -> 28394858 | K25: =J25-J24 -> 0 | L25: =L24 -> 22953158 | M25: =L25-L24 -> 0 | N25: =M25+K25+I25+G25+E25 -> 0 | O25: =IF(B25>0,N25/B25,0) -> 0 | P25: =P24 -> 15485 | Q25: =(P25-P24)*1000 -> 0 | R25: =N25-Q25 -> 0 | S25: =S24 -> 8454 | T25: =S25-S24 -> 0 | U25: =U24 -> 40221 | V25: =U25-U24 -> 0 | W25: =W24 -> 31845 | X25: =W25-W24 -> 0 | Y25: =Y24 -> 624440 | Z25: =Y25-Y24 -> 0 | AA25: =AA24 -> 35061 | AB25: =AA25-AA24 -> 0 | AC25: =AC24 -> 777210 | AD25: =AC25-AC24 -> 0 | AE25: =AB25+X25+T25 -> 0 | AF25: =V25+Z25+AD25 -> 0 | AG25: =IF(AE25>0,AF25/AE25,0) -> 0 | AI25: =R25-'EDl log'!B23 -> -49844850
A26: ='General information '!F29 -> 0 | B26: =SUM(230*A26) -> 0 | C26: 43975 | D26: =D25 -> 31646648 | E26: =D26-D25 -> 0 | F26: =F25 -> 3651832 | G26: =F26-F25 -> 0 | H26: =H25 -> 17432446 | I26: =H26-H25 -> 0 | J26: =J25 -> 28394858 | K26: =J26-J25 -> 0 | L26: =L25 -> 22953158 | M26: =L26-L25 -> 0 | N26: =M26+K26+I26+G26+E26 -> 0 | O26: =IF(B26>0,N26/B26,0) -> 0 | P26: =P25 -> 15485 | Q26: =(P26-P25)*1000 -> 0 | R26: =N26-Q26 -> 0 | S26: =S25 -> 8454 | T26: =S26-S25 -> 0 | U26: =U25 -> 40221 | V26: =U26-U25 -> 0 | W26: =W25 -> 31845 | X26: =W26-W25 -> 0 | Y26: =Y25 -> 624440 | Z26: =Y26-Y25 -> 0 | AA26: =AA25 -> 35061 | AB26: =AA26-AA25 -> 0 | AC26: =AC25 -> 777210 | AD26: =AC26-AC25 -> 0 | AE26: =AB26+X26+T26 -> 0 | AF26: =V26+Z26+AD26 -> 0 | AG26: =IF(AE26>0,AF26/AE26,0) -> 0 | AI26: =R26-'EDl log'!B24 -> -49844850
A27: ='General information '!F30 -> 0 | B27: =SUM(230*A27) -> 0 | C27: 43976 | D27: =D26 -> 31646648 | E27: =D27-D26 -> 0 | F27: =F26 -> 3651832 | G27: =F27-F26 -> 0 | H27: =H26 -> 17432446 | I27: =H27-H26 -> 0 | J27: =J26 -> 28394858 | K27: =J27-J26 -> 0 | L27: =L26 -> 22953158 | M27: =L27-L26 -> 0 | N27: =M27+K27+I27+G27+E27 -> 0 | O27: =IF(B27>0,N27/B27,0) -> 0 | P27: =P26 -> 15485 | Q27: =(P27-P26)*1000 -> 0 | R27: =N27-Q27 -> 0 | S27: =S26 -> 8454 | T27: =S27-S26 -> 0 | U27: =U26 -> 40221 | V27: =U27-U26 -> 0 | W27: 31845 | X27: =W27-W26 -> 0 | Y27: 624440 | Z27: =Y27-Y26 -> 0 | AA27: =AA26 -> 35061 | AB27: =AA27-AA26 -> 0 | AC27: =AC26 -> 777210 | AD27: =AC27-AC26 -> 0 | AE27: =AB27+X27+T27 -> 0 | AF27: =V27+Z27+AD27 -> 0 | AG27: =IF(AE27>0,AF27/AE27,0) -> 0 | AI27: =R27-'EDl log'!B25 -> -49844850
A28: ='General information '!F31 -> 0 | B28: =SUM(230*A28) -> 0 | C28: 43977 | D28: =D27 -> 31646648 | E28: =D28-D27 -> 0 | F28: =F27 -> 3651832 | G28: =F28-F27 -> 0 | H28: =H27 -> 17432446 | I28: =H28-H27 -> 0 | J28: =J27 -> 28394858 | K28: =J28-J27 -> 0 | L28: =L27 -> 22953158 | M28: =L28-L27 -> 0 | N28: =M28+K28+I28+G28+E28 -> 0 | O28: =IF(B28>0,N28/B28,0) -> 0 | P28: =P27 -> 15485 | Q28: =(P28-P27)*1000 -> 0 | R28: =N28-Q28 -> 0 | S28: =S27 -> 8454 | T28: =S28-S27 -> 0 | U28: =U27 -> 40221 | V28: =U28-U27 -> 0 | W28: =W27 -> 31845 | X28: =W28-W27 -> 0 | Y28: =Y27 -> 624440 | Z28: =Y28-Y27 -> 0 | AA28: =AA27 -> 35061 | AB28: =AA28-AA27 -> 0 | AC28: =AC27 -> 777210 | AD28: =AC28-AC27 -> 0 | AE28: =AB28+X28+T28 -> 0 | AF28: =V28+Z28+AD28 -> 0 | AG28: =IF(AE28>0,AF28/AE28,0) -> 0 | AI28: =R28-'EDl log'!B26 -> -49844850
A29: ='General information '!F32 -> 0 | B29: =SUM(230*A29) -> 0 | C29: 43978 | D29: =D28 -> 31646648 | E29: =D29-D28 -> 0 | F29: =F28 -> 3651832 | G29: =F29-F28 -> 0 | H29: =H28 -> 17432446 | I29: =H29-H28 -> 0 | J29: =J28 -> 28394858 | K29: =J29-J28 -> 0 | L29: =L28 -> 22953158 | M29: =L29-L28 -> 0 | N29: =M29+K29+I29+G29+E29 -> 0 | O29: =IF(B29>0,N29/B29,0) -> 0 | P29: =P28 -> 15485 | Q29: =(P29-P28)*1000 -> 0 | R29: =N29-Q29 -> 0 | S29: =S28 -> 8454 | T29: =S29-S28 -> 0 | U29: =U28 -> 40221 | V29: =U29-U28 -> 0 | W29: 31845 | X29: =W29-W28 -> 0 | Y29: =Y28 -> 624440 | Z29: =Y29-Y28 -> 0 | AA29: =AA28 -> 35061 | AB29: =AA29-AA28 -> 0 | AC29: =AC28 -> 777210 | AD29: =AC29-AC28 -> 0 | AE29: =AB29+X29+T29 -> 0 | AF29: =V29+Z29+AD29 -> 0 | AG29: =IF(AE29>0,AF29/AE29,0) -> 0 | AI29: =R29-'EDl log'!B27 -> -49844850
A30: ='General information '!F33 -> 0 | B30: =SUM(230*A30) -> 0 | C30: 43979 | D30: =D29 -> 31646648 | E30: =D30-D29 -> 0 | F30: =F29 -> 3651832 | G30: =F30-F29 -> 0 | H30: =H29 -> 17432446 | I30: =H30-H29 -> 0 | J30: =J29 -> 28394858 | K30: =J30-J29 -> 0 | L30: =L29 -> 22953158 | M30: =L30-L29 -> 0 | N30: =M30+K30+I30+G30+E30 -> 0 | O30: =IF(B30>0,N30/B30,0) -> 0 | P30: =P29 -> 15485 | Q30: =(P30-P29)*1000 -> 0 | R30: =N30-Q30 -> 0 | S30: =S29 -> 8454 | T30: =S30-S29 -> 0 | U30: =U29 -> 40221 | V30: =U30-U29 -> 0 | W30: =W29 -> 31845 | X30: =W30-W29 -> 0 | Y30: =Y29 -> 624440 | Z30: =Y30-Y29 -> 0 | AA30: =AA29 -> 35061 | AB30: =AA30-AA29 -> 0 | AC30: =AC29 -> 777210 | AD30: =AC30-AC29 -> 0 | AE30: =AB30+X30+T30 -> 0 | AF30: =V30+Z30+AD30 -> 0 | AG30: =IF(AE30>0,AF30/AE30,0) -> 0 | AI30: =R30-'EDl log'!B28 -> -49844850
A31: ='General information '!F34 -> 0 | B31: =SUM(230*A31) -> 0 | C31: 43980 | D31: =D30 -> 31646648 | E31: =D31-D30 -> 0 | F31: =F30 -> 3651832 | G31: =F31-F30 -> 0 | H31: =H30 -> 17432446 | I31: =H31-H30 -> 0 | J31: =J30 -> 28394858 | K31: =J31-J30 -> 0 | L31: =L30 -> 22953158 | M31: =L31-L30 -> 0 | N31: =M31+K31+I31+G31+E31 -> 0 | O31: =IF(B31>0,N31/B31,0) -> 0 | P31: =P30 -> 15485 | Q31: =(P31-P30)*1000 -> 0 | R31: =N31-Q31 -> 0 | S31: =S30 -> 8454 | T31: =S31-S30 -> 0 | U31: =U30 -> 40221 | V31: =U31-U30 -> 0 | W31: 31845 | X31: =W31-W30 -> 0 | Y31: 624440 | Z31: =Y31-Y30 -> 0 | AA31: =AA30 -> 35061 | AB31: =AA31-AA30 -> 0 | AC31: =AC30 -> 777210 | AD31: =AC31-AC30 -> 0 | AE31: =AB31+X31+T31 -> 0 | AF31: =V31+Z31+AD31 -> 0 | AG31: =IF(AE31>0,AF31/AE31,0) -> 0 | AI31: =R31-'EDl log'!B29 -> -49844850
A32: ='General information '!F35 -> 0 | B32: =SUM(230*A32) -> 0 | C32: 43981 | D32: =D31 -> 31646648 | E32: =D32-D31 -> 0 | F32: =F31 -> 3651832 | G32: =F32-F31 -> 0 | H32: =H31 -> 17432446 | I32: =H32-H31 -> 0 | J32: =J31 -> 28394858 | K32: =J32-J31 -> 0 | L32: =L31 -> 22953158 | M32: =L32-L31 -> 0 | N32: =M32+K32+I32+G32+E32 -> 0 | O32: =IF(B32>0,N32/B32,0) -> 0 | P32: =P31 -> 15485 | Q32: =(P32-P31)*1000 -> 0 | R32: =N32-Q32 -> 0 | S32: =S31 -> 8454 | T32: =S32-S31 -> 0 | U32: =U31 -> 40221 | V32: =U32-U31 -> 0 | W32: =W31 -> 31845 | X32: =W32-W31 -> 0 | Y32: =Y31 -> 624440 | Z32: =Y32-Y31 -> 0 | AA32: =AA31 -> 35061 | AB32: =AA32-AA31 -> 0 | AC32: =AC31 -> 777210 | AD32: =AC32-AC31 -> 0 | AE32: =AB32+X32+T32 -> 0 | AF32: =V32+Z32+AD32 -> 0 | AG32: =IF(AE32>0,AF32/AE32,0) -> 0 | AI32: =R32-'EDl log'!B30 -> -49844850
A33: ='General information '!F36 -> 0 | B33: =SUM(230*A33) -> 0 | C33: 43982 | D33: =D32 -> 31646648 | E33: =D33-D32 -> 0 | F33: =F32 -> 3651832 | G33: =F33-F32 -> 0 | H33: =H32 -> 17432446 | I33: =H33-H32 -> 0 | J33: =J32 -> 28394858 | K33: =J33-J32 -> 0 | L33: =L32 -> 22953158 | M33: =L33-L32 -> 0 | N33: =M33+K33+I33+G33+E33 -> 0 | O33: =IF(B33>0,N33/B33,0) -> 0 | P33: =P32 -> 15485 | Q33: =(P33-P32)*1000 -> 0 | R33: =N33-Q33 -> 0 | S33: =S32 -> 8454 | T33: =S33-S32 -> 0 | U33: =U32 -> 40221 | V33: =U33-U32 -> 0 | W33: =W32 -> 31845 | X33: =W33-W32 -> 0 | Y33: =Y32 -> 624440 | Z33: =Y33-Y32 -> 0 | AA33: =AA32 -> 35061 | AB33: =AA33-AA32 -> 0 | AC33: =AC32 -> 777210 | AD33: =AC33-AC32 -> 0 | AE33: =AB33+X33+T33 -> 0 | AF33: =V33+Z33+AD33 -> 0 | AG33: =IF(AE33>0,AF33/AE33,0) -> 0 | AI33: =R33-'EDl log'!B31 -> -49844850

Sheet B5
F1: Boiler A | J1: =J36 -> 48.666667 | K1: Boiler B | P1: Boiler C | V1: Boiler | X1: SteamA | AC1: SteamB | AH1: Steam | AI1: Boiler & steam | AL1: Total Boiler Runing H | AM1: Total Steam Runing H | AN1: GAS1 % | AO1: GAS1/L | AP1: GAS2% | AQ1: Gas2/L | AR1: GAS3% | AS1: GAS3/L | AU1: Gas Cons | AV1: Delivery | AW1: Cost/L
B2: Level Tank Gen | C2: Level tank Boiler | D2: Daily Cons Bo. | E2: Boiler litter | F2: Boiler A | G2: Run Hr a | H2: Boiler A fuel | I2: Daily consumption | J2: AVG | K2: index Run H | L2: Run Hrb | M2: Boiler B Fuel | O2: Daily consumption | P2: Boiler C | S2: Run C | U2: Total RH | V2: Total Fuel | X2: SteamA | Y2: Run SA | Z2: Steam A Conter | AA2: Liters | AC2: SteamB | AD2: Run SteamB | AE2: Steam B Conter | AF2: SB Litters | AG2: Avg | AH2: Total Fuel | AI2: Total Fuel
S3: 0
A4: =ELEC!C2 -> 43951 | B4: =[1]B5!B34 -> 245.5 | C4: =[1]B5!C34 -> 251 | D4: =[1]B5!D34 -> 3 | E4: =[1]B5!E34 -> 25.14 | F4: =[1]B5!F34 -> 1537 | G4: =[1]B5!G34 -> 1 | H4: =[1]B5!H34 -> 349198 | I4: =[1]B5!I34 -> 108 | ... AX4: =[1]B5!AX34 -> 0.7
A5: =ELEC!C3 -> 43952 | B5: 242 | C5: 248 | D5: =C4-C5 -> 3 | E5: =D5*8.38 -> 25.14 | F5: 1537 | G5: =F5-F4 -> 0 | H5: 349198 | I5: =SUM(H5-H4) -> 0 | J5: 1 | K5: 1921 | L5: =K5-K4 -> 2 | M5: 140667 | N5: =M5-M4 -> 104 | O5: =SUM(L5*$J$1) -> 97.333333 | P5: 1767 | Q5: 150185 | R5: =Q5-Q4 -> 245 | S5: =SUM(P5-P4) -> 4 | T5: =SUM(S5*$T$2) -> 0 | U5: =SUM(G5+L5+S5) -> 6 | V5: =R5+N5+I5:I5 -> 349 | W5: =SUM(V5/U5) -> 58.166667 | X5: =X4 -> 2417 | Y5: =X5-X4 -> 0 | Z5: =Z4 -> 135845.1 | AA5: =Z5-Z4 -> 0 | AB5: =SUM(Y5*$AB$2) -> 0 | AC5: =AC4 -> 1824 | AD5: =AC5-AC4 -> 0 | AE5: =AE4 -> 358865.2 | AF5: =AE5-AE4 -> 0 | AG5: =IF(AD5>0,AF5/AD5,0) -> 0 | AH5: =AF5+AA5 -> 0 | AI5: =SUM(AH5+V5) -> 349 | AJ5: =-tanks!AW6 -> 349 | AK5: =SUM(AJ5-AI5) -> 0 | AL5: =S5+L5+G5 -> 6 | AM5: =Y5+AD5 -> 0 | AN5: 80 | AO5: =(AN5/100)*3000 -> 2400 | AP5: 80 | AQ5: =(AP5/100)*3000 -> 2400 | AR5: 60 | AS5: =(AR5/100)*3000 -> 1800 | AT5: =SUM(AO5+AQ5+AS5) -> 6600 | AU5: =AT4-AT5+AV5 -> 60 | AX5: =IF(AV5>0,AW5,AX4) -> 0.7
A6: =ELEC!C4 -> 43953 | B6: 240 | C6: 246 | D6: =C5-C6 -> 2 | E6: =D6*8.38 -> 16.76 | F6: 1539 | G6: =F6-F5 -> 2 | H6: 349357 | I6: =SUM(H6-H5) -> 159 | J6: =IF(G6>0,I6/G6,0) -> 79.5 | K6: =K5 -> 1921 | L6: =K6-K5 -> 0 | M6: =M5 -> 140667 | N6: =M6-M5 -> 0 | O6: =SUM(L6*$J$1) -> 0 | P6: 1768 | Q6: 150275 | R6: =Q6-Q5 -> 90 | S6: =SUM(P6-P5) -> 1 | T6: =SUM(S6*$T$2) -> 0 | U6: =SUM(G6+L6+S6) -> 3 | V6: =R6+N6+I6:I6 -> 249 | W6: =SUM(V6/U6) -> 83 | X6: =X5 -> 2417 | Y6: =X6-X5 -> 0 | Z6: =Z5 -> 135845.1 | AA6: =Z6-Z5 -> 0 | AB6: =SUM(Y6*$AB$2) -> 0 | AC6: =AC5 -> 1824 | AD6: =AC6-AC5 -> 0 | AE6: =AE5 -> 358865.2 | AF6: =AE6-AE5 -> 0 | AG6: =IF(AD6>0,AF6/AD6,0) -> 0 | AH6: =AF6+AA6 -> 0 | AI6: =SUM(AH6+V6) -> 249 | AJ6: =-tanks!AW7 -> 249 | AK6: =SUM(AJ6-AI6) -> 0 | AL6: =S6+L6+G6 -> 3 | AM6: =Y6+AD6 -> 0 | AN6: 79 | AO6: =(AN6/100)*3000 -> 2370 | AP6: 79 | AQ6: =(AP6/100)*3000 -> 2370 | AR6: 62 | AS6: =(AR6/100)*3000 -> 1860 | AT6: =SUM(AO6+AQ6+AS6) -> 6600 | AU6: =AT5-AT6+AV6 -> 0 | AX6: =IF(AV6>0,AW6,AX5) -> 0.7
A7: =ELEC!C5 -> 43954 | B7: 237 | C7: 243 | D7: =C6-C7 -> 3 | E7: =D7*8.38 -> 25.14 | F7: 1541 | G7: =F7-F6 -> 2 | H7: 349488 | I7: =SUM(H7-H6) -> 131 | J7: =IF(G7>0,I7/G7,0) -> 65.5 | K7: 1923 | L7: =K7-K6 -> 2 | M7: 140824 | N7: =M7-M6 -> 157 | O7: 1 | P7: 1768 | Q7: 150275 | R7: =Q7-Q6 -> 0 | S7: =SUM(P7-P6) -> 0 | T7: =SUM(S7*$T$2) -> 0 | U7: =SUM(G7+L7+S7) -> 4 | V7: =R7+N7+I7:I7 -> 288 | W7: =SUM(V7/U7) -> 72 | X7: =X6 -> 2417 | Y7: =X7-X6 -> 0 | Z7: 135845.1 | AA7: =Z7-Z6 -> 0 | AB7: =SUM(Y7*$AB$2) -> 0 | AC7: 1824 | AD7: =AC7-AC6 -> 0 | AE7: 358865.7 | AF7: =AE7-AE6 -> 0.5 | AG7: =IF(AD7>0,AF7/AD7,0) -> 0 | AH7: =AF7+AA7 -> 0.5 | AI7: =SUM(AH7+V7) -> 288.5 | AJ7: =-tanks!AW8 -> 288.5 | AK7: =SUM(AJ7-AI7) -> 0 | AL7: =S7+L7+G7 -> 4 | AM7: =Y7+AD7 -> 0 | AN7: 77 | AO7: =(AN7/100)*3000 -> 2310 | AP7: 78 | AQ7: =(AP7/100)*3000 -> 2340 | AR7: 60 | AS7: =(AR7/100)*3000 -> 1800 | AT7: =SUM(AO7+AQ7+AS7) -> 6450 | AU7: =AT6-AT7+AV7 -> 150 | AX7: =IF(AV7>0,AW7,AX6) -> 0.7
A8: =ELEC!C6 -> 43955 | B8: 232 | C8: 239 | D8: =C7-C8 -> 4 | E8: =D8*8.38 -> 33.52 | F8: 1541 | G8: =F8-F7 -> 0 | H8: 349488 | I8: =SUM(H8-H7) -> 0 | J8: =IF(G8>0,I8/G8,0) -> 0 | K8: 1925 | L8: =K8-K7 -> 2 | M8: 140981 | N8: =M8-M7 -> 157 | O8: 1479 | P8: 1770 | Q8: 150466 | R8: =Q8-Q7 -> 191 | S8: =SUM(P8-P7) -> 2 | T8: =SUM(S8*$T$2) -> 0 | U8: =SUM(G8+L8+S8) -> 4 | V8: =R8+N8+I8:I8 -> 348 | W8: =SUM(V8/U8) -> 87 | X8: =X7 -> 2417 | Y8: =X8-X7 -> 0 | Z8: 135871 | AA8: =Z8-Z7 -> 25.9 | AB8: =SUM(Y8*$AB$2) -> 0 | AC8: 1829 | AD8: =AC8-AC7 -> 5 | AE8: 359149.7 | AF8: =AE8-AE7 -> 284 | AG8: =IF(AD8>0,AF8/AD8,0) -> 56.8 | AH8: =AF8+AA8 -> 309.9 | AI8: =SUM(AH8+V8) -> 657.9 | AJ8: =-tanks!AW9 -> 657.9 | AK8: =SUM(AJ8-AI8) -> 0 | AL8: =S8+L8+G8 -> 4 | AM8: =Y8+AD8 -> 5 | AN8: 72 | AO8: =(AN8/100)*3000 -> 2160 | AP8: 75 | AQ8: =(AP8/100)*3000 -> 2250 | AR8: 60 | AS8: =(AR8/100)*3000 -> 1800 | AT8: =SUM(AO8+AQ8+AS8) -> 6210 | AU8: =AT7-AT8+AV8 -> 240 | AX8: =IF(AV8>0,AW8,AX7) -> 0.7
A9: =ELEC!C7 -> 43956 | B9: =B8 -> 232 | C9: =C8 -> 239 | D9: =C8-C9 -> 0 | E9: =D9*8.38 -> 0 | F9: =F8 -> 1541 | G9: =F9-F8 -> 0 | H9: =H8 -> 349488 | I9: =SUM(H9-H8) -> 0 | J9: =IF(G9>0,I9/G9,0) -> 0 | K9: =K8 -> 1925 | L9: =K9-K8 -> 0 | M9: =M8 -> 140981 | N9: =M9-M8 -> 0 | O9: =SUM(L9*$J$1) -> 0 | P9: =P8 -> 1770 | Q9: =Q8 -> 150466 | R9: =Q9-Q8 -> 0 | S9: =SUM(P9-P8) -> 0 | T9: =SUM(S9*$T$2) -> 0 | U9: =SUM(G9+L9+S9) -> 0 | V9: =R9+N9+I9:I9 -> 0 | W9: =SUM(V9/U9) -> #DIV/0! | X9: =X8 -> 2417 | Y9: =X9-X8 -> 0 | Z9: =Z8 -> 135871 | AA9: =Z9-Z8 -> 0 | AB9: =SUM(Y9*$AB$2) -> 0 | AC9: =AC8 -> 1829 | AD9: =AC9-AC8 -> 0 | AE9: =AE8 -> 359149.7 | AF9: =AE9-AE8 -> 0 | AG9: =IF(AD9>0,AF9/AD9,0) -> 0 | AH9: =AF9+AA9 -> 0 | AI9: =SUM(AH9+V9) -> 0 | AJ9: =-tanks!AW10 -> 0 | AK9: =SUM(AJ9-AI9) -> 0 | AL9: =S9+L9+G9 -> 0 | AM9: =Y9+AD9 -> 0 | AN9: =AN8 -> 72 | AO9: =(AN9/100)*3000 -> 2160 | AP9: =AP8 -> 75 | AQ9: =(AP9/100)*3000 -> 2250 | AR9: =AR8 -> 60 | AS9: =(AR9/100)*3000 -> 1800 | AT9: =SUM(AO9+AQ9+AS9) -> 6210 | AU9: =AT8-AT9+AV9 -> 0 | AX9: =IF(AV9>0,AW9,AX8) -> 0.7
A10: =ELEC!C8 -> 43957 | B10: =B9 -> 232 | C10: =C9 -> 239 | D10: =C9-C10 -> 0 | E10: =D10*8.38 -> 0 | F10: =F9 -> 1541 | G10: =F10-F9 -> 0 | H10: =H9 -> 349488 | I10: =SUM(H10-H9) -> 0 | J10: =IF(G10>0,I10/G10,0) -> 0 | K10: =K9 -> 1925 | L10: =K10-K9 -> 0 | M10: =M9 -> 140981 | N10: =M10-M9 -> 0 | O10: =SUM(L10*$J$1) -> 0 | P10: =P9 -> 1770 | Q10: =Q9 -> 150466 | R10: =Q10-Q9 -> 0 | S10: =SUM(P10-P9) -> 0 | T10: =SUM(S10*$T$2) -> 0 | U10: =SUM(G10+L10+S10) -> 0 | V10: =R10+N10+I10:I10 -> 0 | W10: =SUM(V10/U10) -> #DIV/0! | X10: =X9 -> 2417 | Y10: =X10-X9 -> 0 | Z10: =Z9 -> 135871 | AA10: =Z10-Z9 -> 0 | AB10: =SUM(Y10*$AB$2) -> 0 | AC10: =AC9 -> 1829 | AD10: =AC10-AC9 -> 0 | AE10: =AE9 -> 359149.7 | AF10: =AE10-AE9 -> 0 | AG10: =IF(AD10>0,AF10/AD10,0) -> 0 | AH10: =AF10+AA10 -> 0 | AI10: =SUM(AH10+V10) -> 0 | AJ10: =-tanks!AW11 -> 0 | AK10: =SUM(AJ10-AI10) -> 0 | AL10: =S10+L10+G10 -> 0 | AM10: =Y10+AD10 -> 0 | AN10: =AN9 -> 72 | AO10: =(AN10/100)*3000 -> 2160 | AP10: =AP9 -> 75 | AQ10: =(AP10/100)*3000 -> 2250 | AR10: =AR9 -> 60 | AS10: =(AR10/100)*3000 -> 1800 | AT10: =SUM(AO10+AQ10+AS10) -> 6210 | AU10: =AT9-AT10+AV10 -> 0 | AX10: =IF(AV10>0,AW10,AX9) -> 0.7
A11: =ELEC!C9 -> 43958 | B11: =B10 -> 232 | C11: =C10 -> 239 | D11: =C10-C11 -> 0 | E11: =D11*8.38 -> 0 | F11: =F10 -> 1541 | G11: =F11-F10 -> 0 | H11: =H10 -> 349488 | I11: =SUM(H11-H10) -> 0 | J11: =IF(G11>0,I11/G11,0) -> 0 | K11: =K10 -> 1925 | L11: =K11-K10 -> 0 | M11: =M10 -> 140981 | N11: =M11-M10 -> 0 | O11: =SUM(L11*$J$1) -> 0 | P11: =P10 -> 1770 | Q11: =Q10 -> 150466 | R11: =Q11-Q10 -> 0 | S11: =SUM(P11-P10) -> 0 | T11: =SUM(S11*$T$2) -> 0 | U11: =SUM(G11+L11+S11) -> 0 | V11: =R11+N11+I11:I11 -> 0 | W11: =SUM(V11/U11) -> #DIV/0! | X11: =X10 -> 2417 | Y11: =X11-X10 -> 0 | Z11: =Z10 -> 135871 | AA11: =Z11-Z10 -> 0 | AB11: =SUM(Y11*$AB$2) -> 0 | AC11: =AC10 -> 1829 | AD11: =AC11-AC10 -> 0 | AE11: =AE10 -> 359149.7 | AF11: =AE11-AE10 -> 0 | AG11: =IF(AD11>0,AF11/AD11,0) -> 0 | AH11: =AF11+AA11 -> 0 | AI11: =SUM(AH11+V11) -> 0 | AJ11: =-tanks!AW12 -> 0 | AK11: =SUM(AJ11-AI11) -> 0 | AL11: =S11+L11+G11 -> 0 | AM11: =Y11+AD11 -> 0 | AN11: =AN10 -> 72 | AO11: =(AN11/100)*3000 -> 2160 | AP11: =AP10 -> 75 | AQ11: =(AP11/100)*3000 -> 2250 | AR11: =AR10 -> 60 | AS11: =(AR11/100)*3000 -> 1800 | AT11: =SUM(AO11+AQ11+AS11) -> 6210 | AU11: =AT10-AT11+AV11 -> 0 | AX11: =IF(AV11>0,AW11,AX10) -> 0.7
A12: =ELEC!C10 -> 43959 | B12: =B11 -> 232 | C12: =C11 -> 239 | D12: =C11-C12 -> 0 | E12: =D12*8.38 -> 0 | F12: =F11 -> 1541 | G12: =F12-F11 -> 0 | H12: =H11 -> 349488 | I12: =SUM(H12-H11) -> 0 | J12: =IF(G12>0,I12/G12,0) -> 0 | K12: =K11 -> 1925 | L12: =K12-K11 -> 0 | M12: =M11 -> 140981 | N12: =M12-M11 -> 0 | O12: =SUM(L12*$J$1) -> 0 | P12: =P11 -> 1770 | Q12: =Q11 -> 150466 | R12: =Q12-Q11 -> 0 | S12: =SUM(P12-P11) -> 0 | T12: =SUM(S12*$T$2) -> 0 | U12: =SUM(G12+L12+S12) -> 0 | V12: =R12+N12+I12:I12 -> 0 | W12: =SUM(V12/U12) -> #DIV/0! | X12: =X11 -> 2417 | Y12: =X12-X11 -> 0 | Z12: =Z11 -> 135871 | AA12: =Z12-Z11 -> 0 | AB12: =SUM(Y12*$AB$2) -> 0 | AC12: =AC11 -> 1829 | AD12: =AC12-AC11 -> 0 | AE12: =AE11 -> 359149.7 | AF12: =AE12-AE11 -> 0 | AG12: =IF(AD12>0,AF12/AD12,0) -> 0 | AH12: =AF12+AA12 -> 0 | AI12: =SUM(AH12+V12) -> 0 | AJ12: =-tanks!AW13 -> 0 | AK12: =SUM(AJ12-AI12) -> 0 | AL12: =S12+L12+G12 -> 0 | AM12: =Y12+AD12 -> 0 | AN12: =AN11 -> 72 | AO12: =(AN12/100)*3000 -> 2160 | AP12: =AP11 -> 75 | AQ12: =(AP12/100)*3000 -> 2250 | AR12: =AR11 -> 60 | AS12: =(AR12/100)*3000 -> 1800 | AT12: =SUM(AO12+AQ12+AS12) -> 6210 | AU12: =AT11-AT12+AV12 -> 0 | AX12: =IF(AV12>0,AW12,AX11) -> 0.7
A13: =ELEC!C11 -> 43960 | B13: =B12 -> 232 | C13: =C12 -> 239 | D13: =C12-C13 -> 0 | E13: =D13*8.38 -> 0 | F13: =F12 -> 1541 | G13: =F13-F12 -> 0 | H13: =H12 -> 349488 | I13: =SUM(H13-H12) -> 0 | J13: =IF(G13>0,I13/G13,0) -> 0 | K13: =K12 -> 1925 | L13: =K13-K12 -> 0 | M13: =M12 -> 140981 | N13: =M13-M12 -> 0 | O13: =SUM(L13*$J$1) -> 0 | P13: =P12 -> 1770 | Q13: =Q12 -> 150466 | R13: =Q13-Q12 -> 0 | S13: =SUM(P13-P12) -> 0 | T13: =SUM(S13*$T$2) -> 0 | U13: =SUM(G13+L13+S13) -> 0 | V13: =R13+N13+I13:I13 -> 0 | W13: =SUM(V13/U13) -> #DIV/0! | X13: =X12 -> 2417 | Y13: =X13-X12 -> 0 | Z13: =Z12 -> 135871 | AA13: =Z13-Z12 -> 0 | AB13: =SUM(Y13*$AB$2) -> 0 | AC13: =AC12 -> 1829 | AD13: =AC13-AC12 -> 0 | AE13: =AE12 -> 359149.7 | AF13: =AE13-AE12 -> 0 | AG13: =IF(AD13>0,AF13/AD13,0) -> 0 | AH13: =AF13+AA13 -> 0 | AI13: =SUM(AH13+V13) -> 0 | AJ13: =-tanks!AW14 -> 0 | AK13: =SUM(AJ13-AI13) -> 0 | AL13: =S13+L13+G13 -> 0 | AM13: =Y13+AD13 -> 0 | AN13: =AN12 -> 72 | AO13: =(AN13/100)*3000 -> 2160 | AP13: =AP12 -> 75 | AQ13: =(AP13/100)*3000 -> 2250 | AR13: =AR12 -> 60 | AS13: =(AR13/100)*3000 -> 1800 | AT13: =SUM(AO13+AQ13+AS13) -> 6210 | AU13: =AT12-AT13+AV13 -> 0 | AX13: =IF(AV13>0,AW13,AX12) -> 0.7
A14: =ELEC!C12 -> 43961 | B14: =B13 -> 232 | C14: =C13 -> 239 | D14: =C13-C14 -> 0 | E14: =D14*8.38 -> 0 | F14: =F13 -> 1541 | G14: =F14-F13 -> 0 | H14: =H13 -> 349488 | I14: =SUM(H14-H13) -> 0 | J14: =IF(G14>0,I14/G14,0) -> 0 | K14: =K13 -> 1925 | L14: =K14-K13 -> 0 | M14: =M13 -> 140981 | N14: =M14-M13 -> 0 | O14: =SUM(L14*$J$1) -> 0 | P14: =P13 -> 1770 | Q14: =Q13 -> 150466 | R14: =Q14-Q13 -> 0 | S14: =SUM(P14-P13) -> 0 | T14: =SUM(S14*$T$2) -> 0 | U14: =SUM(G14+L14+S14) -> 0 | V14: =R14+N14+I14:I14 -> 0 | W14: =SUM(V14/U14) -> #DIV/0! | X14: =X13 -> 2417 | Y14: =X14-X13 -> 0 | Z14: =Z13 -> 135871 | AA14: =Z14-Z13 -> 0 | AB14: =SUM(Y14*$AB$2) -> 0 | AC14: =AC13 -> 1829 | AD14: =AC14-AC13 -> 0 | AE14: =AE13 -> 359149.7 | AF14: =AE14-AE13 -> 0 | AG14: =IF(AD14>0,AF14/AD14,0) -> 0 | AH14: =AF14+AA14 -> 0 | AI14: =SUM(AH14+V14) -> 0 | AJ14: =-tanks!AW15 -> 0 | AK14: =SUM(AJ14-AI14) -> 0 | AL14: =S14+L14+G14 -> 0 | AM14: =Y14+AD14 -> 0 | AN14: =AN13 -> 72 | AO14: =(AN14/100)*3000 -> 2160 | AP14: =AP13 -> 75 | AQ14: =(AP14/100)*3000 -> 2250 | AR14: =AR13 -> 60 | AS14: =(AR14/100)*3000 -> 1800 | AT14: =SUM(AO14+AQ14+AS14) -> 6210 | AU14: =AT13-AT14+AV14 -> 0 | AX14: =IF(AV14>0,AW14,AX13) -> 0.7
A15: =ELEC!C13 -> 43962 | B15: =B14 -> 232 | C15: =C14 -> 239 | D15: =C14-C15 -> 0 | E15: =D15*8.38 -> 0 | F15: =F14 -> 1541 | G15: =F15-F14 -> 0 | H15: =H14 -> 349488 | I15: =SUM(H15-H14) -> 0 | J15: =IF(G15>0,I15/G15,0) -> 0 | K15: =K14 -> 1925 | L15: =K15-K14 -> 0 | M15: =M14 -> 140981 | N15: =M15-M14 -> 0 | O15: =SUM(L15*$J$1) -> 0 | P15: =P14 -> 1770 | Q15: =Q14 -> 150466 | R15: =Q15-Q14 -> 0 | S15: =SUM(P15-P14) -> 0 | T15: =SUM(S15*$T$2) -> 0 | U15: =SUM(G15+L15+S15) -> 0 | V15: =R15+N15+I15:I15 -> 0 | W15: =SUM(V15/U15) -> #DIV/0! | X15: =X14 -> 2417 | Y15: =X15-X14 -> 0 | Z15: =Z14 -> 135871 | AA15: =Z15-Z14 -> 0 | AB15: =SUM(Y15*$AB$2) -> 0 | AC15: =AC14 -> 1829 | AD15: =AC15-AC14 -> 0 | AE15: =AE14 -> 359149.7 | AF15: =AE15-AE14 -> 0 | AG15: =IF(AD15>0,AF15/AD15,0) -> 0 | AH15: =AF15+AA15 -> 0 | AI15: =SUM(AH15+V15) -> 0 | AJ15: =-tanks!AW16 -> 0 | AK15: =SUM(AJ15-AI15) -> 0 | AL15: =S15+L15+G15 -> 0 | AM15: =Y15+AD15 -> 0 | AN15: =AN14 -> 72 | AO15: =(AN15/100)*3000 -> 2160 | AP15: =AP14 -> 75 | AQ15: =(AP15/100)*3000 -> 2250 | AR15: =AR14 -> 60 | AS15: =(AR15/100)*3000 -> 1800 | AT15: =SUM(AO15+AQ15+AS15) -> 6210 | AU15: =AT14-AT15+AV15 -> 0 | AX15: =IF(AV15>0,AW15,AX14) -> 0.7
A16: =ELEC!C14 -> 43963 | B16: =B15 -> 232 | C16: =C15 -> 239 | D16: =C15-C16 -> 0 | E16: =D16*8.38 -> 0 | F16: =F15 -> 1541 | G16: =F16-F15 -> 0 | H16: =H15 -> 349488 | I16: =SUM(H16-H15) -> 0 | J16: =IF(G16>0,I16/G16,0) -> 0 | K16: =K15 -> 1925 | L16: =K16-K15 -> 0 | M16: =M15 -> 140981 | N16: =M16-M15 -> 0 | O16: =SUM(L16*$J$1) -> 0 | P16: =P15 -> 1770 | Q16: =Q15 -> 150466 | R16: =Q16-Q15 -> 0 | S16: =SUM(P16-P15) -> 0 | T16: =SUM(S16*$T$2) -> 0 | U16: =SUM(G16+L16+S16) -> 0 | V16: =R16+N16+I16:I16 -> 0 | W16: =SUM(V16/U16) -> #DIV/0! | X16: =X15 -> 2417 | Y16: =X16-X15 -> 0 | Z16: =Z15 -> 135871 | AA16: =Z16-Z15 -> 0 | AB16: =SUM(Y16*$AB$2) -> 0 | AC16: =AC15 -> 1829 | AD16: =AC16-AC15 -> 0 | AE16: =AE15 -> 359149.7 | AF16: =AE16-AE15 -> 0 | AG16: =IF(AD16>0,AF16/AD16,0) -> 0 | AH16: =AF16+AA16 -> 0 | AI16: =SUM(AH16+V16) -> 0 | AJ16: =-tanks!AW17 -> 0 | AK16: =SUM(AJ16-AI16) -> 0 | AL16: =S16+L16+G16 -> 0 | AM16: =Y16+AD16 -> 0 | AN16: =AN15 -> 72 | AO16: =(AN16/100)*3000 -> 2160 | AP16: =AP15 -> 75 | AQ16: =(AP16/100)*3000 -> 2250 | AR16: =AR15 -> 60 | AS16: =(AR16/100)*3000 -> 1800 | AT16: =SUM(AO16+AQ16+AS16) -> 6210 | AU16: =AT15-AT16+AV16 -> 0 | AX16: =IF(AV16>0,AW16,AX15) -> 0.7
A17: =ELEC!C15 -> 43964 | B17: =B16 -> 232 | C17: =C16 -> 239 | D17: =C16-C17 -> 0 | E17: =D17*8.38 -> 0 | F17: =F16 -> 1541 | G17: =F17-F16 -> 0 | H17: =H16 -> 349488 | I17: =SUM(H17-H16) -> 0 | J17: =IF(G17>0,I17/G17,0) -> 0 | K17: =K16 -> 1925 | L17: =K17-K16 -> 0 | M17: =M16 -> 140981 | N17: =M17-M16 -> 0 | O17: =SUM(L17*$J$1) -> 0 | P17: =P16 -> 1770 | Q17: =Q16 -> 150466 | R17: =Q17-Q16 -> 0 | S17: =SUM(P17-P16) -> 0 | T17: =SUM(S17*$T$2) -> 0 | U17: =SUM(G17+L17+S17) -> 0 | V17: =R17+N17+I17:I17 -> 0 | X17: =X16 -> 2417 | Y17: =X17-X16 -> 0 | Z17: =Z16 -> 135871 | AA17: =Z17-Z16 -> 0 | AB17: =SUM(Y17*$AB$2) -> 0 | AC17: =AC16 -> 1829 | AD17: =AC17-AC16 -> 0 | AE17: =AE16 -> 359149.7 | AF17: =AE17-AE16 -> 0 | AG17: =IF(AD17>0,AF17/AD17,0) -> 0 | AH17: =AF17+AA17 -> 0 | AI17: =SUM(AH17+V17) -> 0 | AJ17: =-tanks!AW18 -> 0 | AK17: =SUM(AJ17-AI17) -> 0 | AL17: =S17+L17+G17 -> 0 | AM17: =Y17+AD17 -> 0 | AN17: =AN16 -> 72 | AO17: =(AN17/100)*3000 -> 2160 | AP17: =AP16 -> 75 | AQ17: =(AP17/100)*3000 -> 2250 | AR17: =AR16 -> 60 | AS17: =(AR17/100)*3000 -> 1800 | AT17: =SUM(AO17+AQ17+AS17) -> 6210 | AU17: =AT16-AT17+AV17 -> 0 | AX17: =IF(AV17>0,AW17,AX16) -> 0.7
A18: =ELEC!C16 -> 43965 | B18: =B17 -> 232 | C18: =C17 -> 239 | D18: =C17-C18 -> 0 | E18: =D18*8.38 -> 0 | F18: =F17 -> 1541 | G18: =F18-F17 -> 0 | H18: =H17 -> 349488 | I18: =SUM(H18-H17) -> 0 | J18: =IF(G18>0,I18/G18,0) -> 0 | K18: =K17 -> 1925 | L18: =K18-K17 -> 0 | M18: =M17 -> 140981 | N18: =M18-M17 -> 0 | O18: =SUM(L18*$J$1) -> 0 | P18: =P17 -> 1770 | Q18: =Q17 -> 150466 | R18: =Q18-Q17 -> 0 | S18: =SUM(P18-P17) -> 0 | T18: =SUM(S18*$T$2) -> 0 | U18: =SUM(G18+L18+S18) -> 0 | V18: =R18+N18+I18:I18 -> 0 | X18: =X17 -> 2417 | Y18: =X18-X17 -> 0 | Z18: =Z17 -> 135871 | AA18: =Z18-Z17 -> 0 | AB18: =SUM(Y18*$AB$2) -> 0 | AC18: =AC17 -> 1829 | AD18: =AC18-AC17 -> 0 | AE18: =AE17 -> 359149.7 | AF18: =AE18-AE17 -> 0 | AG18: =IF(AD18>0,AF18/AD18,0) -> 0 | AH18: =AF18+AA18 -> 0 | AI18: =SUM(AH18+V18) -> 0 | AJ18: =-tanks!AW19 -> 0 | AK18: =SUM(AJ18-AI18) -> 0 | AL18: =S18+L18+G18 -> 0 | AM18: =Y18+AD18 -> 0 | AN18: =AN17 -> 72 | AO18: =(AN18/100)*3000 -> 2160 | AP18: =AP17 -> 75 | AQ18: =(AP18/100)*3000 -> 2250 | AR18: =AR17 -> 60 | AS18: =(AR18/100)*3000 -> 1800 | AT18: =SUM(AO18+AQ18+AS18) -> 6210 | AU18: =AT17-AT18+AV18 -> 0 | AX18: =IF(AV18>0,AW18,AX17) -> 0.7
A19: =ELEC!C17 -> 43966 | B19: =B18 -> 232 | C19: =C18 -> 239 | D19: =C18-C19 -> 0 | E19: =D19*8.38 -> 0 | F19: =F18 -> 1541 | G19: =F19-F18 -> 0 | H19: =H18 -> 349488 | I19: =SUM(H19-H18) -> 0 | J19: =IF(G19>0,I19/G19,0) -> 0 | K19: =K18 -> 1925 | L19: =K19-K18 -> 0 | M19: =M18 -> 140981 | N19: =M19-M18 -> 0 | O19: =SUM(L19*$J$1) -> 0 | P19: =P18 -> 1770 | Q19: =Q18 -> 150466 | R19: =Q19-Q18 -> 0 | S19: =SUM(P19-P18) -> 0 | T19: =SUM(S19*$T$2) -> 0 | U19: =SUM(G19+L19+S19) -> 0 | V19: =R19+N19+I19:I19 -> 0 | X19: =X18 -> 2417 | Y19: =X19-X18 -> 0 | Z19: =Z18 -> 135871 | AA19: =Z19-Z18 -> 0 | AB19: =SUM(Y19*$AB$2) -> 0 | AC19: =AC18 -> 1829 | AD19: =AC19-AC18 -> 0 | AE19: =AE18 -> 359149.7 | AF19: =AE19-AE18 -> 0 | AG19: =IF(AD19>0,AF19/AD19,0) -> 0 | AH19: =AF19+AA19 -> 0 | AI19: =SUM(AH19+V19) -> 0 | AJ19: =-tanks!AW20 -> 0 | AK19: =SUM(AJ19-AI19) -> 0 | AL19: =S19+L20+G19 -> 0 | AM19: =Y19+AD19 -> 0 | AN19: =AN18 -> 72 | AO19: =(AN19/100)*3000 -> 2160 | AP19: =AP18 -> 75 | AQ19: =(AP19/100)*3000 -> 2250 | AR19: =AR18 -> 60 | AS19: =(AR19/100)*3000 -> 1800 | AT19: =SUM(AO19+AQ19+AS19) -> 6210 | AU19: =AT18-AT19+AV19 -> 0 | AX19: =IF(AV19>0,AW19,AX18) -> 0.7
A20: =ELEC!C18 -> 43967 | B20: =B19 -> 232 | C20: =C19 -> 239 | D20: =C19-C20 -> 0 | E20: =D20*8.38 -> 0 | F20: =F19 -> 1541 | G20: =F20-F19 -> 0 | H20: =H19 -> 349488 | I20: =SUM(H20-H19) -> 0 | J20: =IF(G20>0,I20/G20,0) -> 0 | K20: =K19 -> 1925 | L20: =K20-K19 -> 0 | M20: =M19 -> 140981 | N20: =M20-M19 -> 0 | O20: =SUM(L20*$J$1) -> 0 | P20: =P19 -> 1770 | Q20: =Q19 -> 150466 | R20: =Q20-Q19 -> 0 | S20: =SUM(P20-P19) -> 0 | T20: =SUM(S20*$T$2) -> 0 | U20: =SUM(G20+L20+S20) -> 0 | V20: =R20+N20+I20:I20 -> 0 | X20: =X19 -> 2417 | Y20: =X20-X19 -> 0 | Z20: =Z19 -> 135871 | AA20: =Z20-Z19 -> 0 | AB20: =SUM(Y20*$AB$2) -> 0 | AC20: =AC19 -> 1829 | AD20: =AC20-AC19 -> 0 | AE20: =AE19 -> 359149.7 | AF20: =AE20-AE19 -> 0 | AG20: =IF(AD20>0,AF20/AD20,0) -> 0 | AH20: =AF20+AA20 -> 0 | AI20: =SUM(AH20+V20) -> 0 | AJ20: =-tanks!AW21 -> 0 | AK20: =SUM(AJ20-AI20) -> 0 | AL20: =S20+L21+G20 -> 0 | AM20: =Y20+AD20 -> 0 | AN20: =AN19 -> 72 | AO20: =(AN20/100)*3000 -> 2160 | AP20: =AP19 -> 75 | AQ20: =(AP20/100)*3000 -> 2250 | AR20: =AR19 -> 60 | AS20: =(AR20/100)*3000 -> 1800 | AT20: =SUM(AO20+AQ20+AS20) -> 6210 | AU20: =AT19-AT20+AV20 -> 0 | AX20: =IF(AV20>0,AW20,AX19) -> 0.7
A21: =ELEC!C19 -> 43968 | B21: =B20 -> 232 | C21: =C20 -> 239 | D21: =C20-C21 -> 0 | E21: =D21*8.38 -> 0 | F21: =F20 -> 1541 | G21: =F21-F20 -> 0 | H21: =H20 -> 349488 | I21: =SUM(H21-H20) -> 0 | J21: =IF(G21>0,I21/G21,0) -> 0 | K21: =K20 -> 1925 | L21: =K21-K20 -> 0 | M21: =M20 -> 140981 | N21: =M21-M20 -> 0 | O21: =SUM(L21*$J$1) -> 0 | P21: =P20 -> 1770 | Q21: =Q20 -> 150466 | R21: =Q21-Q20 -> 0 | S21: =SUM(P21-P20) -> 0 | T21: =SUM(S21*$T$2) -> 0 | U21: =SUM(G21+L21+S21) -> 0 | V21: =R21+N21+I21:I21 -> 0 | X21: =X20 -> 2417 | Y21: =X21-X20 -> 0 | Z21: =Z20 -> 135871 | AA21: =Z21-Z20 -> 0 | AB21: =SUM(Y21*$AB$2) -> 0 | AC21: =AC20 -> 1829 | AD21: =AC21-AC20 -> 0 | AE21: =AE20 -> 359149.7 | AF21: =AE21-AE20 -> 0 | AG21: =IF(AD21>0,AF21/AD21,0) -> 0 | AH21: =AF21+AA21 -> 0 | AI21: =SUM(AH21+V21) -> 0 | AJ21: =-tanks!AW22 -> 0 | AK21: =SUM(AJ21-AI21) -> 0 | AL21: =S21+L21+G21 -> 0 | AM21: =Y21+AD21 -> 0 | AN21: =AN20 -> 72 | AO21: =(AN21/100)*3000 -> 2160 | AP21: =AP20 -> 75 | AQ21: =(AP21/100)*3000 -> 2250 | AR21: =AR20 -> 60 | AS21: =(AR21/100)*3000 -> 1800 | AT21: =SUM(AO21+AQ21+AS21) -> 6210 | AU21: =AT20-AT21+AV21 -> 0 | AX21: =IF(AV21>0,AW21,AX20) -> 0.7
A22: =ELEC!C20 -> 43969 | B22: =B21 -> 232 | C22: =C21 -> 239 | D22: =C21-C22 -> 0 | E22: =D22*8.38 -> 0 | F22: =F21 -> 1541 | G22: =F22-F21 -> 0 | H22: =H21 -> 349488 | I22: =SUM(H22-H21) -> 0 | J22: =IF(G22>0,I22/G22,0) -> 0 | K22: =K21 -> 1925 | L22: =K22-K21 -> 0 | M22: =M21 -> 140981 | N22: =M22-M21 -> 0 | O22: =SUM(L22*$J$1) -> 0 | P22: =P21 -> 1770 | Q22: =Q21 -> 150466 | R22: =Q22-Q21 -> 0 | S22: =SUM(P22-P21) -> 0 | T22: =SUM(S22*$T$2) -> 0 | U22: =SUM(G22+L22+S22) -> 0 | V22: =R22+N22+I22:I22 -> 0 | X22: =X21 -> 2417 | Y22: =X22-X21 -> 0 | Z22: =Z21 -> 135871 | AA22: =Z22-Z21 -> 0 | AB22: =SUM(Y22*$AB$2) -> 0 | AC22: =AC21 -> 1829 | AD22: =AC22-AC21 -> 0 | AE22: =AE21 -> 359149.7 | AF22: =AE22-AE21 -> 0 | AG22: =IF(AD22>0,AF22/AD22,0) -> 0 | AH22: =AF22+AA22 -> 0 | AI22: =SUM(AH22+V22) -> 0 | AJ22: =-tanks!AW23 -> 0 | AK22: =SUM(AJ22-AI22) -> 0 | AL22: =S22+L22+G22 -> 0 | AM22: =Y22+AD22 -> 0 | AN22: =AN21 -> 72 | AO22: =(AN22/100)*3000 -> 2160 | AP22: =AP21 -> 75 | AQ22: =(AP22/100)*3000 -> 2250 | AR22: =AR21 -> 60 | AS22: =(AR22/100)*3000 -> 1800 | AT22: =SUM(AO22+AQ22+AS22) -> 6210 | AU22: =AT21-AT22+AV22 -> 0 | AX22: =IF(AV22>0,AW22,AX21) -> 0.7
A23: =ELEC!C21 -> 43970 | B23: =B22 -> 232 | C23: =C22 -> 239 | D23: =C22-C23 -> 0 | E23: =D23*8.38 -> 0 | F23: =F22 -> 1541 | G23: =F23-F22 -> 0 | H23: =H22 -> 349488 | I23: =SUM(H23-H22) -> 0 | J23: =IF(G23>0,I23/G23,0) -> 0 | K23: =K22 -> 1925 | L23: =K23-K22 -> 0 | M23: =M22 -> 140981 | N23: =M23-M22 -> 0 | O23: =SUM(L23*$J$1) -> 0 | P23: =P22 -> 1770 | Q23: =Q22 -> 150466 | R23: =Q23-Q22 -> 0 | S23: =SUM(P23-P22) -> 0 | T23: =SUM(S23*$T$2) -> 0 | U23: =SUM(G23+L23+S23) -> 0 | V23: =R23+N23+I23:I23 -> 0 | X23: =X22 -> 2417 | Y23: =X23-X22 -> 0 | Z23: =Z22 -> 135871 | AA23: =Z23-Z22 -> 0 | AB23: =SUM(Y23*$AB$2) -> 0 | AC23: =AC22 -> 1829 | AD23: =AC23-AC22 -> 0 | AE23: =AE22 -> 359149.7 | AF23: =AE23-AE22 -> 0 | AG23: =IF(AD23>0,AF23/AD23,0) -> 0 | AH23: =AF23+AA23 -> 0 | AI23: =SUM(AH23+V23) -> 0 | AJ23: =-tanks!AW24 -> 0 | AK23: =SUM(AJ23-AI23) -> 0 | AL23: =S23+L23+G23 -> 0 | AM23: =Y23+AD23 -> 0 | AN23: =AN22 -> 72 | AO23: =(AN23/100)*3000 -> 2160 | AP23: =AP22 -> 75 | AQ23: =(AP23/100)*3000 -> 2250 | AR23: =AR22 -> 60 | AS23: =(AR23/100)*3000 -> 1800 | AT23: =SUM(AO23+AQ23+AS23) -> 6210 | AU23: =AT22-AT23+AV23 -> 0 | AX23: =IF(AV23>0,AW23,AX22) -> 0.7
A24: =ELEC!C22 -> 43971 | B24: =B23 -> 232 | C24: =C23 -> 239 | D24: =C23-C24 -> 0 | E24: =D24*8.38 -> 0 | F24: =F23 -> 1541 | G24: =F24-F23 -> 0 | H24: =H23 -> 349488 | I24: =SUM(H24-H23) -> 0 | J24: =IF(G24>0,I24/G24,0) -> 0 | K24: =K23 -> 1925 | L24: =K24-K23 -> 0 | M24: =M23 -> 140981 | N24: =M24-M23 -> 0 | O24: =SUM(L24*$J$1) -> 0 | P24: =P23 -> 1770 | Q24: =Q23 -> 150466 | R24: =Q24-Q23 -> 0 | S24: =SUM(P24-P23) -> 0 | T24: =SUM(S24*$T$2) -> 0 | U24: =SUM(G24+L24+S24) -> 0 | V24: =R24+N24+I24:I24 -> 0 | X24: =X23 -> 2417 | Y24: =X24-X23 -> 0 | Z24: =Z23 -> 135871 | AA24: =Z24-Z23 -> 0 | AB24: =SUM(Y24*$AB$2) -> 0 | AC24: =AC23 -> 1829 | AD24: =AC24-AC23 -> 0 | AE24: =AE23 -> 359149.7 | AF24: =AE24-AE23 -> 0 | AG24: =IF(AD24>0,AF24/AD24,0) -> 0 | AH24: =AF24+AA24 -> 0 | AI24: =SUM(AH24+V24) -> 0 | AJ24: =-tanks!AW25 -> 0 | AK24: =SUM(AJ24-AI24) -> 0 | AL24: =S24+L24+G24 -> 0 | AM24: =Y24+AD24 -> 0 | AN24: =AN23 -> 72 | AO24: =(AN24/100)*3000 -> 2160 | AP24: =AP23 -> 75 | AQ24: =(AP24/100)*3000 -> 2250 | AR24: =AR23 -> 60 | AS24: =(AR24/100)*3000 -> 1800 | AT24: =SUM(AO24+AQ24+AS24) -> 6210 | AU24: =AT23-AT24+AV24 -> 0 | AX24: =IF(AV24>0,AW24,AX23) -> 0.7
A25: =ELEC!C23 -> 43972 | B25: =B24 -> 232 | C25: =C24 -> 239 | D25: =C24-C25 -> 0 | E25: =D25*8.38 -> 0 | F25: =F24 -> 1541 | G25: =F25-F24 -> 0 | H25: =H24 -> 349488 | I25: =SUM(H25-H24) -> 0 | J25: =IF(G25>0,I25/G25,0) -> 0 | K25: =K24 -> 1925 | L25: =K25-K24 -> 0 | M25: =M24 -> 140981 | N25: =M25-M24 -> 0 | O25: =SUM(L25*$J$1) -> 0 | P25: =P24 -> 1770 | Q25: =Q24 -> 150466 | R25: =Q25-Q24 -> 0 | S25: =SUM(P25-P24) -> 0 | T25: =SUM(S25*$T$2) -> 0 | U25: =SUM(G25+L25+S25) -> 0 | V25: =R25+N25+I25:I25 -> 0 | X25: =X24 -> 2417 | Y25: =X25-X24 -> 0 | Z25: =Z24 -> 135871 | AA25: =Z25-Z24 -> 0 | AB25: =SUM(Y25*$AB$2) -> 0 | AC25: =AC24 -> 1829 | AD25: =AC25-AC24 -> 0 | AE25: =AE24 -> 359149.7 | AF25: =AE25-AE24 -> 0 | AG25: =IF(AD25>0,AF25/AD25,0) -> 0 | AH25: =AF25+AA25 -> 0 | AI25: =SUM(AH25+V25) -> 0 | AJ25: =-tanks!AW26 -> 0 | AK25: =SUM(AJ25-AI25) -> 0 | AL25: =S25+L25+G25 -> 0 | AM25: =Y25+AD25 -> 0 | AN25: =AN24 -> 72 | AO25: =(AN25/100)*3000 -> 2160 | AP25: =AP24 -> 75 | AQ25: =(AP25/100)*3000 -> 2250 | AR25: =AR24 -> 60 | AS25: =(AR25/100)*3000 -> 1800 | AT25: =SUM(AO25+AQ25+AS25) -> 6210 | AU25: =AT24-AT25+AV25 -> 0 | AX25: =IF(AV25>0,AW25,AX24) -> 0.7
A26: =ELEC!C24 -> 43973 | B26: =B25 -> 232 | C26: =C25 -> 239 | D26: =C25-C26 -> 0 | E26: =D26*8.38 -> 0 | F26: =F25 -> 1541 | G26: =F26-F25 -> 0 | H26: =H25 -> 349488 | I26: =SUM(H26-H25) -> 0 | J26: =IF(G26>0,I26/G26,0) -> 0 | K26: =K25 -> 1925 | L26: =K26-K25 -> 0 | M26: =M25 -> 140981 | N26: =M26-M25 -> 0 | O26: =SUM(L26*$J$1) -> 0 | P26: =P25 -> 1770 | Q26: =Q25 -> 150466 | R26: =Q26-Q25 -> 0 | S26: =SUM(P26-P25) -> 0 | T26: =SUM(S26*$T$2) -> 0 | U26: =SUM(G26+L26+S26) -> 0 | V26: =R26+N26+I26:I26 -> 0 | X26: =X25 -> 2417 | Y26: =X26-X25 -> 0 | Z26: =Z25 -> 135871 | AA26: =Z26-Z25 -> 0 | AB26: =SUM(Y26*$AB$2) -> 0 | AC26: =AC25 -> 1829 | AD26: =AC26-AC25 -> 0 | AE26: =AE25 -> 359149.7 | AF26: =AE26-AE25 -> 0 | AG26: =IF(AD26>0,AF26/AD26,0) -> 0 | AH26: =AF26+AA26 -> 0 | AI26: =SUM(AH26+V26) -> 0 | AJ26: =-tanks!AW27 -> 0 | AK26: =SUM(AJ26-AI26) -> 0 | AL26: =S26+L26+G26 -> 0 | AM26: =Y26+AD26 -> 0 | AN26: =AN25 -> 72 | AO26: =(AN26/100)*3000 -> 2160 | AP26: =AP25 -> 75 | AQ26: =(AP26/100)*3000 -> 2250 | AR26: =AR25 -> 60 | AS26: =(AR26/100)*3000 -> 1800 | AT26: =SUM(AO26+AQ26+AS26) -> 6210 | AU26: =AT25-AT26+AV26 -> 0 | AX26: =IF(AV26>0,AW26,AX25) -> 0.7
A27: =ELEC!C25 -> 43974 | B27: =B26 -> 232 | C27: =C26 -> 239 | D27: =C26-C27 -> 0 | E27: =D27*8.38 -> 0 | F27: =F26 -> 1541 | G27: =F27-F26 -> 0 | H27: =H26 -> 349488 | I27: =SUM(H27-H26) -> 0 | J27: =IF(G27>0,I27/G27,0) -> 0 | K27: =K26 -> 1925 | L27: =K27-K26 -> 0 | M27: =M26 -> 140981 | N27: =M27-M26 -> 0 | O27: =SUM(L27*$J$1) -> 0 | P27: =P26 -> 1770 | Q27: =Q26 -> 150466 | R27: =Q27-Q26 -> 0 | S27: =SUM(P27-P26) -> 0 | T27: =SUM(S27*$T$2) -> 0 | U27: =SUM(G27+L27+S27) -> 0 | V27: =R27+N27+I27:I27 -> 0 | X27: =X26 -> 2417 | Y27: =X27-X26 -> 0 | Z27: =Z26 -> 135871 | AA27: =Z27-Z26 -> 0 | AB27: =SUM(Y27*$AB$2) -> 0 | AC27: =AC26 -> 1829 | AD27: =AC27-AC26 -> 0 | AE27: =AE26 -> 359149.7 | AF27: =AE27-AE26 -> 0 | AG27: =IF(AD27>0,AF27/AD27,0) -> 0 | AH27: =AF27+AA27 -> 0 | AI27: =SUM(AH27+V27) -> 0 | AJ27: =-tanks!AW28 -> 0 | AK27: =SUM(AJ27-AI27) -> 0 | AL27: =S27+L27+G27 -> 0 | AM27: =Y27+AD27 -> 0 | AN27: =AN26 -> 72 | AO27: =(AN27/100)*3000 -> 2160 | AP27: =AP26 -> 75 | AQ27: =(AP27/100)*3000 -> 2250 | AR27: =AR26 -> 60 | AS27: =(AR27/100)*3000 -> 1800 | AT27: =SUM(AO27+AQ27+AS27) -> 6210 | AU27: =AT26-AT27+AV27 -> 0 | AX27: =IF(AV27>0,AW27,AX26) -> 0.7
A28: =ELEC!C26 -> 43975 | B28: =B27 -> 232 | C28: =C27 -> 239 | D28: =C27-C28 -> 0 | E28: =D28*8.38 -> 0 | F28: =F27 -> 1541 | G28: =F28-F27 -> 0 | H28: =H27 -> 349488 | I28: =SUM(H28-H27) -> 0 | J28: =IF(G28>0,I28/G28,0) -> 0 | K28: =K27 -> 1925 | L28: =K28-K27 -> 0 | M28: =M27 -> 140981 | N28: =M28-M27 -> 0 | O28: =SUM(L28*$J$1) -> 0 | P28: =P27 -> 1770 | Q28: =Q27 -> 150466 | R28: =Q28-Q27 -> 0 | S28: =SUM(P28-P27) -> 0 | T28: =SUM(S28*$T$2) -> 0 | U28: =SUM(G28+L28+S28) -> 0 | V28: =R28+N28+I28:I28 -> 0 | X28: =X27 -> 2417 | Y28: =X28-X27 -> 0 | Z28: =Z27 -> 135871 | AA28: =Z28-Z27 -> 0 | AB28: =SUM(Y28*$AB$2) -> 0 | AC28: =AC27 -> 1829 | AD28: =AC28-AC27 -> 0 | AE28: =AE27 -> 359149.7 | AF28: =AE28-AE27 -> 0 | AG28: =IF(AD28>0,AF28/AD28,0) -> 0 | AH28: =AF28+AA28 -> 0 | AI28: =SUM(AH28+V28) -> 0 | AJ28: =-tanks!AW29 -> 0 | AK28: =SUM(AJ28-AI28) -> 0 | AL28: =S28+L28+G28 -> 0 | AM28: =Y28+AD28 -> 0 | AN28: =AN27 -> 72 | AO28: =(AN28/100)*3000 -> 2160 | AP28: =AP27 -> 75 | AQ28: =(AP28/100)*3000 -> 2250 | AR28: =AR27 -> 60 | AS28: =(AR28/100)*3000 -> 1800 | AT28: =SUM(AO28+AQ28+AS28) -> 6210 | AU28: =AT27-AT28+AV28 -> 0 | AX28: =IF(AV28>0,AW28,AX27) -> 0.7
A29: =ELEC!C27 -> 43976 | B29: =B28 -> 232 | C29: =C28 -> 239 | D29: =C28-C29 -> 0 | E29: =D29*8.38 -> 0 | F29: =F28 -> 1541 | G29: =F29-F28 -> 0 | H29: =H28 -> 349488 | I29: =SUM(H29-H28) -> 0 | J29: =IF(G29>0,I29/G29,0) -> 0 | K29: =K28 -> 1925 | L29: =K29-K28 -> 0 | M29: =M28 -> 140981 | N29: =M29-M28 -> 0 | O29: =SUM(L29*$J$1) -> 0 | P29: =P28 -> 1770 | Q29: =Q28 -> 150466 | R29: =Q29-Q28 -> 0 | S29: =SUM(P29-P28) -> 0 | T29: =SUM(S29*$T$2) -> 0 | U29: =SUM(G29+L29+S29) -> 0 | V29: =R29+N29+I29:I29 -> 0 | X29: =X28 -> 2417 | Y29: =X29-X28 -> 0 | Z29: =Z28 -> 135871 | AA29: =Z29-Z28 -> 0 | AB29: =SUM(Y29*$AB$2) -> 0 | AC29: =AC28 -> 1829 | AD29: =AC29-AC28 -> 0 | AE29: =AE28 -> 359149.7 | AF29: =AE29-AE28 -> 0 | AG29: =IF(AD29>0,AF29/AD29,0) -> 0 | AH29: =AF29+AA29 -> 0 | AI29: =SUM(AH29+V29) -> 0 | AJ29: =-tanks!AW30 -> 0 | AK29: =SUM(AJ29-AI29) -> 0 | AL29: =S29+L29+G29 -> 0 | AM29: =Y29+AD29 -> 0 | AN29: =AN28 -> 72 | AO29: =(AN29/100)*3000 -> 2160 | AP29: =AP28 -> 75 | AQ29: =(AP29/100)*3000 -> 2250 | AR29: =AR28 -> 60 | AS29: =(AR29/100)*3000 -> 1800 | AT29: =SUM(AO29+AQ29+AS29) -> 6210 | AU29: =AT28-AT29+AV29 -> 0 | AX29: =IF(AV29>0,AW29,AX28) -> 0.7
A30: =ELEC!C28 -> 43977 | B30: =B29 -> 232 | C30: =C29 -> 239 | D30: =C29-C30 -> 0 | E30: =D30*8.38 -> 0 | F30: =F29 -> 1541 | G30: =F30-F29 -> 0 | H30: =H29 -> 349488 | I30: =SUM(H30-H29) -> 0 | J30: =IF(G30>0,I30/G30,0) -> 0 | K30: =K29 -> 1925 | L30: =K30-K29 -> 0 | M30: =M29 -> 140981 | N30: =M30-M29 -> 0 | O30: =SUM(L30*$J$1) -> 0 | P30: =P29 -> 1770 | Q30: =Q29 -> 150466 | R30: =Q30-Q29 -> 0 | S30: =SUM(P30-P29) -> 0 | T30: =SUM(S30*$T$2) -> 0 | U30: =SUM(G30+L30+S30) -> 0 | V30: =R30+N30+I30:I30 -> 0 | X30: =X29 -> 2417 | Y30: =X30-X29 -> 0 | Z30: =Z29 -> 135871 | AA30: =Z30-Z29 -> 0 | AB30: =SUM(Y30*$AB$2) -> 0 | AC30: =AC29 -> 1829 | AD30: =AC30-AC29 -> 0 | AE30: =AE29 -> 359149.7 | AF30: =AE30-AE29 -> 0 | AG30: =IF(AD30>0,AF30/AD30,0) -> 0 | AH30: =AF30+AA30 -> 0 | AI30: =SUM(AH30+V30) -> 0 | AJ30: =-tanks!AW31 -> 0 | AK30: =SUM(AJ30-AI30) -> 0 | AL30: =S30+L30+G30 -> 0 | AM30: =Y30+AD30 -> 0 | AN30: =AN29 -> 72 | AO30: =(AN30/100)*3000 -> 2160 | AP30: =AP29 -> 75 | AQ30: =(AP30/100)*3000 -> 2250 | AR30: =AR29 -> 60 | AS30: =(AR30/100)*3000 -> 1800 | AT30: =SUM(AO30+AQ30+AS30) -> 6210 | AU30: =AT29-AT30+AV30 -> 0 | AX30: =IF(AV30>0,AW30,AX29) -> 0.7
A31: =ELEC!C29 -> 43978 | B31: =B30 -> 232 | C31: =C30 -> 239 | D31: =C30-C31 -> 0 | E31: =D31*8.38 -> 0 | F31: =F30 -> 1541 | G31: =F31-F30 -> 0 | H31: =H30 -> 349488 | I31: =SUM(H31-H30) -> 0 | J31: =IF(G31>0,I31/G31,0) -> 0 | K31: =K30 -> 1925 | L31: =K31-K30 -> 0 | M31: =M30 -> 140981 | N31: =M31-M30 -> 0 | O31: =SUM(L31*$J$1) -> 0 | P31: =P30 -> 1770 | Q31: =Q30 -> 150466 | R31: =Q31-Q30 -> 0 | S31: =SUM(P31-P30) -> 0 | T31: =SUM(S31*$T$2) -> 0 | U31: =SUM(G31+L31+S31) -> 0 | V31: =R31+N31+I31:I31 -> 0 | X31: =X30 -> 2417 | Y31: =X31-X30 -> 0 | Z31: =Z30 -> 135871 | AA31: =Z31-Z30 -> 0 | AB31: =SUM(Y31*$AB$2) -> 0 | AC31: =AC30 -> 1829 | AD31: =AC31-AC30 -> 0 | AE31: =AE30 -> 359149.7 | AF31: =AE31-AE30 -> 0 | AG31: =IF(AD31>0,AF31/AD31,0) -> 0 | AH31: =AF31+AA31 -> 0 | AI31: =SUM(AH31+V31) -> 0 | AJ31: =-tanks!AW32 -> 0 | AK31: =SUM(AJ31-AI31) -> 0 | AL31: =S31+L31+G31 -> 0 | AM31: =Y31+AD31 -> 0 | AN31: =AN30 -> 72 | AO31: =(AN31/100)*3000 -> 2160 | AP31: =AP30 -> 75 | AQ31: =(AP31/100)*3000 -> 2250 | AR31: =AR30 -> 60 | AS31: =(AR31/100)*3000 -> 1800 | AT31: =SUM(AO31+AQ31+AS31) -> 6210 | AU31: =AT30-AT31+AV31 -> 0 | AX31: =IF(AV31>0,AW31,AX30) -> 0.7
A32: =ELEC!C30 -> 43979 | B32: =B31 -> 232 | C32: =C31 -> 239 | D32: =C31-C32 -> 0 | E32: =D32*8.38 -> 0 | F32: =F31 -> 1541 | G32: =F32-F31 -> 0 | H32: =H31 -> 349488 | I32: =SUM(H32-H31) -> 0 | J32: =IF(G32>0,I32/G32,0) -> 0 | K32: =K31 -> 1925 | L32: =K32-K31 -> 0 | M32: =M31 -> 140981 | N32: =M32-M31 -> 0 | O32: =SUM(L32*$J$1) -> 0 | P32: =P31 -> 1770 | Q32: =Q31 -> 150466 | R32: =Q32-Q31 -> 0 | S32: =SUM(P32-P31) -> 0 | T32: =SUM(S32*$T$2) -> 0 | U32: =SUM(G32+L32+S32) -> 0 | V32: =R32+N32+I32:I32 -> 0 | X32: =X31 -> 2417 | Y32: =X32-X31 -> 0 | Z32: =Z31 -> 135871 | AA32: =Z32-Z31 -> 0 | AB32: =SUM(Y32*$AB$2) -> 0 | AC32: =AC31 -> 1829 | AD32: =AC32-AC31 -> 0 | AE32: =AE31 -> 359149.7 | AF32: =AE32-AE31 -> 0 | AG32: =IF(AD32>0,AF32/AD32,0) -> 0 | AH32: =AF32+AA32 -> 0 | AI32: =SUM(AH32+V32) -> 0 | AJ32: =-tanks!AW33 -> 0 | AK32: =SUM(AJ32-AI32) -> 0 | AL32: =S32+L32+G32 -> 0 | AM32: =Y32+AD32 -> 0 | AN32: =AN31 -> 72 | AO32: =(AN32/100)*3000 -> 2160 | AP32: =AP31 -> 75 | AQ32: =(AP32/100)*3000 -> 2250 | AR32: =AR31 -> 60 | AS32: =(AR32/100)*3000 -> 1800 | AT32: =SUM(AO32+AQ32+AS32) -> 6210 | AU32: =AT31-AT32+AV32 -> 0 | AX32: =IF(AV32>0,AW32,AX31) -> 0.7
... A35: =ELEC!C33 -> 43982 | B35: =B34 -> 232 | C35: =C34 -> 239 | D35: =C34-C35 -> 0 | E35: =D35*8.38 -> 0 | F35: =F34 -> 1541 | G35: =F35-F34 -> 0 | H35: =H34 -> 349488 | I35: =SUM(H35-H34) -> 0 | J35: =IF(G35>0,I35/G35,0) -> 0 | K35: =K34 -> 1925 | L35: =K35-K34 -> 0 | M35: =M34 -> 140981 | N35: =M35-M34 -> 0 | O35: =SUM(L35*$J$1) -> 0 | P35: =P34 -> 1770 | Q35: =Q34 -> 150466 | R35: =Q35-Q34 -> 0 | S35: =SUM(P35-P34) -> 0 | T35: =SUM(S35*$T$2) -> 0 | U35: =SUM(G35+L35+S35) -> 0 | V35: =R35+N35+I35:I35 -> 0 | X35: =X34 -> 2417 | Y35: =X35-X34 -> 0 | Z35: =Z34 -> 135871 | AA35: =Z35-Z34 -> 0 | AB35: =SUM(Y35*$AB$2) -> 0 | AC35: =AC34 -> 1829 | AD35: =AC35-AC34 -> 0 | AE35: =AE34 -> 359149.7 | AF35: =AE35-AE34 -> 0 | AG35: =IF(AD35>0,AF35/AD35,0) -> 0 | AH35: =AF35+AA35 -> 0 | AI35: =SUM(AH35+V35) -> 0 | AJ35: =-tanks!AW36 -> 0 | AK35: =SUM(AJ35-AI35) -> 0 | AL35: =S35+L35+G35 -> 0 | AM35: =Y35+AD35 -> 0 | AN35: =AN34 -> 72 | AO35: =(AN35/100)*3000 -> 2160 | AP35: =AP34 -> 75 | AQ35: =(AP35/100)*3000 -> 2250 | AR35: =AR34 -> 60 | AS35: =(AR35/100)*3000 -> 1800 | AT35: =SUM(AO35+AQ35+AS35) -> 6210 | AU35: =AT34-AT35+AV35 -> 0 | AX35: =IF(AV35>0,AW35,AX34) -> 0.7
J36: =SUM(J5:J34)/(COUNT(J5:J34)-COUNTIF(J5:J34,0)) -> 48.666667 | AE36: . | AR36: Nb Delivery | AS36: =COUNT(AW5:AW35) -> 0 | AU36: =SUM(AU5:AU35) -> 450 | AV36: =SUM(AV5:AV35) -> 0 | AW36: =SUM(AW5:AW35)/AS36 -> #DIV/0!
AH37: =AF37+AA37 -> 0 | AI37: =SUM(AI5:AI35) -> 1544.4
AH38: =AF38+AA38 -> 0 | AU38: =AU36*0.51 -> 229.5 | AV38: =AV36/0.51 -> 0 | AW38: =SUM(AW5:AW35)/AS36 -> #DIV/0!
AV39: =AV36*0.51 -> 0

Sheet WATER
D1: =SUM(G21:G35) -> 8951595 | AR1: Entrance | AT1: Tank 1 | AV1: Tank 2
AR2: Level | AW2: Quantity CM3 | AZ2: Var
A3: Date | B3: Truck | C3: Truck M3/day | D3: N0. Trucks | F3: REQ. # of trucks | G3: City | H3: City/day | I3: Total water delivery | K3: SW | L3: Cosum SW/day | M3: RO Guest/ Liter | O3: RO K&L/ Liter | Q3: TOTAL RO Production | R3: RO 1 RH | S3: RO 2 RH | T3: RO water counter | U3: RO Cons m3 | V3: Steam Boiler | W3: Steam Boiler/day | X3: Softener Guest | Y3: Guest Sotf/day | Z3: Softener K&L | AA3: K&L Soft/Day | AB3: Fire Tank Level | AC3: Fire Tank Counter | AE3: Laundry Hot Water Counter | AF3: Hot Water Cons/day | AG3: Laundry Cold Water Counter | AH3: Cold Water Cons/day | AI3: Laundry Water Total Cons | AJ3: K&L Sotf/day | AK3: Guest / day | AL3: K&L /day | AM3: Avg Outside Temp | AN3: Banquet Activity | AR3: Date | AT3: MainI | AV3: Kitchen and Laundry | AX3: Guest | AY3: Main Tank | AZ3: Kitchen and Laundry | BA3: Guest | BB3: Kitchen and Laundry | BC3: Main | BD3: Guest | BE3: Total VAR | BF3: Hotel Consumption
E4: 1.66 | AN4: Ball R | AO4: Meeting | AP4: outlet | AT4: 180 | AV4: 220 | AX4: 580 | AY4: =SUM(AT4) -> 180 | AZ4: =SUM(AV4) -> 220 | BA4: =SUM(AX4) -> 580
A5: 43951 | B5: =[1]WATER!B35 -> 108473 | C5: =[1]WATER!C35 -> 0 | D5: =[1]WATER!D35 -> 0 | E5: =[1]WATER!E35 -> 250 | F5: =[1]WATER!F35 -> 0 | G5: =[1]WATER!G35 -> 596433 | H5: =[1]WATER!H35 -> 0 | I5: =[1]WATER!I35 -> 0 | ... BG5: =[1]WATER!BG35 -> -16.1
A6: =ELEC!C3 -> 43952 | B6: =B5 -> 108473 | C6: =B6-B5 -> 0 | D6: =C6/27 -> 0 | E6: =SUM((C6*$E$4)+(7500/'EDl log'!$A$38)) -> 241.93548 | G6: =G5 -> 596433 | H6: =G6-G5 -> 0 | I6: =C6+H6 -> 0 | J6: =IF(I6>0,E6/I6,0) -> 0 | K6: ='Swimming Pool quality check '!H6 -> 6084 | L6: 0 | M6: =M5 -> 457.44 | N6: =SUM(M6-M5) -> 0 | O6: =O5 -> 529.52 | P6: =SUM(O6-O5) -> 0 | Q6: =P6+N6 -> 0 | T6: 4786 | U6: =SUM(T6-T5) -> 1 | V6: =V5 -> 404 | W6: =+V6-V5 -> 0 | X6: 142863 | Y6: =SUM(X6-X5) -> 2 | Z6: 94175 | AA6: =Z6-Z5 -> 1 | AB6: =AB5 -> 266 | AC6: =AC5 -> 671 | AD6: 0 | AE6: =AE5 -> 149.46 | AF6: =AE6-AE5 -> 0 | AG6: 1518 | AH6: =AG6-AG5 -> 0.55 | AI6: =AF6+AH6 -> 0.55 | AJ6: =+Z6-Z5 -> 1 | AK6: =SUM(Y6-L6) -> 2 | AL6: =SUM(AJ6-W6) -> 1 | AM6: ='General information '!D6 -> 19 | AN6: ='General information '!H6 -> 0 | AP6: ='General information '!J6 -> 105 | AR6: =A6 -> 43952 | AS6: =AS5 -> 0.9 | AT6: =AT5 -> 189 | AU6: =AU5 -> 1.1 | AV6: 72 | AW6: 2.9 | AX6: 114 | AY6: =AS6*AT6 -> 170.1 | AZ6: =AU6*AV6 -> 79.2 | BA6: =AW6*AX6 -> 330.6 | BB6: =AY6-AY5 -> 0 | BC6: =AZ6-AZ5 -> -3.3 | BD6: =BA6-BA5 -> -8.7 | BE6: =SUM(BB6:BD6) -> -12 | BF6: =SUM(I6-BE6) -> 12 | BG6: =SUM(I6-BF6) -> -12
A7: =ELEC!C4 -> 43953 | B7: =B6 -> 108473 | C7: =B7-B6 -> 0 | D7: =C7/27 -> 0 | E7: =SUM((C7*$E$4)+(7500/'EDl log'!$A$38)) -> 241.93548 | G7: 596433 | H7: =G7-G6 -> 0 | I7: =C7+H7 -> 0 | J7: =IF(I7>0,E7/I7,0) -> 0 | K7: ='Swimming Pool quality check '!H7 -> 6090 | L7: =K7-K6 -> 6 | M7: =M6 -> 457.44 | N7: =SUM(M7-M6) -> 0 | O7: =O6 -> 529.52 | P7: =SUM(O7-O6) -> 0 | Q7: =P7+N7 -> 0 | T7: 4788 | U7: =SUM(T7-T6) -> 2 | V7: =V6 -> 404 | W7: =+V7-V6 -> 0 | X7: 142929 | Y7: =SUM(X7-X6) -> 66 | Z7: 94220 | AA7: =Z7-Z6 -> 45 | AB7: =AB6 -> 266 | AC7: =AC6 -> 671 | AD7: =AC7-AC6 -> 0 | AE7: =AE6 -> 149.46 | AF7: =AE7-AE6 -> 0 | AG7: =AG6 -> 1518 | AH7: =AG7-AG6 -> 0 | AI7: =AF7+AH7 -> 0 | AJ7: =+Z7-Z6 -> 45 | AK7: =SUM(Y7-L7) -> 60 | AL7: =SUM(AJ7-W7) -> 45 | AM7: ='General information '!D7 -> 17.5 | AN7: ='General information '!H7 -> 0 | AP7: ='General information '!J7 -> 105 | AR7: =A7 -> 43953 | AS7: =AS6 -> 0.9 | AT7: 84 | AU7: =AU6 -> 1.1 | AV7: 98 | AW7: 2.9 | AX7: 124 | AY7: =AS7*AT7 -> 75.6 | AZ7: =AU7*AV7 -> 107.8 | BA7: =AW7*AX7 -> 359.6 | BB7: =AY7-AY6 -> -94.5 | BC7: =AZ7-AZ6 -> 28.6 | BD7: =BA7-BA6 -> 29 | BE7: =SUM(BB7:BD7) -> -36.9 | BF7: =SUM(I7-BE7) -> 36.9 | BG7: =SUM(I7-BF7) -> -36.9
A8: =ELEC!C5 -> 43954 | B8: =B7 -> 108473 | C8: =B8-B7 -> 0 | D8: =C8/27 -> 0 | E8: =SUM((C8*$E$4)+(7500/'EDl log'!$A$38)) -> 241.93548 | G8: 596773 | H8: =G8-G7 -> 340 | I8: =C8+H8 -> 340 | J8: =IF(I8>0,E8/I8,0) -> 0.71157495 | K8: ='Swimming Pool quality check '!H8 -> 6092 | L8: =K8-K7 -> 2 | M8: =M7 -> 457.44 | N8: =SUM(M8-M7) -> 0 | O8: =O7 -> 529.52 | P8: =SUM(O8-O7) -> 0 | Q8: =P8+N8 -> 0 | T8: =T7 -> 4788 | U8: 4789 | V8: 404 | W8: =+V8-V7 -> 0 | X8: 143011 | Y8: =SUM(X8-X7) -> 82 | Z8: 94233 | AA8: =Z8-Z7 -> 13 | AB8: =AB7 -> 266 | AC8: =AC7 -> 671 | AD8: =AC8-AC7 -> 0 | AE8: =AE7 -> 149.46 | AF8: =AE8-AE7 -> 0 | AG8: =AG7 -> 1518 | AH8: =AG8-AG7 -> 0 | AI8: =AF8+AH8 -> 0 | AJ8: =+Z8-Z7 -> 13 | AK8: =SUM(Y8-L8) -> 80 | AL8: =SUM(AJ8-W8) -> 13 | AM8: ='General information '!D8 -> 20.5 | AN8: ='General information '!H8 -> 0 | AP8: ='General information '!J8 -> 96 | AR8: =A8 -> 43954 | AS8: =AS7 -> 0.9 | AT8: 200 | AU8: 1.1 | AV8: 115 | AW8: 2.9 | AX8: 130 | AY8: =AS8*AT8 -> 180 | AZ8: =AU8*AV8 -> 126.5 | BA8: =AW8*AX8 -> 377 | BB8: =AY8-AY7 -> 104.4 | BC8: =AZ8-AZ7 -> 18.7 | BD8: =BA8-BA7 -> 17.4 | BE8: =SUM(BB8:BD8) -> 140.5 | BF8: =SUM(I8-BE8) -> 199.5 | BG8: =SUM(I8-BF8) -> 140.5
A9: =ELEC!C6 -> 43955 | B9: =B8 -> 108473 | C9: =B9-B8 -> 0 | D9: =C9/27 -> 0 | E9: =SUM((C9*$E$4)+(7500/'EDl log'!$A$38)) -> 241.93548 | G9: 596773 | H9: =G9-G8 -> 0 | I9: =C9+H9 -> 0 | J9: =IF(I9>0,E9/I9,0) -> 0 | K9: ='Swimming Pool quality check '!H9 -> 6098 | L9: =K9-K8 -> 6 | M9: =M8 -> 457.44 | N9: =SUM(M9-M8) -> 0 | O9: =O8 -> 529.52 | P9: =SUM(O9-O8) -> 0 | Q9: =P9+N9 -> 0 | T9: =T8 -> 4788 | U9: 4790 | V9: 405 | W9: =+V9-V8 -> 1 | X9: 143013 | Y9: =SUM(X9-X8) -> 2 | Z9: 94254 | AA9: =Z9-Z8 -> 21 | AB9: =AB8 -> 266 | AC9: =AC8 -> 671 | AD9: =AC9-AC8 -> 0 | AE9: =AE8 -> 149.46 | AF9: =AE9-AE8 -> 0 | AG9: =AG8 -> 1518 | AH9: =AG9-AG8 -> 0 | AI9: =AF9+AH9 -> 0 | AJ9: =+Z9-Z8 -> 21 | AK9: =SUM(Y9-L9) -> -4 | AL9: =SUM(AJ9-W9) -> 20 | AM9: ='General information '!D9 -> 20 | AN9: ='General information '!H9 -> 0 | AP9: ='General information '!J9 -> 0 | AR9: =A9 -> 43955 | AS9: =AS8 -> 0.9 | AT9: 200 | AU9: =AU8 -> 1.1 | AV9: 90 | AW9: 2.9 | AX9: 134 | AY9: =AS9*AT9 -> 180 | AZ9: =AU9*AV9 -> 99 | BA9: =AW9*AX9 -> 388.6 | BB9: =AY9-AY8 -> 0 | BC9: =AZ9-AZ8 -> -27.5 | BD9: =BA9-BA8 -> 11.6 | BE9: =SUM(BB9:BD9) -> -15.9 | BF9: =SUM(I9-BE9) -> 15.9 | BG9: =SUM(I9-BF9) -> -15.9
A10: =ELEC!C7 -> 43956 | B10: =B9 -> 108473 | C10: =B10-B9 -> 0 | D10: =C10/27 -> 0 | E10: =SUM((C10*$E$4)+(7500/'EDl log'!$A$38)) -> 241.93548 | G10: =G9 -> 596773 | H10: =G10-G9 -> 0 | I10: =C10+H10 -> 0 | J10: =IF(I10>0,E10/I10,0) -> 0 | K10: ='Swimming Pool quality check '!H10 -> 6098 | L10: =K10-K9 -> 0 | M10: =M9 -> 457.44 | N10: =SUM(M10-M9) -> 0 | O10: =O9 -> 529.52 | P10: =SUM(O10-O9) -> 0 | Q10: =P10+N10 -> 0 | T10: =T9 -> 4788 | U10: =SUM(T10-T9) -> 0 | V10: =V9 -> 405 | W10: =+V10-V9 -> 0 | X10: =X9 -> 143013 | Y10: =SUM(X10-X9) -> 0 | Z10: =Z9 -> 94254 | AA10: =Z10-Z9 -> 0 | AB10: =AB9 -> 266 | AC10: =AC9 -> 671 | AD10: =AC10-AC9 -> 0 | AE10: =AE9 -> 149.46 | AF10: =AE10-AE9 -> 0 | AG10: =AG9 -> 1518 | AH10: =AG10-AG9 -> 0 | AI10: =AF10+AH10 -> 0 | AJ10: =+Z10-Z9 -> 0 | AK10: =SUM(Y10-L10) -> 0 | AL10: =SUM(AJ10-W10) -> 0 | AM10: ='General information '!D10 -> 0 | AN10: ='General information '!H10 -> 0 | AP10: ='General information '!J10 -> 0 | AR10: =A10 -> 43956 | AS10: =AS9 -> 0.9 | AT10: =AT9 -> 200 | AU10: =AU9 -> 1.1 | AV10: =AV9 -> 90 | AW10: 2.9 | AX10: =AX9 -> 134 | AY10: =AS10*AT10 -> 180 | AZ10: =AU10*AV10 -> 99 | BA10: =AW10*AX10 -> 388.6 | BB10: =AY10-AY9 -> 0 | BC10: =AZ10-AZ9 -> 0 | BD10: =BA10-BA9 -> 0 | BE10: =SUM(BB10:BD10) -> 0 | BF10: =SUM(I10-BE10) -> 0 | BG10: =SUM(I10-BF10) -> 0
A11: =ELEC!C8 -> 43957 | B11: =B10 -> 108473 | C11: =B11-B10 -> 0 | D11: =C11/27 -> 0 | E11: =SUM((C11*$E$4)+(7500/'EDl log'!$A$38)) -> 241.93548 | G11: =G10 -> 596773 | H11: =G11-G10 -> 0 | I11: =C11+H11 -> 0 | J11: =IF(I11>0,E11/I11,0) -> 0 | K11: ='Swimming Pool quality check '!H11 -> 6098 | L11: =K11-K10 -> 0 | M11: =M10 -> 457.44 | N11: =SUM(M11-M10) -> 0 | O11: =O10 -> 529.52 | P11: =SUM(O11-O10) -> 0 | Q11: =SUM(P11+N11) -> 0 | T11: =T10 -> 4788 | U11: =SUM(T11-T10) -> 0 | V11: =V10 -> 405 | W11: =+V11-V10 -> 0 | X11: =X10 -> 143013 | Y11: =SUM(X11-X10) -> 0 | Z11: =Z10 -> 94254 | AA11: =Z11-Z10 -> 0 | AB11: =AB10 -> 266 | AC11: =AC10 -> 671 | AD11: =AC11-AC10 -> 0 | AE11: =AE10 -> 149.46 | AF11: =AE11-AE10 -> 0 | AG11: =AG10 -> 1518 | AH11: =AG11-AG10 -> 0 | AI11: =AF11+AH11 -> 0 | AJ11: =+Z11-Z10 -> 0 | AK11: =SUM(Y11-L11) -> 0 | AL11: =SUM(AJ11-W11) -> 0 | AM11: ='General information '!D11 -> 0 | AN11: ='General information '!H11 -> 0 | AP11: ='General information '!J11 -> 0 | AR11: =A11 -> 43957 | AS11: =AS10 -> 0.9 | AT11: =AT10 -> 200 | AU11: =AU10 -> 1.1 | AV11: =AV10 -> 90 | AW11: 2.9 | AX11: =AX10 -> 134 | AY11: =AS11*AT11 -> 180 | AZ11: =AU11*AV11 -> 99 | BA11: =AW11*AX11 -> 388.6 | BB11: =AY11-AY10 -> 0 | BC11: =AZ11-AZ10 -> 0 | BD11: =BA11-BA10 -> 0 | BE11: =SUM(BB11:BD11) -> 0 | BF11: =SUM(I11-BE11) -> 0 | BG11: =SUM(I11-BF11) -> 0
A12: =ELEC!C9 -> 43958 | B12: =B11 -> 108473 | C12: =B12-B11 -> 0 | D12: =C12/27 -> 0 | E12: =SUM((C12*$E$4)+(7500/'EDl log'!$A$38)) -> 241.93548 | G12: =G11 -> 596773 | H12: =G12-G11 -> 0 | I12: =C12+H12 -> 0 | J12: =IF(I12>0,E12/I12,0) -> 0 | K12: ='Swimming Pool quality check '!H12 -> 6098 | L12: =K12-K11 -> 0 | M12: =M11 -> 457.44 | N12: =SUM(M12-M11) -> 0 | O12: =O11 -> 529.52 | P12: =SUM(O12-O11) -> 0 | Q12: =SUM(P12+N12) -> 0 | T12: =T11 -> 4788 | U12: =SUM(T12-T11) -> 0 | V12: =V11 -> 405 | W12: =+V12-V11 -> 0 | X12: =X11 -> 143013 | Y12: =SUM(X12-X11) -> 0 | Z12: =Z11 -> 94254 | AA12: =Z12-Z11 -> 0 | AB12: =AB11 -> 266 | AC12: =AC11 -> 671 | AD12: =AC12-AC11 -> 0 | AE12: =AE11 -> 149.46 | AF12: =AE12-AE11 -> 0 | AG12: =AG11 -> 1518 | AH12: =AG12-AG11 -> 0 | AI12: =AF12+AH12 -> 0 | AJ12: =+Z12-Z11 -> 0 | AK12: =SUM(Y12-L12) -> 0 | AL12: =SUM(AJ12-W12) -> 0 | AM12: ='General information '!D12 -> 0 | AN12: ='General information '!H12 -> 0 | AP12: ='General information '!J12 -> 0 | AR12: =A12 -> 43958 | AS12: =AS11 -> 0.9 | AT12: =AT11 -> 200 | AU12: =AU11 -> 1.1 | AV12: =AV11 -> 90 | AW12: 2.9 | AX12: =AX11 -> 134 | AY12: =AS12*AT12 -> 180 | AZ12: =AU12*AV12 -> 99 | BA12: =AW12*AX12 -> 388.6 | BB12: =AY12-AY11 -> 0 | BC12: =AZ12-AZ11 -> 0 | BD12: =BA12-BA11 -> 0 | BE12: =SUM(BB12:BD12) -> 0 | BF12: =SUM(I12-BE12) -> 0 | BG12: =SUM(I12-BF12) -> 0
A13: =ELEC!C10 -> 43959 | B13: =B12 -> 108473 | C13: =B13-B12 -> 0 | D13: =C13/27 -> 0 | E13: =SUM((C13*$E$4)+(7500/'EDl log'!$A$38)) -> 241.93548 | G13: =G12 -> 596773 | H13: =G13-G12 -> 0 | I13: =C13+H13 -> 0 | J13: =IF(I13>0,E13/I13,0) -> 0 | K13: ='Swimming Pool quality check '!H13 -> 6098 | L13: =K13-K12 -> 0 | M13: =M12 -> 457.44 | N13: =SUM(M13-M12) -> 0 | O13: =O12 -> 529.52 | P13: =SUM(O13-O12) -> 0 | Q13: =SUM(P13+N13) -> 0 | T13: =T12 -> 4788 | U13: =SUM(T13-T12) -> 0 | V13: =V12 -> 405 | W13: =+V13-V12 -> 0 | X13: =X12 -> 143013 | Y13: =SUM(X13-X12) -> 0 | Z13: =Z12 -> 94254 | AA13: =Z13-Z12 -> 0 | AB13: =AB12 -> 266 | AC13: =AC12 -> 671 | AD13: =AC13-AC12 -> 0 | AE13: =AE12 -> 149.46 | AF13: =AE13-AE12 -> 0 | AG13: =AG12 -> 1518 | AH13: =AG13-AG12 -> 0 | AI13: =AF13+AH13 -> 0 | AJ13: =+Z13-Z12 -> 0 | AK13: =SUM(Y13-L13) -> 0 | AL13: =SUM(AJ13-W13) -> 0 | AM13: ='General information '!D13 -> 0 | AN13: ='General information '!J13 -> 0 | AP13: ='General information '!J13 -> 0 | AR13: =A13 -> 43959 | AS13: =AS12 -> 0.9 | AT13: =AT12 -> 200 | AU13: =AU12 -> 1.1 | AV13: =AV12 -> 90 | AW13: 2.9 | AX13: =AX12 -> 134 | AY13: =AS13*AT13 -> 180 | AZ13: =AU13*AV13 -> 99 | BA13: =AW13*AX13 -> 388.6 | BB13: =AY13-AY12 -> 0 | BC13: =AZ13-AZ12 -> 0 | BD13: =BA13-BA12 -> 0 | BE13: =SUM(BB13:BD13) -> 0 | BF13: =SUM(I13-BE13) -> 0 | BG13: =SUM(I13-BF13) -> 0
A14: =ELEC!C11 -> 43960 | B14: =B13 -> 108473 | C14: =B14-B13 -> 0 | D14: =C14/27 -> 0 | E14: =SUM((C14*$E$4)+(7500/'EDl log'!$A$38)) -> 241.93548 | G14: =G13 -> 596773 | H14: =G14-G13 -> 0 | I14: =C14+H14 -> 0 | J14: =IF(I14>0,E14/I14,0) -> 0 | K14: ='Swimming Pool quality check '!H14 -> 6098 | L14: =K14-K13 -> 0 | M14: =M13 -> 457.44 | N14: =SUM(M14-M13) -> 0 | O14: =O13 -> 529.52 | P14: =SUM(O14-O13) -> 0 | Q14: =SUM(P14+N14) -> 0 | T14: =T13 -> 4788 | U14: =SUM(T14-T13) -> 0 | V14: =V13 -> 405 | W14: =+V14-V13 -> 0 | X14: =X13 -> 143013 | Y14: =SUM(X14-X13) -> 0 | Z14: =Z13 -> 94254 | AA14: =Z14-Z13 -> 0 | AB14: =AB13 -> 266 | AC14: =AC13 -> 671 | AD14: =AC14-AC13 -> 0 | AE14: =AE13 -> 149.46 | AF14: =AE14-AE13 -> 0 | AG14: =AG13 -> 1518 | AH14: =AG14-AG13 -> 0 | AI14: =AF14+AH14 -> 0 | AJ14: =+Z14-Z13 -> 0 | AK14: =SUM(Y14-L14) -> 0 | AL14: =SUM(AJ14-W14) -> 0 | AM14: ='General information '!D14 -> 0 | AN14: ='General information '!H14 -> 0 | AP14: ='General information '!J14 -> 0 | AR14: =A14 -> 43960 | AS14: =AS13 -> 0.9 | AT14: =AT13 -> 200 | AU14: =AU13 -> 1.1 | AV14: =AV13 -> 90 | AW14: 2.9 | AX14: =AX13 -> 134 | AY14: =AS14*AT14 -> 180 | AZ14: =AU14*AV14 -> 99 | BA14: =AW14*AX14 -> 388.6 | BB14: =AY14-AY13 -> 0 | BC14: =AZ14-AZ13 -> 0 | BD14: =BA14-BA13 -> 0 | BE14: =SUM(BB14:BD14) -> 0 | BF14: =SUM(I14-BE14) -> 0 | BG14: =SUM(I14-BF14) -> 0
A15: =ELEC!C12 -> 43961 | B15: =B14 -> 108473 | C15: =B15-B14 -> 0 | D15: =C15/27 -> 0 | E15: =SUM((C15*$E$4)+(7500/'EDl log'!$A$38)) -> 241.93548 | G15: =G14 -> 596773 | H15: =G15-G14 -> 0 | I15: =C15+H15 -> 0 | J15: =IF(I15>0,E15/I15,0) -> 0 | K15: ='Swimming Pool quality check '!H15 -> 6098 | L15: =K15-K14 -> 0 | M15: =M14 -> 457.44 | N15: =SUM(M15-M14) -> 0 | O15: =O14 -> 529.52 | P15: =SUM(O15-O14) -> 0 | Q15: =SUM(P15+N15) -> 0 | T15: =T14 -> 4788 | U15: =SUM(T15-T14) -> 0 | V15: =V14 -> 405 | W15: =+V15-V14 -> 0 | X15: =X14 -> 143013 | Y15: =SUM(X15-X14) -> 0 | Z15: =Z14 -> 94254 | AA15: =Z15-Z14 -> 0 | AB15: =AB14 -> 266 | AC15: =AC14 -> 671 | AD15: =AC15-AC14 -> 0 | AE15: =AE14 -> 149.46 | AF15: =AE15-AE14 -> 0 | AG15: =AG14 -> 1518 | AH15: =AG15-AG14 -> 0 | AI15: =AF15+AH15 -> 0 | AJ15: =+Z15-Z14 -> 0 | AK15: =SUM(Y15-L15) -> 0 | AL15: =SUM(AJ15-W15) -> 0 | AM15: ='General information '!D15 -> 0 | AN15: ='General information '!H15 -> 0 | AP15: ='General information '!J15 -> 0 | AR15: =A15 -> 43961 | AS15: =AS14 -> 0.9 | AT15: =AT14 -> 200 | AU15: =AU14 -> 1.1 | AV15: =AV14 -> 90 | AW15: 2.9 | AX15: =AX14 -> 134 | AY15: =AS15*AT15 -> 180 | AZ15: =AU15*AV15 -> 99 | BA15: =AW15*AX15 -> 388.6 | BB15: =AY15-AY14 -> 0 | BC15: =AZ15-AZ14 -> 0 | BD15: =BA15-BA14 -> 0 | BE15: =SUM(BB15:BD15) -> 0 | BF15: =SUM(I15-BE15) -> 0 | BG15: =SUM(I15-BF15) -> 0
A16: =ELEC!C13 -> 43962 | B16: =B15 -> 108473 | C16: =B16-B15 -> 0 | D16: =C16/27 -> 0 | E16: =SUM((C16*$E$4)+(7500/'EDl log'!$A$38)) -> 241.93548 | G16: =G15 -> 596773 | H16: =G16-G15 -> 0 | I16: =C16+H16 -> 0 | J16: =IF(I16>0,E16/I16,0) -> 0 | K16: ='Swimming Pool quality check '!H16 -> 6098 | L16: =K16-K15 -> 0 | M16: =M15 -> 457.44 | N16: =SUM(M16-M15) -> 0 | O16: =O15 -> 529.52 | P16: =SUM(O16-O15) -> 0 | Q16: =SUM(P16+N16) -> 0 | T16: =T15 -> 4788 | U16: =SUM(T16-T15) -> 0 | V16: =V15 -> 405 | W16: =+V16-V15 -> 0 | X16: =X15 -> 143013 | Y16: =SUM(X16-X15) -> 0 | Z16: =Z15 -> 94254 | AA16: =Z16-Z15 -> 0 | AB16: =AB15 -> 266 | AC16: =AC15 -> 671 | AD16: =AC16-AC15 -> 0 | AE16: =AE15 -> 149.46 | AF16: =AE16-AE15 -> 0 | AG16: =AG15 -> 1518 | AH16: =AG16-AG15 -> 0 | AI16: =AF16+AH16 -> 0 | AJ16: =+Z16-Z15 -> 0 | AK16: =SUM(Y16-L16) -> 0 | AL16: =SUM(AJ16-W16) -> 0 | AM16: ='General information '!D16 -> 0 | AN16: ='General information '!H16 -> 0 | AP16: ='General information '!J16 -> 0 | AR16: =A16 -> 43962 | AS16: =AS15 -> 0.9 | AT16: =AT15 -> 200 | AU16: =AU15 -> 1.1 | AV16: =AV15 -> 90 | AW16: 2.9 | AX16: =AX15 -> 134 | AY16: =AS16*AT16 -> 180 | AZ16: =AU16*AV16 -> 99 | BA16: =AW16*AX16 -> 388.6 | BB16: =AY16-AY15 -> 0 | BC16: =AZ16-AZ15 -> 0 | BD16: =BA16-BA15 -> 0 | BE16: =SUM(BB16:BD16) -> 0 | BF16: =SUM(I16-BE16) -> 0 | BG16: =SUM(I16-BF16) -> 0
A17: =ELEC!C14 -> 43963 | B17: =B16 -> 108473 | C17: =B17-B16 -> 0 | D17: =C17/27 -> 0 | E17: =SUM((C17*$E$4)+(7500/'EDl log'!$A$38)) -> 241.93548 | G17: =G16 -> 596773 | H17: =G17-G16 -> 0 | I17: =C17+H17 -> 0 | J17: =IF(I17>0,E17/I17,0) -> 0 | K17: ='Swimming Pool quality check '!H17 -> 6098 | L17: =K17-K16 -> 0 | M17: =M16 -> 457.44 | N17: =SUM(M17-M16) -> 0 | O17: =O16 -> 529.52 | P17: =SUM(O17-O16) -> 0 | Q17: =SUM(P17+N17) -> 0 | T17: =T16 -> 4788 | U17: =SUM(T17-T16) -> 0 | V17: =V16 -> 405 | W17: =+V17-V16 -> 0 | X17: =X16 -> 143013 | Y17: =SUM(X17-X16) -> 0 | Z17: =Z16 -> 94254 | AA17: =Z17-Z16 -> 0 | AB17: =AB16 -> 266 | AC17: =AC16 -> 671 | AD17: =AC17-AC16 -> 0 | AE17: =AE16 -> 149.46 | AF17: =AE17-AE16 -> 0 | AG17: =AG16 -> 1518 | AH17: =AG17-AG16 -> 0 | AI17: =AF17+AH17 -> 0 | AJ17: =+Z17-Z16 -> 0 | AK17: =SUM(Y17-L17) -> 0 | AL17: =SUM(AJ17-W17) -> 0 | AM17: ='General information '!D17 -> 0 | AN17: ='General information '!H17 -> 0 | AP17: ='General information '!J17 -> 0 | AR17: =A17 -> 43963 | AS17: =AS16 -> 0.9 | AT17: =AT16 -> 200 | AU17: =AU16 -> 1.1 | AV17: =AV16 -> 90 | AW17: 2.9 | AX17: =AX16 -> 134 | AY17: =AS17*AT17 -> 180 | AZ17: =AU17*AV17 -> 99 | BA17: =AW17*AX17 -> 388.6 | BB17: =AY17-AY16 -> 0 | BC17: =AZ17-AZ16 -> 0 | BD17: =BA17-BA16 -> 0 | BE17: =SUM(BB17:BD17) -> 0 | BF17: =SUM(I17-BE17) -> 0 | BG17: =SUM(I17-BF17) -> 0
A18: =ELEC!C15 -> 43964 | B18: =B17 -> 108473 | C18: =B18-B17 -> 0 | D18: =C18/27 -> 0 | E18: =SUM((C18*$E$4)+(7500/'EDl log'!$A$38)) -> 241.93548 | G18: =G17 -> 596773 | H18: =G18-G17 -> 0 | I18: =C18+H18 -> 0 | J18: =IF(I18>0,E18/I18,0) -> 0 | K18: ='Swimming Pool quality check '!H18 -> 6098 | L18: =K18-K17 -> 0 | M18: =M17 -> 457.44 | N18: =SUM(M18-M17) -> 0 | O18: =O17 -> 529.52 | P18: =SUM(O18-O17) -> 0 | Q18: =SUM(P18+N18) -> 0 | T18: =T17 -> 4788 | U18: =SUM(T18-T17) -> 0 | V18: =V17 -> 405 | W18: =+V18-V17 -> 0 | X18: =X17 -> 143013 | Y18: =SUM(X18-X17) -> 0 | Z18: =Z17 -> 94254 | AA18: =Z18-Z17 -> 0 | AB18: =AB17 -> 266 | AC18: =AC17 -> 671 | AD18: =AC18-AC17 -> 0 | AE18: =AE17 -> 149.46 | AF18: =AE18-AE17 -> 0 | AG18: =AG17 -> 1518 | AH18: =AG18-AG17 -> 0 | AI18: =AF18+AH18 -> 0 | AJ18: =+Z18-Z17 -> 0 | AK18: =SUM(Y18-L18) -> 0 | AL18: =SUM(AJ18-W18) -> 0 | AM18: ='General information '!D18 -> 0 | AN18: ='General information '!H18 -> 0 | AP18: ='General information '!J18 -> 0 | AR18: =A18 -> 43964 | AS18: =AS17 -> 0.9 | AT18: =AT17 -> 200 | AU18: =AU17 -> 1.1 | AV18: =AV17 -> 90 | AW18: 2.9 | AX18: =AX17 -> 134 | AY18: =AS18*AT18 -> 180 | AZ18: =AU18*AV18 -> 99 | BA18: =AW18*AX18 -> 388.6 | BB18: =AY18-AY17 -> 0 | BC18: =AZ18-AZ17 -> 0 | BD18: =BA18-BA17 -> 0 | BE18: =SUM(BB18:BD18) -> 0 | BF18: =SUM(I18-BE18) -> 0 | BG18: =SUM(I18-BF18) -> 0
A19: =ELEC!C16 -> 43965 | B19: =B18 -> 108473 | C19: =B19-B18 -> 0 | D19: =C19/27 -> 0 | E19: =SUM((C19*$E$4)+(7500/'EDl log'!$A$38)) -> 241.93548 | G19: =G18 -> 596773 | H19: =G19-G18 -> 0 | I19: =C19+H19 -> 0 | J19: =IF(I19>0,E19/I19,0) -> 0 | K19: ='Swimming Pool quality check '!H19 -> 6098 | L19: =K19-K18 -> 0 | M19: =M18 -> 457.44 | N19: =SUM(M19-M18) -> 0 | O19: =O18 -> 529.52 | P19: =SUM(O19-O18) -> 0 | Q19: =SUM(P19+N19) -> 0 | T19: =T18 -> 4788 | U19: =SUM(T19-T18) -> 0 | V19: =V18 -> 405 | W19: =+V19-V18 -> 0 | X19: =X18 -> 143013 | Y19: =SUM(X19-X18) -> 0 | Z19: =Z18 -> 94254 | AA19: =Z19-Z18 -> 0 | AB19: =AB18 -> 266 | AC19: =AC18 -> 671 | AD19: =AC19-AC18 -> 0 | AE19: =AE18 -> 149.46 | AF19: =AE19-AE18 -> 0 | AG19: =AG18 -> 1518 | AH19: =AG19-AG18 -> 0 | AI19: =AF19+AH19 -> 0 | AJ19: =+Z19-Z18 -> 0 | AK19: =SUM(Y19-L19) -> 0 | AL19: =SUM(AJ19-W19) -> 0 | AM19: ='General information '!D19 -> 0 | AN19: ='General information '!H19 -> 0 | AP19: ='General information '!J19 -> 0 | AR19: =A19 -> 43965 | AS19: =AS18 -> 0.9 | AT19: =AT18 -> 200 | AU19: =AU18 -> 1.1 | AV19: =AV18 -> 90 | AW19: 2.9 | AX19: =AX18 -> 134 | AY19: =AS19*AT19 -> 180 | AZ19: =AU19*AV19 -> 99 | BA19: =AW19*AX19 -> 388.6 | BB19: =AY19-AY18 -> 0 | BC19: =AZ19-AZ18 -> 0 | BD19: =BA19-BA18 -> 0 | BE19: =SUM(BB19:BD19) -> 0 | BF19: =SUM(I19-BE19) -> 0 | BG19: =SUM(I19-BF19) -> 0
A20: =ELEC!C17 -> 43966 | B20: =B19 -> 108473 | C20: =B20-B19 -> 0 | D20: =C20/27 -> 0 | E20: =SUM((C20*$E$4)+(7500/'EDl log'!$A$38)) -> 241.93548 | G20: =G19 -> 596773 | H20: =G20-G19 -> 0 | I20: =C20+H20 -> 0 | J20: =IF(I20>0,E20/I20,0) -> 0 | K20: ='Swimming Pool quality check '!H20 -> 6098 | L20: =K20-K19 -> 0 | M20: =M19 -> 457.44 | N20: =SUM(M20-M19) -> 0 | O20: =O19 -> 529.52 | P20: =SUM(O20-O19) -> 0 | Q20: =SUM(P20+N20) -> 0 | T20: =T19 -> 4788 | U20: =SUM(T20-T19) -> 0 | V20: =V19 -> 405 | W20: =+V20-V19 -> 0 | X20: =X19 -> 143013 | Y20: =SUM(X20-X19) -> 0 | Z20: =Z19 -> 94254 | AA20: =Z20-Z19 -> 0 | AB20: =AB19 -> 266 | AC20: =AC19 -> 671 | AD20: =AC20-AC19 -> 0 | AE20: =AE19 -> 149.46 | AF20: =AE20-AE19 -> 0 | AG20: =AG19 -> 1518 | AH20: =AG20-AG19 -> 0 | AI20: =AF20+AH20 -> 0 | AJ20: =+Z20-Z19 -> 0 | AK20: =SUM(Y20-L20) -> 0 | AL20: =SUM(AJ20-W20) -> 0 | AM20: ='General information '!D20 -> 0 | AN20: ='General information '!H20 -> 0 | AP20: ='General information '!J20 -> 0 | AR20: =A20 -> 43966 | AS20: =AS19 -> 0.9 | AT20: =AT19 -> 200 | AU20: =AU19 -> 1.1 | AV20: =AV19 -> 90 | AW20: 2.9 | AX20: =AX19 -> 134 | AY20: =AS20*AT20 -> 180 | AZ20: =AU20*AV20 -> 99 | BA20: =AW20*AX20 -> 388.6 | BB20: =AY20-AY19 -> 0 | BC20: =AZ20-AZ19 -> 0 | BD20: =BA20-BA19 -> 0 | BE20: =SUM(BB20:BD20) -> 0 | BF20: =SUM(I20-BE20) -> 0 | BG20: =SUM(I20-BF20) -> 0
A21: =ELEC!C18 -> 43967 | B21: =B20 -> 108473 | C21: =B21-B20 -> 0 | D21: =C21/27 -> 0 | E21: =SUM((C21*$E$4)+(7500/'EDl log'!$A$38)) -> 241.93548 | G21: =G20 -> 596773 | H21: =G21-G20 -> 0 | I21: =C21+H21 -> 0 | J21: =IF(I21>0,E21/I21,0) -> 0 | K21: ='Swimming Pool quality check '!H21 -> 6098 | L21: =K21-K20 -> 0 | M21: =M20 -> 457.44 | N21: =SUM(M21-M20) -> 0 | O21: =O20 -> 529.52 | P21: =SUM(O21-O20) -> 0 | Q21: =SUM(P21+N21) -> 0 | T21: =T20 -> 4788 | U21: =SUM(T21-T20) -> 0 | V21: =V20 -> 405 | W21: =+V21-V20 -> 0 | X21: =X20 -> 143013 | Y21: =SUM(X21-X20) -> 0 | Z21: =Z20 -> 94254 | AA21: =Z21-Z20 -> 0 | AB21: =AB20 -> 266 | AC21: =AC20 -> 671 | AD21: =AC21-AC20 -> 0 | AE21: =AE20 -> 149.46 | AF21: =AE21-AE20 -> 0 | AG21: =AG20 -> 1518 | AH21: =AG21-AG20 -> 0 | AI21: =AF21+AH21 -> 0 | AJ21: =+Z21-Z20 -> 0 | AK21: =SUM(Y21-L21) -> 0 | AL21: =SUM(AJ21-W21) -> 0 | AM21: ='General information '!D21 -> 0 | AN21: ='General information '!H21 -> 0 | AP21: ='General information '!J21 -> 0 | AR21: =A21 -> 43967 | AS21: =AS20 -> 0.9 | AT21: =AT20 -> 200 | AU21: =AU20 -> 1.1 | AV21: =AV20 -> 90 | AW21: 2.9 | AX21: =AX20 -> 134 | AY21: =AS21*AT21 -> 180 | AZ21: =AU21*AV21 -> 99 | BA21: =AW21*AX21 -> 388.6 | BB21: =AY21-AY20 -> 0 | BC21: =AZ21-AZ20 -> 0 | BD21: =BA21-BA20 -> 0 | BE21: =SUM(BB21:BD21) -> 0 | BF21: =SUM(I21-BE21) -> 0 | BG21: =SUM(I21-BF21) -> 0
A22: =ELEC!C19 -> 43968 | B22: =B21 -> 108473 | C22: =B22-B21 -> 0 | D22: =C22/27 -> 0 | E22: =SUM((C22*$E$4)+(7500/'EDl log'!$A$38)) -> 241.93548 | G22: =G21 -> 596773 | H22: =G22-G21 -> 0 | I22: =C22+H22 -> 0 | J22: =IF(I22>0,E22/I22,0) -> 0 | K22: ='Swimming Pool quality check '!H22 -> 6098 | L22: =K22-K21 -> 0 | M22: =M21 -> 457.44 | N22: =SUM(M22-M21) -> 0 | O22: =O21 -> 529.52 | P22: =SUM(O22-O21) -> 0 | Q22: =SUM(P22+N22) -> 0 | T22: =T21 -> 4788 | U22: =SUM(T22-T21) -> 0 | V22: =V21 -> 405 | W22: =+V22-V21 -> 0 | X22: =X21 -> 143013 | Y22: =SUM(X22-X21) -> 0 | Z22: =Z21 -> 94254 | AA22: =Z22-Z21 -> 0 | AB22: =AB21 -> 266 | AC22: =AC21 -> 671 | AD22: =AC22-AC21 -> 0 | AE22: =AE21 -> 149.46 | AF22: =AE22-AE21 -> 0 | AG22: =AG21 -> 1518 | AH22: =AG22-AG21 -> 0 | AI22: =AF22+AH22 -> 0 | AJ22: =+Z22-Z21 -> 0 | AK22: =SUM(Y22-L22) -> 0 | AL22: =SUM(AJ22-W22) -> 0 | AM22: ='General information '!D22 -> 0 | AN22: ='General information '!H22 -> 0 | AP22: ='General information '!J22 -> 0 | AR22: =A22 -> 43968 | AS22: =AS21 -> 0.9 | AT22: =AT21 -> 200 | AU22: =AU21 -> 1.1 | AV22: =AV21 -> 90 | AW22: 2.9 | AX22: =AX21 -> 134 | AY22: =AS22*AT22 -> 180 | AZ22: =AU22*AV22 -> 99 | BA22: =AW22*AX22 -> 388.6 | BB22: =AY22-AY21 -> 0 | BC22: =AZ22-AZ21 -> 0 | BD22: =BA22-BA21 -> 0 | BE22: =SUM(BB22:BD22) -> 0 | BF22: =SUM(I22-BE22) -> 0 | BG22: =SUM(I22-BF22) -> 0
A23: =ELEC!C20 -> 43969 | B23: =B22 -> 108473 | C23: =B23-B22 -> 0 | D23: =C23/27 -> 0 | E23: =SUM((C23*$E$4)+(7500/'EDl log'!$A$38)) -> 241.93548 | G23: =G22 -> 596773 | H23: =G23-G22 -> 0 | I23: =C23+H23 -> 0 | J23: =IF(I23>0,E23/I23,0) -> 0 | K23: ='Swimming Pool quality check '!H23 -> 6098 | L23: =K23-K22 -> 0 | M23: =M22 -> 457.44 | N23: =SUM(M23-M22) -> 0 | O23: =O22 -> 529.52 | P23: =SUM(O23-O22) -> 0 | Q23: =SUM(P23+N23) -> 0 | T23: =T22 -> 4788 | U23: =SUM(T23-T22) -> 0 | V23: =V22 -> 405 | W23: =+V23-V22 -> 0 | X23: =X22 -> 143013 | Y23: =SUM(X23-X22) -> 0 | Z23: =Z22 -> 94254 | AA23: =Z23-Z22 -> 0 | AB23: =AB22 -> 266 | AC23: =AC22 -> 671 | AD23: =AC23-AC22 -> 0 | AE23: =AE22 -> 149.46 | AF23: =AE23-AE22 -> 0 | AG23: =AG22 -> 1518 | AH23: =AG23-AG22 -> 0 | AI23: =AF23+AH23 -> 0 | AJ23: =+Z23-Z22 -> 0 | AK23: =SUM(Y23-L23) -> 0 | AL23: =SUM(AJ23-W23) -> 0 | AM23: ='General information '!D23 -> 0 | AN23: ='General information '!H23 -> 0 | AP23: ='General information '!J23 -> 0 | AR23: =A23 -> 43969 | AS23: =AS22 -> 0.9 | AT23: =AT22 -> 200 | AU23: =AU22 -> 1.1 | AV23: =AV22 -> 90 | AW23: 2.9 | AX23: =AX22 -> 134 | AY23: =AS23*AT23 -> 180 | AZ23: =AU23*AV23 -> 99 | BA23: =AW23*AX23 -> 388.6 | BB23: =AY23-AY22 -> 0 | BC23: =AZ23-AZ22 -> 0 | BD23: =BA23-BA22 -> 0 | BE23: =SUM(BB23:BD23) -> 0 | BF23: =SUM(I23-BE23) -> 0 | BG23: =SUM(I23-BF23) -> 0
A24: =ELEC!C21 -> 43970 | B24: =B23 -> 108473 | C24: =B24-B23 -> 0 | D24: =C24/27 -> 0 | E24: =SUM((C24*$E$4)+(7500/'EDl log'!$A$38)) -> 241.93548 | G24: =G23 -> 596773 | H24: =G24-G23 -> 0 | I24: =C24+H24 -> 0 | J24: =IF(I24>0,E24/I24,0) -> 0 | K24: ='Swimming Pool quality check '!H24 -> 6098 | L24: =K24-K23 -> 0 | M24: =M23 -> 457.44 | N24: =SUM(M24-M23) -> 0 | O24: =O23 -> 529.52 | P24: =SUM(O24-O23) -> 0 | Q24: =SUM(P24+N24) -> 0 | T24: =T23 -> 4788 | U24: =SUM(T24-T23) -> 0 | V24: =V23 -> 405 | W24: =+V24-V23 -> 0 | X24: =X23 -> 143013 | Y24: =SUM(X24-X23) -> 0 | Z24: =Z23 -> 94254 | AA24: =Z24-Z23 -> 0 | AB24: =AB23 -> 266 | AC24: =AC23 -> 671 | AD24: =AC24-AC23 -> 0 | AE24: =AE23 -> 149.46 | AF24: =AE24-AE23 -> 0 | AG24: =AG23 -> 1518 | AH24: =AG24-AG23 -> 0 | AI24: =AF24+AH24 -> 0 | AJ24: =+Z24-Z23 -> 0 | AK24: =SUM(Y24-L24) -> 0 | AL24: =SUM(AJ24-W24) -> 0 | AM24: ='General information '!D24 -> 0 | AN24: ='General information '!H24 -> 0 | AP24: ='General information '!J24 -> 0 | AR24: =A24 -> 43970 | AS24: =AS23 -> 0.9 | AT24: =AT23 -> 200 | AU24: =AU23 -> 1.1 | AV24: =AV23 -> 90 | AW24: 2.9 | AX24: =AX23 -> 134 | AY24: =AS24*AT24 -> 180 | AZ24: =AU24*AV24 -> 99 | BA24: =AW24*AX24 -> 388.6 | BB24: =AY24-AY23 -> 0 | BC24: =AZ24-AZ23 -> 0 | BD24: =BA24-BA23 -> 0 | BE24: =SUM(BB24:BD24) -> 0 | BF24: =SUM(I24-BE24) -> 0 | BG24: =SUM(I24-BF24) -> 0
A25: =ELEC!C22 -> 43971 | B25: =B24 -> 108473 | C25: =B25-B24 -> 0 | D25: =C25/27 -> 0 | E25: =SUM((C25*$E$4)+(7500/'EDl log'!$A$38)) -> 241.93548 | G25: =G24 -> 596773 | H25: =G25-G24 -> 0 | I25: =C25+H25 -> 0 | J25: =IF(I25>0,E25/I25,0) -> 0 | K25: ='Swimming Pool quality check '!H25 -> 6098 | L25: =K25-K24 -> 0 | M25: =M24 -> 457.44 | N25: =SUM(M25-M24) -> 0 | O25: =O24 -> 529.52 | P25: =SUM(O25-O24) -> 0 | Q25: =SUM(P25+N25) -> 0 | T25: =T24 -> 4788 | U25: =SUM(T25-T24) -> 0 | V25: =V24 -> 405 | W25: =+V25-V24 -> 0 | X25: =X24 -> 143013 | Y25: =SUM(X25-X24) -> 0 | Z25: =Z24 -> 94254 | AA25: =Z25-Z24 -> 0 | AB25: =AB24 -> 266 | AC25: =AC24 -> 671 | AD25: =AC25-AC24 -> 0 | AE25: =AE24 -> 149.46 | AF25: =AE25-AE24 -> 0 | AG25: =AG24 -> 1518 | AH25: =AG25-AG24 -> 0 | AI25: =AF25+AH25 -> 0 | AJ25: =+Z25-Z24 -> 0 | AK25: =SUM(Y25-L25) -> 0 | AL25: =SUM(AJ25-W25) -> 0 | AM25: ='General information '!D25 -> 0 | AN25: ='General information '!H25 -> 0 | AP25: ='General information '!J25 -> 0 | AR25: =A25 -> 43971 | AS25: =AS24 -> 0.9 | AT25: =AT24 -> 200 | AU25: =AU24 -> 1.1 | AV25: =AV24 -> 90 | AW25: 2.9 | AX25: =AX24 -> 134 | AY25: =AS25*AT25 -> 180 | AZ25: =AU25*AV25 -> 99 | BA25: =AW25*AX25 -> 388.6 | BB25: =AY25-AY24 -> 0 | BC25: =AZ25-AZ24 -> 0 | BD25: =BA25-BA24 -> 0 | BE25: =SUM(BB25:BD25) -> 0 | BF25: =SUM(I25-BE25) -> 0 | BG25: =SUM(I25-BF25) -> 0
... A36: =ELEC!C33 -> 43982 | B36: =B35 -> 108473 | C36: =B36-B35 -> 0 | D36: =C36/27 -> 0 | E36: =SUM((C36*$E$4)+(7500/'EDl log'!$A$38)) -> 241.93548 | G36: =G35 -> 596773 | H36: =G36-G35 -> 0 | I36: =C36+H36 -> 0 | J36: =IF(I36>0,E36/I36,0) -> 0 | K36: ='Swimming Pool quality check '!H36 -> 6098 | L36: =K36-K35 -> 0 | M36: =M35 -> 457.44 | N36: =SUM(M36-M35) -> 0 | O36: =O35 -> 529.52 | P36: =SUM(O36-O35) -> 0 | Q36: =SUM(P36+N36) -> 0 | T36: =T35 -> 4788 | U36: =SUM(T36-T35) -> 0 | V36: =V35 -> 405 | W36: =+V36-V35 -> 0 | X36: =X35 -> 143013 | Y36: =SUM(X36-X35) -> 0 | Z36: =Z35 -> 94254 | AA36: =Z36-Z35 -> 0 | AB36: =AB35 -> 266 | AC36: =AC35 -> 671 | AD36: =AC36-AC35 -> 0 | AE36: =AE35 -> 149.46 | AF36: =AE36-AE35 -> 0 | AG36: =AG35 -> 1518 | AH36: =AG36-AG35 -> 0 | AI36: =AF36+AH36 -> 0 | AJ36: =+Z36-Z35 -> 0 | AK36: =SUM(Y36-L36) -> 0 | AL36: =SUM(AJ36-W36) -> 0 | AM36: ='General information '!D36 -> 0 | AN36: ='General information '!H36 -> 0 | AP36: ='General information '!J36 -> 0 | AR36: =A36 -> 43982 | AS36: =AS35 -> 0.9 | AT36: =AT35 -> 200 | AU36: =AU35 -> 1.1 | AV36: =AV35 -> 90 | AW36: 2.9 | AX36: =AX35 -> 134 | AY36: =AS36*AT36 -> 180 | AZ36: =AU36*AV36 -> 99 | BA36: =AW36*AX36 -> 388.6 | BB36: =AY36-AY35 -> 0 | BC36: =AZ36-AZ35 -> 0 | BD36: =BA36-BA35 -> 0 | BE36: =SUM(BB36:BD36) -> 0 | BF36: =SUM(I36-BE36) -> 0 | BG36: =SUM(I36-BF36) -> 0
C37: =SUM(C6:C36) -> 0 | D37: =SUM(D6:D36) -> 0 | F37: =SUM(F6:F36) -> 0 | H37: =SUM(H6:H36) -> 340 | I37: =SUM(I6:I36) -> 340 | L37: =SUM(L7:L36) -> 14 | Q37: =SUM(Q5:Q35) -> 0 | U37: =SUM(U6:U36) -> 9582 | Y37: =SUM(Y35,Y33,Y31,Y29,Y27,Y25,Y23,Y21,Y19,Y17,Y15,Y13,Y11,Y9,Y7+Y36) -> 68 | AJ37: =SUM(AJ6:AJ36) -> 80 | AK37: =SUM(Y37-L37) -> 54 | AL37: =SUM(AL6:AL36) -> 79 | AT37: =AT36 -> 200
C38: =+C37*1.66 -> 0 | E38: =SUM(E6:E36) -> 7500 | F38: =SUM(F6:F36) -> 0 | H38: 7500 | I38: =SUM('General information '!G37/WATER!I37) -> 0.07935 | O38: =SUM(Q37+I37) -> 340 | Z38: =SUM(Y37:AJ37) -> 148 | AK38: =SUM(Y38-L38) -> 0
B39: =9*27 -> 243 | D39: =SUM(D21:D35) -> 0 | F39: =SUM(F6:F36) -> 0 | G39: =SUM(I37) -> 340 | H39: =SUM(H38+C38) -> 7500 | K39: =SUM(H39/G39) -> 22.058824 | AJ39: =SUM(C38-AK38) -> 0 | AM39: =SUM(AJ39/AO38) -> #DIV/0!

Sheet graphic

Sheet General information 
A1: GENERAL & HOTEL'S INFORMATION SHEET
B4: Max Temp | C4: MIN TEMP | D4: AVE TEMP | E4: AVE Humidity | F4: AVE OCC | G4: # of OCC Rooms | H4: Ball room | I4: Meeting rooms | J4: Outlets | K4: Total covers | L4: # of permenant Emp | M4: # of casuals | N4: Total # of EMP | O4: # of EMP/OCC Room
A5: =ELEC!C2 -> 43951 | B5: ='[1]General information '!B35 -> 23 | C5: ='[1]General information '!C35 -> 19 | D5: ='[1]General information '!D35 -> 21 | E5: ='[1]General information '!E35 -> 0.75 | F5: ='[1]General information '!F35 -> 0.013 | G5: ='[1]General information '!G35 -> 2.99 | H5: ='[1]General information '!H35 -> 0 | I5: ='[1]General information '!I35 -> 0 | ... O5: ='[1]General information '!O35 -> 0
A6: =ELEC!C3 -> 43952 | B6: 22 | C6: 16 | D6: =(C6+B6)/2 -> 19 | E6: 0.69 | F6: 0.0435 | G6: =F6*230 -> 10.005 | H6: 0 | J6: 105 | K6: =+J6+H6 -> 105
A7: =ELEC!C4 -> 43953 | B7: 21 | C7: 14 | D7: =(C7+B7)/2 -> 17.5 | E7: 0.63 | F7: 0.039 | G7: =F7*230 -> 8.97 | J7: 105 | K7: =+J7+H7 -> 105
A8: =ELEC!C5 -> 43954 | B8: 24 | C8: 17 | D8: =(C8+B8)/2 -> 20.5 | E8: 0.7 | F8: 0.0261 | G8: =F8*230 -> 6.003 | H8: 0 | J8: 96 | K8: =+J8+H8 -> 96
A9: =ELEC!C6 -> 43955 | B9: 23 | C9: 17 | D9: =(C9+B9)/2 -> 20 | E9: 0.71 | F9: 0.0087 | G9: =F9*230 -> 2.001 | H9: 0 | J9: 0 | K9: =+J9+H9 -> 0
A10: =ELEC!C7 -> 43956 | D10: =(C10+B10)/2 -> 0 | G10: =F10*230 -> 0 | K10: =+J10+H10 -> 0
A11: =ELEC!C8 -> 43957 | D11: =(C11+B11)/2 -> 0 | G11: =F11*230 -> 0 | K11: =+J11+H11 -> 0
A12: =ELEC!C9 -> 43958 | D12: =(C12+B12)/2 -> 0 | G12: =F12*230 -> 0 | K12: =+J12+H12 -> 0
A13: =ELEC!C10 -> 43959 | D13: =(C13+B13)/2 -> 0 | G13: =F13*230 -> 0 | K13: =+J13+H13 -> 0
A14: =ELEC!C11 -> 43960 | D14: =(C14+B14)/2 -> 0 | G14: =F14*230 -> 0 | K14: =+J14+H14 -> 0
A15: =ELEC!C12 -> 43961 | D15: =(C15+B15)/2 -> 0 | G15: =F15*230 -> 0 | K15: =+J15+H15 -> 0
A16: =ELEC!C13 -> 43962 | D16: =(C16+B16)/2 -> 0 | G16: =F16*230 -> 0 | K16: =+J16+H16 -> 0
A17: =ELEC!C14 -> 43963 | D17: =(C17+B17)/2 -> 0 | G17: =F17*230 -> 0 | K17: =+J17+H17 -> 0
A18: =ELEC!C15 -> 43964 | D18: =(C18+B18)/2 -> 0 | G18: =F18*230 -> 0 | K18: =+J18+H18 -> 0
A19: =ELEC!C16 -> 43965 | D19: =(C19+B19)/2 -> 0 | G19: =F19*230 -> 0 | K19: =+J19+H19 -> 0
A20: =ELEC!C17 -> 43966 | D20: =(C20+B20)/2 -> 0 | G20: =F20*230 -> 0 | K20: =+J20+H20 -> 0
A21: =ELEC!C18 -> 43967 | D21: =(C21+B21)/2 -> 0 | G21: =F21*230 -> 0 | K21: =+J21+H21 -> 0
... A26: =ELEC!C23 -> 43972 | D26: =(C26+B26)/2 -> 0 | G26: =F26*230 -> 0 | K26: =+J26+H26 -> 0
A27: =ELEC!C24 -> 43973 | D27: =(C27+B27)/2 -> 0 | G27: =F27*230 -> 0 | K27: =+J27+H27+I27 -> 0
A28: =ELEC!C25 -> 43974 | D28: =(C28+B28)/2 -> 0 | G28: =F28*230 -> 0 | K28: =+J28+H28+I28 -> 0
A29: =ELEC!C26 -> 43975 | D29: =(C29+B29)/2 -> 0 | G29: =F29*230 -> 0 | K29: =+J29+H29+I29 -> 0
A30: =ELEC!C27 -> 43976 | D30: =(C30+B30)/2 -> 0 | G30: =F30*230 -> 0 | K30: =+J30+H30+I30 -> 0
A31: =ELEC!C28 -> 43977 | D31: =(C31+B31)/2 -> 0 | G31: =F31*230 -> 0 | K31: =+J31+H31+I31 -> 0
A32: =ELEC!C29 -> 43978 | D32: =(C32+B32)/2 -> 0 | G32: =F32*230 -> 0 | K32: =+J32+H32+I32 -> 0
A33: =ELEC!C30 -> 43979 | D33: =(C33+B33)/2 -> 0 | G33: =F33*230 -> 0 | K33: =+J33+H33+I33 -> 0
A34: =ELEC!C31 -> 43980 | D34: =(C34+B34)/2 -> 0 | G34: =F34*230 -> 0 | K34: =+J34+H34+I34 -> 0
A35: =ELEC!C32 -> 43981 | D35: =(C35+B35)/2 -> 0 | G35: =F35*230 -> 0 | K35: =+J35+H35+I35 -> 0
A36: =ELEC!C33 -> 43982 | D36: =(C36+B36)/2 -> 0 | G36: =F36*230 -> 0 | K36: =+J36+H36+I36 -> 0
F37: =AVERAGE(F6:F36) -> 0.029325 | G37: =SUM(G6:G35) -> 26.979
D38: =SUM(D6:D36)/'EDl log'!A36 -> 19.25
I41: http://www.accuweather.com/en/lb/lebanon-weather

Sheet tanks
B2: Tank 1 | D2: Tank 2 | F2: Tank 3 | H2: Tank 4 | J2: Tank 5 | L2: Tank 6 | N2: Tank 7 | P2: Tank 8 | R2: Tank 9 | T2: Tank 10 | V2: Tank 11 | Z2: Tank 1 | AB2: Tank 2 | AD2: Tank 3 | AF2: Tank 4 | AH2: Tank 5 | AJ2: Tank 6 | AL2: Tank 7
B3: 6670 | D3: =SUM(B3) -> 6670 | F3: =SUM(D3) -> 6670 | H3: =SUM(F3) -> 6670 | J3: =SUM(H3) -> 6670 | L3: =SUM(J3) -> 6670 | N3: =SUM(L3) -> 6670 | P3: =SUM(N3) -> 6670 | R3: =SUM(P3) -> 6670 | T3: =SUM(R3) -> 6670 | V3: =SUM(T3) -> 6670 | W3: =SUM(B3:V3) -> 73370 | Z3: 2800 | AB3: 2800 | AD3: 2800 | AF3: 2800 | AH3: 2800 | AJ3: 2800 | AL3: 2800 | AM3: =SUM(Z3:AL3) -> 19600 | AO3: =SUM(AM3+W3) -> 92970 | AR3: Total sotck | AS3: Diesel Cons Per day | AT3: Diesel Delivery | BE3: Genset Co | BF3: Steam | BG3: Boil | BH3: Outdoor temperature
B4: =B3/310 -> 21.516129 | D4: =SUM(B4) -> 21.516129 | F4: =SUM(D4) -> 21.516129 | H4: =SUM(F4) -> 21.516129 | J4: =SUM(H4) -> 21.516129 | L4: =SUM(J4) -> 21.516129 | N4: =SUM(L4) -> 21.516129 | P4: =SUM(N4) -> 21.516129 | R4: =SUM(P4) -> 21.516129 | T4: =SUM(R4) -> 21.516129 | V4: =SUM(T4) -> 21.516129 | Z4: =Z3/280 -> 10 | AA4: =AA3/280 -> 0 | AB4: =AB3/280 -> 10 | AC4: =AC3/280 -> 0 | AD4: =AD3/280 -> 10 | AE4: =AE3/280 -> 0 | AF4: =AF3/280 -> 10 | AG4: =AG3/280 -> 0 | ... AL4: =AL3/280 -> 10 | AT4: Delivery | AU4: Cost /L | AW4: Boiler+Steam | AX4: Generator | AZ4: Occupancy | BA4: AVE TEPM | BB4: AVE Humidity
A5: =ELEC!C2 -> 43951 | B5: =[1]tanks!B35 -> 245.5 | C5: =[1]tanks!C35 -> 5282.2097 | D5: =[1]tanks!D35 -> 245.5 | E5: =[1]tanks!E35 -> 5282.2097 | F5: =[1]tanks!F35 -> 245.5 | G5: =[1]tanks!G35 -> 5282.2097 | H5: =[1]tanks!H35 -> 245.5 | I5: =[1]tanks!I35 -> 5282.2097 | ... AO5: =[1]tanks!AO35 -> 17570 | AP5: =[3]tanks!AP34 -> 0 | AQ5: =[1]tanks!$AQ$35 -> 0.81396479 | AR5: =[1]tanks!AR35 -> 75674.306 | AS5: =[1]tanks!AS35 -> -801.69355 | AT5: =[1]tanks!AT35 -> 0 | AU5: =[1]tanks!AU35 -> 0 | AV5: =[1]tanks!AV35 -> 0.284 | AW5: =[1]tanks!AW35 -> -281 | AX5: =[1]tanks!AX35 -> -520.69355 | AY5: =[1]tanks!AY35 -> -801.69355 | ... BA5: =[1]tanks!BA35 -> 21 | BB5: =[1]tanks!$BB$35 -> 0.75 | BC5: =[3]tanks!BC34 -> 0 | BD5: =[3]tanks!BD34 -> 19222 | BE5: =[3]tanks!BE34 -> #REF! | BF5: =[3]tanks!BF34 -> 0 | BG5: =[3]tanks!BG34 -> #REF! | BH5: =[3]tanks!BH34 -> 0
A6: =ELEC!C3 -> 43952 | B6: ='B5'!B5 -> 242 | C6: =B6*$B$4 -> 5206.9032 | D6: =SUM(B6) -> 242 | E6: =D6*$B$4 -> 5206.9032 | F6: =SUM(D6) -> 242 | G6: =F6*$B$4 -> 5206.9032 | H6: =SUM(F6) -> 242 | I6: =H6*$B$4 -> 5206.9032 | J6: =SUM(H6) -> 242 | K6: =J6*$B$4 -> 5206.9032 | L6: =SUM(J6) -> 242 | M6: =L6*$B$4 -> 5206.9032 | N6: =SUM(L6) -> 242 | O6: =N6*$B$4 -> 5206.9032 | P6: =SUM(N6) -> 242 | Q6: =P6*$B$4 -> 5206.9032 | R6: =SUM(P6) -> 242 | S6: =R6*$B$4 -> 5206.9032 | T6: =SUM(R6) -> 242 | U6: =T6*$B$4 -> 5206.9032 | V6: =SUM(T6) -> 242 | W6: =V6*$B$4 -> 5206.9032 | X6: =SUM(Y6/73370) -> 0.78064516 | Y6: =SUM(C6+E6+G6+I6+K6+M6+O6+Q6+S6+U6+W6) -> 57275.935 | Z6: ='B5'!C5 -> 248 | AA6: =SUM(Z6*$Z$4) -> 2480 | AB6: =SUM(Z6) -> 248 | AC6: =SUM(AB6*$Z$4) -> 2480 | AD6: =SUM(AB6) -> 248 | AE6: =SUM(AD6*$Z$4) -> 2480 | AF6: =SUM(AD6) -> 248 | AG6: =SUM(AF6*$Z$4) -> 2480 | AH6: =SUM(AF6) -> 248 | AI6: =SUM(AH6*$Z$4) -> 2480 | AJ6: =SUM(AH6) -> 248 | AK6: =SUM(AJ6*$Z$4) -> 2480 | AL6: =SUM(AJ6) -> 248 | AM6: =SUM(AL6*$Z$4) -> 2480 | AN6: =SUM(AO6/19600) -> 0.88571429 | AO6: =SUM(AA6+AC6+AE6+AG6+AI6+AK6+AM6) -> 17360 | AQ6: =SUM(AR6/92970) -> 0.80279591 | AR6: =SUM(AO6+Y6) -> 74635.935 | AS6: =SUM(AR6-AR5-AT6) -> -1039.371 | AT6: 1 | AV6: =IF(AT6>0,AU6,AV5) -> 0 | AW6: =-SUM('B5'!AI5) -> -349 | AX6: =-SUM(AW6-AS6) -> -690.37097 | AY6: =SUM(AX6+AW6) -> -1039.371 | AZ6: =ELEC!A3 -> 0.0435 | BA6: ='General information '!D6 -> 19 | BB6: =SUM('General information '!E6) -> 0.69 | BC6: =IF(AR3>=AR6,0,1) -> 0 | BD6: 19222 | BE6: =(305/1185)*ELEC!Q4 -> 394.827 | BG6: =#REF!-BE6 -> #REF! | BH6: 21
A7: =ELEC!C4 -> 43953 | B7: ='B5'!B6 -> 240 | C7: =B7*$B$4 -> 5163.871 | D7: =SUM(B7) -> 240 | E7: =D7*$B$4 -> 5163.871 | F7: =SUM(D7) -> 240 | G7: =F7*$B$4 -> 5163.871 | H7: =SUM(F7) -> 240 | I7: =H7*$B$4 -> 5163.871 | J7: =SUM(H7) -> 240 | K7: =J7*$B$4 -> 5163.871 | L7: =SUM(J7) -> 240 | M7: =L7*$B$4 -> 5163.871 | N7: =SUM(L7) -> 240 | O7: =N7*$B$4 -> 5163.871 | P7: =SUM(N7) -> 240 | Q7: =P7*$B$4 -> 5163.871 | R7: =SUM(P7) -> 240 | S7: =R7*$B$4 -> 5163.871 | T7: =SUM(R7) -> 240 | U7: =T7*$B$4 -> 5163.871 | V7: =SUM(T7) -> 240 | W7: =V7*$B$4 -> 5163.871 | X7: =SUM(Y7/73370) -> 0.77419355 | Y7: =SUM(C7+E7+G7+I7+K7+M7+O7+Q7+S7+U7+W7) -> 56802.581 | Z7: ='B5'!C6 -> 246 | AA7: =SUM(Z7*$Z$4) -> 2460 | AB7: =SUM(Z7) -> 246 | AC7: =SUM(AB7*$Z$4) -> 2460 | AD7: =SUM(AB7) -> 246 | AE7: =SUM(AD7*$Z$4) -> 2460 | AF7: =SUM(AD7) -> 246 | AG7: =SUM(AF7*$Z$4) -> 2460 | AH7: =SUM(AF7) -> 246 | AI7: =SUM(AH7*$Z$4) -> 2460 | AJ7: =SUM(AH7) -> 246 | AK7: =SUM(AJ7*$Z$4) -> 2460 | AL7: =SUM(AJ7) -> 246 | AM7: =SUM(AL7*$Z$4) -> 2460 | AN7: =SUM(AO7/19600) -> 0.87857143 | AO7: =SUM(AA7+AC7+AE7+AG7+AI7+AK7+AM7) -> 17220 | AQ7: =SUM(AR7/92970) -> 0.79619857 | AR7: =SUM(AO7+Y7) -> 74022.581 | AS7: =SUM(AR7-AR6-AT7) -> -613.35484 | AV7: =IF(AT7>0,AU7,AV6) -> 0 | AW7: =-SUM('B5'!AI6) -> -249 | AX7: =-SUM(AW7-AS7) -> -364.35484 | AY7: =SUM(AX7+AW7) -> -613.35484 | AZ7: =ELEC!A4 -> 0.039 | BA7: ='General information '!D7 -> 17.5 | BB7: =SUM('General information '!E7) -> 0.63 | BC7: 0 | BD7: 19222 | BE7: =(305/1185)*ELEC!Q5 -> 377.32489 | BG7: =#REF!-BE7 -> #REF! | BH7: 19
A8: =ELEC!C5 -> 43954 | B8: ='B5'!B7 -> 237 | C8: =B8*$B$4 -> 5099.3226 | D8: =SUM(B8) -> 237 | E8: =D8*$B$4 -> 5099.3226 | F8: =SUM(D8) -> 237 | G8: =F8*$B$4 -> 5099.3226 | H8: =SUM(F8) -> 237 | I8: =H8*$B$4 -> 5099.3226 | J8: =SUM(H8) -> 237 | K8: =J8*$B$4 -> 5099.3226 | L8: =SUM(J8) -> 237 | M8: =L8*$B$4 -> 5099.3226 | N8: =SUM(L8) -> 237 | O8: =N8*$B$4 -> 5099.3226 | P8: =SUM(N8) -> 237 | Q8: =P8*$B$4 -> 5099.3226 | R8: =SUM(P8) -> 237 | S8: =R8*$B$4 -> 5099.3226 | T8: =SUM(R8) -> 237 | U8: =T8*$B$4 -> 5099.3226 | V8: =SUM(T8) -> 237 | W8: =V8*$B$4 -> 5099.3226 | X8: =SUM(Y8/73370) -> 0.76451613 | Y8: =SUM(C8+E8+G8+I8+K8+M8+O8+Q8+S8+U8+W8) -> 56092.548 | Z8: ='B5'!C7 -> 243 | AA8: =SUM(Z8*$Z$4) -> 2430 | AB8: =SUM(Z8) -> 243 | AC8: =SUM(AB8*$Z$4) -> 2430 | AD8: =SUM(AB8) -> 243 | AE8: =SUM(AD8*$Z$4) -> 2430 | AF8: =SUM(AD8) -> 243 | AG8: =SUM(AF8*$Z$4) -> 2430 | AH8: =SUM(AF8) -> 243 | AI8: =SUM(AH8*$Z$4) -> 2430 | AJ8: =SUM(AH8) -> 243 | AK8: =SUM(AJ8*$Z$4) -> 2430 | AL8: =SUM(AJ8) -> 243 | AM8: =SUM(AL8*$Z$4) -> 2430 | AN8: =SUM(AO8/19600) -> 0.86785714 | AO8: =SUM(AA8+AC8+AE8+AG8+AI8+AK8+AM8) -> 17010 | AQ8: =SUM(AR8/92970) -> 0.78630255 | AR8: =SUM(AO8+Y8) -> 73102.548 | AS8: =SUM(AR8-AR7-AT8) -> -920.03226 | AV8: =IF(AT8>0,AU8,AV7) -> 0 | AW8: =-SUM('B5'!AI7) -> -288.5 | AX8: =-SUM(AW8-AS8) -> -631.53226 | AY8: =SUM(AX8+AW8) -> -920.03226 | AZ8: =ELEC!A5 -> 0.0261 | BA8: ='General information '!D8 -> 20.5 | BB8: =SUM('General information '!E8) -> 0.7 | BC8: =IF(AR7>=AR8,0,1) -> 0 | BD8: 19222 | BE8: =(305/1185)*ELEC!Q6 -> 257.38397 | BG8: =#REF!-BE8 -> #REF! | BH8: 16
A9: =ELEC!C6 -> 43955 | B9: ='B5'!B8 -> 232 | C9: =B9*$B$4 -> 4991.7419 | D9: =SUM(B9) -> 232 | E9: =D9*$B$4 -> 4991.7419 | F9: =SUM(D9) -> 232 | G9: =F9*$B$4 -> 4991.7419 | H9: =SUM(F9) -> 232 | I9: =H9*$B$4 -> 4991.7419 | J9: =SUM(H9) -> 232 | K9: =J9*$B$4 -> 4991.7419 | L9: =SUM(J9) -> 232 | M9: =L9*$B$4 -> 4991.7419 | N9: =SUM(L9) -> 232 | O9: =N9*$B$4 -> 4991.7419 | P9: =SUM(N9) -> 232 | Q9: =P9*$B$4 -> 4991.7419 | R9: =SUM(P9) -> 232 | S9: =R9*$B$4 -> 4991.7419 | T9: =SUM(R9) -> 232 | U9: =T9*$B$4 -> 4991.7419 | V9: =SUM(T9) -> 232 | W9: =V9*$B$4 -> 4991.7419 | X9: =SUM(Y9/73370) -> 0.7483871 | Y9: =SUM(C9+E9+G9+I9+K9+M9+O9+Q9+S9+U9+W9) -> 54909.161 | Z9: ='B5'!C8 -> 239 | AA9: =SUM(Z9*$Z$4) -> 2390 | AB9: =SUM(Z9) -> 239 | AC9: =SUM(AB9*$Z$4) -> 2390 | AD9: =SUM(AB9) -> 239 | AE9: =SUM(AD9*$Z$4) -> 2390 | AF9: =SUM(AD9) -> 239 | AG9: =SUM(AF9*$Z$4) -> 2390 | AH9: =SUM(AF9) -> 239 | AI9: =SUM(AH9*$Z$4) -> 2390 | AJ9: =SUM(AH9) -> 239 | AK9: =SUM(AJ9*$Z$4) -> 2390 | AL9: =SUM(AJ9) -> 239 | AM9: =SUM(AL9*$Z$4) -> 2390 | AN9: =SUM(AO9/19600) -> 0.85357143 | AO9: =SUM(AA9+AC9+AE9+AG9+AI9+AK9+AM9) -> 16730 | AQ9: =SUM(AR9/92970) -> 0.77056213 | AR9: =SUM(AO9+Y9) -> 71639.161 | AS9: =SUM(AR9-AR8-AT9) -> -1463.3871 | AV9: =IF(AT9>0,AU9,AV8) -> 0 | AW9: =-SUM('B5'!AI8) -> -657.9 | AX9: =-SUM(AW9-AS9) -> -805.4871 | AY9: =SUM(AX9+AW9) -> -1463.3871 | AZ9: =ELEC!A6 -> 0.0087 | BA9: ='General information '!D9 -> 20 | BB9: =SUM('General information '!E9) -> 0.71 | BC9: =IF(AR8>=AR9,0,1) -> 0 | BD9: 19222 | BE9: =(305/1185)*ELEC!Q7 -> 0 | BG9: =#REF!-BE9 -> #REF! | BH9: 18
A10: =ELEC!C7 -> 43956 | B10: ='B5'!B9 -> 232 | C10: =B10*$B$4 -> 4991.7419 | D10: =SUM(B10) -> 232 | E10: =D10*$B$4 -> 4991.7419 | F10: =SUM(D10) -> 232 | G10: =F10*$B$4 -> 4991.7419 | H10: =SUM(F10) -> 232 | I10: =H10*$B$4 -> 4991.7419 | J10: =SUM(H10) -> 232 | K10: =J10*$B$4 -> 4991.7419 | L10: =SUM(J10) -> 232 | M10: =L10*$B$4 -> 4991.7419 | N10: =SUM(L10) -> 232 | O10: =N10*$B$4 -> 4991.7419 | P10: =SUM(N10) -> 232 | Q10: =P10*$B$4 -> 4991.7419 | R10: =SUM(P10) -> 232 | S10: =R10*$B$4 -> 4991.7419 | T10: =SUM(R10) -> 232 | U10: =T10*$B$4 -> 4991.7419 | V10: =SUM(T10) -> 232 | W10: =V10*$B$4 -> 4991.7419 | X10: =SUM(Y10/73370) -> 0.7483871 | Y10: =SUM(C10+E10+G10+I10+K10+M10+O10+Q10+S10+U10+W10) -> 54909.161 | Z10: ='B5'!C9 -> 239 | AA10: =SUM(Z10*$Z$4) -> 2390 | AB10: =SUM(Z10) -> 239 | AC10: =SUM(AB10*$Z$4) -> 2390 | AD10: =SUM(AB10) -> 239 | AE10: =SUM(AD10*$Z$4) -> 2390 | AF10: =SUM(AD10) -> 239 | AG10: =SUM(AF10*$Z$4) -> 2390 | AH10: =SUM(AF10) -> 239 | AI10: =SUM(AH10*$Z$4) -> 2390 | AJ10: =SUM(AH10) -> 239 | AK10: =SUM(AJ10*$Z$4) -> 2390 | AL10: =SUM(AJ10) -> 239 | AM10: =SUM(AL10*$Z$4) -> 2390 | AN10: =SUM(AO10/19600) -> 0.85357143 | AO10: =SUM(AA10+AC10+AE10+AG10+AI10+AK10+AM10) -> 16730 | AQ10: =SUM(AR10/92970) -> 0.77056213 | AR10: =SUM(AO10+Y10) -> 71639.161 | AS10: =SUM(AR10-AR9-AT10) -> 0 | AV10: =IF(AT10>0,AU10,AV9) -> 0 | AW10: =-SUM('B5'!AI9) -> 0 | AX10: =-SUM(AW10-AS10) -> 0 | AY10: =SUM(AX10+AW10) -> 0 | AZ10: =ELEC!A7 -> 0 | BA10: ='General information '!D10 -> 0 | BB10: =SUM('General information '!E10) -> 0 | BC10: =IF(AR9>=AR10,0,1) -> 0 | BD10: 19222 | BE10: =(305/1185)*ELEC!Q8 -> 0 | BG10: =#REF!-BE10 -> #REF! | BH10: 16
A11: =ELEC!C8 -> 43957 | B11: ='B5'!B10 -> 232 | C11: =B11*$B$4 -> 4991.7419 | D11: =SUM(B11) -> 232 | E11: =D11*$B$4 -> 4991.7419 | F11: =SUM(D11) -> 232 | G11: =F11*$B$4 -> 4991.7419 | H11: =SUM(F11) -> 232 | I11: =H11*$B$4 -> 4991.7419 | J11: =SUM(H11) -> 232 | K11: =J11*$B$4 -> 4991.7419 | L11: =SUM(J11) -> 232 | M11: =L11*$B$4 -> 4991.7419 | N11: =SUM(L11) -> 232 | O11: =N11*$B$4 -> 4991.7419 | P11: =SUM(N11) -> 232 | Q11: =P11*$B$4 -> 4991.7419 | R11: =SUM(P11) -> 232 | S11: =R11*$B$4 -> 4991.7419 | T11: =SUM(R11) -> 232 | U11: =T11*$B$4 -> 4991.7419 | V11: =SUM(T11) -> 232 | W11: =V11*$B$4 -> 4991.7419 | X11: =SUM(Y11/73370) -> 0.7483871 | Y11: =SUM(C11+E11+G11+I11+K11+M11+O11+Q11+S11+U11+W11) -> 54909.161 | Z11: ='B5'!C10 -> 239 | AA11: =SUM(Z11*$Z$4) -> 2390 | AB11: =SUM(Z11) -> 239 | AC11: =SUM(AB11*$Z$4) -> 2390 | AD11: =SUM(AB11) -> 239 | AE11: =SUM(AD11*$Z$4) -> 2390 | AF11: =SUM(AD11) -> 239 | AG11: =SUM(AF11*$Z$4) -> 2390 | AH11: =SUM(AF11) -> 239 | AI11: =SUM(AH11*$Z$4) -> 2390 | AJ11: =SUM(AH11) -> 239 | AK11: =SUM(AJ11*$Z$4) -> 2390 | AL11: =SUM(AJ11) -> 239 | AM11: =SUM(AL11*$Z$4) -> 2390 | AN11: =SUM(AO11/19600) -> 0.85357143 | AO11: =SUM(AA11+AC11+AE11+AG11+AI11+AK11+AM11) -> 16730 | AQ11: =SUM(AR11/92970) -> 0.77056213 | AR11: =SUM(AO11+Y11) -> 71639.161 | AS11: =SUM(AR11-AR10-AT11) -> 0 | AV11: =IF(AT11>0,AU11,AV10) -> 0 | AW11: =-SUM('B5'!AI10) -> 0 | AX11: =-SUM(AW11-AS11) -> 0 | AY11: =SUM(AX11+AW11) -> 0 | AZ11: =ELEC!A8 -> 0 | BA11: ='General information '!D11 -> 0 | BB11: =SUM('General information '!E11) -> 0 | BC11: =IF(AR10>=AR11,0,1) -> 0 | BD11: 19222 | BE11: =(305/1185)*ELEC!Q9 -> 0 | BG11: =#REF!-BE11 -> #REF! | BH11: 16.5
A12: =ELEC!C9 -> 43958 | B12: ='B5'!B11 -> 232 | C12: =B12*$B$4 -> 4991.7419 | D12: =SUM(B12) -> 232 | E12: =D12*$B$4 -> 4991.7419 | F12: =SUM(D12) -> 232 | G12: =F12*$B$4 -> 4991.7419 | H12: =SUM(F12) -> 232 | I12: =H12*$B$4 -> 4991.7419 | J12: =SUM(H12) -> 232 | K12: =J12*$B$4 -> 4991.7419 | L12: =SUM(J12) -> 232 | M12: =L12*$B$4 -> 4991.7419 | N12: =SUM(L12) -> 232 | O12: =N12*$B$4 -> 4991.7419 | P12: =SUM(N12) -> 232 | Q12: =P12*$B$4 -> 4991.7419 | R12: =SUM(P12) -> 232 | S12: =R12*$B$4 -> 4991.7419 | T12: =SUM(R12) -> 232 | U12: =T12*$B$4 -> 4991.7419 | V12: =SUM(T12) -> 232 | W12: =V12*$B$4 -> 4991.7419 | X12: =SUM(Y12/73370) -> 0.7483871 | Y12: =SUM(C12+E12+G12+I12+K12+M12+O12+Q12+S12+U12+W12) -> 54909.161 | Z12: ='B5'!C11 -> 239 | AA12: =SUM(Z12*$Z$4) -> 2390 | AB12: =SUM(Z12) -> 239 | AC12: =SUM(AB12*$Z$4) -> 2390 | AD12: =SUM(AB12) -> 239 | AE12: =SUM(AD12*$Z$4) -> 2390 | AF12: =SUM(AD12) -> 239 | AG12: =SUM(AF12*$Z$4) -> 2390 | AH12: =SUM(AF12) -> 239 | AI12: =SUM(AH12*$Z$4) -> 2390 | AJ12: =SUM(AH12) -> 239 | AK12: =SUM(AJ12*$Z$4) -> 2390 | AL12: =SUM(AJ12) -> 239 | AM12: =SUM(AL12*$Z$4) -> 2390 | AN12: =SUM(AO12/19600) -> 0.85357143 | AO12: =SUM(AA12+AC12+AE12+AG12+AI12+AK12+AM12) -> 16730 | AQ12: =SUM(AR12/92970) -> 0.77056213 | AR12: =SUM(AO12+Y12) -> 71639.161 | AS12: =SUM(AR12-AR11-AT12) -> 0 | AV12: =IF(AT12>0,AU12,AV11) -> 0 | AW12: =-SUM('B5'!AI11) -> 0 | AX12: =-SUM(AW12-AS12) -> 0 | AY12: =SUM(AX12+AW12) -> 0 | AZ12: =ELEC!A9 -> 0 | BA12: ='General information '!D12 -> 0 | BB12: =SUM('General information '!E12) -> 0 | BC12: =IF(AR11>=AR12,0,1) -> 0 | BD12: 19222 | BE12: =(305/1185)*ELEC!Q10 -> 0 | BG12: =#REF!-BE12 -> #REF! | BH12: 15.5
A13: =ELEC!C10 -> 43959 | B13: ='B5'!B12 -> 232 | C13: =B13*$B$4 -> 4991.7419 | D13: =SUM(B13) -> 232 | E13: =D13*$B$4 -> 4991.7419 | F13: =SUM(D13) -> 232 | G13: =F13*$B$4 -> 4991.7419 | H13: =SUM(F13) -> 232 | I13: =H13*$B$4 -> 4991.7419 | J13: =SUM(H13) -> 232 | K13: =J13*$B$4 -> 4991.7419 | L13: =SUM(J13) -> 232 | M13: =L13*$B$4 -> 4991.7419 | N13: =SUM(L13) -> 232 | O13: =N13*$B$4 -> 4991.7419 | P13: =SUM(N13) -> 232 | Q13: =P13*$B$4 -> 4991.7419 | R13: =SUM(P13) -> 232 | S13: =R13*$B$4 -> 4991.7419 | T13: =SUM(R13) -> 232 | U13: =T13*$B$4 -> 4991.7419 | V13: =SUM(T13) -> 232 | W13: =V13*$B$4 -> 4991.7419 | X13: =SUM(Y13/73370) -> 0.7483871 | Y13: =SUM(C13+E13+G13+I13+K13+M13+O13+Q13+S13+U13+W13) -> 54909.161 | Z13: ='B5'!C12 -> 239 | AA13: =SUM(Z13*$Z$4) -> 2390 | AB13: =SUM(Z13) -> 239 | AC13: =SUM(AB13*$Z$4) -> 2390 | AD13: =SUM(AB13) -> 239 | AE13: =SUM(AD13*$Z$4) -> 2390 | AF13: =SUM(AD13) -> 239 | AG13: =SUM(AF13*$Z$4) -> 2390 | AH13: =SUM(AF13) -> 239 | AI13: =SUM(AH13*$Z$4) -> 2390 | AJ13: =SUM(AH13) -> 239 | AK13: =SUM(AJ13*$Z$4) -> 2390 | AL13: =SUM(AJ13) -> 239 | AM13: =SUM(AL13*$Z$4) -> 2390 | AN13: =SUM(AO13/19600) -> 0.85357143 | AO13: =SUM(AA13+AC13+AE13+AG13+AI13+AK13+AM13) -> 16730 | AQ13: =SUM(AR13/92970) -> 0.77056213 | AR13: =SUM(AO13+Y13) -> 71639.161 | AS13: =SUM(AR13-AR12-AT13) -> 0 | AV13: =IF(AT13>0,AU13,AV12) -> 0 | AW13: =-SUM('B5'!AI12) -> 0 | AX13: =-SUM(AW13-AS13) -> 0 | AY13: =SUM(AX13+AW13) -> 0 | AZ13: =ELEC!A10 -> 0 | BA13: ='General information '!D13 -> 0 | BB13: =SUM('General information '!E13) -> 0 | BC13: =IF(AR12>=AR13,0,1) -> 0 | BD13: 19222 | BE13: =(305/1185)*ELEC!Q11 -> 0 | BG13: =#REF!-BE13 -> #REF!
A14: =ELEC!C11 -> 43960 | B14: ='B5'!B13 -> 232 | C14: =B14*$B$4 -> 4991.7419 | D14: =SUM(B14) -> 232 | E14: =D14*$B$4 -> 4991.7419 | F14: =SUM(D14) -> 232 | G14: =F14*$B$4 -> 4991.7419 | H14: =SUM(F14) -> 232 | I14: =H14*$B$4 -> 4991.7419 | J14: =SUM(H14) -> 232 | K14: =J14*$B$4 -> 4991.7419 | L14: =SUM(J14) -> 232 | M14: =L14*$B$4 -> 4991.7419 | N14: =SUM(L14) -> 232 | O14: =N14*$B$4 -> 4991.7419 | P14: =SUM(N14) -> 232 | Q14: =P14*$B$4 -> 4991.7419 | R14: =SUM(P14) -> 232 | S14: =R14*$B$4 -> 4991.7419 | T14: =SUM(R14) -> 232 | U14: =T14*$B$4 -> 4991.7419 | V14: =SUM(T14) -> 232 | W14: =V14*$B$4 -> 4991.7419 | X14: =SUM(Y14/73370) -> 0.7483871 | Y14: =SUM(C14+E14+G14+I14+K14+M14+O14+Q14+S14+U14+W14) -> 54909.161 | Z14: ='B5'!C13 -> 239 | AA14: =SUM(Z14*$Z$4) -> 2390 | AB14: =SUM(Z14) -> 239 | AC14: =SUM(AB14*$Z$4) -> 2390 | AD14: =SUM(AB14) -> 239 | AE14: =SUM(AD14*$Z$4) -> 2390 | AF14: =SUM(AD14) -> 239 | AG14: =SUM(AF14*$Z$4) -> 2390 | AH14: =SUM(AF14) -> 239 | AI14: =SUM(AH14*$Z$4) -> 2390 | AJ14: =SUM(AH14) -> 239 | AK14: =SUM(AJ14*$Z$4) -> 2390 | AL14: =SUM(AJ14) -> 239 | AM14: =SUM(AL14*$Z$4) -> 2390 | AN14: =SUM(AO14/19600) -> 0.85357143 | AO14: =SUM(AA14+AC14+AE14+AG14+AI14+AK14+AM14) -> 16730 | AQ14: =SUM(AR14/92970) -> 0.77056213 | AR14: =SUM(AO14+Y14) -> 71639.161 | AS14: =SUM(AR14-AR13-AT14) -> 0 | AV14: =IF(AT14>0,AU14,AV13) -> 0 | AW14: =-SUM('B5'!AI13) -> 0 | AX14: =-SUM(AW14-AS14) -> 0 | AY14: =SUM(AX14+AW14) -> 0 | AZ14: =ELEC!A11 -> 0 | BA14: ='General information '!D14 -> 0 | BB14: =SUM('General information '!E14) -> 0 | BC14: =IF(AR13>=AR14,0,1) -> 0 | BD14: 19222 | BE14: =(305/1185)*ELEC!Q12 -> 0 | BG14: =#REF!-BE14 -> #REF!
A15: =ELEC!C12 -> 43961 | B15: ='B5'!B14 -> 232 | C15: =B15*$B$4 -> 4991.7419 | D15: =SUM(B15) -> 232 | E15: =D15*$B$4 -> 4991.7419 | F15: =SUM(D15) -> 232 | G15: =F15*$B$4 -> 4991.7419 | H15: =SUM(F15) -> 232 | I15: =H15*$B$4 -> 4991.7419 | J15: =SUM(H15) -> 232 | K15: =J15*$B$4 -> 4991.7419 | L15: =SUM(J15) -> 232 | M15: =L15*$B$4 -> 4991.7419 | N15: =SUM(L15) -> 232 | O15: =N15*$B$4 -> 4991.7419 | P15: =SUM(N15) -> 232 | Q15: =P15*$B$4 -> 4991.7419 | R15: =SUM(P15) -> 232 | S15: =R15*$B$4 -> 4991.7419 | T15: =SUM(R15) -> 232 | U15: =T15*$B$4 -> 4991.7419 | V15: =SUM(T15) -> 232 | W15: =V15*$B$4 -> 4991.7419 | X15: =SUM(Y15/73370) -> 0.7483871 | Y15: =SUM(C15+E15+G15+I15+K15+M15+O15+Q15+S15+U15+W15) -> 54909.161 | Z15: ='B5'!C14 -> 239 | AA15: =SUM(Z15*$Z$4) -> 2390 | AB15: =SUM(Z15) -> 239 | AC15: =SUM(AB15*$Z$4) -> 2390 | AD15: =SUM(AB15) -> 239 | AE15: =SUM(AD15*$Z$4) -> 2390 | AF15: =SUM(AD15) -> 239 | AG15: =SUM(AF15*$Z$4) -> 2390 | AH15: =SUM(AF15) -> 239 | AI15: =SUM(AH15*$Z$4) -> 2390 | AJ15: =SUM(AH15) -> 239 | AK15: =SUM(AJ15*$Z$4) -> 2390 | AL15: =SUM(AJ15) -> 239 | AM15: =SUM(AL15*$Z$4) -> 2390 | AN15: =SUM(AO15/19600) -> 0.85357143 | AO15: =SUM(AA15+AC15+AE15+AG15+AI15+AK15+AM15) -> 16730 | AQ15: =SUM(AR15/92970) -> 0.77056213 | AR15: =SUM(AO15+Y15) -> 71639.161 | AS15: =SUM(AR15-AR14-AT15) -> 0 | AV15: =IF(AT15>0,AU15,AV14) -> 0 | AW15: =-SUM('B5'!AI14) -> 0 | AX15: =-SUM(AW15-AS15) -> 0 | AY15: =SUM(AX15+AW15) -> 0 | AZ15: =ELEC!A12 -> 0 | BA15: ='General information '!D15 -> 0 | BB15: =SUM('General information '!E15) -> 0 | BC15: =IF(AR14>=AR15,0,1) -> 0 | BD15: 19222 | BE15: =(305/1185)*ELEC!Q13 -> 0 | BG15: =#REF!-BE15 -> #REF!
A16: =ELEC!C13 -> 43962 | B16: ='B5'!B15 -> 232 | C16: =B16*$B$4 -> 4991.7419 | D16: =SUM(B16) -> 232 | E16: =D16*$B$4 -> 4991.7419 | F16: =SUM(D16) -> 232 | G16: =F16*$B$4 -> 4991.7419 | H16: =SUM(F16) -> 232 | I16: =H16*$B$4 -> 4991.7419 | J16: =SUM(H16) -> 232 | K16: =J16*$B$4 -> 4991.7419 | L16: =SUM(J16) -> 232 | M16: =L16*$B$4 -> 4991.7419 | N16: =SUM(L16) -> 232 | O16: =N16*$B$4 -> 4991.7419 | P16: =SUM(N16) -> 232 | Q16: =P16*$B$4 -> 4991.7419 | R16: =SUM(P16) -> 232 | S16: =R16*$B$4 -> 4991.7419 | T16: =SUM(R16) -> 232 | U16: =T16*$B$4 -> 4991.7419 | V16: =SUM(T16) -> 232 | W16: =V16*$B$4 -> 4991.7419 | X16: =SUM(Y16/73370) -> 0.7483871 | Y16: =SUM(C16+E16+G16+I16+K16+M16+O16+Q16+S16+U16+W16) -> 54909.161 | Z16: ='B5'!C15 -> 239 | AA16: =SUM(Z16*$Z$4) -> 2390 | AB16: =SUM(Z16) -> 239 | AC16: =SUM(AB16*$Z$4) -> 2390 | AD16: =SUM(AB16) -> 239 | AE16: =SUM(AD16*$Z$4) -> 2390 | AF16: =SUM(AD16) -> 239 | AG16: =SUM(AF16*$Z$4) -> 2390 | AH16: =SUM(AF16) -> 239 | AI16: =SUM(AH16*$Z$4) -> 2390 | AJ16: =SUM(AH16) -> 239 | AK16: =SUM(AJ16*$Z$4) -> 2390 | AL16: =SUM(AJ16) -> 239 | AM16: =SUM(AL16*$Z$4) -> 2390 | AN16: =SUM(AO16/19600) -> 0.85357143 | AO16: =SUM(AA16+AC16+AE16+AG16+AI16+AK16+AM16) -> 16730 | AQ16: =SUM(AR16/92970) -> 0.77056213 | AR16: =SUM(AO16+Y16) -> 71639.161 | AS16: =SUM(AR16-AR15-AT16) -> 0 | AV16: =IF(AT16>0,AU16,AV15) -> 0 | AW16: =-SUM('B5'!AI15) -> 0 | AX16: =-SUM(AW16-AS16) -> 0 | AY16: =SUM(AX16+AW16) -> 0 | AZ16: =ELEC!A13 -> 0 | BA16: ='General information '!D16 -> 0 | BB16: =SUM('General information '!E16) -> 0 | BC16: =IF(AR15>=AR16,0,1) -> 0 | BD16: 19222 | BE16: =(305/1185)*ELEC!Q14 -> 0 | BG16: =#REF!-BE16 -> #REF!
A17: =ELEC!C14 -> 43963 | B17: ='B5'!B16 -> 232 | C17: =B17*$B$4 -> 4991.7419 | D17: =SUM(B17) -> 232 | E17: =D17*$B$4 -> 4991.7419 | F17: =SUM(D17) -> 232 | G17: =F17*$B$4 -> 4991.7419 | H17: =SUM(F17) -> 232 | I17: =H17*$B$4 -> 4991.7419 | J17: =SUM(H17) -> 232 | K17: =J17*$B$4 -> 4991.7419 | L17: =SUM(J17) -> 232 | M17: =L17*$B$4 -> 4991.7419 | N17: =SUM(L17) -> 232 | O17: =N17*$B$4 -> 4991.7419 | P17: =SUM(N17) -> 232 | Q17: =P17*$B$4 -> 4991.7419 | R17: =SUM(P17) -> 232 | S17: =R17*$B$4 -> 4991.7419 | T17: =SUM(R17) -> 232 | U17: =T17*$B$4 -> 4991.7419 | V17: =SUM(T17) -> 232 | W17: =V17*$B$4 -> 4991.7419 | X17: =SUM(Y17/73370) -> 0.7483871 | Y17: =SUM(C17+E17+G17+I17+K17+M17+O17+Q17+S17+U17+W17) -> 54909.161 | Z17: ='B5'!C16 -> 239 | AA17: =SUM(Z17*$Z$4) -> 2390 | AB17: =SUM(Z17) -> 239 | AC17: =SUM(AB17*$Z$4) -> 2390 | AD17: =SUM(AB17) -> 239 | AE17: =SUM(AD17*$Z$4) -> 2390 | AF17: =SUM(AD17) -> 239 | AG17: =SUM(AF17*$Z$4) -> 2390 | AH17: =SUM(AF17) -> 239 | AI17: =SUM(AH17*$Z$4) -> 2390 | AJ17: =SUM(AH17) -> 239 | AK17: =SUM(AJ17*$Z$4) -> 2390 | AL17: =SUM(AJ17) -> 239 | AM17: =SUM(AL17*$Z$4) -> 2390 | AN17: =SUM(AO17/19600) -> 0.85357143 | AO17: =SUM(AA17+AC17+AE17+AG17+AI17+AK17+AM17) -> 16730 | AQ17: =SUM(AR17/92970) -> 0.77056213 | AR17: =SUM(AO17+Y17) -> 71639.161 | AS17: =SUM(AR17-AR16-AT17) -> 0 | AV17: =IF(AT17>0,AU17,AV16) -> 0 | AW17: =-SUM('B5'!AI16) -> 0 | AX17: =-SUM(AW17-AS17) -> 0 | AY17: =SUM(AX17+AW17) -> 0 | AZ17: =ELEC!A14 -> 0 | BA17: ='General information '!D17 -> 0 | BB17: =SUM('General information '!E17) -> 0 | BC17: =IF(AR16>=AR17,0,1) -> 0 | BD17: 19222 | BE17: =(305/1185)*ELEC!Q15 -> 0 | BG17: =#REF!-BE17 -> #REF!
A18: =ELEC!C15 -> 43964 | B18: ='B5'!B17 -> 232 | C18: =B18*$B$4 -> 4991.7419 | D18: =SUM(B18) -> 232 | E18: =D18*$B$4 -> 4991.7419 | F18: =SUM(D18) -> 232 | G18: =F18*$B$4 -> 4991.7419 | H18: =SUM(F18) -> 232 | I18: =H18*$B$4 -> 4991.7419 | J18: =SUM(H18) -> 232 | K18: =J18*$B$4 -> 4991.7419 | L18: =SUM(J18) -> 232 | M18: =L18*$B$4 -> 4991.7419 | N18: =SUM(L18) -> 232 | O18: =N18*$B$4 -> 4991.7419 | P18: =SUM(N18) -> 232 | Q18: =P18*$B$4 -> 4991.7419 | R18: =SUM(P18) -> 232 | S18: =R18*$B$4 -> 4991.7419 | T18: =SUM(R18) -> 232 | U18: =T18*$B$4 -> 4991.7419 | V18: =SUM(T18) -> 232 | W18: =V18*$B$4 -> 4991.7419 | X18: =SUM(Y18/73370) -> 0.7483871 | Y18: =SUM(C18+E18+G18+I18+K18+M18+O18+Q18+S18+U18+W18) -> 54909.161 | Z18: ='B5'!C17 -> 239 | AA18: =SUM(Z18*$Z$4) -> 2390 | AB18: =SUM(Z18) -> 239 | AC18: =SUM(AB18*$Z$4) -> 2390 | AD18: =SUM(AB18) -> 239 | AE18: =SUM(AD18*$Z$4) -> 2390 | AF18: =SUM(AD18) -> 239 | AG18: =SUM(AF18*$Z$4) -> 2390 | AH18: =SUM(AF18) -> 239 | AI18: =SUM(AH18*$Z$4) -> 2390 | AJ18: =SUM(AH18) -> 239 | AK18: =SUM(AJ18*$Z$4) -> 2390 | AL18: =SUM(AJ18) -> 239 | AM18: =SUM(AL18*$Z$4) -> 2390 | AN18: =SUM(AO18/19600) -> 0.85357143 | AO18: =SUM(AA18+AC18+AE18+AG18+AI18+AK18+AM18) -> 16730 | AQ18: =SUM(AR18/92970) -> 0.77056213 | AR18: =SUM(AO18+Y18) -> 71639.161 | AS18: =SUM(AR18-AR17-AT18) -> 0 | AV18: =IF(AT18>0,AU18,AV17) -> 0 | AW18: =-SUM('B5'!AI17) -> 0 | AX18: =-SUM(AW18-AS18) -> 0 | AY18: =SUM(AX18+AW18) -> 0 | AZ18: =ELEC!A15 -> 0 | BA18: ='General information '!D18 -> 0 | BB18: =SUM('General information '!E18) -> 0 | BC18: =IF(AR17>=AR18,0,1) -> 0 | BD18: 19222 | BE18: =(305/1185)*ELEC!Q16 -> 0 | BG18: =#REF!-BE18 -> #REF!
A19: =ELEC!C16 -> 43965 | B19: ='B5'!B18 -> 232 | C19: =B19*$B$4 -> 4991.7419 | D19: =SUM(B19) -> 232 | E19: =D19*$B$4 -> 4991.7419 | F19: =SUM(D19) -> 232 | G19: =F19*$B$4 -> 4991.7419 | H19: =SUM(F19) -> 232 | I19: =H19*$B$4 -> 4991.7419 | J19: =SUM(H19) -> 232 | K19: =J19*$B$4 -> 4991.7419 | L19: =SUM(J19) -> 232 | M19: =L19*$B$4 -> 4991.7419 | N19: =SUM(L19) -> 232 | O19: =N19*$B$4 -> 4991.7419 | P19: =SUM(N19) -> 232 | Q19: =P19*$B$4 -> 4991.7419 | R19: =SUM(P19) -> 232 | S19: =R19*$B$4 -> 4991.7419 | T19: =SUM(R19) -> 232 | U19: =T19*$B$4 -> 4991.7419 | V19: =SUM(T19) -> 232 | W19: =V19*$B$4 -> 4991.7419 | X19: =SUM(Y19/73370) -> 0.7483871 | Y19: =SUM(C19+E19+G19+I19+K19+M19+O19+Q19+S19+U19+W19) -> 54909.161 | Z19: ='B5'!C18 -> 239 | AA19: =SUM(Z19*$Z$4) -> 2390 | AB19: =SUM(Z19) -> 239 | AC19: =SUM(AB19*$Z$4) -> 2390 | AD19: =SUM(AB19) -> 239 | AE19: =SUM(AD19*$Z$4) -> 2390 | AF19: =SUM(AD19) -> 239 | AG19: =SUM(AF19*$Z$4) -> 2390 | AH19: =SUM(AF19) -> 239 | AI19: =SUM(AH19*$Z$4) -> 2390 | AJ19: =SUM(AH19) -> 239 | AK19: =SUM(AJ19*$Z$4) -> 2390 | AL19: =SUM(AJ19) -> 239 | AM19: =SUM(AL19*$Z$4) -> 2390 | AN19: =SUM(AO19/19600) -> 0.85357143 | AO19: =SUM(AA19+AC19+AE19+AG19+AI19+AK19+AM19) -> 16730 | AQ19: =SUM(AR19/92970) -> 0.77056213 | AR19: =SUM(AO19+Y19) -> 71639.161 | AS19: =SUM(AR19-AR18-AT19) -> 0 | AV19: =IF(AT19>0,AU19,AV18) -> 0 | AW19: =-SUM('B5'!AI18) -> 0 | AX19: =-SUM(AW19-AS19) -> 0 | AY19: =SUM(AX19+AW19) -> 0 | AZ19: =ELEC!A16 -> 0 | BA19: ='General information '!D19 -> 0 | BB19: =SUM('General information '!E19) -> 0 | BC19: =IF(AR18>=AR19,0,1) -> 0 | BD19: 19222 | BE19: =(305/1185)*ELEC!Q17 -> 0 | BG19: =#REF!-BE19 -> #REF!
A20: =ELEC!C17 -> 43966 | B20: ='B5'!B19 -> 232 | C20: =B20*$B$4 -> 4991.7419 | D20: =SUM(B20) -> 232 | E20: =D20*$B$4 -> 4991.7419 | F20: =SUM(D20) -> 232 | G20: =F20*$B$4 -> 4991.7419 | H20: =SUM(F20) -> 232 | I20: =H20*$B$4 -> 4991.7419 | J20: =SUM(H20) -> 232 | K20: =J20*$B$4 -> 4991.7419 | L20: =SUM(J20) -> 232 | M20: =L20*$B$4 -> 4991.7419 | N20: =SUM(L20) -> 232 | O20: =N20*$B$4 -> 4991.7419 | P20: =SUM(N20) -> 232 | Q20: =P20*$B$4 -> 4991.7419 | R20: =SUM(P20) -> 232 | S20: =R20*$B$4 -> 4991.7419 | T20: =SUM(R20) -> 232 | U20: =T20*$B$4 -> 4991.7419 | V20: =SUM(T20) -> 232 | W20: =V20*$B$4 -> 4991.7419 | X20: =SUM(Y20/73370) -> 0.7483871 | Y20: =SUM(C20+E20+G20+I20+K20+M20+O20+Q20+S20+U20+W20) -> 54909.161 | Z20: ='B5'!C19 -> 239 | AA20: =SUM(Z20*$Z$4) -> 2390 | AB20: =SUM(Z20) -> 239 | AC20: =SUM(AB20*$Z$4) -> 2390 | AD20: =SUM(AB20) -> 239 | AE20: =SUM(AD20*$Z$4) -> 2390 | AF20: =SUM(AD20) -> 239 | AG20: =SUM(AF20*$Z$4) -> 2390 | AH20: =SUM(AF20) -> 239 | AI20: =SUM(AH20*$Z$4) -> 2390 | AJ20: =SUM(AH20) -> 239 | AK20: =SUM(AJ20*$Z$4) -> 2390 | AL20: =SUM(AJ20) -> 239 | AM20: =SUM(AL20*$Z$4) -> 2390 | AN20: =SUM(AO20/19600) -> 0.85357143 | AO20: =SUM(AA20+AC20+AE20+AG20+AI20+AK20+AM20) -> 16730 | AQ20: =SUM(AR20/92970) -> 0.77056213 | AR20: =SUM(AO20+Y20) -> 71639.161 | AS20: =SUM(AR20-AR19-AT20) -> 0 | AV20: =IF(AT20>0,AU20,AV19) -> 0 | AW20: =-SUM('B5'!AI19) -> 0 | AX20: =-SUM(AW20-AS20) -> 0 | AY20: =SUM(AX20+AW20) -> 0 | AZ20: =ELEC!A17 -> 0 | BA20: ='General information '!D20 -> 0 | BB20: =SUM('General information '!E20) -> 0 | BC20: =IF(AR19>=AR20,0,1) -> 0 | BD20: 19222 | BE20: =(305/1185)*ELEC!Q18 -> 0 | BG20: =#REF!-BE20 -> #REF!
A21: =ELEC!C18 -> 43967 | B21: ='B5'!B20 -> 232 | C21: =B21*$B$4 -> 4991.7419 | D21: =SUM(B21) -> 232 | E21: =D21*$B$4 -> 4991.7419 | F21: =SUM(D21) -> 232 | G21: =F21*$B$4 -> 4991.7419 | H21: =SUM(F21) -> 232 | I21: =H21*$B$4 -> 4991.7419 | J21: =SUM(H21) -> 232 | K21: =J21*$B$4 -> 4991.7419 | L21: =SUM(J21) -> 232 | M21: =L21*$B$4 -> 4991.7419 | N21: =SUM(L21) -> 232 | O21: =N21*$B$4 -> 4991.7419 | P21: =SUM(N21) -> 232 | Q21: =P21*$B$4 -> 4991.7419 | R21: =SUM(P21) -> 232 | S21: =R21*$B$4 -> 4991.7419 | T21: =SUM(R21) -> 232 | U21: =T21*$B$4 -> 4991.7419 | V21: =SUM(T21) -> 232 | W21: =V21*$B$4 -> 4991.7419 | X21: =SUM(Y21/73370) -> 0.7483871 | Y21: =SUM(C21+E21+G21+I21+K21+M21+O21+Q21+S21+U21+W21) -> 54909.161 | Z21: ='B5'!C20 -> 239 | AA21: =SUM(Z21*$Z$4) -> 2390 | AB21: =SUM(Z21) -> 239 | AC21: =SUM(AB21*$Z$4) -> 2390 | AD21: =SUM(AB21) -> 239 | AE21: =SUM(AD21*$Z$4) -> 2390 | AF21: =SUM(AD21) -> 239 | AG21: =SUM(AF21*$Z$4) -> 2390 | AH21: =SUM(AF21) -> 239 | AI21: =SUM(AH21*$Z$4) -> 2390 | AJ21: =SUM(AH21) -> 239 | AK21: =SUM(AJ21*$Z$4) -> 2390 | AL21: =SUM(AJ21) -> 239 | AM21: =SUM(AL21*$Z$4) -> 2390 | AN21: =SUM(AO21/19600) -> 0.85357143 | AO21: =SUM(AA21+AC21+AE21+AG21+AI21+AK21+AM21) -> 16730 | AQ21: =SUM(AR21/92970) -> 0.77056213 | AR21: =SUM(AO21+Y21) -> 71639.161 | AS21: =SUM(AR21-AR20-AT21) -> 0 | AV21: =IF(AT21>0,AU21,AV20) -> 0 | AW21: =-SUM('B5'!AI20) -> 0 | AX21: =-SUM(AW21-AS21) -> 0 | AY21: =SUM(AX21+AW21) -> 0 | AZ21: =ELEC!A18 -> 0 | BA21: ='General information '!D21 -> 0 | BB21: =SUM('General information '!E21) -> 0 | BC21: =IF(AR20>=AR21,0,1) -> 0 | BD21: 19222 | BE21: =(305/1185)*ELEC!Q19 -> 0 | BG21: =#REF!-BE21 -> #REF!
A22: =ELEC!C19 -> 43968 | B22: ='B5'!B21 -> 232 | C22: =B22*$B$4 -> 4991.7419 | D22: =SUM(B22) -> 232 | E22: =D22*$B$4 -> 4991.7419 | F22: =SUM(D22) -> 232 | G22: =F22*$B$4 -> 4991.7419 | H22: =SUM(F22) -> 232 | I22: =H22*$B$4 -> 4991.7419 | J22: =SUM(H22) -> 232 | K22: =J22*$B$4 -> 4991.7419 | L22: =SUM(J22) -> 232 | M22: =L22*$B$4 -> 4991.7419 | N22: =SUM(L22) -> 232 | O22: =N22*$B$4 -> 4991.7419 | P22: =SUM(N22) -> 232 | Q22: =P22*$B$4 -> 4991.7419 | R22: =SUM(P22) -> 232 | S22: =R22*$B$4 -> 4991.7419 | T22: =SUM(R22) -> 232 | U22: =T22*$B$4 -> 4991.7419 | V22: =SUM(T22) -> 232 | W22: =V22*$B$4 -> 4991.7419 | X22: =SUM(Y22/73370) -> 0.7483871 | Y22: =SUM(C22+E22+G22+I22+K22+M22+O22+Q22+S22+U22+W22) -> 54909.161 | Z22: ='B5'!C21 -> 239 | AA22: =SUM(Z22*$Z$4) -> 2390 | AB22: =SUM(Z22) -> 239 | AC22: =SUM(AB22*$Z$4) -> 2390 | AD22: =SUM(AB22) -> 239 | AE22: =SUM(AD22*$Z$4) -> 2390 | AF22: =SUM(AD22) -> 239 | AG22: =SUM(AF22*$Z$4) -> 2390 | AH22: =SUM(AF22) -> 239 | AI22: =SUM(AH22*$Z$4) -> 2390 | AJ22: =SUM(AH22) -> 239 | AK22: =SUM(AJ22*$Z$4) -> 2390 | AL22: =SUM(AJ22) -> 239 | AM22: =SUM(AL22*$Z$4) -> 2390 | AN22: =SUM(AO22/19600) -> 0.85357143 | AO22: =SUM(AA22+AC22+AE22+AG22+AI22+AK22+AM22) -> 16730 | AQ22: =SUM(AR22/92970) -> 0.77056213 | AR22: =SUM(AO22+Y22) -> 71639.161 | AS22: =SUM(AR22-AR21-AT22) -> 0 | AV22: =IF(AT22>0,AU22,AV21) -> 0 | AW22: =-SUM('B5'!AI21) -> 0 | AX22: =-SUM(AW22-AS22) -> 0 | AY22: =SUM(AX22+AW22) -> 0 | AZ22: =ELEC!A19 -> 0 | BA22: ='General information '!D22 -> 0 | BB22: =SUM('General information '!E22) -> 0 | BC22: =IF(AR21>=AR22,0,1) -> 0 | BD22: 19222 | BE22: =(305/1185)*ELEC!Q20 -> 0 | BG22: =#REF!-BE22 -> #REF!
A23: =ELEC!C20 -> 43969 | B23: ='B5'!B22 -> 232 | C23: =B23*$B$4 -> 4991.7419 | D23: =SUM(B23) -> 232 | E23: =D23*$B$4 -> 4991.7419 | F23: =SUM(D23) -> 232 | G23: =F23*$B$4 -> 4991.7419 | H23: =SUM(F23) -> 232 | I23: =H23*$B$4 -> 4991.7419 | J23: =SUM(H23) -> 232 | K23: =J23*$B$4 -> 4991.7419 | L23: =SUM(J23) -> 232 | M23: =L23*$B$4 -> 4991.7419 | N23: =SUM(L23) -> 232 | O23: =N23*$B$4 -> 4991.7419 | P23: =SUM(N23) -> 232 | Q23: =P23*$B$4 -> 4991.7419 | R23: =SUM(P23) -> 232 | S23: =R23*$B$4 -> 4991.7419 | T23: =SUM(R23) -> 232 | U23: =T23*$B$4 -> 4991.7419 | V23: =SUM(T23) -> 232 | W23: =V23*$B$4 -> 4991.7419 | X23: =SUM(Y23/73370) -> 0.7483871 | Y23: =SUM(C23+E23+G23+I23+K23+M23+O23+Q23+S23+U23+W23) -> 54909.161 | Z23: ='B5'!C22 -> 239 | AA23: =SUM(Z23*$Z$4) -> 2390 | AB23: =SUM(Z23) -> 239 | AC23: =SUM(AB23*$Z$4) -> 2390 | AD23: =SUM(AB23) -> 239 | AE23: =SUM(AD23*$Z$4) -> 2390 | AF23: =SUM(AD23) -> 239 | AG23: =SUM(AF23*$Z$4) -> 2390 | AH23: =SUM(AF23) -> 239 | AI23: =SUM(AH23*$Z$4) -> 2390 | AJ23: =SUM(AH23) -> 239 | AK23: =SUM(AJ23*$Z$4) -> 2390 | AL23: =SUM(AJ23) -> 239 | AM23: =SUM(AL23*$Z$4) -> 2390 | AN23: =SUM(AO23/19600) -> 0.85357143 | AO23: =SUM(AA23+AC23+AE23+AG23+AI23+AK23+AM23) -> 16730 | AQ23: =SUM(AR23/92970) -> 0.77056213 | AR23: =SUM(AO23+Y23) -> 71639.161 | AS23: =SUM(AR23-AR22-AT23) -> 0 | AV23: =IF(AT23>0,AU23,AV22) -> 0 | AW23: =-SUM('B5'!AI22) -> 0 | AX23: =-SUM(AW23-AS23) -> 0 | AY23: =SUM(AX23+AW23) -> 0 | AZ23: =ELEC!A20 -> 0 | BA23: ='General information '!D23 -> 0 | BB23: =SUM('General information '!E23) -> 0 | BC23: =IF(AR22>=AR23,0,1) -> 0 | BD23: 19222 | BE23: =(305/1185)*ELEC!Q21 -> 0 | BG23: =#REF!-BE23 -> #REF!
A24: =ELEC!C21 -> 43970 | B24: ='B5'!B23 -> 232 | C24: =B24*$B$4 -> 4991.7419 | D24: =SUM(B24) -> 232 | E24: =D24*$B$4 -> 4991.7419 | F24: =SUM(D24) -> 232 | G24: =F24*$B$4 -> 4991.7419 | H24: =SUM(F24) -> 232 | I24: =H24*$B$4 -> 4991.7419 | J24: =SUM(H24) -> 232 | K24: =J24*$B$4 -> 4991.7419 | L24: =SUM(J24) -> 232 | M24: =L24*$B$4 -> 4991.7419 | N24: =SUM(L24) -> 232 | O24: =N24*$B$4 -> 4991.7419 | P24: =SUM(N24) -> 232 | Q24: =P24*$B$4 -> 4991.7419 | R24: =SUM(P24) -> 232 | S24: =R24*$B$4 -> 4991.7419 | T24: =SUM(R24) -> 232 | U24: =T24*$B$4 -> 4991.7419 | V24: =SUM(T24) -> 232 | W24: =V24*$B$4 -> 4991.7419 | X24: =SUM(Y24/73370) -> 0.7483871 | Y24: =SUM(C24+E24+G24+I24+K24+M24+O24+Q24+S24+U24+W24) -> 54909.161 | Z24: ='B5'!C23 -> 239 | AA24: =SUM(Z24*$Z$4) -> 2390 | AB24: =SUM(Z24) -> 239 | AC24: =SUM(AB24*$Z$4) -> 2390 | AD24: =SUM(AB24) -> 239 | AE24: =SUM(AD24*$Z$4) -> 2390 | AF24: =SUM(AD24) -> 239 | AG24: =SUM(AF24*$Z$4) -> 2390 | AH24: =SUM(AF24) -> 239 | AI24: =SUM(AH24*$Z$4) -> 2390 | AJ24: =SUM(AH24) -> 239 | AK24: =SUM(AJ24*$Z$4) -> 2390 | AL24: =SUM(AJ24) -> 239 | AM24: =SUM(AL24*$Z$4) -> 2390 | AN24: =SUM(AO24/19600) -> 0.85357143 | AO24: =SUM(AA24+AC24+AE24+AG24+AI24+AK24+AM24) -> 16730 | AQ24: =SUM(AR24/92970) -> 0.77056213 | AR24: =SUM(AO24+Y24) -> 71639.161 | AS24: =SUM(AR24-AR23-AT24) -> 0 | AV24: =IF(AT24>0,AU24,AV23) -> 0 | AW24: =-SUM('B5'!AI23) -> 0 | AX24: =-SUM(AW24-AS24) -> 0 | AY24: =SUM(AX24+AW24) -> 0 | AZ24: =ELEC!A21 -> 0 | BA24: ='General information '!D24 -> 0 | BB24: =SUM('General information '!E24) -> 0 | BC24: =IF(AR23>=AR24,0,1) -> 0 | BD24: 19222 | BE24: =(305/1185)*ELEC!Q22 -> 0 | BG24: =#REF!-BE24 -> #REF!
... A33: =ELEC!C30 -> 43979 | B33: ='B5'!B32 -> 232 | C33: =B33*$B$4 -> 4991.7419 | D33: =SUM(B33) -> 232 | E33: =D33*$B$4 -> 4991.7419 | F33: =SUM(D33) -> 232 | G33: =F33*$B$4 -> 4991.7419 | H33: =SUM(F33) -> 232 | I33: =H33*$B$4 -> 4991.7419 | J33: =SUM(H33) -> 232 | K33: =J33*$B$4 -> 4991.7419 | L33: =SUM(J33) -> 232 | M33: =L33*$B$4 -> 4991.7419 | N33: =SUM(L33) -> 232 | O33: =N33*$B$4 -> 4991.7419 | P33: =SUM(N33) -> 232 | Q33: =P33*$B$4 -> 4991.7419 | R33: =SUM(P33) -> 232 | S33: =R33*$B$4 -> 4991.7419 | T33: =SUM(R33) -> 232 | U33: =T33*$B$4 -> 4991.7419 | V33: =SUM(T33) -> 232 | W33: =V33*$B$4 -> 4991.7419 | X33: =SUM(Y33/73370) -> 0.7483871 | Y33: =SUM(C33+E33+G33+I33+K33+M33+O33+Q33+S33+U33+W33) -> 54909.161 | Z33: ='B5'!C32 -> 239 | AA33: =SUM(Z33*$Z$4) -> 2390 | AB33: =SUM(Z33) -> 239 | AC33: =SUM(AB33*$Z$4) -> 2390 | AD33: =SUM(AB33) -> 239 | AE33: =SUM(AD33*$Z$4) -> 2390 | AF33: =SUM(AD33) -> 239 | AG33: =SUM(AF33*$Z$4) -> 2390 | AH33: =SUM(AF33) -> 239 | AI33: =SUM(AH33*$Z$4) -> 2390 | AJ33: =SUM(AH33) -> 239 | AK33: =SUM(AJ33*$Z$4) -> 2390 | AL33: =SUM(AJ33) -> 239 | AM33: =SUM(AL33*$Z$4) -> 2390 | AN33: =SUM(AO33/19600) -> 0.85357143 | AO33: =SUM(AA33+AC33+AE33+AG33+AI33+AK33+AM33) -> 16730 | AQ33: =SUM(AR33/92970) -> 0.77056213 | AR33: =SUM(AO33+Y33) -> 71639.161 | AS33: =SUM(AR33-AR32-AT33) -> 0 | AV33: =IF(AT33>0,AU33,AV32) -> 0 | AW33: =-SUM('B5'!AI32) -> 0 | AX33: =-SUM(AW33-AS33) -> 0 | AY33: =SUM(AX33+AW33) -> 0 | AZ33: =ELEC!A30 -> 0 | BA33: ='General information '!D33 -> 0 | BB33: =SUM('General information '!E33) -> 0 | BC33: =IF(AR32>=AR33,0,1) -> 0 | BD33: 19222 | BE33: =(305/1185)*ELEC!Q31 -> 0 | BG33: =#REF!-BE33 -> #REF!
A34: =ELEC!C31 -> 43980 | B34: ='B5'!B33 -> 232 | C34: =B34*$B$4 -> 4991.7419 | D34: =SUM(B34) -> 232 | E34: =D34*$B$4 -> 4991.7419 | F34: =SUM(D34) -> 232 | G34: =F34*$B$4 -> 4991.7419 | H34: =SUM(F34) -> 232 | I34: =H34*$B$4 -> 4991.7419 | J34: =SUM(H34) -> 232 | K34: =J34*$B$4 -> 4991.7419 | L34: =SUM(J34) -> 232 | M34: =L34*$B$4 -> 4991.7419 | N34: =SUM(L34) -> 232 | O34: =N34*$B$4 -> 4991.7419 | P34: =SUM(N34) -> 232 | Q34: =P34*$B$4 -> 4991.7419 | R34: =SUM(P34) -> 232 | S34: =R34*$B$4 -> 4991.7419 | T34: =SUM(R34) -> 232 | U34: =T34*$B$4 -> 4991.7419 | V34: =SUM(T34) -> 232 | W34: =V34*$B$4 -> 4991.7419 | X34: =SUM(Y34/73370) -> 0.7483871 | Y34: =SUM(C34+E34+G34+I34+K34+M34+O34+Q34+S34+U34+W34) -> 54909.161 | Z34: ='B5'!C33 -> 239 | AA34: =SUM(Z34*$Z$4) -> 2390 | AB34: =SUM(Z34) -> 239 | AC34: =SUM(AB34*$Z$4) -> 2390 | AD34: =SUM(AB34) -> 239 | AE34: =SUM(AD34*$Z$4) -> 2390 | AF34: =SUM(AD34) -> 239 | AG34: =SUM(AF34*$Z$4) -> 2390 | AH34: =SUM(AF34) -> 239 | AI34: =SUM(AH34*$Z$4) -> 2390 | AJ34: =SUM(AH34) -> 239 | AK34: =SUM(AJ34*$Z$4) -> 2390 | AL34: =SUM(AJ34) -> 239 | AM34: =SUM(AL34*$Z$4) -> 2390 | AN34: =SUM(AO34/19600) -> 0.85357143 | AO34: =SUM(AA34+AC34+AE34+AG34+AI34+AK34+AM34) -> 16730 | AQ34: =SUM(AR34/92970) -> 0.77056213 | AR34: =SUM(AO34+Y34) -> 71639.161 | AS34: =SUM(AR34-AR33-AT34) -> 0 | AV34: =IF(AT34>0,AU34,AV33) -> 0 | AW34: =-SUM('B5'!AI33) -> 0 | AX34: =-SUM(AW34-AS34) -> 0 | AY34: =SUM(AX34+AW34) -> 0 | AZ34: =ELEC!A31 -> 0 | BA34: ='General information '!D34 -> 0 | BB34: =SUM('General information '!E34) -> 0 | BC34: =IF(AR33>=AR34,0,1) -> 0 | BD34: 19222 | BE34: =(305/1185)*ELEC!#REF! -> #REF! | BG34: =#REF!-BE34 -> #REF!
A35: =ELEC!C32 -> 43981 | B35: ='B5'!B34 -> 232 | C35: =B35*$B$4 -> 4991.7419 | D35: =SUM(B35) -> 232 | E35: =D35*$B$4 -> 4991.7419 | F35: =SUM(D35) -> 232 | G35: =F35*$B$4 -> 4991.7419 | H35: =SUM(F35) -> 232 | I35: =H35*$B$4 -> 4991.7419 | J35: =SUM(H35) -> 232 | K35: =J35*$B$4 -> 4991.7419 | L35: =SUM(J35) -> 232 | M35: =L35*$B$4 -> 4991.7419 | N35: =SUM(L35) -> 232 | O35: =N35*$B$4 -> 4991.7419 | P35: =SUM(N35) -> 232 | Q35: =P35*$B$4 -> 4991.7419 | R35: =SUM(P35) -> 232 | S35: =R35*$B$4 -> 4991.7419 | T35: =SUM(R35) -> 232 | U35: =T35*$B$4 -> 4991.7419 | V35: =SUM(T35) -> 232 | W35: =V35*$B$4 -> 4991.7419 | X35: =SUM(Y35/73370) -> 0.7483871 | Y35: =SUM(C35+E35+G35+I35+K35+M35+O35+Q35+S35+U35+W35) -> 54909.161 | Z35: ='B5'!C34 -> 239 | AA35: =SUM(Z35*$Z$4) -> 2390 | AB35: =SUM(Z35) -> 239 | AC35: =SUM(AB35*$Z$4) -> 2390 | AD35: =SUM(AB35) -> 239 | AE35: =SUM(AD35*$Z$4) -> 2390 | AF35: =SUM(AD35) -> 239 | AG35: =SUM(AF35*$Z$4) -> 2390 | AH35: =SUM(AF35) -> 239 | AI35: =SUM(AH35*$Z$4) -> 2390 | AJ35: =SUM(AH35) -> 239 | AK35: =SUM(AJ35*$Z$4) -> 2390 | AL35: =SUM(AJ35) -> 239 | AM35: =SUM(AL35*$Z$4) -> 2390 | AN35: =SUM(AO35/19600) -> 0.85357143 | AO35: =SUM(AA35+AC35+AE35+AG35+AI35+AK35+AM35) -> 16730 | AQ35: =SUM(AR35/92970) -> 0.77056213 | AR35: =SUM(AO35+Y35) -> 71639.161 | AS35: =SUM(AR35-AR34-AT35) -> 0 | AV35: =IF(AT35>0,AU35,AV34) -> 0 | AW35: =-SUM('B5'!AI34) -> 0 | AX35: =-SUM(AW35-AS35) -> 0 | AY35: =SUM(AX35+AW35) -> 0 | AZ35: =ELEC!A32 -> 0 | BA35: ='General information '!D35 -> 0 | BB35: =SUM('General information '!E35) -> 0 | BC35: =IF(AR34>=AR35,0,1) -> 0 | BD35: 19222 | BE35: =(305/1185)*ELEC!#REF! -> #REF! | BG35: =#REF!-BE35 -> #REF!
A36: =ELEC!C33 -> 43982 | B36: ='B5'!B35 -> 232 | C36: =B36*$B$4 -> 4991.7419 | D36: =SUM(B36) -> 232 | E36: =D36*$B$4 -> 4991.7419 | F36: =SUM(D36) -> 232 | G36: =F36*$B$4 -> 4991.7419 | H36: =SUM(F36) -> 232 | I36: =H36*$B$4 -> 4991.7419 | J36: =SUM(H36) -> 232 | K36: =J36*$B$4 -> 4991.7419 | L36: =SUM(J36) -> 232 | M36: =L36*$B$4 -> 4991.7419 | N36: =SUM(L36) -> 232 | O36: =N36*$B$4 -> 4991.7419 | P36: =SUM(N36) -> 232 | Q36: =P36*$B$4 -> 4991.7419 | R36: =SUM(P36) -> 232 | S36: =R36*$B$4 -> 4991.7419 | T36: =SUM(R36) -> 232 | U36: =T36*$B$4 -> 4991.7419 | V36: =SUM(T36) -> 232 | W36: =V36*$B$4 -> 4991.7419 | X36: =SUM(Y36/73370) -> 0.7483871 | Y36: =SUM(C36+E36+G36+I36+K36+M36+O36+Q36+S36+U36+W36) -> 54909.161 | Z36: ='B5'!C35 -> 239 | AA36: =SUM(Z36*$Z$4) -> 2390 | AB36: =SUM(Z36) -> 239 | AC36: =SUM(AB36*$Z$4) -> 2390 | AD36: =SUM(AB36) -> 239 | AE36: =SUM(AD36*$Z$4) -> 2390 | AF36: =SUM(AD36) -> 239 | AG36: =SUM(AF36*$Z$4) -> 2390 | AH36: =SUM(AF36) -> 239 | AI36: =SUM(AH36*$Z$4) -> 2390 | AJ36: =SUM(AH36) -> 239 | AK36: =SUM(AJ36*$Z$4) -> 2390 | AL36: =SUM(AJ36) -> 239 | AM36: =SUM(AL36*$Z$4) -> 2390 | AN36: =SUM(AO36/19600) -> 0.85357143 | AO36: =SUM(AA36+AC36+AE36+AG36+AI36+AK36+AM36) -> 16730 | AQ36: =SUM(AR36/92970) -> 0.77056213 | AR36: =SUM(AO36+Y36) -> 71639.161 | AS36: =SUM(AR36-AR35-AT36) -> 0 | AV36: =IF(AT36>0,AU36,AV35) -> 0 | AW36: =-SUM('B5'!AI35) -> 0 | AX36: =-SUM(AW36-AS36) -> 0 | AY36: =SUM(AX36+AW36) -> 0 | AZ36: =ELEC!A33 -> 0 | BA36: ='General information '!D36 -> 0 | BB36: =SUM('General information '!E36) -> 0
AR37: NB delivery | AS37: =COUNT(AT6:AT36) -> 1 | AT37: =SUM(AT6:AT36) -> 1 | AU37: =SUM(AU6:AU36)/AS37 -> 0 | AX37: =SUM(AX6:AX36) -> -2491.7452 | AY37: =SUM(AY6:AY36) -> -4036.1452
AT38: =+AT37*AU37 -> 0
AS40: =SUM(AS6:AS36)/'EDl log'!A36 -> -1009.0363

Sheet GEN
B1: GEN1 | C1: RUN HR | D1: Fuel Counter Index | E1: Cons /day | F1: Diesel L/H | H1: next service | I1: ALARM | J1: GEN2 | K1: RUN HR | L1: Fuel Counter Index | M1: Cons /day | N1: Diesel L/H | P1: next service | Q1: ALARM | R1: GEN3 | S1: RUN HR | T1: Fuel Counter Index | U1: Cons /day | V1: Diesel L/H | X1: next service | Y1: ALARM | Z1: RH total | AA1: Gen Con /day | AB1: Total Deisel Cons/day | AC1: H /L | AD1: TOAL KW GEN | AI1: fuel Consuption | AK1: AVG KW/h
A2: =ELEC!C2 -> 43951 | B2: =[4]GEN!B32 -> 8621.09 | C2: =[4]GEN!C32 -> 0 | D2: =[4]GEN!D32 -> 146479.8 | E2: =[4]GEN!E32 -> 0 | F2: =[4]GEN!F32 -> 0 | G2: =[4]GEN!G32 -> 0 | H2: =[4]GEN!H32 -> 8677 | I2: =[4]GEN!I32 -> ok | ... Q2: =[4]GEN!Q32 -> ok | R2: =[1]GEN!R32 -> 11115 | S2: =[1]GEN!S32 -> 2.87 | T2: =[1]GEN!T32 -> 234142 | U2: =[1]GEN!U32 -> 682 | V2: =[1]GEN!V32 -> 237.63066 | W2: =[1]GEN!W32 -> 0 | X2: =[1]GEN!X32 -> 11709 | Y2: =[1]GEN!Y32 -> ok | ... AK2: =[1]GEN!AK32 -> 158.73506
A3: =ELEC!C3 -> 43952 | B3: =B2 -> 8621.09 | C3: =B3-B2 -> 0 | D3: =D2 -> 146479.8 | E3: =SUM(D3-D2) -> 0 | F3: =IF(C3>0,E3/C3,0) -> 0 | G3: =[5]GEN!G32 -> 0 | H3: =H2 -> 8677 | I3: =IF(B3-H3<=0,"ok","oil change") -> ok | J3: =J2 -> 10689.42 | K3: =J3-J2 -> 0 | L3: =L2 -> 237074.9 | M3: =SUM(L3-L2) -> 0 | N3: =IF(K3>0,M3/K3,0) -> 0 | O3: =[5]GEN!O32 -> 0 | P3: =P2 -> 10873 | Q3: =IF(J3-P3<=0,"ok","oil change") -> ok | R3: 11118 | S3: =R3-R2 -> 3 | T3: 234786 | U3: =SUM(T3-T2) -> 644 | V3: =IF(S3>0,U3/S3,0) -> 214.66667 | W3: =[5]GEN!W32 -> 0 | X3: =X2 -> 11709 | Y3: =IF(R3-X3<=0,"ok","oil change") -> ok | Z3: =C3+K3+S3 -> 3 | AA3: =U3+M3+E3 -> 644 | AB3: =V3+N3+F3 -> 214.66667 | AC3: =IF(Z3>0,AA3/Z3,0) -> 214.66667 | AD3: =ELEC!Q3 -> 1400 | AE3: =SUM(AD3/Z3) -> 466.66667 | AF3: =SUM(AE3/1600) -> 0.29166667 | AG3: =SUM(360*AF3) -> 105 | AH3: =SUM(AC3-AG3) -> 109.66667 | AI3: =AD3*AJ3 -> 360.33755 | AJ3: =305/1185 -> 0.25738397 | AK3: =AI3/Z3 -> 120.11252
A4: =ELEC!C4 -> 43953 | B4: =B3 -> 8621.09 | C4: =B4-B3 -> 0 | D4: =D3 -> 146479.8 | E4: =SUM(D4-D3) -> 0 | F4: =IF(C4>0,E4/C4,0) -> 0 | H4: =H3 -> 8677 | I4: =IF(B4-H4<=0,"ok","oil change") -> ok | J4: =J3 -> 10689.42 | K4: =J4-J3 -> 0 | L4: =L3 -> 237074.9 | M4: =SUM(L4-L3) -> 0 | N4: =IF(K4>0,M4/K4,0) -> 0 | P4: =P3 -> 10873 | Q4: =IF(J4-P4<=0,"ok","oil change") -> ok | R4: 11120 | S4: =R4-R3 -> 2 | T4: 235331.1 | U4: =SUM(T4-T3) -> 545.1 | V4: =IF(S4>0,U4/S4,0) -> 272.55 | X4: =X3 -> 11709 | Y4: =IF(R4-X4<=0,"ok","oil change") -> ok | Z4: =C4+K4+S4 -> 2 | AA4: =U4+M4+E4 -> 545.1 | AB4: =V4+N4+F4 -> 272.55 | AC4: =IF(Z4>0,AA4/Z4,0) -> 272.55 | AD4: =ELEC!Q4 -> 1534 | AE4: =SUM(AD4/Z4) -> 767 | AF4: =SUM(AE4/1600) -> 0.479375 | AG4: =SUM(360*AF4) -> 172.575 | AH4: =SUM(AC4-AG4) -> 99.975 | AI4: =AD4*AJ4 -> 394.827 | AJ4: =305/1185 -> 0.25738397 | AK4: =AI4/Z4 -> 197.4135
A5: =ELEC!C5 -> 43954 | B5: =B4 -> 8621.09 | C5: =B5-B4 -> 0 | D5: =D4 -> 146479.8 | E5: =SUM(D5-D4) -> 0 | F5: =IF(C5>0,E5/C5,0) -> 0 | H5: 8497 | I5: =IF(B5-H5<=0,"ok","oil change") -> oil change | J5: =J4 -> 10689.42 | K5: =J5-J4 -> 0 | L5: =L4 -> 237074.9 | M5: =SUM(L5-L4) -> 0 | N5: =IF(K5>0,M5/K5,0) -> 0 | P5: =P4 -> 10873 | Q5: =IF(J5-P5<=0,"ok","oil change") -> ok | R5: 11124 | S5: =R5-R4 -> 4 | T5: 236146 | U5: =SUM(T5-T4) -> 814.9 | V5: =IF(S5>0,U5/S5,0) -> 203.725 | X5: =X4 -> 11709 | Y5: =IF(R5-X5<=0,"ok","oil change") -> ok | Z5: =C5+K5+S5 -> 4 | AA5: =U5+M5+E5 -> 814.9 | AB5: =V5+N5+F5 -> 203.725 | AC5: =IF(Z5>0,AA5/Z5,0) -> 203.725 | AD5: =ELEC!Q5 -> 1466 | AE5: =SUM(AD5/Z5) -> 366.5 | AF5: =SUM(AE5/1600) -> 0.2290625 | AG5: =SUM(320*AF5) -> 73.3 | AH5: =SUM(AC5-AG5) -> 130.425 | AI5: =AD5*AJ5 -> 377.32489 | AJ5: =305/1185 -> 0.25738397 | AK5: =AI5/Z5 -> 94.331224
A6: =ELEC!C6 -> 43955 | B6: =B5 -> 8621.09 | C6: =B6-B5 -> 0 | D6: =D5 -> 146479.8 | E6: =SUM(D6-D5) -> 0 | F6: =IF(C6>0,E6/C6,0) -> 0 | H6: =H5 -> 8497 | I6: =IF(B6-H6<=0,"ok","oil change") -> oil change | J6: =J5 -> 10689.42 | K6: =J6-J5 -> 0 | L6: =L5 -> 237074.9 | M6: =SUM(L6-L5) -> 0 | N6: =IF(K6>0,M6/K6,0) -> 0 | P6: =P5 -> 10873 | Q6: =IF(J6-P6<=0,"ok","oil change") -> ok | R6: 11127 | S6: =R6-R5 -> 3 | T6: 236923 | U6: =SUM(T6-T5) -> 777 | V6: =IF(S6>0,U6/S6,0) -> 259 | X6: =X5 -> 11709 | Y6: =IF(R6-X6<=0,"ok","oil change") -> ok | Z6: =C6+K6+S6 -> 3 | AA6: =U6+M6+E6 -> 777 | AB6: =V6+N6+F6 -> 259 | AC6: =IF(Z6>0,AA6/Z6,0) -> 259 | AD6: =ELEC!Q6 -> 1000 | AE6: =SUM(AD6/Z6) -> 333.33333 | AF6: =SUM(AE6/1600) -> 0.20833333 | AG6: =SUM(320*AF6) -> 66.666667 | AH6: =SUM(AC6-AG6) -> 192.33333 | AI6: =AD6*AJ6 -> 257.38397 | AJ6: =305/1185 -> 0.25738397 | AK6: =AI6/Z6 -> 85.794655
A7: =ELEC!C7 -> 43956 | B7: =B6 -> 8621.09 | C7: =B7-B6 -> 0 | D7: =D6 -> 146479.8 | E7: =SUM(D7-D6) -> 0 | F7: =IF(C7>0,E7/C7,0) -> 0 | H7: =H6 -> 8497 | I7: =IF(B7-H7<=0,"ok","oil change") -> oil change | J7: =J6 -> 10689.42 | K7: =J7-J6 -> 0 | L7: =L6 -> 237074.9 | M7: =SUM(L7-L6) -> 0 | N7: =IF(K7>0,M7/K7,0) -> 0 | P7: =P6 -> 10873 | Q7: =IF(J7-P7<=0,"ok","oil change") -> ok | R7: =R6 -> 11127 | S7: =R7-R6 -> 0 | T7: =T6 -> 236923 | U7: =SUM(T7-T6) -> 0 | V7: =IF(S7>0,U7/S7,0) -> 0 | X7: =X6 -> 11709 | Y7: =IF(R7-X7<=0,"ok","oil change") -> ok | Z7: =C7+K7+S7 -> 0 | AA7: =U7+M7+E7 -> 0 | AB7: =V7+N7+F7 -> 0 | AC7: =IF(Z7>0,AA7/Z7,0) -> 0 | AD7: =ELEC!Q7 -> 0 | AE7: =SUM(AD7/Z7) -> #DIV/0! | AF7: =SUM(AE7/1600) -> #DIV/0! | AH7: =SUM(AC7-AG7) -> #VALUE! | AI7: =AD7*AJ7 -> 0 | AJ7: =305/1185 -> 0.25738397 | AK7: =AI7/Z7 -> #DIV/0!
A8: =ELEC!C8 -> 43957 | B8: =B7 -> 8621.09 | C8: =B8-B7 -> 0 | D8: =D7 -> 146479.8 | E8: =SUM(D8-D7) -> 0 | F8: =IF(C8>0,E8/C8,0) -> 0 | H8: =H7 -> 8497 | I8: =IF(B8-H8<=0,"ok","oil change") -> oil change | J8: =J7 -> 10689.42 | K8: =J8-J7 -> 0 | L8: =L7 -> 237074.9 | M8: =SUM(L8-L7) -> 0 | N8: =IF(K8>0,M8/K8,0) -> 0 | P8: =P7 -> 10873 | Q8: =IF(J8-P8<=0,"ok","oil change") -> ok | R8: =R7 -> 11127 | S8: =R8-R7 -> 0 | T8: =T7 -> 236923 | U8: =SUM(T8-T7) -> 0 | V8: =IF(S8>0,U8/S8,0) -> 0 | X8: =X7 -> 11709 | Y8: =IF(R8-X8<=0,"ok","oil change") -> ok | Z8: =C8+K8+S8 -> 0 | AA8: =U8+M8+E8 -> 0 | AB8: =V8+N8+F8 -> 0 | AC8: =IF(Z8>0,AA8/Z8,0) -> 0 | AD8: =ELEC!Q8 -> 0 | AE8: =SUM(AD8/Z8) -> #DIV/0! | AF8: =SUM(AE8/1600) -> #DIV/0! | AG8: =SUM(320*AF8) -> #DIV/0! | AH8: =SUM(AC8-AG8) -> #DIV/0! | AI8: =AD8*AJ8 -> 0 | AJ8: =305/1185 -> 0.25738397 | AK8: =AI8/Z8 -> #DIV/0!
A9: =ELEC!C9 -> 43958 | B9: =B8 -> 8621.09 | C9: =B9-B8 -> 0 | D9: =D8 -> 146479.8 | E9: =SUM(D9-D8) -> 0 | F9: =IF(C9>0,E9/C9,0) -> 0 | H9: =H8 -> 8497 | I9: =IF(B9-H9<=0,"ok","oil change") -> oil change | J9: =J8 -> 10689.42 | K9: =J9-J8 -> 0 | L9: =L8 -> 237074.9 | M9: =SUM(L9-L8) -> 0 | N9: =IF(K9>0,M9/K9,0) -> 0 | P9: =P8 -> 10873 | Q9: =IF(J9-P9<=0,"ok","oil change") -> ok | R9: =R8 -> 11127 | S9: =R9-R8 -> 0 | T9: =T8 -> 236923 | U9: =SUM(T9-T8) -> 0 | V9: =IF(S9>0,U9/S9,0) -> 0 | X9: =X8 -> 11709 | Y9: =IF(R9-X9<=0,"ok","oil change") -> ok | Z9: =C9+K9+S9 -> 0 | AA9: =U9+M9+E9 -> 0 | AB9: =V9+N9+F9 -> 0 | AC9: =IF(Z9>0,AA9/Z9,0) -> 0 | AD9: =ELEC!Q9 -> 0 | AE9: =SUM(AD9/Z9) -> #DIV/0! | AF9: =SUM(AE9/1600) -> #DIV/0! | AG9: =SUM(320*AF9) -> #DIV/0! | AH9: =SUM(AC9-AG9) -> #DIV/0! | AI9: =AD9*AJ9 -> 0 | AJ9: 0.25738397 | AK9: =IF(Z9>0,AI9/Z9,0) -> 0
A10: =ELEC!C10 -> 43959 | B10: =B9 -> 8621.09 | C10: =B10-B9 -> 0 | D10: =D9 -> 146479.8 | E10: =SUM(D10-D9) -> 0 | F10: =IF(C10>0,E10/C10,0) -> 0 | H10: =H9 -> 8497 | I10: =IF(B10-H10<=0,"ok","oil change") -> oil change | J10: =J9 -> 10689.42 | K10: =J10-J9 -> 0 | L10: =L9 -> 237074.9 | M10: =SUM(L10-L9) -> 0 | N10: =IF(K10>0,M10/K10,0) -> 0 | P10: 10873 | Q10: =IF(J10-P10<=0,"ok","oil change") -> ok | R10: =R9 -> 11127 | S10: =R10-R9 -> 0 | T10: =T9 -> 236923 | U10: =SUM(T10-T9) -> 0 | V10: =IF(S10>0,U10/S10,0) -> 0 | X10: =X9 -> 11709 | Y10: =IF(R10-X10<=0,"ok","oil change") -> ok | Z10: =C10+K10+S10 -> 0 | AA10: =U10+M10+E10 -> 0 | AB10: =V10+N10+F10 -> 0 | AC10: =IF(Z10>0,AA10/Z10,0) -> 0 | AD10: =ELEC!Q10 -> 0 | AE10: =SUM(AD10/Z10) -> #DIV/0! | AF10: =SUM(AE10/1600) -> #DIV/0! | AG10: =SUM(320*AF10) -> #DIV/0! | AH10: =SUM(AC10-AG10) -> #DIV/0! | AI10: =AD10*AJ10 -> 0 | AJ10: =305/1185 -> 0.25738397 | AK10: =IF(Z10>0,AI10/Z10,0) -> 0
A11: =ELEC!C11 -> 43960 | B11: =B10 -> 8621.09 | C11: =B11-B10 -> 0 | D11: =D10 -> 146479.8 | E11: =SUM(D11-D10) -> 0 | F11: =IF(C11>0,E11/C11,0) -> 0 | H11: =H10 -> 8497 | I11: =IF(B11-H11<=0,"ok","oil change") -> oil change | J11: =J10 -> 10689.42 | K11: =J11-J10 -> 0 | L11: =L10 -> 237074.9 | M11: =SUM(L11-L10) -> 0 | N11: =IF(K11>0,M11/K11,0) -> 0 | P11: =P10 -> 10873 | Q11: =IF(J11-P11<=0,"ok","oil change") -> ok | R11: =R10 -> 11127 | S11: =R11-R10 -> 0 | T11: =T10 -> 236923 | U11: =SUM(T11-T10) -> 0 | V11: =IF(S11>0,U11/S11,0) -> 0 | X11: =X10 -> 11709 | Y11: =IF(R11-X11<=0,"ok","oil change") -> ok | Z11: =C11+K11+S11 -> 0 | AA11: =U11+M11+E11 -> 0 | AB11: =V11+N11+F11 -> 0 | AC11: =IF(Z11>0,AA11/Z11,0) -> 0 | AD11: =ELEC!Q11 -> 0 | AE11: =SUM(AD11/Z11) -> #DIV/0! | AF11: =SUM(AE11/1600) -> #DIV/0! | AG11: =SUM(320*AF11) -> #DIV/0! | AH11: =SUM(AC11-AG11) -> #DIV/0! | AI11: =AD11*AJ11 -> 0 | AJ11: =305/1185 -> 0.25738397 | AK11: =IF(Z11>0,AI11/Z11,0) -> 0
A12: =ELEC!C12 -> 43961 | B12: =B11 -> 8621.09 | C12: =B12-B11 -> 0 | D12: =D11 -> 146479.8 | E12: =SUM(D12-D11) -> 0 | F12: =IF(C12>0,E12/C12,0) -> 0 | H12: =H11 -> 8497 | I12: =IF(B12-H12<=0,"ok","oil change") -> oil change | J12: =J11 -> 10689.42 | K12: =J12-J11 -> 0 | L12: =L11 -> 237074.9 | M12: =SUM(L12-L11) -> 0 | N12: =IF(K12>0,M12/K12,0) -> 0 | P12: =P11 -> 10873 | Q12: =IF(J12-P12<=0,"ok","oil change") -> ok | R12: =R11 -> 11127 | S12: =R12-R11 -> 0 | T12: =T11 -> 236923 | U12: =SUM(T12-T11) -> 0 | V12: =IF(S12>0,U12/S12,0) -> 0 | X12: =X11 -> 11709 | Y12: =IF(R12-X12<=0,"ok","oil change") -> ok | Z12: =C12+K12+S12 -> 0 | AA12: =U12+M12+E12 -> 0 | AB12: =V12+N12+F12 -> 0 | AC12: =IF(Z12>0,AA12/Z12,0) -> 0 | AD12: =ELEC!Q12 -> 0 | AE12: =SUM(AD12/Z12) -> #DIV/0! | AF12: =SUM(AE12/1600) -> #DIV/0! | AG12: =SUM(320*AF12) -> #DIV/0! | AH12: =SUM(AC12-AG12) -> #DIV/0! | AI12: =AD12*AJ12 -> 0 | AJ12: =305/1185 -> 0.25738397 | AK12: =IF(Z12>0,AI12/Z12,0) -> 0
A13: =ELEC!C13 -> 43962 | B13: =B12 -> 8621.09 | C13: =B13-B12 -> 0 | D13: =D12 -> 146479.8 | E13: =SUM(D13-D12) -> 0 | F13: =IF(C13>0,E13/C13,0) -> 0 | H13: =H12 -> 8497 | I13: =IF(B13-H13<=0,"ok","oil change") -> oil change | J13: =J12 -> 10689.42 | K13: =J13-J12 -> 0 | L13: =L12 -> 237074.9 | M13: =SUM(L13-L12) -> 0 | N13: =IF(K13>0,M13/K13,0) -> 0 | P13: =P12 -> 10873 | Q13: =IF(J13-P13<=0,"ok","oil change") -> ok | R13: =R12 -> 11127 | S13: =R13-R12 -> 0 | T13: =T12 -> 236923 | U13: =SUM(T13-T12) -> 0 | V13: =IF(S13>0,U13/S13,0) -> 0 | X13: =X12+180 -> 11889 | Y13: =IF(R13-X13<=0,"ok","oil change") -> ok | Z13: =C13+K13+S13 -> 0 | AA13: =U13+M13+E13 -> 0 | AB13: =V13+N13+F13 -> 0 | AC13: =IF(Z13>0,AA13/Z13,0) -> 0 | AD13: =ELEC!Q13 -> 0 | AE13: =SUM(AD13/Z13) -> #DIV/0! | AF13: =SUM(AE13/1600) -> #DIV/0! | AG13: =SUM(320*AF13) -> #DIV/0! | AH13: =SUM(AC13-AG13) -> #DIV/0! | AI13: =AD13*AJ13 -> 0 | AJ13: =305/1185 -> 0.25738397 | AK13: =IF(Z13>0,AI13/Z13,0) -> 0
A14: =ELEC!C14 -> 43963 | B14: =B13 -> 8621.09 | C14: =B14-B13 -> 0 | D14: =D13 -> 146479.8 | E14: =SUM(D14-D13) -> 0 | F14: =IF(C14>0,E14/C14,0) -> 0 | H14: =H13 -> 8497 | I14: =IF(B14-H14<=0,"ok","oil change") -> oil change | J14: =J13 -> 10689.42 | K14: =J14-J13 -> 0 | L14: =L13 -> 237074.9 | M14: =SUM(L14-L13) -> 0 | N14: =IF(K14>0,M14/K14,0) -> 0 | P14: =P13 -> 10873 | Q14: =IF(J14-P14<=0,"ok","oil change") -> ok | R14: =R13 -> 11127 | S14: =R14-R13 -> 0 | T14: =T13 -> 236923 | U14: =SUM(T14-T13) -> 0 | V14: =IF(S14>0,U14/S14,0) -> 0 | X14: =X13 -> 11889 | Y14: =IF(R14-X14<=0,"ok","oil change") -> ok | Z14: =C14+K14+S14 -> 0 | AA14: =U14+M14+E14 -> 0 | AB14: =V14+N14+F14 -> 0 | AC14: =IF(Z14>0,AA14/Z14,0) -> 0 | AD14: =ELEC!Q14 -> 0 | AE14: =SUM(AD14/Z14) -> #DIV/0! | AF14: =SUM(AE14/1600) -> #DIV/0! | AG14: =SUM(320*AF14) -> #DIV/0! | AH14: =SUM(AC14-AG14) -> #DIV/0! | AI14: =AD14*AJ14 -> 0 | AJ14: =305/1185 -> 0.25738397 | AK14: =IF(Z14>0,AI14/Z14,0) -> 0
A15: =ELEC!C15 -> 43964 | B15: =B14 -> 8621.09 | C15: =B15-B14 -> 0 | D15: =D14 -> 146479.8 | E15: =SUM(D15-D14) -> 0 | F15: =IF(C15>0,E15/C15,0) -> 0 | H15: =H14 -> 8497 | I15: =IF(B15-H15<=0,"ok","oil change") -> oil change | J15: =J14 -> 10689.42 | K15: =J15-J14 -> 0 | L15: =L14 -> 237074.9 | M15: =SUM(L15-L14) -> 0 | N15: =IF(K15>0,M15/K15,0) -> 0 | P15: =P14 -> 10873 | Q15: =IF(J15-P15<=0,"ok","oil change") -> ok | R15: =R14 -> 11127 | S15: =R15-R14 -> 0 | T15: =T14 -> 236923 | U15: =SUM(T15-T14) -> 0 | V15: =IF(S15>0,U15/S15,0) -> 0 | X15: =X14 -> 11889 | Y15: =IF(R15-X15<=0,"ok","oil change") -> ok | Z15: =C15+K15+S15 -> 0 | AA15: =U15+M15+E15 -> 0 | AB15: =V15+N15+F15 -> 0 | AC15: =IF(Z15>0,AA15/Z15,0) -> 0 | AD15: =ELEC!Q15 -> 0 | AE15: =SUM(AD15/Z15) -> #DIV/0! | AF15: =SUM(AE15/1600) -> #DIV/0! | AG15: =SUM(320*AF15) -> #DIV/0! | AH15: =SUM(AC15-AG15) -> #DIV/0! | AI15: =AD15*AJ15 -> 0 | AJ15: =305/1185 -> 0.25738397 | AK15: =IF(Z15>0,AI15/Z15,0) -> 0
A16: =ELEC!C16 -> 43965 | B16: =B15 -> 8621.09 | C16: =B16-B15 -> 0 | D16: =D15 -> 146479.8 | E16: =SUM(D16-D15) -> 0 | F16: =IF(C16>0,E16/C16,0) -> 0 | H16: =H15 -> 8497 | I16: =IF(B16-H16<=0,"ok","oil change") -> oil change | J16: =J15 -> 10689.42 | K16: =J16-J15 -> 0 | L16: =L15 -> 237074.9 | M16: =SUM(L16-L15) -> 0 | N16: =IF(K16>0,M16/K16,0) -> 0 | P16: =P15 -> 10873 | Q16: =IF(J16-P16<=0,"ok","oil change") -> ok | R16: =R15 -> 11127 | S16: =R16-R15 -> 0 | T16: =T15 -> 236923 | U16: =SUM(T16-T15) -> 0 | V16: =IF(S16>0,U16/S16,0) -> 0 | X16: =X15 -> 11889 | Y16: =IF(R16-X16<=0,"ok","oil change") -> ok | Z16: =C16+K16+S16 -> 0 | AA16: =U16+M16+E16 -> 0 | AB16: =V16+N16+F16 -> 0 | AC16: =IF(Z16>0,AA16/Z16,0) -> 0 | AD16: =ELEC!Q16 -> 0 | AE16: =SUM(AD16/Z16) -> #DIV/0! | AF16: =SUM(AE16/1600) -> #DIV/0! | AG16: =SUM(320*AF16) -> #DIV/0! | AH16: =SUM(AC16-AG16) -> #DIV/0! | AI16: =AD16*AJ16 -> 0 | AJ16: =305/1185 -> 0.25738397 | AK16: =IF(Z16>0,AI16/Z16,0) -> 0
A17: =ELEC!C17 -> 43966 | B17: =B16 -> 8621.09 | C17: =B17-B16 -> 0 | D17: =D16 -> 146479.8 | E17: =SUM(D17-D16) -> 0 | F17: =IF(C17>0,E17/C17,0) -> 0 | H17: =H16 -> 8497 | I17: =IF(B17-H17<=0,"ok","oil change") -> oil change | J17: =J16 -> 10689.42 | K17: =J17-J16 -> 0 | L17: =L16 -> 237074.9 | M17: =SUM(L17-L16) -> 0 | N17: =IF(K17>0,M17/K17,0) -> 0 | P17: =P16 -> 10873 | Q17: =IF(J17-P17<=0,"ok","oil change") -> ok | R17: =R16 -> 11127 | S17: =R17-R16 -> 0 | T17: =T16 -> 236923 | U17: =SUM(T17-T16) -> 0 | V17: =IF(S17>0,U17/S17,0) -> 0 | X17: =X16 -> 11889 | Y17: =IF(R17-X17<=0,"ok","oil change") -> ok | Z17: =C17+K17+S17 -> 0 | AA17: =U17+M17+E17 -> 0 | AB17: =V17+N17+F17 -> 0 | AC17: =IF(Z17>0,AA17/Z17,0) -> 0 | AD17: =ELEC!Q17 -> 0 | AE17: =SUM(AD17/Z17) -> #DIV/0! | AF17: =SUM(AE17/1600) -> #DIV/0! | AG17: =SUM(320*AF17) -> #DIV/0! | AH17: =SUM(AC17-AG17) -> #DIV/0! | AI17: =AD17*AJ17 -> 0 | AJ17: =305/1185 -> 0.25738397 | AK17: =IF(Z17>0,AI17/Z17,0) -> 0
A18: =ELEC!C18 -> 43967 | B18: =B17 -> 8621.09 | C18: =B18-B17 -> 0 | D18: =D17 -> 146479.8 | E18: =SUM(D18-D17) -> 0 | F18: =IF(C18>0,E18/C18,0) -> 0 | H18: =H17 -> 8497 | I18: =IF(B18-H18<=0,"ok","oil change") -> oil change | J18: =J17 -> 10689.42 | K18: =J18-J17 -> 0 | L18: =L17 -> 237074.9 | M18: =SUM(L18-L17) -> 0 | N18: =IF(K18>0,M18/K18,0) -> 0 | P18: =P17 -> 10873 | Q18: =IF(J18-P14<=0,"ok","oil change") -> ok | R18: =R17 -> 11127 | S18: =R18-R17 -> 0 | T18: =T17 -> 236923 | U18: =SUM(T18-T17) -> 0 | V18: =IF(S18>0,U18/S18,0) -> 0 | X18: =X17 -> 11889 | Y18: =IF(R18-X18<=0,"ok","oil change") -> ok | Z18: =C18+K18+S18 -> 0 | AA18: =U18+M18+E18 -> 0 | AB18: =V18+N18+F18 -> 0 | AC18: =IF(Z18>0,AA18/Z18,0) -> 0 | AD18: =ELEC!Q18 -> 0 | AE18: =SUM(AD18/Z18) -> #DIV/0! | AF18: =SUM(AE18/1600) -> #DIV/0! | AG18: =SUM(320*AF18) -> #DIV/0! | AH18: =SUM(AC18-AG18) -> #DIV/0! | AI18: =AD18*AJ18 -> 0 | AJ18: =305/1185 -> 0.25738397 | AK18: =IF(Z18>0,AI18/Z18,0) -> 0
A19: =ELEC!C19 -> 43968 | B19: =B18 -> 8621.09 | C19: =B19-B18 -> 0 | D19: =D18 -> 146479.8 | E19: =SUM(D19-D18) -> 0 | F19: =IF(C19>0,E19/C19,0) -> 0 | H19: =H18 -> 8497 | I19: =IF(B19-H19<=0,"ok","oil change") -> oil change | J19: =J18 -> 10689.42 | K19: =J19-J18 -> 0 | L19: =L18 -> 237074.9 | M19: =SUM(L19-L18) -> 0 | N19: =IF(K19>0,M19/K19,0) -> 0 | P19: =P18 -> 10873 | Q19: =IF(J19-P19<=0,"ok","oil change") -> ok | R19: =R18 -> 11127 | S19: =R19-R18 -> 0 | T19: =T18 -> 236923 | U19: =SUM(T19-T18) -> 0 | V19: =IF(S19>0,U19/S19,0) -> 0 | X19: =X18 -> 11889 | Y19: =IF(R19-X19<=0,"ok","oil change") -> ok | Z19: =C19+K19+S19 -> 0 | AA19: =U19+M19+E19 -> 0 | AB19: =V19+N19+F19 -> 0 | AC19: =IF(Z19>0,AA19/Z19,0) -> 0 | AD19: =ELEC!Q19 -> 0 | AE19: =SUM(AD19/Z19) -> #DIV/0! | AF19: =SUM(AE19/1600) -> #DIV/0! | AG19: =SUM(320*AF19) -> #DIV/0! | AH19: =SUM(AC19-AG19) -> #DIV/0! | AI19: =AD19*AJ19 -> 0 | AJ19: =305/1185 -> 0.25738397 | AK19: =IF(Z19>0,AI19/Z19,0) -> 0
A20: =ELEC!C20 -> 43969 | B20: =B19 -> 8621.09 | C20: =B20-B19 -> 0 | D20: =D19 -> 146479.8 | E20: =SUM(D20-D19) -> 0 | F20: =IF(C20>0,E20/C20,0) -> 0 | H20: =H19 -> 8497 | I20: =IF(B20-H20<=0,"ok","oil change") -> oil change | J20: =J19 -> 10689.42 | K20: =J20-J19 -> 0 | L20: =L19 -> 237074.9 | M20: =SUM(L20-L19) -> 0 | N20: =IF(K20>0,M20/K20,0) -> 0 | P20: =P19 -> 10873 | Q20: =IF(J20-P20<=0,"ok","oil change") -> ok | R20: =R19 -> 11127 | S20: =R20-R19 -> 0 | T20: =T19 -> 236923 | U20: =SUM(T20-T19) -> 0 | V20: =IF(S20>0,U20/S20,0) -> 0 | X20: =X19 -> 11889 | Y20: =IF(R20-X20<=0,"ok","oil change") -> ok | Z20: =C20+K20+S20 -> 0 | AA20: =U20+M20+E20 -> 0 | AB20: =V20+N20+F20 -> 0 | AC20: =IF(Z20>0,AA20/Z20,0) -> 0 | AD20: =ELEC!Q20 -> 0 | AE20: =SUM(AD20/Z20) -> #DIV/0! | AF20: =SUM(AE20/1600) -> #DIV/0! | AG20: =SUM(320*AF20) -> #DIV/0! | AH20: =SUM(AC20-AG20) -> #DIV/0! | AI20: =AD20*AJ20 -> 0 | AJ20: =305/1185 -> 0.25738397 | AK20: =IF(Z20>0,AI20/Z20,0) -> 0
A21: =ELEC!C21 -> 43970 | B21: =B20 -> 8621.09 | C21: =B21-B20 -> 0 | D21: =D20 -> 146479.8 | E21: =SUM(D21-D20) -> 0 | F21: =IF(C21>0,E21/C21,0) -> 0 | H21: =H20 -> 8497 | I21: =IF(B21-H21<=0,"ok","oil change") -> oil change | J21: =J20 -> 10689.42 | K21: =J21-J20 -> 0 | L21: =L20 -> 237074.9 | M21: =SUM(L21-L20) -> 0 | N21: =IF(K21>0,M21/K21,0) -> 0 | P21: =P20 -> 10873 | Q21: =IF(J21-P21<=0,"ok","oil change") -> ok | R21: =R20 -> 11127 | S21: =R21-R20 -> 0 | T21: =T20 -> 236923 | U21: =SUM(T21-T20) -> 0 | V21: =IF(S21>0,U21/S21,0) -> 0 | X21: =X20 -> 11889 | Y21: =Y20 -> ok | Z21: =C21+K21+S21 -> 0 | AA21: =U21+M21+E21 -> 0 | AB21: =V21+N21+F21 -> 0 | AC21: =IF(Z21>0,AA21/Z21,0) -> 0 | AD21: =ELEC!Q21 -> 0 | AE21: =SUM(AD21/Z21) -> #DIV/0! | AF21: =SUM(AE21/1600) -> #DIV/0! | AG21: =SUM(320*AF21) -> #DIV/0! | AH21: =SUM(AC21-AG21) -> #DIV/0! | AI21: =AD21*AJ21 -> 0 | AJ21: =305/1185 -> 0.25738397 | AK21: =IF(Z21>0,AI21/Z21,0) -> 0
A22: =ELEC!C22 -> 43971 | B22: =B21 -> 8621.09 | C22: =B22-B21 -> 0 | D22: =D21 -> 146479.8 | E22: =SUM(D22-D21) -> 0 | F22: =IF(C22>0,E22/C22,0) -> 0 | H22: =H21 -> 8497 | I22: =IF(B22-H22<=0,"ok","oil change") -> oil change | J22: =J21 -> 10689.42 | K22: =J22-J21 -> 0 | L22: =L21 -> 237074.9 | M22: =SUM(L22-L21) -> 0 | N22: =IF(K22>0,M22/K22,0) -> 0 | P22: =P21 -> 10873 | Q22: =IF(J22-P22<=0,"ok","oil change") -> ok | R22: =R21 -> 11127 | S22: =R22-R21 -> 0 | T22: =T21 -> 236923 | U22: =SUM(T22-T21) -> 0 | V22: =IF(S22>0,U22/S22,0) -> 0 | X22: =X21 -> 11889 | Y22: =IF(R22-X22<=0,"ok","oil change") -> ok | Z22: =C22+K22+S22 -> 0 | AA22: =U22+M22+E22 -> 0 | AB22: =V22+N22+F22 -> 0 | AC22: =IF(Z22>0,AA22/Z22,0) -> 0 | AD22: =ELEC!Q22 -> 0 | AE22: =SUM(AD22/Z22) -> #DIV/0! | AF22: =SUM(AE22/1600) -> #DIV/0! | AG22: =SUM(320*AF22) -> #DIV/0! | AH22: =SUM(AC22-AG22) -> #DIV/0! | AI22: =AD22*AJ22 -> 0 | AJ22: =305/1185 -> 0.25738397 | AK22: =IF(Z22>0,AI22/Z22,0) -> 0
A23: =ELEC!C23 -> 43972 | B23: =B22 -> 8621.09 | C23: =B23-B22 -> 0 | D23: =D22 -> 146479.8 | E23: =SUM(D23-D22) -> 0 | F23: =IF(C23>0,E23/C23,0) -> 0 | H23: =H22 -> 8497 | I23: =IF(B23-H23<=0,"ok","oil change") -> oil change | J23: =J22 -> 10689.42 | K23: =J23-J22 -> 0 | L23: =L22 -> 237074.9 | M23: =SUM(L23-L22) -> 0 | N23: =IF(K23>0,M23/K23,0) -> 0 | P23: =P22 -> 10873 | Q23: =IF(J23-P23<=0,"ok","oil change") -> ok | R23: =R22 -> 11127 | S23: =R23-R22 -> 0 | T23: =T22 -> 236923 | U23: =SUM(T23-T22) -> 0 | V23: =IF(S23>0,U23/S23,0) -> 0 | X23: =X22 -> 11889 | Y23: =IF(R23-X23<=0,"ok","oil change") -> ok | Z23: =C23+K23+S23 -> 0 | AA23: =U23+M23+E23 -> 0 | AB23: =V23+N23+F23 -> 0 | AC23: =IF(Z23>0,AA23/Z23,0) -> 0 | AD23: =ELEC!Q23 -> 0 | AE23: =SUM(AD23/Z23) -> #DIV/0! | AF23: =SUM(AE23/1600) -> #DIV/0! | AG23: =SUM(320*AF23) -> #DIV/0! | AH23: =SUM(AC23-AG23) -> #DIV/0! | AI23: =AD23*AJ23 -> 0 | AJ23: =305/1185 -> 0.25738397 | AK23: =IF(Z23>0,AI23/Z23,0) -> 0
A24: =ELEC!C24 -> 43973 | B24: =B23 -> 8621.09 | C24: =B24-B23 -> 0 | D24: =D23 -> 146479.8 | E24: =SUM(D24-D23) -> 0 | F24: =IF(C24>0,E24/C24,0) -> 0 | H24: =H23 -> 8497 | I24: =IF(B24-H24<=0,"ok","oil change") -> oil change | J24: =J23 -> 10689.42 | K24: =J24-J23 -> 0 | L24: =L23 -> 237074.9 | M24: =SUM(L24-L23) -> 0 | N24: =IF(K24>0,M24/K24,0) -> 0 | P24: =P23 -> 10873 | Q24: =IF(J24-P24<=0,"ok","oil change") -> ok | R24: =R23 -> 11127 | S24: =R24-R23 -> 0 | T24: =T23 -> 236923 | U24: =SUM(T24-T23) -> 0 | V24: =IF(S24>0,U24/S24,0) -> 0 | X24: =X23 -> 11889 | Y24: =IF(R24-X24<=0,"ok","oil change") -> ok | Z24: =C24+K24+S24 -> 0 | AA24: =U24+M24+E24 -> 0 | AB24: =V24+N24+F24 -> 0 | AC24: =IF(Z24>0,AA24/Z24,0) -> 0 | AD24: =ELEC!Q24 -> 0 | AE24: =SUM(AD24/Z24) -> #DIV/0! | AF24: =SUM(AE24/1600) -> #DIV/0! | AG24: =SUM(320*AF24) -> #DIV/0! | AH24: =SUM(AC24-AG24) -> #DIV/0! | AI24: =AD24*AJ24 -> 0 | AJ24: =305/1185 -> 0.25738397 | AK24: =IF(Z24>0,AI24/Z24,0) -> 0
A25: =ELEC!C25 -> 43974 | B25: =B24 -> 8621.09 | C25: =B25-B24 -> 0 | D25: =D24 -> 146479.8 | E25: =SUM(D25-D24) -> 0 | F25: =IF(C25>0,E25/C25,0) -> 0 | H25: =H24 -> 8497 | I25: =IF(B25-H25<=0,"ok","oil change") -> oil change | J25: =J24 -> 10689.42 | K25: =J25-J24 -> 0 | L25: =L24 -> 237074.9 | M25: =SUM(L25-L24) -> 0 | N25: =IF(K25>0,M25/K25,0) -> 0 | P25: =P24 -> 10873 | Q25: =IF(J25-P25<=0,"ok","oil change") -> ok | R25: =R24 -> 11127 | S25: =R25-R24 -> 0 | T25: =T24 -> 236923 | U25: =SUM(T25-T24) -> 0 | V25: =IF(S25>0,U25/S25,0) -> 0 | X25: =X24 -> 11889 | Y25: =IF(R25-X25<=0,"ok","oil change") -> ok | Z25: =C25+K25+S25 -> 0 | AA25: =U25+M25+E25 -> 0 | AB25: =V25+N25+F25 -> 0 | AC25: =IF(Z25>0,AA25/Z25,0) -> 0 | AD25: =ELEC!Q25 -> 0 | AE25: =SUM(AD25/Z25) -> #DIV/0! | AF25: =SUM(AE25/1600) -> #DIV/0! | AG25: =SUM(320*AF25) -> #DIV/0! | AH25: =SUM(AC25-AG25) -> #DIV/0! | AI25: =AD25*AJ25 -> 0 | AJ25: =305/1185 -> 0.25738397 | AK25: =IF(Z25>0,AI25/Z25,0) -> 0
A26: =ELEC!C26 -> 43975 | B26: =B25 -> 8621.09 | C26: =B26-B25 -> 0 | D26: =D25 -> 146479.8 | E26: =SUM(D26-D25) -> 0 | F26: =IF(C26>0,E26/C26,0) -> 0 | H26: =H25 -> 8497 | I26: =IF(B26-H26<=0,"ok","oil change") -> oil change | J26: =J25 -> 10689.42 | K26: =J26-J25 -> 0 | L26: =L25 -> 237074.9 | M26: =SUM(L26-L25) -> 0 | N26: =IF(K26>0,M26/K26,0) -> 0 | P26: =P25 -> 10873 | Q26: =IF(J26-P26<=0,"ok","oil change") -> ok | R26: =R25 -> 11127 | S26: =R26-R25 -> 0 | T26: =T25 -> 236923 | U26: =SUM(T26-T25) -> 0 | V26: =IF(S26>0,U26/S26,0) -> 0 | X26: =X25 -> 11889 | Y26: =IF(R26-X26<=0,"ok","oil change") -> ok | Z26: =C26+K26+S26 -> 0 | AA26: =U26+M26+E26 -> 0 | AB26: =V26+N26+F26 -> 0 | AC26: =IF(Z26>0,AA26/Z26,0) -> 0 | AD26: =ELEC!Q26 -> 0 | AE26: =SUM(AD26/Z26) -> #DIV/0! | AF26: =SUM(AE26/1600) -> #DIV/0! | AG26: =SUM(320*AF26) -> #DIV/0! | AH26: =SUM(AC26-AG26) -> #DIV/0! | AI26: =AD26*AJ26 -> 0 | AJ26: =305/1185 -> 0.25738397 | AK26: =IF(Z26>0,AI26/Z26,0) -> 0
A27: =ELEC!C27 -> 43976 | B27: =B26 -> 8621.09 | C27: =B27-B26 -> 0 | D27: =D26 -> 146479.8 | E27: =SUM(D27-D26) -> 0 | F27: =IF(C27>0,E27/C27,0) -> 0 | H27: =H26 -> 8497 | I27: =IF(B27-H27<=0,"ok","oil change") -> oil change | J27: =J26 -> 10689.42 | K27: =J27-J26 -> 0 | L27: =L26 -> 237074.9 | M27: =SUM(L27-L26) -> 0 | N27: =IF(K27>0,M27/K27,0) -> 0 | P27: =P26 -> 10873 | Q27: =IF(J27-P27<=0,"ok","oil change") -> ok | R27: =R26 -> 11127 | S27: =R27-R26 -> 0 | T27: =T26 -> 236923 | U27: =SUM(T27-T26) -> 0 | V27: =IF(S27>0,U27/S27,0) -> 0 | X27: =X26 -> 11889 | Y27: =IF(R27-X27<=0,"ok","oil change") -> ok | Z27: =C27+K27+S27 -> 0 | AA27: =U27+M27+E27 -> 0 | AB27: =V27+N27+F27 -> 0 | AC27: =IF(Z27>0,AA27/Z27,0) -> 0 | AD27: =ELEC!Q27 -> 0 | AE27: =SUM(AD27/Z27) -> #DIV/0! | AF27: =SUM(AE27/1600) -> #DIV/0! | AG27: =SUM(320*AF27) -> #DIV/0! | AH27: =SUM(AC27-AG27) -> #DIV/0! | AI27: =AD27*AJ27 -> 0 | AJ27: =305/1185 -> 0.25738397 | AK27: =IF(Z27>0,AI27/Z27,0) -> 0
A28: =ELEC!C28 -> 43977 | B28: =B27 -> 8621.09 | C28: =B28-B27 -> 0 | D28: =D27 -> 146479.8 | E28: =SUM(D28-D27) -> 0 | F28: =IF(C28>0,E28/C28,0) -> 0 | H28: =H27 -> 8497 | I28: =IF(B28-H28<=0,"ok","oil change") -> oil change | J28: =J27 -> 10689.42 | K28: =J28-J27 -> 0 | L28: =L27 -> 237074.9 | M28: =SUM(L28-L27) -> 0 | N28: =IF(K28>0,M28/K28,0) -> 0 | P28: =P27 -> 10873 | Q28: =IF(J28-P28<=0,"ok","oil change") -> ok | R28: =R27 -> 11127 | S28: =R28-R27 -> 0 | T28: =T27 -> 236923 | U28: =SUM(T28-T27) -> 0 | V28: =IF(S28>0,U28/S28,0) -> 0 | X28: =X27 -> 11889 | Y28: =IF(R28-X28<=0,"ok","oil change") -> ok | Z28: =C28+K28+S28 -> 0 | AA28: =U28+M28+E28 -> 0 | AB28: =V28+N28+F28 -> 0 | AC28: =IF(Z28>0,AA28/Z28,0) -> 0 | AD28: =ELEC!Q28 -> 0 | AE28: =SUM(AD28/Z28) -> #DIV/0! | AF28: =SUM(AE28/1600) -> #DIV/0! | AG28: =SUM(320*AF28) -> #DIV/0! | AH28: =SUM(AC28-AG28) -> #DIV/0! | AI28: =AD28*AJ28 -> 0 | AJ28: =305/1185 -> 0.25738397 | AK28: =IF(Z28>0,AI28/Z28,0) -> 0
A29: =ELEC!C29 -> 43978 | B29: =B28 -> 8621.09 | C29: =B29-B28 -> 0 | D29: =D28 -> 146479.8 | E29: =SUM(D29-D28) -> 0 | F29: =IF(C29>0,E29/C29,0) -> 0 | H29: =H28 -> 8497 | I29: =IF(B29-H29<=0,"ok","oil change") -> oil change | J29: =J28 -> 10689.42 | K29: =J29-J28 -> 0 | L29: =L28 -> 237074.9 | M29: =SUM(L29-L28) -> 0 | N29: =IF(K29>0,M29/K29,0) -> 0 | P29: =P28 -> 10873 | Q29: =IF(J29-P29<=0,"ok","oil change") -> ok | R29: =R28 -> 11127 | S29: =R29-R28 -> 0 | T29: =T28 -> 236923 | U29: =SUM(T29-T28) -> 0 | V29: =IF(S29>0,U29/S29,0) -> 0 | X29: =X28 -> 11889 | Y29: =IF(R29-X29<=0,"ok","oil change") -> ok | Z29: =C29+K29+S29 -> 0 | AA29: =U29+M29+E29 -> 0 | AB29: =V29+N29+F29 -> 0 | AC29: =IF(Z29>0,AA29/Z29,0) -> 0 | AD29: =ELEC!Q29 -> 0 | AE29: =SUM(AD29/Z29) -> #DIV/0! | AF29: =SUM(AE29/1600) -> #DIV/0! | AG29: =SUM(320*AF29) -> #DIV/0! | AH29: =SUM(AC29-AG29) -> #DIV/0! | AI29: =AD29*AJ29 -> 0 | AJ29: =305/1185 -> 0.25738397 | AK29: =IF(Z29>0,AI29/Z29,0) -> 0
A30: =ELEC!C30 -> 43979 | B30: =B29 -> 8621.09 | C30: =B30-B29 -> 0 | D30: =D29 -> 146479.8 | E30: =SUM(D30-D29) -> 0 | F30: =IF(C30>0,E30/C30,0) -> 0 | H30: =H29 -> 8497 | I30: =IF(B30-H30<=0,"ok","oil change") -> oil change | J30: =J29 -> 10689.42 | K30: =J30-J29 -> 0 | L30: =L29 -> 237074.9 | M30: =SUM(L30-L29) -> 0 | N30: =IF(K30>0,M30/K30,0) -> 0 | P30: =P29 -> 10873 | Q30: =IF(J30-P30<=0,"ok","oil change") -> ok | R30: =R29 -> 11127 | S30: =R30-R29 -> 0 | T30: =T29 -> 236923 | U30: =SUM(T30-T29) -> 0 | V30: =IF(S30>0,U30/S30,0) -> 0 | X30: =X29 -> 11889 | Y30: =IF(R30-X30<=0,"ok","oil change") -> ok | Z30: =C30+K30+S30 -> 0 | AA30: =U30+M30+E30 -> 0 | AB30: =V30+N30+F30 -> 0 | AC30: =IF(Z30>0,AA30/Z30,0) -> 0 | AD30: =ELEC!Q30 -> 0 | AE30: =SUM(AD30/Z30) -> #DIV/0! | AF30: =SUM(AE30/1600) -> #DIV/0! | AG30: =SUM(320*AF30) -> #DIV/0! | AH30: =SUM(AC30-AG30) -> #DIV/0! | AI30: =AD30*AJ30 -> 0 | AJ30: =305/1185 -> 0.25738397 | AK30: =IF(Z30>0,AI30/Z30,0) -> 0
A31: =ELEC!C31 -> 43980 | B31: =B30 -> 8621.09 | C31: =B31-B30 -> 0 | D31: =D30 -> 146479.8 | E31: =SUM(D31-D30) -> 0 | F31: =IF(C31>0,E31/C31,0) -> 0 | H31: =H30 -> 8497 | I31: =IF(B31-H31<=0,"ok","oil change") -> oil change | J31: =J30 -> 10689.42 | K31: =J31-J30 -> 0 | L31: =L30 -> 237074.9 | M31: =SUM(L31-L30) -> 0 | N31: =IF(K31>0,M31/K31,0) -> 0 | P31: =P30 -> 10873 | Q31: =IF(J31-P31<=0,"ok","oil change") -> ok | R31: =R30 -> 11127 | S31: =R31-R30 -> 0 | T31: =T30 -> 236923 | U31: =SUM(T31-T30) -> 0 | V31: =IF(S31>0,U31/S31,0) -> 0 | X31: =X30 -> 11889 | Y31: =IF(R31-X31<=0,"ok","oil change") -> ok | Z31: =C31+K31+S31 -> 0 | AA31: =U31+M31+E31 -> 0 | AB31: =V31+N31+F31 -> 0 | AC31: =IF(Z31>0,AA31/Z31,0) -> 0 | AD31: =ELEC!Q31 -> 0 | AE31: =SUM(AD31/Z31) -> #DIV/0! | AF31: =SUM(AE31/1600) -> #DIV/0! | AG31: =SUM(320*AF31) -> #DIV/0! | AH31: =SUM(AC31-AG31) -> #DIV/0! | AI31: =AD31*AJ31 -> 0 | AJ31: =305/1185 -> 0.25738397 | AK31: =IF(Z31>0,AI31/Z31,0) -> 0
A32: =ELEC!C32 -> 43981 | B32: =B31 -> 8621.09 | C32: =B32-B31 -> 0 | D32: =D31 -> 146479.8 | E32: =SUM(D32-D31) -> 0 | F32: =IF(C32>0,E32/C32,0) -> 0 | H32: =H31 -> 8497 | I32: =IF(B32-H32<=0,"ok","oil change") -> oil change | J32: =J31 -> 10689.42 | K32: =J32-J31 -> 0 | L32: =L31 -> 237074.9 | M32: =SUM(L32-L31) -> 0 | N32: =IF(K32>0,M32/K32,0) -> 0 | P32: =P31 -> 10873 | Q32: =IF(J32-P32<=0,"ok","oil change") -> ok | R32: =R31 -> 11127 | S32: =R32-R31 -> 0 | T32: =T31 -> 236923 | U32: =SUM(T32-T31) -> 0 | V32: =IF(S32>0,U32/S32,0) -> 0 | X32: =X31 -> 11889 | Y32: =IF(R32-X32<=0,"ok","oil change") -> ok | Z32: =C32+K32+S32 -> 0 | AA32: =U32+M32+E32 -> 0 | AB32: =V32+N32+F32 -> 0 | AC32: =IF(Z32>0,AA32/Z32,0) -> 0 | AD32: =ELEC!Q32 -> 0 | AE32: =SUM(AD32/Z32) -> #DIV/0! | AF32: =SUM(AE32/1600) -> #DIV/0! | AG32: =SUM(320*AF32) -> #DIV/0! | AH32: =SUM(AC32-AG32) -> #DIV/0! | AI32: =AD32*AJ32 -> 0 | AJ32: =305/1185 -> 0.25738397 | AK32: =IF(Z32>0,AI32/Z32,0) -> 0
A33: =ELEC!C33 -> 43982 | B33: =B32 -> 8621.09 | C33: =B33-B32 -> 0 | D33: =D32 -> 146479.8 | E33: =SUM(D33-D32) -> 0 | F33: =IF(C33>0,E33/C33,0) -> 0 | H33: =H32 -> 8497 | I33: =IF(B33-H33<=0,"ok","oil change") -> oil change | J33: =J32 -> 10689.42 | K33: =J33-J32 -> 0 | L33: =L32 -> 237074.9 | M33: =SUM(L33-L32) -> 0 | N33: =IF(K33>0,M33/K33,0) -> 0 | P33: =P32 -> 10873 | Q33: =IF(J33-P33<=0,"ok","oil change") -> ok | R33: =R32 -> 11127 | S33: =R33-R32 -> 0 | T33: =T32 -> 236923 | U33: =SUM(T33-T32) -> 0 | V33: =IF(S33>0,U33/S33,0) -> 0 | X33: =X32 -> 11889 | Y33: =IF(R33-X33<=0,"ok","oil change") -> ok | Z33: =C33+K33+S33 -> 0 | AA33: =U33+M33+E33 -> 0 | AB33: =V33+N33+F33 -> 0 | AC33: =IF(Z33>0,AA33/Z33,0) -> 0 | AD33: =ELEC!Q33 -> 0 | AE33: =SUM(AD33/Z33) -> #DIV/0! | AF33: =SUM(AE33/1600) -> #DIV/0! | AG33: =SUM(320*AF33) -> #DIV/0! | AH33: =SUM(AC33-AG33) -> #DIV/0!
P34: =+O34/3 -> 0 | U34: =SUM(C35:S35) -> 12 | X34: 341 | Z34: =SUM(Z3:Z33) -> 12
C35: =SUM(C3:C33) -> 0 | K35: =SUM(K3:K33) -> 0 | S35: =SUM(S3:S33) -> 12

Sheet Sheet1
A1: TOTAL CH RH | B1: TOTAL CH cons KW | C1: TOTAL ELIC KW | D1: TOTAL EDL | E1: TOTAL GEN KW | F1: GEN HR | G1: WATER IN | H1: TOTAL CT | I1: TOTAL WATER | J1: Date
A2: =ELEC!T3+ELEC!X1+ELEC!AB3 -> #VALUE! | B2: =ELEC!AF3 -> 835 | C2: =ELEC!N3 -> 8802.4 | D2: =C2-E2 -> 7402.4 | E2: =ELEC!Q3 -> 1400 | F2: =GEN!Z2 -> 2.87 | G2: =WATER!C5+WATER!H5 -> 0 | H2: =WATER!L5 -> 1 | I2: =WATER!BC5+WATER!BD5+WATER!BE6-Sheet1!G2 -> -28.1 | J2: ='B5'!A4 -> 43951
A3: =ELEC!T4+ELEC!X2+ELEC!AB4 -> 3 | B3: =ELEC!AF4 -> 607 | C3: =ELEC!N4 -> 8701.6 | D3: =C3-E3 -> 7167.6 | E3: =ELEC!Q4 -> 1534 | F3: =GEN!Z3 -> 3 | G3: =WATER!C6+WATER!H6 -> 0 | H3: =WATER!L6 -> 0 | I3: =WATER!BC6+WATER!BD6+WATER!BE7-Sheet1!G3 -> -48.9 | J3: ='B5'!A5 -> 43952
A4: =ELEC!T5+ELEC!X5+ELEC!AB5 -> 8 | B4: =ELEC!AF5 -> 1395 | C4: =ELEC!N5 -> 11338.4 | D4: =C4-E4 -> 9872.4 | E4: =ELEC!Q5 -> 1466 | F4: =GEN!Z4 -> 2 | G4: =WATER!C7+WATER!H7 -> 0 | H4: =WATER!L7 -> 6 | I4: =WATER!BC7+WATER!BD7+WATER!BE8-Sheet1!G4 -> 198.1 | J4: ='B5'!A6 -> 43953
A5: =ELEC!T6+ELEC!X6+ELEC!AB6 -> 4 | B5: =ELEC!AF6 -> 1030 | C5: =ELEC!N6 -> 10592 | D5: =C5-E5 -> 9592 | E5: =ELEC!Q6 -> 1000 | F5: =GEN!Z5 -> 4 | G5: =WATER!C8+WATER!H8 -> 340 | H5: =WATER!L8 -> 2 | I5: =WATER!BC8+WATER!BD8+WATER!BE9-Sheet1!G5 -> -319.8 | J5: ='B5'!A7 -> 43954
A6: =ELEC!T7+ELEC!X7+ELEC!AB7 -> 6 | B6: =ELEC!AF7 -> 0 | C6: =ELEC!N7 -> 0 | D6: =C6-E6 -> 0 | E6: =ELEC!Q24 -> 0 | F6: =GEN!Z6 -> 3 | G6: =WATER!C9+WATER!H9 -> 0 | H6: =WATER!L9 -> 6 | I6: =WATER!BC9+WATER!BD9+WATER!BE10-Sheet1!G6 -> -15.9 | J6: ='B5'!A8 -> 43955
A7: =ELEC!T8+ELEC!X8+ELEC!AB8 -> 0 | B7: =ELEC!AF8 -> 0 | C7: =ELEC!N8 -> 0 | D7: =C7-E7 -> 0 | E7: =ELEC!Q8 -> 0 | F7: =GEN!Z7 -> 0 | G7: =WATER!C10+WATER!H10 -> 0 | H7: =WATER!L10 -> 0 | I7: =WATER!BC10+WATER!BD10+WATER!BE11-Sheet1!G7 -> 0 | J7: ='B5'!A9 -> 43956
A8: =ELEC!T9+ELEC!X9+ELEC!AB9 -> 0 | B8: =ELEC!AF9 -> 0 | C8: =ELEC!N9 -> 0 | D8: =C8-E8 -> 0 | E8: =ELEC!Q9 -> 0 | F8: =GEN!Z8 -> 0 | G8: =WATER!C11+WATER!H11 -> 0 | H8: =WATER!L11 -> 0 | I8: =WATER!BC11+WATER!BD11+WATER!BE12-Sheet1!G8 -> 0 | J8: ='B5'!A10 -> 43957
A9: =ELEC!T10+ELEC!X10+ELEC!AB10 -> 0 | B9: =ELEC!AF10 -> 0 | C9: =ELEC!N10 -> 0 | D9: =C9-E9 -> 0 | E9: =ELEC!Q10 -> 0 | F9: =GEN!Z9 -> 0 | G9: =WATER!C12+WATER!H12 -> 0 | H9: =WATER!L12 -> 0 | I9: =WATER!BC12+WATER!BD12+WATER!BE13-Sheet1!G9 -> 0 | J9: ='B5'!A11 -> 43958
A10: =ELEC!T11+ELEC!X11+ELEC!AB11 -> 0 | B10: =ELEC!AF11 -> 0 | C10: =ELEC!N11 -> 0 | D10: =C10-E10 -> 0 | E10: =ELEC!Q11 -> 0 | F10: =GEN!Z10 -> 0 | G10: =WATER!C13+WATER!H13 -> 0 | H10: =WATER!L13 -> 0 | I10: =WATER!BC13+WATER!BD13+WATER!BE14-Sheet1!G10 -> 0 | J10: ='B5'!A12 -> 43959
A11: =ELEC!T12+ELEC!X12+ELEC!AB12 -> 0 | B11: =ELEC!AF12 -> 0 | C11: =ELEC!N12 -> 0 | D11: =C11-E11 -> 0 | E11: =ELEC!Q12 -> 0 | F11: =GEN!Z11 -> 0 | G11: =WATER!C14+WATER!H14 -> 0 | H11: =WATER!L14 -> 0 | I11: =WATER!BC14+WATER!BD14+WATER!BE15-Sheet1!G11 -> 0 | J11: ='B5'!A13 -> 43960
A12: =ELEC!T13+ELEC!X13+ELEC!AB13 -> 0 | B12: =ELEC!AF13 -> 0 | C12: =ELEC!N13 -> 0 | D12: =C12-E12 -> 0 | E12: =ELEC!Q13 -> 0 | F12: =GEN!Z12 -> 0 | G12: =WATER!C15+WATER!H15 -> 0 | H12: =WATER!L15 -> 0 | I12: =WATER!BC15+WATER!BD15+WATER!BE16-Sheet1!G12 -> 0 | J12: ='B5'!A14 -> 43961
A13: =ELEC!T14+ELEC!X14+ELEC!AB14 -> 0 | B13: =ELEC!AF14 -> 0 | C13: =ELEC!N14 -> 0 | D13: =C13-E13 -> 0 | E13: =ELEC!Q14 -> 0 | F13: =GEN!Z13 -> 0 | G13: =WATER!C16+WATER!H16 -> 0 | H13: =WATER!L16 -> 0 | I13: =WATER!BC16+WATER!BD16+WATER!BE17-Sheet1!G13 -> 0 | J13: ='B5'!A15 -> 43962
A14: =ELEC!T15+ELEC!X15+ELEC!AB15 -> 0 | B14: =ELEC!AF15 -> 0 | C14: =ELEC!N15 -> 0 | D14: =C14-E14 -> 0 | E14: =ELEC!Q15 -> 0 | F14: =GEN!Z14 -> 0 | G14: =WATER!C17+WATER!H17 -> 0 | H14: =WATER!L17 -> 0 | I14: =WATER!BC17+WATER!BD17+WATER!BE18-Sheet1!G14 -> 0 | J14: ='B5'!A16 -> 43963
A15: =ELEC!T16+ELEC!X16+ELEC!AB16 -> 0 | B15: =ELEC!AF16 -> 0 | C15: =ELEC!N16 -> 0 | D15: =C15-E15 -> 0 | E15: =ELEC!Q16 -> 0 | F15: =GEN!Z15 -> 0 | G15: =WATER!C18+WATER!H18 -> 0 | H15: =WATER!L18 -> 0 | I15: =WATER!BC18+WATER!BD18+WATER!BE19-Sheet1!G15 -> 0 | J15: ='B5'!A17 -> 43964
A16: =ELEC!T17+ELEC!X17+ELEC!AB17 -> 0 | B16: =ELEC!AF17 -> 0 | C16: =ELEC!N17 -> 0 | D16: =C16-E16 -> 0 | E16: =ELEC!Q17 -> 0 | F16: =GEN!Z16 -> 0 | G16: =WATER!C19+WATER!H19 -> 0 | H16: =WATER!L19 -> 0 | I16: =WATER!BC19+WATER!BD19+WATER!BE20-Sheet1!G16 -> 0 | J16: ='B5'!A18 -> 43965
A17: =ELEC!T18+ELEC!X18+ELEC!AB18 -> 0 | B17: =ELEC!AF18 -> 0 | C17: =ELEC!N18 -> 0 | D17: =C17-E17 -> 0 | E17: =ELEC!Q18 -> 0 | F17: =GEN!Z17 -> 0 | G17: =WATER!C20+WATER!H20 -> 0 | H17: =WATER!L20 -> 0 | I17: =WATER!BC20+WATER!BD20+WATER!BE21-Sheet1!G17 -> 0 | J17: ='B5'!A19 -> 43966
A18: =ELEC!T19+ELEC!X19+ELEC!AB19 -> 0 | B18: =ELEC!AF19 -> 0 | C18: =ELEC!N19 -> 0 | D18: =C18-E18 -> 0 | E18: =ELEC!Q19 -> 0 | F18: =GEN!Z18 -> 0 | G18: =WATER!C21+WATER!H21 -> 0 | H18: =WATER!L21 -> 0 | I18: =WATER!BC21+WATER!BD21+WATER!BE22-Sheet1!G18 -> 0 | J18: ='B5'!A20 -> 43967
... A29: =ELEC!T30+ELEC!X30+ELEC!AB30 -> 0 | B29: =ELEC!AF30 -> 0 | C29: =ELEC!N30 -> 0 | D29: =C29-E29 -> 0 | E29: =ELEC!Q30 -> 0 | F29: =GEN!Z29 -> 0 | G29: =WATER!C32+WATER!H32 -> 0 | H29: =WATER!L32 -> 0 | I29: =WATER!BC32+WATER!BD32+WATER!BE33-Sheet1!G29 -> 0 | J29: ='B5'!A31 -> 43978
A30: =ELEC!T31+ELEC!X31+ELEC!#REF! -> #REF! | B30: =ELEC!AF31 -> 0 | C30: =ELEC!N31 -> 0 | D30: =C30-E30 -> 0 | E30: =ELEC!Q31 -> 0 | F30: =GEN!Z30 -> 0 | G30: =WATER!C33+WATER!H33 -> 0 | H30: =WATER!L33 -> 0 | I30: =WATER!BC33+WATER!BD33+WATER!BE34-Sheet1!G30 -> 0 | J30: ='B5'!A32 -> 43979
A31: =ELEC!T32+ELEC!X32+ELEC!AB31 -> 0 | B31: =ELEC!AF32 -> 0 | C31: =ELEC!N32 -> 0 | D31: =C31-E31 -> 0 | E31: =ELEC!Q32 -> 0 | F31: =GEN!Z31 -> 0 | G31: =WATER!C34+WATER!H34 -> 0 | H31: =WATER!L34 -> 0 | I31: =WATER!BC34+WATER!BD34+WATER!BE35-Sheet1!G31 -> 0 | J31: ='B5'!A33 -> 43980
A32: =ELEC!#REF!+ELEC!#REF!+ELEC!#REF! -> #REF! | B32: =ELEC!#REF! -> #REF! | C32: =ELEC!#REF! -> #REF! | D32: =C32-E32 -> #REF! | E32: =ELEC!#REF! -> #REF! | F32: =GEN!#REF! -> #REF! | G32: =WATER!#REF!+WATER!#REF! -> #REF! | H32: =WATER!#REF! -> #REF! | I32: =WATER!#REF!+WATER!#REF!+WATER!BE37-Sheet1!G32 -> #REF!

Sheet Report
B1: Boiler Fuel | C1: Steam Fuel | D1: GEN FUEL | E1: FUEL TOTAL | F1: CT/mᶾ | G1: Water Consumption | H1: Chiller KW | I1: GEN KW | J1: EDL KW | K1: occ | L1: covers | M1: temp. C⁰ | N1: RH %
B3: ='B5'!V3 -> 0 | C3: ='B5'!AH3 -> 0 | E3: =B3+C3+D3 -> 0
A4: 42704 | B4: 810 | C4: -606.1 | D4: 1420.5021 | E4: 1624.4021 | F4: 106 | G4: -58.4 | H4: 6284 | I4: 2399 | J4: 23932 | K4: 0 | L4: 0 | M4: 0 | N4: 0
A5: ='B5'!A5 -> 43952 | B5: ='B5'!V5 -> 349 | C5: ='B5'!AH5 -> 0 | D5: =GEN!AI3 -> 360.33755 | E5: =B5+C5+D5 -> 709.33755 | F5: =WATER!L5 -> 1 | G5: =WATER!BG5 -> -16.1 | H5: =ELEC!AF3 -> 835 | I5: =ELEC!Q3 -> 1400 | J5: =ELEC!R3 -> 7402.4
A6: ='B5'!A6 -> 43953 | B6: ='B5'!V6 -> 249 | C6: ='B5'!AH6 -> 0 | D6: =GEN!AI4 -> 394.827 | E6: =B6+C6+D6 -> 643.827 | F6: =WATER!L6 -> 0 | G6: =WATER!BG6 -> -12 | H6: =ELEC!AF4 -> 607 | I6: =ELEC!Q4 -> 1534 | J6: =ELEC!R4 -> 7167.6
A7: ='B5'!A7 -> 43954 | B7: ='B5'!V7 -> 288 | C7: ='B5'!AH7 -> 0.5 | D7: =GEN!AI5 -> 377.32489 | E7: =B7+C7+D7 -> 665.82489 | F7: =WATER!L7 -> 6 | G7: =WATER!BG7 -> -36.9 | H7: =ELEC!AF5 -> 1395 | I7: =ELEC!Q5 -> 1466 | J7: =ELEC!R5 -> 9872.4
A8: ='B5'!A8 -> 43955 | B8: ='B5'!V8 -> 348 | C8: ='B5'!AH8 -> 309.9 | D8: =GEN!AI6 -> 257.38397 | E8: =B8+C8+D8 -> 915.28397 | F8: =WATER!L8 -> 2 | G8: =WATER!BG8 -> 140.5 | H8: =ELEC!AF6 -> 1030 | I8: =ELEC!Q6 -> 1000 | J8: =ELEC!R6 -> 9592
A9: ='B5'!A9 -> 43956 | B9: ='B5'!V9 -> 0 | C9: ='B5'!AH9 -> 0 | D9: =GEN!AI7 -> 0 | E9: =B9+C9+D9 -> 0 | F9: =WATER!L9 -> 6 | G9: =WATER!BG9 -> -15.9 | H9: =ELEC!AF7 -> 0 | I9: =ELEC!Q7 -> 0 | J9: =ELEC!R7 -> 0
A10: ='B5'!A10 -> 43957 | B10: ='B5'!V10 -> 0 | C10: ='B5'!AH10 -> 0 | D10: =GEN!AI8 -> 0 | E10: =B10+C10+D10 -> 0 | F10: =WATER!L10 -> 0 | G10: =WATER!BG10 -> 0 | H10: =ELEC!AF8 -> 0 | I10: =ELEC!Q8 -> 0 | J10: =ELEC!R8 -> 0
A11: ='B5'!A11 -> 43958 | B11: ='B5'!V11 -> 0 | C11: ='B5'!AH11 -> 0 | D11: =GEN!AI9 -> 0 | E11: =B11+C11+D11 -> 0 | F11: =WATER!L11 -> 0 | G11: =WATER!BG11 -> 0 | H11: =ELEC!AF9 -> 0 | I11: =ELEC!Q9 -> 0 | J11: =ELEC!R9 -> 0
A12: ='B5'!A12 -> 43959 | B12: ='B5'!V12 -> 0 | C12: ='B5'!AH12 -> 0 | D12: =GEN!AI10 -> 0 | E12: =B12+C12+D12 -> 0 | F12: =WATER!L12 -> 0 | G12: =WATER!BG12 -> 0 | H12: =ELEC!AF10 -> 0 | I12: =ELEC!Q10 -> 0 | J12: =ELEC!R10 -> 0
A13: ='B5'!A13 -> 43960 | B13: ='B5'!V13 -> 0 | C13: ='B5'!AH13 -> 0 | D13: =GEN!AI11 -> 0 | E13: =B13+C13+D13 -> 0 | F13: =WATER!L13 -> 0 | G13: =WATER!BG13 -> 0 | H13: =ELEC!AF11 -> 0 | I13: =ELEC!Q11 -> 0 | J13: =ELEC!R11 -> 0
A14: ='B5'!A14 -> 43961 | B14: ='B5'!V14 -> 0 | C14: ='B5'!AH14 -> 0 | D14: =GEN!AI12 -> 0 | E14: =B14+C14+D14 -> 0 | F14: =WATER!L14 -> 0 | G14: =WATER!BG14 -> 0 | H14: =ELEC!AF12 -> 0 | I14: =ELEC!Q12 -> 0 | J14: =ELEC!R12 -> 0
A15: ='B5'!A15 -> 43962 | B15: ='B5'!V15 -> 0 | C15: ='B5'!AH15 -> 0 | D15: =GEN!AI13 -> 0 | E15: =B15+C15+D15 -> 0 | F15: =WATER!L15 -> 0 | G15: =WATER!BG15 -> 0 | H15: =ELEC!AF13 -> 0 | I15: =ELEC!Q13 -> 0 | J15: =ELEC!R13 -> 0
A16: ='B5'!A16 -> 43963 | B16: ='B5'!V16 -> 0 | C16: ='B5'!AH16 -> 0 | D16: =GEN!AI14 -> 0 | E16: =B16+C16+D16 -> 0 | F16: =WATER!L16 -> 0 | G16: =WATER!BG16 -> 0 | H16: =ELEC!AF14 -> 0 | I16: =ELEC!Q14 -> 0 | J16: =ELEC!R14 -> 0
... A33: ='B5'!A33 -> 43980 | B33: ='B5'!V33 -> 0 | C33: ='B5'!AH33 -> 0 | D33: =GEN!AI31 -> 0 | E33: =B33+C33+D33 -> 0 | F33: =WATER!L33 -> 0 | G33: =WATER!BG33 -> 0 | H33: =ELEC!AF31 -> 0 | I33: =ELEC!Q31 -> 0 | J33: =ELEC!R31 -> 0
A34: ='B5'!A34 -> 43981 | B34: ='B5'!V34 -> 0 | C34: ='B5'!AH34 -> 0 | D34: =GEN!AI32 -> 0 | E34: =B34+C34+D34 -> 0 | F34: =WATER!L34 -> 0 | G34: =WATER!BG34 -> 0 | H34: =ELEC!#REF! -> #REF! | I34: =ELEC!#REF! -> #REF! | J34: =ELEC!#REF! -> #REF!

Sheet Sheet5
T3: Outdoor conditions
C4: Date | D4: Total Boiler running H | E4: AVE CONSUM | F4: Total Steam running H | G4: AVE CONSUM | H4: Total GEN running H | I4: AVE CONSUM | J4: Actual Diesel Consumption | K4: Actual Gas Consumption | L4: Total ELEC power | M4: Gen ELEC power | N4: EDL ELEC power | O4: Chillers running H | P4: Total Water delivery | Q4: Total water consumption | R4: Total water in tanks | S4: Occupancy | T4: AVE TEPM | U4: AVE Humidity
C5: 42429 | D5: ='B5'!AL4 -> 3 | E5: =D5*90 -> 270 | F5: ='B5'!AM4 -> 0 | G5: =F5*107 -> 0 | H5: =GEN!Z3 -> 3
C6: 42430 | D6: ='B5'!AL5 -> 6 | E6: =D6*90 -> 540 | F6: ='B5'!AM5 -> 0 | G6: =F6*107 -> 0
C7: 42431 | D7: ='B5'!AL6 -> 3 | E7: =D7*90 -> 270 | F7: ='B5'!AM6 -> 0 | G7: =F7*107 -> 0
C8: 42432 | D8: ='B5'!AL7 -> 4 | E8: =D8*90 -> 360 | F8: ='B5'!AM7 -> 0 | G8: =F8*107 -> 0
C9: 42433 | D9: ='B5'!AL8 -> 4 | E9: =D9*90 -> 360 | F9: ='B5'!AM8 -> 5 | G9: =F9*107 -> 535
C10: 42434 | D10: ='B5'!AL9 -> 0 | E10: =D10*90 -> 0 | F10: ='B5'!AM9 -> 0 | G10: =F10*107 -> 0
C11: 42435 | D11: ='B5'!AL10 -> 0 | E11: =D11*90 -> 0 | F11: ='B5'!AM10 -> 0 | G11: =F11*107 -> 0
C12: 42436 | D12: ='B5'!AL11 -> 0 | E12: =D12*90 -> 0 | F12: ='B5'!AM11 -> 0 | G12: =F12*107 -> 0
C13: 42437 | D13: ='B5'!AL12 -> 0 | E13: =D13*90 -> 0 | F13: ='B5'!AM12 -> 0 | G13: =F13*107 -> 0
C14: 42438 | D14: ='B5'!AL13 -> 0 | E14: =D14*90 -> 0 | F14: ='B5'!AM13 -> 0 | G14: =F14*107 -> 0
C15: 42439 | D15: ='B5'!AL14 -> 0 | E15: =D15*90 -> 0 | F15: ='B5'!AM14 -> 0 | G15: =F15*107 -> 0
C16: 42440 | D16: ='B5'!AL15 -> 0 | E16: =D16*90 -> 0 | F16: ='B5'!AM15 -> 0 | G16: =F16*107 -> 0
C17: 42441 | D17: ='B5'!AL16 -> 0 | E17: =D17*90 -> 0 | F17: ='B5'!AM16 -> 0 | G17: =F17*107 -> 0
... C35: 42459 | D35: ='B5'!AL34 -> 0 | E35: =D35*90 -> 0 | F35: ='B5'!AM34 -> 0 | G35: =F35*107 -> 0
C36: 42460 | D36: ='B5'!#REF! -> #REF! | E36: =D36*90 -> #REF! | F36: ='B5'!#REF! -> #REF! | G36: =F36*107 -> #REF!
C37: 42461 | D37: ='B5'!#REF! -> #REF! | E37: =D37*90 -> #REF! | F37: ='B5'!#REF! -> #REF! | G37: =F37*107 -> #REF!

Sheet EDl log
A1: Date | B1: EDL | C1: Conso EDL KW | F1: Peak | G1: 320 | H1: Day | I1: 112 | J1: Night | K1: 80
L2: P | M2: D | N2: N | O2: fee | P2: T EDL | Q2: Gen | R2: Elc C
A3: =ELEC!C2 -> 43951 | B3: ='[1]EDl log'!B33 -> 49827570 | C3: ='[1]EDl log'!C33 -> 4393 | D3: ='[1]EDl log'!D33 -> 4392 | E3: ='[1]EDl log'!E33 -> 49827569 | F3: ='[1]EDl log'!F33 -> 8005615 | G3: ='[1]EDl log'!G33 -> 498 | H3: ='[1]EDl log'!H33 -> 24540104 | I3: ='[1]EDl log'!I33 -> 2185 | ... T3: ='[1]EDl log'!T33 -> 0.066615024 | Z3: VAT | AA3: 0.1
A4: =ELEC!C3 -> 43952 | B4: 49831143 | C4: =SUM(B4-B3) -> 3573 | D4: =SUM(G4+I4+K4) -> 3576 | E4: =B3+D4 -> 49831146 | F4: 8006372 | G4: =F4-F3 -> 757 | H4: 24542022 | I4: =H4-H3 -> 1918 | J4: 17282751 | K4: =J4-J3 -> 901 | L4: =SUM(G4*$Y$28)/1507.5 -> 160.68988 | M4: =SUM(I4*$Y$27)/1507.5 -> 142.49818 | N4: =SUM(K4*$Y$26)/1507.5 -> 47.814262 | O4: =($AC$31/$A$38)/1507.5 -> 19.974586 | P4: =SUM(L4:O4) -> 370.97691 | Q4: =SUM(-tanks!AX6*tanks!$AU$37) -> 0 | R4: =SUM(P4:Q4) -> 370.97691 | S4: =SUM(ELEC!N3) -> 8802.4 | T4: =IF(S4>0,R4/S4,0) -> 0.042144973 | V4: ='[6]EDl log'!V21 -> EDL | W4: 43941 | Z4: Subscription
A5: =ELEC!C4 -> 43953 | B5: 49835173 | C5: =SUM(B5-B4) -> 4030 | D5: =SUM(G5+I5+K5) -> 4027 | E5: =B4+D5 -> 49835170 | F5: 8006885 | G5: =F5-F4 -> 513 | H5: 24544434 | I5: =H5-H4 -> 2412 | J5: 17283853 | K5: =J5-J4 -> 1102 | L5: =SUM(G5*$Y$28)/1507.5 -> 108.89552 | M5: =SUM(I5*$Y$27)/1507.5 -> 179.2 | N5: =SUM(K5*$Y$26)/1507.5 -> 58.480929 | O5: =($AC$31/$A$38)/1507.5 -> 19.974586 | P5: =SUM(L5:O5) -> 366.55104 | Q5: =SUM(-tanks!AX7*tanks!$AU$37) -> 0 | R5: =SUM(P5:Q5) -> 366.55104 | S5: =SUM(ELEC!N4) -> 8701.6 | T5: =IF(S5>0,R5/S5,0) -> 0.042124556 | Z5: KVA | AA5: ='[7]EDl log'!AA5 -> 5000
A6: =ELEC!C5 -> 43954 | B6: 49840476 | C6: =SUM(B6-B5) -> 5303 | D6: =SUM(G6+I6+K6) -> 5304 | E6: =B5+D6 -> 49840477 | F6: 8007520 | G6: =F6-F5 -> 635 | H6: 24547296 | I6: =H6-H5 -> 2862 | J6: 17285660 | K6: =J6-J5 -> 1807 | L6: =SUM(G6*$Y$28)/1507.5 -> 134.7927 | M6: =SUM(I6*$Y$27)/1507.5 -> 212.63284 | N6: =SUM(K6*$Y$26)/1507.5 -> 95.893864 | O6: =($AC$31/$A$38)/1507.5 -> 19.974586 | P6: =SUM(L6:O6) -> 463.29399 | Q6: =SUM(-tanks!AX8*tanks!$AU$37) -> 0 | R6: =SUM(P6:Q6) -> 463.29399 | S6: =SUM(ELEC!N5) -> 11338.4 | T6: =IF(S6>0,R6/S6,0) -> 0.040860614
A7: =ELEC!C6 -> 43955 | B7: 49844850 | C7: =SUM(B7-B6) -> 4374 | D7: =SUM(G7+I7+K7) -> 4374 | E7: =B6+D7 -> 49844850 | F7: 8008235 | G7: =F7-F6 -> 715 | H7: 24549301 | I7: =H7-H6 -> 2005 | J7: 17287314 | K7: =J7-J6 -> 1654 | L7: =SUM(G7*$Y$28)/1507.5 -> 151.77446 | M7: =SUM(I7*$Y$27)/1507.5 -> 148.96186 | N7: =SUM(K7*$Y$26)/1507.5 -> 87.774461 | O7: =($AC$31/$A$38)/1507.5 -> 19.974586 | P7: =SUM(L7:O7) -> 408.48537 | Q7: =SUM(-tanks!AX9*tanks!$AU$37) -> 0 | R7: =SUM(P7:Q7) -> 408.48537 | S7: =SUM(ELEC!N6) -> 10592 | T7: =IF(S7>0,R7/S7,0) -> 0.038565461 | V7: Electricity consumption | X7: Price LL
A8: =ELEC!C7 -> 43956 | B8: =B7 -> 49844850 | C8: =SUM(B8-B7) -> 0 | D8: =SUM(G8+I8+K8) -> 0 | E8: =B7+D8 -> 49844850 | F8: =F7 -> 8008235 | G8: =F8-F7 -> 0 | H8: =H7 -> 24549301 | I8: =H8-H7 -> 0 | J8: =J7 -> 17287314 | K8: =J8-J7 -> 0 | L8: =SUM(G8*$Y$28)/1507.5 -> 0 | M8: =SUM(I8*$Y$27)/1507.5 -> 0 | N8: =SUM(K8*$Y$26)/1507.5 -> 0 | O8: =($AC$31/$A$38)/1507.5 -> 19.974586 | P8: =SUM(L8:O8) -> 19.974586 | Q8: =SUM(-tanks!AX10*tanks!$AU$37) -> 0 | R8: =SUM(P8:Q8) -> 19.974586 | S8: =SUM(ELEC!N7) -> 0 | T8: =IF(S8>0,R8/S8,0) -> 0 | V8: Index in | W8: Index Out | Y8: Kwh Cost | Z8: K | AA8: Kwh | AB8: ='[4]EDl log'!AB25 -> Total cost LL | AC8: Fees
A9: =ELEC!C8 -> 43957 | B9: =B8 -> 49844850 | C9: =SUM(B9-B8) -> 0 | D9: =SUM(G9+I9+K9) -> 0 | E9: =B8+D9 -> 49844850 | F9: =F8 -> 8008235 | G9: =F9-F8 -> 0 | H9: =H8 -> 24549301 | I9: =H9-H8 -> 0 | J9: =J8 -> 17287314 | K9: =J9-J8 -> 0 | L9: =SUM(G9*$Y$28)/1507.5 -> 0 | M9: =SUM(I9*$Y$27)/1507.5 -> 0 | N9: =SUM(K9*$Y$26)/1507.5 -> 0 | O9: =($AC$31/$A$38)/1507.5 -> 19.974586 | P9: =SUM(L9:O9) -> 19.974586 | Q9: =SUM(-tanks!AX11*tanks!$AU$37) -> 0 | R9: =SUM(P9:Q9) -> 19.974586 | S9: =SUM(ELEC!N8) -> 0 | T9: =IF(S9>0,R9/S9,0) -> 0 | V9: ='[4]EDl log'!V26 -> 17242851 | W9: ='[4]EDl log'!W26 -> 17280141 | X9: ='[4]EDl log'!X26 -> Night | Y9: ='[4]EDl log'!Y26 -> 80 | Z9: ='[4]EDl log'!Z26 -> 1 | AA9: ='[4]EDl log'!AA26 -> 37290 | AB9: ='[4]EDl log'!AB26 -> 2983200 | AC9: ='[4]EDl log'!AC26 -> 1033333 | AD9: ='[4]EDl log'!AD26 -> 0.32871134
A10: =ELEC!C9 -> 43958 | B10: =B9 -> 49844850 | C10: =SUM(B10-B9) -> 0 | D10: =SUM(G10+I10+K10) -> 0 | E10: =B9+D10 -> 49844850 | F10: =F9 -> 8008235 | G10: =F10-F9 -> 0 | H10: =H9 -> 24549301 | I10: =H10-H9 -> 0 | J10: =J9 -> 17287314 | K10: =J10-J9 -> 0 | L10: =SUM(G10*$Y$28)/1507.5 -> 0 | M10: =SUM(I10*$Y$27)/1507.5 -> 0 | N10: =SUM(K10*$Y$26)/1507.5 -> 0 | O10: =($AC$31/$A$38)/1507.5 -> 19.974586 | P10: =SUM(L10:O10) -> 19.974586 | Q10: =SUM(-tanks!AX12*tanks!$AU$37) -> 0 | R10: =SUM(P10:Q10) -> 19.974586 | S10: =SUM(ELEC!N9) -> 0 | T10: =IF(S10>0,R10/S10,0) -> 0 | V10: ='[4]EDl log'!V27 -> 24476792 | W10: ='[4]EDl log'!W27 -> 24537919 | X10: ='[4]EDl log'!X27 -> day | Y10: ='[4]EDl log'!Y27 -> 112 | Z10: ='[4]EDl log'!Z27 -> 1 | AA10: ='[4]EDl log'!AA27 -> 61127 | AB10: ='[4]EDl log'!AB27 -> 6846224 | AC10: ='[4]EDl log'!AC27 -> 6200000 | AD10: ='[4]EDl log'!AD27 -> 0.53883448
A11: =ELEC!C10 -> 43959 | B11: =B10 -> 49844850 | C11: =SUM(B11-B10) -> 0 | D11: =SUM(G11+I11+K11) -> 0 | E11: =B10+D11 -> 49844850 | F11: =F10 -> 8008235 | G11: =F11-F10 -> 0 | H11: =H10 -> 24549301 | I11: =H11-H10 -> 0 | J11: =J10 -> 17287314 | K11: =J11-J10 -> 0 | L11: =SUM(G11*$Y$28)/1507.5 -> 0 | M11: =SUM(I11*$Y$27)/1507.5 -> 0 | N11: =SUM(K11*$Y$26)/1507.5 -> 0 | O11: =($AC$31/$A$38)/1507.5 -> 19.974586 | P11: =SUM(L11:O11) -> 19.974586 | Q11: =SUM(-tanks!AX13*tanks!$AU$37) -> 0 | R11: =SUM(P11:Q11) -> 19.974586 | S11: =SUM(ELEC!N10) -> 0 | T11: =IF(S11>0,R11/S11,0) -> 0 | V11: ='[4]EDl log'!V28 -> 7990092 | W11: ='[4]EDl log'!W28 -> 8005117 | X11: ='[4]EDl log'!X28 -> Peak | Y11: ='[4]EDl log'!Y28 -> 320 | Z11: ='[4]EDl log'!Z28 -> 1 | AA11: ='[4]EDl log'!AA28 -> 15025 | AB11: ='[4]EDl log'!AB28 -> 4808000 | AC11: ='[4]EDl log'!AC28 -> 1000 | AD11: ='[4]EDl log'!AD28 -> 0.13244537
A12: =ELEC!C11 -> 43960 | B12: =B11 -> 49844850 | C12: =SUM(B12-B11) -> 0 | D12: =SUM(G12+I12+K12) -> 0 | E12: =B11+D12 -> 49844850 | F12: =F11 -> 8008235 | G12: =F12-F11 -> 0 | H12: =H11 -> 24549301 | I12: =H12-H11 -> 0 | J12: =J11 -> 17287314 | K12: =J12-J11 -> 0 | L12: =SUM(G12*$Y$28)/1507.5 -> 0 | M12: =SUM(I12*$Y$27)/1507.5 -> 0 | N12: =SUM(K12*$Y$26)/1507.5 -> 0 | O12: =($AC$31/$A$38)/1507.5 -> 19.974586 | P12: =SUM(L12:O12) -> 19.974586 | Q12: =SUM(-tanks!AX14*tanks!$AU$37) -> 0 | R12: =SUM(P12:Q12) -> 19.974586 | S12: =SUM(ELEC!N11) -> 0 | T12: =IF(S12>0,R12/S12,0) -> 0 | AA12: ='[4]EDl log'!AA29 -> 113442 | AB12: ='[4]EDl log'!AB29 -> 0 | AC12: ='[4]EDl log'!AC29 -> 0
A13: =ELEC!C12 -> 43961 | B13: =B12 -> 49844850 | C13: =SUM(B13-B12) -> 0 | D13: =SUM(G13+I13+K13) -> 0 | E13: =B12+D13 -> 49844850 | F13: =F12 -> 8008235 | G13: =F13-F12 -> 0 | H13: =H12 -> 24549301 | I13: =H13-H12 -> 0 | J13: =J12 -> 17287314 | K13: =J13-J12 -> 0 | L13: =SUM(G13*$Y$28)/1507.5 -> 0 | M13: =SUM(I13*$Y$27)/1507.5 -> 0 | N13: =SUM(K13*$Y$26)/1507.5 -> 0 | O13: =($AC$31/$A$38)/1507.5 -> 19.974586 | P13: =SUM(L13:O13) -> 19.974586 | Q13: =SUM(-tanks!AX15*tanks!$AU$37) -> 0 | R13: =SUM(P13:Q13) -> 19.974586 | S13: =SUM(ELEC!N12) -> 0 | T13: =IF(S13>0,R13/S13,0) -> 0 | V13: ='[4]EDl log'!V30 -> Occ % | W13: ='[4]EDl log'!W30 -> 0.01607931 | X13: ='[4]EDl log'!X30 -> 0 | Y13: ='[4]EDl log'!Y30 -> Per G | AB13: ='[4]EDl log'!AB30 -> 14637424 | AC13: ='[4]EDl log'!AC30 -> 6993188.6
A14: =ELEC!C13 -> 43962 | B14: =B13 -> 49844850 | C14: =SUM(B14-B13) -> 0 | D14: =SUM(G14+I14+K14) -> 0 | E14: =B13+D14 -> 49844850 | F14: =F13 -> 8008235 | G14: =F14-F13 -> 0 | H14: =H13 -> 24549301 | I14: =H14-H13 -> 0 | J14: =J13 -> 17287314 | K14: =J14-J13 -> 0 | L14: =SUM(G14*$Y$28)/1507.5 -> 0 | M14: =SUM(I14*$Y$27)/1507.5 -> 0 | N14: =SUM(K14*$Y$26)/1507.5 -> 0 | O14: =($AC$31/$A$38)/1507.5 -> 19.974586 | P14: =SUM(L14:O14) -> 19.974586 | Q14: =SUM(-tanks!AX16*tanks!$AU$37) -> 0 | R14: =SUM(P14:Q14) -> 19.974586 | S14: =SUM(ELEC!N13) -> 0 | T14: =IF(S14>0,R14/S14,0) -> 0 | V14: ='[4]EDl log'!V31 -> Gen RH | W14: ='[4]EDl log'!W31 -> 82.64 | X14: ='[4]EDl log'!X31 -> 2.8496552 | Y14: ='[4]EDl log'!Y31 -> 1.4248276 | AB14: ='[4]EDl log'!AB31 -> 21630613 | AC14: ='[4]EDl log'!AC31 -> 6993188.6
A15: =ELEC!C14 -> 43963 | B15: =B14 -> 49844850 | C15: =SUM(B15-B14) -> 0 | D15: =SUM(G15+I15+K15) -> 0 | E15: =B14+D15 -> 49844850 | F15: =F14 -> 8008235 | G15: =F15-F14 -> 0 | H15: =H14 -> 24549301 | I15: =H15-H14 -> 0 | J15: =J14 -> 17287314 | K15: =J15-J14 -> 0 | L15: =SUM(G15*$Y$28)/1507.5 -> 0 | M15: =SUM(I15*$Y$27)/1507.5 -> 0 | N15: =SUM(K15*$Y$26)/1507.5 -> 0 | O15: =($AC$31/$A$38)/1507.5 -> 19.974586 | P15: =SUM(L15:O15) -> 19.974586 | Q15: =SUM(-tanks!AX17*tanks!$AU$37) -> 0 | R15: =SUM(P15:Q15) -> 19.974586 | S15: =SUM(ELEC!N14) -> 0 | T15: =IF(S15>0,R15/S15,0) -> 0 | V15: ='[4]EDl log'!V32 -> H Deg | W15: ='[4]EDl log'!W32 -> -549 | X15: ='[4]EDl log'!X32 -> 0 | Y15: ='[4]EDl log'!Y32 -> 0 | AB15: ='[8]EDl log'!AB32 -> 0 | AC15: ='[4]EDl log'!AC32 -> 0
A16: =ELEC!C15 -> 43964 | B16: =B15 -> 49844850 | C16: =SUM(B16-B15) -> 0 | D16: =SUM(G16+I16+K16) -> 0 | E16: =B15+D16 -> 49844850 | F16: =F15 -> 8008235 | G16: =F16-F15 -> 0 | H16: =H15 -> 24549301 | I16: =H16-H15 -> 0 | J16: =J15 -> 17287314 | K16: =J16-J15 -> 0 | L16: =SUM(G16*$Y$28)/1507.5 -> 0 | M16: =SUM(I16*$Y$27)/1507.5 -> 0 | N16: =SUM(K16*$Y$26)/1507.5 -> 0 | O16: =($AC$31/$A$38)/1507.5 -> 19.974586 | P16: =SUM(L16:O16) -> 19.974586 | Q16: =SUM(-tanks!AX18*tanks!$AU$37) -> 0 | R16: =SUM(P16:Q16) -> 19.974586 | S16: =SUM(ELEC!N15) -> 0 | T16: =IF(S16>0,R16/S16,0) -> 0 | V16: ='[4]EDl log'!V33 -> C Deg | W16: ='[4]EDl log'!W33 -> 0 | X16: ='[4]EDl log'!X33 -> 0 | Y16: ='[4]EDl log'!Y33 -> 0 | AB16: ='[8]EDl log'!AB33 -> 0 | AC16: ='[8]EDl log'!AC33 -> 0
A17: =ELEC!C16 -> 43965 | B17: =B16 -> 49844850 | C17: =SUM(B17-B16) -> 0 | D17: =SUM(G17+I17+K17) -> 0 | E17: =B16+D17 -> 49844850 | F17: =F16 -> 8008235 | G17: =F17-F16 -> 0 | H17: =H16 -> 24549301 | I17: =H17-H16 -> 0 | J17: =J16 -> 17287314 | K17: =J17-J16 -> 0 | L17: =SUM(G17*$Y$28)/1507.5 -> 0 | M17: =SUM(I17*$Y$27)/1507.5 -> 0 | N17: =SUM(K17*$Y$26)/1507.5 -> 0 | O17: =($AC$31/$A$38)/1507.5 -> 19.974586 | P17: =SUM(L17:O17) -> 19.974586 | Q17: =SUM(-tanks!AX19*tanks!$AU$37) -> 0 | R17: =SUM(P17:Q17) -> 19.974586 | S17: =SUM(ELEC!N16) -> 0 | T17: =IF(S17>0,R17/S17,0) -> 0 | W17: ='[9]EDl log'!W34 -> 0 | Z17: ='[10]EDl log'!Z34 -> VAT | AA17: ='[8]EDl log'!$AA$35 -> 0.11 | AB17: ='[4]EDl log'!AB34 -> 2379367.4 | AC17: ='[4]EDl log'!AC34 -> 0
A18: =ELEC!C17 -> 43966 | B18: =B17 -> 49844850 | C18: =SUM(B18-B17) -> 0 | D18: =SUM(G18+I18+K18) -> 0 | E18: =B17+D18 -> 49844850 | F18: =F17 -> 8008235 | G18: =F18-F17 -> 0 | H18: =H17 -> 24549301 | I18: =H18-H17 -> 0 | J18: =J17 -> 17287314 | K18: =J18-J17 -> 0 | L18: =SUM(G18*$Y$28)/1507.5 -> 0 | M18: =SUM(I18*$Y$27)/1507.5 -> 0 | N18: =SUM(K18*$Y$26)/1507.5 -> 0 | O18: =($AC$31/$A$38)/1507.5 -> 19.974586 | P18: =SUM(L18:O18) -> 19.974586 | Q18: =SUM(-tanks!AX20*tanks!$AU$37) -> 0 | R18: =SUM(P18:Q18) -> 19.974586 | S18: =SUM(ELEC!N17) -> 0 | T18: =IF(S18>0,R18/S18,0) -> 0 | AB18: ='[4]EDl log'!AB35 -> 24009980 | AC18: ='[4]EDl log'!AC35 -> 0
A19: =ELEC!C18 -> 43967 | B19: =B18 -> 49844850 | C19: =SUM(B19-B18) -> 0 | D19: =SUM(G19+I19+K19) -> 0 | E19: =B18+D19 -> 49844850 | F19: =F18 -> 8008235 | G19: =F19-F18 -> 0 | H19: =H18 -> 24549301 | I19: =H19-H18 -> 0 | J19: =J18 -> 17287314 | K19: =J19-J18 -> 0 | L19: =SUM(G19*$Y$28)/1507.5 -> 0 | M19: =SUM(I19*$Y$27)/1507.5 -> 0 | N19: =SUM(K19*$Y$26)/1507.5 -> 0 | O19: =($AC$31/$A$38)/1507.5 -> 19.974586 | P19: =SUM(L19:O19) -> 19.974586 | Q19: =SUM(-tanks!AX21*tanks!$AU$37) -> 0 | R19: =SUM(P19:Q19) -> 19.974586 | S19: =SUM(ELEC!N18) -> 0 | T19: =IF(S19>0,R19/S19,0) -> 0 | AA19: $ | AB19: ='[11]EDl log'!AB36 -> #REF! | AC19: ='[11]EDl log'!AC36 -> #REF!
A20: =ELEC!C19 -> 43968 | B20: =B19 -> 49844850 | C20: =SUM(B20-B19) -> 0 | D20: =SUM(G20+I20+K20) -> 0 | E20: =B19+D20 -> 49844850 | F20: =F19 -> 8008235 | G20: =F20-F19 -> 0 | H20: =H19 -> 24549301 | I20: =H20-H19 -> 0 | J20: =J19 -> 17287314 | K20: =J20-J19 -> 0 | L20: =SUM(G20*$Y$28)/1507.5 -> 0 | M20: =SUM(I20*$Y$27)/1507.5 -> 0 | N20: =SUM(K20*$Y$26)/1507.5 -> 0 | O20: =($AC$31/$A$38)/1507.5 -> 19.974586 | P20: =SUM(L20:O20) -> 19.974586 | Q20: =SUM(-tanks!AX22*tanks!$AU$37) -> 0 | R20: =SUM(P20:Q20) -> 19.974586 | S20: =SUM(ELEC!N19) -> 0 | T20: =IF(S20>0,R20/S20,0) -> 0
A21: =ELEC!C20 -> 43969 | B21: =B20 -> 49844850 | C21: =SUM(B21-B20) -> 0 | D21: =SUM(G21+I21+K21) -> 0 | E21: =B20+D21 -> 49844850 | F21: =F20 -> 8008235 | G21: =F21-F20 -> 0 | H21: =H20 -> 24549301 | I21: =H21-H20 -> 0 | J21: =J20 -> 17287314 | K21: =J21-J20 -> 0 | L21: =SUM(G21*$Y$28)/1507.5 -> 0 | M21: =SUM(I21*$Y$27)/1507.5 -> 0 | N21: =SUM(K21*$Y$26)/1507.5 -> 0 | O21: =($AC$31/$A$38)/1507.5 -> 19.974586 | P21: =SUM(L21:O21) -> 19.974586 | Q21: =SUM(-tanks!AX23*tanks!$AU$37) -> 0 | R21: =SUM(P21:Q21) -> 19.974586 | S21: =SUM(ELEC!N20) -> 0 | T21: =IF(S21>0,R21/S21,0) -> 0 | V21: EDL | W21: 43971 | Z21: Subscription
