Workbook
Name _IV99999: [1]Water!$IB$30257

Sheet Total
A1: Site Name | B1: Day | C1: Month | D1: Year | E1: Total Electricity Kwh | F1: Electricity Tariff ($/Kwh) | G1: Natual Gas (m3) | H1: Natural Gas $/m3 | I1: Water Utility Supply (m3) m3 | J1: Water Utility Supply (m3) $/m3 | K1: Room Nights
A2: Cairo at The First Residence | B2: 1 | C2: 3 | D2: 2020 | E2: =Elect!BL6 -> 9275.7 | F2: ='Utility Consnsumption'!K13/'Utility Consnsumption'!J13 -> 1.637964 | G2: =Gas!K7 -> 191.86 | H2: 3.8 | I2: =Water!H7 -> 52.2 | J2: 10 | K2: =Elect!BM6 -> 0
A3: Cairo at The First Residence | B3: =B2+1 -> 2 | C3: 3 | D3: 2020 | E3: =Elect!BL7 -> 16199.26 | F3: =F2 -> 1.637964 | G3: =Gas!K8 -> 170.66 | H3: 3.8 | I3: =Water!H8 -> 139.2 | J3: 10 | K3: =Elect!BM7 -> 0
A4: Cairo at The First Residence | B4: =B3+1 -> 3 | C4: 3 | D4: 2020 | E4: =Elect!BL8 -> 6850.27 | F4: =F3 -> 1.637964 | G4: =Gas!K9 -> 170.66 | H4: 3.8 | I4: =Water!H9 -> 133.4 | J4: 10 | K4: =Elect!BM8 -> 0
A5: Cairo at The First Residence | B5: =B4+1 -> 4 | C5: 3 | D5: 2020 | E5: =Elect!BL9 -> 12233.13 | F5: =F4 -> 1.637964 | G5: =Gas!K10 -> 170.66 | H5: 3.8 | I5: =Water!H10 -> 243.6 | J5: 10 | K5: =Elect!BM9 -> 0
A6: Cairo at The First Residence | B6: =B5+1 -> 5 | C6: 3 | D6: 2020 | E6: =Elect!BL10 -> 15742.95 | F6: =F5 -> 1.637964 | G6: =Gas!K11 -> 280.21212 | H6: 3.8 | I6: =Water!H11 -> 145 | J6: 10 | K6: =Elect!BM10 -> 0
A7: Cairo at The First Residence | B7: =B6+1 -> 6 | C7: 3 | D7: 2020 | E7: =Elect!BL11 -> 6712.55 | F7: =F6 -> 1.637964 | G7: =Gas!K12 -> 319.86606 | H7: 3.8 | I7: =Water!H12 -> 92.8 | J7: 10 | K7: =Elect!BM11 -> 0
A8: Cairo at The First Residence | B8: =B7+1 -> 7 | C8: 3 | D8: 2020 | E8: =Elect!BL12 -> 15222.27 | F8: =F7 -> 1.637964 | G8: =Gas!K13 -> 319.86606 | H8: 3.8 | I8: =Water!H13 -> 98.6 | J8: 10 | K8: =Elect!BM12 -> 0
A9: Cairo at The First Residence | B9: =B8+1 -> 8 | C9: 3 | D9: 2020 | E9: =Elect!BL13 -> 13930.72 | F9: =F8 -> 1.637964 | G9: =Gas!K14 -> 319.86606 | H9: 3.8 | I9: =Water!H14 -> 116 | J9: 10 | K9: =Elect!BM13 -> 0
A10: Cairo at The First Residence | B10: =B9+1 -> 9 | C10: 3 | D10: 2020 | E10: =Elect!BL14 -> 8231.14 | F10: =F9 -> 1.637964 | G10: =Gas!K15 -> 319.86606 | H10: 3.8 | I10: =Water!H15 -> 133.4 | J10: 10 | K10: =Elect!BM14 -> 0
A11: Cairo at The First Residence | B11: =B10+1 -> 10 | C11: 3 | D11: 2020 | E11: =Elect!BL15 -> 13092.23 | F11: =F10 -> 1.637964 | G11: =Gas!K16 -> 319.86606 | H11: 3.8 | I11: =Water!H16 -> 54.52 | J11: 10 | K11: =Elect!BM15 -> 0
A12: Cairo at The First Residence | B12: =B11+1 -> 11 | C12: 3 | D12: 2020 | E12: =Elect!BL16 -> 9014.3 | F12: =F11 -> 1.637964 | G12: =Gas!K17 -> 319.86606 | H12: 3.8 | I12: =Water!H17 -> 80.62 | J12: 10 | K12: =Elect!BM16 -> 0
A13: Cairo at The First Residence | B13: =B12+1 -> 12 | C13: 3 | D13: 2020 | E13: =Elect!BL17 -> 10233.37 | F13: =F12 -> 1.637964 | G13: =Gas!K18 -> 319.86606 | H13: 3.8 | I13: =Water!H18 -> 77.14 | J13: 10 | K13: =Elect!BM17 -> 0
A14: Cairo at The First Residence | B14: =B13+1 -> 13 | C14: 3 | D14: 2020 | E14: =Elect!BL18 -> 10826.08 | F14: =F13 -> 1.637964 | G14: =Gas!K19 -> 319.86606 | H14: 3.8 | I14: =Water!H19 -> 117.16 | J14: 10 | K14: =Elect!BM18 -> 0
... A32: Cairo at The First Residence | B32: =B31+1 -> 31 | C32: 3 | D32: 2020 | E32: =Elect!BL36 -> 0 | F32: =F31 -> 1.637964 | G32: =Gas!K37 -> 0 | H32: 3.8 | I32: =Water!H37 -> 0 | J32: 10 | K32: =Elect!BM36 -> 0

Sheet Submetering
A1: Site Name | B1: Day | C1: Month | D1: Year | E1: Electricity | F1: Main Feeder -KWh | G1: T2+T8 -KWh | H1: La Gourmandize -KWh | I1: Casino 3rd floor EM -KWh | J1: Casino 3rd floor Normal -KWh | K1: Chiller 1 -KWh | L1: Chiller 2 -KWh | M1: Chiller 3 -KWh | N1: Chiller 4 -KWh | O1: Cooling towers -KWh | P1: Chiller Pumps -KWh | Q1: LG Bakery -KWh | R1: Mall Ceiling light -KWh | S1: New chiller for Second floor -KWh | T1: LG Bakery light ( Old lockers ) -KWh | U1: MCCR1 -KWh | V1: Children Swimming pool -KWh | W1: DPH1 -KWh | X1: Main G2 -KWh | Y1: Casino Emergency -KWh | Z1: L / A -KWh | AA1: L / B -KWh | AB1: L / C -KWh | AC1: Water | AD1: Main water meter 1 -m3 | AE1: Main water meter 2 -m3 | AF1: Main water meter 3 -m3 | AG1: Gas | AH1: Main Gas Flow Meter -m3 | AI1: Laundry Gas Flow Meter -m3 | AJ1: Gourmandize Gas Flow Meter -m3 | AK1: Room Nights
A2: Cairo at The First Residence | B2: 1 | C2: 3 | D2: 2020 | F2: =Elect!J6 -> 1534 | G2: =Elect!K6 -> 1084 | H2: =Elect!Q6 -> 0 | I2: =Elect!W6 -> 120 | J2: =Elect!Y6 -> 98 | K2: =Elect!AA6 -> 0 | L2: =Elect!AC6 -> 314.29 | M2: =Elect!AE6 -> 465.34 | N2: =Elect!AG6 -> 326.48 | O2: =Elect!AI6 -> 288.85 | P2: =Elect!AK6 -> 1751.65 | Q2: =Elect!AN6 -> 23 | R2: =Elect!AP6 -> 3 | S2: =Elect!AR6 -> 3.19 | T2: =Elect!AT6 -> 27 | U2: =Elect!AV6 -> 273 | V2: =Elect!AX6 -> 39 | W2: =Elect!AZ6 -> 1473 | X2: =Elect!BB6 -> 2753.9 | Y2: =Elect!BE6 -> 0 | Z2: =Elect!BG6 -> 756 | AA2: =Elect!BI6 -> 67 | AB2: =Elect!BK6 -> 154 | AD2: =Water!C7 -> 40.6 | AE2: =Water!E7 -> 11.6 | AF2: =Water!G7 -> 0 | AH2: =Gas!C7 -> 191.86 | AI2: =Gas!E7 -> 0 | AJ2: =Gas!G7 -> 3 | AK2: =Elect!BM6 -> 0
A3: Cairo at The First Residence | B3: =B2+1 -> 2 | C3: 3 | D3: 2020 | F3: =Elect!J7 -> 1896 | G3: =Elect!K7 -> 1790 | H3: =Elect!Q7 -> 90 | I3: =Elect!W7 -> 150 | J3: =Elect!Y7 -> 96 | K3: =Elect!AA7 -> 0 | L3: =Elect!AC7 -> 531.59 | M3: =Elect!AE7 -> 1767.55 | N3: =Elect!AG7 -> 105.47 | O3: =Elect!AI7 -> 647.13 | P3: =Elect!AK7 -> 3112.16 | Q3: =Elect!AN7 -> 27 | R3: =Elect!AP7 -> 2 | S3: =Elect!AR7 -> 6.16 | T3: =Elect!AT7 -> 45 | U3: =Elect!AV7 -> 453 | V3: =Elect!AX7 -> 38 | W3: =Elect!AZ7 -> 2358 | X3: =Elect!BB7 -> 5120.2 | Y3: =Elect!BE7 -> 0 | Z3: =Elect!BG7 -> 1328 | AA3: =Elect!BI7 -> 114 | AB3: =Elect!BK7 -> 289 | AD3: =Water!C8 -> 133.4 | AE3: =Water!E8 -> 5.8 | AF3: =Water!G8 -> 0 | AH3: =Gas!C8 -> 170.66 | AI3: =Gas!E8 -> 0 | AJ3: =Gas!G8 -> 2 | AK3: =Elect!BM7 -> 0
A4: Cairo at The First Residence | B4: =B3+1 -> 3 | C4: 3 | D4: 2020 | F4: =Elect!J8 -> 1702 | G4: =Elect!K8 -> 776 | H4: =Elect!Q8 -> 30 | I4: =Elect!W8 -> 87 | J4: =Elect!Y8 -> 297 | K4: =Elect!AA8 -> 0 | L4: =Elect!AC8 -> 320.12 | M4: =Elect!AE8 -> 178.08 | N4: =Elect!AG8 -> 0 | O4: =Elect!AI8 -> 229.49 | P4: =Elect!AK8 -> 1278.89 | Q4: =Elect!AN8 -> 4 | R4: =Elect!AP8 -> 2 | S4: =Elect!AR8 -> 2.09 | T4: =Elect!AT8 -> 24 | U4: =Elect!AV8 -> 221 | V4: =Elect!AX8 -> 32 | W4: =Elect!AZ8 -> 966 | X4: =Elect!BB8 -> 1860.6 | Y4: =Elect!BE8 -> 0 | Z4: =Elect!BG8 -> 594 | AA4: =Elect!BI8 -> 46 | AB4: =Elect!BK8 -> 108 | AD4: =Water!C9 -> 92.8 | AE4: =Water!E9 -> 40.6 | AF4: =Water!G9 -> 0 | AH4: =Gas!C9 -> 170.66 | AI4: =Gas!E9 -> 0 | AJ4: =Gas!G9 -> 0 | AK4: =Elect!BM8 -> 0
A5: Cairo at The First Residence | B5: =B4+1 -> 4 | C5: 3 | D5: 2020 | F5: =Elect!J9 -> 1993 | G5: =Elect!K9 -> 1226 | H5: =Elect!Q9 -> 90 | I5: =Elect!W9 -> 135 | J5: =Elect!Y9 -> 228 | K5: =Elect!AA9 -> 0 | L5: =Elect!AC9 -> 1511.03 | M5: =Elect!AE9 -> 0 | N5: =Elect!AG9 -> 0 | O5: =Elect!AI9 -> 396.97 | P5: =Elect!AK9 -> 2288.54 | Q5: =Elect!AN9 -> 12 | R5: =Elect!AP9 -> 2 | S5: =Elect!AR9 -> 4.29 | T5: =Elect!AT9 -> 32 | U5: =Elect!AV9 -> 361 | V5: =Elect!AX9 -> 37 | W5: =Elect!AZ9 -> 1838 | X5: =Elect!BB9 -> 3667.3 | Y5: =Elect!BE9 -> 0 | Z5: =Elect!BG9 -> 917 | AA5: =Elect!BI9 -> 85 | AB5: =Elect!BK9 -> 202 | AD5: =Water!C10 -> 232 | AE5: =Water!E10 -> 11.6 | AF5: =Water!G10 -> 0 | AH5: =Gas!C10 -> 170.66 | AI5: =Gas!E10 -> 0 | AJ5: =Gas!G10 -> 2 | AK5: =Elect!BM9 -> 0
A6: Cairo at The First Residence | B6: =B5+1 -> 5 | C6: 3 | D6: 2020 | F6: =Elect!J10 -> 1723 | G6: =Elect!K10 -> 1590 | H6: =Elect!Q10 -> 60 | I6: =Elect!W10 -> 114 | J6: =Elect!Y10 -> 191 | K6: =Elect!AA10 -> 0 | L6: =Elect!AC10 -> 2708.3 | M6: =Elect!AE10 -> 0 | N6: =Elect!AG10 -> 0 | O6: =Elect!AI10 -> 508.8 | P6: =Elect!AK10 -> 2934.61 | Q6: =Elect!AN10 -> 29 | R6: =Elect!AP10 -> 2 | S6: =Elect!AR10 -> 5.94 | T6: =Elect!AT10 -> 41 | U6: =Elect!AV10 -> 485 | V6: =Elect!AX10 -> 39 | W6: =Elect!AZ10 -> 2436 | X6: =Elect!BB10 -> 4770.3 | Y6: =Elect!BE10 -> 0 | Z6: =Elect!BG10 -> 1282 | AA6: =Elect!BI10 -> 107 | AB6: =Elect!BK10 -> 262 | AD6: =Water!C11 -> 81.2 | AE6: =Water!E11 -> 63.8 | AF6: =Water!G11 -> 0 | AH6: =Gas!C11 -> 170.66 | AI6: =Gas!E11 -> 109.55212 | AJ6: =Gas!G11 -> 2 | AK6: =Elect!BM10 -> 0
A7: Cairo at The First Residence | B7: =B6+1 -> 6 | C7: 3 | D7: 2020 | F7: =Elect!J11 -> 1827 | G7: =Elect!K11 -> 1427 | H7: =Elect!Q11 -> 60 | I7: =Elect!W11 -> 113 | J7: =Elect!Y11 -> 189 | K7: =Elect!AA11 -> 0 | L7: =Elect!AC11 -> 992.16 | M7: =Elect!AE11 -> 0 | N7: =Elect!AG11 -> 0 | O7: =Elect!AI11 -> 179.14 | P7: =Elect!AK11 -> 909.48 | Q7: =Elect!AN11 -> 47 | R7: =Elect!AP11 -> 2 | S7: =Elect!AR11 -> 1.87 | T7: =Elect!AT11 -> 18 | U7: =Elect!AV11 -> 197 | V7: =Elect!AX11 -> 33 | W7: =Elect!AZ11 -> 867 | X7: =Elect!BB11 -> 1578.9 | Y7: =Elect!BE11 -> 0 | Z7: =Elect!BG11 -> 471 | AA7: =Elect!BI11 -> 35 | AB7: =Elect!BK11 -> 84 | AD7: =Water!C12 -> 46.4 | AE7: =Water!E12 -> 46.4 | AF7: =Water!G12 -> 0 | AH7: =Gas!C12 -> 170.66 | AI7: =Gas!E12 -> 149.20606 | AJ7: =Gas!G12 -> 1 | AK7: =Elect!BM11 -> 0
A8: Cairo at The First Residence | B8: =B7+1 -> 7 | C8: 3 | D8: 2020 | F8: =Elect!J12 -> 2458 | G8: =Elect!K12 -> 1967 | H8: =Elect!Q12 -> 120 | I8: =Elect!W12 -> 160 | J8: =Elect!Y12 -> 263 | K8: =Elect!AA12 -> 0 | L8: =Elect!AC12 -> 507.21 | M8: =Elect!AE12 -> 1939.27 | N8: =Elect!AG12 -> 0 | O8: =Elect!AI12 -> 437.78 | P8: =Elect!AK12 -> 2415.74 | Q8: =Elect!AN12 -> 15 | R8: =Elect!AP12 -> 2 | S8: =Elect!AR12 -> 5.17 | T8: =Elect!AT12 -> 36 | U8: =Elect!AV12 -> 371 | V8: =Elect!AX12 -> 44 | W8: =Elect!AZ12 -> 2571 | X8: =Elect!BB12 -> 4300.1 | Y8: =Elect!BE12 -> 0 | Z8: =Elect!BG12 -> 1339 | AA8: =Elect!BI12 -> 95 | AB8: =Elect!BK12 -> 232 | AD8: =Water!C13 -> 69.6 | AE8: =Water!E13 -> 29 | AF8: =Water!G13 -> 0 | AH8: =Gas!C13 -> 170.66 | AI8: =Gas!E13 -> 149.20606 | AJ8: =Gas!G13 -> 1 | AK8: =Elect!BM12 -> 0
A9: Cairo at The First Residence | B9: =B8+1 -> 8 | C9: 3 | D9: 2020 | F9: =Elect!J13 -> 2104 | G9: =Elect!K13 -> 1316 | H9: =Elect!Q13 -> 90 | I9: =Elect!W13 -> 148 | J9: =Elect!Y13 -> 237 | K9: =Elect!AA13 -> 0 | L9: =Elect!AC13 -> 0 | M9: =Elect!AE13 -> 2327.23 | N9: =Elect!AG13 -> 0 | O9: =Elect!AI13 -> 444.14 | P9: =Elect!AK13 -> 2433.23 | Q9: =Elect!AN13 -> 12 | R9: =Elect!AP13 -> 3 | S9: =Elect!AR13 -> 4.62 | T9: =Elect!AT13 -> 31 | U9: =Elect!AV13 -> 332 | V9: =Elect!AX13 -> 38 | W9: =Elect!AZ13 -> 2215 | X9: =Elect!BB13 -> 3896.5 | Y9: =Elect!BE13 -> 0 | Z9: =Elect!BG13 -> 1175 | AA9: =Elect!BI13 -> 89 | AB9: =Elect!BK13 -> 217 | AD9: =Water!C14 -> 75.4 | AE9: =Water!E14 -> 40.6 | AF9: =Water!G14 -> 0 | AH9: =Gas!C14 -> 170.66 | AI9: =Gas!E14 -> 149.20606 | AJ9: =Gas!G14 -> 1 | AK9: =Elect!BM13 -> 0
A10: Cairo at The First Residence | B10: =B9+1 -> 9 | C10: 3 | D10: 2020 | F10: =Elect!J14 -> 962 | G10: =Elect!K14 -> 981 | H10: =Elect!Q14 -> 30 | I10: =Elect!W14 -> 73 | J10: =Elect!Y14 -> 117 | K10: =Elect!AA14 -> 0 | L10: =Elect!AC14 -> 0 | M10: =Elect!AE14 -> 1698.65 | N10: =Elect!AG14 -> 0 | O10: =Elect!AI14 -> 333.9 | P10: =Elect!AK14 -> 1850.76 | Q10: =Elect!AN14 -> 6 | R10: =Elect!AP14 -> 1 | S10: =Elect!AR14 -> 2.53 | T10: =Elect!AT14 -> 27 | U10: =Elect!AV14 -> 251 | V10: =Elect!AX14 -> 19 | W10: =Elect!AZ14 -> 943 | X10: =Elect!BB14 -> 2106.3 | Y10: =Elect!BE14 -> 0 | Z10: =Elect!BG14 -> 627 | AA10: =Elect!BI14 -> 49 | AB10: =Elect!BK14 -> 117 | AD10: =Water!C15 -> 98.6 | AE10: =Water!E15 -> 34.8 | AF10: =Water!G15 -> 0 | AH10: =Gas!C15 -> 170.66 | AI10: =Gas!E15 -> 149.20606 | AJ10: =Gas!G15 -> 0 | AK10: =Elect!BM14 -> 0
A11: Cairo at The First Residence | B11: =B10+1 -> 10 | C11: 3 | D11: 2020 | F11: =Elect!J15 -> 2501 | G11: =Elect!K15 -> 1330 | H11: =Elect!Q15 -> 90 | I11: =Elect!W15 -> 189 | J11: =Elect!Y15 -> 168 | K11: =Elect!AA15 -> 0 | L11: =Elect!AC15 -> 0 | M11: =Elect!AE15 -> 360.4 | N11: =Elect!AG15 -> 527.35 | O11: =Elect!AI15 -> 149.46 | P11: =Elect!AK15 -> 1974.25 | Q11: =Elect!AN15 -> 15 | R11: =Elect!AP15 -> 3 | S11: =Elect!AR15 -> 6.27 | T11: =Elect!AT15 -> 41 | U11: =Elect!AV15 -> 343 | V11: =Elect!AX15 -> 43 | W11: =Elect!AZ15 -> 2196 | X11: =Elect!BB15 -> 4842.5 | Y11: =Elect!BE15 -> 0 | Z11: =Elect!BG15 -> 1375 | AA11: =Elect!BI15 -> 111 | AB11: =Elect!BK15 -> 274 | AD11: =Water!C16 -> 29 | AE11: =Water!E16 -> 17.4 | AF11: =Water!G16 -> 8.12 | AH11: =Gas!C16 -> 170.66 | AI11: =Gas!E16 -> 149.20606 | AJ11: =Gas!G16 -> 2 | AK11: =Elect!BM15 -> 0
A12: Cairo at The First Residence | B12: =B11+1 -> 11 | C12: 3 | D12: 2020 | F12: =Elect!J16 -> 1367 | G12: =Elect!K16 -> 911 | H12: =Elect!Q16 -> 60 | I12: =Elect!W16 -> 99 | J12: =Elect!Y16 -> 292 | K12: =Elect!AA16 -> 0 | L12: =Elect!AC16 -> 601.55 | M12: =Elect!AE16 -> 991.1 | N12: =Elect!AG16 -> 0 | O12: =Elect!AI16 -> 234.79 | P12: =Elect!AK16 -> 1706.07 | Q12: =Elect!AN16 -> 8 | R12: =Elect!AP16 -> 2 | S12: =Elect!AR16 -> 3.19 | T12: =Elect!AT16 -> 31 | U12: =Elect!AV16 -> 221 | V12: =Elect!AX16 -> 21 | W12: =Elect!AZ16 -> 1197 | X12: =Elect!BB16 -> 2570.6 | Y12: =Elect!BE16 -> 0 | Z12: =Elect!BG16 -> 789 | AA12: =Elect!BI16 -> 62 | AB12: =Elect!BK16 -> 150 | AD12: =Water!C17 -> 46.4 | AE12: =Water!E17 -> 29 | AF12: =Water!G17 -> 5.22 | AH12: =Gas!C17 -> 170.66 | AI12: =Gas!E17 -> 149.20606 | AJ12: =Gas!G17 -> 4 | AK12: =Elect!BM16 -> 0
A13: Cairo at The First Residence | B13: =B12+1 -> 12 | C13: 3 | D13: 2020 | F13: =Elect!J17 -> 1552 | G13: =Elect!K17 -> 1122 | H13: =Elect!Q17 -> 60 | I13: =Elect!W17 -> 99 | J13: =Elect!Y17 -> 158 | K13: =Elect!AA17 -> 0 | L13: =Elect!AC17 -> 0 | M13: =Elect!AE17 -> 2015.06 | N13: =Elect!AG17 -> 0 | O13: =Elect!AI17 -> 383.72 | P13: =Elect!AK17 -> 2061.7 | Q13: =Elect!AN17 -> 8 | R13: =Elect!AP17 -> 1 | S13: =Elect!AR17 -> 3.19 | T13: =Elect!AT17 -> 22 | U13: =Elect!AV17 -> 283 | V13: =Elect!AX17 -> 15 | W13: =Elect!AZ17 -> 1187 | X13: =Elect!BB17 -> 2641.7 | Y13: =Elect!BE17 -> 0 | Z13: =Elect!BG17 -> 733 | AA13: =Elect!BI17 -> 63 | AB13: =Elect!BK17 -> 157 | AD13: =Water!C18 -> 40.6 | AE13: =Water!E18 -> 29 | AF13: =Water!G18 -> 7.54 | AH13: =Gas!C18 -> 170.66 | AI13: =Gas!E18 -> 149.20606 | AJ13: =Gas!G18 -> 1 | AK13: =Elect!BM17 -> 0
A14: Cairo at The First Residence | B14: =B13+1 -> 13 | C14: 3 | D14: 2020 | F14: =Elect!J18 -> 1989 | G14: =Elect!K18 -> 1336 | H14: =Elect!Q18 -> 30 | I14: =Elect!W18 -> 136 | J14: =Elect!Y18 -> 217 | K14: =Elect!AA18 -> 0 | L14: =Elect!AC18 -> 0 | M14: =Elect!AE18 -> 555.97 | N14: =Elect!AG18 -> 914.25 | O14: =Elect!AI18 -> 227.9 | P14: =Elect!AK18 -> 1314.93 | Q14: =Elect!AN18 -> 11 | R14: =Elect!AP18 -> 2 | S14: =Elect!AR18 -> 3.63 | T14: =Elect!AT18 -> 29 | U14: =Elect!AV18 -> 298 | V14: =Elect!AX18 -> 0 | W14: =Elect!AZ18 -> 2023 | X14: =Elect!BB18 -> 3427.4 | Y14: =Elect!BE18 -> 0 | Z14: =Elect!BG18 -> 816 | AA14: =Elect!BI18 -> 90 | AB14: =Elect!BK18 -> 212 | AD14: =Water!C19 -> 63.8 | AE14: =Water!E19 -> 46.4 | AF14: =Water!G19 -> 6.96 | AH14: =Gas!C19 -> 170.66 | AI14: =Gas!E19 -> 149.20606 | AJ14: =Gas!G19 -> 1 | AK14: =Elect!BM18 -> 0
... A32: Cairo at The First Residence | B32: =B31+1 -> 31 | C32: 3 | D32: 2020 | F32: =Elect!J36 -> 0 | G32: =Elect!K36 -> 0 | H32: =Elect!Q36 -> 0 | I32: =Elect!W36 -> 0 | J32: =Elect!Y36 -> 0 | K32: =Elect!AA36 -> 0 | L32: =Elect!AC36 -> 0 | M32: =Elect!AE36 -> 0 | N32: =Elect!AG36 -> 0 | O32: =Elect!AI36 -> 0 | P32: =Elect!AK36 -> 0 | Q32: =Elect!AN36 -> 0 | R32: =Elect!AP36 -> 0 | S32: =Elect!AR36 -> 0 | T32: =Elect!AT36 -> 0 | U32: =Elect!AV36 -> 0 | V32: =Elect!AX36 -> 0 | W32: =Elect!AZ36 -> 0 | X32: =Elect!BB36 -> 0 | Y32: =Elect!BE36 -> 0 | Z32: =Elect!BG36 -> 0 | AA32: =Elect!BI36 -> 0 | AB32: =Elect!BK36 -> 0 | AD32: =Water!C37 -> 0 | AE32: =Water!E37 -> 0 | AF32: =Water!G37 -> 0 | AH32: =Gas!C37 -> 0 | AI32: =Gas!E37 -> 0 | AJ32: =Gas!G37 -> 0 | AK32: =Elect!BM36 -> 0

Sheet Elect
A1: April | M1: Electricity | BL1: Power Taxes | BM1: 0.0006 | BN1: Max Demand | BP1: 500 | BQ1: Electricity UP | BS1: 0.46
BL2: Light Taxes | BM2: 0.03 | BN2: PF Penalty | BQ2: Max. Demand UP | BS2: 30
A3: Date | B3: COUNTER (1) | D3: MD | F3: KVAR | H3: n | I3: Guest Rooms Consumption | R3: Casino Consumption | AD3: Plant Room Shared Loads | AW3: To Be Charged By First Arabian | BG3: From Main Panel G2 | BL3: Total Consumption. | BM3: No. Of | BN3: KWH/ | BO3: No. Of | BP3: KWH/ | BQ3: Total Cost | BR3: L.E\ | BS3: L.E\
B4: Reading | C4: Consp. F: *800 | D4: Reading | E4: Consp F: 80 | F4: Reading | G4: Consp. F:*10 | I4: Main Feeder | J4: Consp | K4: T2+T8 | L4: Trans T2 | M4: Consp | N4: Trans T8 | O4: Consp | P4: La Gourmandize | Q4: Consp *30 | R4: Casino 1 | S4: Consp | T4: Casino 2 | U4: Consp | V4: Casino 3rd floor EM | W4: Consp | X4: Casino 3rd floor Normal | Y4: Consp | Z4: Chiller 1 | AA4: Consp 53% | AB4: Chiller 2 | AC4: Consp 53% | AD4: Chiller 3 | AE4: Consp 53% | AF4: Chiller 4 | AG4: Consp 53% | AH4: Cooling towers | AI4: Consp 53% | AJ4: Chiller Pumps | AK4: Consp 53% | AL4: Total Plant Room Consp | AM4: LG Bakery | AN4: Consp | AO4: Mall Ceiling light | AP4: Consp | AQ4: New chiller for Second floor | AR4: Consp | AS4: LG Bakery light ( Old lockers ) | AT4: Consp | AU4: MCCR1 | AV4: Consp | AW4: Children Swimming pool | AX4: Consp | AY4: DPH1 | AZ4: Consp | BA4: Main G2 | BB4: Consp | BC4: Total Consp From First Arabian | BD4: Casino Emergency | BE4: Consp | BF4: L / A | BG4: Consp | BH4: L / B | BI4: Consp | BJ4: L / C | BK4: Consp | BM4: Rooms | BN4: room | BO4: guest | BP4: guest | BR4: Room | BS4: Guest
A5: Last Month Reading | I5: 20903264 | J5: =IF(I5>=I4,I5-I4,0) -> 0 | K5: =M5+O5 -> 0 | L5: 639087 | M5: =IF(L5>=L4,L5-L4,0) -> 0 | N5: 625772 | O5: =IF(N5>=N4,N5-N4,0) -> 0 | P5: 210667 | Q5: =IF(P5>=P4,P5-P4,0)*30 -> 0 | R5: 702925 | S5: =IF(R5>=R4,R5-R4,0) -> 0 | T5: 344001 | U5: =IF(T5>=T4,T5-T4,0) -> 0 | V5: 89901 | W5: =IF(V5>=V4,V5-V4,0) -> 0 | X5: 167667 | Y5: =IF(X5>=X4,X5-X4,0) -> 0 | Z5: 315108 | AA5: =IF(Z5>=Z4,Z5-Z4,0)*0.53 -> 0 | AB5: 657605 | AC5: =IF(AB5>=AB4,AB5-AB4,0)*0.53 -> 0 | AD5: 728396 | AE5: =IF(AD5>=AD4,AD5-AD4,0)*0.53 -> 0 | AF5: 704806 | AG5: =IF(AF5>=AF4,AF5-AF4,0)*0.53 -> 0 | AH5: 196777 | AI5: =IF(AH5>=AH4,AH5-AH4,0)*0.53 -> 0 | AJ5: 230037 | AK5: =IF(AJ5>=AJ4,AJ5-AJ4,0)*0.53 -> 0 | AL5: =AA5+AC5+AE5+AG5+AI5+AK5 -> 0 | AM5: 6884066 | AN5: =IF(AM5>=AM4,AM5-AM4,0) -> 0 | AO5: 536155 | AP5: =IF(AO5>=AO4,AO5-AO4,0) -> 0 | AQ5: 880427 | AR5: =IF(AQ5>=AQ4,AQ5-AQ4,0)*0.11 -> 0 | AS5: 781476 | AT5: =IF(AS5>=AS4,AS5-AS4,0) -> 0 | AU5: 2151442 | AV5: =IF(AU5>=AU4,AU5-AU4,0) -> 0 | AW5: 194717 | AX5: 0 | AY5: 16702581 | AZ5: =IF(AY5>=AY4,AY5-AY4,0) -> 0 | BA5: 20196681 | BB5: =IF(BA5>=BA4,BA5-BA4,0)-(0.6*BG5)-(0.5*BI5)-BK5-BE5 -> 0 | BC5: =AN5+AP5+AR5+AT5+AV5+AX5+AZ5+BB5 -> 0 | BD5: 1323286 | BE5: =IF(BD5>=BD4,BD5-BD4,0) -> 0 | BF5: 3122359 | BG5: =IF(BF5>=BF4,BF5-BF4,0) -> 0 | BH5: 346792 | BI5: =IF(BH5>=BH4,BH5-BH4,0) -> 0 | BJ5: 394126 | BK5: =IF(BJ5>=BJ4,BJ5-BJ4,0) -> 0
A6: 1 | C6: =IF(+B6-B5>0,B6-B5,(B6-B5)>0)*800 -> 0 | E6: =IF(+D6-D5>0,D6-D5,(D6-D5)>0)*80 -> 0 | G6: =IF(+F6-F5>0,F6-F5,(F6-F5)>0)*10 -> 0 | H6: 56 | I6: 20904798 | J6: =IF(I6>=I5,I6-I5,0) -> 1534 | K6: =M6+O6 -> 1084 | L6: 639631 | M6: =IF(L6>=L5,L6-L5,0) -> 544 | N6: 626312 | O6: =IF(N6>=N5,N6-N5,0) -> 540 | P6: 210667 | Q6: =IF(P6>=P5,P6-P5,0)*30 -> 0 | R6: 702925 | S6: =IF(R6>=R5,R6-R5,0) -> 0 | T6: 344001 | U6: =IF(T6>=T5,T6-T5,0) -> 0 | V6: 90021 | W6: =IF(V6>=V5,V6-V5,0) -> 120 | X6: 167765 | Y6: =IF(X6>=X5,X6-X5,0) -> 98 | Z6: 315108 | AA6: =IF(Z6>=Z5,Z6-Z5,0)*0.53 -> 0 | AB6: 658198 | AC6: =IF(AB6>=AB5,AB6-AB5,0)*0.53 -> 314.29 | AD6: 729274 | AE6: =IF(AD6>=AD5,AD6-AD5,0)*0.53 -> 465.34 | AF6: 705422 | AG6: =IF(AF6>=AF5,AF6-AF5,0)*0.53 -> 326.48 | AH6: 197322 | AI6: =IF(AH6>=AH5,AH6-AH5,0)*0.53 -> 288.85 | AJ6: 233342 | AK6: =IF(AJ6>=AJ5,AJ6-AJ5,0)*0.53 -> 1751.65 | AL6: =AA6+AC6+AE6+AG6+AI6+AK6 -> 3146.61 | AM6: 6884089 | AN6: =IF(AM6>=AM5,AM6-AM5,0) -> 23 | AO6: 536158 | AP6: =IF(AO6>=AO5,AO6-AO5,0) -> 3 | AQ6: 880456 | AR6: =IF(AQ6>=AQ5,AQ6-AQ5,0)*0.11 -> 3.19 | AS6: 781503 | AT6: =IF(AS6>=AS5,AS6-AS5,0) -> 27 | AU6: 2151715 | AV6: =IF(AU6>=AU5,AU6-AU5,0) -> 273 | AW6: 194756 | AX6: =IF(AW6>=AW5,AW6-AW5,0) -> 39 | AY6: 16704054 | AZ6: =IF(AY6>=AY5,AY6-AY5,0) -> 1473 | BA6: 20200076 | BB6: =IF(BA6>=BA5,BA6-BA5,0)-(0.6*BG6)-(0.5*BI6)-BK6-BE6 -> 2753.9 | BC6: =AN6+AP6+AR6+AT6+AV6+AX6+AZ6+BB6 -> 4595.09 | BD6: 1323286 | BE6: =IF(BD6>=BD5,BD6-BD5,0) -> 0 | BF6: 3123115 | BG6: =IF(BF6>=BF5,BF6-BF5,0) -> 756 | BH6: 346859 | BI6: =IF(BH6>=BH5,BH6-BH5,0) -> 67 | BJ6: 394280 | BK6: =IF(BJ6>=BJ5,BJ6-BJ5,0) -> 154 | BL6: =J6+Q6+AL6+BC6 -> 9275.7 | BN6: =IF(BL6>0,BL6/#REF!,0) -> #REF! | BP6: =IF(BL6>0,BL6/BO6,0) -> #DIV/0! | BQ6: =BL6*BS1 -> 4266.822 | BR6: =IF(BQ6>0,BQ6/#REF!,0) -> #REF! | BS6: =IF(BQ6>0,BQ6/BO6,0) -> #DIV/0!
A7: 2 | I7: 20906694 | J7: =IF(I7>=I6,I7-I6,0) -> 1896 | K7: =M7+O7 -> 1790 | L7: 640561 | M7: =IF(L7>=L6,L7-L6,0) -> 930 | N7: 627172 | O7: =IF(N7>=N6,N7-N6,0) -> 860 | P7: 210670 | Q7: =IF(P7>=P6,P7-P6,0)*30 -> 90 | R7: 702925 | S7: =IF(R7>=R6,R7-R6,0) -> 0 | T7: 344001 | U7: =IF(T7>=T6,T7-T6,0) -> 0 | V7: 90171 | W7: =IF(V7>=V6,V7-V6,0) -> 150 | X7: 167861 | Y7: =IF(X7>=X6,X7-X6,0) -> 96 | Z7: 315108 | AA7: =IF(Z7>=Z6,Z7-Z6,0)*0.53 -> 0 | AB7: 659201 | AC7: =IF(AB7>=AB6,AB7-AB6,0)*0.53 -> 531.59 | AD7: 732609 | AE7: =IF(AD7>=AD6,AD7-AD6,0)*0.53 -> 1767.55 | AF7: 705621 | AG7: =IF(AF7>=AF6,AF7-AF6,0)*0.53 -> 105.47 | AH7: 198543 | AI7: =IF(AH7>=AH6,AH7-AH6,0)*0.53 -> 647.13 | AJ7: 239214 | AK7: =IF(AJ7>=AJ6,AJ7-AJ6,0)*0.53 -> 3112.16 | AL7: =AA7+AC7+AE7+AG7+AI7+AK7 -> 6163.9 | AM7: 6884116 | AN7: =IF(AM7>=AM6,AM7-AM6,0) -> 27 | AO7: 536160 | AP7: =IF(AO7>=AO6,AO7-AO6,0) -> 2 | AQ7: 880512 | AR7: =IF(AQ7>=AQ6,AQ7-AQ6,0)*0.11 -> 6.16 | AS7: 781548 | AT7: =IF(AS7>=AS6,AS7-AS6,0) -> 45 | AU7: 2152168 | AV7: =IF(AU7>=AU6,AU7-AU6,0) -> 453 | AW7: 194794 | AX7: =IF(AW7>=AW6,AW7-AW6,0) -> 38 | AY7: 16706412 | AZ7: =IF(AY7>=AY6,AY7-AY6,0) -> 2358 | BA7: 20206339 | BB7: =IF(BA7>=BA6,BA7-BA6,0)-(0.6*BG7)-(0.5*BI7)-BK7-BE7 -> 5120.2 | BC7: =AN7+AP7+AR7+AT7+AV7+AX7+AZ7+BB7 -> 8049.36 | BD7: 1323286 | BE7: =IF(BD7>=BD6,BD7-BD6,0) -> 0 | BF7: 3124443 | BG7: =IF(BF7>=BF6,BF7-BF6,0) -> 1328 | BH7: 346973 | BI7: =IF(BH7>=BH6,BH7-BH6,0) -> 114 | BJ7: 394569 | BK7: =IF(BJ7>=BJ6,BJ7-BJ6,0) -> 289 | BL7: =J7+Q7+AL7+BC7 -> 16199.26 | BN7: =IF(BL7>0,BL7/BM6,0) -> #DIV/0! | BP7: =IF(BL7>0,BL7/BO7,0) -> #DIV/0! | BQ7: =BL7*BS1 -> 7451.6596 | BR7: =IF(BQ7>0,BQ7/BM6,0) -> #DIV/0! | BS7: =IF(BQ7>0,BQ7/BO7,0) -> #DIV/0!
A8: 3 | C8: =IF(+B8-B7>0,B8-B7,(B8-B7)>0)*800 -> 0 | E8: =IF(+D8-D7>0,D8-D7,(D8-D7)>0)*80 -> 0 | G8: =IF(+F8-F7>0,F8-F7,(F8-F7)>0)*10 -> 0 | H8: 57 | I8: 20908396 | J8: =IF(I8>=I7,I8-I7,0) -> 1702 | K8: =M8+O8 -> 776 | L8: 640963 | M8: =IF(L8>=L7,L8-L7,0) -> 402 | N8: 627546 | O8: =IF(N8>=N7,N8-N7,0) -> 374 | P8: 210671 | Q8: =IF(P8>=P7,P8-P7,0)*30 -> 30 | R8: 702925 | S8: =IF(R8>=R7,R8-R7,0) -> 0 | T8: 344001 | U8: =IF(T8>=T7,T8-T7,0) -> 0 | V8: 90258 | W8: =IF(V8>=V7,V8-V7,0) -> 87 | X8: 168158 | Y8: =IF(X8>=X7,X8-X7,0) -> 297 | Z8: 315108 | AA8: =IF(Z8>=Z7,Z8-Z7,0)*0.53 -> 0 | AB8: 659805 | AC8: =IF(AB8>=AB7,AB8-AB7,0)*0.53 -> 320.12 | AD8: 732945 | AE8: =IF(AD8>=AD7,AD8-AD7,0)*0.53 -> 178.08 | AF8: 705621 | AG8: =IF(AF8>=AF7,AF8-AF7,0)*0.53 -> 0 | AH8: 198976 | AI8: =IF(AH8>=AH7,AH8-AH7,0)*0.53 -> 229.49 | AJ8: 241627 | AK8: =IF(AJ8>=AJ7,AJ8-AJ7,0)*0.53 -> 1278.89 | AL8: =AA8+AC8+AE8+AG8+AI8+AK8 -> 2006.58 | AM8: 6884120 | AN8: =IF(AM8>=AM7,AM8-AM7,0) -> 4 | AO8: 536162 | AP8: =IF(AO8>=AO7,AO8-AO7,0) -> 2 | AQ8: 880531 | AR8: =IF(AQ8>=AQ7,AQ8-AQ7,0)*0.11 -> 2.09 | AS8: 781572 | AT8: =IF(AS8>=AS7,AS8-AS7,0) -> 24 | AU8: 2152389 | AV8: =IF(AU8>=AU7,AU8-AU7,0) -> 221 | AW8: 194826 | AX8: =IF(AW8>=AW7,AW8-AW7,0) -> 32 | AY8: 16707378 | AZ8: =IF(AY8>=AY7,AY8-AY7,0) -> 966 | BA8: 20208687 | BB8: =IF(BA8>=BA7,BA8-BA7,0)-(0.6*BG8)-(0.5*BI8)-BK8-BE8 -> 1860.6 | BC8: =AN8+AP8+AR8+AT8+AV8+AX8+AZ8+BB8 -> 3111.69 | BD8: 1323286 | BE8: =IF(BD8>=BD7,BD8-BD7,0) -> 0 | BF8: 3125037 | BG8: =IF(BF8>=BF7,BF8-BF7,0) -> 594 | BH8: 347019 | BI8: =IF(BH8>=BH7,BH8-BH7,0) -> 46 | BJ8: 394677 | BK8: =IF(BJ8>=BJ7,BJ8-BJ7,0) -> 108 | BL8: =J8+Q8+AL8+BC8 -> 6850.27 | BN8: =IF(BL8>0,BL8/BM7,0) -> #DIV/0! | BP8: =IF(BL8>0,BL8/BO8,0) -> #DIV/0! | BQ8: =BL8*BS1 -> 3151.1242 | BR8: =IF(BQ8>0,BQ8/BM7,0) -> #DIV/0! | BS8: =IF(BQ8>0,BQ8/BO8,0) -> #DIV/0!
A9: 4 | C9: =IF(+B9-B8>0,B9-B8,(B9-B8)>0)*800 -> 0 | E9: =IF(+D9-D8>0,D9-D8,(D9-D8)>0)*80 -> 0 | G9: =IF(+F9-F8>0,F9-F8,(F9-F8)>0)*10 -> 0 | I9: 20910389 | J9: =IF(I9>=I8,I9-I8,0) -> 1993 | K9: =M9+O9 -> 1226 | L9: 641597 | M9: =IF(L9>=L8,L9-L8,0) -> 634 | N9: 628138 | O9: =IF(N9>=N8,N9-N8,0) -> 592 | P9: 210674 | Q9: =IF(P9>=P8,P9-P8,0)*30 -> 90 | R9: 702925 | S9: =IF(R9>=R8,R9-R8,0) -> 0 | T9: 344001 | U9: =IF(T9>=T8,T9-T8,0) -> 0 | V9: 90393 | W9: =IF(V9>=V8,V9-V8,0) -> 135 | X9: 168386 | Y9: =IF(X9>=X8,X9-X8,0) -> 228 | Z9: 315108 | AA9: =IF(Z9>=Z8,Z9-Z8,0)*0.53 -> 0 | AB9: 662656 | AC9: =IF(AB9>=AB8,AB9-AB8,0)*0.53 -> 1511.03 | AD9: 732945 | AE9: =IF(AD9>=AD8,AD9-AD8,0)*0.53 -> 0 | AF9: 705621 | AG9: =IF(AF9>=AF8,AF9-AF8,0)*0.53 -> 0 | AH9: 199725 | AI9: =IF(AH9>=AH8,AH9-AH8,0)*0.53 -> 396.97 | AJ9: 245945 | AK9: =IF(AJ9>=AJ8,AJ9-AJ8,0)*0.53 -> 2288.54 | AL9: =AA9+AC9+AE9+AG9+AI9+AK9 -> 4196.54 | AM9: 6884132 | AN9: =IF(AM9>=AM8,AM9-AM8,0) -> 12 | AO9: 536164 | AP9: =IF(AO9>=AO8,AO9-AO8,0) -> 2 | AQ9: 880570 | AR9: =IF(AQ9>=AQ8,AQ9-AQ8,0)*0.11 -> 4.29 | AS9: 781604 | AT9: =IF(AS9>=AS8,AS9-AS8,0) -> 32 | AU9: 2152750 | AV9: =IF(AU9>=AU8,AU9-AU8,0) -> 361 | AW9: 194863 | AX9: =IF(AW9>=AW8,AW9-AW8,0) -> 37 | AY9: 16709216 | AZ9: =IF(AY9>=AY8,AY9-AY8,0) -> 1838 | BA9: 20213149 | BB9: =IF(BA9>=BA8,BA9-BA8,0)-(0.6*BG9)-(0.5*BI9)-BK9-BE9 -> 3667.3 | BC9: =AN9+AP9+AR9+AT9+AV9+AX9+AZ9+BB9 -> 5953.59 | BD9: 1323286 | BE9: =IF(BD9>=BD8,BD9-BD8,0) -> 0 | BF9: 3125954 | BG9: =IF(BF9>=BF8,BF9-BF8,0) -> 917 | BH9: 347104 | BI9: =IF(BH9>=BH8,BH9-BH8,0) -> 85 | BJ9: 394879 | BK9: =IF(BJ9>=BJ8,BJ9-BJ8,0) -> 202 | BL9: =J9+Q9+AL9+BC9 -> 12233.13 | BN9: =IF(BL9>0,BL9/BM8,0) -> #DIV/0! | BP9: =IF(BL9>0,BL9/BO9,0) -> #DIV/0! | BQ9: =BL9*BS1 -> 5627.2398 | BR9: =IF(BQ9>0,BQ9/BM8,0) -> #DIV/0! | BS9: =IF(BQ9>0,BQ9/BO9,0) -> #DIV/0!
A10: 5 | C10: =IF(+B10-B9>0,B10-B9,(B10-B9)>0)*800 -> 0 | E10: =IF(+D10-D9>0,D10-D9,(D10-D9)>0)*80 -> 0 | G10: =IF(+F10-F9>0,F10-F9,(F10-F9)>0)*10 -> 0 | H10: 58 | I10: 20912112 | J10: =IF(I10>=I9,I10-I9,0) -> 1723 | K10: =M10+O10 -> 1590 | L10: 642226 | M10: =IF(L10>=L9,L10-L9,0) -> 629 | N10: 629099 | O10: =IF(N10>=N9,N10-N9,0) -> 961 | P10: 210676 | Q10: =IF(P10>=P9,P10-P9,0)*30 -> 60 | R10: 702925 | S10: =IF(R10>=R9,R10-R9,0) -> 0 | T10: 344001 | U10: =IF(T10>=T9,T10-T9,0) -> 0 | V10: 90507 | W10: =IF(V10>=V9,V10-V9,0) -> 114 | X10: 168577 | Y10: =IF(X10>=X9,X10-X9,0) -> 191 | Z10: 315108 | AA10: =IF(Z10>=Z9,Z10-Z9,0)*0.53 -> 0 | AB10: 667766 | AC10: =IF(AB10>=AB9,AB10-AB9,0)*0.53 -> 2708.3 | AD10: 732945 | AE10: =IF(AD10>=AD9,AD10-AD9,0)*0.53 -> 0 | AF10: 705621 | AG10: =IF(AF10>=AF9,AF10-AF9,0)*0.53 -> 0 | AH10: 200685 | AI10: =IF(AH10>=AH9,AH10-AH9,0)*0.53 -> 508.8 | AJ10: 251482 | AK10: =IF(AJ10>=AJ9,AJ10-AJ9,0)*0.53 -> 2934.61 | AL10: =AA10+AC10+AE10+AG10+AI10+AK10 -> 6151.71 | AM10: 6884161 | AN10: =IF(AM10>=AM9,AM10-AM9,0) -> 29 | AO10: 536166 | AP10: =IF(AO10>=AO9,AO10-AO9,0) -> 2 | AQ10: 880624 | AR10: =IF(AQ10>=AQ9,AQ10-AQ9,0)*0.11 -> 5.94 | AS10: 781645 | AT10: =IF(AS10>=AS9,AS10-AS9,0) -> 41 | AU10: 2153235 | AV10: =IF(AU10>=AU9,AU10-AU9,0) -> 485 | AW10: 194902 | AX10: =IF(AW10>=AW9,AW10-AW9,0) -> 39 | AY10: 16711652 | AZ10: =IF(AY10>=AY9,AY10-AY9,0) -> 2436 | BA10: 20219004 | BB10: =IF(BA10>=BA9,BA10-BA9,0)-(0.6*BG10)-(0.5*BI10)-BK10-BE10 -> 4770.3 | BC10: =AN10+AP10+AR10+AT10+AV10+AX10+AZ10+BB10 -> 7808.24 | BD10: 1323286 | BE10: =IF(BD10>=BD9,BD10-BD9,0) -> 0 | BF10: 3127236 | BG10: =IF(BF10>=BF9,BF10-BF9,0) -> 1282 | BH10: 347211 | BI10: =IF(BH10>=BH9,BH10-BH9,0) -> 107 | BJ10: 395141 | BK10: =IF(BJ10>=BJ9,BJ10-BJ9,0) -> 262 | BL10: =J10+Q10+AL10+BC10 -> 15742.95 | BN10: =IF(BL10>0,BL10/BM9,0) -> #DIV/0! | BP10: =IF(BL10>0,BL10/BO10,0) -> #DIV/0! | BQ10: =BL10*BS1 -> 7241.757 | BR10: =IF(BQ10>0,BQ10/BM9,0) -> #DIV/0! | BS10: =IF(BQ10>0,BQ10/BO10,0) -> #DIV/0!
A11: 6 | C11: =IF(+B11-B10>0,B11-B10,(B11-B10)>0)*800 -> 0 | E11: =IF(+D11-D10>0,D11-D10,(D11-D10)>0)*80 -> 0 | G11: =IF(+F11-F10>0,F11-F10,(F11-F10)>0)*10 -> 0 | I11: 20913939 | J11: =IF(I11>=I10,I11-I10,0) -> 1827 | K11: =M11+O11 -> 1427 | L11: 642761 | M11: =IF(L11>=L10,L11-L10,0) -> 535 | N11: 629991 | O11: =IF(N11>=N10,N11-N10,0) -> 892 | P11: 210678 | Q11: =IF(P11>=P10,P11-P10,0)*30 -> 60 | R11: 702925 | S11: =IF(R11>=R10,R11-R10,0) -> 0 | T11: 344001 | U11: =IF(T11>=T10,T11-T10,0) -> 0 | V11: 90620 | W11: =IF(V11>=V10,V11-V10,0) -> 113 | X11: 168766 | Y11: =IF(X11>=X10,X11-X10,0) -> 189 | Z11: 315108 | AA11: =IF(Z11>=Z10,Z11-Z10,0)*0.53 -> 0 | AB11: 669638 | AC11: =IF(AB11>=AB10,AB11-AB10,0)*0.53 -> 992.16 | AD11: 732945 | AE11: =IF(AD11>=AD10,AD11-AD10,0)*0.53 -> 0 | AF11: 705621 | AG11: =IF(AF11>=AF10,AF11-AF10,0)*0.53 -> 0 | AH11: 201023 | AI11: =IF(AH11>=AH10,AH11-AH10,0)*0.53 -> 179.14 | AJ11: 253198 | AK11: =IF(AJ11>=AJ10,AJ11-AJ10,0)*0.53 -> 909.48 | AL11: =AA11+AC11+AE11+AG11+AI11+AK11 -> 2080.78 | AM11: 6884208 | AN11: =IF(AM11>=AM10,AM11-AM10,0) -> 47 | AO11: 536168 | AP11: =IF(AO11>=AO10,AO11-AO10,0) -> 2 | AQ11: 880641 | AR11: =IF(AQ11>=AQ10,AQ11-AQ10,0)*0.11 -> 1.87 | AS11: 781663 | AT11: =IF(AS11>=AS10,AS11-AS10,0) -> 18 | AU11: 2153432 | AV11: =IF(AU11>=AU10,AU11-AU10,0) -> 197 | AW11: 194935 | AX11: =IF(AW11>=AW10,AW11-AW10,0) -> 33 | AY11: 16712519 | AZ11: =IF(AY11>=AY10,AY11-AY10,0) -> 867 | BA11: 20220967 | BB11: =IF(BA11>=BA10,BA11-BA10,0)-(0.6*BG11)-(0.5*BI11)-BK11-BE11 -> 1578.9 | BC11: =AN11+AP11+AR11+AT11+AV11+AX11+AZ11+BB11 -> 2744.77 | BD11: 1323286 | BE11: =IF(BD11>=BD10,BD11-BD10,0) -> 0 | BF11: 3127707 | BG11: =IF(BF11>=BF10,BF11-BF10,0) -> 471 | BH11: 347246 | BI11: =IF(BH11>=BH10,BH11-BH10,0) -> 35 | BJ11: 395225 | BK11: =IF(BJ11>=BJ10,BJ11-BJ10,0) -> 84 | BL11: =J11+Q11+AL11+BC11 -> 6712.55 | BN11: =IF(BL11>0,BL11/BM10,0) -> #DIV/0! | BP11: =IF(BL11>0,BL11/BO11,0) -> #DIV/0! | BQ11: =BL11*BS1 -> 3087.773 | BR11: =IF(BQ11>0,BQ11/BM10,0) -> #DIV/0! | BS11: =IF(BQ11>0,BQ11/BO11,0) -> #DIV/0!
A12: 7 | C12: =IF(+B12-B11>0,B12-B11,(B12-B11)>0)*800 -> 0 | E12: =IF(+D12-D11>0,D12-D11,(D12-D11)>0)*80 -> 0 | G12: =IF(+F12-F11>0,F12-F11,(F12-F11)>0)*10 -> 0 | H12: 59 | I12: 20916397 | J12: =IF(I12>=I11,I12-I11,0) -> 2458 | K12: =M12+O12 -> 1967 | L12: 643637 | M12: =IF(L12>=L11,L12-L11,0) -> 876 | N12: 631082 | O12: =IF(N12>=N11,N12-N11,0) -> 1091 | P12: 210682 | Q12: =IF(P12>=P11,P12-P11,0)*30 -> 120 | R12: 702925 | S12: =IF(R12>=R11,R12-R11,0) -> 0 | T12: 344001 | U12: =IF(T12>=T11,T12-T11,0) -> 0 | V12: 90780 | W12: =IF(V12>=V11,V12-V11,0) -> 160 | X12: 169029 | Y12: =IF(X12>=X11,X12-X11,0) -> 263 | Z12: 315108 | AA12: =IF(Z12>=Z11,Z12-Z11,0)*0.53 -> 0 | AB12: 670595 | AC12: =IF(AB12>=AB11,AB12-AB11,0)*0.53 -> 507.21 | AD12: 736604 | AE12: =IF(AD12>=AD11,AD12-AD11,0)*0.53 -> 1939.27 | AF12: 705621 | AG12: =IF(AF12>=AF11,AF12-AF11,0)*0.53 -> 0 | AH12: 201849 | AI12: =IF(AH12>=AH11,AH12-AH11,0)*0.53 -> 437.78 | AJ12: 257756 | AK12: =IF(AJ12>=AJ11,AJ12-AJ11,0)*0.53 -> 2415.74 | AL12: =AA12+AC12+AE12+AG12+AI12+AK12 -> 5300 | AM12: 6884223 | AN12: =IF(AM12>=AM11,AM12-AM11,0) -> 15 | AO12: 536170 | AP12: =IF(AO12>=AO11,AO12-AO11,0) -> 2 | AQ12: 880688 | AR12: =IF(AQ12>=AQ11,AQ12-AQ11,0)*0.11 -> 5.17 | AS12: 781699 | AT12: =IF(AS12>=AS11,AS12-AS11,0) -> 36 | AU12: 2153803 | AV12: =IF(AU12>=AU11,AU12-AU11,0) -> 371 | AW12: 194979 | AX12: =IF(AW12>=AW11,AW12-AW11,0) -> 44 | AY12: 16715090 | AZ12: =IF(AY12>=AY11,AY12-AY11,0) -> 2571 | BA12: 20226350 | BB12: =IF(BA12>=BA11,BA12-BA11,0)-(0.6*BG12)-(0.5*BI12)-BK12-BE12 -> 4300.1 | BC12: =AN12+AP12+AR12+AT12+AV12+AX12+AZ12+BB12 -> 7344.27 | BD12: 1323286 | BE12: =IF(BD12>=BD11,BD12-BD11,0) -> 0 | BF12: 3129046 | BG12: =IF(BF12>=BF11,BF12-BF11,0) -> 1339 | BH12: 347341 | BI12: =IF(BH12>=BH11,BH12-BH11,0) -> 95 | BJ12: 395457 | BK12: =IF(BJ12>=BJ11,BJ12-BJ11,0) -> 232 | BL12: =J12+Q12+AL12+BC12 -> 15222.27 | BN12: =IF(BL12>0,BL12/BM11,0) -> #DIV/0! | BP12: =IF(BL12>0,BL12/BO12,0) -> #DIV/0! | BQ12: =BL12*BS1 -> 7002.2442 | BR12: =IF(BQ12>0,BQ12/BM11,0) -> #DIV/0! | BS12: =IF(BQ12>0,BQ12/BO12,0) -> #DIV/0!
A13: 8 | C13: =IF(+B13-B12>0,B13-B12,(B13-B12)>0)*800 -> 0 | E13: =IF(+D13-D12>0,D13-D12,(D13-D12)>0)*80 -> 0 | G13: =IF(+F13-F12>0,F13-F12,(F13-F12)>0)*10 -> 0 | I13: 20918501 | J13: =IF(I13>=I12,I13-I12,0) -> 2104 | K13: =M13+O13 -> 1316 | L13: 644414 | M13: =IF(L13>=L12,L13-L12,0) -> 777 | N13: 631621 | O13: =IF(N13>=N12,N13-N12,0) -> 539 | P13: 210685 | Q13: =IF(P13>=P12,P13-P12,0)*30 -> 90 | R13: 702925 | S13: =IF(R13>=R12,R13-R12,0) -> 0 | T13: 344001 | U13: =IF(T13>=T12,T13-T12,0) -> 0 | V13: 90928 | W13: =IF(V13>=V12,V13-V12,0) -> 148 | X13: 169266 | Y13: =IF(X13>=X12,X13-X12,0) -> 237 | Z13: 315108 | AA13: =IF(Z13>=Z12,Z13-Z12,0)*0.53 -> 0 | AB13: 670595 | AC13: =IF(AB13>=AB12,AB13-AB12,0)*0.53 -> 0 | AD13: 740995 | AE13: =IF(AD13>=AD12,AD13-AD12,0)*0.53 -> 2327.23 | AF13: 705621 | AG13: =IF(AF13>=AF12,AF13-AF12,0)*0.53 -> 0 | AH13: 202687 | AI13: =IF(AH13>=AH12,AH13-AH12,0)*0.53 -> 444.14 | AJ13: 262347 | AK13: =IF(AJ13>=AJ12,AJ13-AJ12,0)*0.53 -> 2433.23 | AL13: =AA13+AC13+AE13+AG13+AI13+AK13 -> 5204.6 | AM13: 6884235 | AN13: =IF(AM13>=AM12,AM13-AM12,0) -> 12 | AO13: 536173 | AP13: =IF(AO13>=AO12,AO13-AO12,0) -> 3 | AQ13: 880730 | AR13: =IF(AQ13>=AQ12,AQ13-AQ12,0)*0.11 -> 4.62 | AS13: 781730 | AT13: =IF(AS13>=AS12,AS13-AS12,0) -> 31 | AU13: 2154135 | AV13: =IF(AU13>=AU12,AU13-AU12,0) -> 332 | AW13: 195017 | AX13: =IF(AW13>=AW12,AW13-AW12,0) -> 38 | AY13: 16717305 | AZ13: =IF(AY13>=AY12,AY13-AY12,0) -> 2215 | BA13: 20231213 | BB13: =IF(BA13>=BA12,BA13-BA12,0)-(0.6*BG13)-(0.5*BI13)-BK13-BE13 -> 3896.5 | BC13: =AN13+AP13+AR13+AT13+AV13+AX13+AZ13+BB13 -> 6532.12 | BD13: 1323286 | BE13: =IF(BD13>=BD12,BD13-BD12,0) -> 0 | BF13: 3130221 | BG13: =IF(BF13>=BF12,BF13-BF12,0) -> 1175 | BH13: 347430 | BI13: =IF(BH13>=BH12,BH13-BH12,0) -> 89 | BJ13: 395674 | BK13: =IF(BJ13>=BJ12,BJ13-BJ12,0) -> 217 | BL13: =J13+Q13+AL13+BC13 -> 13930.72 | BN13: =IF(BL13>0,BL13/BM12,0) -> #DIV/0! | BP13: =IF(BL13>0,BL13/BO13,0) -> #DIV/0! | BQ13: =BL13*BS1 -> 6408.1312 | BR13: =IF(BQ13>0,BQ13/BM12,0) -> #DIV/0! | BS13: =IF(BQ13>0,BQ13/BO13,0) -> #DIV/0!
A14: 9 | C14: =IF(+B14-B13>0,B14-B13,(B14-B13)>0)*800 -> 0 | E14: =IF(+D14-D13>0,D14-D13,(D14-D13)>0)*80 -> 0 | G14: =IF(+F14-F13>0,F14-F13,(F14-F13)>0)*10 -> 0 | H14: 60 | I14: 20919463 | J14: =IF(I14>=I13,I14-I13,0) -> 962 | K14: =M14+O14 -> 981 | L14: 644997 | M14: =IF(L14>=L13,L14-L13,0) -> 583 | N14: 632019 | O14: =IF(N14>=N13,N14-N13,0) -> 398 | P14: 210686 | Q14: =IF(P14>=P13,P14-P13,0)*30 -> 30 | R14: 702925 | S14: =IF(R14>=R13,R14-R13,0) -> 0 | T14: 344001 | U14: =IF(T14>=T13,T14-T13,0) -> 0 | V14: 91001 | W14: =IF(V14>=V13,V14-V13,0) -> 73 | X14: 169383 | Y14: =IF(X14>=X13,X14-X13,0) -> 117 | Z14: 315108 | AA14: =IF(Z14>=Z13,Z14-Z13,0)*0.53 -> 0 | AB14: 670595 | AC14: =IF(AB14>=AB13,AB14-AB13,0)*0.53 -> 0 | AD14: 744200 | AE14: =IF(AD14>=AD13,AD14-AD13,0)*0.53 -> 1698.65 | AF14: 705621 | AG14: =IF(AF14>=AF13,AF14-AF13,0)*0.53 -> 0 | AH14: 203317 | AI14: =IF(AH14>=AH13,AH14-AH13,0)*0.53 -> 333.9 | AJ14: 265839 | AK14: =IF(AJ14>=AJ13,AJ14-AJ13,0)*0.53 -> 1850.76 | AL14: =AA14+AC14+AE14+AG14+AI14+AK14 -> 3883.31 | AM14: 6884241 | AN14: =IF(AM14>=AM13,AM14-AM13,0) -> 6 | AO14: 536174 | AP14: =IF(AO14>=AO13,AO14-AO13,0) -> 1 | AQ14: 880753 | AR14: =IF(AQ14>=AQ13,AQ14-AQ13,0)*0.11 -> 2.53 | AS14: 781757 | AT14: =IF(AS14>=AS13,AS14-AS13,0) -> 27 | AU14: 2154386 | AV14: =IF(AU14>=AU13,AU14-AU13,0) -> 251 | AW14: 195036 | AX14: =IF(AW14>=AW13,AW14-AW13,0) -> 19 | AY14: 16718248 | AZ14: =IF(AY14>=AY13,AY14-AY13,0) -> 943 | BA14: 20233837 | BB14: =IF(BA14>=BA13,BA14-BA13,0)-(0.6*BG14)-(0.5*BI14)-BK14-BE14 -> 2106.3 | BC14: =AN14+AP14+AR14+AT14+AV14+AX14+AZ14+BB14 -> 3355.83 | BD14: 1323286 | BE14: =IF(BD14>=BD13,BD14-BD13,0) -> 0 | BF14: 3130848 | BG14: =IF(BF14>=BF13,BF14-BF13,0) -> 627 | BH14: 347479 | BI14: =IF(BH14>=BH13,BH14-BH13,0) -> 49 | BJ14: 395791 | BK14: =IF(BJ14>=BJ13,BJ14-BJ13,0) -> 117 | BL14: =J14+Q14+AL14+BC14 -> 8231.14 | BN14: =IF(BL14>0,BL14/BM13,0) -> #DIV/0! | BP14: =IF(BL14>0,BL14/BO14,0) -> #DIV/0! | BQ14: =BL14*BS1 -> 3786.3244 | BR14: =IF(BQ14>0,BQ14/BM13,0) -> #DIV/0! | BS14: =IF(BQ14>0,BQ14/BO14,0) -> #DIV/0!
A15: 10 | C15: =IF(+B15-B14>0,B15-B14,(B15-B14)>0)*800 -> 0 | E15: =IF(+D15-D14>0,D15-D14,(D15-D14)>0)*80 -> 0 | G15: =IF(+F15-F14>0,F15-F14,(F15-F14)>0)*10 -> 0 | I15: 20921964 | J15: =IF(I15>=I14,I15-I14,0) -> 2501 | K15: =M15+O15 -> 1330 | L15: 645807 | M15: =IF(L15>=L14,L15-L14,0) -> 810 | N15: 632539 | O15: =IF(N15>=N14,N15-N14,0) -> 520 | P15: 210689 | Q15: =IF(P15>=P14,P15-P14,0)*30 -> 90 | R15: 702925 | S15: =IF(R15>=R14,R15-R14,0) -> 0 | T15: 344001 | U15: =IF(T15>=T14,T15-T14,0) -> 0 | V15: 91190 | W15: =IF(V15>=V14,V15-V14,0) -> 189 | X15: 169551 | Y15: =IF(X15>=X14,X15-X14,0) -> 168 | Z15: 315108 | AA15: =IF(Z15>=Z14,Z15-Z14,0)*0.53 -> 0 | AB15: 670595 | AC15: =IF(AB15>=AB14,AB15-AB14,0)*0.53 -> 0 | AD15: 744880 | AE15: =IF(AD15>=AD14,AD15-AD14,0)*0.53 -> 360.4 | AF15: 706616 | AG15: =IF(AF15>=AF14,AF15-AF14,0)*0.53 -> 527.35 | AH15: 203599 | AI15: =IF(AH15>=AH14,AH15-AH14,0)*0.53 -> 149.46 | AJ15: 269564 | AK15: =IF(AJ15>=AJ14,AJ15-AJ14,0)*0.53 -> 1974.25 | AL15: =AA15+AC15+AE15+AG15+AI15+AK15 -> 3011.46 | AM15: 6884256 | AN15: =IF(AM15>=AM14,AM15-AM14,0) -> 15 | AO15: 536177 | AP15: =IF(AO15>=AO14,AO15-AO14,0) -> 3 | AQ15: 880810 | AR15: =IF(AQ15>=AQ14,AQ15-AQ14,0)*0.11 -> 6.27 | AS15: 781798 | AT15: =IF(AS15>=AS14,AS15-AS14,0) -> 41 | AU15: 2154729 | AV15: =IF(AU15>=AU14,AU15-AU14,0) -> 343 | AW15: 195079 | AX15: =IF(AW15>=AW14,AW15-AW14,0) -> 43 | AY15: 16720444 | AZ15: =IF(AY15>=AY14,AY15-AY14,0) -> 2196 | BA15: 20239834 | BB15: =IF(BA15>=BA14,BA15-BA14,0)-(0.6*BG15)-(0.5*BI15)-BK15-BE15 -> 4842.5 | BC15: =AN15+AP15+AR15+AT15+AV15+AX15+AZ15+BB15 -> 7489.77 | BD15: 1323286 | BE15: =IF(BD15>=BD14,BD15-BD14,0) -> 0 | BF15: 3132223 | BG15: =IF(BF15>=BF14,BF15-BF14,0) -> 1375 | BH15: 347590 | BI15: =IF(BH15>=BH14,BH15-BH14,0) -> 111 | BJ15: 396065 | BK15: =IF(BJ15>=BJ14,BJ15-BJ14,0) -> 274 | BL15: =J15+Q15+AL15+BC15 -> 13092.23 | BN15: =IF(BL15>0,BL15/BM14,0) -> #DIV/0! | BP15: =IF(BL15>0,BL15/BO15,0) -> #DIV/0! | BQ15: =BL15*BS1 -> 6022.4258 | BR15: =IF(BQ15>0,BQ15/BM14,0) -> #DIV/0! | BS15: =IF(BQ15>0,BQ15/BO15,0) -> #DIV/0!
A16: 11 | C16: =IF(+B16-B15>0,B16-B15,(B16-B15)>0)*800 -> 0 | E16: =IF(+D16-D15>0,D16-D15,(D16-D15)>0)*80 -> 0 | G16: =IF(+F16-F15>0,F16-F15,(F16-F15)>0)*10 -> 0 | H16: 61 | I16: 20923331 | J16: =IF(I16>=I15,I16-I15,0) -> 1367 | K16: =M16+O16 -> 911 | L16: 646356 | M16: =IF(L16>=L15,L16-L15,0) -> 549 | N16: 632901 | O16: =IF(N16>=N15,N16-N15,0) -> 362 | P16: 210691 | Q16: =IF(P16>=P15,P16-P15,0)*30 -> 60 | R16: 702925 | S16: =IF(R16>=R15,R16-R15,0) -> 0 | T16: 344001 | U16: =IF(T20>=T15,T20-T15,0) -> 0 | V16: 91289 | W16: =IF(V16>=V15,V16-V15,0) -> 99 | X16: 169843 | Y16: =IF(X16>=X15,X16-X15,0) -> 292 | Z16: 315108 | AA16: =IF(Z16>=Z15,Z16-Z15,0)*0.53 -> 0 | AB16: 671730 | AC16: =IF(AB16>=AB15,AB16-AB15,0)*0.53 -> 601.55 | AD16: 746750 | AE16: =IF(AD16>=AD15,AD16-AD15,0)*0.53 -> 991.1 | AF16: 706616 | AG16: =IF(AF16>=AF15,AF16-AF15,0)*0.53 -> 0 | AH16: 204042 | AI16: =IF(AH16>=AH15,AH16-AH15,0)*0.53 -> 234.79 | AJ16: 272783 | AK16: =IF(AJ16>=AJ15,AJ16-AJ15,0)*0.53 -> 1706.07 | AL16: =AA16+AC16+AE16+AG16+AI16+AK16 -> 3533.51 | AM16: 6884264 | AN16: =IF(AM16>=AM15,AM16-AM15,0) -> 8 | AO16: 536179 | AP16: =IF(AO16>=AO15,AO16-AO15,0) -> 2 | AQ16: 880839 | AR16: =IF(AQ16>=AQ15,AQ16-AQ15,0)*0.11 -> 3.19 | AS16: 781829 | AT16: =IF(AS16>=AS15,AS16-AS15,0) -> 31 | AU16: 2154950 | AV16: =IF(AU16>=AU15,AU16-AU15,0) -> 221 | AW16: 195100 | AX16: =IF(AW16>=AW15,AW16-AW15,0) -> 21 | AY16: 16721641 | AZ16: =IF(AY16>=AY15,AY16-AY15,0) -> 1197 | BA16: 20243059 | BB16: =IF(BA16>=BA15,BA16-BA15,0)-(0.6*BG16)-(0.5*BI16)-BK16-BE16 -> 2570.6 | BC16: =AN16+AP16+AR16+AT16+AV16+AX16+AZ16+BB16 -> 4053.79 | BD16: 1323286 | BE16: =IF(BD16>=BD15,BD16-BD15,0) -> 0 | BF16: 3133012 | BG16: =IF(BF16>=BF15,BF16-BF15,0) -> 789 | BH16: 347652 | BI16: =IF(BH16>=BH15,BH16-BH15,0) -> 62 | BJ16: 396215 | BK16: =IF(BJ16>=BJ15,BJ16-BJ15,0) -> 150 | BL16: =J16+Q16+AL16+BC16 -> 9014.3 | BN16: =IF(BL16>0,BL16/BM15,0) -> #DIV/0! | BP16: =IF(BL16>0,BL16/BO16,0) -> #DIV/0! | BQ16: =BL16*BS1 -> 4146.578 | BR16: =IF(BQ16>0,BQ16/BM15,0) -> #DIV/0! | BS16: =IF(BQ16>0,BQ16/BO16,0) -> #DIV/0!
A17: 12 | C17: =IF(+B17-B16>0,B17-B16,(B17-B16)>0)*800 -> 0 | E17: =IF(+D17-D16>0,D17-D16,(D17-D16)>0)*80 -> 0 | G17: =IF(+F17-F16>0,F17-F16,(F17-F16)>0)*10 -> 0 | I17: 20924883 | J17: =IF(I17>=I16,I17-I16,0) -> 1552 | K17: =M17+O17 -> 1122 | L17: 647009 | M17: =IF(L17>=L16,L17-L16,0) -> 653 | N17: 633370 | O17: =IF(N17>=N16,N17-N16,0) -> 469 | P17: 210693 | Q17: =IF(P17>=P16,P17-P16,0)*30 -> 60 | R17: 702925 | S17: =IF(R17>=R16,R17-R16,0) -> 0 | T17: 344001 | U17: =IF(T17>=T20,T17-T20,0) -> 0 | V17: 91388 | W17: =IF(V17>=V16,V17-V16,0) -> 99 | X17: 170001 | Y17: =IF(X17>=X16,X17-X16,0) -> 158 | Z17: 315108 | AA17: =IF(Z17>=Z16,Z17-Z16,0)*0.53 -> 0 | AB17: 671730 | AC17: =IF(AB17>=AB16,AB17-AB16,0)*0.53 -> 0 | AD17: 750552 | AE17: =IF(AD17>=AD16,AD17-AD16,0)*0.53 -> 2015.06 | AF17: 706616 | AG17: =IF(AF17>=AF16,AF17-AF16,0)*0.53 -> 0 | AH17: 204766 | AI17: =IF(AH17>=AH16,AH17-AH16,0)*0.53 -> 383.72 | AJ17: 276673 | AK17: =IF(AJ17>=AJ16,AJ17-AJ16,0)*0.53 -> 2061.7 | AL17: =AA17+AC17+AE17+AG17+AI17+AK17 -> 4460.48 | AM17: 6884272 | AN17: =IF(AM17>=AM16,AM17-AM16,0) -> 8 | AO17: 536180 | AP17: =IF(AO17>=AO16,AO17-AO16,0) -> 1 | AQ17: 880868 | AR17: =IF(AQ17>=AQ16,AQ17-AQ16,0)*0.11 -> 3.19 | AS17: 781851 | AT17: =IF(AS17>=AS16,AS17-AS16,0) -> 22 | AU17: 2155233 | AV17: =IF(AU17>=AU16,AU17-AU16,0) -> 283 | AW17: 195115 | AX17: =IF(AW17>=AW16,AW17-AW16,0) -> 15 | AY17: 16722828 | AZ17: =IF(AY17>=AY16,AY17-AY16,0) -> 1187 | BA17: 20246329 | BB17: =IF(BA17>=BA16,BA17-BA16,0)-(0.6*BG17)-(0.5*BI17)-BK17-BE17 -> 2641.7 | BC17: =AN17+AP17+AR17+AT17+AV17+AX17+AZ17+BB17 -> 4160.89 | BD17: 1323286 | BE17: =IF(BD17>=BF16,BD17-BF16,0) -> 0 | BF17: 3133745 | BG17: =IF(BF17>=BF16,BF17-BF16,0) -> 733 | BH17: 347715 | BI17: =IF(BH17>=BH16,BH17-BH16,0) -> 63 | BJ17: 396372 | BK17: =IF(BJ17>=BJ16,BJ17-BJ16,0) -> 157 | BL17: =J17+Q17+AL17+BC17 -> 10233.37 | BN17: =IF(BL17>0,BL17/BM16,0) -> #DIV/0! | BP17: =IF(BL17>0,BL17/BO17,0) -> #DIV/0! | BQ17: =BL17*BS1 -> 4707.3502 | BR17: =IF(BQ17>0,BQ17/BM16,0) -> #DIV/0! | BS17: =IF(BQ17>0,BQ17/BO17,0) -> #DIV/0!
A18: 13 | C18: =IF(+B18-B17>0,B18-B17,(B18-B17)>0)*800 -> 0 | E18: =IF(+D18-D17>0,D18-D17,(D18-D17)>0)*80 -> 0 | G18: =IF(+F18-F17>0,F18-F17,(F18-F17)>0)*10 -> 0 | H18: 62 | I18: 20926872 | J18: =IF(I18>=I17,I18-I17,0) -> 1989 | K18: =M18+O18 -> 1336 | L18: 647634 | M18: =IF(L18>=L17,L18-L17,0) -> 625 | N18: 634081 | O18: =IF(N18>=N17,N18-N17,0) -> 711 | P18: 210694 | Q18: =IF(P18>=P17,P18-P17,0)*30 -> 30 | R18: 702925 | S18: =IF(R18>=R17,R18-R17,0) -> 0 | T18: 344001 | U18: =IF(T18>=T17,T18-T17,0) -> 0 | V18: 91524 | W18: =IF(V18>=V17,V18-V17,0) -> 136 | X18: 170218 | Y18: =IF(X18>=X17,X18-X17,0) -> 217 | Z18: 315108 | AA18: =IF(Z18>=Z17,Z18-Z17,0)*0.53 -> 0 | AB18: 671730 | AC18: =IF(AB18>=AB17,AB18-AB17,0)*0.53 -> 0 | AD18: 751601 | AE18: =IF(AD18>=AD17,AD18-AD17,0)*0.53 -> 555.97 | AF18: 708341 | AG18: =IF(AF18>=AF17,AF18-AF17,0)*0.53 -> 914.25 | AH18: 205196 | AI18: =IF(AH18>=AH17,AH18-AH17,0)*0.53 -> 227.9 | AJ18: 279154 | AK18: =IF(AJ18>=AJ17,AJ18-AJ17,0)*0.53 -> 1314.93 | AL18: =AA18+AC18+AE18+AG18+AI18+AK18 -> 3013.05 | AM18: 6884283 | AN18: =IF(AM18>=AM17,AM18-AM17,0) -> 11 | AO18: 536182 | AP18: =IF(AO18>=AO17,AO18-AO17,0) -> 2 | AQ18: 880901 | AR18: =IF(AQ18>=AQ17,AQ18-AQ17,0)*0.11 -> 3.63 | AS18: 781880 | AT18: =IF(AS18>=AS17,AS18-AS17,0) -> 29 | AU18: 2155531 | AV18: =IF(AU18>=AU17,AU18-AU17,0) -> 298 | AW18: 195115 | AX18: =IF(AW18>=AW17,AW18-AW17,0) -> 0 | AY18: 16724851 | AZ18: =IF(AY18>=AY17,AY18-AY17,0) -> 2023 | BA18: 20250503 | BB18: =IF(BA18>=BA17,BA18-BA17,0)-(0.6*BG18)-(0.5*BI18)-BK18-BE18 -> 3427.4 | BC18: =AN18+AP18+AR18+AT18+AV18+AX18+AZ18+BB18 -> 5794.03 | BD18: 1323286 | BE18: =IF(BD18>=BD17,BD18-BD17,0) -> 0 | BF18: 3134561 | BG18: =IF(BF18>=BF17,BF18-BF17,0) -> 816 | BH18: 347805 | BI18: =IF(BH18>=BH17,BH18-BH17,0) -> 90 | BJ18: 396584 | BK18: =IF(BJ18>=BJ17,BJ18-BJ17,0) -> 212 | BL18: =J18+Q18+AL18+BC18 -> 10826.08 | BN18: =IF(BL18>0,BL18/BM17,0) -> #DIV/0! | BP18: =IF(BL18>0,BL18/BO18,0) -> #DIV/0! | BQ18: =BL18*BS1 -> 4979.9968 | BR18: =IF(BQ18>0,BQ18/BM17,0) -> #DIV/0! | BS18: =IF(BQ18>0,BQ18/BO18,0) -> #DIV/0!
A19: 14 | C19: =IF(+B19-B18>0,B19-B18,(B19-B18)>0)*800 -> 0 | E19: =IF(+D19-D18>0,D19-D18,(D19-D18)>0)*80 -> 0 | G19: =IF(+F19-F18>0,F19-F18,(F19-F18)>0)*10 -> 0 | I19: 20928953 | J19: =IF(I19>=I18,I19-I18,0) -> 2081 | K19: =M19+O19 -> 1361 | L19: 648360 | M19: =IF(L19>=L18,L19-L18,0) -> 726 | N19: 634716 | O19: =IF(N19>=N18,N19-N18,0) -> 635 | P19: 210695 | Q19: =IF(P19>=P18,P19-P18,0)*30 -> 30 | R19: 702925 | S19: =IF(R19>=R18,R19-R18,0) -> 0 | T19: 344001 | U19: =IF(T19>=T18,T19-T18,0) -> 0 | V19: 91661 | W19: =IF(V19>=V18,V19-V18,0) -> 137 | X19: 170439 | Y19: =IF(X19>=X18,X19-X18,0) -> 221 | Z19: 315108 | AA19: =IF(Z19>=Z18,Z19-Z18,0)*0.53 -> 0 | AB19: 671730 | AC19: =IF(AB19>=AB18,AB19-AB18,0)*0.53 -> 0 | AD19: 752723 | AE19: =IF(AD19>=AD18,AD19-AD18,0)*0.53 -> 594.66 | AF19: 710269 | AG19: =IF(AF19>=AF18,AF19-AF18,0)*0.53 -> 1021.84 | AH19: 205548 | AI19: =IF(AH19>=AH18,AH19-AH18,0)*0.53 -> 186.56 | AJ19: 283464 | AK19: =IF(AJ19>=AJ18,AJ19-AJ18,0)*0.53 -> 2284.3 | AL19: =AA19+AC19+AE19+AG19+AI19+AK19 -> 4087.36 | AM19: 6884293 | AN19: =IF(AM19>=AM18,AM19-AM18,0) -> 10 | AO19: 536183 | AP19: =IF(AO19>=AO18,AO19-AO18,0) -> 1 | AQ19: 880948 | AR19: =IF(AQ19>=AQ18,AQ19-AQ18,0)*0.11 -> 5.17 | AS19: 781916 | AT19: =IF(AS19>=AS18,AS19-AS18,0) -> 36 | AU19: 2155832 | AV19: =IF(AU19>=AU18,AU19-AU18,0) -> 301 | AW19: 195116 | AX19: =IF(AW19>=AW18,AW19-AW18,0) -> 1 | AY19: 16726874 | AZ19: =IF(AY19>=AY18,AY19-AY18,0) -> 2023 | BA19: 20254893 | BB19: =IF(BA19>=BA18,BA19-BA18,0)-(0.6*BG19)-(0.5*BI19)-BK19-BE19 -> 3524.3 | BC19: =AN19+AP19+AR19+AT19+AV19+AX19+AZ19+BB19 -> 5901.47 | BD19: 1323286 | BE19: =IF(BD19>=BD18,BD19-BD18,0) -> 0 | BF19: 3135623 | BG19: =IF(BF19>=BF18,BF19-BF18,0) -> 1062 | BH19: 347882 | BI19: =IF(BH19>=BH18,BH19-BH18,0) -> 77 | BJ19: 396774 | BK19: =IF(BJ19>=BJ18,BJ19-BJ18,0) -> 190 | BL19: =J19+Q19+AL19+BC19 -> 12099.83 | BN19: =IF(BL19>0,BL19/BM18,0) -> #DIV/0! | BP19: =IF(BL19>0,BL19/BO19,0) -> #DIV/0! | BQ19: =BL19*BS1 -> 5565.9218 | BR19: =IF(BQ19>0,BQ19/BM18,0) -> #DIV/0! | BS19: =IF(BQ19>0,BQ19/BO19,0) -> #DIV/0!
A20: 15 | C20: =IF(+B20-B19>0,B20-B19,(B20-B19)>0)*800 -> 0 | E20: =IF(+D20-D19>0,D20-D19,(D20-D19)>0)*80 -> 0 | G20: =IF(+F20-F19>0,F20-F19,(F20-F19)>0)*10 -> 0 | H20: 63 | I20: 20930749 | J20: =IF(I20>=I19,I20-I19,0) -> 1796 | K20: =M20+O20 -> 1328 | L20: 648989 | M20: =IF(L20>=L19,L20-L19,0) -> 629 | N20: 635415 | O20: =IF(N20>=N19,N20-N19,0) -> 699 | P20: 210697 | Q20: =IF(P20>=P19,P20-P19,0)*30 -> 60 | R20: 702925 | S20: =IF(R20>=R19,R20-R19,0) -> 0 | T20: 344001 | U20: =IF(T20>=T19,T20-T19,0) -> 0 | V20: 91776 | W20: =IF(V20>=V19,V20-V19,0) -> 115 | X20: 170637 | Y20: =IF(X20>=X19,X20-X19,0) -> 198 | Z20: 315108 | AA20: =IF(Z20>=Z19,Z20-Z19,0)*0.53 -> 0 | AB20: 671730 | AC20: =IF(AB20>=AB19,AB20-AB19,0)*0.53 -> 0 | AD20: 752791 | AE20: =IF(AD20>=AD19,AD20-AD19,0)*0.53 -> 36.04 | AF20: 713327 | AG20: =IF(AF20>=AF19,AF20-AF19,0)*0.53 -> 1620.74 | AH20: 205989 | AI20: =IF(AH20>=AH19,AH20-AH19,0)*0.53 -> 233.73 | AJ20: 286921 | AK20: =IF(AJ20>=AJ19,AJ20-AJ19,0)*0.53 -> 1832.21 | AL20: =AA20+AC20+AE20+AG20+AI20+AK20 -> 3722.72 | AM20: 6884303 | AN20: =IF(AM20>=AM19,AM20-AM19,0) -> 10 | AO20: 536185 | AP20: =IF(AO20>=AO19,AO20-AO19,0) -> 2 | AQ20: 880981 | AR20: =IF(AQ20>=AQ19,AQ20-AQ19,0)*0.11 -> 3.63 | AS20: 781945 | AT20: =IF(AS20>=AS19,AS20-AS19,0) -> 29 | AU20: 2156132 | AV20: =IF(AU20>=AU19,AU20-AU19,0) -> 300 | AW20: 195116 | AX20: =IF(AW20>=AW19,AW20-AW19,0) -> 0 | AY20: 16728500 | AZ20: =IF(AY20>=AY19,AY20-AY19,0) -> 1626 | BA20: 20258705 | BB20: =IF(BA20>=BA19,BA20-BA19,0)-(0.6*BG20)-(0.5*BI20)-BK20-BE20 -> 3008.6 | BC20: =AN20+AP20+AR20+AT20+AV20+AX20+AZ20+BB20 -> 4979.23 | BD20: 1323286 | BE20: =IF(BD20>=BD19,BD20-BD19,0) -> 0 | BF20: 3136612 | BG20: =IF(BF20>=BF19,BF20-BF19,0) -> 989 | BH20: 347956 | BI20: =IF(BH20>=BH19,BH20-BH19,0) -> 74 | BJ20: 396947 | BK20: =IF(BJ20>=BJ19,BJ20-BJ19,0) -> 173 | BL20: =J20+Q20+AL20+BC20 -> 10557.95 | BN20: =IF(BL20>0,BL20/BM20,0) -> #DIV/0! | BP20: =IF(BL20>0,BL20/BO20,0) -> #DIV/0! | BQ20: =BL20*BS1 -> 4856.657 | BR20: =IF(BQ20>0,BQ20/BM20,0) -> #DIV/0! | BS20: =IF(BQ20>0,BQ20/BO20,0) -> #DIV/0!
A21: 16 | C21: =IF(+B21-B20>0,B21-B20,(B21-B20)>0)*800 -> 0 | E21: =IF(+D21-D20>0,D21-D20,(D21-D20)>0)*80 -> 0 | G21: =IF(+F21-F20>0,F21-F20,(F21-F20)>0)*10 -> 0 | I21: 20932550 | J21: =IF(I21>=I20,I21-I20,0) -> 1801 | K21: =M21+O21 -> 1379 | L21: 649619 | M21: =IF(L21>=L20,L21-L20,0) -> 630 | N21: 636164 | O21: =IF(N21>=N20,N21-N20,0) -> 749 | P21: 210700 | Q21: =IF(P21>=P20,P21-P20,0)*30 -> 90 | R21: 702925 | S21: =IF(R21>=R20,R21-R20,0) -> 0 | T21: 344001 | U21: =IF(T21>=T20,T21-T20,0) -> 0 | V21: 91884 | W21: =IF(V21>=V20,V21-V20,0) -> 108 | X21: 170825 | Y21: =IF(X21>=X20,X21-X20,0) -> 188 | Z21: 315108 | AA21: =IF(Z21>=Z20,Z21-Z20,0)*0.53 -> 0 | AB21: 671730 | AC21: =IF(AB21>=AB20,AB21-AB20,0)*0.53 -> 0 | AD21: 757497 | AE21: =IF(AD21>=AD20,AD21-AD20,0)*0.53 -> 2494.18 | AF21: 713327 | AG21: =IF(AF21>=AF20,AF21-AF20,0)*0.53 -> 0 | AH21: 206711 | AI21: =IF(AH21>=AH20,AH21-AH20,0)*0.53 -> 382.66 | AJ21: 291110 | AK21: =IF(AJ21>=AJ20,AJ21-AJ20,0)*0.53 -> 2220.17 | AL21: =AA21+AC21+AE21+AG21+AI21+AK21 -> 5097.01 | AM21: 6884318 | AN21: =IF(AM21>=AM20,AM21-AM20,0) -> 15 | AO21: 536187 | AP21: =IF(AO21>=AO20,AO21-AO20,0) -> 2 | AQ21: 881016 | AR21: =IF(AQ21>=AQ20,AQ21-AQ20,0)*0.11 -> 3.85 | AS21: 781973 | AT21: =IF(AS21>=AS20,AS21-AS20,0) -> 28 | AU21: 2156460 | AV21: =IF(AU21>=AU20,AU21-AU20,0) -> 328 | AW21: 195116 | AX21: =IF(AW21>=AW20,AW21-AW20,0) -> 0 | AY21: 16730236 | AZ21: =IF(AY21>=AY20,AY21-AY20,0) -> 1736 | BA21: 20262750 | BB21: =IF(BA21>=BA20,BA21-BA20,0)-(0.6*BG21)-(0.5*BI21)-BK21-BE21 -> 3192.1 | BC21: =AN21+AP21+AR21+AT21+AV21+AX21+AZ21+BB21 -> 5304.95 | BD21: 1323286 | BE21: =IF(BD21>=BD20,BD21-BD20,0) -> 0 | BF21: 3137666 | BG21: =IF(BF21>=BF20,BF21-BF20,0) -> 1054 | BH21: 348029 | BI21: =IF(BH21>=BH20,BH21-BH20,0) -> 73 | BJ21: 397131 | BK21: =IF(BJ21>=BJ20,BJ21-BJ20,0) -> 184 | BL21: =J21+Q21+AL21+BC21 -> 12292.96 | BN21: =IF(BL21>0,BL21/BM21,0) -> #DIV/0! | BP21: =IF(BL21>0,BL21/BO21,0) -> #DIV/0! | BQ21: =BL21*BS1 -> 5654.7616 | BR21: =IF(BQ21>0,BQ21/BM21,0) -> #DIV/0! | BS21: =IF(BQ21>0,BQ21/BO21,0) -> #DIV/0!
A22: 17 | C22: =IF(+B22-B21>0,B22-B21,(B22-B21)>0)*800 -> 0 | E22: =IF(+D22-D21>0,D22-D21,(D22-D21)>0)*80 -> 0 | G22: =IF(+F22-F21>0,F22-F21,(F22-F21)>0)*10 -> 0 | H22: 64 | I22: 20935088 | J22: =IF(I22>=I21,I22-I21,0) -> 2538 | K22: =M22+O22 -> 967 | L22: 650171 | M22: =IF(L22>=L21,L22-L21,0) -> 552 | N22: 636579 | O22: =IF(N22>=N21,N22-N21,0) -> 415 | P22: 210704 | Q22: =IF(P22>=P21,P22-P21,0)*30 -> 120 | R22: 702925 | S22: =IF(R22>=R21,R22-R21,0) -> 0 | T22: 344001 | U22: =IF(T22>=T21,T22-T21,0) -> 0 | V22: 92015 | W22: =IF(V22>=V21,V22-V21,0) -> 131 | X22: 171046 | Y22: =IF(X22>=X21,X22-X21,0) -> 221 | Z22: 315108 | AA22: =IF(Z22>=Z21,Z22-Z21,0)*0.53 -> 0 | AB22: 671730 | AC22: =IF(AB22>=AB21,AB22-AB21,0)*0.53 -> 0 | AD22: 762245 | AE22: =IF(AD22>=AD21,AD22-AD21,0)*0.53 -> 2516.44 | AF22: 714945 | AG22: =IF(AF22>=AF21,AF22-AF21,0)*0.53 -> 857.54 | AH22: 207229 | AI22: =IF(AH22>=AH21,AH22-AH21,0)*0.53 -> 274.54 | AJ22: 295198 | AK22: =IF(AJ22>=AJ21,AJ22-AJ21,0)*0.53 -> 2166.64 | AL22: =AA22+AC22+AE22+AG22+AI22+AK22 -> 5815.16 | AM22: 6884330 | AN22: =IF(AM22>=AM21,AM22-AM21,0) -> 12 | AO22: 536189 | AP22: =IF(AO22>=AO21,AO22-AO21,0) -> 2 | AQ22: 881040 | AR22: =IF(AQ22>=AQ21,AQ22-AQ21,0)*0.11 -> 2.64 | AS22: 782007 | AT22: =IF(AS22>=AS21,AS22-AS21,0) -> 34 | AU22: 2156808 | AV22: =IF(AU22>=AU21,AU22-AU21,0) -> 348 | AW22: 195116 | AX22: =IF(AW22>=AW21,AW22-AW21,0) -> 0 | AY22: 16732117 | AZ22: =IF(AY22>=AY21,AY22-AY21,0) -> 1881 | BA22: 20268022 | BB22: =IF(BA22>=BA21,BA22-BA21,0)-(0.6*BG22)-(0.5*BI22)-BK22-BE22 -> 4227.5 | BC22: =AN22+AP22+AR22+AT22+AV22+AX22+AZ22+BB22 -> 6507.14 | BD22: 1323286 | BE22: =IF(BD22>=BD21,BD22-BD21,0) -> 0 | BF22: 3139046 | BG22: =IF(BF22>=BF21,BF22-BF21,0) -> 1380 | BH22: 348112 | BI22: =IF(BH22>=BH21,BH22-BH21,0) -> 83 | BJ22: 397306 | BK22: =IF(BJ22>=BJ21,BJ22-BJ21,0) -> 175 | BL22: =J22+Q22+AL22+BC22 -> 14980.3 | BN22: =IF(BL22>0,BL22/BM22,0) -> #DIV/0! | BP22: =IF(BL22>0,BL22/BO22,0) -> #DIV/0! | BQ22: =BL22*BS1 -> 6890.938 | BR22: =IF(BQ22>0,BQ22/BM22,0) -> #DIV/0! | BS22: =IF(BQ22>0,BQ22/BO22,0) -> #DIV/0!
A23: 18 | C23: =IF(+B23-B22>0,B23-B22,(B23-B22)>0)*800 -> 0 | E23: =IF(+D23-D22>0,D23-D22,(D23-D22)>0)*80 -> 0 | G23: =IF(+F23-F22>0,F23-F22,(F23-F22)>0)*10 -> 0 | I23: 20936488 | J23: =IF(I23>=I22,I23-I22,0) -> 1400 | K23: =M23+O23 -> 1300 | L23: 650871 | M23: =IF(L23>=L22,L23-L22,0) -> 700 | N23: 637179 | O23: =IF(N23>=N22,N23-N22,0) -> 600 | P23: 210707 | Q23: =IF(P23>=P22,P23-P22,0)*30 -> 90 | R23: 702925 | S23: =IF(R23>=R22,R23-R22,0) -> 0 | T23: 344001 | U23: =IF(T23>=T22,T23-T22,0) -> 0 | V23: 92148 | W23: =IF(V23>=V22,V23-V22,0) -> 133 | X23: 171246 | Y23: =IF(X23>=X22,X23-X22,0) -> 200 | Z23: 315108 | AA23: =IF(Z23>=Z22,Z23-Z22,0)*0.53 -> 0 | AB23: 671730 | AC23: =IF(AB23>=AB22,AB23-AB22,0)*0.53 -> 0 | AD23: 762245 | AE23: =IF(AD23>=AD22,AD23-AD22,0)*0.53 -> 0 | AF23: 714945 | AG23: =IF(AF23>=AF22,AF23-AF22,0)*0.53 -> 0 | AH23: 207829 | AI23: =IF(AH23>=AH22,AH23-AH22,0)*0.53 -> 318 | AJ23: 298598 | AK23: =IF(AJ23>=AJ22,AJ23-AJ22,0)*0.53 -> 1802 | AL23: =AA23+AC23+AE23+AG23+AI23+AK23 -> 2120 | AM23: 6884338 | AN23: =IF(AM23>=AM22,AM23-AM22,0) -> 8 | AO23: 536191 | AP23: =IF(AO23>=AO22,AO23-AO22,0) -> 2 | AQ23: 881091 | AR23: =IF(AQ23>=AQ22,AQ23-AQ22,0)*0.11 -> 5.61 | AS23: 782037 | AT23: =IF(AS23>=AS22,AS23-AS22,0) -> 30 | AU23: 2157068 | AV23: =IF(AU23>=AU22,AU23-AU22,0) -> 260 | AW23: 195116 | AX23: =IF(AW23>=AW22,AW23-AW22,0) -> 0 | AY23: 16733717 | AZ23: =IF(AY23>=AY22,AY23-AY22,0) -> 1600 | BA23: 20271022 | BB23: =IF(BA23>=BA22,BA23-BA22,0)-(0.6*BG23)-(0.5*BI23)-BK23-BE23 -> 2285 | BC23: =AN23+AP23+AR23+AT23+AV23+AX23+AZ23+BB23 -> 4190.61 | BD23: 1323286 | BE23: =IF(BD23>=BD22,BD23-BD22,0) -> 0 | BF23: 3139846 | BG23: =IF(BF23>=BF22,BF23-BF22,0) -> 800 | BH23: 348182 | BI23: =IF(BH23>=BH22,BH23-BH22,0) -> 70 | BJ23: 397506 | BK23: =IF(BJ23>=BJ22,BJ23-BJ22,0) -> 200 | BL23: =J23+Q23+AL23+BC23 -> 7800.61 | BN23: =IF(BL23>0,BL23/BM23,0) -> #DIV/0! | BP23: =IF(BL23>0,BL23/BO23,0) -> #DIV/0! | BQ23: =BL23*BS1 -> 3588.2806 | BR23: =IF(BQ23>0,BQ23/BM23,0) -> #DIV/0! | BS23: =IF(BQ23>0,BQ23/BO23,0) -> #DIV/0!
A24: 19 | C24: =IF(+B24-B23>0,B24-B23,(B24-B23)>0)*800 -> 0 | E24: =IF(+D24-D23>0,D24-D23,(D24-D23)>0)*80 -> 0 | G24: =IF(+F24-F23>0,F24-F23,(F24-F23)>0)*10 -> 0 | H24: 65 | I24: 20938357 | J24: =IF(I24>=I23,I24-I23,0) -> 1869 | K24: =M24+O24 -> 1475 | L24: 651613 | M24: =IF(L24>=L23,L24-L23,0) -> 742 | N24: 637912 | O24: =IF(N24>=N23,N24-N23,0) -> 733 | P24: 210710 | Q24: =IF(P24>=P23,P24-P23,0)*30 -> 90 | R24: 702925 | S24: =IF(R24>=R23,R24-R23,0) -> 0 | T24: 344001 | U24: =IF(T24>=T23,T24-T23,0) -> 0 | V24: 92270 | W24: =IF(V24>=V23,V24-V23,0) -> 122 | X24: 171447 | Y24: =IF(X24>=X23,X24-X23,0) -> 201 | Z24: 315108 | AA24: =IF(Z24>=Z23,Z24-Z23,0)*0.53 -> 0 | AB24: 671730 | AC24: =IF(AB24>=AB23,AB24-AB23,0)*0.53 -> 0 | AD24: 767090 | AE24: =IF(AD24>=AD23,AD24-AD23,0)*0.53 -> 2567.85 | AF24: 714945 | AG24: =IF(AF24>=AF23,AF24-AF23,0)*0.53 -> 0 | AH24: 208707 | AI24: =IF(AH24>=AH23,AH24-AH23,0)*0.53 -> 465.34 | AJ24: 303488 | AK24: =IF(AJ24>=AJ23,AJ24-AJ23,0)*0.53 -> 2591.7 | AL24: =AA24+AC24+AE24+AG24+AI24+AK24 -> 5624.89 | AM24: 6884359 | AN24: =IF(AM24>=AM23,AM24-AM23,0) -> 21 | AO24: 536194 | AP24: =IF(AO24>=AO23,AO24-AO23,0) -> 3 | AQ24: 881128 | AR24: =IF(AQ24>=AQ23,AQ24-AQ23,0)*0.11 -> 4.07 | AS24: 782069 | AT24: =IF(AS24>=AS23,AS24-AS23,0) -> 32 | AU24: 2157447 | AV24: =IF(AU24>=AU23,AU24-AU23,0) -> 379 | AW24: 195116 | AX24: =IF(AW24>=AW23,AW24-AW23,0) -> 0 | AY24: 16735590 | AZ24: =IF(AY24>=AY23,AY24-AY23,0) -> 1873 | BA24: 20275231 | BB24: =IF(BA24>=BA23,BA24-BA23,0)-(0.6*BG24)-(0.5*BI24)-BK24-BE24 -> 3299.8 | BC24: =AN24+AP24+AR24+AT24+AV24+AX24+AZ24+BB24 -> 5611.87 | BD24: 1323286 | BE24: =IF(BD24>=BD23,BD24-BD23,0) -> 0 | BF24: 3140983 | BG24: =IF(BF24>=BF23,BF24-BF23,0) -> 1137 | BH24: 348256 | BI24: =IF(BH24>=BH23,BH24-BH23,0) -> 74 | BJ24: 397696 | BK24: =IF(BJ24>=BJ23,BJ24-BJ23,0) -> 190 | BL24: =J24+Q24+AL24+BC24 -> 13195.76 | BN24: =IF(BL24>0,BL24/BM24,0) -> #DIV/0! | BP24: =IF(BL24>0,BL24/BO24,0) -> #DIV/0! | BQ24: =BL24*BS1 -> 6070.0496 | BR24: =IF(BQ24>0,BQ24/BM24,0) -> #DIV/0! | BS24: =IF(BQ24>0,BQ24/BO24,0) -> #DIV/0!
A25: 20 | C25: =IF(+B25-B24>0,B25-B24,(B25-B24)>0)*800 -> 0 | E25: =IF(+D25-D24>0,D25-D24,(D25-D24)>0)*80 -> 0 | G25: =IF(+F25-F24>0,F25-F24,(F25-F24)>0)*10 -> 0 | I25: 20940346 | J25: =IF(I25>=I24,I25-I24,0) -> 1989 | K25: =M25+O25 -> 1026 | L25: 652121 | M25: =IF(L25>=L24,L25-L24,0) -> 508 | N25: 638430 | O25: =IF(N25>=N24,N25-N24,0) -> 518 | P25: 210713 | Q25: =IF(P25>=P24,P25-P24,0)*30 -> 90 | R25: 702925 | S25: =IF(R25>=R24,R25-R24,0) -> 0 | T25: 344001 | U25: =IF(T25>=T24,T25-T24,0) -> 0 | V25: 92414 | W25: =IF(V25>=V24,V25-V24,0) -> 144 | X25: 171682 | Y25: =IF(X25>=X24,X25-X24,0) -> 235 | Z25: 315108 | AA25: =IF(Z25>=Z24,Z25-Z24,0)*0.53 -> 0 | AB25: 671730 | AC25: =IF(AB25>=AB24,AB25-AB24,0)*0.53 -> 0 | AD25: 769991 | AE25: =IF(AD25>=AD24,AD25-AD24,0)*0.53 -> 1537.53 | AF25: 714945 | AG25: =IF(AF25>=AF24,AF25-AF24,0)*0.53 -> 0 | AH25: 209138 | AI25: =IF(AH25>=AH24,AH25-AH24,0)*0.53 -> 228.43 | AJ25: 306312 | AK25: =IF(AJ25>=AJ24,AJ25-AJ24,0)*0.53 -> 1496.72 | AL25: =AA25+AC25+AE25+AG25+AI25+AK25 -> 3262.68 | AM25: 6884369 | AN25: =IF(AM25>=AM24,AM25-AM24,0) -> 10 | AO25: 536195 | AP25: =IF(AO25>=AO24,AO25-AO24,0) -> 1 | AQ25: 881169 | AR25: =IF(AQ25>=AQ24,AQ25-AQ24,0)*0.11 -> 4.51 | AS25: 782093 | AT25: =IF(AS25>=AS24,AS25-AS24,0) -> 24 | AU25: 2157709 | AV25: =IF(AU25>=AU24,AU25-AU24,0) -> 262 | AW25: 195116 | AX25: =IF(AW25>=AW24,AW25-AW24,0) -> 0 | AY25: 16736982 | AZ25: =IF(AY25>=AY24,AY25-AY24,0) -> 1392 | BA25: 20279667 | BB25: =IF(BA25>=BA24,BA25-BA24,0)-(0.6*BG25)-(0.5*BI25)-BK25-BE25 -> 3465.4 | BC25: =AN25+AP25+AR25+AT25+AV25+AX25+AZ25+BB25 -> 5158.91 | BD25: 1323286 | BE25: =IF(BD25>=BD24,BD25-BD24,0) -> 0 | BF25: 3142189 | BG25: =IF(BF25>=BF24,BF25-BF24,0) -> 1206 | BH25: 348340 | BI25: =IF(BH25>=BH24,BH25-BH24,0) -> 84 | BJ25: 397901 | BK25: =IF(BJ25>=BJ24,BJ25-BJ24,0) -> 205 | BL25: =J25+Q25+AL25+BC25 -> 10500.59 | BN25: =IF(BL25>0,BL25/BM25,0) -> #DIV/0! | BP25: =IF(BL25>0,BL25/BO25,0) -> #DIV/0! | BQ25: =BL25*BS1 -> 4830.2714 | BR25: =IF(BQ25>0,BQ25/BM25,0) -> #DIV/0! | BS25: =IF(BQ25>0,BQ25/BO25,0) -> #DIV/0!
A26: 21 | C26: =IF(+B26-B25>0,B26-B25,(B26-B25)>0)*800 -> 0 | E26: =IF(+D26-D25>0,D26-D25,(D26-D25)>0)*80 -> 0 | G26: =IF(+F26-F25>0,F26-F25,(F26-F25)>0)*10 -> 0 | H26: 66 | I26: 20942692 | J26: =IF(I26>=I25,I26-I25,0) -> 2346 | K26: =M26+O26 -> 1677 | L26: 652920 | M26: =IF(L26>=L25,L26-L25,0) -> 799 | N26: 639308 | O26: =IF(N26>=N25,N26-N25,0) -> 878 | P26: 210717 | Q26: =IF(P26>=P25,P26-P25,0)*30 -> 120 | R26: 702925 | S26: =IF(R26>=R25,R26-R25,0) -> 0 | T26: 344001 | U26: =IF(T26>=T25,T26-T25,0) -> 0 | V26: 92579 | W26: =IF(V26>=V25,V26-V25,0) -> 165 | X26: 171954 | Y26: =IF(X26>=X25,X26-X25,0) -> 272 | Z26: 315108 | AA26: =IF(Z26>=Z25,Z26-Z25,0)*0.53 -> 0 | AB26: 671730 | AC26: =IF(AB26>=AB25,AB26-AB25,0)*0.53 -> 0 | AD26: 773957 | AE26: =IF(AD26>=AD25,AD26-AD25,0)*0.53 -> 2101.98 | AF26: 714945 | AG26: =IF(AF26>=AF25,AF26-AF25,0)*0.53 -> 0 | AH26: 210160 | AI26: =IF(AH26>=AH25,AH26-AH25,0)*0.53 -> 541.66 | AJ26: 310719 | AK26: =IF(AJ26>=AJ25,AJ26-AJ25,0)*0.53 -> 2335.71 | AL26: =AA26+AC26+AE26+AG26+AI26+AK26 -> 4979.35 | AM26: 6884396 | AN26: =IF(AM26>=AM25,AM26-AM25,0) -> 27 | AO26: 536198 | AP26: =IF(AO26>=AO25,AO26-AO25,0) -> 3 | AQ26: 881220 | AR26: =IF(AQ26>=AQ25,AQ26-AQ25,0)*0.11 -> 5.61 | AS26: 782133 | AT26: =IF(AS26>=AS25,AS26-AS25,0) -> 40 | AU26: 2158182 | AV26: =IF(AU26>=AU25,AU26-AU25,0) -> 473 | AW26: 195116 | AX26: =IF(AW26>=AW25,AW26-AW25,0) -> 0 | AY26: 16739052 | AZ26: =IF(AY26>=AY25,AY26-AY25,0) -> 2070 | BA26: 20282327 | BB26: =IF(BA26>=BA25,BA26-BA25,0)-(0.6*BG26)-(0.5*BI26)-BK26-BE26 -> 1406 | BC26: =AN26+AP26+AR26+AT26+AV26+AX26+AZ26+BB26 -> 4024.61 | BD26: 1323286 | BE26: =IF(BD26>=BD25,BD26-BD25,0) -> 0 | BF26: 3143754 | BG26: =IF(BF26>=BF25,BF26-BF25,0) -> 1565 | BH26: 348442 | BI26: =IF(BH26>=BH25,BH26-BH25,0) -> 102 | BJ26: 398165 | BK26: =IF(BJ26>=BJ25,BJ26-BJ25,0) -> 264 | BL26: =J26+Q26+AL26+BC26 -> 11469.96 | BN26: =IF(BL26>0,BL26/BM26,0) -> #DIV/0! | BP26: =IF(BL26>0,BL26/BO26,0) -> #DIV/0! | BQ26: =BL26*BS1 -> 5276.1816 | BR26: =IF(BQ26>0,BQ26/BM26,0) -> #DIV/0! | BS26: =IF(BQ26>0,BQ26/BO26,0) -> #DIV/0!
A27: 22 | C27: =IF(+B27-B26>0,B27-B26,(B27-B26)>0)*800 -> 0 | E27: =IF(+D27-D26>0,D27-D26,(D27-D26)>0)*80 -> 0 | G27: =IF(+F27-F26>0,F27-F26,(F27-F26)>0)*10 -> 0 | I27: 20943946 | J27: =IF(I27>=I26,I27-I26,0) -> 1254 | K27: =M27+O27 -> 883 | L27: 653312 | M27: =IF(L27>=L26,L27-L26,0) -> 392 | N27: 639799 | O27: =IF(N27>=N26,N27-N26,0) -> 491 | P27: 210718 | Q27: =IF(P27>=P26,P27-P26,0)*30 -> 30 | R27: 702925 | S27: =IF(R27>=R26,R27-R26,0) -> 0 | T27: 344001 | U27: =IF(T27>=T26,T27-T26,0) -> 0 | V27: 92641 | W27: =IF(V27>=V26,V27-V26,0) -> 62 | X27: 172059 | Y27: =IF(X27>=X26,X27-X26,0) -> 105 | Z27: 315108 | AA27: =IF(Z27>=Z26,Z27-Z26,0)*0.53 -> 0 | AB27: 671730 | AC27: =IF(AB27>=AB26,AB27-AB26,0)*0.53 -> 0 | AD27: 777363 | AE27: =IF(AD27>=AD26,AD27-AD26,0)*0.53 -> 1805.18 | AF27: 714945 | AG27: =IF(AF27>=AF26,AF27-AF26,0)*0.53 -> 0 | AH27: 210670 | AI27: =IF(AH27>=AH26,AH27-AH26,0)*0.53 -> 270.3 | AJ27: 313071 | AK27: =IF(AJ27>=AJ26,AJ27-AJ26,0)*0.53 -> 1246.56 | AL27: =AA27+AC27+AE27+AG27+AI27+AK27 -> 3322.04 | AM27: 6884412 | AN27: =IF(AM27>=AM26,AM27-AM26,0) -> 16 | AO27: 536198 | AP27: =IF(AO27>=AO26,AO27-AO26,0) -> 0 | AQ27: 881235 | AR27: =IF(AQ27>=AQ26,AQ27-AQ26,0)*0.11 -> 1.65 | AS27: 782154 | AT27: =IF(AS27>=AS26,AS27-AS26,0) -> 21 | AU27: 2158422 | AV27: =IF(AU27>=AU26,AU27-AU26,0) -> 240 | AW27: 195116 | AX27: =IF(AW27>=AW26,AW27-AW26,0) -> 0 | AY27: 16739983 | AZ27: =IF(AY27>=AY26,AY27-AY26,0) -> 931 | BA27: 20287094 | BB27: =IF(BA27>=BA26,BA27-BA26,0)-(0.6*BG27)-(0.5*BI27)-BK27-BE27 -> 4385.3 | BC27: =AN27+AP27+AR27+AT27+AV27+AX27+AZ27+BB27 -> 5594.95 | BD27: 1323286 | BE27: =IF(BD27>=BD26,BD27-BD26,0) -> 0 | BF27: 3144226 | BG27: =IF(BF27>=BF26,BF27-BF26,0) -> 472 | BH27: 348481 | BI27: =IF(BH27>=BH26,BH27-BH26,0) -> 39 | BJ27: 398244 | BK27: =IF(BJ27>=BJ26,BJ27-BJ26,0) -> 79 | BL27: =J27+Q27+AL27+BC27 -> 10200.99 | BN27: =IF(BL27>0,BL27/BM27,0) -> #DIV/0! | BP27: =IF(BL27>0,BL27/BO27,0) -> #DIV/0! | BQ27: =BL27*BS1 -> 4692.4554 | BR27: =IF(BQ27>0,BQ27/BM27,0) -> #DIV/0! | BS27: =IF(BQ27>0,BQ27/BO27,0) -> #DIV/0!
A28: 23 | C28: =IF(+B28-B27>0,B28-B27,(B28-B27)>0)*800 -> 0 | E28: =IF(+D28-D27>0,D28-D27,(D28-D27)>0)*80 -> 0 | G28: =IF(+F28-F27>0,F28-F27,(F28-F27)>0)*10 -> 0 | H28: 67 | I28: 20945700 | J28: =IF(I28>=I27,I28-I27,0) -> 1754 | K28: =M28+O28 -> 1201 | L28: 653852 | M28: =IF(L28>=L27,L28-L27,0) -> 540 | N28: 640460 | O28: =IF(N28>=N27,N28-N27,0) -> 661 | P28: 210720 | Q28: =IF(P28>=P27,P28-P27,0)*30 -> 60 | R28: 702925 | S28: =IF(R28>=R27,R28-R27,0) -> 0 | T28: 344001 | U28: =IF(T28>=T27,T28-T27,0) -> 0 | V28: 92764 | W28: =IF(V28>=V27,V28-V27,0) -> 123 | X28: 172266 | Y28: =IF(X28>=X27,X28-X27,0) -> 207 | Z28: 315108 | AA28: =IF(Z28>=Z27,Z28-Z27,0)*0.53 -> 0 | AB28: 671730 | AC28: =IF(AB28>=AB27,AB28-AB27,0)*0.53 -> 0 | AD28: 781017 | AE28: =IF(AD28>=AD27,AD28-AD27,0)*0.53 -> 1936.62 | AF28: 714945 | AG28: =IF(AF28>=AF27,AF28-AF27,0)*0.53 -> 0 | AH28: 211527 | AI28: =IF(AH28>=AH27,AH28-AH27,0)*0.53 -> 454.21 | AJ28: 316270 | AK28: =IF(AJ28>=AJ27,AJ28-AJ27,0)*0.53 -> 1695.47 | AL28: =AA28+AC28+AE28+AG28+AI28+AK28 -> 4086.3 | AM28: 6884435 | AN28: =IF(AM28>=AM27,AM28-AM27,0) -> 23 | AO28: 536199 | AP28: =IF(AO28>=AO27,AO28-AO27,0) -> 1 | AQ28: 881279 | AR28: =IF(AQ28>=AQ27,AQ28-AQ27,0)*0.11 -> 4.84 | AS28: 782185 | AT28: =IF(AS28>=AS27,AS28-AS27,0) -> 31 | AU28: 2158789 | AV28: =IF(AU28>=AU27,AU28-AU27,0) -> 367 | AW28: 195116 | AX28: =IF(AW28>=AW27,AW28-AW27,0) -> 0 | AY28: 16741912 | AZ28: =IF(AY28>=AY27,AY28-AY27,0) -> 1929 | BA28: 20291649 | BB28: =IF(BA28>=BA27,BA28-BA27,0)-(0.6*BG28)-(0.5*BI28)-BK28-BE28 -> 3570.5 | BC28: =AN28+AP28+AR28+AT28+AV28+AX28+AZ28+BB28 -> 5926.34 | BD28: 1323286 | BE28: =IF(BD28>=BD27,BD28-BD27,0) -> 0 | BF28: 3145456 | BG28: =IF(BF28>=BF27,BF28-BF27,0) -> 1230 | BH28: 348566 | BI28: =IF(BH28>=BH27,BH28-BH27,0) -> 85 | BJ28: 398448 | BK28: =IF(BJ28>=BJ27,BJ28-BJ27,0) -> 204 | BL28: =J28+Q28+AL28+BC28 -> 11826.64 | BN28: =IF(BL28>0,BL28/BM28,0) -> #DIV/0! | BP28: =IF(BL28>0,BL28/BO28,0) -> #DIV/0! | BQ28: =BL28*BS1 -> 5440.2544 | BR28: =IF(BQ28>0,BQ28/BM28,0) -> #DIV/0! | BS28: =IF(BQ28>0,BQ28/BO28,0) -> #DIV/0!
A29: 24 | C29: =IF(+B29-B28>0,B29-B28,(B29-B28)>0)*800 -> 0 | E29: =IF(+D29-D28>0,D29-D28,(D29-D28)>0)*80 -> 0 | G29: =IF(+F29-F28>0,F29-F28,(F29-F28)>0)*10 -> 0 | I29: 20947232 | J29: =IF(I29>=I28,I29-I28,0) -> 1532 | K29: =M29+O29 -> 1881 | L29: 654749 | M29: =IF(L29>=L28,L29-L28,0) -> 897 | N29: 641444 | O29: =IF(N29>=N28,N29-N28,0) -> 984 | P29: 210724 | Q29: =IF(P29>=P28,P29-P28,0)*30 -> 120 | R29: 702925 | S29: =IF(R29>=R28,R29-R28,0) -> 0 | T29: 344001 | U29: =IF(T29>=T28,T29-T28,0) -> 0 | V29: 92957 | W29: =IF(V29>=V28,V29-V28,0) -> 193 | X29: 172588 | Y29: =IF(X29>=X28,X29-X28,0) -> 322 | Z29: 315108 | AA29: =IF(Z29>=Z28,Z29-Z28,0)*0.53 -> 0 | AB29: 671730 | AC29: =IF(AB29>=AB28,AB29-AB28,0)*0.53 -> 0 | AD29: 786147 | AE29: =IF(AD29>=AD28,AD29-AD28,0)*0.53 -> 2718.9 | AF29: 714945 | AG29: =IF(AF29>=AF28,AF29-AF28,0)*0.53 -> 0 | AH29: 212654 | AI29: =IF(AH29>=AH28,AH29-AH28,0)*0.53 -> 597.31 | AJ29: 321381 | AK29: =IF(AJ29>=AJ28,AJ29-AJ28,0)*0.53 -> 2708.83 | AL29: =AA29+AC29+AE29+AG29+AI29+AK29 -> 6025.04 | AM29: 6884470 | AN29: =IF(AM29>=AM28,AM29-AM28,0) -> 35 | AO29: 536202 | AP29: =IF(AO29>=AO28,AO29-AO28,0) -> 3 | AQ29: 881338 | AR29: =IF(AQ29>=AQ28,AQ29-AQ28,0)*0.11 -> 6.49 | AS29: 782246 | AT29: =IF(AS29>=AS28,AS29-AS28,0) -> 61 | AU29: 2159296 | AV29: =IF(AU29>=AU28,AU29-AU28,0) -> 507 | AW29: 195116 | AX29: =IF(AW29>=AW28,AW29-AW28,0) -> 0 | AY29: 16744784 | AZ29: =IF(AY29>=AY28,AY29-AY28,0) -> 2872 | BA29: 20297896 | BB29: =IF(BA29>=BA28,BA29-BA28,0)-(0.6*BG29)-(0.5*BI29)-BK29-BE29 -> 4965.4 | BC29: =AN29+AP29+AR29+AT29+AV29+AX29+AZ29+BB29 -> 8449.89 | BD29: 1323286 | BE29: =IF(BD29>=BD28,BD29-BD28,0) -> 0 | BF29: 3147012 | BG29: =IF(BF29>=BF28,BF29-BF28,0) -> 1556 | BH29: 348684 | BI29: =IF(BH29>=BH28,BH29-BH28,0) -> 118 | BJ29: 398737 | BK29: =IF(BJ29>=BJ28,BJ29-BJ28,0) -> 289 | BL29: =J29+Q29+AL29+BC29 -> 16126.93 | BN29: =IF(BL29>0,BL29/BM29,0) -> #DIV/0! | BP29: =IF(BL29>0,BL29/BO29,0) -> #DIV/0! | BQ29: =BL29*BS1 -> 7418.3878 | BR29: =IF(BQ29>0,BQ29/BM29,0) -> #DIV/0! | BS29: =IF(BQ29>0,BQ29/BO29,0) -> #DIV/0!
A30: 25 | C30: =IF(+B30-B29>0,B30-B29,(B30-B29)>0)*800 -> 0 | E30: =IF(+D30-D29>0,D30-D29,(D30-D29)>0)*80 -> 0 | G30: =IF(+F30-F29>0,F30-F29,(F30-F29)>0)*10 -> 0 | H30: 68 | I30: 20949700 | J30: =IF(I30>=I29,I30-I29,0) -> 2468 | K30: =M30+O30 -> 772 | L30: 655126 | M30: =IF(L30>=L29,L30-L29,0) -> 377 | N30: 641839 | O30: =IF(N30>=N29,N30-N29,0) -> 395 | P30: 210724 | Q30: =IF(P30>=P29,P30-P29,0)*30 -> 0 | R30: 702925 | S30: =IF(R30>=R29,R30-R29,0) -> 0 | T30: 344001 | U30: =IF(T30>=T29,T30-T29,0) -> 0 | V30: 93012 | W30: =IF(V30>=V29,V30-V29,0) -> 55 | X30: 172679 | Y30: =IF(X30>=X29,X30-X29,0) -> 91 | Z30: 315108 | AA30: =IF(Z30>=Z29,Z30-Z29,0)*0.53 -> 0 | AB30: 671730 | AC30: =IF(AB30>=AB29,AB30-AB29,0)*0.53 -> 0 | AD30: 789177 | AE30: =IF(AD30>=AD29,AD30-AD29,0)*0.53 -> 1605.9 | AF30: 714945 | AG30: =IF(AF30>=AF29,AF30-AF29,0)*0.53 -> 0 | AH30: 213117 | AI30: =IF(AH30>=AH29,AH30-AH29,0)*0.53 -> 245.39 | AJ30: 324053 | AK30: =IF(AJ30>=AJ29,AJ30-AJ29,0)*0.53 -> 1416.16 | AL30: =AA30+AC30+AE30+AG30+AI30+AK30 -> 3267.45 | AM30: 6884489 | AN30: =IF(AM30>=AM29,AM30-AM29,0) -> 19 | AO30: 536202 | AP30: =IF(AO30>=AO29,AO30-AO29,0) -> 0 | AQ30: 881354 | AR30: =IF(AQ30>=AQ29,AQ30-AQ29,0)*0.11 -> 1.76 | AS30: 782267 | AT30: =IF(AS30>=AS29,AS30-AS29,0) -> 21 | AU30: 2159513 | AV30: =IF(AU30>=AU29,AU30-AU29,0) -> 217 | AW30: 195116 | AX30: =IF(AW30>=AW29,AW30-AW29,0) -> 0 | AY30: 16745775 | AZ30: =IF(AY30>=AY29,AY30-AY29,0) -> 991 | BA30: 20299628 | BB30: =IF(BA30>=BA29,BA30-BA29,0)-(0.6*BG30)-(0.5*BI30)-BK30-BE30 -> 1385.1 | BC30: =AN30+AP30+AR30+AT30+AV30+AX30+AZ30+BB30 -> 2634.86 | BD30: 1323286 | BE30: =IF(BD30>=BD29,BD30-BD29,0) -> 0 | BF30: 3147426 | BG30: =IF(BF30>=BF29,BF30-BF29,0) -> 414 | BH30: 348719 | BI30: =IF(BH30>=BH29,BH30-BH29,0) -> 35 | BJ30: 398818 | BK30: =IF(BJ30>=BJ29,BJ30-BJ29,0) -> 81 | BL30: =J30+Q30+AL30+BC30 -> 8370.31 | BN30: =IF(BL30>0,BL30/BM30,0) -> #DIV/0! | BP30: =IF(BL30>0,BL30/BO30,0) -> #DIV/0! | BQ30: =BL30*BS1 -> 3850.3426 | BR30: =IF(BQ30>0,BQ30/BM30,0) -> #DIV/0! | BS30: =IF(BQ30>0,BQ30/BO30,0) -> #DIV/0!
A31: 26 | C31: =IF(+B31-B30>0,B31-B30,(B31-B30)>0)*800 -> 0 | E31: =IF(+D31-D30>0,D31-D30,(D31-D30)>0)*80 -> 0 | G31: =IF(+F31-F30>0,F31-F30,(F31-F30)>0)*10 -> 0 | I31: 20951219 | J31: =IF(I31>=I30,I31-I30,0) -> 1519 | K31: =M31+O31 -> 1238 | L31: 655712 | M31: =IF(L31>=L30,L31-L30,0) -> 586 | N31: 642491 | O31: =IF(N31>=N30,N31-N30,0) -> 652 | P31: 210728 | Q31: =IF(P31>=P30,P31-P30,0)*30 -> 120 | R31: 702925 | S31: =IF(R31>=R30,R31-R30,0) -> 0 | T31: 344001 | U31: =IF(T31>=T30,T31-T30,0) -> 0 | V31: 93150 | W31: =IF(V31>=V30,V31-V30,0) -> 138 | X31: 172909 | Y31: =IF(X31>=X30,X31-X30,0) -> 230 | Z31: 315108 | AA31: =IF(Z31>=Z30,Z31-Z30,0)*0.53 -> 0 | AB31: 671730 | AC31: =IF(AB31>=AB30,AB31-AB30,0)*0.53 -> 0 | AD31: 793324 | AE31: =IF(AD31>=AD30,AD31-AD30,0)*0.53 -> 2197.91 | AF31: 714945 | AG31: =IF(AF31>=AF30,AF31-AF30,0)*0.53 -> 0 | AH31: 213919 | AI31: =IF(AH31>=AH30,AH31-AH30,0)*0.53 -> 425.06 | AJ31: 328323 | AK31: =IF(AJ31>=AJ30,AJ31-AJ30,0)*0.53 -> 2263.1 | AL31: =AA31+AC31+AE31+AG31+AI31+AK31 -> 4886.07 | AM31: 6884511 | AN31: =IF(AM31>=AM30,AM31-AM30,0) -> 22 | AO31: 536205 | AP31: =IF(AO31>=AO30,AO31-AO30,0) -> 3 | AQ31: 881440 | AR31: =IF(AQ31>=AQ30,AQ31-AQ30,0)*0.11 -> 9.46 | AS31: 782298 | AT31: =IF(AS31>=AS30,AS31-AS30,0) -> 31 | AU31: 2159813 | AV31: =IF(AU31>=AU30,AU31-AU30,0) -> 300 | AW31: 195116 | AX31: =IF(AW31>=AW30,AW31-AW30,0) -> 0 | AY31: 16747770 | AZ31: =IF(AY31>=AY30,AY31-AY30,0) -> 1995 | BA31: 20303995 | BB31: =IF(BA31>=BA30,BA31-BA30,0)-(0.6*BG31)-(0.5*BI31)-BK31-BE31 -> 3520.3 | BC31: =AN31+AP31+AR31+AT31+AV31+AX31+AZ31+BB31 -> 5880.76 | BD31: 1323286 | BE31: =IF(BD31>=BD30,BD31-BD30,0) -> 0 | BF31: 3148433 | BG31: =IF(BF31>=BF30,BF31-BF30,0) -> 1007 | BH31: 348804 | BI31: =IF(BH31>=BH30,BH31-BH30,0) -> 85 | BJ31: 399018 | BK31: =IF(BJ31>=BJ30,BJ31-BJ30,0) -> 200 | BL31: =J31+Q31+AL31+BC31 -> 12405.83 | BN31: =IF(BL31>0,BL31/BM31,0) -> #DIV/0! | BP31: =IF(BL31>0,BL31/BO31,0) -> #DIV/0! | BQ31: =BL31*BS1 -> 5706.6818 | BR31: =IF(BQ31>0,BQ31/BM31,0) -> #DIV/0! | BS31: =IF(BQ31>0,BQ31/BO31,0) -> #DIV/0!
A32: 27 | C32: =IF(+B32-B31>0,B32-B31,(B32-B31)>0)*800 -> 0 | E32: =IF(+D32-D31>0,D32-D31,(D32-D31)>0)*80 -> 0 | G32: =IF(+F32-F31>0,F32-F31,(F32-F31)>0)*10 -> 0 | H32: 69 | I32: 20953530 | J32: =IF(I32>=I31,I32-I31,0) -> 2311 | K32: =M32+O32 -> 1352 | L32: 656337 | M32: =IF(L32>=L31,L32-L31,0) -> 625 | N32: 643218 | O32: =IF(N32>=N31,N32-N31,0) -> 727 | P32: 210731 | Q32: =IF(P32>=P31,P32-P31,0)*30 -> 90 | R32: 702925 | S32: =IF(R32>=R31,R32-R31,0) -> 0 | T32: 344001 | U32: =IF(T32>=T31,T32-T31,0) -> 0 | V32: 93285 | W32: =IF(V32>=V31,V32-V31,0) -> 135 | X32: 173139 | Y32: =IF(X32>=X31,X32-X31,0) -> 230 | Z32: 315108 | AA32: =IF(Z32>=Z31,Z32-Z31,0)*0.53 -> 0 | AB32: 671730 | AC32: =IF(AB32>=AB31,AB32-AB31,0)*0.53 -> 0 | AD32: 797036 | AE32: =IF(AD32>=AD31,AD32-AD31,0)*0.53 -> 1967.36 | AF32: 715317 | AG32: =IF(AF32>=AF31,AF32-AF31,0)*0.53 -> 197.16 | AH32: 214775 | AI32: =IF(AH32>=AH31,AH32-AH31,0)*0.53 -> 453.68 | AJ32: 332551 | AK32: =IF(AJ32>=AJ31,AJ32-AJ31,0)*0.53 -> 2240.84 | AL32: =AA32+AC32+AE32+AG32+AI32+AK32 -> 4859.04 | AM32: 6884536 | AN32: =IF(AM32>=AM31,AM32-AM31,0) -> 25 | AO32: 536208 | AP32: =IF(AO32>=AO31,AO32-AO31,0) -> 3 | AQ32: 881472 | AR32: =IF(AQ32>=AQ31,AQ32-AQ31,0)*0.11 -> 3.52 | AS32: 782331 | AT32: =IF(AS32>=AS31,AS32-AS31,0) -> 33 | AU32: 2160167 | AV32: =IF(AU32>=AU31,AU32-AU31,0) -> 354 | AW32: 195116 | AX32: =IF(AW32>=AW31,AW32-AW31,0) -> 0 | AY32: 16749885 | AZ32: =IF(AY32>=AY31,AY32-AY31,0) -> 2115 | BA32: 20308454 | BB32: =IF(BA32>=BA31,BA32-BA31,0)-(0.6*BG32)-(0.5*BI32)-BK32-BE32 -> 3601 | BC32: =AN32+AP32+AR32+AT32+AV32+AX32+AZ32+BB32 -> 6134.52 | BD32: 1323286 | BE32: =IF(BD32>=BD31,BD32-BD31,0) -> 0 | BF32: 3149453 | BG32: =IF(BF32>=BF31,BF32-BF31,0) -> 1020 | BH32: 348890 | BI32: =IF(BH32>=BH31,BH32-BH31,0) -> 86 | BJ32: 399221 | BK32: =IF(BJ32>=BJ31,BJ32-BJ31,0) -> 203 | BL32: =J32+Q32+AL32+BC32 -> 13394.56 | BN32: =IF(BL32>0,BL32/BM32,0) -> #DIV/0! | BP32: =IF(BL32>0,BL32/BO32,0) -> #DIV/0! | BQ32: =BL32*BS1 -> 6161.4976 | BR32: =IF(BQ32>0,BQ32/BM32,0) -> #DIV/0! | BS32: =IF(BQ32>0,BQ32/BO32,0) -> #DIV/0!
A33: 28 | C33: =IF(+B33-B32>0,B33-B32,(B33-B32)>0)*800 -> 0 | E33: =IF(+D33-D32>0,D33-D32,(D33-D32)>0)*80 -> 0 | G33: =IF(+F33-F32>0,F33-F32,(F33-F32)>0)*10 -> 0 | I33: 20955210 | J33: =IF(I33>=I32,I33-I32,0) -> 1680 | K33: =M33+O33 -> 1161 | L33: 656860 | M33: =IF(L33>=L32,L33-L32,0) -> 523 | N33: 643856 | O33: =IF(N33>=N32,N33-N32,0) -> 638 | P33: 210733 | Q33: =IF(P33>=P32,P33-P32,0)*30 -> 60 | R33: 702925 | S33: =IF(R33>=R32,R33-R32,0) -> 0 | T33: 344001 | U33: =IF(T33>=T32,T33-T32,0) -> 0 | V33: 93415 | W33: =IF(V33>=V32,V33-V32,0) -> 130 | X33: 173359 | Y33: =IF(X33>=X32,X33-X32,0) -> 220 | Z33: 315108 | AA33: =IF(Z33>=Z32,Z33-Z32,0)*0.53 -> 0 | AB33: 671730 | AC33: =IF(AB33>=AB32,AB33-AB32,0)*0.53 -> 0 | AD33: 797883 | AE33: =IF(AD33>=AD32,AD33-AD32,0)*0.53 -> 448.91 | AF33: 717521 | AG33: =IF(AF33>=AF32,AF33-AF32,0)*0.53 -> 1168.12 | AH33: 215349 | AI33: =IF(AH33>=AH32,AH33-AH32,0)*0.53 -> 304.22 | AJ33: 336088 | AK33: =IF(AJ33>=AJ32,AJ33-AJ32,0)*0.53 -> 1874.61 | AL33: =AA33+AC33+AE33+AG33+AI33+AK33 -> 3795.86 | AM33: 6884557 | AN33: =IF(AM33>=AM32,AM33-AM32,0) -> 21 | AO33: 536211 | AP33: =IF(AO33>=AO32,AO33-AO32,0) -> 3 | AQ33: 881522 | AR33: =IF(AQ33>=AQ32,AQ33-AQ32,0)*0.11 -> 5.5 | AS33: 782347 | AT33: =IF(AS33>=AS32,AS33-AS32,0) -> 16 | AU33: 2160465 | AV33: =IF(AU33>=AU32,AU33-AU32,0) -> 298 | AW33: 195116 | AX33: =IF(AW33>=AW32,AW33-AW32,0) -> 0 | AY33: 16751399 | AZ33: =IF(AY33>=AY32,AY33-AY32,0) -> 1514 | BA33: 20311714 | BB33: =IF(BA33>=BA32,BA33-BA32,0)-(0.6*BG33)-(0.5*BI33)-BK33-BE33 -> 2624.8 | BC33: =AN33+AP33+AR33+AT33+AV33+AX33+AZ33+BB33 -> 4482.3 | BD33: 1323286 | BE33: =IF(BD33>=BD32,BD33-BD32,0) -> 0 | BF33: 3150205 | BG33: =IF(BF33>=BF32,BF33-BF32,0) -> 752 | BH33: 348950 | BI33: =IF(BH33>=BH32,BH33-BH32,0) -> 60 | BJ33: 399375 | BK33: =IF(BJ33>=BJ32,BJ33-BJ32,0) -> 154 | BL33: =J33+Q33+AL33+BC33 -> 10018.16 | BN33: =IF(BL33>0,BL33/BM33,0) -> #DIV/0! | BP33: =IF(BL33>0,BL33/BO33,0) -> #DIV/0! | BQ33: =BL33*BS1 -> 4608.3536 | BR33: =IF(BQ33>0,BQ33/BM33,0) -> #DIV/0! | BS33: =IF(BQ33>0,BQ33/BO33,0) -> #DIV/0!
A34: 29 | C34: =IF(+B34-B33>0,B34-B33,(B34-B33)>0)*800 -> 0 | E34: =IF(+D34-D33>0,D34-D33,(D34-D33)>0)*80 -> 0 | G34: =IF(+F34-F33>0,F34-F33,(F34-F33)>0)*10 -> 0 | I34: 20957424 | J34: =IF(I34>=I33,I34-I33,0) -> 2214 | K34: =M34+O34 -> 1625 | L34: 657614 | M34: =IF(L34>=L33,L34-L33,0) -> 754 | N34: 644727 | O34: =IF(N34>=N33,N34-N33,0) -> 871 | P34: 210736 | Q34: =IF(P34>=P33,P34-P33,0)*30 -> 90 | R34: 702925 | S34: =IF(R34>=R33,R34-R33,0) -> 0 | T34: 344001 | U34: =IF(T34>=T33,T34-T33,0) -> 0 | V34: 93526 | W34: =IF(V34>=V33,V34-V33,0) -> 111 | X34: 173547 | Y34: =IF(X34>=X33,X34-X33,0) -> 188 | Z34: 315108 | AA34: =IF(Z34>=Z33,Z34-Z33,0)*0.53 -> 0 | AB34: 671730 | AC34: =IF(AB34>=AB33,AB34-AB33,0)*0.53 -> 0 | AD34: 798439 | AE34: =IF(AD34>=AD33,AD34-AD33,0)*0.53 -> 294.68 | AF34: 720359 | AG34: =IF(AF34>=AF33,AF34-AF33,0)*0.53 -> 1504.14 | AH34: 216304 | AI34: =IF(AH34>=AH33,AH34-AH33,0)*0.53 -> 506.15 | AJ34: 341483 | AK34: =IF(AJ34>=AJ33,AJ34-AJ33,0)*0.53 -> 2859.35 | AL34: =AA34+AC34+AE34+AG34+AI34+AK34 -> 5164.32 | AM34: 6884581 | AN34: =IF(AM34>=AM33,AM34-AM33,0) -> 24 | AO34: 536212 | AP34: =IF(AO34>=AO33,AO34-AO33,0) -> 1 | AQ34: 881590 | AR34: =IF(AQ34>=AQ33,AQ34-AQ33,0)*0.11 -> 7.48 | AS34: 782369 | AT34: =IF(AS34>=AS33,AS34-AS33,0) -> 22 | AU34: 2160870 | AV34: =IF(AU34>=AU33,AU34-AU33,0) -> 405 | AW34: 195116 | AX34: =IF(AW34>=AW33,AW34-AW33,0) -> 0 | AY34: 16753760 | AZ34: =IF(AY34>=AY33,AY34-AY33,0) -> 2361 | BA34: 20316337 | BB34: =IF(BA34>=BA33,BA34-BA33,0)-(0.6*BG34)-(0.5*BI34)-BK34-BE34 -> 3756.7 | BC34: =AN34+AP34+AR34+AT34+AV34+AX34+AZ34+BB34 -> 6577.18 | BD34: 1323286 | BE34: =IF(BD34>=BD33,BD34-BD33,0) -> 0 | BF34: 3151218 | BG34: =IF(BF34>=BF33,BF34-BF33,0) -> 1013 | BH34: 349035 | BI34: =IF(BH34>=BH33,BH34-BH33,0) -> 85 | BJ34: 399591 | BK34: =IF(BJ34>=BJ33,BJ34-BJ33,0) -> 216 | BL34: =J34+Q34+AL34+BC34 -> 14045.5 | BN34: =IF(BL34>0,BL34/BM34,0) -> #DIV/0! | BP34: =IF(BL34>0,BL34/BO34,0) -> #DIV/0! | BQ34: =BL34*BS1 -> 6460.93 | BR34: =IF(BQ34>0,BQ34/BM34,0) -> #DIV/0! | BS34: =IF(BQ34>0,BQ34/BO34,0) -> #DIV/0!
A35: 30 | C35: =IF(+B35-B34>0,B35-B34,(B35-B34)>0)*800 -> 0 | E35: =IF(+D35-D34>0,D35-D34,(D35-D34)>0)*80 -> 0 | G35: =IF(+F35-F34>0,F35-F34,(F35-F34)>0)*10 -> 0 | I35: 20959638 | J35: =IF(I35>=I34,I35-I34,0) -> 2214 | K35: =M35+O35 -> 1625 | L35: 658368 | M35: =IF(L35>=L34,L35-L34,0) -> 754 | N35: 645598 | O35: =IF(N35>=N34,N35-N34,0) -> 871 | P35: 210739 | Q35: =IF(P35>=P34,P35-P34,0)*30 -> 90 | R35: 702925 | S35: =IF(R35>=R34,R35-R34,0) -> 0 | T35: 344001 | U35: =IF(T35>=T34,T35-T34,0) -> 0 | V35: 93637 | W35: =IF(V35>=V34,V35-V34,0) -> 111 | X35: 173735 | Y35: =IF(X35>=X34,X35-X34,0) -> 188 | Z35: 315108 | AA35: =IF(Z35>=Z34,Z35-Z34,0)*0.53 -> 0 | AB35: 671730 | AC35: =IF(AB35>=AB34,AB35-AB34,0)*0.53 -> 0 | AD35: 798995 | AE35: =IF(AD35>=AD34,AD35-AD34,0)*0.53 -> 294.68 | AF35: 723197 | AG35: =IF(AF35>=AF34,AF35-AF34,0)*0.53 -> 1504.14 | AH35: 217259 | AI35: =IF(AH35>=AH34,AH35-AH34,0)*0.53 -> 506.15 | AJ35: 346878 | AK35: =IF(AJ35>=AJ34,AJ35-AJ34,0)*0.53 -> 2859.35 | AL35: =AA35+AC35+AE35+AG35+AI35+AK35 -> 5164.32 | AM35: 6884605 | AN35: =IF(AM35>=AM34,AM35-AM34,0) -> 24 | AO35: 536213 | AP35: =IF(AO35>=AO34,AO35-AO34,0) -> 1 | AQ35: 881658 | AR35: =IF(AQ35>=AQ34,AQ35-AQ34,0)*0.11 -> 7.48 | AS35: 782391 | AT35: =IF(AS35>=AS34,AS35-AS34,0) -> 22 | AU35: 2161275 | AV35: =IF(AU35>=AU34,AU35-AU34,0) -> 405 | AW35: 195116 | AX35: =IF(AW35>=AW34,AW35-AW34,0) -> 0 | AY35: 16756121 | AZ35: =IF(AY35>=AY34,AY35-AY34,0) -> 2361 | BA35: 20320960 | BB35: =IF(BA35>=BA34,BA35-BA34,0)-(0.6*BG35)-(0.5*BI35)-BK35-BE35 -> 3756.7 | BC35: =AN35+AP35+AR35+AT35+AV35+AX35+AZ35+BB35 -> 6577.18 | BD35: 1323286 | BE35: =IF(BD35>=BD34,BD35-BD34,0) -> 0 | BF35: 3152231 | BG35: =IF(BF35>=BF34,BF35-BF34,0) -> 1013 | BH35: 349120 | BI35: =IF(BH35>=BH34,BH35-BH34,0) -> 85 | BJ35: 399807 | BK35: =IF(BJ35>=BJ34,BJ35-BJ34,0) -> 216 | BL35: =J35+Q35+AL35+BC35 -> 14045.5 | BN35: =IF(BL35>0,BL35/BM35,0) -> #DIV/0! | BP35: =IF(BL35>0,BL35/BO35,0) -> #DIV/0! | BQ35: =BL35*BS1 -> 6460.93 | BR35: =IF(BQ35>0,BQ35/BM35,0) -> #DIV/0! | BS35: =IF(BQ35>0,BQ35/BO35,0) -> #DIV/0!
A36: 31 | J36: =IF(I36>=I35,I36-I35,0) -> 0 | K36: =M36+O36 -> 0 | M36: =IF(L36>=L35,L36-L35,0) -> 0 | O36: =IF(N36>=N35,N36-N35,0) -> 0 | Q36: =IF(P36>=P35,P36-P35,0)*30 -> 0 | R36: 702925 | S36: =IF(R36>=R35,R36-R35,0) -> 0 | T36: 344001 | U36: =IF(T36>=T35,T36-T35,0) -> 0 | W36: =IF(V36>=V35,V36-V35,0) -> 0 | Y36: =IF(X36>=X35,X36-X35,0) -> 0 | Z36: 315108 | AA36: =IF(Z36>=Z35,Z36-Z35,0)*0.53 -> 0 | AC36: =IF(AB36>=AB35,AB36-AB35,0)*0.53 -> 0 | AE36: =IF(AD36>=AD35,AD36-AD35,0)*0.53 -> 0 | AG36: =IF(AF36>=AF35,AF36-AF35,0)*0.53 -> 0 | AI36: =IF(AH36>=AH35,AH36-AH35,0)*0.53 -> 0 | AK36: =IF(AJ36>=AJ35,AJ36-AJ35,0)*0.53 -> 0 | AL36: =AA36+AC36+AE36+AG36+AI36+AK36 -> 0 | AN36: =IF(AM36>=AM35,AM36-AM35,0) -> 0 | AP36: =IF(AO36>=AO35,AO36-AO35,0) -> 0 | AR36: =IF(AQ36>=AQ35,AQ36-AQ35,0)*0.11 -> 0 | AT36: =IF(AS36>=AS35,AS36-AS35,0) -> 0 | AV36: =IF(AU36>=AU35,AU36-AU35,0) -> 0 | AX36: =IF(AW36>=AW35,AW36-AW35,0) -> 0 | AZ36: =IF(AY36>=AY35,AY36-AY35,0) -> 0 | BB36: =IF(BA36>=BA35,BA36-BA35,0)-(0.6*BG36)-(0.5*BI36)-BK36-BE36 -> 0 | BC36: =AN36+AP36+AR36+AT36+AV36+AX36+AZ36+BB36 -> 0 | BD36: 1323286 | BE36: =IF(BD36>=BD35,BD36-BD35,0) -> 0 | BG36: =IF(BF36>=BF35,BF36-BF35,0) -> 0 | BI36: =IF(BH36>=BH35,BH36-BH35,0) -> 0 | BK36: =IF(BJ36>=BJ35,BJ36-BJ35,0) -> 0 | BL36: =J36+Q36+AL36+BC36 -> 0 | BN36: =IF(BL36>0,BL36/BM36,0) -> 0 | BP36: =IF(BL36>0,BL36/BO36,0) -> 0 | BQ36: =BL36*BS1 -> 0 | BR36: =IF(BQ36>0,BQ36/BM36,0) -> 0 | BS36: =IF(BQ36>0,BQ36/BO36,0) -> 0
A37: MTD | C37: =SUM(C9:C35) -> 0 | E37: =SUM(E9:E35) -> 0 | F37: =SUM(F9:F35) -> 0 | G37: =SUM(G9:G35) -> 0 | J37: =SUM(J6:J36) -> 56374 | K37: =SUM(K6:K36) -> 39107 | M37: =SUM(M6:M36) -> 19281 | O37: =SUM(O6:O36) -> 19826 | Q37: =SUM(Q6:Q36) -> 2160 | S37: =SUM(S6:S36) -> 0 | U37: =SUM(U6:U36) -> 0 | W37: =SUM(W6:W36) -> 3736 | Y37: =SUM(Y6:Y36) -> 6068 | AA37: =SUM(AA6:AA36) -> 0 | AC37: =SUM(AC5:AC36) -> 7486.25 | AE37: =SUM(AE6:AE36) -> 37417.47 | AG37: =SUM(AG6:AG36) -> 9747.23 | AI37: =SUM(AI6:AI36) -> 10855.46 | AK37: =SUM(AK6:AK36) -> 61925.73 | AL37: =SUM(AL6:AL36) -> 127432.14 | AN37: =SUM(AN6:AN36) -> 539 | AP37: =SUM(AP6:AP36) -> 58 | AR37: =SUM(AR6:AR36) -> 135.41 | AT37: =SUM(AT6:AT36) -> 915 | AV37: =SUM(AV6:AV36) -> 9833 | AX37: =SUM(AX6:AX36) -> 399 | AZ37: =SUM(AZ6:AZ36) -> 53540 | BB37: =SUM(BB6:BB36) -> 99510.8 | BC37: =SUM(BC6:BC36) -> 164930.21 | BE37: =SUM(BE6:BE36) -> 0 | BG37: =SUM(BG6:BG36) -> 29872 | BI37: =SUM(BI6:BI36) -> 2328 | BK37: =SUM(BK6:BK36) -> 5681 | BL37: =SUM(BL6:BL36) -> 350896.35 | BM37: =SUM(BM6:BM36) -> 0 | BN37: =IF(BL37>0,BL37/BM37,0) -> #DIV/0! | BO37: =SUM(BO6:BO35) -> 0 | BP37: =IF(BL37>0,BL37/BO37,0) -> #DIV/0! | BQ37: =SUM(BQ6:BQ35) -> 161412.32 | BR37: =IF(BQ37>0,BQ37/BM37,0) -> #DIV/0! | BS37: =IF(BQ37>0,BQ37/BO37,0) -> #DIV/0!
A38: AVER. Act | C38: =C37/C47 -> #DIV/0! | E38: =E37/C47 -> #DIV/0! | F38: =F37/C47 -> #DIV/0! | G38: =G37/C47 -> #DIV/0! | J38: =J37/J46 -> 1879.1333 | K38: =K37/J46 -> 1303.5667 | M38: =M37/J46 -> 642.7 | O38: =O37/J46 -> 660.86667 | Q38: =Q37/J46 -> 72 | S38: =S37/J46 -> 0 | U38: =U37/J46 -> 0 | W38: =W37/J46 -> 124.53333 | Y38: =Y37/J46 -> 202.26667 | AA38: =AA37/J46 -> 0 | AE38: =AE37/J46 -> 1247.249 | AG38: =AG37/J46 -> 324.90767 | AI38: =AI37/J46 -> 361.84867 | AK38: =AK37/J46 -> 2064.191 | AL38: =AL37/J46 -> 4247.738 | AN38: =AN37/J46 -> 17.966667 | AP38: =AP37/J46 -> 1.9333333 | AR38: =AR37/J46 -> 4.5136667 | AT38: =AT37/J46 -> 30.5 | AV38: =AV37/J46 -> 327.76667 | AX38: =AX37/J46 -> 13.3 | AZ38: =AZ37/J46 -> 1784.6667 | BB38: =BB37/J46 -> 3317.0267 | BE38: =BE37/J46 -> 0 | BG38: =BG37/J46 -> 995.73333 | BI38: =BI37/J46 -> 77.6 | BK38: =BK37/J46 -> 189.36667 | BL38: =BL37/$J$48 -> #DIV/0! | BM38: =BM37/$J$48 -> #DIV/0! | BN38: =BL38/BM38 -> #DIV/0! | BO38: =BO37/$J$48 -> #DIV/0! | BP38: =BL38/BO38 -> #DIV/0! | BQ38: =BQ37/$J$48 -> #DIV/0! | BR38: =BQ38/BM38 -> #DIV/0! | BS38: =BQ38/BO38 -> #DIV/0!
A39: AVER. Bud | BL39: =(BQ39-($T$1*$BE$2+$T$2))/(0.7*$Q$1+0.3*$Q$2+$BE$1) -> #DIV/0! | BM39: =[2]YTD!AY2341 -> 0 | BN39: =IF(BL39>0,BL39/BM39,0) -> #DIV/0! | BO39: =[2]YTD!AY2342 -> 0 | BP39: =IF(BL39>0,BL39/BO39,0) -> #DIV/0! | BQ39: =[2]YTD!AY2345 -> 0 | BR39: =IF(BQ39>0,BQ39/BM39,0) -> 0 | BS39: =IF(BQ39>0,BQ39/BO39,0) -> 0
A40: Total RFC | BL40: =(BL39/$J$49)*$J$48 -> #DIV/0! | BM40: =BM41*BF48 -> #DIV/0! | BN40: =IF(BL40>0,BL40/BM40,0) -> #DIV/0! | BO40: =BO41*$J$48 -> #DIV/0! | BP40: =IF(BL40>0,BL40/BO40,0) -> #DIV/0! | BQ40: =BQ39/$J$49*BF48 -> #DIV/0! | BR40: =IF(BQ40>0,BQ40/BM40,0) -> #DIV/0! | BS40: =IF(BQ40>0,BQ40/BO40,0) -> #DIV/0!
A41: RFC MTD | BL41: =BL39/$J$49 -> #DIV/0! | BM41: =BM39/$J$49 -> #DIV/0! | BO41: =BO39/$J$49 -> #DIV/0! | BQ41: =BQ39/$J$49 -> #DIV/0!
A42: AVER RFC | BL42: =(BQ42-($T$1*$BE$2+$T$2))/(0.7*$Q$1+0.3*$Q$2+$BE$1) -> #DIV/0! | BM42: =[2]YTD!AY2358 -> 0 | BN42: =IF(BL42>0,BL42/BM42,0) -> #DIV/0! | BO42: =[2]YTD!AY2359 -> 0 | BP42: =IF(BL42>0,BL42/BO42,0) -> #DIV/0! | BQ42: =[2]YTD!AY2362 -> 0 | BR42: =IF(BQ42>0,BQ42/BM42,0) -> 0 | BS42: =IF(BQ42>0,BQ42/BO42,0) -> 0
A43: Tot. Act. 13 | BL43: =(BL42/$J$49)*$J$48 -> #DIV/0! | BM43: =BM42/BF49*BF48 -> #DIV/0! | BN43: =IF(BL43>0,BL43/BM43,0) -> #DIV/0! | BO43: =BO42/BF49*BF48 -> #DIV/0! | BP43: =IF(BL43>0,BL43/BO43,0) -> #DIV/0! | BQ43: =BQ42/BF49*BF48 -> #DIV/0! | BR43: =IF(BQ43>0,BQ43/BM43,0) -> #DIV/0! | BS43: =IF(BQ43>0,BQ43/BO43,0) -> #DIV/0!
A44: Ave. Act. 13 | BL44: =BL42/BF49 -> #DIV/0! | BM44: =BM42/BF49 -> #DIV/0! | BO44: =BO42/BF49 -> #DIV/0! | BQ44: =BQ42/BF49 -> #DIV/0!
A45: Accounting Readings | I45: =IF(I33>0,I33,0) -> 20955210 | BL45: =[2]Consp!AJ33 -> 8688.15 | BN45: =[2]Consp!CF33 -> 0 | BP45: =[2]Consp!CG33 -> 0 | BQ45: =[2]Consp!CH33 -> 0 | BR45: =[2]Consp!CI33 -> 0 | BS45: =[2]Consp!CJ33 -> 0
A46: No of Days MTD | J46: =COUNTIF(I6:I35,">0") -> 30 | BL46: =[2]Consp!AJ34 -> 310.29107 | BN46: =[2]Consp!CF34 -> 0 | BP46: =[2]Consp!CG34 -> 0 | BQ46: =[2]Consp!CH34 -> 0 | BR46: =[2]Consp!CI34 -> 0 | BS46: =[2]Consp!CJ34 -> 0
A47: No of Days month | J47: =COUNTIF(A6:A35,">0") -> 30
I56: =-L11 -> -642761

Sheet Water
A1: =Elect!A1 -> April | T1: Main Water UP | V1: 4 | W1: Water Truck UP
A3: Day | E3: Water Incoming | I3: New casino | N3: Rooms Consumption | P3: Public Areas consumption | R3: Swimming pool | T3: No. of rooms | U3: Cons. Per occ. room | V3: No. of guest | W3: Cons. Per guest | X3: Total cost | Y3: L.E\ | Z3: L.E\
B4: Main water meter 1 | D4: Main water meter 2 | F4: Main water meter 3 | H4: Total Inc. | I4: Hot water | K4: Cold water | N4: Express Riser | O4: Consp. | P4: Read. | Q4: Cons. | R4: Read. | S4: Cons. | Y4: Room | Z4: Guest
B5: Counter | C5: Produc 58% | D5: Counter | E5: Produc 58% | F5: Counter | G5: Produc 58% | I5: Counter | K5: Counter
B6: 73894 | C6: =IF(B6>=B5,B6-B5,0)*10*0.58 -> 0 | D6: 145828 | E6: =IF(D6>=D5,D6-D5,0)*10*0.58 -> 0 | F6: 15966 | G6: =IF(F6>=F5,F6-F5,0)*0.58 -> 0 | I6: 194 | K6: 2443
A7: 1 | B7: 73901 | C7: =IF(B7>=B6,B7-B6,0)*10*0.58 -> 40.6 | D7: 145830 | E7: =IF(D7>=D6,D7-D6,0)*10*0.58 -> 11.6 | F7: 15966 | G7: =IF(F7>=F6,F7-F6,0)*0.58 -> 0 | H7: =C7+E7+G7 -> 52.2 | O7: =IF(N7>=N6,N7-N6,0) -> 0 | Q7: =(H7-O7)*0.58 -> 30.276 | S7: =IF(R7-R6>0,R7-R6,0) -> 0 | T7: =Elect!BM6 -> 0 | U7: =H7/T7 -> #DIV/0! | V7: =Elect!BO6 -> 0 | W7: =H7/V7 -> #DIV/0! | X7: =H7*V1 -> 208.8 | Y7: =IF(X7>0,X7/T7,0) -> #DIV/0! | Z7: 0
A8: 2 | B8: 73924 | C8: =IF(B8>=B7,B8-B7,0)*10*0.58 -> 133.4 | D8: 145831 | E8: =IF(D8>=D7,D8-D7,0)*10*0.58 -> 5.8 | F8: 15966 | G8: =IF(F8>=F7,F8-F7,0)*0.58 -> 0 | H8: =C8+E8+G8 -> 139.2 | O8: =IF(N8>=N7,N8-N7,0) -> 0 | Q8: =(H8-O8)*0.58 -> 80.736 | S8: =IF(R8-R7>0,R8-R7,0) -> 0 | T8: =Elect!BM7 -> 0 | U8: =H8/T8 -> #DIV/0! | V8: =Elect!BO7 -> 0 | W8: =H8/V8 -> #DIV/0! | X8: =H8*V1 -> 556.8 | Y8: =IF(X8>0,X8/T8,0) -> #DIV/0! | Z8: =IF(X8>0,X8/V8,0) -> #DIV/0!
A9: 3 | B9: 73940 | C9: =IF(B9>=B8,B9-B8,0)*10*0.58 -> 92.8 | D9: 145838 | E9: =IF(D9>=D8,D9-D8,0)*10*0.58 -> 40.6 | F9: 15966 | G9: =IF(F9>=F8,F9-F8,0)*0.58 -> 0 | H9: =C9+E9+G9 -> 133.4 | O9: =IF(N9>=N8,N9-N8,0) -> 0 | Q9: =(H9-O9)*0.58 -> 77.372 | S9: =IF(R9-R8>0,R9-R8,0) -> 0 | T9: =Elect!BM8 -> 0 | U9: =H9/T9 -> #DIV/0! | V9: =Elect!BO8 -> 0 | W9: =H9/V9 -> #DIV/0! | X9: =H9*V1 -> 533.6 | Y9: =IF(X9>0,X9/T9,0) -> #DIV/0! | Z9: =IF(X9>0,X9/V9,0) -> #DIV/0!
A10: 4 | B10: 73980 | C10: =IF(B10>=B9,B10-B9,0)*10*0.58 -> 232 | D10: 145840 | E10: =IF(D10>=D9,D10-D9,0)*10*0.58 -> 11.6 | F10: 15966 | G10: =IF(F10>=F9,F10-F9,0)*0.58 -> 0 | H10: =C10+E10+G10 -> 243.6 | O10: =IF(N10>=N9,N10-N9,0) -> 0 | Q10: =(H10-O10)*0.58 -> 141.288 | S10: =IF(R10-R9>0,R10-R9,0) -> 0 | T10: =Elect!BM9 -> 0 | U10: =H10/T10 -> #DIV/0! | V10: =Elect!BO9 -> 0 | W10: =H10/V10 -> #DIV/0! | X10: =H10*V1 -> 974.4 | Y10: =IF(X10>0,X10/T10,0) -> #DIV/0! | Z10: =IF(X10>0,X10/V10,0) -> #DIV/0!
A11: 5 | B11: 73994 | C11: =IF(B11>=B10,B11-B10,0)*10*0.58 -> 81.2 | D11: 145851 | E11: =IF(D11>=D10,D11-D10,0)*10*0.58 -> 63.8 | F11: 15966 | G11: =IF(F11>=F10,F11-F10,0)*0.58 -> 0 | H11: =C11+E11+G11 -> 145 | O11: =IF(N11>=N10,N11-N10,0) -> 0 | Q11: =(H11-O11)*0.58 -> 84.1 | S11: =IF(R11-R10>0,R11-R10,0) -> 0 | T11: =Elect!BM10 -> 0 | U11: =H11/T11 -> #DIV/0! | V11: =Elect!BO10 -> 0 | W11: =H11/V11 -> #DIV/0! | X11: =H11*V1 -> 580 | Y11: =IF(X11>0,X11/T11,0) -> #DIV/0! | Z11: =IF(X11>0,X11/V11,0) -> #DIV/0!
A12: 6 | B12: 74002 | C12: =IF(B12>=B11,B12-B11,0)*10*0.58 -> 46.4 | D12: 145859 | E12: =IF(D12>=D11,D12-D11,0)*10*0.58 -> 46.4 | F12: 15966 | G12: =IF(F12>=F11,F12-F11,0)*0.58 -> 0 | H12: =C12+E12+G12 -> 92.8 | O12: =IF(N12>=N11,N12-N11,0) -> 0 | Q12: =(H12-O12)*0.58 -> 53.824 | S12: =IF(R12-R11>0,R12-R11,0) -> 0 | T12: =Elect!BM11 -> 0 | U12: =H12/T12 -> #DIV/0! | V12: =Elect!BO11 -> 0 | W12: =H12/V12 -> #DIV/0! | X12: =H12*V1 -> 371.2 | Y12: =IF(X12>0,X12/T12,0) -> #DIV/0! | Z12: =IF(X12>0,X12/V12,0) -> #DIV/0!
A13: 7 | B13: 74014 | C13: =IF(B13>=B12,B13-B12,0)*10*0.58 -> 69.6 | D13: 145864 | E13: =IF(D13>=D12,D13-D12,0)*10*0.58 -> 29 | F13: 15966 | G13: =IF(F13>=F12,F13-F12,0)*0.58 -> 0 | H13: =C13+E13+G13 -> 98.6 | O13: =IF(N13>=N12,N13-N12,0) -> 0 | Q13: =(H13-O13)*0.58 -> 57.188 | S13: =IF(R13-R12>0,R13-R12,0) -> 0 | T13: =Elect!BM12 -> 0 | U13: =H13/T13 -> #DIV/0! | V13: =Elect!BO12 -> 0 | W13: =H13/V13 -> #DIV/0! | X13: =H13*V1 -> 394.4 | Y13: =IF(X13>0,X13/T13,0) -> #DIV/0! | Z13: =IF(X13>0,X13/V13,0) -> #DIV/0!
A14: 8 | B14: 74027 | C14: =IF(B14>=B13,B14-B13,0)*10*0.58 -> 75.4 | D14: 145871 | E14: =IF(D14>=D13,D14-D13,0)*10*0.58 -> 40.6 | F14: 15966 | G14: =IF(F14>=F13,F14-F13,0)*0.58 -> 0 | H14: =C14+E14+G14 -> 116 | O14: =IF(N14>=N13,N14-N13,0) -> 0 | Q14: =(H14-O14)*0.58 -> 67.28 | S14: =IF(R14-R13>0,R14-R13,0) -> 0 | T14: =Elect!BM13 -> 0 | U14: =H14/T14 -> #DIV/0! | V14: =Elect!BO13 -> 0 | W14: =H14/V14 -> #DIV/0! | X14: =H14*V1 -> 464 | Y14: =IF(X14>0,X14/T14,0) -> #DIV/0! | Z14: =IF(X14>0,X14/V14,0) -> #DIV/0!
A15: 9 | B15: 74044 | C15: =IF(B15>=B14,B15-B14,0)*10*0.58 -> 98.6 | D15: 145877 | E15: =IF(D15>=D14,D15-D14,0)*10*0.58 -> 34.8 | F15: 15966 | G15: =IF(F15>=F14,F15-F14,0)*0.58 -> 0 | H15: =C15+E15+G15 -> 133.4 | O15: =IF(N15>=N14,N15-N14,0) -> 0 | Q15: =(H15-O15)*0.58 -> 77.372 | S15: =IF(R15-R14>0,R15-R14,0) -> 0 | T15: =Elect!BM14 -> 0 | U15: =H15/T15 -> #DIV/0! | V15: =Elect!BO14 -> 0 | W15: =H15/V15 -> #DIV/0! | X15: =H15*V1 -> 533.6 | Y15: =IF(X15>0,X15/T15,0) -> #DIV/0! | Z15: =IF(X15>0,X15/V15,0) -> #DIV/0!
A16: 10 | B16: 74049 | C16: =IF(B16>=B15,B16-B15,0)*10*0.58 -> 29 | D16: 145880 | E16: =IF(D16>=D15,D16-D15,0)*10*0.58 -> 17.4 | F16: 15980 | G16: =IF(F16>=F15,F16-F15,0)*0.58 -> 8.12 | H16: =C16+E16+G16 -> 54.52 | O16: =IF(N16>=N15,N16-N15,0) -> 0 | Q16: =(H16-O16)*0.58 -> 31.6216 | S16: =IF(R16-R15>0,R16-R15,0) -> 0 | T16: =Elect!BM15 -> 0 | U16: =H16/T16 -> #DIV/0! | V16: =Elect!BO15 -> 0 | W16: =H16/V16 -> #DIV/0! | X16: =H16*V1 -> 218.08 | Y16: =IF(X16>0,X16/T16,0) -> #DIV/0! | Z16: =IF(X16>0,X16/V16,0) -> #DIV/0!
A17: 11 | B17: 74057 | C17: =IF(B17>=B16,B17-B16,0)*10*0.58 -> 46.4 | D17: 145885 | E17: =IF(D17>=D16,D17-D16,0)*10*0.58 -> 29 | F17: 15989 | G17: =IF(F17>=F16,F17-F16,0)*0.58 -> 5.22 | H17: =C17+E17+G17 -> 80.62 | O17: =IF(N17>=N16,N17-N16,0) -> 0 | Q17: =(H17-O17)*0.58 -> 46.7596 | S17: =IF(R17-R16>0,R17-R16,0) -> 0 | T17: =Elect!BM16 -> 0 | U17: =H17/T17 -> #DIV/0! | V17: =Elect!BO16 -> 0 | W17: =H17/V17 -> #DIV/0! | X17: =H17*V1 -> 322.48 | Y17: =IF(X17>0,X17/T17,0) -> #DIV/0! | Z17: =IF(X17>0,X17/V17,0) -> #DIV/0!
A18: 12 | B18: 74064 | C18: =IF(B18>=B17,B18-B17,0)*10*0.58 -> 40.6 | D18: 145890 | E18: =IF(D18>=D17,D18-D17,0)*10*0.58 -> 29 | F18: 16002 | G18: =IF(F18>=F17,F18-F17,0)*0.58 -> 7.54 | H18: =C18+E18+G18 -> 77.14 | O18: =IF(N18>=N17,N18-N17,0) -> 0 | Q18: =(H18-O18)*0.58 -> 44.7412 | S18: =IF(R18-R17>0,R18-R17,0) -> 0 | T18: =Elect!BM17 -> 0 | U18: =H18/T18 -> #DIV/0! | V18: =Elect!BO17 -> 0 | W18: =H18/V18 -> #DIV/0! | X18: =H18*V1 -> 308.56 | Y18: =IF(X18>0,X18/T18,0) -> #DIV/0! | Z18: =IF(X18>0,X18/V18,0) -> #DIV/0!
A19: 13 | B19: 74075 | C19: =IF(B19>=B18,B19-B18,0)*10*0.58 -> 63.8 | D19: 145898 | E19: =IF(D19>=D18,D19-D18,0)*10*0.58 -> 46.4 | F19: 16014 | G19: =IF(F19>=F18,F19-F18,0)*0.58 -> 6.96 | H19: =C19+E19+G19 -> 117.16 | O19: =IF(N19>=N18,N19-N18,0) -> 0 | Q19: =(H19-O19)*0.58 -> 67.9528 | S19: =IF(R19-R18>0,R19-R18,0) -> 0 | T19: =Elect!BM18 -> 0 | U19: =H19/T19 -> #DIV/0! | V19: =Elect!BO18 -> 0 | W19: =H19/V19 -> #DIV/0! | X19: =H19*V1 -> 468.64 | Y19: =IF(X19>0,X19/T19,0) -> #DIV/0! | Z19: =IF(X19>0,X19/V19,0) -> #DIV/0!
A20: 14 | B20: 74082 | C20: =IF(B20>=B19,B20-B19,0)*10*0.58 -> 40.6 | D20: 145903 | E20: =IF(D20>=D19,D20-D19,0)*10*0.58 -> 29 | F20: 16027 | G20: =IF(F20>=F19,F20-F19,0)*0.58 -> 7.54 | H20: =C20+E20+G20 -> 77.14 | O20: =IF(N20>=N19,N20-N19,0) -> 0 | Q20: =(H20-O20)*0.58 -> 44.7412 | S20: =IF(R20-R19>0,R20-R19,0) -> 0 | T20: =Elect!BM19 -> 0 | U20: =H20/T20 -> #DIV/0! | V20: =Elect!BO19 -> 0 | W20: =H20/V20 -> #DIV/0! | X20: =H20*V1 -> 308.56 | Y20: =IF(X20>0,X20/T20,0) -> #DIV/0! | Z20: =IF(X20>0,X20/V20,0) -> #DIV/0!
A21: 15 | B21: 74091 | C21: =IF(B21>=B20,B21-B20,0)*10*0.58 -> 52.2 | D21: 145912 | E21: =IF(D21>=D20,D21-D20,0)*10*0.58 -> 52.2 | F21: 16034 | G21: =IF(F21>=F20,F21-F20,0)*0.58 -> 4.06 | H21: =C21+E21+G21 -> 108.46 | O21: =IF(N21>=N20,N21-N20,0) -> 0 | Q21: =(H21-O21)*0.58 -> 62.9068 | S21: =IF(R21-R20>0,R21-R20,0) -> 0 | T21: =Elect!BM20 -> 0 | U21: =H21/T21 -> #DIV/0! | V21: =Elect!BO20 -> 0 | W21: =H21/V21 -> #DIV/0! | X21: =H21*V1 -> 433.84 | Y21: =IF(X21>0,X21/T21,0) -> #DIV/0! | Z21: =IF(X21>0,X21/V21,0) -> #DIV/0!
A22: 16 | B22: 74097 | C22: =IF(B22>=B21,B22-B21,0)*10*0.58 -> 34.8 | D22: 145919 | E22: =IF(D22>=D21,D22-D21,0)*10*0.58 -> 40.6 | F22: 16040 | G22: =IF(F22>=F21,F22-F21,0)*0.58 -> 3.48 | H22: =C22+E22+G22 -> 78.88 | O22: =IF(N22>=N21,N22-N21,0) -> 0 | Q22: =(H22-O22)*0.58 -> 45.7504 | S22: =IF(R22-R21>0,R22-R21,0) -> 0 | T22: =Elect!BM21 -> 0 | U22: =H22/T22 -> #DIV/0! | V22: =Elect!BO21 -> 0 | W22: =H22/V22 -> #DIV/0! | X22: =H22*V1 -> 315.52 | Y22: =IF(X22>0,X22/T22,0) -> #DIV/0! | Z22: =IF(X22>0,X22/V22,0) -> #DIV/0!
A23: 17 | B23: 74100 | C23: =IF(B23>=B22,B23-B22,0)*10*0.58 -> 17.4 | D23: 145925 | E23: =IF(D23>=D22,D23-D22,0)*10*0.58 -> 34.8 | F23: 16042 | G23: =IF(F23>=F22,F23-F22,0)*0.58 -> 1.16 | H23: =C23+E23+G23 -> 53.36 | O23: =IF(N23>=N22,N23-N22,0) -> 0 | Q23: =(H23-O23)*0.58 -> 30.9488 | S23: =IF(R23-R22>0,R23-R22,0) -> 0 | T23: =Elect!BM22 -> 0 | U23: =H23/T23 -> #DIV/0! | V23: =Elect!BO22 -> 0 | W23: =H23/V23 -> #DIV/0! | X23: =H23*V1 -> 213.44 | Y23: =IF(X23>0,X23/T23,0) -> #DIV/0! | Z23: =IF(X23>0,X23/V23,0) -> #DIV/0!
A24: 18 | B24: 74106 | C24: =IF(B24>=B23,B24-B23,0)*10*0.58 -> 34.8 | D24: 145930 | E24: =IF(D24>=D23,D24-D23,0)*10*0.58 -> 29 | F24: 16046 | G24: =IF(F24>=F23,F24-F23,0)*0.58 -> 2.32 | H24: =C24+E24+G24 -> 66.12 | O24: =IF(N24>=N23,N24-N23,0) -> 0 | Q24: =(H24-O24)*0.58 -> 38.3496 | S24: =IF(R24-R23>0,R24-R23,0) -> 0 | T24: =Elect!BM23 -> 0 | U24: =H24/T24 -> #DIV/0! | V24: =Elect!BO23 -> 0 | W24: =H24/V24 -> #DIV/0! | X24: =H24*V1 -> 264.48 | Y24: =IF(X24>0,X24/T24,0) -> #DIV/0! | Z24: =IF(X24>0,X24/V24,0) -> #DIV/0!
A25: 19 | B25: 74108 | C25: =IF(B25>=B24,B25-B24,0)*10*0.58 -> 11.6 | D25: 145939 | E25: =IF(D25>=D24,D25-D24,0)*10*0.58 -> 52.2 | F25: 16046 | G25: =IF(F25>=F24,F25-F24,0)*0.58 -> 0 | H25: =C25+E25+G25 -> 63.8 | O25: =IF(N25>=N24,N25-N24,0) -> 0 | Q25: =(H25-O25)*0.58 -> 37.004 | S25: =IF(R25-R24>0,R25-R24,0) -> 0 | T25: =Elect!BM24 -> 0 | U25: =H25/T25 -> #DIV/0! | V25: =Elect!BO24 -> 0 | W25: =H25/V25 -> #DIV/0! | X25: =H25*V1 -> 255.2 | Y25: =IF(X25>0,X25/T25,0) -> #DIV/0! | Z25: =IF(X25>0,X25/V25,0) -> #DIV/0!
A26: 20 | B26: 74110 | C26: =IF(B26>=B25,B26-B25,0)*10*0.58 -> 11.6 | D26: 145941 | E26: =IF(D26>=D25,D26-D25,0)*10*0.58 -> 11.6 | F26: 16047 | G26: =IF(F26>=F25,F26-F25,0)*0.58 -> 0.58 | H26: =C26+E26+G26 -> 23.78 | O26: =IF(N26>=N25,N26-N25,0) -> 0 | Q26: =(H26-O26)*0.58 -> 13.7924 | S26: =IF(R26-R25>0,R26-R25,0) -> 0 | T26: =Elect!BM25 -> 0 | U26: =H26/T26 -> #DIV/0! | V26: =Elect!BO25 -> 0 | W26: =H26/V26 -> #DIV/0! | X26: =H26*V1 -> 95.12 | Y26: =IF(X26>0,X26/T26,0) -> #DIV/0! | Z26: =IF(X26>0,X26/V26,0) -> #DIV/0!
A27: 21 | B27: 74111 | C27: =IF(B27>=B26,B27-B26,0)*10*0.58 -> 5.8 | D27: 145942 | E27: =IF(D27>=D26,D27-D26,0)*10*0.58 -> 5.8 | F27: 16047 | G27: =IF(F27>=F26,F27-F26,0)*0.58 -> 0 | H27: =C27+E27+G27 -> 11.6 | O27: =IF(N27>=N26,N27-N26,0) -> 0 | Q27: =(H27-O27)*0.58 -> 6.728 | S27: =IF(R27-R26>0,R27-R26,0) -> 0 | T27: =Elect!BM26 -> 0 | U27: =H27/T27 -> #DIV/0! | V27: =Elect!BO26 -> 0 | W27: =H27/V27 -> #DIV/0! | X27: =H27*V1 -> 46.4 | Y27: =IF(X27>0,X27/T27,0) -> #DIV/0! | Z27: =IF(X27>0,X27/V27,0) -> #DIV/0!
A28: 22 | B28: 74112 | C28: =IF(B28>=B27,B28-B27,0)*10*0.58 -> 5.8 | D28: 145945 | E28: =IF(D28>=D27,D28-D27,0)*10*0.58 -> 17.4 | F28: 16047 | G28: =IF(F28>=F27,F28-F27,0)*0.58 -> 0 | H28: =C28+E28+G28 -> 23.2 | O28: =IF(N28>=N27,N28-N27,0) -> 0 | Q28: =(H28-O28)*0.58 -> 13.456 | S28: =IF(R28-R27>0,R28-R27,0) -> 0 | T28: =Elect!BM27 -> 0 | U28: =H28/T28 -> #DIV/0! | V28: =Elect!BO27 -> 0 | W28: =H28/V28 -> #DIV/0! | X28: =H28*V1 -> 92.8 | Y28: =IF(X28>0,X28/T28,0) -> #DIV/0! | Z28: =IF(X28>0,X28/V28,0) -> #DIV/0!
A29: 23 | B29: 74112 | C29: =IF(B29>=B28,B29-B28,0)*10*0.58 -> 0 | D29: 145973 | E29: =IF(D29>=D28,D29-D28,0)*10*0.58 -> 162.4 | F29: 16047 | G29: =IF(F29>=F28,F29-F28,0)*0.58 -> 0 | H29: =C29+E29+G29 -> 162.4 | O29: =IF(N29>=N28,N29-N28,0) -> 0 | Q29: =(H29-O29)*0.58 -> 94.192 | S29: =IF(R29-R28>0,R29-R28,0) -> 0 | T29: =Elect!BM28 -> 0 | U29: =H29/T29 -> #DIV/0! | V29: =Elect!BO28 -> 0 | W29: =H29/V29 -> #DIV/0! | X29: =H29*V1 -> 649.6 | Y29: =IF(X29>0,X29/T29,0) -> #DIV/0! | Z29: =IF(X29>0,X29/V29,0) -> #DIV/0!
A30: 24 | B30: 74112 | C30: =IF(B30>=B29,B30-B29,0)*10*0.58 -> 0 | D30: 145985 | E30: =IF(D30>=D29,D30-D29,0)*10*0.58 -> 69.6 | F30: 16047 | G30: =IF(F30>=F29,F30-F29,0)*0.58 -> 0 | H30: =C30+E30+G30 -> 69.6 | O30: =IF(N30>=N29,N30-N29,0) -> 0 | Q30: =(H30-O30)*0.58 -> 40.368 | S30: =IF(R30-R29>0,R30-R29,0) -> 0 | T30: =Elect!BM29 -> 0 | U30: =H30/T30 -> #DIV/0! | V30: =Elect!BO29 -> 0 | W30: =H30/V30 -> #DIV/0! | X30: =H30*V1 -> 278.4 | Y30: =IF(X30>0,X30/T30,0) -> #DIV/0! | Z30: =IF(X30>0,X30/V30,0) -> #DIV/0!
A31: 25 | B31: 74112 | C31: =IF(B31>=B30,B31-B30,0)*10*0.58 -> 0 | D31: 145999 | E31: =IF(D31>=D30,D31-D30,0)*10*0.58 -> 81.2 | F31: 16047 | G31: =IF(F31>=F30,F31-F30,0)*0.58 -> 0 | H31: =C31+E31+G31 -> 81.2 | O31: =IF(N31>=N30,N31-N30,0) -> 0 | Q31: =(H31-O31)*0.58 -> 47.096 | S31: =IF(R31-R30>0,R31-R30,0) -> 0 | T31: =Elect!BM30 -> 0 | U31: =H31/T31 -> #DIV/0! | V31: =Elect!BO30 -> 0 | W31: =H31/V31 -> #DIV/0! | X31: =H31*V1 -> 324.8 | Y31: =IF(X31>0,X31/T31,0) -> #DIV/0! | Z31: =IF(X31>0,X31/V31,0) -> #DIV/0!
A32: 26 | B32: 74113 | C32: =IF(B32>=B31,B32-B31,0)*10*0.58 -> 5.8 | D32: 146015 | E32: =IF(D32>=D31,D32-D31,0)*10*0.58 -> 92.8 | F32: 16047 | G32: =IF(F32>=F31,F32-F31,0)*0.58 -> 0 | H32: =C32+E32+G32 -> 98.6 | O32: =IF(N32>=N31,N32-N31,0) -> 0 | Q32: =(H32-O32)*0.58 -> 57.188 | S32: =IF(R32-R31>0,R32-R31,0) -> 0 | T32: =Elect!BM31 -> 0 | U32: =H32/T32 -> #DIV/0! | V32: =Elect!BO31 -> 0 | W32: =H32/V32 -> #DIV/0! | X32: =H32*V1 -> 394.4 | Y32: =IF(X32>0,X32/T32,0) -> #DIV/0! | Z32: =IF(X32>0,X32/V32,0) -> #DIV/0!
A33: 27 | B33: 74113 | C33: =IF(B33>=B32,B33-B32,0)*10*0.58 -> 0 | D33: 146028 | E33: =IF(D33>=D32,D33-D32,0)*10*0.58 -> 75.4 | F33: 16047 | G33: =IF(F33>=F32,F33-F32,0)*0.58 -> 0 | H33: =C33+E33+G33 -> 75.4 | O33: =IF(N33>=N32,N33-N32,0) -> 0 | Q33: =(H33-O33)*0.58 -> 43.732 | S33: =IF(R33-R32>0,R33-R32,0) -> 0 | T33: =Elect!BM32 -> 0 | U33: =H33/T33 -> #DIV/0! | V33: =Elect!BO32 -> 0 | W33: =H33/V33 -> #DIV/0! | X33: =H33*V1 -> 301.6 | Y33: =IF(X33>0,X33/T33,0) -> #DIV/0! | Z33: =IF(X33>0,X33/V33,0) -> #DIV/0!
A34: 28 | B34: 74114 | C34: =IF(B34>=B33,B34-B33,0)*10*0.58 -> 5.8 | D34: 146039 | E34: =IF(D34>=D33,D34-D33,0)*10*0.58 -> 63.8 | F34: 16047 | G34: =IF(F34>=F33,F34-F33,0)*0.58 -> 0 | H34: =C34+E34+G34 -> 69.6 | O34: =IF(N34>=N33,N34-N33,0) -> 0 | Q34: =(H34-O34)*0.58 -> 40.368 | S34: =IF(R34-R33>0,R34-R33,0) -> 0 | T34: =Elect!BM33 -> 0 | U34: =H34/T34 -> #DIV/0! | V34: =Elect!BO33 -> 0 | W34: =H34/V34 -> #DIV/0! | X34: =H34*V1 -> 278.4 | Y34: =IF(X34>0,X34/T34,0) -> #DIV/0! | Z34: =IF(X34>0,X34/V34,0) -> #DIV/0!
A35: 29 | B35: 74115 | C35: =IF(B35>=B34,B35-B34,0)*10*0.58 -> 5.8 | D35: 146046 | E35: =IF(D35>=D34,D35-D34,0)*10*0.58 -> 40.6 | F35: 16047 | G35: =IF(F35>=F34,F35-F34,0)*0.58 -> 0 | H35: =C35+E35+G35 -> 46.4 | O35: =IF(N35>=N34,N35-N34,0) -> 0 | Q35: =(H35-O35)*0.58 -> 26.912 | S35: =IF(R35-R34>0,R35-R34,0) -> 0 | T35: =Elect!BM34 -> 0 | U35: =H35/T35 -> #DIV/0! | V35: =Elect!BO34 -> 0 | W35: =H35/V35 -> #DIV/0! | X35: =H35*V1 -> 185.6 | Y35: =IF(X35>0,X35/T35,0) -> #DIV/0! | Z35: =IF(X35>0,X35/V35,0) -> #DIV/0!
A36: 30 | B36: 74116 | C36: =IF(B36>=B35,B36-B35,0)*10*0.58 -> 5.8 | D36: 146053 | E36: =IF(D36>=D35,D36-D35,0)*10*0.58 -> 40.6 | F36: 16047 | G36: =IF(F36>=F35,F36-F35,0)*0.58 -> 0 | H36: =C36+E36+G36 -> 46.4 | I36: 200 | K36: 2518 | O36: =IF(N36>=N35,N36-N35,0) -> 0 | Q36: =(H36-O36)*0.58 -> 26.912 | S36: =IF(R36-R35>0,R36-R35,0) -> 0 | T36: =Elect!BM35 -> 0 | U36: =H36/T36 -> #DIV/0! | V36: =Elect!BO35 -> 0 | W36: =H36/V36 -> #DIV/0! | X36: =H36*V1 -> 185.6 | Y36: =IF(X36>0,X36/T36,0) -> #DIV/0! | Z36: =IF(X36>0,X36/V36,0) -> #DIV/0!
A37: 31 | C37: =IF(B37>=B36,B37-B36,0)*10*0.58 -> 0 | E37: =IF(D37>=D36,D37-D36,0)*10*0.58 -> 0 | G37: =IF(F37>=F36,F37-F36,0)*0.58 -> 0 | H37: =C37+E37+G37 -> 0 | O37: =IF(N37>=N36,N37-N36,0) -> 0 | Q37: =(H37-O37)*0.58 -> 0 | S37: =IF(R37-R36>0,R37-R36,0) -> 0 | T37: =Elect!BM36 -> 0 | U37: =H37/T37 -> #DIV/0! | V37: =Elect!BO36 -> 0 | W37: =H37/V37 -> #DIV/0! | X37: =H37*V7 -> 0 | Y37: =IF(X37>0,X37/T37,0) -> 0 | Z37: =IF(X37>0,X37/V37,0) -> 0
A38: MTD | C38: =SUM(C7:C37) -> 1287.6 | E38: =SUM(E7:E37) -> 1305 | G38: =SUM(G7:G37) -> 46.98 | H38: =SUM(H7:H37) -> 2639.58 | I38: =I37-I6 -> -194 | K38: =K37-K6 -> -2443 | O38: =SUM(O7:O36) -> 0 | Q38: =SUM(Q7:Q34) -> 1477.1324 | S38: =SUM(S7:S34) -> 0 | T38: =SUM(T7:T36) -> 0 | U38: =IF(H38>0,H38/T38,0) -> #DIV/0! | V38: =SUM(V7:V36) -> 0 | W38: =IF(H38>0,H38/V38,0) -> #DIV/0! | X38: =SUM(X7:X36) -> 10558.32 | Y38: =IF(X38>0,X38/T38,0) -> #DIV/0! | Z38: =IF(X38>0,X38/V38,0) -> #DIV/0!
A39: AVER. Act | C39: =C38/B49 -> 41.535484 | E39: =E38/B49 -> 42.096774 | G39: =G38/B49 -> 1.5154839 | H39: =H38/B49 -> 85.147742 | O39: =O38/B49 -> 0 | Q39: =Q38/B49 -> 47.649432 | S39: =S38/C49 -> #DIV/0! | T39: =T38/B49 -> 0 | U39: =IF(H39>0,H39/T39,0) -> #DIV/0! | V39: =V38/B49 -> 0 | W39: =IF(H39>0,H39/V39,0) -> #DIV/0! | X39: =X38/B49 -> 340.59097 | Y39: =IF(X39>0,X39/T39,0) -> #DIV/0! | Z39: =IF(X39>0,X39/V39,0) -> #DIV/0!
A40: TOTAL Budget | T40: =YTD!Q2341 -> 0 | U40: =IF(#REF!>0,#REF!/T40,0) -> #REF! | V40: =YTD!Q2342 -> 0 | W40: =IF(#REF!>0,#REF!/V40,0) -> #REF! | X40: =YTD!Q2346 -> 0 | Y40: =IF(X40>0,X40/T40,0) -> 0 | Z40: =IF(X40>0,X40/V40,0) -> 0
A41: Budget MTD | T41: =T42*C49 -> #VALUE! | U41: =IF(#REF!>0,#REF!/T41,0) -> #REF! | V41: =V42*C49 -> #VALUE! | W41: =IF(#REF!>0,#REF!/V41,0) -> #REF! | X41: =#REF!*5.62 -> #REF! | Y41: =IF(X41>0,X41/T41,0) -> #REF! | Z41: =IF(X41>0,X41/V41,0) -> #REF!
A42: AVER. Bud | T42: =T40/$A$49 -> #VALUE! | V42: =V40/$A$49 -> #VALUE!
A43: Total RFC | T43: =YTD!Q2358 -> 0 | V43: =YTD!Q2359 -> 0 | X43: =YTD!Q2363 -> 0 | Y43: =IF(X43>0,X43/T43,0) -> 0 | Z43: =IF(X43>0,X43/V43,0) -> 0
A44: RFC MTD | T44: =T43/A49*C49 -> #VALUE! | V44: =V43/A49*C49 -> #VALUE! | X44: =X43/A49*C49 -> #VALUE! | Y44: =IF(X44>0,X44/T44,0) -> #VALUE! | Z44: =IF(X44>0,X44/V44,0) -> #VALUE!
A45: AVER RFC | T45: =T43/A49 -> #VALUE! | V45: =V44/A49*C49 -> #VALUE! | X45: =X43/A49 -> #VALUE!
A46: MTD 13 | U46: =Consp!BH33 -> 1.1514679 | W46: =Consp!BI33 -> 0.57929342 | X46: =Consp!BJ33 -> 140121.3 | Y46: =Consp!BK33 -> 6.8331854 | Z46: =Consp!BL33 -> 3.4377159
A47: AVER. Act 13 | U47: =Consp!BH34 -> 1.1761372 | W47: =Consp!BI34 -> 0.60007377 | X47: =Consp!BJ34 -> 5004.3322 | Y47: =Consp!BK34 -> 6.8331854 | Z47: =Consp!BL34 -> 3.4377159
A48: Accounting Readings | B48: =B34 -> 74114 | D48: =D34 -> 146039 | F48: =F34 -> 16047
A49: No of Days MTD | B49: 31
C54: 82183
C55: 82221
C56: 82259 | O56: 45480
C57: 82297 | O57: 45514
C58: 82329 | O58: 45539
C59: 82385
C60: 82405 | O60: 45607
C61: 82430 | O61: 45637
C62: 82500 | O62: 45668
C63: 82590 | O63: 45694
C64: 82607.333 | O64: 1
A150: Water Incoming

Sheet Gas
A1: =Elect!A1 -> April | E1: Gas | H1: Gas UP | J1: 1.61
A4: NO. | B4: Main Gas Flow Meter | D4: Laundry Gas Flow Meter | F4: Grumandiz Gas Flow Meter | H4: Plant Room Gas Share Cost | I4: Hotel Consumption Cost | J4: La Grumandiz Cost | K4: Total Natural Gas Consumption
B5: Read | C5: Cons | D5: Read | E5: Cons | F5: Read | G5: Cons | H5: LE/DAY | I5: LE/DAY | J5: LE/DAY | K5: Cons
B6: 7832714 | C6: =IF(B6>=B5,B6-B5,0)*1.06 -> 0 | D6: 231501 | E6: =IF(D6>=D5,D6-D5,0)*0.7 -> 0 | F6: 556161 | G6: =IF(F6>=F5,F6-F5,0) -> 0 | K6: =C6+E6 -> 0
A7: 1 | B7: 7832895 | C7: =IF(B7>=B6,B7-B6,0)*1.06 -> 191.86 | D7: 231501 | E7: =IF(D7>=D6,D7-D6,0)*0.7 -> 0 | F7: 556164 | G7: =IF(F7>=F6,F7-F6,0) -> 3 | H7: =(E7*0.55)*1.61 -> 0 | I7: =C7*J1 -> 308.8946 | J7: =G7*J1 -> 4.83 | K7: =C7+E7 -> 191.86
A8: 2 | B8: 7833056 | C8: =IF(B8>=B7,B8-B7,0)*1.06 -> 170.66 | D8: 231501 | E8: =IF(D8>=D7,D8-D7,0)*0.7 -> 0 | F8: 556166 | G8: =IF(F8>=F7,F8-F7,0) -> 2 | H8: =(E8*0.55)*1.61 -> 0 | I8: =C8*J1 -> 274.7626 | J8: =G8*J1 -> 3.22 | K8: =C8+E8 -> 170.66
A9: 3 | B9: 7833217 | C9: =IF(B9>=B8,B9-B8,0)*1.06 -> 170.66 | D9: 231501 | E9: =IF(D9>=D8,D9-D8,0)*0.7 -> 0 | F9: 556166 | G9: =IF(F9>=F8,F9-F8,0) -> 0 | H9: =(E9*0.55)*1.61 -> 0 | I9: =C9*J1 -> 274.7626 | J9: =G9*J1 -> 0 | K9: =C9+E9 -> 170.66
A10: 4 | B10: 7833378 | C10: =IF(B10>=B9,B10-B9,0)*1.06 -> 170.66 | D10: 231501 | E10: =IF(D10>=D9,D10-D9,0)*0.7 -> 0 | F10: 556168 | G10: =IF(F10>=F9,F10-F9,0) -> 2 | H10: =(E10*0.55)*1.61 -> 0 | I10: =C10*J1 -> 274.7626 | J10: =G10*J1 -> 3.22 | K10: =C10+E10 -> 170.66
A11: 5 | B11: 7833539 | C11: =IF(B11>=B10,B11-B10,0)*1.06 -> 170.66 | D11: 231657.5 | E11: =IF(D11>=D10,D11-D10,0)*0.7 -> 109.55212 | F11: 556170 | G11: =IF(F11>=F10,F11-F10,0) -> 2 | H11: =(E11*0.55)*1.61 -> 97.008403 | I11: =C11*J1 -> 274.7626 | J11: =G11*J1 -> 3.22 | K11: =C11+E11 -> 280.21212
A12: 6 | B12: 7833700 | C12: =IF(B12>=B11,B12-B11,0)*1.06 -> 170.66 | D12: 231870.65 | E12: =IF(D12>=D11,D12-D11,0)*0.7 -> 149.20606 | F12: 556171 | G12: =IF(F12>=F11,F12-F11,0) -> 1 | H12: =(E12*0.55)*1.61 -> 132.12197 | I12: =C12*J1 -> 274.7626 | J12: =G12*J1 -> 1.61 | K12: =C12+E12 -> 319.86606
A13: 7 | B13: 7833861 | C13: =IF(B13>=B12,B13-B12,0)*1.06 -> 170.66 | D13: 232083.81 | E13: =IF(D13>=D12,D13-D12,0)*0.7 -> 149.20606 | F13: 556172 | G13: =IF(F13>=F12,F13-F12,0) -> 1 | H13: =(E13*0.55)*1.61 -> 132.12197 | I13: =C13*J1 -> 274.7626 | J13: =G13*J1 -> 1.61 | K13: =C13+E13 -> 319.86606
A14: 8 | B14: 7834022 | C14: =IF(B14>=B13,B14-B13,0)*1.06 -> 170.66 | D14: 232296.96 | E14: =IF(D14>=D13,D14-D13,0)*0.7 -> 149.20606 | F14: 556173 | G14: =IF(F14>=F13,F14-F13,0) -> 1 | H14: =(E14*0.55)*1.61 -> 132.12197 | I14: =C14*J1 -> 274.7626 | J14: =G14*J1 -> 1.61 | K14: =C14+E14 -> 319.86606
A15: 9 | B15: 7834183 | C15: =IF(B15>=B14,B15-B14,0)*1.06 -> 170.66 | D15: 232510.11 | E15: =IF(D15>=D14,D15-D14,0)*0.7 -> 149.20606 | F15: 556173 | G15: =IF(F15>=F14,F15-F14,0) -> 0 | H15: =(E15*0.55)*1.61 -> 132.12197 | I15: =C15*J1 -> 274.7626 | J15: =G15*J1 -> 0 | K15: =C15+E15 -> 319.86606
A16: 10 | B16: 7834344 | C16: =IF(B16>=B15,B16-B15,0)*1.06 -> 170.66 | D16: 232723.26 | E16: =IF(D16>=D15,D16-D15,0)*0.7 -> 149.20606 | F16: 556175 | G16: =IF(F16>=F15,F16-F15,0) -> 2 | H16: =(E16*0.55)*1.61 -> 132.12197 | I16: =C16*J1 -> 274.7626 | J16: =G16*J1 -> 3.22 | K16: =C16+E16 -> 319.86606
A17: 11 | B17: 7834505 | C17: =IF(B17>=B16,B17-B16,0)*1.06 -> 170.66 | D17: 232936.41 | E17: =IF(D17>=D16,D17-D16,0)*0.7 -> 149.20606 | F17: 556179 | G17: =IF(F17>=F16,F17-F16,0) -> 4 | H17: =(E17*0.55)*1.61 -> 132.12197 | I17: =C17*J1 -> 274.7626 | J17: =G17*J1 -> 6.44 | K17: =C17+E17 -> 319.86606
A18: 12 | B18: 7834666 | C18: =IF(B18>=B17,B18-B17,0)*1.06 -> 170.66 | D18: 233149.56 | E18: =IF(D18>=D17,D18-D17,0)*0.7 -> 149.20606 | F18: 556180 | G18: =IF(F18>=F17,F18-F17,0) -> 1 | H18: =(E18*0.55)*1.61 -> 132.12197 | I18: =C18*J1 -> 274.7626 | J18: =G18*J1 -> 1.61 | K18: =C18+E18 -> 319.86606
A19: 13 | B19: 7834827 | C19: =IF(B19>=B18,B19-B18,0)*1.06 -> 170.66 | D19: 233362.72 | E19: =IF(D19>=D18,D19-D18,0)*0.7 -> 149.20606 | F19: 556181 | G19: =IF(F19>=F18,F19-F18,0) -> 1 | H19: =(E19*0.55)*1.61 -> 132.12197 | I19: =C19*J1 -> 274.7626 | J19: =G19*J1 -> 1.61 | K19: =C19+E19 -> 319.86606
A20: 14 | B20: 7834988 | C20: =IF(B20>=B19,B20-B19,0)*1.06 -> 170.66 | D20: 233575.87 | E20: =IF(D20>=D19,D20-D19,0)*0.7 -> 149.20606 | F20: 556182 | G20: =IF(F20>=F19,F20-F19,0) -> 1 | H20: =(E20*0.55)*1.61 -> 132.12197 | I20: =C20*J1 -> 274.7626 | J20: =G20*J1 -> 1.61 | K20: =C20+E20 -> 319.86606
A21: 15 | B21: 7835149 | C21: =IF(B21>=B20,B21-B20,0)*1.06 -> 170.66 | D21: 233878 | E21: =IF(D21>=D20,D21-D20,0)*0.7 -> 211.49333 | F21: 556178 | G21: =IF(F21>=F20,F21-F20,0) -> 0 | H21: =(E21*0.55)*1.61 -> 187.27735 | I21: =C21*J1 -> 274.7626 | J21: =G21*J1 -> 0 | K21: =C21+E21 -> 382.15333
A22: 16 | B22: 7835310 | C22: =IF(B22>=B21,B22-B21,0)*1.06 -> 170.66 | D22: 234028 | E22: =IF(D22>=D21,D22-D21,0)*0.7 -> 105 | F22: 556180 | G22: =IF(F22>=F21,F22-F21,0) -> 2 | H22: =(E22*0.55)*1.61 -> 92.9775 | I22: =C22*J1 -> 274.7626 | J22: =G22*J1 -> 3.22 | K22: =C22+E22 -> 275.66
A23: 17 | B23: 7835471 | C23: =IF(B23>=B22,B23-B22,0)*1.06 -> 170.66 | D23: 234250 | E23: =IF(D23>=D22,D23-D22,0)*0.7 -> 155.4 | F23: 556181 | G23: =IF(F23>=F22,F23-F22,0) -> 1 | H23: =(E23*0.55)*1.61 -> 137.6067 | I23: =C23*J1 -> 274.7626 | J23: =G23*J1 -> 1.61 | K23: =C23+E23 -> 326.06
A24: 18 | B24: 7835632 | C24: =IF(B24>=B23,B24-B23,0)*1.06 -> 170.66 | D24: 234329 | E24: =IF(D24>=D23,D24-D23,0)*0.7 -> 55.3 | F24: 556181 | G24: =IF(F24>=F23,F24-F23,0) -> 0 | H24: =(E24*0.55)*1.61 -> 48.96815 | I24: =C24*J1 -> 274.7626 | J24: =G24*J1 -> 0 | K24: =C24+E24 -> 225.96
A25: 19 | B25: 7835793 | C25: =IF(B25>=B24,B25-B24,0)*1.06 -> 170.66 | D25: 234401 | E25: =IF(D25>=D24,D25-D24,0)*0.7 -> 50.4 | F25: 556182 | G25: =IF(F25>=F24,F25-F24,0) -> 1 | H25: =(E25*0.55)*1.61 -> 44.6292 | I25: =C25*J1 -> 274.7626 | J25: =G25*J1 -> 1.61 | K25: =C25+E25 -> 221.06
A26: 20 | B26: 7835954 | C26: =IF(B26>=B25,B26-B25,0)*1.06 -> 170.66 | D26: 234933 | E26: =IF(D26>=D25,D26-D25,0)*0.7 -> 372.4 | F26: 556185 | G26: =IF(F26>=F25,F26-F25,0) -> 3 | H26: =(E26*0.55)*1.61 -> 329.7602 | I26: =C26*J1 -> 274.7626 | J26: =G26*J1 -> 4.83 | K26: =C26+E26 -> 543.06
A27: 21 | B27: 7836115 | C27: =IF(B27>=B26,B27-B26,0)*1.06 -> 170.66 | D27: 235117 | E27: =IF(D27>=D26,D27-D26,0)*0.7 -> 128.8 | F27: 556186 | G27: =IF(F27>=F26,F27-F26,0) -> 1 | H27: =(E27*0.55)*1.61 -> 114.0524 | I27: =C27*J1 -> 274.7626 | J27: =G27*J1 -> 1.61 | K27: =C27+E27 -> 299.46
A28: 22 | B28: 7836276 | C28: =IF(B28>=B27,B28-B27,0)*1.06 -> 170.66 | D28: 235312 | E28: =IF(D28>=D27,D28-D27,0)*0.7 -> 136.5 | F28: 556188 | G28: =IF(F28>=F27,F28-F27,0) -> 2 | H28: =(E28*0.55)*1.61 -> 120.87075 | I28: =C28*J1 -> 274.7626 | J28: =G28*J1 -> 3.22 | K28: =C28+E28 -> 307.16
A29: 23 | B29: 7836437 | C29: =IF(B29>=B28,B29-B28,0)*1.06 -> 170.66 | D29: 235522 | E29: =IF(D29>=D28,D29-D28,0)*0.7 -> 147 | F29: 556189 | G29: =IF(F29>=F28,F29-F28,0) -> 1 | H29: =(E29*0.55)*1.61 -> 130.1685 | I29: =C29*J1 -> 274.7626 | J29: =G29*J1 -> 1.61 | K29: =C29+E29 -> 317.66
A30: 24 | B30: 7836598 | C30: =IF(B30>=B29,B30-B29,0)*1.06 -> 170.66 | D30: 235712 | E30: =IF(D30>=D29,D30-D29,0)*0.7 -> 133 | F30: 556189 | G30: =IF(F30>=F29,F30-F29,0) -> 0 | H30: =(E30*0.55)*1.61 -> 117.7715 | I30: =C30*J1 -> 274.7626 | J30: =G30*J1 -> 0 | K30: =C30+E30 -> 303.66
A31: 25 | B31: 7836759 | C31: =IF(B31>=B30,B31-B30,0)*1.06 -> 170.66 | D31: 235902 | E31: =IF(D31>=D30,D31-D30,0)*0.7 -> 133 | F31: 556189 | G31: =IF(F31>=F30,F31-F30,0) -> 0 | H31: =(E31*0.55)*1.61 -> 117.7715 | I31: =C31*J3 -> 0 | J31: =G31*J1 -> 0 | K31: =C31+E31 -> 303.66
A32: 26 | B32: 7836920 | C32: =IF(B32>=B31,B32-B31,0)*1.06 -> 170.66 | D32: 236098 | E32: =IF(D32>=D31,D32-D31,0)*0.7 -> 137.2 | F32: 556191 | G32: =IF(F32>=F31,F32-F31,0) -> 2 | H32: =(E32*0.55)*1.61 -> 121.4906 | I32: =C32*J1 -> 274.7626 | J32: =G32*J1 -> 3.22 | K32: =C32+E32 -> 307.86
A33: 27 | B33: 7837081 | C33: =IF(B33>=B32,B33-B32,0)*1.06 -> 170.66 | D33: 236309 | E33: =IF(D33>=D32,D33-D32,0)*0.7 -> 147.7 | F33: 556191 | G33: =IF(F33>=F32,F33-F32,0) -> 0 | H33: =(E33*0.55)*1.61 -> 130.78835 | I33: =C33*J1 -> 274.7626 | J33: =G33*J1 -> 0 | K33: =C33+E33 -> 318.36
A34: 28 | B34: 7837136 | C34: =IF(B34>=B33,B34-B33,0)*1.06 -> 58.3 | D34: 236419 | E34: =IF(D34>=D33,D34-D33,0)*0.7 -> 77 | F34: 556192 | G34: =IF(F34>=F33,F34-F33,0) -> 1 | H34: =(E34*0.55)*1.61 -> 68.1835 | I34: =C34*J1 -> 93.863 | J34: =G34*J1 -> 1.61 | K34: =C34+E34 -> 135.3
A35: 29 | B35: 7837250 | C35: =IF(B35>=B34,B35-B34,0)*1.06 -> 120.84 | D35: 236525 | E35: =IF(D35>=D34,D35-D34,0)*0.7 -> 74.2 | F35: 556192 | G35: =IF(F35>=F34,F35-F34,0) -> 0 | H35: =(E35*0.55)*1.61 -> 65.7041 | I35: =C35*J1 -> 194.5524 | J35: =G35*J1 -> 0 | K35: =C35+E35 -> 195.04
A36: 30 | B36: 7837364 | C36: =IF(B36>=B35,B36-B35,0)*1.06 -> 120.84 | D36: 236631 | E36: =IF(D36>=D35,D36-D35,0)*0.7 -> 74.2 | F36: 556192 | G36: =IF(F36>=F35,F36-F35,0) -> 0 | H36: =(E36*0.55)*1.61 -> 65.7041 | I36: =C36*J1 -> 194.5524 | J36: =G36*J1 -> 0 | K36: =C36+E36 -> 195.04
A37: 31 | C37: =IF(B37>=B36,B37-B36,0)*1.06 -> 0 | E37: =IF(D37>=D36,D37-D36,0)*0.7 -> 0 | G37: =IF(F37>=F36,F37-F36,0) -> 0 | H37: =(E37*0.55)*1.61 -> 0 | I37: =C37*J1 -> 0 | J37: =G37*J1 -> 0 | K37: =C37+E37 -> 0
A38: MTD | C38: =SUM(C7:C37) -> 4929 | E38: =SUM(E7:E37) -> 3591 | G38: =SUM(G7:G37) -> 35 | H38: =SUM(H6:H37) -> 3179.8305 | I38: =SUM(I6:I37) -> 7660.9274 | J38: =SUM(J6:J37) -> 56.35 | K38: =SUM(K6:K37) -> 8520
A39: Average MTD. | C39: =C38/A51 -> 164.3 | E39: =E38/A51 -> 119.7 | G39: =G38/A51 -> 1.1666667 | J39: =J38/#REF! -> #REF!
A40: Total Budget
A41: Budget MTD
A42: AVER. Bud | J42: =#REF!/$A$51 -> #REF!
A43: Total RFC
A44: RFC MTD
A45: AVER RFC
A46: MTD 2013
A47: AVER. Act 2013
A48: Accounting Readings | C48: =IF(C34>0,C34,0) -> 58.3 | E48: =IF(E34>0,E34,0) -> 77 | G48: =IF(G34>0,G34,0) -> 1
A50: Cost MTD
A51: =Elect!J46 -> 30

Sheet Consp
A1: =Elect!A1 -> April | L1: Summary | P1: =Elect!A1 -> April
B2: Elect Consuumption | H2: Water Incoming | U2: Water Consumption | AC2: Irrigation | AG2: Gas | AJ2: Cost | AK2: Solar Meter [ LIT ] | AL2: No. of Eng. | AM2: No. of Gardners | AN2: Cons. (lit) | AO2: Received Gas (tons) | AP2: Fuel Cost | AQ2: Solar level [cm] | AR2: Received Solar (tons) | AS2: Fuel Cost | AT2: Occupancy 10 | AV2: Occupancy07 | AZ2: Elect 2009 | BE2: Elect 2010 | BJ2: Water 2009 | BO2: Water 2010
A3: Date | B3: COUNTER (2) | D3: MD | F3: KVAR | H3: R.O | J3: Qenna | L3: Trucks | N3: Rimievera Line Meter | O3: Total Inc. | Q3: Total Main S.Pool | S3: Total Bar & Beach cons. | U3: Total S. Pool cons. | W3: Hotel consumption. | Y3: Sold Water | AA3: Irr. Water from R.O | AC3: Irr. Consumption. | AE3: Storage Water One tank | AF3: Grand Cons | AG3: % | AH3: Stock | AI3: Cons. | AJ3: 0 | AT3: No of guest | AU3: No. of rooms | AV3: No. of rooms | AW3: No. of guest | AX3: Cons. Per occ. room | AY3: Cons. Per guest | AZ3: Total cost | BA3: cost per room | BB3: cost per guest | BC3: Cons. Per occ. room | BD3: Cons. Per guest | BE3: Total cost | BF3: cost per room | BG3: cost per guest | BH3: Cons. Per occ. room | BI3: Cons. Per guest | BJ3: Total cost | BK3: cost per room | BL3: cost per guest | BM3: Cons. Per occ. room | BN3: Cons. Per guest | BO3: Total cost | BP3: cost per room | BQ3: cost per guest
B4: 2013 | C4: 2014 | D4: 2013 | E4: 2014 | F4: 2013 | G4: 2014 | H4: 2013 | I4: 2014 | J4: 2009 | K4: 2010 | L4: 2009 | M4: 2010 | O4: 2009 | P4: 2010 | Q4: 2009 | R4: 2010 | S4: 2009 | T4: 2010 | U4: 2009 | V4: 2010 | W4: 2009 | X4: 2010 | Y4: 2009 | Z4: 2010 | AA4: 2009 | AB4: 2010 | AC4: 2009 | AD4: 2010
A5: 1 | B5: =[3]Consp!C6 -> 33600 | C5: =Elect!J6 -> 1534 | D5: =[3]Consp!$E$6 -> 0 | E5: =Elect!M6 -> 544 | F5: =[3]Consp!G6 -> 20 | G5: =Elect!O6 -> 540 | H5: =[3]Consp!I6 -> 800 | I5: =Water!C7 -> 40.6 | J5: =[4]Consp!$K$6 -> 0 | K5: =Water!E7 -> 11.6 | L5: 0 | M5: =Water!#REF! -> #REF! | N5: =Water!#REF! -> #REF! | O5: =[5]Consp!P6 -> 1005 | P5: =Water!H7 -> 52.2 | Q5: =[5]Consp!R6 -> 114 | R5: =Water!O7 -> 0 | S5: =[5]Consp!T6 -> 13 | T5: =Water!#REF! -> #REF! | U5: =[5]Consp!V6 -> 147 | V5: =Water!#REF! -> #REF! | W5: =[5]Consp!X6 -> 755 | X5: =Water!Q7 -> 30.276 | Y5: 0 | Z5: =Water!#REF! -> #REF! | AA5: 0 | AB5: 0 | AC5: =[3]Consp!AD6 -> 690 | AD5: =Water!#REF! -> #REF! | AE5: =Water!#REF! -> #REF! | AF5: =Water!#REF! -> #REF! | AG5: =Gas!#REF! -> #REF! | AH5: =Gas!C7 -> 191.86 | AI5: =Gas!#REF! -> #REF! | AJ5: =Gas!J7 -> 4.83 | AK5: =Gas!#REF! -> #REF! | AL5: =Gas!#REF! -> #REF! | AM5: =Gas!#REF! -> #REF! | AN5: =Gas!#REF! -> #REF! | AO5: =Gas!#REF! -> #REF! | AP5: =Gas!#REF! -> #REF! | AQ5: =Gas!#REF! -> #REF! | AR5: =Gas!#REF! -> #REF! | AS5: =Gas!#REF! -> #REF! | AT5: =Elect!BK6 -> 154 | AU5: =Elect!BI6 -> 67 | AV5: =Elect!#REF! -> #REF! | AW5: =Elect!BK6 -> 154 | AX5: =[3]Consp!BC6 -> 48.695652 | AY5: =[3]Consp!BD6 -> 24.705882 | AZ5: =[3]Consp!BE6 -> 8835.4834 | BA5: =[3]Consp!BF6 -> 12.805048 | BB5: =[3]Consp!BG6 -> 6.496679 | BC5: =Elect!#REF! -> #REF! | BD5: =Elect!#REF! -> #REF! | BE5: =Elect!#REF! -> #REF! | BF5: =Elect!#REF! -> #REF! | BG5: =Elect!#REF! -> #REF! | BH5: =[3]Consp!BM6 -> 1.142029 | BI5: =[3]Consp!BN6 -> 0.57941176 | BJ5: =[3]Consp!BO6 -> 4569.1158 | BK5: =[3]Consp!BP6 -> 6.6219069 | BL5: =[3]Consp!BQ6 -> 3.3596439 | BM5: =Water!U7 -> #DIV/0! | BN5: =Water!W7 -> #DIV/0! | BO5: =Water!X7 -> 208.8 | BP5: =Water!Y7 -> #DIV/0! | BQ5: =Water!Z7 -> 0
A6: 2 | B6: =[3]Consp!C7 -> 31200 | C6: =Elect!J7 -> 1896 | D6: =[3]Consp!$E$6 -> 0 | E6: =Elect!M7 -> 930 | F6: =[3]Consp!G7 -> 20 | G6: =Elect!O7 -> 860 | H6: =[3]Consp!I7 -> 936 | I6: =Water!C8 -> 133.4 | J6: =[4]Consp!$K$6 -> 0 | K6: =Water!E8 -> 5.8 | L6: 0 | M6: =Water!#REF! -> #REF! | N6: =Water!#REF! -> #REF! | O6: =[5]Consp!P7 -> 1006 | P6: =Water!H8 -> 139.2 | Q6: =[5]Consp!R7 -> 113 | R6: =Water!O8 -> 0 | S6: =[5]Consp!T7 -> 17 | T6: =Water!#REF! -> #REF! | U6: =[5]Consp!V7 -> 140 | V6: =Water!#REF! -> #REF! | W6: =[5]Consp!X7 -> 792 | X6: =Water!Q8 -> 80.736 | Y6: 0 | Z6: =Water!#REF! -> #REF! | AA6: 0 | AB6: 0 | AC6: =[3]Consp!AD7 -> 370 | AD6: =Water!#REF! -> #REF! | AE6: =Water!#REF! -> #REF! | AF6: =Water!#REF! -> #REF! | AG6: =Gas!B7 -> 7832895 | AH6: =Gas!C8 -> 170.66 | AI6: =Gas!#REF! -> #REF! | AJ6: =Gas!J8 -> 3.22 | AK6: =Gas!#REF! -> #REF! | AL6: =Gas!#REF! -> #REF! | AM6: =Gas!#REF! -> #REF! | AN6: =Gas!#REF! -> #REF! | AO6: =Gas!#REF! -> #REF! | AP6: =Gas!#REF! -> #REF! | AQ6: =Gas!#REF! -> #REF! | AR6: =Gas!#REF! -> #REF! | AS6: =Gas!#REF! -> #REF! | AT6: =Elect!BK7 -> 289 | AU6: =Elect!BI7 -> 114 | AX6: =[3]Consp!BC7 -> 47.416413 | AY6: =[3]Consp!BD7 -> 23.981553 | AZ6: =[3]Consp!BE7 -> 8299.2754 | BA6: =[3]Consp!BF7 -> 12.612881 | BB6: =[3]Consp!BG7 -> 6.379151 | BC6: =Elect!BJ7 -> 394569 | BD6: =Elect!#REF! -> #REF! | BE6: =Elect!#REF! -> #REF! | BF6: =Elect!#REF! -> #REF! | BG6: =Elect!#REF! -> #REF! | BH6: =[3]Consp!BM7 -> 1.2021277 | BI6: =[3]Consp!BN7 -> 0.60799385 | BJ6: =[3]Consp!BO7 -> 5345.8654 | BK6: =[3]Consp!BP7 -> 8.1244156 | BL6: =[3]Consp!BQ7 -> 4.1090434 | BM6: =Water!U8 -> #DIV/0! | BN6: =Water!W8 -> #DIV/0! | BO6: =Water!X8 -> 556.8 | BP6: =Water!Y8 -> #DIV/0! | BQ6: =Water!Z8 -> #DIV/0!
A7: 3 | B7: =[3]Consp!C8 -> 31200 | C7: =Elect!J8 -> 1702 | D7: =[3]Consp!$E$6 -> 0 | E7: =Elect!M8 -> 402 | F7: =[3]Consp!G8 -> 20 | G7: =Elect!O8 -> 374 | H7: =[3]Consp!I8 -> 685 | I7: =Water!C9 -> 92.8 | J7: =[4]Consp!$K$6 -> 0 | K7: =Water!E9 -> 40.6 | L7: 0 | M7: =Water!#REF! -> #REF! | N7: =Water!#REF! -> #REF! | O7: =[5]Consp!P8 -> 902 | P7: =Water!H9 -> 133.4 | Q7: =[5]Consp!R8 -> 126 | R7: =Water!O9 -> 0 | S7: =[5]Consp!T8 -> 26 | T7: =Water!#REF! -> #REF! | U7: =[5]Consp!V8 -> 134 | V7: =Water!#REF! -> #REF! | W7: =[5]Consp!X8 -> 766 | X7: =Water!Q9 -> 77.372 | Y7: 0 | Z7: =Water!#REF! -> #REF! | AA7: 0 | AB7: 0 | AC7: =[3]Consp!AD8 -> 740 | AD7: =Water!#REF! -> #REF! | AE7: =Water!#REF! -> #REF! | AF7: =Water!#REF! -> #REF! | AG7: =Gas!B9 -> 7833217 | AH7: =Gas!C9 -> 170.66 | AI7: =Gas!#REF! -> #REF! | AJ7: =Gas!J9 -> 0 | AK7: =Gas!#REF! -> #REF! | AL7: =Gas!#REF! -> #REF! | AM7: =Gas!#REF! -> #REF! | AN7: =Gas!#REF! -> #REF! | AO7: =Gas!#REF! -> #REF! | AP7: =Gas!#REF! -> #REF! | AQ7: =Gas!#REF! -> #REF! | AR7: =Gas!#REF! -> #REF! | AS7: =Gas!#REF! -> #REF! | AT7: =Elect!BK8 -> 108 | AU7: =Elect!BI8 -> 46 | AX7: =[3]Consp!BC8 -> 47.926267 | AY7: =[3]Consp!BD8 -> 24.223602 | AZ7: =[3]Consp!BE8 -> 8299.2754 | BA7: =[3]Consp!BF8 -> 12.748503 | BB7: =[3]Consp!BG8 -> 6.4435368 | BC7: =Elect!BJ8 -> 394677 | BD7: =Elect!#REF! -> #REF! | BE7: =Elect!#REF! -> #REF! | BF7: =Elect!#REF! -> #REF! | BG7: =Elect!#REF! -> #REF! | BH7: =[3]Consp!BM8 -> 1.0875576 | BI7: =[3]Consp!BN8 -> 0.54968944 | BJ7: =[3]Consp!BO8 -> 3912.3054 | BK7: =[3]Consp!BP8 -> 6.0096857 | BL7: =[3]Consp!BQ8 -> 3.0375042 | BM7: =Water!U9 -> #DIV/0! | BN7: =Water!W9 -> #DIV/0! | BO7: =Water!X9 -> 533.6 | BP7: =Water!Y9 -> #DIV/0! | BQ7: =Water!Z9 -> #DIV/0!
A8: 4 | B8: =[3]Consp!C9 -> 33600 | C8: =Elect!J9 -> 1993 | D8: =[3]Consp!$E$6 -> 0 | E8: =Elect!M9 -> 634 | F8: =[3]Consp!G9 -> 20 | G8: =Elect!O9 -> 592 | H8: =[3]Consp!I9 -> 786 | I8: =Water!C10 -> 232 | J8: =[4]Consp!$K$6 -> 0 | K8: =Water!E10 -> 11.6 | L8: 0 | M8: =Water!#REF! -> #REF! | N8: =Water!#REF! -> #REF! | O8: =[5]Consp!P9 -> 930 | P8: =Water!H10 -> 243.6 | Q8: =[5]Consp!R9 -> 153 | R8: =Water!O10 -> 0 | S8: =[5]Consp!T9 -> 46 | T8: =Water!#REF! -> #REF! | U8: =[5]Consp!V9 -> 150 | V8: =Water!#REF! -> #REF! | W8: =[5]Consp!X9 -> 766 | X8: =Water!Q10 -> 141.288 | Y8: 0 | Z8: =Water!#REF! -> #REF! | AA8: 0 | AB8: 0 | AC8: =[3]Consp!AD9 -> 820 | AD8: =Water!#REF! -> #REF! | AE8: =Water!#REF! -> #REF! | AF8: =Water!#REF! -> #REF! | AG8: =Gas!B10 -> 7833378 | AH8: =Gas!C10 -> 170.66 | AI8: =Gas!#REF! -> #REF! | AJ8: =Gas!J10 -> 3.22 | AK8: =Gas!#REF! -> #REF! | AL8: =Gas!#REF! -> #REF! | AM8: =Gas!#REF! -> #REF! | AN8: =Gas!#REF! -> #REF! | AO8: =Gas!#REF! -> #REF! | AP8: =Gas!#REF! -> #REF! | AQ8: =Gas!#REF! -> #REF! | AR8: =Gas!#REF! -> #REF! | AS8: =Gas!#REF! -> #REF! | AT8: =Elect!BK9 -> 202 | AU8: =Elect!BI9 -> 85 | AX8: =[3]Consp!BC9 -> 51.06383 | AY8: =[3]Consp!BD9 -> 25.866051 | AZ8: =[3]Consp!BE9 -> 8835.4834 | BA8: =[3]Consp!BF9 -> 13.427786 | BB8: =[3]Consp!BG9 -> 6.8017578 | BC8: =Elect!BJ9 -> 394879 | BD8: =Elect!#REF! -> #REF! | BE8: =Elect!#REF! -> #REF! | BF8: =Elect!#REF! -> #REF! | BG8: =Elect!#REF! -> #REF! | BH8: =[3]Consp!BM9 -> 1.2218845 | BI8: =[3]Consp!BN9 -> 0.61893764 | BJ8: =[3]Consp!BO9 -> 4489.1562 | BK8: =[3]Consp!BP9 -> 6.8224259 | BL8: =[3]Consp!BQ9 -> 3.4558555 | BM8: =Water!U10 -> #DIV/0! | BN8: =Water!W10 -> #DIV/0! | BO8: =Water!X10 -> 974.4 | BP8: =Water!Y10 -> #DIV/0! | BQ8: =Water!Z10 -> #DIV/0!
A9: 5 | B9: =[3]Consp!C10 -> 31200 | C9: =Elect!J10 -> 1723 | D9: =[3]Consp!$E$6 -> 0 | E9: =Elect!M10 -> 629 | F9: =[3]Consp!G10 -> 20 | G9: =Elect!O10 -> 961 | H9: =[3]Consp!I10 -> 789 | I9: =Water!C11 -> 81.2 | J9: =[4]Consp!$K$6 -> 0 | K9: =Water!E11 -> 63.8 | L9: 0 | M9: =Water!#REF! -> #REF! | N9: =Water!#REF! -> #REF! | O9: =[5]Consp!P10 -> 1003 | P9: =Water!H11 -> 145 | Q9: =[5]Consp!R10 -> 102 | R9: =Water!O11 -> 0 | S9: =[5]Consp!T10 -> 8 | T9: =Water!#REF! -> #REF! | U9: =[5]Consp!V10 -> 130 | V9: =Water!#REF! -> #REF! | W9: =[5]Consp!X10 -> 735 | X9: =Water!Q11 -> 84.1 | Y9: 0 | Z9: =Water!#REF! -> #REF! | AA9: 0 | AB9: 0 | AC9: =[3]Consp!AD10 -> 640 | AD9: =Water!#REF! -> #REF! | AE9: =Water!#REF! -> #REF! | AF9: =Water!#REF! -> #REF! | AG9: =Gas!B11 -> 7833539 | AH9: =Gas!C11 -> 170.66 | AI9: =Gas!#REF! -> #REF! | AJ9: =Gas!J11 -> 3.22 | AK9: =Gas!#REF! -> #REF! | AL9: =Gas!#REF! -> #REF! | AM9: =Gas!#REF! -> #REF! | AN9: =Gas!#REF! -> #REF! | AO9: =Gas!#REF! -> #REF! | AP9: =Gas!#REF! -> #REF! | AQ9: =Gas!#REF! -> #REF! | AR9: =Gas!#REF! -> #REF! | AS9: =Gas!#REF! -> #REF! | AT9: =Elect!BK10 -> 262 | AU9: =Elect!BI10 -> 107 | AX9: =[3]Consp!BC10 -> 49.840256 | AY9: =[3]Consp!BD10 -> 25.181598 | AZ9: =[3]Consp!BE10 -> 8299.2754 | BA9: =[3]Consp!BF10 -> 13.257628 | BB9: =[3]Consp!BG10 -> 6.698366 | BC9: =Elect!BJ10 -> 395141 | BD9: =Elect!#REF! -> #REF! | BE9: =Elect!#REF! -> #REF! | BF9: =Elect!#REF! -> #REF! | BG9: =Elect!#REF! -> #REF! | BH9: =[3]Consp!BM10 -> 1.1980831 | BI9: =[3]Consp!BN10 -> 0.60532688 | BJ9: =[3]Consp!BO10 -> 4506.2904 | BK9: =[3]Consp!BP10 -> 7.198547 | BL9: =[3]Consp!BQ10 -> 3.6370383 | BM9: =Water!U11 -> #DIV/0! | BN9: =Water!W11 -> #DIV/0! | BO9: =Water!X11 -> 580 | BP9: =Water!Y11 -> #DIV/0! | BQ9: =Water!Z11 -> #DIV/0!
A10: 6 | B10: =[3]Consp!C11 -> 33600 | C10: =Elect!J11 -> 1827 | D10: =[3]Consp!$E$6 -> 0 | E10: =Elect!M11 -> 535 | F10: =[3]Consp!G11 -> 20 | G10: =Elect!O11 -> 892 | H10: =[3]Consp!I11 -> 805 | I10: =Water!C12 -> 46.4 | J10: =[4]Consp!$K$6 -> 0 | K10: =Water!E12 -> 46.4 | L10: 0 | M10: =Water!#REF! -> #REF! | N10: =Water!#REF! -> #REF! | O10: =[5]Consp!P11 -> 1004 | P10: =Water!H12 -> 92.8 | Q10: =[5]Consp!R11 -> 115 | R10: =Water!O12 -> 0 | S10: =[5]Consp!T11 -> 21 | T10: =Water!#REF! -> #REF! | U10: =[5]Consp!V11 -> 141 | V10: =Water!#REF! -> #REF! | W10: =[5]Consp!X11 -> 725 | X10: =Water!Q12 -> 53.824 | Y10: 0 | Z10: =Water!#REF! -> #REF! | AA10: 0 | AB10: 0 | AC10: =[3]Consp!AD11 -> 510 | AD10: =Water!#REF! -> #REF! | AE10: =Water!#REF! -> #REF! | AF10: =Water!#REF! -> #REF! | AG10: =Gas!B12 -> 7833700 | AH10: =Gas!C12 -> 170.66 | AI10: =Gas!#REF! -> #REF! | AJ10: =Gas!J12 -> 1.61 | AK10: =Gas!#REF! -> #REF! | AL10: =Gas!#REF! -> #REF! | AM10: =Gas!#REF! -> #REF! | AN10: =Gas!#REF! -> #REF! | AO10: =Gas!#REF! -> #REF! | AP10: =Gas!#REF! -> #REF! | AQ10: =Gas!#REF! -> #REF! | AR10: =Gas!#REF! -> #REF! | AS10: =Gas!#REF! -> #REF! | AT10: =Elect!BK11 -> 84 | AU10: =Elect!BI11 -> 35 | AX10: =[3]Consp!BC11 -> 47.457627 | AY10: =[3]Consp!BD11 -> 23.512946 | AZ10: =[3]Consp!BE11 -> 8835.4834 | BA10: =[3]Consp!BF11 -> 12.479496 | BB10: =[3]Consp!BG11 -> 6.1829835 | BC10: =Elect!BJ11 -> 395225 | BD10: =Elect!#REF! -> #REF! | BE10: =Elect!#REF! -> #REF! | BF10: =Elect!#REF! -> #REF! | BG10: =Elect!#REF! -> #REF! | BH10: =[3]Consp!BM11 -> 1.1567797 | BI10: =[3]Consp!BN11 -> 0.57312806 | BJ10: =[3]Consp!BO11 -> 4597.6727 | BK10: =[3]Consp!BP11 -> 6.4938881 | BL10: =[3]Consp!BQ11 -> 3.2174057 | BM10: =Water!U12 -> #DIV/0! | BN10: =Water!W12 -> #DIV/0! | BO10: =Water!X12 -> 371.2 | BP10: =Water!Y12 -> #DIV/0! | BQ10: =Water!Z12 -> #DIV/0!
A11: 7 | B11: =[3]Consp!C12 -> 31200 | C11: =Elect!J12 -> 2458 | D11: =[3]Consp!$E$6 -> 0 | E11: =Elect!M12 -> 876 | F11: =[3]Consp!G12 -> 20 | G11: =Elect!O12 -> 1091 | H11: =[3]Consp!I12 -> 871 | I11: =Water!C13 -> 69.6 | J11: =[4]Consp!$K$6 -> 0 | K11: =Water!E13 -> 29 | L11: 0 | M11: =Water!#REF! -> #REF! | N11: =Water!#REF! -> #REF! | O11: =[5]Consp!P12 -> 837 | P11: =Water!H13 -> 98.6 | Q11: =[5]Consp!R12 -> 113 | R11: =Water!O13 -> 0 | S11: =[5]Consp!T12 -> 1 | T11: =Water!#REF! -> #REF! | U11: =[5]Consp!V12 -> 151 | V11: =Water!#REF! -> #REF! | W11: =[5]Consp!X12 -> 732 | X11: =Water!Q13 -> 57.188 | Y11: 0 | Z11: =Water!#REF! -> #REF! | AA11: 0 | AB11: 0 | AC11: =[3]Consp!AD12 -> 1010 | AD11: =Water!#REF! -> #REF! | AE11: =Water!#REF! -> #REF! | AF11: =Water!#REF! -> #REF! | AG11: =Gas!B13 -> 7833861 | AH11: =Gas!C13 -> 170.66 | AI11: =Gas!#REF! -> #REF! | AJ11: =Gas!J13 -> 1.61 | AK11: =Gas!#REF! -> #REF! | AL11: =Gas!#REF! -> #REF! | AM11: =Gas!#REF! -> #REF! | AN11: =Gas!#REF! -> #REF! | AO11: =Gas!#REF! -> #REF! | AP11: =Gas!#REF! -> #REF! | AQ11: =Gas!#REF! -> #REF! | AR11: =Gas!#REF! -> #REF! | AS11: =Gas!#REF! -> #REF! | AT11: =Elect!BK12 -> 232 | AU11: =Elect!BI12 -> 95 | AX11: =[3]Consp!BC12 -> 43.454039 | AY11: =[3]Consp!BD12 -> 21.517241 | AZ11: =[3]Consp!BE12 -> 8299.2754 | BA11: =[3]Consp!BF12 -> 11.558879 | BB11: =[3]Consp!BG12 -> 5.7236382 | BC11: =Elect!BJ12 -> 395457 | BD11: =Elect!#REF! -> #REF! | BE11: =Elect!#REF! -> #REF! | BF11: =Elect!#REF! -> #REF! | BG11: =Elect!#REF! -> #REF! | BH11: =[3]Consp!BM12 -> 1.1713092 | BI11: =[3]Consp!BN12 -> 0.58 | BJ11: =[3]Consp!BO12 -> 4974.6248 | BK11: =[3]Consp!BP12 -> 6.9284468 | BL11: =[3]Consp!BQ12 -> 3.4307757 | BM11: =Water!U13 -> #DIV/0! | BN11: =Water!W13 -> #DIV/0! | BO11: =Water!X13 -> 394.4 | BP11: =Water!Y13 -> #DIV/0! | BQ11: =Water!Z13 -> #DIV/0!
A12: 8 | B12: =[3]Consp!C13 -> 33600 | C12: =Elect!J13 -> 2104 | D12: =[3]Consp!$E$6 -> 0 | E12: =Elect!M13 -> 777 | F12: =[3]Consp!G13 -> 20 | G12: =Elect!O13 -> 539 | H12: =[3]Consp!I13 -> 963 | I12: =Water!C14 -> 75.4 | J12: =[4]Consp!$K$6 -> 0 | K12: =Water!E14 -> 40.6 | L12: 0 | M12: =Water!#REF! -> #REF! | N12: =Water!#REF! -> #REF! | O12: =[5]Consp!P13 -> 1000 | P12: =Water!H14 -> 116 | Q12: =[5]Consp!R13 -> 128 | R12: =Water!O14 -> 0 | S12: =[5]Consp!T13 -> 24 | T12: =Water!#REF! -> #REF! | U12: =[5]Consp!V13 -> 148 | V12: =Water!#REF! -> #REF! | W12: =[5]Consp!X13 -> 719 | X12: =Water!Q14 -> 67.28 | Y12: 0 | Z12: =Water!#REF! -> #REF! | AA12: 0 | AB12: 0 | AC12: =[3]Consp!AD13 -> 630 | AD12: =Water!#REF! -> #REF! | AE12: =Water!#REF! -> #REF! | AF12: =Water!#REF! -> #REF! | AG12: =Gas!B14 -> 7834022 | AH12: =Gas!C14 -> 170.66 | AI12: =Gas!#REF! -> #REF! | AJ12: =Gas!J14 -> 1.61 | AK12: =Gas!#REF! -> #REF! | AL12: =Gas!#REF! -> #REF! | AM12: =Gas!#REF! -> #REF! | AN12: =Gas!#REF! -> #REF! | AO12: =Gas!#REF! -> #REF! | AP12: =Gas!#REF! -> #REF! | AQ12: =Gas!#REF! -> #REF! | AR12: =Gas!#REF! -> #REF! | AS12: =Gas!#REF! -> #REF! | AT12: =Elect!BK13 -> 217 | AU12: =Elect!BI13 -> 89 | AX12: =[3]Consp!BC13 -> 48.837209 | AY12: =[3]Consp!BD13 -> 24.086022 | AZ12: =[3]Consp!BE13 -> 8835.4834 | BA12: =[3]Consp!BF13 -> 12.842272 | BB12: =[3]Consp!BG13 -> 6.3336799 | BC12: =Elect!BJ13 -> 395674 | BD12: =Elect!#REF! -> #REF! | BE12: =Elect!#REF! -> #REF! | BF12: =Elect!#REF! -> #REF! | BG12: =Elect!#REF! -> #REF! | BH12: =[3]Consp!BM13 -> 1.2194767 | BI12: =[3]Consp!BN13 -> 0.60143369 | BJ12: =[3]Consp!BO13 -> 5500.0731 | BK12: =[3]Consp!BP13 -> 7.9942923 | BL12: =[3]Consp!BQ13 -> 3.9427047 | BM12: =Water!U14 -> #DIV/0! | BN12: =Water!W14 -> #DIV/0! | BO12: =Water!X14 -> 464 | BP12: =Water!Y14 -> #DIV/0! | BQ12: =Water!Z14 -> #DIV/0!
A13: 9 | B13: =[3]Consp!C14 -> 33600 | C13: =Elect!J14 -> 962 | D13: =[3]Consp!$E$6 -> 0 | E13: =Elect!M14 -> 583 | F13: =[3]Consp!G14 -> 20 | G13: =Elect!O14 -> 398 | H13: =[3]Consp!I14 -> 790 | I13: =Water!C15 -> 98.6 | J13: =[4]Consp!$K$6 -> 0 | K13: =Water!E15 -> 34.8 | L13: 0 | M13: =Water!#REF! -> #REF! | N13: =Water!#REF! -> #REF! | O13: =[5]Consp!P14 -> 841 | P13: =Water!H15 -> 133.4 | Q13: =[5]Consp!R14 -> 127 | R13: =Water!O15 -> 0 | S13: =[5]Consp!T14 -> 21 | T13: =Water!#REF! -> #REF! | U13: =[5]Consp!V14 -> 139 | V13: =Water!#REF! -> #REF! | W13: =[5]Consp!X14 -> 701 | X13: =Water!Q15 -> 77.372 | Y13: 0 | Z13: =Water!#REF! -> #REF! | AA13: 0 | AB13: 0 | AC13: =[3]Consp!AD14 -> 440 | AD13: =Water!#REF! -> #REF! | AE13: =Water!#REF! -> #REF! | AF13: =Water!#REF! -> #REF! | AG13: =Gas!B15 -> 7834183 | AH13: =Gas!C15 -> 170.66 | AI13: =Gas!#REF! -> #REF! | AJ13: =Gas!J15 -> 0 | AK13: =Gas!#REF! -> #REF! | AL13: =Gas!#REF! -> #REF! | AM13: =Gas!#REF! -> #REF! | AN13: =Gas!#REF! -> #REF! | AO13: =Gas!#REF! -> #REF! | AP13: =Gas!#REF! -> #REF! | AQ13: =Gas!#REF! -> #REF! | AR13: =Gas!#REF! -> #REF! | AS13: =Gas!#REF! -> #REF! | AT13: =Elect!BK14 -> 117 | AU13: =Elect!BI14 -> 49 | AX13: =[3]Consp!BC14 -> 49.194729 | AY13: =[3]Consp!BD14 -> 24.1033 | AZ13: =[3]Consp!BE14 -> 8835.4834 | BA13: =[3]Consp!BF14 -> 12.936286 | BB13: =[3]Consp!BG14 -> 6.3382234 | BC13: =Elect!BJ14 -> 395791 | BD13: =Elect!#REF! -> #REF! | BE13: =Elect!#REF! -> #REF! | BF13: =Elect!#REF! -> #REF! | BG13: =Elect!#REF! -> #REF! | BH13: =[3]Consp!BM14 -> 1.1903367 | BI13: =[3]Consp!BN14 -> 0.58321377 | BJ13: =[3]Consp!BO14 -> 4512.0018 | BK13: =[3]Consp!BP14 -> 6.606152 | BL13: =[3]Consp!BQ14 -> 3.2367301 | BM13: =Water!U15 -> #DIV/0! | BN13: =Water!W15 -> #DIV/0! | BO13: =Water!X15 -> 533.6 | BP13: =Water!Y15 -> #DIV/0! | BQ13: =Water!Z15 -> #DIV/0!
A14: 10 | B14: =[3]Consp!C15 -> 31200 | C14: =Elect!J15 -> 2501 | D14: =[3]Consp!$E$6 -> 0 | E14: =Elect!M15 -> 810 | F14: =[3]Consp!G15 -> 20 | G14: =Elect!O15 -> 520 | H14: =[3]Consp!I15 -> 792 | I14: =Water!C16 -> 29 | J14: =[4]Consp!$K$6 -> 0 | K14: =Water!E16 -> 17.4 | L14: 0 | M14: =Water!#REF! -> #REF! | N14: =Water!#REF! -> #REF! | O14: =[5]Consp!P15 -> 972 | P14: =Water!H16 -> 54.52 | Q14: =[5]Consp!R15 -> 126 | R14: =Water!O16 -> 0 | S14: =[5]Consp!T15 -> 18 | T14: =Water!#REF! -> #REF! | U14: =[5]Consp!V15 -> 145 | V14: =Water!#REF! -> #REF! | W14: =[5]Consp!X15 -> 756 | X14: =Water!Q16 -> 31.6216 | Y14: 0 | Z14: =Water!#REF! -> #REF! | AA14: 0 | AB14: 0 | AC14: =[3]Consp!AD15 -> 580 | AD14: =Water!#REF! -> #REF! | AE14: =Water!#REF! -> #REF! | AF14: =Water!#REF! -> #REF! | AG14: =Gas!B16 -> 7834344 | AH14: =Gas!C16 -> 170.66 | AI14: =Gas!#REF! -> #REF! | AJ14: =Gas!J16 -> 3.22 | AK14: =Gas!#REF! -> #REF! | AL14: =Gas!#REF! -> #REF! | AM14: =Gas!#REF! -> #REF! | AN14: =Gas!#REF! -> #REF! | AO14: =Gas!#REF! -> #REF! | AP14: =Gas!#REF! -> #REF! | AQ14: =Gas!#REF! -> #REF! | AR14: =Gas!#REF! -> #REF! | AS14: =Gas!#REF! -> #REF! | AT14: =Elect!BK15 -> 274 | AU14: =Elect!BI15 -> 111 | AX14: =[3]Consp!BC15 -> 49.52381 | AY14: =[3]Consp!BD15 -> 24.781573 | AZ14: =[3]Consp!BE15 -> 8299.2754 | BA14: =[3]Consp!BF15 -> 13.173453 | BB14: =[3]Consp!BG15 -> 6.5919582 | BC14: =Elect!BJ15 -> 396065 | BD14: =Elect!#REF! -> #REF! | BE14: =Elect!#REF! -> #REF! | BF14: =Elect!#REF! -> #REF! | BG14: =Elect!#REF! -> #REF! | BH14: =[3]Consp!BM15 -> 1.2730159 | BI14: =[3]Consp!BN15 -> 0.6370135 | BJ14: =[3]Consp!BO15 -> 4469.9646 | BK14: =[3]Consp!BP15 -> 7.0951819 | BL14: =[3]Consp!BQ15 -> 3.5504087 | BM14: =Water!U16 -> #DIV/0! | BN14: =Water!W16 -> #DIV/0! | BO14: =Water!X16 -> 218.08 | BP14: =Water!Y16 -> #DIV/0! | BQ14: =Water!Z16 -> #DIV/0!
A15: 11 | B15: =[3]Consp!C16 -> 33600 | C15: =Elect!J16 -> 1367 | D15: =[3]Consp!$E$6 -> 0 | E15: =Elect!M16 -> 549 | F15: =[3]Consp!G16 -> 20 | G15: =Elect!O16 -> 362 | H15: =[3]Consp!I16 -> 817 | I15: =Water!C17 -> 46.4 | J15: =[4]Consp!$K$6 -> 0 | K15: =Water!E17 -> 29 | L15: 0 | M15: =Water!#REF! -> #REF! | N15: =Water!#REF! -> #REF! | O15: =[5]Consp!P16 -> 875 | P15: =Water!H17 -> 80.62 | Q15: =[5]Consp!R16 -> 122 | R15: =Water!O17 -> 0 | S15: =[5]Consp!T16 -> 20 | T15: =Water!#REF! -> #REF! | U15: =[5]Consp!V16 -> 156 | V15: =Water!#REF! -> #REF! | W15: =[5]Consp!X16 -> 712 | X15: =Water!Q17 -> 46.7596 | Y15: 0 | Z15: =Water!#REF! -> #REF! | AA15: 0 | AB15: 0 | AC15: =[3]Consp!AD16 -> 850 | AD15: =Water!#REF! -> #REF! | AE15: =Water!#REF! -> #REF! | AF15: =Water!#REF! -> #REF! | AG15: =Gas!#REF! -> #REF! | AH15: =Gas!C17 -> 170.66 | AI15: =Gas!#REF! -> #REF! | AJ15: =Gas!J17 -> 6.44 | AK15: =Gas!#REF! -> #REF! | AL15: =Gas!#REF! -> #REF! | AM15: =Gas!#REF! -> #REF! | AN15: =Gas!#REF! -> #REF! | AO15: =Gas!#REF! -> #REF! | AP15: =Gas!#REF! -> #REF! | AQ15: =Gas!#REF! -> #REF! | AR15: =Gas!#REF! -> #REF! | AS15: =Gas!#REF! -> #REF! | AT15: =Elect!BK16 -> 150 | AU15: =Elect!BI16 -> 62 | AX15: =[3]Consp!BC16 -> 53.333333 | AY15: =[3]Consp!BD16 -> 26.751592 | AZ15: =[3]Consp!BE16 -> 8835.4834 | BA15: =[3]Consp!BF16 -> 14.024577 | BB15: =[3]Consp!BG16 -> 7.0346206 | BC15: =Elect!BJ16 -> 396215 | BD15: =Elect!#REF! -> #REF! | BE15: =Elect!#REF! -> #REF! | BF15: =Elect!#REF! -> #REF! | BG15: =Elect!#REF! -> #REF! | BH15: =[3]Consp!BM16 -> 1.3460317 | BI15: =[3]Consp!BN16 -> 0.67515924 | BJ15: =[3]Consp!BO16 -> 4666.2095 | BK15: =[3]Consp!BP16 -> 7.4066817 | BL15: =[3]Consp!BQ16 -> 3.7151349 | BM15: =Water!U17 -> #DIV/0! | BN15: =Water!W17 -> #DIV/0! | BO15: =Water!X17 -> 322.48 | BP15: =Water!Y17 -> #DIV/0! | BQ15: =Water!Z17 -> #DIV/0!
A16: 12 | B16: =[3]Consp!C17 -> 33600 | C16: =Elect!J17 -> 1552 | D16: =[3]Consp!$E$6 -> 0 | E16: =Elect!M17 -> 653 | F16: =[3]Consp!G17 -> 20 | G16: =Elect!O17 -> 469 | H16: =[3]Consp!I17 -> 907 | I16: =Water!C18 -> 40.6 | J16: =[4]Consp!$K$6 -> 0 | K16: =Water!E18 -> 29 | L16: 0 | M16: =Water!#REF! -> #REF! | N16: =Water!#REF! -> #REF! | O16: =[5]Consp!P17 -> 965 | P16: =Water!H18 -> 77.14 | Q16: =[5]Consp!R17 -> 125 | R16: =Water!O18 -> 0 | S16: =[5]Consp!T17 -> 4 | T16: =Water!#REF! -> #REF! | U16: =[5]Consp!V17 -> 167 | V16: =Water!#REF! -> #REF! | W16: =[5]Consp!X17 -> 705 | X16: =Water!Q18 -> 44.7412 | Y16: 0 | Z16: =Water!#REF! -> #REF! | AA16: 0 | AB16: 0 | AC16: =[3]Consp!AD17 -> 880 | AD16: =Water!#REF! -> #REF! | AE16: =Water!#REF! -> #REF! | AF16: =Water!#REF! -> #REF! | AG16: =Gas!B18 -> 7834666 | AH16: =Gas!C18 -> 170.66 | AI16: =Gas!#REF! -> #REF! | AJ16: =Gas!J18 -> 1.61 | AK16: =Gas!#REF! -> #REF! | AL16: =Gas!#REF! -> #REF! | AM16: =Gas!#REF! -> #REF! | AN16: =Gas!#REF! -> #REF! | AO16: =Gas!#REF! -> #REF! | AP16: =Gas!#REF! -> #REF! | AQ16: =Gas!#REF! -> #REF! | AR16: =Gas!#REF! -> #REF! | AS16: =Gas!#REF! -> #REF! | AT16: =Elect!BK17 -> 157 | AU16: =Elect!BI17 -> 63 | AX16: =[3]Consp!BC17 -> 50.45045 | AY16: =[3]Consp!BD17 -> 25.339367 | AZ16: =[3]Consp!BE17 -> 8835.4834 | BA16: =[3]Consp!BF17 -> 13.266492 | BB16: =[3]Consp!BG17 -> 6.6632605 | BC16: =Elect!BJ17 -> 396372 | BD16: =Elect!#REF! -> #REF! | BE16: =Elect!#REF! -> #REF! | BF16: =Elect!#REF! -> #REF! | BG16: =Elect!#REF! -> #REF! | BH16: =[3]Consp!BM17 -> 1.2162162 | BI16: =[3]Consp!BN17 -> 0.61085973 | BJ16: =[3]Consp!BO17 -> 5180.235 | BK16: =[3]Consp!BP17 -> 7.7781306 | BL16: =[3]Consp!BQ17 -> 3.9066629 | BM16: =Water!U18 -> #DIV/0! | BN16: =Water!W18 -> #DIV/0! | BO16: =Water!X18 -> 308.56 | BP16: =Water!Y18 -> #DIV/0! | BQ16: =Water!Z18 -> #DIV/0!
A17: 13 | B17: =[3]Consp!C18 -> 31200 | C17: =Elect!J18 -> 1989 | D17: =[3]Consp!$E$6 -> 0 | E17: =Elect!M18 -> 625 | F17: =[3]Consp!G18 -> 20 | G17: =Elect!O18 -> 711 | H17: =[3]Consp!I18 -> 812 | I17: =Water!C19 -> 63.8 | J17: =[4]Consp!$K$6 -> 0 | K17: =Water!E19 -> 46.4 | L17: 0 | M17: =Water!#REF! -> #REF! | N17: =Water!#REF! -> #REF! | O17: =[5]Consp!P18 -> 822 | P17: =Water!H19 -> 117.16 | Q17: =[5]Consp!R18 -> 123 | R17: =Water!O19 -> 0 | S17: =[5]Consp!T18 -> 7 | T17: =Water!#REF! -> #REF! | U17: =[5]Consp!V18 -> 163 | V17: =Water!#REF! -> #REF! | W17: =[5]Consp!X18 -> 692 | X17: =Water!Q19 -> 67.9528 | Y17: 0 | Z17: =Water!#REF! -> #REF! | AA17: 0 | AB17: 0 | AC17: =[3]Consp!AD18 -> 460 | AD17: =Water!#REF! -> #REF! | AE17: =Water!#REF! -> #REF! | AF17: =Water!#REF! -> #REF! | AG17: =Gas!B19 -> 7834827 | AH17: =Gas!C19 -> 170.66 | AI17: =Gas!#REF! -> #REF! | AJ17: =Gas!J19 -> 1.61 | AK17: =Gas!#REF! -> #REF! | AL17: =Gas!#REF! -> #REF! | AM17: =Gas!#REF! -> #REF! | AN17: =Gas!#REF! -> #REF! | AO17: =Gas!#REF! -> #REF! | AP17: =Gas!#REF! -> #REF! | AQ17: =Gas!#REF! -> #REF! | AR17: =Gas!#REF! -> #REF! | AS17: =Gas!#REF! -> #REF! | AT17: =Elect!BK18 -> 212 | AU17: =Elect!BI18 -> 90 | AX17: =[3]Consp!BC18 -> 46.567164 | AY17: =[3]Consp!BD18 -> 23.214286 | AZ17: =[3]Consp!BE18 -> 8299.2754 | BA17: =[3]Consp!BF18 -> 12.386978 | BB17: =[3]Consp!BG18 -> 6.1750561 | BC17: =Elect!BJ18 -> 396584 | BD17: =Elect!#REF! -> #REF! | BE17: =Elect!#REF! -> #REF! | BF17: =Elect!#REF! -> #REF! | BG17: =Elect!#REF! -> #REF! | BH17: =[3]Consp!BM18 -> 1.0850746 | BI17: =[3]Consp!BN18 -> 0.54092262 | BJ17: =[3]Consp!BO18 -> 4637.6525 | BK17: =[3]Consp!BP18 -> 6.9218694 | BL17: =[3]Consp!BQ18 -> 3.4506343 | BM17: =Water!U19 -> #DIV/0! | BN17: =Water!W19 -> #DIV/0! | BO17: =Water!X19 -> 468.64 | BP17: =Water!Y19 -> #DIV/0! | BQ17: =Water!Z19 -> #DIV/0!
A18: 14 | B18: =[3]Consp!C19 -> 33600 | C18: =Elect!J19 -> 2081 | D18: =[3]Consp!$E$6 -> 0 | E18: =Elect!M19 -> 726 | F18: =[3]Consp!G19 -> 30 | G18: =Elect!O19 -> 635 | H18: =[3]Consp!I19 -> 810 | I18: =Water!C20 -> 40.6 | J18: =[4]Consp!$K$6 -> 0 | K18: =Water!E20 -> 29 | L18: 0 | M18: =Water!#REF! -> #REF! | N18: =Water!#REF! -> #REF! | O18: =[5]Consp!P19 -> 943 | P18: =Water!H20 -> 77.14 | Q18: =[5]Consp!R19 -> 118 | R18: =Water!O20 -> 0 | S18: =[5]Consp!T19 -> 18 | T18: =Water!#REF! -> #REF! | U18: =[5]Consp!V19 -> 152 | V18: =Water!#REF! -> #REF! | W18: =[5]Consp!X19 -> 708 | X18: =Water!Q20 -> 44.7412 | Y18: 0 | Z18: =Water!#REF! -> #REF! | AA18: 0 | AB18: 0 | AC18: =[3]Consp!AD19 -> 490 | AD18: =Water!#REF! -> #REF! | AE18: =Water!#REF! -> #REF! | AF18: =Water!#REF! -> #REF! | AG18: =Gas!B20 -> 7834988 | AH18: =Gas!C20 -> 170.66 | AI18: =Gas!#REF! -> #REF! | AJ18: =Gas!J20 -> 1.61 | AK18: =Gas!#REF! -> #REF! | AL18: =Gas!#REF! -> #REF! | AM18: =Gas!#REF! -> #REF! | AN18: =Gas!#REF! -> #REF! | AO18: =Gas!#REF! -> #REF! | AP18: =Gas!#REF! -> #REF! | AQ18: =Gas!#REF! -> #REF! | AR18: =Gas!#REF! -> #REF! | AS18: =Gas!#REF! -> #REF! | AT18: =Elect!BK19 -> 190 | AU18: =Elect!BI19 -> 77 | AX18: =[3]Consp!BC19 -> 47.795164 | AY18: =[3]Consp!BD19 -> 24.207493 | AZ18: =[3]Consp!BE19 -> 8835.4834 | BA18: =[3]Consp!BF19 -> 12.568255 | BB18: =[3]Consp!BG19 -> 6.3656221 | BC18: =Elect!BJ6 -> 394280 | BD18: =Elect!#REF! -> #REF! | BE18: =Elect!#REF! -> #REF! | BF18: =Elect!#REF! -> #REF! | BG18: =Elect!#REF! -> #REF! | BH18: =[3]Consp!BM19 -> 1.1024182 | BI18: =[3]Consp!BN19 -> 0.55835735 | BJ18: =[3]Consp!BO19 -> 4626.2297 | BK18: =[3]Consp!BP19 -> 6.5806966 | BL18: =[3]Consp!BQ19 -> 3.3330185 | BM18: =Water!U20 -> #DIV/0! | BN18: =Water!W20 -> #DIV/0! | BO18: =Water!X20 -> 308.56 | BP18: =Water!Y20 -> #DIV/0! | BQ18: =Water!Z20 -> #DIV/0!
A19: 15 | B19: =[3]Consp!C20 -> 31200 | C19: =Elect!J20 -> 1796 | D19: =[3]Consp!$E$6 -> 0 | E19: =Elect!M20 -> 629 | F19: =[3]Consp!G20 -> 20 | G19: =Elect!O20 -> 699 | H19: =[3]Consp!I20 -> 841 | I19: =Water!C21 -> 52.2 | J19: =[4]Consp!$K$6 -> 0 | K19: =Water!E21 -> 52.2 | L19: 0 | M19: =Water!#REF! -> #REF! | N19: =Water!#REF! -> #REF! | O19: =[5]Consp!P20 -> 947 | P19: =Water!H21 -> 108.46 | Q19: =[5]Consp!R20 -> 131 | R19: =Water!O21 -> 0 | S19: =[5]Consp!T20 -> 23 | T19: =Water!#REF! -> #REF! | U19: =[5]Consp!V20 -> 166 | V19: =Water!#REF! -> #REF! | W19: =[5]Consp!X20 -> 787 | X19: =Water!Q21 -> 62.9068 | Y19: 0 | Z19: =Water!#REF! -> #REF! | AA19: 0 | AB19: 0 | AC19: =[3]Consp!AD20 -> 730 | AD19: =Water!#REF! -> #REF! | AE19: =Water!#REF! -> #REF! | AF19: =Water!#REF! -> #REF! | AG19: =Gas!B21 -> 7835149 | AH19: =Gas!C21 -> 170.66 | AI19: =Gas!#REF! -> #REF! | AJ19: =Gas!J21 -> 0 | AK19: =Gas!#REF! -> #REF! | AL19: =Gas!#REF! -> #REF! | AM19: =Gas!#REF! -> #REF! | AN19: =Gas!#REF! -> #REF! | AO19: =Gas!#REF! -> #REF! | AP19: =Gas!#REF! -> #REF! | AQ19: =Gas!#REF! -> #REF! | AR19: =Gas!#REF! -> #REF! | AS19: =Gas!#REF! -> #REF! | AT19: =Elect!BK20 -> 173 | AU19: =Elect!BI20 -> 74 | AX19: =[3]Consp!BC20 -> 41.6 | AY19: =[3]Consp!BD20 -> 20.995962 | AZ19: =[3]Consp!BE20 -> 8299.2754 | BA19: =[3]Consp!BF20 -> 11.065701 | BB19: =[3]Consp!BG20 -> 5.5849767 | BC19: =Elect!BJ20 -> 396947 | BD19: =Elect!#REF! -> #REF! | BE19: =Elect!#REF! -> #REF! | BF19: =Elect!#REF! -> #REF! | BG19: =Elect!#REF! -> #REF! | BH19: =[3]Consp!BM20 -> 1.1506667 | BI19: =[3]Consp!BN20 -> 0.58114478 | BJ19: =[3]Consp!BO20 -> 4803.283 | BK19: =[3]Consp!BP20 -> 6.4043773 | BL19: =[3]Consp!BQ20 -> 3.234534 | BM19: =Water!U21 -> #DIV/0! | BN19: =Water!W21 -> #DIV/0! | BO19: =Water!X21 -> 433.84 | BP19: =Water!Y21 -> #DIV/0! | BQ19: =Water!Z21 -> #DIV/0!
A20: 16 | B20: =[3]Consp!C21 -> 36000 | C20: =Elect!J21 -> 1801 | D20: =[3]Consp!$E$6 -> 0 | E20: =Elect!M21 -> 630 | F20: =[3]Consp!G21 -> 20 | G20: =Elect!O21 -> 749 | H20: =[3]Consp!I21 -> 932 | I20: =Water!C22 -> 34.8 | J20: =[4]Consp!$K$6 -> 0 | K20: =Water!E22 -> 40.6 | L20: 0 | M20: =Water!#REF! -> #REF! | N20: =Water!#REF! -> #REF! | O20: =[5]Consp!P21 -> 998 | P20: =Water!H22 -> 78.88 | Q20: =[5]Consp!R21 -> 136 | R20: =Water!O22 -> 0 | S20: =[5]Consp!T21 -> 22 | T20: =Water!#REF! -> #REF! | U20: =[5]Consp!V21 -> 162 | V20: =Water!#REF! -> #REF! | W20: =[5]Consp!X21 -> 703 | X20: =Water!Q22 -> 45.7504 | Y20: 0 | Z20: =Water!#REF! -> #REF! | AA20: 0 | AB20: 0 | AC20: =[3]Consp!AD21 -> 600 | AD20: =Water!#REF! -> #REF! | AE20: =Water!#REF! -> #REF! | AF20: =Water!#REF! -> #REF! | AG20: =Gas!B22 -> 7835310 | AH20: =Gas!C22 -> 170.66 | AI20: =Gas!#REF! -> #REF! | AJ20: =Gas!J22 -> 3.22 | AK20: =Gas!#REF! -> #REF! | AL20: =Gas!#REF! -> #REF! | AM20: =Gas!#REF! -> #REF! | AN20: =Gas!#REF! -> #REF! | AO20: =Gas!#REF! -> #REF! | AP20: =Gas!#REF! -> #REF! | AQ20: =Gas!#REF! -> #REF! | AR20: =Gas!#REF! -> #REF! | AS20: =Gas!#REF! -> #REF! | AT20: =Elect!BK21 -> 184 | AU20: =Elect!BI21 -> 73 | AX20: =[3]Consp!BC21 -> 48 | AY20: =[3]Consp!BD21 -> 24.22611 | AZ20: =[3]Consp!BE21 -> 9371.6914 | BA20: =[3]Consp!BF21 -> 12.495589 | BB20: =[3]Consp!BG21 -> 6.3066564 | BC20: =Elect!BJ21 -> 397131 | BD20: =Elect!#REF! -> #REF! | BE20: =Elect!#REF! -> #REF! | BF20: =Elect!#REF! -> #REF! | BG20: =Elect!#REF! -> #REF! | BH20: =[3]Consp!BM21 -> 1.1626667 | BI20: =[3]Consp!BN21 -> 0.58720539 | BJ20: =[3]Consp!BO21 -> 5323.0199 | BK20: =[3]Consp!BP21 -> 7.0973598 | BL20: =[3]Consp!BQ21 -> 3.5845252 | BM20: =Water!U22 -> #DIV/0! | BN20: =Water!W22 -> #DIV/0! | BO20: =Water!X22 -> 315.52 | BP20: =Water!Y22 -> #DIV/0! | BQ20: =Water!Z22 -> #DIV/0!
A21: 17 | B21: =[3]Consp!C22 -> 33600 | C21: =Elect!J22 -> 2538 | D21: =[3]Consp!$E$6 -> 0 | E21: =Elect!M22 -> 552 | F21: =[3]Consp!G22 -> 20 | G21: =Elect!O22 -> 415 | H21: =[3]Consp!I22 -> 972 | I21: =Water!C23 -> 17.4 | J21: =[4]Consp!$K$6 -> 0 | K21: =Water!E23 -> 34.8 | L21: 0 | M21: =Water!#REF! -> #REF! | N21: =Water!#REF! -> #REF! | O21: =[5]Consp!P22 -> 998 | P21: =Water!H23 -> 53.36 | Q21: =[5]Consp!R22 -> 136 | R21: =Water!O23 -> 0 | S21: =[5]Consp!T22 -> 38 | T21: =Water!#REF! -> #REF! | U21: =[5]Consp!V22 -> 137 | V21: =Water!#REF! -> #REF! | W21: =[5]Consp!X22 -> 740 | X21: =Water!Q23 -> 30.9488 | Y21: 0 | Z21: =Water!#REF! -> #REF! | AA21: 0 | AB21: 0 | AC21: =[3]Consp!AD22 -> 690 | AD21: =Water!#REF! -> #REF! | AE21: =Water!#REF! -> #REF! | AF21: =Water!#REF! -> #REF! | AG21: =Gas!B23 -> 7835471 | AH21: =Gas!C23 -> 170.66 | AI21: =Gas!#REF! -> #REF! | AJ21: =Gas!J23 -> 1.61 | AK21: =Gas!#REF! -> #REF! | AL21: =Gas!#REF! -> #REF! | AM21: =Gas!#REF! -> #REF! | AN21: =Gas!#REF! -> #REF! | AO21: =Gas!#REF! -> #REF! | AP21: =Gas!#REF! -> #REF! | AQ21: =Gas!#REF! -> #REF! | AR21: =Gas!#REF! -> #REF! | AS21: =Gas!#REF! -> #REF! | AT21: =Elect!BK22 -> 175 | AU21: =Elect!BI22 -> 83 | AX21: =[3]Consp!BC22 -> 44.385733 | AY21: =[3]Consp!BD22 -> 22.207535 | AZ21: =[3]Consp!BE22 -> 8835.4834 | BA21: =[3]Consp!BF22 -> 11.671709 | BB21: =[3]Consp!BG22 -> 5.8397115 | BC21: =Elect!BJ22 -> 397306 | BD21: =Elect!#REF! -> #REF! | BE21: =Elect!#REF! -> #REF! | BF21: =Elect!#REF! -> #REF! | BG21: =Elect!#REF! -> #REF! | BH21: =[3]Consp!BM22 -> 1.1770145 | BI21: =[3]Consp!BN22 -> 0.58889623 | BJ21: =[3]Consp!BO22 -> 5551.4757 | BK21: =[3]Consp!BP22 -> 7.3335213 | BL21: =[3]Consp!BQ22 -> 3.6691842 | BM21: =Water!U23 -> #DIV/0! | BN21: =Water!W23 -> #DIV/0! | BO21: =Water!X23 -> 213.44 | BP21: =Water!Y23 -> #DIV/0! | BQ21: =Water!Z23 -> #DIV/0!
A22: 18 | B22: =[3]Consp!C23 -> 33600 | C22: =Elect!J23 -> 1400 | D22: =[3]Consp!$E$6 -> 0 | E22: =Elect!M23 -> 700 | F22: =[3]Consp!G23 -> 20 | G22: =Elect!O23 -> 600 | H22: =[3]Consp!I23 -> 864 | I22: =Water!C24 -> 34.8 | J22: =[4]Consp!$K$6 -> 0 | K22: =Water!E24 -> 29 | L22: 0 | M22: =Water!#REF! -> #REF! | N22: =Water!#REF! -> #REF! | O22: =[5]Consp!P23 -> 1002 | P22: =Water!H24 -> 66.12 | Q22: =[5]Consp!R23 -> 118 | R22: =Water!O24 -> 0 | S22: =[5]Consp!T23 -> 21 | T22: =Water!#REF! -> #REF! | U22: =[5]Consp!V23 -> 133 | V22: =Water!#REF! -> #REF! | W22: =[5]Consp!X23 -> 769 | X22: =Water!Q24 -> 38.3496 | Y22: 0 | Z22: =Water!#REF! -> #REF! | AA22: 0 | AB22: 0 | AC22: =[3]Consp!AD23 -> 930 | AD22: =Water!#REF! -> #REF! | AE22: =Water!#REF! -> #REF! | AF22: =Water!#REF! -> #REF! | AG22: =Gas!B24 -> 7835632 | AH22: =Gas!C24 -> 170.66 | AI22: =Gas!#REF! -> #REF! | AJ22: =Gas!J24 -> 0 | AK22: =Gas!#REF! -> #REF! | AL22: =Gas!#REF! -> #REF! | AM22: =Gas!#REF! -> #REF! | AN22: =Gas!#REF! -> #REF! | AO22: =Gas!#REF! -> #REF! | AP22: =Gas!#REF! -> #REF! | AQ22: =Gas!#REF! -> #REF! | AR22: =Gas!#REF! -> #REF! | AS22: =Gas!#REF! -> #REF! | AT22: =Elect!BK23 -> 200 | AU22: =Elect!BI23 -> 70 | AX22: =[3]Consp!BC23 -> 44.680851 | AY22: =[3]Consp!BD23 -> 22.459893 | AZ22: =[3]Consp!BE23 -> 8835.4834 | BA22: =[3]Consp!BF23 -> 11.749313 | BB22: =[3]Consp!BG23 -> 5.9060718 | BC22: =Elect!BJ23 -> 397506 | BD22: =Elect!#REF! -> #REF! | BE22: =Elect!#REF! -> #REF! | BF22: =Elect!#REF! -> #REF! | BG22: =Elect!#REF! -> #REF! | BH22: =[3]Consp!BM23 -> 1.1236702 | BI22: =[3]Consp!BN23 -> 0.56483957 | BJ22: =[3]Consp!BO23 -> 4934.645 | BK22: =[3]Consp!BP23 -> 6.562028 | BL22: =[3]Consp!BQ23 -> 3.2985595 | BM22: =Water!U24 -> #DIV/0! | BN22: =Water!W24 -> #DIV/0! | BO22: =Water!X24 -> 264.48 | BP22: =Water!Y24 -> #DIV/0! | BQ22: =Water!Z24 -> #DIV/0!
A23: 19 | B23: =[3]Consp!C24 -> 33600 | C23: =Elect!J24 -> 1869 | D23: =[3]Consp!$E$6 -> 0 | E23: =Elect!M24 -> 742 | F23: =[3]Consp!G24 -> 30 | G23: =Elect!O24 -> 733 | H23: =[3]Consp!I24 -> 894 | I23: =Water!C25 -> 11.6 | J23: =[4]Consp!$K$6 -> 0 | K23: =Water!E25 -> 52.2 | L23: 0 | M23: =Water!#REF! -> #REF! | N23: =Water!#REF! -> #REF! | O23: =[5]Consp!P24 -> 944 | P23: =Water!H25 -> 63.8 | Q23: =[5]Consp!R24 -> 110 | R23: =Water!O25 -> 0 | S23: =[5]Consp!T24 -> 14 | T23: =Water!#REF! -> #REF! | U23: =[5]Consp!V24 -> 155 | V23: =Water!#REF! -> #REF! | W23: =[5]Consp!X24 -> 721 | X23: =Water!Q25 -> 37.004 | Y23: 0 | Z23: =Water!#REF! -> #REF! | AA23: 0 | AB23: 0 | AC23: =[3]Consp!AD24 -> 660 | AD23: =Water!#REF! -> #REF! | AE23: =Water!#REF! -> #REF! | AF23: =Water!#REF! -> #REF! | AG23: =Gas!B25 -> 7835793 | AH23: =Gas!C25 -> 170.66 | AI23: =Gas!#REF! -> #REF! | AJ23: =Gas!J25 -> 1.61 | AK23: =Gas!#REF! -> #REF! | AL23: =Gas!#REF! -> #REF! | AM23: =Gas!#REF! -> #REF! | AN23: =Gas!#REF! -> #REF! | AO23: =Gas!#REF! -> #REF! | AP23: =Gas!#REF! -> #REF! | AQ23: =Gas!#REF! -> #REF! | AR23: =Gas!#REF! -> #REF! | AS23: =Gas!#REF! -> #REF! | AT23: =Elect!BK24 -> 190 | AU23: =Elect!BI24 -> 74 | AX23: =[3]Consp!BC24 -> 44.8 | AY23: =[3]Consp!BD24 -> 22.44489 | AZ23: =[3]Consp!BE24 -> 8835.4834 | BA23: =[3]Consp!BF24 -> 11.780645 | BB23: =[3]Consp!BG24 -> 5.9021265 | BC23: =Elect!BJ24 -> 397696 | BD23: =Elect!#REF! -> #REF! | BE23: =Elect!#REF! -> #REF! | BF23: =Elect!#REF! -> #REF! | BG23: =Elect!#REF! -> #REF! | BH23: =[3]Consp!BM24 -> 1.1346667 | BI23: =[3]Consp!BN24 -> 0.56847027 | BJ23: =[3]Consp!BO24 -> 5105.9869 | BK23: =[3]Consp!BP24 -> 6.8079825 | BL23: =[3]Consp!BQ24 -> 3.4108129 | BM23: =Water!U25 -> #DIV/0! | BN23: =Water!W25 -> #DIV/0! | BO23: =Water!X25 -> 255.2 | BP23: =Water!Y25 -> #DIV/0! | BQ23: =Water!Z25 -> #DIV/0!
A24: 20 | B24: =[3]Consp!C25 -> 33600 | C24: =Elect!J25 -> 1989 | D24: =[3]Consp!$E$6 -> 0 | E24: =Elect!M25 -> 508 | F24: =[3]Consp!G25 -> 20 | G24: =Elect!O25 -> 518 | H24: =[3]Consp!I25 -> 944 | I24: =Water!C26 -> 11.6 | J24: =[4]Consp!$K$6 -> 0 | K24: =Water!E26 -> 11.6 | L24: 0 | M24: =Water!#REF! -> #REF! | N24: =Water!#REF! -> #REF! | O24: =[5]Consp!P25 -> 1000 | P24: =Water!H26 -> 23.78 | Q24: =[5]Consp!R25 -> 138 | R24: =Water!O26 -> 0 | S24: =[5]Consp!T25 -> 15 | T24: =Water!#REF! -> #REF! | U24: =[5]Consp!V25 -> 165 | V24: =Water!#REF! -> #REF! | W24: =[5]Consp!X25 -> 778 | X24: =Water!Q26 -> 13.7924 | Y24: 0 | Z24: =Water!#REF! -> #REF! | AA24: 0 | AB24: 0 | AC24: =[3]Consp!AD25 -> 560 | AD24: =Water!#REF! -> #REF! | AE24: =Water!#REF! -> #REF! | AF24: =Water!#REF! -> #REF! | AG24: =Gas!B26 -> 7835954 | AH24: =Gas!C26 -> 170.66 | AI24: =Gas!#REF! -> #REF! | AJ24: =Gas!J26 -> 4.83 | AK24: =Gas!#REF! -> #REF! | AL24: =Gas!#REF! -> #REF! | AM24: =Gas!#REF! -> #REF! | AN24: =Gas!#REF! -> #REF! | AO24: =Gas!#REF! -> #REF! | AP24: =Gas!#REF! -> #REF! | AQ24: =Gas!#REF! -> #REF! | AR24: =Gas!#REF! -> #REF! | AS24: =Gas!#REF! -> #REF! | AT24: =Elect!BK25 -> 205 | AU24: =Elect!BI25 -> 84 | AX24: =[3]Consp!BC25 -> 42.857143 | AY24: =[3]Consp!BD25 -> 21.649485 | AZ24: =[3]Consp!BE25 -> 8835.4834 | BA24: =[3]Consp!BF25 -> 11.269749 | BB24: =[3]Consp!BG25 -> 5.6929661 | BC24: =Elect!BJ25 -> 397901 | BD24: =Elect!#REF! -> #REF! | BE24: =Elect!#REF! -> #REF! | BF24: =Elect!#REF! -> #REF! | BG24: =Elect!#REF! -> #REF! | BH24: =[3]Consp!BM25 -> 1.1683673 | BI24: =[3]Consp!BN25 -> 0.59020619 | BJ24: =[3]Consp!BO25 -> 5391.5566 | BK24: =[3]Consp!BP25 -> 6.8769855 | BL24: =[3]Consp!BQ25 -> 3.4739411 | BM24: =Water!U26 -> #DIV/0! | BN24: =Water!W26 -> #DIV/0! | BO24: =Water!X26 -> 95.12 | BP24: =Water!Y26 -> #DIV/0! | BQ24: =Water!Z26 -> #DIV/0!
A25: 21 | B25: =[3]Consp!C26 -> 36000 | C25: =Elect!J26 -> 2346 | D25: =[3]Consp!$E$6 -> 0 | E25: =Elect!M26 -> 799 | F25: =[3]Consp!G26 -> 20 | G25: =Elect!O26 -> 878 | H25: =[3]Consp!I26 -> 916 | I25: =Water!C27 -> 5.8 | J25: =[4]Consp!$K$6 -> 0 | K25: =Water!E27 -> 5.8 | L25: 0 | M25: =Water!#REF! -> #REF! | N25: =Water!#REF! -> #REF! | O25: =[5]Consp!P26 -> 998 | P25: =Water!H27 -> 11.6 | Q25: =[5]Consp!R26 -> 186 | R25: =Water!O27 -> 0 | S25: =[5]Consp!T26 -> 43 | T25: =Water!#REF! -> #REF! | U25: =[5]Consp!V26 -> 176 | V25: =Water!#REF! -> #REF! | W25: =[5]Consp!X26 -> 773 | X25: =Water!Q27 -> 6.728 | Y25: 0 | Z25: =Water!#REF! -> #REF! | AA25: 0 | AB25: 0 | AC25: =[3]Consp!AD26 -> 950 | AD25: =Water!#REF! -> #REF! | AE25: =Water!#REF! -> #REF! | AF25: =Water!#REF! -> #REF! | AG25: =Gas!B27 -> 7836115 | AH25: =Gas!C27 -> 170.66 | AI25: =Gas!#REF! -> #REF! | AJ25: =Gas!J27 -> 1.61 | AK25: =Gas!#REF! -> #REF! | AL25: =Gas!#REF! -> #REF! | AM25: =Gas!#REF! -> #REF! | AN25: =Gas!#REF! -> #REF! | AO25: =Gas!#REF! -> #REF! | AP25: =Gas!#REF! -> #REF! | AQ25: =Gas!#REF! -> #REF! | AR25: =Gas!#REF! -> #REF! | AS25: =Gas!#REF! -> #REF! | AT25: =Elect!BK26 -> 264 | AU25: =Elect!BI26 -> 102 | AX25: =[3]Consp!BC26 -> 43.956044 | AY25: =[3]Consp!BD26 -> 22.222222 | AZ25: =[3]Consp!BE26 -> 9371.6914 | BA25: =[3]Consp!BF26 -> 11.442847 | BB25: =[3]Consp!BG26 -> 5.7849947 | BC25: =Elect!BJ26 -> 398165 | BD25: =Elect!#REF! -> #REF! | BE25: =Elect!#REF! -> #REF! | BF25: =Elect!#REF! -> #REF! | BG25: =Elect!#REF! -> #REF! | BH25: =[3]Consp!BM26 -> 1.0586081 | BI25: =[3]Consp!BN26 -> 0.53518519 | BJ25: =[3]Consp!BO26 -> 5231.6376 | BK25: =[3]Consp!BP26 -> 6.3878358 | BL25: =[3]Consp!BQ26 -> 3.2294059 | BM25: =Water!U27 -> #DIV/0! | BN25: =Water!W27 -> #DIV/0! | BO25: =Water!X27 -> 46.4 | BP25: =Water!Y27 -> #DIV/0! | BQ25: =Water!Z27 -> #DIV/0!
A26: 22 | B26: =[3]Consp!C27 -> 33600 | C26: =Elect!J27 -> 1254 | D26: =[3]Consp!$E$6 -> 0 | E26: =Elect!M27 -> 392 | F26: =[3]Consp!G27 -> 20 | G26: =Elect!O27 -> 491 | H26: =[3]Consp!I27 -> 931 | I26: =Water!C28 -> 5.8 | J26: =[4]Consp!$K$6 -> 0 | K26: =Water!E28 -> 17.4 | L26: 0 | M26: =Water!#REF! -> #REF! | N26: =Water!#REF! -> #REF! | O26: =[5]Consp!P27 -> 969 | P26: =Water!H28 -> 23.2 | Q26: =[5]Consp!R27 -> 151 | R26: =Water!O28 -> 0 | S26: =[5]Consp!T27 -> 29 | T26: =Water!#REF! -> #REF! | U26: =[5]Consp!V27 -> 157 | V26: =Water!#REF! -> #REF! | W26: =[5]Consp!X27 -> 697 | X26: =Water!Q28 -> 13.456 | Y26: 0 | Z26: =Water!#REF! -> #REF! | AA26: 0 | AB26: 0 | AC26: =[3]Consp!AD27 -> 700 | AD26: =Water!#REF! -> #REF! | AE26: =Water!#REF! -> #REF! | AF26: =Water!#REF! -> #REF! | AG26: =Gas!B28 -> 7836276 | AH26: =Gas!C28 -> 170.66 | AI26: =Gas!#REF! -> #REF! | AJ26: =Gas!J28 -> 3.22 | AK26: =Gas!#REF! -> #REF! | AL26: =Gas!#REF! -> #REF! | AM26: =Gas!#REF! -> #REF! | AN26: =Gas!#REF! -> #REF! | AO26: =Gas!#REF! -> #REF! | AP26: =Gas!#REF! -> #REF! | AQ26: =Gas!#REF! -> #REF! | AR26: =Gas!#REF! -> #REF! | AS26: =Gas!#REF! -> #REF! | AT26: =Elect!BK27 -> 79 | AU26: =Elect!BI27 -> 39 | AX26: =[3]Consp!BC27 -> 39.952438 | AY26: =[3]Consp!BD27 -> 20.253165 | AZ26: =[3]Consp!BE27 -> 8835.4834 | BA26: =[3]Consp!BF27 -> 10.505926 | BB26: =[3]Consp!BG27 -> 5.3257887 | BC26: =Elect!BJ27 -> 398244 | BD26: =Elect!#REF! -> #REF! | BE26: =Elect!#REF! -> #REF! | BF26: =Elect!#REF! -> #REF! | BG26: =Elect!#REF! -> #REF! | BH26: =[3]Consp!BM27 -> 1.0903686 | BI26: =[3]Consp!BN27 -> 0.55274262 | BJ26: =[3]Consp!BO27 -> 5317.3085 | BK26: =[3]Consp!BP27 -> 6.3226022 | BL26: =[3]Consp!BQ27 -> 3.2051287 | BM26: =Water!U28 -> #DIV/0! | BN26: =Water!W28 -> #DIV/0! | BO26: =Water!X28 -> 92.8 | BP26: =Water!Y28 -> #DIV/0! | BQ26: =Water!Z28 -> #DIV/0!
A27: 23 | B27: =[3]Consp!C28 -> 36000 | C27: =Elect!J28 -> 1754 | D27: =[3]Consp!$E$6 -> 0 | E27: =Elect!M28 -> 540 | F27: =[3]Consp!G28 -> 30 | G27: =Elect!O28 -> 661 | H27: =[3]Consp!I28 -> 1009 | I27: =Water!C29 -> 0 | J27: =[4]Consp!$K$6 -> 0 | K27: =Water!E29 -> 162.4 | L27: 0 | M27: =Water!#REF! -> #REF! | N27: =Water!#REF! -> #REF! | O27: =[5]Consp!P28 -> 902 | P27: =Water!H29 -> 162.4 | Q27: =[5]Consp!R28 -> 131 | R27: =Water!O29 -> 0 | S27: =[5]Consp!T28 -> 6 | T27: =Water!#REF! -> #REF! | U27: =[5]Consp!V28 -> 167 | V27: =Water!#REF! -> #REF! | W27: =[5]Consp!X28 -> 748 | X27: =Water!Q29 -> 94.192 | Y27: 0 | Z27: =Water!#REF! -> #REF! | AA27: 0 | AB27: 0 | AC27: =[3]Consp!AD28 -> 690 | AD27: =Water!#REF! -> #REF! | AE27: =Water!#REF! -> #REF! | AF27: =Water!#REF! -> #REF! | AG27: =Gas!B29 -> 7836437 | AH27: =Gas!C29 -> 170.66 | AI27: =Gas!#REF! -> #REF! | AJ27: =Gas!J29 -> 1.61 | AK27: =Gas!#REF! -> #REF! | AL27: =Gas!#REF! -> #REF! | AM27: =Gas!#REF! -> #REF! | AN27: =Gas!#REF! -> #REF! | AO27: =Gas!#REF! -> #REF! | AP27: =Gas!#REF! -> #REF! | AQ27: =Gas!#REF! -> #REF! | AR27: =Gas!#REF! -> #REF! | AS27: =Gas!#REF! -> #REF! | AT27: =Elect!BK28 -> 204 | AU27: =Elect!BI28 -> 85 | AX27: =[3]Consp!BC28 -> 42.755344 | AY27: =[3]Consp!BD28 -> 21.543986 | AZ27: =[3]Consp!BE28 -> 9371.6914 | BA27: =[3]Consp!BF28 -> 11.130275 | BB27: =[3]Consp!BG28 -> 5.6084329 | BC27: =Elect!BJ28 -> 398448 | BD27: =Elect!#REF! -> #REF! | BE27: =Elect!#REF! -> #REF! | BF27: =Elect!#REF! -> #REF! | BG27: =Elect!#REF! -> #REF! | BH27: =[3]Consp!BM28 -> 1.0712589 | BI27: =[3]Consp!BN28 -> 0.53979653 | BJ27: =[3]Consp!BO28 -> 5762.7973 | BK27: =[3]Consp!BP28 -> 6.8441773 | BL27: =[3]Consp!BQ28 -> 3.4487117 | BM27: =Water!U29 -> #DIV/0! | BN27: =Water!W29 -> #DIV/0! | BO27: =Water!X29 -> 649.6 | BP27: =Water!Y29 -> #DIV/0! | BQ27: =Water!Z29 -> #DIV/0!
A28: 24 | B28: =[3]Consp!C29 -> 33600 | C28: =Elect!J29 -> 1532 | D28: =[3]Consp!$E$6 -> 0 | E28: =Elect!M29 -> 897 | F28: =[3]Consp!G29 -> 20 | G28: =Elect!O29 -> 984 | H28: =[3]Consp!I29 -> 891 | I28: =Water!C30 -> 0 | J28: =[4]Consp!$K$6 -> 0 | K28: =Water!E30 -> 69.6 | L28: 0 | M28: =Water!#REF! -> #REF! | N28: =Water!#REF! -> #REF! | O28: =[5]Consp!P29 -> 818 | P28: =Water!H30 -> 69.6 | Q28: =[5]Consp!R29 -> 221 | R28: =Water!O30 -> 0 | S28: =[5]Consp!T29 -> 93 | T28: =Water!#REF! -> #REF! | U28: =[5]Consp!V29 -> 191 | V28: =Water!#REF! -> #REF! | W28: =[5]Consp!X29 -> 827 | X28: =Water!Q30 -> 40.368 | Y28: 0 | Z28: =Water!#REF! -> #REF! | AA28: 0 | AB28: 0 | AC28: =[3]Consp!AD29 -> 470 | AD28: =Water!#REF! -> #REF! | AE28: =Water!#REF! -> #REF! | AF28: =Water!#REF! -> #REF! | AG28: =Gas!B30 -> 7836598 | AH28: =Gas!C30 -> 170.66 | AI28: =Gas!#REF! -> #REF! | AJ28: =Gas!J30 -> 0 | AK28: =Gas!#REF! -> #REF! | AL28: =Gas!#REF! -> #REF! | AM28: =Gas!#REF! -> #REF! | AN28: =Gas!#REF! -> #REF! | AO28: =Gas!#REF! -> #REF! | AP28: =Gas!#REF! -> #REF! | AQ28: =Gas!#REF! -> #REF! | AR28: =Gas!#REF! -> #REF! | AS28: =Gas!#REF! -> #REF! | AT28: =Elect!BK29 -> 289 | AU28: =Elect!BI29 -> 118 | AX28: =[3]Consp!BC29 -> 39.904988 | AY28: =[3]Consp!BD29 -> 20.289855 | AZ28: =[3]Consp!BE29 -> 8835.4834 | BA28: =[3]Consp!BF29 -> 10.493448 | BB28: =[3]Consp!BG29 -> 5.3354369 | BC28: =Elect!BJ29 -> 398737 | BD28: =Elect!#REF! -> #REF! | BE28: =Elect!#REF! -> #REF! | BF28: =Elect!#REF! -> #REF! | BG28: =Elect!#REF! -> #REF! | BH28: =[3]Consp!BM29 -> 1.1104513 | BI28: =[3]Consp!BN29 -> 0.56461353 | BJ28: =[3]Consp!BO29 -> 5088.8527 | BK28: =[3]Consp!BP29 -> 6.043768 | BL28: =[3]Consp!BQ29 -> 3.0729787 | BM28: =Water!U30 -> #DIV/0! | BN28: =Water!W30 -> #DIV/0! | BO28: =Water!X30 -> 278.4 | BP28: =Water!Y30 -> #DIV/0! | BQ28: =Water!Z30 -> #DIV/0!
A29: 25 | B29: =[3]Consp!C30 -> 33600 | C29: =Elect!J30 -> 2468 | D29: =[3]Consp!$E$6 -> 0 | E29: =Elect!M30 -> 377 | F29: =[3]Consp!G30 -> 20 | G29: =Elect!O30 -> 395 | H29: =[3]Consp!I30 -> 1008 | I29: =Water!C31 -> 0 | J29: =[4]Consp!$K$6 -> 0 | K29: =Water!E31 -> 81.2 | L29: 0 | M29: =Water!#REF! -> #REF! | N29: =Water!#REF! -> #REF! | O29: =[5]Consp!P30 -> 1290 | P29: =Water!H31 -> 81.2 | Q29: =[5]Consp!R30 -> 34 | R29: =Water!O31 -> 0 | S29: =[5]Consp!T30 -> 34 | T29: =Water!#REF! -> #REF! | U29: =[5]Consp!V30 -> 55 | V29: =Water!#REF! -> #REF! | W29: =[5]Consp!X30 -> 681 | X29: =Water!Q31 -> 47.096 | Y29: 0 | Z29: =Water!#REF! -> #REF! | AA29: 0 | AB29: 0 | AC29: =[3]Consp!AD30 -> 1170 | AD29: =Water!#REF! -> #REF! | AE29: =Water!#REF! -> #REF! | AF29: =Water!#REF! -> #REF! | AG29: =Gas!B31 -> 7836759 | AH29: =Gas!C31 -> 170.66 | AI29: =Gas!#REF! -> #REF! | AJ29: =Gas!J31 -> 0 | AK29: =Gas!#REF! -> #REF! | AL29: =Gas!#REF! -> #REF! | AM29: =Gas!#REF! -> #REF! | AN29: =Gas!#REF! -> #REF! | AO29: =Gas!#REF! -> #REF! | AP29: =Gas!#REF! -> #REF! | AQ29: =Gas!#REF! -> #REF! | AR29: =Gas!#REF! -> #REF! | AS29: =Gas!#REF! -> #REF! | AT29: =Elect!BK30 -> 81 | AU29: =Elect!BI30 -> 35 | AX29: =[3]Consp!BC30 -> 39.763314 | AY29: =[3]Consp!BD30 -> 20.20445 | AZ29: =[3]Consp!BE30 -> 8835.4834 | BA29: =[3]Consp!BF30 -> 10.456193 | BB29: =[3]Consp!BG30 -> 5.3129786 | BC29: =Elect!BJ30 -> 398818 | BD29: =Elect!#REF! -> #REF! | BE29: =Elect!#REF! -> #REF! | BF29: =Elect!#REF! -> #REF! | BG29: =Elect!#REF! -> #REF! | BH29: =[3]Consp!BM30 -> 1.0059172 | BI29: =[3]Consp!BN30 -> 0.51112447 | BJ29: =[3]Consp!BO30 -> 5757.0859 | BK29: =[3]Consp!BP30 -> 6.8131194 | BL29: =[3]Consp!BQ30 -> 3.4618676 | BM29: =Water!U31 -> #DIV/0! | BN29: =Water!W31 -> #DIV/0! | BO29: =Water!X31 -> 324.8 | BP29: =Water!Y31 -> #DIV/0! | BQ29: =Water!Z31 -> #DIV/0!
A30: 26 | B30: =[3]Consp!C31 -> 31200 | C30: =Elect!J31 -> 1519 | D30: =[3]Consp!$E$6 -> 0 | E30: =Elect!M31 -> 586 | F30: =[3]Consp!G31 -> 20 | G30: =Elect!O31 -> 652 | H30: =[3]Consp!I31 -> 760 | I30: =Water!C32 -> 5.8 | J30: =[4]Consp!$K$6 -> 0 | K30: =Water!E32 -> 92.8 | L30: 0 | M30: =Water!#REF! -> #REF! | N30: =Water!#REF! -> #REF! | O30: =[5]Consp!P31 -> 1004 | P30: =Water!H32 -> 98.6 | Q30: =[5]Consp!R31 -> 131 | R30: =Water!O32 -> 0 | S30: =[5]Consp!T31 -> 33 | T30: =Water!#REF! -> #REF! | U30: =[5]Consp!V31 -> 145 | V30: =Water!#REF! -> #REF! | W30: =[5]Consp!X31 -> 916 | X30: =Water!Q32 -> 57.188 | Y30: 0 | Z30: =Water!#REF! -> #REF! | AA30: 0 | AB30: 0 | AC30: =[3]Consp!AD31 -> 810 | AD30: =Water!#REF! -> #REF! | AE30: =Water!#REF! -> #REF! | AF30: =Water!#REF! -> #REF! | AG30: =Gas!B32 -> 7836920 | AH30: =Gas!C32 -> 170.66 | AI30: =Gas!#REF! -> #REF! | AJ30: =Gas!J32 -> 3.22 | AK30: =Gas!#REF! -> #REF! | AL30: =Gas!#REF! -> #REF! | AM30: =Gas!#REF! -> #REF! | AN30: =Gas!#REF! -> #REF! | AO30: =Gas!#REF! -> #REF! | AP30: =Gas!#REF! -> #REF! | AQ30: =Gas!#REF! -> #REF! | AR30: =Gas!#REF! -> #REF! | AS30: =Gas!#REF! -> #REF! | AT30: =Elect!BK31 -> 200 | AU30: =Elect!BI31 -> 85 | AX30: =[3]Consp!BC31 -> 37.275986 | AY30: =[3]Consp!BD31 -> 18.989653 | AZ30: =[3]Consp!BE31 -> 8299.2754 | BA30: =[3]Consp!BF31 -> 9.9155023 | BB30: =[3]Consp!BG31 -> 5.0512936 | BC30: =Elect!BJ31 -> 399018 | BD30: =Elect!#REF! -> #REF! | BE30: =Elect!#REF! -> #REF! | BF30: =Elect!#REF! -> #REF! | BG30: =Elect!#REF! -> #REF! | BH30: =[3]Consp!BM31 -> 1.1063321 | BI30: =[3]Consp!BN31 -> 0.56360316 | BJ30: =[3]Consp!BO31 -> 4340.66 | BK30: =[3]Consp!BP31 -> 5.1859737 | BL30: =[3]Consp!BQ31 -> 2.6419111 | BM30: =Water!U32 -> #DIV/0! | BN30: =Water!W32 -> #DIV/0! | BO30: =Water!X32 -> 394.4 | BP30: =Water!Y32 -> #DIV/0! | BQ30: =Water!Z32 -> #DIV/0!
... A32: 28 | B32: =[3]Consp!C33 -> 33600 | C32: =Elect!J33 -> 1680 | D32: =[3]Consp!$E$6 -> 0 | E32: =Elect!M33 -> 523 | F32: =[3]Consp!G33 -> 20 | G32: =Elect!O33 -> 638 | H32: =[3]Consp!I33 -> 1008 | I32: =Water!C34 -> 5.8 | J32: =[4]Consp!$K$6 -> 0 | K32: =Water!E34 -> 63.8 | L32: 1 | M32: =Water!#REF! -> #REF! | N32: =Water!#REF! -> #REF! | O32: =[5]Consp!P33 -> 1013 | P32: =Water!H34 -> 69.6 | Q32: =[5]Consp!R33 -> 142 | R32: =Water!O34 -> 0 | S32: =[5]Consp!T33 -> 13 | T32: =Water!#REF! -> #REF! | U32: =[5]Consp!V33 -> 155 | V32: =Water!#REF! -> #REF! | W32: =[5]Consp!X33 -> 825 | X32: =Water!Q34 -> 40.368 | Y32: 1 | Z32: =Water!#REF! -> #REF! | AA32: 0 | AB32: 0 | AC32: =[3]Consp!AD33 -> 650 | AD32: =Water!#REF! -> #REF! | AE32: =Water!#REF! -> #REF! | AF32: =Water!#REF! -> #REF! | AG32: =Gas!B34 -> 7837136 | AH32: =Gas!C34 -> 58.3 | AI32: =Gas!#REF! -> #REF! | AJ32: =Gas!J34 -> 1.61 | AK32: =Gas!#REF! -> #REF! | AL32: =Gas!#REF! -> #REF! | AM32: =Gas!#REF! -> #REF! | AN32: =Gas!#REF! -> #REF! | AO32: =Gas!#REF! -> #REF! | AP32: =Gas!#REF! -> #REF! | AQ32: =Gas!#REF! -> #REF! | AR32: =Gas!#REF! -> #REF! | AS32: =Gas!#REF! -> #REF! | AT32: =Elect!BK33 -> 154 | AU32: =Elect!BI33 -> 60 | AX32: =[3]Consp!BC33 -> 45.34413 | AY32: =[3]Consp!BD33 -> 22.687373 | AZ32: =[3]Consp!BE33 -> 8835.4834 | BA32: =[3]Consp!BF33 -> 11.923729 | BB32: =[3]Consp!BG33 -> 5.9658902 | BC32: =Elect!BJ33 -> 399375 | BD32: =Elect!#REF! -> #REF! | BE32: =Elect!#REF! -> #REF! | BF32: =Elect!#REF! -> #REF! | BG32: =Elect!#REF! -> #REF! | BH32: =[3]Consp!BM33 -> 1.2294197 | BI32: =[3]Consp!BN33 -> 0.61512492 | BJ32: =[3]Consp!BO33 -> 5757.0859 | BK32: =[3]Consp!BP33 -> 7.7693467 | BL32: =[3]Consp!BQ33 -> 3.8872963 | BM32: =Water!U34 -> #DIV/0! | BN32: =Water!W34 -> #DIV/0! | BO32: =Water!X34 -> 278.4 | BP32: =Water!Y34 -> #DIV/0! | BQ32: =Water!Z34 -> #DIV/0!
A33: MTD | B33: =[3]Consp!C35 -> 931200 | C33: =Elect!J34 -> 2214 | D33: =[3]Consp!$E$6 -> 0 | E33: =Elect!M34 -> 754 | F33: =[3]Consp!G35 -> 600 | G33: =Elect!O34 -> 871 | H33: =[3]Consp!I35 -> 24543 | I33: =Water!C38 -> 1287.6 | J33: =[4]Consp!$K$6 -> 0 | K33: =Water!E39 -> 42.096774 | L33: 3 | M33: =Water!#REF! -> #REF! | N33: =Water!#REF! -> #REF! | O33: =[5]Consp!P34 -> 1013 | P33: =Water!H38 -> 2639.58 | Q33: =[5]Consp!R34 -> 109 | R33: =Water!O38 -> 0 | S33: =[5]Consp!T34 -> 15 | T33: =Water!#REF! -> #REF! | U33: =[5]Consp!V34 -> 147 | V33: =Water!#REF! -> #REF! | W33: =[5]Consp!X34 -> 730 | X33: =Water!Q38 -> 1477.1324 | Y33: 3 | Z33: =Water!#REF! -> #REF! | AA33: 0 | AB33: 0 | AC33: =[3]Consp!AD35 -> 0 | AD33: =Water!#REF! -> #REF! | AE33: =Water!#REF! -> #REF! | AF33: =Water!#REF! -> #REF! | AG33: =Gas!B38 -> 0 | AH33: =Gas!C38 -> 4929 | AI33: =Gas!#REF! -> #REF! | AJ33: =Gas!J38 -> 56.35 | AK33: =Gas!#REF! -> #REF! | AL33: =Gas!#REF! -> #REF! | AM33: =Gas!#REF! -> #REF! | AN33: =Gas!#REF! -> #REF! | AO33: =Gas!#REF! -> #REF! | AP33: =Gas!#REF! -> #REF! | AQ33: =Gas!#REF! -> #REF! | AR33: =Gas!#REF! -> #REF! | AS33: =Gas!#REF! -> #REF! | AT33: =Elect!BK34 -> 216 | AU33: =Elect!BI34 -> 85 | AX33: =[3]Consp!BC35 -> 45.411099 | AY33: =[3]Consp!BD35 -> 22.844806 | AZ33: =[3]Consp!BE35 -> 245248.7 | BA33: =[3]Consp!BF35 -> 11.959851 | BB33: =[3]Consp!BG35 -> 6.0166013 | BC33: =Elect!BJ34 -> 399591 | BD33: =Elect!#REF! -> #REF! | BE33: =Elect!#REF! -> #REF! | BF33: =Elect!#REF! -> #REF! | BG33: =Elect!#REF! -> #REF! | BH33: =[3]Consp!BM35 -> 1.1514679 | BI33: =[3]Consp!BN35 -> 0.57929342 | BJ33: =[3]Consp!BO35 -> 140121.3 | BK33: =[3]Consp!BP35 -> 6.8331854 | BL33: =[3]Consp!BQ35 -> 3.4377159 | BM33: =Water!U38 -> #DIV/0! | BN33: =Water!W38 -> #DIV/0! | BO33: =Water!X38 -> 10558.32 | BP33: =Water!Y38 -> #DIV/0! | BQ33: =Water!Z38 -> #DIV/0!
A34: AVER. Act | B34: =[3]Consp!C36 -> 33257.143 | C34: =Elect!J35 -> 2214 | D34: =[3]Consp!$E$6 -> 0 | E34: =Elect!M35 -> 754 | F34: =[3]Consp!G36 -> 21.428571 | G34: =Elect!O35 -> 871 | H34: =[3]Consp!I36 -> 876.53571 | I34: =Water!C39 -> 41.535484 | J34: =[4]Consp!$K$6 -> 0 | K34: =Water!E40 -> 0 | L34: 4 | M34: =Water!#REF! -> #REF! | N34: =Water!#REF! -> #REF! | O34: =[5]Consp!P35 -> 1014 | P34: =Water!H39 -> 85.147742 | Q34: =[5]Consp!R35 -> 138 | R34: =Water!O39 -> 0 | S34: =[5]Consp!T35 -> 24 | T34: =Water!#REF! -> #REF! | U34: =[5]Consp!V35 -> 145 | V34: =Water!#REF! -> #REF! | W34: =[5]Consp!X35 -> 877 | X34: =Water!Q39 -> 47.649432 | Y34: 4 | Z34: =Water!#REF! -> #REF! | AA34: 0 | AB34: 0 | AC34: =[3]Consp!AD36 -> 0 | AD34: =Water!#REF! -> #REF! | AE34: =Water!#REF! -> #REF! | AF34: =Water!#REF! -> #REF! | AG34: =Gas!B39 -> 0 | AH34: =Gas!C39 -> 164.3 | AI34: =Gas!#REF! -> #REF! | AJ34: =Gas!J39 -> #REF! | AK34: =Gas!#REF! -> #REF! | AL34: =Gas!#REF! -> #REF! | AM34: =Gas!#REF! -> #REF! | AN34: =Gas!#REF! -> #REF! | AO34: =Gas!#REF! -> #REF! | AP34: =Gas!#REF! -> #REF! | AQ34: =Gas!#REF! -> #REF! | AR34: =Gas!#REF! -> #REF! | AS34: =Gas!#REF! -> #REF! | AT34: =Elect!BK35 -> 216 | AU34: =Elect!BI35 -> 85 | AX34: =[3]Consp!BC36 -> 45.411099 | AY34: =[3]Consp!BD36 -> 22.844806 | AZ34: =[3]Consp!BE36 -> 8758.8823 | BA34: =[3]Consp!BF36 -> 11.959851 | BB34: =[3]Consp!BG36 -> 6.0166013 | BC34: =Elect!BJ35 -> 399807 | BD34: =Elect!#REF! -> #REF! | BE34: =Elect!#REF! -> #REF! | BF34: =Elect!#REF! -> #REF! | BG34: =Elect!#REF! -> #REF! | BH34: =[3]Consp!BM36 -> 1.1761372 | BI34: =[3]Consp!BN36 -> 0.60007377 | BJ34: =[3]Consp!BO36 -> 5004.3322 | BK34: =[3]Consp!BP36 -> 6.8331854 | BL34: =[3]Consp!BQ36 -> 3.4377159 | BM34: =Water!U39 -> #DIV/0! | BN34: =Water!W39 -> #DIV/0! | BO34: =Water!X39 -> 340.59097 | BP34: =Water!Y39 -> #DIV/0! | BQ34: =Water!Z39 -> #DIV/0!
A35: TOTAL Budget | B35: =[3]Consp!C37 -> 1040026 | C35: =Elect!J5 -> 0 | D35: =[3]Consp!$E$6 -> 0 | E35: =Elect!M5 -> 0 | F35: =[3]Consp!G37 -> 0 | G35: =Elect!O5 -> 0 | H35: =[3]Consp!I37 -> 0 | I35: =Water!C40 -> 0 | J35: =[4]Consp!$K$6 -> 0 | K35: =Water!E41 -> 0 | L35: 5 | M35: =Water!#REF! -> #REF! | N35: =Water!#REF! -> #REF! | O35: =[5]Consp!P36 -> 1010 | P35: =Water!H40 -> 0 | Q35: =[5]Consp!R36 -> 148 | R35: =Water!O40 -> 0 | S35: =[5]Consp!T36 -> 22 | T35: =Water!#REF! -> #REF! | U35: =[5]Consp!V36 -> 151 | V35: =Water!#REF! -> #REF! | W35: =[5]Consp!X36 -> 833 | X35: =Water!Q40 -> 0 | Y35: 5 | Z35: =Water!#REF! -> #REF! | AA35: 0 | AB35: 0 | AC35: =[3]Consp!AD37 -> 0 | AD35: =Water!#REF! -> #REF! | AE35: =Water!#REF! -> #REF! | AF35: =Water!#REF! -> #REF! | AG35: =Gas!B40 -> 0 | AH35: =Gas!C40 -> 0 | AI35: =Gas!#REF! -> #REF! | AJ35: =Gas!J40 -> 0 | AK35: =Gas!#REF! -> #REF! | AL35: =Gas!#REF! -> #REF! | AM35: =Gas!#REF! -> #REF! | AN35: =Gas!#REF! -> #REF! | AO35: =Gas!#REF! -> #REF! | AP35: =Gas!#REF! -> #REF! | AQ35: =Gas!#REF! -> #REF! | AR35: =Gas!#REF! -> #REF! | AS35: =Gas!#REF! -> #REF! | AT35: =Elect!BK5 -> 0 | AU35: =Elect!BI5 -> 0 | AX35: =[3]Consp!BC37 -> 45.679286 | AY35: =[3]Consp!BD37 -> 23.305904 | AZ35: =[3]Consp!BE37 -> 264708.4 | BA35: =[3]Consp!BF37 -> 11.626335 | BB35: =[3]Consp!BG37 -> 5.9318409 | BC35: =Elect!BJ5 -> 394126 | BD35: =Elect!#REF! -> #REF! | BE35: =Elect!#REF! -> #REF! | BF35: =Elect!#REF! -> #REF! | BG35: =Elect!#REF! -> #REF! | BH35: =[3]Consp!BM37 -> 1.1761372 | BI35: =[3]Consp!BN37 -> 0.60007377 | BJ35: =[3]Consp!BO37 -> 150494 | BK35: =[3]Consp!BP37 -> 6.6098911 | BL35: =[3]Consp!BQ37 -> 3.3724146 | BM35: =Water!U40 -> #REF! | BN35: =Water!W40 -> #REF! | BO35: =Water!X40 -> 0 | BP35: =Water!Y40 -> 0 | BQ35: =Water!Z40 -> 0
A36: Budget MTD | B36: =[3]Consp!C38 -> 1040026 | C36: =Elect!#REF! -> #REF! | D36: =[3]Consp!$E$6 -> 0 | E36: =Elect!#REF! -> #REF! | F36: =[3]Consp!G38 -> 0 | G36: =Elect!#REF! -> #REF! | H36: =[3]Consp!I38 -> 0 | I36: =Water!C41 -> 0 | J36: =[4]Consp!$K$6 -> 0 | K36: =Water!E42 -> 0 | L36: 6 | M36: =Water!#REF! -> #REF! | N36: =Water!#REF! -> #REF! | O36: =[5]Consp!P37 -> 30039 | P36: =Water!H41 -> 0 | Q36: =[5]Consp!R37 -> 129.54839 | R36: =Water!O41 -> 0 | S36: =[5]Consp!T37 -> 719 | T36: =Water!#REF! -> #REF! | U36: =[5]Consp!V37 -> 4609 | V36: =Water!#REF! -> #REF! | W36: =[5]Consp!X37 -> 23430 | X36: =Water!Q41 -> 0 | Y36: 6 | Z36: =Water!#REF! -> #REF! | AA36: 0 | AB36: 0 | AC36: =[3]Consp!AD38 -> 0 | AD36: =Water!#REF! -> #REF! | AE36: =Water!#REF! -> #REF! | AF36: =Water!#REF! -> #REF! | AG36: =Gas!B41 -> 0 | AH36: =Gas!C41 -> 0 | AI36: =Gas!#REF! -> #REF! | AJ36: =Gas!J41 -> 0 | AK36: =Gas!#REF! -> #REF! | AL36: =Gas!#REF! -> #REF! | AM36: =Gas!#REF! -> #REF! | AN36: =Gas!#REF! -> #REF! | AO36: =Gas!#REF! -> #REF! | AP36: =Gas!#REF! -> #REF! | AQ36: =Gas!#REF! -> #REF! | AR36: =Gas!#REF! -> #REF! | AS36: =Gas!#REF! -> #REF! | AT36: =Elect!#REF! -> #REF! | AU36: =Elect!#REF! -> #REF! | AX36: =[3]Consp!BC38 -> 45.679286 | AY36: =[3]Consp!BD38 -> 23.305904 | AZ36: =[3]Consp!BE38 -> 264708.4 | BA36: =[3]Consp!BF38 -> 11.626335 | BB36: =[3]Consp!BG38 -> 5.9318409 | BC36: =Elect!#REF! -> #REF! | BD36: =Elect!#REF! -> #REF! | BE36: =Elect!#REF! -> #REF! | BF36: =Elect!#REF! -> #REF! | BG36: =Elect!#REF! -> #REF! | BH36: =[3]Consp!BM38 -> 0 | BI36: =[3]Consp!BN38 -> 0 | BJ36: =[3]Consp!BO38 -> 135930.06 | BK36: =[3]Consp!BP38 -> 6.6098911 | BL36: =[3]Consp!BQ38 -> 3.3724146 | BM36: =Water!U41 -> #REF! | BN36: =Water!W41 -> #REF! | BO36: =Water!X41 -> #REF! | BP36: =Water!Y41 -> #REF! | BQ36: =Water!Z41 -> #REF!
A37: AVER. Bud | B37: =[3]Consp!C39 -> 37143.785 | C37: =Elect!J39 -> 0 | D37: =[3]Consp!$E$6 -> 0 | E37: =Elect!M39 -> 0 | F37: =[3]Consp!G39 -> 0 | G37: =Elect!O39 -> 0 | H37: =[3]Consp!I39 -> 0 | I37: =Water!C42 -> 0 | J37: =[4]Consp!$K$6 -> 0 | K37: =Water!E43 -> 0 | L37: 7 | M37: =Water!#REF! -> #REF! | N37: =Water!#REF! -> #REF! | O37: =[5]Consp!P38 -> 969 | P37: =Water!H42 -> 0 | Q37: =[5]Consp!R38 -> 0 | R37: =Water!O42 -> 0 | S37: =[5]Consp!T38 -> 23.193548 | T37: =Water!#REF! -> #REF! | U37: =[5]Consp!V38 -> 148.67742 | V37: =Water!#REF! -> #REF! | W37: =[5]Consp!X38 -> 755.80645 | X37: =Water!Q42 -> 0 | Y37: 7 | Z37: =Water!#REF! -> #REF! | AA37: 0 | AB37: 0 | AC37: =[3]Consp!AD39 -> 0 | AD37: =Water!#REF! -> #REF! | AE37: =Water!#REF! -> #REF! | AF37: =Water!#REF! -> #REF! | AG37: =Gas!B42 -> 0 | AH37: =Gas!C42 -> 0 | AI37: =Gas!#REF! -> #REF! | AJ37: =Gas!J42 -> #REF! | AK37: =Gas!#REF! -> #REF! | AL37: =Gas!#REF! -> #REF! | AM37: =Gas!#REF! -> #REF! | AN37: =Gas!#REF! -> #REF! | AO37: =Gas!#REF! -> #REF! | AP37: =Gas!#REF! -> #REF! | AQ37: =Gas!#REF! -> #REF! | AR37: =Gas!#REF! -> #REF! | AS37: =Gas!#REF! -> #REF! | AT37: =Elect!BK39 -> 0 | AU37: =Elect!BI39 -> 0 | AX37: =[3]Consp!BC39 -> 0 | AY37: =[3]Consp!BD39 -> 0 | AZ37: =[3]Consp!BE39 -> 9453.8714 | BA37: =[3]Consp!BF39 -> 0 | BB37: =[3]Consp!BG39 -> 0 | BC37: =Elect!BJ39 -> 0 | BD37: =Elect!#REF! -> #REF! | BE37: =Elect!#REF! -> #REF! | BF37: =Elect!#REF! -> #REF! | BG37: =Elect!#REF! -> #REF! | BH37: =[3]Consp!BM39 -> 0 | BI37: =[3]Consp!BN39 -> 0 | BJ37: =[3]Consp!BO39 -> 0 | BK37: =[3]Consp!BP39 -> 0 | BL37: =[3]Consp!BQ39 -> 0 | BM37: =Water!U42 -> 0 | BN37: =Water!W42 -> 0 | BO37: =Water!X42 -> 0 | BP37: =Water!Y42 -> 0 | BQ37: =Water!Z42 -> 0
A38: Total RFC | B38: =[3]Consp!C40 -> 784008.53 | C38: =Elect!J40 -> 0 | D38: =[3]Consp!$E$6 -> 0 | E38: =Elect!M40 -> 0 | F38: =[3]Consp!G40 -> 0 | G38: =Elect!O40 -> 0 | H38: =[3]Consp!I40 -> 0 | I38: =Water!C43 -> 0 | J38: =[4]Consp!$K$6 -> 0 | K38: =Water!E44 -> 0 | L38: 8 | M38: =Water!#REF! -> #REF! | N38: =Water!#REF! -> #REF! | O38: =[5]Consp!P39 -> 0 | P38: =Water!H43 -> 0 | Q38: =[5]Consp!R39 -> 0 | R38: =Water!O43 -> 0 | S38: =[5]Consp!T39 -> 0 | T38: =Water!#REF! -> #REF! | U38: =[5]Consp!V39 -> 0 | V38: =Water!#REF! -> #REF! | W38: =[5]Consp!X39 -> 0 | X38: =Water!Q43 -> 0 | Y38: 8 | Z38: =Water!#REF! -> #REF! | AA38: 0 | AB38: 0 | AC38: =[3]Consp!AD40 -> 0 | AD38: =Water!#REF! -> #REF! | AE38: =Water!#REF! -> #REF! | AF38: =Water!#REF! -> #REF! | AG38: =Gas!B43 -> 0 | AH38: =Gas!C43 -> 0 | AI38: =Gas!#REF! -> #REF! | AJ38: =Gas!J43 -> 0 | AK38: =Gas!#REF! -> #REF! | AL38: =Gas!#REF! -> #REF! | AM38: =Gas!#REF! -> #REF! | AN38: =Gas!#REF! -> #REF! | AO38: =Gas!#REF! -> #REF! | AP38: =Gas!#REF! -> #REF! | AQ38: =Gas!#REF! -> #REF! | AR38: =Gas!#REF! -> #REF! | AS38: =Gas!#REF! -> #REF! | AT38: =Elect!BK40 -> 0 | AU38: =Elect!BI40 -> 0 | AX38: =[3]Consp!BC40 -> 38.173558 | AY38: =[3]Consp!BD40 -> 19.219193 | AZ38: =[3]Consp!BE40 -> 208225.85 | BA38: =[3]Consp!BF40 -> 10.138565 | BB38: =[3]Consp!BG40 -> 5.1044505 | BC38: =Elect!BJ40 -> 0 | BD38: =Elect!#REF! -> #REF! | BE38: =Elect!#REF! -> #REF! | BF38: =Elect!#REF! -> #REF! | BG38: =Elect!#REF! -> #REF! | BH38: =[3]Consp!BM40 -> 0 | BI38: =[3]Consp!BN40 -> 0 | BJ38: =[3]Consp!BO40 -> 127385.62 | BK38: =[3]Consp!BP40 -> 6.2024355 | BL38: =[3]Consp!BQ40 -> 3.1227323 | BM38: =Water!U43 -> 0 | BN38: =Water!W43 -> 0 | BO38: =Water!X43 -> 0 | BP38: =Water!Y43 -> 0 | BQ38: =Water!Z43 -> 0
A39: RFC MTD | B39: =[3]Consp!C41 -> 784008.53 | C39: =Elect!J41 -> 0 | D39: =[3]Consp!$E$6 -> 0 | E39: =Elect!M41 -> 0 | F39: =[3]Consp!G41 -> 0 | G39: =Elect!O41 -> 0 | H39: =[3]Consp!I41 -> 0 | I39: =Water!C44 -> 0 | J39: =[4]Consp!$K$6 -> 0 | K39: =Water!E45 -> 0 | L39: 9 | M39: =Water!#REF! -> #REF! | N39: =Water!#REF! -> #REF! | O39: =[5]Consp!P40 -> 0 | P39: =Water!H44 -> 0 | Q39: =[5]Consp!R40 -> 0 | R39: =Water!O44 -> 0 | S39: =[5]Consp!T40 -> 0 | T39: =Water!#REF! -> #REF! | U39: =[5]Consp!V40 -> 0 | V39: =Water!#REF! -> #REF! | W39: =[5]Consp!X40 -> 0 | X39: =Water!Q44 -> 0 | Y39: 9 | Z39: =Water!#REF! -> #REF! | AA39: 0 | AB39: 0 | AC39: =[3]Consp!AD41 -> 0 | AD39: =Water!#REF! -> #REF! | AE39: =Water!#REF! -> #REF! | AF39: =Water!#REF! -> #REF! | AG39: =Gas!B44 -> 0 | AH39: =Gas!C44 -> 0 | AI39: =Gas!#REF! -> #REF! | AJ39: =Gas!J44 -> 0 | AK39: =Gas!#REF! -> #REF! | AL39: =Gas!#REF! -> #REF! | AM39: =Gas!#REF! -> #REF! | AN39: =Gas!#REF! -> #REF! | AO39: =Gas!#REF! -> #REF! | AP39: =Gas!#REF! -> #REF! | AQ39: =Gas!#REF! -> #REF! | AR39: =Gas!#REF! -> #REF! | AS39: =Gas!#REF! -> #REF! | AT39: =Elect!BK41 -> 0 | AU39: =Elect!BI41 -> 0 | AX39: =[3]Consp!BC41 -> 38.173558 | AY39: =[3]Consp!BD41 -> 19.219193 | AZ39: =[3]Consp!BE41 -> 208225.85 | BA39: =[3]Consp!BF41 -> 10.138565 | BB39: =[3]Consp!BG41 -> 5.1044505 | BC39: =Elect!BJ41 -> 0 | BD39: =Elect!#REF! -> #REF! | BE39: =Elect!#REF! -> #REF! | BF39: =Elect!#REF! -> #REF! | BG39: =Elect!#REF! -> #REF! | BH39: =[3]Consp!BM41 -> 0 | BI39: =[3]Consp!BN41 -> 0 | BJ39: =[3]Consp!BO41 -> 115057.98 | BK39: =[3]Consp!BP41 -> 6.2024355 | BL39: =[3]Consp!BQ41 -> 3.1227323 | BM39: =Water!U44 -> 0 | BN39: =Water!W44 -> 0 | BO39: =Water!X44 -> #VALUE! | BP39: =Water!Y44 -> #VALUE! | BQ39: =Water!Z44 -> #VALUE!
A40: AVER RFC | B40: =[3]Consp!C42 -> 28000.305 | C40: =Elect!J42 -> 0 | D40: =[3]Consp!$E$6 -> 0 | E40: =Elect!M42 -> 0 | F40: =[3]Consp!G42 -> 0 | G40: =Elect!O42 -> 0 | H40: =[3]Consp!I42 -> 0 | I40: =Water!C45 -> 0 | J40: =[4]Consp!$K$6 -> 0 | K40: =Water!E46 -> 0 | L40: 10 | M40: =Water!#REF! -> #REF! | N40: =Water!#REF! -> #REF! | O40: =[5]Consp!P41 -> 0 | P40: =Water!H45 -> 0 | Q40: =[5]Consp!R41 -> 0 | R40: =Water!O45 -> 0 | S40: =[5]Consp!T41 -> 0 | T40: =Water!#REF! -> #REF! | U40: =[5]Consp!V41 -> 0 | V40: =Water!#REF! -> #REF! | W40: =[5]Consp!X41 -> 0 | X40: =Water!Q45 -> 0 | Y40: 10 | Z40: =Water!#REF! -> #REF! | AA40: 0 | AB40: 0 | AC40: =[3]Consp!AD42 -> 0 | AD40: =Water!#REF! -> #REF! | AE40: =Water!#REF! -> #REF! | AF40: =Water!#REF! -> #REF! | AG40: =Gas!B45 -> 0 | AH40: =Gas!C45 -> 0 | AI40: =Gas!#REF! -> #REF! | AJ40: =Gas!J45 -> 0 | AK40: =Gas!#REF! -> #REF! | AL40: =Gas!#REF! -> #REF! | AM40: =Gas!#REF! -> #REF! | AN40: =Gas!#REF! -> #REF! | AO40: =Gas!#REF! -> #REF! | AP40: =Gas!#REF! -> #REF! | AQ40: =Gas!#REF! -> #REF! | AR40: =Gas!#REF! -> #REF! | AS40: =Gas!#REF! -> #REF! | AT40: =Elect!BK42 -> 0 | AU40: =Elect!BI42 -> 0 | AX40: =[3]Consp!BC42 -> 0 | AY40: =[3]Consp!BD42 -> 0 | AZ40: =[3]Consp!BE42 -> 7436.6375 | BA40: =[3]Consp!BF42 -> 0 | BB40: =[3]Consp!BG42 -> 0 | BC40: =Elect!BJ42 -> 0 | BD40: =Elect!#REF! -> #REF! | BE40: =Elect!#REF! -> #REF! | BF40: =Elect!#REF! -> #REF! | BG40: =Elect!#REF! -> #REF! | BH40: =[3]Consp!BM42 -> 1.1254646 | BI40: =[3]Consp!BN42 -> 0.57264868 | BJ40: =[3]Consp!BO42 -> 4109.2135 | BK40: =[3]Consp!BP42 -> 0 | BL40: =[3]Consp!BQ42 -> 0 | BM40: =Water!U45 -> 0 | BN40: =Water!W45 -> 0 | BO40: =Water!X45 -> #VALUE! | BP40: =Water!Y45 -> 0 | BQ40: =Water!Z45 -> 0

Sheet Temp.
A2: HILTON INTERNATIONAL
A3: GULF, MIDDLE EAST AND ASIA SPECIFIC
A4: HOTEL:HILTON HURGHADA LONG BEACH RESORT | G4: =Elect!A1 -> April
A7: DATE | B7: MAX TEMP | C7: MIN TEMP | D7: MAX TEMP | E7: MIN TEMP | F7: DAY | G7: DD. C | H7: DD. H | I7: MTD | J7: MTD
B8: C | C8: C | D8: F | E8: F | F8: PARAMETER | I8: COOLING | J8: HEATING
A10: 1 | D10: =SUM((B10*9/5)+32) -> 32 | E10: =SUM((C10*9/5)+32) -> 32 | F10: =SUM(((B10+C10)/2)-18.33) -> -18.33 | G10: =SUM(0+(F10)+ABS(F10))/2 -> 0 | H10: =IF((SUM(0-(F10)+ABS(F10))/2)<18,SUM(0-(F10)+ABS(F10))/2,0) -> 0 | I10: =SUM(G10:G10) -> 0 | J10: =SUM(H10:H10) -> 0
A11: 2 | D11: =SUM((B11*9/5)+32) -> 32 | E11: =SUM((C11*9/5)+32) -> 32 | F11: =SUM(((B11+C11)/2)-18.33) -> -18.33 | G11: =SUM(0+(F11)+ABS(F11))/2 -> 0 | H11: =IF((SUM(0-(F11)+ABS(F11))/2)<18,SUM(0-(F11)+ABS(F11))/2,0) -> 0 | I11: =SUM(G10:G11) -> 0 | J11: =SUM(H10:H11) -> 0
A12: 3 | D12: =SUM((B12*9/5)+32) -> 32 | E12: =SUM((C12*9/5)+32) -> 32 | F12: =SUM(((B12+C12)/2)-18.33) -> -18.33 | G12: =SUM(0+(F12)+ABS(F12))/2 -> 0 | H12: =IF((SUM(0-(F12)+ABS(F12))/2)<18,SUM(0-(F12)+ABS(F12))/2,0) -> 0 | I12: =SUM(G10:G12) -> 0 | J12: =SUM(H10:H12) -> 0
A13: 4 | D13: =SUM((B13*9/5)+32) -> 32 | E13: =SUM((C13*9/5)+32) -> 32 | F13: =SUM(((B13+C13)/2)-18.33) -> -18.33 | G13: =SUM(0+(F13)+ABS(F13))/2 -> 0 | H13: =IF((SUM(0-(F13)+ABS(F13))/2)<18,SUM(0-(F13)+ABS(F13))/2,0) -> 0 | I13: =SUM(G10:G13) -> 0 | J13: =SUM(H10:H13) -> 0
A14: 5 | D14: =SUM((B14*9/5)+32) -> 32 | E14: =SUM((C14*9/5)+32) -> 32 | F14: =SUM(((B14+C14)/2)-18.33) -> -18.33 | G14: =SUM(0+(F14)+ABS(F14))/2 -> 0 | H14: =IF((SUM(0-(F14)+ABS(F14))/2)<18,SUM(0-(F14)+ABS(F14))/2,0) -> 0 | I14: =SUM(G10:G14) -> 0 | J14: =SUM(H10:H14) -> 0
A15: 6 | D15: =SUM((B15*9/5)+32) -> 32 | E15: =SUM((C15*9/5)+32) -> 32 | F15: =SUM(((B15+C15)/2)-18.33) -> -18.33 | G15: =SUM(0+(F15)+ABS(F15))/2 -> 0 | H15: =IF((SUM(0-(F15)+ABS(F15))/2)<18,SUM(0-(F15)+ABS(F15))/2,0) -> 0 | I15: =SUM(G10:G15) -> 0 | J15: =SUM(H10:H15) -> 0
A16: 7 | D16: =SUM((B16*9/5)+32) -> 32 | E16: =SUM((C16*9/5)+32) -> 32 | F16: =SUM(((B16+C16)/2)-18.33) -> -18.33 | G16: =SUM(0+(F16)+ABS(F16))/2 -> 0 | H16: =IF((SUM(0-(F16)+ABS(F16))/2)<18,SUM(0-(F16)+ABS(F16))/2,0) -> 0 | I16: =SUM(G10:G16) -> 0 | J16: =SUM(H10:H16) -> 0
A17: 8 | D17: =SUM((B17*9/5)+32) -> 32 | E17: =SUM((C17*9/5)+32) -> 32 | F17: =SUM(((B17+C17)/2)-18.33) -> -18.33 | G17: =SUM(0+(F17)+ABS(F17))/2 -> 0 | H17: =IF((SUM(0-(F17)+ABS(F17))/2)<18,SUM(0-(F17)+ABS(F17))/2,0) -> 0 | I17: =SUM(G10:G17) -> 0 | J17: =SUM(H10:H17) -> 0
A18: 9 | D18: =SUM((B18*9/5)+32) -> 32 | E18: =SUM((C18*9/5)+32) -> 32 | F18: =SUM(((B18+C18)/2)-18.33) -> -18.33 | G18: =SUM(0+(F18)+ABS(F18))/2 -> 0 | H18: =IF((SUM(0-(F18)+ABS(F18))/2)<18,SUM(0-(F18)+ABS(F18))/2,0) -> 0 | I18: =SUM(G10:G18) -> 0 | J18: =SUM(H10:H18) -> 0
A19: 10 | D19: =SUM((B19*9/5)+32) -> 32 | E19: =SUM((C19*9/5)+32) -> 32 | F19: =SUM(((B19+C19)/2)-18.33) -> -18.33 | G19: =SUM(0+(F19)+ABS(F19))/2 -> 0 | H19: =IF((SUM(0-(F19)+ABS(F19))/2)<18,SUM(0-(F19)+ABS(F19))/2,0) -> 0 | I19: =SUM(G10:G19) -> 0 | J19: =SUM(H10:H19) -> 0
A20: 11 | D20: =SUM((B20*9/5)+32) -> 32 | E20: =SUM((C20*9/5)+32) -> 32 | F20: =SUM(((B20+C20)/2)-18.33) -> -18.33 | G20: =SUM(0+(F20)+ABS(F20))/2 -> 0 | H20: =IF((SUM(0-(F20)+ABS(F20))/2)<18,SUM(0-(F20)+ABS(F20))/2,0) -> 0 | I20: =SUM(G10:G20) -> 0 | J20: =SUM(H10:H20) -> 0
A21: 12 | D21: =SUM((B21*9/5)+32) -> 32 | E21: =SUM((C21*9/5)+32) -> 32 | F21: =SUM(((B21+C21)/2)-18.33) -> -18.33 | G21: =SUM(0+(F21)+ABS(F21))/2 -> 0 | H21: =IF((SUM(0-(F21)+ABS(F21))/2)<18,SUM(0-(F21)+ABS(F21))/2,0) -> 0 | I21: =SUM(G10:G21) -> 0 | J21: =SUM(H10:H21) -> 0
A22: 13 | D22: =SUM((B22*9/5)+32) -> 32 | E22: =SUM((C22*9/5)+32) -> 32 | F22: =SUM(((B22+C22)/2)-18.33) -> -18.33 | G22: =SUM(0+(F22)+ABS(F22))/2 -> 0 | H22: =IF((SUM(0-(F22)+ABS(F22))/2)<18,SUM(0-(F22)+ABS(F22))/2,0) -> 0 | I22: =SUM(G10:G22) -> 0 | J22: =SUM(H10:H22) -> 0
A23: 14 | D23: =SUM((B23*9/5)+32) -> 32 | E23: =SUM((C23*9/5)+32) -> 32 | F23: =SUM(((B23+C23)/2)-18.33) -> -18.33 | G23: =SUM(0+(F23)+ABS(F23))/2 -> 0 | H23: =IF((SUM(0-(F23)+ABS(F23))/2)<18,SUM(0-(F23)+ABS(F23))/2,0) -> 0 | I23: =SUM(G10:G23) -> 0 | J23: =SUM(H10:H23) -> 0
A24: 15 | D24: =SUM((B24*9/5)+32) -> 32 | E24: =SUM((C24*9/5)+32) -> 32 | F24: =SUM(((B24+C24)/2)-18.33) -> -18.33 | G24: =SUM(0+(F24)+ABS(F24))/2 -> 0 | H24: =IF((SUM(0-(F24)+ABS(F24))/2)<18,SUM(0-(F24)+ABS(F24))/2,0) -> 0 | I24: =SUM(G11:G24) -> 0 | J24: =SUM(H11:H24) -> 0
A25: 16 | D25: =SUM((B25*9/5)+32) -> 32 | E25: =SUM((C25*9/5)+32) -> 32 | F25: =SUM(((B25+C25)/2)-18.33) -> -18.33 | G25: =SUM(0+(F25)+ABS(F25))/2 -> 0 | H25: =IF((SUM(0-(F25)+ABS(F25))/2)<18,SUM(0-(F25)+ABS(F25))/2,0) -> 0 | I25: =SUM(G12:G25) -> 0 | J25: =SUM(H12:H25) -> 0
A26: 17 | D26: =SUM((B26*9/5)+32) -> 32 | E26: =SUM((C26*9/5)+32) -> 32 | F26: =SUM(((B26+C26)/2)-18.33) -> -18.33 | G26: =SUM(0+(F26)+ABS(F26))/2 -> 0 | H26: =IF((SUM(0-(F26)+ABS(F26))/2)<18,SUM(0-(F26)+ABS(F26))/2,0) -> 0 | I26: =SUM(G13:G26) -> 0 | J26: =SUM(H13:H26) -> 0
A27: 18 | D27: =SUM((B27*9/5)+32) -> 32 | E27: =SUM((C27*9/5)+32) -> 32 | F27: =SUM(((B27+C27)/2)-18.33) -> -18.33 | G27: =SUM(0+(F27)+ABS(F27))/2 -> 0 | H27: =IF((SUM(0-(F27)+ABS(F27))/2)<18,SUM(0-(F27)+ABS(F27))/2,0) -> 0 | I27: =SUM(G14:G27) -> 0 | J27: =SUM(H14:H27) -> 0
A28: 19 | D28: =SUM((B28*9/5)+32) -> 32 | E28: =SUM((C28*9/5)+32) -> 32 | F28: =SUM(((B28+C28)/2)-18.33) -> -18.33 | G28: =SUM(0+(F28)+ABS(F28))/2 -> 0 | H28: =IF((SUM(0-(F28)+ABS(F28))/2)<18,SUM(0-(F28)+ABS(F28))/2,0) -> 0 | I28: =SUM(G15:G28) -> 0 | J28: =SUM(H15:H28) -> 0
A29: 20 | D29: =SUM((B29*9/5)+32) -> 32 | E29: =SUM((C29*9/5)+32) -> 32 | F29: =SUM(((B29+C29)/2)-18.33) -> -18.33 | G29: =SUM(0+(F29)+ABS(F29))/2 -> 0 | H29: =IF((SUM(0-(F29)+ABS(F29))/2)<18,SUM(0-(F29)+ABS(F29))/2,0) -> 0 | I29: =SUM(G16:G29) -> 0 | J29: =SUM(H16:H29) -> 0
A30: 21 | D30: =SUM((B30*9/5)+32) -> 32 | E30: =SUM((C30*9/5)+32) -> 32 | F30: =SUM(((B30+C30)/2)-18.33) -> -18.33 | G30: =SUM(0+(F30)+ABS(F30))/2 -> 0 | H30: =IF((SUM(0-(F30)+ABS(F30))/2)<18,SUM(0-(F30)+ABS(F30))/2,0) -> 0 | I30: =SUM(G17:G30) -> 0 | J30: =SUM(H17:H30) -> 0
A31: 22 | D31: =SUM((B31*9/5)+32) -> 32 | E31: =SUM((C31*9/5)+32) -> 32 | F31: =SUM(((B31+C31)/2)-18.33) -> -18.33 | G31: =SUM(0+(F31)+ABS(F31))/2 -> 0 | H31: =IF((SUM(0-(F31)+ABS(F31))/2)<18,SUM(0-(F31)+ABS(F31))/2,0) -> 0 | I31: =SUM(G18:G31) -> 0 | J31: =SUM(H18:H31) -> 0
A32: 23 | D32: =SUM((B32*9/5)+32) -> 32 | E32: =SUM((C32*9/5)+32) -> 32 | F32: =SUM(((B32+C32)/2)-18.33) -> -18.33 | G32: =SUM(0+(F32)+ABS(F32))/2 -> 0 | H32: =IF((SUM(0-(F32)+ABS(F32))/2)<18,SUM(0-(F32)+ABS(F32))/2,0) -> 0 | I32: =SUM(G19:G32) -> 0 | J32: =SUM(H19:H32) -> 0
A33: 24 | D33: =SUM((B33*9/5)+32) -> 32 | E33: =SUM((C33*9/5)+32) -> 32 | F33: =SUM(((B33+C33)/2)-18.33) -> -18.33 | G33: =SUM(0+(F33)+ABS(F33))/2 -> 0 | H33: =IF((SUM(0-(F33)+ABS(F33))/2)<18,SUM(0-(F33)+ABS(F33))/2,0) -> 0 | I33: =SUM(G20:G33) -> 0 | J33: =SUM(H20:H33) -> 0
A34: 25 | D34: =SUM((B34*9/5)+32) -> 32 | E34: =SUM((C34*9/5)+32) -> 32 | F34: =SUM(((B34+C34)/2)-18.33) -> -18.33 | G34: =SUM(0+(F34)+ABS(F34))/2 -> 0 | H34: =IF((SUM(0-(F34)+ABS(F34))/2)<18,SUM(0-(F34)+ABS(F34))/2,0) -> 0 | I34: =SUM(G21:G34) -> 0 | J34: =SUM(H21:H34) -> 0
... A40: 31 | D40: =SUM((B40*9/5)+32) -> 32 | E40: =SUM((C40*9/5)+32) -> 32 | F40: =SUM(((B40+C40)/2)-18.33) -> -18.33 | G40: =SUM(0+(F40)+ABS(F40))/2 -> 0 | H40: =IF((SUM(0-(F40)+ABS(F40))/2)<18,SUM(0-(F40)+ABS(F40))/2,0) -> 0 | I40: =SUM(G27:G40) -> 0 | J40: =SUM(H27:H40) -> 0
E42: =SUM(G10:G40) -> 0 | F42: deg c
E44: =SUM(H10:H40) -> 0 | F44: deg c

Sheet M-Rep
B3: =Elect!A1 -> April
D4: Y.T.D
A5: Energy breakdown | C5: 2009 | D5: 2005 | E5: 2006
A6: Elect.
A7: Chillers KWH | C7: N/A | D7: =[7]Sheet1!AS7 -> N/A | E7: N/A
A8: Laundry KWH | C8: N/A | D8: =[7]Sheet1!AS8 -> N/A | E8: N/A
A9: Kitchen KWH | C9: N/A | D9: =[7]Sheet1!AS9 -> N/A | E9: N/A
A10: Gas
A11: Kit M3 | C11: =Gas!#REF!/1000 -> #REF!
A12: Laundry M3 | C12: N/A | D12: =B11+[8]Utilities!AU12 -> 0 | E12: =C11+[8]Utilities!AO12 -> #REF!
A13: Water | D13: N/A | E13: N/A
A14: Laundry HW | C14: N/A
A15: Laundry CW | C15: N/A
A16: Kit HW | C16: N/A
A17: kIt CW | C17: N/A | D17: N/A | E17: N/A
A18: Dmstc HW | C18: N/A | D18: N/A | E18: N/A
A19: Dmstc CW | C19: N/A | D19: N/A | E19: N/A
A20: S.Pool MKUP | C20: =#REF! -> #REF! | D20: N/A | E20: N/A
A21: Ctower MKUP | C21: N/A | D21: N/A | E21: N/A
A22: Gardens Irrigat. | C22: =Water!S38 -> 0 | D22: N/A | E22: N/A
A23: Swage water treatment | C23: =Water!#REF! -> #REF! | D23: =B20+[8]Utilities!AN23 -> 27437 | E23: =C20+[8]Utilities!AO23 -> #REF!
A24: Utilities consumption | D24: N/A | E24: N/A
A25: Elect. Kwh | C25: =Elect!J34 -> 2214 | D25: =B22+[8]Utilities!AN25 -> 12266 | E25: =C22+[8]Utilities!AO25 -> 814
A26: M.D (9.5 LE) | D26: =B23+[8]Utilities!AN26 -> 147773 | E26: =C23+[8]Utilities!AO26 -> #REF!
A27: Water M3 | C27: =Water!H38 -> 2639.58
A28: Fuel Ltr | C28: =Gas!#REF!*1000 -> #REF! | D28: =B25+[8]Utilities!AN28 -> 12876868 | E28: =C25+[8]Utilities!AO28 -> 14503014
A29: Gas M3/ Boilers, chillers,..etc | C29: N/A | D29: =B26+[8]Utilities!AN29 -> 28880 | E29: =C26+[8]Utilities!AO29 -> 32980
A30: Gas M3 Kitchen | C30: =Gas!#REF!/1000 -> #REF! | D30: =B27+[8]Utilities!AN30 -> 244283 | E30: =C27+[8]Utilities!AO30 -> 254313.58
A31: Total Energy | D31: =B28+[8]Utilities!AN31 -> 620770 | E31: =C28+[8]Utilities!AO31 -> #REF!
A32: Control Parameters | D32: =[9]Submetering!AO32 -> #REF! | E32: N/A
A33: No. of Rooms % occ. | C33: =YTD!Q4 -> 0 | D33: =B30+[8]Utilities!AN33 -> 39.395 | E33: =C30+[8]Utilities!AO33 -> #REF!
A34: No. of Occ. Rooms | C34: =YTD!Q5 -> 0
A35: guest count | C35: =YTD!Q6 -> 0
A36: Food covers | D36: =#REF!+[8]Utilities!AN36 -> #REF! | E36: =#REF!+[8]Utilities!AO36 -> #REF!
A37: Laundry W. Kg | D37: =AVERAGE(B33,[8]Utilities!AN37) -> 0.8807 | E37: =AVERAGE(C33,[8]Utilities!AO37) -> 0.46351998
A38: DDC | C38: =Temp.!E42 -> 0 | D38: =B34+[8]Utilities!AN38 -> 196150 | E38: =C34+[8]Utilities!AO38 -> 237021
A39: DDH | C39: =Temp.!E44 -> 0 | D39: =B35+[8]Utilities!AN39 -> 400070 | E39: =C35+[8]Utilities!AO39 -> 466105
A40: Utilities Entergy cost | D40: =B36+[8]Utilities!AN40 -> 1583714 | E40: =C36+[8]Utilities!AO40 -> 1940567
A41: Elect. | C41: =Elect!#REF! -> #REF! | D41: =B37+[8]Utilities!AN41 -> 1690339 | E41: =C37+[8]Utilities!AO41 -> 3118671.6
A42: M.D | C42: =C26*Elect!#REF! -> #REF! | D42: =B38+[8]Utilities!AN42 -> 2381.51 | E42: =C38+[8]Utilities!AO42 -> 2480.24
A43: Water | C43: =Water!X38 -> 10558.32 | D43: =B39+[8]Utilities!AN43 -> 112 | E43: =C39+[8]Utilities!AO43 -> 97.53
A44: Fuel | C44: =Gas!#REF! -> #REF!
A45: Gas Boilers, chillers,etc.. | C45: N/A | D45: =B41+[8]Utilities!AN45 -> 2138156.8 | E45: =C41+[8]Utilities!AO45 -> #REF!
A46: Gas Kitchen | C46: =C30*Gas!M2*1000 -> #REF! | D46: =B42+[8]Utilities!AN46 -> 223044.2 | E46: =C42+[8]Utilities!AO46 -> #REF!
A47: TOTAL LE | C47: =SUM(C41:C46) -> #REF! | D47: =B43+[8]Utilities!AN47 -> 1330535.7 | E47: =C43+[8]Utilities!AO47 -> 1389169.1
A48: No. of POMEC Staff | D48: =B44+[8]Utilities!AN48 -> 330278 | E48: =C44+[8]Utilities!AO48 -> #REF!
A49: Hotel Age | C49: 6 | D49: N/A | E49: N/A
A50: No. of rooms | C50: =31*912 -> 28272 | D50: =B46+[8]Utilities!AN50 -> 36597.525 | E50: =C46+[8]Utilities!AO50 -> #REF!
A51: Building Volume | C51: 243175 | D51: =SUM(D45:D50) -> 4058612.3 | E51: =SUM(E45:E50) -> #REF!
A52: Building area | C52: 75064
A53: US$ Rate | C53: 5.59402 | D53: =AVERAGE(B48,[8]Utilities!AN53) -> 61 | E53: =AVERAGE(C48,[8]Utilities!AO53) -> 72
A54: Total R&M MTD | C54: =YTD!Q65 -> 0 | D54: =[9]Submetering!AO54 -> #REF! | E54: 243175 | F54: =YTD!Q64 -> 0
A55: Staff - HLP | D55: =[9]Submetering!AO55 -> #REF! | E55: 75064
A56: Staff - R&M | D56: =AVERAGE(B53,[8]Utilities!AN56) -> 5.755 | E56: =AVERAGE(C53,[8]Utilities!AO56) -> 5.65951
A57: Staff - Grounds

Sheet YTD
A1: =Elect!A1 -> April | H1: Actual 2014
C3: JAN | D3: FEB | E3: MAR | F3: APR | G3: MAY | H3: JUN | I3: JUL | J3: AUG | K3: SEP | L3: OCT | M3: NOV | N3: DEC | O3: TOTAL | P3: YTD | Q3: Month Act
A4: Occ Room % | O4: =SUM(C4:N4) -> 0 | P4: =(IF($A$1=39814,C4,(IF($A$1=39845,SUM(C4:D4),(IF($A$1=39873,SUM(C4:E4),(IF($A$1=39904,SUM(C4:F4),(IF($A$1=39934,SUM(C4:G4),(IF($A$1=39965,SUM(C4:H4),(IF($A$1=39995,SUM(C4:I4),0)))))))))))))+(IF($A$1=40026,SUM(C4:J4),(IF($A$1=40057,SUM(C4:K4),(IF($A$1=40087,SUM(C4:L4),(IF($A$1=40118,SUM(C4:M4))))))))))+(IF($A$1=40148,SUM(C4:N4),0)) -> 0 | Q4: =(IF($A$1=39814,C4,(IF($A$1=39845,D4,(IF($A$1=39873,E4,(IF($A$1=39904,F4,(IF($A$1=39934,G4,(IF($A$1=39965,H4,(IF($A$1=39995,I4,0)))))))))))))+(IF($A$1=40026,J4,(IF($A$1=40057,K4,(IF($A$1=40087,L4,(IF($A$1=40118,M4)))))))))+(IF($A$1=40148,N4,0)) -> 0 | S4: 40179 | DE4: 1
A5: Occ Room | C5: 25072 | D5: =Elect!BI34 -> 85 | O5: =SUM(C5:N5) -> 25157 | P5: =(IF($A$1=40179,C5,(IF($A$1=40210,SUM(C5:D5),(IF($A$1=40238,SUM(C5:E5),(IF($A$1=40269,SUM(C5:F5),(IF($A$1=40299,SUM(C5:G5),(IF($A$1=40330,SUM(C5:H5),(IF($A$1=40360,SUM(C5:I5),0)))))))))))))+(IF($A$1=40391,SUM(C5:J5),(IF($A$1=40422,SUM(C5:K5),(IF($A$1=40452,SUM(C5:L5),(IF($A$1=40483,SUM(C5:M5))))))))))+(IF($A$1=40513,SUM(C5:N5),0)) -> 0 | Q5: =(IF($A$1=40179,C5,(IF($A$1=40210,D5,(IF($A$1=40238,E5,(IF($A$1=40269,F5,(IF($A$1=40299,G5,(IF($A$1=40330,H5,(IF($A$1=40360,I5,0)))))))))))))+(IF($A$1=40391,J5,(IF($A$1=40422,K5,(IF($A$1=40452,L5,(IF($A$1=40483,M5)))))))))+(IF($A$1=40513,N5,0)) -> 0 | S5: 40210 | DE5: 2
A6: Number of Guest | C6: =[10]Elect!$S$37 -> 50662 | D6: =Elect!BK34 -> 216 | O6: =SUM(C6:N6) -> 50878 | P6: =(IF($A$1=40179,C6,(IF($A$1=40210,SUM(C6:D6),(IF($A$1=40238,SUM(C6:E6),(IF($A$1=40269,SUM(C6:F6),(IF($A$1=40299,SUM(C6:G6),(IF($A$1=40330,SUM(C6:H6),(IF($A$1=40360,SUM(C6:I6),0)))))))))))))+(IF($A$1=40391,SUM(C6:J6),(IF($A$1=40422,SUM(C6:K6),(IF($A$1=40452,SUM(C6:L6),(IF($A$1=40483,SUM(C6:M6))))))))))+(IF($A$1=40513,SUM(C6:N6),0)) -> 0 | Q6: =(IF($A$1=40179,C6,(IF($A$1=40210,D6,(IF($A$1=40238,E6,(IF($A$1=40269,F6,(IF($A$1=40299,G6,(IF($A$1=40330,H6,(IF($A$1=40360,I6,0)))))))))))))+(IF($A$1=40391,J6,(IF($A$1=40422,K6,(IF($A$1=40452,L6,(IF($A$1=40483,M6)))))))))+(IF($A$1=40513,N6,0)) -> 0 | S6: 40238 | DE6: 3
A7: PAY & REL. EXP. | O7: =SUM(C7:N7) -> 0 | P7: =(IF($A$1=40179,C7,(IF($A$1=40210,SUM(C7:D7),(IF($A$1=40238,SUM(C7:E7),(IF($A$1=40269,SUM(C7:F7),(IF($A$1=40299,SUM(C7:G7),(IF($A$1=40330,SUM(C7:H7),(IF($A$1=40360,SUM(C7:I7),0)))))))))))))+(IF($A$1=40391,SUM(C7:J7),(IF($A$1=40422,SUM(C7:K7),(IF($A$1=40452,SUM(C7:L7),(IF($A$1=40483,SUM(C7:M7))))))))))+(IF($A$1=40513,SUM(C7:N7),0)) -> 0 | Q7: =(IF($A$1=40179,C7,(IF($A$1=40210,D7,(IF($A$1=40238,E7,(IF($A$1=40269,F7,(IF($A$1=40299,G7,(IF($A$1=40330,H7,(IF($A$1=40360,I7,0)))))))))))))+(IF($A$1=40391,J7,(IF($A$1=40422,K7,(IF($A$1=40452,L7,(IF($A$1=40483,M7)))))))))+(IF($A$1=40513,N7,0)) -> 0
A8: SALARIES | B8: 53241001 | O8: =SUM(C8:N8) -> 0 | P8: =(IF($A$1=40179,C8,(IF($A$1=40210,SUM(C8:D8),(IF($A$1=40238,SUM(C8:E8),(IF($A$1=40269,SUM(C8:F8),(IF($A$1=40299,SUM(C8:G8),(IF($A$1=40330,SUM(C8:H8),(IF($A$1=40360,SUM(C8:I8),0)))))))))))))+(IF($A$1=40391,SUM(C8:J8),(IF($A$1=40422,SUM(C8:K8),(IF($A$1=40452,SUM(C8:L8),(IF($A$1=40483,SUM(C8:M8))))))))))+(IF($A$1=40513,SUM(C8:N8),0)) -> 0 | Q8: =(IF($A$1=40179,C8,(IF($A$1=40210,D8,(IF($A$1=40238,E8,(IF($A$1=40269,F8,(IF($A$1=40299,G8,(IF($A$1=40330,H8,(IF($A$1=40360,I8,0)))))))))))))+(IF($A$1=40391,J8,(IF($A$1=40422,K8,(IF($A$1=40452,L8,(IF($A$1=40483,M8)))))))))+(IF($A$1=40513,N8,0)) -> 0
A9: EXTRA WAGES | B9: 53242099 | O9: =SUM(C9:N9) -> 0 | P9: =(IF($A$1=40179,C9,(IF($A$1=40210,SUM(C9:D9),(IF($A$1=40238,SUM(C9:E9),(IF($A$1=40269,SUM(C9:F9),(IF($A$1=40299,SUM(C9:G9),(IF($A$1=40330,SUM(C9:H9),(IF($A$1=40360,SUM(C9:I9),0)))))))))))))+(IF($A$1=40391,SUM(C9:J9),(IF($A$1=40422,SUM(C9:K9),(IF($A$1=40452,SUM(C9:L9),(IF($A$1=40483,SUM(C9:M9))))))))))+(IF($A$1=40513,SUM(C9:N9),0)) -> 0 | Q9: =(IF($A$1=40179,C9,(IF($A$1=40210,D9,(IF($A$1=40238,E9,(IF($A$1=40269,F9,(IF($A$1=40299,G9,(IF($A$1=40330,H9,(IF($A$1=40360,I9,0)))))))))))))+(IF($A$1=40391,J9,(IF($A$1=40422,K9,(IF($A$1=40452,L9,(IF($A$1=40483,M9)))))))))+(IF($A$1=40513,N9,0)) -> 0
A10: SERVICE | B10: 53243001 | O10: =SUM(C10:N10) -> 0 | P10: =(IF($A$1=40179,C10,(IF($A$1=40210,SUM(C10:D10),(IF($A$1=40238,SUM(C10:E10),(IF($A$1=40269,SUM(C10:F10),(IF($A$1=40299,SUM(C10:G10),(IF($A$1=40330,SUM(C10:H10),(IF($A$1=40360,SUM(C10:I10),0)))))))))))))+(IF($A$1=40391,SUM(C10:J10),(IF($A$1=40422,SUM(C10:K10),(IF($A$1=40452,SUM(C10:L10),(IF($A$1=40483,SUM(C10:M10))))))))))+(IF($A$1=40513,SUM(C10:N10),0)) -> 0 | Q10: =(IF($A$1=40179,C10,(IF($A$1=40210,D10,(IF($A$1=40238,E10,(IF($A$1=40269,F10,(IF($A$1=40299,G10,(IF($A$1=40330,H10,(IF($A$1=40360,I10,0)))))))))))))+(IF($A$1=40391,J10,(IF($A$1=40422,K10,(IF($A$1=40452,L10,(IF($A$1=40483,M10)))))))))+(IF($A$1=40513,N10,0)) -> 0
A11: RELATED EXP. | B11: 53244001 | O11: =SUM(C11:N11) -> 0 | P11: =(IF($A$1=40179,C11,(IF($A$1=40210,SUM(C11:D11),(IF($A$1=40238,SUM(C11:E11),(IF($A$1=40269,SUM(C11:F11),(IF($A$1=40299,SUM(C11:G11),(IF($A$1=40330,SUM(C11:H11),(IF($A$1=40360,SUM(C11:I11),0)))))))))))))+(IF($A$1=40391,SUM(C11:J11),(IF($A$1=40422,SUM(C11:K11),(IF($A$1=40452,SUM(C11:L11),(IF($A$1=40483,SUM(C11:M11))))))))))+(IF($A$1=40513,SUM(C11:N11),0)) -> 0 | Q11: =(IF($A$1=40179,C11,(IF($A$1=40210,D11,(IF($A$1=40238,E11,(IF($A$1=40269,F11,(IF($A$1=40299,G11,(IF($A$1=40330,H11,(IF($A$1=40360,I11,0)))))))))))))+(IF($A$1=40391,J11,(IF($A$1=40422,K11,(IF($A$1=40452,L11,(IF($A$1=40483,M11)))))))))+(IF($A$1=40513,N11,0)) -> 0
A12: EMPL. MEALS | B12: 53245001 | O12: =SUM(C12:N12) -> 0 | P12: =(IF($A$1=40179,C12,(IF($A$1=40210,SUM(C12:D12),(IF($A$1=40238,SUM(C12:E12),(IF($A$1=40269,SUM(C12:F12),(IF($A$1=40299,SUM(C12:G12),(IF($A$1=40330,SUM(C12:H12),(IF($A$1=40360,SUM(C12:I12),0)))))))))))))+(IF($A$1=40391,SUM(C12:J12),(IF($A$1=40422,SUM(C12:K12),(IF($A$1=40452,SUM(C12:L12),(IF($A$1=40483,SUM(C12:M12))))))))))+(IF($A$1=40513,SUM(C12:N12),0)) -> 0 | Q12: =(IF($A$1=40179,C12,(IF($A$1=40210,D12,(IF($A$1=40238,E12,(IF($A$1=40269,F12,(IF($A$1=40299,G12,(IF($A$1=40330,H12,(IF($A$1=40360,I12,0)))))))))))))+(IF($A$1=40391,J12,(IF($A$1=40422,K12,(IF($A$1=40452,L12,(IF($A$1=40483,M12)))))))))+(IF($A$1=40513,N12,0)) -> 0
