Workbook

Sheet Total
A1: Site Name | B1: Day | C1: Month | D1: Year | E1: Total Electricity Kwh | F1: Electricity Tariff ($/Kwh) | G1: Total Fuel Oil (Liters) | H1: Fuel Oil $/Liter | I1: LPG (Kg) | J1: LPG $/Kg | K1: Water Utility Supply (m3) m3 | L1: Water Utility Supply (m3) $/m3 | M1: Irrigation Water (m3) m3 | N1: Irrigation water $/m3 | O1: Room Nights
A2: Beirut | B2: 1 | C2: 6 | D2: 2020 | E2: =ELEC!N3 -> 14293 | F2: =SUM('EDl log'!T4) -> 0.066086751 | G2: =-tanks!AW6 -> 452 | H2: =SUM(tanks!AV6) -> 0.1 | I2: =('B5'!AU5)*0.51 -> 91.8 | J2: ='B5'!AX5/0.51 -> 1.372549 | K2: =WATER!I6 -> 11 | L2: =SUM(WATER!J6) -> 22.727273 | M2: =WATER!Q6 -> 0 | N2: 0.6 | O2: =ELEC!B3 -> 4.991
A3: Beirut | B3: =B2+1 -> 2 | C3: 6 | D3: 2020 | E3: =ELEC!N4 -> 13728 | F3: =SUM('EDl log'!T5) -> 0.059017146 | G3: =-tanks!AW7 -> 296 | H3: =SUM(tanks!AV7) -> 0.1 | I3: =('B5'!AU6)*0.51 -> 45.9 | J3: ='B5'!AX6/0.51 -> 1.372549 | K3: =WATER!I7 -> 0 | L3: =SUM(WATER!J7) -> 0 | M3: =WATER!Q7 -> 0 | N3: 0.6 | O3: =ELEC!B4 -> 2.001
A4: Beirut | B4: =B3+1 -> 3 | C4: 6 | D4: 2020 | E4: =ELEC!N5 -> 14416 | F4: =SUM('EDl log'!T6) -> 0.077029595 | G4: =-tanks!AW8 -> 370.6 | H4: =SUM(tanks!AV8) -> 0.1 | I4: =('B5'!AU7)*0.51 -> 61.2 | J4: ='B5'!AX7/0.51 -> 1.372549 | K4: =WATER!I8 -> 0 | L4: =SUM(WATER!J8) -> 0 | M4: =WATER!Q8 -> 0 | N4: 0.6 | O4: =ELEC!B5 -> 6.003
A5: Beirut | B5: =B4+1 -> 4 | C5: 6 | D5: 2020 | E5: =ELEC!N6 -> 12453 | F5: =SUM('EDl log'!T7) -> 0.020989932 | G5: =-tanks!AW9 -> 628 | H5: =SUM(tanks!AV9) -> 0.34 | I5: =('B5'!AU8)*0.51 -> 178.5 | J5: ='B5'!AX8/0.51 -> 1.372549 | K5: =WATER!I9 -> 172 | L5: =SUM(WATER!J9) -> 1.4534884 | M5: =WATER!Q9 -> 0 | N5: 0.6 | O5: =ELEC!B6 -> 4.991
A6: Beirut | B6: =B5+1 -> 5 | C6: 6 | D6: 2020 | E6: =ELEC!N7 -> 13633 | F6: =SUM('EDl log'!T8) -> 0.070245062 | G6: =-tanks!AW10 -> 334 | H6: =SUM(tanks!AV10) -> 0.34 | I6: =('B5'!AU9)*0.51 -> 45.9 | J6: ='B5'!AX9/0.51 -> 1.372549 | K6: =WATER!I10 -> 0 | L6: =SUM(WATER!J10) -> 0 | M6: =WATER!Q10 -> 0 | N6: 0.6 | O6: =ELEC!B7 -> 2.99
A7: Beirut | B7: =B6+1 -> 6 | C7: 6 | D7: 2020 | E7: =ELEC!N8 -> 13778 | F7: =SUM('EDl log'!T9) -> 0.062633868 | G7: =-tanks!AW11 -> 391 | H7: =SUM(tanks!AV11) -> 0.34 | I7: =('B5'!AU10)*0.51 -> 30.6 | J7: ='B5'!AX10/0.51 -> 1.372549 | K7: =WATER!I11 -> 0 | L7: =SUM(WATER!J11) -> 0 | M7: =WATER!Q11 -> 0 | N7: 0.6 | O7: =ELEC!B8 -> 4.991
A8: Beirut | B8: =B7+1 -> 7 | C8: 6 | D8: 2020 | E8: =ELEC!N9 -> 16205 | F8: =SUM('EDl log'!T10) -> 0.068091428 | G8: =-tanks!AW12 -> 363 | H8: =SUM(tanks!AV12) -> 0.34 | I8: =('B5'!AU11)*0.51 -> 30.6 | J8: ='B5'!AX11/0.51 -> 1.372549 | K8: =WATER!I12 -> 0 | L8: =SUM(WATER!J12) -> 0 | M8: =WATER!Q12 -> 0 | N8: 0.6 | O8: =ELEC!B9 -> 4.002
A9: Beirut | B9: =B8+1 -> 8 | C9: 6 | D9: 2020 | E9: =ELEC!N10 -> 15745 | F9: =SUM('EDl log'!T11) -> 0.062002075 | G9: =-tanks!AW13 -> 360 | H9: =SUM(tanks!AV13) -> 0.34 | I9: =('B5'!AU12)*0.51 -> 45.9 | J9: ='B5'!AX12/0.51 -> 1.372549 | K9: =WATER!I13 -> 72 | L9: =SUM(WATER!J13) -> 3.4722222 | M9: =WATER!Q13 -> 0 | N9: 0.6 | O9: =ELEC!B10 -> 2.99
A10: Beirut | B10: =B9+1 -> 9 | C10: 6 | D10: 2020 | E10: =ELEC!N11 -> 15283 | F10: =SUM('EDl log'!T12) -> 0.066403002 | G10: =-tanks!AW14 -> 282 | H10: =SUM(tanks!AV14) -> 0.34 | I10: =('B5'!AU13)*0.51 -> 76.5 | J10: ='B5'!AX13/0.51 -> 1.372549 | K10: =WATER!I14 -> 0 | L10: =SUM(WATER!J14) -> 0 | M10: =WATER!Q14 -> 0 | N10: 0.6 | O10: =ELEC!B11 -> 4.002
A11: Beirut | B11: =B10+1 -> 10 | C11: 6 | D11: 2020 | E11: =ELEC!N12 -> 16634 | F11: =SUM('EDl log'!T13) -> 0.070013883 | G11: =-tanks!AW15 -> 600.4 | H11: =SUM(tanks!AV15) -> 0.34 | I11: =('B5'!AU14)*0.51 -> 76.5 | J11: ='B5'!AX14/0.51 -> 1.372549 | K11: =WATER!I15 -> 400 | L11: =SUM(WATER!J15) -> 0.625 | M11: =WATER!Q15 -> 0 | N11: 0.6 | O11: =ELEC!B12 -> 4.002
A12: Beirut | B12: =B11+1 -> 11 | C12: 6 | D12: 2020 | E12: =ELEC!N13 -> 14437 | F12: =SUM('EDl log'!T14) -> 0.091721918 | G12: =-tanks!AW16 -> 368.1 | H12: =SUM(tanks!AV16) -> 0.34 | I12: =('B5'!AU15)*0.51 -> 91.8 | J12: ='B5'!AX15/0.51 -> 1.372549 | K12: =WATER!I16 -> 0 | L12: =SUM(WATER!J16) -> 0 | M12: =WATER!Q16 -> 0 | N12: 0.6 | O12: =ELEC!B13 -> 2.99
A13: Beirut | B13: =B12+1 -> 12 | C13: 6 | D13: 2020 | E13: =ELEC!N14 -> 15870 | F13: =SUM('EDl log'!T16) -> 0.071192434 | G13: =-tanks!AW17 -> 366 | H13: =SUM(tanks!AV17) -> 0.34 | I13: =('B5'!AU16)*0.51 -> 45.9 | J13: ='B5'!AX16/0.51 -> 1.372549 | K13: =WATER!I17 -> 120 | L13: =SUM(WATER!J17) -> 2.0833333 | M13: =WATER!Q17 -> 0 | N13: 0.6 | O13: =ELEC!B14 -> 6.9
A14: Beirut | B14: =B13+1 -> 13 | C14: 6 | D14: 2020 | E14: =ELEC!N15 -> 15047 | F14: =SUM('EDl log'!T17) -> 0.071692466 | G14: =-tanks!AW18 -> 319 | H14: =SUM(tanks!AV18) -> 0.34 | I14: =('B5'!AU17)*0.51 -> 61.2 | J14: ='B5'!AX17/0.51 -> 1.372549 | K14: =WATER!I18 -> 0 | L14: =SUM(WATER!J18) -> 0 | M14: =WATER!Q18 -> 0 | N14: 0.6 | O14: =ELEC!B15 -> 4.002
A15: Beirut | B15: =B14+1 -> 14 | C15: 6 | D15: 2020 | E15: =ELEC!N16 -> 14400 | F15: =SUM('EDl log'!T18) -> 0.075406422 | G15: =-tanks!AW19 -> 302 | H15: =SUM(tanks!AV19) -> 0.34 | I15: =('B5'!AU18)*0.51 -> 45.9 | J15: ='B5'!AX18/0.51 -> 1.372549 | K15: =WATER!I19 -> 0 | L15: =SUM(WATER!J19) -> 0 | M15: =WATER!Q19 -> 0 | N15: 0.6 | O15: =ELEC!B16 -> 2.99
A16: Beirut | B16: =B15+1 -> 15 | C16: 6 | D16: 2020 | E16: =ELEC!N17 -> 15381 | F16: =SUM('EDl log'!T19) -> 0.063495348 | G16: =-tanks!AW20 -> 352 | H16: =SUM(tanks!AV20) -> 0.36 | I16: =('B5'!AU19)*0.51 -> 61.2 | J16: ='B5'!AX19/0.51 -> 1.372549 | K16: =WATER!I20 -> 0 | L16: =SUM(WATER!J20) -> 0 | M16: =WATER!Q20 -> 0 | N16: 0.6 | O16: =ELEC!B17 -> 2.99
A17: Beirut | B17: =B16+1 -> 16 | C17: 6 | D17: 2020 | E17: =ELEC!N18 -> 15463 | F17: =SUM('EDl log'!T20) -> 0.075298067 | G17: =-tanks!AW21 -> 346 | H17: =SUM(tanks!AV21) -> 0.36 | I17: =('B5'!AU20)*0.51 -> 45.9 | J17: ='B5'!AX20/0.51 -> 1.372549 | K17: =WATER!I21 -> 80 | L17: =SUM(WATER!J21) -> 3.125 | M17: =WATER!Q21 -> 0 | N17: 0.6 | O17: =ELEC!B18 -> 4.991
A18: Beirut | B18: =B17+1 -> 17 | C18: 6 | D18: 2020 | E18: =ELEC!N19 -> 14854 | F18: =SUM('EDl log'!T21) -> 0.044932263 | G18: =-tanks!AW22 -> 312 | H18: =SUM(tanks!AV22) -> 0.393 | I18: =('B5'!AU21)*0.51 -> 45.9 | J18: ='B5'!AX21/0.51 -> 1.372549 | K18: =WATER!I22 -> 0 | L18: =SUM(WATER!J22) -> 0 | M18: =WATER!Q22 -> 0 | N18: 0.6 | O18: =ELEC!B19 -> 4.002
A19: Beirut | B19: =B18+1 -> 18 | C19: 6 | D19: 2020 | E19: =ELEC!N20 -> 17822 | F19: =SUM('EDl log'!T22) -> 0.072850854 | G19: =-tanks!AW23 -> 588.6 | H19: =SUM(tanks!AV23) -> 0.393 | I19: =('B5'!AU22)*0.51 -> 260.1 | J19: ='B5'!AX22/0.51 -> 1.372549 | K19: =WATER!I23 -> 338 | L19: =SUM(WATER!J23) -> 0.73964497 | M19: =WATER!Q23 -> 0 | N19: 0.6 | O19: =ELEC!B20 -> 4.991
A20: Beirut | B20: =B19+1 -> 19 | C20: 6 | D20: 2020 | E20: =ELEC!N21 -> 18356 | F20: =SUM('EDl log'!T23) -> 0.068584898 | G20: =-tanks!AW24 -> 482 | H20: =SUM(tanks!AV24) -> 0.393 | I20: =('B5'!AU23)*0.51 -> 76.5 | J20: ='B5'!AX23/0.51 -> 1.372549 | K20: =WATER!I24 -> 0 | L20: =SUM(WATER!J24) -> 0 | M20: =WATER!Q24 -> 0 | N20: 0.6 | O20: =ELEC!B21 -> 6.992
A21: Beirut | B21: =B20+1 -> 20 | C21: 6 | D21: 2020 | E21: =ELEC!N22 -> 15602 | F21: =SUM('EDl log'!T24) -> 0.065339039 | G21: =-tanks!AW25 -> 279 | H21: =SUM(tanks!AV25) -> 0.393 | I21: =('B5'!AU24)*0.51 -> 30.6 | J21: ='B5'!AX24/0.51 -> 1.372549 | K21: =WATER!I25 -> 246 | L21: =SUM(WATER!J25) -> 1.0162602 | M21: =WATER!Q25 -> 0 | N21: 0.6 | O21: =ELEC!B22 -> 4.991
A22: Beirut | B22: =B21+1 -> 21 | C22: 6 | D22: 2020 | E22: =ELEC!N23 -> 15615 | F22: =SUM('EDl log'!T25) -> 0.068667534 | G22: =-tanks!AW26 -> 382 | H22: =SUM(tanks!AV26) -> 0.393 | I22: =('B5'!AU25)*0.51 -> 45.9 | J22: ='B5'!AX25/0.51 -> 1.372549 | K22: =WATER!I26 -> 0 | L22: =SUM(WATER!J26) -> 0 | M22: =WATER!Q26 -> 0 | N22: 0.6 | O22: =ELEC!B23 -> 2.001
A23: Beirut | B23: =B22+1 -> 22 | C23: 6 | D23: 2020 | E23: =ELEC!N24 -> 16091 | F23: =SUM('EDl log'!T26) -> 0.074020049 | G23: =-tanks!AW27 -> 449 | H23: =SUM(tanks!AV27) -> 0.393 | I23: =('B5'!AU26)*0.51 -> -30.6 | J23: ='B5'!AX26/0.51 -> 1.372549 | K23: =WATER!I27 -> 0 | L23: =SUM(WATER!J27) -> 0 | M23: =WATER!Q27 -> 0 | N23: 0.6 | O23: =ELEC!B24 -> 6.003
A24: Beirut | B24: =B23+1 -> 23 | C24: 6 | D24: 2020 | E24: =ELEC!N25 -> 15947 | F24: =SUM('EDl log'!T27) -> 0.070187627 | G24: =-tanks!AW28 -> 318 | H24: =SUM(tanks!AV28) -> 0.393 | I24: =('B5'!AU27)*0.51 -> 45.9 | J24: ='B5'!AX27/0.51 -> 1.372549 | K24: =WATER!I28 -> 0 | L24: =SUM(WATER!J28) -> 0 | M24: =WATER!Q28 -> 0 | N24: 0.6 | O24: =ELEC!B25 -> 4.002
... A31: Beirut | B31: =B30+1 -> 30 | C31: 6 | D31: 2020 | E31: =ELEC!N32 -> 0 | F31: =SUM('EDl log'!T34) -> 0 | G31: =-tanks!AW35 -> 0 | H31: =SUM(tanks!AV35) -> 0.4128 | I31: =('B5'!AU34)*0.51 -> 0 | J31: ='B5'!AX34/0.51 -> 1.372549 | K31: =WATER!I35 -> 0 | L31: =SUM(WATER!J35) -> 0 | M31: =WATER!Q35 -> 0 | N31: 0.6 | O31: =ELEC!B32 -> 0

Sheet Submetering
A1: Site Name | B1: Day | C1: Month | D1: Year | E1: ATS1 Kwh | F1: ATS2 Kwh | G1: ATS3 Kwh | H1: ATS4 Kwh | I1: ATS5 Kwh | J1: Guest (m3) | K1: Kitchen & Laundry (m3) | L1: Room Nights
A2: Beirut | B2: 1 | C2: 6 | D2: 2020 | E2: =ELEC!M3 -> 5278 | F2: =ELEC!K3 -> 2192 | G2: =ELEC!I3 -> 1830 | H2: =ELEC!E3 -> 3460 | I2: =ELEC!G3 -> 1533 | J2: =WATER!Y6 -> 0 | K2: =WATER!AJ6 -> 0 | L2: =ELEC!B3 -> 4.991
A3: Beirut | B3: =B2+1 -> 2 | C3: 6 | D3: 2020 | E3: =ELEC!M4 -> 5374 | F3: =ELEC!K4 -> 2326 | G3: =ELEC!I4 -> 1596 | H3: =ELEC!E4 -> 3082 | I3: =ELEC!G4 -> 1350 | J3: =WATER!Y7 -> 0 | K3: =WATER!AJ7 -> 0 | L3: =ELEC!B4 -> 2.001
A4: Beirut | B4: =B3+1 -> 3 | C4: 6 | D4: 2020 | E4: =ELEC!M5 -> 3912 | F4: =ELEC!K5 -> 2394 | G4: =ELEC!I5 -> 1642 | H4: =ELEC!E5 -> 5024 | I4: =ELEC!G5 -> 1444 | J4: =WATER!Y8 -> 0 | K4: =WATER!AJ8 -> 0 | L4: =ELEC!B5 -> 6.003
A5: Beirut | B5: =B4+1 -> 4 | C5: 6 | D5: 2020 | E5: =ELEC!M6 -> 4642 | F5: =ELEC!K6 -> 2140 | G5: =ELEC!I6 -> 1582 | H5: =ELEC!E6 -> 2568 | I5: =ELEC!G6 -> 1521 | J5: =WATER!Y9 -> 30 | K5: =WATER!AJ9 -> 44 | L5: =ELEC!B6 -> 4.991
A6: Beirut | B6: =B5+1 -> 5 | C6: 6 | D6: 2020 | E6: =ELEC!M7 -> 5086 | F6: =ELEC!K7 -> 2000 | G6: =ELEC!I7 -> 1906 | H6: =ELEC!E7 -> 2948 | I6: =ELEC!G7 -> 1693 | J6: =WATER!Y10 -> 0 | K6: =WATER!AJ10 -> 33 | L6: =ELEC!B7 -> 2.99
A7: Beirut | B7: =B6+1 -> 6 | C7: 6 | D7: 2020 | E7: =ELEC!M8 -> 4466 | F7: =ELEC!K8 -> 2156 | G7: =ELEC!I8 -> 1690 | H7: =ELEC!E8 -> 3890 | I7: =ELEC!G8 -> 1576 | J7: =WATER!Y11 -> 0 | K7: =WATER!AJ11 -> 0 | L7: =ELEC!B8 -> 4.991
A8: Beirut | B8: =B7+1 -> 7 | C8: 6 | D8: 2020 | E8: =ELEC!M9 -> 4834 | F8: =ELEC!K9 -> 2572 | G8: =ELEC!I9 -> 1810 | H8: =ELEC!E9 -> 5210 | I8: =ELEC!G9 -> 1779 | J8: =WATER!Y12 -> 0 | K8: =WATER!AJ12 -> 0 | L8: =ELEC!B9 -> 4.002
A9: Beirut | B9: =B8+1 -> 8 | C9: 6 | D9: 2020 | E9: =ELEC!M10 -> 6270 | F9: =ELEC!K10 -> 2636 | G9: =ELEC!I10 -> 1756 | H9: =ELEC!E10 -> 3342 | I9: =ELEC!G10 -> 1741 | J9: =WATER!Y13 -> 3 | K9: =WATER!AJ13 -> 0 | L9: =ELEC!B10 -> 2.99
A10: Beirut | B10: =B9+1 -> 9 | C10: 6 | D10: 2020 | E10: =ELEC!M11 -> 4206 | F10: =ELEC!K11 -> 2540 | G10: =ELEC!I11 -> 1692 | H10: =ELEC!E11 -> 5186 | I10: =ELEC!G11 -> 1659 | J10: =WATER!Y14 -> 77 | K10: =WATER!AJ14 -> 46 | L10: =ELEC!B11 -> 4.002
A11: Beirut | B11: =B10+1 -> 10 | C11: 6 | D11: 2020 | E11: =ELEC!M12 -> 6604 | F11: =ELEC!K12 -> 2836 | G11: =ELEC!I12 -> 1750 | H11: =ELEC!E12 -> 3796 | I11: =ELEC!G12 -> 1648 | J11: =WATER!Y15 -> 46 | K11: =WATER!AJ15 -> 71 | L11: =ELEC!B12 -> 4.002
A12: Beirut | B12: =B11+1 -> 11 | C12: 6 | D12: 2020 | E12: =ELEC!M13 -> 5816 | F12: =ELEC!K13 -> 2328 | G12: =ELEC!I13 -> 1632 | H12: =ELEC!E13 -> 2998 | I12: =ELEC!G13 -> 1663 | J12: =WATER!Y16 -> 44 | K12: =WATER!AJ16 -> 19 | L12: =ELEC!B13 -> 2.99
A13: Beirut | B13: =B12+1 -> 12 | C13: 6 | D13: 2020 | E13: =ELEC!M14 -> 4732 | F13: =ELEC!K14 -> 2650 | G13: =ELEC!I14 -> 1914 | H13: =ELEC!E14 -> 4748 | I13: =ELEC!G14 -> 1826 | J13: =WATER!Y17 -> 0 | K13: =WATER!AJ17 -> 0 | L13: =ELEC!B14 -> 6.9
A14: Beirut | B14: =B13+1 -> 13 | C14: 6 | D14: 2020 | E14: =ELEC!M15 -> 5584 | F14: =ELEC!K15 -> 2570 | G14: =ELEC!I15 -> 1742 | H14: =ELEC!E15 -> 3480 | I14: =ELEC!G15 -> 1671 | J14: =WATER!Y18 -> 0 | K14: =WATER!AJ18 -> 0 | L14: =ELEC!B15 -> 4.002
... A31: Beirut | B31: =B30+1 -> 30 | C31: 6 | D31: 2020 | E31: =ELEC!M32 -> 0 | F31: =ELEC!K32 -> 0 | G31: =ELEC!I32 -> 0 | H31: =ELEC!E32 -> 0 | I31: =ELEC!G32 -> 0 | J31: =WATER!Y35 -> 0 | K31: =WATER!AJ35 -> 0 | L31: =ELEC!B32 -> 0

Sheet ELEC
A1: OOC | B1: Room OCC | D1: MDB3 | E1: MDB3/day | F1: EMDB2 | G1: EMDB2/day | H1: EMDB1 | I1: EMDB1/day | J1: MDB2 | K1: mdb2/day | L1: MDB1 | M1: MDB1/Day | N1: Total KWH | O1: KWH/Rooc | P1: Gen MHW | Q1: Gen/Day KWH | R1: EDL KWH | S1: CH1 RH | T1: RH | U1: C1h1 power | V1: CH1 Con KWH | W1: CH2 RH | X1: RH | Y1: Ch2 power | Z1: CH2 Con KWH | AA1: CH3 RH | AB1: RH | AC1: Ch3 power | AD1: CH3 Con KWH | AE1: RH total | AF1: KWH total | AG1: AVG chiller KW/Hr
A2: =[1]ELEC!A32 -> 0.013 | B2: 0.0299 | C2: 43982 | D2: =[2]ELEC!D33 -> 31738156 | E2: =[2]ELEC!E33 -> 3210 | F2: =[2]ELEC!F33 -> 3692449 | G2: =[2]ELEC!G33 -> 1387 | H2: =[2]ELEC!H33 -> 17470270 | I2: =[2]ELEC!I33 -> 1740 | J2: =[2]ELEC!J33 -> 28449698 | K2: =[2]ELEC!K33 -> 2176 | ... AI2: =[2]ELEC!AI33 -> -49957087
A3: ='General information '!F6 -> 0.0217 | B3: =SUM(230*A3) -> 4.991 | C3: 43983 | D3: 31741616 | E3: =D3-D2 -> 3460 | F3: 3693982 | G3: =F3-F2 -> 1533 | H3: 17472100 | I3: =H3-H2 -> 1830 | J3: 28451890 | K3: =J3-J2 -> 2192 | L3: 23072552 | M3: =L3-L2 -> 5278 | N3: =M3+K3+I3+G3+E3 -> 14293 | O3: =IF(B3>0,N3/B3,0) -> 2863.7548 | P3: 15549 | Q3: =(P3-P2)*1000 -> 2000 | R3: =+N3-Q3 -> 12293 | S3: 8609 | T3: =S3-S2 -> 20 | U3: 75398 | V3: =U3-U2 -> 2206 | W3: 31853 | X3: =W3-W2 -> 0 | Y3: 625865 | Z3: =Y3-Y2 -> 0 | AA3: 35119 | AB3: =AA3-AA2 -> 0 | AC3: 790452 | AD3: =AC3-AC2 -> 0 | AE3: =AB3+X3+T3 -> 20 | AF3: =V3+Z3+AD3 -> 2206 | AG3: =IF(AE3>0,AF3/AE3,0) -> 110.3
A4: ='General information '!F7 -> 0.0087 | B4: =SUM(230*A4) -> 2.001 | C4: 43984 | D4: 31744698 | E4: =D4-D3 -> 3082 | F4: 3695332 | G4: =F4-F3 -> 1350 | H4: 17473696 | I4: =H4-H3 -> 1596 | J4: 28454216 | K4: =J4-J3 -> 2326 | L4: 23077926 | M4: =L4-L3 -> 5374 | N4: =M4+K4+I4+G4+E4 -> 13728 | O4: =IF(B4>0,N4/B4,0) -> 6860.5697 | P4: 15551 | Q4: =(P4-P3)*1000 -> 2000 | R4: =N4-Q4 -> 11728 | S4: 8620 | T4: =S4-S3 -> 11 | U4: 77802 | V4: =U4-U3 -> 2404 | W4: =W3 -> 31853 | X4: =W4-W3 -> 0 | Y4: =Y3 -> 625865 | Z4: =Y4-Y3 -> 0 | AA4: =AA3 -> 35119 | AB4: =AA4-AA3 -> 0 | AC4: =AC3 -> 790452 | AD4: =AC4-AC3 -> 0 | AE4: =AB4+X4+T4 -> 11 | AF4: =V4+Z4+AD4 -> 2404 | AG4: =IF(AE4>0,AF4/AE4,0) -> 218.54545
A5: ='General information '!F8 -> 0.0261 | B5: =SUM(230*A5) -> 6.003 | C5: 43985 | D5: 31749722 | E5: =D5-D4 -> 5024 | F5: 3696776 | G5: =F5-F4 -> 1444 | H5: 17475338 | I5: =H5-H4 -> 1642 | J5: 28456610 | K5: =J5-J4 -> 2394 | L5: 23081838 | M5: =L5-L4 -> 3912 | N5: =M5+K5+I5+G5+E5 -> 14416 | O5: =IF(B5>0,N5/B5,0) -> 2401.4659 | P5: 15553 | Q5: =(P5-P4)*1000 -> 2000 | R5: =N5-Q5 -> 12416 | S5: 8625 | T5: =S5-S4 -> 5 | U5: 78590 | V5: =U5-U4 -> 788 | W5: =W4 -> 31853 | X5: =W5-W4 -> 0 | Y5: =Y4 -> 625865 | Z5: =Y5-Y4 -> 0 | AA5: 35126 | AB5: =AA5-AA4 -> 7 | AC5: 791862 | AD5: =AC5-AC4 -> 1410 | AE5: =AB5+X5+T5 -> 12 | AF5: =V5+Z5+AD5 -> 2198 | AG5: =IF(AE5>0,AF5/AE5,0) -> 183.16667 | AI5: =R5-'EDl log'!B3 -> -49976236
A6: ='General information '!F9 -> 0.0217 | B6: =SUM(230*A6) -> 4.991 | C6: 43986 | D6: 31752290 | E6: =D6-D5 -> 2568 | F6: 3698297 | G6: =F6-F5 -> 1521 | H6: 17476920 | I6: =H6-H5 -> 1582 | J6: 28458750 | K6: =J6-J5 -> 2140 | L6: 23086480 | M6: =L6-L5 -> 4642 | N6: =M6+K6+I6+G6+E6 -> 12453 | O6: =IF(B6>0,N6/B6,0) -> 2495.0912 | P6: 15555 | Q6: =(P6-P5)*1000 -> 2000 | R6: =N6-Q6 -> 10453 | S6: 8632 | T6: =S6-S5 -> 7 | U6: 80356 | V6: =U6-U5 -> 1766 | W6: =W5 -> 31853 | X6: =W6-W5 -> 0 | Y6: =Y5 -> 625865 | Z6: =Y6-Y5 -> 0 | AA6: 35127 | AB6: =AA6-AA5 -> 1 | AC6: 792067 | AD6: =AC6-AC5 -> 205 | AE6: =AB6+X6+T6 -> 8 | AF6: =V6+Z6+AD6 -> 1971 | AG6: =IF(AE6>0,AF6/AE6,0) -> 246.375 | AI6: =R6-'EDl log'!B4 -> -49984599
A7: ='General information '!F10 -> 0.013 | B7: =SUM(230*A7) -> 2.99 | C7: 43987 | D7: 31755238 | E7: =D7-D6 -> 2948 | F7: 3699990 | G7: =F7-F6 -> 1693 | H7: 17478826 | I7: =H7-H6 -> 1906 | J7: 28460750 | K7: =J7-J6 -> 2000 | L7: 23091566 | M7: =L7-L6 -> 5086 | N7: =M7+K7+I7+G7+E7 -> 13633 | O7: =IF(B7>0,N7/B7,0) -> 4559.5318 | P7: 15557 | Q7: =(P7-P6)*1000 -> 2000 | R7: =N7-Q7 -> 11633 | S7: 8639 | T7: =S7-S6 -> 7 | U7: 81962 | V7: =U7-U6 -> 1606 | W7: =W6 -> 31853 | X7: =W7-W6 -> 0 | Y7: =Y6 -> 625865 | Z7: =Y7-Y6 -> 0 | AA7: =AA6 -> 35127 | AB7: 0 | AC7: =AC6 -> 792067 | AD7: =AC7-AC6 -> 0 | AE7: =AB7+X7+T7 -> 7 | AF7: =V7+Z7+AD7 -> 1606 | AG7: =IF(AE7>0,AF7/AE7,0) -> 229.42857 | AI7: =R7-'EDl log'!B5 -> -49989529
A8: ='General information '!F11 -> 0.0217 | B8: =SUM(230*A8) -> 4.991 | C8: 43988 | D8: 31759128 | E8: =D8-D7 -> 3890 | F8: 3701566 | G8: =F8-F7 -> 1576 | H8: 17480516 | I8: =H8-H7 -> 1690 | J8: 28462906 | K8: =J8-J7 -> 2156 | L8: 23096032 | M8: =L8-L7 -> 4466 | N8: =M8+K8+I8+G8+E8 -> 13778 | O8: =IF(B8>0,N8/B8,0) -> 2760.569 | P8: 15559 | Q8: =(P8-P7)*1000 -> 2000 | R8: =N8-Q8 -> 11778 | S8: 8644 | T8: =S8-S7 -> 5 | U8: 83336 | V8: =U8-U7 -> 1374 | W8: =W7 -> 31853 | X8: =W8-W7 -> 0 | Y8: =Y7 -> 625865 | Z8: =Y8-Y7 -> 0 | AA8: 35130 | AB8: =AA8-AA7 -> 3 | AC8: 792883 | AD8: =AC8-AC7 -> 816 | AE8: =AB8+X8+T8 -> 8 | AF8: =V8+Z8+AD8 -> 2190 | AG8: =IF(AE8>0,AF8/AE8,0) -> 273.75 | AI8: =R8-'EDl log'!B6 -> -49995898
A9: ='General information '!F12 -> 0.0174 | B9: =SUM(230*A9) -> 4.002 | C9: 43989 | D9: 31764338 | E9: =D9-D8 -> 5210 | F9: 3703345 | G9: =F9-F8 -> 1779 | H9: 17482326 | I9: =H9-H8 -> 1810 | J9: 28465478 | K9: =J9-J8 -> 2572 | L9: 23100866 | M9: =L9-L8 -> 4834 | N9: =M9+K9+I9+G9+E9 -> 16205 | O9: =IF(B9>0,N9/B9,0) -> 4049.2254 | P9: 15561 | Q9: =(P9-P8)*1000 -> 2000 | R9: =N9-Q9 -> 14205 | S9: 8650 | T9: =S9-S8 -> 6 | U9: 84790 | V9: =U9-U8 -> 1454 | W9: 31853 | X9: =W9-W8 -> 0 | Y9: =Y8 -> 625865 | Z9: =Y9-Y8 -> 0 | AA9: 35137 | AB9: =AA9-AA8 -> 7 | AC9: 794338 | AD9: =AC9-AC8 -> 1455 | AE9: =AB9+X9+T9 -> 13 | AF9: =V9+Z9+AD9 -> 2909 | AG9: =IF(AE9>0,AF9/AE9,0) -> 223.76923 | AI9: =R9-'EDl log'!B7 -> -49999035
A10: ='General information '!F13 -> 0.013 | B10: =SUM(230*A10) -> 2.99 | C10: 43990 | D10: 31767680 | E10: =D10-D9 -> 3342 | F10: 3705086 | G10: =F10-F9 -> 1741 | H10: 17484082 | I10: =H10-H9 -> 1756 | J10: 28468114 | K10: =J10-J9 -> 2636 | L10: 23107136 | M10: =L10-L9 -> 6270 | N10: =M10+K10+I10+G10+E10 -> 15745 | O10: =IF(B10>0,N10/B10,0) -> 5265.8863 | P10: 15563 | Q10: =(P10-P9)*1000 -> 2000 | R10: =N10-Q10 -> 13745 | S10: 8662 | T10: =S10-S9 -> 12 | U10: 87625 | V10: =U10-U9 -> 2835 | W10: =W9 -> 31853 | X10: =W10-W9 -> 0 | Y10: =Y9 -> 625865 | Z10: =Y10-Y9 -> 0 | AA10: =AA9 -> 35137 | AB10: =AA10-AA9 -> 0 | AC10: =AC9 -> 794338 | AD10: =AC10-AC9 -> 0 | AE10: =AB10+X10+T10 -> 12 | AF10: =V10+Z10+AD10 -> 2835 | AG10: =IF(AE10>0,AF10/AE10,0) -> 236.25 | AI10: =R10-'EDl log'!B8 -> -50005354
A11: ='General information '!F14 -> 0.0174 | B11: =SUM(230*A11) -> 4.002 | C11: 43991 | D11: 31772866 | E11: =D11-D10 -> 5186 | F11: 3706745 | G11: =F11-F10 -> 1659 | H11: 17485774 | I11: =H11-H10 -> 1692 | J11: 28470654 | K11: =J11-J10 -> 2540 | L11: 23111342 | M11: =L11-L10 -> 4206 | N11: =M11+K11+I11+G11+E11 -> 15283 | O11: =IF(B11>0,N11/B11,0) -> 3818.8406 | P11: 15565 | Q11: =(P11-P10)*1000 -> 2000 | R11: =N11-Q11 -> 13283 | S11: 8665 | T11: =S11-S10 -> 3 | U11: 88326 | V11: =U11-U10 -> 701 | W11: 31853 | X11: =W11-W10 -> 0 | Y11: =Y10 -> 625865 | Z11: =Y11-Y10 -> 0 | AA11: 35145 | AB11: =AA11-AA10 -> 8 | AC11: 796009 | AD11: =AC11-AC10 -> 1671 | AE11: =AB11+X11+T11 -> 11 | AF11: =V11+Z11+AD11 -> 2372 | AG11: =IF(AE11>0,AF11/AE11,0) -> 215.63636 | AI11: =R11-'EDl log'!B9 -> -50011933
A12: ='General information '!F15 -> 0.0174 | B12: =SUM(230*A12) -> 4.002 | C12: 43992 | D12: 31776662 | E12: =D12-D11 -> 3796 | F12: 3708393 | G12: =F12-F11 -> 1648 | H12: 17487524 | I12: =H12-H11 -> 1750 | J12: 28473490 | K12: =J12-J11 -> 2836 | L12: 23117946 | M12: =L12-L11 -> 6604 | N12: =M12+K12+I12+G12+E12 -> 16634 | O12: =IF(B12>0,N12/B12,0) -> 4156.4218 | P12: 15571 | Q12: =(P12-P11)*1000 -> 6000 | R12: =N12-Q12 -> 10634 | S12: 8679 | T12: =S12-S11 -> 14 | U12: 91701 | V12: =U12-U11 -> 3375 | W12: 31853 | X12: =W12-W11 -> 0 | Y12: =Y11 -> 625865 | Z12: =Y12-Y11 -> 0 | AA12: 35145 | AB12: =AA12-AA11 -> 0 | AC12: 796009 | AD12: =AC12-AC11 -> 0 | AE12: =AB12+X12+T12 -> 14 | AF12: =V12+Z12+AD12 -> 3375 | AG12: =IF(AE12>0,AF12/AE12,0) -> 241.07143 | AI12: =R12-'EDl log'!B10 -> -50021868
A13: ='General information '!F16 -> 0.013 | B13: =SUM(230*A13) -> 2.99 | C13: 43993 | D13: 31779660 | E13: =D13-D12 -> 2998 | F13: 3710056 | G13: =F13-F12 -> 1663 | H13: 17489156 | I13: =H13-H12 -> 1632 | J13: 28475818 | K13: =J13-J12 -> 2328 | L13: 23123762 | M13: =L13-L12 -> 5816 | N13: =M13+K13+I13+G13+E13 -> 14437 | O13: =IF(B13>0,N13/B13,0) -> 4828.4281 | P13: 15576 | Q13: =(P13-P12)*1000 -> 5000 | R13: =N13-Q13 -> 9437 | S13: 8689 | T13: =S13-S12 -> 10 | U13: 94466 | V13: =U13-U12 -> 2765 | W13: 31853 | X13: =W13-W12 -> 0 | Y13: 625865 | Z13: =Y13-Y12 -> 0 | AA13: 35145 | AB13: =AA13-AA12 -> 0 | AC13: 796020 | AD13: =AC13-AC12 -> 11 | AE13: =AB13+X13+T13 -> 10 | AF13: =V13+Z13+AD13 -> 2776 | AG13: =IF(AE13>0,AF13/AE13,0) -> 277.6 | AI13: =R13-'EDl log'!B11 -> -50030059
A14: ='General information '!F17 -> 0.03 | B14: =SUM(230*A14) -> 6.9 | C14: 43994 | D14: 31784408 | E14: =D14-D13 -> 4748 | F14: 3711882 | G14: =F14-F13 -> 1826 | H14: 17491070 | I14: =H14-H13 -> 1914 | J14: 28478468 | K14: =J14-J13 -> 2650 | L14: 23128494 | M14: =L14-L13 -> 4732 | N14: =M14+K14+I14+G14+E14 -> 15870 | O14: =IF(B14>0,N14/B14,0) -> 2300 | P14: 15582 | Q14: =(P14-P13)*1000 -> 6000 | R14: =N14-Q14 -> 9870 | S14: 8693 | T14: =S14-S13 -> 4 | U14: 95407 | V14: =U14-U13 -> 941 | W14: =W13 -> 31853 | X14: =W14-W13 -> 0 | Y14: =Y13 -> 625865 | Z14: =Y14-Y13 -> 0 | AA14: 35151 | AB14: =AA14-AA13 -> 6 | AC14: 797425 | AD14: =AC14-AC13 -> 1405 | AE14: =AB14+X14+T14 -> 10 | AF14: =V14+Z14+AD14 -> 2346 | AG14: =IF(AE14>0,AF14/AE14,0) -> 234.6 | AI14: =R14-'EDl log'!B12 -> -50036557
A15: ='General information '!F18 -> 0.0174 | B15: =SUM(230*A15) -> 4.002 | C15: 43995 | D15: 31787888 | E15: =D15-D14 -> 3480 | F15: 3713553 | G15: =F15-F14 -> 1671 | H15: 17492812 | I15: =H15-H14 -> 1742 | J15: 28481038 | K15: =J15-J14 -> 2570 | L15: 23134078 | M15: =L15-L14 -> 5584 | N15: =M15+K15+I15+G15+E15 -> 15047 | O15: =IF(B15>0,N15/B15,0) -> 3759.8701 | P15: 15588 | Q15: =(P15-P14)*1000 -> 6000 | R15: =N15-Q15 -> 9047 | S15: 8703 | T15: =S15-S14 -> 10 | U15: 97598 | V15: =U15-U14 -> 2191 | W15: =W14 -> 31853 | X15: =W15-W14 -> 0 | Y15: =Y14 -> 625865 | Z15: =Y15-Y14 -> 0 | AA15: 35152 | AB15: =AA15-AA14 -> 1 | AC15: 797715 | AD15: =AC15-AC14 -> 290 | AE15: =AB15+X15+T15 -> 11 | AF15: =V15+Z15+AD15 -> 2481 | AG15: =IF(AE15>0,AF15/AE15,0) -> 225.54545 | AI15: =R15-'EDl log'!B13 -> -50043103
A16: ='General information '!F19 -> 0.013 | B16: =SUM(230*A16) -> 2.99 | C16: 43996 | D16: 31791758 | E16: =D16-D15 -> 3870 | F16: 3715135 | G16: =F16-F15 -> 1582 | H16: 17494450 | I16: =H16-H15 -> 1638 | J16: 28483540 | K16: =J16-J15 -> 2502 | L16: 23138886 | M16: =L16-L15 -> 4808 | N16: =M16+K16+I16+G16+E16 -> 14400 | O16: =IF(B16>0,N16/B16,0) -> 4816.0535 | P16: 15591 | Q16: =(P16-P15)*1000 -> 3000 | R16: =N16-Q16 -> 11400 | S16: 8710 | T16: =S16-S15 -> 7 | U16: 99409 | V16: =U16-U15 -> 1811 | W16: =W15 -> 31853 | X16: =W16-W15 -> 0 | Y16: =Y15 -> 625865 | Z16: =Y16-Y15 -> 0 | AA16: 35155 | AB16: =AA16-AA15 -> 3 | AC16: 798430 | AD16: =AC16-AC15 -> 715 | AE16: =AB16+X16+T16 -> 10 | AF16: =V16+Z16+AD16 -> 2526 | AG16: =IF(AE16>0,AF16/AE16,0) -> 252.6 | AI16: =R16-'EDl log'!B14 -> -50043254
A17: ='General information '!F20 -> 0.013 | B17: =SUM(230*A17) -> 2.99 | C17: 43997 | D17: 31795582 | E17: =D17-D16 -> 3824 | F17: 3716824 | G17: =F17-F16 -> 1689 | H17: 17496382 | I17: =H17-H16 -> 1932 | J17: 28486266 | K17: =J17-J16 -> 2726 | L17: 23144096 | M17: =L17-L16 -> 5210 | N17: =M17+K17+I17+G17+E17 -> 15381 | O17: =IF(B17>0,N17/B17,0) -> 5144.1472 | P17: 15597 | Q17: =(P17-P16)*1000 -> 6000 | R17: =N17-Q17 -> 9381 | S17: 8717 | T17: =S17-S16 -> 7 | U17: 100987 | V17: =U17-U16 -> 1578 | W17: =W16 -> 31853 | X17: =W17-W16 -> 0 | Y17: =Y16 -> 625865 | Z17: =Y17-Y16 -> 0 | AA17: 35159 | AB17: =AA17-AA16 -> 4 | AC17: 799323 | AD17: =AC17-AC16 -> 893 | AE17: =AB17+X17+T17 -> 11 | AF17: =V17+Z17+AD17 -> 2471 | AG17: =IF(AE17>0,AF17/AE17,0) -> 224.63636 | AI17: =R17-'EDl log'!B16 -> 1647
A18: ='General information '!F21 -> 0.0217 | B18: =SUM(230*A18) -> 4.991 | C18: 43998 | D18: 31798858 | E18: =D18-D17 -> 3276 | F18: 3718457 | G18: =F18-F17 -> 1633 | H18: 17498118 | I18: =H18-H17 -> 1736 | J18: 28488778 | K18: =J18-J17 -> 2512 | L18: 23150402 | M18: =L18-L17 -> 6306 | N18: =M18+K18+I18+G18+E18 -> 15463 | O18: =IF(B18>0,N18/B18,0) -> 3098.1767 | P18: 15602 | Q18: =(P18-P17)*1000 -> 5000 | R18: =N18-Q18 -> 10463 | S18: 8729 | T18: =S18-S17 -> 12 | U18: =U17 -> 100987 | V18: =U18-U17 -> 0 | W18: =W17 -> 31853 | X18: =W18-W17 -> 0 | Y18: =Y17 -> 625865 | Z18: =Y18-Y17 -> 0 | AA18: =AA17 -> 35159 | AB18: =AA18-AA17 -> 0 | AC18: =AC17 -> 799323 | AD18: =AC18-AC17 -> 0 | AE18: =AB18+X18+T18 -> 12 | AF18: =V18+Z18+AD18 -> 0 | AG18: =IF(AE18>0,AF18/AE18,0) -> 0 | AI18: =R18-'EDl log'!B17 -> -1651
A19: ='General information '!F22 -> 0.0174 | B19: =SUM(230*A19) -> 4.002 | C19: 43999 | D19: 31802702 | E19: =D19-D18 -> 3844 | F19: 3720039 | G19: =F19-F18 -> 1582 | H19: 17499770 | I19: =H19-H18 -> 1652 | J19: 28491058 | K19: =J19-J18 -> 2280 | L19: 23155898 | M19: =L19-L18 -> 5496 | N19: =M19+K19+I19+G19+E19 -> 14854 | O19: =IF(B19>0,N19/B19,0) -> 3711.6442 | P19: 15605 | Q19: =(P19-P18)*1000 -> 3000 | R19: =N19-Q19 -> 11854 | S19: 8738 | T19: =S19-S18 -> 9 | U19: 105996 | V19: =U19-U18 -> 5009 | W19: =W18 -> 31853 | X19: =W19-W18 -> 0 | Y19: =Y18 -> 625865 | Z19: =Y19-Y18 -> 0 | AA19: 35162 | AB19: =AA19-AA18 -> 3 | AC19: 799844 | AD19: =AC19-AC18 -> 521 | AE19: =AB19+X19+T19 -> 12 | AF19: =V19+Z19+AD19 -> 5530 | AG19: =IF(AE19>0,AF19/AE19,0) -> 460.83333 | AI19: =R19-'EDl log'!B18 -> -6258
A20: ='General information '!F23 -> 0.0217 | B20: =SUM(230*A20) -> 4.991 | C20: 44000 | D20: 31807178 | E20: =D20-D19 -> 4476 | F20: 3721847 | G20: =F20-F19 -> 1808 | H20: 17501702 | I20: =H20-H19 -> 1932 | J20: 28493794 | K20: =J20-J19 -> 2736 | L20: 23162768 | M20: =L20-L19 -> 6870 | N20: =M20+K20+I20+G20+E20 -> 17822 | O20: =IF(B20>0,N20/B20,0) -> 3570.8275 | P20: 15611 | Q20: =(P20-P19)*1000 -> 6000 | R20: =N20-Q20 -> 11822 | S20: 8749 | T20: =S20-S19 -> 11 | U20: 108602 | V20: =U20-U19 -> 2606 | W20: 31853 | X20: =W20-W19 -> 0 | Y20: =Y19 -> 625865 | Z20: =Y20-Y19 -> 0 | AA20: 35164 | AB20: =AA20-AA19 -> 2 | AC20: 800461 | AD20: =AC20-AC19 -> 617 | AE20: =AB20+X20+T20 -> 13 | AF20: =V20+Z20+AD20 -> 3223 | AG20: =IF(AE20>0,AF20/AE20,0) -> 247.92308 | AI20: =R20-'EDl log'!B19 -> -11176
A21: ='General information '!F24 -> 0.0304 | B21: =SUM(230*A21) -> 6.992 | C21: 44001 | D21: 31811426 | E21: =D21-D20 -> 4248 | F21: 3723517 | G21: =F21-F20 -> 1670 | H21: 17503466 | I21: =H21-H20 -> 1764 | J21: 28496722 | K21: =J21-J20 -> 2928 | L21: 23170514 | M21: =L21-L20 -> 7746 | N21: =M21+K21+I21+G21+E21 -> 18356 | O21: =IF(B21>0,N21/B21,0) -> 2625.286 | P21: 15616 | Q21: =(P21-P20)*1000 -> 5000 | R21: =N21-Q21 -> 13356 | S21: 8769 | T21: =S21-S20 -> 20 | U21: 113396 | V21: =U21-U20 -> 4794 | W21: =W20 -> 31853 | X21: =W21-W20 -> 0 | Y21: =Y20 -> 625865 | Z21: =Y21-Y20 -> 0 | AA21: =AA20 -> 35164 | AB21: =AA21-AA20 -> 0 | AC21: =AC20 -> 800461 | AD21: =AC21-AC20 -> 0 | AE21: =AB21+X21+T21 -> 20 | AF21: =V21+Z21+AD21 -> 4794 | AG21: =IF(AE21>0,AF21/AE21,0) -> 239.7 | AI21: =R21-'EDl log'!B20 -> -15123
A22: ='General information '!F25 -> 0.0217 | B22: =SUM(230*A22) -> 4.991 | C22: 44002 | D22: 31815706 | E22: =D22-D21 -> 4280 | F22: 3725089 | G22: =F22-F21 -> 1572 | H22: 17505106 | I22: =H22-H21 -> 1640 | J22: 28499050 | K22: =J22-J21 -> 2328 | L22: 23176296 | M22: =L22-L21 -> 5782 | N22: =M22+K22+I22+G22+E22 -> 15602 | O22: =IF(B22>0,N22/B22,0) -> 3126.0268 | P22: 15619 | Q22: =(P22-P21)*1000 -> 3000 | R22: =N22-Q22 -> 12602 | S22: 8783 | T22: =S22-S21 -> 14 | U22: 115780 | V22: =U22-U21 -> 2384 | W22: =W21 -> 31853 | X22: =W22-W21 -> 0 | Y22: =Y21 -> 625865 | Z22: =Y22-Y21 -> 0 | AA22: 35166 | AB22: =AA22-AA21 -> 2 | AC22: 800805 | AD22: =AC22-AC21 -> 344 | AE22: =AB22+X22+T22 -> 16 | AF22: =V22+Z22+AD22 -> 2728 | AG22: =IF(AE22>0,AF22/AE22,0) -> 170.5 | AI22: =R22-'EDl log'!B21 -> -21837
A23: ='General information '!F26 -> 0.0087 | B23: =SUM(230*A23) -> 2.001 | C23: 44003 | D23: 31821202 | E23: =D23-D22 -> 5496 | F23: 3726754 | G23: =F23-F22 -> 1665 | H23: 17506732 | I23: =H23-H22 -> 1626 | J23: 28501450 | K23: =J23-J22 -> 2400 | L23: 23180724 | M23: =L23-L22 -> 4428 | N23: =M23+K23+I23+G23+E23 -> 15615 | O23: =IF(B23>0,N23/B23,0) -> 7803.5982 | P23: 15621 | Q23: =(P23-P22)*1000 -> 2000 | R23: =N23-Q23 -> 13615 | S23: 8789 | T23: =S23-S22 -> 6 | U23: 116856 | V23: =U23-U22 -> 1076 | W23: =W22 -> 31853 | X23: =W23-W22 -> 0 | Y23: =Y22 -> 625865 | Z23: =Y23-Y22 -> 0 | AA23: 35176 | AB23: =AA23-AA22 -> 10 | AC23: 803132 | AD23: =AC23-AC22 -> 2327 | AE23: =AB23+X23+T23 -> 16 | AF23: =V23+Z23+AD23 -> 3403 | AG23: =IF(AE23>0,AF23/AE23,0) -> 212.6875 | AI23: =R23-'EDl log'!B22 -> -26897
A24: ='General information '!F27 -> 0.0261 | B24: =SUM(230*A24) -> 6.003 | C24: 44004 | D24: 31824916 | E24: =D24-D23 -> 3714 | F24: 3728359 | G24: =F24-F23 -> 1605 | H24: 17508354 | I24: =H24-H23 -> 1622 | J24: 28503978 | K24: =J24-J23 -> 2528 | L24: 23187346 | M24: =L24-L23 -> 6622 | N24: =M24+K24+I24+G24+E24 -> 16091 | O24: =IF(B24>0,N24/B24,0) -> 2680.4931 | P24: 15625 | Q24: =(P24-P23)*1000 -> 4000 | R24: =N24-Q24 -> 12091 | S24: 8803 | T24: =S24-S23 -> 14 | U24: 120006 | V24: =U24-U23 -> 3150 | W24: 31853 | X24: =W24-W23 -> 0 | Y24: =Y23 -> 625865 | Z24: =Y24-Y23 -> 0 | AA24: 35176 | AB24: =AA24-AA23 -> 0 | AC24: 803132 | AD24: =AC24-AC23 -> 0 | AE24: =AB24+X24+T24 -> 14 | AF24: =V24+Z24+AD24 -> 3150 | AG24: =IF(AE24>0,AF24/AE24,0) -> 225 | AI24: =R24-'EDl log'!B23 -> -35393
A25: ='General information '!F28 -> 0.0174 | B25: =SUM(230*A25) -> 4.002 | C25: 44005 | D25: 31829298 | E25: =D25-D24 -> 4382 | F25: 3729902 | G25: =F25-F24 -> 1543 | H25: 17509960 | I25: =H25-H24 -> 1606 | J25: 28506386 | K25: =J25-J24 -> 2408 | L25: 23193354 | M25: =L25-L24 -> 6008 | N25: =M25+K25+I25+G25+E25 -> 15947 | O25: =IF(B25>0,N25/B25,0) -> 3984.7576 | P25: 15629 | Q25: =(P25-P24)*1000 -> 4000 | R25: =N25-Q25 -> 11947 | S25: 8813 | T25: =S25-S24 -> 10 | U25: 122274 | V25: =U25-U24 -> 2268 | W25: =W24 -> 31853 | X25: =W25-W24 -> 0 | Y25: =Y24 -> 625865 | Z25: =Y25-Y24 -> 0 | AA25: 35179 | AB25: =AA25-AA24 -> 3 | AC25: 803981 | AD25: =AC25-AC24 -> 849 | AE25: =AB25+X25+T25 -> 13 | AF25: =V25+Z25+AD25 -> 3117 | AG25: =IF(AE25>0,AF25/AE25,0) -> 239.76923 | AI25: =R25-'EDl log'!B24 -> -42243
A26: ='General information '!F29 -> 0.013 | B26: =SUM(230*A26) -> 2.99 | C26: 44006 | D26: 31835342 | E26: =D26-D25 -> 6044 | F26: 3731469 | G26: =F26-F25 -> 1567 | H26: 17511654 | I26: =H26-H25 -> 1694 | J26: 28508454 | K26: =J26-J25 -> 2068 | L26: 23197692 | M26: =L26-L25 -> 4338 | N26: =M26+K26+I26+G26+E26 -> 15711 | O26: =IF(B26>0,N26/B26,0) -> 5254.5151 | P26: 15633 | Q26: =(P26-P25)*1000 -> 4000 | R26: =N26-Q26 -> 11711 | S26: 8818 | T26: =S26-S25 -> 5 | U26: 123044 | V26: =U26-U25 -> 770 | W26: 31853 | X26: =W26-W25 -> 0 | Y26: 625865 | Z26: =Y26-Y25 -> 0 | AA26: 35190 | AB26: =AA26-AA25 -> 11 | AC26: 806296 | AD26: =AC26-AC25 -> 2315 | AE26: =AB26+X26+T26 -> 16 | AF26: =V26+Z26+AD26 -> 3085 | AG26: =IF(AE26>0,AF26/AE26,0) -> 192.8125 | AI26: =R26-'EDl log'!B25 -> -49693
A27: ='General information '!F30 -> 0.0174 | B27: =SUM(230*A27) -> 4.002 | C27: 44007 | D27: 31839150 | E27: =D27-D26 -> 3808 | F27: 3733053 | G27: =F27-F26 -> 1584 | H27: 17513322 | I27: =H27-H26 -> 1668 | J27: 28511946 | K27: =J27-J26 -> 3492 | L27: 23204778 | M27: =L27-L26 -> 7086 | N27: =M27+K27+I27+G27+E27 -> 17638 | O27: =IF(B27>0,N27/B27,0) -> 4407.2964 | P27: 15637 | Q27: =(P27-P26)*1000 -> 4000 | R27: =N27-Q27 -> 13638 | S27: 8834 | T27: =S27-S26 -> 16 | U27: 126434 | V27: =U27-U26 -> 3390 | W27: =W26 -> 31853 | X27: =W27-W26 -> 0 | Y27: =Y26 -> 625865 | Z27: =Y27-Y26 -> 0 | AA27: =AA26 -> 35190 | AB27: =AA27-AA26 -> 0 | AC27: =AC26 -> 806296 | AD27: =AC27-AC26 -> 0 | AE27: =AB27+X27+T27 -> 16 | AF27: =V27+Z27+AD27 -> 3390 | AG27: =IF(AE27>0,AF27/AE27,0) -> 211.875 | AI27: =R27-'EDl log'!B26 -> -53896
A28: ='General information '!F31 -> 0.013 | B28: =SUM(230*A28) -> 2.99 | C28: 44008 | D28: 31845238 | E28: =D28-D27 -> 6088 | F28: 3734656 | G28: =F28-F27 -> 1603 | H28: 17514934 | I28: =H28-H27 -> 1612 | J28: 28514366 | K28: =J28-J27 -> 2420 | L28: 23208570 | M28: =L28-L27 -> 3792 | N28: =M28+K28+I28+G28+E28 -> 15515 | O28: =IF(B28>0,N28/B28,0) -> 5188.9632 | P28: 15642 | Q28: =(P28-P27)*1000 -> 5000 | R28: =N28-Q28 -> 10515 | S28: 8836 | T28: =S28-S27 -> 2 | U28: 126839 | V28: =U28-U27 -> 405 | W28: =W27 -> 31853 | X28: =W28-W27 -> 0 | Y28: =Y27 -> 625865 | Z28: =Y28-Y27 -> 0 | AA28: 35201 | AB28: =AA28-AA27 -> 11 | AC28: 809095 | AD28: =AC28-AC27 -> 2799 | AE28: =AB28+X28+T28 -> 13 | AF28: =V28+Z28+AD28 -> 3204 | AG28: =IF(AE28>0,AF28/AE28,0) -> 246.46154 | AI28: =R28-'EDl log'!B27 -> -63112
A29: ='General information '!F32 -> 0.024 | B29: =SUM(230*A29) -> 5.52 | C29: 44009 | D29: 31848856 | E29: =D29-D28 -> 3618 | F29: 3736373 | G29: =F29-F28 -> 1717 | H29: 17516742 | I29: =H29-H28 -> 1808 | J29: 28517086 | K29: =J29-J28 -> 2720 | L29: 23215918 | M29: =L29-L28 -> 7348 | N29: =M29+K29+I29+G29+E29 -> 17211 | O29: =IF(B29>0,N29/B29,0) -> 3117.9348 | P29: 15647 | Q29: =(P29-P28)*1000 -> 5000 | R29: =N29-Q29 -> 12211 | S29: 8849 | T29: =S29-S28 -> 13 | U29: 129921 | V29: =U29-U28 -> 3082 | W29: =W28 -> 31853 | X29: =W29-W28 -> 0 | Y29: =Y28 -> 625865 | Z29: =Y29-Y28 -> 0 | AA29: 35202 | AB29: =AA29-AA28 -> 1 | AC29: 809274 | AD29: =AC29-AC28 -> 179 | AE29: =AB29+X29+T29 -> 14 | AF29: =V29+Z29+AD29 -> 3261 | AG29: =IF(AE29>0,AF29/AE29,0) -> 232.92857 | AI29: =R29-'EDl log'!B28 -> -67445
A30: ='General information '!F33 -> 0.0348 | B30: =SUM(230*A30) -> 8.004 | C30: 44010 | D30: 31853208 | E30: =D30-D29 -> 4352 | F30: 3738167 | G30: =F30-F29 -> 1794 | H30: 17518488 | I30: =H30-H29 -> 1746 | J30: 28520040 | K30: =J30-J29 -> 2954 | L30: 23223886 | M30: =L30-L29 -> 7968 | N30: =M30+K30+I30+G30+E30 -> 18814 | O30: =IF(B30>0,N30/B30,0) -> 2350.5747 | P30: 15653 | Q30: =(P30-P29)*1000 -> 6000 | R30: =N30-Q30 -> 12814 | S30: 8871 | T30: =S30-S29 -> 22 | U30: 134599 | V30: =U30-U29 -> 4678 | W30: =W29 -> 31853 | X30: =W30-W29 -> 0 | Y30: =Y29 -> 625865 | Z30: =Y30-Y29 -> 0 | AA30: 35202 | AB30: =AA30-AA29 -> 0 | AC30: =AC29 -> 809274 | AD30: =AC30-AC29 -> 0 | AE30: =AB30+X30+T30 -> 22 | AF30: =V30+Z30+AD30 -> 4678 | AG30: =IF(AE30>0,AF30/AE30,0) -> 212.63636 | AI30: =R30-'EDl log'!B29 -> -73944
A31: ='General information '!F34 -> 0 | B31: =SUM(230*A31) -> 0 | C31: 44011 | D31: =D30 -> 31853208 | E31: =D31-D30 -> 0 | F31: =F30 -> 3738167 | G31: =F31-F30 -> 0 | H31: =H30 -> 17518488 | I31: =H31-H30 -> 0 | J31: =J30 -> 28520040 | K31: =J31-J30 -> 0 | L31: =L30 -> 23223886 | M31: =L31-L30 -> 0 | N31: =M31+K31+I31+G31+E31 -> 0 | O31: =IF(B31>0,N31/B31,0) -> 0 | P31: =P30 -> 15653 | Q31: =(P31-P30)*1000 -> 0 | R31: =N31-Q31 -> 0 | S31: =S30 -> 8871 | T31: =S31-S30 -> 0 | U31: =U30 -> 134599 | V31: =U31-U30 -> 0 | W31: =W30 -> 31853 | X31: =W31-W30 -> 0 | Y31: =Y30 -> 625865 | Z31: =Y31-Y30 -> 0 | AA31: =AA30 -> 35202 | AB31: =AA31-AA30 -> 0 | AC31: =AC30 -> 809274 | AD31: =AC31-AC30 -> 0 | AE31: =AB31+X31+T31 -> 0 | AF31: =V31+Z31+AD31 -> 0 | AG31: =IF(AE31>0,AF31/AE31,0) -> 0 | AI31: =R31-'EDl log'!B30 -> -92355
A32: ='General information '!F35 -> 0 | B32: =SUM(230*A32) -> 0 | C32: 44012 | D32: =D31 -> 31853208 | E32: =D32-D31 -> 0 | F32: =F31 -> 3738167 | G32: =F32-F31 -> 0 | H32: =H31 -> 17518488 | I32: =H32-H31 -> 0 | J32: =J31 -> 28520040 | K32: =J32-J31 -> 0 | L32: =L31 -> 23223886 | M32: =L32-L31 -> 0 | N32: =M32+K32+I32+G32+E32 -> 0 | O32: =IF(B32>0,N32/B32,0) -> 0 | P32: =P31 -> 15653 | Q32: =(P32-P31)*1000 -> 0 | R32: =N32-Q32 -> 0 | S32: =S31 -> 8871 | T32: =S32-S31 -> 0 | U32: =U31 -> 134599 | V32: =U32-U31 -> 0 | W32: =W31 -> 31853 | X32: =W32-W31 -> 0 | Y32: =Y31 -> 625865 | Z32: =Y32-Y31 -> 0 | AA32: =AA31 -> 35202 | AB32: =AA32-AA31 -> 0 | AC32: =AC31 -> 809274 | AD32: =AC32-AC31 -> 0 | AE32: =AB32+X32+T32 -> 0 | AF32: =V32+Z32+AD32 -> 0 | AG32: =IF(AE32>0,AF32/AE32,0) -> 0 | AI32: =R32-'EDl log'!B31 -> -98696

Sheet B5
F1: Boiler A | J1: =J35 -> 73.101852 | K1: Boiler B | P1: Boiler C | V1: Boiler | X1: SteamA | AC1: SteamB | AH1: Steam | AI1: Boiler & steam | AL1: Total Boiler Runing H | AM1: Total Steam Runing H | AN1: GAS1 % | AO1: GAS1/L | AP1: GAS2% | AQ1: Gas2/L | AR1: GAS3% | AS1: GAS3/L | AU1: Gas Cons | AV1: Delivery | AW1: Cost/L
B2: Level Tank Gen | C2: Level tank Boiler | D2: Daily Cons Bo. | E2: Boiler litter | F2: Boiler A | G2: Run Hr a | H2: Boiler A fuel | I2: Daily consumption | J2: AVG | K2: index Run H | L2: Run Hrb | M2: Boiler B Fuel | O2: Daily consumption | P2: Boiler C | S2: Run C | U2: Total RH | V2: Total Fuel | X2: SteamA | Y2: Run SA | Z2: Steam A Conter | AA2: Liters | AC2: SteamB | AD2: Run SteamB | AE2: Steam B Conter | AF2: SB Litters | AG2: Avg | AH2: Total Fuel | AI2: Total Fuel
S3: 0
A4: =ELEC!C2 -> 43982 | B4: =[2]B5!B35 -> 179 | C4: =[2]B5!C35 -> 186 | D4: =[2]B5!D35 -> 3.2 | E4: =[2]B5!E35 -> 26.816 | F4: =[2]B5!F35 -> 1578 | G4: =[2]B5!G35 -> 0 | H4: =[2]B5!H35 -> 352431 | I4: =[2]B5!I35 -> 0 | ... AW4: =[2]B5!AW35 -> 0 | AX4: =[1]B5!AX34 -> 0.7
A5: =ELEC!C3 -> 43983 | B5: 175 | C5: 182 | D5: =C4-C5 -> 4 | E5: =D5*8.38 -> 33.52 | F5: 1581 | G5: =F5-F4 -> 3 | H5: 352662 | I5: =SUM(H5-H4) -> 231 | J5: 1 | K5: =K4 -> 1962 | L5: =K5-K4 -> 0 | M5: =M4 -> 143825 | N5: =M5-M4 -> 0 | O5: =SUM(L5*$J$1) -> 0 | P5: 1797 | Q5: 152534 | R5: =Q5-Q4 -> 221 | S5: =SUM(P5-P4) -> 3 | T5: =SUM(S5*$T$2) -> 0 | U5: =SUM(G5+L5+S5) -> 6 | V5: =R5+N5+I5:I5 -> 452 | W5: =SUM(V5/U5) -> 75.333333 | X5: =X4 -> 2418 | Y5: =X5-X4 -> 0 | Z5: =Z4 -> 135904 | AA5: =Z5-Z4 -> 0 | AB5: =SUM(Y5*$AB$2) -> 0 | AC5: =AC4 -> 1841 | AD5: =AC5-AC4 -> 0 | AE5: =AE4 -> 359849.4 | AF5: =AE5-AE4 -> 0 | AG5: =IF(AD5>0,AF5/AD5,0) -> 0 | AH5: =AF5+AA5 -> 0 | AI5: =SUM(AH5+V5) -> 452 | AJ5: =-tanks!AW6 -> 452 | AK5: =SUM(AJ5-AI5) -> 0 | AL5: =S5+L5+G5 -> 6 | AM5: =Y5+AD5 -> 0 | AN5: 67 | AO5: =(AN5/100)*3000 -> 2010 | AP5: 78 | AQ5: =(AP5/100)*3000 -> 2340 | AR5: 69 | AS5: =(AR5/100)*3000 -> 2070 | AT5: =SUM(AO5+AQ5+AS5) -> 6420 | AU5: =AT4-AT5+AV5 -> 180 | AX5: =IF(AV5>0,AW5,AX4) -> 0.7
A6: =ELEC!C4 -> 43984 | B6: 173 | C6: 179 | D6: =C5-C6 -> 3 | E6: =D6*8.38 -> 25.14 | F6: 1582 | G6: =F6-F5 -> 1 | H6: 352783 | I6: =SUM(H6-H5) -> 121 | J6: =IF(G6>0,I6/G6,0) -> 121 | K6: 1965 | L6: =K6-K5 -> 3 | M6: 144000 | N6: =M6-M5 -> 175 | O6: =SUM(L6*$J$1) -> 219.30556 | P6: =P5 -> 1797 | Q6: 152534 | R6: =Q6-Q5 -> 0 | S6: =SUM(P6-P5) -> 0 | T6: =SUM(S6*$T$2) -> 0 | U6: =SUM(G6+L6+S6) -> 4 | V6: =R6+N6+I6:I6 -> 296 | W6: =SUM(V6/U6) -> 74 | X6: =X5 -> 2418 | Y6: =X6-X5 -> 0 | Z6: =Z5 -> 135904 | AA6: =Z6-Z5 -> 0 | AB6: =SUM(Y6*$AB$2) -> 0 | AC6: =AC5 -> 1841 | AD6: =AC6-AC5 -> 0 | AE6: =AE5 -> 359849.4 | AF6: =AE6-AE5 -> 0 | AG6: =IF(AD6>0,AF6/AD6,0) -> 0 | AH6: =AF6+AA6 -> 0 | AI6: =SUM(AH6+V6) -> 296 | AJ6: =-tanks!AW7 -> 296 | AK6: =SUM(AJ6-AI6) -> 0 | AL6: =S6+L6+G6 -> 4 | AM6: =Y6+AD6 -> 0 | AN6: 65 | AO6: =(AN6/100)*3000 -> 1950 | AP6: 75 | AQ6: =(AP6/100)*3000 -> 2250 | AR6: 71 | AS6: =(AR6/100)*3000 -> 2130 | AT6: =SUM(AO6+AQ6+AS6) -> 6330 | AU6: =AT5-AT6+AV6 -> 90 | AX6: =IF(AV6>0,AW6,AX5) -> 0.7
A7: =ELEC!C5 -> 43985 | B7: 168 | C7: 173 | D7: =C6-C7 -> 6 | E7: =D7*8.38 -> 50.28 | F7: 1582 | G7: =F7-F6 -> 0 | H7: 352783 | I7: =SUM(H7-H6) -> 0 | J7: =IF(G7>0,I7/G7,0) -> 0 | K7: 1967 | L7: =K7-K6 -> 2 | M7: 144145 | N7: =M7-M6 -> 145 | O7: 1 | P7: 1799 | Q7: 152706 | R7: =Q7-Q6 -> 172 | S7: =SUM(P7-P6) -> 2 | T7: =SUM(S7*$T$2) -> 0 | U7: =SUM(G7+L7+S7) -> 4 | V7: =R7+N7+I7:I7 -> 317 | W7: =SUM(V7/U7) -> 79.25 | X7: 2418 | Y7: =X7-X6 -> 0 | Z7: 135958 | AA7: =Z7-Z6 -> 54 | AB7: =SUM(Y7*$AB$2) -> 0 | AC7: 1841 | AD7: =AC7-AC6 -> 0 | AE7: 359849 | AF7: =AE7-AE6 -> -0.4 | AG7: =IF(AD7>0,AF7/AD7,0) -> 0 | AH7: =AF7+AA7 -> 53.6 | AI7: =SUM(AH7+V7) -> 370.6 | AJ7: =-tanks!AW8 -> 370.6 | AK7: =SUM(AJ7-AI7) -> 0 | AL7: =S7+L7+G7 -> 4 | AM7: =Y7+AD7 -> 0 | AN7: 70 | AO7: =(AN7/100)*3000 -> 2100 | AP7: 73 | AQ7: =(AP7/100)*3000 -> 2190 | AR7: 64 | AS7: =(AR7/100)*3000 -> 1920 | AT7: =SUM(AO7+AQ7+AS7) -> 6210 | AU7: =AT6-AT7+AV7 -> 120 | AX7: =IF(AV7>0,AW7,AX6) -> 0.7
A8: =ELEC!C6 -> 43986 | B8: 203 | C8: 210 | D8: =C7-C8 -> -37 | E8: =D8*8.38 -> -310.06 | F8: 1585 | G8: =F8-F7 -> 3 | H8: 352951 | I8: =SUM(H8-H7) -> 168 | J8: =IF(G8>0,I8/G8,0) -> 56 | K8: =K7 -> 1967 | L8: =K8-K7 -> 0 | M8: =M7 -> 144145 | N8: =M8-M7 -> 0 | O8: 1479 | P8: 1803 | Q8: 152938 | R8: =Q8-Q7 -> 232 | S8: =SUM(P8-P7) -> 4 | T8: =SUM(S8*$T$2) -> 0 | U8: =SUM(G8+L8+S8) -> 7 | V8: =R8+N8+I8:I8 -> 400 | W8: =SUM(V8/U8) -> 57.142857 | X8: =X7 -> 2418 | Y8: =X8-X7 -> 0 | Z8: =Z7 -> 135958 | AA8: =Z8-Z7 -> 0 | AB8: =SUM(Y8*$AB$2) -> 0 | AC8: 1845 | AD8: =AC8-AC7 -> 4 | AE8: 360077 | AF8: =AE8-AE7 -> 228 | AG8: =IF(AD8>0,AF8/AD8,0) -> 57 | AH8: =AF8+AA8 -> 228 | AI8: =SUM(AH8+V8) -> 628 | AJ8: =-tanks!AW9 -> 628 | AK8: =SUM(AJ8-AI8) -> 0 | AL8: =S8+L8+G8 -> 7 | AM8: =Y8+AD8 -> 4 | AN8: 79 | AO8: =(AN8/100)*3000 -> 2370 | AP8: 83 | AQ8: =(AP8/100)*3000 -> 2490 | AR8: 70 | AS8: =(AR8/100)*3000 -> 2100 | AT8: =SUM(AO8+AQ8+AS8) -> 6960 | AU8: =AT7-AT8+AV8 -> 350 | AV8: 1100 | AW8: 0.7 | AX8: =IF(AV8>0,AW8,AX7) -> 0.7
A9: =ELEC!C7 -> 43987 | B9: 199 | C9: 205 | D9: =C8-C9 -> 5 | E9: =D9*8.38 -> 41.9 | F9: 1587 | G9: =F9-F8 -> 2 | H9: 353130 | I9: =SUM(H9-H8) -> 179 | J9: =IF(G9>0,I9/G9,0) -> 89.5 | K9: 1968 | L9: =K9-K8 -> 1 | M9: 144264 | N9: =M9-M8 -> 119 | O9: =SUM(L9*$J$1) -> 73.101852 | P9: =P8 -> 1803 | Q9: 152974 | R9: =Q9-Q8 -> 36 | S9: =SUM(P9-P8) -> 0 | T9: =SUM(S9*$T$2) -> 0 | U9: =SUM(G9+L9+S9) -> 3 | V9: =R9+N9+I9:I9 -> 334 | W9: =SUM(V9/U9) -> 111.33333 | X9: =X8 -> 2418 | Y9: =X9-X8 -> 0 | Z9: =Z8 -> 135958 | AA9: =Z9-Z8 -> 0 | AB9: =SUM(Y9*$AB$2) -> 0 | AC9: =AC8 -> 1845 | AD9: =AC9-AC8 -> 0 | AE9: =AE8 -> 360077 | AF9: =AE9-AE8 -> 0 | AG9: =IF(AD9>0,AF9/AD9,0) -> 0 | AH9: =AF9+AA9 -> 0 | AI9: =SUM(AH9+V9) -> 334 | AJ9: =-tanks!AW10 -> 334 | AK9: =SUM(AJ9-AI9) -> 0 | AL9: =S9+L9+G9 -> 3 | AM9: =Y9+AD9 -> 0 | AN9: =AN8 -> 79 | AO9: =(AN9/100)*3000 -> 2370 | AP9: =AP8 -> 83 | AQ9: =(AP9/100)*3000 -> 2490 | AR9: 67 | AS9: =(AR9/100)*3000 -> 2010 | AT9: =SUM(AO9+AQ9+AS9) -> 6870 | AU9: =AT8-AT9+AV9 -> 90 | AX9: =IF(AV9>0,AW9,AX8) -> 0.7
A10: =ELEC!C8 -> 43988 | B10: 196 | C10: 202 | D10: =C9-C10 -> 3 | E10: =D10*8.38 -> 25.14 | F10: 1589 | G10: =F10-F9 -> 2 | H10: 353275 | I10: =SUM(H10-H9) -> 145 | J10: =IF(G10>0,I10/G10,0) -> 72.5 | K10: 1972 | L10: =K10-K9 -> 4 | M10: 144510 | N10: =M10-M9 -> 246 | O10: =SUM(L10*$J$1) -> 292.40741 | P10: =P9 -> 1803 | Q10: 152974 | R10: =Q10-Q9 -> 0 | S10: =SUM(P10-P9) -> 0 | T10: =SUM(S10*$T$2) -> 0 | U10: =SUM(G10+L10+S10) -> 6 | V10: =R10+N10+I10:I10 -> 391 | W10: =SUM(V10/U10) -> 65.166667 | X10: =X9 -> 2418 | Y10: =X10-X9 -> 0 | Z10: =Z9 -> 135958 | AA10: =Z10-Z9 -> 0 | AB10: =SUM(Y10*$AB$2) -> 0 | AC10: =AC9 -> 1845 | AD10: =AC10-AC9 -> 0 | AE10: =AE9 -> 360077 | AF10: =AE10-AE9 -> 0 | AG10: =IF(AD10>0,AF10/AD10,0) -> 0 | AH10: =AF10+AA10 -> 0 | AI10: =SUM(AH10+V10) -> 391 | AJ10: =-tanks!AW11 -> 391 | AK10: =SUM(AJ10-AI10) -> 0 | AL10: =S10+L10+G10 -> 6 | AM10: =Y10+AD10 -> 0 | AN10: 78 | AO10: =(AN10/100)*3000 -> 2340 | AP10: 81 | AQ10: =(AP10/100)*3000 -> 2430 | AR10: 68 | AS10: =(AR10/100)*3000 -> 2040 | AT10: =SUM(AO10+AQ10+AS10) -> 6810 | AU10: =AT9-AT10+AV10 -> 60 | AX10: =IF(AV10>0,AW10,AX9) -> 0.7
A11: =ELEC!C9 -> 43989 | B11: 192 | C11: 198 | D11: =C10-C11 -> 4 | E11: =D11*8.38 -> 33.52 | F11: 1593 | G11: =F11-F10 -> 4 | H11: 353638 | I11: =SUM(H11-H10) -> 363 | J11: =IF(G11>0,I11/G11,0) -> 90.75 | K11: =K10 -> 1972 | L11: =K11-K10 -> 0 | M11: =M10 -> 144510 | N11: =M11-M10 -> 0 | O11: 1803 | P11: =P10 -> 1803 | Q11: 152974 | R11: =Q11-Q10 -> 0 | S11: =SUM(P11-P10) -> 0 | T11: =SUM(S11*$T$2) -> 0 | U11: =SUM(G11+L11+S11) -> 4 | V11: =R11+N11+I11:I11 -> 363 | W11: =SUM(V11/U11) -> 90.75 | X11: =X10 -> 2418 | Y11: =X11-X10 -> 0 | Z11: =Z10 -> 135958 | AA11: =Z11-Z10 -> 0 | AB11: =SUM(Y11*$AB$2) -> 0 | AC11: =AC10 -> 1845 | AD11: =AC11-AC10 -> 0 | AE11: =AE10 -> 360077 | AF11: =AE11-AE10 -> 0 | AG11: =IF(AD11>0,AF11/AD11,0) -> 0 | AH11: =AF11+AA11 -> 0 | AI11: =SUM(AH11+V11) -> 363 | AJ11: =-tanks!AW12 -> 363 | AK11: =SUM(AJ11-AI11) -> 0 | AL11: =S11+L11+G11 -> 4 | AM11: =Y11+AD11 -> 0 | AN11: 77 | AO11: =(AN11/100)*3000 -> 2310 | AP11: 80 | AQ11: =(AP11/100)*3000 -> 2400 | AR11: =AR10 -> 68 | AS11: =(AR11/100)*3000 -> 2040 | AT11: =SUM(AO11+AQ11+AS11) -> 6750 | AU11: =AT10-AT11+AV11 -> 60 | AX11: =IF(AV11>0,AW11,AX10) -> 0.7
A12: =ELEC!C10 -> 43990 | B12: 188 | C12: 196 | D12: =C11-C12 -> 2 | E12: =D12*8.38 -> 16.76 | F12: 1596 | G12: =F12-F11 -> 3 | H12: 353825 | I12: =SUM(H12-H11) -> 187 | J12: =IF(G12>0,I12/G12,0) -> 62.333333 | K12: 1974 | L12: =K12-K11 -> 2 | M12: 144683 | N12: =M12-M11 -> 173 | O12: =SUM(L12*$J$1) -> 146.2037 | P12: =P11 -> 1803 | Q12: 152974 | R12: =Q12-Q11 -> 0 | S12: =SUM(P12-P11) -> 0 | T12: =SUM(S12*$T$2) -> 0 | U12: =SUM(G12+L12+S12) -> 5 | V12: =R12+N12+I12:I12 -> 360 | W12: =SUM(V12/U12) -> 72 | X12: =X11 -> 2418 | Y12: =X12-X11 -> 0 | Z12: =Z11 -> 135958 | AA12: =Z12-Z11 -> 0 | AB12: =SUM(Y12*$AB$2) -> 0 | AC12: =AC11 -> 1845 | AD12: =AC12-AC11 -> 0 | AE12: =AE11 -> 360077 | AF12: =AE12-AE11 -> 0 | AG12: =IF(AD12>0,AF12/AD12,0) -> 0 | AH12: =AF12+AA12 -> 0 | AI12: =SUM(AH12+V12) -> 360 | AJ12: =-tanks!AW13 -> 360 | AK12: =SUM(AJ12-AI12) -> 0 | AL12: =S12+L12+G12 -> 5 | AM12: =Y12+AD12 -> 0 | AN12: 76 | AO12: =(AN12/100)*3000 -> 2280 | AP12: 80 | AQ12: =(AP12/100)*3000 -> 2400 | AR12: 66 | AS12: =(AR12/100)*3000 -> 1980 | AT12: =SUM(AO12+AQ12+AS12) -> 6660 | AU12: =AT11-AT12+AV12 -> 90 | AX12: =IF(AV12>0,AW12,AX11) -> 0.7
A13: =ELEC!C11 -> 43991 | B13: 185.2 | C13: 191.3 | D13: =C12-C13 -> 4.7 | E13: =D13*8.38 -> 39.386 | F13: 1596 | G13: =F13-F12 -> 0 | H13: 353837 | I13: =SUM(H13-H12) -> 12 | J13: =IF(G13>0,I13/G13,0) -> 0 | K13: 1977 | L13: =K13-K12 -> 3 | M13: 144953 | N13: =M13-M12 -> 270 | O13: =SUM(L13*$J$1) -> 219.30556 | P13: 1803 | Q13: 152974 | R13: =Q13-Q12 -> 0 | S13: =SUM(P13-P12) -> 0 | T13: =SUM(S13*$T$2) -> 0 | U13: =SUM(G13+L13+S13) -> 3 | V13: =R13+N13+I13:I13 -> 282 | W13: =SUM(V13/U13) -> 94 | X13: 2418 | Y13: =X13-X12 -> 0 | Z13: 135958 | AA13: =Z13-Z12 -> 0 | AB13: =SUM(Y13*$AB$2) -> 0 | AC13: 1845 | AD13: =AC13-AC12 -> 0 | AE13: 360077 | AF13: =AE13-AE12 -> 0 | AG13: =IF(AD13>0,AF13/AD13,0) -> 0 | AH13: =AF13+AA13 -> 0 | AI13: =SUM(AH13+V13) -> 282 | AJ13: =-tanks!AW14 -> 282 | AK13: =SUM(AJ13-AI13) -> 0 | AL13: =S13+L13+G13 -> 3 | AM13: =Y13+AD13 -> 0 | AN13: 75 | AO13: =(AN13/100)*3000 -> 2250 | AP13: 77 | AQ13: =(AP13/100)*3000 -> 2310 | AR13: 65 | AS13: =(AR13/100)*3000 -> 1950 | AT13: =SUM(AO13+AQ13+AS13) -> 6510 | AU13: =AT12-AT13+AV13 -> 150 | AX13: =IF(AV13>0,AW13,AX12) -> 0.7
A14: =ELEC!C12 -> 43992 | B14: 177.2 | C14: 183.5 | D14: =C13-C14 -> 7.8 | E14: =D14*8.38 -> 65.364 | F14: 1596 | G14: =F14-F13 -> 0 | H14: 353837 | I14: =SUM(H14-H13) -> 0 | J14: =IF(G14>0,I14/G14,0) -> 0 | K14: 1983 | L14: =K14-K13 -> 6 | M14: 145331 | N14: =M14-M13 -> 378 | O14: =SUM(L14*$J$1) -> 438.61111 | P14: 1803 | Q14: 152974 | R14: =Q14-Q13 -> 0 | S14: =SUM(P14-P13) -> 0 | T14: =SUM(S14*$T$2) -> 0 | U14: =SUM(G14+L14+S14) -> 6 | V14: =R14+N14+I14:I14 -> 378 | W14: =SUM(V14/U14) -> 63 | X14: 2418 | Y14: =X14-X13 -> 0 | Z14: 135958 | AA14: =Z14-Z13 -> 0 | AB14: =SUM(Y14*$AB$2) -> 0 | AC14: 1848 | AD14: =AC14-AC13 -> 3 | AE14: 360299.4 | AF14: =AE14-AE13 -> 222.4 | AG14: =IF(AD14>0,AF14/AD14,0) -> 74.133333 | AH14: =AF14+AA14 -> 222.4 | AI14: =SUM(AH14+V14) -> 600.4 | AJ14: =-tanks!AW15 -> 600.4 | AK14: =SUM(AJ14-AI14) -> 0 | AL14: =S14+L14+G14 -> 6 | AM14: =Y14+AD14 -> 3 | AN14: 73 | AO14: =(AN14/100)*3000 -> 2190 | AP14: 75 | AQ14: =(AP14/100)*3000 -> 2250 | AR14: 64 | AS14: =(AR14/100)*3000 -> 1920 | AT14: =SUM(AO14+AQ14+AS14) -> 6360 | AU14: =AT13-AT14+AV14 -> 150 | AX14: =IF(AV14>0,AW14,AX13) -> 0.7
A15: =ELEC!C13 -> 43993 | B15: 169 | C15: 175 | D15: =C14-C15 -> 8.5 | E15: =D15*8.38 -> 71.23 | F15: 1596 | G15: =F15-F14 -> 0 | H15: 353837 | I15: =SUM(H15-H14) -> 0 | J15: =IF(G15>0,I15/G15,0) -> 0 | K15: 1987 | L15: =K15-K14 -> 4 | M15: 145693 | N15: =M15-M14 -> 362 | O15: =SUM(L15*$J$1) -> 292.40741 | P15: 1803 | Q15: 152974 | R15: =Q15-Q14 -> 0 | S15: =SUM(P15-P14) -> 0 | T15: =SUM(S15*$T$2) -> 0 | U15: =SUM(G15+L15+S15) -> 4 | V15: =R15+N15+I15:I15 -> 362 | W15: =SUM(V15/U15) -> 90.5 | X15: 2418 | Y15: =X15-X14 -> 0 | Z15: 135964.1 | AA15: =Z15-Z14 -> 6.1 | AB15: =SUM(Y15*$AB$2) -> 0 | AC15: 1848 | AD15: =AC15-AC14 -> 0 | AE15: =AE14 -> 360299.4 | AF15: =AE15-AE14 -> 0 | AG15: =IF(AD15>0,AF15/AD15,0) -> 0 | AH15: =AF15+AA15 -> 6.1 | AI15: =SUM(AH15+V15) -> 368.1 | AJ15: =-tanks!AW16 -> 368.1 | AK15: =SUM(AJ15-AI15) -> 0 | AL15: =S15+L15+G15 -> 4 | AM15: =Y15+AD15 -> 0 | AN15: 72 | AO15: =(AN15/100)*3000 -> 2160 | AP15: 73 | AQ15: =(AP15/100)*3000 -> 2190 | AR15: 61 | AS15: =(AR15/100)*3000 -> 1830 | AT15: =SUM(AO15+AQ15+AS15) -> 6180 | AU15: =AT14-AT15+AV15 -> 180 | AX15: =IF(AV15>0,AW15,AX14) -> 0.7
A16: =ELEC!C14 -> 43994 | B16: 161.5 | C16: 168 | D16: =C15-C16 -> 7 | E16: =D16*8.38 -> 58.66 | F16: =F15 -> 1596 | G16: =F16-F15 -> 0 | H16: =H15 -> 353837 | I16: =SUM(H16-H15) -> 0 | J16: =IF(G16>0,I16/G16,0) -> 0 | K16: 1992 | L16: =K16-K15 -> 5 | M16: 146059 | N16: =M16-M15 -> 366 | O16: =SUM(L16*$J$1) -> 365.50926 | P16: 1803 | Q16: 152974 | R16: =Q16-Q15 -> 0 | S16: =SUM(P16-P15) -> 0 | T16: =SUM(S16*$T$2) -> 0 | U16: =SUM(G16+L16+S16) -> 5 | V16: =R16+N16+I16:I16 -> 366 | W16: =SUM(V16/U16) -> 73.2 | X16: 2418 | Y16: =X16-X15 -> 0 | Z16: 135964.1 | AA16: =Z16-Z15 -> 0 | AB16: =SUM(Y16*$AB$2) -> 0 | AC16: 1848 | AD16: =AC16-AC15 -> 0 | AE16: =AE15 -> 360299.4 | AF16: =AE16-AE15 -> 0 | AG16: =IF(AD16>0,AF16/AD16,0) -> 0 | AH16: =AF16+AA16 -> 0 | AI16: =SUM(AH16+V16) -> 366 | AJ16: =-tanks!AW17 -> 366 | AK16: =SUM(AJ16-AI16) -> 0 | AL16: =S16+L16+G16 -> 5 | AM16: =Y16+AD16 -> 0 | AN16: 70 | AO16: =(AN16/100)*3000 -> 2100 | AP16: 72 | AQ16: =(AP16/100)*3000 -> 2160 | AR16: 61 | AS16: =(AR16/100)*3000 -> 1830 | AT16: =SUM(AO16+AQ16+AS16) -> 6090 | AU16: =AT15-AT16+AV16 -> 90 | AX16: =IF(AV16>0,AW16,AX15) -> 0.7
A17: =ELEC!C15 -> 43995 | B17: 155 | C17: 161 | D17: =C16-C17 -> 7 | E17: =D17*8.38 -> 58.66 | F17: =F16 -> 1596 | G17: =F17-F16 -> 0 | H17: =H16 -> 353837 | I17: =SUM(H17-H16) -> 0 | J17: =IF(G17>0,I17/G17,0) -> 0 | K17: 1996 | L17: =K17-K16 -> 4 | M17: 146378 | N17: =M17-M16 -> 319 | O17: =SUM(L17*$J$1) -> 292.40741 | P17: =P16 -> 1803 | Q17: =Q16 -> 152974 | R17: =Q17-Q16 -> 0 | S17: =SUM(P17-P16) -> 0 | T17: =SUM(S17*$T$2) -> 0 | U17: =SUM(G17+L17+S17) -> 4 | V17: =R17+N17+I17:I17 -> 319 | X17: =X16 -> 2418 | Y17: =X17-X16 -> 0 | Z17: =Z16 -> 135964.1 | AA17: =Z17-Z16 -> 0 | AB17: =SUM(Y17*$AB$2) -> 0 | AC17: =AC16 -> 1848 | AD17: =AC17-AC16 -> 0 | AE17: =AE16 -> 360299.4 | AF17: =AE17-AE16 -> 0 | AG17: =IF(AD17>0,AF17/AD17,0) -> 0 | AH17: =AF17+AA17 -> 0 | AI17: =SUM(AH17+V17) -> 319 | AJ17: =-tanks!AW18 -> 319 | AK17: =SUM(AJ17-AI17) -> 0 | AL17: =S17+L17+G17 -> 4 | AM17: =Y17+AD17 -> 0 | AN17: 68 | AO17: =(AN17/100)*3000 -> 2040 | AP17: 71 | AQ17: =(AP17/100)*3000 -> 2130 | AR17: 60 | AS17: =(AR17/100)*3000 -> 1800 | AT17: =SUM(AO17+AQ17+AS17) -> 5970 | AU17: =AT16-AT17+AV17 -> 120 | AX17: =IF(AV17>0,AW17,AX16) -> 0.7
A18: =ELEC!C16 -> 43996 | B18: 150 | C18: 156 | D18: =C17-C18 -> 5 | E18: =D18*8.38 -> 41.9 | F18: =F17 -> 1596 | G18: =F18-F17 -> 0 | H18: =H17 -> 353837 | I18: =SUM(H18-H17) -> 0 | J18: =IF(G18>0,I18/G18,0) -> 0 | K18: 2000 | L18: =K18-K17 -> 4 | M18: 146680 | N18: =M18-M17 -> 302 | O18: =SUM(L18*$J$1) -> 292.40741 | P18: =P17 -> 1803 | Q18: =Q17 -> 152974 | R18: =Q18-Q17 -> 0 | S18: =SUM(P18-P17) -> 0 | T18: =SUM(S18*$T$2) -> 0 | U18: =SUM(G18+L18+S18) -> 4 | V18: =R18+N18+I18:I18 -> 302 | X18: =X17 -> 2418 | Y18: =X18-X17 -> 0 | Z18: =Z17 -> 135964.1 | AA18: =Z18-Z17 -> 0 | AB18: =SUM(Y18*$AB$2) -> 0 | AC18: =AC17 -> 1848 | AD18: =AC18-AC17 -> 0 | AE18: =AE17 -> 360299.4 | AF18: =AE18-AE17 -> 0 | AG18: =IF(AD18>0,AF18/AD18,0) -> 0 | AH18: =AF18+AA18 -> 0 | AI18: =SUM(AH18+V18) -> 302 | AJ18: =-tanks!AW19 -> 302 | AK18: =SUM(AJ18-AI18) -> 0 | AL18: =S18+L18+G18 -> 4 | AM18: =Y18+AD18 -> 0 | AN18: =AN17 -> 68 | AO18: =(AN18/100)*3000 -> 2040 | AP18: 68 | AQ18: =(AP18/100)*3000 -> 2040 | AR18: =AR17 -> 60 | AS18: =(AR18/100)*3000 -> 1800 | AT18: =SUM(AO18+AQ18+AS18) -> 5880 | AU18: =AT17-AT18+AV18 -> 90 | AX18: =IF(AV18>0,AW18,AX17) -> 0.7
A19: =ELEC!C17 -> 43997 | B19: 172 | C19: 178 | D19: =C18-C19 -> -22 | E19: =D19*8.38 -> -184.36 | F19: 1596 | G19: =F19-F18 -> 0 | H19: =H18 -> 353837 | I19: =SUM(H19-H18) -> 0 | J19: =IF(G19>0,I19/G19,0) -> 0 | K19: 2005 | L19: =K19-K18 -> 5 | M19: 147032 | N19: =M19-M18 -> 352 | O19: =SUM(L19*$J$1) -> 365.50926 | P19: =P18 -> 1803 | Q19: =Q18 -> 152974 | R19: =Q19-Q18 -> 0 | S19: =SUM(P19-P18) -> 0 | T19: =SUM(S19*$T$2) -> 0 | U19: =SUM(G19+L19+S19) -> 5 | V19: =R19+N19+I19:I19 -> 352 | X19: =X18 -> 2418 | Y19: =X19-X18 -> 0 | Z19: =Z18 -> 135964.1 | AA19: =Z19-Z18 -> 0 | AB19: =SUM(Y19*$AB$2) -> 0 | AC19: =AC18 -> 1848 | AD19: =AC19-AC18 -> 0 | AE19: =AE18 -> 360299.4 | AF19: =AE19-AE18 -> 0 | AG19: =IF(AD19>0,AF19/AD19,0) -> 0 | AH19: =AF19+AA19 -> 0 | AI19: =SUM(AH19+V19) -> 352 | AJ19: =-tanks!AW20 -> 352 | AK19: =SUM(AJ19-AI19) -> 0 | AL19: =S19+L20+G19 -> 5 | AM19: =Y19+AD19 -> 0 | AN19: 67 | AO19: =(AN19/100)*3000 -> 2010 | AP19: 67 | AQ19: =(AP19/100)*3000 -> 2010 | AR19: 58 | AS19: =(AR19/100)*3000 -> 1740 | AT19: =SUM(AO19+AQ19+AS19) -> 5760 | AU19: =AT18-AT19+AV19 -> 120 | AX19: =IF(AV19>0,AW19,AX18) -> 0.7
A20: =ELEC!C18 -> 43998 | B20: 166 | C20: 172 | D20: =C19-C20 -> 6 | E20: =D20*8.38 -> 50.28 | F20: =F19 -> 1596 | G20: =F20-F19 -> 0 | H20: 353837 | I20: =SUM(H20-H19) -> 0 | J20: =IF(G20>0,I20/G20,0) -> 0 | K20: 2010 | L20: =K20-K19 -> 5 | M20: 147378 | N20: =M20-M19 -> 346 | O20: =SUM(L20*$J$1) -> 365.50926 | P20: =P19 -> 1803 | Q20: =Q19 -> 152974 | R20: =Q20-Q19 -> 0 | S20: =SUM(P20-P19) -> 0 | T20: =SUM(S20*$T$2) -> 0 | U20: =SUM(G20+L20+S20) -> 5 | V20: =R20+N20+I20:I20 -> 346 | X20: =X19 -> 2418 | Y20: =X20-X19 -> 0 | Z20: =Z19 -> 135964.1 | AA20: =Z20-Z19 -> 0 | AB20: =SUM(Y20*$AB$2) -> 0 | AC20: =AC19 -> 1848 | AD20: =AC20-AC19 -> 0 | AE20: =AE19 -> 360299.4 | AF20: =AE20-AE19 -> 0 | AG20: =IF(AD20>0,AF20/AD20,0) -> 0 | AH20: =AF20+AA20 -> 0 | AI20: =SUM(AH20+V20) -> 346 | AJ20: =-tanks!AW21 -> 346 | AK20: =SUM(AJ20-AI20) -> 0 | AL20: =S20+L21+G20 -> 4 | AM20: =Y20+AD20 -> 0 | AN20: 66 | AO20: =(AN20/100)*3000 -> 1980 | AP20: 66 | AQ20: =(AP20/100)*3000 -> 1980 | AR20: 57 | AS20: =(AR20/100)*3000 -> 1710 | AT20: =SUM(AO20+AQ20+AS20) -> 5670 | AU20: =AT19-AT20+AV20 -> 90 | AX20: =IF(AV20>0,AW20,AX19) -> 0.7
A21: =ELEC!C19 -> 43999 | B21: 192 | C21: 198 | D21: =C20-C21 -> -26 | E21: =D21*8.38 -> -217.88 | F21: =F20 -> 1596 | G21: =F21-F20 -> 0 | H21: =H20 -> 353837 | I21: =SUM(H21-H20) -> 0 | J21: =IF(G21>0,I21/G21,0) -> 0 | K21: 2014 | L21: =K21-K20 -> 4 | M21: 147690 | N21: =M21-M20 -> 312 | O21: =SUM(L21*$J$1) -> 292.40741 | P21: =P20 -> 1803 | Q21: =Q20 -> 152974 | R21: =Q21-Q20 -> 0 | S21: =SUM(P21-P20) -> 0 | T21: =SUM(S21*$T$2) -> 0 | U21: =SUM(G21+L21+S21) -> 4 | V21: =R21+N21+I21:I21 -> 312 | X21: =X20 -> 2418 | Y21: =X21-X20 -> 0 | Z21: =Z20 -> 135964.1 | AA21: =Z21-Z20 -> 0 | AB21: =SUM(Y21*$AB$2) -> 0 | AC21: =AC20 -> 1848 | AD21: =AC21-AC20 -> 0 | AE21: =AE20 -> 360299.4 | AF21: =AE21-AE20 -> 0 | AG21: =IF(AD21>0,AF21/AD21,0) -> 0 | AH21: =AF21+AA21 -> 0 | AI21: =SUM(AH21+V21) -> 312 | AJ21: =-tanks!AW22 -> 312 | AK21: =SUM(AJ21-AI21) -> 0 | AL21: =S21+L21+G21 -> 4 | AM21: =Y21+AD21 -> 0 | AN21: =AN20 -> 66 | AO21: =(AN21/100)*3000 -> 1980 | AP21: =AP20 -> 66 | AQ21: =(AP21/100)*3000 -> 1980 | AR21: 54 | AS21: =(AR21/100)*3000 -> 1620 | AT21: =SUM(AO21+AQ21+AS21) -> 5580 | AU21: =AT20-AT21+AV21 -> 90 | AX21: =IF(AV21>0,AW21,AX20) -> 0.7
A22: =ELEC!C20 -> 44000 | B22: 183 | C22: 189 | D22: =C21-C22 -> 9 | E22: =D22*8.38 -> 75.42 | F22: 1596 | G22: =F22-F21 -> 0 | H22: 353837 | I22: =SUM(H22-H21) -> 0 | J22: =IF(G22>0,I22/G22,0) -> 0 | K22: 2019 | L22: =K22-K21 -> 5 | M22: 148041 | N22: =M22-M21 -> 351 | O22: =SUM(L22*$J$1) -> 365.50926 | P22: 1803 | Q22: 152974 | R22: =Q22-Q21 -> 0 | S22: =SUM(P22-P21) -> 0 | T22: =SUM(S22*$T$2) -> 0 | U22: =SUM(G22+L22+S22) -> 5 | V22: =R22+N22+I22:I22 -> 351 | X22: 2418 | Y22: =X22-X21 -> 0 | Z22: 135964.1 | AA22: =Z22-Z21 -> 0 | AB22: =SUM(Y22*$AB$2) -> 0 | AC22: 1852 | AD22: =AC22-AC21 -> 4 | AE22: 360537 | AF22: =AE22-AE21 -> 237.6 | AG22: =IF(AD22>0,AF22/AD22,0) -> 59.4 | AH22: =AF22+AA22 -> 237.6 | AI22: =SUM(AH22+V22) -> 588.6 | AJ22: =-tanks!AW23 -> 588.6 | AK22: =SUM(AJ22-AI22) -> 0 | AL22: =S22+L22+G22 -> 5 | AM22: =Y22+AD22 -> 4 | AN22: 80 | AO22: =(AN22/100)*3000 -> 2400 | AP22: 80 | AQ22: =(AP22/100)*3000 -> 2400 | AR22: 79 | AS22: =(AR22/100)*3000 -> 2370 | AT22: =SUM(AO22+AQ22+AS22) -> 7170 | AU22: =AT21-AT22+AV22 -> 510 | AV22: 2100 | AW22: 0.7 | AX22: =IF(AV22>0,AW22,AX21) -> 0.7
A23: =ELEC!C21 -> 44001 | B23: 177 | C23: 182.1 | D23: =C22-C23 -> 6.9 | E23: =D23*8.38 -> 57.822 | F23: 1596 | G23: =F23-F22 -> 0 | H23: =H22 -> 353837 | I23: =SUM(H23-H22) -> 0 | J23: =IF(G23>0,I23/G23,0) -> 0 | K23: 2025 | L23: =K23-K22 -> 6 | M23: 148523 | N23: =M23-M22 -> 482 | O23: =SUM(L23*$J$1) -> 438.61111 | P23: =P22 -> 1803 | Q23: =Q22 -> 152974 | R23: =Q23-Q22 -> 0 | S23: =SUM(P23-P22) -> 0 | T23: =SUM(S23*$T$2) -> 0 | U23: =SUM(G23+L23+S23) -> 6 | V23: =R23+N23+I23:I23 -> 482 | X23: =X22 -> 2418 | Y23: =X23-X22 -> 0 | Z23: =Z22 -> 135964.1 | AA23: =Z23-Z22 -> 0 | AB23: =SUM(Y23*$AB$2) -> 0 | AC23: =AC22 -> 1852 | AD23: =AC23-AC22 -> 0 | AE23: =AE22 -> 360537 | AF23: =AE23-AE22 -> 0 | AG23: =IF(AD23>0,AF23/AD23,0) -> 0 | AH23: =AF23+AA23 -> 0 | AI23: =SUM(AH23+V23) -> 482 | AJ23: =-tanks!AW24 -> 482 | AK23: =SUM(AJ23-AI23) -> 0 | AL23: =S23+L23+G23 -> 6 | AM23: =Y23+AD23 -> 0 | AN23: 78 | AO23: =(AN23/100)*3000 -> 2340 | AP23: 78 | AQ23: =(AP23/100)*3000 -> 2340 | AR23: 78 | AS23: =(AR23/100)*3000 -> 2340 | AT23: =SUM(AO23+AQ23+AS23) -> 7020 | AU23: =AT22-AT23+AV23 -> 150 | AX23: =IF(AV23>0,AW23,AX22) -> 0.7
A24: =ELEC!C22 -> 44002 | B24: 173 | C24: 179 | D24: =C23-C24 -> 3.1 | E24: =D24*8.38 -> 25.978 | F24: =F23 -> 1596 | G24: =F24-F23 -> 0 | H24: =H23 -> 353837 | I24: =SUM(H24-H23) -> 0 | J24: =IF(G24>0,I24/G24,0) -> 0 | K24: 2029 | L24: =K24-K23 -> 4 | M24: 148802 | N24: =M24-M23 -> 279 | O24: =SUM(L24*$J$1) -> 292.40741 | P24: =P23 -> 1803 | Q24: =Q23 -> 152974 | R24: =Q24-Q23 -> 0 | S24: =SUM(P24-P23) -> 0 | T24: =SUM(S24*$T$2) -> 0 | U24: =SUM(G24+L24+S24) -> 4 | V24: =R24+N24+I24:I24 -> 279 | X24: =X23 -> 2418 | Y24: =X24-X23 -> 0 | Z24: =Z23 -> 135964.1 | AA24: =Z24-Z23 -> 0 | AB24: =SUM(Y24*$AB$2) -> 0 | AC24: =AC23 -> 1852 | AD24: =AC24-AC23 -> 0 | AE24: =AE23 -> 360537 | AF24: =AE24-AE23 -> 0 | AG24: =IF(AD24>0,AF24/AD24,0) -> 0 | AH24: =AF24+AA24 -> 0 | AI24: =SUM(AH24+V24) -> 279 | AJ24: =-tanks!AW25 -> 279 | AK24: =SUM(AJ24-AI24) -> 0 | AL24: =S24+L24+G24 -> 4 | AM24: =Y24+AD24 -> 0 | AN24: 76 | AO24: =(AN24/100)*3000 -> 2280 | AP24: 78 | AQ24: =(AP24/100)*3000 -> 2340 | AR24: =AR23 -> 78 | AS24: =(AR24/100)*3000 -> 2340 | AT24: =SUM(AO24+AQ24+AS24) -> 6960 | AU24: =AT23-AT24+AV24 -> 60 | AX24: =IF(AV24>0,AW24,AX23) -> 0.7
A25: =ELEC!C23 -> 44003 | B25: 169 | C25: 175.2 | D25: =C24-C25 -> 3.8 | E25: =D25*8.38 -> 31.844 | F25: 1596 | G25: =F25-F24 -> 0 | H25: 353837 | I25: =SUM(H25-H24) -> 0 | J25: =IF(G25>0,I25/G25,0) -> 0 | K25: 2034 | L25: =K25-K24 -> 5 | M25: 149184 | N25: =M25-M24 -> 382 | O25: =SUM(L25*$J$1) -> 365.50926 | P25: 1803 | Q25: 152974 | R25: =Q25-Q24 -> 0 | S25: =SUM(P25-P24) -> 0 | T25: =SUM(S25*$T$2) -> 0 | U25: =SUM(G25+L25+S25) -> 5 | V25: =R25+N25+I25:I25 -> 382 | X25: 2418 | Y25: =X25-X24 -> 0 | Z25: 135964.1 | AA25: =Z25-Z24 -> 0 | AB25: =SUM(Y25*$AB$2) -> 0 | AC25: 1852 | AD25: =AC25-AC24 -> 0 | AE25: 360537 | AF25: =AE25-AE24 -> 0 | AG25: =IF(AD25>0,AF25/AD25,0) -> 0 | AH25: =AF25+AA25 -> 0 | AI25: =SUM(AH25+V25) -> 382 | AJ25: =-tanks!AW26 -> 382 | AK25: =SUM(AJ25-AI25) -> 0 | AL25: =S25+L25+G25 -> 5 | AM25: =Y25+AD25 -> 0 | AN25: 75 | AO25: =(AN25/100)*3000 -> 2250 | AP25: 77 | AQ25: =(AP25/100)*3000 -> 2310 | AR25: 77 | AS25: =(AR25/100)*3000 -> 2310 | AT25: =SUM(AO25+AQ25+AS25) -> 6870 | AU25: =AT24-AT25+AV25 -> 90 | AX25: =IF(AV25>0,AW25,AX24) -> 0.7
A26: =ELEC!C24 -> 44004 | B26: 162.5 | C26: 169 | D26: =C25-C26 -> 6.2 | E26: =D26*8.38 -> 51.956 | F26: 1596 | G26: =F26-F25 -> 0 | H26: 353837 | I26: =SUM(H26-H25) -> 0 | J26: =IF(G26>0,I26/G26,0) -> 0 | K26: 2040 | L26: =K26-K25 -> 6 | M26: 149633 | N26: =M26-M25 -> 449 | O26: =SUM(L26*$J$1) -> 438.61111 | P26: 1803 | Q26: 152974 | R26: =Q26-Q25 -> 0 | S26: =SUM(P26-P25) -> 0 | T26: =SUM(S26*$T$2) -> 0 | U26: =SUM(G26+L26+S26) -> 6 | V26: =R26+N26+I26:I26 -> 449 | X26: 2418 | Y26: =X26-X25 -> 0 | Z26: 135964.1 | AA26: =Z26-Z25 -> 0 | AB26: =SUM(Y26*$AB$2) -> 0 | AC26: 1852 | AD26: =AC26-AC25 -> 0 | AE26: 360537 | AF26: =AE26-AE25 -> 0 | AG26: =IF(AD26>0,AF26/AD26,0) -> 0 | AH26: =AF26+AA26 -> 0 | AI26: =SUM(AH26+V26) -> 449 | AJ26: =-tanks!AW27 -> 449 | AK26: =SUM(AJ26-AI26) -> 0 | AL26: =S26+L26+G26 -> 6 | AM26: =Y26+AD26 -> 0 | AN26: 79 | AO26: =(AN26/100)*3000 -> 2370 | AP26: 77 | AQ26: =(AP26/100)*3000 -> 2310 | AR26: 75 | AS26: =(AR26/100)*3000 -> 2250 | AT26: =SUM(AO26+AQ26+AS26) -> 6930 | AU26: =AT25-AT26+AV26 -> -60 | AX26: =IF(AV26>0,AW26,AX25) -> 0.7
A27: =ELEC!C25 -> 44005 | B27: 157 | C27: 164 | D27: =C26-C27 -> 5 | E27: =D27*8.38 -> 41.9 | F27: =F26 -> 1596 | G27: =F27-F26 -> 0 | H27: =H26 -> 353837 | I27: =SUM(H27-H26) -> 0 | J27: =IF(G27>0,I27/G27,0) -> 0 | K27: 2044 | L27: =K27-K26 -> 4 | M27: 149951 | N27: =M27-M26 -> 318 | O27: =SUM(L27*$J$1) -> 292.40741 | P27: =P26 -> 1803 | Q27: =Q26 -> 152974 | R27: =Q27-Q26 -> 0 | S27: =SUM(P27-P26) -> 0 | T27: =SUM(S27*$T$2) -> 0 | U27: =SUM(G27+L27+S27) -> 4 | V27: =R27+N27+I27:I27 -> 318 | X27: =X26 -> 2418 | Y27: =X27-X26 -> 0 | Z27: =Z26 -> 135964.1 | AA27: =Z27-Z26 -> 0 | AB27: =SUM(Y27*$AB$2) -> 0 | AC27: =AC26 -> 1852 | AD27: =AC27-AC26 -> 0 | AE27: =AE26 -> 360537 | AF27: =AE27-AE26 -> 0 | AG27: =IF(AD27>0,AF27/AD27,0) -> 0 | AH27: =AF27+AA27 -> 0 | AI27: =SUM(AH27+V27) -> 318 | AJ27: =-tanks!AW28 -> 318 | AK27: =SUM(AJ27-AI27) -> 0 | AL27: =S27+L27+G27 -> 4 | AM27: =Y27+AD27 -> 0 | AN27: 77 | AO27: =(AN27/100)*3000 -> 2310 | AP27: 76 | AQ27: =(AP27/100)*3000 -> 2280 | AR27: =AR26 -> 75 | AS27: =(AR27/100)*3000 -> 2250 | AT27: =SUM(AO27+AQ27+AS27) -> 6840 | AU27: =AT26-AT27+AV27 -> 90 | AX27: =IF(AV27>0,AW27,AX26) -> 0.7
A28: =ELEC!C26 -> 44006 | B28: 150.2 | C28: 157 | D28: =C27-C28 -> 7 | E28: =D28*8.38 -> 58.66 | F28: 1596 | G28: =F28-F27 -> 0 | H28: 353850 | I28: =SUM(H28-H27) -> 13 | J28: =IF(G28>0,I28/G28,0) -> 0 | K28: 2050 | L28: =K28-K27 -> 6 | M28: 150372 | N28: =M28-M27 -> 421 | O28: =SUM(L28*$J$1) -> 438.61111 | P28: 1803 | Q28: 152974 | R28: =Q28-Q27 -> 0 | S28: =SUM(P28-P27) -> 0 | T28: =SUM(S28*$T$2) -> 0 | U28: =SUM(G28+L28+S28) -> 6 | V28: =R28+N28+I28:I28 -> 434 | X28: 2418 | Y28: =X28-X27 -> 0 | Z28: 135964.1 | AA28: =Z28-Z27 -> 0 | AB28: =SUM(Y28*$AB$2) -> 0 | AC28: 1852 | AD28: =AC28-AC27 -> 0 | AE28: 360537 | AF28: =AE28-AE27 -> 0 | AG28: =IF(AD28>0,AF28/AD28,0) -> 0 | AH28: =AF28+AA28 -> 0 | AI28: =SUM(AH28+V28) -> 434 | AJ28: =-tanks!AW29 -> 434 | AK28: =SUM(AJ28-AI28) -> 0 | AL28: =S28+L28+G28 -> 6 | AM28: =Y28+AD28 -> 0 | AN28: 75 | AO28: =(AN28/100)*3000 -> 2250 | AP28: 76 | AQ28: =(AP28/100)*3000 -> 2280 | AR28: 74 | AS28: =(AR28/100)*3000 -> 2220 | AT28: =SUM(AO28+AQ28+AS28) -> 6750 | AU28: =AT27-AT28+AV28 -> 90 | AX28: =IF(AV28>0,AW28,AX27) -> 0.7
A29: =ELEC!C27 -> 44007 | B29: 186 | C29: 191 | D29: =C28-C29 -> -34 | E29: =D29*8.38 -> -284.92 | F29: =F28 -> 1596 | G29: =F29-F28 -> 0 | H29: =H28 -> 353850 | I29: =SUM(H29-H28) -> 0 | J29: =IF(G29>0,I29/G29,0) -> 0 | K29: 2054 | L29: =K29-K28 -> 4 | M29: 150694 | N29: =M29-M28 -> 322 | O29: =SUM(L29*$J$1) -> 292.40741 | P29: =P28 -> 1803 | Q29: =Q28 -> 152974 | R29: =Q29-Q28 -> 0 | S29: =SUM(P29-P28) -> 0 | T29: =SUM(S29*$T$2) -> 0 | U29: =SUM(G29+L29+S29) -> 4 | V29: =R29+N29+I29:I29 -> 322 | X29: =X28 -> 2418 | Y29: =X29-X28 -> 0 | Z29: =Z28 -> 135964.1 | AA29: =Z29-Z28 -> 0 | AB29: =SUM(Y29*$AB$2) -> 0 | AC29: 1857 | AD29: =AC29-AC28 -> 5 | AE29: 360818 | AF29: =AE29-AE28 -> 281 | AG29: =IF(AD29>0,AF29/AD29,0) -> 56.2 | AH29: =AF29+AA29 -> 281 | AI29: =SUM(AH29+V29) -> 603 | AJ29: =-tanks!AW30 -> 603 | AK29: =SUM(AJ29-AI29) -> 0 | AL29: =S29+L29+G29 -> 4 | AM29: =Y29+AD29 -> 5 | AN29: 79 | AO29: =(AN29/100)*3000 -> 2370 | AP29: 82 | AQ29: =(AP29/100)*3000 -> 2460 | AR29: 83 | AS29: =(AR29/100)*3000 -> 2490 | AT29: =SUM(AO29+AQ29+AS29) -> 7320 | AU29: =AT28-AT29+AV29 -> 530 | AV29: 1100 | AW29: 0.7 | AX29: =IF(AV29>0,AW29,AX28) -> 0.7
A30: =ELEC!C28 -> 44008 | B30: 176 | C30: 185 | D30: =C29-C30 -> 6 | E30: =D30*8.38 -> 50.28 | F30: 1598 | G30: =F30-F29 -> 2 | H30: 353983 | I30: =SUM(H30-H29) -> 133 | J30: =IF(G30>0,I30/G30,0) -> 66.5 | K30: =K29 -> 2054 | L30: =K30-K29 -> 0 | M30: =M29 -> 150694 | N30: =M30-M29 -> 0 | O30: =SUM(L30*$J$1) -> 0 | P30: 1806 | Q30: 153182 | R30: =Q30-Q29 -> 208 | S30: =SUM(P30-P29) -> 3 | T30: =SUM(S30*$T$2) -> 0 | U30: =SUM(G30+L30+S30) -> 5 | V30: =R30+N30+I30:I30 -> 341 | X30: =X29 -> 2418 | Y30: =X30-X29 -> 0 | Z30: =Z29 -> 135964.1 | AA30: =Z30-Z29 -> 0 | AB30: =SUM(Y30*$AB$2) -> 0 | AC30: =AC29 -> 1857 | AD30: =AC30-AC29 -> 0 | AE30: =AE29 -> 360818 | AF30: =AE30-AE29 -> 0 | AG30: =IF(AD30>0,AF30/AD30,0) -> 0 | AH30: =AF30+AA30 -> 0 | AI30: =SUM(AH30+V30) -> 341 | AJ30: =-tanks!AW31 -> 341 | AK30: =SUM(AJ30-AI30) -> 0 | AL30: =S30+L30+G30 -> 5 | AM30: =Y30+AD30 -> 0 | AN30: 78 | AO30: =(AN30/100)*3000 -> 2340 | AP30: 82 | AQ30: =(AP30/100)*3000 -> 2460 | AR30: 83 | AS30: =(AR30/100)*3000 -> 2490 | AT30: =SUM(AO30+AQ30+AS30) -> 7290 | AU30: =AT29-AT30+AV30 -> 30 | AX30: =IF(AV30>0,AW30,AX29) -> 0.7
A31: =ELEC!C29 -> 44009 | B31: 171.4 | C31: 177.2 | D31: =C30-C31 -> 7.8 | E31: =D31*8.38 -> 65.364 | F31: 1601 | G31: =F31-F30 -> 3 | H31: 354278 | I31: =SUM(H31-H30) -> 295 | J31: =IF(G31>0,I31/G31,0) -> 98.333333 | K31: 2055 | L31: =K31-K30 -> 1 | M31: 150771 | N31: =M31-M30 -> 77 | O31: =SUM(L31*$J$1) -> 73.101852 | P31: 1806 | Q31: =Q30 -> 153182 | R31: =Q31-Q30 -> 0 | S31: =SUM(P31-P30) -> 0 | T31: =SUM(S31*$T$2) -> 0 | U31: =SUM(G31+L31+S31) -> 4 | V31: =R31+N31+I31:I31 -> 372 | X31: =X30 -> 2418 | Y31: =X31-X30 -> 0 | Z31: =Z30 -> 135964.1 | AA31: =Z31-Z30 -> 0 | AB31: =SUM(Y31*$AB$2) -> 0 | AC31: =AC30 -> 1857 | AD31: =AC31-AC30 -> 0 | AE31: =AE30 -> 360818 | AF31: =AE31-AE30 -> 0 | AG31: =IF(AD31>0,AF31/AD31,0) -> 0 | AH31: =AF31+AA31 -> 0 | AI31: =SUM(AH31+V31) -> 372 | AJ31: =-tanks!AW32 -> 372 | AK31: =SUM(AJ31-AI31) -> 0 | AL31: =S31+L31+G31 -> 4 | AM31: =Y31+AD31 -> 0 | AN31: 77 | AO31: =(AN31/100)*3000 -> 2310 | AP31: 82 | AQ31: =(AP31/100)*3000 -> 2460 | AR31: 82 | AS31: =(AR31/100)*3000 -> 2460 | AT31: =SUM(AO31+AQ31+AS31) -> 7230 | AU31: =AT30-AT31+AV31 -> 60 | AX31: =IF(AV31>0,AW31,AX30) -> 0.7
A32: =ELEC!C30 -> 44010 | B32: 165 | C32: 170 | D32: =C31-C32 -> 7.2 | E32: =D32*8.38 -> 60.336 | F32: =F31 -> 1601 | G32: =F32-F31 -> 0 | H32: 354278 | I32: =SUM(H32-H31) -> 0 | J32: =IF(G32>0,I32/G32,0) -> 0 | K32: 2061 | L32: =K32-K31 -> 6 | M32: 151168 | N32: =M32-M31 -> 397 | O32: =SUM(L32*$J$1) -> 438.61111 | P32: =P31 -> 1806 | Q32: =Q31 -> 153182 | R32: =Q32-Q31 -> 0 | S32: =SUM(P32-P31) -> 0 | T32: =SUM(S32*$T$2) -> 0 | U32: =SUM(G32+L32+S32) -> 6 | V32: =R32+N32+I32:I32 -> 397 | X32: =X31 -> 2418 | Y32: =X32-X31 -> 0 | Z32: =Z31 -> 135964.1 | AA32: =Z32-Z31 -> 0 | AB32: =SUM(Y32*$AB$2) -> 0 | AC32: =AC31 -> 1857 | AD32: =AC32-AC31 -> 0 | AE32: =AE31 -> 360818 | AF32: =AE32-AE31 -> 0 | AG32: =IF(AD32>0,AF32/AD32,0) -> 0 | AH32: =AF32+AA32 -> 0 | AI32: =SUM(AH32+V32) -> 397 | AJ32: =-tanks!AW33 -> 397 | AK32: =SUM(AJ32-AI32) -> 0 | AL32: =S32+L32+G32 -> 6 | AM32: =Y32+AD32 -> 0 | AN32: 74 | AO32: =(AN32/100)*3000 -> 2220 | AP32: 79 | AQ32: =(AP32/100)*3000 -> 2370 | AR32: 78 | AS32: =(AR32/100)*3000 -> 2340 | AT32: =SUM(AO32+AQ32+AS32) -> 6930 | AU32: =AT31-AT32+AV32 -> 300 | AX32: =IF(AV32>0,AW32,AX31) -> 0.7
A33: =ELEC!C31 -> 44011 | B33: =B32 -> 165 | C33: =C32 -> 170 | D33: =C32-C33 -> 0 | E33: =D33*8.38 -> 0 | F33: =F32 -> 1601 | G33: =F33-F32 -> 0 | H33: =H32 -> 354278 | I33: =SUM(H33-H32) -> 0 | J33: =IF(G33>0,I33/G33,0) -> 0 | K33: =K32 -> 2061 | L33: =K33-K32 -> 0 | M33: =M32 -> 151168 | N33: =M33-M32 -> 0 | O33: =SUM(L33*$J$1) -> 0 | P33: =P32 -> 1806 | Q33: =Q32 -> 153182 | R33: =Q33-Q32 -> 0 | S33: =SUM(P33-P32) -> 0 | T33: =SUM(S33*$T$2) -> 0 | U33: =SUM(G33+L33+S33) -> 0 | V33: =R33+N33+I33:I33 -> 0 | X33: =X32 -> 2418 | Y33: =X33-X32 -> 0 | Z33: =Z32 -> 135964.1 | AA33: =Z33-Z32 -> 0 | AB33: =SUM(Y33*$AB$2) -> 0 | AC33: =AC32 -> 1857 | AD33: =AC33-AC32 -> 0 | AE33: =AE32 -> 360818 | AF33: =AE33-AE32 -> 0 | AG33: =IF(AD33>0,AF33/AD33,0) -> 0 | AH33: =AF33+AA33 -> 0 | AI33: =SUM(AH33+V33) -> 0 | AJ33: =-tanks!AW34 -> 0 | AK33: =SUM(AJ33-AI33) -> 0 | AL33: =S33+L33+G33 -> 0 | AM33: =Y33+AD33 -> 0 | AN33: =AN32 -> 74 | AO33: =(AN33/100)*3000 -> 2220 | AP33: =AP32 -> 79 | AQ33: =(AP33/100)*3000 -> 2370 | AR33: =AR32 -> 78 | AS33: =(AR33/100)*3000 -> 2340 | AT33: =SUM(AO33+AQ33+AS33) -> 6930 | AU33: =AT32-AT33+AV33 -> 0 | AX33: =IF(AV33>0,AW33,AX32) -> 0.7
A34: =ELEC!C32 -> 44012 | B34: =B33 -> 165 | C34: =C33 -> 170 | D34: =C33-C34 -> 0 | E34: =D34*8.38 -> 0 | F34: =F33 -> 1601 | G34: =F34-F33 -> 0 | H34: =H33 -> 354278 | I34: =SUM(H34-H33) -> 0 | J34: =IF(G34>0,I34/G34,0) -> 0 | K34: =K33 -> 2061 | L34: =K34-K33 -> 0 | M34: =M33 -> 151168 | N34: =M34-M33 -> 0 | O34: =SUM(L34*$J$1) -> 0 | P34: =P33 -> 1806 | Q34: =Q33 -> 153182 | R34: =Q34-Q33 -> 0 | S34: =SUM(P34-P33) -> 0 | T34: =SUM(S34*$T$2) -> 0 | U34: =SUM(G34+L34+S34) -> 0 | V34: =R34+N34+I34:I34 -> 0 | X34: =X33 -> 2418 | Y34: =X34-X33 -> 0 | Z34: =Z33 -> 135964.1 | AA34: =Z34-Z33 -> 0 | AB34: =SUM(Y34*$AB$2) -> 0 | AC34: =AC33 -> 1857 | AD34: =AC34-AC33 -> 0 | AE34: =AE33 -> 360818 | AF34: =AE34-AE33 -> 0 | AG34: =IF(AD34>0,AF34/AD34,0) -> 0 | AH34: =AF34+AA34 -> 0 | AI34: =SUM(AH34+V34) -> 0 | AJ34: =-tanks!AW35 -> 0 | AK34: =SUM(AJ34-AI34) -> 0 | AL34: =S34+L34+G34 -> 0 | AM34: =Y34+AD34 -> 0 | AN34: =AN33 -> 74 | AO34: =(AN34/100)*3000 -> 2220 | AP34: =AP33 -> 79 | AQ34: =(AP34/100)*3000 -> 2370 | AR34: =AR33 -> 78 | AS34: =(AR34/100)*3000 -> 2340 | AT34: =SUM(AO34+AQ34+AS34) -> 6930 | AU34: =AT33-AT34+AV34 -> 0 | AX34: =IF(AV34>0,AW34,AX33) -> 0.7
J35: =SUM(J5:J34)/(COUNT(J5:J34)-COUNTIF(J5:J34,0)) -> 73.101852 | AE35: . | AR35: Nb Delivery | AS35: =COUNT(AW5:AW34) -> 3 | AU35: =SUM(AU5:AU34) -> 3970 | AV35: =SUM(AV5:AV34) -> 4300 | AW35: =SUM(AW5:AW34)/AS35 -> 0.7
AH36: =AF36+AA36 -> 0 | AI36: =SUM(AI5:AI34) -> 11087.7
AH37: =AF37+AA37 -> 0 | AU37: =AU35*0.51 -> 2024.7 | AV37: =AV35/0.51 -> 8431.3725 | AW37: =SUM(AW5:AW34)/AS35 -> 0.7
AV38: =AV35*0.51 -> 2193

Sheet WATER
D1: =SUM(G21:G35) -> 9006835 | AR1: Entrance | AT1: Tank 1 | AV1: Tank 2
AR2: Level | AW2: Quantity CM3 | AZ2: Var
A3: Date | B3: Truck | C3: Truck M3/day | D3: N0. Trucks | F3: REQ. # of trucks | G3: City | H3: City/day | I3: Total water delivery | K3: SW | L3: Cosum SW/day | M3: RO Guest/ Liter | O3: RO K&L/ Liter | Q3: TOTAL RO Production | R3: RO 1 RH | S3: RO 2 RH | T3: RO water counter | U3: RO Cons m3 | V3: Steam Boiler | W3: Steam Boiler/day | X3: Softener Guest | Y3: Guest Sotf/day | Z3: Softener K&L | AA3: K&L Soft/Day | AB3: Fire Tank Level | AC3: Fire Tank Counter | AE3: Laundry Hot Water Counter | AF3: Hot Water Cons/day | AG3: Laundry Cold Water Counter | AH3: Cold Water Cons/day | AI3: Laundry Water Total Cons | AJ3: K&L Sotf/day | AK3: Guest / day | AL3: K&L /day | AM3: Avg Outside Temp | AN3: Banquet Activity | AR3: Date | AT3: MainI | AV3: Kitchen and Laundry | AX3: Guest | AY3: Main Tank | AZ3: Kitchen and Laundry | BA3: Guest | BB3: Kitchen and Laundry | BC3: Main | BD3: Guest | BE3: Total VAR | BF3: Hotel Consumption
E4: 1.66 | AN4: Ball R | AO4: Meeting | AP4: outlet | AT4: 180 | AV4: 220 | AX4: 580 | AY4: =SUM(AT4) -> 180 | AZ4: =SUM(AV4) -> 220 | BA4: =SUM(AX4) -> 580
A5: 43982 | B5: =[2]WATER!B36 -> 108473 | C5: =[2]WATER!C36 -> 0 | D5: =[2]WATER!D36 -> 0 | E5: =[2]WATER!E36 -> 241.93548 | F5: =[2]WATER!F36 -> 0 | G5: =[2]WATER!G36 -> 598974 | H5: =[2]WATER!H36 -> 325 | I5: =[2]WATER!I36 -> 325 | ... BG5: =[2]WATER!BG36 -> 116.4
A6: =ELEC!C3 -> 43983 | B6: =B5 -> 108473 | C6: =B6-B5 -> 0 | D6: =C6/27 -> 0 | E6: =SUM((C6*$E$4)+(7500/'EDl log'!$A$39)) -> 250 | G6: 598985 | H6: =G6-G5 -> 11 | I6: =C6+H6 -> 11 | J6: =IF(I6>0,E6/I6,0) -> 22.727273 | K6: ='Swimming Pool quality check '!H6 -> 6212 | L6: 0 | M6: =M5 -> 457.44 | N6: =SUM(M6-M5) -> 0 | O6: =O5 -> 529.52 | P6: =SUM(O6-O5) -> 0 | Q6: =P6+N6 -> 0 | T6: 4832 | U6: =SUM(T6-T5) -> 2 | V6: 408 | W6: =+V6-V5 -> 1 | X6: =X5 -> 143783 | Y6: =SUM(X6-X5) -> 0 | Z6: =Z5 -> 94798 | AA6: =Z6-Z5 -> 0 | AB6: 268 | AC6: =AC5 -> 671 | AD6: 0 | AE6: 155.8 | AF6: =AE6-AE5 -> 0.1 | AG6: 1594.6 | AH6: =AG6-AG5 -> 2.6 | AI6: =AF6+AH6 -> 2.7 | AJ6: =+Z6-Z5 -> 0 | AK6: =SUM(Y6-L6) -> 0 | AL6: =SUM(AJ6-W6) -> -1 | AM6: ='General information '!D6 -> 22.5 | AN6: ='General information '!H6 -> 0 | AP6: ='General information '!J6 -> 137 | AR6: =A6 -> 43983 | AS6: =AS5 -> 0.9 | AT6: =AT5 -> 155 | AU6: =AU5 -> 1.1 | AV6: 114 | AW6: 2.9 | AX6: 138 | AY6: =AS6*AT6 -> 139.5 | AZ6: =AU6*AV6 -> 125.4 | BA6: =AW6*AX6 -> 400.2 | BB6: =AY6-AY5 -> 0 | BC6: =AZ6-AZ5 -> -16.5 | BD6: =BA6-BA5 -> -8.7 | BE6: =SUM(BB6:BD6) -> -25.2 | BF6: =SUM(I6-BE6) -> 36.2 | BG6: =SUM(I6-BF6) -> -25.2
A7: =ELEC!C4 -> 43984 | B7: =B6 -> 108473 | C7: =B7-B6 -> 0 | D7: =C7/27 -> 0 | E7: =SUM((C7*$E$4)+(7500/'EDl log'!$A$39)) -> 250 | G7: =G6 -> 598985 | H7: =G7-G6 -> 0 | I7: =C7+H7 -> 0 | J7: =IF(I7>0,E7/I7,0) -> 0 | K7: ='Swimming Pool quality check '!H7 -> 6214 | L7: =K7-K6 -> 2 | M7: =M6 -> 457.44 | N7: =SUM(M7-M6) -> 0 | O7: =O6 -> 529.52 | P7: =SUM(O7-O6) -> 0 | Q7: =P7+N7 -> 0 | T7: 4834 | U7: =SUM(T7-T6) -> 2 | V7: 408 | W7: =+V7-V6 -> 0 | X7: =X6 -> 143783 | Y7: =SUM(X7-X6) -> 0 | Z7: =Z6 -> 94798 | AA7: =Z7-Z6 -> 0 | AB7: =AB6 -> 268 | AC7: =AC6 -> 671 | AD7: =AC7-AC6 -> 0 | AE7: =AE6 -> 155.8 | AF7: =AE7-AE6 -> 0 | AG7: 1594.6 | AH7: =AG7-AG6 -> 0 | AI7: =AF7+AH7 -> 0 | AJ7: =+Z7-Z6 -> 0 | AK7: =SUM(Y7-L7) -> -2 | AL7: =SUM(AJ7-W7) -> 0 | AM7: ='General information '!D7 -> 22 | AN7: ='General information '!H7 -> 0 | AP7: ='General information '!J7 -> 126 | AR7: =A7 -> 43984 | AS7: =AS6 -> 0.9 | AT7: 145 | AU7: =AU6 -> 1.1 | AV7: 130 | AW7: 2.9 | AX7: 120 | AY7: =AS7*AT7 -> 130.5 | AZ7: =AU7*AV7 -> 143 | BA7: =AW7*AX7 -> 348 | BB7: =AY7-AY6 -> -9 | BC7: =AZ7-AZ6 -> 17.6 | BD7: =BA7-BA6 -> -52.2 | BE7: =SUM(BB7:BD7) -> -43.6 | BF7: =SUM(I7-BE7) -> 43.6 | BG7: =SUM(I7-BF7) -> -43.6
A8: =ELEC!C5 -> 43985 | B8: 108473 | C8: =B8-B7 -> 0 | D8: =C8/27 -> 0 | E8: =SUM((C8*$E$4)+(7500/'EDl log'!$A$39)) -> 250 | G8: 598985 | H8: =G8-G7 -> 0 | I8: =C8+H8 -> 0 | J8: =IF(I8>0,E8/I8,0) -> 0 | K8: ='Swimming Pool quality check '!H8 -> 6218 | L8: =K8-K7 -> 4 | M8: =M7 -> 457.44 | N8: =SUM(M8-M7) -> 0 | O8: =O7 -> 529.52 | P8: =SUM(O8-O7) -> 0 | Q8: =P8+N8 -> 0 | T8: 4835 | U8: =SUM(T8-T7) -> 1 | V8: 408 | W8: =+V8-V7 -> 0 | X8: 143783 | Y8: =SUM(X8-X7) -> 0 | Z8: 94798 | AA8: =Z8-Z7 -> 0 | AB8: =AB7 -> 268 | AC8: =AC7 -> 671 | AD8: =AC8-AC7 -> 0 | AE8: 157.78 | AF8: =AE8-AE7 -> 1.98 | AG8: 1607.46 | AH8: =AG8-AG7 -> 12.86 | AI8: =AF8+AH8 -> 14.84 | AJ8: =+Z8-Z7 -> 0 | AK8: =SUM(Y8-L8) -> -4 | AL8: =SUM(AJ8-W8) -> 0 | AM8: ='General information '!D8 -> 23 | AN8: ='General information '!H8 -> 0 | AP8: ='General information '!J8 -> 172 | AR8: =A8 -> 43985 | AS8: =AS7 -> 0.9 | AT8: 145 | AU8: 1.1 | AV8: 125 | AW8: 2.9 | AX8: 100 | AY8: =AS8*AT8 -> 130.5 | AZ8: =AU8*AV8 -> 137.5 | BA8: =AW8*AX8 -> 290 | BB8: =AY8-AY7 -> 0 | BC8: =AZ8-AZ7 -> -5.5 | BD8: =BA8-BA7 -> -58 | BE8: =SUM(BB8:BD8) -> -63.5 | BF8: =SUM(I8-BE8) -> 63.5 | BG8: =SUM(I8-BF8) -> -63.5
A9: =ELEC!C6 -> 43986 | B9: =B8 -> 108473 | C9: =B9-B8 -> 0 | D9: =C9/27 -> 0 | E9: =SUM((C9*$E$4)+(7500/'EDl log'!$A$39)) -> 250 | G9: 599157 | H9: =G9-G8 -> 172 | I9: =C9+H9 -> 172 | J9: =IF(I9>0,E9/I9,0) -> 1.4534884 | K9: ='Swimming Pool quality check '!H9 -> 6218 | L9: =K9-K8 -> 0 | M9: =M8 -> 457.44 | N9: =SUM(M9-M8) -> 0 | O9: =O8 -> 529.52 | P9: =SUM(O9-O8) -> 0 | Q9: =P9+N9 -> 0 | T9: 4837 | U9: =SUM(T9-T8) -> 2 | V9: =V8 -> 408 | W9: =+V9-V8 -> 0 | X9: 143813 | Y9: =SUM(X9-X8) -> 30 | Z9: 94842 | AA9: =Z9-Z8 -> 44 | AB9: =AB8 -> 268 | AC9: =AC8 -> 671 | AD9: =AC9-AC8 -> 0 | AE9: 157.86 | AF9: =AE9-AE8 -> 0.08 | AG9: 1609.2 | AH9: =AG9-AG8 -> 1.74 | AI9: =AF9+AH9 -> 1.82 | AJ9: =+Z9-Z8 -> 44 | AK9: =SUM(Y9-L9) -> 30 | AL9: =SUM(AJ9-W9) -> 44 | AM9: ='General information '!D9 -> 22 | AN9: ='General information '!H9 -> 0 | AP9: ='General information '!J9 -> 182 | AR9: =A9 -> 43986 | AS9: =AS8 -> 0.9 | AT9: 175 | AU9: =AU8 -> 1.1 | AV9: 115 | AW9: 2.9 | AX9: 126 | AY9: =AS9*AT9 -> 157.5 | AZ9: =AU9*AV9 -> 126.5 | BA9: =AW9*AX9 -> 365.4 | BB9: =AY9-AY8 -> 27 | BC9: =AZ9-AZ8 -> -11 | BD9: =BA9-BA8 -> 75.4 | BE9: =SUM(BB9:BD9) -> 91.4 | BF9: =SUM(I9-BE9) -> 80.6 | BG9: =SUM(I9-BF9) -> 91.4
A10: =ELEC!C7 -> 43987 | B10: =B9 -> 108473 | C10: =B10-B9 -> 0 | D10: =C10/27 -> 0 | E10: =SUM((C10*$E$4)+(7500/'EDl log'!$A$39)) -> 250 | G10: =G9 -> 599157 | H10: =G10-G9 -> 0 | I10: =C10+H10 -> 0 | J10: =IF(I10>0,E10/I10,0) -> 0 | K10: ='Swimming Pool quality check '!H10 -> 6228 | L10: =K10-K9 -> 10 | M10: =M9 -> 457.44 | N10: =SUM(M10-M9) -> 0 | O10: =O9 -> 529.52 | P10: =SUM(O10-O9) -> 0 | Q10: =P10+N10 -> 0 | T10: 4839 | U10: =SUM(T10-T9) -> 2 | V10: =V9 -> 408 | W10: =+V10-V9 -> 0 | X10: 143813 | Y10: =SUM(X10-X9) -> 0 | Z10: 94875 | AA10: =Z10-Z9 -> 33 | AB10: =AB9 -> 268 | AC10: =AC9 -> 671 | AD10: =AC10-AC9 -> 0 | AE10: =AE9 -> 157.86 | AF10: =AE10-AE9 -> 0 | AG10: 1612.2 | AH10: =AG10-AG9 -> 3 | AI10: =AF10+AH10 -> 3 | AJ10: =+Z10-Z9 -> 33 | AK10: =SUM(Y10-L10) -> -10 | AL10: =SUM(AJ10-W10) -> 33 | AM10: ='General information '!D10 -> 21 | AN10: ='General information '!H10 -> 0 | AP10: ='General information '!J10 -> 292 | AR10: =A10 -> 43987 | AS10: =AS9 -> 0.9 | AT10: 146 | AU10: =AU9 -> 1.1 | AV10: 122 | AW10: 2.9 | AX10: 119 | AY10: =AS10*AT10 -> 131.4 | AZ10: =AU10*AV10 -> 134.2 | BA10: =AW10*AX10 -> 345.1 | BB10: =AY10-AY9 -> -26.1 | BC10: =AZ10-AZ9 -> 7.7 | BD10: =BA10-BA9 -> -20.3 | BE10: =SUM(BB10:BD10) -> -38.7 | BF10: =SUM(I10-BE10) -> 38.7 | BG10: =SUM(I10-BF10) -> -38.7
A11: =ELEC!C8 -> 43988 | B11: =B10 -> 108473 | C11: =B11-B10 -> 0 | D11: =C11/27 -> 0 | E11: =SUM((C11*$E$4)+(7500/'EDl log'!$A$39)) -> 250 | G11: =G10 -> 599157 | H11: =G11-G10 -> 0 | I11: =C11+H11 -> 0 | J11: =IF(I11>0,E11/I11,0) -> 0 | K11: ='Swimming Pool quality check '!H11 -> 6232 | L11: =K11-K10 -> 4 | M11: =M10 -> 457.44 | N11: =SUM(M11-M10) -> 0 | O11: =O10 -> 529.52 | P11: =SUM(O11-O10) -> 0 | Q11: =SUM(P11+N11) -> 0 | T11: 4841 | U11: =SUM(T11-T10) -> 2 | V11: =V10 -> 408 | W11: =+V11-V10 -> 0 | X11: =X10 -> 143813 | Y11: =SUM(X11-X10) -> 0 | Z11: =Z10 -> 94875 | AA11: =Z11-Z10 -> 0 | AB11: =AB10 -> 268 | AC11: =AC10 -> 671 | AD11: =AC11-AC10 -> 0 | AE11: =AE10 -> 157.86 | AF11: =AE11-AE10 -> 0 | AG11: 1614.6 | AH11: =AG11-AG10 -> 2.4 | AI11: =AF11+AH11 -> 2.4 | AJ11: =+Z11-Z10 -> 0 | AK11: =SUM(Y11-L11) -> -4 | AL11: =SUM(AJ11-W11) -> 0 | AM11: ='General information '!D11 -> 22 | AN11: ='General information '!H11 -> 0 | AP11: ='General information '!J11 -> 61 | AR11: =A11 -> 43988 | AS11: =AS10 -> 0.9 | AT11: =AT10 -> 146 | AU11: =AU10 -> 1.1 | AV11: 122 | AW11: 2.9 | AX11: 95 | AY11: =AS11*AT11 -> 131.4 | AZ11: =AU11*AV11 -> 134.2 | BA11: =AW11*AX11 -> 275.5 | BB11: =AY11-AY10 -> 0 | BC11: =AZ11-AZ10 -> 0 | BD11: =BA11-BA10 -> -69.6 | BE11: =SUM(BB11:BD11) -> -69.6 | BF11: =SUM(I11-BE11) -> 69.6 | BG11: =SUM(I11-BF11) -> -69.6
A12: =ELEC!C9 -> 43989 | B12: =B11 -> 108473 | C12: =B12-B11 -> 0 | D12: =C12/27 -> 0 | E12: =SUM((C12*$E$4)+(7500/'EDl log'!$A$39)) -> 250 | G12: =G11 -> 599157 | H12: =G12-G11 -> 0 | I12: =C12+H12 -> 0 | J12: =IF(I12>0,E12/I12,0) -> 0 | K12: ='Swimming Pool quality check '!H12 -> 6232 | L12: =K12-K11 -> 0 | M12: =M11 -> 457.44 | N12: =SUM(M12-M11) -> 0 | O12: =O11 -> 529.52 | P12: =SUM(O12-O11) -> 0 | Q12: =SUM(P12+N12) -> 0 | T12: 4843 | U12: =SUM(T12-T11) -> 2 | V12: =V11 -> 408 | W12: =+V12-V11 -> 0 | X12: 143813 | Y12: =SUM(X12-X11) -> 0 | Z12: =Z11 -> 94875 | AA12: =Z12-Z11 -> 0 | AB12: =AB11 -> 268 | AC12: 670 | AD12: =AC12-AC11 -> -1 | AE12: =AE11 -> 157.86 | AF12: =AE12-AE11 -> 0 | AG12: =AG11 -> 1614.6 | AH12: =AG12-AG11 -> 0 | AI12: =AF12+AH12 -> 0 | AJ12: =+Z12-Z11 -> 0 | AK12: =SUM(Y12-L12) -> 0 | AL12: =SUM(AJ12-W12) -> 0 | AM12: ='General information '!D12 -> 24 | AN12: ='General information '!H12 -> 0 | AP12: ='General information '!J12 -> 206 | AR12: =A12 -> 43989 | AS12: =AS11 -> 0.9 | AT12: =AT11 -> 146 | AU12: =AU11 -> 1.1 | AV12: 93 | AW12: 2.9 | AX12: 102 | AY12: =AS12*AT12 -> 131.4 | AZ12: =AU12*AV12 -> 102.3 | BA12: =AW12*AX12 -> 295.8 | BB12: =AY12-AY11 -> 0 | BC12: =AZ12-AZ11 -> -31.9 | BD12: =BA12-BA11 -> 20.3 | BE12: =SUM(BB12:BD12) -> -11.6 | BF12: =SUM(I12-BE12) -> 11.6 | BG12: =SUM(I12-BF12) -> -11.6
A13: =ELEC!C10 -> 43990 | B13: =B12 -> 108473 | C13: =B13-B12 -> 0 | D13: =C13/27 -> 0 | E13: =SUM((C13*$E$4)+(7500/'EDl log'!$A$39)) -> 250 | G13: 599229 | H13: =G13-G12 -> 72 | I13: =C13+H13 -> 72 | J13: =IF(I13>0,E13/I13,0) -> 3.4722222 | K13: ='Swimming Pool quality check '!H13 -> 6242 | L13: =K13-K12 -> 10 | M13: =M12 -> 457.44 | N13: =SUM(M13-M12) -> 0 | O13: =O12 -> 529.52 | P13: =SUM(O13-O12) -> 0 | Q13: =SUM(P13+N13) -> 0 | T13: 4845 | U13: =SUM(T13-T12) -> 2 | V13: =V12 -> 408 | W13: =+V13-V12 -> 0 | X13: 143816 | Y13: =SUM(X13-X12) -> 3 | Z13: =Z12 -> 94875 | AA13: =Z13-Z12 -> 0 | AB13: =AB12 -> 268 | AC13: =AC12 -> 670 | AD13: =AC13-AC12 -> 0 | AE13: =AE12 -> 157.86 | AF13: =AE13-AE12 -> 0 | AG13: 1621 | AH13: =AG13-AG12 -> 6.4 | AI13: =AF13+AH13 -> 6.4 | AJ13: =+Z13-Z12 -> 0 | AK13: =SUM(Y13-L13) -> -7 | AL13: =SUM(AJ13-W13) -> 0 | AM13: ='General information '!D13 -> 24 | AN13: ='General information '!J13 -> 115 | AP13: ='General information '!J13 -> 115 | AR13: =A13 -> 43990 | AS13: =AS12 -> 0.9 | AT13: 180 | AU13: =AU12 -> 1.1 | AV13: 77 | AW13: 2.9 | AX13: 98 | AY13: =AS13*AT13 -> 162 | AZ13: =AU13*AV13 -> 84.7 | BA13: =AW13*AX13 -> 284.2 | BB13: =AY13-AY12 -> 30.6 | BC13: =AZ13-AZ12 -> -17.6 | BD13: =BA13-BA12 -> -11.6 | BE13: =SUM(BB13:BD13) -> 1.4 | BF13: =SUM(I13-BE13) -> 70.6 | BG13: =SUM(I13-BF13) -> 1.4
A14: =ELEC!C11 -> 43991 | B14: 108473 | C14: =B14-B13 -> 0 | D14: =C14/27 -> 0 | E14: =SUM((C14*$E$4)+(7500/'EDl log'!$A$39)) -> 250 | G14: 599229 | H14: =G14-G13 -> 0 | I14: =C14+H14 -> 0 | J14: =IF(I14>0,E14/I14,0) -> 0 | K14: ='Swimming Pool quality check '!H14 -> 6247 | L14: =K14-K13 -> 5 | M14: =M13 -> 457.44 | N14: =SUM(M14-M13) -> 0 | O14: =O13 -> 529.52 | P14: =SUM(O14-O13) -> 0 | Q14: =SUM(P14+N14) -> 0 | T14: 4847 | U14: =SUM(T14-T13) -> 2 | V14: 408 | W14: =+V14-V13 -> 0 | X14: 143893 | Y14: =SUM(X14-X13) -> 77 | Z14: 94921 | AA14: =Z14-Z13 -> 46 | AB14: =AB13 -> 268 | AC14: =AC13 -> 670 | AD14: =AC14-AC13 -> 0 | AE14: =AE13 -> 157.86 | AF14: =AE14-AE13 -> 0 | AG14: 1621.16 | AH14: =AG14-AG13 -> 0.16 | AI14: =AF14+AH14 -> 0.16 | AJ14: =+Z14-Z13 -> 46 | AK14: =SUM(Y14-L14) -> 72 | AL14: =SUM(AJ14-W14) -> 46 | AM14: ='General information '!D14 -> 24 | AN14: ='General information '!H14 -> 0 | AP14: ='General information '!J14 -> 186 | AR14: =A14 -> 43991 | AS14: =AS13 -> 0.9 | AT14: 39 | AU14: =AU13 -> 1.1 | AV14: 90 | AW14: 2.9 | AX14: 108 | AY14: =AS14*AT14 -> 35.1 | AZ14: =AU14*AV14 -> 99 | BA14: =AW14*AX14 -> 313.2 | BB14: =AY14-AY13 -> -126.9 | BC14: =AZ14-AZ13 -> 14.3 | BD14: =BA14-BA13 -> 29 | BE14: =SUM(BB14:BD14) -> -83.6 | BF14: =SUM(I14-BE14) -> 83.6 | BG14: =SUM(I14-BF14) -> -83.6
A15: =ELEC!C12 -> 43992 | B15: 108473 | C15: =B15-B14 -> 0 | D15: =C15/27 -> 0 | E15: =SUM((C15*$E$4)+(7500/'EDl log'!$A$39)) -> 250 | G15: 599629 | H15: =G15-G14 -> 400 | I15: =C15+H15 -> 400 | J15: =IF(I15>0,E15/I15,0) -> 0.625 | K15: ='Swimming Pool quality check '!H15 -> 6252 | L15: =K15-K14 -> 5 | M15: =M14 -> 457.44 | N15: =SUM(M15-M14) -> 0 | O15: =O14 -> 529.52 | P15: =SUM(O15-O14) -> 0 | Q15: =SUM(P15+N15) -> 0 | T15: 4849 | U15: =SUM(T15-T14) -> 2 | V15: 408 | W15: =+V15-V14 -> 0 | X15: 143939 | Y15: =SUM(X15-X14) -> 46 | Z15: 94992 | AA15: =Z15-Z14 -> 71 | AB15: =AB14 -> 268 | AC15: =AC14 -> 670 | AD15: =AC15-AC14 -> 0 | AE15: 159.02 | AF15: =AE15-AE14 -> 1.16 | AG15: 1634.16 | AH15: =AG15-AG14 -> 13 | AI15: =AF15+AH15 -> 14.16 | AJ15: =+Z15-Z14 -> 71 | AK15: =SUM(Y15-L15) -> 41 | AL15: =SUM(AJ15-W15) -> 71 | AM15: ='General information '!D15 -> 24 | AN15: ='General information '!H15 -> 0 | AP15: ='General information '!J15 -> 177 | AR15: =A15 -> 43992 | AS15: =AS14 -> 0.9 | AT15: 190 | AU15: =AU14 -> 1.1 | AV15: 115 | AW15: 2.9 | AX15: 121 | AY15: =AS15*AT15 -> 171 | AZ15: =AU15*AV15 -> 126.5 | BA15: =AW15*AX15 -> 350.9 | BB15: =AY15-AY14 -> 135.9 | BC15: =AZ15-AZ14 -> 27.5 | BD15: =BA15-BA14 -> 37.7 | BE15: =SUM(BB15:BD15) -> 201.1 | BF15: =SUM(I15-BE15) -> 198.9 | BG15: =SUM(I15-BF15) -> 201.1
A16: =ELEC!C13 -> 43993 | B16: 108473 | C16: =B16-B15 -> 0 | D16: =C16/27 -> 0 | E16: =SUM((C16*$E$4)+(7500/'EDl log'!$A$39)) -> 250 | G16: 599629 | H16: =G16-G15 -> 0 | I16: =C16+H16 -> 0 | J16: =IF(I16>0,E16/I16,0) -> 0 | K16: ='Swimming Pool quality check '!H16 -> 6258 | L16: =K16-K15 -> 6 | M16: =M15 -> 457.44 | N16: =SUM(M16-M15) -> 0 | O16: =O15 -> 529.52 | P16: =SUM(O16-O15) -> 0 | Q16: =SUM(P16+N16) -> 0 | T16: 4852 | U16: =SUM(T16-T15) -> 3 | V16: 408 | W16: =+V16-V15 -> 0 | X16: 143983 | Y16: =SUM(X16-X15) -> 44 | Z16: 95011 | AA16: =Z16-Z15 -> 19 | AB16: =AB15 -> 268 | AC16: =AC15 -> 670 | AD16: =AC16-AC15 -> 0 | AE16: 159.02 | AF16: =AE16-AE15 -> 0 | AG16: 1635.2 | AH16: =AG16-AG15 -> 1.04 | AI16: =AF16+AH16 -> 1.04 | AJ16: =+Z16-Z15 -> 19 | AK16: =SUM(Y16-L16) -> 38 | AL16: =SUM(AJ16-W16) -> 19 | AM16: ='General information '!D16 -> 24 | AN16: ='General information '!H16 -> 0 | AP16: ='General information '!J16 -> 162 | AR16: =A16 -> 43993 | AS16: =AS15 -> 0.9 | AT16: 111 | AU16: =AU15 -> 1.1 | AV16: 134 | AW16: 2.9 | AX16: 120 | AY16: =AS16*AT16 -> 99.9 | AZ16: =AU16*AV16 -> 147.4 | BA16: =AW16*AX16 -> 348 | BB16: =AY16-AY15 -> -71.1 | BC16: =AZ16-AZ15 -> 20.9 | BD16: =BA16-BA15 -> -2.9 | BE16: =SUM(BB16:BD16) -> -53.1 | BF16: =SUM(I16-BE16) -> 53.1 | BG16: =SUM(I16-BF16) -> -53.1
A17: =ELEC!C14 -> 43994 | B17: 108473 | C17: =B17-B16 -> 0 | D17: =C17/27 -> 0 | E17: =SUM((C17*$E$4)+(7500/'EDl log'!$A$39)) -> 250 | G17: 599749 | H17: =G17-G16 -> 120 | I17: =C17+H17 -> 120 | J17: =IF(I17>0,E17/I17,0) -> 2.0833333 | K17: ='Swimming Pool quality check '!H17 -> 6258 | L17: =K17-K16 -> 0 | M17: =M16 -> 457.44 | N17: =SUM(M17-M16) -> 0 | O17: =O16 -> 529.52 | P17: =SUM(O17-O16) -> 0 | Q17: =SUM(P17+N17) -> 0 | T17: 4854 | U17: =SUM(T17-T16) -> 2 | V17: =V16 -> 408 | W17: =+V17-V16 -> 0 | X17: 143983 | Y17: =SUM(X17-X16) -> 0 | Z17: =Z16 -> 95011 | AA17: =Z17-Z16 -> 0 | AB17: =AB16 -> 268 | AC17: =AC16 -> 670 | AD17: =AC17-AC16 -> 0 | AE17: =AE16 -> 159.02 | AF17: =AE17-AE16 -> 0 | AG17: 1637.9 | AH17: =AG17-AG16 -> 2.7 | AI17: =AF17+AH17 -> 2.7 | AJ17: =+Z17-Z16 -> 0 | AK17: =SUM(Y17-L17) -> 0 | AL17: =SUM(AJ17-W17) -> 0 | AM17: ='General information '!D17 -> 23.5 | AN17: ='General information '!H17 -> 0 | AP17: ='General information '!J17 -> 173 | AR17: =A17 -> 43994 | AS17: =AS16 -> 0.9 | AT17: 176 | AU17: =AU16 -> 1.1 | AV17: 109 | AW17: 2.9 | AX17: 113 | AY17: =AS17*AT17 -> 158.4 | AZ17: =AU17*AV17 -> 119.9 | BA17: =AW17*AX17 -> 327.7 | BB17: =AY17-AY16 -> 58.5 | BC17: =AZ17-AZ16 -> -27.5 | BD17: =BA17-BA16 -> -20.3 | BE17: =SUM(BB17:BD17) -> 10.7 | BF17: =SUM(I17-BE17) -> 109.3 | BG17: =SUM(I17-BF17) -> 10.7
A18: =ELEC!C15 -> 43995 | B18: =B17 -> 108473 | C18: =B18-B17 -> 0 | D18: =C18/27 -> 0 | E18: =SUM((C18*$E$4)+(7500/'EDl log'!$A$39)) -> 250 | G18: 599749 | H18: =G18-G17 -> 0 | I18: =C18+H18 -> 0 | J18: =IF(I18>0,E18/I18,0) -> 0 | K18: ='Swimming Pool quality check '!H18 -> 6266 | L18: =K18-K17 -> 8 | M18: =M17 -> 457.44 | N18: =SUM(M18-M17) -> 0 | O18: =O17 -> 529.52 | P18: =SUM(O18-O17) -> 0 | Q18: =SUM(P18+N18) -> 0 | T18: 4856 | U18: =SUM(T18-T17) -> 2 | V18: =V17 -> 408 | W18: =+V18-V17 -> 0 | X18: 143983 | Y18: =SUM(X18-X17) -> 0 | Z18: =Z17 -> 95011 | AA18: =Z18-Z17 -> 0 | AB18: =AB17 -> 268 | AC18: =AC17 -> 670 | AD18: =AC18-AC17 -> 0 | AE18: =AE17 -> 159.02 | AF18: =AE18-AE17 -> 0 | AG18: 1639.5 | AH18: =AG18-AG17 -> 1.6 | AI18: =AF18+AH18 -> 1.6 | AJ18: =+Z18-Z17 -> 0 | AK18: =SUM(Y18-L18) -> -8 | AL18: =SUM(AJ18-W18) -> 0 | AM18: ='General information '!D18 -> 22.5 | AN18: ='General information '!H18 -> 0 | AP18: ='General information '!J18 -> 114 | AR18: =A18 -> 43995 | AS18: =AS17 -> 0.9 | AT18: =AT17 -> 176 | AU18: =AU17 -> 1.1 | AV18: 106 | AW18: 2.9 | AX18: 100 | AY18: =AS18*AT18 -> 158.4 | AZ18: =AU18*AV18 -> 116.6 | BA18: =AW18*AX18 -> 290 | BB18: =AY18-AY17 -> 0 | BC18: =AZ18-AZ17 -> -3.3 | BD18: =BA18-BA17 -> -37.7 | BE18: =SUM(BB18:BD18) -> -41 | BF18: =SUM(I18-BE18) -> 41 | BG18: =SUM(I18-BF18) -> -41
A19: =ELEC!C16 -> 43996 | B19: =B18 -> 108473 | C19: =B19-B18 -> 0 | D19: =C19/27 -> 0 | E19: =SUM((C19*$E$4)+(7500/'EDl log'!$A$39)) -> 250 | G19: =G18 -> 599749 | H19: =G19-G18 -> 0 | I19: =C19+H19 -> 0 | J19: =IF(I19>0,E19/I19,0) -> 0 | K19: ='Swimming Pool quality check '!H19 -> 6278 | L19: =K19-K18 -> 12 | M19: =M18 -> 457.44 | N19: =SUM(M19-M18) -> 0 | O19: =O18 -> 529.52 | P19: =SUM(O19-O18) -> 0 | Q19: =SUM(P19+N19) -> 0 | T19: 4859 | U19: =SUM(T19-T18) -> 3 | V19: =V18 -> 408 | W19: =+V19-V18 -> 0 | X19: =X18 -> 143983 | Y19: =SUM(X19-X18) -> 0 | Z19: =Z18 -> 95011 | AA19: =Z19-Z18 -> 0 | AB19: =AB18 -> 268 | AC19: =AC18 -> 670 | AD19: =AC19-AC18 -> 0 | AE19: =AE18 -> 159.02 | AF19: =AE19-AE18 -> 0 | AG19: 1644 | AH19: =AG19-AG18 -> 4.5 | AI19: =AF19+AH19 -> 4.5 | AJ19: =+Z19-Z18 -> 0 | AK19: =SUM(Y19-L19) -> -12 | AL19: =SUM(AJ19-W19) -> 0 | AM19: ='General information '!D19 -> 23.5 | AN19: ='General information '!H19 -> 0 | AP19: ='General information '!J19 -> 202 | AR19: =A19 -> 43996 | AS19: =AS18 -> 0.9 | AT19: 177 | AU19: =AU18 -> 1.1 | AV19: 89 | AW19: 2.9 | AX19: 96 | AY19: =AS19*AT19 -> 159.3 | AZ19: =AU19*AV19 -> 97.9 | BA19: =AW19*AX19 -> 278.4 | BB19: =AY19-AY18 -> 0.9 | BC19: =AZ19-AZ18 -> -18.7 | BD19: =BA19-BA18 -> -11.6 | BE19: =SUM(BB19:BD19) -> -29.4 | BF19: =SUM(I19-BE19) -> 29.4 | BG19: =SUM(I19-BF19) -> -29.4
A20: =ELEC!C17 -> 43997 | B20: =B19 -> 108473 | C20: =B20-B19 -> 0 | D20: =C20/27 -> 0 | E20: =SUM((C20*$E$4)+(7500/'EDl log'!$A$39)) -> 250 | G20: =G19 -> 599749 | H20: =G20-G19 -> 0 | I20: =C20+H20 -> 0 | J20: =IF(I20>0,E20/I20,0) -> 0 | K20: ='Swimming Pool quality check '!H20 -> 6280 | L20: =K20-K19 -> 2 | M20: =M19 -> 457.44 | N20: =SUM(M20-M19) -> 0 | O20: =O19 -> 529.52 | P20: =SUM(O20-O19) -> 0 | Q20: =SUM(P20+N20) -> 0 | T20: 4861 | U20: =SUM(T20-T19) -> 2 | V20: 409 | W20: =+V20-V19 -> 1 | X20: =X19 -> 143983 | Y20: =SUM(X20-X19) -> 0 | Z20: =Z19 -> 95011 | AA20: =Z20-Z19 -> 0 | AB20: =AB19 -> 268 | AC20: =AC19 -> 670 | AD20: =AC20-AC19 -> 0 | AE20: 159.22 | AF20: =AE20-AE19 -> 0.2 | AG20: 1647 | AH20: =AG20-AG19 -> 3 | AI20: =AF20+AH20 -> 3.2 | AJ20: =+Z20-Z19 -> 0 | AK20: =SUM(Y20-L20) -> -2 | AL20: =SUM(AJ20-W20) -> -1 | AM20: ='General information '!D20 -> 23 | AN20: ='General information '!H20 -> 0 | AP20: ='General information '!J20 -> 158 | AR20: =A20 -> 43997 | AS20: =AS19 -> 0.9 | AT20: 161 | AU20: =AU19 -> 1.1 | AV20: 66 | AW20: 2.9 | AX20: 89 | AY20: =AS20*AT20 -> 144.9 | AZ20: =AU20*AV20 -> 72.6 | BA20: =AW20*AX20 -> 258.1 | BB20: =AY20-AY19 -> -14.4 | BC20: =AZ20-AZ19 -> -25.3 | BD20: =BA20-BA19 -> -20.3 | BE20: =SUM(BB20:BD20) -> -60 | BF20: =SUM(I20-BE20) -> 60 | BG20: =SUM(I20-BF20) -> -60
A21: =ELEC!C18 -> 43998 | B21: =B20 -> 108473 | C21: =B21-B20 -> 0 | D21: =C21/27 -> 0 | E21: =SUM((C21*$E$4)+(7500/'EDl log'!$A$39)) -> 250 | G21: 599829 | H21: =G21-G20 -> 80 | I21: =C21+H21 -> 80 | J21: =IF(I21>0,E21/I21,0) -> 3.125 | K21: ='Swimming Pool quality check '!H21 -> 6288 | L21: =K21-K20 -> 8 | M21: =M20 -> 457.44 | N21: =SUM(M21-M20) -> 0 | O21: =O20 -> 529.52 | P21: =SUM(O21-O20) -> 0 | Q21: =SUM(P21+N21) -> 0 | T21: 4864 | U21: =SUM(T21-T20) -> 3 | V21: =V20 -> 409 | W21: =+V21-V20 -> 0 | X21: 143985 | Y21: =SUM(X21-X20) -> 2 | Z21: 95030 | AA21: =Z21-Z20 -> 19 | AB21: =AB20 -> 268 | AC21: =AC20 -> 670 | AD21: =AC21-AC20 -> 0 | AE21: =AE20 -> 159.22 | AF21: =AE21-AE20 -> 0 | AG21: =AG20 -> 1647 | AH21: =AG21-AG20 -> 0 | AI21: =AF21+AH21 -> 0 | AJ21: =+Z21-Z20 -> 19 | AK21: =SUM(Y21-L21) -> -6 | AL21: =SUM(AJ21-W21) -> 19 | AM21: ='General information '!D21 -> 23.5 | AN21: ='General information '!H21 -> 0 | AP21: ='General information '!J21 -> 228 | AR21: =A21 -> 43998 | AS21: =AS20 -> 0.9 | AT21: 163 | AU21: =AU20 -> 1.1 | AV21: 80 | AW21: 2.9 | AX21: 79 | AY21: =AS21*AT21 -> 146.7 | AZ21: =AU21*AV21 -> 88 | BA21: =AW21*AX21 -> 229.1 | BB21: =AY21-AY20 -> 1.8 | BC21: =AZ21-AZ20 -> 15.4 | BD21: =BA21-BA20 -> -29 | BE21: =SUM(BB21:BD21) -> -11.8 | BF21: =SUM(I21-BE21) -> 91.8 | BG21: =SUM(I21-BF21) -> -11.8
A22: =ELEC!C19 -> 43999 | B22: =B21 -> 108473 | C22: =B22-B21 -> 0 | D22: =C22/27 -> 0 | E22: =SUM((C22*$E$4)+(7500/'EDl log'!$A$39)) -> 250 | G22: =G21 -> 599829 | H22: =G22-G21 -> 0 | I22: =C22+H22 -> 0 | J22: =IF(I22>0,E22/I22,0) -> 0 | K22: ='Swimming Pool quality check '!H22 -> 6292 | L22: =K22-K21 -> 4 | M22: =M21 -> 457.44 | N22: =SUM(M22-M21) -> 0 | O22: =O21 -> 529.52 | P22: =SUM(O22-O21) -> 0 | Q22: =SUM(P22+N22) -> 0 | T22: =T21 -> 4864 | U22: =SUM(T22-T21) -> 0 | V22: =V21 -> 409 | W22: =+V22-V21 -> 0 | X22: 144119 | Y22: =SUM(X22-X21) -> 134 | Z22: 95078 | AA22: =Z22-Z21 -> 48 | AB22: =AB21 -> 268 | AC22: =AC21 -> 670 | AD22: =AC22-AC21 -> 0 | AE22: =AE21 -> 159.22 | AF22: =AE22-AE21 -> 0 | AG22: 1649 | AH22: =AG22-AG21 -> 2 | AI22: =AF22+AH22 -> 2 | AJ22: =+Z22-Z21 -> 48 | AK22: =SUM(Y22-L22) -> 130 | AL22: =SUM(AJ22-W22) -> 48 | AM22: ='General information '!D22 -> 24.5 | AN22: ='General information '!H22 -> 0 | AP22: ='General information '!J22 -> 234 | AR22: =A22 -> 43999 | AS22: =AS21 -> 0.9 | AT22: 40 | AU22: =AU21 -> 1.1 | AV22: 105 | AW22: 2.9 | AX22: 100 | AY22: =AS22*AT22 -> 36 | AZ22: =AU22*AV22 -> 115.5 | BA22: =AW22*AX22 -> 290 | BB22: =AY22-AY21 -> -110.7 | BC22: =AZ22-AZ21 -> 27.5 | BD22: =BA22-BA21 -> 60.9 | BE22: =SUM(BB22:BD22) -> -22.3 | BF22: =SUM(I22-BE22) -> 22.3 | BG22: =SUM(I22-BF22) -> -22.3
A23: =ELEC!C20 -> 44000 | B23: 108473 | C23: =B23-B22 -> 0 | D23: =C23/27 -> 0 | E23: =SUM((C23*$E$4)+(7500/'EDl log'!$A$39)) -> 250 | G23: 600167 | H23: =G23-G22 -> 338 | I23: =C23+H23 -> 338 | J23: =IF(I23>0,E23/I23,0) -> 0.73964497 | K23: ='Swimming Pool quality check '!H23 -> 6294 | L23: =K23-K22 -> 2 | M23: =M22 -> 457.44 | N23: =SUM(M23-M22) -> 0 | O23: =O22 -> 529.52 | P23: =SUM(O23-O22) -> 0 | Q23: =SUM(P23+N23) -> 0 | T23: 4868 | U23: =SUM(T23-T22) -> 4 | V23: 409 | W23: =+V23-V22 -> 0 | X23: 144177 | Y23: =SUM(X23-X22) -> 58 | Z23: 95118 | AA23: =Z23-Z22 -> 40 | AB23: =AB22 -> 268 | AC23: =AC22 -> 670 | AD23: =AC23-AC22 -> 0 | AE23: 160.58 | AF23: =AE23-AE22 -> 1.36 | AG23: 1664.26 | AH23: =AG23-AG22 -> 15.26 | AI23: =AF23+AH23 -> 16.62 | AJ23: =+Z23-Z22 -> 40 | AK23: =SUM(Y23-L23) -> 56 | AL23: =SUM(AJ23-W23) -> 40 | AM23: ='General information '!D23 -> 25.5 | AN23: ='General information '!H23 -> 0 | AP23: ='General information '!J23 -> 273 | AR23: =A23 -> 44000 | AS23: =AS22 -> 0.9 | AT23: 125 | AU23: =AU22 -> 1.1 | AV23: 93 | AW23: 2.9 | AX23: 113 | AY23: =AS23*AT23 -> 112.5 | AZ23: =AU23*AV23 -> 102.3 | BA23: =AW23*AX23 -> 327.7 | BB23: =AY23-AY22 -> 76.5 | BC23: =AZ23-AZ22 -> -13.2 | BD23: =BA23-BA22 -> 37.7 | BE23: =SUM(BB23:BD23) -> 101 | BF23: =SUM(I23-BE23) -> 237 | BG23: =SUM(I23-BF23) -> 101
A24: =ELEC!C21 -> 44001 | B24: =B23 -> 108473 | C24: =B24-B23 -> 0 | D24: =C24/27 -> 0 | E24: =SUM((C24*$E$4)+(7500/'EDl log'!$A$39)) -> 250 | G24: =G23 -> 600167 | H24: =G24-G23 -> 0 | I24: =C24+H24 -> 0 | J24: =IF(I24>0,E24/I24,0) -> 0 | K24: ='Swimming Pool quality check '!H24 -> 6297 | L24: =K24-K23 -> 3 | M24: =M23 -> 457.44 | N24: =SUM(M24-M23) -> 0 | O24: =O23 -> 529.52 | P24: =SUM(O24-O23) -> 0 | Q24: =SUM(P24+N24) -> 0 | T24: 4871 | U24: =SUM(T24-T23) -> 3 | V24: =V23 -> 409 | W24: =+V24-V23 -> 0 | X24: 144180 | Y24: =SUM(X24-X23) -> 3 | Z24: =Z23 -> 95118 | AA24: =Z24-Z23 -> 0 | AB24: =AB23 -> 268 | AC24: =AC23 -> 670 | AD24: =AC24-AC23 -> 0 | AE24: =AE23 -> 160.58 | AF24: =AE24-AE23 -> 0 | AG24: 1664.74 | AH24: =AG24-AG23 -> 0.48 | AI24: =AF24+AH24 -> 0.48 | AJ24: =+Z24-Z23 -> 0 | AK24: =SUM(Y24-L24) -> 0 | AL24: =SUM(AJ24-W24) -> 0 | AM24: ='General information '!D24 -> 25.5 | AN24: ='General information '!H24 -> 0 | AP24: ='General information '!J24 -> 248 | AR24: =A24 -> 44001 | AS24: =AS23 -> 0.9 | AT24: 121 | AU24: =AU23 -> 1.1 | AV24: 91 | AW24: 2.9 | AX24: 106 | AY24: =AS24*AT24 -> 108.9 | AZ24: =AU24*AV24 -> 100.1 | BA24: =AW24*AX24 -> 307.4 | BB24: =AY24-AY23 -> -3.6 | BC24: =AZ24-AZ23 -> -2.2 | BD24: =BA24-BA23 -> -20.3 | BE24: =SUM(BB24:BD24) -> -26.1 | BF24: =SUM(I24-BE24) -> 26.1 | BG24: =SUM(I24-BF24) -> -26.1
A25: =ELEC!C22 -> 44002 | B25: =B24 -> 108473 | C25: =B25-B24 -> 0 | D25: =C25/27 -> 0 | E25: =SUM((C25*$E$4)+(7500/'EDl log'!$A$39)) -> 250 | G25: 600413 | H25: =G25-G24 -> 246 | I25: =C25+H25 -> 246 | J25: =IF(I25>0,E25/I25,0) -> 1.0162602 | K25: ='Swimming Pool quality check '!H25 -> 6299 | L25: =K25-K24 -> 2 | M25: =M24 -> 457.44 | N25: =SUM(M25-M24) -> 0 | O25: =O24 -> 529.52 | P25: =SUM(O25-O24) -> 0 | Q25: =SUM(P25+N25) -> 0 | T25: 4873 | U25: =SUM(T25-T24) -> 2 | V25: =V24 -> 409 | W25: =+V25-V24 -> 0 | X25: 144211 | Y25: =SUM(X25-X24) -> 31 | Z25: 95154 | AA25: =Z25-Z24 -> 36 | AB25: =AB24 -> 268 | AC25: =AC24 -> 670 | AD25: =AC25-AC24 -> 0 | AE25: =AE24 -> 160.58 | AF25: =AE25-AE24 -> 0 | AG25: 1666.76 | AH25: =AG25-AG24 -> 2.02 | AI25: =AF25+AH25 -> 2.02 | AJ25: =+Z25-Z24 -> 36 | AK25: =SUM(Y25-L25) -> 29 | AL25: =SUM(AJ25-W25) -> 36 | AM25: ='General information '!D25 -> 24.5 | AN25: ='General information '!H25 -> 0 | AP25: ='General information '!J25 -> 304 | AR25: =A25 -> 44002 | AS25: =AS24 -> 0.9 | AT25: 195 | AU25: =AU24 -> 1.1 | AV25: 100 | AW25: 2.9 | AX25: 115 | AY25: =AS25*AT25 -> 175.5 | AZ25: =AU25*AV25 -> 110 | BA25: =AW25*AX25 -> 333.5 | BB25: =AY25-AY24 -> 66.6 | BC25: =AZ25-AZ24 -> 9.9 | BD25: =BA25-BA24 -> 26.1 | BE25: =SUM(BB25:BD25) -> 102.6 | BF25: =SUM(I25-BE25) -> 143.4 | BG25: =SUM(I25-BF25) -> 102.6
A26: =ELEC!C23 -> 44003 | B26: 108473 | C26: =B26-B25 -> 0 | D26: =C26/27 -> 0 | E26: =SUM((C26*$E$4)+(7500/'EDl log'!$A$39)) -> 250 | G26: 600413 | H26: =G26-G25 -> 0 | I26: =C26+H26 -> 0 | J26: =IF(I26>0,E26/I26,0) -> 0 | K26: ='Swimming Pool quality check '!H26 -> 6303 | L26: =K26-K25 -> 4 | M26: =M25 -> 457.44 | N26: =SUM(M26-M25) -> 0 | O26: =O25 -> 529.52 | P26: =SUM(O26-O25) -> 0 | Q26: =SUM(P26+N26) -> 0 | T26: 4877 | U26: =SUM(T26-T25) -> 4 | V26: 409 | W26: =+V26-V25 -> 0 | X26: 144211 | Y26: =SUM(X26-X25) -> 0 | Z26: 95154 | AA26: =Z26-Z25 -> 0 | AB26: 268 | AC26: 670 | AD26: =AC26-AC25 -> 0 | AE26: 160.58 | AF26: =AE26-AE25 -> 0 | AG26: 1668.5 | AH26: =AG26-AG25 -> 1.74 | AI26: =AF26+AH26 -> 1.74 | AJ26: =+Z26-Z25 -> 0 | AK26: =SUM(Y26-L26) -> -4 | AL26: =SUM(AJ26-W26) -> 0 | AM26: ='General information '!D26 -> 25 | AN26: ='General information '!H26 -> 0 | AP26: ='General information '!J26 -> 196 | AR26: =A26 -> 44003 | AS26: =AS25 -> 0.9 | AT26: 193 | AU26: =AU25 -> 1.1 | AV26: 75 | AW26: 2.9 | AX26: 97 | AY26: =AS26*AT26 -> 173.7 | AZ26: =AU26*AV26 -> 82.5 | BA26: =AW26*AX26 -> 281.3 | BB26: =AY26-AY25 -> -1.8 | BC26: =AZ26-AZ25 -> -27.5 | BD26: =BA26-BA25 -> -52.2 | BE26: =SUM(BB26:BD26) -> -81.5 | BF26: =SUM(I26-BE26) -> 81.5 | BG26: =SUM(I26-BF26) -> -81.5
A27: =ELEC!C24 -> 44004 | B27: 108473 | C27: =B27-B26 -> 0 | D27: =C27/27 -> 0 | E27: =SUM((C27*$E$4)+(7500/'EDl log'!$A$39)) -> 250 | G27: 600413 | H27: =G27-G26 -> 0 | I27: =C27+H27 -> 0 | J27: =IF(I27>0,E27/I27,0) -> 0 | K27: ='Swimming Pool quality check '!H27 -> 6310 | L27: =K27-K26 -> 7 | M27: =M26 -> 457.44 | N27: =SUM(M27-M26) -> 0 | O27: =O26 -> 529.52 | P27: =SUM(O27-O26) -> 0 | Q27: =SUM(P27+N27) -> 0 | T27: 4879 | U27: =SUM(T27-T26) -> 2 | V27: 409 | W27: =+V27-V26 -> 0 | X27: 144239 | Y27: =SUM(X27-X26) -> 28 | Z27: 95183 | AA27: =Z27-Z26 -> 29 | AB27: =AB26 -> 268 | AC27: =AC26 -> 670 | AD27: =AC27-AC26 -> 0 | AE27: =AE26 -> 160.58 | AF27: =AE27-AE26 -> 0 | AG27: 1670.5 | AH27: =AG27-AG26 -> 2 | AI27: =AF27+AH27 -> 2 | AJ27: =+Z27-Z26 -> 29 | AK27: =SUM(Y27-L27) -> 21 | AL27: =SUM(AJ27-W27) -> 29 | AM27: ='General information '!D27 -> 25.5 | AN27: ='General information '!H27 -> 0 | AP27: ='General information '!J27 -> 317.62 | AR27: =A27 -> 44004 | AS27: =AS26 -> 0.9 | AT27: 183 | AU27: =AU26 -> 1.1 | AV27: 86 | AW27: 2.9 | AX27: 92 | AY27: =AS27*AT27 -> 164.7 | AZ27: =AU27*AV27 -> 94.6 | BA27: =AW27*AX27 -> 266.8 | BB27: =AY27-AY26 -> -9 | BC27: =AZ27-AZ26 -> 12.1 | BD27: =BA27-BA26 -> -14.5 | BE27: =SUM(BB27:BD27) -> -11.4 | BF27: =SUM(I27-BE27) -> 11.4 | BG27: =SUM(I27-BF27) -> -11.4
A28: =ELEC!C25 -> 44005 | B28: =B27 -> 108473 | C28: =B28-B27 -> 0 | D28: =C28/27 -> 0 | E28: =SUM((C28*$E$4)+(7500/'EDl log'!$A$39)) -> 250 | G28: =G27 -> 600413 | H28: =G28-G27 -> 0 | I28: =C28+H28 -> 0 | J28: =IF(I28>0,E28/I28,0) -> 0 | K28: ='Swimming Pool quality check '!H28 -> 6310 | L28: =K28-K27 -> 0 | M28: =M27 -> 457.44 | N28: =SUM(M28-M27) -> 0 | O28: =O27 -> 529.52 | P28: =SUM(O28-O27) -> 0 | Q28: =SUM(P28+N28) -> 0 | T28: 4881 | U28: =SUM(T28-T27) -> 2 | V28: =V27 -> 409 | W28: =+V28-V27 -> 0 | X28: =X27 -> 144239 | Y28: =SUM(X28-X27) -> 0 | Z28: 95183 | AA28: =Z28-Z27 -> 0 | AB28: =AB27 -> 268 | AC28: =AC27 -> 670 | AD28: =AC28-AC27 -> 0 | AE28: =AE27 -> 160.58 | AF28: =AE28-AE27 -> 0 | AG28: 1670.5 | AH28: =AG28-AG27 -> 0 | AI28: =AF28+AH28 -> 0 | AJ28: =+Z28-Z27 -> 0 | AK28: =SUM(Y28-L28) -> 0 | AL28: =SUM(AJ28-W28) -> 0 | AM28: ='General information '!D28 -> 25 | AN28: ='General information '!H28 -> 0 | AP28: ='General information '!J28 -> 174 | AR28: =A28 -> 44005 | AS28: =AS27 -> 0.9 | AT28: 152 | AU28: =AU27 -> 1.1 | AV28: 72 | AW28: 2.9 | AX28: 82 | AY28: =AS28*AT28 -> 136.8 | AZ28: =AU28*AV28 -> 79.2 | BA28: =AW28*AX28 -> 237.8 | BB28: =AY28-AY27 -> -27.9 | BC28: =AZ28-AZ27 -> -15.4 | BD28: =BA28-BA27 -> -29 | BE28: =SUM(BB28:BD28) -> -72.3 | BF28: =SUM(I28-BE28) -> 72.3 | BG28: =SUM(I28-BF28) -> -72.3
A29: =ELEC!C26 -> 44006 | B29: 108473 | C29: =B29-B28 -> 0 | D29: =C29/27 -> 0 | E29: =SUM((C29*$E$4)+(7500/'EDl log'!$A$39)) -> 250 | G29: 600667 | H29: =G29-G28 -> 254 | I29: =C29+H29 -> 254 | J29: =IF(I29>0,E29/I29,0) -> 0.98425197 | K29: ='Swimming Pool quality check '!H29 -> 6310 | L29: =K29-K28 -> 0 | M29: =M28 -> 457.44 | N29: =SUM(M29-M28) -> 0 | O29: =O28 -> 529.52 | P29: =SUM(O29-O28) -> 0 | Q29: =SUM(P29+N29) -> 0 | T29: 4884 | U29: =SUM(T29-T28) -> 3 | V29: 409 | W29: =+V29-V28 -> 0 | X29: 144407 | Y29: =SUM(X29-X28) -> 168 | Z29: 95238 | AA29: =Z29-Z28 -> 55 | AB29: =AB28 -> 268 | AC29: =AC28 -> 670 | AD29: =AC29-AC28 -> 0 | AE29: 160.58 | AF29: =AE29-AE28 -> 0 | AG29: 1673 | AH29: =AG29-AG28 -> 2.5 | AI29: =AF29+AH29 -> 2.5 | AJ29: =+Z29-Z28 -> 55 | AK29: =SUM(Y29-L29) -> 168 | AL29: =SUM(AJ29-W29) -> 55 | AM29: ='General information '!D29 -> 25 | AN29: ='General information '!H29 -> 0 | AP29: ='General information '!J29 -> 226 | AR29: =A29 -> 44006 | AS29: =AS28 -> 0.9 | AT29: 70 | AU29: =AU28 -> 1.1 | AV29: 98 | AW29: 2.9 | AX29: 113 | AY29: =AS29*AT29 -> 63 | AZ29: =AU29*AV29 -> 107.8 | BA29: =AW29*AX29 -> 327.7 | BB29: =AY29-AY28 -> -73.8 | BC29: =AZ29-AZ28 -> 28.6 | BD29: =BA29-BA28 -> 89.9 | BE29: =SUM(BB29:BD29) -> 44.7 | BF29: =SUM(I29-BE29) -> 209.3 | BG29: =SUM(I29-BF29) -> 44.7
A30: =ELEC!C27 -> 44007 | B30: =B29 -> 108473 | C30: =B30-B29 -> 0 | D30: =C30/27 -> 0 | E30: =SUM((C30*$E$4)+(7500/'EDl log'!$A$39)) -> 250 | G30: =G29 -> 600667 | H30: =G30-G29 -> 0 | I30: =C30+H30 -> 0 | J30: =IF(I30>0,E30/I30,0) -> 0 | K30: ='Swimming Pool quality check '!H30 -> 6319 | L30: =K30-K29 -> 9 | M30: =M29 -> 457.44 | N30: =SUM(M30-M29) -> 0 | O30: =O29 -> 529.52 | P30: =SUM(O30-O29) -> 0 | Q30: =SUM(P30+N30) -> 0 | T30: 4886 | U30: =SUM(T30-T29) -> 2 | V30: =V29 -> 409 | W30: =+V30-V29 -> 0 | X30: =X29 -> 144407 | Y30: =SUM(X30-X29) -> 0 | Z30: 95264 | AA30: =Z30-Z29 -> 26 | AB30: =AB29 -> 268 | AC30: =AC29 -> 670 | AD30: =AC30-AC29 -> 0 | AE30: =AE29 -> 160.58 | AF30: =AE30-AE29 -> 0 | AG30: =AG29 -> 1673 | AH30: =AG30-AG29 -> 0 | AI30: =AF30+AH30 -> 0 | AJ30: =+Z30-Z29 -> 26 | AK30: =SUM(Y30-L30) -> -9 | AL30: =SUM(AJ30-W30) -> 26 | AM30: ='General information '!D30 -> 30 | AN30: ='General information '!H30 -> 0 | AP30: ='General information '!J30 -> 239 | AR30: =A30 -> 44007 | AS30: =AS29 -> 0.9 | AT30: 54 | AU30: =AU29 -> 1.1 | AV30: 100 | AW30: 2.9 | AX30: 105 | AY30: =AS30*AT30 -> 48.6 | AZ30: =AU30*AV30 -> 110 | BA30: =AW30*AX30 -> 304.5 | BB30: =AY30-AY29 -> -14.4 | BC30: =AZ30-AZ29 -> 2.2 | BD30: =BA30-BA29 -> -23.2 | BE30: =SUM(BB30:BD30) -> -35.4 | BF30: =SUM(I30-BE30) -> 35.4 | BG30: =SUM(I30-BF30) -> -35.4
A31: =ELEC!C28 -> 44008 | B31: 108535 | C31: =B31-B30 -> 62 | D31: =C31/27 -> 2.2962963 | E31: =SUM((C31*$E$4)+(7500/'EDl log'!$A$39)) -> 352.92 | F31: 2 | G31: 600679 | H31: =G31-G30 -> 12 | I31: =C31+H31 -> 74 | J31: =IF(I31>0,E31/I31,0) -> 4.7691892 | K31: ='Swimming Pool quality check '!H31 -> 6328 | L31: =K31-K30 -> 9 | M31: =M30 -> 457.44 | N31: =SUM(M31-M30) -> 0 | O31: =O30 -> 529.52 | P31: =SUM(O31-O30) -> 0 | Q31: =SUM(P31+N31) -> 0 | T31: 4888 | U31: =SUM(T31-T30) -> 2 | V31: 410 | W31: =+V31-V30 -> 1 | X31: 144408 | Y31: =SUM(X31-X30) -> 1 | Z31: =Z30 -> 95264 | AA31: =Z31-Z30 -> 0 | AB31: 259 | AC31: 670 | AD31: =AC31-AC30 -> 0 | AE31: 161.7 | AF31: =AE31-AE30 -> 1.12 | AG31: 1685.6 | AH31: =AG31-AG30 -> 12.6 | AI31: =AF31+AH31 -> 13.72 | AJ31: =+Z31-Z30 -> 0 | AK31: =SUM(Y31-L31) -> -8 | AL31: =SUM(AJ31-W31) -> -1 | AM31: ='General information '!D31 -> 26 | AN31: ='General information '!H31 -> 0 | AP31: ='General information '!J31 -> 223 | AR31: =A31 -> 44008 | AS31: =AS30 -> 0.9 | AT31: 108 | AU31: =AU30 -> 1.1 | AV31: 94 | AW31: 2.9 | AX31: 93 | AY31: =AS31*AT31 -> 97.2 | AZ31: =AU31*AV31 -> 103.4 | BA31: =AW31*AX31 -> 269.7 | BB31: =AY31-AY30 -> 48.6 | BC31: =AZ31-AZ30 -> -6.6 | BD31: =BA31-BA30 -> -34.8 | BE31: =SUM(BB31:BD31) -> 7.2 | BF31: =SUM(I31-BE31) -> 66.8 | BG31: =SUM(I31-BF31) -> 7.2
A32: =ELEC!C29 -> 44009 | B32: =B31 -> 108535 | C32: =B32-B31 -> 0 | D32: =C32/27 -> 0 | E32: =SUM((C32*$E$4)+(7500/'EDl log'!$A$39)) -> 250 | G32: =G31 -> 600679 | H32: =G32-G31 -> 0 | I32: =C32+H32 -> 0 | J32: =IF(I32>0,E32/I32,0) -> 0 | K32: ='Swimming Pool quality check '!H32 -> 6337 | L32: =K32-K31 -> 9 | M32: =M31 -> 457.44 | N32: =SUM(M32-M31) -> 0 | O32: =O31 -> 529.52 | P32: =SUM(O32-O31) -> 0 | Q32: =SUM(P32+N32) -> 0 | T32: 4890 | U32: =SUM(T32-T31) -> 2 | V32: =V31 -> 410 | W32: =+V32-V31 -> 0 | X32: =X31 -> 144408 | Y32: =SUM(X32-X31) -> 0 | Z32: 95265 | AA32: =Z32-Z31 -> 1 | AB32: =AB31 -> 259 | AC32: 670 | AD32: =AC32-AC31 -> 0 | AE32: =AE31 -> 161.7 | AF32: =AE32-AE31 -> 0 | AG32: 1688.52 | AH32: =AG32-AG31 -> 2.92 | AI32: =AF32+AH32 -> 2.92 | AJ32: =+Z32-Z31 -> 1 | AK32: 0 | AL32: =SUM(AJ32-W32) -> 1 | AM32: ='General information '!D32 -> 27 | AN32: ='General information '!H32 -> 0 | AP32: ='General information '!J32 -> 236 | AR32: =A32 -> 44009 | AS32: =AS31 -> 0.9 | AT32: 98 | AU32: =AU31 -> 1.1 | AV32: 69 | AW32: 2.9 | AX32: 82 | AY32: =AS32*AT32 -> 88.2 | AZ32: =AU32*AV32 -> 75.9 | BA32: =AW32*AX32 -> 237.8 | BB32: =AY32-AY31 -> -9 | BC32: =AZ32-AZ31 -> -27.5 | BD32: =BA32-BA31 -> -31.9 | BE32: =SUM(BB32:BD32) -> -68.4 | BF32: =SUM(I32-BE32) -> 68.4 | BG32: =SUM(I32-BF32) -> -68.4
A33: =ELEC!C30 -> 44010 | B33: =B32 -> 108535 | C33: =B33-B32 -> 0 | D33: =C33/27 -> 0 | E33: =SUM((C33*$E$4)+(7500/'EDl log'!$A$39)) -> 250 | G33: 600833 | H33: =G33-G32 -> 154 | I33: =C33+H33 -> 154 | J33: =IF(I33>0,E33/I33,0) -> 1.6233766 | K33: ='Swimming Pool quality check '!H33 -> 6348 | L33: =K33-K32 -> 11 | M33: =M32 -> 457.44 | N33: =SUM(M33-M32) -> 0 | O33: =O32 -> 529.52 | P33: =SUM(O33-O32) -> 0 | Q33: =SUM(P33+N33) -> 0 | T33: 4893 | U33: =SUM(T33-T32) -> 3 | V33: =V32 -> 410 | W33: =+V33-V32 -> 0 | X33: 144461 | Y33: =SUM(X33-X32) -> 53 | Z33: 95321 | AA33: =Z33-Z32 -> 56 | AB33: =AB32 -> 259 | AC33: =AC32 -> 670 | AD33: =AC33-AC32 -> 0 | AE33: =AE32 -> 161.7 | AF33: =AE33-AE32 -> 0 | AG33: 1689.75 | AH33: =AG33-AG32 -> 1.23 | AI33: =AF33+AH33 -> 1.23 | AJ33: =+Z33-Z32 -> 56 | AK33: =SUM(Y33-L33) -> 42 | AL33: =SUM(AJ33-W33) -> 56 | AM33: ='General information '!D33 -> 28 | AN33: ='General information '!H33 -> 0 | AP33: ='General information '!J33 -> 218 | AR33: =A33 -> 44010 | AS33: =AS32 -> 0.9 | AT33: 54 | AU33: =AU32 -> 1.1 | AV33: 107 | AW33: 2.9 | AX33: 84 | AY33: =AS33*AT33 -> 48.6 | AZ33: =AU33*AV33 -> 117.7 | BA33: =AW33*AX33 -> 243.6 | BB33: =AY33-AY32 -> -39.6 | BC33: =AZ33-AZ32 -> 41.8 | BD33: =BA33-BA32 -> 5.8 | BE33: =SUM(BB33:BD33) -> 8 | BF33: =SUM(I33-BE33) -> 146 | BG33: =SUM(I33-BF33) -> 8
A34: =ELEC!C31 -> 44011 | B34: =B33 -> 108535 | C34: =B34-B33 -> 0 | D34: =C34/27 -> 0 | E34: =SUM((C34*$E$4)+(7500/'EDl log'!$A$39)) -> 250 | G34: =G33 -> 600833 | H34: =G34-G33 -> 0 | I34: =C34+H34 -> 0 | J34: =IF(I34>0,E34/I34,0) -> 0 | K34: ='Swimming Pool quality check '!H34 -> 6348 | L34: =K34-K33 -> 0 | M34: =M33 -> 457.44 | N34: =SUM(M34-M33) -> 0 | O34: =O33 -> 529.52 | P34: =SUM(O34-O33) -> 0 | Q34: =SUM(P34+N34) -> 0 | T34: =T33 -> 4893 | U34: =SUM(T34-T33) -> 0 | V34: =V33 -> 410 | W34: =+V34-V33 -> 0 | X34: =X33 -> 144461 | Y34: =SUM(X34-X33) -> 0 | Z34: =Z33 -> 95321 | AA34: =Z34-Z33 -> 0 | AB34: =AB33 -> 259 | AC34: =AC33 -> 670 | AD34: =AC34-AC33 -> 0 | AE34: =AE33 -> 161.7 | AF34: =AE34-AE33 -> 0 | AG34: =AG33 -> 1689.75 | AH34: =AG34-AG33 -> 0 | AI34: =AF34+AH34 -> 0 | AJ34: =+Z34-Z33 -> 0 | AK34: =SUM(Y34-L34) -> 0 | AL34: =SUM(AJ34-W34) -> 0 | AM34: ='General information '!D34 -> 0 | AN34: ='General information '!H34 -> 0 | AP34: ='General information '!J34 -> 0 | AR34: =A34 -> 44011 | AS34: =AS33 -> 0.9 | AT34: =AT33 -> 54 | AU34: =AU33 -> 1.1 | AV34: =AV33 -> 107 | AW34: 2.9 | AX34: =AX33 -> 84 | AY34: =AS34*AT34 -> 48.6 | AZ34: =AU34*AV34 -> 117.7 | BA34: =AW34*AX34 -> 243.6 | BB34: =AY34-AY33 -> 0 | BC34: =AZ34-AZ33 -> 0 | BD34: =BA34-BA33 -> 0 | BE34: =SUM(BB34:BD34) -> 0 | BF34: =SUM(I34-BE34) -> 0 | BG34: =SUM(I34-BF34) -> 0
A35: =ELEC!C32 -> 44012 | B35: =B34 -> 108535 | C35: =B35-B34 -> 0 | D35: =C35/27 -> 0 | E35: =SUM((C35*$E$4)+(7500/'EDl log'!$A$39)) -> 250 | G35: =G34 -> 600833 | H35: =G35-G34 -> 0 | I35: =C35+H35 -> 0 | J35: =IF(I35>0,E35/I35,0) -> 0 | K35: ='Swimming Pool quality check '!H35 -> 6348 | L35: =K35-K34 -> 0 | M35: =M34 -> 457.44 | N35: =SUM(M35-M34) -> 0 | O35: =O34 -> 529.52 | P35: =SUM(O35-O34) -> 0 | Q35: =SUM(P35+N35) -> 0 | T35: =T34 -> 4893 | U35: =SUM(T35-T34) -> 0 | V35: =V34 -> 410 | W35: =+V35-V34 -> 0 | X35: =X34 -> 144461 | Y35: =SUM(X35-X34) -> 0 | Z35: =Z34 -> 95321 | AA35: =Z35-Z34 -> 0 | AB35: =AB34 -> 259 | AC35: =AC34 -> 670 | AD35: =AC35-AC34 -> 0 | AE35: =AE34 -> 161.7 | AF35: =AE35-AE34 -> 0 | AG35: =AG34 -> 1689.75 | AH35: =AG35-AG34 -> 0 | AI35: =AF35+AH35 -> 0 | AJ35: =+Z35-Z34 -> 0 | AK35: =SUM(Y35-L35) -> 0 | AL35: =SUM(AJ35-W35) -> 0 | AM35: ='General information '!D35 -> 0 | AN35: ='General information '!H35 -> 0 | AP35: ='General information '!J35 -> 0 | AR35: =A35 -> 44012 | AS35: =AS34 -> 0.9 | AT35: =AT34 -> 54 | AU35: =AU34 -> 1.1 | AV35: =AV34 -> 107 | AW35: 2.9 | AX35: =AX34 -> 84 | AY35: =AS35*AT35 -> 48.6 | AZ35: =AU35*AV35 -> 117.7 | BA35: =AW35*AX35 -> 243.6 | BB35: =AY35-AY34 -> 0 | BC35: =AZ35-AZ34 -> 0 | BD35: =BA35-BA34 -> 0 | BE35: =SUM(BB35:BD35) -> 0 | BF35: =SUM(I35-BE35) -> 0 | BG35: =SUM(I35-BF35) -> 0
C36: =SUM(C6:C35) -> 62 | D36: =SUM(D6:D35) -> 2.2962963 | F36: =SUM(F6:F35) -> 2 | H36: =SUM(H6:H35) -> 1859 | I36: =SUM(I6:I35) -> 1921 | L36: =SUM(L7:L35) -> 136 | Q36: =SUM(Q5:Q35) -> 0 | U36: =SUM(U6:U35) -> 63 | Y36: =SUM(Y35,Y33,Y31,Y29,Y27,Y25,Y23,Y21,Y19,Y17,Y15,Y13,Y11,Y9,Y7+#REF!) -> #REF! | AJ36: =SUM(AJ6:AJ35) -> 523 | AK36: =SUM(Y36-L36) -> #REF! | AL36: =SUM(AL6:AL35) -> 520
C37: =+C36*1.66 -> 102.92 | E37: =SUM(E6:E35) -> 7602.92 | F37: =SUM(F6:F35) -> 2 | H37: 7500 | I37: =SUM('General information '!G36/WATER!I36) -> 0.063672046 | O37: =SUM(Q36+I36) -> 1921 | Z37: =SUM(Y36:AJ36) -> #REF! | AK37: =SUM(Y37-L37) -> 0
B38: =9*27 -> 243 | D38: =SUM(D21:D35) -> 2.2962963 | F38: =SUM(F6:F35) -> 2 | G38: =SUM(I36) -> 1921 | H38: =SUM(H37+C37) -> 7602.92 | K38: =SUM(H38/G38) -> 3.9577928 | AJ38: =SUM(C37-AK37) -> 102.92 | AM38: =SUM(AJ38/AO37) -> #DIV/0!

Sheet graphic

Sheet General information 
A1: GENERAL & HOTEL'S INFORMATION SHEET
B4: Max Temp | C4: MIN TEMP | D4: AVE TEMP | E4: AVE Humidity | F4: AVE OCC | G4: # of OCC Rooms | H4: Ball room | I4: Meeting rooms | J4: Outlets | K4: Total covers | L4: # of permenant Emp | M4: # of casuals | N4: Total # of EMP | O4: # of EMP/OCC Room
A5: =ELEC!C2 -> 43982 | B5: ='[2]General information '!B36 -> 24 | C5: ='[2]General information '!C36 -> 19 | D5: ='[2]General information '!D36 -> 21.5 | E5: ='[2]General information '!E36 -> 0.59 | F5: ='[2]General information '!F36 -> 0.0174 | G5: ='[2]General information '!G36 -> 4.002 | H5: ='[2]General information '!H36 -> 0 | I5: ='[2]General information '!I36 -> 0 | ... O5: ='[2]General information '!O36 -> 0
A6: =ELEC!C3 -> 43983 | B6: 25 | C6: 20 | D6: =(C6+B6)/2 -> 22.5 | E6: 0.61 | F6: 0.0217 | G6: =F6*230 -> 4.991 | H6: 0 | J6: 137 | K6: =+J6+H6 -> 137
A7: =ELEC!C4 -> 43984 | B7: 24 | C7: 20 | D7: =(C7+B7)/2 -> 22 | E7: 0.6 | F7: 0.0087 | G7: =F7*230 -> 2.001 | H7: 0 | J7: 126 | K7: =+J7+H7 -> 126
A8: =ELEC!C5 -> 43985 | B8: 27 | C8: 19 | D8: =(C8+B8)/2 -> 23 | E8: 0.6 | F8: 0.0261 | G8: =F8*230 -> 6.003 | J8: 172 | K8: =+J8+H8 -> 172
A9: =ELEC!C6 -> 43986 | B9: 26 | C9: 18 | D9: =(C9+B9)/2 -> 22 | E9: 0.62 | F9: 0.0217 | G9: =F9*230 -> 4.991 | H9: 0 | J9: 182 | K9: =+J9+H9 -> 182
A10: =ELEC!C7 -> 43987 | B10: 25 | C10: 17 | D10: =(C10+B10)/2 -> 21 | E10: 0.6 | F10: 0.013 | G10: =F10*230 -> 2.99 | H10: 0 | J10: 292 | K10: =+J10+H10 -> 292
A11: =ELEC!C8 -> 43988 | B11: 26 | C11: 18 | D11: =(C11+B11)/2 -> 22 | E11: 0.63 | F11: 0.0217 | G11: =F11*230 -> 4.991 | H11: 0 | J11: 61 | K11: =+J11+H11 -> 61
A12: =ELEC!C9 -> 43989 | B12: 27 | C12: 21 | D12: =(C12+B12)/2 -> 24 | E12: 0.7 | F12: 0.0174 | G12: =F12*230 -> 4.002 | J12: 206 | K12: =+J12+H12 -> 206
A13: =ELEC!C10 -> 43990 | B13: 26 | C13: 22 | D13: =(C13+B13)/2 -> 24 | E13: 0.72 | F13: 0.013 | G13: =F13*230 -> 2.99 | H13: 0 | J13: 115 | K13: =+J13+H13 -> 115
A14: =ELEC!C11 -> 43991 | B14: 28 | C14: 20 | D14: =(C14+B14)/2 -> 24 | E14: 0.68 | F14: 0.0174 | G14: =F14*230 -> 4.002 | J14: 186 | K14: =+J14+H14 -> 186
A15: =ELEC!C12 -> 43992 | B15: 28 | C15: 20 | D15: =(C15+B15)/2 -> 24 | E15: 0.65 | F15: 0.0174 | G15: =F15*230 -> 4.002 | J15: 177 | K15: =+J15+H15 -> 177
A16: =ELEC!C13 -> 43993 | B16: 28 | C16: 20 | D16: =(C16+B16)/2 -> 24 | E16: 0.68 | F16: 0.013 | G16: =F16*230 -> 2.99 | J16: 162 | K16: =+J16+H16 -> 162
A17: =ELEC!C14 -> 43994 | B17: 27 | C17: 20 | D17: =(C17+B17)/2 -> 23.5 | E17: 0.42 | F17: 0.03 | G17: =F17*230 -> 6.9 | J17: 173 | K17: =+J17+H17 -> 173
A18: =ELEC!C15 -> 43995 | B18: 25 | C18: 20 | D18: =(C18+B18)/2 -> 22.5 | E18: 0.47 | F18: 0.0174 | G18: =F18*230 -> 4.002 | J18: 114 | K18: =+J18+H18 -> 114
A19: =ELEC!C16 -> 43996 | B19: 26 | C19: 21 | D19: =(C19+B19)/2 -> 23.5 | E19: 0.65 | F19: 0.013 | G19: =F19*230 -> 2.99 | H19: 0 | J19: 202 | K19: =+J19+H19 -> 202
A20: =ELEC!C17 -> 43997 | B20: 26 | C20: 20 | D20: =(C20+B20)/2 -> 23 | E20: 0.62 | F20: 0.013 | G20: =F20*230 -> 2.99 | H20: 0 | J20: 158 | K20: =+J20+H20 -> 158
A21: =ELEC!C18 -> 43998 | B21: 26 | C21: 21 | D21: =(C21+B21)/2 -> 23.5 | E21: 0.65 | F21: 0.0217 | G21: =F21*230 -> 4.991 | H21: 0 | J21: 228 | K21: =+J21+H21 -> 228
A22: =ELEC!C19 -> 43999 | B22: 27 | C22: 22 | D22: =(C22+B22)/2 -> 24.5 | E22: 0.72 | F22: 0.0174 | G22: =F22*230 -> 4.002 | H22: 0 | J22: 234 | K22: =+J22+H22 -> 234
A23: =ELEC!C20 -> 44000 | B23: 27 | C23: 24 | D23: =(C23+B23)/2 -> 25.5 | E23: 0.65 | F23: 0.0217 | G23: =F23*230 -> 4.991 | J23: 273 | K23: =+J23+H23 -> 273
A24: =ELEC!C21 -> 44001 | B24: 27 | C24: 24 | D24: =(C24+B24)/2 -> 25.5 | E24: 0.7 | F24: 0.0304 | G24: =F24*230 -> 6.992 | H24: 0 | J24: 248 | K24: =+J24+H24 -> 248
A25: =ELEC!C22 -> 44002 | B25: 26 | C25: 23 | D25: =(C25+B25)/2 -> 24.5 | E25: 0.65 | F25: 0.0217 | G25: =F25*230 -> 4.991 | J25: 304 | K25: =+J25+H25 -> 304
A26: =ELEC!C23 -> 44003 | B26: 29 | C26: 21 | D26: =(C26+B26)/2 -> 25 | E26: 0.65 | F26: 0.0087 | G26: =F26*230 -> 2.001 | J26: 196 | K26: =+J26+H26 -> 196
A27: =ELEC!C24 -> 44004 | B27: 29 | C27: 22 | D27: =(C27+B27)/2 -> 25.5 | E27: 0.7 | F27: 0.0261 | G27: =F27*230 -> 6.003 | J27: 317.62 | K27: =+J27+H27+I27 -> 317.62
A28: =ELEC!C25 -> 44005 | B28: 27 | C28: 23 | D28: =(C28+B28)/2 -> 25 | E28: 0.65 | F28: 0.0174 | G28: =F28*230 -> 4.002 | H28: 0 | J28: 174 | K28: =+J28+H28+I28 -> 174
A29: =ELEC!C26 -> 44006 | B29: 27 | C29: 23 | D29: =(C29+B29)/2 -> 25 | E29: 0.65 | F29: 0.013 | G29: =F29*230 -> 2.99 | J29: 226 | K29: =+J29+H29+I29 -> 226
A30: =ELEC!C27 -> 44007 | B30: 33 | C30: 27 | D30: =(C30+B30)/2 -> 30 | E30: 0.69 | F30: 0.0174 | G30: =F30*230 -> 4.002 | H30: 0 | J30: 239 | K30: =+J30+H30+I30 -> 239
A31: =ELEC!C28 -> 44008 | B31: 28 | C31: 24 | D31: =(C31+B31)/2 -> 26 | E31: 0.66 | F31: 0.013 | G31: =F31*230 -> 2.99 | J31: 223 | K31: =+J31+H31+I31 -> 223
A32: =ELEC!C29 -> 44009 | B32: 29 | C32: 25 | D32: =(C32+B32)/2 -> 27 | E32: 0.55 | F32: 0.024 | G32: =F32*230 -> 5.52 | J32: 236 | K32: =+J32+H32+I32 -> 236
A33: =ELEC!C30 -> 44010 | B33: 30 | C33: 26 | D33: =(C33+B33)/2 -> 28 | E33: 0.66 | F33: 0.0348 | G33: =F33*230 -> 8.004 | H33: 0 | J33: 218 | K33: =+J33+H33+I33 -> 218
A34: =ELEC!C31 -> 44011 | D34: =(C34+B34)/2 -> 0 | G34: =F34*230 -> 0 | K34: =+J34+H34+I34 -> 0
A35: =ELEC!C32 -> 44012 | D35: =(C35+B35)/2 -> 0 | G35: =F35*230 -> 0 | K35: =+J35+H35+I35 -> 0
F36: =AVERAGE(F6:F35) -> 0.018992857 | G36: =SUM(G6:G35) -> 122.314
D37: =SUM(D6:D35)/'EDl log'!A37 -> 24.285714
I40: http://www.accuweather.com/en/lb/lebanon-weather

Sheet tanks
B2: Tank 1 | D2: Tank 2 | F2: Tank 3 | H2: Tank 4 | J2: Tank 5 | L2: Tank 6 | N2: Tank 7 | P2: Tank 8 | R2: Tank 9 | T2: Tank 10 | V2: Tank 11 | Z2: Tank 1 | AB2: Tank 2 | AD2: Tank 3 | AF2: Tank 4 | AH2: Tank 5 | AJ2: Tank 6 | AL2: Tank 7
B3: 6670 | D3: =SUM(B3) -> 6670 | F3: =SUM(D3) -> 6670 | H3: =SUM(F3) -> 6670 | J3: =SUM(H3) -> 6670 | L3: =SUM(J3) -> 6670 | N3: =SUM(L3) -> 6670 | P3: =SUM(N3) -> 6670 | R3: =SUM(P3) -> 6670 | T3: =SUM(R3) -> 6670 | V3: =SUM(T3) -> 6670 | W3: =SUM(B3:V3) -> 73370 | Z3: 2800 | AB3: 2800 | AD3: 2800 | AF3: 2800 | AH3: 2800 | AJ3: 2800 | AL3: 2800 | AM3: =SUM(Z3:AL3) -> 19600 | AO3: =SUM(AM3+W3) -> 92970 | AR3: Total sotck | AS3: Diesel Cons Per day | AT3: Diesel Delivery | BE3: Genset Co | BF3: Steam | BG3: Boil | BH3: Outdoor temperature
B4: =B3/310 -> 21.516129 | D4: =SUM(B4) -> 21.516129 | F4: =SUM(D4) -> 21.516129 | H4: =SUM(F4) -> 21.516129 | J4: =SUM(H4) -> 21.516129 | L4: =SUM(J4) -> 21.516129 | N4: =SUM(L4) -> 21.516129 | P4: =SUM(N4) -> 21.516129 | R4: =SUM(P4) -> 21.516129 | T4: =SUM(R4) -> 21.516129 | V4: =SUM(T4) -> 21.516129 | Z4: =Z3/280 -> 10 | AA4: =AA3/280 -> 0 | AB4: =AB3/280 -> 10 | AC4: =AC3/280 -> 0 | AD4: =AD3/280 -> 10 | AE4: =AE3/280 -> 0 | AF4: =AF3/280 -> 10 | AG4: =AG3/280 -> 0 | ... AL4: =AL3/280 -> 10 | AT4: Delivery | AU4: Cost /L | AW4: Boiler+Steam | AX4: Generator | AZ4: Occupancy | BA4: AVE TEPM | BB4: AVE Humidity
A5: =ELEC!C2 -> 43982 | B5: =[2]tanks!B36 -> 179 | C5: =[2]tanks!C36 -> 3851.3871 | D5: =[2]tanks!D36 -> 179 | E5: =[2]tanks!E36 -> 3851.3871 | F5: =[2]tanks!F36 -> 179 | G5: =[2]tanks!G36 -> 3851.3871 | H5: =[2]tanks!H36 -> 179 | I5: =[2]tanks!I36 -> 3851.3871 | ... BH5: =[2]tanks!BH36 -> 0
A6: =ELEC!C3 -> 43983 | B6: ='B5'!B5 -> 175 | C6: =B6*$B$4 -> 3765.3226 | D6: =SUM(B6) -> 175 | E6: =D6*$B$4 -> 3765.3226 | F6: =SUM(D6) -> 175 | G6: =F6*$B$4 -> 3765.3226 | H6: =SUM(F6) -> 175 | I6: =H6*$B$4 -> 3765.3226 | J6: =SUM(H6) -> 175 | K6: =J6*$B$4 -> 3765.3226 | L6: =SUM(J6) -> 175 | M6: =L6*$B$4 -> 3765.3226 | N6: =SUM(L6) -> 175 | O6: =N6*$B$4 -> 3765.3226 | P6: =SUM(N6) -> 175 | Q6: =P6*$B$4 -> 3765.3226 | R6: =SUM(P6) -> 175 | S6: =R6*$B$4 -> 3765.3226 | T6: =SUM(R6) -> 175 | U6: =T6*$B$4 -> 3765.3226 | V6: =SUM(T6) -> 175 | W6: =V6*$B$4 -> 3765.3226 | X6: =SUM(Y6/73370) -> 0.56451613 | Y6: =SUM(C6+E6+G6+I6+K6+M6+O6+Q6+S6+U6+W6) -> 41418.548 | Z6: ='B5'!C5 -> 182 | AA6: =SUM(Z6*$Z$4) -> 1820 | AB6: =SUM(Z6) -> 182 | AC6: =SUM(AB6*$Z$4) -> 1820 | AD6: =SUM(AB6) -> 182 | AE6: =SUM(AD6*$Z$4) -> 1820 | AF6: =SUM(AD6) -> 182 | AG6: =SUM(AF6*$Z$4) -> 1820 | AH6: =SUM(AF6) -> 182 | AI6: =SUM(AH6*$Z$4) -> 1820 | AJ6: =SUM(AH6) -> 182 | AK6: =SUM(AJ6*$Z$4) -> 1820 | AL6: =SUM(AJ6) -> 182 | AM6: =SUM(AL6*$Z$4) -> 1820 | AN6: =SUM(AO6/19600) -> 0.65 | AO6: =SUM(AA6+AC6+AE6+AG6+AI6+AK6+AM6) -> 12740 | AQ6: =SUM(AR6/92970) -> 0.5825379 | AR6: =SUM(AO6+Y6) -> 54158.548 | AS6: =SUM(AR6-AR5-AT6) -> -1226.8097 | AT6: 0.1 | AU6: 0.1 | AV6: =IF(AT6>0,AU6,AV5) -> 0.1 | AW6: =-SUM('B5'!AI5) -> -452 | AX6: =-SUM(AW6-AS6) -> -774.80968 | AY6: =SUM(AX6+AW6) -> -1226.8097 | AZ6: =ELEC!A3 -> 0.0217 | BA6: ='General information '!D6 -> 22.5 | BB6: =SUM('General information '!E6) -> 0.61 | BC6: =IF(AR3>=AR6,0,1) -> 0 | BD6: 19222 | BE6: =(305/1185)*ELEC!Q4 -> 514.76793 | BG6: =#REF!-BE6 -> #REF! | BH6: 21
A7: =ELEC!C4 -> 43984 | B7: ='B5'!B6 -> 173 | C7: =B7*$B$4 -> 3722.2903 | D7: =SUM(B7) -> 173 | E7: =D7*$B$4 -> 3722.2903 | F7: =SUM(D7) -> 173 | G7: =F7*$B$4 -> 3722.2903 | H7: =SUM(F7) -> 173 | I7: =H7*$B$4 -> 3722.2903 | J7: =SUM(H7) -> 173 | K7: =J7*$B$4 -> 3722.2903 | L7: =SUM(J7) -> 173 | M7: =L7*$B$4 -> 3722.2903 | N7: =SUM(L7) -> 173 | O7: =N7*$B$4 -> 3722.2903 | P7: =SUM(N7) -> 173 | Q7: =P7*$B$4 -> 3722.2903 | R7: =SUM(P7) -> 173 | S7: =R7*$B$4 -> 3722.2903 | T7: =SUM(R7) -> 173 | U7: =T7*$B$4 -> 3722.2903 | V7: =SUM(T7) -> 173 | W7: =V7*$B$4 -> 3722.2903 | X7: =SUM(Y7/73370) -> 0.55806452 | Y7: =SUM(C7+E7+G7+I7+K7+M7+O7+Q7+S7+U7+W7) -> 40945.194 | Z7: ='B5'!C6 -> 179 | AA7: =SUM(Z7*$Z$4) -> 1790 | AB7: =SUM(Z7) -> 179 | AC7: =SUM(AB7*$Z$4) -> 1790 | AD7: =SUM(AB7) -> 179 | AE7: =SUM(AD7*$Z$4) -> 1790 | AF7: =SUM(AD7) -> 179 | AG7: =SUM(AF7*$Z$4) -> 1790 | AH7: =SUM(AF7) -> 179 | AI7: =SUM(AH7*$Z$4) -> 1790 | AJ7: =SUM(AH7) -> 179 | AK7: =SUM(AJ7*$Z$4) -> 1790 | AL7: =SUM(AJ7) -> 179 | AM7: =SUM(AL7*$Z$4) -> 1790 | AN7: =SUM(AO7/19600) -> 0.63928571 | AO7: =SUM(AA7+AC7+AE7+AG7+AI7+AK7+AM7) -> 12530 | AQ7: =SUM(AR7/92970) -> 0.57518763 | AR7: =SUM(AO7+Y7) -> 53475.194 | AS7: =SUM(AR7-AR6-AT7) -> -683.35484 | AV7: =IF(AT7>0,AU7,AV6) -> 0.1 | AW7: =-SUM('B5'!AI6) -> -296 | AX7: =-SUM(AW7-AS7) -> -387.35484 | AY7: =SUM(AX7+AW7) -> -683.35484 | AZ7: =ELEC!A4 -> 0.0087 | BA7: ='General information '!D7 -> 22 | BB7: =SUM('General information '!E7) -> 0.6 | BC7: 0 | BD7: 19222 | BE7: =(305/1185)*ELEC!Q5 -> 514.76793 | BG7: =#REF!-BE7 -> #REF! | BH7: 19
A8: =ELEC!C5 -> 43985 | B8: ='B5'!B7 -> 168 | C8: =B8*$B$4 -> 3614.7097 | D8: =SUM(B8) -> 168 | E8: =D8*$B$4 -> 3614.7097 | F8: =SUM(D8) -> 168 | G8: =F8*$B$4 -> 3614.7097 | H8: =SUM(F8) -> 168 | I8: =H8*$B$4 -> 3614.7097 | J8: =SUM(H8) -> 168 | K8: =J8*$B$4 -> 3614.7097 | L8: =SUM(J8) -> 168 | M8: =L8*$B$4 -> 3614.7097 | N8: =SUM(L8) -> 168 | O8: =N8*$B$4 -> 3614.7097 | P8: =SUM(N8) -> 168 | Q8: =P8*$B$4 -> 3614.7097 | R8: =SUM(P8) -> 168 | S8: =R8*$B$4 -> 3614.7097 | T8: =SUM(R8) -> 168 | U8: =T8*$B$4 -> 3614.7097 | V8: =SUM(T8) -> 168 | W8: =V8*$B$4 -> 3614.7097 | X8: =SUM(Y8/73370) -> 0.54193548 | Y8: =SUM(C8+E8+G8+I8+K8+M8+O8+Q8+S8+U8+W8) -> 39761.806 | Z8: ='B5'!C7 -> 173 | AA8: =SUM(Z8*$Z$4) -> 1730 | AB8: =SUM(Z8) -> 173 | AC8: =SUM(AB8*$Z$4) -> 1730 | AD8: =SUM(AB8) -> 173 | AE8: =SUM(AD8*$Z$4) -> 1730 | AF8: =SUM(AD8) -> 173 | AG8: =SUM(AF8*$Z$4) -> 1730 | AH8: =SUM(AF8) -> 173 | AI8: =SUM(AH8*$Z$4) -> 1730 | AJ8: =SUM(AH8) -> 173 | AK8: =SUM(AJ8*$Z$4) -> 1730 | AL8: =SUM(AJ8) -> 173 | AM8: =SUM(AL8*$Z$4) -> 1730 | AN8: =SUM(AO8/19600) -> 0.61785714 | AO8: =SUM(AA8+AC8+AE8+AG8+AI8+AK8+AM8) -> 12110 | AQ8: =SUM(AR8/92970) -> 0.55794134 | AR8: =SUM(AO8+Y8) -> 51871.806 | AS8: =SUM(AR8-AR7-AT8) -> -1603.3871 | AV8: =IF(AT8>0,AU8,AV7) -> 0.1 | AW8: =-SUM('B5'!AI7) -> -370.6 | AX8: =-SUM(AW8-AS8) -> -1232.7871 | AY8: =SUM(AX8+AW8) -> -1603.3871 | AZ8: =ELEC!A5 -> 0.0261 | BA8: ='General information '!D8 -> 23 | BB8: =SUM('General information '!E8) -> 0.6 | BC8: =IF(AR7>=AR8,0,1) -> 0 | BD8: 19222 | BE8: =(305/1185)*ELEC!Q6 -> 514.76793 | BG8: =#REF!-BE8 -> #REF! | BH8: 16
A9: =ELEC!C6 -> 43986 | B9: ='B5'!B8 -> 203 | C9: =B9*$B$4 -> 4367.7742 | D9: =SUM(B9) -> 203 | E9: =D9*$B$4 -> 4367.7742 | F9: =SUM(D9) -> 203 | G9: =F9*$B$4 -> 4367.7742 | H9: =SUM(F9) -> 203 | I9: =H9*$B$4 -> 4367.7742 | J9: =SUM(H9) -> 203 | K9: =J9*$B$4 -> 4367.7742 | L9: =SUM(J9) -> 203 | M9: =L9*$B$4 -> 4367.7742 | N9: =SUM(L9) -> 203 | O9: =N9*$B$4 -> 4367.7742 | P9: =SUM(N9) -> 203 | Q9: =P9*$B$4 -> 4367.7742 | R9: =SUM(P9) -> 203 | S9: =R9*$B$4 -> 4367.7742 | T9: =SUM(R9) -> 203 | U9: =T9*$B$4 -> 4367.7742 | V9: =SUM(T9) -> 203 | W9: =V9*$B$4 -> 4367.7742 | X9: =SUM(Y9/73370) -> 0.65483871 | Y9: =SUM(C9+E9+G9+I9+K9+M9+O9+Q9+S9+U9+W9) -> 48045.516 | Z9: ='B5'!C8 -> 210 | AA9: =SUM(Z9*$Z$4) -> 2100 | AB9: =SUM(Z9) -> 210 | AC9: =SUM(AB9*$Z$4) -> 2100 | AD9: =SUM(AB9) -> 210 | AE9: =SUM(AD9*$Z$4) -> 2100 | AF9: =SUM(AD9) -> 210 | AG9: =SUM(AF9*$Z$4) -> 2100 | AH9: =SUM(AF9) -> 210 | AI9: =SUM(AH9*$Z$4) -> 2100 | AJ9: =SUM(AH9) -> 210 | AK9: =SUM(AJ9*$Z$4) -> 2100 | AL9: =SUM(AJ9) -> 210 | AM9: =SUM(AL9*$Z$4) -> 2100 | AN9: =SUM(AO9/19600) -> 0.75 | AO9: =SUM(AA9+AC9+AE9+AG9+AI9+AK9+AM9) -> 14700 | AQ9: =SUM(AR9/92970) -> 0.67490068 | AR9: =SUM(AO9+Y9) -> 62745.516 | AS9: =SUM(AR9-AR8-AT9) -> 520.70968 | AT9: 10353 | AU9: 0.34 | AV9: =IF(AT9>0,AU9,AV8) -> 0.34 | AW9: =-SUM('B5'!AI8) -> -628 | AX9: =-SUM(AW9-AS9) -> 1148.7097 | AY9: =SUM(AX9+AW9) -> 520.70968 | AZ9: =ELEC!A6 -> 0.0217 | BA9: ='General information '!D9 -> 22 | BB9: =SUM('General information '!E9) -> 0.62 | BC9: =IF(AR8>=AR9,0,1) -> 1 | BD9: 19222 | BE9: =(305/1185)*ELEC!Q7 -> 514.76793 | BG9: =#REF!-BE9 -> #REF! | BH9: 18
A10: =ELEC!C7 -> 43987 | B10: ='B5'!B9 -> 199 | C10: =B10*$B$4 -> 4281.7097 | D10: =SUM(B10) -> 199 | E10: =D10*$B$4 -> 4281.7097 | F10: =SUM(D10) -> 199 | G10: =F10*$B$4 -> 4281.7097 | H10: =SUM(F10) -> 199 | I10: =H10*$B$4 -> 4281.7097 | J10: =SUM(H10) -> 199 | K10: =J10*$B$4 -> 4281.7097 | L10: =SUM(J10) -> 199 | M10: =L10*$B$4 -> 4281.7097 | N10: =SUM(L10) -> 199 | O10: =N10*$B$4 -> 4281.7097 | P10: =SUM(N10) -> 199 | Q10: =P10*$B$4 -> 4281.7097 | R10: =SUM(P10) -> 199 | S10: =R10*$B$4 -> 4281.7097 | T10: =SUM(R10) -> 199 | U10: =T10*$B$4 -> 4281.7097 | V10: =SUM(T10) -> 199 | W10: =V10*$B$4 -> 4281.7097 | X10: =SUM(Y10/73370) -> 0.64193548 | Y10: =SUM(C10+E10+G10+I10+K10+M10+O10+Q10+S10+U10+W10) -> 47098.806 | Z10: ='B5'!C9 -> 205 | AA10: =SUM(Z10*$Z$4) -> 2050 | AB10: =SUM(Z10) -> 205 | AC10: =SUM(AB10*$Z$4) -> 2050 | AD10: =SUM(AB10) -> 205 | AE10: =SUM(AD10*$Z$4) -> 2050 | AF10: =SUM(AD10) -> 205 | AG10: =SUM(AF10*$Z$4) -> 2050 | AH10: =SUM(AF10) -> 205 | AI10: =SUM(AH10*$Z$4) -> 2050 | AJ10: =SUM(AH10) -> 205 | AK10: =SUM(AJ10*$Z$4) -> 2050 | AL10: =SUM(AJ10) -> 205 | AM10: =SUM(AL10*$Z$4) -> 2050 | AN10: =SUM(AO10/19600) -> 0.73214286 | AO10: =SUM(AA10+AC10+AE10+AG10+AI10+AK10+AM10) -> 14350 | AQ10: =SUM(AR10/92970) -> 0.66095306 | AR10: =SUM(AO10+Y10) -> 61448.806 | AS10: =SUM(AR10-AR9-AT10) -> -1296.7097 | AV10: =IF(AT10>0,AU10,AV9) -> 0.34 | AW10: =-SUM('B5'!AI9) -> -334 | AX10: =-SUM(AW10-AS10) -> -962.70968 | AY10: =SUM(AX10+AW10) -> -1296.7097 | AZ10: =ELEC!A7 -> 0.013 | BA10: ='General information '!D10 -> 21 | BB10: =SUM('General information '!E10) -> 0.6 | BC10: =IF(AR9>=AR10,0,1) -> 0 | BD10: 19222 | BE10: =(305/1185)*ELEC!Q8 -> 514.76793 | BG10: =#REF!-BE10 -> #REF! | BH10: 16
A11: =ELEC!C8 -> 43988 | B11: ='B5'!B10 -> 196 | C11: =B11*$B$4 -> 4217.1613 | D11: =SUM(B11) -> 196 | E11: =D11*$B$4 -> 4217.1613 | F11: =SUM(D11) -> 196 | G11: =F11*$B$4 -> 4217.1613 | H11: =SUM(F11) -> 196 | I11: =H11*$B$4 -> 4217.1613 | J11: =SUM(H11) -> 196 | K11: =J11*$B$4 -> 4217.1613 | L11: =SUM(J11) -> 196 | M11: =L11*$B$4 -> 4217.1613 | N11: =SUM(L11) -> 196 | O11: =N11*$B$4 -> 4217.1613 | P11: =SUM(N11) -> 196 | Q11: =P11*$B$4 -> 4217.1613 | R11: =SUM(P11) -> 196 | S11: =R11*$B$4 -> 4217.1613 | T11: =SUM(R11) -> 196 | U11: =T11*$B$4 -> 4217.1613 | V11: =SUM(T11) -> 196 | W11: =V11*$B$4 -> 4217.1613 | X11: =SUM(Y11/73370) -> 0.63225806 | Y11: =SUM(C11+E11+G11+I11+K11+M11+O11+Q11+S11+U11+W11) -> 46388.774 | Z11: ='B5'!C10 -> 202 | AA11: =SUM(Z11*$Z$4) -> 2020 | AB11: =SUM(Z11) -> 202 | AC11: =SUM(AB11*$Z$4) -> 2020 | AD11: =SUM(AB11) -> 202 | AE11: =SUM(AD11*$Z$4) -> 2020 | AF11: =SUM(AD11) -> 202 | AG11: =SUM(AF11*$Z$4) -> 2020 | AH11: =SUM(AF11) -> 202 | AI11: =SUM(AH11*$Z$4) -> 2020 | AJ11: =SUM(AH11) -> 202 | AK11: =SUM(AJ11*$Z$4) -> 2020 | AL11: =SUM(AJ11) -> 202 | AM11: =SUM(AL11*$Z$4) -> 2020 | AN11: =SUM(AO11/19600) -> 0.72142857 | AO11: =SUM(AA11+AC11+AE11+AG11+AI11+AK11+AM11) -> 14140 | AQ11: =SUM(AR11/92970) -> 0.65105705 | AR11: =SUM(AO11+Y11) -> 60528.774 | AS11: =SUM(AR11-AR10-AT11) -> -920.03226 | AV11: =IF(AT11>0,AU11,AV10) -> 0.34 | AW11: =-SUM('B5'!AI10) -> -391 | AX11: =-SUM(AW11-AS11) -> -529.03226 | AY11: =SUM(AX11+AW11) -> -920.03226 | AZ11: =ELEC!A8 -> 0.0217 | BA11: ='General information '!D11 -> 22 | BB11: =SUM('General information '!E11) -> 0.63 | BC11: =IF(AR10>=AR11,0,1) -> 0 | BD11: 19222 | BE11: =(305/1185)*ELEC!Q9 -> 514.76793 | BG11: =#REF!-BE11 -> #REF! | BH11: 16.5
A12: =ELEC!C9 -> 43989 | B12: ='B5'!B11 -> 192 | C12: =B12*$B$4 -> 4131.0968 | D12: =SUM(B12) -> 192 | E12: =D12*$B$4 -> 4131.0968 | F12: =SUM(D12) -> 192 | G12: =F12*$B$4 -> 4131.0968 | H12: =SUM(F12) -> 192 | I12: =H12*$B$4 -> 4131.0968 | J12: =SUM(H12) -> 192 | K12: =J12*$B$4 -> 4131.0968 | L12: =SUM(J12) -> 192 | M12: =L12*$B$4 -> 4131.0968 | N12: =SUM(L12) -> 192 | O12: =N12*$B$4 -> 4131.0968 | P12: =SUM(N12) -> 192 | Q12: =P12*$B$4 -> 4131.0968 | R12: =SUM(P12) -> 192 | S12: =R12*$B$4 -> 4131.0968 | T12: =SUM(R12) -> 192 | U12: =T12*$B$4 -> 4131.0968 | V12: =SUM(T12) -> 192 | W12: =V12*$B$4 -> 4131.0968 | X12: =SUM(Y12/73370) -> 0.61935484 | Y12: =SUM(C12+E12+G12+I12+K12+M12+O12+Q12+S12+U12+W12) -> 45442.065 | Z12: ='B5'!C11 -> 198 | AA12: =SUM(Z12*$Z$4) -> 1980 | AB12: =SUM(Z12) -> 198 | AC12: =SUM(AB12*$Z$4) -> 1980 | AD12: =SUM(AB12) -> 198 | AE12: =SUM(AD12*$Z$4) -> 1980 | AF12: =SUM(AD12) -> 198 | AG12: =SUM(AF12*$Z$4) -> 1980 | AH12: =SUM(AF12) -> 198 | AI12: =SUM(AH12*$Z$4) -> 1980 | AJ12: =SUM(AH12) -> 198 | AK12: =SUM(AJ12*$Z$4) -> 1980 | AL12: =SUM(AJ12) -> 198 | AM12: =SUM(AL12*$Z$4) -> 1980 | AN12: =SUM(AO12/19600) -> 0.70714286 | AO12: =SUM(AA12+AC12+AE12+AG12+AI12+AK12+AM12) -> 13860 | AQ12: =SUM(AR12/92970) -> 0.63786237 | AR12: =SUM(AO12+Y12) -> 59302.065 | AS12: =SUM(AR12-AR11-AT12) -> -1226.7097 | AV12: =IF(AT12>0,AU12,AV11) -> 0.34 | AW12: =-SUM('B5'!AI11) -> -363 | AX12: =-SUM(AW12-AS12) -> -863.70968 | AY12: =SUM(AX12+AW12) -> -1226.7097 | AZ12: =ELEC!A9 -> 0.0174 | BA12: ='General information '!D12 -> 24 | BB12: =SUM('General information '!E12) -> 0.7 | BC12: =IF(AR11>=AR12,0,1) -> 0 | BD12: 19222 | BE12: =(305/1185)*ELEC!Q10 -> 514.76793 | BG12: =#REF!-BE12 -> #REF! | BH12: 15.5
A13: =ELEC!C10 -> 43990 | B13: ='B5'!B12 -> 188 | C13: =B13*$B$4 -> 4045.0323 | D13: =SUM(B13) -> 188 | E13: =D13*$B$4 -> 4045.0323 | F13: =SUM(D13) -> 188 | G13: =F13*$B$4 -> 4045.0323 | H13: =SUM(F13) -> 188 | I13: =H13*$B$4 -> 4045.0323 | J13: =SUM(H13) -> 188 | K13: =J13*$B$4 -> 4045.0323 | L13: =SUM(J13) -> 188 | M13: =L13*$B$4 -> 4045.0323 | N13: =SUM(L13) -> 188 | O13: =N13*$B$4 -> 4045.0323 | P13: =SUM(N13) -> 188 | Q13: =P13*$B$4 -> 4045.0323 | R13: =SUM(P13) -> 188 | S13: =R13*$B$4 -> 4045.0323 | T13: =SUM(R13) -> 188 | U13: =T13*$B$4 -> 4045.0323 | V13: =SUM(T13) -> 188 | W13: =V13*$B$4 -> 4045.0323 | X13: =SUM(Y13/73370) -> 0.60645161 | Y13: =SUM(C13+E13+G13+I13+K13+M13+O13+Q13+S13+U13+W13) -> 44495.355 | Z13: ='B5'!C12 -> 196 | AA13: =SUM(Z13*$Z$4) -> 1960 | AB13: =SUM(Z13) -> 196 | AC13: =SUM(AB13*$Z$4) -> 1960 | AD13: =SUM(AB13) -> 196 | AE13: =SUM(AD13*$Z$4) -> 1960 | AF13: =SUM(AD13) -> 196 | AG13: =SUM(AF13*$Z$4) -> 1960 | AH13: =SUM(AF13) -> 196 | AI13: =SUM(AH13*$Z$4) -> 1960 | AJ13: =SUM(AH13) -> 196 | AK13: =SUM(AJ13*$Z$4) -> 1960 | AL13: =SUM(AJ13) -> 196 | AM13: =SUM(AL13*$Z$4) -> 1960 | AN13: =SUM(AO13/19600) -> 0.7 | AO13: =SUM(AA13+AC13+AE13+AG13+AI13+AK13+AM13) -> 13720 | AQ13: =SUM(AR13/92970) -> 0.62617355 | AR13: =SUM(AO13+Y13) -> 58215.355 | AS13: =SUM(AR13-AR12-AT13) -> -1086.7097 | AV13: =IF(AT13>0,AU13,AV12) -> 0.34 | AW13: =-SUM('B5'!AI12) -> -360 | AX13: =-SUM(AW13-AS13) -> -726.70968 | AY13: =SUM(AX13+AW13) -> -1086.7097 | AZ13: =ELEC!A10 -> 0.013 | BA13: ='General information '!D13 -> 24 | BB13: =SUM('General information '!E13) -> 0.72 | BC13: =IF(AR12>=AR13,0,1) -> 0 | BD13: 19222 | BE13: =(305/1185)*ELEC!Q11 -> 514.76793 | BG13: =#REF!-BE13 -> #REF!
A14: =ELEC!C11 -> 43991 | B14: ='B5'!B13 -> 185.2 | C14: =B14*$B$4 -> 3984.7871 | D14: =SUM(B14) -> 185.2 | E14: =D14*$B$4 -> 3984.7871 | F14: =SUM(D14) -> 185.2 | G14: =F14*$B$4 -> 3984.7871 | H14: =SUM(F14) -> 185.2 | I14: =H14*$B$4 -> 3984.7871 | J14: =SUM(H14) -> 185.2 | K14: =J14*$B$4 -> 3984.7871 | L14: =SUM(J14) -> 185.2 | M14: =L14*$B$4 -> 3984.7871 | N14: =SUM(L14) -> 185.2 | O14: =N14*$B$4 -> 3984.7871 | P14: =SUM(N14) -> 185.2 | Q14: =P14*$B$4 -> 3984.7871 | R14: =SUM(P14) -> 185.2 | S14: =R14*$B$4 -> 3984.7871 | T14: =SUM(R14) -> 185.2 | U14: =T14*$B$4 -> 3984.7871 | V14: =SUM(T14) -> 185.2 | W14: =V14*$B$4 -> 3984.7871 | X14: =SUM(Y14/73370) -> 0.59741935 | Y14: =SUM(C14+E14+G14+I14+K14+M14+O14+Q14+S14+U14+W14) -> 43832.658 | Z14: ='B5'!C13 -> 191.3 | AA14: =SUM(Z14*$Z$4) -> 1913 | AB14: =SUM(Z14) -> 191.3 | AC14: =SUM(AB14*$Z$4) -> 1913 | AD14: =SUM(AB14) -> 191.3 | AE14: =SUM(AD14*$Z$4) -> 1913 | AF14: =SUM(AD14) -> 191.3 | AG14: =SUM(AF14*$Z$4) -> 1913 | AH14: =SUM(AF14) -> 191.3 | AI14: =SUM(AH14*$Z$4) -> 1913 | AJ14: =SUM(AH14) -> 191.3 | AK14: =SUM(AJ14*$Z$4) -> 1913 | AL14: =SUM(AJ14) -> 191.3 | AM14: =SUM(AL14*$Z$4) -> 1913 | AN14: =SUM(AO14/19600) -> 0.68321429 | AO14: =SUM(AA14+AC14+AE14+AG14+AI14+AK14+AM14) -> 13391 | AQ14: =SUM(AR14/92970) -> 0.6155067 | AR14: =SUM(AO14+Y14) -> 57223.658 | AS14: =SUM(AR14-AR13-AT14) -> -991.69677 | AV14: =IF(AT14>0,AU14,AV13) -> 0.34 | AW14: =-SUM('B5'!AI13) -> -282 | AX14: =-SUM(AW14-AS14) -> -709.69677 | AY14: =SUM(AX14+AW14) -> -991.69677 | AZ14: =ELEC!A11 -> 0.0174 | BA14: ='General information '!D14 -> 24 | BB14: =SUM('General information '!E14) -> 0.68 | BC14: =IF(AR13>=AR14,0,1) -> 0 | BD14: 19222 | BE14: =(305/1185)*ELEC!Q12 -> 1544.3038 | BG14: =#REF!-BE14 -> #REF!
A15: =ELEC!C12 -> 43992 | B15: ='B5'!B14 -> 177.2 | C15: =B15*$B$4 -> 3812.6581 | D15: =SUM(B15) -> 177.2 | E15: =D15*$B$4 -> 3812.6581 | F15: =SUM(D15) -> 177.2 | G15: =F15*$B$4 -> 3812.6581 | H15: =SUM(F15) -> 177.2 | I15: =H15*$B$4 -> 3812.6581 | J15: =SUM(H15) -> 177.2 | K15: =J15*$B$4 -> 3812.6581 | L15: =SUM(J15) -> 177.2 | M15: =L15*$B$4 -> 3812.6581 | N15: =SUM(L15) -> 177.2 | O15: =N15*$B$4 -> 3812.6581 | P15: =SUM(N15) -> 177.2 | Q15: =P15*$B$4 -> 3812.6581 | R15: =SUM(P15) -> 177.2 | S15: =R15*$B$4 -> 3812.6581 | T15: =SUM(R15) -> 177.2 | U15: =T15*$B$4 -> 3812.6581 | V15: =SUM(T15) -> 177.2 | W15: =V15*$B$4 -> 3812.6581 | X15: =SUM(Y15/73370) -> 0.5716129 | Y15: =SUM(C15+E15+G15+I15+K15+M15+O15+Q15+S15+U15+W15) -> 41939.239 | Z15: ='B5'!C14 -> 183.5 | AA15: =SUM(Z15*$Z$4) -> 1835 | AB15: =SUM(Z15) -> 183.5 | AC15: =SUM(AB15*$Z$4) -> 1835 | AD15: =SUM(AB15) -> 183.5 | AE15: =SUM(AD15*$Z$4) -> 1835 | AF15: =SUM(AD15) -> 183.5 | AG15: =SUM(AF15*$Z$4) -> 1835 | AH15: =SUM(AF15) -> 183.5 | AI15: =SUM(AH15*$Z$4) -> 1835 | AJ15: =SUM(AH15) -> 183.5 | AK15: =SUM(AJ15*$Z$4) -> 1835 | AL15: =SUM(AJ15) -> 183.5 | AM15: =SUM(AL15*$Z$4) -> 1835 | AN15: =SUM(AO15/19600) -> 0.65535714 | AO15: =SUM(AA15+AC15+AE15+AG15+AI15+AK15+AM15) -> 12845 | AQ15: =SUM(AR15/92970) -> 0.58926792 | AR15: =SUM(AO15+Y15) -> 54784.239 | AS15: =SUM(AR15-AR14-AT15) -> -2439.4194 | AV15: =IF(AT15>0,AU15,AV14) -> 0.34 | AW15: =-SUM('B5'!AI14) -> -600.4 | AX15: =-SUM(AW15-AS15) -> -1839.0194 | AY15: =SUM(AX15+AW15) -> -2439.4194 | AZ15: =ELEC!A12 -> 0.0174 | BA15: ='General information '!D15 -> 24 | BB15: =SUM('General information '!E15) -> 0.65 | BC15: =IF(AR14>=AR15,0,1) -> 0 | BD15: 19222 | BE15: =(305/1185)*ELEC!Q13 -> 1286.9198 | BG15: =#REF!-BE15 -> #REF!
A16: =ELEC!C13 -> 43993 | B16: ='B5'!B15 -> 169 | C16: =B16*$B$4 -> 3636.2258 | D16: =SUM(B16) -> 169 | E16: =D16*$B$4 -> 3636.2258 | F16: =SUM(D16) -> 169 | G16: =F16*$B$4 -> 3636.2258 | H16: =SUM(F16) -> 169 | I16: =H16*$B$4 -> 3636.2258 | J16: =SUM(H16) -> 169 | K16: =J16*$B$4 -> 3636.2258 | L16: =SUM(J16) -> 169 | M16: =L16*$B$4 -> 3636.2258 | N16: =SUM(L16) -> 169 | O16: =N16*$B$4 -> 3636.2258 | P16: =SUM(N16) -> 169 | Q16: =P16*$B$4 -> 3636.2258 | R16: =SUM(P16) -> 169 | S16: =R16*$B$4 -> 3636.2258 | T16: =SUM(R16) -> 169 | U16: =T16*$B$4 -> 3636.2258 | V16: =SUM(T16) -> 169 | W16: =V16*$B$4 -> 3636.2258 | X16: =SUM(Y16/73370) -> 0.54516129 | Y16: =SUM(C16+E16+G16+I16+K16+M16+O16+Q16+S16+U16+W16) -> 39998.484 | Z16: ='B5'!C15 -> 175 | AA16: =SUM(Z16*$Z$4) -> 1750 | AB16: =SUM(Z16) -> 175 | AC16: =SUM(AB16*$Z$4) -> 1750 | AD16: =SUM(AB16) -> 175 | AE16: =SUM(AD16*$Z$4) -> 1750 | AF16: =SUM(AD16) -> 175 | AG16: =SUM(AF16*$Z$4) -> 1750 | AH16: =SUM(AF16) -> 175 | AI16: =SUM(AH16*$Z$4) -> 1750 | AJ16: =SUM(AH16) -> 175 | AK16: =SUM(AJ16*$Z$4) -> 1750 | AL16: =SUM(AJ16) -> 175 | AM16: =SUM(AL16*$Z$4) -> 1750 | AN16: =SUM(AO16/19600) -> 0.625 | AO16: =SUM(AA16+AC16+AE16+AG16+AI16+AK16+AM16) -> 12250 | AQ16: =SUM(AR16/92970) -> 0.56199294 | AR16: =SUM(AO16+Y16) -> 52248.484 | AS16: =SUM(AR16-AR15-AT16) -> -2535.7548 | AV16: =IF(AT16>0,AU16,AV15) -> 0.34 | AW16: =-SUM('B5'!AI15) -> -368.1 | AX16: =-SUM(AW16-AS16) -> -2167.6548 | AY16: =SUM(AX16+AW16) -> -2535.7548 | AZ16: =ELEC!A13 -> 0.013 | BA16: ='General information '!D16 -> 24 | BB16: =SUM('General information '!E16) -> 0.68 | BC16: =IF(AR15>=AR16,0,1) -> 0 | BD16: 19222 | BE16: =(305/1185)*ELEC!Q14 -> 1544.3038 | BG16: =#REF!-BE16 -> #REF!
A17: =ELEC!C14 -> 43994 | B17: ='B5'!B16 -> 161.5 | C17: =B17*$B$4 -> 3474.8548 | D17: =SUM(B17) -> 161.5 | E17: =D17*$B$4 -> 3474.8548 | F17: =SUM(D17) -> 161.5 | G17: =F17*$B$4 -> 3474.8548 | H17: =SUM(F17) -> 161.5 | I17: =H17*$B$4 -> 3474.8548 | J17: =SUM(H17) -> 161.5 | K17: =J17*$B$4 -> 3474.8548 | L17: =SUM(J17) -> 161.5 | M17: =L17*$B$4 -> 3474.8548 | N17: =SUM(L17) -> 161.5 | O17: =N17*$B$4 -> 3474.8548 | P17: =SUM(N17) -> 161.5 | Q17: =P17*$B$4 -> 3474.8548 | R17: =SUM(P17) -> 161.5 | S17: =R17*$B$4 -> 3474.8548 | T17: =SUM(R17) -> 161.5 | U17: =T17*$B$4 -> 3474.8548 | V17: =SUM(T17) -> 161.5 | W17: =V17*$B$4 -> 3474.8548 | X17: =SUM(Y17/73370) -> 0.52096774 | Y17: =SUM(C17+E17+G17+I17+K17+M17+O17+Q17+S17+U17+W17) -> 38223.403 | Z17: ='B5'!C16 -> 168 | AA17: =SUM(Z17*$Z$4) -> 1680 | AB17: =SUM(Z17) -> 168 | AC17: =SUM(AB17*$Z$4) -> 1680 | AD17: =SUM(AB17) -> 168 | AE17: =SUM(AD17*$Z$4) -> 1680 | AF17: =SUM(AD17) -> 168 | AG17: =SUM(AF17*$Z$4) -> 1680 | AH17: =SUM(AF17) -> 168 | AI17: =SUM(AH17*$Z$4) -> 1680 | AJ17: =SUM(AH17) -> 168 | AK17: =SUM(AJ17*$Z$4) -> 1680 | AL17: =SUM(AJ17) -> 168 | AM17: =SUM(AL17*$Z$4) -> 1680 | AN17: =SUM(AO17/19600) -> 0.6 | AO17: =SUM(AA17+AC17+AE17+AG17+AI17+AK17+AM17) -> 11760 | AQ17: =SUM(AR17/92970) -> 0.53762938 | AR17: =SUM(AO17+Y17) -> 49983.403 | AS17: =SUM(AR17-AR16-AT17) -> -2265.0806 | AV17: =IF(AT17>0,AU17,AV16) -> 0.34 | AW17: =-SUM('B5'!AI16) -> -366 | AX17: =-SUM(AW17-AS17) -> -1899.0806 | AY17: =SUM(AX17+AW17) -> -2265.0806 | AZ17: =ELEC!A14 -> 0.03 | BA17: ='General information '!D17 -> 23.5 | BB17: =SUM('General information '!E17) -> 0.42 | BC17: =IF(AR16>=AR17,0,1) -> 0 | BD17: 19222 | BE17: =(305/1185)*ELEC!Q15 -> 1544.3038 | BG17: =#REF!-BE17 -> #REF!
A18: =ELEC!C15 -> 43995 | B18: ='B5'!B17 -> 155 | C18: =B18*$B$4 -> 3335 | D18: =SUM(B18) -> 155 | E18: =D18*$B$4 -> 3335 | F18: =SUM(D18) -> 155 | G18: =F18*$B$4 -> 3335 | H18: =SUM(F18) -> 155 | I18: =H18*$B$4 -> 3335 | J18: =SUM(H18) -> 155 | K18: =J18*$B$4 -> 3335 | L18: =SUM(J18) -> 155 | M18: =L18*$B$4 -> 3335 | N18: =SUM(L18) -> 155 | O18: =N18*$B$4 -> 3335 | P18: =SUM(N18) -> 155 | Q18: =P18*$B$4 -> 3335 | R18: =SUM(P18) -> 155 | S18: =R18*$B$4 -> 3335 | T18: =SUM(R18) -> 155 | U18: =T18*$B$4 -> 3335 | V18: =SUM(T18) -> 155 | W18: =V18*$B$4 -> 3335 | X18: =SUM(Y18/73370) -> 0.5 | Y18: =SUM(C18+E18+G18+I18+K18+M18+O18+Q18+S18+U18+W18) -> 36685 | Z18: ='B5'!C17 -> 161 | AA18: =SUM(Z18*$Z$4) -> 1610 | AB18: =SUM(Z18) -> 161 | AC18: =SUM(AB18*$Z$4) -> 1610 | AD18: =SUM(AB18) -> 161 | AE18: =SUM(AD18*$Z$4) -> 1610 | AF18: =SUM(AD18) -> 161 | AG18: =SUM(AF18*$Z$4) -> 1610 | AH18: =SUM(AF18) -> 161 | AI18: =SUM(AH18*$Z$4) -> 1610 | AJ18: =SUM(AH18) -> 161 | AK18: =SUM(AJ18*$Z$4) -> 1610 | AL18: =SUM(AJ18) -> 161 | AM18: =SUM(AL18*$Z$4) -> 1610 | AN18: =SUM(AO18/19600) -> 0.575 | AO18: =SUM(AA18+AC18+AE18+AG18+AI18+AK18+AM18) -> 11270 | AQ18: =SUM(AR18/92970) -> 0.51581155 | AR18: =SUM(AO18+Y18) -> 47955 | AS18: =SUM(AR18-AR17-AT18) -> -2028.4032 | AV18: =IF(AT18>0,AU18,AV17) -> 0.34 | AW18: =-SUM('B5'!AI17) -> -319 | AX18: =-SUM(AW18-AS18) -> -1709.4032 | AY18: =SUM(AX18+AW18) -> -2028.4032 | AZ18: =ELEC!A15 -> 0.0174 | BA18: ='General information '!D18 -> 22.5 | BB18: =SUM('General information '!E18) -> 0.47 | BC18: =IF(AR17>=AR18,0,1) -> 0 | BD18: 19222 | BE18: =(305/1185)*ELEC!Q16 -> 772.1519 | BG18: =#REF!-BE18 -> #REF!
A19: =ELEC!C16 -> 43996 | B19: ='B5'!B18 -> 150 | C19: =B19*$B$4 -> 3227.4194 | D19: =SUM(B19) -> 150 | E19: =D19*$B$4 -> 3227.4194 | F19: =SUM(D19) -> 150 | G19: =F19*$B$4 -> 3227.4194 | H19: =SUM(F19) -> 150 | I19: =H19*$B$4 -> 3227.4194 | J19: =SUM(H19) -> 150 | K19: =J19*$B$4 -> 3227.4194 | L19: =SUM(J19) -> 150 | M19: =L19*$B$4 -> 3227.4194 | N19: =SUM(L19) -> 150 | O19: =N19*$B$4 -> 3227.4194 | P19: =SUM(N19) -> 150 | Q19: =P19*$B$4 -> 3227.4194 | R19: =SUM(P19) -> 150 | S19: =R19*$B$4 -> 3227.4194 | T19: =SUM(R19) -> 150 | U19: =T19*$B$4 -> 3227.4194 | V19: =SUM(T19) -> 150 | W19: =V19*$B$4 -> 3227.4194 | X19: =SUM(Y19/73370) -> 0.48387097 | Y19: =SUM(C19+E19+G19+I19+K19+M19+O19+Q19+S19+U19+W19) -> 35501.613 | Z19: ='B5'!C18 -> 156 | AA19: =SUM(Z19*$Z$4) -> 1560 | AB19: =SUM(Z19) -> 156 | AC19: =SUM(AB19*$Z$4) -> 1560 | AD19: =SUM(AB19) -> 156 | AE19: =SUM(AD19*$Z$4) -> 1560 | AF19: =SUM(AD19) -> 156 | AG19: =SUM(AF19*$Z$4) -> 1560 | AH19: =SUM(AF19) -> 156 | AI19: =SUM(AH19*$Z$4) -> 1560 | AJ19: =SUM(AH19) -> 156 | AK19: =SUM(AJ19*$Z$4) -> 1560 | AL19: =SUM(AJ19) -> 156 | AM19: =SUM(AL19*$Z$4) -> 1560 | AN19: =SUM(AO19/19600) -> 0.55714286 | AO19: =SUM(AA19+AC19+AE19+AG19+AI19+AK19+AM19) -> 10920 | AQ19: =SUM(AR19/92970) -> 0.4993182 | AR19: =SUM(AO19+Y19) -> 46421.613 | AS19: =SUM(AR19-AR18-AT19) -> -1533.3871 | AV19: =IF(AT19>0,AU19,AV18) -> 0.34 | AW19: =-SUM('B5'!AI18) -> -302 | AX19: =-SUM(AW19-AS19) -> -1231.3871 | AY19: =SUM(AX19+AW19) -> -1533.3871 | AZ19: =ELEC!A16 -> 0.013 | BA19: ='General information '!D19 -> 23.5 | BB19: =SUM('General information '!E19) -> 0.65 | BC19: =IF(AR18>=AR19,0,1) -> 0 | BD19: 19222 | BE19: =(305/1185)*ELEC!Q17 -> 1544.3038 | BG19: =#REF!-BE19 -> #REF!
A20: =ELEC!C17 -> 43997 | B20: ='B5'!B19 -> 172 | C20: =B20*$B$4 -> 3700.7742 | D20: =SUM(B20) -> 172 | E20: =D20*$B$4 -> 3700.7742 | F20: =SUM(D20) -> 172 | G20: =F20*$B$4 -> 3700.7742 | H20: =SUM(F20) -> 172 | I20: =H20*$B$4 -> 3700.7742 | J20: =SUM(H20) -> 172 | K20: =J20*$B$4 -> 3700.7742 | L20: =SUM(J20) -> 172 | M20: =L20*$B$4 -> 3700.7742 | N20: =SUM(L20) -> 172 | O20: =N20*$B$4 -> 3700.7742 | P20: =SUM(N20) -> 172 | Q20: =P20*$B$4 -> 3700.7742 | R20: =SUM(P20) -> 172 | S20: =R20*$B$4 -> 3700.7742 | T20: =SUM(R20) -> 172 | U20: =T20*$B$4 -> 3700.7742 | V20: =SUM(T20) -> 172 | W20: =V20*$B$4 -> 3700.7742 | X20: =SUM(Y20/73370) -> 0.55483871 | Y20: =SUM(C20+E20+G20+I20+K20+M20+O20+Q20+S20+U20+W20) -> 40708.516 | Z20: ='B5'!C19 -> 178 | AA20: =SUM(Z20*$Z$4) -> 1780 | AB20: =SUM(Z20) -> 178 | AC20: =SUM(AB20*$Z$4) -> 1780 | AD20: =SUM(AB20) -> 178 | AE20: =SUM(AD20*$Z$4) -> 1780 | AF20: =SUM(AD20) -> 178 | AG20: =SUM(AF20*$Z$4) -> 1780 | AH20: =SUM(AF20) -> 178 | AI20: =SUM(AH20*$Z$4) -> 1780 | AJ20: =SUM(AH20) -> 178 | AK20: =SUM(AJ20*$Z$4) -> 1780 | AL20: =SUM(AJ20) -> 178 | AM20: =SUM(AL20*$Z$4) -> 1780 | AN20: =SUM(AO20/19600) -> 0.63571429 | AO20: =SUM(AA20+AC20+AE20+AG20+AI20+AK20+AM20) -> 12460 | AQ20: =SUM(AR20/92970) -> 0.57188895 | AR20: =SUM(AO20+Y20) -> 53168.516 | AS20: =SUM(AR20-AR19-AT20) -> -1553.0968 | AT20: 8300 | AU20: 0.36 | AV20: =IF(AT20>0,AU20,AV19) -> 0.36 | AW20: =-SUM('B5'!AI19) -> -352 | AX20: =-SUM(AW20-AS20) -> -1201.0968 | AY20: =SUM(AX20+AW20) -> -1553.0968 | AZ20: =ELEC!A17 -> 0.013 | BA20: ='General information '!D20 -> 23 | BB20: =SUM('General information '!E20) -> 0.62 | BC20: =IF(AR19>=AR20,0,1) -> 1 | BD20: 19222 | BE20: =(305/1185)*ELEC!Q18 -> 1286.9198 | BG20: =#REF!-BE20 -> #REF!
A21: =ELEC!C18 -> 43998 | B21: ='B5'!B20 -> 166 | C21: =B21*$B$4 -> 3571.6774 | D21: =SUM(B21) -> 166 | E21: =D21*$B$4 -> 3571.6774 | F21: =SUM(D21) -> 166 | G21: =F21*$B$4 -> 3571.6774 | H21: =SUM(F21) -> 166 | I21: =H21*$B$4 -> 3571.6774 | J21: =SUM(H21) -> 166 | K21: =J21*$B$4 -> 3571.6774 | L21: =SUM(J21) -> 166 | M21: =L21*$B$4 -> 3571.6774 | N21: =SUM(L21) -> 166 | O21: =N21*$B$4 -> 3571.6774 | P21: =SUM(N21) -> 166 | Q21: =P21*$B$4 -> 3571.6774 | R21: =SUM(P21) -> 166 | S21: =R21*$B$4 -> 3571.6774 | T21: =SUM(R21) -> 166 | U21: =T21*$B$4 -> 3571.6774 | V21: =SUM(T21) -> 166 | W21: =V21*$B$4 -> 3571.6774 | X21: =SUM(Y21/73370) -> 0.53548387 | Y21: =SUM(C21+E21+G21+I21+K21+M21+O21+Q21+S21+U21+W21) -> 39288.452 | Z21: ='B5'!C20 -> 172 | AA21: =SUM(Z21*$Z$4) -> 1720 | AB21: =SUM(Z21) -> 172 | AC21: =SUM(AB21*$Z$4) -> 1720 | AD21: =SUM(AB21) -> 172 | AE21: =SUM(AD21*$Z$4) -> 1720 | AF21: =SUM(AD21) -> 172 | AG21: =SUM(AF21*$Z$4) -> 1720 | AH21: =SUM(AF21) -> 172 | AI21: =SUM(AH21*$Z$4) -> 1720 | AJ21: =SUM(AH21) -> 172 | AK21: =SUM(AJ21*$Z$4) -> 1720 | AL21: =SUM(AJ21) -> 172 | AM21: =SUM(AL21*$Z$4) -> 1720 | AN21: =SUM(AO21/19600) -> 0.61428571 | AO21: =SUM(AA21+AC21+AE21+AG21+AI21+AK21+AM21) -> 12040 | AQ21: =SUM(AR21/92970) -> 0.55209693 | AR21: =SUM(AO21+Y21) -> 51328.452 | AS21: =SUM(AR21-AR20-AT21) -> -1840.0645 | AV21: =IF(AT21>0,AU21,AV20) -> 0.36 | AW21: =-SUM('B5'!AI20) -> -346 | AX21: =-SUM(AW21-AS21) -> -1494.0645 | AY21: =SUM(AX21+AW21) -> -1840.0645 | AZ21: =ELEC!A18 -> 0.0217 | BA21: ='General information '!D21 -> 23.5 | BB21: =SUM('General information '!E21) -> 0.65 | BC21: =IF(AR20>=AR21,0,1) -> 0 | BD21: 19222 | BE21: =(305/1185)*ELEC!Q19 -> 772.1519 | BG21: =#REF!-BE21 -> #REF!
A22: =ELEC!C19 -> 43999 | B22: ='B5'!B21 -> 192 | C22: =B22*$B$4 -> 4131.0968 | D22: =SUM(B22) -> 192 | E22: =D22*$B$4 -> 4131.0968 | F22: =SUM(D22) -> 192 | G22: =F22*$B$4 -> 4131.0968 | H22: =SUM(F22) -> 192 | I22: =H22*$B$4 -> 4131.0968 | J22: =SUM(H22) -> 192 | K22: =J22*$B$4 -> 4131.0968 | L22: =SUM(J22) -> 192 | M22: =L22*$B$4 -> 4131.0968 | N22: =SUM(L22) -> 192 | O22: =N22*$B$4 -> 4131.0968 | P22: =SUM(N22) -> 192 | Q22: =P22*$B$4 -> 4131.0968 | R22: =SUM(P22) -> 192 | S22: =R22*$B$4 -> 4131.0968 | T22: =SUM(R22) -> 192 | U22: =T22*$B$4 -> 4131.0968 | V22: =SUM(T22) -> 192 | W22: =V22*$B$4 -> 4131.0968 | X22: =SUM(Y22/73370) -> 0.61935484 | Y22: =SUM(C22+E22+G22+I22+K22+M22+O22+Q22+S22+U22+W22) -> 45442.065 | Z22: ='B5'!C21 -> 198 | AA22: =SUM(Z22*$Z$4) -> 1980 | AB22: =SUM(Z22) -> 198 | AC22: =SUM(AB22*$Z$4) -> 1980 | AD22: =SUM(AB22) -> 198 | AE22: =SUM(AD22*$Z$4) -> 1980 | AF22: =SUM(AD22) -> 198 | AG22: =SUM(AF22*$Z$4) -> 1980 | AH22: =SUM(AF22) -> 198 | AI22: =SUM(AH22*$Z$4) -> 1980 | AJ22: =SUM(AH22) -> 198 | AK22: =SUM(AJ22*$Z$4) -> 1980 | AL22: =SUM(AJ22) -> 198 | AM22: =SUM(AL22*$Z$4) -> 1980 | AN22: =SUM(AO22/19600) -> 0.70714286 | AO22: =SUM(AA22+AC22+AE22+AG22+AI22+AK22+AM22) -> 13860 | AQ22: =SUM(AR22/92970) -> 0.63786237 | AR22: =SUM(AO22+Y22) -> 59302.065 | AS22: =SUM(AR22-AR21-AT22) -> -217.3871 | AT22: 8191 | AU22: 0.393 | AV22: =IF(AT22>0,AU22,AV21) -> 0.393 | AW22: =-SUM('B5'!AI21) -> -312 | AX22: =-SUM(AW22-AS22) -> 94.612903 | AY22: =SUM(AX22+AW22) -> -217.3871 | AZ22: =ELEC!A19 -> 0.0174 | BA22: ='General information '!D22 -> 24.5 | BB22: =SUM('General information '!E22) -> 0.72 | BC22: =IF(AR21>=AR22,0,1) -> 1 | BD22: 19222 | BE22: =(305/1185)*ELEC!Q20 -> 1544.3038 | BG22: =#REF!-BE22 -> #REF!
A23: =ELEC!C20 -> 44000 | B23: ='B5'!B22 -> 183 | C23: =B23*$B$4 -> 3937.4516 | D23: =SUM(B23) -> 183 | E23: =D23*$B$4 -> 3937.4516 | F23: =SUM(D23) -> 183 | G23: =F23*$B$4 -> 3937.4516 | H23: =SUM(F23) -> 183 | I23: =H23*$B$4 -> 3937.4516 | J23: =SUM(H23) -> 183 | K23: =J23*$B$4 -> 3937.4516 | L23: =SUM(J23) -> 183 | M23: =L23*$B$4 -> 3937.4516 | N23: =SUM(L23) -> 183 | O23: =N23*$B$4 -> 3937.4516 | P23: =SUM(N23) -> 183 | Q23: =P23*$B$4 -> 3937.4516 | R23: =SUM(P23) -> 183 | S23: =R23*$B$4 -> 3937.4516 | T23: =SUM(R23) -> 183 | U23: =T23*$B$4 -> 3937.4516 | V23: =SUM(T23) -> 183 | W23: =V23*$B$4 -> 3937.4516 | X23: =SUM(Y23/73370) -> 0.59032258 | Y23: =SUM(C23+E23+G23+I23+K23+M23+O23+Q23+S23+U23+W23) -> 43311.968 | Z23: ='B5'!C22 -> 189 | AA23: =SUM(Z23*$Z$4) -> 1890 | AB23: =SUM(Z23) -> 189 | AC23: =SUM(AB23*$Z$4) -> 1890 | AD23: =SUM(AB23) -> 189 | AE23: =SUM(AD23*$Z$4) -> 1890 | AF23: =SUM(AD23) -> 189 | AG23: =SUM(AF23*$Z$4) -> 1890 | AH23: =SUM(AF23) -> 189 | AI23: =SUM(AH23*$Z$4) -> 1890 | AJ23: =SUM(AH23) -> 189 | AK23: =SUM(AJ23*$Z$4) -> 1890 | AL23: =SUM(AJ23) -> 189 | AM23: =SUM(AL23*$Z$4) -> 1890 | AN23: =SUM(AO23/19600) -> 0.675 | AO23: =SUM(AA23+AC23+AE23+AG23+AI23+AK23+AM23) -> 13230 | AQ23: =SUM(AR23/92970) -> 0.60817433 | AR23: =SUM(AO23+Y23) -> 56541.968 | AS23: =SUM(AR23-AR22-AT23) -> -2760.0968 | AV23: =IF(AT23>0,AU23,AV22) -> 0.393 | AW23: =-SUM('B5'!AI22) -> -588.6 | AX23: =-SUM(AW23-AS23) -> -2171.4968 | AY23: =SUM(AX23+AW23) -> -2760.0968 | AZ23: =ELEC!A20 -> 0.0217 | BA23: ='General information '!D23 -> 25.5 | BB23: =SUM('General information '!E23) -> 0.65 | BC23: =IF(AR22>=AR23,0,1) -> 0 | BD23: 19222 | BE23: =(305/1185)*ELEC!Q21 -> 1286.9198 | BG23: =#REF!-BE23 -> #REF!
A24: =ELEC!C21 -> 44001 | B24: ='B5'!B23 -> 177 | C24: =B24*$B$4 -> 3808.3548 | D24: =SUM(B24) -> 177 | E24: =D24*$B$4 -> 3808.3548 | F24: =SUM(D24) -> 177 | G24: =F24*$B$4 -> 3808.3548 | H24: =SUM(F24) -> 177 | I24: =H24*$B$4 -> 3808.3548 | J24: =SUM(H24) -> 177 | K24: =J24*$B$4 -> 3808.3548 | L24: =SUM(J24) -> 177 | M24: =L24*$B$4 -> 3808.3548 | N24: =SUM(L24) -> 177 | O24: =N24*$B$4 -> 3808.3548 | P24: =SUM(N24) -> 177 | Q24: =P24*$B$4 -> 3808.3548 | R24: =SUM(P24) -> 177 | S24: =R24*$B$4 -> 3808.3548 | T24: =SUM(R24) -> 177 | U24: =T24*$B$4 -> 3808.3548 | V24: =SUM(T24) -> 177 | W24: =V24*$B$4 -> 3808.3548 | X24: =SUM(Y24/73370) -> 0.57096774 | Y24: =SUM(C24+E24+G24+I24+K24+M24+O24+Q24+S24+U24+W24) -> 41891.903 | Z24: ='B5'!C23 -> 182.1 | AA24: =SUM(Z24*$Z$4) -> 1821 | AB24: =SUM(Z24) -> 182.1 | AC24: =SUM(AB24*$Z$4) -> 1821 | AD24: =SUM(AB24) -> 182.1 | AE24: =SUM(AD24*$Z$4) -> 1821 | AF24: =SUM(AD24) -> 182.1 | AG24: =SUM(AF24*$Z$4) -> 1821 | AH24: =SUM(AF24) -> 182.1 | AI24: =SUM(AH24*$Z$4) -> 1821 | AJ24: =SUM(AH24) -> 182.1 | AK24: =SUM(AJ24*$Z$4) -> 1821 | AL24: =SUM(AJ24) -> 182.1 | AM24: =SUM(AL24*$Z$4) -> 1821 | AN24: =SUM(AO24/19600) -> 0.65035714 | AO24: =SUM(AA24+AC24+AE24+AG24+AI24+AK24+AM24) -> 12747 | AQ24: =SUM(AR24/92970) -> 0.58770467 | AR24: =SUM(AO24+Y24) -> 54638.903 | AS24: =SUM(AR24-AR23-AT24) -> -1903.0645 | AV24: =IF(AT24>0,AU24,AV23) -> 0.393 | AW24: =-SUM('B5'!AI23) -> -482 | AX24: =-SUM(AW24-AS24) -> -1421.0645 | AY24: =SUM(AX24+AW24) -> -1903.0645 | AZ24: =ELEC!A21 -> 0.0304 | BA24: ='General information '!D24 -> 25.5 | BB24: =SUM('General information '!E24) -> 0.7 | BC24: =IF(AR23>=AR24,0,1) -> 0 | BD24: 19222 | BE24: =(305/1185)*ELEC!Q22 -> 772.1519 | BG24: =#REF!-BE24 -> #REF!
A25: =ELEC!C22 -> 44002 | B25: ='B5'!B24 -> 173 | C25: =B25*$B$4 -> 3722.2903 | D25: =SUM(B25) -> 173 | E25: =D25*$B$4 -> 3722.2903 | F25: =SUM(D25) -> 173 | G25: =F25*$B$4 -> 3722.2903 | H25: =SUM(F25) -> 173 | I25: =H25*$B$4 -> 3722.2903 | J25: =SUM(H25) -> 173 | K25: =J25*$B$4 -> 3722.2903 | L25: =SUM(J25) -> 173 | M25: =L25*$B$4 -> 3722.2903 | N25: =SUM(L25) -> 173 | O25: =N25*$B$4 -> 3722.2903 | P25: =SUM(N25) -> 173 | Q25: =P25*$B$4 -> 3722.2903 | R25: =SUM(P25) -> 173 | S25: =R25*$B$4 -> 3722.2903 | T25: =SUM(R25) -> 173 | U25: =T25*$B$4 -> 3722.2903 | V25: =SUM(T25) -> 173 | W25: =V25*$B$4 -> 3722.2903 | X25: =SUM(Y25/73370) -> 0.55806452 | Y25: =SUM(C25+E25+G25+I25+K25+M25+O25+Q25+S25+U25+W25) -> 40945.194 | Z25: ='B5'!C24 -> 179 | AA25: =SUM(Z25*$Z$4) -> 1790 | AB25: =SUM(Z25) -> 179 | AC25: =SUM(AB25*$Z$4) -> 1790 | AD25: =SUM(AB25) -> 179 | AE25: =SUM(AD25*$Z$4) -> 1790 | AF25: =SUM(AD25) -> 179 | AG25: =SUM(AF25*$Z$4) -> 1790 | AH25: =SUM(AF25) -> 179 | AI25: =SUM(AH25*$Z$4) -> 1790 | AJ25: =SUM(AH25) -> 179 | AK25: =SUM(AJ25*$Z$4) -> 1790 | AL25: =SUM(AJ25) -> 179 | AM25: =SUM(AL25*$Z$4) -> 1790 | AN25: =SUM(AO25/19600) -> 0.63928571 | AO25: =SUM(AA25+AC25+AE25+AG25+AI25+AK25+AM25) -> 12530 | AQ25: =SUM(AR25/92970) -> 0.57518763 | AR25: =SUM(AO25+Y25) -> 53475.194 | AS25: =SUM(AR25-AR24-AT25) -> -1163.7097 | AV25: =IF(AT25>0,AU25,AV24) -> 0.393 | AW25: =-SUM('B5'!AI24) -> -279 | AX25: =-SUM(AW25-AS25) -> -884.70968 | AY25: =SUM(AX25+AW25) -> -1163.7097 | AZ25: =ELEC!A22 -> 0.0217 | BA25: ='General information '!D25 -> 24.5 | BB25: =SUM('General information '!E25) -> 0.65 | BC25: =IF(AR24>=AR25,0,1) -> 0 | BD25: 19222 | BE25: =(305/1185)*ELEC!Q23 -> 514.76793 | BG25: =#REF!-BE25 -> #REF!
A26: =ELEC!C23 -> 44003 | B26: ='B5'!B25 -> 169 | C26: =B26*$B$4 -> 3636.2258 | D26: =SUM(B26) -> 169 | E26: =D26*$B$4 -> 3636.2258 | F26: =SUM(D26) -> 169 | G26: =F26*$B$4 -> 3636.2258 | H26: =SUM(F26) -> 169 | I26: =H26*$B$4 -> 3636.2258 | J26: =SUM(H26) -> 169 | K26: =J26*$B$4 -> 3636.2258 | L26: =SUM(J26) -> 169 | M26: =L26*$B$4 -> 3636.2258 | N26: =SUM(L26) -> 169 | O26: =N26*$B$4 -> 3636.2258 | P26: =SUM(N26) -> 169 | Q26: =P26*$B$4 -> 3636.2258 | R26: =SUM(P26) -> 169 | S26: =R26*$B$4 -> 3636.2258 | T26: =SUM(R26) -> 169 | U26: =T26*$B$4 -> 3636.2258 | V26: =SUM(T26) -> 169 | W26: =V26*$B$4 -> 3636.2258 | X26: =SUM(Y26/73370) -> 0.54516129 | Y26: =SUM(C26+E26+G26+I26+K26+M26+O26+Q26+S26+U26+W26) -> 39998.484 | Z26: ='B5'!C25 -> 175.2 | AA26: =SUM(Z26*$Z$4) -> 1752 | AB26: =SUM(Z26) -> 175.2 | AC26: =SUM(AB26*$Z$4) -> 1752 | AD26: =SUM(AB26) -> 175.2 | AE26: =SUM(AD26*$Z$4) -> 1752 | AF26: =SUM(AD26) -> 175.2 | AG26: =SUM(AF26*$Z$4) -> 1752 | AH26: =SUM(AF26) -> 175.2 | AI26: =SUM(AH26*$Z$4) -> 1752 | AJ26: =SUM(AH26) -> 175.2 | AK26: =SUM(AJ26*$Z$4) -> 1752 | AL26: =SUM(AJ26) -> 175.2 | AM26: =SUM(AL26*$Z$4) -> 1752 | AN26: =SUM(AO26/19600) -> 0.62571429 | AO26: =SUM(AA26+AC26+AE26+AG26+AI26+AK26+AM26) -> 12264 | AQ26: =SUM(AR26/92970) -> 0.56214353 | AR26: =SUM(AO26+Y26) -> 52262.484 | AS26: =SUM(AR26-AR25-AT26) -> -1212.7097 | AV26: =IF(AT26>0,AU26,AV25) -> 0.393 | AW26: =-SUM('B5'!AI25) -> -382 | AX26: =-SUM(AW26-AS26) -> -830.70968 | AY26: =SUM(AX26+AW26) -> -1212.7097 | AZ26: =ELEC!A23 -> 0.0087 | BA26: ='General information '!D26 -> 25 | BB26: =SUM('General information '!E26) -> 0.65 | BC26: =IF(AR25>=AR26,0,1) -> 0 | BD26: 19222 | BE26: =(305/1185)*ELEC!Q24 -> 1029.5359 | BG26: =#REF!-BE26 -> #REF!
A27: =ELEC!C24 -> 44004 | B27: ='B5'!B26 -> 162.5 | C27: =B27*$B$4 -> 3496.371 | D27: =SUM(B27) -> 162.5 | E27: =D27*$B$4 -> 3496.371 | F27: =SUM(D27) -> 162.5 | G27: =F27*$B$4 -> 3496.371 | H27: =SUM(F27) -> 162.5 | I27: =H27*$B$4 -> 3496.371 | J27: =SUM(H27) -> 162.5 | K27: =J27*$B$4 -> 3496.371 | L27: =SUM(J27) -> 162.5 | M27: =L27*$B$4 -> 3496.371 | N27: =SUM(L27) -> 162.5 | O27: =N27*$B$4 -> 3496.371 | P27: =SUM(N27) -> 162.5 | Q27: =P27*$B$4 -> 3496.371 | R27: =SUM(P27) -> 162.5 | S27: =R27*$B$4 -> 3496.371 | T27: =SUM(R27) -> 162.5 | U27: =T27*$B$4 -> 3496.371 | V27: =SUM(T27) -> 162.5 | W27: =V27*$B$4 -> 3496.371 | X27: =SUM(Y27/73370) -> 0.52419355 | Y27: =SUM(C27+E27+G27+I27+K27+M27+O27+Q27+S27+U27+W27) -> 38460.081 | Z27: ='B5'!C26 -> 169 | AA27: =SUM(Z27*$Z$4) -> 1690 | AB27: =SUM(Z27) -> 169 | AC27: =SUM(AB27*$Z$4) -> 1690 | AD27: =SUM(AB27) -> 169 | AE27: =SUM(AD27*$Z$4) -> 1690 | AF27: =SUM(AD27) -> 169 | AG27: =SUM(AF27*$Z$4) -> 1690 | AH27: =SUM(AF27) -> 169 | AI27: =SUM(AH27*$Z$4) -> 1690 | AJ27: =SUM(AH27) -> 169 | AK27: =SUM(AJ27*$Z$4) -> 1690 | AL27: =SUM(AJ27) -> 169 | AM27: =SUM(AL27*$Z$4) -> 1690 | AN27: =SUM(AO27/19600) -> 0.60357143 | AO27: =SUM(AA27+AC27+AE27+AG27+AI27+AK27+AM27) -> 11830 | AQ27: =SUM(AR27/92970) -> 0.54092805 | AR27: =SUM(AO27+Y27) -> 50290.081 | AS27: =SUM(AR27-AR26-AT27) -> -1972.4032 | AV27: =IF(AT27>0,AU27,AV26) -> 0.393 | AW27: =-SUM('B5'!AI26) -> -449 | AX27: =-SUM(AW27-AS27) -> -1523.4032 | AY27: =SUM(AX27+AW27) -> -1972.4032 | AZ27: =ELEC!A24 -> 0.0261 | BA27: ='General information '!D27 -> 25.5 | BB27: =SUM('General information '!E27) -> 0.7 | BC27: =IF(AR26>=AR27,0,1) -> 0 | BD27: 19222 | BE27: =(305/1185)*ELEC!Q25 -> 1029.5359 | BG27: =#REF!-BE27 -> #REF!
A28: =ELEC!C25 -> 44005 | B28: ='B5'!B27 -> 157 | C28: =B28*$B$4 -> 3378.0323 | D28: =SUM(B28) -> 157 | E28: =D28*$B$4 -> 3378.0323 | F28: =SUM(D28) -> 157 | G28: =F28*$B$4 -> 3378.0323 | H28: =SUM(F28) -> 157 | I28: =H28*$B$4 -> 3378.0323 | J28: =SUM(H28) -> 157 | K28: =J28*$B$4 -> 3378.0323 | L28: =SUM(J28) -> 157 | M28: =L28*$B$4 -> 3378.0323 | N28: =SUM(L28) -> 157 | O28: =N28*$B$4 -> 3378.0323 | P28: =SUM(N28) -> 157 | Q28: =P28*$B$4 -> 3378.0323 | R28: =SUM(P28) -> 157 | S28: =R28*$B$4 -> 3378.0323 | T28: =SUM(R28) -> 157 | U28: =T28*$B$4 -> 3378.0323 | V28: =SUM(T28) -> 157 | W28: =V28*$B$4 -> 3378.0323 | X28: =SUM(Y28/73370) -> 0.50645161 | Y28: =SUM(C28+E28+G28+I28+K28+M28+O28+Q28+S28+U28+W28) -> 37158.355 | Z28: ='B5'!C27 -> 164 | AA28: =SUM(Z28*$Z$4) -> 1640 | AB28: =SUM(Z28) -> 164 | AC28: =SUM(AB28*$Z$4) -> 1640 | AD28: =SUM(AB28) -> 164 | AE28: =SUM(AD28*$Z$4) -> 1640 | AF28: =SUM(AD28) -> 164 | AG28: =SUM(AF28*$Z$4) -> 1640 | AH28: =SUM(AF28) -> 164 | AI28: =SUM(AH28*$Z$4) -> 1640 | AJ28: =SUM(AH28) -> 164 | AK28: =SUM(AJ28*$Z$4) -> 1640 | AL28: =SUM(AJ28) -> 164 | AM28: =SUM(AL28*$Z$4) -> 1640 | AN28: =SUM(AO28/19600) -> 0.58571429 | AO28: =SUM(AA28+AC28+AE28+AG28+AI28+AK28+AM28) -> 11480 | AQ28: =SUM(AR28/92970) -> 0.52316182 | AR28: =SUM(AO28+Y28) -> 48638.355 | AS28: =SUM(AR28-AR27-AT28) -> -1651.7258 | AV28: =IF(AT28>0,AU28,AV27) -> 0.393 | AW28: =-SUM('B5'!AI27) -> -318 | AX28: =-SUM(AW28-AS28) -> -1333.7258 | AY28: =SUM(AX28+AW28) -> -1651.7258 | AZ28: =ELEC!A25 -> 0.0174 | BA28: ='General information '!D28 -> 25 | BB28: =SUM('General information '!E28) -> 0.65 | BC28: =IF(AR27>=AR28,0,1) -> 0 | BD28: 19222 | BE28: =(305/1185)*ELEC!Q26 -> 1029.5359 | BG28: =#REF!-BE28 -> #REF!
A29: =ELEC!C26 -> 44006 | B29: ='B5'!B28 -> 150.2 | C29: =B29*$B$4 -> 3231.7226 | D29: =SUM(B29) -> 150.2 | E29: =D29*$B$4 -> 3231.7226 | F29: =SUM(D29) -> 150.2 | G29: =F29*$B$4 -> 3231.7226 | H29: =SUM(F29) -> 150.2 | I29: =H29*$B$4 -> 3231.7226 | J29: =SUM(H29) -> 150.2 | K29: =J29*$B$4 -> 3231.7226 | L29: =SUM(J29) -> 150.2 | M29: =L29*$B$4 -> 3231.7226 | N29: =SUM(L29) -> 150.2 | O29: =N29*$B$4 -> 3231.7226 | P29: =SUM(N29) -> 150.2 | Q29: =P29*$B$4 -> 3231.7226 | R29: =SUM(P29) -> 150.2 | S29: =R29*$B$4 -> 3231.7226 | T29: =SUM(R29) -> 150.2 | U29: =T29*$B$4 -> 3231.7226 | V29: =SUM(T29) -> 150.2 | W29: =V29*$B$4 -> 3231.7226 | X29: =SUM(Y29/73370) -> 0.48451613 | Y29: =SUM(C29+E29+G29+I29+K29+M29+O29+Q29+S29+U29+W29) -> 35548.948 | Z29: ='B5'!C28 -> 157 | AA29: =SUM(Z29*$Z$4) -> 1570 | AB29: =SUM(Z29) -> 157 | AC29: =SUM(AB29*$Z$4) -> 1570 | AD29: =SUM(AB29) -> 157 | AE29: =SUM(AD29*$Z$4) -> 1570 | AF29: =SUM(AD29) -> 157 | AG29: =SUM(AF29*$Z$4) -> 1570 | AH29: =SUM(AF29) -> 157 | AI29: =SUM(AH29*$Z$4) -> 1570 | AJ29: =SUM(AH29) -> 157 | AK29: =SUM(AJ29*$Z$4) -> 1570 | AL29: =SUM(AJ29) -> 157 | AM29: =SUM(AL29*$Z$4) -> 1570 | AN29: =SUM(AO29/19600) -> 0.56071429 | AO29: =SUM(AA29+AC29+AE29+AG29+AI29+AK29+AM29) -> 10990 | AQ29: =SUM(AR29/92970) -> 0.50058028 | AR29: =SUM(AO29+Y29) -> 46538.948 | AS29: =SUM(AR29-AR28-AT29) -> -2099.4065 | AV29: =IF(AT29>0,AU29,AV28) -> 0.393 | AW29: =-SUM('B5'!AI28) -> -434 | AX29: =-SUM(AW29-AS29) -> -1665.4065 | AY29: =SUM(AX29+AW29) -> -2099.4065 | AZ29: =ELEC!A26 -> 0.013 | BA29: ='General information '!D29 -> 25 | BB29: =SUM('General information '!E29) -> 0.65 | BC29: =IF(AR28>=AR29,0,1) -> 0 | BD29: 19222 | BE29: =(305/1185)*ELEC!Q27 -> 1029.5359 | BG29: =#REF!-BE29 -> #REF!
A30: =ELEC!C27 -> 44007 | B30: ='B5'!B29 -> 186 | C30: =B30*$B$4 -> 4002 | D30: =SUM(B30) -> 186 | E30: =D30*$B$4 -> 4002 | F30: =SUM(D30) -> 186 | G30: =F30*$B$4 -> 4002 | H30: =SUM(F30) -> 186 | I30: =H30*$B$4 -> 4002 | J30: =SUM(H30) -> 186 | K30: =J30*$B$4 -> 4002 | L30: =SUM(J30) -> 186 | M30: =L30*$B$4 -> 4002 | N30: =SUM(L30) -> 186 | O30: =N30*$B$4 -> 4002 | P30: =SUM(N30) -> 186 | Q30: =P30*$B$4 -> 4002 | R30: =SUM(P30) -> 186 | S30: =R30*$B$4 -> 4002 | T30: =SUM(R30) -> 186 | U30: =T30*$B$4 -> 4002 | V30: =SUM(T30) -> 186 | W30: =V30*$B$4 -> 4002 | X30: =SUM(Y30/73370) -> 0.6 | Y30: =SUM(C30+E30+G30+I30+K30+M30+O30+Q30+S30+U30+W30) -> 44022 | Z30: ='B5'!C29 -> 191 | AA30: =SUM(Z30*$Z$4) -> 1910 | AB30: =SUM(Z30) -> 191 | AC30: =SUM(AB30*$Z$4) -> 1910 | AD30: =SUM(AB30) -> 191 | AE30: =SUM(AD30*$Z$4) -> 1910 | AF30: =SUM(AD30) -> 191 | AG30: =SUM(AF30*$Z$4) -> 1910 | AH30: =SUM(AF30) -> 191 | AI30: =SUM(AH30*$Z$4) -> 1910 | AJ30: =SUM(AH30) -> 191 | AK30: =SUM(AJ30*$Z$4) -> 1910 | AL30: =SUM(AJ30) -> 191 | AM30: =SUM(AL30*$Z$4) -> 1910 | AN30: =SUM(AO30/19600) -> 0.68214286 | AO30: =SUM(AA30+AC30+AE30+AG30+AI30+AK30+AM30) -> 13370 | AQ30: =SUM(AR30/92970) -> 0.61731741 | AR30: =SUM(AO30+Y30) -> 57392 | AS30: =SUM(AR30-AR29-AT30) -> 5.0516129 | AT30: 10848 | AU30: 0.4128 | AV30: =IF(AT30>0,AU30,AV29) -> 0.4128 | AW30: =-SUM('B5'!AI29) -> -603 | AX30: =-SUM(AW30-AS30) -> 608.05161 | AY30: =SUM(AX30+AW30) -> 5.0516129 | AZ30: =ELEC!A27 -> 0.0174 | BA30: ='General information '!D30 -> 30 | BB30: =SUM('General information '!E30) -> 0.69 | BC30: =IF(AR29>=AR30,0,1) -> 1 | BD30: 19222 | BE30: =(305/1185)*ELEC!Q28 -> 1286.9198 | BG30: =#REF!-BE30 -> #REF!
A31: =ELEC!C28 -> 44008 | B31: ='B5'!B30 -> 176 | C31: =B31*$B$4 -> 3786.8387 | D31: =SUM(B31) -> 176 | E31: =D31*$B$4 -> 3786.8387 | F31: =SUM(D31) -> 176 | G31: =F31*$B$4 -> 3786.8387 | H31: =SUM(F31) -> 176 | I31: =H31*$B$4 -> 3786.8387 | J31: =SUM(H31) -> 176 | K31: =J31*$B$4 -> 3786.8387 | L31: =SUM(J31) -> 176 | M31: =L31*$B$4 -> 3786.8387 | N31: =SUM(L31) -> 176 | O31: =N31*$B$4 -> 3786.8387 | P31: =SUM(N31) -> 176 | Q31: =P31*$B$4 -> 3786.8387 | R31: =SUM(P31) -> 176 | S31: =R31*$B$4 -> 3786.8387 | T31: =SUM(R31) -> 176 | U31: =T31*$B$4 -> 3786.8387 | V31: =SUM(T31) -> 176 | W31: =V31*$B$4 -> 3786.8387 | X31: =SUM(Y31/73370) -> 0.56774194 | Y31: =SUM(C31+E31+G31+I31+K31+M31+O31+Q31+S31+U31+W31) -> 41655.226 | Z31: ='B5'!C30 -> 185 | AA31: =SUM(Z31*$Z$4) -> 1850 | AB31: =SUM(Z31) -> 185 | AC31: =SUM(AB31*$Z$4) -> 1850 | AD31: =SUM(AB31) -> 185 | AE31: =SUM(AD31*$Z$4) -> 1850 | AF31: =SUM(AD31) -> 185 | AG31: =SUM(AF31*$Z$4) -> 1850 | AH31: =SUM(AF31) -> 185 | AI31: =SUM(AH31*$Z$4) -> 1850 | AJ31: =SUM(AH31) -> 185 | AK31: =SUM(AJ31*$Z$4) -> 1850 | AL31: =SUM(AJ31) -> 185 | AM31: =SUM(AL31*$Z$4) -> 1850 | AN31: =SUM(AO31/19600) -> 0.66071429 | AO31: =SUM(AA31+AC31+AE31+AG31+AI31+AK31+AM31) -> 12950 | AQ31: =SUM(AR31/92970) -> 0.58734243 | AR31: =SUM(AO31+Y31) -> 54605.226 | AS31: =SUM(AR31-AR30-AT31) -> -2786.7742 | AV31: =IF(AT31>0,AU31,AV30) -> 0.4128 | AW31: =-SUM('B5'!AI30) -> -341 | AX31: =-SUM(AW31-AS31) -> -2445.7742 | AY31: =SUM(AX31+AW31) -> -2786.7742 | AZ31: =ELEC!A28 -> 0.013 | BA31: ='General information '!D31 -> 26 | BB31: =SUM('General information '!E31) -> 0.66 | BC31: =IF(AR30>=AR31,0,1) -> 0 | BD31: 19222 | BE31: =(305/1185)*ELEC!Q29 -> 1286.9198 | BG31: =#REF!-BE31 -> #REF!
A32: =ELEC!C29 -> 44009 | B32: ='B5'!B31 -> 171.4 | C32: =B32*$B$4 -> 3687.8645 | D32: =SUM(B32) -> 171.4 | E32: =D32*$B$4 -> 3687.8645 | F32: =SUM(D32) -> 171.4 | G32: =F32*$B$4 -> 3687.8645 | H32: =SUM(F32) -> 171.4 | I32: =H32*$B$4 -> 3687.8645 | J32: =SUM(H32) -> 171.4 | K32: =J32*$B$4 -> 3687.8645 | L32: =SUM(J32) -> 171.4 | M32: =L32*$B$4 -> 3687.8645 | N32: =SUM(L32) -> 171.4 | O32: =N32*$B$4 -> 3687.8645 | P32: =SUM(N32) -> 171.4 | Q32: =P32*$B$4 -> 3687.8645 | R32: =SUM(P32) -> 171.4 | S32: =R32*$B$4 -> 3687.8645 | T32: =SUM(R32) -> 171.4 | U32: =T32*$B$4 -> 3687.8645 | V32: =SUM(T32) -> 171.4 | W32: =V32*$B$4 -> 3687.8645 | X32: =SUM(Y32/73370) -> 0.55290323 | Y32: =SUM(C32+E32+G32+I32+K32+M32+O32+Q32+S32+U32+W32) -> 40566.51 | Z32: ='B5'!C31 -> 177.2 | AA32: =SUM(Z32*$Z$4) -> 1772 | AB32: =SUM(Z32) -> 177.2 | AC32: =SUM(AB32*$Z$4) -> 1772 | AD32: =SUM(AB32) -> 177.2 | AE32: =SUM(AD32*$Z$4) -> 1772 | AF32: =SUM(AD32) -> 177.2 | AG32: =SUM(AF32*$Z$4) -> 1772 | AH32: =SUM(AF32) -> 177.2 | AI32: =SUM(AH32*$Z$4) -> 1772 | AJ32: =SUM(AH32) -> 177.2 | AK32: =SUM(AJ32*$Z$4) -> 1772 | AL32: =SUM(AJ32) -> 177.2 | AM32: =SUM(AL32*$Z$4) -> 1772 | AN32: =SUM(AO32/19600) -> 0.63285714 | AO32: =SUM(AA32+AC32+AE32+AG32+AI32+AK32+AM32) -> 12404 | AQ32: =SUM(AR32/92970) -> 0.56975917 | AR32: =SUM(AO32+Y32) -> 52970.51 | AS32: =SUM(AR32-AR31-AT32) -> -1634.7161 | AV32: =IF(AT32>0,AU32,AV31) -> 0.4128 | AW32: =-SUM('B5'!AI31) -> -372 | AX32: =-SUM(AW32-AS32) -> -1262.7161 | AY32: =SUM(AX32+AW32) -> -1634.7161 | AZ32: =ELEC!A29 -> 0.024 | BA32: ='General information '!D32 -> 27 | BB32: =SUM('General information '!E32) -> 0.55 | BC32: =IF(AR31>=AR32,0,1) -> 0 | BD32: 19222 | BE32: =(305/1185)*ELEC!Q30 -> 1544.3038 | BG32: =#REF!-BE32 -> #REF!
A33: =ELEC!C30 -> 44010 | B33: ='B5'!B32 -> 165 | C33: =B33*$B$4 -> 3550.1613 | D33: =SUM(B33) -> 165 | E33: =D33*$B$4 -> 3550.1613 | F33: =SUM(D33) -> 165 | G33: =F33*$B$4 -> 3550.1613 | H33: =SUM(F33) -> 165 | I33: =H33*$B$4 -> 3550.1613 | J33: =SUM(H33) -> 165 | K33: =J33*$B$4 -> 3550.1613 | L33: =SUM(J33) -> 165 | M33: =L33*$B$4 -> 3550.1613 | N33: =SUM(L33) -> 165 | O33: =N33*$B$4 -> 3550.1613 | P33: =SUM(N33) -> 165 | Q33: =P33*$B$4 -> 3550.1613 | R33: =SUM(P33) -> 165 | S33: =R33*$B$4 -> 3550.1613 | T33: =SUM(R33) -> 165 | U33: =T33*$B$4 -> 3550.1613 | V33: =SUM(T33) -> 165 | W33: =V33*$B$4 -> 3550.1613 | X33: =SUM(Y33/73370) -> 0.53225806 | Y33: =SUM(C33+E33+G33+I33+K33+M33+O33+Q33+S33+U33+W33) -> 39051.774 | Z33: ='B5'!C32 -> 170 | AA33: =SUM(Z33*$Z$4) -> 1700 | AB33: =SUM(Z33) -> 170 | AC33: =SUM(AB33*$Z$4) -> 1700 | AD33: =SUM(AB33) -> 170 | AE33: =SUM(AD33*$Z$4) -> 1700 | AF33: =SUM(AD33) -> 170 | AG33: =SUM(AF33*$Z$4) -> 1700 | AH33: =SUM(AF33) -> 170 | AI33: =SUM(AH33*$Z$4) -> 1700 | AJ33: =SUM(AH33) -> 170 | AK33: =SUM(AJ33*$Z$4) -> 1700 | AL33: =SUM(AJ33) -> 170 | AM33: =SUM(AL33*$Z$4) -> 1700 | AN33: =SUM(AO33/19600) -> 0.60714286 | AO33: =SUM(AA33+AC33+AE33+AG33+AI33+AK33+AM33) -> 11900 | AQ33: =SUM(AR33/92970) -> 0.54804533 | AR33: =SUM(AO33+Y33) -> 50951.774 | AS33: =SUM(AR33-AR32-AT33) -> -2018.7355 | AV33: =IF(AT33>0,AU33,AV32) -> 0.4128 | AW33: =-SUM('B5'!AI32) -> -397 | AX33: =-SUM(AW33-AS33) -> -1621.7355 | AY33: =SUM(AX33+AW33) -> -2018.7355 | AZ33: =ELEC!A30 -> 0.0348 | BA33: ='General information '!D33 -> 28 | BB33: =SUM('General information '!E33) -> 0.66 | BC33: =IF(AR32>=AR33,0,1) -> 0 | BD33: 19222 | BE33: =(305/1185)*ELEC!Q31 -> 0 | BG33: =#REF!-BE33 -> #REF!
A34: =ELEC!C31 -> 44011 | B34: ='B5'!B33 -> 165 | C34: =B34*$B$4 -> 3550.1613 | D34: =SUM(B34) -> 165 | E34: =D34*$B$4 -> 3550.1613 | F34: =SUM(D34) -> 165 | G34: =F34*$B$4 -> 3550.1613 | H34: =SUM(F34) -> 165 | I34: =H34*$B$4 -> 3550.1613 | J34: =SUM(H34) -> 165 | K34: =J34*$B$4 -> 3550.1613 | L34: =SUM(J34) -> 165 | M34: =L34*$B$4 -> 3550.1613 | N34: =SUM(L34) -> 165 | O34: =N34*$B$4 -> 3550.1613 | P34: =SUM(N34) -> 165 | Q34: =P34*$B$4 -> 3550.1613 | R34: =SUM(P34) -> 165 | S34: =R34*$B$4 -> 3550.1613 | T34: =SUM(R34) -> 165 | U34: =T34*$B$4 -> 3550.1613 | V34: =SUM(T34) -> 165 | W34: =V34*$B$4 -> 3550.1613 | X34: =SUM(Y34/73370) -> 0.53225806 | Y34: =SUM(C34+E34+G34+I34+K34+M34+O34+Q34+S34+U34+W34) -> 39051.774 | Z34: ='B5'!C33 -> 170 | AA34: =SUM(Z34*$Z$4) -> 1700 | AB34: =SUM(Z34) -> 170 | AC34: =SUM(AB34*$Z$4) -> 1700 | AD34: =SUM(AB34) -> 170 | AE34: =SUM(AD34*$Z$4) -> 1700 | AF34: =SUM(AD34) -> 170 | AG34: =SUM(AF34*$Z$4) -> 1700 | AH34: =SUM(AF34) -> 170 | AI34: =SUM(AH34*$Z$4) -> 1700 | AJ34: =SUM(AH34) -> 170 | AK34: =SUM(AJ34*$Z$4) -> 1700 | AL34: =SUM(AJ34) -> 170 | AM34: =SUM(AL34*$Z$4) -> 1700 | AN34: =SUM(AO34/19600) -> 0.60714286 | AO34: =SUM(AA34+AC34+AE34+AG34+AI34+AK34+AM34) -> 11900 | AQ34: =SUM(AR34/92970) -> 0.54804533 | AR34: =SUM(AO34+Y34) -> 50951.774 | AS34: =SUM(AR34-AR33-AT34) -> 0 | AV34: =IF(AT34>0,AU34,AV33) -> 0.4128 | AW34: =-SUM('B5'!AI33) -> 0 | AX34: =-SUM(AW34-AS34) -> 0 | AY34: =SUM(AX34+AW34) -> 0 | AZ34: =ELEC!A31 -> 0 | BA34: ='General information '!D34 -> 0 | BB34: =SUM('General information '!E34) -> 0 | BC34: =IF(AR33>=AR34,0,1) -> 0 | BD34: 19222 | BE34: =(305/1185)*ELEC!#REF! -> #REF! | BG34: =#REF!-BE34 -> #REF!
A35: =ELEC!C32 -> 44012 | B35: ='B5'!B34 -> 165 | C35: =B35*$B$4 -> 3550.1613 | D35: =SUM(B35) -> 165 | E35: =D35*$B$4 -> 3550.1613 | F35: =SUM(D35) -> 165 | G35: =F35*$B$4 -> 3550.1613 | H35: =SUM(F35) -> 165 | I35: =H35*$B$4 -> 3550.1613 | J35: =SUM(H35) -> 165 | K35: =J35*$B$4 -> 3550.1613 | L35: =SUM(J35) -> 165 | M35: =L35*$B$4 -> 3550.1613 | N35: =SUM(L35) -> 165 | O35: =N35*$B$4 -> 3550.1613 | P35: =SUM(N35) -> 165 | Q35: =P35*$B$4 -> 3550.1613 | R35: =SUM(P35) -> 165 | S35: =R35*$B$4 -> 3550.1613 | T35: =SUM(R35) -> 165 | U35: =T35*$B$4 -> 3550.1613 | V35: =SUM(T35) -> 165 | W35: =V35*$B$4 -> 3550.1613 | X35: =SUM(Y35/73370) -> 0.53225806 | Y35: =SUM(C35+E35+G35+I35+K35+M35+O35+Q35+S35+U35+W35) -> 39051.774 | Z35: ='B5'!C34 -> 170 | AA35: =SUM(Z35*$Z$4) -> 1700 | AB35: =SUM(Z35) -> 170 | AC35: =SUM(AB35*$Z$4) -> 1700 | AD35: =SUM(AB35) -> 170 | AE35: =SUM(AD35*$Z$4) -> 1700 | AF35: =SUM(AD35) -> 170 | AG35: =SUM(AF35*$Z$4) -> 1700 | AH35: =SUM(AF35) -> 170 | AI35: =SUM(AH35*$Z$4) -> 1700 | AJ35: =SUM(AH35) -> 170 | AK35: =SUM(AJ35*$Z$4) -> 1700 | AL35: =SUM(AJ35) -> 170 | AM35: =SUM(AL35*$Z$4) -> 1700 | AN35: =SUM(AO35/19600) -> 0.60714286 | AO35: =SUM(AA35+AC35+AE35+AG35+AI35+AK35+AM35) -> 11900 | AQ35: =SUM(AR35/92970) -> 0.54804533 | AR35: =SUM(AO35+Y35) -> 50951.774 | AS35: =SUM(AR35-AR34-AT35) -> 0 | AV35: =IF(AT35>0,AU35,AV34) -> 0.4128 | AW35: =-SUM('B5'!AI34) -> 0 | AX35: =-SUM(AW35-AS35) -> 0 | AY35: =SUM(AX35+AW35) -> 0 | AZ35: =ELEC!A32 -> 0 | BA35: ='General information '!D35 -> 0 | BB35: =SUM('General information '!E35) -> 0 | BC35: =IF(AR34>=AR35,0,1) -> 0 | BD35: 19222 | BE35: =(305/1185)*ELEC!#REF! -> #REF! | BG35: =#REF!-BE35 -> #REF!
AR36: NB delivery | AS36: =COUNT(AT6:AT35) -> 5 | AT36: =SUM(AT6:AT35) -> 37692.1 | AU36: =SUM(AU6:AU35)/AS36 -> 0.32116 | AX36: =SUM(AX6:AX35) -> -31037.884 | AY36: =SUM(AY6:AY35) -> -42125.584
AT37: =+AT36*AU36 -> 12105.195
AS39: =SUM(AS6:AS35)/'EDl log'!A37 -> -1504.4851

Sheet GEN
B1: GEN1 | C1: RUN HR | D1: Fuel Counter Index | E1: Cons /day | F1: Diesel L/H | H1: next service | I1: ALARM | J1: GEN2 | K1: RUN HR | L1: Fuel Counter Index | M1: Cons /day | N1: Diesel L/H | P1: next service | Q1: ALARM | R1: GEN3 | S1: RUN HR | T1: Fuel Counter Index | U1: Cons /day | V1: Diesel L/H | X1: next service | Y1: ALARM | Z1: RH total | AA1: Gen Con /day | AB1: Total Deisel Cons/day | AC1: H /L | AD1: TOAL KW GEN | AI1: fuel Consuption | AK1: AVG KW/h
A2: =ELEC!C2 -> 43982 | B2: =[2]GEN!B33 -> 8655 | C2: =[2]GEN!C33 -> 3 | D2: =[2]GEN!D33 -> 153095 | E2: =[2]GEN!E33 -> 1435 | F2: =[2]GEN!F33 -> 478.33333 | G2: =[2]GEN!G33 -> 0 | H2: =[2]GEN!H33 -> 8770 | I2: =[2]GEN!I33 -> ok | ... AK2: =[2]GEN!AK33 -> 0
A3: =ELEC!C3 -> 43983 | B3: 8659 | C3: =B3-B2 -> 4 | D3: 153808 | E3: =SUM(D3-D2) -> 713 | F3: =IF(C3>0,E3/C3,0) -> 178.25 | G3: =[3]GEN!G32 -> 0 | H3: =H2 -> 8770 | I3: =IF(B3-H3<=0,"ok","oil change") -> ok | J3: =J2 -> 10689 | K3: =J3-J2 -> 0 | L3: 237118 | M3: =SUM(L3-L2) -> 43 | N3: =IF(K3>0,M3/K3,0) -> 0 | O3: =[3]GEN!O32 -> 0 | P3: =P2 -> 10873 | Q3: =IF(J3-P3<=0,"ok","oil change") -> ok | R3: =R2 -> 11201 | S3: =R3-R2 -> 0 | T3: 253331 | U3: =SUM(T3-T2) -> 49 | V3: =IF(S3>0,U3/S3,0) -> 0 | W3: =[3]GEN!W32 -> 0 | X3: =X2 -> 11889 | Y3: =IF(R3-X3<=0,"ok","oil change") -> ok | Z3: =C3+K3+S3 -> 4 | AA3: =U3+M3+E3 -> 805 | AB3: =V3+N3+F3 -> 178.25 | AC3: =IF(Z3>0,AA3/Z3,0) -> 201.25 | AD3: =ELEC!Q3 -> 2000 | AE3: =SUM(AD3/Z3) -> 500 | AF3: =SUM(AE3/1600) -> 0.3125 | AG3: =SUM(360*AF3) -> 112.5 | AH3: =SUM(AC3-AG3) -> 88.75 | AI3: =AD3*AJ3 -> 514.76793 | AJ3: =305/1185 -> 0.25738397 | AK3: =AI3/Z3 -> 128.69198
A4: =ELEC!C4 -> 43984 | B4: 8662 | C4: =B4-B3 -> 3 | D4: 154342 | E4: =SUM(D4-D3) -> 534 | F4: =IF(C4>0,E4/C4,0) -> 178 | H4: =H3 -> 8770 | I4: =IF(B4-H4<=0,"ok","oil change") -> ok | J4: =J3 -> 10689 | K4: =J4-J3 -> 0 | L4: =L3 -> 237118 | M4: =SUM(L4-L3) -> 0 | N4: =IF(K4>0,M4/K4,0) -> 0 | P4: =P3 -> 10873 | Q4: =IF(J4-P4<=0,"ok","oil change") -> ok | R4: =R3 -> 11201 | S4: =R4-R3 -> 0 | T4: 253377 | U4: =SUM(T4-T3) -> 46 | V4: =IF(S4>0,U4/S4,0) -> 0 | X4: =X3 -> 11889 | Y4: =IF(R4-X4<=0,"ok","oil change") -> ok | Z4: =C4+K4+S4 -> 3 | AA4: =U4+M4+E4 -> 580 | AB4: =V4+N4+F4 -> 178 | AC4: =IF(Z4>0,AA4/Z4,0) -> 193.33333 | AD4: =ELEC!Q4 -> 2000 | AE4: =SUM(AD4/Z4) -> 666.66667 | AF4: =SUM(AE4/1600) -> 0.41666667 | AG4: =SUM(360*AF4) -> 150 | AH4: =SUM(AC4-AG4) -> 43.333333 | AI4: =AD4*AJ4 -> 514.76793 | AJ4: =305/1185 -> 0.25738397 | AK4: =AI4/Z4 -> 171.58931
A5: =ELEC!C5 -> 43985 | B5: 8665 | C5: =B5-B4 -> 3 | D5: 154903 | E5: =SUM(D5-D4) -> 561 | F5: =IF(C5>0,E5/C5,0) -> 187 | H5: =H4 -> 8770 | I5: =IF(B5-H5<=0,"ok","oil change") -> ok | J5: 10689 | K5: =J5-J4 -> 0 | L5: =L4 -> 237118 | M5: =SUM(L5-L4) -> 0 | N5: =IF(K5>0,M5/K5,0) -> 0 | P5: =P4 -> 10873 | Q5: =IF(J5-P5<=0,"ok","oil change") -> ok | R5: 11201 | S5: =R5-R4 -> 0 | T5: 253380 | U5: =SUM(T5-T4) -> 3 | V5: =IF(S5>0,U5/S5,0) -> 0 | X5: =X4 -> 11889 | Y5: =IF(R5-X5<=0,"ok","oil change") -> ok | Z5: =C5+K5+S5 -> 3 | AA5: =U5+M5+E5 -> 564 | AB5: =V5+N5+F5 -> 187 | AC5: =IF(Z5>0,AA5/Z5,0) -> 188 | AD5: =ELEC!Q5 -> 2000 | AE5: =SUM(AD5/Z5) -> 666.66667 | AF5: =SUM(AE5/1600) -> 0.41666667 | AG5: =SUM(320*AF5) -> 133.33333 | AH5: =SUM(AC5-AG5) -> 54.666667 | AI5: =AD5*AJ5 -> 514.76793 | AJ5: =305/1185 -> 0.25738397 | AK5: =AI5/Z5 -> 171.58931
A6: =ELEC!C6 -> 43986 | B6: 8667 | C6: =B6-B5 -> 2 | D6: 155467 | E6: =SUM(D6-D5) -> 564 | F6: =IF(C6>0,E6/C6,0) -> 282 | H6: =H5 -> 8770 | I6: =IF(B6-H6<=0,"ok","oil change") -> ok | J6: =J5 -> 10689 | K6: =J6-J5 -> 0 | L6: =L5 -> 237118 | M6: =SUM(L6-L5) -> 0 | N6: =IF(K6>0,M6/K6,0) -> 0 | P6: =P5 -> 10873 | Q6: =IF(J6-P6<=0,"ok","oil change") -> ok | R6: =R5 -> 11201 | S6: =R6-R5 -> 0 | T6: 253380 | U6: =SUM(T6-T5) -> 0 | V6: =IF(S6>0,U6/S6,0) -> 0 | X6: =X5 -> 11889 | Y6: =IF(R6-X6<=0,"ok","oil change") -> ok | Z6: =C6+K6+S6 -> 2 | AA6: =U6+M6+E6 -> 564 | AB6: =V6+N6+F6 -> 282 | AC6: =IF(Z6>0,AA6/Z6,0) -> 282 | AD6: =ELEC!Q6 -> 2000 | AE6: =SUM(AD6/Z6) -> 1000 | AF6: =SUM(AE6/1600) -> 0.625 | AG6: =SUM(320*AF6) -> 200 | AH6: =SUM(AC6-AG6) -> 82 | AI6: =AD6*AJ6 -> 514.76793 | AJ6: =305/1185 -> 0.25738397 | AK6: =AI6/Z6 -> 257.38397
A7: =ELEC!C7 -> 43987 | B7: =B6 -> 8667 | C7: =B7-B6 -> 0 | D7: =D6 -> 155467 | E7: =SUM(D7-D6) -> 0 | F7: =IF(C7>0,E7/C7,0) -> 0 | H7: =H6 -> 8770 | I7: =IF(B7-H7<=0,"ok","oil change") -> ok | J7: 10693 | K7: =J7-J6 -> 4 | L7: 237634 | M7: =SUM(L7-L6) -> 516 | N7: =IF(K7>0,M7/K7,0) -> 129 | P7: =P6 -> 10873 | Q7: =IF(J7-P7<=0,"ok","oil change") -> ok | R7: =R6 -> 11201 | S7: =R7-R6 -> 0 | T7: 253394 | U7: =SUM(T7-T6) -> 14 | V7: =IF(S7>0,U7/S7,0) -> 0 | X7: =X6 -> 11889 | Y7: =IF(R7-X7<=0,"ok","oil change") -> ok | Z7: =C7+K7+S7 -> 4 | AA7: =U7+M7+E7 -> 530 | AB7: =V7+N7+F7 -> 129 | AC7: =IF(Z7>0,AA7/Z7,0) -> 132.5 | AD7: =ELEC!Q7 -> 2000 | AE7: =SUM(AD7/Z7) -> 500 | AF7: =SUM(AE7/1600) -> 0.3125 | AH7: =SUM(AC7-AG7) -> #VALUE! | AI7: =AD7*AJ7 -> 514.76793 | AJ7: =305/1185 -> 0.25738397 | AK7: =AI7/Z7 -> 128.69198
A8: =ELEC!C8 -> 43988 | B8: 8668 | C8: =B8-B7 -> 1 | D8: 155499 | E8: =SUM(D8-D7) -> 32 | F8: =IF(C8>0,E8/C8,0) -> 32 | H8: =H7 -> 8770 | I8: =IF(B8-H8<=0,"ok","oil change") -> ok | J8: 10696 | K8: =J8-J7 -> 3 | L8: 238182 | M8: =SUM(L8-L7) -> 548 | N8: =IF(K8>0,M8/K8,0) -> 182.66667 | P8: =P7 -> 10873 | Q8: =IF(J8-P8<=0,"ok","oil change") -> ok | R8: =R7 -> 11201 | S8: =R8-R7 -> 0 | T8: 253394 | U8: =SUM(T8-T7) -> 0 | V8: =IF(S8>0,U8/S8,0) -> 0 | X8: =X7 -> 11889 | Y8: =IF(R8-X8<=0,"ok","oil change") -> ok | Z8: =C8+K8+S8 -> 4 | AA8: =U8+M8+E8 -> 580 | AB8: =V8+N8+F8 -> 214.66667 | AC8: =IF(Z8>0,AA8/Z8,0) -> 145 | AD8: =ELEC!Q8 -> 2000 | AE8: =SUM(AD8/Z8) -> 500 | AF8: =SUM(AE8/1600) -> 0.3125 | AG8: =SUM(320*AF8) -> 100 | AH8: =SUM(AC8-AG8) -> 45 | AI8: =AD8*AJ8 -> 514.76793 | AJ8: =305/1185 -> 0.25738397 | AK8: =AI8/Z8 -> 128.69198
A9: =ELEC!C9 -> 43989 | B9: 8669 | C9: =B9-B8 -> 1 | D9: 155788 | E9: =SUM(D9-D8) -> 289 | F9: =IF(C9>0,E9/C9,0) -> 289 | H9: =H8 -> 8770 | I9: =IF(B9-H9<=0,"ok","oil change") -> ok | J9: 10698 | K9: =J9-J8 -> 2 | L9: 238479 | M9: =SUM(L9-L8) -> 297 | N9: =IF(K9>0,M9/K9,0) -> 148.5 | P9: =P8 -> 10873 | Q9: =IF(J9-P9<=0,"ok","oil change") -> ok | R9: =R8 -> 11201 | S9: =R9-R8 -> 0 | T9: 253394 | U9: =SUM(T9-T8) -> 0 | V9: =IF(S9>0,U9/S9,0) -> 0 | X9: =X8 -> 11889 | Y9: =IF(R9-X9<=0,"ok","oil change") -> ok | Z9: =C9+K9+S9 -> 3 | AA9: =U9+M9+E9 -> 586 | AB9: =V9+N9+F9 -> 437.5 | AC9: =IF(Z9>0,AA9/Z9,0) -> 195.33333 | AD9: =ELEC!Q9 -> 2000 | AE9: =SUM(AD9/Z9) -> 666.66667 | AF9: =SUM(AE9/1600) -> 0.41666667 | AG9: =SUM(320*AF9) -> 133.33333 | AH9: =SUM(AC9-AG9) -> 62 | AI9: =AD9*AJ9 -> 514.76793 | AJ9: 0.25738397 | AK9: =IF(Z9>0,AI9/Z9,0) -> 171.58931
A10: =ELEC!C10 -> 43990 | B10: 8672 | C10: =B10-B9 -> 3 | D10: 156350 | E10: =SUM(D10-D9) -> 562 | F10: =IF(C10>0,E10/C10,0) -> 187.33333 | H10: =H9 -> 8770 | I10: =IF(B10-H10<=0,"ok","oil change") -> ok | J10: =J9 -> 10698 | K10: =J10-J9 -> 0 | L10: =L9 -> 238479 | M10: =SUM(L10-L9) -> 0 | N10: =IF(K10>0,M10/K10,0) -> 0 | P10: 10873 | Q10: =IF(J10-P10<=0,"ok","oil change") -> ok | R10: =R9 -> 11201 | S10: =R10-R9 -> 0 | T10: 253394 | U10: =SUM(T10-T9) -> 0 | V10: =IF(S10>0,U10/S10,0) -> 0 | X10: =X9 -> 11889 | Y10: =IF(R10-X10<=0,"ok","oil change") -> ok | Z10: =C10+K10+S10 -> 3 | AA10: =U10+M10+E10 -> 562 | AB10: =V10+N10+F10 -> 187.33333 | AC10: =IF(Z10>0,AA10/Z10,0) -> 187.33333 | AD10: =ELEC!Q10 -> 2000 | AE10: =SUM(AD10/Z10) -> 666.66667 | AF10: =SUM(AE10/1600) -> 0.41666667 | AG10: =SUM(320*AF10) -> 133.33333 | AH10: =SUM(AC10-AG10) -> 54 | AI10: =AD10*AJ10 -> 514.76793 | AJ10: =305/1185 -> 0.25738397 | AK10: =IF(Z10>0,AI10/Z10,0) -> 171.58931
A11: =ELEC!C11 -> 43991 | B11: 8672 | C11: =B11-B10 -> 0 | D11: 156429 | E11: =SUM(D11-D10) -> 79 | F11: =IF(C11>0,E11/C11,0) -> 0 | H11: =H10 -> 8770 | I11: =IF(B11-H11<=0,"ok","oil change") -> ok | J11: 10698 | K11: =J11-J10 -> 0 | L11: =L10 -> 238479 | M11: =SUM(L11-L10) -> 0 | N11: =IF(K11>0,M11/K11,0) -> 0 | P11: =P10 -> 10873 | Q11: =IF(J11-P11<=0,"ok","oil change") -> ok | R11: 11205 | S11: =R11-R10 -> 4 | T11: 254281 | U11: =SUM(T11-T10) -> 887 | V11: =IF(S11>0,U11/S11,0) -> 221.75 | X11: =X10 -> 11889 | Y11: =IF(R11-X11<=0,"ok","oil change") -> ok | Z11: =C11+K11+S11 -> 4 | AA11: =U11+M11+E11 -> 966 | AB11: =V11+N11+F11 -> 221.75 | AC11: =IF(Z11>0,AA11/Z11,0) -> 241.5 | AD11: =ELEC!Q11 -> 2000 | AE11: =SUM(AD11/Z11) -> 500 | AF11: =SUM(AE11/1600) -> 0.3125 | AG11: =SUM(320*AF11) -> 100 | AH11: =SUM(AC11-AG11) -> 141.5 | AI11: =AD11*AJ11 -> 514.76793 | AJ11: =305/1185 -> 0.25738397 | AK11: =IF(Z11>0,AI11/Z11,0) -> 128.69198
A12: =ELEC!C12 -> 43992 | B12: 8672 | C12: =B12-B11 -> 0 | D12: 156438 | E12: =SUM(D12-D11) -> 9 | F12: =IF(C12>0,E12/C12,0) -> 0 | H12: =H11 -> 8770 | I12: =IF(B12-H12<=0,"ok","oil change") -> ok | J12: =J11 -> 10698 | K12: =J12-J11 -> 0 | L12: =L11 -> 238479 | M12: =SUM(L12-L11) -> 0 | N12: =IF(K12>0,M12/K12,0) -> 0 | P12: =P11 -> 10873 | Q12: =IF(J12-P12<=0,"ok","oil change") -> ok | R12: 11212 | S12: =R12-R11 -> 7 | T12: 256096 | U12: =SUM(T12-T11) -> 1815 | V12: =IF(S12>0,U12/S12,0) -> 259.28571 | X12: =X11 -> 11889 | Y12: =IF(R12-X12<=0,"ok","oil change") -> ok | Z12: =C12+K12+S12 -> 7 | AA12: =U12+M12+E12 -> 1824 | AB12: =V12+N12+F12 -> 259.28571 | AC12: =IF(Z12>0,AA12/Z12,0) -> 260.57143 | AD12: =ELEC!Q12 -> 6000 | AE12: =SUM(AD12/Z12) -> 857.14286 | AF12: =SUM(AE12/1600) -> 0.53571429 | AG12: =SUM(320*AF12) -> 171.42857 | AH12: =SUM(AC12-AG12) -> 89.142857 | AI12: =AD12*AJ12 -> 1544.3038 | AJ12: =305/1185 -> 0.25738397 | AK12: =IF(Z12>0,AI12/Z12,0) -> 220.61483
A13: =ELEC!C13 -> 43993 | B13: 8672 | C13: =B13-B12 -> 0 | D13: 156998 | E13: =SUM(D13-D12) -> 560 | F13: =IF(C13>0,E13/C13,0) -> 0 | H13: =H12 -> 8770 | I13: =IF(B13-H13<=0,"ok","oil change") -> ok | J13: 10698 | K13: =J13-J12 -> 0 | L13: =L12 -> 238479 | M13: =SUM(L13-L12) -> 0 | N13: =IF(K13>0,M13/K13,0) -> 0 | P13: =P12 -> 10873 | Q13: =IF(J13-P13<=0,"ok","oil change") -> ok | R13: 11221 | S13: =R13-R12 -> 9 | T13: 258169 | U13: =SUM(T13-T12) -> 2073 | V13: =IF(S13>0,U13/S13,0) -> 230.33333 | X13: =X12+180 -> 12069 | Y13: =IF(R13-X13<=0,"ok","oil change") -> ok | Z13: =C13+K13+S13 -> 9 | AA13: =U13+M13+E13 -> 2633 | AB13: =V13+N13+F13 -> 230.33333 | AC13: =IF(Z13>0,AA13/Z13,0) -> 292.55556 | AD13: =ELEC!Q13 -> 5000 | AE13: =SUM(AD13/Z13) -> 555.55556 | AF13: =SUM(AE13/1600) -> 0.34722222 | AG13: =SUM(320*AF13) -> 111.11111 | AH13: =SUM(AC13-AG13) -> 181.44444 | AI13: =AD13*AJ13 -> 1286.9198 | AJ13: =305/1185 -> 0.25738397 | AK13: =IF(Z13>0,AI13/Z13,0) -> 142.99109
A14: =ELEC!C14 -> 43994 | B14: 8676 | C14: =B14-B13 -> 4 | D14: 158308 | E14: =SUM(D14-D13) -> 1310 | F14: =IF(C14>0,E14/C14,0) -> 327.5 | H14: =H13 -> 8770 | I14: =IF(B14-H14<=0,"ok","oil change") -> ok | J14: 10698 | K14: =J14-J13 -> 0 | L14: =L13 -> 238479 | M14: =SUM(L14-L13) -> 0 | N14: =IF(K14>0,M14/K14,0) -> 0 | P14: =P13 -> 10873 | Q14: =IF(J14-P14<=0,"ok","oil change") -> ok | R14: 11226 | S14: =R14-R13 -> 5 | T14: 259153 | U14: =SUM(T14-T13) -> 984 | V14: =IF(S14>0,U14/S14,0) -> 196.8 | X14: =X13 -> 12069 | Y14: =IF(R14-X14<=0,"ok","oil change") -> ok | Z14: =C14+K14+S14 -> 9 | AA14: =U14+M14+E14 -> 2294 | AB14: =V14+N14+F14 -> 524.3 | AC14: =IF(Z14>0,AA14/Z14,0) -> 254.88889 | AD14: =ELEC!Q14 -> 6000 | AE14: =SUM(AD14/Z14) -> 666.66667 | AF14: =SUM(AE14/1600) -> 0.41666667 | AG14: =SUM(320*AF14) -> 133.33333 | AH14: =SUM(AC14-AG14) -> 121.55556 | AI14: =AD14*AJ14 -> 1544.3038 | AJ14: =305/1185 -> 0.25738397 | AK14: =IF(Z14>0,AI14/Z14,0) -> 171.58931
A15: =ELEC!C15 -> 43995 | B15: 8684 | C15: =B15-B14 -> 8 | D15: 159491 | E15: =SUM(D15-D14) -> 1183 | F15: =IF(C15>0,E15/C15,0) -> 147.875 | H15: =H14 -> 8770 | I15: =IF(B15-H15<=0,"ok","oil change") -> ok | J15: =J14 -> 10698 | K15: =J15-J14 -> 0 | L15: =L14 -> 238479 | M15: =SUM(L15-L14) -> 0 | N15: =IF(K15>0,M15/K15,0) -> 0 | P15: =P14 -> 10873 | Q15: =IF(J15-P15<=0,"ok","oil change") -> ok | R15: =R14 -> 11226 | S15: =R15-R14 -> 0 | T15: 259153 | U15: =SUM(T15-T14) -> 0 | V15: =IF(S15>0,U15/S15,0) -> 0 | X15: =X14 -> 12069 | Y15: =IF(R15-X15<=0,"ok","oil change") -> ok | Z15: =C15+K15+S15 -> 8 | AA15: =U15+M15+E15 -> 1183 | AB15: =V15+N15+F15 -> 147.875 | AC15: =IF(Z15>0,AA15/Z15,0) -> 147.875 | AD15: =ELEC!Q15 -> 6000 | AE15: =SUM(AD15/Z15) -> 750 | AF15: =SUM(AE15/1600) -> 0.46875 | AG15: =SUM(320*AF15) -> 150 | AH15: =SUM(AC15-AG15) -> -2.125 | AI15: =AD15*AJ15 -> 1544.3038 | AJ15: =305/1185 -> 0.25738397 | AK15: =IF(Z15>0,AI15/Z15,0) -> 193.03797
A16: =ELEC!C16 -> 43996 | B16: 8689 | C16: =B16-B15 -> 5 | D16: 159491 | E16: =SUM(D16-D15) -> 0 | F16: =IF(C16>0,E16/C16,0) -> 0 | H16: =H15 -> 8770 | I16: =IF(B16-H16<=0,"ok","oil change") -> ok | J16: 10698 | K16: =J16-J15 -> 0 | L16: =L15 -> 238479 | M16: =SUM(L16-L15) -> 0 | N16: =IF(K16>0,M16/K16,0) -> 0 | P16: =P15 -> 10873 | Q16: =IF(J16-P16<=0,"ok","oil change") -> ok | R16: 11226 | S16: =R16-R15 -> 0 | T16: =T15 -> 259153 | U16: =SUM(T16-T15) -> 0 | V16: =IF(S16>0,U16/S16,0) -> 0 | X16: =X15 -> 12069 | Y16: =IF(R16-X16<=0,"ok","oil change") -> ok | Z16: =C16+K16+S16 -> 5 | AA16: =U16+M16+E16 -> 0 | AB16: =V16+N16+F16 -> 0 | AC16: =IF(Z16>0,AA16/Z16,0) -> 0 | AD16: =ELEC!Q16 -> 3000 | AE16: =SUM(AD16/Z16) -> 600 | AF16: =SUM(AE16/1600) -> 0.375 | AG16: =SUM(320*AF16) -> 120 | AH16: =SUM(AC16-AG16) -> -120 | AI16: =AD16*AJ16 -> 772.1519 | AJ16: =305/1185 -> 0.25738397 | AK16: =IF(Z16>0,AI16/Z16,0) -> 154.43038
A17: =ELEC!C17 -> 43997 | B17: 8697 | C17: =B17-B16 -> 8 | D17: 160634 | E17: =SUM(D17-D16) -> 1143 | F17: =IF(C17>0,E17/C17,0) -> 142.875 | H17: =H16 -> 8770 | I17: =IF(B17-H17<=0,"ok","oil change") -> ok | J17: =J16 -> 10698 | K17: =J17-J16 -> 0 | L17: =L16 -> 238479 | M17: =SUM(L17-L16) -> 0 | N17: =IF(K17>0,M17/K17,0) -> 0 | P17: =P16 -> 10873 | Q17: =IF(J17-P17<=0,"ok","oil change") -> ok | R17: =R16 -> 11226 | S17: =R17-R16 -> 0 | T17: =T16 -> 259153 | U17: =SUM(T17-T16) -> 0 | V17: =IF(S17>0,U17/S17,0) -> 0 | X17: =X16 -> 12069 | Y17: =IF(R17-X17<=0,"ok","oil change") -> ok | Z17: =C17+K17+S17 -> 8 | AA17: =U17+M17+E17 -> 1143 | AB17: =V17+N17+F17 -> 142.875 | AC17: =IF(Z17>0,AA17/Z17,0) -> 142.875 | AD17: =ELEC!Q17 -> 6000 | AE17: =SUM(AD17/Z17) -> 750 | AF17: =SUM(AE17/1600) -> 0.46875 | AG17: =SUM(320*AF17) -> 150 | AH17: =SUM(AC17-AG17) -> -7.125 | AI17: =AD17*AJ17 -> 1544.3038 | AJ17: =305/1185 -> 0.25738397 | AK17: =IF(Z17>0,AI17/Z17,0) -> 193.03797
A18: =ELEC!C18 -> 43998 | B18: 8704 | C18: =B18-B17 -> 7 | D18: 161446 | E18: =SUM(D18-D17) -> 812 | F18: =IF(C18>0,E18/C18,0) -> 116 | H18: =H17 -> 8770 | I18: =IF(B18-H18<=0,"ok","oil change") -> ok | J18: =J17 -> 10698 | K18: =J18-J17 -> 0 | L18: =L17 -> 238479 | M18: =SUM(L18-L17) -> 0 | N18: =IF(K18>0,M18/K18,0) -> 0 | P18: =P17 -> 10873 | Q18: =IF(J18-P14<=0,"ok","oil change") -> ok | R18: =R17 -> 11226 | S18: =R18-R17 -> 0 | T18: =T17 -> 259153 | U18: =SUM(T18-T17) -> 0 | V18: =IF(S18>0,U18/S18,0) -> 0 | X18: =X17 -> 12069 | Y18: =IF(R18-X18<=0,"ok","oil change") -> ok | Z18: =C18+K18+S18 -> 7 | AA18: =U18+M18+E18 -> 812 | AB18: =V18+N18+F18 -> 116 | AC18: =IF(Z18>0,AA18/Z18,0) -> 116 | AD18: =ELEC!Q18 -> 5000 | AE18: =SUM(AD18/Z18) -> 714.28571 | AF18: =SUM(AE18/1600) -> 0.44642857 | AG18: =SUM(320*AF18) -> 142.85714 | AH18: =SUM(AC18-AG18) -> -26.857143 | AI18: =AD18*AJ18 -> 1286.9198 | AJ18: =305/1185 -> 0.25738397 | AK18: =IF(Z18>0,AI18/Z18,0) -> 183.84569
A19: =ELEC!C19 -> 43999 | B19: 8709 | C19: =B19-B18 -> 5 | D19: 162454 | E19: =SUM(D19-D18) -> 1008 | F19: =IF(C19>0,E19/C19,0) -> 201.6 | H19: =H18 -> 8770 | I19: =IF(B19-H19<=0,"ok","oil change") -> ok | J19: =J18 -> 10698 | K19: =J19-J18 -> 0 | L19: =L18 -> 238479 | M19: =SUM(L19-L18) -> 0 | N19: =IF(K19>0,M19/K19,0) -> 0 | P19: =P18 -> 10873 | Q19: =IF(J19-P19<=0,"ok","oil change") -> ok | R19: =R18 -> 11226 | S19: =R19-R18 -> 0 | T19: =T18 -> 259153 | U19: =SUM(T19-T18) -> 0 | V19: =IF(S19>0,U19/S19,0) -> 0 | X19: =X18 -> 12069 | Y19: =IF(R19-X19<=0,"ok","oil change") -> ok | Z19: =C19+K19+S19 -> 5 | AA19: =U19+M19+E19 -> 1008 | AB19: =V19+N19+F19 -> 201.6 | AC19: =IF(Z19>0,AA19/Z19,0) -> 201.6 | AD19: =ELEC!Q19 -> 3000 | AE19: =SUM(AD19/Z19) -> 600 | AF19: =SUM(AE19/1600) -> 0.375 | AG19: =SUM(320*AF19) -> 120 | AH19: =SUM(AC19-AG19) -> 81.6 | AI19: =AD19*AJ19 -> 772.1519 | AJ19: =305/1185 -> 0.25738397 | AK19: =IF(Z19>0,AI19/Z19,0) -> 154.43038
A20: =ELEC!C20 -> 44000 | B20: 8717 | C20: =B20-B19 -> 8 | D20: 163377 | E20: =SUM(D20-D19) -> 923 | F20: =IF(C20>0,E20/C20,0) -> 115.375 | H20: =H19 -> 8770 | I20: =IF(B20-H20<=0,"ok","oil change") -> ok | J20: 10698 | K20: =J20-J19 -> 0 | L20: =L19 -> 238479 | M20: =SUM(L20-L19) -> 0 | N20: =IF(K20>0,M20/K20,0) -> 0 | P20: =P19 -> 10873 | Q20: =IF(J20-P20<=0,"ok","oil change") -> ok | R20: 11226 | S20: =R20-R19 -> 0 | T20: =T19 -> 259153 | U20: =SUM(T20-T19) -> 0 | V20: =IF(S20>0,U20/S20,0) -> 0 | X20: =X19 -> 12069 | Y20: =IF(R20-X20<=0,"ok","oil change") -> ok | Z20: =C20+K20+S20 -> 8 | AA20: =U20+M20+E20 -> 923 | AB20: =V20+N20+F20 -> 115.375 | AC20: =IF(Z20>0,AA20/Z20,0) -> 115.375 | AD20: =ELEC!Q20 -> 6000 | AE20: =SUM(AD20/Z20) -> 750 | AF20: =SUM(AE20/1600) -> 0.46875 | AG20: =SUM(320*AF20) -> 150 | AH20: =SUM(AC20-AG20) -> -34.625 | AI20: =AD20*AJ20 -> 1544.3038 | AJ20: =305/1185 -> 0.25738397 | AK20: =IF(Z20>0,AI20/Z20,0) -> 193.03797
A21: =ELEC!C21 -> 44001 | B21: 8723 | C21: =B21-B20 -> 6 | D21: 164067 | E21: =SUM(D21-D20) -> 690 | F21: =IF(C21>0,E21/C21,0) -> 115 | H21: =H20 -> 8770 | I21: =IF(B21-H21<=0,"ok","oil change") -> ok | J21: =J20 -> 10698 | K21: =J21-J20 -> 0 | L21: =L20 -> 238479 | M21: =SUM(L21-L20) -> 0 | N21: =IF(K21>0,M21/K21,0) -> 0 | P21: =P20 -> 10873 | Q21: =IF(J21-P21<=0,"ok","oil change") -> ok | R21: =R20 -> 11226 | S21: =R21-R20 -> 0 | T21: =T20 -> 259153 | U21: =SUM(T21-T20) -> 0 | V21: =IF(S21>0,U21/S21,0) -> 0 | X21: =X20 -> 12069 | Y21: =Y20 -> ok | Z21: =C21+K21+S21 -> 6 | AA21: =U21+M21+E21 -> 690 | AB21: =V21+N21+F21 -> 115 | AC21: =IF(Z21>0,AA21/Z21,0) -> 115 | AD21: =ELEC!Q21 -> 5000 | AE21: =SUM(AD21/Z21) -> 833.33333 | AF21: =SUM(AE21/1600) -> 0.52083333 | AG21: =SUM(320*AF21) -> 166.66667 | AH21: =SUM(AC21-AG21) -> -51.666667 | AI21: =AD21*AJ21 -> 1286.9198 | AJ21: =305/1185 -> 0.25738397 | AK21: =IF(Z21>0,AI21/Z21,0) -> 214.48664
A22: =ELEC!C22 -> 44002 | B22: 8725 | C22: =B22-B21 -> 2 | D22: 164300 | E22: =SUM(D22-D21) -> 233 | F22: =IF(C22>0,E22/C22,0) -> 116.5 | H22: =H21 -> 8770 | I22: =IF(B22-H22<=0,"ok","oil change") -> ok | J22: =J21 -> 10698 | K22: =J22-J21 -> 0 | L22: =L21 -> 238479 | M22: =SUM(L22-L21) -> 0 | N22: =IF(K22>0,M22/K22,0) -> 0 | P22: =P21 -> 10873 | Q22: =IF(J22-P22<=0,"ok","oil change") -> ok | R22: 11229 | S22: =R22-R21 -> 3 | T22: 259611 | U22: =SUM(T22-T21) -> 458 | V22: =IF(S22>0,U22/S22,0) -> 152.66667 | X22: =X21 -> 12069 | Y22: =IF(R22-X22<=0,"ok","oil change") -> ok | Z22: =C22+K22+S22 -> 5 | AA22: =U22+M22+E22 -> 691 | AB22: =V22+N22+F22 -> 269.16667 | AC22: =IF(Z22>0,AA22/Z22,0) -> 138.2 | AD22: =ELEC!Q22 -> 3000 | AE22: =SUM(AD22/Z22) -> 600 | AF22: =SUM(AE22/1600) -> 0.375 | AG22: =SUM(320*AF22) -> 120 | AH22: =SUM(AC22-AG22) -> 18.2 | AI22: =AD22*AJ22 -> 772.1519 | AJ22: =305/1185 -> 0.25738397 | AK22: =IF(Z22>0,AI22/Z22,0) -> 154.43038
A23: =ELEC!C23 -> 44003 | B23: 8725 | C23: =B23-B22 -> 0 | D23: 164300 | E23: =SUM(D23-D22) -> 0 | F23: =IF(C23>0,E23/C23,0) -> 0 | H23: =H22 -> 8770 | I23: =IF(B23-H23<=0,"ok","oil change") -> ok | J23: 10698 | K23: =J23-J22 -> 0 | L23: 238497 | M23: =SUM(L23-L22) -> 18 | N23: =IF(K23>0,M23/K23,0) -> 0 | P23: =P22 -> 10873 | Q23: =IF(J23-P23<=0,"ok","oil change") -> ok | R23: 11232 | S23: =R23-R22 -> 3 | T23: 260388 | U23: =SUM(T23-T22) -> 777 | V23: =IF(S23>0,U23/S23,0) -> 259 | X23: =X22 -> 12069 | Y23: =IF(R23-X23<=0,"ok","oil change") -> ok | Z23: =C23+K23+S23 -> 3 | AA23: =U23+M23+E23 -> 795 | AB23: =V23+N23+F23 -> 259 | AC23: =IF(Z23>0,AA23/Z23,0) -> 265 | AD23: =ELEC!Q23 -> 2000 | AE23: =SUM(AD23/Z23) -> 666.66667 | AF23: =SUM(AE23/1600) -> 0.41666667 | AG23: =SUM(320*AF23) -> 133.33333 | AH23: =SUM(AC23-AG23) -> 131.66667 | AI23: =AD23*AJ23 -> 514.76793 | AJ23: =305/1185 -> 0.25738397 | AK23: =IF(Z23>0,AI23/Z23,0) -> 171.58931
A24: =ELEC!C24 -> 44004 | B24: =B23 -> 8725 | C24: =B24-B23 -> 0 | D24: =D23 -> 164300 | E24: =SUM(D24-D23) -> 0 | F24: =IF(C24>0,E24/C24,0) -> 0 | H24: =H23 -> 8770 | I24: =IF(B24-H24<=0,"ok","oil change") -> ok | J24: =J23 -> 10698 | K24: =J24-J23 -> 0 | L24: =L23 -> 238497 | M24: =SUM(L24-L23) -> 0 | N24: =IF(K24>0,M24/K24,0) -> 0 | P24: =P23 -> 10873 | Q24: =IF(J24-P24<=0,"ok","oil change") -> ok | R24: 11238 | S24: =R24-R23 -> 6 | T24: 261853 | U24: =SUM(T24-T23) -> 1465 | V24: =IF(S24>0,U24/S24,0) -> 244.16667 | X24: =X23 -> 12069 | Y24: =IF(R24-X24<=0,"ok","oil change") -> ok | Z24: =C24+K24+S24 -> 6 | AA24: =U24+M24+E24 -> 1465 | AB24: =V24+N24+F24 -> 244.16667 | AC24: =IF(Z24>0,AA24/Z24,0) -> 244.16667 | AD24: =ELEC!Q24 -> 4000 | AE24: =SUM(AD24/Z24) -> 666.66667 | AF24: =SUM(AE24/1600) -> 0.41666667 | AG24: =SUM(320*AF24) -> 133.33333 | AH24: =SUM(AC24-AG24) -> 110.83333 | AI24: =AD24*AJ24 -> 1029.5359 | AJ24: =305/1185 -> 0.25738397 | AK24: =IF(Z24>0,AI24/Z24,0) -> 171.58931
A25: =ELEC!C25 -> 44005 | B25: =B24 -> 8725 | C25: =B25-B24 -> 0 | D25: =D24 -> 164300 | E25: =SUM(D25-D24) -> 0 | F25: =IF(C25>0,E25/C25,0) -> 0 | H25: 8770 | I25: =IF(B25-H25<=0,"ok","oil change") -> ok | J25: =J24 -> 10698 | K25: =J25-J24 -> 0 | L25: =L24 -> 238497 | M25: =SUM(L25-L24) -> 0 | N25: =IF(K25>0,M25/K25,0) -> 0 | P25: =P24 -> 10873 | Q25: =IF(J25-P25<=0,"ok","oil change") -> ok | R25: 11244 | S25: =R25-R24 -> 6 | T25: 263169 | U25: =SUM(T25-T24) -> 1316 | V25: =IF(S25>0,U25/S25,0) -> 219.33333 | X25: =X24 -> 12069 | Y25: =IF(R25-X25<=0,"ok","oil change") -> ok | Z25: =C25+K25+S25 -> 6 | AA25: =U25+M25+E25 -> 1316 | AB25: =V25+N25+F25 -> 219.33333 | AC25: =IF(Z25>0,AA25/Z25,0) -> 219.33333 | AD25: =ELEC!Q25 -> 4000 | AE25: =SUM(AD25/Z25) -> 666.66667 | AF25: =SUM(AE25/1600) -> 0.41666667 | AG25: =SUM(320*AF25) -> 133.33333 | AH25: =SUM(AC25-AG25) -> 86 | AI25: =AD25*AJ25 -> 1029.5359 | AJ25: =305/1185 -> 0.25738397 | AK25: =IF(Z25>0,AI25/Z25,0) -> 171.58931
A26: =ELEC!C26 -> 44006 | B26: 8725 | C26: =B26-B25 -> 0 | D26: 164310 | E26: =SUM(D26-D25) -> 10 | F26: =IF(C26>0,E26/C26,0) -> 0 | H26: =H25 -> 8770 | I26: =IF(B26-H26<=0,"ok","oil change") -> ok | J26: 10698 | K26: =J26-J25 -> 0 | L26: 238497 | M26: =SUM(L26-L25) -> 0 | N26: =IF(K26>0,M26/K26,0) -> 0 | P26: =P25 -> 10873 | Q26: =IF(J26-P26<=0,"ok","oil change") -> ok | R26: 11250 | S26: =R26-R25 -> 6 | T26: 264452 | U26: =SUM(T26-T25) -> 1283 | V26: =IF(S26>0,U26/S26,0) -> 213.83333 | X26: =X25 -> 12069 | Y26: =IF(R26-X26<=0,"ok","oil change") -> ok | Z26: =C26+K26+S26 -> 6 | AA26: =U26+M26+E26 -> 1293 | AB26: =V26+N26+F26 -> 213.83333 | AC26: =IF(Z26>0,AA26/Z26,0) -> 215.5 | AD26: =ELEC!Q26 -> 4000 | AE26: =SUM(AD26/Z26) -> 666.66667 | AF26: =SUM(AE26/1600) -> 0.41666667 | AG26: =SUM(320*AF26) -> 133.33333 | AH26: =SUM(AC26-AG26) -> 82.166667 | AI26: =AD26*AJ26 -> 1029.5359 | AJ26: =305/1185 -> 0.25738397 | AK26: =IF(Z26>0,AI26/Z26,0) -> 171.58931
A27: =ELEC!C27 -> 44007 | B27: 8728 | C27: =B27-B26 -> 3 | D27: 164584 | E27: =SUM(D27-D26) -> 274 | F27: =IF(C27>0,E27/C27,0) -> 91.333333 | H27: =H26 -> 8770 | I27: =IF(B27-H27<=0,"ok","oil change") -> ok | J27: =J26 -> 10698 | K27: =J27-J26 -> 0 | L27: =L26 -> 238497 | M27: =SUM(L27-L26) -> 0 | N27: =IF(K27>0,M27/K27,0) -> 0 | P27: =P26 -> 10873 | Q27: =IF(J27-P27<=0,"ok","oil change") -> ok | R27: 11252 | S27: =R27-R26 -> 2 | T27: 264751 | U27: =SUM(T27-T26) -> 299 | V27: =IF(S27>0,U27/S27,0) -> 149.5 | X27: =X26 -> 12069 | Y27: =IF(R27-X27<=0,"ok","oil change") -> ok | Z27: =C27+K27+S27 -> 5 | AA27: =U27+M27+E27 -> 573 | AB27: =V27+N27+F27 -> 240.83333 | AC27: =IF(Z27>0,AA27/Z27,0) -> 114.6 | AD27: =ELEC!Q27 -> 4000 | AE27: =SUM(AD27/Z27) -> 800 | AF27: =SUM(AE27/1600) -> 0.5 | AG27: =SUM(320*AF27) -> 160 | AH27: =SUM(AC27-AG27) -> -45.4 | AI27: =AD27*AJ27 -> 1029.5359 | AJ27: =305/1185 -> 0.25738397 | AK27: =IF(Z27>0,AI27/Z27,0) -> 205.90717
A28: =ELEC!C28 -> 44008 | B28: 8734 | C28: =B28-B27 -> 6 | D28: 165427 | E28: =SUM(D28-D27) -> 843 | F28: =IF(C28>0,E28/C28,0) -> 140.5 | H28: =H27 -> 8770 | I28: =IF(B28-H28<=0,"ok","oil change") -> ok | J28: 10698 | K28: =J28-J27 -> 0 | L28: =L27 -> 238497 | M28: =SUM(L28-L27) -> 0 | N28: =IF(K28>0,M28/K28,0) -> 0 | P28: =P27 -> 10873 | Q28: =IF(J28-P28<=0,"ok","oil change") -> ok | R28: =R27 -> 11252 | S28: =R28-R27 -> 0 | T28: 264771 | U28: =SUM(T28-T27) -> 20 | V28: =IF(S28>0,U28/S28,0) -> 0 | X28: =X27 -> 12069 | Y28: =IF(R28-X28<=0,"ok","oil change") -> ok | Z28: =C28+K28+S28 -> 6 | AA28: =U28+M28+E28 -> 863 | AB28: =V28+N28+F28 -> 140.5 | AC28: =IF(Z28>0,AA28/Z28,0) -> 143.83333 | AD28: =ELEC!Q28 -> 5000 | AE28: =SUM(AD28/Z28) -> 833.33333 | AF28: =SUM(AE28/1600) -> 0.52083333 | AG28: =SUM(320*AF28) -> 166.66667 | AH28: =SUM(AC28-AG28) -> -22.833333 | AI28: =AD28*AJ28 -> 1286.9198 | AJ28: =305/1185 -> 0.25738397 | AK28: =IF(Z28>0,AI28/Z28,0) -> 214.48664
A29: =ELEC!C29 -> 44009 | B29: 8741 | C29: =B29-B28 -> 7 | D29: 166182 | E29: =SUM(D29-D28) -> 755 | F29: =IF(C29>0,E29/C29,0) -> 107.85714 | H29: =H28 -> 8770 | I29: =IF(B29-H29<=0,"ok","oil change") -> ok | J29: 10698 | K29: =J29-J28 -> 0 | L29: =L28 -> 238497 | M29: =SUM(L29-L28) -> 0 | N29: =IF(K29>0,M29/K29,0) -> 0 | P29: =P28 -> 10873 | Q29: =IF(J29-P29<=0,"ok","oil change") -> ok | R29: =R28 -> 11252 | S29: =R29-R28 -> 0 | T29: =T28 -> 264771 | U29: =SUM(T29-T28) -> 0 | V29: =IF(S29>0,U29/S29,0) -> 0 | X29: =X28 -> 12069 | Y29: =IF(R29-X29<=0,"ok","oil change") -> ok | Z29: =C29+K29+S29 -> 7 | AA29: =U29+M29+E29 -> 755 | AB29: =V29+N29+F29 -> 107.85714 | AC29: =IF(Z29>0,AA29/Z29,0) -> 107.85714 | AD29: =ELEC!Q29 -> 5000 | AE29: =SUM(AD29/Z29) -> 714.28571 | AF29: =SUM(AE29/1600) -> 0.44642857 | AG29: =SUM(320*AF29) -> 142.85714 | AH29: =SUM(AC29-AG29) -> -35 | AI29: =AD29*AJ29 -> 1286.9198 | AJ29: =305/1185 -> 0.25738397 | AK29: =IF(Z29>0,AI29/Z29,0) -> 183.84569
A30: =ELEC!C30 -> 44010 | B30: 8748 | C30: =B30-B29 -> 7 | D30: 167174 | E30: =SUM(D30-D29) -> 992 | F30: =IF(C30>0,E30/C30,0) -> 141.71429 | H30: =H29 -> 8770 | I30: =IF(B30-H30<=0,"ok","oil change") -> ok | J30: =J29 -> 10698 | K30: =J30-J29 -> 0 | L30: =L29 -> 238497 | M30: =SUM(L30-L29) -> 0 | N30: =IF(K30>0,M30/K30,0) -> 0 | P30: =P29 -> 10873 | Q30: =IF(J30-P30<=0,"ok","oil change") -> ok | R30: =R29 -> 11252 | S30: =R30-R29 -> 0 | T30: =T29 -> 264771 | U30: =SUM(T30-T29) -> 0 | V30: =IF(S30>0,U30/S30,0) -> 0 | X30: =X29 -> 12069 | Y30: =IF(R30-X30<=0,"ok","oil change") -> ok | Z30: =C30+K30+S30 -> 7 | AA30: =U30+M30+E30 -> 992 | AB30: =V30+N30+F30 -> 141.71429 | AC30: =IF(Z30>0,AA30/Z30,0) -> 141.71429 | AD30: =ELEC!Q30 -> 6000 | AE30: =SUM(AD30/Z30) -> 857.14286 | AF30: =SUM(AE30/1600) -> 0.53571429 | AG30: =SUM(320*AF30) -> 171.42857 | AH30: =SUM(AC30-AG30) -> -29.714286 | AI30: =AD30*AJ30 -> 1544.3038 | AJ30: =305/1185 -> 0.25738397 | AK30: =IF(Z30>0,AI30/Z30,0) -> 220.61483
