Workbook

Sheet Total
A1: Site Name | B1: Day | C1: Month | D1: Year | E1: Total Electricity Kwh | F1: Electricity Tariff ($/Kwh) | G1: Total Fuel Oil (Liters) | H1: Fuel Oil $/Liter | I1: LPG (Kg) | J1: LPG $/Kg | K1: Water Utility Supply (m3) m3 | L1: Water Utility Supply (m3) $/m3 | M1: Irrigation Water (m3) m3 | N1: Irrigation water $/m3 | O1: Room Nights
A2: Beirut | B2: 1 | C2: 7 | D2: 2020 | E2: =ELEC!N3 -> 18028 | F2: =SUM('EDl log'!T4) -> 0.07605543 | G2: =-tanks!AW6 -> 417 | H2: =SUM(tanks!AV6) -> 0.4624 | I2: =('B5'!AU5)*0.51 -> 45.9 | J2: ='B5'!AX5/0.51 -> 1.372549 | K2: =WATER!I6 -> 0 | L2: =SUM(WATER!J6) -> 0 | M2: =WATER!Q6 -> 0 | N2: 0.6 | O2: =ELEC!B3 -> 12.995
A3: Beirut | B3: =B2+1 -> 2 | C3: 7 | D3: 2020 | E3: =ELEC!N4 -> 18859 | F3: =SUM('EDl log'!T5) -> 0.14347425 | G3: =-tanks!AW7 -> 735 | H3: =SUM(tanks!AV7) -> 0.4624 | I3: =('B5'!AU6)*0.51 -> 204 | J3: ='B5'!AX6/0.51 -> 1.372549 | K3: =WATER!I7 -> 393 | L3: =SUM(WATER!J7) -> 0.61561192 | M3: =WATER!Q7 -> 0 | N3: 0.6 | O3: =ELEC!B4 -> 8.97
A4: Beirut | B4: =B3+1 -> 3 | C4: 7 | D4: 2020 | E4: =ELEC!N5 -> 20891 | F4: =SUM('EDl log'!T6) -> 0.12581363 | G4: =-tanks!AW8 -> 388 | H4: =SUM(tanks!AV8) -> 0.4624 | I4: =('B5'!AU7)*0.51 -> 91.8 | J4: ='B5'!AX7/0.51 -> 1.372549 | K4: =WATER!I8 -> 0 | L4: =SUM(WATER!J8) -> 0 | M4: =WATER!Q8 -> 0 | N4: 0.6 | O4: =ELEC!B5 -> 20.01
A5: Beirut | B5: =B4+1 -> 4 | C5: 7 | D5: 2020 | E5: =ELEC!N6 -> 18152 | F5: =SUM('EDl log'!T7) -> 0.14411071 | G5: =-tanks!AW9 -> 534 | H5: =SUM(tanks!AV9) -> 0.4624 | I5: =('B5'!AU8)*0.51 -> 15.3 | J5: ='B5'!AX8/0.51 -> 1.372549 | K5: =WATER!I9 -> 563 | L5: =SUM(WATER!J9) -> 0.42972555 | M5: =WATER!Q9 -> 0 | N5: 0.6 | O5: =ELEC!B6 -> 20.01
A6: Beirut | B6: =B5+1 -> 5 | C6: 7 | D6: 2020 | E6: =ELEC!N7 -> 18161 | F6: =SUM('EDl log'!T8) -> 0.14808001 | G6: =-tanks!AW10 -> 338 | H6: =SUM(tanks!AV10) -> 0.4624 | I6: =('B5'!AU9)*0.51 -> 61.2 | J6: ='B5'!AX9/0.51 -> 1.372549 | K6: =WATER!I10 -> 45 | L6: =SUM(WATER!J10) -> 5.3763441 | M6: =WATER!Q10 -> 0 | N6: 0.6 | O6: =ELEC!B7 -> 18.009
A7: Beirut | B7: =B6+1 -> 6 | C7: 7 | D7: 2020 | E7: =ELEC!N8 -> 20764 | F7: =SUM('EDl log'!T9) -> 0.11673631 | G7: =-tanks!AW11 -> 430 | H7: =SUM(tanks!AV11) -> 0.4624 | I7: =('B5'!AU10)*0.51 -> 76.5 | J7: ='B5'!AX10/0.51 -> 1.372549 | K7: =WATER!I11 -> 227 | L7: =SUM(WATER!J11) -> 1.0657951 | M7: =WATER!Q11 -> 0 | N7: 0.6 | O7: =ELEC!B8 -> 18.998
A8: Beirut | B8: =B7+1 -> 7 | C8: 7 | D8: 2020 | E8: =ELEC!N9 -> 20479 | F8: =SUM('EDl log'!T10) -> 0.12312308 | G8: =-tanks!AW12 -> 657 | H8: =SUM(tanks!AV12) -> 0.4624 | I8: =('B5'!AU11)*0.51 -> 76.5 | J8: ='B5'!AX11/0.51 -> 1.372549 | K8: =WATER!I12 -> 201 | L8: =SUM(WATER!J12) -> 1.2036591 | M8: =WATER!Q12 -> 0 | N8: 0.6 | O8: =ELEC!B9 -> 18.009
A9: Beirut | B9: =B8+1 -> 8 | C9: 7 | D9: 2020 | E9: =ELEC!N10 -> 23543 | F9: =SUM('EDl log'!T11) -> 0.10181056 | G9: =-tanks!AW13 -> 512 | H9: =SUM(tanks!AV13) -> 0.5284 | I9: =('B5'!AU12)*0.51 -> 107.1 | J9: ='B5'!AX12/0.51 -> 1.372549 | K9: =WATER!I13 -> 0 | L9: =SUM(WATER!J13) -> 0 | M9: =WATER!Q13 -> 0 | N9: 0.6 | O9: =ELEC!B10 -> 20.01
A10: Beirut | B10: =B9+1 -> 9 | C10: 7 | D10: 2020 | E10: =ELEC!N11 -> 18109 | F10: =SUM('EDl log'!T12) -> 0.18501511 | G10: =-tanks!AW14 -> 256 | H10: =SUM(tanks!AV14) -> 0.5284 | I10: =('B5'!AU13)*0.51 -> 198.9 | J10: ='B5'!AX13/0.51 -> 1.372549 | K10: =WATER!I14 -> 0 | L10: =SUM(WATER!J14) -> 0 | M10: =WATER!Q14 -> 0 | N10: 0.6 | O10: =ELEC!B11 -> 25.001
A11: Beirut | B11: =B10+1 -> 10 | C11: 7 | D11: 2020 | E11: =ELEC!N12 -> 20053 | F11: =SUM('EDl log'!T13) -> 0.053734013 | G11: =-tanks!AW15 -> 342.8 | H11: =SUM(tanks!AV15) -> 0.5284 | I11: =('B5'!AU14)*0.51 -> 91.8 | J11: ='B5'!AX14/0.51 -> 1.372549 | K11: =WATER!I15 -> 112 | L11: =SUM(WATER!J15) -> 2.1601382 | M11: =WATER!Q15 -> 0 | N11: 0.6 | O11: =ELEC!B12 -> 25.99
A12: Beirut | B12: =B11+1 -> 11 | C12: 7 | D12: 2020 | E12: =ELEC!N13 -> 21073 | F12: =SUM('EDl log'!T14) -> 0.14727445 | G12: =-tanks!AW16 -> 335 | H12: =SUM(tanks!AV16) -> 0.5284 | I12: =('B5'!AU15)*0.51 -> 61.2 | J12: ='B5'!AX15/0.51 -> 1.372549 | K12: =WATER!I16 -> 0 | L12: =SUM(WATER!J16) -> 0 | M12: =WATER!Q16 -> 0 | N12: 0.6 | O12: =ELEC!B13 -> 37.95
A13: Beirut | B13: =B12+1 -> 12 | C13: 7 | D13: 2020 | E13: =ELEC!N14 -> 20084 | F13: =SUM('EDl log'!T15) -> 0.15428782 | G13: =-tanks!AW17 -> 220 | H13: =SUM(tanks!AV17) -> 0.5284 | I13: =('B5'!AU16)*0.51 -> 15.3 | J13: ='B5'!AX16/0.51 -> 1.372549 | K13: =WATER!I17 -> 271 | L13: =SUM(WATER!J17) -> 0.89275086 | M13: =WATER!Q17 -> 0 | N13: 0.6 | O13: =ELEC!B14 -> 23
A14: Beirut | B14: =B13+1 -> 13 | C14: 7 | D14: 2020 | E14: =ELEC!N15 -> 19864 | F14: =SUM('EDl log'!T16) -> 0.13118039 | G14: =-tanks!AW18 -> 165 | H14: =SUM(tanks!AV18) -> 0.5284 | I14: =('B5'!AU17)*0.51 -> 30.6 | J14: ='B5'!AX17/0.51 -> 1.372549 | K14: =WATER!I18 -> 0 | L14: =SUM(WATER!J18) -> 0 | M14: =WATER!Q18 -> 0 | N14: 0.6 | O14: =ELEC!B15 -> 27.991
... A31: Beirut | B31: =B30+1 -> 30 | C31: 7 | D31: 2020 | E31: =ELEC!N32 -> 0 | F31: =SUM('EDl log'!T33) -> 0 | G31: =-tanks!AW35 -> 0 | H31: =SUM(tanks!AV35) -> 0.5383 | I31: =('B5'!AU34)*0.51 -> 0 | J31: ='B5'!AX34/0.51 -> 1.372549 | K31: =WATER!I35 -> 0 | L31: =SUM(WATER!J35) -> 0 | M31: =WATER!Q35 -> 0 | N31: 0.6 | O31: =ELEC!B32 -> 0
A32: Beirut | B32: =B31+1 -> 31 | C32: 7 | D32: 2020 | E32: =ELEC!N33 -> 0 | F32: =SUM('EDl log'!T35) -> 0 | G32: =-tanks!AW37 -> 0 | H32: =SUM(tanks!AV37) -> 0 | I32: =('B5'!AU36)*0.51 -> 1417.8 | J32: ='B5'!AX36/0.51 -> 0 | K32: =WATER!I37 -> 2195 | L32: =SUM(WATER!J37) -> 0 | M32: =WATER!Q37 -> 0 | N32: 0.6 | O32: =ELEC!B33 -> 23.94875

Sheet Submetering
A1: Site Name | B1: Day | C1: Month | D1: Year | E1: ATS1 Kwh | F1: ATS2 Kwh | G1: ATS3 Kwh | H1: ATS4 Kwh | I1: ATS5 Kwh | J1: Guest (m3) | K1: Kitchen & Laundry (m3) | L1: Room Nights
A2: Beirut | B2: 1 | C2: 7 | D2: 2020 | E2: =ELEC!M3 -> 7896 | F2: =ELEC!K3 -> 2847 | G2: =ELEC!I3 -> 1774 | H2: =ELEC!E3 -> 3656 | I2: =ELEC!G3 -> 1855 | J2: =WATER!Y6 -> 115 | K2: =WATER!AJ6 -> 10 | L2: =ELEC!B3 -> 12.995
A3: Beirut | B3: =B2+1 -> 2 | C3: 7 | D3: 2020 | E3: =ELEC!M4 -> 8320 | F3: =ELEC!K4 -> 3057 | G3: =ELEC!I4 -> 1778 | H3: =ELEC!E4 -> 3856 | I3: =ELEC!G4 -> 1848 | J3: =WATER!Y7 -> 69 | K3: =WATER!AJ7 -> 48 | L3: =ELEC!B4 -> 8.97
A4: Beirut | B4: =B3+1 -> 3 | C4: 7 | D4: 2020 | E4: =ELEC!M5 -> 9244 | F4: =ELEC!K5 -> 3108 | G4: =ELEC!I5 -> 2010 | H4: =ELEC!E5 -> 4478 | I4: =ELEC!G5 -> 2051 | J4: =WATER!Y8 -> 48 | K4: =WATER!AJ8 -> 52 | L4: =ELEC!B5 -> 20.01
A5: Beirut | B5: =B4+1 -> 4 | C5: 7 | D5: 2020 | E5: =ELEC!M6 -> 8346 | F5: =ELEC!K6 -> 2220 | G5: =ELEC!I6 -> 1890 | H5: =ELEC!E6 -> 3772 | I5: =ELEC!G6 -> 1924 | J5: =WATER!Y9 -> 180 | K5: =WATER!AJ9 -> 73 | L5: =ELEC!B6 -> 20.01
A6: Beirut | B6: =B5+1 -> 5 | C6: 7 | D6: 2020 | E6: =ELEC!M7 -> 6172 | F6: =ELEC!K7 -> 2178 | G6: =ELEC!I7 -> 1996 | H6: =ELEC!E7 -> 5838 | I6: =ELEC!G7 -> 1977 | J6: =WATER!Y10 -> 2 | K6: =WATER!AJ10 -> 1 | L6: =ELEC!B7 -> 18.009
A7: Beirut | B7: =B6+1 -> 6 | C7: 7 | D7: 2020 | E7: =ELEC!M8 -> 8976 | F7: =ELEC!K8 -> 2448 | G7: =ELEC!I8 -> 2216 | H7: =ELEC!E8 -> 5028 | I7: =ELEC!G8 -> 2096 | J7: =WATER!Y11 -> 110 | K7: =WATER!AJ11 -> 43 | L7: =ELEC!B8 -> 18.998
A8: Beirut | B8: =B7+1 -> 7 | C8: 7 | D8: 2020 | E8: =ELEC!M9 -> 6248 | F8: =ELEC!K9 -> 2470 | G8: =ELEC!I9 -> 2320 | H8: =ELEC!E9 -> 7468 | I8: =ELEC!G9 -> 1973 | J8: =WATER!Y12 -> 111 | K8: =WATER!AJ12 -> 53 | L8: =ELEC!B9 -> 18.009
A9: Beirut | B9: =B8+1 -> 8 | C9: 7 | D9: 2020 | E9: =ELEC!M10 -> 10244 | F9: =ELEC!K10 -> 3566 | G9: =ELEC!I10 -> 2396 | H9: =ELEC!E10 -> 5190 | I9: =ELEC!G10 -> 2147 | J9: =WATER!Y13 -> 0 | K9: =WATER!AJ13 -> 0 | L9: =ELEC!B10 -> 20.01
A10: Beirut | B10: =B9+1 -> 9 | C10: 7 | D10: 2020 | E10: =ELEC!M11 -> 7658 | F10: =ELEC!K11 -> 2358 | G10: =ELEC!I11 -> 2000 | H10: =ELEC!E11 -> 4328 | I10: =ELEC!G11 -> 1765 | J10: =WATER!Y14 -> 0 | K10: =WATER!AJ14 -> 0 | L10: =ELEC!B11 -> 25.001
A11: Beirut | B11: =B10+1 -> 10 | C11: 7 | D11: 2020 | E11: =ELEC!M12 -> 3718 | F11: =ELEC!K12 -> 2532 | G11: =ELEC!I12 -> 2376 | H11: =ELEC!E12 -> 9500 | I11: =ELEC!G12 -> 1927 | J11: =WATER!Y15 -> 91 | K11: =WATER!AJ15 -> 24 | L11: =ELEC!B12 -> 25.99
A12: Beirut | B12: =B11+1 -> 11 | C12: 7 | D12: 2020 | E12: =ELEC!M13 -> 6858 | F12: =ELEC!K13 -> 3036 | G12: =ELEC!I13 -> 2372 | H12: =ELEC!E13 -> 6870 | I12: =ELEC!G13 -> 1937 | J12: =WATER!Y16 -> 0 | K12: =WATER!AJ16 -> 0 | L12: =ELEC!B13 -> 37.95
A13: Beirut | B13: =B12+1 -> 12 | C13: 7 | D13: 2020 | E13: =ELEC!M14 -> 8808 | F13: =ELEC!K14 -> 2836 | G13: =ELEC!I14 -> 2350 | H13: =ELEC!E14 -> 4100 | I13: =ELEC!G14 -> 1990 | J13: =WATER!Y17 -> 42 | K13: =WATER!AJ17 -> 66 | L13: =ELEC!B14 -> 23
A14: Beirut | B14: =B13+1 -> 13 | C14: 7 | D14: 2020 | E14: =ELEC!M15 -> 8276 | F14: =ELEC!K15 -> 2050 | G14: =ELEC!I15 -> 2418 | H14: =ELEC!E15 -> 4884 | I14: =ELEC!G15 -> 2236 | J14: =WATER!Y18 -> 3 | K14: =WATER!AJ18 -> 0 | L14: =ELEC!B15 -> 27.991
... A31: Beirut | B31: =B30+1 -> 30 | C31: 7 | D31: 2020 | E31: =ELEC!M32 -> 0 | F31: =ELEC!K32 -> 0 | G31: =ELEC!I32 -> 0 | H31: =ELEC!E32 -> 0 | I31: =ELEC!G32 -> 0 | J31: =WATER!Y35 -> 0 | K31: =WATER!AJ35 -> 0 | L31: =ELEC!B32 -> 0
A32: Beirut | B32: =B31+1 -> 31 | C32: 7 | D32: 2020 | E32: =ELEC!M33 -> 0 | F32: =ELEC!K33 -> 0 | G32: =ELEC!I33 -> 0 | H32: =ELEC!E33 -> 0 | I32: =ELEC!G33 -> 0 | J32: =WATER!Y36 -> 0 | K32: =WATER!AJ37 -> 423 | L32: =ELEC!B33 -> 23.94875

Sheet ELEC
A1: OOC | B1: Room OCC | D1: MDB3 | E1: MDB3/day | F1: EMDB2 | G1: EMDB2/day | H1: EMDB1 | I1: EMDB1/day | J1: MDB2 | K1: mdb2/day | L1: MDB1 | M1: MDB1/Day | N1: Total KWH | O1: KWH/Rooc | P1: Gen MHW | Q1: Gen/Day KWH | R1: EDL KWH | S1: CH1 RH | T1: RH | U1: C1h1 power | V1: CH1 Con KWH | W1: CH2 RH | X1: RH | Y1: Ch2 power | Z1: CH2 Con KWH | AA1: CH3 RH | AB1: RH | AC1: Ch3 power | AD1: CH3 Con KWH | AE1: RH total | AF1: KWH total | AG1: AVG chiller KW/Hr
A2: =[1]ELEC!A32 -> 0.0478 | B2: =[1]ELEC!B32 -> 10.994 | C2: 44012 | D2: =[1]ELEC!D32 -> 31865522 | E2: =[1]ELEC!E32 -> 4902 | F2: =[1]ELEC!F32 -> 3741866 | G2: =[1]ELEC!G32 -> 1782 | H2: =[1]ELEC!H32 -> 17521942 | I2: =[1]ELEC!I32 -> 1668 | J2: =[1]ELEC!J32 -> 28525590 | K2: =[1]ELEC!K32 -> 2504 | ... AI2: =[1]ELEC!AI32 -> -94226
A3: ='General information '!F6 -> 0.0565 | B3: =SUM(230*A3) -> 12.995 | C3: 44013 | D3: 31869178 | E3: =D3-D2 -> 3656 | F3: 3743721 | G3: =F3-F2 -> 1855 | H3: 17523716 | I3: =H3-H2 -> 1774 | J3: 28528437 | K3: =J3-J2 -> 2847 | L3: 23241532 | M3: =L3-L2 -> 7896 | N3: =M3+K3+I3+G3+E3 -> 18028 | O3: =IF(B3>0,N3/B3,0) -> 1387.3028 | P3: 15689 | Q3: =(P3-P2)*1000 -> 14000 | R3: =+N3-Q3 -> 4028 | S3: 8899 | T3: =S3-S2 -> 16 | U3: 141258 | V3: =U3-U2 -> 3740 | W3: 31853 | X3: =W3-W2 -> 0 | Y3: =Y2 -> 625865 | Z3: =Y3-Y2 -> 0 | AA3: 35228 | AB3: =AA3-AA2 -> 0 | AC3: =AC2 -> 814514 | AD3: =AC3-AC2 -> 0 | AE3: =AB3+X3+T3 -> 16 | AF3: =V3+Z3+AD3 -> 3740 | AG3: =IF(AE3>0,AF3/AE3,0) -> 233.75
A4: ='General information '!F7 -> 0.039 | B4: =SUM(230*A4) -> 8.97 | C4: 44014 | D4: 31873034 | E4: =D4-D3 -> 3856 | F4: 3745569 | G4: =F4-F3 -> 1848 | H4: 17525494 | I4: =H4-H3 -> 1778 | J4: 28531494 | K4: =J4-J3 -> 3057 | L4: 23249852 | M4: =L4-L3 -> 8320 | N4: =M4+K4+I4+G4+E4 -> 18859 | O4: =IF(B4>0,N4/B4,0) -> 2102.4526 | P4: 15702 | Q4: =(P4-P3)*1000 -> 13000 | R4: =N4-Q4 -> 5859 | S4: 8921 | T4: =S4-S3 -> 22 | U4: 146286 | V4: =U4-U3 -> 5028 | W4: =W3 -> 31853 | X4: =W4-W3 -> 0 | Y4: =Y3 -> 625865 | Z4: =Y4-Y3 -> 0 | AA4: =AA3 -> 35228 | AB4: =AA4-AA3 -> 0 | AC4: =AC3 -> 814514 | AD4: =AC4-AC3 -> 0 | AE4: =AB4+X4+T4 -> 22 | AF4: =V4+Z4+AD4 -> 5028 | AG4: =IF(AE4>0,AF4/AE4,0) -> 228.54545
A5: ='General information '!F8 -> 0.087 | B5: =SUM(230*A5) -> 20.01 | C5: 44015 | D5: 31877512 | E5: =D5-D4 -> 4478 | F5: 3747620 | G5: =F5-F4 -> 2051 | H5: 17527504 | I5: =H5-H4 -> 2010 | J5: 28534602 | K5: =J5-J4 -> 3108 | L5: 23259096 | M5: =L5-L4 -> 9244 | N5: =M5+K5+I5+G5+E5 -> 20891 | O5: =IF(B5>0,N5/B5,0) -> 1044.028 | P5: 15716 | Q5: =(P5-P4)*1000 -> 14000 | R5: =N5-Q5 -> 6891 | S5: 8939 | T5: =S5-S4 -> 18 | U5: 150883 | V5: =U5-U4 -> 4597 | W5: =W4 -> 31853 | X5: =W5-W4 -> 0 | Y5: =Y4 -> 625865 | Z5: =Y5-Y4 -> 0 | AA5: 35229 | AB5: =AA5-AA4 -> 1 | AC5: 814845 | AD5: =AC5-AC4 -> 331 | AE5: =AB5+X5+T5 -> 19 | AF5: =V5+Z5+AD5 -> 4928 | AG5: =IF(AE5>0,AF5/AE5,0) -> 259.36842 | AI5: =R5-'EDl log'!B3 -> -105299
A6: ='General information '!F9 -> 0.087 | B6: =SUM(230*A6) -> 20.01 | C6: 44016 | D6: 31881284 | E6: =D6-D5 -> 3772 | F6: 3749544 | G6: =F6-F5 -> 1924 | H6: 17529394 | I6: =H6-H5 -> 1890 | J6: 28536822 | K6: =J6-J5 -> 2220 | L6: 23267442 | M6: =L6-L5 -> 8346 | N6: =M6+K6+I6+G6+E6 -> 18152 | O6: =IF(B6>0,N6/B6,0) -> 907.14643 | P6: 15732 | Q6: =(P6-P5)*1000 -> 16000 | R6: =N6-Q6 -> 2152 | S6: 8959 | T6: =S6-S5 -> 20 | U6: 155326 | V6: =U6-U5 -> 4443 | W6: =W5 -> 31853 | X6: =W6-W5 -> 0 | Y6: =Y5 -> 625865 | Z6: =Y6-Y5 -> 0 | AA6: 35229 | AB6: =AA6-AA5 -> 0 | AC6: =AC5 -> 814845 | AD6: =AC6-AC5 -> 0 | AE6: =AB6+X6+T6 -> 20 | AF6: =V6+Z6+AD6 -> 4443 | AG6: =IF(AE6>0,AF6/AE6,0) -> 222.15 | AI6: =R6-'EDl log'!B4 -> -111978
A7: ='General information '!F10 -> 0.0783 | B7: =SUM(230*A7) -> 18.009 | C7: 44017 | D7: 31887122 | E7: =D7-D6 -> 5838 | F7: 3751521 | G7: =F7-F6 -> 1977 | H7: 17531390 | I7: =H7-H6 -> 1996 | J7: 28539000 | K7: =J7-J6 -> 2178 | L7: 23273614 | M7: =L7-L6 -> 6172 | N7: =M7+K7+I7+G7+E7 -> 18161 | O7: =IF(B7>0,N7/B7,0) -> 1008.4402 | P7: 15747 | Q7: =(P7-P6)*1000 -> 15000 | R7: =N7-Q7 -> 3161 | S7: 8971 | T7: =S7-S6 -> 12 | U7: 158305 | V7: =U7-U6 -> 2979 | W7: 31853 | X7: =W7-W6 -> 0 | Y7: =Y6 -> 625865 | Z7: =Y7-Y6 -> 0 | AA7: 35238 | AB7: =AA7-AA6 -> 9 | AC7: 816851 | AD7: =AC7-AC6 -> 2006 | AE7: =AB7+X7+T7 -> 21 | AF7: =V7+Z7+AD7 -> 4985 | AG7: =IF(AE7>0,AF7/AE7,0) -> 237.38095 | AI7: =R7-'EDl log'!B5 -> -114241
A8: ='General information '!F11 -> 0.0826 | B8: =SUM(230*A8) -> 18.998 | C8: 44018 | D8: 31892150 | E8: =D8-D7 -> 5028 | F8: 3753617 | G8: =F8-F7 -> 2096 | H8: 17533606 | I8: =H8-H7 -> 2216 | J8: 28541448 | K8: =J8-J7 -> 2448 | L8: 23282590 | M8: =L8-L7 -> 8976 | N8: =M8+K8+I8+G8+E8 -> 20764 | O8: =IF(B8>0,N8/B8,0) -> 1092.9572 | P8: 15765 | Q8: =(P8-P7)*1000 -> 18000 | R8: =N8-Q8 -> 2764 | S8: 8991 | T8: =S8-S7 -> 20 | U8: 162800 | V8: =U8-U7 -> 4495 | W8: =W7 -> 31853 | X8: =W8-W7 -> 0 | Y8: =Y7 -> 625865 | Z8: =Y8-Y7 -> 0 | AA8: 35240 | AB8: =AA8-AA7 -> 2 | AC8: 817378 | AD8: =AC8-AC7 -> 527 | AE8: =AB8+X8+T8 -> 22 | AF8: =V8+Z8+AD8 -> 5022 | AG8: =IF(AE8>0,AF8/AE8,0) -> 228.27273 | AI8: =R8-'EDl log'!B6 -> -118318
A9: ='General information '!F12 -> 0.0783 | B9: =SUM(230*A9) -> 18.009 | C9: 44019 | D9: 31899618 | E9: =D9-D8 -> 7468 | F9: 3755590 | G9: =F9-F8 -> 1973 | H9: 17535926 | I9: =H9-H8 -> 2320 | J9: 28543918 | K9: =J9-J8 -> 2470 | L9: 23288838 | M9: =L9-L8 -> 6248 | N9: =M9+K9+I9+G9+E9 -> 20479 | O9: =IF(B9>0,N9/B9,0) -> 1137.1536 | P9: 15780 | Q9: =(P9-P8)*1000 -> 15000 | R9: =N9-Q9 -> 5479 | S9: 9001 | T9: =S9-S8 -> 10 | U9: 165542 | V9: =U9-U8 -> 2742 | W9: 31853 | X9: =W9-W8 -> 0 | Y9: =Y8 -> 625865 | Z9: =Y9-Y8 -> 0 | AA9: 35253 | AB9: =AA9-AA8 -> 13 | AC9: 820446 | AD9: =AC9-AC8 -> 3068 | AE9: =AB9+X9+T9 -> 23 | AF9: =V9+Z9+AD9 -> 5810 | AG9: =IF(AE9>0,AF9/AE9,0) -> 252.6087 | AI9: =R9-'EDl log'!B7 -> -116573
A10: ='General information '!F13 -> 0.087 | B10: =SUM(230*A10) -> 20.01 | C10: 44020 | D10: 31904808 | E10: =D10-D9 -> 5190 | F10: 3757737 | G10: =F10-F9 -> 2147 | H10: 17538322 | I10: =H10-H9 -> 2396 | J10: 28547484 | K10: =J10-J9 -> 3566 | L10: 23299082 | M10: =L10-L9 -> 10244 | N10: =M10+K10+I10+G10+E10 -> 23543 | O10: =IF(B10>0,N10/B10,0) -> 1176.5617 | P10: 15795 | Q10: =(P10-P9)*1000 -> 15000 | R10: =N10-Q10 -> 8543 | S10: 9025 | T10: =S10-S9 -> 24 | U10: 171163 | V10: =U10-U9 -> 5621 | W10: 31853 | X10: =W10-W9 -> 0 | Y10: 625865 | Z10: =Y10-Y9 -> 0 | AA10: 35253 | AB10: =AA10-AA9 -> 0 | AC10: 820459 | AD10: =AC10-AC9 -> 13 | AE10: =AB10+X10+T10 -> 24 | AF10: =V10+Z10+AD10 -> 5634 | AG10: =IF(AE10>0,AF10/AE10,0) -> 234.75 | AI10: =R10-'EDl log'!B8 -> -115625
A11: ='General information '!F14 -> 0.1087 | B11: =SUM(230*A11) -> 25.001 | C11: 44021 | D11: 31909136 | E11: =D11-D10 -> 4328 | F11: 3759502 | G11: =F11-F10 -> 1765 | H11: 17540322 | I11: =H11-H10 -> 2000 | J11: 28549842 | K11: =J11-J10 -> 2358 | L11: 23306740 | M11: =L11-L10 -> 7658 | N11: =M11+K11+I11+G11+E11 -> 18109 | O11: =IF(B11>0,N11/B11,0) -> 724.33103 | P11: 15815 | Q11: =(P11-P10)*1000 -> 20000 | R11: =N11-Q11 -> -1891 | S11: 9046 | T11: =S11-S10 -> 21 | U11: 175732 | V11: =U11-U10 -> 4569 | W11: 31853 | X11: =W11-W10 -> 0 | Y11: =Y10 -> 625865 | Z11: =Y11-Y10 -> 0 | AA11: 35254 | AB11: =AA11-AA10 -> 1 | AC11: 820817 | AD11: =AC11-AC10 -> 358 | AE11: =AB11+X11+T11 -> 22 | AF11: =V11+Z11+AD11 -> 4927 | AG11: =IF(AE11>0,AF11/AE11,0) -> 223.95455 | AI11: =R11-'EDl log'!B9 -> -127584
A12: ='General information '!F15 -> 0.113 | B12: =SUM(230*A12) -> 25.99 | C12: 44022 | D12: 31918636 | E12: =D12-D11 -> 9500 | F12: 3761429 | G12: =F12-F11 -> 1927 | H12: 17542698 | I12: =H12-H11 -> 2376 | J12: 28552374 | K12: =J12-J11 -> 2532 | L12: 23310458 | M12: =L12-L11 -> 3718 | N12: =M12+K12+I12+G12+E12 -> 20053 | O12: =IF(B12>0,N12/B12,0) -> 771.56599 | P12: 15832 | Q12: =(P12-P11)*1000 -> 17000 | R12: =N12-Q12 -> 3053 | S12: 9046 | T12: =S12-S11 -> 0 | U12: =U11 -> 175732 | V12: =U12-U11 -> 0 | W12: 31853 | X12: =W12-W11 -> 0 | Y12: =Y11 -> 625865 | Z12: =Y12-Y11 -> 0 | AA12: 35277 | AB12: =AA12-AA11 -> 23 | AC12: 825666 | AD12: =AC12-AC11 -> 4849 | AE12: =AB12+X12+T12 -> 23 | AF12: =V12+Z12+AD12 -> 4849 | AG12: =IF(AE12>0,AF12/AE12,0) -> 210.82609 | AI12: =R12-'EDl log'!B10 -> -122640
A13: ='General information '!F16 -> 0.165 | B13: =SUM(230*A13) -> 37.95 | C13: 44023 | D13: 31925506 | E13: =D13-D12 -> 6870 | F13: 3763366 | G13: =F13-F12 -> 1937 | H13: 17545070 | I13: =H13-H12 -> 2372 | J13: 28555410 | K13: =J13-J12 -> 3036 | L13: 23317316 | M13: =L13-L12 -> 6858 | N13: =M13+K13+I13+G13+E13 -> 21073 | O13: =IF(B13>0,N13/B13,0) -> 555.28327 | P13: 15850 | Q13: =(P13-P12)*1000 -> 18000 | R13: =N13-Q13 -> 3073 | S13: 9058 | T13: =S13-S12 -> 12 | U13: 178830 | V13: =U13-U12 -> 3098 | W13: 31853 | X13: =W13-W12 -> 0 | Y13: =Y12 -> 625865 | Z13: =Y13-Y12 -> 0 | AA13: 35288 | AB13: =AA13-AA12 -> 11 | AC13: 827959 | AD13: =AC13-AC12 -> 2293 | AE13: =AB13+X13+T13 -> 23 | AF13: =V13+Z13+AD13 -> 5391 | AG13: =IF(AE13>0,AF13/AE13,0) -> 234.3913 | AI13: =R13-'EDl log'!B11 -> -122620
A14: ='General information '!F17 -> 0.1 | B14: =SUM(230*A14) -> 23 | C14: 44024 | D14: 31929606 | E14: =D14-D13 -> 4100 | F14: 3765356 | G14: =F14-F13 -> 1990 | H14: 17547420 | I14: =H14-H13 -> 2350 | J14: 28558246 | K14: =J14-J13 -> 2836 | L14: 23326124 | M14: =L14-L13 -> 8808 | N14: =M14+K14+I14+G14+E14 -> 20084 | O14: =IF(B14>0,N14/B14,0) -> 873.21739 | P14: 15869 | Q14: =(P14-P13)*1000 -> 19000 | R14: =N14-Q14 -> 1084 | S14: 9081 | T14: =S14-S13 -> 23 | U14: 183861 | V14: =U14-U13 -> 5031 | W14: 31853 | X14: =W14-W13 -> 0 | Y14: =Y13 -> 625865 | Z14: =Y14-Y13 -> 0 | AA14: 35288 | AB14: =AA14-AA13 -> 0 | AC14: 827989 | AD14: =AC14-AC13 -> 30 | AE14: =AB14+X14+T14 -> 23 | AF14: =V14+Z14+AD14 -> 5061 | AG14: =IF(AE14>0,AF14/AE14,0) -> 220.04348 | AI14: =R14-'EDl log'!B12 -> -132180
A15: ='General information '!F18 -> 0.1217 | B15: =SUM(230*A15) -> 27.991 | C15: 44025 | D15: 31934490 | E15: =D15-D14 -> 4884 | F15: 3767592 | G15: =F15-F14 -> 2236 | H15: 17549838 | I15: =H15-H14 -> 2418 | J15: 28560296 | K15: =J15-J14 -> 2050 | L15: 23334400 | M15: =L15-L14 -> 8276 | N15: =M15+K15+I15+G15+E15 -> 19864 | O15: =IF(B15>0,N15/B15,0) -> 709.65668 | P15: 15883 | Q15: =(P15-P14)*1000 -> 14000 | R15: =N15-Q15 -> 5864 | S15: 9101 | T15: =S15-S14 -> 20 | U15: 188212 | V15: =U15-U14 -> 4351 | W15: 31853 | X15: =W15-W14 -> 0 | Y15: 625865 | Z15: =Y15-Y14 -> 0 | AA15: 35290 | AB15: =AA15-AA14 -> 2 | AC15: 828442 | AD15: =AC15-AC14 -> 453 | AE15: =AB15+X15+T15 -> 22 | AF15: =V15+Z15+AD15 -> 4804 | AG15: =IF(AE15>0,AF15/AE15,0) -> 218.36364 | AI15: =R15-'EDl log'!B13 -> -127800
A16: ='General information '!F19 -> 0.1271 | B16: =SUM(230*A16) -> 29.233 | C16: 44026 | D16: 31944038 | E16: =D16-D15 -> 9548 | F16: 3769558 | G16: =F16-F15 -> 1966 | H16: 17552096 | I16: =H16-H15 -> 2258 | J16: 28562678 | K16: =J16-J15 -> 2382 | L16: 23337998 | M16: =L16-L15 -> 3598 | N16: =M16+K16+I16+G16+E16 -> 19752 | O16: =IF(B16>0,N16/B16,0) -> 675.67475 | P16: 15901 | Q16: =(P16-P15)*1000 -> 18000 | R16: =N16-Q16 -> 1752 | S16: 9101 | T16: =S16-S15 -> 0 | U16: 188213 | V16: =U16-U15 -> 1 | W16: =W15 -> 31853 | X16: =W16-W15 -> 0 | Y16: 625865 | Z16: =Y16-Y15 -> 0 | AA16: 35314 | AB16: =AA16-AA15 -> 24 | AC16: 833458 | AD16: =AC16-AC15 -> 5016 | AE16: =AB16+X16+T16 -> 24 | AF16: =V16+Z16+AD16 -> 5017 | AG16: =IF(AE16>0,AF16/AE16,0) -> 209.04167 | AI16: =R16-'EDl log'!B14 -> -134253
A17: ='General information '!F20 -> 0.1348 | B17: =SUM(230*A17) -> 31.004 | C17: 44027 | D17: 31949588 | E17: =D17-D16 -> 5550 | F17: 3771812 | G17: =F17-F16 -> 2254 | H17: 17554498 | I17: =H17-H16 -> 2402 | J17: 28565690 | K17: =J17-J16 -> 3012 | L17: 23347120 | M17: =L17-L16 -> 9122 | N17: =M17+K17+I17+G17+E17 -> 22340 | O17: =IF(B17>0,N17/B17,0) -> 720.55219 | P17: 15918 | Q17: =(P17-P16)*1000 -> 17000 | R17: =N17-Q17 -> 5340 | S17: 9120 | T17: =S17-S16 -> 19 | U17: 192930 | V17: =U17-U16 -> 4717 | W17: =W16 -> 31853 | X17: =W17-W16 -> 0 | Y17: =Y16 -> 625865 | Z17: =Y17-Y16 -> 0 | AA17: 35316 | AB17: =AA17-AA16 -> 2 | AC17: 834137 | AD17: =AC17-AC16 -> 679 | AE17: =AB17+X17+T17 -> 21 | AF17: =V17+Z17+AD17 -> 5396 | AG17: =IF(AE17>0,AF17/AE17,0) -> 256.95238 | AI17: =R17-'EDl log'!B15 -> -131110
A18: ='General information '!F21 -> 0.2 | B18: =SUM(230*A18) -> 46 | C18: 44028 | D18: 31955118 | E18: =D18-D17 -> 5530 | F18: 3773880 | G18: =F18-F17 -> 2068 | H18: 17556730 | I18: =H18-H17 -> 2232 | J18: 28570926 | K18: =J18-J17 -> 5236 | L18: 23352798 | M18: =L18-L17 -> 5678 | N18: =M18+K18+I18+G18+E18 -> 20744 | O18: =IF(B18>0,N18/B18,0) -> 450.95652 | P18: 15937 | Q18: =(P18-P17)*1000 -> 19000 | R18: =N18-Q18 -> 1744 | S18: 9130 | T18: =S18-S17 -> 10 | U18: 195258 | V18: =U18-U17 -> 2328 | W18: 31862 | X18: =W18-W17 -> 9 | Y18: 628067 | Z18: =Y18-Y17 -> 2202 | AA18: 35320 | AB18: =AA18-AA17 -> 4 | AC18: 834917 | AD18: =AC18-AC17 -> 780 | AE18: =AB18+X18+T18 -> 23 | AF18: =V18+Z18+AD18 -> 5310 | AG18: =IF(AE18>0,AF18/AE18,0) -> 230.86957 | AI18: =R18-'EDl log'!B16 -> -134706
A19: ='General information '!F22 -> 0 | B19: =SUM(230*A19) -> 0 | C19: 44029 | D19: =D18 -> 31955118 | E19: =D19-D18 -> 0 | F19: =F18 -> 3773880 | G19: =F19-F18 -> 0 | H19: =H18 -> 17556730 | I19: =H19-H18 -> 0 | J19: =J18 -> 28570926 | K19: =J19-J18 -> 0 | L19: =L18 -> 23352798 | M19: =L19-L18 -> 0 | N19: =M19+K19+I19+G19+E19 -> 0 | O19: =IF(B19>0,N19/B19,0) -> 0 | P19: =P18 -> 15937 | Q19: =(P19-P18)*1000 -> 0 | R19: =N19-Q19 -> 0 | S19: =S18 -> 9130 | T19: =S19-S18 -> 0 | U19: =U18 -> 195258 | V19: =U19-U18 -> 0 | W19: =W18 -> 31862 | X19: =W19-W18 -> 0 | Y19: =Y18 -> 628067 | Z19: =Y19-Y18 -> 0 | AA19: =AA18 -> 35320 | AB19: =AA19-AA18 -> 0 | AC19: =AC18 -> 834917 | AD19: =AC19-AC18 -> 0 | AE19: =AB19+X19+T19 -> 0 | AF19: =V19+Z19+AD19 -> 0 | AG19: =IF(AE19>0,AF19/AE19,0) -> 0 | AI19: =R19-'EDl log'!B17 -> -140459
A20: ='General information '!F23 -> 0 | B20: =SUM(230*A20) -> 0 | C20: 44030 | D20: =D19 -> 31955118 | E20: =D20-D19 -> 0 | F20: =F19 -> 3773880 | G20: =F20-F19 -> 0 | H20: =H19 -> 17556730 | I20: =H20-H19 -> 0 | J20: =J19 -> 28570926 | K20: =J20-J19 -> 0 | L20: =L19 -> 23352798 | M20: =L20-L19 -> 0 | N20: =M20+K20+I20+G20+E20 -> 0 | O20: =IF(B20>0,N20/B20,0) -> 0 | P20: =P19 -> 15937 | Q20: =(P20-P19)*1000 -> 0 | R20: =N20-Q20 -> 0 | S20: =S19 -> 9130 | T20: =S20-S19 -> 0 | U20: =U19 -> 195258 | V20: =U20-U19 -> 0 | W20: =W19 -> 31862 | X20: =W20-W19 -> 0 | Y20: =Y19 -> 628067 | Z20: =Y20-Y19 -> 0 | AA20: =AA19 -> 35320 | AB20: =AA20-AA19 -> 0 | AC20: =AC19 -> 834917 | AD20: =AC20-AC19 -> 0 | AE20: =AB20+X20+T20 -> 0 | AF20: =V20+Z20+AD20 -> 0 | AG20: =IF(AE20>0,AF20/AE20,0) -> 0 | AI20: =R20-'EDl log'!B18 -> -143143
A21: ='General information '!F24 -> 0 | B21: =SUM(230*A21) -> 0 | C21: 44031 | D21: =D20 -> 31955118 | E21: =D21-D20 -> 0 | F21: =F20 -> 3773880 | G21: =F21-F20 -> 0 | H21: =H20 -> 17556730 | I21: =H21-H20 -> 0 | J21: =J20 -> 28570926 | K21: =J21-J20 -> 0 | L21: =L20 -> 23352798 | M21: =L21-L20 -> 0 | N21: =M21+K21+I21+G21+E21 -> 0 | O21: =IF(B21>0,N21/B21,0) -> 0 | P21: =P20 -> 15937 | Q21: =(P21-P20)*1000 -> 0 | R21: =N21-Q21 -> 0 | S21: =S20 -> 9130 | T21: =S21-S20 -> 0 | U21: =U20 -> 195258 | V21: =U21-U20 -> 0 | W21: =W20 -> 31862 | X21: =W21-W20 -> 0 | Y21: =Y20 -> 628067 | Z21: =Y21-Y20 -> 0 | AA21: =AA20 -> 35320 | AB21: =AA21-AA20 -> 0 | AC21: =AC20 -> 834917 | AD21: =AC21-AC20 -> 0 | AE21: =AB21+X21+T21 -> 0 | AF21: =V21+Z21+AD21 -> 0 | AG21: =IF(AE21>0,AF21/AE21,0) -> 0 | AI21: =R21-'EDl log'!B19 -> -144480
A22: ='General information '!F25 -> 0 | B22: =SUM(230*A22) -> 0 | C22: 44032 | D22: =D21 -> 31955118 | E22: =D22-D21 -> 0 | F22: =F21 -> 3773880 | G22: =F22-F21 -> 0 | H22: =H21 -> 17556730 | I22: =H22-H21 -> 0 | J22: =J21 -> 28570926 | K22: =J22-J21 -> 0 | L22: =L21 -> 23352798 | M22: =L22-L21 -> 0 | N22: =M22+K22+I22+G22+E22 -> 0 | O22: =IF(B22>0,N22/B22,0) -> 0 | P22: =P21 -> 15937 | Q22: =(P22-P21)*1000 -> 0 | R22: =N22-Q22 -> 0 | S22: =S21 -> 9130 | T22: =S22-S21 -> 0 | U22: =U21 -> 195258 | V22: =U22-U21 -> 0 | W22: =W21 -> 31862 | X22: =W22-W21 -> 0 | Y22: =Y21 -> 628067 | Z22: =Y22-Y21 -> 0 | AA22: =AA21 -> 35320 | AB22: =AA22-AA21 -> 0 | AC22: =AC21 -> 834917 | AD22: =AC22-AC21 -> 0 | AE22: =AB22+X22+T22 -> 0 | AF22: =V22+Z22+AD22 -> 0 | AG22: =IF(AE22>0,AF22/AE22,0) -> 0 | AI22: =R22-'EDl log'!B20 -> -144480
A23: ='General information '!F26 -> 0 | B23: =SUM(230*A23) -> 0 | C23: 44033 | D23: =D22 -> 31955118 | E23: =D23-D22 -> 0 | F23: =F22 -> 3773880 | G23: =F23-F22 -> 0 | H23: =H22 -> 17556730 | I23: =H23-H22 -> 0 | J23: =J22 -> 28570926 | K23: =J23-J22 -> 0 | L23: =L22 -> 23352798 | M23: =L23-L22 -> 0 | N23: =M23+K23+I23+G23+E23 -> 0 | O23: =IF(B23>0,N23/B23,0) -> 0 | P23: =P22 -> 15937 | Q23: =(P23-P22)*1000 -> 0 | R23: =N23-Q23 -> 0 | S23: =S22 -> 9130 | T23: =S23-S22 -> 0 | U23: =U22 -> 195258 | V23: =U23-U22 -> 0 | W23: =W22 -> 31862 | X23: =W23-W22 -> 0 | Y23: =Y22 -> 628067 | Z23: =Y23-Y22 -> 0 | AA23: =AA22 -> 35320 | AB23: =AA23-AA22 -> 0 | AC23: =AC22 -> 834917 | AD23: =AC23-AC22 -> 0 | AE23: =AB23+X23+T23 -> 0 | AF23: =V23+Z23+AD23 -> 0 | AG23: =IF(AE23>0,AF23/AE23,0) -> 0 | AI23: =R23-'EDl log'!B21 -> -144480
A24: ='General information '!F27 -> 0 | B24: =SUM(230*A24) -> 0 | C24: 44034 | D24: =D23 -> 31955118 | E24: =D24-D23 -> 0 | F24: =F23 -> 3773880 | G24: =F24-F23 -> 0 | H24: =H23 -> 17556730 | I24: =H24-H23 -> 0 | J24: =J23 -> 28570926 | K24: =J24-J23 -> 0 | L24: =L23 -> 23352798 | M24: =L24-L23 -> 0 | N24: =M24+K24+I24+G24+E24 -> 0 | O24: =IF(B24>0,N24/B24,0) -> 0 | P24: =P23 -> 15937 | Q24: =(P24-P23)*1000 -> 0 | R24: =N24-Q24 -> 0 | S24: =S23 -> 9130 | T24: =S24-S23 -> 0 | U24: =U23 -> 195258 | V24: =U24-U23 -> 0 | W24: =W23 -> 31862 | X24: =W24-W23 -> 0 | Y24: =Y23 -> 628067 | Z24: =Y24-Y23 -> 0 | AA24: =AA23 -> 35320 | AB24: =AA24-AA23 -> 0 | AC24: =AC23 -> 834917 | AD24: =AC24-AC23 -> 0 | AE24: =AB24+X24+T24 -> 0 | AF24: =V24+Z24+AD24 -> 0 | AG24: =IF(AE24>0,AF24/AE24,0) -> 0 | AI24: =R24-'EDl log'!B22 -> -144480
A25: ='General information '!F28 -> 0 | B25: =SUM(230*A25) -> 0 | C25: 44035 | D25: =D24 -> 31955118 | E25: =D25-D24 -> 0 | F25: =F24 -> 3773880 | G25: =F25-F24 -> 0 | H25: =H24 -> 17556730 | I25: =H25-H24 -> 0 | J25: =J24 -> 28570926 | K25: =J25-J24 -> 0 | L25: =L24 -> 23352798 | M25: =L25-L24 -> 0 | N25: =M25+K25+I25+G25+E25 -> 0 | O25: =IF(B25>0,N25/B25,0) -> 0 | P25: =P24 -> 15937 | Q25: =(P25-P24)*1000 -> 0 | R25: =N25-Q25 -> 0 | S25: =S24 -> 9130 | T25: =S25-S24 -> 0 | U25: =U24 -> 195258 | V25: =U25-U24 -> 0 | W25: =W24 -> 31862 | X25: =W25-W24 -> 0 | Y25: =Y24 -> 628067 | Z25: =Y25-Y24 -> 0 | AA25: =AA24 -> 35320 | AB25: =AA25-AA24 -> 0 | AC25: =AC24 -> 834917 | AD25: =AC25-AC24 -> 0 | AE25: =AB25+X25+T25 -> 0 | AF25: =V25+Z25+AD25 -> 0 | AG25: =IF(AE25>0,AF25/AE25,0) -> 0 | AI25: =R25-'EDl log'!B23 -> -144480
A26: ='General information '!F29 -> 0 | B26: =SUM(230*A26) -> 0 | C26: 44036 | D26: =D25 -> 31955118 | E26: =D26-D25 -> 0 | F26: =F25 -> 3773880 | G26: =F26-F25 -> 0 | H26: =H25 -> 17556730 | I26: =H26-H25 -> 0 | J26: =J25 -> 28570926 | K26: =J26-J25 -> 0 | L26: =L25 -> 23352798 | M26: =L26-L25 -> 0 | N26: =M26+K26+I26+G26+E26 -> 0 | O26: =IF(B26>0,N26/B26,0) -> 0 | P26: =P25 -> 15937 | Q26: =(P26-P25)*1000 -> 0 | R26: =N26-Q26 -> 0 | S26: =S25 -> 9130 | T26: =S26-S25 -> 0 | U26: =U25 -> 195258 | V26: =U26-U25 -> 0 | W26: =W25 -> 31862 | X26: =W26-W25 -> 0 | Y26: =Y25 -> 628067 | Z26: =Y26-Y25 -> 0 | AA26: =AA25 -> 35320 | AB26: =AA26-AA25 -> 0 | AC26: =AC25 -> 834917 | AD26: =AC26-AC25 -> 0 | AE26: =AB26+X26+T26 -> 0 | AF26: =V26+Z26+AD26 -> 0 | AG26: =IF(AE26>0,AF26/AE26,0) -> 0 | AI26: =R26-'EDl log'!B24 -> -144480
A27: ='General information '!F30 -> 0 | B27: =SUM(230*A27) -> 0 | C27: 44037 | D27: =D26 -> 31955118 | E27: =D27-D26 -> 0 | F27: =F26 -> 3773880 | G27: =F27-F26 -> 0 | H27: =H26 -> 17556730 | I27: =H27-H26 -> 0 | J27: =J26 -> 28570926 | K27: =J27-J26 -> 0 | L27: =L26 -> 23352798 | M27: =L27-L26 -> 0 | N27: =M27+K27+I27+G27+E27 -> 0 | O27: =IF(B27>0,N27/B27,0) -> 0 | P27: =P26 -> 15937 | Q27: =(P27-P26)*1000 -> 0 | R27: =N27-Q27 -> 0 | S27: =S26 -> 9130 | T27: =S27-S26 -> 0 | U27: =U26 -> 195258 | V27: =U27-U26 -> 0 | W27: =W26 -> 31862 | X27: =W27-W26 -> 0 | Y27: =Y26 -> 628067 | Z27: =Y27-Y26 -> 0 | AA27: =AA26 -> 35320 | AB27: =AA27-AA26 -> 0 | AC27: =AC26 -> 834917 | AD27: =AC27-AC26 -> 0 | AE27: =AB27+X27+T27 -> 0 | AF27: =V27+Z27+AD27 -> 0 | AG27: =IF(AE27>0,AF27/AE27,0) -> 0 | AI27: =R27-'EDl log'!B25 -> -144480
A28: ='General information '!F31 -> 0 | B28: =SUM(230*A28) -> 0 | C28: 44038 | D28: =D27 -> 31955118 | E28: =D28-D27 -> 0 | F28: =F27 -> 3773880 | G28: =F28-F27 -> 0 | H28: =H27 -> 17556730 | I28: =H28-H27 -> 0 | J28: =J27 -> 28570926 | K28: =J28-J27 -> 0 | L28: =L27 -> 23352798 | M28: =L28-L27 -> 0 | N28: =M28+K28+I28+G28+E28 -> 0 | O28: =IF(B28>0,N28/B28,0) -> 0 | P28: =P27 -> 15937 | Q28: =(P28-P27)*1000 -> 0 | R28: =N28-Q28 -> 0 | S28: =S27 -> 9130 | T28: =S28-S27 -> 0 | U28: =U27 -> 195258 | V28: =U28-U27 -> 0 | W28: =W27 -> 31862 | X28: =W28-W27 -> 0 | Y28: =Y27 -> 628067 | Z28: =Y28-Y27 -> 0 | AA28: =AA27 -> 35320 | AB28: =AA28-AA27 -> 0 | AC28: =AC27 -> 834917 | AD28: =AC28-AC27 -> 0 | AE28: =AB28+X28+T28 -> 0 | AF28: =V28+Z28+AD28 -> 0 | AG28: =IF(AE28>0,AF28/AE28,0) -> 0 | AI28: =R28-'EDl log'!B26 -> -144480
A29: ='General information '!F32 -> 0 | B29: =SUM(230*A29) -> 0 | C29: 44039 | D29: =D28 -> 31955118 | E29: =D29-D28 -> 0 | F29: =F28 -> 3773880 | G29: =F29-F28 -> 0 | H29: =H28 -> 17556730 | I29: =H29-H28 -> 0 | J29: =J28 -> 28570926 | K29: =J29-J28 -> 0 | L29: =L28 -> 23352798 | M29: =L29-L28 -> 0 | N29: =M29+K29+I29+G29+E29 -> 0 | O29: =IF(B29>0,N29/B29,0) -> 0 | P29: =P28 -> 15937 | Q29: =(P29-P28)*1000 -> 0 | R29: =N29-Q29 -> 0 | S29: =S28 -> 9130 | T29: =S29-S28 -> 0 | U29: =U28 -> 195258 | V29: =U29-U28 -> 0 | W29: =W28 -> 31862 | X29: =W29-W28 -> 0 | Y29: =Y28 -> 628067 | Z29: =Y29-Y28 -> 0 | AA29: =AA28 -> 35320 | AB29: =AA29-AA28 -> 0 | AC29: =AC28 -> 834917 | AD29: =AC29-AC28 -> 0 | AE29: =AB29+X29+T29 -> 0 | AF29: =V29+Z29+AD29 -> 0 | AG29: =IF(AE29>0,AF29/AE29,0) -> 0 | AI29: =R29-'EDl log'!B27 -> -144480
A30: ='General information '!F33 -> 0 | B30: =SUM(230*A30) -> 0 | C30: 44040 | D30: =D29 -> 31955118 | E30: =D30-D29 -> 0 | F30: =F29 -> 3773880 | G30: =F30-F29 -> 0 | H30: =H29 -> 17556730 | I30: =H30-H29 -> 0 | J30: =J29 -> 28570926 | K30: =J30-J29 -> 0 | L30: =L29 -> 23352798 | M30: =L30-L29 -> 0 | N30: =M30+K30+I30+G30+E30 -> 0 | O30: =IF(B30>0,N30/B30,0) -> 0 | P30: =P29 -> 15937 | Q30: =(P30-P29)*1000 -> 0 | R30: =N30-Q30 -> 0 | S30: =S29 -> 9130 | T30: =S30-S29 -> 0 | U30: =U29 -> 195258 | V30: =U30-U29 -> 0 | W30: =W29 -> 31862 | X30: =W30-W29 -> 0 | Y30: =Y29 -> 628067 | Z30: =Y30-Y29 -> 0 | AA30: =AA29 -> 35320 | AB30: =AA30-AA29 -> 0 | AC30: =AC29 -> 834917 | AD30: =AC30-AC29 -> 0 | AE30: =AB30+X30+T30 -> 0 | AF30: =V30+Z30+AD30 -> 0 | AG30: =IF(AE30>0,AF30/AE30,0) -> 0 | AI30: =R30-'EDl log'!B28 -> -144480
... A32: ='General information '!F35 -> 0 | B32: =SUM(230*A32) -> 0 | C32: 44042 | D32: =D31 -> 31955118 | E32: =D32-D31 -> 0 | F32: =F31 -> 3773880 | G32: =F32-F31 -> 0 | H32: =H31 -> 17556730 | I32: =H32-H31 -> 0 | J32: =J31 -> 28570926 | K32: =J32-J31 -> 0 | L32: =L31 -> 23352798 | M32: =L32-L31 -> 0 | N32: =M32+K32+I32+G32+E32 -> 0 | O32: =IF(B32>0,N32/B32,0) -> 0 | P32: =P31 -> 15937 | Q32: =(P32-P31)*1000 -> 0 | R32: =N32-Q32 -> 0 | S32: =S31 -> 9130 | T32: =S32-S31 -> 0 | U32: =U31 -> 195258 | V32: =U32-U31 -> 0 | W32: =W31 -> 31862 | X32: =W32-W31 -> 0 | Y32: =Y31 -> 628067 | Z32: =Y32-Y31 -> 0 | AA32: =AA31 -> 35320 | AB32: =AA32-AA31 -> 0 | AC32: =AC31 -> 834917 | AD32: =AC32-AC31 -> 0 | AE32: =AB32+X32+T32 -> 0 | AF32: =V32+Z32+AD32 -> 0 | AG32: =IF(AE32>0,AF32/AE32,0) -> 0 | AI32: =R32-'EDl log'!B30 -> -144480
A33: ='General information '!F37 -> 0.104125 | B33: =SUM(230*A33) -> 23.94875 | C33: 44043 | D33: =D32 -> 31955118 | E33: =D33-D32 -> 0 | F33: =F32 -> 3773880 | G33: =F33-F32 -> 0 | H33: =H32 -> 17556730 | I33: =H33-H32 -> 0 | J33: =J32 -> 28570926 | K33: =J33-J32 -> 0 | L33: =L32 -> 23352798 | M33: =L33-L32 -> 0 | N33: =M33+K33+I33+G33+E33 -> 0 | O33: =IF(B33>0,N33/B33,0) -> 0 | P33: =P32 -> 15937 | Q33: =(P33-P32)*1000 -> 0 | R33: =N33-Q33 -> 0 | S33: =S32 -> 9130 | T33: =S33-S32 -> 0 | U33: =U32 -> 195258 | V33: =U33-U32 -> 0 | W33: =W32 -> 31862 | X33: =W33-W32 -> 0 | Y33: =Y32 -> 628067 | Z33: =Y33-Y32 -> 0 | AA33: =AA32 -> 35320 | AB33: =AA33-AA32 -> 0 | AC33: =AC32 -> 834917 | AD33: =AC33-AC32 -> 0 | AE33: =AB33+X33+T33 -> 0 | AF33: =V33+Z33+AD33 -> 0 | AG33: =IF(AE33>0,AF33/AE33,0) -> 0 | AI33: =R33-'EDl log'!B31 -> -144480

Sheet B5
F1: Boiler A | J1: =J36 -> 71.527778 | K1: Boiler B | P1: Boiler C | V1: Boiler | X1: SteamA | AC1: SteamB | AH1: Steam | AI1: Boiler & steam | AL1: Total Boiler Runing H | AM1: Total Steam Runing H | AN1: GAS1 % | AO1: GAS1/L | AP1: GAS2% | AQ1: Gas2/L | AR1: GAS3% | AS1: GAS3/L | AU1: Gas Cons | AV1: Delivery | AW1: Cost/L
B2: Level Tank Gen | C2: Level tank Boiler | D2: Daily Cons Bo. | E2: Boiler litter | F2: Boiler A | G2: Run Hr a | H2: Boiler A fuel | I2: Daily consumption | J2: AVG | K2: index Run H | L2: Run Hrb | M2: Boiler B Fuel | O2: Daily consumption | P2: Boiler C | S2: Run C | U2: Total RH | V2: Total Fuel | X2: SteamA | Y2: Run SA | Z2: Steam A Conter | AA2: Liters | AC2: SteamB | AD2: Run SteamB | AE2: Steam B Conter | AF2: SB Litters | AG2: Avg | AH2: Total Fuel | AI2: Total Fuel
S3: 0
A4: =ELEC!C2 -> 44012 | B4: =[1]B5!B34 -> 140 | C4: =[1]B5!C34 -> 147 | D4: =[1]B5!D34 -> 11 | E4: =[1]B5!E34 -> 92.18 | F4: =[1]B5!F34 -> 1602 | G4: =[1]B5!G34 -> 1 | H4: =[1]B5!H34 -> 354323 | I4: =[1]B5!I34 -> 50 | ... AX4: =[1]B5!AX34 -> 0.7
A5: =ELEC!C3 -> 44013 | B5: 183 | C5: 190 | D5: =C4-C5 -> -43 | E5: =D5*8.38 -> -360.34 | F5: 1605 | G5: =F5-F4 -> 3 | H5: 354564 | I5: =SUM(H5-H4) -> 241 | J5: 1 | K5: =K4 -> 2069 | L5: =K5-K4 -> 0 | M5: =M4 -> 151781 | N5: =M5-M4 -> 0 | O5: =O4 -> 211.875 | P5: 1809 | Q5: 153475 | R5: =Q5-Q4 -> 176 | S5: =SUM(P5-P4) -> 2 | T5: =SUM(S5*$T$2) -> 0 | U5: =SUM(G5+L5+S5) -> 5 | V5: =R5+N5+I5:I5 -> 417 | W5: =SUM(V5/U5) -> 83.4 | X5: 2418 | Y5: =X5-X4 -> 0 | Z5: =Z4 -> 135964.1 | AA5: =Z5-Z4 -> 0 | AB5: =SUM(Y5*$AB$2) -> 0 | AC5: =AC4 -> 1857 | AD5: =AC5-AC4 -> 0 | AE5: =AE4 -> 360818 | AF5: =AE5-AE4 -> 0 | AG5: =IF(AD5>0,AF5/AD5,0) -> 0 | AH5: =AF5+AA5 -> 0 | AI5: =SUM(AH5+V5) -> 417 | AJ5: =-tanks!AW6 -> 417 | AK5: =SUM(AJ5-AI5) -> 0 | AL5: =S5+L5+G5 -> 5 | AM5: =Y5+AD5 -> 0 | AN5: 69 | AO5: =(AN5/100)*3000 -> 2070 | AP5: 76 | AQ5: =(AP5/100)*3000 -> 2280 | AR5: 76 | AS5: =(AR5/100)*3000 -> 2280 | AT5: =SUM(AO5+AQ5+AS5) -> 6630 | AU5: =AT4-AT5+AV5 -> 90 | AX5: =IF(AV5>0,AW5,AX4) -> 0.7
A6: =ELEC!C4 -> 44014 | B6: 165 | C6: 172 | D6: =C5-C6 -> 18 | E6: =D6*8.38 -> 150.84 | F6: =F5 -> 1605 | G6: =F6-F5 -> 0 | H6: =H5 -> 354564 | I6: =SUM(H6-H5) -> 0 | J6: =IF(G6>0,I6/G6,0) -> 0 | K6: =K5 -> 2069 | L6: =K6-K5 -> 0 | M6: =M5 -> 151781 | N6: =M6-M5 -> 0 | O6: =O5 -> 211.875 | P6: 1815 | Q6: 153940 | R6: =Q6-Q5 -> 465 | S6: =SUM(P6-P5) -> 6 | T6: =SUM(S6*$T$2) -> 0 | U6: =SUM(G6+L6+S6) -> 6 | V6: =R6+N6+I6:I6 -> 465 | W6: =SUM(V6/U6) -> 77.5 | X6: =X5 -> 2418 | Y6: =X6-X5 -> 0 | Z6: =Z5 -> 135964.1 | AA6: =Z6-Z5 -> 0 | AB6: =SUM(Y6*$AB$2) -> 0 | AC6: 1862 | AD6: =AC6-AC5 -> 5 | AE6: 361088 | AF6: =AE6-AE5 -> 270 | AG6: =IF(AD6>0,AF6/AD6,0) -> 54 | AH6: =AF6+AA6 -> 270 | AI6: =SUM(AH6+V6) -> 735 | AJ6: =-tanks!AW7 -> 735 | AK6: =SUM(AJ6-AI6) -> 0 | AL6: =S6+L6+G6 -> 6 | AM6: =Y6+AD6 -> 5 | AN6: 80 | AO6: =(AN6/100)*3000 -> 2400 | AP6: 80 | AQ6: =(AP6/100)*3000 -> 2400 | AR6: 81 | AS6: =(AR6/100)*3000 -> 2430 | AT6: =SUM(AO6+AQ6+AS6) -> 7230 | AU6: =AT5-AT6+AV6 -> 400 | AV6: 1000 | AW6: 0.7 | AX6: =IF(AV6>0,AW6,AX5) -> 0.7
A7: =ELEC!C5 -> 44015 | B7: 149 | C7: 158 | D7: =C6-C7 -> 14 | E7: =D7*8.38 -> 117.32 | F7: 1608 | G7: =F7-F6 -> 3 | H7: 354815 | I7: =SUM(H7-H6) -> 251 | J7: =IF(G7>0,I7/G7,0) -> 83.666667 | K7: =K6 -> 2069 | L7: =K7-K6 -> 0 | M7: =M6 -> 151781 | N7: =M7-M6 -> 0 | O7: =O6 -> 211.875 | P7: 1817 | Q7: 154077 | R7: =Q7-Q6 -> 137 | S7: =SUM(P7-P6) -> 2 | T7: =SUM(S7*$T$2) -> 0 | U7: =SUM(G7+L7+S7) -> 5 | V7: =R7+N7+I7:I7 -> 388 | W7: =SUM(V7/U7) -> 77.6 | X7: =X6 -> 2418 | Y7: =X7-X6 -> 0 | Z7: =Z6 -> 135964.1 | AA7: =Z7-Z6 -> 0 | AB7: =SUM(Y7*$AB$2) -> 0 | AC7: =AC6 -> 1862 | AD7: =AC7-AC6 -> 0 | AE7: =AE6 -> 361088 | AF7: =AE7-AE6 -> 0 | AG7: =IF(AD7>0,AF7/AD7,0) -> 0 | AH7: =AF7+AA7 -> 0 | AI7: =SUM(AH7+V7) -> 388 | AJ7: =-tanks!AW8 -> 388 | AK7: =SUM(AJ7-AI7) -> 0 | AL7: =S7+L7+G7 -> 5 | AM7: =Y7+AD7 -> 0 | AN7: 78 | AO7: =(AN7/100)*3000 -> 2340 | AP7: 79 | AQ7: =(AP7/100)*3000 -> 2370 | AR7: 78 | AS7: =(AR7/100)*3000 -> 2340 | AT7: =SUM(AO7+AQ7+AS7) -> 7050 | AU7: =AT6-AT7+AV7 -> 180 | AX7: =IF(AV7>0,AW7,AX6) -> 0.7
A8: =ELEC!C6 -> 44016 | B8: 131 | C8: 141.5 | D8: =C7-C8 -> 16.5 | E8: =D8*8.38 -> 138.27 | F8: 1611 | G8: =F8-F7 -> 3 | H8: 355017 | I8: =SUM(H8-H7) -> 202 | J8: =IF(G8>0,I8/G8,0) -> 67.333333 | K8: 2070 | L8: =K8-K7 -> 1 | M8: 151864 | N8: =M8-M7 -> 83 | O8: =O7 -> 211.875 | P8: 1819 | Q8: 154326 | R8: =Q8-Q7 -> 249 | S8: =SUM(P8-P7) -> 2 | T8: =SUM(S8*$T$2) -> 0 | U8: =SUM(G8+L8+S8) -> 6 | V8: =R8+N8+I8:I8 -> 534 | W8: =SUM(V8/U8) -> 89 | X8: =X7 -> 2418 | Y8: =X8-X7 -> 0 | Z8: =Z7 -> 135964.1 | AA8: =Z8-Z7 -> 0 | AB8: =SUM(Y8*$AB$2) -> 0 | AC8: =AC7 -> 1862 | AD8: =AC8-AC7 -> 0 | AE8: =AE7 -> 361088 | AF8: =AE8-AE7 -> 0 | AG8: =IF(AD8>0,AF8/AD8,0) -> 0 | AH8: =AF8+AA8 -> 0 | AI8: =SUM(AH8+V8) -> 534 | AJ8: =-tanks!AW9 -> 534 | AK8: =SUM(AJ8-AI8) -> 0 | AL8: =S8+L8+G8 -> 6 | AM8: =Y8+AD8 -> 0 | AN8: 78 | AO8: =(AN8/100)*3000 -> 2340 | AP8: 79 | AQ8: =(AP8/100)*3000 -> 2370 | AR8: 77 | AS8: =(AR8/100)*3000 -> 2310 | AT8: =SUM(AO8+AQ8+AS8) -> 7020 | AU8: =AT7-AT8+AV8 -> 30 | AX8: =IF(AV8>0,AW8,AX7) -> 0.7
A9: =ELEC!C7 -> 44017 | B9: 113 | C9: 125 | D9: =C8-C9 -> 16.5 | E9: =D9*8.38 -> 138.27 | F9: 1611 | G9: =F9-F8 -> 0 | H9: 355017 | I9: =SUM(H9-H8) -> 0 | J9: =IF(G9>0,I9/G9,0) -> 0 | K9: 2071 | L9: =K9-K8 -> 1 | M9: 151957 | N9: =M9-M8 -> 93 | O9: =O8 -> 211.875 | P9: 1823 | Q9: 154571 | R9: =Q9-Q8 -> 245 | S9: =SUM(P9-P8) -> 4 | T9: =SUM(S9*$T$2) -> 0 | U9: =SUM(G9+L9+S9) -> 5 | V9: =R9+N9+I9:I9 -> 338 | W9: =SUM(V9/U9) -> 67.6 | X9: 2418 | Y9: =X9-X8 -> 0 | Z9: =Z8 -> 135964.1 | AA9: =Z9-Z8 -> 0 | AB9: =SUM(Y9*$AB$2) -> 0 | AC9: 1862 | AD9: =AC9-AC8 -> 0 | AE9: 361088 | AF9: =AE9-AE8 -> 0 | AG9: =IF(AD9>0,AF9/AD9,0) -> 0 | AH9: =AF9+AA9 -> 0 | AI9: =SUM(AH9+V9) -> 338 | AJ9: =-tanks!AW10 -> 338 | AK9: =SUM(AJ9-AI9) -> 0 | AL9: =S9+L9+G9 -> 5 | AM9: =Y9+AD9 -> 0 | AN9: 77 | AO9: =(AN9/100)*3000 -> 2310 | AP9: 78 | AQ9: =(AP9/100)*3000 -> 2340 | AR9: 75 | AS9: =(AR9/100)*3000 -> 2250 | AT9: =SUM(AO9+AQ9+AS9) -> 6900 | AU9: =AT8-AT9+AV9 -> 120 | AX9: =IF(AV9>0,AW9,AX8) -> 0.7
A10: =ELEC!C8 -> 44018 | B10: 136 | C10: 143 | D10: =C9-C10 -> -18 | E10: =D10*8.38 -> -150.84 | F10: =F9 -> 1611 | G10: =F10-F9 -> 0 | H10: 355017 | I10: =SUM(H10-H9) -> 0 | J10: =IF(G10>0,I10/G10,0) -> 0 | K10: 2072 | L10: =K10-K9 -> 1 | M10: 152028 | N10: =M10-M9 -> 71 | O10: =O9 -> 211.875 | P10: 1825 | Q10: 154746 | R10: =Q10-Q9 -> 175 | S10: =SUM(P10-P9) -> 2 | T10: =SUM(S10*$T$2) -> 0 | U10: =SUM(G10+L10+S10) -> 3 | V10: =R10+N10+I10:I10 -> 246 | W10: =SUM(V10/U10) -> 82 | X10: 2418 | Y10: =X10-X9 -> 0 | Z10: 135964.1 | AA10: =Z10-Z9 -> 0 | AB10: =SUM(Y10*$AB$2) -> 0 | AC10: 1865 | AD10: =AC10-AC9 -> 3 | AE10: 361272 | AF10: =AE10-AE9 -> 184 | AG10: =IF(AD10>0,AF10/AD10,0) -> 61.333333 | AH10: =AF10+AA10 -> 184 | AI10: =SUM(AH10+V10) -> 430 | AJ10: =-tanks!AW11 -> 430 | AK10: =SUM(AJ10-AI10) -> 0 | AL10: =S10+L10+G10 -> 3 | AM10: =Y10+AD10 -> 3 | AN10: 75 | AO10: =(AN10/100)*3000 -> 2250 | AP10: 76 | AQ10: =(AP10/100)*3000 -> 2280 | AR10: 74 | AS10: =(AR10/100)*3000 -> 2220 | AT10: =SUM(AO10+AQ10+AS10) -> 6750 | AU10: =AT9-AT10+AV10 -> 150 | AX10: =IF(AV10>0,AW10,AX9) -> 0.7
A11: =ELEC!C9 -> 44019 | B11: 118 | C11: 125.4 | D11: =C10-C11 -> 17.6 | E11: =D11*8.38 -> 147.488 | F11: 1614 | G11: =F11-F10 -> 3 | H11: 355214 | I11: =SUM(H11-H10) -> 197 | J11: =IF(G11>0,I11/G11,0) -> 65.666667 | K11: 2075 | L11: =K11-K10 -> 3 | M11: 152253 | N11: =M11-M10 -> 225 | O11: =O10 -> 211.875 | P11: 1827 | Q11: 154981 | R11: =Q11-Q10 -> 235 | S11: =SUM(P11-P10) -> 2 | T11: =SUM(S11*$T$2) -> 0 | U11: =SUM(G11+L11+S11) -> 8 | V11: =R11+N11+I11:I11 -> 657 | W11: =SUM(V11/U11) -> 82.125 | X11: 2418 | Y11: =X11-X10 -> 0 | Z11: =Z10 -> 135964.1 | AA11: =Z11-Z10 -> 0 | AB11: =SUM(Y11*$AB$2) -> 0 | AC11: 1865 | AD11: =AC11-AC10 -> 0 | AE11: 361272 | AF11: =AE11-AE10 -> 0 | AG11: =IF(AD11>0,AF11/AD11,0) -> 0 | AH11: =AF11+AA11 -> 0 | AI11: =SUM(AH11+V11) -> 657 | AJ11: =-tanks!AW12 -> 657 | AK11: =SUM(AJ11-AI11) -> 0 | AL11: =S11+L11+G11 -> 8 | AM11: =Y11+AD11 -> 0 | AN11: 73 | AO11: =(AN11/100)*3000 -> 2190 | AP11: 75 | AQ11: =(AP11/100)*3000 -> 2250 | AR11: 72 | AS11: =(AR11/100)*3000 -> 2160 | AT11: =SUM(AO11+AQ11+AS11) -> 6600 | AU11: =AT10-AT11+AV11 -> 150 | AX11: =IF(AV11>0,AW11,AX10) -> 0.7
A12: =ELEC!C10 -> 44020 | B12: 138.2 | C12: 145.3 | D12: =C11-C12 -> -19.9 | E12: =D12*8.38 -> -166.762 | F12: 1615 | G12: =F12-F11 -> 1 | H12: 355291 | I12: =SUM(H12-H11) -> 77 | J12: =IF(G12>0,I12/G12,0) -> 77 | K12: 2075 | L12: =K12-K11 -> 0 | M12: 152253 | N12: =M12-M11 -> 0 | O12: =O11 -> 211.875 | P12: 1829 | Q12: 155136 | R12: =Q12-Q11 -> 155 | S12: =SUM(P12-P11) -> 2 | T12: =SUM(S12*$T$2) -> 0 | U12: =SUM(G12+L12+S12) -> 3 | V12: =R12+N12+I12:I12 -> 232 | W12: =SUM(V12/U12) -> 77.333333 | X12: 2418 | Y12: =X12-X11 -> 0 | Z12: =Z11 -> 135964.1 | AA12: =Z12-Z11 -> 0 | AB12: =SUM(Y12*$AB$2) -> 0 | AC12: 1869 | AD12: =AC12-AC11 -> 4 | AE12: 361552 | AF12: =AE12-AE11 -> 280 | AG12: =IF(AD12>0,AF12/AD12,0) -> 70 | AH12: =AF12+AA12 -> 280 | AI12: =SUM(AH12+V12) -> 512 | AJ12: =-tanks!AW13 -> 512 | AK12: =SUM(AJ12-AI12) -> 0 | AL12: =S12+L12+G12 -> 3 | AM12: =Y12+AD12 -> 4 | AN12: 70 | AO12: =(AN12/100)*3000 -> 2100 | AP12: 73 | AQ12: =(AP12/100)*3000 -> 2190 | AR12: 70 | AS12: =(AR12/100)*3000 -> 2100 | AT12: =SUM(AO12+AQ12+AS12) -> 6390 | AU12: =AT11-AT12+AV12 -> 210 | AX12: =IF(AV12>0,AW12,AX11) -> 0.7
A13: =ELEC!C11 -> 44021 | B13: 120.3 | C13: 127.2 | D13: =C12-C13 -> 18.1 | E13: =D13*8.38 -> 151.678 | F13: 1618 | G13: =F13-F12 -> 3 | H13: 355545 | I13: =SUM(H13-H12) -> 254 | J13: =IF(G13>0,I13/G13,0) -> 84.666667 | K13: 2075 | L13: =K13-K12 -> 0 | M13: 152253 | N13: =M13-M12 -> 0 | O13: =O12 -> 211.875 | P13: 1829 | Q13: 155136 | R13: =Q13-Q12 -> 0 | S13: =SUM(P13-P12) -> 0 | T13: =SUM(S13*$T$2) -> 0 | U13: =SUM(G13+L13+S13) -> 3 | V13: =R13+N13+I13:I13 -> 254 | W13: =SUM(V13/U13) -> 84.666667 | X13: 2418 | Y13: =X13-X12 -> 0 | Z13: 135964 | AA13: =Z13-Z12 -> -0.1 | AB13: =SUM(Y13*$AB$2) -> 0 | AC13: 1869 | AD13: =AC13-AC12 -> 0 | AE13: 361554.1 | AF13: =AE13-AE12 -> 2.1 | AG13: =IF(AD13>0,AF13/AD13,0) -> 0 | AH13: =AF13+AA13 -> 2 | AI13: =SUM(AH13+V13) -> 256 | AJ13: =-tanks!AW14 -> 256 | AK13: =SUM(AJ13-AI13) -> 0 | AL13: =S13+L13+G13 -> 3 | AM13: =Y13+AD13 -> 0 | AN13: 79 | AO13: =(AN13/100)*3000 -> 2370 | AP13: 80 | AQ13: =(AP13/100)*3000 -> 2400 | AR13: 81 | AS13: =(AR13/100)*3000 -> 2430 | AT13: =SUM(AO13+AQ13+AS13) -> 7200 | AU13: =AT12-AT13+AV13 -> 390 | AV13: 1200 | AW13: 0.7 | AX13: =IF(AV13>0,AW13,AX12) -> 0.7
A14: =ELEC!C12 -> 44022 | B14: 178.2 | C14: 185 | D14: =C13-C14 -> -57.8 | E14: =D14*8.38 -> -484.364 | F14: 1621 | G14: =F14-F13 -> 3 | H14: 355804 | I14: =SUM(H14-H13) -> 259 | J14: =IF(G14>0,I14/G14,0) -> 86.333333 | K14: 2075 | L14: =K14-K13 -> 0 | M14: 152253 | N14: =M14-M13 -> 0 | O14: =O13 -> 211.875 | P14: 1829 | Q14: 155219 | R14: =Q14-Q13 -> 83 | S14: =SUM(P14-P13) -> 0 | T14: =SUM(S14*$T$2) -> 0 | U14: =SUM(G14+L14+S14) -> 3 | V14: =R14+N14+I14:I14 -> 342 | W14: =SUM(V14/U14) -> 114 | X14: 2418 | Y14: =X14-X13 -> 0 | Z14: 135964 | AA14: =Z14-Z13 -> 0 | AB14: =SUM(Y14*$AB$2) -> 0 | AC14: 1869 | AD14: =AC14-AC13 -> 0 | AE14: 361554.9 | AF14: =AE14-AE13 -> 0.8 | AG14: =IF(AD14>0,AF14/AD14,0) -> 0 | AH14: =AF14+AA14 -> 0.8 | AI14: =SUM(AH14+V14) -> 342.8 | AJ14: =-tanks!AW15 -> 342.8 | AK14: =SUM(AJ14-AI14) -> 0 | AL14: =S14+L14+G14 -> 3 | AM14: =Y14+AD14 -> 0 | AN14: 77 | AO14: =(AN14/100)*3000 -> 2310 | AP14: 79 | AQ14: =(AP14/100)*3000 -> 2370 | AR14: 78 | AS14: =(AR14/100)*3000 -> 2340 | AT14: =SUM(AO14+AQ14+AS14) -> 7020 | AU14: =AT13-AT14+AV14 -> 180 | AX14: =IF(AV14>0,AW14,AX13) -> 0.7
A15: =ELEC!C13 -> 44023 | B15: 159 | C15: 166 | D15: =C14-C15 -> 19 | E15: =D15*8.38 -> 159.22 | F15: =F14 -> 1621 | G15: =F15-F14 -> 0 | H15: =H14 -> 355804 | I15: =SUM(H15-H14) -> 0 | J15: =IF(G15>0,I15/G15,0) -> 0 | K15: =K14 -> 2075 | L15: =K15-K14 -> 0 | M15: =M14 -> 152253 | N15: =M15-M14 -> 0 | O15: =O14 -> 211.875 | P15: 1830 | Q15: 155334 | R15: =Q15-Q14 -> 115 | S15: =SUM(P15-P14) -> 1 | T15: =SUM(S15*$T$2) -> 0 | U15: =SUM(G15+L15+S15) -> 1 | V15: =R15+N15+I15:I15 -> 115 | W15: =SUM(V15/U15) -> 115 | X15: =X14 -> 2418 | Y15: =X15-X14 -> 0 | Z15: =Z14 -> 135964 | AA15: =Z15-Z14 -> 0 | AB15: =SUM(Y15*$AB$2) -> 0 | AC15: 1873 | AD15: =AC15-AC14 -> 4 | AE15: 361774.9 | AF15: =AE15-AE14 -> 220 | AG15: =IF(AD15>0,AF15/AD15,0) -> 55 | AH15: =AF15+AA15 -> 220 | AI15: =SUM(AH15+V15) -> 335 | AJ15: =-tanks!AW16 -> 335 | AK15: =SUM(AJ15-AI15) -> 0 | AL15: =S15+L15+G15 -> 1 | AM15: =Y15+AD15 -> 4 | AN15: 76 | AO15: =(AN15/100)*3000 -> 2280 | AP15: 78 | AQ15: =(AP15/100)*3000 -> 2340 | AR15: 76 | AS15: =(AR15/100)*3000 -> 2280 | AT15: =SUM(AO15+AQ15+AS15) -> 6900 | AU15: =AT14-AT15+AV15 -> 120 | AX15: =IF(AV15>0,AW15,AX14) -> 0.7
A16: =ELEC!C14 -> 44024 | B16: 139 | C16: 146 | D16: =C15-C16 -> 20 | E16: =D16*8.38 -> 167.6 | F16: 1623 | G16: =F16-F15 -> 2 | H16: 355940 | I16: =SUM(H16-H15) -> 136 | J16: =IF(G16>0,I16/G16,0) -> 68 | K16: 2076 | L16: =K16-K15 -> 1 | M16: 152337 | N16: =M16-M15 -> 84 | O16: =O15 -> 211.875 | P16: 1830 | Q16: 155334 | R16: =Q16-Q15 -> 0 | S16: =SUM(P16-P15) -> 0 | T16: =SUM(S16*$T$2) -> 0 | U16: =SUM(G16+L16+S16) -> 3 | V16: =R16+N16+I16:I16 -> 220 | W16: =SUM(V16/U16) -> 73.333333 | X16: 2418 | Y16: =X16-X15 -> 0 | Z16: 135964 | AA16: =Z16-Z15 -> 0 | AB16: =SUM(Y16*$AB$2) -> 0 | AC16: 1873 | AD16: =AC16-AC15 -> 0 | AE16: =AE15 -> 361774.9 | AF16: =AE16-AE15 -> 0 | AG16: =IF(AD16>0,AF16/AD16,0) -> 0 | AH16: =AF16+AA16 -> 0 | AI16: =SUM(AH16+V16) -> 220 | AJ16: =-tanks!AW17 -> 220 | AK16: =SUM(AJ16-AI16) -> 0 | AL16: =S16+L16+G16 -> 3 | AM16: =Y16+AD16 -> 0 | AN16: 75 | AO16: =(AN16/100)*3000 -> 2250 | AP16: 78 | AQ16: =(AP16/100)*3000 -> 2340 | AR16: 76 | AS16: =(AR16/100)*3000 -> 2280 | AT16: =SUM(AO16+AQ16+AS16) -> 6870 | AU16: =AT15-AT16+AV16 -> 30 | AX16: =IF(AV16>0,AW16,AX15) -> 0.7
A17: =ELEC!C15 -> 44025 | B17: 122.2 | C17: 129 | D17: =C16-C17 -> 17 | E17: =D17*8.38 -> 142.46 | F17: 1624 | G17: =F17-F16 -> 1 | H17: 356052 | I17: =SUM(H17-H16) -> 112 | J17: =IF(G17>0,I17/G17,0) -> 112 | K17: 2077 | L17: =K17-K16 -> 1 | M17: 152390 | N17: =M17-M16 -> 53 | O17: =O16 -> 211.875 | P17: 1830 | Q17: 155334 | R17: =Q17-Q16 -> 0 | S17: =SUM(P17-P16) -> 0 | T17: =SUM(S17*$T$2) -> 0 | U17: =SUM(G17+L17+S17) -> 2 | V17: =R17+N17+I17:I17 -> 165 | X17: 2418 | Y17: =X17-X16 -> 0 | Z17: 135964 | AA17: =Z17-Z16 -> 0 | AB17: =SUM(Y17*$AB$2) -> 0 | AC17: 1873 | AD17: =AC17-AC16 -> 0 | AE17: =AE16 -> 361774.9 | AF17: =AE17-AE16 -> 0 | AG17: =IF(AD17>0,AF17/AD17,0) -> 0 | AH17: =AF17+AA17 -> 0 | AI17: =SUM(AH17+V17) -> 165 | AJ17: =-tanks!AW18 -> 165 | AK17: =SUM(AJ17-AI17) -> 0 | AL17: =S17+L17+G17 -> 2 | AM17: =Y17+AD17 -> 0 | AN17: 73 | AO17: =(AN17/100)*3000 -> 2190 | AP17: 78 | AQ17: =(AP17/100)*3000 -> 2340 | AR17: 76 | AS17: =(AR17/100)*3000 -> 2280 | AT17: =SUM(AO17+AQ17+AS17) -> 6810 | AU17: =AT16-AT17+AV17 -> 60 | AX17: =IF(AV17>0,AW17,AX16) -> 0.7
A18: =ELEC!C16 -> 44026 | B18: 137 | C18: 144 | D18: =C17-C18 -> -15 | E18: =D18*8.38 -> -125.7 | F18: 1628 | G18: =F18-F17 -> 4 | H18: 356324 | I18: =SUM(H18-H17) -> 272 | J18: =IF(G18>0,I18/G18,0) -> 68 | K18: 2077 | L18: =K18-K17 -> 0 | M18: 152390 | N18: =M18-M17 -> 0 | O18: =O17 -> 211.875 | P18: 1830 | Q18: 155334 | R18: =Q18-Q17 -> 0 | S18: =SUM(P18-P17) -> 0 | T18: =SUM(S18*$T$2) -> 0 | U18: =SUM(G18+L18+S18) -> 4 | V18: =R18+N18+I18:I18 -> 272 | X18: 2418 | Y18: =X18-X17 -> 0 | Z18: 135964 | AA18: =Z18-Z17 -> 0 | AB18: =SUM(Y18*$AB$2) -> 0 | AC18: 1875 | AD18: =AC18-AC17 -> 2 | AE18: 361937 | AF18: =AE18-AE17 -> 162.1 | AG18: =IF(AD18>0,AF18/AD18,0) -> 81.05 | AH18: =AF18+AA18 -> 162.1 | AI18: =SUM(AH18+V18) -> 434.1 | AJ18: =-tanks!AW19 -> 434.1 | AK18: =SUM(AJ18-AI18) -> 0 | AL18: =S18+L18+G18 -> 4 | AM18: =Y18+AD18 -> 2 | AN18: 71 | AO18: =(AN18/100)*3000 -> 2130 | AP18: 76 | AQ18: =(AP18/100)*3000 -> 2280 | AR18: 75 | AS18: =(AR18/100)*3000 -> 2250 | AT18: =SUM(AO18+AQ18+AS18) -> 6660 | AU18: =AT17-AT18+AV18 -> 150 | AX18: =IF(AV18>0,AW18,AX17) -> 0.7
A19: =ELEC!C17 -> 44027 | B19: 118.2 | C19: 125.2 | D19: =C18-C19 -> 18.8 | E19: =D19*8.38 -> 157.544 | F19: 1630 | G19: =F19-F18 -> 2 | H19: 356492 | I19: =SUM(H19-H18) -> 168 | J19: =IF(G19>0,I19/G19,0) -> 84 | K19: 2077 | L19: =K19-K18 -> 0 | M19: 152390 | N19: =M19-M18 -> 0 | O19: =O18 -> 211.875 | P19: 1830 | Q19: 155334 | R19: =Q19-Q18 -> 0 | S19: =SUM(P19-P18) -> 0 | T19: =SUM(S19*$T$2) -> 0 | U19: =SUM(G19+L19+S19) -> 2 | V19: =R19+N19+I19:I19 -> 168 | X19: 2418 | Y19: =X19-X18 -> 0 | Z19: 135964 | AA19: =Z19-Z18 -> 0 | AB19: =SUM(Y19*$AB$2) -> 0 | AC19: 1880 | AD19: =AC19-AC18 -> 5 | AE19: 362221 | AF19: =AE19-AE18 -> 284 | AG19: =IF(AD19>0,AF19/AD19,0) -> 56.8 | AH19: =AF19+AA19 -> 284 | AI19: =SUM(AH19+V19) -> 452 | AJ19: =-tanks!AW20 -> 452 | AK19: =SUM(AJ19-AI19) -> 0 | AL19: =S19+L20+G19 -> 2 | AM19: =Y19+AD19 -> 5 | AN19: 69 | AO19: =(AN19/100)*3000 -> 2070 | AP19: 73 | AQ19: =(AP19/100)*3000 -> 2190 | AR19: 73 | AS19: =(AR19/100)*3000 -> 2190 | AT19: =SUM(AO19+AQ19+AS19) -> 6450 | AU19: =AT18-AT19+AV19 -> 210 | AX19: =IF(AV19>0,AW19,AX18) -> 0.7
A20: =ELEC!C18 -> 44028 | B20: 171.3 | C20: 178 | D20: =C19-C20 -> -52.8 | E20: =D20*8.38 -> -442.464 | F20: 1633 | G20: =F20-F19 -> 3 | H20: 356674 | I20: =SUM(H20-H19) -> 182 | J20: =IF(G20>0,I20/G20,0) -> 60.666667 | K20: 2077 | L20: =K20-K19 -> 0 | M20: 152390 | N20: =M20-M19 -> 0 | O20: =O19 -> 211.875 | P20: 1830 | Q20: 155334 | R20: =Q20-Q19 -> 0 | S20: =SUM(P20-P19) -> 0 | T20: =SUM(S20*$T$2) -> 0 | U20: =SUM(G20+L20+S20) -> 3 | V20: =R20+N20+I20:I20 -> 182 | X20: 2418 | Y20: =X20-X19 -> 0 | Z20: 135964 | AA20: =Z20-Z19 -> 0 | AB20: =SUM(Y20*$AB$2) -> 0 | AC20: 1881 | AD20: =AC20-AC19 -> 1 | AE20: 362296 | AF20: =AE20-AE19 -> 75 | AG20: =IF(AD20>0,AF20/AD20,0) -> 75 | AH20: =AF20+AA20 -> 75 | AI20: =SUM(AH20+V20) -> 257 | AJ20: =-tanks!AW21 -> 257 | AK20: =SUM(AJ20-AI20) -> 0 | AL20: =S20+L21+G20 -> 3 | AM20: =Y20+AD20 -> 1 | AN20: 83 | AO20: =(AN20/100)*3000 -> 2490 | AP20: 83 | AQ20: =(AP20/100)*3000 -> 2490 | AR20: 82 | AS20: =(AR20/100)*3000 -> 2460 | AT20: =SUM(AO20+AQ20+AS20) -> 7440 | AU20: =AT19-AT20+AV20 -> 310 | AV20: 1300 | AW20: 0.7 | AX20: =IF(AV20>0,AW20,AX19) -> 0.7
A21: =ELEC!C19 -> 44029 | B21: =B20 -> 171.3 | C21: =C20 -> 178 | D21: =C20-C21 -> 0 | E21: =D21*8.38 -> 0 | F21: =F20 -> 1633 | G21: =F21-F20 -> 0 | H21: =H20 -> 356674 | I21: =SUM(H21-H20) -> 0 | J21: =IF(G21>0,I21/G21,0) -> 0 | K21: =K20 -> 2077 | L21: =K21-K20 -> 0 | M21: =M20 -> 152390 | N21: =M21-M20 -> 0 | O21: =O20 -> 211.875 | P21: =P20 -> 1830 | Q21: =Q20 -> 155334 | R21: =Q21-Q20 -> 0 | S21: =SUM(P21-P20) -> 0 | T21: =SUM(S21*$T$2) -> 0 | U21: =SUM(G21+L21+S21) -> 0 | V21: =R21+N21+I21:I21 -> 0 | X21: =X20 -> 2418 | Y21: =X21-X20 -> 0 | Z21: =Z20 -> 135964 | AA21: =Z21-Z20 -> 0 | AB21: =SUM(Y21*$AB$2) -> 0 | AC21: =AC20 -> 1881 | AD21: =AC21-AC20 -> 0 | AE21: =AE20 -> 362296 | AF21: =AE21-AE20 -> 0 | AG21: =IF(AD21>0,AF21/AD21,0) -> 0 | AH21: =AF21+AA21 -> 0 | AI21: =SUM(AH21+V21) -> 0 | AJ21: =-tanks!AW22 -> 0 | AK21: =SUM(AJ21-AI21) -> 0 | AL21: =S21+L21+G21 -> 0 | AM21: =Y21+AD21 -> 0 | AN21: =AN20 -> 83 | AO21: =(AN21/100)*3000 -> 2490 | AP21: =AP20 -> 83 | AQ21: =(AP21/100)*3000 -> 2490 | AR21: =AR20 -> 82 | AS21: =(AR21/100)*3000 -> 2460 | AT21: =SUM(AO21+AQ21+AS21) -> 7440 | AU21: =AT20-AT21+AV21 -> 0 | AX21: =IF(AV21>0,AW21,AX20) -> 0.7
A22: =ELEC!C20 -> 44030 | B22: =B21 -> 171.3 | C22: =C21 -> 178 | D22: =C21-C22 -> 0 | E22: =D22*8.38 -> 0 | F22: =F21 -> 1633 | G22: =F22-F21 -> 0 | H22: =H21 -> 356674 | I22: =SUM(H22-H21) -> 0 | J22: =IF(G22>0,I22/G22,0) -> 0 | K22: =K21 -> 2077 | L22: =K22-K21 -> 0 | M22: =M21 -> 152390 | N22: =M22-M21 -> 0 | O22: =O21 -> 211.875 | P22: =P21 -> 1830 | Q22: =Q21 -> 155334 | R22: =Q22-Q21 -> 0 | S22: =SUM(P22-P21) -> 0 | T22: =SUM(S22*$T$2) -> 0 | U22: =SUM(G22+L22+S22) -> 0 | V22: =R22+N22+I22:I22 -> 0 | X22: =X21 -> 2418 | Y22: =X22-X21 -> 0 | Z22: =Z21 -> 135964 | AA22: =Z22-Z21 -> 0 | AB22: =SUM(Y22*$AB$2) -> 0 | AC22: =AC21 -> 1881 | AD22: =AC22-AC21 -> 0 | AE22: =AE21 -> 362296 | AF22: =AE22-AE21 -> 0 | AG22: =IF(AD22>0,AF22/AD22,0) -> 0 | AH22: =AF22+AA22 -> 0 | AI22: =SUM(AH22+V22) -> 0 | AJ22: =-tanks!AW23 -> 0 | AK22: =SUM(AJ22-AI22) -> 0 | AL22: =S22+L22+G22 -> 0 | AM22: =Y22+AD22 -> 0 | AN22: =AN21 -> 83 | AO22: =(AN22/100)*3000 -> 2490 | AP22: =AP21 -> 83 | AQ22: =(AP22/100)*3000 -> 2490 | AR22: =AR21 -> 82 | AS22: =(AR22/100)*3000 -> 2460 | AT22: =SUM(AO22+AQ22+AS22) -> 7440 | AU22: =AT21-AT22+AV22 -> 0 | AX22: =IF(AV22>0,AW22,AX21) -> 0.7
A23: =ELEC!C21 -> 44031 | B23: =B22 -> 171.3 | C23: =C22 -> 178 | D23: =C22-C23 -> 0 | E23: =D23*8.38 -> 0 | F23: =F22 -> 1633 | G23: =F23-F22 -> 0 | H23: =H22 -> 356674 | I23: =SUM(H23-H22) -> 0 | J23: =IF(G23>0,I23/G23,0) -> 0 | K23: =K22 -> 2077 | L23: =K23-K22 -> 0 | M23: =M22 -> 152390 | N23: =M23-M22 -> 0 | O23: =O22 -> 211.875 | P23: =P22 -> 1830 | Q23: =Q22 -> 155334 | R23: =Q23-Q22 -> 0 | S23: =SUM(P23-P22) -> 0 | T23: =SUM(S23*$T$2) -> 0 | U23: =SUM(G23+L23+S23) -> 0 | V23: =R23+N23+I23:I23 -> 0 | X23: =X22 -> 2418 | Y23: =X23-X22 -> 0 | Z23: =Z22 -> 135964 | AA23: =Z23-Z22 -> 0 | AB23: =SUM(Y23*$AB$2) -> 0 | AC23: =AC22 -> 1881 | AD23: =AC23-AC22 -> 0 | AE23: =AE22 -> 362296 | AF23: =AE23-AE22 -> 0 | AG23: =IF(AD23>0,AF23/AD23,0) -> 0 | AH23: =AF23+AA23 -> 0 | AI23: =SUM(AH23+V23) -> 0 | AJ23: =-tanks!AW24 -> 0 | AK23: =SUM(AJ23-AI23) -> 0 | AL23: =S23+L23+G23 -> 0 | AM23: =Y23+AD23 -> 0 | AN23: =AN22 -> 83 | AO23: =(AN23/100)*3000 -> 2490 | AP23: =AP22 -> 83 | AQ23: =(AP23/100)*3000 -> 2490 | AR23: =AR22 -> 82 | AS23: =(AR23/100)*3000 -> 2460 | AT23: =SUM(AO23+AQ23+AS23) -> 7440 | AU23: =AT22-AT23+AV23 -> 0 | AX23: =IF(AV23>0,AW23,AX22) -> 0.7
A24: =ELEC!C22 -> 44032 | B24: =B23 -> 171.3 | C24: =C23 -> 178 | D24: =C23-C24 -> 0 | E24: =D24*8.38 -> 0 | F24: =F23 -> 1633 | G24: =F24-F23 -> 0 | H24: =H23 -> 356674 | I24: =SUM(H24-H23) -> 0 | J24: =IF(G24>0,I24/G24,0) -> 0 | K24: =K23 -> 2077 | L24: =K24-K23 -> 0 | M24: =M23 -> 152390 | N24: =M24-M23 -> 0 | O24: =O23 -> 211.875 | P24: =P23 -> 1830 | Q24: =Q23 -> 155334 | R24: =Q24-Q23 -> 0 | S24: =SUM(P24-P23) -> 0 | T24: =SUM(S24*$T$2) -> 0 | U24: =SUM(G24+L24+S24) -> 0 | V24: =R24+N24+I24:I24 -> 0 | X24: =X23 -> 2418 | Y24: =X24-X23 -> 0 | Z24: =Z23 -> 135964 | AA24: =Z24-Z23 -> 0 | AB24: =SUM(Y24*$AB$2) -> 0 | AC24: =AC23 -> 1881 | AD24: =AC24-AC23 -> 0 | AE24: =AE23 -> 362296 | AF24: =AE24-AE23 -> 0 | AG24: =IF(AD24>0,AF24/AD24,0) -> 0 | AH24: =AF24+AA24 -> 0 | AI24: =SUM(AH24+V24) -> 0 | AJ24: =-tanks!AW25 -> 0 | AK24: =SUM(AJ24-AI24) -> 0 | AL24: =S24+L24+G24 -> 0 | AM24: =Y24+AD24 -> 0 | AN24: =AN23 -> 83 | AO24: =(AN24/100)*3000 -> 2490 | AP24: =AP23 -> 83 | AQ24: =(AP24/100)*3000 -> 2490 | AR24: =AR23 -> 82 | AS24: =(AR24/100)*3000 -> 2460 | AT24: =SUM(AO24+AQ24+AS24) -> 7440 | AU24: =AT23-AT24+AV24 -> 0 | AX24: =IF(AV24>0,AW24,AX23) -> 0.7
A25: =ELEC!C23 -> 44033 | B25: =B24 -> 171.3 | C25: =C24 -> 178 | D25: =C24-C25 -> 0 | E25: =D25*8.38 -> 0 | F25: =F24 -> 1633 | G25: =F25-F24 -> 0 | H25: =H24 -> 356674 | I25: =SUM(H25-H24) -> 0 | J25: =IF(G25>0,I25/G25,0) -> 0 | K25: =K24 -> 2077 | L25: =K25-K24 -> 0 | M25: =M24 -> 152390 | N25: =M25-M24 -> 0 | O25: =O24 -> 211.875 | P25: =P24 -> 1830 | Q25: =Q24 -> 155334 | R25: =Q25-Q24 -> 0 | S25: =SUM(P25-P24) -> 0 | T25: =SUM(S25*$T$2) -> 0 | U25: =SUM(G25+L25+S25) -> 0 | V25: =R25+N25+I25:I25 -> 0 | X25: =X24 -> 2418 | Y25: =X25-X24 -> 0 | Z25: =Z24 -> 135964 | AA25: =Z25-Z24 -> 0 | AB25: =SUM(Y25*$AB$2) -> 0 | AC25: =AC24 -> 1881 | AD25: =AC25-AC24 -> 0 | AE25: =AE24 -> 362296 | AF25: =AE25-AE24 -> 0 | AG25: =IF(AD25>0,AF25/AD25,0) -> 0 | AH25: =AF25+AA25 -> 0 | AI25: =SUM(AH25+V25) -> 0 | AJ25: =-tanks!AW26 -> 0 | AK25: =SUM(AJ25-AI25) -> 0 | AL25: =S25+L25+G25 -> 0 | AM25: =Y25+AD25 -> 0 | AN25: =AN24 -> 83 | AO25: =(AN25/100)*3000 -> 2490 | AP25: =AP24 -> 83 | AQ25: =(AP25/100)*3000 -> 2490 | AR25: =AR24 -> 82 | AS25: =(AR25/100)*3000 -> 2460 | AT25: =SUM(AO25+AQ25+AS25) -> 7440 | AU25: =AT24-AT25+AV25 -> 0 | AX25: =IF(AV25>0,AW25,AX24) -> 0.7
A26: =ELEC!C24 -> 44034 | B26: =B25 -> 171.3 | C26: =C25 -> 178 | D26: =C25-C26 -> 0 | E26: =D26*8.38 -> 0 | F26: =F25 -> 1633 | G26: =F26-F25 -> 0 | H26: =H25 -> 356674 | I26: =SUM(H26-H25) -> 0 | J26: =IF(G26>0,I26/G26,0) -> 0 | K26: =K25 -> 2077 | L26: =K26-K25 -> 0 | M26: =M25 -> 152390 | N26: =M26-M25 -> 0 | O26: =O25 -> 211.875 | P26: =P25 -> 1830 | Q26: =Q25 -> 155334 | R26: =Q26-Q25 -> 0 | S26: =SUM(P26-P25) -> 0 | T26: =SUM(S26*$T$2) -> 0 | U26: =SUM(G26+L26+S26) -> 0 | V26: =R26+N26+I26:I26 -> 0 | X26: =X25 -> 2418 | Y26: =X26-X25 -> 0 | Z26: =Z25 -> 135964 | AA26: =Z26-Z25 -> 0 | AB26: =SUM(Y26*$AB$2) -> 0 | AC26: =AC25 -> 1881 | AD26: =AC26-AC25 -> 0 | AE26: =AE25 -> 362296 | AF26: =AE26-AE25 -> 0 | AG26: =IF(AD26>0,AF26/AD26,0) -> 0 | AH26: =AF26+AA26 -> 0 | AI26: =SUM(AH26+V26) -> 0 | AJ26: =-tanks!AW27 -> 0 | AK26: =SUM(AJ26-AI26) -> 0 | AL26: =S26+L26+G26 -> 0 | AM26: =Y26+AD26 -> 0 | AN26: =AN25 -> 83 | AO26: =(AN26/100)*3000 -> 2490 | AP26: =AP25 -> 83 | AQ26: =(AP26/100)*3000 -> 2490 | AR26: =AR25 -> 82 | AS26: =(AR26/100)*3000 -> 2460 | AT26: =SUM(AO26+AQ26+AS26) -> 7440 | AU26: =AT25-AT26+AV26 -> 0 | AX26: =IF(AV26>0,AW26,AX25) -> 0.7
A27: =ELEC!C25 -> 44035 | B27: =B26 -> 171.3 | C27: =C26 -> 178 | D27: =C26-C27 -> 0 | E27: =D27*8.38 -> 0 | F27: =F26 -> 1633 | G27: =F27-F26 -> 0 | H27: =H26 -> 356674 | I27: =SUM(H27-H26) -> 0 | J27: =IF(G27>0,I27/G27,0) -> 0 | K27: =K26 -> 2077 | L27: =K27-K26 -> 0 | M27: =M26 -> 152390 | N27: =M27-M26 -> 0 | O27: =O26 -> 211.875 | P27: =P26 -> 1830 | Q27: =Q26 -> 155334 | R27: =Q27-Q26 -> 0 | S27: =SUM(P27-P26) -> 0 | T27: =SUM(S27*$T$2) -> 0 | U27: =SUM(G27+L27+S27) -> 0 | V27: =R27+N27+I27:I27 -> 0 | X27: =X26 -> 2418 | Y27: =X27-X26 -> 0 | Z27: =Z26 -> 135964 | AA27: =Z27-Z26 -> 0 | AB27: =SUM(Y27*$AB$2) -> 0 | AC27: =AC26 -> 1881 | AD27: =AC27-AC26 -> 0 | AE27: =AE26 -> 362296 | AF27: =AE27-AE26 -> 0 | AG27: =IF(AD27>0,AF27/AD27,0) -> 0 | AH27: =AF27+AA27 -> 0 | AI27: =SUM(AH27+V27) -> 0 | AJ27: =-tanks!AW28 -> 0 | AK27: =SUM(AJ27-AI27) -> 0 | AL27: =S27+L27+G27 -> 0 | AM27: =Y27+AD27 -> 0 | AN27: =AN26 -> 83 | AO27: =(AN27/100)*3000 -> 2490 | AP27: =AP26 -> 83 | AQ27: =(AP27/100)*3000 -> 2490 | AR27: =AR26 -> 82 | AS27: =(AR27/100)*3000 -> 2460 | AT27: =SUM(AO27+AQ27+AS27) -> 7440 | AU27: =AT26-AT27+AV27 -> 0 | AX27: =IF(AV27>0,AW27,AX26) -> 0.7
A28: =ELEC!C26 -> 44036 | B28: =B27 -> 171.3 | C28: =C27 -> 178 | D28: =C27-C28 -> 0 | E28: =D28*8.38 -> 0 | F28: =F27 -> 1633 | G28: =F28-F27 -> 0 | H28: =H27 -> 356674 | I28: =SUM(H28-H27) -> 0 | J28: =IF(G28>0,I28/G28,0) -> 0 | K28: =K27 -> 2077 | L28: =K28-K27 -> 0 | M28: =M27 -> 152390 | N28: =M28-M27 -> 0 | O28: =O27 -> 211.875 | P28: =P27 -> 1830 | Q28: =Q27 -> 155334 | R28: =Q28-Q27 -> 0 | S28: =SUM(P28-P27) -> 0 | T28: =SUM(S28*$T$2) -> 0 | U28: =SUM(G28+L28+S28) -> 0 | V28: =R28+N28+I28:I28 -> 0 | X28: =X27 -> 2418 | Y28: =X28-X27 -> 0 | Z28: =Z27 -> 135964 | AA28: =Z28-Z27 -> 0 | AB28: =SUM(Y28*$AB$2) -> 0 | AC28: =AC27 -> 1881 | AD28: =AC28-AC27 -> 0 | AE28: =AE27 -> 362296 | AF28: =AE28-AE27 -> 0 | AG28: =IF(AD28>0,AF28/AD28,0) -> 0 | AH28: =AF28+AA28 -> 0 | AI28: =SUM(AH28+V28) -> 0 | AJ28: =-tanks!AW29 -> 0 | AK28: =SUM(AJ28-AI28) -> 0 | AL28: =S28+L28+G28 -> 0 | AM28: =Y28+AD28 -> 0 | AN28: =AN27 -> 83 | AO28: =(AN28/100)*3000 -> 2490 | AP28: =AP27 -> 83 | AQ28: =(AP28/100)*3000 -> 2490 | AR28: =AR27 -> 82 | AS28: =(AR28/100)*3000 -> 2460 | AT28: =SUM(AO28+AQ28+AS28) -> 7440 | AU28: =AT27-AT28+AV28 -> 0 | AX28: =IF(AV28>0,AW28,AX27) -> 0.7
A29: =ELEC!C27 -> 44037 | B29: =B28 -> 171.3 | C29: =C28 -> 178 | D29: =C28-C29 -> 0 | E29: =D29*8.38 -> 0 | F29: =F28 -> 1633 | G29: =F29-F28 -> 0 | H29: =H28 -> 356674 | I29: =SUM(H29-H28) -> 0 | J29: =IF(G29>0,I29/G29,0) -> 0 | K29: =K28 -> 2077 | L29: =K29-K28 -> 0 | M29: =M28 -> 152390 | N29: =M29-M28 -> 0 | O29: =O28 -> 211.875 | P29: =P28 -> 1830 | Q29: =Q28 -> 155334 | R29: =Q29-Q28 -> 0 | S29: =SUM(P29-P28) -> 0 | T29: =SUM(S29*$T$2) -> 0 | U29: =SUM(G29+L29+S29) -> 0 | V29: =R29+N29+I29:I29 -> 0 | X29: =X28 -> 2418 | Y29: =X29-X28 -> 0 | Z29: =Z28 -> 135964 | AA29: =Z29-Z28 -> 0 | AB29: =SUM(Y29*$AB$2) -> 0 | AC29: =AC28 -> 1881 | AD29: =AC29-AC28 -> 0 | AE29: =AE28 -> 362296 | AF29: =AE29-AE28 -> 0 | AG29: =IF(AD29>0,AF29/AD29,0) -> 0 | AH29: =AF29+AA29 -> 0 | AI29: =SUM(AH29+V29) -> 0 | AJ29: =-tanks!AW30 -> 0 | AK29: =SUM(AJ29-AI29) -> 0 | AL29: =S29+L29+G29 -> 0 | AM29: =Y29+AD29 -> 0 | AN29: =AN28 -> 83 | AO29: =(AN29/100)*3000 -> 2490 | AP29: =AP28 -> 83 | AQ29: =(AP29/100)*3000 -> 2490 | AR29: =AR28 -> 82 | AS29: =(AR29/100)*3000 -> 2460 | AT29: =SUM(AO29+AQ29+AS29) -> 7440 | AU29: =AT28-AT29+AV29 -> 0 | AX29: =IF(AV29>0,AW29,AX28) -> 0.7
A30: =ELEC!C28 -> 44038 | B30: =B29 -> 171.3 | C30: =C29 -> 178 | D30: =C29-C30 -> 0 | E30: =D30*8.38 -> 0 | F30: =F29 -> 1633 | G30: =F30-F29 -> 0 | H30: =H29 -> 356674 | I30: =SUM(H30-H29) -> 0 | J30: =IF(G30>0,I30/G30,0) -> 0 | K30: =K29 -> 2077 | L30: =K30-K29 -> 0 | M30: =M29 -> 152390 | N30: =M30-M29 -> 0 | O30: =O29 -> 211.875 | P30: =P29 -> 1830 | Q30: =Q29 -> 155334 | R30: =Q30-Q29 -> 0 | S30: =SUM(P30-P29) -> 0 | T30: =SUM(S30*$T$2) -> 0 | U30: =SUM(G30+L30+S30) -> 0 | V30: =R30+N30+I30:I30 -> 0 | X30: =X29 -> 2418 | Y30: =X30-X29 -> 0 | Z30: =Z29 -> 135964 | AA30: =Z30-Z29 -> 0 | AB30: =SUM(Y30*$AB$2) -> 0 | AC30: =AC29 -> 1881 | AD30: =AC30-AC29 -> 0 | AE30: =AE29 -> 362296 | AF30: =AE30-AE29 -> 0 | AG30: =IF(AD30>0,AF30/AD30,0) -> 0 | AH30: =AF30+AA30 -> 0 | AI30: =SUM(AH30+V30) -> 0 | AJ30: =-tanks!AW31 -> 0 | AK30: =SUM(AJ30-AI30) -> 0 | AL30: =S30+L30+G30 -> 0 | AM30: =Y30+AD30 -> 0 | AN30: =AN29 -> 83 | AO30: =(AN30/100)*3000 -> 2490 | AP30: =AP29 -> 83 | AQ30: =(AP30/100)*3000 -> 2490 | AR30: =AR29 -> 82 | AS30: =(AR30/100)*3000 -> 2460 | AT30: =SUM(AO30+AQ30+AS30) -> 7440 | AU30: =AT29-AT30+AV30 -> 0 | AX30: =IF(AV30>0,AW30,AX29) -> 0.7
A31: =ELEC!C29 -> 44039 | B31: =B30 -> 171.3 | C31: =C30 -> 178 | D31: =C30-C31 -> 0 | E31: =D31*8.38 -> 0 | F31: =F30 -> 1633 | G31: =F31-F30 -> 0 | H31: =H30 -> 356674 | I31: =SUM(H31-H30) -> 0 | J31: =IF(G31>0,I31/G31,0) -> 0 | K31: =K30 -> 2077 | L31: =K31-K30 -> 0 | M31: =M30 -> 152390 | N31: =M31-M30 -> 0 | O31: =O30 -> 211.875 | P31: =P30 -> 1830 | Q31: =Q30 -> 155334 | R31: =Q31-Q30 -> 0 | S31: =SUM(P31-P30) -> 0 | T31: =SUM(S31*$T$2) -> 0 | U31: =SUM(G31+L31+S31) -> 0 | V31: =R31+N31+I31:I31 -> 0 | X31: =X30 -> 2418 | Y31: =X31-X30 -> 0 | Z31: =Z30 -> 135964 | AA31: =Z31-Z30 -> 0 | AB31: =SUM(Y31*$AB$2) -> 0 | AC31: =AC30 -> 1881 | AD31: =AC31-AC30 -> 0 | AE31: =AE30 -> 362296 | AF31: =AE31-AE30 -> 0 | AG31: =IF(AD31>0,AF31/AD31,0) -> 0 | AH31: =AF31+AA31 -> 0 | AI31: =SUM(AH31+V31) -> 0 | AJ31: =-tanks!AW32 -> 0 | AK31: =SUM(AJ31-AI31) -> 0 | AL31: =S31+L31+G31 -> 0 | AM31: =Y31+AD31 -> 0 | AN31: =AN30 -> 83 | AO31: =(AN31/100)*3000 -> 2490 | AP31: =AP30 -> 83 | AQ31: =(AP31/100)*3000 -> 2490 | AR31: =AR30 -> 82 | AS31: =(AR31/100)*3000 -> 2460 | AT31: =SUM(AO31+AQ31+AS31) -> 7440 | AU31: =AT30-AT31+AV31 -> 0 | AX31: =IF(AV31>0,AW31,AX30) -> 0.7
A32: =ELEC!C30 -> 44040 | B32: =B31 -> 171.3 | C32: =C31 -> 178 | D32: =C31-C32 -> 0 | E32: =D32*8.38 -> 0 | F32: =F31 -> 1633 | G32: =F32-F31 -> 0 | H32: =H31 -> 356674 | I32: =SUM(H32-H31) -> 0 | J32: =IF(G32>0,I32/G32,0) -> 0 | K32: =K31 -> 2077 | L32: =K32-K31 -> 0 | M32: =M31 -> 152390 | N32: =M32-M31 -> 0 | O32: =O31 -> 211.875 | P32: =P31 -> 1830 | Q32: =Q31 -> 155334 | R32: =Q32-Q31 -> 0 | S32: =SUM(P32-P31) -> 0 | T32: =SUM(S32*$T$2) -> 0 | U32: =SUM(G32+L32+S32) -> 0 | V32: =R32+N32+I32:I32 -> 0 | X32: =X31 -> 2418 | Y32: =X32-X31 -> 0 | Z32: =Z31 -> 135964 | AA32: =Z32-Z31 -> 0 | AB32: =SUM(Y32*$AB$2) -> 0 | AC32: =AC31 -> 1881 | AD32: =AC32-AC31 -> 0 | AE32: =AE31 -> 362296 | AF32: =AE32-AE31 -> 0 | AG32: =IF(AD32>0,AF32/AD32,0) -> 0 | AH32: =AF32+AA32 -> 0 | AI32: =SUM(AH32+V32) -> 0 | AJ32: =-tanks!AW33 -> 0 | AK32: =SUM(AJ32-AI32) -> 0 | AL32: =S32+L32+G32 -> 0 | AM32: =Y32+AD32 -> 0 | AN32: =AN31 -> 83 | AO32: =(AN32/100)*3000 -> 2490 | AP32: =AP31 -> 83 | AQ32: =(AP32/100)*3000 -> 2490 | AR32: =AR31 -> 82 | AS32: =(AR32/100)*3000 -> 2460 | AT32: =SUM(AO32+AQ32+AS32) -> 7440 | AU32: =AT31-AT32+AV32 -> 0 | AX32: =IF(AV32>0,AW32,AX31) -> 0.7
... A34: =ELEC!C32 -> 44042 | B34: =B33 -> 171.3 | C34: =C33 -> 178 | D34: =C33-C34 -> 0 | E34: =D34*8.38 -> 0 | F34: =F33 -> 1633 | G34: =F34-F33 -> 0 | H34: =H33 -> 356674 | I34: =SUM(H34-H33) -> 0 | J34: =IF(G34>0,I34/G34,0) -> 0 | K34: =K33 -> 2077 | L34: =K34-K33 -> 0 | M34: =M33 -> 152390 | N34: =M34-M33 -> 0 | O34: =O33 -> 211.875 | P34: =P33 -> 1830 | Q34: =Q33 -> 155334 | R34: =Q34-Q33 -> 0 | S34: =SUM(P34-P33) -> 0 | T34: =SUM(S34*$T$2) -> 0 | U34: =SUM(G34+L34+S34) -> 0 | V34: =R34+N34+I34:I34 -> 0 | X34: =X33 -> 2418 | Y34: =X34-X33 -> 0 | Z34: =Z33 -> 135964 | AA34: =Z34-Z33 -> 0 | AB34: =SUM(Y34*$AB$2) -> 0 | AC34: =AC33 -> 1881 | AD34: =AC34-AC33 -> 0 | AE34: =AE33 -> 362296 | AF34: =AE34-AE33 -> 0 | AG34: =IF(AD34>0,AF34/AD34,0) -> 0 | AH34: =AF34+AA34 -> 0 | AI34: =SUM(AH34+V34) -> 0 | AJ34: =-tanks!AW35 -> 0 | AK34: =SUM(AJ34-AI34) -> 0 | AL34: =S34+L34+G34 -> 0 | AM34: =Y34+AD34 -> 0 | AN34: =AN33 -> 83 | AO34: =(AN34/100)*3000 -> 2490 | AP34: =AP33 -> 83 | AQ34: =(AP34/100)*3000 -> 2490 | AR34: =AR33 -> 82 | AS34: =(AR34/100)*3000 -> 2460 | AT34: =SUM(AO34+AQ34+AS34) -> 7440 | AU34: =AT33-AT34+AV34 -> 0 | AX34: =IF(AV34>0,AW34,AX33) -> 0.7
A35: =ELEC!C33 -> 44043 | B35: =B34 -> 171.3 | C35: =C34 -> 178 | D35: =C34-C35 -> 0 | E35: =D35*8.38 -> 0 | F35: =F34 -> 1633 | G35: =F35-F34 -> 0 | H35: =H34 -> 356674 | I35: =SUM(H35-H34) -> 0 | J35: =IF(G35>0,I35/G35,0) -> 0 | K35: =K34 -> 2077 | L35: =K35-K34 -> 0 | M35: =M34 -> 152390 | N35: =M35-M34 -> 0 | O35: =O34 -> 211.875 | P35: =P34 -> 1830 | Q35: =Q34 -> 155334 | R35: =Q35-Q34 -> 0 | S35: =SUM(P35-P34) -> 0 | T35: =SUM(S35*$T$2) -> 0 | U35: =SUM(G35+L35+S35) -> 0 | V35: =R35+N35+I35:I35 -> 0 | X35: =X34 -> 2418 | Y35: =X35-X34 -> 0 | Z35: =Z34 -> 135964 | AA35: =Z35-Z34 -> 0 | AB35: =SUM(Y35*$AB$2) -> 0 | AC35: =AC34 -> 1881 | AD35: =AC35-AC34 -> 0 | AE35: =AE34 -> 362296 | AF35: =AE35-AE34 -> 0 | AG35: =IF(AD35>0,AF35/AD35,0) -> 0 | AH35: =AF35+AA35 -> 0 | AI35: =SUM(AH35+V35) -> 0 | AJ35: =-tanks!AW37 -> 0 | AK35: =SUM(AJ35-AI35) -> 0 | AL35: =S35+L35+G35 -> 0 | AM35: =Y35+AD35 -> 0 | AN35: =AN34 -> 83 | AO35: =(AN35/100)*3000 -> 2490 | AP35: =AP34 -> 83 | AQ35: =(AP35/100)*3000 -> 2490 | AR35: =AR34 -> 82 | AS35: =(AR35/100)*3000 -> 2460 | AT35: =SUM(AO35+AQ35+AS35) -> 7440 | AU35: =AT34-AT35+AV35 -> 0 | AX35: =IF(AV35>0,AW35,AX34) -> 0.7
J36: =SUM(J5:J34)/(COUNT(J5:J34)-COUNTIF(J5:J34,0)) -> 71.527778 | V36: =SUM(V5:V35) -> 4995 | AE36: . | AH36: =SUM(AH5:AH35) -> 1477.9 | AL36: =SUM(AL5:AL35) -> 62 | AM36: =SUM(AM5:AM35) -> 24 | AR36: Nb Delivery | AS36: =COUNT(AW5:AW34) -> 3 | AU36: =SUM(AU5:AU34) -> 2780 | AV36: =SUM(AV5:AV34) -> 3500 | AW36: =SUM(AW5:AW34)/AS36 -> 0.7
AH37: =AF37+AA37 -> 0 | AI37: =SUM(AI5:AI34) -> 6472.9
AH38: =AF38+AA38 -> 0 | AU38: =AU36*0.51 -> 1417.8 | AV38: =AV36/0.51 -> 6862.7451 | AW38: =SUM(AW5:AW34)/AS36 -> 0.7
AV39: =AV36*0.51 -> 1785

Sheet WATER
D1: =SUM(G21:G35) -> 9051615 | AR1: Entrance | AT1: Tank 1 | AV1: Tank 2
AR2: Level | AW2: Quantity CM3 | AZ2: Var
A3: Date | B3: Truck | C3: Truck M3/day | D3: N0. Trucks | F3: REQ. # of trucks | G3: City | H3: City/day | I3: Total water delivery | K3: SW | L3: Cosum SW/day | M3: RO Guest/ Liter | O3: RO K&L/ Liter | Q3: TOTAL RO Production | R3: RO 1 RH | S3: RO 2 RH | T3: RO water counter | U3: RO Cons m3 | V3: Steam Boiler | W3: Steam Boiler/day | X3: Softener Guest | Y3: Guest Sotf/day | Z3: Softener K&L | AA3: K&L Soft/Day | AB3: Fire Tank Level | AC3: Fire Tank Counter | AE3: Laundry Hot Water Counter | AF3: Hot Water Cons/day | AG3: Laundry Cold Water Counter | AH3: Cold Water Cons/day | AI3: Laundry Water Total Cons | AJ3: K&L Sotf/day | AK3: Guest / day | AL3: K&L /day | AM3: Avg Outside Temp | AN3: Banquet Activity | AR3: Date | AT3: MainI | AV3: Kitchen and Laundry | AX3: Guest | AY3: Main Tank | AZ3: Kitchen and Laundry | BA3: Guest | BB3: Kitchen and Laundry | BC3: Main | BD3: Guest | BE3: Total VAR | BF3: Hotel Consumption
E4: 1.66 | AN4: Ball R | AO4: Meeting | AP4: outlet | AT4: 180 | AV4: 220 | AX4: 580 | AY4: =SUM(AT4) -> 180 | AZ4: =SUM(AV4) -> 220 | BA4: =SUM(AX4) -> 580
A5: =[1]WATER!$A$35 -> 44012 | B5: =[1]WATER!B35 -> 108535 | C5: =[1]WATER!C35 -> 0 | D5: =[1]WATER!D35 -> 0 | E5: =[1]WATER!E35 -> 250 | F5: =[1]WATER!F35 -> 0 | G5: =[1]WATER!G35 -> 601246 | H5: =[1]WATER!H35 -> 413 | I5: =[1]WATER!I35 -> 413 | ... BG5: =[1]WATER!BG35 -> 180.2
A6: =ELEC!C3 -> 44013 | B6: 108535 | C6: =B6-B5 -> 0 | D6: =C6/27 -> 0 | E6: =SUM((C6*$E$4)+(7500/'EDl log'!$A$39)) -> 241.93548 | G6: 601246 | H6: =G6-G5 -> 0 | I6: =C6+H6 -> 0 | J6: =IF(I6>0,E6/I6,0) -> 0 | K6: ='Swimming Pool quality check '!H6 -> 6366 | L6: 0 | M6: =M5 -> 457.44 | N6: =SUM(M6-M5) -> 0 | O6: =O5 -> 529.52 | P6: =SUM(O6-O5) -> 0 | Q6: =P6+N6 -> 0 | T6: 4902 | U6: =SUM(T6-T5) -> 3 | V6: 410 | W6: =+V6-V5 -> 0 | X6: 144684 | Y6: =SUM(X6-X5) -> 115 | Z6: 95367 | AA6: =Z6-Z5 -> 10 | AB6: =AB5 -> 259 | AC6: =AC5 -> 670 | AD6: 0 | AE6: =AE5 -> 162.18 | AF6: =AE6-AE5 -> 0 | AG6: =AG5 -> 1697.9 | AH6: =AG6-AG5 -> 0 | AI6: =AF6+AH6 -> 0 | AJ6: =+Z6-Z5 -> 10 | AK6: =SUM(Y6-L6) -> 115 | AL6: =SUM(AJ6-W6) -> 10 | AM6: ='General information '!D6 -> 26 | AN6: ='General information '!H6 -> 0 | AP6: ='General information '!J6 -> 196 | AR6: =A6 -> 44013 | AS6: =AS5 -> 0.9 | AT6: 50 | AU6: =AU5 -> 1.1 | AV6: 95 | AW6: 2.9 | AX6: 110 | AY6: =AS6*AT6 -> 45 | AZ6: =AU6*AV6 -> 104.5 | BA6: =AW6*AX6 -> 319 | BB6: =AY6-AY5 -> -90 | BC6: =AZ6-AZ5 -> -5.5 | BD6: =BA6-BA5 -> 20.3 | BE6: =SUM(BB6:BD6) -> -75.2 | BF6: =SUM(I6-BE6) -> 75.2 | BG6: =SUM(I6-BF6) -> -75.2
A7: =ELEC!C4 -> 44014 | B7: =B6 -> 108535 | C7: =B7-B6 -> 0 | D7: =C7/27 -> 0 | E7: =SUM((C7*$E$4)+(7500/'EDl log'!$A$39)) -> 241.93548 | G7: 601639 | H7: =G7-G6 -> 393 | I7: =C7+H7 -> 393 | J7: =IF(I7>0,E7/I7,0) -> 0.61561192 | K7: ='Swimming Pool quality check '!H7 -> 6366 | L7: =K7-K6 -> 0 | M7: =M6 -> 457.44 | N7: =SUM(M7-M6) -> 0 | O7: =O6 -> 529.52 | P7: =SUM(O7-O6) -> 0 | Q7: =P7+N7 -> 0 | T7: 4906 | U7: =SUM(T7-T6) -> 4 | V7: =V6 -> 410 | W7: =+V7-V6 -> 0 | X7: 144753 | Y7: =SUM(X7-X6) -> 69 | Z7: 95415 | AA7: =Z7-Z6 -> 48 | AB7: =AB6 -> 259 | AC7: =AC6 -> 670 | AD7: =AC7-AC6 -> 0 | AE7: 163.58 | AF7: =AE7-AE6 -> 1.4 | AG7: 1716.5 | AH7: =AG7-AG6 -> 18.6 | AI7: =AF7+AH7 -> 20 | AJ7: =+Z7-Z6 -> 48 | AK7: =SUM(Y7-L7) -> 69 | AL7: =SUM(AJ7-W7) -> 48 | AM7: ='General information '!D7 -> 26 | AN7: ='General information '!H7 -> 0 | AP7: ='General information '!J7 -> 262 | AR7: =A7 -> 44014 | AS7: =AS6 -> 0.9 | AT7: 170 | AU7: =AU6 -> 1.1 | AV7: 100 | AW7: 2.9 | AX7: 113 | AY7: =AS7*AT7 -> 153 | AZ7: =AU7*AV7 -> 110 | BA7: =AW7*AX7 -> 327.7 | BB7: =AY7-AY6 -> 108 | BC7: =AZ7-AZ6 -> 5.5 | BD7: =BA7-BA6 -> 8.7 | BE7: =SUM(BB7:BD7) -> 122.2 | BF7: =SUM(I7-BE7) -> 270.8 | BG7: =SUM(I7-BF7) -> 122.2
A8: =ELEC!C5 -> 44015 | B8: =B7 -> 108535 | C8: =B8-B7 -> 0 | D8: =C8/27 -> 0 | E8: =SUM((C8*$E$4)+(7500/'EDl log'!$A$39)) -> 241.93548 | G8: =G7 -> 601639 | H8: =G8-G7 -> 0 | I8: =C8+H8 -> 0 | J8: =IF(I8>0,E8/I8,0) -> 0 | K8: ='Swimming Pool quality check '!H8 -> 6368 | L8: =K8-K7 -> 2 | M8: =M7 -> 457.44 | N8: =SUM(M8-M7) -> 0 | O8: =O7 -> 529.52 | P8: =SUM(O8-O7) -> 0 | Q8: =P8+N8 -> 0 | T8: 4908 | U8: =SUM(T8-T7) -> 2 | V8: 411 | W8: =+V8-V7 -> 1 | X8: 144801 | Y8: =SUM(X8-X7) -> 48 | Z8: 95467 | AA8: =Z8-Z7 -> 52 | AB8: =AB7 -> 259 | AC8: =AC7 -> 670 | AD8: =AC8-AC7 -> 0 | AE8: =AE7 -> 163.58 | AF8: =AE8-AE7 -> 0 | AG8: 1718 | AH8: =AG8-AG7 -> 1.5 | AI8: =AF8+AH8 -> 1.5 | AJ8: =+Z8-Z7 -> 52 | AK8: =SUM(Y8-L8) -> 46 | AL8: =SUM(AJ8-W8) -> 51 | AM8: ='General information '!D8 -> 26.5 | AN8: ='General information '!H8 -> 0 | AP8: ='General information '!J8 -> 263 | AR8: =A8 -> 44015 | AS8: =AS7 -> 0.9 | AT8: 59 | AU8: 1.1 | AV8: 121 | AW8: 2.9 | AX8: 117 | AY8: =AS8*AT8 -> 53.1 | AZ8: =AU8*AV8 -> 133.1 | BA8: =AW8*AX8 -> 339.3 | BB8: =AY8-AY7 -> -99.9 | BC8: =AZ8-AZ7 -> 23.1 | BD8: =BA8-BA7 -> 11.6 | BE8: =SUM(BB8:BD8) -> -65.2 | BF8: =SUM(I8-BE8) -> 65.2 | BG8: =SUM(I8-BF8) -> -65.2
A9: =ELEC!C6 -> 44016 | B9: 108535 | C9: =B9-B8 -> 0 | D9: =C9/27 -> 0 | E9: =SUM((C9*$E$4)+(7500/'EDl log'!$A$39)) -> 241.93548 | G9: 602202 | H9: =G9-G8 -> 563 | I9: =C9+H9 -> 563 | J9: =IF(I9>0,E9/I9,0) -> 0.42972555 | K9: ='Swimming Pool quality check '!H9 -> 6378 | L9: =K9-K8 -> 10 | M9: =M8 -> 457.44 | N9: =SUM(M9-M8) -> 0 | O9: =O8 -> 529.52 | P9: =SUM(O9-O8) -> 0 | Q9: =P9+N9 -> 0 | T9: 4911 | U9: =SUM(T9-T8) -> 3 | V9: =V8 -> 411 | W9: =+V9-V8 -> 0 | X9: 144981 | Y9: =SUM(X9-X8) -> 180 | Z9: 95540 | AA9: =Z9-Z8 -> 73 | AB9: =AB8 -> 259 | AC9: =AC8 -> 670 | AD9: =AC9-AC8 -> 0 | AE9: 163.64 | AF9: =AE9-AE8 -> 0.06 | AG9: 1721.76 | AH9: =AG9-AG8 -> 3.76 | AI9: =AF9+AH9 -> 3.82 | AJ9: =+Z9-Z8 -> 73 | AK9: =SUM(Y9-L9) -> 170 | AL9: =SUM(AJ9-W9) -> 73 | AM9: ='General information '!D9 -> 26 | AN9: ='General information '!H9 -> 0 | AP9: ='General information '!J9 -> 258 | AR9: =A9 -> 44016 | AS9: =AS8 -> 0.9 | AT9: 152 | AU9: =AU8 -> 1.1 | AV9: 170 | AW9: 2.9 | AX9: 140 | AY9: =AS9*AT9 -> 136.8 | AZ9: =AU9*AV9 -> 187 | BA9: =AW9*AX9 -> 406 | BB9: =AY9-AY8 -> 83.7 | BC9: =AZ9-AZ8 -> 53.9 | BD9: =BA9-BA8 -> 66.7 | BE9: =SUM(BB9:BD9) -> 204.3 | BF9: =SUM(I9-BE9) -> 358.7 | BG9: =SUM(I9-BF9) -> 204.3
A10: =ELEC!C7 -> 44017 | B10: 108535 | C10: =B10-B9 -> 0 | D10: =C10/27 -> 0 | E10: =SUM((C10*$E$4)+(7500/'EDl log'!$A$39)) -> 241.93548 | G10: 602247 | H10: =G10-G9 -> 45 | I10: =C10+H10 -> 45 | J10: =IF(I10>0,E10/I10,0) -> 5.3763441 | K10: ='Swimming Pool quality check '!H10 -> 6386 | L10: =K10-K9 -> 8 | M10: =M9 -> 457.44 | N10: =SUM(M10-M9) -> 0 | O10: =O9 -> 529.52 | P10: =SUM(O10-O9) -> 0 | Q10: =P10+N10 -> 0 | T10: 4915 | U10: =SUM(T10-T9) -> 4 | V10: 411 | W10: =+V10-V9 -> 0 | X10: 144983 | Y10: =SUM(X10-X9) -> 2 | Z10: 95541 | AA10: =Z10-Z9 -> 1 | AB10: =AB9 -> 259 | AC10: =AC9 -> 670 | AD10: =AC10-AC9 -> 0 | AE10: 163.77 | AF10: =AE10-AE9 -> 0.13 | AG10: 1724.45 | AH10: =AG10-AG9 -> 2.69 | AI10: =AF10+AH10 -> 2.82 | AJ10: =+Z10-Z9 -> 1 | AK10: =SUM(Y10-L10) -> -6 | AL10: =SUM(AJ10-W10) -> 1 | AM10: ='General information '!D10 -> 28 | AN10: ='General information '!H10 -> 0 | AP10: ='General information '!J10 -> 801 | AR10: =A10 -> 44017 | AS10: =AS9 -> 0.9 | AT10: 185 | AU10: =AU9 -> 1.1 | AV10: 143 | AW10: 2.9 | AX10: 134 | AY10: =AS10*AT10 -> 166.5 | AZ10: =AU10*AV10 -> 157.3 | BA10: =AW10*AX10 -> 388.6 | BB10: =AY10-AY9 -> 29.7 | BC10: =AZ10-AZ9 -> -29.7 | BD10: =BA10-BA9 -> -17.4 | BE10: =SUM(BB10:BD10) -> -17.4 | BF10: =SUM(I10-BE10) -> 62.4 | BG10: =SUM(I10-BF10) -> -17.4
A11: =ELEC!C8 -> 44018 | B11: 108535 | C11: =B11-B10 -> 0 | D11: =C11/27 -> 0 | E11: =SUM((C11*$E$4)+(7500/'EDl log'!$A$39)) -> 241.93548 | G11: 602474 | H11: =G11-G10 -> 227 | I11: =C11+H11 -> 227 | J11: =IF(I11>0,E11/I11,0) -> 1.0657951 | K11: ='Swimming Pool quality check '!H11 -> 6392 | L11: =K11-K10 -> 6 | M11: =M10 -> 457.44 | N11: =SUM(M11-M10) -> 0 | O11: =O10 -> 529.52 | P11: =SUM(O11-O10) -> 0 | Q11: =SUM(P11+N11) -> 0 | T11: 4918 | U11: =SUM(T11-T10) -> 3 | V11: 412 | W11: =+V11-V10 -> 1 | X11: 145093 | Y11: =SUM(X11-X10) -> 110 | Z11: 95584 | AA11: =Z11-Z10 -> 43 | AB11: 259 | AC11: 670 | AD11: =AC11-AC10 -> 0 | AE11: 164.76 | AF11: =AE11-AE10 -> 0.99 | AG11: 1736.06 | AH11: =AG11-AG10 -> 11.61 | AI11: =AF11+AH11 -> 12.6 | AJ11: =+Z11-Z10 -> 43 | AK11: =SUM(Y11-L11) -> 104 | AL11: =SUM(AJ11-W11) -> 42 | AM11: ='General information '!D11 -> 27 | AN11: ='General information '!H11 -> 0 | AP11: ='General information '!J11 -> 230 | AR11: =A11 -> 44018 | AS11: =AS10 -> 0.9 | AT11: 181 | AU11: =AU10 -> 1.1 | AV11: 152 | AW11: 2.9 | AX11: 148 | AY11: =AS11*AT11 -> 162.9 | AZ11: =AU11*AV11 -> 167.2 | BA11: =AW11*AX11 -> 429.2 | BB11: =AY11-AY10 -> -3.6 | BC11: =AZ11-AZ10 -> 9.9 | BD11: =BA11-BA10 -> 40.6 | BE11: =SUM(BB11:BD11) -> 46.9 | BF11: =SUM(I11-BE11) -> 180.1 | BG11: =SUM(I11-BF11) -> 46.9
A12: =ELEC!C9 -> 44019 | B12: 108535 | C12: =B12-B11 -> 0 | D12: =C12/27 -> 0 | E12: =SUM((C12*$E$4)+(7500/'EDl log'!$A$39)) -> 241.93548 | G12: 602675 | H12: =G12-G11 -> 201 | I12: =C12+H12 -> 201 | J12: =IF(I12>0,E12/I12,0) -> 1.2036591 | K12: ='Swimming Pool quality check '!H12 -> 6400 | L12: =K12-K11 -> 8 | M12: =M11 -> 457.44 | N12: =SUM(M12-M11) -> 0 | O12: =O11 -> 529.52 | P12: =SUM(O12-O11) -> 0 | Q12: =SUM(P12+N12) -> 0 | T12: 4925 | U12: =SUM(T12-T11) -> 7 | V12: 413 | W12: =+V12-V11 -> 1 | X12: 145204 | Y12: =SUM(X12-X11) -> 111 | Z12: 95637 | AA12: =Z12-Z11 -> 53 | AB12: =AB11 -> 259 | AC12: =AC11 -> 670 | AD12: =AC12-AC11 -> 0 | AE12: 166.34 | AF12: =AE12-AE11 -> 1.58 | AG12: 1753.68 | AH12: =AG12-AG11 -> 17.62 | AI12: =AF12+AH12 -> 19.2 | AJ12: =+Z12-Z11 -> 53 | AK12: =SUM(Y12-L12) -> 103 | AL12: =SUM(AJ12-W12) -> 52 | AM12: ='General information '!D12 -> 26 | AN12: ='General information '!H12 -> 0 | AP12: ='General information '!J12 -> 268 | AR12: =A12 -> 44019 | AS12: =AS11 -> 0.9 | AT12: 162 | AU12: =AU11 -> 1.1 | AV12: 135 | AW12: 2.9 | AX12: 133 | AY12: =AS12*AT12 -> 145.8 | AZ12: =AU12*AV12 -> 148.5 | BA12: =AW12*AX12 -> 385.7 | BB12: =AY12-AY11 -> -17.1 | BC12: =AZ12-AZ11 -> -18.7 | BD12: =BA12-BA11 -> -43.5 | BE12: =SUM(BB12:BD12) -> -79.3 | BF12: =SUM(I12-BE12) -> 280.3 | BG12: =SUM(I12-BF12) -> -79.3
A13: =ELEC!C10 -> 44020 | B13: 108535 | C13: =B13-B12 -> 0 | D13: =C13/27 -> 0 | E13: =SUM((C13*$E$4)+(7500/'EDl log'!$A$39)) -> 241.93548 | G13: 602675 | H13: =G13-G12 -> 0 | I13: =C13+H13 -> 0 | J13: =IF(I13>0,E13/I13,0) -> 0 | K13: ='Swimming Pool quality check '!H13 -> 6405 | L13: =K13-K12 -> 5 | M13: =M12 -> 457.44 | N13: =SUM(M13-M12) -> 0 | O13: =O12 -> 529.52 | P13: =SUM(O13-O12) -> 0 | Q13: =SUM(P13+N13) -> 0 | T13: 4929 | U13: =SUM(T13-T12) -> 4 | V13: 413 | W13: =+V13-V12 -> 0 | X13: 145204 | Y13: =SUM(X13-X12) -> 0 | Z13: 95637 | AA13: =Z13-Z12 -> 0 | AB13: 259 | AC13: =AC12 -> 670 | AD13: =AC13-AC12 -> 0 | AE13: =AE12 -> 166.34 | AF13: =AE13-AE12 -> 0 | AG13: =AG12 -> 1753.68 | AH13: =AG13-AG12 -> 0 | AI13: =AF13+AH13 -> 0 | AJ13: =+Z13-Z12 -> 0 | AK13: =SUM(Y13-L13) -> -5 | AL13: =SUM(AJ13-W13) -> 0 | AM13: ='General information '!D13 -> 26 | AN13: ='General information '!J13 -> 336 | AP13: ='General information '!J13 -> 336 | AR13: =A13 -> 44020 | AS13: =AS12 -> 0.9 | AT13: 127 | AU13: =AU12 -> 1.1 | AV13: 149 | AW13: 2.9 | AX13: 145 | AY13: =AS13*AT13 -> 114.3 | AZ13: =AU13*AV13 -> 163.9 | BA13: =AW13*AX13 -> 420.5 | BB13: =AY13-AY12 -> -31.5 | BC13: =AZ13-AZ12 -> 15.4 | BD13: =BA13-BA12 -> 34.8 | BE13: =SUM(BB13:BD13) -> 18.7 | BF13: =SUM(I13-BE13) -> -18.7 | BG13: =SUM(I13-BF13) -> 18.7
A14: =ELEC!C11 -> 44021 | B14: =B13 -> 108535 | C14: =B14-B13 -> 0 | D14: =C14/27 -> 0 | E14: =SUM((C14*$E$4)+(7500/'EDl log'!$A$39)) -> 241.93548 | G14: =G13 -> 602675 | H14: =G14-G13 -> 0 | I14: =C14+H14 -> 0 | J14: =IF(I14>0,E14/I14,0) -> 0 | K14: ='Swimming Pool quality check '!H14 -> 6412 | L14: =K14-K13 -> 7 | M14: =M13 -> 457.44 | N14: =SUM(M14-M13) -> 0 | O14: =O13 -> 529.52 | P14: =SUM(O14-O13) -> 0 | Q14: =SUM(P14+N14) -> 0 | T14: =T13 -> 4929 | U14: =SUM(T14-T13) -> 0 | V14: =V13 -> 413 | W14: =+V14-V13 -> 0 | X14: =X13 -> 145204 | Y14: =SUM(X14-X13) -> 0 | Z14: 95637 | AA14: =Z14-Z13 -> 0 | AB14: =AB13 -> 259 | AC14: =AC13 -> 670 | AD14: =AC14-AC13 -> 0 | AE14: 166.34 | AF14: =AE14-AE13 -> 0 | AG14: 1757.69 | AH14: =AG14-AG13 -> 4.01 | AI14: =AF14+AH14 -> 4.01 | AJ14: =+Z14-Z13 -> 0 | AK14: =SUM(Y14-L14) -> -7 | AL14: =SUM(AJ14-W14) -> 0 | AM14: ='General information '!D14 -> 26 | AN14: ='General information '!H14 -> 0 | AP14: ='General information '!J14 -> 375 | AR14: =A14 -> 44021 | AS14: =AS13 -> 0.9 | AT14: 127 | AU14: =AU13 -> 1.1 | AV14: 128 | AW14: 2.9 | AX14: 128 | AY14: =AS14*AT14 -> 114.3 | AZ14: =AU14*AV14 -> 140.8 | BA14: =AW14*AX14 -> 371.2 | BB14: =AY14-AY13 -> 0 | BC14: =AZ14-AZ13 -> -23.1 | BD14: =BA14-BA13 -> -49.3 | BE14: =SUM(BB14:BD14) -> -72.4 | BF14: =SUM(I14-BE14) -> 72.4 | BG14: =SUM(I14-BF14) -> -72.4
A15: =ELEC!C12 -> 44022 | B15: 108535 | C15: =B15-B14 -> 0 | D15: =C15/27 -> 0 | E15: =SUM((C15*$E$4)+(7500/'EDl log'!$A$39)) -> 241.93548 | G15: 602787 | H15: =G15-G14 -> 112 | I15: =C15+H15 -> 112 | J15: =IF(I15>0,E15/I15,0) -> 2.1601382 | K15: ='Swimming Pool quality check '!H15 -> 6419 | L15: =K15-K14 -> 7 | M15: =M14 -> 457.44 | N15: =SUM(M15-M14) -> 0 | O15: =O14 -> 529.52 | P15: =SUM(O15-O14) -> 0 | Q15: =SUM(P15+N15) -> 0 | T15: 4932 | U15: =SUM(T15-T14) -> 3 | V15: 413 | W15: =+V15-V14 -> 0 | X15: 145295 | Y15: =SUM(X15-X14) -> 91 | Z15: 95661 | AA15: =Z15-Z14 -> 24 | AB15: =AB14 -> 259 | AC15: =AC14 -> 670 | AD15: =AC15-AC14 -> 0 | AE15: 166.96 | AF15: =AE15-AE14 -> 0.62 | AG15: 1762.96 | AH15: =AG15-AG14 -> 5.27 | AI15: =AF15+AH15 -> 5.89 | AJ15: =+Z15-Z14 -> 24 | AK15: =SUM(Y15-L15) -> 84 | AL15: =SUM(AJ15-W15) -> 24 | AM15: ='General information '!D15 -> 26 | AN15: ='General information '!H15 -> 0 | AP15: ='General information '!J15 -> 329 | AR15: =A15 -> 44022 | AS15: =AS14 -> 0.9 | AT15: 70 | AU15: =AU14 -> 1.1 | AV15: 127 | AW15: 2.9 | AX15: 139 | AY15: =AS15*AT15 -> 63 | AZ15: =AU15*AV15 -> 139.7 | BA15: =AW15*AX15 -> 403.1 | BB15: =AY15-AY14 -> -51.3 | BC15: =AZ15-AZ14 -> -1.1 | BD15: =BA15-BA14 -> 31.9 | BE15: =SUM(BB15:BD15) -> -20.5 | BF15: =SUM(I15-BE15) -> 132.5 | BG15: =SUM(I15-BF15) -> -20.5
A16: =ELEC!C13 -> 44023 | B16: 108535 | C16: =B16-B15 -> 0 | D16: =C16/27 -> 0 | E16: =SUM((C16*$E$4)+(7500/'EDl log'!$A$39)) -> 241.93548 | G16: =G15 -> 602787 | H16: =G16-G15 -> 0 | I16: =C16+H16 -> 0 | J16: =IF(I16>0,E16/I16,0) -> 0 | K16: ='Swimming Pool quality check '!H16 -> 6423 | L16: =K16-K15 -> 4 | M16: =M15 -> 457.44 | N16: =SUM(M16-M15) -> 0 | O16: =O15 -> 529.52 | P16: =SUM(O16-O15) -> 0 | Q16: =SUM(P16+N16) -> 0 | T16: 4935 | U16: =SUM(T16-T15) -> 3 | V16: =V15 -> 413 | W16: =+V16-V15 -> 0 | X16: 145295 | Y16: =SUM(X16-X15) -> 0 | Z16: 95661 | AA16: =Z16-Z15 -> 0 | AB16: 258 | AC16: =AC15 -> 670 | AD16: =AC16-AC15 -> 0 | AE16: 168.16 | AF16: =AE16-AE15 -> 1.2 | AG16: 1774.6 | AH16: =AG16-AG15 -> 11.64 | AI16: =AF16+AH16 -> 12.84 | AJ16: =+Z16-Z15 -> 0 | AK16: =SUM(Y16-L16) -> -4 | AL16: =SUM(AJ16-W16) -> 0 | AM16: ='General information '!D16 -> 28 | AN16: ='General information '!H16 -> 0 | AP16: ='General information '!J16 -> 323 | AR16: =A16 -> 44023 | AS16: =AS15 -> 0.9 | AT16: 53 | AU16: =AU15 -> 1.1 | AV16: 101 | AW16: 2.9 | AX16: 124 | AY16: =AS16*AT16 -> 47.7 | AZ16: =AU16*AV16 -> 111.1 | BA16: =AW16*AX16 -> 359.6 | BB16: =AY16-AY15 -> -15.3 | BC16: =AZ16-AZ15 -> -28.6 | BD16: =BA16-BA15 -> -43.5 | BE16: =SUM(BB16:BD16) -> -87.4 | BF16: =SUM(I16-BE16) -> 87.4 | BG16: =SUM(I16-BF16) -> -87.4
A17: =ELEC!C14 -> 44024 | B17: 108535 | C17: =B17-B16 -> 0 | D17: =C17/27 -> 0 | E17: =SUM((C17*$E$4)+(7500/'EDl log'!$A$39)) -> 241.93548 | G17: 603058 | H17: =G17-G16 -> 271 | I17: =C17+H17 -> 271 | J17: =IF(I17>0,E17/I17,0) -> 0.89275086 | K17: ='Swimming Pool quality check '!H17 -> 6434 | L17: =K17-K16 -> 11 | M17: =M16 -> 457.44 | N17: =SUM(M17-M16) -> 0 | O17: =O16 -> 529.52 | P17: =SUM(O17-O16) -> 0 | Q17: =SUM(P17+N17) -> 0 | T17: 4938 | U17: =SUM(T17-T16) -> 3 | V17: 413 | W17: =+V17-V16 -> 0 | X17: 145337 | Y17: =SUM(X17-X16) -> 42 | Z17: 95727 | AA17: =Z17-Z16 -> 66 | AB17: 258 | AC17: 670 | AD17: =AC17-AC16 -> 0 | AE17: =AE16 -> 168.16 | AF17: =AE17-AE16 -> 0 | AG17: 1778.62 | AH17: =AG17-AG16 -> 4.02 | AI17: =AF17+AH17 -> 4.02 | AJ17: =+Z17-Z16 -> 66 | AK17: =SUM(Y17-L17) -> 31 | AL17: =SUM(AJ17-W17) -> 66 | AM17: ='General information '!D17 -> 26 | AN17: ='General information '!H17 -> 0 | AP17: ='General information '!J17 -> 357 | AR17: =A17 -> 44024 | AS17: =AS16 -> 0.9 | AT17: 117 | AU17: =AU16 -> 1.1 | AV17: 122 | AW17: 2.9 | AX17: 122 | AY17: =AS17*AT17 -> 105.3 | AZ17: =AU17*AV17 -> 134.2 | BA17: =AW17*AX17 -> 353.8 | BB17: =AY17-AY16 -> 57.6 | BC17: =AZ17-AZ16 -> 23.1 | BD17: =BA17-BA16 -> -5.8 | BE17: =SUM(BB17:BD17) -> 74.9 | BF17: =SUM(I17-BE17) -> 196.1 | BG17: =SUM(I17-BF17) -> 74.9
A18: =ELEC!C15 -> 44025 | B18: 108535 | C18: =B18-B17 -> 0 | D18: =C18/27 -> 0 | E18: =SUM((C18*$E$4)+(7500/'EDl log'!$A$39)) -> 241.93548 | G18: 603058 | H18: =G18-G17 -> 0 | I18: =C18+H18 -> 0 | J18: =IF(I18>0,E18/I18,0) -> 0 | K18: ='Swimming Pool quality check '!H18 -> 6438 | L18: =K18-K17 -> 4 | M18: =M17 -> 457.44 | N18: =SUM(M18-M17) -> 0 | O18: =O17 -> 529.52 | P18: =SUM(O18-O17) -> 0 | Q18: =SUM(P18+N18) -> 0 | T18: 4942 | U18: =SUM(T18-T17) -> 4 | V18: 413 | W18: =+V18-V17 -> 0 | X18: 145340 | Y18: =SUM(X18-X17) -> 3 | Z18: 95727 | AA18: =Z18-Z17 -> 0 | AB18: =AB17 -> 258 | AC18: =AC17 -> 670 | AD18: =AC18-AC17 -> 0 | AE18: 169.11 | AF18: =AE18-AE17 -> 0.95 | AG18: 1791.61 | AH18: =AG18-AG17 -> 12.99 | AI18: =AF18+AH18 -> 13.94 | AJ18: =+Z18-Z17 -> 0 | AK18: =SUM(Y18-L18) -> -1 | AL18: =SUM(AJ18-W18) -> 0 | AM18: ='General information '!D18 -> 26.5 | AN18: ='General information '!H18 -> 0 | AP18: ='General information '!J18 -> 297 | AR18: =A18 -> 44025 | AS18: =AS17 -> 0.9 | AT18: 112 | AU18: =AU17 -> 1.1 | AV18: 110 | AW18: 2.9 | AX18: 108 | AY18: =AS18*AT18 -> 100.8 | AZ18: =AU18*AV18 -> 121 | BA18: =AW18*AX18 -> 313.2 | BB18: =AY18-AY17 -> -4.5 | BC18: =AZ18-AZ17 -> -13.2 | BD18: =BA18-BA17 -> -40.6 | BE18: =SUM(BB18:BD18) -> -58.3 | BF18: =SUM(I18-BE18) -> 58.3 | BG18: =SUM(I18-BF18) -> -58.3
A19: =ELEC!C16 -> 44026 | B19: 108535 | C19: =B19-B18 -> 0 | D19: =C19/27 -> 0 | E19: =SUM((C19*$E$4)+(7500/'EDl log'!$A$39)) -> 241.93548 | G19: 603282 | H19: =G19-G18 -> 224 | I19: =C19+H19 -> 224 | J19: =IF(I19>0,E19/I19,0) -> 1.0800691 | K19: ='Swimming Pool quality check '!H19 -> 6443 | L19: =K19-K18 -> 5 | M19: =M18 -> 457.44 | N19: =SUM(M19-M18) -> 0 | O19: =O18 -> 529.52 | P19: =SUM(O19-O18) -> 0 | Q19: =SUM(P19+N19) -> 0 | T19: 4945 | U19: =SUM(T19-T18) -> 3 | V19: 413 | W19: =+V19-V18 -> 0 | X19: 145490 | Y19: =SUM(X19-X18) -> 150 | Z19: 95769 | AA19: =Z19-Z18 -> 42 | AB19: =AB18 -> 258 | AC19: =AC18 -> 670 | AD19: =AC19-AC18 -> 0 | AE19: 169.11 | AF19: =AE19-AE18 -> 0 | AG19: 1793.62 | AH19: =AG19-AG18 -> 2.01 | AI19: =AF19+AH19 -> 2.01 | AJ19: =+Z19-Z18 -> 42 | AK19: =SUM(Y19-L19) -> 145 | AL19: =SUM(AJ19-W19) -> 42 | AM19: ='General information '!D19 -> 27.5 | AN19: ='General information '!H19 -> 0 | AP19: ='General information '!J19 -> 332 | AR19: =A19 -> 44026 | AS19: =AS18 -> 0.9 | AT19: 53 | AU19: =AU18 -> 1.1 | AV19: 114 | AW19: 2.9 | AX19: 130 | AY19: =AS19*AT19 -> 47.7 | AZ19: =AU19*AV19 -> 125.4 | BA19: =AW19*AX19 -> 377 | BB19: =AY19-AY18 -> -53.1 | BC19: =AZ19-AZ18 -> 4.4 | BD19: =BA19-BA18 -> 63.8 | BE19: =SUM(BB19:BD19) -> 15.1 | BF19: =SUM(I19-BE19) -> 208.9 | BG19: =SUM(I19-BF19) -> 15.1
A20: =ELEC!C17 -> 44027 | B20: 108535 | C20: =B20-B19 -> 0 | D20: =C20/27 -> 0 | E20: =SUM((C20*$E$4)+(7500/'EDl log'!$A$39)) -> 241.93548 | G20: 603282 | H20: =G20-G19 -> 0 | I20: =C20+H20 -> 0 | J20: =IF(I20>0,E20/I20,0) -> 0 | K20: ='Swimming Pool quality check '!H20 -> 6443 | L20: =K20-K19 -> 0 | M20: =M19 -> 457.44 | N20: =SUM(M20-M19) -> 0 | O20: =O19 -> 529.52 | P20: =SUM(O20-O19) -> 0 | Q20: =SUM(P20+N20) -> 0 | T20: 4949 | U20: =SUM(T20-T19) -> 4 | V20: 415 | W20: =+V20-V19 -> 2 | X20: 145527 | Y20: =SUM(X20-X19) -> 37 | Z20: 95780 | AA20: =Z20-Z19 -> 11 | AB20: =AB19 -> 258 | AC20: =AC19 -> 670 | AD20: =AC20-AC19 -> 0 | AE20: 171.25 | AF20: =AE20-AE19 -> 2.14 | AG20: 1813.38 | AH20: =AG20-AG19 -> 19.76 | AI20: =AF20+AH20 -> 21.9 | AJ20: =+Z20-Z19 -> 11 | AK20: =SUM(Y20-L20) -> 37 | AL20: =SUM(AJ20-W20) -> 9 | AM20: ='General information '!D20 -> 26.5 | AN20: ='General information '!H20 -> 0 | AP20: ='General information '!J20 -> 350 | AR20: =A20 -> 44027 | AS20: =AS19 -> 0.9 | AT20: 0 | AU20: =AU19 -> 1.1 | AV20: 90 | AW20: 2.9 | AX20: 121 | AY20: =AS20*AT20 -> 0 | AZ20: =AU20*AV20 -> 99 | BA20: =AW20*AX20 -> 350.9 | BB20: =AY20-AY19 -> -47.7 | BC20: =AZ20-AZ19 -> -26.4 | BD20: =BA20-BA19 -> -26.1 | BE20: =SUM(BB20:BD20) -> -100.2 | BF20: =SUM(I20-BE20) -> 100.2 | BG20: =SUM(I20-BF20) -> -100.2
A21: =ELEC!C18 -> 44028 | B21: 108535 | C21: =B21-B20 -> 0 | D21: =C21/27 -> 0 | E21: =SUM((C21*$E$4)+(7500/'EDl log'!$A$39)) -> 241.93548 | G21: 603441 | H21: =G21-G20 -> 159 | I21: =C21+H21 -> 159 | J21: =IF(I21>0,E21/I21,0) -> 1.5216068 | K21: ='Swimming Pool quality check '!H21 -> 6451 | L21: =K21-K20 -> 8 | M21: =M20 -> 457.44 | N21: =SUM(M21-M20) -> 0 | O21: =O20 -> 529.52 | P21: =SUM(O21-O20) -> 0 | Q21: =SUM(P21+N21) -> 0 | T21: 4952 | U21: =SUM(T21-T20) -> 3 | V21: 415 | W21: =+V21-V20 -> 0 | X21: 145527 | Y21: =SUM(X21-X20) -> 0 | Z21: 95780 | AA21: =Z21-Z20 -> 0 | AB21: 258 | AC21: =AC20 -> 670 | AD21: =AC21-AC20 -> 0 | AE21: 171.62 | AF21: =AE21-AE20 -> 0.37 | AG21: 1816.13 | AH21: =AG21-AG20 -> 2.75 | AI21: =AF21+AH21 -> 3.12 | AJ21: =+Z21-Z20 -> 0 | AK21: =SUM(Y21-L21) -> -8 | AL21: =SUM(AJ21-W21) -> 0 | AM21: ='General information '!D21 -> 27.5 | AN21: ='General information '!H21 -> 0 | AP21: ='General information '!J21 -> 0 | AR21: =A21 -> 44028 | AS21: =AS20 -> 0.9 | AT21: 93 | AU21: =AU20 -> 1.1 | AV21: 83 | AW21: 2.9 | AX21: 90 | AY21: =AS21*AT21 -> 83.7 | AZ21: =AU21*AV21 -> 91.3 | BA21: =AW21*AX21 -> 261 | BB21: =AY21-AY20 -> 83.7 | BC21: =AZ21-AZ20 -> -7.7 | BD21: =BA21-BA20 -> -89.9 | BE21: =SUM(BB21:BD21) -> -13.9 | BF21: =SUM(I21-BE21) -> 172.9 | BG21: =SUM(I21-BF21) -> -13.9
A22: =ELEC!C19 -> 44029 | B22: =B21 -> 108535 | C22: =B22-B21 -> 0 | D22: =C22/27 -> 0 | E22: =SUM((C22*$E$4)+(7500/'EDl log'!$A$39)) -> 241.93548 | G22: =G21 -> 603441 | H22: =G22-G21 -> 0 | I22: =C22+H22 -> 0 | J22: =IF(I22>0,E22/I22,0) -> 0 | K22: ='Swimming Pool quality check '!H22 -> 6451 | L22: =K22-K21 -> 0 | M22: =M21 -> 457.44 | N22: =SUM(M22-M21) -> 0 | O22: =O21 -> 529.52 | P22: =SUM(O22-O21) -> 0 | Q22: =SUM(P22+N22) -> 0 | T22: =T21 -> 4952 | U22: =SUM(T22-T21) -> 0 | V22: =V21 -> 415 | W22: =+V22-V21 -> 0 | X22: =X21 -> 145527 | Y22: =SUM(X22-X21) -> 0 | Z22: =Z21 -> 95780 | AA22: =Z22-Z21 -> 0 | AB22: =AB21 -> 258 | AC22: =AC21 -> 670 | AD22: =AC22-AC21 -> 0 | AE22: =AE21 -> 171.62 | AF22: =AE22-AE21 -> 0 | AG22: =AG21 -> 1816.13 | AH22: =AG22-AG21 -> 0 | AI22: =AF22+AH22 -> 0 | AJ22: =+Z22-Z21 -> 0 | AK22: =SUM(Y22-L22) -> 0 | AL22: =SUM(AJ22-W22) -> 0 | AM22: ='General information '!D22 -> 0 | AN22: ='General information '!H22 -> 0 | AP22: ='General information '!J22 -> 0 | AR22: =A22 -> 44029 | AS22: =AS21 -> 0.9 | AT22: =AT21 -> 93 | AU22: =AU21 -> 1.1 | AV22: =AV21 -> 83 | AW22: 2.9 | AX22: =AX21 -> 90 | AY22: =AS22*AT22 -> 83.7 | AZ22: =AU22*AV22 -> 91.3 | BA22: =AW22*AX22 -> 261 | BB22: =AY22-AY21 -> 0 | BC22: =AZ22-AZ21 -> 0 | BD22: =BA22-BA21 -> 0 | BE22: =SUM(BB22:BD22) -> 0 | BF22: =SUM(I22-BE22) -> 0 | BG22: =SUM(I22-BF22) -> 0
A23: =ELEC!C20 -> 44030 | B23: =B22 -> 108535 | C23: =B23-B22 -> 0 | D23: =C23/27 -> 0 | E23: =SUM((C23*$E$4)+(7500/'EDl log'!$A$39)) -> 241.93548 | G23: =G22 -> 603441 | H23: =G23-G22 -> 0 | I23: =C23+H23 -> 0 | J23: =IF(I23>0,E23/I23,0) -> 0 | K23: ='Swimming Pool quality check '!H23 -> 6451 | L23: =K23-K22 -> 0 | M23: =M22 -> 457.44 | N23: =SUM(M23-M22) -> 0 | O23: =O22 -> 529.52 | P23: =SUM(O23-O22) -> 0 | Q23: =SUM(P23+N23) -> 0 | T23: =T22 -> 4952 | U23: =SUM(T23-T22) -> 0 | V23: =V22 -> 415 | W23: =+V23-V22 -> 0 | X23: =X22 -> 145527 | Y23: =SUM(X23-X22) -> 0 | Z23: =Z22 -> 95780 | AA23: =Z23-Z22 -> 0 | AB23: =AB22 -> 258 | AC23: =AC22 -> 670 | AD23: =AC23-AC22 -> 0 | AE23: =AE22 -> 171.62 | AF23: =AE23-AE22 -> 0 | AG23: =AG22 -> 1816.13 | AH23: =AG23-AG22 -> 0 | AI23: =AF23+AH23 -> 0 | AJ23: =+Z23-Z22 -> 0 | AK23: =SUM(Y23-L23) -> 0 | AL23: =SUM(AJ23-W23) -> 0 | AM23: ='General information '!D23 -> 0 | AN23: ='General information '!H23 -> 0 | AP23: ='General information '!J23 -> 0 | AR23: =A23 -> 44030 | AS23: =AS22 -> 0.9 | AT23: =AT22 -> 93 | AU23: =AU22 -> 1.1 | AV23: =AV22 -> 83 | AW23: 2.9 | AX23: =AX22 -> 90 | AY23: =AS23*AT23 -> 83.7 | AZ23: =AU23*AV23 -> 91.3 | BA23: =AW23*AX23 -> 261 | BB23: =AY23-AY22 -> 0 | BC23: =AZ23-AZ22 -> 0 | BD23: =BA23-BA22 -> 0 | BE23: =SUM(BB23:BD23) -> 0 | BF23: =SUM(I23-BE23) -> 0 | BG23: =SUM(I23-BF23) -> 0
A24: =ELEC!C21 -> 44031 | B24: =B23 -> 108535 | C24: =B24-B23 -> 0 | D24: =C24/27 -> 0 | E24: =SUM((C24*$E$4)+(7500/'EDl log'!$A$39)) -> 241.93548 | G24: =G23 -> 603441 | H24: =G24-G23 -> 0 | I24: =C24+H24 -> 0 | J24: =IF(I24>0,E24/I24,0) -> 0 | K24: ='Swimming Pool quality check '!H24 -> 6451 | L24: =K24-K23 -> 0 | M24: =M23 -> 457.44 | N24: =SUM(M24-M23) -> 0 | O24: =O23 -> 529.52 | P24: =SUM(O24-O23) -> 0 | Q24: =SUM(P24+N24) -> 0 | T24: =T23 -> 4952 | U24: =SUM(T24-T23) -> 0 | V24: =V23 -> 415 | W24: =+V24-V23 -> 0 | X24: =X23 -> 145527 | Y24: =SUM(X24-X23) -> 0 | Z24: =Z23 -> 95780 | AA24: =Z24-Z23 -> 0 | AB24: =AB23 -> 258 | AC24: =AC23 -> 670 | AD24: =AC24-AC23 -> 0 | AE24: =AE23 -> 171.62 | AF24: =AE24-AE23 -> 0 | AG24: =AG23 -> 1816.13 | AH24: =AG24-AG23 -> 0 | AI24: =AF24+AH24 -> 0 | AJ24: =+Z24-Z23 -> 0 | AK24: =SUM(Y24-L24) -> 0 | AL24: =SUM(AJ24-W24) -> 0 | AM24: ='General information '!D24 -> 0 | AN24: ='General information '!H24 -> 0 | AP24: ='General information '!J24 -> 0 | AR24: =A24 -> 44031 | AS24: =AS23 -> 0.9 | AT24: =AT23 -> 93 | AU24: =AU23 -> 1.1 | AV24: =AV23 -> 83 | AW24: 2.9 | AX24: =AX23 -> 90 | AY24: =AS24*AT24 -> 83.7 | AZ24: =AU24*AV24 -> 91.3 | BA24: =AW24*AX24 -> 261 | BB24: =AY24-AY23 -> 0 | BC24: =AZ24-AZ23 -> 0 | BD24: =BA24-BA23 -> 0 | BE24: =SUM(BB24:BD24) -> 0 | BF24: =SUM(I24-BE24) -> 0 | BG24: =SUM(I24-BF24) -> 0
A25: =ELEC!C22 -> 44032 | B25: =B24 -> 108535 | C25: =B25-B24 -> 0 | D25: =C25/27 -> 0 | E25: =SUM((C25*$E$4)+(7500/'EDl log'!$A$39)) -> 241.93548 | G25: =G24 -> 603441 | H25: =G25-G24 -> 0 | I25: =C25+H25 -> 0 | J25: =IF(I25>0,E25/I25,0) -> 0 | K25: ='Swimming Pool quality check '!H25 -> 6451 | L25: =K25-K24 -> 0 | M25: =M24 -> 457.44 | N25: =SUM(M25-M24) -> 0 | O25: =O24 -> 529.52 | P25: =SUM(O25-O24) -> 0 | Q25: =SUM(P25+N25) -> 0 | T25: =T24 -> 4952 | U25: =SUM(T25-T24) -> 0 | V25: =V24 -> 415 | W25: =+V25-V24 -> 0 | X25: =X24 -> 145527 | Y25: =SUM(X25-X24) -> 0 | Z25: =Z24 -> 95780 | AA25: =Z25-Z24 -> 0 | AB25: =AB24 -> 258 | AC25: =AC24 -> 670 | AD25: =AC25-AC24 -> 0 | AE25: =AE24 -> 171.62 | AF25: =AE25-AE24 -> 0 | AG25: =AG24 -> 1816.13 | AH25: =AG25-AG24 -> 0 | AI25: =AF25+AH25 -> 0 | AJ25: =+Z25-Z24 -> 0 | AK25: =SUM(Y25-L25) -> 0 | AL25: =SUM(AJ25-W25) -> 0 | AM25: ='General information '!D25 -> 0 | AN25: ='General information '!H25 -> 0 | AP25: ='General information '!J25 -> 0 | AR25: =A25 -> 44032 | AS25: =AS24 -> 0.9 | AT25: =AT24 -> 93 | AU25: =AU24 -> 1.1 | AV25: =AV24 -> 83 | AW25: 2.9 | AX25: =AX24 -> 90 | AY25: =AS25*AT25 -> 83.7 | AZ25: =AU25*AV25 -> 91.3 | BA25: =AW25*AX25 -> 261 | BB25: =AY25-AY24 -> 0 | BC25: =AZ25-AZ24 -> 0 | BD25: =BA25-BA24 -> 0 | BE25: =SUM(BB25:BD25) -> 0 | BF25: =SUM(I25-BE25) -> 0 | BG25: =SUM(I25-BF25) -> 0
A26: =ELEC!C23 -> 44033 | B26: =B25 -> 108535 | C26: =B26-B25 -> 0 | D26: =C26/27 -> 0 | E26: =SUM((C26*$E$4)+(7500/'EDl log'!$A$39)) -> 241.93548 | G26: =G25 -> 603441 | H26: =G26-G25 -> 0 | I26: =C26+H26 -> 0 | J26: =IF(I26>0,E26/I26,0) -> 0 | K26: ='Swimming Pool quality check '!H26 -> 6451 | L26: =K26-K25 -> 0 | M26: =M25 -> 457.44 | N26: =SUM(M26-M25) -> 0 | O26: =O25 -> 529.52 | P26: =SUM(O26-O25) -> 0 | Q26: =SUM(P26+N26) -> 0 | T26: =T25 -> 4952 | U26: =SUM(T26-T25) -> 0 | V26: =V25 -> 415 | W26: =+V26-V25 -> 0 | X26: =X25 -> 145527 | Y26: =SUM(X26-X25) -> 0 | Z26: =Z25 -> 95780 | AA26: =Z26-Z25 -> 0 | AB26: =AB25 -> 258 | AC26: =AC25 -> 670 | AD26: =AC26-AC25 -> 0 | AE26: =AE25 -> 171.62 | AF26: =AE26-AE25 -> 0 | AG26: =AG25 -> 1816.13 | AH26: =AG26-AG25 -> 0 | AI26: =AF26+AH26 -> 0 | AJ26: =+Z26-Z25 -> 0 | AK26: =SUM(Y26-L26) -> 0 | AL26: =SUM(AJ26-W26) -> 0 | AM26: ='General information '!D26 -> 0 | AN26: ='General information '!H26 -> 0 | AP26: ='General information '!J26 -> 0 | AR26: =A26 -> 44033 | AS26: =AS25 -> 0.9 | AT26: =AT25 -> 93 | AU26: =AU25 -> 1.1 | AV26: =AV25 -> 83 | AW26: 2.9 | AX26: =AX25 -> 90 | AY26: =AS26*AT26 -> 83.7 | AZ26: =AU26*AV26 -> 91.3 | BA26: =AW26*AX26 -> 261 | BB26: =AY26-AY25 -> 0 | BC26: =AZ26-AZ25 -> 0 | BD26: =BA26-BA25 -> 0 | BE26: =SUM(BB26:BD26) -> 0 | BF26: =SUM(I26-BE26) -> 0 | BG26: =SUM(I26-BF26) -> 0
A27: =ELEC!C24 -> 44034 | B27: =B26 -> 108535 | C27: =B27-B26 -> 0 | D27: =C27/27 -> 0 | E27: =SUM((C27*$E$4)+(7500/'EDl log'!$A$39)) -> 241.93548 | G27: =G26 -> 603441 | H27: =G27-G26 -> 0 | I27: =C27+H27 -> 0 | J27: =IF(I27>0,E27/I27,0) -> 0 | K27: ='Swimming Pool quality check '!H27 -> 6451 | L27: =K27-K26 -> 0 | M27: =M26 -> 457.44 | N27: =SUM(M27-M26) -> 0 | O27: =O26 -> 529.52 | P27: =SUM(O27-O26) -> 0 | Q27: =SUM(P27+N27) -> 0 | T27: =T26 -> 4952 | U27: =SUM(T27-T26) -> 0 | V27: =V26 -> 415 | W27: =+V27-V26 -> 0 | X27: =X26 -> 145527 | Y27: =SUM(X27-X26) -> 0 | Z27: =Z26 -> 95780 | AA27: =Z27-Z26 -> 0 | AB27: =AB26 -> 258 | AC27: =AC26 -> 670 | AD27: =AC27-AC26 -> 0 | AE27: =AE26 -> 171.62 | AF27: =AE27-AE26 -> 0 | AG27: =AG26 -> 1816.13 | AH27: =AG27-AG26 -> 0 | AI27: =AF27+AH27 -> 0 | AJ27: =+Z27-Z26 -> 0 | AK27: =SUM(Y27-L27) -> 0 | AL27: =SUM(AJ27-W27) -> 0 | AM27: ='General information '!D27 -> 0 | AN27: ='General information '!H27 -> 0 | AP27: ='General information '!J27 -> 0 | AR27: =A27 -> 44034 | AS27: =AS26 -> 0.9 | AT27: =AT26 -> 93 | AU27: =AU26 -> 1.1 | AV27: =AV26 -> 83 | AW27: 2.9 | AX27: =AX26 -> 90 | AY27: =AS27*AT27 -> 83.7 | AZ27: =AU27*AV27 -> 91.3 | BA27: =AW27*AX27 -> 261 | BB27: =AY27-AY26 -> 0 | BC27: =AZ27-AZ26 -> 0 | BD27: =BA27-BA26 -> 0 | BE27: =SUM(BB27:BD27) -> 0 | BF27: =SUM(I27-BE27) -> 0 | BG27: =SUM(I27-BF27) -> 0
A28: =ELEC!C25 -> 44035 | B28: =B27 -> 108535 | C28: =B28-B27 -> 0 | D28: =C28/27 -> 0 | E28: =SUM((C28*$E$4)+(7500/'EDl log'!$A$39)) -> 241.93548 | G28: =G27 -> 603441 | H28: =G28-G27 -> 0 | I28: =C28+H28 -> 0 | J28: =IF(I28>0,E28/I28,0) -> 0 | K28: ='Swimming Pool quality check '!H28 -> 6451 | L28: =K28-K27 -> 0 | M28: =M27 -> 457.44 | N28: =SUM(M28-M27) -> 0 | O28: =O27 -> 529.52 | P28: =SUM(O28-O27) -> 0 | Q28: =SUM(P28+N28) -> 0 | T28: =T27 -> 4952 | U28: =SUM(T28-T27) -> 0 | V28: =V27 -> 415 | W28: =+V28-V27 -> 0 | X28: =X27 -> 145527 | Y28: =SUM(X28-X27) -> 0 | Z28: =Z27 -> 95780 | AA28: =Z28-Z27 -> 0 | AB28: =AB27 -> 258 | AC28: =AC27 -> 670 | AD28: =AC28-AC27 -> 0 | AE28: =AE27 -> 171.62 | AF28: =AE28-AE27 -> 0 | AG28: =AG27 -> 1816.13 | AH28: =AG28-AG27 -> 0 | AI28: =AF28+AH28 -> 0 | AJ28: =+Z28-Z27 -> 0 | AK28: =SUM(Y28-L28) -> 0 | AL28: =SUM(AJ28-W28) -> 0 | AM28: ='General information '!D28 -> 0 | AN28: ='General information '!H28 -> 0 | AP28: ='General information '!J28 -> 0 | AR28: =A28 -> 44035 | AS28: =AS27 -> 0.9 | AT28: =AT27 -> 93 | AU28: =AU27 -> 1.1 | AV28: =AV27 -> 83 | AW28: 2.9 | AX28: =AX27 -> 90 | AY28: =AS28*AT28 -> 83.7 | AZ28: =AU28*AV28 -> 91.3 | BA28: =AW28*AX28 -> 261 | BB28: =AY28-AY27 -> 0 | BC28: =AZ28-AZ27 -> 0 | BD28: =BA28-BA27 -> 0 | BE28: =SUM(BB28:BD28) -> 0 | BF28: =SUM(I28-BE28) -> 0 | BG28: =SUM(I28-BF28) -> 0
A29: =ELEC!C26 -> 44036 | B29: =B28 -> 108535 | C29: =B29-B28 -> 0 | D29: =C29/27 -> 0 | E29: =SUM((C29*$E$4)+(7500/'EDl log'!$A$39)) -> 241.93548 | G29: =G28 -> 603441 | H29: =G29-G28 -> 0 | I29: =C29+H29 -> 0 | J29: =IF(I29>0,E29/I29,0) -> 0 | K29: ='Swimming Pool quality check '!H29 -> 6451 | L29: =K29-K28 -> 0 | M29: =M28 -> 457.44 | N29: =SUM(M29-M28) -> 0 | O29: =O28 -> 529.52 | P29: =SUM(O29-O28) -> 0 | Q29: =SUM(P29+N29) -> 0 | T29: =T28 -> 4952 | U29: =SUM(T29-T28) -> 0 | V29: =V28 -> 415 | W29: =+V29-V28 -> 0 | X29: =X28 -> 145527 | Y29: =SUM(X29-X28) -> 0 | Z29: =Z28 -> 95780 | AA29: =Z29-Z28 -> 0 | AB29: =AB28 -> 258 | AC29: =AC28 -> 670 | AD29: =AC29-AC28 -> 0 | AE29: =AE28 -> 171.62 | AF29: =AE29-AE28 -> 0 | AG29: =AG28 -> 1816.13 | AH29: =AG29-AG28 -> 0 | AI29: =AF29+AH29 -> 0 | AJ29: =+Z29-Z28 -> 0 | AK29: =SUM(Y29-L29) -> 0 | AL29: =SUM(AJ29-W29) -> 0 | AM29: ='General information '!D29 -> 0 | AN29: ='General information '!H29 -> 0 | AP29: ='General information '!J29 -> 0 | AR29: =A29 -> 44036 | AS29: =AS28 -> 0.9 | AT29: =AT28 -> 93 | AU29: =AU28 -> 1.1 | AV29: =AV28 -> 83 | AW29: 2.9 | AX29: =AX28 -> 90 | AY29: =AS29*AT29 -> 83.7 | AZ29: =AU29*AV29 -> 91.3 | BA29: =AW29*AX29 -> 261 | BB29: =AY29-AY28 -> 0 | BC29: =AZ29-AZ28 -> 0 | BD29: =BA29-BA28 -> 0 | BE29: =SUM(BB29:BD29) -> 0 | BF29: =SUM(I29-BE29) -> 0 | BG29: =SUM(I29-BF29) -> 0
A30: =ELEC!C27 -> 44037 | B30: =B29 -> 108535 | C30: =B30-B29 -> 0 | D30: =C30/27 -> 0 | E30: =SUM((C30*$E$4)+(7500/'EDl log'!$A$39)) -> 241.93548 | G30: =G29 -> 603441 | H30: =G30-G29 -> 0 | I30: =C30+H30 -> 0 | J30: =IF(I30>0,E30/I30,0) -> 0 | K30: ='Swimming Pool quality check '!H30 -> 6451 | L30: =K30-K29 -> 0 | M30: =M29 -> 457.44 | N30: =SUM(M30-M29) -> 0 | O30: =O29 -> 529.52 | P30: =SUM(O30-O29) -> 0 | Q30: =SUM(P30+N30) -> 0 | T30: =T29 -> 4952 | U30: =SUM(T30-T29) -> 0 | V30: =V29 -> 415 | W30: =+V30-V29 -> 0 | X30: =X29 -> 145527 | Y30: =SUM(X30-X29) -> 0 | Z30: =Z29 -> 95780 | AA30: =Z30-Z29 -> 0 | AB30: =AB29 -> 258 | AC30: =AC29 -> 670 | AD30: =AC30-AC29 -> 0 | AE30: =AE29 -> 171.62 | AF30: =AE30-AE29 -> 0 | AG30: =AG29 -> 1816.13 | AH30: =AG30-AG29 -> 0 | AI30: =AF30+AH30 -> 0 | AJ30: =+Z30-Z29 -> 0 | AK30: =SUM(Y30-L30) -> 0 | AL30: =SUM(AJ30-W30) -> 0 | AM30: ='General information '!D30 -> 0 | AN30: ='General information '!H30 -> 0 | AP30: ='General information '!J30 -> 0 | AR30: =A30 -> 44037 | AS30: =AS29 -> 0.9 | AT30: =AT29 -> 93 | AU30: =AU29 -> 1.1 | AV30: =AV29 -> 83 | AW30: 2.9 | AX30: =AX29 -> 90 | AY30: =AS30*AT30 -> 83.7 | AZ30: =AU30*AV30 -> 91.3 | BA30: =AW30*AX30 -> 261 | BB30: =AY30-AY29 -> 0 | BC30: =AZ30-AZ29 -> 0 | BD30: =BA30-BA29 -> 0 | BE30: =SUM(BB30:BD30) -> 0 | BF30: =SUM(I30-BE30) -> 0 | BG30: =SUM(I30-BF30) -> 0
A31: =ELEC!C28 -> 44038 | B31: =B30 -> 108535 | C31: =B31-B30 -> 0 | D31: =C31/27 -> 0 | E31: =SUM((C31*$E$4)+(7500/'EDl log'!$A$39)) -> 241.93548 | G31: =G30 -> 603441 | H31: =G31-G30 -> 0 | I31: =C31+H31 -> 0 | J31: =IF(I31>0,E31/I31,0) -> 0 | K31: ='Swimming Pool quality check '!H31 -> 6451 | L31: =K31-K30 -> 0 | M31: =M30 -> 457.44 | N31: =SUM(M31-M30) -> 0 | O31: =O30 -> 529.52 | P31: =SUM(O31-O30) -> 0 | Q31: =SUM(P31+N31) -> 0 | T31: =T30 -> 4952 | U31: =SUM(T31-T30) -> 0 | V31: =V30 -> 415 | W31: =+V31-V30 -> 0 | X31: =X30 -> 145527 | Y31: =SUM(X31-X30) -> 0 | Z31: =Z30 -> 95780 | AA31: =Z31-Z30 -> 0 | AB31: =AB30 -> 258 | AC31: =AC30 -> 670 | AD31: =AC31-AC30 -> 0 | AE31: =AE30 -> 171.62 | AF31: =AE31-AE30 -> 0 | AG31: =AG30 -> 1816.13 | AH31: =AG31-AG30 -> 0 | AI31: =AF31+AH31 -> 0 | AJ31: =+Z31-Z30 -> 0 | AK31: =SUM(Y31-L31) -> 0 | AL31: =SUM(AJ31-W31) -> 0 | AM31: ='General information '!D31 -> 0 | AN31: ='General information '!H31 -> 0 | AP31: ='General information '!J31 -> 0 | AR31: =A31 -> 44038 | AS31: =AS30 -> 0.9 | AT31: =AT30 -> 93 | AU31: =AU30 -> 1.1 | AV31: =AV30 -> 83 | AW31: 2.9 | AX31: =AX30 -> 90 | AY31: =AS31*AT31 -> 83.7 | AZ31: =AU31*AV31 -> 91.3 | BA31: =AW31*AX31 -> 261 | BB31: =AY31-AY30 -> 0 | BC31: =AZ31-AZ30 -> 0 | BD31: =BA31-BA30 -> 0 | BE31: =SUM(BB31:BD31) -> 0 | BF31: =SUM(I31-BE31) -> 0 | BG31: =SUM(I31-BF31) -> 0
A32: =ELEC!C29 -> 44039 | B32: =B31 -> 108535 | C32: =B32-B31 -> 0 | D32: =C32/27 -> 0 | E32: =SUM((C32*$E$4)+(7500/'EDl log'!$A$39)) -> 241.93548 | G32: =G31 -> 603441 | H32: =G32-G31 -> 0 | I32: =C32+H32 -> 0 | J32: =IF(I32>0,E32/I32,0) -> 0 | K32: ='Swimming Pool quality check '!H32 -> 6451 | L32: =K32-K31 -> 0 | M32: =M31 -> 457.44 | N32: =SUM(M32-M31) -> 0 | O32: =O31 -> 529.52 | P32: =SUM(O32-O31) -> 0 | Q32: =SUM(P32+N32) -> 0 | T32: =T31 -> 4952 | U32: =SUM(T32-T31) -> 0 | V32: =V31 -> 415 | W32: =+V32-V31 -> 0 | X32: =X31 -> 145527 | Y32: =SUM(X32-X31) -> 0 | Z32: =Z31 -> 95780 | AA32: =Z32-Z31 -> 0 | AB32: =AB31 -> 258 | AC32: =AC31 -> 670 | AD32: =AC32-AC31 -> 0 | AE32: =AE31 -> 171.62 | AF32: =AE32-AE31 -> 0 | AG32: =AG31 -> 1816.13 | AH32: =AG32-AG31 -> 0 | AI32: =AF32+AH32 -> 0 | AJ32: =+Z32-Z31 -> 0 | AK32: 0 | AL32: =SUM(AJ32-W32) -> 0 | AM32: ='General information '!D32 -> 0 | AN32: ='General information '!H32 -> 0 | AP32: ='General information '!J32 -> 0 | AR32: =A32 -> 44039 | AS32: =AS31 -> 0.9 | AT32: =AT31 -> 93 | AU32: =AU31 -> 1.1 | AV32: =AV31 -> 83 | AW32: 2.9 | AX32: =AX31 -> 90 | AY32: =AS32*AT32 -> 83.7 | AZ32: =AU32*AV32 -> 91.3 | BA32: =AW32*AX32 -> 261 | BB32: =AY32-AY31 -> 0 | BC32: =AZ32-AZ31 -> 0 | BD32: =BA32-BA31 -> 0 | BE32: =SUM(BB32:BD32) -> 0 | BF32: =SUM(I32-BE32) -> 0 | BG32: =SUM(I32-BF32) -> 0
A33: =ELEC!C30 -> 44040 | B33: =B32 -> 108535 | C33: =B33-B32 -> 0 | D33: =C33/27 -> 0 | E33: =SUM((C33*$E$4)+(7500/'EDl log'!$A$39)) -> 241.93548 | G33: =G32 -> 603441 | H33: =G33-G32 -> 0 | I33: =C33+H33 -> 0 | J33: =IF(I33>0,E33/I33,0) -> 0 | K33: ='Swimming Pool quality check '!H33 -> 6451 | L33: =K33-K32 -> 0 | M33: =M32 -> 457.44 | N33: =SUM(M33-M32) -> 0 | O33: =O32 -> 529.52 | P33: =SUM(O33-O32) -> 0 | Q33: =SUM(P33+N33) -> 0 | T33: =T32 -> 4952 | U33: =SUM(T33-T32) -> 0 | V33: =V32 -> 415 | W33: =+V33-V32 -> 0 | X33: =X32 -> 145527 | Y33: =SUM(X33-X32) -> 0 | Z33: =Z32 -> 95780 | AA33: =Z33-Z32 -> 0 | AB33: =AB32 -> 258 | AC33: =AC32 -> 670 | AD33: =AC33-AC32 -> 0 | AE33: =AE32 -> 171.62 | AF33: =AE33-AE32 -> 0 | AG33: =AG32 -> 1816.13 | AH33: =AG33-AG32 -> 0 | AI33: =AF33+AH33 -> 0 | AJ33: =+Z33-Z32 -> 0 | AK33: =SUM(Y33-L33) -> 0 | AL33: =SUM(AJ33-W33) -> 0 | AM33: ='General information '!D33 -> 0 | AN33: ='General information '!H33 -> 0 | AP33: ='General information '!J33 -> 0 | AR33: =A33 -> 44040 | AS33: =AS32 -> 0.9 | AT33: =AT32 -> 93 | AU33: =AU32 -> 1.1 | AV33: =AV32 -> 83 | AW33: 2.9 | AX33: =AX32 -> 90 | AY33: =AS33*AT33 -> 83.7 | AZ33: =AU33*AV33 -> 91.3 | BA33: =AW33*AX33 -> 261 | BB33: =AY33-AY32 -> 0 | BC33: =AZ33-AZ32 -> 0 | BD33: =BA33-BA32 -> 0 | BE33: =SUM(BB33:BD33) -> 0 | BF33: =SUM(I33-BE33) -> 0 | BG33: =SUM(I33-BF33) -> 0
A34: =ELEC!C31 -> 44041 | B34: =B33 -> 108535 | C34: =B34-B33 -> 0 | D34: =C34/27 -> 0 | E34: =SUM((C34*$E$4)+(7500/'EDl log'!$A$39)) -> 241.93548 | G34: =G33 -> 603441 | H34: =G34-G33 -> 0 | I34: =C34+H34 -> 0 | J34: =IF(I34>0,E34/I34,0) -> 0 | K34: ='Swimming Pool quality check '!H34 -> 6451 | L34: =K34-K33 -> 0 | M34: =M33 -> 457.44 | N34: =SUM(M34-M33) -> 0 | O34: =O33 -> 529.52 | P34: =SUM(O34-O33) -> 0 | Q34: =SUM(P34+N34) -> 0 | T34: =T33 -> 4952 | U34: =SUM(T34-T33) -> 0 | V34: =V33 -> 415 | W34: =+V34-V33 -> 0 | X34: =X33 -> 145527 | Y34: =SUM(X34-X33) -> 0 | Z34: =Z33 -> 95780 | AA34: =Z34-Z33 -> 0 | AB34: =AB33 -> 258 | AC34: =AC33 -> 670 | AD34: =AC34-AC33 -> 0 | AE34: =AE33 -> 171.62 | AF34: =AE34-AE33 -> 0 | AG34: =AG33 -> 1816.13 | AH34: =AG34-AG33 -> 0 | AI34: =AF34+AH34 -> 0 | AJ34: =+Z34-Z33 -> 0 | AK34: =SUM(Y34-L34) -> 0 | AL34: =SUM(AJ34-W34) -> 0 | AM34: ='General information '!D34 -> 0 | AN34: ='General information '!H34 -> 0 | AP34: ='General information '!J34 -> 0 | AR34: =A34 -> 44041 | AS34: =AS33 -> 0.9 | AT34: =AT33 -> 93 | AU34: =AU33 -> 1.1 | AV34: =AV33 -> 83 | AW34: 2.9 | AX34: =AX33 -> 90 | AY34: =AS34*AT34 -> 83.7 | AZ34: =AU34*AV34 -> 91.3 | BA34: =AW34*AX34 -> 261 | BB34: =AY34-AY33 -> 0 | BC34: =AZ34-AZ33 -> 0 | BD34: =BA34-BA33 -> 0 | BE34: =SUM(BB34:BD34) -> 0 | BF34: =SUM(I34-BE34) -> 0 | BG34: =SUM(I34-BF34) -> 0
A35: =ELEC!C32 -> 44042 | B35: =B34 -> 108535 | C35: =B35-B34 -> 0 | D35: =C35/27 -> 0 | E35: =SUM((C35*$E$4)+(7500/'EDl log'!$A$39)) -> 241.93548 | G35: =G34 -> 603441 | H35: =G35-G34 -> 0 | I35: =C35+H35 -> 0 | J35: =IF(I35>0,E35/I35,0) -> 0 | K35: ='Swimming Pool quality check '!H35 -> 6451 | L35: =K35-K34 -> 0 | M35: =M34 -> 457.44 | N35: =SUM(M35-M34) -> 0 | O35: =O34 -> 529.52 | P35: =SUM(O35-O34) -> 0 | Q35: =SUM(P35+N35) -> 0 | T35: =T34 -> 4952 | U35: =SUM(T35-T34) -> 0 | V35: =V34 -> 415 | W35: =+V35-V34 -> 0 | X35: =X34 -> 145527 | Y35: =SUM(X35-X34) -> 0 | Z35: =Z34 -> 95780 | AA35: =Z35-Z34 -> 0 | AB35: =AB34 -> 258 | AC35: =AC34 -> 670 | AD35: =AC35-AC34 -> 0 | AE35: =AE34 -> 171.62 | AF35: =AE35-AE34 -> 0 | AG35: =AG34 -> 1816.13 | AH35: =AG35-AG34 -> 0 | AI35: =AF35+AH35 -> 0 | AJ35: =+Z35-Z34 -> 0 | AK35: =SUM(Y35-L35) -> 0 | AL35: =SUM(AJ35-W35) -> 0 | AM35: ='General information '!D35 -> 0 | AN35: ='General information '!H35 -> 0 | AP35: ='General information '!J35 -> 0 | AR35: =A35 -> 44042 | AS35: =AS34 -> 0.9 | AT35: =AT34 -> 93 | AU35: =AU34 -> 1.1 | AV35: =AV34 -> 83 | AW35: 2.9 | AX35: =AX34 -> 90 | AY35: =AS35*AT35 -> 83.7 | AZ35: =AU35*AV35 -> 91.3 | BA35: =AW35*AX35 -> 261 | BB35: =AY35-AY34 -> 0 | BC35: =AZ35-AZ34 -> 0 | BD35: =BA35-BA34 -> 0 | BE35: =SUM(BB35:BD35) -> 0 | BF35: =SUM(I35-BE35) -> 0 | BG35: =SUM(I35-BF35) -> 0
A36: =ELEC!C33 -> 44043 | B36: =B35 -> 108535 | C36: =B36-B35 -> 0 | D36: =C36/27 -> 0 | E36: =SUM((C36*$E$4)+(7500/'EDl log'!$A$39)) -> 241.93548 | G36: =G35 -> 603441 | H36: =G36-G35 -> 0 | I36: =C36+H36 -> 0 | J36: =IF(I36>0,E36/I36,0) -> 0 | K36: ='Swimming Pool quality check '!H37 -> 0 | L36: =K36-K35 -> -6451 | M36: =M35 -> 457.44 | N36: =SUM(M36-M35) -> 0 | O36: =O35 -> 529.52 | P36: =SUM(O36-O35) -> 0 | Q36: =SUM(P36+N36) -> 0 | T36: =T35 -> 4952 | U36: =SUM(T36-T35) -> 0 | V36: =V35 -> 415 | W36: =+V36-V35 -> 0 | X36: =X35 -> 145527 | Y36: =SUM(X36-X35) -> 0 | Z36: =Z35 -> 95780 | AA36: =Z36-Z35 -> 0 | AB36: =AB35 -> 258 | AC36: =AC35 -> 670 | AD36: =AC36-AC35 -> 0 | AE36: =AE35 -> 171.62 | AF36: =AE36-AE35 -> 0 | AG36: =AG35 -> 1816.13 | AH36: =AG36-AG35 -> 0 | AI36: =AF36+AH36 -> 0 | AJ36: =+Z36-Z35 -> 0 | AK36: =SUM(Y36-L36) -> 6451 | AL36: =SUM(AJ36-W36) -> 0 | AM36: ='General information '!D37 -> 0 | AN36: ='General information '!H37 -> 0 | AP36: ='General information '!J37 -> 0 | AR36: =A36 -> 44043 | AS36: =AS35 -> 0.9 | AT36: =AT35 -> 93 | AU36: =AU35 -> 1.1 | AV36: =AV35 -> 83 | AW36: 2.9 | AX36: =AX35 -> 90 | AY36: =AS36*AT36 -> 83.7 | AZ36: =AU36*AV36 -> 91.3 | BA36: =AW36*AX36 -> 261 | BB36: =AY36-AY35 -> 0 | BC36: =AZ36-AZ35 -> 0 | BD36: =BA36-BA35 -> 0 | BE36: =SUM(BB36:BD36) -> 0 | BF36: =SUM(I36-BE36) -> 0 | BG36: =SUM(I36-BF36) -> 0
C37: =SUM(C6:C35) -> 0 | D37: =SUM(D6:D35) -> 0 | F37: =SUM(F6:F35) -> 0 | H37: =SUM(H6:H35) -> 2195 | I37: =SUM(I6:I35) -> 2195 | L37: =SUM(L7:L35) -> 85 | Q37: =SUM(Q5:Q35) -> 0 | U37: =SUM(U6:U35) -> 53 | Y37: =SUM(Y35,Y33,Y31,Y29,Y27,Y25,Y23,Y21,Y19,Y17,Y15,Y13,Y11,Y9,Y7+#REF!) -> #REF! | AJ37: =SUM(AJ6:AJ35) -> 423 | AK37: =SUM(Y37-L37) -> #REF! | AL37: =SUM(AL6:AL35) -> 418
C38: =+C37*1.66 -> 0 | E38: =SUM(E6:E35) -> 7258.0645 | F38: =SUM(F6:F35) -> 0 | H38: 7500 | I38: =SUM('General information '!G37/WATER!I37) -> 0.17456948 | O38: =SUM(Q37+I37) -> 2195 | Z38: =SUM(Y37:AJ37) -> #REF! | AK38: =SUM(Y38-L38) -> 0
B39: =9*27 -> 243 | D39: =SUM(D21:D35) -> 0 | F39: =SUM(F6:F35) -> 0 | G39: =SUM(I37) -> 2195 | H39: =SUM(H38+C38) -> 7500 | K39: =SUM(H39/G39) -> 3.4168565 | AJ39: =SUM(C38-AK38) -> 0 | AM39: =SUM(AJ39/AO38) -> #DIV/0!

Sheet graphic

Sheet General information 
A1: GENERAL & HOTEL'S INFORMATION SHEET
B4: Max Temp | C4: MIN TEMP | D4: AVE TEMP | E4: AVE Humidity | F4: AVE OCC | G4: # of OCC Rooms | H4: Ball room | I4: Meeting rooms | J4: Outlets | K4: Total covers | L4: # of permenant Emp | M4: # of casuals | N4: Total # of EMP | O4: # of EMP/OCC Room
A5: =ELEC!C2 -> 44012 | B5: ='[1]General information '!B35 -> 30 | C5: ='[1]General information '!C35 -> 22 | D5: ='[1]General information '!D35 -> 26 | E5: ='[1]General information '!E35 -> 0.75 | F5: ='[1]General information '!F35 -> 0.0478 | G5: ='[1]General information '!G35 -> 10.994 | H5: ='[1]General information '!H35 -> 0 | I5: ='[1]General information '!I35 -> 0 | ... O5: ='[1]General information '!O35 -> 0
A6: =ELEC!C3 -> 44013 | B6: 28 | C6: 24 | D6: =(C6+B6)/2 -> 26 | E6: 0.7 | F6: 0.0565 | G6: =F6*230 -> 12.995 | J6: 196 | K6: =+J6+H6 -> 196
A7: =ELEC!C4 -> 44014 | B7: 29 | C7: 23 | D7: =(C7+B7)/2 -> 26 | E7: 0.62 | F7: 0.039 | G7: =F7*230 -> 8.97 | J7: 262 | K7: =+J7+H7 -> 262
A8: =ELEC!C5 -> 44015 | B8: 29 | C8: 24 | D8: =(C8+B8)/2 -> 26.5 | E8: 0.65 | F8: 0.087 | G8: =F8*230 -> 20.01 | J8: 263 | K8: =+J8+H8 -> 263
A9: =ELEC!C6 -> 44016 | B9: 28 | C9: 24 | D9: =(C9+B9)/2 -> 26 | E9: 0.66 | F9: 0.087 | G9: =F9*230 -> 20.01 | J9: 258 | K9: =+J9+H9 -> 258
A10: =ELEC!C7 -> 44017 | B10: 30 | C10: 26 | D10: =(C10+B10)/2 -> 28 | E10: 0.7 | F10: 0.0783 | G10: =F10*230 -> 18.009 | J10: 801 | K10: =+J10+H10 -> 801
A11: =ELEC!C8 -> 44018 | B11: 29 | C11: 25 | D11: =(C11+B11)/2 -> 27 | E11: 0.69 | F11: 0.0826 | G11: =F11*230 -> 18.998 | J11: 230 | K11: =+J11+H11 -> 230
A12: =ELEC!C9 -> 44019 | B12: 30 | C12: 22 | D12: =(C12+B12)/2 -> 26 | E12: 0.68 | F12: 0.0783 | G12: =F12*230 -> 18.009 | J12: 268 | K12: =+J12+H12 -> 268
A13: =ELEC!C10 -> 44020 | B13: 30 | C13: 22 | D13: =(C13+B13)/2 -> 26 | E13: 0.7 | F13: 0.087 | G13: =F13*230 -> 20.01 | J13: 336 | K13: =+J13+H13 -> 336
A14: =ELEC!C11 -> 44021 | B14: 30 | C14: 22 | D14: =(C14+B14)/2 -> 26 | E14: 0.65 | F14: 0.1087 | G14: =F14*230 -> 25.001 | J14: 375 | K14: =+J14+H14 -> 375
A15: =ELEC!C12 -> 44022 | B15: 30 | C15: 22 | D15: =(C15+B15)/2 -> 26 | E15: 0.7 | F15: 0.113 | G15: =F15*230 -> 25.99 | J15: 329 | K15: =+J15+H15 -> 329
A16: =ELEC!C13 -> 44023 | B16: 30 | C16: 26 | D16: =(C16+B16)/2 -> 28 | E16: 0.56 | F16: 0.165 | G16: =F16*230 -> 37.95 | J16: 323 | K16: =+J16+H16 -> 323
A17: =ELEC!C14 -> 44024 | B17: 30 | C17: 22 | D17: =(C17+B17)/2 -> 26 | E17: 0.62 | F17: 0.1 | G17: =F17*230 -> 23 | J17: 357 | K17: =+J17+H17 -> 357
... A21: =ELEC!C18 -> 44028 | B21: 30 | C21: 25 | D21: =(C21+B21)/2 -> 27.5 | E21: 0.68 | F21: 0.2 | G21: =F21*230 -> 46 | J21: 0 | K21: =+J21+H21 -> 0
A22: =ELEC!C19 -> 44029 | D22: =(C22+B22)/2 -> 0 | G22: =F22*230 -> 0 | K22: =+J22+H22 -> 0
A23: =ELEC!C20 -> 44030 | D23: =(C23+B23)/2 -> 0 | G23: =F23*230 -> 0 | K23: =+J23+H23 -> 0
A24: =ELEC!C21 -> 44031 | D24: =(C24+B24)/2 -> 0 | G24: =F24*230 -> 0 | K24: =+J24+H24 -> 0
A25: =ELEC!C22 -> 44032 | D25: =(C25+B25)/2 -> 0 | G25: =F25*230 -> 0 | K25: =+J25+H25 -> 0
A26: =ELEC!C23 -> 44033 | D26: =(C26+B26)/2 -> 0 | G26: =F26*230 -> 0 | K26: =+J26+H26 -> 0
A27: =ELEC!C24 -> 44034 | D27: =(C27+B27)/2 -> 0 | G27: =F27*230 -> 0 | K27: =+J27+H27+I27 -> 0
A28: =ELEC!C25 -> 44035 | D28: =(C28+B28)/2 -> 0 | G28: =F28*230 -> 0 | K28: =+J28+H28+I28 -> 0
A29: =ELEC!C26 -> 44036 | D29: =(C29+B29)/2 -> 0 | G29: =F29*230 -> 0 | K29: =+J29+H29+I29 -> 0
A30: =ELEC!C27 -> 44037 | D30: =(C30+B30)/2 -> 0 | G30: =F30*230 -> 0 | K30: =+J30+H30+I30 -> 0
A31: =ELEC!C28 -> 44038 | D31: =(C31+B31)/2 -> 0 | G31: =F31*230 -> 0 | K31: =+J31+H31+I31 -> 0
A32: =ELEC!C29 -> 44039 | D32: =(C32+B32)/2 -> 0 | G32: =F32*230 -> 0 | K32: =+J32+H32+I32 -> 0
A33: =ELEC!C30 -> 44040 | D33: =(C33+B33)/2 -> 0 | G33: =F33*230 -> 0 | K33: =+J33+H33+I33 -> 0
A34: =ELEC!C31 -> 44041 | D34: =(C34+B34)/2 -> 0 | G34: =F34*230 -> 0 | K34: =+J34+H34+I34 -> 0
A35: =ELEC!C32 -> 44042 | D35: =(C35+B35)/2 -> 0 | G35: =F35*230 -> 0 | K35: =+J35+H35+I35 -> 0
A36: =ELEC!C33 -> 44043 | D36: =(C36+B36)/2 -> 0 | G36: =F36*230 -> 0 | K36: =+J36+H36+I36 -> 0
F37: =AVERAGE(F6:F35) -> 0.104125 | G37: =SUM(G6:G35) -> 383.18
D38: =SUM(D6:D35)/'EDl log'!A37 -> 32.730769
I41: http://www.accuweather.com/en/lb/lebanon-weather

Sheet tanks
B2: Tank 1 | D2: Tank 2 | F2: Tank 3 | H2: Tank 4 | J2: Tank 5 | L2: Tank 6 | N2: Tank 7 | P2: Tank 8 | R2: Tank 9 | T2: Tank 10 | V2: Tank 11 | Z2: Tank 1 | AB2: Tank 2 | AD2: Tank 3 | AF2: Tank 4 | AH2: Tank 5 | AJ2: Tank 6 | AL2: Tank 7
B3: 6670 | D3: =SUM(B3) -> 6670 | F3: =SUM(D3) -> 6670 | H3: =SUM(F3) -> 6670 | J3: =SUM(H3) -> 6670 | L3: =SUM(J3) -> 6670 | N3: =SUM(L3) -> 6670 | P3: =SUM(N3) -> 6670 | R3: =SUM(P3) -> 6670 | T3: =SUM(R3) -> 6670 | V3: =SUM(T3) -> 6670 | W3: =SUM(B3:V3) -> 73370 | Z3: 2800 | AB3: 2800 | AD3: 2800 | AF3: 2800 | AH3: 2800 | AJ3: 2800 | AL3: 2800 | AM3: =SUM(Z3:AL3) -> 19600 | AO3: =SUM(AM3+W3) -> 92970 | AR3: Total sotck | AS3: Diesel Cons Per day | AT3: Diesel Delivery | BE3: Genset Co | BF3: Steam | BG3: Boil | BH3: Outdoor temperature
B4: =B3/310 -> 21.516129 | D4: =SUM(B4) -> 21.516129 | F4: =SUM(D4) -> 21.516129 | H4: =SUM(F4) -> 21.516129 | J4: =SUM(H4) -> 21.516129 | L4: =SUM(J4) -> 21.516129 | N4: =SUM(L4) -> 21.516129 | P4: =SUM(N4) -> 21.516129 | R4: =SUM(P4) -> 21.516129 | T4: =SUM(R4) -> 21.516129 | V4: =SUM(T4) -> 21.516129 | Z4: =Z3/280 -> 10 | AA4: =AA3/280 -> 0 | AB4: =AB3/280 -> 10 | AC4: =AC3/280 -> 0 | AD4: =AD3/280 -> 10 | AE4: =AE3/280 -> 0 | AF4: =AF3/280 -> 10 | AG4: =AG3/280 -> 0 | ... AL4: =AL3/280 -> 10 | AT4: Delivery | AU4: Cost /L | AW4: Boiler+Steam | AX4: Generator | AZ4: Occupancy | BA4: AVE TEPM | BB4: AVE Humidity
A5: =ELEC!C2 -> 44012 | B5: =[1]tanks!B35 -> 140 | C5: =[1]tanks!C35 -> 3012.2581 | D5: =[1]tanks!D35 -> 140 | E5: =[1]tanks!E35 -> 3012.2581 | F5: =[1]tanks!F35 -> 140 | G5: =[1]tanks!G35 -> 3012.2581 | H5: =[1]tanks!H35 -> 140 | I5: =[1]tanks!I35 -> 3012.2581 | ... BB5: =[1]tanks!BB35 -> 0.75 | BC5: =[2]tanks!BC36 -> 0 | BD5: =[2]tanks!BD36 -> 0 | BE5: =[2]tanks!BE36 -> 0 | BF5: =[2]tanks!BF36 -> 0 | BG5: =[2]tanks!BG36 -> 0 | BH5: =[2]tanks!BH36 -> 0
A6: =ELEC!C3 -> 44013 | B6: ='B5'!B5 -> 183 | C6: =B6*$B$4 -> 3937.4516 | D6: =SUM(B6) -> 183 | E6: =D6*$B$4 -> 3937.4516 | F6: =SUM(D6) -> 183 | G6: =F6*$B$4 -> 3937.4516 | H6: =SUM(F6) -> 183 | I6: =H6*$B$4 -> 3937.4516 | J6: =SUM(H6) -> 183 | K6: =J6*$B$4 -> 3937.4516 | L6: =SUM(J6) -> 183 | M6: =L6*$B$4 -> 3937.4516 | N6: =SUM(L6) -> 183 | O6: =N6*$B$4 -> 3937.4516 | P6: =SUM(N6) -> 183 | Q6: =P6*$B$4 -> 3937.4516 | R6: =SUM(P6) -> 183 | S6: =R6*$B$4 -> 3937.4516 | T6: =SUM(R6) -> 183 | U6: =T6*$B$4 -> 3937.4516 | V6: =SUM(T6) -> 183 | W6: =V6*$B$4 -> 3937.4516 | X6: =SUM(Y6/73370) -> 0.59032258 | Y6: =SUM(C6+E6+G6+I6+K6+M6+O6+Q6+S6+U6+W6) -> 43311.968 | Z6: ='B5'!C5 -> 190 | AA6: =SUM(Z6*$Z$4) -> 1900 | AB6: =SUM(Z6) -> 190 | AC6: =SUM(AB6*$Z$4) -> 1900 | AD6: =SUM(AB6) -> 190 | AE6: =SUM(AD6*$Z$4) -> 1900 | AF6: =SUM(AD6) -> 190 | AG6: =SUM(AF6*$Z$4) -> 1900 | AH6: =SUM(AF6) -> 190 | AI6: =SUM(AH6*$Z$4) -> 1900 | AJ6: =SUM(AH6) -> 190 | AK6: =SUM(AJ6*$Z$4) -> 1900 | AL6: =SUM(AJ6) -> 190 | AM6: =SUM(AL6*$Z$4) -> 1900 | AN6: =SUM(AO6/19600) -> 0.67857143 | AO6: =SUM(AA6+AC6+AE6+AG6+AI6+AK6+AM6) -> 13300 | AQ6: =SUM(AR6/92970) -> 0.60892726 | AR6: =SUM(AO6+Y6) -> 56611.968 | AS6: =SUM(AR6-AR5-AT6) -> -2560.871 | AT6: 15748 | AU6: 0.4624 | AV6: =IF(AT6>0,AU6,AV5) -> 0.4624 | AW6: =-SUM('B5'!AI5) -> -417 | AX6: =-SUM(AW6-AS6) -> -2143.871 | AY6: =SUM(AX6+AW6) -> -2560.871 | AZ6: =ELEC!A3 -> 0.0565 | BA6: ='General information '!D6 -> 26 | BB6: =SUM('General information '!E6) -> 0.7 | BC6: =IF(AR3>=AR6,0,1) -> 0 | BD6: 19222 | BE6: =(305/1185)*ELEC!Q4 -> 3345.9916 | BG6: =#REF!-BE6 -> #REF! | BH6: 21
A7: =ELEC!C4 -> 44014 | B7: ='B5'!B6 -> 165 | C7: =B7*$B$4 -> 3550.1613 | D7: =SUM(B7) -> 165 | E7: =D7*$B$4 -> 3550.1613 | F7: =SUM(D7) -> 165 | G7: =F7*$B$4 -> 3550.1613 | H7: =SUM(F7) -> 165 | I7: =H7*$B$4 -> 3550.1613 | J7: =SUM(H7) -> 165 | K7: =J7*$B$4 -> 3550.1613 | L7: =SUM(J7) -> 165 | M7: =L7*$B$4 -> 3550.1613 | N7: =SUM(L7) -> 165 | O7: =N7*$B$4 -> 3550.1613 | P7: =SUM(N7) -> 165 | Q7: =P7*$B$4 -> 3550.1613 | R7: =SUM(P7) -> 165 | S7: =R7*$B$4 -> 3550.1613 | T7: =SUM(R7) -> 165 | U7: =T7*$B$4 -> 3550.1613 | V7: =SUM(T7) -> 165 | W7: =V7*$B$4 -> 3550.1613 | X7: =SUM(Y7/73370) -> 0.53225806 | Y7: =SUM(C7+E7+G7+I7+K7+M7+O7+Q7+S7+U7+W7) -> 39051.774 | Z7: ='B5'!C6 -> 172 | AA7: =SUM(Z7*$Z$4) -> 1720 | AB7: =SUM(Z7) -> 172 | AC7: =SUM(AB7*$Z$4) -> 1720 | AD7: =SUM(AB7) -> 172 | AE7: =SUM(AD7*$Z$4) -> 1720 | AF7: =SUM(AD7) -> 172 | AG7: =SUM(AF7*$Z$4) -> 1720 | AH7: =SUM(AF7) -> 172 | AI7: =SUM(AH7*$Z$4) -> 1720 | AJ7: =SUM(AH7) -> 172 | AK7: =SUM(AJ7*$Z$4) -> 1720 | AL7: =SUM(AJ7) -> 172 | AM7: =SUM(AL7*$Z$4) -> 1720 | AN7: =SUM(AO7/19600) -> 0.61428571 | AO7: =SUM(AA7+AC7+AE7+AG7+AI7+AK7+AM7) -> 12040 | AQ7: =SUM(AR7/92970) -> 0.54955119 | AR7: =SUM(AO7+Y7) -> 51091.774 | AS7: =SUM(AR7-AR6-AT7) -> -5520.1935 | AV7: =IF(AT7>0,AU7,AV6) -> 0.4624 | AW7: =-SUM('B5'!AI6) -> -735 | AX7: =-SUM(AW7-AS7) -> -4785.1935 | AY7: =SUM(AX7+AW7) -> -5520.1935 | AZ7: =ELEC!A4 -> 0.039 | BA7: ='General information '!D7 -> 26 | BB7: =SUM('General information '!E7) -> 0.62 | BC7: 0 | BD7: 19222 | BE7: =(305/1185)*ELEC!Q5 -> 3603.3755 | BG7: =#REF!-BE7 -> #REF! | BH7: 19
A8: =ELEC!C5 -> 44015 | B8: ='B5'!B7 -> 149 | C8: =B8*$B$4 -> 3205.9032 | D8: =SUM(B8) -> 149 | E8: =D8*$B$4 -> 3205.9032 | F8: =SUM(D8) -> 149 | G8: =F8*$B$4 -> 3205.9032 | H8: =SUM(F8) -> 149 | I8: =H8*$B$4 -> 3205.9032 | J8: =SUM(H8) -> 149 | K8: =J8*$B$4 -> 3205.9032 | L8: =SUM(J8) -> 149 | M8: =L8*$B$4 -> 3205.9032 | N8: =SUM(L8) -> 149 | O8: =N8*$B$4 -> 3205.9032 | P8: =SUM(N8) -> 149 | Q8: =P8*$B$4 -> 3205.9032 | R8: =SUM(P8) -> 149 | S8: =R8*$B$4 -> 3205.9032 | T8: =SUM(R8) -> 149 | U8: =T8*$B$4 -> 3205.9032 | V8: =SUM(T8) -> 149 | W8: =V8*$B$4 -> 3205.9032 | X8: =SUM(Y8/73370) -> 0.48064516 | Y8: =SUM(C8+E8+G8+I8+K8+M8+O8+Q8+S8+U8+W8) -> 35264.935 | Z8: ='B5'!C7 -> 158 | AA8: =SUM(Z8*$Z$4) -> 1580 | AB8: =SUM(Z8) -> 158 | AC8: =SUM(AB8*$Z$4) -> 1580 | AD8: =SUM(AB8) -> 158 | AE8: =SUM(AD8*$Z$4) -> 1580 | AF8: =SUM(AD8) -> 158 | AG8: =SUM(AF8*$Z$4) -> 1580 | AH8: =SUM(AF8) -> 158 | AI8: =SUM(AH8*$Z$4) -> 1580 | AJ8: =SUM(AH8) -> 158 | AK8: =SUM(AJ8*$Z$4) -> 1580 | AL8: =SUM(AJ8) -> 158 | AM8: =SUM(AL8*$Z$4) -> 1580 | AN8: =SUM(AO8/19600) -> 0.56428571 | AO8: =SUM(AA8+AC8+AE8+AG8+AI8+AK8+AM8) -> 11060 | AQ8: =SUM(AR8/92970) -> 0.49827832 | AR8: =SUM(AO8+Y8) -> 46324.935 | AS8: =SUM(AR8-AR7-AT8) -> -4766.8387 | AV8: =IF(AT8>0,AU8,AV7) -> 0.4624 | AW8: =-SUM('B5'!AI7) -> -388 | AX8: =-SUM(AW8-AS8) -> -4378.8387 | AY8: =SUM(AX8+AW8) -> -4766.8387 | AZ8: =ELEC!A5 -> 0.087 | BA8: ='General information '!D8 -> 26.5 | BB8: =SUM('General information '!E8) -> 0.65 | BC8: =IF(AR7>=AR8,0,1) -> 0 | BD8: 19222 | BE8: =(305/1185)*ELEC!Q6 -> 4118.1435 | BG8: =#REF!-BE8 -> #REF! | BH8: 16
A9: =ELEC!C6 -> 44016 | B9: ='B5'!B8 -> 131 | C9: =B9*$B$4 -> 2818.6129 | D9: =SUM(B9) -> 131 | E9: =D9*$B$4 -> 2818.6129 | F9: =SUM(D9) -> 131 | G9: =F9*$B$4 -> 2818.6129 | H9: =SUM(F9) -> 131 | I9: =H9*$B$4 -> 2818.6129 | J9: =SUM(H9) -> 131 | K9: =J9*$B$4 -> 2818.6129 | L9: =SUM(J9) -> 131 | M9: =L9*$B$4 -> 2818.6129 | N9: =SUM(L9) -> 131 | O9: =N9*$B$4 -> 2818.6129 | P9: =SUM(N9) -> 131 | Q9: =P9*$B$4 -> 2818.6129 | R9: =SUM(P9) -> 131 | S9: =R9*$B$4 -> 2818.6129 | T9: =SUM(R9) -> 131 | U9: =T9*$B$4 -> 2818.6129 | V9: =SUM(T9) -> 131 | W9: =V9*$B$4 -> 2818.6129 | X9: =SUM(Y9/73370) -> 0.42258065 | Y9: =SUM(C9+E9+G9+I9+K9+M9+O9+Q9+S9+U9+W9) -> 31004.742 | Z9: ='B5'!C8 -> 141.5 | AA9: =SUM(Z9*$Z$4) -> 1415 | AB9: =SUM(Z9) -> 141.5 | AC9: =SUM(AB9*$Z$4) -> 1415 | AD9: =SUM(AB9) -> 141.5 | AE9: =SUM(AD9*$Z$4) -> 1415 | AF9: =SUM(AD9) -> 141.5 | AG9: =SUM(AF9*$Z$4) -> 1415 | AH9: =SUM(AF9) -> 141.5 | AI9: =SUM(AH9*$Z$4) -> 1415 | AJ9: =SUM(AH9) -> 141.5 | AK9: =SUM(AJ9*$Z$4) -> 1415 | AL9: =SUM(AJ9) -> 141.5 | AM9: =SUM(AL9*$Z$4) -> 1415 | AN9: =SUM(AO9/19600) -> 0.50535714 | AO9: =SUM(AA9+AC9+AE9+AG9+AI9+AK9+AM9) -> 9905 | AQ9: =SUM(AR9/92970) -> 0.44003164 | AR9: =SUM(AO9+Y9) -> 40909.742 | AS9: =SUM(AR9-AR8-AT9) -> -5415.1935 | AV9: =IF(AT9>0,AU9,AV8) -> 0.4624 | AW9: =-SUM('B5'!AI8) -> -534 | AX9: =-SUM(AW9-AS9) -> -4881.1935 | AY9: =SUM(AX9+AW9) -> -5415.1935 | AZ9: =ELEC!A6 -> 0.087 | BA9: ='General information '!D9 -> 26 | BB9: =SUM('General information '!E9) -> 0.66 | BC9: =IF(AR8>=AR9,0,1) -> 0 | BD9: 19222 | BE9: =(305/1185)*ELEC!Q7 -> 3860.7595 | BG9: =#REF!-BE9 -> #REF! | BH9: 18
A10: =ELEC!C7 -> 44017 | B10: ='B5'!B9 -> 113 | C10: =B10*$B$4 -> 2431.3226 | D10: =SUM(B10) -> 113 | E10: =D10*$B$4 -> 2431.3226 | F10: =SUM(D10) -> 113 | G10: =F10*$B$4 -> 2431.3226 | H10: =SUM(F10) -> 113 | I10: =H10*$B$4 -> 2431.3226 | J10: =SUM(H10) -> 113 | K10: =J10*$B$4 -> 2431.3226 | L10: =SUM(J10) -> 113 | M10: =L10*$B$4 -> 2431.3226 | N10: =SUM(L10) -> 113 | O10: =N10*$B$4 -> 2431.3226 | P10: =SUM(N10) -> 113 | Q10: =P10*$B$4 -> 2431.3226 | R10: =SUM(P10) -> 113 | S10: =R10*$B$4 -> 2431.3226 | T10: =SUM(R10) -> 113 | U10: =T10*$B$4 -> 2431.3226 | V10: =SUM(T10) -> 113 | W10: =V10*$B$4 -> 2431.3226 | X10: =SUM(Y10/73370) -> 0.36451613 | Y10: =SUM(C10+E10+G10+I10+K10+M10+O10+Q10+S10+U10+W10) -> 26744.548 | Z10: ='B5'!C9 -> 125 | AA10: =SUM(Z10*$Z$4) -> 1250 | AB10: =SUM(Z10) -> 125 | AC10: =SUM(AB10*$Z$4) -> 1250 | AD10: =SUM(AB10) -> 125 | AE10: =SUM(AD10*$Z$4) -> 1250 | AF10: =SUM(AD10) -> 125 | AG10: =SUM(AF10*$Z$4) -> 1250 | AH10: =SUM(AF10) -> 125 | AI10: =SUM(AH10*$Z$4) -> 1250 | AJ10: =SUM(AH10) -> 125 | AK10: =SUM(AJ10*$Z$4) -> 1250 | AL10: =SUM(AJ10) -> 125 | AM10: =SUM(AL10*$Z$4) -> 1250 | AN10: =SUM(AO10/19600) -> 0.44642857 | AO10: =SUM(AA10+AC10+AE10+AG10+AI10+AK10+AM10) -> 8750 | AQ10: =SUM(AR10/92970) -> 0.38178497 | AR10: =SUM(AO10+Y10) -> 35494.548 | AS10: =SUM(AR10-AR9-AT10) -> -5415.1935 | AV10: =IF(AT10>0,AU10,AV9) -> 0.4624 | AW10: =-SUM('B5'!AI9) -> -338 | AX10: =-SUM(AW10-AS10) -> -5077.1935 | AY10: =SUM(AX10+AW10) -> -5415.1935 | AZ10: =ELEC!A7 -> 0.0783 | BA10: ='General information '!D10 -> 28 | BB10: =SUM('General information '!E10) -> 0.7 | BC10: =IF(AR9>=AR10,0,1) -> 0 | BD10: 19222 | BE10: =(305/1185)*ELEC!Q8 -> 4632.9114 | BG10: =#REF!-BE10 -> #REF! | BH10: 16
A11: =ELEC!C8 -> 44018 | B11: ='B5'!B10 -> 136 | C11: =B11*$B$4 -> 2926.1935 | D11: =SUM(B11) -> 136 | E11: =D11*$B$4 -> 2926.1935 | F11: =SUM(D11) -> 136 | G11: =F11*$B$4 -> 2926.1935 | H11: =SUM(F11) -> 136 | I11: =H11*$B$4 -> 2926.1935 | J11: =SUM(H11) -> 136 | K11: =J11*$B$4 -> 2926.1935 | L11: =SUM(J11) -> 136 | M11: =L11*$B$4 -> 2926.1935 | N11: =SUM(L11) -> 136 | O11: =N11*$B$4 -> 2926.1935 | P11: =SUM(N11) -> 136 | Q11: =P11*$B$4 -> 2926.1935 | R11: =SUM(P11) -> 136 | S11: =R11*$B$4 -> 2926.1935 | T11: =SUM(R11) -> 136 | U11: =T11*$B$4 -> 2926.1935 | V11: =SUM(T11) -> 136 | W11: =V11*$B$4 -> 2926.1935 | X11: =SUM(Y11/73370) -> 0.43870968 | Y11: =SUM(C11+E11+G11+I11+K11+M11+O11+Q11+S11+U11+W11) -> 32188.129 | Z11: ='B5'!C10 -> 143 | AA11: =SUM(Z11*$Z$4) -> 1430 | AB11: =SUM(Z11) -> 143 | AC11: =SUM(AB11*$Z$4) -> 1430 | AD11: =SUM(AB11) -> 143 | AE11: =SUM(AD11*$Z$4) -> 1430 | AF11: =SUM(AD11) -> 143 | AG11: =SUM(AF11*$Z$4) -> 1430 | AH11: =SUM(AF11) -> 143 | AI11: =SUM(AH11*$Z$4) -> 1430 | AJ11: =SUM(AH11) -> 143 | AK11: =SUM(AJ11*$Z$4) -> 1430 | AL11: =SUM(AJ11) -> 143 | AM11: =SUM(AL11*$Z$4) -> 1430 | AN11: =SUM(AO11/19600) -> 0.51071429 | AO11: =SUM(AA11+AC11+AE11+AG11+AI11+AK11+AM11) -> 10010 | AQ11: =SUM(AR11/92970) -> 0.45388974 | AR11: =SUM(AO11+Y11) -> 42198.129 | AS11: =SUM(AR11-AR10-AT11) -> -4633.4194 | AT11: 11337 | AU11: 0.4624 | AV11: =IF(AT11>0,AU11,AV10) -> 0.4624 | AW11: =-SUM('B5'!AI10) -> -430 | AX11: =-SUM(AW11-AS11) -> -4203.4194 | AY11: =SUM(AX11+AW11) -> -4633.4194 | AZ11: =ELEC!A8 -> 0.0826 | BA11: ='General information '!D11 -> 27 | BB11: =SUM('General information '!E11) -> 0.69 | BC11: =IF(AR10>=AR11,0,1) -> 1 | BD11: 19222 | BE11: =(305/1185)*ELEC!Q9 -> 3860.7595 | BG11: =#REF!-BE11 -> #REF! | BH11: 16.5
A12: =ELEC!C9 -> 44019 | B12: ='B5'!B11 -> 118 | C12: =B12*$B$4 -> 2538.9032 | D12: =SUM(B12) -> 118 | E12: =D12*$B$4 -> 2538.9032 | F12: =SUM(D12) -> 118 | G12: =F12*$B$4 -> 2538.9032 | H12: =SUM(F12) -> 118 | I12: =H12*$B$4 -> 2538.9032 | J12: =SUM(H12) -> 118 | K12: =J12*$B$4 -> 2538.9032 | L12: =SUM(J12) -> 118 | M12: =L12*$B$4 -> 2538.9032 | N12: =SUM(L12) -> 118 | O12: =N12*$B$4 -> 2538.9032 | P12: =SUM(N12) -> 118 | Q12: =P12*$B$4 -> 2538.9032 | R12: =SUM(P12) -> 118 | S12: =R12*$B$4 -> 2538.9032 | T12: =SUM(R12) -> 118 | U12: =T12*$B$4 -> 2538.9032 | V12: =SUM(T12) -> 118 | W12: =V12*$B$4 -> 2538.9032 | X12: =SUM(Y12/73370) -> 0.38064516 | Y12: =SUM(C12+E12+G12+I12+K12+M12+O12+Q12+S12+U12+W12) -> 27927.935 | Z12: ='B5'!C11 -> 125.4 | AA12: =SUM(Z12*$Z$4) -> 1254 | AB12: =SUM(Z12) -> 125.4 | AC12: =SUM(AB12*$Z$4) -> 1254 | AD12: =SUM(AB12) -> 125.4 | AE12: =SUM(AD12*$Z$4) -> 1254 | AF12: =SUM(AD12) -> 125.4 | AG12: =SUM(AF12*$Z$4) -> 1254 | AH12: =SUM(AF12) -> 125.4 | AI12: =SUM(AH12*$Z$4) -> 1254 | AJ12: =SUM(AH12) -> 125.4 | AK12: =SUM(AJ12*$Z$4) -> 1254 | AL12: =SUM(AJ12) -> 125.4 | AM12: =SUM(AL12*$Z$4) -> 1254 | AN12: =SUM(AO12/19600) -> 0.44785714 | AO12: =SUM(AA12+AC12+AE12+AG12+AI12+AK12+AM12) -> 8778 | AQ12: =SUM(AR12/92970) -> 0.39481484 | AR12: =SUM(AO12+Y12) -> 36705.935 | AS12: =SUM(AR12-AR11-AT12) -> -5492.1935 | AV12: =IF(AT12>0,AU12,AV11) -> 0.4624 | AW12: =-SUM('B5'!AI11) -> -657 | AX12: =-SUM(AW12-AS12) -> -4835.1935 | AY12: =SUM(AX12+AW12) -> -5492.1935 | AZ12: =ELEC!A9 -> 0.0783 | BA12: ='General information '!D12 -> 26 | BB12: =SUM('General information '!E12) -> 0.68 | BC12: =IF(AR11>=AR12,0,1) -> 0 | BD12: 19222 | BE12: =(305/1185)*ELEC!Q10 -> 3860.7595 | BG12: =#REF!-BE12 -> #REF! | BH12: 15.5
A13: =ELEC!C10 -> 44020 | B13: ='B5'!B12 -> 138.2 | C13: =B13*$B$4 -> 2973.529 | D13: =SUM(B13) -> 138.2 | E13: =D13*$B$4 -> 2973.529 | F13: =SUM(D13) -> 138.2 | G13: =F13*$B$4 -> 2973.529 | H13: =SUM(F13) -> 138.2 | I13: =H13*$B$4 -> 2973.529 | J13: =SUM(H13) -> 138.2 | K13: =J13*$B$4 -> 2973.529 | L13: =SUM(J13) -> 138.2 | M13: =L13*$B$4 -> 2973.529 | N13: =SUM(L13) -> 138.2 | O13: =N13*$B$4 -> 2973.529 | P13: =SUM(N13) -> 138.2 | Q13: =P13*$B$4 -> 2973.529 | R13: =SUM(P13) -> 138.2 | S13: =R13*$B$4 -> 2973.529 | T13: =SUM(R13) -> 138.2 | U13: =T13*$B$4 -> 2973.529 | V13: =SUM(T13) -> 138.2 | W13: =V13*$B$4 -> 2973.529 | X13: =SUM(Y13/73370) -> 0.44580645 | Y13: =SUM(C13+E13+G13+I13+K13+M13+O13+Q13+S13+U13+W13) -> 32708.819 | Z13: ='B5'!C12 -> 145.3 | AA13: =SUM(Z13*$Z$4) -> 1453 | AB13: =SUM(Z13) -> 145.3 | AC13: =SUM(AB13*$Z$4) -> 1453 | AD13: =SUM(AB13) -> 145.3 | AE13: =SUM(AD13*$Z$4) -> 1453 | AF13: =SUM(AD13) -> 145.3 | AG13: =SUM(AF13*$Z$4) -> 1453 | AH13: =SUM(AF13) -> 145.3 | AI13: =SUM(AH13*$Z$4) -> 1453 | AJ13: =SUM(AH13) -> 145.3 | AK13: =SUM(AJ13*$Z$4) -> 1453 | AL13: =SUM(AJ13) -> 145.3 | AM13: =SUM(AL13*$Z$4) -> 1453 | AN13: =SUM(AO13/19600) -> 0.51892857 | AO13: =SUM(AA13+AC13+AE13+AG13+AI13+AK13+AM13) -> 10171 | AQ13: =SUM(AR13/92970) -> 0.46122211 | AR13: =SUM(AO13+Y13) -> 42879.819 | AS13: =SUM(AR13-AR12-AT13) -> -5102.1161 | AT13: 11276 | AU13: 0.5284 | AV13: =IF(AT13>0,AU13,AV12) -> 0.5284 | AW13: =-SUM('B5'!AI12) -> -512 | AX13: =-SUM(AW13-AS13) -> -4590.1161 | AY13: =SUM(AX13+AW13) -> -5102.1161 | AZ13: =ELEC!A10 -> 0.087 | BA13: ='General information '!D13 -> 26 | BB13: =SUM('General information '!E13) -> 0.7 | BC13: =IF(AR12>=AR13,0,1) -> 1 | BD13: 19222 | BE13: =(305/1185)*ELEC!Q11 -> 5147.6793 | BG13: =#REF!-BE13 -> #REF!
A14: =ELEC!C11 -> 44021 | B14: ='B5'!B13 -> 120.3 | C14: =B14*$B$4 -> 2588.3903 | D14: =SUM(B14) -> 120.3 | E14: =D14*$B$4 -> 2588.3903 | F14: =SUM(D14) -> 120.3 | G14: =F14*$B$4 -> 2588.3903 | H14: =SUM(F14) -> 120.3 | I14: =H14*$B$4 -> 2588.3903 | J14: =SUM(H14) -> 120.3 | K14: =J14*$B$4 -> 2588.3903 | L14: =SUM(J14) -> 120.3 | M14: =L14*$B$4 -> 2588.3903 | N14: =SUM(L14) -> 120.3 | O14: =N14*$B$4 -> 2588.3903 | P14: =SUM(N14) -> 120.3 | Q14: =P14*$B$4 -> 2588.3903 | R14: =SUM(P14) -> 120.3 | S14: =R14*$B$4 -> 2588.3903 | T14: =SUM(R14) -> 120.3 | U14: =T14*$B$4 -> 2588.3903 | V14: =SUM(T14) -> 120.3 | W14: =V14*$B$4 -> 2588.3903 | X14: =SUM(Y14/73370) -> 0.38806452 | Y14: =SUM(C14+E14+G14+I14+K14+M14+O14+Q14+S14+U14+W14) -> 28472.294 | Z14: ='B5'!C13 -> 127.2 | AA14: =SUM(Z14*$Z$4) -> 1272 | AB14: =SUM(Z14) -> 127.2 | AC14: =SUM(AB14*$Z$4) -> 1272 | AD14: =SUM(AB14) -> 127.2 | AE14: =SUM(AD14*$Z$4) -> 1272 | AF14: =SUM(AD14) -> 127.2 | AG14: =SUM(AF14*$Z$4) -> 1272 | AH14: =SUM(AF14) -> 127.2 | AI14: =SUM(AH14*$Z$4) -> 1272 | AJ14: =SUM(AH14) -> 127.2 | AK14: =SUM(AJ14*$Z$4) -> 1272 | AL14: =SUM(AJ14) -> 127.2 | AM14: =SUM(AL14*$Z$4) -> 1272 | AN14: =SUM(AO14/19600) -> 0.45428571 | AO14: =SUM(AA14+AC14+AE14+AG14+AI14+AK14+AM14) -> 8904 | AQ14: =SUM(AR14/92970) -> 0.40202532 | AR14: =SUM(AO14+Y14) -> 37376.294 | AS14: =SUM(AR14-AR13-AT14) -> -5503.5258 | AV14: =IF(AT14>0,AU14,AV13) -> 0.5284 | AW14: =-SUM('B5'!AI13) -> -256 | AX14: =-SUM(AW14-AS14) -> -5247.5258 | AY14: =SUM(AX14+AW14) -> -5503.5258 | AZ14: =ELEC!A11 -> 0.1087 | BA14: ='General information '!D14 -> 26 | BB14: =SUM('General information '!E14) -> 0.65 | BC14: =IF(AR13>=AR14,0,1) -> 0 | BD14: 19222 | BE14: =(305/1185)*ELEC!Q12 -> 4375.5274 | BG14: =#REF!-BE14 -> #REF!
A15: =ELEC!C12 -> 44022 | B15: ='B5'!B14 -> 178.2 | C15: =B15*$B$4 -> 3834.1742 | D15: =SUM(B15) -> 178.2 | E15: =D15*$B$4 -> 3834.1742 | F15: =SUM(D15) -> 178.2 | G15: =F15*$B$4 -> 3834.1742 | H15: =SUM(F15) -> 178.2 | I15: =H15*$B$4 -> 3834.1742 | J15: =SUM(H15) -> 178.2 | K15: =J15*$B$4 -> 3834.1742 | L15: =SUM(J15) -> 178.2 | M15: =L15*$B$4 -> 3834.1742 | N15: =SUM(L15) -> 178.2 | O15: =N15*$B$4 -> 3834.1742 | P15: =SUM(N15) -> 178.2 | Q15: =P15*$B$4 -> 3834.1742 | R15: =SUM(P15) -> 178.2 | S15: =R15*$B$4 -> 3834.1742 | T15: =SUM(R15) -> 178.2 | U15: =T15*$B$4 -> 3834.1742 | V15: =SUM(T15) -> 178.2 | W15: =V15*$B$4 -> 3834.1742 | X15: =SUM(Y15/73370) -> 0.57483871 | Y15: =SUM(C15+E15+G15+I15+K15+M15+O15+Q15+S15+U15+W15) -> 42175.916 | Z15: ='B5'!C14 -> 185 | AA15: =SUM(Z15*$Z$4) -> 1850 | AB15: =SUM(Z15) -> 185 | AC15: =SUM(AB15*$Z$4) -> 1850 | AD15: =SUM(AB15) -> 185 | AE15: =SUM(AD15*$Z$4) -> 1850 | AF15: =SUM(AD15) -> 185 | AG15: =SUM(AF15*$Z$4) -> 1850 | AH15: =SUM(AF15) -> 185 | AI15: =SUM(AH15*$Z$4) -> 1850 | AJ15: =SUM(AH15) -> 185 | AK15: =SUM(AJ15*$Z$4) -> 1850 | AL15: =SUM(AJ15) -> 185 | AM15: =SUM(AL15*$Z$4) -> 1850 | AN15: =SUM(AO15/19600) -> 0.66071429 | AO15: =SUM(AA15+AC15+AE15+AG15+AI15+AK15+AM15) -> 12950 | AQ15: =SUM(AR15/92970) -> 0.59294306 | AR15: =SUM(AO15+Y15) -> 55125.916 | AS15: =SUM(AR15-AR14-AT15) -> -2293.3774 | AT15: 20043 | AU15: 0.5284 | AV15: =IF(AT15>0,AU15,AV14) -> 0.5284 | AW15: =-SUM('B5'!AI14) -> -342.8 | AX15: =-SUM(AW15-AS15) -> -1950.5774 | AY15: =SUM(AX15+AW15) -> -2293.3774 | AZ15: =ELEC!A12 -> 0.113 | BA15: ='General information '!D15 -> 26 | BB15: =SUM('General information '!E15) -> 0.7 | BC15: =IF(AR14>=AR15,0,1) -> 1 | BD15: 19222 | BE15: =(305/1185)*ELEC!Q13 -> 4632.9114 | BG15: =#REF!-BE15 -> #REF!
A16: =ELEC!C13 -> 44023 | B16: ='B5'!B15 -> 159 | C16: =B16*$B$4 -> 3421.0645 | D16: =SUM(B16) -> 159 | E16: =D16*$B$4 -> 3421.0645 | F16: =SUM(D16) -> 159 | G16: =F16*$B$4 -> 3421.0645 | H16: =SUM(F16) -> 159 | I16: =H16*$B$4 -> 3421.0645 | J16: =SUM(H16) -> 159 | K16: =J16*$B$4 -> 3421.0645 | L16: =SUM(J16) -> 159 | M16: =L16*$B$4 -> 3421.0645 | N16: =SUM(L16) -> 159 | O16: =N16*$B$4 -> 3421.0645 | P16: =SUM(N16) -> 159 | Q16: =P16*$B$4 -> 3421.0645 | R16: =SUM(P16) -> 159 | S16: =R16*$B$4 -> 3421.0645 | T16: =SUM(R16) -> 159 | U16: =T16*$B$4 -> 3421.0645 | V16: =SUM(T16) -> 159 | W16: =V16*$B$4 -> 3421.0645 | X16: =SUM(Y16/73370) -> 0.51290323 | Y16: =SUM(C16+E16+G16+I16+K16+M16+O16+Q16+S16+U16+W16) -> 37631.71 | Z16: ='B5'!C15 -> 166 | AA16: =SUM(Z16*$Z$4) -> 1660 | AB16: =SUM(Z16) -> 166 | AC16: =SUM(AB16*$Z$4) -> 1660 | AD16: =SUM(AB16) -> 166 | AE16: =SUM(AD16*$Z$4) -> 1660 | AF16: =SUM(AD16) -> 166 | AG16: =SUM(AF16*$Z$4) -> 1660 | AH16: =SUM(AF16) -> 166 | AI16: =SUM(AH16*$Z$4) -> 1660 | AJ16: =SUM(AH16) -> 166 | AK16: =SUM(AJ16*$Z$4) -> 1660 | AL16: =SUM(AJ16) -> 166 | AM16: =SUM(AL16*$Z$4) -> 1660 | AN16: =SUM(AO16/19600) -> 0.59285714 | AO16: =SUM(AA16+AC16+AE16+AG16+AI16+AK16+AM16) -> 11620 | AQ16: =SUM(AR16/92970) -> 0.52975917 | AR16: =SUM(AO16+Y16) -> 49251.71 | AS16: =SUM(AR16-AR15-AT16) -> -5874.2065 | AV16: =IF(AT16>0,AU16,AV15) -> 0.5284 | AW16: =-SUM('B5'!AI15) -> -335 | AX16: =-SUM(AW16-AS16) -> -5539.2065 | AY16: =SUM(AX16+AW16) -> -5874.2065 | AZ16: =ELEC!A13 -> 0.165 | BA16: ='General information '!D16 -> 28 | BB16: =SUM('General information '!E16) -> 0.56 | BC16: =IF(AR15>=AR16,0,1) -> 0 | BD16: 19222 | BE16: =(305/1185)*ELEC!Q14 -> 4890.2954 | BG16: =#REF!-BE16 -> #REF!
A17: =ELEC!C14 -> 44024 | B17: ='B5'!B16 -> 139 | C17: =B17*$B$4 -> 2990.7419 | D17: =SUM(B17) -> 139 | E17: =D17*$B$4 -> 2990.7419 | F17: =SUM(D17) -> 139 | G17: =F17*$B$4 -> 2990.7419 | H17: =SUM(F17) -> 139 | I17: =H17*$B$4 -> 2990.7419 | J17: =SUM(H17) -> 139 | K17: =J17*$B$4 -> 2990.7419 | L17: =SUM(J17) -> 139 | M17: =L17*$B$4 -> 2990.7419 | N17: =SUM(L17) -> 139 | O17: =N17*$B$4 -> 2990.7419 | P17: =SUM(N17) -> 139 | Q17: =P17*$B$4 -> 2990.7419 | R17: =SUM(P17) -> 139 | S17: =R17*$B$4 -> 2990.7419 | T17: =SUM(R17) -> 139 | U17: =T17*$B$4 -> 2990.7419 | V17: =SUM(T17) -> 139 | W17: =V17*$B$4 -> 2990.7419 | X17: =SUM(Y17/73370) -> 0.4483871 | Y17: =SUM(C17+E17+G17+I17+K17+M17+O17+Q17+S17+U17+W17) -> 32898.161 | Z17: ='B5'!C16 -> 146 | AA17: =SUM(Z17*$Z$4) -> 1460 | AB17: =SUM(Z17) -> 146 | AC17: =SUM(AB17*$Z$4) -> 1460 | AD17: =SUM(AB17) -> 146 | AE17: =SUM(AD17*$Z$4) -> 1460 | AF17: =SUM(AD17) -> 146 | AG17: =SUM(AF17*$Z$4) -> 1460 | AH17: =SUM(AF17) -> 146 | AI17: =SUM(AH17*$Z$4) -> 1460 | AJ17: =SUM(AH17) -> 146 | AK17: =SUM(AJ17*$Z$4) -> 1460 | AL17: =SUM(AJ17) -> 146 | AM17: =SUM(AL17*$Z$4) -> 1460 | AN17: =SUM(AO17/19600) -> 0.52142857 | AO17: =SUM(AA17+AC17+AE17+AG17+AI17+AK17+AM17) -> 10220 | AQ17: =SUM(AR17/92970) -> 0.46378575 | AR17: =SUM(AO17+Y17) -> 43118.161 | AS17: =SUM(AR17-AR16-AT17) -> -6133.5484 | AV17: =IF(AT17>0,AU17,AV16) -> 0.5284 | AW17: =-SUM('B5'!AI16) -> -220 | AX17: =-SUM(AW17-AS17) -> -5913.5484 | AY17: =SUM(AX17+AW17) -> -6133.5484 | AZ17: =ELEC!A14 -> 0.1 | BA17: ='General information '!D17 -> 26 | BB17: =SUM('General information '!E17) -> 0.62 | BC17: =IF(AR16>=AR17,0,1) -> 0 | BD17: 19222 | BE17: =(305/1185)*ELEC!Q15 -> 3603.3755 | BG17: =#REF!-BE17 -> #REF!
A18: =ELEC!C15 -> 44025 | B18: ='B5'!B17 -> 122.2 | C18: =B18*$B$4 -> 2629.271 | D18: =SUM(B18) -> 122.2 | E18: =D18*$B$4 -> 2629.271 | F18: =SUM(D18) -> 122.2 | G18: =F18*$B$4 -> 2629.271 | H18: =SUM(F18) -> 122.2 | I18: =H18*$B$4 -> 2629.271 | J18: =SUM(H18) -> 122.2 | K18: =J18*$B$4 -> 2629.271 | L18: =SUM(J18) -> 122.2 | M18: =L18*$B$4 -> 2629.271 | N18: =SUM(L18) -> 122.2 | O18: =N18*$B$4 -> 2629.271 | P18: =SUM(N18) -> 122.2 | Q18: =P18*$B$4 -> 2629.271 | R18: =SUM(P18) -> 122.2 | S18: =R18*$B$4 -> 2629.271 | T18: =SUM(R18) -> 122.2 | U18: =T18*$B$4 -> 2629.271 | V18: =SUM(T18) -> 122.2 | W18: =V18*$B$4 -> 2629.271 | X18: =SUM(Y18/73370) -> 0.39419355 | Y18: =SUM(C18+E18+G18+I18+K18+M18+O18+Q18+S18+U18+W18) -> 28921.981 | Z18: ='B5'!C17 -> 129 | AA18: =SUM(Z18*$Z$4) -> 1290 | AB18: =SUM(Z18) -> 129 | AC18: =SUM(AB18*$Z$4) -> 1290 | AD18: =SUM(AB18) -> 129 | AE18: =SUM(AD18*$Z$4) -> 1290 | AF18: =SUM(AD18) -> 129 | AG18: =SUM(AF18*$Z$4) -> 1290 | AH18: =SUM(AF18) -> 129 | AI18: =SUM(AH18*$Z$4) -> 1290 | AJ18: =SUM(AH18) -> 129 | AK18: =SUM(AJ18*$Z$4) -> 1290 | AL18: =SUM(AJ18) -> 129 | AM18: =SUM(AL18*$Z$4) -> 1290 | AN18: =SUM(AO18/19600) -> 0.46071429 | AO18: =SUM(AA18+AC18+AE18+AG18+AI18+AK18+AM18) -> 9030 | AQ18: =SUM(AR18/92970) -> 0.4082175 | AR18: =SUM(AO18+Y18) -> 37951.981 | AS18: =SUM(AR18-AR17-AT18) -> -5166.1806 | AV18: =IF(AT18>0,AU18,AV17) -> 0.5284 | AW18: =-SUM('B5'!AI17) -> -165 | AX18: =-SUM(AW18-AS18) -> -5001.1806 | AY18: =SUM(AX18+AW18) -> -5166.1806 | AZ18: =ELEC!A15 -> 0.1217 | BA18: ='General information '!D18 -> 26.5 | BB18: =SUM('General information '!E18) -> 0.65 | BC18: =IF(AR17>=AR18,0,1) -> 0 | BD18: 19222 | BE18: =(305/1185)*ELEC!Q16 -> 4632.9114 | BG18: =#REF!-BE18 -> #REF!
A19: =ELEC!C16 -> 44026 | B19: ='B5'!B18 -> 137 | C19: =B19*$B$4 -> 2947.7097 | D19: =SUM(B19) -> 137 | E19: =D19*$B$4 -> 2947.7097 | F19: =SUM(D19) -> 137 | G19: =F19*$B$4 -> 2947.7097 | H19: =SUM(F19) -> 137 | I19: =H19*$B$4 -> 2947.7097 | J19: =SUM(H19) -> 137 | K19: =J19*$B$4 -> 2947.7097 | L19: =SUM(J19) -> 137 | M19: =L19*$B$4 -> 2947.7097 | N19: =SUM(L19) -> 137 | O19: =N19*$B$4 -> 2947.7097 | P19: =SUM(N19) -> 137 | Q19: =P19*$B$4 -> 2947.7097 | R19: =SUM(P19) -> 137 | S19: =R19*$B$4 -> 2947.7097 | T19: =SUM(R19) -> 137 | U19: =T19*$B$4 -> 2947.7097 | V19: =SUM(T19) -> 137 | W19: =V19*$B$4 -> 2947.7097 | X19: =SUM(Y19/73370) -> 0.44193548 | Y19: =SUM(C19+E19+G19+I19+K19+M19+O19+Q19+S19+U19+W19) -> 32424.806 | Z19: ='B5'!C18 -> 144 | AA19: =SUM(Z19*$Z$4) -> 1440 | AB19: =SUM(Z19) -> 144 | AC19: =SUM(AB19*$Z$4) -> 1440 | AD19: =SUM(AB19) -> 144 | AE19: =SUM(AD19*$Z$4) -> 1440 | AF19: =SUM(AD19) -> 144 | AG19: =SUM(AF19*$Z$4) -> 1440 | AH19: =SUM(AF19) -> 144 | AI19: =SUM(AH19*$Z$4) -> 1440 | AJ19: =SUM(AH19) -> 144 | AK19: =SUM(AJ19*$Z$4) -> 1440 | AL19: =SUM(AJ19) -> 144 | AM19: =SUM(AL19*$Z$4) -> 1440 | AN19: =SUM(AO19/19600) -> 0.51428571 | AO19: =SUM(AA19+AC19+AE19+AG19+AI19+AK19+AM19) -> 10080 | AQ19: =SUM(AR19/92970) -> 0.45718841 | AR19: =SUM(AO19+Y19) -> 42504.806 | AS19: =SUM(AR19-AR18-AT19) -> -4216.1742 | AT19: 8769 | AU19: 0.5284 | AV19: =IF(AT19>0,AU19,AV18) -> 0.5284 | AW19: =-SUM('B5'!AI18) -> -434.1 | AX19: =-SUM(AW19-AS19) -> -3782.0742 | AY19: =SUM(AX19+AW19) -> -4216.1742 | AZ19: =ELEC!A16 -> 0.1271 | BA19: ='General information '!D19 -> 27.5 | BB19: =SUM('General information '!E19) -> 0.65 | BC19: =IF(AR18>=AR19,0,1) -> 1 | BD19: 19222 | BE19: =(305/1185)*ELEC!Q17 -> 4375.5274 | BG19: =#REF!-BE19 -> #REF!
A20: =ELEC!C17 -> 44027 | B20: ='B5'!B19 -> 118.2 | C20: =B20*$B$4 -> 2543.2065 | D20: =SUM(B20) -> 118.2 | E20: =D20*$B$4 -> 2543.2065 | F20: =SUM(D20) -> 118.2 | G20: =F20*$B$4 -> 2543.2065 | H20: =SUM(F20) -> 118.2 | I20: =H20*$B$4 -> 2543.2065 | J20: =SUM(H20) -> 118.2 | K20: =J20*$B$4 -> 2543.2065 | L20: =SUM(J20) -> 118.2 | M20: =L20*$B$4 -> 2543.2065 | N20: =SUM(L20) -> 118.2 | O20: =N20*$B$4 -> 2543.2065 | P20: =SUM(N20) -> 118.2 | Q20: =P20*$B$4 -> 2543.2065 | R20: =SUM(P20) -> 118.2 | S20: =R20*$B$4 -> 2543.2065 | T20: =SUM(R20) -> 118.2 | U20: =T20*$B$4 -> 2543.2065 | V20: =SUM(T20) -> 118.2 | W20: =V20*$B$4 -> 2543.2065 | X20: =SUM(Y20/73370) -> 0.38129032 | Y20: =SUM(C20+E20+G20+I20+K20+M20+O20+Q20+S20+U20+W20) -> 27975.271 | Z20: ='B5'!C19 -> 125.2 | AA20: =SUM(Z20*$Z$4) -> 1252 | AB20: =SUM(Z20) -> 125.2 | AC20: =SUM(AB20*$Z$4) -> 1252 | AD20: =SUM(AB20) -> 125.2 | AE20: =SUM(AD20*$Z$4) -> 1252 | AF20: =SUM(AD20) -> 125.2 | AG20: =SUM(AF20*$Z$4) -> 1252 | AH20: =SUM(AF20) -> 125.2 | AI20: =SUM(AH20*$Z$4) -> 1252 | AJ20: =SUM(AH20) -> 125.2 | AK20: =SUM(AJ20*$Z$4) -> 1252 | AL20: =SUM(AJ20) -> 125.2 | AM20: =SUM(AL20*$Z$4) -> 1252 | AN20: =SUM(AO20/19600) -> 0.44714286 | AO20: =SUM(AA20+AC20+AE20+AG20+AI20+AK20+AM20) -> 8764 | AQ20: =SUM(AR20/92970) -> 0.3951734 | AR20: =SUM(AO20+Y20) -> 36739.271 | AS20: =SUM(AR20-AR19-AT20) -> -5765.5355 | AV20: =IF(AT20>0,AU20,AV19) -> 0.5284 | AW20: =-SUM('B5'!AI19) -> -452 | AX20: =-SUM(AW20-AS20) -> -5313.5355 | AY20: =SUM(AX20+AW20) -> -5765.5355 | AZ20: =ELEC!A17 -> 0.1348 | BA20: ='General information '!D20 -> 26.5 | BB20: =SUM('General information '!E20) -> 0.66 | BC20: =IF(AR19>=AR20,0,1) -> 0 | BD20: 19222 | BE20: =(305/1185)*ELEC!Q18 -> 4890.2954 | BG20: =#REF!-BE20 -> #REF!
A21: =ELEC!C18 -> 44028 | B21: ='B5'!B20 -> 171.3 | C21: =B21*$B$4 -> 3685.7129 | D21: =SUM(B21) -> 171.3 | E21: =D21*$B$4 -> 3685.7129 | F21: =SUM(D21) -> 171.3 | G21: =F21*$B$4 -> 3685.7129 | H21: =SUM(F21) -> 171.3 | I21: =H21*$B$4 -> 3685.7129 | J21: =SUM(H21) -> 171.3 | K21: =J21*$B$4 -> 3685.7129 | L21: =SUM(J21) -> 171.3 | M21: =L21*$B$4 -> 3685.7129 | N21: =SUM(L21) -> 171.3 | O21: =N21*$B$4 -> 3685.7129 | P21: =SUM(N21) -> 171.3 | Q21: =P21*$B$4 -> 3685.7129 | R21: =SUM(P21) -> 171.3 | S21: =R21*$B$4 -> 3685.7129 | T21: =SUM(R21) -> 171.3 | U21: =T21*$B$4 -> 3685.7129 | V21: =SUM(T21) -> 171.3 | W21: =V21*$B$4 -> 3685.7129 | X21: =SUM(Y21/73370) -> 0.55258065 | Y21: =SUM(C21+E21+G21+I21+K21+M21+O21+Q21+S21+U21+W21) -> 40542.842 | Z21: ='B5'!C20 -> 178 | AA21: =SUM(Z21*$Z$4) -> 1780 | AB21: =SUM(Z21) -> 178 | AC21: =SUM(AB21*$Z$4) -> 1780 | AD21: =SUM(AB21) -> 178 | AE21: =SUM(AD21*$Z$4) -> 1780 | AF21: =SUM(AD21) -> 178 | AG21: =SUM(AF21*$Z$4) -> 1780 | AH21: =SUM(AF21) -> 178 | AI21: =SUM(AH21*$Z$4) -> 1780 | AJ21: =SUM(AH21) -> 178 | AK21: =SUM(AJ21*$Z$4) -> 1780 | AL21: =SUM(AJ21) -> 178 | AM21: =SUM(AL21*$Z$4) -> 1780 | AN21: =SUM(AO21/19600) -> 0.63571429 | AO21: =SUM(AA21+AC21+AE21+AG21+AI21+AK21+AM21) -> 12460 | AQ21: =SUM(AR21/92970) -> 0.57010694 | AR21: =SUM(AO21+Y21) -> 53002.842 | AS21: =SUM(AR21-AR20-AT21) -> -3442.429 | AT21: 19706 | AU21: 0.5383 | AV21: =IF(AT21>0,AU21,AV20) -> 0.5383 | AW21: =-SUM('B5'!AI20) -> -257 | AX21: =-SUM(AW21-AS21) -> -3185.429 | AY21: =SUM(AX21+AW21) -> -3442.429 | AZ21: =ELEC!A18 -> 0.2 | BA21: ='General information '!D21 -> 27.5 | BB21: =SUM('General information '!E21) -> 0.68 | BC21: =IF(AR20>=AR21,0,1) -> 1 | BD21: 19222 | BE21: =(305/1185)*ELEC!Q19 -> 0 | BG21: =#REF!-BE21 -> #REF!
A22: =ELEC!C19 -> 44029 | B22: ='B5'!B21 -> 171.3 | C22: =B22*$B$4 -> 3685.7129 | D22: =SUM(B22) -> 171.3 | E22: =D22*$B$4 -> 3685.7129 | F22: =SUM(D22) -> 171.3 | G22: =F22*$B$4 -> 3685.7129 | H22: =SUM(F22) -> 171.3 | I22: =H22*$B$4 -> 3685.7129 | J22: =SUM(H22) -> 171.3 | K22: =J22*$B$4 -> 3685.7129 | L22: =SUM(J22) -> 171.3 | M22: =L22*$B$4 -> 3685.7129 | N22: =SUM(L22) -> 171.3 | O22: =N22*$B$4 -> 3685.7129 | P22: =SUM(N22) -> 171.3 | Q22: =P22*$B$4 -> 3685.7129 | R22: =SUM(P22) -> 171.3 | S22: =R22*$B$4 -> 3685.7129 | T22: =SUM(R22) -> 171.3 | U22: =T22*$B$4 -> 3685.7129 | V22: =SUM(T22) -> 171.3 | W22: =V22*$B$4 -> 3685.7129 | X22: =SUM(Y22/73370) -> 0.55258065 | Y22: =SUM(C22+E22+G22+I22+K22+M22+O22+Q22+S22+U22+W22) -> 40542.842 | Z22: ='B5'!C21 -> 178 | AA22: =SUM(Z22*$Z$4) -> 1780 | AB22: =SUM(Z22) -> 178 | AC22: =SUM(AB22*$Z$4) -> 1780 | AD22: =SUM(AB22) -> 178 | AE22: =SUM(AD22*$Z$4) -> 1780 | AF22: =SUM(AD22) -> 178 | AG22: =SUM(AF22*$Z$4) -> 1780 | AH22: =SUM(AF22) -> 178 | AI22: =SUM(AH22*$Z$4) -> 1780 | AJ22: =SUM(AH22) -> 178 | AK22: =SUM(AJ22*$Z$4) -> 1780 | AL22: =SUM(AJ22) -> 178 | AM22: =SUM(AL22*$Z$4) -> 1780 | AN22: =SUM(AO22/19600) -> 0.63571429 | AO22: =SUM(AA22+AC22+AE22+AG22+AI22+AK22+AM22) -> 12460 | AQ22: =SUM(AR22/92970) -> 0.57010694 | AR22: =SUM(AO22+Y22) -> 53002.842 | AS22: =SUM(AR22-AR21-AT22) -> 0 | AV22: =IF(AT22>0,AU22,AV21) -> 0.5383 | AW22: =-SUM('B5'!AI21) -> 0 | AX22: =-SUM(AW22-AS22) -> 0 | AY22: =SUM(AX22+AW22) -> 0 | AZ22: =ELEC!A19 -> 0 | BA22: ='General information '!D22 -> 0 | BB22: =SUM('General information '!E22) -> 0 | BC22: =IF(AR21>=AR22,0,1) -> 0 | BD22: 19222 | BE22: =(305/1185)*ELEC!Q20 -> 0 | BG22: =#REF!-BE22 -> #REF!
A23: =ELEC!C20 -> 44030 | B23: ='B5'!B22 -> 171.3 | C23: =B23*$B$4 -> 3685.7129 | D23: =SUM(B23) -> 171.3 | E23: =D23*$B$4 -> 3685.7129 | F23: =SUM(D23) -> 171.3 | G23: =F23*$B$4 -> 3685.7129 | H23: =SUM(F23) -> 171.3 | I23: =H23*$B$4 -> 3685.7129 | J23: =SUM(H23) -> 171.3 | K23: =J23*$B$4 -> 3685.7129 | L23: =SUM(J23) -> 171.3 | M23: =L23*$B$4 -> 3685.7129 | N23: =SUM(L23) -> 171.3 | O23: =N23*$B$4 -> 3685.7129 | P23: =SUM(N23) -> 171.3 | Q23: =P23*$B$4 -> 3685.7129 | R23: =SUM(P23) -> 171.3 | S23: =R23*$B$4 -> 3685.7129 | T23: =SUM(R23) -> 171.3 | U23: =T23*$B$4 -> 3685.7129 | V23: =SUM(T23) -> 171.3 | W23: =V23*$B$4 -> 3685.7129 | X23: =SUM(Y23/73370) -> 0.55258065 | Y23: =SUM(C23+E23+G23+I23+K23+M23+O23+Q23+S23+U23+W23) -> 40542.842 | Z23: ='B5'!C22 -> 178 | AA23: =SUM(Z23*$Z$4) -> 1780 | AB23: =SUM(Z23) -> 178 | AC23: =SUM(AB23*$Z$4) -> 1780 | AD23: =SUM(AB23) -> 178 | AE23: =SUM(AD23*$Z$4) -> 1780 | AF23: =SUM(AD23) -> 178 | AG23: =SUM(AF23*$Z$4) -> 1780 | AH23: =SUM(AF23) -> 178 | AI23: =SUM(AH23*$Z$4) -> 1780 | AJ23: =SUM(AH23) -> 178 | AK23: =SUM(AJ23*$Z$4) -> 1780 | AL23: =SUM(AJ23) -> 178 | AM23: =SUM(AL23*$Z$4) -> 1780 | AN23: =SUM(AO23/19600) -> 0.63571429 | AO23: =SUM(AA23+AC23+AE23+AG23+AI23+AK23+AM23) -> 12460 | AQ23: =SUM(AR23/92970) -> 0.57010694 | AR23: =SUM(AO23+Y23) -> 53002.842 | AS23: =SUM(AR23-AR22-AT23) -> 0 | AV23: =IF(AT23>0,AU23,AV22) -> 0.5383 | AW23: =-SUM('B5'!AI22) -> 0 | AX23: =-SUM(AW23-AS23) -> 0 | AY23: =SUM(AX23+AW23) -> 0 | AZ23: =ELEC!A20 -> 0 | BA23: ='General information '!D23 -> 0 | BB23: =SUM('General information '!E23) -> 0 | BC23: =IF(AR22>=AR23,0,1) -> 0 | BD23: 19222 | BE23: =(305/1185)*ELEC!Q21 -> 0 | BG23: =#REF!-BE23 -> #REF!
A24: =ELEC!C21 -> 44031 | B24: ='B5'!B23 -> 171.3 | C24: =B24*$B$4 -> 3685.7129 | D24: =SUM(B24) -> 171.3 | E24: =D24*$B$4 -> 3685.7129 | F24: =SUM(D24) -> 171.3 | G24: =F24*$B$4 -> 3685.7129 | H24: =SUM(F24) -> 171.3 | I24: =H24*$B$4 -> 3685.7129 | J24: =SUM(H24) -> 171.3 | K24: =J24*$B$4 -> 3685.7129 | L24: =SUM(J24) -> 171.3 | M24: =L24*$B$4 -> 3685.7129 | N24: =SUM(L24) -> 171.3 | O24: =N24*$B$4 -> 3685.7129 | P24: =SUM(N24) -> 171.3 | Q24: =P24*$B$4 -> 3685.7129 | R24: =SUM(P24) -> 171.3 | S24: =R24*$B$4 -> 3685.7129 | T24: =SUM(R24) -> 171.3 | U24: =T24*$B$4 -> 3685.7129 | V24: =SUM(T24) -> 171.3 | W24: =V24*$B$4 -> 3685.7129 | X24: =SUM(Y24/73370) -> 0.55258065 | Y24: =SUM(C24+E24+G24+I24+K24+M24+O24+Q24+S24+U24+W24) -> 40542.842 | Z24: ='B5'!C23 -> 178 | AA24: =SUM(Z24*$Z$4) -> 1780 | AB24: =SUM(Z24) -> 178 | AC24: =SUM(AB24*$Z$4) -> 1780 | AD24: =SUM(AB24) -> 178 | AE24: =SUM(AD24*$Z$4) -> 1780 | AF24: =SUM(AD24) -> 178 | AG24: =SUM(AF24*$Z$4) -> 1780 | AH24: =SUM(AF24) -> 178 | AI24: =SUM(AH24*$Z$4) -> 1780 | AJ24: =SUM(AH24) -> 178 | AK24: =SUM(AJ24*$Z$4) -> 1780 | AL24: =SUM(AJ24) -> 178 | AM24: =SUM(AL24*$Z$4) -> 1780 | AN24: =SUM(AO24/19600) -> 0.63571429 | AO24: =SUM(AA24+AC24+AE24+AG24+AI24+AK24+AM24) -> 12460 | AQ24: =SUM(AR24/92970) -> 0.57010694 | AR24: =SUM(AO24+Y24) -> 53002.842 | AS24: =SUM(AR24-AR23-AT24) -> 0 | AV24: =IF(AT24>0,AU24,AV23) -> 0.5383 | AW24: =-SUM('B5'!AI23) -> 0 | AX24: =-SUM(AW24-AS24) -> 0 | AY24: =SUM(AX24+AW24) -> 0 | AZ24: =ELEC!A21 -> 0 | BA24: ='General information '!D24 -> 0 | BB24: =SUM('General information '!E24) -> 0 | BC24: =IF(AR23>=AR24,0,1) -> 0 | BD24: 19222 | BE24: =(305/1185)*ELEC!Q22 -> 0 | BG24: =#REF!-BE24 -> #REF!
A25: =ELEC!C22 -> 44032 | B25: ='B5'!B24 -> 171.3 | C25: =B25*$B$4 -> 3685.7129 | D25: =SUM(B25) -> 171.3 | E25: =D25*$B$4 -> 3685.7129 | F25: =SUM(D25) -> 171.3 | G25: =F25*$B$4 -> 3685.7129 | H25: =SUM(F25) -> 171.3 | I25: =H25*$B$4 -> 3685.7129 | J25: =SUM(H25) -> 171.3 | K25: =J25*$B$4 -> 3685.7129 | L25: =SUM(J25) -> 171.3 | M25: =L25*$B$4 -> 3685.7129 | N25: =SUM(L25) -> 171.3 | O25: =N25*$B$4 -> 3685.7129 | P25: =SUM(N25) -> 171.3 | Q25: =P25*$B$4 -> 3685.7129 | R25: =SUM(P25) -> 171.3 | S25: =R25*$B$4 -> 3685.7129 | T25: =SUM(R25) -> 171.3 | U25: =T25*$B$4 -> 3685.7129 | V25: =SUM(T25) -> 171.3 | W25: =V25*$B$4 -> 3685.7129 | X25: =SUM(Y25/73370) -> 0.55258065 | Y25: =SUM(C25+E25+G25+I25+K25+M25+O25+Q25+S25+U25+W25) -> 40542.842 | Z25: ='B5'!C24 -> 178 | AA25: =SUM(Z25*$Z$4) -> 1780 | AB25: =SUM(Z25) -> 178 | AC25: =SUM(AB25*$Z$4) -> 1780 | AD25: =SUM(AB25) -> 178 | AE25: =SUM(AD25*$Z$4) -> 1780 | AF25: =SUM(AD25) -> 178 | AG25: =SUM(AF25*$Z$4) -> 1780 | AH25: =SUM(AF25) -> 178 | AI25: =SUM(AH25*$Z$4) -> 1780 | AJ25: =SUM(AH25) -> 178 | AK25: =SUM(AJ25*$Z$4) -> 1780 | AL25: =SUM(AJ25) -> 178 | AM25: =SUM(AL25*$Z$4) -> 1780 | AN25: =SUM(AO25/19600) -> 0.63571429 | AO25: =SUM(AA25+AC25+AE25+AG25+AI25+AK25+AM25) -> 12460 | AQ25: =SUM(AR25/92970) -> 0.57010694 | AR25: =SUM(AO25+Y25) -> 53002.842 | AS25: =SUM(AR25-AR24-AT25) -> 0 | AV25: =IF(AT25>0,AU25,AV24) -> 0.5383 | AW25: =-SUM('B5'!AI24) -> 0 | AX25: =-SUM(AW25-AS25) -> 0 | AY25: =SUM(AX25+AW25) -> 0 | AZ25: =ELEC!A22 -> 0 | BA25: ='General information '!D25 -> 0 | BB25: =SUM('General information '!E25) -> 0 | BC25: =IF(AR24>=AR25,0,1) -> 0 | BD25: 19222 | BE25: =(305/1185)*ELEC!Q23 -> 0 | BG25: =#REF!-BE25 -> #REF!
A26: =ELEC!C23 -> 44033 | B26: ='B5'!B25 -> 171.3 | C26: =B26*$B$4 -> 3685.7129 | D26: =SUM(B26) -> 171.3 | E26: =D26*$B$4 -> 3685.7129 | F26: =SUM(D26) -> 171.3 | G26: =F26*$B$4 -> 3685.7129 | H26: =SUM(F26) -> 171.3 | I26: =H26*$B$4 -> 3685.7129 | J26: =SUM(H26) -> 171.3 | K26: =J26*$B$4 -> 3685.7129 | L26: =SUM(J26) -> 171.3 | M26: =L26*$B$4 -> 3685.7129 | N26: =SUM(L26) -> 171.3 | O26: =N26*$B$4 -> 3685.7129 | P26: =SUM(N26) -> 171.3 | Q26: =P26*$B$4 -> 3685.7129 | R26: =SUM(P26) -> 171.3 | S26: =R26*$B$4 -> 3685.7129 | T26: =SUM(R26) -> 171.3 | U26: =T26*$B$4 -> 3685.7129 | V26: =SUM(T26) -> 171.3 | W26: =V26*$B$4 -> 3685.7129 | X26: =SUM(Y26/73370) -> 0.55258065 | Y26: =SUM(C26+E26+G26+I26+K26+M26+O26+Q26+S26+U26+W26) -> 40542.842 | Z26: ='B5'!C25 -> 178 | AA26: =SUM(Z26*$Z$4) -> 1780 | AB26: =SUM(Z26) -> 178 | AC26: =SUM(AB26*$Z$4) -> 1780 | AD26: =SUM(AB26) -> 178 | AE26: =SUM(AD26*$Z$4) -> 1780 | AF26: =SUM(AD26) -> 178 | AG26: =SUM(AF26*$Z$4) -> 1780 | AH26: =SUM(AF26) -> 178 | AI26: =SUM(AH26*$Z$4) -> 1780 | AJ26: =SUM(AH26) -> 178 | AK26: =SUM(AJ26*$Z$4) -> 1780 | AL26: =SUM(AJ26) -> 178 | AM26: =SUM(AL26*$Z$4) -> 1780 | AN26: =SUM(AO26/19600) -> 0.63571429 | AO26: =SUM(AA26+AC26+AE26+AG26+AI26+AK26+AM26) -> 12460 | AQ26: =SUM(AR26/92970) -> 0.57010694 | AR26: =SUM(AO26+Y26) -> 53002.842 | AS26: =SUM(AR26-AR25-AT26) -> 0 | AV26: =IF(AT26>0,AU26,AV25) -> 0.5383 | AW26: =-SUM('B5'!AI25) -> 0 | AX26: =-SUM(AW26-AS26) -> 0 | AY26: =SUM(AX26+AW26) -> 0 | AZ26: =ELEC!A23 -> 0 | BA26: ='General information '!D26 -> 0 | BB26: =SUM('General information '!E26) -> 0 | BC26: =IF(AR25>=AR26,0,1) -> 0 | BD26: 19222 | BE26: =(305/1185)*ELEC!Q24 -> 0 | BG26: =#REF!-BE26 -> #REF!
A27: =ELEC!C24 -> 44034 | B27: ='B5'!B26 -> 171.3 | C27: =B27*$B$4 -> 3685.7129 | D27: =SUM(B27) -> 171.3 | E27: =D27*$B$4 -> 3685.7129 | F27: =SUM(D27) -> 171.3 | G27: =F27*$B$4 -> 3685.7129 | H27: =SUM(F27) -> 171.3 | I27: =H27*$B$4 -> 3685.7129 | J27: =SUM(H27) -> 171.3 | K27: =J27*$B$4 -> 3685.7129 | L27: =SUM(J27) -> 171.3 | M27: =L27*$B$4 -> 3685.7129 | N27: =SUM(L27) -> 171.3 | O27: =N27*$B$4 -> 3685.7129 | P27: =SUM(N27) -> 171.3 | Q27: =P27*$B$4 -> 3685.7129 | R27: =SUM(P27) -> 171.3 | S27: =R27*$B$4 -> 3685.7129 | T27: =SUM(R27) -> 171.3 | U27: =T27*$B$4 -> 3685.7129 | V27: =SUM(T27) -> 171.3 | W27: =V27*$B$4 -> 3685.7129 | X27: =SUM(Y27/73370) -> 0.55258065 | Y27: =SUM(C27+E27+G27+I27+K27+M27+O27+Q27+S27+U27+W27) -> 40542.842 | Z27: ='B5'!C26 -> 178 | AA27: =SUM(Z27*$Z$4) -> 1780 | AB27: =SUM(Z27) -> 178 | AC27: =SUM(AB27*$Z$4) -> 1780 | AD27: =SUM(AB27) -> 178 | AE27: =SUM(AD27*$Z$4) -> 1780 | AF27: =SUM(AD27) -> 178 | AG27: =SUM(AF27*$Z$4) -> 1780 | AH27: =SUM(AF27) -> 178 | AI27: =SUM(AH27*$Z$4) -> 1780 | AJ27: =SUM(AH27) -> 178 | AK27: =SUM(AJ27*$Z$4) -> 1780 | AL27: =SUM(AJ27) -> 178 | AM27: =SUM(AL27*$Z$4) -> 1780 | AN27: =SUM(AO27/19600) -> 0.63571429 | AO27: =SUM(AA27+AC27+AE27+AG27+AI27+AK27+AM27) -> 12460 | AQ27: =SUM(AR27/92970) -> 0.57010694 | AR27: =SUM(AO27+Y27) -> 53002.842 | AS27: =SUM(AR27-AR26-AT27) -> 0 | AV27: =IF(AT27>0,AU27,AV26) -> 0.5383 | AW27: =-SUM('B5'!AI26) -> 0 | AX27: =-SUM(AW27-AS27) -> 0 | AY27: =SUM(AX27+AW27) -> 0 | AZ27: =ELEC!A24 -> 0 | BA27: ='General information '!D27 -> 0 | BB27: =SUM('General information '!E27) -> 0 | BC27: =IF(AR26>=AR27,0,1) -> 0 | BD27: 19222 | BE27: =(305/1185)*ELEC!Q25 -> 0 | BG27: =#REF!-BE27 -> #REF!
A28: =ELEC!C25 -> 44035 | B28: ='B5'!B27 -> 171.3 | C28: =B28*$B$4 -> 3685.7129 | D28: =SUM(B28) -> 171.3 | E28: =D28*$B$4 -> 3685.7129 | F28: =SUM(D28) -> 171.3 | G28: =F28*$B$4 -> 3685.7129 | H28: =SUM(F28) -> 171.3 | I28: =H28*$B$4 -> 3685.7129 | J28: =SUM(H28) -> 171.3 | K28: =J28*$B$4 -> 3685.7129 | L28: =SUM(J28) -> 171.3 | M28: =L28*$B$4 -> 3685.7129 | N28: =SUM(L28) -> 171.3 | O28: =N28*$B$4 -> 3685.7129 | P28: =SUM(N28) -> 171.3 | Q28: =P28*$B$4 -> 3685.7129 | R28: =SUM(P28) -> 171.3 | S28: =R28*$B$4 -> 3685.7129 | T28: =SUM(R28) -> 171.3 | U28: =T28*$B$4 -> 3685.7129 | V28: =SUM(T28) -> 171.3 | W28: =V28*$B$4 -> 3685.7129 | X28: =SUM(Y28/73370) -> 0.55258065 | Y28: =SUM(C28+E28+G28+I28+K28+M28+O28+Q28+S28+U28+W28) -> 40542.842 | Z28: ='B5'!C27 -> 178 | AA28: =SUM(Z28*$Z$4) -> 1780 | AB28: =SUM(Z28) -> 178 | AC28: =SUM(AB28*$Z$4) -> 1780 | AD28: =SUM(AB28) -> 178 | AE28: =SUM(AD28*$Z$4) -> 1780 | AF28: =SUM(AD28) -> 178 | AG28: =SUM(AF28*$Z$4) -> 1780 | AH28: =SUM(AF28) -> 178 | AI28: =SUM(AH28*$Z$4) -> 1780 | AJ28: =SUM(AH28) -> 178 | AK28: =SUM(AJ28*$Z$4) -> 1780 | AL28: =SUM(AJ28) -> 178 | AM28: =SUM(AL28*$Z$4) -> 1780 | AN28: =SUM(AO28/19600) -> 0.63571429 | AO28: =SUM(AA28+AC28+AE28+AG28+AI28+AK28+AM28) -> 12460 | AQ28: =SUM(AR28/92970) -> 0.57010694 | AR28: =SUM(AO28+Y28) -> 53002.842 | AS28: =SUM(AR28-AR27-AT28) -> 0 | AV28: =IF(AT28>0,AU28,AV27) -> 0.5383 | AW28: =-SUM('B5'!AI27) -> 0 | AX28: =-SUM(AW28-AS28) -> 0 | AY28: =SUM(AX28+AW28) -> 0 | AZ28: =ELEC!A25 -> 0 | BA28: ='General information '!D28 -> 0 | BB28: =SUM('General information '!E28) -> 0 | BC28: =IF(AR27>=AR28,0,1) -> 0 | BD28: 19222 | BE28: =(305/1185)*ELEC!Q26 -> 0 | BG28: =#REF!-BE28 -> #REF!
A29: =ELEC!C26 -> 44036 | B29: ='B5'!B28 -> 171.3 | C29: =B29*$B$4 -> 3685.7129 | D29: =SUM(B29) -> 171.3 | E29: =D29*$B$4 -> 3685.7129 | F29: =SUM(D29) -> 171.3 | G29: =F29*$B$4 -> 3685.7129 | H29: =SUM(F29) -> 171.3 | I29: =H29*$B$4 -> 3685.7129 | J29: =SUM(H29) -> 171.3 | K29: =J29*$B$4 -> 3685.7129 | L29: =SUM(J29) -> 171.3 | M29: =L29*$B$4 -> 3685.7129 | N29: =SUM(L29) -> 171.3 | O29: =N29*$B$4 -> 3685.7129 | P29: =SUM(N29) -> 171.3 | Q29: =P29*$B$4 -> 3685.7129 | R29: =SUM(P29) -> 171.3 | S29: =R29*$B$4 -> 3685.7129 | T29: =SUM(R29) -> 171.3 | U29: =T29*$B$4 -> 3685.7129 | V29: =SUM(T29) -> 171.3 | W29: =V29*$B$4 -> 3685.7129 | X29: =SUM(Y29/73370) -> 0.55258065 | Y29: =SUM(C29+E29+G29+I29+K29+M29+O29+Q29+S29+U29+W29) -> 40542.842 | Z29: ='B5'!C28 -> 178 | AA29: =SUM(Z29*$Z$4) -> 1780 | AB29: =SUM(Z29) -> 178 | AC29: =SUM(AB29*$Z$4) -> 1780 | AD29: =SUM(AB29) -> 178 | AE29: =SUM(AD29*$Z$4) -> 1780 | AF29: =SUM(AD29) -> 178 | AG29: =SUM(AF29*$Z$4) -> 1780 | AH29: =SUM(AF29) -> 178 | AI29: =SUM(AH29*$Z$4) -> 1780 | AJ29: =SUM(AH29) -> 178 | AK29: =SUM(AJ29*$Z$4) -> 1780 | AL29: =SUM(AJ29) -> 178 | AM29: =SUM(AL29*$Z$4) -> 1780 | AN29: =SUM(AO29/19600) -> 0.63571429 | AO29: =SUM(AA29+AC29+AE29+AG29+AI29+AK29+AM29) -> 12460 | AQ29: =SUM(AR29/92970) -> 0.57010694 | AR29: =SUM(AO29+Y29) -> 53002.842 | AS29: =SUM(AR29-AR28-AT29) -> 0 | AV29: =IF(AT29>0,AU29,AV28) -> 0.5383 | AW29: =-SUM('B5'!AI28) -> 0 | AX29: =-SUM(AW29-AS29) -> 0 | AY29: =SUM(AX29+AW29) -> 0 | AZ29: =ELEC!A26 -> 0 | BA29: ='General information '!D29 -> 0 | BB29: =SUM('General information '!E29) -> 0 | BC29: =IF(AR28>=AR29,0,1) -> 0 | BD29: 19222 | BE29: =(305/1185)*ELEC!Q27 -> 0 | BG29: =#REF!-BE29 -> #REF!
A30: =ELEC!C27 -> 44037 | B30: ='B5'!B29 -> 171.3 | C30: =B30*$B$4 -> 3685.7129 | D30: =SUM(B30) -> 171.3 | E30: =D30*$B$4 -> 3685.7129 | F30: =SUM(D30) -> 171.3 | G30: =F30*$B$4 -> 3685.7129 | H30: =SUM(F30) -> 171.3 | I30: =H30*$B$4 -> 3685.7129 | J30: =SUM(H30) -> 171.3 | K30: =J30*$B$4 -> 3685.7129 | L30: =SUM(J30) -> 171.3 | M30: =L30*$B$4 -> 3685.7129 | N30: =SUM(L30) -> 171.3 | O30: =N30*$B$4 -> 3685.7129 | P30: =SUM(N30) -> 171.3 | Q30: =P30*$B$4 -> 3685.7129 | R30: =SUM(P30) -> 171.3 | S30: =R30*$B$4 -> 3685.7129 | T30: =SUM(R30) -> 171.3 | U30: =T30*$B$4 -> 3685.7129 | V30: =SUM(T30) -> 171.3 | W30: =V30*$B$4 -> 3685.7129 | X30: =SUM(Y30/73370) -> 0.55258065 | Y30: =SUM(C30+E30+G30+I30+K30+M30+O30+Q30+S30+U30+W30) -> 40542.842 | Z30: ='B5'!C29 -> 178 | AA30: =SUM(Z30*$Z$4) -> 1780 | AB30: =SUM(Z30) -> 178 | AC30: =SUM(AB30*$Z$4) -> 1780 | AD30: =SUM(AB30) -> 178 | AE30: =SUM(AD30*$Z$4) -> 1780 | AF30: =SUM(AD30) -> 178 | AG30: =SUM(AF30*$Z$4) -> 1780 | AH30: =SUM(AF30) -> 178 | AI30: =SUM(AH30*$Z$4) -> 1780 | AJ30: =SUM(AH30) -> 178 | AK30: =SUM(AJ30*$Z$4) -> 1780 | AL30: =SUM(AJ30) -> 178 | AM30: =SUM(AL30*$Z$4) -> 1780 | AN30: =SUM(AO30/19600) -> 0.63571429 | AO30: =SUM(AA30+AC30+AE30+AG30+AI30+AK30+AM30) -> 12460 | AQ30: =SUM(AR30/92970) -> 0.57010694 | AR30: =SUM(AO30+Y30) -> 53002.842 | AS30: =SUM(AR30-AR29-AT30) -> 0 | AV30: =IF(AT30>0,AU30,AV29) -> 0.5383 | AW30: =-SUM('B5'!AI29) -> 0 | AX30: =-SUM(AW30-AS30) -> 0 | AY30: =SUM(AX30+AW30) -> 0 | AZ30: =ELEC!A27 -> 0 | BA30: ='General information '!D30 -> 0 | BB30: =SUM('General information '!E30) -> 0 | BC30: =IF(AR29>=AR30,0,1) -> 0 | BD30: 19222 | BE30: =(305/1185)*ELEC!Q28 -> 0 | BG30: =#REF!-BE30 -> #REF!
A31: =ELEC!C28 -> 44038 | B31: ='B5'!B30 -> 171.3 | C31: =B31*$B$4 -> 3685.7129 | D31: =SUM(B31) -> 171.3 | E31: =D31*$B$4 -> 3685.7129 | F31: =SUM(D31) -> 171.3 | G31: =F31*$B$4 -> 3685.7129 | H31: =SUM(F31) -> 171.3 | I31: =H31*$B$4 -> 3685.7129 | J31: =SUM(H31) -> 171.3 | K31: =J31*$B$4 -> 3685.7129 | L31: =SUM(J31) -> 171.3 | M31: =L31*$B$4 -> 3685.7129 | N31: =SUM(L31) -> 171.3 | O31: =N31*$B$4 -> 3685.7129 | P31: =SUM(N31) -> 171.3 | Q31: =P31*$B$4 -> 3685.7129 | R31: =SUM(P31) -> 171.3 | S31: =R31*$B$4 -> 3685.7129 | T31: =SUM(R31) -> 171.3 | U31: =T31*$B$4 -> 3685.7129 | V31: =SUM(T31) -> 171.3 | W31: =V31*$B$4 -> 3685.7129 | X31: =SUM(Y31/73370) -> 0.55258065 | Y31: =SUM(C31+E31+G31+I31+K31+M31+O31+Q31+S31+U31+W31) -> 40542.842 | Z31: ='B5'!C30 -> 178 | AA31: =SUM(Z31*$Z$4) -> 1780 | AB31: =SUM(Z31) -> 178 | AC31: =SUM(AB31*$Z$4) -> 1780 | AD31: =SUM(AB31) -> 178 | AE31: =SUM(AD31*$Z$4) -> 1780 | AF31: =SUM(AD31) -> 178 | AG31: =SUM(AF31*$Z$4) -> 1780 | AH31: =SUM(AF31) -> 178 | AI31: =SUM(AH31*$Z$4) -> 1780 | AJ31: =SUM(AH31) -> 178 | AK31: =SUM(AJ31*$Z$4) -> 1780 | AL31: =SUM(AJ31) -> 178 | AM31: =SUM(AL31*$Z$4) -> 1780 | AN31: =SUM(AO31/19600) -> 0.63571429 | AO31: =SUM(AA31+AC31+AE31+AG31+AI31+AK31+AM31) -> 12460 | AQ31: =SUM(AR31/92970) -> 0.57010694 | AR31: =SUM(AO31+Y31) -> 53002.842 | AS31: =SUM(AR31-AR30-AT31) -> 0 | AV31: =IF(AT31>0,AU31,AV30) -> 0.5383 | AW31: =-SUM('B5'!AI30) -> 0 | AX31: =-SUM(AW31-AS31) -> 0 | AY31: =SUM(AX31+AW31) -> 0 | AZ31: =ELEC!A28 -> 0 | BA31: ='General information '!D31 -> 0 | BB31: =SUM('General information '!E31) -> 0 | BC31: =IF(AR30>=AR31,0,1) -> 0 | BD31: 19222 | BE31: =(305/1185)*ELEC!Q29 -> 0 | BG31: =#REF!-BE31 -> #REF!
A32: =ELEC!C29 -> 44039 | B32: ='B5'!B31 -> 171.3 | C32: =B32*$B$4 -> 3685.7129 | D32: =SUM(B32) -> 171.3 | E32: =D32*$B$4 -> 3685.7129 | F32: =SUM(D32) -> 171.3 | G32: =F32*$B$4 -> 3685.7129 | H32: =SUM(F32) -> 171.3 | I32: =H32*$B$4 -> 3685.7129 | J32: =SUM(H32) -> 171.3 | K32: =J32*$B$4 -> 3685.7129 | L32: =SUM(J32) -> 171.3 | M32: =L32*$B$4 -> 3685.7129 | N32: =SUM(L32) -> 171.3 | O32: =N32*$B$4 -> 3685.7129 | P32: =SUM(N32) -> 171.3 | Q32: =P32*$B$4 -> 3685.7129 | R32: =SUM(P32) -> 171.3 | S32: =R32*$B$4 -> 3685.7129 | T32: =SUM(R32) -> 171.3 | U32: =T32*$B$4 -> 3685.7129 | V32: =SUM(T32) -> 171.3 | W32: =V32*$B$4 -> 3685.7129 | X32: =SUM(Y32/73370) -> 0.55258065 | Y32: =SUM(C32+E32+G32+I32+K32+M32+O32+Q32+S32+U32+W32) -> 40542.842 | Z32: ='B5'!C31 -> 178 | AA32: =SUM(Z32*$Z$4) -> 1780 | AB32: =SUM(Z32) -> 178 | AC32: =SUM(AB32*$Z$4) -> 1780 | AD32: =SUM(AB32) -> 178 | AE32: =SUM(AD32*$Z$4) -> 1780 | AF32: =SUM(AD32) -> 178 | AG32: =SUM(AF32*$Z$4) -> 1780 | AH32: =SUM(AF32) -> 178 | AI32: =SUM(AH32*$Z$4) -> 1780 | AJ32: =SUM(AH32) -> 178 | AK32: =SUM(AJ32*$Z$4) -> 1780 | AL32: =SUM(AJ32) -> 178 | AM32: =SUM(AL32*$Z$4) -> 1780 | AN32: =SUM(AO32/19600) -> 0.63571429 | AO32: =SUM(AA32+AC32+AE32+AG32+AI32+AK32+AM32) -> 12460 | AQ32: =SUM(AR32/92970) -> 0.57010694 | AR32: =SUM(AO32+Y32) -> 53002.842 | AS32: =SUM(AR32-AR31-AT32) -> 0 | AV32: =IF(AT32>0,AU32,AV31) -> 0.5383 | AW32: =-SUM('B5'!AI31) -> 0 | AX32: =-SUM(AW32-AS32) -> 0 | AY32: =SUM(AX32+AW32) -> 0 | AZ32: =ELEC!A29 -> 0 | BA32: ='General information '!D32 -> 0 | BB32: =SUM('General information '!E32) -> 0 | BC32: =IF(AR31>=AR32,0,1) -> 0 | BD32: 19222 | BE32: =(305/1185)*ELEC!Q30 -> 0 | BG32: =#REF!-BE32 -> #REF!
A33: =ELEC!C30 -> 44040 | B33: ='B5'!B32 -> 171.3 | C33: =B33*$B$4 -> 3685.7129 | D33: =SUM(B33) -> 171.3 | E33: =D33*$B$4 -> 3685.7129 | F33: =SUM(D33) -> 171.3 | G33: =F33*$B$4 -> 3685.7129 | H33: =SUM(F33) -> 171.3 | I33: =H33*$B$4 -> 3685.7129 | J33: =SUM(H33) -> 171.3 | K33: =J33*$B$4 -> 3685.7129 | L33: =SUM(J33) -> 171.3 | M33: =L33*$B$4 -> 3685.7129 | N33: =SUM(L33) -> 171.3 | O33: =N33*$B$4 -> 3685.7129 | P33: =SUM(N33) -> 171.3 | Q33: =P33*$B$4 -> 3685.7129 | R33: =SUM(P33) -> 171.3 | S33: =R33*$B$4 -> 3685.7129 | T33: =SUM(R33) -> 171.3 | U33: =T33*$B$4 -> 3685.7129 | V33: =SUM(T33) -> 171.3 | W33: =V33*$B$4 -> 3685.7129 | X33: =SUM(Y33/73370) -> 0.55258065 | Y33: =SUM(C33+E33+G33+I33+K33+M33+O33+Q33+S33+U33+W33) -> 40542.842 | Z33: ='B5'!C32 -> 178 | AA33: =SUM(Z33*$Z$4) -> 1780 | AB33: =SUM(Z33) -> 178 | AC33: =SUM(AB33*$Z$4) -> 1780 | AD33: =SUM(AB33) -> 178 | AE33: =SUM(AD33*$Z$4) -> 1780 | AF33: =SUM(AD33) -> 178 | AG33: =SUM(AF33*$Z$4) -> 1780 | AH33: =SUM(AF33) -> 178 | AI33: =SUM(AH33*$Z$4) -> 1780 | AJ33: =SUM(AH33) -> 178 | AK33: =SUM(AJ33*$Z$4) -> 1780 | AL33: =SUM(AJ33) -> 178 | AM33: =SUM(AL33*$Z$4) -> 1780 | AN33: =SUM(AO33/19600) -> 0.63571429 | AO33: =SUM(AA33+AC33+AE33+AG33+AI33+AK33+AM33) -> 12460 | AQ33: =SUM(AR33/92970) -> 0.57010694 | AR33: =SUM(AO33+Y33) -> 53002.842 | AS33: =SUM(AR33-AR32-AT33) -> 0 | AV33: =IF(AT33>0,AU33,AV32) -> 0.5383 | AW33: =-SUM('B5'!AI32) -> 0 | AX33: =-SUM(AW33-AS33) -> 0 | AY33: =SUM(AX33+AW33) -> 0 | AZ33: =ELEC!A30 -> 0 | BA33: ='General information '!D33 -> 0 | BB33: =SUM('General information '!E33) -> 0 | BC33: =IF(AR32>=AR33,0,1) -> 0 | BD33: 19222 | BE33: =(305/1185)*ELEC!Q31 -> 0 | BG33: =#REF!-BE33 -> #REF!
A34: =ELEC!C31 -> 44041 | B34: ='B5'!B33 -> 171.3 | C34: =B34*$B$4 -> 3685.7129 | D34: =SUM(B34) -> 171.3 | E34: =D34*$B$4 -> 3685.7129 | F34: =SUM(D34) -> 171.3 | G34: =F34*$B$4 -> 3685.7129 | H34: =SUM(F34) -> 171.3 | I34: =H34*$B$4 -> 3685.7129 | J34: =SUM(H34) -> 171.3 | K34: =J34*$B$4 -> 3685.7129 | L34: =SUM(J34) -> 171.3 | M34: =L34*$B$4 -> 3685.7129 | N34: =SUM(L34) -> 171.3 | O34: =N34*$B$4 -> 3685.7129 | P34: =SUM(N34) -> 171.3 | Q34: =P34*$B$4 -> 3685.7129 | R34: =SUM(P34) -> 171.3 | S34: =R34*$B$4 -> 3685.7129 | T34: =SUM(R34) -> 171.3 | U34: =T34*$B$4 -> 3685.7129 | V34: =SUM(T34) -> 171.3 | W34: =V34*$B$4 -> 3685.7129 | X34: =SUM(Y34/73370) -> 0.55258065 | Y34: =SUM(C34+E34+G34+I34+K34+M34+O34+Q34+S34+U34+W34) -> 40542.842 | Z34: ='B5'!C33 -> 178 | AA34: =SUM(Z34*$Z$4) -> 1780 | AB34: =SUM(Z34) -> 178 | AC34: =SUM(AB34*$Z$4) -> 1780 | AD34: =SUM(AB34) -> 178 | AE34: =SUM(AD34*$Z$4) -> 1780 | AF34: =SUM(AD34) -> 178 | AG34: =SUM(AF34*$Z$4) -> 1780 | AH34: =SUM(AF34) -> 178 | AI34: =SUM(AH34*$Z$4) -> 1780 | AJ34: =SUM(AH34) -> 178 | AK34: =SUM(AJ34*$Z$4) -> 1780 | AL34: =SUM(AJ34) -> 178 | AM34: =SUM(AL34*$Z$4) -> 1780 | AN34: =SUM(AO34/19600) -> 0.63571429 | AO34: =SUM(AA34+AC34+AE34+AG34+AI34+AK34+AM34) -> 12460 | AQ34: =SUM(AR34/92970) -> 0.57010694 | AR34: =SUM(AO34+Y34) -> 53002.842 | AS34: =SUM(AR34-AR33-AT34) -> 0 | AV34: =IF(AT34>0,AU34,AV33) -> 0.5383 | AW34: =-SUM('B5'!AI33) -> 0 | AX34: =-SUM(AW34-AS34) -> 0 | AY34: =SUM(AX34+AW34) -> 0 | AZ34: =ELEC!A31 -> 0 | BA34: ='General information '!D34 -> 0 | BB34: =SUM('General information '!E34) -> 0 | BC34: =IF(AR33>=AR34,0,1) -> 0 | BD34: 19222 | BE34: =(305/1185)*ELEC!#REF! -> #REF! | BG34: =#REF!-BE34 -> #REF!
A35: =ELEC!C32 -> 44042 | B35: ='B5'!B34 -> 171.3 | C35: =B35*$B$4 -> 3685.7129 | D35: =SUM(B35) -> 171.3 | E35: =D35*$B$4 -> 3685.7129 | F35: =SUM(D35) -> 171.3 | G35: =F35*$B$4 -> 3685.7129 | H35: =SUM(F35) -> 171.3 | I35: =H35*$B$4 -> 3685.7129 | J35: =SUM(H35) -> 171.3 | K35: =J35*$B$4 -> 3685.7129 | L35: =SUM(J35) -> 171.3 | M35: =L35*$B$4 -> 3685.7129 | N35: =SUM(L35) -> 171.3 | O35: =N35*$B$4 -> 3685.7129 | P35: =SUM(N35) -> 171.3 | Q35: =P35*$B$4 -> 3685.7129 | R35: =SUM(P35) -> 171.3 | S35: =R35*$B$4 -> 3685.7129 | T35: =SUM(R35) -> 171.3 | U35: =T35*$B$4 -> 3685.7129 | V35: =SUM(T35) -> 171.3 | W35: =V35*$B$4 -> 3685.7129 | X35: =SUM(Y35/73370) -> 0.55258065 | Y35: =SUM(C35+E35+G35+I35+K35+M35+O35+Q35+S35+U35+W35) -> 40542.842 | Z35: ='B5'!C34 -> 178 | AA35: =SUM(Z35*$Z$4) -> 1780 | AB35: =SUM(Z35) -> 178 | AC35: =SUM(AB35*$Z$4) -> 1780 | AD35: =SUM(AB35) -> 178 | AE35: =SUM(AD35*$Z$4) -> 1780 | AF35: =SUM(AD35) -> 178 | AG35: =SUM(AF35*$Z$4) -> 1780 | AH35: =SUM(AF35) -> 178 | AI35: =SUM(AH35*$Z$4) -> 1780 | AJ35: =SUM(AH35) -> 178 | AK35: =SUM(AJ35*$Z$4) -> 1780 | AL35: =SUM(AJ35) -> 178 | AM35: =SUM(AL35*$Z$4) -> 1780 | AN35: =SUM(AO35/19600) -> 0.63571429 | AO35: =SUM(AA35+AC35+AE35+AG35+AI35+AK35+AM35) -> 12460 | AQ35: =SUM(AR35/92970) -> 0.57010694 | AR35: =SUM(AO35+Y35) -> 53002.842 | AS35: =SUM(AR35-AR34-AT35) -> 0 | AV35: =IF(AT35>0,AU35,AV34) -> 0.5383 | AW35: =-SUM('B5'!AI34) -> 0 | AX35: =-SUM(AW35-AS35) -> 0 | AY35: =SUM(AX35+AW35) -> 0 | AZ35: =ELEC!A32 -> 0 | BA35: ='General information '!D35 -> 0 | BB35: =SUM('General information '!E35) -> 0 | BC35: =IF(AR34>=AR35,0,1) -> 0 | BD35: 19222 | BE35: =(305/1185)*ELEC!#REF! -> #REF! | BG35: =#REF!-BE35 -> #REF!
A36: =ELEC!C33 -> 44043 | B36: ='B5'!B35 -> 171.3 | C36: =B36*$B$4 -> 3685.7129 | D36: =SUM(B36) -> 171.3 | E36: =D36*$B$4 -> 3685.7129 | F36: =SUM(D36) -> 171.3 | G36: =F36*$B$4 -> 3685.7129 | H36: =SUM(F36) -> 171.3 | I36: =H36*$B$4 -> 3685.7129 | J36: =SUM(H36) -> 171.3 | K36: =J36*$B$4 -> 3685.7129 | L36: =SUM(J36) -> 171.3 | M36: =L36*$B$4 -> 3685.7129 | N36: =SUM(L36) -> 171.3 | O36: =N36*$B$4 -> 3685.7129 | P36: =SUM(N36) -> 171.3 | Q36: =P36*$B$4 -> 3685.7129 | R36: =SUM(P36) -> 171.3 | S36: =R36*$B$4 -> 3685.7129 | T36: =SUM(R36) -> 171.3 | U36: =T36*$B$4 -> 3685.7129 | V36: =SUM(T36) -> 171.3 | W36: =V36*$B$4 -> 3685.7129 | X36: =SUM(Y36/73370) -> 0.55258065 | Y36: =SUM(C36+E36+G36+I36+K36+M36+O36+Q36+S36+U36+W36) -> 40542.842 | Z36: ='B5'!C35 -> 178 | AA36: =SUM(Z36*$Z$4) -> 1780 | AB36: =SUM(Z36) -> 178 | AC36: =SUM(AB36*$Z$4) -> 1780 | AD36: =SUM(AB36) -> 178 | AE36: =SUM(AD36*$Z$4) -> 1780 | AF36: =SUM(AD36) -> 178 | AG36: =SUM(AF36*$Z$4) -> 1780 | AH36: =SUM(AF36) -> 178 | AI36: =SUM(AH36*$Z$4) -> 1780 | AJ36: =SUM(AH36) -> 178 | AK36: =SUM(AJ36*$Z$4) -> 1780 | AL36: =SUM(AJ36) -> 178 | AM36: =SUM(AL36*$Z$4) -> 1780 | AN36: =SUM(AO36/19600) -> 0.63571429 | AO36: =SUM(AA36+AC36+AE36+AG36+AI36+AK36+AM36) -> 12460 | AQ36: =SUM(AR36/92970) -> 0.57010694 | AR36: =SUM(AO36+Y36) -> 53002.842 | AS36: =SUM(AR36-AR35-AT36) -> 0 | AV36: =IF(AT36>0,AU36,AV35) -> 0.5383 | AW36: =-SUM('B5'!AI35) -> 0 | AX36: =-SUM(AW36-AS36) -> 0 | AY36: =SUM(AX36+AW36) -> 0 | AZ36: =ELEC!A33 -> 0.104125 | BA36: ='General information '!D36 -> 0 | BB36: =SUM('General information '!E36) -> 0 | BC36: =IF(AR35>=AR36,0,1) -> 0 | BD36: 19222 | BE36: =(305/1185)*ELEC!#REF! -> #REF! | BG36: =#REF!-BE36 -> #REF!
AR37: NB delivery | AS37: =COUNT(AT6:AT35) -> 6 | AT37: =SUM(AT6:AT35) -> 86879 | AU37: =SUM(AU6:AU35)/AS37 -> 0.50805 | AX37: =SUM(AX6:AX35) -> -70828.097 | AY37: =SUM(AY6:AY35) -> -77300.997
AT38: =+AT37*AU37 -> 44138.876
AS40: =SUM(AS6:AS35)/'EDl log'!A37 -> -5946.2305

Sheet GEN
B1: GEN1 | C1: RUN HR | D1: Fuel Counter Index | E1: Cons /day | F1: Diesel L/H | H1: next service | I1: ALARM | J1: GEN2 | K1: RUN HR | L1: Fuel Counter Index | M1: Cons /day | N1: Diesel L/H | P1: next service | Q1: ALARM | R1: GEN3 | S1: RUN HR | T1: Fuel Counter Index | U1: Cons /day | V1: Diesel L/H | X1: next service | Y1: ALARM | Z1: RH total | AA1: Gen Con /day | AB1: Total Deisel Cons/day | AC1: H /L | AD1: TOAL KW GEN | AI1: fuel Consuption | AK1: AVG KW/h
A2: =ELEC!C2 -> 44012 | B2: =[1]GEN!B32 -> 8777 | C2: =[1]GEN!C32 -> 15 | D2: =[1]GEN!D32 -> 171037 | E2: =[1]GEN!E32 -> 2409 | F2: =[1]GEN!F32 -> 160.6 | G2: =[1]GEN!G32 -> 0 | H2: =[1]GEN!H32 -> 8770 | I2: =[1]GEN!I32 -> oil change | ... AK2: =[1]GEN!AK32 -> 205.90717
A3: =ELEC!C3 -> 44013 | B3: 8789 | C3: =B3-B2 -> 12 | D3: 172770 | E3: =SUM(D3-D2) -> 1733 | F3: =IF(C3>0,E3/C3,0) -> 144.41667 | G3: =[3]GEN!G32 -> 0 | H3: =H2 -> 8770 | I3: =IF(B3-H3<=0,"ok","oil change") -> oil change | J3: =J2 -> 10698 | K3: =J3-J2 -> 0 | L3: =L2 -> 238499 | M3: =SUM(L3-L2) -> 0 | N3: =IF(K3>0,M3/K3,0) -> 0 | O3: =[3]GEN!O32 -> 0 | P3: =P2 -> 10873 | Q3: =IF(J3-P3<=0,"ok","oil change") -> ok | R3: 11260 | S3: =R3-R2 -> 8 | T3: =T2 -> 264828 | U3: =SUM(T3-T2) -> 0 | V3: =IF(S3>0,U3/S3,0) -> 0 | W3: =[3]GEN!W32 -> 0 | X3: =X2 -> 12069 | Y3: =IF(R3-X3<=0,"ok","oil change") -> ok | Z3: =C3+K3+S3 -> 20 | AA3: =U3+M3+E3 -> 1733 | AB3: =V3+N3+F3 -> 144.41667 | AC3: =IF(Z3>0,AA3/Z3,0) -> 86.65 | AD3: =ELEC!Q3 -> 14000 | AE3: =SUM(AD3/Z3) -> 700 | AF3: =SUM(AE3/1600) -> 0.4375 | AG3: =SUM(360*AF3) -> 157.5 | AH3: =SUM(AC3-AG3) -> -70.85 | AI3: =AD3*AJ3 -> 3603.3755 | AJ3: =305/1185 -> 0.25738397 | AK3: =AI3/Z3 -> 180.16878
A4: =ELEC!C4 -> 44014 | B4: 8789 | C4: =B4-B3 -> 0 | D4: 172771 | E4: =SUM(D4-D3) -> 1 | F4: =IF(C4>0,E4/C4,0) -> 0 | H4: =H3 -> 8770 | I4: =IF(B4-H4<=0,"ok","oil change") -> oil change | J4: =J3 -> 10698 | K4: =J4-J3 -> 0 | L4: =L3 -> 238499 | M4: =SUM(L4-L3) -> 0 | N4: =IF(K4>0,M4/K4,0) -> 0 | P4: =P3 -> 10873 | Q4: =IF(J4-P4<=0,"ok","oil change") -> ok | R4: 11276 | S4: =R4-R3 -> 16 | T4: 269562 | U4: =SUM(T4-T3) -> 4734 | V4: =IF(S4>0,U4/S4,0) -> 295.875 | X4: =X3 -> 12069 | Y4: =IF(R4-X4<=0,"ok","oil change") -> ok | Z4: =C4+K4+S4 -> 16 | AA4: =U4+M4+E4 -> 4735 | AB4: =V4+N4+F4 -> 295.875 | AC4: =IF(Z4>0,AA4/Z4,0) -> 295.9375 | AD4: =ELEC!Q4 -> 13000 | AE4: =SUM(AD4/Z4) -> 812.5 | AF4: =SUM(AE4/1600) -> 0.5078125 | AG4: =SUM(360*AF4) -> 182.8125 | AH4: =SUM(AC4-AG4) -> 113.125 | AI4: =AD4*AJ4 -> 3345.9916 | AJ4: =305/1185 -> 0.25738397 | AK4: =AI4/Z4 -> 209.12447
A5: =ELEC!C5 -> 44015 | B5: 8806 | C5: =B5-B4 -> 17 | D5: 175464 | E5: =SUM(D5-D4) -> 2693 | F5: =IF(C5>0,E5/C5,0) -> 158.41176 | H5: =H4 -> 8770 | I5: =IF(B5-H5<=0,"ok","oil change") -> oil change | J5: =J4 -> 10698 | K5: =J5-J4 -> 0 | L5: =L4 -> 238499 | M5: =SUM(L5-L4) -> 0 | N5: =IF(K5>0,M5/K5,0) -> 0 | P5: =P4 -> 10873 | Q5: =IF(J5-P5<=0,"ok","oil change") -> ok | R5: 11277 | S5: =R5-R4 -> 1 | T5: 269762 | U5: =SUM(T5-T4) -> 200 | V5: =IF(S5>0,U5/S5,0) -> 200 | X5: =X4 -> 12069 | Y5: =IF(R5-X5<=0,"ok","oil change") -> ok | Z5: =C5+K5+S5 -> 18 | AA5: =U5+M5+E5 -> 2893 | AB5: =V5+N5+F5 -> 358.41176 | AC5: =IF(Z5>0,AA5/Z5,0) -> 160.72222 | AD5: =ELEC!Q5 -> 14000 | AE5: =SUM(AD5/Z5) -> 777.77778 | AF5: =SUM(AE5/1600) -> 0.48611111 | AG5: =SUM(320*AF5) -> 155.55556 | AH5: =SUM(AC5-AG5) -> 5.1666667 | AI5: =AD5*AJ5 -> 3603.3755 | AJ5: =305/1185 -> 0.25738397 | AK5: =AI5/Z5 -> 200.18753
A6: =ELEC!C6 -> 44016 | B6: 8814 | C6: =B6-B5 -> 8 | D6: 176540 | E6: =SUM(D6-D5) -> 1076 | F6: =IF(C6>0,E6/C6,0) -> 134.5 | H6: =H5 -> 8770 | I6: =IF(B6-H6<=0,"ok","oil change") -> oil change | J6: =J5 -> 10698 | K6: =J6-J5 -> 0 | L6: =L5 -> 238499 | M6: =SUM(L6-L5) -> 0 | N6: =IF(K6>0,M6/K6,0) -> 0 | P6: =P5 -> 10873 | Q6: =IF(J6-P6<=0,"ok","oil change") -> ok | R6: 11290 | S6: =R6-R5 -> 13 | T6: 272338 | U6: =SUM(T6-T5) -> 2576 | V6: =IF(S6>0,U6/S6,0) -> 198.15385 | X6: =X5 -> 12069 | Y6: =IF(R6-X6<=0,"ok","oil change") -> ok | Z6: =C6+K6+S6 -> 21 | AA6: =U6+M6+E6 -> 3652 | AB6: =V6+N6+F6 -> 332.65385 | AC6: =IF(Z6>0,AA6/Z6,0) -> 173.90476 | AD6: =ELEC!Q6 -> 16000 | AE6: =SUM(AD6/Z6) -> 761.90476 | AF6: =SUM(AE6/1600) -> 0.47619048 | AG6: =SUM(320*AF6) -> 152.38095 | AH6: =SUM(AC6-AG6) -> 21.52381 | AI6: =AD6*AJ6 -> 4118.1435 | AJ6: =305/1185 -> 0.25738397 | AK6: =AI6/Z6 -> 196.10207
A7: =ELEC!C7 -> 44017 | B7: 8814 | C7: =B7-B6 -> 0 | D7: 176540 | E7: =SUM(D7-D6) -> 0 | F7: =IF(C7>0,E7/C7,0) -> 0 | H7: =H6 -> 8770 | I7: =IF(B7-H7<=0,"ok","oil change") -> oil change | J7: =J6 -> 10698 | K7: =J7-J6 -> 0 | L7: =L6 -> 238499 | M7: =SUM(L7-L6) -> 0 | N7: =IF(K7>0,M7/K7,0) -> 0 | P7: =P6 -> 10873 | Q7: =IF(J7-P7<=0,"ok","oil change") -> ok | R7: 11308 | S7: =R7-R6 -> 18 | T7: 276502 | U7: =SUM(T7-T6) -> 4164 | V7: =IF(S7>0,U7/S7,0) -> 231.33333 | X7: =X6 -> 12069 | Y7: =IF(R7-X7<=0,"ok","oil change") -> ok | Z7: =C7+K7+S7 -> 18 | AA7: =U7+M7+E7 -> 4164 | AB7: =V7+N7+F7 -> 231.33333 | AC7: =IF(Z7>0,AA7/Z7,0) -> 231.33333 | AD7: =ELEC!Q7 -> 15000 | AE7: =SUM(AD7/Z7) -> 833.33333 | AF7: =SUM(AE7/1600) -> 0.52083333 | AH7: =SUM(AC7-AG7) -> #VALUE! | AI7: =AD7*AJ7 -> 3860.7595 | AJ7: =305/1185 -> 0.25738397 | AK7: =AI7/Z7 -> 214.48664
A8: =ELEC!C8 -> 44018 | B8: 8814 | C8: =B8-B7 -> 0 | D8: 176540 | E8: =SUM(D8-D7) -> 0 | F8: =IF(C8>0,E8/C8,0) -> 0 | H8: =H7 -> 8770 | I8: =IF(B8-H8<=0,"ok","oil change") -> oil change | J8: 10698 | K8: =J8-J7 -> 0 | L8: 238500 | M8: =SUM(L8-L7) -> 1 | N8: =IF(K8>0,M8/K8,0) -> 0 | P8: =P7 -> 10873 | Q8: =IF(J8-P8<=0,"ok","oil change") -> ok | R8: 11329 | S8: =R8-R7 -> 21 | T8: 280205 | U8: =SUM(T8-T7) -> 3703 | V8: =IF(S8>0,U8/S8,0) -> 176.33333 | X8: =X7 -> 12069 | Y8: =IF(R8-X8<=0,"ok","oil change") -> ok | Z8: =C8+K8+S8 -> 21 | AA8: =U8+M8+E8 -> 3704 | AB8: =V8+N8+F8 -> 176.33333 | AC8: =IF(Z8>0,AA8/Z8,0) -> 176.38095 | AD8: =ELEC!Q8 -> 18000 | AE8: =SUM(AD8/Z8) -> 857.14286 | AF8: =SUM(AE8/1600) -> 0.53571429 | AG8: =SUM(320*AF8) -> 171.42857 | AH8: =SUM(AC8-AG8) -> 4.952381 | AI8: =AD8*AJ8 -> 4632.9114 | AJ8: =305/1185 -> 0.25738397 | AK8: =AI8/Z8 -> 220.61483
A9: =ELEC!C9 -> 44019 | B9: 8814 | C9: =B9-B8 -> 0 | D9: 176540 | E9: =SUM(D9-D8) -> 0 | F9: =IF(C9>0,E9/C9,0) -> 0 | H9: =H8 -> 8770 | I9: =IF(B9-H9<=0,"ok","oil change") -> oil change | J9: 10698 | K9: =J9-J8 -> 0 | L9: =L8 -> 238500 | M9: =SUM(L9-L8) -> 0 | N9: =IF(K9>0,M9/K9,0) -> 0 | P9: =P8 -> 10873 | Q9: =IF(J9-P9<=0,"ok","oil change") -> ok | R9: 11347 | S9: =R9-R8 -> 18 | T9: 283947 | U9: =SUM(T9-T8) -> 3742 | V9: =IF(S9>0,U9/S9,0) -> 207.88889 | X9: =X8 -> 12069 | Y9: =IF(R9-X9<=0,"ok","oil change") -> ok | Z9: =C9+K9+S9 -> 18 | AA9: =U9+M9+E9 -> 3742 | AB9: =V9+N9+F9 -> 207.88889 | AC9: =IF(Z9>0,AA9/Z9,0) -> 207.88889 | AD9: =ELEC!Q9 -> 15000 | AE9: =SUM(AD9/Z9) -> 833.33333 | AF9: =SUM(AE9/1600) -> 0.52083333 | AG9: =SUM(320*AF9) -> 166.66667 | AH9: =SUM(AC9-AG9) -> 41.222222 | AI9: =AD9*AJ9 -> 3860.7595 | AJ9: 0.25738397 | AK9: =IF(Z9>0,AI9/Z9,0) -> 214.48664
A10: =ELEC!C10 -> 44020 | B10: 8816 | C10: =B10-B9 -> 2 | D10: 177318 | E10: =SUM(D10-D9) -> 778 | F10: =IF(C10>0,E10/C10,0) -> 389 | H10: =H9 -> 8770 | I10: =IF(B10-H10<=0,"ok","oil change") -> oil change | J10: 10698 | K10: =J10-J9 -> 0 | L10: 238500 | M10: =SUM(L10-L9) -> 0 | N10: =IF(K10>0,M10/K10,0) -> 0 | P10: 10873 | Q10: =IF(J10-P10<=0,"ok","oil change") -> ok | R10: 11369 | S10: =R10-R9 -> 22 | T10: 287489 | U10: =SUM(T10-T9) -> 3542 | V10: =IF(S10>0,U10/S10,0) -> 161 | X10: =X9 -> 12069 | Y10: =IF(R10-X10<=0,"ok","oil change") -> ok | Z10: =C10+K10+S10 -> 24 | AA10: =U10+M10+E10 -> 4320 | AB10: =V10+N10+F10 -> 550 | AC10: =IF(Z10>0,AA10/Z10,0) -> 180 | AD10: =ELEC!Q10 -> 15000 | AE10: =SUM(AD10/Z10) -> 625 | AF10: =SUM(AE10/1600) -> 0.390625 | AG10: =SUM(320*AF10) -> 125 | AH10: =SUM(AC10-AG10) -> 55 | AI10: =AD10*AJ10 -> 3860.7595 | AJ10: =305/1185 -> 0.25738397 | AK10: =IF(Z10>0,AI10/Z10,0) -> 160.86498
A11: =ELEC!C11 -> 44021 | B11: 8828 | C11: =B11-B10 -> 12 | D11: 178121 | E11: =SUM(D11-D10) -> 803 | F11: =IF(C11>0,E11/C11,0) -> 66.916667 | H11: =H10 -> 8770 | I11: =IF(B11-H11<=0,"ok","oil change") -> oil change | J11: 10698 | K11: =J11-J10 -> 0 | L11: 238500 | M11: =SUM(L11-L10) -> 0 | N11: =IF(K11>0,M11/K11,0) -> 0 | P11: =P10 -> 10873 | Q11: =IF(J11-P11<=0,"ok","oil change") -> ok | R11: 11375 | S11: =R11-R10 -> 6 | T11: 289463 | U11: =SUM(T11-T10) -> 1974 | V11: =IF(S11>0,U11/S11,0) -> 329 | X11: =X10 -> 12069 | Y11: =IF(R11-X11<=0,"ok","oil change") -> ok | Z11: =C11+K11+S11 -> 18 | AA11: =U11+M11+E11 -> 2777 | AB11: =V11+N11+F11 -> 395.91667 | AC11: =IF(Z11>0,AA11/Z11,0) -> 154.27778 | AD11: =ELEC!Q11 -> 20000 | AE11: =SUM(AD11/Z11) -> 1111.1111 | AF11: =SUM(AE11/1600) -> 0.69444444 | AG11: =SUM(320*AF11) -> 222.22222 | AH11: =SUM(AC11-AG11) -> -67.944444 | AI11: =AD11*AJ11 -> 5147.6793 | AJ11: =305/1185 -> 0.25738397 | AK11: =IF(Z11>0,AI11/Z11,0) -> 285.98218
A12: =ELEC!C12 -> 44022 | B12: 8830 | C12: =B12-B11 -> 2 | D12: 178272 | E12: =SUM(D12-D11) -> 151 | F12: =IF(C12>0,E12/C12,0) -> 75.5 | H12: =H11 -> 8770 | I12: =IF(B12-H12<=0,"ok","oil change") -> oil change | J12: =J11 -> 10698 | K12: =J12-J11 -> 0 | L12: =L11 -> 238500 | M12: =SUM(L12-L11) -> 0 | N12: =IF(K12>0,M12/K12,0) -> 0 | P12: =P11 -> 10873 | Q12: =IF(J12-P12<=0,"ok","oil change") -> ok | R12: 11394 | S12: =R12-R11 -> 19 | T12: 292548 | U12: =SUM(T12-T11) -> 3085 | V12: =IF(S12>0,U12/S12,0) -> 162.36842 | X12: =X11 -> 12069 | Y12: =IF(R12-X12<=0,"ok","oil change") -> ok | Z12: =C12+K12+S12 -> 21 | AA12: =U12+M12+E12 -> 3236 | AB12: =V12+N12+F12 -> 237.86842 | AC12: =IF(Z12>0,AA12/Z12,0) -> 154.09524 | AD12: =ELEC!Q12 -> 17000 | AE12: =SUM(AD12/Z12) -> 809.52381 | AF12: =SUM(AE12/1600) -> 0.50595238 | AG12: =SUM(320*AF12) -> 161.90476 | AH12: =SUM(AC12-AG12) -> -7.8095238 | AI12: =AD12*AJ12 -> 4375.5274 | AJ12: =305/1185 -> 0.25738397 | AK12: =IF(Z12>0,AI12/Z12,0) -> 208.35845
A13: =ELEC!C13 -> 44023 | B13: 8834 | C13: =B13-B12 -> 4 | D13: 179136 | E13: =SUM(D13-D12) -> 864 | F13: =IF(C13>0,E13/C13,0) -> 216 | H13: =H12 -> 8770 | I13: =IF(B13-H13<=0,"ok","oil change") -> oil change | J13: =J12 -> 10698 | K13: =J13-J12 -> 0 | L13: =L12 -> 238500 | M13: =SUM(L13-L12) -> 0 | N13: =IF(K13>0,M13/K13,0) -> 0 | P13: =P12 -> 10873 | Q13: =IF(J13-P13<=0,"ok","oil change") -> ok | R13: 11409 | S13: =R13-R12 -> 15 | T13: 295054 | U13: =SUM(T13-T12) -> 2506 | V13: =IF(S13>0,U13/S13,0) -> 167.06667 | X13: =X12+180 -> 12249 | Y13: =IF(R13-X13<=0,"ok","oil change") -> ok | Z13: =C13+K13+S13 -> 19 | AA13: =U13+M13+E13 -> 3370 | AB13: =V13+N13+F13 -> 383.06667 | AC13: =IF(Z13>0,AA13/Z13,0) -> 177.36842 | AD13: =ELEC!Q13 -> 18000 | AE13: =SUM(AD13/Z13) -> 947.36842 | AF13: =SUM(AE13/1600) -> 0.59210526 | AG13: =SUM(320*AF13) -> 189.47368 | AH13: =SUM(AC13-AG13) -> -12.105263 | AI13: =AD13*AJ13 -> 4632.9114 | AJ13: =305/1185 -> 0.25738397 | AK13: =IF(Z13>0,AI13/Z13,0) -> 243.83744
A14: =ELEC!C14 -> 44024 | B14: 8850 | C14: =B14-B13 -> 16 | D14: 180221 | E14: =SUM(D14-D13) -> 1085 | F14: =IF(C14>0,E14/C14,0) -> 67.8125 | H14: =H13 -> 8770 | I14: =IF(B14-H14<=0,"ok","oil change") -> oil change | J14: 10698 | K14: =J14-J13 -> 0 | L14: =L13 -> 238500 | M14: =SUM(L14-L13) -> 0 | N14: =IF(K14>0,M14/K14,0) -> 0 | P14: =P13 -> 10873 | Q14: =IF(J14-P14<=0,"ok","oil change") -> ok | R14: 11415 | S14: =R14-R13 -> 6 | T14: 296420 | U14: =SUM(T14-T13) -> 1366 | V14: =IF(S14>0,U14/S14,0) -> 227.66667 | X14: =X13 -> 12249 | Y14: =IF(R14-X14<=0,"ok","oil change") -> ok | Z14: =C14+K14+S14 -> 22 | AA14: =U14+M14+E14 -> 2451 | AB14: =V14+N14+F14 -> 295.47917 | AC14: =IF(Z14>0,AA14/Z14,0) -> 111.40909 | AD14: =ELEC!Q14 -> 19000 | AE14: =SUM(AD14/Z14) -> 863.63636 | AF14: =SUM(AE14/1600) -> 0.53977273 | AG14: =SUM(320*AF14) -> 172.72727 | AH14: =SUM(AC14-AG14) -> -61.318182 | AI14: =AD14*AJ14 -> 4890.2954 | AJ14: =305/1185 -> 0.25738397 | AK14: =IF(Z14>0,AI14/Z14,0) -> 222.28615
A15: =ELEC!C15 -> 44025 | B15: 8853 | C15: =B15-B14 -> 3 | D15: 180547 | E15: =SUM(D15-D14) -> 326 | F15: =IF(C15>0,E15/C15,0) -> 108.66667 | H15: =H14 -> 8770 | I15: =IF(B15-H15<=0,"ok","oil change") -> oil change | J15: 10698 | K15: =J15-J14 -> 0 | L15: =L14 -> 238500 | M15: =SUM(L15-L14) -> 0 | N15: =IF(K15>0,M15/K15,0) -> 0 | P15: =P14 -> 10873 | Q15: =IF(J15-P15<=0,"ok","oil change") -> ok | R15: 11430 | S15: =R15-R14 -> 15 | T15: 298881 | U15: =SUM(T15-T14) -> 2461 | V15: =IF(S15>0,U15/S15,0) -> 164.06667 | X15: =X14 -> 12249 | Y15: =IF(R15-X15<=0,"ok","oil change") -> ok | Z15: =C15+K15+S15 -> 18 | AA15: =U15+M15+E15 -> 2787 | AB15: =V15+N15+F15 -> 272.73333 | AC15: =IF(Z15>0,AA15/Z15,0) -> 154.83333 | AD15: =ELEC!Q15 -> 14000 | AE15: =SUM(AD15/Z15) -> 777.77778 | AF15: =SUM(AE15/1600) -> 0.48611111 | AG15: =SUM(320*AF15) -> 155.55556 | AH15: =SUM(AC15-AG15) -> -0.72222222 | AI15: =AD15*AJ15 -> 3603.3755 | AJ15: =305/1185 -> 0.25738397 | AK15: =IF(Z15>0,AI15/Z15,0) -> 200.18753
A16: =ELEC!C16 -> 44026 | B16: 8860 | C16: =B16-B15 -> 7 | D16: 181036 | E16: =SUM(D16-D15) -> 489 | F16: =IF(C16>0,E16/C16,0) -> 69.857143 | H16: =H15 -> 8770 | I16: =IF(B16-H16<=0,"ok","oil change") -> oil change | J16: =J15 -> 10698 | K16: =J16-J15 -> 0 | L16: =L15 -> 238500 | M16: =SUM(L16-L15) -> 0 | N16: =IF(K16>0,M16/K16,0) -> 0 | P16: =P15 -> 10873 | Q16: =IF(J16-P16<=0,"ok","oil change") -> ok | R16: 11445 | S16: =R16-R15 -> 15 | T16: 301793 | U16: =SUM(T16-T15) -> 2912 | V16: =IF(S16>0,U16/S16,0) -> 194.13333 | X16: =X15 -> 12249 | Y16: =IF(R16-X16<=0,"ok","oil change") -> ok | Z16: =C16+K16+S16 -> 22 | AA16: =U16+M16+E16 -> 3401 | AB16: =V16+N16+F16 -> 263.99048 | AC16: =IF(Z16>0,AA16/Z16,0) -> 154.59091 | AD16: =ELEC!Q16 -> 18000 | AE16: =SUM(AD16/Z16) -> 818.18182 | AF16: =SUM(AE16/1600) -> 0.51136364 | AG16: =SUM(320*AF16) -> 163.63636 | AH16: =SUM(AC16-AG16) -> -9.0454545 | AI16: =AD16*AJ16 -> 4632.9114 | AJ16: =305/1185 -> 0.25738397 | AK16: =IF(Z16>0,AI16/Z16,0) -> 210.58688
A17: =ELEC!C17 -> 44027 | B17: 8871 | C17: =B17-B16 -> 11 | D17: 182388 | E17: =SUM(D17-D16) -> 1352 | F17: =IF(C17>0,E17/C17,0) -> 122.90909 | H17: =H16 -> 8770 | I17: =IF(B17-H17<=0,"ok","oil change") -> oil change | J17: 10698 | K17: =J17-J16 -> 0 | L17: 238500 | M17: =SUM(L17-L16) -> 0 | N17: =IF(K17>0,M17/K17,0) -> 0 | P17: =P16 -> 10873 | Q17: =IF(J17-P17<=0,"ok","oil change") -> ok | R17: 11452 | S17: =R17-R16 -> 7 | T17: 303591 | U17: =SUM(T17-T16) -> 1798 | V17: =IF(S17>0,U17/S17,0) -> 256.85714 | X17: =X16 -> 12249 | Y17: =IF(R17-X17<=0,"ok","oil change") -> ok | Z17: =C17+K17+S17 -> 18 | AA17: =U17+M17+E17 -> 3150 | AB17: =V17+N17+F17 -> 379.76623 | AC17: =IF(Z17>0,AA17/Z17,0) -> 175 | AD17: =ELEC!Q17 -> 17000 | AE17: =SUM(AD17/Z17) -> 944.44444 | AF17: =SUM(AE17/1600) -> 0.59027778 | AG17: =SUM(320*AF17) -> 188.88889 | AH17: =SUM(AC17-AG17) -> -13.888889 | AI17: =AD17*AJ17 -> 4375.5274 | AJ17: =305/1185 -> 0.25738397 | AK17: =IF(Z17>0,AI17/Z17,0) -> 243.08486
A18: =ELEC!C18 -> 44028 | B18: 8879 | C18: =B18-B17 -> 8 | D18: 183419 | E18: =SUM(D18-D17) -> 1031 | F18: =IF(C18>0,E18/C18,0) -> 128.875 | H18: =H17 -> 8770 | I18: =IF(B18-H18<=0,"ok","oil change") -> oil change | J18: 10698 | K18: =J18-J17 -> 0 | L18: =L17 -> 238500 | M18: =SUM(L18-L17) -> 0 | N18: =IF(K18>0,M18/K18,0) -> 0 | P18: =P17 -> 10873 | Q18: =IF(J18-P14<=0,"ok","oil change") -> ok | R18: 11465 | S18: =R18-R17 -> 13 | T18: 305926 | U18: =SUM(T18-T17) -> 2335 | V18: =IF(S18>0,U18/S18,0) -> 179.61538 | X18: =X17 -> 12249 | Y18: =IF(R18-X18<=0,"ok","oil change") -> ok | Z18: =C18+K18+S18 -> 21 | AA18: =U18+M18+E18 -> 3366 | AB18: =V18+N18+F18 -> 308.49038 | AC18: =IF(Z18>0,AA18/Z18,0) -> 160.28571 | AD18: =ELEC!Q18 -> 19000 | AE18: =SUM(AD18/Z18) -> 904.7619 | AF18: =SUM(AE18/1600) -> 0.56547619 | AG18: =SUM(320*AF18) -> 180.95238 | AH18: =SUM(AC18-AG18) -> -20.666667 | AI18: =AD18*AJ18 -> 4890.2954 | AJ18: =305/1185 -> 0.25738397 | AK18: =IF(Z18>0,AI18/Z18,0) -> 232.87121
A19: =ELEC!C19 -> 44029 | B19: =B18 -> 8879 | C19: =B19-B18 -> 0 | D19: =D18 -> 183419 | E19: =SUM(D19-D18) -> 0 | F19: =IF(C19>0,E19/C19,0) -> 0 | H19: =H18 -> 8770 | I19: =IF(B19-H19<=0,"ok","oil change") -> oil change | J19: =J18 -> 10698 | K19: =J19-J18 -> 0 | L19: =L18 -> 238500 | M19: =SUM(L19-L18) -> 0 | N19: =IF(K19>0,M19/K19,0) -> 0 | P19: =P18 -> 10873 | Q19: =IF(J19-P19<=0,"ok","oil change") -> ok | R19: =R18 -> 11465 | S19: =R19-R18 -> 0 | T19: =T18 -> 305926 | U19: =SUM(T19-T18) -> 0 | V19: =IF(S19>0,U19/S19,0) -> 0 | X19: =X18 -> 12249 | Y19: =IF(R19-X19<=0,"ok","oil change") -> ok | Z19: =C19+K19+S19 -> 0 | AA19: =U19+M19+E19 -> 0 | AB19: =V19+N19+F19 -> 0 | AC19: =IF(Z19>0,AA19/Z19,0) -> 0 | AD19: =ELEC!Q19 -> 0 | AE19: =SUM(AD19/Z19) -> #DIV/0! | AF19: =SUM(AE19/1600) -> #DIV/0! | AG19: =SUM(320*AF19) -> #DIV/0! | AH19: =SUM(AC19-AG19) -> #DIV/0! | AI19: =AD19*AJ19 -> 0 | AJ19: =305/1185 -> 0.25738397 | AK19: =IF(Z19>0,AI19/Z19,0) -> 0
A20: =ELEC!C20 -> 44030 | B20: =B19 -> 8879 | C20: =B20-B19 -> 0 | D20: =D19 -> 183419 | E20: =SUM(D20-D19) -> 0 | F20: =IF(C20>0,E20/C20,0) -> 0 | H20: =H19 -> 8770 | I20: =IF(B20-H20<=0,"ok","oil change") -> oil change | J20: =J19 -> 10698 | K20: =J20-J19 -> 0 | L20: =L19 -> 238500 | M20: =SUM(L20-L19) -> 0 | N20: =IF(K20>0,M20/K20,0) -> 0 | P20: =P19 -> 10873 | Q20: =IF(J20-P20<=0,"ok","oil change") -> ok | R20: =R19 -> 11465 | S20: =R20-R19 -> 0 | T20: =T19 -> 305926 | U20: =SUM(T20-T19) -> 0 | V20: =IF(S20>0,U20/S20,0) -> 0 | X20: =X19 -> 12249 | Y20: =IF(R20-X20<=0,"ok","oil change") -> ok | Z20: =C20+K20+S20 -> 0 | AA20: =U20+M20+E20 -> 0 | AB20: =V20+N20+F20 -> 0 | AC20: =IF(Z20>0,AA20/Z20,0) -> 0 | AD20: =ELEC!Q20 -> 0 | AE20: =SUM(AD20/Z20) -> #DIV/0! | AF20: =SUM(AE20/1600) -> #DIV/0! | AG20: =SUM(320*AF20) -> #DIV/0! | AH20: =SUM(AC20-AG20) -> #DIV/0! | AI20: =AD20*AJ20 -> 0 | AJ20: =305/1185 -> 0.25738397 | AK20: =IF(Z20>0,AI20/Z20,0) -> 0
A21: =ELEC!C21 -> 44031 | B21: =B20 -> 8879 | C21: =B21-B20 -> 0 | D21: =D20 -> 183419 | E21: =SUM(D21-D20) -> 0 | F21: =IF(C21>0,E21/C21,0) -> 0 | H21: =H20 -> 8770 | I21: =IF(B21-H21<=0,"ok","oil change") -> oil change | J21: =J20 -> 10698 | K21: =J21-J20 -> 0 | L21: =L20 -> 238500 | M21: =SUM(L21-L20) -> 0 | N21: =IF(K21>0,M21/K21,0) -> 0 | P21: =P20 -> 10873 | Q21: =IF(J21-P21<=0,"ok","oil change") -> ok | R21: =R20 -> 11465 | S21: =R21-R20 -> 0 | T21: =T20 -> 305926 | U21: =SUM(T21-T20) -> 0 | V21: =IF(S21>0,U21/S21,0) -> 0 | X21: =X20 -> 12249 | Y21: =Y20 -> ok | Z21: =C21+K21+S21 -> 0 | AA21: =U21+M21+E21 -> 0 | AB21: =V21+N21+F21 -> 0 | AC21: =IF(Z21>0,AA21/Z21,0) -> 0 | AD21: =ELEC!Q21 -> 0 | AE21: =SUM(AD21/Z21) -> #DIV/0! | AF21: =SUM(AE21/1600) -> #DIV/0! | AG21: =SUM(320*AF21) -> #DIV/0! | AH21: =SUM(AC21-AG21) -> #DIV/0! | AI21: =AD21*AJ21 -> 0 | AJ21: =305/1185 -> 0.25738397 | AK21: =IF(Z21>0,AI21/Z21,0) -> 0
A22: =ELEC!C22 -> 44032 | B22: =B21 -> 8879 | C22: =B22-B21 -> 0 | D22: =D21 -> 183419 | E22: =SUM(D22-D21) -> 0 | F22: =IF(C22>0,E22/C22,0) -> 0 | H22: =H21 -> 8770 | I22: =IF(B22-H22<=0,"ok","oil change") -> oil change | J22: =J21 -> 10698 | K22: =J22-J21 -> 0 | L22: =L21 -> 238500 | M22: =SUM(L22-L21) -> 0 | N22: =IF(K22>0,M22/K22,0) -> 0 | P22: =P21 -> 10873 | Q22: =IF(J22-P22<=0,"ok","oil change") -> ok | R22: =R21 -> 11465 | S22: =R22-R21 -> 0 | T22: =T21 -> 305926 | U22: =SUM(T22-T21) -> 0 | V22: =IF(S22>0,U22/S22,0) -> 0 | X22: =X21 -> 12249 | Y22: =IF(R22-X22<=0,"ok","oil change") -> ok | Z22: =C22+K22+S22 -> 0 | AA22: =U22+M22+E22 -> 0 | AB22: =V22+N22+F22 -> 0 | AC22: =IF(Z22>0,AA22/Z22,0) -> 0 | AD22: =ELEC!Q22 -> 0 | AE22: =SUM(AD22/Z22) -> #DIV/0! | AF22: =SUM(AE22/1600) -> #DIV/0! | AG22: =SUM(320*AF22) -> #DIV/0! | AH22: =SUM(AC22-AG22) -> #DIV/0! | AI22: =AD22*AJ22 -> 0 | AJ22: =305/1185 -> 0.25738397 | AK22: =IF(Z22>0,AI22/Z22,0) -> 0
A23: =ELEC!C23 -> 44033 | B23: =B22 -> 8879 | C23: =B23-B22 -> 0 | D23: =D22 -> 183419 | E23: =SUM(D23-D22) -> 0 | F23: =IF(C23>0,E23/C23,0) -> 0 | H23: =H22 -> 8770 | I23: =IF(B23-H23<=0,"ok","oil change") -> oil change | J23: =J22 -> 10698 | K23: =J23-J22 -> 0 | L23: =L22 -> 238500 | M23: =SUM(L23-L22) -> 0 | N23: =IF(K23>0,M23/K23,0) -> 0 | P23: =P22 -> 10873 | Q23: =IF(J23-P23<=0,"ok","oil change") -> ok | R23: =R22 -> 11465 | S23: =R23-R22 -> 0 | T23: =T22 -> 305926 | U23: =SUM(T23-T22) -> 0 | V23: =IF(S23>0,U23/S23,0) -> 0 | X23: =X22 -> 12249 | Y23: =IF(R23-X23<=0,"ok","oil change") -> ok | Z23: =C23+K23+S23 -> 0 | AA23: =U23+M23+E23 -> 0 | AB23: =V23+N23+F23 -> 0 | AC23: =IF(Z23>0,AA23/Z23,0) -> 0 | AD23: =ELEC!Q23 -> 0 | AE23: =SUM(AD23/Z23) -> #DIV/0! | AF23: =SUM(AE23/1600) -> #DIV/0! | AG23: =SUM(320*AF23) -> #DIV/0! | AH23: =SUM(AC23-AG23) -> #DIV/0! | AI23: =AD23*AJ23 -> 0 | AJ23: =305/1185 -> 0.25738397 | AK23: =IF(Z23>0,AI23/Z23,0) -> 0
A24: =ELEC!C24 -> 44034 | B24: =B23 -> 8879 | C24: =B24-B23 -> 0 | D24: =D23 -> 183419 | E24: =SUM(D24-D23) -> 0 | F24: =IF(C24>0,E24/C24,0) -> 0 | H24: =H23 -> 8770 | I24: =IF(B24-H24<=0,"ok","oil change") -> oil change | J24: =J23 -> 10698 | K24: =J24-J23 -> 0 | L24: =L23 -> 238500 | M24: =SUM(L24-L23) -> 0 | N24: =IF(K24>0,M24/K24,0) -> 0 | P24: =P23 -> 10873 | Q24: =IF(J24-P24<=0,"ok","oil change") -> ok | R24: =R23 -> 11465 | S24: =R24-R23 -> 0 | T24: =T23 -> 305926 | U24: =SUM(T24-T23) -> 0 | V24: =IF(S24>0,U24/S24,0) -> 0 | X24: =X23 -> 12249 | Y24: =IF(R24-X24<=0,"ok","oil change") -> ok | Z24: =C24+K24+S24 -> 0 | AA24: =U24+M24+E24 -> 0 | AB24: =V24+N24+F24 -> 0 | AC24: =IF(Z24>0,AA24/Z24,0) -> 0 | AD24: =ELEC!Q24 -> 0 | AE24: =SUM(AD24/Z24) -> #DIV/0! | AF24: =SUM(AE24/1600) -> #DIV/0! | AG24: =SUM(320*AF24) -> #DIV/0! | AH24: =SUM(AC24-AG24) -> #DIV/0! | AI24: =AD24*AJ24 -> 0 | AJ24: =305/1185 -> 0.25738397 | AK24: =IF(Z24>0,AI24/Z24,0) -> 0
A25: =ELEC!C25 -> 44035 | B25: =B24 -> 8879 | C25: =B25-B24 -> 0 | D25: =D24 -> 183419 | E25: =SUM(D25-D24) -> 0 | F25: =IF(C25>0,E25/C25,0) -> 0 | H25: 8770 | I25: =IF(B25-H25<=0,"ok","oil change") -> oil change | J25: =J24 -> 10698 | K25: =J25-J24 -> 0 | L25: =L24 -> 238500 | M25: =SUM(L25-L24) -> 0 | N25: =IF(K25>0,M25/K25,0) -> 0 | P25: =P24 -> 10873 | Q25: =IF(J25-P25<=0,"ok","oil change") -> ok | R25: =R24 -> 11465 | S25: =R25-R24 -> 0 | T25: =T24 -> 305926 | U25: =SUM(T25-T24) -> 0 | V25: =IF(S25>0,U25/S25,0) -> 0 | X25: =X24 -> 12249 | Y25: =IF(R25-X25<=0,"ok","oil change") -> ok | Z25: =C25+K25+S25 -> 0 | AA25: =U25+M25+E25 -> 0 | AB25: =V25+N25+F25 -> 0 | AC25: =IF(Z25>0,AA25/Z25,0) -> 0 | AD25: =ELEC!Q25 -> 0 | AE25: =SUM(AD25/Z25) -> #DIV/0! | AF25: =SUM(AE25/1600) -> #DIV/0! | AG25: =SUM(320*AF25) -> #DIV/0! | AH25: =SUM(AC25-AG25) -> #DIV/0! | AI25: =AD25*AJ25 -> 0 | AJ25: =305/1185 -> 0.25738397 | AK25: =IF(Z25>0,AI25/Z25,0) -> 0
A26: =ELEC!C26 -> 44036 | B26: =B25 -> 8879 | C26: =B26-B25 -> 0 | D26: =D25 -> 183419 | E26: =SUM(D26-D25) -> 0 | F26: =IF(C26>0,E26/C26,0) -> 0 | H26: =H25 -> 8770 | I26: =IF(B26-H26<=0,"ok","oil change") -> oil change | J26: =J25 -> 10698 | K26: =J26-J25 -> 0 | L26: =L25 -> 238500 | M26: =SUM(L26-L25) -> 0 | N26: =IF(K26>0,M26/K26,0) -> 0 | P26: =P25 -> 10873 | Q26: =IF(J26-P26<=0,"ok","oil change") -> ok | R26: =R25 -> 11465 | S26: =R26-R25 -> 0 | T26: =T25 -> 305926 | U26: =SUM(T26-T25) -> 0 | V26: =IF(S26>0,U26/S26,0) -> 0 | X26: =X25 -> 12249 | Y26: =IF(R26-X26<=0,"ok","oil change") -> ok | Z26: =C26+K26+S26 -> 0 | AA26: =U26+M26+E26 -> 0 | AB26: =V26+N26+F26 -> 0 | AC26: =IF(Z26>0,AA26/Z26,0) -> 0 | AD26: =ELEC!Q26 -> 0 | AE26: =SUM(AD26/Z26) -> #DIV/0! | AF26: =SUM(AE26/1600) -> #DIV/0! | AG26: =SUM(320*AF26) -> #DIV/0! | AH26: =SUM(AC26-AG26) -> #DIV/0! | AI26: =AD26*AJ26 -> 0 | AJ26: =305/1185 -> 0.25738397 | AK26: =IF(Z26>0,AI26/Z26,0) -> 0
A27: =ELEC!C27 -> 44037 | B27: =B26 -> 8879 | C27: =B27-B26 -> 0 | D27: =D26 -> 183419 | E27: =SUM(D27-D26) -> 0 | F27: =IF(C27>0,E27/C27,0) -> 0 | H27: =H26 -> 8770 | I27: =IF(B27-H27<=0,"ok","oil change") -> oil change | J27: =J26 -> 10698 | K27: =J27-J26 -> 0 | L27: =L26 -> 238500 | M27: =SUM(L27-L26) -> 0 | N27: =IF(K27>0,M27/K27,0) -> 0 | P27: =P26 -> 10873 | Q27: =IF(J27-P27<=0,"ok","oil change") -> ok | R27: =R26 -> 11465 | S27: =R27-R26 -> 0 | T27: =T26 -> 305926 | U27: =SUM(T27-T26) -> 0 | V27: =IF(S27>0,U27/S27,0) -> 0 | X27: =X26 -> 12249 | Y27: =IF(R27-X27<=0,"ok","oil change") -> ok | Z27: =C27+K27+S27 -> 0 | AA27: =U27+M27+E27 -> 0 | AB27: =V27+N27+F27 -> 0 | AC27: =IF(Z27>0,AA27/Z27,0) -> 0 | AD27: =ELEC!Q27 -> 0 | AE27: =SUM(AD27/Z27) -> #DIV/0! | AF27: =SUM(AE27/1600) -> #DIV/0! | AG27: =SUM(320*AF27) -> #DIV/0! | AH27: =SUM(AC27-AG27) -> #DIV/0! | AI27: =AD27*AJ27 -> 0 | AJ27: =305/1185 -> 0.25738397 | AK27: =IF(Z27>0,AI27/Z27,0) -> 0
A28: =ELEC!C28 -> 44038 | B28: =B27 -> 8879 | C28: =B28-B27 -> 0 | D28: =D27 -> 183419 | E28: =SUM(D28-D27) -> 0 | F28: =IF(C28>0,E28/C28,0) -> 0 | H28: =H27 -> 8770 | I28: =IF(B28-H28<=0,"ok","oil change") -> oil change | J28: =J27 -> 10698 | K28: =J28-J27 -> 0 | L28: =L27 -> 238500 | M28: =SUM(L28-L27) -> 0 | N28: =IF(K28>0,M28/K28,0) -> 0 | P28: =P27 -> 10873 | Q28: =IF(J28-P28<=0,"ok","oil change") -> ok | R28: =R27 -> 11465 | S28: =R28-R27 -> 0 | T28: =T27 -> 305926 | U28: =SUM(T28-T27) -> 0 | V28: =IF(S28>0,U28/S28,0) -> 0 | X28: =X27 -> 12249 | Y28: =IF(R28-X28<=0,"ok","oil change") -> ok | Z28: =C28+K28+S28 -> 0 | AA28: =U28+M28+E28 -> 0 | AB28: =V28+N28+F28 -> 0 | AC28: =IF(Z28>0,AA28/Z28,0) -> 0 | AD28: =ELEC!Q28 -> 0 | AE28: =SUM(AD28/Z28) -> #DIV/0! | AF28: =SUM(AE28/1600) -> #DIV/0! | AG28: =SUM(320*AF28) -> #DIV/0! | AH28: =SUM(AC28-AG28) -> #DIV/0! | AI28: =AD28*AJ28 -> 0 | AJ28: =305/1185 -> 0.25738397 | AK28: =IF(Z28>0,AI28/Z28,0) -> 0
A29: =ELEC!C29 -> 44039 | B29: =B28 -> 8879 | C29: =B29-B28 -> 0 | D29: =D28 -> 183419 | E29: =SUM(D29-D28) -> 0 | F29: =IF(C29>0,E29/C29,0) -> 0 | H29: =H28 -> 8770 | I29: =IF(B29-H29<=0,"ok","oil change") -> oil change | J29: =J28 -> 10698 | K29: =J29-J28 -> 0 | L29: =L28 -> 238500 | M29: =SUM(L29-L28) -> 0 | N29: =IF(K29>0,M29/K29,0) -> 0 | P29: =P28 -> 10873 | Q29: =IF(J29-P29<=0,"ok","oil change") -> ok | R29: =R28 -> 11465 | S29: =R29-R28 -> 0 | T29: =T28 -> 305926 | U29: =SUM(T29-T28) -> 0 | V29: =IF(S29>0,U29/S29,0) -> 0 | X29: =X28 -> 12249 | Y29: =IF(R29-X29<=0,"ok","oil change") -> ok | Z29: =C29+K29+S29 -> 0 | AA29: =U29+M29+E29 -> 0 | AB29: =V29+N29+F29 -> 0 | AC29: =IF(Z29>0,AA29/Z29,0) -> 0 | AD29: =ELEC!Q29 -> 0 | AE29: =SUM(AD29/Z29) -> #DIV/0! | AF29: =SUM(AE29/1600) -> #DIV/0! | AG29: =SUM(320*AF29) -> #DIV/0! | AH29: =SUM(AC29-AG29) -> #DIV/0! | AI29: =AD29*AJ29 -> 0 | AJ29: =305/1185 -> 0.25738397 | AK29: =IF(Z29>0,AI29/Z29,0) -> 0
