Workbook

Sheet Total
A1: Site Name | B1: Day | C1: Month | D1: Year | E1: Total Electricity Kwh | F1: Electricity Tariff ($/Kwh) | G1: LPG (Kg) | H1: LPG $/Kg | I1: Water Utility Supply (m3) m3 | J1: Water Utility Supply (m3) $/m3 | K1: Room Nights | L1: Utilities day cost dh
A2: Serengeti | B2: 1 | C2: 8 | D2: 2020 | E2: ='UTILITY REPORT 1'!F3 -> 1872 | F2: =('UTILITY REPORT 1'!E3*'UTILITY REPORT 1'!D3)/'UTILITY REPORT 1'!F3 -> 0.39605769 | G2: =IF('Utility summery'!M6<0,"0",'Utility summery'!M6) -> 315873.14 | H2: 0 | I2: =IF('UTILITY REPORT 1'!G3<0,"0",'UTILITY REPORT 1'!G3) -> 51 | J2: 0 | K2: ='UTILITY REPORT 1'!C3 -> 0 | L2: =E2*F2+G2*H2+#REF!*#REF!+I2*J2 -> #REF!
A3: Serengeti | B3: =B2+1 -> 2 | C3: 8 | D3: 2020 | E3: ='UTILITY REPORT 1'!F4 -> 2030 | F3: =('UTILITY REPORT 1'!E4*'UTILITY REPORT 1'!D4)/'UTILITY REPORT 1'!F4 -> 0.38525123 | G3: =IF('Utility summery'!M7<0,"0",'Utility summery'!M7) -> 25.784 | H3: 0 | I3: =IF('UTILITY REPORT 1'!G4<0,"0",'UTILITY REPORT 1'!G4) -> 53 | J3: 0 | K3: ='UTILITY REPORT 1'!C4 -> 0 | L3: =E3*F3+G3*H3+#REF!*#REF!+I3*J3 -> #REF!
A4: Serengeti | B4: =B3+1 -> 3 | C4: 8 | D4: 2020 | E4: ='UTILITY REPORT 1'!F5 -> 1818 | F4: =('UTILITY REPORT 1'!E5*'UTILITY REPORT 1'!D5)/'UTILITY REPORT 1'!F5 -> 0.43366887 | G4: =IF('Utility summery'!M8<0,"0",'Utility summery'!M8) -> 65.648 | H4: 0 | I4: =IF('UTILITY REPORT 1'!G5<0,"0",'UTILITY REPORT 1'!G5) -> 42 | J4: 0 | K4: ='UTILITY REPORT 1'!C5 -> 0 | L4: =E4*F4+G4*H4+#REF!*#REF!+I4*J4 -> #REF!
A5: Serengeti | B5: =B4+1 -> 4 | C5: 8 | D5: 2020 | E5: ='UTILITY REPORT 1'!F6 -> 1980 | F5: =('UTILITY REPORT 1'!E6*'UTILITY REPORT 1'!D6)/'UTILITY REPORT 1'!F6 -> 0.40081313 | G5: =IF('Utility summery'!M9<0,"0",'Utility summery'!M9) -> 22.704 | H5: 0 | I5: =IF('UTILITY REPORT 1'!G6<0,"0",'UTILITY REPORT 1'!G6) -> 67 | J5: 0 | K5: ='UTILITY REPORT 1'!C6 -> 0 | L5: =E5*F5+G5*H5+#REF!*#REF!+I5*J5 -> #REF!
A6: Serengeti | B6: =B5+1 -> 5 | C6: 8 | D6: 2020 | E6: ='UTILITY REPORT 1'!F7 -> 1724 | F6: =('UTILITY REPORT 1'!E7*'UTILITY REPORT 1'!D7)/'UTILITY REPORT 1'!F7 -> 0.45012761 | G6: =IF('Utility summery'!M10<0,"0",'Utility summery'!M10) -> 31.24 | H6: 0 | I6: =IF('UTILITY REPORT 1'!G7<0,"0",'UTILITY REPORT 1'!G7) -> 49 | J6: 0 | K6: ='UTILITY REPORT 1'!C7 -> 0 | L6: =E6*F6+G6*H6+#REF!*#REF!+I6*J6 -> #REF!
A7: Serengeti | B7: =B6+1 -> 6 | C7: 8 | D7: 2020 | E7: ='UTILITY REPORT 1'!F8 -> 1892 | F7: =('UTILITY REPORT 1'!E8*'UTILITY REPORT 1'!D8)/'UTILITY REPORT 1'!F8 -> 0.4112685 | G7: =IF('Utility summery'!M11<0,"0",'Utility summery'!M11) -> 8.448 | H7: 0 | I7: =IF('UTILITY REPORT 1'!G8<0,"0",'UTILITY REPORT 1'!G8) -> 66 | J7: 0 | K7: ='UTILITY REPORT 1'!C8 -> 0 | L7: =E7*F7+G7*H7+#REF!*#REF!+I7*J7 -> #REF!
A8: Serengeti | B8: =B7+1 -> 7 | C8: 8 | D8: 2020 | E8: ='UTILITY REPORT 1'!F9 -> 1882 | F8: =('UTILITY REPORT 1'!E9*'UTILITY REPORT 1'!D9)/'UTILITY REPORT 1'!F9 -> 0.41004251 | G8: =IF('Utility summery'!M12<0,"0",'Utility summery'!M12) -> 0 | H8: 0 | I8: =IF('UTILITY REPORT 1'!G9<0,"0",'UTILITY REPORT 1'!G9) -> 51 | J8: 0 | K8: ='UTILITY REPORT 1'!C9 -> 0 | L8: =E8*F8+G8*H8+#REF!*#REF!+I8*J8 -> #REF!
A9: Serengeti | B9: =B8+1 -> 8 | C9: 8 | D9: 2020 | E9: ='UTILITY REPORT 1'!F10 -> 0 | F9: =('UTILITY REPORT 1'!E10*'UTILITY REPORT 1'!D10)/'UTILITY REPORT 1'!F10 -> #DIV/0! | G9: =IF('Utility summery'!M13<0,"0",'Utility summery'!M13) -> 0 | H9: 0 | I9: =IF('UTILITY REPORT 1'!G10<0,"0",'UTILITY REPORT 1'!G10) -> 0 | J9: 0 | K9: ='UTILITY REPORT 1'!C10 -> 0 | L9: =E9*F9+G9*H9+#REF!*#REF!+I9*J9 -> #DIV/0!
A10: Serengeti | B10: =B9+1 -> 9 | C10: 8 | D10: 2020 | E10: ='UTILITY REPORT 1'!F11 -> 0 | F10: =('UTILITY REPORT 1'!E11*'UTILITY REPORT 1'!D11)/'UTILITY REPORT 1'!F11 -> #DIV/0! | G10: =IF('Utility summery'!M14<0,"0",'Utility summery'!M14) -> 0 | H10: 0 | I10: =IF('UTILITY REPORT 1'!G11<0,"0",'UTILITY REPORT 1'!G11) -> 0 | J10: 0 | K10: ='UTILITY REPORT 1'!C11 -> 0 | L10: =E10*F10+G10*H10+#REF!*#REF!+I10*J10 -> #DIV/0!
A11: Serengeti | B11: =B10+1 -> 10 | C11: 8 | D11: 2020 | E11: ='UTILITY REPORT 1'!F12 -> 0 | F11: =('UTILITY REPORT 1'!E12*'UTILITY REPORT 1'!D12)/'UTILITY REPORT 1'!F12 -> #DIV/0! | G11: =IF('Utility summery'!M15<0,"0",'Utility summery'!M15) -> 0 | H11: 0 | I11: =IF('UTILITY REPORT 1'!G12<0,"0",'UTILITY REPORT 1'!G12) -> 0 | J11: 0 | K11: ='UTILITY REPORT 1'!C12 -> 0 | L11: =E11*F11+G11*H11+#REF!*#REF!+I11*J11 -> #DIV/0!
A12: Serengeti | B12: =B11+1 -> 11 | C12: 8 | D12: 2020 | E12: ='UTILITY REPORT 1'!F13 -> 0 | F12: =('UTILITY REPORT 1'!E13*'UTILITY REPORT 1'!D13)/'UTILITY REPORT 1'!F13 -> #DIV/0! | G12: =IF('Utility summery'!M16<0,"0",'Utility summery'!M16) -> 0 | H12: 0 | I12: =IF('UTILITY REPORT 1'!G13<0,"0",'UTILITY REPORT 1'!G13) -> 0 | J12: 0 | K12: ='UTILITY REPORT 1'!C13 -> 0 | L12: =E12*F12+G12*H12+#REF!*#REF!+I12*J12 -> #DIV/0!
A13: Serengeti | B13: =B12+1 -> 12 | C13: 8 | D13: 2020 | E13: ='UTILITY REPORT 1'!F14 -> 0 | F13: =('UTILITY REPORT 1'!E14*'UTILITY REPORT 1'!D14)/'UTILITY REPORT 1'!F14 -> #DIV/0! | G13: =IF('Utility summery'!M17<0,"0",'Utility summery'!M17) -> 0 | H13: 0 | I13: =IF('UTILITY REPORT 1'!G14<0,"0",'UTILITY REPORT 1'!G14) -> 0 | J13: 0 | K13: ='UTILITY REPORT 1'!C14 -> 0 | L13: =E13*F13+G13*H13+#REF!*#REF!+I13*J13 -> #DIV/0!
A14: Serengeti | B14: =B13+1 -> 13 | C14: 8 | D14: 2020 | E14: ='UTILITY REPORT 1'!F15 -> 0 | F14: =('UTILITY REPORT 1'!E15*'UTILITY REPORT 1'!D15)/'UTILITY REPORT 1'!F15 -> #DIV/0! | G14: =IF('Utility summery'!M18<0,"0",'Utility summery'!M18) -> 0 | H14: 0 | I14: =IF('UTILITY REPORT 1'!G15<0,"0",'UTILITY REPORT 1'!G15) -> 0 | J14: 0 | K14: ='UTILITY REPORT 1'!C15 -> 0 | L14: =E14*F14+G14*H14+#REF!*#REF!+I14*J14 -> #DIV/0!
... A30: Serengeti | B30: =B29+1 -> 29 | C30: 8 | D30: 2020 | E30: ='UTILITY REPORT 1'!F31 -> 0 | F30: =('UTILITY REPORT 1'!E31*'UTILITY REPORT 1'!D31)/'UTILITY REPORT 1'!F31 -> #DIV/0! | G30: =IF('Utility summery'!M34<0,"0",'Utility summery'!M34) -> 0 | H30: 0 | I30: =IF('UTILITY REPORT 1'!G31<0,"0",'UTILITY REPORT 1'!G31) -> 0 | J30: 0 | K30: ='UTILITY REPORT 1'!C31 -> 0 | L30: =E30*F30+G30*H30+#REF!*#REF!+I30*J30 -> #DIV/0!
A31: Serengeti | B31: 30 | C31: 8 | D31: 2020 | E31: ='UTILITY REPORT 1'!F32 -> 0 | F31: =('UTILITY REPORT 1'!E32*'UTILITY REPORT 1'!D32)/'UTILITY REPORT 1'!F32 -> #DIV/0! | G31: =IF('Utility summery'!M35<0,"0",'Utility summery'!M35) -> 0 | H31: 0 | I31: =IF('UTILITY REPORT 1'!G32<0,"0",'UTILITY REPORT 1'!G32) -> 0 | J31: 0 | K31: ='UTILITY REPORT 1'!C32 -> 0 | L31: =E31*F31+G31*H31+#REF!*#REF!+I31*J31 -> #DIV/0!
A32: Serengeti | B32: =B31+1 -> 31 | C32: 8 | D32: 2020 | E32: ='UTILITY REPORT 1'!F33 -> 0 | F32: =('UTILITY REPORT 1'!E33*'UTILITY REPORT 1'!D33)/'UTILITY REPORT 1'!F33 -> #DIV/0! | G32: =IF('Utility summery'!M36<0,"0",'Utility summery'!M36) -> 0 | H32: 0 | I32: =IF('UTILITY REPORT 1'!G33<0,"0",'UTILITY REPORT 1'!G33) -> 0 | J32: 0 | K32: ='UTILITY REPORT 1'!C33 -> 0

Sheet Submetering
A1: Site Name | B1: Day | C1: Month | D1: Year | E1: Transport Consumption (LT) | F1: Generators Consumption (LT) | G1: Total Electricity Kwh | H1: Kitchen (KWh) | I1: Laundry (KWh) | J1: STP (M3) | K1: RO prodution (M3) | L1: Amani Restaurant (M3) | M1: Kitchen (M3) | N1: Laundry (M3) | O1: Laundry (M3) | P1: Total water Consumption (M3) | Q1: Borehole #1 (M3) | R1: Borehole #2 (M3) | S1: Borehole #3 (M3) | T1: Borehole #4 (M3) | U1: Borehole #5 (M3) | V1: Borehole #6 (M3) | W1: Total Bore holes production (M3) | X1: Room Nights
A2: Serengeti | B2: 1 | C2: 8 | D2: 2020 | E2: ='UTILITY REPORT 1'!I3 -> 16.85 | F2: ='UTILITY REPORT 1'!E3 -> 741.42 | G2: ='UTILITY REPORT 1'!F3 -> 1872 | H2: =IF('Kit report'!F4<0,"0",'Kit report'!F4) -> 144 | I2: =IF('Kit report'!X4<0,"0",'Kit report'!X4) -> 20 | J2: =IF('Utility summery'!H6<0,"0",'Utility summery'!H6) -> 48 | K2: =IF('UTILITY REPORT 1'!H3<0,"0",'UTILITY REPORT 1'!H3) -> 78 | L2: ='Water-Meter'!K6 -> 1 | M2: ='Water-Meter'!H6 -> 0 | N2: ='Water-Meter'!Q6 -> 1 | O2: =K2*E2+H2*I2+#REF!*#REF!+J2*L2 -> #REF! | P2: ='Water-Meter'!E6 -> 51 | Q2: =IF('Water-Meter'!U6<0,"0",'Water-Meter'!U6) -> 80 | R2: =IF('Water-Meter'!X6<0,"0",'Water-Meter'!X6) -> 0 | S2: =IF('Water-Meter'!AA6<0,"0",'Water-Meter'!AA6) -> 35 | T2: =IF('Water-Meter'!AD6<0,"0",'Water-Meter'!AD6) -> 12 | U2: =IF('Water-Meter'!AG6<0,"0",'Water-Meter'!AG6) -> 0 | V2: =IF('Water-Meter'!AJ6<0,"0",'Water-Meter'!AJ6) -> 43 | W2: ='Water-Meter'!AN6 -> 170 | X2: =Total!K2 -> 0
A3: Serengeti | B3: =B2+1 -> 2 | C3: 8 | D3: 2020 | E3: ='UTILITY REPORT 1'!I4 -> 0 | F3: ='UTILITY REPORT 1'!E4 -> 782.06 | G3: ='UTILITY REPORT 1'!F4 -> 2030 | H3: =IF('Kit report'!F5<0,"0",'Kit report'!F5) -> 168 | I3: =IF('Kit report'!X5<0,"0",'Kit report'!X5) -> 40 | J3: =IF('Utility summery'!H7<0,"0",'Utility summery'!H7) -> 31 | K3: =IF('UTILITY REPORT 1'!H4<0,"0",'UTILITY REPORT 1'!H4) -> 156 | L3: ='Water-Meter'!K7 -> 1 | M3: ='Water-Meter'!H7 -> 0 | N3: ='Water-Meter'!Q7 -> 1 | O3: =K3*E3+H3*I3+#REF!*#REF!+J3*L3 -> #REF! | P3: ='Water-Meter'!E7 -> 53 | Q3: =IF('Water-Meter'!U7<0,"0",'Water-Meter'!U7) -> 97 | R3: =IF('Water-Meter'!X7<0,"0",'Water-Meter'!X7) -> 0 | S3: =IF('Water-Meter'!AA7<0,"0",'Water-Meter'!AA7) -> 38 | T3: =IF('Water-Meter'!AD7<0,"0",'Water-Meter'!AD7) -> 17 | U3: =IF('Water-Meter'!AG7<0,"0",'Water-Meter'!AG7) -> 0 | V3: =IF('Water-Meter'!AJ7<0,"0",'Water-Meter'!AJ7) -> 33 | W3: ='Water-Meter'!AN7 -> 185 | X3: =Total!K3 -> 0
A4: Serengeti | B4: =B3+1 -> 3 | C4: 8 | D4: 2020 | E4: ='UTILITY REPORT 1'!I5 -> 25.31 | F4: ='UTILITY REPORT 1'!E5 -> 788.41 | G4: ='UTILITY REPORT 1'!F5 -> 1818 | H4: =IF('Kit report'!F6<0,"0",'Kit report'!F6) -> 132 | I4: =IF('Kit report'!X6<0,"0",'Kit report'!X6) -> 20 | J4: =IF('Utility summery'!H8<0,"0",'Utility summery'!H8) -> 70 | K4: =IF('UTILITY REPORT 1'!H5<0,"0",'UTILITY REPORT 1'!H5) -> 0 | L4: ='Water-Meter'!K8 -> 1 | M4: ='Water-Meter'!H8 -> 0 | N4: ='Water-Meter'!Q8 -> 1 | O4: =K4*E4+H4*I4+#REF!*#REF!+J4*L4 -> #REF! | P4: ='Water-Meter'!E8 -> 42 | Q4: =IF('Water-Meter'!U8<0,"0",'Water-Meter'!U8) -> 83 | R4: =IF('Water-Meter'!X8<0,"0",'Water-Meter'!X8) -> 0 | S4: =IF('Water-Meter'!AA8<0,"0",'Water-Meter'!AA8) -> 40 | T4: =IF('Water-Meter'!AD8<0,"0",'Water-Meter'!AD8) -> 20 | U4: =IF('Water-Meter'!AG8<0,"0",'Water-Meter'!AG8) -> 0 | V4: =IF('Water-Meter'!AJ8<0,"0",'Water-Meter'!AJ8) -> 12 | W4: ='Water-Meter'!AN8 -> 155 | X4: =Total!K4 -> 0
A5: Serengeti | B5: =B4+1 -> 4 | C5: 8 | D5: 2020 | E5: ='UTILITY REPORT 1'!I6 -> 149.86 | F5: ='UTILITY REPORT 1'!E6 -> 793.61 | G5: ='UTILITY REPORT 1'!F6 -> 1980 | H5: =IF('Kit report'!F7<0,"0",'Kit report'!F7) -> 180 | I5: =IF('Kit report'!X7<0,"0",'Kit report'!X7) -> 20 | J5: =IF('Utility summery'!H9<0,"0",'Utility summery'!H9) -> 36 | K5: =IF('UTILITY REPORT 1'!H6<0,"0",'UTILITY REPORT 1'!H6) -> 55 | L5: ='Water-Meter'!K9 -> 0 | M5: ='Water-Meter'!H9 -> 0 | N5: ='Water-Meter'!Q9 -> 1 | O5: =K5*E5+H5*I5+#REF!*#REF!+J5*L5 -> #REF! | P5: ='Water-Meter'!E9 -> 67 | Q5: =IF('Water-Meter'!U9<0,"0",'Water-Meter'!U9) -> 87 | R5: =IF('Water-Meter'!X9<0,"0",'Water-Meter'!X9) -> 0 | S5: =IF('Water-Meter'!AA9<0,"0",'Water-Meter'!AA9) -> 37 | T5: =IF('Water-Meter'!AD9<0,"0",'Water-Meter'!AD9) -> 16 | U5: =IF('Water-Meter'!AG9<0,"0",'Water-Meter'!AG9) -> 0 | V5: =IF('Water-Meter'!AJ9<0,"0",'Water-Meter'!AJ9) -> 2 | W5: ='Water-Meter'!AN9 -> 142 | X5: =Total!K5 -> 0
A6: Serengeti | B6: =B5+1 -> 5 | C6: 8 | D6: 2020 | E6: ='UTILITY REPORT 1'!I7 -> 87.31 | F6: ='UTILITY REPORT 1'!E7 -> 776.02 | G6: ='UTILITY REPORT 1'!F7 -> 1724 | H6: =IF('Kit report'!F8<0,"0",'Kit report'!F8) -> 168 | I6: =IF('Kit report'!X8<0,"0",'Kit report'!X8) -> 20 | J6: =IF('Utility summery'!H10<0,"0",'Utility summery'!H10) -> 21 | K6: =IF('UTILITY REPORT 1'!H7<0,"0",'UTILITY REPORT 1'!H7) -> 56 | L6: ='Water-Meter'!K10 -> 1 | M6: ='Water-Meter'!H10 -> 0 | N6: ='Water-Meter'!Q10 -> 1 | O6: =K6*E6+H6*I6+#REF!*#REF!+J6*L6 -> #REF! | P6: ='Water-Meter'!E10 -> 49 | Q6: =IF('Water-Meter'!U10<0,"0",'Water-Meter'!U10) -> 89 | R6: =IF('Water-Meter'!X10<0,"0",'Water-Meter'!X10) -> 0 | S6: =IF('Water-Meter'!AA10<0,"0",'Water-Meter'!AA10) -> 38 | T6: =IF('Water-Meter'!AD10<0,"0",'Water-Meter'!AD10) -> 16 | U6: =IF('Water-Meter'!AG10<0,"0",'Water-Meter'!AG10) -> 0 | V6: =IF('Water-Meter'!AJ10<0,"0",'Water-Meter'!AJ10) -> 0 | W6: ='Water-Meter'!AN10 -> 143 | X6: =Total!K6 -> 0
A7: Serengeti | B7: =B6+1 -> 6 | C7: 8 | D7: 2020 | E7: ='UTILITY REPORT 1'!I8 -> 52.6 | F7: ='UTILITY REPORT 1'!E8 -> 778.12 | G7: ='UTILITY REPORT 1'!F8 -> 1892 | H7: =IF('Kit report'!F9<0,"0",'Kit report'!F9) -> 156 | I7: =IF('Kit report'!X9<0,"0",'Kit report'!X9) -> 40 | J7: =IF('Utility summery'!H11<0,"0",'Utility summery'!H11) -> 40 | K7: =IF('UTILITY REPORT 1'!H8<0,"0",'UTILITY REPORT 1'!H8) -> 50 | L7: ='Water-Meter'!K11 -> 1 | M7: ='Water-Meter'!H11 -> 0 | N7: ='Water-Meter'!Q11 -> 3 | O7: =K7*E7+H7*I7+#REF!*#REF!+J7*L7 -> #REF! | P7: ='Water-Meter'!E11 -> 66 | Q7: =IF('Water-Meter'!U11<0,"0",'Water-Meter'!U11) -> 87 | R7: =IF('Water-Meter'!X11<0,"0",'Water-Meter'!X11) -> 0 | S7: =IF('Water-Meter'!AA11<0,"0",'Water-Meter'!AA11) -> 37 | T7: =IF('Water-Meter'!AD11<0,"0",'Water-Meter'!AD11) -> 16 | U7: =IF('Water-Meter'!AG11<0,"0",'Water-Meter'!AG11) -> 0 | V7: =IF('Water-Meter'!AJ11<0,"0",'Water-Meter'!AJ11) -> 5 | W7: ='Water-Meter'!AN11 -> 145 | X7: =Total!K7 -> 0
A8: Serengeti | B8: =B7+1 -> 7 | C8: 8 | D8: 2020 | E8: ='UTILITY REPORT 1'!I9 -> 0 | F8: ='UTILITY REPORT 1'!E9 -> 771.7 | G8: ='UTILITY REPORT 1'!F9 -> 1882 | H8: =IF('Kit report'!F10<0,"0",'Kit report'!F10) -> 156 | I8: =IF('Kit report'!X10<0,"0",'Kit report'!X10) -> 40 | J8: =IF('Utility summery'!H12<0,"0",'Utility summery'!H12) -> 38 | K8: =IF('UTILITY REPORT 1'!H9<0,"0",'UTILITY REPORT 1'!H9) -> 55 | L8: ='Water-Meter'!K12 -> 1 | M8: ='Water-Meter'!H12 -> 0 | N8: ='Water-Meter'!Q12 -> 1 | O8: =K8*E8+H8*I8+#REF!*#REF!+J8*L8 -> #REF! | P8: ='Water-Meter'!E12 -> 51 | Q8: =IF('Water-Meter'!U12<0,"0",'Water-Meter'!U12) -> 87 | R8: =IF('Water-Meter'!X12<0,"0",'Water-Meter'!X12) -> 0 | S8: =IF('Water-Meter'!AA12<0,"0",'Water-Meter'!AA12) -> 38 | T8: =IF('Water-Meter'!AD12<0,"0",'Water-Meter'!AD12) -> 15 | U8: =IF('Water-Meter'!AG12<0,"0",'Water-Meter'!AG12) -> 0 | V8: =IF('Water-Meter'!AJ12<0,"0",'Water-Meter'!AJ12) -> 0 | W8: ='Water-Meter'!AN12 -> 140 | X8: =Total!K8 -> 0
A9: Serengeti | B9: =B8+1 -> 8 | C9: 8 | D9: 2020 | E9: ='UTILITY REPORT 1'!I10 -> 0 | F9: ='UTILITY REPORT 1'!E10 -> 0 | G9: ='UTILITY REPORT 1'!F10 -> 0 | H9: =IF('Kit report'!F11<0,"0",'Kit report'!F11) -> 0 | I9: =IF('Kit report'!X11<0,"0",'Kit report'!X11) -> 0 | J9: =IF('Utility summery'!H13<0,"0",'Utility summery'!H13) -> 0 | K9: =IF('UTILITY REPORT 1'!H10<0,"0",'UTILITY REPORT 1'!H10) -> 0 | L9: ='Water-Meter'!K13 -> 0 | M9: ='Water-Meter'!H13 -> 0 | N9: ='Water-Meter'!Q13 -> 0 | O9: =K9*E9+H9*I9+#REF!*#REF!+J9*L9 -> #REF! | P9: ='Water-Meter'!E13 -> 0 | Q9: =IF('Water-Meter'!U13<0,"0",'Water-Meter'!U13) -> 0 | R9: =IF('Water-Meter'!X13<0,"0",'Water-Meter'!X13) -> 0 | S9: =IF('Water-Meter'!AA13<0,"0",'Water-Meter'!AA13) -> 0 | T9: =IF('Water-Meter'!AD13<0,"0",'Water-Meter'!AD13) -> 0 | U9: =IF('Water-Meter'!AG13<0,"0",'Water-Meter'!AG13) -> 0 | V9: =IF('Water-Meter'!AJ13<0,"0",'Water-Meter'!AJ13) -> 0 | W9: ='Water-Meter'!AN13 -> -14679 | X9: =Total!K9 -> 0
A10: Serengeti | B10: =B9+1 -> 9 | C10: 8 | D10: 2020 | E10: ='UTILITY REPORT 1'!I11 -> 0 | F10: ='UTILITY REPORT 1'!E11 -> 0 | G10: ='UTILITY REPORT 1'!F11 -> 0 | H10: =IF('Kit report'!F12<0,"0",'Kit report'!F12) -> 0 | I10: =IF('Kit report'!X12<0,"0",'Kit report'!X12) -> 0 | J10: =IF('Utility summery'!H14<0,"0",'Utility summery'!H14) -> 0 | K10: =IF('UTILITY REPORT 1'!H11<0,"0",'UTILITY REPORT 1'!H11) -> 0 | L10: ='Water-Meter'!K14 -> 0 | M10: ='Water-Meter'!H14 -> 0 | N10: ='Water-Meter'!Q14 -> 0 | O10: =K10*E10+H10*I10+#REF!*#REF!+J10*L10 -> #REF! | P10: ='Water-Meter'!E14 -> 0 | Q10: =IF('Water-Meter'!U14<0,"0",'Water-Meter'!U14) -> 0 | R10: =IF('Water-Meter'!X14<0,"0",'Water-Meter'!X14) -> 0 | S10: =IF('Water-Meter'!AA14<0,"0",'Water-Meter'!AA14) -> 0 | T10: =IF('Water-Meter'!AD14<0,"0",'Water-Meter'!AD14) -> 0 | U10: =IF('Water-Meter'!AG14<0,"0",'Water-Meter'!AG14) -> 0 | V10: =IF('Water-Meter'!AJ14<0,"0",'Water-Meter'!AJ14) -> 0 | W10: ='Water-Meter'!AN14 -> 0 | X10: =Total!K10 -> 0
A11: Serengeti | B11: =B10+1 -> 10 | C11: 8 | D11: 2020 | E11: ='UTILITY REPORT 1'!I12 -> 0 | F11: ='UTILITY REPORT 1'!E12 -> 0 | G11: ='UTILITY REPORT 1'!F12 -> 0 | H11: =IF('Kit report'!F13<0,"0",'Kit report'!F13) -> 0 | I11: =IF('Kit report'!X13<0,"0",'Kit report'!X13) -> 0 | J11: =IF('Utility summery'!H15<0,"0",'Utility summery'!H15) -> 0 | K11: =IF('UTILITY REPORT 1'!H12<0,"0",'UTILITY REPORT 1'!H12) -> 0 | L11: ='Water-Meter'!K15 -> 0 | M11: ='Water-Meter'!H15 -> 0 | N11: ='Water-Meter'!Q15 -> 0 | O11: =K11*E11+H11*I11+#REF!*#REF!+J11*L11 -> #REF! | P11: ='Water-Meter'!E15 -> 0 | Q11: =IF('Water-Meter'!U15<0,"0",'Water-Meter'!U15) -> 0 | R11: =IF('Water-Meter'!X15<0,"0",'Water-Meter'!X15) -> 0 | S11: =IF('Water-Meter'!AA15<0,"0",'Water-Meter'!AA15) -> 0 | T11: =IF('Water-Meter'!AD15<0,"0",'Water-Meter'!AD15) -> 0 | U11: =IF('Water-Meter'!AG15<0,"0",'Water-Meter'!AG15) -> 0 | V11: =IF('Water-Meter'!AJ15<0,"0",'Water-Meter'!AJ15) -> 0 | W11: ='Water-Meter'!AN15 -> 0 | X11: =Total!K11 -> 0
A12: Serengeti | B12: =B11+1 -> 11 | C12: 8 | D12: 2020 | E12: ='UTILITY REPORT 1'!I13 -> 0 | F12: ='UTILITY REPORT 1'!E13 -> 0 | G12: ='UTILITY REPORT 1'!F13 -> 0 | H12: =IF('Kit report'!F14<0,"0",'Kit report'!F14) -> 0 | I12: =IF('Kit report'!X14<0,"0",'Kit report'!X14) -> 0 | J12: =IF('Utility summery'!H16<0,"0",'Utility summery'!H16) -> 0 | K12: =IF('UTILITY REPORT 1'!H13<0,"0",'UTILITY REPORT 1'!H13) -> 0 | L12: ='Water-Meter'!K16 -> 0 | M12: ='Water-Meter'!H16 -> 0 | N12: ='Water-Meter'!Q16 -> 0 | O12: =K12*E12+H12*I12+#REF!*#REF!+J12*L12 -> #REF! | P12: ='Water-Meter'!E16 -> 0 | Q12: =IF('Water-Meter'!U16<0,"0",'Water-Meter'!U16) -> 0 | R12: =IF('Water-Meter'!X16<0,"0",'Water-Meter'!X16) -> 0 | S12: =IF('Water-Meter'!AA16<0,"0",'Water-Meter'!AA16) -> 0 | T12: =IF('Water-Meter'!AD16<0,"0",'Water-Meter'!AD16) -> 0 | U12: =IF('Water-Meter'!AG16<0,"0",'Water-Meter'!AG16) -> 0 | V12: =IF('Water-Meter'!AJ16<0,"0",'Water-Meter'!AJ16) -> 0 | W12: ='Water-Meter'!AN16 -> 0 | X12: =Total!K12 -> 0
A13: Serengeti | B13: =B12+1 -> 12 | C13: 8 | D13: 2020 | E13: ='UTILITY REPORT 1'!I14 -> 0 | F13: ='UTILITY REPORT 1'!E14 -> 0 | G13: ='UTILITY REPORT 1'!F14 -> 0 | H13: =IF('Kit report'!F15<0,"0",'Kit report'!F15) -> 0 | I13: =IF('Kit report'!X15<0,"0",'Kit report'!X15) -> 0 | J13: =IF('Utility summery'!H17<0,"0",'Utility summery'!H17) -> 0 | K13: =IF('UTILITY REPORT 1'!H14<0,"0",'UTILITY REPORT 1'!H14) -> 0 | L13: ='Water-Meter'!K17 -> 0 | M13: ='Water-Meter'!H17 -> 0 | N13: ='Water-Meter'!Q17 -> 0 | O13: =K13*E13+H13*I13+#REF!*#REF!+J13*L13 -> #REF! | P13: ='Water-Meter'!E17 -> 0 | Q13: =IF('Water-Meter'!U17<0,"0",'Water-Meter'!U17) -> 0 | R13: =IF('Water-Meter'!X17<0,"0",'Water-Meter'!X17) -> 0 | S13: =IF('Water-Meter'!AA17<0,"0",'Water-Meter'!AA17) -> 0 | T13: =IF('Water-Meter'!AD17<0,"0",'Water-Meter'!AD17) -> 0 | U13: =IF('Water-Meter'!AG17<0,"0",'Water-Meter'!AG17) -> 0 | V13: =IF('Water-Meter'!AJ17<0,"0",'Water-Meter'!AJ17) -> 0 | W13: ='Water-Meter'!AN17 -> 0 | X13: =Total!K13 -> 0
A14: Serengeti | B14: =B13+1 -> 13 | C14: 8 | D14: 2020 | E14: ='UTILITY REPORT 1'!I15 -> 0 | F14: ='UTILITY REPORT 1'!E15 -> 0 | G14: ='UTILITY REPORT 1'!F15 -> 0 | H14: =IF('Kit report'!F16<0,"0",'Kit report'!F16) -> 0 | I14: =IF('Kit report'!X16<0,"0",'Kit report'!X16) -> 0 | J14: =IF('Utility summery'!H18<0,"0",'Utility summery'!H18) -> 0 | K14: =IF('UTILITY REPORT 1'!H15<0,"0",'UTILITY REPORT 1'!H15) -> 0 | L14: ='Water-Meter'!K18 -> 0 | M14: ='Water-Meter'!H18 -> 0 | N14: ='Water-Meter'!Q18 -> 0 | O14: =K14*E14+H14*I14+#REF!*#REF!+J14*L14 -> #REF! | P14: ='Water-Meter'!E18 -> 0 | Q14: =IF('Water-Meter'!U18<0,"0",'Water-Meter'!U18) -> 0 | R14: =IF('Water-Meter'!X18<0,"0",'Water-Meter'!X18) -> 0 | S14: =IF('Water-Meter'!AA18<0,"0",'Water-Meter'!AA18) -> 0 | T14: =IF('Water-Meter'!AD18<0,"0",'Water-Meter'!AD18) -> 0 | U14: =IF('Water-Meter'!AG18<0,"0",'Water-Meter'!AG18) -> 0 | V14: =IF('Water-Meter'!AJ18<0,"0",'Water-Meter'!AJ18) -> 0 | W14: ='Water-Meter'!AN18 -> 0 | X14: =Total!K14 -> 0
... A30: Serengeti | B30: =B29+1 -> 29 | C30: 8 | D30: 2020 | E30: ='UTILITY REPORT 1'!I31 -> 0 | F30: ='UTILITY REPORT 1'!E31 -> 0 | G30: ='UTILITY REPORT 1'!F31 -> 0 | H30: =IF('Kit report'!F32<0,"0",'Kit report'!F32) -> 0 | I30: =IF('Kit report'!X32<0,"0",'Kit report'!X32) -> 0 | J30: =IF('Utility summery'!H34<0,"0",'Utility summery'!H34) -> 0 | K30: =IF('UTILITY REPORT 1'!H31<0,"0",'UTILITY REPORT 1'!H31) -> 0 | L30: ='Water-Meter'!K34 -> 0 | M30: ='Water-Meter'!H34 -> 0 | N30: ='Water-Meter'!Q34 -> 0 | O30: =K30*E30+H30*I30+#REF!*#REF!+J30*L30 -> #REF! | P30: ='Water-Meter'!E34 -> 0 | Q30: =IF('Water-Meter'!U34<0,"0",'Water-Meter'!U34) -> 0 | R30: =IF('Water-Meter'!X34<0,"0",'Water-Meter'!X34) -> 0 | S30: =IF('Water-Meter'!AA34<0,"0",'Water-Meter'!AA34) -> 0 | T30: =IF('Water-Meter'!AD34<0,"0",'Water-Meter'!AD34) -> 0 | U30: =IF('Water-Meter'!AG34<0,"0",'Water-Meter'!AG34) -> 0 | V30: =IF('Water-Meter'!AJ34<0,"0",'Water-Meter'!AJ34) -> 0 | W30: ='Water-Meter'!AN34 -> 0 | X30: =Total!K30 -> 0
A31: Serengeti | B31: 30 | C31: 8 | D31: 2020 | E31: ='UTILITY REPORT 1'!I32 -> 0 | F31: ='UTILITY REPORT 1'!E32 -> 0 | G31: ='UTILITY REPORT 1'!F32 -> 0 | H31: =IF('Kit report'!F33<0,"0",'Kit report'!F33) -> 0 | I31: =IF('Kit report'!X33<0,"0",'Kit report'!X33) -> 0 | J31: =IF('Utility summery'!H35<0,"0",'Utility summery'!H35) -> 0 | K31: =IF('UTILITY REPORT 1'!H32<0,"0",'UTILITY REPORT 1'!H32) -> 0 | L31: ='Water-Meter'!K35 -> 0 | M31: ='Water-Meter'!H35 -> 0 | N31: ='Water-Meter'!Q35 -> 0 | O31: =K31*E31+H31*I31+#REF!*#REF!+J31*L31 -> #REF! | P31: ='Water-Meter'!E35 -> 0 | Q31: =IF('Water-Meter'!U35<0,"0",'Water-Meter'!U35) -> 0 | R31: =IF('Water-Meter'!X35<0,"0",'Water-Meter'!X35) -> 0 | S31: =IF('Water-Meter'!AA35<0,"0",'Water-Meter'!AA35) -> 0 | T31: =IF('Water-Meter'!AD35<0,"0",'Water-Meter'!AD35) -> 0 | U31: =IF('Water-Meter'!AG35<0,"0",'Water-Meter'!AG35) -> 0 | V31: =IF('Water-Meter'!AJ35<0,"0",'Water-Meter'!AJ35) -> 0 | W31: ='Water-Meter'!AN35 -> 0 | X31: =Total!K31 -> 0
A32: Serengeti | B32: =B31+1 -> 31 | C32: 8 | E32: ='UTILITY REPORT 1'!I33 -> 0 | F32: ='UTILITY REPORT 1'!E33 -> 0 | G32: ='UTILITY REPORT 1'!F33 -> 0 | H32: =IF('Kit report'!F34<0,"0",'Kit report'!F34) -> 0 | I32: =IF('Kit report'!X34<0,"0",'Kit report'!X34) -> 0 | J32: =IF('Utility summery'!H36<0,"0",'Utility summery'!H36) -> 0 | K32: =IF('UTILITY REPORT 1'!H33<0,"0",'UTILITY REPORT 1'!H33) -> 0 | L32: ='Water-Meter'!K36 -> 0 | M32: ='Water-Meter'!H36 -> 0 | N32: ='Water-Meter'!Q36 -> 0 | P32: ='Water-Meter'!E36 -> 0 | Q32: =IF('Water-Meter'!U36<0,"0",'Water-Meter'!U36) -> 0 | R32: =IF('Water-Meter'!X36<0,"0",'Water-Meter'!X36) -> 0 | S32: =IF('Water-Meter'!AA36<0,"0",'Water-Meter'!AA36) -> 0 | T32: =IF('Water-Meter'!AD36<0,"0",'Water-Meter'!AD36) -> 0 | U32: =IF('Water-Meter'!AG36<0,"0",'Water-Meter'!AG36) -> 0 | V32: =IF('Water-Meter'!AJ36<0,"0",'Water-Meter'!AJ36) -> 0 | W32: ='Water-Meter'!AN36 -> 0 | X32: =Total!K32 -> 0

Sheet UTILITY REPORT 1
A1: UTILITY REPORT
A2: Date | B2: % | C2: Guest Rooms Occupied | D2: Diesel cost Per Liter ($) | E2: Diesel consumption (LT) | F2: Power production (KW) | G2: Water consumption (M3) | H2: RO prodution (M3) | I2: Transport Consupmtion (LT)
A3: =Gen!B11 -> 44044 | B3: =Gen!C11 -> 0 | C3: ='Summery Report'!E5 -> 0 | D3: 1 | E3: =Gen!T11 -> 741.42 | F3: =Gen!U11 -> 1872 | G3: ='Water-Meter'!E6 -> 51 | H3: ='Utility report '!AC6 -> 78 | I3: =Gen!AK11 -> 16.85
A4: =Gen!B12 -> 44045 | B4: =Gen!C12 -> 0 | C4: ='Summery Report'!E6 -> 0 | D4: 1 | E4: =Gen!T12 -> 782.06 | F4: =Gen!U12 -> 2030 | G4: ='Water-Meter'!E7 -> 53 | H4: ='Utility report '!AC7 -> 156 | I4: =Gen!AK12 -> 0
A5: =Gen!B13 -> 44046 | B5: =Gen!C13 -> 0 | C5: ='Summery Report'!E7 -> 0 | D5: 1 | E5: =Gen!T13 -> 788.41 | F5: =Gen!U13 -> 1818 | G5: ='Water-Meter'!E8 -> 42 | H5: ='Utility report '!AC8 -> 0 | I5: =Gen!AK13 -> 25.31
A6: =Gen!B14 -> 44047 | B6: =Gen!C14 -> 0 | C6: ='Summery Report'!E8 -> 0 | D6: 1 | E6: =Gen!T14 -> 793.61 | F6: =Gen!U14 -> 1980 | G6: ='Water-Meter'!E9 -> 67 | H6: ='Utility report '!AC9 -> 55 | I6: =Gen!AK14 -> 149.86
A7: =Gen!B15 -> 44048 | B7: =Gen!C15 -> 0 | C7: ='Summery Report'!E9 -> 0 | D7: 1 | E7: =Gen!T15 -> 776.02 | F7: =Gen!U15 -> 1724 | G7: ='Water-Meter'!E10 -> 49 | H7: ='Utility report '!AC10 -> 56 | I7: =Gen!AK15 -> 87.31
A8: =Gen!B16 -> 44049 | B8: =Gen!C16 -> 0 | C8: ='Summery Report'!E10 -> 0 | D8: 1 | E8: =Gen!T16 -> 778.12 | F8: =Gen!U16 -> 1892 | G8: ='Water-Meter'!E11 -> 66 | H8: ='Utility report '!AC11 -> 50 | I8: =Gen!AK16 -> 52.6
A9: =Gen!B17 -> 44050 | B9: =Gen!C17 -> 0 | C9: ='Summery Report'!E11 -> 0 | D9: 1 | E9: =Gen!T17 -> 771.7 | F9: =Gen!U17 -> 1882 | G9: ='Water-Meter'!E12 -> 51 | H9: ='Utility report '!AC12 -> 55 | I9: =Gen!AK17 -> 0
A10: =Gen!B18 -> 44051 | B10: =Gen!C18 -> 0 | C10: ='Summery Report'!E12 -> 0 | D10: 1 | E10: =Gen!T18 -> 0 | F10: =Gen!U18 -> 0 | G10: ='Water-Meter'!E13 -> 0 | H10: ='Utility report '!AC13 -> -36392 | I10: =Gen!AK18 -> 0
A11: =Gen!B19 -> 44052 | B11: =Gen!C19 -> 0 | C11: ='Summery Report'!E13 -> 0 | D11: 1 | E11: =Gen!T19 -> 0 | F11: =Gen!U19 -> 0 | G11: ='Water-Meter'!E14 -> 0 | H11: ='Utility report '!AC14 -> 0 | I11: =Gen!AK19 -> 0
A12: =Gen!B20 -> 44053 | B12: =Gen!C20 -> 0 | C12: ='Summery Report'!E14 -> 0 | D12: 1 | E12: =Gen!T20 -> 0 | F12: =Gen!U20 -> 0 | G12: ='Water-Meter'!E15 -> 0 | H12: ='Utility report '!AC15 -> 0 | I12: =Gen!AK20 -> 0
A13: =Gen!B21 -> 44054 | B13: =Gen!C21 -> 0 | C13: ='Summery Report'!E15 -> 0 | D13: 1 | E13: =Gen!T21 -> 0 | F13: =Gen!U21 -> 0 | G13: ='Water-Meter'!E16 -> 0 | H13: ='Utility report '!AC16 -> 0 | I13: =Gen!AK21 -> 0
A14: =Gen!B22 -> 44055 | B14: =Gen!C22 -> 0 | C14: ='Summery Report'!E16 -> 0 | D14: 1 | E14: =Gen!T22 -> 0 | F14: =Gen!U22 -> 0 | G14: ='Water-Meter'!E17 -> 0 | H14: ='Utility report '!AC17 -> 0 | I14: =Gen!AK22 -> 0
... A33: =Gen!B41 -> 44074 | B33: =Gen!C41 -> 0 | C33: ='Summery Report'!E35 -> 0 | D33: 1 | E33: =Gen!T41 -> 0 | F33: =Gen!U41 -> 0 | G33: ='Water-Meter'!E36 -> 0 | H33: ='Utility report '!AC36 -> 0 | I33: =Gen!AK41 -> 0
B34: =Gen!C42 -> 0 | C34: ='Summery Report'!E36 -> 0 | D34: 2 | E34: =Gen!T42 -> 0 | F34: =Gen!U42 -> 0 | G34: ='Water-Meter'!E37 -> 0 | H34: ='Utility report '!AC37 -> 0 | I34: =Gen!AK42 -> 0

Sheet Utility summery
A4: Date | B4: Room Occupied | C4: Electricity Units Generated KW | D4: Diseal | G4: Water | J4: Gas | N4: Cost of utilites
D5: Generator | E5: Transport | F5: Total | G5: RO | H5: STP | I5: Total Consumption | J5: 2 ton | K5: 1 Ton | L5: 1 Ton | M5: Total consumption | N5: Electricity /1.4$/liter | O5: Diseal for Transport | P5: Gas /2.38$/Kg | Q5: Total HLP Cost | R5: Electricity Cost/Room $ | S5: cost/Room $
A6: =Gen!B11 -> 44044 | B6: ='Summery Report'!E5 -> 0 | C6: =Gen!U11 -> 1872 | D6: =Gen!T11 -> 741.42 | E6: =Gen!AK11 -> 16.85 | F6: =Gen!AS11 -> 758.27 | G6: ='Utility report '!AC6 -> 78 | H6: ='Utility report '!AE6 -> 48 | I6: ='Water-Meter'!E6 -> 51 | J6: ='Lpg (2)'!B10 -> 85 | K6: ='Lpg (2)'!C10 -> 85 | L6: ='Lpg (2)'!D10 -> 85 | M6: ='Lpg (2)'!G10 -> 315873.14 | O6: =E6 -> 16.85 | P6: ='[1]Lpg (2)'!#REF! -> #REF! | Q6: ='[1]Summery Report'!#REF! -> #REF! | R6: =N6/B6 -> #DIV/0! | S6: =Q6/B6 -> #REF!
A7: =Gen!B12 -> 44045 | B7: ='Summery Report'!E6 -> 0 | C7: =Gen!U12 -> 2030 | D7: =Gen!T12 -> 782.06 | E7: =Gen!AK12 -> 0 | F7: =Gen!AS12 -> 782.06 | G7: ='Utility report '!AC7 -> 156 | H7: ='Utility report '!AE7 -> 31 | I7: ='Water-Meter'!E7 -> 53 | J7: ='Lpg (2)'!B11 -> 85 | K7: ='Lpg (2)'!C11 -> 85 | L7: ='Lpg (2)'!D11 -> 85 | M7: ='Lpg (2)'!G11 -> 25.784 | N7: =D7*1.4 -> 1094.884 | O7: =E7*1.4 -> 0 | P7: ='[1]Lpg (2)'!#REF! -> #REF! | Q7: ='[1]Summery Report'!#REF! -> #REF! | R7: =N7/B7 -> #DIV/0! | S7: =Q7/B7 -> #REF!
A8: =Gen!B13 -> 44046 | B8: ='Summery Report'!E7 -> 0 | C8: =Gen!U13 -> 1818 | D8: =Gen!T13 -> 788.41 | E8: =Gen!AK13 -> 25.31 | F8: =Gen!AS13 -> 813.72 | G8: ='Utility report '!AC8 -> 0 | H8: ='Utility report '!AE8 -> 70 | I8: ='Water-Meter'!E8 -> 42 | J8: ='Lpg (2)'!B12 -> 85 | K8: ='Lpg (2)'!C12 -> 85 | L8: ='Lpg (2)'!D12 -> 84 | M8: ='Lpg (2)'!G12 -> 65.648 | N8: =D8*1.4 -> 1103.774 | O8: =E8*1.4 -> 35.434 | P8: ='[1]Lpg (2)'!#REF! -> #REF! | Q8: ='[1]Summery Report'!#REF! -> #REF! | R8: =N8/B8 -> #DIV/0! | S8: =Q8/B8 -> #REF!
A9: =Gen!B14 -> 44047 | B9: ='Summery Report'!E8 -> 0 | C9: =Gen!U14 -> 1980 | D9: =Gen!T14 -> 793.61 | E9: =Gen!AK14 -> 149.86 | F9: =Gen!AS14 -> 943.47 | G9: ='Utility report '!AC9 -> 55 | H9: ='Utility report '!AE9 -> 36 | I9: ='Water-Meter'!E9 -> 67 | J9: ='Lpg (2)'!B13 -> 85 | K9: ='Lpg (2)'!C13 -> 85 | L9: ='Lpg (2)'!D13 -> 84 | M9: ='Lpg (2)'!G13 -> 22.704 | N9: =D9*1.4 -> 1111.054 | O9: =E9*1.4 -> 209.804 | P9: ='[1]Lpg (2)'!#REF! -> #REF! | Q9: ='[1]Summery Report'!#REF! -> #REF! | R9: =N9/B9 -> #DIV/0! | S9: =Q9/B9 -> #REF!
A10: =Gen!B15 -> 44048 | B10: ='Summery Report'!E9 -> 0 | C10: =Gen!U15 -> 1724 | D10: =Gen!T15 -> 776.02 | E10: =Gen!AK15 -> 87.31 | F10: =Gen!AS15 -> 863.33 | G10: ='Utility report '!AC10 -> 56 | H10: ='Utility report '!AE10 -> 21 | I10: ='Water-Meter'!E10 -> 49 | J10: ='Lpg (2)'!B14 -> 85 | K10: ='Lpg (2)'!C14 -> 85 | L10: ='Lpg (2)'!D14 -> 84 | M10: ='Lpg (2)'!G14 -> 31.24 | N10: =D10*1.4 -> 1086.428 | O10: =E10*1.4 -> 122.234 | P10: ='[1]Lpg (2)'!#REF! -> #REF! | Q10: ='[1]Summery Report'!#REF! -> #REF! | R10: =N10/B10 -> #DIV/0! | S10: =Q10/B10 -> #REF!
A11: =Gen!B16 -> 44049 | B11: ='Summery Report'!E10 -> 0 | C11: =Gen!U16 -> 1892 | D11: =Gen!T16 -> 778.12 | E11: =Gen!AK16 -> 52.6 | F11: =Gen!AS16 -> 830.72 | G11: ='Utility report '!AC11 -> 50 | H11: ='Utility report '!AE11 -> 40 | I11: ='Water-Meter'!E11 -> 66 | J11: ='Lpg (2)'!B15 -> 85 | K11: ='Lpg (2)'!C15 -> 85 | L11: ='Lpg (2)'!D15 -> 83 | M11: ='Lpg (2)'!G15 -> 8.448 | N11: =D11*1.4 -> 1089.368 | O11: =E11*1.4 -> 73.64 | P11: ='[1]Lpg (2)'!#REF! -> #REF! | Q11: ='[1]Summery Report'!#REF! -> #REF! | R11: =N11/B11 -> #DIV/0! | S11: =Q11/B11 -> #REF!
A12: =Gen!B17 -> 44050 | B12: ='Summery Report'!E11 -> 0 | C12: =Gen!U17 -> 1882 | D12: =Gen!T17 -> 771.7 | E12: =Gen!AK17 -> 0 | F12: =Gen!AS17 -> 771.7 | G12: ='Utility report '!AC12 -> 55 | H12: ='Utility report '!AE12 -> 38 | I12: ='Water-Meter'!E12 -> 51 | J12: ='Lpg (2)'!B16 -> 85 | K12: ='Lpg (2)'!C16 -> 85 | L12: ='Lpg (2)'!D16 -> 0 | M12: ='Lpg (2)'!G16 -> -316026.96 | N12: =D12*1.4 -> 1080.38 | O12: =E12*1.4 -> 0 | P12: ='[1]Lpg (2)'!#REF! -> #REF! | Q12: ='[1]Summery Report'!#REF! -> #REF! | R12: =N12/B12 -> #DIV/0! | S12: =Q12/B12 -> #REF!
A13: =Gen!B18 -> 44051 | B13: ='Summery Report'!E12 -> 0 | C13: =Gen!U18 -> 0 | D13: =Gen!T18 -> 0 | E13: =Gen!AK18 -> 0 | F13: =Gen!AS18 -> 0 | G13: ='Utility report '!AC13 -> -36392 | H13: ='Utility report '!AE13 -> -203604 | I13: ='Water-Meter'!E13 -> 0 | J13: ='Lpg (2)'!B17 -> 0 | K13: ='Lpg (2)'!C17 -> 0 | L13: ='Lpg (2)'!D17 -> 0 | M13: ='Lpg (2)'!G17 -> 0 | N13: =D13*1.4 -> 0 | O13: =E13*1.4 -> 0 | P13: ='[1]Lpg (2)'!#REF! -> #REF! | Q13: ='[1]Summery Report'!#REF! -> #REF! | R13: =N13/B13 -> #DIV/0! | S13: =Q13/B13 -> #REF!
A14: =Gen!B19 -> 44052 | B14: ='Summery Report'!E13 -> 0 | C14: =Gen!U19 -> 0 | D14: =Gen!T19 -> 0 | E14: =Gen!AK19 -> 0 | F14: =Gen!AS19 -> 0 | G14: ='Utility report '!AC14 -> 0 | H14: ='Utility report '!AE14 -> 0 | I14: ='Water-Meter'!E14 -> 0 | J14: ='Lpg (2)'!B18 -> 0 | K14: ='Lpg (2)'!C18 -> 0 | L14: ='Lpg (2)'!D18 -> 0 | M14: ='Lpg (2)'!G18 -> 0 | N14: =D14*1.4 -> 0 | O14: =E14*1.4 -> 0 | P14: ='[1]Lpg (2)'!#REF! -> #REF! | Q14: ='[1]Summery Report'!#REF! -> #REF! | R14: =N14/B14 -> #DIV/0! | S14: =Q14/B14 -> #REF!
A15: =Gen!B20 -> 44053 | B15: ='Summery Report'!E14 -> 0 | C15: =Gen!U20 -> 0 | D15: =Gen!T20 -> 0 | E15: =Gen!AK20 -> 0 | F15: =Gen!AS20 -> 0 | G15: ='Utility report '!AC15 -> 0 | H15: ='Utility report '!AE15 -> 0 | I15: ='Water-Meter'!E15 -> 0 | J15: ='Lpg (2)'!B19 -> 0 | K15: ='Lpg (2)'!C19 -> 0 | L15: ='Lpg (2)'!D19 -> 0 | M15: ='Lpg (2)'!G19 -> 0 | N15: =D15*1.4 -> 0 | O15: =E15*1.4 -> 0 | P15: ='[1]Lpg (2)'!#REF! -> #REF! | Q15: ='[1]Summery Report'!#REF! -> #REF! | R15: =N15/B15 -> #DIV/0! | S15: =Q15/B15 -> #REF!
A16: =Gen!B21 -> 44054 | B16: ='Summery Report'!E15 -> 0 | C16: =Gen!U21 -> 0 | D16: =Gen!T21 -> 0 | E16: =Gen!AK21 -> 0 | F16: =Gen!AS21 -> 0 | G16: ='Utility report '!AC16 -> 0 | H16: ='Utility report '!AE16 -> 0 | I16: ='Water-Meter'!E16 -> 0 | J16: ='Lpg (2)'!B20 -> 0 | K16: ='Lpg (2)'!C20 -> 0 | L16: ='Lpg (2)'!D20 -> 0 | M16: ='Lpg (2)'!G20 -> 0 | N16: =D16*1.4 -> 0 | O16: =E16*1.4 -> 0 | P16: ='[1]Lpg (2)'!#REF! -> #REF! | Q16: ='[1]Summery Report'!#REF! -> #REF! | R16: =N16/B16 -> #DIV/0! | S16: =Q16/B16 -> #REF!
A17: =Gen!B22 -> 44055 | B17: ='Summery Report'!E16 -> 0 | C17: =Gen!U22 -> 0 | D17: =Gen!T22 -> 0 | E17: =Gen!AK22 -> 0 | F17: =Gen!AS22 -> 0 | G17: ='Utility report '!AC17 -> 0 | H17: ='Utility report '!AE17 -> 0 | I17: ='Water-Meter'!E17 -> 0 | J17: ='Lpg (2)'!B21 -> 0 | K17: ='Lpg (2)'!C22 -> 0 | L17: ='Lpg (2)'!D21 -> 0 | M17: ='Lpg (2)'!G21 -> 0 | N17: =D17*1.4 -> 0 | O17: =E17*1.4 -> 0 | P17: ='[1]Lpg (2)'!#REF! -> #REF! | Q17: ='[1]Summery Report'!#REF! -> #REF! | R17: =N17/B17 -> #DIV/0! | S17: =Q17/B17 -> #REF!
A18: =Gen!B23 -> 44056 | B18: ='Summery Report'!E17 -> 0 | C18: =Gen!U23 -> 0 | D18: =Gen!T23 -> 0 | E18: =Gen!AK23 -> 0 | F18: =Gen!AS23 -> 0 | G18: ='Utility report '!AC18 -> 0 | H18: ='Utility report '!AE18 -> 0 | I18: ='Water-Meter'!E18 -> 0 | J18: ='Lpg (2)'!B22 -> 0 | K18: ='Lpg (2)'!C23 -> 0 | L18: ='Lpg (2)'!D22 -> 0 | M18: ='Lpg (2)'!G22 -> 0 | N18: =D18*1.4 -> 0 | O18: =E18*1.4 -> 0 | P18: ='[1]Lpg (2)'!#REF! -> #REF! | Q18: ='[1]Summery Report'!#REF! -> #REF! | R18: =N18/B18 -> #DIV/0! | S18: =Q18/B18 -> #REF!
A19: =Gen!B24 -> 44057 | B19: ='Summery Report'!E18 -> 0 | C19: =Gen!U24 -> 0 | D19: =Gen!T24 -> 0 | E19: =Gen!AK24 -> 0 | F19: =Gen!AS24 -> 0 | G19: ='Utility report '!AC19 -> 0 | H19: ='Utility report '!AE19 -> 0 | I19: ='Water-Meter'!E19 -> 0 | J19: ='Lpg (2)'!B23 -> 0 | K19: ='Lpg (2)'!C24 -> 0 | L19: ='Lpg (2)'!D23 -> 0 | M19: ='Lpg (2)'!G23 -> 0 | N19: =D19*1.4 -> 0 | O19: =E19*1.4 -> 0 | P19: ='[1]Lpg (2)'!#REF! -> #REF! | Q19: ='[1]Summery Report'!#REF! -> #REF! | R19: =N19/B19 -> #DIV/0! | S19: =Q19/B19 -> #REF!
A20: =Gen!B25 -> 44058 | B20: ='Summery Report'!E19 -> 0 | C20: =Gen!U25 -> 0 | D20: =Gen!T25 -> 0 | E20: =Gen!AK25 -> 0 | F20: =Gen!AS25 -> 0 | G20: ='Utility report '!AC20 -> 0 | H20: ='Utility report '!AE20 -> 0 | I20: ='Water-Meter'!E20 -> 0 | J20: ='Lpg (2)'!B24 -> 0 | K20: ='Lpg (2)'!C25 -> 0 | L20: ='Lpg (2)'!D24 -> 0 | M20: ='Lpg (2)'!G24 -> 0 | N20: =D20*1.4 -> 0 | O20: =E20*1.4 -> 0 | P20: ='[1]Lpg (2)'!#REF! -> #REF! | Q20: ='[1]Summery Report'!#REF! -> #REF! | R20: =N20/B20 -> #DIV/0! | S20: =Q20/B20 -> #REF!
A21: =Gen!B26 -> 44059 | B21: ='Summery Report'!E20 -> 0 | C21: =Gen!U26 -> 0 | D21: =Gen!T26 -> 0 | E21: =Gen!AK26 -> 0 | F21: =Gen!AS26 -> 0 | G21: ='Utility report '!AC21 -> 0 | H21: ='Utility report '!AE21 -> 0 | I21: ='Water-Meter'!E21 -> 0 | J21: ='Lpg (2)'!B25 -> 0 | K21: ='Lpg (2)'!C25 -> 0 | L21: ='Lpg (2)'!D25 -> 0 | M21: ='Lpg (2)'!G25 -> 0 | N21: =D21*1.4 -> 0 | O21: =E21*1.4 -> 0 | P21: ='[1]Lpg (2)'!#REF! -> #REF! | Q21: ='[1]Summery Report'!#REF! -> #REF! | R21: =N21/B21 -> #DIV/0! | S21: =Q21/B21 -> #REF!
A22: =Gen!B27 -> 44060 | B22: ='Summery Report'!E21 -> 0 | C22: =Gen!U27 -> 0 | D22: =Gen!T27 -> 0 | E22: =Gen!AK27 -> 0 | F22: =Gen!AS27 -> 0 | G22: ='Utility report '!AC22 -> 0 | H22: ='Utility report '!AE22 -> 0 | I22: ='Water-Meter'!E22 -> 0 | J22: ='Lpg (2)'!B26 -> 0 | K22: ='Lpg (2)'!C26 -> 0 | L22: ='Lpg (2)'!D26 -> 0 | M22: ='Lpg (2)'!G26 -> 0 | N22: =D22*1.4 -> 0 | O22: =E22*1.4 -> 0 | P22: ='[1]Lpg (2)'!#REF! -> #REF! | Q22: ='[1]Summery Report'!#REF! -> #REF! | R22: =N22/B22 -> #DIV/0! | S22: =Q22/B22 -> #REF!
A23: =Gen!B28 -> 44061 | B23: ='Summery Report'!E22 -> 0 | C23: =Gen!U28 -> 0 | D23: =Gen!T28 -> 0 | E23: =Gen!AK28 -> 0 | F23: =Gen!AS28 -> 0 | G23: ='Utility report '!AC23 -> 0 | H23: ='Utility report '!AE23 -> 0 | I23: ='Water-Meter'!E23 -> 0 | J23: ='Lpg (2)'!B27 -> 0 | K23: ='Lpg (2)'!C27 -> 0 | L23: ='Lpg (2)'!D27 -> 0 | M23: ='Lpg (2)'!G27 -> 0 | N23: =D23*1.4 -> 0 | O23: =E23*1.4 -> 0 | P23: ='[1]Lpg (2)'!#REF! -> #REF! | Q23: ='[1]Summery Report'!#REF! -> #REF! | R23: =N23/B23 -> #DIV/0! | S23: =Q23/B23 -> #REF!
A24: =Gen!B29 -> 44062 | B24: ='Summery Report'!E23 -> 0 | C24: =Gen!U29 -> 0 | D24: =Gen!T29 -> 0 | E24: =Gen!AK29 -> 0 | F24: =Gen!AS29 -> 0 | G24: ='Utility report '!AC24 -> 0 | H24: ='Utility report '!AE24 -> 0 | I24: ='Water-Meter'!E24 -> 0 | J24: ='Lpg (2)'!B28 -> 0 | K24: ='Lpg (2)'!C28 -> 0 | L24: ='Lpg (2)'!D28 -> 0 | M24: ='Lpg (2)'!G28 -> 0 | N24: =D24*1.4 -> 0 | O24: =E24*1.4 -> 0 | P24: ='[1]Lpg (2)'!#REF! -> #REF! | Q24: ='[1]Summery Report'!#REF! -> #REF! | R24: =N24/B24 -> #DIV/0! | S24: =Q24/B24 -> #REF!
A25: =Gen!B30 -> 44063 | B25: ='Summery Report'!E24 -> 0 | C25: =Gen!U30 -> 0 | D25: =Gen!T30 -> 0 | E25: =Gen!AK30 -> 0 | F25: =Gen!AS30 -> 0 | G25: ='Utility report '!AC25 -> 0 | H25: ='Utility report '!AE25 -> 0 | I25: ='Water-Meter'!E25 -> 0 | J25: ='Lpg (2)'!B29 -> 0 | K25: ='Lpg (2)'!C29 -> 0 | L25: ='Lpg (2)'!D29 -> 0 | M25: ='Lpg (2)'!G29 -> 0 | N25: =D25*1.4 -> 0 | O25: =E25*1.4 -> 0 | P25: ='[1]Lpg (2)'!#REF! -> #REF! | Q25: ='[1]Summery Report'!#REF! -> #REF! | R25: =N25/B25 -> #DIV/0! | S25: =Q25/B25 -> #REF!
A26: =Gen!B31 -> 44064 | B26: ='Summery Report'!E25 -> 0 | C26: =Gen!U31 -> 0 | D26: =Gen!T31 -> 0 | E26: =Gen!AK31 -> 0 | F26: =Gen!AS31 -> 0 | G26: ='Utility report '!AC26 -> 0 | H26: ='Utility report '!AE26 -> 0 | I26: ='Water-Meter'!E26 -> 0 | J26: ='Lpg (2)'!B30 -> 0 | K26: ='Lpg (2)'!C30 -> 0 | L26: ='Lpg (2)'!D30 -> 0 | M26: ='Lpg (2)'!G30 -> 0 | N26: =D26*1.4 -> 0 | O26: =E26*1.4 -> 0 | P26: ='[1]Lpg (2)'!#REF! -> #REF! | Q26: ='[1]Summery Report'!#REF! -> #REF! | R26: =N26/B26 -> #DIV/0! | S26: =Q26/B26 -> #REF!
A27: =Gen!B32 -> 44065 | B27: ='Summery Report'!E26 -> 0 | C27: =Gen!U32 -> 0 | D27: =Gen!T32 -> 0 | E27: =Gen!AK32 -> 0 | F27: =Gen!AS32 -> 0 | G27: ='Utility report '!AC27 -> 0 | H27: ='Utility report '!AE27 -> 0 | I27: ='Water-Meter'!E27 -> 0 | J27: ='Lpg (2)'!B31 -> 0 | K27: ='Lpg (2)'!C31 -> 0 | L27: ='Lpg (2)'!D31 -> 0 | M27: ='Lpg (2)'!G31 -> 0 | N27: =D27*1.4 -> 0 | O27: =E27*1.4 -> 0 | P27: ='[1]Lpg (2)'!#REF! -> #REF! | Q27: ='[1]Summery Report'!#REF! -> #REF! | R27: =N27/B27 -> #DIV/0! | S27: =Q27/B27 -> #REF!
A28: =Gen!B33 -> 44066 | B28: ='Summery Report'!E27 -> 0 | C28: =Gen!U33 -> 0 | D28: =Gen!T33 -> 0 | E28: =Gen!AK33 -> 0 | F28: =Gen!AS33 -> 0 | G28: ='Utility report '!AC28 -> 0 | H28: ='Utility report '!AE28 -> 0 | I28: ='Water-Meter'!E28 -> 0 | J28: ='Lpg (2)'!B32 -> 0 | K28: ='Lpg (2)'!C32 -> 0 | L28: ='Lpg (2)'!D32 -> 0 | M28: ='Lpg (2)'!G32 -> 0 | N28: =D28*1.4 -> 0 | O28: =E28*1.4 -> 0 | P28: ='[1]Lpg (2)'!#REF! -> #REF! | Q28: ='[1]Summery Report'!#REF! -> #REF! | R28: =N28/B28 -> #DIV/0! | S28: =Q28/B28 -> #REF!
A29: =Gen!B34 -> 44067 | B29: ='Summery Report'!E28 -> 0 | C29: =Gen!U34 -> 0 | D29: =Gen!T34 -> 0 | E29: =Gen!AK34 -> 0 | F29: =Gen!AS34 -> 0 | G29: ='Utility report '!AC29 -> 0 | H29: ='Utility report '!AE29 -> 0 | I29: ='Water-Meter'!E29 -> 0 | J29: ='Lpg (2)'!B33 -> 0 | K29: ='Lpg (2)'!C33 -> 0 | L29: ='Lpg (2)'!D33 -> 0 | M29: ='Lpg (2)'!G33 -> 0 | N29: =D29*1.4 -> 0 | O29: =E29*1.4 -> 0 | P29: ='[1]Lpg (2)'!#REF! -> #REF! | Q29: ='[1]Summery Report'!#REF! -> #REF! | R29: =N29/B29 -> #DIV/0! | S29: =Q29/B29 -> #REF!
A30: =Gen!B35 -> 44068 | B30: ='Summery Report'!E29 -> 0 | C30: =Gen!U35 -> 0 | D30: =Gen!T35 -> 0 | E30: =Gen!AK35 -> 0 | F30: =Gen!AS35 -> 0 | G30: ='Utility report '!AC30 -> 0 | H30: ='Utility report '!AE30 -> 0 | I30: ='Water-Meter'!E30 -> 0 | J30: ='Lpg (2)'!B34 -> 0 | K30: ='Lpg (2)'!C34 -> 0 | L30: ='Lpg (2)'!D34 -> 0 | M30: ='Lpg (2)'!G34 -> 0 | N30: =D30*1.4 -> 0 | O30: =E30*1.4 -> 0 | P30: ='[1]Lpg (2)'!#REF! -> #REF! | Q30: ='[1]Summery Report'!#REF! -> #REF! | R30: =N30/B30 -> #DIV/0! | S30: =Q30/B30 -> #REF!
A31: =Gen!B36 -> 44069 | B31: ='Summery Report'!E30 -> 0 | C31: =Gen!U36 -> 0 | D31: =Gen!T36 -> 0 | E31: =Gen!AK36 -> 0 | F31: =Gen!AS36 -> 0 | G31: ='Utility report '!AC31 -> 0 | H31: ='Utility report '!AE31 -> 0 | I31: ='Water-Meter'!E31 -> 0 | J31: ='Lpg (2)'!B35 -> 0 | K31: ='Lpg (2)'!C35 -> 0 | L31: ='Lpg (2)'!D35 -> 0 | M31: ='Lpg (2)'!G35 -> 0 | N31: =D31*1.4 -> 0 | O31: =E31*1.4 -> 0 | P31: ='[1]Lpg (2)'!#REF! -> #REF! | Q31: ='[1]Summery Report'!#REF! -> #REF! | R31: =N31/B31 -> #DIV/0! | S31: =Q31/B31 -> #REF!
A32: =Gen!B37 -> 44070 | B32: ='Summery Report'!E31 -> 0 | C32: =Gen!U37 -> 0 | D32: =Gen!T37 -> 0 | E32: =Gen!AK37 -> 0 | F32: =Gen!AS37 -> 0 | G32: ='Utility report '!AC32 -> 0 | H32: ='Utility report '!AE32 -> 0 | I32: ='Water-Meter'!E32 -> 0 | J32: ='Lpg (2)'!B36 -> 0 | K32: ='Lpg (2)'!C36 -> 0 | L32: ='Lpg (2)'!D36 -> 0 | M32: ='Lpg (2)'!G36 -> 0 | N32: =D32*1.4 -> 0 | O32: =E32*1.4 -> 0 | P32: ='[1]Lpg (2)'!#REF! -> #REF! | Q32: ='[1]Summery Report'!#REF! -> #REF! | R32: =N32/B32 -> #DIV/0! | S32: =Q32/B32 -> #REF!
A33: =Gen!B38 -> 44071 | B33: ='Summery Report'!E32 -> 0 | C33: =Gen!U38 -> 0 | D33: =Gen!T38 -> 0 | E33: =Gen!AK38 -> 0 | F33: =Gen!AS38 -> 0 | G33: ='Utility report '!AC33 -> 0 | H33: ='Utility report '!AE33 -> 0 | I33: ='Water-Meter'!E33 -> 0 | J33: ='Lpg (2)'!B37 -> 0 | K33: ='Lpg (2)'!C37 -> 0 | L33: ='Lpg (2)'!D37 -> 0 | M33: ='Lpg (2)'!G37 -> 0 | N33: =D33*1.4 -> 0 | O33: =E33*1.4 -> 0 | P33: ='[1]Lpg (2)'!#REF! -> #REF! | Q33: ='[1]Summery Report'!#REF! -> #REF! | R33: =N33/B33 -> #DIV/0! | S33: =Q33/B33 -> #REF! | T33: =3124/13 -> 240.30769
A34: =Gen!B39 -> 44072 | B34: ='Summery Report'!E33 -> 0 | C34: =Gen!U39 -> 0 | D34: =Gen!T39 -> 0 | E34: =Gen!AK39 -> 0 | F34: =Gen!AS39 -> 0 | G34: ='Utility report '!AC34 -> 0 | H34: ='Utility report '!AE34 -> 0 | I34: ='Water-Meter'!E34 -> 0 | J34: ='Lpg (2)'!B38 -> 0 | K34: ='Lpg (2)'!C38 -> 0 | L34: ='Lpg (2)'!D38 -> 0 | M34: ='Lpg (2)'!G38 -> 0 | N34: =D34*1.4 -> 0 | O34: =E34*1.4 -> 0 | P34: ='[1]Lpg (2)'!#REF! -> #REF! | Q34: ='[1]Summery Report'!#REF! -> #REF! | R34: =N34/B34 -> #DIV/0! | S34: =Q34/B34 -> #REF!
A35: =Gen!B40 -> 44073 | B35: ='Summery Report'!E34 -> 0 | C35: =Gen!U40 -> 0 | D35: =Gen!T40 -> 0 | E35: =Gen!AK40 -> 0 | F35: =Gen!AS40 -> 0 | G35: ='Utility report '!AC35 -> 0 | H35: ='Utility report '!AE35 -> 0 | I35: ='Water-Meter'!E35 -> 0 | J35: ='Lpg (2)'!B39 -> 0 | K35: ='Lpg (2)'!C39 -> 0 | L35: ='Lpg (2)'!D39 -> 0 | M35: ='Lpg (2)'!G39 -> 0 | N35: =D35*1.4 -> 0 | O35: =E35*1.4 -> 0 | P35: ='[1]Lpg (2)'!#REF! -> #REF! | Q35: ='[1]Summery Report'!#REF! -> #REF! | R35: =N35/B35 -> #DIV/0! | S35: =Q35/B35 -> #REF!
A36: =Gen!B41 -> 44074 | B36: ='Summery Report'!E35 -> 0 | C36: =Gen!U41 -> 0 | D36: =Gen!T41 -> 0 | E36: =Gen!AK41 -> 0 | F36: =Gen!AS41 -> 0 | G36: ='Utility report '!AC36 -> 0 | H36: ='Utility report '!AE36 -> 0 | I36: ='Water-Meter'!E36 -> 0 | J36: ='Lpg (2)'!B40 -> 0 | K36: ='Lpg (2)'!C40 -> 0 | L36: ='Lpg (2)'!D40 -> 0 | M36: ='Lpg (2)'!G40 -> 0 | N36: =D36*1.4 -> 0 | O36: =E36*1.4 -> 0 | P36: ='[1]Lpg (2)'!#REF! -> #REF! | Q36: ='[1]Summery Report'!#REF! -> #REF! | R36: =N36/B36 -> #DIV/0! | S36: =Q36/B36 -> #REF!
A37: =Gen!B42 -> 0 | B37: ='Summery Report'!E36 -> 0 | C37: =Gen!U42 -> 0 | D37: =Gen!T42 -> 0 | E37: =Gen!AK42 -> 0 | F37: =Gen!AS42 -> 0 | G37: ='Utility report '!AC37 -> 0 | H37: ='Utility report '!AE37 -> 0 | I37: ='Water-Meter'!E37 -> 0 | J37: ='Lpg (2)'!B41 -> 0 | K37: ='Lpg (2)'!C41 -> 0 | L37: ='Lpg (2)'!D41 -> 0 | M37: ='Lpg (2)'!G41 -> 0 | Q37: ='[1]Summery Report'!#REF! -> #REF! | R37: =N37/B37 -> #DIV/0! | S37: =Q37/B37 -> #REF!
A39: Total | B39: =SUM(B7:B37) -> 0 | C39: =SUM(C7:C35) -> 11326 | D39: =SUM(D7:D35) -> 4689.92 | E39: =SUM(E7:E35) -> 315.08 | F39: =SUM(F7:F35) -> 5005 | G39: =SUM(G7:G35) -> -36020 | H39: =SUM(H7:H35) -> -203368 | I39: =SUM(I7:I35) -> 328 | J39: =SUM(J7:J35) -> 510 | ... S39: =SUM(S7:S35) -> #REF!

Sheet Utility report 
A1: DAILY UTILITY REPORT AUGUST 2020
A2: Date | B2: Total occupancy | H2: Diesel balance LTS | I2: Diesel Deliveries | J2: Gen.Diesel consumption LTS | L2: Total Diesel consumption LTS | M2: Water Meter reading | N2: Water consumption m³ | O2: R.O WATER PRODUCTION LTRS + TIME | AA2: Total RO production | AB2: RO Meter reading | AD2: 0 | AE2: STP | AF2: GAS TANK A | AG2: GAS TANK B | AH2: GAS TANK C | AI2: Total Gas Tanks | AJ2: Kg /day | AK2: TOTAL GAS cons.
A3: Rate Tsh /$ | B3: 1640 | C3: Diesel cost / lits | D3: 2175 | F3: =SUM(D3/B3) -> 1.3262195 | H3: =Gen!D11 -> 41431.87 | K3: Transport consumption | M3: Balance | O3: PLANT NO 1 | S3: PLANT NO 2 | W3: PLANT NO 3 | AA3: /day | AB3: Balance | AC3: Production | AD3: 0 | AE3: Production | AF3: Capacity | AG3: Capacity | AH3: Capacity | AI3: Kg | AJ3: /day | AK3: /day
B4: Rooms OCC | C4: % | D4: Guest Rooms Occ | F4: Electricity Production Cost /Room Occ by guest | G4: All Cost /Room Occ by guest | O4: Flow M3 | P4: Reading Hours Meter | Q4: Hrs | R4: total production M3 | S4: Flow M3 | T4: Reading Hours Meter | U4: Hrs | V4: total production M3 | W4: Flow M3 | X4: READING HOURS METER | Y4: Hrs | Z4: total production M3 | AA4: M3 | AC4: M3 | AE4: M3 | AF4: 2000 | AG4: 1000 | AH4: 1000 | AI4: =SUM([2]Sheet1!$AA$36) -> 950 | AJ4: Kg | AK4: M3
T5: 16713 | AB5: 35942 | AD5: 203320 | AF5: 0.85 | AG5: 0.85 | AH5: 0.85
A6: =Gen!B11 -> 44044 | B6: ='Summery Report'!E5 -> 0 | C6: =Gen!C11 -> 0 | D6: ='Summery Report'!E5 -> 0 | E6: =SUM(F3) -> 1.3262195 | F6: =SUM(J6*E6)/D6 -> #DIV/0! | G6: =SUM(L6*E6)/D6 -> #DIV/0! | H6: =Gen!D11 -> 41431.87 | I6: =Gen!F11 -> 0 | J6: =Gen!T11 -> 741.42 | K6: =Gen!AK11 -> 16.85 | L6: =SUM(J6:K6) -> 758.27 | M6: ='Water-Meter'!K46 -> 349.48762 | N6: ='Water-Meter'!E6 -> 51 | Q6: =SUM(P6-P5) -> 0 | R6: =SUM(Q6*O6) -> 0 | S6: 7.5 | T6: 16725 | U6: =T6-T5 -> 12 | V6: - | Y6: =X6-X5 -> 0 | Z6: =Y6-Y5 -> 0 | AA6: =Z6-Z5 -> 0 | AB6: 36020 | AC6: =AB6-AB5 -> 78 | AD6: 203368 | AE6: =AD6-AD5 -> 48 | AF6: ='Lpg (2)'!B10*2000/85 -> 2000 | AG6: ='Lpg (2)'!C10*1000/85 -> 1000 | AH6: ='Lpg (2)'!D10*1000/85 -> 1000 | AI6: =SUM(AF6*2000)+(AG6*1000)+(AH6*1000) -> 6000000 | AJ6: =SUM(AI5-AI6) -> -6000000
A7: =Gen!B12 -> 44045 | B7: ='Summery Report'!E6 -> 0 | C7: =Gen!C12 -> 0 | D7: ='Summery Report'!E6 -> 0 | E7: =SUM(E6) -> 1.3262195 | F7: =SUM(J7*E7)/D7 -> #DIV/0! | G7: =SUM(L7*E7)/D7 -> #DIV/0! | H7: =Gen!D12 -> 40673.6 | I7: =Gen!F12 -> 0 | J7: =Gen!T12 -> 782.06 | K7: =Gen!AK12 -> 0 | L7: =SUM(J7:K7) -> 782.06 | M7: ='Water-Meter'!K47 -> 388.24985 | N7: ='Water-Meter'!E7 -> 53 | Q7: =SUM(P7-P6) -> 0 | R7: =SUM(Q7*O7) -> 0 | S7: 7.5 | T7: 16749 | U7: =T7-T6 -> 24 | V7: =SUM(U7*S7) -> 180 | Y7: =X7-X6 -> 0 | Z7: =SUM(Y7*W7) -> 0 | AA7: =SUM(Z7*X9) -> 0 | AB7: 36176 | AC7: =AB7-AB6 -> 156 | AD7: 203399 | AE7: =AD7-AD6 -> 31 | AF7: ='Lpg (2)'!B11*2000/85 -> 2000 | AG7: ='Lpg (2)'!C11*1000/85 -> 1000 | AH7: ='Lpg (2)'!D11*1000/85 -> 1000 | AI7: =SUM(AF6*2000)+(AG7*1000)+(AH7*1000) -> 6000000 | AJ7: =SUM(AI6-AI7) -> 0
A8: =Gen!B13 -> 44046 | B8: ='Summery Report'!E7 -> 0 | C8: =Gen!C13 -> 0 | D8: ='Summery Report'!E7 -> 0 | E8: =SUM(E7) -> 1.3262195 | F8: =SUM(J8*E8)/D8 -> #DIV/0! | G8: =SUM(L8*E8)/D8 -> #DIV/0! | H8: =Gen!D13 -> 39891.54 | I8: =Gen!F13 -> 0 | J8: =Gen!T13 -> 788.41 | K8: =Gen!AK13 -> 25.31 | L8: =SUM(J8:K8) -> 813.72 | M8: ='Water-Meter'!K48 -> 442.42456 | N8: ='Water-Meter'!E8 -> 42 | Q8: =SUM(P8-P7) -> 0 | R8: =SUM(Q8*O8) -> 0 | S8: 7.5 | T8: 16749 | U8: =T8-T7 -> 0 | V8: =SUM(U8*S8) -> 0 | Y8: =X8-X7 -> 0 | Z8: =SUM(Y8*W8) -> 0 | AA8: =SUM(Z8*X10) -> 0 | AB8: 36176 | AC8: =AB8-AB7 -> 0 | AD8: 203469 | AE8: =AD8-AD7 -> 70 | AF8: ='Lpg (2)'!B12*2000/85 -> 2000 | AG8: ='Lpg (2)'!C12*1000/85 -> 1000 | AH8: ='Lpg (2)'!D12*1000/85 -> 988.23529 | AI8: =SUM(AF7*2000)+(AG8*1000)+(AH8*1000) -> 5988235.3 | AJ8: =SUM(AI7-AI8) -> 11764.706
A9: =Gen!B14 -> 44047 | B9: ='Summery Report'!E8 -> 0 | C9: =Gen!C14 -> 0 | D9: ='Summery Report'!E8 -> 0 | E9: =SUM(E8) -> 1.3262195 | F9: =SUM(J9*E9)/D9 -> #DIV/0! | G9: =SUM(L9*E9)/D9 -> #DIV/0! | H9: =Gen!D14 -> 39077.82 | I9: =Gen!F14 -> 0 | J9: =Gen!T14 -> 793.61 | K9: =Gen!AK14 -> 149.86 | L9: =SUM(J9:K9) -> 943.47 | M9: ='Water-Meter'!K49 -> 518.61523 | N9: ='Water-Meter'!E9 -> 67 | Q9: =SUM(P9-P8) -> 0 | R9: =SUM(Q9*O9) -> 0 | S9: 7.5 | T9: 16749 | U9: =T9-T8 -> 0 | V9: =SUM(U9*S9) -> 0 | W9: 2.7 | X9: 24606 | Y9: =X9-X8 -> 24606 | Z9: =SUM(Y9*W9) -> 66436.2 | AA9: =SUM(Z9*X11) -> 1.6377852e+09 | AB9: 36231 | AC9: =AB9-AB8 -> 55 | AD9: 203505 | AE9: =AD9-AD8 -> 36 | AF9: ='Lpg (2)'!B13*2000/85 -> 2000 | AG9: ='Lpg (2)'!C13*1000/85 -> 1000 | AH9: ='Lpg (2)'!D13*1000/85 -> 988.23529 | AI9: =SUM(AF8*2000)+(AG9*1000)+(AH9*1000) -> 5988235.3 | AJ9: =SUM(AI8-AI9) -> 0
A10: =Gen!B15 -> 44048 | B10: ='Summery Report'!E9 -> 0 | C10: =Gen!C15 -> 0 | D10: ='Summery Report'!E9 -> 0 | E10: =SUM(E9) -> 1.3262195 | F10: =SUM(J10*E10)/D10 -> #DIV/0! | G10: =SUM(L10*E10)/D10 -> #DIV/0! | H10: =Gen!D15 -> 38134.35 | I10: =Gen!F15 -> 0 | J10: =Gen!T15 -> 776.02 | K10: =Gen!AK15 -> 87.31 | L10: =SUM(J10:K10) -> 863.33 | M10: ='Water-Meter'!K50 -> 579.19289 | N10: ='Water-Meter'!E10 -> 49 | Q10: =SUM(P10-P9) -> 0 | R10: =SUM(Q10*O10) -> 0 | S10: 7.5 | T10: 16749 | U10: =T10-T9 -> 0 | V10: =SUM(U10*S10) -> 0 | W10: 2.7 | X10: 24630 | Y10: =X10-X9 -> 24 | Z10: =SUM(Y10*W10) -> 64.8 | AA10: =SUM(Z10*X12) -> 1599004.8 | AB10: 36287 | AC10: =AB10-AB9 -> 56 | AD10: 203526 | AE10: =AD10-AD9 -> 21 | AF10: ='Lpg (2)'!B14*2000/85 -> 2000 | AG10: ='Lpg (2)'!C14*1000/85 -> 1000 | AH10: ='Lpg (2)'!D14*1000/85 -> 988.23529 | AI10: =SUM(AF9*2000)+(AG10*1000)+(AH10*1000) -> 5988235.3 | AJ10: =SUM(AI9-AI10) -> 0
A11: =Gen!B16 -> 44049 | B11: ='Summery Report'!E10 -> 0 | C11: =Gen!C16 -> 0 | D11: ='Summery Report'!E10 -> 0 | E11: =SUM(E10) -> 1.3262195 | F11: =SUM(J11*E11)/D11 -> #DIV/0! | G11: =SUM(L11*E11)/D11 -> #DIV/0! | H11: =Gen!D16 -> 37271.02 | I11: =Gen!F16 -> 0 | J11: =Gen!T16 -> 778.12 | K11: =Gen!AK16 -> 52.6 | L11: =SUM(J11:K11) -> 830.72 | M11: ='Water-Meter'!K51 -> 588.89159 | N11: ='Water-Meter'!E11 -> 66 | Q11: =SUM(P11-P10) -> 0 | R11: =SUM(Q11*O11) -> 0 | S11: 7.5 | T11: 16749 | U11: =T11-T10 -> 0 | V11: =SUM(U11*S11) -> 0 | W11: 2.7 | X11: 24652 | Y11: =X11-X10 -> 22 | Z11: =SUM(Y11*W11) -> 59.4 | AA11: =SUM(Z11*X13) -> 0 | AB11: 36337 | AC11: =AB11-AB10 -> 50 | AD11: 203566 | AE11: =AD11-AD10 -> 40 | AF11: ='Lpg (2)'!B15*2000/85 -> 2000 | AG11: ='Lpg (2)'!C15*1000/85 -> 1000 | AH11: ='Lpg (2)'!D15*1000/85 -> 976.47059 | AI11: =SUM(AF10*2000)+(AG11*1000)+(AH11*1000) -> 5976470.6 | AJ11: =SUM(AI10-AI11) -> 11764.706
A12: =Gen!B17 -> 44050 | B12: ='Summery Report'!E11 -> 0 | C12: =Gen!C17 -> 0 | D12: ='Summery Report'!E11 -> 0 | E12: =SUM(E11) -> 1.3262195 | F12: =SUM(J12*E12)/D12 -> #DIV/0! | G12: =SUM(L12*E12)/D12 -> #DIV/0! | H12: =Gen!D17 -> 36440.3 | I12: =Gen!F17 -> 0 | J12: =Gen!T17 -> 771.7 | K12: =Gen!AK17 -> 0 | L12: =SUM(J12:K12) -> 771.7 | M12: ='Water-Meter'!K52 -> 571.60065 | N12: ='Water-Meter'!E12 -> 51 | Q12: =SUM(P12-P11) -> 0 | R12: =SUM(Q12*O12) -> 0 | S12: 7.5 | T12: 16749 | U12: =T12-T11 -> 0 | V12: =SUM(U12*S12) -> 0 | W12: 2.7 | X12: 24676 | Y12: =X12-X11 -> 24 | Z12: =SUM(Y12*W12) -> 64.8 | AA12: =SUM(Z12*X14) -> 0 | AB12: 36392 | AC12: =AB12-AB11 -> 55 | AD12: 203604 | AE12: =AD12-AD11 -> 38 | AF12: ='Lpg (2)'!B16*2000/85 -> 2000 | AG12: ='Lpg (2)'!C16*1000/85 -> 1000 | AH12: ='Lpg (2)'!D16*1000/85 -> 0 | AI12: =SUM(AF11*2000)+(AG12*1000)+(AH12*1000) -> 5000000 | AJ12: =SUM(AI11-AI12) -> 976470.59
A13: =Gen!B18 -> 44051 | B13: ='Summery Report'!E12 -> 0 | C13: =Gen!C18 -> 0 | D13: ='Summery Report'!E12 -> 0 | E13: =SUM(E12) -> 1.3262195 | F13: =SUM(J13*E13)/D13 -> #DIV/0! | G13: =SUM(L13*E13)/D13 -> #DIV/0! | H13: =Gen!D18 -> 35668.6 | I13: =Gen!F18 -> 0 | J13: =Gen!T18 -> 0 | K13: =Gen!AK18 -> 0 | L13: =SUM(J13:K13) -> 0 | M13: ='Water-Meter'!K53 -> 574.56424 | N13: ='Water-Meter'!E13 -> 0 | Q13: =SUM(P13-P12) -> 0 | R13: =SUM(Q13*O13) -> 0 | U13: =T13-T12 -> -16749 | V13: =SUM(U13*S13) -> 0 | Y13: =X13-X12 -> -24676 | Z13: =SUM(Y13*W13) -> 0 | AA13: =SUM(Z13*X15) -> 0 | AC13: =AB13-AB12 -> -36392 | AE13: =AD13-AD12 -> -203604 | AF13: ='Lpg (2)'!B17*2000/85 -> 0 | AG13: ='Lpg (2)'!C17*1000/85 -> 0 | AH13: ='Lpg (2)'!D17*1000/85 -> 0 | AI13: =SUM(AF12*2000)+(AG13*1000)+(AH13*1000) -> 4000000 | AJ13: =SUM(AI12-AI13) -> 1000000
A14: =Gen!B19 -> 44052 | B14: ='Summery Report'!E13 -> 0 | C14: =Gen!C19 -> 0 | D14: ='Summery Report'!E13 -> 0 | E14: =SUM(E13) -> 1.3262195 | F14: =SUM(J14*E14)/D14 -> #DIV/0! | G14: =SUM(L14*E14)/D14 -> #DIV/0! | H14: =Gen!D19 -> 35668.6 | I14: =Gen!F19 -> 0 | J14: =Gen!T19 -> 0 | K14: =Gen!AK19 -> 0 | L14: =SUM(J14:K14) -> 0 | M14: ='Water-Meter'!K54 -> 0 | N14: ='Water-Meter'!E14 -> 0 | Q14: =SUM(P14-P13) -> 0 | R14: =SUM(Q14*O14) -> 0 | U14: =T14-T13 -> 0 | V14: =SUM(U14*S14) -> 0 | Y14: =X14-X13 -> 0 | Z14: =SUM(Y14*W14) -> 0 | AA14: =SUM(Z14*X16) -> 0 | AC14: =AB14-AB13 -> 0 | AE14: =AD14-AD13 -> 0 | AF14: ='Lpg (2)'!B18*2000/85 -> 0 | AG14: ='Lpg (2)'!C18*1000/85 -> 0 | AH14: ='Lpg (2)'!D18*1000/85 -> 0 | AI14: =SUM(AF13*2000)+(AG14*1000)+(AH14*1000) -> 0 | AJ14: =SUM(AI13-AI14) -> 4000000
A15: =Gen!B20 -> 44053 | B15: ='Summery Report'!E14 -> 0 | C15: =Gen!C20 -> 0 | D15: ='Summery Report'!E14 -> 0 | E15: =SUM(E14) -> 1.3262195 | F15: =SUM(J15*E15)/D15 -> #DIV/0! | G15: =SUM(L15*E15)/D15 -> #DIV/0! | H15: =Gen!D20 -> 35668.6 | I15: =Gen!F20 -> 0 | J15: =Gen!T20 -> 0 | K15: =Gen!AK20 -> 0 | L15: =SUM(J15:K15) -> 0 | M15: ='Water-Meter'!K55 -> 0 | N15: ='Water-Meter'!E15 -> 0 | Q15: =SUM(P15-P14) -> 0 | R15: =SUM(Q15*O15) -> 0 | U15: =T15-T14 -> 0 | V15: =SUM(U15*S15) -> 0 | Y15: =X15-X14 -> 0 | Z15: =SUM(Y15*W15) -> 0 | AA15: =SUM(Z15*X17) -> 0 | AC15: =AB15-AB14 -> 0 | AE15: =AD15-AD14 -> 0 | AF15: ='Lpg (2)'!B19*2000/85 -> 0 | AG15: ='Lpg (2)'!C19*1000/85 -> 0 | AH15: ='Lpg (2)'!D19*1000/85 -> 0 | AI15: =SUM(AF15*2000)+(AG15*1000)+(AH15*1000) -> 0 | AJ15: =SUM(AI14-AI15) -> 0
A16: =Gen!B21 -> 44054 | B16: ='Summery Report'!E15 -> 0 | C16: =Gen!C21 -> 0 | D16: ='Summery Report'!E15 -> 0 | E16: =SUM(E15) -> 1.3262195 | F16: =SUM(J16*E16)/D16 -> #DIV/0! | G16: =SUM(L16*E16)/D16 -> #DIV/0! | H16: =Gen!D21 -> 35668.6 | I16: =Gen!F21 -> 0 | J16: =Gen!T21 -> 0 | K16: =Gen!AK21 -> 0 | L16: =SUM(J16:K16) -> 0 | M16: ='Water-Meter'!K56 -> 0 | N16: ='Water-Meter'!E16 -> 0 | Q16: =SUM(P16-P15) -> 0 | R16: =SUM(Q16*O16) -> 0 | U16: =T16-T15 -> 0 | V16: =SUM(U16*S16) -> 0 | Y16: =X16-X15 -> 0 | Z16: =SUM(Y16*W16) -> 0 | AA16: =SUM(Z16*X18) -> 0 | AC16: =AB16-AB15 -> 0 | AE16: =AD16-AD15 -> 0 | AF16: ='Lpg (2)'!B20*2000/85 -> 0 | AG16: ='Lpg (2)'!C20*1000/85 -> 0 | AH16: ='Lpg (2)'!D20*1000/85 -> 0 | AI16: =SUM(AF16*2000)+(AG16*1000)+(AH16*1000) -> 0 | AJ16: =SUM(AI15-AI16) -> 0
A17: =Gen!B22 -> 44055 | B17: ='Summery Report'!E16 -> 0 | C17: =Gen!C22 -> 0 | D17: ='Summery Report'!E16 -> 0 | E17: =SUM(E16) -> 1.3262195 | F17: =SUM(J17*E17)/D17 -> #DIV/0! | G17: =SUM(L17*E17)/D17 -> #DIV/0! | H17: =Gen!D22 -> 35668.6 | I17: =Gen!F22 -> 0 | J17: =Gen!T22 -> 0 | K17: =Gen!AK22 -> 0 | L17: =SUM(J17:K17) -> 0 | M17: ='Water-Meter'!K57 -> 0 | N17: ='Water-Meter'!E17 -> 0 | Q17: =SUM(P18-P16) -> 0 | R17: =SUM(Q17*O17) -> 0 | U17: =T17-T16 -> 0 | V17: =SUM(U17*S17) -> 0 | Y17: =X17-X16 -> 0 | Z17: =SUM(Y17*W17) -> 0 | AA17: =SUM(Z17*X19) -> 0 | AC17: =AB17-AB16 -> 0 | AE17: =AD17-AD16 -> 0 | AF17: ='Lpg (2)'!B21*2000/85 -> 0 | AG17: ='Lpg (2)'!C21*1000/85 -> 0 | AH17: ='Lpg (2)'!D21*1000/85 -> 0 | AI17: =SUM(AF17*2000)+(AG17*1000)+(AH17*1000) -> 0 | AJ17: =SUM(AI16-AI17) -> 0
A18: =Gen!B23 -> 44056 | B18: ='Summery Report'!E17 -> 0 | C18: =Gen!C23 -> 0 | D18: ='Summery Report'!E17 -> 0 | E18: =SUM(E17) -> 1.3262195 | F18: =SUM(J18*E18)/D18 -> #DIV/0! | G18: =SUM(L18*E18)/D18 -> #DIV/0! | H18: =Gen!D23 -> 35668.6 | I18: =Gen!F23 -> 0 | J18: =Gen!T23 -> 0 | K18: =Gen!AK23 -> 0 | L18: =SUM(J18:K18) -> 0 | M18: ='Water-Meter'!K58 -> 0 | N18: ='Water-Meter'!E18 -> 0 | R18: =SUM(Q18*O18) -> 0 | U18: =T18-T17 -> 0 | V18: =SUM(U18*S18) -> 0 | Y18: =X18-X17 -> 0 | Z18: =SUM(Y18*W18) -> 0 | AA18: =SUM(Z18*X20) -> 0 | AC18: =AB18-AB17 -> 0 | AE18: =AD18-AD17 -> 0 | AF18: ='Lpg (2)'!B22*2000/85 -> 0 | AG18: ='Lpg (2)'!C22*1000/85 -> 0 | AH18: ='Lpg (2)'!D22*1000/85 -> 0 | AI18: =SUM(AF18*2000)+(AG18*1000)+(AH18*1000) -> 0 | AJ18: =SUM(AI17-AI18) -> 0
A19: =Gen!B24 -> 44057 | B19: ='Summery Report'!E18 -> 0 | C19: =Gen!C24 -> 0 | D19: ='Summery Report'!E18 -> 0 | E19: =SUM(E18) -> 1.3262195 | F19: =SUM(J19*E19)/D19 -> #DIV/0! | G19: =SUM(L19*E19)/D19 -> #DIV/0! | H19: =Gen!D24 -> 35668.6 | I19: =Gen!F24 -> 18000 | J19: =Gen!T24 -> 0 | K19: =Gen!AK24 -> 0 | L19: =SUM(J19:K19) -> 0 | M19: ='Water-Meter'!K59 -> 0 | N19: ='Water-Meter'!E19 -> 0 | R19: =SUM(Q19*O19) -> 0 | U19: =T19-T18 -> 0 | V19: =SUM(U19*S19) -> 0 | Y19: =X19-X18 -> 0 | Z19: =SUM(Y19*W19) -> 0 | AA19: =SUM(Z19*X21) -> 0 | AE19: =AD19-AD18 -> 0 | AF19: ='Lpg (2)'!B23*2000/85 -> 0 | AG19: ='Lpg (2)'!C23*1000/85 -> 0 | AH19: ='Lpg (2)'!D23*1000/85 -> 0 | AI19: =SUM(AF19*2000)+(AG19*1000)+(AH19*1000) -> 0 | AJ19: =SUM(AI18-AI19) -> 0
A20: =Gen!B25 -> 44058 | B20: ='Summery Report'!E19 -> 0 | C20: =Gen!C25 -> 0 | D20: ='Summery Report'!E19 -> 0 | E20: =SUM(E19) -> 1.3262195 | F20: =SUM(J20*E20)/D20 -> #DIV/0! | G20: =SUM(L20*E20)/D20 -> #DIV/0! | H20: =Gen!D25 -> 35668.6 | I20: =Gen!F25 -> 0 | J20: =Gen!T25 -> 0 | K20: =Gen!AK25 -> 0 | L20: =SUM(J20:K20) -> 0 | M20: ='Water-Meter'!K60 -> 0 | N20: ='Water-Meter'!E20 -> 0 | Q20: =SUM(P20-P19) -> 0 | R20: =SUM(Q20*O20) -> 0 | U20: =T20-T19 -> 0 | V20: =SUM(U20*S20) -> 0 | Y20: =X20-X19 -> 0 | Z20: =SUM(Y20*W20) -> 0 | AA20: =SUM(Z20*X22) -> 0 | AC20: =AB20-AB19 -> 0 | AE20: =AD20-AD19 -> 0 | AF20: ='Lpg (2)'!B24*2000/85 -> 0 | AG20: ='Lpg (2)'!C24*1000/85 -> 0 | AH20: ='Lpg (2)'!D24*1000/85 -> 0 | AI20: =SUM(AF20*2000)+(AG20*1000)+(AH20*1000) -> 0 | AJ20: =SUM(AI19-AI20) -> 0
A21: =Gen!B26 -> 44059 | B21: ='Summery Report'!E20 -> 0 | C21: =Gen!C26 -> 0 | D21: ='Summery Report'!E20 -> 0 | E21: =SUM(E20) -> 1.3262195 | F21: =SUM(J21*E21)/D21 -> #DIV/0! | G21: =SUM(L21*E21)/D21 -> #DIV/0! | H21: =Gen!D26 -> 35668.6 | I21: =Gen!F26 -> 0 | J21: =Gen!T26 -> 0 | K21: =Gen!AK26 -> 0 | L21: =SUM(J21:K21) -> 0 | M21: ='Water-Meter'!K61 -> 0 | N21: ='Water-Meter'!E21 -> 0 | Q21: =SUM(P21-P20) -> 0 | R21: =SUM(Q21*O21) -> 0 | U21: =T22-T20 -> 0 | V21: =SUM(U21*S21) -> 0 | Y21: =X21-X20 -> 0 | Z21: =SUM(Y21*W21) -> 0 | AA21: =SUM(Z21*X23) -> 0 | AC21: =AB21-AB20 -> 0 | AE21: =AD21-AD20 -> 0 | AF21: ='Lpg (2)'!B25*2000/85 -> 0 | AG21: ='Lpg (2)'!C25*1000/85 -> 0 | AH21: ='Lpg (2)'!D25*1000/85 -> 0 | AI21: =SUM(AF21*2000)+(AG21*1000)+(AH21*1000) -> 0 | AJ21: =SUM(AI20-AI21) -> 0
A22: =Gen!B27 -> 44060 | B22: ='Summery Report'!E21 -> 0 | C22: =Gen!C27 -> 0 | D22: ='Summery Report'!E21 -> 0 | E22: =SUM(E21) -> 1.3262195 | F22: =SUM(J22*E22)/D22 -> #DIV/0! | G22: =SUM(L22*E22)/D22 -> #DIV/0! | H22: =Gen!D27 -> 35668.6 | I22: =Gen!F27 -> 0 | J22: =Gen!T27 -> 0 | K22: =Gen!AK27 -> 0 | L22: =SUM(J22:K22) -> 0 | M22: ='Water-Meter'!K62 -> 0 | N22: ='Water-Meter'!E22 -> 0 | Q22: =SUM(P22-P21) -> 0 | R22: =SUM(Q22*O22) -> 0 | U22: =T23-T21 -> 0 | V22: =SUM(U22*S22) -> 0 | Y22: =X22-X21 -> 0 | Z22: =SUM(Y22*W22) -> 0 | AA22: =SUM(Z22*X24) -> 0 | AC22: =AB22-AB21 -> 0 | AE22: =AD22-AD21 -> 0 | AF22: ='Lpg (2)'!B26*2000/85 -> 0 | AG22: ='Lpg (2)'!C26*1000/85 -> 0 | AH22: ='Lpg (2)'!D26*1000/85 -> 0 | AI22: =SUM(AF22*2000)+(AG22*1000)+(AH22*1000) -> 0 | AJ22: =SUM(AI21-AI22) -> 0
A23: =Gen!B28 -> 44061 | B23: ='Summery Report'!E22 -> 0 | C23: =Gen!C28 -> 0 | D23: ='Summery Report'!E22 -> 0 | E23: =SUM(E22) -> 1.3262195 | F23: =SUM(J23*E23)/D23 -> #DIV/0! | G23: =SUM(L23*E23)/D23 -> #DIV/0! | H23: =Gen!D28 -> 35668.6 | I23: =Gen!F28 -> 0 | J23: =Gen!T28 -> 0 | K23: =Gen!AK28 -> 0 | L23: =SUM(J23:K23) -> 0 | M23: ='Water-Meter'!K63 -> 0 | N23: ='Water-Meter'!E23 -> 0 | Q23: =SUM(P23-P22) -> 0 | R23: =SUM(Q23*O23) -> 0 | U23: =T24-T22 -> 0 | V23: =SUM(U23*S23) -> 0 | Y23: =X23-X22 -> 0 | Z23: =SUM(Y23*W23) -> 0 | AA23: =SUM(Z23*X25) -> 0 | AC23: =AB23-AB22 -> 0 | AE23: =AD23-AD22 -> 0 | AF23: ='Lpg (2)'!B27*2000/85 -> 0 | AG23: ='Lpg (2)'!C27*1000/85 -> 0 | AH23: ='Lpg (2)'!D27*1000/85 -> 0 | AI23: =SUM(AF23*2000)+(AG23*1000)+(AH23*1000) -> 0 | AJ23: =SUM(AI22-AI23) -> 0
A24: =Gen!B29 -> 44062 | B24: ='Summery Report'!E23 -> 0 | C24: =Gen!C29 -> 0 | D24: ='Summery Report'!E23 -> 0 | E24: =SUM(E23) -> 1.3262195 | F24: =SUM(J24*E24)/D24 -> #DIV/0! | G24: =SUM(L24*E24)/D24 -> #DIV/0! | H24: =Gen!D29 -> 35668.6 | I24: =Gen!F29 -> 0 | J24: =Gen!T29 -> 0 | K24: =Gen!AK29 -> 0 | L24: =SUM(J24:K24) -> 0 | M24: ='Water-Meter'!K64 -> 0 | N24: ='Water-Meter'!E24 -> 0 | Q24: =SUM(P24-P23) -> 0 | R24: =SUM(Q24*O24) -> 0 | U24: =T24-T23 -> 0 | V24: =SUM(U24*S24) -> 0 | Y24: =X24-X23 -> 0 | Z24: =SUM(Y24*W24) -> 0 | AA24: =SUM(Z24*X26) -> 0 | AC24: =AB24-AB23 -> 0 | AE24: =AD24-AD23 -> 0 | AF24: ='Lpg (2)'!B28*2000/85 -> 0 | AG24: ='Lpg (2)'!C28*1000/85 -> 0 | AH24: ='Lpg (2)'!D28*1000/85 -> 0 | AI24: =SUM(AF24*2000)+(AG24*1000)+(AH24*1000) -> 0 | AJ24: =SUM(AI23-AI24) -> 0
A25: =Gen!B30 -> 44063 | B25: ='Summery Report'!E24 -> 0 | C25: =Gen!C30 -> 0 | D25: ='Summery Report'!E24 -> 0 | E25: =SUM(E24) -> 1.3262195 | F25: =SUM(J25*E25)/D25 -> #DIV/0! | G25: =SUM(L25*E25)/D25 -> #DIV/0! | H25: =Gen!D30 -> 35668.6 | I25: =Gen!F30 -> 0 | J25: =Gen!T30 -> 0 | K25: =Gen!AK30 -> 0 | L25: =SUM(J25:K25) -> 0 | M25: ='Water-Meter'!K65 -> 0 | N25: ='Water-Meter'!E25 -> 0 | Q25: =SUM(P25-P24) -> 0 | R25: =SUM(Q25*O25) -> 0 | U25: =T25-T24 -> 0 | V25: =SUM(U25*S25) -> 0 | Y25: =X25-X24 -> 0 | Z25: =SUM(Y25*W25) -> 0 | AA25: =SUM(Z25*X27) -> 0 | AC25: =AB25-AB24 -> 0 | AE25: =AD25-AD24 -> 0 | AF25: ='Lpg (2)'!B29*2000/85 -> 0 | AG25: ='Lpg (2)'!C29*1000/85 -> 0 | AH25: ='Lpg (2)'!D29*1000/85 -> 0 | AI25: =SUM(AF25*2000)+(AG25*1000)+(AH25*1000) -> 0 | AJ25: =SUM(AI24-AI25) -> 0
A26: =Gen!B31 -> 44064 | B26: ='Summery Report'!E25 -> 0 | C26: =Gen!C31 -> 0 | D26: ='Summery Report'!E25 -> 0 | E26: =SUM(E25) -> 1.3262195 | F26: =SUM(J26*E26)/D26 -> #DIV/0! | G26: =SUM(L26*E26)/D26 -> #DIV/0! | H26: =Gen!D31 -> 35668.6 | I26: =Gen!F31 -> 0 | J26: =Gen!T31 -> 0 | K26: =Gen!AK31 -> 0 | L26: =SUM(J26:K26) -> 0 | M26: ='Water-Meter'!K66 -> 0 | N26: ='Water-Meter'!E26 -> 0 | Q26: =SUM(P26-P25) -> 0 | R26: =SUM(Q26*O26) -> 0 | U26: =T26-T25 -> 0 | V26: =SUM(U26*S26) -> 0 | Y26: =X26-X25 -> 0 | Z26: =SUM(Y26*W26) -> 0 | AA26: =SUM(Z26*X28) -> 0 | AC26: =AB26-AB25 -> 0 | AE26: =AD26-AD25 -> 0 | AF26: ='Lpg (2)'!B30*2000/85 -> 0 | AG26: ='Lpg (2)'!C30*1000/85 -> 0 | AH26: ='Lpg (2)'!D30*1000/85 -> 0 | AI26: =SUM(AF26*2000)+(AG26*1000)+(AH26*1000) -> 0 | AJ26: =SUM(AI25-AI26) -> 0
A27: =Gen!B32 -> 44065 | B27: ='Summery Report'!E26 -> 0 | C27: =Gen!C32 -> 0 | D27: ='Summery Report'!E26 -> 0 | E27: =SUM(E26) -> 1.3262195 | F27: =SUM(J27*E27)/D27 -> #DIV/0! | G27: =SUM(L27*E27)/D27 -> #DIV/0! | H27: =Gen!D32 -> 35668.6 | I27: =Gen!F32 -> 0 | J27: =Gen!T32 -> 0 | K27: =Gen!AK32 -> 0 | L27: =SUM(J27:K27) -> 0 | M27: ='Water-Meter'!K67 -> 0 | N27: ='Water-Meter'!E27 -> 0 | Q27: =SUM(P27-P26) -> 0 | R27: =SUM(Q27*O27) -> 0 | U27: =T27-T26 -> 0 | V27: =SUM(U27*S27) -> 0 | Y27: =X27-X26 -> 0 | Z27: =SUM(Y27*W27) -> 0 | AA27: =SUM(Z27*X29) -> 0 | AC27: =AB27-AB26 -> 0 | AE27: =AD27-AD26 -> 0 | AF27: ='Lpg (2)'!B31*2000/85 -> 0 | AG27: ='Lpg (2)'!C31*1000/85 -> 0 | AH27: ='Lpg (2)'!D31*1000/85 -> 0 | AI27: =SUM(AF27*2000)+(AG27*1000)+(AH27*1000) -> 0 | AJ27: =SUM(AI26-AI27) -> 0
A28: =Gen!B33 -> 44066 | B28: ='Summery Report'!E27 -> 0 | C28: =Gen!C33 -> 0 | D28: ='Summery Report'!E27 -> 0 | E28: =SUM(E27) -> 1.3262195 | F28: =SUM(J28*E28)/D28 -> #DIV/0! | G28: =SUM(L28*E28)/D28 -> #DIV/0! | H28: =Gen!D33 -> 35668.6 | I28: =Gen!F33 -> 0 | J28: =Gen!T33 -> 0 | K28: =Gen!AK33 -> 0 | L28: =SUM(J28:K28) -> 0 | M28: ='Water-Meter'!K68 -> 0 | N28: ='Water-Meter'!E28 -> 0 | Q28: =SUM(P28-P27) -> 0 | R28: =SUM(Q28*O28) -> 0 | U28: =T28-T27 -> 0 | V28: =SUM(U28*S28) -> 0 | Y28: =X28-X27 -> 0 | Z28: =SUM(Y28*W28) -> 0 | AA28: =SUM(Z28*X30) -> 0 | AC28: =SUM(AB28-AB27) -> 0 | AE28: =AD28-AD27 -> 0 | AF28: ='Lpg (2)'!B32*2000/85 -> 0 | AG28: ='Lpg (2)'!C32*1000/85 -> 0 | AH28: ='Lpg (2)'!D32*1000/85 -> 0 | AI28: =SUM(AF28*2000)+(AG28*1000)+(AH28*1000) -> 0 | AJ28: =SUM(AI27-AI28) -> 0
A29: =Gen!B34 -> 44067 | B29: ='Summery Report'!E28 -> 0 | C29: =Gen!C34 -> 0 | D29: ='Summery Report'!E28 -> 0 | E29: =SUM(E28) -> 1.3262195 | F29: =SUM(J29*E29)/D29 -> #DIV/0! | G29: =SUM(L29*E29)/D29 -> #DIV/0! | H29: =Gen!D34 -> 35668.6 | I29: =Gen!F34 -> 0 | J29: =Gen!T34 -> 0 | K29: =Gen!AK34 -> 0 | L29: =SUM(J29:K29) -> 0 | M29: ='Water-Meter'!K69 -> 0 | N29: ='Water-Meter'!E29 -> 0 | Q29: =SUM(P29-P28) -> 0 | R29: =SUM(Q29*O29) -> 0 | U29: =T29-T28 -> 0 | V29: =SUM(U29*S29) -> 0 | Y29: =X29-X28 -> 0 | Z29: =SUM(Y29*W29) -> 0 | AA29: =SUM(Z29*X31) -> 0 | AC29: =SUM(AB29-AB28) -> 0 | AE29: =AD29-AD28 -> 0 | AF29: ='Lpg (2)'!B33*2000/85 -> 0 | AG29: ='Lpg (2)'!C33*1000/85 -> 0 | AH29: ='Lpg (2)'!D33*1000/85 -> 0 | AI29: =SUM(AF29*2000)+(AG29*1000)+(AH29*1000) -> 0 | AJ29: =SUM(AI28-AI29) -> 0
A30: =Gen!B35 -> 44068 | B30: ='Summery Report'!E29 -> 0 | C30: =Gen!C35 -> 0 | D30: ='Summery Report'!E29 -> 0 | E30: =SUM(E29) -> 1.3262195 | F30: =SUM(J30*E30)/D30 -> #DIV/0! | G30: =SUM(L30*E30)/D30 -> #DIV/0! | H30: =Gen!D35 -> 35668.6 | I30: =Gen!F35 -> 0 | J30: =Gen!T35 -> 0 | K30: =Gen!AK35 -> 0 | L30: =SUM(J30:K30) -> 0 | M30: ='Water-Meter'!K70 -> 0 | N30: ='Water-Meter'!E30 -> 0 | Q30: =SUM(P30-P29) -> 0 | R30: =SUM(Q30*O30) -> 0 | U30: =T30-T29 -> 0 | V30: =SUM(U30*S30) -> 0 | Y30: =X30-X29 -> 0 | Z30: =SUM(Y30*W30) -> 0 | AA30: =SUM(Z30*X32) -> 0 | AC30: =SUM(AB30-AB29) -> 0 | AE30: =AD30-AD29 -> 0 | AF30: ='Lpg (2)'!B34*2000/85 -> 0 | AG30: ='Lpg (2)'!C34*1000/85 -> 0 | AH30: ='Lpg (2)'!D34*1000/85 -> 0 | AI30: =SUM(AF30*2000)+(AG30*1000)+(AH30*1000) -> 0 | AJ30: =SUM(AI29-AI30) -> 0
A31: =Gen!B36 -> 44069 | B31: ='Summery Report'!E30 -> 0 | C31: =Gen!C36 -> 0 | D31: ='Summery Report'!E30 -> 0 | E31: =SUM(E30) -> 1.3262195 | F31: =SUM(J31*E31)/D31 -> #DIV/0! | G31: =SUM(L31*E31)/D31 -> #DIV/0! | H31: =Gen!D36 -> 35668.6 | I31: =Gen!F36 -> 0 | J31: =Gen!T36 -> 0 | K31: =Gen!AK36 -> 0 | L31: =SUM(J31:K31) -> 0 | M31: ='Water-Meter'!K71 -> 0 | N31: ='Water-Meter'!E31 -> 0 | Q31: =SUM(P31-P30) -> 0 | R31: =SUM(Q31*O31) -> 0 | U31: =T31-T30 -> 0 | V31: =SUM(U31*S31) -> 0 | Y31: =X31-X30 -> 0 | Z31: =SUM(Y31*W31) -> 0 | AA31: =SUM(Z31*X33) -> 0 | AC31: =SUM(AB31-AB30) -> 0 | AE31: =AD31-AD30 -> 0 | AF31: ='Lpg (2)'!B35*2000/85 -> 0 | AG31: ='Lpg (2)'!C35*1000/85 -> 0 | AH31: ='Lpg (2)'!D35*1000/85 -> 0 | AI31: =SUM(AF31*2000)+(AG31*1000)+(AH31*1000) -> 0 | AJ31: =SUM(AI30-AI31) -> 0
A32: =Gen!B37 -> 44070 | B32: ='Summery Report'!E31 -> 0 | C32: =Gen!C37 -> 0 | D32: ='Summery Report'!E31 -> 0 | E32: =SUM(E31) -> 1.3262195 | F32: =SUM(J32*E32)/D32 -> #DIV/0! | G32: =SUM(L32*E32)/D32 -> #DIV/0! | H32: =Gen!D37 -> 35668.6 | I32: =Gen!F37 -> 0 | J32: =Gen!T37 -> 0 | K32: =Gen!AK37 -> 0 | L32: =SUM(J32:K32) -> 0 | M32: ='Water-Meter'!K72 -> 0 | N32: ='Water-Meter'!E32 -> 0 | Q32: =SUM(P32-P31) -> 0 | R32: =SUM(Q32*O32) -> 0 | U32: =T32-T31 -> 0 | V32: =SUM(U32*S32) -> 0 | Y32: =X32-X31 -> 0 | Z32: =SUM(Y32*W32) -> 0 | AA32: =SUM(Z32*X34) -> 0 | AC32: =SUM(AB32-AB31) -> 0 | AE32: =AD32-AD31 -> 0 | AF32: ='Lpg (2)'!B36*2000/85 -> 0 | AG32: ='Lpg (2)'!C36*1000/85 -> 0 | AH32: ='Lpg (2)'!D36*1000/85 -> 0 | AI32: =SUM(AF32*2000)+(AG32*1000)+(AH32*1000) -> 0 | AJ32: =SUM(AI31-AI32) -> 0
A33: =Gen!B38 -> 44071 | B33: ='Summery Report'!E32 -> 0 | C33: =Gen!C38 -> 0 | D33: ='Summery Report'!E32 -> 0 | E33: =SUM(E32) -> 1.3262195 | F33: =SUM(J33*E33)/D33 -> #DIV/0! | G33: =SUM(L33*E33)/D33 -> #DIV/0! | H33: =Gen!D38 -> 35668.6 | I33: =Gen!F38 -> 10000 | J33: =Gen!T38 -> 0 | K33: =Gen!AK38 -> 0 | L33: =SUM(J33:K33) -> 0 | M33: ='Water-Meter'!K73 -> 0 | N33: ='Water-Meter'!E33 -> 0 | Q33: =SUM(P33-P32) -> 0 | R33: =SUM(Q33*O33) -> 0 | U33: =T33-T32 -> 0 | V33: =SUM(U33*S33) -> 0 | Y33: =X33-X32 -> 0 | Z33: =SUM(Y33*W33) -> 0 | AA33: =SUM(Z33*X35) -> 0 | AC33: =SUM(AB33-AB32) -> 0 | AE33: =AD33-AD32 -> 0 | AF33: ='Lpg (2)'!B37*2000/85 -> 0 | AG33: ='Lpg (2)'!C37*1000/85 -> 0 | AH33: ='Lpg (2)'!D37*1000/85 -> 0 | AI33: =SUM(AF33*2000)+(AG33*1000)+(AH33*1000) -> 0 | AJ33: =SUM(AI32-AI33) -> 0
A34: =Gen!B39 -> 44072 | B34: ='Summery Report'!E33 -> 0 | C34: =Gen!C39 -> 0 | D34: ='Summery Report'!E33 -> 0 | E34: =SUM(E33) -> 1.3262195 | F34: =SUM(J34*E34)/D34 -> #DIV/0! | G34: =SUM(L34*E34)/D34 -> #DIV/0! | H34: =Gen!D39 -> 35668.6 | I34: =Gen!F39 -> 0 | J34: =Gen!T39 -> 0 | K34: =Gen!AK39 -> 0 | L34: =SUM(J34:K34) -> 0 | M34: ='Water-Meter'!K74 -> 0 | N34: ='Water-Meter'!E34 -> 0 | Q34: =SUM(P34-P33) -> 0 | R34: =SUM(Q34*O34) -> 0 | U34: =T34-T33 -> 0 | V34: =SUM(U34*S34) -> 0 | Y34: =X34-X33 -> 0 | Z34: =SUM(Y34*W34) -> 0 | AA34: =SUM(Z34*X36) -> 0 | AC34: =SUM(AB34-AB33) -> 0 | AE34: =AD34-AD33 -> 0 | AF34: ='Lpg (2)'!B38*2000/85 -> 0 | AG34: ='Lpg (2)'!C38*1000/85 -> 0 | AH34: ='Lpg (2)'!D38*1000/85 -> 0 | AI34: =SUM(AF34*2000)+(AG34*1000)+(AH34*1000) -> 0 | AJ34: =SUM(AI33-AI34) -> 0
A35: =Gen!B40 -> 44073 | B35: ='Summery Report'!E34 -> 0 | C35: =Gen!C40 -> 0 | D35: ='Summery Report'!E34 -> 0 | E35: =SUM(E34) -> 1.3262195 | F35: =SUM(J35*E35)/D35 -> #DIV/0! | G35: =SUM(L35*E35)/D35 -> #DIV/0! | H35: =Gen!D40 -> 35668.6 | I35: =Gen!F40 -> 0 | J35: =Gen!T40 -> 0 | K35: =Gen!AK40 -> 0 | L35: =SUM(J35:K35) -> 0 | M35: ='Water-Meter'!K75 -> 0 | N35: ='Water-Meter'!E35 -> 0 | Q35: =SUM(P35-P34) -> 0 | R35: =SUM(Q35*O35) -> 0 | U35: =T35-T34 -> 0 | V35: =SUM(U35*S35) -> 0 | Y35: =X35-X34 -> 0 | Z35: =SUM(Y35*W35) -> 0 | AA35: =SUM(Z35*X37) -> 0 | AC35: =SUM(AB35-AB34) -> 0 | AE35: =AD35-AD34 -> 0 | AF35: ='Lpg (2)'!B39*2000/85 -> 0 | AG35: ='Lpg (2)'!C39*1000/85 -> 0 | AH35: ='Lpg (2)'!D39*1000/85 -> 0 | AI35: =SUM(AF35*2000)+(AG35*1000)+(AH35*1000) -> 0 | AJ35: =SUM(AI34-AI35) -> 0
A36: =Gen!B41 -> 44074 | B36: ='Summery Report'!E35 -> 0 | C36: =Gen!C41 -> 0 | D36: ='Summery Report'!E35 -> 0 | E36: =SUM(E35) -> 1.3262195 | F36: =SUM(J36*E36)/D36 -> #DIV/0! | G36: =SUM(L36*E36)/D36 -> #DIV/0! | H36: =Gen!D41 -> 35668.6 | I36: =Gen!F41 -> 0 | J36: =Gen!T41 -> 0 | K36: =Gen!AK41 -> 0 | L36: =SUM(J36:K36) -> 0 | M36: ='Water-Meter'!K76 -> 0 | N36: ='Water-Meter'!E36 -> 0 | Q36: =SUM(P36-P35) -> 0 | R36: =SUM(Q36*O36) -> 0 | U36: =T36-T35 -> 0 | V36: =SUM(U36*S36) -> 0 | Y36: =X36-X35 -> 0 | Z36: =SUM(Y36*W36) -> 0 | AA36: =SUM(Z36*X38) -> 0 | AC36: =SUM(AB36-AB35) -> 0 | AE36: =AD36-AD35 -> 0 | AF36: ='Lpg (2)'!B40*2000/85 -> 0 | AG36: ='Lpg (2)'!C40*1000/85 -> 0 | AH36: ='Lpg (2)'!D40*1000/85 -> 0 | AI36: =SUM(AF36*1000)+(AG36*1000)+(AH36*2000) -> 0 | AJ36: =SUM(AI35-AI36) -> 0
A37: =Gen!B42 -> 0 | B37: 0 | J37: =SUM(J6:J36) -> 5431.34 | L37: =SUM(J37:K37) -> 5431.34 | N37: ='Water-Meter'!E37 -> 0 | AC37: =SUM(AB37-AB36) -> 0 | AE37: =AD37-AD36 -> 0 | AJ37: =SUM(AJ6:AJ36) -> 0 | AK37: =SUM(AK6:AK36) -> 0

Sheet Kit report
B1: KITCHEN THREE PHASE KWH METER READING | H1: KITCHEN WATER METER READING | M1: AMANI Restaurant WATER METER READING | T1: LAUNDRY THREE PHASE KWH METER READING | Y1: LAUNDRY WATER METER READING
A2: Occ % | B2: DATE | C2: READING TIME | D2: METER READING OPEN | E2: METER READING ClOSE | F2: UNIT USED Kwh | H2: DATE | I2: READING TIME | J2: METER READING OPEN Cbm | K2: METER READING ClOSE Cbm | L2: UNIT USED Cbm | M2: DATE | N2: READING TIME | O2: METER READING OPEN Cbm | P2: METER READING ClOSE Cbm | Q2: UNIT USED Cbm | R2: Cost Per day Elct+Water $ | S2: % as per the total Lodge consumption | T2: DATE | U2: READING TIME | V2: METER READING OPEN (Kwh) | W2: METER READING ClOSE (Kwh) | X2: UNIT USED Kwh | Y2: DATE | Z2: READING TIME | AA2: METER READING OPEN Cbm | AB2: METER READING ClOSE Cbm | AC2: UNIT USED Cbm
A3: =Gen!B11 -> 44044 | B3: Close Last Month | E3: 8750.7 | F3: X120 | H3: Close Last Month | J3: ='Water-Meter'!G5 -> 38000 | K3: ='Water-Meter'!G5 -> 38000 | M3: Close Last Month | O3: ='Water-Meter'!J5 -> 7991 | P3: ='Water-Meter'!J5 -> 7991 | T3: Close Last Month | W3: 7812.1 | X3: =(W3-V3)*200 -> 1562420 | Y3: Close Last Month
A4: =Gen!C11 -> 0 | B4: =Gen!B11 -> 44044 | D4: =E3 -> 8750.7 | E4: 8751.9 | F4: =SUM(E4-D4)*120 -> 144 | H4: =B4 -> 44044 | J4: ='Water-Meter'!G6 -> 38000 | K4: ='Water-Meter'!G6 -> 38000 | L4: =SUM(K4-J4) -> 0 | M4: =H4 -> 44044 | O4: ='Water-Meter'!J6 -> 7992 | P4: ='Water-Meter'!J6 -> 7992 | Q4: =N4-O3 -> -7991 | R4: =SUM(Q4/1615) -> -4.9479876 | S4: =Gen!T11 -> 741.42 | T4: =M4 -> 44044 | V4: =W3 -> 7812.1 | W4: 7812.2 | X4: =(W4-V4)*200 -> 20 | Y4: =T4 -> 44044 | AB4: ='Water-Meter'!P6 -> 20203 | AC4: =AA4-AB3 -> 0
A5: =Gen!C12 -> 0 | B5: =Gen!B12 -> 44045 | D5: =E4 -> 8751.9 | E5: 8753.3 | F5: =SUM(E5-D5)*120 -> 168 | H5: =B5 -> 44045 | J5: ='Water-Meter'!G7 -> 38000 | K5: ='Water-Meter'!G7 -> 38000 | L5: =SUM(K5-J5) -> 0 | M5: =H5 -> 44045 | O5: ='Water-Meter'!J7 -> 7993 | P5: ='Water-Meter'!J7 -> 7993 | Q5: =N5-O4 -> -7992 | R5: =SUM(Q5/1615) -> -4.9486068 | S5: =Gen!T12 -> 782.06 | T5: =M5 -> 44045 | V5: =W4 -> 7812.2 | W5: 7812.4 | X5: =(W5-V5)*200 -> 40 | Y5: =T5 -> 44045 | AB5: ='Water-Meter'!P7 -> 20204 | AC5: =AA5-AB4 -> -20203
A6: =Gen!C13 -> 0 | B6: =Gen!B13 -> 44046 | D6: =E5 -> 8753.3 | E6: 8754.4 | F6: =SUM(E6-D6)*120 -> 132 | H6: =B6 -> 44046 | J6: ='Water-Meter'!G8 -> 38000 | K6: ='Water-Meter'!G8 -> 38000 | L6: =SUM(K6-J6) -> 0 | M6: =H6 -> 44046 | O6: ='Water-Meter'!J8 -> 7994 | P6: ='Water-Meter'!J8 -> 7994 | Q6: =N6-O5 -> -7993 | R6: =SUM(Q6/1615) -> -4.949226 | S6: =Gen!T13 -> 788.41 | T6: =M6 -> 44046 | V6: =W5 -> 7812.4 | W6: 7812.5 | X6: =(W6-V6)*200 -> 20 | Y6: =T6 -> 44046 | AB6: ='Water-Meter'!P8 -> 20205 | AC6: =AA6-AB5 -> -20204
A7: =Gen!C14 -> 0 | B7: =Gen!B14 -> 44047 | D7: =E6 -> 8754.4 | E7: 8755.9 | F7: =SUM(E7-D7)*120 -> 180 | H7: =B7 -> 44047 | J7: ='Water-Meter'!G9 -> 38000 | K7: ='Water-Meter'!G9 -> 38000 | L7: =SUM(K7-J7) -> 0 | M7: =H7 -> 44047 | O7: ='Water-Meter'!J9 -> 7994 | P7: ='Water-Meter'!J9 -> 7994 | Q7: =N7-O6 -> -7994 | R7: =SUM(Q7/1615) -> -4.9498452 | S7: =Gen!T14 -> 793.61 | T7: =M7 -> 44047 | V7: =W6 -> 7812.5 | W7: 7812.6 | X7: =(W7-V7)*200 -> 20 | Y7: =T7 -> 44047 | AB7: ='Water-Meter'!P9 -> 20206 | AC7: =AA7-AB6 -> -20205
A8: =Gen!C15 -> 0 | B8: =Gen!B15 -> 44048 | D8: =E7 -> 8755.9 | E8: 8757.3 | F8: =SUM(E8-D8)*120 -> 168 | H8: =B8 -> 44048 | J8: ='Water-Meter'!G10 -> 38000 | K8: ='Water-Meter'!G10 -> 38000 | L8: =SUM(K8-J8) -> 0 | M8: =H8 -> 44048 | O8: ='Water-Meter'!J10 -> 7995 | P8: ='Water-Meter'!J10 -> 7995 | Q8: =N8-O7 -> -7994 | R8: =SUM(Q8/1615) -> -4.9498452 | S8: =Gen!T15 -> 776.02 | T8: =M8 -> 44048 | V8: =W7 -> 7812.6 | W8: 7812.7 | X8: =(W8-V8)*200 -> 20 | Y8: =T8 -> 44048 | AB8: ='Water-Meter'!P10 -> 20207 | AC8: =AA8-AB7 -> -20206
A9: =Gen!C16 -> 0 | B9: =Gen!B16 -> 44049 | D9: =E8 -> 8757.3 | E9: 8758.6 | F9: =SUM(E9-D9)*120 -> 156 | H9: =B9 -> 44049 | J9: ='Water-Meter'!G11 -> 38000 | K9: ='Water-Meter'!G11 -> 38000 | L9: =SUM(K9-J9) -> 0 | M9: =H9 -> 44049 | O9: ='Water-Meter'!J11 -> 7996 | P9: ='Water-Meter'!J11 -> 7996 | Q9: =N9-O8 -> -7995 | R9: =SUM(Q9/1615) -> -4.9504644 | S9: =Gen!T16 -> 778.12 | T9: =M9 -> 44049 | V9: =W8 -> 7812.7 | W9: 7812.9 | X9: =(W9-V9)*200 -> 40 | Y9: =T9 -> 44049 | AB9: ='Water-Meter'!P11 -> 20210 | AC9: =AA9-AB8 -> -20207
A10: =Gen!C17 -> 0 | B10: =Gen!B17 -> 44050 | D10: =E9 -> 8758.6 | E10: 8759.9 | F10: =SUM(E10-D10)*120 -> 156 | H10: =B10 -> 44050 | J10: ='Water-Meter'!G12 -> 38000 | K10: ='Water-Meter'!G12 -> 38000 | L10: =SUM(K10-J10) -> 0 | M10: =H10 -> 44050 | O10: ='Water-Meter'!J12 -> 7997 | P10: ='Water-Meter'!J12 -> 7997 | Q10: =N10-O9 -> -7996 | R10: =SUM(Q10/1615) -> -4.9510836 | S10: =Gen!T17 -> 771.7 | T10: =M10 -> 44050 | V10: =W9 -> 7812.9 | W10: 7813.1 | X10: =(W10-V10)*200 -> 40 | Y10: =T10 -> 44050 | AB10: ='Water-Meter'!P12 -> 20211 | AC10: =AA10-AB9 -> -20210
A11: =Gen!C18 -> 0 | B11: =Gen!B18 -> 44051 | D11: =E10 -> 8759.9 | F11: =SUM(E11-D11)*120 -> -1051188 | H11: =B11 -> 44051 | J11: ='Water-Meter'!G13 -> 0 | K11: ='Water-Meter'!G13 -> 0 | L11: =SUM(K11-J11) -> 0 | M11: =H11 -> 44051 | O11: ='Water-Meter'!J13 -> 0 | P11: ='Water-Meter'!J13 -> 0 | Q11: =N11-O10 -> -7997 | R11: =SUM(Q11/1615) -> -4.9517028 | S11: =Gen!T18 -> 0 | T11: =M11 -> 44051 | V11: =W10 -> 7813.1 | X11: =(W11-V11)*200 -> -1562620 | Y11: =T11 -> 44051 | AB11: ='Water-Meter'!P13 -> 0 | AC11: =AA11-AB10 -> -20211
A12: =Gen!C19 -> 0 | B12: =Gen!B19 -> 44052 | D12: =E11 -> 0 | F12: =SUM(E12-D12)*120 -> 0 | H12: =B12 -> 44052 | J12: ='Water-Meter'!G14 -> 0 | K12: ='Water-Meter'!G14 -> 0 | L12: =SUM(K12-J12) -> 0 | M12: =H12 -> 44052 | O12: ='Water-Meter'!J14 -> 0 | P12: ='Water-Meter'!J14 -> 0 | Q12: =N12-O11 -> 0 | R12: =SUM(Q12/1615) -> 0 | S12: =Gen!T19 -> 0 | T12: =M12 -> 44052 | V12: =W11 -> 0 | X12: =(W12-V12)*200 -> 0 | Y12: =T12 -> 44052 | AB12: ='Water-Meter'!P14 -> 0 | AC12: =AA12-AB11 -> 0
A13: =Gen!C20 -> 0 | B13: =Gen!B20 -> 44053 | D13: =E12 -> 0 | F13: =SUM(E13-D13)*120 -> 0 | H13: =B13 -> 44053 | J13: ='Water-Meter'!G15 -> 0 | K13: ='Water-Meter'!G15 -> 0 | L13: =SUM(K13-J13) -> 0 | M13: =H13 -> 44053 | O13: ='Water-Meter'!J15 -> 0 | P13: ='Water-Meter'!J15 -> 0 | Q13: =N13-O12 -> 0 | R13: =SUM(Q13/1615) -> 0 | S13: =Gen!T20 -> 0 | T13: =M13 -> 44053 | V13: =W12 -> 0 | X13: =(W13-V13)*200 -> 0 | Y13: =T13 -> 44053 | AB13: ='Water-Meter'!P15 -> 0 | AC13: =AA13-AB12 -> 0
A14: =Gen!C21 -> 0 | B14: =Gen!B21 -> 44054 | D14: =E13 -> 0 | F14: =SUM(E14-D14)*120 -> 0 | H14: =B14 -> 44054 | J14: ='Water-Meter'!G16 -> 0 | K14: ='Water-Meter'!G16 -> 0 | L14: =SUM(K14-J14) -> 0 | M14: =H14 -> 44054 | O14: ='Water-Meter'!J16 -> 0 | P14: ='Water-Meter'!J16 -> 0 | Q14: =N14-O13 -> 0 | R14: =SUM(Q14/1615) -> 0 | S14: =Gen!T21 -> 0 | T14: =M14 -> 44054 | V14: =W13 -> 0 | X14: =(W14-V14)*200 -> 0 | Y14: =T14 -> 44054 | AB14: ='Water-Meter'!P16 -> 0 | AC14: =AA14-AB13 -> 0
A15: =Gen!C22 -> 0 | B15: =Gen!B22 -> 44055 | D15: =E14 -> 0 | F15: =SUM(E15-D15)*120 -> 0 | H15: =B15 -> 44055 | J15: ='Water-Meter'!G17 -> 0 | K15: ='Water-Meter'!G17 -> 0 | L15: =SUM(K15-J15) -> 0 | M15: =H15 -> 44055 | O15: ='Water-Meter'!J17 -> 0 | P15: ='Water-Meter'!J17 -> 0 | Q15: =N15-O14 -> 0 | R15: =SUM(Q15/1615) -> 0 | S15: =Gen!T22 -> 0 | T15: =M15 -> 44055 | V15: =W14 -> 0 | X15: =(W15-V15)*200 -> 0 | Y15: =T15 -> 44055 | AB15: ='Water-Meter'!P17 -> 0 | AC15: =AA15-AB14 -> 0
A16: =Gen!C23 -> 0 | B16: =Gen!B23 -> 44056 | D16: =E15 -> 0 | F16: =SUM(E16-D16)*120 -> 0 | H16: =B16 -> 44056 | J16: ='Water-Meter'!G18 -> 0 | K16: ='Water-Meter'!G18 -> 0 | L16: =SUM(K16-J16) -> 0 | M16: =H16 -> 44056 | O16: ='Water-Meter'!J18 -> 0 | P16: ='Water-Meter'!J18 -> 0 | Q16: =N16-O15 -> 0 | R16: =SUM(Q16/1615) -> 0 | S16: =Gen!T23 -> 0 | T16: =M16 -> 44056 | V16: =W15 -> 0 | X16: =(W16-V16)*200 -> 0 | Y16: =T16 -> 44056 | AB16: ='Water-Meter'!P18 -> 0 | AC16: =AA16-AB15 -> 0
A17: =Gen!C24 -> 0 | B17: =Gen!B24 -> 44057 | D17: =E16 -> 0 | F17: =SUM(E17-D17)*120 -> 0 | H17: =B17 -> 44057 | J17: ='Water-Meter'!G19 -> 0 | K17: ='Water-Meter'!G19 -> 0 | L17: =SUM(K17-J17) -> 0 | M17: =H17 -> 44057 | O17: ='Water-Meter'!J19 -> 0 | P17: ='Water-Meter'!J19 -> 0 | Q17: =N17-O16 -> 0 | R17: =SUM(Q17/1615) -> 0 | S17: =Gen!T24 -> 0 | T17: =M17 -> 44057 | V17: =W16 -> 0 | X17: =(W17-V17)*200 -> 0 | Y17: =T17 -> 44057 | AB17: ='Water-Meter'!P19 -> 0 | AC17: =AA17-AB16 -> 0
A18: =Gen!C25 -> 0 | B18: =Gen!B25 -> 44058 | D18: =E17 -> 0 | F18: =SUM(E18-D18)*120 -> 0 | H18: =B18 -> 44058 | J18: ='Water-Meter'!G20 -> 0 | K18: ='Water-Meter'!G20 -> 0 | L18: =SUM(K18-J18) -> 0 | M18: =H18 -> 44058 | O18: ='Water-Meter'!J20 -> 0 | P18: ='Water-Meter'!J20 -> 0 | Q18: =N18-O17 -> 0 | R18: =SUM(Q18/1615) -> 0 | S18: =Gen!T25 -> 0 | T18: =M18 -> 44058 | V18: =W17 -> 0 | X18: =(W18-V18)*200 -> 0 | Y18: =T18 -> 44058 | AB18: ='Water-Meter'!P20 -> 0 | AC18: =AA18-AB17 -> 0
A19: =Gen!C26 -> 0 | B19: =Gen!B26 -> 44059 | D19: =E18 -> 0 | F19: =SUM(E19-D19)*120 -> 0 | H19: =B19 -> 44059 | J19: ='Water-Meter'!G21 -> 0 | K19: ='Water-Meter'!G21 -> 0 | L19: =SUM(K19-J19) -> 0 | M19: =H19 -> 44059 | O19: ='Water-Meter'!J21 -> 0 | P19: ='Water-Meter'!J21 -> 0 | Q19: =N19-O18 -> 0 | R19: =SUM(Q19/1615) -> 0 | S19: =Gen!T26 -> 0 | T19: =M19 -> 44059 | V19: =W18 -> 0 | X19: =(W19-V19)*200 -> 0 | Y19: =T19 -> 44059 | AB19: ='Water-Meter'!P21 -> 0 | AC19: =AA19-AB18 -> 0
A20: =Gen!C27 -> 0 | B20: =Gen!B27 -> 44060 | D20: =E19 -> 0 | F20: =SUM(E20-D20)*120 -> 0 | H20: =B20 -> 44060 | J20: ='Water-Meter'!G22 -> 0 | K20: ='Water-Meter'!G22 -> 0 | L20: =SUM(K20-J20) -> 0 | M20: =H20 -> 44060 | O20: ='Water-Meter'!J22 -> 0 | P20: ='Water-Meter'!J22 -> 0 | Q20: =N20-O19 -> 0 | R20: =SUM(Q20/1615) -> 0 | S20: =Gen!T27 -> 0 | T20: =M20 -> 44060 | V20: =W19 -> 0 | X20: =(W20-V20)*200 -> 0 | Y20: =T20 -> 44060 | AB20: ='Water-Meter'!P22 -> 0 | AC20: =AA20-AB19 -> 0
A21: =Gen!C28 -> 0 | B21: =Gen!B28 -> 44061 | D21: =E20 -> 0 | F21: =SUM(E21-D21)*120 -> 0 | H21: =B21 -> 44061 | J21: ='Water-Meter'!G23 -> 0 | K21: ='Water-Meter'!G23 -> 0 | L21: =SUM(K21-J21) -> 0 | M21: =H21 -> 44061 | O21: ='Water-Meter'!J23 -> 0 | P21: ='Water-Meter'!J23 -> 0 | Q21: =N21-O20 -> 0 | R21: =SUM(Q21/1615) -> 0 | S21: =Gen!T28 -> 0 | T21: =M21 -> 44061 | V21: =W20 -> 0 | X21: =(W21-V21)*200 -> 0 | Y21: =T21 -> 44061 | AB21: ='Water-Meter'!P23 -> 0 | AC21: =AA21-AB20 -> 0
A22: =Gen!C29 -> 0 | B22: =Gen!B29 -> 44062 | D22: =E21 -> 0 | F22: =SUM(E22-D22)*120 -> 0 | H22: =B22 -> 44062 | J22: ='Water-Meter'!G24 -> 0 | K22: ='Water-Meter'!G24 -> 0 | L22: =SUM(K22-J22) -> 0 | M22: =H22 -> 44062 | O22: ='Water-Meter'!J24 -> 0 | P22: ='Water-Meter'!J24 -> 0 | Q22: =N22-O21 -> 0 | R22: =SUM(Q22/1615) -> 0 | S22: =Gen!T29 -> 0 | T22: =M22 -> 44062 | V22: =W21 -> 0 | X22: =(W22-V22)*200 -> 0 | Y22: =T22 -> 44062 | AB22: ='Water-Meter'!P24 -> 0 | AC22: =AA22-AB21 -> 0
A23: =Gen!C30 -> 0 | B23: =Gen!B30 -> 44063 | D23: =E22 -> 0 | F23: =SUM(E23-D23)*120 -> 0 | H23: =B23 -> 44063 | J23: ='Water-Meter'!G25 -> 0 | K23: ='Water-Meter'!G26 -> 0 | L23: =SUM(K23-J23) -> 0 | M23: =H23 -> 44063 | O23: ='Water-Meter'!J25 -> 0 | P23: ='Water-Meter'!J25 -> 0 | Q23: =N23-O22 -> 0 | R23: =SUM(Q23/1615) -> 0 | S23: =Gen!T30 -> 0 | T23: =M23 -> 44063 | V23: =W22 -> 0 | X23: =(W23-V23)*200 -> 0 | Y23: =T23 -> 44063 | AB23: ='Water-Meter'!P25 -> 0 | AC23: =AA23-AB22 -> 0
A24: =Gen!C31 -> 0 | B24: =Gen!B31 -> 44064 | D24: =SUM(E23) -> 0 | F24: =SUM(E24-D24)*120 -> 0 | H24: =B24 -> 44064 | J24: ='Water-Meter'!G26 -> 0 | K24: ='Water-Meter'!G27 -> 0 | L24: =SUM(K24-J24) -> 0 | M24: =H24 -> 44064 | O24: ='Water-Meter'!J26 -> 0 | P24: ='Water-Meter'!J26 -> 0 | Q24: =N24-O23 -> 0 | R24: =SUM(Q24/1615) -> 0 | S24: =Gen!T31 -> 0 | T24: 5835.7 | V24: =W23 -> 0 | X24: =(W24-V24)*200 -> 0 | Y24: =T24 -> 5835.7 | AB24: ='Water-Meter'!P26 -> 0 | AC24: =AA24-AB23 -> 0
A25: =Gen!C32 -> 0 | B25: =Gen!B32 -> 44065 | D25: =SUM(E24) -> 0 | F25: =SUM(E25-D25)*120 -> 0 | H25: =B25 -> 44065 | J25: ='Water-Meter'!G27 -> 0 | K25: ='Water-Meter'!G28 -> 0 | L25: =SUM(K25-J25) -> 0 | M25: =H25 -> 44065 | O25: ='Water-Meter'!J27 -> 0 | P25: ='Water-Meter'!J27 -> 0 | Q25: =N25-O24 -> 0 | R25: =SUM(Q25/1615) -> 0 | S25: =Gen!T32 -> 0 | T25: =M25 -> 44065 | V25: =W24 -> 0 | X25: =(W25-V25)*200 -> 0 | Y25: =T25 -> 44065 | AB25: ='Water-Meter'!P27 -> 0 | AC25: =AA25-AB24 -> 0
A26: =Gen!C33 -> 0 | B26: =Gen!B33 -> 44066 | D26: =SUM(E25) -> 0 | F26: =SUM(E26-D26)*120 -> 0 | H26: =B26 -> 44066 | J26: ='Water-Meter'!G28 -> 0 | K26: ='Water-Meter'!G29 -> 0 | L26: =SUM(K26-J26) -> 0 | M26: =H26 -> 44066 | O26: ='Water-Meter'!J28 -> 0 | P26: ='Water-Meter'!J28 -> 0 | Q26: =N26-O25 -> 0 | R26: =SUM(Q26/1615) -> 0 | S26: =Gen!T33 -> 0 | T26: =M26 -> 44066 | V26: =W25 -> 0 | X26: =(W26-V26)*200 -> 0 | Y26: =T26 -> 44066 | AB26: ='Water-Meter'!P28 -> 0 | AC26: =AA26-AB25 -> 0
A27: =Gen!C34 -> 0 | B27: =Gen!B34 -> 44067 | D27: =SUM(E26) -> 0 | F27: =SUM(E27-D27)*120 -> 0 | H27: =B27 -> 44067 | J27: ='Water-Meter'!G29 -> 0 | K27: ='Water-Meter'!G30 -> 0 | L27: =SUM(K27-J27) -> 0 | M27: =H27 -> 44067 | O27: ='Water-Meter'!J29 -> 0 | P27: ='Water-Meter'!J29 -> 0 | Q27: =N27-O26 -> 0 | R27: =SUM(Q27/1615) -> 0 | S27: =Gen!T34 -> 0 | T27: =M27 -> 44067 | V27: =W26 -> 0 | X27: =(W27-V27)*200 -> 0 | Y27: =T27 -> 44067 | AB27: ='Water-Meter'!P29 -> 0 | AC27: =AA27-AB26 -> 0
A28: =Gen!C35 -> 0 | B28: =Gen!B35 -> 44068 | D28: =SUM(E27) -> 0 | F28: =SUM(E28-D28)*120 -> 0 | H28: =B28 -> 44068 | J28: ='Water-Meter'!G30 -> 0 | K28: ='Water-Meter'!G31 -> 0 | L28: =SUM(K28-J28) -> 0 | M28: =H28 -> 44068 | O28: ='Water-Meter'!J30 -> 0 | P28: ='Water-Meter'!J30 -> 0 | Q28: =N28-O27 -> 0 | R28: =SUM(Q28/1615) -> 0 | S28: =Gen!T35 -> 0 | T28: =M28 -> 44068 | V28: =W27 -> 0 | X28: =(W28-V28)*200 -> 0 | Y28: =T28 -> 44068 | AB28: ='Water-Meter'!P30 -> 0 | AC28: =AA28-AB27 -> 0
A29: =Gen!C36 -> 0 | B29: =Gen!B36 -> 44069 | D29: =SUM(E28) -> 0 | F29: =SUM(E29-D29)*120 -> 0 | H29: =B29 -> 44069 | J29: ='Water-Meter'!G31 -> 0 | K29: ='Water-Meter'!G32 -> 0 | L29: =SUM(K29-J29) -> 0 | M29: =H29 -> 44069 | O29: ='Water-Meter'!J31 -> 0 | P29: ='Water-Meter'!J31 -> 0 | Q29: =N29-O28 -> 0 | R29: =SUM(Q29/1615) -> 0 | S29: =Gen!T36 -> 0 | T29: =M29 -> 44069 | V29: =W28 -> 0 | X29: =(W29-V29)*200 -> 0 | Y29: =T29 -> 44069 | AB29: ='Water-Meter'!P31 -> 0 | AC29: =AA29-AB28 -> 0
A30: =Gen!C37 -> 0 | B30: =Gen!B37 -> 44070 | D30: =SUM(E29) -> 0 | F30: =SUM(E30-D30)*120 -> 0 | H30: =B30 -> 44070 | J30: ='Water-Meter'!G32 -> 0 | K30: ='Water-Meter'!G33 -> 0 | L30: =SUM(K30-J30) -> 0 | M30: =H30 -> 44070 | O30: ='Water-Meter'!J32 -> 0 | P30: ='Water-Meter'!J32 -> 0 | Q30: =N30-O29 -> 0 | R30: =SUM(Q30/1615) -> 0 | S30: =Gen!T37 -> 0 | T30: =M30 -> 44070 | V30: =W29 -> 0 | X30: =(W30-V30)*200 -> 0 | Y30: =T30 -> 44070 | AB30: ='Water-Meter'!P32 -> 0 | AC30: =AA30-AB29 -> 0
A31: =Gen!C38 -> 0 | B31: =Gen!B38 -> 44071 | D31: =SUM(E30) -> 0 | F31: =SUM(E31-D31)*120 -> 0 | H31: =B31 -> 44071 | J31: ='Water-Meter'!G33 -> 0 | K31: ='Water-Meter'!G34 -> 0 | L31: =SUM(K31-J31) -> 0 | M31: =H31 -> 44071 | O31: ='Water-Meter'!J33 -> 0 | P31: ='Water-Meter'!J33 -> 0 | Q31: =N31-O30 -> 0 | R31: =SUM(Q31/1615) -> 0 | S31: =Gen!T38 -> 0 | T31: =M31 -> 44071 | V31: =W30 -> 0 | X31: =(W31-V31)*200 -> 0 | Y31: =T31 -> 44071 | AB31: ='Water-Meter'!P33 -> 0 | AC31: =AA31-AB30 -> 0
A32: =Gen!C39 -> 0 | B32: =Gen!B39 -> 44072 | D32: =SUM(E31) -> 0 | F32: =SUM(E32-D32)*120 -> 0 | H32: =B32 -> 44072 | J32: ='Water-Meter'!G34 -> 0 | K32: ='Water-Meter'!G34 -> 0 | L32: =SUM(K32-J32) -> 0 | M32: =H32 -> 44072 | O32: ='Water-Meter'!J34 -> 0 | P32: ='Water-Meter'!J34 -> 0 | Q32: =N32-O31 -> 0 | R32: =SUM(Q32/1615) -> 0 | S32: =Gen!T39 -> 0 | T32: =M32 -> 44072 | V32: =W31 -> 0 | X32: =(W32-V32)*200 -> 0 | Y32: =T32 -> 44072 | AB32: ='Water-Meter'!P34 -> 0 | AC32: =AA32-AB31 -> 0
A33: =Gen!C40 -> 0 | B33: =Gen!B40 -> 44073 | D33: =SUM(E32) -> 0 | F33: =SUM(E33-D33)*120 -> 0 | H33: =B33 -> 44073 | J33: ='Water-Meter'!G35 -> 0 | K33: ='Water-Meter'!G35 -> 0 | L33: =SUM(K33-J33) -> 0 | M33: =H33 -> 44073 | O33: ='Water-Meter'!J35 -> 0 | P33: ='Water-Meter'!J35 -> 0 | Q33: =N33-O32 -> 0 | R33: =SUM(Q33/1615) -> 0 | S33: =Gen!T40 -> 0 | T33: =M33 -> 44073 | V33: =W32 -> 0 | X33: =(W33-V33)*200 -> 0 | Y33: =T33 -> 44073 | AB33: ='Water-Meter'!P35 -> 0 | AC33: =AA33-AB32 -> 0
A34: =Gen!C41 -> 0 | B34: =Gen!B41 -> 44074 | D34: =SUM(E33) -> 0 | F34: =SUM(E34-D34)*120 -> 0 | H34: =B34 -> 44074 | J34: ='Water-Meter'!G36 -> 0 | K34: ='Water-Meter'!G36 -> 0 | L34: =SUM(K34-J34) -> 0 | M34: =H34 -> 44074 | O34: ='Water-Meter'!J36 -> 0 | P34: ='Water-Meter'!J36 -> 0 | Q34: =N34-O33 -> 0 | R34: =SUM(Q34/1615) -> 0 | S34: =Gen!T41 -> 0 | T34: =M34 -> 44074 | V34: =SUM(W33) -> 0 | X34: =(W34-V34)*200 -> 0 | Y34: =T34 -> 44074 | AB34: ='Water-Meter'!P36 -> 0 | AC34: =AA34-AB33 -> 0
A35: =[1]Gen!B42 -> #REF! | B35: =[1]Gen!A42 -> #REF! | D35: =SUM(E34) -> 0 | F35: =SUM(F4:F6) -> 444 | H35: =B35 -> #REF! | J35: =SUM(K34) -> 0 | K35: ='Water-Meter'!G37 -> 0 | L35: =SUM(L5:L34) -> 0 | M35: =H35 -> #REF! | P35: ='Water-Meter'!J37 -> 0 | Q35: =N35-O34 -> 0 | R35: =SUM(Q35/1615) -> 0 | S35: =Gen!T42 -> 0 | T35: =M35 -> #REF! | V35: =SUM(W34) -> 0 | X35: =(W35-V35)*200 -> 0 | Y35: =T35 -> #REF! | AB35: ='Water-Meter'!P37 -> 0 | AC35: =AA35-AB34 -> 0
X36: =SUM(X4:X6) -> 80

Sheet Summery Report
A2: Generator and Diseal Summry Report August 2020
A4: Date | B4: Gen Set Hours Working | C4: Occ% | D4: Total OCC Room | E4: Guest Room Occ | F4: Total Kwh Generated | G4: Diesel consumed by Gen (Ltrs) | H4: Diesel consumed by Vehicle (Ltrs) | I4: Total diesel consumed (Ltrs) | J4: Balance stock of Diesel (Ltrs) | K4: Water consumed | L4: Gas consumed (KG)
A5: =Gen!B11 -> 44044 | B5: ='Daily report Gen'!Z6 -> 152886 | C5: =Gen!C11 -> 0 | D5: =E5 -> 0 | F5: =Gen!U9 -> 0 | G5: =Gen!T9 -> 0 | H5: =Gen!AK11 -> 16.85 | I5: =SUM(G5:H5) -> 16.85 | J5: =Gen!D11 -> 41431.87 | K5: ='Water-Meter'!E6 -> 51 | L5: ='Lpg (2)'!G10 -> 315873.14 | M5: =SUM(#REF!-#REF!) -> #REF!
A6: =Gen!B12 -> 44045 | B6: ='Daily report Gen'!Z7 -> 25 | C6: =Gen!C12 -> 0 | D6: =E6 -> 0 | F6: =Gen!U10 -> 0 | G6: =Gen!T10 -> 0 | H6: =Gen!AK12 -> 0 | I6: =SUM(G6:H6) -> 0 | J6: =Gen!D12 -> 40673.6 | K6: ='Water-Meter'!E7 -> 53 | L6: ='Lpg (2)'!G11 -> 25.784 | M6: =SUM(#REF!-#REF!) -> #REF!
A7: =Gen!B13 -> 44046 | B7: ='Daily report Gen'!Z8 -> 24 | C7: =Gen!C13 -> 0 | D7: =E7 -> 0 | F7: =Gen!U11 -> 1872 | G7: =Gen!T11 -> 741.42 | H7: =Gen!AK13 -> 25.31 | I7: =SUM(G7:H7) -> 766.73 | J7: =Gen!D13 -> 39891.54 | K7: ='Water-Meter'!E8 -> 42 | L7: ='Lpg (2)'!G12 -> 65.648 | M7: =SUM(#REF!-#REF!) -> #REF!
A8: =Gen!B14 -> 44047 | B8: ='Daily report Gen'!Z9 -> 23 | C8: =Gen!C14 -> 0 | D8: =E8 -> 0 | F8: =Gen!U12 -> 2030 | G8: =Gen!T12 -> 782.06 | H8: =Gen!AK14 -> 149.86 | I8: =SUM(G8:H8) -> 931.92 | J8: =Gen!D14 -> 39077.82 | K8: ='Water-Meter'!E9 -> 67 | L8: ='Lpg (2)'!G13 -> 22.704 | M8: =SUM(#REF!-#REF!) -> #REF!
A9: =Gen!B15 -> 44048 | B9: ='Daily report Gen'!Z10 -> 24 | C9: =Gen!C15 -> 0 | D9: =E9 -> 0 | F9: =Gen!U13 -> 1818 | G9: =Gen!T13 -> 788.41 | H9: =Gen!AK15 -> 87.31 | I9: =SUM(G9:H9) -> 875.72 | J9: =Gen!D15 -> 38134.35 | K9: ='Water-Meter'!E10 -> 49 | L9: ='Lpg (2)'!G14 -> 31.24 | M9: =SUM(#REF!-#REF!) -> #REF!
A10: =Gen!B16 -> 44049 | B10: ='Daily report Gen'!Z11 -> 24 | C10: =Gen!C16 -> 0 | D10: =E10 -> 0 | F10: =Gen!U14 -> 1980 | G10: =Gen!T14 -> 793.61 | H10: =Gen!AK16 -> 52.6 | I10: =SUM(G10:H10) -> 846.21 | J10: =Gen!D16 -> 37271.02 | K10: ='Water-Meter'!E11 -> 66 | L10: ='Lpg (2)'!G15 -> 8.448 | M10: =SUM(#REF!-#REF!) -> #REF!
A11: =Gen!B17 -> 44050 | B11: ='Daily report Gen'!Z12 -> 25 | C11: =Gen!C17 -> 0 | D11: =E11 -> 0 | F11: =Gen!U15 -> 1724 | G11: =Gen!T15 -> 776.02 | H11: =Gen!AK17 -> 0 | I11: =SUM(G11:H11) -> 776.02 | J11: =Gen!D17 -> 36440.3 | K11: ='Water-Meter'!E12 -> 51 | L11: ='Lpg (2)'!G16 -> -316026.96 | M11: =SUM(#REF!-#REF!) -> #REF!
A12: =Gen!B18 -> 44051 | B12: ='Daily report Gen'!Z13 -> 24 | C12: =Gen!C18 -> 0 | D12: =E12 -> 0 | F12: =Gen!U16 -> 1892 | G12: =Gen!T16 -> 778.12 | H12: =Gen!AK18 -> 0 | I12: =SUM(G12:H12) -> 778.12 | J12: =Gen!D18 -> 35668.6 | K12: ='Water-Meter'!E13 -> 0 | L12: ='Lpg (2)'!G17 -> 0 | M12: =SUM(#REF!-#REF!) -> #REF!
A13: =Gen!B19 -> 44052 | B13: ='Daily report Gen'!Z14 -> -153055 | C13: =Gen!C19 -> 0 | D13: =E13 -> 0 | F13: =Gen!U17 -> 1882 | G13: =Gen!T17 -> 771.7 | H13: =Gen!AK19 -> 0 | I13: =SUM(G13:H13) -> 771.7 | J13: =Gen!D19 -> 35668.6 | K13: ='Water-Meter'!E14 -> 0 | L13: ='Lpg (2)'!G18 -> 0 | M13: =SUM(#REF!-#REF!) -> #REF!
A14: =Gen!B20 -> 44053 | B14: ='Daily report Gen'!Z15 -> 0 | C14: =Gen!C20 -> 0 | D14: =E14 -> 0 | F14: =Gen!U18 -> 0 | G14: =Gen!T18 -> 0 | H14: =Gen!AK20 -> 0 | I14: =SUM(G14:H14) -> 0 | J14: =Gen!D20 -> 35668.6 | K14: ='Water-Meter'!E15 -> 0 | L14: ='Lpg (2)'!G19 -> 0 | M14: =SUM(#REF!-#REF!) -> #REF!
A15: =Gen!B21 -> 44054 | B15: ='Daily report Gen'!Z16 -> 0 | C15: =Gen!C21 -> 0 | D15: =E15 -> 0 | F15: =Gen!U19 -> 0 | G15: =Gen!T19 -> 0 | H15: =Gen!AK21 -> 0 | I15: =SUM(G15:H15) -> 0 | J15: =Gen!D21 -> 35668.6 | K15: ='Water-Meter'!E16 -> 0 | L15: ='Lpg (2)'!G20 -> 0 | M15: =SUM(#REF!-#REF!) -> #REF!
A16: =Gen!B22 -> 44055 | B16: ='Daily report Gen'!Z17 -> 0 | C16: =Gen!C22 -> 0 | D16: =E16 -> 0 | F16: =Gen!U20 -> 0 | G16: =Gen!T20 -> 0 | H16: =Gen!AK22 -> 0 | I16: =SUM(G16:H16) -> 0 | J16: =Gen!D22 -> 35668.6 | K16: ='Water-Meter'!E17 -> 0 | L16: ='Lpg (2)'!G21 -> 0 | M16: =SUM(#REF!-#REF!) -> #REF!
... A35: =Gen!B41 -> 44074 | B35: ='Daily report Gen'!Z36 -> 0 | C35: =Gen!C41 -> 0 | D35: =E35 -> 0 | F35: =Gen!U39 -> 0 | G35: =Gen!T39 -> 0 | H35: =Gen!AK41 -> 0 | I35: =SUM(G35:H35) -> 0 | J35: =Gen!D41 -> 35668.6 | K35: ='Water-Meter'!E36 -> 0 | L35: ='Lpg (2)'!G40 -> 0 | M35: =SUM(#REF!-#REF!) -> #REF!
A36: =Gen!B42 -> 0 | B36: ='Daily report Gen'!Z37 -> 0 | C36: =Gen!C42 -> 0 | D36: =E36 -> 0 | F36: =Gen!U40 -> 0 | G36: =Gen!T40 -> 0 | H36: =Gen!AK42 -> 0 | I36: =SUM(G36:H36) -> 0 | J36: =Gen!D42 -> 35668.6 | K36: ='Water-Meter'!E37 -> 0 | L36: ='Lpg (2)'!G41 -> 0

Sheet Daily report Gen
A1: =A6 -> 44044
K3: GENERATOR NO.1 | N3: GENERATOR NO.2 | Q3: GENERATOR NO.4 | T3: GENERATOR NO.5 | W3: GENERATOR NO.6
A4: DATE | B4: OCC% | C4: D-TANK A | D4: D-TANK B | E4: DELIVERY DATE | F4: DELIVERY | G4: ISSUED-VEHICLE | H4: OTHERS | I4: M-R LV PANEL 1. KW-HR | J4: M-R LV PANEL 2. KW-HR | K4: OPEN HRS READING | L4: CLOSE HRS READING | M4: RUNNING HRS | N4: OPEN HRS READING | O4: CLOSE HRS READING | P4: RUNNING HRS | Q4: OPEN HRS READING | R4: CLOSE HRS READING | S4: RUNNING HRS | T4: OPEN HRS READING | U4: CLOSE HRS READING | V4: RUNNING HRS | W4: OPEN HRS READING | X4: CLOSE HRS READING | Y4: RUNNING HRS | Z4: TOTAL RUNNING HRS | AA4: MAX KW | AB4: MIN-KW | AC4: TOTAL DIESEL CONS.
A6: =Gen!B11 -> 44044 | C6: 21029.67 | D6: 20400.2 | G6: 16.85 | I6: 30839.4 | J6: 20468.8 | K6: =L5 -> 0 | L6: 34779 | M6: =L6-K6 -> 34779 | N6: =O5 -> 0 | O6: 29890 | P6: =O6-N6 -> 29890 | Q6: =R5 -> 0 | R6: 35426 | S6: =R6-Q6 -> 35426 | T6: =U5 -> 0 | U6: 32182 | V6: =U6-T6 -> 32182 | W6: =X5 -> 0 | X6: 20609 | Y6: =X6-W6 -> 20609 | Z6: =Y6+V6+S6+P6+M6 -> 152886 | AA6: 134 | AB6: 78 | AC6: =Gen!T11 -> 741.42
A7: =Gen!B12 -> 44045 | C7: 20293.41 | D7: 20400.2 | I7: 30842.1 | J7: 20441.3 | K7: =L6 -> 34779 | L7: 34779 | M7: =L7-K7 -> 0 | N7: =O6 -> 29890 | O7: 29902 | P7: =O7-N7 -> 12 | Q7: =R6 -> 35426 | R7: 35439 | S7: =R7-Q7 -> 13 | T7: =U6 -> 32182 | U7: 32182 | V7: =U7-T7 -> 0 | W7: =X6 -> 20609 | X7: 20609 | Y7: =X7-W7 -> 0 | Z7: =Y7+V7+S7+P7+M7 -> 25 | AA7: 135 | AB7: 76 | AC7: =Gen!T12 -> 782.06
A8: =Gen!B13 -> 44046 | C8: 19471.34 | D8: 20400.2 | G8: 25.31 | I8: 30844.7 | J8: 20444.3 | K8: =L7 -> 34779 | L8: 34792 | M8: =L8-K8 -> 13 | N8: =O7 -> 29902 | O8: 29913 | P8: =O8-N8 -> 11 | Q8: =R7 -> 35439 | R8: 35439 | S8: =R8-Q8 -> 0 | T8: =U7 -> 32182 | U8: 32182 | V8: =U8-T8 -> 0 | W8: =X7 -> 20609 | X8: 20609 | Y8: =X8-W8 -> 0 | Z8: =Y8+V8+S8+P8+M8 -> 24 | AA8: 131 | AB8: 73 | AC8: =Gen!T13 -> 788.41
A9: =Gen!B14 -> 44047 | C9: 18702.93 | D9: 20400.2 | G9: 149.86 | I9: 30847.3 | J9: 20446.6 | K9: =L8 -> 34792 | L9: 34792 | M9: =L9-K9 -> 0 | N9: =O8 -> 29913 | O9: 29913 | P9: =O9-N9 -> 0 | Q9: =R8 -> 35439 | R9: 35451 | S9: =R9-Q9 -> 12 | T9: =U8 -> 32182 | U9: 32182 | V9: =U9-T9 -> 0 | W9: =X8 -> 20609 | X9: 20620 | Y9: =X9-W9 -> 11 | Z9: =Y9+V9+S9+P9+M9 -> 23 | AA9: 134 | AB9: 75 | AC9: =Gen!T14 -> 793.61
A10: =Gen!B15 -> 44048 | C10: 17734.15 | D10: 20400.2 | G10: 87.31 | I10: 30850.1 | J10: 20449.2 | K10: =L9 -> 34792 | L10: 34804 | M10: =L10-K10 -> 12 | N10: =O9 -> 29913 | O10: 29913 | P10: =O10-N10 -> 0 | Q10: =R9 -> 35451 | R10: 35451 | S10: =R10-Q10 -> 0 | T10: =U9 -> 32182 | U10: 32182 | V10: =U10-T10 -> 0 | W10: =X9 -> 20620 | X10: 20632 | Y10: =X10-W10 -> 12 | Z10: =Y10+V10+S10+P10+M10 -> 24 | AA10: 132 | AB10: 72 | AC10: =Gen!T15 -> 776.02
A11: =Gen!B16 -> 44049 | C11: 16874.82 | D11: 20400.2 | G11: 52.6 | I11: 30852.7 | J11: 20451.7 | K11: =L10 -> 34804 | L11: 34817 | M11: =L11-K11 -> 13 | N11: =O10 -> 29913 | O11: 29924 | P11: =O11-N11 -> 11 | Q11: =R10 -> 35451 | R11: 35451 | S11: =R11-Q11 -> 0 | T11: =U10 -> 32182 | U11: 32182 | V11: =U11-T11 -> 0 | W11: =X10 -> 20632 | X11: 20632 | Y11: =X11-W11 -> 0 | Z11: =Y11+V11+S11+P11+M11 -> 24 | AA11: 135 | AB11: 73 | AC11: =Gen!T16 -> 778.12
A12: =Gen!B17 -> 44050 | C12: 16044.11 | D12: 20400.2 | I12: 30855.2 | J12: 20454.2 | K12: =L11 -> 34817 | L12: 34829 | M12: =L12-K12 -> 12 | N12: =O11 -> 29924 | O12: 29924 | P12: =O12-N12 -> 0 | Q12: =R11 -> 35451 | R12: 35451 | S12: =R12-Q12 -> 0 | T12: =U11 -> 32182 | U12: 32182 | V12: =U12-T12 -> 0 | W12: =X11 -> 20632 | X12: 20645 | Y12: =X12-W12 -> 13 | Z12: =Y12+V12+S12+P12+M12 -> 25 | AA12: 131 | AB12: 72 | AC12: =Gen!T17 -> 771.7
A13: =Gen!B18 -> 44051 | C13: 15270.41 | D13: 20400.2 | I13: 30857.8 | J13: 20456.8 | K13: =L12 -> 34829 | L13: 34829 | M13: =L13-K13 -> 0 | N13: =O12 -> 29924 | O13: 29937 | P13: =O13-N13 -> 13 | Q13: =R12 -> 35451 | R13: 35451 | S13: =R13-Q13 -> 0 | T13: =U12 -> 32182 | U13: 32182 | V13: =U13-T13 -> 0 | W13: =X12 -> 20645 | X13: 20656 | Y13: =X13-W13 -> 11 | Z13: =Y13+V13+S13+P13+M13 -> 24 | AA13: 134 | AB13: 73 | AC13: =Gen!T18 -> 0
A14: =Gen!B19 -> 44052 | K14: =L13 -> 34829 | M14: =L14-K14 -> -34829 | N14: =O13 -> 29937 | P14: =O14-N14 -> -29937 | Q14: =R13 -> 35451 | S14: =R14-Q14 -> -35451 | T14: =U13 -> 32182 | V14: =U14-T14 -> -32182 | W14: =X13 -> 20656 | Y14: =X14-W14 -> -20656 | Z14: =Y14+V14+S14+P14+M14 -> -153055 | AC14: =Gen!T19 -> 0
A15: =Gen!B20 -> 44053 | K15: =L14 -> 0 | M15: =L15-K15 -> 0 | N15: =O14 -> 0 | P15: =O15-N15 -> 0 | Q15: =R14 -> 0 | S15: =R15-Q15 -> 0 | T15: =U14 -> 0 | V15: =U15-T15 -> 0 | W15: =X14 -> 0 | Y15: =X15-W15 -> 0 | Z15: =Y15+V15+S15+P15+M15 -> 0 | AC15: =Gen!T20 -> 0
A16: =Gen!B21 -> 44054 | K16: =L15 -> 0 | M16: =L16-K16 -> 0 | N16: =O15 -> 0 | P16: =O16-N16 -> 0 | Q16: =R15 -> 0 | S16: =R16-Q16 -> 0 | T16: =U15 -> 0 | V16: =U16-T16 -> 0 | W16: =X15 -> 0 | Y16: =X16-W16 -> 0 | Z16: =Y16+V16+S16+P16+M16 -> 0 | AC16: =Gen!T21 -> 0
A17: =Gen!B22 -> 44055 | K17: =L16 -> 0 | M17: =L17-K17 -> 0 | N17: =O16 -> 0 | P17: =O17-N17 -> 0 | Q17: =R16 -> 0 | S17: =R17-Q17 -> 0 | T17: =U16 -> 0 | V17: =U17-T17 -> 0 | W17: =X16 -> 0 | Y17: =X17-W17 -> 0 | Z17: =Y17+V17+S17+P17+M17 -> 0 | AC17: =Gen!T22 -> 0
A18: =Gen!B23 -> 44056 | K18: =L17 -> 0 | M18: =L18-K18 -> 0 | N18: =O17 -> 0 | P18: =O18-N18 -> 0 | Q18: =R17 -> 0 | S18: =R18-Q18 -> 0 | T18: =U17 -> 0 | V18: =U18-T18 -> 0 | W18: =X17 -> 0 | Y18: =X18-W18 -> 0 | Z18: =Y18+V18+S18+P18+M18 -> 0 | AC18: =Gen!T23 -> 0
A19: =Gen!B24 -> 44057 | K19: =L18 -> 0 | M19: =L19-K19 -> 0 | N19: =O18 -> 0 | P19: =O19-N19 -> 0 | Q19: =R18 -> 0 | S19: =R19-Q19 -> 0 | T19: =U18 -> 0 | V19: =U19-T19 -> 0 | W19: =X18 -> 0 | Y19: =X19-W19 -> 0 | Z19: =Y19+V19+S19+P19+M19 -> 0 | AC19: =Gen!T24 -> 0
A20: =Gen!B25 -> 44058 | K20: =L19 -> 0 | M20: =L20-K20 -> 0 | N20: =O19 -> 0 | P20: =O20-N20 -> 0 | Q20: =R19 -> 0 | S20: =R20-Q20 -> 0 | T20: =U19 -> 0 | V20: =U20-T20 -> 0 | W20: =X19 -> 0 | Y20: =X20-W20 -> 0 | Z20: =Y20+V20+S20+P20+M20 -> 0 | AC20: =Gen!T25 -> 0
A21: =Gen!B26 -> 44059 | K21: =L20 -> 0 | M21: =L21-K21 -> 0 | N21: =O20 -> 0 | P21: =O21-N21 -> 0 | Q21: =R20 -> 0 | S21: =R21-Q21 -> 0 | T21: =U20 -> 0 | V21: =U21-T21 -> 0 | W21: =X20 -> 0 | Y21: =X21-W21 -> 0 | Z21: =Y21+V21+S21+P21+M21 -> 0 | AC21: =Gen!T26 -> 0
A22: =Gen!B27 -> 44060 | K22: =L21 -> 0 | M22: =L22-K22 -> 0 | N22: =O21 -> 0 | P22: =O22-N22 -> 0 | Q22: =R21 -> 0 | S22: =R22-Q22 -> 0 | T22: =U21 -> 0 | V22: =U22-T22 -> 0 | W22: =X21 -> 0 | Y22: =X22-W22 -> 0 | Z22: =Y22+V22+S22+P22+M22 -> 0 | AC22: =Gen!T27 -> 0
A23: =Gen!B28 -> 44061 | K23: =L22 -> 0 | M23: =L23-K23 -> 0 | N23: =O22 -> 0 | P23: =O23-N23 -> 0 | Q23: =R22 -> 0 | S23: =R23-Q23 -> 0 | T23: =U22 -> 0 | V23: =U23-T23 -> 0 | W23: =X22 -> 0 | Y23: =X23-W23 -> 0 | Z23: =Y23+V23+S23+P23+M23 -> 0 | AC23: =Gen!T28 -> 0
A24: =Gen!B29 -> 44062 | K24: =L23 -> 0 | M24: =L24-K24 -> 0 | N24: =O23 -> 0 | P24: =O24-N24 -> 0 | Q24: =R23 -> 0 | S24: =R24-Q24 -> 0 | T24: =U23 -> 0 | V24: =U24-T24 -> 0 | W24: =X23 -> 0 | Y24: =X24-W24 -> 0 | Z24: =Y24+V24+S24+P24+M24 -> 0 | AC24: =Gen!T29 -> 0
A25: =Gen!B30 -> 44063 | K25: =L24 -> 0 | M25: =L25-K25 -> 0 | N25: =O24 -> 0 | P25: =O25-N25 -> 0 | Q25: =R24 -> 0 | S25: =R25-Q25 -> 0 | T25: =U24 -> 0 | V25: =U25-T25 -> 0 | W25: =X24 -> 0 | Y25: =X25-W25 -> 0 | Z25: =Y25+V25+S25+P25+M25 -> 0 | AC25: =Gen!T30 -> 0
... A37: =Gen!B42 -> 0 | K37: =L36 -> 0 | M37: =L37-K37 -> 0 | N37: =O36 -> 0 | P37: =O37-N37 -> 0 | Q37: =R36 -> 0 | S37: =R37-Q37 -> 0 | T37: =U36 -> 0 | V37: =U37-T37 -> 0 | W37: =X36 -> 0 | Y37: =X37-W37 -> 0 | Z37: =Y37+V37+S37+P37+M37 -> 0 | AC37: =Gen!T42 -> 0

Sheet Gen
E2: HLP REPORT
I3: ='Daily report Gen'!A6 -> 44044
G6: BILILA LODGE INVESTMENT LIMITED | W6: 1 | X6: 2 | Y6: 3 | Z6: 4 | AA6: 5 | AB6: 6 | AC6: 7 | AD6: 8 | AE6: 9 | AF6: 10 | AG6: 11
G7: Diesel Consumed by 500KVA Generator | N7: 500KVA Generator KWh | W7: Safari-STAFF | X7: Safari-STAFF | Y7: Lc/swg/gust | Z7: Eng pikcup | AA7: VIP Safari Car | AB7: GX Guest | AC7: GX Guest | AD7: T/Hillux/pur | AE7: TATA | AF7: MAN | AG7: F/Truck | AH7: Incenerator | AI7: A&K | AJ7: OTHER | AK7: TOTAL CO
B8: Date | C8: Occupancy % | D8: OPENING | E8: Received | F8: Schedule delivery | G8: Company | H8: 1 | I8: 2 | J8: 3 | K8: 4 | L8: 5 | M8: 6 | N8: 1 | O8: 2 | P8: 3 | Q8: 4 | R8: 5 | S8: 6 | T8: Total Diseal Consumed | U8: Total Kwh generated | V8: Average Diesel/Kwh | W8: T 128 AXJ | X8: T 134 AXJ | Y8: T 499 AXG | Z8: T 217 CHV | AA8: T 214 CHV | AB8: T 139 AXE | AC8: T 242 AXN | AD8: T 476 AWZ | AE8: T 226 AUQ | AF8: T 308 CLD | AG8: T 852 AWU | AH8: Machine ENG | AI8: Vehicle | AJ8: Vehicle | AS8: Total Diseal Consumed Gen & Vehicle | AT8: Total cost /Day (TSH) | AU8: BALANCE
D9: =[4]Gen!$D$43 -> 41431.87 | T9: =SUM(G9:M9) -> 0 | U9: =SUM(N9:S9) -> 0 | AS9: =SUM(AK9+T9) -> 0 | AU9: 38784.7
T10: =SUM(G10:M10) -> 0 | U10: =SUM(N10:S10) -> 0 | V10: =SUM(O10:T10) -> 0 | AK10: =SUM(W10:AJ10) -> 0 | AS10: =SUM(AK10+T10) -> 0
B11: 44044 | D11: =SUM(D9+E11) -> 41431.87 | I11: 280.34 | K11: 461.08 | O11: 813 | Q11: 1059 | T11: =SUM(G11:M11) -> 741.42 | U11: =SUM(N11:S11) -> 1872 | V11: =T11/U11 -> 0.39605769 | Y11: 16.85 | AK11: =SUM(W11:AJ11) -> 16.85 | AS11: =SUM(AK11+T11) -> 758.27 | AT11: =AS11*AV11 -> 0 | AU11: =D11 -> 41431.87
B12: 44045 | D12: =SUM(D11-AS11+E12) -> 40673.6 | H12: 404.99 | I12: 377.07 | N12: 1065 | O12: 965 | T12: =SUM(G12:M12) -> 782.06 | U12: =SUM(N12:S12) -> 2030 | V12: =T12/U12 -> 0.38525123 | AK12: =SUM(W12:AJ12) -> 0 | AS12: =SUM(AK12+T12) -> 782.06 | AT12: =AS12*AV12 -> 0 | AU12: =D12 -> 40673.6
B13: 44046 | D13: =SUM(D12-AS12+E13) -> 39891.54 | K13: 419.82 | M13: 368.59 | Q13: 1020 | S13: 798 | T13: =SUM(G13:M13) -> 788.41 | U13: =SUM(N13:S13) -> 1818 | V13: =T13/U13 -> 0.43366887 | Y13: 25.31 | AK13: =SUM(W13:AJ13) -> 25.31 | AS13: =SUM(AK13+T13) -> 813.72 | AT13: =AS13*AV13 -> 0 | AU13: =D13 -> 39891.54
B14: 44047 | D14: =SUM(D13-AS13+E14) -> 39077.82 | H14: 403.84 | M14: 389.77 | N14: 1057 | S14: 923 | T14: =SUM(G14:M14) -> 793.61 | U14: =SUM(N14:S14) -> 1980 | V14: =T14/U14 -> 0.40081313 | AC14: 96.12 | AD14: 53.74 | AK14: =SUM(W14:AJ14) -> 149.86 | AS14: =SUM(AK14+T14) -> 943.47 | AT14: =AS14*AV14 -> 0 | AU14: =D14 -> 39077.82
B15: 44048 | D15: =SUM(D14-AS14+E15) -> 38134.35 | H15: 396.03 | I15: 379.99 | N15: 880 | O15: 844 | T15: =SUM(G15:M15) -> 776.02 | U15: =SUM(N15:S15) -> 1724 | V15: =T15/U15 -> 0.45012761 | X15: 87.31 | AK15: =SUM(W15:AJ15) -> 87.31 | AS15: =SUM(AK15+T15) -> 863.33 | AT15: =AS15*AV15 -> 0 | AU15: =D15 -> 38134.35
B16: 44049 | D16: =SUM(D15-AS15+E16) -> 37271.02 | H16: 380.55 | M16: 397.57 | N16: 886 | S16: 1006 | T16: =SUM(G16:M16) -> 778.12 | U16: =SUM(N16:S16) -> 1892 | V16: =T16/U16 -> 0.4112685 | Y16: 52.6 | AK16: =SUM(W16:AJ16) -> 52.6 | AS16: =SUM(AK16+T16) -> 830.72 | AT16: =AS16*AV16 -> 0 | AU16: =D16 -> 37271.02
B17: 44050 | D17: =SUM(D16-AS16+E17) -> 36440.3 | I17: 420.24 | M17: 351.46 | O17: 1048 | S17: 834 | T17: =SUM(G17:M17) -> 771.7 | U17: =SUM(N17:S17) -> 1882 | V17: =T17/U17 -> 0.41004251 | AK17: =SUM(W17:AJ17) -> 0 | AS17: =SUM(AK17+T17) -> 771.7 | AT17: =AS17*AV17 -> 0 | AU17: =D17 -> 36440.3
B18: 44051 | D18: =SUM(D17-AS17+E18) -> 35668.6 | T18: =SUM(G18:M18) -> 0 | U18: =SUM(N18:S18) -> 0 | V18: =T18/U18 -> #DIV/0! | AK18: =SUM(W18:AJ18) -> 0 | AS18: =SUM(AK18+T18) -> 0 | AT18: =AS18*AV18 -> 0 | AU18: =D18 -> 35668.6
B19: 44052 | D19: =SUM(D18-AS18+E19) -> 35668.6 | T19: =SUM(G19:M19) -> 0 | U19: =SUM(N19:S19) -> 0 | V19: =T19/U19 -> #DIV/0! | AK19: =SUM(W19:AJ19) -> 0 | AS19: =SUM(AK19+T19) -> 0 | AT19: =AS19*AV19 -> 0 | AU19: =D19 -> 35668.6
B20: 44053 | D20: =SUM(D19-AS19+E20) -> 35668.6 | T20: =SUM(G20:M20) -> 0 | U20: =SUM(N20:S20) -> 0 | V20: =T20/U20 -> #DIV/0! | AK20: =SUM(W20:AJ20) -> 0 | AS20: =SUM(AK20+T20) -> 0 | AT20: =AS20*AV20 -> 0 | AU20: =D20 -> 35668.6
B21: 44054 | D21: =SUM(D20-AS20+E21) -> 35668.6 | T21: =SUM(G21:M21) -> 0 | U21: =SUM(N21:S21) -> 0 | V21: =T21/U21 -> #DIV/0! | AK21: =SUM(W21:AJ21) -> 0 | AS21: =SUM(AK21+T21) -> 0 | AT21: =AS21*AV21 -> 0 | AU21: =D21 -> 35668.6
B22: 44055 | D22: =SUM(D21-AS21+E22) -> 35668.6 | T22: =SUM(G22:M22) -> 0 | U22: =SUM(N22:S22) -> 0 | V22: =T22/U22 -> #DIV/0! | AK22: =SUM(W22:AJ22) -> 0 | AS22: =SUM(AK22+T22) -> 0 | AT22: =AS22*AV22 -> 0 | AU22: =D22 -> 35668.6
B23: 44056 | D23: =SUM(D22-AS22+E23) -> 35668.6 | T23: =SUM(G23:M23) -> 0 | U23: =SUM(N23:S23) -> 0 | V23: =T23/U23 -> #DIV/0! | AK23: =SUM(W23:AJ23) -> 0 | AS23: =SUM(AK23+T23) -> 0 | AT23: =AS23*AV23 -> 0 | AU23: =D23 -> 35668.6
B24: 44057 | D24: =SUM(D23-AS23+E24) -> 35668.6 | F24: 18000 | G24: PUMA | T24: =SUM(G24:M24) -> 0 | U24: =SUM(N24:S24) -> 0 | V24: =T24/U24 -> #DIV/0! | AK24: =SUM(W24:AJ24) -> 0 | AS24: =SUM(AK24+T24) -> 0 | AT24: =AS24*AV24 -> 0 | AU24: =D24 -> 35668.6
B25: 44058 | D25: =SUM(D24-AS24+E25) -> 35668.6 | T25: =SUM(G25:M25) -> 0 | U25: =SUM(N25:S25) -> 0 | V25: =T25/U25 -> #DIV/0! | AK25: =SUM(W25:AJ25) -> 0 | AS25: =SUM(AK25+T25) -> 0 | AT25: =AS25*AV25 -> 0 | AU25: =D25 -> 35668.6
B26: 44059 | D26: =SUM(D25-AS25+E26) -> 35668.6 | T26: =SUM(G26:M26) -> 0 | U26: =SUM(N26:S26) -> 0 | V26: =T26/U26 -> #DIV/0! | AK26: =SUM(W26:AJ26) -> 0 | AS26: =SUM(AK26+T26) -> 0 | AT26: =AS26*AV26 -> 0 | AU26: =D26 -> 35668.6
B27: 44060 | D27: =SUM(D26-AS26+E27) -> 35668.6 | T27: =SUM(G27:M27) -> 0 | U27: =SUM(N27:S27) -> 0 | V27: =T27/U27 -> #DIV/0! | AK27: =SUM(W27:AJ27) -> 0 | AS27: =SUM(AK27+T27) -> 0 | AT27: =AS27*AV27 -> 0 | AU27: =D27 -> 35668.6
B28: 44061 | D28: =SUM(D27-AS27+E28) -> 35668.6 | T28: =SUM(G28:M28) -> 0 | U28: =SUM(N28:S28) -> 0 | V28: =T28/U28 -> #DIV/0! | AK28: =SUM(W28:AJ28) -> 0 | AS28: =SUM(AK28+T28) -> 0 | AT28: =AS28*AV28 -> 0 | AU28: =D28 -> 35668.6
B29: 44062 | D29: =SUM(D28-AS28+E29) -> 35668.6 | T29: =SUM(G29:M29) -> 0 | U29: =SUM(N29:S29) -> 0 | V29: =T29/U29 -> #DIV/0! | AK29: =SUM(W29:AJ29) -> 0 | AS29: =SUM(AK29+T29) -> 0 | AT29: =AS29*AV29 -> 0 | AU29: =D29 -> 35668.6
B30: 44063 | D30: =SUM(D29-AS29+E30) -> 35668.6 | T30: =SUM(G30:M30) -> 0 | U30: =SUM(N30:S30) -> 0 | V30: =T30/U30 -> #DIV/0! | AK30: =SUM(W30:AJ30) -> 0 | AS30: =SUM(AK30+T30) -> 0 | AT30: =AS30*AV30 -> 0 | AU30: =D30 -> 35668.6
B31: 44064 | D31: =SUM(D30-AS30+E31) -> 35668.6 | T31: =SUM(G31:M31) -> 0 | U31: =SUM(N31:S31) -> 0 | V31: =T31/U31 -> #DIV/0! | AK31: =SUM(W31:AJ31) -> 0 | AS31: =SUM(AK31+T31) -> 0 | AT31: =AS31*AV31 -> 0 | AU31: =D31 -> 35668.6
B32: 44065 | D32: =SUM(D31-AS31+E32) -> 35668.6 | T32: =SUM(G32:M32) -> 0 | U32: =SUM(N32:S32) -> 0 | V32: =T32/U32 -> #DIV/0! | AK32: =SUM(W32:AJ32) -> 0 | AS32: =SUM(AK32+T32) -> 0 | AT32: =AS32*AV32 -> 0 | AU32: =D32 -> 35668.6
B33: 44066 | D33: =SUM(D32-AS32+E33) -> 35668.6 | T33: =SUM(G33:M33) -> 0 | U33: =SUM(N33:S33) -> 0 | V33: =T33/U33 -> #DIV/0! | AK33: =SUM(W33:AJ33) -> 0 | AS33: =SUM(AK33+T33) -> 0 | AT33: =AS33*AV33 -> 0 | AU33: =D33 -> 35668.6
B34: 44067 | D34: =SUM(D33-AS33+E34) -> 35668.6 | T34: =SUM(G34:M34) -> 0 | U34: =SUM(N34:S34) -> 0 | V34: =T34/U34 -> #DIV/0! | AK34: =SUM(W34:AJ34) -> 0 | AS34: =SUM(AK34+T34) -> 0 | AT34: =AS34*AV34 -> 0 | AU34: =D34 -> 35668.6
B35: 44068 | D35: =SUM(D34-AS34+E35) -> 35668.6 | T35: =SUM(G35:M35) -> 0 | U35: =O35+Q35 -> 0 | V35: =T35/U35 -> #DIV/0! | AK35: =SUM(W35:AJ35) -> 0 | AS35: =SUM(AK35+T35) -> 0 | AT35: =AS35*AV35 -> 0 | AU35: =D35 -> 35668.6
B36: 44069 | D36: =SUM(D35-AS35+E36) -> 35668.6 | T36: =SUM(G36:M36) -> 0 | U36: =SUM(N36:S36) -> 0 | V36: =T36/U36 -> #DIV/0! | AK36: =SUM(W36:AJ36) -> 0 | AS36: =SUM(AK36+T36) -> 0 | AT36: =AS36*AV36 -> 0 | AU36: =D36 -> 35668.6
B37: 44070 | D37: =SUM(D36-AS36+E37) -> 35668.6 | T37: =SUM(G37:M37) -> 0 | U37: =SUM(N37:S37) -> 0 | V37: =T37/U37 -> #DIV/0! | AK37: =SUM(W37:AJ37) -> 0 | AS37: =SUM(AK37+T37) -> 0 | AT37: =AS37*AV37 -> 0 | AU37: =D37 -> 35668.6
B38: 44071 | D38: =SUM(D37-AS37+E38) -> 35668.6 | F38: 10000 | G38: PUMA | T38: =SUM(G38:M38) -> 0 | U38: =SUM(N38:S38) -> 0 | V38: =T38/U38 -> #DIV/0! | AK38: =SUM(W38:AJ38) -> 0 | AS38: =SUM(AK38+T38) -> 0 | AT38: =AS38*AV38 -> 0 | AU38: =D38 -> 35668.6
B39: 44072 | D39: =SUM(D38-AS38+E39) -> 35668.6 | T39: =SUM(G39:M39) -> 0 | U39: =SUM(N39:S39) -> 0 | V39: =T39/U39 -> #DIV/0! | AK39: =SUM(W39:AJ39) -> 0 | AS39: =SUM(AK39+T39) -> 0 | AT39: =AS39*AV39 -> 0 | AU39: =D39 -> 35668.6
B40: 44073 | D40: =SUM(D39-AS39+E40) -> 35668.6 | T40: =SUM(G40:M40) -> 0 | U40: =SUM(N40:S40) -> 0 | V40: =T40/U40 -> #DIV/0! | AK40: =SUM(W40:AJ40) -> 0 | AS40: =SUM(AK40+T40) -> 0 | AT40: =AS40*AV40 -> 0 | AU40: =D40 -> 35668.6
B41: 44074 | D41: =SUM(D40-AS40+E41) -> 35668.6 | T41: =SUM(G41:M41) -> 0 | U41: =SUM(N41:S41) -> 0 | V41: =T41/U41 -> #DIV/0! | AK41: =SUM(W41:AJ41) -> 0 | AS41: =SUM(AK41+T41) -> 0 | AT41: =AS41*AV41 -> 0 | AU41: =D41 -> 35668.6
D42: =SUM(D41-AS41+E42) -> 35668.6 | T42: =SUM(G42:M42) -> 0 | U42: =SUM(N42:S42) -> 0 | AK42: =SUM(W42:AJ42) -> 0 | AS42: =SUM(AK42+T42) -> 0 | AT42: =AS42*AV42 -> 0 | AU42: =D42 -> 35668.6
B43: BF | C43: =AVERAGE(C11:C42) -> #DIV/0! | D43: =SUM(D42-AS42+E43) -> 35668.6 | T43: =SUM(G43:M43) -> 0 | U43: =SUM(N43:S43) -> 0 | AK43: =SUM(W43:AJ43) -> 0 | AS43: =SUM(AK43+T43) -> 0 | AT43: =AS43*AV43 -> 0 | AU43: =D43 -> 35668.6
T44: =SUM(G44:M44) -> 0 | AK44: =SUM(W44:AJ44) -> 0 | AS44: =T44+AK44 -> 0 | AT44: =AS44*AV44 -> 0
E45: =SUM(E11:E44) -> 0 | F45: =SUM(F11:F42) -> 28000 | G45: =SUM(G11:G44) -> 0 | H45: =SUM(H11:H44) -> 1585.41 | I45: =SUM(I11:I44) -> 1457.64 | J45: =SUM(J11:J44) -> 0 | K45: =SUM(K11:K44) -> 880.9 | L45: =SUM(L11:L44) -> 0 | M45: =SUM(M11:M44) -> 1507.39 | N45: =SUM(N11:N44) -> 3888 | ... P45: =SUM(P11:P44) -> 0 | Q45: =SUM(Q11:Q43) -> 2079 | R45: =SUM(R11:R44) -> 0 | S45: =SUM(S11:S44) -> 3561 | T45: =SUM(G45:M45) -> 5431.34 | U45: =SUM(N45:S45) -> 13198 | V45: =SUM(V11:V42) -> #DIV/0! | W45: =SUM(W9:W44) -> 0 | X45: =SUM(X9:X44) -> 87.31 | Y45: =SUM(Y9:Y44) -> 94.76 | Z45: =SUM(Z9:Z44) -> 0 | AA45: =SUM(AA9:AA44) -> 0 | AB45: =SUM(AB9:AB44) -> 0 | AC45: =SUM(AC9:AC44) -> 96.12 | AD45: =SUM(AD10:AD44) -> 53.74 | AE45: =SUM(AE10:AE44) -> 0 | AF45: =SUM(AF9:AF44) -> 0 | AG45: =SUM(AG9:AG44) -> 0 | AH45: =SUM(AH9:AH44) -> 0 | AI45: =SUM(AI9:AI43) -> 0 | AJ45: =SUM(AJ9:AJ39) -> 0 | AK45: =SUM(AK9:AK44) -> 331.93 | AS45: =SUM(AS11:AS43) -> 5763.27 | AT45: =SUM(AT11:AT44) -> 0
B46: Nb Day | T46: =AVERAGE(T11:T26) -> 339.45875
U47: =T45*2315 -> 12573552 | V47: TZS | AS47: =AS45*2143 -> 12350688 | AT47: TZS
B48: Av. Occ | U48: =U47/2289 -> 5493.0328 | V48: USD | AS48: =AS47/2289 -> 5395.6696 | AT48: USD
C50: A & K VEHICLES | I50: MAULY VEHICLES | O50: GREEN LAND VEHICLES | U50: OTHERS VEHICLES
C51: Date | D51: Vehicles | E51: Liters | F51: Driver name | G51: Authority manager | I51: Date | J51: Vehicles | K51: Liters | L51: Driver name | M51: Authority manager | O51: Date | P51: Vehicles | Q51: Liters | R51: Driver name | S51: Authorized Manager | U51: Date | V51: Vehicles | W51: Liters | X51: Driver name | Y51: Athorized Manager | Z51: Reasons

Sheet Energy Graph
A1: Date | B1: Usage KW | C1: Occ % | D1: Cost per room Total Occ | E1: Cost per room Guest Occ
A2: =Gen!B11 -> 44044 | B2: =SUM('[1]Summery Report'!F5) -> 5669 | C2: =SUM('[1]Summery Report'!C5) -> 0.623 | D2: =SUM('[1]Summery Report'!#REF!) -> #REF! | E2: =SUM('[1]Summery Report'!#REF!) -> #REF! | F2: 0.1
A3: =Gen!B12 -> 44045 | B3: =SUM('[1]Summery Report'!F6) -> 6159 | C3: =SUM('[1]Summery Report'!C6) -> 0.779 | D3: =SUM('[1]Summery Report'!#REF!) -> #REF! | E3: =SUM('[1]Summery Report'!#REF!) -> #REF! | F3: 0.1375
A4: =Gen!B13 -> 44046 | B4: =SUM('[1]Summery Report'!F7) -> 6580 | C4: =SUM('[1]Summery Report'!C7) -> 0.532 | D4: =SUM('[1]Summery Report'!#REF!) -> #REF! | E4: =SUM('[1]Summery Report'!#REF!) -> #REF! | F4: 0.0875
A5: =Gen!B14 -> 44047 | B5: =SUM('[1]Summery Report'!F8) -> 6223 | C5: =SUM('[1]Summery Report'!C8) -> 0.61 | D5: =SUM('[1]Summery Report'!#REF!) -> #REF! | E5: =SUM('[1]Summery Report'!#REF!) -> #REF! | F5: 0.225
A6: =Gen!B15 -> 44048 | B6: =SUM('[1]Summery Report'!F9) -> 5984 | C6: =SUM('[1]Summery Report'!C9) -> 0.688 | D6: =SUM('[1]Summery Report'!#REF!) -> #REF! | E6: =SUM('[1]Summery Report'!#REF!) -> #REF! | F6: 0.2
A7: =Gen!B16 -> 44049 | B7: =SUM('[1]Summery Report'!F10) -> 6103 | C7: =SUM('[1]Summery Report'!C10) -> 0.532 | D7: =SUM('[1]Summery Report'!#REF!) -> #REF! | E7: =SUM('[1]Summery Report'!#REF!) -> #REF! | F7: 0.35
A8: =Gen!B17 -> 44050 | B8: =SUM('[1]Summery Report'!F11) -> 5576 | C8: =SUM('[1]Summery Report'!C11) -> 0.753 | D8: =SUM('[1]Summery Report'!#REF!) -> #REF! | E8: =SUM('[1]Summery Report'!#REF!) -> #REF! | F8: 0.375
A9: =Gen!B18 -> 44051 | B9: =SUM('[1]Summery Report'!F12) -> 5532 | C9: =SUM('[1]Summery Report'!C12) -> 0.156 | D9: =SUM('[1]Summery Report'!#REF!) -> #REF! | E9: =SUM('[1]Summery Report'!#REF!) -> #REF! | F9: 0.325
A10: =Gen!B19 -> 44052 | B10: =SUM('[1]Summery Report'!F13) -> 6233 | C10: =SUM('[1]Summery Report'!C13) -> 0.442 | D10: =SUM('[1]Summery Report'!#REF!) -> #REF! | E10: =SUM('[1]Summery Report'!#REF!) -> #REF! | F10: 0.75
A11: =Gen!B20 -> 44053 | B11: =SUM('[1]Summery Report'!F14) -> 6063 | C11: =SUM('[1]Summery Report'!C14) -> 0.325 | D11: =SUM('[1]Summery Report'!#REF!) -> #REF! | E11: =SUM('[1]Summery Report'!#REF!) -> #REF! | F11: 0.7625
A12: =Gen!B21 -> 44054 | B12: =SUM('[1]Summery Report'!F15) -> 5967 | C12: =SUM('[1]Summery Report'!C15) -> 0.455 | D12: =SUM('[1]Summery Report'!#REF!) -> #REF! | E12: =SUM('[1]Summery Report'!#REF!) -> #REF! | F12: 0.1625
A13: =Gen!B22 -> 44055 | B13: =SUM('[1]Summery Report'!F16) -> 5863 | C13: =SUM('[1]Summery Report'!C16) -> 0.416 | D13: =SUM('[1]Summery Report'!#REF!) -> #REF! | E13: =SUM('[1]Summery Report'!#REF!) -> #REF! | F13: 0.1125
... A32: =Gen!B41 -> 44074 | B32: =SUM('[1]Summery Report'!F35) -> 0 | C32: =SUM('[1]Summery Report'!C35) -> 0 | D32: =SUM('[1]Summery Report'!#REF!) -> #REF! | E32: =SUM('[1]Summery Report'!#REF!) -> #REF! | F32: 0.175
A33: =Gen!B42 -> 0 | B33: =[1]Gen!S41 -> 0

Sheet Lpg (2)
C3: Four Sasons Safari Lodge Serengeti
G6: VALUE | H6: Cost
A7: DATE | B7: A | C7: B | D7: C | F7: Meter Reading | G7: Total | H7: Occu | I7: No.of | J7: Kg
B8: 2Ton% | C8: 1Ton (%) | D8: 1Ton% | F8: consumption | G8: Consumption Kg | H8: % | I8: pax | J8: per pax
A10: =Gen!B11 -> 44044 | B10: 85 | C10: 85 | D10: 85 | F10: 71789.35 | G10: =(F10-F9)*4.4 -> 315873.14 | H10: =Gen!C11 -> 0 | I10: =SUM(F10/H10) -> #DIV/0! | J10: =SUM(G10/I10) -> #DIV/0!
A11: =Gen!B12 -> 44045 | B11: 85 | C11: 85 | D11: 85 | F11: 71795.21 | G11: =(F11-F10)*4.4 -> 25.784 | H11: =Gen!C12 -> 0 | I11: =SUM(F11/H11) -> #DIV/0! | J11: =SUM(G11/I11) -> #DIV/0!
A12: =Gen!B13 -> 44046 | B12: 85 | C12: 85 | D12: 84 | F12: 71810.13 | G12: =(F12-F11)*4.4 -> 65.648 | H12: =Gen!C13 -> 0 | I12: =SUM(F12/H12) -> #DIV/0! | J12: =SUM(G12/I12) -> #DIV/0!
A13: =Gen!B14 -> 44047 | B13: 85 | C13: 85 | D13: 84 | F13: 71815.29 | G13: =(F13-F12)*4.4 -> 22.704 | H13: =Gen!C14 -> 0 | I13: =SUM(F13/H13) -> #DIV/0! | J13: =SUM(G13/I13) -> #DIV/0!
A14: =Gen!B15 -> 44048 | B14: 85 | C14: 85 | D14: 84 | F14: 71822.39 | G14: =(F14-F13)*4.4 -> 31.24 | H14: =Gen!C15 -> 0 | I14: =SUM(F14/H14) -> #DIV/0! | J14: =SUM(G14/I14) -> #DIV/0!
A15: =Gen!B16 -> 44049 | B15: 85 | C15: 85 | D15: 83 | F15: 71824.31 | G15: =(F15-F14)*4.4 -> 8.448 | H15: =Gen!C16 -> 0 | I15: =SUM(F15/H15) -> #DIV/0! | J15: =SUM(G15/I15) -> #DIV/0!
A16: =Gen!B17 -> 44050 | B16: 85 | C16: 85 | G16: =(F16-F15)*4.4 -> -316026.96 | H16: =Gen!C17 -> 0 | I16: =SUM(F16/H16) -> #DIV/0! | J16: =SUM(G16/I16) -> #DIV/0!
A17: =Gen!B18 -> 44051 | G17: =(F17-F16)*4.4 -> 0 | H17: =Gen!C18 -> 0 | I17: =SUM(F17/H17) -> #DIV/0! | J17: =SUM(G17/I17) -> #DIV/0!
A18: =Gen!B19 -> 44052 | G18: =(F18-F17)*4.4 -> 0 | H18: =Gen!C19 -> 0 | I18: =SUM(F18/H18) -> #DIV/0! | J18: =SUM(G18/I18) -> #DIV/0!
A19: =Gen!B20 -> 44053 | G19: =(F19-F18)*4.4 -> 0 | H19: =Gen!C20 -> 0 | I19: =SUM(F19/H19) -> #DIV/0! | J19: =SUM(G19/I19) -> #DIV/0!
A20: =Gen!B21 -> 44054 | G20: =(F20-F19)*4.4 -> 0 | H20: =Gen!C21 -> 0 | I20: =SUM(F20/H20) -> #DIV/0! | J20: =SUM(G20/I20) -> #DIV/0!
A21: =Gen!B22 -> 44055 | G21: =(F21-F20)*4.4 -> 0 | H21: =Gen!C22 -> 0 | I21: =SUM(F21/H21) -> #DIV/0! | J21: =SUM(G21/I21) -> #DIV/0!
A22: =Gen!B23 -> 44056 | G22: =(F22-F21)*4.4 -> 0 | H22: =Gen!C23 -> 0 | I22: =SUM(F22/H22) -> #DIV/0! | J22: =SUM(G22/I22) -> #DIV/0!
A23: =Gen!B24 -> 44057 | G23: =(F23-F22)*4.4 -> 0 | H23: =Gen!C24 -> 0 | I23: =SUM(F23/H23) -> #DIV/0! | J23: =SUM(G23/I23) -> #DIV/0!
A24: =Gen!B25 -> 44058 | G24: =(F24-F23)*4.4 -> 0 | H24: =Gen!C25 -> 0 | I24: =SUM(F24/H24) -> #DIV/0! | J24: =SUM(G24/I24) -> #DIV/0!
A25: =Gen!B26 -> 44059 | G25: =(F25-F24)*4.4 -> 0 | H25: =Gen!C26 -> 0 | I25: =SUM(F25/H25) -> #DIV/0! | J25: =SUM(G25/I25) -> #DIV/0!
A26: =Gen!B27 -> 44060 | G26: =(F26-F25)*4.4 -> 0 | H26: =Gen!C27 -> 0 | I26: =SUM(F26/H26) -> #DIV/0! | J26: =SUM(G26/I26) -> #DIV/0!
A27: =Gen!B28 -> 44061 | G27: =(F27-F26)*4.4 -> 0 | H27: =Gen!C28 -> 0 | I27: =SUM(F27/H27) -> #DIV/0! | J27: =SUM(G27/I27) -> #DIV/0!
A28: =Gen!B29 -> 44062 | G28: =(F28-F27)*4.4 -> 0 | H28: =Gen!C29 -> 0 | I28: =SUM(F28/H28) -> #DIV/0! | J28: =SUM(G28/I28) -> #DIV/0!
... A40: =Gen!B41 -> 44074 | G40: =(F40-F39)*4.4 -> 0 | H40: =Gen!C41 -> 0 | I40: =SUM(F40/H40) -> #DIV/0! | J40: =SUM(G40/I40) -> #DIV/0!
A41: =Gen!B42 -> 0 | H41: =Gen!C42 -> 0 | I41: =SUM(F41/H41) -> #DIV/0!
C42: TOTAL USAGE | E42: =SUM(E10:E40) -> 0 | F42: =SUM(F10:F40) -> 430856.68 | G42: =SUM(G10:G40) -> 0
F45: =E12-E11 -> 0 | G45: =F45*4.4 -> 0

Sheet LPG_Graph
A1: Date | B1: Usage KG | C1: Occ %
A2: =Gen!B11 -> 44044 | B2: ='[1]Lpg (2)'!G10 -> 197.56 | C2: =SUM([1]Gen!B11) -> 0.623
A3: =Gen!B12 -> 44045 | B3: ='[1]Lpg (2)'!G11 -> 131.956 | C3: =SUM([1]Gen!B12) -> 0.779
A4: =Gen!B13 -> 44046 | B4: ='[1]Lpg (2)'!G12 -> 117.48 | C4: =SUM([1]Gen!B13) -> 0.532
A5: =Gen!B14 -> 44047 | B5: ='[1]Lpg (2)'!G13 -> 102.96 | C5: =SUM([1]Gen!B14) -> 0.61
A6: =Gen!B15 -> 44048 | B6: ='[1]Lpg (2)'!G14 -> 101.816 | C6: =SUM([1]Gen!B15) -> 0.688
A7: =Gen!B16 -> 44049 | B7: ='[1]Lpg (2)'!G15 -> 106.92 | C7: =SUM([1]Gen!B16) -> 0.532
A8: =Gen!B17 -> 44050 | B8: ='[1]Lpg (2)'!G16 -> 116.732 | C8: =SUM([1]Gen!B17) -> 0.753
A9: =Gen!B18 -> 44051 | B9: ='[1]Lpg (2)'!G17 -> 105.732 | C9: =SUM([1]Gen!B18) -> 0.156
A10: =Gen!B19 -> 44052 | B10: ='[1]Lpg (2)'!G18 -> 114.4 | C10: =SUM([1]Gen!B19) -> 0.442
A11: =Gen!B20 -> 44053 | B11: ='[1]Lpg (2)'!G19 -> 102.08 | C11: =SUM([1]Gen!B20) -> 0.325
A12: =Gen!B21 -> 44054 | B12: ='[1]Lpg (2)'!G20 -> 105.292 | C12: =SUM([1]Gen!B21) -> 0.455
A13: =Gen!B22 -> 44055 | B13: ='[1]Lpg (2)'!G21 -> 114.664 | C13: =SUM([1]Gen!B22) -> 0.416
... A32: =Gen!B41 -> 44074 | B32: ='[1]Lpg (2)'!G40 -> 0 | C32: =SUM([1]Gen!B41) -> #REF!

Sheet Water-Meter
A1: Four Seasons Safari Lodge Serengeti - Water Report
C2: Main Meter | F2: KITCHEN | I2: Amani café | L2: Main SW POOL | O2: Laundry | S2: BORE HOLE NO.1 METER READING | V2: BORE HOLE NO.2 METER READING | Y2: BORE HOLE NO.3 METER READING | AB2: BORE HOLE NO.4 METER READING | AE2: BORE HOLE NO.5 METER READING | AH2: BORE HOLE NO.6 METER READING | AK2: RAIN WATER - METER READING | AN2: TOTAL WATER PRODUCTION
A3: DATE | C3: Open Bal | D3: Final | E3: consumption | F3: Open Bal | G3: Final | H3: consumption | I3: Open Bal | J3: Final | K3: consumption | L3: Open Bal | M3: Final | N3: consumption | O3: Open Bal | P3: Final | Q3: consumption | R3: Total consumption
S4: OPEN | T4: FINAL | U4: PROD. | V4: OPEN | W4: FINAL | X4: PROD. | Y4: OPEN | Z4: FINAL | AA4: PROD. | AB4: OPEN | AC4: FINAL | AD4: M3 | AE4: OPEN | AF4: FINAL | AG4: M3 | AH4: OPEN | AI4: FINAL | AJ4: M3 | AK4: OPEN | AL4: FINAL | AM4: M3
C5: =D4 -> 0 | D5: 238256 | E5: =IF((D5-D4)<0,"0",(D5-D4)) -> 238256 | F5: =G4 -> 0 | G5: ='[5]Water-Meter'!$G$35 -> 38000 | H5: =IF((G5-G4)<0,"0",(G5-G4)) -> 38000 | I5: =J4 -> 0 | J5: 7991 | K5: =IF((J5-J4)<0,"0",(J5-J4)) -> 7991 | L5: =M4 -> 0 | M5: ='[5]Water-Meter'!$M$35 -> 12366 | N5: =IF((M5-M4)<0,"0",(M5-M4)) -> 12366 | O5: =P4 -> 0 | P5: 20202 | Q5: =IF((P5-P4)<0,"0",(P5-P4)) -> 20202 | T5: 55859 | V5: =W4 -> FINAL | W5: 73030 | Y5: =Z4 -> FINAL | Z5: 82254 | AB5: =AC4 -> FINAL | AC5: 14567 | AE5: =AF4 -> FINAL | AF5: ='[5]Water-Meter'!$AF$35 -> 18300 | AH5: =AI4 -> FINAL | AI5: 25240 | AK5: =AL4 -> FINAL
A6: =Gen!B11 -> 44044 | C6: =D5 -> 238256 | D6: 238307 | E6: =IF((D6-D5)<0,"0",(D6-D5)) -> 51 | F6: =G5 -> 38000 | G6: ='[5]Water-Meter'!$G$35 -> 38000 | H6: =IF((G6-G5)<0,"0",(G6-G5)) -> 0 | I6: =J5 -> 7991 | J6: 7992 | K6: =J6-J5 -> 1 | L6: =M5 -> 12366 | M6: ='[5]Water-Meter'!$M$35 -> 12366 | N6: =IF((M6-M5)<0,"0",(M6-M5)) -> 0 | O6: =P5 -> 20202 | P6: 20203 | Q6: =IF((P6-P5)<0,"0",(P6-P5)) -> 1 | S6: =T5 -> 55859 | T6: 55939 | U6: =IF((T6-T5)<0,"0",(T6-T5)) -> 80 | V6: =W5 -> 73030 | W6: 73030 | X6: =IF((W6-W5)<0,"0",(W6-W5)) -> 0 | Y6: =Z5 -> 82254 | Z6: 82289 | AA6: =IF((Z6-Z5)<0,"0",(Z6-Z5)) -> 35 | AB6: =AC5 -> 14567 | AC6: 14579 | AD6: =AC6-AB6 -> 12 | AE6: =AF5 -> 18300 | AF6: ='[5]Water-Meter'!$AF$35 -> 18300 | AG6: =IF((AF6-AF5)<0,"0",(AF6-AF5)) -> 0 | AH6: =AI5 -> 25240 | AI6: 25283 | AJ6: =IF((AI6-AI5)<0,"0",(AI6-AI5)) -> 43 | AK6: =AL5 -> 0 | AM6: =IF((AL6-AL5)<0,"0",(AL6-AL5)) -> 0 | AN6: =U6+X6+AA6+AD6+AG6+AJ6+AM6 -> 170
A7: =Gen!B12 -> 44045 | C7: =D6 -> 238307 | D7: 238360 | E7: =IF((D7-D6)<0,"0",(D7-D6)) -> 53 | F7: =G6 -> 38000 | G7: ='[5]Water-Meter'!$G$35 -> 38000 | H7: =IF((G7-G6)<0,"0",(G7-G6)) -> 0 | I7: =J6 -> 7992 | J7: 7993 | K7: =J7-J6 -> 1 | L7: =M6 -> 12366 | M7: ='[5]Water-Meter'!$M$35 -> 12366 | N7: =IF((M7-M6)<0,"0",(M7-M6)) -> 0 | O7: =P6 -> 20203 | P7: 20204 | Q7: =IF((P7-P6)<0,"0",(P7-P6)) -> 1 | S7: =T6 -> 55939 | T7: 56036 | U7: =IF((T7-T6)<0,"0",(T7-T6)) -> 97 | V7: =W6 -> 73030 | W7: 73030 | X7: =IF((W7-W6)<0,"0",(W7-W6)) -> 0 | Y7: =Z6 -> 82289 | Z7: 82327 | AA7: =IF((Z7-Z6)<0,"0",(Z7-Z6)) -> 38 | AB7: =AC6 -> 14579 | AC7: 14596 | AD7: =AC7-AB7 -> 17 | AE7: =AF6 -> 18300 | AF7: ='[5]Water-Meter'!$AF$35 -> 18300 | AG7: =IF((AF7-AF6)<0,"0",(AF7-AF6)) -> 0 | AH7: =AI6 -> 25283 | AI7: 25316 | AJ7: =IF((AI7-AI6)<0,"0",(AI7-AI6)) -> 33 | AK7: =AL6 -> 0 | AM7: =IF((AL7-AL6)<0,"0",(AL7-AL6)) -> 0 | AN7: =U7+X7+AA7+AD7+AG7+AJ7+AM7 -> 185
A8: =Gen!B13 -> 44046 | C8: =D7 -> 238360 | D8: 238402 | E8: =IF((D8-D7)<0,"0",(D8-D7)) -> 42 | F8: =G7 -> 38000 | G8: ='[5]Water-Meter'!$G$35 -> 38000 | H8: =IF((G8-G7)<0,"0",(G8-G7)) -> 0 | I8: =J7 -> 7993 | J8: 7994 | K8: =J8-J7 -> 1 | L8: =M7 -> 12366 | M8: ='[5]Water-Meter'!$M$35 -> 12366 | N8: =IF((M8-M7)<0,"0",(M8-M7)) -> 0 | O8: =P7 -> 20204 | P8: 20205 | Q8: =IF((P8-P7)<0,"0",(P8-P7)) -> 1 | S8: =T7 -> 56036 | T8: 56119 | U8: =IF((T8-T7)<0,"0",(T8-T7)) -> 83 | V8: =W7 -> 73030 | W8: 73030 | X8: =IF((W8-W7)<0,"0",(W8-W7)) -> 0 | Y8: =Z7 -> 82327 | Z8: 82367 | AA8: =IF((Z8-Z7)<0,"0",(Z8-Z7)) -> 40 | AB8: =AC7 -> 14596 | AC8: 14616 | AD8: =AC8-AB8 -> 20 | AE8: =AF7 -> 18300 | AF8: ='[5]Water-Meter'!$AF$35 -> 18300 | AG8: =IF((AF8-AF7)<0,"0",(AF8-AF7)) -> 0 | AH8: =AI7 -> 25316 | AI8: 25328 | AJ8: =IF((AI8-AI7)<0,"0",(AI8-AI7)) -> 12 | AK8: =AL7 -> 0 | AM8: =IF((AL8-AL7)<0,"0",(AL8-AL7)) -> 0 | AN8: =U8+X8+AA8+AD8+AG8+AJ8+AM8 -> 155
A9: =Gen!B14 -> 44047 | C9: =D8 -> 238402 | D9: 238469 | E9: =IF((D9-D8)<0,"0",(D9-D8)) -> 67 | F9: =G8 -> 38000 | G9: ='[5]Water-Meter'!$G$35 -> 38000 | H9: =IF((G9-G8)<0,"0",(G9-G8)) -> 0 | I9: =J8 -> 7994 | J9: 7994 | K9: =J9-J8 -> 0 | L9: =M8 -> 12366 | M9: ='[5]Water-Meter'!$M$35 -> 12366 | N9: =IF((M9-M8)<0,"0",(M9-M8)) -> 0 | O9: =P8 -> 20205 | P9: 20206 | Q9: =IF((P9-P8)<0,"0",(P9-P8)) -> 1 | S9: =T8 -> 56119 | T9: 56206 | U9: =IF((T9-T8)<0,"0",(T9-T8)) -> 87 | V9: =W8 -> 73030 | W9: 73030 | X9: =IF((W9-W8)<0,"0",(W9-W8)) -> 0 | Y9: =Z8 -> 82367 | Z9: 82404 | AA9: =IF((Z9-Z8)<0,"0",(Z9-Z8)) -> 37 | AB9: =AC8 -> 14616 | AC9: 14632 | AD9: =AC9-AB9 -> 16 | AE9: =AF8 -> 18300 | AF9: ='[5]Water-Meter'!$AF$35 -> 18300 | AG9: =IF((AF9-AF8)<0,"0",(AF9-AF8)) -> 0 | AH9: =AI9 -> 25330 | AI9: 25330 | AJ9: =IF((AI9-AI8)<0,"0",(AI9-AI8)) -> 2 | AK9: =AL8 -> 0 | AM9: =IF((AL9-AL8)<0,"0",(AL9-AL8)) -> 0 | AN9: =U9+X9+AA9+AD9+AG9+AJ9+AM9 -> 142
A10: =Gen!B15 -> 44048 | C10: =D9 -> 238469 | D10: 238518 | E10: =IF((D10-D9)<0,"0",(D10-D9)) -> 49 | F10: =G9 -> 38000 | G10: ='[5]Water-Meter'!$G$35 -> 38000 | H10: =IF((G10-G9)<0,"0",(G10-G9)) -> 0 | I10: =J9 -> 7994 | J10: 7995 | K10: =IF((J10-J9)<0,"0",(J10-J9)) -> 1 | L10: =M9 -> 12366 | M10: ='[5]Water-Meter'!$M$35 -> 12366 | N10: =IF((M10-M9)<0,"0",(M10-M9)) -> 0 | O10: =P9 -> 20206 | P10: 20207 | Q10: =IF((P10-P9)<0,"0",(P10-P9)) -> 1 | S10: =T9 -> 56206 | T10: 56295 | U10: =IF((T10-T9)<0,"0",(T10-T9)) -> 89 | V10: =W9 -> 73030 | W10: 73030 | X10: =IF((W10-W9)<0,"0",(W10-W9)) -> 0 | Y10: =Z9 -> 82404 | Z10: 82442 | AA10: =IF((Z10-Z9)<0,"0",(Z10-Z9)) -> 38 | AB10: =AC9 -> 14632 | AC10: 14648 | AD10: =AC10-AB10 -> 16 | AE10: =AF9 -> 18300 | AF10: ='[5]Water-Meter'!$AF$35 -> 18300 | AG10: =IF((AF11-AF9)<0,"0",(AF11-AF9)) -> 0 | AH10: =AI9 -> 25330 | AI10: 25330 | AJ10: =IF((AI10-AI9)<0,"0",(AI10-AI9)) -> 0 | AK10: =AL9 -> 0 | AM10: =IF((AL10-AL9)<0,"0",(AL10-AL9)) -> 0 | AN10: =U10+X10+AA10+AD10+AG10+AJ10+AM10 -> 143
A11: =Gen!B16 -> 44049 | C11: =D10 -> 238518 | D11: 238584 | E11: =IF((D11-D10)<0,"0",(D11-D10)) -> 66 | F11: =G10 -> 38000 | G11: ='[5]Water-Meter'!$G$35 -> 38000 | H11: =IF((G11-G10)<0,"0",(G11-G10)) -> 0 | I11: =J10 -> 7995 | J11: 7996 | K11: =IF((J11-J10)<0,"0",(J11-J10)) -> 1 | L11: =M10 -> 12366 | M11: ='[5]Water-Meter'!$M$35 -> 12366 | N11: =IF((M11-M10)<0,"0",(M11-M10)) -> 0 | O11: =P10 -> 20207 | P11: 20210 | Q11: =IF((P11-P10)<0,"0",(P11-P10)) -> 3 | S11: =T10 -> 56295 | T11: 56382 | U11: =IF((T11-T10)<0,"0",(T11-T10)) -> 87 | V11: =W10 -> 73030 | W11: 73030 | X11: =IF((W11-W10)<0,"0",(W11-W10)) -> 0 | Y11: =Z10 -> 82442 | Z11: 82479 | AA11: =IF((Z11-Z10)<0,"0",(Z11-Z10)) -> 37 | AB11: =AC10 -> 14648 | AC11: 14664 | AD11: =AC11-AB11 -> 16 | AE11: =AF11 -> 18300 | AF11: ='[5]Water-Meter'!$AF$35 -> 18300 | AG11: =IF((AF12-AF10)<0,"0",(AF12-AF10)) -> 0 | AH11: =AI10 -> 25330 | AI11: 25335 | AJ11: =IF((AI11-AI10)<0,"0",(AI11-AI10)) -> 5 | AK11: =AL10 -> 0 | AM11: =IF((AL11-AL10)<0,"0",(AL11-AL10)) -> 0 | AN11: =U11+X11+AA11+AD11+AG11+AJ11+AM11 -> 145
A12: =Gen!B17 -> 44050 | C12: =D11 -> 238584 | D12: 238635 | E12: =IF((D12-D11)<0,"0",(D12-D11)) -> 51 | F12: =G11 -> 38000 | G12: ='[5]Water-Meter'!$G$35 -> 38000 | H12: =IF((G12-G11)<0,"0",(G12-G11)) -> 0 | I12: =J11 -> 7996 | J12: 7997 | K12: =IF((J12-J11)<0,"0",(J12-J11)) -> 1 | L12: =M11 -> 12366 | M12: ='[5]Water-Meter'!$M$35 -> 12366 | N12: =IF((M12-M11)<0,"0",(M12-M11)) -> 0 | O12: =P11 -> 20210 | P12: 20211 | Q12: =IF((P12-P11)<0,"0",(P12-P11)) -> 1 | S12: =T11 -> 56382 | T12: 56469 | U12: =IF((T12-T11)<0,"0",(T12-T11)) -> 87 | V12: =W11 -> 73030 | W12: 73030 | X12: =IF((W12-W11)<0,"0",(W12-W11)) -> 0 | Y12: =Z11 -> 82479 | Z12: 82517 | AA12: =IF((Z12-Z11)<0,"0",(Z12-Z11)) -> 38 | AB12: =AC11 -> 14664 | AC12: 14679 | AD12: =AC12-AB12 -> 15 | AE12: =AF12 -> 18300 | AF12: ='[5]Water-Meter'!$AF$35 -> 18300 | AG12: =IF((AF13-AF11)<0,"0",(AF13-AF11)) -> 0 | AH12: =AI11 -> 25335 | AI12: 25335 | AJ12: =IF((AI12-AI11)<0,"0",(AI12-AI11)) -> 0 | AK12: =AL11 -> 0 | AM12: =IF((AL12-AL11)<0,"0",(AL12-AL11)) -> 0 | AN12: =U12+X12+AA12+AD12+AG12+AJ12+AM12 -> 140
A13: =Gen!B18 -> 44051 | C13: =D12 -> 238635 | E13: =IF((D13-D12)<0,"0",(D13-D12)) -> 0 | F13: =G12 -> 38000 | H13: =IF((G13-G12)<0,"0",(G13-G12)) -> 0 | I13: =J12 -> 7997 | K13: =IF((J13-J12)<0,"0",(J13-J12)) -> 0 | L13: =M12 -> 12366 | N13: =IF((M13-M12)<0,"0",(M13-M12)) -> 0 | O13: =P12 -> 20211 | Q13: =IF((P13-P12)<0,"0",(P13-P12)) -> 0 | S13: =T12 -> 56469 | U13: =IF((T13-T12)<0,"0",(T13-T12)) -> 0 | V13: =W12 -> 73030 | X13: =IF((W13-W12)<0,"0",(W13-W12)) -> 0 | Y13: =Z12 -> 82517 | AA13: =IF((Z13-Z12)<0,"0",(Z13-Z12)) -> 0 | AB13: =AC12 -> 14679 | AD13: =AC13-AB13 -> -14679 | AE13: =AF13 -> 0 | AG13: =IF((AF14-AF12)<0,"0",(AF14-AF12)) -> 0 | AH13: =AI12 -> 25335 | AJ13: =IF((AI13-AI12)<0,"0",(AI13-AI12)) -> 0 | AK13: =AL12 -> 0 | AM13: =IF((AL13-AL12)<0,"0",(AL13-AL12)) -> 0 | AN13: =U13+X13+AA13+AD13+AG13+AJ13+AM13 -> -14679
A14: =Gen!B19 -> 44052 | C14: =D13 -> 0 | E14: =IF((D14-D13)<0,"0",(D14-D13)) -> 0 | F14: =G13 -> 0 | H14: =IF((G14-G13)<0,"0",(G14-G13)) -> 0 | I14: =J13 -> 0 | K14: =IF((J14-J13)<0,"0",(J14-J13)) -> 0 | L14: =M13 -> 0 | N14: =IF((M14-M13)<0,"0",(M14-M13)) -> 0 | O14: =P13 -> 0 | Q14: =IF((P14-P13)<0,"0",(P14-P13)) -> 0 | S14: =T13 -> 0 | U14: =IF((T14-T13)<0,"0",(T14-T13)) -> 0 | V14: =W13 -> 0 | X14: =IF((W14-W13)<0,"0",(W14-W13)) -> 0 | Y14: =Z13 -> 0 | AA14: =IF((Z14-Z13)<0,"0",(Z14-Z13)) -> 0 | AB14: =AC13 -> 0 | AD14: =AC14-AB14 -> 0 | AE14: =AF14 -> 0 | AG14: =IF((AF15-AF13)<0,"0",(AF15-AF13)) -> 0 | AH14: =AI13 -> 0 | AJ14: =IF((AI14-AI13)<0,"0",(AI14-AI13)) -> 0 | AK14: =AL13 -> 0 | AM14: =IF((AL14-AL13)<0,"0",(AL14-AL13)) -> 0 | AN14: =U14+X14+AA14+AD14+AG14+AJ14+AM14 -> 0
A15: =Gen!B20 -> 44053 | C15: =D14 -> 0 | E15: =IF((D15-D14)<0,"0",(D15-D14)) -> 0 | F15: =G14 -> 0 | H15: =IF((G15-G14)<0,"0",(G15-G14)) -> 0 | I15: =J14 -> 0 | K15: =IF((J15-J14)<0,"0",(J15-J14)) -> 0 | L15: =M14 -> 0 | N15: =IF((M15-M14)<0,"0",(M15-M14)) -> 0 | O15: =P14 -> 0 | Q15: =IF((P15-P14)<0,"0",(P15-P14)) -> 0 | S15: =T14 -> 0 | U15: =IF((T15-T14)<0,"0",(T15-T14)) -> 0 | V15: =W14 -> 0 | X15: =IF((W15-W14)<0,"0",(W15-W14)) -> 0 | Y15: =Z14 -> 0 | AA15: =IF((Z15-Z14)<0,"0",(Z15-Z14)) -> 0 | AB15: =AC14 -> 0 | AD15: =AC15-AB15 -> 0 | AE15: =AF15 -> 0 | AG15: =IF((AF16-AF14)<0,"0",(AF16-AF14)) -> 0 | AH15: =AI14 -> 0 | AJ15: =IF((AI15-AI14)<0,"0",(AI15-AI14)) -> 0 | AK15: =AL14 -> 0 | AM15: =IF((AL15-AL14)<0,"0",(AL15-AL14)) -> 0 | AN15: =U15+X15+AA15+AD15+AG15+AJ15+AM15 -> 0
A16: =Gen!B21 -> 44054 | C16: =D15 -> 0 | E16: =IF((D16-D15)<0,"0",(D16-D15)) -> 0 | F16: =G15 -> 0 | H16: =IF((G16-G15)<0,"0",(G16-G15)) -> 0 | I16: =J15 -> 0 | K16: =IF((J16-J15)<0,"0",(J16-J15)) -> 0 | N16: =IF((M16-M15)<0,"0",(M16-M15)) -> 0 | O16: =P15 -> 0 | Q16: =IF((P16-P15)<0,"0",(P16-P15)) -> 0 | S16: =T15 -> 0 | U16: =IF((T16-T15)<0,"0",(T16-T15)) -> 0 | V16: =W15 -> 0 | X16: =IF((W16-W15)<0,"0",(W16-W15)) -> 0 | Y16: =Z15 -> 0 | AA16: =IF((Z16-Z15)<0,"0",(Z16-Z15)) -> 0 | AB16: =AC15 -> 0 | AD16: =AC16-AB16 -> 0 | AE16: =AF16 -> 0 | AG16: =IF((AF17-AF15)<0,"0",(AF17-AF15)) -> 0 | AH16: =AI15 -> 0 | AJ16: =IF((AI16-AI15)<0,"0",(AI16-AI15)) -> 0 | AK16: =AL15 -> 0 | AM16: =IF((AL16-AL15)<0,"0",(AL16-AL15)) -> 0 | AN16: =U16+X16+AA16+AD16+AG16+AJ16+AM16 -> 0
A17: =Gen!B22 -> 44055 | C17: =D16 -> 0 | E17: =IF((D17-D16)<0,"0",(D17-D16)) -> 0 | F17: =G16 -> 0 | H17: =IF((G17-G16)<0,"0",(G17-G16)) -> 0 | I17: =J16 -> 0 | K17: =IF((J17-J16)<0,"0",(J17-J16)) -> 0 | N17: =IF((M17-M16)<0,"0",(M17-M16)) -> 0 | O17: =P16 -> 0 | Q17: =IF((P17-P16)<0,"0",(P17-P16)) -> 0 | S17: =T16 -> 0 | U17: =IF((T17-T16)<0,"0",(T17-T16)) -> 0 | V17: =W16 -> 0 | X17: =IF((W17-W16)<0,"0",(W17-W16)) -> 0 | Y17: =Z16 -> 0 | AA17: =IF((Z17-Z16)<0,"0",(Z17-Z16)) -> 0 | AB17: =AC16 -> 0 | AD17: =AC17-AB17 -> 0 | AE17: =AF17 -> 0 | AG17: =IF((AF18-AF16)<0,"0",(AF18-AF16)) -> 0 | AH17: =AI16 -> 0 | AJ17: =IF((AI17-AI16)<0,"0",(AI17-AI16)) -> 0 | AK17: =AL16 -> 0 | AM17: =IF((AL17-AL16)<0,"0",(AL17-AL16)) -> 0 | AN17: =U17+X17+AA17+AD17+AG17+AJ17+AM17 -> 0
A18: =Gen!B23 -> 44056 | C18: =D17 -> 0 | E18: =IF((D18-D17)<0,"0",(D18-D17)) -> 0 | F18: =G17 -> 0 | H18: =IF((G18-G17)<0,"0",(G18-G17)) -> 0 | K18: =IF((J18-J17)<0,"0",(J18-J17)) -> 0 | L18: =M17 -> 0 | N18: =IF((M18-M17)<0,"0",(M18-M17)) -> 0 | O18: =P17 -> 0 | Q18: =IF((P18-P17)<0,"0",(P18-P17)) -> 0 | S18: =T17 -> 0 | U18: =IF((T18-T17)<0,"0",(T18-T17)) -> 0 | V18: =W17 -> 0 | X18: =IF((W18-W17)<0,"0",(W18-W17)) -> 0 | Y18: =Z17 -> 0 | AA18: =IF((Z18-Z17)<0,"0",(Z18-Z17)) -> 0 | AB18: =AC17 -> 0 | AD18: =AC18-AB18 -> 0 | AE18: =AF18 -> 0 | AG18: =IF((AF18-AF17)<0,"0",(AF18-AF17)) -> 0 | AH18: =AI17 -> 0 | AJ18: =IF((AI18-AI17)<0,"0",(AI18-AI17)) -> 0 | AK18: =AL17 -> 0 | AM18: =IF((AL18-AL17)<0,"0",(AL18-AL17)) -> 0 | AN18: =U18+X18+AA18+AD18+AG18+AJ18+AM18 -> 0
A19: =Gen!B24 -> 44057 | C19: =D18 -> 0 | E19: =IF((D19-D18)<0,"0",(D19-D18)) -> 0 | F19: =G18 -> 0 | H19: =IF((G19-G18)<0,"0",(G19-G18)) -> 0 | I19: =J18 -> 0 | K19: =IF((J19-J18)<0,"0",(J19-J18)) -> 0 | L19: =M18 -> 0 | N19: =IF((M19-M18)<0,"0",(M19-M18)) -> 0 | O19: =P18 -> 0 | Q19: =IF((P19-P18)<0,"0",(P19-P18)) -> 0 | S19: =T18 -> 0 | U19: =IF((T19-T18)<0,"0",(T19-T18)) -> 0 | V19: =W18 -> 0 | X19: =IF((W19-W18)<0,"0",(W19-W18)) -> 0 | Y19: =Z18 -> 0 | AA19: =IF((Z19-Z18)<0,"0",(Z19-Z18)) -> 0 | AB19: =AC18 -> 0 | AD19: =AC19-AB19 -> 0 | AE19: =AF19 -> 0 | AG19: =IF((AF19-AF18)<0,"0",(AF19-AF18)) -> 0 | AH19: =AI18 -> 0 | AJ19: =IF((AI19-AI18)<0,"0",(AI19-AI18)) -> 0 | AK19: =AL18 -> 0 | AM19: =IF((AL19-AL18)<0,"0",(AL19-AL18)) -> 0 | AN19: =U19+X19+AA19+AD19+AG19+AJ19+AM19 -> 0
A20: =Gen!B25 -> 44058 | C20: =D19 -> 0 | E20: =IF((D20-D19)<0,"0",(D20-D19)) -> 0 | F20: =G19 -> 0 | H20: =IF((G20-G19)<0,"0",(G20-G19)) -> 0 | I20: =J19 -> 0 | K20: =IF((J20-J19)<0,"0",(J20-J19)) -> 0 | L20: =M19 -> 0 | N20: =IF((M20-M19)<0,"0",(M20-M19)) -> 0 | O20: =P19 -> 0 | Q20: =IF((P20-P19)<0,"0",(P20-P19)) -> 0 | S20: =T19 -> 0 | U20: =IF((T20-T19)<0,"0",(T20-T19)) -> 0 | V20: =W19 -> 0 | X20: =IF((W20-W19)<0,"0",(W20-W19)) -> 0 | Y20: =Z19 -> 0 | AA20: =IF((Z20-Z19)<0,"0",(Z20-Z19)) -> 0 | AB20: =AC19 -> 0 | AD20: =AC20-AB20 -> 0 | AE20: =AF20 -> 0 | AG20: =IF((AF20-AF19)<0,"0",(AF20-AF19)) -> 0 | AH20: =AI19 -> 0 | AJ20: =IF((AI20-AI19)<0,"0",(AI20-AI19)) -> 0 | AK20: =AL19 -> 0 | AM20: =IF((AL20-AL19)<0,"0",(AL20-AL19)) -> 0 | AN20: =U20+X20+AA20+AD20+AG20+AJ20+AM20 -> 0
A21: =Gen!B26 -> 44059 | C21: =D20 -> 0 | E21: =IF((D21-D20)<0,"0",(D21-D20)) -> 0 | F21: =G20 -> 0 | H21: =IF((G21-G20)<0,"0",(G21-G20)) -> 0 | I21: =J20 -> 0 | K21: =IF((J21-J20)<0,"0",(J21-J20)) -> 0 | L21: =M20 -> 0 | N21: =IF((M21-M20)<0,"0",(M21-M20)) -> 0 | O21: =P20 -> 0 | Q21: =IF((P21-P20)<0,"0",(P21-P20)) -> 0 | S21: =T20 -> 0 | U21: =IF((T21-T20)<0,"0",(T21-T20)) -> 0 | V21: =W20 -> 0 | X21: =IF((W21-W20)<0,"0",(W21-W20)) -> 0 | Y21: =Z20 -> 0 | AA21: =IF((Z21-Z20)<0,"0",(Z21-Z20)) -> 0 | AB21: =AC20 -> 0 | AD21: =AC21-AB21 -> 0 | AE21: =AF20 -> 0 | AG21: =IF((AF21-AF20)<0,"0",(AF21-AF20)) -> 0 | AH21: =AI20 -> 0 | AJ21: =IF((AI21-AI20)<0,"0",(AI21-AI20)) -> 0 | AK21: =AL20 -> 0 | AM21: =IF((AL21-AL20)<0,"0",(AL21-AL20)) -> 0 | AN21: =U21+X21+AA21+AD21+AG21+AJ21+AM21 -> 0
A22: =Gen!B27 -> 44060 | C22: =D21 -> 0 | E22: =IF((D22-D21)<0,"0",(D22-D21)) -> 0 | F22: =G21 -> 0 | H22: =IF((G22-G21)<0,"0",(G22-G21)) -> 0 | I22: =J21 -> 0 | K22: =IF((J22-J21)<0,"0",(J22-J21)) -> 0 | L22: =M21 -> 0 | N22: =IF((M22-M21)<0,"0",(M22-M21)) -> 0 | O22: =P21 -> 0 | Q22: =IF((P22-P21)<0,"0",(P22-P21)) -> 0 | S22: =T21 -> 0 | U22: =IF((T22-T21)<0,"0",(T22-T21)) -> 0 | V22: =W21 -> 0 | X22: =IF((W22-W21)<0,"0",(W22-W21)) -> 0 | Y22: =Z21 -> 0 | AA22: =IF((Z22-Z21)<0,"0",(Z22-Z21)) -> 0 | AB22: =AC21 -> 0 | AD22: =AC22-AB22 -> 0 | AE22: =AF21 -> 0 | AG22: =IF((AF22-AF21)<0,"0",(AF22-AF21)) -> 0 | AH22: =AI21 -> 0 | AJ22: =IF((AI22-AI21)<0,"0",(AI22-AI21)) -> 0 | AK22: =AL21 -> 0 | AM22: =IF((AL22-AL21)<0,"0",(AL22-AL21)) -> 0 | AN22: =U22+X22+AA22+AD22+AG22+AJ22+AM22 -> 0
A23: =Gen!B28 -> 44061 | C23: =D22 -> 0 | E23: =IF((D23-D22)<0,"0",(D23-D22)) -> 0 | F23: =G22 -> 0 | H23: =IF((G23-G22)<0,"0",(G23-G22)) -> 0 | I23: =J22 -> 0 | K23: =IF((J23-J22)<0,"0",(J23-J22)) -> 0 | L23: =M22 -> 0 | N23: =IF((M23-M22)<0,"0",(M23-M22)) -> 0 | O23: =P22 -> 0 | Q23: =IF((P23-P22)<0,"0",(P23-P22)) -> 0 | S23: =T22 -> 0 | U23: =IF((T23-T22)<0,"0",(T23-T22)) -> 0 | V23: =W22 -> 0 | X23: =IF((W23-W22)<0,"0",(W23-W22)) -> 0 | Y23: =Z22 -> 0 | AA23: =IF((Z23-Z22)<0,"0",(Z23-Z22)) -> 0 | AB23: =AC22 -> 0 | AD23: =AC23-AB23 -> 0 | AE23: =AF22 -> 0 | AG23: =IF((AF23-AF22)<0,"0",(AF23-AF22)) -> 0 | AH23: =AI22 -> 0 | AJ23: =IF((AI23-AI22)<0,"0",(AI23-AI22)) -> 0 | AK23: =AL22 -> 0 | AM23: =IF((AL23-AL22)<0,"0",(AL23-AL22)) -> 0 | AN23: =U23+X23+AA23+AD23+AG23+AJ23+AM23 -> 0
A24: =Gen!B29 -> 44062 | C24: =D23 -> 0 | E24: =IF((D24-D23)<0,"0",(D24-D23)) -> 0 | F24: =G23 -> 0 | H24: =IF((G24-G23)<0,"0",(G24-G23)) -> 0 | I24: =J23 -> 0 | K24: =IF((J24-J23)<0,"0",(J24-J23)) -> 0 | L24: =M23 -> 0 | N24: =IF((M24-M23)<0,"0",(M24-M23)) -> 0 | O24: =P23 -> 0 | Q24: =IF((P24-P23)<0,"0",(P24-P23)) -> 0 | S24: =T23 -> 0 | U24: =IF((T24-T23)<0,"0",(T24-T23)) -> 0 | V24: =W23 -> 0 | X24: =IF((W24-W23)<0,"0",(W24-W23)) -> 0 | Y24: =Z23 -> 0 | AA24: =IF((Z24-Z23)<0,"0",(Z24-Z23)) -> 0 | AB24: =AC23 -> 0 | AD24: =AC24-AB24 -> 0 | AE24: =AF23 -> 0 | AG24: =IF((AF24-AF23)<0,"0",(AF24-AF23)) -> 0 | AH24: =AI23 -> 0 | AJ24: =IF((AI24-AI23)<0,"0",(AI24-AI23)) -> 0 | AK24: =AL23 -> 0 | AM24: =IF((AL24-AL23)<0,"0",(AL24-AL23)) -> 0 | AN24: =U24+X24+AA24+AD24+AG24+AJ24+AM24 -> 0
A25: =Gen!B30 -> 44063 | C25: =D24 -> 0 | E25: =IF((D25-D24)<0,"0",(D25-D24)) -> 0 | F25: =G24 -> 0 | H25: =IF((G26-G24)<0,"0",(G26-G24)) -> 0 | I25: =J24 -> 0 | K25: =IF((J25-J24)<0,"0",(J25-J24)) -> 0 | L25: =M24 -> 0 | N25: =IF((M25-M24)<0,"0",(M25-M24)) -> 0 | O25: =P24 -> 0 | Q25: =IF((P25-P24)<0,"0",(P25-P24)) -> 0 | S25: =T24 -> 0 | U25: =IF((T25-T24)<0,"0",(T25-T24)) -> 0 | V25: =W24 -> 0 | X25: =IF((W25-W24)<0,"0",(W25-W24)) -> 0 | Y25: =Z24 -> 0 | AA25: =IF((Z25-Z24)<0,"0",(Z25-Z24)) -> 0 | AB25: =AC24 -> 0 | AD25: =AC25-AB25 -> 0 | AE25: =AF24 -> 0 | AG25: =IF((AF25-AF24)<0,"0",(AF25-AF24)) -> 0 | AH25: =AI24 -> 0 | AJ25: =IF((AI25-AI24)<0,"0",(AI25-AI24)) -> 0 | AK25: =AL24 -> 0 | AM25: =IF((AL25-AL24)<0,"0",(AL25-AL24)) -> 0 | AN25: =U25+X25+AA25+AD25+AG25+AJ25+AM25 -> 0
A26: =Gen!B31 -> 44064 | C26: =D25 -> 0 | E26: =IF((D26-D25)<0,"0",(D26-D25)) -> 0 | F26: =G26 -> 0 | H26: =IF((G27-G25)<0,"0",(G27-G25)) -> 0 | I26: =J25 -> 0 | K26: =IF((J26-J25)<0,"0",(J26-J25)) -> 0 | L26: =M25 -> 0 | N26: =IF((M26-M25)<0,"0",(M26-M25)) -> 0 | O26: =P25 -> 0 | Q26: =IF((P26-P25)<0,"0",(P26-P25)) -> 0 | S26: =T25 -> 0 | U26: =IF((T26-T25)<0,"0",(T26-T25)) -> 0 | V26: =W25 -> 0 | X26: =IF((W26-W25)<0,"0",(W26-W25)) -> 0 | Y26: =Z25 -> 0 | AA26: =IF((Z26-Z25)<0,"0",(Z26-Z25)) -> 0 | AB26: =AC25 -> 0 | AD26: =AC26-AB26 -> 0 | AE26: =AF25 -> 0 | AG26: =IF((AF26-AF25)<0,"0",(AF26-AF25)) -> 0 | AH26: =AI25 -> 0 | AJ26: =IF((AI26-AI25)<0,"0",(AI26-AI25)) -> 0 | AK26: =AL25 -> 0 | AM26: =IF((AL26-AL25)<0,"0",(AL26-AL25)) -> 0 | AN26: =U26+X26+AA26+AD26+AG26+AJ26+AM26 -> 0
A27: =Gen!B32 -> 44065 | C27: =D26 -> 0 | E27: =IF((D27-D26)<0,"0",(D27-D26)) -> 0 | F27: =G27 -> 0 | H27: =IF((G28-G26)<0,"0",(G28-G26)) -> 0 | I27: =J26 -> 0 | K27: =IF((J27-J26)<0,"0",(J27-J26)) -> 0 | L27: =M26 -> 0 | N27: =IF((M27-M26)<0,"0",(M27-M26)) -> 0 | O27: =P26 -> 0 | Q27: =IF((P27-P26)<0,"0",(P27-P26)) -> 0 | S27: =T26 -> 0 | U27: =IF((T27-T26)<0,"0",(T27-T26)) -> 0 | V27: =W26 -> 0 | X27: =IF((W27-W26)<0,"0",(W27-W26)) -> 0 | Y27: =Z26 -> 0 | AA27: =IF((Z27-Z26)<0,"0",(Z27-Z26)) -> 0 | AB27: =AC26 -> 0 | AD27: =AC27-AB27 -> 0 | AE27: =AF26 -> 0 | AG27: =IF((AF27-AF26)<0,"0",(AF27-AF26)) -> 0 | AH27: =AI26 -> 0 | AJ27: =IF((AI27-AI26)<0,"0",(AI27-AI26)) -> 0 | AK27: =AL26 -> 0 | AM27: =IF((AL27-AL26)<0,"0",(AL27-AL26)) -> 0 | AN27: =U27+X27+AA27+AD27+AG27+AJ27+AM27 -> 0
A28: =Gen!B33 -> 44066 | C28: =D27 -> 0 | E28: =IF((D28-D27)<0,"0",(D28-D27)) -> 0 | F28: =G28 -> 0 | H28: =IF((G28-G27)<0,"0",(G28-G27)) -> 0 | I28: =J27 -> 0 | K28: =IF((J28-J27)<0,"0",(J28-J27)) -> 0 | L28: =M27 -> 0 | N28: =IF((M28-M27)<0,"0",(M28-M27)) -> 0 | O28: =P27 -> 0 | Q28: =IF((P28-P27)<0,"0",(P28-P27)) -> 0 | S28: =T27 -> 0 | U28: =IF((T28-T27)<0,"0",(T28-T27)) -> 0 | V28: =W27 -> 0 | X28: =IF((W28-W27)<0,"0",(W28-W27)) -> 0 | Y28: =Z27 -> 0 | AA28: =IF((Z28-Z27)<0,"0",(Z28-Z27)) -> 0 | AB28: =AC27 -> 0 | AD28: =AC28-AB28 -> 0 | AE28: =AF27 -> 0 | AG28: =IF((AF28-AF27)<0,"0",(AF28-AF27)) -> 0 | AH28: =AI27 -> 0 | AJ28: =IF((AI28-AI27)<0,"0",(AI28-AI27)) -> 0 | AK28: =AL27 -> 0 | AM28: =IF((AL28-AL27)<0,"0",(AL28-AL27)) -> 0 | AN28: =U28+X28+AA28+AD28+AG28+AJ28+AM28 -> 0
A29: =Gen!B34 -> 44067 | C29: =D28 -> 0 | E29: =IF((D29-D28)<0,"0",(D29-D28)) -> 0 | F29: =G29 -> 0 | H29: =IF((G29-G28)<0,"0",(G29-G28)) -> 0 | I29: =J28 -> 0 | K29: =IF((J29-J28)<0,"0",(J29-J28)) -> 0 | L29: =M28 -> 0 | N29: =IF((M29-M28)<0,"0",(M29-M28)) -> 0 | O29: =P28 -> 0 | Q29: =IF((P29-P28)<0,"0",(P29-P28)) -> 0 | S29: =T28 -> 0 | U29: =IF((T29-T28)<0,"0",(T29-T28)) -> 0 | V29: =W28 -> 0 | X29: =IF((W29-W28)<0,"0",(W29-W28)) -> 0 | Y29: =Z28 -> 0 | AA29: =IF((Z29-Z28)<0,"0",(Z29-Z28)) -> 0 | AB29: =AC28 -> 0 | AD29: =AC29-AB29 -> 0 | AE29: =AF28 -> 0 | AG29: =IF((AF29-AF28)<0,"0",(AF29-AF28)) -> 0 | AH29: =AI28 -> 0 | AJ29: =IF((AI29-AI28)<0,"0",(AI29-AI28)) -> 0 | AK29: =AL28 -> 0 | AM29: =IF((AL29-AL28)<0,"0",(AL29-AL28)) -> 0 | AN29: =U29+X29+AA29+AD29+AG29+AJ29+AM29 -> 0
A30: =Gen!B35 -> 44068 | C30: =D29 -> 0 | E30: =IF((D30-D29)<0,"0",(D30-D29)) -> 0 | F30: =G30 -> 0 | H30: =IF((G30-G29)<0,"0",(G30-G29)) -> 0 | I30: =J29 -> 0 | K30: =IF((J30-J29)<0,"0",(J30-J29)) -> 0 | L30: =M29 -> 0 | N30: =IF((M30-M29)<0,"0",(M30-M29)) -> 0 | O30: =P29 -> 0 | Q30: =IF((P30-P29)<0,"0",(P30-P29)) -> 0 | S30: =T29 -> 0 | U30: =IF((T30-T29)<0,"0",(T30-T29)) -> 0 | V30: =W29 -> 0 | X30: =IF((W30-W29)<0,"0",(W30-W29)) -> 0 | Y30: =Z29 -> 0 | AA30: =IF((Z30-Z29)<0,"0",(Z30-Z29)) -> 0 | AB30: =AC29 -> 0 | AD30: =AC30-AB30 -> 0 | AE30: =AF29 -> 0 | AG30: =IF((AF30-AF29)<0,"0",(AF30-AF29)) -> 0 | AH30: =AI29 -> 0 | AJ30: =IF((AI30-AI29)<0,"0",(AI30-AI29)) -> 0 | AK30: =AL29 -> 0 | AM30: =IF((AL30-AL29)<0,"0",(AL30-AL29)) -> 0 | AN30: =U30+X30+AA30+AD30+AG30+AJ30+AM30 -> 0
A31: =Gen!B36 -> 44069 | C31: =D30 -> 0 | E31: =IF((D31-D30)<0,"0",(D31-D30)) -> 0 | F31: =G31 -> 0 | H31: =IF((G31-G30)<0,"0",(G31-G30)) -> 0 | I31: =J30 -> 0 | K31: =IF((J31-J30)<0,"0",(J31-J30)) -> 0 | L31: =M30 -> 0 | N31: =IF((M31-M30)<0,"0",(M31-M30)) -> 0 | O31: =P30 -> 0 | Q31: =IF((P31-P30)<0,"0",(P31-P30)) -> 0 | S31: =T30 -> 0 | U31: =IF((T31-T30)<0,"0",(T31-T30)) -> 0 | V31: =W30 -> 0 | X31: =IF((W31-W30)<0,"0",(W31-W30)) -> 0 | Y31: =Z30 -> 0 | AA31: =IF((Z31-Z30)<0,"0",(Z31-Z30)) -> 0 | AB31: =AC30 -> 0 | AD31: =AC31-AB31 -> 0 | AE31: =AF30 -> 0 | AG31: =IF((AF31-AF30)<0,"0",(AF31-AF30)) -> 0 | AH31: =AI30 -> 0 | AJ31: =IF((AI31-AI30)<0,"0",(AI31-AI30)) -> 0 | AK31: =AL30 -> 0 | AM31: =IF((AL31-AL30)<0,"0",(AL31-AL30)) -> 0 | AN31: =U31+X31+AA31+AD31+AG31+AJ31+AM31 -> 0
A32: =Gen!B37 -> 44070 | B32: 10/27//2009 | C32: =D31 -> 0 | E32: =IF((D32-D31)<0,"0",(D32-D31)) -> 0 | F32: =G31 -> 0 | H32: =IF((G32-G31)<0,"0",(G32-G31)) -> 0 | I32: =J31 -> 0 | K32: =IF((J32-J31)<0,"0",(J32-J31)) -> 0 | L32: =M31 -> 0 | N32: =IF((M32-M31)<0,"0",(M32-M31)) -> 0 | O32: =P31 -> 0 | Q32: =IF((P32-P31)<0,"0",(P32-P31)) -> 0 | S32: =T31 -> 0 | U32: =IF((T32-T31)<0,"0",(T32-T31)) -> 0 | V32: =W31 -> 0 | X32: =IF((W32-W31)<0,"0",(W32-W31)) -> 0 | Y32: =Z31 -> 0 | AA32: =IF((Z32-Z31)<0,"0",(Z32-Z31)) -> 0 | AB32: =AC31 -> 0 | AD32: =AC32-AB32 -> 0 | AE32: =AF31 -> 0 | AG32: =IF((AF32-AF31)<0,"0",(AF32-AF31)) -> 0 | AH32: =AI31 -> 0 | AJ32: =IF((AI32-AI31)<0,"0",(AI32-AI31)) -> 0 | AK32: =AL31 -> 0 | AM32: =IF((AL32-AL31)<0,"0",(AL32-AL31)) -> 0 | AN32: =U32+X32+AA32+AD32+AG32+AJ32+AM32 -> 0
A33: =Gen!B38 -> 44071 | C33: =D32 -> 0 | E33: =IF((D33-D32)<0,"0",(D33-D32)) -> 0 | F33: =G32 -> 0 | H33: =IF((G33-G32)<0,"0",(G33-G32)) -> 0 | I33: =J32 -> 0 | K33: =IF((J33-J32)<0,"0",(J33-J32)) -> 0 | L33: =M32 -> 0 | N33: =IF((M33-M32)<0,"0",(M33-M32)) -> 0 | O33: =P32 -> 0 | Q33: =IF((P33-P32)<0,"0",(P33-P32)) -> 0 | S33: =T32 -> 0 | U33: =IF((T33-T32)<0,"0",(T33-T32)) -> 0 | V33: =W32 -> 0 | X33: =IF((W33-W32)<0,"0",(W33-W32)) -> 0 | Y33: =Z32 -> 0 | AA33: =IF((Z33-Z32)<0,"0",(Z33-Z32)) -> 0 | AB33: =AC32 -> 0 | AD33: =AC33-AB33 -> 0 | AE33: =AF32 -> 0 | AG33: =IF((AF33-AF32)<0,"0",(AF33-AF32)) -> 0 | AH33: =AI32 -> 0 | AJ33: =IF((AI33-AI32)<0,"0",(AI33-AI32)) -> 0 | AK33: =AL32 -> 0 | AM33: =IF((AL33-AL32)<0,"0",(AL33-AL32)) -> 0 | AN33: =U33+X33+AA33+AD33+AG33+AJ33+AM33 -> 0
A34: =Gen!B39 -> 44072 | C34: =D33 -> 0 | E34: =IF((D34-D33)<0,"0",(D34-D33)) -> 0 | F34: =G33 -> 0 | H34: =IF((G34-G33)<0,"0",(G34-G33)) -> 0 | I34: =J33 -> 0 | K34: =IF((J34-J33)<0,"0",(J34-J33)) -> 0 | L34: =M33 -> 0 | N34: =IF((M34-M33)<0,"0",(M34-M33)) -> 0 | O34: =P33 -> 0 | Q34: =IF((P34-P33)<0,"0",(P34-P33)) -> 0 | S34: =T33 -> 0 | U34: =IF((T34-T33)<0,"0",(T34-T33)) -> 0 | V34: =W33 -> 0 | X34: =IF((W34-W33)<0,"0",(W34-W33)) -> 0 | Y34: =Z33 -> 0 | AA34: =IF((Z34-Z33)<0,"0",(Z34-Z33)) -> 0 | AB34: =AC33 -> 0 | AD34: =AC34-AB34 -> 0 | AE34: =AF33 -> 0 | AG34: =IF((AF34-AF33)<0,"0",(AF34-AF33)) -> 0 | AH34: =AI33 -> 0 | AJ34: =IF((AI34-AI33)<0,"0",(AI34-AI33)) -> 0 | AK34: =AL33 -> 0 | AM34: =IF((AL34-AL33)<0,"0",(AL34-AL33)) -> 0 | AN34: =U34+X34+AA34+AD34+AG34+AJ34+AM34 -> 0
A35: =Gen!B40 -> 44073 | C35: =D34 -> 0 | E35: =IF((D35-D34)<0,"0",(D35-D34)) -> 0 | F35: =G34 -> 0 | H35: =IF((G35-G34)<0,"0",(G35-G34)) -> 0 | I35: =J34 -> 0 | K35: =IF((J35-J34)<0,"0",(J35-J34)) -> 0 | L35: =M34 -> 0 | N35: =IF((M35-M34)<0,"0",(M35-M34)) -> 0 | O35: =P34 -> 0 | Q35: =IF((P35-P34)<0,"0",(P35-P34)) -> 0 | S35: =T34 -> 0 | U35: =IF((T35-T34)<0,"0",(T35-T34)) -> 0 | V35: =W34 -> 0 | X35: =IF((W35-W34)<0,"0",(W35-W34)) -> 0 | Y35: =Z34 -> 0 | AA35: =IF((Z35-Z34)<0,"0",(Z35-Z34)) -> 0 | AB35: =AC34 -> 0 | AD35: =AC35-AB35 -> 0 | AE35: =AF34 -> 0 | AG35: =IF((AF35-AF34)<0,"0",(AF35-AF34)) -> 0 | AH35: =AI34 -> 0 | AJ35: =IF((AI35-AI34)<0,"0",(AI35-AI34)) -> 0 | AK35: =AL34 -> 0 | AM35: =IF((AL35-AL34)<0,"0",(AL35-AL34)) -> 0 | AN35: =U35+X35+AA35+AD35+AG35+AJ35+AM35 -> 0
A36: =Gen!B41 -> 44074 | C36: =D35 -> 0 | E36: =IF((D36-D35)<0,"0",(D36-D35)) -> 0 | F36: =G35 -> 0 | H36: =IF((G36-G35)<0,"0",(G36-G35)) -> 0 | I36: =J35 -> 0 | K36: =IF((J36-J35)<0,"0",(J36-J35)) -> 0 | L36: =M35 -> 0 | N36: =IF((M36-M35)<0,"0",(M36-M35)) -> 0 | O36: =P35 -> 0 | Q36: =IF((P36-P35)<0,"0",(P36-P35)) -> 0 | S36: =T35 -> 0 | U36: =IF((T36-T35)<0,"0",(T36-T35)) -> 0 | V36: =W35 -> 0 | X36: =IF((W36-W35)<0,"0",(W36-W35)) -> 0 | Y36: =Z35 -> 0 | AA36: =IF((Z36-Z35)<0,"0",(Z36-Z35)) -> 0 | AB36: =AC35 -> 0 | AD36: =AC36-AB36 -> 0 | AE36: =AF35 -> 0 | AG36: =IF((AF36-AF35)<0,"0",(AF36-AF35)) -> 0 | AH36: =AI35 -> 0 | AJ36: =IF((AI36-AI35)<0,"0",(AI36-AI35)) -> 0 | AK36: =AL35 -> 0 | AM36: =IF((AL36-AL35)<0,"0",(AL36-AL35)) -> 0 | AN36: =U36+X36+AA36+AD36+AG36+AJ36+AM36 -> 0
A37: =Gen!B42 -> 0 | C37: =D36 -> 0 | E37: =IF((D37-D36)<0,"0",(D37-D36)) -> 0 | F37: =G36 -> 0 | H37: =IF((G37-G36)<0,"0",(G37-G36)) -> 0 | I37: =J36 -> 0 | K37: =IF((J37-J36)<0,"0",(J37-J36)) -> 0 | L37: =M36 -> 0 | N37: =IF((M37-M36)<0,"0",(M37-M36)) -> 0 | O37: =P36 -> 0 | Q37: =IF((P37-P36)<0,"0",(P37-P36)) -> 0 | S37: =T36 -> 0 | U37: =IF((T37-T36)<0,"0",(T37-T36)) -> 0 | V37: =W36 -> 0 | X37: =IF((W37-W36)<0,"0",(W37-W36)) -> 0 | Y37: =Z36 -> 0 | AA37: =IF((Z37-Z36)<0,"0",(Z37-Z36)) -> 0 | AB37: =AC36 -> 0 | AD37: =AC37-AB37 -> 0 | AE37: =AF36 -> 0 | AG37: =IF((AF37-AF36)<0,"0",(AF37-AF36)) -> 0 | AH37: =AI36 -> 0 | AJ37: =IF((AI37-AI36)<0,"0",(AI37-AI36)) -> 0 | AK37: =AL36 -> 0 | AM37: =IF((AL37-AL36)<0,"0",(AL37-AL36)) -> 0 | AN37: =U38+X38+AA38+AD38+AG38+AJ38+AM38 -> 610
C38: TOTAL USAGE | E38: =SUM(E6:E36) -> 379 | F38: KL | H38: =SUM(H6:H37) -> 0 | K38: =SUM(K6:K37) -> 6 | N38: =M38-M37 -> 0 | Q38: =P38-O38 -> 0 | R38: =E38 -> 379 | U38: =SUM(U6:U37) -> 610 | AJ38: =IF((AI39-AI37)<0,"0",(AI39-AI37)) -> 0 | AN38: =U38+X38+AA38+AD38+AG38+AJ38+AM38 -> 610
C42: WATER TANK LEVEL
C43: RAW WATER TANK NO.1 | E43: RAW WATER TANK NO.2 | G43: TREATED WATER TANK | I43: TREATED -HILL TANK | K43: TOTAL WATER AVAILABLE
C44: CAPACITY 217 m³ | E44: CAPACITY 92 m³ | G44: CAPACITY 146 m³ | I44: CAPACITY 213 m³
C45: cm | D45: m³ | E45: cm | F45: m³ | H45: m³ | I45: cm | J45: m³ | K45: m³
A46: =Gen!B11 -> 44044 | C46: 156 | D46: =C46*217/300 -> 112.84 | E46: 120 | F46: =E46*92/305 -> 36.196721 | G46: 290 | H46: =G46*146/383 -> 110.5483 | I46: 130 | J46: =I46*213/308 -> 89.902597 | K46: =D46+F46+H46+J46 -> 349.48762
A47: =Gen!B12 -> 44045 | C47: 196 | D47: =C47*217/300 -> 141.77333 | E47: 160 | F47: =E47*92/305 -> 48.262295 | G47: 139 | H47: =G47*146/383 -> 52.986945 | I47: 210 | J47: =I47*213/308 -> 145.22727 | K47: =D47+F47+H47+J47 -> 388.24985
A48: =Gen!B13 -> 44046 | C48: 135 | D48: =C48*217/300 -> 97.65 | E48: 99 | F48: =E48*92/305 -> 29.862295 | G48: 300 | H48: =G48*146/383 -> 114.36031 | I48: 290 | J48: =I48*213/308 -> 200.55195 | K48: =D48+F48+H48+J48 -> 442.42456
A49: =Gen!B14 -> 44047 | C49: 240 | D49: =C49*217/300 -> 173.6 | E49: 225 | F49: =E49*92/305 -> 67.868852 | G49: 210 | H49: =G49*146/383 -> 80.052219 | I49: 285 | J49: =I49*213/308 -> 197.09416 | K49: =D49+F49+H49+J49 -> 518.61523
A50: =Gen!B15 -> 44048 | C50: 300 | D50: =C50*217/300 -> 217 | E50: 290 | F50: =E50*92/305 -> 87.47541 | G50: 200 | H50: =G50*146/383 -> 76.240209 | I50: 287 | J50: =I50*213/308 -> 198.47727 | K50: =D50+F50+H50+J50 -> 579.19289
A51: =Gen!B16 -> 44049 | C51: 300 | D51: =C51*217/300 -> 217 | E51: 290 | F51: =E51*92/305 -> 87.47541 | G51: 220 | H51: =G51*146/383 -> 83.86423 | I51: 290 | J51: =I51*213/308 -> 200.55195 | K51: =D51+F51+H51+J51 -> 588.89159
A52: =Gen!B17 -> 44050 | C52: 301 | D52: =C52*217/300 -> 217.72333 | E52: 290 | F52: =E52*92/305 -> 87.47541 | G52: 180 | H52: =G52*146/383 -> 68.616188 | I52: 286 | J52: =I52*213/308 -> 197.78571 | K52: =D52+F52+H52+J52 -> 571.60065
A53: =Gen!B18 -> 44051 | C53: 300 | D53: =C53*217/300 -> 217 | E53: 285 | F53: =E53*92/305 -> 85.967213 | G53: 190 | H53: =G53*146/383 -> 72.428198 | I53: 288 | J53: =I53*213/308 -> 199.16883 | K53: =D53+F53+H53+J53 -> 574.56424
A54: =Gen!B19 -> 44052 | D54: =C54*217/300 -> 0 | F54: =E54*92/305 -> 0 | H54: =G54*146/383 -> 0 | J54: =I54*213/308 -> 0 | K54: =D54+F54+H54+J54 -> 0
A55: =Gen!B20 -> 44053 | D55: =C55*217/300 -> 0 | F55: =E55*92/305 -> 0 | H55: =G55*146/383 -> 0 | J55: =I55*213/308 -> 0 | K55: =D55+F55+H55+J55 -> 0
A56: =Gen!B21 -> 44054 | D56: =C56*217/300 -> 0 | F56: =E56*92/305 -> 0 | H56: =G56*146/383 -> 0 | J56: =I56*213/308 -> 0 | K56: =D56+F56+H56+J56 -> 0
A57: =Gen!B22 -> 44055 | D57: =C57*217/300 -> 0 | F57: =E57*92/305 -> 0 | H57: =G57*146/383 -> 0 | J57: =I57*213/308 -> 0 | K57: =D57+F57+H57+J57 -> 0
A58: =Gen!B23 -> 44056 | D58: =C58*217/300 -> 0 | F58: =E58*92/305 -> 0 | H58: =G58*146/383 -> 0 | J58: =I58*213/308 -> 0 | K58: =D58+F58+H58+J58 -> 0
A59: =Gen!B24 -> 44057 | D59: =C59*217/300 -> 0 | F59: =E59*92/305 -> 0 | H59: =G59*146/383 -> 0 | J59: =I59*213/308 -> 0 | K59: =D59+F59+H59+J59 -> 0
A60: =Gen!B25 -> 44058 | D60: =C60*217/300 -> 0 | F60: =E60*92/305 -> 0 | H60: =G60*146/383 -> 0 | J60: =I60*213/308 -> 0 | K60: =D60+F60+H60+J60 -> 0
A61: =Gen!B26 -> 44059 | D61: =C61*217/300 -> 0 | F61: =E61*92/305 -> 0 | H61: =G61*146/383 -> 0 | J61: =I61*213/308 -> 0 | K61: =D61+F61+H61+J61 -> 0
A62: =Gen!B27 -> 44060 | D62: =C62*217/300 -> 0 | F62: =E62*92/305 -> 0 | H62: =G62*146/383 -> 0 | J62: =I62*213/308 -> 0 | K62: =D62+F62+H62+J62 -> 0
A63: =Gen!B28 -> 44061 | D63: =C63*217/300 -> 0 | F63: =E63*92/305 -> 0 | H63: =G63*146/383 -> 0 | J63: =I63*213/308 -> 0 | K63: =D63+F63+H63+J63 -> 0
A64: =Gen!B29 -> 44062 | D64: =C64*217/300 -> 0 | F64: =E64*92/305 -> 0 | H64: =G64*146/383 -> 0 | J64: =I64*213/308 -> 0 | K64: =D64+F64+H64+J64 -> 0
A65: =Gen!B30 -> 44063 | D65: =C65*217/300 -> 0 | F65: =E65*92/305 -> 0 | H65: =G65*146/383 -> 0 | J65: =I65*213/308 -> 0 | K65: =D65+F65+H65+J65 -> 0
... A77: =Gen!B42 -> 0 | D77: =C77*217/300 -> 0 | F77: =E77*92/305 -> 0 | H77: =G77*146/383 -> 0 | J77: =I77*213/308 -> 0 | K77: =D77+F77+H77+J77 -> 0
A78: =Gen!B43 -> BF

Sheet Water_Graph 
A1: Date | B1: Usage | C1: Occ %
A2: =Gen!B11 -> 44044 | B2: =SUM('[1]Water-Meter'!R10) -> #REF! | C2: =SUM([1]Gen!B11) -> 0.623
A3: =Gen!B12 -> 44045 | B3: =SUM('[1]Water-Meter'!R11) -> #REF! | C3: =SUM([1]Gen!B12) -> 0.779
A4: =Gen!B13 -> 44046 | B4: =SUM('[1]Water-Meter'!R12) -> #REF! | C4: =SUM([1]Gen!B13) -> 0.532
A5: =Gen!B14 -> 44047 | B5: =SUM('[1]Water-Meter'!R13) -> #REF! | C5: =SUM([1]Gen!B14) -> 0.61
A6: =Gen!B15 -> 44048 | B6: =SUM('[1]Water-Meter'!R14) -> #REF! | C6: =SUM([1]Gen!B15) -> 0.688
A7: =Gen!B16 -> 44049 | B7: =SUM('[1]Water-Meter'!R15) -> #REF! | C7: =SUM([1]Gen!B16) -> 0.532
A8: =Gen!B17 -> 44050 | B8: =SUM('[1]Water-Meter'!R16) -> #REF! | C8: =SUM([1]Gen!B17) -> 0.753
A9: =Gen!B18 -> 44051 | B9: =SUM('[1]Water-Meter'!R17) -> #REF! | C9: =SUM([1]Gen!B18) -> 0.156
A10: =Gen!B19 -> 44052 | B10: =SUM('[1]Water-Meter'!R18) -> #REF! | C10: =SUM([1]Gen!B19) -> 0.442
A11: =Gen!B20 -> 44053 | B11: =SUM('[1]Water-Meter'!R19) -> #REF! | C11: =SUM([1]Gen!B20) -> 0.325
A12: =Gen!B21 -> 44054 | B12: =SUM('[1]Water-Meter'!R20) -> #REF! | C12: =SUM([1]Gen!B21) -> 0.455
A13: =Gen!B22 -> 44055 | B13: =SUM('[1]Water-Meter'!R21) -> #REF! | C13: =SUM([1]Gen!B22) -> 0.416
... A32: =Gen!B41 -> 44074 | B32: =SUM('[1]Water-Meter'!R40) -> #REF! | C32: =SUM([1]Gen!B41) -> #REF!

Sheet Sheet1
A2: Generator and Diseal Summry Report | Q2: 2209.85 | R2: Diesel Cost | S2: Rate$ | T2: 1584
M3: % of Gas balance in Tank | P3: % of Dieasel balance in Tank | Q3: HLP Cost (TSH) | V3: Total Cost (TSH) | W3: Consumption Guest Occ% | AA3: Budget Cost Per Room occ
A4: Date | B4: Gen Set Hours Working | C4: Occ% | D4: Total OCC Room | E4: Guest Room Occ | F4: Total Kwh Generated | G4: Diseal consumed by Gen (Ltrs) | H4: Diseal consumed by Veichel (Ltrs) | I4: Total diseal consumed (Ltrs) | J4: Balance stock of Diseal (Ltrs) | K4: Water consumed | L4: Gas consumed (KG) | M4: 3 | N4: 2 | O4: 1 | Q4: Electricity | R4: Cost per Room Total OOC Usd | S4: Cost per Room Guest OOC Usd | T4: Water | U4: Gas
A5: =Gen!B11 -> 44044 | B5: 0 | C5: =Gen!C11 -> 0 | D5: =SUM(77*C5) -> 0 | F5: =Gen!U11 -> 1872 | G5: =Gen!T11 -> 741.42 | H5: =[1]Gen!#REF! -> #REF! | I5: =SUM(G5:H5) -> #REF! | J5: =[1]Gen!AT11 -> 47806.65 | K5: ='Water-Meter'!E6 -> 51 | L5: ='Lpg (2)'!G10 -> 315873.14 | M5: =#REF! -> #REF! | N5: =#REF! -> #REF! | O5: =#REF! -> #REF! | P5: =J5/52000 -> 0.91935865 | Q5: =I5*Q2 -> #REF! | R5: =SUM(Q5/D5)/X5 -> #REF! | S5: =SUM(Q5/E5)/X5 -> #REF! | T5: =(K5*102)/X5 -> 3.2840909 | U5: =SUM(L5*1963)/X5 -> 391451.37 | V5: =SUM(Q5+T5+U5) -> #REF! | W5: =SUM(V5/E5)/T2 -> #REF! | X5: =SUM(T2) -> 1584 | Y5: 106 | Z5: =SUM(Y5-S5) -> #REF! | AA5: 106
A6: =Gen!B12 -> 44045 | B6: 0 | C6: =Gen!C12 -> 0 | D6: =SUM(77*C6) -> 0 | F6: =Gen!U12 -> 2030 | G6: =Gen!T12 -> 782.06 | H6: =[1]Gen!#REF! -> #REF! | I6: =SUM(G6:H6) -> #REF! | J6: =[1]Gen!AT12 -> 45423.89 | K6: ='Water-Meter'!E7 -> 53 | L6: ='Lpg (2)'!G11 -> 25.784 | M6: =#REF! -> #REF! | N6: =#REF! -> #REF! | O6: =#REF! -> #REF! | P6: =J6/52000 -> 0.87353635 | Q6: =I6*Q2 -> #REF! | R6: =SUM(Q6/D6)/X6 -> #REF! | S6: =SUM(Q6/E6)/X6 -> #REF! | T6: =(K6*102)/X6 -> 3.4128788 | U6: =SUM(L6*1963)/X6 -> 31.953278 | V6: =SUM(Q6+T6+U6) -> #REF! | W6: =SUM(V6/E6)/T2 -> #REF! | X6: =SUM(X5) -> 1584 | Y6: 106 | Z6: =SUM(Y6-S6) -> #REF!
A7: =Gen!B13 -> 44046 | B7: 0 | C7: =Gen!C13 -> 0 | D7: =SUM(77*C7) -> 0 | F7: =Gen!U13 -> 1818 | G7: =Gen!T13 -> 788.41 | H7: =[1]Gen!#REF! -> #REF! | I7: =SUM(G7:H7) -> #REF! | J7: =[1]Gen!AT13 -> 42919.59 | K7: ='Water-Meter'!E8 -> 42 | L7: ='Lpg (2)'!G12 -> 65.648 | M7: =#REF! -> #REF! | N7: =#REF! -> #REF! | O7: =#REF! -> #REF! | P7: =J7/52000 -> 0.82537673 | Q7: =I7*Q2 -> #REF! | R7: =SUM(Q7/D7)/X7 -> #REF! | S7: =SUM(Q7/E7)/X7 -> #REF! | T7: =(K7*102)/X7 -> 2.7045455 | U7: =SUM(L7*1963)/X7 -> 81.355444 | V7: =SUM(Q7+T7+U7) -> #REF! | W7: =SUM(V7/E7)/T2 -> #REF! | X7: =SUM(X6) -> 1584 | Y7: 106 | Z7: =SUM(Y7-S7) -> #REF!
A8: =Gen!B14 -> 44047 | B8: 0 | C8: =Gen!C14 -> 0 | D8: =SUM(77*C8) -> 0 | F8: =Gen!U14 -> 1980 | G8: =Gen!T14 -> 793.61 | H8: =[1]Gen!AJ9 -> #REF! | I8: =SUM(G8:H8) -> #REF! | J8: =[1]Gen!AT14 -> 40258.94 | K8: ='Water-Meter'!E9 -> 67 | L8: ='Lpg (2)'!G13 -> 22.704 | M8: =#REF! -> #REF! | N8: =#REF! -> #REF! | O8: =#REF! -> #REF! | P8: =J8/52000 -> 0.77421038 | Q8: =I8*Q2 -> #REF! | R8: =SUM(Q8/D8)/X8 -> #REF! | S8: =SUM(Q8/E8)/X8 -> #REF! | T8: =(K8*102)/X8 -> 4.3143939 | U8: =SUM(L8*1963)/X8 -> 28.136333 | V8: =SUM(Q8+T8+U8) -> #REF! | W8: =SUM(V8/E8)/T2 -> #REF! | X8: =SUM(X7) -> 1584 | Y8: 106 | Z8: =SUM(Y8-S8) -> #REF!
A9: =Gen!B15 -> 44048 | B9: 0 | C9: =Gen!C15 -> 0 | D9: =SUM(77*C9) -> 0 | F9: =Gen!U15 -> 1724 | G9: =Gen!T15 -> 776.02 | H9: =[1]Gen!AJ10 -> 0 | I9: =SUM(G9:H9) -> 776.02 | J9: =[1]Gen!AT15 -> 37525.21 | K9: ='Water-Meter'!E10 -> 49 | L9: ='Lpg (2)'!G14 -> 31.24 | M9: =#REF! -> #REF! | N9: =#REF! -> #REF! | O9: =#REF! -> #REF! | P9: =J9/52000 -> 0.72163865 | Q9: =I9*Q2 -> 1714887.8 | R9: =SUM(Q9/D9)/X9 -> #DIV/0! | S9: =SUM(Q9/E9)/X9 -> #DIV/0! | T9: =(K9*102)/X9 -> 3.155303 | U9: =SUM(L9*1963)/X9 -> 38.714722 | V9: =SUM(Q9+T9+U9) -> 1714929.7 | W9: =SUM(V9/E9)/T2 -> #DIV/0! | X9: =SUM(X8) -> 1584 | Y9: 106 | Z9: =SUM(Y9-S9) -> #DIV/0!
A10: =Gen!B16 -> 44049 | B10: 0 | C10: =Gen!C16 -> 0 | D10: =SUM(77*C10) -> 0 | F10: =Gen!U16 -> 1892 | G10: =Gen!T16 -> 778.12 | H10: =[1]Gen!#REF! -> #REF! | I10: =SUM(G10:H10) -> #REF! | J10: =[1]Gen!AT16 -> 35107.69 | K10: ='Water-Meter'!E11 -> 66 | L10: ='Lpg (2)'!G15 -> 8.448 | M10: =#REF! -> #REF! | N10: =#REF! -> #REF! | O10: =#REF! -> #REF! | P10: =J10/52000 -> 0.67514788 | Q10: =I10*Q2 -> #REF! | R10: =SUM(Q10/D10)/X10 -> #REF! | S10: =SUM(Q10/E10)/X10 -> #REF! | T10: =(K10*102)/X10 -> 4.25 | U10: =SUM(L10*1963)/X10 -> 10.469333 | V10: =SUM(Q10+T10+U10) -> #REF! | W10: =SUM(V10/E10)/T2 -> #REF! | X10: =SUM(X9) -> 1584 | Y10: 106 | Z10: =SUM(Y10-S10) -> #REF!
A11: =Gen!B17 -> 44050 | B11: 0 | C11: =Gen!C17 -> 0 | D11: =SUM(77*C11) -> 0 | F11: =Gen!U17 -> 1882 | G11: =Gen!T17 -> 771.7 | H11: =[1]Gen!AJ25 -> 80.56 | I11: =SUM(G11:H11) -> 852.26 | J11: =[1]Gen!AT17 -> 47513.14 | K11: ='Water-Meter'!E12 -> 51 | L11: ='Lpg (2)'!G16 -> -316026.96 | M11: =#REF! -> #REF! | N11: =#REF! -> #REF! | O11: =#REF! -> #REF! | P11: =J11/52000 -> 0.91371423 | Q11: =I11*Q2 -> 1883366.8 | R11: =SUM(Q11/D11)/X11 -> #DIV/0! | S11: =SUM(Q11/E11)/X11 -> #DIV/0! | T11: =(K11*102)/X11 -> 3.2840909 | U11: =SUM(L11*1963)/X11 -> -391642 | V11: =SUM(Q11+T11+U11) -> 1491728 | W11: =SUM(V11/E11)/T2 -> #DIV/0! | X11: =SUM(X10) -> 1584 | Y11: 106 | Z11: =SUM(Y11-S11) -> #DIV/0!
A12: =Gen!B18 -> 44051 | B12: 0 | C12: =Gen!C18 -> 0 | D12: =SUM(77*C12) -> 0 | F12: =Gen!U18 -> 0 | G12: =Gen!T18 -> 0 | H12: =[1]Gen!#REF! -> #REF! | I12: =SUM(G12:H12) -> #REF! | J12: =[1]Gen!AT18 -> 45161.89 | K12: ='Water-Meter'!E13 -> 0 | L12: ='Lpg (2)'!G17 -> 0 | M12: =#REF! -> #REF! | N12: =#REF! -> #REF! | O12: =#REF! -> #REF! | P12: =J12/52000 -> 0.86849788 | Q12: =I12*Q2 -> #REF! | R12: =SUM(Q12/D12)/X12 -> #REF! | S12: =SUM(Q12/E12)/X12 -> #REF! | T12: =(K12*102)/X12 -> 0 | U12: =SUM(L12*1963)/X12 -> 0 | V12: =SUM(Q12+T12+U12) -> #REF! | W12: =SUM(V12/E12)/T2 -> #REF! | X12: =SUM(X11) -> 1584 | Y12: 106 | Z12: =SUM(Y12-S12) -> #REF!
A13: =Gen!B19 -> 44052 | B13: 0 | C13: =Gen!C19 -> 0 | D13: =SUM(77*C13) -> 0 | F13: =Gen!U19 -> 0 | G13: =Gen!T19 -> 0 | H13: =[1]Gen!#REF! -> #REF! | I13: =SUM(G13:H13) -> #REF! | J13: =[1]Gen!AT19 -> 42825.48 | K13: ='Water-Meter'!E14 -> 0 | L13: ='Lpg (2)'!G18 -> 0 | M13: =#REF! -> #REF! | N13: =#REF! -> #REF! | O13: =#REF! -> #REF! | P13: =J13/52000 -> 0.82356692 | Q13: =I13*Q2 -> #REF! | R13: =SUM(Q13/D13)/X13 -> #REF! | S13: =SUM(Q13/E13)/X13 -> #REF! | T13: =(K13*102)/X13 -> 0 | U13: =SUM(L13*1963)/X13 -> 0 | V13: =SUM(Q13+T13+U13) -> #REF! | W13: =SUM(V13/E13)/T2 -> #REF! | X13: =SUM(X12) -> 1584 | Y13: 106 | Z13: =SUM(Y13-S13) -> #REF!
A14: =Gen!B20 -> 44053 | B14: 0 | C14: =Gen!C20 -> 0 | D14: =SUM(77*C14) -> 0 | F14: =Gen!U20 -> 0 | G14: =Gen!T20 -> 0 | H14: =[1]Gen!#REF! -> #REF! | I14: =SUM(G14:H14) -> #REF! | J14: =[1]Gen!AT20 -> 40110.38 | K14: ='Water-Meter'!E15 -> 0 | L14: ='Lpg (2)'!G19 -> 0 | M14: =#REF! -> #REF! | N14: =#REF! -> #REF! | O14: =#REF! -> #REF! | P14: =J14/52000 -> 0.77135346 | Q14: =I14*Q2 -> #REF! | R14: =SUM(Q14/D14)/X14 -> #REF! | S14: =SUM(Q14/E14)/X14 -> #REF! | T14: =(K14*102)/X14 -> 0 | U14: =SUM(L14*1963)/X14 -> 0 | V14: =SUM(Q14+T14+U14) -> #REF! | W14: =SUM(V14/E14)/T2 -> #REF! | X14: =SUM(X13) -> 1584 | Y14: 106 | Z14: =SUM(Y14-S14) -> #REF!
A15: =Gen!B21 -> 44054 | B15: 0 | C15: =Gen!C21 -> 0 | D15: =SUM(77*C15) -> 0 | F15: =Gen!U21 -> 0 | G15: =Gen!T21 -> 0 | H15: =[1]Gen!#REF! -> #REF! | I15: =SUM(G15:H15) -> #REF! | J15: =[1]Gen!AT21 -> 37540.57 | K15: ='Water-Meter'!E16 -> 0 | L15: ='Lpg (2)'!G20 -> 0 | M15: =#REF! -> #REF! | N15: =#REF! -> #REF! | O15: =#REF! -> #REF! | P15: =J15/52000 -> 0.72193404 | Q15: =I15*Q2 -> #REF! | R15: =SUM(Q15/D15)/X15 -> #REF! | S15: =SUM(Q15/E15)/X15 -> #REF! | T15: =(K15*102)/X15 -> 0 | U15: =SUM(L15*1963)/X15 -> 0 | V15: =SUM(Q15+T15+U15) -> #REF! | W15: =SUM(V15/E15)/T2 -> #REF! | X15: =SUM(X14) -> 1584 | Y15: 106 | Z15: =SUM(Y15-S15) -> #REF!
A16: =Gen!B22 -> 44055 | B16: 0 | C16: =Gen!C22 -> 0 | D16: =SUM(77*C16) -> 0 | F16: =Gen!U22 -> 0 | G16: =Gen!T22 -> 0 | H16: =[1]Gen!#REF! -> #REF! | I16: =SUM(G16:H16) -> #REF! | J16: =[1]Gen!AT22 -> 34967.29 | K16: ='Water-Meter'!E17 -> 0 | L16: ='Lpg (2)'!G21 -> 0 | M16: =#REF! -> #REF! | N16: =#REF! -> #REF! | O16: =#REF! -> #REF! | P16: =J16/52000 -> 0.67244788 | Q16: =I16*Q2 -> #REF! | R16: =SUM(Q16/D16)/X16 -> #REF! | S16: =SUM(Q16/E16)/X16 -> #REF! | T16: =(K16*102)/X16 -> 0 | U16: =SUM(L16*1963)/X16 -> 0 | V16: =SUM(Q16+T16+U16) -> #REF! | W16: =SUM(V16/E16)/T2 -> #REF! | X16: =SUM(X15) -> 1584 | Y16: 106 | Z16: =SUM(Y16-S16) -> #REF!
A17: =Gen!B23 -> 44056 | B17: 0 | C17: =Gen!C23 -> 0 | D17: =SUM(77*C17) -> 0 | F17: =Gen!U23 -> 0 | G17: =Gen!T23 -> 0 | H17: =[1]Gen!#REF! -> #REF! | I17: =SUM(G17:H17) -> #REF! | J17: =[1]Gen!AT23 -> 32228.76 | K17: ='Water-Meter'!E18 -> 0 | L17: ='Lpg (2)'!G22 -> 0 | M17: =#REF! -> #REF! | N17: =#REF! -> #REF! | O17: =#REF! -> #REF! | P17: =J17/52000 -> 0.61978385 | Q17: =I17*Q2 -> #REF! | R17: =SUM(Q17/D17)/X17 -> #REF! | S17: =SUM(Q17/E17)/X17 -> #REF! | T17: =(K17*102)/X17 -> 0 | U17: =SUM(L17*1963)/X17 -> 0 | V17: =SUM(Q17+T17+U17) -> #REF! | W17: =SUM(V17/E17)/T2 -> #REF! | X17: =SUM(X16) -> 1584 | Y17: 106 | Z17: =SUM(Y17-S17) -> #REF!
A18: =Gen!B24 -> 44057 | B18: 0 | C18: =Gen!C24 -> 0 | D18: =SUM(77*C18) -> 0 | F18: =Gen!U24 -> 0 | G18: =Gen!T24 -> 0 | H18: =[1]Gen!AJ27 -> 597.9 | I18: =SUM(G18:H18) -> 597.9 | J18: =[1]Gen!AT24 -> 29915.45 | K18: ='Water-Meter'!E19 -> 0 | L18: ='Lpg (2)'!G23 -> 0 | M18: =#REF! -> #REF! | N18: =#REF! -> #REF! | O18: =#REF! -> #REF! | P18: =J18/52000 -> 0.57529712 | Q18: =I18*Q2 -> 1321269.3 | R18: =SUM(Q18/D18)/X18 -> #DIV/0! | S18: =SUM(Q18/E18)/X18 -> #DIV/0! | T18: =(K18*102)/X18 -> 0 | U18: =SUM(L18*1963)/X18 -> 0 | V18: =SUM(Q18+T18+U18) -> 1321269.3 | W18: =SUM(V18/E18)/T2 -> #DIV/0! | X18: =SUM(X17) -> 1584 | Y18: 106 | Z18: =SUM(Y18-S18) -> #DIV/0!
A19: =Gen!B25 -> 44058 | B19: 0 | C19: =Gen!C25 -> 0 | D19: =SUM(77*C19) -> 0 | F19: =Gen!U25 -> 0 | G19: =Gen!T25 -> 0 | H19: =[1]Gen!AJ28 -> 227.73 | I19: =SUM(G19:H19) -> 227.73 | J19: =[1]Gen!AT25 -> 42248.24 | K19: ='Water-Meter'!E20 -> 0 | L19: ='Lpg (2)'!G24 -> 0 | M19: =#REF! -> #REF! | N19: =#REF! -> #REF! | O19: =#REF! -> #REF! | P19: =J19/52000 -> 0.81246615 | Q19: =I19*Q2 -> 503249.14 | R19: =SUM(Q19/D19)/X19 -> #DIV/0! | S19: =SUM(Q19/E19)/X19 -> #DIV/0! | T19: =(K19*102)/X19 -> 0 | U19: =SUM(L19*1963)/X19 -> 0 | V19: =SUM(Q19+T19+U19) -> 503249.14 | W19: =SUM(V19/E19)/T2 -> #DIV/0! | X19: =SUM(X18) -> 1584 | Y19: 106 | Z19: =SUM(Y19-S19) -> #DIV/0!
A20: =Gen!B26 -> 44059 | B20: 0 | C20: =Gen!C26 -> 0 | D20: =SUM(77*C20) -> 0 | F20: =Gen!U26 -> 0 | G20: =Gen!T26 -> 0 | H20: =[1]Gen!AJ29 -> 88.29 | I20: =SUM(G20:H20) -> 88.29 | J20: =[1]Gen!AT26 -> 39497.37 | K20: ='Water-Meter'!E21 -> 0 | L20: ='Lpg (2)'!G25 -> 0 | M20: =#REF! -> #REF! | N20: =#REF! -> #REF! | O20: =#REF! -> #REF! | P20: =J20/52000 -> 0.75956481 | Q20: =I20*Q2 -> 195107.66 | R20: =SUM(Q20/D20)/X20 -> #DIV/0! | S20: =SUM(Q20/E20)/X20 -> #DIV/0! | T20: =(K20*102)/X20 -> 0 | U20: =SUM(L20*1963)/X20 -> 0 | V20: =SUM(Q20+T20+U20) -> 195107.66 | W20: =SUM(V20/E20)/T2 -> #DIV/0! | X20: =SUM(X19) -> 1584 | Y20: 106 | Z20: =SUM(Y20-S20) -> #DIV/0!
A21: =Gen!B27 -> 44060 | B21: 0 | C21: =Gen!C27 -> 0 | D21: =SUM(77*C21) -> 0 | F21: =Gen!U27 -> 0 | G21: =Gen!T27 -> 0 | H21: =[1]Gen!AJ30 -> 783.92 | I21: =SUM(G21:H21) -> 783.92 | J21: =[1]Gen!AT27 -> 36688.35 | K21: ='Water-Meter'!E22 -> 0 | L21: ='Lpg (2)'!G26 -> 0 | M21: =#REF! -> #REF! | N21: =#REF! -> #REF! | O21: =#REF! -> #REF! | P21: =J21/52000 -> 0.70554519 | Q21: =I21*Q2 -> 1732345.6 | R21: =SUM(Q21/D21)/X21 -> #DIV/0! | S21: =SUM(Q21/E21)/X21 -> #DIV/0! | T21: =(K21*102)/X21 -> 0 | U21: =SUM(L21*1963)/X21 -> 0 | V21: =SUM(Q21+T21+U21) -> 1732345.6 | W21: =SUM(V21/E21)/T2 -> #DIV/0! | X21: =SUM(X20) -> 1584 | Y21: 106 | Z21: =SUM(Y21-S21) -> #DIV/0!
A22: =Gen!B28 -> 44061 | B22: 0 | C22: =Gen!C28 -> 0 | D22: =SUM(77*C22) -> 0 | F22: =Gen!U28 -> 0 | G22: =Gen!T28 -> 0 | H22: =[1]Gen!#REF! -> #REF! | I22: =SUM(G22:H22) -> #REF! | J22: =[1]Gen!AT28 -> 33769.34 | K22: ='Water-Meter'!E23 -> 0 | L22: ='Lpg (2)'!G27 -> 0 | M22: =#REF! -> #REF! | N22: =#REF! -> #REF! | O22: =#REF! -> #REF! | P22: =J22/52000 -> 0.64941038 | Q22: =I22*Q2 -> #REF! | R22: =SUM(Q22/D22)/X22 -> #REF! | S22: =SUM(Q22/E22)/X22 -> #REF! | T22: =(K22*102)/X22 -> 0 | U22: =SUM(L22*1963)/X22 -> 0 | V22: =SUM(Q22+T22+U22) -> #REF! | W22: =SUM(V22/E22)/T2 -> #REF! | X22: =SUM(X21) -> 1584 | Y22: 106 | Z22: =SUM(Y22-S22) -> #REF!
A23: =Gen!B29 -> 44062 | B23: 0 | C23: =Gen!C29 -> 0 | D23: =SUM(77*C23) -> 0 | F23: =Gen!U29 -> 0 | G23: =Gen!T29 -> 0 | H23: =[1]Gen!#REF! -> #REF! | I23: =SUM(G23:H23) -> #REF! | J23: =[1]Gen!AT29 -> 31336.77 | K23: ='Water-Meter'!E24 -> 0 | L23: ='Lpg (2)'!G28 -> 0 | M23: =#REF! -> #REF! | N23: =#REF! -> #REF! | O23: =#REF! -> #REF! | P23: =J23/52000 -> 0.60263019 | Q23: =I23*Q2 -> #REF! | R23: =SUM(Q23/D23)/X23 -> #REF! | S23: =SUM(Q23/E23)/X23 -> #REF! | T23: =(K23*102)/X23 -> 0 | U23: =SUM(L23*1963)/X23 -> 0 | V23: =SUM(Q23+T23+U23) -> #REF! | W23: =SUM(V23/E23)/T2 -> #REF! | X23: =SUM(X22) -> 1584 | Y23: 106 | Z23: =SUM(Y23-S23) -> #REF!
A24: =Gen!B30 -> 44063 | B24: 0 | C24: =Gen!C30 -> 0 | D24: =SUM(77*C24) -> 0 | F24: =Gen!U30 -> 0 | G24: =Gen!T30 -> 0 | H24: =[1]Gen!#REF! -> #REF! | I24: =SUM(G24:H24) -> #REF! | J24: =[1]Gen!AT30 -> 29403.3 | K24: ='Water-Meter'!E25 -> 0 | L24: ='Lpg (2)'!G29 -> 0 | M24: =#REF! -> #REF! | N24: =#REF! -> #REF! | O24: =#REF! -> #REF! | P24: =J24/52000 -> 0.56544808 | Q24: =I24*Q2 -> #REF! | R24: =SUM(Q24/D24)/X24 -> #REF! | S24: =SUM(Q24/E24)/X24 -> #REF! | T24: =(K24*102)/X24 -> 0 | U24: =SUM(L24*1963)/X24 -> 0 | V24: =SUM(Q24+T24+U24) -> #REF! | W24: =SUM(V24/E24)/T2 -> #REF! | X24: =SUM(X23) -> 1584 | Y24: 106 | Z24: =SUM(Y24-S24) -> #REF!
A25: =Gen!B31 -> 44064 | B25: 0 | C25: =Gen!C31 -> 0 | D25: =SUM(77*C25) -> 0 | F25: =Gen!U31 -> 0 | G25: =Gen!T31 -> 0 | H25: =[1]Gen!AJ31 -> 172.05 | I25: =SUM(G25:H25) -> 172.05 | J25: =[1]Gen!AT31 -> 41422.37 | K25: ='Water-Meter'!E26 -> 0 | L25: ='Lpg (2)'!G30 -> 0 | M25: =#REF! -> #REF! | N25: =#REF! -> #REF! | O25: =#REF! -> #REF! | P25: =J25/52000 -> 0.79658404 | Q25: =I25*Q2 -> 380204.69 | R25: =SUM(Q25/D25)/X25 -> #DIV/0! | S25: =SUM(Q25/E25)/X25 -> #DIV/0! | T25: =(K25*102)/X25 -> 0 | U25: =SUM(L25*1963)/X25 -> 0 | V25: =SUM(Q25+T25+U25) -> 380204.69 | W25: =SUM(V25/E25)/T2 -> #DIV/0! | X25: =SUM(X24) -> 1584 | Y25: 106 | Z25: =SUM(Y25-S25) -> #DIV/0!
A26: =Gen!B32 -> 44065 | B26: 0 | C26: =Gen!C32 -> 0 | D26: =SUM(77*C26) -> 0 | F26: =Gen!U32 -> 0 | G26: =Gen!T32 -> 0 | H26: =[1]Gen!AJ32 -> 18.63 | I26: =SUM(G26:H26) -> 18.63 | J26: =[1]Gen!AT32 -> 38988.16 | K26: ='Water-Meter'!E27 -> 0 | L26: ='Lpg (2)'!G31 -> 0 | M26: =#REF! -> #REF! | N26: =#REF! -> #REF! | O26: =#REF! -> #REF! | P26: =J26/52000 -> 0.74977231 | Q26: =I26*Q2 -> 41169.505 | R26: =SUM(Q26/D26)/X26 -> #DIV/0! | S26: =SUM(Q26/E26)/X26 -> #DIV/0! | T26: =(K26*102)/X26 -> 0 | U26: =SUM(L26*1963)/X26 -> 0 | V26: =SUM(Q26+T26+U26) -> 41169.505 | W26: =SUM(V26/E26)/T2 -> #DIV/0! | X26: =SUM(X25) -> 1584 | Y26: 106 | Z26: =SUM(Y26-S26) -> #DIV/0!
A27: =Gen!B33 -> 44066 | B27: 0 | C27: =Gen!C33 -> 0 | D27: =SUM(77*C27) -> 0 | F27: =Gen!U33 -> 0 | G27: =Gen!T33 -> 0 | H27: =[1]Gen!AJ33 -> 311.34 | I27: =SUM(G27:H27) -> 311.34 | J27: =[1]Gen!AT33 -> 36682.67 | K27: ='Water-Meter'!E28 -> 0 | L27: ='Lpg (2)'!G32 -> 0 | M27: =#REF! -> #REF! | N27: =#REF! -> #REF! | O27: =#REF! -> #REF! | P27: =J27/52000 -> 0.70543596 | Q27: =I27*Q2 -> 688014.7 | R27: =SUM(Q27/D27)/X27 -> #DIV/0! | S27: =SUM(Q27/E27)/X27 -> #DIV/0! | T27: =(K27*102)/X27 -> 0 | U27: =SUM(L27*1963)/X27 -> 0 | V27: =SUM(Q27+T27+U27) -> 688014.7 | W27: =SUM(V27/E27)/T2 -> #DIV/0! | X27: =SUM(X26) -> 1584 | Y27: 106 | Z27: =SUM(Y27-S27) -> #DIV/0!
A28: =Gen!B34 -> 44067 | B28: 0 | C28: =Gen!C34 -> 0 | D28: =SUM(77*C28) -> 0 | F28: =Gen!U34 -> 0 | G28: =Gen!T34 -> 0 | H28: =[1]Gen!AJ34 -> 380.7 | I28: =SUM(G28:H28) -> 380.7 | J28: =[1]Gen!AT34 -> 44223.03 | K28: ='Water-Meter'!E29 -> 0 | L28: ='Lpg (2)'!G33 -> 0 | M28: =#REF! -> #REF! | N28: =#REF! -> #REF! | O28: =#REF! -> #REF! | P28: =J28/52000 -> 0.85044288 | Q28: =I28*Q2 -> 841289.89 | R28: =SUM(Q28/D28)/X28 -> #DIV/0! | S28: =SUM(Q28/E28)/X28 -> #DIV/0! | T28: =(K28*102)/X28 -> 0 | U28: =SUM(L28*1963)/X28 -> 0 | V28: =SUM(Q28+T28+U28) -> 841289.89 | W28: =SUM(V28/E28)/T2 -> #DIV/0! | X28: =SUM(X27) -> 1584 | Y28: 106 | Z28: =SUM(Y28-S28) -> #DIV/0!
A29: =Gen!B35 -> 44068 | B29: 0 | C29: =Gen!C35 -> 0 | D29: =SUM(77*C29) -> 0 | F29: =Gen!U35 -> 0 | G29: =Gen!T35 -> 0 | H29: =[1]Gen!AJ35 -> 273.37 | I29: =SUM(G29:H29) -> 273.37 | J29: =[1]Gen!AT35 -> 41629.06 | K29: ='Water-Meter'!E30 -> 0 | L29: ='Lpg (2)'!G34 -> 0 | M29: =#REF! -> #REF! | N29: =#REF! -> #REF! | O29: =#REF! -> #REF! | P29: =J29/52000 -> 0.80055885 | Q29: =I29*Q2 -> 604106.69 | R29: =SUM(Q29/D29)/X29 -> #DIV/0! | S29: =SUM(Q29/E29)/X29 -> #DIV/0! | T29: =(K29*102)/X29 -> 0 | U29: =SUM(L29*1963)/X29 -> 0 | V29: =SUM(Q29+T29+U29) -> 604106.69 | W29: =SUM(V29/E29)/T2 -> #DIV/0! | X29: =SUM(X28) -> 1584 | Y29: 106 | Z29: =SUM(Y29-S29) -> #DIV/0!
A30: =Gen!B36 -> 44069 | B30: 0 | C30: =Gen!C36 -> 0 | D30: =SUM(77*C30) -> 0 | F30: =Gen!U36 -> 0 | G30: =Gen!T36 -> 0 | H30: =[1]Gen!AJ36 -> 396.56 | I30: =SUM(G30:H30) -> 396.56 | J30: =[1]Gen!AT36 -> 39251.17 | K30: ='Water-Meter'!E31 -> 0 | L30: ='Lpg (2)'!G35 -> 0 | M30: =#REF! -> #REF! | N30: =#REF! -> #REF! | O30: =#REF! -> #REF! | P30: =J30/52000 -> 0.75483019 | Q30: =I30*Q2 -> 876338.12 | R30: =SUM(Q30/D30)/X30 -> #DIV/0! | S30: =SUM(Q30/E30)/X30 -> #DIV/0! | T30: =(K30*102)/X30 -> 0 | U30: =SUM(L30*1963)/X30 -> 0 | V30: =SUM(Q30+T30+U30) -> 876338.12 | W30: =SUM(V30/E30)/T2 -> #DIV/0! | X30: =SUM(X29) -> 1584 | Y30: 106 | Z30: =SUM(Y30-S30) -> #DIV/0!
A31: =Gen!B37 -> 44070 | B31: 0 | C31: =Gen!C37 -> 0 | D31: =SUM(77*C31) -> 0 | F31: =Gen!U37 -> 0 | G31: =Gen!T37 -> 0 | H31: =[1]Gen!AJ37 -> 280.63 | I31: =SUM(G31:H31) -> 280.63 | J31: =[1]Gen!AT37 -> 36384.37 | K31: ='Water-Meter'!E32 -> 0 | L31: ='Lpg (2)'!G36 -> 0 | M31: =#REF! -> #REF! | N31: =#REF! -> #REF! | O31: =#REF! -> #REF! | P31: =J31/52000 -> 0.69969942 | Q31: =I31*Q2 -> 620150.21 | R31: =SUM(Q31/D31)/X31 -> #DIV/0! | S31: =SUM(Q31/E31)/X31 -> #DIV/0! | T31: =(K31*102)/X31 -> 0 | U31: =SUM(L31*1963)/X31 -> 0 | V31: =SUM(Q31+T31+U31) -> 620150.21 | W31: =SUM(V31/E31)/T2 -> #DIV/0! | X31: =SUM(X30) -> 1584 | Y31: 106 | Z31: =SUM(Y31-S31) -> #DIV/0!
A32: =Gen!B38 -> 44071 | B32: 0 | C32: =Gen!C38 -> 0 | D32: =SUM(77*C32) -> 0 | F32: =Gen!U38 -> 0 | G32: =Gen!T38 -> 0 | H32: =[1]Gen!AJ38 -> 0 | I32: =SUM(G32:H32) -> 0 | J32: =[1]Gen!AT38 -> 33780 | K32: ='Water-Meter'!E33 -> 0 | L32: ='Lpg (2)'!G37 -> 0 | M32: =#REF! -> #REF! | N32: =#REF! -> #REF! | O32: =#REF! -> #REF! | P32: =J32/52000 -> 0.64961538 | Q32: =I32*Q2 -> 0 | R32: =SUM(Q32/D32)/X32 -> #DIV/0! | S32: =SUM(Q32/E32)/X32 -> #DIV/0! | T32: =(K32*102)/X32 -> 0 | U32: =SUM(L32*1963)/X32 -> 0 | V32: =SUM(Q32+T32+U32) -> 0 | W32: =SUM(V32/E32)/T2 -> #DIV/0! | X32: =SUM(X31) -> 1584 | Y32: 106 | Z32: =SUM(Y32-S32) -> #DIV/0!
A33: =Gen!B39 -> 44072 | B33: 0 | C33: =Gen!C39 -> 0 | D33: =SUM(77*C33) -> 0 | F33: =Gen!U39 -> 0 | G33: =Gen!T39 -> 0 | H33: =[1]Gen!AJ39 -> 0 | I33: =SUM(G33:H33) -> 0 | J33: =[1]Gen!AT39 -> 33780 | K33: ='Water-Meter'!E34 -> 0 | L33: ='Lpg (2)'!G38 -> 0 | M33: =#REF! -> #REF! | N33: =#REF! -> #REF! | O33: =#REF! -> #REF! | P33: =J33/52000 -> 0.64961538 | Q33: =I33*Q2 -> 0 | R33: =SUM(Q33/D33)/X33 -> #DIV/0! | S33: =SUM(Q33/E33)/X33 -> #DIV/0! | T33: =(K33*102)/X33 -> 0 | U33: =SUM(L33*1963)/X33 -> 0 | V33: =SUM(Q33+T33+U33) -> 0 | W33: =SUM(V33/E33)/T2 -> #DIV/0! | X33: =SUM(X32) -> 1584 | Y33: 106 | Z33: =SUM(Y33-S33) -> #DIV/0!
A34: =Gen!B40 -> 44073 | B34: 0 | C34: =Gen!C40 -> 0 | D34: =SUM(77*C34) -> 0 | F34: =Gen!U40 -> 0 | G34: =Gen!T40 -> 0 | H34: =[1]Gen!AJ40 -> 0 | I34: =SUM(G34:H34) -> 0 | J34: =[1]Gen!AT40 -> 33780 | K34: ='Water-Meter'!E35 -> 0 | L34: ='Lpg (2)'!G39 -> 0 | M34: =#REF! -> #REF! | N34: =#REF! -> #REF! | O34: =#REF! -> #REF! | P34: =J34/52000 -> 0.64961538 | Q34: =I34*Q2 -> 0 | R34: =SUM(Q34/D34)/X34 -> #DIV/0! | S34: =SUM(Q34/E34)/X34 -> #DIV/0! | T34: =(K34*102)/X34 -> 0 | U34: =SUM(L34*1963)/X34 -> 0 | V34: =SUM(Q34+T34+U34) -> 0 | W34: =SUM(V34/E34)/T2 -> #DIV/0! | X34: =SUM(X33) -> 1584 | Y34: 106 | Z34: =SUM(Y34-S34) -> #DIV/0!
A35: =Gen!B41 -> 44074 | B35: 0 | C35: =Gen!C41 -> 0 | D35: =SUM(77*C35) -> 0 | F35: =Gen!U41 -> 0 | G35: =Gen!T41 -> 0 | H35: =[1]Gen!AJ41 -> 0 | I35: =SUM(G35:H35) -> 0 | J35: =[1]Gen!AT41 -> 33780 | K35: ='Water-Meter'!E36 -> 0 | L35: ='Lpg (2)'!G40 -> 0 | M35: =#REF! -> #REF! | N35: =#REF! -> #REF! | O35: =#REF! -> #REF! | P35: =J35/52000 -> 0.64961538 | Q35: =I35*Q2 -> 0 | R35: =SUM(Q35/D35)/X35 -> #DIV/0! | S35: =SUM(Q35/E35)/X35 -> #DIV/0! | T35: =(K35*102)/X35 -> 0 | U35: =SUM(L35*1963)/X35 -> 0 | V35: =SUM(Q35+T35+U35) -> 0 | W35: =SUM(V35/E35)/T2 -> #DIV/0! | X35: =SUM(X34) -> 1584 | Y35: 106 | Z35: =SUM(Y35-S35) -> #DIV/0!
K36: ='Water-Meter'!E37 -> 0 | Q36: =I36*2057.79 -> 0 | V36: =SUM(Q36+T36+U36) -> 0
K37: ='Water-Meter'!E38 -> 379 | S37: =SUM(S5:S16)/[1]Gen!A47 -> #REF!
B38: =SUM(B5:B37)/[1]Gen!A47 -> #REF! | M38: =0.5*2057.79 -> 1028.895
B39: =SUM(B38*[1]Gen!A47) -> #REF! | C39: =SUM(B39/250) -> #REF! | M39: =M38/1500 -> 0.68593 | O39: =(24*2.2)*2 -> 105.6 | P39: =O39*1029 -> 108662.4 | R39: Over budget | S39: =SUM(S37-Y35) -> #REF!
P40: =P39/K5 -> 2130.6353

Sheet VODACOM AND AIRTEL
A1: VODACOM AND AIRTEL KWH METER READING
B2: VODACOM TOWER | E2: AIRTEL TOWER
A3: DATE | B3: OPEN METER READING | C3: CLOSE METER READING | D3: UNIT CONSUMED | E3: OPEN METER READING | F3: CLOSE METER READING | G3: UNIT CONSUMED
A4: 42736 | B4: 24085 | C4: 25775 | D4: =C4-B4 -> 1690 | E4: 190896 | F4: 193152 | G4: =F4-E4 -> 2256
A5: 42767 | B5: =C4 -> 25775 | C5: 27592 | D5: =C5-B5 -> 1817 | E5: =F4 -> 193152 | F5: 195378 | G5: =F5-E5 -> 2226
A6: 42795 | B6: =C5 -> 27592 | C6: 29398 | D6: =C6-B6 -> 1806 | E6: =F5 -> 195378 | F6: 197503 | G6: =F6-E6 -> 2125
A7: 42826 | B7: =C6 -> 29398 | C7: 31148 | D7: =C7-B7 -> 1750 | E7: =F6 -> 197503 | F7: 199571 | G7: =F7-E7 -> 2068
A8: 42856 | B8: =C7 -> 31148 | C8: 32896 | D8: =C8-B8 -> 1748 | E8: =F7 -> 199571 | F8: 201766 | G8: =F8-E8 -> 2195
A9: 42887 | B9: =C8 -> 32896 | C9: 34620 | D9: =C9-B9 -> 1724 | E9: =F8 -> 201766 | F9: 203951 | G9: =F9-E9 -> 2185
A10: 42917 | B10: =C9 -> 34620 | C10: 36384 | D10: =C10-B10 -> 1764 | E10: =F9 -> 203951 | F10: 206045 | G10: =F10-E10 -> 2094
A11: 42948 | B11: =C10 -> 36384 | C11: 38320 | D11: =C11-B11 -> 1936 | E11: =F10 -> 206045 | F11: 208289 | G11: =F11-E11 -> 2244
A12: 42979 | B12: =C11 -> 38320 | C12: 40226 | D12: =C12-B12 -> 1906 | E12: =F11 -> 208289 | F12: 210468 | G12: =F12-E12 -> 2179
A13: 43009 | B13: =C12 -> 40226 | C13: 41900 | D13: =C13-B13 -> 1674 | E13: =F12 -> 210468 | F13: 212474 | G13: =F13-E13 -> 2006
A14: 43040 | B14: =C13 -> 41900 | C14: 43712 | D14: =C14-B14 -> 1812 | E14: =F13 -> 212474 | F14: 214566 | G14: =F14-E14 -> 2092
A15: 43070 | B15: =C14 -> 43712 | C15: 46071 | D15: =C15-B15 -> 2359 | E15: =F14 -> 214566 | F15: 216654 | G15: =F15-E15 -> 2088
A16: 43101 | B16: =C15 -> 46071 | C16: 48188 | D16: =C16-B16 -> 2117 | E16: =F15 -> 216654 | F16: 218779 | G16: =F16-E16 -> 2125
... A44: 43952 | B44: =C43 -> 102607 | C44: 104898 | D44: =C44-B44 -> 2291 | E44: =F43 -> 276874 | F44: 279093 | G44: =F44-E44 -> 2219
A45: 43983 | B45: =C44 -> 104898 | D45: =C45-B45 -> -104898 | E45: =F44 -> 279093 | G45: =F45-E45 -> -279093
A46: 44013 | B46: =C45 -> 0 | D46: =C46-B46 -> 0 | E46: =F45 -> 0 | G46: =F46-E46 -> 0
A47: 44044 | B47: =C46 -> 0 | D47: =C47-B47 -> 0 | E47: =F46 -> 0 | G47: =F47-E47 -> 0
A48: 44075 | B48: =C47 -> 0 | D48: =C48-B48 -> 0 | E48: =F47 -> 0 | G48: =F48-E48 -> 0
A49: 44105 | B49: =C48 -> 0 | D49: =C49-B49 -> 0 | E49: =F48 -> 0 | G49: =F49-E49 -> 0
A50: 44136 | B50: =C49 -> 0 | D50: =C50-B50 -> 0 | E50: =F49 -> 0 | G50: =F50-E50 -> 0
A51: 44166 | B51: =C50 -> 0 | D51: =C51-B51 -> 0 | E51: =F50 -> 0 | G51: =F51-E51 -> 0
A52: 44197 | B52: =C51 -> 0 | D52: =C52-B52 -> 0 | E52: =F51 -> 0 | G52: =F52-E52 -> 0
A53: 44228 | B53: =C52 -> 0 | D53: =C53-B53 -> 0 | E53: =F52 -> 0 | G53: =F53-E53 -> 0
A54: 44256 | B54: =C53 -> 0 | D54: =C54-B54 -> 0 | E54: =F53 -> 0 | G54: =F54-E54 -> 0
A55: 44287 | B55: =C54 -> 0 | D55: =C55-B55 -> 0 | E55: =F54 -> 0 | G55: =F55-E55 -> 0
A56: 44317 | B56: =C55 -> 0 | D56: =C56-B56 -> 0 | E56: =F55 -> 0 | G56: =F56-E56 -> 0
... A78: 44986 | B78: =C77 -> 0 | D78: =C78-B78 -> 0 | E78: =F77 -> 0 | G78: =F78-E78 -> 0

Sheet FUEL METER READING
A1: FUEL METER 1 READNG | H1: FUEL METER 2 READING
A2: DATE | B2: OPEN METER READING | C2: CLOSE METER READING | D2: Diesel consumed | E2: HLP-GENSETS | F2: DIFFERENCE | G2: OPEN METER | H2: CLOSE METER | I2: DIESEL CONSUMED | J2: HLP-VEHICLES | K2: DIFFERENCE | L2: TOTAL DIESEL CONS.
A3: 42736 | B3: 5670348 | C3: 5735627 | D3: =C3-B3 -> 65279 | E3: 65276.07 | F3: =D3-E3 -> 2.93 | G3: 0 | I3: =H3-G3 -> 0 | K3: =I3-J3 -> 0
A4: 42767 | B4: =C3 -> 5735627 | C4: 5797781 | D4: =C4-B4 -> 62154 | E4: 62154.9 | F4: =D4-E4 -> -0.9 | G4: =H3 -> 0 | I4: =H4-G4 -> 0 | K4: =I4-J4 -> 0
A5: 42795 | B5: =C4 -> 5797781 | C5: 5864602 | D5: =C5-B5 -> 66821 | E5: 66820.89 | F5: =D5-E5 -> 0.11 | G5: =H4 -> 0 | I5: =H5-G5 -> 0 | K5: =I5-J5 -> 0
A6: 42826 | B6: =C5 -> 5864602 | C6: 5927895 | D6: =C6-B6 -> 63293 | E6: 63292.38 | F6: =D6-E6 -> 0.62 | G6: =H5 -> 0 | I6: =H6-G6 -> 0 | K6: =I6-J6 -> 0
A7: 42856 | B7: =C6 -> 5927895 | C7: 5995212 | D7: =C7-B7 -> 67317 | E7: 67313.47 | F7: =D7-E7 -> 3.53 | G7: =H6 -> 0 | I7: =H7-G7 -> 0 | K7: =I7-J7 -> 0
A8: 42887 | B8: =C7 -> 5995212 | C8: 6065754 | D8: =C8-B8 -> 70542 | E8: 70542.6 | F8: =D8-E8 -> -0.6 | G8: =H7 -> 0 | I8: =H8-G8 -> 0 | K8: =I8-J8 -> 0
A9: 42917 | B9: =C8 -> 6065754 | C9: 6141089 | D9: =C9-B9 -> 75335 | E9: 75335 | F9: =D9-E9 -> 0 | G9: 2442 | H9: 15003 | I9: =H9-G9 -> 12561 | K9: =I9-J9 -> 12561
A10: 42948 | B10: =C9 -> 6141089 | C10: 6212470 | D10: =C10-B10 -> 71381 | E10: 71379.9 | F10: =D10-E10 -> 1.1 | G10: =H9 -> 15003 | H10: 25033 | I10: =H10-G10 -> 10030 | J10: 10029.74 | K10: =I10-J10 -> 0.26 | L10: =I10+D10 -> 81411
A11: 42979 | B11: =C10 -> 6212470 | C11: 6276921 | D11: =C11-B11 -> 64451 | E11: 64450.62 | F11: =D11-E11 -> 0.38 | G11: =H10 -> 25033 | H11: 32815 | I11: =H11-G11 -> 7782 | J11: 7781.72 | K11: =I11-J11 -> 0.28 | L11: =I11+D11 -> 72233
A12: 43009 | B12: =C11 -> 6276921 | C12: 6352831 | D12: =C12-B12 -> 75910 | E12: 75906.79 | F12: =D12-E12 -> 3.21 | G12: =H11 -> 32815 | H12: 39587 | I12: =H12-G12 -> 6772 | J12: 6772.04 | K12: =I12-J12 -> -0.04 | L12: =I12+D12 -> 82682
A13: 43040 | B13: =C12 -> 6352831 | C13: 6410003 | D13: =C13-B13 -> 57172 | E13: 57171.51 | F13: =D13-E13 -> 0.49 | G13: =H12 -> 39587 | H13: 45717 | I13: =H13-G13 -> 6130 | J13: 6129.55 | K13: =I13-J13 -> 0.45 | L13: =I13+D13 -> 63302
A14: 43070 | B14: =C13 -> 6410003 | C14: 6476953 | D14: =C14-B14 -> 66950 | E14: 66951.14 | F14: =D14-E14 -> -1.14 | G14: =H13 -> 45717 | H14: 52890 | I14: =H14-G14 -> 7173 | J14: 7173.94 | K14: =I14-J14 -> -0.94 | L14: =I14+D14 -> 74123
A15: 43101 | B15: =C14 -> 6476953 | C15: 6542879 | D15: =C15-B15 -> 65926 | E15: 65927.77 | F15: =D15-E15 -> -1.77 | G15: =H14 -> 52890 | H15: 59763 | I15: =H15-G15 -> 6873 | J15: 6874.87 | K15: =I15-J15 -> -1.87 | L15: =I15+D15 -> 72799
A16: 43132 | B16: =C15 -> 6542879 | C16: 6604433 | D16: =C16-B16 -> 61554 | E16: 61553.03 | F16: =D16-E16 -> 0.97 | G16: =H15 -> 59763 | H16: 66652 | I16: =H16-G16 -> 6889 | J16: 6890.89 | K16: =I16-J16 -> -1.89 | L16: =I16+D16 -> 68443
A17: 43160 | B17: =C16 -> 6604433 | C17: 6660226 | D17: =C17-B17 -> 55793 | E17: 55792.75 | F17: =D17-E17 -> 0.25 | G17: =H16 -> 66652 | H17: 77607 | I17: =H17-G17 -> 10955 | J17: 10955.45 | K17: =I17-J17 -> -0.45 | L17: =I17+D17 -> 66748
A18: 43191 | B18: =C17 -> 6660226 | C18: 6714539 | D18: =C18-B18 -> 54313 | E18: 54312.28 | F18: =D18-E18 -> 0.72 | G18: =H17 -> 77607 | H18: 82271 | I18: =H18-G18 -> 4664 | J18: 4665.22 | K18: =I18-J18 -> -1.22 | L18: =I18+D18 -> 58977
A19: 43221 | B19: =C18 -> 6714539 | C19: 6774547 | D19: =C19-B19 -> 60008 | E19: 60007.47 | F19: =D19-E19 -> 0.53 | G19: =H18 -> 82271 | H19: 88664 | I19: =H19-G19 -> 6393 | J19: 6392.14 | K19: =I19-J19 -> 0.86 | L19: =I19+D19 -> 66401
A20: 43252 | B20: =C19 -> 6774547 | C20: 6845214 | D20: =C20-B20 -> 70667 | E20: 70666.29 | F20: =D20-E20 -> 0.71 | G20: =H19 -> 88664 | H20: 99683 | I20: =H20-G20 -> 11019 | J20: 11020.51 | K20: =I20-J20 -> -1.51 | L20: =I20+D20 -> 81686
A21: 43282 | B21: =C20 -> 6845214 | C21: 6921964 | D21: =C21-B21 -> 76750 | E21: 76750.25 | F21: =D21-E21 -> -0.25 | G21: =H20 -> 99683 | H21: 107936 | I21: =H21-G21 -> 8253 | J21: 8252.24 | K21: =I21-J21 -> 0.76 | L21: =I21+D21 -> 85003
... A45: 44013 | B45: =C44 -> 8379633 | C45: 8401424 | D45: =C45-B45 -> 21791 | E45: 21791.54 | F45: =D45-E45 -> -0.54 | G45: =H44 -> 266245 | H45: 267428 | I45: =H45-G45 -> 1183 | J45: 1182.19 | K45: =I45-J45 -> 0.81 | L45: =I45+D45 -> 22974
A46: 44044 | B46: =C45 -> 8401424 | D46: =C46-B46 -> -8401424 | F46: =D46-E46 -> -8401424 | G46: =H45 -> 267428 | I46: =H46-G46 -> -267428 | K46: =I46-J46 -> -267428 | L46: =I46+D46 -> -8668852
A47: 44075 | B47: =C46 -> 0 | D47: =C47-B47 -> 0 | F47: =D47-E47 -> 0 | G47: =H46 -> 0 | I47: =H47-G47 -> 0 | K47: =I47-J47 -> 0 | L47: =I47+D47 -> 0
A48: 44105 | B48: =C47 -> 0 | D48: =C48-B48 -> 0 | F48: =D48-E48 -> 0 | G48: =H47 -> 0 | I48: =H48-G48 -> 0 | K48: =I48-J48 -> 0 | L48: =I48+D48 -> 0
A49: 44136 | B49: =C48 -> 0 | D49: =C49-B49 -> 0 | F49: =D49-E49 -> 0 | G49: =H48 -> 0 | I49: =H49-G49 -> 0 | K49: =I49-J49 -> 0 | L49: =I49+D49 -> 0
A50: 44166 | B50: =C49 -> 0 | D50: =C50-B50 -> 0 | F50: =D50-E50 -> 0 | G50: =H49 -> 0 | I50: =H50-G50 -> 0 | K50: =I50-J50 -> 0 | L50: =I50+D50 -> 0
A51: 44197 | B51: =C50 -> 0 | D51: =C51-B51 -> 0 | F51: =D51-E51 -> 0 | G51: =H50 -> 0 | I51: =H51-G51 -> 0 | K51: =I51-J51 -> 0 | L51: =I51+D51 -> 0
A52: 44228 | B52: =C51 -> 0 | D52: =C52-B52 -> 0 | F52: =D52-E52 -> 0 | G52: =H51 -> 0 | I52: =H52-G52 -> 0 | K52: =I52-J52 -> 0 | L52: =I52+D52 -> 0
A53: 44256 | B53: =C52 -> 0 | D53: =C53-B53 -> 0 | F53: =D53-E53 -> 0 | G53: =H52 -> 0 | I53: =H53-G53 -> 0 | K53: =I53-J53 -> 0 | L53: =I53+D53 -> 0
A54: 44287 | B54: =C53 -> 0 | D54: =C54-B54 -> 0 | F54: =D54-E54 -> 0 | G54: =H53 -> 0 | I54: =H54-G54 -> 0 | K54: =I54-J54 -> 0 | L54: =I54+D54 -> 0
A55: 44317 | B55: =C54 -> 0 | D55: =C55-B55 -> 0 | F55: =D55-E55 -> 0 | G55: =H54 -> 0 | I55: =H55-G55 -> 0 | K55: =I55-J55 -> 0 | L55: =I55+D55 -> 0
A56: 44348 | B56: =C55 -> 0 | D56: =C56-B56 -> 0 | F56: =D56-E56 -> 0 | G56: =H55 -> 0 | I56: =H56-G56 -> 0 | K56: =I56-J56 -> 0 | L56: =I56+D56 -> 0
A57: 44378 | B57: =C56 -> 0 | D57: =C57-B57 -> 0 | F57: =D57-E57 -> 0 | G57: =H56 -> 0 | I57: =H57-G57 -> 0 | K57: =I57-J57 -> 0 | L57: =I57+D57 -> 0
... A77: 44986 | B77: =C76 -> 0 | D77: =C77-B77 -> 0 | F77: =D77-E77 -> 0 | G77: =H76 -> 0 | I77: =H77-G77 -> 0 | K77: =I77-J77 -> 0 | L77: =I77+D77 -> 0
B94: DIESEL PUMP 01 READINGS | H94: DIESEL PUMP 02 READINGS

Sheet Daily utility report 
A1: DAILY UTILITIES REPORT
A2: =A5 -> 44044
A3: DATE | B3: OCC % | D3: GENERATOR FUEL (LTR) | F3: WATER (M³) | I3: ELECTRICAL (Kwh)
C4: VEHICLE CONSUMPTION | D4: CONSUMPTION | E4: BALANCE | F4: CONSUMPTION | G4: BOREHOLE PRODUCTION | H4: RO PRODUCTION | I4: KITCHEN | J4: LAUNDRY
A5: =Gen!B11 -> 44044 | B5: =Gen!C11 -> 0 | C5: =Gen!AK11 -> 16.85 | D5: =Gen!T11 -> 741.42 | E5: =Gen!D11 -> 41431.87 | F5: ='Water-Meter'!E6 -> 51 | G5: ='Water-Meter'!AN6 -> 170 | H5: ='Utility report '!AC6 -> 78 | I5: ='Kit report'!F4 -> 144 | J5: ='Kit report'!X4 -> 20
A6: =Gen!B12 -> 44045 | B6: =Gen!C12 -> 0 | C6: =Gen!AK12 -> 0 | D6: =Gen!T12 -> 782.06 | E6: =Gen!D12 -> 40673.6 | F6: ='Water-Meter'!E7 -> 53 | G6: ='Water-Meter'!AN7 -> 185 | H6: ='Utility report '!AC7 -> 156 | I6: ='Kit report'!F5 -> 168 | J6: ='Kit report'!X5 -> 40
A7: =Gen!B13 -> 44046 | B7: =Gen!C13 -> 0 | C7: =Gen!AK13 -> 25.31 | D7: =Gen!T13 -> 788.41 | E7: =Gen!D13 -> 39891.54 | F7: ='Water-Meter'!E8 -> 42 | G7: ='Water-Meter'!AN8 -> 155 | H7: ='Utility report '!AC8 -> 0 | I7: ='Kit report'!F6 -> 132 | J7: ='Kit report'!X6 -> 20
A8: =Gen!B14 -> 44047 | B8: =Gen!C14 -> 0 | C8: =Gen!AK14 -> 149.86 | D8: =Gen!T14 -> 793.61 | E8: =Gen!D14 -> 39077.82 | F8: ='Water-Meter'!E9 -> 67 | G8: ='Water-Meter'!AN9 -> 142 | H8: ='Utility report '!AC9 -> 55 | I8: ='Kit report'!F7 -> 180 | J8: ='Kit report'!X7 -> 20
A9: =Gen!B15 -> 44048 | B9: =Gen!C15 -> 0 | C9: =Gen!AK15 -> 87.31 | D9: =Gen!T15 -> 776.02 | E9: =Gen!D15 -> 38134.35 | F9: ='Water-Meter'!E10 -> 49 | G9: ='Water-Meter'!AN10 -> 143 | H9: ='Utility report '!AC10 -> 56 | I9: ='Kit report'!F8 -> 168 | J9: ='Kit report'!X8 -> 20
A10: =Gen!B16 -> 44049 | B10: =Gen!C16 -> 0 | C10: =Gen!AK16 -> 52.6 | D10: =Gen!T16 -> 778.12 | E10: =Gen!D16 -> 37271.02 | F10: ='Water-Meter'!E11 -> 66 | G10: ='Water-Meter'!AN11 -> 145 | H10: ='Utility report '!AC11 -> 50 | I10: ='Kit report'!F9 -> 156 | J10: ='Kit report'!X9 -> 40
A11: =Gen!B17 -> 44050 | B11: =Gen!C17 -> 0 | C11: =Gen!AK17 -> 0 | D11: =Gen!T17 -> 771.7 | E11: =Gen!D17 -> 36440.3 | F11: ='Water-Meter'!E12 -> 51 | G11: ='Water-Meter'!AN12 -> 140 | H11: ='Utility report '!AC12 -> 55 | I11: ='Kit report'!F10 -> 156 | J11: ='Kit report'!X10 -> 40
A12: =Gen!B18 -> 44051 | B12: =Gen!C18 -> 0 | C12: =Gen!AK18 -> 0 | D12: =Gen!T18 -> 0 | E12: =Gen!D18 -> 35668.6 | F12: ='Water-Meter'!E13 -> 0 | G12: ='Water-Meter'!AN13 -> -14679 | H12: ='Utility report '!AC13 -> -36392 | I12: ='Kit report'!F11 -> -1051188 | J12: ='Kit report'!X11 -> -1562620
A13: =Gen!B19 -> 44052 | B13: =Gen!C19 -> 0 | C13: =Gen!AK19 -> 0 | D13: =Gen!T19 -> 0 | E13: =Gen!D19 -> 35668.6 | F13: ='Water-Meter'!E14 -> 0 | G13: ='Water-Meter'!AN14 -> 0 | H13: ='Utility report '!AC14 -> 0 | I13: ='Kit report'!F12 -> 0 | J13: ='Kit report'!X12 -> 0
A14: =Gen!B20 -> 44053 | B14: =Gen!C20 -> 0 | C14: =Gen!AK20 -> 0 | D14: =Gen!T20 -> 0 | E14: =Gen!D20 -> 35668.6 | F14: ='Water-Meter'!E15 -> 0 | G14: ='Water-Meter'!AN15 -> 0 | H14: ='Utility report '!AC15 -> 0 | I14: ='Kit report'!F13 -> 0 | J14: ='Kit report'!X13 -> 0
A15: =Gen!B21 -> 44054 | B15: =Gen!C21 -> 0 | C15: =Gen!AK21 -> 0 | D15: =Gen!T21 -> 0 | E15: =Gen!D21 -> 35668.6 | F15: ='Water-Meter'!E16 -> 0 | G15: ='Water-Meter'!AN16 -> 0 | H15: ='Utility report '!AC16 -> 0 | I15: ='Kit report'!F14 -> 0 | J15: ='Kit report'!X14 -> 0
A16: =Gen!B22 -> 44055 | B16: =Gen!C22 -> 0 | C16: =Gen!AK22 -> 0 | D16: =Gen!T22 -> 0 | E16: =Gen!D22 -> 35668.6 | F16: ='Water-Meter'!E17 -> 0 | G16: ='Water-Meter'!AN17 -> 0 | H16: ='Utility report '!AC17 -> 0 | I16: ='Kit report'!F15 -> 0 | J16: ='Kit report'!X15 -> 0
... A27: =Gen!B33 -> 44066 | B27: =Gen!C33 -> 0 | C27: =Gen!AK33 -> 0 | D27: =Gen!T33 -> 0 | E27: =Gen!D33 -> 35668.6 | F27: ='Water-Meter'!E28 -> 0 | G27: ='Water-Meter'!AN28 -> 0 | H27: ='Utility report '!AC28 -> 0 | I27: ='Kit report'!F26 -> 0 | J27: ='Kit report'!X26 -> 0
A28: =Gen!B34 -> 44067 | B28: 0.091 | C28: =Gen!AK34 -> 0 | D28: =Gen!T34 -> 0 | E28: =Gen!D34 -> 35668.6 | F28: ='Water-Meter'!E29 -> 0 | G28: ='Water-Meter'!AN29 -> 0 | H28: ='Utility report '!AC29 -> 0 | I28: ='Kit report'!F27 -> 0 | J28: ='Kit report'!X27 -> 0
A29: =Gen!B35 -> 44068 | B29: =Gen!C35 -> 0 | C29: =Gen!AK35 -> 0 | D29: =Gen!T35 -> 0 | E29: =Gen!D35 -> 35668.6 | F29: ='Water-Meter'!E30 -> 0 | G29: ='Water-Meter'!AN30 -> 0 | H29: ='Utility report '!AC30 -> 0 | I29: ='Kit report'!F28 -> 0 | J29: ='Kit report'!X28 -> 0
A30: =Gen!B36 -> 44069 | B30: =Gen!C36 -> 0 | C30: =Gen!AK36 -> 0 | D30: =Gen!T36 -> 0 | E30: =Gen!D36 -> 35668.6 | F30: ='Water-Meter'!E31 -> 0 | G30: ='Water-Meter'!AN31 -> 0 | H30: ='Utility report '!AC31 -> 0 | I30: ='Kit report'!F29 -> 0 | J30: ='Kit report'!X29 -> 0
A31: =Gen!B37 -> 44070 | B31: =Gen!C37 -> 0 | C31: =Gen!AK37 -> 0 | D31: =Gen!T37 -> 0 | E31: =Gen!D37 -> 35668.6 | F31: ='Water-Meter'!E32 -> 0 | G31: ='Water-Meter'!AN32 -> 0 | H31: ='Utility report '!AC32 -> 0 | I31: ='Kit report'!F30 -> 0 | J31: ='Kit report'!X30 -> 0
A32: =Gen!B38 -> 44071 | B32: =Gen!C38 -> 0 | C32: =Gen!AK38 -> 0 | D32: =Gen!T38 -> 0 | E32: =Gen!D38 -> 35668.6 | F32: ='Water-Meter'!E33 -> 0 | G32: ='Water-Meter'!AN33 -> 0 | H32: ='Utility report '!AC33 -> 0 | I32: ='Kit report'!F31 -> 0 | J32: ='Kit report'!X31 -> 0
A33: =Gen!B39 -> 44072 | B33: =Gen!C39 -> 0 | C33: =Gen!AK39 -> 0 | D33: =Gen!T39 -> 0 | E33: =Gen!D39 -> 35668.6 | F33: ='Water-Meter'!E34 -> 0 | G33: ='Water-Meter'!AN34 -> 0 | H33: ='Utility report '!AC34 -> 0 | I33: ='Kit report'!F32 -> 0 | J33: ='Kit report'!X32 -> 0
A34: =Gen!B40 -> 44073 | B34: =Gen!C40 -> 0 | C34: =Gen!AK40 -> 0 | D34: =Gen!T40 -> 0 | E34: =Gen!D40 -> 35668.6 | F34: ='Water-Meter'!E35 -> 0 | G34: ='Water-Meter'!AN35 -> 0 | H34: ='Utility report '!AC35 -> 0 | I34: ='Kit report'!F33 -> 0 | J34: ='Kit report'!X33 -> 0
A35: =Gen!B41 -> 44074 | B35: =Gen!C41 -> 0 | C35: =Gen!AK41 -> 0 | D35: =Gen!T41 -> 0 | E35: =Gen!D41 -> 35668.6 | F35: ='Water-Meter'!E36 -> 0 | G35: ='Water-Meter'!AN36 -> 0 | H35: ='Utility report '!AC36 -> 0 | I35: ='Kit report'!F34 -> 0 | J35: ='Kit report'!X34 -> 0
C36: =Gen!AK42 -> 0 | D36: =Gen!T42 -> 0 | E36: =Gen!D42 -> 35668.6 | F36: ='Water-Meter'!E37 -> 0 | G36: ='Water-Meter'!AN37 -> 610 | H36: ='Utility report '!AC37 -> 0 | I36: ='Kit report'!F35 -> 444 | J36: ='Kit report'!X35 -> 0
