Workbook

Sheet Total
A1: Site Name | B1: Day | C1: Month | D1: Year | E1: Total Electricity Kwh | F1: Electricity Tariff ($/Kwh) | G1: Total Fuel Oil (Liters) | H1: Fuel Oil $/Liter | I1: LPG (Kg) | J1: LPG $/Kg | K1: Water Utility Supply (m3) m3 | L1: Water Utility Supply (m3) $/m3 | M1: Irrigation Water (m3) m3 | N1: Irrigation water $/m3 | O1: Room Nights
A2: Beirut | B2: 1 | C2: 8 | D2: 2020 | E2: =ELEC!N3 -> 25351 | F2: =SUM('EDl log'!T4) -> 0.14031446 | G2: =-tanks!AW6 -> 380 | H2: =SUM(tanks!AV6) -> 0.5383 | I2: =('B5'!AU5)*0.51 -> 76.5 | J2: ='B5'!AX5/0.51 -> 1.5686275 | K2: =WATER!I6 -> 494 | L2: =SUM(WATER!J6) -> 0.69808802 | M2: =WATER!Q6 -> 0 | N2: 0.6 | O2: =ELEC!B3 -> 89.01
A3: Beirut | B3: =B2+1 -> 2 | C3: 8 | D3: 2020 | E3: =ELEC!N4 -> 24732 | F3: =SUM('EDl log'!T5) -> 0.092087922 | G3: =-tanks!AW7 -> 229 | H3: =SUM(tanks!AV7) -> 0.5383 | I3: =('B5'!AU6)*0.51 -> 183.6 | J3: ='B5'!AX6/0.51 -> 1.5686275 | K3: =WATER!I7 -> 0 | L3: =SUM(WATER!J7) -> 0 | M3: =WATER!Q7 -> 0 | N3: 0.6 | O3: =ELEC!B4 -> 77.993
A4: Beirut | B4: =B3+1 -> 3 | C4: 8 | D4: 2020 | E4: =ELEC!N5 -> 23757 | F4: =SUM('EDl log'!T6) -> 0.097640186 | G4: =-tanks!AW8 -> 680 | H4: =SUM(tanks!AV8) -> 0.54 | I4: =('B5'!AU7)*0.51 -> 183.6 | J4: ='B5'!AX7/0.51 -> 1.5686275 | K4: =WATER!I8 -> 366 | L4: =SUM(WATER!J8) -> 0.66102591 | M4: =WATER!Q8 -> 0 | N4: 0.6 | O4: =ELEC!B5 -> 69
A5: Beirut | B5: =B4+1 -> 4 | C5: 8 | D5: 2020 | E5: =ELEC!N6 -> 25244 | F5: =SUM('EDl log'!T7) -> 0.05481389 | G5: =-tanks!AW9 -> 0 | H5: =SUM(tanks!AV9) -> 0.54 | I5: =('B5'!AU8)*0.51 -> 0 | J5: ='B5'!AX8/0.51 -> 1.5686275 | K5: =WATER!I9 -> 0 | L5: =SUM(WATER!J9) -> 0 | M5: =WATER!Q9 -> 0 | N5: 0.6 | O5: =ELEC!B6 -> 0
A6: Beirut | B6: =B5+1 -> 5 | C6: 8 | D6: 2020 | E6: =ELEC!N7 -> 10988 | F6: =SUM('EDl log'!T8) -> 0.25447665 | G6: =-tanks!AW10 -> 144 | H6: =SUM(tanks!AV10) -> 0.54 | I6: =('B5'!AU9)*0.51 -> 0 | J6: ='B5'!AX9/0.51 -> 1.5686275 | K6: =WATER!I10 -> 172 | L6: =SUM(WATER!J10) -> 2.0049737 | M6: =WATER!Q10 -> 0 | N6: 0.6 | O6: =ELEC!B7 -> 0
A7: Beirut | B7: =B6+1 -> 6 | C7: 8 | D7: 2020 | E7: =ELEC!N8 -> 10699 | F7: =SUM('EDl log'!T9) -> 0.05068698 | G7: =-tanks!AW11 -> 0 | H7: =SUM(tanks!AV11) -> 0.54 | I7: =('B5'!AU10)*0.51 -> 0 | J7: ='B5'!AX10/0.51 -> 1.5686275 | K7: =WATER!I11 -> 0 | L7: =SUM(WATER!J11) -> 0 | M7: =WATER!Q11 -> 0 | N7: 0.6 | O7: =ELEC!B8 -> 0
A8: Beirut | B8: =B7+1 -> 7 | C8: 8 | D8: 2020 | E8: =ELEC!N9 -> 9781 | F8: =SUM('EDl log'!T10) -> -0.054155968 | G8: =-tanks!AW12 -> 0 | H8: =SUM(tanks!AV12) -> 0.535 | I8: =('B5'!AU11)*0.51 -> 0 | J8: ='B5'!AX11/0.51 -> 1.5686275 | K8: =WATER!I12 -> 0 | L8: =SUM(WATER!J12) -> 0 | M8: =WATER!Q12 -> 0 | N8: 0.6 | O8: =ELEC!B9 -> 0
A9: Beirut | B9: =B8+1 -> 8 | C9: 8 | D9: 2020 | E9: =ELEC!N10 -> 10647 | F9: =SUM('EDl log'!T11) -> 0.10342312 | G9: =-tanks!AW13 -> 0 | H9: =SUM(tanks!AV13) -> 0.535 | I9: =('B5'!AU12)*0.51 -> 0 | J9: ='B5'!AX12/0.51 -> 1.5686275 | K9: =WATER!I13 -> 0 | L9: =SUM(WATER!J13) -> 0 | M9: =WATER!Q13 -> 0 | N9: 0.6 | O9: =ELEC!B10 -> 0
A10: Beirut | B10: =B9+1 -> 9 | C10: 8 | D10: 2020 | E10: =ELEC!N11 -> 8400 | F10: =SUM('EDl log'!T12) -> 0.086638155 | G10: =-tanks!AW14 -> 0 | H10: =SUM(tanks!AV14) -> 0.535 | I10: =('B5'!AU13)*0.51 -> 0 | J10: ='B5'!AX13/0.51 -> 1.5686275 | K10: =WATER!I14 -> 0 | L10: =SUM(WATER!J14) -> 0 | M10: =WATER!Q14 -> 0 | N10: 0.6 | O10: =ELEC!B11 -> 0
A11: Beirut | B11: =B10+1 -> 10 | C11: 8 | D11: 2020 | E11: =ELEC!N12 -> 10457 | F11: =SUM('EDl log'!T13) -> 0.072990145 | G11: =-tanks!AW15 -> 0 | H11: =SUM(tanks!AV15) -> 0.535 | I11: =('B5'!AU14)*0.51 -> 0 | J11: ='B5'!AX14/0.51 -> 1.5686275 | K11: =WATER!I15 -> 0 | L11: =SUM(WATER!J15) -> 0 | M11: =WATER!Q15 -> 0 | N11: 0.6 | O11: =ELEC!B12 -> 0
A12: Beirut | B12: =B11+1 -> 11 | C12: 8 | D12: 2020 | E12: =ELEC!N13 -> 10265 | F12: =SUM('EDl log'!T14) -> 0.074713175 | G12: =-tanks!AW16 -> 115.2 | H12: =SUM(tanks!AV16) -> 0.535 | I12: =('B5'!AU15)*0.51 -> 0 | J12: ='B5'!AX15/0.51 -> 1.5686275 | K12: =WATER!I16 -> 0 | L12: =SUM(WATER!J16) -> 0 | M12: =WATER!Q16 -> 0 | N12: 0.6 | O12: =ELEC!B13 -> 0
A13: Beirut | B13: =B12+1 -> 12 | C13: 8 | D13: 2020 | E13: =ELEC!N14 -> 10779 | F13: =SUM('EDl log'!T15) -> 0.13059941 | G13: =-tanks!AW17 -> 0 | H13: =SUM(tanks!AV17) -> 0.535 | I13: =('B5'!AU16)*0.51 -> 0 | J13: ='B5'!AX16/0.51 -> 1.5686275 | K13: =WATER!I17 -> 0 | L13: =SUM(WATER!J17) -> 0 | M13: =WATER!Q17 -> 0 | N13: 0.6 | O13: =ELEC!B14 -> 0
A14: Beirut | B14: =B13+1 -> 13 | C14: 8 | D14: 2020 | E14: =ELEC!N15 -> 11455 | F14: =SUM('EDl log'!T16) -> 0.039500481 | G14: =-tanks!AW18 -> 0 | H14: =SUM(tanks!AV18) -> 0.535 | I14: =('B5'!AU17)*0.51 -> 0 | J14: ='B5'!AX17/0.51 -> 1.5686275 | K14: =WATER!I18 -> 0 | L14: =SUM(WATER!J18) -> 0 | M14: =WATER!Q18 -> 0 | N14: 0.6 | O14: =ELEC!B15 -> 0
... A32: Beirut | B32: =B31+1 -> 31 | C32: 8 | D32: 2020 | E32: =ELEC!N33 -> 0 | F32: =SUM('EDl log'!T34) -> 0 | G32: =-tanks!AW36 -> 0 | H32: =SUM(tanks!AV36) -> 0.535 | I32: =('B5'!AU35)*0.51 -> 0 | J32: ='B5'!AX35/0.51 -> 1.5686275 | K32: =WATER!I36 -> 0 | L32: =SUM(WATER!J36) -> 0 | M32: =WATER!Q36 -> 0 | N32: 0.6 | O32: =ELEC!B33 -> 0

Sheet Submetering
A1: Site Name | B1: Day | C1: Month | D1: Year | E1: ATS1 Kwh | F1: ATS2 Kwh | G1: ATS3 Kwh | H1: ATS4 Kwh | I1: ATS5 Kwh | J1: Guest (m3) | K1: Kitchen & Laundry (m3) | L1: Room Nights
A2: Beirut | B2: 1 | C2: 8 | D2: 2020 | E2: =ELEC!M3 -> 6992 | F2: =ELEC!K3 -> 7022 | G2: =ELEC!I3 -> 3104 | H2: =ELEC!E3 -> 5596 | I2: =ELEC!G3 -> 2637 | J2: =WATER!Y6 -> 73 | K2: =WATER!AJ6 -> 30 | L2: =ELEC!B3 -> 89.01
A3: Beirut | B3: =B2+1 -> 2 | C3: 8 | D3: 2020 | E3: =ELEC!M4 -> 10480 | F3: =ELEC!K4 -> 3280 | G3: =ELEC!I4 -> 3214 | H3: =ELEC!E4 -> 5232 | I3: =ELEC!G4 -> 2526 | J3: =WATER!Y7 -> 53 | K3: =WATER!AJ7 -> 32 | L3: =ELEC!B4 -> 77.993
A4: Beirut | B4: =B3+1 -> 3 | C4: 8 | D4: 2020 | E4: =ELEC!M5 -> 6864 | F4: =ELEC!K5 -> 2790 | G4: =ELEC!I5 -> 2934 | H4: =ELEC!E5 -> 8820 | I4: =ELEC!G5 -> 2349 | J4: =WATER!Y8 -> 104 | K4: =WATER!AJ8 -> 81 | L4: =ELEC!B5 -> 69
A5: Beirut | B5: =B4+1 -> 4 | C5: 8 | D5: 2020 | E5: =ELEC!M6 -> 7014 | F5: =ELEC!K6 -> 2520 | G5: =ELEC!I6 -> 3692 | H5: =ELEC!E6 -> 9186 | I5: =ELEC!G6 -> 2832 | J5: =WATER!Y9 -> 0 | K5: =WATER!AJ9 -> 0 | L5: =ELEC!B6 -> 0
A6: Beirut | B6: =B5+1 -> 5 | C6: 8 | D6: 2020 | E6: =ELEC!M7 -> 3062 | F6: =ELEC!K7 -> 3352 | G6: =ELEC!I7 -> 1178 | H6: =ELEC!E7 -> 2654 | I6: =ELEC!G7 -> 742 | J6: =WATER!Y10 -> 13 | K6: =WATER!AJ10 -> 22 | L6: =ELEC!B7 -> 0
A7: Beirut | B7: =B6+1 -> 6 | C7: 8 | D7: 2020 | E7: =ELEC!M8 -> 4204 | F7: =ELEC!K8 -> 1578 | G7: =ELEC!I8 -> 1120 | H7: =ELEC!E8 -> 2690 | I7: =ELEC!G8 -> 1107 | J7: =WATER!Y11 -> 0 | K7: =WATER!AJ11 -> 0 | L7: =ELEC!B8 -> 0
A8: Beirut | B8: =B7+1 -> 7 | C8: 8 | D8: 2020 | E8: =ELEC!M9 -> 4188 | F8: =ELEC!K9 -> 734 | G8: =ELEC!I9 -> 1028 | H8: =ELEC!E9 -> 2926 | I8: =ELEC!G9 -> 905 | J8: =WATER!Y12 -> 70 | K8: =WATER!AJ12 -> 40 | L8: =ELEC!B9 -> 0
A9: Beirut | B9: =B8+1 -> 8 | C9: 8 | D9: 2020 | E9: =ELEC!M10 -> 1858 | F9: =ELEC!K10 -> 1112 | G9: =ELEC!I10 -> 1114 | H9: =ELEC!E10 -> 5800 | I9: =ELEC!G10 -> 763 | J9: =WATER!Y13 -> 76 | K9: =WATER!AJ13 -> 32 | L9: =ELEC!B10 -> 0
A10: Beirut | B10: =B9+1 -> 9 | C10: 8 | D10: 2020 | E10: =ELEC!M11 -> 3154 | F10: =ELEC!K11 -> 800 | G10: =ELEC!I11 -> 1070 | H10: =ELEC!E11 -> 2524 | I10: =ELEC!G11 -> 852 | J10: =WATER!Y14 -> 125 | K10: =WATER!AJ14 -> 1 | L10: =ELEC!B11 -> 0
A11: Beirut | B11: =B10+1 -> 10 | C11: 8 | D11: 2020 | E11: =ELEC!M12 -> 2050 | F11: =ELEC!K12 -> 1056 | G11: =ELEC!I12 -> 1090 | H11: =ELEC!E12 -> 5508 | I11: =ELEC!G12 -> 753 | J11: =WATER!Y15 -> 100 | K11: =WATER!AJ15 -> 51 | L11: =ELEC!B12 -> 0
A12: Beirut | B12: =B11+1 -> 11 | C12: 8 | D12: 2020 | E12: =ELEC!M13 -> 3870 | F12: =ELEC!K13 -> 1468 | G12: =ELEC!I13 -> 1200 | H12: =ELEC!E13 -> 2784 | I12: =ELEC!G13 -> 943 | J12: =WATER!Y16 -> 29 | K12: =WATER!AJ16 -> 11 | L12: =ELEC!B13 -> 0
A13: Beirut | B13: =B12+1 -> 12 | C13: 8 | D13: 2020 | E13: =ELEC!M14 -> 4004 | F13: =ELEC!K14 -> 852 | G13: =ELEC!I14 -> 1468 | H13: =ELEC!E14 -> 3252 | I13: =ELEC!G14 -> 1203 | J13: =WATER!Y17 -> 0 | K13: =WATER!AJ17 -> 31 | L13: =ELEC!B14 -> 0
A14: Beirut | B14: =B13+1 -> 13 | C14: 8 | D14: 2020 | E14: =ELEC!M15 -> 3420 | F14: =ELEC!K15 -> 1020 | G14: =ELEC!I15 -> 1468 | H14: =ELEC!E15 -> 4400 | I14: =ELEC!G15 -> 1147 | J14: =WATER!Y18 -> 0 | K14: =WATER!AJ18 -> 0 | L14: =ELEC!B15 -> 0
... A32: Beirut | B32: =B31+1 -> 31 | C32: 8 | D32: 2020 | E32: =ELEC!M33 -> 0 | F32: =ELEC!K33 -> 0 | G32: =ELEC!I33 -> 0 | H32: =ELEC!E33 -> 0 | I32: =ELEC!G33 -> 0 | J32: =WATER!Y36 -> 0 | K32: =WATER!AJ36 -> 0 | L32: =ELEC!B33 -> 0

Sheet ELEC
A1: OOC | B1: Room OCC | D1: MDB3 | E1: MDB3/day | F1: EMDB2 | G1: EMDB2/day | H1: EMDB1 | I1: EMDB1/day | J1: MDB2 | K1: mdb2/day | L1: MDB1 | M1: MDB1/Day | N1: Total KWH | O1: KWH/Rooc | P1: Gen MHW | Q1: Gen/Day KWH | R1: EDL KWH | S1: CH1 RH | T1: RH | U1: C1h1 power | V1: CH1 Con KWH | W1: CH2 RH | X1: RH | Y1: Ch2 power | Z1: CH2 Con KWH | AA1: CH3 RH | AB1: RH | AC1: Ch3 power | AD1: CH3 Con KWH | AE1: RH total | AF1: KWH total | AG1: AVG chiller KW/Hr
A2: =[1]ELEC!$A$33 -> 0.3609 | B2: =[1]ELEC!$B$33 -> 83.007 | C2: 44043 | D2: =[1]ELEC!D33 -> 32042098 | E2: =[1]ELEC!E33 -> 6288 | F2: =[1]ELEC!F33 -> 3808714 | G2: =[1]ELEC!G33 -> 2565 | H2: =[1]ELEC!H33 -> 17595910 | I2: =[1]ELEC!I33 -> 2998 | J2: =[1]ELEC!J33 -> 28649166 | K2: =[1]ELEC!K33 -> 6152 | ... AI2: =[1]ELEC!AI33 -> -166787
A3: ='General information '!F6 -> 0.387 | B3: =SUM(230*A3) -> 89.01 | C3: 44044 | D3: 32047694 | E3: =D3-D2 -> 5596 | F3: 3811351 | G3: =F3-F2 -> 2637 | H3: 17599014 | I3: =H3-H2 -> 3104 | J3: 28656188 | K3: =J3-J2 -> 7022 | L3: 23457686 | M3: =L3-L2 -> 6992 | N3: =M3+K3+I3+G3+E3 -> 25351 | O3: =IF(B3>0,N3/B3,0) -> 284.8107 | P3: 16174 | Q3: =(P3-P2)*1000 -> 17000 | R3: =+N3-Q3 -> 8351 | S3: 9275 | T3: =S3-S2 -> 11 | U3: 233995 | V3: =U3-U2 -> 2707 | W3: 32033 | X3: =W3-W2 -> 15 | Y3: 669511 | Z3: =Y3-Y2 -> 4041 | AA3: 35377 | AB3: =AA3-AA2 -> 0 | AC3: =AC2 -> 849402 | AD3: =AC3-AC2 -> 0 | AE3: =AB3+X3+T3 -> 26 | AF3: =V3+Z3+AD3 -> 6748 | AG3: =IF(AE3>0,AF3/AE3,0) -> 259.53846
A4: ='General information '!F7 -> 0.3391 | B4: =SUM(230*A4) -> 77.993 | C4: 44045 | D4: 32052926 | E4: =D4-D3 -> 5232 | F4: 3813877 | G4: =F4-F3 -> 2526 | H4: 17602228 | I4: =H4-H3 -> 3214 | J4: 28659468 | K4: =J4-J3 -> 3280 | L4: 23468166 | M4: =L4-L3 -> 10480 | N4: =M4+K4+I4+G4+E4 -> 24732 | O4: =IF(B4>0,N4/B4,0) -> 317.10538 | P4: 16184 | Q4: =(P4-P3)*1000 -> 10000 | R4: =N4-Q4 -> 14732 | S4: 9298 | T4: =S4-S3 -> 23 | U4: 239777 | V4: =U4-U3 -> 5782 | W4: 32036 | X4: =W4-W3 -> 3 | Y4: 669993 | Z4: =Y4-Y3 -> 482 | AA4: 35377 | AB4: =AA4-AA3 -> 0 | AC4: 849402 | AD4: =AC4-AC3 -> 0 | AE4: =AB4+X4+T4 -> 26 | AF4: =V4+Z4+AD4 -> 6264 | AG4: =IF(AE4>0,AF4/AE4,0) -> 240.92308
A5: ='General information '!F8 -> 0.3 | B5: =SUM(230*A5) -> 69 | C5: 44046 | D5: 32061746 | E5: =D5-D4 -> 8820 | F5: 3816226 | G5: =F5-F4 -> 2349 | H5: 17605162 | I5: =H5-H4 -> 2934 | J5: 28662258 | K5: =J5-J4 -> 2790 | L5: 23475030 | M5: =L5-L4 -> 6864 | N5: =M5+K5+I5+G5+E5 -> 23757 | O5: =IF(B5>0,N5/B5,0) -> 344.30435 | P5: 16199 | Q5: =(P5-P4)*1000 -> 15000 | R5: =N5-Q5 -> 8757 | S5: 9309 | T5: =S5-S4 -> 11 | U5: 242688 | V5: =U5-U4 -> 2911 | W5: 32036 | X5: =W5-W4 -> 0 | Y5: =Y4 -> 669993 | Z5: =Y5-Y4 -> 0 | AA5: 35390 | AB5: =AA5-AA4 -> 13 | AC5: 852906 | AD5: =AC5-AC4 -> 3504 | AE5: =AB5+X5+T5 -> 24 | AF5: =V5+Z5+AD5 -> 6415 | AG5: =IF(AE5>0,AF5/AE5,0) -> 267.29167 | AI5: =R5-'EDl log'!B3 -> -197253
A6: ='General information '!F9 -> 0 | B6: =SUM(230*A6) -> 0 | C6: 44047 | D6: 32070932 | E6: =D6-D5 -> 9186 | F6: 3819058 | G6: =F6-F5 -> 2832 | H6: 17608854 | I6: =H6-H5 -> 3692 | J6: 28664778 | K6: =J6-J5 -> 2520 | L6: 23482044 | M6: =L6-L5 -> 7014 | N6: =M6+K6+I6+G6+E6 -> 25244 | O6: =IF(B6>0,N6/B6,0) -> 0 | P6: =P5 -> 16199 | Q6: =(P6-P5)*1000 -> 0 | R6: =N6-Q6 -> 25244 | S6: =S5 -> 9309 | T6: =S6-S5 -> 0 | U6: =U5 -> 242688 | V6: =U6-U5 -> 0 | W6: =W5 -> 32036 | X6: =W6-W5 -> 0 | Y6: =Y5 -> 669993 | Z6: =Y6-Y5 -> 0 | AA6: =AA5 -> 35390 | AB6: =AA6-AA5 -> 0 | AC6: =AC5 -> 852906 | AD6: =AC6-AC5 -> 0 | AE6: =AB6+X6+T6 -> 0 | AF6: =V6+Z6+AD6 -> 0 | AG6: =IF(AE6>0,AF6/AE6,0) -> 0 | AI6: =R6-'EDl log'!B4 -> -185451
A7: ='General information '!F10 -> 0 | B7: =SUM(230*A7) -> 0 | C7: 44048 | D7: 32073586 | E7: =D7-D6 -> 2654 | F7: 3819800 | G7: =F7-F6 -> 742 | H7: 17610032 | I7: =H7-H6 -> 1178 | J7: 28668130 | K7: =J7-J6 -> 3352 | L7: 23485106 | M7: =L7-L6 -> 3062 | N7: =M7+K7+I7+G7+E7 -> 10988 | O7: =IF(B7>0,N7/B7,0) -> 0 | P7: 16213 | Q7: =(P7-P6)*1000 -> 14000 | R7: =N7-Q7 -> -3012 | S7: 9319 | T7: =S7-S6 -> 10 | U7: 245384 | V7: =U7-U6 -> 2696 | W7: 32044 | X7: =W7-W6 -> 8 | Y7: 671974 | Z7: =Y7-Y6 -> 1981 | AA7: 35405 | AB7: =AA7-AA6 -> 15 | AC7: 856413 | AD7: =AC7-AC6 -> 3507 | AE7: =AB7+X7+T7 -> 33 | AF7: =V7+Z7+AD7 -> 8184 | AG7: =IF(AE7>0,AF7/AE7,0) -> 248 | AI7: =R7-'EDl log'!B5 -> -221667
A8: ='General information '!F11 -> 0 | B8: =SUM(230*A8) -> 0 | C8: 44049 | D8: 32076276 | E8: =D8-D7 -> 2690 | F8: 3820907 | G8: =F8-F7 -> 1107 | H8: 17611152 | I8: =H8-H7 -> 1120 | J8: 28669708 | K8: =J8-J7 -> 1578 | L8: 23489310 | M8: =L8-L7 -> 4204 | N8: =M8+K8+I8+G8+E8 -> 10699 | O8: =IF(B8>0,N8/B8,0) -> 0 | P8: 16218 | Q8: =(P8-P7)*1000 -> 5000 | R8: =N8-Q8 -> 5699 | S8: 9327 | T8: =S8-S7 -> 8 | U8: 246875 | V8: =U8-U7 -> 1491 | W8: 32046 | X8: =W8-W7 -> 2 | Y8: 672604 | Z8: =Y8-Y7 -> 630 | AA8: 35405 | AB8: =AA8-AA7 -> 0 | AC8: =AC7 -> 856413 | AD8: =AC8-AC7 -> 0 | AE8: =AB8+X8+T8 -> 10 | AF8: =V8+Z8+AD8 -> 2121 | AG8: =IF(AE8>0,AF8/AE8,0) -> 212.1 | AI8: =R8-'EDl log'!B6 -> -217453
A9: ='General information '!F12 -> 0 | B9: =SUM(230*A9) -> 0 | C9: 44050 | D9: 32079202 | E9: =D9-D8 -> 2926 | F9: 3821812 | G9: =F9-F8 -> 905 | H9: 17612180 | I9: =H9-H8 -> 1028 | J9: 28670442 | K9: =J9-J8 -> 734 | L9: 23493498 | M9: =L9-L8 -> 4188 | N9: =M9+K9+I9+G9+E9 -> 9781 | O9: =IF(B9>0,N9/B9,0) -> 0 | P9: 16219 | Q9: =(P9-P8)*1000 -> 1000 | R9: =N9-Q9 -> 8781 | S9: 9336 | T9: =S9-S8 -> 9 | U9: 248851 | V9: =U9-U8 -> 1976 | W9: 32046 | X9: =W9-W8 -> 0 | Y9: 672606 | Z9: =Y9-Y8 -> 2 | AA9: 35407 | AB9: =AA9-AA8 -> 2 | AC9: 856808 | AD9: =AC9-AC8 -> 395 | AE9: =AB9+X9+T9 -> 11 | AF9: =V9+Z9+AD9 -> 2373 | AG9: =IF(AE9>0,AF9/AE9,0) -> 215.72727 | AI9: =R9-'EDl log'!B7 -> -221782
A10: ='General information '!F13 -> 0 | B10: =SUM(230*A10) -> 0 | C10: 44051 | D10: 32085002 | E10: =D10-D9 -> 5800 | F10: 3822575 | G10: =F10-F9 -> 763 | H10: 17613294 | I10: =H10-H9 -> 1114 | J10: 28671554 | K10: =J10-J9 -> 1112 | L10: 23495356 | M10: =L10-L9 -> 1858 | N10: =M10+K10+I10+G10+E10 -> 10647 | O10: =IF(B10>0,N10/B10,0) -> 0 | P10: 16221 | Q10: =(P10-P9)*1000 -> 2000 | R10: =N10-Q10 -> 8647 | S10: 9337 | T10: =S10-S9 -> 1 | U10: 249122 | V10: =U10-U9 -> 271 | W10: 32046 | X10: =W10-W9 -> 0 | Y10: 672607 | Z10: =Y10-Y9 -> 1 | AA10: 35420 | AB10: =AA10-AA9 -> 13 | AC10: 859223 | AD10: =AC10-AC9 -> 2415 | AE10: =AB10+X10+T10 -> 14 | AF10: =V10+Z10+AD10 -> 2687 | AG10: =IF(AE10>0,AF10/AE10,0) -> 191.92857 | AI10: =R10-'EDl log'!B8 -> -224496
A11: ='General information '!F14 -> 0 | B11: =SUM(230*A11) -> 0 | C11: 44052 | D11: 32087526 | E11: =D11-D10 -> 2524 | F11: 3823427 | G11: =F11-F10 -> 852 | H11: 17614364 | I11: =H11-H10 -> 1070 | J11: 28672354 | K11: =J11-J10 -> 800 | L11: 23498510 | M11: =L11-L10 -> 3154 | N11: =M11+K11+I11+G11+E11 -> 8400 | O11: =IF(B11>0,N11/B11,0) -> 0 | P11: 16223 | Q11: =(P11-P10)*1000 -> 2000 | R11: =N11-Q11 -> 6400 | S11: 9346 | T11: =S11-S10 -> 9 | U11: 250635 | V11: =U11-U10 -> 1513 | W11: =W10 -> 32046 | X11: =W11-W10 -> 0 | Y11: =Y10 -> 672607 | Z11: =Y11-Y10 -> 0 | AA11: 35422 | AB11: =AA11-AA10 -> 2 | AC11: 859491 | AD11: =AC11-AC10 -> 268 | AE11: =AB11+X11+T11 -> 11 | AF11: =V11+Z11+AD11 -> 1781 | AG11: =IF(AE11>0,AF11/AE11,0) -> 161.90909 | AI11: =R11-'EDl log'!B9 -> -231591
A12: ='General information '!F15 -> 0 | B12: =SUM(230*A12) -> 0 | C12: 44053 | D12: 32093034 | E12: =D12-D11 -> 5508 | F12: 3824180 | G12: =F12-F11 -> 753 | H12: 17615454 | I12: =H12-H11 -> 1090 | J12: 28673410 | K12: =J12-J11 -> 1056 | L12: 23500560 | M12: =L12-L11 -> 2050 | N12: =M12+K12+I12+G12+E12 -> 10457 | O12: =IF(B12>0,N12/B12,0) -> 0 | P12: 16224 | Q12: =(P12-P11)*1000 -> 1000 | R12: =N12-Q12 -> 9457 | S12: 9348 | T12: =S12-S11 -> 2 | U12: 250968 | V12: =U12-U11 -> 333 | W12: 32046 | X12: =W12-W11 -> 0 | Y12: 672607 | Z12: =Y12-Y11 -> 0 | AA12: 35434 | AB12: =AA12-AA11 -> 12 | AC12: 861734 | AD12: =AC12-AC11 -> 2243 | AE12: =AB12+X12+T12 -> 14 | AF12: =V12+Z12+AD12 -> 2576 | AG12: =IF(AE12>0,AF12/AE12,0) -> 184 | AI12: =R12-'EDl log'!B10 -> -232684
A13: ='General information '!F16 -> 0 | B13: =SUM(230*A13) -> 0 | C13: 44054 | D13: 32095818 | E13: =D13-D12 -> 2784 | F13: 3825123 | G13: =F13-F12 -> 943 | H13: 17616654 | I13: =H13-H12 -> 1200 | J13: 28674878 | K13: =J13-J12 -> 1468 | L13: 23504430 | M13: =L13-L12 -> 3870 | N13: =M13+K13+I13+G13+E13 -> 10265 | O13: =IF(B13>0,N13/B13,0) -> 0 | P13: 16226 | Q13: =(P13-P12)*1000 -> 2000 | R13: =N13-Q13 -> 8265 | S13: 9356 | T13: =S13-S12 -> 8 | U13: 252595 | V13: =U13-U12 -> 1627 | W13: 32046 | X13: =W13-W12 -> 0 | Y13: 672607 | Z13: =Y13-Y12 -> 0 | AA13: 35434 | AB13: =AA13-AA12 -> 0 | AC13: 861734 | AD13: =AC13-AC12 -> 0 | AE13: =AB13+X13+T13 -> 8 | AF13: =V13+Z13+AD13 -> 1627 | AG13: =IF(AE13>0,AF13/AE13,0) -> 203.375 | AI13: =R13-'EDl log'!B11 -> -238500
A14: ='General information '!F17 -> 0 | B14: =SUM(230*A14) -> 0 | C14: 44055 | D14: 32099070 | E14: =D14-D13 -> 3252 | F14: 3826326 | G14: =F14-F13 -> 1203 | H14: 17618122 | I14: =H14-H13 -> 1468 | J14: 28675730 | K14: =J14-J13 -> 852 | L14: 23508434 | M14: =L14-L13 -> 4004 | N14: =M14+K14+I14+G14+E14 -> 10779 | O14: =IF(B14>0,N14/B14,0) -> 0 | P14: 16228 | Q14: =(P14-P13)*1000 -> 2000 | R14: =N14-Q14 -> 8779 | S14: 9363 | T14: =S14-S13 -> 7 | U14: 254289 | V14: =U14-U13 -> 1694 | W14: 32049 | X14: =W14-W13 -> 3 | Y14: 673052 | Z14: =Y14-Y13 -> 445 | AA14: 35437 | AB14: =AA14-AA13 -> 3 | AC14: 862371 | AD14: =AC14-AC13 -> 637 | AE14: =AB14+X14+T14 -> 13 | AF14: =V14+Z14+AD14 -> 2776 | AG14: =IF(AE14>0,AF14/AE14,0) -> 213.53846 | AI14: =R14-'EDl log'!B12 -> -241502
A15: ='General information '!F18 -> 0 | B15: =SUM(230*A15) -> 0 | C15: 44056 | D15: 32103470 | E15: =D15-D14 -> 4400 | F15: 3827473 | G15: =F15-F14 -> 1147 | H15: 17619590 | I15: =H15-H14 -> 1468 | J15: 28676750 | K15: =J15-J14 -> 1020 | L15: 23511854 | M15: =L15-L14 -> 3420 | N15: =M15+K15+I15+G15+E15 -> 11455 | O15: =IF(B15>0,N15/B15,0) -> 0 | P15: 16230 | Q15: =(P15-P14)*1000 -> 2000 | R15: =N15-Q15 -> 9455 | S15: 9368 | T15: =S15-S14 -> 5 | U15: 255509 | V15: =U15-U14 -> 1220 | W15: 32049 | X15: =W15-W14 -> 0 | Y15: 673052 | Z15: =Y15-Y14 -> 0 | AA15: 35444 | AB15: =AA15-AA14 -> 7 | AC15: 863877 | AD15: =AC15-AC14 -> 1506 | AE15: =AB15+X15+T15 -> 12 | AF15: =V15+Z15+AD15 -> 2726 | AG15: =IF(AE15>0,AF15/AE15,0) -> 227.16667 | AI15: =R15-'EDl log'!B13 -> -245532
A16: ='General information '!F19 -> 0 | B16: =SUM(230*A16) -> 0 | C16: 44057 | D16: 32108176 | E16: =D16-D15 -> 4706 | F16: 3828616 | G16: =F16-F15 -> 1143 | H16: 17621124 | I16: =H16-H15 -> 1534 | J16: 28677648 | K16: =J16-J15 -> 898 | L16: 23514782 | M16: =L16-L15 -> 2928 | N16: =M16+K16+I16+G16+E16 -> 11209 | O16: =IF(B16>0,N16/B16,0) -> 0 | P16: 16234 | Q16: =(P16-P15)*1000 -> 4000 | R16: =N16-Q16 -> 7209 | S16: =S15 -> 9368 | T16: =S16-S15 -> 0 | U16: =U15 -> 255509 | V16: =U16-U15 -> 0 | W16: =W15 -> 32049 | X16: =W16-W15 -> 0 | Y16: =Y15 -> 673052 | Z16: =Y16-Y15 -> 0 | AA16: 35454 | AB16: =AA16-AA15 -> 10 | AC16: 866059 | AD16: =AC16-AC15 -> 2182 | AE16: =AB16+X16+T16 -> 10 | AF16: =V16+Z16+AD16 -> 2182 | AG16: =IF(AE16>0,AF16/AE16,0) -> 218.2 | AI16: =R16-'EDl log'!B14 -> -252392
A17: ='General information '!F20 -> 0 | B17: =SUM(230*A17) -> 0 | C17: 44058 | D17: 32112390 | E17: =D17-D16 -> 4214 | F17: 3829736 | G17: =F17-F16 -> 1120 | H17: 17622674 | I17: =H17-H16 -> 1550 | J17: 28678218 | K17: =J17-J16 -> 570 | L17: 23517032 | M17: =L17-L16 -> 2250 | N17: =M17+K17+I17+G17+E17 -> 9704 | O17: =IF(B17>0,N17/B17,0) -> 0 | P17: 16236 | Q17: =(P17-P16)*1000 -> 2000 | R17: =N17-Q17 -> 7704 | S17: 9371 | T17: =S17-S16 -> 3 | U17: 256194 | V17: =U17-U16 -> 685 | W17: =W16 -> 32049 | X17: =W17-W16 -> 0 | Y17: =Y16 -> 673052 | Z17: =Y17-Y16 -> 0 | AA17: 35461 | AB17: =AA17-AA16 -> 7 | AC17: 867187 | AD17: =AC17-AC16 -> 1128 | AE17: =AB17+X17+T17 -> 10 | AF17: =V17+Z17+AD17 -> 1813 | AG17: =IF(AE17>0,AF17/AE17,0) -> 181.3 | AI17: =R17-'EDl log'!B15 -> -256520
A18: ='General information '!F21 -> 0 | B18: =SUM(230*A18) -> 0 | C18: 44059 | D18: 32115318 | E18: =D18-D17 -> 2928 | F18: 3830785 | G18: =F18-F17 -> 1049 | H18: 17624060 | I18: =H18-H17 -> 1386 | J18: 28678922 | K18: =J18-J17 -> 704 | L18: 23520330 | M18: =L18-L17 -> 3298 | N18: =M18+K18+I18+G18+E18 -> 9365 | O18: =IF(B18>0,N18/B18,0) -> 0 | P18: 16238 | Q18: =(P18-P17)*1000 -> 2000 | R18: =N18-Q18 -> 7365 | S18: 9377 | T18: =S18-S17 -> 6 | U18: 257494 | V18: =U18-U17 -> 1300 | W18: 32049 | X18: =W18-W17 -> 0 | Y18: =Y17 -> 673052 | Z18: =Y18-Y17 -> 0 | AA18: 35463 | AB18: =AA18-AA17 -> 2 | AC18: 867699 | AD18: =AC18-AC17 -> 512 | AE18: =AB18+X18+T18 -> 8 | AF18: =V18+Z18+AD18 -> 1812 | AG18: =IF(AE18>0,AF18/AE18,0) -> 226.5 | AI18: =R18-'EDl log'!B16 -> -261463
A19: ='General information '!F22 -> 0 | B19: =SUM(230*A19) -> 0 | C19: 44060 | D19: 32120150 | E19: =D19-D18 -> 4832 | F19: 3831819 | G19: =F19-F18 -> 1034 | H19: 17625264 | I19: =H19-H18 -> 1204 | J19: 28679954 | K19: =J19-J18 -> 1032 | L19: 23523954 | M19: =L19-L18 -> 3624 | N19: =M19+K19+I19+G19+E19 -> 11726 | O19: =IF(B19>0,N19/B19,0) -> 0 | P19: 16239 | Q19: =(P19-P18)*1000 -> 1000 | R19: =N19-Q19 -> 10726 | S19: 9384 | T19: =S19-S18 -> 7 | U19: 258864 | V19: =U19-U18 -> 1370 | W19: 32049 | X19: =W19-W18 -> 0 | Y19: 673052 | Z19: =Y19-Y18 -> 0 | AA19: =AA18 -> 35463 | AB19: =AA19-AA18 -> 0 | AC19: =AC18 -> 867699 | AD19: =AC19-AC18 -> 0 | AE19: =AB19+X19+T19 -> 7 | AF19: =V19+Z19+AD19 -> 1370 | AG19: =IF(AE19>0,AF19/AE19,0) -> 195.71429 | AI19: =R19-'EDl log'!B17 -> -261989
A20: ='General information '!F23 -> 0 | B20: =SUM(230*A20) -> 0 | C20: 44061 | D20: 32126336 | E20: =D20-D19 -> 6186 | F20: 3832913 | G20: =F20-F19 -> 1094 | H20: 17626674 | I20: =H20-H19 -> 1410 | J20: 28680930 | K20: =J20-J19 -> 976 | L20: 23526392 | M20: =L20-L19 -> 2438 | N20: =M20+K20+I20+G20+E20 -> 12104 | O20: =IF(B20>0,N20/B20,0) -> 0 | P20: 16240 | Q20: =(P20-P19)*1000 -> 1000 | R20: =N20-Q20 -> 11104 | S20: 9384 | T20: =S20-S19 -> 0 | U20: 258864 | V20: =U20-U19 -> 0 | W20: 32049 | X20: =W20-W19 -> 0 | Y20: =Y19 -> 673052 | Z20: =Y20-Y19 -> 0 | AA20: 35482 | AB20: =AA20-AA19 -> 19 | AC20: 871793 | AD20: =AC20-AC19 -> 4094 | AE20: =AB20+X20+T20 -> 19 | AF20: =V20+Z20+AD20 -> 4094 | AG20: =IF(AE20>0,AF20/AE20,0) -> 215.47368 | AI20: =R20-'EDl log'!B18 -> -265711
A21: ='General information '!F24 -> 0 | B21: =SUM(230*A21) -> 0 | C21: 44062 | D21: =D20 -> 32126336 | E21: =D21-D20 -> 0 | F21: =F20 -> 3832913 | G21: =F21-F20 -> 0 | H21: =H20 -> 17626674 | I21: =H21-H20 -> 0 | J21: =J20 -> 28680930 | K21: =J21-J20 -> 0 | L21: =L20 -> 23526392 | M21: =L21-L20 -> 0 | N21: =M21+K21+I21+G21+E21 -> 0 | O21: =IF(B21>0,N21/B21,0) -> 0 | P21: =P20 -> 16240 | Q21: =(P21-P20)*1000 -> 0 | R21: =N21-Q21 -> 0 | S21: =S20 -> 9384 | T21: =S21-S20 -> 0 | U21: =U20 -> 258864 | V21: =U21-U20 -> 0 | W21: =W20 -> 32049 | X21: =W21-W20 -> 0 | Y21: =Y20 -> 673052 | Z21: =Y21-Y20 -> 0 | AA21: =AA20 -> 35482 | AB21: =AA21-AA20 -> 0 | AC21: =AC20 -> 871793 | AD21: =AC21-AC20 -> 0 | AE21: =AB21+X21+T21 -> 0 | AF21: =V21+Z21+AD21 -> 0 | AG21: =IF(AE21>0,AF21/AE21,0) -> 0 | AI21: =R21-'EDl log'!B19 -> -280938
A22: ='General information '!F25 -> 0 | B22: =SUM(230*A22) -> 0 | C22: 44063 | D22: =D21 -> 32126336 | E22: =D22-D21 -> 0 | F22: =F21 -> 3832913 | G22: =F22-F21 -> 0 | H22: =H21 -> 17626674 | I22: =H22-H21 -> 0 | J22: =J21 -> 28680930 | K22: =J22-J21 -> 0 | L22: =L21 -> 23526392 | M22: =L22-L21 -> 0 | N22: =M22+K22+I22+G22+E22 -> 0 | O22: =IF(B22>0,N22/B22,0) -> 0 | P22: =P21 -> 16240 | Q22: =(P22-P21)*1000 -> 0 | R22: =N22-Q22 -> 0 | S22: =S21 -> 9384 | T22: =S22-S21 -> 0 | U22: =U21 -> 258864 | V22: =U22-U21 -> 0 | W22: =W21 -> 32049 | X22: =W22-W21 -> 0 | Y22: =Y21 -> 673052 | Z22: =Y22-Y21 -> 0 | AA22: =AA21 -> 35482 | AB22: =AA22-AA21 -> 0 | AC22: =AC21 -> 871793 | AD22: =AC22-AC21 -> 0 | AE22: =AB22+X22+T22 -> 0 | AF22: =V22+Z22+AD22 -> 0 | AG22: =IF(AE22>0,AF22/AE22,0) -> 0 | AI22: =R22-'EDl log'!B20 -> -286074
A23: ='General information '!F26 -> 0 | B23: =SUM(230*A23) -> 0 | C23: 44064 | D23: =D22 -> 32126336 | E23: =D23-D22 -> 0 | F23: =F22 -> 3832913 | G23: =F23-F22 -> 0 | H23: =H22 -> 17626674 | I23: =H23-H22 -> 0 | J23: =J22 -> 28680930 | K23: =J23-J22 -> 0 | L23: =L22 -> 23526392 | M23: =L23-L22 -> 0 | N23: =M23+K23+I23+G23+E23 -> 0 | O23: =IF(B23>0,N23/B23,0) -> 0 | P23: =P22 -> 16240 | Q23: =(P23-P22)*1000 -> 0 | R23: =N23-Q23 -> 0 | S23: =S22 -> 9384 | T23: =S23-S22 -> 0 | U23: =U22 -> 258864 | V23: =U23-U22 -> 0 | W23: =W22 -> 32049 | X23: =W23-W22 -> 0 | Y23: =Y22 -> 673052 | Z23: =Y23-Y22 -> 0 | AA23: =AA22 -> 35482 | AB23: =AA23-AA22 -> 0 | AC23: =AC22 -> 871793 | AD23: =AC23-AC22 -> 0 | AE23: =AB23+X23+T23 -> 0 | AF23: =V23+Z23+AD23 -> 0 | AG23: =IF(AE23>0,AF23/AE23,0) -> 0 | AI23: =R23-'EDl log'!B21 -> -291983
A24: ='General information '!F27 -> 0 | B24: =SUM(230*A24) -> 0 | C24: 44065 | D24: =D23 -> 32126336 | E24: =D24-D23 -> 0 | F24: =F23 -> 3832913 | G24: =F24-F23 -> 0 | H24: =H23 -> 17626674 | I24: =H24-H23 -> 0 | J24: =J23 -> 28680930 | K24: =J24-J23 -> 0 | L24: =L23 -> 23526392 | M24: =L24-L23 -> 0 | N24: =M24+K24+I24+G24+E24 -> 0 | O24: =IF(B24>0,N24/B24,0) -> 0 | P24: =P23 -> 16240 | Q24: =(P24-P23)*1000 -> 0 | R24: =N24-Q24 -> 0 | S24: =S23 -> 9384 | T24: =S24-S23 -> 0 | U24: =U23 -> 258864 | V24: =U24-U23 -> 0 | W24: =W23 -> 32049 | X24: =W24-W23 -> 0 | Y24: =Y23 -> 673052 | Z24: =Y24-Y23 -> 0 | AA24: =AA23 -> 35482 | AB24: =AA24-AA23 -> 0 | AC24: =AC23 -> 871793 | AD24: =AC24-AC23 -> 0 | AE24: =AB24+X24+T24 -> 0 | AF24: =V24+Z24+AD24 -> 0 | AG24: =IF(AE24>0,AF24/AE24,0) -> 0 | AI24: =R24-'EDl log'!B22 -> -291983
A25: ='General information '!F28 -> 0 | B25: =SUM(230*A25) -> 0 | C25: 44066 | D25: =D24 -> 32126336 | E25: =D25-D24 -> 0 | F25: =F24 -> 3832913 | G25: =F25-F24 -> 0 | H25: =H24 -> 17626674 | I25: =H25-H24 -> 0 | J25: =J24 -> 28680930 | K25: =J25-J24 -> 0 | L25: =L24 -> 23526392 | M25: =L25-L24 -> 0 | N25: =M25+K25+I25+G25+E25 -> 0 | O25: =IF(B25>0,N25/B25,0) -> 0 | P25: =P24 -> 16240 | Q25: =(P25-P24)*1000 -> 0 | R25: =N25-Q25 -> 0 | S25: =S24 -> 9384 | T25: =S25-S24 -> 0 | U25: =U24 -> 258864 | V25: =U25-U24 -> 0 | W25: =W24 -> 32049 | X25: =W25-W24 -> 0 | Y25: =Y24 -> 673052 | Z25: =Y25-Y24 -> 0 | AA25: =AA24 -> 35482 | AB25: =AA25-AA24 -> 0 | AC25: =AC24 -> 871793 | AD25: =AC25-AC24 -> 0 | AE25: =AB25+X25+T25 -> 0 | AF25: =V25+Z25+AD25 -> 0 | AG25: =IF(AE25>0,AF25/AE25,0) -> 0 | AI25: =R25-'EDl log'!B23 -> -291983
A26: ='General information '!F29 -> 0 | B26: =SUM(230*A26) -> 0 | C26: 44067 | D26: =D25 -> 32126336 | E26: =D26-D25 -> 0 | F26: =F25 -> 3832913 | G26: =F26-F25 -> 0 | H26: =H25 -> 17626674 | I26: =H26-H25 -> 0 | J26: =J25 -> 28680930 | K26: =J26-J25 -> 0 | L26: =L25 -> 23526392 | M26: =L26-L25 -> 0 | N26: =M26+K26+I26+G26+E26 -> 0 | O26: =IF(B26>0,N26/B26,0) -> 0 | P26: =P25 -> 16240 | Q26: =(P26-P25)*1000 -> 0 | R26: =N26-Q26 -> 0 | S26: =S25 -> 9384 | T26: =S26-S25 -> 0 | U26: =U25 -> 258864 | V26: =U26-U25 -> 0 | W26: =W25 -> 32049 | X26: =W26-W25 -> 0 | Y26: =Y25 -> 673052 | Z26: =Y26-Y25 -> 0 | AA26: =AA25 -> 35482 | AB26: =AA26-AA25 -> 0 | AC26: =AC25 -> 871793 | AD26: =AC26-AC25 -> 0 | AE26: =AB26+X26+T26 -> 0 | AF26: =V26+Z26+AD26 -> 0 | AG26: =IF(AE26>0,AF26/AE26,0) -> 0 | AI26: =R26-'EDl log'!B24 -> -291983
A27: ='General information '!F30 -> 0 | B27: =SUM(230*A27) -> 0 | C27: 44068 | D27: =D26 -> 32126336 | E27: =D27-D26 -> 0 | F27: =F26 -> 3832913 | G27: =F27-F26 -> 0 | H27: =H26 -> 17626674 | I27: =H27-H26 -> 0 | J27: =J26 -> 28680930 | K27: =J27-J26 -> 0 | L27: =L26 -> 23526392 | M27: =L27-L26 -> 0 | N27: =M27+K27+I27+G27+E27 -> 0 | O27: =IF(B27>0,N27/B27,0) -> 0 | P27: =P26 -> 16240 | Q27: =(P27-P26)*1000 -> 0 | R27: =N27-Q27 -> 0 | S27: =S26 -> 9384 | T27: =S27-S26 -> 0 | U27: =U26 -> 258864 | V27: =U27-U26 -> 0 | W27: =W26 -> 32049 | X27: =W27-W26 -> 0 | Y27: =Y26 -> 673052 | Z27: =Y27-Y26 -> 0 | AA27: =AA26 -> 35482 | AB27: =AA27-AA26 -> 0 | AC27: =AC26 -> 871793 | AD27: =AC27-AC26 -> 0 | AE27: =AB27+X27+T27 -> 0 | AF27: =V27+Z27+AD27 -> 0 | AG27: =IF(AE27>0,AF27/AE27,0) -> 0 | AI27: =R27-'EDl log'!B25 -> -291983
A28: ='General information '!F31 -> 0 | B28: =SUM(230*A28) -> 0 | C28: 44069 | D28: =D27 -> 32126336 | E28: =D28-D27 -> 0 | F28: =F27 -> 3832913 | G28: =F28-F27 -> 0 | H28: =H27 -> 17626674 | I28: =H28-H27 -> 0 | J28: =J27 -> 28680930 | K28: =J28-J27 -> 0 | L28: =L27 -> 23526392 | M28: =L28-L27 -> 0 | N28: =M28+K28+I28+G28+E28 -> 0 | O28: =IF(B28>0,N28/B28,0) -> 0 | P28: =P27 -> 16240 | Q28: =(P28-P27)*1000 -> 0 | R28: =N28-Q28 -> 0 | S28: =S27 -> 9384 | T28: =S28-S27 -> 0 | U28: =U27 -> 258864 | V28: =U28-U27 -> 0 | W28: =W27 -> 32049 | X28: =W28-W27 -> 0 | Y28: =Y27 -> 673052 | Z28: =Y28-Y27 -> 0 | AA28: =AA27 -> 35482 | AB28: =AA28-AA27 -> 0 | AC28: =AC27 -> 871793 | AD28: =AC28-AC27 -> 0 | AE28: =AB28+X28+T28 -> 0 | AF28: =V28+Z28+AD28 -> 0 | AG28: =IF(AE28>0,AF28/AE28,0) -> 0 | AI28: =R28-'EDl log'!B26 -> -291983
A29: ='General information '!F32 -> 0 | B29: =SUM(230*A29) -> 0 | C29: 44070 | D29: =D28 -> 32126336 | E29: =D29-D28 -> 0 | F29: =F28 -> 3832913 | G29: =F29-F28 -> 0 | H29: =H28 -> 17626674 | I29: =H29-H28 -> 0 | J29: =J28 -> 28680930 | K29: =J29-J28 -> 0 | L29: =L28 -> 23526392 | M29: =L29-L28 -> 0 | N29: =M29+K29+I29+G29+E29 -> 0 | O29: =IF(B29>0,N29/B29,0) -> 0 | P29: =P28 -> 16240 | Q29: =(P29-P28)*1000 -> 0 | R29: =N29-Q29 -> 0 | S29: =S28 -> 9384 | T29: =S29-S28 -> 0 | U29: =U28 -> 258864 | V29: =U29-U28 -> 0 | W29: =W28 -> 32049 | X29: =W29-W28 -> 0 | Y29: =Y28 -> 673052 | Z29: =Y29-Y28 -> 0 | AA29: =AA28 -> 35482 | AB29: =AA29-AA28 -> 0 | AC29: =AC28 -> 871793 | AD29: =AC29-AC28 -> 0 | AE29: =AB29+X29+T29 -> 0 | AF29: =V29+Z29+AD29 -> 0 | AG29: =IF(AE29>0,AF29/AE29,0) -> 0 | AI29: =R29-'EDl log'!B27 -> -291983
A30: ='General information '!F33 -> 0 | B30: =SUM(230*A30) -> 0 | C30: 44071 | D30: =D29 -> 32126336 | E30: =D30-D29 -> 0 | F30: =F29 -> 3832913 | G30: =F30-F29 -> 0 | H30: =H29 -> 17626674 | I30: =H30-H29 -> 0 | J30: =J29 -> 28680930 | K30: =J30-J29 -> 0 | L30: =L29 -> 23526392 | M30: =L30-L29 -> 0 | N30: =M30+K30+I30+G30+E30 -> 0 | O30: =IF(B30>0,N30/B30,0) -> 0 | P30: =P29 -> 16240 | Q30: =(P30-P29)*1000 -> 0 | R30: =N30-Q30 -> 0 | S30: =S29 -> 9384 | T30: =S30-S29 -> 0 | U30: =U29 -> 258864 | V30: =U30-U29 -> 0 | W30: =W29 -> 32049 | X30: =W30-W29 -> 0 | Y30: =Y29 -> 673052 | Z30: =Y30-Y29 -> 0 | AA30: =AA29 -> 35482 | AB30: =AA30-AA29 -> 0 | AC30: =AC29 -> 871793 | AD30: =AC30-AC29 -> 0 | AE30: =AB30+X30+T30 -> 0 | AF30: =V30+Z30+AD30 -> 0 | AG30: =IF(AE30>0,AF30/AE30,0) -> 0 | AI30: =R30-'EDl log'!B28 -> -291983
A31: ='General information '!F34 -> 0 | B31: =SUM(230*A31) -> 0 | C31: 44072 | D31: =D30 -> 32126336 | E31: =D31-D30 -> 0 | F31: =F30 -> 3832913 | G31: =F31-F30 -> 0 | H31: =H30 -> 17626674 | I31: =H31-H30 -> 0 | J31: =J30 -> 28680930 | K31: =J31-J30 -> 0 | L31: =L30 -> 23526392 | M31: =L31-L30 -> 0 | N31: =M31+K31+I31+G31+E31 -> 0 | O31: =IF(B31>0,N31/B31,0) -> 0 | P31: =P30 -> 16240 | Q31: =(P31-P30)*1000 -> 0 | R31: =N31-Q31 -> 0 | S31: =S30 -> 9384 | T31: =S31-S30 -> 0 | U31: =U30 -> 258864 | V31: =U31-U30 -> 0 | W31: =W30 -> 32049 | X31: =W31-W30 -> 0 | Y31: =Y30 -> 673052 | Z31: =Y31-Y30 -> 0 | AA31: =AA30 -> 35482 | AB31: =AA31-AA30 -> 0 | AC31: =AC30 -> 871793 | AD31: =AC31-AC30 -> 0 | AE31: =AB31+X31+T31 -> 0 | AF31: =V31+Z31+AD31 -> 0 | AG31: =IF(AE31>0,AF31/AE31,0) -> 0 | AI31: =R31-'EDl log'!B29 -> -291983
A32: ='General information '!F35 -> 0 | B32: =SUM(230*A32) -> 0 | C32: 44073 | D32: =D31 -> 32126336 | E32: =D32-D31 -> 0 | F32: =F31 -> 3832913 | G32: =F32-F31 -> 0 | H32: =H31 -> 17626674 | I32: =H32-H31 -> 0 | J32: =J31 -> 28680930 | K32: =J32-J31 -> 0 | L32: =L31 -> 23526392 | M32: =L32-L31 -> 0 | N32: =M32+K32+I32+G32+E32 -> 0 | O32: =IF(B32>0,N32/B32,0) -> 0 | P32: =P31 -> 16240 | Q32: =(P32-P31)*1000 -> 0 | R32: =N32-Q32 -> 0 | S32: =S31 -> 9384 | T32: =S32-S31 -> 0 | U32: =U31 -> 258864 | V32: =U32-U31 -> 0 | W32: =W31 -> 32049 | X32: =W32-W31 -> 0 | Y32: =Y31 -> 673052 | Z32: =Y32-Y31 -> 0 | AA32: =AA31 -> 35482 | AB32: =AA32-AA31 -> 0 | AC32: =AC31 -> 871793 | AD32: =AC32-AC31 -> 0 | AE32: =AB32+X32+T32 -> 0 | AF32: =V32+Z32+AD32 -> 0 | AG32: =IF(AE32>0,AF32/AE32,0) -> 0 | AI32: =R32-'EDl log'!B30 -> -291983
A33: ='General information '!F36 -> 0 | B33: =SUM(230*A33) -> 0 | C33: 44074 | D33: =D32 -> 32126336 | E33: =D33-D32 -> 0 | F33: =F32 -> 3832913 | G33: =F33-F32 -> 0 | H33: =H32 -> 17626674 | I33: =H33-H32 -> 0 | J33: =J32 -> 28680930 | K33: =J33-J32 -> 0 | L33: =L32 -> 23526392 | M33: =L33-L32 -> 0 | N33: =M33+K33+I33+G33+E33 -> 0 | O33: =IF(B33>0,N33/B33,0) -> 0 | P33: =P32 -> 16240 | Q33: =(P33-P32)*1000 -> 0 | R33: =N33-Q33 -> 0 | S33: =S32 -> 9384 | T33: =S33-S32 -> 0 | U33: =U32 -> 258864 | V33: =U33-U32 -> 0 | W33: =W32 -> 32049 | X33: =W33-W32 -> 0 | Y33: =Y32 -> 673052 | Z33: =Y33-Y32 -> 0 | AA33: =AA32 -> 35482 | AB33: =AA33-AA32 -> 0 | AC33: =AC32 -> 871793 | AD33: =AC33-AC32 -> 0 | AE33: =AB33+X33+T33 -> 0 | AF33: =V33+Z33+AD33 -> 0 | AG33: =IF(AE33>0,AF33/AE33,0) -> 0 | AI33: =R33-'EDl log'!B31 -> -291983

Sheet B5
F1: Boiler A | J1: =J36 -> 1 | K1: Boiler B | P1: Boiler C | V1: Boiler | X1: SteamA | AC1: SteamB | AH1: Steam | AI1: Boiler & steam | AL1: Total Boiler Runing H | AM1: Total Steam Runing H | AN1: GAS1 % | AO1: GAS1/L | AP1: GAS2% | AQ1: Gas2/L | AR1: GAS3% | AS1: GAS3/L | AU1: Gas Cons | AV1: Delivery | AW1: Cost/L
B2: Level Tank Gen | C2: Level tank Boiler | D2: Daily Cons Bo. | E2: Boiler litter | F2: Boiler A | G2: Run Hr a | H2: Boiler A fuel | I2: Daily consumption | J2: AVG | K2: index Run H | L2: Run Hrb | M2: Boiler B Fuel | O2: Daily consumption | P2: Boiler C | S2: Run C | U2: Total RH | V2: Total Fuel | X2: SteamA | Y2: Run SA | Z2: Steam A Conter | AA2: Liters | AC2: SteamB | AD2: Run SteamB | AE2: Steam B Conter | AF2: SB Litters | AG2: Avg | AH2: Total Fuel | AI2: Total Fuel
S3: 0
A4: =ELEC!C2 -> 44043 | B4: =[1]B5!B35 -> 218 | C4: =[1]B5!C35 -> 223 | D4: =[1]B5!D35 -> -22 | E4: =[1]B5!E35 -> -184.36 | F4: =[1]B5!F35 -> 1648 | G4: =[1]B5!G35 -> 0 | H4: =[1]B5!H35 -> 357868 | I4: =[1]B5!I35 -> 0 | ... AX4: =[1]B5!AX35 -> 0.8
A5: =ELEC!C3 -> 44044 | B5: 197.3 | C5: 204 | D5: =C4-C5 -> 19 | E5: =D5*8.38 -> 159.22 | F5: =F4 -> 1648 | G5: =F5-F4 -> 0 | H5: =H4 -> 357868 | I5: =SUM(H5-H4) -> 0 | J5: 1 | K5: 2098 | L5: =K5-K4 -> 2 | M5: 153977 | N5: =M5-M4 -> 197 | O5: =O4 -> 211.875 | P5: 1835 | Q5: 155805 | R5: =Q5-Q4 -> 53 | S5: =SUM(P5-P4) -> 1 | T5: =SUM(S5*$T$2) -> 0 | U5: =SUM(G5+L5+S5) -> 3 | V5: =R5+N5+I5:I5 -> 250 | W5: =SUM(V5/U5) -> 83.333333 | X5: =X4 -> 2418 | Y5: =X5-X4 -> 0 | Z5: 135983 | AA5: =Z5-Z4 -> 19 | AB5: =SUM(Y5*$AB$2) -> 0 | AC5: 1923 | AD5: =AC5-AC4 -> 2 | AE5: 364710 | AF5: =AE5-AE4 -> 111 | AG5: =IF(AD5>0,AF5/AD5,0) -> 55.5 | AH5: =AF5+AA5 -> 130 | AI5: =SUM(AH5+V5) -> 380 | AJ5: =-tanks!AW6 -> 380 | AK5: =SUM(AJ5-AI5) -> 0 | AL5: =S5+L5+G5 -> 3 | AM5: =Y5+AD5 -> 2 | AN5: 75 | AO5: =(AN5/100)*3000 -> 2250 | AP5: 78 | AQ5: =(AP5/100)*3000 -> 2340 | AR5: 78 | AS5: =(AR5/100)*3000 -> 2340 | AT5: =SUM(AO5+AQ5+AS5) -> 6930 | AU5: =AT4-AT5+AV5 -> 150 | AX5: =IF(AV5>0,AW5,AX4) -> 0.8
A6: =ELEC!C4 -> 44045 | B6: 188 | C6: 194 | D6: =C5-C6 -> 10 | E6: =D6*8.38 -> 83.8 | F6: 1648 | G6: =F6-F5 -> 0 | H6: 357868 | I6: =SUM(H6-H5) -> 0 | J6: =IF(G6>0,I6/G6,0) -> 0 | K6: 2101 | L6: =K6-K5 -> 3 | M6: 154206 | N6: =M6-M5 -> 229 | O6: =O5 -> 211.875 | P6: 1835 | Q6: 155805 | R6: =Q6-Q5 -> 0 | S6: =SUM(P6-P5) -> 0 | T6: =SUM(S6*$T$2) -> 0 | U6: =SUM(G6+L6+S6) -> 3 | V6: =R6+N6+I6:I6 -> 229 | W6: =SUM(V6/U6) -> 76.333333 | X6: 2418 | Y6: =X6-X5 -> 0 | Z6: 135983 | AA6: =Z6-Z5 -> 0 | AB6: =SUM(Y6*$AB$2) -> 0 | AC6: 1923 | AD6: =AC6-AC5 -> 0 | AE6: 364710 | AF6: =AE6-AE5 -> 0 | AG6: =IF(AD6>0,AF6/AD6,0) -> 0 | AH6: =AF6+AA6 -> 0 | AI6: =SUM(AH6+V6) -> 229 | AJ6: =-tanks!AW7 -> 229 | AK6: =SUM(AJ6-AI6) -> 0 | AL6: =S6+L6+G6 -> 3 | AM6: =Y6+AD6 -> 0 | AN6: 70 | AO6: =(AN6/100)*3000 -> 2100 | AP6: 74 | AQ6: =(AP6/100)*3000 -> 2220 | AR6: 75 | AS6: =(AR6/100)*3000 -> 2250 | AT6: =SUM(AO6+AQ6+AS6) -> 6570 | AU6: =AT5-AT6+AV6 -> 360 | AX6: =IF(AV6>0,AW6,AX5) -> 0.8
A7: =ELEC!C5 -> 44046 | B7: 207 | C7: 213 | D7: =C6-C7 -> -19 | E7: =D7*8.38 -> -159.22 | F7: 1648 | G7: =F7-F6 -> 0 | H7: 357868 | I7: =SUM(H7-H6) -> 0 | J7: =IF(G7>0,I7/G7,0) -> 0 | K7: 2105 | L7: =K7-K6 -> 4 | M7: 154439 | N7: =M7-M6 -> 233 | O7: =O6 -> 211.875 | P7: 1835 | Q7: 155805 | R7: =Q7-Q6 -> 0 | S7: =SUM(P7-P6) -> 0 | T7: =SUM(S7*$T$2) -> 0 | U7: =SUM(G7+L7+S7) -> 4 | V7: =R7+N7+I7:I7 -> 233 | W7: =SUM(V7/U7) -> 58.25 | X7: 2418 | Y7: =X7-X6 -> 0 | Z7: 135983 | AA7: =Z7-Z6 -> 0 | AB7: =SUM(Y7*$AB$2) -> 0 | AC7: 1932 | AD7: =AC7-AC6 -> 9 | AE7: 365157 | AF7: =AE7-AE6 -> 447 | AG7: =IF(AD7>0,AF7/AD7,0) -> 49.666667 | AH7: =AF7+AA7 -> 447 | AI7: =SUM(AH7+V7) -> 680 | AJ7: =-tanks!AW8 -> 680 | AK7: =SUM(AJ7-AI7) -> 0 | AL7: =S7+L7+G7 -> 4 | AM7: =Y7+AD7 -> 9 | AN7: 67 | AO7: =(AN7/100)*3000 -> 2010 | AP7: 70 | AQ7: =(AP7/100)*3000 -> 2100 | AR7: 70 | AS7: =(AR7/100)*3000 -> 2100 | AT7: =SUM(AO7+AQ7+AS7) -> 6210 | AU7: =AT6-AT7+AV7 -> 360 | AX7: =IF(AV7>0,AW7,AX6) -> 0.8
A8: =ELEC!C6 -> 44047 | B8: 207 | C8: 194 | D8: =C7-C8 -> 19 | E8: =D8*8.38 -> 159.22 | F8: =F7 -> 1648 | G8: =F8-F7 -> 0 | H8: =H7 -> 357868 | I8: =SUM(H8-H7) -> 0 | J8: =IF(G8>0,I8/G8,0) -> 0 | K8: 2106 | L8: =K8-K7 -> 1 | M8: =M7 -> 154439 | N8: =M8-M7 -> 0 | O8: =O7 -> 211.875 | P8: =P7 -> 1835 | Q8: =Q7 -> 155805 | R8: =Q8-Q7 -> 0 | S8: =SUM(P8-P7) -> 0 | T8: =SUM(S8*$T$2) -> 0 | U8: =SUM(G8+L8+S8) -> 1 | V8: =R8+N8+I8:I8 -> 0 | W8: =SUM(V8/U8) -> 0 | X8: =X7 -> 2418 | Y8: =X8-X7 -> 0 | Z8: =Z7 -> 135983 | AA8: =Z8-Z7 -> 0 | AB8: =SUM(Y8*$AB$2) -> 0 | AC8: =AC7 -> 1932 | AD8: =AC8-AC7 -> 0 | AE8: =AE7 -> 365157 | AF8: =AE8-AE7 -> 0 | AG8: =IF(AD8>0,AF8/AD8,0) -> 0 | AH8: =AF8+AA8 -> 0 | AI8: =SUM(AH8+V8) -> 0 | AJ8: =-tanks!AW9 -> 0 | AK8: =SUM(AJ8-AI8) -> 0 | AL8: =S8+L8+G8 -> 1 | AM8: =Y8+AD8 -> 0 | AN8: =AN7 -> 67 | AO8: =(AN8/100)*3000 -> 2010 | AP8: =AP7 -> 70 | AQ8: =(AP8/100)*3000 -> 2100 | AR8: =AR7 -> 70 | AS8: =(AR8/100)*3000 -> 2100 | AT8: =SUM(AO8+AQ8+AS8) -> 6210 | AU8: =AT7-AT8+AV8 -> 0 | AX8: =IF(AV8>0,AW8,AX7) -> 0.8
A9: =ELEC!C7 -> 44048 | B9: 187 | C9: 194 | D9: =C8-C9 -> 0 | E9: =D9*8.38 -> 0 | F9: 1648 | G9: =F9-F8 -> 0 | H9: 357868 | I9: =SUM(H9-H8) -> 0 | J9: =IF(G9>0,I9/G9,0) -> 0 | K9: 2106 | L9: =K9-K8 -> 0 | M9: 154583 | N9: =M9-M8 -> 144 | O9: =O8 -> 211.875 | P9: 1835 | Q9: 155805 | R9: =Q9-Q8 -> 0 | S9: =SUM(P9-P8) -> 0 | T9: =SUM(S9*$T$2) -> 0 | U9: =SUM(G9+L9+S9) -> 0 | V9: =R9+N9+I9:I9 -> 144 | W9: =SUM(V9/U9) -> #DIV/0! | X9: 2418 | Y9: =X9-X8 -> 0 | Z9: 135983 | AA9: =Z9-Z8 -> 0 | AB9: =SUM(Y9*$AB$2) -> 0 | AC9: 1932 | AD9: =AC9-AC8 -> 0 | AE9: 365157 | AF9: =AE9-AE8 -> 0 | AG9: =IF(AD9>0,AF9/AD9,0) -> 0 | AH9: =AF9+AA9 -> 0 | AI9: =SUM(AH9+V9) -> 144 | AJ9: =-tanks!AW10 -> 144 | AK9: =SUM(AJ9-AI9) -> 0 | AL9: =S9+L9+G9 -> 0 | AM9: =Y9+AD9 -> 0 | AN9: =AN8 -> 67 | AO9: =(AN9/100)*3000 -> 2010 | AP9: =AP8 -> 70 | AQ9: =(AP9/100)*3000 -> 2100 | AR9: =AR8 -> 70 | AS9: =(AR9/100)*3000 -> 2100 | AT9: =SUM(AO9+AQ9+AS9) -> 6210 | AU9: =AT8-AT9+AV9 -> 0 | AX9: =IF(AV9>0,AW9,AX8) -> 0.8
A10: =ELEC!C8 -> 44049 | B10: 186 | C10: 192 | D10: =C9-C10 -> 2 | E10: =D10*8.38 -> 16.76 | F10: =F9 -> 1648 | G10: =F10-F9 -> 0 | H10: =H9 -> 357868 | I10: =SUM(H10-H9) -> 0 | J10: =IF(G10>0,I10/G10,0) -> 0 | K10: 2106 | L10: =K10-K9 -> 0 | M10: =M9 -> 154583 | N10: =M10-M9 -> 0 | O10: =O9 -> 211.875 | P10: =P9 -> 1835 | Q10: =Q9 -> 155805 | R10: =Q10-Q9 -> 0 | S10: =SUM(P10-P9) -> 0 | T10: =SUM(S10*$T$2) -> 0 | U10: =SUM(G10+L10+S10) -> 0 | V10: =R10+N10+I10:I10 -> 0 | W10: =SUM(V10/U10) -> #DIV/0! | X10: =X9 -> 2418 | Y10: =X10-X9 -> 0 | Z10: =Z9 -> 135983 | AA10: =Z10-Z9 -> 0 | AB10: =SUM(Y10*$AB$2) -> 0 | AC10: =AC9 -> 1932 | AD10: =AC10-AC9 -> 0 | AE10: =AE9 -> 365157 | AF10: =AE10-AE9 -> 0 | AG10: =IF(AD10>0,AF10/AD10,0) -> 0 | AH10: =AF10+AA10 -> 0 | AI10: =SUM(AH10+V10) -> 0 | AJ10: =-tanks!AW11 -> 0 | AK10: =SUM(AJ10-AI10) -> 0 | AL10: =S10+L10+G10 -> 0 | AM10: =Y10+AD10 -> 0 | AN10: =AN9 -> 67 | AO10: =(AN10/100)*3000 -> 2010 | AP10: =AP9 -> 70 | AQ10: =(AP10/100)*3000 -> 2100 | AR10: =AR9 -> 70 | AS10: =(AR10/100)*3000 -> 2100 | AT10: =SUM(AO10+AQ10+AS10) -> 6210 | AU10: =AT9-AT10+AV10 -> 0 | AX10: =IF(AV10>0,AW10,AX9) -> 0.8
A11: =ELEC!C9 -> 44050 | B11: 268 | C11: 226 | D11: =C10-C11 -> -34 | E11: =D11*8.38 -> -284.92 | F11: 1648 | G11: =F11-F10 -> 0 | H11: 357868 | I11: =SUM(H11-H10) -> 0 | J11: =IF(G11>0,I11/G11,0) -> 0 | K11: 2106 | L11: =K11-K10 -> 0 | M11: 154583 | N11: =M11-M10 -> 0 | O11: =O10 -> 211.875 | P11: 1835 | Q11: 155805 | R11: =Q11-Q10 -> 0 | S11: =SUM(P11-P10) -> 0 | T11: =SUM(S11*$T$2) -> 0 | U11: =SUM(G11+L11+S11) -> 0 | V11: =R11+N11+I11:I11 -> 0 | W11: =SUM(V11/U11) -> #DIV/0! | X11: =X10 -> 2418 | Y11: =X11-X10 -> 0 | Z11: 135983 | AA11: =Z11-Z10 -> 0 | AB11: =SUM(Y11*$AB$2) -> 0 | AC11: 1932 | AD11: =AC11-AC10 -> 0 | AE11: 365157 | AF11: =AE11-AE10 -> 0 | AG11: =IF(AD11>0,AF11/AD11,0) -> 0 | AH11: =AF11+AA11 -> 0 | AI11: =SUM(AH11+V11) -> 0 | AJ11: =-tanks!AW12 -> 0 | AK11: =SUM(AJ11-AI11) -> 0 | AL11: =S11+L11+G11 -> 0 | AM11: =Y11+AD11 -> 0 | AN11: =AN10 -> 67 | AO11: =(AN11/100)*3000 -> 2010 | AP11: =AP10 -> 70 | AQ11: =(AP11/100)*3000 -> 2100 | AR11: =AR10 -> 70 | AS11: =(AR11/100)*3000 -> 2100 | AT11: =SUM(AO11+AQ11+AS11) -> 6210 | AU11: =AT10-AT11+AV11 -> 0 | AX11: =IF(AV11>0,AW11,AX10) -> 0.8
A12: =ELEC!C10 -> 44051 | B12: 253.3 | C12: 259.5 | D12: =C11-C12 -> -33.5 | E12: =D12*8.38 -> -280.73 | F12: 1648 | G12: =F12-F11 -> 0 | H12: =H11 -> 357868 | I12: =SUM(H12-H11) -> 0 | J12: =IF(G12>0,I12/G12,0) -> 0 | K12: =K11 -> 2106 | L12: =K12-K11 -> 0 | M12: =M11 -> 154583 | N12: =M12-M11 -> 0 | O12: =O11 -> 211.875 | P12: =P11 -> 1835 | Q12: =Q11 -> 155805 | R12: =Q12-Q11 -> 0 | S12: =SUM(P12-P11) -> 0 | T12: =SUM(S12*$T$2) -> 0 | U12: =SUM(G12+L12+S12) -> 0 | V12: =R12+N12+I12:I12 -> 0 | W12: =SUM(V12/U12) -> #DIV/0! | X12: =X11 -> 2418 | Y12: =X12-X11 -> 0 | Z12: =Z11 -> 135983 | AA12: =Z12-Z11 -> 0 | AB12: =SUM(Y12*$AB$2) -> 0 | AC12: =AC11 -> 1932 | AD12: =AC12-AC11 -> 0 | AE12: =AE11 -> 365157 | AF12: =AE12-AE11 -> 0 | AG12: =IF(AD12>0,AF12/AD12,0) -> 0 | AH12: =AF12+AA12 -> 0 | AI12: =SUM(AH12+V12) -> 0 | AJ12: =-tanks!AW13 -> 0 | AK12: =SUM(AJ12-AI12) -> 0 | AL12: =S12+L12+G12 -> 0 | AM12: =Y12+AD12 -> 0 | AN12: =AN11 -> 67 | AO12: =(AN12/100)*3000 -> 2010 | AP12: =AP11 -> 70 | AQ12: =(AP12/100)*3000 -> 2100 | AR12: =AR11 -> 70 | AS12: =(AR12/100)*3000 -> 2100 | AT12: =SUM(AO12+AQ12+AS12) -> 6210 | AU12: =AT11-AT12+AV12 -> 0 | AX12: =IF(AV12>0,AW12,AX11) -> 0.8
A13: =ELEC!C11 -> 44052 | B13: 251.4 | C13: 257.4 | D13: =C12-C13 -> 2.1 | E13: =D13*8.38 -> 17.598 | F13: =F12 -> 1648 | G13: =F13-F12 -> 0 | H13: =H12 -> 357868 | I13: =SUM(H13-H12) -> 0 | J13: =IF(G13>0,I13/G13,0) -> 0 | K13: =K12 -> 2106 | L13: =K13-K12 -> 0 | M13: =M12 -> 154583 | N13: =M13-M12 -> 0 | O13: =O12 -> 211.875 | P13: =P12 -> 1835 | Q13: =Q12 -> 155805 | R13: =Q13-Q12 -> 0 | S13: =SUM(P13-P12) -> 0 | T13: =SUM(S13*$T$2) -> 0 | U13: =SUM(G13+L13+S13) -> 0 | V13: =R13+N13+I13:I13 -> 0 | W13: =SUM(V13/U13) -> #DIV/0! | X13: =X12 -> 2418 | Y13: =X13-X12 -> 0 | Z13: =Z12 -> 135983 | AA13: =Z13-Z12 -> 0 | AB13: =SUM(Y13*$AB$2) -> 0 | AC13: =AC12 -> 1932 | AD13: =AC13-AC12 -> 0 | AE13: =AE12 -> 365157 | AF13: =AE13-AE12 -> 0 | AG13: =IF(AD13>0,AF13/AD13,0) -> 0 | AH13: =AF13+AA13 -> 0 | AI13: =SUM(AH13+V13) -> 0 | AJ13: =-tanks!AW14 -> 0 | AK13: =SUM(AJ13-AI13) -> 0 | AL13: =S13+L13+G13 -> 0 | AM13: =Y13+AD13 -> 0 | AN13: =AN12 -> 67 | AO13: =(AN13/100)*3000 -> 2010 | AP13: =AP12 -> 70 | AQ13: =(AP13/100)*3000 -> 2100 | AR13: =AR12 -> 70 | AS13: =(AR13/100)*3000 -> 2100 | AT13: =SUM(AO13+AQ13+AS13) -> 6210 | AU13: =AT12-AT13+AV13 -> 0 | AX13: =IF(AV13>0,AW13,AX12) -> 0.8
A14: =ELEC!C12 -> 44053 | B14: 250 | C14: 255.4 | D14: =C13-C14 -> 2 | E14: =D14*8.38 -> 16.76 | F14: 1648 | G14: =F14-F13 -> 0 | H14: 357868 | I14: =SUM(H14-H13) -> 0 | J14: =IF(G14>0,I14/G14,0) -> 0 | K14: =K13 -> 2106 | L14: =K14-K13 -> 0 | M14: =M13 -> 154583 | N14: =M14-M13 -> 0 | O14: =O13 -> 211.875 | P14: =P13 -> 1835 | Q14: =Q13 -> 155805 | R14: =Q14-Q13 -> 0 | S14: =SUM(P14-P13) -> 0 | T14: =SUM(S14*$T$2) -> 0 | U14: =SUM(G14+L14+S14) -> 0 | V14: =R14+N14+I14:I14 -> 0 | W14: =SUM(V14/U14) -> #DIV/0! | X14: =X13 -> 2418 | Y14: =X14-X13 -> 0 | Z14: =Z13 -> 135983 | AA14: =Z14-Z13 -> 0 | AB14: =SUM(Y14*$AB$2) -> 0 | AC14: =AC13 -> 1932 | AD14: =AC14-AC13 -> 0 | AE14: =AE13 -> 365157 | AF14: =AE14-AE13 -> 0 | AG14: =IF(AD14>0,AF14/AD14,0) -> 0 | AH14: =AF14+AA14 -> 0 | AI14: =SUM(AH14+V14) -> 0 | AJ14: =-tanks!AW15 -> 0 | AK14: =SUM(AJ14-AI14) -> 0 | AL14: =S14+L14+G14 -> 0 | AM14: =Y14+AD14 -> 0 | AN14: =AN13 -> 67 | AO14: =(AN14/100)*3000 -> 2010 | AP14: =AP13 -> 70 | AQ14: =(AP14/100)*3000 -> 2100 | AR14: =AR13 -> 70 | AS14: =(AR14/100)*3000 -> 2100 | AT14: =SUM(AO14+AQ14+AS14) -> 6210 | AU14: =AT13-AT14+AV14 -> 0 | AX14: =IF(AV14>0,AW14,AX13) -> 0.8
A15: =ELEC!C13 -> 44054 | B15: 248 | C15: 253.3 | D15: =C14-C15 -> 2.1 | E15: =D15*8.38 -> 17.598 | F15: 1648 | G15: =F15-F14 -> 0 | H15: =H14 -> 357868 | I15: =SUM(H15-H14) -> 0 | J15: =IF(G15>0,I15/G15,0) -> 0 | K15: 2107 | L15: =K15-K14 -> 1 | M15: 154592 | N15: =M15-M14 -> 9 | O15: =O14 -> 211.875 | P15: 1835 | Q15: =Q14 -> 155805 | R15: =Q15-Q14 -> 0 | S15: =SUM(P15-P14) -> 0 | T15: =SUM(S15*$T$2) -> 0 | U15: =SUM(G15+L15+S15) -> 1 | V15: =R15+N15+I15:I15 -> 9 | W15: =SUM(V15/U15) -> 9 | X15: 2419 | Y15: =X15-X14 -> 1 | Z15: 136036 | AA15: =Z15-Z14 -> 53 | AB15: =SUM(Y15*$AB$2) -> 0 | AC15: 1933 | AD15: =AC15-AC14 -> 1 | AE15: 365210.2 | AF15: =AE15-AE14 -> 53.2 | AG15: =IF(AD15>0,AF15/AD15,0) -> 53.2 | AH15: =AF15+AA15 -> 106.2 | AI15: =SUM(AH15+V15) -> 115.2 | AJ15: =-tanks!AW16 -> 115.2 | AK15: =SUM(AJ15-AI15) -> 0 | AL15: =S15+L15+G15 -> 1 | AM15: =Y15+AD15 -> 2 | AN15: =AN14 -> 67 | AO15: =(AN15/100)*3000 -> 2010 | AP15: =AP14 -> 70 | AQ15: =(AP15/100)*3000 -> 2100 | AR15: =AR14 -> 70 | AS15: =(AR15/100)*3000 -> 2100 | AT15: =SUM(AO15+AQ15+AS15) -> 6210 | AU15: =AT14-AT15+AV15 -> 0 | AX15: =IF(AV15>0,AW15,AX14) -> 0.8
A16: =ELEC!C14 -> 44055 | B16: 242.4 | C16: 248 | D16: =C15-C16 -> 5.3 | E16: =D16*8.38 -> 44.414 | F16: 1648 | G16: =F16-F15 -> 0 | H16: =H15 -> 357868 | I16: =SUM(H16-H15) -> 0 | J16: =IF(G16>0,I16/G16,0) -> 0 | K16: =K15 -> 2107 | L16: =K16-K15 -> 0 | M16: =M15 -> 154592 | N16: =M16-M15 -> 0 | O16: =O15 -> 211.875 | P16: =P15 -> 1835 | Q16: =Q15 -> 155805 | R16: =Q16-Q15 -> 0 | S16: =SUM(P16-P15) -> 0 | T16: =SUM(S16*$T$2) -> 0 | U16: =SUM(G16+L16+S16) -> 0 | V16: =R16+N16+I16:I16 -> 0 | W16: =SUM(V16/U16) -> #DIV/0! | X16: =X15 -> 2419 | Y16: =X16-X15 -> 0 | Z16: =Z15 -> 136036 | AA16: =Z16-Z15 -> 0 | AB16: =SUM(Y16*$AB$2) -> 0 | AC16: =AC15 -> 1933 | AD16: =AC16-AC15 -> 0 | AE16: =AE15 -> 365210.2 | AF16: =AE16-AE15 -> 0 | AG16: =IF(AD16>0,AF16/AD16,0) -> 0 | AH16: =AF16+AA16 -> 0 | AI16: =SUM(AH16+V16) -> 0 | AJ16: =-tanks!AW17 -> 0 | AK16: =SUM(AJ16-AI16) -> 0 | AL16: =S16+L16+G16 -> 0 | AM16: =Y16+AD16 -> 0 | AN16: =AN15 -> 67 | AO16: =(AN16/100)*3000 -> 2010 | AP16: =AP15 -> 70 | AQ16: =(AP16/100)*3000 -> 2100 | AR16: =AR15 -> 70 | AS16: =(AR16/100)*3000 -> 2100 | AT16: =SUM(AO16+AQ16+AS16) -> 6210 | AU16: =AT15-AT16+AV16 -> 0 | AX16: =IF(AV16>0,AW16,AX15) -> 0.8
A17: =ELEC!C15 -> 44056 | B17: =B16 -> 242.4 | C17: =C16 -> 248 | D17: =C16-C17 -> 0 | E17: =D17*8.38 -> 0 | F17: =F16 -> 1648 | G17: =F17-F16 -> 0 | H17: =H16 -> 357868 | I17: =SUM(H17-H16) -> 0 | J17: =IF(G17>0,I17/G17,0) -> 0 | K17: =K16 -> 2107 | L17: =K17-K16 -> 0 | M17: =M16 -> 154592 | N17: =M17-M16 -> 0 | O17: =O16 -> 211.875 | P17: =P16 -> 1835 | Q17: =Q16 -> 155805 | R17: =Q17-Q16 -> 0 | S17: =SUM(P17-P16) -> 0 | T17: =SUM(S17*$T$2) -> 0 | U17: =SUM(G17+L17+S17) -> 0 | V17: =R17+N17+I17:I17 -> 0 | X17: =X16 -> 2419 | Y17: =X17-X16 -> 0 | Z17: =Z16 -> 136036 | AA17: =Z17-Z16 -> 0 | AB17: =SUM(Y17*$AB$2) -> 0 | AC17: =AC16 -> 1933 | AD17: =AC17-AC16 -> 0 | AE17: =AE16 -> 365210.2 | AF17: =AE17-AE16 -> 0 | AG17: =IF(AD17>0,AF17/AD17,0) -> 0 | AH17: =AF17+AA17 -> 0 | AI17: =SUM(AH17+V17) -> 0 | AJ17: =-tanks!AW18 -> 0 | AK17: =SUM(AJ17-AI17) -> 0 | AL17: =S17+L17+G17 -> 0 | AM17: =Y17+AD17 -> 0 | AN17: =AN16 -> 67 | AO17: =(AN17/100)*3000 -> 2010 | AP17: =AP16 -> 70 | AQ17: =(AP17/100)*3000 -> 2100 | AR17: =AR16 -> 70 | AS17: =(AR17/100)*3000 -> 2100 | AT17: =SUM(AO17+AQ17+AS17) -> 6210 | AU17: =AT16-AT17+AV17 -> 0 | AX17: =IF(AV17>0,AW17,AX16) -> 0.8
A18: =ELEC!C16 -> 44057 | B18: 238 | C18: 244.5 | D18: =C17-C18 -> 3.5 | E18: =D18*8.38 -> 29.33 | F18: =F17 -> 1648 | G18: =F18-F17 -> 0 | H18: =H17 -> 357868 | I18: =SUM(H18-H17) -> 0 | J18: =IF(G18>0,I18/G18,0) -> 0 | K18: =K17 -> 2107 | L18: =K18-K17 -> 0 | M18: =M17 -> 154592 | N18: =M18-M17 -> 0 | O18: =O17 -> 211.875 | P18: =P17 -> 1835 | Q18: =Q17 -> 155805 | R18: =Q18-Q17 -> 0 | S18: =SUM(P18-P17) -> 0 | T18: =SUM(S18*$T$2) -> 0 | U18: =SUM(G18+L18+S18) -> 0 | V18: =R18+N18+I18:I18 -> 0 | X18: =X17 -> 2419 | Y18: =X18-X17 -> 0 | Z18: =Z17 -> 136036 | AA18: =Z18-Z17 -> 0 | AB18: =SUM(Y18*$AB$2) -> 0 | AC18: =AC17 -> 1933 | AD18: =AC18-AC17 -> 0 | AE18: =AE17 -> 365210.2 | AF18: =AE18-AE17 -> 0 | AG18: =IF(AD18>0,AF18/AD18,0) -> 0 | AH18: =AF18+AA18 -> 0 | AI18: =SUM(AH18+V18) -> 0 | AJ18: =-tanks!AW19 -> 0 | AK18: =SUM(AJ18-AI18) -> 0 | AL18: =S18+L18+G18 -> 0 | AM18: =Y18+AD18 -> 0 | AN18: =AN17 -> 67 | AO18: =(AN18/100)*3000 -> 2010 | AP18: =AP17 -> 70 | AQ18: =(AP18/100)*3000 -> 2100 | AR18: =AR17 -> 70 | AS18: =(AR18/100)*3000 -> 2100 | AT18: =SUM(AO18+AQ18+AS18) -> 6210 | AU18: =AT17-AT18+AV18 -> 0 | AX18: =IF(AV18>0,AW18,AX17) -> 0.8
A19: =ELEC!C17 -> 44058 | B19: 235 | C19: 241.2 | D19: =C18-C19 -> 3.3 | E19: =D19*8.38 -> 27.654 | F19: =F18 -> 1648 | G19: =F19-F18 -> 0 | H19: =H18 -> 357868 | I19: =SUM(H19-H18) -> 0 | J19: =IF(G19>0,I19/G19,0) -> 0 | K19: =K18 -> 2107 | L19: =K19-K18 -> 0 | M19: =M18 -> 154592 | N19: =M19-M18 -> 0 | O19: =O18 -> 211.875 | P19: =P18 -> 1835 | Q19: =Q18 -> 155805 | R19: =Q19-Q18 -> 0 | S19: =SUM(P19-P18) -> 0 | T19: =SUM(S19*$T$2) -> 0 | U19: =SUM(G19+L19+S19) -> 0 | V19: =R19+N19+I19:I19 -> 0 | X19: =X18 -> 2419 | Y19: =X19-X18 -> 0 | Z19: =Z18 -> 136036 | AA19: =Z19-Z18 -> 0 | AB19: =SUM(Y19*$AB$2) -> 0 | AC19: =AC18 -> 1933 | AD19: =AC19-AC18 -> 0 | AE19: =AE18 -> 365210.2 | AF19: =AE19-AE18 -> 0 | AG19: =IF(AD19>0,AF19/AD19,0) -> 0 | AH19: =AF19+AA19 -> 0 | AI19: =SUM(AH19+V19) -> 0 | AJ19: =-tanks!AW20 -> 0 | AK19: =SUM(AJ19-AI19) -> 0 | AL19: =S19+L20+G19 -> 0 | AM19: =Y19+AD19 -> 0 | AN19: =AN18 -> 67 | AO19: =(AN19/100)*3000 -> 2010 | AP19: =AP18 -> 70 | AQ19: =(AP19/100)*3000 -> 2100 | AR19: =AR18 -> 70 | AS19: =(AR19/100)*3000 -> 2100 | AT19: =SUM(AO19+AQ19+AS19) -> 6210 | AU19: =AT18-AT19+AV19 -> 0 | AX19: =IF(AV19>0,AW19,AX18) -> 0.8
A20: =ELEC!C18 -> 44059 | B20: 234.4 | C20: 240.1 | D20: =C19-C20 -> 1.1 | E20: =D20*8.38 -> 9.218 | F20: =F19 -> 1648 | G20: =F20-F19 -> 0 | H20: =H19 -> 357868 | I20: =SUM(H20-H19) -> 0 | J20: =IF(G20>0,I20/G20,0) -> 0 | K20: =K19 -> 2107 | L20: =K20-K19 -> 0 | M20: =M19 -> 154592 | N20: =M20-M19 -> 0 | O20: =O19 -> 211.875 | P20: =P19 -> 1835 | Q20: =Q19 -> 155805 | R20: =Q20-Q19 -> 0 | S20: =SUM(P20-P19) -> 0 | T20: =SUM(S20*$T$2) -> 0 | U20: =SUM(G20+L20+S20) -> 0 | V20: =R20+N20+I20:I20 -> 0 | X20: =X19 -> 2419 | Y20: =X20-X19 -> 0 | Z20: =Z19 -> 136036 | AA20: =Z20-Z19 -> 0 | AB20: =SUM(Y20*$AB$2) -> 0 | AC20: =AC19 -> 1933 | AD20: =AC20-AC19 -> 0 | AE20: =AE19 -> 365210.2 | AF20: =AE20-AE19 -> 0 | AG20: =IF(AD20>0,AF20/AD20,0) -> 0 | AH20: =AF20+AA20 -> 0 | AI20: =SUM(AH20+V20) -> 0 | AJ20: =-tanks!AW21 -> 0 | AK20: =SUM(AJ20-AI20) -> 0 | AL20: =S20+L21+G20 -> 0 | AM20: =Y20+AD20 -> 0 | AN20: =AN19 -> 67 | AO20: =(AN20/100)*3000 -> 2010 | AP20: =AP19 -> 70 | AQ20: =(AP20/100)*3000 -> 2100 | AR20: =AR19 -> 70 | AS20: =(AR20/100)*3000 -> 2100 | AT20: =SUM(AO20+AQ20+AS20) -> 6210 | AU20: =AT19-AT20+AV20 -> 0 | AX20: =IF(AV20>0,AW20,AX19) -> 0.8
A21: 232 | B21: 232 | C21: 238.1 | D21: =C20-C21 -> 2 | E21: =D21*8.38 -> 16.76 | F21: =F20 -> 1648 | G21: =F21-F20 -> 0 | H21: =H20 -> 357868 | I21: =SUM(H21-H20) -> 0 | J21: =IF(G21>0,I21/G21,0) -> 0 | K21: =K20 -> 2107 | L21: =K21-K20 -> 0 | M21: =M20 -> 154592 | N21: =M21-M20 -> 0 | O21: =O20 -> 211.875 | P21: =P20 -> 1835 | Q21: =Q20 -> 155805 | R21: =Q21-Q20 -> 0 | S21: =SUM(P21-P20) -> 0 | T21: =SUM(S21*$T$2) -> 0 | U21: =SUM(G21+L21+S21) -> 0 | V21: =R21+N21+I21:I21 -> 0 | X21: =X20 -> 2419 | Y21: =X21-X20 -> 0 | Z21: =Z20 -> 136036 | AA21: =Z21-Z20 -> 0 | AB21: =SUM(Y21*$AB$2) -> 0 | AC21: =AC20 -> 1933 | AD21: =AC21-AC20 -> 0 | AE21: =AE20 -> 365210.2 | AF21: =AE21-AE20 -> 0 | AG21: =IF(AD21>0,AF21/AD21,0) -> 0 | AH21: =AF21+AA21 -> 0 | AI21: =SUM(AH21+V21) -> 0 | AJ21: =-tanks!AW22 -> 0 | AK21: =SUM(AJ21-AI21) -> 0 | AL21: =S21+L21+G21 -> 0 | AM21: =Y21+AD21 -> 0 | AN21: =AN20 -> 67 | AO21: =(AN21/100)*3000 -> 2010 | AP21: =AP20 -> 70 | AQ21: =(AP21/100)*3000 -> 2100 | AR21: =AR20 -> 70 | AS21: =(AR21/100)*3000 -> 2100 | AT21: =SUM(AO21+AQ21+AS21) -> 6210 | AU21: =AT20-AT21+AV21 -> 0 | AX21: =IF(AV21>0,AW21,AX20) -> 0.8
A22: =ELEC!C20 -> 44061 | B22: 230 | C22: 236 | D22: =C21-C22 -> 2.1 | E22: =D22*8.38 -> 17.598 | F22: =F21 -> 1648 | G22: =F22-F21 -> 0 | H22: =H21 -> 357868 | I22: =SUM(H22-H21) -> 0 | J22: =IF(G22>0,I22/G22,0) -> 0 | K22: 2108 | L22: =K22-K21 -> 1 | M22: 154682 | N22: =M22-M21 -> 90 | O22: =O21 -> 211.875 | P22: 1837 | Q22: 155926 | R22: =Q22-Q21 -> 121 | S22: =SUM(P22-P21) -> 2 | T22: =SUM(S22*$T$2) -> 0 | U22: =SUM(G22+L22+S22) -> 3 | V22: =R22+N22+I22:I22 -> 211 | X22: 2424 | Y22: =X22-X21 -> 5 | Z22: 136280 | AA22: =Z22-Z21 -> 244 | AB22: =SUM(Y22*$AB$2) -> 0 | AC22: =AC21 -> 1933 | AD22: =AC22-AC21 -> 0 | AE22: =AE21 -> 365210.2 | AF22: =AE22-AE21 -> 0 | AG22: =IF(AD22>0,AF22/AD22,0) -> 0 | AH22: =AF22+AA22 -> 244 | AI22: =SUM(AH22+V22) -> 455 | AJ22: =-tanks!AW23 -> 455 | AK22: =SUM(AJ22-AI22) -> 0 | AL22: =S22+L22+G22 -> 3 | AM22: =Y22+AD22 -> 5 | AN22: =AN21 -> 67 | AO22: =(AN22/100)*3000 -> 2010 | AP22: =AP21 -> 70 | AQ22: =(AP22/100)*3000 -> 2100 | AR22: =AR21 -> 70 | AS22: =(AR22/100)*3000 -> 2100 | AT22: =SUM(AO22+AQ22+AS22) -> 6210 | AU22: =AT21-AT22+AV22 -> 0 | AX22: =IF(AV22>0,AW22,AX21) -> 0.8
A23: =ELEC!C21 -> 44062 | B23: =B22 -> 230 | C23: =C22 -> 236 | D23: =C22-C23 -> 0 | E23: =D23*8.38 -> 0 | F23: =F22 -> 1648 | G23: =F23-F22 -> 0 | H23: =H22 -> 357868 | I23: =SUM(H23-H22) -> 0 | J23: =IF(G23>0,I23/G23,0) -> 0 | K23: =K22 -> 2108 | L23: =K23-K22 -> 0 | M23: =M22 -> 154682 | N23: =M23-M22 -> 0 | O23: =O22 -> 211.875 | P23: =P22 -> 1837 | Q23: =Q22 -> 155926 | R23: =Q23-Q22 -> 0 | S23: =SUM(P23-P22) -> 0 | T23: =SUM(S23*$T$2) -> 0 | U23: =SUM(G23+L23+S23) -> 0 | V23: =R23+N23+I23:I23 -> 0 | X23: =X22 -> 2424 | Y23: =X23-X22 -> 0 | Z23: =Z22 -> 136280 | AA23: =Z23-Z22 -> 0 | AB23: =SUM(Y23*$AB$2) -> 0 | AC23: =AC22 -> 1933 | AD23: =AC23-AC22 -> 0 | AE23: =AE22 -> 365210.2 | AF23: =AE23-AE22 -> 0 | AG23: =IF(AD23>0,AF23/AD23,0) -> 0 | AH23: =AF23+AA23 -> 0 | AI23: =SUM(AH23+V23) -> 0 | AJ23: =-tanks!AW24 -> 0 | AK23: =SUM(AJ23-AI23) -> 0 | AL23: =S23+L23+G23 -> 0 | AM23: =Y23+AD23 -> 0 | AN23: =AN22 -> 67 | AO23: =(AN23/100)*3000 -> 2010 | AP23: =AP22 -> 70 | AQ23: =(AP23/100)*3000 -> 2100 | AR23: =AR22 -> 70 | AS23: =(AR23/100)*3000 -> 2100 | AT23: =SUM(AO23+AQ23+AS23) -> 6210 | AU23: =AT22-AT23+AV23 -> 0 | AX23: =IF(AV23>0,AW23,AX22) -> 0.8
A24: =ELEC!C22 -> 44063 | B24: =B23 -> 230 | C24: =C23 -> 236 | D24: =C23-C24 -> 0 | E24: =D24*8.38 -> 0 | F24: =F23 -> 1648 | G24: =F24-F23 -> 0 | H24: =H23 -> 357868 | I24: =SUM(H24-H23) -> 0 | J24: =IF(G24>0,I24/G24,0) -> 0 | K24: =K23 -> 2108 | L24: =K24-K23 -> 0 | M24: =M23 -> 154682 | N24: =M24-M23 -> 0 | O24: =O23 -> 211.875 | P24: =P23 -> 1837 | Q24: =Q23 -> 155926 | R24: =Q24-Q23 -> 0 | S24: =SUM(P24-P23) -> 0 | T24: =SUM(S24*$T$2) -> 0 | U24: =SUM(G24+L24+S24) -> 0 | V24: =R24+N24+I24:I24 -> 0 | X24: =X23 -> 2424 | Y24: =X24-X23 -> 0 | Z24: =Z23 -> 136280 | AA24: =Z24-Z23 -> 0 | AB24: =SUM(Y24*$AB$2) -> 0 | AC24: =AC23 -> 1933 | AD24: =AC24-AC23 -> 0 | AE24: =AE23 -> 365210.2 | AF24: =AE24-AE23 -> 0 | AG24: =IF(AD24>0,AF24/AD24,0) -> 0 | AH24: =AF24+AA24 -> 0 | AI24: =SUM(AH24+V24) -> 0 | AJ24: =-tanks!AW25 -> 0 | AK24: =SUM(AJ24-AI24) -> 0 | AL24: =S24+L24+G24 -> 0 | AM24: =Y24+AD24 -> 0 | AN24: =AN23 -> 67 | AO24: =(AN24/100)*3000 -> 2010 | AP24: =AP23 -> 70 | AQ24: =(AP24/100)*3000 -> 2100 | AR24: =AR23 -> 70 | AS24: =(AR24/100)*3000 -> 2100 | AT24: =SUM(AO24+AQ24+AS24) -> 6210 | AU24: =AT23-AT24+AV24 -> 0 | AX24: =IF(AV24>0,AW24,AX23) -> 0.8
A25: =ELEC!C23 -> 44064 | B25: =B24 -> 230 | C25: =C24 -> 236 | D25: =C24-C25 -> 0 | E25: =D25*8.38 -> 0 | F25: =F24 -> 1648 | G25: =F25-F24 -> 0 | H25: =H24 -> 357868 | I25: =SUM(H25-H24) -> 0 | J25: =IF(G25>0,I25/G25,0) -> 0 | K25: =K24 -> 2108 | L25: =K25-K24 -> 0 | M25: =M24 -> 154682 | N25: =M25-M24 -> 0 | O25: =O24 -> 211.875 | P25: =P24 -> 1837 | Q25: =Q24 -> 155926 | R25: =Q25-Q24 -> 0 | S25: =SUM(P25-P24) -> 0 | T25: =SUM(S25*$T$2) -> 0 | U25: =SUM(G25+L25+S25) -> 0 | V25: =R25+N25+I25:I25 -> 0 | X25: =X24 -> 2424 | Y25: =X25-X24 -> 0 | Z25: =Z24 -> 136280 | AA25: =Z25-Z24 -> 0 | AB25: =SUM(Y25*$AB$2) -> 0 | AC25: =AC24 -> 1933 | AD25: =AC25-AC24 -> 0 | AE25: =AE24 -> 365210.2 | AF25: =AE25-AE24 -> 0 | AG25: =IF(AD25>0,AF25/AD25,0) -> 0 | AH25: =AF25+AA25 -> 0 | AI25: =SUM(AH25+V25) -> 0 | AJ25: =-tanks!AW26 -> 0 | AK25: =SUM(AJ25-AI25) -> 0 | AL25: =S25+L25+G25 -> 0 | AM25: =Y25+AD25 -> 0 | AN25: =AN24 -> 67 | AO25: =(AN25/100)*3000 -> 2010 | AP25: =AP24 -> 70 | AQ25: =(AP25/100)*3000 -> 2100 | AR25: =AR24 -> 70 | AS25: =(AR25/100)*3000 -> 2100 | AT25: =SUM(AO25+AQ25+AS25) -> 6210 | AU25: =AT24-AT25+AV25 -> 0 | AX25: =IF(AV25>0,AW25,AX24) -> 0.8
A26: =ELEC!C24 -> 44065 | B26: =B25 -> 230 | C26: =C25 -> 236 | D26: =C25-C26 -> 0 | E26: =D26*8.38 -> 0 | F26: =F25 -> 1648 | G26: =F26-F25 -> 0 | H26: =H25 -> 357868 | I26: =SUM(H26-H25) -> 0 | J26: =IF(G26>0,I26/G26,0) -> 0 | K26: =K25 -> 2108 | L26: =K26-K25 -> 0 | M26: =M25 -> 154682 | N26: =M26-M25 -> 0 | O26: =O25 -> 211.875 | P26: =P25 -> 1837 | Q26: =Q25 -> 155926 | R26: =Q26-Q25 -> 0 | S26: =SUM(P26-P25) -> 0 | T26: =SUM(S26*$T$2) -> 0 | U26: =SUM(G26+L26+S26) -> 0 | V26: =R26+N26+I26:I26 -> 0 | X26: =X25 -> 2424 | Y26: =X26-X25 -> 0 | Z26: =Z25 -> 136280 | AA26: =Z26-Z25 -> 0 | AB26: =SUM(Y26*$AB$2) -> 0 | AC26: =AC25 -> 1933 | AD26: =AC26-AC25 -> 0 | AE26: =AE25 -> 365210.2 | AF26: =AE26-AE25 -> 0 | AG26: =IF(AD26>0,AF26/AD26,0) -> 0 | AH26: =AF26+AA26 -> 0 | AI26: =SUM(AH26+V26) -> 0 | AJ26: =-tanks!AW27 -> 0 | AK26: =SUM(AJ26-AI26) -> 0 | AL26: =S26+L26+G26 -> 0 | AM26: =Y26+AD26 -> 0 | AN26: =AN25 -> 67 | AO26: =(AN26/100)*3000 -> 2010 | AP26: =AP25 -> 70 | AQ26: =(AP26/100)*3000 -> 2100 | AR26: =AR25 -> 70 | AS26: =(AR26/100)*3000 -> 2100 | AT26: =SUM(AO26+AQ26+AS26) -> 6210 | AU26: =AT25-AT26+AV26 -> 0 | AX26: =IF(AV26>0,AW26,AX25) -> 0.8
A27: =ELEC!C25 -> 44066 | B27: =B26 -> 230 | C27: =C26 -> 236 | D27: =C26-C27 -> 0 | E27: =D27*8.38 -> 0 | F27: =F26 -> 1648 | G27: =F27-F26 -> 0 | H27: =H26 -> 357868 | I27: =SUM(H27-H26) -> 0 | J27: =IF(G27>0,I27/G27,0) -> 0 | K27: =K26 -> 2108 | L27: =K27-K26 -> 0 | M27: =M26 -> 154682 | N27: =M27-M26 -> 0 | O27: =O26 -> 211.875 | P27: =P26 -> 1837 | Q27: =Q26 -> 155926 | R27: =Q27-Q26 -> 0 | S27: =SUM(P27-P26) -> 0 | T27: =SUM(S27*$T$2) -> 0 | U27: =SUM(G27+L27+S27) -> 0 | V27: =R27+N27+I27:I27 -> 0 | X27: =X26 -> 2424 | Y27: =X27-X26 -> 0 | Z27: =Z26 -> 136280 | AA27: =Z27-Z26 -> 0 | AB27: =SUM(Y27*$AB$2) -> 0 | AC27: =AC26 -> 1933 | AD27: =AC27-AC26 -> 0 | AE27: =AE26 -> 365210.2 | AF27: =AE27-AE26 -> 0 | AG27: =IF(AD27>0,AF27/AD27,0) -> 0 | AH27: =AF27+AA27 -> 0 | AI27: =SUM(AH27+V27) -> 0 | AJ27: =-tanks!AW28 -> 0 | AK27: =SUM(AJ27-AI27) -> 0 | AL27: =S27+L27+G27 -> 0 | AM27: =Y27+AD27 -> 0 | AN27: =AN26 -> 67 | AO27: =(AN27/100)*3000 -> 2010 | AP27: =AP26 -> 70 | AQ27: =(AP27/100)*3000 -> 2100 | AR27: =AR26 -> 70 | AS27: =(AR27/100)*3000 -> 2100 | AT27: =SUM(AO27+AQ27+AS27) -> 6210 | AU27: =AT26-AT27+AV27 -> 0 | AX27: =IF(AV27>0,AW27,AX26) -> 0.8
A28: =ELEC!C26 -> 44067 | B28: =B27 -> 230 | C28: =C27 -> 236 | D28: =C27-C28 -> 0 | E28: =D28*8.38 -> 0 | F28: =F27 -> 1648 | G28: =F28-F27 -> 0 | H28: =H27 -> 357868 | I28: =SUM(H28-H27) -> 0 | J28: =IF(G28>0,I28/G28,0) -> 0 | K28: =K27 -> 2108 | L28: =K28-K27 -> 0 | M28: =M27 -> 154682 | N28: =M28-M27 -> 0 | O28: =O27 -> 211.875 | P28: =P27 -> 1837 | Q28: =Q27 -> 155926 | R28: =Q28-Q27 -> 0 | S28: =SUM(P28-P27) -> 0 | T28: =SUM(S28*$T$2) -> 0 | U28: =SUM(G28+L28+S28) -> 0 | V28: =R28+N28+I28:I28 -> 0 | X28: =X27 -> 2424 | Y28: =X28-X27 -> 0 | Z28: =Z27 -> 136280 | AA28: =Z28-Z27 -> 0 | AB28: =SUM(Y28*$AB$2) -> 0 | AC28: =AC27 -> 1933 | AD28: =AC28-AC27 -> 0 | AE28: =AE27 -> 365210.2 | AF28: =AE28-AE27 -> 0 | AG28: =IF(AD28>0,AF28/AD28,0) -> 0 | AH28: =AF28+AA28 -> 0 | AI28: =SUM(AH28+V28) -> 0 | AJ28: =-tanks!AW29 -> 0 | AK28: =SUM(AJ28-AI28) -> 0 | AL28: =S28+L28+G28 -> 0 | AM28: =Y28+AD28 -> 0 | AN28: =AN27 -> 67 | AO28: =(AN28/100)*3000 -> 2010 | AP28: =AP27 -> 70 | AQ28: =(AP28/100)*3000 -> 2100 | AR28: =AR27 -> 70 | AS28: =(AR28/100)*3000 -> 2100 | AT28: =SUM(AO28+AQ28+AS28) -> 6210 | AU28: =AT27-AT28+AV28 -> 0 | AX28: =IF(AV28>0,AW28,AX27) -> 0.8
A29: =ELEC!C27 -> 44068 | B29: =B28 -> 230 | C29: =C28 -> 236 | D29: =C28-C29 -> 0 | E29: =D29*8.38 -> 0 | F29: =F28 -> 1648 | G29: =F29-F28 -> 0 | H29: =H28 -> 357868 | I29: =SUM(H29-H28) -> 0 | J29: =IF(G29>0,I29/G29,0) -> 0 | K29: =K28 -> 2108 | L29: =K29-K28 -> 0 | M29: =M28 -> 154682 | N29: =M29-M28 -> 0 | O29: =O28 -> 211.875 | P29: =P28 -> 1837 | Q29: =Q28 -> 155926 | R29: =Q29-Q28 -> 0 | S29: =SUM(P29-P28) -> 0 | T29: =SUM(S29*$T$2) -> 0 | U29: =SUM(G29+L29+S29) -> 0 | V29: =R29+N29+I29:I29 -> 0 | X29: =X28 -> 2424 | Y29: =X29-X28 -> 0 | Z29: =Z28 -> 136280 | AA29: =Z29-Z28 -> 0 | AB29: =SUM(Y29*$AB$2) -> 0 | AC29: =AC28 -> 1933 | AD29: =AC29-AC28 -> 0 | AE29: =AE28 -> 365210.2 | AF29: =AE29-AE28 -> 0 | AG29: =IF(AD29>0,AF29/AD29,0) -> 0 | AH29: =AF29+AA29 -> 0 | AI29: =SUM(AH29+V29) -> 0 | AJ29: =-tanks!AW30 -> 0 | AK29: =SUM(AJ29-AI29) -> 0 | AL29: =S29+L29+G29 -> 0 | AM29: =Y29+AD29 -> 0 | AN29: =AN28 -> 67 | AO29: =(AN29/100)*3000 -> 2010 | AP29: =AP28 -> 70 | AQ29: =(AP29/100)*3000 -> 2100 | AR29: =AR28 -> 70 | AS29: =(AR29/100)*3000 -> 2100 | AT29: =SUM(AO29+AQ29+AS29) -> 6210 | AU29: =AT28-AT29+AV29 -> 0 | AX29: =IF(AV29>0,AW29,AX28) -> 0.8
A30: =ELEC!C28 -> 44069 | B30: =B29 -> 230 | C30: =C29 -> 236 | D30: =C29-C30 -> 0 | E30: =D30*8.38 -> 0 | F30: =F29 -> 1648 | G30: =F30-F29 -> 0 | H30: =H29 -> 357868 | I30: =SUM(H30-H29) -> 0 | J30: =IF(G30>0,I30/G30,0) -> 0 | K30: =K29 -> 2108 | L30: =K30-K29 -> 0 | M30: =M29 -> 154682 | N30: =M30-M29 -> 0 | O30: =O29 -> 211.875 | P30: =P29 -> 1837 | Q30: =Q29 -> 155926 | R30: =Q30-Q29 -> 0 | S30: =SUM(P30-P29) -> 0 | T30: =SUM(S30*$T$2) -> 0 | U30: =SUM(G30+L30+S30) -> 0 | V30: =R30+N30+I30:I30 -> 0 | X30: =X29 -> 2424 | Y30: =X30-X29 -> 0 | Z30: =Z29 -> 136280 | AA30: =Z30-Z29 -> 0 | AB30: =SUM(Y30*$AB$2) -> 0 | AC30: =AC29 -> 1933 | AD30: =AC30-AC29 -> 0 | AE30: =AE29 -> 365210.2 | AF30: =AE30-AE29 -> 0 | AG30: =IF(AD30>0,AF30/AD30,0) -> 0 | AH30: =AF30+AA30 -> 0 | AI30: =SUM(AH30+V30) -> 0 | AJ30: =-tanks!AW31 -> 0 | AK30: =SUM(AJ30-AI30) -> 0 | AL30: =S30+L30+G30 -> 0 | AM30: =Y30+AD30 -> 0 | AN30: =AN29 -> 67 | AO30: =(AN30/100)*3000 -> 2010 | AP30: =AP29 -> 70 | AQ30: =(AP30/100)*3000 -> 2100 | AR30: =AR29 -> 70 | AS30: =(AR30/100)*3000 -> 2100 | AT30: =SUM(AO30+AQ30+AS30) -> 6210 | AU30: =AT29-AT30+AV30 -> 0 | AX30: =IF(AV30>0,AW30,AX29) -> 0.8
A31: =ELEC!C29 -> 44070 | B31: =B30 -> 230 | C31: =C30 -> 236 | D31: =C30-C31 -> 0 | E31: =D31*8.38 -> 0 | F31: =F30 -> 1648 | G31: =F31-F30 -> 0 | H31: =H30 -> 357868 | I31: =SUM(H31-H30) -> 0 | J31: =IF(G31>0,I31/G31,0) -> 0 | K31: =K30 -> 2108 | L31: =K31-K30 -> 0 | M31: =M30 -> 154682 | N31: =M31-M30 -> 0 | O31: =O30 -> 211.875 | P31: =P30 -> 1837 | Q31: =Q30 -> 155926 | R31: =Q31-Q30 -> 0 | S31: =SUM(P31-P30) -> 0 | T31: =SUM(S31*$T$2) -> 0 | U31: =SUM(G31+L31+S31) -> 0 | V31: =R31+N31+I31:I31 -> 0 | X31: =X30 -> 2424 | Y31: =X31-X30 -> 0 | Z31: =Z30 -> 136280 | AA31: =Z31-Z30 -> 0 | AB31: =SUM(Y31*$AB$2) -> 0 | AC31: =AC30 -> 1933 | AD31: =AC31-AC30 -> 0 | AE31: =AE30 -> 365210.2 | AF31: =AE31-AE30 -> 0 | AG31: =IF(AD31>0,AF31/AD31,0) -> 0 | AH31: =AF31+AA31 -> 0 | AI31: =SUM(AH31+V31) -> 0 | AJ31: =-tanks!AW32 -> 0 | AK31: =SUM(AJ31-AI31) -> 0 | AL31: =S31+L31+G31 -> 0 | AM31: =Y31+AD31 -> 0 | AN31: =AN30 -> 67 | AO31: =(AN31/100)*3000 -> 2010 | AP31: =AP30 -> 70 | AQ31: =(AP31/100)*3000 -> 2100 | AR31: =AR30 -> 70 | AS31: =(AR31/100)*3000 -> 2100 | AT31: =SUM(AO31+AQ31+AS31) -> 6210 | AU31: =AT30-AT31+AV31 -> 0 | AX31: =IF(AV31>0,AW31,AX30) -> 0.8
A32: =ELEC!C30 -> 44071 | B32: =B31 -> 230 | C32: =C31 -> 236 | D32: =C31-C32 -> 0 | E32: =D32*8.38 -> 0 | F32: =F31 -> 1648 | G32: =F32-F31 -> 0 | H32: =H31 -> 357868 | I32: =SUM(H32-H31) -> 0 | J32: =IF(G32>0,I32/G32,0) -> 0 | K32: =K31 -> 2108 | L32: =K32-K31 -> 0 | M32: =M31 -> 154682 | N32: =M32-M31 -> 0 | O32: =O31 -> 211.875 | P32: =P31 -> 1837 | Q32: =Q31 -> 155926 | R32: =Q32-Q31 -> 0 | S32: =SUM(P32-P31) -> 0 | T32: =SUM(S32*$T$2) -> 0 | U32: =SUM(G32+L32+S32) -> 0 | V32: =R32+N32+I32:I32 -> 0 | X32: =X31 -> 2424 | Y32: =X32-X31 -> 0 | Z32: =Z31 -> 136280 | AA32: =Z32-Z31 -> 0 | AB32: =SUM(Y32*$AB$2) -> 0 | AC32: =AC31 -> 1933 | AD32: =AC32-AC31 -> 0 | AE32: =AE31 -> 365210.2 | AF32: =AE32-AE31 -> 0 | AG32: =IF(AD32>0,AF32/AD32,0) -> 0 | AH32: =AF32+AA32 -> 0 | AI32: =SUM(AH32+V32) -> 0 | AJ32: =-tanks!AW33 -> 0 | AK32: =SUM(AJ32-AI32) -> 0 | AL32: =S32+L32+G32 -> 0 | AM32: =Y32+AD32 -> 0 | AN32: =AN31 -> 67 | AO32: =(AN32/100)*3000 -> 2010 | AP32: =AP31 -> 70 | AQ32: =(AP32/100)*3000 -> 2100 | AR32: =AR31 -> 70 | AS32: =(AR32/100)*3000 -> 2100 | AT32: =SUM(AO32+AQ32+AS32) -> 6210 | AU32: =AT31-AT32+AV32 -> 0 | AX32: =IF(AV32>0,AW32,AX31) -> 0.8
A33: =ELEC!C31 -> 44072 | B33: =B32 -> 230 | C33: =C32 -> 236 | D33: =C32-C33 -> 0 | E33: =D33*8.38 -> 0 | F33: =F32 -> 1648 | G33: =F33-F32 -> 0 | H33: =H32 -> 357868 | I33: =SUM(H33-H32) -> 0 | J33: =IF(G33>0,I33/G33,0) -> 0 | K33: =K32 -> 2108 | L33: =K33-K32 -> 0 | M33: =M32 -> 154682 | N33: =M33-M32 -> 0 | O33: =O32 -> 211.875 | P33: =P32 -> 1837 | Q33: =Q32 -> 155926 | R33: =Q33-Q32 -> 0 | S33: =SUM(P33-P32) -> 0 | T33: =SUM(S33*$T$2) -> 0 | U33: =SUM(G33+L33+S33) -> 0 | V33: =R33+N33+I33:I33 -> 0 | X33: =X32 -> 2424 | Y33: =X33-X32 -> 0 | Z33: =Z32 -> 136280 | AA33: =Z33-Z32 -> 0 | AB33: =SUM(Y33*$AB$2) -> 0 | AC33: =AC32 -> 1933 | AD33: =AC33-AC32 -> 0 | AE33: =AE32 -> 365210.2 | AF33: =AE33-AE32 -> 0 | AG33: =IF(AD33>0,AF33/AD33,0) -> 0 | AH33: =AF33+AA33 -> 0 | AI33: =SUM(AH33+V33) -> 0 | AJ33: =-tanks!AW34 -> 0 | AK33: =SUM(AJ33-AI33) -> 0 | AL33: =S33+L33+G33 -> 0 | AM33: =Y33+AD33 -> 0 | AN33: =AN32 -> 67 | AO33: =(AN33/100)*3000 -> 2010 | AP33: =AP32 -> 70 | AQ33: =(AP33/100)*3000 -> 2100 | AR33: =AR32 -> 70 | AS33: =(AR33/100)*3000 -> 2100 | AT33: =SUM(AO33+AQ33+AS33) -> 6210 | AU33: =AT32-AT33+AV33 -> 0 | AX33: =IF(AV33>0,AW33,AX32) -> 0.8
A34: =ELEC!C32 -> 44073 | B34: =B33 -> 230 | C34: =C33 -> 236 | D34: =C33-C34 -> 0 | E34: =D34*8.38 -> 0 | F34: =F33 -> 1648 | G34: =F34-F33 -> 0 | H34: =H33 -> 357868 | I34: =SUM(H34-H33) -> 0 | J34: =IF(G34>0,I34/G34,0) -> 0 | K34: =K33 -> 2108 | L34: =K34-K33 -> 0 | M34: =M33 -> 154682 | N34: =M34-M33 -> 0 | O34: =O33 -> 211.875 | P34: =P33 -> 1837 | Q34: =Q33 -> 155926 | R34: =Q34-Q33 -> 0 | S34: =SUM(P34-P33) -> 0 | T34: =SUM(S34*$T$2) -> 0 | U34: =SUM(G34+L34+S34) -> 0 | V34: =R34+N34+I34:I34 -> 0 | X34: =X33 -> 2424 | Y34: =X34-X33 -> 0 | Z34: =Z33 -> 136280 | AA34: =Z34-Z33 -> 0 | AB34: =SUM(Y34*$AB$2) -> 0 | AC34: =AC33 -> 1933 | AD34: =AC34-AC33 -> 0 | AE34: =AE33 -> 365210.2 | AF34: =AE34-AE33 -> 0 | AG34: =IF(AD34>0,AF34/AD34,0) -> 0 | AH34: =AF34+AA34 -> 0 | AI34: =SUM(AH34+V34) -> 0 | AJ34: =-tanks!AW35 -> 0 | AK34: =SUM(AJ34-AI34) -> 0 | AL34: =S34+L34+G34 -> 0 | AM34: =Y34+AD34 -> 0 | AN34: =AN33 -> 67 | AO34: =(AN34/100)*3000 -> 2010 | AP34: =AP33 -> 70 | AQ34: =(AP34/100)*3000 -> 2100 | AR34: =AR33 -> 70 | AS34: =(AR34/100)*3000 -> 2100 | AT34: =SUM(AO34+AQ34+AS34) -> 6210 | AU34: =AT33-AT34+AV34 -> 0 | AX34: =IF(AV34>0,AW34,AX33) -> 0.8
A35: =ELEC!C33 -> 44074 | B35: =B34 -> 230 | C35: =C34 -> 236 | D35: =C34-C35 -> 0 | E35: =D35*8.38 -> 0 | F35: =F34 -> 1648 | G35: =F35-F34 -> 0 | H35: =H34 -> 357868 | I35: =SUM(H35-H34) -> 0 | J35: =IF(G35>0,I35/G35,0) -> 0 | K35: =K34 -> 2108 | L35: =K35-K34 -> 0 | M35: =M34 -> 154682 | N35: =M35-M34 -> 0 | O35: =O34 -> 211.875 | P35: =P34 -> 1837 | Q35: =Q34 -> 155926 | R35: =Q35-Q34 -> 0 | S35: =SUM(P35-P34) -> 0 | T35: =SUM(S35*$T$2) -> 0 | U35: =SUM(G35+L35+S35) -> 0 | V35: =R35+N35+I35:I35 -> 0 | X35: =X34 -> 2424 | Y35: =X35-X34 -> 0 | Z35: =Z34 -> 136280 | AA35: =Z35-Z34 -> 0 | AB35: =SUM(Y35*$AB$2) -> 0 | AC35: =AC34 -> 1933 | AD35: =AC35-AC34 -> 0 | AE35: =AE34 -> 365210.2 | AF35: =AE35-AE34 -> 0 | AG35: =IF(AD35>0,AF35/AD35,0) -> 0 | AH35: =AF35+AA35 -> 0 | AI35: =SUM(AH35+V35) -> 0 | AJ35: =-tanks!AW37 -> 0 | AK35: =SUM(AJ35-AI35) -> 0 | AL35: =S35+L35+G35 -> 0 | AM35: =Y35+AD35 -> 0 | AN35: =AN34 -> 67 | AO35: =(AN35/100)*3000 -> 2010 | AP35: =AP34 -> 70 | AQ35: =(AP35/100)*3000 -> 2100 | AR35: =AR34 -> 70 | AS35: =(AR35/100)*3000 -> 2100 | AT35: =SUM(AO35+AQ35+AS35) -> 6210 | AU35: =AT34-AT35+AV35 -> 0 | AX35: =IF(AV35>0,AW35,AX34) -> 0.8
J36: =SUM(J5:J34)/(COUNT(J5:J34)-COUNTIF(J5:J34,0)) -> 1 | V36: =SUM(V5:V35) -> 1076 | AE36: . | AH36: =SUM(AH5:AH35) -> 927.2 | AL36: =SUM(AL5:AL35) -> 15 | AM36: =SUM(AM5:AM35) -> 18 | AR36: Nb Delivery | AS36: =COUNT(AW5:AW34) -> 0 | AU36: =SUM(AU5:AU34) -> 870 | AV36: =SUM(AV5:AV34) -> 0 | AW36: =SUM(AW5:AW34)/AS36 -> #DIV/0!
AH37: =AF37+AA37 -> 0 | AI37: =SUM(AI5:AI34) -> 2003.2
AH38: =AF38+AA38 -> 0 | AU38: =AU36*0.51 -> 443.7 | AV38: =AV36/0.51 -> 0 | AW38: =SUM(AW5:AW34)/AS36 -> #DIV/0!
AV39: =AV36*0.51 -> 0

Sheet WATER
D1: =SUM(G21:G35) -> 9086085 | AR1: Entrance | AT1: Tank 1 | AV1: Tank 2
AR2: Level | AW2: Quantity CM3 | AZ2: Var
A3: Date | B3: Truck | C3: Truck M3/day | D3: N0. Trucks | F3: REQ. # of trucks | G3: City | H3: City/day | I3: Total water delivery | K3: SW | L3: Cosum SW/day | M3: RO Guest/ Liter | O3: RO K&L/ Liter | Q3: TOTAL RO Production | R3: RO 1 RH | S3: RO 2 RH | T3: RO water counter | U3: RO Cons m3 | V3: Steam Boiler | W3: Steam Boiler/day | X3: Softener Guest | Y3: Guest Sotf/day | Z3: Softener K&L | AA3: K&L Soft/Day | AB3: Fire Tank Level | AC3: Fire Tank Counter | AE3: Laundry Hot Water Counter | AF3: Hot Water Cons/day | AG3: Laundry Cold Water Counter | AH3: Cold Water Cons/day | AI3: Laundry Water Total Cons | AJ3: K&L Sotf/day | AK3: Guest / day | AL3: K&L /day | AM3: Avg Outside Temp | AN3: Banquet Activity | AR3: Date | AT3: MainI | AV3: Kitchen and Laundry | AX3: Guest | AY3: Main Tank | AZ3: Kitchen and Laundry | BA3: Guest | BB3: Kitchen and Laundry | BC3: Main | BD3: Guest | BE3: Total VAR | BF3: Hotel Consumption
E4: 1.66 | AN4: Ball R | AO4: Meeting | AP4: outlet | AT4: 180 | AV4: 220 | AX4: 580 | AY4: =SUM(AT4) -> 180 | AZ4: =SUM(AV4) -> 220 | BA4: =SUM(AX4) -> 580
A5: =[2]WATER!$A$35 -> 44012 | B5: =[1]WATER!B36 -> 108972 | C5: =[1]WATER!C36 -> 63 | D5: =[1]WATER!D36 -> 2.3333333 | E5: =[1]WATER!E36 -> 346.51548 | F5: =[1]WATER!F36 -> 0 | G5: =[1]WATER!G36 -> 604831 | H5: =[1]WATER!H36 -> 89 | I5: =[1]WATER!I36 -> 152 | ... BG5: =[1]WATER!BG36 -> -29.7
A6: =ELEC!C3 -> 44044 | B6: 109034 | C6: =B6-B5 -> 62 | D6: =C6/27 -> 2.2962963 | E6: =SUM((C6*$E$4)+(7500/'EDl log'!$A$39)) -> 344.85548 | F6: 2 | G6: 605263 | H6: =G6-G5 -> 432 | I6: =C6+H6 -> 494 | J6: =IF(I6>0,E6/I6,0) -> 0.69808802 | K6: ='Swimming Pool quality check '!H6 -> 6543 | L6: 0 | M6: =M5 -> 457.44 | N6: =SUM(M6-M5) -> 0 | O6: =O5 -> 529.52 | P6: =SUM(O6-O5) -> 0 | Q6: =P6+N6 -> 0 | T6: 5024 | U6: =SUM(T6-T5) -> 7 | V6: 422 | W6: =+V6-V5 -> 0 | X6: 146470 | Y6: =SUM(X6-X5) -> 73 | Z6: 96315 | AA6: =Z6-Z5 -> 30 | AB6: =AB5 -> 258 | AC6: =AC5 -> 670 | AD6: 0 | AE6: 187.39 | AF6: =AE6-AE5 -> 0.81 | AG6: 1995.05 | AH6: =AG6-AG5 -> 10.01 | AI6: =AF6+AH6 -> 10.82 | AJ6: =+Z6-Z5 -> 30 | AK6: =SUM(Y6-L6) -> 73 | AL6: =SUM(AJ6-W6) -> 30 | AM6: ='General information '!D6 -> 28 | AN6: ='General information '!H6 -> 0 | AP6: ='General information '!J6 -> 613 | AR6: =A6 -> 44044 | AS6: =AS5 -> 0.9 | AT6: 128 | AU6: =AU5 -> 1.1 | AV6: 55 | AW6: 2.9 | AX6: 66 | AY6: =AS6*AT6 -> 115.2 | AZ6: =AU6*AV6 -> 60.5 | BA6: =AW6*AX6 -> 191.4 | BB6: =AY6-AY5 -> 70.2 | BC6: =AZ6-AZ5 -> -19.8 | BD6: =BA6-BA5 -> -5.8 | BE6: =SUM(BB6:BD6) -> 44.6 | BF6: =SUM(I6-BE6) -> 449.4 | BG6: =SUM(I6-BF6) -> 44.6
A7: =ELEC!C4 -> 44045 | B7: 109034 | C7: =B7-B6 -> 0 | D7: =C7/27 -> 0 | E7: =SUM((C7*$E$4)+(7500/'EDl log'!$A$39)) -> 241.93548 | G7: 605263 | H7: =G7-G6 -> 0 | I7: =C7+H7 -> 0 | J7: =IF(I7>0,E7/I7,0) -> 0 | K7: ='Swimming Pool quality check '!H7 -> 6550 | L7: =K7-K6 -> 7 | M7: =M6 -> 457.44 | N7: =SUM(M7-M6) -> 0 | O7: =O6 -> 529.52 | P7: =SUM(O7-O6) -> 0 | Q7: =P7+N7 -> 0 | T7: =T6 -> 5024 | U7: =SUM(T7-T6) -> 0 | V7: 422 | W7: =+V7-V6 -> 0 | X7: 146523 | Y7: =SUM(X7-X6) -> 53 | Z7: 96347 | AA7: =Z7-Z6 -> 32 | AB7: =AB6 -> 258 | AC7: =AC6 -> 670 | AD7: =AC7-AC6 -> 0 | AE7: 187.62 | AF7: =AE7-AE6 -> 0.23 | AG7: 2000.5 | AH7: =AG7-AG6 -> 5.45 | AI7: =AF7+AH7 -> 5.68 | AJ7: =+Z7-Z6 -> 32 | AK7: =SUM(Y7-L7) -> 46 | AL7: =SUM(AJ7-W7) -> 32 | AM7: ='General information '!D7 -> 28.5 | AN7: ='General information '!H7 -> 0 | AP7: ='General information '!J7 -> 652 | AR7: =A7 -> 44045 | AS7: =AS6 -> 0.9 | AT7: 33 | AU7: =AU6 -> 1.1 | AV7: 61 | AW7: 2.9 | AX7: 61 | AY7: =AS7*AT7 -> 29.7 | AZ7: =AU7*AV7 -> 67.1 | BA7: =AW7*AX7 -> 176.9 | BB7: =AY7-AY6 -> -85.5 | BC7: =AZ7-AZ6 -> 6.6 | BD7: =BA7-BA6 -> -14.5 | BE7: =SUM(BB7:BD7) -> -93.4 | BF7: =SUM(I7-BE7) -> 93.4 | BG7: =SUM(I7-BF7) -> -93.4
A8: =ELEC!C5 -> 44046 | B8: 109034 | C8: =B8-B7 -> 0 | D8: =C8/27 -> 0 | E8: =SUM((C8*$E$4)+(7500/'EDl log'!$A$39)) -> 241.93548 | G8: 605629 | H8: =G8-G7 -> 366 | I8: =C8+H8 -> 366 | J8: =IF(I8>0,E8/I8,0) -> 0.66102591 | K8: ='Swimming Pool quality check '!H8 -> 6555 | L8: =K8-K7 -> 5 | M8: =M7 -> 457.44 | N8: =SUM(M8-M7) -> 0 | O8: =O7 -> 529.52 | P8: =SUM(O8-O7) -> 0 | Q8: =P8+N8 -> 0 | T8: =T7 -> 5024 | U8: =SUM(T8-T7) -> 0 | V8: =V7 -> 422 | W8: =+V8-V7 -> 0 | X8: 146627 | Y8: =SUM(X8-X7) -> 104 | Z8: 96428 | AA8: =Z8-Z7 -> 81 | AB8: =AB7 -> 258 | AC8: =AC7 -> 670 | AD8: =AC8-AC7 -> 0 | AE8: 190.18 | AF8: =AE8-AE7 -> 2.56 | AG8: 2031.84 | AH8: =AG8-AG7 -> 31.34 | AI8: =AF8+AH8 -> 33.9 | AJ8: =+Z8-Z7 -> 81 | AK8: =SUM(Y8-L8) -> 99 | AL8: =SUM(AJ8-W8) -> 81 | AM8: ='General information '!D8 -> 29 | AN8: ='General information '!H8 -> 0 | AP8: ='General information '!J8 -> 0 | AR8: =A8 -> 44046 | AS8: =AS7 -> 0.9 | AT8: 45 | AU8: 1.1 | AV8: 76 | AW8: 2.9 | AX8: 72 | AY8: =AS8*AT8 -> 40.5 | AZ8: =AU8*AV8 -> 83.6 | BA8: =AW8*AX8 -> 208.8 | BB8: =AY8-AY7 -> 10.8 | BC8: =AZ8-AZ7 -> 16.5 | BD8: =BA8-BA7 -> 31.9 | BE8: =SUM(BB8:BD8) -> 59.2 | BF8: =SUM(I8-BE8) -> 306.8 | BG8: =SUM(I8-BF8) -> 59.2
A9: =ELEC!C6 -> 44047 | B9: =B8 -> 109034 | C9: =B9-B8 -> 0 | D9: =C9/27 -> 0 | E9: =SUM((C9*$E$4)+(7500/'EDl log'!$A$39)) -> 241.93548 | G9: =G8 -> 605629 | H9: =G9-G8 -> 0 | I9: =C9+H9 -> 0 | J9: =IF(I9>0,E9/I9,0) -> 0 | K9: ='Swimming Pool quality check '!H9 -> 6555 | L9: =K9-K8 -> 0 | M9: =M8 -> 457.44 | N9: =SUM(M9-M8) -> 0 | O9: =O8 -> 529.52 | P9: =SUM(O9-O8) -> 0 | Q9: =P9+N9 -> 0 | T9: =T8 -> 5024 | U9: =SUM(T9-T8) -> 0 | V9: =V8 -> 422 | W9: =+V9-V8 -> 0 | X9: =X8 -> 146627 | Y9: =SUM(X9-X8) -> 0 | Z9: =Z8 -> 96428 | AA9: =Z9-Z8 -> 0 | AB9: =AB8 -> 258 | AC9: 670 | AD9: =AC9-AC8 -> 0 | AE9: =AE8 -> 190.18 | AF9: =AE9-AE8 -> 0 | AG9: =AG8 -> 2031.84 | AH9: =AG9-AG8 -> 0 | AI9: =AF9+AH9 -> 0 | AJ9: =+Z9-Z8 -> 0 | AK9: =SUM(Y9-L9) -> 0 | AL9: =SUM(AJ9-W9) -> 0 | AM9: ='General information '!D9 -> 28.5 | AN9: ='General information '!H9 -> 0 | AP9: ='General information '!J9 -> 0 | AR9: =A9 -> 44047 | AS9: =AS8 -> 0.9 | AT9: 63 | AU9: =AU8 -> 1.1 | AV9: 26 | AW9: 2.9 | AX9: 76 | AY9: =AS9*AT9 -> 56.7 | AZ9: =AU9*AV9 -> 28.6 | BA9: =AW9*AX9 -> 220.4 | BB9: =AY9-AY8 -> 16.2 | BC9: =AZ9-AZ8 -> -55 | BD9: =BA9-BA8 -> 11.6 | BE9: =SUM(BB9:BD9) -> -27.2 | BF9: =SUM(I9-BE9) -> 27.2 | BG9: =SUM(I9-BF9) -> -27.2
A10: =ELEC!C7 -> 44048 | B10: 109096 | C10: =B10-B9 -> 62 | D10: =C10/27 -> 2.2962963 | E10: =SUM((C10*$E$4)+(7500/'EDl log'!$A$39)) -> 344.85548 | G10: 605739 | H10: =G10-G9 -> 110 | I10: =C10+H10 -> 172 | J10: =IF(I10>0,E10/I10,0) -> 2.0049737 | K10: ='Swimming Pool quality check '!H10 -> 6555 | L10: =K10-K9 -> 0 | M10: =M9 -> 457.44 | N10: =SUM(M10-M9) -> 0 | O10: =O9 -> 529.52 | P10: =SUM(O10-O9) -> 0 | Q10: =P10+N10 -> 0 | T10: 5040 | U10: =SUM(T10-T9) -> 16 | V10: 425 | W10: =+V10-V9 -> 3 | X10: 146640 | Y10: =SUM(X10-X9) -> 13 | Z10: 96450 | AA10: =Z10-Z9 -> 22 | AB10: =AB9 -> 258 | AC10: 670 | AD10: =AC10-AC9 -> 0 | AE10: 190.18 | AF10: =AE10-AE9 -> 0 | AG10: =AG9 -> 2031.84 | AH10: =AG10-AG9 -> 0 | AI10: =AF10+AH10 -> 0 | AJ10: =+Z10-Z9 -> 22 | AK10: =SUM(Y10-L10) -> 13 | AL10: =SUM(AJ10-W10) -> 19 | AM10: ='General information '!D10 -> 28.5 | AN10: ='General information '!H10 -> 0 | AP10: ='General information '!J10 -> 0 | AR10: =A10 -> 44048 | AS10: =AS9 -> 0.9 | AT10: 83 | AU10: =AU9 -> 1.1 | AV10: 76 | AW10: 2.9 | AX10: 62 | AY10: =AS10*AT10 -> 74.7 | AZ10: =AU10*AV10 -> 83.6 | BA10: =AW10*AX10 -> 179.8 | BB10: =AY10-AY9 -> 18 | BC10: =AZ10-AZ9 -> 55 | BD10: =BA10-BA9 -> -40.6 | BE10: =SUM(BB10:BD10) -> 32.4 | BF10: =SUM(I10-BE10) -> 139.6 | BG10: =SUM(I10-BF10) -> 32.4
A11: =ELEC!C8 -> 44049 | B11: =B10 -> 109096 | C11: =B11-B10 -> 0 | D11: =C11/27 -> 0 | E11: =SUM((C11*$E$4)+(7500/'EDl log'!$A$39)) -> 241.93548 | G11: =G10 -> 605739 | H11: =G11-G10 -> 0 | I11: =C11+H11 -> 0 | J11: =IF(I11>0,E11/I11,0) -> 0 | K11: ='Swimming Pool quality check '!H11 -> 6555 | L11: =K11-K10 -> 0 | M11: =M10 -> 457.44 | N11: =SUM(M11-M10) -> 0 | O11: =O10 -> 529.52 | P11: =SUM(O11-O10) -> 0 | Q11: =SUM(P11+N11) -> 0 | T11: =T10 -> 5040 | U11: =SUM(T11-T10) -> 0 | V11: =V10 -> 425 | W11: =+V11-V10 -> 0 | X11: =X10 -> 146640 | Y11: =SUM(X11-X10) -> 0 | Z11: =Z10 -> 96450 | AA11: =Z11-Z10 -> 0 | AB11: =AB10 -> 258 | AC11: 670 | AD11: =AC11-AC10 -> 0 | AE11: =AE10 -> 190.18 | AF11: =AE11-AE10 -> 0 | AG11: =AG10 -> 2031.84 | AH11: =AG11-AG10 -> 0 | AI11: =AF11+AH11 -> 0 | AJ11: =+Z11-Z10 -> 0 | AK11: =SUM(Y11-L11) -> 0 | AL11: =SUM(AJ11-W11) -> 0 | AM11: ='General information '!D11 -> 28.5 | AN11: ='General information '!H11 -> 0 | AP11: ='General information '!J11 -> 0 | AR11: =A11 -> 44049 | AS11: =AS10 -> 0.9 | AT11: 89 | AU11: =AU10 -> 1.1 | AV11: 68 | AW11: 2.9 | AX11: 60 | AY11: =AS11*AT11 -> 80.1 | AZ11: =AU11*AV11 -> 74.8 | BA11: =AW11*AX11 -> 174 | BB11: =AY11-AY10 -> 5.4 | BC11: =AZ11-AZ10 -> -8.8 | BD11: =BA11-BA10 -> -5.8 | BE11: =SUM(BB11:BD11) -> -9.2 | BF11: =SUM(I11-BE11) -> 9.2 | BG11: =SUM(I11-BF11) -> -9.2
A12: =ELEC!C9 -> 44050 | B12: 109096 | C12: =B12-B11 -> 0 | D12: =C12/27 -> 0 | E12: =SUM((C12*$E$4)+(7500/'EDl log'!$A$39)) -> 241.93548 | G12: 605739 | H12: =G12-G11 -> 0 | I12: =C12+H12 -> 0 | J12: =IF(I12>0,E12/I12,0) -> 0 | K12: ='Swimming Pool quality check '!H12 -> 6555 | L12: =K12-K11 -> 0 | M12: =M11 -> 457.44 | N12: =SUM(M12-M11) -> 0 | O12: =O11 -> 529.52 | P12: =SUM(O12-O11) -> 0 | Q12: =SUM(P12+N12) -> 0 | T12: =T11 -> 5040 | U12: =SUM(T12-T11) -> 0 | V12: =V11 -> 425 | W12: =+V12-V11 -> 0 | X12: 146710 | Y12: =SUM(X12-X11) -> 70 | Z12: 96490 | AA12: =Z12-Z11 -> 40 | AB12: =AB11 -> 258 | AC12: =AC11 -> 670 | AD12: =AC12-AC11 -> 0 | AE12: 190.66 | AF12: =AE12-AE11 -> 0.48 | AG12: 2038.22 | AH12: =AG12-AG11 -> 6.38 | AI12: =AF12+AH12 -> 6.86 | AJ12: =+Z12-Z11 -> 40 | AK12: =SUM(Y12-L12) -> 70 | AL12: =SUM(AJ12-W12) -> 40 | AM12: ='General information '!D12 -> 27 | AN12: ='General information '!H12 -> 0 | AP12: ='General information '!J12 -> 0 | AR12: =A12 -> 44050 | AS12: =AS11 -> 0.9 | AT12: 153 | AU12: =AU11 -> 1.1 | AV12: 94 | AW12: 2.9 | AX12: 75 | AY12: =AS12*AT12 -> 137.7 | AZ12: =AU12*AV12 -> 103.4 | BA12: =AW12*AX12 -> 217.5 | BB12: =AY12-AY11 -> 57.6 | BC12: =AZ12-AZ11 -> 28.6 | BD12: =BA12-BA11 -> 43.5 | BE12: =SUM(BB12:BD12) -> 129.7 | BF12: =SUM(I12-BE12) -> -129.7 | BG12: =SUM(I12-BF12) -> 129.7
A13: =ELEC!C10 -> 44051 | B13: =B12 -> 109096 | C13: =B13-B12 -> 0 | D13: =C13/27 -> 0 | E13: =SUM((C13*$E$4)+(7500/'EDl log'!$A$39)) -> 241.93548 | G13: =G12 -> 605739 | H13: =G13-G12 -> 0 | I13: =C13+H13 -> 0 | J13: =IF(I13>0,E13/I13,0) -> 0 | K13: ='Swimming Pool quality check '!H13 -> 6555 | L13: =K13-K12 -> 0 | M13: =M12 -> 457.44 | N13: =SUM(M13-M12) -> 0 | O13: =O12 -> 529.52 | P13: =SUM(O13-O12) -> 0 | Q13: =SUM(P13+N13) -> 0 | T13: =T12 -> 5040 | U13: =SUM(T13-T12) -> 0 | V13: =V12 -> 425 | W13: =+V13-V12 -> 0 | X13: 146786 | Y13: =SUM(X13-X12) -> 76 | Z13: 96522 | AA13: =Z13-Z12 -> 32 | AB13: =AB12 -> 258 | AC13: =AC12 -> 670 | AD13: =AC13-AC12 -> 0 | AE13: =AE12 -> 190.66 | AF13: =AE13-AE12 -> 0 | AG13: =AG12 -> 2038.22 | AH13: =AG13-AG12 -> 0 | AI13: =AF13+AH13 -> 0 | AJ13: =+Z13-Z12 -> 32 | AK13: =SUM(Y13-L13) -> 76 | AL13: =SUM(AJ13-W13) -> 32 | AM13: ='General information '!D13 -> 28.5 | AN13: ='General information '!J13 -> 0 | AP13: ='General information '!J13 -> 0 | AR13: =A13 -> 44051 | AS13: =AS12 -> 0.9 | AT13: 55 | AU13: =AU12 -> 1.1 | AV13: 114 | AW13: 2.9 | AX13: 93 | AY13: =AS13*AT13 -> 49.5 | AZ13: =AU13*AV13 -> 125.4 | BA13: =AW13*AX13 -> 269.7 | BB13: =AY13-AY12 -> -88.2 | BC13: =AZ13-AZ12 -> 22 | BD13: =BA13-BA12 -> 52.2 | BE13: =SUM(BB13:BD13) -> -14 | BF13: =SUM(I13-BE13) -> 14 | BG13: =SUM(I13-BF13) -> -14
A14: =ELEC!C11 -> 44052 | B14: =B13 -> 109096 | C14: =B14-B13 -> 0 | D14: =C14/27 -> 0 | E14: =SUM((C14*$E$4)+(7500/'EDl log'!$A$39)) -> 241.93548 | G14: =G13 -> 605739 | H14: =G14-G13 -> 0 | I14: =C14+H14 -> 0 | J14: =IF(I14>0,E14/I14,0) -> 0 | K14: ='Swimming Pool quality check '!H14 -> 6555 | L14: =K14-K13 -> 0 | M14: =M13 -> 457.44 | N14: =SUM(M14-M13) -> 0 | O14: =O13 -> 529.52 | P14: =SUM(O14-O13) -> 0 | Q14: =SUM(P14+N14) -> 0 | T14: =T13 -> 5040 | U14: =SUM(T14-T13) -> 0 | V14: =V13 -> 425 | W14: =+V14-V13 -> 0 | X14: 146911 | Y14: =SUM(X14-X13) -> 125 | Z14: 96523 | AA14: =Z14-Z13 -> 1 | AB14: =AB13 -> 258 | AC14: =AC13 -> 670 | AD14: =AC14-AC13 -> 0 | AE14: =AE13 -> 190.66 | AF14: =AE14-AE13 -> 0 | AG14: =AG13 -> 2038.22 | AH14: =AG14-AG13 -> 0 | AI14: =AF14+AH14 -> 0 | AJ14: =+Z14-Z13 -> 1 | AK14: =SUM(Y14-L14) -> 125 | AL14: =SUM(AJ14-W14) -> 1 | AM14: ='General information '!D14 -> 29 | AN14: ='General information '!H14 -> 0 | AP14: ='General information '!J14 -> 0 | AR14: =A14 -> 44052 | AS14: =AS13 -> 0.9 | AT14: 151 | AU14: =AU13 -> 1.1 | AV14: 103 | AW14: 2.9 | AX14: 124 | AY14: =AS14*AT14 -> 135.9 | AZ14: =AU14*AV14 -> 113.3 | BA14: =AW14*AX14 -> 359.6 | BB14: =AY14-AY13 -> 86.4 | BC14: =AZ14-AZ13 -> -12.1 | BD14: =BA14-BA13 -> 89.9 | BE14: =SUM(BB14:BD14) -> 164.2 | BF14: =SUM(I14-BE14) -> -164.2 | BG14: =SUM(I14-BF14) -> 164.2
A15: =ELEC!C12 -> 44053 | B15: =B14 -> 109096 | C15: =B15-B14 -> 0 | D15: =C15/27 -> 0 | E15: =SUM((C15*$E$4)+(7500/'EDl log'!$A$39)) -> 241.93548 | G15: =G14 -> 605739 | H15: =G15-G14 -> 0 | I15: =C15+H15 -> 0 | J15: =IF(I15>0,E15/I15,0) -> 0 | K15: ='Swimming Pool quality check '!H15 -> 6555 | L15: =K15-K14 -> 0 | M15: =M14 -> 457.44 | N15: =SUM(M15-M14) -> 0 | O15: =O14 -> 529.52 | P15: =SUM(O15-O14) -> 0 | Q15: =SUM(P15+N15) -> 0 | T15: =T14 -> 5040 | U15: =SUM(T15-T14) -> 0 | V15: =V14 -> 425 | W15: =+V15-V14 -> 0 | X15: 147011 | Y15: =SUM(X15-X14) -> 100 | Z15: 96574 | AA15: =Z15-Z14 -> 51 | AB15: =AB14 -> 258 | AC15: =AC14 -> 670 | AD15: =AC15-AC14 -> 0 | AE15: =AE14 -> 190.66 | AF15: =AE15-AE14 -> 0 | AG15: =AG14 -> 2038.22 | AH15: =AG15-AG14 -> 0 | AI15: =AF15+AH15 -> 0 | AJ15: =+Z15-Z14 -> 51 | AK15: =SUM(Y15-L15) -> 100 | AL15: =SUM(AJ15-W15) -> 51 | AM15: ='General information '!D15 -> 27 | AN15: ='General information '!H15 -> 0 | AP15: ='General information '!J15 -> 0 | AR15: =A15 -> 44053 | AS15: =AS14 -> 0.9 | AT15: 7 | AU15: =AU14 -> 1.1 | AV15: 141 | AW15: 2.9 | AX15: 146 | AY15: =AS15*AT15 -> 6.3 | AZ15: =AU15*AV15 -> 155.1 | BA15: =AW15*AX15 -> 423.4 | BB15: =AY15-AY14 -> -129.6 | BC15: =AZ15-AZ14 -> 41.8 | BD15: =BA15-BA14 -> 63.8 | BE15: =SUM(BB15:BD15) -> -24 | BF15: =SUM(I15-BE15) -> 24 | BG15: =SUM(I15-BF15) -> -24
A16: =ELEC!C13 -> 44054 | B16: 109096 | C16: =B16-B15 -> 0 | D16: =C16/27 -> 0 | E16: =SUM((C16*$E$4)+(7500/'EDl log'!$A$39)) -> 241.93548 | G16: =G15 -> 605739 | H16: =G16-G15 -> 0 | I16: =C16+H16 -> 0 | J16: =IF(I16>0,E16/I16,0) -> 0 | K16: ='Swimming Pool quality check '!H16 -> 6555 | L16: =K16-K15 -> 0 | M16: =M15 -> 457.44 | N16: =SUM(M16-M15) -> 0 | O16: =O15 -> 529.52 | P16: =SUM(O16-O15) -> 0 | Q16: =SUM(P16+N16) -> 0 | T16: =T15 -> 5040 | U16: =SUM(T16-T15) -> 0 | V16: =V15 -> 425 | W16: =+V16-V15 -> 0 | X16: 147040 | Y16: =SUM(X16-X15) -> 29 | Z16: 96585 | AA16: =Z16-Z15 -> 11 | AB16: 264 | AC16: 698 | AD16: =AC16-AC15 -> 28 | AE16: 190.66 | AF16: =AE16-AE15 -> 0 | AG16: =AG15 -> 2038.22 | AH16: =AG16-AG15 -> 0 | AI16: =AF16+AH16 -> 0 | AJ16: =+Z16-Z15 -> 11 | AK16: =SUM(Y16-L16) -> 29 | AL16: =SUM(AJ16-W16) -> 11 | AM16: ='General information '!D16 -> 28.5 | AN16: ='General information '!H16 -> 0 | AP16: ='General information '!J16 -> 0 | AR16: =A16 -> 44054 | AS16: =AS15 -> 0.9 | AT16: 171 | AU16: =AU15 -> 1.1 | AV16: 156 | AW16: 2.9 | AX16: 152 | AY16: =AS16*AT16 -> 153.9 | AZ16: =AU16*AV16 -> 171.6 | BA16: =AW16*AX16 -> 440.8 | BB16: =AY16-AY15 -> 147.6 | BC16: =AZ16-AZ15 -> 16.5 | BD16: =BA16-BA15 -> 17.4 | BE16: =SUM(BB16:BD16) -> 181.5 | BF16: =SUM(I16-BE16) -> -181.5 | BG16: =SUM(I16-BF16) -> 181.5
A17: =ELEC!C14 -> 44055 | B17: =B16 -> 109096 | C17: =B17-B16 -> 0 | D17: =C17/27 -> 0 | E17: =SUM((C17*$E$4)+(7500/'EDl log'!$A$39)) -> 241.93548 | G17: =G16 -> 605739 | H17: =G17-G16 -> 0 | I17: =C17+H17 -> 0 | J17: =IF(I17>0,E17/I17,0) -> 0 | K17: ='Swimming Pool quality check '!H17 -> 6555 | L17: =K17-K16 -> 0 | M17: =M16 -> 457.44 | N17: =SUM(M17-M16) -> 0 | O17: =O16 -> 529.52 | P17: =SUM(O17-O16) -> 0 | Q17: =SUM(P17+N17) -> 0 | T17: =T16 -> 5040 | U17: =SUM(T17-T16) -> 0 | V17: =V16 -> 425 | W17: =+V17-V16 -> 0 | X17: =X16 -> 147040 | Y17: =SUM(X17-X16) -> 0 | Z17: 96616 | AA17: =Z17-Z16 -> 31 | AB17: =AB16 -> 264 | AC17: =AC16 -> 698 | AD17: =AC17-AC16 -> 0 | AE17: =AE16 -> 190.66 | AF17: =AE17-AE16 -> 0 | AG17: =AG16 -> 2038.22 | AH17: =AG17-AG16 -> 0 | AI17: =AF17+AH17 -> 0 | AJ17: =+Z17-Z16 -> 31 | AK17: =SUM(Y17-L17) -> 0 | AL17: =SUM(AJ17-W17) -> 31 | AM17: ='General information '!D17 -> 28 | AN17: ='General information '!H17 -> 0 | AP17: ='General information '!J17 -> 0 | AR17: =A17 -> 44055 | AS17: =AS16 -> 0.9 | AT17: 29 | AU17: =AU16 -> 1.1 | AV17: 168 | AW17: 2.9 | AX17: 180 | AY17: =AS17*AT17 -> 26.1 | AZ17: =AU17*AV17 -> 184.8 | BA17: =AW17*AX17 -> 522 | BB17: =AY17-AY16 -> -127.8 | BC17: =AZ17-AZ16 -> 13.2 | BD17: =BA17-BA16 -> 81.2 | BE17: =SUM(BB17:BD17) -> -33.4 | BF17: =SUM(I17-BE17) -> 33.4 | BG17: =SUM(I17-BF17) -> -33.4
A18: =ELEC!C15 -> 44056 | B18: 109096 | C18: =B18-B17 -> 0 | D18: =C18/27 -> 0 | E18: =SUM((C18*$E$4)+(7500/'EDl log'!$A$39)) -> 241.93548 | G18: =G17 -> 605739 | H18: =G18-G17 -> 0 | I18: =C18+H18 -> 0 | J18: =IF(I18>0,E18/I18,0) -> 0 | K18: ='Swimming Pool quality check '!H18 -> 6555 | L18: =K18-K17 -> 0 | M18: =M17 -> 457.44 | N18: =SUM(M18-M17) -> 0 | O18: =O17 -> 529.52 | P18: =SUM(O18-O17) -> 0 | Q18: =SUM(P18+N18) -> 0 | T18: =T17 -> 5040 | U18: =SUM(T18-T17) -> 0 | V18: =V17 -> 425 | W18: =+V18-V17 -> 0 | X18: =X17 -> 147040 | Y18: =SUM(X18-X17) -> 0 | Z18: =Z17 -> 96616 | AA18: =Z18-Z17 -> 0 | AB18: =AB17 -> 264 | AC18: =AC17 -> 698 | AD18: =AC18-AC17 -> 0 | AE18: =AE17 -> 190.66 | AF18: =AE18-AE17 -> 0 | AG18: =AG17 -> 2038.22 | AH18: =AG18-AG17 -> 0 | AI18: =AF18+AH18 -> 0 | AJ18: =+Z18-Z17 -> 0 | AK18: =SUM(Y18-L18) -> 0 | AL18: =SUM(AJ18-W18) -> 0 | AM18: ='General information '!D18 -> 27.5 | AN18: ='General information '!H18 -> 0 | AP18: ='General information '!J18 -> 0 | AR18: =A18 -> 44056 | AS18: =AS17 -> 0.9 | AT18: 185 | AU18: =AU17 -> 1.1 | AV18: 201 | AW18: 2.9 | AX18: 202 | AY18: =AS18*AT18 -> 166.5 | AZ18: =AU18*AV18 -> 221.1 | BA18: =AW18*AX18 -> 585.8 | BB18: =AY18-AY17 -> 140.4 | BC18: =AZ18-AZ17 -> 36.3 | BD18: =BA18-BA17 -> 63.8 | BE18: =SUM(BB18:BD18) -> 240.5 | BF18: =SUM(I18-BE18) -> -240.5 | BG18: =SUM(I18-BF18) -> 240.5
A19: =ELEC!C16 -> 44057 | B19: =B18 -> 109096 | C19: =B19-B18 -> 0 | D19: =C19/27 -> 0 | E19: =SUM((C19*$E$4)+(7500/'EDl log'!$A$39)) -> 241.93548 | G19: =G18 -> 605739 | H19: =G19-G18 -> 0 | I19: =C19+H19 -> 0 | J19: =IF(I19>0,E19/I19,0) -> 0 | K19: ='Swimming Pool quality check '!H19 -> 6555 | L19: =K19-K18 -> 0 | M19: =M18 -> 457.44 | N19: =SUM(M19-M18) -> 0 | O19: =O18 -> 529.52 | P19: =SUM(O19-O18) -> 0 | Q19: =SUM(P19+N19) -> 0 | T19: =T18 -> 5040 | U19: =SUM(T19-T18) -> 0 | V19: =V18 -> 425 | W19: =+V19-V18 -> 0 | X19: =X18 -> 147040 | Y19: =SUM(X19-X18) -> 0 | Z19: =Z18 -> 96616 | AA19: =Z19-Z18 -> 0 | AB19: =AB18 -> 264 | AC19: =AC18 -> 698 | AD19: =AC19-AC18 -> 0 | AE19: =AE18 -> 190.66 | AF19: =AE19-AE18 -> 0 | AG19: =AG18 -> 2038.22 | AH19: =AG19-AG18 -> 0 | AI19: =AF19+AH19 -> 0 | AJ19: =+Z19-Z18 -> 0 | AK19: =SUM(Y19-L19) -> 0 | AL19: =SUM(AJ19-W19) -> 0 | AM19: ='General information '!D19 -> 27.5 | AN19: ='General information '!H19 -> 0 | AP19: ='General information '!J19 -> 0 | AR19: =A19 -> 44057 | AS19: =AS18 -> 0.9 | AT19: =AT18 -> 185 | AU19: =AU18 -> 1.1 | AV19: =AV18 -> 201 | AW19: 2.9 | AX19: =AX18 -> 202 | AY19: =AS19*AT19 -> 166.5 | AZ19: =AU19*AV19 -> 221.1 | BA19: =AW19*AX19 -> 585.8 | BB19: =AY19-AY18 -> 0 | BC19: =AZ19-AZ18 -> 0 | BD19: =BA19-BA18 -> 0 | BE19: =SUM(BB19:BD19) -> 0 | BF19: =SUM(I19-BE19) -> 0 | BG19: =SUM(I19-BF19) -> 0
A20: =ELEC!C17 -> 44058 | B20: =B19 -> 109096 | C20: =B20-B19 -> 0 | D20: =C20/27 -> 0 | E20: =SUM((C20*$E$4)+(7500/'EDl log'!$A$39)) -> 241.93548 | G20: =G19 -> 605739 | H20: =G20-G19 -> 0 | I20: =C20+H20 -> 0 | J20: =IF(I20>0,E20/I20,0) -> 0 | K20: ='Swimming Pool quality check '!H20 -> 6555 | L20: =K20-K19 -> 0 | M20: =M19 -> 457.44 | N20: =SUM(M20-M19) -> 0 | O20: =O19 -> 529.52 | P20: =SUM(O20-O19) -> 0 | Q20: =SUM(P20+N20) -> 0 | T20: =T19 -> 5040 | U20: =SUM(T20-T19) -> 0 | V20: =V19 -> 425 | W20: =+V20-V19 -> 0 | X20: 147253 | Y20: =SUM(X20-X19) -> 213 | Z20: 96647 | AA20: =Z20-Z19 -> 31 | AB20: =AB19 -> 264 | AC20: =AC19 -> 698 | AD20: =AC20-AC19 -> 0 | AE20: =AE19 -> 190.66 | AF20: =AE20-AE19 -> 0 | AG20: =AG19 -> 2038.22 | AH20: =AG20-AG19 -> 0 | AI20: =AF20+AH20 -> 0 | AJ20: =+Z20-Z19 -> 31 | AK20: =SUM(Y20-L20) -> 213 | AL20: =SUM(AJ20-W20) -> 31 | AM20: ='General information '!D20 -> 27.5 | AN20: ='General information '!H20 -> 0 | AP20: ='General information '!J20 -> 0 | AR20: =A20 -> 44058 | AS20: =AS19 -> 0.9 | AT20: 183 | AU20: =AU19 -> 1.1 | AV20: 187 | AW20: 2.9 | AX20: 197 | AY20: =AS20*AT20 -> 164.7 | AZ20: =AU20*AV20 -> 205.7 | BA20: =AW20*AX20 -> 571.3 | BB20: =AY20-AY19 -> -1.8 | BC20: =AZ20-AZ19 -> -15.4 | BD20: =BA20-BA19 -> -14.5 | BE20: =SUM(BB20:BD20) -> -31.7 | BF20: =SUM(I20-BE20) -> 31.7 | BG20: =SUM(I20-BF20) -> -31.7
A21: =ELEC!C18 -> 44059 | B21: =B20 -> 109096 | C21: =B21-B20 -> 0 | D21: =C21/27 -> 0 | E21: =SUM((C21*$E$4)+(7500/'EDl log'!$A$39)) -> 241.93548 | G21: =G20 -> 605739 | H21: =G21-G20 -> 0 | I21: =C21+H21 -> 0 | J21: =IF(I21>0,E21/I21,0) -> 0 | K21: ='Swimming Pool quality check '!H21 -> 6555 | L21: =K21-K20 -> 0 | M21: =M20 -> 457.44 | N21: =SUM(M21-M20) -> 0 | O21: =O20 -> 529.52 | P21: =SUM(O21-O20) -> 0 | Q21: =SUM(P21+N21) -> 0 | T21: =T20 -> 5040 | U21: =SUM(T21-T20) -> 0 | V21: =V20 -> 425 | W21: =+V21-V20 -> 0 | X21: =X20 -> 147253 | Y21: =SUM(X21-X20) -> 0 | Z21: =Z20 -> 96647 | AA21: =Z21-Z20 -> 0 | AB21: =AB20 -> 264 | AC21: =AC20 -> 698 | AD21: =AC21-AC20 -> 0 | AE21: =AE20 -> 190.66 | AF21: =AE21-AE20 -> 0 | AG21: =AG20 -> 2038.22 | AH21: =AG21-AG20 -> 0 | AI21: =AF21+AH21 -> 0 | AJ21: =+Z21-Z20 -> 0 | AK21: =SUM(Y21-L21) -> 0 | AL21: =SUM(AJ21-W21) -> 0 | AM21: ='General information '!D21 -> 28 | AN21: ='General information '!H21 -> 0 | AP21: ='General information '!J21 -> 0 | AR21: =A21 -> 44059 | AS21: =AS20 -> 0.9 | AT21: =AT20 -> 183 | AU21: =AU20 -> 1.1 | AV21: 184 | AW21: 2.9 | AX21: 196 | AY21: =AS21*AT21 -> 164.7 | AZ21: =AU21*AV21 -> 202.4 | BA21: =AW21*AX21 -> 568.4 | BB21: =AY21-AY20 -> 0 | BC21: =AZ21-AZ20 -> -3.3 | BD21: =BA21-BA20 -> -2.9 | BE21: =SUM(BB21:BD21) -> -6.2 | BF21: =SUM(I21-BE21) -> 6.2 | BG21: =SUM(I21-BF21) -> -6.2
A22: =ELEC!C19 -> 44060 | B22: =B21 -> 109096 | C22: =B22-B21 -> 0 | D22: =C22/27 -> 0 | E22: =SUM((C22*$E$4)+(7500/'EDl log'!$A$39)) -> 241.93548 | F22: 2 | G22: =G21 -> 605739 | H22: =G22-G21 -> 0 | I22: =C22+H22 -> 0 | J22: =IF(I22>0,E22/I22,0) -> 0 | K22: ='Swimming Pool quality check '!H22 -> 6555 | L22: =K22-K21 -> 0 | M22: =M21 -> 457.44 | N22: =SUM(M22-M21) -> 0 | O22: =O21 -> 529.52 | P22: =SUM(O22-O21) -> 0 | Q22: =SUM(P22+N22) -> 0 | T22: =T21 -> 5040 | U22: =SUM(T22-T21) -> 0 | V22: =V21 -> 425 | W22: =+V22-V21 -> 0 | X22: =X21 -> 147253 | Y22: =SUM(X22-X21) -> 0 | Z22: =Z21 -> 96647 | AA22: =Z22-Z21 -> 0 | AB22: =AB21 -> 264 | AC22: =AC21 -> 698 | AD22: =AC22-AC21 -> 0 | AE22: =AE21 -> 190.66 | AF22: =AE22-AE21 -> 0 | AG22: =AG21 -> 2038.22 | AH22: =AG22-AG21 -> 0 | AI22: =AF22+AH22 -> 0 | AJ22: =+Z22-Z21 -> 0 | AK22: =SUM(Y22-L22) -> 0 | AL22: =SUM(AJ22-W22) -> 0 | AM22: ='General information '!D22 -> 28.5 | AN22: ='General information '!H22 -> 0 | AP22: ='General information '!J22 -> 0 | AR22: =A22 -> 44060 | AS22: =AS21 -> 0.9 | AT22: 183 | AU22: =AU21 -> 1.1 | AV22: 180 | AW22: 2.9 | AX22: 194 | AY22: =AS22*AT22 -> 164.7 | AZ22: =AU22*AV22 -> 198 | BA22: =AW22*AX22 -> 562.6 | BB22: =AY22-AY21 -> 0 | BC22: =AZ22-AZ21 -> -4.4 | BD22: =BA22-BA21 -> -5.8 | BE22: =SUM(BB22:BD22) -> -10.2 | BF22: =SUM(I22-BE22) -> 10.2 | BG22: =SUM(I22-BF22) -> -10.2
A23: =ELEC!C20 -> 44061 | B23: =B22 -> 109096 | C23: =B23-B22 -> 0 | D23: =C23/27 -> 0 | E23: =SUM((C23*$E$4)+(7500/'EDl log'!$A$39)) -> 241.93548 | G23: =G22 -> 605739 | H23: =G23-G22 -> 0 | I23: =C23+H23 -> 0 | J23: =IF(I23>0,E23/I23,0) -> 0 | K23: ='Swimming Pool quality check '!H23 -> 6555 | L23: =K23-K22 -> 0 | M23: =M22 -> 457.44 | N23: =SUM(M23-M22) -> 0 | O23: =O22 -> 529.52 | P23: =SUM(O23-O22) -> 0 | Q23: =SUM(P23+N23) -> 0 | T23: =T22 -> 5040 | U23: =SUM(T23-T22) -> 0 | V23: =V22 -> 425 | W23: =+V23-V22 -> 0 | X23: 147294 | Y23: =SUM(X23-X22) -> 41 | Z23: 96674 | AA23: =Z23-Z22 -> 27 | AB23: =AB22 -> 264 | AC23: =AC22 -> 698 | AD23: =AC23-AC22 -> 0 | AE23: 193.63 | AF23: =AE23-AE22 -> 2.97 | AG23: 2064.68 | AH23: =AG23-AG22 -> 26.46 | AI23: =AF23+AH23 -> 29.43 | AJ23: =+Z23-Z22 -> 27 | AK23: =SUM(Y23-L23) -> 41 | AL23: =SUM(AJ23-W23) -> 27 | AM23: ='General information '!D23 -> 0 | AN23: ='General information '!H23 -> 0 | AP23: ='General information '!J23 -> 0 | AR23: =A23 -> 44061 | AS23: =AS22 -> 0.9 | AT23: 110 | AU23: =AU22 -> 1.1 | AV23: 170 | AW23: 2.9 | AX23: 200 | AY23: =AS23*AT23 -> 99 | AZ23: =AU23*AV23 -> 187 | BA23: =AW23*AX23 -> 580 | BB23: =AY23-AY22 -> -65.7 | BC23: =AZ23-AZ22 -> -11 | BD23: =BA23-BA22 -> 17.4 | BE23: =SUM(BB23:BD23) -> -59.3 | BF23: =SUM(I23-BE23) -> 59.3 | BG23: =SUM(I23-BF23) -> -59.3
A24: =ELEC!C21 -> 44062 | B24: =B23 -> 109096 | C24: =B24-B23 -> 0 | D24: =C24/27 -> 0 | E24: =SUM((C24*$E$4)+(7500/'EDl log'!$A$39)) -> 241.93548 | G24: =G23 -> 605739 | H24: =G24-G23 -> 0 | I24: =C24+H24 -> 0 | J24: =IF(I24>0,E24/I24,0) -> 0 | K24: ='Swimming Pool quality check '!H24 -> 6555 | L24: =K24-K23 -> 0 | M24: =M23 -> 457.44 | N24: =SUM(M24-M23) -> 0 | O24: =O23 -> 529.52 | P24: =SUM(O24-O23) -> 0 | Q24: =SUM(P24+N24) -> 0 | T24: =T23 -> 5040 | U24: =SUM(T24-T23) -> 0 | V24: =V23 -> 425 | W24: =+V24-V23 -> 0 | X24: =X23 -> 147294 | Y24: =SUM(X24-X23) -> 0 | Z24: =Z23 -> 96674 | AA24: =Z24-Z23 -> 0 | AB24: =AB23 -> 264 | AC24: =AC23 -> 698 | AD24: =AC24-AC23 -> 0 | AE24: =AE23 -> 193.63 | AF24: =AE24-AE23 -> 0 | AG24: =AG23 -> 2064.68 | AH24: =AG24-AG23 -> 0 | AI24: =AF24+AH24 -> 0 | AJ24: =+Z24-Z23 -> 0 | AK24: =SUM(Y24-L24) -> 0 | AL24: =SUM(AJ24-W24) -> 0 | AM24: ='General information '!D24 -> 0 | AN24: ='General information '!H24 -> 0 | AP24: ='General information '!J24 -> 0 | AR24: =A24 -> 44062 | AS24: =AS23 -> 0.9 | AT24: =AT23 -> 110 | AU24: =AU23 -> 1.1 | AV24: =AV23 -> 170 | AW24: 2.9 | AX24: =AX23 -> 200 | AY24: =AS24*AT24 -> 99 | AZ24: =AU24*AV24 -> 187 | BA24: =AW24*AX24 -> 580 | BB24: =AY24-AY23 -> 0 | BC24: =AZ24-AZ23 -> 0 | BD24: =BA24-BA23 -> 0 | BE24: =SUM(BB24:BD24) -> 0 | BF24: =SUM(I24-BE24) -> 0 | BG24: =SUM(I24-BF24) -> 0
A25: =ELEC!C22 -> 44063 | B25: =B24 -> 109096 | C25: =B25-B24 -> 0 | D25: =C25/27 -> 0 | E25: =SUM((C25*$E$4)+(7500/'EDl log'!$A$39)) -> 241.93548 | G25: =G24 -> 605739 | H25: =G25-G24 -> 0 | I25: =C25+H25 -> 0 | J25: =IF(I25>0,E25/I25,0) -> 0 | K25: ='Swimming Pool quality check '!H25 -> 6555 | L25: =K25-K24 -> 0 | M25: =M24 -> 457.44 | N25: =SUM(M25-M24) -> 0 | O25: =O24 -> 529.52 | P25: =SUM(O25-O24) -> 0 | Q25: =SUM(P25+N25) -> 0 | T25: =T24 -> 5040 | U25: =SUM(T25-T24) -> 0 | V25: =V24 -> 425 | W25: =+V25-V24 -> 0 | X25: =X24 -> 147294 | Y25: =SUM(X25-X24) -> 0 | Z25: =Z24 -> 96674 | AA25: =Z25-Z24 -> 0 | AB25: =AB24 -> 264 | AC25: =AC24 -> 698 | AD25: =AC25-AC24 -> 0 | AE25: =AE24 -> 193.63 | AF25: =AE25-AE24 -> 0 | AG25: =AG24 -> 2064.68 | AH25: =AG25-AG24 -> 0 | AI25: =AF25+AH25 -> 0 | AJ25: =+Z25-Z24 -> 0 | AK25: =SUM(Y25-L25) -> 0 | AL25: =SUM(AJ25-W25) -> 0 | AM25: ='General information '!D25 -> 0 | AN25: ='General information '!H25 -> 0 | AP25: ='General information '!J25 -> 0 | AR25: =A25 -> 44063 | AS25: =AS24 -> 0.9 | AT25: =AT24 -> 110 | AU25: =AU24 -> 1.1 | AV25: =AV24 -> 170 | AW25: 2.9 | AX25: =AX24 -> 200 | AY25: =AS25*AT25 -> 99 | AZ25: =AU25*AV25 -> 187 | BA25: =AW25*AX25 -> 580 | BB25: =AY25-AY24 -> 0 | BC25: =AZ25-AZ24 -> 0 | BD25: =BA25-BA24 -> 0 | BE25: =SUM(BB25:BD25) -> 0 | BF25: =SUM(I25-BE25) -> 0 | BG25: =SUM(I25-BF25) -> 0
A26: =ELEC!C23 -> 44064 | B26: =B25 -> 109096 | C26: =B26-B25 -> 0 | D26: =C26/27 -> 0 | E26: =SUM((C26*$E$4)+(7500/'EDl log'!$A$39)) -> 241.93548 | G26: =G25 -> 605739 | H26: =G26-G25 -> 0 | I26: =C26+H26 -> 0 | J26: =IF(I26>0,E26/I26,0) -> 0 | K26: ='Swimming Pool quality check '!H26 -> 6555 | L26: =K26-K25 -> 0 | M26: =M25 -> 457.44 | N26: =SUM(M26-M25) -> 0 | O26: =O25 -> 529.52 | P26: =SUM(O26-O25) -> 0 | Q26: =SUM(P26+N26) -> 0 | T26: =T25 -> 5040 | U26: =SUM(T26-T25) -> 0 | V26: =V25 -> 425 | W26: =+V26-V25 -> 0 | X26: =X25 -> 147294 | Y26: =SUM(X26-X25) -> 0 | Z26: =Z25 -> 96674 | AA26: =Z26-Z25 -> 0 | AB26: =AB25 -> 264 | AC26: =AC25 -> 698 | AD26: =AC26-AC25 -> 0 | AE26: =AE25 -> 193.63 | AF26: =AE26-AE25 -> 0 | AG26: =AG25 -> 2064.68 | AH26: =AG26-AG25 -> 0 | AI26: =AF26+AH26 -> 0 | AJ26: =+Z26-Z25 -> 0 | AK26: =SUM(Y26-L26) -> 0 | AL26: =SUM(AJ26-W26) -> 0 | AM26: ='General information '!D26 -> 0 | AN26: ='General information '!H26 -> 0 | AP26: ='General information '!J26 -> 0 | AR26: =A26 -> 44064 | AS26: =AS25 -> 0.9 | AT26: =AT25 -> 110 | AU26: =AU25 -> 1.1 | AV26: =AV25 -> 170 | AW26: 2.9 | AX26: =AX25 -> 200 | AY26: =AS26*AT26 -> 99 | AZ26: =AU26*AV26 -> 187 | BA26: =AW26*AX26 -> 580 | BB26: =AY26-AY25 -> 0 | BC26: =AZ26-AZ25 -> 0 | BD26: =BA26-BA25 -> 0 | BE26: =SUM(BB26:BD26) -> 0 | BF26: =SUM(I26-BE26) -> 0 | BG26: =SUM(I26-BF26) -> 0
A27: =ELEC!C24 -> 44065 | B27: =B26 -> 109096 | C27: =B27-B26 -> 0 | D27: =C27/27 -> 0 | E27: =SUM((C27*$E$4)+(7500/'EDl log'!$A$39)) -> 241.93548 | G27: =G26 -> 605739 | H27: =G27-G26 -> 0 | I27: =C27+H27 -> 0 | J27: =IF(I27>0,E27/I27,0) -> 0 | K27: ='Swimming Pool quality check '!H27 -> 6555 | L27: =K27-K26 -> 0 | M27: =M26 -> 457.44 | N27: =SUM(M27-M26) -> 0 | O27: =O26 -> 529.52 | P27: =SUM(O27-O26) -> 0 | Q27: =SUM(P27+N27) -> 0 | T27: =T26 -> 5040 | U27: =SUM(T27-T26) -> 0 | V27: =V26 -> 425 | W27: =+V27-V26 -> 0 | X27: =X26 -> 147294 | Y27: =SUM(X27-X26) -> 0 | Z27: =Z26 -> 96674 | AA27: =Z27-Z26 -> 0 | AB27: =AB26 -> 264 | AC27: =AC26 -> 698 | AD27: =AC27-AC26 -> 0 | AE27: =AE26 -> 193.63 | AF27: =AE27-AE26 -> 0 | AG27: =AG26 -> 2064.68 | AH27: =AG27-AG26 -> 0 | AI27: =AF27+AH27 -> 0 | AJ27: =+Z27-Z26 -> 0 | AK27: =SUM(Y27-L27) -> 0 | AL27: =SUM(AJ27-W27) -> 0 | AM27: ='General information '!D27 -> 0 | AN27: ='General information '!H27 -> 0 | AP27: ='General information '!J27 -> 0 | AR27: =A27 -> 44065 | AS27: =AS26 -> 0.9 | AT27: =AT26 -> 110 | AU27: =AU26 -> 1.1 | AV27: =AV26 -> 170 | AW27: 2.9 | AX27: =AX26 -> 200 | AY27: =AS27*AT27 -> 99 | AZ27: =AU27*AV27 -> 187 | BA27: =AW27*AX27 -> 580 | BB27: =AY27-AY26 -> 0 | BC27: =AZ27-AZ26 -> 0 | BD27: =BA27-BA26 -> 0 | BE27: =SUM(BB27:BD27) -> 0 | BF27: =SUM(I27-BE27) -> 0 | BG27: =SUM(I27-BF27) -> 0
A28: =ELEC!C25 -> 44066 | B28: =B27 -> 109096 | C28: =B28-B27 -> 0 | D28: =C28/27 -> 0 | E28: =SUM((C28*$E$4)+(7500/'EDl log'!$A$39)) -> 241.93548 | G28: =G27 -> 605739 | H28: =G28-G27 -> 0 | I28: =C28+H28 -> 0 | J28: =IF(I28>0,E28/I28,0) -> 0 | K28: ='Swimming Pool quality check '!H28 -> 6555 | L28: =K28-K27 -> 0 | M28: =M27 -> 457.44 | N28: =SUM(M28-M27) -> 0 | O28: =O27 -> 529.52 | P28: =SUM(O28-O27) -> 0 | Q28: =SUM(P28+N28) -> 0 | T28: =T27 -> 5040 | U28: =SUM(T28-T27) -> 0 | V28: =V27 -> 425 | W28: =+V28-V27 -> 0 | X28: =X27 -> 147294 | Y28: =SUM(X28-X27) -> 0 | Z28: =Z27 -> 96674 | AA28: =Z28-Z27 -> 0 | AB28: =AB27 -> 264 | AC28: =AC27 -> 698 | AD28: =AC28-AC27 -> 0 | AE28: =AE27 -> 193.63 | AF28: =AE28-AE27 -> 0 | AG28: =AG27 -> 2064.68 | AH28: =AG28-AG27 -> 0 | AI28: =AF28+AH28 -> 0 | AJ28: =+Z28-Z27 -> 0 | AK28: =SUM(Y28-L28) -> 0 | AL28: =SUM(AJ28-W28) -> 0 | AM28: ='General information '!D28 -> 0 | AN28: ='General information '!H28 -> 0 | AP28: ='General information '!J28 -> 0 | AR28: =A28 -> 44066 | AS28: =AS27 -> 0.9 | AT28: =AT27 -> 110 | AU28: =AU27 -> 1.1 | AV28: =AV27 -> 170 | AW28: 2.9 | AX28: =AX27 -> 200 | AY28: =AS28*AT28 -> 99 | AZ28: =AU28*AV28 -> 187 | BA28: =AW28*AX28 -> 580 | BB28: =AY28-AY27 -> 0 | BC28: =AZ28-AZ27 -> 0 | BD28: =BA28-BA27 -> 0 | BE28: =SUM(BB28:BD28) -> 0 | BF28: =SUM(I28-BE28) -> 0 | BG28: =SUM(I28-BF28) -> 0
A29: =ELEC!C26 -> 44067 | B29: =B28 -> 109096 | C29: =B29-B28 -> 0 | D29: =C29/27 -> 0 | E29: =SUM((C29*$E$4)+(7500/'EDl log'!$A$39)) -> 241.93548 | G29: =G28 -> 605739 | H29: =G29-G28 -> 0 | I29: =C29+H29 -> 0 | J29: =IF(I29>0,E29/I29,0) -> 0 | K29: ='Swimming Pool quality check '!H29 -> 6555 | L29: =K29-K28 -> 0 | M29: =M28 -> 457.44 | N29: =SUM(M29-M28) -> 0 | O29: =O28 -> 529.52 | P29: =SUM(O29-O28) -> 0 | Q29: =SUM(P29+N29) -> 0 | T29: =T28 -> 5040 | U29: =SUM(T29-T28) -> 0 | V29: =V28 -> 425 | W29: =+V29-V28 -> 0 | X29: =X28 -> 147294 | Y29: =SUM(X29-X28) -> 0 | Z29: =Z28 -> 96674 | AA29: =Z29-Z28 -> 0 | AB29: =AB28 -> 264 | AC29: =AC28 -> 698 | AD29: =AC29-AC28 -> 0 | AE29: =AE28 -> 193.63 | AF29: =AE29-AE28 -> 0 | AG29: =AG28 -> 2064.68 | AH29: =AG29-AG28 -> 0 | AI29: =AF29+AH29 -> 0 | AJ29: =+Z29-Z28 -> 0 | AK29: =SUM(Y29-L29) -> 0 | AL29: =SUM(AJ29-W29) -> 0 | AM29: ='General information '!D29 -> 0 | AN29: ='General information '!H29 -> 0 | AP29: ='General information '!J29 -> 0 | AR29: =A29 -> 44067 | AS29: =AS28 -> 0.9 | AT29: =AT28 -> 110 | AU29: =AU28 -> 1.1 | AV29: =AV28 -> 170 | AW29: 2.9 | AX29: =AX28 -> 200 | AY29: =AS29*AT29 -> 99 | AZ29: =AU29*AV29 -> 187 | BA29: =AW29*AX29 -> 580 | BB29: =AY29-AY28 -> 0 | BC29: =AZ29-AZ28 -> 0 | BD29: =BA29-BA28 -> 0 | BE29: =SUM(BB29:BD29) -> 0 | BF29: =SUM(I29-BE29) -> 0 | BG29: =SUM(I29-BF29) -> 0
A30: =ELEC!C27 -> 44068 | B30: =B29 -> 109096 | C30: =B30-B29 -> 0 | D30: =C30/27 -> 0 | E30: =SUM((C30*$E$4)+(7500/'EDl log'!$A$39)) -> 241.93548 | G30: =G29 -> 605739 | H30: =G30-G29 -> 0 | I30: =C30+H30 -> 0 | J30: =IF(I30>0,E30/I30,0) -> 0 | K30: ='Swimming Pool quality check '!H30 -> 6555 | L30: =K30-K29 -> 0 | M30: =M29 -> 457.44 | N30: =SUM(M30-M29) -> 0 | O30: =O29 -> 529.52 | P30: =SUM(O30-O29) -> 0 | Q30: =SUM(P30+N30) -> 0 | T30: =T29 -> 5040 | U30: =SUM(T30-T29) -> 0 | V30: =V29 -> 425 | W30: =+V30-V29 -> 0 | X30: =X29 -> 147294 | Y30: =SUM(X30-X29) -> 0 | Z30: =Z29 -> 96674 | AA30: =Z30-Z29 -> 0 | AB30: =AB29 -> 264 | AC30: =AC29 -> 698 | AD30: =AC30-AC29 -> 0 | AE30: =AE29 -> 193.63 | AF30: =AE30-AE29 -> 0 | AG30: =AG29 -> 2064.68 | AH30: =AG30-AG29 -> 0 | AI30: =AF30+AH30 -> 0 | AJ30: =+Z30-Z29 -> 0 | AK30: =SUM(Y30-L30) -> 0 | AL30: =SUM(AJ30-W30) -> 0 | AM30: ='General information '!D30 -> 0 | AN30: ='General information '!H30 -> 0 | AP30: ='General information '!J30 -> 0 | AR30: =A30 -> 44068 | AS30: =AS29 -> 0.9 | AT30: =AT29 -> 110 | AU30: =AU29 -> 1.1 | AV30: =AV29 -> 170 | AW30: 2.9 | AX30: =AX29 -> 200 | AY30: =AS30*AT30 -> 99 | AZ30: =AU30*AV30 -> 187 | BA30: =AW30*AX30 -> 580 | BB30: =AY30-AY29 -> 0 | BC30: =AZ30-AZ29 -> 0 | BD30: =BA30-BA29 -> 0 | BE30: =SUM(BB30:BD30) -> 0 | BF30: =SUM(I30-BE30) -> 0 | BG30: =SUM(I30-BF30) -> 0
A31: =ELEC!C28 -> 44069 | B31: =B30 -> 109096 | C31: =B31-B30 -> 0 | D31: =C31/27 -> 0 | E31: =SUM((C31*$E$4)+(7500/'EDl log'!$A$39)) -> 241.93548 | G31: =G30 -> 605739 | H31: =G31-G30 -> 0 | I31: =C31+H31 -> 0 | J31: =IF(I31>0,E31/I31,0) -> 0 | K31: ='Swimming Pool quality check '!H31 -> 6555 | L31: =K31-K30 -> 0 | M31: =M30 -> 457.44 | N31: =SUM(M31-M30) -> 0 | O31: =O30 -> 529.52 | P31: =SUM(O31-O30) -> 0 | Q31: =SUM(P31+N31) -> 0 | T31: =T30 -> 5040 | U31: =SUM(T31-T30) -> 0 | V31: =V30 -> 425 | W31: =+V31-V30 -> 0 | X31: =X30 -> 147294 | Y31: =SUM(X31-X30) -> 0 | Z31: =Z30 -> 96674 | AA31: =Z31-Z30 -> 0 | AB31: =AB30 -> 264 | AC31: =AC30 -> 698 | AD31: =AC31-AC30 -> 0 | AE31: =AE30 -> 193.63 | AF31: =AE31-AE30 -> 0 | AG31: =AG30 -> 2064.68 | AH31: =AG31-AG30 -> 0 | AI31: =AF31+AH31 -> 0 | AJ31: =+Z31-Z30 -> 0 | AK31: =SUM(Y31-L31) -> 0 | AL31: =SUM(AJ31-W31) -> 0 | AM31: ='General information '!D31 -> 0 | AN31: ='General information '!H31 -> 0 | AP31: ='General information '!J31 -> 0 | AR31: =A31 -> 44069 | AS31: =AS30 -> 0.9 | AT31: =AT30 -> 110 | AU31: =AU30 -> 1.1 | AV31: =AV30 -> 170 | AW31: 2.9 | AX31: =AX30 -> 200 | AY31: =AS31*AT31 -> 99 | AZ31: =AU31*AV31 -> 187 | BA31: =AW31*AX31 -> 580 | BB31: =AY31-AY30 -> 0 | BC31: =AZ31-AZ30 -> 0 | BD31: =BA31-BA30 -> 0 | BE31: =SUM(BB31:BD31) -> 0 | BF31: =SUM(I31-BE31) -> 0 | BG31: =SUM(I31-BF31) -> 0
A32: =ELEC!C29 -> 44070 | B32: =B31 -> 109096 | C32: =B32-B31 -> 0 | D32: =C32/27 -> 0 | E32: =SUM((C32*$E$4)+(7500/'EDl log'!$A$39)) -> 241.93548 | G32: =G31 -> 605739 | H32: =G32-G31 -> 0 | I32: =C32+H32 -> 0 | J32: =IF(I32>0,E32/I32,0) -> 0 | K32: ='Swimming Pool quality check '!H32 -> 6555 | L32: =K32-K31 -> 0 | M32: =M31 -> 457.44 | N32: =SUM(M32-M31) -> 0 | O32: =O31 -> 529.52 | P32: =SUM(O32-O31) -> 0 | Q32: =SUM(P32+N32) -> 0 | T32: =T31 -> 5040 | U32: =SUM(T32-T31) -> 0 | V32: =V31 -> 425 | W32: =+V32-V31 -> 0 | X32: =X31 -> 147294 | Y32: =SUM(X32-X31) -> 0 | Z32: =Z31 -> 96674 | AA32: =Z32-Z31 -> 0 | AB32: =AB31 -> 264 | AC32: =AC31 -> 698 | AD32: =AC32-AC31 -> 0 | AE32: =AE31 -> 193.63 | AF32: =AE32-AE31 -> 0 | AG32: =AG31 -> 2064.68 | AH32: =AG32-AG31 -> 0 | AI32: =AF32+AH32 -> 0 | AJ32: =+Z32-Z31 -> 0 | AK32: 0 | AL32: =SUM(AJ32-W32) -> 0 | AM32: ='General information '!D32 -> 0 | AN32: ='General information '!H32 -> 0 | AP32: ='General information '!J32 -> 0 | AR32: =A32 -> 44070 | AS32: =AS31 -> 0.9 | AT32: =AT31 -> 110 | AU32: =AU31 -> 1.1 | AV32: =AV31 -> 170 | AW32: 2.9 | AX32: =AX31 -> 200 | AY32: =AS32*AT32 -> 99 | AZ32: =AU32*AV32 -> 187 | BA32: =AW32*AX32 -> 580 | BB32: =AY32-AY31 -> 0 | BC32: =AZ32-AZ31 -> 0 | BD32: =BA32-BA31 -> 0 | BE32: =SUM(BB32:BD32) -> 0 | BF32: =SUM(I32-BE32) -> 0 | BG32: =SUM(I32-BF32) -> 0
A33: =ELEC!C30 -> 44071 | B33: =B32 -> 109096 | C33: =B33-B32 -> 0 | D33: =C33/27 -> 0 | E33: =SUM((C33*$E$4)+(7500/'EDl log'!$A$39)) -> 241.93548 | G33: =G32 -> 605739 | H33: =G33-G32 -> 0 | I33: =C33+H33 -> 0 | J33: =IF(I33>0,E33/I33,0) -> 0 | K33: ='Swimming Pool quality check '!H33 -> 6555 | L33: =K33-K32 -> 0 | M33: =M32 -> 457.44 | N33: =SUM(M33-M32) -> 0 | O33: =O32 -> 529.52 | P33: =SUM(O33-O32) -> 0 | Q33: =SUM(P33+N33) -> 0 | T33: =T32 -> 5040 | U33: =SUM(T33-T32) -> 0 | V33: =V32 -> 425 | W33: =+V33-V32 -> 0 | X33: =X32 -> 147294 | Y33: =SUM(X33-X32) -> 0 | Z33: =Z32 -> 96674 | AA33: =Z33-Z32 -> 0 | AB33: =AB32 -> 264 | AC33: =AC32 -> 698 | AD33: =AC33-AC32 -> 0 | AE33: =AE32 -> 193.63 | AF33: =AE33-AE32 -> 0 | AG33: =AG32 -> 2064.68 | AH33: =AG33-AG32 -> 0 | AI33: =AF33+AH33 -> 0 | AJ33: =+Z33-Z32 -> 0 | AK33: =SUM(Y33-L33) -> 0 | AL33: =SUM(AJ33-W33) -> 0 | AM33: ='General information '!D33 -> 0 | AN33: ='General information '!H33 -> 0 | AP33: ='General information '!J33 -> 0 | AR33: =A33 -> 44071 | AS33: =AS32 -> 0.9 | AT33: =AT32 -> 110 | AU33: =AU32 -> 1.1 | AV33: =AV32 -> 170 | AW33: 2.9 | AX33: =AX32 -> 200 | AY33: =AS33*AT33 -> 99 | AZ33: =AU33*AV33 -> 187 | BA33: =AW33*AX33 -> 580 | BB33: =AY33-AY32 -> 0 | BC33: =AZ33-AZ32 -> 0 | BD33: =BA33-BA32 -> 0 | BE33: =SUM(BB33:BD33) -> 0 | BF33: =SUM(I33-BE33) -> 0 | BG33: =SUM(I33-BF33) -> 0
A34: =ELEC!C31 -> 44072 | B34: =B33 -> 109096 | C34: =B34-B33 -> 0 | D34: =C34/27 -> 0 | E34: =SUM((C34*$E$4)+(7500/'EDl log'!$A$39)) -> 241.93548 | G34: =G33 -> 605739 | H34: =G34-G33 -> 0 | I34: =C34+H34 -> 0 | J34: =IF(I34>0,E34/I34,0) -> 0 | K34: ='Swimming Pool quality check '!H34 -> 6555 | L34: =K34-K33 -> 0 | M34: =M33 -> 457.44 | N34: =SUM(M34-M33) -> 0 | O34: =O33 -> 529.52 | P34: =SUM(O34-O33) -> 0 | Q34: =SUM(P34+N34) -> 0 | T34: =T33 -> 5040 | U34: =SUM(T34-T33) -> 0 | V34: =V33 -> 425 | W34: =+V34-V33 -> 0 | X34: =X33 -> 147294 | Y34: =SUM(X34-X33) -> 0 | Z34: =Z33 -> 96674 | AA34: =Z34-Z33 -> 0 | AB34: =AB33 -> 264 | AC34: =AC33 -> 698 | AD34: =AC34-AC33 -> 0 | AE34: =AE33 -> 193.63 | AF34: =AE34-AE33 -> 0 | AG34: =AG33 -> 2064.68 | AH34: =AG34-AG33 -> 0 | AI34: =AF34+AH34 -> 0 | AJ34: =+Z34-Z33 -> 0 | AK34: =SUM(Y34-L34) -> 0 | AL34: =SUM(AJ34-W34) -> 0 | AM34: ='General information '!D34 -> 0 | AN34: ='General information '!H34 -> 0 | AP34: ='General information '!J34 -> 0 | AR34: =A34 -> 44072 | AS34: =AS33 -> 0.9 | AT34: =AT33 -> 110 | AU34: =AU33 -> 1.1 | AV34: =AV33 -> 170 | AW34: 2.9 | AX34: =AX33 -> 200 | AY34: =AS34*AT34 -> 99 | AZ34: =AU34*AV34 -> 187 | BA34: =AW34*AX34 -> 580 | BB34: =AY34-AY33 -> 0 | BC34: =AZ34-AZ33 -> 0 | BD34: =BA34-BA33 -> 0 | BE34: =SUM(BB34:BD34) -> 0 | BF34: =SUM(I34-BE34) -> 0 | BG34: =SUM(I34-BF34) -> 0
A35: =ELEC!C32 -> 44073 | B35: =B34 -> 109096 | C35: =B35-B34 -> 0 | D35: =C35/27 -> 0 | E35: =SUM((C35*$E$4)+(7500/'EDl log'!$A$39)) -> 241.93548 | G35: =G34 -> 605739 | H35: =G35-G34 -> 0 | I35: =C35+H35 -> 0 | J35: =IF(I35>0,E35/I35,0) -> 0 | K35: ='Swimming Pool quality check '!H35 -> 6555 | L35: =K35-K34 -> 0 | M35: =M34 -> 457.44 | N35: =SUM(M35-M34) -> 0 | O35: =O34 -> 529.52 | P35: =SUM(O35-O34) -> 0 | Q35: =SUM(P35+N35) -> 0 | T35: =T34 -> 5040 | U35: =SUM(T35-T34) -> 0 | V35: =V34 -> 425 | W35: =+V35-V34 -> 0 | X35: =X34 -> 147294 | Y35: =SUM(X35-X34) -> 0 | Z35: =Z34 -> 96674 | AA35: =Z35-Z34 -> 0 | AB35: =AB34 -> 264 | AC35: =AC34 -> 698 | AD35: =AC35-AC34 -> 0 | AE35: =AE34 -> 193.63 | AF35: =AE35-AE34 -> 0 | AG35: =AG34 -> 2064.68 | AH35: =AG35-AG34 -> 0 | AI35: =AF35+AH35 -> 0 | AJ35: =+Z35-Z34 -> 0 | AK35: =SUM(Y35-L35) -> 0 | AL35: =SUM(AJ35-W35) -> 0 | AM35: ='General information '!D35 -> 0 | AN35: ='General information '!H35 -> 0 | AP35: ='General information '!J35 -> 0 | AR35: =A35 -> 44073 | AS35: =AS34 -> 0.9 | AT35: =AT34 -> 110 | AU35: =AU34 -> 1.1 | AV35: =AV34 -> 170 | AW35: 2.9 | AX35: =AX34 -> 200 | AY35: =AS35*AT35 -> 99 | AZ35: =AU35*AV35 -> 187 | BA35: =AW35*AX35 -> 580 | BB35: =AY35-AY34 -> 0 | BC35: =AZ35-AZ34 -> 0 | BD35: =BA35-BA34 -> 0 | BE35: =SUM(BB35:BD35) -> 0 | BF35: =SUM(I35-BE35) -> 0 | BG35: =SUM(I35-BF35) -> 0
A36: =ELEC!C33 -> 44074 | B36: =B35 -> 109096 | C36: =B36-B35 -> 0 | D36: =C36/27 -> 0 | E36: =SUM((C36*$E$4)+(7500/'EDl log'!$A$39)) -> 241.93548 | G36: =G35 -> 605739 | H36: =G36-G35 -> 0 | I36: =C36+H36 -> 0 | J36: =IF(I36>0,E36/I36,0) -> 0 | K36: ='Swimming Pool quality check '!H36 -> 6555 | L36: =K36-K35 -> 0 | M36: =M35 -> 457.44 | N36: =SUM(M36-M35) -> 0 | O36: =O35 -> 529.52 | P36: =SUM(O36-O35) -> 0 | Q36: =SUM(P36+N36) -> 0 | T36: =T35 -> 5040 | U36: =SUM(T36-T35) -> 0 | V36: =V35 -> 425 | W36: =+V36-V35 -> 0 | X36: =X35 -> 147294 | Y36: =SUM(X36-X35) -> 0 | Z36: =Z35 -> 96674 | AA36: =Z36-Z35 -> 0 | AB36: =AB35 -> 264 | AC36: =AC35 -> 698 | AD36: =AC36-AC35 -> 0 | AE36: =AE35 -> 193.63 | AF36: =AE36-AE35 -> 0 | AG36: =AG35 -> 2064.68 | AH36: =AG36-AG35 -> 0 | AI36: =AF36+AH36 -> 0 | AJ36: =+Z36-Z35 -> 0 | AK36: =SUM(Y36-L36) -> 0 | AL36: =SUM(AJ36-W36) -> 0 | AM36: ='General information '!D37 -> 0 | AN36: ='General information '!H37 -> 0 | AP36: ='General information '!J37 -> 0 | AR36: =A36 -> 44074 | AS36: =AS35 -> 0.9 | AT36: =AT35 -> 110 | AU36: =AU35 -> 1.1 | AV36: =AV35 -> 170 | AW36: 2.9 | AX36: =AX35 -> 200 | AY36: =AS36*AT36 -> 99 | AZ36: =AU36*AV36 -> 187 | BA36: =AW36*AX36 -> 580 | BB36: =AY36-AY35 -> 0 | BC36: =AZ36-AZ35 -> 0 | BD36: =BA36-BA35 -> 0 | BE36: =SUM(BB36:BD36) -> 0 | BF36: =SUM(I36-BE36) -> 0 | BG36: =SUM(I36-BF36) -> 0
C37: =SUM(C6:C35) -> 124 | D37: =SUM(D6:D35) -> 4.5925926 | F37: =SUM(F6:F35) -> 4 | H37: =SUM(H6:H35) -> 908 | I37: =SUM(I6:I35) -> 1032 | L37: =SUM(L7:L35) -> 12 | Q37: =SUM(Q5:Q35) -> 0 | U37: =SUM(U6:U35) -> 23 | Y37: =SUM(Y35,Y33,Y31,Y29,Y27,Y25,Y23,Y21,Y19,Y17,Y15,Y13,Y11,Y9,Y7+#REF!) -> #REF! | AJ37: =SUM(AJ6:AJ35) -> 389 | AK37: =SUM(Y37-L37) -> #REF! | AL37: =SUM(AL6:AL35) -> 386
C38: =+C37*1.66 -> 205.84 | E38: =SUM(E6:E35) -> 7463.9045 | F38: =SUM(F6:F35) -> 4 | H38: 7500 | I38: =SUM('General information '!G37/WATER!I37) -> 0.22868508 | O38: =SUM(Q37+I37) -> 1032 | Z38: =SUM(Y37:AJ37) -> #REF! | AK38: =SUM(Y38-L38) -> 0
B39: =9*27 -> 243 | D39: =SUM(D21:D35) -> 0 | F39: =SUM(F6:F35) -> 4 | G39: =SUM(I37) -> 1032 | H39: =SUM(H38+C38) -> 7705.84 | K39: =SUM(H39/G39) -> 7.4668992 | AJ39: =SUM(C38-AK38) -> 205.84 | AM39: =SUM(AJ39/AO38) -> #DIV/0!

Sheet graphic

Sheet General information 
A1: GENERAL & HOTEL'S INFORMATION SHEET
B4: Max Temp | C4: MIN TEMP | D4: AVE TEMP | E4: AVE Humidity | F4: AVE OCC | G4: # of OCC Rooms | H4: Ball room | I4: Meeting rooms | J4: Outlets | K4: Total covers | L4: # of permenant Emp | M4: # of casuals | N4: Total # of EMP | O4: # of EMP/OCC Room
A5: =ELEC!C2 -> 44043 | B5: ='[1]General information '!B36 -> 31 | C5: ='[1]General information '!C36 -> 26 | D5: ='[1]General information '!D36 -> 28.5 | E5: ='[1]General information '!E36 -> 0.52 | F5: ='[1]General information '!F36 -> 0.3609 | G5: ='[1]General information '!G36 -> 83.007 | H5: ='[1]General information '!H36 -> 0 | I5: ='[1]General information '!I36 -> 0 | ... O5: ='[1]General information '!O36 -> 0
A6: =ELEC!C3 -> 44044 | B6: 30 | C6: 26 | D6: =(C6+B6)/2 -> 28 | E6: 0.66 | F6: 0.387 | G6: =F6*230 -> 89.01 | J6: 613 | K6: =+J6+H6 -> 613
A7: =ELEC!C4 -> 44045 | B7: 31 | C7: 26 | D7: =(C7+B7)/2 -> 28.5 | E7: 0.67 | F7: 0.3391 | G7: =F7*230 -> 77.993 | J7: 652 | K7: =+J7+H7 -> 652
A8: =ELEC!C5 -> 44046 | B8: 31 | C8: 27 | D8: =(C8+B8)/2 -> 29 | E8: 0.7 | F8: 0.3 | G8: =F8*230 -> 69 | K8: =+J8+H8 -> 0
A9: =ELEC!C6 -> 44047 | B9: 31 | C9: 26 | D9: =(C9+B9)/2 -> 28.5 | E9: 0.69 | F9: 0 | G9: =F9*230 -> 0 | K9: =+J9+H9 -> 0
A10: =ELEC!C7 -> 44048 | B10: 30 | C10: 27 | D10: =(C10+B10)/2 -> 28.5 | E10: 0.67 | F10: 0 | G10: =F10*230 -> 0 | K10: =+J10+H10 -> 0
A11: =ELEC!C8 -> 44049 | B11: 31 | C11: 26 | D11: =(C11+B11)/2 -> 28.5 | E11: 0.69 | F11: 0 | G11: =F11*230 -> 0 | K11: =+J11+H11 -> 0
A12: =ELEC!C9 -> 44050 | B12: 31 | C12: 23 | D12: =(C12+B12)/2 -> 27 | E12: 0.7 | F12: 0 | G12: =F12*230 -> 0 | K12: =+J12+H12 -> 0
A13: =ELEC!C10 -> 44051 | B13: 33 | C13: 24 | D13: =(C13+B13)/2 -> 28.5 | E13: 0.46 | F13: 0 | G13: =F13*230 -> 0 | K13: =+J13+H13 -> 0
A14: =ELEC!C11 -> 44052 | B14: 31 | C14: 27 | D14: =(C14+B14)/2 -> 29 | E14: 0.6 | G14: =F14*230 -> 0 | K14: =+J14+H14 -> 0
A15: =ELEC!C12 -> 44053 | B15: 31 | C15: 23 | D15: =(C15+B15)/2 -> 27 | E15: 0.69 | G15: =F15*230 -> 0 | K15: =+J15+H15 -> 0
A16: =ELEC!C13 -> 44054 | B16: 30 | C16: 27 | D16: =(C16+B16)/2 -> 28.5 | E16: 0.67 | G16: =F16*230 -> 0 | K16: =+J16+H16 -> 0
A17: =ELEC!C14 -> 44055 | B17: 30 | C17: 26 | D17: =(C17+B17)/2 -> 28 | E17: 0.67 | G17: =F17*230 -> 0 | K17: =+J17+H17 -> 0
A18: =ELEC!C15 -> 44056 | B18: 32 | C18: 23 | D18: =(C18+B18)/2 -> 27.5 | G18: =F18*230 -> 0 | K18: =+J18+H18 -> 0
A19: =ELEC!C16 -> 44057 | B19: 31 | C19: 24 | D19: =(C19+B19)/2 -> 27.5 | E19: 0.68 | F19: 0 | G19: 0 | H19: 0 | I19: 0 | J19: 0 | K19: =+J19+H19 -> 0
A20: =ELEC!C17 -> 44058 | B20: 31 | C20: 24 | D20: =(C20+B20)/2 -> 27.5 | E20: 0.67 | F20: 0 | G20: =F20*230 -> 0 | H20: 0 | I20: 0 | J20: 0 | K20: =+J20+H20 -> 0
A21: =ELEC!C18 -> 44059 | B21: 31 | C21: 25 | D21: =(C21+B21)/2 -> 28 | E21: 0.66 | G21: =F21*230 -> 0 | K21: =+J21+H21 -> 0
A22: =ELEC!C19 -> 44060 | B22: 31 | C22: 26 | D22: =(C22+B22)/2 -> 28.5 | E22: 0.69 | G22: =F22*230 -> 0 | K22: =+J22+H22 -> 0
A23: =ELEC!C20 -> 44061 | D23: =(C23+B23)/2 -> 0 | G23: =F23*230 -> 0 | K23: =+J23+H23 -> 0
A24: =ELEC!C21 -> 44062 | D24: =(C24+B24)/2 -> 0 | G24: =F24*230 -> 0 | K24: =+J24+H24 -> 0
A25: =ELEC!C22 -> 44063 | D25: =(C25+B25)/2 -> 0 | G25: =F25*230 -> 0 | K25: =+J25+H25 -> 0
A26: =ELEC!C23 -> 44064 | D26: =(C26+B26)/2 -> 0 | G26: =F26*230 -> 0 | K26: =+J26+H26 -> 0
A27: =ELEC!C24 -> 44065 | D27: =(C27+B27)/2 -> 0 | G27: =F27*230 -> 0 | K27: =+J27+H27+I27 -> 0
A28: =ELEC!C25 -> 44066 | D28: =(C28+B28)/2 -> 0 | G28: =F28*230 -> 0 | K28: =+J28+H28+I28 -> 0
A29: =ELEC!C26 -> 44067 | D29: =(C29+B29)/2 -> 0 | G29: =F29*230 -> 0 | K29: =+J29+H29+I29 -> 0
A30: =ELEC!C27 -> 44068 | D30: =(C30+B30)/2 -> 0 | G30: =F30*230 -> 0 | K30: =+J30+H30+I30 -> 0
A31: =ELEC!C28 -> 44069 | D31: =(C31+B31)/2 -> 0 | G31: =F31*230 -> 0 | K31: =+J31+H31+I31 -> 0
A32: =ELEC!C29 -> 44070 | D32: =(C32+B32)/2 -> 0 | G32: =F32*230 -> 0 | K32: =+J32+H32+I32 -> 0
A33: =ELEC!C30 -> 44071 | D33: =(C33+B33)/2 -> 0 | G33: =F33*230 -> 0 | K33: =+J33+H33+I33 -> 0
A34: =ELEC!C31 -> 44072 | D34: =(C34+B34)/2 -> 0 | G34: =F34*230 -> 0 | K34: =+J34+H34+I34 -> 0
A35: =ELEC!C32 -> 44073 | D35: =(C35+B35)/2 -> 0 | G35: =F35*230 -> 0 | K35: =+J35+H35+I35 -> 0
A36: =ELEC!C33 -> 44074 | D36: =(C36+B36)/2 -> 0 | G36: =F36*230 -> 0 | K36: =+J36+H36+I36 -> 0
F37: =AVERAGE(F6:F35) -> 0.10261 | G37: =SUM(G6:G35) -> 236.003
D38: =SUM(D6:D35)/'EDl log'!A37 -> 26.555556
I41: http://www.accuweather.com/en/lb/lebanon-weather

Sheet tanks
B2: Tank 1 | D2: Tank 2 | F2: Tank 3 | H2: Tank 4 | J2: Tank 5 | L2: Tank 6 | N2: Tank 7 | P2: Tank 8 | R2: Tank 9 | T2: Tank 10 | V2: Tank 11 | Z2: Tank 1 | AB2: Tank 2 | AD2: Tank 3 | AF2: Tank 4 | AH2: Tank 5 | AJ2: Tank 6 | AL2: Tank 7
B3: 6670 | D3: =SUM(B3) -> 6670 | F3: =SUM(D3) -> 6670 | H3: =SUM(F3) -> 6670 | J3: =SUM(H3) -> 6670 | L3: =SUM(J3) -> 6670 | N3: =SUM(L3) -> 6670 | P3: =SUM(N3) -> 6670 | R3: =SUM(P3) -> 6670 | T3: =SUM(R3) -> 6670 | V3: =SUM(T3) -> 6670 | W3: =SUM(B3:V3) -> 73370 | Z3: 2800 | AB3: 2800 | AD3: 2800 | AF3: 2800 | AH3: 2800 | AJ3: 2800 | AL3: 2800 | AM3: =SUM(Z3:AL3) -> 19600 | AO3: =SUM(AM3+W3) -> 92970 | AR3: Total sotck | AS3: Diesel Cons Per day | AT3: Diesel Delivery | BE3: Genset Co | BF3: Steam | BG3: Boil | BH3: Outdoor temperature
B4: =B3/310 -> 21.516129 | D4: =SUM(B4) -> 21.516129 | F4: =SUM(D4) -> 21.516129 | H4: =SUM(F4) -> 21.516129 | J4: =SUM(H4) -> 21.516129 | L4: =SUM(J4) -> 21.516129 | N4: =SUM(L4) -> 21.516129 | P4: =SUM(N4) -> 21.516129 | R4: =SUM(P4) -> 21.516129 | T4: =SUM(R4) -> 21.516129 | V4: =SUM(T4) -> 21.516129 | Z4: =Z3/280 -> 10 | AA4: =AA3/280 -> 0 | AB4: =AB3/280 -> 10 | AC4: =AC3/280 -> 0 | AD4: =AD3/280 -> 10 | AE4: =AE3/280 -> 0 | AF4: =AF3/280 -> 10 | AG4: =AG3/280 -> 0 | ... AL4: =AL3/280 -> 10 | AT4: Delivery | AU4: Cost /L | AW4: Boiler+Steam | AX4: Generator | AZ4: Occupancy | BA4: AVE TEPM | BB4: AVE Humidity
A5: =ELEC!C2 -> 44043 | B5: =[1]tanks!B36 -> 218 | C5: =[1]tanks!C36 -> 4690.5161 | D5: =[1]tanks!D36 -> 218 | E5: =[1]tanks!E36 -> 4690.5161 | F5: =[1]tanks!F36 -> 218 | G5: =[1]tanks!G36 -> 4690.5161 | H5: =[1]tanks!H36 -> 218 | I5: =[1]tanks!I36 -> 4690.5161 | ... BH5: =[1]tanks!BH36 -> 0
A6: =ELEC!C3 -> 44044 | B6: ='B5'!B5 -> 197.3 | C6: =B6*$B$4 -> 4245.1323 | D6: =SUM(B6) -> 197.3 | E6: =D6*$B$4 -> 4245.1323 | F6: =SUM(D6) -> 197.3 | G6: =F6*$B$4 -> 4245.1323 | H6: =SUM(F6) -> 197.3 | I6: =H6*$B$4 -> 4245.1323 | J6: =SUM(H6) -> 197.3 | K6: =J6*$B$4 -> 4245.1323 | L6: =SUM(J6) -> 197.3 | M6: =L6*$B$4 -> 4245.1323 | N6: =SUM(L6) -> 197.3 | O6: =N6*$B$4 -> 4245.1323 | P6: =SUM(N6) -> 197.3 | Q6: =P6*$B$4 -> 4245.1323 | R6: =SUM(P6) -> 197.3 | S6: =R6*$B$4 -> 4245.1323 | T6: =SUM(R6) -> 197.3 | U6: =T6*$B$4 -> 4245.1323 | V6: =SUM(T6) -> 197.3 | W6: =V6*$B$4 -> 4245.1323 | X6: =SUM(Y6/73370) -> 0.63645161 | Y6: =SUM(C6+E6+G6+I6+K6+M6+O6+Q6+S6+U6+W6) -> 46696.455 | Z6: ='B5'!C5 -> 204 | AA6: =SUM(Z6*$Z$4) -> 2040 | AB6: =SUM(Z6) -> 204 | AC6: =SUM(AB6*$Z$4) -> 2040 | AD6: =SUM(AB6) -> 204 | AE6: =SUM(AD6*$Z$4) -> 2040 | AF6: =SUM(AD6) -> 204 | AG6: =SUM(AF6*$Z$4) -> 2040 | AH6: =SUM(AF6) -> 204 | AI6: =SUM(AH6*$Z$4) -> 2040 | AJ6: =SUM(AH6) -> 204 | AK6: =SUM(AJ6*$Z$4) -> 2040 | AL6: =SUM(AJ6) -> 204 | AM6: =SUM(AL6*$Z$4) -> 2040 | AN6: =SUM(AO6/19600) -> 0.72857143 | AO6: =SUM(AA6+AC6+AE6+AG6+AI6+AK6+AM6) -> 14280 | AQ6: =SUM(AR6/92970) -> 0.65587238 | AR6: =SUM(AO6+Y6) -> 60976.455 | AS6: =SUM(AR6-AR5-AT6) -> -6229.2226 | AV6: =IF(AT6>0,AU6,AV5) -> 0.5383 | AW6: =-SUM('B5'!AI5) -> -380 | AX6: =-SUM(AW6-AS6) -> -5849.2226 | AY6: =SUM(AX6+AW6) -> -6229.2226 | AZ6: =ELEC!A3 -> 0.387 | BA6: ='General information '!D6 -> 28 | BB6: =SUM('General information '!E6) -> 0.66 | BC6: =IF(AR3>=AR6,0,1) -> 0 | BD6: 19222 | BE6: =(305/1185)*ELEC!Q4 -> 2573.8397 | BG6: =#REF!-BE6 -> #REF! | BH6: 21
A7: =ELEC!C4 -> 44045 | B7: ='B5'!B6 -> 188 | C7: =B7*$B$4 -> 4045.0323 | D7: =SUM(B7) -> 188 | E7: =D7*$B$4 -> 4045.0323 | F7: =SUM(D7) -> 188 | G7: =F7*$B$4 -> 4045.0323 | H7: =SUM(F7) -> 188 | I7: =H7*$B$4 -> 4045.0323 | J7: =SUM(H7) -> 188 | K7: =J7*$B$4 -> 4045.0323 | L7: =SUM(J7) -> 188 | M7: =L7*$B$4 -> 4045.0323 | N7: =SUM(L7) -> 188 | O7: =N7*$B$4 -> 4045.0323 | P7: =SUM(N7) -> 188 | Q7: =P7*$B$4 -> 4045.0323 | R7: =SUM(P7) -> 188 | S7: =R7*$B$4 -> 4045.0323 | T7: =SUM(R7) -> 188 | U7: =T7*$B$4 -> 4045.0323 | V7: =SUM(T7) -> 188 | W7: =V7*$B$4 -> 4045.0323 | X7: =SUM(Y7/73370) -> 0.60645161 | Y7: =SUM(C7+E7+G7+I7+K7+M7+O7+Q7+S7+U7+W7) -> 44495.355 | Z7: ='B5'!C6 -> 194 | AA7: =SUM(Z7*$Z$4) -> 1940 | AB7: =SUM(Z7) -> 194 | AC7: =SUM(AB7*$Z$4) -> 1940 | AD7: =SUM(AB7) -> 194 | AE7: =SUM(AD7*$Z$4) -> 1940 | AF7: =SUM(AD7) -> 194 | AG7: =SUM(AF7*$Z$4) -> 1940 | AH7: =SUM(AF7) -> 194 | AI7: =SUM(AH7*$Z$4) -> 1940 | AJ7: =SUM(AH7) -> 194 | AK7: =SUM(AJ7*$Z$4) -> 1940 | AL7: =SUM(AJ7) -> 194 | AM7: =SUM(AL7*$Z$4) -> 1940 | AN7: =SUM(AO7/19600) -> 0.69285714 | AO7: =SUM(AA7+AC7+AE7+AG7+AI7+AK7+AM7) -> 13580 | AQ7: =SUM(AR7/92970) -> 0.62466769 | AR7: =SUM(AO7+Y7) -> 58075.355 | AS7: =SUM(AR7-AR6-AT7) -> -2901.1 | AV7: =IF(AT7>0,AU7,AV6) -> 0.5383 | AW7: =-SUM('B5'!AI6) -> -229 | AX7: =-SUM(AW7-AS7) -> -2672.1 | AY7: =SUM(AX7+AW7) -> -2901.1 | AZ7: =ELEC!A4 -> 0.3391 | BA7: ='General information '!D7 -> 28.5 | BB7: =SUM('General information '!E7) -> 0.67 | BC7: 0 | BD7: 19222 | BE7: =(305/1185)*ELEC!Q5 -> 3860.7595 | BG7: =#REF!-BE7 -> #REF! | BH7: 19
A8: =ELEC!C5 -> 44046 | B8: ='B5'!B7 -> 207 | C8: =B8*$B$4 -> 4453.8387 | D8: =SUM(B8) -> 207 | E8: =D8*$B$4 -> 4453.8387 | F8: =SUM(D8) -> 207 | G8: =F8*$B$4 -> 4453.8387 | H8: =SUM(F8) -> 207 | I8: =H8*$B$4 -> 4453.8387 | J8: =SUM(H8) -> 207 | K8: =J8*$B$4 -> 4453.8387 | L8: =SUM(J8) -> 207 | M8: =L8*$B$4 -> 4453.8387 | N8: =SUM(L8) -> 207 | O8: =N8*$B$4 -> 4453.8387 | P8: =SUM(N8) -> 207 | Q8: =P8*$B$4 -> 4453.8387 | R8: =SUM(P8) -> 207 | S8: =R8*$B$4 -> 4453.8387 | T8: =SUM(R8) -> 207 | U8: =T8*$B$4 -> 4453.8387 | V8: =SUM(T8) -> 207 | W8: =V8*$B$4 -> 4453.8387 | X8: =SUM(Y8/73370) -> 0.66774194 | Y8: =SUM(C8+E8+G8+I8+K8+M8+O8+Q8+S8+U8+W8) -> 48992.226 | Z8: ='B5'!C7 -> 213 | AA8: =SUM(Z8*$Z$4) -> 2130 | AB8: =SUM(Z8) -> 213 | AC8: =SUM(AB8*$Z$4) -> 2130 | AD8: =SUM(AB8) -> 213 | AE8: =SUM(AD8*$Z$4) -> 2130 | AF8: =SUM(AD8) -> 213 | AG8: =SUM(AF8*$Z$4) -> 2130 | AH8: =SUM(AF8) -> 213 | AI8: =SUM(AH8*$Z$4) -> 2130 | AJ8: =SUM(AH8) -> 213 | AK8: =SUM(AJ8*$Z$4) -> 2130 | AL8: =SUM(AJ8) -> 213 | AM8: =SUM(AL8*$Z$4) -> 2130 | AN8: =SUM(AO8/19600) -> 0.76071429 | AO8: =SUM(AA8+AC8+AE8+AG8+AI8+AK8+AM8) -> 14910 | AQ8: =SUM(AR8/92970) -> 0.68734243 | AR8: =SUM(AO8+Y8) -> 63902.226 | AS8: =SUM(AR8-AR7-AT8) -> -4239.129 | AT8: 10066 | AU8: 0.54 | AV8: =IF(AT8>0,AU8,AV7) -> 0.54 | AW8: =-SUM('B5'!AI7) -> -680 | AX8: =-SUM(AW8-AS8) -> -3559.129 | AY8: =SUM(AX8+AW8) -> -4239.129 | AZ8: =ELEC!A5 -> 0.3 | BA8: ='General information '!D8 -> 29 | BB8: =SUM('General information '!E8) -> 0.7 | BC8: =IF(AR7>=AR8,0,1) -> 1 | BD8: 19222 | BE8: =(305/1185)*ELEC!Q6 -> 0 | BG8: =#REF!-BE8 -> #REF! | BH8: 16
A9: =ELEC!C6 -> 44047 | B9: ='B5'!B8 -> 207 | C9: =B9*$B$4 -> 4453.8387 | D9: =SUM(B9) -> 207 | E9: =D9*$B$4 -> 4453.8387 | F9: =SUM(D9) -> 207 | G9: =F9*$B$4 -> 4453.8387 | H9: =SUM(F9) -> 207 | I9: =H9*$B$4 -> 4453.8387 | J9: =SUM(H9) -> 207 | K9: =J9*$B$4 -> 4453.8387 | L9: =SUM(J9) -> 207 | M9: =L9*$B$4 -> 4453.8387 | N9: =SUM(L9) -> 207 | O9: =N9*$B$4 -> 4453.8387 | P9: =SUM(N9) -> 207 | Q9: =P9*$B$4 -> 4453.8387 | R9: =SUM(P9) -> 207 | S9: =R9*$B$4 -> 4453.8387 | T9: =SUM(R9) -> 207 | U9: =T9*$B$4 -> 4453.8387 | V9: =SUM(T9) -> 207 | W9: =V9*$B$4 -> 4453.8387 | X9: =SUM(Y9/73370) -> 0.66774194 | Y9: =SUM(C9+E9+G9+I9+K9+M9+O9+Q9+S9+U9+W9) -> 48992.226 | Z9: ='B5'!C8 -> 194 | AA9: =SUM(Z9*$Z$4) -> 1940 | AB9: =SUM(Z9) -> 194 | AC9: =SUM(AB9*$Z$4) -> 1940 | AD9: =SUM(AB9) -> 194 | AE9: =SUM(AD9*$Z$4) -> 1940 | AF9: =SUM(AD9) -> 194 | AG9: =SUM(AF9*$Z$4) -> 1940 | AH9: =SUM(AF9) -> 194 | AI9: =SUM(AH9*$Z$4) -> 1940 | AJ9: =SUM(AH9) -> 194 | AK9: =SUM(AJ9*$Z$4) -> 1940 | AL9: =SUM(AJ9) -> 194 | AM9: =SUM(AL9*$Z$4) -> 1940 | AN9: =SUM(AO9/19600) -> 0.69285714 | AO9: =SUM(AA9+AC9+AE9+AG9+AI9+AK9+AM9) -> 13580 | AQ9: =SUM(AR9/92970) -> 0.67303674 | AR9: =SUM(AO9+Y9) -> 62572.226 | AS9: =SUM(AR9-AR8-AT9) -> -1330 | AV9: =IF(AT9>0,AU9,AV8) -> 0.54 | AW9: =-SUM('B5'!AI8) -> 0 | AX9: =-SUM(AW9-AS9) -> -1330 | AY9: =SUM(AX9+AW9) -> -1330 | AZ9: =ELEC!A6 -> 0 | BA9: ='General information '!D9 -> 28.5 | BB9: =SUM('General information '!E9) -> 0.69 | BC9: =IF(AR8>=AR9,0,1) -> 0 | BD9: 19222 | BE9: =(305/1185)*ELEC!Q7 -> 3603.3755 | BG9: =#REF!-BE9 -> #REF! | BH9: 18
A10: =ELEC!C7 -> 44048 | B10: ='B5'!B9 -> 187 | C10: =B10*$B$4 -> 4023.5161 | D10: =SUM(B10) -> 187 | E10: =D10*$B$4 -> 4023.5161 | F10: =SUM(D10) -> 187 | G10: =F10*$B$4 -> 4023.5161 | H10: =SUM(F10) -> 187 | I10: =H10*$B$4 -> 4023.5161 | J10: =SUM(H10) -> 187 | K10: =J10*$B$4 -> 4023.5161 | L10: =SUM(J10) -> 187 | M10: =L10*$B$4 -> 4023.5161 | N10: =SUM(L10) -> 187 | O10: =N10*$B$4 -> 4023.5161 | P10: =SUM(N10) -> 187 | Q10: =P10*$B$4 -> 4023.5161 | R10: =SUM(P10) -> 187 | S10: =R10*$B$4 -> 4023.5161 | T10: =SUM(R10) -> 187 | U10: =T10*$B$4 -> 4023.5161 | V10: =SUM(T10) -> 187 | W10: =V10*$B$4 -> 4023.5161 | X10: =SUM(Y10/73370) -> 0.60322581 | Y10: =SUM(C10+E10+G10+I10+K10+M10+O10+Q10+S10+U10+W10) -> 44258.677 | Z10: ='B5'!C9 -> 194 | AA10: =SUM(Z10*$Z$4) -> 1940 | AB10: =SUM(Z10) -> 194 | AC10: =SUM(AB10*$Z$4) -> 1940 | AD10: =SUM(AB10) -> 194 | AE10: =SUM(AD10*$Z$4) -> 1940 | AF10: =SUM(AD10) -> 194 | AG10: =SUM(AF10*$Z$4) -> 1940 | AH10: =SUM(AF10) -> 194 | AI10: =SUM(AH10*$Z$4) -> 1940 | AJ10: =SUM(AH10) -> 194 | AK10: =SUM(AJ10*$Z$4) -> 1940 | AL10: =SUM(AJ10) -> 194 | AM10: =SUM(AL10*$Z$4) -> 1940 | AN10: =SUM(AO10/19600) -> 0.69285714 | AO10: =SUM(AA10+AC10+AE10+AG10+AI10+AK10+AM10) -> 13580 | AQ10: =SUM(AR10/92970) -> 0.62212195 | AR10: =SUM(AO10+Y10) -> 57838.677 | AS10: =SUM(AR10-AR9-AT10) -> -4733.5484 | AV10: =IF(AT10>0,AU10,AV9) -> 0.54 | AW10: =-SUM('B5'!AI9) -> -144 | AX10: =-SUM(AW10-AS10) -> -4589.5484 | AY10: =SUM(AX10+AW10) -> -4733.5484 | AZ10: =ELEC!A7 -> 0 | BA10: ='General information '!D10 -> 28.5 | BB10: =SUM('General information '!E10) -> 0.67 | BC10: =IF(AR9>=AR10,0,1) -> 0 | BD10: 19222 | BE10: =(305/1185)*ELEC!Q8 -> 1286.9198 | BG10: =#REF!-BE10 -> #REF! | BH10: 16
A11: =ELEC!C8 -> 44049 | B11: ='B5'!B10 -> 186 | C11: =B11*$B$4 -> 4002 | D11: =SUM(B11) -> 186 | E11: =D11*$B$4 -> 4002 | F11: =SUM(D11) -> 186 | G11: =F11*$B$4 -> 4002 | H11: =SUM(F11) -> 186 | I11: =H11*$B$4 -> 4002 | J11: =SUM(H11) -> 186 | K11: =J11*$B$4 -> 4002 | L11: =SUM(J11) -> 186 | M11: =L11*$B$4 -> 4002 | N11: =SUM(L11) -> 186 | O11: =N11*$B$4 -> 4002 | P11: =SUM(N11) -> 186 | Q11: =P11*$B$4 -> 4002 | R11: =SUM(P11) -> 186 | S11: =R11*$B$4 -> 4002 | T11: =SUM(R11) -> 186 | U11: =T11*$B$4 -> 4002 | V11: =SUM(T11) -> 186 | W11: =V11*$B$4 -> 4002 | X11: =SUM(Y11/73370) -> 0.6 | Y11: =SUM(C11+E11+G11+I11+K11+M11+O11+Q11+S11+U11+W11) -> 44022 | Z11: ='B5'!C10 -> 192 | AA11: =SUM(Z11*$Z$4) -> 1920 | AB11: =SUM(Z11) -> 192 | AC11: =SUM(AB11*$Z$4) -> 1920 | AD11: =SUM(AB11) -> 192 | AE11: =SUM(AD11*$Z$4) -> 1920 | AF11: =SUM(AD11) -> 192 | AG11: =SUM(AF11*$Z$4) -> 1920 | AH11: =SUM(AF11) -> 192 | AI11: =SUM(AH11*$Z$4) -> 1920 | AJ11: =SUM(AH11) -> 192 | AK11: =SUM(AJ11*$Z$4) -> 1920 | AL11: =SUM(AJ11) -> 192 | AM11: =SUM(AL11*$Z$4) -> 1920 | AN11: =SUM(AO11/19600) -> 0.68571429 | AO11: =SUM(AA11+AC11+AE11+AG11+AI11+AK11+AM11) -> 13440 | AQ11: =SUM(AR11/92970) -> 0.61807035 | AR11: =SUM(AO11+Y11) -> 57462 | AS11: =SUM(AR11-AR10-AT11) -> -376.67742 | AV11: =IF(AT11>0,AU11,AV10) -> 0.54 | AW11: =-SUM('B5'!AI10) -> 0 | AX11: =-SUM(AW11-AS11) -> -376.67742 | AY11: =SUM(AX11+AW11) -> -376.67742 | AZ11: =ELEC!A8 -> 0 | BA11: ='General information '!D11 -> 28.5 | BB11: =SUM('General information '!E11) -> 0.69 | BC11: =IF(AR10>=AR11,0,1) -> 0 | BD11: 19222 | BE11: =(305/1185)*ELEC!Q9 -> 257.38397 | BG11: =#REF!-BE11 -> #REF! | BH11: 16.5
A12: =ELEC!C9 -> 44050 | B12: ='B5'!B11 -> 268 | C12: =B12*$B$4 -> 5766.3226 | D12: =SUM(B12) -> 268 | E12: =D12*$B$4 -> 5766.3226 | F12: =SUM(D12) -> 268 | G12: =F12*$B$4 -> 5766.3226 | H12: =SUM(F12) -> 268 | I12: =H12*$B$4 -> 5766.3226 | J12: =SUM(H12) -> 268 | K12: =J12*$B$4 -> 5766.3226 | L12: =SUM(J12) -> 268 | M12: =L12*$B$4 -> 5766.3226 | N12: =SUM(L12) -> 268 | O12: =N12*$B$4 -> 5766.3226 | P12: =SUM(N12) -> 268 | Q12: =P12*$B$4 -> 5766.3226 | R12: =SUM(P12) -> 268 | S12: =R12*$B$4 -> 5766.3226 | T12: =SUM(R12) -> 268 | U12: =T12*$B$4 -> 5766.3226 | V12: =SUM(T12) -> 268 | W12: =V12*$B$4 -> 5766.3226 | X12: =SUM(Y12/73370) -> 0.86451613 | Y12: =SUM(C12+E12+G12+I12+K12+M12+O12+Q12+S12+U12+W12) -> 63429.548 | Z12: ='B5'!C11 -> 226 | AA12: =SUM(Z12*$Z$4) -> 2260 | AB12: =SUM(Z12) -> 226 | AC12: =SUM(AB12*$Z$4) -> 2260 | AD12: =SUM(AB12) -> 226 | AE12: =SUM(AD12*$Z$4) -> 2260 | AF12: =SUM(AD12) -> 226 | AG12: =SUM(AF12*$Z$4) -> 2260 | AH12: =SUM(AF12) -> 226 | AI12: =SUM(AH12*$Z$4) -> 2260 | AJ12: =SUM(AH12) -> 226 | AK12: =SUM(AJ12*$Z$4) -> 2260 | AL12: =SUM(AJ12) -> 226 | AM12: =SUM(AL12*$Z$4) -> 2260 | AN12: =SUM(AO12/19600) -> 0.80714286 | AO12: =SUM(AA12+AC12+AE12+AG12+AI12+AK12+AM12) -> 15820 | AQ12: =SUM(AR12/92970) -> 0.85242066 | AR12: =SUM(AO12+Y12) -> 79249.548 | AS12: =SUM(AR12-AR11-AT12) -> 2113.5484 | AT12: 19674 | AU12: 0.535 | AV12: =IF(AT12>0,AU12,AV11) -> 0.535 | AW12: =-SUM('B5'!AI11) -> 0 | AX12: =-SUM(AW12-AS12) -> 2113.5484 | AY12: =SUM(AX12+AW12) -> 2113.5484 | AZ12: =ELEC!A9 -> 0 | BA12: ='General information '!D12 -> 27 | BB12: =SUM('General information '!E12) -> 0.7 | BC12: =IF(AR11>=AR12,0,1) -> 1 | BD12: 19222 | BE12: =(305/1185)*ELEC!Q10 -> 514.76793 | BG12: =#REF!-BE12 -> #REF! | BH12: 15.5
A13: =ELEC!C10 -> 44051 | B13: ='B5'!B12 -> 253.3 | C13: =B13*$B$4 -> 5450.0355 | D13: =SUM(B13) -> 253.3 | E13: =D13*$B$4 -> 5450.0355 | F13: =SUM(D13) -> 253.3 | G13: =F13*$B$4 -> 5450.0355 | H13: =SUM(F13) -> 253.3 | I13: =H13*$B$4 -> 5450.0355 | J13: =SUM(H13) -> 253.3 | K13: =J13*$B$4 -> 5450.0355 | L13: =SUM(J13) -> 253.3 | M13: =L13*$B$4 -> 5450.0355 | N13: =SUM(L13) -> 253.3 | O13: =N13*$B$4 -> 5450.0355 | P13: =SUM(N13) -> 253.3 | Q13: =P13*$B$4 -> 5450.0355 | R13: =SUM(P13) -> 253.3 | S13: =R13*$B$4 -> 5450.0355 | T13: =SUM(R13) -> 253.3 | U13: =T13*$B$4 -> 5450.0355 | V13: =SUM(T13) -> 253.3 | W13: =V13*$B$4 -> 5450.0355 | X13: =SUM(Y13/73370) -> 0.81709677 | Y13: =SUM(C13+E13+G13+I13+K13+M13+O13+Q13+S13+U13+W13) -> 59950.39 | Z13: ='B5'!C12 -> 259.5 | AA13: =SUM(Z13*$Z$4) -> 2595 | AB13: =SUM(Z13) -> 259.5 | AC13: =SUM(AB13*$Z$4) -> 2595 | AD13: =SUM(AB13) -> 259.5 | AE13: =SUM(AD13*$Z$4) -> 2595 | AF13: =SUM(AD13) -> 259.5 | AG13: =SUM(AF13*$Z$4) -> 2595 | AH13: =SUM(AF13) -> 259.5 | AI13: =SUM(AH13*$Z$4) -> 2595 | AJ13: =SUM(AH13) -> 259.5 | AK13: =SUM(AJ13*$Z$4) -> 2595 | AL13: =SUM(AJ13) -> 259.5 | AM13: =SUM(AL13*$Z$4) -> 2595 | AN13: =SUM(AO13/19600) -> 0.92678571 | AO13: =SUM(AA13+AC13+AE13+AG13+AI13+AK13+AM13) -> 18165 | AQ13: =SUM(AR13/92970) -> 0.84022147 | AR13: =SUM(AO13+Y13) -> 78115.39 | AS13: =SUM(AR13-AR12-AT13) -> -1134.1581 | AV13: =IF(AT13>0,AU13,AV12) -> 0.535 | AW13: =-SUM('B5'!AI12) -> 0 | AX13: =-SUM(AW13-AS13) -> -1134.1581 | AY13: =SUM(AX13+AW13) -> -1134.1581 | AZ13: =ELEC!A10 -> 0 | BA13: ='General information '!D13 -> 28.5 | BB13: =SUM('General information '!E13) -> 0.46 | BC13: =IF(AR12>=AR13,0,1) -> 0 | BD13: 19222 | BE13: =(305/1185)*ELEC!Q11 -> 514.76793 | BG13: =#REF!-BE13 -> #REF!
A14: =ELEC!C11 -> 44052 | B14: ='B5'!B13 -> 251.4 | C14: =B14*$B$4 -> 5409.1548 | D14: =SUM(B14) -> 251.4 | E14: =D14*$B$4 -> 5409.1548 | F14: =SUM(D14) -> 251.4 | G14: =F14*$B$4 -> 5409.1548 | H14: =SUM(F14) -> 251.4 | I14: =H14*$B$4 -> 5409.1548 | J14: =SUM(H14) -> 251.4 | K14: =J14*$B$4 -> 5409.1548 | L14: =SUM(J14) -> 251.4 | M14: =L14*$B$4 -> 5409.1548 | N14: =SUM(L14) -> 251.4 | O14: =N14*$B$4 -> 5409.1548 | P14: =SUM(N14) -> 251.4 | Q14: =P14*$B$4 -> 5409.1548 | R14: =SUM(P14) -> 251.4 | S14: =R14*$B$4 -> 5409.1548 | T14: =SUM(R14) -> 251.4 | U14: =T14*$B$4 -> 5409.1548 | V14: =SUM(T14) -> 251.4 | W14: =V14*$B$4 -> 5409.1548 | X14: =SUM(Y14/73370) -> 0.81096774 | Y14: =SUM(C14+E14+G14+I14+K14+M14+O14+Q14+S14+U14+W14) -> 59500.703 | Z14: ='B5'!C13 -> 257.4 | AA14: =SUM(Z14*$Z$4) -> 2574 | AB14: =SUM(Z14) -> 257.4 | AC14: =SUM(AB14*$Z$4) -> 2574 | AD14: =SUM(AB14) -> 257.4 | AE14: =SUM(AD14*$Z$4) -> 2574 | AF14: =SUM(AD14) -> 257.4 | AG14: =SUM(AF14*$Z$4) -> 2574 | AH14: =SUM(AF14) -> 257.4 | AI14: =SUM(AH14*$Z$4) -> 2574 | AJ14: =SUM(AH14) -> 257.4 | AK14: =SUM(AJ14*$Z$4) -> 2574 | AL14: =SUM(AJ14) -> 257.4 | AM14: =SUM(AL14*$Z$4) -> 2574 | AN14: =SUM(AO14/19600) -> 0.91928571 | AO14: =SUM(AA14+AC14+AE14+AG14+AI14+AK14+AM14) -> 18018 | AQ14: =SUM(AR14/92970) -> 0.83380341 | AR14: =SUM(AO14+Y14) -> 77518.703 | AS14: =SUM(AR14-AR13-AT14) -> -596.6871 | AV14: =IF(AT14>0,AU14,AV13) -> 0.535 | AW14: =-SUM('B5'!AI13) -> 0 | AX14: =-SUM(AW14-AS14) -> -596.6871 | AY14: =SUM(AX14+AW14) -> -596.6871 | AZ14: =ELEC!A11 -> 0 | BA14: ='General information '!D14 -> 29 | BB14: =SUM('General information '!E14) -> 0.6 | BC14: =IF(AR13>=AR14,0,1) -> 0 | BD14: 19222 | BE14: =(305/1185)*ELEC!Q12 -> 257.38397 | BG14: =#REF!-BE14 -> #REF!
A15: =ELEC!C12 -> 44053 | B15: ='B5'!B14 -> 250 | C15: =B15*$B$4 -> 5379.0323 | D15: =SUM(B15) -> 250 | E15: =D15*$B$4 -> 5379.0323 | F15: =SUM(D15) -> 250 | G15: =F15*$B$4 -> 5379.0323 | H15: =SUM(F15) -> 250 | I15: =H15*$B$4 -> 5379.0323 | J15: =SUM(H15) -> 250 | K15: =J15*$B$4 -> 5379.0323 | L15: =SUM(J15) -> 250 | M15: =L15*$B$4 -> 5379.0323 | N15: =SUM(L15) -> 250 | O15: =N15*$B$4 -> 5379.0323 | P15: =SUM(N15) -> 250 | Q15: =P15*$B$4 -> 5379.0323 | R15: =SUM(P15) -> 250 | S15: =R15*$B$4 -> 5379.0323 | T15: =SUM(R15) -> 250 | U15: =T15*$B$4 -> 5379.0323 | V15: =SUM(T15) -> 250 | W15: =V15*$B$4 -> 5379.0323 | X15: =SUM(Y15/73370) -> 0.80645161 | Y15: =SUM(C15+E15+G15+I15+K15+M15+O15+Q15+S15+U15+W15) -> 59169.355 | Z15: ='B5'!C14 -> 255.4 | AA15: =SUM(Z15*$Z$4) -> 2554 | AB15: =SUM(Z15) -> 255.4 | AC15: =SUM(AB15*$Z$4) -> 2554 | AD15: =SUM(AB15) -> 255.4 | AE15: =SUM(AD15*$Z$4) -> 2554 | AF15: =SUM(AD15) -> 255.4 | AG15: =SUM(AF15*$Z$4) -> 2554 | AH15: =SUM(AF15) -> 255.4 | AI15: =SUM(AH15*$Z$4) -> 2554 | AJ15: =SUM(AH15) -> 255.4 | AK15: =SUM(AJ15*$Z$4) -> 2554 | AL15: =SUM(AJ15) -> 255.4 | AM15: =SUM(AL15*$Z$4) -> 2554 | AN15: =SUM(AO15/19600) -> 0.91214286 | AO15: =SUM(AA15+AC15+AE15+AG15+AI15+AK15+AM15) -> 17878 | AQ15: =SUM(AR15/92970) -> 0.82873351 | AR15: =SUM(AO15+Y15) -> 77047.355 | AS15: =SUM(AR15-AR14-AT15) -> -471.34839 | AV15: =IF(AT15>0,AU15,AV14) -> 0.535 | AW15: =-SUM('B5'!AI14) -> 0 | AX15: =-SUM(AW15-AS15) -> -471.34839 | AY15: =SUM(AX15+AW15) -> -471.34839 | AZ15: =ELEC!A12 -> 0 | BA15: ='General information '!D15 -> 27 | BB15: =SUM('General information '!E15) -> 0.69 | BC15: =IF(AR14>=AR15,0,1) -> 0 | BD15: 19222 | BE15: =(305/1185)*ELEC!Q13 -> 514.76793 | BG15: =#REF!-BE15 -> #REF!
A16: =ELEC!C13 -> 44054 | B16: ='B5'!B15 -> 248 | C16: =B16*$B$4 -> 5336 | D16: =SUM(B16) -> 248 | E16: =D16*$B$4 -> 5336 | F16: =SUM(D16) -> 248 | G16: =F16*$B$4 -> 5336 | H16: =SUM(F16) -> 248 | I16: =H16*$B$4 -> 5336 | J16: =SUM(H16) -> 248 | K16: =J16*$B$4 -> 5336 | L16: =SUM(J16) -> 248 | M16: =L16*$B$4 -> 5336 | N16: =SUM(L16) -> 248 | O16: =N16*$B$4 -> 5336 | P16: =SUM(N16) -> 248 | Q16: =P16*$B$4 -> 5336 | R16: =SUM(P16) -> 248 | S16: =R16*$B$4 -> 5336 | T16: =SUM(R16) -> 248 | U16: =T16*$B$4 -> 5336 | V16: =SUM(T16) -> 248 | W16: =V16*$B$4 -> 5336 | X16: =SUM(Y16/73370) -> 0.8 | Y16: =SUM(C16+E16+G16+I16+K16+M16+O16+Q16+S16+U16+W16) -> 58696 | Z16: ='B5'!C15 -> 253.3 | AA16: =SUM(Z16*$Z$4) -> 2533 | AB16: =SUM(Z16) -> 253.3 | AC16: =SUM(AB16*$Z$4) -> 2533 | AD16: =SUM(AB16) -> 253.3 | AE16: =SUM(AD16*$Z$4) -> 2533 | AF16: =SUM(AD16) -> 253.3 | AG16: =SUM(AF16*$Z$4) -> 2533 | AH16: =SUM(AF16) -> 253.3 | AI16: =SUM(AH16*$Z$4) -> 2533 | AJ16: =SUM(AH16) -> 253.3 | AK16: =SUM(AJ16*$Z$4) -> 2533 | AL16: =SUM(AJ16) -> 253.3 | AM16: =SUM(AL16*$Z$4) -> 2533 | AN16: =SUM(AO16/19600) -> 0.90464286 | AO16: =SUM(AA16+AC16+AE16+AG16+AI16+AK16+AM16) -> 17731 | AQ16: =SUM(AR16/92970) -> 0.82206088 | AR16: =SUM(AO16+Y16) -> 76427 | AS16: =SUM(AR16-AR15-AT16) -> -620.35484 | AV16: =IF(AT16>0,AU16,AV15) -> 0.535 | AW16: =-SUM('B5'!AI15) -> -115.2 | AX16: =-SUM(AW16-AS16) -> -505.15484 | AY16: =SUM(AX16+AW16) -> -620.35484 | AZ16: =ELEC!A13 -> 0 | BA16: ='General information '!D16 -> 28.5 | BB16: =SUM('General information '!E16) -> 0.67 | BC16: =IF(AR15>=AR16,0,1) -> 0 | BD16: 19222 | BE16: =(305/1185)*ELEC!Q14 -> 514.76793 | BG16: =#REF!-BE16 -> #REF!
A17: =ELEC!C14 -> 44055 | B17: ='B5'!B16 -> 242.4 | C17: =B17*$B$4 -> 5215.5097 | D17: =SUM(B17) -> 242.4 | E17: =D17*$B$4 -> 5215.5097 | F17: =SUM(D17) -> 242.4 | G17: =F17*$B$4 -> 5215.5097 | H17: =SUM(F17) -> 242.4 | I17: =H17*$B$4 -> 5215.5097 | J17: =SUM(H17) -> 242.4 | K17: =J17*$B$4 -> 5215.5097 | L17: =SUM(J17) -> 242.4 | M17: =L17*$B$4 -> 5215.5097 | N17: =SUM(L17) -> 242.4 | O17: =N17*$B$4 -> 5215.5097 | P17: =SUM(N17) -> 242.4 | Q17: =P17*$B$4 -> 5215.5097 | R17: =SUM(P17) -> 242.4 | S17: =R17*$B$4 -> 5215.5097 | T17: =SUM(R17) -> 242.4 | U17: =T17*$B$4 -> 5215.5097 | V17: =SUM(T17) -> 242.4 | W17: =V17*$B$4 -> 5215.5097 | X17: =SUM(Y17/73370) -> 0.78193548 | Y17: =SUM(C17+E17+G17+I17+K17+M17+O17+Q17+S17+U17+W17) -> 57370.606 | Z17: ='B5'!C16 -> 248 | AA17: =SUM(Z17*$Z$4) -> 2480 | AB17: =SUM(Z17) -> 248 | AC17: =SUM(AB17*$Z$4) -> 2480 | AD17: =SUM(AB17) -> 248 | AE17: =SUM(AD17*$Z$4) -> 2480 | AF17: =SUM(AD17) -> 248 | AG17: =SUM(AF17*$Z$4) -> 2480 | AH17: =SUM(AF17) -> 248 | AI17: =SUM(AH17*$Z$4) -> 2480 | AJ17: =SUM(AH17) -> 248 | AK17: =SUM(AJ17*$Z$4) -> 2480 | AL17: =SUM(AJ17) -> 248 | AM17: =SUM(AL17*$Z$4) -> 2480 | AN17: =SUM(AO17/19600) -> 0.88571429 | AO17: =SUM(AA17+AC17+AE17+AG17+AI17+AK17+AM17) -> 17360 | AQ17: =SUM(AR17/92970) -> 0.8038142 | AR17: =SUM(AO17+Y17) -> 74730.606 | AS17: =SUM(AR17-AR16-AT17) -> -1696.3935 | AV17: =IF(AT17>0,AU17,AV16) -> 0.535 | AW17: =-SUM('B5'!AI16) -> 0 | AX17: =-SUM(AW17-AS17) -> -1696.3935 | AY17: =SUM(AX17+AW17) -> -1696.3935 | AZ17: =ELEC!A14 -> 0 | BA17: ='General information '!D17 -> 28 | BB17: =SUM('General information '!E17) -> 0.67 | BC17: =IF(AR16>=AR17,0,1) -> 0 | BD17: 19222 | BE17: =(305/1185)*ELEC!Q15 -> 514.76793 | BG17: =#REF!-BE17 -> #REF!
A18: =ELEC!C15 -> 44056 | B18: ='B5'!B17 -> 242.4 | C18: =B18*$B$4 -> 5215.5097 | D18: =SUM(B18) -> 242.4 | E18: =D18*$B$4 -> 5215.5097 | F18: =SUM(D18) -> 242.4 | G18: =F18*$B$4 -> 5215.5097 | H18: =SUM(F18) -> 242.4 | I18: =H18*$B$4 -> 5215.5097 | J18: =SUM(H18) -> 242.4 | K18: =J18*$B$4 -> 5215.5097 | L18: =SUM(J18) -> 242.4 | M18: =L18*$B$4 -> 5215.5097 | N18: =SUM(L18) -> 242.4 | O18: =N18*$B$4 -> 5215.5097 | P18: =SUM(N18) -> 242.4 | Q18: =P18*$B$4 -> 5215.5097 | R18: =SUM(P18) -> 242.4 | S18: =R18*$B$4 -> 5215.5097 | T18: =SUM(R18) -> 242.4 | U18: =T18*$B$4 -> 5215.5097 | V18: =SUM(T18) -> 242.4 | W18: =V18*$B$4 -> 5215.5097 | X18: =SUM(Y18/73370) -> 0.78193548 | Y18: =SUM(C18+E18+G18+I18+K18+M18+O18+Q18+S18+U18+W18) -> 57370.606 | Z18: ='B5'!C17 -> 248 | AA18: =SUM(Z18*$Z$4) -> 2480 | AB18: =SUM(Z18) -> 248 | AC18: =SUM(AB18*$Z$4) -> 2480 | AD18: =SUM(AB18) -> 248 | AE18: =SUM(AD18*$Z$4) -> 2480 | AF18: =SUM(AD18) -> 248 | AG18: =SUM(AF18*$Z$4) -> 2480 | AH18: =SUM(AF18) -> 248 | AI18: =SUM(AH18*$Z$4) -> 2480 | AJ18: =SUM(AH18) -> 248 | AK18: =SUM(AJ18*$Z$4) -> 2480 | AL18: =SUM(AJ18) -> 248 | AM18: =SUM(AL18*$Z$4) -> 2480 | AN18: =SUM(AO18/19600) -> 0.88571429 | AO18: =SUM(AA18+AC18+AE18+AG18+AI18+AK18+AM18) -> 17360 | AQ18: =SUM(AR18/92970) -> 0.8038142 | AR18: =SUM(AO18+Y18) -> 74730.606 | AS18: =SUM(AR18-AR17-AT18) -> 0 | AV18: =IF(AT18>0,AU18,AV17) -> 0.535 | AW18: =-SUM('B5'!AI17) -> 0 | AX18: =-SUM(AW18-AS18) -> 0 | AY18: =SUM(AX18+AW18) -> 0 | AZ18: =ELEC!A15 -> 0 | BA18: ='General information '!D18 -> 27.5 | BB18: =SUM('General information '!E18) -> 0 | BC18: =IF(AR17>=AR18,0,1) -> 0 | BD18: 19222 | BE18: =(305/1185)*ELEC!Q16 -> 1029.5359 | BG18: =#REF!-BE18 -> #REF!
A19: =ELEC!C16 -> 44057 | B19: ='B5'!B18 -> 238 | C19: =B19*$B$4 -> 5120.8387 | D19: =SUM(B19) -> 238 | E19: =D19*$B$4 -> 5120.8387 | F19: =SUM(D19) -> 238 | G19: =F19*$B$4 -> 5120.8387 | H19: =SUM(F19) -> 238 | I19: =H19*$B$4 -> 5120.8387 | J19: =SUM(H19) -> 238 | K19: =J19*$B$4 -> 5120.8387 | L19: =SUM(J19) -> 238 | M19: =L19*$B$4 -> 5120.8387 | N19: =SUM(L19) -> 238 | O19: =N19*$B$4 -> 5120.8387 | P19: =SUM(N19) -> 238 | Q19: =P19*$B$4 -> 5120.8387 | R19: =SUM(P19) -> 238 | S19: =R19*$B$4 -> 5120.8387 | T19: =SUM(R19) -> 238 | U19: =T19*$B$4 -> 5120.8387 | V19: =SUM(T19) -> 238 | W19: =V19*$B$4 -> 5120.8387 | X19: =SUM(Y19/73370) -> 0.76774194 | Y19: =SUM(C19+E19+G19+I19+K19+M19+O19+Q19+S19+U19+W19) -> 56329.226 | Z19: ='B5'!C18 -> 244.5 | AA19: =SUM(Z19*$Z$4) -> 2445 | AB19: =SUM(Z19) -> 244.5 | AC19: =SUM(AB19*$Z$4) -> 2445 | AD19: =SUM(AB19) -> 244.5 | AE19: =SUM(AD19*$Z$4) -> 2445 | AF19: =SUM(AD19) -> 244.5 | AG19: =SUM(AF19*$Z$4) -> 2445 | AH19: =SUM(AF19) -> 244.5 | AI19: =SUM(AH19*$Z$4) -> 2445 | AJ19: =SUM(AH19) -> 244.5 | AK19: =SUM(AJ19*$Z$4) -> 2445 | AL19: =SUM(AJ19) -> 244.5 | AM19: =SUM(AL19*$Z$4) -> 2445 | AN19: =SUM(AO19/19600) -> 0.87321429 | AO19: =SUM(AA19+AC19+AE19+AG19+AI19+AK19+AM19) -> 17115 | AQ19: =SUM(AR19/92970) -> 0.78997769 | AR19: =SUM(AO19+Y19) -> 73444.226 | AS19: =SUM(AR19-AR18-AT19) -> -1286.3806 | AV19: =IF(AT19>0,AU19,AV18) -> 0.535 | AW19: =-SUM('B5'!AI18) -> 0 | AX19: =-SUM(AW19-AS19) -> -1286.3806 | AY19: =SUM(AX19+AW19) -> -1286.3806 | AZ19: =ELEC!A16 -> 0 | BA19: ='General information '!D19 -> 27.5 | BB19: =SUM('General information '!E19) -> 0.68 | BC19: =IF(AR18>=AR19,0,1) -> 0 | BD19: 19222 | BE19: =(305/1185)*ELEC!Q17 -> 514.76793 | BG19: =#REF!-BE19 -> #REF!
A20: =ELEC!C17 -> 44058 | B20: ='B5'!B19 -> 235 | C20: =B20*$B$4 -> 5056.2903 | D20: =SUM(B20) -> 235 | E20: =D20*$B$4 -> 5056.2903 | F20: =SUM(D20) -> 235 | G20: =F20*$B$4 -> 5056.2903 | H20: =SUM(F20) -> 235 | I20: =H20*$B$4 -> 5056.2903 | J20: =SUM(H20) -> 235 | K20: =J20*$B$4 -> 5056.2903 | L20: =SUM(J20) -> 235 | M20: =L20*$B$4 -> 5056.2903 | N20: =SUM(L20) -> 235 | O20: =N20*$B$4 -> 5056.2903 | P20: =SUM(N20) -> 235 | Q20: =P20*$B$4 -> 5056.2903 | R20: =SUM(P20) -> 235 | S20: =R20*$B$4 -> 5056.2903 | T20: =SUM(R20) -> 235 | U20: =T20*$B$4 -> 5056.2903 | V20: =SUM(T20) -> 235 | W20: =V20*$B$4 -> 5056.2903 | X20: =SUM(Y20/73370) -> 0.75806452 | Y20: =SUM(C20+E20+G20+I20+K20+M20+O20+Q20+S20+U20+W20) -> 55619.194 | Z20: ='B5'!C19 -> 241.2 | AA20: =SUM(Z20*$Z$4) -> 2412 | AB20: =SUM(Z20) -> 241.2 | AC20: =SUM(AB20*$Z$4) -> 2412 | AD20: =SUM(AB20) -> 241.2 | AE20: =SUM(AD20*$Z$4) -> 2412 | AF20: =SUM(AD20) -> 241.2 | AG20: =SUM(AF20*$Z$4) -> 2412 | AH20: =SUM(AF20) -> 241.2 | AI20: =SUM(AH20*$Z$4) -> 2412 | AJ20: =SUM(AH20) -> 241.2 | AK20: =SUM(AJ20*$Z$4) -> 2412 | AL20: =SUM(AJ20) -> 241.2 | AM20: =SUM(AL20*$Z$4) -> 2412 | AN20: =SUM(AO20/19600) -> 0.86142857 | AO20: =SUM(AA20+AC20+AE20+AG20+AI20+AK20+AM20) -> 16884 | AQ20: =SUM(AR20/92970) -> 0.7798558 | AR20: =SUM(AO20+Y20) -> 72503.194 | AS20: =SUM(AR20-AR19-AT20) -> -941.03226 | AV20: =IF(AT20>0,AU20,AV19) -> 0.535 | AW20: =-SUM('B5'!AI19) -> 0 | AX20: =-SUM(AW20-AS20) -> -941.03226 | AY20: =SUM(AX20+AW20) -> -941.03226 | AZ20: =ELEC!A17 -> 0 | BA20: ='General information '!D20 -> 27.5 | BB20: =SUM('General information '!E20) -> 0.67 | BC20: =IF(AR19>=AR20,0,1) -> 0 | BD20: 19222 | BE20: =(305/1185)*ELEC!Q18 -> 514.76793 | BG20: =#REF!-BE20 -> #REF!
A21: =ELEC!C18 -> 44059 | B21: ='B5'!B20 -> 234.4 | C21: =B21*$B$4 -> 5043.3806 | D21: =SUM(B21) -> 234.4 | E21: =D21*$B$4 -> 5043.3806 | F21: =SUM(D21) -> 234.4 | G21: =F21*$B$4 -> 5043.3806 | H21: =SUM(F21) -> 234.4 | I21: =H21*$B$4 -> 5043.3806 | J21: =SUM(H21) -> 234.4 | K21: =J21*$B$4 -> 5043.3806 | L21: =SUM(J21) -> 234.4 | M21: =L21*$B$4 -> 5043.3806 | N21: =SUM(L21) -> 234.4 | O21: =N21*$B$4 -> 5043.3806 | P21: =SUM(N21) -> 234.4 | Q21: =P21*$B$4 -> 5043.3806 | R21: =SUM(P21) -> 234.4 | S21: =R21*$B$4 -> 5043.3806 | T21: =SUM(R21) -> 234.4 | U21: =T21*$B$4 -> 5043.3806 | V21: =SUM(T21) -> 234.4 | W21: =V21*$B$4 -> 5043.3806 | X21: =SUM(Y21/73370) -> 0.75612903 | Y21: =SUM(C21+E21+G21+I21+K21+M21+O21+Q21+S21+U21+W21) -> 55477.187 | Z21: ='B5'!C20 -> 240.1 | AA21: =SUM(Z21*$Z$4) -> 2401 | AB21: =SUM(Z21) -> 240.1 | AC21: =SUM(AB21*$Z$4) -> 2401 | AD21: =SUM(AB21) -> 240.1 | AE21: =SUM(AD21*$Z$4) -> 2401 | AF21: =SUM(AD21) -> 240.1 | AG21: =SUM(AF21*$Z$4) -> 2401 | AH21: =SUM(AF21) -> 240.1 | AI21: =SUM(AH21*$Z$4) -> 2401 | AJ21: =SUM(AH21) -> 240.1 | AK21: =SUM(AJ21*$Z$4) -> 2401 | AL21: =SUM(AJ21) -> 240.1 | AM21: =SUM(AL21*$Z$4) -> 2401 | AN21: =SUM(AO21/19600) -> 0.8575 | AO21: =SUM(AA21+AC21+AE21+AG21+AI21+AK21+AM21) -> 16807 | AQ21: =SUM(AR21/92970) -> 0.77750013 | AR21: =SUM(AO21+Y21) -> 72284.187 | AS21: =SUM(AR21-AR20-AT21) -> -219.00645 | AV21: =IF(AT21>0,AU21,AV20) -> 0.535 | AW21: =-SUM('B5'!AI20) -> 0 | AX21: =-SUM(AW21-AS21) -> -219.00645 | AY21: =SUM(AX21+AW21) -> -219.00645 | AZ21: =ELEC!A18 -> 0 | BA21: ='General information '!D21 -> 28 | BB21: =SUM('General information '!E21) -> 0.66 | BC21: =IF(AR20>=AR21,0,1) -> 0 | BD21: 19222 | BE21: =(305/1185)*ELEC!Q19 -> 257.38397 | BG21: =#REF!-BE21 -> #REF!
A22: =ELEC!C19 -> 44060 | B22: ='B5'!B21 -> 232 | C22: =B22*$B$4 -> 4991.7419 | D22: =SUM(B22) -> 232 | E22: =D22*$B$4 -> 4991.7419 | F22: =SUM(D22) -> 232 | G22: =F22*$B$4 -> 4991.7419 | H22: =SUM(F22) -> 232 | I22: =H22*$B$4 -> 4991.7419 | J22: =SUM(H22) -> 232 | K22: =J22*$B$4 -> 4991.7419 | L22: =SUM(J22) -> 232 | M22: =L22*$B$4 -> 4991.7419 | N22: =SUM(L22) -> 232 | O22: =N22*$B$4 -> 4991.7419 | P22: =SUM(N22) -> 232 | Q22: =P22*$B$4 -> 4991.7419 | R22: =SUM(P22) -> 232 | S22: =R22*$B$4 -> 4991.7419 | T22: =SUM(R22) -> 232 | U22: =T22*$B$4 -> 4991.7419 | V22: =SUM(T22) -> 232 | W22: =V22*$B$4 -> 4991.7419 | X22: =SUM(Y22/73370) -> 0.7483871 | Y22: =SUM(C22+E22+G22+I22+K22+M22+O22+Q22+S22+U22+W22) -> 54909.161 | Z22: ='B5'!C21 -> 238.1 | AA22: =SUM(Z22*$Z$4) -> 2381 | AB22: =SUM(Z22) -> 238.1 | AC22: =SUM(AB22*$Z$4) -> 2381 | AD22: =SUM(AB22) -> 238.1 | AE22: =SUM(AD22*$Z$4) -> 2381 | AF22: =SUM(AD22) -> 238.1 | AG22: =SUM(AF22*$Z$4) -> 2381 | AH22: =SUM(AF22) -> 238.1 | AI22: =SUM(AH22*$Z$4) -> 2381 | AJ22: =SUM(AH22) -> 238.1 | AK22: =SUM(AJ22*$Z$4) -> 2381 | AL22: =SUM(AJ22) -> 238.1 | AM22: =SUM(AL22*$Z$4) -> 2381 | AN22: =SUM(AO22/19600) -> 0.85035714 | AO22: =SUM(AA22+AC22+AE22+AG22+AI22+AK22+AM22) -> 16667 | AQ22: =SUM(AR22/92970) -> 0.76988449 | AR22: =SUM(AO22+Y22) -> 71576.161 | AS22: =SUM(AR22-AR21-AT22) -> -708.02581 | AV22: =IF(AT22>0,AU22,AV21) -> 0.535 | AW22: =-SUM('B5'!AI21) -> 0 | AX22: =-SUM(AW22-AS22) -> -708.02581 | AY22: =SUM(AX22+AW22) -> -708.02581 | AZ22: =ELEC!A19 -> 0 | BA22: ='General information '!D22 -> 28.5 | BB22: =SUM('General information '!E22) -> 0.69 | BC22: =IF(AR21>=AR22,0,1) -> 0 | BD22: 19222 | BE22: =(305/1185)*ELEC!Q20 -> 257.38397 | BG22: =#REF!-BE22 -> #REF!
A23: =ELEC!C20 -> 44061 | B23: ='B5'!B22 -> 230 | C23: =B23*$B$4 -> 4948.7097 | D23: =SUM(B23) -> 230 | E23: =D23*$B$4 -> 4948.7097 | F23: =SUM(D23) -> 230 | G23: =F23*$B$4 -> 4948.7097 | H23: =SUM(F23) -> 230 | I23: =H23*$B$4 -> 4948.7097 | J23: =SUM(H23) -> 230 | K23: =J23*$B$4 -> 4948.7097 | L23: =SUM(J23) -> 230 | M23: =L23*$B$4 -> 4948.7097 | N23: =SUM(L23) -> 230 | O23: =N23*$B$4 -> 4948.7097 | P23: =SUM(N23) -> 230 | Q23: =P23*$B$4 -> 4948.7097 | R23: =SUM(P23) -> 230 | S23: =R23*$B$4 -> 4948.7097 | T23: =SUM(R23) -> 230 | U23: =T23*$B$4 -> 4948.7097 | V23: =SUM(T23) -> 230 | W23: =V23*$B$4 -> 4948.7097 | X23: =SUM(Y23/73370) -> 0.74193548 | Y23: =SUM(C23+E23+G23+I23+K23+M23+O23+Q23+S23+U23+W23) -> 54435.806 | Z23: ='B5'!C22 -> 236 | AA23: =SUM(Z23*$Z$4) -> 2360 | AB23: =SUM(Z23) -> 236 | AC23: =SUM(AB23*$Z$4) -> 2360 | AD23: =SUM(AB23) -> 236 | AE23: =SUM(AD23*$Z$4) -> 2360 | AF23: =SUM(AD23) -> 236 | AG23: =SUM(AF23*$Z$4) -> 2360 | AH23: =SUM(AF23) -> 236 | AI23: =SUM(AH23*$Z$4) -> 2360 | AJ23: =SUM(AH23) -> 236 | AK23: =SUM(AJ23*$Z$4) -> 2360 | AL23: =SUM(AJ23) -> 236 | AM23: =SUM(AL23*$Z$4) -> 2360 | AN23: =SUM(AO23/19600) -> 0.84285714 | AO23: =SUM(AA23+AC23+AE23+AG23+AI23+AK23+AM23) -> 16520 | AQ23: =SUM(AR23/92970) -> 0.76321186 | AR23: =SUM(AO23+Y23) -> 70955.806 | AS23: =SUM(AR23-AR22-AT23) -> -620.35484 | AV23: =IF(AT23>0,AU23,AV22) -> 0.535 | AW23: =-SUM('B5'!AI22) -> -455 | AX23: =-SUM(AW23-AS23) -> -165.35484 | AY23: =SUM(AX23+AW23) -> -620.35484 | AZ23: =ELEC!A20 -> 0 | BA23: ='General information '!D23 -> 0 | BB23: =SUM('General information '!E23) -> 0 | BC23: =IF(AR22>=AR23,0,1) -> 0 | BD23: 19222 | BE23: =(305/1185)*ELEC!Q21 -> 0 | BG23: =#REF!-BE23 -> #REF!
A24: =ELEC!C21 -> 44062 | B24: ='B5'!B23 -> 230 | C24: =B24*$B$4 -> 4948.7097 | D24: =SUM(B24) -> 230 | E24: =D24*$B$4 -> 4948.7097 | F24: =SUM(D24) -> 230 | G24: =F24*$B$4 -> 4948.7097 | H24: =SUM(F24) -> 230 | I24: =H24*$B$4 -> 4948.7097 | J24: =SUM(H24) -> 230 | K24: =J24*$B$4 -> 4948.7097 | L24: =SUM(J24) -> 230 | M24: =L24*$B$4 -> 4948.7097 | N24: =SUM(L24) -> 230 | O24: =N24*$B$4 -> 4948.7097 | P24: =SUM(N24) -> 230 | Q24: =P24*$B$4 -> 4948.7097 | R24: =SUM(P24) -> 230 | S24: =R24*$B$4 -> 4948.7097 | T24: =SUM(R24) -> 230 | U24: =T24*$B$4 -> 4948.7097 | V24: =SUM(T24) -> 230 | W24: =V24*$B$4 -> 4948.7097 | X24: =SUM(Y24/73370) -> 0.74193548 | Y24: =SUM(C24+E24+G24+I24+K24+M24+O24+Q24+S24+U24+W24) -> 54435.806 | Z24: ='B5'!C23 -> 236 | AA24: =SUM(Z24*$Z$4) -> 2360 | AB24: =SUM(Z24) -> 236 | AC24: =SUM(AB24*$Z$4) -> 2360 | AD24: =SUM(AB24) -> 236 | AE24: =SUM(AD24*$Z$4) -> 2360 | AF24: =SUM(AD24) -> 236 | AG24: =SUM(AF24*$Z$4) -> 2360 | AH24: =SUM(AF24) -> 236 | AI24: =SUM(AH24*$Z$4) -> 2360 | AJ24: =SUM(AH24) -> 236 | AK24: =SUM(AJ24*$Z$4) -> 2360 | AL24: =SUM(AJ24) -> 236 | AM24: =SUM(AL24*$Z$4) -> 2360 | AN24: =SUM(AO24/19600) -> 0.84285714 | AO24: =SUM(AA24+AC24+AE24+AG24+AI24+AK24+AM24) -> 16520 | AQ24: =SUM(AR24/92970) -> 0.76321186 | AR24: =SUM(AO24+Y24) -> 70955.806 | AS24: =SUM(AR24-AR23-AT24) -> 0 | AV24: =IF(AT24>0,AU24,AV23) -> 0.535 | AW24: =-SUM('B5'!AI23) -> 0 | AX24: =-SUM(AW24-AS24) -> 0 | AY24: =SUM(AX24+AW24) -> 0 | AZ24: =ELEC!A21 -> 0 | BA24: ='General information '!D24 -> 0 | BB24: =SUM('General information '!E24) -> 0 | BC24: =IF(AR23>=AR24,0,1) -> 0 | BD24: 19222 | BE24: =(305/1185)*ELEC!Q22 -> 0 | BG24: =#REF!-BE24 -> #REF!
... A33: =ELEC!C30 -> 44071 | B33: ='B5'!B32 -> 230 | C33: =B33*$B$4 -> 4948.7097 | D33: =SUM(B33) -> 230 | E33: =D33*$B$4 -> 4948.7097 | F33: =SUM(D33) -> 230 | G33: =F33*$B$4 -> 4948.7097 | H33: =SUM(F33) -> 230 | I33: =H33*$B$4 -> 4948.7097 | J33: =SUM(H33) -> 230 | K33: =J33*$B$4 -> 4948.7097 | L33: =SUM(J33) -> 230 | M33: =L33*$B$4 -> 4948.7097 | N33: =SUM(L33) -> 230 | O33: =N33*$B$4 -> 4948.7097 | P33: =SUM(N33) -> 230 | Q33: =P33*$B$4 -> 4948.7097 | R33: =SUM(P33) -> 230 | S33: =R33*$B$4 -> 4948.7097 | T33: =SUM(R33) -> 230 | U33: =T33*$B$4 -> 4948.7097 | V33: =SUM(T33) -> 230 | W33: =V33*$B$4 -> 4948.7097 | X33: =SUM(Y33/73370) -> 0.74193548 | Y33: =SUM(C33+E33+G33+I33+K33+M33+O33+Q33+S33+U33+W33) -> 54435.806 | Z33: ='B5'!C32 -> 236 | AA33: =SUM(Z33*$Z$4) -> 2360 | AB33: =SUM(Z33) -> 236 | AC33: =SUM(AB33*$Z$4) -> 2360 | AD33: =SUM(AB33) -> 236 | AE33: =SUM(AD33*$Z$4) -> 2360 | AF33: =SUM(AD33) -> 236 | AG33: =SUM(AF33*$Z$4) -> 2360 | AH33: =SUM(AF33) -> 236 | AI33: =SUM(AH33*$Z$4) -> 2360 | AJ33: =SUM(AH33) -> 236 | AK33: =SUM(AJ33*$Z$4) -> 2360 | AL33: =SUM(AJ33) -> 236 | AM33: =SUM(AL33*$Z$4) -> 2360 | AN33: =SUM(AO33/19600) -> 0.84285714 | AO33: =SUM(AA33+AC33+AE33+AG33+AI33+AK33+AM33) -> 16520 | AQ33: =SUM(AR33/92970) -> 0.76321186 | AR33: =SUM(AO33+Y33) -> 70955.806 | AS33: =SUM(AR33-AR32-AT33) -> 0 | AV33: =IF(AT33>0,AU33,AV32) -> 0.535 | AW33: =-SUM('B5'!AI32) -> 0 | AX33: =-SUM(AW33-AS33) -> 0 | AY33: =SUM(AX33+AW33) -> 0 | AZ33: =ELEC!A30 -> 0 | BA33: ='General information '!D33 -> 0 | BB33: =SUM('General information '!E33) -> 0 | BC33: =IF(AR32>=AR33,0,1) -> 0 | BD33: 19222 | BE33: =(305/1185)*ELEC!Q31 -> 0 | BG33: =#REF!-BE33 -> #REF!
A34: =ELEC!C31 -> 44072 | B34: ='B5'!B33 -> 230 | C34: =B34*$B$4 -> 4948.7097 | D34: =SUM(B34) -> 230 | E34: =D34*$B$4 -> 4948.7097 | F34: =SUM(D34) -> 230 | G34: =F34*$B$4 -> 4948.7097 | H34: =SUM(F34) -> 230 | I34: =H34*$B$4 -> 4948.7097 | J34: =SUM(H34) -> 230 | K34: =J34*$B$4 -> 4948.7097 | L34: =SUM(J34) -> 230 | M34: =L34*$B$4 -> 4948.7097 | N34: =SUM(L34) -> 230 | O34: =N34*$B$4 -> 4948.7097 | P34: =SUM(N34) -> 230 | Q34: =P34*$B$4 -> 4948.7097 | R34: =SUM(P34) -> 230 | S34: =R34*$B$4 -> 4948.7097 | T34: =SUM(R34) -> 230 | U34: =T34*$B$4 -> 4948.7097 | V34: =SUM(T34) -> 230 | W34: =V34*$B$4 -> 4948.7097 | X34: =SUM(Y34/73370) -> 0.74193548 | Y34: =SUM(C34+E34+G34+I34+K34+M34+O34+Q34+S34+U34+W34) -> 54435.806 | Z34: ='B5'!C33 -> 236 | AA34: =SUM(Z34*$Z$4) -> 2360 | AB34: =SUM(Z34) -> 236 | AC34: =SUM(AB34*$Z$4) -> 2360 | AD34: =SUM(AB34) -> 236 | AE34: =SUM(AD34*$Z$4) -> 2360 | AF34: =SUM(AD34) -> 236 | AG34: =SUM(AF34*$Z$4) -> 2360 | AH34: =SUM(AF34) -> 236 | AI34: =SUM(AH34*$Z$4) -> 2360 | AJ34: =SUM(AH34) -> 236 | AK34: =SUM(AJ34*$Z$4) -> 2360 | AL34: =SUM(AJ34) -> 236 | AM34: =SUM(AL34*$Z$4) -> 2360 | AN34: =SUM(AO34/19600) -> 0.84285714 | AO34: =SUM(AA34+AC34+AE34+AG34+AI34+AK34+AM34) -> 16520 | AQ34: =SUM(AR34/92970) -> 0.76321186 | AR34: =SUM(AO34+Y34) -> 70955.806 | AS34: =SUM(AR34-AR33-AT34) -> 0 | AV34: =IF(AT34>0,AU34,AV33) -> 0.535 | AW34: =-SUM('B5'!AI33) -> 0 | AX34: =-SUM(AW34-AS34) -> 0 | AY34: =SUM(AX34+AW34) -> 0 | AZ34: =ELEC!A31 -> 0 | BA34: ='General information '!D34 -> 0 | BB34: =SUM('General information '!E34) -> 0 | BC34: =IF(AR33>=AR34,0,1) -> 0 | BD34: 19222 | BE34: =(305/1185)*ELEC!#REF! -> #REF! | BG34: =#REF!-BE34 -> #REF!
A35: =ELEC!C32 -> 44073 | B35: ='B5'!B34 -> 230 | C35: =B35*$B$4 -> 4948.7097 | D35: =SUM(B35) -> 230 | E35: =D35*$B$4 -> 4948.7097 | F35: =SUM(D35) -> 230 | G35: =F35*$B$4 -> 4948.7097 | H35: =SUM(F35) -> 230 | I35: =H35*$B$4 -> 4948.7097 | J35: =SUM(H35) -> 230 | K35: =J35*$B$4 -> 4948.7097 | L35: =SUM(J35) -> 230 | M35: =L35*$B$4 -> 4948.7097 | N35: =SUM(L35) -> 230 | O35: =N35*$B$4 -> 4948.7097 | P35: =SUM(N35) -> 230 | Q35: =P35*$B$4 -> 4948.7097 | R35: =SUM(P35) -> 230 | S35: =R35*$B$4 -> 4948.7097 | T35: =SUM(R35) -> 230 | U35: =T35*$B$4 -> 4948.7097 | V35: =SUM(T35) -> 230 | W35: =V35*$B$4 -> 4948.7097 | X35: =SUM(Y35/73370) -> 0.74193548 | Y35: =SUM(C35+E35+G35+I35+K35+M35+O35+Q35+S35+U35+W35) -> 54435.806 | Z35: ='B5'!C34 -> 236 | AA35: =SUM(Z35*$Z$4) -> 2360 | AB35: =SUM(Z35) -> 236 | AC35: =SUM(AB35*$Z$4) -> 2360 | AD35: =SUM(AB35) -> 236 | AE35: =SUM(AD35*$Z$4) -> 2360 | AF35: =SUM(AD35) -> 236 | AG35: =SUM(AF35*$Z$4) -> 2360 | AH35: =SUM(AF35) -> 236 | AI35: =SUM(AH35*$Z$4) -> 2360 | AJ35: =SUM(AH35) -> 236 | AK35: =SUM(AJ35*$Z$4) -> 2360 | AL35: =SUM(AJ35) -> 236 | AM35: =SUM(AL35*$Z$4) -> 2360 | AN35: =SUM(AO35/19600) -> 0.84285714 | AO35: =SUM(AA35+AC35+AE35+AG35+AI35+AK35+AM35) -> 16520 | AQ35: =SUM(AR35/92970) -> 0.76321186 | AR35: =SUM(AO35+Y35) -> 70955.806 | AS35: =SUM(AR35-AR34-AT35) -> 0 | AV35: =IF(AT35>0,AU35,AV34) -> 0.535 | AW35: =-SUM('B5'!AI34) -> 0 | AX35: =-SUM(AW35-AS35) -> 0 | AY35: =SUM(AX35+AW35) -> 0 | AZ35: =ELEC!A32 -> 0 | BA35: ='General information '!D35 -> 0 | BB35: =SUM('General information '!E35) -> 0 | BC35: =IF(AR34>=AR35,0,1) -> 0 | BD35: 19222 | BE35: =(305/1185)*ELEC!#REF! -> #REF! | BG35: =#REF!-BE35 -> #REF!
A36: =ELEC!C33 -> 44074 | B36: ='B5'!B35 -> 230 | C36: =B36*$B$4 -> 4948.7097 | D36: =SUM(B36) -> 230 | E36: =D36*$B$4 -> 4948.7097 | F36: =SUM(D36) -> 230 | G36: =F36*$B$4 -> 4948.7097 | H36: =SUM(F36) -> 230 | I36: =H36*$B$4 -> 4948.7097 | J36: =SUM(H36) -> 230 | K36: =J36*$B$4 -> 4948.7097 | L36: =SUM(J36) -> 230 | M36: =L36*$B$4 -> 4948.7097 | N36: =SUM(L36) -> 230 | O36: =N36*$B$4 -> 4948.7097 | P36: =SUM(N36) -> 230 | Q36: =P36*$B$4 -> 4948.7097 | R36: =SUM(P36) -> 230 | S36: =R36*$B$4 -> 4948.7097 | T36: =SUM(R36) -> 230 | U36: =T36*$B$4 -> 4948.7097 | V36: =SUM(T36) -> 230 | W36: =V36*$B$4 -> 4948.7097 | X36: =SUM(Y36/73370) -> 0.74193548 | Y36: =SUM(C36+E36+G36+I36+K36+M36+O36+Q36+S36+U36+W36) -> 54435.806 | Z36: ='B5'!C35 -> 236 | AA36: =SUM(Z36*$Z$4) -> 2360 | AB36: =SUM(Z36) -> 236 | AC36: =SUM(AB36*$Z$4) -> 2360 | AD36: =SUM(AB36) -> 236 | AE36: =SUM(AD36*$Z$4) -> 2360 | AF36: =SUM(AD36) -> 236 | AG36: =SUM(AF36*$Z$4) -> 2360 | AH36: =SUM(AF36) -> 236 | AI36: =SUM(AH36*$Z$4) -> 2360 | AJ36: =SUM(AH36) -> 236 | AK36: =SUM(AJ36*$Z$4) -> 2360 | AL36: =SUM(AJ36) -> 236 | AM36: =SUM(AL36*$Z$4) -> 2360 | AN36: =SUM(AO36/19600) -> 0.84285714 | AO36: =SUM(AA36+AC36+AE36+AG36+AI36+AK36+AM36) -> 16520 | AQ36: =SUM(AR36/92970) -> 0.76321186 | AR36: =SUM(AO36+Y36) -> 70955.806 | AS36: =SUM(AR36-AR35-AT36) -> 0 | AV36: =IF(AT36>0,AU36,AV35) -> 0.535 | AW36: =-SUM('B5'!AI35) -> 0 | AX36: =-SUM(AW36-AS36) -> 0 | AY36: =SUM(AX36+AW36) -> 0 | AZ36: =ELEC!A33 -> 0 | BA36: ='General information '!D36 -> 0 | BB36: =SUM('General information '!E36) -> 0 | BC36: =IF(AR35>=AR36,0,1) -> 0 | BD36: 19222 | BE36: =(305/1185)*ELEC!#REF! -> #REF! | BG36: =#REF!-BE36 -> #REF!
AR37: NB delivery | AS37: =COUNT(AT6:AT35) -> 2 | AT37: =SUM(AT6:AT35) -> 29740 | AU37: =SUM(AU6:AU35)/AS37 -> 0.5375 | AX37: =SUM(AX6:AX35) -> -23986.671 | AY37: =SUM(AY6:AY35) -> -25989.871
AT38: =+AT37*AU37 -> 15985.25
AS40: =SUM(AS6:AS35)/'EDl log'!A37 -> -1443.8817

Sheet GEN
B1: GEN1 | C1: RUN HR | D1: Fuel Counter Index | E1: Cons /day | F1: Diesel L/H | H1: next service | I1: ALARM | J1: GEN2 | K1: RUN HR | L1: Fuel Counter Index | M1: Cons /day | N1: Diesel L/H | P1: next service | Q1: ALARM | R1: GEN3 | S1: RUN HR | T1: Fuel Counter Index | U1: Cons /day | V1: Diesel L/H | X1: next service | Y1: ALARM | Z1: RH total | AA1: Gen Con /day | AB1: Total Deisel Cons/day | AC1: H /L | AD1: TOAL KW GEN | AI1: fuel Consuption | AK1: AVG KW/h
A2: =ELEC!C2 -> 44043 | B2: =[1]GEN!B33 -> 8997 | C2: =[1]GEN!C33 -> 9 | D2: =[1]GEN!D33 -> 202059 | E2: =[1]GEN!E33 -> 2345 | F2: =[1]GEN!F33 -> 260.55556 | G2: =[1]GEN!G33 -> 0 | H2: =[1]GEN!H33 -> 9100 | I2: =[1]GEN!I33 -> ok | ... AK2: =[1]GEN!AK33 -> 178.1889
A3: =ELEC!C3 -> 44044 | B3: 9005 | C3: =B3-B2 -> 8 | D3: 203305 | E3: =SUM(D3-D2) -> 1246 | F3: =IF(C3>0,E3/C3,0) -> 155.75 | G3: =[3]GEN!G32 -> 0 | H3: =H2 -> 9100 | I3: =IF(B3-H3<=0,"ok","oil change") -> ok | J3: =J2 -> 10698 | K3: =J3-J2 -> 0 | L3: =L2 -> 238500 | M3: =SUM(L3-L2) -> 0 | N3: =IF(K3>0,M3/K3,0) -> 0 | O3: =[3]GEN!O32 -> 0 | P3: =P2 -> 10873 | Q3: =IF(J3-P3<=0,"ok","oil change") -> ok | R3: 11612 | S3: =R3-R2 -> 17 | T3: 336958 | U3: =SUM(T3-T2) -> 3442 | V3: =IF(S3>0,U3/S3,0) -> 202.47059 | W3: =[3]GEN!W32 -> 0 | X3: =X2 -> 12249 | Y3: =IF(R3-X3<=0,"ok","oil change") -> ok | Z3: =C3+K3+S3 -> 25 | AA3: =U3+M3+E3 -> 4688 | AB3: =V3+N3+F3 -> 358.22059 | AC3: =IF(Z3>0,AA3/Z3,0) -> 187.52 | AD3: =ELEC!Q3 -> 17000 | AE3: =SUM(AD3/Z3) -> 680 | AF3: =SUM(AE3/1600) -> 0.425 | AG3: =SUM(360*AF3) -> 153 | AH3: =SUM(AC3-AG3) -> 34.52 | AI3: =AD3*AJ3 -> 4375.5274 | AJ3: =305/1185 -> 0.25738397 | AK3: =AI3/Z3 -> 175.0211
A4: =ELEC!C4 -> 44045 | B4: 9010 | C4: =B4-B3 -> 5 | D4: 204588 | E4: =SUM(D4-D3) -> 1283 | F4: =IF(C4>0,E4/C4,0) -> 256.6 | H4: =H3 -> 9100 | I4: =IF(B4-H4<=0,"ok","oil change") -> ok | J4: 10698 | K4: =J4-J3 -> 0 | L4: =L3 -> 238500 | M4: =SUM(L4-L3) -> 0 | N4: =IF(K4>0,M4/K4,0) -> 0 | P4: =P3 -> 10873 | Q4: =IF(J4-P4<=0,"ok","oil change") -> ok | R4: 11616 | S4: =R4-R3 -> 4 | T4: 337790 | U4: =SUM(T4-T3) -> 832 | V4: =IF(S4>0,U4/S4,0) -> 208 | X4: =X3 -> 12249 | Y4: =IF(R4-X4<=0,"ok","oil change") -> ok | Z4: =C4+K4+S4 -> 9 | AA4: =U4+M4+E4 -> 2115 | AB4: =V4+N4+F4 -> 464.6 | AC4: =IF(Z4>0,AA4/Z4,0) -> 235 | AD4: =ELEC!Q4 -> 10000 | AE4: =SUM(AD4/Z4) -> 1111.1111 | AF4: =SUM(AE4/1600) -> 0.69444444 | AG4: =SUM(360*AF4) -> 250 | AH4: =SUM(AC4-AG4) -> -15 | AI4: =AD4*AJ4 -> 2573.8397 | AJ4: =305/1185 -> 0.25738397 | AK4: =AI4/Z4 -> 285.98218
A5: =ELEC!C5 -> 44046 | B5: 9025 | C5: =B5-B4 -> 15 | D5: 206848 | E5: =SUM(D5-D4) -> 2260 | F5: =IF(C5>0,E5/C5,0) -> 150.66667 | H5: =H4 -> 9100 | I5: =IF(B5-H5<=0,"ok","oil change") -> ok | J5: 10698 | K5: =J5-J4 -> 0 | L5: =L4 -> 238500 | M5: =SUM(L5-L4) -> 0 | N5: =IF(K5>0,M5/K5,0) -> 0 | P5: =P4 -> 10873 | Q5: =IF(J5-P5<=0,"ok","oil change") -> ok | R5: 11620 | S5: =R5-R4 -> 4 | T5: 338550 | U5: =SUM(T5-T4) -> 760 | V5: =IF(S5>0,U5/S5,0) -> 190 | X5: =X4 -> 12249 | Y5: =IF(R5-X5<=0,"ok","oil change") -> ok | Z5: =C5+K5+S5 -> 19 | AA5: =U5+M5+E5 -> 3020 | AB5: =V5+N5+F5 -> 340.66667 | AC5: =IF(Z5>0,AA5/Z5,0) -> 158.94737 | AD5: =ELEC!Q5 -> 15000 | AE5: =SUM(AD5/Z5) -> 789.47368 | AF5: =SUM(AE5/1600) -> 0.49342105 | AG5: =SUM(320*AF5) -> 157.89474 | AH5: =SUM(AC5-AG5) -> 1.0526316 | AI5: =AD5*AJ5 -> 3860.7595 | AJ5: =305/1185 -> 0.25738397 | AK5: =AI5/Z5 -> 203.19787
A6: =ELEC!C6 -> 44047 | B6: 9038 | C6: =B6-B5 -> 13 | D6: 208538 | E6: =SUM(D6-D5) -> 1690 | F6: =IF(C6>0,E6/C6,0) -> 130 | H6: =H5 -> 9100 | I6: =IF(B6-H6<=0,"ok","oil change") -> ok | J6: =J5 -> 10698 | K6: =J6-J5 -> 0 | L6: =L5 -> 238500 | M6: =SUM(L6-L5) -> 0 | N6: =IF(K6>0,M6/K6,0) -> 0 | P6: =P5 -> 10873 | Q6: =IF(J6-P6<=0,"ok","oil change") -> ok | R6: 11627 | S6: =R6-R5 -> 7 | T6: 339880 | U6: =SUM(T6-T5) -> 1330 | V6: =IF(S6>0,U6/S6,0) -> 190 | X6: =X5 -> 12249 | Y6: =IF(R6-X6<=0,"ok","oil change") -> ok | Z6: =C6+K6+S6 -> 20 | AA6: =U6+M6+E6 -> 3020 | AB6: =V6+N6+F6 -> 320 | AC6: =IF(Z6>0,AA6/Z6,0) -> 151 | AD6: =ELEC!Q6 -> 0 | AE6: =SUM(AD6/Z6) -> 0 | AF6: =SUM(AE6/1600) -> 0 | AG6: =SUM(320*AF6) -> 0 | AH6: =SUM(AC6-AG6) -> 151 | AI6: =AD6*AJ6 -> 0 | AJ6: =305/1185 -> 0.25738397 | AK6: =AI6/Z6 -> 0
A7: =ELEC!C7 -> 44048 | B7: 9046 | C7: =B7-B6 -> 8 | D7: 210869 | E7: =SUM(D7-D6) -> 2331 | F7: =IF(C7>0,E7/C7,0) -> 291.375 | H7: =H6 -> 9100 | I7: =IF(B7-H7<=0,"ok","oil change") -> ok | J7: 10698 | K7: =J7-J6 -> 0 | L7: =L6 -> 238500 | M7: =SUM(L7-L6) -> 0 | N7: =IF(K7>0,M7/K7,0) -> 0 | P7: =P6 -> 10873 | Q7: =IF(J7-P7<=0,"ok","oil change") -> ok | R7: 11627 | S7: =R7-R6 -> 0 | T7: 340042 | U7: =SUM(T7-T6) -> 162 | V7: =IF(S7>0,U7/S7,0) -> 0 | X7: =X6 -> 12249 | Y7: =IF(R7-X7<=0,"ok","oil change") -> ok | Z7: =C7+K7+S7 -> 8 | AA7: =U7+M7+E7 -> 2493 | AB7: =V7+N7+F7 -> 291.375 | AC7: =IF(Z7>0,AA7/Z7,0) -> 311.625 | AD7: =ELEC!Q7 -> 14000 | AE7: =SUM(AD7/Z7) -> 1750 | AF7: =SUM(AE7/1600) -> 1.09375 | AH7: =SUM(AC7-AG7) -> #VALUE! | AI7: =AD7*AJ7 -> 3603.3755 | AJ7: =305/1185 -> 0.25738397 | AK7: =AI7/Z7 -> 450.42194
A8: =ELEC!C8 -> 44049 | B8: 9048 | C8: =B8-B7 -> 2 | D8: 211390 | E8: =SUM(D8-D7) -> 521 | F8: =IF(C8>0,E8/C8,0) -> 260.5 | H8: =H7 -> 9100 | I8: =IF(B8-H8<=0,"ok","oil change") -> ok | J8: =J7 -> 10698 | K8: =J8-J7 -> 0 | L8: =L7 -> 238500 | M8: =SUM(L8-L7) -> 0 | N8: =IF(K8>0,M8/K8,0) -> 0 | P8: =P7 -> 10873 | Q8: =IF(J8-P8<=0,"ok","oil change") -> ok | R8: =R7 -> 11627 | S8: =R8-R7 -> 0 | T8: =T7 -> 340042 | U8: =SUM(T8-T7) -> 0 | V8: =IF(S8>0,U8/S8,0) -> 0 | X8: =X7 -> 12249 | Y8: =IF(R8-X8<=0,"ok","oil change") -> ok | Z8: =C8+K8+S8 -> 2 | AA8: =U8+M8+E8 -> 521 | AB8: =V8+N8+F8 -> 260.5 | AC8: =IF(Z8>0,AA8/Z8,0) -> 260.5 | AD8: =ELEC!Q8 -> 5000 | AE8: =SUM(AD8/Z8) -> 2500 | AF8: =SUM(AE8/1600) -> 1.5625 | AG8: =SUM(320*AF8) -> 500 | AH8: =SUM(AC8-AG8) -> -239.5 | AI8: =AD8*AJ8 -> 1286.9198 | AJ8: =305/1185 -> 0.25738397 | AK8: =AI8/Z8 -> 643.45992
A9: =ELEC!C9 -> 44050 | B9: 9052 | C9: =B9-B8 -> 4 | D9: 212052 | E9: =SUM(D9-D8) -> 662 | F9: =IF(C9>0,E9/C9,0) -> 165.5 | H9: =H8 -> 9100 | I9: =IF(B9-H9<=0,"ok","oil change") -> ok | J9: 10698 | K9: =J9-J8 -> 0 | L9: =L8 -> 238500 | M9: =SUM(L9-L8) -> 0 | N9: =IF(K9>0,M9/K9,0) -> 0 | P9: =P8 -> 10873 | Q9: =IF(J9-P9<=0,"ok","oil change") -> ok | R9: 11627 | S9: =R9-R8 -> 0 | T9: 340042 | U9: =SUM(T9-T8) -> 0 | V9: =IF(S9>0,U9/S9,0) -> 0 | X9: =X8 -> 12249 | Y9: =IF(R9-X9<=0,"ok","oil change") -> ok | Z9: =C9+K9+S9 -> 4 | AA9: =U9+M9+E9 -> 662 | AB9: =V9+N9+F9 -> 165.5 | AC9: =IF(Z9>0,AA9/Z9,0) -> 165.5 | AD9: =ELEC!Q9 -> 1000 | AE9: =SUM(AD9/Z9) -> 250 | AF9: =SUM(AE9/1600) -> 0.15625 | AG9: =SUM(320*AF9) -> 50 | AH9: =SUM(AC9-AG9) -> 115.5 | AI9: =AD9*AJ9 -> 257.38397 | AJ9: 0.25738397 | AK9: =IF(Z9>0,AI9/Z9,0) -> 64.345992
A10: =ELEC!C10 -> 44051 | B10: 9055 | C10: =B10-B9 -> 3 | D10: 212879 | E10: =SUM(D10-D9) -> 827 | F10: =IF(C10>0,E10/C10,0) -> 275.66667 | H10: =H9 -> 9100 | I10: =IF(B10-H10<=0,"ok","oil change") -> ok | J10: =J9 -> 10698 | K10: =J10-J9 -> 0 | L10: =L9 -> 238500 | M10: =SUM(L10-L9) -> 0 | N10: =IF(K10>0,M10/K10,0) -> 0 | P10: 10873 | Q10: =IF(J10-P10<=0,"ok","oil change") -> ok | R10: 11627 | S10: =R10-R9 -> 0 | T10: =T9 -> 340042 | U10: =SUM(T10-T9) -> 0 | V10: =IF(S10>0,U10/S10,0) -> 0 | X10: =X9 -> 12249 | Y10: =IF(R10-X10<=0,"ok","oil change") -> ok | Z10: =C10+K10+S10 -> 3 | AA10: =U10+M10+E10 -> 827 | AB10: =V10+N10+F10 -> 275.66667 | AC10: =IF(Z10>0,AA10/Z10,0) -> 275.66667 | AD10: =ELEC!Q10 -> 2000 | AE10: =SUM(AD10/Z10) -> 666.66667 | AF10: =SUM(AE10/1600) -> 0.41666667 | AG10: =SUM(320*AF10) -> 133.33333 | AH10: =SUM(AC10-AG10) -> 142.33333 | AI10: =AD10*AJ10 -> 514.76793 | AJ10: =305/1185 -> 0.25738397 | AK10: =IF(Z10>0,AI10/Z10,0) -> 171.58931
A11: =ELEC!C11 -> 44052 | B11: 9058 | C11: =B11-B10 -> 3 | D11: 213567 | E11: =SUM(D11-D10) -> 688 | F11: =IF(C11>0,E11/C11,0) -> 229.33333 | H11: =H10 -> 9100 | I11: =IF(B11-H11<=0,"ok","oil change") -> ok | J11: =J10 -> 10698 | K11: =J11-J10 -> 0 | L11: =L10 -> 238500 | M11: =SUM(L11-L10) -> 0 | N11: =IF(K11>0,M11/K11,0) -> 0 | P11: =P10 -> 10873 | Q11: =IF(J11-P11<=0,"ok","oil change") -> ok | R11: =R10 -> 11627 | S11: =R11-R10 -> 0 | T11: =T10 -> 340042 | U11: =SUM(T11-T10) -> 0 | V11: =IF(S11>0,U11/S11,0) -> 0 | X11: =X10 -> 12249 | Y11: =IF(R11-X11<=0,"ok","oil change") -> ok | Z11: =C11+K11+S11 -> 3 | AA11: =U11+M11+E11 -> 688 | AB11: =V11+N11+F11 -> 229.33333 | AC11: =IF(Z11>0,AA11/Z11,0) -> 229.33333 | AD11: =ELEC!Q11 -> 2000 | AE11: =SUM(AD11/Z11) -> 666.66667 | AF11: =SUM(AE11/1600) -> 0.41666667 | AG11: =SUM(320*AF11) -> 133.33333 | AH11: =SUM(AC11-AG11) -> 96 | AI11: =AD11*AJ11 -> 514.76793 | AJ11: =305/1185 -> 0.25738397 | AK11: =IF(Z11>0,AI11/Z11,0) -> 171.58931
A12: =ELEC!C12 -> 44053 | B12: 9061 | C12: =B12-B11 -> 3 | D12: 214264 | E12: =SUM(D12-D11) -> 697 | F12: =IF(C12>0,E12/C12,0) -> 232.33333 | H12: =H11 -> 9100 | I12: =IF(B12-H12<=0,"ok","oil change") -> ok | J12: =J11 -> 10698 | K12: =J12-J11 -> 0 | L12: =L11 -> 238500 | M12: =SUM(L12-L11) -> 0 | N12: =IF(K12>0,M12/K12,0) -> 0 | P12: =P11 -> 10873 | Q12: =IF(J12-P12<=0,"ok","oil change") -> ok | R12: =R11 -> 11627 | S12: =R12-R11 -> 0 | T12: =T11 -> 340042 | U12: =SUM(T12-T11) -> 0 | V12: =IF(S12>0,U12/S12,0) -> 0 | X12: =X11 -> 12249 | Y12: =IF(R12-X12<=0,"ok","oil change") -> ok | Z12: =C12+K12+S12 -> 3 | AA12: =U12+M12+E12 -> 697 | AB12: =V12+N12+F12 -> 232.33333 | AC12: =IF(Z12>0,AA12/Z12,0) -> 232.33333 | AD12: =ELEC!Q12 -> 1000 | AE12: =SUM(AD12/Z12) -> 333.33333 | AF12: =SUM(AE12/1600) -> 0.20833333 | AG12: =SUM(320*AF12) -> 66.666667 | AH12: =SUM(AC12-AG12) -> 165.66667 | AI12: =AD12*AJ12 -> 257.38397 | AJ12: =305/1185 -> 0.25738397 | AK12: =IF(Z12>0,AI12/Z12,0) -> 85.794655
A13: =ELEC!C13 -> 44054 | B13: 9064 | C13: =B13-B12 -> 3 | D13: 215063 | E13: =SUM(D13-D12) -> 799 | F13: =IF(C13>0,E13/C13,0) -> 266.33333 | H13: =H12 -> 9100 | I13: =IF(B13-H13<=0,"ok","oil change") -> ok | J13: =J12 -> 10698 | K13: =J13-J12 -> 0 | L13: =L12 -> 238500 | M13: =SUM(L13-L12) -> 0 | N13: =IF(K13>0,M13/K13,0) -> 0 | P13: =P12 -> 10873 | Q13: =IF(J13-P13<=0,"ok","oil change") -> ok | R13: 11627 | S13: =R13-R12 -> 0 | T13: 340045 | U13: =SUM(T13-T12) -> 3 | V13: =IF(S13>0,U13/S13,0) -> 0 | X13: =X12+180 -> 12429 | Y13: =IF(R13-X13<=0,"ok","oil change") -> ok | Z13: =C13+K13+S13 -> 3 | AA13: =U13+M13+E13 -> 802 | AB13: =V13+N13+F13 -> 266.33333 | AC13: =IF(Z13>0,AA13/Z13,0) -> 267.33333 | AD13: =ELEC!Q13 -> 2000 | AE13: =SUM(AD13/Z13) -> 666.66667 | AF13: =SUM(AE13/1600) -> 0.41666667 | AG13: =SUM(320*AF13) -> 133.33333 | AH13: =SUM(AC13-AG13) -> 134 | AI13: =AD13*AJ13 -> 514.76793 | AJ13: =305/1185 -> 0.25738397 | AK13: =IF(Z13>0,AI13/Z13,0) -> 171.58931
A14: =ELEC!C14 -> 44055 | B14: 9067 | C14: =B14-B13 -> 3 | D14: 215713 | E14: =SUM(D14-D13) -> 650 | F14: =IF(C14>0,E14/C14,0) -> 216.66667 | H14: =H13 -> 9100 | I14: =IF(B14-H14<=0,"ok","oil change") -> ok | J14: =J13 -> 10698 | K14: =J14-J13 -> 0 | L14: =L13 -> 238500 | M14: =SUM(L14-L13) -> 0 | N14: =IF(K14>0,M14/K14,0) -> 0 | P14: =P13 -> 10873 | Q14: =IF(J14-P14<=0,"ok","oil change") -> ok | R14: =R13 -> 11627 | S14: =R14-R13 -> 0 | T14: =T13 -> 340045 | U14: =SUM(T14-T13) -> 0 | V14: =IF(S14>0,U14/S14,0) -> 0 | X14: =X13 -> 12429 | Y14: =IF(R14-X14<=0,"ok","oil change") -> ok | Z14: =C14+K14+S14 -> 3 | AA14: =U14+M14+E14 -> 650 | AB14: =V14+N14+F14 -> 216.66667 | AC14: =IF(Z14>0,AA14/Z14,0) -> 216.66667 | AD14: =ELEC!Q14 -> 2000 | AE14: =SUM(AD14/Z14) -> 666.66667 | AF14: =SUM(AE14/1600) -> 0.41666667 | AG14: =SUM(320*AF14) -> 133.33333 | AH14: =SUM(AC14-AG14) -> 83.333333 | AI14: =AD14*AJ14 -> 514.76793 | AJ14: =305/1185 -> 0.25738397 | AK14: =IF(Z14>0,AI14/Z14,0) -> 171.58931
A15: =ELEC!C15 -> 44056 | B15: 9071 | C15: =B15-B14 -> 4 | D15: 216260 | E15: =SUM(D15-D14) -> 547 | F15: =IF(C15>0,E15/C15,0) -> 136.75 | H15: =H14 -> 9100 | I15: =IF(B15-H15<=0,"ok","oil change") -> ok | J15: =J14 -> 10698 | K15: =J15-J14 -> 0 | L15: =L14 -> 238500 | M15: =SUM(L15-L14) -> 0 | N15: =IF(K15>0,M15/K15,0) -> 0 | P15: =P14 -> 10873 | Q15: =IF(J15-P15<=0,"ok","oil change") -> ok | R15: 11629 | S15: =R15-R14 -> 2 | T15: 340575 | U15: =SUM(T15-T14) -> 530 | V15: =IF(S15>0,U15/S15,0) -> 265 | X15: =X14 -> 12429 | Y15: =IF(R15-X15<=0,"ok","oil change") -> ok | Z15: =C15+K15+S15 -> 6 | AA15: =U15+M15+E15 -> 1077 | AB15: =V15+N15+F15 -> 401.75 | AC15: =IF(Z15>0,AA15/Z15,0) -> 179.5 | AD15: =ELEC!Q15 -> 2000 | AE15: =SUM(AD15/Z15) -> 333.33333 | AF15: =SUM(AE15/1600) -> 0.20833333 | AG15: =SUM(320*AF15) -> 66.666667 | AH15: =SUM(AC15-AG15) -> 112.83333 | AI15: =AD15*AJ15 -> 514.76793 | AJ15: =305/1185 -> 0.25738397 | AK15: =IF(Z15>0,AI15/Z15,0) -> 85.794655
A16: =ELEC!C16 -> 44057 | B16: =B15 -> 9071 | C16: =B16-B15 -> 0 | D16: =D15 -> 216260 | E16: =SUM(D16-D15) -> 0 | F16: =IF(C16>0,E16/C16,0) -> 0 | H16: =H15 -> 9100 | I16: =IF(B16-H16<=0,"ok","oil change") -> ok | J16: =J15 -> 10698 | K16: =J16-J15 -> 0 | L16: =L15 -> 238500 | M16: =SUM(L16-L15) -> 0 | N16: =IF(K16>0,M16/K16,0) -> 0 | P16: =P15 -> 10873 | Q16: =IF(J16-P16<=0,"ok","oil change") -> ok | R16: 11635 | S16: =R16-R15 -> 6 | T16: 341869 | U16: =SUM(T16-T15) -> 1294 | V16: =IF(S16>0,U16/S16,0) -> 215.66667 | X16: =X15 -> 12429 | Y16: =IF(R16-X16<=0,"ok","oil change") -> ok | Z16: =C16+K16+S16 -> 6 | AA16: =U16+M16+E16 -> 1294 | AB16: =V16+N16+F16 -> 215.66667 | AC16: =IF(Z16>0,AA16/Z16,0) -> 215.66667 | AD16: =ELEC!Q16 -> 4000 | AE16: =SUM(AD16/Z16) -> 666.66667 | AF16: =SUM(AE16/1600) -> 0.41666667 | AG16: =SUM(320*AF16) -> 133.33333 | AH16: =SUM(AC16-AG16) -> 82.333333 | AI16: =AD16*AJ16 -> 1029.5359 | AJ16: =305/1185 -> 0.25738397 | AK16: =IF(Z16>0,AI16/Z16,0) -> 171.58931
A17: =ELEC!C17 -> 44058 | B17: =B16 -> 9071 | C17: =B17-B16 -> 0 | D17: =D16 -> 216260 | E17: =SUM(D17-D16) -> 0 | F17: =IF(C17>0,E17/C17,0) -> 0 | H17: =H16 -> 9100 | I17: =IF(B17-H17<=0,"ok","oil change") -> ok | J17: =J16 -> 10698 | K17: =J17-J16 -> 0 | L17: =L16 -> 238500 | M17: =SUM(L17-L16) -> 0 | N17: =IF(K17>0,M17/K17,0) -> 0 | P17: =P16 -> 10873 | Q17: =IF(J17-P17<=0,"ok","oil change") -> ok | R17: 11640 | S17: =R17-R16 -> 5 | T17: 342996 | U17: =SUM(T17-T16) -> 1127 | V17: =IF(S17>0,U17/S17,0) -> 225.4 | X17: =X16 -> 12429 | Y17: =IF(R17-X17<=0,"ok","oil change") -> ok | Z17: =C17+K17+S17 -> 5 | AA17: =U17+M17+E17 -> 1127 | AB17: =V17+N17+F17 -> 225.4 | AC17: =IF(Z17>0,AA17/Z17,0) -> 225.4 | AD17: =ELEC!Q17 -> 2000 | AE17: =SUM(AD17/Z17) -> 400 | AF17: =SUM(AE17/1600) -> 0.25 | AG17: =SUM(320*AF17) -> 80 | AH17: =SUM(AC17-AG17) -> 145.4 | AI17: =AD17*AJ17 -> 514.76793 | AJ17: =305/1185 -> 0.25738397 | AK17: =IF(Z17>0,AI17/Z17,0) -> 102.95359
A18: =ELEC!C18 -> 44059 | B18: 9074 | C18: =B18-B17 -> 3 | D18: 217025 | E18: =SUM(D18-D17) -> 765 | F18: =IF(C18>0,E18/C18,0) -> 255 | H18: =H17 -> 9100 | I18: =IF(B18-H18<=0,"ok","oil change") -> ok | J18: =J17 -> 10698 | K18: =J18-J17 -> 0 | L18: =L17 -> 238500 | M18: =SUM(L18-L17) -> 0 | N18: =IF(K18>0,M18/K18,0) -> 0 | P18: =P17 -> 10873 | Q18: =IF(J18-P14<=0,"ok","oil change") -> ok | R18: =R17 -> 11640 | S18: =R18-R17 -> 0 | T18: =T17 -> 342996 | U18: =SUM(T18-T17) -> 0 | V18: =IF(S18>0,U18/S18,0) -> 0 | X18: =X17 -> 12429 | Y18: =IF(R18-X18<=0,"ok","oil change") -> ok | Z18: =C18+K18+S18 -> 3 | AA18: =U18+M18+E18 -> 765 | AB18: =V18+N18+F18 -> 255 | AC18: =IF(Z18>0,AA18/Z18,0) -> 255 | AD18: =ELEC!Q18 -> 2000 | AE18: =SUM(AD18/Z18) -> 666.66667 | AF18: =SUM(AE18/1600) -> 0.41666667 | AG18: =SUM(320*AF18) -> 133.33333 | AH18: =SUM(AC18-AG18) -> 121.66667 | AI18: =AD18*AJ18 -> 514.76793 | AJ18: =305/1185 -> 0.25738397 | AK18: =IF(Z18>0,AI18/Z18,0) -> 171.58931
A19: =ELEC!C19 -> 44060 | B19: 9077 | C19: =B19-B18 -> 3 | D19: 217619 | E19: =SUM(D19-D18) -> 594 | F19: =IF(C19>0,E19/C19,0) -> 198 | H19: =H18 -> 9100 | I19: =IF(B19-H19<=0,"ok","oil change") -> ok | J19: =J18 -> 10698 | K19: =J19-J18 -> 0 | L19: =L18 -> 238500 | M19: =SUM(L19-L18) -> 0 | N19: =IF(K19>0,M19/K19,0) -> 0 | P19: =P18 -> 10873 | Q19: =IF(J19-P19<=0,"ok","oil change") -> ok | R19: =R18 -> 11640 | S19: =R19-R18 -> 0 | T19: =T18 -> 342996 | U19: =SUM(T19-T18) -> 0 | V19: =IF(S19>0,U19/S19,0) -> 0 | X19: =X18 -> 12429 | Y19: =IF(R19-X19<=0,"ok","oil change") -> ok | Z19: =C19+K19+S19 -> 3 | AA19: =U19+M19+E19 -> 594 | AB19: =V19+N19+F19 -> 198 | AC19: =IF(Z19>0,AA19/Z19,0) -> 198 | AD19: =ELEC!Q19 -> 1000 | AE19: =SUM(AD19/Z19) -> 333.33333 | AF19: =SUM(AE19/1600) -> 0.20833333 | AG19: =SUM(320*AF19) -> 66.666667 | AH19: =SUM(AC19-AG19) -> 131.33333 | AI19: =AD19*AJ19 -> 257.38397 | AJ19: =305/1185 -> 0.25738397 | AK19: =IF(Z19>0,AI19/Z19,0) -> 85.794655
A20: =ELEC!C20 -> 44061 | B20: 9079 | C20: =B20-B19 -> 2 | D20: 218240 | E20: =SUM(D20-D19) -> 621 | F20: =IF(C20>0,E20/C20,0) -> 310.5 | H20: =H19 -> 9100 | I20: =IF(B20-H20<=0,"ok","oil change") -> ok | J20: =J19 -> 10698 | K20: =J20-J19 -> 0 | L20: =L19 -> 238500 | M20: =SUM(L20-L19) -> 0 | N20: =IF(K20>0,M20/K20,0) -> 0 | P20: =P19 -> 10873 | Q20: =IF(J20-P20<=0,"ok","oil change") -> ok | R20: =R19 -> 11640 | S20: =R20-R19 -> 0 | T20: =T19 -> 342996 | U20: =SUM(T20-T19) -> 0 | V20: =IF(S20>0,U20/S20,0) -> 0 | X20: =X19 -> 12429 | Y20: =IF(R20-X20<=0,"ok","oil change") -> ok | Z20: =C20+K20+S20 -> 2 | AA20: =U20+M20+E20 -> 621 | AB20: =V20+N20+F20 -> 310.5 | AC20: =IF(Z20>0,AA20/Z20,0) -> 310.5 | AD20: =ELEC!Q20 -> 1000 | AE20: =SUM(AD20/Z20) -> 500 | AF20: =SUM(AE20/1600) -> 0.3125 | AG20: =SUM(320*AF20) -> 100 | AH20: =SUM(AC20-AG20) -> 210.5 | AI20: =AD20*AJ20 -> 257.38397 | AJ20: =305/1185 -> 0.25738397 | AK20: =IF(Z20>0,AI20/Z20,0) -> 128.69198
A21: =ELEC!C21 -> 44062 | B21: =B20 -> 9079 | C21: =B21-B20 -> 0 | D21: =D20 -> 218240 | E21: =SUM(D21-D20) -> 0 | F21: =IF(C21>0,E21/C21,0) -> 0 | H21: =H20 -> 9100 | I21: =IF(B21-H21<=0,"ok","oil change") -> ok | J21: =J20 -> 10698 | K21: =J21-J20 -> 0 | L21: =L20 -> 238500 | M21: =SUM(L21-L20) -> 0 | N21: =IF(K21>0,M21/K21,0) -> 0 | P21: =P20 -> 10873 | Q21: =IF(J21-P21<=0,"ok","oil change") -> ok | R21: =R20 -> 11640 | S21: =R21-R20 -> 0 | T21: =T20 -> 342996 | U21: =SUM(T21-T20) -> 0 | V21: =IF(S21>0,U21/S21,0) -> 0 | X21: =X20 -> 12429 | Y21: =Y20 -> ok | Z21: =C21+K21+S21 -> 0 | AA21: =U21+M21+E21 -> 0 | AB21: =V21+N21+F21 -> 0 | AC21: =IF(Z21>0,AA21/Z21,0) -> 0 | AD21: =ELEC!Q21 -> 0 | AE21: =SUM(AD21/Z21) -> #DIV/0! | AF21: =SUM(AE21/1600) -> #DIV/0! | AG21: =SUM(320*AF21) -> #DIV/0! | AH21: =SUM(AC21-AG21) -> #DIV/0! | AI21: =AD21*AJ21 -> 0 | AJ21: =305/1185 -> 0.25738397 | AK21: =IF(Z21>0,AI21/Z21,0) -> 0
A22: =ELEC!C22 -> 44063 | B22: =B21 -> 9079 | C22: =B22-B21 -> 0 | D22: =D21 -> 218240 | E22: =SUM(D22-D21) -> 0 | F22: =IF(C22>0,E22/C22,0) -> 0 | H22: =H21 -> 9100 | I22: =IF(B22-H22<=0,"ok","oil change") -> ok | J22: =J21 -> 10698 | K22: =J22-J21 -> 0 | L22: =L21 -> 238500 | M22: =SUM(L22-L21) -> 0 | N22: =IF(K22>0,M22/K22,0) -> 0 | P22: =P21 -> 10873 | Q22: =IF(J22-P22<=0,"ok","oil change") -> ok | R22: =R21 -> 11640 | S22: =R22-R21 -> 0 | T22: =T21 -> 342996 | U22: =SUM(T22-T21) -> 0 | V22: =IF(S22>0,U22/S22,0) -> 0 | X22: =X21 -> 12429 | Y22: =IF(R22-X22<=0,"ok","oil change") -> ok | Z22: =C22+K22+S22 -> 0 | AA22: =U22+M22+E22 -> 0 | AB22: =V22+N22+F22 -> 0 | AC22: =IF(Z22>0,AA22/Z22,0) -> 0 | AD22: =ELEC!Q22 -> 0 | AE22: =SUM(AD22/Z22) -> #DIV/0! | AF22: =SUM(AE22/1600) -> #DIV/0! | AG22: =SUM(320*AF22) -> #DIV/0! | AH22: =SUM(AC22-AG22) -> #DIV/0! | AI22: =AD22*AJ22 -> 0 | AJ22: =305/1185 -> 0.25738397 | AK22: =IF(Z22>0,AI22/Z22,0) -> 0
A23: =ELEC!C23 -> 44064 | B23: =B22 -> 9079 | C23: =B23-B22 -> 0 | D23: =D22 -> 218240 | E23: =SUM(D23-D22) -> 0 | F23: =IF(C23>0,E23/C23,0) -> 0 | H23: =H22 -> 9100 | I23: =IF(B23-H23<=0,"ok","oil change") -> ok | J23: =J22 -> 10698 | K23: =J23-J22 -> 0 | L23: =L22 -> 238500 | M23: =SUM(L23-L22) -> 0 | N23: =IF(K23>0,M23/K23,0) -> 0 | P23: =P22 -> 10873 | Q23: =IF(J23-P23<=0,"ok","oil change") -> ok | R23: =R22 -> 11640 | S23: =R23-R22 -> 0 | T23: =T22 -> 342996 | U23: =SUM(T23-T22) -> 0 | V23: =IF(S23>0,U23/S23,0) -> 0 | X23: =X22 -> 12429 | Y23: =IF(R23-X23<=0,"ok","oil change") -> ok | Z23: =C23+K23+S23 -> 0 | AA23: =U23+M23+E23 -> 0 | AB23: =V23+N23+F23 -> 0 | AC23: =IF(Z23>0,AA23/Z23,0) -> 0 | AD23: =ELEC!Q23 -> 0 | AE23: =SUM(AD23/Z23) -> #DIV/0! | AF23: =SUM(AE23/1600) -> #DIV/0! | AG23: =SUM(320*AF23) -> #DIV/0! | AH23: =SUM(AC23-AG23) -> #DIV/0! | AI23: =AD23*AJ23 -> 0 | AJ23: =305/1185 -> 0.25738397 | AK23: =IF(Z23>0,AI23/Z23,0) -> 0
A24: =ELEC!C24 -> 44065 | B24: =B23 -> 9079 | C24: =B24-B23 -> 0 | D24: =D23 -> 218240 | E24: =SUM(D24-D23) -> 0 | F24: =IF(C24>0,E24/C24,0) -> 0 | H24: =8920+180 -> 9100 | I24: =IF(B24-H24<=0,"ok","oil change") -> ok | J24: =J23 -> 10698 | K24: =J24-J23 -> 0 | L24: =L23 -> 238500 | M24: =SUM(L24-L23) -> 0 | N24: =IF(K24>0,M24/K24,0) -> 0 | P24: =P23 -> 10873 | Q24: =IF(J24-P24<=0,"ok","oil change") -> ok | R24: =R23 -> 11640 | S24: =R24-R23 -> 0 | T24: =T23 -> 342996 | U24: =SUM(T24-T23) -> 0 | V24: =IF(S24>0,U24/S24,0) -> 0 | X24: =X23 -> 12429 | Y24: =IF(R24-X24<=0,"ok","oil change") -> ok | Z24: =C24+K24+S24 -> 0 | AA24: =U24+M24+E24 -> 0 | AB24: =V24+N24+F24 -> 0 | AC24: =IF(Z24>0,AA24/Z24,0) -> 0 | AD24: =ELEC!Q24 -> 0 | AE24: =SUM(AD24/Z24) -> #DIV/0! | AF24: =SUM(AE24/1600) -> #DIV/0! | AG24: =SUM(320*AF24) -> #DIV/0! | AH24: =SUM(AC24-AG24) -> #DIV/0! | AI24: =AD24*AJ24 -> 0 | AJ24: =305/1185 -> 0.25738397 | AK24: =IF(Z24>0,AI24/Z24,0) -> 0
A25: =ELEC!C25 -> 44066 | B25: =B24 -> 9079 | C25: =B25-B24 -> 0 | D25: =D24 -> 218240 | E25: =SUM(D25-D24) -> 0 | F25: =IF(C25>0,E25/C25,0) -> 0 | H25: =8920+180 -> 9100 | I25: =IF(B25-H25<=0,"ok","oil change") -> ok | J25: =J24 -> 10698 | K25: =J25-J24 -> 0 | L25: =L24 -> 238500 | M25: =SUM(L25-L24) -> 0 | N25: =IF(K25>0,M25/K25,0) -> 0 | P25: =P24 -> 10873 | Q25: =IF(J25-P25<=0,"ok","oil change") -> ok | R25: =R24 -> 11640 | S25: =R25-R24 -> 0 | T25: =T24 -> 342996 | U25: =SUM(T25-T24) -> 0 | V25: =IF(S25>0,U25/S25,0) -> 0 | X25: =X24 -> 12429 | Y25: =IF(R25-X25<=0,"ok","oil change") -> ok | Z25: =C25+K25+S25 -> 0 | AA25: =U25+M25+E25 -> 0 | AB25: =V25+N25+F25 -> 0 | AC25: =IF(Z25>0,AA25/Z25,0) -> 0 | AD25: =ELEC!Q25 -> 0 | AE25: =SUM(AD25/Z25) -> #DIV/0! | AF25: =SUM(AE25/1600) -> #DIV/0! | AG25: =SUM(320*AF25) -> #DIV/0! | AH25: =SUM(AC25-AG25) -> #DIV/0! | AI25: =AD25*AJ25 -> 0 | AJ25: =305/1185 -> 0.25738397 | AK25: =IF(Z25>0,AI25/Z25,0) -> 0
A26: =ELEC!C26 -> 44067 | B26: =B25 -> 9079 | C26: =B26-B25 -> 0 | D26: =D25 -> 218240 | E26: =SUM(D26-D25) -> 0 | F26: =IF(C26>0,E26/C26,0) -> 0 | H26: =8920+180 -> 9100 | I26: =IF(B26-H26<=0,"ok","oil change") -> ok | J26: =J25 -> 10698 | K26: =J26-J25 -> 0 | L26: =L25 -> 238500 | M26: =SUM(L26-L25) -> 0 | N26: =IF(K26>0,M26/K26,0) -> 0 | P26: =P25 -> 10873 | Q26: =IF(J26-P26<=0,"ok","oil change") -> ok | R26: =R25 -> 11640 | S26: =R26-R25 -> 0 | T26: =T25 -> 342996 | U26: =SUM(T26-T25) -> 0 | V26: =IF(S26>0,U26/S26,0) -> 0 | X26: =X25 -> 12429 | Y26: =IF(R26-X26<=0,"ok","oil change") -> ok | Z26: =C26+K26+S26 -> 0 | AA26: =U26+M26+E26 -> 0 | AB26: =V26+N26+F26 -> 0 | AC26: =IF(Z26>0,AA26/Z26,0) -> 0 | AD26: =ELEC!Q26 -> 0 | AE26: =SUM(AD26/Z26) -> #DIV/0! | AF26: =SUM(AE26/1600) -> #DIV/0! | AG26: =SUM(320*AF26) -> #DIV/0! | AH26: =SUM(AC26-AG26) -> #DIV/0! | AI26: =AD26*AJ26 -> 0 | AJ26: =305/1185 -> 0.25738397 | AK26: =IF(Z26>0,AI26/Z26,0) -> 0
A27: =ELEC!C27 -> 44068 | B27: =B26 -> 9079 | C27: =B27-B26 -> 0 | D27: =D26 -> 218240 | E27: =SUM(D27-D26) -> 0 | F27: =IF(C27>0,E27/C27,0) -> 0 | H27: =8920+180 -> 9100 | I27: =IF(B27-H27<=0,"ok","oil change") -> ok | J27: =J26 -> 10698 | K27: =J27-J26 -> 0 | L27: =L26 -> 238500 | M27: =SUM(L27-L26) -> 0 | N27: =IF(K27>0,M27/K27,0) -> 0 | P27: =P26 -> 10873 | Q27: =IF(J27-P27<=0,"ok","oil change") -> ok | R27: =R26 -> 11640 | S27: =R27-R26 -> 0 | T27: =T26 -> 342996 | U27: =SUM(T27-T26) -> 0 | V27: =IF(S27>0,U27/S27,0) -> 0 | X27: =X26 -> 12429 | Y27: =IF(R27-X27<=0,"ok","oil change") -> ok | Z27: =C27+K27+S27 -> 0 | AA27: =U27+M27+E27 -> 0 | AB27: =V27+N27+F27 -> 0 | AC27: =IF(Z27>0,AA27/Z27,0) -> 0 | AD27: =ELEC!Q27 -> 0 | AE27: =SUM(AD27/Z27) -> #DIV/0! | AF27: =SUM(AE27/1600) -> #DIV/0! | AG27: =SUM(320*AF27) -> #DIV/0! | AH27: =SUM(AC27-AG27) -> #DIV/0! | AI27: =AD27*AJ27 -> 0 | AJ27: =305/1185 -> 0.25738397 | AK27: =IF(Z27>0,AI27/Z27,0) -> 0
A28: =ELEC!C28 -> 44069 | B28: =B27 -> 9079 | C28: =B28-B27 -> 0 | D28: =D27 -> 218240 | E28: =SUM(D28-D27) -> 0 | F28: =IF(C28>0,E28/C28,0) -> 0 | H28: =8920+180 -> 9100 | I28: =IF(B28-H28<=0,"ok","oil change") -> ok | J28: =J27 -> 10698 | K28: =J28-J27 -> 0 | L28: =L27 -> 238500 | M28: =SUM(L28-L27) -> 0 | N28: =IF(K28>0,M28/K28,0) -> 0 | P28: =P27 -> 10873 | Q28: =IF(J28-P28<=0,"ok","oil change") -> ok | R28: =R27 -> 11640 | S28: =R28-R27 -> 0 | T28: =T27 -> 342996 | U28: =SUM(T28-T27) -> 0 | V28: =IF(S28>0,U28/S28,0) -> 0 | X28: =X27 -> 12429 | Y28: =IF(R28-X28<=0,"ok","oil change") -> ok | Z28: =C28+K28+S28 -> 0 | AA28: =U28+M28+E28 -> 0 | AB28: =V28+N28+F28 -> 0 | AC28: =IF(Z28>0,AA28/Z28,0) -> 0 | AD28: =ELEC!Q28 -> 0 | AE28: =SUM(AD28/Z28) -> #DIV/0! | AF28: =SUM(AE28/1600) -> #DIV/0! | AG28: =SUM(320*AF28) -> #DIV/0! | AH28: =SUM(AC28-AG28) -> #DIV/0! | AI28: =AD28*AJ28 -> 0 | AJ28: =305/1185 -> 0.25738397 | AK28: =IF(Z28>0,AI28/Z28,0) -> 0
A29: =ELEC!C29 -> 44070 | B29: =B28 -> 9079 | C29: =B29-B28 -> 0 | D29: =D28 -> 218240 | E29: =SUM(D29-D28) -> 0 | F29: =IF(C29>0,E29/C29,0) -> 0 | H29: =8920+180 -> 9100 | I29: =IF(B29-H29<=0,"ok","oil change") -> ok | J29: =J28 -> 10698 | K29: =J29-J28 -> 0 | L29: =L28 -> 238500 | M29: =SUM(L29-L28) -> 0 | N29: =IF(K29>0,M29/K29,0) -> 0 | P29: =P28 -> 10873 | Q29: =IF(J29-P29<=0,"ok","oil change") -> ok | R29: =R28 -> 11640 | S29: =R29-R28 -> 0 | T29: =T28 -> 342996 | U29: =SUM(T29-T28) -> 0 | V29: =IF(S29>0,U29/S29,0) -> 0 | X29: =X28 -> 12429 | Y29: =IF(R29-X29<=0,"ok","oil change") -> ok | Z29: =C29+K29+S29 -> 0 | AA29: =U29+M29+E29 -> 0 | AB29: =V29+N29+F29 -> 0 | AC29: =IF(Z29>0,AA29/Z29,0) -> 0 | AD29: =ELEC!Q29 -> 0 | AE29: =SUM(AD29/Z29) -> #DIV/0! | AF29: =SUM(AE29/1600) -> #DIV/0! | AG29: =SUM(320*AF29) -> #DIV/0! | AH29: =SUM(AC29-AG29) -> #DIV/0! | AI29: =AD29*AJ29 -> 0 | AJ29: =305/1185 -> 0.25738397 | AK29: =IF(Z29>0,AI29/Z29,0) -> 0
A30: =ELEC!C30 -> 44071 | B30: =B29 -> 9079 | C30: =B30-B29 -> 0 | D30: =D29 -> 218240 | E30: =SUM(D30-D29) -> 0 | F30: =IF(C30>0,E30/C30,0) -> 0 | H30: =8920+180 -> 9100 | I30: =IF(B30-H30<=0,"ok","oil change") -> ok | J30: =J29 -> 10698 | K30: =J30-J29 -> 0 | L30: =L29 -> 238500 | M30: =SUM(L30-L29) -> 0 | N30: =IF(K30>0,M30/K30,0) -> 0 | P30: =P29 -> 10873 | Q30: =IF(J30-P30<=0,"ok","oil change") -> ok | R30: =R29 -> 11640 | S30: =R30-R29 -> 0 | T30: =T29 -> 342996 | U30: =SUM(T30-T29) -> 0 | V30: =IF(S30>0,U30/S30,0) -> 0 | X30: =X29 -> 12429 | Y30: =IF(R30-X30<=0,"ok","oil change") -> ok | Z30: =C30+K30+S30 -> 0 | AA30: =U30+M30+E30 -> 0 | AB30: =V30+N30+F30 -> 0 | AC30: =IF(Z30>0,AA30/Z30,0) -> 0 | AD30: =ELEC!Q30 -> 0 | AE30: =SUM(AD30/Z30) -> #DIV/0! | AF30: =SUM(AE30/1600) -> #DIV/0! | AG30: =SUM(320*AF30) -> #DIV/0! | AH30: =SUM(AC30-AG30) -> #DIV/0! | AI30: =AD30*AJ30 -> 0 | AJ30: =305/1185 -> 0.25738397 | AK30: =IF(Z30>0,AI30/Z30,0) -> 0
A31: =ELEC!C31 -> 44072 | B31: =B30 -> 9079 | C31: =B31-B30 -> 0 | D31: =D30 -> 218240 | E31: =SUM(D31-D30) -> 0 | F31: =IF(C31>0,E31/C31,0) -> 0 | H31: =8920+180 -> 9100 | I31: =IF(B31-H31<=0,"ok","oil change") -> ok | J31: =J30 -> 10698 | K31: =J31-J30 -> 0 | L31: =L30 -> 238500 | M31: =SUM(L31-L30) -> 0 | N31: =IF(K31>0,M31/K31,0) -> 0 | P31: =P30 -> 10873 | Q31: =IF(J31-P31<=0,"ok","oil change") -> ok | R31: =R30 -> 11640 | S31: =R31-R30 -> 0 | T31: =T30 -> 342996 | U31: =SUM(T31-T30) -> 0 | V31: =IF(S31>0,U31/S31,0) -> 0 | X31: =X30 -> 12429 | Y31: =IF(R31-X31<=0,"ok","oil change") -> ok | Z31: =C31+K31+S31 -> 0 | AA31: =U31+M31+E31 -> 0 | AB31: =V31+N31+F31 -> 0 | AC31: =IF(Z31>0,AA31/Z31,0) -> 0 | AD31: =ELEC!Q31 -> 0 | AE31: =SUM(AD31/Z31) -> #DIV/0! | AF31: =SUM(AE31/1600) -> #DIV/0! | AG31: =SUM(320*AF31) -> #DIV/0! | AH31: =SUM(AC31-AG31) -> #DIV/0! | AI31: =AD31*AJ31 -> 0 | AJ31: =305/1185 -> 0.25738397 | AK31: =IF(Z31>0,AI31/Z31,0) -> 0
A32: =ELEC!C32 -> 44073 | B32: =B31 -> 9079 | C32: =B32-B31 -> 0 | D32: =D31 -> 218240 | E32: =SUM(D32-D31) -> 0 | F32: =IF(C32>0,E32/C32,0) -> 0 | H32: =8920+180 -> 9100 | I32: =IF(B32-H32<=0,"ok","oil change") -> ok | J32: =J31 -> 10698 | K32: =J32-J31 -> 0 | L32: =L31 -> 238500 | M32: =SUM(L32-L31) -> 0 | N32: =IF(K32>0,M32/K32,0) -> 0 | P32: =P31 -> 10873 | Q32: =IF(J32-P32<=0,"ok","oil change") -> ok | R32: =R31 -> 11640 | S32: =R32-R31 -> 0 | T32: =T31 -> 342996 | U32: =SUM(T32-T31) -> 0 | V32: =IF(S32>0,U32/S32,0) -> 0 | X32: =X31 -> 12429 | Y32: =IF(R32-X32<=0,"ok","oil change") -> ok | Z32: =C32+K32+S32 -> 0 | AA32: =U32+M32+E32 -> 0 | AB32: =V32+N32+F32 -> 0 | AC32: =IF(Z32>0,AA32/Z32,0) -> 0 | AD32: =ELEC!Q32 -> 0 | AE32: =SUM(AD32/Z32) -> #DIV/0! | AF32: =SUM(AE32/1600) -> #DIV/0! | AG32: =SUM(320*AF32) -> #DIV/0! | AH32: =SUM(AC32-AG32) -> #DIV/0! | AI32: =AD32*AJ32 -> 0 | AJ32: =305/1185 -> 0.25738397 | AK32: =IF(Z32>0,AI32/Z32,0) -> 0
A33: =ELEC!C33 -> 44074 | B33: =B32 -> 9079 | C33: =B33-B32 -> 0 | D33: =D32 -> 218240 | E33: =SUM(D33-D32) -> 0 | F33: =IF(C33>0,E33/C33,0) -> 0 | H33: =8920+180 -> 9100 | I33: =IF(B33-H33<=0,"ok","oil change") -> ok | J33: =J32 -> 10698 | K33: =J33-J32 -> 0 | L33: =L32 -> 238500 | M33: =SUM(L33-L32) -> 0 | N33: =IF(K33>0,M33/K33,0) -> 0 | P33: =P32 -> 10873 | Q33: =IF(J33-P33<=0,"ok","oil change") -> ok | R33: =R32 -> 11640 | S33: =R33-R32 -> 0 | T33: =T32 -> 342996 | U33: =SUM(T33-T32) -> 0 | V33: =IF(S33>0,U33/S33,0) -> 0 | X33: =X32 -> 12429 | Y33: =IF(R33-X33<=0,"ok","oil change") -> ok | Z33: =C33+K33+S33 -> 0 | AA33: =U33+M33+E33 -> 0 | AB33: =V33+N33+F33 -> 0 | AC33: =IF(Z33>0,AA33/Z33,0) -> 0 | AD33: =ELEC!Q33 -> 0 | AE33: =SUM(AD33/Z33) -> #DIV/0! | AF33: =SUM(AE33/1600) -> #DIV/0! | AG33: =SUM(320*AF33) -> #DIV/0! | AH33: =SUM(AC33-AG33) -> #DIV/0! | AI33: =AD33*AJ33 -> 0 | AJ33: =305/1185 -> 0.25738397 | AK33: =IF(Z33>0,AI33/Z33,0) -> 0
P34: =+O34/3 -> 0 | U34: =SUM(C35:S35) -> 127 | X34: 341 | Z34: =SUM(Z3:Z32) -> 127
C35: =SUM(C3:C32) -> 82 | K35: =SUM(K3:K32) -> 0 | S35: =SUM(S3:S32) -> 45

Sheet Sheet1
A1: TOTAL CH RH | B1: TOTAL CH cons KW | C1: TOTAL ELIC KW | D1: TOTAL EDL | E1: TOTAL GEN KW | F1: GEN HR | G1: WATER IN | H1: TOTAL CT | I1: TOTAL WATER | J1: Date
A2: =ELEC!T3+ELEC!X1+ELEC!AB3 -> #VALUE! | B2: =ELEC!AF3 -> 6748 | C2: =ELEC!N3 -> 25351 | D2: =C2-E2 -> 8351 | E2: =ELEC!Q3 -> 17000 | F2: =GEN!Z2 -> 13 | G2: =WATER!C5+WATER!H5 -> 152 | H2: =WATER!L5 -> 0 | I2: =WATER!BC5+WATER!BD5+WATER!BE6-Sheet1!G2 -> -116.4 | J2: ='B5'!A4 -> 44043
A3: =ELEC!T4+ELEC!X2+ELEC!AB4 -> 35 | B3: =ELEC!AF4 -> 6264 | C3: =ELEC!N4 -> 24732 | D3: =C3-E3 -> 14732 | E3: =ELEC!Q4 -> 10000 | F3: =GEN!Z3 -> 25 | G3: =WATER!C6+WATER!H6 -> 494 | H3: =WATER!L6 -> 0 | I3: =WATER!BC6+WATER!BD6+WATER!BE7-Sheet1!G3 -> -613 | J3: ='B5'!A5 -> 44044
A4: =ELEC!T5+ELEC!X5+ELEC!AB5 -> 24 | B4: =ELEC!AF5 -> 6415 | C4: =ELEC!N5 -> 23757 | D4: =C4-E4 -> 8757 | E4: =ELEC!Q5 -> 15000 | F4: =GEN!Z4 -> 9 | G4: =WATER!C7+WATER!H7 -> 0 | H4: =WATER!L7 -> 7 | I4: =WATER!BC7+WATER!BD7+WATER!BE8-Sheet1!G4 -> 51.3 | J4: ='B5'!A6 -> 44045
A5: =ELEC!T6+ELEC!X6+ELEC!AB6 -> 0 | B5: =ELEC!AF6 -> 0 | C5: =ELEC!N6 -> 25244 | D5: =C5-E5 -> 25244 | E5: =ELEC!Q6 -> 0 | F5: =GEN!Z5 -> 19 | G5: =WATER!C8+WATER!H8 -> 366 | H5: =WATER!L8 -> 5 | I5: =WATER!BC8+WATER!BD8+WATER!BE9-Sheet1!G5 -> -344.8 | J5: ='B5'!A7 -> 44046
A6: =ELEC!T7+ELEC!X7+ELEC!AB7 -> 33 | B6: =ELEC!AF7 -> 8184 | C6: =ELEC!N7 -> 10988 | D6: =C6-E6 -> 10988 | E6: =ELEC!Q24 -> 0 | F6: =GEN!Z6 -> 20 | G6: =WATER!C9+WATER!H9 -> 0 | H6: =WATER!L9 -> 0 | I6: =WATER!BC9+WATER!BD9+WATER!BE10-Sheet1!G6 -> -11 | J6: ='B5'!A8 -> 44047
A7: =ELEC!T8+ELEC!X8+ELEC!AB8 -> 10 | B7: =ELEC!AF8 -> 2121 | C7: =ELEC!N8 -> 10699 | D7: =C7-E7 -> 5699 | E7: =ELEC!Q8 -> 5000 | F7: =GEN!Z7 -> 8 | G7: =WATER!C10+WATER!H10 -> 172 | H7: =WATER!L10 -> 0 | I7: =WATER!BC10+WATER!BD10+WATER!BE11-Sheet1!G7 -> -166.8 | J7: ='B5'!A9 -> 44048
A8: =ELEC!T9+ELEC!X9+ELEC!AB9 -> 11 | B8: =ELEC!AF9 -> 2373 | C8: =ELEC!N9 -> 9781 | D8: =C8-E8 -> 8781 | E8: =ELEC!Q9 -> 1000 | F8: =GEN!Z8 -> 2 | G8: =WATER!C11+WATER!H11 -> 0 | H8: =WATER!L11 -> 0 | I8: =WATER!BC11+WATER!BD11+WATER!BE12-Sheet1!G8 -> 115.1 | J8: ='B5'!A10 -> 44049
A9: =ELEC!T10+ELEC!X10+ELEC!AB10 -> 14 | B9: =ELEC!AF10 -> 2687 | C9: =ELEC!N10 -> 10647 | D9: =C9-E9 -> 8647 | E9: =ELEC!Q10 -> 2000 | F9: =GEN!Z9 -> 4 | G9: =WATER!C12+WATER!H12 -> 0 | H9: =WATER!L12 -> 0 | I9: =WATER!BC12+WATER!BD12+WATER!BE13-Sheet1!G9 -> 58.1 | J9: ='B5'!A11 -> 44050
A10: =ELEC!T11+ELEC!X11+ELEC!AB11 -> 11 | B10: =ELEC!AF11 -> 1781 | C10: =ELEC!N11 -> 8400 | D10: =C10-E10 -> 6400 | E10: =ELEC!Q11 -> 2000 | F10: =GEN!Z10 -> 3 | G10: =WATER!C13+WATER!H13 -> 0 | H10: =WATER!L13 -> 0 | I10: =WATER!BC13+WATER!BD13+WATER!BE14-Sheet1!G10 -> 238.4 | J10: ='B5'!A12 -> 44051
A11: =ELEC!T12+ELEC!X12+ELEC!AB12 -> 14 | B11: =ELEC!AF12 -> 2576 | C11: =ELEC!N12 -> 10457 | D11: =C11-E11 -> 9457 | E11: =ELEC!Q12 -> 1000 | F11: =GEN!Z11 -> 3 | G11: =WATER!C14+WATER!H14 -> 0 | H11: =WATER!L14 -> 0 | I11: =WATER!BC14+WATER!BD14+WATER!BE15-Sheet1!G11 -> 53.8 | J11: ='B5'!A13 -> 44052
A12: =ELEC!T13+ELEC!X13+ELEC!AB13 -> 8 | B12: =ELEC!AF13 -> 1627 | C12: =ELEC!N13 -> 10265 | D12: =C12-E12 -> 8265 | E12: =ELEC!Q13 -> 2000 | F12: =GEN!Z12 -> 3 | G12: =WATER!C15+WATER!H15 -> 0 | H12: =WATER!L15 -> 0 | I12: =WATER!BC15+WATER!BD15+WATER!BE16-Sheet1!G12 -> 287.1 | J12: ='B5'!A14 -> 44053
A13: =ELEC!T14+ELEC!X14+ELEC!AB14 -> 13 | B13: =ELEC!AF14 -> 2776 | C13: =ELEC!N14 -> 10779 | D13: =C13-E13 -> 8779 | E13: =ELEC!Q14 -> 2000 | F13: =GEN!Z13 -> 3 | G13: =WATER!C16+WATER!H16 -> 0 | H13: =WATER!L16 -> 0 | I13: =WATER!BC16+WATER!BD16+WATER!BE17-Sheet1!G13 -> 0.5 | J13: ='B5'!A15 -> 44054
A14: =ELEC!T15+ELEC!X15+ELEC!AB15 -> 12 | B14: =ELEC!AF15 -> 2726 | C14: =ELEC!N15 -> 11455 | D14: =C14-E14 -> 9455 | E14: =ELEC!Q15 -> 2000 | F14: =GEN!Z14 -> 3 | G14: =WATER!C17+WATER!H17 -> 0 | H14: =WATER!L17 -> 0 | I14: =WATER!BC17+WATER!BD17+WATER!BE18-Sheet1!G14 -> 334.9 | J14: ='B5'!A16 -> 44055
A15: =ELEC!T16+ELEC!X16+ELEC!AB16 -> 10 | B15: =ELEC!AF16 -> 2182 | C15: =ELEC!N16 -> 11209 | D15: =C15-E15 -> 7209 | E15: =ELEC!Q16 -> 4000 | F15: =GEN!Z15 -> 6 | G15: =WATER!C18+WATER!H18 -> 0 | H15: =WATER!L18 -> 0 | I15: =WATER!BC18+WATER!BD18+WATER!BE19-Sheet1!G15 -> 100.1 | J15: ='B5'!A17 -> 44056
A16: =ELEC!T17+ELEC!X17+ELEC!AB17 -> 10 | B16: =ELEC!AF17 -> 1813 | C16: =ELEC!N17 -> 9704 | D16: =C16-E16 -> 7704 | E16: =ELEC!Q17 -> 2000 | F16: =GEN!Z16 -> 6 | G16: =WATER!C19+WATER!H19 -> 0 | H16: =WATER!L19 -> 0 | I16: =WATER!BC19+WATER!BD19+WATER!BE20-Sheet1!G16 -> -31.7 | J16: ='B5'!A18 -> 44057
A17: =ELEC!T18+ELEC!X18+ELEC!AB18 -> 8 | B17: =ELEC!AF18 -> 1812 | C17: =ELEC!N18 -> 9365 | D17: =C17-E17 -> 7365 | E17: =ELEC!Q18 -> 2000 | F17: =GEN!Z17 -> 5 | G17: =WATER!C20+WATER!H20 -> 0 | H17: =WATER!L20 -> 0 | I17: =WATER!BC20+WATER!BD20+WATER!BE21-Sheet1!G17 -> -36.1 | J17: ='B5'!A19 -> 44058
A18: =ELEC!T19+ELEC!X19+ELEC!AB19 -> 7 | B18: =ELEC!AF19 -> 1370 | C18: =ELEC!N19 -> 11726 | D18: =C18-E18 -> 10726 | E18: =ELEC!Q19 -> 1000 | F18: =GEN!Z18 -> 3 | G18: =WATER!C21+WATER!H21 -> 0 | H18: =WATER!L21 -> 0 | I18: =WATER!BC21+WATER!BD21+WATER!BE22-Sheet1!G18 -> -16.4 | J18: ='B5'!A20 -> 44059
... A29: =ELEC!T30+ELEC!X30+ELEC!AB30 -> 0 | B29: =ELEC!AF30 -> 0 | C29: =ELEC!N30 -> 0 | D29: =C29-E29 -> 0 | E29: =ELEC!Q30 -> 0 | F29: =GEN!Z29 -> 0 | G29: =WATER!C32+WATER!H32 -> 0 | H29: =WATER!L32 -> 0 | I29: =WATER!BC32+WATER!BD32+WATER!BE33-Sheet1!G29 -> 0 | J29: ='B5'!A31 -> 44070
A30: =ELEC!T31+ELEC!X31+ELEC!#REF! -> #REF! | B30: =ELEC!AF31 -> 0 | C30: =ELEC!N31 -> 0 | D30: =C30-E30 -> 0 | E30: =ELEC!Q31 -> 0 | F30: =GEN!Z30 -> 0 | G30: =WATER!C33+WATER!H33 -> 0 | H30: =WATER!L33 -> 0 | I30: =WATER!BC33+WATER!BD33+WATER!BE34-Sheet1!G30 -> 0 | J30: ='B5'!A32 -> 44071
A31: =ELEC!T32+ELEC!X32+ELEC!AB31 -> 0 | B31: =ELEC!AF32 -> 0 | C31: =ELEC!N32 -> 0 | D31: =C31-E31 -> 0 | E31: =ELEC!Q32 -> 0 | F31: =GEN!Z31 -> 0 | G31: =WATER!C34+WATER!H34 -> 0 | H31: =WATER!L34 -> 0 | I31: =WATER!BC34+WATER!BD34+WATER!BE35-Sheet1!G31 -> 0 | J31: ='B5'!A33 -> 44072
A32: =ELEC!#REF!+ELEC!#REF!+ELEC!#REF! -> #REF! | B32: =ELEC!#REF! -> #REF! | C32: =ELEC!#REF! -> #REF! | D32: =C32-E32 -> #REF! | E32: =ELEC!#REF! -> #REF! | F32: =GEN!#REF! -> #REF! | G32: =WATER!#REF!+WATER!#REF! -> #REF! | H32: =WATER!#REF! -> #REF! | I32: =WATER!#REF!+WATER!#REF!+WATER!BE37-Sheet1!G32 -> #REF!

Sheet Report
B1: Boiler Fuel | C1: Steam Fuel | D1: GEN FUEL | E1: FUEL TOTAL | F1: CT/mᶾ | G1: Water Consumption | H1: Chiller KW | I1: GEN KW | J1: EDL KW | K1: occ | L1: covers | M1: temp. C⁰ | N1: RH %
B3: ='B5'!V3 -> 0 | C3: ='B5'!AH3 -> 0 | E3: =B3+C3+D3 -> 0
A4: 42704 | B4: 810 | C4: -606.1 | D4: 1420.5021 | E4: 1624.4021 | F4: 106 | G4: -58.4 | H4: 6284 | I4: 2399 | J4: 23932 | K4: 0 | L4: 0 | M4: 0 | N4: 0
A5: ='B5'!A5 -> 44044 | B5: ='B5'!V5 -> 250 | C5: ='B5'!AH5 -> 130 | D5: =GEN!AI3 -> 4375.5274 | E5: =B5+C5+D5 -> 4755.5274 | F5: =WATER!L5 -> 0 | G5: =WATER!BG5 -> -29.7 | H5: =ELEC!AF3 -> 6748 | I5: =ELEC!Q3 -> 17000 | J5: =ELEC!R3 -> 8351
A6: ='B5'!A6 -> 44045 | B6: ='B5'!V6 -> 229 | C6: ='B5'!AH6 -> 0 | D6: =GEN!AI4 -> 2573.8397 | E6: =B6+C6+D6 -> 2802.8397 | F6: =WATER!L6 -> 0 | G6: =WATER!BG6 -> 44.6 | H6: =ELEC!AF4 -> 6264 | I6: =ELEC!Q4 -> 10000 | J6: =ELEC!R4 -> 14732
A7: ='B5'!A7 -> 44046 | B7: ='B5'!V7 -> 233 | C7: ='B5'!AH7 -> 447 | D7: =GEN!AI5 -> 3860.7595 | E7: =B7+C7+D7 -> 4540.7595 | F7: =WATER!L7 -> 7 | G7: =WATER!BG7 -> -93.4 | H7: =ELEC!AF5 -> 6415 | I7: =ELEC!Q5 -> 15000 | J7: =ELEC!R5 -> 8757
A8: ='B5'!A8 -> 44047 | B8: ='B5'!V8 -> 0 | C8: ='B5'!AH8 -> 0 | D8: =GEN!AI6 -> 0 | E8: =B8+C8+D8 -> 0 | F8: =WATER!L8 -> 5 | G8: =WATER!BG8 -> 59.2 | H8: =ELEC!AF6 -> 0 | I8: =ELEC!Q6 -> 0 | J8: =ELEC!R6 -> 25244
A9: ='B5'!A9 -> 44048 | B9: ='B5'!V9 -> 144 | C9: ='B5'!AH9 -> 0 | D9: =GEN!AI7 -> 3603.3755 | E9: =B9+C9+D9 -> 3747.3755 | F9: =WATER!L9 -> 0 | G9: =WATER!BG9 -> -27.2 | H9: =ELEC!AF7 -> 8184 | I9: =ELEC!Q7 -> 14000 | J9: =ELEC!R7 -> -3012
A10: ='B5'!A10 -> 44049 | B10: ='B5'!V10 -> 0 | C10: ='B5'!AH10 -> 0 | D10: =GEN!AI8 -> 1286.9198 | E10: =B10+C10+D10 -> 1286.9198 | F10: =WATER!L10 -> 0 | G10: =WATER!BG10 -> 32.4 | H10: =ELEC!AF8 -> 2121 | I10: =ELEC!Q8 -> 5000 | J10: =ELEC!R8 -> 5699
A11: ='B5'!A11 -> 44050 | B11: ='B5'!V11 -> 0 | C11: ='B5'!AH11 -> 0 | D11: =GEN!AI9 -> 257.38397 | E11: =B11+C11+D11 -> 257.38397 | F11: =WATER!L11 -> 0 | G11: =WATER!BG11 -> -9.2 | H11: =ELEC!AF9 -> 2373 | I11: =ELEC!Q9 -> 1000 | J11: =ELEC!R9 -> 8781
A12: ='B5'!A12 -> 44051 | B12: ='B5'!V12 -> 0 | C12: ='B5'!AH12 -> 0 | D12: =GEN!AI10 -> 514.76793 | E12: =B12+C12+D12 -> 514.76793 | F12: =WATER!L12 -> 0 | G12: =WATER!BG12 -> 129.7 | H12: =ELEC!AF10 -> 2687 | I12: =ELEC!Q10 -> 2000 | J12: =ELEC!R10 -> 8647
A13: ='B5'!A13 -> 44052 | B13: ='B5'!V13 -> 0 | C13: ='B5'!AH13 -> 0 | D13: =GEN!AI11 -> 514.76793 | E13: =B13+C13+D13 -> 514.76793 | F13: =WATER!L13 -> 0 | G13: =WATER!BG13 -> -14 | H13: =ELEC!AF11 -> 1781 | I13: =ELEC!Q11 -> 2000 | J13: =ELEC!R11 -> 6400
A14: ='B5'!A14 -> 44053 | B14: ='B5'!V14 -> 0 | C14: ='B5'!AH14 -> 0 | D14: =GEN!AI12 -> 257.38397 | E14: =B14+C14+D14 -> 257.38397 | F14: =WATER!L14 -> 0 | G14: =WATER!BG14 -> 164.2 | H14: =ELEC!AF12 -> 2576 | I14: =ELEC!Q12 -> 1000 | J14: =ELEC!R12 -> 9457
