Workbook

Sheet Total
A1: Site Name | B1: Day | C1: Month | D1: Year | E1: Total Electricity Kwh | F1: Electricity Tariff ($/Kwh) | G1: LPG (Kg) | H1: LPG $/Kg | I1: Water Utility Supply (m3) m3 | J1: Water Utility Supply (m3) $/m3 | K1: Room Nights | L1: Utilities day cost dh
A2: Serengeti | B2: 1 | C2: 9 | D2: 2020 | E2: ='UTILITY REPORT 1'!F3 -> 2111 | F2: =('UTILITY REPORT 1'!E3*'UTILITY REPORT 1'!D3)/'UTILITY REPORT 1'!F3 -> 0.42227854 | G2: =IF('Utility summery'!M6<0,"0",'Utility summery'!M6) -> 76.032 | H2: 0 | I2: =IF('UTILITY REPORT 1'!G3<0,"0",'UTILITY REPORT 1'!G3) -> 56 | J2: 0 | K2: ='UTILITY REPORT 1'!C3 -> 3 | L2: =E2*F2+G2*H2+#REF!*#REF!+I2*J2 -> #REF!
A3: Serengeti | B3: =B2+1 -> 2 | C3: 9 | D3: 2020 | E3: ='UTILITY REPORT 1'!F4 -> 2147 | F3: =('UTILITY REPORT 1'!E4*'UTILITY REPORT 1'!D4)/'UTILITY REPORT 1'!F4 -> 0.38282254 | G3: =IF('Utility summery'!M7<0,"0",'Utility summery'!M7) -> 58.608 | H3: 0 | I3: =IF('UTILITY REPORT 1'!G4<0,"0",'UTILITY REPORT 1'!G4) -> 58 | J3: 0 | K3: ='UTILITY REPORT 1'!C4 -> 4 | L3: =E3*F3+G3*H3+#REF!*#REF!+I3*J3 -> #REF!
A4: Serengeti | B4: =B3+1 -> 3 | C4: 9 | D4: 2020 | E4: ='UTILITY REPORT 1'!F5 -> 2188 | F4: =('UTILITY REPORT 1'!E5*'UTILITY REPORT 1'!D5)/'UTILITY REPORT 1'!F5 -> 0.49829982 | G4: =IF('Utility summery'!M8<0,"0",'Utility summery'!M8) -> 66.264 | H4: 0 | I4: =IF('UTILITY REPORT 1'!G5<0,"0",'UTILITY REPORT 1'!G5) -> 51 | J4: 0 | K4: ='UTILITY REPORT 1'!C5 -> 4 | L4: =E4*F4+G4*H4+#REF!*#REF!+I4*J4 -> #REF!
A5: Serengeti | B5: =B4+1 -> 4 | C5: 9 | D5: 2020 | E5: ='UTILITY REPORT 1'!F6 -> 2448 | F5: =('UTILITY REPORT 1'!E6*'UTILITY REPORT 1'!D6)/'UTILITY REPORT 1'!F6 -> 0.35473448 | G5: =IF('Utility summery'!M9<0,"0",'Utility summery'!M9) -> 63.536 | H5: 0 | I5: =IF('UTILITY REPORT 1'!G6<0,"0",'UTILITY REPORT 1'!G6) -> 54 | J5: 0 | K5: ='UTILITY REPORT 1'!C6 -> 8 | L5: =E5*F5+G5*H5+#REF!*#REF!+I5*J5 -> #REF!
A6: Serengeti | B6: =B5+1 -> 5 | C6: 9 | D6: 2020 | E6: ='UTILITY REPORT 1'!F7 -> 2152 | F6: =('UTILITY REPORT 1'!E7*'UTILITY REPORT 1'!D7)/'UTILITY REPORT 1'!F7 -> 0.39125465 | G6: =IF('Utility summery'!M10<0,"0",'Utility summery'!M10) -> 50.072 | H6: 0 | I6: =IF('UTILITY REPORT 1'!G7<0,"0",'UTILITY REPORT 1'!G7) -> 50 | J6: 0 | K6: ='UTILITY REPORT 1'!C7 -> 8 | L6: =E6*F6+G6*H6+#REF!*#REF!+I6*J6 -> #REF!
A7: Serengeti | B7: =B6+1 -> 6 | C7: 9 | D7: 2020 | E7: ='UTILITY REPORT 1'!F8 -> 2052 | F7: =('UTILITY REPORT 1'!E8*'UTILITY REPORT 1'!D8)/'UTILITY REPORT 1'!F8 -> 0.45737817 | G7: =IF('Utility summery'!M11<0,"0",'Utility summery'!M11) -> 49.588 | H7: 0 | I7: =IF('UTILITY REPORT 1'!G8<0,"0",'UTILITY REPORT 1'!G8) -> 52 | J7: 0 | K7: ='UTILITY REPORT 1'!C8 -> 7 | L7: =E7*F7+G7*H7+#REF!*#REF!+I7*J7 -> #REF!
A8: Serengeti | B8: =B7+1 -> 7 | C8: 9 | D8: 2020 | E8: ='UTILITY REPORT 1'!F9 -> 2010 | F8: =('UTILITY REPORT 1'!E9*'UTILITY REPORT 1'!D9)/'UTILITY REPORT 1'!F9 -> 0.45287065 | G8: =IF('Utility summery'!M12<0,"0",'Utility summery'!M12) -> 62.568 | H8: 0 | I8: =IF('UTILITY REPORT 1'!G9<0,"0",'UTILITY REPORT 1'!G9) -> 58 | J8: 0 | K8: ='UTILITY REPORT 1'!C9 -> 3 | L8: =E8*F8+G8*H8+#REF!*#REF!+I8*J8 -> #REF!
A9: Serengeti | B9: =B8+1 -> 8 | C9: 9 | D9: 2020 | E9: ='UTILITY REPORT 1'!F10 -> 2245 | F9: =('UTILITY REPORT 1'!E10*'UTILITY REPORT 1'!D10)/'UTILITY REPORT 1'!F10 -> 0.42236526 | G9: =IF('Utility summery'!M13<0,"0",'Utility summery'!M13) -> 54.868 | H9: 0 | I9: =IF('UTILITY REPORT 1'!G10<0,"0",'UTILITY REPORT 1'!G10) -> 46 | J9: 0 | K9: ='UTILITY REPORT 1'!C10 -> 7 | L9: =E9*F9+G9*H9+#REF!*#REF!+I9*J9 -> #REF!
A10: Serengeti | B10: =B9+1 -> 9 | C10: 9 | D10: 2020 | E10: ='UTILITY REPORT 1'!F11 -> 2101 | F10: =('UTILITY REPORT 1'!E11*'UTILITY REPORT 1'!D11)/'UTILITY REPORT 1'!F11 -> 0.43613993 | G10: =IF('Utility summery'!M14<0,"0",'Utility summery'!M14) -> 57.42 | H10: 0 | I10: =IF('UTILITY REPORT 1'!G11<0,"0",'UTILITY REPORT 1'!G11) -> 52 | J10: 0 | K10: ='UTILITY REPORT 1'!C11 -> 5 | L10: =E10*F10+G10*H10+#REF!*#REF!+I10*J10 -> #REF!
A11: Serengeti | B11: =B10+1 -> 10 | C11: 9 | D11: 2020 | E11: ='UTILITY REPORT 1'!F12 -> 2199 | F11: =('UTILITY REPORT 1'!E12*'UTILITY REPORT 1'!D12)/'UTILITY REPORT 1'!F12 -> 0.4447658 | G11: =IF('Utility summery'!M15<0,"0",'Utility summery'!M15) -> 44 | H11: 0 | I11: =IF('UTILITY REPORT 1'!G12<0,"0",'UTILITY REPORT 1'!G12) -> 55 | J11: 0 | K11: ='UTILITY REPORT 1'!C12 -> 1 | L11: =E11*F11+G11*H11+#REF!*#REF!+I11*J11 -> #REF!
A12: Serengeti | B12: =B11+1 -> 11 | C12: 9 | D12: 2020 | E12: ='UTILITY REPORT 1'!F13 -> 2126 | F12: =('UTILITY REPORT 1'!E13*'UTILITY REPORT 1'!D13)/'UTILITY REPORT 1'!F13 -> 0.36808561 | G12: =IF('Utility summery'!M16<0,"0",'Utility summery'!M16) -> 70.928 | H12: 0 | I12: =IF('UTILITY REPORT 1'!G13<0,"0",'UTILITY REPORT 1'!G13) -> 94 | J12: 0 | K12: ='UTILITY REPORT 1'!C13 -> 3 | L12: =E12*F12+G12*H12+#REF!*#REF!+I12*J12 -> #REF!
A13: Serengeti | B13: =B12+1 -> 12 | C13: 9 | D13: 2020 | E13: ='UTILITY REPORT 1'!F14 -> 2174 | F13: =('UTILITY REPORT 1'!E14*'UTILITY REPORT 1'!D14)/'UTILITY REPORT 1'!F14 -> 0.33706532 | G13: =IF('Utility summery'!M17<0,"0",'Utility summery'!M17) -> 53.9 | H13: 0 | I13: =IF('UTILITY REPORT 1'!G14<0,"0",'UTILITY REPORT 1'!G14) -> 59 | J13: 0 | K13: ='UTILITY REPORT 1'!C14 -> 3 | L13: =E13*F13+G13*H13+#REF!*#REF!+I13*J13 -> #REF!
A14: Serengeti | B14: =B13+1 -> 13 | C14: 9 | D14: 2020 | E14: ='UTILITY REPORT 1'!F15 -> 2113 | F14: =('UTILITY REPORT 1'!E15*'UTILITY REPORT 1'!D15)/'UTILITY REPORT 1'!F15 -> 0.44284903 | G14: =IF('Utility summery'!M18<0,"0",'Utility summery'!M18) -> 55.396 | H14: 0 | I14: =IF('UTILITY REPORT 1'!G15<0,"0",'UTILITY REPORT 1'!G15) -> 36 | J14: 0 | K14: ='UTILITY REPORT 1'!C15 -> 3 | L14: =E14*F14+G14*H14+#REF!*#REF!+I14*J14 -> #REF!
... A30: Serengeti | B30: =B29+1 -> 29 | C30: 9 | D30: 2020 | E30: ='UTILITY REPORT 1'!F31 -> 0 | F30: =('UTILITY REPORT 1'!E31*'UTILITY REPORT 1'!D31)/'UTILITY REPORT 1'!F31 -> #DIV/0! | G30: =IF('Utility summery'!M34<0,"0",'Utility summery'!M34) -> 0 | H30: 0 | I30: =IF('UTILITY REPORT 1'!G31<0,"0",'UTILITY REPORT 1'!G31) -> 0 | J30: 0 | K30: ='UTILITY REPORT 1'!C31 -> 5 | L30: =E30*F30+G30*H30+#REF!*#REF!+I30*J30 -> #DIV/0!
A31: Serengeti | B31: 30 | C31: 9 | D31: 2020 | E31: ='UTILITY REPORT 1'!F32 -> 0 | F31: =('UTILITY REPORT 1'!E32*'UTILITY REPORT 1'!D32)/'UTILITY REPORT 1'!F32 -> #DIV/0! | G31: =IF('Utility summery'!M35<0,"0",'Utility summery'!M35) -> 0 | H31: 0 | I31: =IF('UTILITY REPORT 1'!G32<0,"0",'UTILITY REPORT 1'!G32) -> 0 | J31: 0 | K31: ='UTILITY REPORT 1'!C32 -> 0 | L31: =E31*F31+G31*H31+#REF!*#REF!+I31*J31 -> #DIV/0!
E32: ='UTILITY REPORT 1'!F33 -> 0 | F32: =('UTILITY REPORT 1'!E33*'UTILITY REPORT 1'!D33)/'UTILITY REPORT 1'!F33 -> #DIV/0! | G32: =IF('Utility summery'!M36<0,"0",'Utility summery'!M36) -> 0 | H32: 0 | I32: =IF('UTILITY REPORT 1'!G33<0,"0",'UTILITY REPORT 1'!G33) -> 0 | J32: 0 | K32: ='UTILITY REPORT 1'!C33 -> 0

Sheet Submetering
A1: Site Name | B1: Day | C1: Month | D1: Year | E1: Transport Consumption (LT) | F1: Generators Consumption (LT) | G1: Total Electricity Kwh | H1: Kitchen (KWh) | I1: Laundry (KWh) | J1: STP (M3) | K1: RO prodution (M3) | L1: Amani Restaurant (M3) | M1: Kitchen (M3) | N1: Laundry (M3) | O1: Laundry (M3) | P1: Total water Consumption (M3) | Q1: Borehole #1 (M3) | R1: Borehole #2 (M3) | S1: Borehole #3 (M3) | T1: Borehole #4 (M3) | U1: Borehole #5 (M3) | V1: Borehole #6 (M3) | W1: Total Bore holes production (M3) | X1: Room Nights
A2: Serengeti | B2: 1 | C2: 9 | D2: 2020 | E2: ='UTILITY REPORT 1'!I3 -> 69.21 | F2: ='UTILITY REPORT 1'!E3 -> 891.43 | G2: ='UTILITY REPORT 1'!F3 -> 2111 | H2: =IF('Kit report'!F4<0,"0",'Kit report'!F4) -> 192 | I2: =IF('Kit report'!X4<0,"0",'Kit report'!X4) -> 80 | J2: =IF('Utility summery'!H6<0,"0",'Utility summery'!H6) -> 47 | K2: =IF('UTILITY REPORT 1'!H3<0,"0",'UTILITY REPORT 1'!H3) -> 74 | L2: ='Water-Meter'!K6 -> 2 | M2: ='Water-Meter'!H6 -> 0 | N2: ='Water-Meter'!Q6 -> 1 | O2: =K2*E2+H2*I2+#REF!*#REF!+J2*L2 -> #REF! | P2: ='Water-Meter'!E6 -> 56 | Q2: =IF('Water-Meter'!U6<0,"0",'Water-Meter'!U6) -> 86 | R2: =IF('Water-Meter'!X6<0,"0",'Water-Meter'!X6) -> 0 | S2: =IF('Water-Meter'!AA6<0,"0",'Water-Meter'!AA6) -> 0 | T2: =IF('Water-Meter'!AD6<0,"0",'Water-Meter'!AD6) -> 15 | U2: =IF('Water-Meter'!AG6<0,"0",'Water-Meter'!AG6) -> 0 | V2: =IF('Water-Meter'!AJ6<0,"0",'Water-Meter'!AJ6) -> 5 | W2: ='Water-Meter'!AN6 -> 106 | X2: =Total!K2 -> 3
A3: Serengeti | B3: =B2+1 -> 2 | C3: 9 | D3: 2020 | E3: ='UTILITY REPORT 1'!I4 -> 80.65 | F3: ='UTILITY REPORT 1'!E4 -> 821.92 | G3: ='UTILITY REPORT 1'!F4 -> 2147 | H3: =IF('Kit report'!F5<0,"0",'Kit report'!F5) -> 192 | I3: =IF('Kit report'!X5<0,"0",'Kit report'!X5) -> 20 | J3: =IF('Utility summery'!H7<0,"0",'Utility summery'!H7) -> 30 | K3: =IF('UTILITY REPORT 1'!H4<0,"0",'UTILITY REPORT 1'!H4) -> 26 | L3: ='Water-Meter'!K7 -> 1 | M3: ='Water-Meter'!H7 -> 0 | N3: ='Water-Meter'!Q7 -> 2 | O3: =K3*E3+H3*I3+#REF!*#REF!+J3*L3 -> #REF! | P3: ='Water-Meter'!E7 -> 58 | Q3: =IF('Water-Meter'!U7<0,"0",'Water-Meter'!U7) -> 82 | R3: =IF('Water-Meter'!X7<0,"0",'Water-Meter'!X7) -> 0 | S3: =IF('Water-Meter'!AA7<0,"0",'Water-Meter'!AA7) -> 0 | T3: =IF('Water-Meter'!AD7<0,"0",'Water-Meter'!AD7) -> 17 | U3: =IF('Water-Meter'!AG7<0,"0",'Water-Meter'!AG7) -> 0 | V3: =IF('Water-Meter'!AJ7<0,"0",'Water-Meter'!AJ7) -> 26 | W3: ='Water-Meter'!AN7 -> 125 | X3: =Total!K3 -> 4
A4: Serengeti | B4: =B3+1 -> 3 | C4: 9 | D4: 2020 | E4: ='UTILITY REPORT 1'!I5 -> 10.02 | F4: ='UTILITY REPORT 1'!E5 -> 1090.28 | G4: ='UTILITY REPORT 1'!F5 -> 2188 | H4: =IF('Kit report'!F6<0,"0",'Kit report'!F6) -> 204 | I4: =IF('Kit report'!X6<0,"0",'Kit report'!X6) -> 40 | J4: =IF('Utility summery'!H8<0,"0",'Utility summery'!H8) -> 36 | K4: =IF('UTILITY REPORT 1'!H5<0,"0",'UTILITY REPORT 1'!H5) -> 79 | L4: ='Water-Meter'!K8 -> 1 | M4: ='Water-Meter'!H8 -> 0 | N4: ='Water-Meter'!Q8 -> 1 | O4: =K4*E4+H4*I4+#REF!*#REF!+J4*L4 -> #REF! | P4: ='Water-Meter'!E8 -> 51 | Q4: =IF('Water-Meter'!U8<0,"0",'Water-Meter'!U8) -> 83 | R4: =IF('Water-Meter'!X8<0,"0",'Water-Meter'!X8) -> 0 | S4: =IF('Water-Meter'!AA8<0,"0",'Water-Meter'!AA8) -> 0 | T4: =IF('Water-Meter'!AD8<0,"0",'Water-Meter'!AD8) -> 15 | U4: =IF('Water-Meter'!AG8<0,"0",'Water-Meter'!AG8) -> 0 | V4: =IF('Water-Meter'!AJ8<0,"0",'Water-Meter'!AJ8) -> 26 | W4: ='Water-Meter'!AN8 -> 124 | X4: =Total!K4 -> 4
A5: Serengeti | B5: =B4+1 -> 4 | C5: 9 | D5: 2020 | E5: ='UTILITY REPORT 1'!I6 -> 0 | F5: ='UTILITY REPORT 1'!E6 -> 868.39 | G5: ='UTILITY REPORT 1'!F6 -> 2448 | H5: =IF('Kit report'!F7<0,"0",'Kit report'!F7) -> 216 | I5: =IF('Kit report'!X7<0,"0",'Kit report'!X7) -> 100 | J5: =IF('Utility summery'!H9<0,"0",'Utility summery'!H9) -> 45 | K5: =IF('UTILITY REPORT 1'!H6<0,"0",'UTILITY REPORT 1'!H6) -> 92 | L5: ='Water-Meter'!K9 -> 1 | M5: ='Water-Meter'!H9 -> 0 | N5: ='Water-Meter'!Q9 -> 1 | O5: =K5*E5+H5*I5+#REF!*#REF!+J5*L5 -> #REF! | P5: ='Water-Meter'!E9 -> 54 | Q5: =IF('Water-Meter'!U9<0,"0",'Water-Meter'!U9) -> 77 | R5: =IF('Water-Meter'!X9<0,"0",'Water-Meter'!X9) -> 0 | S5: =IF('Water-Meter'!AA9<0,"0",'Water-Meter'!AA9) -> 25 | T5: =IF('Water-Meter'!AD9<0,"0",'Water-Meter'!AD9) -> 15 | U5: =IF('Water-Meter'!AG9<0,"0",'Water-Meter'!AG9) -> 0 | V5: =IF('Water-Meter'!AJ9<0,"0",'Water-Meter'!AJ9) -> 22 | W5: ='Water-Meter'!AN9 -> 139 | X5: =Total!K5 -> 8
A6: Serengeti | B6: =B5+1 -> 5 | C6: 9 | D6: 2020 | E6: ='UTILITY REPORT 1'!I7 -> 27.01 | F6: ='UTILITY REPORT 1'!E7 -> 841.98 | G6: ='UTILITY REPORT 1'!F7 -> 2152 | H6: =IF('Kit report'!F8<0,"0",'Kit report'!F8) -> 204 | I6: =IF('Kit report'!X8<0,"0",'Kit report'!X8) -> 40 | J6: =IF('Utility summery'!H10<0,"0",'Utility summery'!H10) -> 43 | K6: =IF('UTILITY REPORT 1'!H7<0,"0",'UTILITY REPORT 1'!H7) -> 1 | L6: ='Water-Meter'!K10 -> 1 | M6: ='Water-Meter'!H10 -> 0 | N6: ='Water-Meter'!Q10 -> 2 | O6: =K6*E6+H6*I6+#REF!*#REF!+J6*L6 -> #REF! | P6: ='Water-Meter'!E10 -> 50 | Q6: =IF('Water-Meter'!U10<0,"0",'Water-Meter'!U10) -> 20 | R6: =IF('Water-Meter'!X10<0,"0",'Water-Meter'!X10) -> 0 | S6: =IF('Water-Meter'!AA10<0,"0",'Water-Meter'!AA10) -> 43 | T6: =IF('Water-Meter'!AD10<0,"0",'Water-Meter'!AD10) -> 16 | U6: =IF('Water-Meter'!AG10<0,"0",'Water-Meter'!AG10) -> 0 | V6: =IF('Water-Meter'!AJ10<0,"0",'Water-Meter'!AJ10) -> 24 | W6: ='Water-Meter'!AN10 -> 103 | X6: =Total!K6 -> 8
A7: Serengeti | B7: =B6+1 -> 6 | C7: 9 | D7: 2020 | E7: ='UTILITY REPORT 1'!I8 -> 0 | F7: ='UTILITY REPORT 1'!E8 -> 938.54 | G7: ='UTILITY REPORT 1'!F8 -> 2052 | H7: =IF('Kit report'!F9<0,"0",'Kit report'!F9) -> 144 | I7: =IF('Kit report'!X9<0,"0",'Kit report'!X9) -> 60 | J7: =IF('Utility summery'!H11<0,"0",'Utility summery'!H11) -> 35 | K7: =IF('UTILITY REPORT 1'!H8<0,"0",'UTILITY REPORT 1'!H8) -> 68 | L7: ='Water-Meter'!K11 -> 1 | M7: ='Water-Meter'!H11 -> 0 | N7: ='Water-Meter'!Q11 -> 2 | O7: =K7*E7+H7*I7+#REF!*#REF!+J7*L7 -> #REF! | P7: ='Water-Meter'!E11 -> 52 | Q7: =IF('Water-Meter'!U11<0,"0",'Water-Meter'!U11) -> 13 | R7: =IF('Water-Meter'!X11<0,"0",'Water-Meter'!X11) -> 0 | S7: =IF('Water-Meter'!AA11<0,"0",'Water-Meter'!AA11) -> 33 | T7: =IF('Water-Meter'!AD11<0,"0",'Water-Meter'!AD11) -> 15 | U7: =IF('Water-Meter'!AG11<0,"0",'Water-Meter'!AG11) -> 0 | V7: =IF('Water-Meter'!AJ11<0,"0",'Water-Meter'!AJ11) -> 22 | W7: ='Water-Meter'!AN11 -> 83 | X7: =Total!K7 -> 7
A8: Serengeti | B8: =B7+1 -> 7 | C8: 9 | D8: 2020 | E8: ='UTILITY REPORT 1'!I9 -> 258.14 | F8: ='UTILITY REPORT 1'!E9 -> 910.27 | G8: ='UTILITY REPORT 1'!F9 -> 2010 | H8: =IF('Kit report'!F10<0,"0",'Kit report'!F10) -> 192 | I8: =IF('Kit report'!X10<0,"0",'Kit report'!X10) -> 40 | J8: =IF('Utility summery'!H12<0,"0",'Utility summery'!H12) -> 44 | K8: =IF('UTILITY REPORT 1'!H9<0,"0",'UTILITY REPORT 1'!H9) -> 45 | L8: ='Water-Meter'!K12 -> 1 | M8: ='Water-Meter'!H12 -> 0 | N8: ='Water-Meter'!Q12 -> 1 | O8: =K8*E8+H8*I8+#REF!*#REF!+J8*L8 -> #REF! | P8: ='Water-Meter'!E12 -> 58 | Q8: =IF('Water-Meter'!U12<0,"0",'Water-Meter'!U12) -> 21 | R8: =IF('Water-Meter'!X12<0,"0",'Water-Meter'!X12) -> 0 | S8: =IF('Water-Meter'!AA12<0,"0",'Water-Meter'!AA12) -> 43 | T8: =IF('Water-Meter'!AD12<0,"0",'Water-Meter'!AD12) -> 17 | U8: =IF('Water-Meter'!AG12<0,"0",'Water-Meter'!AG12) -> 0 | V8: =IF('Water-Meter'!AJ12<0,"0",'Water-Meter'!AJ12) -> 25 | W8: ='Water-Meter'!AN12 -> 106 | X8: =Total!K8 -> 3
A9: Serengeti | B9: =B8+1 -> 8 | C9: 9 | D9: 2020 | E9: ='UTILITY REPORT 1'!I10 -> 123.3 | F9: ='UTILITY REPORT 1'!E10 -> 948.21 | G9: ='UTILITY REPORT 1'!F10 -> 2245 | H9: =IF('Kit report'!F11<0,"0",'Kit report'!F11) -> 192 | I9: =IF('Kit report'!X11<0,"0",'Kit report'!X11) -> 60 | J9: =IF('Utility summery'!H13<0,"0",'Utility summery'!H13) -> 35 | K9: =IF('UTILITY REPORT 1'!H10<0,"0",'UTILITY REPORT 1'!H10) -> 54 | L9: ='Water-Meter'!K13 -> 1 | M9: ='Water-Meter'!H13 -> 0 | N9: ='Water-Meter'!Q13 -> 4 | O9: =K9*E9+H9*I9+#REF!*#REF!+J9*L9 -> #REF! | P9: ='Water-Meter'!E13 -> 46 | Q9: =IF('Water-Meter'!U13<0,"0",'Water-Meter'!U13) -> 62 | R9: =IF('Water-Meter'!X13<0,"0",'Water-Meter'!X13) -> 0 | S9: =IF('Water-Meter'!AA13<0,"0",'Water-Meter'!AA13) -> 38 | T9: =IF('Water-Meter'!AD13<0,"0",'Water-Meter'!AD13) -> 15 | U9: =IF('Water-Meter'!AG13<0,"0",'Water-Meter'!AG13) -> 0 | V9: =IF('Water-Meter'!AJ13<0,"0",'Water-Meter'!AJ13) -> 23 | W9: ='Water-Meter'!AN13 -> 138 | X9: =Total!K9 -> 7
A10: Serengeti | B10: =B9+1 -> 9 | C10: 9 | D10: 2020 | E10: ='UTILITY REPORT 1'!I11 -> 0 | F10: ='UTILITY REPORT 1'!E11 -> 916.33 | G10: ='UTILITY REPORT 1'!F11 -> 2101 | H10: =IF('Kit report'!F12<0,"0",'Kit report'!F12) -> 192 | I10: =IF('Kit report'!X12<0,"0",'Kit report'!X12) -> 0 | J10: =IF('Utility summery'!H14<0,"0",'Utility summery'!H14) -> 39 | K10: =IF('UTILITY REPORT 1'!H11<0,"0",'UTILITY REPORT 1'!H11) -> 46 | L10: ='Water-Meter'!K14 -> 2 | M10: ='Water-Meter'!H14 -> 0 | N10: ='Water-Meter'!Q14 -> 1 | O10: =K10*E10+H10*I10+#REF!*#REF!+J10*L10 -> #REF! | P10: ='Water-Meter'!E14 -> 52 | Q10: =IF('Water-Meter'!U14<0,"0",'Water-Meter'!U14) -> 17 | R10: =IF('Water-Meter'!X14<0,"0",'Water-Meter'!X14) -> 0 | S10: =IF('Water-Meter'!AA14<0,"0",'Water-Meter'!AA14) -> 37 | T10: =IF('Water-Meter'!AD14<0,"0",'Water-Meter'!AD14) -> 17 | U10: =IF('Water-Meter'!AG14<0,"0",'Water-Meter'!AG14) -> 0 | V10: =IF('Water-Meter'!AJ14<0,"0",'Water-Meter'!AJ14) -> 21 | W10: ='Water-Meter'!AN14 -> 92 | X10: =Total!K10 -> 5
A11: Serengeti | B11: =B10+1 -> 10 | C11: 9 | D11: 2020 | E11: ='UTILITY REPORT 1'!I12 -> 0 | F11: ='UTILITY REPORT 1'!E12 -> 978.04 | G11: ='UTILITY REPORT 1'!F12 -> 2199 | H11: =IF('Kit report'!F13<0,"0",'Kit report'!F13) -> 204 | I11: =IF('Kit report'!X13<0,"0",'Kit report'!X13) -> 140 | J11: =IF('Utility summery'!H15<0,"0",'Utility summery'!H15) -> 34 | K11: =IF('UTILITY REPORT 1'!H12<0,"0",'UTILITY REPORT 1'!H12) -> 103 | L11: ='Water-Meter'!K15 -> 1 | M11: ='Water-Meter'!H15 -> 0 | N11: ='Water-Meter'!Q15 -> 1 | O11: =K11*E11+H11*I11+#REF!*#REF!+J11*L11 -> #REF! | P11: ='Water-Meter'!E15 -> 55 | Q11: =IF('Water-Meter'!U15<0,"0",'Water-Meter'!U15) -> 20 | R11: =IF('Water-Meter'!X15<0,"0",'Water-Meter'!X15) -> 0 | S11: =IF('Water-Meter'!AA15<0,"0",'Water-Meter'!AA15) -> 38 | T11: =IF('Water-Meter'!AD15<0,"0",'Water-Meter'!AD15) -> 20 | U11: =IF('Water-Meter'!AG15<0,"0",'Water-Meter'!AG15) -> 0 | V11: =IF('Water-Meter'!AJ15<0,"0",'Water-Meter'!AJ15) -> 23 | W11: ='Water-Meter'!AN15 -> 101 | X11: =Total!K11 -> 1
A12: Serengeti | B12: =B11+1 -> 11 | C12: 9 | D12: 2020 | E12: ='UTILITY REPORT 1'!I13 -> 0 | F12: ='UTILITY REPORT 1'!E13 -> 782.55 | G12: ='UTILITY REPORT 1'!F13 -> 2126 | H12: =IF('Kit report'!F14<0,"0",'Kit report'!F14) -> 192 | I12: =IF('Kit report'!X14<0,"0",'Kit report'!X14) -> 20 | J12: =IF('Utility summery'!H16<0,"0",'Utility summery'!H16) -> 29 | K12: =IF('UTILITY REPORT 1'!H13<0,"0",'UTILITY REPORT 1'!H13) -> 1 | L12: ='Water-Meter'!K16 -> 1 | M12: ='Water-Meter'!H16 -> 0 | N12: ='Water-Meter'!Q16 -> 1 | O12: =K12*E12+H12*I12+#REF!*#REF!+J12*L12 -> #REF! | P12: ='Water-Meter'!E16 -> 94 | Q12: =IF('Water-Meter'!U16<0,"0",'Water-Meter'!U16) -> 21 | R12: =IF('Water-Meter'!X16<0,"0",'Water-Meter'!X16) -> 0 | S12: =IF('Water-Meter'!AA16<0,"0",'Water-Meter'!AA16) -> 37 | T12: =IF('Water-Meter'!AD16<0,"0",'Water-Meter'!AD16) -> 20 | U12: =IF('Water-Meter'!AG16<0,"0",'Water-Meter'!AG16) -> 0 | V12: =IF('Water-Meter'!AJ16<0,"0",'Water-Meter'!AJ16) -> 23 | W12: ='Water-Meter'!AN16 -> 101 | X12: =Total!K12 -> 3
A13: Serengeti | B13: =B12+1 -> 12 | C13: 9 | D13: 2020 | E13: ='UTILITY REPORT 1'!I14 -> 0 | F13: ='UTILITY REPORT 1'!E14 -> 732.78 | G13: ='UTILITY REPORT 1'!F14 -> 2174 | H13: =IF('Kit report'!F15<0,"0",'Kit report'!F15) -> 180 | I13: =IF('Kit report'!X15<0,"0",'Kit report'!X15) -> 20 | J13: =IF('Utility summery'!H17<0,"0",'Utility summery'!H17) -> 33 | K13: =IF('UTILITY REPORT 1'!H14<0,"0",'UTILITY REPORT 1'!H14) -> 10 | L13: ='Water-Meter'!K17 -> 1 | M13: ='Water-Meter'!H17 -> 0 | N13: ='Water-Meter'!Q17 -> 1 | O13: =K13*E13+H13*I13+#REF!*#REF!+J13*L13 -> #REF! | P13: ='Water-Meter'!E17 -> 59 | Q13: =IF('Water-Meter'!U17<0,"0",'Water-Meter'!U17) -> 9 | R13: =IF('Water-Meter'!X17<0,"0",'Water-Meter'!X17) -> 0 | S13: =IF('Water-Meter'!AA17<0,"0",'Water-Meter'!AA17) -> 36 | T13: =IF('Water-Meter'!AD17<0,"0",'Water-Meter'!AD17) -> 19 | U13: =IF('Water-Meter'!AG17<0,"0",'Water-Meter'!AG17) -> 0 | V13: =IF('Water-Meter'!AJ17<0,"0",'Water-Meter'!AJ17) -> 22 | W13: ='Water-Meter'!AN17 -> 86 | X13: =Total!K13 -> 3
A14: Serengeti | B14: =B13+1 -> 13 | C14: 9 | D14: 2020 | E14: ='UTILITY REPORT 1'!I15 -> 71.04 | F14: ='UTILITY REPORT 1'!E15 -> 935.74 | G14: ='UTILITY REPORT 1'!F15 -> 2113 | H14: =IF('Kit report'!F16<0,"0",'Kit report'!F16) -> 180 | I14: =IF('Kit report'!X16<0,"0",'Kit report'!X16) -> 40 | J14: =IF('Utility summery'!H18<0,"0",'Utility summery'!H18) -> 34 | K14: =IF('UTILITY REPORT 1'!H15<0,"0",'UTILITY REPORT 1'!H15) -> 16 | L14: ='Water-Meter'!K18 -> 1 | M14: ='Water-Meter'!H18 -> 0 | N14: ='Water-Meter'!Q18 -> 1 | O14: =K14*E14+H14*I14+#REF!*#REF!+J14*L14 -> #REF! | P14: ='Water-Meter'!E18 -> 36 | Q14: =IF('Water-Meter'!U18<0,"0",'Water-Meter'!U18) -> 82 | R14: =IF('Water-Meter'!X18<0,"0",'Water-Meter'!X18) -> 0 | S14: =IF('Water-Meter'!AA18<0,"0",'Water-Meter'!AA18) -> 36 | T14: =IF('Water-Meter'!AD18<0,"0",'Water-Meter'!AD18) -> 20 | U14: =IF('Water-Meter'!AG18<0,"0",'Water-Meter'!AG18) -> 0 | V14: =IF('Water-Meter'!AJ18<0,"0",'Water-Meter'!AJ18) -> 23 | W14: ='Water-Meter'!AN18 -> 161 | X14: =Total!K14 -> 3
... A30: Serengeti | B30: =B29+1 -> 29 | C30: 9 | D30: 2020 | E30: ='UTILITY REPORT 1'!I31 -> 0 | F30: ='UTILITY REPORT 1'!E31 -> 0 | G30: ='UTILITY REPORT 1'!F31 -> 0 | H30: =IF('Kit report'!F32<0,"0",'Kit report'!F32) -> 0 | I30: =IF('Kit report'!X32<0,"0",'Kit report'!X32) -> 0 | J30: =IF('Utility summery'!H34<0,"0",'Utility summery'!H34) -> 0 | K30: =IF('UTILITY REPORT 1'!H31<0,"0",'UTILITY REPORT 1'!H31) -> 0 | L30: ='Water-Meter'!K34 -> 0 | M30: ='Water-Meter'!H34 -> 0 | N30: ='Water-Meter'!Q34 -> 0 | O30: =K30*E30+H30*I30+#REF!*#REF!+J30*L30 -> #REF! | P30: ='Water-Meter'!E34 -> 0 | Q30: =IF('Water-Meter'!U34<0,"0",'Water-Meter'!U34) -> 0 | R30: =IF('Water-Meter'!X34<0,"0",'Water-Meter'!X34) -> 0 | S30: =IF('Water-Meter'!AA34<0,"0",'Water-Meter'!AA34) -> 0 | T30: =IF('Water-Meter'!AD34<0,"0",'Water-Meter'!AD34) -> 0 | U30: =IF('Water-Meter'!AG34<0,"0",'Water-Meter'!AG34) -> 0 | V30: =IF('Water-Meter'!AJ34<0,"0",'Water-Meter'!AJ34) -> 0 | W30: ='Water-Meter'!AN34 -> 0 | X30: =Total!K30 -> 5
A31: Serengeti | B31: 30 | C31: 9 | D31: 2020 | E31: ='UTILITY REPORT 1'!I32 -> 0 | F31: ='UTILITY REPORT 1'!E32 -> 0 | G31: ='UTILITY REPORT 1'!F32 -> 0 | H31: =IF('Kit report'!F33<0,"0",'Kit report'!F33) -> 0 | I31: =IF('Kit report'!X33<0,"0",'Kit report'!X33) -> 0 | J31: =IF('Utility summery'!H35<0,"0",'Utility summery'!H35) -> 0 | K31: =IF('UTILITY REPORT 1'!H32<0,"0",'UTILITY REPORT 1'!H32) -> 0 | L31: ='Water-Meter'!K35 -> 0 | M31: ='Water-Meter'!H35 -> 0 | N31: ='Water-Meter'!Q35 -> 0 | O31: =K31*E31+H31*I31+#REF!*#REF!+J31*L31 -> #REF! | P31: ='Water-Meter'!E35 -> 0 | Q31: =IF('Water-Meter'!U35<0,"0",'Water-Meter'!U35) -> 0 | R31: =IF('Water-Meter'!X35<0,"0",'Water-Meter'!X35) -> 0 | S31: =IF('Water-Meter'!AA35<0,"0",'Water-Meter'!AA35) -> 0 | T31: =IF('Water-Meter'!AD35<0,"0",'Water-Meter'!AD35) -> 0 | U31: =IF('Water-Meter'!AG35<0,"0",'Water-Meter'!AG35) -> 0 | V31: =IF('Water-Meter'!AJ35<0,"0",'Water-Meter'!AJ35) -> 0 | W31: ='Water-Meter'!AN35 -> 0 | X31: =Total!K31 -> 0
E32: ='UTILITY REPORT 1'!I33 -> 0 | F32: ='UTILITY REPORT 1'!E33 -> 0 | G32: ='UTILITY REPORT 1'!F33 -> 0 | H32: =IF('Kit report'!F34<0,"0",'Kit report'!F34) -> 0 | I32: =IF('Kit report'!X34<0,"0",'Kit report'!X34) -> 0 | J32: =IF('Utility summery'!H36<0,"0",'Utility summery'!H36) -> 0 | K32: =IF('UTILITY REPORT 1'!H33<0,"0",'UTILITY REPORT 1'!H33) -> 0 | L32: ='Water-Meter'!K36 -> 0 | M32: ='Water-Meter'!H36 -> 0 | N32: ='Water-Meter'!Q36 -> 0 | P32: ='Water-Meter'!E36 -> 0 | Q32: =IF('Water-Meter'!U36<0,"0",'Water-Meter'!U36) -> 0 | R32: =IF('Water-Meter'!X36<0,"0",'Water-Meter'!X36) -> 0 | S32: =IF('Water-Meter'!AA36<0,"0",'Water-Meter'!AA36) -> 0 | T32: =IF('Water-Meter'!AD36<0,"0",'Water-Meter'!AD36) -> 0 | U32: =IF('Water-Meter'!AG36<0,"0",'Water-Meter'!AG36) -> 0 | V32: =IF('Water-Meter'!AJ36<0,"0",'Water-Meter'!AJ36) -> 0 | W32: ='Water-Meter'!AN36 -> 0 | X32: =Total!K32 -> 0

Sheet UTILITY REPORT 1
A1: UTILITY REPORT
A2: Date | B2: % | C2: Guest Rooms Occupied | D2: Diesel cost Per Liter ($) | E2: Diesel consumption (LT) | F2: Power production (KW) | G2: Water consumption (M3) | H2: RO prodution (M3) | I2: Transport Consupmtion (LT)
A3: =Gen!B11 -> 44075 | B3: =Gen!C11 -> 0.039 | C3: ='Summery Report'!E5 -> 3 | D3: 1 | E3: =Gen!T11 -> 891.43 | F3: =Gen!U11 -> 2111 | G3: ='Water-Meter'!E6 -> 56 | H3: ='Utility report '!AC6 -> 74 | I3: =Gen!AK11 -> 69.21
A4: =Gen!B12 -> 44076 | B4: =Gen!C12 -> 0.039 | C4: ='Summery Report'!E6 -> 4 | D4: 1 | E4: =Gen!T12 -> 821.92 | F4: =Gen!U12 -> 2147 | G4: ='Water-Meter'!E7 -> 58 | H4: ='Utility report '!AC7 -> 26 | I4: =Gen!AK12 -> 80.65
A5: =Gen!B13 -> 44077 | B5: =Gen!C13 -> 0.039 | C5: ='Summery Report'!E7 -> 4 | D5: 1 | E5: =Gen!T13 -> 1090.28 | F5: =Gen!U13 -> 2188 | G5: ='Water-Meter'!E8 -> 51 | H5: ='Utility report '!AC8 -> 79 | I5: =Gen!AK13 -> 10.02
A6: =Gen!B14 -> 44078 | B6: =Gen!C14 -> 0.0909 | C6: ='Summery Report'!E8 -> 8 | D6: 1 | E6: =Gen!T14 -> 868.39 | F6: =Gen!U14 -> 2448 | G6: ='Water-Meter'!E9 -> 54 | H6: ='Utility report '!AC9 -> 92 | I6: =Gen!AK14 -> 0
A7: =Gen!B15 -> 44079 | B7: =Gen!C15 -> 0.0909 | C7: ='Summery Report'!E9 -> 8 | D7: 1 | E7: =Gen!T15 -> 841.98 | F7: =Gen!U15 -> 2152 | G7: ='Water-Meter'!E10 -> 50 | H7: ='Utility report '!AC10 -> 1 | I7: =Gen!AK15 -> 27.01
A8: =Gen!B16 -> 44080 | B8: =Gen!C16 -> 0.0909 | C8: ='Summery Report'!E10 -> 7 | D8: 1 | E8: =Gen!T16 -> 938.54 | F8: =Gen!U16 -> 2052 | G8: ='Water-Meter'!E11 -> 52 | H8: ='Utility report '!AC11 -> 68 | I8: =Gen!AK16 -> 0
A9: =Gen!B17 -> 44081 | B9: =Gen!C17 -> 0.026 | C9: ='Summery Report'!E11 -> 3 | D9: 1 | E9: =Gen!T17 -> 910.27 | F9: =Gen!U17 -> 2010 | G9: ='Water-Meter'!E12 -> 58 | H9: ='Utility report '!AC12 -> 45 | I9: =Gen!AK17 -> 258.14
A10: =Gen!B18 -> 44082 | B10: =Gen!C18 -> 0.039 | C10: ='Summery Report'!E12 -> 7 | D10: 1 | E10: =Gen!T18 -> 948.21 | F10: =Gen!U18 -> 2245 | G10: ='Water-Meter'!E13 -> 46 | H10: ='Utility report '!AC13 -> 54 | I10: =Gen!AK18 -> 123.3
A11: =Gen!B19 -> 44083 | B11: =Gen!C19 -> 0.065 | C11: ='Summery Report'!E13 -> 5 | D11: 1 | E11: =Gen!T19 -> 916.33 | F11: =Gen!U19 -> 2101 | G11: ='Water-Meter'!E14 -> 52 | H11: ='Utility report '!AC14 -> 46 | I11: =Gen!AK19 -> 0
A12: =Gen!B20 -> 44084 | B12: =Gen!C20 -> 0.013 | C12: ='Summery Report'!E14 -> 1 | D12: 1 | E12: =Gen!T20 -> 978.04 | F12: =Gen!U20 -> 2199 | G12: ='Water-Meter'!E15 -> 55 | H12: ='Utility report '!AC15 -> 103 | I12: =Gen!AK20 -> 0
A13: =Gen!B21 -> 44085 | B13: =Gen!C21 -> 0.039 | C13: ='Summery Report'!E15 -> 3 | D13: 1 | E13: =Gen!T21 -> 782.55 | F13: =Gen!U21 -> 2126 | G13: ='Water-Meter'!E16 -> 94 | H13: ='Utility report '!AC16 -> 1 | I13: =Gen!AK21 -> 0
A14: =Gen!B22 -> 44086 | B14: =Gen!C22 -> 0.02 | C14: ='Summery Report'!E16 -> 3 | D14: 1 | E14: =Gen!T22 -> 732.78 | F14: =Gen!U22 -> 2174 | G14: ='Water-Meter'!E17 -> 59 | H14: ='Utility report '!AC17 -> 10 | I14: =Gen!AK22 -> 0
... A33: =Gen!B41 -> 0 | B33: =Gen!C41 -> 0 | C33: ='Summery Report'!E35 -> 0 | D33: 1 | E33: =Gen!T41 -> 0 | F33: =Gen!U41 -> 0 | G33: ='Water-Meter'!E36 -> 0 | H33: ='Utility report '!AC36 -> 0 | I33: =Gen!AK41 -> 0
B34: =Gen!C42 -> 0 | C34: ='Summery Report'!E36 -> 0 | D34: 2 | E34: =Gen!T42 -> 0 | F34: =Gen!U42 -> 0 | G34: ='Water-Meter'!E37 -> 0 | H34: ='Utility report '!AC37 -> 0 | I34: =Gen!AK42 -> 0

Sheet Utility summery
A4: Date | B4: Room Occupied | C4: Electricity Units Generated KW | D4: Diseal | G4: Water | J4: Gas | N4: Cost of utilites
D5: Generator | E5: Transport | F5: Total | G5: RO | H5: STP | I5: Total Consumption | J5: 2 ton | K5: 1 Ton | L5: 1 Ton | M5: Total consumption | N5: Electricity /1.4$/liter | O5: Diseal for Transport | P5: Gas /2.38$/Kg | Q5: Total HLP Cost | R5: Electricity Cost/Room $ | S5: cost/Room $
A6: =Gen!B11 -> 44075 | B6: ='Summery Report'!E5 -> 3 | C6: =Gen!U11 -> 2111 | D6: =Gen!T11 -> 891.43 | E6: =Gen!AK11 -> 69.21 | F6: =Gen!AS11 -> 960.64 | G6: ='Utility report '!AC6 -> 74 | H6: ='Utility report '!AE6 -> 47 | I6: ='Water-Meter'!E6 -> 56 | J6: ='Lpg (2)'!B10 -> 85 | K6: ='Lpg (2)'!C10 -> 85 | L6: ='Lpg (2)'!D10 -> 2 | M6: ='Lpg (2)'!G10 -> 76.032 | O6: =E6 -> 69.21 | P6: ='[1]Lpg (2)'!#REF! -> #REF! | Q6: ='[1]Summery Report'!#REF! -> #REF! | R6: =N6/B6 -> 0 | S6: =Q6/B6 -> #REF!
A7: =Gen!B12 -> 44076 | B7: ='Summery Report'!E6 -> 4 | C7: =Gen!U12 -> 2147 | D7: =Gen!T12 -> 821.92 | E7: =Gen!AK12 -> 80.65 | F7: =Gen!AS12 -> 902.57 | G7: ='Utility report '!AC7 -> 26 | H7: ='Utility report '!AE7 -> 30 | I7: ='Water-Meter'!E7 -> 58 | J7: ='Lpg (2)'!B11 -> 85 | K7: ='Lpg (2)'!C11 -> 85 | L7: ='Lpg (2)'!D11 -> 2 | M7: ='Lpg (2)'!G11 -> 58.608 | N7: =D7*1.4 -> 1150.688 | O7: =E7*1.4 -> 112.91 | P7: ='[1]Lpg (2)'!#REF! -> #REF! | Q7: ='[1]Summery Report'!#REF! -> #REF! | R7: =N7/B7 -> 287.672 | S7: =Q7/B7 -> #REF!
A8: =Gen!B13 -> 44077 | B8: ='Summery Report'!E7 -> 4 | C8: =Gen!U13 -> 2188 | D8: =Gen!T13 -> 1090.28 | E8: =Gen!AK13 -> 10.02 | F8: =Gen!AS13 -> 1100.3 | G8: ='Utility report '!AC8 -> 79 | H8: ='Utility report '!AE8 -> 36 | I8: ='Water-Meter'!E8 -> 51 | J8: ='Lpg (2)'!B12 -> 85 | K8: ='Lpg (2)'!C12 -> 85 | L8: ='Lpg (2)'!D12 -> 1 | M8: ='Lpg (2)'!G12 -> 66.264 | N8: =D8*1.4 -> 1526.392 | O8: =E8*1.4 -> 14.028 | P8: ='[1]Lpg (2)'!#REF! -> #REF! | Q8: ='[1]Summery Report'!#REF! -> #REF! | R8: =N8/B8 -> 381.598 | S8: =Q8/B8 -> #REF!
A9: =Gen!B14 -> 44078 | B9: ='Summery Report'!E8 -> 8 | C9: =Gen!U14 -> 2448 | D9: =Gen!T14 -> 868.39 | E9: =Gen!AK14 -> 0 | F9: =Gen!AS14 -> 868.39 | G9: ='Utility report '!AC9 -> 92 | H9: ='Utility report '!AE9 -> 45 | I9: ='Water-Meter'!E9 -> 54 | J9: ='Lpg (2)'!B13 -> 85 | K9: ='Lpg (2)'!C13 -> 85 | L9: ='Lpg (2)'!D13 -> 1 | M9: ='Lpg (2)'!G13 -> 63.536 | N9: =D9*1.4 -> 1215.746 | O9: =E9*1.4 -> 0 | P9: ='[1]Lpg (2)'!#REF! -> #REF! | Q9: ='[1]Summery Report'!#REF! -> #REF! | R9: =N9/B9 -> 151.96825 | S9: =Q9/B9 -> #REF!
A10: =Gen!B15 -> 44079 | B10: ='Summery Report'!E9 -> 8 | C10: =Gen!U15 -> 2152 | D10: =Gen!T15 -> 841.98 | E10: =Gen!AK15 -> 27.01 | F10: =Gen!AS15 -> 868.99 | G10: ='Utility report '!AC10 -> 1 | H10: ='Utility report '!AE10 -> 43 | I10: ='Water-Meter'!E10 -> 50 | J10: ='Lpg (2)'!B14 -> 85 | K10: ='Lpg (2)'!C14 -> 85 | L10: ='Lpg (2)'!D14 -> 1 | M10: ='Lpg (2)'!G14 -> 50.072 | N10: =D10*1.4 -> 1178.772 | O10: =E10*1.4 -> 37.814 | P10: ='[1]Lpg (2)'!#REF! -> #REF! | Q10: ='[1]Summery Report'!#REF! -> #REF! | R10: =N10/B10 -> 147.3465 | S10: =Q10/B10 -> #REF!
A11: =Gen!B16 -> 44080 | B11: ='Summery Report'!E10 -> 7 | C11: =Gen!U16 -> 2052 | D11: =Gen!T16 -> 938.54 | E11: =Gen!AK16 -> 0 | F11: =Gen!AS16 -> 938.54 | G11: ='Utility report '!AC11 -> 68 | H11: ='Utility report '!AE11 -> 35 | I11: ='Water-Meter'!E11 -> 52 | J11: ='Lpg (2)'!B15 -> 85 | K11: ='Lpg (2)'!C15 -> 85 | L11: ='Lpg (2)'!D15 -> 1 | M11: ='Lpg (2)'!G15 -> 49.588 | N11: =D11*1.4 -> 1313.956 | O11: =E11*1.4 -> 0 | P11: ='[1]Lpg (2)'!#REF! -> #REF! | Q11: ='[1]Summery Report'!#REF! -> #REF! | R11: =N11/B11 -> 187.708 | S11: =Q11/B11 -> #REF!
A12: =Gen!B17 -> 44081 | B12: ='Summery Report'!E11 -> 3 | C12: =Gen!U17 -> 2010 | D12: =Gen!T17 -> 910.27 | E12: =Gen!AK17 -> 258.14 | F12: =Gen!AS17 -> 1168.41 | G12: ='Utility report '!AC12 -> 45 | H12: ='Utility report '!AE12 -> 44 | I12: ='Water-Meter'!E12 -> 58 | J12: ='Lpg (2)'!B16 -> 85 | K12: ='Lpg (2)'!C16 -> 85 | L12: ='Lpg (2)'!D16 -> 0 | M12: ='Lpg (2)'!G16 -> 62.568 | N12: =D12*1.4 -> 1274.378 | O12: =E12*1.4 -> 361.396 | P12: ='[1]Lpg (2)'!#REF! -> #REF! | Q12: ='[1]Summery Report'!#REF! -> #REF! | R12: =N12/B12 -> 424.79267 | S12: =Q12/B12 -> #REF!
A13: =Gen!B18 -> 44082 | B13: ='Summery Report'!E12 -> 7 | C13: =Gen!U18 -> 2245 | D13: =Gen!T18 -> 948.21 | E13: =Gen!AK18 -> 123.3 | F13: =Gen!AS18 -> 1071.51 | G13: ='Utility report '!AC13 -> 54 | H13: ='Utility report '!AE13 -> 35 | I13: ='Water-Meter'!E13 -> 46 | J13: ='Lpg (2)'!B17 -> 85 | K13: ='Lpg (2)'!C17 -> 81 | L13: ='Lpg (2)'!D17 -> 0 | M13: ='Lpg (2)'!G17 -> 54.868 | N13: =D13*1.4 -> 1327.494 | O13: =E13*1.4 -> 172.62 | P13: ='[1]Lpg (2)'!#REF! -> #REF! | Q13: ='[1]Summery Report'!#REF! -> #REF! | R13: =N13/B13 -> 189.642 | S13: =Q13/B13 -> #REF!
A14: =Gen!B19 -> 44083 | B14: ='Summery Report'!E13 -> 5 | C14: =Gen!U19 -> 2101 | D14: =Gen!T19 -> 916.33 | E14: =Gen!AK19 -> 0 | F14: =Gen!AS19 -> 916.33 | G14: ='Utility report '!AC14 -> 46 | H14: ='Utility report '!AE14 -> 39 | I14: ='Water-Meter'!E14 -> 52 | J14: ='Lpg (2)'!B18 -> 85 | K14: ='Lpg (2)'!C18 -> 75 | L14: ='Lpg (2)'!D18 -> 0 | M14: ='Lpg (2)'!G18 -> 57.42 | N14: =D14*1.4 -> 1282.862 | O14: =E14*1.4 -> 0 | P14: ='[1]Lpg (2)'!#REF! -> #REF! | Q14: ='[1]Summery Report'!#REF! -> #REF! | R14: =N14/B14 -> 256.5724 | S14: =Q14/B14 -> #REF!
A15: =Gen!B20 -> 44084 | B15: ='Summery Report'!E14 -> 1 | C15: =Gen!U20 -> 2199 | D15: =Gen!T20 -> 978.04 | E15: =Gen!AK20 -> 0 | F15: =Gen!AS20 -> 978.04 | G15: ='Utility report '!AC15 -> 103 | H15: ='Utility report '!AE15 -> 34 | I15: ='Water-Meter'!E15 -> 55 | J15: ='Lpg (2)'!B19 -> 85 | K15: ='Lpg (2)'!C19 -> 72 | L15: ='Lpg (2)'!D19 -> 0 | M15: ='Lpg (2)'!G19 -> 44 | N15: =D15*1.4 -> 1369.256 | O15: =E15*1.4 -> 0 | P15: ='[1]Lpg (2)'!#REF! -> #REF! | Q15: ='[1]Summery Report'!#REF! -> #REF! | R15: =N15/B15 -> 1369.256 | S15: =Q15/B15 -> #REF!
A16: =Gen!B21 -> 44085 | B16: ='Summery Report'!E15 -> 3 | C16: =Gen!U21 -> 2126 | D16: =Gen!T21 -> 782.55 | E16: =Gen!AK21 -> 0 | F16: =Gen!AS21 -> 782.55 | G16: ='Utility report '!AC16 -> 1 | H16: ='Utility report '!AE16 -> 29 | I16: ='Water-Meter'!E16 -> 94 | J16: ='Lpg (2)'!B20 -> 85 | K16: ='Lpg (2)'!C20 -> 68 | L16: ='Lpg (2)'!D20 -> 0 | M16: ='Lpg (2)'!G20 -> 70.928 | N16: =D16*1.4 -> 1095.57 | O16: =E16*1.4 -> 0 | P16: ='[1]Lpg (2)'!#REF! -> #REF! | Q16: ='[1]Summery Report'!#REF! -> #REF! | R16: =N16/B16 -> 365.19 | S16: =Q16/B16 -> #REF!
A17: =Gen!B22 -> 44086 | B17: ='Summery Report'!E16 -> 3 | C17: =Gen!U22 -> 2174 | D17: =Gen!T22 -> 732.78 | E17: =Gen!AK22 -> 0 | F17: =Gen!AS22 -> 732.78 | G17: ='Utility report '!AC17 -> 10 | H17: ='Utility report '!AE17 -> 33 | I17: ='Water-Meter'!E17 -> 59 | J17: ='Lpg (2)'!B21 -> 85 | K17: ='Lpg (2)'!C22 -> 58 | L17: ='Lpg (2)'!D21 -> 0 | M17: ='Lpg (2)'!G21 -> 53.9 | N17: =D17*1.4 -> 1025.892 | O17: =E17*1.4 -> 0 | P17: ='[1]Lpg (2)'!#REF! -> #REF! | Q17: ='[1]Summery Report'!#REF! -> #REF! | R17: =N17/B17 -> 341.964 | S17: =Q17/B17 -> #REF!
A18: =Gen!B23 -> 44087 | B18: ='Summery Report'!E17 -> 3 | C18: =Gen!U23 -> 2113 | D18: =Gen!T23 -> 935.74 | E18: =Gen!AK23 -> 71.04 | F18: =Gen!AS23 -> 1006.78 | G18: ='Utility report '!AC18 -> 16 | H18: ='Utility report '!AE18 -> 34 | I18: ='Water-Meter'!E18 -> 36 | J18: ='Lpg (2)'!B22 -> 85 | K18: ='Lpg (2)'!C23 -> 52 | L18: ='Lpg (2)'!D22 -> 0 | M18: ='Lpg (2)'!G22 -> 55.396 | N18: =D18*1.4 -> 1310.036 | O18: =E18*1.4 -> 99.456 | P18: ='[1]Lpg (2)'!#REF! -> #REF! | Q18: ='[1]Summery Report'!#REF! -> #REF! | R18: =N18/B18 -> 436.67867 | S18: =Q18/B18 -> #REF!
A19: =Gen!B24 -> 44088 | B19: ='Summery Report'!E18 -> 4 | C19: =Gen!U24 -> 2040 | D19: =Gen!T24 -> 890.09 | E19: =Gen!AK24 -> 0 | F19: =Gen!AS24 -> 890.09 | G19: ='Utility report '!AC19 -> 33 | H19: ='Utility report '!AE19 -> 34 | I19: ='Water-Meter'!E19 -> 53 | J19: ='Lpg (2)'!B23 -> 85 | K19: ='Lpg (2)'!C24 -> 50 | L19: ='Lpg (2)'!D23 -> 0 | M19: ='Lpg (2)'!G23 -> 56.452 | N19: =D19*1.4 -> 1246.126 | O19: =E19*1.4 -> 0 | P19: ='[1]Lpg (2)'!#REF! -> #REF! | Q19: ='[1]Summery Report'!#REF! -> #REF! | R19: =N19/B19 -> 311.5315 | S19: =Q19/B19 -> #REF!
A20: =Gen!B25 -> 44089 | B20: ='Summery Report'!E19 -> 4 | C20: =Gen!U25 -> 2084 | D20: =Gen!T25 -> 888.98 | E20: =Gen!AK25 -> 0 | F20: =Gen!AS25 -> 888.98 | G20: ='Utility report '!AC20 -> 41 | H20: ='Utility report '!AE20 -> 36 | I20: ='Water-Meter'!E20 -> 40 | J20: ='Lpg (2)'!B24 -> 85 | K20: ='Lpg (2)'!C25 -> 43 | L20: ='Lpg (2)'!D24 -> 0 | M20: ='Lpg (2)'!G24 -> 52.052 | N20: =D20*1.4 -> 1244.572 | O20: =E20*1.4 -> 0 | P20: ='[1]Lpg (2)'!#REF! -> #REF! | Q20: ='[1]Summery Report'!#REF! -> #REF! | R20: =N20/B20 -> 311.143 | S20: =Q20/B20 -> #REF!
A21: =Gen!B26 -> 44090 | B21: ='Summery Report'!E20 -> 11 | C21: =Gen!U26 -> 2489 | D21: =Gen!T26 -> 1095.46 | E21: =Gen!AK26 -> 181.14 | F21: =Gen!AS26 -> 1276.6 | G21: ='Utility report '!AC21 -> 16 | H21: ='Utility report '!AE21 -> 36 | I21: ='Water-Meter'!E21 -> 30 | J21: ='Lpg (2)'!B25 -> 85 | K21: ='Lpg (2)'!C25 -> 43 | L21: ='Lpg (2)'!D25 -> 0 | M21: ='Lpg (2)'!G25 -> 49.192 | N21: =D21*1.4 -> 1533.644 | O21: =E21*1.4 -> 253.596 | P21: ='[1]Lpg (2)'!#REF! -> #REF! | Q21: ='[1]Summery Report'!#REF! -> #REF! | R21: =N21/B21 -> 139.42218 | S21: =Q21/B21 -> #REF!
A22: =Gen!B27 -> 44091 | B22: ='Summery Report'!E21 -> 10 | C22: =Gen!U27 -> 2499 | D22: =Gen!T27 -> 1018.07 | E22: =Gen!AK27 -> 25.41 | F22: =Gen!AS27 -> 1043.48 | G22: ='Utility report '!AC22 -> 55 | H22: ='Utility report '!AE22 -> 37 | I22: ='Water-Meter'!E22 -> 49 | J22: ='Lpg (2)'!B26 -> 85 | K22: ='Lpg (2)'!C26 -> 40 | L22: ='Lpg (2)'!D26 -> 0 | M22: ='Lpg (2)'!G26 -> 55.088 | N22: =D22*1.4 -> 1425.298 | O22: =E22*1.4 -> 35.574 | P22: ='[1]Lpg (2)'!#REF! -> #REF! | Q22: ='[1]Summery Report'!#REF! -> #REF! | R22: =N22/B22 -> 142.5298 | S22: =Q22/B22 -> #REF!
A23: =Gen!B28 -> 44092 | B23: ='Summery Report'!E22 -> 12 | C23: =Gen!U28 -> 2622 | D23: =Gen!T28 -> 1041.27 | E23: =Gen!AK28 -> 0 | F23: =Gen!AS28 -> 1041.27 | G23: ='Utility report '!AC23 -> 20 | H23: ='Utility report '!AE23 -> 34 | I23: ='Water-Meter'!E23 -> 50 | J23: ='Lpg (2)'!B27 -> 85 | K23: ='Lpg (2)'!C27 -> 38 | L23: ='Lpg (2)'!D27 -> 0 | M23: ='Lpg (2)'!G27 -> 65.34 | N23: =D23*1.4 -> 1457.778 | O23: =E23*1.4 -> 0 | P23: ='[1]Lpg (2)'!#REF! -> #REF! | Q23: ='[1]Summery Report'!#REF! -> #REF! | R23: =N23/B23 -> 121.4815 | S23: =Q23/B23 -> #REF!
A24: =Gen!B29 -> 44093 | B24: ='Summery Report'!E23 -> 8 | C24: =Gen!U29 -> 2500 | D24: =Gen!T29 -> 1129.88 | E24: =Gen!AK29 -> 374.38 | F24: =Gen!AS29 -> 1504.26 | G24: ='Utility report '!AC24 -> 42 | H24: ='Utility report '!AE24 -> 32 | I24: ='Water-Meter'!E24 -> 51 | J24: ='Lpg (2)'!B28 -> 85 | K24: ='Lpg (2)'!C28 -> 30 | L24: ='Lpg (2)'!D28 -> 0 | M24: ='Lpg (2)'!G28 -> 65.428 | N24: =D24*1.4 -> 1581.832 | O24: =E24*1.4 -> 524.132 | P24: ='[1]Lpg (2)'!#REF! -> #REF! | Q24: ='[1]Summery Report'!#REF! -> #REF! | R24: =N24/B24 -> 197.729 | S24: =Q24/B24 -> #REF!
A25: =Gen!B30 -> 44094 | B25: ='Summery Report'!E24 -> 6 | C25: =Gen!U30 -> 2313 | D25: =Gen!T30 -> 1055.66 | E25: =Gen!AK30 -> 44.98 | F25: =Gen!AS30 -> 1100.64 | G25: ='Utility report '!AC25 -> 0 | H25: ='Utility report '!AE25 -> 38 | I25: ='Water-Meter'!E25 -> 46 | J25: ='Lpg (2)'!B29 -> 85 | K25: ='Lpg (2)'!C29 -> 29 | L25: ='Lpg (2)'!D29 -> 0 | M25: ='Lpg (2)'!G29 -> 69.828 | N25: =D25*1.4 -> 1477.924 | O25: =E25*1.4 -> 62.972 | P25: ='[1]Lpg (2)'!#REF! -> #REF! | Q25: ='[1]Summery Report'!#REF! -> #REF! | R25: =N25/B25 -> 246.32067 | S25: =Q25/B25 -> #REF!
A26: =Gen!B31 -> 44095 | B26: ='Summery Report'!E25 -> 6 | C26: =Gen!U31 -> 2356 | D26: =Gen!T31 -> 957.7 | E26: =Gen!AK31 -> 0 | F26: =Gen!AS31 -> 957.7 | G26: ='Utility report '!AC26 -> 74 | H26: ='Utility report '!AE26 -> 34 | I26: ='Water-Meter'!E26 -> 46 | J26: ='Lpg (2)'!B30 -> 85 | K26: ='Lpg (2)'!C30 -> 25 | L26: ='Lpg (2)'!D30 -> 0 | M26: ='Lpg (2)'!G30 -> 75.68 | N26: =D26*1.4 -> 1340.78 | O26: =E26*1.4 -> 0 | P26: ='[1]Lpg (2)'!#REF! -> #REF! | Q26: ='[1]Summery Report'!#REF! -> #REF! | R26: =N26/B26 -> 223.46333 | S26: =Q26/B26 -> #REF!
A27: =Gen!B32 -> 44096 | B27: ='Summery Report'!E26 -> 3 | C27: =Gen!U32 -> 2289 | D27: =Gen!T32 -> 982.5 | E27: =Gen!AK32 -> 0 | F27: =Gen!AS32 -> 982.5 | G27: ='Utility report '!AC27 -> 44 | H27: ='Utility report '!AE27 -> 38 | I27: ='Water-Meter'!E27 -> 56 | J27: ='Lpg (2)'!B31 -> 85 | K27: ='Lpg (2)'!C31 -> 23 | L27: ='Lpg (2)'!D31 -> 0 | M27: ='Lpg (2)'!G31 -> 55.748 | N27: =D27*1.4 -> 1375.5 | O27: =E27*1.4 -> 0 | P27: ='[1]Lpg (2)'!#REF! -> #REF! | Q27: ='[1]Summery Report'!#REF! -> #REF! | R27: =N27/B27 -> 458.5 | S27: =Q27/B27 -> #REF!
A28: =Gen!B33 -> 44097 | B28: ='Summery Report'!E27 -> 3 | C28: =Gen!U33 -> 2286 | D28: =Gen!T33 -> 989.79 | E28: =Gen!AK33 -> 187.28 | F28: =Gen!AS33 -> 1177.07 | G28: ='Utility report '!AC28 -> 47 | H28: ='Utility report '!AE28 -> 31 | I28: ='Water-Meter'!E28 -> 49 | J28: ='Lpg (2)'!B32 -> 85 | K28: ='Lpg (2)'!C32 -> 20 | L28: ='Lpg (2)'!D32 -> 0 | M28: ='Lpg (2)'!G32 -> 39.204 | N28: =D28*1.4 -> 1385.706 | O28: =E28*1.4 -> 262.192 | P28: ='[1]Lpg (2)'!#REF! -> #REF! | Q28: ='[1]Summery Report'!#REF! -> #REF! | R28: =N28/B28 -> 461.902 | S28: =Q28/B28 -> #REF!
A29: =Gen!B34 -> 44098 | B29: ='Summery Report'!E28 -> 2 | C29: =Gen!U34 -> 2289 | D29: =Gen!T34 -> 1004.25 | E29: =Gen!AK34 -> 0 | F29: =Gen!AS34 -> 1004.25 | G29: ='Utility report '!AC29 -> 56 | H29: ='Utility report '!AE29 -> 36 | I29: ='Water-Meter'!E29 -> 48 | J29: ='Lpg (2)'!B33 -> 85 | K29: ='Lpg (2)'!C33 -> 19 | L29: ='Lpg (2)'!D33 -> 0 | M29: ='Lpg (2)'!G33 -> 72.6 | N29: =D29*1.4 -> 1405.95 | O29: =E29*1.4 -> 0 | P29: ='[1]Lpg (2)'!#REF! -> #REF! | Q29: ='[1]Summery Report'!#REF! -> #REF! | R29: =N29/B29 -> 702.975 | S29: =Q29/B29 -> #REF!
A30: =Gen!B35 -> 44099 | B30: ='Summery Report'!E29 -> 3 | C30: =Gen!U35 -> 2244 | D30: =Gen!T35 -> 1019.08 | E30: =Gen!AK35 -> 74.6 | F30: =Gen!AS35 -> 1093.68 | G30: ='Utility report '!AC30 -> 70 | H30: ='Utility report '!AE30 -> 30 | I30: ='Water-Meter'!E30 -> 50 | J30: ='Lpg (2)'!B34 -> 85 | K30: ='Lpg (2)'!C34 -> 18 | L30: ='Lpg (2)'!D34 -> 0 | M30: ='Lpg (2)'!G34 -> 63.272 | N30: =D30*1.4 -> 1426.712 | O30: =E30*1.4 -> 104.44 | P30: ='[1]Lpg (2)'!#REF! -> #REF! | Q30: ='[1]Summery Report'!#REF! -> #REF! | R30: =N30/B30 -> 475.57067 | S30: =Q30/B30 -> #REF!
A31: =Gen!B36 -> 44100 | B31: ='Summery Report'!E30 -> 4 | C31: =Gen!U36 -> 2313 | D31: =Gen!T36 -> 878.8 | E31: =Gen!AK36 -> 0 | F31: =Gen!AS36 -> 878.8 | G31: ='Utility report '!AC31 -> 47 | H31: ='Utility report '!AE31 -> 33 | I31: ='Water-Meter'!E31 -> 55 | J31: ='Lpg (2)'!B35 -> 85 | K31: ='Lpg (2)'!C35 -> 17 | L31: ='Lpg (2)'!D35 -> 0 | M31: ='Lpg (2)'!G35 -> 63.668 | N31: =D31*1.4 -> 1230.32 | O31: =E31*1.4 -> 0 | P31: ='[1]Lpg (2)'!#REF! -> #REF! | Q31: ='[1]Summery Report'!#REF! -> #REF! | R31: =N31/B31 -> 307.58 | S31: =Q31/B31 -> #REF!
A32: =Gen!B37 -> 44101 | B32: ='Summery Report'!E31 -> 5 | C32: =Gen!U37 -> 2327 | D32: =Gen!T37 -> 975.74 | E32: =Gen!AK37 -> 0 | F32: =Gen!AS37 -> 975.74 | G32: ='Utility report '!AC32 -> 68 | H32: ='Utility report '!AE32 -> 37 | I32: ='Water-Meter'!E32 -> 58 | J32: ='Lpg (2)'!B36 -> 85 | K32: ='Lpg (2)'!C36 -> 16 | L32: ='Lpg (2)'!D36 -> 0 | M32: ='Lpg (2)'!G36 -> 54.692 | N32: =D32*1.4 -> 1366.036 | O32: =E32*1.4 -> 0 | P32: ='[1]Lpg (2)'!#REF! -> #REF! | Q32: ='[1]Summery Report'!#REF! -> #REF! | R32: =N32/B32 -> 273.2072 | S32: =Q32/B32 -> #REF!
A33: =Gen!B38 -> 44102 | B33: ='Summery Report'!E32 -> 5 | C33: =Gen!U38 -> 2289 | D33: =Gen!T38 -> 969.39 | E33: =Gen!AK38 -> 0 | F33: =Gen!AS38 -> 969.39 | G33: ='Utility report '!AC33 -> 46 | H33: ='Utility report '!AE33 -> 35 | I33: ='Water-Meter'!E33 -> 52 | J33: ='Lpg (2)'!B37 -> 85 | K33: ='Lpg (2)'!C37 -> 15 | L33: ='Lpg (2)'!D37 -> 0 | M33: ='Lpg (2)'!G37 -> 75.68 | N33: =D33*1.4 -> 1357.146 | O33: =E33*1.4 -> 0 | P33: ='[1]Lpg (2)'!#REF! -> #REF! | Q33: ='[1]Summery Report'!#REF! -> #REF! | R33: =N33/B33 -> 271.4292 | S33: =Q33/B33 -> #REF! | T33: =3124/13 -> 240.30769
A34: =Gen!B39 -> 44103 | B34: ='Summery Report'!E33 -> 5 | C34: =Gen!U39 -> 0 | D34: =Gen!T39 -> 0 | E34: =Gen!AK39 -> 0 | F34: =Gen!AS39 -> 0 | G34: ='Utility report '!AC34 -> -39082 | H34: ='Utility report '!AE34 -> -205609 | I34: ='Water-Meter'!E34 -> 0 | J34: ='Lpg (2)'!B38 -> 85 | K34: ='Lpg (2)'!C38 -> 14 | L34: ='Lpg (2)'!D38 -> 0 | M34: ='Lpg (2)'!G38 -> -318841.51 | N34: =D34*1.4 -> 0 | O34: =E34*1.4 -> 0 | P34: ='[1]Lpg (2)'!#REF! -> #REF! | Q34: ='[1]Summery Report'!#REF! -> #REF! | R34: =N34/B34 -> 0 | S34: =Q34/B34 -> #REF!
A35: =Gen!B40 -> 44104 | B35: ='Summery Report'!E34 -> 0 | C35: =Gen!U40 -> 0 | D35: =Gen!T40 -> 0 | E35: =Gen!AK40 -> 0 | F35: =Gen!AS40 -> 0 | G35: ='Utility report '!AC35 -> 0 | H35: ='Utility report '!AE35 -> 0 | I35: ='Water-Meter'!E35 -> 0 | J35: ='Lpg (2)'!B39 -> 0 | K35: ='Lpg (2)'!C39 -> 0 | L35: ='Lpg (2)'!D39 -> 0 | M35: ='Lpg (2)'!G39 -> 0 | N35: =D35*1.4 -> 0 | O35: =E35*1.4 -> 0 | P35: ='[1]Lpg (2)'!#REF! -> #REF! | Q35: ='[1]Summery Report'!#REF! -> #REF! | R35: =N35/B35 -> #DIV/0! | S35: =Q35/B35 -> #REF!
A36: =Gen!B41 -> 0 | B36: ='Summery Report'!E35 -> 0 | C36: =Gen!U41 -> 0 | D36: =Gen!T41 -> 0 | E36: =Gen!AK41 -> 0 | F36: =Gen!AS41 -> 0 | G36: ='Utility report '!AC36 -> 0 | H36: ='Utility report '!AE36 -> 0 | I36: ='Water-Meter'!E36 -> 0 | J36: ='Lpg (2)'!B40 -> 0 | K36: ='Lpg (2)'!C40 -> 0 | L36: ='Lpg (2)'!D40 -> 0 | M36: ='Lpg (2)'!G40 -> 0 | N36: =D36*1.4 -> 0 | O36: =E36*1.4 -> 0 | P36: ='[1]Lpg (2)'!#REF! -> #REF! | Q36: ='[1]Summery Report'!#REF! -> #REF! | R36: =N36/B36 -> #DIV/0! | S36: =Q36/B36 -> #REF!
A37: =Gen!B42 -> 0 | B37: ='Summery Report'!E36 -> 0 | C37: =Gen!U42 -> 0 | D37: =Gen!T42 -> 0 | E37: =Gen!AK42 -> 0 | F37: =Gen!AS42 -> 0 | G37: ='Utility report '!AC37 -> 0 | H37: ='Utility report '!AE37 -> 0 | I37: ='Water-Meter'!E37 -> 0 | J37: ='Lpg (2)'!B41 -> 0 | K37: ='Lpg (2)'!C41 -> 0 | L37: ='Lpg (2)'!D41 -> 0 | M37: ='Lpg (2)'!G41 -> 0 | Q37: ='[1]Summery Report'!#REF! -> #REF! | R37: =N37/B37 -> #DIV/0! | S37: =Q37/B37 -> #REF!
A39: Total | B39: =SUM(B7:B37) -> 147 | C39: =SUM(C7:C35) -> 60895 | D39: =SUM(D7:D35) -> 25661.69 | E39: =SUM(E7:E35) -> 1457.95 | F39: =SUM(F7:F35) -> 27119.64 | G39: =SUM(G7:G35) -> -37882 | H39: =SUM(H7:H35) -> -204651 | I39: =SUM(I7:I35) -> 1398 | J39: =SUM(J7:J35) -> 2380 | ... S39: =SUM(S7:S35) -> #REF!

Sheet Utility report 
A1: DAILY UTILITY REPORT AUGUST 2020
A2: Date | B2: Total occupancy | H2: Diesel balance LTS | I2: Diesel Deliveries | J2: Gen.Diesel consumption LTS | L2: Total Diesel consumption LTS | M2: Water Meter reading | N2: Water consumption m³ | O2: R.O WATER PRODUCTION LTRS + TIME | AA2: Total RO production | AB2: RO Meter reading | AD2: 0 | AE2: STP | AF2: GAS TANK A | AG2: GAS TANK B | AH2: GAS TANK C | AI2: Total Gas Tanks | AJ2: Kg /day | AK2: TOTAL GAS cons.
A3: Rate Tsh /$ | B3: 1640 | C3: Diesel cost / lits | D3: 2175 | F3: =SUM(D3/B3) -> 1.3262195 | H3: =Gen!D11 -> 41590.62 | K3: Transport consumption | M3: Balance | O3: PLANT NO 1 | S3: PLANT NO 2 | W3: PLANT NO 3 | AA3: /day | AB3: Balance | AD3: 0 | AE3: Production | AF3: Capacity | AG3: Capacity | AH3: Capacity | AI3: Kg | AJ3: /day | AK3: /day
B4: Rooms OCC | C4: % | D4: Guest Rooms Occ | F4: Electricity Production Cost /Room Occ by guest | G4: All Cost /Room Occ by guest | O4: Flow M3 | P4: Reading Hours Meter | Q4: Hrs | R4: total production M3 | S4: Flow M3 | T4: Reading Hours Meter | U4: Hrs | V4: total production M3 | W4: Flow M3 | X4: READING HOURS METER | Y4: Hrs | Z4: total production M3 | AA4: M3 | AC4: M3 | AE4: M3 | AF4: 2000 | AG4: 1000 | AH4: 1000 | AI4: =SUM([2]Sheet1!$AA$36) -> 950 | AJ4: Kg | AK4: M3
T5: 16846 | U5: -11 | V5: 0 | X5: 24962 | Y5: 23 | Z5: 0 | AA5: 0 | AB5: 37808 | AC5: 80 | AD5: 204604 | AF5: 0.85 | AG5: 0.85 | AH5: 0.85
A6: =Gen!B11 -> 44075 | B6: ='Summery Report'!E5 -> 3 | C6: =Gen!C11 -> 0.039 | D6: ='Summery Report'!E5 -> 3 | E6: =SUM(F3) -> 1.3262195 | F6: =SUM(J6*E6)/D6 -> 394.07729 | G6: =SUM(L6*E6)/D6 -> 424.67317 | H6: =Gen!D11 -> 41590.62 | I6: =Gen!F11 -> 0 | J6: =Gen!T11 -> 891.43 | K6: =Gen!AK11 -> 69.21 | L6: =SUM(J6:K6) -> 960.64 | M6: ='Water-Meter'!K46 -> 555.23309 | N6: ='Water-Meter'!E6 -> 56 | P6: 19032 | Q6: =SUM(P6-P5) -> 19032 | R6: =SUM(Q6*O6) -> 0 | S6: 2.5 | T6: 16868.19 | U6: =T6-T5 -> 22.19 | V6: - | W6: 2.3 | X6: 24962 | Y6: =X6-X5 -> 0 | Z6: =Y6-Y5 -> -23 | AA6: =Z6-Z5 -> -23 | AB6: 37882 | AC6: =AB6-AB5 -> 74 | AD6: 204651 | AE6: =AD6-AD5 -> 47 | AF6: ='Lpg (2)'!B10*2000/85 -> 2000 | AG6: ='Lpg (2)'!C10*1000/85 -> 1000 | AH6: ='Lpg (2)'!D10*1000/85 -> 23.529412 | AI6: =SUM(AF6*2000)+(AG6*1000)+(AH6*1000) -> 5023529.4 | AJ6: =SUM(AI5-AI6) -> -5023529.4
A7: =Gen!B12 -> 44076 | B7: ='Summery Report'!E6 -> 4 | C7: =Gen!C12 -> 0.039 | D7: ='Summery Report'!E6 -> 4 | E7: =SUM(E6) -> 1.3262195 | F7: =SUM(J7*E7)/D7 -> 272.51159 | G7: =SUM(L7*E7)/D7 -> 299.25149 | H7: =Gen!D12 -> 40629.98 | I7: =Gen!F12 -> 0 | J7: =Gen!T12 -> 821.92 | K7: =Gen!AK12 -> 80.65 | L7: =SUM(J7:K7) -> 902.57 | M7: ='Water-Meter'!K47 -> 557.98926 | N7: ='Water-Meter'!E7 -> 58 | P7: 19032 | Q7: =SUM(P7-P6) -> 0 | R7: =SUM(Q7*O7) -> 0 | S7: 2.2 | T7: 16868.19 | U7: =T7-T6 -> 0 | V7: =SUM(U7*S7) -> 0 | W7: 2.3 | X7: 24974 | Y7: =X7-X6 -> 12 | Z7: =SUM(Y7*W7) -> 27.6 | AA7: =SUM(Z7*X9) -> 689571.37 | AB7: 37908 | AC7: =AB7-AB6 -> 26 | AD7: 204681 | AE7: =AD7-AD6 -> 30 | AF7: ='Lpg (2)'!B11*2000/85 -> 2000 | AG7: ='Lpg (2)'!C11*1000/85 -> 1000 | AH7: ='Lpg (2)'!D11*1000/85 -> 23.529412 | AI7: =SUM(AF6*2000)+(AG7*1000)+(AH7*1000) -> 5023529.4 | AJ7: =SUM(AI6-AI7) -> 0
A8: =Gen!B13 -> 44077 | B8: ='Summery Report'!E7 -> 4 | C8: =Gen!C13 -> 0.039 | D8: ='Summery Report'!E7 -> 4 | E8: =SUM(E7) -> 1.3262195 | F8: =SUM(J8*E8)/D8 -> 361.48765 | G8: =SUM(L8*E8)/D8 -> 364.80983 | H8: =Gen!D13 -> 39727.41 | I8: =Gen!F13 -> 0 | J8: =Gen!T13 -> 1090.28 | K8: =Gen!AK13 -> 10.02 | L8: =SUM(J8:K8) -> 1100.3 | M8: ='Water-Meter'!K48 -> 589.5058 | N8: ='Water-Meter'!E8 -> 51 | P8: 19032 | Q8: =SUM(P8-P7) -> 0 | R8: =SUM(Q8*O8) -> 0 | S8: 2.2 | T8: 16878 | U8: =T8-T7 -> 9.81 | V8: =SUM(U8*S8) -> 21.582 | W8: 2.3 | X8: 24976 | Y8: =X8-X7 -> 2 | Z8: =SUM(Y8*W8) -> 4.6 | AA8: =SUM(Z8*X10) -> 114928.56 | AB8: 37987 | AC8: =AB8-AB7 -> 79 | AD8: 204717 | AE8: =AD8-AD7 -> 36 | AF8: ='Lpg (2)'!B12*2000/85 -> 2000 | AG8: ='Lpg (2)'!C12*1000/85 -> 1000 | AH8: ='Lpg (2)'!D12*1000/85 -> 11.764706 | AI8: =SUM(AF7*2000)+(AG8*1000)+(AH8*1000) -> 5011764.7 | AJ8: =SUM(AI7-AI8) -> 11764.706
A9: =Gen!B14 -> 44078 | B9: ='Summery Report'!E8 -> 8 | C9: =Gen!C14 -> 0.0909 | D9: ='Summery Report'!E8 -> 8 | E9: =SUM(E8) -> 1.3262195 | F9: =SUM(J9*E9)/D9 -> 143.95947 | G9: =SUM(L9*E9)/D9 -> 143.95947 | H9: =Gen!D14 -> 38627.11 | I9: =Gen!F14 -> 0 | J9: =Gen!T14 -> 868.39 | K9: =Gen!AK14 -> 0 | L9: =SUM(J9:K9) -> 868.39 | M9: ='Water-Meter'!K49 -> 604.63027 | N9: ='Water-Meter'!E9 -> 54 | P9: 19032 | Q9: =SUM(P9-P8) -> 0 | R9: =SUM(Q9*O9) -> 0 | S9: 2.2 | T9: 16889.9 | U9: =T9-T8 -> 11.9 | V9: =SUM(U9*S9) -> 26.18 | W9: 2.3 | X9: 24984.47 | Y9: =X9-X8 -> 8.47 | Z9: =SUM(Y9*W9) -> 19.481 | AA9: =SUM(Z9*X11) -> 486722.46 | AB9: 38079 | AC9: =AB9-AB8 -> 92 | AD9: 204762 | AE9: =AD9-AD8 -> 45 | AF9: ='Lpg (2)'!B13*2000/85 -> 2000 | AG9: ='Lpg (2)'!C13*1000/85 -> 1000 | AH9: ='Lpg (2)'!D13*1000/85 -> 11.764706 | AI9: =SUM(AF8*2000)+(AG9*1000)+(AH9*1000) -> 5011764.7 | AJ9: =SUM(AI8-AI9) -> 0
A10: =Gen!B15 -> 44079 | B10: ='Summery Report'!E9 -> 8 | C10: =Gen!C15 -> 0.0909 | D10: ='Summery Report'!E9 -> 8 | E10: =SUM(E9) -> 1.3262195 | F10: =SUM(J10*E10)/D10 -> 139.58129 | G10: =SUM(L10*E10)/D10 -> 144.05894 | H10: =Gen!D15 -> 37758.72 | I10: =Gen!F15 -> 0 | J10: =Gen!T15 -> 841.98 | K10: =Gen!AK15 -> 27.01 | L10: =SUM(J10:K10) -> 868.99 | M10: ='Water-Meter'!K50 -> 599.8961 | N10: ='Water-Meter'!E10 -> 50 | P10: 19032 | Q10: =SUM(P10-P9) -> 0 | R10: =SUM(Q10*O10) -> 0 | T10: 16889.9 | U10: =T10-T9 -> 0 | V10: =SUM(U10*S10) -> 0 | X10: 24984.47 | Y10: =X10-X9 -> 0 | Z10: =SUM(Y10*W10) -> 0 | AA10: =SUM(Z10*X12) -> 0 | AB10: 38080 | AC10: =AB10-AB9 -> 1 | AD10: 204805 | AE10: =AD10-AD9 -> 43 | AF10: ='Lpg (2)'!B14*2000/85 -> 2000 | AG10: ='Lpg (2)'!C14*1000/85 -> 1000 | AH10: ='Lpg (2)'!D14*1000/85 -> 11.764706 | AI10: =SUM(AF9*2000)+(AG10*1000)+(AH10*1000) -> 5011764.7 | AJ10: =SUM(AI9-AI10) -> 0
A11: =Gen!B16 -> 44080 | B11: ='Summery Report'!E10 -> 7 | C11: =Gen!C16 -> 0.0909 | D11: ='Summery Report'!E10 -> 7 | E11: =SUM(E10) -> 1.3262195 | F11: =SUM(J11*E11)/D11 -> 177.81572 | G11: =SUM(L11*E11)/D11 -> 177.81572 | H11: =Gen!D16 -> 36889.73 | I11: =Gen!F16 -> 0 | J11: =Gen!T16 -> 938.54 | K11: =Gen!AK16 -> 0 | L11: =SUM(J11:K11) -> 938.54 | M11: ='Water-Meter'!K51 -> 568.30387 | N11: ='Water-Meter'!E11 -> 52 | P11: 19032 | Q11: =SUM(P11-P10) -> 0 | R11: =SUM(Q11*O11) -> 0 | S11: 2.2 | T11: 16901.9 | U11: =T11-T10 -> 12 | V11: =SUM(U11*S11) -> 26.4 | X11: 24984.47 | Y11: =X11-X10 -> 0 | Z11: =SUM(Y11*W11) -> 0 | AA11: =SUM(Z11*X13) -> 0 | AB11: 38148 | AC11: =AB11-AB10 -> 68 | AD11: 204840 | AE11: =AD11-AD10 -> 35 | AF11: ='Lpg (2)'!B15*2000/85 -> 2000 | AG11: ='Lpg (2)'!C15*1000/85 -> 1000 | AH11: ='Lpg (2)'!D15*1000/85 -> 11.764706 | AI11: =SUM(AF10*2000)+(AG11*1000)+(AH11*1000) -> 5011764.7 | AJ11: =SUM(AI10-AI11) -> 0
A12: =Gen!B17 -> 44081 | B12: ='Summery Report'!E11 -> 3 | C12: =Gen!C17 -> 0.026 | D12: ='Summery Report'!E11 -> 3 | E12: =SUM(E11) -> 1.3262195 | F12: =SUM(J12*E12)/D12 -> 402.40595 | G12: =SUM(L12*E12)/D12 -> 516.52271 | H12: =Gen!D17 -> 35951.19 | I12: =Gen!F17 -> 0 | J12: =Gen!T17 -> 910.27 | K12: =Gen!AK17 -> 258.14 | L12: =SUM(J12:K12) -> 1168.41 | M12: ='Water-Meter'!K52 -> 579.92812 | N12: ='Water-Meter'!E12 -> 58 | P12: 19032 | Q12: =SUM(P12-P11) -> 0 | R12: =SUM(Q12*O12) -> 0 | S12: 2.2 | T12: 16905 | U12: =T12-T11 -> 3.1 | V12: =SUM(U12*S12) -> 6.82 | W12: 2.3 | X12: 24988 | Y12: =X12-X11 -> 3.53 | Z12: =SUM(Y12*W12) -> 8.119 | AA12: =SUM(Z12*X14) -> 203186.09 | AB12: 38193 | AC12: =AB12-AB11 -> 45 | AD12: 204884 | AE12: =AD12-AD11 -> 44 | AF12: ='Lpg (2)'!B16*2000/85 -> 2000 | AG12: ='Lpg (2)'!C16*1000/85 -> 1000 | AH12: ='Lpg (2)'!D16*1000/85 -> 0 | AI12: =SUM(AF11*2000)+(AG12*1000)+(AH12*1000) -> 5000000 | AJ12: =SUM(AI11-AI12) -> 11764.706
A13: =Gen!B18 -> 44082 | B13: ='Summery Report'!E12 -> 7 | C13: =Gen!C18 -> 0.039 | D13: ='Summery Report'!E12 -> 7 | E13: =SUM(E12) -> 1.3262195 | F13: =SUM(J13*E13)/D13 -> 179.6478 | G13: =SUM(L13*E13)/D13 -> 203.00821 | H13: =Gen!D18 -> 34782.78 | I13: =Gen!F18 -> 0 | J13: =Gen!T18 -> 948.21 | K13: =Gen!AK18 -> 123.3 | L13: =SUM(J13:K13) -> 1071.51 | M13: ='Water-Meter'!K53 -> 587.39319 | N13: ='Water-Meter'!E13 -> 46 | P13: 19032 | Q13: =SUM(P13-P12) -> 0 | R13: =SUM(Q13*O13) -> 0 | S13: 2.2 | T13: 16909 | U13: =T13-T12 -> 4 | V13: =SUM(U13*S13) -> 8.8 | W13: 2.3 | X13: 25002 | Y13: =X13-X12 -> 14 | Z13: =SUM(Y13*W13) -> 32.2 | AA13: =SUM(Z13*X15) -> 806159.2 | AB13: 38247 | AC13: =AB13-AB12 -> 54 | AD13: 204919 | AE13: =AD13-AD12 -> 35 | AF13: ='Lpg (2)'!B17*2000/85 -> 2000 | AG13: ='Lpg (2)'!C17*1000/85 -> 952.94118 | AH13: ='Lpg (2)'!D17*1000/85 -> 0 | AI13: =SUM(AF12*2000)+(AG13*1000)+(AH13*1000) -> 4952941.2 | AJ13: =SUM(AI12-AI13) -> 47058.824
A14: =Gen!B19 -> 44083 | B14: ='Summery Report'!E13 -> 5 | C14: =Gen!C19 -> 0.065 | D14: ='Summery Report'!E13 -> 5 | E14: =SUM(E13) -> 1.3262195 | F14: =SUM(J14*E14)/D14 -> 243.05095 | G14: =SUM(L14*E14)/D14 -> 243.05095 | H14: =Gen!D19 -> 33711.27 | I14: =Gen!F19 -> 0 | J14: =Gen!T19 -> 916.33 | K14: =Gen!AK19 -> 0 | L14: =SUM(J14:K14) -> 916.33 | M14: ='Water-Meter'!K54 -> 571.5844 | N14: ='Water-Meter'!E14 -> 52 | P14: 19032 | Q14: =SUM(P14-P13) -> 0 | R14: =SUM(Q14*O14) -> 0 | T14: 16909 | U14: =T14-T13 -> 0 | V14: =SUM(U14*S14) -> 0 | W14: 2.3 | X14: 25026 | Y14: =X14-X13 -> 24 | Z14: =SUM(Y14*W14) -> 55.2 | AA14: =SUM(Z14*X16) -> 1381987.2 | AB14: 38293 | AC14: =AB14-AB13 -> 46 | AD14: 204958 | AE14: =AD14-AD13 -> 39 | AF14: ='Lpg (2)'!B18*2000/85 -> 2000 | AG14: ='Lpg (2)'!C18*1000/85 -> 882.35294 | AH14: ='Lpg (2)'!D18*1000/85 -> 0 | AI14: =SUM(AF13*2000)+(AG14*1000)+(AH14*1000) -> 4882352.9 | AJ14: =SUM(AI13-AI14) -> 70588.235
A15: =Gen!B20 -> 44084 | B15: ='Summery Report'!E14 -> 1 | C15: =Gen!C20 -> 0.013 | D15: ='Summery Report'!E14 -> 1 | E15: =SUM(E14) -> 1.3262195 | F15: =SUM(J15*E15)/D15 -> 1297.0957 | G15: =SUM(L15*E15)/D15 -> 1297.0957 | H15: =Gen!D20 -> 32794.94 | I15: =Gen!F20 -> 0 | J15: =Gen!T20 -> 978.04 | K15: =Gen!AK20 -> 0 | L15: =SUM(J15:K15) -> 978.04 | M15: ='Water-Meter'!K55 -> 531.82243 | N15: ='Water-Meter'!E15 -> 55 | P15: 19032 | Q15: =SUM(P15-P14) -> 0 | R15: =SUM(Q15*O15) -> 0 | S15: 2.2 | T15: 16923 | U15: =T15-T14 -> 14 | V15: =SUM(U15*S15) -> 30.8 | W15: 2.3 | X15: 25036 | Y15: =X15-X14 -> 10 | Z15: =SUM(Y15*W15) -> 23 | AA15: =SUM(Z15*X17) -> 575874 | AB15: 38396 | AC15: =AB15-AB14 -> 103 | AD15: 204992 | AE15: =AD15-AD14 -> 34 | AF15: ='Lpg (2)'!B19*2000/85 -> 2000 | AG15: ='Lpg (2)'!C19*1000/85 -> 847.05882 | AH15: ='Lpg (2)'!D19*1000/85 -> 0 | AI15: =SUM(AF15*2000)+(AG15*1000)+(AH15*1000) -> 4847058.8 | AJ15: =SUM(AI14-AI15) -> 35294.118
A16: =Gen!B21 -> 44085 | B16: ='Summery Report'!E15 -> 3 | C16: =Gen!C21 -> 0.039 | D16: ='Summery Report'!E15 -> 3 | E16: =SUM(E15) -> 1.3262195 | F16: =SUM(J16*E16)/D16 -> 345.94436 | G16: =SUM(L16*E16)/D16 -> 345.94436 | H16: =Gen!D21 -> 31816.9 | I16: =Gen!F21 -> 0 | J16: =Gen!T21 -> 782.55 | K16: =Gen!AK21 -> 0 | L16: =SUM(J16:K16) -> 782.55 | M16: ='Water-Meter'!K56 -> 487.74937 | N16: ='Water-Meter'!E16 -> 94 | P16: 19032 | Q16: =SUM(P16-P15) -> 0 | R16: =SUM(Q16*O16) -> 0 | T16: 16923 | U16: =T16-T15 -> 0 | V16: =SUM(U16*S16) -> 0 | X16: 25036 | Y16: =X16-X15 -> 0 | Z16: =SUM(Y16*W16) -> 0 | AA16: =SUM(Z16*X18) -> 0 | AB16: 38397 | AC16: =AB16-AB15 -> 1 | AD16: 205021 | AE16: =AD16-AD15 -> 29 | AF16: ='Lpg (2)'!B20*2000/85 -> 2000 | AG16: ='Lpg (2)'!C20*1000/85 -> 800 | AH16: ='Lpg (2)'!D20*1000/85 -> 0 | AI16: =SUM(AF16*2000)+(AG16*1000)+(AH16*1000) -> 4800000 | AJ16: =SUM(AI15-AI16) -> 47058.824
A17: =Gen!B22 -> 44086 | B17: ='Summery Report'!E16 -> 3 | C17: =Gen!C22 -> 0.02 | D17: ='Summery Report'!E16 -> 3 | E17: =SUM(E16) -> 1.3262195 | F17: =SUM(J17*E17)/D17 -> 323.94238 | G17: =SUM(L17*E17)/D17 -> 323.94238 | H17: =Gen!D22 -> 31034.35 | I17: =Gen!F22 -> 0 | J17: =Gen!T22 -> 732.78 | K17: =Gen!AK22 -> 0 | L17: =SUM(J17:K17) -> 732.78 | M17: ='Water-Meter'!K57 -> 528.01042 | N17: ='Water-Meter'!E17 -> 59 | P17: 19032 | Q17: =SUM(P18-P16) -> 0 | R17: =SUM(Q17*O17) -> 0 | T17: 16923 | U17: =T17-T16 -> 0 | V17: =SUM(U17*S17) -> 0 | X17: 25038 | Y17: =X17-X16 -> 2 | Z17: =SUM(Y17*W17) -> 0 | AA17: =SUM(Z17*X19) -> 0 | AB17: 38407 | AC17: =AB17-AB16 -> 10 | AD17: 205054 | AE17: =AD17-AD16 -> 33 | AF17: ='Lpg (2)'!B21*2000/85 -> 2000 | AG17: ='Lpg (2)'!C21*1000/85 -> 705.88235 | AH17: ='Lpg (2)'!D21*1000/85 -> 0 | AI17: =SUM(AF17*2000)+(AG17*1000)+(AH17*1000) -> 4705882.4 | AJ17: =SUM(AI16-AI17) -> 94117.647
A18: =Gen!B23 -> 44087 | B18: ='Summery Report'!E17 -> 3 | C18: =Gen!C23 -> 0.03 | D18: ='Summery Report'!E17 -> 3 | E18: =SUM(E17) -> 1.3262195 | F18: =SUM(J18*E18)/D18 -> 413.66555 | G18: =SUM(L18*E18)/D18 -> 445.07043 | H18: =Gen!D23 -> 30301.57 | I18: =Gen!F23 -> 0 | J18: =Gen!T23 -> 935.74 | K18: =Gen!AK23 -> 71.04 | L18: =SUM(J18:K18) -> 1006.78 | M18: ='Water-Meter'!K58 -> 509.30183 | N18: ='Water-Meter'!E18 -> 36 | P18: 19032 | R18: =SUM(Q18*O18) -> 0 | T18: 16923 | U18: =T18-T17 -> 0 | V18: =SUM(U18*S18) -> 0 | X18: 25042 | Y18: =X18-X17 -> 4 | Z18: =SUM(Y18*W18) -> 0 | AA18: =SUM(Z18*X20) -> 0 | AB18: 38423 | AC18: =AB18-AB17 -> 16 | AD18: 205088 | AE18: =AD18-AD17 -> 34 | AF18: ='Lpg (2)'!B22*2000/85 -> 2000 | AG18: ='Lpg (2)'!C22*1000/85 -> 682.35294 | AH18: ='Lpg (2)'!D22*1000/85 -> 0 | AI18: =SUM(AF18*2000)+(AG18*1000)+(AH18*1000) -> 4682352.9 | AJ18: =SUM(AI17-AI18) -> 23529.412
A19: =Gen!B24 -> 44088 | B19: ='Summery Report'!E18 -> 4 | C19: =Gen!C24 -> 0.04 | D19: ='Summery Report'!E18 -> 4 | E19: =SUM(E18) -> 1.3262195 | F19: =SUM(J19*E19)/D19 -> 295.11368 | G19: =SUM(L19*E19)/D19 -> 295.11368 | H19: =Gen!D24 -> 29294.79 | I19: =Gen!F24 -> 0 | J19: =Gen!T24 -> 890.09 | K19: =Gen!AK24 -> 0 | L19: =SUM(J19:K19) -> 890.09 | M19: ='Water-Meter'!K59 -> 517.21956 | N19: ='Water-Meter'!E19 -> 53 | P19: 19032 | R19: =SUM(Q19*O19) -> 0 | T19: 16923 | U19: =T19-T18 -> 0 | V19: =SUM(U19*S19) -> 0 | X19: 25050 | Y19: =X19-X18 -> 8 | Z19: =SUM(Y19*W19) -> 0 | AA19: =SUM(Z19*X21) -> 0 | AB19: 38456 | AC19: =AB19-AB18 -> 33 | AD19: 205122 | AE19: =AD19-AD18 -> 34 | AF19: ='Lpg (2)'!B23*2000/85 -> 2000 | AG19: ='Lpg (2)'!C23*1000/85 -> 611.76471 | AH19: ='Lpg (2)'!D23*1000/85 -> 0 | AI19: =SUM(AF19*2000)+(AG19*1000)+(AH19*1000) -> 4611764.7 | AJ19: =SUM(AI18-AI19) -> 70588.235
A20: =Gen!B25 -> 44089 | B20: ='Summery Report'!E19 -> 4 | C20: =Gen!C25 -> 0.03 | D20: ='Summery Report'!E19 -> 4 | E20: =SUM(E19) -> 1.3262195 | F20: =SUM(J20*E20)/D20 -> 294.74566 | G20: =SUM(L20*E20)/D20 -> 294.74566 | H20: =Gen!D25 -> 28404.7 | I20: =Gen!F25 -> 10000 | J20: =Gen!T25 -> 888.98 | K20: =Gen!AK25 -> 0 | L20: =SUM(J20:K20) -> 888.98 | M20: ='Water-Meter'!K60 -> 473.33092 | N20: ='Water-Meter'!E20 -> 40 | P20: 19032 | Q20: =SUM(P20-P19) -> 0 | R20: =SUM(Q20*O20) -> 0 | T20: 16923 | U20: =T20-T19 -> 0 | V20: =SUM(U20*S20) -> 0 | X20: 25053 | Y20: =X20-X19 -> 3 | Z20: =SUM(Y20*W20) -> 0 | AA20: =SUM(Z20*X22) -> 0 | AB20: 38497 | AC20: =AB20-AB19 -> 41 | AD20: 205158 | AE20: =AD20-AD19 -> 36 | AF20: ='Lpg (2)'!B24*2000/85 -> 2000 | AG20: ='Lpg (2)'!C24*1000/85 -> 588.23529 | AH20: ='Lpg (2)'!D24*1000/85 -> 0 | AI20: =SUM(AF20*2000)+(AG20*1000)+(AH20*1000) -> 4588235.3 | AJ20: =SUM(AI19-AI20) -> 23529.412
A21: =Gen!B26 -> 44090 | B21: ='Summery Report'!E20 -> 11 | C21: =Gen!C26 -> 0.1299 | D21: ='Summery Report'!E20 -> 11 | E21: =SUM(E20) -> 1.3262195 | F21: =SUM(J21*E21)/D21 -> 132.07458 | G21: =SUM(L21*E21)/D21 -> 153.9138 | H21: =Gen!D26 -> 27515.72 | I21: =Gen!F26 -> 0 | J21: =Gen!T26 -> 1095.46 | K21: =Gen!AK26 -> 181.14 | L21: =SUM(J21:K21) -> 1276.6 | M21: ='Water-Meter'!K61 -> 423.3223 | N21: ='Water-Meter'!E21 -> 30 | P21: 19032 | Q21: =SUM(P21-P20) -> 0 | R21: =SUM(Q21*O21) -> 0 | T21: 16923 | U21: =T22-T20 -> 0 | V21: =SUM(U21*S21) -> 0 | X21: 25055 | Y21: =X21-X20 -> 2 | Z21: =SUM(Y21*W21) -> 0 | AA21: =SUM(Z21*X23) -> 0 | AB21: 38513 | AC21: =AB21-AB20 -> 16 | AD21: 205194 | AE21: =AD21-AD20 -> 36 | AF21: ='Lpg (2)'!B25*2000/85 -> 2000 | AG21: ='Lpg (2)'!C25*1000/85 -> 505.88235 | AH21: ='Lpg (2)'!D25*1000/85 -> 0 | AI21: =SUM(AF21*2000)+(AG21*1000)+(AH21*1000) -> 4505882.4 | AJ21: =SUM(AI20-AI21) -> 82352.941
A22: =Gen!B27 -> 44091 | B22: ='Summery Report'!E21 -> 10 | C22: =Gen!C27 -> 0.1169 | D22: ='Summery Report'!E21 -> 10 | E22: =SUM(E21) -> 1.3262195 | F22: =SUM(J22*E22)/D22 -> 135.01843 | G22: =SUM(L22*E22)/D22 -> 138.38835 | H22: =Gen!D27 -> 36239.12 | I22: =Gen!F27 -> 0 | J22: =Gen!T27 -> 1018.07 | K22: =Gen!AK27 -> 25.41 | L22: =SUM(J22:K22) -> 1043.48 | M22: ='Water-Meter'!K62 -> 418.14115 | N22: ='Water-Meter'!E22 -> 49 | P22: 19032 | Q22: =SUM(P22-P21) -> 0 | R22: =SUM(Q22*O22) -> 0 | T22: 16923 | U22: =T23-T21 -> 0 | V22: =SUM(U22*S22) -> 0 | X22: 25055 | Y22: =X22-X21 -> 0 | Z22: =SUM(Y22*W22) -> 0 | AA22: =SUM(Z22*X24) -> 0 | AB22: 38568 | AC22: =AB22-AB21 -> 55 | AD22: 205231 | AE22: =AD22-AD21 -> 37 | AF22: ='Lpg (2)'!B26*2000/85 -> 2000 | AG22: ='Lpg (2)'!C26*1000/85 -> 470.58824 | AH22: ='Lpg (2)'!D26*1000/85 -> 0 | AI22: =SUM(AF22*2000)+(AG22*1000)+(AH22*1000) -> 4470588.2 | AJ22: =SUM(AI21-AI22) -> 35294.118
A23: =Gen!B28 -> 44092 | B23: ='Summery Report'!E22 -> 12 | C23: =Gen!C28 -> 0.1429 | D23: ='Summery Report'!E22 -> 12 | E23: =SUM(E22) -> 1.3262195 | F23: =SUM(J23*E23)/D23 -> 115.07938 | G23: =SUM(L23*E23)/D23 -> 115.07938 | H23: =Gen!D28 -> 35195.64 | I23: =Gen!F28 -> 0 | J23: =Gen!T28 -> 1041.27 | K23: =Gen!AK28 -> 0 | L23: =SUM(J23:K23) -> 1041.27 | M23: ='Water-Meter'!K63 -> 390.17663 | N23: ='Water-Meter'!E23 -> 50 | P23: 19032 | Q23: =SUM(P23-P22) -> 0 | R23: =SUM(Q23*O23) -> 0 | T23: 16923 | U23: =T24-T22 -> 0 | V23: =SUM(U23*S23) -> 0 | X23: 25055 | Y23: =X23-X22 -> 0 | Z23: =SUM(Y23*W23) -> 0 | AA23: =SUM(Z23*X25) -> 0 | AB23: 38588 | AC23: =AB23-AB22 -> 20 | AD23: 205265 | AE23: =AD23-AD22 -> 34 | AF23: ='Lpg (2)'!B27*2000/85 -> 2000 | AG23: ='Lpg (2)'!C27*1000/85 -> 447.05882 | AH23: ='Lpg (2)'!D27*1000/85 -> 0 | AI23: =SUM(AF23*2000)+(AG23*1000)+(AH23*1000) -> 4447058.8 | AJ23: =SUM(AI22-AI23) -> 23529.412
A24: =Gen!B29 -> 44093 | B24: ='Summery Report'!E23 -> 8 | C24: =Gen!C29 -> 0.0909 | D24: ='Summery Report'!E23 -> 8 | E24: =SUM(E23) -> 1.3262195 | F24: =SUM(J24*E24)/D24 -> 187.30861 | G24: =SUM(L24*E24)/D24 -> 249.37237 | H24: =Gen!D29 -> 34154.37 | I24: =Gen!F29 -> 0 | J24: =Gen!T29 -> 1129.88 | K24: =Gen!AK29 -> 374.38 | L24: =SUM(J24:K24) -> 1504.26 | M24: ='Water-Meter'!K64 -> 396.24042 | N24: ='Water-Meter'!E24 -> 51 | P24: 19032 | Q24: =SUM(P24-P23) -> 0 | R24: =SUM(Q24*O24) -> 0 | T24: 16923 | U24: =T24-T23 -> 0 | V24: =SUM(U24*S24) -> 0 | X24: 25055 | Y24: =X24-X23 -> 0 | Z24: =SUM(Y24*W24) -> 0 | AA24: =SUM(Z24*X26) -> 0 | AB24: 38630 | AC24: =AB24-AB23 -> 42 | AD24: 205297 | AE24: =AD24-AD23 -> 32 | AF24: ='Lpg (2)'!B28*2000/85 -> 2000 | AG24: ='Lpg (2)'!C28*1000/85 -> 352.94118 | AH24: ='Lpg (2)'!D28*1000/85 -> 0 | AI24: =SUM(AF24*2000)+(AG24*1000)+(AH24*1000) -> 4352941.2 | AJ24: =SUM(AI23-AI24) -> 94117.647
A25: =Gen!B30 -> 44094 | B25: ='Summery Report'!E24 -> 6 | C25: =Gen!C30 -> 0.0649 | D25: ='Summery Report'!E24 -> 6 | E25: =SUM(E24) -> 1.3262195 | F25: =SUM(J25*E25)/D25 -> 233.33948 | G25: =SUM(L25*E25)/D25 -> 243.28171 | H25: =Gen!D30 -> 32650.11 | I25: =Gen!F30 -> 0 | J25: =Gen!T30 -> 1055.66 | K25: =Gen!AK30 -> 44.98 | L25: =SUM(J25:K25) -> 1100.64 | M25: ='Water-Meter'!K65 -> 442.68283 | N25: ='Water-Meter'!E25 -> 46 | P25: 19032 | Q25: =SUM(P25-P24) -> 0 | R25: =SUM(Q25*O25) -> 0 | T25: 16923 | U25: =T25-T24 -> 0 | V25: =SUM(U25*S25) -> 0 | X25: 25055 | Y25: =X25-X24 -> 0 | Z25: =SUM(Y25*W25) -> 0 | AA25: =SUM(Z25*X27) -> 0 | AB25: 38630 | AC25: =AB25-AB24 -> 0 | AD25: 205335 | AE25: =AD25-AD24 -> 38 | AF25: ='Lpg (2)'!B29*2000/85 -> 2000 | AG25: ='Lpg (2)'!C29*1000/85 -> 341.17647 | AH25: ='Lpg (2)'!D29*1000/85 -> 0 | AI25: =SUM(AF25*2000)+(AG25*1000)+(AH25*1000) -> 4341176.5 | AJ25: =SUM(AI24-AI25) -> 11764.706
A26: =Gen!B31 -> 44095 | B26: ='Summery Report'!E25 -> 6 | C26: =Gen!C31 -> 0.0649 | D26: ='Summery Report'!E25 -> 6 | E26: =SUM(E25) -> 1.3262195 | F26: =SUM(J26*E26)/D26 -> 211.68674 | G26: =SUM(L26*E26)/D26 -> 211.68674 | H26: =Gen!D31 -> 31549.47 | I26: =Gen!F31 -> 0 | J26: =Gen!T31 -> 957.7 | K26: =Gen!AK31 -> 0 | L26: =SUM(J26:K26) -> 957.7 | M26: ='Water-Meter'!K66 -> 437.55796 | N26: ='Water-Meter'!E26 -> 46 | P26: 19032 | Q26: =SUM(P26-P25) -> 0 | R26: =SUM(Q26*O26) -> 0 | T26: 16957 | U26: =T26-T25 -> 34 | V26: =SUM(U26*S26) -> 0 | W26: 2.2 | X26: 25066 | Y26: =X26-X25 -> 11 | Z26: =SUM(Y26*W26) -> 24.2 | AA26: =SUM(Z26*X28) -> 606936 | AB26: 38704 | AC26: =AB26-AB25 -> 74 | AD26: 205369 | AE26: =AD26-AD25 -> 34 | AF26: ='Lpg (2)'!B30*2000/85 -> 2000 | AG26: ='Lpg (2)'!C30*1000/85 -> 294.11765 | AH26: ='Lpg (2)'!D30*1000/85 -> 0 | AI26: =SUM(AF26*2000)+(AG26*1000)+(AH26*1000) -> 4294117.6 | AJ26: =SUM(AI25-AI26) -> 47058.824
A27: =Gen!B32 -> 44096 | B27: ='Summery Report'!E26 -> 3 | C27: =Gen!C32 -> 0.026 | D27: ='Summery Report'!E26 -> 3 | E27: =SUM(E26) -> 1.3262195 | F27: =SUM(J27*E27)/D27 -> 434.33689 | G27: =SUM(L27*E27)/D27 -> 434.33689 | H27: =Gen!D32 -> 30591.77 | I27: =Gen!F32 -> 0 | J27: =Gen!T32 -> 982.5 | K27: =Gen!AK32 -> 0 | L27: =SUM(J27:K27) -> 982.5 | M27: ='Water-Meter'!K67 -> 489.97874 | N27: ='Water-Meter'!E27 -> 56 | P27: 19032 | Q27: =SUM(P27-P26) -> 0 | R27: =SUM(Q27*O27) -> 0 | T27: 16957 | U27: =T27-T26 -> 0 | V27: =SUM(U27*S27) -> 0 | W27: 2.2 | X27: 25074 | Y27: =X27-X26 -> 8 | Z27: =SUM(Y27*W27) -> 17.6 | AA27: =SUM(Z27*X29) -> 441496 | AB27: 38748 | AC27: =AB27-AB26 -> 44 | AD27: 205407 | AE27: =AD27-AD26 -> 38 | AF27: ='Lpg (2)'!B31*2000/85 -> 2000 | AG27: ='Lpg (2)'!C31*1000/85 -> 270.58824 | AH27: ='Lpg (2)'!D31*1000/85 -> 0 | AI27: =SUM(AF27*2000)+(AG27*1000)+(AH27*1000) -> 4270588.2 | AJ27: =SUM(AI26-AI27) -> 23529.412
A28: =Gen!B33 -> 44097 | B28: ='Summery Report'!E27 -> 3 | C28: =Gen!C33 -> 0.026 | D28: ='Summery Report'!E27 -> 3 | E28: =SUM(E27) -> 1.3262195 | F28: =SUM(J28*E28)/D28 -> 437.5596 | G28: =SUM(L28*E28)/D28 -> 520.35107 | H28: =Gen!D33 -> 29609.27 | I28: =Gen!F33 -> 0 | J28: =Gen!T33 -> 989.79 | K28: =Gen!AK33 -> 187.28 | L28: =SUM(J28:K28) -> 1177.07 | M28: ='Water-Meter'!K68 -> 541.90348 | N28: ='Water-Meter'!E28 -> 49 | P28: 19032 | Q28: =SUM(P28-P27) -> 0 | R28: =SUM(Q28*O28) -> 0 | T28: 16957 | U28: =T28-T27 -> 0 | V28: =SUM(U28*S28) -> 0 | W28: 2.2 | X28: 25080 | Y28: =X28-X27 -> 6 | Z28: =SUM(Y28*W28) -> 13.2 | AA28: =SUM(Z28*X30) -> 331425.6 | AB28: 38795 | AC28: =SUM(AB28-AB27) -> 47 | AD28: 205438 | AE28: =AD28-AD27 -> 31 | AF28: ='Lpg (2)'!B32*2000/85 -> 2000 | AG28: ='Lpg (2)'!C32*1000/85 -> 235.29412 | AH28: ='Lpg (2)'!D32*1000/85 -> 0 | AI28: =SUM(AF28*2000)+(AG28*1000)+(AH28*1000) -> 4235294.1 | AJ28: =SUM(AI27-AI28) -> 35294.118
A29: =Gen!B34 -> 44098 | B29: ='Summery Report'!E28 -> 2 | C29: =Gen!C34 -> 0.013 | D29: ='Summery Report'!E28 -> 2 | E29: =SUM(E28) -> 1.3262195 | F29: =SUM(J29*E29)/D29 -> 665.92797 | G29: =SUM(L29*E29)/D29 -> 665.92797 | H29: =Gen!D34 -> 28432.2 | I29: =Gen!F34 -> 0 | J29: =Gen!T34 -> 1004.25 | K29: =Gen!AK34 -> 0 | L29: =SUM(J29:K29) -> 1004.25 | M29: ='Water-Meter'!K69 -> 571.6617 | N29: ='Water-Meter'!E29 -> 48 | P29: 19032 | Q29: =SUM(P29-P28) -> 0 | R29: =SUM(Q29*O29) -> 0 | S29: 2.3 | T29: 16978 | U29: =T29-T28 -> 21 | V29: =SUM(U29*S29) -> 48.3 | W29: 2.2 | X29: 25085 | Y29: =X29-X28 -> 5 | Z29: =SUM(Y29*W29) -> 11 | AA29: =SUM(Z29*X31) -> 276188 | AB29: 38851 | AC29: =SUM(AB29-AB28) -> 56 | AD29: 205474 | AE29: =AD29-AD28 -> 36 | AF29: ='Lpg (2)'!B33*2000/85 -> 2000 | AG29: ='Lpg (2)'!C33*1000/85 -> 223.52941 | AH29: ='Lpg (2)'!D33*1000/85 -> 0 | AI29: =SUM(AF29*2000)+(AG29*1000)+(AH29*1000) -> 4223529.4 | AJ29: =SUM(AI28-AI29) -> 11764.706
A30: =Gen!B35 -> 44099 | B30: ='Summery Report'!E29 -> 3 | C30: =Gen!C35 -> 0.013 | D30: ='Summery Report'!E29 -> 3 | E30: =SUM(E29) -> 1.3262195 | F30: =SUM(J30*E30)/D30 -> 450.50793 | G30: =SUM(L30*E30)/D30 -> 483.48659 | H30: =Gen!D35 -> 27427.95 | I30: =Gen!F35 -> 0 | J30: =Gen!T35 -> 1019.08 | K30: =Gen!AK35 -> 74.6 | L30: =SUM(J30:K30) -> 1093.68 | M30: ='Water-Meter'!K70 -> 593.45977 | N30: ='Water-Meter'!E30 -> 50 | P30: 19032 | Q30: =SUM(P30-P29) -> 0 | R30: =SUM(Q30*O30) -> 0 | S30: 2.3 | T30: 16983 | U30: =T30-T29 -> 5 | V30: =SUM(U30*S30) -> 11.5 | W30: 2.2 | X30: 25108 | Y30: =X30-X29 -> 23 | Z30: =SUM(Y30*W30) -> 50.6 | AA30: =SUM(Z30*X32) -> 1270464.8 | AB30: 38921 | AC30: =SUM(AB30-AB29) -> 70 | AD30: 205504 | AE30: =AD30-AD29 -> 30 | AF30: ='Lpg (2)'!B34*2000/85 -> 2000 | AG30: ='Lpg (2)'!C34*1000/85 -> 211.76471 | AH30: ='Lpg (2)'!D34*1000/85 -> 0 | AI30: =SUM(AF30*2000)+(AG30*1000)+(AH30*1000) -> 4211764.7 | AJ30: =SUM(AI29-AI30) -> 11764.706
A31: =Gen!B36 -> 44100 | B31: ='Summery Report'!E30 -> 4 | C31: =Gen!C36 -> 0.026 | D31: ='Summery Report'!E30 -> 4 | E31: =SUM(E30) -> 1.3262195 | F31: =SUM(J31*E31)/D31 -> 291.37043 | G31: =SUM(L31*E31)/D31 -> 291.37043 | H31: =Gen!D36 -> 26334.27 | I31: =Gen!F36 -> 0 | J31: =Gen!T36 -> 878.8 | K31: =Gen!AK36 -> 0 | L31: =SUM(J31:K31) -> 878.8 | M31: ='Water-Meter'!K71 -> 584.68185 | N31: ='Water-Meter'!E31 -> 55 | P31: 19032 | Q31: =SUM(P31-P30) -> 0 | R31: =SUM(Q31*O31) -> 0 | T31: 16983 | U31: =T31-T30 -> 0 | V31: =SUM(U31*S31) -> 0 | W31: 2.2 | X31: 25108 | Y31: =X31-X30 -> 0 | Z31: =SUM(Y31*W31) -> 0 | AA31: =SUM(Z31*X33) -> 0 | AB31: 38968 | AC31: =SUM(AB31-AB30) -> 47 | AD31: 205537 | AE31: =AD31-AD30 -> 33 | AF31: ='Lpg (2)'!B35*2000/85 -> 2000 | AG31: ='Lpg (2)'!C35*1000/85 -> 200 | AH31: ='Lpg (2)'!D35*1000/85 -> 0 | AI31: =SUM(AF31*2000)+(AG31*1000)+(AH31*1000) -> 4200000 | AJ31: =SUM(AI30-AI31) -> 11764.706
A32: =Gen!B37 -> 44101 | B32: ='Summery Report'!E31 -> 5 | C32: =Gen!C37 -> 0.0519 | D32: ='Summery Report'!E31 -> 5 | E32: =SUM(E31) -> 1.3262195 | F32: =SUM(J32*E32)/D32 -> 258.80909 | G32: =SUM(L32*E32)/D32 -> 258.80909 | H32: =Gen!D37 -> 43455.47 | I32: =Gen!F37 -> 18000 | J32: =Gen!T37 -> 975.74 | K32: =Gen!AK37 -> 0 | L32: =SUM(J32:K32) -> 975.74 | M32: ='Water-Meter'!K72 -> 587.44078 | N32: ='Water-Meter'!E32 -> 58 | P32: 19032 | Q32: =SUM(P32-P31) -> 0 | R32: =SUM(Q32*O32) -> 0 | S32: 2.2 | T32: 16989 | U32: =T32-T31 -> 6 | V32: =SUM(U32*S32) -> 13.2 | X32: 25108 | Y32: =X32-X31 -> 0 | Z32: =SUM(Y32*W32) -> 0 | AA32: =SUM(Z32*X34) -> 0 | AB32: 39036 | AC32: =SUM(AB32-AB31) -> 68 | AD32: 205574 | AE32: =AD32-AD31 -> 37 | AF32: ='Lpg (2)'!B36*2000/85 -> 2000 | AG32: ='Lpg (2)'!C36*1000/85 -> 188.23529 | AH32: ='Lpg (2)'!D36*1000/85 -> 0 | AI32: =SUM(AF32*2000)+(AG32*1000)+(AH32*1000) -> 4188235.3 | AJ32: =SUM(AI31-AI32) -> 11764.706
A33: =Gen!B38 -> 44102 | B33: ='Summery Report'!E32 -> 5 | C33: =Gen!C38 -> 0.0519 | D33: ='Summery Report'!E32 -> 5 | E33: =SUM(E32) -> 1.3262195 | F33: =SUM(J33*E33)/D33 -> 257.12479 | G33: =SUM(L33*E33)/D33 -> 257.12479 | H33: =Gen!D38 -> 42479.73 | I33: =Gen!F38 -> 0 | J33: =Gen!T38 -> 969.39 | K33: =Gen!AK38 -> 0 | L33: =SUM(J33:K33) -> 969.39 | M33: ='Water-Meter'!K73 -> 599.10195 | N33: ='Water-Meter'!E33 -> 52 | Q33: =SUM(P33-P32) -> -19032 | R33: =SUM(Q33*O33) -> 0 | U33: =T33-T32 -> -16989 | V33: =SUM(U33*S33) -> 0 | Y33: =X33-X32 -> -25108 | Z33: =SUM(Y33*W33) -> 0 | AA33: =SUM(Z33*X35) -> 0 | AB33: 39082 | AC33: =SUM(AB33-AB32) -> 46 | AD33: 205609 | AE33: =AD33-AD32 -> 35 | AF33: ='Lpg (2)'!B37*2000/85 -> 2000 | AG33: ='Lpg (2)'!C37*1000/85 -> 176.47059 | AH33: ='Lpg (2)'!D37*1000/85 -> 0 | AI33: =SUM(AF33*2000)+(AG33*1000)+(AH33*1000) -> 4176470.6 | AJ33: =SUM(AI32-AI33) -> 11764.706
A34: =Gen!B39 -> 44103 | B34: ='Summery Report'!E33 -> 5 | C34: =Gen!C39 -> 0.0519 | D34: ='Summery Report'!E33 -> 5 | E34: =SUM(E33) -> 1.3262195 | F34: =SUM(J34*E34)/D34 -> 0 | G34: =SUM(L34*E34)/D34 -> 0 | H34: =Gen!D39 -> 41510.34 | I34: =Gen!F39 -> 0 | J34: =Gen!T39 -> 0 | K34: =Gen!AK39 -> 0 | L34: =SUM(J34:K34) -> 0 | M34: ='Water-Meter'!K74 -> 579.36164 | N34: ='Water-Meter'!E34 -> 0 | Q34: =SUM(P34-P33) -> 0 | R34: =SUM(Q34*O34) -> 0 | U34: =T34-T33 -> 0 | V34: =SUM(U34*S34) -> 0 | Y34: =X34-X33 -> 0 | Z34: =SUM(Y34*W34) -> 0 | AA34: =SUM(Z34*X36) -> 0 | AC34: =SUM(AB34-AB33) -> -39082 | AE34: =AD34-AD33 -> -205609 | AF34: ='Lpg (2)'!B38*2000/85 -> 2000 | AG34: ='Lpg (2)'!C38*1000/85 -> 164.70588 | AH34: ='Lpg (2)'!D38*1000/85 -> 0 | AI34: =SUM(AF34*2000)+(AG34*1000)+(AH34*1000) -> 4164705.9 | AJ34: =SUM(AI33-AI34) -> 11764.706
A35: =Gen!B40 -> 44104 | B35: ='Summery Report'!E34 -> 0 | C35: =Gen!C40 -> 0 | D35: ='Summery Report'!E34 -> 0 | E35: =SUM(E34) -> 1.3262195 | F35: =SUM(J35*E35)/D35 -> #DIV/0! | G35: =SUM(L35*E35)/D35 -> #DIV/0! | H35: =Gen!D40 -> 41510.34 | I35: =Gen!F40 -> 0 | J35: =Gen!T40 -> 0 | K35: =Gen!AK40 -> 0 | L35: =SUM(J35:K35) -> 0 | M35: ='Water-Meter'!K75 -> 0 | N35: ='Water-Meter'!E35 -> 0 | Q35: =SUM(P35-P34) -> 0 | R35: =SUM(Q35*O35) -> 0 | U35: =T35-T34 -> 0 | V35: =SUM(U35*S35) -> 0 | Y35: =X35-X34 -> 0 | Z35: =SUM(Y35*W35) -> 0 | AA35: =SUM(Z35*X37) -> 0 | AC35: =SUM(AB35-AB34) -> 0 | AE35: =AD35-AD34 -> 0 | AF35: ='Lpg (2)'!B39*2000/85 -> 0 | AG35: ='Lpg (2)'!C39*1000/85 -> 0 | AH35: ='Lpg (2)'!D39*1000/85 -> 0 | AI35: =SUM(AF35*2000)+(AG35*1000)+(AH35*1000) -> 0 | AJ35: =SUM(AI34-AI35) -> 4164705.9
A36: =Gen!B41 -> 0 | B36: ='Summery Report'!E35 -> 0 | C36: =Gen!C41 -> 0 | D36: ='Summery Report'!E35 -> 0 | E36: =SUM(E35) -> 1.3262195 | F36: =SUM(J36*E36)/D36 -> #DIV/0! | G36: =SUM(L36*E36)/D36 -> #DIV/0! | H36: =Gen!D41 -> 41510.34 | I36: =Gen!F41 -> 0 | J36: =Gen!T41 -> 0 | K36: =Gen!AK41 -> 0 | L36: =SUM(J36:K36) -> 0 | M36: ='Water-Meter'!K76 -> 0 | N36: ='Water-Meter'!E36 -> 0 | Q36: =SUM(P36-P35) -> 0 | R36: =SUM(Q36*O36) -> 0 | U36: =T36-T35 -> 0 | V36: =SUM(U36*S36) -> 0 | Y36: =X36-X35 -> 0 | Z36: =SUM(Y36*W36) -> 0 | AA36: =SUM(Z36*X38) -> 0 | AC36: =SUM(AB36-AB35) -> 0 | AE36: =AD36-AD35 -> 0 | AF36: ='Lpg (2)'!B40*2000/85 -> 0 | AG36: ='Lpg (2)'!C40*1000/85 -> 0 | AH36: ='Lpg (2)'!D40*1000/85 -> 0 | AI36: =SUM(AF36*1000)+(AG36*1000)+(AH36*2000) -> 0 | AJ36: =SUM(AI35-AI36) -> 0
A37: =Gen!B42 -> 0 | B37: 0 | J37: =SUM(J6:J36) -> 26553.12 | L37: =SUM(J37:K37) -> 26553.12 | N37: ='Water-Meter'!E37 -> 0 | AC37: =SUM(AB37-AB36) -> 0 | AE37: =AD37-AD36 -> 0 | AJ37: =SUM(AJ6:AJ36) -> 0 | AK37: =SUM(AK6:AK36) -> 0

Sheet Kit report
B1: KITCHEN THREE PHASE KWH METER READING | H1: KITCHEN WATER METER READING | M1: AMANI Restaurant WATER METER READING | T1: LAUNDRY THREE PHASE KWH METER READING | Y1: LAUNDRY WATER METER READING
A2: Occ % | B2: DATE | C2: READING TIME | D2: METER READING OPEN | E2: METER READING ClOSE | F2: UNIT USED Kwh | H2: DATE | I2: READING TIME | J2: METER READING OPEN Cbm | K2: METER READING ClOSE Cbm | L2: UNIT USED Cbm | M2: DATE | N2: READING TIME | O2: METER READING OPEN Cbm | P2: METER READING ClOSE Cbm | Q2: UNIT USED Cbm | R2: Cost Per day Elct+Water $ | S2: % as per the total Lodge consumption | T2: DATE | U2: READING TIME | V2: METER READING OPEN (Kwh) | W2: METER READING ClOSE (Kwh) | X2: UNIT USED Kwh | Y2: DATE | Z2: READING TIME | AA2: METER READING OPEN Cbm | AB2: METER READING ClOSE Cbm | AC2: UNIT USED Cbm
A3: =Gen!B11 -> 44075 | B3: Close Last Month | E3: 8794.7 | F3: X120 | H3: Close Last Month | J3: ='Water-Meter'!G5 -> 38000 | K3: ='Water-Meter'!G5 -> 38000 | M3: Close Last Month | O3: ='Water-Meter'!J5 -> 8021 | P3: ='Water-Meter'!J5 -> 8021 | T3: Close Last Month | W3: 7819.2 | X3: =(W3-V3)*200 -> 1563840 | Y3: Close Last Month
A4: =Gen!C11 -> 0.039 | B4: =Gen!B11 -> 44075 | D4: =E3 -> 8794.7 | E4: 8796.3 | F4: =SUM(E4-D4)*120 -> 192 | H4: =B4 -> 44075 | J4: ='Water-Meter'!G6 -> 38000 | K4: ='Water-Meter'!G6 -> 38000 | L4: =SUM(K4-J4) -> 0 | M4: =H4 -> 44075 | O4: ='Water-Meter'!J6 -> 8023 | P4: ='Water-Meter'!J6 -> 8023 | Q4: =N4-O3 -> -8021 | R4: =SUM(Q4/1615) -> -4.9665635 | S4: =Gen!T11 -> 891.43 | T4: =M4 -> 44075 | V4: =W3 -> 7819.2 | W4: 7819.6 | X4: =(W4-V4)*200 -> 80 | Y4: =T4 -> 44075 | AB4: ='Water-Meter'!P6 -> 20255 | AC4: =AA4-AB3 -> 0
A5: =Gen!C12 -> 0.039 | B5: =Gen!B12 -> 44076 | D5: =E4 -> 8796.3 | E5: 8797.9 | F5: =SUM(E5-D5)*120 -> 192 | H5: =B5 -> 44076 | J5: ='Water-Meter'!G7 -> 38000 | K5: ='Water-Meter'!G7 -> 38000 | L5: =SUM(K5-J5) -> 0 | M5: =H5 -> 44076 | O5: ='Water-Meter'!J7 -> 8024 | P5: ='Water-Meter'!J7 -> 8024 | Q5: =N5-O4 -> -8023 | R5: =SUM(Q5/1615) -> -4.9678019 | S5: =Gen!T12 -> 821.92 | T5: =M5 -> 44076 | V5: =W4 -> 7819.6 | W5: 7819.7 | X5: =(W5-V5)*200 -> 20 | Y5: =T5 -> 44076 | AB5: ='Water-Meter'!P7 -> 20257 | AC5: =AA5-AB4 -> -20255
A6: =Gen!C13 -> 0.039 | B6: =Gen!B13 -> 44077 | D6: =E5 -> 8797.9 | E6: 8799.6 | F6: =SUM(E6-D6)*120 -> 204 | H6: =B6 -> 44077 | J6: ='Water-Meter'!G8 -> 38000 | K6: ='Water-Meter'!G8 -> 38000 | L6: =SUM(K6-J6) -> 0 | M6: =H6 -> 44077 | O6: ='Water-Meter'!J8 -> 8025 | P6: ='Water-Meter'!J8 -> 8025 | Q6: =N6-O5 -> -8024 | R6: =SUM(Q6/1615) -> -4.9684211 | S6: =Gen!T13 -> 1090.28 | T6: =M6 -> 44077 | V6: =W5 -> 7819.7 | W6: 7819.9 | X6: =(W6-V6)*200 -> 40 | Y6: =T6 -> 44077 | AB6: ='Water-Meter'!P8 -> 20258 | AC6: =AA6-AB5 -> -20257
A7: =Gen!C14 -> 0.0909 | B7: =Gen!B14 -> 44078 | D7: =E6 -> 8799.6 | E7: 8801.4 | F7: =SUM(E7-D7)*120 -> 216 | H7: =B7 -> 44078 | J7: ='Water-Meter'!G9 -> 38000 | K7: ='Water-Meter'!G9 -> 38000 | L7: =SUM(K7-J7) -> 0 | M7: =H7 -> 44078 | O7: ='Water-Meter'!J9 -> 8026 | P7: ='Water-Meter'!J9 -> 8026 | Q7: =N7-O6 -> -8025 | R7: =SUM(Q7/1615) -> -4.9690402 | S7: =Gen!T14 -> 868.39 | T7: =M7 -> 44078 | V7: =W6 -> 7819.9 | W7: 7820.4 | X7: =(W7-V7)*200 -> 100 | Y7: =T7 -> 44078 | AB7: ='Water-Meter'!P9 -> 20259 | AC7: =AA7-AB6 -> -20258
A8: =Gen!C15 -> 0.0909 | B8: =Gen!B15 -> 44079 | D8: =E7 -> 8801.4 | E8: 8803.1 | F8: =SUM(E8-D8)*120 -> 204 | H8: =B8 -> 44079 | J8: ='Water-Meter'!G10 -> 38000 | K8: ='Water-Meter'!G10 -> 38000 | L8: =SUM(K8-J8) -> 0 | M8: =H8 -> 44079 | O8: ='Water-Meter'!J10 -> 8027 | P8: ='Water-Meter'!J10 -> 8027 | Q8: =N8-O7 -> -8026 | R8: =SUM(Q8/1615) -> -4.9696594 | S8: =Gen!T15 -> 841.98 | T8: =M8 -> 44079 | V8: =W7 -> 7820.4 | W8: 7820.6 | X8: =(W8-V8)*200 -> 40 | Y8: =T8 -> 44079 | AB8: ='Water-Meter'!P10 -> 20261 | AC8: =AA8-AB7 -> -20259
A9: =Gen!C16 -> 0.0909 | B9: =Gen!B16 -> 44080 | D9: =E8 -> 8803.1 | E9: 8804.3 | F9: =SUM(E9-D9)*120 -> 144 | H9: =B9 -> 44080 | J9: ='Water-Meter'!G11 -> 38000 | K9: ='Water-Meter'!G11 -> 38000 | L9: =SUM(K9-J9) -> 0 | M9: =H9 -> 44080 | O9: ='Water-Meter'!J11 -> 8028 | P9: ='Water-Meter'!J11 -> 8028 | Q9: =N9-O8 -> -8027 | R9: =SUM(Q9/1615) -> -4.9702786 | S9: =Gen!T16 -> 938.54 | T9: =M9 -> 44080 | V9: =W8 -> 7820.6 | W9: 7820.9 | X9: =(W9-V9)*200 -> 60 | Y9: =T9 -> 44080 | AB9: ='Water-Meter'!P11 -> 20263 | AC9: =AA9-AB8 -> -20261
A10: =Gen!C17 -> 0.026 | B10: =Gen!B17 -> 44081 | D10: =E9 -> 8804.3 | E10: 8805.9 | F10: =SUM(E10-D10)*120 -> 192 | H10: =B10 -> 44081 | J10: ='Water-Meter'!G12 -> 38000 | K10: ='Water-Meter'!G12 -> 38000 | L10: =SUM(K10-J10) -> 0 | M10: =H10 -> 44081 | O10: ='Water-Meter'!J12 -> 8029 | P10: ='Water-Meter'!J12 -> 8029 | Q10: =N10-O9 -> -8028 | R10: =SUM(Q10/1615) -> -4.9708978 | S10: =Gen!T17 -> 910.27 | T10: =M10 -> 44081 | V10: =W9 -> 7820.9 | W10: 7821.1 | X10: =(W10-V10)*200 -> 40 | Y10: =T10 -> 44081 | AB10: ='Water-Meter'!P12 -> 20264 | AC10: =AA10-AB9 -> -20263
A11: =Gen!C18 -> 0.039 | B11: =Gen!B18 -> 44082 | D11: =E10 -> 8805.9 | E11: 8807.5 | F11: =SUM(E11-D11)*120 -> 192 | H11: =B11 -> 44082 | J11: ='Water-Meter'!G13 -> 38000 | K11: ='Water-Meter'!G13 -> 38000 | L11: =SUM(K11-J11) -> 0 | M11: =H11 -> 44082 | O11: ='Water-Meter'!J13 -> 8030 | P11: ='Water-Meter'!J13 -> 8030 | Q11: =N11-O10 -> -8029 | R11: =SUM(Q11/1615) -> -4.971517 | S11: =Gen!T18 -> 948.21 | T11: =M11 -> 44082 | V11: =W10 -> 7821.1 | W11: 7821.4 | X11: =(W11-V11)*200 -> 60 | Y11: =T11 -> 44082 | AB11: ='Water-Meter'!P13 -> 20268 | AC11: =AA11-AB10 -> -20264
A12: =Gen!C19 -> 0.065 | B12: =Gen!B19 -> 44083 | D12: =E11 -> 8807.5 | E12: 8809.1 | F12: =SUM(E12-D12)*120 -> 192 | H12: =B12 -> 44083 | J12: ='Water-Meter'!G14 -> 38000 | K12: ='Water-Meter'!G14 -> 38000 | L12: =SUM(K12-J12) -> 0 | M12: =H12 -> 44083 | O12: ='Water-Meter'!J14 -> 8032 | P12: ='Water-Meter'!J14 -> 8032 | Q12: =N12-O11 -> -8030 | R12: =SUM(Q12/1615) -> -4.9721362 | S12: =Gen!T19 -> 916.33 | T12: =M12 -> 44083 | V12: =W11 -> 7821.4 | W12: 7821.4 | X12: =(W12-V12)*200 -> 0 | Y12: =T12 -> 44083 | AB12: ='Water-Meter'!P14 -> 20269 | AC12: =AA12-AB11 -> -20268
A13: =Gen!C20 -> 0.013 | B13: =Gen!B20 -> 44084 | D13: =E12 -> 8809.1 | E13: 8810.8 | F13: =SUM(E13-D13)*120 -> 204 | H13: =B13 -> 44084 | J13: ='Water-Meter'!G15 -> 38000 | K13: ='Water-Meter'!G15 -> 38000 | L13: =SUM(K13-J13) -> 0 | M13: =H13 -> 44084 | O13: ='Water-Meter'!J15 -> 8033 | P13: ='Water-Meter'!J15 -> 8033 | Q13: =N13-O12 -> -8032 | R13: =SUM(Q13/1615) -> -4.9733746 | S13: =Gen!T20 -> 978.04 | T13: =M13 -> 44084 | V13: =W12 -> 7821.4 | W13: 7822.1 | X13: =(W13-V13)*200 -> 140 | Y13: =T13 -> 44084 | AB13: ='Water-Meter'!P15 -> 20270 | AC13: =AA13-AB12 -> -20269
A14: =Gen!C21 -> 0.039 | B14: =Gen!B21 -> 44085 | D14: =E13 -> 8810.8 | E14: 8812.4 | F14: =SUM(E14-D14)*120 -> 192 | H14: =B14 -> 44085 | J14: ='Water-Meter'!G16 -> 38000 | K14: ='Water-Meter'!G16 -> 38000 | L14: =SUM(K14-J14) -> 0 | M14: =H14 -> 44085 | O14: ='Water-Meter'!J16 -> 8034 | P14: ='Water-Meter'!J16 -> 8034 | Q14: =N14-O13 -> -8033 | R14: =SUM(Q14/1615) -> -4.9739938 | S14: =Gen!T21 -> 782.55 | T14: =M14 -> 44085 | V14: =W13 -> 7822.1 | W14: 7822.2 | X14: =(W14-V14)*200 -> 20 | Y14: =T14 -> 44085 | AB14: ='Water-Meter'!P16 -> 20271 | AC14: =AA14-AB13 -> -20270
A15: =Gen!C22 -> 0.02 | B15: =Gen!B22 -> 44086 | D15: =E14 -> 8812.4 | E15: 8813.9 | F15: =SUM(E15-D15)*120 -> 180 | H15: =B15 -> 44086 | J15: ='Water-Meter'!G17 -> 38000 | K15: ='Water-Meter'!G17 -> 38000 | L15: =SUM(K15-J15) -> 0 | M15: =H15 -> 44086 | O15: ='Water-Meter'!J17 -> 8035 | P15: ='Water-Meter'!J17 -> 8035 | Q15: =N15-O14 -> -8034 | R15: =SUM(Q15/1615) -> -4.974613 | S15: =Gen!T22 -> 732.78 | T15: =M15 -> 44086 | V15: =W14 -> 7822.2 | W15: 7822.3 | X15: =(W15-V15)*200 -> 20 | Y15: =T15 -> 44086 | AB15: ='Water-Meter'!P17 -> 20272 | AC15: =AA15-AB14 -> -20271
A16: =Gen!C23 -> 0.03 | B16: =Gen!B23 -> 44087 | D16: =E15 -> 8813.9 | E16: 8815.4 | F16: =SUM(E16-D16)*120 -> 180 | H16: =B16 -> 44087 | J16: ='Water-Meter'!G18 -> 38000 | K16: ='Water-Meter'!G18 -> 38000 | L16: =SUM(K16-J16) -> 0 | M16: =H16 -> 44087 | O16: 8036 | P16: ='Water-Meter'!J18 -> 8036 | Q16: =N16-O15 -> -8035 | R16: =SUM(Q16/1615) -> -4.9752322 | S16: =Gen!T23 -> 935.74 | T16: =M16 -> 44087 | V16: =W15 -> 7822.3 | W16: 7822.5 | X16: =(W16-V16)*200 -> 40 | Y16: =T16 -> 44087 | AB16: ='Water-Meter'!P18 -> 20273 | AC16: =AA16-AB15 -> -20272
A17: =Gen!C24 -> 0.04 | B17: =Gen!B24 -> 44088 | D17: =E16 -> 8815.4 | E17: 8817.1 | F17: =SUM(E17-D17)*120 -> 204 | H17: =B17 -> 44088 | J17: ='Water-Meter'!G19 -> 38000 | K17: ='Water-Meter'!G19 -> 38000 | L17: =SUM(K17-J17) -> 0 | M17: =H17 -> 44088 | O17: ='Water-Meter'!J19 -> 8036 | P17: ='Water-Meter'!J19 -> 8036 | Q17: =N17-O16 -> -8036 | R17: =SUM(Q17/1615) -> -4.9758514 | S17: =Gen!T24 -> 890.09 | T17: =M17 -> 44088 | V17: 7822.5 | W17: 7822.9 | X17: =(W17-V17)*200 -> 80 | Y17: =T17 -> 44088 | AB17: ='Water-Meter'!P19 -> 20276 | AC17: =AA17-AB16 -> -20273
A18: =Gen!C25 -> 0.03 | B18: =Gen!B25 -> 44089 | D18: =E17 -> 8817.1 | E18: 8818.8 | F18: =SUM(E18-D18)*120 -> 204 | H18: =B18 -> 44089 | J18: ='Water-Meter'!G20 -> 38000 | K18: ='Water-Meter'!G20 -> 38000 | L18: =SUM(K18-J18) -> 0 | M18: =H18 -> 44089 | O18: ='Water-Meter'!J20 -> 8037 | P18: ='Water-Meter'!J20 -> 8037 | Q18: =N18-O17 -> -8036 | R18: =SUM(Q18/1615) -> -4.9758514 | S18: =Gen!T25 -> 888.98 | T18: =M18 -> 44089 | V18: =W17 -> 7822.9 | W18: 7823.1 | X18: =(W18-V18)*200 -> 40 | Y18: =T18 -> 44089 | AB18: ='Water-Meter'!P20 -> 20278 | AC18: =AA18-AB17 -> -20276
A19: =Gen!C26 -> 0.1299 | B19: =Gen!B26 -> 44090 | D19: =E18 -> 8818.8 | E19: 8820.7 | F19: =SUM(E19-D19)*120 -> 228 | H19: =B19 -> 44090 | J19: ='Water-Meter'!G21 -> 38000 | K19: ='Water-Meter'!G21 -> 38000 | L19: =SUM(K19-J19) -> 0 | M19: =H19 -> 44090 | O19: ='Water-Meter'!J21 -> 8038 | P19: ='Water-Meter'!J21 -> 8038 | Q19: =N19-O18 -> -8037 | R19: =SUM(Q19/1615) -> -4.9764706 | S19: =Gen!T26 -> 1095.46 | T19: =M19 -> 44090 | V19: =W18 -> 7823.1 | W19: 7823.4 | X19: =(W19-V19)*200 -> 60 | Y19: =T19 -> 44090 | AB19: ='Water-Meter'!P21 -> 20280 | AC19: =AA19-AB18 -> -20278
A20: =Gen!C27 -> 0.1169 | B20: =Gen!B27 -> 44091 | D20: =E19 -> 8820.7 | E20: 8822.4 | F20: =SUM(E20-D20)*120 -> 204 | H20: =B20 -> 44091 | J20: ='Water-Meter'!G22 -> 38000 | K20: ='Water-Meter'!G22 -> 38000 | L20: =SUM(K20-J20) -> 0 | M20: =H20 -> 44091 | O20: ='Water-Meter'!J22 -> 8038 | P20: ='Water-Meter'!J22 -> 8038 | Q20: =N20-O19 -> -8038 | R20: =SUM(Q20/1615) -> -4.9770898 | S20: =Gen!T27 -> 1018.07 | T20: =M20 -> 44091 | V20: =W19 -> 7823.4 | W20: 7823.8 | X20: =(W20-V20)*200 -> 80 | Y20: =T20 -> 44091 | AB20: ='Water-Meter'!P22 -> 20282 | AC20: =AA20-AB19 -> -20280
A21: =Gen!C28 -> 0.1429 | B21: =Gen!B28 -> 44092 | D21: =E20 -> 8822.4 | E21: 8824.2 | F21: =SUM(E21-D21)*120 -> 216 | H21: =B21 -> 44092 | J21: ='Water-Meter'!G23 -> 38000 | K21: ='Water-Meter'!G23 -> 38000 | L21: =SUM(K21-J21) -> 0 | M21: =H21 -> 44092 | O21: ='Water-Meter'!J23 -> 8039 | P21: ='Water-Meter'!J23 -> 8039 | Q21: =N21-O20 -> -8038 | R21: =SUM(Q21/1615) -> -4.9770898 | S21: =Gen!T28 -> 1041.27 | T21: =M21 -> 44092 | V21: =W20 -> 7823.8 | W21: 7824.1 | X21: =(W21-V21)*200 -> 60 | Y21: =T21 -> 44092 | AB21: ='Water-Meter'!P23 -> 20284 | AC21: =AA21-AB20 -> -20282
A22: =Gen!C29 -> 0.0909 | B22: =Gen!B29 -> 44093 | D22: =E21 -> 8824.2 | E22: 8826.1 | F22: =SUM(E22-D22)*120 -> 228 | H22: =B22 -> 44093 | J22: ='Water-Meter'!G24 -> 38000 | K22: ='Water-Meter'!G24 -> 38000 | L22: =SUM(K22-J22) -> 0 | M22: =H22 -> 44093 | O22: ='Water-Meter'!J24 -> 8040 | P22: ='Water-Meter'!J24 -> 8040 | Q22: =N22-O21 -> -8039 | R22: =SUM(Q22/1615) -> -4.977709 | S22: =Gen!T29 -> 1129.88 | T22: =M22 -> 44093 | V22: =W21 -> 7824.1 | W22: 7824.5 | X22: =(W22-V22)*200 -> 80 | Y22: =T22 -> 44093 | AB22: ='Water-Meter'!P24 -> 20286 | AC22: =AA22-AB21 -> -20284
A23: =Gen!C30 -> 0.0649 | B23: =Gen!B30 -> 44094 | D23: =E22 -> 8826.1 | E23: 8827.8 | F23: =SUM(E23-D23)*120 -> 204 | H23: =B23 -> 44094 | J23: ='Water-Meter'!G25 -> 38000 | K23: ='Water-Meter'!G26 -> 38000 | L23: =SUM(K23-J23) -> 0 | M23: =H23 -> 44094 | O23: ='Water-Meter'!J25 -> 8042 | P23: ='Water-Meter'!J25 -> 8042 | Q23: =N23-O22 -> -8040 | R23: =SUM(Q23/1615) -> -4.9783282 | S23: =Gen!T30 -> 1055.66 | T23: =M23 -> 44094 | V23: =W22 -> 7824.5 | W23: 7824.9 | X23: =(W23-V23)*200 -> 80 | Y23: =T23 -> 44094 | AB23: ='Water-Meter'!P25 -> 20288 | AC23: =AA23-AB22 -> -20286
A24: =Gen!C31 -> 0.0649 | B24: =Gen!B31 -> 44095 | D24: =SUM(E23) -> 8827.8 | E24: 8829.5 | F24: =SUM(E24-D24)*120 -> 204 | H24: =B24 -> 44095 | J24: ='Water-Meter'!G26 -> 38000 | K24: ='Water-Meter'!G27 -> 38000 | L24: =SUM(K24-J24) -> 0 | M24: =H24 -> 44095 | O24: ='Water-Meter'!J26 -> 8042 | P24: ='Water-Meter'!J26 -> 8042 | Q24: =N24-O23 -> -8042 | R24: =SUM(Q24/1615) -> -4.9795666 | S24: =Gen!T31 -> 957.7 | T24: 5835.7 | V24: =W23 -> 7824.9 | W24: 7825.2 | X24: =(W24-V24)*200 -> 60 | Y24: =T24 -> 5835.7 | AB24: ='Water-Meter'!P26 -> 20290 | AC24: =AA24-AB23 -> -20288
A25: =Gen!C32 -> 0.026 | B25: =Gen!B32 -> 44096 | D25: =SUM(E24) -> 8829.5 | E25: 8831.2 | F25: =SUM(E25-D25)*120 -> 204 | H25: =B25 -> 44096 | J25: ='Water-Meter'!G27 -> 38000 | K25: ='Water-Meter'!G28 -> 38000 | L25: =SUM(K25-J25) -> 0 | M25: =H25 -> 44096 | O25: ='Water-Meter'!J27 -> 8043 | P25: ='Water-Meter'!J27 -> 8043 | Q25: =N25-O24 -> -8042 | R25: =SUM(Q25/1615) -> -4.9795666 | S25: =Gen!T32 -> 982.5 | T25: =M25 -> 44096 | V25: =W24 -> 7825.2 | W25: 7825.2 | X25: =(W25-V25)*200 -> 0 | Y25: =T25 -> 44096 | AB25: ='Water-Meter'!P27 -> 20292 | AC25: =AA25-AB24 -> -20290
A26: =Gen!C33 -> 0.026 | B26: =Gen!B33 -> 44097 | D26: =SUM(E25) -> 8831.2 | E26: 8833.1 | F26: =SUM(E26-D26)*120 -> 228 | H26: =B26 -> 44097 | J26: ='Water-Meter'!G28 -> 38000 | K26: ='Water-Meter'!G29 -> 38000 | L26: =SUM(K26-J26) -> 0 | M26: =H26 -> 44097 | O26: ='Water-Meter'!J28 -> 8044 | P26: ='Water-Meter'!J28 -> 8044 | Q26: =N26-O25 -> -8043 | R26: =SUM(Q26/1615) -> -4.9801858 | S26: =Gen!T33 -> 989.79 | T26: =M26 -> 44097 | V26: =W25 -> 7825.2 | W26: 7825.7 | X26: =(W26-V26)*200 -> 100 | Y26: =T26 -> 44097 | AB26: ='Water-Meter'!P28 -> 20294 | AC26: =AA26-AB25 -> -20292
A27: =Gen!C34 -> 0.013 | B27: =Gen!B34 -> 44098 | D27: =SUM(E26) -> 8833.1 | E27: 8834.8 | F27: =SUM(E27-D27)*120 -> 204 | H27: =B27 -> 44098 | J27: ='Water-Meter'!G29 -> 38000 | K27: ='Water-Meter'!G30 -> 38000 | L27: =SUM(K27-J27) -> 0 | M27: =H27 -> 44098 | O27: ='Water-Meter'!J29 -> 8045 | P27: ='Water-Meter'!J29 -> 8045 | Q27: =N27-O26 -> -8044 | R27: =SUM(Q27/1615) -> -4.980805 | S27: =Gen!T34 -> 1004.25 | T27: =M27 -> 44098 | V27: =W26 -> 7825.7 | W27: 7826.3 | X27: =(W27-V27)*200 -> 120 | Y27: =T27 -> 44098 | AB27: ='Water-Meter'!P29 -> 20297 | AC27: =AA27-AB26 -> -20294
A28: =Gen!C35 -> 0.013 | B28: =Gen!B35 -> 44099 | D28: =SUM(E27) -> 8834.8 | E28: 8836.4 | F28: =SUM(E28-D28)*120 -> 192 | H28: =B28 -> 44099 | J28: ='Water-Meter'!G30 -> 38000 | K28: ='Water-Meter'!G31 -> 38000 | L28: =SUM(K28-J28) -> 0 | M28: =H28 -> 44099 | O28: ='Water-Meter'!J30 -> 8046 | P28: ='Water-Meter'!J30 -> 8046 | Q28: =N28-O27 -> -8045 | R28: =SUM(Q28/1615) -> -4.9814241 | S28: =Gen!T35 -> 1019.08 | T28: =M28 -> 44099 | V28: =W27 -> 7826.3 | W28: 7826.8 | X28: =(W28-V28)*200 -> 100 | Y28: =T28 -> 44099 | AB28: ='Water-Meter'!P30 -> 20303 | AC28: =AA28-AB27 -> -20297
A29: =Gen!C36 -> 0.026 | B29: =Gen!B36 -> 44100 | D29: =SUM(E28) -> 8836.4 | E29: 8838.1 | F29: =SUM(E29-D29)*120 -> 204 | H29: =B29 -> 44100 | J29: ='Water-Meter'!G31 -> 38000 | K29: ='Water-Meter'!G32 -> 38000 | L29: =SUM(K29-J29) -> 0 | M29: =H29 -> 44100 | O29: ='Water-Meter'!J31 -> 8047 | P29: ='Water-Meter'!J31 -> 8047 | Q29: =N29-O28 -> -8046 | R29: =SUM(Q29/1615) -> -4.9820433 | S29: =Gen!T36 -> 878.8 | T29: =M29 -> 44100 | V29: =W28 -> 7826.8 | W29: 7827 | X29: =(W29-V29)*200 -> 40 | Y29: =T29 -> 44100 | AB29: ='Water-Meter'!P31 -> 20307 | AC29: =AA29-AB28 -> -20303
A30: =Gen!C37 -> 0.0519 | B30: =Gen!B37 -> 44101 | D30: =SUM(E29) -> 8838.1 | E30: 8839.7 | F30: =SUM(E30-D30)*120 -> 192 | H30: =B30 -> 44101 | J30: ='Water-Meter'!G32 -> 38000 | K30: ='Water-Meter'!G33 -> 38000 | L30: =SUM(K30-J30) -> 0 | M30: =H30 -> 44101 | O30: ='Water-Meter'!J32 -> 8048 | P30: ='Water-Meter'!J32 -> 8048 | Q30: =N30-O29 -> -8047 | R30: =SUM(Q30/1615) -> -4.9826625 | S30: =Gen!T37 -> 975.74 | T30: =M30 -> 44101 | V30: =W29 -> 7827 | W30: 7827.2 | X30: =(W30-V30)*200 -> 40 | Y30: =T30 -> 44101 | AB30: ='Water-Meter'!P32 -> 20310 | AC30: =AA30-AB29 -> -20307
A31: =Gen!C38 -> 0.0519 | B31: =Gen!B38 -> 44102 | D31: =SUM(E30) -> 8839.7 | E31: 8841.4 | F31: =SUM(E31-D31)*120 -> 204 | H31: =B31 -> 44102 | J31: ='Water-Meter'!G33 -> 38000 | K31: ='Water-Meter'!G34 -> 0 | L31: =SUM(K31-J31) -> -38000 | M31: =H31 -> 44102 | O31: ='Water-Meter'!J33 -> 8048 | P31: ='Water-Meter'!J33 -> 8048 | Q31: =N31-O30 -> -8048 | R31: =SUM(Q31/1615) -> -4.9832817 | S31: =Gen!T38 -> 969.39 | T31: =M31 -> 44102 | V31: =W30 -> 7827.2 | W31: 7827.7 | X31: =(W31-V31)*200 -> 100 | Y31: =T31 -> 44102 | AB31: ='Water-Meter'!P33 -> 20312 | AC31: =AA31-AB30 -> -20310
A32: =Gen!C39 -> 0.0519 | B32: =Gen!B39 -> 44103 | D32: =SUM(E31) -> 8841.4 | F32: =SUM(E32-D32)*120 -> -1060968 | H32: =B32 -> 44103 | J32: ='Water-Meter'!G34 -> 0 | K32: ='Water-Meter'!G34 -> 0 | L32: =SUM(K32-J32) -> 0 | M32: =H32 -> 44103 | O32: ='Water-Meter'!J34 -> 0 | P32: ='Water-Meter'!J34 -> 0 | Q32: =N32-O31 -> -8048 | R32: =SUM(Q32/1615) -> -4.9832817 | S32: =Gen!T39 -> 0 | T32: =M32 -> 44103 | V32: =W31 -> 7827.7 | X32: =(W32-V32)*200 -> -1565540 | Y32: =T32 -> 44103 | AB32: ='Water-Meter'!P34 -> 0 | AC32: =AA32-AB31 -> -20312
A33: =Gen!C40 -> 0 | B33: =Gen!B40 -> 44104 | D33: =SUM(E32) -> 0 | F33: =SUM(E33-D33)*120 -> 0 | H33: =B33 -> 44104 | J33: ='Water-Meter'!G35 -> 0 | K33: ='Water-Meter'!G35 -> 0 | L33: =SUM(K33-J33) -> 0 | M33: =H33 -> 44104 | O33: ='Water-Meter'!J35 -> 0 | P33: ='Water-Meter'!J35 -> 0 | Q33: =N33-O32 -> 0 | R33: =SUM(Q33/1615) -> 0 | S33: =Gen!T40 -> 0 | T33: =M33 -> 44104 | V33: =W32 -> 0 | X33: =(W33-V33)*200 -> 0 | Y33: =T33 -> 44104 | AB33: ='Water-Meter'!P35 -> 0 | AC33: =AA33-AB32 -> 0
A34: =Gen!C41 -> 0 | B34: =Gen!B41 -> 0 | D34: =SUM(E33) -> 0 | F34: =SUM(E34-D34)*120 -> 0 | H34: =B34 -> 0 | J34: ='Water-Meter'!G36 -> 0 | K34: ='Water-Meter'!G36 -> 0 | L34: =SUM(K34-J34) -> 0 | M34: =H34 -> 0 | O34: ='Water-Meter'!J36 -> 0 | P34: ='Water-Meter'!J36 -> 0 | Q34: =N34-O33 -> 0 | R34: =SUM(Q34/1615) -> 0 | S34: =Gen!T41 -> 0 | T34: =M34 -> 0 | V34: =SUM(W33) -> 0 | X34: =(W34-V34)*200 -> 0 | Y34: =T34 -> 0 | AB34: ='Water-Meter'!P36 -> 0 | AC34: =AA34-AB33 -> 0
A35: =[1]Gen!B42 -> #REF! | B35: =[1]Gen!A42 -> #REF! | D35: =SUM(E34) -> 0 | F35: =SUM(F4:F6) -> 588 | H35: =B35 -> #REF! | J35: =SUM(K34) -> 0 | K35: ='Water-Meter'!G37 -> 0 | L35: =SUM(L5:L34) -> -38000 | M35: =H35 -> #REF! | P35: ='Water-Meter'!J37 -> 0 | Q35: =N35-O34 -> 0 | R35: =SUM(Q35/1615) -> 0 | S35: =Gen!T42 -> 0 | T35: =M35 -> #REF! | V35: =SUM(W34) -> 0 | X35: =(W35-V35)*200 -> 0 | Y35: =T35 -> #REF! | AB35: ='Water-Meter'!P37 -> 0 | AC35: =AA35-AB34 -> 0
X36: =SUM(X4:X6) -> 140

Sheet Summery Report
A2: Generator and Diseal Summry Report August 2020
A4: Date | B4: Gen Set Hours Working | C4: Occ% | D4: Total OCC Room | E4: Guest Room Occ | F4: Total Kwh Generated | G4: Diesel consumed by Gen (Ltrs) | H4: Diesel consumed by Vehicle (Ltrs) | I4: Total diesel consumed (Ltrs) | J4: Balance stock of Diesel (Ltrs) | K4: Water consumed | L4: Gas consumed (KG)
A5: =Gen!B11 -> 44075 | B5: ='Daily report Gen'!AC6 -> 25 | C5: =Gen!C11 -> 0.039 | D5: =E5 -> 3 | E5: 3 | F5: =Gen!U9 -> 0 | G5: =Gen!T9 -> 0 | H5: =Gen!AK11 -> 69.21 | I5: =SUM(G5:H5) -> 69.21 | J5: =Gen!D11 -> 41590.62 | K5: ='Water-Meter'!E6 -> 56 | L5: ='Lpg (2)'!G10 -> 76.032 | M5: =SUM(#REF!-#REF!) -> #REF!
A6: =Gen!B12 -> 44076 | B6: ='Daily report Gen'!AC7 -> 24 | C6: =Gen!C12 -> 0.039 | D6: =E6 -> 4 | E6: 4 | F6: =Gen!U10 -> 0 | G6: =Gen!T10 -> 0 | H6: =Gen!AK12 -> 80.65 | I6: =SUM(G6:H6) -> 80.65 | J6: =Gen!D12 -> 40629.98 | K6: ='Water-Meter'!E7 -> 58 | L6: ='Lpg (2)'!G11 -> 58.608 | M6: =SUM(#REF!-#REF!) -> #REF!
A7: =Gen!B13 -> 44077 | B7: ='Daily report Gen'!AC8 -> 24 | C7: =Gen!C13 -> 0.039 | D7: =E7 -> 4 | E7: 4 | F7: =Gen!U11 -> 2111 | G7: =Gen!T11 -> 891.43 | H7: =Gen!AK13 -> 10.02 | I7: =SUM(G7:H7) -> 901.45 | J7: =Gen!D13 -> 39727.41 | K7: ='Water-Meter'!E8 -> 51 | L7: ='Lpg (2)'!G12 -> 66.264 | M7: =SUM(#REF!-#REF!) -> #REF!
A8: =Gen!B14 -> 44078 | B8: ='Daily report Gen'!AC9 -> 25 | C8: =Gen!C14 -> 0.0909 | D8: =E8 -> 8 | E8: 8 | F8: =Gen!U12 -> 2147 | G8: =Gen!T12 -> 821.92 | H8: =Gen!AK14 -> 0 | I8: =SUM(G8:H8) -> 821.92 | J8: =Gen!D14 -> 38627.11 | K8: ='Water-Meter'!E9 -> 54 | L8: ='Lpg (2)'!G13 -> 63.536 | M8: =SUM(#REF!-#REF!) -> #REF!
A9: =Gen!B15 -> 44079 | B9: ='Daily report Gen'!AC10 -> 24 | C9: =Gen!C15 -> 0.0909 | D9: =E9 -> 8 | E9: 8 | F9: =Gen!U13 -> 2188 | G9: =Gen!T13 -> 1090.28 | H9: =Gen!AK15 -> 27.01 | I9: =SUM(G9:H9) -> 1117.29 | J9: =Gen!D15 -> 37758.72 | K9: ='Water-Meter'!E10 -> 50 | L9: ='Lpg (2)'!G14 -> 50.072 | M9: =SUM(#REF!-#REF!) -> #REF!
A10: =Gen!B16 -> 44080 | B10: ='Daily report Gen'!AC11 -> 23 | C10: =Gen!C16 -> 0.0909 | D10: =E10 -> 7 | E10: 7 | F10: =Gen!U14 -> 2448 | G10: =Gen!T14 -> 868.39 | H10: =Gen!AK16 -> 0 | I10: =SUM(G10:H10) -> 868.39 | J10: =Gen!D16 -> 36889.73 | K10: ='Water-Meter'!E11 -> 52 | L10: ='Lpg (2)'!G15 -> 49.588 | M10: =SUM(#REF!-#REF!) -> #REF!
A11: =Gen!B17 -> 44081 | B11: ='Daily report Gen'!AC12 -> 27 | C11: =Gen!C17 -> 0.026 | D11: =E11 -> 3 | E11: 3 | F11: =Gen!U15 -> 2152 | G11: =Gen!T15 -> 841.98 | H11: =Gen!AK17 -> 258.14 | I11: =SUM(G11:H11) -> 1100.12 | J11: =Gen!D17 -> 35951.19 | K11: ='Water-Meter'!E12 -> 58 | L11: ='Lpg (2)'!G16 -> 62.568 | M11: =SUM(#REF!-#REF!) -> #REF!
A12: =Gen!B18 -> 44082 | B12: ='Daily report Gen'!AC13 -> 25 | C12: =Gen!C18 -> 0.039 | D12: =E12 -> 7 | E12: 7 | F12: =Gen!U16 -> 2052 | G12: =Gen!T16 -> 938.54 | H12: =Gen!AK18 -> 123.3 | I12: =SUM(G12:H12) -> 1061.84 | J12: =Gen!D18 -> 34782.78 | K12: ='Water-Meter'!E13 -> 46 | L12: ='Lpg (2)'!G17 -> 54.868 | M12: =SUM(#REF!-#REF!) -> #REF!
A13: =Gen!B19 -> 44083 | B13: ='Daily report Gen'!AC14 -> 23 | C13: =Gen!C19 -> 0.065 | D13: =E13 -> 5 | E13: 5 | F13: =Gen!U17 -> 2010 | G13: =Gen!T17 -> 910.27 | H13: =Gen!AK19 -> 0 | I13: =SUM(G13:H13) -> 910.27 | J13: =Gen!D19 -> 33711.27 | K13: ='Water-Meter'!E14 -> 52 | L13: ='Lpg (2)'!G18 -> 57.42 | M13: =SUM(#REF!-#REF!) -> #REF!
A14: =Gen!B20 -> 44084 | B14: ='Daily report Gen'!AC15 -> 24 | C14: =Gen!C20 -> 0.013 | D14: =E14 -> 1 | E14: 1 | F14: =Gen!U18 -> 2245 | G14: =Gen!T18 -> 948.21 | H14: =Gen!AK20 -> 0 | I14: =SUM(G14:H14) -> 948.21 | J14: =Gen!D20 -> 32794.94 | K14: ='Water-Meter'!E15 -> 55 | L14: ='Lpg (2)'!G19 -> 44 | M14: =SUM(#REF!-#REF!) -> #REF!
A15: =Gen!B21 -> 44085 | B15: ='Daily report Gen'!AC16 -> 13 | C15: =Gen!C21 -> 0.039 | D15: =E15 -> 3 | E15: 3 | F15: =Gen!U19 -> 2101 | G15: =Gen!T19 -> 916.33 | H15: =Gen!AK21 -> 0 | I15: =SUM(G15:H15) -> 916.33 | J15: =Gen!D21 -> 31816.9 | K15: ='Water-Meter'!E16 -> 94 | L15: ='Lpg (2)'!G20 -> 70.928 | M15: =SUM(#REF!-#REF!) -> #REF!
A16: =Gen!B22 -> 44086 | B16: ='Daily report Gen'!AC17 -> 24 | C16: =Gen!C22 -> 0.02 | D16: =E16 -> 3 | E16: 3 | F16: =Gen!U20 -> 2199 | G16: =Gen!T20 -> 978.04 | H16: =Gen!AK22 -> 0 | I16: =SUM(G16:H16) -> 978.04 | J16: =Gen!D22 -> 31034.35 | K16: ='Water-Meter'!E17 -> 59 | L16: ='Lpg (2)'!G21 -> 53.9 | M16: =SUM(#REF!-#REF!) -> #REF!
... A33: =Gen!B39 -> 44103 | B33: ='Daily report Gen'!AC34 -> -154334 | C33: =Gen!C39 -> 0.0519 | D33: =E33 -> 5 | E33: 5 | F33: =Gen!U37 -> 2327 | G33: =Gen!T37 -> 975.74 | H33: =Gen!AK39 -> 0 | I33: =SUM(G33:H33) -> 975.74 | J33: =Gen!D39 -> 41510.34 | K33: ='Water-Meter'!E34 -> 0 | L33: ='Lpg (2)'!G38 -> -318841.51 | M33: =SUM(#REF!-#REF!) -> #REF!
A34: =Gen!B40 -> 44104 | B34: ='Daily report Gen'!AC35 -> 0 | C34: =Gen!C40 -> 0 | D34: =E34 -> 0 | F34: =Gen!U38 -> 2289 | G34: =Gen!T38 -> 969.39 | H34: =Gen!AK40 -> 0 | I34: =SUM(G34:H34) -> 969.39 | J34: =Gen!D40 -> 41510.34 | K34: ='Water-Meter'!E35 -> 0 | L34: ='Lpg (2)'!G39 -> 0 | M34: =SUM(#REF!-#REF!) -> #REF!
A35: =Gen!B41 -> 0 | B35: ='Daily report Gen'!AC36 -> 0 | C35: =Gen!C41 -> 0 | D35: =E35 -> 0 | F35: =Gen!U39 -> 0 | G35: =Gen!T39 -> 0 | H35: =Gen!AK41 -> 0 | I35: =SUM(G35:H35) -> 0 | J35: =Gen!D41 -> 41510.34 | K35: ='Water-Meter'!E36 -> 0 | L35: ='Lpg (2)'!G40 -> 0 | M35: =SUM(#REF!-#REF!) -> #REF!
A36: =Gen!B42 -> 0 | B36: ='Daily report Gen'!AC37 -> 0 | C36: =Gen!C42 -> 0 | D36: =E36 -> 0 | F36: =Gen!U40 -> 0 | G36: =Gen!T40 -> 0 | H36: =Gen!AK42 -> 0 | I36: =SUM(G36:H36) -> 0 | J36: =Gen!D42 -> 41510.34 | K36: ='Water-Meter'!E37 -> 0 | L36: ='Lpg (2)'!G41 -> 0

Sheet Daily report Gen
A1: =A6 -> 44075
N3: GENERATOR NO.1 | Q3: GENERATOR NO.2 | T3: GENERATOR NO.4 | W3: GENERATOR NO.5 | Z3: GENERATOR NO.6
A4: DATE | B4: OCC% | C4: D-TANK A | D4: D-TANK B | E4: DELIVERY DATE | F4: DELIVERY | G4: ISSUED-VEHICLE | H4: OTHERS | I4: M-R LV PANEL 1. KWH | J4: KWH PRODUCTIONS | K4: M-R LV PANEL 2. KWH | L4: KWH PRODUCTIONS | M4: TOTAL KWH PRODUCTIONS | N4: OPEN HRS READING | O4: CLOSE HRS READING | P4: RUNNING HRS | Q4: OPEN HRS READING | R4: CLOSE HRS READING | S4: RUNNING HRS | T4: OPEN HRS READING | U4: CLOSE HRS READING | V4: RUNNING HRS | W4: OPEN HRS READING | X4: CLOSE HRS READING | Y4: RUNNING HRS | Z4: OPEN HRS READING | AA4: CLOSE HRS READING | AB4: RUNNING HRS | AC4: TOTAL RUNNING HRS | AD4: MAX KW | AE4: MIN-KW | AF4: TOTAL DIESEL CONS.
J5: X200 | L5: X200 | O5: 34999 | R5: 30116 | U5: 35490 | X5: 32209 | AA5: 20830 | AD5: 150 | AE5: 74
A6: =Gen!B11 -> 44075 | B6: 0.039 | C6: 22190.42 | D6: 16140.2 | G6: 69.21 | I6: 30924.4 | J6: =SUM(I7-I6)*351 -> 1158.3 | K6: 20515.4 | L6: =SUM(K7-K6)*351 -> 947.7 | M6: =J6+L6 -> 2106 | N6: =O5 -> 34999 | O6: 35011 | P6: =O6-N6 -> 12 | Q6: =R5 -> 30116 | R6: 30116 | S6: =R6-Q6 -> 0 | T6: =U5 -> 35490 | U6: 35491 | V6: =U6-T6 -> 1 | W6: =X5 -> 32209 | X6: 32220 | Y6: =X6-W6 -> 11 | Z6: =AA5 -> 20830 | AA6: 20831 | AB6: =AA6-Z6 -> 1 | AC6: =AB6+Y6+V6+S6+P6 -> 25 | AD6: 160 | AE6: 100 | AF6: =Gen!T11 -> 891.43
A7: =Gen!B12 -> 44076 | B7: 0.039 | C7: 21229.78 | D7: 16140.2 | G7: 80.65 | I7: 30927.7 | J7: =SUM(I8-I7)*351 -> 1193.4 | K7: 20518.1 | L7: =SUM(K8-K7)*351 -> 982.8 | M7: =J7+L7 -> 2176.2 | N7: =O6 -> 35011 | O7: 35012 | P7: =O7-N7 -> 1 | Q7: =R6 -> 30116 | R7: 30127 | S7: =R7-Q7 -> 11 | T7: =U6 -> 35491 | U7: 35503 | V7: =U7-T7 -> 12 | W7: =X6 -> 32220 | X7: 32220 | Y7: =X7-W7 -> 0 | Z7: =AA6 -> 20831 | AA7: 20831 | AB7: =AA7-Z7 -> 0 | AC7: =AB7+Y7+V7+S7+P7 -> 24 | AD7: 200 | AE7: 98 | AF7: =Gen!T12 -> 821.92
A8: =Gen!B13 -> 44077 | B8: 0.039 | C8: 20407.86 | D8: 16140.2 | G8: 10.02 | I8: 30931.1 | J8: =SUM(I9-I8)*351 -> 1088.1 | K8: 20520.9 | L8: =SUM(K9-K8)*351 -> 1053 | M8: =J8+L8 -> 2141.1 | N8: =O7 -> 35012 | O8: 35024 | P8: =O8-N8 -> 12 | Q8: =R7 -> 30127 | R8: 30127 | S8: =R8-Q8 -> 0 | T8: =U7 -> 35503 | U8: 35504 | V8: =U8-T8 -> 1 | W8: =X7 -> 32220 | X8: 32220 | Y8: =X8-W8 -> 0 | Z8: =AA7 -> 20831 | AA8: 20842 | AB8: =AA8-Z8 -> 11 | AC8: =AB8+Y8+V8+S8+P8 -> 24 | AD8: 220 | AE8: 120 | AF8: =Gen!T13 -> 1090.28
A9: =Gen!B14 -> 44078 | B9: 0.0909 | C9: 19227.93 | D9: 16140.2 | I9: 30934.2 | J9: =SUM(I10-I9)*351 -> 1228.5 | K9: 20523.9 | L9: =SUM(K10-K9)*351 -> 1158.3 | M9: =J9+L9 -> 2386.8 | N9: =O8 -> 35024 | O9: 35024 | P9: =O9-N9 -> 0 | Q9: =R8 -> 30127 | R9: 30127 | S9: =R9-Q9 -> 0 | T9: =U8 -> 35504 | U9: 35504 | V9: =U9-T9 -> 0 | W9: =X8 -> 32220 | X9: 32233 | Y9: =X9-W9 -> 13 | Z9: =AA8 -> 20842 | AA9: 20854 | AB9: =AA9-Z9 -> 12 | AC9: =AB9+Y9+V9+S9+P9 -> 25 | AD9: 180 | AE9: 100 | AF9: =Gen!T14 -> 868.39
A10: =Gen!B15 -> 44079 | B10: 0.0909 | C10: 18358.52 | D10: 16140.2 | G10: 27.01 | I10: 30937.7 | J10: =SUM(I11-I10)*351 -> 2246.4 | K10: 20527.2 | L10: =SUM(K11-K10)*351 -> 2070.9 | M10: =J10+L10 -> 4317.3 | N10: =O9 -> 35024 | O10: 35036 | P10: =O10-N10 -> 12 | Q10: =R9 -> 30127 | R10: 30139 | S10: =R10-Q10 -> 12 | T10: =U9 -> 35504 | U10: 35504 | V10: =U10-T10 -> 0 | W10: =X9 -> 32233 | X10: 32233 | Y10: =X10-W10 -> 0 | Z10: =AA9 -> 20854 | AA10: 20854 | AB10: =AA10-Z10 -> 0 | AC10: =AB10+Y10+V10+S10+P10 -> 24 | AD10: 130 | AE10: 75 | AF10: =Gen!T15 -> 841.98
A11: =Gen!B16 -> 44080 | B11: 0.0909 | C11: 17489.53 | D11: 16140.2 | I11: 30944.1 | J11: =SUM(I12-I11)*351 -> 1053 | K11: 20533.1 | L11: =SUM(K12-K11)*351 -> 1053 | M11: =J11+L11 -> 2106 | N11: =O10 -> 35036 | O11: 35036 | P11: =O11-N11 -> 0 | Q11: =R10 -> 30139 | R11: 30139 | S11: =R11-Q11 -> 0 | T11: =U10 -> 35504 | U11: 35515 | V11: =U11-T11 -> 11 | W11: =X10 -> 32233 | X11: 32245 | Y11: =X11-W11 -> 12 | Z11: =AA10 -> 20854 | AA11: 20854 | AB11: =AA11-Z11 -> 0 | AC11: =AB11+Y11+V11+S11+P11 -> 23 | AD11: 180 | AE11: 99 | AF11: =Gen!T16 -> 938.54
A12: =Gen!B17 -> 44081 | B12: 0.026 | C12: 16550.99 | D12: 16140.2 | G12: 258.14 | I12: 30947.1 | J12: =SUM(I13-I12)*351 -> 1123.2 | K12: 20536.1 | L12: =SUM(K13-K12)*351 -> 1053 | M12: =J12+L12 -> 2176.2 | N12: =O11 -> 35036 | O12: 35049 | P12: =O12-N12 -> 13 | Q12: =R11 -> 30139 | R12: 30140 | S12: =R12-Q12 -> 1 | T12: =U11 -> 35515 | U12: 35515 | V12: =U12-T12 -> 0 | W12: =X11 -> 32245 | X12: 32246 | Y12: =X12-W12 -> 1 | Z12: =AA11 -> 20854 | AA12: 20866 | AB12: =AA12-Z12 -> 12 | AC12: =AB12+Y12+V12+S12+P12 -> 27 | AD12: 200 | AE12: 110 | AF12: =Gen!T17 -> 910.27
A13: =Gen!B18 -> 44082 | B13: 0.039 | C13: 15382.58 | D13: 16140.2 | G13: 123.3 | I13: 30950.3 | J13: =SUM(I14-I13)*351 -> 1088.1 | K13: 20539.1 | L13: =SUM(K14-K13)*351 -> 912.6 | M13: =J13+L13 -> 2000.7 | N13: =O12 -> 35049 | O13: 35049 | P13: =O13-N13 -> 0 | Q13: =R12 -> 30140 | R13: 30152 | S13: =R13-Q13 -> 12 | T13: =U12 -> 35515 | U13: 35528 | V13: =U13-T13 -> 13 | W13: =X12 -> 32246 | X13: 32246 | Y13: =X13-W13 -> 0 | Z13: =AA12 -> 20866 | AA13: 20866 | AB13: =AA13-Z13 -> 0 | AC13: =AB13+Y13+V13+S13+P13 -> 25 | AD13: 200 | AE13: 100 | AF13: =Gen!T18 -> 948.21
A14: =Gen!B19 -> 44083 | B14: 0.065 | C14: 14311.07 | D14: 16140.2 | I14: 30953.4 | J14: =SUM(I15-I14)*351 -> 1158.3 | K14: 20541.7 | L14: =SUM(K15-K14)*351 -> 947.7 | M14: =J14+L14 -> 2106 | N14: =O13 -> 35049 | O14: 35049 | P14: =O14-N14 -> 0 | Q14: =R13 -> 30152 | R14: 30152 | S14: =R14-Q14 -> 0 | T14: =U13 -> 35528 | U14: 35528 | V14: =U14-T14 -> 0 | W14: =X13 -> 32246 | X14: 32257 | Y14: =X14-W14 -> 11 | Z14: =AA13 -> 20866 | AA14: 20878 | AB14: =AA14-Z14 -> 12 | AC14: =AB14+Y14+V14+S14+P14 -> 23 | AD14: 180 | AE14: 90 | AF14: =Gen!T19 -> 916.33
A15: =Gen!B20 -> 44084 | B15: 0.013 | C15: 13394.74 | D15: 16140.2 | I15: 30956.7 | J15: =SUM(I16-I15)*351 -> 0 | K15: 20544.4 | L15: =SUM(K16-K15)*351 -> -7211084.4 | M15: =J15+L15 -> -7211084.4 | N15: =O14 -> 35049 | O15: 35060 | P15: =O15-N15 -> 11 | Q15: =R14 -> 30152 | R15: 30152 | S15: =R15-Q15 -> 0 | T15: =U14 -> 35528 | U15: 35540 | V15: =U15-T15 -> 12 | W15: =X14 -> 32257 | X15: 32258 | Y15: =X15-W15 -> 1 | Z15: =AA14 -> 20878 | AA15: 20878 | AB15: =AA15-Z15 -> 0 | AC15: =AB15+Y15+V15+S15+P15 -> 24 | AD15: 190 | AE15: 90 | AF15: =Gen!T20 -> 978.04
A16: =Gen!B21 -> 44085 | B16: 0.039 | C16: 12416.7 | D16: 16140.2 | I16: 30956.7 | J16: =SUM(I17-I16)*351 -> 1228.5 | L16: =SUM(K17-K16)*351 -> 7212032.1 | M16: =J16+L16 -> 7213260.6 | N16: =O15 -> 35060 | O16: 35060 | P16: =O16-N16 -> 0 | Q16: =R15 -> 30152 | R16: 30152 | S16: =R16-Q16 -> 0 | T16: =U15 -> 35540 | U16: 35540 | V16: =U16-T16 -> 0 | W16: =X15 -> 32258 | X16: 32258 | Y16: =X16-W16 -> 0 | Z16: =AA15 -> 20878 | AA16: 20891 | AB16: =AA16-Z16 -> 13 | AC16: =AB16+Y16+V16+S16+P16 -> 13 | AD16: 160 | AE16: 75 | AF16: =Gen!T21 -> 782.55
A17: =Gen!B22 -> 44086 | B17: 0.02 | C17: =Gen!D22-'Daily report Gen'!D17 -> 14894.15 | D17: 16140.2 | I17: 30960.2 | J17: =SUM(I18-I17)*351 -> 2211.3 | K17: 20547.1 | L17: =SUM(K18-K17)*351 -> 1895.4 | M17: =J17+L17 -> 4106.7 | N17: =O16 -> 35060 | O17: 35060 | P17: =O17-N17 -> 0 | Q17: =R16 -> 30152 | R17: 30164 | S17: =R17-Q17 -> 12 | T17: =U16 -> 35540 | U17: 35540 | V17: =U17-T17 -> 0 | W17: =X16 -> 32258 | X17: 32258 | Y17: =X17-W17 -> 0 | Z17: =AA16 -> 20891 | AA17: 20903 | AB17: =AA17-Z17 -> 12 | AC17: =AB17+Y17+V17+S17+P17 -> 24 | AD17: 200 | AE17: 90 | AF17: =Gen!T22 -> 732.78
A18: =Gen!B23 -> 44087 | B18: 0.03 | C18: 10901.37 | D18: 16140.2 | I18: 30966.5 | J18: =SUM(I19-I18)*351 -> 1158.3 | K18: 20552.5 | L18: =SUM(K19-K18)*351 -> 912.6 | M18: =J18+L18 -> 2070.9 | N18: =O17 -> 35060 | O18: 35060 | P18: =O18-N18 -> 0 | Q18: =R17 -> 30164 | R18: 30164 | S18: =R18-Q18 -> 0 | T18: =U17 -> 35540 | U18: 35540 | V18: =U18-T18 -> 0 | W18: =X17 -> 32258 | X18: 32270 | Y18: =X18-W18 -> 12 | Z18: =AA17 -> 20903 | AA18: 20903 | AB18: =AA18-Z18 -> 0 | AC18: =AB18+Y18+V18+S18+P18 -> 12 | AD18: 190 | AE18: 99 | AF18: =Gen!T23 -> 935.74
A19: =Gen!B24 -> 44088 | B19: 0.04 | C19: 9894.59 | D19: 16140.2 | I19: 30969.8 | J19: =SUM(I20-I19)*351 -> 1193.4 | K19: 20555.1 | L19: =SUM(K20-K19)*351 -> 912.6 | M19: =J19+L19 -> 2106 | N19: =O18 -> 35060 | O19: 35073 | P19: =O19-N19 -> 13 | Q19: =R18 -> 30164 | R19: 30164 | S19: =R19-Q19 -> 0 | T19: =U18 -> 35540 | U19: 35540 | V19: =U19-T19 -> 0 | W19: =X18 -> 32270 | X19: 32282 | Y19: =X19-W19 -> 12 | Z19: =AA18 -> 20903 | AA19: 20903 | AB19: =AA19-Z19 -> 0 | AC19: =AB19+Y19+V19+S19+P19 -> 25 | AD19: 200 | AE19: 110 | AF19: =Gen!T24 -> 890.09
A20: =Gen!B25 -> 44089 | B20: 0.03 | C20: 9004.5 | D20: 16140.2 | I20: 30973.2 | J20: =SUM(I21-I20)*351 -> 1368.9 | K20: 20557.7 | L20: =SUM(K21-K20)*351 -> 1474.2 | M20: =J20+L20 -> 2843.1 | N20: =O19 -> 35073 | O20: 35086 | P20: =O20-N20 -> 13 | Q20: =R19 -> 30164 | R20: 30164 | S20: =R20-Q20 -> 0 | T20: =U19 -> 35540 | U20: 35552 | V20: =U20-T20 -> 12 | W20: =X19 -> 32282 | X20: 32282 | Y20: =X20-W20 -> 0 | Z20: =AA19 -> 20903 | AA20: 20904 | AB20: =AA20-Z20 -> 1 | AC20: =AB20+Y20+V20+S20+P20 -> 26 | AD20: 190 | AE20: 100 | AF20: =Gen!T25 -> 888.98
A21: =Gen!B26 -> 44090 | B21: 0.11 | C21: 8115.52 | D21: 16140.2 | I21: 30977.1 | J21: =SUM(I22-I21)*351 -> 1404 | K21: 20561.9 | L21: =SUM(K22-K21)*351 -> 772.2 | M21: =J21+L21 -> 2176.2 | N21: =O20 -> 35086 | O21: 35086 | P21: =O21-N21 -> 0 | Q21: =R20 -> 30164 | R21: 30164 | S21: =R21-Q21 -> 0 | T21: =U20 -> 35552 | U21: 35564 | V21: =U21-T21 -> 12 | W21: =X20 -> 32282 | X21: 32296 | Y21: =X21-W21 -> 14 | Z21: =AA20 -> 20904 | AA21: 20904 | AB21: =AA21-Z21 -> 0 | AC21: =AB21+Y21+V21+S21+P21 -> 26 | AD21: 200 | AE21: 95 | AF21: =Gen!T26 -> 1095.46
A22: =Gen!B27 -> 44091 | B22: 0.1 | C22: 6838.92 | D22: 16140.2 | I22: 30981.1 | J22: =SUM(I23-I22)*351 -> 1404 | K22: 20564.1 | L22: =SUM(K23-K22)*351 -> 1123.2 | M22: =J22+L22 -> 2527.2 | N22: =O21 -> 35086 | O22: 35098 | P22: =O22-N22 -> 12 | Q22: =R21 -> 30164 | R22: 30164 | S22: =R22-Q22 -> 0 | T22: =U21 -> 35564 | U22: 35564 | V22: =U22-T22 -> 0 | W22: =X21 -> 32296 | X22: 32296 | Y22: =X22-W22 -> 0 | Z22: =AA21 -> 20904 | AA22: 20915 | AB22: =AA22-Z22 -> 11 | AC22: =AB22+Y22+V22+S22+P22 -> 23 | AD22: 210 | AE22: 120 | AF22: =Gen!T27 -> 1018.07
A23: =Gen!B28 -> 44092 | B23: 0.12 | C23: 15795.44 | D23: 16140.2 | I23: 30985.1 | J23: =SUM(I24-I23)*351 -> 1263.6 | K23: 20567.3 | L23: =SUM(K24-K23)*351 -> 1088.1 | M23: =J23+L23 -> 2351.7 | N23: =O22 -> 35098 | O23: 35098 | P23: =O23-N23 -> 0 | Q23: =R22 -> 30164 | R23: 30165 | S23: =R23-Q23 -> 1 | T23: =U22 -> 35564 | U23: 35577 | V23: =U23-T23 -> 13 | W23: =X22 -> 32296 | X23: 32296 | Y23: =X23-W23 -> 0 | Z23: =AA22 -> 20915 | AA23: 20927 | AB23: =AA23-Z23 -> 12 | AC23: =AB23+Y23+V23+S23+P23 -> 26 | AD23: 230 | AE23: 130 | AF23: =Gen!T28 -> 1041.27
A24: =Gen!B29 -> 44093 | B24: 0.0909 | C24: 14754.17 | D24: 16140.2 | G24: 374.38 | I24: 30988.7 | J24: =SUM(I25-I24)*351 -> 1333.8 | K24: 20570.4 | L24: =SUM(K25-K24)*351 -> 1017.9 | M24: =J24+L24 -> 2351.7 | N24: =O23 -> 35098 | O24: 35110 | P24: =O24-N24 -> 12 | Q24: =R23 -> 30165 | R24: 30165 | S24: =R24-Q24 -> 0 | T24: =U23 -> 35577 | U24: 35589 | V24: =U24-T24 -> 12 | W24: =X23 -> 32296 | X24: 32308 | Y24: =X24-W24 -> 12 | Z24: =AA23 -> 20927 | AA24: 20940 | AB24: =AA24-Z24 -> 13 | AC24: =AB24+Y24+V24+S24+P24 -> 49 | AD24: 220 | AE24: 122 | AF24: =Gen!T29 -> 1129.88
A25: =Gen!B30 -> 44094 | B25: 0.0649 | C25: 13319.02 | D25: 16140.2 | G25: 44.98 | I25: 30992.5 | J25: =SUM(I26-I25)*351 -> 1263.6 | K25: 20573.3 | L25: =SUM(K26-K25)*351 -> 1053 | M25: =J25+L25 -> 2316.6 | N25: =O24 -> 35110 | O25: 35111 | P25: =O25-N25 -> 1 | Q25: =R24 -> 30165 | R25: 30165 | S25: =R25-Q25 -> 0 | T25: =U24 -> 35589 | U25: 35601 | V25: =U25-T25 -> 12 | W25: =X24 -> 32308 | X25: 32321 | Y25: =X25-W25 -> 13 | Z25: =AA24 -> 20940 | AA25: 20940 | AB25: =AA25-Z25 -> 0 | AC25: =AB25+Y25+V25+S25+P25 -> 26 | AD25: 230 | AE25: 130 | AF25: =Gen!T30 -> 1055.66
A26: =Gen!B31 -> 44095 | B26: 0.0649 | C26: 12149.27 | D26: 16140.2 | I26: 30996.1 | J26: =SUM(I27-I26)*351 -> 1193.4 | K26: 20576.3 | L26: =SUM(K27-K26)*351 -> 1017.9 | M26: =J26+L26 -> 2211.3 | N26: =O25 -> 35111 | O26: 35122 | P26: =O26-N26 -> 11 | Q26: =R25 -> 30165 | R26: 30165 | S26: =R26-Q26 -> 0 | T26: =U25 -> 35601 | U26: 35601 | V26: =U26-T26 -> 0 | W26: =X25 -> 32321 | X26: 32321 | Y26: =X26-W26 -> 0 | Z26: =AA25 -> 20940 | AA26: 20952 | AB26: =AA26-Z26 -> 12 | AC26: =AB26+Y26+V26+S26+P26 -> 23 | AD26: 200 | AE26: 100 | AF26: =Gen!T31 -> 957.7
A27: =Gen!B32 -> 44096 | B27: 0.026 | C27: 11191.57 | D27: 16140.2 | I27: 30999.5 | J27: =SUM(I28-I27)*351 -> 1263.6 | K27: 20579.2 | L27: =SUM(K28-K27)*351 -> 1017.9 | M27: =J27+L27 -> 2281.5 | N27: =O26 -> 35122 | O27: 35123 | P27: =O27-N27 -> 1 | Q27: =R26 -> 30165 | R27: 30165 | S27: =R27-Q27 -> 0 | T27: =U26 -> 35601 | U27: 35613 | V27: =U27-T27 -> 12 | W27: =X26 -> 32321 | X27: 32333 | Y27: =X27-W27 -> 12 | Z27: =AA26 -> 20952 | AA27: 20952 | AB27: =AA27-Z27 -> 0 | AC27: =AB27+Y27+V27+S27+P27 -> 25 | AD27: 190 | AE27: 95 | AF27: =Gen!T32 -> 982.5
A28: =Gen!B33 -> 44097 | B28: 0.026 | C28: 10209.7 | D28: 16140.2 | G28: 187.28 | I28: 31003.1 | J28: =SUM(I29-I28)*351 -> 1263.6 | K28: 20582.1 | L28: =SUM(K29-K28)*351 -> 947.7 | M28: =J28+L28 -> 2211.3 | N28: =O27 -> 35123 | O28: 35134 | P28: =O28-N28 -> 11 | Q28: =R27 -> 30165 | R28: 30165 | S28: =R28-Q28 -> 0 | T28: =U27 -> 35613 | U28: 35613 | V28: =U28-T28 -> 0 | W28: =X27 -> 32333 | X28: 32333 | Y28: =X28-W28 -> 0 | Z28: =AA27 -> 20952 | AA28: 20965 | AB28: =AA28-Z28 -> 13 | AC28: =AB28+Y28+V28+S28+P28 -> 24 | AD28: 200 | AE28: 99 | AF28: =Gen!T33 -> 989.79
A29: =Gen!B34 -> 44098 | B29: 0.013 | C29: 9036.01 | D29: 16140.2 | I29: 31006.7 | J29: =SUM(I30-I29)*351 -> 1193.4 | K29: 20584.8 | L29: =SUM(K30-K29)*351 -> 982.8 | M29: =J29+L29 -> 2176.2 | N29: =O28 -> 35134 | O29: 35135 | P29: =O29-N29 -> 1 | Q29: =R28 -> 30165 | R29: 30165 | S29: =R29-Q29 -> 0 | T29: =U28 -> 35613 | U29: 35625 | V29: =U29-T29 -> 12 | W29: =X28 -> 32333 | X29: 32346 | Y29: =X29-W29 -> 13 | Z29: =AA28 -> 20965 | AA29: 20965 | AB29: =AA29-Z29 -> 0 | AC29: =AB29+Y29+V29+S29+P29 -> 26 | AD29: 200 | AE29: 90 | AF29: =Gen!T34 -> 1004.25
A30: =Gen!B35 -> 44099 | B30: 0.013 | C30: 8017.75 | D30: 16140.2 | G30: 74.6 | I30: 31010.1 | J30: =SUM(I31-I30)*351 -> 1263.6 | K30: 20587.6 | L30: =SUM(K31-K30)*351 -> 1017.9 | M30: =J30+L30 -> 2281.5 | N30: =O29 -> 35135 | O30: 35147 | P30: =O30-N30 -> 12 | Q30: =R29 -> 30165 | R30: 30165 | S30: =R30-Q30 -> 0 | T30: =U29 -> 35625 | U30: 35625 | V30: =U30-T30 -> 0 | W30: =X29 -> 32346 | X30: 32346 | Y30: =X30-W30 -> 0 | Z30: =AA29 -> 20965 | AA30: 20977 | AB30: =AA30-Z30 -> 12 | AC30: =AB30+Y30+V30+S30+P30 -> 24 | AD30: 190 | AE30: 89 | AF30: =Gen!T35 -> 1019.08
A31: =Gen!B36 -> 44100 | B31: 0.026 | C31: 6934.07 | D31: 16140.2 | I31: 31013.7 | J31: =SUM(I32-I31)*351 -> 1298.7 | K31: 20590.5 | L31: =SUM(K32-K31)*351 -> 1017.9 | M31: =J31+L31 -> 2316.6 | N31: =O30 -> 35147 | O31: 35147 | P31: =O31-N31 -> 0 | Q31: =R30 -> 30165 | R31: 30165 | S31: =R31-Q31 -> 0 | T31: =U30 -> 35625 | U31: 35637 | V31: =U31-T31 -> 12 | W31: =X30 -> 32346 | X31: 32358 | Y31: =X31-W31 -> 12 | Z31: =AA30 -> 20977 | AA31: 20977 | AB31: =AA31-Z31 -> 0 | AC31: =AB31+Y31+V31+S31+P31 -> 24 | AD31: 180 | AE31: 80 | AF31: =Gen!T36 -> 878.8
A32: =Gen!B37 -> 44101 | B32: 0.0519 | C32: 27055.4 | D32: 16140.2 | F32: 18000 | I32: 31017.4 | J32: =SUM(I33-I32)*351 -> 1298.7 | K32: 20593.4 | L32: =SUM(K33-K32)*351 -> 982.8 | M32: =J32+L32 -> 2281.5 | N32: =O31 -> 35147 | O32: 35159 | P32: =O32-N32 -> 12 | Q32: =R31 -> 30165 | R32: 30165 | S32: =R32-Q32 -> 0 | T32: =U31 -> 35637 | U32: 35638 | V32: =U32-T32 -> 1 | W32: =X31 -> 32358 | X32: 32359 | Y32: =X32-W32 -> 1 | Z32: =AA31 -> 20977 | AA32: 20989 | AB32: =AA32-Z32 -> 12 | AC32: =AB32+Y32+V32+S32+P32 -> 26 | AD32: 189 | AE32: 90 | AF32: =Gen!T37 -> 975.74
A33: =Gen!B38 -> 44102 | B33: 0.0519 | C33: 26339.53 | D33: 16140.2 | I33: 31021.1 | J33: =SUM(I34-I33)*351 -> -10888406 | K33: 20596.2 | L33: =SUM(K34-K33)*351 -> -7229266.2 | M33: =J33+L33 -> -18117672 | N33: =O32 -> 35159 | O33: 35160 | P33: =O33-N33 -> 1 | Q33: =R32 -> 30165 | R33: 30165 | S33: =R33-Q33 -> 0 | T33: =U32 -> 35638 | U33: 35649 | V33: =U33-T33 -> 11 | W33: =X32 -> 32359 | X33: 32371 | Y33: =X33-W33 -> 12 | Z33: =AA32 -> 20989 | AA33: 20989 | AB33: =AA33-Z33 -> 0 | AC33: =AB33+Y33+V33+S33+P33 -> 24 | AD33: 195 | AE33: 90 | AF33: =Gen!T38 -> 969.39
A34: =Gen!B39 -> 44103 | B34: 0.0519 | C34: 25370.14 | D34: 16140.2 | J34: =SUM(I35-I34)*351 -> 0 | L34: =SUM(K35-K34)*351 -> 0 | M34: =J34+L34 -> 0 | N34: =O33 -> 35160 | P34: =O34-N34 -> -35160 | Q34: =R33 -> 30165 | S34: =R34-Q34 -> -30165 | T34: =U33 -> 35649 | V34: =U34-T34 -> -35649 | W34: =X33 -> 32371 | Y34: =X34-W34 -> -32371 | Z34: =AA33 -> 20989 | AB34: =AA34-Z34 -> -20989 | AC34: =AB34+Y34+V34+S34+P34 -> -154334 | AF34: =Gen!T39 -> 0
A35: =Gen!B40 -> 44104 | J35: =SUM(I36-I35)*351 -> 0 | L35: =SUM(K36-K35)*351 -> 0 | M35: =J35+L35 -> 0 | N35: =O34 -> 0 | P35: =O35-N35 -> 0 | Q35: =R34 -> 0 | S35: =R35-Q35 -> 0 | T35: =U34 -> 0 | V35: =U35-T35 -> 0 | W35: =X34 -> 0 | Y35: =X35-W35 -> 0 | Z35: =AA34 -> 0 | AB35: =AA35-Z35 -> 0 | AC35: =AB35+Y35+V35+S35+P35 -> 0 | AF35: =Gen!T40 -> 0
A36: =Gen!B41 -> 0 | J36: =SUM(I37-I36)*351 -> 0 | L36: =SUM(K37-K36)*351 -> 0 | M36: =J36+L36 -> 0 | N36: =O35 -> 0 | P36: =O36-N36 -> 0 | Q36: =R35 -> 0 | S36: =R36-Q36 -> 0 | T36: =U35 -> 0 | V36: =U36-T36 -> 0 | W36: =X35 -> 0 | Y36: =X36-W36 -> 0 | Z36: =AA35 -> 0 | AB36: =AA36-Z36 -> 0 | AC36: =AB36+Y36+V36+S36+P36 -> 0 | AF36: =Gen!T41 -> 0
A37: =Gen!B42 -> 0 | N37: =O36 -> 0 | P37: =O37-N37 -> 0 | Q37: =R36 -> 0 | S37: =R37-Q37 -> 0 | T37: =U36 -> 0 | V37: =U37-T37 -> 0 | W37: =X36 -> 0 | Y37: =X37-W37 -> 0 | Z37: =AA36 -> 0 | AB37: =AA37-Z37 -> 0 | AC37: =AB37+Y37+V37+S37+P37 -> 0 | AF37: =Gen!T42 -> 0

Sheet Gen
E2: HLP REPORT
I3: ='Daily report Gen'!A6 -> 44075
G6: BILILA LODGE INVESTMENT LIMITED | W6: 1 | X6: 2 | Y6: 3 | Z6: 4 | AA6: 5 | AB6: 6 | AC6: 7 | AD6: 8 | AE6: 9 | AF6: 10 | AG6: 11
G7: Diesel Consumed by 500KVA Generator | N7: 500KVA Generator KWh | W7: Safari-STAFF | X7: Safari-STAFF | Y7: Lc/swg/gust | Z7: Eng pikcup | AA7: VIP Safari Car | AB7: GX Guest | AC7: GX Guest | AD7: T/Hillux/pur | AE7: TATA | AF7: MAN | AG7: F/Truck | AH7: Incenerator | AI7: A&K | AJ7: OTHER | AK7: TOTAL CO
B8: Date | C8: Occupancy % | D8: OPENING | E8: Received | F8: Schedule delivery | G8: Company | H8: 1 | I8: 2 | J8: 3 | K8: 4 | L8: 5 | M8: 6 | N8: 1 | O8: 2 | P8: 3 | Q8: 4 | R8: 5 | S8: 6 | T8: Total Diseal Consumed | U8: Total Kwh generated | V8: Average Diesel/Kwh | W8: T 128 AXJ | X8: T 134 AXJ | Y8: T 499 AXG | Z8: T 217 CHV | AA8: T 214 CHV | AB8: T 139 AXE | AC8: T 242 AXN | AD8: T 476 AWZ | AE8: T 226 AUQ | AF8: T 308 CLD | AG8: T 852 AWU | AH8: Machine ENG | AI8: Vehicle | AJ8: Vehicle | AS8: Total Diseal Consumed Gen & Vehicle | AT8: Total cost /Day (TSH) | AU8: BALANCE
D9: 41590.62 | T9: =SUM(G9:M9) -> 0 | U9: =SUM(N9:S9) -> 0 | AS9: =SUM(AK9+T9) -> 0 | AU9: 38784.7
T10: =SUM(G10:M10) -> 0 | U10: =SUM(N10:S10) -> 0 | V10: =SUM(O10:T10) -> 0 | AK10: =SUM(W10:AJ10) -> 0 | AS10: =SUM(AK10+T10) -> 0
B11: 44075 | C11: 0.039 | D11: =SUM(D9+E11) -> 41590.62 | H11: 355.12 | L11: 536.31 | N11: 1002 | R11: 1109 | T11: =SUM(G11:M11) -> 891.43 | U11: =SUM(N11:S11) -> 2111 | V11: =T11/U11 -> 0.42227854 | AA11: 69.21 | AK11: =SUM(W11:AJ11) -> 69.21 | AS11: =SUM(AK11+T11) -> 960.64 | AT11: =AS11*AV11 -> 0 | AU11: =D11 -> 41590.62
B12: 44076 | C12: 0.039 | D12: =SUM(D11-AS11+E12) -> 40629.98 | I12: 409.57 | K12: 412.35 | O12: 1041 | Q12: 1106 | T12: =SUM(G12:M12) -> 821.92 | U12: =SUM(N12:S12) -> 2147 | V12: =T12/U12 -> 0.38282254 | AA12: 80.65 | AK12: =SUM(W12:AJ12) -> 80.65 | AS12: =SUM(AK12+T12) -> 902.57 | AT12: =AS12*AV12 -> 0 | AU12: =D12 -> 40629.98
B13: 44077 | C13: 0.039 | D13: =SUM(D12-AS12+E13) -> 39727.41 | H13: 494.46 | M13: 595.82 | N13: 1067 | S13: 1121 | T13: =SUM(G13:M13) -> 1090.28 | U13: =SUM(N13:S13) -> 2188 | V13: =T13/U13 -> 0.49829982 | Y13: 10.02 | AK13: =SUM(W13:AJ13) -> 10.02 | AS13: =SUM(AK13+T13) -> 1100.3 | AT13: =AS13*AV13 -> 0 | AU13: =D13 -> 39727.41
B14: 44078 | C14: 0.0909 | D14: =SUM(D13-AS13+E14) -> 38627.11 | L14: 481.15 | M14: 387.24 | R14: 1284 | S14: 1164 | T14: =SUM(G14:M14) -> 868.39 | U14: =SUM(N14:S14) -> 2448 | V14: =T14/U14 -> 0.35473448 | AK14: =SUM(W14:AJ14) -> 0 | AS14: =SUM(AK14+T14) -> 868.39 | AT14: =AS14*AV14 -> 0 | AU14: =D14 -> 38627.11
B15: 44079 | C15: 0.0909 | D15: =SUM(D14-AS14+E15) -> 37758.72 | H15: 507.97 | I15: 334.01 | N15: 1136 | O15: 1016 | T15: =SUM(G15:M15) -> 841.98 | U15: =SUM(N15:S15) -> 2152 | V15: =T15/U15 -> 0.39125465 | Y15: 27.01 | AK15: =SUM(W15:AJ15) -> 27.01 | AS15: =SUM(AK15+T15) -> 868.99 | AT15: =AS15*AV15 -> 0 | AU15: =D15 -> 37758.72
B16: 44080 | C16: 0.0909 | D16: =SUM(D15-AS15+E16) -> 36889.73 | K16: 532.58 | L16: 405.96 | Q16: 1081 | R16: 971 | T16: =SUM(G16:M16) -> 938.54 | U16: =SUM(N16:S16) -> 2052 | V16: =T16/U16 -> 0.45737817 | AK16: =SUM(W16:AJ16) -> 0 | AS16: =SUM(AK16+T16) -> 938.54 | AT16: =AS16*AV16 -> 0 | AU16: =D16 -> 36889.73
B17: 44081 | C17: 0.026 | D17: =SUM(D16-AS16+E17) -> 35951.19 | H17: 394.85 | M17: 515.42 | N17: 1017 | S17: 993 | T17: =SUM(G17:M17) -> 910.27 | U17: =SUM(N17:S17) -> 2010 | V17: =T17/U17 -> 0.45287065 | Y17: 27.13 | AI17: 146 | AJ17: 85.01 | AK17: =SUM(W17:AJ17) -> 258.14 | AS17: =SUM(AK17+T17) -> 1168.41 | AT17: =AS17*AV17 -> 0 | AU17: =D17 -> 35951.19
B18: 44082 | C18: 0.039 | D18: =SUM(D17-AS17+E18) -> 34782.78 | I18: 554.05 | K18: 394.16 | O18: 1087 | Q18: 1158 | T18: =SUM(G18:M18) -> 948.21 | U18: =SUM(N18:S18) -> 2245 | V18: =T18/U18 -> 0.42236526 | X18: 35.66 | AA18: 87.64 | AK18: =SUM(W18:AJ18) -> 123.3 | AS18: =SUM(AK18+T18) -> 1071.51 | AT18: =AS18*AV18 -> 0 | AU18: =D18 -> 34782.78
B19: 44083 | C19: 0.065 | D19: =SUM(D18-AS18+E19) -> 33711.27 | L19: 433.34 | M19: 482.99 | R19: 966 | S19: 1135 | T19: =SUM(G19:M19) -> 916.33 | U19: =SUM(N19:S19) -> 2101 | V19: =T19/U19 -> 0.43613993 | AK19: =SUM(W19:AJ19) -> 0 | AS19: =SUM(AK19+T19) -> 916.33 | AT19: =AS19*AV19 -> 0 | AU19: =D19 -> 33711.27
B20: 44084 | C20: 0.013 | D20: =SUM(D19-AS19+E20) -> 32794.94 | H20: 414.86 | K20: 563.18 | N20: 1010 | Q20: 1189 | T20: =SUM(G20:M20) -> 978.04 | U20: =SUM(N20:S20) -> 2199 | V20: =T20/U20 -> 0.4447658 | AK20: =SUM(W20:AJ20) -> 0 | AS20: =SUM(AK20+T20) -> 978.04 | AT20: =AS20*AV20 -> 0 | AU20: =D20 -> 32794.94
B21: 44085 | C21: 0.039 | D21: =SUM(D20-AS20+E21) -> 31816.9 | K21: 337.42 | M21: 445.13 | Q21: 939 | S21: 1187 | T21: =SUM(G21:M21) -> 782.55 | U21: =SUM(N21:S21) -> 2126 | V21: =T21/U21 -> 0.36808561 | AK21: =SUM(W21:AJ21) -> 0 | AS21: =SUM(AK21+T21) -> 782.55 | AT21: =AS21*AV21 -> 0 | AU21: =D21 -> 31816.9
B22: 44086 | C22: 0.02 | D22: =SUM(D21-AS21+E22) -> 31034.35 | I22: 348.67 | M22: 384.11 | N22: 1133 | R22: 1041 | T22: =SUM(G22:M22) -> 732.78 | U22: =SUM(N22:S22) -> 2174 | V22: =T22/U22 -> 0.33706532 | AK22: =SUM(W22:AJ22) -> 0 | AS22: =SUM(AK22+T22) -> 732.78 | AT22: =AS22*AV22 -> 0 | AU22: =D22 -> 31034.35
B23: 44087 | C23: 0.03 | D23: =SUM(D22-AS22+E23) -> 30301.57 | H23: 480.77 | L23: 454.97 | N23: 1010 | R23: 1103 | T23: =SUM(G23:M23) -> 935.74 | U23: =SUM(N23:S23) -> 2113 | V23: =T23/U23 -> 0.44284903 | AA23: 71.04 | AK23: =SUM(W23:AJ23) -> 71.04 | AS23: =SUM(AK23+T23) -> 1006.78 | AT23: =AS23*AV23 -> 0 | AU23: =D23 -> 30301.57
B24: 44088 | C24: 0.04 | D24: =SUM(D23-AS23+E24) -> 29294.79 | K24: 413.7 | L24: 476.39 | Q24: 999 | R24: 1041 | T24: =SUM(G24:M24) -> 890.09 | U24: =SUM(N24:S24) -> 2040 | V24: =T24/U24 -> 0.43631863 | AK24: =SUM(W24:AJ24) -> 0 | AS24: =SUM(AK24+T24) -> 890.09 | AT24: =AS24*AV24 -> 0 | AU24: =D24 -> 29294.79
B25: 44089 | C25: 0.03 | D25: =SUM(D24-AS24+E25) -> 28404.7 | F25: 10000 | G25: PUMA | H25: 448.3 | M25: 440.68 | N25: 1074 | S25: 1010 | T25: =SUM(G25:M25) -> 888.98 | U25: =SUM(N25:S25) -> 2084 | V25: =T25/U25 -> 0.4265739 | AK25: =SUM(W25:AJ25) -> 0 | AS25: =SUM(AK25+T25) -> 888.98 | AT25: =AS25*AV25 -> 0 | AU25: =D25 -> 28404.7
B26: 44090 | C26: 0.1299 | D26: =SUM(D25-AS25+E26) -> 27515.72 | K26: 576.66 | L26: 518.8 | Q26: 1275 | R26: 1214 | T26: =SUM(G26:M26) -> 1095.46 | U26: =SUM(N26:S26) -> 2489 | V26: =T26/U26 -> 0.44012053 | Y26: 39.14 | AA26: 73 | AI26: 69 | AK26: =SUM(W26:AJ26) -> 181.14 | AS26: =SUM(AK26+T26) -> 1276.6 | AT26: =AS26*AV26 -> 0 | AU26: =D26 -> 27515.72
B27: 44091 | C27: 0.1169 | D27: =SUM(D26-AS26+E27) -> 36239.12 | E27: 10000 | H27: 482.52 | M27: 535.55 | N27: 1186 | S27: 1313 | T27: =SUM(G27:M27) -> 1018.07 | U27: =SUM(N27:S27) -> 2499 | V27: =T27/U27 -> 0.40739096 | X27: 25.41 | AK27: =SUM(W27:AJ27) -> 25.41 | AS27: =SUM(AK27+T27) -> 1043.48 | AT27: =AS27*AV27 -> 0 | AU27: =D27 -> 36239.12
B28: 44092 | C28: 0.1429 | D28: =SUM(D27-AS27+E28) -> 35195.64 | K28: 487.16 | L28: 554.11 | Q28: 1199 | R28: 1423 | T28: =SUM(G28:M28) -> 1041.27 | U28: =SUM(N28:S28) -> 2622 | V28: =T28/U28 -> 0.39712815 | AK28: =SUM(W28:AJ28) -> 0 | AS28: =SUM(AK28+T28) -> 1041.27 | AT28: =AS28*AV28 -> 0 | AU28: =D28 -> 35195.64
B29: 44093 | C29: 0.0909 | D29: =SUM(D28-AS28+E29) -> 34154.37 | H29: 471.9 | M29: 657.98 | N29: 1103 | S29: 1397 | T29: =SUM(G29:M29) -> 1129.88 | U29: =SUM(N29:S29) -> 2500 | V29: =T29/U29 -> 0.451952 | Z29: 80.25 | AA29: 69.13 | AI29: 225 | AK29: =SUM(W29:AJ29) -> 374.38 | AS29: =SUM(AK29+T29) -> 1504.26 | AT29: =AS29*AV29 -> 0 | AU29: =D29 -> 34154.37
B30: 44094 | C30: 0.0649 | D30: =SUM(D29-AS29+E30) -> 32650.11 | K30: 459.51 | L30: 596.15 | Q30: 1080 | R30: 1233 | T30: =SUM(G30:M30) -> 1055.66 | U30: =SUM(N30:S30) -> 2313 | V30: =T30/U30 -> 0.45640294 | AA30: 44.98 | AK30: =SUM(W30:AJ30) -> 44.98 | AS30: =SUM(AK30+T30) -> 1100.64 | AT30: =AS30*AV30 -> 0 | AU30: =D30 -> 32650.11
B31: 44095 | C31: 0.0649 | D31: =SUM(D30-AS30+E31) -> 31549.47 | H31: 464.24 | M31: 493.46 | N31: 1128 | S31: 1228 | T31: =SUM(G31:M31) -> 957.7 | U31: =SUM(N31:S31) -> 2356 | V31: =T31/U31 -> 0.40649406 | AK31: =SUM(W31:AJ31) -> 0 | AS31: =SUM(AK31+T31) -> 957.7 | AT31: =AS31*AV31 -> 0 | AU31: =D31 -> 31549.47
B32: 44096 | C32: 0.026 | D32: =SUM(D31-AS31+E32) -> 30591.77 | K32: 475.4 | L32: 507.1 | Q32: 1060 | R32: 1229 | T32: =SUM(G32:M32) -> 982.5 | U32: =SUM(N32:S32) -> 2289 | V32: =T32/U32 -> 0.42922674 | AK32: =SUM(W32:AJ32) -> 0 | AS32: =SUM(AK32+T32) -> 982.5 | AT32: =AS32*AV32 -> 0 | AU32: =D32 -> 30591.77
B33: 44097 | C33: 0.026 | D33: =SUM(D32-AS32+E33) -> 29609.27 | H33: 343.34 | M33: 646.45 | N33: 978 | S33: 1308 | T33: =SUM(G33:M33) -> 989.79 | U33: =SUM(N33:S33) -> 2286 | V33: =T33/U33 -> 0.432979 | X33: 34.27 | AI33: 153.01 | AK33: =SUM(W33:AJ33) -> 187.28 | AS33: =SUM(AK33+T33) -> 1177.07 | AT33: =AS33*AV33 -> 0 | AU33: =D33 -> 29609.27
B34: 44098 | C34: 0.013 | D34: =SUM(D33-AS33+E34) -> 28432.2 | K34: 477.44 | L34: 526.81 | Q34: 1025 | R34: 1264 | T34: =SUM(G34:M34) -> 1004.25 | U34: =SUM(N34:S34) -> 2289 | V34: =T34/U34 -> 0.4387287 | AK34: =SUM(W34:AJ34) -> 0 | AS34: =SUM(AK34+T34) -> 1004.25 | AT34: =AS34*AV34 -> 0 | AU34: =D34 -> 28432.2
B35: 44099 | C35: 0.013 | D35: =SUM(D34-AS34+E35) -> 27427.95 | H35: 444.98 | M35: 574.1 | N35: 1079 | S35: 1165 | T35: =SUM(G35:M35) -> 1019.08 | U35: =SUM(N35:S35) -> 2244 | V35: =T35/U35 -> 0.45413547 | X35: 27.39 | Z35: 47.21 | AK35: =SUM(W35:AJ35) -> 74.6 | AS35: =SUM(AK35+T35) -> 1093.68 | AT35: =AS35*AV35 -> 0 | AU35: =D35 -> 27427.95
B36: 44100 | C36: 0.026 | D36: =SUM(D35-AS35+E36) -> 26334.27 | K36: 371.89 | L36: 506.91 | Q36: 1079 | R36: 1234 | T36: =SUM(G36:M36) -> 878.8 | U36: =SUM(N36:S36) -> 2313 | V36: =T36/U36 -> 0.37993947 | AK36: =SUM(W36:AJ36) -> 0 | AS36: =SUM(AK36+T36) -> 878.8 | AT36: =AS36*AV36 -> 0 | AU36: =D36 -> 26334.27
B37: 44101 | C37: 0.0519 | D37: =SUM(D36-AS36+E37) -> 43455.47 | E37: 18000 | F37: 18000 | G37: PUMA | H37: 473.74 | M37: 502 | N37: 1093 | S37: 1234 | T37: =SUM(G37:M37) -> 975.74 | U37: =SUM(N37:S37) -> 2327 | V37: =T37/U37 -> 0.41931242 | AK37: =SUM(W37:AJ37) -> 0 | AS37: =SUM(AK37+T37) -> 975.74 | AT37: =AS37*AV37 -> 0 | AU37: =D37 -> 43455.47
B38: 44102 | C38: 0.0519 | D38: =SUM(D37-AS37+E38) -> 42479.73 | K38: 442.32 | L38: 527.07 | Q38: 1021 | R38: 1268 | T38: =SUM(G38:M38) -> 969.39 | U38: =SUM(N38:S38) -> 2289 | V38: =T38/U38 -> 0.42349934 | AK38: =SUM(W38:AJ38) -> 0 | AS38: =SUM(AK38+T38) -> 969.39 | AT38: =AS38*AV38 -> 0 | AU38: =D38 -> 42479.73
B39: 44103 | C39: 0.0519 | D39: =SUM(D38-AS38+E39) -> 41510.34 | T39: =SUM(G39:M39) -> 0 | U39: =SUM(N39:S39) -> 0 | V39: =T39/U39 -> #DIV/0! | AK39: =SUM(W39:AJ39) -> 0 | AS39: =SUM(AK39+T39) -> 0 | AT39: =AS39*AV39 -> 0 | AU39: =D39 -> 41510.34
B40: 44104 | D40: =SUM(D39-AS39+E40) -> 41510.34 | T40: =SUM(G40:M40) -> 0 | U40: =SUM(N40:S40) -> 0 | V40: =T40/U40 -> #DIV/0! | AK40: =SUM(W40:AJ40) -> 0 | AS40: =SUM(AK40+T40) -> 0 | AT40: =AS40*AV40 -> 0 | AU40: =D40 -> 41510.34
D41: =SUM(D40-AS40+E41) -> 41510.34 | T41: =SUM(G41:M41) -> 0 | U41: =SUM(N41:S41) -> 0 | V41: =T41/U41 -> #DIV/0! | AK41: =SUM(W41:AJ41) -> 0 | AS41: =SUM(AK41+T41) -> 0 | AT41: =AS41*AV41 -> 0 | AU41: =D41 -> 41510.34
D42: =SUM(D41-AS41+E42) -> 41510.34 | T42: =SUM(G42:M42) -> 0 | U42: =SUM(N42:S42) -> 0 | AK42: =SUM(W42:AJ42) -> 0 | AS42: =SUM(AK42+T42) -> 0 | AT42: =AS42*AV42 -> 0 | AU42: =D42 -> 41510.34
B43: BF | C43: =AVERAGE(C11:C42) -> 0.053855172 | D43: =SUM(D42-AS42+E43) -> 41510.34 | T43: =SUM(G43:M43) -> 0 | U43: =SUM(N43:S43) -> 0 | AK43: =SUM(W43:AJ43) -> 0 | AS43: =SUM(AK43+T43) -> 0 | AT43: =AS43*AV43 -> 0 | AU43: =D43 -> 41510.34
T44: =SUM(G44:M44) -> 0 | AK44: =SUM(W44:AJ44) -> 0 | AS44: =T44+AK44 -> 0 | AT44: =AS44*AV44 -> 0
E45: =SUM(E11:E44) -> 28000 | F45: =SUM(F11:F42) -> 28000 | G45: =SUM(G11:G44) -> 0 | H45: =SUM(H11:H44) -> 5777.05 | I45: =SUM(I11:I44) -> 1646.3 | J45: =SUM(J11:J44) -> 0 | K45: =SUM(K11:K44) -> 5943.77 | L45: =SUM(L11:L44) -> 6525.07 | M45: =SUM(M11:M44) -> 6660.93 | N45: =SUM(N11:N44) -> 15016 | ... P45: =SUM(P11:P44) -> 0 | Q45: =SUM(Q11:Q43) -> 14211 | R45: =SUM(R11:R44) -> 16380 | S45: =SUM(S11:S44) -> 14255 | T45: =SUM(G45:M45) -> 26553.12 | U45: =SUM(N45:S45) -> 63006 | V45: =SUM(V11:V42) -> #DIV/0! | W45: =SUM(W9:W44) -> 0 | X45: =SUM(X9:X44) -> 122.73 | Y45: =SUM(Y9:Y44) -> 103.3 | Z45: =SUM(Z9:Z44) -> 127.46 | AA45: =SUM(AA9:AA44) -> 495.65 | AB45: =SUM(AB9:AB44) -> 0 | AC45: =SUM(AC9:AC44) -> 0 | AD45: =SUM(AD10:AD44) -> 0 | AE45: =SUM(AE10:AE44) -> 0 | AF45: =SUM(AF9:AF44) -> 0 | AG45: =SUM(AG9:AG44) -> 0 | AH45: =SUM(AH9:AH44) -> 0 | AI45: =SUM(AI9:AI43) -> 593.01 | AJ45: =SUM(AJ9:AJ39) -> 85.01 | AK45: =SUM(AK9:AK44) -> 1527.16 | AS45: =SUM(AS11:AS43) -> 28080.28 | AT45: =SUM(AT11:AT44) -> 0
B46: Nb Day | T46: =AVERAGE(T11:T26) -> 908.18687
U47: =T45*2315 -> 61470473 | V47: TZS | AS47: =AS45*2143 -> 60176040 | AT47: TZS
B48: Av. Occ | U48: =U47/2289 -> 26854.728 | V48: USD | AS48: =AS47/2289 -> 26289.227 | AT48: USD
C50: A & K VEHICLES | I50: MAULY VEHICLES | O50: GREEN LAND VEHICLES | U50: OTHERS VEHICLES
C51: Date | D51: Vehicles | E51: Liters | F51: Driver name | G51: Authority manager | I51: Date | J51: Vehicles | K51: Liters | L51: Driver name | M51: Authority manager | O51: Date | P51: Vehicles | Q51: Liters | R51: Driver name | S51: Authorized Manager | U51: Date | V51: Vehicles | W51: Liters | X51: Driver name | Y51: Athorized Manager | Z51: Reasons
C52: 44081 | D52: T 880 DKQ | E52: 146 | F52: Emanuel | G52: Noel | U52: 44081 | V52: T818 CBX | W52: 39 | X52: Sita | Y52: Noel | Z52: Cssh paid
C53: 44090 | D53: T 111 CWQ | E53: 69 | F53: Jeremiah | G53: Noel | U53: 44081 | V53: T466DNY | W53: 46.01 | X53: Abdullah | Y53: Noel | Z53: Cssh paid
C54: 44093 | D54: T 111 CWQ | E54: 118 | F54: Jeremiah | G54: Noel
C55: 44093 | D55: T 391 DQR | E55: 107 | F55: Hassan | G55: Noel
C56: 44097 | D56: T 880 DKQ | E56: 110 | F56: Kswa | G56: Noel
C57: 44097 | D57: T 111 CWQ | E57: 43 | F57: Jeremiah | G57: Noel

Sheet Energy Graph
A1: Date | B1: Usage KW | C1: Occ % | D1: Cost per room Total Occ | E1: Cost per room Guest Occ
A2: =Gen!B11 -> 44075 | B2: =SUM('[1]Summery Report'!F5) -> 5669 | C2: =SUM('[1]Summery Report'!C5) -> 0.623 | D2: =SUM('[1]Summery Report'!#REF!) -> #REF! | E2: =SUM('[1]Summery Report'!#REF!) -> #REF! | F2: 0.1
A3: =Gen!B12 -> 44076 | B3: =SUM('[1]Summery Report'!F6) -> 6159 | C3: =SUM('[1]Summery Report'!C6) -> 0.779 | D3: =SUM('[1]Summery Report'!#REF!) -> #REF! | E3: =SUM('[1]Summery Report'!#REF!) -> #REF! | F3: 0.1375
A4: =Gen!B13 -> 44077 | B4: =SUM('[1]Summery Report'!F7) -> 6580 | C4: =SUM('[1]Summery Report'!C7) -> 0.532 | D4: =SUM('[1]Summery Report'!#REF!) -> #REF! | E4: =SUM('[1]Summery Report'!#REF!) -> #REF! | F4: 0.0875
A5: =Gen!B14 -> 44078 | B5: =SUM('[1]Summery Report'!F8) -> 6223 | C5: =SUM('[1]Summery Report'!C8) -> 0.61 | D5: =SUM('[1]Summery Report'!#REF!) -> #REF! | E5: =SUM('[1]Summery Report'!#REF!) -> #REF! | F5: 0.225
A6: =Gen!B15 -> 44079 | B6: =SUM('[1]Summery Report'!F9) -> 5984 | C6: =SUM('[1]Summery Report'!C9) -> 0.688 | D6: =SUM('[1]Summery Report'!#REF!) -> #REF! | E6: =SUM('[1]Summery Report'!#REF!) -> #REF! | F6: 0.2
A7: =Gen!B16 -> 44080 | B7: =SUM('[1]Summery Report'!F10) -> 6103 | C7: =SUM('[1]Summery Report'!C10) -> 0.532 | D7: =SUM('[1]Summery Report'!#REF!) -> #REF! | E7: =SUM('[1]Summery Report'!#REF!) -> #REF! | F7: 0.35
A8: =Gen!B17 -> 44081 | B8: =SUM('[1]Summery Report'!F11) -> 5576 | C8: =SUM('[1]Summery Report'!C11) -> 0.753 | D8: =SUM('[1]Summery Report'!#REF!) -> #REF! | E8: =SUM('[1]Summery Report'!#REF!) -> #REF! | F8: 0.375
A9: =Gen!B18 -> 44082 | B9: =SUM('[1]Summery Report'!F12) -> 5532 | C9: =SUM('[1]Summery Report'!C12) -> 0.156 | D9: =SUM('[1]Summery Report'!#REF!) -> #REF! | E9: =SUM('[1]Summery Report'!#REF!) -> #REF! | F9: 0.325
A10: =Gen!B19 -> 44083 | B10: =SUM('[1]Summery Report'!F13) -> 6233 | C10: =SUM('[1]Summery Report'!C13) -> 0.442 | D10: =SUM('[1]Summery Report'!#REF!) -> #REF! | E10: =SUM('[1]Summery Report'!#REF!) -> #REF! | F10: 0.75
A11: =Gen!B20 -> 44084 | B11: =SUM('[1]Summery Report'!F14) -> 6063 | C11: =SUM('[1]Summery Report'!C14) -> 0.325 | D11: =SUM('[1]Summery Report'!#REF!) -> #REF! | E11: =SUM('[1]Summery Report'!#REF!) -> #REF! | F11: 0.7625
A12: =Gen!B21 -> 44085 | B12: =SUM('[1]Summery Report'!F15) -> 5967 | C12: =SUM('[1]Summery Report'!C15) -> 0.455 | D12: =SUM('[1]Summery Report'!#REF!) -> #REF! | E12: =SUM('[1]Summery Report'!#REF!) -> #REF! | F12: 0.1625
A13: =Gen!B22 -> 44086 | B13: =SUM('[1]Summery Report'!F16) -> 5863 | C13: =SUM('[1]Summery Report'!C16) -> 0.416 | D13: =SUM('[1]Summery Report'!#REF!) -> #REF! | E13: =SUM('[1]Summery Report'!#REF!) -> #REF! | F13: 0.1125
... A32: =Gen!B41 -> 0 | B32: =SUM('[1]Summery Report'!F35) -> 0 | C32: =SUM('[1]Summery Report'!C35) -> 0 | D32: =SUM('[1]Summery Report'!#REF!) -> #REF! | E32: =SUM('[1]Summery Report'!#REF!) -> #REF! | F32: 0.175
A33: =Gen!B42 -> 0 | B33: =[1]Gen!S41 -> 0

Sheet Lpg (2)
C3: Four Sasons Safari Lodge Serengeti
G6: VALUE | H6: Cost
A7: DATE | B7: A | C7: B | D7: C | F7: Meter Reading | G7: Total | H7: Occu | I7: No.of | J7: Kg
B8: 2Ton% | C8: 1Ton (%) | D8: 1Ton% | F8: consumption | G8: Consumption Kg | H8: % | I8: pax | J8: per pax
F9: 72082.82
A10: =Gen!B11 -> 44075 | B10: 85 | C10: 85 | D10: 2 | F10: 72100.1 | G10: =(F10-F9)*4.4 -> 76.032 | H10: =Gen!C11 -> 0.039 | I10: =SUM(F10/H10) -> 1848720.5 | J10: =SUM(G10/I10) -> 4.1126822e-05
A11: =Gen!B12 -> 44076 | B11: 85 | C11: 85 | D11: 2 | F11: 72113.42 | G11: =(F11-F10)*4.4 -> 58.608 | H11: =Gen!C12 -> 0.039 | I11: =SUM(F11/H11) -> 1849062.1 | J11: =SUM(G11/I11) -> 3.169607e-05
A12: =Gen!B13 -> 44077 | B12: 85 | C12: 85 | D12: 1 | F12: 72128.48 | G12: =(F12-F11)*4.4 -> 66.264 | H12: =Gen!C13 -> 0.039 | I12: =SUM(F12/H12) -> 1849448.2 | J12: =SUM(G12/I12) -> 3.5829065e-05
A13: =Gen!B14 -> 44078 | B13: 85 | C13: 85 | D13: 1 | F13: 72142.92 | G13: =(F13-F12)*4.4 -> 63.536 | H13: =Gen!C14 -> 0.0909 | I13: =SUM(F13/H13) -> 793651.49 | J13: =SUM(G13/I13) -> 8.005529e-05
A14: =Gen!B15 -> 44079 | B14: 85 | C14: 85 | D14: 1 | F14: 72154.3 | G14: =(F14-F13)*4.4 -> 50.072 | H14: =Gen!C15 -> 0.0909 | I14: =SUM(F14/H14) -> 793776.68 | J14: =SUM(G14/I14) -> 6.3080715e-05
A15: =Gen!B16 -> 44080 | B15: 85 | C15: 85 | D15: 1 | F15: 72165.57 | G15: =(F15-F14)*4.4 -> 49.588 | H15: =Gen!C16 -> 0.0909 | I15: =SUM(F15/H15) -> 793900.66 | J15: =SUM(G15/I15) -> 6.2461215e-05
A16: =Gen!B17 -> 44081 | B16: 85 | C16: 85 | D16: 0 | F16: 72179.79 | G16: =(F16-F15)*4.4 -> 62.568 | H16: =Gen!C17 -> 0.026 | I16: =SUM(F16/H16) -> 2776145.8 | J16: =SUM(G16/I16) -> 2.2537721e-05
A17: =Gen!B18 -> 44082 | B17: 85 | C17: 81 | D17: 0 | F17: 72192.26 | G17: =(F17-F16)*4.4 -> 54.868 | H17: =Gen!C18 -> 0.039 | I17: =SUM(F17/H17) -> 1851083.6 | J17: =SUM(G17/I17) -> 2.9641017e-05
A18: =Gen!B19 -> 44083 | B18: 85 | C18: 75 | D18: 0 | F18: 72205.31 | G18: =(F18-F17)*4.4 -> 57.42 | H18: =Gen!C19 -> 0.065 | I18: =SUM(F18/H18) -> 1110850.9 | J18: =SUM(G18/I18) -> 5.1690104e-05
A19: =Gen!B20 -> 44084 | B19: 85 | C19: 72 | D19: 0 | F19: 72215.31 | G19: =(F19-F18)*4.4 -> 44 | H19: =Gen!C20 -> 0.013 | I19: =SUM(F19/H19) -> 5555023.8 | J19: =SUM(G19/I19) -> 7.9207581e-06
A20: =Gen!B21 -> 44085 | B20: 85 | C20: 68 | D20: 0 | F20: 72231.43 | G20: =(F20-F19)*4.4 -> 70.928 | H20: =Gen!C21 -> 0.039 | I20: =SUM(F20/H20) -> 1852087.9 | J20: =SUM(G20/I20) -> 3.8296238e-05
A21: =Gen!B22 -> 44086 | B21: 85 | C21: 60 | D21: 0 | F21: 72243.68 | G21: =(F21-F20)*4.4 -> 53.9 | H21: =Gen!C22 -> 0.02 | I21: =SUM(F21/H21) -> 3612184 | J21: =SUM(G21/I21) -> 1.492172e-05
... A28: =Gen!B29 -> 44093 | B28: 85 | C28: 30 | D28: 0 | F28: 72334.35 | G28: =(F28-F27)*4.4 -> 65.428 | H28: =Gen!C29 -> 0.0909 | I28: =SUM(F28/H28) -> 795757.43 | J28: =SUM(G28/I28) -> 8.2221036e-05
A29: =Gen!B30 -> 44094 | B29: 85 | C29: 29 | D29: 0 | E29: 0 | F29: 72350.22 | G29: =(F29-F28)*4.4 -> 69.828 | H29: =Gen!C30 -> 0.0649 | I29: =SUM(F29/H29) -> 1114795.4 | J29: =SUM(G29/I29) -> 6.2637504e-05
A30: =Gen!B31 -> 44095 | B30: 85 | C30: 25 | D30: 0 | F30: 72367.42 | G30: =(F30-F29)*4.4 -> 75.68 | H30: =Gen!C31 -> 0.0649 | I30: =SUM(F30/H30) -> 1115060.4 | J30: =SUM(G30/I30) -> 6.7870763e-05
A31: =Gen!B32 -> 44096 | B31: 85 | C31: 23 | D31: 0 | F31: 72380.09 | G31: =(F31-F30)*4.4 -> 55.748 | H31: =Gen!C32 -> 0.026 | I31: =SUM(F31/H31) -> 2783849.6 | J31: =SUM(G31/I31) -> 2.0025507e-05
A32: =Gen!B33 -> 44097 | B32: 85 | C32: 20 | D32: 0 | F32: 72389 | G32: =(F32-F31)*4.4 -> 39.204 | H32: =Gen!C33 -> 0.026 | I32: =SUM(F32/H32) -> 2784192.3 | J32: =SUM(G32/I32) -> 1.4080924e-05
A33: =Gen!B34 -> 44098 | B33: 85 | C33: 19 | D33: 0 | F33: 72405.5 | G33: =(F33-F32)*4.4 -> 72.6 | H33: =Gen!C34 -> 0.013 | I33: =SUM(F33/H33) -> 5569653.8 | J33: =SUM(G33/I33) -> 1.3034921e-05
A34: =Gen!B35 -> 44099 | B34: 85 | C34: 18 | D34: 0 | F34: 72419.88 | G34: =(F34-F33)*4.4 -> 63.272 | H34: =Gen!C35 -> 0.013 | I34: =SUM(F34/H34) -> 5570760 | J34: =SUM(G34/I34) -> 1.1357876e-05
A35: =Gen!B36 -> 44100 | B35: 85 | C35: 17 | D35: 0 | F35: 72434.35 | G35: =(F35-F34)*4.4 -> 63.668 | H35: =Gen!C36 -> 0.026 | I35: =SUM(F35/H35) -> 2785936.5 | J35: =SUM(G35/I35) -> 2.2853356e-05
A36: =Gen!B37 -> 44101 | B36: 85 | C36: 16 | D36: 0 | F36: 72446.78 | G36: =(F36-F35)*4.4 -> 54.692 | H36: =Gen!C37 -> 0.0519 | I36: =SUM(F36/H36) -> 1395891.7 | J36: =SUM(G36/I36) -> 3.918069e-05
A37: =Gen!B38 -> 44102 | B37: 85 | C37: 15 | D37: 0 | F37: 72463.98 | G37: =(F37-F36)*4.4 -> 75.68 | H37: =Gen!C38 -> 0.0519 | I37: =SUM(F37/H37) -> 1396223.1 | J37: =SUM(G37/I37) -> 5.4203371e-05
A38: =Gen!B39 -> 44103 | B38: 85 | C38: 14 | D38: 0 | G38: =(F38-F37)*4.4 -> -318841.51 | H38: =Gen!C39 -> 0.0519 | I38: =SUM(F38/H38) -> 0 | J38: =SUM(G38/I38) -> #DIV/0!
A39: =Gen!B40 -> 44104 | G39: =(F39-F38)*4.4 -> 0 | H39: =Gen!C40 -> 0 | I39: =SUM(F39/H39) -> #DIV/0! | J39: =SUM(G39/I39) -> #DIV/0!
A40: =Gen!B41 -> 0 | G40: =(F40-F39)*4.4 -> 0 | H40: =Gen!C41 -> 0 | I40: =SUM(F40/H40) -> #DIV/0! | J40: =SUM(G40/I40) -> #DIV/0!
A41: =Gen!B42 -> 0 | H41: =Gen!C42 -> 0 | I41: =SUM(F41/H41) -> #DIV/0!
C42: TOTAL USAGE | E42: =SUM(E10:E40) -> 0 | F42: =SUM(F10:F40) -> 2023786.7 | G42: =SUM(G10:G40) -> -317164.41
F45: =E12-E11 -> 0 | G45: =F45*4.4 -> 0

Sheet LPG_Graph
A1: Date | B1: Usage KG | C1: Occ %
A2: =Gen!B11 -> 44075 | B2: ='[1]Lpg (2)'!G10 -> 197.56 | C2: =SUM([1]Gen!B11) -> 0.623
A3: =Gen!B12 -> 44076 | B3: ='[1]Lpg (2)'!G11 -> 131.956 | C3: =SUM([1]Gen!B12) -> 0.779
A4: =Gen!B13 -> 44077 | B4: ='[1]Lpg (2)'!G12 -> 117.48 | C4: =SUM([1]Gen!B13) -> 0.532
A5: =Gen!B14 -> 44078 | B5: ='[1]Lpg (2)'!G13 -> 102.96 | C5: =SUM([1]Gen!B14) -> 0.61
A6: =Gen!B15 -> 44079 | B6: ='[1]Lpg (2)'!G14 -> 101.816 | C6: =SUM([1]Gen!B15) -> 0.688
A7: =Gen!B16 -> 44080 | B7: ='[1]Lpg (2)'!G15 -> 106.92 | C7: =SUM([1]Gen!B16) -> 0.532
A8: =Gen!B17 -> 44081 | B8: ='[1]Lpg (2)'!G16 -> 116.732 | C8: =SUM([1]Gen!B17) -> 0.753
A9: =Gen!B18 -> 44082 | B9: ='[1]Lpg (2)'!G17 -> 105.732 | C9: =SUM([1]Gen!B18) -> 0.156
A10: =Gen!B19 -> 44083 | B10: ='[1]Lpg (2)'!G18 -> 114.4 | C10: =SUM([1]Gen!B19) -> 0.442
A11: =Gen!B20 -> 44084 | B11: ='[1]Lpg (2)'!G19 -> 102.08 | C11: =SUM([1]Gen!B20) -> 0.325
A12: =Gen!B21 -> 44085 | B12: ='[1]Lpg (2)'!G20 -> 105.292 | C12: =SUM([1]Gen!B21) -> 0.455
A13: =Gen!B22 -> 44086 | B13: ='[1]Lpg (2)'!G21 -> 114.664 | C13: =SUM([1]Gen!B22) -> 0.416
... A32: =Gen!B41 -> 0 | B32: ='[1]Lpg (2)'!G40 -> 0 | C32: =SUM([1]Gen!B41) -> #REF!

Sheet Water-Meter
A1: Four Seasons Safari Lodge Serengeti - Water Report
C2: Main Meter | F2: KITCHEN | I2: Amani café | L2: Main SW POOL | O2: Laundry | S2: BORE HOLE NO.1 METER READING | V2: BORE HOLE NO.2 METER READING | Y2: BORE HOLE NO.3 METER READING | AB2: BORE HOLE NO.4 METER READING | AE2: BORE HOLE NO.5 METER READING | AH2: BORE HOLE NO.6 METER READING | AK2: RAIN WATER - METER READING | AN2: TOTAL WATER PRODUCTION
A3: DATE | C3: Open Bal | D3: Final | E3: consumption | F3: Open Bal | G3: Final | H3: consumption | I3: Open Bal | J3: Final | K3: consumption | L3: Open Bal | M3: Final | N3: consumption | O3: Open Bal | P3: Final | Q3: consumption | R3: Total consumption
S4: OPEN | T4: FINAL | U4: PROD. | V4: OPEN | W4: FINAL | X4: PROD. | Y4: OPEN | Z4: FINAL | AA4: PROD. | AB4: OPEN | AC4: FINAL | AD4: M3 | AE4: OPEN | AF4: FINAL | AG4: M3 | AH4: OPEN | AI4: FINAL | AJ4: M3 | AK4: OPEN | AL4: FINAL | AM4: M3
C5: =D4 -> 0 | D5: 239973 | E5: 45 | F5: 38000 | G5: 38000 | H5: 0 | I5: 8020 | J5: 8021 | K5: 1 | L5: 12710 | M5: 12740 | N5: 0 | O5: 20252 | P5: 20254 | Q5: =IF((P5-P4)<0,"0",(P5-P4)) -> 20254 | T5: 58181 | V5: 73030 | W5: 73030 | X5: 0 | Y5: 83091 | Z5: 83091 | AA5: 0 | AB5: 15108 | AC5: 15123 | AE5: 18300 | AF5: 18300 | AG5: 0 | AH5: 25336 | AI5: 25336 | AK5: =AL4 -> FINAL
A6: =Gen!B11 -> 44075 | C6: =D5 -> 239973 | D6: 240029 | E6: =IF((D6-D5)<0,"0",(D6-D5)) -> 56 | F6: =G5 -> 38000 | G6: 38000 | H6: =IF((G6-G5)<0,"0",(G6-G5)) -> 0 | I6: =J5 -> 8021 | J6: 8023 | K6: =J6-J5 -> 2 | L6: =M5 -> 12740 | M6: 12745 | N6: =IF((M6-M5)<0,"0",(M6-M5)) -> 5 | O6: =P5 -> 20254 | P6: 20255 | Q6: =IF((P6-P5)<0,"0",(P6-P5)) -> 1 | S6: =T5 -> 58181 | T6: 58267 | U6: =IF((T6-T5)<0,"0",(T6-T5)) -> 86 | V6: =W5 -> 73030 | W6: 73030 | X6: =IF((W6-W5)<0,"0",(W6-W5)) -> 0 | Y6: =Z5 -> 83091 | Z6: 83091 | AA6: =IF((Z6-Z5)<0,"0",(Z6-Z5)) -> 0 | AB6: =AC5 -> 15123 | AC6: 15138 | AD6: =IF((AC6-AC5)<0,"0",(AC6-AC5)) -> 15 | AE6: =AF5 -> 18300 | AF6: 18300 | AG6: =IF((AF6-AF5)<0,"0",(AF6-AF5)) -> 0 | AH6: =AI5 -> 25336 | AI6: 25341 | AJ6: =IF((AI6-AI5)<0,"0",(AI6-AI5)) -> 5 | AK6: =AL5 -> 0 | AM6: =IF((AL6-AL5)<0,"0",(AL6-AL5)) -> 0 | AN6: =U6+X6+AA6+AD6+AG6+AJ6+AM6 -> 106
A7: =Gen!B12 -> 44076 | C7: =D6 -> 240029 | D7: 240087 | E7: =IF((D7-D6)<0,"0",(D7-D6)) -> 58 | F7: =G6 -> 38000 | G7: 38000 | H7: =IF((G7-G6)<0,"0",(G7-G6)) -> 0 | I7: =J6 -> 8023 | J7: 8024 | K7: =J7-J6 -> 1 | L7: =M6 -> 12745 | M7: 12745 | N7: =IF((M7-M6)<0,"0",(M7-M6)) -> 0 | O7: =P6 -> 20255 | P7: 20257 | Q7: =IF((P7-P6)<0,"0",(P7-P6)) -> 2 | S7: =T6 -> 58267 | T7: 58349 | U7: =IF((T7-T6)<0,"0",(T7-T6)) -> 82 | V7: =W6 -> 73030 | W7: 73030 | X7: =IF((W7-W6)<0,"0",(W7-W6)) -> 0 | Y7: =Z6 -> 83091 | Z7: 83091 | AA7: =IF((Z7-Z6)<0,"0",(Z7-Z6)) -> 0 | AB7: =AC6 -> 15138 | AC7: 15155 | AD7: =IF((AC7-AC6)<0,"0",(AC7-AC6)) -> 17 | AE7: =AF6 -> 18300 | AF7: 18300 | AG7: =IF((AF7-AF6)<0,"0",(AF7-AF6)) -> 0 | AH7: =AI6 -> 25341 | AI7: 25367 | AJ7: =IF((AI7-AI6)<0,"0",(AI7-AI6)) -> 26 | AK7: =AL6 -> 0 | AM7: =IF((AL7-AL6)<0,"0",(AL7-AL6)) -> 0 | AN7: =U7+X7+AA7+AD7+AG7+AJ7+AM7 -> 125
A8: =Gen!B13 -> 44077 | C8: =D7 -> 240087 | D8: 240138 | E8: =IF((D8-D7)<0,"0",(D8-D7)) -> 51 | F8: =G7 -> 38000 | G8: 38000 | H8: =IF((G8-G7)<0,"0",(G8-G7)) -> 0 | I8: =J7 -> 8024 | J8: 8025 | K8: =J8-J7 -> 1 | L8: =M7 -> 12745 | M8: 12745 | N8: =IF((M8-M7)<0,"0",(M8-M7)) -> 0 | O8: =P7 -> 20257 | P8: 20258 | Q8: =IF((P8-P7)<0,"0",(P8-P7)) -> 1 | S8: =T7 -> 58349 | T8: 58432 | U8: =IF((T8-T7)<0,"0",(T8-T7)) -> 83 | V8: =W7 -> 73030 | W8: 73030 | X8: =IF((W8-W7)<0,"0",(W8-W7)) -> 0 | Y8: =Z7 -> 83091 | Z8: 83091 | AA8: =IF((Z8-Z7)<0,"0",(Z8-Z7)) -> 0 | AB8: =AC7 -> 15155 | AC8: 15170 | AD8: =IF((AC8-AC7)<0,"0",(AC8-AC7)) -> 15 | AE8: =AF7 -> 18300 | AF8: 18300 | AG8: =IF((AF8-AF7)<0,"0",(AF8-AF7)) -> 0 | AH8: =AI7 -> 25367 | AI8: 25393 | AJ8: =IF((AI8-AI7)<0,"0",(AI8-AI7)) -> 26 | AK8: =AL7 -> 0 | AM8: =IF((AL8-AL7)<0,"0",(AL8-AL7)) -> 0 | AN8: =U8+X8+AA8+AD8+AG8+AJ8+AM8 -> 124
A9: =Gen!B14 -> 44078 | C9: =D8 -> 240138 | D9: 240192 | E9: =IF((D9-D8)<0,"0",(D9-D8)) -> 54 | F9: =G8 -> 38000 | G9: 38000 | H9: =IF((G9-G8)<0,"0",(G9-G8)) -> 0 | I9: =J8 -> 8025 | J9: 8026 | K9: =J9-J8 -> 1 | L9: =M8 -> 12745 | M9: 12750 | N9: =IF((M9-M8)<0,"0",(M9-M8)) -> 5 | O9: =P8 -> 20258 | P9: 20259 | Q9: =IF((P9-P8)<0,"0",(P9-P8)) -> 1 | S9: =T8 -> 58432 | T9: 58509 | U9: =IF((T9-T8)<0,"0",(T9-T8)) -> 77 | V9: =W8 -> 73030 | W9: 73030 | X9: =IF((W9-W8)<0,"0",(W9-W8)) -> 0 | Y9: =Z8 -> 83091 | Z9: 83116 | AA9: =IF((Z9-Z8)<0,"0",(Z9-Z8)) -> 25 | AB9: =AC8 -> 15170 | AC9: 15185 | AD9: =IF((AC9-AC8)<0,"0",(AC9-AC8)) -> 15 | AE9: =AF8 -> 18300 | AF9: 18300 | AG9: =IF((AF9-AF8)<0,"0",(AF9-AF8)) -> 0 | AH9: =AI9 -> 25415 | AI9: 25415 | AJ9: =IF((AI9-AI8)<0,"0",(AI9-AI8)) -> 22 | AK9: =AL8 -> 0 | AM9: =IF((AL9-AL8)<0,"0",(AL9-AL8)) -> 0 | AN9: =U9+X9+AA9+AD9+AG9+AJ9+AM9 -> 139
A10: =Gen!B15 -> 44079 | C10: =D9 -> 240192 | D10: 240242 | E10: =IF((D10-D9)<0,"0",(D10-D9)) -> 50 | F10: =G9 -> 38000 | G10: 38000 | H10: =IF((G10-G9)<0,"0",(G10-G9)) -> 0 | I10: =J9 -> 8026 | J10: 8027 | K10: =IF((J10-J9)<0,"0",(J10-J9)) -> 1 | L10: =M9 -> 12750 | M10: 12750 | N10: =IF((M10-M9)<0,"0",(M10-M9)) -> 0 | O10: =P9 -> 20259 | P10: 20261 | Q10: =IF((P10-P9)<0,"0",(P10-P9)) -> 2 | S10: =T9 -> 58509 | T10: 58529 | U10: =IF((T10-T9)<0,"0",(T10-T9)) -> 20 | V10: =W9 -> 73030 | W10: 73030 | X10: =IF((W10-W9)<0,"0",(W10-W9)) -> 0 | Y10: =Z9 -> 83116 | Z10: 83159 | AA10: =IF((Z10-Z9)<0,"0",(Z10-Z9)) -> 43 | AB10: =AC9 -> 15185 | AC10: 15201 | AD10: =IF((AC10-AC9)<0,"0",(AC10-AC9)) -> 16 | AE10: =AF9 -> 18300 | AF10: 18300 | AG10: =IF((AF10-AF9)<0,"0",(AF10-AF9)) -> 0 | AH10: =AI9 -> 25415 | AI10: 25439 | AJ10: =IF((AI10-AI9)<0,"0",(AI10-AI9)) -> 24 | AK10: =AL9 -> 0 | AM10: =IF((AL10-AL9)<0,"0",(AL10-AL9)) -> 0 | AN10: =U10+X10+AA10+AD10+AG10+AJ10+AM10 -> 103
A11: =Gen!B16 -> 44080 | C11: =D10 -> 240242 | D11: 240294 | E11: =IF((D11-D10)<0,"0",(D11-D10)) -> 52 | F11: =G10 -> 38000 | G11: 38000 | H11: =IF((G11-G10)<0,"0",(G11-G10)) -> 0 | I11: =J10 -> 8027 | J11: 8028 | K11: =IF((J11-J10)<0,"0",(J11-J10)) -> 1 | L11: =M10 -> 12750 | M11: 12755 | N11: =IF((M11-M10)<0,"0",(M11-M10)) -> 5 | O11: =P10 -> 20261 | P11: 20263 | Q11: =IF((P11-P10)<0,"0",(P11-P10)) -> 2 | S11: =T10 -> 58529 | T11: 58542 | U11: =IF((T11-T10)<0,"0",(T11-T10)) -> 13 | V11: =W10 -> 73030 | W11: 73030 | X11: =IF((W11-W10)<0,"0",(W11-W10)) -> 0 | Y11: =Z10 -> 83159 | Z11: 83192 | AA11: =IF((Z11-Z10)<0,"0",(Z11-Z10)) -> 33 | AB11: =AC10 -> 15201 | AC11: 15216 | AD11: =IF((AC11-AC10)<0,"0",(AC11-AC10)) -> 15 | AE11: =AF11 -> 18300 | AF11: 18300 | AG11: =IF((AF11-AF10)<0,"0",(AF11-AF10)) -> 0 | AH11: =AI10 -> 25439 | AI11: 25461 | AJ11: =IF((AI11-AI10)<0,"0",(AI11-AI10)) -> 22 | AK11: =AL10 -> 0 | AM11: =IF((AL11-AL10)<0,"0",(AL11-AL10)) -> 0 | AN11: =U11+X11+AA11+AD11+AG11+AJ11+AM11 -> 83
A12: =Gen!B17 -> 44081 | C12: =D11 -> 240294 | D12: 240352 | E12: =IF((D12-D11)<0,"0",(D12-D11)) -> 58 | F12: =G11 -> 38000 | G12: 38000 | H12: =IF((G12-G11)<0,"0",(G12-G11)) -> 0 | I12: =J11 -> 8028 | J12: 8029 | K12: =IF((J12-J11)<0,"0",(J12-J11)) -> 1 | L12: =M11 -> 12755 | M12: 12755 | N12: =IF((M12-M11)<0,"0",(M12-M11)) -> 0 | O12: =P11 -> 20263 | P12: 20264 | Q12: =IF((P12-P11)<0,"0",(P12-P11)) -> 1 | S12: =T11 -> 58542 | T12: 58563 | U12: =IF((T12-T11)<0,"0",(T12-T11)) -> 21 | V12: =W11 -> 73030 | W12: 73030 | X12: =IF((W12-W11)<0,"0",(W12-W11)) -> 0 | Y12: =Z11 -> 83192 | Z12: 83235 | AA12: =IF((Z12-Z11)<0,"0",(Z12-Z11)) -> 43 | AB12: =AC11 -> 15216 | AC12: 15233 | AD12: =IF((AC12-AC11)<0,"0",(AC12-AC11)) -> 17 | AE12: =AF12 -> 18300 | AF12: 18300 | AG12: =IF((AF12-AF11)<0,"0",(AF12-AF11)) -> 0 | AH12: =AI11 -> 25461 | AI12: 25486 | AJ12: =IF((AI12-AI11)<0,"0",(AI12-AI11)) -> 25 | AK12: =AL11 -> 0 | AM12: =IF((AL12-AL11)<0,"0",(AL12-AL11)) -> 0 | AN12: =U12+X12+AA12+AD12+AG12+AJ12+AM12 -> 106
A13: =Gen!B18 -> 44082 | C13: =D12 -> 240352 | D13: 240398 | E13: =IF((D13-D12)<0,"0",(D13-D12)) -> 46 | F13: =G12 -> 38000 | G13: 38000 | H13: =IF((G13-G12)<0,"0",(G13-G12)) -> 0 | I13: =J12 -> 8029 | J13: 8030 | K13: =IF((J13-J12)<0,"0",(J13-J12)) -> 1 | L13: =M12 -> 12755 | M13: 12755 | N13: =IF((M13-M12)<0,"0",(M13-M12)) -> 0 | O13: =P12 -> 20264 | P13: 20268 | Q13: =IF((P13-P12)<0,"0",(P13-P12)) -> 4 | S13: =T12 -> 58563 | T13: 58625 | U13: =IF((T13-T12)<0,"0",(T13-T12)) -> 62 | V13: =W12 -> 73030 | W13: 73030 | X13: =IF((W13-W12)<0,"0",(W13-W12)) -> 0 | Y13: =Z12 -> 83235 | Z13: 83273 | AA13: =IF((Z13-Z12)<0,"0",(Z13-Z12)) -> 38 | AB13: =AC12 -> 15233 | AC13: 15248 | AD13: =IF((AC13-AC12)<0,"0",(AC13-AC12)) -> 15 | AE13: =AF13 -> 18300 | AF13: 18300 | AG13: =IF((AF13-AF12)<0,"0",(AF13-AF12)) -> 0 | AH13: =AI12 -> 25486 | AI13: 25509 | AJ13: =IF((AI13-AI12)<0,"0",(AI13-AI12)) -> 23 | AK13: =AL12 -> 0 | AM13: =IF((AL13-AL12)<0,"0",(AL13-AL12)) -> 0 | AN13: =U13+X13+AA13+AD13+AG13+AJ13+AM13 -> 138
A14: =Gen!B19 -> 44083 | C14: =D13 -> 240398 | D14: 240450 | E14: =IF((D14-D13)<0,"0",(D14-D13)) -> 52 | F14: =G13 -> 38000 | G14: 38000 | H14: =IF((G14-G13)<0,"0",(G14-G13)) -> 0 | I14: =J13 -> 8030 | J14: 8032 | K14: =IF((J14-J13)<0,"0",(J14-J13)) -> 2 | L14: =M13 -> 12755 | M14: 12755 | N14: =IF((M14-M13)<0,"0",(M14-M13)) -> 0 | O14: =P13 -> 20268 | P14: 20269 | Q14: =IF((P14-P13)<0,"0",(P14-P13)) -> 1 | S14: =T13 -> 58625 | T14: 58642 | U14: =IF((T14-T13)<0,"0",(T14-T13)) -> 17 | V14: =W13 -> 73030 | W14: 73030 | X14: =IF((W14-W13)<0,"0",(W14-W13)) -> 0 | Y14: =Z13 -> 83273 | Z14: 83310 | AA14: =IF((Z14-Z13)<0,"0",(Z14-Z13)) -> 37 | AB14: =AC13 -> 15248 | AC14: 15265 | AD14: =IF((AC14-AC13)<0,"0",(AC14-AC13)) -> 17 | AE14: =AF14 -> 18300 | AF14: 18300 | AG14: =IF((AF14-AF13)<0,"0",(AF14-AF13)) -> 0 | AH14: =AI13 -> 25509 | AI14: 25530 | AJ14: =IF((AI14-AI13)<0,"0",(AI14-AI13)) -> 21 | AK14: =AL13 -> 0 | AM14: =IF((AL14-AL13)<0,"0",(AL14-AL13)) -> 0 | AN14: =U14+X14+AA14+AD14+AG14+AJ14+AM14 -> 92
A15: =Gen!B20 -> 44084 | C15: =D14 -> 240450 | D15: 240505 | E15: =IF((D15-D14)<0,"0",(D15-D14)) -> 55 | F15: =G14 -> 38000 | G15: 38000 | H15: =IF((G15-G14)<0,"0",(G15-G14)) -> 0 | I15: =J14 -> 8032 | J15: 8033 | K15: =IF((J15-J14)<0,"0",(J15-J14)) -> 1 | L15: =M14 -> 12755 | M15: 12755 | N15: =IF((M15-M14)<0,"0",(M15-M14)) -> 0 | O15: =P14 -> 20269 | P15: 20270 | Q15: =IF((P15-P14)<0,"0",(P15-P14)) -> 1 | S15: =T14 -> 58642 | T15: 58662 | U15: =IF((T15-T14)<0,"0",(T15-T14)) -> 20 | V15: =W14 -> 73030 | W15: 73030 | X15: =IF((W15-W14)<0,"0",(W15-W14)) -> 0 | Y15: =Z14 -> 83310 | Z15: 83348 | AA15: =IF((Z15-Z14)<0,"0",(Z15-Z14)) -> 38 | AB15: =AC14 -> 15265 | AC15: 15285 | AD15: =IF((AC15-AC14)<0,"0",(AC15-AC14)) -> 20 | AE15: =AF15 -> 18300 | AF15: 18300 | AG15: =IF((AF15-AF14)<0,"0",(AF15-AF14)) -> 0 | AH15: =AI14 -> 25530 | AI15: 25553 | AJ15: =IF((AI15-AI14)<0,"0",(AI15-AI14)) -> 23 | AK15: =AL14 -> 0 | AM15: =IF((AL15-AL14)<0,"0",(AL15-AL14)) -> 0 | AN15: =U15+X15+AA15+AD15+AG15+AJ15+AM15 -> 101
A16: =Gen!B21 -> 44085 | C16: =D15 -> 240505 | D16: 240599 | E16: =IF((D16-D15)<0,"0",(D16-D15)) -> 94 | F16: =G15 -> 38000 | G16: 38000 | H16: =IF((G16-G15)<0,"0",(G16-G15)) -> 0 | I16: =J15 -> 8033 | J16: 8034 | K16: =IF((J16-J15)<0,"0",(J16-J15)) -> 1 | L16: =M15 -> 12755 | M16: 12755 | N16: =IF((M16-M15)<0,"0",(M16-M15)) -> 0 | O16: =P15 -> 20270 | P16: 20271 | Q16: =IF((P16-P15)<0,"0",(P16-P15)) -> 1 | S16: =T15 -> 58662 | T16: 58683 | U16: =IF((T16-T15)<0,"0",(T16-T15)) -> 21 | V16: =W15 -> 73030 | W16: 73030 | X16: =IF((W16-W15)<0,"0",(W16-W15)) -> 0 | Y16: =Z15 -> 83348 | Z16: 83385 | AA16: =IF((Z16-Z15)<0,"0",(Z16-Z15)) -> 37 | AB16: =AC15 -> 15285 | AC16: 15305 | AD16: =IF((AC16-AC15)<0,"0",(AC16-AC15)) -> 20 | AE16: =AF16 -> 18300 | AF16: 18300 | AG16: =IF((AF16-AF15)<0,"0",(AF16-AF15)) -> 0 | AH16: =AI15 -> 25553 | AI16: 25576 | AJ16: =IF((AI16-AI15)<0,"0",(AI16-AI15)) -> 23 | AK16: =AL15 -> 0 | AM16: =IF((AL16-AL15)<0,"0",(AL16-AL15)) -> 0 | AN16: =U16+X16+AA16+AD16+AG16+AJ16+AM16 -> 101
A17: =Gen!B22 -> 44086 | C17: =D16 -> 240599 | D17: 240658 | E17: =IF((D17-D16)<0,"0",(D17-D16)) -> 59 | F17: =G16 -> 38000 | G17: 38000 | H17: =IF((G17-G16)<0,"0",(G17-G16)) -> 0 | I17: =J16 -> 8034 | J17: 8035 | K17: =IF((J17-J16)<0,"0",(J17-J16)) -> 1 | L17: =M16 -> 12755 | M17: 12755 | N17: =IF((M17-M16)<0,"0",(M17-M16)) -> 0 | O17: =P16 -> 20271 | P17: 20272 | Q17: =IF((P17-P16)<0,"0",(P17-P16)) -> 1 | S17: =T16 -> 58683 | T17: 58692 | U17: =IF((T17-T16)<0,"0",(T17-T16)) -> 9 | V17: =W16 -> 73030 | W17: 73030 | X17: =IF((W17-W16)<0,"0",(W17-W16)) -> 0 | Y17: =Z16 -> 83385 | Z17: 83421 | AA17: =IF((Z17-Z16)<0,"0",(Z17-Z16)) -> 36 | AB17: =AC16 -> 15305 | AC17: 15324 | AD17: =IF((AC17-AC16)<0,"0",(AC17-AC16)) -> 19 | AE17: =AF17 -> 18300 | AF17: 18300 | AG17: =IF((AF17-AF16)<0,"0",(AF17-AF16)) -> 0 | AH17: =AI16 -> 25576 | AI17: 25598 | AJ17: =IF((AI17-AI16)<0,"0",(AI17-AI16)) -> 22 | AK17: =AL16 -> 0 | AM17: =IF((AL17-AL16)<0,"0",(AL17-AL16)) -> 0 | AN17: =U17+X17+AA17+AD17+AG17+AJ17+AM17 -> 86
A18: =Gen!B23 -> 44087 | C18: =D17 -> 240658 | D18: 240694 | E18: =IF((D18-D17)<0,"0",(D18-D17)) -> 36 | F18: =G17 -> 38000 | G18: 38000 | H18: =IF((G18-G17)<0,"0",(G18-G17)) -> 0 | I18: =J17 -> 8035 | J18: 8036 | K18: =IF((J18-J17)<0,"0",(J18-J17)) -> 1 | L18: =M17 -> 12755 | M18: 12755 | N18: =IF((M18-M17)<0,"0",(M18-M17)) -> 0 | O18: =P17 -> 20272 | P18: 20273 | Q18: =IF((P18-P17)<0,"0",(P18-P17)) -> 1 | S18: =T17 -> 58692 | T18: 58774 | U18: =IF((T18-T17)<0,"0",(T18-T17)) -> 82 | V18: =W17 -> 73030 | W18: 73030 | X18: =IF((W18-W17)<0,"0",(W18-W17)) -> 0 | Y18: =Z17 -> 83421 | Z18: 83457 | AA18: =IF((Z18-Z17)<0,"0",(Z18-Z17)) -> 36 | AB18: =AC17 -> 15324 | AC18: 15344 | AD18: =IF((AC18-AC17)<0,"0",(AC18-AC17)) -> 20 | AE18: =AF18 -> 18300 | AF18: 18300 | AG18: =IF((AF18-AF17)<0,"0",(AF18-AF17)) -> 0 | AH18: =AI17 -> 25598 | AI18: 25621 | AJ18: =IF((AI18-AI17)<0,"0",(AI18-AI17)) -> 23 | AK18: =AL17 -> 0 | AM18: =IF((AL18-AL17)<0,"0",(AL18-AL17)) -> 0 | AN18: =U18+X18+AA18+AD18+AG18+AJ18+AM18 -> 161
A19: =Gen!B24 -> 44088 | C19: =D18 -> 240694 | D19: 240747 | E19: =IF((D19-D18)<0,"0",(D19-D18)) -> 53 | F19: =G18 -> 38000 | G19: 38000 | H19: =IF((G19-G18)<0,"0",(G19-G18)) -> 0 | I19: =J18 -> 8036 | J19: 8036 | K19: =IF((J19-J18)<0,"0",(J19-J18)) -> 0 | L19: =M18 -> 12755 | M19: 12755 | N19: =IF((M19-M18)<0,"0",(M19-M18)) -> 0 | O19: =P18 -> 20273 | P19: 20276 | Q19: =IF((P19-P18)<0,"0",(P19-P18)) -> 3 | S19: =T18 -> 58774 | T19: 58795 | U19: =IF((T19-T18)<0,"0",(T19-T18)) -> 21 | V19: =W18 -> 73030 | W19: 73030 | X19: =IF((W19-W18)<0,"0",(W19-W18)) -> 0 | Y19: =Z18 -> 83457 | Z19: 83494 | AA19: =IF((Z19-Z18)<0,"0",(Z19-Z18)) -> 37 | AB19: =AC18 -> 15344 | AC19: 15364 | AD19: =IF((AC19-AC18)<0,"0",(AC19-AC18)) -> 20 | AE19: =AF19 -> 18300 | AF19: 18300 | AG19: =IF((AF19-AF18)<0,"0",(AF19-AF18)) -> 0 | AH19: =AI18 -> 25621 | AI19: 25643 | AJ19: =IF((AI19-AI18)<0,"0",(AI19-AI18)) -> 22 | AK19: =AL18 -> 0 | AM19: =IF((AL19-AL18)<0,"0",(AL19-AL18)) -> 0 | AN19: =U19+X19+AA19+AD19+AG19+AJ19+AM19 -> 100
A20: =Gen!B25 -> 44089 | C20: =D19 -> 240747 | D20: 240787 | E20: =IF((D20-D19)<0,"0",(D20-D19)) -> 40 | F20: =G19 -> 38000 | G20: 38000 | H20: =IF((G20-G19)<0,"0",(G20-G19)) -> 0 | I20: =J19 -> 8036 | J20: 8037 | K20: =IF((J20-J19)<0,"0",(J20-J19)) -> 1 | L20: =M19 -> 12755 | M20: 12755 | N20: =IF((M20-M19)<0,"0",(M20-M19)) -> 0 | O20: =P19 -> 20276 | P20: 20278 | Q20: =IF((P20-P19)<0,"0",(P20-P19)) -> 2 | S20: =T19 -> 58795 | T20: 58795 | U20: =IF((T20-T19)<0,"0",(T20-T19)) -> 0 | V20: =W19 -> 73030 | W20: 73030 | X20: =IF((W20-W19)<0,"0",(W20-W19)) -> 0 | Y20: =Z19 -> 83494 | Z20: 83530 | AA20: =IF((Z20-Z19)<0,"0",(Z20-Z19)) -> 36 | AB20: =AC19 -> 15364 | AC20: 15383 | AD20: =IF((AC20-AC19)<0,"0",(AC20-AC19)) -> 19 | AE20: =AF20 -> 18300 | AF20: 18300 | AG20: =IF((AF20-AF19)<0,"0",(AF20-AF19)) -> 0 | AH20: =AI19 -> 25643 | AI20: 25665 | AJ20: =IF((AI20-AI19)<0,"0",(AI20-AI19)) -> 22 | AK20: =AL19 -> 0 | AM20: =IF((AL20-AL19)<0,"0",(AL20-AL19)) -> 0 | AN20: =U20+X20+AA20+AD20+AG20+AJ20+AM20 -> 77
A21: =Gen!B26 -> 44090 | C21: =D20 -> 240787 | D21: 240817 | E21: =IF((D21-D20)<0,"0",(D21-D20)) -> 30 | F21: =G20 -> 38000 | G21: 38000 | H21: =IF((G21-G20)<0,"0",(G21-G20)) -> 0 | I21: =J20 -> 8037 | J21: 8038 | K21: =IF((J21-J20)<0,"0",(J21-J20)) -> 1 | L21: =M20 -> 12755 | M21: 12755 | N21: =IF((M21-M20)<0,"0",(M21-M20)) -> 0 | O21: =P20 -> 20278 | P21: 20280 | Q21: =IF((P21-P20)<0,"0",(P21-P20)) -> 2 | S21: =T20 -> 58795 | T21: 58865 | U21: =IF((T21-T20)<0,"0",(T21-T20)) -> 70 | V21: =W20 -> 73030 | W21: 73030 | X21: =IF((W21-W20)<0,"0",(W21-W20)) -> 0 | Y21: =Z20 -> 83530 | Z21: 83567 | AA21: =IF((Z21-Z20)<0,"0",(Z21-Z20)) -> 37 | AB21: =AC20 -> 15383 | AC21: 15403 | AD21: =IF((AC21-AC20)<0,"0",(AC21-AC20)) -> 20 | AE21: =AF20 -> 18300 | AF21: 18300 | AG21: =IF((AF21-AF20)<0,"0",(AF21-AF20)) -> 0 | AH21: =AI20 -> 25665 | AI21: 25687 | AJ21: =IF((AI21-AI20)<0,"0",(AI21-AI20)) -> 22 | AK21: =AL20 -> 0 | AM21: =IF((AL21-AL20)<0,"0",(AL21-AL20)) -> 0 | AN21: =U21+X21+AA21+AD21+AG21+AJ21+AM21 -> 149
A22: =Gen!B27 -> 44091 | C22: =D21 -> 240817 | D22: 240866 | E22: =IF((D22-D21)<0,"0",(D22-D21)) -> 49 | F22: =G21 -> 38000 | G22: 38000 | H22: =IF((G22-G21)<0,"0",(G22-G21)) -> 0 | I22: =J21 -> 8038 | J22: 8038 | K22: =IF((J22-J21)<0,"0",(J22-J21)) -> 0 | L22: =M21 -> 12755 | M22: 12755 | N22: =IF((M22-M21)<0,"0",(M22-M21)) -> 0 | O22: =P21 -> 20280 | P22: 20282 | Q22: =IF((P22-P21)<0,"0",(P22-P21)) -> 2 | S22: =T21 -> 58865 | T22: 58890 | U22: =IF((T22-T21)<0,"0",(T22-T21)) -> 25 | V22: =W21 -> 73030 | W22: 73030 | X22: =IF((W22-W21)<0,"0",(W22-W21)) -> 0 | Y22: =Z21 -> 83567 | Z22: 83604 | AA22: =IF((Z22-Z21)<0,"0",(Z22-Z21)) -> 37 | AB22: =AC21 -> 15403 | AC22: 15423 | AD22: =IF((AC22-AC21)<0,"0",(AC22-AC21)) -> 20 | AE22: =AF21 -> 18300 | AF22: 18300 | AG22: =IF((AF22-AF21)<0,"0",(AF22-AF21)) -> 0 | AH22: =AI21 -> 25687 | AI22: 25710 | AJ22: =IF((AI22-AI21)<0,"0",(AI22-AI21)) -> 23 | AK22: =AL21 -> 0 | AM22: =IF((AL22-AL21)<0,"0",(AL22-AL21)) -> 0 | AN22: =U22+X22+AA22+AD22+AG22+AJ22+AM22 -> 105
A23: =Gen!B28 -> 44092 | C23: =D22 -> 240866 | D23: 240916 | E23: =IF((D23-D22)<0,"0",(D23-D22)) -> 50 | F23: =G22 -> 38000 | G23: 38000 | H23: =IF((G23-G22)<0,"0",(G23-G22)) -> 0 | I23: =J22 -> 8038 | J23: 8039 | K23: =IF((J23-J22)<0,"0",(J23-J22)) -> 1 | L23: =M22 -> 12755 | M23: 12755 | N23: =IF((M23-M22)<0,"0",(M23-M22)) -> 0 | O23: =P22 -> 20282 | P23: 20284 | Q23: =IF((P23-P22)<0,"0",(P23-P22)) -> 2 | S23: =T22 -> 58890 | T23: 58918 | U23: =IF((T23-T22)<0,"0",(T23-T22)) -> 28 | V23: =W22 -> 73030 | W23: 73030 | X23: =IF((W23-W22)<0,"0",(W23-W22)) -> 0 | Y23: =Z22 -> 83604 | Z23: 83639 | AA23: =IF((Z23-Z22)<0,"0",(Z23-Z22)) -> 35 | AB23: =AC22 -> 15423 | AC23: 15442 | AD23: =IF((AC23-AC22)<0,"0",(AC23-AC22)) -> 19 | AE23: =AF22 -> 18300 | AF23: 18300 | AG23: =IF((AF23-AF22)<0,"0",(AF23-AF22)) -> 0 | AH23: =AI22 -> 25710 | AI23: 25732 | AJ23: =IF((AI23-AI22)<0,"0",(AI23-AI22)) -> 22 | AK23: =AL22 -> 0 | AM23: =IF((AL23-AL22)<0,"0",(AL23-AL22)) -> 0 | AN23: =U23+X23+AA23+AD23+AG23+AJ23+AM23 -> 104
A24: =Gen!B29 -> 44093 | C24: =D23 -> 240916 | D24: 240967 | E24: =IF((D24-D23)<0,"0",(D24-D23)) -> 51 | F24: =G23 -> 38000 | G24: 38000 | H24: =IF((G24-G23)<0,"0",(G24-G23)) -> 0 | I24: =J23 -> 8039 | J24: 8040 | K24: =IF((J24-J23)<0,"0",(J24-J23)) -> 1 | L24: =M23 -> 12755 | M24: 12755 | N24: =IF((M24-M23)<0,"0",(M24-M23)) -> 0 | O24: =P23 -> 20284 | P24: 20286 | Q24: =IF((P24-P23)<0,"0",(P24-P23)) -> 2 | S24: =T23 -> 58918 | T24: 58993 | U24: =IF((T24-T23)<0,"0",(T24-T23)) -> 75 | V24: =W23 -> 73030 | W24: 73030 | X24: =IF((W24-W23)<0,"0",(W24-W23)) -> 0 | Y24: =Z23 -> 83639 | Z24: 83675 | AA24: =IF((Z24-Z23)<0,"0",(Z24-Z23)) -> 36 | AB24: =AC23 -> 15442 | AC24: 15461 | AD24: =IF((AC24-AC23)<0,"0",(AC24-AC23)) -> 19 | AE24: =AF23 -> 18300 | AF24: 18300 | AG24: =IF((AF24-AF23)<0,"0",(AF24-AF23)) -> 0 | AH24: =AI23 -> 25732 | AI24: 25753 | AJ24: =IF((AI24-AI23)<0,"0",(AI24-AI23)) -> 21 | AK24: =AL23 -> 0 | AM24: =IF((AL24-AL23)<0,"0",(AL24-AL23)) -> 0 | AN24: =U24+X24+AA24+AD24+AG24+AJ24+AM24 -> 151
A25: =Gen!B30 -> 44094 | C25: =D24 -> 240967 | D25: 241013 | E25: =IF((D25-D24)<0,"0",(D25-D24)) -> 46 | F25: =G24 -> 38000 | G25: 38000 | H25: =IF((G26-G24)<0,"0",(G26-G24)) -> 0 | I25: =J24 -> 8040 | J25: 8042 | K25: =IF((J25-J24)<0,"0",(J25-J24)) -> 2 | L25: =M24 -> 12755 | M25: 12755 | N25: =IF((M25-M24)<0,"0",(M25-M24)) -> 0 | O25: =P24 -> 20286 | P25: 20288 | Q25: =IF((P25-P24)<0,"0",(P25-P24)) -> 2 | S25: =T24 -> 58993 | T25: 59066 | U25: =IF((T25-T24)<0,"0",(T25-T24)) -> 73 | V25: =W24 -> 73030 | W25: 73030 | X25: =IF((W25-W24)<0,"0",(W25-W24)) -> 0 | Y25: =Z24 -> 83675 | Z25: 83711 | AA25: =IF((Z25-Z24)<0,"0",(Z25-Z24)) -> 36 | AB25: =AC24 -> 15461 | AC25: 15481 | AD25: =IF((AC25-AC24)<0,"0",(AC25-AC24)) -> 20 | AE25: =AF24 -> 18300 | AF25: 18300 | AG25: =IF((AF25-AF24)<0,"0",(AF25-AF24)) -> 0 | AH25: =AI24 -> 25753 | AI25: 25776 | AJ25: =IF((AI25-AI24)<0,"0",(AI25-AI24)) -> 23 | AK25: =AL24 -> 0 | AM25: =IF((AL25-AL24)<0,"0",(AL25-AL24)) -> 0 | AN25: =U25+X25+AA25+AD25+AG25+AJ25+AM25 -> 152
A26: =Gen!B31 -> 44095 | C26: =D25 -> 241013 | D26: 241059 | E26: =IF((D26-D25)<0,"0",(D26-D25)) -> 46 | F26: =G26 -> 38000 | G26: 38000 | H26: =IF((G27-G25)<0,"0",(G27-G25)) -> 0 | I26: =J25 -> 8042 | J26: 8042 | K26: =IF((J26-J25)<0,"0",(J26-J25)) -> 0 | L26: =M25 -> 12755 | M26: 12755 | N26: =IF((M26-M25)<0,"0",(M26-M25)) -> 0 | O26: =P25 -> 20288 | P26: 20290 | Q26: =IF((P26-P25)<0,"0",(P26-P25)) -> 2 | S26: =T25 -> 59066 | T26: 59127 | U26: =IF((T26-T25)<0,"0",(T26-T25)) -> 61 | V26: =W25 -> 73030 | W26: 73030 | X26: =IF((W26-W25)<0,"0",(W26-W25)) -> 0 | Y26: =Z25 -> 83711 | Z26: 83747 | AA26: =IF((Z26-Z25)<0,"0",(Z26-Z25)) -> 36 | AB26: =AC25 -> 15481 | AC26: 15500 | AD26: =IF((AC26-AC25)<0,"0",(AC26-AC25)) -> 19 | AE26: =AF25 -> 18300 | AF26: 18300 | AG26: =IF((AF26-AF25)<0,"0",(AF26-AF25)) -> 0 | AH26: =AI25 -> 25776 | AI26: 25797 | AJ26: =IF((AI26-AI25)<0,"0",(AI26-AI25)) -> 21 | AK26: =AL25 -> 0 | AM26: =IF((AL26-AL25)<0,"0",(AL26-AL25)) -> 0 | AN26: =U26+X26+AA26+AD26+AG26+AJ26+AM26 -> 137
A27: =Gen!B32 -> 44096 | C27: =D26 -> 241059 | D27: 241115 | E27: =IF((D27-D26)<0,"0",(D27-D26)) -> 56 | F27: =G27 -> 38000 | G27: 38000 | H27: =IF((G28-G26)<0,"0",(G28-G26)) -> 0 | I27: =J26 -> 8042 | J27: 8043 | K27: =IF((J27-J26)<0,"0",(J27-J26)) -> 1 | L27: =M26 -> 12755 | M27: 12755 | N27: =IF((M27-M26)<0,"0",(M27-M26)) -> 0 | O27: =P26 -> 20290 | P27: 20292 | Q27: =IF((P27-P26)<0,"0",(P27-P26)) -> 2 | S27: =T26 -> 59127 | T27: 59198 | U27: =IF((T27-T26)<0,"0",(T27-T26)) -> 71 | V27: =W26 -> 73030 | W27: 73030 | X27: =IF((W27-W26)<0,"0",(W27-W26)) -> 0 | Y27: =Z26 -> 83747 | Z27: 83782 | AA27: =IF((Z27-Z26)<0,"0",(Z27-Z26)) -> 35 | AB27: =AC26 -> 15500 | AC27: 15519 | AD27: =IF((AC27-AC26)<0,"0",(AC27-AC26)) -> 19 | AE27: =AF26 -> 18300 | AF27: 18300 | AG27: =IF((AF27-AF26)<0,"0",(AF27-AF26)) -> 0 | AH27: =AI26 -> 25797 | AI27: 25819 | AJ27: =IF((AI27-AI26)<0,"0",(AI27-AI26)) -> 22 | AK27: =AL26 -> 0 | AM27: =IF((AL27-AL26)<0,"0",(AL27-AL26)) -> 0 | AN27: =U27+X27+AA27+AD27+AG27+AJ27+AM27 -> 147
A28: =Gen!B33 -> 44097 | C28: =D27 -> 241115 | D28: 241164 | E28: =IF((D28-D27)<0,"0",(D28-D27)) -> 49 | F28: =G28 -> 38000 | G28: 38000 | H28: =IF((G28-G27)<0,"0",(G28-G27)) -> 0 | I28: =J27 -> 8043 | J28: 8044 | K28: =IF((J28-J27)<0,"0",(J28-J27)) -> 1 | L28: =M27 -> 12755 | M28: 12755 | N28: =IF((M28-M27)<0,"0",(M28-M27)) -> 0 | O28: =P27 -> 20292 | P28: 20294 | Q28: =IF((P28-P27)<0,"0",(P28-P27)) -> 2 | S28: =T27 -> 59198 | T28: 59260 | U28: =IF((T28-T27)<0,"0",(T28-T27)) -> 62 | V28: =W27 -> 73030 | W28: 73030 | X28: =IF((W28-W27)<0,"0",(W28-W27)) -> 0 | Y28: =Z27 -> 83782 | Z28: 83817 | AA28: =IF((Z28-Z27)<0,"0",(Z28-Z27)) -> 35 | AB28: =AC27 -> 15519 | AC28: 15537 | AD28: =IF((AC28-AC27)<0,"0",(AC28-AC27)) -> 18 | AE28: =AF27 -> 18300 | AF28: 18300 | AG28: =IF((AF28-AF27)<0,"0",(AF28-AF27)) -> 0 | AH28: =AI27 -> 25819 | AI28: 25841 | AJ28: =IF((AI28-AI27)<0,"0",(AI28-AI27)) -> 22 | AK28: =AL27 -> 0 | AM28: =IF((AL28-AL27)<0,"0",(AL28-AL27)) -> 0 | AN28: =U28+X28+AA28+AD28+AG28+AJ28+AM28 -> 137
A29: =Gen!B34 -> 44098 | C29: =D28 -> 241164 | D29: 241212 | E29: =IF((D29-D28)<0,"0",(D29-D28)) -> 48 | F29: =G29 -> 38000 | G29: 38000 | H29: =IF((G29-G28)<0,"0",(G29-G28)) -> 0 | I29: =J28 -> 8044 | J29: 8045 | K29: =IF((J29-J28)<0,"0",(J29-J28)) -> 1 | L29: =M28 -> 12755 | M29: 12755 | N29: =IF((M29-M28)<0,"0",(M29-M28)) -> 0 | O29: =P28 -> 20294 | P29: 20297 | Q29: =IF((P29-P28)<0,"0",(P29-P28)) -> 3 | S29: =T28 -> 59260 | T29: 59317 | U29: =IF((T29-T28)<0,"0",(T29-T28)) -> 57 | V29: =W28 -> 73030 | W29: 73030 | X29: =IF((W29-W28)<0,"0",(W29-W28)) -> 0 | Y29: =Z28 -> 83817 | Z29: 83853 | AA29: =IF((Z29-Z28)<0,"0",(Z29-Z28)) -> 36 | AB29: =AC28 -> 15537 | AC29: 15556 | AD29: =IF((AC29-AC28)<0,"0",(AC29-AC28)) -> 19 | AE29: =AF28 -> 18300 | AF29: 18300 | AG29: =IF((AF29-AF28)<0,"0",(AF29-AF28)) -> 0 | AH29: =AI28 -> 25841 | AI29: 25863 | AJ29: =IF((AI29-AI28)<0,"0",(AI29-AI28)) -> 22 | AK29: =AL28 -> 0 | AM29: =IF((AL29-AL28)<0,"0",(AL29-AL28)) -> 0 | AN29: =U29+X29+AA29+AD29+AG29+AJ29+AM29 -> 134
A30: =Gen!B35 -> 44099 | C30: =D29 -> 241212 | D30: 241262 | E30: =IF((D30-D29)<0,"0",(D30-D29)) -> 50 | F30: =G30 -> 38000 | G30: 38000 | H30: =IF((G30-G29)<0,"0",(G30-G29)) -> 0 | I30: =J29 -> 8045 | J30: 8046 | K30: =IF((J30-J29)<0,"0",(J30-J29)) -> 1 | L30: =M29 -> 12755 | M30: 12755 | N30: =IF((M30-M29)<0,"0",(M30-M29)) -> 0 | O30: =P29 -> 20297 | P30: 20303 | Q30: =IF((P30-P29)<0,"0",(P30-P29)) -> 6 | S30: =T29 -> 59317 | T30: 59368 | U30: =IF((T30-T29)<0,"0",(T30-T29)) -> 51 | V30: =W29 -> 73030 | W30: 73030 | X30: =IF((W30-W29)<0,"0",(W30-W29)) -> 0 | Y30: =Z29 -> 83853 | Z30: 83889 | AA30: =IF((Z30-Z29)<0,"0",(Z30-Z29)) -> 36 | AB30: =AC29 -> 15556 | AC30: 15574 | AD30: =IF((AC30-AC29)<0,"0",(AC30-AC29)) -> 18 | AE30: =AF29 -> 18300 | AF30: 18300 | AG30: =IF((AF30-AF29)<0,"0",(AF30-AF29)) -> 0 | AH30: =AI29 -> 25863 | AI30: 25885 | AJ30: =IF((AI30-AI29)<0,"0",(AI30-AI29)) -> 22 | AK30: =AL29 -> 0 | AM30: =IF((AL30-AL29)<0,"0",(AL30-AL29)) -> 0 | AN30: =U30+X30+AA30+AD30+AG30+AJ30+AM30 -> 127
A31: =Gen!B36 -> 44100 | C31: =D30 -> 241262 | D31: 241317 | E31: =IF((D31-D30)<0,"0",(D31-D30)) -> 55 | F31: =G31 -> 38000 | G31: 38000 | H31: =IF((G31-G30)<0,"0",(G31-G30)) -> 0 | I31: =J30 -> 8046 | J31: 8047 | K31: =IF((J31-J30)<0,"0",(J31-J30)) -> 1 | L31: =M30 -> 12755 | M31: 12765 | N31: =IF((M31-M30)<0,"0",(M31-M30)) -> 10 | O31: =P30 -> 20303 | P31: 20307 | Q31: =IF((P31-P30)<0,"0",(P31-P30)) -> 4 | S31: =T30 -> 59368 | T31: 59434 | U31: =IF((T31-T30)<0,"0",(T31-T30)) -> 66 | V31: =W30 -> 73030 | W31: 73030 | X31: =IF((W31-W30)<0,"0",(W31-W30)) -> 0 | Y31: =Z30 -> 83889 | Z31: 83924 | AA31: =IF((Z31-Z30)<0,"0",(Z31-Z30)) -> 35 | AB31: =AC30 -> 15574 | AC31: 15593 | AD31: =IF((AC31-AC30)<0,"0",(AC31-AC30)) -> 19 | AE31: =AF30 -> 18300 | AF31: 18300 | AG31: =IF((AF31-AF30)<0,"0",(AF31-AF30)) -> 0 | AH31: =AI30 -> 25885 | AI31: 25906 | AJ31: =IF((AI31-AI30)<0,"0",(AI31-AI30)) -> 21 | AK31: =AL30 -> 0 | AM31: =IF((AL31-AL30)<0,"0",(AL31-AL30)) -> 0 | AN31: =U31+X31+AA31+AD31+AG31+AJ31+AM31 -> 141
A32: =Gen!B37 -> 44101 | B32: 10/27//2009 | C32: =D31 -> 241317 | D32: 241375 | E32: =IF((D32-D31)<0,"0",(D32-D31)) -> 58 | F32: =G31 -> 38000 | G32: 38000 | H32: =IF((G32-G31)<0,"0",(G32-G31)) -> 0 | I32: =J31 -> 8047 | J32: 8048 | K32: =IF((J32-J31)<0,"0",(J32-J31)) -> 1 | L32: =M31 -> 12765 | M32: 12765 | N32: =IF((M32-M31)<0,"0",(M32-M31)) -> 0 | O32: =P31 -> 20307 | P32: 20310 | Q32: =IF((P32-P31)<0,"0",(P32-P31)) -> 3 | S32: =T31 -> 59434 | T32: 59501 | U32: =IF((T32-T31)<0,"0",(T32-T31)) -> 67 | V32: =W31 -> 73030 | W32: 73030 | X32: =IF((W32-W31)<0,"0",(W32-W31)) -> 0 | Y32: =Z31 -> 83924 | Z32: 83960 | AA32: =IF((Z32-Z31)<0,"0",(Z32-Z31)) -> 36 | AB32: =AC31 -> 15593 | AC32: 15611 | AD32: =IF((AC32-AC31)<0,"0",(AC32-AC31)) -> 18 | AE32: =AF31 -> 18300 | AF32: 18300 | AG32: =IF((AF32-AF31)<0,"0",(AF32-AF31)) -> 0 | AH32: =AI31 -> 25906 | AI32: 25928 | AJ32: =IF((AI32-AI31)<0,"0",(AI32-AI31)) -> 22 | AK32: =AL31 -> 0 | AM32: =IF((AL32-AL31)<0,"0",(AL32-AL31)) -> 0 | AN32: =U32+X32+AA32+AD32+AG32+AJ32+AM32 -> 143
A33: =Gen!B38 -> 44102 | C33: =D32 -> 241375 | D33: 241427 | E33: =IF((D33-D32)<0,"0",(D33-D32)) -> 52 | F33: =G32 -> 38000 | G33: 38000 | H33: =IF((G33-G32)<0,"0",(G33-G32)) -> 0 | I33: =J32 -> 8048 | J33: 8048 | K33: =IF((J33-J32)<0,"0",(J33-J32)) -> 0 | L33: =M32 -> 12765 | M33: 12765 | N33: =IF((M33-M32)<0,"0",(M33-M32)) -> 0 | O33: =P32 -> 20310 | P33: 20312 | Q33: =IF((P33-P32)<0,"0",(P33-P32)) -> 2 | S33: =T32 -> 59501 | T33: 59531 | U33: =IF((T33-T32)<0,"0",(T33-T32)) -> 30 | V33: =W32 -> 73030 | W33: 73030 | X33: =IF((W33-W32)<0,"0",(W33-W32)) -> 0 | Y33: =Z32 -> 83960 | Z33: 83995 | AA33: =IF((Z33-Z32)<0,"0",(Z33-Z32)) -> 35 | AB33: =AC32 -> 15611 | AC33: 15630 | AD33: =IF((AC33-AC32)<0,"0",(AC33-AC32)) -> 19 | AE33: =AF32 -> 18300 | AF33: 18300 | AG33: =IF((AF33-AF32)<0,"0",(AF33-AF32)) -> 0 | AH33: =AI32 -> 25928 | AI33: 25950 | AJ33: =IF((AI33-AI32)<0,"0",(AI33-AI32)) -> 22 | AK33: =AL32 -> 0 | AM33: =IF((AL33-AL32)<0,"0",(AL33-AL32)) -> 0 | AN33: =U33+X33+AA33+AD33+AG33+AJ33+AM33 -> 106
A34: =Gen!B39 -> 44103 | C34: =D33 -> 241427 | E34: =IF((D34-D33)<0,"0",(D34-D33)) -> 0 | F34: =G33 -> 38000 | H34: =IF((G34-G33)<0,"0",(G34-G33)) -> 0 | I34: =J33 -> 8048 | K34: =IF((J34-J33)<0,"0",(J34-J33)) -> 0 | L34: =M33 -> 12765 | N34: =IF((M34-M33)<0,"0",(M34-M33)) -> 0 | O34: =P33 -> 20312 | Q34: =IF((P34-P33)<0,"0",(P34-P33)) -> 0 | S34: =T33 -> 59531 | U34: =IF((T34-T33)<0,"0",(T34-T33)) -> 0 | V34: =W33 -> 73030 | X34: =IF((W34-W33)<0,"0",(W34-W33)) -> 0 | Y34: =Z33 -> 83995 | AA34: =IF((Z34-Z33)<0,"0",(Z34-Z33)) -> 0 | AB34: =AC33 -> 15630 | AD34: =IF((AC34-AC33)<0,"0",(AC34-AC33)) -> 0 | AE34: =AF33 -> 18300 | AG34: =IF((AF34-AF33)<0,"0",(AF34-AF33)) -> 0 | AH34: =AI33 -> 25950 | AJ34: =IF((AI34-AI33)<0,"0",(AI34-AI33)) -> 0 | AK34: =AL33 -> 0 | AM34: =IF((AL34-AL33)<0,"0",(AL34-AL33)) -> 0 | AN34: =U34+X34+AA34+AD34+AG34+AJ34+AM34 -> 0
A35: =Gen!B40 -> 44104 | C35: =D34 -> 0 | E35: =IF((D35-D34)<0,"0",(D35-D34)) -> 0 | F35: =G34 -> 0 | H35: =IF((G35-G34)<0,"0",(G35-G34)) -> 0 | I35: =J34 -> 0 | K35: =IF((J35-J34)<0,"0",(J35-J34)) -> 0 | L35: =M34 -> 0 | N35: =IF((M35-M34)<0,"0",(M35-M34)) -> 0 | O35: =P34 -> 0 | Q35: =IF((P35-P34)<0,"0",(P35-P34)) -> 0 | S35: =T34 -> 0 | U35: =IF((T35-T34)<0,"0",(T35-T34)) -> 0 | V35: =W34 -> 0 | X35: =IF((W35-W34)<0,"0",(W35-W34)) -> 0 | Y35: =Z34 -> 0 | AA35: =IF((Z35-Z34)<0,"0",(Z35-Z34)) -> 0 | AB35: =AC34 -> 0 | AD35: =IF((AC35-AC34)<0,"0",(AC35-AC34)) -> 0 | AE35: =AF34 -> 0 | AG35: =IF((AF35-AF34)<0,"0",(AF35-AF34)) -> 0 | AH35: =AI34 -> 0 | AJ35: =IF((AI35-AI34)<0,"0",(AI35-AI34)) -> 0 | AK35: =AL34 -> 0 | AM35: =IF((AL35-AL34)<0,"0",(AL35-AL34)) -> 0 | AN35: =U35+X35+AA35+AD35+AG35+AJ35+AM35 -> 0
A36: =Gen!B41 -> 0 | C36: =D35 -> 0 | E36: =IF((D36-D35)<0,"0",(D36-D35)) -> 0 | F36: =G35 -> 0 | H36: =IF((G36-G35)<0,"0",(G36-G35)) -> 0 | I36: =J35 -> 0 | K36: =IF((J36-J35)<0,"0",(J36-J35)) -> 0 | L36: =M35 -> 0 | N36: =IF((M36-M35)<0,"0",(M36-M35)) -> 0 | O36: =P35 -> 0 | Q36: =IF((P36-P35)<0,"0",(P36-P35)) -> 0 | S36: =T35 -> 0 | U36: =IF((T36-T35)<0,"0",(T36-T35)) -> 0 | V36: =W35 -> 0 | X36: =IF((W36-W35)<0,"0",(W36-W35)) -> 0 | Y36: =Z35 -> 0 | AA36: =IF((Z36-Z35)<0,"0",(Z36-Z35)) -> 0 | AB36: =AC35 -> 0 | AD36: =IF((AC36-AC35)<0,"0",(AC36-AC35)) -> 0 | AE36: =AF35 -> 0 | AG36: =IF((AF36-AF35)<0,"0",(AF36-AF35)) -> 0 | AH36: =AI35 -> 0 | AJ36: =IF((AI36-AI35)<0,"0",(AI36-AI35)) -> 0 | AK36: =AL35 -> 0 | AM36: =IF((AL36-AL35)<0,"0",(AL36-AL35)) -> 0 | AN36: =U36+X36+AA36+AD36+AG36+AJ36+AM36 -> 0
A37: =Gen!B42 -> 0 | C37: =D36 -> 0 | E37: =IF((D37-D36)<0,"0",(D37-D36)) -> 0 | F37: =G36 -> 0 | H37: =IF((G37-G36)<0,"0",(G37-G36)) -> 0 | I37: =J36 -> 0 | K37: =IF((J37-J36)<0,"0",(J37-J36)) -> 0 | L37: =M36 -> 0 | N37: =IF((M37-M36)<0,"0",(M37-M36)) -> 0 | O37: =P36 -> 0 | Q37: =IF((P37-P36)<0,"0",(P37-P36)) -> 0 | S37: =T36 -> 0 | U37: =IF((T37-T36)<0,"0",(T37-T36)) -> 0 | V37: =W36 -> 0 | X37: =IF((W37-W36)<0,"0",(W37-W36)) -> 0 | Y37: =Z36 -> 0 | AA37: =IF((Z37-Z36)<0,"0",(Z37-Z36)) -> 0 | AB37: =AC36 -> 0 | AD37: =IF((AC37-AC36)<0,"0",(AC37-AC36)) -> 0 | AE37: =AF36 -> 0 | AG37: =IF((AF37-AF36)<0,"0",(AF37-AF36)) -> 0 | AH37: =AI36 -> 0 | AJ37: =IF((AI37-AI36)<0,"0",(AI37-AI36)) -> 0 | AK37: =AL36 -> 0 | AM37: =IF((AL37-AL36)<0,"0",(AL37-AL36)) -> 0 | AN37: =U38+X38+AA38+AD38+AG38+AJ38+AM38 -> 1350
C38: TOTAL USAGE | E38: =SUM(E6:E36) -> 1454 | F38: KL | H38: =SUM(H6:H37) -> 0 | K38: =SUM(K6:K37) -> 27 | N38: =M38-M37 -> 0 | Q38: =P38-O38 -> 0 | R38: =E38 -> 1454 | U38: =SUM(U6:U37) -> 1350 | AJ38: =IF((AI39-AI37)<0,"0",(AI39-AI37)) -> 0 | AN38: =U38+X38+AA38+AD38+AG38+AJ38+AM38 -> 1350
C42: WATER TANK LEVEL
C43: RAW WATER TANK NO.1 | E43: RAW WATER TANK NO.2 | G43: TREATED WATER TANK | I43: TREATED -HILL TANK | K43: TOTAL WATER AVAILABLE
C44: CAPACITY 217 m³ | E44: CAPACITY 92 m³ | G44: CAPACITY 146 m³ | I44: CAPACITY 213 m³
C45: cm | D45: m³ | E45: cm | F45: m³ | H45: m³ | I45: cm | J45: m³ | K45: m³
A46: =Gen!B11 -> 44075 | C46: 285 | D46: =C46*217/300 -> 206.15 | E46: 215 | F46: =E46*92/305 -> 64.852459 | G46: 205 | H46: =G46*146/383 -> 78.146214 | I46: 298 | J46: =I46*213/308 -> 206.08442 | K46: =D46+F46+H46+J46 -> 555.23309
A47: =Gen!B12 -> 44076 | C47: 245 | D47: =C47*217/300 -> 177.21667 | E47: 200 | F47: =E47*92/305 -> 60.327869 | G47: 300 | H47: =G47*146/383 -> 114.36031 | I47: 298 | J47: =I47*213/308 -> 206.08442 | K47: =D47+F47+H47+J47 -> 557.98926
A48: =Gen!B13 -> 44077 | C48: 300 | D48: =C48*217/300 -> 217 | E48: 295 | F48: =E48*92/305 -> 88.983607 | G48: 185 | H48: =G48*146/383 -> 70.522193 | I48: 308 | J48: =I48*213/308 -> 213 | K48: =D48+F48+H48+J48 -> 589.5058
A49: =Gen!B14 -> 44078 | C49: 295 | D49: =C49*217/300 -> 213.38333 | E49: 260 | F49: =E49*92/305 -> 78.42623 | G49: 280 | H49: =G49*146/383 -> 106.73629 | I49: 298 | J49: =I49*213/308 -> 206.08442 | K49: =D49+F49+H49+J49 -> 604.63027
A50: =Gen!B15 -> 44079 | C50: 280 | D50: =C50*217/300 -> 202.53333 | E50: 255 | F50: =E50*92/305 -> 76.918033 | G50: 300 | H50: =G50*146/383 -> 114.36031 | I50: 298 | J50: =I50*213/308 -> 206.08442 | K50: =D50+F50+H50+J50 -> 599.8961
A51: =Gen!B16 -> 44080 | C51: 300 | D51: =C51*217/300 -> 217 | E51: 235 | F51: =E51*92/305 -> 70.885246 | G51: 195 | H51: =G51*146/383 -> 74.334204 | I51: 298 | J51: =I51*213/308 -> 206.08442 | K51: =D51+F51+H51+J51 -> 568.30387
A52: =Gen!B17 -> 44081 | C52: 285 | D52: =C52*217/300 -> 206.15 | E52: 240 | F52: =E52*92/305 -> 72.393443 | G52: 250 | H52: =G52*146/383 -> 95.300261 | I52: 298 | J52: =I52*213/308 -> 206.08442 | K52: =D52+F52+H52+J52 -> 579.92812
A53: =Gen!B18 -> 44082 | C53: 295 | D53: =C53*217/300 -> 213.38333 | E53: 285 | F53: =E53*92/305 -> 85.967213 | G53: 215 | H53: =G53*146/383 -> 81.958225 | I53: 298 | J53: =I53*213/308 -> 206.08442 | K53: =D53+F53+H53+J53 -> 587.39319
A54: =Gen!B19 -> 44083 | C54: 275 | D54: =C54*217/300 -> 198.91667 | E54: 230 | F54: =E54*92/305 -> 69.377049 | G54: 255 | H54: =G54*146/383 -> 97.206266 | I54: 298 | J54: =I54*213/308 -> 206.08442 | K54: =D54+F54+H54+J54 -> 571.5844
A55: =Gen!B20 -> 44084 | C55: 250 | D55: =C55*217/300 -> 180.83333 | E55: 215 | F55: =E55*92/305 -> 64.852459 | G55: 210 | H55: =G55*146/383 -> 80.052219 | I55: 298 | J55: =I55*213/308 -> 206.08442 | K55: =D55+F55+H55+J55 -> 531.82243
A56: =Gen!B21 -> 44085 | C56: 175 | D56: =C56*217/300 -> 126.58333 | E56: 135 | F56: =E56*92/305 -> 40.721311 | G56: 300 | H56: =G56*146/383 -> 114.36031 | I56: 298 | J56: =I56*213/308 -> 206.08442 | K56: =D56+F56+H56+J56 -> 487.74937
A57: =Gen!B22 -> 44086 | C57: 250 | D57: =C57*217/300 -> 180.83333 | E57: 215 | F57: =E57*92/305 -> 64.852459 | G57: 200 | H57: =G57*146/383 -> 76.240209 | I57: 298 | J57: =I57*213/308 -> 206.08442 | K57: =D57+F57+H57+J57 -> 528.01042
... A74: =Gen!B39 -> 44103 | C74: 285 | D74: =C74*217/300 -> 206.15 | E74: 245 | F74: =E74*92/305 -> 73.901639 | G74: 250 | H74: =G74*146/383 -> 95.300261 | I74: 295 | J74: =I74*213/308 -> 204.00974 | K74: =D74+F74+H74+J74 -> 579.36164
A75: =Gen!B40 -> 44104 | D75: =C75*217/300 -> 0 | F75: =E75*92/305 -> 0 | H75: =G75*146/383 -> 0 | J75: =I75*213/308 -> 0 | K75: =D75+F75+H75+J75 -> 0
A76: =Gen!B41 -> 0 | D76: =C76*217/300 -> 0 | F76: =E76*92/305 -> 0 | H76: =G76*146/383 -> 0 | J76: =I76*213/308 -> 0 | K76: =D76+F76+H76+J76 -> 0
A77: =Gen!B42 -> 0 | D77: =C77*217/300 -> 0 | F77: =E77*92/305 -> 0 | H77: =G77*146/383 -> 0 | J77: =I77*213/308 -> 0 | K77: =D77+F77+H77+J77 -> 0
A78: =Gen!B43 -> BF

Sheet Water_Graph 
A1: Date | B1: Usage | C1: Occ %
A2: =Gen!B11 -> 44075 | B2: =SUM('[1]Water-Meter'!R10) -> #REF! | C2: =SUM([1]Gen!B11) -> 0.623
A3: =Gen!B12 -> 44076 | B3: =SUM('[1]Water-Meter'!R11) -> #REF! | C3: =SUM([1]Gen!B12) -> 0.779
A4: =Gen!B13 -> 44077 | B4: =SUM('[1]Water-Meter'!R12) -> #REF! | C4: =SUM([1]Gen!B13) -> 0.532
A5: =Gen!B14 -> 44078 | B5: =SUM('[1]Water-Meter'!R13) -> #REF! | C5: =SUM([1]Gen!B14) -> 0.61
A6: =Gen!B15 -> 44079 | B6: =SUM('[1]Water-Meter'!R14) -> #REF! | C6: =SUM([1]Gen!B15) -> 0.688
A7: =Gen!B16 -> 44080 | B7: =SUM('[1]Water-Meter'!R15) -> #REF! | C7: =SUM([1]Gen!B16) -> 0.532
A8: =Gen!B17 -> 44081 | B8: =SUM('[1]Water-Meter'!R16) -> #REF! | C8: =SUM([1]Gen!B17) -> 0.753
A9: =Gen!B18 -> 44082 | B9: =SUM('[1]Water-Meter'!R17) -> #REF! | C9: =SUM([1]Gen!B18) -> 0.156
A10: =Gen!B19 -> 44083 | B10: =SUM('[1]Water-Meter'!R18) -> #REF! | C10: =SUM([1]Gen!B19) -> 0.442
A11: =Gen!B20 -> 44084 | B11: =SUM('[1]Water-Meter'!R19) -> #REF! | C11: =SUM([1]Gen!B20) -> 0.325
A12: =Gen!B21 -> 44085 | B12: =SUM('[1]Water-Meter'!R20) -> #REF! | C12: =SUM([1]Gen!B21) -> 0.455
A13: =Gen!B22 -> 44086 | B13: =SUM('[1]Water-Meter'!R21) -> #REF! | C13: =SUM([1]Gen!B22) -> 0.416
... A32: =Gen!B41 -> 0 | B32: =SUM('[1]Water-Meter'!R40) -> #REF! | C32: =SUM([1]Gen!B41) -> #REF!

Sheet Sheet1
A2: Generator and Diseal Summry Report | Q2: 2209.85 | R2: Diesel Cost | S2: Rate$ | T2: 1584
M3: % of Gas balance in Tank | P3: % of Dieasel balance in Tank | Q3: HLP Cost (TSH) | V3: Total Cost (TSH) | W3: Consumption Guest Occ% | AA3: Budget Cost Per Room occ
A4: Date | B4: Gen Set Hours Working | C4: Occ% | D4: Total OCC Room | E4: Guest Room Occ | F4: Total Kwh Generated | G4: Diseal consumed by Gen (Ltrs) | H4: Diseal consumed by Veichel (Ltrs) | I4: Total diseal consumed (Ltrs) | J4: Balance stock of Diseal (Ltrs) | K4: Water consumed | L4: Gas consumed (KG) | M4: 3 | N4: 2 | O4: 1 | Q4: Electricity | R4: Cost per Room Total OOC Usd | S4: Cost per Room Guest OOC Usd | T4: Water | U4: Gas
A5: =Gen!B11 -> 44075 | B5: 0 | C5: =Gen!C11 -> 0.039 | D5: =SUM(77*C5) -> 3.003 | F5: =Gen!U11 -> 2111 | G5: =Gen!T11 -> 891.43 | H5: =[1]Gen!#REF! -> #REF! | I5: =SUM(G5:H5) -> #REF! | J5: =[1]Gen!AT11 -> 47806.65 | K5: ='Water-Meter'!E6 -> 56 | L5: ='Lpg (2)'!G10 -> 76.032 | M5: =#REF! -> #REF! | N5: =#REF! -> #REF! | O5: =#REF! -> #REF! | P5: =J5/52000 -> 0.91935865 | Q5: =I5*Q2 -> #REF! | R5: =SUM(Q5/D5)/X5 -> #REF! | S5: =SUM(Q5/E5)/X5 -> #REF! | T5: =(K5*102)/X5 -> 3.6060606 | U5: =SUM(L5*1963)/X5 -> 94.224 | V5: =SUM(Q5+T5+U5) -> #REF! | W5: =SUM(V5/E5)/T2 -> #REF! | X5: =SUM(T2) -> 1584 | Y5: 106 | Z5: =SUM(Y5-S5) -> #REF! | AA5: 106
A6: =Gen!B12 -> 44076 | B6: 0 | C6: =Gen!C12 -> 0.039 | D6: =SUM(77*C6) -> 3.003 | F6: =Gen!U12 -> 2147 | G6: =Gen!T12 -> 821.92 | H6: =[1]Gen!#REF! -> #REF! | I6: =SUM(G6:H6) -> #REF! | J6: =[1]Gen!AT12 -> 45423.89 | K6: ='Water-Meter'!E7 -> 58 | L6: ='Lpg (2)'!G11 -> 58.608 | M6: =#REF! -> #REF! | N6: =#REF! -> #REF! | O6: =#REF! -> #REF! | P6: =J6/52000 -> 0.87353635 | Q6: =I6*Q2 -> #REF! | R6: =SUM(Q6/D6)/X6 -> #REF! | S6: =SUM(Q6/E6)/X6 -> #REF! | T6: =(K6*102)/X6 -> 3.7348485 | U6: =SUM(L6*1963)/X6 -> 72.631 | V6: =SUM(Q6+T6+U6) -> #REF! | W6: =SUM(V6/E6)/T2 -> #REF! | X6: =SUM(X5) -> 1584 | Y6: 106 | Z6: =SUM(Y6-S6) -> #REF!
A7: =Gen!B13 -> 44077 | B7: 0 | C7: =Gen!C13 -> 0.039 | D7: =SUM(77*C7) -> 3.003 | F7: =Gen!U13 -> 2188 | G7: =Gen!T13 -> 1090.28 | H7: =[1]Gen!#REF! -> #REF! | I7: =SUM(G7:H7) -> #REF! | J7: =[1]Gen!AT13 -> 42919.59 | K7: ='Water-Meter'!E8 -> 51 | L7: ='Lpg (2)'!G12 -> 66.264 | M7: =#REF! -> #REF! | N7: =#REF! -> #REF! | O7: =#REF! -> #REF! | P7: =J7/52000 -> 0.82537673 | Q7: =I7*Q2 -> #REF! | R7: =SUM(Q7/D7)/X7 -> #REF! | S7: =SUM(Q7/E7)/X7 -> #REF! | T7: =(K7*102)/X7 -> 3.2840909 | U7: =SUM(L7*1963)/X7 -> 82.118833 | V7: =SUM(Q7+T7+U7) -> #REF! | W7: =SUM(V7/E7)/T2 -> #REF! | X7: =SUM(X6) -> 1584 | Y7: 106 | Z7: =SUM(Y7-S7) -> #REF!
A8: =Gen!B14 -> 44078 | B8: 0 | C8: =Gen!C14 -> 0.0909 | D8: =SUM(77*C8) -> 6.9993 | F8: =Gen!U14 -> 2448 | G8: =Gen!T14 -> 868.39 | H8: =[1]Gen!AJ9 -> #REF! | I8: =SUM(G8:H8) -> #REF! | J8: =[1]Gen!AT14 -> 40258.94 | K8: ='Water-Meter'!E9 -> 54 | L8: ='Lpg (2)'!G13 -> 63.536 | M8: =#REF! -> #REF! | N8: =#REF! -> #REF! | O8: =#REF! -> #REF! | P8: =J8/52000 -> 0.77421038 | Q8: =I8*Q2 -> #REF! | R8: =SUM(Q8/D8)/X8 -> #REF! | S8: =SUM(Q8/E8)/X8 -> #REF! | T8: =(K8*102)/X8 -> 3.4772727 | U8: =SUM(L8*1963)/X8 -> 78.738111 | V8: =SUM(Q8+T8+U8) -> #REF! | W8: =SUM(V8/E8)/T2 -> #REF! | X8: =SUM(X7) -> 1584 | Y8: 106 | Z8: =SUM(Y8-S8) -> #REF!
A9: =Gen!B15 -> 44079 | B9: 0 | C9: =Gen!C15 -> 0.0909 | D9: =SUM(77*C9) -> 6.9993 | F9: =Gen!U15 -> 2152 | G9: =Gen!T15 -> 841.98 | H9: =[1]Gen!AJ10 -> 0 | I9: =SUM(G9:H9) -> 841.98 | J9: =[1]Gen!AT15 -> 37525.21 | K9: ='Water-Meter'!E10 -> 50 | L9: ='Lpg (2)'!G14 -> 50.072 | M9: =#REF! -> #REF! | N9: =#REF! -> #REF! | O9: =#REF! -> #REF! | P9: =J9/52000 -> 0.72163865 | Q9: =I9*Q2 -> 1860649.5 | R9: =SUM(Q9/D9)/X9 -> 167.82428 | S9: =SUM(Q9/E9)/X9 -> #DIV/0! | T9: =(K9*102)/X9 -> 3.219697 | U9: =SUM(L9*1963)/X9 -> 62.052611 | V9: =SUM(Q9+T9+U9) -> 1860714.8 | W9: =SUM(V9/E9)/T2 -> #DIV/0! | X9: =SUM(X8) -> 1584 | Y9: 106 | Z9: =SUM(Y9-S9) -> #DIV/0!
A10: =Gen!B16 -> 44080 | B10: 0 | C10: =Gen!C16 -> 0.0909 | D10: =SUM(77*C10) -> 6.9993 | F10: =Gen!U16 -> 2052 | G10: =Gen!T16 -> 938.54 | H10: =[1]Gen!#REF! -> #REF! | I10: =SUM(G10:H10) -> #REF! | J10: =[1]Gen!AT16 -> 35107.69 | K10: ='Water-Meter'!E11 -> 52 | L10: ='Lpg (2)'!G15 -> 49.588 | M10: =#REF! -> #REF! | N10: =#REF! -> #REF! | O10: =#REF! -> #REF! | P10: =J10/52000 -> 0.67514788 | Q10: =I10*Q2 -> #REF! | R10: =SUM(Q10/D10)/X10 -> #REF! | S10: =SUM(Q10/E10)/X10 -> #REF! | T10: =(K10*102)/X10 -> 3.3484848 | U10: =SUM(L10*1963)/X10 -> 61.452806 | V10: =SUM(Q10+T10+U10) -> #REF! | W10: =SUM(V10/E10)/T2 -> #REF! | X10: =SUM(X9) -> 1584 | Y10: 106 | Z10: =SUM(Y10-S10) -> #REF!
A11: =Gen!B17 -> 44081 | B11: 0 | C11: =Gen!C17 -> 0.026 | D11: =SUM(77*C11) -> 2.002 | F11: =Gen!U17 -> 2010 | G11: =Gen!T17 -> 910.27 | H11: =[1]Gen!AJ25 -> 80.56 | I11: =SUM(G11:H11) -> 990.83 | J11: =[1]Gen!AT17 -> 47513.14 | K11: ='Water-Meter'!E12 -> 58 | L11: ='Lpg (2)'!G16 -> 62.568 | M11: =#REF! -> #REF! | N11: =#REF! -> #REF! | O11: =#REF! -> #REF! | P11: =J11/52000 -> 0.91371423 | Q11: =I11*Q2 -> 2189585.7 | R11: =SUM(Q11/D11)/X11 -> 690.46663 | S11: =SUM(Q11/E11)/X11 -> #DIV/0! | T11: =(K11*102)/X11 -> 3.7348485 | U11: =SUM(L11*1963)/X11 -> 77.5385 | V11: =SUM(Q11+T11+U11) -> 2189666.9 | W11: =SUM(V11/E11)/T2 -> #DIV/0! | X11: =SUM(X10) -> 1584 | Y11: 106 | Z11: =SUM(Y11-S11) -> #DIV/0!
A12: =Gen!B18 -> 44082 | B12: 0 | C12: =Gen!C18 -> 0.039 | D12: =SUM(77*C12) -> 3.003 | F12: =Gen!U18 -> 2245 | G12: =Gen!T18 -> 948.21 | H12: =[1]Gen!#REF! -> #REF! | I12: =SUM(G12:H12) -> #REF! | J12: =[1]Gen!AT18 -> 45161.89 | K12: ='Water-Meter'!E13 -> 46 | L12: ='Lpg (2)'!G17 -> 54.868 | M12: =#REF! -> #REF! | N12: =#REF! -> #REF! | O12: =#REF! -> #REF! | P12: =J12/52000 -> 0.86849788 | Q12: =I12*Q2 -> #REF! | R12: =SUM(Q12/D12)/X12 -> #REF! | S12: =SUM(Q12/E12)/X12 -> #REF! | T12: =(K12*102)/X12 -> 2.9621212 | U12: =SUM(L12*1963)/X12 -> 67.996139 | V12: =SUM(Q12+T12+U12) -> #REF! | W12: =SUM(V12/E12)/T2 -> #REF! | X12: =SUM(X11) -> 1584 | Y12: 106 | Z12: =SUM(Y12-S12) -> #REF!
A13: =Gen!B19 -> 44083 | B13: 0 | C13: =Gen!C19 -> 0.065 | D13: =SUM(77*C13) -> 5.005 | F13: =Gen!U19 -> 2101 | G13: =Gen!T19 -> 916.33 | H13: =[1]Gen!#REF! -> #REF! | I13: =SUM(G13:H13) -> #REF! | J13: =[1]Gen!AT19 -> 42825.48 | K13: ='Water-Meter'!E14 -> 52 | L13: ='Lpg (2)'!G18 -> 57.42 | M13: =#REF! -> #REF! | N13: =#REF! -> #REF! | O13: =#REF! -> #REF! | P13: =J13/52000 -> 0.82356692 | Q13: =I13*Q2 -> #REF! | R13: =SUM(Q13/D13)/X13 -> #REF! | S13: =SUM(Q13/E13)/X13 -> #REF! | T13: =(K13*102)/X13 -> 3.3484848 | U13: =SUM(L13*1963)/X13 -> 71.15875 | V13: =SUM(Q13+T13+U13) -> #REF! | W13: =SUM(V13/E13)/T2 -> #REF! | X13: =SUM(X12) -> 1584 | Y13: 106 | Z13: =SUM(Y13-S13) -> #REF!
A14: =Gen!B20 -> 44084 | B14: 0 | C14: =Gen!C20 -> 0.013 | D14: =SUM(77*C14) -> 1.001 | F14: =Gen!U20 -> 2199 | G14: =Gen!T20 -> 978.04 | H14: =[1]Gen!#REF! -> #REF! | I14: =SUM(G14:H14) -> #REF! | J14: =[1]Gen!AT20 -> 40110.38 | K14: ='Water-Meter'!E15 -> 55 | L14: ='Lpg (2)'!G19 -> 44 | M14: =#REF! -> #REF! | N14: =#REF! -> #REF! | O14: =#REF! -> #REF! | P14: =J14/52000 -> 0.77135346 | Q14: =I14*Q2 -> #REF! | R14: =SUM(Q14/D14)/X14 -> #REF! | S14: =SUM(Q14/E14)/X14 -> #REF! | T14: =(K14*102)/X14 -> 3.5416667 | U14: =SUM(L14*1963)/X14 -> 54.527778 | V14: =SUM(Q14+T14+U14) -> #REF! | W14: =SUM(V14/E14)/T2 -> #REF! | X14: =SUM(X13) -> 1584 | Y14: 106 | Z14: =SUM(Y14-S14) -> #REF!
A15: =Gen!B21 -> 44085 | B15: 0 | C15: =Gen!C21 -> 0.039 | D15: =SUM(77*C15) -> 3.003 | F15: =Gen!U21 -> 2126 | G15: =Gen!T21 -> 782.55 | H15: =[1]Gen!#REF! -> #REF! | I15: =SUM(G15:H15) -> #REF! | J15: =[1]Gen!AT21 -> 37540.57 | K15: ='Water-Meter'!E16 -> 94 | L15: ='Lpg (2)'!G20 -> 70.928 | M15: =#REF! -> #REF! | N15: =#REF! -> #REF! | O15: =#REF! -> #REF! | P15: =J15/52000 -> 0.72193404 | Q15: =I15*Q2 -> #REF! | R15: =SUM(Q15/D15)/X15 -> #REF! | S15: =SUM(Q15/E15)/X15 -> #REF! | T15: =(K15*102)/X15 -> 6.0530303 | U15: =SUM(L15*1963)/X15 -> 87.898778 | V15: =SUM(Q15+T15+U15) -> #REF! | W15: =SUM(V15/E15)/T2 -> #REF! | X15: =SUM(X14) -> 1584 | Y15: 106 | Z15: =SUM(Y15-S15) -> #REF!
A16: =Gen!B22 -> 44086 | B16: 0 | C16: =Gen!C22 -> 0.02 | D16: =SUM(77*C16) -> 1.54 | F16: =Gen!U22 -> 2174 | G16: =Gen!T22 -> 732.78 | H16: =[1]Gen!#REF! -> #REF! | I16: =SUM(G16:H16) -> #REF! | J16: =[1]Gen!AT22 -> 34967.29 | K16: ='Water-Meter'!E17 -> 59 | L16: ='Lpg (2)'!G21 -> 53.9 | M16: =#REF! -> #REF! | N16: =#REF! -> #REF! | O16: =#REF! -> #REF! | P16: =J16/52000 -> 0.67244788 | Q16: =I16*Q2 -> #REF! | R16: =SUM(Q16/D16)/X16 -> #REF! | S16: =SUM(Q16/E16)/X16 -> #REF! | T16: =(K16*102)/X16 -> 3.7992424 | U16: =SUM(L16*1963)/X16 -> 66.796528 | V16: =SUM(Q16+T16+U16) -> #REF! | W16: =SUM(V16/E16)/T2 -> #REF! | X16: =SUM(X15) -> 1584 | Y16: 106 | Z16: =SUM(Y16-S16) -> #REF!
A17: =Gen!B23 -> 44087 | B17: 0 | C17: =Gen!C23 -> 0.03 | D17: =SUM(77*C17) -> 2.31 | F17: =Gen!U23 -> 2113 | G17: =Gen!T23 -> 935.74 | H17: =[1]Gen!#REF! -> #REF! | I17: =SUM(G17:H17) -> #REF! | J17: =[1]Gen!AT23 -> 32228.76 | K17: ='Water-Meter'!E18 -> 36 | L17: ='Lpg (2)'!G22 -> 55.396 | M17: =#REF! -> #REF! | N17: =#REF! -> #REF! | O17: =#REF! -> #REF! | P17: =J17/52000 -> 0.61978385 | Q17: =I17*Q2 -> #REF! | R17: =SUM(Q17/D17)/X17 -> #REF! | S17: =SUM(Q17/E17)/X17 -> #REF! | T17: =(K17*102)/X17 -> 2.3181818 | U17: =SUM(L17*1963)/X17 -> 68.650472 | V17: =SUM(Q17+T17+U17) -> #REF! | W17: =SUM(V17/E17)/T2 -> #REF! | X17: =SUM(X16) -> 1584 | Y17: 106 | Z17: =SUM(Y17-S17) -> #REF!
A18: =Gen!B24 -> 44088 | B18: 0 | C18: =Gen!C24 -> 0.04 | D18: =SUM(77*C18) -> 3.08 | F18: =Gen!U24 -> 2040 | G18: =Gen!T24 -> 890.09 | H18: =[1]Gen!AJ27 -> 597.9 | I18: =SUM(G18:H18) -> 1487.99 | J18: =[1]Gen!AT24 -> 29915.45 | K18: ='Water-Meter'!E19 -> 53 | L18: ='Lpg (2)'!G23 -> 56.452 | M18: =#REF! -> #REF! | N18: =#REF! -> #REF! | O18: =#REF! -> #REF! | P18: =J18/52000 -> 0.57529712 | Q18: =I18*Q2 -> 3288234.7 | R18: =SUM(Q18/D18)/X18 -> 673.99537 | S18: =SUM(Q18/E18)/X18 -> #DIV/0! | T18: =(K18*102)/X18 -> 3.4128788 | U18: =SUM(L18*1963)/X18 -> 69.959139 | V18: =SUM(Q18+T18+U18) -> 3288308.1 | W18: =SUM(V18/E18)/T2 -> #DIV/0! | X18: =SUM(X17) -> 1584 | Y18: 106 | Z18: =SUM(Y18-S18) -> #DIV/0!
A19: =Gen!B25 -> 44089 | B19: 0 | C19: =Gen!C25 -> 0.03 | D19: =SUM(77*C19) -> 2.31 | F19: =Gen!U25 -> 2084 | G19: =Gen!T25 -> 888.98 | H19: =[1]Gen!AJ28 -> 227.73 | I19: =SUM(G19:H19) -> 1116.71 | J19: =[1]Gen!AT25 -> 42248.24 | K19: ='Water-Meter'!E20 -> 40 | L19: ='Lpg (2)'!G24 -> 52.052 | M19: =#REF! -> #REF! | N19: =#REF! -> #REF! | O19: =#REF! -> #REF! | P19: =J19/52000 -> 0.81246615 | Q19: =I19*Q2 -> 2467761.6 | R19: =SUM(Q19/D19)/X19 -> 674.4287 | S19: =SUM(Q19/E19)/X19 -> #DIV/0! | T19: =(K19*102)/X19 -> 2.5757576 | U19: =SUM(L19*1963)/X19 -> 64.506361 | V19: =SUM(Q19+T19+U19) -> 2467828.7 | W19: =SUM(V19/E19)/T2 -> #DIV/0! | X19: =SUM(X18) -> 1584 | Y19: 106 | Z19: =SUM(Y19-S19) -> #DIV/0!
A20: =Gen!B26 -> 44090 | B20: 0 | C20: =Gen!C26 -> 0.1299 | D20: =SUM(77*C20) -> 10.0023 | F20: =Gen!U26 -> 2489 | G20: =Gen!T26 -> 1095.46 | H20: =[1]Gen!AJ29 -> 88.29 | I20: =SUM(G20:H20) -> 1183.75 | J20: =[1]Gen!AT26 -> 39497.37 | K20: ='Water-Meter'!E21 -> 30 | L20: ='Lpg (2)'!G25 -> 49.192 | M20: =#REF! -> #REF! | N20: =#REF! -> #REF! | O20: =#REF! -> #REF! | P20: =J20/52000 -> 0.75956481 | Q20: =I20*Q2 -> 2615909.9 | R20: =SUM(Q20/D20)/X20 -> 165.10785 | S20: =SUM(Q20/E20)/X20 -> #DIV/0! | T20: =(K20*102)/X20 -> 1.9318182 | U20: =SUM(L20*1963)/X20 -> 60.962056 | V20: =SUM(Q20+T20+U20) -> 2615972.8 | W20: =SUM(V20/E20)/T2 -> #DIV/0! | X20: =SUM(X19) -> 1584 | Y20: 106 | Z20: =SUM(Y20-S20) -> #DIV/0!
A21: =Gen!B27 -> 44091 | B21: 0 | C21: =Gen!C27 -> 0.1169 | D21: =SUM(77*C21) -> 9.0013 | F21: =Gen!U27 -> 2499 | G21: =Gen!T27 -> 1018.07 | H21: =[1]Gen!AJ30 -> 783.92 | I21: =SUM(G21:H21) -> 1801.99 | J21: =[1]Gen!AT27 -> 36688.35 | K21: ='Water-Meter'!E22 -> 49 | L21: ='Lpg (2)'!G26 -> 55.088 | M21: =#REF! -> #REF! | N21: =#REF! -> #REF! | O21: =#REF! -> #REF! | P21: =J21/52000 -> 0.70554519 | Q21: =I21*Q2 -> 3982127.6 | R21: =SUM(Q21/D21)/X21 -> 279.2896 | S21: =SUM(Q21/E21)/X21 -> #DIV/0! | T21: =(K21*102)/X21 -> 3.155303 | U21: =SUM(L21*1963)/X21 -> 68.268778 | V21: =SUM(Q21+T21+U21) -> 3982199 | W21: =SUM(V21/E21)/T2 -> #DIV/0! | X21: =SUM(X20) -> 1584 | Y21: 106 | Z21: =SUM(Y21-S21) -> #DIV/0!
A22: =Gen!B28 -> 44092 | B22: 0 | C22: =Gen!C28 -> 0.1429 | D22: =SUM(77*C22) -> 11.0033 | F22: =Gen!U28 -> 2622 | G22: =Gen!T28 -> 1041.27 | H22: =[1]Gen!#REF! -> #REF! | I22: =SUM(G22:H22) -> #REF! | J22: =[1]Gen!AT28 -> 33769.34 | K22: ='Water-Meter'!E23 -> 50 | L22: ='Lpg (2)'!G27 -> 65.34 | M22: =#REF! -> #REF! | N22: =#REF! -> #REF! | O22: =#REF! -> #REF! | P22: =J22/52000 -> 0.64941038 | Q22: =I22*Q2 -> #REF! | R22: =SUM(Q22/D22)/X22 -> #REF! | S22: =SUM(Q22/E22)/X22 -> #REF! | T22: =(K22*102)/X22 -> 3.219697 | U22: =SUM(L22*1963)/X22 -> 80.97375 | V22: =SUM(Q22+T22+U22) -> #REF! | W22: =SUM(V22/E22)/T2 -> #REF! | X22: =SUM(X21) -> 1584 | Y22: 106 | Z22: =SUM(Y22-S22) -> #REF!
A23: =Gen!B29 -> 44093 | B23: 0 | C23: =Gen!C29 -> 0.0909 | D23: =SUM(77*C23) -> 6.9993 | F23: =Gen!U29 -> 2500 | G23: =Gen!T29 -> 1129.88 | H23: =[1]Gen!#REF! -> #REF! | I23: =SUM(G23:H23) -> #REF! | J23: =[1]Gen!AT29 -> 31336.77 | K23: ='Water-Meter'!E24 -> 51 | L23: ='Lpg (2)'!G28 -> 65.428 | M23: =#REF! -> #REF! | N23: =#REF! -> #REF! | O23: =#REF! -> #REF! | P23: =J23/52000 -> 0.60263019 | Q23: =I23*Q2 -> #REF! | R23: =SUM(Q23/D23)/X23 -> #REF! | S23: =SUM(Q23/E23)/X23 -> #REF! | T23: =(K23*102)/X23 -> 3.2840909 | U23: =SUM(L23*1963)/X23 -> 81.082806 | V23: =SUM(Q23+T23+U23) -> #REF! | W23: =SUM(V23/E23)/T2 -> #REF! | X23: =SUM(X22) -> 1584 | Y23: 106 | Z23: =SUM(Y23-S23) -> #REF!
A24: =Gen!B30 -> 44094 | B24: 0 | C24: =Gen!C30 -> 0.0649 | D24: =SUM(77*C24) -> 4.9973 | F24: =Gen!U30 -> 2313 | G24: =Gen!T30 -> 1055.66 | H24: =[1]Gen!#REF! -> #REF! | I24: =SUM(G24:H24) -> #REF! | J24: =[1]Gen!AT30 -> 29403.3 | K24: ='Water-Meter'!E25 -> 46 | L24: ='Lpg (2)'!G29 -> 69.828 | M24: =#REF! -> #REF! | N24: =#REF! -> #REF! | O24: =#REF! -> #REF! | P24: =J24/52000 -> 0.56544808 | Q24: =I24*Q2 -> #REF! | R24: =SUM(Q24/D24)/X24 -> #REF! | S24: =SUM(Q24/E24)/X24 -> #REF! | T24: =(K24*102)/X24 -> 2.9621212 | U24: =SUM(L24*1963)/X24 -> 86.535583 | V24: =SUM(Q24+T24+U24) -> #REF! | W24: =SUM(V24/E24)/T2 -> #REF! | X24: =SUM(X23) -> 1584 | Y24: 106 | Z24: =SUM(Y24-S24) -> #REF!
A25: =Gen!B31 -> 44095 | B25: 0 | C25: =Gen!C31 -> 0.0649 | D25: =SUM(77*C25) -> 4.9973 | F25: =Gen!U31 -> 2356 | G25: =Gen!T31 -> 957.7 | H25: =[1]Gen!AJ31 -> 172.05 | I25: =SUM(G25:H25) -> 1129.75 | J25: =[1]Gen!AT31 -> 41422.37 | K25: ='Water-Meter'!E26 -> 46 | L25: ='Lpg (2)'!G30 -> 75.68 | M25: =#REF! -> #REF! | N25: =#REF! -> #REF! | O25: =#REF! -> #REF! | P25: =J25/52000 -> 0.79658404 | Q25: =I25*Q2 -> 2496578 | R25: =SUM(Q25/D25)/X25 -> 315.39481 | S25: =SUM(Q25/E25)/X25 -> #DIV/0! | T25: =(K25*102)/X25 -> 2.9621212 | U25: =SUM(L25*1963)/X25 -> 93.787778 | V25: =SUM(Q25+T25+U25) -> 2496674.8 | W25: =SUM(V25/E25)/T2 -> #DIV/0! | X25: =SUM(X24) -> 1584 | Y25: 106 | Z25: =SUM(Y25-S25) -> #DIV/0!
A26: =Gen!B32 -> 44096 | B26: 0 | C26: =Gen!C32 -> 0.026 | D26: =SUM(77*C26) -> 2.002 | F26: =Gen!U32 -> 2289 | G26: =Gen!T32 -> 982.5 | H26: =[1]Gen!AJ32 -> 18.63 | I26: =SUM(G26:H26) -> 1001.13 | J26: =[1]Gen!AT32 -> 38988.16 | K26: ='Water-Meter'!E27 -> 56 | L26: ='Lpg (2)'!G31 -> 55.748 | M26: =#REF! -> #REF! | N26: =#REF! -> #REF! | O26: =#REF! -> #REF! | P26: =J26/52000 -> 0.74977231 | Q26: =I26*Q2 -> 2212347.1 | R26: =SUM(Q26/D26)/X26 -> 697.64425 | S26: =SUM(Q26/E26)/X26 -> #DIV/0! | T26: =(K26*102)/X26 -> 3.6060606 | U26: =SUM(L26*1963)/X26 -> 69.086694 | V26: =SUM(Q26+T26+U26) -> 2212419.8 | W26: =SUM(V26/E26)/T2 -> #DIV/0! | X26: =SUM(X25) -> 1584 | Y26: 106 | Z26: =SUM(Y26-S26) -> #DIV/0!
A27: =Gen!B33 -> 44097 | B27: 0 | C27: =Gen!C33 -> 0.026 | D27: =SUM(77*C27) -> 2.002 | F27: =Gen!U33 -> 2286 | G27: =Gen!T33 -> 989.79 | H27: =[1]Gen!AJ33 -> 311.34 | I27: =SUM(G27:H27) -> 1301.13 | J27: =[1]Gen!AT33 -> 36682.67 | K27: ='Water-Meter'!E28 -> 49 | L27: ='Lpg (2)'!G32 -> 39.204 | M27: =#REF! -> #REF! | N27: =#REF! -> #REF! | O27: =#REF! -> #REF! | P27: =J27/52000 -> 0.70543596 | Q27: =I27*Q2 -> 2875302.1 | R27: =SUM(Q27/D27)/X27 -> 906.70129 | S27: =SUM(Q27/E27)/X27 -> #DIV/0! | T27: =(K27*102)/X27 -> 3.155303 | U27: =SUM(L27*1963)/X27 -> 48.58425 | V27: =SUM(Q27+T27+U27) -> 2875353.9 | W27: =SUM(V27/E27)/T2 -> #DIV/0! | X27: =SUM(X26) -> 1584 | Y27: 106 | Z27: =SUM(Y27-S27) -> #DIV/0!
A28: =Gen!B34 -> 44098 | B28: 0 | C28: =Gen!C34 -> 0.013 | D28: =SUM(77*C28) -> 1.001 | F28: =Gen!U34 -> 2289 | G28: =Gen!T34 -> 1004.25 | H28: =[1]Gen!AJ34 -> 380.7 | I28: =SUM(G28:H28) -> 1384.95 | J28: =[1]Gen!AT34 -> 44223.03 | K28: ='Water-Meter'!E29 -> 48 | L28: ='Lpg (2)'!G33 -> 72.6 | M28: =#REF! -> #REF! | N28: =#REF! -> #REF! | O28: =#REF! -> #REF! | P28: =J28/52000 -> 0.85044288 | Q28: =I28*Q2 -> 3060531.8 | R28: =SUM(Q28/D28)/X28 -> 1930.2237 | S28: =SUM(Q28/E28)/X28 -> #DIV/0! | T28: =(K28*102)/X28 -> 3.0909091 | U28: =SUM(L28*1963)/X28 -> 89.970833 | V28: =SUM(Q28+T28+U28) -> 3060624.8 | W28: =SUM(V28/E28)/T2 -> #DIV/0! | X28: =SUM(X27) -> 1584 | Y28: 106 | Z28: =SUM(Y28-S28) -> #DIV/0!
A29: =Gen!B35 -> 44099 | B29: 0 | C29: =Gen!C35 -> 0.013 | D29: =SUM(77*C29) -> 1.001 | F29: =Gen!U35 -> 2244 | G29: =Gen!T35 -> 1019.08 | H29: =[1]Gen!AJ35 -> 273.37 | I29: =SUM(G29:H29) -> 1292.45 | J29: =[1]Gen!AT35 -> 41629.06 | K29: ='Water-Meter'!E30 -> 50 | L29: ='Lpg (2)'!G34 -> 63.272 | M29: =#REF! -> #REF! | N29: =#REF! -> #REF! | O29: =#REF! -> #REF! | P29: =J29/52000 -> 0.80055885 | Q29: =I29*Q2 -> 2856120.6 | R29: =SUM(Q29/D29)/X29 -> 1801.3052 | S29: =SUM(Q29/E29)/X29 -> #DIV/0! | T29: =(K29*102)/X29 -> 3.219697 | U29: =SUM(L29*1963)/X29 -> 78.410944 | V29: =SUM(Q29+T29+U29) -> 2856202.3 | W29: =SUM(V29/E29)/T2 -> #DIV/0! | X29: =SUM(X28) -> 1584 | Y29: 106 | Z29: =SUM(Y29-S29) -> #DIV/0!
A30: =Gen!B36 -> 44100 | B30: 0 | C30: =Gen!C36 -> 0.026 | D30: =SUM(77*C30) -> 2.002 | F30: =Gen!U36 -> 2313 | G30: =Gen!T36 -> 878.8 | H30: =[1]Gen!AJ36 -> 396.56 | I30: =SUM(G30:H30) -> 1275.36 | J30: =[1]Gen!AT36 -> 39251.17 | K30: ='Water-Meter'!E31 -> 55 | L30: ='Lpg (2)'!G35 -> 63.668 | M30: =#REF! -> #REF! | N30: =#REF! -> #REF! | O30: =#REF! -> #REF! | P30: =J30/52000 -> 0.75483019 | Q30: =I30*Q2 -> 2818354.3 | R30: =SUM(Q30/D30)/X30 -> 888.74329 | S30: =SUM(Q30/E30)/X30 -> #DIV/0! | T30: =(K30*102)/X30 -> 3.5416667 | U30: =SUM(L30*1963)/X30 -> 78.901694 | V30: =SUM(Q30+T30+U30) -> 2818436.7 | W30: =SUM(V30/E30)/T2 -> #DIV/0! | X30: =SUM(X29) -> 1584 | Y30: 106 | Z30: =SUM(Y30-S30) -> #DIV/0!
A31: =Gen!B37 -> 44101 | B31: 0 | C31: =Gen!C37 -> 0.0519 | D31: =SUM(77*C31) -> 3.9963 | F31: =Gen!U37 -> 2327 | G31: =Gen!T37 -> 975.74 | H31: =[1]Gen!AJ37 -> 280.63 | I31: =SUM(G31:H31) -> 1256.37 | J31: =[1]Gen!AT37 -> 36384.37 | K31: ='Water-Meter'!E32 -> 58 | L31: ='Lpg (2)'!G36 -> 54.692 | M31: =#REF! -> #REF! | N31: =#REF! -> #REF! | O31: =#REF! -> #REF! | P31: =J31/52000 -> 0.69969942 | Q31: =I31*Q2 -> 2776389.2 | R31: =SUM(Q31/D31)/X31 -> 438.59845 | S31: =SUM(Q31/E31)/X31 -> #DIV/0! | T31: =(K31*102)/X31 -> 3.7348485 | U31: =SUM(L31*1963)/X31 -> 67.778028 | V31: =SUM(Q31+T31+U31) -> 2776460.8 | W31: =SUM(V31/E31)/T2 -> #DIV/0! | X31: =SUM(X30) -> 1584 | Y31: 106 | Z31: =SUM(Y31-S31) -> #DIV/0!
A32: =Gen!B38 -> 44102 | B32: 0 | C32: =Gen!C38 -> 0.0519 | D32: =SUM(77*C32) -> 3.9963 | F32: =Gen!U38 -> 2289 | G32: =Gen!T38 -> 969.39 | H32: =[1]Gen!AJ38 -> 0 | I32: =SUM(G32:H32) -> 969.39 | J32: =[1]Gen!AT38 -> 33780 | K32: ='Water-Meter'!E33 -> 52 | L32: ='Lpg (2)'!G37 -> 75.68 | M32: =#REF! -> #REF! | N32: =#REF! -> #REF! | O32: =#REF! -> #REF! | P32: =J32/52000 -> 0.64961538 | Q32: =I32*Q2 -> 2142206.5 | R32: =SUM(Q32/D32)/X32 -> 338.4138 | S32: =SUM(Q32/E32)/X32 -> #DIV/0! | T32: =(K32*102)/X32 -> 3.3484848 | U32: =SUM(L32*1963)/X32 -> 93.787778 | V32: =SUM(Q32+T32+U32) -> 2142303.6 | W32: =SUM(V32/E32)/T2 -> #DIV/0! | X32: =SUM(X31) -> 1584 | Y32: 106 | Z32: =SUM(Y32-S32) -> #DIV/0!
