Workbook

Sheet Total
A1: Site Name | B1: Day | C1: Month | D1: Year | E1: Total Electricity Kwh | F1: Electricity Tariff ($/Kwh) | G1: Total Fuel Oil (Liters) | H1: Fuel Oil $/Liter | I1: LPG (Kg) | J1: LPG $/Kg | K1: Water Utility Supply (m3) m3 | L1: Water Utility Supply (m3) $/m3 | M1: Irrigation Water (m3) m3 | N1: Irrigation water $/m3 | O1: Room Nights
A2: Beirut | B2: 1 | C2: 9 | D2: 2020 | E2: =ELEC!N3 -> 11078 | F2: =SUM('EDl log'!T4) -> 0.083178659 | G2: =-tanks!AW6 -> 155 | H2: =SUM(tanks!AV6) -> 0.53 | I2: =('B5'!AU5)*0.51 -> 0 | J2: ='B5'!AX5/0.51 -> 1.5686275 | K2: =WATER!I6 -> 0 | L2: =SUM(WATER!J6) -> 0 | M2: =WATER!Q6 -> 0 | N2: 0.6 | O2: =ELEC!B3 -> 0
A3: Beirut | B3: =B2+1 -> 2 | C3: 9 | D3: 2020 | E3: =ELEC!N4 -> 12266 | F3: =SUM('EDl log'!T5) -> 0.10639618 | G3: =-tanks!AW7 -> 0 | H3: =SUM(tanks!AV7) -> 0.53 | I3: =('B5'!AU6)*0.51 -> 0 | J3: ='B5'!AX6/0.51 -> 1.5686275 | K3: =WATER!I7 -> 0 | L3: =SUM(WATER!J7) -> 0 | M3: =WATER!Q7 -> 0 | N3: 0.6 | O3: =ELEC!B4 -> 0
A4: Beirut | B4: =B3+1 -> 3 | C4: 9 | D4: 2020 | E4: =ELEC!N5 -> 12559 | F4: =SUM('EDl log'!T6) -> 0.096652465 | G4: =-tanks!AW8 -> 350 | H4: =SUM(tanks!AV8) -> 0.53 | I4: =('B5'!AU7)*0.51 -> 0 | J4: ='B5'!AX7/0.51 -> 1.5686275 | K4: =WATER!I8 -> 0 | L4: =SUM(WATER!J8) -> 0 | M4: =WATER!Q8 -> 0 | N4: 0.6 | O4: =ELEC!B5 -> 0
A5: Beirut | B5: =B4+1 -> 4 | C5: 9 | D5: 2020 | E5: =ELEC!N6 -> 12925 | F5: =SUM('EDl log'!T7) -> 0.11097463 | G5: =-tanks!AW9 -> 303 | H5: =SUM(tanks!AV9) -> 0.53 | I5: =('B5'!AU8)*0.51 -> 0 | J5: ='B5'!AX8/0.51 -> 1.5686275 | K5: =WATER!I9 -> 0 | L5: =SUM(WATER!J9) -> 0 | M5: =WATER!Q9 -> 0 | N5: 0.6 | O5: =ELEC!B6 -> 0
A6: Beirut | B6: =B5+1 -> 5 | C6: 9 | D6: 2020 | E6: =ELEC!N7 -> 10761 | F6: =SUM('EDl log'!T8) -> 0.087390022 | G6: =-tanks!AW10 -> 0 | H6: =SUM(tanks!AV10) -> 0.53 | I6: =('B5'!AU9)*0.51 -> 0 | J6: ='B5'!AX9/0.51 -> 1.5686275 | K6: =WATER!I10 -> 0 | L6: =SUM(WATER!J10) -> 0 | M6: =WATER!Q10 -> 0 | N6: 0.6 | O6: =ELEC!B7 -> 0
A7: Beirut | B7: =B6+1 -> 6 | C7: 9 | D7: 2020 | E7: =ELEC!N8 -> 10340 | F7: =SUM('EDl log'!T9) -> 0.11498091 | G7: =-tanks!AW11 -> 0 | H7: =SUM(tanks!AV11) -> 0.53 | I7: =('B5'!AU10)*0.51 -> 0 | J7: ='B5'!AX10/0.51 -> 1.5686275 | K7: =WATER!I11 -> 118 | L7: =SUM(WATER!J11) -> 2.1186441 | M7: =WATER!Q11 -> 0 | N7: 0.6 | O7: =ELEC!B8 -> 0
A8: Beirut | B8: =B7+1 -> 7 | C8: 9 | D8: 2020 | E8: =ELEC!N9 -> 12789 | F8: =SUM('EDl log'!T10) -> 0.092334781 | G8: =-tanks!AW12 -> 0 | H8: =SUM(tanks!AV12) -> 0.53 | I8: =('B5'!AU11)*0.51 -> 0 | J8: ='B5'!AX11/0.51 -> 1.5686275 | K8: =WATER!I12 -> 0 | L8: =SUM(WATER!J12) -> 0 | M8: =WATER!Q12 -> 0 | N8: 0.6 | O8: =ELEC!B9 -> 0
A9: Beirut | B9: =B8+1 -> 8 | C9: 9 | D9: 2020 | E9: =ELEC!N10 -> 12367 | F9: =SUM('EDl log'!T11) -> 0.15042934 | G9: =-tanks!AW13 -> 0 | H9: =SUM(tanks!AV13) -> 0.53 | I9: =('B5'!AU12)*0.51 -> 0 | J9: ='B5'!AX12/0.51 -> 1.5686275 | K9: =WATER!I13 -> 0 | L9: =SUM(WATER!J13) -> 0 | M9: =WATER!Q13 -> 0 | N9: 0.6 | O9: =ELEC!B10 -> 0
A10: Beirut | B10: =B9+1 -> 9 | C10: 9 | D10: 2020 | E10: =ELEC!N11 -> 11724 | F10: =SUM('EDl log'!T12) -> 0.091466843 | G10: =-tanks!AW14 -> 0 | H10: =SUM(tanks!AV14) -> 0.53 | I10: =('B5'!AU13)*0.51 -> 183.6 | J10: ='B5'!AX13/0.51 -> 1.5686275 | K10: =WATER!I14 -> 0 | L10: =SUM(WATER!J14) -> 0 | M10: =WATER!Q14 -> 0 | N10: 0.6 | O10: =ELEC!B11 -> 0
A11: Beirut | B11: =B10+1 -> 10 | C11: 9 | D11: 2020 | E11: =ELEC!N12 -> 11004 | F11: =SUM('EDl log'!T13) -> 0.025994703 | G11: =-tanks!AW15 -> 0 | H11: =SUM(tanks!AV15) -> 0.54 | I11: =('B5'!AU14)*0.51 -> 0 | J11: ='B5'!AX14/0.51 -> 1.5686275 | K11: =WATER!I15 -> 0 | L11: =SUM(WATER!J15) -> 0 | M11: =WATER!Q15 -> 0 | N11: 0.6 | O11: =ELEC!B12 -> 0
A12: Beirut | B12: =B11+1 -> 11 | C12: 9 | D12: 2020 | E12: =ELEC!N13 -> 11016 | F12: =SUM('EDl log'!T14) -> 0.1003431 | G12: =-tanks!AW16 -> 0 | H12: =SUM(tanks!AV16) -> 0.54 | I12: =('B5'!AU15)*0.51 -> 0 | J12: ='B5'!AX15/0.51 -> 1.5686275 | K12: =WATER!I16 -> 0 | L12: =SUM(WATER!J16) -> 0 | M12: =WATER!Q16 -> 0 | N12: 0.6 | O12: =ELEC!B13 -> 0
A13: Beirut | B13: =B12+1 -> 12 | C13: 9 | D13: 2020 | E13: =ELEC!N14 -> 10368 | F13: =SUM('EDl log'!T15) -> 0.10096417 | G13: =-tanks!AW17 -> 0 | H13: =SUM(tanks!AV17) -> 0.54 | I13: =('B5'!AU16)*0.51 -> 0 | J13: ='B5'!AX16/0.51 -> 1.5686275 | K13: =WATER!I17 -> 0 | L13: =SUM(WATER!J17) -> 0 | M13: =WATER!Q17 -> 0 | N13: 0.6 | O13: =ELEC!B14 -> 0
A14: Beirut | B14: =B13+1 -> 13 | C14: 9 | D14: 2020 | E14: =ELEC!N15 -> 9041 | F14: =SUM('EDl log'!T16) -> 0.10004211 | G14: =-tanks!AW18 -> 0 | H14: =SUM(tanks!AV18) -> 0.54 | I14: =('B5'!AU17)*0.51 -> 45.9 | J14: ='B5'!AX17/0.51 -> 1.5686275 | K14: =WATER!I18 -> 0 | L14: =SUM(WATER!J18) -> 0 | M14: =WATER!Q18 -> 0 | N14: 0.6 | O14: =ELEC!B15 -> 0
... A31: Beirut | B31: =B30+1 -> 30 | C31: 9 | D31: 2020 | E31: =ELEC!N32 -> 11854 | F31: =SUM('EDl log'!T33) -> 0.10054052 | G31: =-tanks!AW35 -> 0 | H31: =SUM(tanks!AV35) -> 0.503 | I31: =('B5'!AU34)*0.51 -> 0 | J31: ='B5'!AX34/0.51 -> 1.5686275 | K31: =WATER!I35 -> 0 | L31: =SUM(WATER!J35) -> 0 | M31: =WATER!Q35 -> 0 | N31: 0.6 | O31: =ELEC!B32 -> 0

Sheet Submetering
A1: Site Name | B1: Day | C1: Month | D1: Year | E1: ATS1 Kwh | F1: ATS2 Kwh | G1: ATS3 Kwh | H1: ATS4 Kwh | I1: ATS5 Kwh | J1: Guest (m3) | K1: Kitchen & Laundry (m3) | L1: Room Nights
A2: Beirut | B2: 1 | C2: 9 | D2: 2020 | E2: =ELEC!M3 -> 3970 | F2: =ELEC!K3 -> 1156 | G2: =ELEC!I3 -> 1266 | H2: =ELEC!E3 -> 3758 | I2: =ELEC!G3 -> 928 | J2: =WATER!Y6 -> 80 | K2: =WATER!AJ6 -> 0 | L2: =ELEC!B3 -> 0
A3: Beirut | B3: =B2+1 -> 2 | C3: 9 | D3: 2020 | E3: =ELEC!M4 -> 5398 | F3: =ELEC!K4 -> 1040 | G3: =ELEC!I4 -> 1444 | H3: =ELEC!E4 -> 3418 | I3: =ELEC!G4 -> 966 | J3: =WATER!Y7 -> 58 | K3: =WATER!AJ7 -> 0 | L3: =ELEC!B4 -> 0
A4: Beirut | B4: =B3+1 -> 3 | C4: 9 | D4: 2020 | E4: =ELEC!M5 -> 3032 | F4: =ELEC!K5 -> 1114 | G4: =ELEC!I5 -> 1442 | H4: =ELEC!E5 -> 6014 | I4: =ELEC!G5 -> 957 | J4: =WATER!Y8 -> 0 | K4: =WATER!AJ8 -> 0 | L4: =ELEC!B5 -> 0
A5: Beirut | B5: =B4+1 -> 4 | C5: 9 | D5: 2020 | E5: =ELEC!M6 -> 2028 | F5: =ELEC!K6 -> 1124 | G5: =ELEC!I6 -> 1464 | H5: =ELEC!E6 -> 7308 | I5: =ELEC!G6 -> 1001 | J5: =WATER!Y9 -> 0 | K5: =WATER!AJ9 -> 66 | L5: =ELEC!B6 -> 0
A6: Beirut | B6: =B5+1 -> 5 | C6: 9 | D6: 2020 | E6: =ELEC!M7 -> 1700 | F6: =ELEC!K7 -> 898 | G6: =ELEC!I7 -> 1242 | H6: =ELEC!E7 -> 5960 | I6: =ELEC!G7 -> 961 | J6: =WATER!Y10 -> 0 | K6: =WATER!AJ10 -> 0 | L6: =ELEC!B7 -> 0
A7: Beirut | B7: =B6+1 -> 6 | C7: 9 | D7: 2020 | E7: =ELEC!M8 -> 1910 | F7: =ELEC!K8 -> 832 | G7: =ELEC!I8 -> 1282 | H7: =ELEC!E8 -> 5292 | I7: =ELEC!G8 -> 1024 | J7: =WATER!Y11 -> 0 | K7: =WATER!AJ11 -> 0 | L7: =ELEC!B8 -> 0
A8: Beirut | B8: =B7+1 -> 7 | C8: 9 | D8: 2020 | E8: =ELEC!M9 -> 4920 | F8: =ELEC!K9 -> 1196 | G8: =ELEC!I9 -> 1052 | H8: =ELEC!E9 -> 4710 | I8: =ELEC!G9 -> 911 | J8: =WATER!Y12 -> 0 | K8: =WATER!AJ12 -> 0 | L8: =ELEC!B9 -> 0
A9: Beirut | B9: =B8+1 -> 8 | C9: 9 | D9: 2020 | E9: =ELEC!M10 -> 4974 | F9: =ELEC!K10 -> 1196 | G9: =ELEC!I10 -> 900 | H9: =ELEC!E10 -> 4468 | I9: =ELEC!G10 -> 829 | J9: =WATER!Y13 -> 0 | K9: =WATER!AJ13 -> 0 | L9: =ELEC!B10 -> 0
A10: Beirut | B10: =B9+1 -> 9 | C10: 9 | D10: 2020 | E10: =ELEC!M11 -> 5108 | F10: =ELEC!K11 -> 1016 | G10: =ELEC!I11 -> 1040 | H10: =ELEC!E11 -> 3700 | I10: =ELEC!G11 -> 860 | J10: =WATER!Y14 -> 0 | K10: =WATER!AJ14 -> 0 | L10: =ELEC!B11 -> 0
A11: Beirut | B11: =B10+1 -> 10 | C11: 9 | D11: 2020 | E11: =ELEC!M12 -> 4768 | F11: =ELEC!K12 -> 960 | G11: =ELEC!I12 -> 956 | H11: =ELEC!E12 -> 3524 | I11: =ELEC!G12 -> 796 | J11: =WATER!Y15 -> 0 | K11: =WATER!AJ15 -> 0 | L11: =ELEC!B12 -> 0
A12: Beirut | B12: =B11+1 -> 11 | C12: 9 | D12: 2020 | E12: =ELEC!M13 -> 4722 | F12: =ELEC!K13 -> 1006 | G12: =ELEC!I13 -> 986 | H12: =ELEC!E13 -> 3482 | I12: =ELEC!G13 -> 820 | J12: =WATER!Y16 -> 0 | K12: =WATER!AJ16 -> 0 | L12: =ELEC!B13 -> 0
A13: Beirut | B13: =B12+1 -> 12 | C13: 9 | D13: 2020 | E13: =ELEC!M14 -> 4550 | F13: =ELEC!K14 -> 976 | G13: =ELEC!I14 -> 1002 | H13: =ELEC!E14 -> 2998 | I13: =ELEC!G14 -> 842 | J13: =WATER!Y17 -> 0 | K13: =WATER!AJ17 -> 32 | L13: =ELEC!B14 -> 0
A14: Beirut | B14: =B13+1 -> 13 | C14: 9 | D14: 2020 | E14: =ELEC!M15 -> 3956 | F14: =ELEC!K15 -> 786 | G14: =ELEC!I15 -> 972 | H14: =ELEC!E15 -> 2520 | I14: =ELEC!G15 -> 807 | J14: =WATER!Y18 -> 0 | K14: =WATER!AJ18 -> 0 | L14: =ELEC!B15 -> 0
... A31: Beirut | B31: =B30+1 -> 30 | C31: 9 | D31: 2020 | E31: =ELEC!M32 -> 5496 | F31: =ELEC!K32 -> 1056 | G31: =ELEC!I32 -> 940 | H31: =ELEC!E32 -> 3568 | I31: =ELEC!G32 -> 794 | J31: =WATER!Y35 -> 60 | K31: =WATER!AJ35 -> 23 | L31: =ELEC!B32 -> 0

Sheet ELEC
A1: OOC | B1: Room OCC | D1: MDB3 | E1: MDB3/day | F1: EMDB2 | G1: EMDB2/day | H1: EMDB1 | I1: EMDB1/day | J1: MDB2 | K1: mdb2/day | L1: MDB1 | M1: MDB1/Day | N1: Total KWH | O1: KWH/Rooc | P1: Gen MHW | Q1: Gen/Day KWH | R1: EDL KWH | S1: CH1 RH | T1: RH | U1: C1h1 power | V1: CH1 Con KWH | W1: CH2 RH | X1: RH | Y1: Ch2 power | Z1: CH2 Con KWH | AA1: CH3 RH | AB1: RH | AC1: Ch3 power | AD1: CH3 Con KWH | AE1: RH total | AF1: KWH total | AG1: AVG chiller KW/Hr
A2: =[1]ELEC!$A$33 -> 0 | B2: =[1]ELEC!$B$33 -> 0 | C2: 44074 | D2: =[1]ELEC!D33 -> 32168402 | E2: =[1]ELEC!E33 -> 2944 | F2: =[1]ELEC!F33 -> 3846115 | G2: =[1]ELEC!G33 -> 1023 | H2: =[1]ELEC!H33 -> 17640934 | I2: =[1]ELEC!I33 -> 1218 | J2: =[1]ELEC!J33 -> 28692174 | K2: =[1]ELEC!K33 -> 880 | ... AL2: =[1]ELEC!AL33 -> 0
A3: ='General information '!F6 -> 0 | B3: =SUM(230*A3) -> 0 | C3: 44075 | D3: 32172160 | E3: =D3-D2 -> 3758 | F3: 3847043 | G3: =F3-F2 -> 928 | H3: 17642200 | I3: =H3-H2 -> 1266 | J3: 28693330 | K3: =J3-J2 -> 1156 | L3: 23581616 | M3: =L3-L2 -> 3970 | N3: =M3+K3+I3+G3+E3 -> 11078 | O3: =IF(B3>0,N3/B3,0) -> 0 | P3: 16264 | Q3: =(P3-P2)*1000 -> 1000 | R3: =+N3-Q3 -> 10078 | S3: 9498 | T3: =S3-S2 -> 9 | U3: 285005 | V3: =U3-U2 -> 2005 | W3: 32049 | X3: =W3-W2 -> 0 | Y3: 673052 | Z3: =Y3-Y2 -> 0 | AA3: 35503 | AB3: =AA3-AA2 -> 2 | AC3: 876365 | AD3: =AC3-AC2 -> 468 | AE3: =AB3+X3+T3 -> 11 | AF3: =V3+Z3+AD3 -> 2473 | AG3: =IF(AE3>0,AF3/AE3,0) -> 224.81818
A4: ='General information '!F7 -> 0 | B4: =SUM(230*A4) -> 0 | C4: 44076 | D4: 32175578 | E4: =D4-D3 -> 3418 | F4: 3848009 | G4: =F4-F3 -> 966 | H4: 17643644 | I4: =H4-H3 -> 1444 | J4: 28694370 | K4: =J4-J3 -> 1040 | L4: 23587014 | M4: =L4-L3 -> 5398 | N4: =M4+K4+I4+G4+E4 -> 12266 | O4: =IF(B4>0,N4/B4,0) -> 0 | P4: 16269 | Q4: =(P4-P3)*1000 -> 5000 | R4: =N4-Q4 -> 7266 | S4: 9511 | T4: =S4-S3 -> 13 | U4: 288090 | V4: =U4-U3 -> 3085 | W4: =W3 -> 32049 | X4: =W4-W3 -> 0 | Y4: =Y3 -> 673052 | Z4: =Y4-Y3 -> 0 | AA4: =AA3 -> 35503 | AB4: =AA4-AA3 -> 0 | AC4: =AC3 -> 876365 | AD4: =AC4-AC3 -> 0 | AE4: =AB4+X4+T4 -> 13 | AF4: =V4+Z4+AD4 -> 3085 | AG4: =IF(AE4>0,AF4/AE4,0) -> 237.30769
A5: ='General information '!F8 -> 0 | B5: =SUM(230*A5) -> 0 | C5: 44077 | D5: 32181592 | E5: =D5-D4 -> 6014 | F5: 3848966 | G5: =F5-F4 -> 957 | H5: 17645086 | I5: =H5-H4 -> 1442 | J5: 28695484 | K5: =J5-J4 -> 1114 | L5: 23590046 | M5: =L5-L4 -> 3032 | N5: =M5+K5+I5+G5+E5 -> 12559 | O5: =IF(B5>0,N5/B5,0) -> 0 | P5: 16274 | Q5: =(P5-P4)*1000 -> 5000 | R5: =N5-Q5 -> 7559 | S5: 9517 | T5: =S5-S4 -> 6 | U5: 289529 | V5: =U5-U4 -> 1439 | W5: 32049 | X5: =W5-W4 -> 0 | Y5: =Y4 -> 673052 | Z5: =Y5-Y4 -> 0 | AA5: 35512 | AB5: =AA5-AA4 -> 9 | AC5: 878376 | AD5: =AC5-AC4 -> 2011 | AE5: =AB5+X5+T5 -> 15 | AF5: =V5+Z5+AD5 -> 3450 | AG5: =IF(AE5>0,AF5/AE5,0) -> 230 | AI5: =R5-'EDl log'!B3 -> -341719
A6: ='General information '!F9 -> 0 | B6: =SUM(230*A6) -> 0 | C6: 44078 | D6: 32188900 | E6: =D6-D5 -> 7308 | F6: 3849967 | G6: =F6-F5 -> 1001 | H6: 17646550 | I6: =H6-H5 -> 1464 | J6: 28696608 | K6: =J6-J5 -> 1124 | L6: 23592074 | M6: =L6-L5 -> 2028 | N6: =M6+K6+I6+G6+E6 -> 12925 | O6: =IF(B6>0,N6/B6,0) -> 0 | P6: 16279 | Q6: =(P6-P5)*1000 -> 5000 | R6: =N6-Q6 -> 7925 | S6: =S5 -> 9517 | T6: =S6-S5 -> 0 | U6: =U5 -> 289529 | V6: =U6-U5 -> 0 | W6: =W5 -> 32049 | X6: =W6-W5 -> 0 | Y6: =Y5 -> 673052 | Z6: =Y6-Y5 -> 0 | AA6: 35528 | AB6: =AA6-AA5 -> 16 | AC6: 881970 | AD6: =AC6-AC5 -> 3594 | AE6: =AB6+X6+T6 -> 16 | AF6: =V6+Z6+AD6 -> 3594 | AG6: =IF(AE6>0,AF6/AE6,0) -> 224.625 | AI6: =R6-'EDl log'!B4 -> -346172
A7: ='General information '!F10 -> 0 | B7: =SUM(230*A7) -> 0 | C7: 44079 | D7: 32194860 | E7: =D7-D6 -> 5960 | F7: 3850928 | G7: =F7-F6 -> 961 | H7: 17647792 | I7: =H7-H6 -> 1242 | J7: 28697506 | K7: =J7-J6 -> 898 | L7: 23593774 | M7: =L7-L6 -> 1700 | N7: =M7+K7+I7+G7+E7 -> 10761 | O7: =IF(B7>0,N7/B7,0) -> 0 | P7: 16281 | Q7: =(P7-P6)*1000 -> 2000 | R7: =N7-Q7 -> 8761 | S7: =S6 -> 9517 | T7: =S7-S6 -> 0 | U7: =U6 -> 289529 | V7: =U7-U6 -> 0 | W7: =W6 -> 32049 | X7: =W7-W6 -> 0 | Y7: =Y6 -> 673052 | Z7: =Y7-Y6 -> 0 | AA7: 35538 | AB7: =AA7-AA6 -> 10 | AC7: 884534 | AD7: =AC7-AC6 -> 2564 | AE7: =AB7+X7+T7 -> 10 | AF7: =V7+Z7+AD7 -> 2564 | AG7: =IF(AE7>0,AF7/AE7,0) -> 256.4 | AI7: =R7-'EDl log'!B5 -> -349353
A8: ='General information '!F11 -> 0 | B8: =SUM(230*A8) -> 0 | C8: 44080 | D8: 32200152 | E8: =D8-D7 -> 5292 | F8: 3851952 | G8: =F8-F7 -> 1024 | H8: 17649074 | I8: =H8-H7 -> 1282 | J8: 28698338 | K8: =J8-J7 -> 832 | L8: 23595684 | M8: =L8-L7 -> 1910 | N8: =M8+K8+I8+G8+E8 -> 10340 | O8: =IF(B8>0,N8/B8,0) -> 0 | P8: 16285 | Q8: =(P8-P7)*1000 -> 4000 | R8: =N8-Q8 -> 6340 | S8: =S7 -> 9517 | T8: =S8-S7 -> 0 | U8: =U7 -> 289529 | V8: =U8-U7 -> 0 | W8: =W7 -> 32049 | X8: =W8-W7 -> 0 | Y8: =Y7 -> 673052 | Z8: =Y8-Y7 -> 0 | AA8: 35545 | AB8: =AA8-AA7 -> 7 | AC8: 886156 | AD8: =AC8-AC7 -> 1622 | AE8: =AB8+X8+T8 -> 7 | AF8: =V8+Z8+AD8 -> 1622 | AG8: =IF(AE8>0,AF8/AE8,0) -> 231.71429 | AI8: =R8-'EDl log'!B6 -> -355743
A9: ='General information '!F12 -> 0 | B9: =SUM(230*A9) -> 0 | C9: 44081 | D9: 32204862 | E9: =D9-D8 -> 4710 | F9: 3852863 | G9: =F9-F8 -> 911 | H9: 17650126 | I9: =H9-H8 -> 1052 | J9: 28699534 | K9: =J9-J8 -> 1196 | L9: 23600604 | M9: =L9-L8 -> 4920 | N9: =M9+K9+I9+G9+E9 -> 12789 | O9: =IF(B9>0,N9/B9,0) -> 0 | P9: 16290 | Q9: =(P9-P8)*1000 -> 5000 | R9: =N9-Q9 -> 7789 | S9: 9527 | T9: =S9-S8 -> 10 | U9: 292016 | V9: =U9-U8 -> 2487 | W9: =W8 -> 32049 | X9: =W9-W8 -> 0 | Y9: =Y8 -> 673052 | Z9: =Y9-Y8 -> 0 | AA9: 35550 | AB9: =AA9-AA8 -> 5 | AC9: 887256 | AD9: =AC9-AC8 -> 1100 | AE9: =AB9+X9+T9 -> 15 | AF9: =V9+Z9+AD9 -> 3587 | AG9: =IF(AE9>0,AF9/AE9,0) -> 239.13333 | AI9: =R9-'EDl log'!B7 -> -358678
A10: ='General information '!F13 -> 0 | B10: =SUM(230*A10) -> 0 | C10: 44082 | D10: 32209330 | E10: =D10-D9 -> 4468 | F10: 3853692 | G10: =F10-F9 -> 829 | H10: 17651026 | I10: =H10-H9 -> 900 | J10: 28700730 | K10: =J10-J9 -> 1196 | L10: 23605578 | M10: =L10-L9 -> 4974 | N10: =M10+K10+I10+G10+E10 -> 12367 | O10: =IF(B10>0,N10/B10,0) -> 0 | P10: 16298 | Q10: =(P10-P9)*1000 -> 8000 | R10: =N10-Q10 -> 4367 | S10: 9541 | T10: =S10-S9 -> 14 | U10: 295149 | V10: =U10-U9 -> 3133 | W10: 32049 | X10: =W10-W9 -> 0 | Y10: =Y9 -> 673052 | Z10: =Y10-Y9 -> 0 | AA10: 35556 | AB10: =AA10-AA9 -> 6 | AC10: 888280 | AD10: =AC10-AC9 -> 1024 | AE10: =AB10+X10+T10 -> 20 | AF10: =V10+Z10+AD10 -> 4157 | AG10: =IF(AE10>0,AF10/AE10,0) -> 207.85 | AI10: =R10-'EDl log'!B8 -> -366632
A11: ='General information '!F14 -> 0 | B11: =SUM(230*A11) -> 0 | C11: 44083 | D11: 32213030 | E11: =D11-D10 -> 3700 | F11: 3854552 | G11: =F11-F10 -> 860 | H11: 17652066 | I11: =H11-H10 -> 1040 | J11: 28701746 | K11: =J11-J10 -> 1016 | L11: 23610686 | M11: =L11-L10 -> 5108 | N11: =M11+K11+I11+G11+E11 -> 11724 | O11: =IF(B11>0,N11/B11,0) -> 0 | P11: 16300 | Q11: =(P11-P10)*1000 -> 2000 | R11: =N11-Q11 -> 9724 | S11: 9554 | T11: =S11-S10 -> 13 | U11: 298048 | V11: =U11-U10 -> 2899 | W11: =W10 -> 32049 | X11: =W11-W10 -> 0 | Y11: =Y10 -> 673052 | Z11: =Y11-Y10 -> 0 | AA11: =AA10 -> 35556 | AB11: =AA11-AA10 -> 0 | AC11: =AC10 -> 888280 | AD11: =AC11-AC10 -> 0 | AE11: =AB11+X11+T11 -> 13 | AF11: =V11+Z11+AD11 -> 2899 | AG11: =IF(AE11>0,AF11/AE11,0) -> 223 | AI11: =R11-'EDl log'!B9 -> -364617
A12: ='General information '!F15 -> 0 | B12: =SUM(230*A12) -> 0 | C12: 44084 | D12: 32216554 | E12: =D12-D11 -> 3524 | F12: 3855348 | G12: =F12-F11 -> 796 | H12: 17653022 | I12: =H12-H11 -> 956 | J12: 28702706 | K12: =J12-J11 -> 960 | L12: 23615454 | M12: =L12-L11 -> 4768 | N12: =M12+K12+I12+G12+E12 -> 11004 | O12: =IF(B12>0,N12/B12,0) -> 0 | P12: 16302 | Q12: =(P12-P11)*1000 -> 2000 | R12: =N12-Q12 -> 9004 | S12: 9566 | T12: =S12-S11 -> 12 | U12: 300876 | V12: =U12-U11 -> 2828 | W12: =W11 -> 32049 | X12: =W12-W11 -> 0 | Y12: =Y11 -> 673052 | Z12: =Y12-Y11 -> 0 | AA12: =AA11 -> 35556 | AB12: =AA12-AA11 -> 0 | AC12: =AC11 -> 888280 | AD12: =AC12-AC11 -> 0 | AE12: =AB12+X12+T12 -> 12 | AF12: =V12+Z12+AD12 -> 2828 | AG12: =IF(AE12>0,AF12/AE12,0) -> 235.66667 | AI12: =R12-'EDl log'!B10 -> -369575
A13: ='General information '!F16 -> 0 | B13: =SUM(230*A13) -> 0 | C13: 44085 | D13: 32220036 | E13: =D13-D12 -> 3482 | F13: 3856168 | G13: =F13-F12 -> 820 | H13: 17654008 | I13: =H13-H12 -> 986 | J13: 28703712 | K13: =J13-J12 -> 1006 | L13: 23620176 | M13: =L13-L12 -> 4722 | N13: =M13+K13+I13+G13+E13 -> 11016 | O13: =IF(B13>0,N13/B13,0) -> 0 | P13: 16305 | Q13: =(P13-P12)*1000 -> 3000 | R13: =N13-Q13 -> 8016 | S13: 9579 | T13: =S13-S12 -> 13 | U13: 303680 | V13: =U13-U12 -> 2804 | W13: =W12 -> 32049 | X13: =W13-W12 -> 0 | Y13: =Y12 -> 673052 | Z13: =Y13-Y12 -> 0 | AA13: =AA12 -> 35556 | AB13: =AA13-AA12 -> 0 | AC13: =AC12 -> 888280 | AD13: =AC13-AC12 -> 0 | AE13: =AB13+X13+T13 -> 13 | AF13: =V13+Z13+AD13 -> 2804 | AG13: =IF(AE13>0,AF13/AE13,0) -> 215.69231 | AI13: =R13-'EDl log'!B11 -> -372739
A14: ='General information '!F17 -> 0 | B14: =SUM(230*A14) -> 0 | C14: 44086 | D14: 32223034 | E14: =D14-D13 -> 2998 | F14: 3857010 | G14: =F14-F13 -> 842 | H14: 17655010 | I14: =H14-H13 -> 1002 | J14: 28704688 | K14: =J14-J13 -> 976 | L14: 23624726 | M14: =L14-L13 -> 4550 | N14: =M14+K14+I14+G14+E14 -> 10368 | O14: =IF(B14>0,N14/B14,0) -> 0 | P14: 16308 | Q14: =(P14-P13)*1000 -> 3000 | R14: =N14-Q14 -> 7368 | S14: 9590 | T14: =S14-S13 -> 11 | U14: 306003 | V14: =U14-U13 -> 2323 | W14: =W13 -> 32049 | X14: =W14-W13 -> 0 | Y14: =Y13 -> 673052 | Z14: =Y14-Y13 -> 0 | AA14: =AA13 -> 35556 | AB14: =AA14-AA13 -> 0 | AC14: =AC13 -> 888280 | AD14: =AC14-AC13 -> 0 | AE14: =AB14+X14+T14 -> 11 | AF14: =V14+Z14+AD14 -> 2323 | AG14: =IF(AE14>0,AF14/AE14,0) -> 211.18182 | AI14: =R14-'EDl log'!B12 -> -378323
A15: ='General information '!F18 -> 0 | B15: =SUM(230*A15) -> 0 | C15: 44087 | D15: 32225554 | E15: =D15-D14 -> 2520 | F15: 3857817 | G15: =F15-F14 -> 807 | H15: 17655982 | I15: =H15-H14 -> 972 | J15: 28705474 | K15: =J15-J14 -> 786 | L15: 23628682 | M15: =L15-L14 -> 3956 | N15: =M15+K15+I15+G15+E15 -> 9041 | O15: =IF(B15>0,N15/B15,0) -> 0 | P15: 16310 | Q15: =(P15-P14)*1000 -> 2000 | R15: =N15-Q15 -> 7041 | S15: 9599 | T15: =S15-S14 -> 9 | U15: 307976 | V15: =U15-U14 -> 1973 | W15: =W14 -> 32049 | X15: =W15-W14 -> 0 | Y15: =Y14 -> 673052 | Z15: =Y15-Y14 -> 0 | AA15: =AA14 -> 35556 | AB15: =AA15-AA14 -> 0 | AC15: =AC14 -> 888280 | AD15: =AC15-AC14 -> 0 | AE15: =AB15+X15+T15 -> 9 | AF15: =V15+Z15+AD15 -> 1973 | AG15: =IF(AE15>0,AF15/AE15,0) -> 219.22222 | AI15: =R15-'EDl log'!B13 -> -383392
A16: ='General information '!F19 -> 0 | B16: =SUM(230*A16) -> 0 | C16: 44088 | D16: 32228614 | E16: =D16-D15 -> 3060 | F16: 3858662 | G16: =F16-F15 -> 845 | H16: 17656862 | I16: =H16-H15 -> 880 | J16: 28706274 | K16: =J16-J15 -> 800 | L16: 23632202 | M16: =L16-L15 -> 3520 | N16: =M16+K16+I16+G16+E16 -> 9105 | O16: =IF(B16>0,N16/B16,0) -> 0 | P16: 16312 | Q16: =(P16-P15)*1000 -> 2000 | R16: =N16-Q16 -> 7105 | S16: 9606 | T16: =S16-S15 -> 7 | U16: 309536 | V16: =U16-U15 -> 1560 | W16: =W15 -> 32049 | X16: =W16-W15 -> 0 | Y16: =Y15 -> 673052 | Z16: =Y16-Y15 -> 0 | AA16: =AA15 -> 35556 | AB16: =AA16-AA15 -> 0 | AC16: =AC15 -> 888280 | AD16: =AC16-AC15 -> 0 | AE16: =AB16+X16+T16 -> 7 | AF16: =V16+Z16+AD16 -> 1560 | AG16: =IF(AE16>0,AF16/AE16,0) -> 222.85714 | AI16: =R16-'EDl log'!B14 -> -387314
A17: ='General information '!F20 -> 0 | B17: =SUM(230*A17) -> 0 | C17: 44089 | D17: 32234230 | E17: =D17-D16 -> 5616 | F17: 3859581 | G17: =F17-F16 -> 919 | H17: 17657838 | I17: =H17-H16 -> 976 | J17: 28707206 | K17: =J17-J16 -> 932 | L17: 23634214 | M17: =L17-L16 -> 2012 | N17: =M17+K17+I17+G17+E17 -> 10455 | O17: =IF(B17>0,N17/B17,0) -> 0 | P17: 16315 | Q17: =(P17-P16)*1000 -> 3000 | R17: =N17-Q17 -> 7455 | S17: 9606 | T17: =S17-S16 -> 0 | U17: 309536 | V17: =U17-U16 -> 0 | W17: =W16 -> 32049 | X17: =W17-W16 -> 0 | Y17: =Y16 -> 673052 | Z17: =Y17-Y16 -> 0 | AA17: 35566 | AB17: =AA17-AA16 -> 10 | AC17: 890520 | AD17: =AC17-AC16 -> 2240 | AE17: =AB17+X17+T17 -> 10 | AF17: =V17+Z17+AD17 -> 2240 | AG17: =IF(AE17>0,AF17/AE17,0) -> 224 | AI17: =R17-'EDl log'!B15 -> -391299
A18: ='General information '!F21 -> 0 | B18: =SUM(230*A18) -> 0 | C18: 44090 | D18: 32240010 | E18: =D18-D17 -> 5780 | F18: 3860356 | G18: =F18-F17 -> 775 | H18: 17658660 | I18: =H18-H17 -> 822 | J18: 28708154 | K18: =J18-J17 -> 948 | L18: 23636052 | M18: =L18-L17 -> 1838 | N18: =M18+K18+I18+G18+E18 -> 10163 | O18: =IF(B18>0,N18/B18,0) -> 0 | P18: 16318 | Q18: =(P18-P17)*1000 -> 3000 | R18: =N18-Q18 -> 7163 | S18: =S17 -> 9606 | T18: =S18-S17 -> 0 | U18: =U17 -> 309536 | V18: =U18-U17 -> 0 | W18: =W17 -> 32049 | X18: =W18-W17 -> 0 | Y18: =Y17 -> 673052 | Z18: =Y18-Y17 -> 0 | AA18: 35581 | AB18: =AA18-AA17 -> 15 | AC18: 893493 | AD18: =AC18-AC17 -> 2973 | AE18: =AB18+X18+T18 -> 15 | AF18: =V18+Z18+AD18 -> 2973 | AG18: =IF(AE18>0,AF18/AE18,0) -> 198.2 | AI18: =R18-'EDl log'!B16 -> -395093
A19: ='General information '!F22 -> 0 | B19: =SUM(230*A19) -> 0 | C19: 44091 | D19: 32244176 | E19: =D19-D18 -> 4166 | F19: 3861274 | G19: =F19-F18 -> 918 | H19: 17659610 | I19: =H19-H18 -> 950 | J19: 28708896 | K19: =J19-J18 -> 742 | L19: 23638502 | M19: =L19-L18 -> 2450 | N19: =M19+K19+I19+G19+E19 -> 9226 | O19: =IF(B19>0,N19/B19,0) -> 0 | P19: 16319 | Q19: =(P19-P18)*1000 -> 1000 | R19: =N19-Q19 -> 8226 | S19: =S18 -> 9606 | T19: =S19-S18 -> 0 | U19: =U18 -> 309536 | V19: =U19-U18 -> 0 | W19: =W18 -> 32049 | X19: =W19-W18 -> 0 | Y19: =Y18 -> 673052 | Z19: =Y19-Y18 -> 0 | AA19: 35586 | AB19: =AA19-AA18 -> 5 | AC19: 894782 | AD19: =AC19-AC18 -> 1289 | AE19: =AB19+X19+T19 -> 5 | AF19: =V19+Z19+AD19 -> 1289 | AG19: =IF(AE19>0,AF19/AE19,0) -> 257.8 | AI19: =R19-'EDl log'!B17 -> -397757
A20: ='General information '!F23 -> 0 | B20: =SUM(230*A20) -> 0 | C20: 44092 | D20: 32247138 | E20: =D20-D19 -> 2962 | F20: 3862133 | G20: =F20-F19 -> 859 | H20: 17660518 | I20: =H20-H19 -> 908 | J20: 28709748 | K20: =J20-J19 -> 852 | L20: 23642594 | M20: =L20-L19 -> 4092 | N20: =M20+K20+I20+G20+E20 -> 9673 | O20: =IF(B20>0,N20/B20,0) -> 0 | P20: 16321 | Q20: =(P20-P19)*1000 -> 2000 | R20: =N20-Q20 -> 7673 | S20: 9617 | T20: =S20-S19 -> 11 | U20: 312110 | V20: =U20-U19 -> 2574 | W20: =W19 -> 32049 | X20: =W20-W19 -> 0 | Y20: =Y19 -> 673052 | Z20: =Y20-Y19 -> 0 | AA20: =AA19 -> 35586 | AB20: =AA20-AA19 -> 0 | AC20: =AC19 -> 894782 | AD20: =AC20-AC19 -> 0 | AE20: =AB20+X20+T20 -> 11 | AF20: =V20+Z20+AD20 -> 2574 | AG20: =IF(AE20>0,AF20/AE20,0) -> 234 | AI20: =R20-'EDl log'!B18 -> -402044
A21: ='General information '!F24 -> 0 | B21: =SUM(230*A21) -> 0 | C21: 44093 | D21: 32250282 | E21: =D21-D20 -> 3144 | F21: 3862894 | G21: =F21-F20 -> 761 | H21: 17661350 | I21: =H21-H20 -> 832 | J21: 28710350 | K21: =J21-J20 -> 602 | L21: 23645122 | M21: =L21-L20 -> 2528 | N21: =M21+K21+I21+G21+E21 -> 7867 | O21: =IF(B21>0,N21/B21,0) -> 0 | P21: 16323 | Q21: =(P21-P20)*1000 -> 2000 | R21: =N21-Q21 -> 5867 | S21: 9620 | T21: =S21-S20 -> 3 | U21: 312929 | V21: =U21-U20 -> 819 | W21: =W20 -> 32049 | X21: =W21-W20 -> 0 | Y21: =Y20 -> 673052 | Z21: =Y21-Y20 -> 0 | AA21: 35589 | AB21: =AA21-AA20 -> 3 | AC21: 895463 | AD21: =AC21-AC20 -> 681 | AE21: =AB21+X21+T21 -> 6 | AF21: =V21+Z21+AD21 -> 1500 | AG21: =IF(AE21>0,AF21/AE21,0) -> 250 | AI21: =R21-'EDl log'!B19 -> -407885
A22: ='General information '!F25 -> 0 | B22: =SUM(230*A22) -> 0 | C22: 44094 | D22: 32252830 | E22: =D22-D21 -> 2548 | F22: 3863701 | G22: =F22-F21 -> 807 | H22: 17662226 | I22: =H22-H21 -> 876 | J22: 28711104 | K22: =J22-J21 -> 754 | L22: 23649018 | M22: =L22-L21 -> 3896 | N22: =M22+K22+I22+G22+E22 -> 8881 | O22: =IF(B22>0,N22/B22,0) -> 0 | P22: 16325.495 | Q22: =(P22-P21)*1000 -> 2495 | R22: =N22-Q22 -> 6386 | S22: 9629 | T22: =S22-S21 -> 9 | U22: 314977 | V22: =U22-U21 -> 2048 | W22: =W21 -> 32049 | X22: =W22-W21 -> 0 | Y22: =Y21 -> 673052 | Z22: =Y22-Y21 -> 0 | AA22: 35589 | AB22: =AA22-AA21 -> 0 | AC22: 895463 | AD22: =AC22-AC21 -> 0 | AE22: =AB22+X22+T22 -> 9 | AF22: =V22+Z22+AD22 -> 2048 | AG22: =IF(AE22>0,AF22/AE22,0) -> 227.55556 | AI22: =R22-'EDl log'!B20 -> -411263
A23: ='General information '!F26 -> 0 | B23: =SUM(230*A23) -> 0 | C23: 44095 | D23: 32256638 | E23: =D23-D22 -> 3808 | F23: 3864507 | G23: =F23-F22 -> 806 | H23: 17663058 | I23: =H23-H22 -> 832 | J23: 28711894 | K23: =J23-J22 -> 790 | L23: 23652040 | M23: =L23-L22 -> 3022 | N23: =M23+K23+I23+G23+E23 -> 9258 | O23: =IF(B23>0,N23/B23,0) -> 0 | P23: 16327 | Q23: =(P23-P22)*1000 -> 1505 | R23: =N23-Q23 -> 7753 | S23: 9634 | T23: =S23-S22 -> 5 | U23: 316092 | V23: =U23-U22 -> 1115 | W23: =W22 -> 32049 | X23: =W23-W22 -> 0 | Y23: =Y22 -> 673052 | Z23: =Y23-Y22 -> 0 | AA23: 35594 | AB23: =AA23-AA22 -> 5 | AC23: 896638 | AD23: =AC23-AC22 -> 1175 | AE23: =AB23+X23+T23 -> 10 | AF23: =V23+Z23+AD23 -> 2290 | AG23: =IF(AE23>0,AF23/AE23,0) -> 229 | AI23: =R23-'EDl log'!B21 -> -414151
A24: ='General information '!F27 -> 0 | B24: =SUM(230*A24) -> 0 | C24: 44096 | D24: 32260010 | E24: =D24-D23 -> 3372 | F24: 3865337 | G24: =F24-F23 -> 830 | H24: 17663930 | I24: =H24-H23 -> 872 | J24: 28712882 | K24: =J24-J23 -> 988 | L24: 23656666 | M24: =L24-L23 -> 4626 | N24: =M24+K24+I24+G24+E24 -> 10688 | O24: =IF(B24>0,N24/B24,0) -> 0 | P24: 16331 | Q24: =(P24-P23)*1000 -> 4000 | R24: =N24-Q24 -> 6688 | S24: 9645 | T24: =S24-S23 -> 11 | U24: 318534 | V24: =U24-U23 -> 2442 | W24: =W23 -> 32049 | X24: =W24-W23 -> 0 | Y24: =Y23 -> 673052 | Z24: =Y24-Y23 -> 0 | AA24: 35594 | AB24: =AA24-AA23 -> 0 | AC24: 896638 | AD24: =AC24-AC23 -> 0 | AE24: =AB24+X24+T24 -> 11 | AF24: =V24+Z24+AD24 -> 2442 | AG24: =IF(AE24>0,AF24/AE24,0) -> 222 | AI24: =R24-'EDl log'!B22 -> -418321
A25: ='General information '!F28 -> 0 | B25: =SUM(230*A25) -> 0 | C25: 44097 | D25: 32265002 | E25: =D25-D24 -> 4992 | F25: 3866176 | G25: =F25-F24 -> 839 | H25: 17664806 | I25: =H25-H24 -> 876 | J25: 28713734 | K25: =J25-J24 -> 852 | L25: 23659450 | M25: =L25-L24 -> 2784 | N25: =M25+K25+I25+G25+E25 -> 10343 | O25: =IF(B25>0,N25/B25,0) -> 0 | P25: 16333 | Q25: =(P25-P24)*1000 -> 2000 | R25: =N25-Q25 -> 8343 | S25: 9647 | T25: =S25-S24 -> 2 | U25: 319062 | V25: =U25-U24 -> 528 | W25: =W24 -> 32049 | X25: =W25-W24 -> 0 | Y25: =Y24 -> 673052 | Z25: =Y25-Y24 -> 0 | AA25: 35603 | AB25: =AA25-AA24 -> 9 | AC25: 898412 | AD25: =AC25-AC24 -> 1774 | AE25: =AB25+X25+T25 -> 11 | AF25: =V25+Z25+AD25 -> 2302 | AG25: =IF(AE25>0,AF25/AE25,0) -> 209.27273 | AI25: =R25-'EDl log'!B23 -> -420247
A26: ='General information '!F29 -> 0 | B26: =SUM(230*A26) -> 0 | C26: 44098 | D26: 32269102 | E26: =D26-D25 -> 4100 | F26: 3867053 | G26: =F26-F25 -> 877 | H26: 17665670 | I26: =H26-H25 -> 864 | J26: 28714568 | K26: =J26-J25 -> 834 | L26: 23663002 | M26: =L26-L25 -> 3552 | N26: =M26+K26+I26+G26+E26 -> 10227 | O26: =IF(B26>0,N26/B26,0) -> 0 | P26: 16335 | Q26: =(P26-P25)*1000 -> 2000 | R26: =N26-Q26 -> 8227 | S26: 9653 | T26: =S26-S25 -> 6 | U26: 320308 | V26: =U26-U25 -> 1246 | W26: =W25 -> 32049 | X26: =W26-W25 -> 0 | Y26: =Y25 -> 673052 | Z26: =Y26-Y25 -> 0 | AA26: 35607 | AB26: =AA26-AA25 -> 4 | AC26: 899487 | AD26: =AC26-AC25 -> 1075 | AE26: =AB26+X26+T26 -> 10 | AF26: =V26+Z26+AD26 -> 2321 | AG26: =IF(AE26>0,AF26/AE26,0) -> 232.1 | AI26: =R26-'EDl log'!B24 -> -424041
A27: ='General information '!F30 -> 0 | B27: =SUM(230*A27) -> 0 | C27: 44099 | D27: 32271638 | E27: =D27-D26 -> 2536 | F27: 3867913 | G27: =F27-F26 -> 860 | H27: 17666516 | I27: =H27-H26 -> 846 | J27: 28715200 | K27: =J27-J26 -> 632 | L27: 23666314 | M27: =L27-L26 -> 3312 | N27: =M27+K27+I27+G27+E27 -> 8186 | O27: =IF(B27>0,N27/B27,0) -> 0 | P27: 16336 | Q27: =(P27-P26)*1000 -> 1000 | R27: =N27-Q27 -> 7186 | S27: 9659 | T27: =S27-S26 -> 6 | U27: 321733 | V27: =U27-U26 -> 1425 | W27: =W26 -> 32049 | X27: =W27-W26 -> 0 | Y27: =Y26 -> 673052 | Z27: =Y27-Y26 -> 0 | AA27: =AA26 -> 35607 | AB27: =AA27-AA26 -> 0 | AC27: =AC26 -> 899487 | AD27: =AC27-AC26 -> 0 | AE27: =AB27+X27+T27 -> 6 | AF27: =V27+Z27+AD27 -> 1425 | AG27: =IF(AE27>0,AF27/AE27,0) -> 237.5 | AI27: =R27-'EDl log'!B25 -> -428540
A28: ='General information '!F31 -> 0 | B28: =SUM(230*A28) -> 0 | C28: 44100 | D28: 32273914 | E28: =D28-D27 -> 2276 | F28: 3868769 | G28: =F28-F27 -> 856 | H28: 17667358 | I28: =H28-H27 -> 842 | J28: 28715794 | K28: =J28-J27 -> 594 | L28: 23669310 | M28: =L28-L27 -> 2996 | N28: =M28+K28+I28+G28+E28 -> 7564 | O28: =IF(B28>0,N28/B28,0) -> 0 | P28: 16338 | Q28: =(P28-P27)*1000 -> 2000 | R28: =N28-Q28 -> 5564 | S28: 9665 | T28: =S28-S27 -> 6 | U28: 322890 | V28: =U28-U27 -> 1157 | W28: =W27 -> 32049 | X28: =W28-W27 -> 0 | Y28: =Y27 -> 673052 | Z28: =Y28-Y27 -> 0 | AA28: =AA27 -> 35607 | AB28: =AA28-AA27 -> 0 | AC28: =AC27 -> 899487 | AD28: =AC28-AC27 -> 0 | AE28: =AB28+X28+T28 -> 6 | AF28: =V28+Z28+AD28 -> 1157 | AG28: =IF(AE28>0,AF28/AE28,0) -> 192.83333 | AI28: =R28-'EDl log'!B26 -> -434771
A29: ='General information '!F32 -> 0 | B29: =SUM(230*A29) -> 0 | C29: 44101 | D29: 32277052 | E29: =D29-D28 -> 3138 | F29: 3869563 | G29: =F29-F28 -> 794 | H29: 17668258 | I29: =H29-H28 -> 900 | J29: 28716674 | K29: =J29-J28 -> 880 | L29: 23673590 | M29: =L29-L28 -> 4280 | N29: =M29+K29+I29+G29+E29 -> 9992 | O29: =IF(B29>0,N29/B29,0) -> 0 | P29: 16338.9 | Q29: =(P29-P28)*1000 -> 900 | R29: =N29-Q29 -> 9092 | S29: 9673 | T29: =S29-S28 -> 8 | U29: 325151 | V29: =U29-U28 -> 2261 | W29: =W28 -> 32049 | X29: =W29-W28 -> 0 | Y29: =Y28 -> 673052 | Z29: =Y29-Y28 -> 0 | AA29: 35607 | AB29: =AA29-AA28 -> 0 | AC29: 899488 | AD29: =AC29-AC28 -> 1 | AE29: =AB29+X29+T29 -> 8 | AF29: =V29+Z29+AD29 -> 2262 | AG29: =IF(AE29>0,AF29/AE29,0) -> 282.75 | AI29: =R29-'EDl log'!B27 -> -435706
A30: ='General information '!F33 -> 0 | B30: =SUM(230*A30) -> 0 | C30: 44102 | D30: 32280280 | E30: =D30-D29 -> 3228 | F30: 3870362 | G30: =F30-F29 -> 799 | H30: 17669074 | I30: =H30-H29 -> 816 | J30: 28717602 | K30: =J30-J29 -> 928 | L30: 23677902 | M30: =L30-L29 -> 4312 | N30: =M30+K30+I30+G30+E30 -> 10083 | O30: =IF(B30>0,N30/B30,0) -> 0 | P30: 16340 | Q30: =(P30-P29)*1000 -> 1100 | R30: =N30-Q30 -> 8983 | S30: 9684 | T30: =S30-S29 -> 11 | U30: 327795 | V30: =U30-U29 -> 2644 | W30: =W29 -> 32049 | X30: =W30-W29 -> 0 | Y30: =Y29 -> 673052 | Z30: =Y30-Y29 -> 0 | AA30: 35607 | AB30: =AA30-AA29 -> 0 | AC30: 899488 | AD30: =AC30-AC29 -> 0 | AE30: =AB30+X30+T30 -> 11 | AF30: =V30+Z30+AD30 -> 2644 | AG30: =IF(AE30>0,AF30/AE30,0) -> 240.36364 | AI30: =R30-'EDl log'!B28 -> -439366
A31: ='General information '!F34 -> 0 | B31: =SUM(230*A31) -> 0 | C31: 44103 | D31: 32283632 | E31: =D31-D30 -> 3352 | F31: 3871226 | G31: =F31-F30 -> 864 | H31: 17669934 | I31: =H31-H30 -> 860 | J31: 28718582 | K31: =J31-J30 -> 980 | L31: 23683074 | M31: =L31-L30 -> 5172 | N31: =M31+K31+I31+G31+E31 -> 11228 | O31: =IF(B31>0,N31/B31,0) -> 0 | P31: 16342 | Q31: =(P31-P30)*1000 -> 2000 | R31: =N31-Q31 -> 9228 | S31: 9695 | T31: =S31-S30 -> 11 | U31: 330743 | V31: =U31-U30 -> 2948 | W31: =W30 -> 32049 | X31: =W31-W30 -> 0 | Y31: =Y30 -> 673052 | Z31: =Y31-Y30 -> 0 | AA31: =AA30 -> 35607 | AB31: =AA31-AA30 -> 0 | AC31: =AC30 -> 899488 | AD31: =AC31-AC30 -> 0 | AE31: =AB31+X31+T31 -> 11 | AF31: =V31+Z31+AD31 -> 2948 | AG31: =IF(AE31>0,AF31/AE31,0) -> 268 | AI31: =R31-'EDl log'!B29 -> -442364
A32: ='General information '!F35 -> 0 | B32: =SUM(230*A32) -> 0 | C32: 44104 | D32: 32287200 | E32: =D32-D31 -> 3568 | F32: 3872020 | G32: =F32-F31 -> 794 | H32: 17670874 | I32: =H32-H31 -> 940 | J32: 28719638 | K32: =J32-J31 -> 1056 | L32: 23688570 | M32: =L32-L31 -> 5496 | N32: =M32+K32+I32+G32+E32 -> 11854 | O32: =IF(B32>0,N32/B32,0) -> 0 | P32: 16346 | Q32: =(P32-P31)*1000 -> 4000 | R32: =N32-Q32 -> 7854 | S32: 9708 | T32: =S32-S31 -> 13 | U32: 333763 | V32: =U32-U31 -> 3020 | W32: =W31 -> 32049 | X32: =W32-W31 -> 0 | Y32: =Y31 -> 673052 | Z32: =Y32-Y31 -> 0 | AA32: =AA31 -> 35607 | AB32: =AA32-AA31 -> 0 | AC32: =AC31 -> 899488 | AD32: =AC32-AC31 -> 0 | AE32: =AB32+X32+T32 -> 13 | AF32: =V32+Z32+AD32 -> 3020 | AG32: =IF(AE32>0,AF32/AE32,0) -> 232.30769 | AI32: =R32-'EDl log'!B30 -> -448502

Sheet B5
F1: Boiler A | J1: =J35 -> 1 | K1: Boiler B | P1: Boiler C | V1: Boiler | X1: SteamA | AC1: SteamB | AH1: Steam | AI1: Boiler & steam | AL1: Total Boiler Runing H | AM1: Total Steam Runing H | AN1: GAS1 % | AO1: GAS1/L | AP1: GAS2% | AQ1: Gas2/L | AR1: GAS3% | AS1: GAS3/L | AU1: Gas Cons | AV1: Delivery | AW1: Cost/L
B2: Level Tank Gen | C2: Level tank Boiler | D2: Daily Cons Bo. | E2: Boiler litter | F2: Boiler A | G2: Run Hr a | H2: Boiler A fuel | I2: Daily consumption | J2: AVG | K2: index Run H | L2: Run Hrb | M2: Boiler B Fuel | O2: Daily consumption | P2: Boiler C | S2: Run C | U2: Total RH | V2: Total Fuel | X2: SteamA | Y2: Run SA | Z2: Steam A Conter | AA2: Liters | AC2: SteamB | AD2: Run SteamB | AE2: Steam B Conter | AF2: SB Litters | AG2: Avg | AH2: Total Fuel | AI2: Total Fuel
S3: 0
A4: =ELEC!C2 -> 44074 | B4: =[1]B5!B35 -> 239 | C4: =[1]B5!C35 -> 244 | D4: =[1]B5!D35 -> 4 | E4: =[1]B5!E35 -> 33.52 | F4: =[1]B5!F35 -> 1648 | G4: =[1]B5!G35 -> 0 | H4: =[1]B5!H35 -> 357868 | I4: =[1]B5!I35 -> 0 | ... AX4: =[1]B5!AX35 -> 0.8
A5: =ELEC!C3 -> 44075 | B5: 236 | C5: 242 | D5: =C4-C5 -> 2 | E5: =D5*8.38 -> 16.76 | F5: 1648 | G5: =F5-F4 -> 0 | H5: =H4 -> 357868 | I5: =SUM(H5-H4) -> 0 | J5: 1 | K5: =K4 -> 2110 | L5: =K5-K4 -> 0 | M5: =M4 -> 154820 | N5: =M5-M4 -> 0 | O5: =O4 -> 211.875 | P5: 1839 | Q5: 156094 | R5: =Q5-Q4 -> 155 | S5: =SUM(P5-P4) -> 2 | T5: =SUM(S5*$T$2) -> 0 | U5: =SUM(G5+L5+S5) -> 2 | V5: =R5+N5+I5:I5 -> 155 | W5: =SUM(V5/U5) -> 77.5 | X5: =X4 -> 2435 | Y5: =X5-X4 -> 0 | Z5: =Z4 -> 136853 | AA5: =Z5-Z4 -> 0 | AB5: =SUM(Y5*$AB$2) -> 0 | AC5: =AC4 -> 1933 | AD5: =AC5-AC4 -> 0 | AE5: =AE4 -> 365210.2 | AF5: =AE5-AE4 -> 0 | AG5: =IF(AD5>0,AF5/AD5,0) -> 0 | AH5: =AF5+AA5 -> 0 | AI5: =SUM(AH5+V5) -> 155 | AJ5: =-tanks!AW6 -> 155 | AK5: =SUM(AJ5-AI5) -> 0 | AL5: =S5+L5+G5 -> 2 | AM5: =Y5+AD5 -> 0 | AN5: =AN4 -> 63 | AO5: =(AN5/100)*3000 -> 1890 | AP5: =AP4 -> 69 | AQ5: =(AP5/100)*3000 -> 2070 | AR5: =AR4 -> 69 | AS5: =(AR5/100)*3000 -> 2070 | AT5: =SUM(AO5+AQ5+AS5) -> 6030 | AU5: =AT4-AT5+AV5 -> 0 | AX5: =IF(AV5>0,AW5,AX4) -> 0.8
A6: =ELEC!C4 -> 44076 | B6: 231 | C6: 237 | D6: =C5-C6 -> 5 | E6: =D6*8.38 -> 41.9 | F6: =F5 -> 1648 | G6: =F6-F5 -> 0 | H6: =H5 -> 357868 | I6: =SUM(H6-H5) -> 0 | J6: =IF(G6>0,I6/G6,0) -> 0 | K6: =K5 -> 2110 | L6: =K6-K5 -> 0 | M6: =M5 -> 154820 | N6: =M6-M5 -> 0 | O6: =O5 -> 211.875 | P6: =P5 -> 1839 | Q6: =Q5 -> 156094 | R6: =Q6-Q5 -> 0 | S6: =SUM(P6-P5) -> 0 | T6: =SUM(S6*$T$2) -> 0 | U6: =SUM(G6+L6+S6) -> 0 | V6: =R6+N6+I6:I6 -> 0 | W6: =SUM(V6/U6) -> #DIV/0! | X6: =X5 -> 2435 | Y6: =X6-X5 -> 0 | Z6: =Z5 -> 136853 | AA6: =Z6-Z5 -> 0 | AB6: =SUM(Y6*$AB$2) -> 0 | AC6: =AC5 -> 1933 | AD6: =AC6-AC5 -> 0 | AE6: =AE5 -> 365210.2 | AF6: =AE6-AE5 -> 0 | AG6: =IF(AD6>0,AF6/AD6,0) -> 0 | AH6: =AF6+AA6 -> 0 | AI6: =SUM(AH6+V6) -> 0 | AJ6: =-tanks!AW7 -> 0 | AK6: =SUM(AJ6-AI6) -> 0 | AL6: =S6+L6+G6 -> 0 | AM6: =Y6+AD6 -> 0 | AN6: =AN5 -> 63 | AO6: =(AN6/100)*3000 -> 1890 | AP6: =AP5 -> 69 | AQ6: =(AP6/100)*3000 -> 2070 | AR6: =AR5 -> 69 | AS6: =(AR6/100)*3000 -> 2070 | AT6: =SUM(AO6+AQ6+AS6) -> 6030 | AU6: =AT5-AT6+AV6 -> 0 | AX6: =IF(AV6>0,AW6,AX5) -> 0.8
A7: =ELEC!C5 -> 44077 | B7: 225 | C7: 231 | D7: =C6-C7 -> 6 | E7: =D7*8.38 -> 50.28 | F7: =F6 -> 1648 | G7: =F7-F6 -> 0 | H7: =H6 -> 357868 | I7: =SUM(H7-H6) -> 0 | J7: =IF(G7>0,I7/G7,0) -> 0 | K7: =K6 -> 2110 | L7: =K7-K6 -> 0 | M7: =M6 -> 154820 | N7: =M7-M6 -> 0 | O7: =O6 -> 211.875 | P7: =P6 -> 1839 | Q7: =Q6 -> 156094 | R7: =Q7-Q6 -> 0 | S7: =SUM(P7-P6) -> 0 | T7: =SUM(S7*$T$2) -> 0 | U7: =SUM(G7+L7+S7) -> 0 | V7: =R7+N7+I7:I7 -> 0 | W7: =SUM(V7/U7) -> #DIV/0! | X7: 2443 | Y7: =X7-X6 -> 8 | Z7: 137203 | AA7: =Z7-Z6 -> 350 | AB7: =SUM(Y7*$AB$2) -> 0 | AC7: =AC6 -> 1933 | AD7: =AC7-AC6 -> 0 | AE7: =AE6 -> 365210.2 | AF7: =AE7-AE6 -> 0 | AG7: =IF(AD7>0,AF7/AD7,0) -> 0 | AH7: =AF7+AA7 -> 350 | AI7: =SUM(AH7+V7) -> 350 | AJ7: =-tanks!AW8 -> 350 | AK7: =SUM(AJ7-AI7) -> 0 | AL7: =S7+L7+G7 -> 0 | AM7: =Y7+AD7 -> 8 | AN7: =AN6 -> 63 | AO7: =(AN7/100)*3000 -> 1890 | AP7: =AP6 -> 69 | AQ7: =(AP7/100)*3000 -> 2070 | AR7: =AR6 -> 69 | AS7: =(AR7/100)*3000 -> 2070 | AT7: =SUM(AO7+AQ7+AS7) -> 6030 | AU7: =AT6-AT7+AV7 -> 0 | AX7: =IF(AV7>0,AW7,AX6) -> 0.8
A8: =ELEC!C6 -> 44078 | B8: 218.4 | C8: 224.3 | D8: =C7-C8 -> 6.7 | E8: =D8*8.38 -> 56.146 | F8: =F7 -> 1648 | G8: =F8-F7 -> 0 | H8: =H7 -> 357868 | I8: =SUM(H8-H7) -> 0 | J8: =IF(G8>0,I8/G8,0) -> 0 | K8: =K7 -> 2110 | L8: =K8-K7 -> 0 | M8: =M7 -> 154820 | N8: =M8-M7 -> 0 | O8: =O7 -> 211.875 | P8: =P7 -> 1839 | Q8: =Q7 -> 156094 | R8: =Q8-Q7 -> 0 | S8: =SUM(P8-P7) -> 0 | T8: =SUM(S8*$T$2) -> 0 | U8: =SUM(G8+L8+S8) -> 0 | V8: =R8+N8+I8:I8 -> 0 | W8: =SUM(V8/U8) -> #DIV/0! | X8: 2448 | Y8: =X8-X7 -> 5 | Z8: 137506 | AA8: =Z8-Z7 -> 303 | AB8: =SUM(Y8*$AB$2) -> 0 | AC8: =AC7 -> 1933 | AD8: =AC8-AC7 -> 0 | AE8: =AE7 -> 365210.2 | AF8: =AE8-AE7 -> 0 | AG8: =IF(AD8>0,AF8/AD8,0) -> 0 | AH8: =AF8+AA8 -> 303 | AI8: =SUM(AH8+V8) -> 303 | AJ8: =-tanks!AW9 -> 303 | AK8: =SUM(AJ8-AI8) -> 0 | AL8: =S8+L8+G8 -> 0 | AM8: =Y8+AD8 -> 5 | AN8: 63 | AO8: =(AN8/100)*3000 -> 1890 | AP8: 69 | AQ8: =(AP8/100)*3000 -> 2070 | AR8: =AR7 -> 69 | AS8: =(AR8/100)*3000 -> 2070 | AT8: =SUM(AO8+AQ8+AS8) -> 6030 | AU8: =AT7-AT8+AV8 -> 0 | AX8: =IF(AV8>0,AW8,AX7) -> 0.8
A9: =ELEC!C7 -> 44079 | B9: 216 | C9: 222 | D9: =C8-C9 -> 2.3 | E9: =D9*8.38 -> 19.274 | F9: =F8 -> 1648 | G9: =F9-F8 -> 0 | H9: =H8 -> 357868 | I9: =SUM(H9-H8) -> 0 | J9: =IF(G9>0,I9/G9,0) -> 0 | K9: =K8 -> 2110 | L9: =K9-K8 -> 0 | M9: =M8 -> 154820 | N9: =M9-M8 -> 0 | O9: =O8 -> 211.875 | P9: =P8 -> 1839 | Q9: =Q8 -> 156094 | R9: =Q9-Q8 -> 0 | S9: =SUM(P9-P8) -> 0 | T9: =SUM(S9*$T$2) -> 0 | U9: =SUM(G9+L9+S9) -> 0 | V9: =R9+N9+I9:I9 -> 0 | W9: =SUM(V9/U9) -> #DIV/0! | X9: =X8 -> 2448 | Y9: =X9-X8 -> 0 | Z9: =Z8 -> 137506 | AA9: =Z9-Z8 -> 0 | AB9: =SUM(Y9*$AB$2) -> 0 | AC9: =AC8 -> 1933 | AD9: =AC9-AC8 -> 0 | AE9: =AE8 -> 365210.2 | AF9: =AE9-AE8 -> 0 | AG9: =IF(AD9>0,AF9/AD9,0) -> 0 | AH9: =AF9+AA9 -> 0 | AI9: =SUM(AH9+V9) -> 0 | AJ9: =-tanks!AW10 -> 0 | AK9: =SUM(AJ9-AI9) -> 0 | AL9: =S9+L9+G9 -> 0 | AM9: =Y9+AD9 -> 0 | AN9: =AN8 -> 63 | AO9: =(AN9/100)*3000 -> 1890 | AP9: =AP8 -> 69 | AQ9: =(AP9/100)*3000 -> 2070 | AR9: =AR8 -> 69 | AS9: =(AR9/100)*3000 -> 2070 | AT9: =SUM(AO9+AQ9+AS9) -> 6030 | AU9: =AT8-AT9+AV9 -> 0 | AX9: =IF(AV9>0,AW9,AX8) -> 0.8
A10: =ELEC!C8 -> 44080 | B10: 211 | C10: 218 | D10: =C9-C10 -> 4 | E10: =D10*8.38 -> 33.52 | F10: =F9 -> 1648 | G10: =F10-F9 -> 0 | H10: =H9 -> 357868 | I10: =SUM(H10-H9) -> 0 | J10: =IF(G10>0,I10/G10,0) -> 0 | K10: =K9 -> 2110 | L10: =K10-K9 -> 0 | M10: =M9 -> 154820 | N10: =M10-M9 -> 0 | O10: =O9 -> 211.875 | P10: =P9 -> 1839 | Q10: =Q9 -> 156094 | R10: =Q10-Q9 -> 0 | S10: =SUM(P10-P9) -> 0 | T10: =SUM(S10*$T$2) -> 0 | U10: =SUM(G10+L10+S10) -> 0 | V10: =R10+N10+I10:I10 -> 0 | W10: =SUM(V10/U10) -> #DIV/0! | X10: =X9 -> 2448 | Y10: =X10-X9 -> 0 | Z10: =Z9 -> 137506 | AA10: =Z10-Z9 -> 0 | AB10: =SUM(Y10*$AB$2) -> 0 | AC10: =AC9 -> 1933 | AD10: =AC10-AC9 -> 0 | AE10: =AE9 -> 365210.2 | AF10: =AE10-AE9 -> 0 | AG10: =IF(AD10>0,AF10/AD10,0) -> 0 | AH10: =AF10+AA10 -> 0 | AI10: =SUM(AH10+V10) -> 0 | AJ10: =-tanks!AW11 -> 0 | AK10: =SUM(AJ10-AI10) -> 0 | AL10: =S10+L10+G10 -> 0 | AM10: =Y10+AD10 -> 0 | AN10: =AN9 -> 63 | AO10: =(AN10/100)*3000 -> 1890 | AP10: =AP9 -> 69 | AQ10: =(AP10/100)*3000 -> 2070 | AR10: =AR9 -> 69 | AS10: =(AR10/100)*3000 -> 2070 | AT10: =SUM(AO10+AQ10+AS10) -> 6030 | AU10: =AT9-AT10+AV10 -> 0 | AX10: =IF(AV10>0,AW10,AX9) -> 0.8
A11: =ELEC!C9 -> 44081 | B11: 207 | C11: 213 | D11: =C10-C11 -> 5 | E11: =D11*8.38 -> 41.9 | F11: =F10 -> 1648 | G11: =F11-F10 -> 0 | H11: =H10 -> 357868 | I11: =SUM(H11-H10) -> 0 | J11: =IF(G11>0,I11/G11,0) -> 0 | K11: =K10 -> 2110 | L11: =K11-K10 -> 0 | M11: =M10 -> 154820 | N11: =M11-M10 -> 0 | O11: =O10 -> 211.875 | P11: =P10 -> 1839 | Q11: =Q10 -> 156094 | R11: =Q11-Q10 -> 0 | S11: =SUM(P11-P10) -> 0 | T11: =SUM(S11*$T$2) -> 0 | U11: =SUM(G11+L11+S11) -> 0 | V11: =R11+N11+I11:I11 -> 0 | W11: =SUM(V11/U11) -> #DIV/0! | X11: =X10 -> 2448 | Y11: =X11-X10 -> 0 | Z11: =Z10 -> 137506 | AA11: =Z11-Z10 -> 0 | AB11: =SUM(Y11*$AB$2) -> 0 | AC11: =AC10 -> 1933 | AD11: =AC11-AC10 -> 0 | AE11: =AE10 -> 365210.2 | AF11: =AE11-AE10 -> 0 | AG11: =IF(AD11>0,AF11/AD11,0) -> 0 | AH11: =AF11+AA11 -> 0 | AI11: =SUM(AH11+V11) -> 0 | AJ11: =-tanks!AW12 -> 0 | AK11: =SUM(AJ11-AI11) -> 0 | AL11: =S11+L11+G11 -> 0 | AM11: =Y11+AD11 -> 0 | AN11: =AN10 -> 63 | AO11: =(AN11/100)*3000 -> 1890 | AP11: =AP10 -> 69 | AQ11: =(AP11/100)*3000 -> 2070 | AR11: =AR10 -> 69 | AS11: =(AR11/100)*3000 -> 2070 | AT11: =SUM(AO11+AQ11+AS11) -> 6030 | AU11: =AT10-AT11+AV11 -> 0 | AX11: =IF(AV11>0,AW11,AX10) -> 0.8
A12: =ELEC!C10 -> 44082 | B12: 197.2 | C12: 204 | D12: =C11-C12 -> 9 | E12: =D12*8.38 -> 75.42 | F12: 1648 | G12: =F12-F11 -> 0 | H12: =H11 -> 357868 | I12: =SUM(H12-H11) -> 0 | J12: =IF(G12>0,I12/G12,0) -> 0 | K12: =K11 -> 2110 | L12: =K12-K11 -> 0 | M12: =M11 -> 154820 | N12: =M12-M11 -> 0 | O12: =O11 -> 211.875 | P12: =P11 -> 1839 | Q12: =Q11 -> 156094 | R12: =Q12-Q11 -> 0 | S12: =SUM(P12-P11) -> 0 | T12: =SUM(S12*$T$2) -> 0 | U12: =SUM(G12+L12+S12) -> 0 | V12: =R12+N12+I12:I12 -> 0 | W12: =SUM(V12/U12) -> #DIV/0! | X12: 2448 | Y12: =X12-X11 -> 0 | Z12: =Z11 -> 137506 | AA12: =Z12-Z11 -> 0 | AB12: =SUM(Y12*$AB$2) -> 0 | AC12: =AC11 -> 1933 | AD12: =AC12-AC11 -> 0 | AE12: =AE11 -> 365210.2 | AF12: =AE12-AE11 -> 0 | AG12: =IF(AD12>0,AF12/AD12,0) -> 0 | AH12: =AF12+AA12 -> 0 | AI12: =SUM(AH12+V12) -> 0 | AJ12: =-tanks!AW13 -> 0 | AK12: =SUM(AJ12-AI12) -> 0 | AL12: =S12+L12+G12 -> 0 | AM12: =Y12+AD12 -> 0 | AN12: =AN11 -> 63 | AO12: =(AN12/100)*3000 -> 1890 | AP12: =AP11 -> 69 | AQ12: =(AP12/100)*3000 -> 2070 | AR12: =AR11 -> 69 | AS12: =(AR12/100)*3000 -> 2070 | AT12: =SUM(AO12+AQ12+AS12) -> 6030 | AU12: =AT11-AT12+AV12 -> 0 | AX12: =IF(AV12>0,AW12,AX11) -> 0.8
A13: =ELEC!C11 -> 44083 | B13: 194 | C13: 201 | D13: =C12-C13 -> 3 | E13: =D13*8.38 -> 25.14 | F13: =F12 -> 1648 | G13: =F13-F12 -> 0 | H13: =H12 -> 357868 | I13: =SUM(H13-H12) -> 0 | J13: =IF(G13>0,I13/G13,0) -> 0 | K13: =K12 -> 2110 | L13: =K13-K12 -> 0 | M13: =M12 -> 154820 | N13: =M13-M12 -> 0 | O13: =O12 -> 211.875 | P13: =P12 -> 1839 | Q13: =Q12 -> 156094 | R13: =Q13-Q12 -> 0 | S13: =SUM(P13-P12) -> 0 | T13: =SUM(S13*$T$2) -> 0 | U13: =SUM(G13+L13+S13) -> 0 | V13: =R13+N13+I13:I13 -> 0 | W13: =SUM(V13/U13) -> #DIV/0! | X13: =X12 -> 2448 | Y13: =X13-X12 -> 0 | Z13: =Z12 -> 137506 | AA13: =Z13-Z12 -> 0 | AB13: =SUM(Y13*$AB$2) -> 0 | AC13: =AC12 -> 1933 | AD13: =AC13-AC12 -> 0 | AE13: =AE12 -> 365210.2 | AF13: =AE13-AE12 -> 0 | AG13: =IF(AD13>0,AF13/AD13,0) -> 0 | AH13: =AF13+AA13 -> 0 | AI13: =SUM(AH13+V13) -> 0 | AJ13: =-tanks!AW14 -> 0 | AK13: =SUM(AJ13-AI13) -> 0 | AL13: =S13+L13+G13 -> 0 | AM13: =Y13+AD13 -> 0 | AN13: =AN12 -> 63 | AO13: =(AN13/100)*3000 -> 1890 | AP13: 57 | AQ13: =(AP13/100)*3000 -> 1710 | AR13: =AR12 -> 69 | AS13: =(AR13/100)*3000 -> 2070 | AT13: =SUM(AO13+AQ13+AS13) -> 5670 | AU13: =AT12-AT13+AV13 -> 360 | AX13: =IF(AV13>0,AW13,AX12) -> 0.8
A14: =ELEC!C12 -> 44084 | B14: 245 | C14: 250 | D14: =C13-C14 -> -49 | E14: =D14*8.38 -> -410.62 | F14: =F13 -> 1648 | G14: =F14-F13 -> 0 | H14: =H13 -> 357868 | I14: =SUM(H14-H13) -> 0 | J14: =IF(G14>0,I14/G14,0) -> 0 | K14: =K13 -> 2110 | L14: =K14-K13 -> 0 | M14: =M13 -> 154820 | N14: =M14-M13 -> 0 | O14: =O13 -> 211.875 | P14: =P13 -> 1839 | Q14: =Q13 -> 156094 | R14: =Q14-Q13 -> 0 | S14: =SUM(P14-P13) -> 0 | T14: =SUM(S14*$T$2) -> 0 | U14: =SUM(G14+L14+S14) -> 0 | V14: =R14+N14+I14:I14 -> 0 | W14: =SUM(V14/U14) -> #DIV/0! | X14: =X13 -> 2448 | Y14: =X14-X13 -> 0 | Z14: =Z13 -> 137506 | AA14: =Z14-Z13 -> 0 | AB14: =SUM(Y14*$AB$2) -> 0 | AC14: =AC13 -> 1933 | AD14: =AC14-AC13 -> 0 | AE14: =AE13 -> 365210.2 | AF14: =AE14-AE13 -> 0 | AG14: =IF(AD14>0,AF14/AD14,0) -> 0 | AH14: =AF14+AA14 -> 0 | AI14: =SUM(AH14+V14) -> 0 | AJ14: =-tanks!AW15 -> 0 | AK14: =SUM(AJ14-AI14) -> 0 | AL14: =S14+L14+G14 -> 0 | AM14: =Y14+AD14 -> 0 | AN14: =AN13 -> 63 | AO14: =(AN14/100)*3000 -> 1890 | AP14: =AP13 -> 57 | AQ14: =(AP14/100)*3000 -> 1710 | AR14: =AR13 -> 69 | AS14: =(AR14/100)*3000 -> 2070 | AT14: =SUM(AO14+AQ14+AS14) -> 5670 | AU14: =AT13-AT14+AV14 -> 0 | AX14: =IF(AV14>0,AW14,AX13) -> 0.8
A15: =ELEC!C13 -> 44085 | B15: 241 | C15: 247 | D15: =C14-C15 -> 3 | E15: =D15*8.38 -> 25.14 | F15: =F14 -> 1648 | G15: =F15-F14 -> 0 | H15: =H14 -> 357868 | I15: =SUM(H15-H14) -> 0 | J15: =IF(G15>0,I15/G15,0) -> 0 | K15: =K14 -> 2110 | L15: =K15-K14 -> 0 | M15: =M14 -> 154820 | N15: =M15-M14 -> 0 | O15: =O14 -> 211.875 | P15: =P14 -> 1839 | Q15: =Q14 -> 156094 | R15: =Q15-Q14 -> 0 | S15: =SUM(P15-P14) -> 0 | T15: =SUM(S15*$T$2) -> 0 | U15: =SUM(G15+L15+S15) -> 0 | V15: =R15+N15+I15:I15 -> 0 | W15: =SUM(V15/U15) -> #DIV/0! | X15: =X14 -> 2448 | Y15: =X15-X14 -> 0 | Z15: =Z14 -> 137506 | AA15: =Z15-Z14 -> 0 | AB15: =SUM(Y15*$AB$2) -> 0 | AC15: =AC14 -> 1933 | AD15: =AC15-AC14 -> 0 | AE15: =AE14 -> 365210.2 | AF15: =AE15-AE14 -> 0 | AG15: =IF(AD15>0,AF15/AD15,0) -> 0 | AH15: =AF15+AA15 -> 0 | AI15: =SUM(AH15+V15) -> 0 | AJ15: =-tanks!AW16 -> 0 | AK15: =SUM(AJ15-AI15) -> 0 | AL15: =S15+L15+G15 -> 0 | AM15: =Y15+AD15 -> 0 | AN15: =AN14 -> 63 | AO15: =(AN15/100)*3000 -> 1890 | AP15: =AP14 -> 57 | AQ15: =(AP15/100)*3000 -> 1710 | AR15: =AR14 -> 69 | AS15: =(AR15/100)*3000 -> 2070 | AT15: =SUM(AO15+AQ15+AS15) -> 5670 | AU15: =AT14-AT15+AV15 -> 0 | AX15: =IF(AV15>0,AW15,AX14) -> 0.8
A16: =ELEC!C14 -> 44086 | B16: 238 | C16: 243.2 | D16: =C15-C16 -> 3.8 | E16: =D16*8.38 -> 31.844 | F16: =F15 -> 1648 | G16: =F16-F15 -> 0 | H16: =H15 -> 357868 | I16: =SUM(H16-H15) -> 0 | J16: =IF(G16>0,I16/G16,0) -> 0 | K16: =K15 -> 2110 | L16: =K16-K15 -> 0 | M16: =M15 -> 154820 | N16: =M16-M15 -> 0 | O16: =O15 -> 211.875 | P16: =P15 -> 1839 | Q16: =Q15 -> 156094 | R16: =Q16-Q15 -> 0 | S16: =SUM(P16-P15) -> 0 | T16: =SUM(S16*$T$2) -> 0 | U16: =SUM(G16+L16+S16) -> 0 | V16: =R16+N16+I16:I16 -> 0 | W16: =SUM(V16/U16) -> #DIV/0! | X16: =X15 -> 2448 | Y16: =X16-X15 -> 0 | Z16: =Z15 -> 137506 | AA16: =Z16-Z15 -> 0 | AB16: =SUM(Y16*$AB$2) -> 0 | AC16: =AC15 -> 1933 | AD16: =AC16-AC15 -> 0 | AE16: =AE15 -> 365210.2 | AF16: =AE16-AE15 -> 0 | AG16: =IF(AD16>0,AF16/AD16,0) -> 0 | AH16: =AF16+AA16 -> 0 | AI16: =SUM(AH16+V16) -> 0 | AJ16: =-tanks!AW17 -> 0 | AK16: =SUM(AJ16-AI16) -> 0 | AL16: =S16+L16+G16 -> 0 | AM16: =Y16+AD16 -> 0 | AN16: =AN15 -> 63 | AO16: =(AN16/100)*3000 -> 1890 | AP16: =AP15 -> 57 | AQ16: =(AP16/100)*3000 -> 1710 | AR16: =AR15 -> 69 | AS16: =(AR16/100)*3000 -> 2070 | AT16: =SUM(AO16+AQ16+AS16) -> 5670 | AU16: =AT15-AT16+AV16 -> 0 | AX16: =IF(AV16>0,AW16,AX15) -> 0.8
A17: =ELEC!C15 -> 44087 | B17: 235 | C17: 241.2 | D17: =C16-C17 -> 2 | E17: =D17*8.38 -> 16.76 | F17: 1648 | G17: =F17-F16 -> 0 | H17: =H16 -> 357868 | I17: =SUM(H17-H16) -> 0 | J17: =IF(G17>0,I17/G17,0) -> 0 | K17: =K16 -> 2110 | L17: =K17-K16 -> 0 | M17: =M16 -> 154820 | N17: =M17-M16 -> 0 | O17: =O16 -> 211.875 | P17: =P16 -> 1839 | Q17: =Q16 -> 156094 | R17: =Q17-Q16 -> 0 | S17: =SUM(P17-P16) -> 0 | T17: =SUM(S17*$T$2) -> 0 | U17: =SUM(G17+L17+S17) -> 0 | V17: =R17+N17+I17:I17 -> 0 | X17: =X16 -> 2448 | Y17: =X17-X16 -> 0 | Z17: =Z16 -> 137506 | AA17: =Z17-Z16 -> 0 | AB17: =SUM(Y17*$AB$2) -> 0 | AC17: =AC16 -> 1933 | AD17: =AC17-AC16 -> 0 | AE17: =AE16 -> 365210.2 | AF17: =AE17-AE16 -> 0 | AG17: =IF(AD17>0,AF17/AD17,0) -> 0 | AH17: =AF17+AA17 -> 0 | AI17: =SUM(AH17+V17) -> 0 | AJ17: =-tanks!AW18 -> 0 | AK17: =SUM(AJ17-AI17) -> 0 | AL17: =S17+L17+G17 -> 0 | AM17: =Y17+AD17 -> 0 | AN17: =AN16 -> 63 | AO17: =(AN17/100)*3000 -> 1890 | AP17: 54 | AQ17: =(AP17/100)*3000 -> 1620 | AR17: =AR16 -> 69 | AS17: =(AR17/100)*3000 -> 2070 | AT17: =SUM(AO17+AQ17+AS17) -> 5580 | AU17: =AT16-AT17+AV17 -> 90 | AX17: =IF(AV17>0,AW17,AX16) -> 0.8
A18: =ELEC!C16 -> 44088 | B18: 233.4 | C18: 239 | D18: =C17-C18 -> 2.2 | E18: =D18*8.38 -> 18.436 | F18: =F17 -> 1648 | G18: =F18-F17 -> 0 | H18: =H17 -> 357868 | I18: =SUM(H18-H17) -> 0 | J18: =IF(G18>0,I18/G18,0) -> 0 | K18: =K17 -> 2110 | L18: =K18-K17 -> 0 | M18: =M17 -> 154820 | N18: =M18-M17 -> 0 | O18: =O17 -> 211.875 | P18: =P17 -> 1839 | Q18: =Q17 -> 156094 | R18: =Q18-Q17 -> 0 | S18: =SUM(P18-P17) -> 0 | T18: =SUM(S18*$T$2) -> 0 | U18: =SUM(G18+L18+S18) -> 0 | V18: =R18+N18+I18:I18 -> 0 | X18: =X17 -> 2448 | Y18: =X18-X17 -> 0 | Z18: =Z17 -> 137506 | AA18: =Z18-Z17 -> 0 | AB18: =SUM(Y18*$AB$2) -> 0 | AC18: =AC17 -> 1933 | AD18: =AC18-AC17 -> 0 | AE18: =AE17 -> 365210.2 | AF18: =AE18-AE17 -> 0 | AG18: =IF(AD18>0,AF18/AD18,0) -> 0 | AH18: =AF18+AA18 -> 0 | AI18: =SUM(AH18+V18) -> 0 | AJ18: =-tanks!AW19 -> 0 | AK18: =SUM(AJ18-AI18) -> 0 | AL18: =S18+L18+G18 -> 0 | AM18: =Y18+AD18 -> 0 | AN18: 63 | AO18: =(AN18/100)*3000 -> 1890 | AP18: 54 | AQ18: =(AP18/100)*3000 -> 1620 | AR18: 69 | AS18: =(AR18/100)*3000 -> 2070 | AT18: =SUM(AO18+AQ18+AS18) -> 5580 | AU18: =AT17-AT18+AV18 -> 0 | AX18: =IF(AV18>0,AW18,AX17) -> 0.8
A19: =ELEC!C17 -> 44089 | B19: 229 | C19: 236 | D19: =C18-C19 -> 3 | E19: =D19*8.38 -> 25.14 | F19: 1648 | G19: =F19-F18 -> 0 | H19: =H18 -> 357868 | I19: =SUM(H19-H18) -> 0 | J19: =IF(G19>0,I19/G19,0) -> 0 | K19: =K18 -> 2110 | L19: =K19-K18 -> 0 | M19: =M18 -> 154820 | N19: =M19-M18 -> 0 | O19: =O18 -> 211.875 | P19: =P18 -> 1839 | Q19: =Q18 -> 156094 | R19: =Q19-Q18 -> 0 | S19: =SUM(P19-P18) -> 0 | T19: =SUM(S19*$T$2) -> 0 | U19: =SUM(G19+L19+S19) -> 0 | V19: =R19+N19+I19:I19 -> 0 | X19: =X18 -> 2448 | Y19: =X19-X18 -> 0 | Z19: =Z18 -> 137506 | AA19: =Z19-Z18 -> 0 | AB19: =SUM(Y19*$AB$2) -> 0 | AC19: =AC18 -> 1933 | AD19: =AC19-AC18 -> 0 | AE19: =AE18 -> 365210.2 | AF19: =AE19-AE18 -> 0 | AG19: =IF(AD19>0,AF19/AD19,0) -> 0 | AH19: =AF19+AA19 -> 0 | AI19: =SUM(AH19+V19) -> 0 | AJ19: =-tanks!AW20 -> 0 | AK19: =SUM(AJ19-AI19) -> 0 | AL19: =S19+L20+G19 -> 0 | AM19: =Y19+AD19 -> 0 | AN19: 63 | AO19: =(AN19/100)*3000 -> 1890 | AP19: 53 | AQ19: =(AP19/100)*3000 -> 1590 | AR19: 69 | AS19: =(AR19/100)*3000 -> 2070 | AT19: =SUM(AO19+AQ19+AS19) -> 5550 | AU19: =AT18-AT19+AV19 -> 30 | AX19: =IF(AV19>0,AW19,AX18) -> 0.8
A20: =ELEC!C18 -> 44090 | B20: 226.4 | C20: 232.4 | D20: =C19-C20 -> 3.6 | E20: =D20*8.38 -> 30.168 | F20: =F19 -> 1648 | G20: =F20-F19 -> 0 | H20: =H19 -> 357868 | I20: =SUM(H20-H19) -> 0 | J20: =IF(G20>0,I20/G20,0) -> 0 | K20: =K19 -> 2110 | L20: =K20-K19 -> 0 | M20: =M19 -> 154820 | N20: =M20-M19 -> 0 | O20: =O19 -> 211.875 | P20: =P19 -> 1839 | Q20: =Q19 -> 156094 | R20: =Q20-Q19 -> 0 | S20: =SUM(P20-P19) -> 0 | T20: =SUM(S20*$T$2) -> 0 | U20: =SUM(G20+L20+S20) -> 0 | V20: =R20+N20+I20:I20 -> 0 | X20: =X19 -> 2448 | Y20: =X20-X19 -> 0 | Z20: =Z19 -> 137506 | AA20: =Z20-Z19 -> 0 | AB20: =SUM(Y20*$AB$2) -> 0 | AC20: =AC19 -> 1933 | AD20: =AC20-AC19 -> 0 | AE20: =AE19 -> 365210.2 | AF20: =AE20-AE19 -> 0 | AG20: =IF(AD20>0,AF20/AD20,0) -> 0 | AH20: =AF20+AA20 -> 0 | AI20: =SUM(AH20+V20) -> 0 | AJ20: =-tanks!AW21 -> 0 | AK20: =SUM(AJ20-AI20) -> 0 | AL20: =S20+L21+G20 -> 0 | AM20: =Y20+AD20 -> 0 | AN20: =AN19 -> 63 | AO20: =(AN20/100)*3000 -> 1890 | AP20: 52 | AQ20: =(AP20/100)*3000 -> 1560 | AR20: 68 | AS20: =(AR20/100)*3000 -> 2040 | AT20: =SUM(AO20+AQ20+AS20) -> 5490 | AU20: =AT19-AT20+AV20 -> 60 | AX20: =IF(AV20>0,AW20,AX19) -> 0.8
A21: =ELEC!C19 -> 44091 | B21: 225 | C21: 231 | D21: =C20-C21 -> 1.4 | E21: =D21*8.38 -> 11.732 | F21: =F20 -> 1648 | G21: =F21-F20 -> 0 | H21: =H20 -> 357868 | I21: =SUM(H21-H20) -> 0 | J21: =IF(G21>0,I21/G21,0) -> 0 | K21: =K20 -> 2110 | L21: =K21-K20 -> 0 | M21: =M20 -> 154820 | N21: =M21-M20 -> 0 | O21: =O20 -> 211.875 | P21: =P20 -> 1839 | Q21: =Q20 -> 156094 | R21: =Q21-Q20 -> 0 | S21: =SUM(P21-P20) -> 0 | T21: =SUM(S21*$T$2) -> 0 | U21: =SUM(G21+L21+S21) -> 0 | V21: =R21+N21+I21:I21 -> 0 | X21: =X20 -> 2448 | Y21: =X21-X20 -> 0 | Z21: =Z20 -> 137506 | AA21: =Z21-Z20 -> 0 | AB21: =SUM(Y21*$AB$2) -> 0 | AC21: =AC20 -> 1933 | AD21: =AC21-AC20 -> 0 | AE21: =AE20 -> 365210.2 | AF21: =AE21-AE20 -> 0 | AG21: =IF(AD21>0,AF21/AD21,0) -> 0 | AH21: =AF21+AA21 -> 0 | AI21: =SUM(AH21+V21) -> 0 | AJ21: =-tanks!AW22 -> 0 | AK21: =SUM(AJ21-AI21) -> 0 | AL21: =S21+L21+G21 -> 0 | AM21: =Y21+AD21 -> 0 | AN21: =AN20 -> 63 | AO21: =(AN21/100)*3000 -> 1890 | AP21: =AP20 -> 52 | AQ21: =(AP21/100)*3000 -> 1560 | AR21: =AR20 -> 68 | AS21: =(AR21/100)*3000 -> 2040 | AT21: =SUM(AO21+AQ21+AS21) -> 5490 | AU21: =AT20-AT21+AV21 -> 0 | AX21: =IF(AV21>0,AW21,AX20) -> 0.8
A22: =ELEC!C20 -> 44092 | B22: 223 | C22: 229.1 | D22: =C21-C22 -> 1.9 | E22: =D22*8.38 -> 15.922 | F22: =F21 -> 1648 | G22: =F22-F21 -> 0 | H22: =H21 -> 357868 | I22: =SUM(H22-H21) -> 0 | J22: =IF(G22>0,I22/G22,0) -> 0 | K22: =K21 -> 2110 | L22: =K22-K21 -> 0 | M22: =M21 -> 154820 | N22: =M22-M21 -> 0 | O22: =O21 -> 211.875 | P22: =P21 -> 1839 | Q22: =Q21 -> 156094 | R22: =Q22-Q21 -> 0 | S22: =SUM(P22-P21) -> 0 | T22: =SUM(S22*$T$2) -> 0 | U22: =SUM(G22+L22+S22) -> 0 | V22: =R22+N22+I22:I22 -> 0 | X22: =X21 -> 2448 | Y22: =X22-X21 -> 0 | Z22: =Z21 -> 137506 | AA22: =Z22-Z21 -> 0 | AB22: =SUM(Y22*$AB$2) -> 0 | AC22: =AC21 -> 1933 | AD22: =AC22-AC21 -> 0 | AE22: =AE21 -> 365210.2 | AF22: =AE22-AE21 -> 0 | AG22: =IF(AD22>0,AF22/AD22,0) -> 0 | AH22: =AF22+AA22 -> 0 | AI22: =SUM(AH22+V22) -> 0 | AJ22: =-tanks!AW23 -> 0 | AK22: =SUM(AJ22-AI22) -> 0 | AL22: =S22+L22+G22 -> 0 | AM22: =Y22+AD22 -> 0 | AN22: 62 | AO22: =(AN22/100)*3000 -> 1860 | AP22: =AP21 -> 52 | AQ22: =(AP22/100)*3000 -> 1560 | AR22: =AR21 -> 68 | AS22: =(AR22/100)*3000 -> 2040 | AT22: =SUM(AO22+AQ22+AS22) -> 5460 | AU22: =AT21-AT22+AV22 -> 30 | AX22: =IF(AV22>0,AW22,AX21) -> 0.8
A23: =ELEC!C21 -> 44093 | B23: 220 | C23: 226 | D23: =C22-C23 -> 3.1 | E23: =D23*8.38 -> 25.978 | F23: =F22 -> 1648 | G23: =F23-F22 -> 0 | H23: =H22 -> 357868 | I23: =SUM(H23-H22) -> 0 | J23: =IF(G23>0,I23/G23,0) -> 0 | K23: =K22 -> 2110 | L23: =K23-K22 -> 0 | M23: =M22 -> 154820 | N23: =M23-M22 -> 0 | O23: =O22 -> 211.875 | P23: =P22 -> 1839 | Q23: =Q22 -> 156094 | R23: =Q23-Q22 -> 0 | S23: =SUM(P23-P22) -> 0 | T23: =SUM(S23*$T$2) -> 0 | U23: =SUM(G23+L23+S23) -> 0 | V23: =R23+N23+I23:I23 -> 0 | X23: =X22 -> 2448 | Y23: =X23-X22 -> 0 | Z23: =Z22 -> 137506 | AA23: =Z23-Z22 -> 0 | AB23: =SUM(Y23*$AB$2) -> 0 | AC23: =AC22 -> 1933 | AD23: =AC23-AC22 -> 0 | AE23: =AE22 -> 365210.2 | AF23: =AE23-AE22 -> 0 | AG23: =IF(AD23>0,AF23/AD23,0) -> 0 | AH23: =AF23+AA23 -> 0 | AI23: =SUM(AH23+V23) -> 0 | AJ23: =-tanks!AW24 -> 0 | AK23: =SUM(AJ23-AI23) -> 0 | AL23: =S23+L23+G23 -> 0 | AM23: =Y23+AD23 -> 0 | AN23: =AN22 -> 62 | AO23: =(AN23/100)*3000 -> 1860 | AP23: =AP22 -> 52 | AQ23: =(AP23/100)*3000 -> 1560 | AR23: =AR22 -> 68 | AS23: =(AR23/100)*3000 -> 2040 | AT23: =SUM(AO23+AQ23+AS23) -> 5460 | AU23: =AT22-AT23+AV23 -> 0 | AX23: =IF(AV23>0,AW23,AX22) -> 0.8
A24: =ELEC!C22 -> 44094 | B24: 218 | C24: 224 | D24: =C23-C24 -> 2 | E24: =D24*8.38 -> 16.76 | F24: 1648 | G24: =F24-F23 -> 0 | H24: =H23 -> 357868 | I24: =SUM(H24-H23) -> 0 | J24: =IF(G24>0,I24/G24,0) -> 0 | K24: =K23 -> 2110 | L24: =K24-K23 -> 0 | M24: =M23 -> 154820 | N24: =M24-M23 -> 0 | O24: =O23 -> 211.875 | P24: =P23 -> 1839 | Q24: =Q23 -> 156094 | R24: =Q24-Q23 -> 0 | S24: =SUM(P24-P23) -> 0 | T24: =SUM(S24*$T$2) -> 0 | U24: =SUM(G24+L24+S24) -> 0 | V24: =R24+N24+I24:I24 -> 0 | X24: =X23 -> 2448 | Y24: =X24-X23 -> 0 | Z24: =Z23 -> 137506 | AA24: =Z24-Z23 -> 0 | AB24: =SUM(Y24*$AB$2) -> 0 | AC24: =AC23 -> 1933 | AD24: =AC24-AC23 -> 0 | AE24: =AE23 -> 365210.2 | AF24: =AE24-AE23 -> 0 | AG24: =IF(AD24>0,AF24/AD24,0) -> 0 | AH24: =AF24+AA24 -> 0 | AI24: =SUM(AH24+V24) -> 0 | AJ24: =-tanks!AW25 -> 0 | AK24: =SUM(AJ24-AI24) -> 0 | AL24: =S24+L24+G24 -> 0 | AM24: =Y24+AD24 -> 0 | AN24: 62 | AO24: =(AN24/100)*3000 -> 1860 | AP24: 51 | AQ24: =(AP24/100)*3000 -> 1530 | AR24: 68 | AS24: =(AR24/100)*3000 -> 2040 | AT24: =SUM(AO24+AQ24+AS24) -> 5430 | AU24: =AT23-AT24+AV24 -> 30 | AX24: =IF(AV24>0,AW24,AX23) -> 0.8
A25: =ELEC!C23 -> 44095 | B25: 215 | C25: 221 | D25: =C24-C25 -> 3 | E25: =D25*8.38 -> 25.14 | F25: =F24 -> 1648 | G25: =F25-F24 -> 0 | H25: =H24 -> 357868 | I25: =SUM(H25-H24) -> 0 | J25: =IF(G25>0,I25/G25,0) -> 0 | K25: =K24 -> 2110 | L25: =K25-K24 -> 0 | M25: =M24 -> 154820 | N25: =M25-M24 -> 0 | O25: =O24 -> 211.875 | P25: =P24 -> 1839 | Q25: =Q24 -> 156094 | R25: =Q25-Q24 -> 0 | S25: =SUM(P25-P24) -> 0 | T25: =SUM(S25*$T$2) -> 0 | U25: =SUM(G25+L25+S25) -> 0 | V25: =R25+N25+I25:I25 -> 0 | X25: =X24 -> 2448 | Y25: =X25-X24 -> 0 | Z25: =Z24 -> 137506 | AA25: =Z25-Z24 -> 0 | AB25: =SUM(Y25*$AB$2) -> 0 | AC25: =AC24 -> 1933 | AD25: =AC25-AC24 -> 0 | AE25: =AE24 -> 365210.2 | AF25: =AE25-AE24 -> 0 | AG25: =IF(AD25>0,AF25/AD25,0) -> 0 | AH25: =AF25+AA25 -> 0 | AI25: =SUM(AH25+V25) -> 0 | AJ25: =-tanks!AW26 -> 0 | AK25: =SUM(AJ25-AI25) -> 0 | AL25: =S25+L25+G25 -> 0 | AM25: =Y25+AD25 -> 0 | AN25: =AN24 -> 62 | AO25: =(AN25/100)*3000 -> 1860 | AP25: =AP24 -> 51 | AQ25: =(AP25/100)*3000 -> 1530 | AR25: =AR24 -> 68 | AS25: =(AR25/100)*3000 -> 2040 | AT25: =SUM(AO25+AQ25+AS25) -> 5430 | AU25: =AT24-AT25+AV25 -> 0 | AX25: =IF(AV25>0,AW25,AX24) -> 0.8
A26: =ELEC!C24 -> 44096 | B26: 211 | C26: 217 | D26: =C25-C26 -> 4 | E26: =D26*8.38 -> 33.52 | F26: =F25 -> 1648 | G26: =F26-F25 -> 0 | H26: =H25 -> 357868 | I26: =SUM(H26-H25) -> 0 | J26: =IF(G26>0,I26/G26,0) -> 0 | K26: =K25 -> 2110 | L26: =K26-K25 -> 0 | M26: =M25 -> 154820 | N26: =M26-M25 -> 0 | O26: =O25 -> 211.875 | P26: =P25 -> 1839 | Q26: =Q25 -> 156094 | R26: =Q26-Q25 -> 0 | S26: =SUM(P26-P25) -> 0 | T26: =SUM(S26*$T$2) -> 0 | U26: =SUM(G26+L26+S26) -> 0 | V26: =R26+N26+I26:I26 -> 0 | X26: =X25 -> 2448 | Y26: =X26-X25 -> 0 | Z26: =Z25 -> 137506 | AA26: =Z26-Z25 -> 0 | AB26: =SUM(Y26*$AB$2) -> 0 | AC26: =AC25 -> 1933 | AD26: =AC26-AC25 -> 0 | AE26: =AE25 -> 365210.2 | AF26: =AE26-AE25 -> 0 | AG26: =IF(AD26>0,AF26/AD26,0) -> 0 | AH26: =AF26+AA26 -> 0 | AI26: =SUM(AH26+V26) -> 0 | AJ26: =-tanks!AW27 -> 0 | AK26: =SUM(AJ26-AI26) -> 0 | AL26: =S26+L26+G26 -> 0 | AM26: =Y26+AD26 -> 0 | AN26: =AN25 -> 62 | AO26: =(AN26/100)*3000 -> 1860 | AP26: =AP25 -> 51 | AQ26: =(AP26/100)*3000 -> 1530 | AR26: =AR25 -> 68 | AS26: =(AR26/100)*3000 -> 2040 | AT26: =SUM(AO26+AQ26+AS26) -> 5430 | AU26: =AT25-AT26+AV26 -> 0 | AX26: =IF(AV26>0,AW26,AX25) -> 0.8
A27: =ELEC!C25 -> 44097 | B27: 209 | C27: 215 | D27: =C26-C27 -> 2 | E27: =D27*8.38 -> 16.76 | F27: =F26 -> 1648 | G27: =F27-F26 -> 0 | H27: =H26 -> 357868 | I27: =SUM(H27-H26) -> 0 | J27: =IF(G27>0,I27/G27,0) -> 0 | K27: =K26 -> 2110 | L27: =K27-K26 -> 0 | M27: =M26 -> 154820 | N27: =M27-M26 -> 0 | O27: =O26 -> 211.875 | P27: =P26 -> 1839 | Q27: =Q26 -> 156094 | R27: =Q27-Q26 -> 0 | S27: =SUM(P27-P26) -> 0 | T27: =SUM(S27*$T$2) -> 0 | U27: =SUM(G27+L27+S27) -> 0 | V27: =R27+N27+I27:I27 -> 0 | X27: =X26 -> 2448 | Y27: =X27-X26 -> 0 | Z27: =Z26 -> 137506 | AA27: =Z27-Z26 -> 0 | AB27: =SUM(Y27*$AB$2) -> 0 | AC27: =AC26 -> 1933 | AD27: =AC27-AC26 -> 0 | AE27: =AE26 -> 365210.2 | AF27: =AE27-AE26 -> 0 | AG27: =IF(AD27>0,AF27/AD27,0) -> 0 | AH27: =AF27+AA27 -> 0 | AI27: =SUM(AH27+V27) -> 0 | AJ27: =-tanks!AW28 -> 0 | AK27: =SUM(AJ27-AI27) -> 0 | AL27: =S27+L27+G27 -> 0 | AM27: =Y27+AD27 -> 0 | AN27: =AN26 -> 62 | AO27: =(AN27/100)*3000 -> 1860 | AP27: =AP26 -> 51 | AQ27: =(AP27/100)*3000 -> 1530 | AR27: =AR26 -> 68 | AS27: =(AR27/100)*3000 -> 2040 | AT27: =SUM(AO27+AQ27+AS27) -> 5430 | AU27: =AT26-AT27+AV27 -> 0 | AX27: =IF(AV27>0,AW27,AX26) -> 0.8
A28: =ELEC!C26 -> 44098 | B28: 245 | C28: 250.3 | D28: =C27-C28 -> -35.3 | E28: =D28*8.38 -> -295.814 | F28: =F27 -> 1648 | G28: =F28-F27 -> 0 | H28: =H27 -> 357868 | I28: =SUM(H28-H27) -> 0 | J28: =IF(G28>0,I28/G28,0) -> 0 | K28: =K27 -> 2110 | L28: =K28-K27 -> 0 | M28: =M27 -> 154820 | N28: =M28-M27 -> 0 | O28: =O27 -> 211.875 | P28: =P27 -> 1839 | Q28: =Q27 -> 156094 | R28: =Q28-Q27 -> 0 | S28: =SUM(P28-P27) -> 0 | T28: =SUM(S28*$T$2) -> 0 | U28: =SUM(G28+L28+S28) -> 0 | V28: =R28+N28+I28:I28 -> 0 | X28: =X27 -> 2448 | Y28: =X28-X27 -> 0 | Z28: =Z27 -> 137506 | AA28: =Z28-Z27 -> 0 | AB28: =SUM(Y28*$AB$2) -> 0 | AC28: =AC27 -> 1933 | AD28: =AC28-AC27 -> 0 | AE28: =AE27 -> 365210.2 | AF28: =AE28-AE27 -> 0 | AG28: =IF(AD28>0,AF28/AD28,0) -> 0 | AH28: =AF28+AA28 -> 0 | AI28: =SUM(AH28+V28) -> 0 | AJ28: =-tanks!AW29 -> 0 | AK28: =SUM(AJ28-AI28) -> 0 | AL28: =S28+L28+G28 -> 0 | AM28: =Y28+AD28 -> 0 | AN28: =AN27 -> 62 | AO28: =(AN28/100)*3000 -> 1860 | AP28: =AP27 -> 51 | AQ28: =(AP28/100)*3000 -> 1530 | AR28: =AR27 -> 68 | AS28: =(AR28/100)*3000 -> 2040 | AT28: =SUM(AO28+AQ28+AS28) -> 5430 | AU28: =AT27-AT28+AV28 -> 0 | AX28: =IF(AV28>0,AW28,AX27) -> 0.8
A29: =ELEC!C27 -> 44099 | B29: 242 | C29: 249 | D29: =C28-C29 -> 1.3 | E29: =D29*8.38 -> 10.894 | F29: =F28 -> 1648 | G29: =F29-F28 -> 0 | H29: =H28 -> 357868 | I29: =SUM(H29-H28) -> 0 | J29: =IF(G29>0,I29/G29,0) -> 0 | K29: =K28 -> 2110 | L29: =K29-K28 -> 0 | M29: =M28 -> 154820 | N29: =M29-M28 -> 0 | O29: =O28 -> 211.875 | P29: =P28 -> 1839 | Q29: =Q28 -> 156094 | R29: =Q29-Q28 -> 0 | S29: =SUM(P29-P28) -> 0 | T29: =SUM(S29*$T$2) -> 0 | U29: =SUM(G29+L29+S29) -> 0 | V29: =R29+N29+I29:I29 -> 0 | X29: =X28 -> 2448 | Y29: =X29-X28 -> 0 | Z29: =Z28 -> 137506 | AA29: =Z29-Z28 -> 0 | AB29: =SUM(Y29*$AB$2) -> 0 | AC29: =AC28 -> 1933 | AD29: =AC29-AC28 -> 0 | AE29: =AE28 -> 365210.2 | AF29: =AE29-AE28 -> 0 | AG29: =IF(AD29>0,AF29/AD29,0) -> 0 | AH29: =AF29+AA29 -> 0 | AI29: =SUM(AH29+V29) -> 0 | AJ29: =-tanks!AW30 -> 0 | AK29: =SUM(AJ29-AI29) -> 0 | AL29: =S29+L29+G29 -> 0 | AM29: =Y29+AD29 -> 0 | AN29: =AN28 -> 62 | AO29: =(AN29/100)*3000 -> 1860 | AP29: =AP28 -> 51 | AQ29: =(AP29/100)*3000 -> 1530 | AR29: =AR28 -> 68 | AS29: =(AR29/100)*3000 -> 2040 | AT29: =SUM(AO29+AQ29+AS29) -> 5430 | AU29: =AT28-AT29+AV29 -> 0 | AX29: =IF(AV29>0,AW29,AX28) -> 0.8
A30: =ELEC!C28 -> 44100 | B30: 240.2 | C30: 247 | D30: =C29-C30 -> 2 | E30: =D30*8.38 -> 16.76 | F30: 1648 | G30: =F30-F29 -> 0 | H30: =H29 -> 357868 | I30: =SUM(H30-H29) -> 0 | J30: =IF(G30>0,I30/G30,0) -> 0 | K30: =K29 -> 2110 | L30: =K30-K29 -> 0 | M30: =M29 -> 154820 | N30: =M30-M29 -> 0 | O30: =O29 -> 211.875 | P30: =P29 -> 1839 | Q30: =Q29 -> 156094 | R30: =Q30-Q29 -> 0 | S30: =SUM(P30-P29) -> 0 | T30: =SUM(S30*$T$2) -> 0 | U30: =SUM(G30+L30+S30) -> 0 | V30: =R30+N30+I30:I30 -> 0 | X30: =X29 -> 2448 | Y30: =X30-X29 -> 0 | Z30: =Z29 -> 137506 | AA30: =Z30-Z29 -> 0 | AB30: =SUM(Y30*$AB$2) -> 0 | AC30: =AC29 -> 1933 | AD30: =AC30-AC29 -> 0 | AE30: =AE29 -> 365210.2 | AF30: =AE30-AE29 -> 0 | AG30: =IF(AD30>0,AF30/AD30,0) -> 0 | AH30: =AF30+AA30 -> 0 | AI30: =SUM(AH30+V30) -> 0 | AJ30: =-tanks!AW31 -> 0 | AK30: =SUM(AJ30-AI30) -> 0 | AL30: =S30+L30+G30 -> 0 | AM30: =Y30+AD30 -> 0 | AN30: 62 | AO30: =(AN30/100)*3000 -> 1860 | AP30: 51 | AQ30: =(AP30/100)*3000 -> 1530 | AR30: 68 | AS30: =(AR30/100)*3000 -> 2040 | AT30: =SUM(AO30+AQ30+AS30) -> 5430 | AU30: =AT29-AT30+AV30 -> 0 | AX30: =IF(AV30>0,AW30,AX29) -> 0.8
A31: =ELEC!C29 -> 44101 | B31: 239.3 | C31: 246 | D31: =C30-C31 -> 1 | E31: =D31*8.38 -> 8.38 | F31: =F30 -> 1648 | G31: =F31-F30 -> 0 | H31: =H30 -> 357868 | I31: =SUM(H31-H30) -> 0 | J31: =IF(G31>0,I31/G31,0) -> 0 | K31: =K30 -> 2110 | L31: =K31-K30 -> 0 | M31: =M30 -> 154820 | N31: =M31-M30 -> 0 | O31: =O30 -> 211.875 | P31: =P30 -> 1839 | Q31: =Q30 -> 156094 | R31: =Q31-Q30 -> 0 | S31: =SUM(P31-P30) -> 0 | T31: =SUM(S31*$T$2) -> 0 | U31: =SUM(G31+L31+S31) -> 0 | V31: =R31+N31+I31:I31 -> 0 | X31: =X30 -> 2448 | Y31: =X31-X30 -> 0 | Z31: =Z30 -> 137506 | AA31: =Z31-Z30 -> 0 | AB31: =SUM(Y31*$AB$2) -> 0 | AC31: =AC30 -> 1933 | AD31: =AC31-AC30 -> 0 | AE31: =AE30 -> 365210.2 | AF31: =AE31-AE30 -> 0 | AG31: =IF(AD31>0,AF31/AD31,0) -> 0 | AH31: =AF31+AA31 -> 0 | AI31: =SUM(AH31+V31) -> 0 | AJ31: =-tanks!AW32 -> 0 | AK31: =SUM(AJ31-AI31) -> 0 | AL31: =S31+L31+G31 -> 0 | AM31: =Y31+AD31 -> 0 | AN31: 62 | AO31: =(AN31/100)*3000 -> 1860 | AP31: 51 | AQ31: =(AP31/100)*3000 -> 1530 | AR31: 68 | AS31: =(AR31/100)*3000 -> 2040 | AT31: =SUM(AO31+AQ31+AS31) -> 5430 | AU31: =AT30-AT31+AV31 -> 0 | AX31: =IF(AV31>0,AW31,AX30) -> 0.8
A32: =ELEC!C30 -> 44102 | B32: 238 | C32: 244 | D32: =C31-C32 -> 2 | E32: =D32*8.38 -> 16.76 | F32: 1648 | G32: =F32-F31 -> 0 | H32: =H31 -> 357868 | I32: =SUM(H32-H31) -> 0 | J32: =IF(G32>0,I32/G32,0) -> 0 | K32: =K31 -> 2110 | L32: =K32-K31 -> 0 | M32: =M31 -> 154820 | N32: =M32-M31 -> 0 | O32: =O31 -> 211.875 | P32: =P31 -> 1839 | Q32: =Q31 -> 156094 | R32: =Q32-Q31 -> 0 | S32: =SUM(P32-P31) -> 0 | T32: =SUM(S32*$T$2) -> 0 | U32: =SUM(G32+L32+S32) -> 0 | V32: =R32+N32+I32:I32 -> 0 | X32: =X31 -> 2448 | Y32: =X32-X31 -> 0 | Z32: =Z31 -> 137506 | AA32: =Z32-Z31 -> 0 | AB32: =SUM(Y32*$AB$2) -> 0 | AC32: =AC31 -> 1933 | AD32: =AC32-AC31 -> 0 | AE32: =AE31 -> 365210.2 | AF32: =AE32-AE31 -> 0 | AG32: =IF(AD32>0,AF32/AD32,0) -> 0 | AH32: =AF32+AA32 -> 0 | AI32: =SUM(AH32+V32) -> 0 | AJ32: =-tanks!AW33 -> 0 | AK32: =SUM(AJ32-AI32) -> 0 | AL32: =S32+L32+G32 -> 0 | AM32: =Y32+AD32 -> 0 | AN32: =AN31 -> 62 | AO32: =(AN32/100)*3000 -> 1860 | AP32: =AP31 -> 51 | AQ32: =(AP32/100)*3000 -> 1530 | AR32: =AR31 -> 68 | AS32: =(AR32/100)*3000 -> 2040 | AT32: =SUM(AO32+AQ32+AS32) -> 5430 | AU32: =AT31-AT32+AV32 -> 0 | AX32: =IF(AV32>0,AW32,AX31) -> 0.8
A33: =ELEC!C31 -> 44103 | B33: 255.2 | C33: 261 | D33: =C32-C33 -> -17 | E33: =D33*8.38 -> -142.46 | F33: 1648 | G33: =F33-F32 -> 0 | H33: =H32 -> 357868 | I33: =SUM(H33-H32) -> 0 | J33: =IF(G33>0,I33/G33,0) -> 0 | K33: =K32 -> 2110 | L33: =K33-K32 -> 0 | M33: =M32 -> 154820 | N33: =M33-M32 -> 0 | O33: =O32 -> 211.875 | P33: =P32 -> 1839 | Q33: =Q32 -> 156094 | R33: =Q33-Q32 -> 0 | S33: =SUM(P33-P32) -> 0 | T33: =SUM(S33*$T$2) -> 0 | U33: =SUM(G33+L33+S33) -> 0 | V33: =R33+N33+I33:I33 -> 0 | X33: =X32 -> 2448 | Y33: =X33-X32 -> 0 | Z33: =Z32 -> 137506 | AA33: =Z33-Z32 -> 0 | AB33: =SUM(Y33*$AB$2) -> 0 | AC33: =AC32 -> 1933 | AD33: =AC33-AC32 -> 0 | AE33: =AE32 -> 365210.2 | AF33: =AE33-AE32 -> 0 | AG33: =IF(AD33>0,AF33/AD33,0) -> 0 | AH33: =AF33+AA33 -> 0 | AI33: =SUM(AH33+V33) -> 0 | AJ33: =-tanks!AW34 -> 0 | AK33: =SUM(AJ33-AI33) -> 0 | AL33: =S33+L33+G33 -> 0 | AM33: =Y33+AD33 -> 0 | AN33: =AN32 -> 62 | AO33: =(AN33/100)*3000 -> 1860 | AP33: =AP32 -> 51 | AQ33: =(AP33/100)*3000 -> 1530 | AR33: =AR32 -> 68 | AS33: =(AR33/100)*3000 -> 2040 | AT33: =SUM(AO33+AQ33+AS33) -> 5430 | AU33: =AT32-AT33+AV33 -> 0 | AX33: =IF(AV33>0,AW33,AX32) -> 0.8
A34: =ELEC!C32 -> 44104 | B34: 251 | C34: 257 | D34: =C33-C34 -> 4 | E34: =D34*8.38 -> 33.52 | F34: =F33 -> 1648 | G34: =F34-F33 -> 0 | H34: =H33 -> 357868 | I34: =SUM(H34-H33) -> 0 | J34: =IF(G34>0,I34/G34,0) -> 0 | K34: =K33 -> 2110 | L34: =K34-K33 -> 0 | M34: =M33 -> 154820 | N34: =M34-M33 -> 0 | O34: =O33 -> 211.875 | P34: =P33 -> 1839 | Q34: =Q33 -> 156094 | R34: =Q34-Q33 -> 0 | S34: =SUM(P34-P33) -> 0 | T34: =SUM(S34*$T$2) -> 0 | U34: =SUM(G34+L34+S34) -> 0 | V34: =R34+N34+I34:I34 -> 0 | X34: =X33 -> 2448 | Y34: =X34-X33 -> 0 | Z34: =Z33 -> 137506 | AA34: =Z34-Z33 -> 0 | AB34: =SUM(Y34*$AB$2) -> 0 | AC34: =AC33 -> 1933 | AD34: =AC34-AC33 -> 0 | AE34: =AE33 -> 365210.2 | AF34: =AE34-AE33 -> 0 | AG34: =IF(AD34>0,AF34/AD34,0) -> 0 | AH34: =AF34+AA34 -> 0 | AI34: =SUM(AH34+V34) -> 0 | AJ34: =-tanks!AW35 -> 0 | AK34: =SUM(AJ34-AI34) -> 0 | AL34: =S34+L34+G34 -> 0 | AM34: =Y34+AD34 -> 0 | AN34: =AN33 -> 62 | AO34: =(AN34/100)*3000 -> 1860 | AP34: =AP33 -> 51 | AQ34: =(AP34/100)*3000 -> 1530 | AR34: =AR33 -> 68 | AS34: =(AR34/100)*3000 -> 2040 | AT34: =SUM(AO34+AQ34+AS34) -> 5430 | AU34: =AT33-AT34+AV34 -> 0 | AX34: =IF(AV34>0,AW34,AX33) -> 0.8
J35: =SUM(J5:J34)/(COUNT(J5:J34)-COUNTIF(J5:J34,0)) -> 1 | V35: =SUM(V5:V34) -> 155 | AE35: . | AH35: =SUM(AH5:AH34) -> 653 | AL35: =SUM(AL5:AL34) -> 2 | AM35: =SUM(AM5:AM34) -> 13 | AR35: Nb Delivery | AS35: =COUNT(AW5:AW34) -> 0 | AU35: =SUM(AU5:AU34) -> 600 | AV35: =SUM(AV5:AV34) -> 0 | AW35: =SUM(AW5:AW34)/AS35 -> #DIV/0!
AH36: =AF36+AA36 -> 0 | AI36: =SUM(AI5:AI34) -> 808
AH37: =AF37+AA37 -> 0 | AU37: =AU35*0.51 -> 306 | AV37: =AV35/0.51 -> 0 | AW37: =SUM(AW5:AW34)/AS35 -> #DIV/0!
AV38: =AV35*0.51 -> 0

Sheet WATER
D1: =SUM(G21:G35) -> 9127590 | AR1: Entrance | AT1: Tank 1 | AV1: Tank 2
AR2: Level | AW2: Quantity CM3 | AZ2: Var
A3: Date | B3: Truck | C3: Truck M3/day | D3: N0. Trucks | F3: REQ. # of trucks | G3: City | H3: City/day | I3: Total water delivery | K3: SW | L3: Cosum SW/day | M3: RO Guest/ Liter | O3: RO K&L/ Liter | Q3: TOTAL RO Production | R3: RO 1 RH | S3: RO 2 RH | T3: RO water counter | U3: RO Cons m3 | V3: Steam Boiler | W3: Steam Boiler/day | X3: Softener Guest | Y3: Guest Sotf/day | Z3: Softener K&L | AA3: K&L Soft/Day | AB3: Fire Tank Level | AC3: Fire Tank Counter | AE3: Laundry Hot Water Counter | AF3: Hot Water Cons/day | AG3: Laundry Cold Water Counter | AH3: Cold Water Cons/day | AI3: Laundry Water Total Cons | AJ3: K&L Sotf/day | AK3: Guest / day | AL3: K&L /day | AM3: Avg Outside Temp | AN3: Banquet Activity | AR3: Date | AT3: MainI | AV3: Kitchen and Laundry | AX3: Guest | AY3: Main Tank | AZ3: Kitchen and Laundry | BA3: Guest | BB3: Kitchen and Laundry | BC3: Main | BD3: Guest | BE3: Total VAR | BF3: Hotel Consumption
E4: 1.66 | AN4: Ball R | AO4: Meeting | AP4: outlet | AT4: 180 | AV4: 220 | AX4: 580 | AY4: =SUM(AT4) -> 180 | AZ4: =SUM(AV4) -> 220 | BA4: =SUM(AX4) -> 580
A5: 44074 | B5: =[1]WATER!B36 -> 109096 | C5: =[1]WATER!C36 -> 0 | D5: =[1]WATER!D36 -> 0 | E5: =[1]WATER!E36 -> 241.93548 | F5: =[1]WATER!F36 -> 0 | G5: =[1]WATER!G36 -> 607824 | H5: =[1]WATER!H36 -> 0 | I5: =[1]WATER!I36 -> 0 | ... BG5: =[1]WATER!BG36 -> -118.2
A6: =ELEC!C3 -> 44075 | B6: 109096 | C6: =B6-B5 -> 0 | D6: =C6/27 -> 0 | E6: =SUM((C6*$E$4)+(7500/'EDl log'!$A$38)) -> 250 | G6: 607824 | H6: =G6-G5 -> 0 | I6: =C6+H6 -> 0 | J6: =IF(I6>0,E6/I6,0) -> 0 | K6: ='Swimming Pool quality check '!H6 -> 6543 | L6: 0 | M6: =M5 -> 457.44 | N6: =SUM(M6-M5) -> 0 | O6: =O5 -> 529.52 | P6: =SUM(O6-O5) -> 0 | Q6: =P6+N6 -> 0 | T6: 5057 | U6: =SUM(T6-T5) -> 10 | V6: =V5 -> 427 | W6: =+V6-V5 -> 0 | X6: 147392 | Y6: =SUM(X6-X5) -> 80 | Z6: 96799 | AA6: =Z6-Z5 -> 0 | AB6: =AB5 -> 264 | AC6: =AC5 -> 698 | AD6: 0 | AE6: 206.52 | AF6: =AE6-AE5 -> 0 | AG6: 2111.2 | AH6: =AG6-AG5 -> 0 | AI6: =AF6+AH6 -> 0 | AJ6: =+Z6-Z5 -> 0 | AK6: =SUM(Y6-L6) -> 80 | AL6: =SUM(AJ6-W6) -> 0 | AM6: ='General information '!D6 -> 30 | AN6: ='General information '!H6 -> 0 | AP6: ='General information '!J6 -> 0 | AR6: =A6 -> 44075 | AS6: =AS5 -> 0.9 | AT6: 133 | AU6: =AU5 -> 1.1 | AV6: 128 | AW6: 2.9 | AX6: 122 | AY6: =AS6*AT6 -> 119.7 | AZ6: =AU6*AV6 -> 140.8 | BA6: =AW6*AX6 -> 353.8 | BB6: =AY6-AY5 -> -9.9 | BC6: =AZ6-AZ5 -> -19.8 | BD6: =BA6-BA5 -> -116 | BE6: =SUM(BB6:BD6) -> -145.7 | BF6: =SUM(I6-BE6) -> 145.7 | BG6: =SUM(I6-BF6) -> -145.7
A7: =ELEC!C4 -> 44076 | B7: =B6 -> 109096 | C7: =B7-B6 -> 0 | D7: =C7/27 -> 0 | E7: =SUM((C7*$E$4)+(7500/'EDl log'!$A$38)) -> 250 | G7: =G6 -> 607824 | H7: =G7-G6 -> 0 | I7: =C7+H7 -> 0 | J7: =IF(I7>0,E7/I7,0) -> 0 | K7: ='Swimming Pool quality check '!H7 -> 6550 | L7: =K7-K6 -> 7 | M7: =M6 -> 457.44 | N7: =SUM(M7-M6) -> 0 | O7: =O6 -> 529.52 | P7: =SUM(O7-O6) -> 0 | Q7: =P7+N7 -> 0 | T7: 5060 | U7: =SUM(T7-T6) -> 3 | V7: =V6 -> 427 | W7: =+V7-V6 -> 0 | X7: 147450 | Y7: =SUM(X7-X6) -> 58 | Z7: =Z6 -> 96799 | AA7: =Z7-Z6 -> 0 | AB7: =AB6 -> 264 | AC7: =AC6 -> 698 | AD7: =AC7-AC6 -> 0 | AE7: =AE6 -> 206.52 | AF7: =AE7-AE6 -> 0 | AG7: =AG6 -> 2111.2 | AH7: =AG7-AG6 -> 0 | AI7: =AF7+AH7 -> 0 | AJ7: =+Z7-Z6 -> 0 | AK7: =SUM(Y7-L7) -> 51 | AL7: =SUM(AJ7-W7) -> 0 | AM7: ='General information '!D7 -> 29 | AN7: ='General information '!H7 -> 0 | AP7: ='General information '!J7 -> 0 | AR7: =A7 -> 44076 | AS7: =AS6 -> 0.9 | AT7: 82 | AU7: =AU6 -> 1.1 | AV7: 117 | AW7: 2.9 | AX7: 125 | AY7: =AS7*AT7 -> 73.8 | AZ7: =AU7*AV7 -> 128.7 | BA7: =AW7*AX7 -> 362.5 | BB7: =AY7-AY6 -> -45.9 | BC7: =AZ7-AZ6 -> -12.1 | BD7: =BA7-BA6 -> 8.7 | BE7: =SUM(BB7:BD7) -> -49.3 | BF7: =SUM(I7-BE7) -> 49.3 | BG7: =SUM(I7-BF7) -> -49.3
A8: =ELEC!C5 -> 44077 | B8: =B7 -> 109096 | C8: =B8-B7 -> 0 | D8: =C8/27 -> 0 | E8: =SUM((C8*$E$4)+(7500/'EDl log'!$A$38)) -> 250 | G8: 607824 | H8: =G8-G7 -> 0 | I8: =C8+H8 -> 0 | J8: =IF(I8>0,E8/I8,0) -> 0 | K8: ='Swimming Pool quality check '!H8 -> 6555 | L8: =K8-K7 -> 5 | M8: =M7 -> 457.44 | N8: =SUM(M8-M7) -> 0 | O8: =O7 -> 529.52 | P8: =SUM(O8-O7) -> 0 | Q8: =P8+N8 -> 0 | T8: =T7 -> 5060 | U8: =SUM(T8-T7) -> 0 | V8: 449 | W8: =+V8-V7 -> 22 | X8: =X7 -> 147450 | Y8: =SUM(X8-X7) -> 0 | Z8: =Z7 -> 96799 | AA8: =Z8-Z7 -> 0 | AB8: =AB7 -> 264 | AC8: =AC7 -> 698 | AD8: =AC8-AC7 -> 0 | AE8: 215.08 | AF8: =AE8-AE7 -> 8.56 | AG8: 2151.99 | AH8: =AG8-AG7 -> 40.79 | AI8: =AF8+AH8 -> 49.35 | AJ8: =+Z8-Z7 -> 0 | AK8: =SUM(Y8-L8) -> -5 | AL8: =SUM(AJ8-W8) -> -22 | AM8: ='General information '!D8 -> 31.5 | AN8: ='General information '!H8 -> 0 | AP8: ='General information '!J8 -> 0 | AR8: =A8 -> 44077 | AS8: =AS7 -> 0.9 | AT8: =AT7 -> 82 | AU8: 1.1 | AV8: 72 | AW8: 2.9 | AX8: 113 | AY8: =AS8*AT8 -> 73.8 | AZ8: =AU8*AV8 -> 79.2 | BA8: =AW8*AX8 -> 327.7 | BB8: =AY8-AY7 -> 0 | BC8: =AZ8-AZ7 -> -49.5 | BD8: =BA8-BA7 -> -34.8 | BE8: =SUM(BB8:BD8) -> -84.3 | BF8: =SUM(I8-BE8) -> 84.3 | BG8: =SUM(I8-BF8) -> -84.3
A9: =ELEC!C6 -> 44078 | B9: =B8 -> 109096 | C9: =B9-B8 -> 0 | D9: =C9/27 -> 0 | E9: =SUM((C9*$E$4)+(7500/'EDl log'!$A$38)) -> 250 | G9: =G8 -> 607824 | H9: =G9-G8 -> 0 | I9: =C9+H9 -> 0 | J9: =IF(I9>0,E9/I9,0) -> 0 | K9: ='Swimming Pool quality check '!H9 -> 6555 | L9: =K9-K8 -> 0 | M9: =M8 -> 457.44 | N9: =SUM(M9-M8) -> 0 | O9: =O8 -> 529.52 | P9: =SUM(O9-O8) -> 0 | Q9: =P9+N9 -> 0 | T9: 5065 | U9: =SUM(T9-T8) -> 5 | V9: 452 | W9: =+V9-V8 -> 3 | X9: =X8 -> 147450 | Y9: =SUM(X9-X8) -> 0 | Z9: 96865 | AA9: =Z9-Z8 -> 66 | AB9: =AB8 -> 264 | AC9: =AC8 -> 698 | AD9: =AC9-AC8 -> 0 | AE9: =AE8 -> 215.08 | AF9: =AE9-AE8 -> 0 | AG9: =AG8 -> 2151.99 | AH9: =AG9-AG8 -> 0 | AI9: =AF9+AH9 -> 0 | AJ9: =+Z9-Z8 -> 66 | AK9: =SUM(Y9-L9) -> 0 | AL9: =SUM(AJ9-W9) -> 63 | AM9: ='General information '!D9 -> 30 | AN9: ='General information '!H9 -> 0 | AP9: ='General information '!J9 -> 0 | AR9: =A9 -> 44078 | AS9: =AS8 -> 0.9 | AT9: 15 | AU9: =AU8 -> 1.1 | AV9: 80 | AW9: 2.9 | AX9: 107 | AY9: =AS9*AT9 -> 13.5 | AZ9: =AU9*AV9 -> 88 | BA9: =AW9*AX9 -> 310.3 | BB9: =AY9-AY8 -> -60.3 | BC9: =AZ9-AZ8 -> 8.8 | BD9: =BA9-BA8 -> -17.4 | BE9: =SUM(BB9:BD9) -> -68.9 | BF9: =SUM(I9-BE9) -> 68.9 | BG9: =SUM(I9-BF9) -> -68.9
A10: =ELEC!C7 -> 44079 | B10: =B9 -> 109096 | C10: =B10-B9 -> 0 | D10: =C10/27 -> 0 | E10: =SUM((C10*$E$4)+(7500/'EDl log'!$A$38)) -> 250 | G10: =G9 -> 607824 | H10: =G10-G9 -> 0 | I10: =C10+H10 -> 0 | J10: =IF(I10>0,E10/I10,0) -> 0 | K10: ='Swimming Pool quality check '!H10 -> 6555 | L10: =K10-K9 -> 0 | M10: =M9 -> 457.44 | N10: =SUM(M10-M9) -> 0 | O10: =O9 -> 529.52 | P10: =SUM(O10-O9) -> 0 | Q10: =P10+N10 -> 0 | T10: 5067 | U10: =SUM(T10-T9) -> 2 | V10: 452 | W10: =+V10-V9 -> 0 | X10: =X9 -> 147450 | Y10: =SUM(X10-X9) -> 0 | Z10: =Z9 -> 96865 | AA10: =Z10-Z9 -> 0 | AB10: =AB9 -> 264 | AC10: =AC9 -> 698 | AD10: =AC10-AC9 -> 0 | AE10: 217.84 | AF10: =AE10-AE9 -> 2.76 | AG10: 2176.58 | AH10: =AG10-AG9 -> 24.59 | AI10: =AF10+AH10 -> 27.35 | AJ10: =+Z10-Z9 -> 0 | AK10: =SUM(Y10-L10) -> 0 | AL10: =SUM(AJ10-W10) -> 0 | AM10: ='General information '!D10 -> 28 | AN10: ='General information '!H10 -> 0 | AP10: ='General information '!J10 -> 0 | AR10: =A10 -> 44079 | AS10: =AS9 -> 0.9 | AT10: 15 | AU10: =AU9 -> 1.1 | AV10: 84 | AW10: 2.9 | AX10: 93 | AY10: =AS10*AT10 -> 13.5 | AZ10: =AU10*AV10 -> 92.4 | BA10: =AW10*AX10 -> 269.7 | BB10: =AY10-AY9 -> 0 | BC10: =AZ10-AZ9 -> 4.4 | BD10: =BA10-BA9 -> -40.6 | BE10: =SUM(BB10:BD10) -> -36.2 | BF10: =SUM(I10-BE10) -> 36.2 | BG10: =SUM(I10-BF10) -> -36.2
A11: =ELEC!C8 -> 44080 | B11: =B10 -> 109096 | C11: =B11-B10 -> 0 | D11: =C11/27 -> 0 | E11: =SUM((C11*$E$4)+(7500/'EDl log'!$A$38)) -> 250 | G11: 607942 | H11: =G11-G10 -> 118 | I11: =C11+H11 -> 118 | J11: =IF(I11>0,E11/I11,0) -> 2.1186441 | K11: ='Swimming Pool quality check '!H11 -> 6555 | L11: =K11-K10 -> 0 | M11: =M10 -> 457.44 | N11: =SUM(M11-M10) -> 0 | O11: =O10 -> 529.52 | P11: =SUM(O11-O10) -> 0 | Q11: =SUM(P11+N11) -> 0 | T11: 5069 | U11: =SUM(T11-T10) -> 2 | V11: =V10 -> 452 | W11: =+V11-V10 -> 0 | X11: =X10 -> 147450 | Y11: =SUM(X11-X10) -> 0 | Z11: =Z10 -> 96865 | AA11: =Z11-Z10 -> 0 | AB11: =AB10 -> 264 | AC11: =AC10 -> 698 | AD11: =AC11-AC10 -> 0 | AE11: =AE10 -> 217.84 | AF11: =AE11-AE10 -> 0 | AG11: =AG10 -> 2176.58 | AH11: =AG11-AG10 -> 0 | AI11: =AF11+AH11 -> 0 | AJ11: =+Z11-Z10 -> 0 | AK11: =SUM(Y11-L11) -> 0 | AL11: =SUM(AJ11-W11) -> 0 | AM11: ='General information '!D11 -> 28 | AN11: ='General information '!H11 -> 0 | AP11: ='General information '!J11 -> 0 | AR11: =A11 -> 44080 | AS11: =AS10 -> 0.9 | AT11: 74 | AU11: =AU10 -> 1.1 | AV11: 78 | AW11: 2.9 | AX11: 87 | AY11: =AS11*AT11 -> 66.6 | AZ11: =AU11*AV11 -> 85.8 | BA11: =AW11*AX11 -> 252.3 | BB11: =AY11-AY10 -> 53.1 | BC11: =AZ11-AZ10 -> -6.6 | BD11: =BA11-BA10 -> -17.4 | BE11: =SUM(BB11:BD11) -> 29.1 | BF11: =SUM(I11-BE11) -> 88.9 | BG11: =SUM(I11-BF11) -> 29.1
A12: =ELEC!C9 -> 44081 | B12: =B11 -> 109096 | C12: =B12-B11 -> 0 | D12: =C12/27 -> 0 | E12: =SUM((C12*$E$4)+(7500/'EDl log'!$A$38)) -> 250 | G12: =G11 -> 607942 | H12: =G12-G11 -> 0 | I12: =C12+H12 -> 0 | J12: =IF(I12>0,E12/I12,0) -> 0 | K12: ='Swimming Pool quality check '!H12 -> 6555 | L12: =K12-K11 -> 0 | M12: =M11 -> 457.44 | N12: =SUM(M12-M11) -> 0 | O12: =O11 -> 529.52 | P12: =SUM(O12-O11) -> 0 | Q12: =SUM(P12+N12) -> 0 | T12: 5071 | U12: =SUM(T12-T11) -> 2 | V12: =V11 -> 452 | W12: =+V12-V11 -> 0 | X12: =X11 -> 147450 | Y12: =SUM(X12-X11) -> 0 | Z12: =Z11 -> 96865 | AA12: =Z12-Z11 -> 0 | AB12: =AB11 -> 264 | AC12: =AC11 -> 698 | AD12: =AC12-AC11 -> 0 | AE12: =AE11 -> 217.84 | AF12: =AE12-AE11 -> 0 | AG12: =AG11 -> 2176.58 | AH12: =AG12-AG11 -> 0 | AI12: =AF12+AH12 -> 0 | AJ12: =+Z12-Z11 -> 0 | AK12: =SUM(Y12-L12) -> 0 | AL12: =SUM(AJ12-W12) -> 0 | AM12: ='General information '!D12 -> 29.5 | AN12: ='General information '!H12 -> 0 | AP12: ='General information '!J12 -> 0 | AR12: =A12 -> 44081 | AS12: =AS11 -> 0.9 | AT12: 69 | AU12: =AU11 -> 1.1 | AV12: 69 | AW12: 2.9 | AX12: 85 | AY12: =AS12*AT12 -> 62.1 | AZ12: =AU12*AV12 -> 75.9 | BA12: =AW12*AX12 -> 246.5 | BB12: =AY12-AY11 -> -4.5 | BC12: =AZ12-AZ11 -> -9.9 | BD12: =BA12-BA11 -> -5.8 | BE12: =SUM(BB12:BD12) -> -20.2 | BF12: =SUM(I12-BE12) -> 20.2 | BG12: =SUM(I12-BF12) -> -20.2
A13: =ELEC!C10 -> 44082 | B13: 109096 | C13: =B13-B12 -> 0 | D13: =C13/27 -> 0 | E13: =SUM((C13*$E$4)+(7500/'EDl log'!$A$38)) -> 250 | G13: =G12 -> 607942 | H13: =G13-G12 -> 0 | I13: =C13+H13 -> 0 | J13: =IF(I13>0,E13/I13,0) -> 0 | K13: ='Swimming Pool quality check '!H13 -> 6555 | L13: =K13-K12 -> 0 | M13: =M12 -> 457.44 | N13: =SUM(M13-M12) -> 0 | O13: =O12 -> 529.52 | P13: =SUM(O13-O12) -> 0 | Q13: =SUM(P13+N13) -> 0 | T13: 5074 | U13: =SUM(T13-T12) -> 3 | V13: =V12 -> 452 | W13: =+V13-V12 -> 0 | X13: =X12 -> 147450 | Y13: =SUM(X13-X12) -> 0 | Z13: 96865 | AA13: =Z13-Z12 -> 0 | AB13: =AB12 -> 264 | AC13: =AC12 -> 698 | AD13: =AC13-AC12 -> 0 | AE13: =AE12 -> 217.84 | AF13: =AE13-AE12 -> 0 | AG13: =AG12 -> 2176.58 | AH13: =AG13-AG12 -> 0 | AI13: =AF13+AH13 -> 0 | AJ13: =+Z13-Z12 -> 0 | AK13: =SUM(Y13-L13) -> 0 | AL13: =SUM(AJ13-W13) -> 0 | AM13: ='General information '!D13 -> 29.5 | AN13: ='General information '!J13 -> 0 | AP13: ='General information '!J13 -> 0 | AR13: =A13 -> 44082 | AS13: =AS12 -> 0.9 | AT13: 69 | AU13: =AU12 -> 1.1 | AV13: 69 | AW13: 2.9 | AX13: 79 | AY13: =AS13*AT13 -> 62.1 | AZ13: =AU13*AV13 -> 75.9 | BA13: =AW13*AX13 -> 229.1 | BB13: =AY13-AY12 -> 0 | BC13: =AZ13-AZ12 -> 0 | BD13: =BA13-BA12 -> -17.4 | BE13: =SUM(BB13:BD13) -> -17.4 | BF13: =SUM(I13-BE13) -> 17.4 | BG13: =SUM(I13-BF13) -> -17.4
A14: =ELEC!C11 -> 44083 | B14: =B13 -> 109096 | C14: =B14-B13 -> 0 | D14: =C14/27 -> 0 | E14: =SUM((C14*$E$4)+(7500/'EDl log'!$A$38)) -> 250 | G14: =G13 -> 607942 | H14: =G14-G13 -> 0 | I14: =C14+H14 -> 0 | J14: =IF(I14>0,E14/I14,0) -> 0 | K14: ='Swimming Pool quality check '!H14 -> 6555 | L14: =K14-K13 -> 0 | M14: =M13 -> 457.44 | N14: =SUM(M14-M13) -> 0 | O14: =O13 -> 529.52 | P14: =SUM(O14-O13) -> 0 | Q14: =SUM(P14+N14) -> 0 | T14: 5077 | U14: =SUM(T14-T13) -> 3 | V14: =V13 -> 452 | W14: =+V14-V13 -> 0 | X14: =X13 -> 147450 | Y14: =SUM(X14-X13) -> 0 | Z14: =Z13 -> 96865 | AA14: =Z14-Z13 -> 0 | AB14: =AB13 -> 264 | AC14: =AC13 -> 698 | AD14: =AC14-AC13 -> 0 | AE14: =AE13 -> 217.84 | AF14: =AE14-AE13 -> 0 | AG14: =AG13 -> 2176.58 | AH14: =AG14-AG13 -> 0 | AI14: =AF14+AH14 -> 0 | AJ14: =+Z14-Z13 -> 0 | AK14: =SUM(Y14-L14) -> 0 | AL14: =SUM(AJ14-W14) -> 0 | AM14: ='General information '!D14 -> 29.5 | AN14: ='General information '!H14 -> 0 | AP14: ='General information '!J14 -> 0 | AR14: =A14 -> 44083 | AS14: =AS13 -> 0.9 | AT14: 62 | AU14: =AU13 -> 1.1 | AV14: 53 | AW14: 2.9 | AX14: 75 | AY14: =AS14*AT14 -> 55.8 | AZ14: =AU14*AV14 -> 58.3 | BA14: =AW14*AX14 -> 217.5 | BB14: =AY14-AY13 -> -6.3 | BC14: =AZ14-AZ13 -> -17.6 | BD14: =BA14-BA13 -> -11.6 | BE14: =SUM(BB14:BD14) -> -35.5 | BF14: =SUM(I14-BE14) -> 35.5 | BG14: =SUM(I14-BF14) -> -35.5
A15: =ELEC!C12 -> 44084 | B15: =B14 -> 109096 | C15: =B15-B14 -> 0 | D15: =C15/27 -> 0 | E15: =SUM((C15*$E$4)+(7500/'EDl log'!$A$38)) -> 250 | G15: =G14 -> 607942 | H15: =G15-G14 -> 0 | I15: =C15+H15 -> 0 | J15: =IF(I15>0,E15/I15,0) -> 0 | K15: ='Swimming Pool quality check '!H15 -> 6555 | L15: =K15-K14 -> 0 | M15: =M14 -> 457.44 | N15: =SUM(M15-M14) -> 0 | O15: =O14 -> 529.52 | P15: =SUM(O15-O14) -> 0 | Q15: =SUM(P15+N15) -> 0 | T15: 5079 | U15: =SUM(T15-T14) -> 2 | V15: =V14 -> 452 | W15: =+V15-V14 -> 0 | X15: =X14 -> 147450 | Y15: =SUM(X15-X14) -> 0 | Z15: =Z14 -> 96865 | AA15: =Z15-Z14 -> 0 | AB15: =AB14 -> 264 | AC15: =AC14 -> 698 | AD15: =AC15-AC14 -> 0 | AE15: =AE14 -> 217.84 | AF15: =AE15-AE14 -> 0 | AG15: =AG14 -> 2176.58 | AH15: =AG15-AG14 -> 0 | AI15: =AF15+AH15 -> 0 | AJ15: =+Z15-Z14 -> 0 | AK15: =SUM(Y15-L15) -> 0 | AL15: =SUM(AJ15-W15) -> 0 | AM15: ='General information '!D15 -> 29 | AN15: ='General information '!H15 -> 0 | AP15: ='General information '!J15 -> 0 | AR15: =A15 -> 44084 | AS15: =AS14 -> 0.9 | AT15: 62 | AU15: =AU14 -> 1.1 | AV15: 46 | AW15: 2.9 | AX15: 69 | AY15: =AS15*AT15 -> 55.8 | AZ15: =AU15*AV15 -> 50.6 | BA15: =AW15*AX15 -> 200.1 | BB15: =AY15-AY14 -> 0 | BC15: =AZ15-AZ14 -> -7.7 | BD15: =BA15-BA14 -> -17.4 | BE15: =SUM(BB15:BD15) -> -25.1 | BF15: =SUM(I15-BE15) -> 25.1 | BG15: =SUM(I15-BF15) -> -25.1
A16: =ELEC!C13 -> 44085 | B16: =B15 -> 109096 | C16: =B16-B15 -> 0 | D16: =C16/27 -> 0 | E16: =SUM((C16*$E$4)+(7500/'EDl log'!$A$38)) -> 250 | G16: =G15 -> 607942 | H16: =G16-G15 -> 0 | I16: =C16+H16 -> 0 | J16: =IF(I16>0,E16/I16,0) -> 0 | K16: ='Swimming Pool quality check '!H16 -> 6555 | L16: =K16-K15 -> 0 | M16: =M15 -> 457.44 | N16: =SUM(M16-M15) -> 0 | O16: =O15 -> 529.52 | P16: =SUM(O16-O15) -> 0 | Q16: =SUM(P16+N16) -> 0 | T16: 5082 | U16: =SUM(T16-T15) -> 3 | V16: =V15 -> 452 | W16: =+V16-V15 -> 0 | X16: =X15 -> 147450 | Y16: =SUM(X16-X15) -> 0 | Z16: =Z15 -> 96865 | AA16: =Z16-Z15 -> 0 | AB16: =AB15 -> 264 | AC16: =AC15 -> 698 | AD16: =AC16-AC15 -> 0 | AE16: =AE15 -> 217.84 | AF16: =AE16-AE15 -> 0 | AG16: =AG15 -> 2176.58 | AH16: =AG16-AG15 -> 0 | AI16: =AF16+AH16 -> 0 | AJ16: =+Z16-Z15 -> 0 | AK16: =SUM(Y16-L16) -> 0 | AL16: =SUM(AJ16-W16) -> 0 | AM16: ='General information '!D16 -> 30 | AN16: ='General information '!H16 -> 0 | AP16: ='General information '!J16 -> 0 | AR16: =A16 -> 44085 | AS16: =AS15 -> 0.9 | AT16: =AT15 -> 62 | AU16: =AU15 -> 1.1 | AV16: 32 | AW16: 2.9 | AX16: 60 | AY16: =AS16*AT16 -> 55.8 | AZ16: =AU16*AV16 -> 35.2 | BA16: =AW16*AX16 -> 174 | BB16: =AY16-AY15 -> 0 | BC16: =AZ16-AZ15 -> -15.4 | BD16: =BA16-BA15 -> -26.1 | BE16: =SUM(BB16:BD16) -> -41.5 | BF16: =SUM(I16-BE16) -> 41.5 | BG16: =SUM(I16-BF16) -> -41.5
A17: =ELEC!C14 -> 44086 | B17: =B16 -> 109096 | C17: =B17-B16 -> 0 | D17: =C17/27 -> 0 | E17: =SUM((C17*$E$4)+(7500/'EDl log'!$A$38)) -> 250 | G17: =G16 -> 607942 | H17: =G17-G16 -> 0 | I17: =C17+H17 -> 0 | J17: =IF(I17>0,E17/I17,0) -> 0 | K17: ='Swimming Pool quality check '!H17 -> 6555 | L17: =K17-K16 -> 0 | M17: =M16 -> 457.44 | N17: =SUM(M17-M16) -> 0 | O17: =O16 -> 529.52 | P17: =SUM(O17-O16) -> 0 | Q17: =SUM(P17+N17) -> 0 | T17: 5084 | U17: =SUM(T17-T16) -> 2 | V17: =V16 -> 452 | W17: =+V17-V16 -> 0 | X17: =X16 -> 147450 | Y17: =SUM(X17-X16) -> 0 | Z17: 96897 | AA17: =Z17-Z16 -> 32 | AB17: =AB16 -> 264 | AC17: =AC16 -> 698 | AD17: =AC17-AC16 -> 0 | AE17: =AE16 -> 217.84 | AF17: =AE17-AE16 -> 0 | AG17: =AG16 -> 2176.58 | AH17: =AG17-AG16 -> 0 | AI17: =AF17+AH17 -> 0 | AJ17: =+Z17-Z16 -> 32 | AK17: =SUM(Y17-L17) -> 0 | AL17: =SUM(AJ17-W17) -> 32 | AM17: ='General information '!D17 -> 29.5 | AN17: ='General information '!H17 -> 0 | AP17: ='General information '!J17 -> 0 | AR17: =A17 -> 44086 | AS17: =AS16 -> 0.9 | AT17: 22 | AU17: =AU16 -> 1.1 | AV17: 51 | AW17: 2.9 | AX17: 58 | AY17: =AS17*AT17 -> 19.8 | AZ17: =AU17*AV17 -> 56.1 | BA17: =AW17*AX17 -> 168.2 | BB17: =AY17-AY16 -> -36 | BC17: =AZ17-AZ16 -> 20.9 | BD17: =BA17-BA16 -> -5.8 | BE17: =SUM(BB17:BD17) -> -20.9 | BF17: =SUM(I17-BE17) -> 20.9 | BG17: =SUM(I17-BF17) -> -20.9
A18: =ELEC!C15 -> 44087 | B18: =B17 -> 109096 | C18: =B18-B17 -> 0 | D18: =C18/27 -> 0 | E18: =SUM((C18*$E$4)+(7500/'EDl log'!$A$38)) -> 250 | G18: =G17 -> 607942 | H18: =G18-G17 -> 0 | I18: =C18+H18 -> 0 | J18: =IF(I18>0,E18/I18,0) -> 0 | K18: ='Swimming Pool quality check '!H18 -> 6555 | L18: =K18-K17 -> 0 | M18: =M17 -> 457.44 | N18: =SUM(M18-M17) -> 0 | O18: =O17 -> 529.52 | P18: =SUM(O18-O17) -> 0 | Q18: =SUM(P18+N18) -> 0 | T18: 5086 | U18: =SUM(T18-T17) -> 2 | V18: =V17 -> 452 | W18: =+V18-V17 -> 0 | X18: =X17 -> 147450 | Y18: =SUM(X18-X17) -> 0 | Z18: =Z17 -> 96897 | AA18: =Z18-Z17 -> 0 | AB18: =AB17 -> 264 | AC18: =AC17 -> 698 | AD18: =AC18-AC17 -> 0 | AE18: =AE17 -> 217.84 | AF18: =AE18-AE17 -> 0 | AG18: =AG17 -> 2176.58 | AH18: =AG18-AG17 -> 0 | AI18: =AF18+AH18 -> 0 | AJ18: =+Z18-Z17 -> 0 | AK18: =SUM(Y18-L18) -> 0 | AL18: =SUM(AJ18-W18) -> 0 | AM18: ='General information '!D18 -> 28 | AN18: ='General information '!H18 -> 0 | AP18: ='General information '!J18 -> 0 | AR18: =A18 -> 44087 | AS18: =AS17 -> 0.9 | AT18: =AT17 -> 22 | AU18: =AU17 -> 1.1 | AV18: 43 | AW18: 2.9 | AX18: 58 | AY18: =AS18*AT18 -> 19.8 | AZ18: =AU18*AV18 -> 47.3 | BA18: =AW18*AX18 -> 168.2 | BB18: =AY18-AY17 -> 0 | BC18: =AZ18-AZ17 -> -8.8 | BD18: =BA18-BA17 -> 0 | BE18: =SUM(BB18:BD18) -> -8.8 | BF18: =SUM(I18-BE18) -> 8.8 | BG18: =SUM(I18-BF18) -> -8.8
A19: =ELEC!C16 -> 44088 | B19: =B18 -> 109096 | C19: =B19-B18 -> 0 | D19: =C19/27 -> 0 | E19: =SUM((C19*$E$4)+(7500/'EDl log'!$A$38)) -> 250 | G19: =G18 -> 607942 | H19: =G19-G18 -> 0 | I19: =C19+H19 -> 0 | J19: =IF(I19>0,E19/I19,0) -> 0 | K19: ='Swimming Pool quality check '!H19 -> 6555 | L19: =K19-K18 -> 0 | M19: =M18 -> 457.44 | N19: =SUM(M19-M18) -> 0 | O19: =O18 -> 529.52 | P19: =SUM(O19-O18) -> 0 | Q19: =SUM(P19+N19) -> 0 | T19: 5088 | U19: =SUM(T19-T18) -> 2 | V19: =V18 -> 452 | W19: =+V19-V18 -> 0 | X19: =X18 -> 147450 | Y19: =SUM(X19-X18) -> 0 | Z19: 96922 | AA19: =Z19-Z18 -> 25 | AB19: =AB18 -> 264 | AC19: =AC18 -> 698 | AD19: =AC19-AC18 -> 0 | AE19: =AE18 -> 217.84 | AF19: =AE19-AE18 -> 0 | AG19: =AG18 -> 2176.58 | AH19: =AG19-AG18 -> 0 | AI19: =AF19+AH19 -> 0 | AJ19: =+Z19-Z18 -> 25 | AK19: =SUM(Y19-L19) -> 0 | AL19: =SUM(AJ19-W19) -> 25 | AM19: ='General information '!D19 -> 28.5 | AN19: ='General information '!H19 -> 0 | AP19: ='General information '!J19 -> 0 | AR19: =A19 -> 44088 | AS19: =AS18 -> 0.9 | AT19: 0 | AU19: =AU18 -> 1.1 | AV19: 56 | AW19: 2.9 | AX19: 57 | AY19: =AS19*AT19 -> 0 | AZ19: =AU19*AV19 -> 61.6 | BA19: =AW19*AX19 -> 165.3 | BB19: =AY19-AY18 -> -19.8 | BC19: =AZ19-AZ18 -> 14.3 | BD19: =BA19-BA18 -> -2.9 | BE19: =SUM(BB19:BD19) -> -8.4 | BF19: =SUM(I19-BE19) -> 8.4 | BG19: =SUM(I19-BF19) -> -8.4
A20: =ELEC!C17 -> 44089 | B20: =B19 -> 109096 | C20: =B20-B19 -> 0 | D20: =C20/27 -> 0 | E20: =SUM((C20*$E$4)+(7500/'EDl log'!$A$38)) -> 250 | G20: =G19 -> 607942 | H20: =G20-G19 -> 0 | I20: =C20+H20 -> 0 | J20: =IF(I20>0,E20/I20,0) -> 0 | K20: ='Swimming Pool quality check '!H20 -> 6555 | L20: =K20-K19 -> 0 | M20: =M19 -> 457.44 | N20: =SUM(M20-M19) -> 0 | O20: =O19 -> 529.52 | P20: =SUM(O20-O19) -> 0 | Q20: =SUM(P20+N20) -> 0 | T20: 5089 | U20: =SUM(T20-T19) -> 1 | V20: =V19 -> 452 | W20: =+V20-V19 -> 0 | X20: =X19 -> 147450 | Y20: =SUM(X20-X19) -> 0 | Z20: =Z19 -> 96922 | AA20: =Z20-Z19 -> 0 | AB20: =AB19 -> 264 | AC20: =AC19 -> 698 | AD20: =AC20-AC19 -> 0 | AE20: =AE19 -> 217.84 | AF20: =AE20-AE19 -> 0 | AG20: =AG19 -> 2176.58 | AH20: =AG20-AG19 -> 0 | AI20: =AF20+AH20 -> 0 | AJ20: =+Z20-Z19 -> 0 | AK20: =SUM(Y20-L20) -> 0 | AL20: =SUM(AJ20-W20) -> 0 | AM20: ='General information '!D20 -> 26.5 | AN20: ='General information '!H20 -> 0 | AP20: ='General information '!J20 -> 0 | AR20: =A20 -> 44089 | AS20: =AS19 -> 0.9 | AT20: =AT19 -> 0 | AU20: =AU19 -> 1.1 | AV20: 48 | AW20: 2.9 | AX20: 52 | AY20: =AS20*AT20 -> 0 | AZ20: =AU20*AV20 -> 52.8 | BA20: =AW20*AX20 -> 150.8 | BB20: =AY20-AY19 -> 0 | BC20: =AZ20-AZ19 -> -8.8 | BD20: =BA20-BA19 -> -14.5 | BE20: =SUM(BB20:BD20) -> -23.3 | BF20: =SUM(I20-BE20) -> 23.3 | BG20: =SUM(I20-BF20) -> -23.3
A21: =ELEC!C18 -> 44090 | B21: =B20 -> 109096 | C21: =B21-B20 -> 0 | D21: =C21/27 -> 0 | E21: =SUM((C21*$E$4)+(7500/'EDl log'!$A$38)) -> 250 | G21: 608127 | H21: =G21-G20 -> 185 | I21: =C21+H21 -> 185 | J21: =IF(I21>0,E21/I21,0) -> 1.3513514 | K21: ='Swimming Pool quality check '!H21 -> 6555 | L21: =K21-K20 -> 0 | M21: =M20 -> 457.44 | N21: =SUM(M21-M20) -> 0 | O21: =O20 -> 529.52 | P21: =SUM(O21-O20) -> 0 | Q21: =SUM(P21+N21) -> 0 | T21: 5093 | U21: =SUM(T21-T20) -> 4 | V21: =V20 -> 452 | W21: =+V21-V20 -> 0 | X21: =X20 -> 147450 | Y21: =SUM(X21-X20) -> 0 | Z21: =Z20 -> 96922 | AA21: =Z21-Z20 -> 0 | AB21: =AB20 -> 264 | AC21: =AC20 -> 698 | AD21: =AC21-AC20 -> 0 | AE21: =AE20 -> 217.84 | AF21: =AE21-AE20 -> 0 | AG21: =AG20 -> 2176.58 | AH21: =AG21-AG20 -> 0 | AI21: =AF21+AH21 -> 0 | AJ21: =+Z21-Z20 -> 0 | AK21: =SUM(Y21-L21) -> 0 | AL21: =SUM(AJ21-W21) -> 0 | AM21: ='General information '!D21 -> 28.5 | AN21: ='General information '!H21 -> 0 | AP21: ='General information '!J21 -> 0 | AR21: =A21 -> 44090 | AS21: =AS20 -> 0.9 | AT21: 72 | AU21: =AU20 -> 1.1 | AV21: 40 | AW21: 2.9 | AX21: 48 | AY21: =AS21*AT21 -> 64.8 | AZ21: =AU21*AV21 -> 44 | BA21: =AW21*AX21 -> 139.2 | BB21: =AY21-AY20 -> 64.8 | BC21: =AZ21-AZ20 -> -8.8 | BD21: =BA21-BA20 -> -11.6 | BE21: =SUM(BB21:BD21) -> 44.4 | BF21: =SUM(I21-BE21) -> 140.6 | BG21: =SUM(I21-BF21) -> 44.4
A22: =ELEC!C19 -> 44091 | B22: =B21 -> 109096 | C22: =B22-B21 -> 0 | D22: =C22/27 -> 0 | E22: =SUM((C22*$E$4)+(7500/'EDl log'!$A$38)) -> 250 | G22: =G21 -> 608127 | H22: =G22-G21 -> 0 | I22: =C22+H22 -> 0 | J22: =IF(I22>0,E22/I22,0) -> 0 | K22: ='Swimming Pool quality check '!H22 -> 6555 | L22: =K22-K21 -> 0 | M22: =M21 -> 457.44 | N22: =SUM(M22-M21) -> 0 | O22: =O21 -> 529.52 | P22: =SUM(O22-O21) -> 0 | Q22: =SUM(P22+N22) -> 0 | T22: =T21 -> 5093 | U22: =SUM(T22-T21) -> 0 | V22: =V21 -> 452 | W22: =+V22-V21 -> 0 | X22: 147461 | Y22: =SUM(X22-X21) -> 11 | Z22: 96945 | AA22: =Z22-Z21 -> 23 | AB22: =AB21 -> 264 | AC22: =AC21 -> 698 | AD22: =AC22-AC21 -> 0 | AE22: =AE21 -> 217.84 | AF22: =AE22-AE21 -> 0 | AG22: =AG21 -> 2176.58 | AH22: =AG22-AG21 -> 0 | AI22: =AF22+AH22 -> 0 | AJ22: =+Z22-Z21 -> 23 | AK22: =SUM(Y22-L22) -> 11 | AL22: =SUM(AJ22-W22) -> 23 | AM22: ='General information '!D22 -> 28 | AN22: ='General information '!H22 -> 0 | AP22: ='General information '!J22 -> 0 | AR22: =A22 -> 44091 | AS22: =AS21 -> 0.9 | AT22: 0 | AU22: =AU21 -> 1.1 | AV22: 41 | AW22: 2.9 | AX22: 56 | AY22: =AS22*AT22 -> 0 | AZ22: =AU22*AV22 -> 45.1 | BA22: =AW22*AX22 -> 162.4 | BB22: =AY22-AY21 -> -64.8 | BC22: =AZ22-AZ21 -> 1.1 | BD22: =BA22-BA21 -> 23.2 | BE22: =SUM(BB22:BD22) -> -40.5 | BF22: =SUM(I22-BE22) -> 40.5 | BG22: =SUM(I22-BF22) -> -40.5
A23: =ELEC!C20 -> 44092 | B23: =B22 -> 109096 | C23: =B23-B22 -> 0 | D23: =C23/27 -> 0 | E23: =SUM((C23*$E$4)+(7500/'EDl log'!$A$38)) -> 250 | G23: 608269 | H23: =G23-G22 -> 142 | I23: =C23+H23 -> 142 | J23: =IF(I23>0,E23/I23,0) -> 1.7605634 | K23: ='Swimming Pool quality check '!H23 -> 6555 | L23: =K23-K22 -> 0 | M23: =M22 -> 457.44 | N23: =SUM(M23-M22) -> 0 | O23: =O22 -> 529.52 | P23: =SUM(O23-O22) -> 0 | Q23: =SUM(P23+N23) -> 0 | T23: 5097 | U23: =SUM(T23-T22) -> 4 | V23: =V22 -> 452 | W23: =+V23-V22 -> 0 | X23: 147461 | Y23: =SUM(X23-X22) -> 0 | Z23: 97015 | AA23: =Z23-Z22 -> 70 | AB23: =AB22 -> 264 | AC23: =AC22 -> 698 | AD23: =AC23-AC22 -> 0 | AE23: =AE22 -> 217.84 | AF23: =AE23-AE22 -> 0 | AG23: =AG22 -> 2176.58 | AH23: =AG23-AG22 -> 0 | AI23: =AF23+AH23 -> 0 | AJ23: =+Z23-Z22 -> 70 | AK23: =SUM(Y23-L23) -> 0 | AL23: =SUM(AJ23-W23) -> 70 | AM23: ='General information '!D23 -> 27.5 | AN23: ='General information '!H23 -> 0 | AP23: ='General information '!J23 -> 0 | AR23: =A23 -> 44092 | AS23: =AS22 -> 0.9 | AT23: 18 | AU23: =AU22 -> 1.1 | AV23: 96 | AW23: 2.9 | AX23: 53 | AY23: =AS23*AT23 -> 16.2 | AZ23: =AU23*AV23 -> 105.6 | BA23: =AW23*AX23 -> 153.7 | BB23: =AY23-AY22 -> 16.2 | BC23: =AZ23-AZ22 -> 60.5 | BD23: =BA23-BA22 -> -8.7 | BE23: =SUM(BB23:BD23) -> 68 | BF23: =SUM(I23-BE23) -> 74 | BG23: =SUM(I23-BF23) -> 68
A24: =ELEC!C21 -> 44093 | B24: =B23 -> 109096 | C24: =B24-B23 -> 0 | D24: =C24/27 -> 0 | E24: =SUM((C24*$E$4)+(7500/'EDl log'!$A$38)) -> 250 | G24: =G23 -> 608269 | H24: =G24-G23 -> 0 | I24: =C24+H24 -> 0 | J24: =IF(I24>0,E24/I24,0) -> 0 | K24: ='Swimming Pool quality check '!H24 -> 6555 | L24: =K24-K23 -> 0 | M24: =M23 -> 457.44 | N24: =SUM(M24-M23) -> 0 | O24: =O23 -> 529.52 | P24: =SUM(O24-O23) -> 0 | Q24: =SUM(P24+N24) -> 0 | T24: 5100 | U24: =SUM(T24-T23) -> 3 | V24: =V23 -> 452 | W24: =+V24-V23 -> 0 | X24: =X23 -> 147461 | Y24: =SUM(X24-X23) -> 0 | Z24: =Z23 -> 97015 | AA24: =Z24-Z23 -> 0 | AB24: =AB23 -> 264 | AC24: =AC23 -> 698 | AD24: =AC24-AC23 -> 0 | AE24: =AE23 -> 217.84 | AF24: =AE24-AE23 -> 0 | AG24: =AG23 -> 2176.58 | AH24: =AG24-AG23 -> 0 | AI24: =AF24+AH24 -> 0 | AJ24: =+Z24-Z23 -> 0 | AK24: =SUM(Y24-L24) -> 0 | AL24: =SUM(AJ24-W24) -> 0 | AM24: ='General information '!D24 -> 28.5 | AN24: ='General information '!H24 -> 0 | AP24: ='General information '!J24 -> 0 | AR24: =A24 -> 44093 | AS24: =AS23 -> 0.9 | AT24: 18 | AU24: =AU23 -> 1.1 | AV24: 88 | AW24: 2.9 | AX24: 49 | AY24: =AS24*AT24 -> 16.2 | AZ24: =AU24*AV24 -> 96.8 | BA24: =AW24*AX24 -> 142.1 | BB24: =AY24-AY23 -> 0 | BC24: =AZ24-AZ23 -> -8.8 | BD24: =BA24-BA23 -> -11.6 | BE24: =SUM(BB24:BD24) -> -20.4 | BF24: =SUM(I24-BE24) -> 20.4 | BG24: =SUM(I24-BF24) -> -20.4
A25: =ELEC!C22 -> 44094 | B25: 109096 | C25: =B25-B24 -> 0 | D25: =C25/27 -> 0 | E25: =SUM((C25*$E$4)+(7500/'EDl log'!$A$38)) -> 250 | G25: 608391 | H25: =G25-G24 -> 122 | I25: =C25+H25 -> 122 | J25: =IF(I25>0,E25/I25,0) -> 2.0491803 | K25: ='Swimming Pool quality check '!H25 -> 6555 | L25: =K25-K24 -> 0 | M25: =M24 -> 457.44 | N25: =SUM(M25-M24) -> 0 | O25: =O24 -> 529.52 | P25: =SUM(O25-O24) -> 0 | Q25: =SUM(P25+N25) -> 0 | T25: 5102 | U25: =SUM(T25-T24) -> 2 | V25: =V24 -> 452 | W25: =+V25-V24 -> 0 | X25: 147534 | Y25: =SUM(X25-X24) -> 73 | Z25: =Z24 -> 97015 | AA25: =Z25-Z24 -> 0 | AB25: =AB24 -> 264 | AC25: =AC24 -> 698 | AD25: =AC25-AC24 -> 0 | AE25: =AE24 -> 217.84 | AF25: =AE25-AE24 -> 0 | AG25: =AG24 -> 2176.58 | AH25: =AG25-AG24 -> 0 | AI25: =AF25+AH25 -> 0 | AJ25: =+Z25-Z24 -> 0 | AK25: =SUM(Y25-L25) -> 73 | AL25: =SUM(AJ25-W25) -> 0 | AM25: ='General information '!D25 -> 26 | AN25: ='General information '!H25 -> 0 | AP25: ='General information '!J25 -> 0 | AR25: =A25 -> 44094 | AS25: =AS24 -> 0.9 | AT25: 55 | AU25: =AU24 -> 1.1 | AV25: 80 | AW25: 2.9 | AX25: 53 | AY25: =AS25*AT25 -> 49.5 | AZ25: =AU25*AV25 -> 88 | BA25: =AW25*AX25 -> 153.7 | BB25: =AY25-AY24 -> 33.3 | BC25: =AZ25-AZ24 -> -8.8 | BD25: =BA25-BA24 -> 11.6 | BE25: =SUM(BB25:BD25) -> 36.1 | BF25: =SUM(I25-BE25) -> 85.9 | BG25: =SUM(I25-BF25) -> 36.1
A26: =ELEC!C23 -> 44095 | B26: =B25 -> 109096 | C26: =B26-B25 -> 0 | D26: =C26/27 -> 0 | E26: =SUM((C26*$E$4)+(7500/'EDl log'!$A$38)) -> 250 | G26: =G25 -> 608391 | H26: =G26-G25 -> 0 | I26: =C26+H26 -> 0 | J26: =IF(I26>0,E26/I26,0) -> 0 | K26: ='Swimming Pool quality check '!H26 -> 6555 | L26: =K26-K25 -> 0 | M26: =M25 -> 457.44 | N26: =SUM(M26-M25) -> 0 | O26: =O25 -> 529.52 | P26: =SUM(O26-O25) -> 0 | Q26: =SUM(P26+N26) -> 0 | T26: 5105 | U26: =SUM(T26-T25) -> 3 | V26: =V25 -> 452 | W26: =+V26-V25 -> 0 | X26: 147587 | Y26: =SUM(X26-X25) -> 53 | Z26: =Z25 -> 97015 | AA26: =Z26-Z25 -> 0 | AB26: =AB25 -> 264 | AC26: =AC25 -> 698 | AD26: =AC26-AC25 -> 0 | AE26: =AE25 -> 217.84 | AF26: =AE26-AE25 -> 0 | AG26: =AG25 -> 2176.58 | AH26: =AG26-AG25 -> 0 | AI26: =AF26+AH26 -> 0 | AJ26: =+Z26-Z25 -> 0 | AK26: =SUM(Y26-L26) -> 53 | AL26: =SUM(AJ26-W26) -> 0 | AM26: ='General information '!D26 -> 28.5 | AN26: ='General information '!H26 -> 0 | AP26: ='General information '!J26 -> 0 | AR26: =A26 -> 44095 | AS26: =AS25 -> 0.9 | AT26: 0 | AU26: =AU25 -> 1.1 | AV26: 73 | AW26: 2.9 | AX26: 64 | AY26: =AS26*AT26 -> 0 | AZ26: =AU26*AV26 -> 80.3 | BA26: =AW26*AX26 -> 185.6 | BB26: =AY26-AY25 -> -49.5 | BC26: =AZ26-AZ25 -> -7.7 | BD26: =BA26-BA25 -> 31.9 | BE26: =SUM(BB26:BD26) -> -25.3 | BF26: =SUM(I26-BE26) -> 25.3 | BG26: =SUM(I26-BF26) -> -25.3
A27: =ELEC!C24 -> 44096 | B27: =B26 -> 109096 | C27: =B27-B26 -> 0 | D27: =C27/27 -> 0 | E27: =SUM((C27*$E$4)+(7500/'EDl log'!$A$38)) -> 250 | G27: 608508 | H27: =G27-G26 -> 117 | I27: =C27+H27 -> 117 | J27: =IF(I27>0,E27/I27,0) -> 2.1367521 | K27: ='Swimming Pool quality check '!H27 -> 6555 | L27: =K27-K26 -> 0 | M27: =M26 -> 457.44 | N27: =SUM(M27-M26) -> 0 | O27: =O26 -> 529.52 | P27: =SUM(O27-O26) -> 0 | Q27: =SUM(P27+N27) -> 0 | T27: 5107 | U27: =SUM(T27-T26) -> 2 | V27: =V26 -> 452 | W27: =+V27-V26 -> 0 | X27: 147587 | Y27: =SUM(X27-X26) -> 0 | Z27: =Z26 -> 97015 | AA27: =Z27-Z26 -> 0 | AB27: =AB26 -> 264 | AC27: =AC26 -> 698 | AD27: =AC27-AC26 -> 0 | AE27: =AE26 -> 217.84 | AF27: =AE27-AE26 -> 0 | AG27: =AG26 -> 2176.58 | AH27: =AG27-AG26 -> 0 | AI27: =AF27+AH27 -> 0 | AJ27: =+Z27-Z26 -> 0 | AK27: =SUM(Y27-L27) -> 0 | AL27: =SUM(AJ27-W27) -> 0 | AM27: ='General information '!D27 -> 28.5 | AN27: ='General information '!H27 -> 0 | AP27: ='General information '!J27 -> 0 | AR27: =A27 -> 44096 | AS27: =AS26 -> 0.9 | AT27: 64 | AU27: =AU26 -> 1.1 | AV27: 65 | AW27: 2.9 | AX27: 61 | AY27: =AS27*AT27 -> 57.6 | AZ27: =AU27*AV27 -> 71.5 | BA27: =AW27*AX27 -> 176.9 | BB27: =AY27-AY26 -> 57.6 | BC27: =AZ27-AZ26 -> -8.8 | BD27: =BA27-BA26 -> -8.7 | BE27: =SUM(BB27:BD27) -> 40.1 | BF27: =SUM(I27-BE27) -> 76.9 | BG27: =SUM(I27-BF27) -> 40.1
A28: =ELEC!C25 -> 44097 | B28: =B27 -> 109096 | C28: =B28-B27 -> 0 | D28: =C28/27 -> 0 | E28: =SUM((C28*$E$4)+(7500/'EDl log'!$A$38)) -> 250 | G28: =G27 -> 608508 | H28: =G28-G27 -> 0 | I28: =C28+H28 -> 0 | J28: =IF(I28>0,E28/I28,0) -> 0 | K28: ='Swimming Pool quality check '!H28 -> 6555 | L28: =K28-K27 -> 0 | M28: =M27 -> 457.44 | N28: =SUM(M28-M27) -> 0 | O28: =O27 -> 529.52 | P28: =SUM(O28-O27) -> 0 | Q28: =SUM(P28+N28) -> 0 | T28: 5108 | U28: =SUM(T28-T27) -> 1 | V28: =V27 -> 452 | W28: =+V28-V27 -> 0 | X28: =X27 -> 147587 | Y28: =SUM(X28-X27) -> 0 | Z28: 97015 | AA28: =Z28-Z27 -> 0 | AB28: =AB27 -> 264 | AC28: =AC27 -> 698 | AD28: =AC28-AC27 -> 0 | AE28: =AE27 -> 217.84 | AF28: =AE28-AE27 -> 0 | AG28: =AG27 -> 2176.58 | AH28: =AG28-AG27 -> 0 | AI28: =AF28+AH28 -> 0 | AJ28: =+Z28-Z27 -> 0 | AK28: =SUM(Y28-L28) -> 0 | AL28: =SUM(AJ28-W28) -> 0 | AM28: ='General information '!D28 -> 28 | AN28: ='General information '!H28 -> 0 | AP28: ='General information '!J28 -> 0 | AR28: =A28 -> 44097 | AS28: =AS27 -> 0.9 | AT28: 64 | AU28: =AU27 -> 1.1 | AV28: 57 | AW28: 2.9 | AX28: 55 | AY28: =AS28*AT28 -> 57.6 | AZ28: =AU28*AV28 -> 62.7 | BA28: =AW28*AX28 -> 159.5 | BB28: =AY28-AY27 -> 0 | BC28: =AZ28-AZ27 -> -8.8 | BD28: =BA28-BA27 -> -17.4 | BE28: =SUM(BB28:BD28) -> -26.2 | BF28: =SUM(I28-BE28) -> 26.2 | BG28: =SUM(I28-BF28) -> -26.2
A29: =ELEC!C26 -> 44098 | B29: =B28 -> 109096 | C29: =B29-B28 -> 0 | D29: =C29/27 -> 0 | E29: =SUM((C29*$E$4)+(7500/'EDl log'!$A$38)) -> 250 | G29: 608645 | H29: =G29-G28 -> 137 | I29: =C29+H29 -> 137 | J29: =IF(I29>0,E29/I29,0) -> 1.8248175 | K29: ='Swimming Pool quality check '!H29 -> 6555 | L29: =K29-K28 -> 0 | M29: =M28 -> 457.44 | N29: =SUM(M29-M28) -> 0 | O29: =O28 -> 529.52 | P29: =SUM(O29-O28) -> 0 | Q29: =SUM(P29+N29) -> 0 | T29: 5111 | U29: =SUM(T29-T28) -> 3 | V29: =V28 -> 452 | W29: =+V29-V28 -> 0 | X29: =X28 -> 147587 | Y29: =SUM(X29-X28) -> 0 | Z29: 97035 | AA29: =Z29-Z28 -> 20 | AB29: =AB28 -> 264 | AC29: =AC28 -> 698 | AD29: =AC29-AC28 -> 0 | AE29: =AE28 -> 217.84 | AF29: =AE29-AE28 -> 0 | AG29: =AG28 -> 2176.58 | AH29: =AG29-AG28 -> 0 | AI29: =AF29+AH29 -> 0 | AJ29: =+Z29-Z28 -> 20 | AK29: =SUM(Y29-L29) -> 0 | AL29: =SUM(AJ29-W29) -> 20 | AM29: ='General information '!D29 -> 28.5 | AN29: ='General information '!H29 -> 0 | AP29: ='General information '!J29 -> 0 | AR29: =A29 -> 44098 | AS29: =AS28 -> 0.9 | AT29: 126 | AU29: =AU28 -> 1.1 | AV29: 64 | AW29: 2.9 | AX29: 53 | AY29: =AS29*AT29 -> 113.4 | AZ29: =AU29*AV29 -> 70.4 | BA29: =AW29*AX29 -> 153.7 | BB29: =AY29-AY28 -> 55.8 | BC29: =AZ29-AZ28 -> 7.7 | BD29: =BA29-BA28 -> -5.8 | BE29: =SUM(BB29:BD29) -> 57.7 | BF29: =SUM(I29-BE29) -> 79.3 | BG29: =SUM(I29-BF29) -> 57.7
A30: =ELEC!C27 -> 44099 | B30: =B29 -> 109096 | C30: =B30-B29 -> 0 | D30: =C30/27 -> 0 | E30: =SUM((C30*$E$4)+(7500/'EDl log'!$A$38)) -> 250 | G30: =G29 -> 608645 | H30: =G30-G29 -> 0 | I30: =C30+H30 -> 0 | J30: =IF(I30>0,E30/I30,0) -> 0 | K30: ='Swimming Pool quality check '!H30 -> 6555 | L30: =K30-K29 -> 0 | M30: =M29 -> 457.44 | N30: =SUM(M30-M29) -> 0 | O30: =O29 -> 529.52 | P30: =SUM(O30-O29) -> 0 | Q30: =SUM(P30+N30) -> 0 | T30: 5113 | U30: =SUM(T30-T29) -> 2 | V30: =V29 -> 452 | W30: =+V30-V29 -> 0 | X30: =X29 -> 147587 | Y30: =SUM(X30-X29) -> 0 | Z30: =Z29 -> 97035 | AA30: =Z30-Z29 -> 0 | AB30: =AB29 -> 264 | AC30: =AC29 -> 698 | AD30: =AC30-AC29 -> 0 | AE30: =AE29 -> 217.84 | AF30: =AE30-AE29 -> 0 | AG30: =AG29 -> 2176.58 | AH30: =AG30-AG29 -> 0 | AI30: =AF30+AH30 -> 0 | AJ30: =+Z30-Z29 -> 0 | AK30: =SUM(Y30-L30) -> 0 | AL30: =SUM(AJ30-W30) -> 0 | AM30: ='General information '!D30 -> 27.5 | AN30: ='General information '!H30 -> 0 | AP30: ='General information '!J30 -> 0 | AR30: =A30 -> 44099 | AS30: =AS29 -> 0.9 | AT30: 116 | AU30: =AU29 -> 1.1 | AV30: 57 | AW30: 2.9 | AX30: 51 | AY30: =AS30*AT30 -> 104.4 | AZ30: =AU30*AV30 -> 62.7 | BA30: =AW30*AX30 -> 147.9 | BB30: =AY30-AY29 -> -9 | BC30: =AZ30-AZ29 -> -7.7 | BD30: =BA30-BA29 -> -5.8 | BE30: =SUM(BB30:BD30) -> -22.5 | BF30: =SUM(I30-BE30) -> 22.5 | BG30: =SUM(I30-BF30) -> -22.5
A31: =ELEC!C28 -> 44100 | B31: 109096 | C31: =B31-B30 -> 0 | D31: =C31/27 -> 0 | E31: =SUM((C31*$E$4)+(7500/'EDl log'!$A$38)) -> 250 | G31: 608742 | H31: =G31-G30 -> 97 | I31: =C31+H31 -> 97 | J31: =IF(I31>0,E31/I31,0) -> 2.5773196 | K31: ='Swimming Pool quality check '!H31 -> 6555 | L31: =K31-K30 -> 0 | M31: =M30 -> 457.44 | N31: =SUM(M31-M30) -> 0 | O31: =O30 -> 529.52 | P31: =SUM(O31-O30) -> 0 | Q31: =SUM(P31+N31) -> 0 | T31: 5116 | U31: =SUM(T31-T30) -> 3 | V31: =V30 -> 452 | W31: =+V31-V30 -> 0 | X31: =X30 -> 147587 | Y31: =SUM(X31-X30) -> 0 | Z31: =Z30 -> 97035 | AA31: =Z31-Z30 -> 0 | AB31: =AB30 -> 264 | AC31: =AC30 -> 698 | AD31: =AC31-AC30 -> 0 | AE31: =AE30 -> 217.84 | AF31: =AE31-AE30 -> 0 | AG31: =AG30 -> 2176.58 | AH31: =AG31-AG30 -> 0 | AI31: =AF31+AH31 -> 0 | AJ31: =+Z31-Z30 -> 0 | AK31: =SUM(Y31-L31) -> 0 | AL31: =SUM(AJ31-W31) -> 0 | AM31: ='General information '!D31 -> 28 | AN31: ='General information '!H31 -> 0 | AP31: ='General information '!J31 -> 0 | AR31: =A31 -> 44100 | AS31: =AS30 -> 0.9 | AT31: 172 | AU31: =AU30 -> 1.1 | AV31: 50 | AW31: 2.9 | AX31: 49 | AY31: =AS31*AT31 -> 154.8 | AZ31: =AU31*AV31 -> 55 | BA31: =AW31*AX31 -> 142.1 | BB31: =AY31-AY30 -> 50.4 | BC31: =AZ31-AZ30 -> -7.7 | BD31: =BA31-BA30 -> -5.8 | BE31: =SUM(BB31:BD31) -> 36.9 | BF31: =SUM(I31-BE31) -> 60.1 | BG31: =SUM(I31-BF31) -> 36.9
A32: =ELEC!C29 -> 44101 | B32: =B31 -> 109096 | C32: =B32-B31 -> 0 | D32: =C32/27 -> 0 | E32: =SUM((C32*$E$4)+(7500/'EDl log'!$A$38)) -> 250 | G32: =G31 -> 608742 | H32: =G32-G31 -> 0 | I32: =C32+H32 -> 0 | J32: =IF(I32>0,E32/I32,0) -> 0 | K32: ='Swimming Pool quality check '!H32 -> 6555 | L32: =K32-K31 -> 0 | M32: =M31 -> 457.44 | N32: =SUM(M32-M31) -> 0 | O32: =O31 -> 529.52 | P32: =SUM(O32-O31) -> 0 | Q32: =SUM(P32+N32) -> 0 | T32: 5117 | U32: =SUM(T32-T31) -> 1 | V32: =V31 -> 452 | W32: =+V32-V31 -> 0 | X32: =X31 -> 147587 | Y32: =SUM(X32-X31) -> 0 | Z32: =Z31 -> 97035 | AA32: =Z32-Z31 -> 0 | AB32: =AB31 -> 264 | AC32: =AC31 -> 698 | AD32: =AC32-AC31 -> 0 | AE32: =AE31 -> 217.84 | AF32: =AE32-AE31 -> 0 | AG32: =AG31 -> 2176.58 | AH32: =AG32-AG31 -> 0 | AI32: =AF32+AH32 -> 0 | AJ32: =+Z32-Z31 -> 0 | AK32: =SUM(Y32-L32) -> 0 | AL32: =SUM(AJ32-W32) -> 0 | AM32: ='General information '!D32 -> 27.5 | AN32: ='General information '!H32 -> 0 | AP32: ='General information '!J32 -> 0 | AR32: =A32 -> 44101 | AS32: =AS31 -> 0.9 | AT32: =AT31 -> 172 | AU32: =AU31 -> 1.1 | AV32: 43 | AW32: 2.9 | AX32: 44 | AY32: =AS32*AT32 -> 154.8 | AZ32: =AU32*AV32 -> 47.3 | BA32: =AW32*AX32 -> 127.6 | BB32: =AY32-AY31 -> 0 | BC32: =AZ32-AZ31 -> -7.7 | BD32: =BA32-BA31 -> -14.5 | BE32: =SUM(BB32:BD32) -> -22.2 | BF32: =SUM(I32-BE32) -> 22.2 | BG32: =SUM(I32-BF32) -> -22.2
A33: =ELEC!C30 -> 44102 | B33: 109096 | C33: =B33-B32 -> 0 | D33: =C33/27 -> 0 | E33: =SUM((C33*$E$4)+(7500/'EDl log'!$A$38)) -> 250 | G33: =G32 -> 608742 | H33: =G33-G32 -> 0 | I33: =C33+H33 -> 0 | J33: =IF(I33>0,E33/I33,0) -> 0 | K33: ='Swimming Pool quality check '!H33 -> 6555 | L33: =K33-K32 -> 0 | M33: =M32 -> 457.44 | N33: =SUM(M33-M32) -> 0 | O33: =O32 -> 529.52 | P33: =SUM(O33-O32) -> 0 | Q33: =SUM(P33+N33) -> 0 | T33: 5120 | U33: =SUM(T33-T32) -> 3 | V33: =V32 -> 452 | W33: =+V33-V32 -> 0 | X33: =X32 -> 147587 | Y33: =SUM(X33-X32) -> 0 | Z33: =Z32 -> 97035 | AA33: =Z33-Z32 -> 0 | AB33: =AB32 -> 264 | AC33: =AC32 -> 698 | AD33: =AC33-AC32 -> 0 | AE33: =AE32 -> 217.84 | AF33: =AE33-AE32 -> 0 | AG33: =AG32 -> 2176.58 | AH33: =AG33-AG32 -> 0 | AI33: =AF33+AH33 -> 0 | AJ33: =+Z33-Z32 -> 0 | AK33: =SUM(Y33-L33) -> 0 | AL33: =SUM(AJ33-W33) -> 0 | AM33: ='General information '!D33 -> 27.5 | AN33: ='General information '!H33 -> 0 | AP33: ='General information '!J33 -> 0 | AR33: =A33 -> 44102 | AS33: =AS32 -> 0.9 | AT33: 172 | AU33: =AU32 -> 1.1 | AV33: 36 | AW33: 2.9 | AX33: 39 | AY33: =AS33*AT33 -> 154.8 | AZ33: =AU33*AV33 -> 39.6 | BA33: =AW33*AX33 -> 113.1 | BB33: =AY33-AY32 -> 0 | BC33: =AZ33-AZ32 -> -7.7 | BD33: =BA33-BA32 -> -14.5 | BE33: =SUM(BB33:BD33) -> -22.2 | BF33: =SUM(I33-BE33) -> 22.2 | BG33: =SUM(I33-BF33) -> -22.2
A34: =ELEC!C31 -> 44103 | B34: =B33 -> 109096 | C34: =B34-B33 -> 0 | D34: =C34/27 -> 0 | E34: =SUM((C34*$E$4)+(7500/'EDl log'!$A$38)) -> 250 | G34: =G33 -> 608742 | H34: =G34-G33 -> 0 | I34: =C34+H34 -> 0 | J34: =IF(I34>0,E34/I34,0) -> 0 | K34: ='Swimming Pool quality check '!H34 -> 6555 | L34: =K34-K33 -> 0 | M34: =M33 -> 457.44 | N34: =SUM(M34-M33) -> 0 | O34: =O33 -> 529.52 | P34: =SUM(O34-O33) -> 0 | Q34: =SUM(P34+N34) -> 0 | T34: 5122 | U34: =SUM(T34-T33) -> 2 | V34: =V33 -> 452 | W34: =+V34-V33 -> 0 | X34: =X33 -> 147587 | Y34: =SUM(X34-X33) -> 0 | Z34: =Z33 -> 97035 | AA34: =Z34-Z33 -> 0 | AB34: =AB33 -> 264 | AC34: =AC33 -> 698 | AD34: =AC34-AC33 -> 0 | AE34: =AE33 -> 217.84 | AF34: =AE34-AE33 -> 0 | AG34: =AG33 -> 2176.58 | AH34: =AG34-AG33 -> 0 | AI34: =AF34+AH34 -> 0 | AJ34: =+Z34-Z33 -> 0 | AK34: =SUM(Y34-L34) -> 0 | AL34: =SUM(AJ34-W34) -> 0 | AM34: ='General information '!D34 -> 28.5 | AN34: ='General information '!H34 -> 0 | AP34: ='General information '!J34 -> 0 | AR34: =A34 -> 44103 | AS34: =AS33 -> 0.9 | AT34: =AT33 -> 172 | AU34: =AU33 -> 1.1 | AV34: 30 | AW34: 2.9 | AX34: 33 | AY34: =AS34*AT34 -> 154.8 | AZ34: =AU34*AV34 -> 33 | BA34: =AW34*AX34 -> 95.7 | BB34: =AY34-AY33 -> 0 | BC34: =AZ34-AZ33 -> -6.6 | BD34: =BA34-BA33 -> -17.4 | BE34: =SUM(BB34:BD34) -> -24 | BF34: =SUM(I34-BE34) -> 24 | BG34: =SUM(I34-BF34) -> -24
A35: =ELEC!C32 -> 44104 | B35: =B34 -> 109096 | C35: =B35-B34 -> 0 | D35: =C35/27 -> 0 | E35: =SUM((C35*$E$4)+(7500/'EDl log'!$A$38)) -> 250 | G35: =G34 -> 608742 | H35: =G35-G34 -> 0 | I35: =C35+H35 -> 0 | J35: =IF(I35>0,E35/I35,0) -> 0 | K35: ='Swimming Pool quality check '!H35 -> 6555 | L35: =K35-K34 -> 0 | M35: =M34 -> 457.44 | N35: =SUM(M35-M34) -> 0 | O35: =O34 -> 529.52 | P35: =SUM(O35-O34) -> 0 | Q35: =SUM(P35+N35) -> 0 | T35: 5125 | U35: =SUM(T35-T34) -> 3 | V35: =V34 -> 452 | W35: =+V35-V34 -> 0 | X35: 147647 | Y35: =SUM(X35-X34) -> 60 | Z35: 97058 | AA35: =Z35-Z34 -> 23 | AB35: =AB34 -> 264 | AC35: =AC34 -> 698 | AD35: =AC35-AC34 -> 0 | AE35: =AE34 -> 217.84 | AF35: =AE35-AE34 -> 0 | AG35: =AG34 -> 2176.58 | AH35: =AG35-AG34 -> 0 | AI35: =AF35+AH35 -> 0 | AJ35: =+Z35-Z34 -> 23 | AK35: =SUM(Y35-L35) -> 60 | AL35: =SUM(AJ35-W35) -> 23 | AM35: ='General information '!D35 -> 28.5 | AN35: ='General information '!H35 -> 0 | AP35: ='General information '!J35 -> 0 | AR35: =A35 -> 44104 | AS35: =AS34 -> 0.9 | AT35: 63 | AU35: =AU34 -> 1.1 | AV35: 41 | AW35: 2.9 | AX35: 44 | AY35: =AS35*AT35 -> 56.7 | AZ35: =AU35*AV35 -> 45.1 | BA35: =AW35*AX35 -> 127.6 | BB35: =AY35-AY34 -> -98.1 | BC35: =AZ35-AZ34 -> 12.1 | BD35: =BA35-BA34 -> 31.9 | BE35: =SUM(BB35:BD35) -> -54.1 | BF35: =SUM(I35-BE35) -> 54.1 | BG35: =SUM(I35-BF35) -> -54.1
C36: =SUM(C6:C35) -> 0 | D36: =SUM(D6:D35) -> 0 | F36: =SUM(F6:F35) -> 0 | H36: =SUM(H6:H35) -> 918 | I36: =SUM(I6:I35) -> 918 | L36: =SUM(L7:L35) -> 12 | Q36: =SUM(Q5:Q35) -> 0 | U36: =SUM(U6:U35) -> 78 | Y36: =SUM(Y35,Y33,Y31,Y29,Y27,Y25,Y23,Y21,Y19,Y17,Y15,Y13,Y11,Y9,Y7+#REF!) -> #REF! | AJ36: =SUM(AJ6:AJ35) -> 259 | AK36: =SUM(Y36-L36) -> #REF! | AL36: =SUM(AL6:AL35) -> 234
C37: =+C36*1.66 -> 0 | E37: =SUM(E6:E35) -> 7500 | F37: =SUM(F6:F35) -> 0 | H37: 7500 | I37: =SUM('General information '!G36/WATER!I36) -> 0 | O37: =SUM(Q36+I36) -> 918 | Z37: =SUM(Y36:AJ36) -> #REF! | AK37: =SUM(Y37-L37) -> 0
B38: =9*27 -> 243 | D38: =SUM(D21:D35) -> 0 | F38: =SUM(F6:F35) -> 0 | G38: =SUM(I36) -> 918 | H38: =SUM(H37+C37) -> 7500 | K38: =SUM(H38/G38) -> 8.1699346 | AJ38: =SUM(C37-AK37) -> 0 | AM38: =SUM(AJ38/AO37) -> #DIV/0!

Sheet graphic

Sheet General information 
A1: GENERAL & HOTEL'S INFORMATION SHEET
B4: Max Temp | C4: MIN TEMP | D4: AVE TEMP | E4: AVE Humidity | F4: AVE OCC | G4: # of OCC Rooms | H4: Ball room | I4: Meeting rooms | J4: Outlets | K4: Total covers | L4: # of permenant Emp | M4: # of casuals | N4: Total # of EMP | O4: # of EMP/OCC Room
A5: =ELEC!C2 -> 44074 | B5: ='[1]General information '!B36 -> 32 | C5: ='[1]General information '!C36 -> 28 | D5: ='[1]General information '!D36 -> 30 | E5: ='[1]General information '!E36 -> 0.76 | F5: ='[1]General information '!F36 -> 0 | G5: ='[1]General information '!G36 -> 0 | H5: ='[1]General information '!H36 -> 0 | I5: ='[1]General information '!I36 -> 0 | ... O5: ='[1]General information '!O36 -> 0
A6: =ELEC!C3 -> 44075 | B6: 32 | C6: 28 | D6: =(C6+B6)/2 -> 30 | E6: 0.8 | F6: 0 | G6: =F6*230 -> 0 | K6: =+J6+H6 -> 0
A7: =ELEC!C4 -> 44076 | B7: 31 | C7: 27 | D7: =(C7+B7)/2 -> 29 | E7: 0.76 | F7: 0 | G7: =F7*230 -> 0 | K7: =+J7+H7 -> 0
A8: =ELEC!C5 -> 44077 | B8: 34 | C8: 29 | D8: =(C8+B8)/2 -> 31.5 | E8: 0.71 | F8: 0 | G8: =F8*230 -> 0 | K8: =+J8+H8 -> 0
A9: =ELEC!C6 -> 44078 | B9: 33 | C9: 27 | D9: =(C9+B9)/2 -> 30 | E9: 0.71 | F9: 0 | G9: =F9*230 -> 0 | K9: =+J9+H9 -> 0
A10: =ELEC!C7 -> 44079 | B10: 31 | C10: 25 | D10: =(C10+B10)/2 -> 28 | E10: 0.64 | F10: 0 | G10: =F10*230 -> 0 | K10: =+J10+H10 -> 0
A11: =ELEC!C8 -> 44080 | B11: 31 | C11: 25 | D11: =(C11+B11)/2 -> 28 | E11: 0.76 | F11: 0 | G11: =F11*230 -> 0 | K11: =+J11+H11 -> 0
A12: =ELEC!C9 -> 44081 | B12: 32 | C12: 27 | D12: =(C12+B12)/2 -> 29.5 | E12: 0.75 | F12: 0 | G12: =F12*230 -> 0 | K12: =+J12+H12 -> 0
A13: =ELEC!C10 -> 44082 | B13: 32 | C13: 27 | D13: =(C13+B13)/2 -> 29.5 | E13: 0.76 | F13: 0 | G13: =F13*230 -> 0 | K13: =+J13+H13 -> 0
A14: =ELEC!C11 -> 44083 | B14: 31 | C14: 28 | D14: =(C14+B14)/2 -> 29.5 | E14: 0.75 | F14: 0 | G14: =F14*230 -> 0 | K14: =+J14+H14 -> 0
A15: =ELEC!C12 -> 44084 | B15: 32 | C15: 26 | D15: =(C15+B15)/2 -> 29 | E15: 0.64 | F15: 0 | G15: =F15*230 -> 0 | K15: =+J15+H15 -> 0
A16: =ELEC!C13 -> 44085 | B16: 32 | C16: 28 | D16: =(C16+B16)/2 -> 30 | E16: 0.77 | F16: 0 | G16: =F16*230 -> 0 | K16: =+J16+H16 -> 0
A17: =ELEC!C14 -> 44086 | B17: 31 | C17: 28 | D17: =(C17+B17)/2 -> 29.5 | E17: 0.75 | F17: 0 | G17: =F17*230 -> 0 | K17: =+J17+H17 -> 0
A18: =ELEC!C15 -> 44087 | B18: 31 | C18: 25 | D18: =(C18+B18)/2 -> 28 | E18: 0.62 | F18: 0 | G18: =F18*230 -> 0 | K18: =+J18+H18 -> 0
A19: =ELEC!C16 -> 44088 | B19: 31 | C19: 26 | D19: =(C19+B19)/2 -> 28.5 | E19: 0.69 | F19: 0 | G19: 0 | K19: =+J19+H19 -> 0
A20: =ELEC!C17 -> 44089 | B20: 30 | C20: 23 | D20: =(C20+B20)/2 -> 26.5 | E20: 0.74 | F20: 0 | G20: =F20*230 -> 0 | K20: =+J20+H20 -> 0
A21: =ELEC!C18 -> 44090 | B21: 31 | C21: 26 | D21: =(C21+B21)/2 -> 28.5 | E21: 0.72 | F21: 0 | G21: =F21*230 -> 0 | K21: =+J21+H21 -> 0
A22: =ELEC!C19 -> 44091 | B22: 30 | C22: 26 | D22: =(C22+B22)/2 -> 28 | E22: 0.75 | F22: 0 | G22: =F22*230 -> 0 | K22: =+J22+H22 -> 0
A23: =ELEC!C20 -> 44092 | B23: 30 | C23: 25 | D23: =(C23+B23)/2 -> 27.5 | E23: 0.77 | F23: 0 | G23: =F23*230 -> 0 | K23: =+J23+H23 -> 0
A24: =ELEC!C21 -> 44093 | B24: 32 | C24: 25 | D24: =(C24+B24)/2 -> 28.5 | E24: 0.64 | F24: 0 | G24: =F24*230 -> 0 | K24: =+J24+H24 -> 0
A25: =ELEC!C22 -> 44094 | B25: 30 | C25: 22 | D25: =(C25+B25)/2 -> 26 | E25: 0.65 | F25: 0 | G25: =F25*230 -> 0 | K25: =+J25+H25 -> 0
A26: =ELEC!C23 -> 44095 | B26: 30 | C26: 27 | D26: =(C26+B26)/2 -> 28.5 | E26: 0.64 | F26: 0 | G26: =F26*230 -> 0 | K26: =+J26+H26 -> 0
A27: =ELEC!C24 -> 44096 | B27: 30 | C27: 27 | D27: =(C27+B27)/2 -> 28.5 | E27: 0.65 | F27: 0 | G27: =F27*230 -> 0 | K27: =+J27+H27+I27 -> 0
A28: =ELEC!C25 -> 44097 | B28: 30 | C28: 26 | D28: =(C28+B28)/2 -> 28 | E28: 0.67 | F28: 0 | G28: =F28*230 -> 0 | K28: =+J28+H28+I28 -> 0
A29: =ELEC!C26 -> 44098 | B29: 31 | C29: 26 | D29: =(C29+B29)/2 -> 28.5 | E29: 0.66 | F29: 0 | G29: =F29*230 -> 0 | K29: =+J29+H29+I29 -> 0
A30: =ELEC!C27 -> 44099 | B30: 29 | C30: 26 | D30: =(C30+B30)/2 -> 27.5 | E30: 0.65 | F30: 0 | G30: =F30*230 -> 0 | K30: =+J30+H30+I30 -> 0
A31: =ELEC!C28 -> 44100 | B31: 30 | C31: 26 | D31: =(C31+B31)/2 -> 28 | E31: 0.65 | F31: 0 | G31: =F31*230 -> 0 | K31: =+J31+H31+I31 -> 0
A32: =ELEC!C29 -> 44101 | B32: 30 | C32: 25 | D32: =(C32+B32)/2 -> 27.5 | E32: 0.55 | F32: 0 | G32: =F32*230 -> 0 | K32: =+J32+H32+I32 -> 0
A33: =ELEC!C30 -> 44102 | B33: 30 | C33: 25 | D33: =(C33+B33)/2 -> 27.5 | E33: 0.49 | F33: 0 | G33: =F33*230 -> 0 | K33: =+J33+H33+I33 -> 0
A34: =ELEC!C31 -> 44103 | B34: 32 | C34: 25 | D34: =(C34+B34)/2 -> 28.5 | E34: 0.59 | F34: 0 | G34: =F34*230 -> 0 | K34: =+J34+H34+I34 -> 0
A35: =ELEC!C32 -> 44104 | B35: 31 | C35: 26 | D35: =(C35+B35)/2 -> 28.5 | E35: 0.65 | F35: 0 | G35: =F35*230 -> 0 | K35: =+J35+H35+I35 -> 0
F36: =AVERAGE(F6:F35) -> 0 | G36: =SUM(G6:G35) -> 0
D37: =SUM(D6:D35)/'EDl log'!A36 -> 28.533333
I40: http://www.accuweather.com/en/lb/lebanon-weather

Sheet tanks
B2: Tank 1 | D2: Tank 2 | F2: Tank 3 | H2: Tank 4 | J2: Tank 5 | L2: Tank 6 | N2: Tank 7 | P2: Tank 8 | R2: Tank 9 | T2: Tank 10 | V2: Tank 11 | Z2: Tank 1 | AB2: Tank 2 | AD2: Tank 3 | AF2: Tank 4 | AH2: Tank 5 | AJ2: Tank 6 | AL2: Tank 7
B3: 6670 | D3: =SUM(B3) -> 6670 | F3: =SUM(D3) -> 6670 | H3: =SUM(F3) -> 6670 | J3: =SUM(H3) -> 6670 | L3: =SUM(J3) -> 6670 | N3: =SUM(L3) -> 6670 | P3: =SUM(N3) -> 6670 | R3: =SUM(P3) -> 6670 | T3: =SUM(R3) -> 6670 | V3: =SUM(T3) -> 6670 | W3: =SUM(B3:V3) -> 73370 | Z3: 2800 | AB3: 2800 | AD3: 2800 | AF3: 2800 | AH3: 2800 | AJ3: 2800 | AL3: 2800 | AM3: =SUM(Z3:AL3) -> 19600 | AO3: =SUM(AM3+W3) -> 92970 | AR3: Total sotck | AS3: Diesel Cons Per day | AT3: Diesel Delivery | BE3: Genset Co | BF3: Steam | BG3: Boil | BH3: Outdoor temperature
B4: =B3/310 -> 21.516129 | D4: =SUM(B4) -> 21.516129 | F4: =SUM(D4) -> 21.516129 | H4: =SUM(F4) -> 21.516129 | J4: =SUM(H4) -> 21.516129 | L4: =SUM(J4) -> 21.516129 | N4: =SUM(L4) -> 21.516129 | P4: =SUM(N4) -> 21.516129 | R4: =SUM(P4) -> 21.516129 | T4: =SUM(R4) -> 21.516129 | V4: =SUM(T4) -> 21.516129 | Z4: =Z3/280 -> 10 | AA4: =AA3/280 -> 0 | AB4: =AB3/280 -> 10 | AC4: =AC3/280 -> 0 | AD4: =AD3/280 -> 10 | AE4: =AE3/280 -> 0 | AF4: =AF3/280 -> 10 | AG4: =AG3/280 -> 0 | ... AL4: =AL3/280 -> 10 | AT4: Delivery | AU4: Cost /L | AW4: Boiler+Steam | AX4: Generator | AZ4: Occupancy | BA4: AVE TEPM | BB4: AVE Humidity
A5: =ELEC!C2 -> 44074 | B5: =[1]tanks!B36 -> 239 | C5: =[1]tanks!C36 -> 5142.3548 | D5: =[1]tanks!D36 -> 239 | E5: =[1]tanks!E36 -> 5142.3548 | F5: =[1]tanks!F36 -> 239 | G5: =[1]tanks!G36 -> 5142.3548 | H5: =[1]tanks!H36 -> 239 | I5: =[1]tanks!I36 -> 5142.3548 | ... BB5: =[1]tanks!BB36 -> 0.76 | BC5: =[2]tanks!BC36 -> 1 | BD5: =[2]tanks!BD36 -> 19222 | BE5: =[2]tanks!BE36 -> #REF! | BF5: =[2]tanks!BF36 -> 0 | BG5: =[2]tanks!BG36 -> #REF! | BH5: =[2]tanks!BH36 -> 0
A6: =ELEC!C3 -> 44075 | B6: ='B5'!B5 -> 236 | C6: =B6*$B$4 -> 5077.8065 | D6: =SUM(B6) -> 236 | E6: =D6*$B$4 -> 5077.8065 | F6: =SUM(D6) -> 236 | G6: =F6*$B$4 -> 5077.8065 | H6: =SUM(F6) -> 236 | I6: =H6*$B$4 -> 5077.8065 | J6: =SUM(H6) -> 236 | K6: =J6*$B$4 -> 5077.8065 | L6: =SUM(J6) -> 236 | M6: =L6*$B$4 -> 5077.8065 | N6: =SUM(L6) -> 236 | O6: =N6*$B$4 -> 5077.8065 | P6: =SUM(N6) -> 236 | Q6: =P6*$B$4 -> 5077.8065 | R6: =SUM(P6) -> 236 | S6: =R6*$B$4 -> 5077.8065 | T6: =SUM(R6) -> 236 | U6: =T6*$B$4 -> 5077.8065 | V6: =SUM(T6) -> 236 | W6: =V6*$B$4 -> 5077.8065 | X6: =SUM(Y6/73370) -> 0.76129032 | Y6: =SUM(C6+E6+G6+I6+K6+M6+O6+Q6+S6+U6+W6) -> 55855.871 | Z6: ='B5'!C5 -> 242 | AA6: =SUM(Z6*$Z$4) -> 2420 | AB6: =SUM(Z6) -> 242 | AC6: =SUM(AB6*$Z$4) -> 2420 | AD6: =SUM(AB6) -> 242 | AE6: =SUM(AD6*$Z$4) -> 2420 | AF6: =SUM(AD6) -> 242 | AG6: =SUM(AF6*$Z$4) -> 2420 | AH6: =SUM(AF6) -> 242 | AI6: =SUM(AH6*$Z$4) -> 2420 | AJ6: =SUM(AH6) -> 242 | AK6: =SUM(AJ6*$Z$4) -> 2420 | AL6: =SUM(AJ6) -> 242 | AM6: =SUM(AL6*$Z$4) -> 2420 | AN6: =SUM(AO6/19600) -> 0.86428571 | AO6: =SUM(AA6+AC6+AE6+AG6+AI6+AK6+AM6) -> 16940 | AQ6: =SUM(AR6/92970) -> 0.78300388 | AR6: =SUM(AO6+Y6) -> 72795.871 | AS6: =SUM(AR6-AR5-AT6) -> -850.03226 | AV6: =IF(AT6>0,AU6,AV5) -> 0.53 | AW6: =-SUM('B5'!AI5) -> -155 | AX6: =-SUM(AW6-AS6) -> -695.03226 | AY6: =SUM(AX6+AW6) -> -850.03226 | AZ6: =ELEC!A3 -> 0 | BA6: ='General information '!D6 -> 30 | BB6: =SUM('General information '!E6) -> 0.8 | BC6: =IF(AR3>=AR6,0,1) -> 0 | BD6: 19222 | BE6: =(305/1185)*ELEC!Q4 -> 1286.9198 | BG6: =#REF!-BE6 -> #REF! | BH6: 21
A7: =ELEC!C4 -> 44076 | B7: ='B5'!B6 -> 231 | C7: =B7*$B$4 -> 4970.2258 | D7: =SUM(B7) -> 231 | E7: =D7*$B$4 -> 4970.2258 | F7: =SUM(D7) -> 231 | G7: =F7*$B$4 -> 4970.2258 | H7: =SUM(F7) -> 231 | I7: =H7*$B$4 -> 4970.2258 | J7: =SUM(H7) -> 231 | K7: =J7*$B$4 -> 4970.2258 | L7: =SUM(J7) -> 231 | M7: =L7*$B$4 -> 4970.2258 | N7: =SUM(L7) -> 231 | O7: =N7*$B$4 -> 4970.2258 | P7: =SUM(N7) -> 231 | Q7: =P7*$B$4 -> 4970.2258 | R7: =SUM(P7) -> 231 | S7: =R7*$B$4 -> 4970.2258 | T7: =SUM(R7) -> 231 | U7: =T7*$B$4 -> 4970.2258 | V7: =SUM(T7) -> 231 | W7: =V7*$B$4 -> 4970.2258 | X7: =SUM(Y7/73370) -> 0.74516129 | Y7: =SUM(C7+E7+G7+I7+K7+M7+O7+Q7+S7+U7+W7) -> 54672.484 | Z7: ='B5'!C6 -> 237 | AA7: =SUM(Z7*$Z$4) -> 2370 | AB7: =SUM(Z7) -> 237 | AC7: =SUM(AB7*$Z$4) -> 2370 | AD7: =SUM(AB7) -> 237 | AE7: =SUM(AD7*$Z$4) -> 2370 | AF7: =SUM(AD7) -> 237 | AG7: =SUM(AF7*$Z$4) -> 2370 | AH7: =SUM(AF7) -> 237 | AI7: =SUM(AH7*$Z$4) -> 2370 | AJ7: =SUM(AH7) -> 237 | AK7: =SUM(AJ7*$Z$4) -> 2370 | AL7: =SUM(AJ7) -> 237 | AM7: =SUM(AL7*$Z$4) -> 2370 | AN7: =SUM(AO7/19600) -> 0.84642857 | AO7: =SUM(AA7+AC7+AE7+AG7+AI7+AK7+AM7) -> 16590 | AQ7: =SUM(AR7/92970) -> 0.76651053 | AR7: =SUM(AO7+Y7) -> 71262.484 | AS7: =SUM(AR7-AR6-AT7) -> -1533.3871 | AV7: =IF(AT7>0,AU7,AV6) -> 0.53 | AW7: =-SUM('B5'!AI6) -> 0 | AX7: =-SUM(AW7-AS7) -> -1533.3871 | AY7: =SUM(AX7+AW7) -> -1533.3871 | AZ7: =ELEC!A4 -> 0 | BA7: ='General information '!D7 -> 29 | BB7: =SUM('General information '!E7) -> 0.76 | BC7: 0 | BD7: 19222 | BE7: =(305/1185)*ELEC!Q5 -> 1286.9198 | BG7: =#REF!-BE7 -> #REF! | BH7: 19
A8: =ELEC!C5 -> 44077 | B8: ='B5'!B7 -> 225 | C8: =B8*$B$4 -> 4841.129 | D8: =SUM(B8) -> 225 | E8: =D8*$B$4 -> 4841.129 | F8: =SUM(D8) -> 225 | G8: =F8*$B$4 -> 4841.129 | H8: =SUM(F8) -> 225 | I8: =H8*$B$4 -> 4841.129 | J8: =SUM(H8) -> 225 | K8: =J8*$B$4 -> 4841.129 | L8: =SUM(J8) -> 225 | M8: =L8*$B$4 -> 4841.129 | N8: =SUM(L8) -> 225 | O8: =N8*$B$4 -> 4841.129 | P8: =SUM(N8) -> 225 | Q8: =P8*$B$4 -> 4841.129 | R8: =SUM(P8) -> 225 | S8: =R8*$B$4 -> 4841.129 | T8: =SUM(R8) -> 225 | U8: =T8*$B$4 -> 4841.129 | V8: =SUM(T8) -> 225 | W8: =V8*$B$4 -> 4841.129 | X8: =SUM(Y8/73370) -> 0.72580645 | Y8: =SUM(C8+E8+G8+I8+K8+M8+O8+Q8+S8+U8+W8) -> 53252.419 | Z8: ='B5'!C7 -> 231 | AA8: =SUM(Z8*$Z$4) -> 2310 | AB8: =SUM(Z8) -> 231 | AC8: =SUM(AB8*$Z$4) -> 2310 | AD8: =SUM(AB8) -> 231 | AE8: =SUM(AD8*$Z$4) -> 2310 | AF8: =SUM(AD8) -> 231 | AG8: =SUM(AF8*$Z$4) -> 2310 | AH8: =SUM(AF8) -> 231 | AI8: =SUM(AH8*$Z$4) -> 2310 | AJ8: =SUM(AH8) -> 231 | AK8: =SUM(AJ8*$Z$4) -> 2310 | AL8: =SUM(AJ8) -> 231 | AM8: =SUM(AL8*$Z$4) -> 2310 | AN8: =SUM(AO8/19600) -> 0.825 | AO8: =SUM(AA8+AC8+AE8+AG8+AI8+AK8+AM8) -> 16170 | AQ8: =SUM(AR8/92970) -> 0.7467185 | AR8: =SUM(AO8+Y8) -> 69422.419 | AS8: =SUM(AR8-AR7-AT8) -> -1840.0645 | AV8: =IF(AT8>0,AU8,AV7) -> 0.53 | AW8: =-SUM('B5'!AI7) -> -350 | AX8: =-SUM(AW8-AS8) -> -1490.0645 | AY8: =SUM(AX8+AW8) -> -1840.0645 | AZ8: =ELEC!A5 -> 0 | BA8: ='General information '!D8 -> 31.5 | BB8: =SUM('General information '!E8) -> 0.71 | BC8: =IF(AR7>=AR8,0,1) -> 0 | BD8: 19222 | BE8: =(305/1185)*ELEC!Q6 -> 1286.9198 | BG8: =#REF!-BE8 -> #REF! | BH8: 16
A9: =ELEC!C6 -> 44078 | B9: ='B5'!B8 -> 218.4 | C9: =B9*$B$4 -> 4699.1226 | D9: =SUM(B9) -> 218.4 | E9: =D9*$B$4 -> 4699.1226 | F9: =SUM(D9) -> 218.4 | G9: =F9*$B$4 -> 4699.1226 | H9: =SUM(F9) -> 218.4 | I9: =H9*$B$4 -> 4699.1226 | J9: =SUM(H9) -> 218.4 | K9: =J9*$B$4 -> 4699.1226 | L9: =SUM(J9) -> 218.4 | M9: =L9*$B$4 -> 4699.1226 | N9: =SUM(L9) -> 218.4 | O9: =N9*$B$4 -> 4699.1226 | P9: =SUM(N9) -> 218.4 | Q9: =P9*$B$4 -> 4699.1226 | R9: =SUM(P9) -> 218.4 | S9: =R9*$B$4 -> 4699.1226 | T9: =SUM(R9) -> 218.4 | U9: =T9*$B$4 -> 4699.1226 | V9: =SUM(T9) -> 218.4 | W9: =V9*$B$4 -> 4699.1226 | X9: =SUM(Y9/73370) -> 0.70451613 | Y9: =SUM(C9+E9+G9+I9+K9+M9+O9+Q9+S9+U9+W9) -> 51690.348 | Z9: ='B5'!C8 -> 224.3 | AA9: =SUM(Z9*$Z$4) -> 2243 | AB9: =SUM(Z9) -> 224.3 | AC9: =SUM(AB9*$Z$4) -> 2243 | AD9: =SUM(AB9) -> 224.3 | AE9: =SUM(AD9*$Z$4) -> 2243 | AF9: =SUM(AD9) -> 224.3 | AG9: =SUM(AF9*$Z$4) -> 2243 | AH9: =SUM(AF9) -> 224.3 | AI9: =SUM(AH9*$Z$4) -> 2243 | AJ9: =SUM(AH9) -> 224.3 | AK9: =SUM(AJ9*$Z$4) -> 2243 | AL9: =SUM(AJ9) -> 224.3 | AM9: =SUM(AL9*$Z$4) -> 2243 | AN9: =SUM(AO9/19600) -> 0.80107143 | AO9: =SUM(AA9+AC9+AE9+AG9+AI9+AK9+AM9) -> 15701 | AQ9: =SUM(AR9/92970) -> 0.72487198 | AR9: =SUM(AO9+Y9) -> 67391.348 | AS9: =SUM(AR9-AR8-AT9) -> -2031.071 | AV9: =IF(AT9>0,AU9,AV8) -> 0.53 | AW9: =-SUM('B5'!AI8) -> -303 | AX9: =-SUM(AW9-AS9) -> -1728.071 | AY9: =SUM(AX9+AW9) -> -2031.071 | AZ9: =ELEC!A6 -> 0 | BA9: ='General information '!D9 -> 30 | BB9: =SUM('General information '!E9) -> 0.71 | BC9: =IF(AR8>=AR9,0,1) -> 0 | BD9: 19222 | BE9: =(305/1185)*ELEC!Q7 -> 514.76793 | BG9: =#REF!-BE9 -> #REF! | BH9: 18
A10: =ELEC!C7 -> 44079 | B10: ='B5'!B9 -> 216 | C10: =B10*$B$4 -> 4647.4839 | D10: =SUM(B10) -> 216 | E10: =D10*$B$4 -> 4647.4839 | F10: =SUM(D10) -> 216 | G10: =F10*$B$4 -> 4647.4839 | H10: =SUM(F10) -> 216 | I10: =H10*$B$4 -> 4647.4839 | J10: =SUM(H10) -> 216 | K10: =J10*$B$4 -> 4647.4839 | L10: =SUM(J10) -> 216 | M10: =L10*$B$4 -> 4647.4839 | N10: =SUM(L10) -> 216 | O10: =N10*$B$4 -> 4647.4839 | P10: =SUM(N10) -> 216 | Q10: =P10*$B$4 -> 4647.4839 | R10: =SUM(P10) -> 216 | S10: =R10*$B$4 -> 4647.4839 | T10: =SUM(R10) -> 216 | U10: =T10*$B$4 -> 4647.4839 | V10: =SUM(T10) -> 216 | W10: =V10*$B$4 -> 4647.4839 | X10: =SUM(Y10/73370) -> 0.69677419 | Y10: =SUM(C10+E10+G10+I10+K10+M10+O10+Q10+S10+U10+W10) -> 51122.323 | Z10: ='B5'!C9 -> 222 | AA10: =SUM(Z10*$Z$4) -> 2220 | AB10: =SUM(Z10) -> 222 | AC10: =SUM(AB10*$Z$4) -> 2220 | AD10: =SUM(AB10) -> 222 | AE10: =SUM(AD10*$Z$4) -> 2220 | AF10: =SUM(AD10) -> 222 | AG10: =SUM(AF10*$Z$4) -> 2220 | AH10: =SUM(AF10) -> 222 | AI10: =SUM(AH10*$Z$4) -> 2220 | AJ10: =SUM(AH10) -> 222 | AK10: =SUM(AJ10*$Z$4) -> 2220 | AL10: =SUM(AJ10) -> 222 | AM10: =SUM(AL10*$Z$4) -> 2220 | AN10: =SUM(AO10/19600) -> 0.79285714 | AO10: =SUM(AA10+AC10+AE10+AG10+AI10+AK10+AM10) -> 15540 | AQ10: =SUM(AR10/92970) -> 0.71703047 | AR10: =SUM(AO10+Y10) -> 66662.323 | AS10: =SUM(AR10-AR9-AT10) -> -729.02581 | AV10: =IF(AT10>0,AU10,AV9) -> 0.53 | AW10: =-SUM('B5'!AI9) -> 0 | AX10: =-SUM(AW10-AS10) -> -729.02581 | AY10: =SUM(AX10+AW10) -> -729.02581 | AZ10: =ELEC!A7 -> 0 | BA10: ='General information '!D10 -> 28 | BB10: =SUM('General information '!E10) -> 0.64 | BC10: =IF(AR9>=AR10,0,1) -> 0 | BD10: 19222 | BE10: =(305/1185)*ELEC!Q8 -> 1029.5359 | BG10: =#REF!-BE10 -> #REF! | BH10: 16
A11: =ELEC!C8 -> 44080 | B11: ='B5'!B10 -> 211 | C11: =B11*$B$4 -> 4539.9032 | D11: =SUM(B11) -> 211 | E11: =D11*$B$4 -> 4539.9032 | F11: =SUM(D11) -> 211 | G11: =F11*$B$4 -> 4539.9032 | H11: =SUM(F11) -> 211 | I11: =H11*$B$4 -> 4539.9032 | J11: =SUM(H11) -> 211 | K11: =J11*$B$4 -> 4539.9032 | L11: =SUM(J11) -> 211 | M11: =L11*$B$4 -> 4539.9032 | N11: =SUM(L11) -> 211 | O11: =N11*$B$4 -> 4539.9032 | P11: =SUM(N11) -> 211 | Q11: =P11*$B$4 -> 4539.9032 | R11: =SUM(P11) -> 211 | S11: =R11*$B$4 -> 4539.9032 | T11: =SUM(R11) -> 211 | U11: =T11*$B$4 -> 4539.9032 | V11: =SUM(T11) -> 211 | W11: =V11*$B$4 -> 4539.9032 | X11: =SUM(Y11/73370) -> 0.68064516 | Y11: =SUM(C11+E11+G11+I11+K11+M11+O11+Q11+S11+U11+W11) -> 49938.935 | Z11: ='B5'!C10 -> 218 | AA11: =SUM(Z11*$Z$4) -> 2180 | AB11: =SUM(Z11) -> 218 | AC11: =SUM(AB11*$Z$4) -> 2180 | AD11: =SUM(AB11) -> 218 | AE11: =SUM(AD11*$Z$4) -> 2180 | AF11: =SUM(AD11) -> 218 | AG11: =SUM(AF11*$Z$4) -> 2180 | AH11: =SUM(AF11) -> 218 | AI11: =SUM(AH11*$Z$4) -> 2180 | AJ11: =SUM(AH11) -> 218 | AK11: =SUM(AJ11*$Z$4) -> 2180 | AL11: =SUM(AJ11) -> 218 | AM11: =SUM(AL11*$Z$4) -> 2180 | AN11: =SUM(AO11/19600) -> 0.77857143 | AO11: =SUM(AA11+AC11+AE11+AG11+AI11+AK11+AM11) -> 15260 | AQ11: =SUM(AR11/92970) -> 0.70129005 | AR11: =SUM(AO11+Y11) -> 65198.935 | AS11: =SUM(AR11-AR10-AT11) -> -1463.3871 | AV11: =IF(AT11>0,AU11,AV10) -> 0.53 | AW11: =-SUM('B5'!AI10) -> 0 | AX11: =-SUM(AW11-AS11) -> -1463.3871 | AY11: =SUM(AX11+AW11) -> -1463.3871 | AZ11: =ELEC!A8 -> 0 | BA11: ='General information '!D11 -> 28 | BB11: =SUM('General information '!E11) -> 0.76 | BC11: =IF(AR10>=AR11,0,1) -> 0 | BD11: 19222 | BE11: =(305/1185)*ELEC!Q9 -> 1286.9198 | BG11: =#REF!-BE11 -> #REF! | BH11: 16.5
A12: =ELEC!C9 -> 44081 | B12: ='B5'!B11 -> 207 | C12: =B12*$B$4 -> 4453.8387 | D12: =SUM(B12) -> 207 | E12: =D12*$B$4 -> 4453.8387 | F12: =SUM(D12) -> 207 | G12: =F12*$B$4 -> 4453.8387 | H12: =SUM(F12) -> 207 | I12: =H12*$B$4 -> 4453.8387 | J12: =SUM(H12) -> 207 | K12: =J12*$B$4 -> 4453.8387 | L12: =SUM(J12) -> 207 | M12: =L12*$B$4 -> 4453.8387 | N12: =SUM(L12) -> 207 | O12: =N12*$B$4 -> 4453.8387 | P12: =SUM(N12) -> 207 | Q12: =P12*$B$4 -> 4453.8387 | R12: =SUM(P12) -> 207 | S12: =R12*$B$4 -> 4453.8387 | T12: =SUM(R12) -> 207 | U12: =T12*$B$4 -> 4453.8387 | V12: =SUM(T12) -> 207 | W12: =V12*$B$4 -> 4453.8387 | X12: =SUM(Y12/73370) -> 0.66774194 | Y12: =SUM(C12+E12+G12+I12+K12+M12+O12+Q12+S12+U12+W12) -> 48992.226 | Z12: ='B5'!C11 -> 213 | AA12: =SUM(Z12*$Z$4) -> 2130 | AB12: =SUM(Z12) -> 213 | AC12: =SUM(AB12*$Z$4) -> 2130 | AD12: =SUM(AB12) -> 213 | AE12: =SUM(AD12*$Z$4) -> 2130 | AF12: =SUM(AD12) -> 213 | AG12: =SUM(AF12*$Z$4) -> 2130 | AH12: =SUM(AF12) -> 213 | AI12: =SUM(AH12*$Z$4) -> 2130 | AJ12: =SUM(AH12) -> 213 | AK12: =SUM(AJ12*$Z$4) -> 2130 | AL12: =SUM(AJ12) -> 213 | AM12: =SUM(AL12*$Z$4) -> 2130 | AN12: =SUM(AO12/19600) -> 0.76071429 | AO12: =SUM(AA12+AC12+AE12+AG12+AI12+AK12+AM12) -> 14910 | AQ12: =SUM(AR12/92970) -> 0.68734243 | AR12: =SUM(AO12+Y12) -> 63902.226 | AS12: =SUM(AR12-AR11-AT12) -> -1296.7097 | AV12: =IF(AT12>0,AU12,AV11) -> 0.53 | AW12: =-SUM('B5'!AI11) -> 0 | AX12: =-SUM(AW12-AS12) -> -1296.7097 | AY12: =SUM(AX12+AW12) -> -1296.7097 | AZ12: =ELEC!A9 -> 0 | BA12: ='General information '!D12 -> 29.5 | BB12: =SUM('General information '!E12) -> 0.75 | BC12: =IF(AR11>=AR12,0,1) -> 0 | BD12: 19222 | BE12: =(305/1185)*ELEC!Q10 -> 2059.0717 | BG12: =#REF!-BE12 -> #REF! | BH12: 15.5
A13: =ELEC!C10 -> 44082 | B13: ='B5'!B12 -> 197.2 | C13: =B13*$B$4 -> 4242.9806 | D13: =SUM(B13) -> 197.2 | E13: =D13*$B$4 -> 4242.9806 | F13: =SUM(D13) -> 197.2 | G13: =F13*$B$4 -> 4242.9806 | H13: =SUM(F13) -> 197.2 | I13: =H13*$B$4 -> 4242.9806 | J13: =SUM(H13) -> 197.2 | K13: =J13*$B$4 -> 4242.9806 | L13: =SUM(J13) -> 197.2 | M13: =L13*$B$4 -> 4242.9806 | N13: =SUM(L13) -> 197.2 | O13: =N13*$B$4 -> 4242.9806 | P13: =SUM(N13) -> 197.2 | Q13: =P13*$B$4 -> 4242.9806 | R13: =SUM(P13) -> 197.2 | S13: =R13*$B$4 -> 4242.9806 | T13: =SUM(R13) -> 197.2 | U13: =T13*$B$4 -> 4242.9806 | V13: =SUM(T13) -> 197.2 | W13: =V13*$B$4 -> 4242.9806 | X13: =SUM(Y13/73370) -> 0.63612903 | Y13: =SUM(C13+E13+G13+I13+K13+M13+O13+Q13+S13+U13+W13) -> 46672.787 | Z13: ='B5'!C12 -> 204 | AA13: =SUM(Z13*$Z$4) -> 2040 | AB13: =SUM(Z13) -> 204 | AC13: =SUM(AB13*$Z$4) -> 2040 | AD13: =SUM(AB13) -> 204 | AE13: =SUM(AD13*$Z$4) -> 2040 | AF13: =SUM(AD13) -> 204 | AG13: =SUM(AF13*$Z$4) -> 2040 | AH13: =SUM(AF13) -> 204 | AI13: =SUM(AH13*$Z$4) -> 2040 | AJ13: =SUM(AH13) -> 204 | AK13: =SUM(AJ13*$Z$4) -> 2040 | AL13: =SUM(AJ13) -> 204 | AM13: =SUM(AL13*$Z$4) -> 2040 | AN13: =SUM(AO13/19600) -> 0.72857143 | AO13: =SUM(AA13+AC13+AE13+AG13+AI13+AK13+AM13) -> 14280 | AQ13: =SUM(AR13/92970) -> 0.6556178 | AR13: =SUM(AO13+Y13) -> 60952.787 | AS13: =SUM(AR13-AR12-AT13) -> -2949.4387 | AV13: =IF(AT13>0,AU13,AV12) -> 0.53 | AW13: =-SUM('B5'!AI12) -> 0 | AX13: =-SUM(AW13-AS13) -> -2949.4387 | AY13: =SUM(AX13+AW13) -> -2949.4387 | AZ13: =ELEC!A10 -> 0 | BA13: ='General information '!D13 -> 29.5 | BB13: =SUM('General information '!E13) -> 0.76 | BC13: =IF(AR12>=AR13,0,1) -> 0 | BD13: 19222 | BE13: =(305/1185)*ELEC!Q11 -> 514.76793 | BG13: =#REF!-BE13 -> #REF!
A14: =ELEC!C11 -> 44083 | B14: ='B5'!B13 -> 194 | C14: =B14*$B$4 -> 4174.129 | D14: =SUM(B14) -> 194 | E14: =D14*$B$4 -> 4174.129 | F14: =SUM(D14) -> 194 | G14: =F14*$B$4 -> 4174.129 | H14: =SUM(F14) -> 194 | I14: =H14*$B$4 -> 4174.129 | J14: =SUM(H14) -> 194 | K14: =J14*$B$4 -> 4174.129 | L14: =SUM(J14) -> 194 | M14: =L14*$B$4 -> 4174.129 | N14: =SUM(L14) -> 194 | O14: =N14*$B$4 -> 4174.129 | P14: =SUM(N14) -> 194 | Q14: =P14*$B$4 -> 4174.129 | R14: =SUM(P14) -> 194 | S14: =R14*$B$4 -> 4174.129 | T14: =SUM(R14) -> 194 | U14: =T14*$B$4 -> 4174.129 | V14: =SUM(T14) -> 194 | W14: =V14*$B$4 -> 4174.129 | X14: =SUM(Y14/73370) -> 0.62580645 | Y14: =SUM(C14+E14+G14+I14+K14+M14+O14+Q14+S14+U14+W14) -> 45915.419 | Z14: ='B5'!C13 -> 201 | AA14: =SUM(Z14*$Z$4) -> 2010 | AB14: =SUM(Z14) -> 201 | AC14: =SUM(AB14*$Z$4) -> 2010 | AD14: =SUM(AB14) -> 201 | AE14: =SUM(AD14*$Z$4) -> 2010 | AF14: =SUM(AD14) -> 201 | AG14: =SUM(AF14*$Z$4) -> 2010 | AH14: =SUM(AF14) -> 201 | AI14: =SUM(AH14*$Z$4) -> 2010 | AJ14: =SUM(AH14) -> 201 | AK14: =SUM(AJ14*$Z$4) -> 2010 | AL14: =SUM(AJ14) -> 201 | AM14: =SUM(AL14*$Z$4) -> 2010 | AN14: =SUM(AO14/19600) -> 0.71785714 | AO14: =SUM(AA14+AC14+AE14+AG14+AI14+AK14+AM14) -> 14070 | AQ14: =SUM(AR14/92970) -> 0.64521264 | AR14: =SUM(AO14+Y14) -> 59985.419 | AS14: =SUM(AR14-AR13-AT14) -> -967.36774 | AV14: =IF(AT14>0,AU14,AV13) -> 0.53 | AW14: =-SUM('B5'!AI13) -> 0 | AX14: =-SUM(AW14-AS14) -> -967.36774 | AY14: =SUM(AX14+AW14) -> -967.36774 | AZ14: =ELEC!A11 -> 0 | BA14: ='General information '!D14 -> 29.5 | BB14: =SUM('General information '!E14) -> 0.75 | BC14: =IF(AR13>=AR14,0,1) -> 0 | BD14: 19222 | BE14: =(305/1185)*ELEC!Q12 -> 514.76793 | BG14: =#REF!-BE14 -> #REF!
A15: =ELEC!C12 -> 44084 | B15: ='B5'!B14 -> 245 | C15: =B15*$B$4 -> 5271.4516 | D15: =SUM(B15) -> 245 | E15: =D15*$B$4 -> 5271.4516 | F15: =SUM(D15) -> 245 | G15: =F15*$B$4 -> 5271.4516 | H15: =SUM(F15) -> 245 | I15: =H15*$B$4 -> 5271.4516 | J15: =SUM(H15) -> 245 | K15: =J15*$B$4 -> 5271.4516 | L15: =SUM(J15) -> 245 | M15: =L15*$B$4 -> 5271.4516 | N15: =SUM(L15) -> 245 | O15: =N15*$B$4 -> 5271.4516 | P15: =SUM(N15) -> 245 | Q15: =P15*$B$4 -> 5271.4516 | R15: =SUM(P15) -> 245 | S15: =R15*$B$4 -> 5271.4516 | T15: =SUM(R15) -> 245 | U15: =T15*$B$4 -> 5271.4516 | V15: =SUM(T15) -> 245 | W15: =V15*$B$4 -> 5271.4516 | X15: =SUM(Y15/73370) -> 0.79032258 | Y15: =SUM(C15+E15+G15+I15+K15+M15+O15+Q15+S15+U15+W15) -> 57985.968 | Z15: ='B5'!C14 -> 250 | AA15: =SUM(Z15*$Z$4) -> 2500 | AB15: =SUM(Z15) -> 250 | AC15: =SUM(AB15*$Z$4) -> 2500 | AD15: =SUM(AB15) -> 250 | AE15: =SUM(AD15*$Z$4) -> 2500 | AF15: =SUM(AD15) -> 250 | AG15: =SUM(AF15*$Z$4) -> 2500 | AH15: =SUM(AF15) -> 250 | AI15: =SUM(AH15*$Z$4) -> 2500 | AJ15: =SUM(AH15) -> 250 | AK15: =SUM(AJ15*$Z$4) -> 2500 | AL15: =SUM(AJ15) -> 250 | AM15: =SUM(AL15*$Z$4) -> 2500 | AN15: =SUM(AO15/19600) -> 0.89285714 | AO15: =SUM(AA15+AC15+AE15+AG15+AI15+AK15+AM15) -> 17500 | AQ15: =SUM(AR15/92970) -> 0.81193899 | AR15: =SUM(AO15+Y15) -> 75485.968 | AS15: =SUM(AR15-AR14-AT15) -> 500.54839 | AT15: 15000 | AU15: 0.54 | AV15: =IF(AT15>0,AU15,AV14) -> 0.54 | AW15: =-SUM('B5'!AI14) -> 0 | AX15: =-SUM(AW15-AS15) -> 500.54839 | AY15: =SUM(AX15+AW15) -> 500.54839 | AZ15: =ELEC!A12 -> 0 | BA15: ='General information '!D15 -> 29 | BB15: =SUM('General information '!E15) -> 0.64 | BC15: =IF(AR14>=AR15,0,1) -> 1 | BD15: 19222 | BE15: =(305/1185)*ELEC!Q13 -> 772.1519 | BG15: =#REF!-BE15 -> #REF!
A16: =ELEC!C13 -> 44085 | B16: ='B5'!B15 -> 241 | C16: =B16*$B$4 -> 5185.3871 | D16: =SUM(B16) -> 241 | E16: =D16*$B$4 -> 5185.3871 | F16: =SUM(D16) -> 241 | G16: =F16*$B$4 -> 5185.3871 | H16: =SUM(F16) -> 241 | I16: =H16*$B$4 -> 5185.3871 | J16: =SUM(H16) -> 241 | K16: =J16*$B$4 -> 5185.3871 | L16: =SUM(J16) -> 241 | M16: =L16*$B$4 -> 5185.3871 | N16: =SUM(L16) -> 241 | O16: =N16*$B$4 -> 5185.3871 | P16: =SUM(N16) -> 241 | Q16: =P16*$B$4 -> 5185.3871 | R16: =SUM(P16) -> 241 | S16: =R16*$B$4 -> 5185.3871 | T16: =SUM(R16) -> 241 | U16: =T16*$B$4 -> 5185.3871 | V16: =SUM(T16) -> 241 | W16: =V16*$B$4 -> 5185.3871 | X16: =SUM(Y16/73370) -> 0.77741935 | Y16: =SUM(C16+E16+G16+I16+K16+M16+O16+Q16+S16+U16+W16) -> 57039.258 | Z16: ='B5'!C15 -> 247 | AA16: =SUM(Z16*$Z$4) -> 2470 | AB16: =SUM(Z16) -> 247 | AC16: =SUM(AB16*$Z$4) -> 2470 | AD16: =SUM(AB16) -> 247 | AE16: =SUM(AD16*$Z$4) -> 2470 | AF16: =SUM(AD16) -> 247 | AG16: =SUM(AF16*$Z$4) -> 2470 | AH16: =SUM(AF16) -> 247 | AI16: =SUM(AH16*$Z$4) -> 2470 | AJ16: =SUM(AH16) -> 247 | AK16: =SUM(AJ16*$Z$4) -> 2470 | AL16: =SUM(AJ16) -> 247 | AM16: =SUM(AL16*$Z$4) -> 2470 | AN16: =SUM(AO16/19600) -> 0.88214286 | AO16: =SUM(AA16+AC16+AE16+AG16+AI16+AK16+AM16) -> 17290 | AQ16: =SUM(AR16/92970) -> 0.79949724 | AR16: =SUM(AO16+Y16) -> 74329.258 | AS16: =SUM(AR16-AR15-AT16) -> -1156.7097 | AV16: =IF(AT16>0,AU16,AV15) -> 0.54 | AW16: =-SUM('B5'!AI15) -> 0 | AX16: =-SUM(AW16-AS16) -> -1156.7097 | AY16: =SUM(AX16+AW16) -> -1156.7097 | AZ16: =ELEC!A13 -> 0 | BA16: ='General information '!D16 -> 30 | BB16: =SUM('General information '!E16) -> 0.77 | BC16: =IF(AR15>=AR16,0,1) -> 0 | BD16: 19222 | BE16: =(305/1185)*ELEC!Q14 -> 772.1519 | BG16: =#REF!-BE16 -> #REF!
A17: =ELEC!C14 -> 44086 | B17: ='B5'!B16 -> 238 | C17: =B17*$B$4 -> 5120.8387 | D17: =SUM(B17) -> 238 | E17: =D17*$B$4 -> 5120.8387 | F17: =SUM(D17) -> 238 | G17: =F17*$B$4 -> 5120.8387 | H17: =SUM(F17) -> 238 | I17: =H17*$B$4 -> 5120.8387 | J17: =SUM(H17) -> 238 | K17: =J17*$B$4 -> 5120.8387 | L17: =SUM(J17) -> 238 | M17: =L17*$B$4 -> 5120.8387 | N17: =SUM(L17) -> 238 | O17: =N17*$B$4 -> 5120.8387 | P17: =SUM(N17) -> 238 | Q17: =P17*$B$4 -> 5120.8387 | R17: =SUM(P17) -> 238 | S17: =R17*$B$4 -> 5120.8387 | T17: =SUM(R17) -> 238 | U17: =T17*$B$4 -> 5120.8387 | V17: =SUM(T17) -> 238 | W17: =V17*$B$4 -> 5120.8387 | X17: =SUM(Y17/73370) -> 0.76774194 | Y17: =SUM(C17+E17+G17+I17+K17+M17+O17+Q17+S17+U17+W17) -> 56329.226 | Z17: ='B5'!C16 -> 243.2 | AA17: =SUM(Z17*$Z$4) -> 2432 | AB17: =SUM(Z17) -> 243.2 | AC17: =SUM(AB17*$Z$4) -> 2432 | AD17: =SUM(AB17) -> 243.2 | AE17: =SUM(AD17*$Z$4) -> 2432 | AF17: =SUM(AD17) -> 243.2 | AG17: =SUM(AF17*$Z$4) -> 2432 | AH17: =SUM(AF17) -> 243.2 | AI17: =SUM(AH17*$Z$4) -> 2432 | AJ17: =SUM(AH17) -> 243.2 | AK17: =SUM(AJ17*$Z$4) -> 2432 | AL17: =SUM(AJ17) -> 243.2 | AM17: =SUM(AL17*$Z$4) -> 2432 | AN17: =SUM(AO17/19600) -> 0.86857143 | AO17: =SUM(AA17+AC17+AE17+AG17+AI17+AK17+AM17) -> 17024 | AQ17: =SUM(AR17/92970) -> 0.78899888 | AR17: =SUM(AO17+Y17) -> 73353.226 | AS17: =SUM(AR17-AR16-AT17) -> -976.03226 | AV17: =IF(AT17>0,AU17,AV16) -> 0.54 | AW17: =-SUM('B5'!AI16) -> 0 | AX17: =-SUM(AW17-AS17) -> -976.03226 | AY17: =SUM(AX17+AW17) -> -976.03226 | AZ17: =ELEC!A14 -> 0 | BA17: ='General information '!D17 -> 29.5 | BB17: =SUM('General information '!E17) -> 0.75 | BC17: =IF(AR16>=AR17,0,1) -> 0 | BD17: 19222 | BE17: =(305/1185)*ELEC!Q15 -> 514.76793 | BG17: =#REF!-BE17 -> #REF!
A18: =ELEC!C15 -> 44087 | B18: ='B5'!B17 -> 235 | C18: =B18*$B$4 -> 5056.2903 | D18: =SUM(B18) -> 235 | E18: =D18*$B$4 -> 5056.2903 | F18: =SUM(D18) -> 235 | G18: =F18*$B$4 -> 5056.2903 | H18: =SUM(F18) -> 235 | I18: =H18*$B$4 -> 5056.2903 | J18: =SUM(H18) -> 235 | K18: =J18*$B$4 -> 5056.2903 | L18: =SUM(J18) -> 235 | M18: =L18*$B$4 -> 5056.2903 | N18: =SUM(L18) -> 235 | O18: =N18*$B$4 -> 5056.2903 | P18: =SUM(N18) -> 235 | Q18: =P18*$B$4 -> 5056.2903 | R18: =SUM(P18) -> 235 | S18: =R18*$B$4 -> 5056.2903 | T18: =SUM(R18) -> 235 | U18: =T18*$B$4 -> 5056.2903 | V18: =SUM(T18) -> 235 | W18: =V18*$B$4 -> 5056.2903 | X18: =SUM(Y18/73370) -> 0.75806452 | Y18: =SUM(C18+E18+G18+I18+K18+M18+O18+Q18+S18+U18+W18) -> 55619.194 | Z18: ='B5'!C17 -> 241.2 | AA18: =SUM(Z18*$Z$4) -> 2412 | AB18: =SUM(Z18) -> 241.2 | AC18: =SUM(AB18*$Z$4) -> 2412 | AD18: =SUM(AB18) -> 241.2 | AE18: =SUM(AD18*$Z$4) -> 2412 | AF18: =SUM(AD18) -> 241.2 | AG18: =SUM(AF18*$Z$4) -> 2412 | AH18: =SUM(AF18) -> 241.2 | AI18: =SUM(AH18*$Z$4) -> 2412 | AJ18: =SUM(AH18) -> 241.2 | AK18: =SUM(AJ18*$Z$4) -> 2412 | AL18: =SUM(AJ18) -> 241.2 | AM18: =SUM(AL18*$Z$4) -> 2412 | AN18: =SUM(AO18/19600) -> 0.86142857 | AO18: =SUM(AA18+AC18+AE18+AG18+AI18+AK18+AM18) -> 16884 | AQ18: =SUM(AR18/92970) -> 0.7798558 | AR18: =SUM(AO18+Y18) -> 72503.194 | AS18: =SUM(AR18-AR17-AT18) -> -850.03226 | AV18: =IF(AT18>0,AU18,AV17) -> 0.54 | AW18: =-SUM('B5'!AI17) -> 0 | AX18: =-SUM(AW18-AS18) -> -850.03226 | AY18: =SUM(AX18+AW18) -> -850.03226 | AZ18: =ELEC!A15 -> 0 | BA18: ='General information '!D18 -> 28 | BB18: =SUM('General information '!E18) -> 0.62 | BC18: =IF(AR17>=AR18,0,1) -> 0 | BD18: 19222 | BE18: =(305/1185)*ELEC!Q16 -> 514.76793 | BG18: =#REF!-BE18 -> #REF!
A19: =ELEC!C16 -> 44088 | B19: ='B5'!B18 -> 233.4 | C19: =B19*$B$4 -> 5021.8645 | D19: =SUM(B19) -> 233.4 | E19: =D19*$B$4 -> 5021.8645 | F19: =SUM(D19) -> 233.4 | G19: =F19*$B$4 -> 5021.8645 | H19: =SUM(F19) -> 233.4 | I19: =H19*$B$4 -> 5021.8645 | J19: =SUM(H19) -> 233.4 | K19: =J19*$B$4 -> 5021.8645 | L19: =SUM(J19) -> 233.4 | M19: =L19*$B$4 -> 5021.8645 | N19: =SUM(L19) -> 233.4 | O19: =N19*$B$4 -> 5021.8645 | P19: =SUM(N19) -> 233.4 | Q19: =P19*$B$4 -> 5021.8645 | R19: =SUM(P19) -> 233.4 | S19: =R19*$B$4 -> 5021.8645 | T19: =SUM(R19) -> 233.4 | U19: =T19*$B$4 -> 5021.8645 | V19: =SUM(T19) -> 233.4 | W19: =V19*$B$4 -> 5021.8645 | X19: =SUM(Y19/73370) -> 0.75290323 | Y19: =SUM(C19+E19+G19+I19+K19+M19+O19+Q19+S19+U19+W19) -> 55240.51 | Z19: ='B5'!C18 -> 239 | AA19: =SUM(Z19*$Z$4) -> 2390 | AB19: =SUM(Z19) -> 239 | AC19: =SUM(AB19*$Z$4) -> 2390 | AD19: =SUM(AB19) -> 239 | AE19: =SUM(AD19*$Z$4) -> 2390 | AF19: =SUM(AD19) -> 239 | AG19: =SUM(AF19*$Z$4) -> 2390 | AH19: =SUM(AF19) -> 239 | AI19: =SUM(AH19*$Z$4) -> 2390 | AJ19: =SUM(AH19) -> 239 | AK19: =SUM(AJ19*$Z$4) -> 2390 | AL19: =SUM(AJ19) -> 239 | AM19: =SUM(AL19*$Z$4) -> 2390 | AN19: =SUM(AO19/19600) -> 0.85357143 | AO19: =SUM(AA19+AC19+AE19+AG19+AI19+AK19+AM19) -> 16730 | AQ19: =SUM(AR19/92970) -> 0.77412617 | AR19: =SUM(AO19+Y19) -> 71970.51 | AS19: =SUM(AR19-AR18-AT19) -> -532.68387 | AV19: =IF(AT19>0,AU19,AV18) -> 0.54 | AW19: =-SUM('B5'!AI18) -> 0 | AX19: =-SUM(AW19-AS19) -> -532.68387 | AY19: =SUM(AX19+AW19) -> -532.68387 | AZ19: =ELEC!A16 -> 0 | BA19: ='General information '!D19 -> 28.5 | BB19: =SUM('General information '!E19) -> 0.69 | BC19: =IF(AR18>=AR19,0,1) -> 0 | BD19: 19222 | BE19: =(305/1185)*ELEC!Q17 -> 772.1519 | BG19: =#REF!-BE19 -> #REF!
A20: =ELEC!C17 -> 44089 | B20: ='B5'!B19 -> 229 | C20: =B20*$B$4 -> 4927.1935 | D20: =SUM(B20) -> 229 | E20: =D20*$B$4 -> 4927.1935 | F20: =SUM(D20) -> 229 | G20: =F20*$B$4 -> 4927.1935 | H20: =SUM(F20) -> 229 | I20: =H20*$B$4 -> 4927.1935 | J20: =SUM(H20) -> 229 | K20: =J20*$B$4 -> 4927.1935 | L20: =SUM(J20) -> 229 | M20: =L20*$B$4 -> 4927.1935 | N20: =SUM(L20) -> 229 | O20: =N20*$B$4 -> 4927.1935 | P20: =SUM(N20) -> 229 | Q20: =P20*$B$4 -> 4927.1935 | R20: =SUM(P20) -> 229 | S20: =R20*$B$4 -> 4927.1935 | T20: =SUM(R20) -> 229 | U20: =T20*$B$4 -> 4927.1935 | V20: =SUM(T20) -> 229 | W20: =V20*$B$4 -> 4927.1935 | X20: =SUM(Y20/73370) -> 0.73870968 | Y20: =SUM(C20+E20+G20+I20+K20+M20+O20+Q20+S20+U20+W20) -> 54199.129 | Z20: ='B5'!C19 -> 236 | AA20: =SUM(Z20*$Z$4) -> 2360 | AB20: =SUM(Z20) -> 236 | AC20: =SUM(AB20*$Z$4) -> 2360 | AD20: =SUM(AB20) -> 236 | AE20: =SUM(AD20*$Z$4) -> 2360 | AF20: =SUM(AD20) -> 236 | AG20: =SUM(AF20*$Z$4) -> 2360 | AH20: =SUM(AF20) -> 236 | AI20: =SUM(AH20*$Z$4) -> 2360 | AJ20: =SUM(AH20) -> 236 | AK20: =SUM(AJ20*$Z$4) -> 2360 | AL20: =SUM(AJ20) -> 236 | AM20: =SUM(AL20*$Z$4) -> 2360 | AN20: =SUM(AO20/19600) -> 0.84285714 | AO20: =SUM(AA20+AC20+AE20+AG20+AI20+AK20+AM20) -> 16520 | AQ20: =SUM(AR20/92970) -> 0.76066612 | AR20: =SUM(AO20+Y20) -> 70719.129 | AS20: =SUM(AR20-AR19-AT20) -> -1251.3806 | AV20: =IF(AT20>0,AU20,AV19) -> 0.54 | AW20: =-SUM('B5'!AI19) -> 0 | AX20: =-SUM(AW20-AS20) -> -1251.3806 | AY20: =SUM(AX20+AW20) -> -1251.3806 | AZ20: =ELEC!A17 -> 0 | BA20: ='General information '!D20 -> 26.5 | BB20: =SUM('General information '!E20) -> 0.74 | BC20: =IF(AR19>=AR20,0,1) -> 0 | BD20: 19222 | BE20: =(305/1185)*ELEC!Q18 -> 772.1519 | BG20: =#REF!-BE20 -> #REF!
A21: =ELEC!C18 -> 44090 | B21: ='B5'!B20 -> 226.4 | C21: =B21*$B$4 -> 4871.2516 | D21: =SUM(B21) -> 226.4 | E21: =D21*$B$4 -> 4871.2516 | F21: =SUM(D21) -> 226.4 | G21: =F21*$B$4 -> 4871.2516 | H21: =SUM(F21) -> 226.4 | I21: =H21*$B$4 -> 4871.2516 | J21: =SUM(H21) -> 226.4 | K21: =J21*$B$4 -> 4871.2516 | L21: =SUM(J21) -> 226.4 | M21: =L21*$B$4 -> 4871.2516 | N21: =SUM(L21) -> 226.4 | O21: =N21*$B$4 -> 4871.2516 | P21: =SUM(N21) -> 226.4 | Q21: =P21*$B$4 -> 4871.2516 | R21: =SUM(P21) -> 226.4 | S21: =R21*$B$4 -> 4871.2516 | T21: =SUM(R21) -> 226.4 | U21: =T21*$B$4 -> 4871.2516 | V21: =SUM(T21) -> 226.4 | W21: =V21*$B$4 -> 4871.2516 | X21: =SUM(Y21/73370) -> 0.73032258 | Y21: =SUM(C21+E21+G21+I21+K21+M21+O21+Q21+S21+U21+W21) -> 53583.768 | Z21: ='B5'!C20 -> 232.4 | AA21: =SUM(Z21*$Z$4) -> 2324 | AB21: =SUM(Z21) -> 232.4 | AC21: =SUM(AB21*$Z$4) -> 2324 | AD21: =SUM(AB21) -> 232.4 | AE21: =SUM(AD21*$Z$4) -> 2324 | AF21: =SUM(AD21) -> 232.4 | AG21: =SUM(AF21*$Z$4) -> 2324 | AH21: =SUM(AF21) -> 232.4 | AI21: =SUM(AH21*$Z$4) -> 2324 | AJ21: =SUM(AH21) -> 232.4 | AK21: =SUM(AJ21*$Z$4) -> 2324 | AL21: =SUM(AJ21) -> 232.4 | AM21: =SUM(AL21*$Z$4) -> 2324 | AN21: =SUM(AO21/19600) -> 0.83 | AO21: =SUM(AA21+AC21+AE21+AG21+AI21+AK21+AM21) -> 16268 | AQ21: =SUM(AR21/92970) -> 0.75133664 | AR21: =SUM(AO21+Y21) -> 69851.768 | AS21: =SUM(AR21-AR20-AT21) -> -867.36129 | AV21: =IF(AT21>0,AU21,AV20) -> 0.54 | AW21: =-SUM('B5'!AI20) -> 0 | AX21: =-SUM(AW21-AS21) -> -867.36129 | AY21: =SUM(AX21+AW21) -> -867.36129 | AZ21: =ELEC!A18 -> 0 | BA21: ='General information '!D21 -> 28.5 | BB21: =SUM('General information '!E21) -> 0.72 | BC21: =IF(AR20>=AR21,0,1) -> 0 | BD21: 19222 | BE21: =(305/1185)*ELEC!Q19 -> 257.38397 | BG21: =#REF!-BE21 -> #REF!
A22: =ELEC!C19 -> 44091 | B22: ='B5'!B21 -> 225 | C22: =B22*$B$4 -> 4841.129 | D22: =SUM(B22) -> 225 | E22: =D22*$B$4 -> 4841.129 | F22: =SUM(D22) -> 225 | G22: =F22*$B$4 -> 4841.129 | H22: =SUM(F22) -> 225 | I22: =H22*$B$4 -> 4841.129 | J22: =SUM(H22) -> 225 | K22: =J22*$B$4 -> 4841.129 | L22: =SUM(J22) -> 225 | M22: =L22*$B$4 -> 4841.129 | N22: =SUM(L22) -> 225 | O22: =N22*$B$4 -> 4841.129 | P22: =SUM(N22) -> 225 | Q22: =P22*$B$4 -> 4841.129 | R22: =SUM(P22) -> 225 | S22: =R22*$B$4 -> 4841.129 | T22: =SUM(R22) -> 225 | U22: =T22*$B$4 -> 4841.129 | V22: =SUM(T22) -> 225 | W22: =V22*$B$4 -> 4841.129 | X22: =SUM(Y22/73370) -> 0.72580645 | Y22: =SUM(C22+E22+G22+I22+K22+M22+O22+Q22+S22+U22+W22) -> 53252.419 | Z22: ='B5'!C21 -> 231 | AA22: =SUM(Z22*$Z$4) -> 2310 | AB22: =SUM(Z22) -> 231 | AC22: =SUM(AB22*$Z$4) -> 2310 | AD22: =SUM(AB22) -> 231 | AE22: =SUM(AD22*$Z$4) -> 2310 | AF22: =SUM(AD22) -> 231 | AG22: =SUM(AF22*$Z$4) -> 2310 | AH22: =SUM(AF22) -> 231 | AI22: =SUM(AH22*$Z$4) -> 2310 | AJ22: =SUM(AH22) -> 231 | AK22: =SUM(AJ22*$Z$4) -> 2310 | AL22: =SUM(AJ22) -> 231 | AM22: =SUM(AL22*$Z$4) -> 2310 | AN22: =SUM(AO22/19600) -> 0.825 | AO22: =SUM(AA22+AC22+AE22+AG22+AI22+AK22+AM22) -> 16170 | AQ22: =SUM(AR22/92970) -> 0.7467185 | AR22: =SUM(AO22+Y22) -> 69422.419 | AS22: =SUM(AR22-AR21-AT22) -> -429.34839 | AV22: =IF(AT22>0,AU22,AV21) -> 0.54 | AW22: =-SUM('B5'!AI21) -> 0 | AX22: =-SUM(AW22-AS22) -> -429.34839 | AY22: =SUM(AX22+AW22) -> -429.34839 | AZ22: =ELEC!A19 -> 0 | BA22: ='General information '!D22 -> 28 | BB22: =SUM('General information '!E22) -> 0.75 | BC22: =IF(AR21>=AR22,0,1) -> 0 | BD22: 19222 | BE22: =(305/1185)*ELEC!Q20 -> 514.76793 | BG22: =#REF!-BE22 -> #REF!
A23: =ELEC!C20 -> 44092 | B23: ='B5'!B22 -> 223 | C23: =B23*$B$4 -> 4798.0968 | D23: =SUM(B23) -> 223 | E23: =D23*$B$4 -> 4798.0968 | F23: =SUM(D23) -> 223 | G23: =F23*$B$4 -> 4798.0968 | H23: =SUM(F23) -> 223 | I23: =H23*$B$4 -> 4798.0968 | J23: =SUM(H23) -> 223 | K23: =J23*$B$4 -> 4798.0968 | L23: =SUM(J23) -> 223 | M23: =L23*$B$4 -> 4798.0968 | N23: =SUM(L23) -> 223 | O23: =N23*$B$4 -> 4798.0968 | P23: =SUM(N23) -> 223 | Q23: =P23*$B$4 -> 4798.0968 | R23: =SUM(P23) -> 223 | S23: =R23*$B$4 -> 4798.0968 | T23: =SUM(R23) -> 223 | U23: =T23*$B$4 -> 4798.0968 | V23: =SUM(T23) -> 223 | W23: =V23*$B$4 -> 4798.0968 | X23: =SUM(Y23/73370) -> 0.71935484 | Y23: =SUM(C23+E23+G23+I23+K23+M23+O23+Q23+S23+U23+W23) -> 52779.065 | Z23: ='B5'!C22 -> 229.1 | AA23: =SUM(Z23*$Z$4) -> 2291 | AB23: =SUM(Z23) -> 229.1 | AC23: =SUM(AB23*$Z$4) -> 2291 | AD23: =SUM(AB23) -> 229.1 | AE23: =SUM(AD23*$Z$4) -> 2291 | AF23: =SUM(AD23) -> 229.1 | AG23: =SUM(AF23*$Z$4) -> 2291 | AH23: =SUM(AF23) -> 229.1 | AI23: =SUM(AH23*$Z$4) -> 2291 | AJ23: =SUM(AH23) -> 229.1 | AK23: =SUM(AJ23*$Z$4) -> 2291 | AL23: =SUM(AJ23) -> 229.1 | AM23: =SUM(AL23*$Z$4) -> 2291 | AN23: =SUM(AO23/19600) -> 0.81821429 | AO23: =SUM(AA23+AC23+AE23+AG23+AI23+AK23+AM23) -> 16037 | AQ23: =SUM(AR23/92970) -> 0.74019646 | AR23: =SUM(AO23+Y23) -> 68816.065 | AS23: =SUM(AR23-AR22-AT23) -> -606.35484 | AV23: =IF(AT23>0,AU23,AV22) -> 0.54 | AW23: =-SUM('B5'!AI22) -> 0 | AX23: =-SUM(AW23-AS23) -> -606.35484 | AY23: =SUM(AX23+AW23) -> -606.35484 | AZ23: =ELEC!A20 -> 0 | BA23: ='General information '!D23 -> 27.5 | BB23: =SUM('General information '!E23) -> 0.77 | BC23: =IF(AR22>=AR23,0,1) -> 0 | BD23: 19222 | BE23: =(305/1185)*ELEC!Q21 -> 514.76793 | BG23: =#REF!-BE23 -> #REF!
A24: =ELEC!C21 -> 44093 | B24: ='B5'!B23 -> 220 | C24: =B24*$B$4 -> 4733.5484 | D24: =SUM(B24) -> 220 | E24: =D24*$B$4 -> 4733.5484 | F24: =SUM(D24) -> 220 | G24: =F24*$B$4 -> 4733.5484 | H24: =SUM(F24) -> 220 | I24: =H24*$B$4 -> 4733.5484 | J24: =SUM(H24) -> 220 | K24: =J24*$B$4 -> 4733.5484 | L24: =SUM(J24) -> 220 | M24: =L24*$B$4 -> 4733.5484 | N24: =SUM(L24) -> 220 | O24: =N24*$B$4 -> 4733.5484 | P24: =SUM(N24) -> 220 | Q24: =P24*$B$4 -> 4733.5484 | R24: =SUM(P24) -> 220 | S24: =R24*$B$4 -> 4733.5484 | T24: =SUM(R24) -> 220 | U24: =T24*$B$4 -> 4733.5484 | V24: =SUM(T24) -> 220 | W24: =V24*$B$4 -> 4733.5484 | X24: =SUM(Y24/73370) -> 0.70967742 | Y24: =SUM(C24+E24+G24+I24+K24+M24+O24+Q24+S24+U24+W24) -> 52069.032 | Z24: ='B5'!C23 -> 226 | AA24: =SUM(Z24*$Z$4) -> 2260 | AB24: =SUM(Z24) -> 226 | AC24: =SUM(AB24*$Z$4) -> 2260 | AD24: =SUM(AB24) -> 226 | AE24: =SUM(AD24*$Z$4) -> 2260 | AF24: =SUM(AD24) -> 226 | AG24: =SUM(AF24*$Z$4) -> 2260 | AH24: =SUM(AF24) -> 226 | AI24: =SUM(AH24*$Z$4) -> 2260 | AJ24: =SUM(AH24) -> 226 | AK24: =SUM(AJ24*$Z$4) -> 2260 | AL24: =SUM(AJ24) -> 226 | AM24: =SUM(AL24*$Z$4) -> 2260 | AN24: =SUM(AO24/19600) -> 0.80714286 | AO24: =SUM(AA24+AC24+AE24+AG24+AI24+AK24+AM24) -> 15820 | AQ24: =SUM(AR24/92970) -> 0.73022515 | AR24: =SUM(AO24+Y24) -> 67889.032 | AS24: =SUM(AR24-AR23-AT24) -> -927.03226 | AV24: =IF(AT24>0,AU24,AV23) -> 0.54 | AW24: =-SUM('B5'!AI23) -> 0 | AX24: =-SUM(AW24-AS24) -> -927.03226 | AY24: =SUM(AX24+AW24) -> -927.03226 | AZ24: =ELEC!A21 -> 0 | BA24: ='General information '!D24 -> 28.5 | BB24: =SUM('General information '!E24) -> 0.64 | BC24: =IF(AR23>=AR24,0,1) -> 0 | BD24: 19222 | BE24: =(305/1185)*ELEC!Q22 -> 642.173 | BG24: =#REF!-BE24 -> #REF!
A25: =ELEC!C22 -> 44094 | B25: ='B5'!B24 -> 218 | C25: =B25*$B$4 -> 4690.5161 | D25: =SUM(B25) -> 218 | E25: =D25*$B$4 -> 4690.5161 | F25: =SUM(D25) -> 218 | G25: =F25*$B$4 -> 4690.5161 | H25: =SUM(F25) -> 218 | I25: =H25*$B$4 -> 4690.5161 | J25: =SUM(H25) -> 218 | K25: =J25*$B$4 -> 4690.5161 | L25: =SUM(J25) -> 218 | M25: =L25*$B$4 -> 4690.5161 | N25: =SUM(L25) -> 218 | O25: =N25*$B$4 -> 4690.5161 | P25: =SUM(N25) -> 218 | Q25: =P25*$B$4 -> 4690.5161 | R25: =SUM(P25) -> 218 | S25: =R25*$B$4 -> 4690.5161 | T25: =SUM(R25) -> 218 | U25: =T25*$B$4 -> 4690.5161 | V25: =SUM(T25) -> 218 | W25: =V25*$B$4 -> 4690.5161 | X25: =SUM(Y25/73370) -> 0.70322581 | Y25: =SUM(C25+E25+G25+I25+K25+M25+O25+Q25+S25+U25+W25) -> 51595.677 | Z25: ='B5'!C24 -> 224 | AA25: =SUM(Z25*$Z$4) -> 2240 | AB25: =SUM(Z25) -> 224 | AC25: =SUM(AB25*$Z$4) -> 2240 | AD25: =SUM(AB25) -> 224 | AE25: =SUM(AD25*$Z$4) -> 2240 | AF25: =SUM(AD25) -> 224 | AG25: =SUM(AF25*$Z$4) -> 2240 | AH25: =SUM(AF25) -> 224 | AI25: =SUM(AH25*$Z$4) -> 2240 | AJ25: =SUM(AH25) -> 224 | AK25: =SUM(AJ25*$Z$4) -> 2240 | AL25: =SUM(AJ25) -> 224 | AM25: =SUM(AL25*$Z$4) -> 2240 | AN25: =SUM(AO25/19600) -> 0.8 | AO25: =SUM(AA25+AC25+AE25+AG25+AI25+AK25+AM25) -> 15680 | AQ25: =SUM(AR25/92970) -> 0.72362781 | AR25: =SUM(AO25+Y25) -> 67275.677 | AS25: =SUM(AR25-AR24-AT25) -> -613.35484 | AV25: =IF(AT25>0,AU25,AV24) -> 0.54 | AW25: =-SUM('B5'!AI24) -> 0 | AX25: =-SUM(AW25-AS25) -> -613.35484 | AY25: =SUM(AX25+AW25) -> -613.35484 | AZ25: =ELEC!A22 -> 0 | BA25: ='General information '!D25 -> 26 | BB25: =SUM('General information '!E25) -> 0.65 | BC25: =IF(AR24>=AR25,0,1) -> 0 | BD25: 19222 | BE25: =(305/1185)*ELEC!Q23 -> 387.36287 | BG25: =#REF!-BE25 -> #REF!
A26: =ELEC!C23 -> 44095 | B26: ='B5'!B25 -> 215 | C26: =B26*$B$4 -> 4625.9677 | D26: =SUM(B26) -> 215 | E26: =D26*$B$4 -> 4625.9677 | F26: =SUM(D26) -> 215 | G26: =F26*$B$4 -> 4625.9677 | H26: =SUM(F26) -> 215 | I26: =H26*$B$4 -> 4625.9677 | J26: =SUM(H26) -> 215 | K26: =J26*$B$4 -> 4625.9677 | L26: =SUM(J26) -> 215 | M26: =L26*$B$4 -> 4625.9677 | N26: =SUM(L26) -> 215 | O26: =N26*$B$4 -> 4625.9677 | P26: =SUM(N26) -> 215 | Q26: =P26*$B$4 -> 4625.9677 | R26: =SUM(P26) -> 215 | S26: =R26*$B$4 -> 4625.9677 | T26: =SUM(R26) -> 215 | U26: =T26*$B$4 -> 4625.9677 | V26: =SUM(T26) -> 215 | W26: =V26*$B$4 -> 4625.9677 | X26: =SUM(Y26/73370) -> 0.69354839 | Y26: =SUM(C26+E26+G26+I26+K26+M26+O26+Q26+S26+U26+W26) -> 50885.645 | Z26: ='B5'!C25 -> 221 | AA26: =SUM(Z26*$Z$4) -> 2210 | AB26: =SUM(Z26) -> 221 | AC26: =SUM(AB26*$Z$4) -> 2210 | AD26: =SUM(AB26) -> 221 | AE26: =SUM(AD26*$Z$4) -> 2210 | AF26: =SUM(AD26) -> 221 | AG26: =SUM(AF26*$Z$4) -> 2210 | AH26: =SUM(AF26) -> 221 | AI26: =SUM(AH26*$Z$4) -> 2210 | AJ26: =SUM(AH26) -> 221 | AK26: =SUM(AJ26*$Z$4) -> 2210 | AL26: =SUM(AJ26) -> 221 | AM26: =SUM(AL26*$Z$4) -> 2210 | AN26: =SUM(AO26/19600) -> 0.78928571 | AO26: =SUM(AA26+AC26+AE26+AG26+AI26+AK26+AM26) -> 15470 | AQ26: =SUM(AR26/92970) -> 0.7137318 | AR26: =SUM(AO26+Y26) -> 66355.645 | AS26: =SUM(AR26-AR25-AT26) -> -920.03226 | AV26: =IF(AT26>0,AU26,AV25) -> 0.54 | AW26: =-SUM('B5'!AI25) -> 0 | AX26: =-SUM(AW26-AS26) -> -920.03226 | AY26: =SUM(AX26+AW26) -> -920.03226 | AZ26: =ELEC!A23 -> 0 | BA26: ='General information '!D26 -> 28.5 | BB26: =SUM('General information '!E26) -> 0.64 | BC26: =IF(AR25>=AR26,0,1) -> 0 | BD26: 19222 | BE26: =(305/1185)*ELEC!Q24 -> 1029.5359 | BG26: =#REF!-BE26 -> #REF!
A27: =ELEC!C24 -> 44096 | B27: ='B5'!B26 -> 211 | C27: =B27*$B$4 -> 4539.9032 | D27: =SUM(B27) -> 211 | E27: =D27*$B$4 -> 4539.9032 | F27: =SUM(D27) -> 211 | G27: =F27*$B$4 -> 4539.9032 | H27: =SUM(F27) -> 211 | I27: =H27*$B$4 -> 4539.9032 | J27: =SUM(H27) -> 211 | K27: =J27*$B$4 -> 4539.9032 | L27: =SUM(J27) -> 211 | M27: =L27*$B$4 -> 4539.9032 | N27: =SUM(L27) -> 211 | O27: =N27*$B$4 -> 4539.9032 | P27: =SUM(N27) -> 211 | Q27: =P27*$B$4 -> 4539.9032 | R27: =SUM(P27) -> 211 | S27: =R27*$B$4 -> 4539.9032 | T27: =SUM(R27) -> 211 | U27: =T27*$B$4 -> 4539.9032 | V27: =SUM(T27) -> 211 | W27: =V27*$B$4 -> 4539.9032 | X27: =SUM(Y27/73370) -> 0.68064516 | Y27: =SUM(C27+E27+G27+I27+K27+M27+O27+Q27+S27+U27+W27) -> 49938.935 | Z27: ='B5'!C26 -> 217 | AA27: =SUM(Z27*$Z$4) -> 2170 | AB27: =SUM(Z27) -> 217 | AC27: =SUM(AB27*$Z$4) -> 2170 | AD27: =SUM(AB27) -> 217 | AE27: =SUM(AD27*$Z$4) -> 2170 | AF27: =SUM(AD27) -> 217 | AG27: =SUM(AF27*$Z$4) -> 2170 | AH27: =SUM(AF27) -> 217 | AI27: =SUM(AH27*$Z$4) -> 2170 | AJ27: =SUM(AH27) -> 217 | AK27: =SUM(AJ27*$Z$4) -> 2170 | AL27: =SUM(AJ27) -> 217 | AM27: =SUM(AL27*$Z$4) -> 2170 | AN27: =SUM(AO27/19600) -> 0.775 | AO27: =SUM(AA27+AC27+AE27+AG27+AI27+AK27+AM27) -> 15190 | AQ27: =SUM(AR27/92970) -> 0.70053711 | AR27: =SUM(AO27+Y27) -> 65128.935 | AS27: =SUM(AR27-AR26-AT27) -> -1226.7097 | AV27: =IF(AT27>0,AU27,AV26) -> 0.54 | AW27: =-SUM('B5'!AI26) -> 0 | AX27: =-SUM(AW27-AS27) -> -1226.7097 | AY27: =SUM(AX27+AW27) -> -1226.7097 | AZ27: =ELEC!A24 -> 0 | BA27: ='General information '!D27 -> 28.5 | BB27: =SUM('General information '!E27) -> 0.65 | BC27: =IF(AR26>=AR27,0,1) -> 0 | BD27: 19222 | BE27: =(305/1185)*ELEC!Q25 -> 514.76793 | BG27: =#REF!-BE27 -> #REF!
A28: =ELEC!C25 -> 44097 | B28: ='B5'!B27 -> 209 | C28: =B28*$B$4 -> 4496.871 | D28: =SUM(B28) -> 209 | E28: =D28*$B$4 -> 4496.871 | F28: =SUM(D28) -> 209 | G28: =F28*$B$4 -> 4496.871 | H28: =SUM(F28) -> 209 | I28: =H28*$B$4 -> 4496.871 | J28: =SUM(H28) -> 209 | K28: =J28*$B$4 -> 4496.871 | L28: =SUM(J28) -> 209 | M28: =L28*$B$4 -> 4496.871 | N28: =SUM(L28) -> 209 | O28: =N28*$B$4 -> 4496.871 | P28: =SUM(N28) -> 209 | Q28: =P28*$B$4 -> 4496.871 | R28: =SUM(P28) -> 209 | S28: =R28*$B$4 -> 4496.871 | T28: =SUM(R28) -> 209 | U28: =T28*$B$4 -> 4496.871 | V28: =SUM(T28) -> 209 | W28: =V28*$B$4 -> 4496.871 | X28: =SUM(Y28/73370) -> 0.67419355 | Y28: =SUM(C28+E28+G28+I28+K28+M28+O28+Q28+S28+U28+W28) -> 49465.581 | Z28: ='B5'!C27 -> 215 | AA28: =SUM(Z28*$Z$4) -> 2150 | AB28: =SUM(Z28) -> 215 | AC28: =SUM(AB28*$Z$4) -> 2150 | AD28: =SUM(AB28) -> 215 | AE28: =SUM(AD28*$Z$4) -> 2150 | AF28: =SUM(AD28) -> 215 | AG28: =SUM(AF28*$Z$4) -> 2150 | AH28: =SUM(AF28) -> 215 | AI28: =SUM(AH28*$Z$4) -> 2150 | AJ28: =SUM(AH28) -> 215 | AK28: =SUM(AJ28*$Z$4) -> 2150 | AL28: =SUM(AJ28) -> 215 | AM28: =SUM(AL28*$Z$4) -> 2150 | AN28: =SUM(AO28/19600) -> 0.76785714 | AO28: =SUM(AA28+AC28+AE28+AG28+AI28+AK28+AM28) -> 15050 | AQ28: =SUM(AR28/92970) -> 0.69393977 | AR28: =SUM(AO28+Y28) -> 64515.581 | AS28: =SUM(AR28-AR27-AT28) -> -613.35484 | AV28: =IF(AT28>0,AU28,AV27) -> 0.54 | AW28: =-SUM('B5'!AI27) -> 0 | AX28: =-SUM(AW28-AS28) -> -613.35484 | AY28: =SUM(AX28+AW28) -> -613.35484 | AZ28: =ELEC!A25 -> 0 | BA28: ='General information '!D28 -> 28 | BB28: =SUM('General information '!E28) -> 0.67 | BC28: =IF(AR27>=AR28,0,1) -> 0 | BD28: 19222 | BE28: =(305/1185)*ELEC!Q26 -> 514.76793 | BG28: =#REF!-BE28 -> #REF!
A29: =ELEC!C26 -> 44098 | B29: ='B5'!B28 -> 245 | C29: =B29*$B$4 -> 5271.4516 | D29: =SUM(B29) -> 245 | E29: =D29*$B$4 -> 5271.4516 | F29: =SUM(D29) -> 245 | G29: =F29*$B$4 -> 5271.4516 | H29: =SUM(F29) -> 245 | I29: =H29*$B$4 -> 5271.4516 | J29: =SUM(H29) -> 245 | K29: =J29*$B$4 -> 5271.4516 | L29: =SUM(J29) -> 245 | M29: =L29*$B$4 -> 5271.4516 | N29: =SUM(L29) -> 245 | O29: =N29*$B$4 -> 5271.4516 | P29: =SUM(N29) -> 245 | Q29: =P29*$B$4 -> 5271.4516 | R29: =SUM(P29) -> 245 | S29: =R29*$B$4 -> 5271.4516 | T29: =SUM(R29) -> 245 | U29: =T29*$B$4 -> 5271.4516 | V29: =SUM(T29) -> 245 | W29: =V29*$B$4 -> 5271.4516 | X29: =SUM(Y29/73370) -> 0.79032258 | Y29: =SUM(C29+E29+G29+I29+K29+M29+O29+Q29+S29+U29+W29) -> 57985.968 | Z29: ='B5'!C28 -> 250.3 | AA29: =SUM(Z29*$Z$4) -> 2503 | AB29: =SUM(Z29) -> 250.3 | AC29: =SUM(AB29*$Z$4) -> 2503 | AD29: =SUM(AB29) -> 250.3 | AE29: =SUM(AD29*$Z$4) -> 2503 | AF29: =SUM(AD29) -> 250.3 | AG29: =SUM(AF29*$Z$4) -> 2503 | AH29: =SUM(AF29) -> 250.3 | AI29: =SUM(AH29*$Z$4) -> 2503 | AJ29: =SUM(AH29) -> 250.3 | AK29: =SUM(AJ29*$Z$4) -> 2503 | AL29: =SUM(AJ29) -> 250.3 | AM29: =SUM(AL29*$Z$4) -> 2503 | AN29: =SUM(AO29/19600) -> 0.89392857 | AO29: =SUM(AA29+AC29+AE29+AG29+AI29+AK29+AM29) -> 17521 | AQ29: =SUM(AR29/92970) -> 0.81216487 | AR29: =SUM(AO29+Y29) -> 75506.968 | AS29: =SUM(AR29-AR28-AT29) -> 1321.3871 | AT29: 9670 | AU29: 0.503 | AV29: =IF(AT29>0,AU29,AV28) -> 0.503 | AW29: =-SUM('B5'!AI28) -> 0 | AX29: =-SUM(AW29-AS29) -> 1321.3871 | AY29: =SUM(AX29+AW29) -> 1321.3871 | AZ29: =ELEC!A26 -> 0 | BA29: ='General information '!D29 -> 28.5 | BB29: =SUM('General information '!E29) -> 0.66 | BC29: =IF(AR28>=AR29,0,1) -> 1 | BD29: 19222 | BE29: =(305/1185)*ELEC!Q27 -> 257.38397 | BG29: =#REF!-BE29 -> #REF!
A30: =ELEC!C27 -> 44099 | B30: ='B5'!B29 -> 242 | C30: =B30*$B$4 -> 5206.9032 | D30: =SUM(B30) -> 242 | E30: =D30*$B$4 -> 5206.9032 | F30: =SUM(D30) -> 242 | G30: =F30*$B$4 -> 5206.9032 | H30: =SUM(F30) -> 242 | I30: =H30*$B$4 -> 5206.9032 | J30: =SUM(H30) -> 242 | K30: =J30*$B$4 -> 5206.9032 | L30: =SUM(J30) -> 242 | M30: =L30*$B$4 -> 5206.9032 | N30: =SUM(L30) -> 242 | O30: =N30*$B$4 -> 5206.9032 | P30: =SUM(N30) -> 242 | Q30: =P30*$B$4 -> 5206.9032 | R30: =SUM(P30) -> 242 | S30: =R30*$B$4 -> 5206.9032 | T30: =SUM(R30) -> 242 | U30: =T30*$B$4 -> 5206.9032 | V30: =SUM(T30) -> 242 | W30: =V30*$B$4 -> 5206.9032 | X30: =SUM(Y30/73370) -> 0.78064516 | Y30: =SUM(C30+E30+G30+I30+K30+M30+O30+Q30+S30+U30+W30) -> 57275.935 | Z30: ='B5'!C29 -> 249 | AA30: =SUM(Z30*$Z$4) -> 2490 | AB30: =SUM(Z30) -> 249 | AC30: =SUM(AB30*$Z$4) -> 2490 | AD30: =SUM(AB30) -> 249 | AE30: =SUM(AD30*$Z$4) -> 2490 | AF30: =SUM(AD30) -> 249 | AG30: =SUM(AF30*$Z$4) -> 2490 | AH30: =SUM(AF30) -> 249 | AI30: =SUM(AH30*$Z$4) -> 2490 | AJ30: =SUM(AH30) -> 249 | AK30: =SUM(AJ30*$Z$4) -> 2490 | AL30: =SUM(AJ30) -> 249 | AM30: =SUM(AL30*$Z$4) -> 2490 | AN30: =SUM(AO30/19600) -> 0.88928571 | AO30: =SUM(AA30+AC30+AE30+AG30+AI30+AK30+AM30) -> 17430 | AQ30: =SUM(AR30/92970) -> 0.80354884 | AR30: =SUM(AO30+Y30) -> 74705.935 | AS30: =SUM(AR30-AR29-AT30) -> -801.03226 | AV30: =IF(AT30>0,AU30,AV29) -> 0.503 | AW30: =-SUM('B5'!AI29) -> 0 | AX30: =-SUM(AW30-AS30) -> -801.03226 | AY30: =SUM(AX30+AW30) -> -801.03226 | AZ30: =ELEC!A27 -> 0 | BA30: ='General information '!D30 -> 27.5 | BB30: =SUM('General information '!E30) -> 0.65 | BC30: =IF(AR29>=AR30,0,1) -> 0 | BD30: 19222 | BE30: =(305/1185)*ELEC!Q28 -> 514.76793 | BG30: =#REF!-BE30 -> #REF!
A31: =ELEC!C28 -> 44100 | B31: ='B5'!B30 -> 240.2 | C31: =B31*$B$4 -> 5168.1742 | D31: =SUM(B31) -> 240.2 | E31: =D31*$B$4 -> 5168.1742 | F31: =SUM(D31) -> 240.2 | G31: =F31*$B$4 -> 5168.1742 | H31: =SUM(F31) -> 240.2 | I31: =H31*$B$4 -> 5168.1742 | J31: =SUM(H31) -> 240.2 | K31: =J31*$B$4 -> 5168.1742 | L31: =SUM(J31) -> 240.2 | M31: =L31*$B$4 -> 5168.1742 | N31: =SUM(L31) -> 240.2 | O31: =N31*$B$4 -> 5168.1742 | P31: =SUM(N31) -> 240.2 | Q31: =P31*$B$4 -> 5168.1742 | R31: =SUM(P31) -> 240.2 | S31: =R31*$B$4 -> 5168.1742 | T31: =SUM(R31) -> 240.2 | U31: =T31*$B$4 -> 5168.1742 | V31: =SUM(T31) -> 240.2 | W31: =V31*$B$4 -> 5168.1742 | X31: =SUM(Y31/73370) -> 0.77483871 | Y31: =SUM(C31+E31+G31+I31+K31+M31+O31+Q31+S31+U31+W31) -> 56849.916 | Z31: ='B5'!C30 -> 247 | AA31: =SUM(Z31*$Z$4) -> 2470 | AB31: =SUM(Z31) -> 247 | AC31: =SUM(AB31*$Z$4) -> 2470 | AD31: =SUM(AB31) -> 247 | AE31: =SUM(AD31*$Z$4) -> 2470 | AF31: =SUM(AD31) -> 247 | AG31: =SUM(AF31*$Z$4) -> 2470 | AH31: =SUM(AF31) -> 247 | AI31: =SUM(AH31*$Z$4) -> 2470 | AJ31: =SUM(AH31) -> 247 | AK31: =SUM(AJ31*$Z$4) -> 2470 | AL31: =SUM(AJ31) -> 247 | AM31: =SUM(AL31*$Z$4) -> 2470 | AN31: =SUM(AO31/19600) -> 0.88214286 | AO31: =SUM(AA31+AC31+AE31+AG31+AI31+AK31+AM31) -> 17290 | AQ31: =SUM(AR31/92970) -> 0.79746064 | AR31: =SUM(AO31+Y31) -> 74139.916 | AS31: =SUM(AR31-AR30-AT31) -> -566.01935 | AV31: =IF(AT31>0,AU31,AV30) -> 0.503 | AW31: =-SUM('B5'!AI30) -> 0 | AX31: =-SUM(AW31-AS31) -> -566.01935 | AY31: =SUM(AX31+AW31) -> -566.01935 | AZ31: =ELEC!A28 -> 0 | BA31: ='General information '!D31 -> 28 | BB31: =SUM('General information '!E31) -> 0.65 | BC31: =IF(AR30>=AR31,0,1) -> 0 | BD31: 19222 | BE31: =(305/1185)*ELEC!Q29 -> 231.64557 | BG31: =#REF!-BE31 -> #REF!
A32: =ELEC!C29 -> 44101 | B32: ='B5'!B31 -> 239.3 | C32: =B32*$B$4 -> 5148.8097 | D32: =SUM(B32) -> 239.3 | E32: =D32*$B$4 -> 5148.8097 | F32: =SUM(D32) -> 239.3 | G32: =F32*$B$4 -> 5148.8097 | H32: =SUM(F32) -> 239.3 | I32: =H32*$B$4 -> 5148.8097 | J32: =SUM(H32) -> 239.3 | K32: =J32*$B$4 -> 5148.8097 | L32: =SUM(J32) -> 239.3 | M32: =L32*$B$4 -> 5148.8097 | N32: =SUM(L32) -> 239.3 | O32: =N32*$B$4 -> 5148.8097 | P32: =SUM(N32) -> 239.3 | Q32: =P32*$B$4 -> 5148.8097 | R32: =SUM(P32) -> 239.3 | S32: =R32*$B$4 -> 5148.8097 | T32: =SUM(R32) -> 239.3 | U32: =T32*$B$4 -> 5148.8097 | V32: =SUM(T32) -> 239.3 | W32: =V32*$B$4 -> 5148.8097 | X32: =SUM(Y32/73370) -> 0.77193548 | Y32: =SUM(C32+E32+G32+I32+K32+M32+O32+Q32+S32+U32+W32) -> 56636.906 | Z32: ='B5'!C31 -> 246 | AA32: =SUM(Z32*$Z$4) -> 2460 | AB32: =SUM(Z32) -> 246 | AC32: =SUM(AB32*$Z$4) -> 2460 | AD32: =SUM(AB32) -> 246 | AE32: =SUM(AD32*$Z$4) -> 2460 | AF32: =SUM(AD32) -> 246 | AG32: =SUM(AF32*$Z$4) -> 2460 | AH32: =SUM(AF32) -> 246 | AI32: =SUM(AH32*$Z$4) -> 2460 | AJ32: =SUM(AH32) -> 246 | AK32: =SUM(AJ32*$Z$4) -> 2460 | AL32: =SUM(AJ32) -> 246 | AM32: =SUM(AL32*$Z$4) -> 2460 | AN32: =SUM(AO32/19600) -> 0.87857143 | AO32: =SUM(AA32+AC32+AE32+AG32+AI32+AK32+AM32) -> 17220 | AQ32: =SUM(AR32/92970) -> 0.79441655 | AR32: =SUM(AO32+Y32) -> 73856.906 | AS32: =SUM(AR32-AR31-AT32) -> -283.00968 | AV32: =IF(AT32>0,AU32,AV31) -> 0.503 | AW32: =-SUM('B5'!AI31) -> 0 | AX32: =-SUM(AW32-AS32) -> -283.00968 | AY32: =SUM(AX32+AW32) -> -283.00968 | AZ32: =ELEC!A29 -> 0 | BA32: ='General information '!D32 -> 27.5 | BB32: =SUM('General information '!E32) -> 0.55 | BC32: =IF(AR31>=AR32,0,1) -> 0 | BD32: 19222 | BE32: =(305/1185)*ELEC!Q30 -> 283.12236 | BG32: =#REF!-BE32 -> #REF!
A33: =ELEC!C30 -> 44102 | B33: ='B5'!B32 -> 238 | C33: =B33*$B$4 -> 5120.8387 | D33: =SUM(B33) -> 238 | E33: =D33*$B$4 -> 5120.8387 | F33: =SUM(D33) -> 238 | G33: =F33*$B$4 -> 5120.8387 | H33: =SUM(F33) -> 238 | I33: =H33*$B$4 -> 5120.8387 | J33: =SUM(H33) -> 238 | K33: =J33*$B$4 -> 5120.8387 | L33: =SUM(J33) -> 238 | M33: =L33*$B$4 -> 5120.8387 | N33: =SUM(L33) -> 238 | O33: =N33*$B$4 -> 5120.8387 | P33: =SUM(N33) -> 238 | Q33: =P33*$B$4 -> 5120.8387 | R33: =SUM(P33) -> 238 | S33: =R33*$B$4 -> 5120.8387 | T33: =SUM(R33) -> 238 | U33: =T33*$B$4 -> 5120.8387 | V33: =SUM(T33) -> 238 | W33: =V33*$B$4 -> 5120.8387 | X33: =SUM(Y33/73370) -> 0.76774194 | Y33: =SUM(C33+E33+G33+I33+K33+M33+O33+Q33+S33+U33+W33) -> 56329.226 | Z33: ='B5'!C32 -> 244 | AA33: =SUM(Z33*$Z$4) -> 2440 | AB33: =SUM(Z33) -> 244 | AC33: =SUM(AB33*$Z$4) -> 2440 | AD33: =SUM(AB33) -> 244 | AE33: =SUM(AD33*$Z$4) -> 2440 | AF33: =SUM(AD33) -> 244 | AG33: =SUM(AF33*$Z$4) -> 2440 | AH33: =SUM(AF33) -> 244 | AI33: =SUM(AH33*$Z$4) -> 2440 | AJ33: =SUM(AH33) -> 244 | AK33: =SUM(AJ33*$Z$4) -> 2440 | AL33: =SUM(AJ33) -> 244 | AM33: =SUM(AL33*$Z$4) -> 2440 | AN33: =SUM(AO33/19600) -> 0.87142857 | AO33: =SUM(AA33+AC33+AE33+AG33+AI33+AK33+AM33) -> 17080 | AQ33: =SUM(AR33/92970) -> 0.78960122 | AR33: =SUM(AO33+Y33) -> 73409.226 | AS33: =SUM(AR33-AR32-AT33) -> -447.68065 | AV33: =IF(AT33>0,AU33,AV32) -> 0.503 | AW33: =-SUM('B5'!AI32) -> 0 | AX33: =-SUM(AW33-AS33) -> -447.68065 | AY33: =SUM(AX33+AW33) -> -447.68065 | AZ33: =ELEC!A30 -> 0 | BA33: ='General information '!D33 -> 27.5 | BB33: =SUM('General information '!E33) -> 0.49 | BC33: =IF(AR32>=AR33,0,1) -> 0 | BD33: 19222 | BE33: =(305/1185)*ELEC!Q31 -> 514.76793 | BG33: =#REF!-BE33 -> #REF!
A34: =ELEC!C31 -> 44103 | B34: ='B5'!B33 -> 255.2 | C34: =B34*$B$4 -> 5490.9161 | D34: =SUM(B34) -> 255.2 | E34: =D34*$B$4 -> 5490.9161 | F34: =SUM(D34) -> 255.2 | G34: =F34*$B$4 -> 5490.9161 | H34: =SUM(F34) -> 255.2 | I34: =H34*$B$4 -> 5490.9161 | J34: =SUM(H34) -> 255.2 | K34: =J34*$B$4 -> 5490.9161 | L34: =SUM(J34) -> 255.2 | M34: =L34*$B$4 -> 5490.9161 | N34: =SUM(L34) -> 255.2 | O34: =N34*$B$4 -> 5490.9161 | P34: =SUM(N34) -> 255.2 | Q34: =P34*$B$4 -> 5490.9161 | R34: =SUM(P34) -> 255.2 | S34: =R34*$B$4 -> 5490.9161 | T34: =SUM(R34) -> 255.2 | U34: =T34*$B$4 -> 5490.9161 | V34: =SUM(T34) -> 255.2 | W34: =V34*$B$4 -> 5490.9161 | X34: =SUM(Y34/73370) -> 0.82322581 | Y34: =SUM(C34+E34+G34+I34+K34+M34+O34+Q34+S34+U34+W34) -> 60400.077 | Z34: ='B5'!C33 -> 261 | AA34: =SUM(Z34*$Z$4) -> 2610 | AB34: =SUM(Z34) -> 261 | AC34: =SUM(AB34*$Z$4) -> 2610 | AD34: =SUM(AB34) -> 261 | AE34: =SUM(AD34*$Z$4) -> 2610 | AF34: =SUM(AD34) -> 261 | AG34: =SUM(AF34*$Z$4) -> 2610 | AH34: =SUM(AF34) -> 261 | AI34: =SUM(AH34*$Z$4) -> 2610 | AJ34: =SUM(AH34) -> 261 | AK34: =SUM(AJ34*$Z$4) -> 2610 | AL34: =SUM(AJ34) -> 261 | AM34: =SUM(AL34*$Z$4) -> 2610 | AN34: =SUM(AO34/19600) -> 0.93214286 | AO34: =SUM(AA34+AC34+AE34+AG34+AI34+AK34+AM34) -> 18270 | AQ34: =SUM(AR34/92970) -> 0.84618777 | AR34: =SUM(AO34+Y34) -> 78670.077 | AS34: =SUM(AR34-AR33-AT34) -> 221.85161 | AT34: 5039 | AU34: 0.503 | AV34: =IF(AT34>0,AU34,AV33) -> 0.503 | AW34: =-SUM('B5'!AI33) -> 0 | AX34: =-SUM(AW34-AS34) -> 221.85161 | AY34: =SUM(AX34+AW34) -> 221.85161 | AZ34: =ELEC!A31 -> 0 | BA34: ='General information '!D34 -> 28.5 | BB34: =SUM('General information '!E34) -> 0.59 | BC34: =IF(AR33>=AR34,0,1) -> 1 | BD34: 19222 | BE34: =(305/1185)*ELEC!#REF! -> #REF! | BG34: =#REF!-BE34 -> #REF!
A35: =ELEC!C32 -> 44104 | B35: ='B5'!B34 -> 251 | C35: =B35*$B$4 -> 5400.5484 | D35: =SUM(B35) -> 251 | E35: =D35*$B$4 -> 5400.5484 | F35: =SUM(D35) -> 251 | G35: =F35*$B$4 -> 5400.5484 | H35: =SUM(F35) -> 251 | I35: =H35*$B$4 -> 5400.5484 | J35: =SUM(H35) -> 251 | K35: =J35*$B$4 -> 5400.5484 | L35: =SUM(J35) -> 251 | M35: =L35*$B$4 -> 5400.5484 | N35: =SUM(L35) -> 251 | O35: =N35*$B$4 -> 5400.5484 | P35: =SUM(N35) -> 251 | Q35: =P35*$B$4 -> 5400.5484 | R35: =SUM(P35) -> 251 | S35: =R35*$B$4 -> 5400.5484 | T35: =SUM(R35) -> 251 | U35: =T35*$B$4 -> 5400.5484 | V35: =SUM(T35) -> 251 | W35: =V35*$B$4 -> 5400.5484 | X35: =SUM(Y35/73370) -> 0.80967742 | Y35: =SUM(C35+E35+G35+I35+K35+M35+O35+Q35+S35+U35+W35) -> 59406.032 | Z35: ='B5'!C34 -> 257 | AA35: =SUM(Z35*$Z$4) -> 2570 | AB35: =SUM(Z35) -> 257 | AC35: =SUM(AB35*$Z$4) -> 2570 | AD35: =SUM(AB35) -> 257 | AE35: =SUM(AD35*$Z$4) -> 2570 | AF35: =SUM(AD35) -> 257 | AG35: =SUM(AF35*$Z$4) -> 2570 | AH35: =SUM(AF35) -> 257 | AI35: =SUM(AH35*$Z$4) -> 2570 | AJ35: =SUM(AH35) -> 257 | AK35: =SUM(AJ35*$Z$4) -> 2570 | AL35: =SUM(AJ35) -> 257 | AM35: =SUM(AL35*$Z$4) -> 2570 | AN35: =SUM(AO35/19600) -> 0.91785714 | AO35: =SUM(AA35+AC35+AE35+AG35+AI35+AK35+AM35) -> 17990 | AQ35: =SUM(AR35/92970) -> 0.83248394 | AR35: =SUM(AO35+Y35) -> 77396.032 | AS35: =SUM(AR35-AR34-AT35) -> -1274.0452 | AV35: =IF(AT35>0,AU35,AV34) -> 0.503 | AW35: =-SUM('B5'!AI34) -> 0 | AX35: =-SUM(AW35-AS35) -> -1274.0452 | AY35: =SUM(AX35+AW35) -> -1274.0452 | AZ35: =ELEC!A32 -> 0 | BA35: ='General information '!D35 -> 28.5 | BB35: =SUM('General information '!E35) -> 0.65 | BC35: =IF(AR34>=AR35,0,1) -> 0 | BD35: 19222 | BE35: =(305/1185)*ELEC!#REF! -> #REF! | BG35: =#REF!-BE35 -> #REF!
AR36: NB delivery | AS36: =COUNT(AT6:AT35) -> 3 | AT36: =SUM(AT6:AT35) -> 29709 | AU36: =SUM(AU6:AU35)/AS36 -> 0.51533333 | AX36: =SUM(AX6:AX35) -> -25150.871 | AY36: =SUM(AY6:AY35) -> -25958.871
AT37: =+AT36*AU36 -> 15310.038
AS39: =SUM(AS6:AS35)/'EDl log'!A36 -> -865.2957

Sheet GEN
B1: GEN1 | C1: RUN HR | D1: Fuel Counter Index | E1: Cons /day | F1: Diesel L/H | H1: next service | I1: ALARM | J1: GEN2 | K1: RUN HR | L1: Fuel Counter Index | M1: Cons /day | N1: Diesel L/H | P1: next service | Q1: ALARM | R1: GEN3 | S1: RUN HR | T1: Fuel Counter Index | U1: Cons /day | V1: Diesel L/H | X1: next service | Y1: ALARM | Z1: RH total | AA1: Gen Con /day | AB1: Total Deisel Cons/day | AC1: H /L | AD1: TOAL KW GEN | AI1: fuel Consuption | AK1: AVG KW/h
A2: =ELEC!C2 -> 44074 | B2: =[1]GEN!B33 -> 9112 | C2: =[1]GEN!C33 -> 0 | D2: 225093 | E2: =[1]GEN!E33 -> 0 | F2: =[1]GEN!F33 -> 0 | G2: =[1]GEN!G33 -> 0 | H2: =[1]GEN!H33 -> 9100 | I2: =[1]GEN!I33 -> oil change | J2: =[1]GEN!J33 -> 10698 | K2: =[1]GEN!K33 -> 0 | L2: =[1]GEN!L33 -> 238500 | ... AK2: =[1]GEN!AK33 -> 171.58931
A3: =ELEC!C3 -> 44075 | B3: 9112 | C3: =B3-B2 -> 0 | D3: =D2 -> 225093 | E3: =SUM(D3-D2) -> 0 | F3: =IF(C3>0,E3/C3,0) -> 0 | G3: =[3]GEN!G32 -> 0 | H3: =H2+180 -> 9280 | I3: =IF(B3-H3<=0,"ok","oil change") -> ok | J3: 10698 | K3: =J3-J2 -> 0 | L3: =L2 -> 238500 | M3: =SUM(L3-L2) -> 0 | N3: =IF(K3>0,M3/K3,0) -> 0 | O3: =[3]GEN!O32 -> 0 | P3: =P2 -> 10873 | Q3: =IF(J3-P3<=0,"ok","oil change") -> ok | R3: 11653 | S3: =R3-R2 -> 3 | T3: 346214 | U3: =SUM(T3-T2) -> 706 | V3: =IF(S3>0,U3/S3,0) -> 235.33333 | W3: =[3]GEN!W32 -> 0 | X3: =X2 -> 12429 | Y3: =IF(R3-X3<=0,"ok","oil change") -> ok | Z3: =C3+K3+S3 -> 3 | AA3: =U3+M3+E3 -> 706 | AB3: =V3+N3+F3 -> 235.33333 | AC3: =IF(Z3>0,AA3/Z3,0) -> 235.33333 | AD3: =ELEC!Q3 -> 1000 | AE3: =SUM(AD3/Z3) -> 333.33333 | AF3: =SUM(AE3/1600) -> 0.20833333 | AG3: =SUM(360*AF3) -> 75 | AH3: =SUM(AC3-AG3) -> 160.33333 | AI3: =AD3*AJ3 -> 257.38397 | AJ3: =305/1185 -> 0.25738397 | AK3: =AI3/Z3 -> 85.794655
A4: =ELEC!C4 -> 44076 | B4: 9113 | C4: =B4-B3 -> 1 | D4: 225380 | E4: =SUM(D4-D3) -> 287 | F4: =IF(C4>0,E4/C4,0) -> 287 | H4: =H3 -> 9280 | I4: =IF(B4-H4<=0,"ok","oil change") -> ok | J4: 10698 | K4: =J4-J3 -> 0 | L4: 238500 | M4: =SUM(L4-L3) -> 0 | N4: =IF(K4>0,M4/K4,0) -> 0 | P4: =P3 -> 10873 | Q4: =IF(J4-P4<=0,"ok","oil change") -> ok | R4: 11658 | S4: =R4-R3 -> 5 | T4: 347163 | U4: =SUM(T4-T3) -> 949 | V4: =IF(S4>0,U4/S4,0) -> 189.8 | X4: =X3 -> 12429 | Y4: =IF(R4-X4<=0,"ok","oil change") -> ok | Z4: =C4+K4+S4 -> 6 | AA4: =U4+M4+E4 -> 1236 | AB4: =V4+N4+F4 -> 476.8 | AC4: =IF(Z4>0,AA4/Z4,0) -> 206 | AD4: =ELEC!Q4 -> 5000 | AE4: =SUM(AD4/Z4) -> 833.33333 | AF4: =SUM(AE4/1600) -> 0.52083333 | AG4: =SUM(360*AF4) -> 187.5 | AH4: =SUM(AC4-AG4) -> 18.5 | AI4: =AD4*AJ4 -> 1286.9198 | AJ4: =305/1185 -> 0.25738397 | AK4: =AI4/Z4 -> 214.48664
A5: =ELEC!C5 -> 44077 | B5: 9121 | C5: =B5-B4 -> 8 | D5: 226901 | E5: =SUM(D5-D4) -> 1521 | F5: =IF(C5>0,E5/C5,0) -> 190.125 | H5: =H4 -> 9280 | I5: =IF(B5-H5<=0,"ok","oil change") -> ok | J5: =J4 -> 10698 | K5: =J5-J4 -> 0 | L5: =L4 -> 238500 | M5: =SUM(L5-L4) -> 0 | N5: =IF(K5>0,M5/K5,0) -> 0 | P5: =P4 -> 10873 | Q5: =IF(J5-P5<=0,"ok","oil change") -> ok | R5: 11658 | S5: =R5-R4 -> 0 | T5: =T4 -> 347163 | U5: =SUM(T5-T4) -> 0 | V5: =IF(S5>0,U5/S5,0) -> 0 | X5: =X4 -> 12429 | Y5: =IF(R5-X5<=0,"ok","oil change") -> ok | Z5: =C5+K5+S5 -> 8 | AA5: =U5+M5+E5 -> 1521 | AB5: =V5+N5+F5 -> 190.125 | AC5: =IF(Z5>0,AA5/Z5,0) -> 190.125 | AD5: =ELEC!Q5 -> 5000 | AE5: =SUM(AD5/Z5) -> 625 | AF5: =SUM(AE5/1600) -> 0.390625 | AG5: =SUM(320*AF5) -> 125 | AH5: =SUM(AC5-AG5) -> 65.125 | AI5: =AD5*AJ5 -> 1286.9198 | AJ5: =305/1185 -> 0.25738397 | AK5: =AI5/Z5 -> 160.86498
A6: =ELEC!C6 -> 44078 | B6: 9128 | C6: =B6-B5 -> 7 | D6: 227869 | E6: =SUM(D6-D5) -> 968 | F6: =IF(C6>0,E6/C6,0) -> 138.28571 | H6: 9298 | I6: =IF(B6-H6<=0,"ok","oil change") -> ok | J6: =J5 -> 10698 | K6: =J6-J5 -> 0 | L6: =L5 -> 238500 | M6: =SUM(L6-L5) -> 0 | N6: =IF(K6>0,M6/K6,0) -> 0 | P6: =P5 -> 10873 | Q6: =IF(J6-P6<=0,"ok","oil change") -> ok | R6: 11658 | S6: =R6-R5 -> 0 | T6: =T5 -> 347163 | U6: =SUM(T6-T5) -> 0 | V6: =IF(S6>0,U6/S6,0) -> 0 | X6: =X5 -> 12429 | Y6: =IF(R6-X6<=0,"ok","oil change") -> ok | Z6: =C6+K6+S6 -> 7 | AA6: =U6+M6+E6 -> 968 | AB6: =V6+N6+F6 -> 138.28571 | AC6: =IF(Z6>0,AA6/Z6,0) -> 138.28571 | AD6: =ELEC!Q6 -> 5000 | AE6: =SUM(AD6/Z6) -> 714.28571 | AF6: =SUM(AE6/1600) -> 0.44642857 | AG6: =SUM(320*AF6) -> 142.85714 | AH6: =SUM(AC6-AG6) -> -4.5714286 | AI6: =AD6*AJ6 -> 1286.9198 | AJ6: =305/1185 -> 0.25738397 | AK6: =AI6/Z6 -> 183.84569
A7: =ELEC!C7 -> 44079 | B7: 9132 | C7: =B7-B6 -> 4 | D7: =D6 -> 227869 | E7: =SUM(D7-D6) -> 0 | F7: =IF(C7>0,E7/C7,0) -> 0 | H7: =H6 -> 9298 | I7: =IF(B7-H7<=0,"ok","oil change") -> ok | J7: =J6 -> 10698 | K7: =J7-J6 -> 0 | L7: =L6 -> 238500 | M7: =SUM(L7-L6) -> 0 | N7: =IF(K7>0,M7/K7,0) -> 0 | P7: =P6 -> 10873 | Q7: =IF(J7-P7<=0,"ok","oil change") -> ok | R7: =R6 -> 11658 | S7: =R7-R6 -> 0 | T7: =T6 -> 347163 | U7: =SUM(T7-T6) -> 0 | V7: =IF(S7>0,U7/S7,0) -> 0 | X7: =X6 -> 12429 | Y7: =IF(R7-X7<=0,"ok","oil change") -> ok | Z7: =C7+K7+S7 -> 4 | AA7: =U7+M7+E7 -> 0 | AB7: =V7+N7+F7 -> 0 | AC7: =IF(Z7>0,AA7/Z7,0) -> 0 | AD7: =ELEC!Q7 -> 2000 | AE7: =SUM(AD7/Z7) -> 500 | AF7: =SUM(AE7/1600) -> 0.3125 | AH7: =SUM(AC7-AG7) -> #VALUE! | AI7: =AD7*AJ7 -> 514.76793 | AJ7: =305/1185 -> 0.25738397 | AK7: =AI7/Z7 -> 128.69198
A8: =ELEC!C8 -> 44080 | B8: 9140 | C8: =B8-B7 -> 8 | D8: 230126 | E8: =SUM(D8-D7) -> 2257 | F8: =IF(C8>0,E8/C8,0) -> 282.125 | H8: =H7 -> 9298 | I8: =IF(B8-H8<=0,"ok","oil change") -> ok | J8: =J7 -> 10698 | K8: =J8-J7 -> 0 | L8: =L7 -> 238500 | M8: =SUM(L8-L7) -> 0 | N8: =IF(K8>0,M8/K8,0) -> 0 | P8: =P7 -> 10873 | Q8: =IF(J8-P8<=0,"ok","oil change") -> ok | R8: =R7 -> 11658 | S8: =R8-R7 -> 0 | T8: =T7 -> 347163 | U8: =SUM(T8-T7) -> 0 | V8: =IF(S8>0,U8/S8,0) -> 0 | X8: =X7 -> 12429 | Y8: =IF(R8-X8<=0,"ok","oil change") -> ok | Z8: =C8+K8+S8 -> 8 | AA8: =U8+M8+E8 -> 2257 | AB8: =V8+N8+F8 -> 282.125 | AC8: =IF(Z8>0,AA8/Z8,0) -> 282.125 | AD8: =ELEC!Q8 -> 4000 | AE8: =SUM(AD8/Z8) -> 500 | AF8: =SUM(AE8/1600) -> 0.3125 | AG8: =SUM(320*AF8) -> 100 | AH8: =SUM(AC8-AG8) -> 182.125 | AI8: =AD8*AJ8 -> 1029.5359 | AJ8: =305/1185 -> 0.25738397 | AK8: =AI8/Z8 -> 128.69198
A9: =ELEC!C9 -> 44081 | B9: 9148 | C9: =B9-B8 -> 8 | D9: 230116 | E9: =SUM(D9-D8) -> -10 | F9: =IF(C9>0,E9/C9,0) -> -1.25 | H9: =H8 -> 9298 | I9: =IF(B9-H9<=0,"ok","oil change") -> ok | J9: =J8 -> 10698 | K9: =J9-J8 -> 0 | L9: =L8 -> 238500 | M9: =SUM(L9-L8) -> 0 | N9: =IF(K9>0,M9/K9,0) -> 0 | P9: =P8 -> 10873 | Q9: =IF(J9-P9<=0,"ok","oil change") -> ok | R9: =R8 -> 11658 | S9: =R9-R8 -> 0 | T9: =T8 -> 347163 | U9: =SUM(T9-T8) -> 0 | V9: =IF(S9>0,U9/S9,0) -> 0 | X9: =X8 -> 12429 | Y9: =IF(R9-X9<=0,"ok","oil change") -> ok | Z9: =C9+K9+S9 -> 8 | AA9: =U9+M9+E9 -> -10 | AB9: =V9+N9+F9 -> -1.25 | AC9: =IF(Z9>0,AA9/Z9,0) -> -1.25 | AD9: =ELEC!Q9 -> 5000 | AE9: =SUM(AD9/Z9) -> 625 | AF9: =SUM(AE9/1600) -> 0.390625 | AG9: =SUM(320*AF9) -> 125 | AH9: =SUM(AC9-AG9) -> -126.25 | AI9: =AD9*AJ9 -> 1286.9198 | AJ9: 0.25738397 | AK9: =IF(Z9>0,AI9/Z9,0) -> 160.86498
A10: =ELEC!C10 -> 44082 | B10: 9162 | C10: =B10-B9 -> 14 | D10: =D9 -> 230116 | E10: =SUM(D10-D9) -> 0 | F10: =IF(C10>0,E10/C10,0) -> 0 | H10: =H9 -> 9298 | I10: =IF(B10-H10<=0,"ok","oil change") -> ok | J10: =J9 -> 10698 | K10: =J10-J9 -> 0 | L10: =L9 -> 238500 | M10: =SUM(L10-L9) -> 0 | N10: =IF(K10>0,M10/K10,0) -> 0 | P10: 10873 | Q10: =IF(J10-P10<=0,"ok","oil change") -> ok | R10: 11658 | S10: =R10-R9 -> 0 | T10: =T9 -> 347163 | U10: =SUM(T10-T9) -> 0 | V10: =IF(S10>0,U10/S10,0) -> 0 | X10: =X9 -> 12429 | Y10: =IF(R10-X10<=0,"ok","oil change") -> ok | Z10: =C10+K10+S10 -> 14 | AA10: =U10+M10+E10 -> 0 | AB10: =V10+N10+F10 -> 0 | AC10: =IF(Z10>0,AA10/Z10,0) -> 0 | AD10: =ELEC!Q10 -> 8000 | AE10: =SUM(AD10/Z10) -> 571.42857 | AF10: =SUM(AE10/1600) -> 0.35714286 | AG10: =SUM(320*AF10) -> 114.28571 | AH10: =SUM(AC10-AG10) -> -114.28571 | AI10: =AD10*AJ10 -> 2059.0717 | AJ10: =305/1185 -> 0.25738397 | AK10: =IF(Z10>0,AI10/Z10,0) -> 147.07655
A11: =ELEC!C11 -> 44083 | B11: 9166 | C11: =B11-B10 -> 4 | D11: 235548 | E11: =SUM(D11-D10) -> 5432 | F11: =IF(C11>0,E11/C11,0) -> 1358 | H11: =H10 -> 9298 | I11: =IF(B11-H11<=0,"ok","oil change") -> ok | J11: =J10 -> 10698 | K11: =J11-J10 -> 0 | L11: =L10 -> 238500 | M11: =SUM(L11-L10) -> 0 | N11: =IF(K11>0,M11/K11,0) -> 0 | P11: =P10 -> 10873 | Q11: =IF(J11-P11<=0,"ok","oil change") -> ok | R11: 11659 | S11: =R11-R10 -> 1 | T11: 347562 | U11: =SUM(T11-T10) -> 399 | V11: =IF(S11>0,U11/S11,0) -> 399 | X11: =X10 -> 12429 | Y11: =IF(R11-X11<=0,"ok","oil change") -> ok | Z11: =C11+K11+S11 -> 5 | AA11: =U11+M11+E11 -> 5831 | AB11: =V11+N11+F11 -> 1757 | AC11: =IF(Z11>0,AA11/Z11,0) -> 1166.2 | AD11: =ELEC!Q11 -> 2000 | AE11: =SUM(AD11/Z11) -> 400 | AF11: =SUM(AE11/1600) -> 0.25 | AG11: =SUM(320*AF11) -> 80 | AH11: =SUM(AC11-AG11) -> 1086.2 | AI11: =AD11*AJ11 -> 514.76793 | AJ11: =305/1185 -> 0.25738397 | AK11: =IF(Z11>0,AI11/Z11,0) -> 102.95359
A12: =ELEC!C12 -> 44084 | B12: =B11 -> 9166 | C12: =B12-B11 -> 0 | D12: =D11 -> 235548 | E12: =SUM(D12-D11) -> 0 | F12: =IF(C12>0,E12/C12,0) -> 0 | H12: =H11 -> 9298 | I12: =IF(B12-H12<=0,"ok","oil change") -> ok | J12: =J11 -> 10698 | K12: =J12-J11 -> 0 | L12: =L11 -> 238500 | M12: =SUM(L12-L11) -> 0 | N12: =IF(K12>0,M12/K12,0) -> 0 | P12: =P11 -> 10873 | Q12: =IF(J12-P12<=0,"ok","oil change") -> ok | R12: 11662 | S12: =R12-R11 -> 3 | T12: 348112 | U12: =SUM(T12-T11) -> 550 | V12: =IF(S12>0,U12/S12,0) -> 183.33333 | X12: =X11 -> 12429 | Y12: =IF(R12-X12<=0,"ok","oil change") -> ok | Z12: =C12+K12+S12 -> 3 | AA12: =U12+M12+E12 -> 550 | AB12: =V12+N12+F12 -> 183.33333 | AC12: =IF(Z12>0,AA12/Z12,0) -> 183.33333 | AD12: =ELEC!Q12 -> 2000 | AE12: =SUM(AD12/Z12) -> 666.66667 | AF12: =SUM(AE12/1600) -> 0.41666667 | AG12: =SUM(320*AF12) -> 133.33333 | AH12: =SUM(AC12-AG12) -> 50 | AI12: =AD12*AJ12 -> 514.76793 | AJ12: =305/1185 -> 0.25738397 | AK12: =IF(Z12>0,AI12/Z12,0) -> 171.58931
A13: =ELEC!C13 -> 44085 | B13: =B12 -> 9166 | C13: =B13-B12 -> 0 | D13: =D12 -> 235548 | E13: =SUM(D13-D12) -> 0 | F13: =IF(C13>0,E13/C13,0) -> 0 | H13: =H12 -> 9298 | I13: =IF(B13-H13<=0,"ok","oil change") -> ok | J13: =J12 -> 10698 | K13: =J13-J12 -> 0 | L13: =L12 -> 238500 | M13: =SUM(L13-L12) -> 0 | N13: =IF(K13>0,M13/K13,0) -> 0 | P13: =P12 -> 10873 | Q13: =IF(J13-P13<=0,"ok","oil change") -> ok | R13: 11669 | S13: =R13-R12 -> 7 | T13: 349508 | U13: =SUM(T13-T12) -> 1396 | V13: =IF(S13>0,U13/S13,0) -> 199.42857 | X13: =X12+180 -> 12609 | Y13: =IF(R13-X13<=0,"ok","oil change") -> ok | Z13: =C13+K13+S13 -> 7 | AA13: =U13+M13+E13 -> 1396 | AB13: =V13+N13+F13 -> 199.42857 | AC13: =IF(Z13>0,AA13/Z13,0) -> 199.42857 | AD13: =ELEC!Q13 -> 3000 | AE13: =SUM(AD13/Z13) -> 428.57143 | AF13: =SUM(AE13/1600) -> 0.26785714 | AG13: =SUM(320*AF13) -> 85.714286 | AH13: =SUM(AC13-AG13) -> 113.71429 | AI13: =AD13*AJ13 -> 772.1519 | AJ13: =305/1185 -> 0.25738397 | AK13: =IF(Z13>0,AI13/Z13,0) -> 110.30741
A14: =ELEC!C14 -> 44086 | B14: =B13 -> 9166 | C14: =B14-B13 -> 0 | D14: =D13 -> 235548 | E14: =SUM(D14-D13) -> 0 | F14: =IF(C14>0,E14/C14,0) -> 0 | H14: =H13 -> 9298 | I14: =IF(B14-H14<=0,"ok","oil change") -> ok | J14: =J13 -> 10698 | K14: =J14-J13 -> 0 | L14: =L13 -> 238500 | M14: =SUM(L14-L13) -> 0 | N14: =IF(K14>0,M14/K14,0) -> 0 | P14: =P13 -> 10873 | Q14: =IF(J14-P14<=0,"ok","oil change") -> ok | R14: 11675 | S14: =R14-R13 -> 6 | T14: 350834 | U14: =SUM(T14-T13) -> 1326 | V14: =IF(S14>0,U14/S14,0) -> 221 | X14: =X13 -> 12609 | Y14: =IF(R14-X14<=0,"ok","oil change") -> ok | Z14: =C14+K14+S14 -> 6 | AA14: =U14+M14+E14 -> 1326 | AB14: =V14+N14+F14 -> 221 | AC14: =IF(Z14>0,AA14/Z14,0) -> 221 | AD14: =ELEC!Q14 -> 3000 | AE14: =SUM(AD14/Z14) -> 500 | AF14: =SUM(AE14/1600) -> 0.3125 | AG14: =SUM(320*AF14) -> 100 | AH14: =SUM(AC14-AG14) -> 121 | AI14: =AD14*AJ14 -> 772.1519 | AJ14: =305/1185 -> 0.25738397 | AK14: =IF(Z14>0,AI14/Z14,0) -> 128.69198
A15: =ELEC!C15 -> 44087 | B15: 9166 | C15: =B15-B14 -> 0 | D15: 235549 | E15: =SUM(D15-D14) -> 1 | F15: =IF(C15>0,E15/C15,0) -> 0 | H15: =H14 -> 9298 | I15: =IF(B15-H15<=0,"ok","oil change") -> ok | J15: 10698 | K15: =J15-J14 -> 0 | L15: =L14 -> 238500 | M15: =SUM(L15-L14) -> 0 | N15: =IF(K15>0,M15/K15,0) -> 0 | P15: =P14 -> 10873 | Q15: =IF(J15-P15<=0,"ok","oil change") -> ok | R15: 11679 | S15: =R15-R14 -> 4 | T15: 351748 | U15: =SUM(T15-T14) -> 914 | V15: =IF(S15>0,U15/S15,0) -> 228.5 | X15: =X14 -> 12609 | Y15: =IF(R15-X15<=0,"ok","oil change") -> ok | Z15: =C15+K15+S15 -> 4 | AA15: =U15+M15+E15 -> 915 | AB15: =V15+N15+F15 -> 228.5 | AC15: =IF(Z15>0,AA15/Z15,0) -> 228.75 | AD15: =ELEC!Q15 -> 2000 | AE15: =SUM(AD15/Z15) -> 500 | AF15: =SUM(AE15/1600) -> 0.3125 | AG15: =SUM(320*AF15) -> 100 | AH15: =SUM(AC15-AG15) -> 128.75 | AI15: =AD15*AJ15 -> 514.76793 | AJ15: =305/1185 -> 0.25738397 | AK15: =IF(Z15>0,AI15/Z15,0) -> 128.69198
A16: =ELEC!C16 -> 44088 | B16: 9166 | C16: =B16-B15 -> 0 | D16: 235549 | E16: =SUM(D16-D15) -> 0 | F16: =IF(C16>0,E16/C16,0) -> 0 | H16: =H15 -> 9298 | I16: =IF(B16-H16<=0,"ok","oil change") -> ok | J16: =J15 -> 10698 | K16: =J16-J15 -> 0 | L16: =L15 -> 238500 | M16: =SUM(L16-L15) -> 0 | N16: =IF(K16>0,M16/K16,0) -> 0 | P16: =P15 -> 10873 | Q16: =IF(J16-P16<=0,"ok","oil change") -> ok | R16: 11682 | S16: =R16-R15 -> 3 | T16: 352350 | U16: =SUM(T16-T15) -> 602 | V16: =IF(S16>0,U16/S16,0) -> 200.66667 | X16: =X15 -> 12609 | Y16: =IF(R16-X16<=0,"ok","oil change") -> ok | Z16: =C16+K16+S16 -> 3 | AA16: =U16+M16+E16 -> 602 | AB16: =V16+N16+F16 -> 200.66667 | AC16: =IF(Z16>0,AA16/Z16,0) -> 200.66667 | AD16: =ELEC!Q16 -> 2000 | AE16: =SUM(AD16/Z16) -> 666.66667 | AF16: =SUM(AE16/1600) -> 0.41666667 | AG16: =SUM(320*AF16) -> 133.33333 | AH16: =SUM(AC16-AG16) -> 67.333333 | AI16: =AD16*AJ16 -> 514.76793 | AJ16: =305/1185 -> 0.25738397 | AK16: =IF(Z16>0,AI16/Z16,0) -> 171.58931
A17: =ELEC!C17 -> 44089 | B17: 9166 | C17: =B17-B16 -> 0 | D17: 235549 | E17: =SUM(D17-D16) -> 0 | F17: =IF(C17>0,E17/C17,0) -> 0 | H17: =H16 -> 9298 | I17: =IF(B17-H17<=0,"ok","oil change") -> ok | J17: =J16 -> 10698 | K17: =J17-J16 -> 0 | L17: =L16 -> 238500 | M17: =SUM(L17-L16) -> 0 | N17: =IF(K17>0,M17/K17,0) -> 0 | P17: =P16 -> 10873 | Q17: =IF(J17-P17<=0,"ok","oil change") -> ok | R17: 11687 | S17: =R17-R16 -> 5 | T17: 353470 | U17: =SUM(T17-T16) -> 1120 | V17: =IF(S17>0,U17/S17,0) -> 224 | X17: =X16 -> 12609 | Y17: =IF(R17-X17<=0,"ok","oil change") -> ok | Z17: =C17+K17+S17 -> 5 | AA17: =U17+M17+E17 -> 1120 | AB17: =V17+N17+F17 -> 224 | AC17: =IF(Z17>0,AA17/Z17,0) -> 224 | AD17: =ELEC!Q17 -> 3000 | AE17: =SUM(AD17/Z17) -> 600 | AF17: =SUM(AE17/1600) -> 0.375 | AG17: =SUM(320*AF17) -> 120 | AH17: =SUM(AC17-AG17) -> 104 | AI17: =AD17*AJ17 -> 772.1519 | AJ17: =305/1185 -> 0.25738397 | AK17: =IF(Z17>0,AI17/Z17,0) -> 154.43038
A18: =ELEC!C18 -> 44090 | B18: =B17 -> 9166 | C18: =B18-B17 -> 0 | D18: =D17 -> 235549 | E18: =SUM(D18-D17) -> 0 | F18: =IF(C18>0,E18/C18,0) -> 0 | H18: =H17 -> 9298 | I18: =IF(B18-H18<=0,"ok","oil change") -> ok | J18: =J17 -> 10698 | K18: =J18-J17 -> 0 | L18: =L17 -> 238500 | M18: =SUM(L18-L17) -> 0 | N18: =IF(K18>0,M18/K18,0) -> 0 | P18: =P17 -> 10873 | Q18: =IF(J18-P14<=0,"ok","oil change") -> ok | R18: 11693 | S18: =R18-R17 -> 6 | T18: 354748 | U18: =SUM(T18-T17) -> 1278 | V18: =IF(S18>0,U18/S18,0) -> 213 | X18: =X17 -> 12609 | Y18: =IF(R18-X18<=0,"ok","oil change") -> ok | Z18: =C18+K18+S18 -> 6 | AA18: =U18+M18+E18 -> 1278 | AB18: =V18+N18+F18 -> 213 | AC18: =IF(Z18>0,AA18/Z18,0) -> 213 | AD18: =ELEC!Q18 -> 3000 | AE18: =SUM(AD18/Z18) -> 500 | AF18: =SUM(AE18/1600) -> 0.3125 | AG18: =SUM(320*AF18) -> 100 | AH18: =SUM(AC18-AG18) -> 113 | AI18: =AD18*AJ18 -> 772.1519 | AJ18: =305/1185 -> 0.25738397 | AK18: =IF(Z18>0,AI18/Z18,0) -> 128.69198
A19: =ELEC!C19 -> 44091 | B19: =B18 -> 9166 | C19: =B19-B18 -> 0 | D19: =D18 -> 235549 | E19: =SUM(D19-D18) -> 0 | F19: =IF(C19>0,E19/C19,0) -> 0 | H19: =H18 -> 9298 | I19: =IF(B19-H19<=0,"ok","oil change") -> ok | J19: =J18 -> 10698 | K19: =J19-J18 -> 0 | L19: =L18 -> 238500 | M19: =SUM(L19-L18) -> 0 | N19: =IF(K19>0,M19/K19,0) -> 0 | P19: =P18 -> 10873 | Q19: =IF(J19-P19<=0,"ok","oil change") -> ok | R19: 11697 | S19: =R19-R18 -> 4 | T19: 355432 | U19: =SUM(T19-T18) -> 684 | V19: =IF(S19>0,U19/S19,0) -> 171 | X19: =X18 -> 12609 | Y19: =IF(R19-X19<=0,"ok","oil change") -> ok | Z19: =C19+K19+S19 -> 4 | AA19: =U19+M19+E19 -> 684 | AB19: =V19+N19+F19 -> 171 | AC19: =IF(Z19>0,AA19/Z19,0) -> 171 | AD19: =ELEC!Q19 -> 1000 | AE19: =SUM(AD19/Z19) -> 250 | AF19: =SUM(AE19/1600) -> 0.15625 | AG19: =SUM(320*AF19) -> 50 | AH19: =SUM(AC19-AG19) -> 121 | AI19: =AD19*AJ19 -> 257.38397 | AJ19: =305/1185 -> 0.25738397 | AK19: =IF(Z19>0,AI19/Z19,0) -> 64.345992
A20: =ELEC!C20 -> 44092 | B20: =B19 -> 9166 | C20: =B20-B19 -> 0 | D20: =D19 -> 235549 | E20: =SUM(D20-D19) -> 0 | F20: =IF(C20>0,E20/C20,0) -> 0 | H20: =H19 -> 9298 | I20: =IF(B20-H20<=0,"ok","oil change") -> ok | J20: =J19 -> 10698 | K20: =J20-J19 -> 0 | L20: =L19 -> 238500 | M20: =SUM(L20-L19) -> 0 | N20: =IF(K20>0,M20/K20,0) -> 0 | P20: =P19 -> 10873 | Q20: =IF(J20-P20<=0,"ok","oil change") -> ok | R20: 11700 | S20: =R20-R19 -> 3 | T20: 356228 | U20: =SUM(T20-T19) -> 796 | V20: =IF(S20>0,U20/S20,0) -> 265.33333 | X20: =X19 -> 12609 | Y20: =IF(R20-X20<=0,"ok","oil change") -> ok | Z20: =C20+K20+S20 -> 3 | AA20: =U20+M20+E20 -> 796 | AB20: =V20+N20+F20 -> 265.33333 | AC20: =IF(Z20>0,AA20/Z20,0) -> 265.33333 | AD20: =ELEC!Q20 -> 2000 | AE20: =SUM(AD20/Z20) -> 666.66667 | AF20: =SUM(AE20/1600) -> 0.41666667 | AG20: =SUM(320*AF20) -> 133.33333 | AH20: =SUM(AC20-AG20) -> 132 | AI20: =AD20*AJ20 -> 514.76793 | AJ20: =305/1185 -> 0.25738397 | AK20: =IF(Z20>0,AI20/Z20,0) -> 171.58931
A21: =ELEC!C21 -> 44093 | B21: =B20 -> 9166 | C21: =B21-B20 -> 0 | D21: =D20 -> 235549 | E21: =SUM(D21-D20) -> 0 | F21: =IF(C21>0,E21/C21,0) -> 0 | H21: =H20 -> 9298 | I21: =IF(B21-H21<=0,"ok","oil change") -> ok | J21: =J20 -> 10698 | K21: =J21-J20 -> 0 | L21: =L20 -> 238500 | M21: =SUM(L21-L20) -> 0 | N21: =IF(K21>0,M21/K21,0) -> 0 | P21: =P20 -> 10873 | Q21: =IF(J21-P21<=0,"ok","oil change") -> ok | R21: 11705 | S21: =R21-R20 -> 5 | T21: 357658 | U21: =SUM(T21-T20) -> 1430 | V21: =IF(S21>0,U21/S21,0) -> 286 | X21: =X20 -> 12609 | Y21: =Y20 -> ok | Z21: =C21+K21+S21 -> 5 | AA21: =U21+M21+E21 -> 1430 | AB21: =V21+N21+F21 -> 286 | AC21: =IF(Z21>0,AA21/Z21,0) -> 286 | AD21: =ELEC!Q21 -> 2000 | AE21: =SUM(AD21/Z21) -> 400 | AF21: =SUM(AE21/1600) -> 0.25 | AG21: =SUM(320*AF21) -> 80 | AH21: =SUM(AC21-AG21) -> 206 | AI21: =AD21*AJ21 -> 514.76793 | AJ21: =305/1185 -> 0.25738397 | AK21: =IF(Z21>0,AI21/Z21,0) -> 102.95359
A22: =ELEC!C22 -> 44094 | B22: 9170 | C22: =B22-B21 -> 4 | D22: 236426 | E22: =SUM(D22-D21) -> 877 | F22: =IF(C22>0,E22/C22,0) -> 219.25 | H22: =H21 -> 9298 | I22: =IF(B22-H22<=0,"ok","oil change") -> ok | J22: =J21 -> 10698 | K22: =J22-J21 -> 0 | L22: =L21 -> 238500 | M22: =SUM(L22-L21) -> 0 | N22: =IF(K22>0,M22/K22,0) -> 0 | P22: =P21 -> 10873 | Q22: =IF(J22-P22<=0,"ok","oil change") -> ok | R22: =R21 -> 11705 | S22: =R22-R21 -> 0 | T22: =T21 -> 357658 | U22: =SUM(T22-T21) -> 0 | V22: =IF(S22>0,U22/S22,0) -> 0 | X22: =X21 -> 12609 | Y22: =IF(R22-X22<=0,"ok","oil change") -> ok | Z22: =C22+K22+S22 -> 4 | AA22: =U22+M22+E22 -> 877 | AB22: =V22+N22+F22 -> 219.25 | AC22: =IF(Z22>0,AA22/Z22,0) -> 219.25 | AD22: =ELEC!Q22 -> 2495 | AE22: =SUM(AD22/Z22) -> 623.75 | AF22: =SUM(AE22/1600) -> 0.38984375 | AG22: =SUM(320*AF22) -> 124.75 | AH22: =SUM(AC22-AG22) -> 94.5 | AI22: =AD22*AJ22 -> 642.173 | AJ22: =305/1185 -> 0.25738397 | AK22: =IF(Z22>0,AI22/Z22,0) -> 160.54325
A23: =ELEC!C23 -> 44095 | B23: 9175 | C23: =B23-B22 -> 5 | D23: 237558 | E23: =SUM(D23-D22) -> 1132 | F23: =IF(C23>0,E23/C23,0) -> 226.4 | H23: =H22 -> 9298 | I23: =IF(B23-H23<=0,"ok","oil change") -> ok | J23: =J22 -> 10698 | K23: =J23-J22 -> 0 | L23: =L22 -> 238500 | M23: =SUM(L23-L22) -> 0 | N23: =IF(K23>0,M23/K23,0) -> 0 | P23: =P22 -> 10873 | Q23: =IF(J23-P23<=0,"ok","oil change") -> ok | R23: =R22 -> 11705 | S23: =R23-R22 -> 0 | T23: =T22 -> 357658 | U23: =SUM(T23-T22) -> 0 | V23: =IF(S23>0,U23/S23,0) -> 0 | X23: =X22 -> 12609 | Y23: =IF(R23-X23<=0,"ok","oil change") -> ok | Z23: =C23+K23+S23 -> 5 | AA23: =U23+M23+E23 -> 1132 | AB23: =V23+N23+F23 -> 226.4 | AC23: =IF(Z23>0,AA23/Z23,0) -> 226.4 | AD23: =ELEC!Q23 -> 1505 | AE23: =SUM(AD23/Z23) -> 301 | AF23: =SUM(AE23/1600) -> 0.188125 | AG23: =SUM(320*AF23) -> 60.2 | AH23: =SUM(AC23-AG23) -> 166.2 | AI23: =AD23*AJ23 -> 387.36287 | AJ23: =305/1185 -> 0.25738397 | AK23: =IF(Z23>0,AI23/Z23,0) -> 77.472574
A24: =ELEC!C24 -> 44096 | B24: 9182 | C24: =B24-B23 -> 7 | D24: 239169 | E24: =SUM(D24-D23) -> 1611 | F24: =IF(C24>0,E24/C24,0) -> 230.14286 | H24: =H23 -> 9298 | I24: =IF(B24-H24<=0,"ok","oil change") -> ok | J24: =J23 -> 10698 | K24: =J24-J23 -> 0 | L24: =L23 -> 238500 | M24: =SUM(L24-L23) -> 0 | N24: =IF(K24>0,M24/K24,0) -> 0 | P24: =P23 -> 10873 | Q24: =IF(J24-P24<=0,"ok","oil change") -> ok | R24: =R23 -> 11705 | S24: =R24-R23 -> 0 | T24: =T23 -> 357658 | U24: =SUM(T24-T23) -> 0 | V24: =IF(S24>0,U24/S24,0) -> 0 | X24: =X23 -> 12609 | Y24: =IF(R24-X24<=0,"ok","oil change") -> ok | Z24: =C24+K24+S24 -> 7 | AA24: =U24+M24+E24 -> 1611 | AB24: =V24+N24+F24 -> 230.14286 | AC24: =IF(Z24>0,AA24/Z24,0) -> 230.14286 | AD24: =ELEC!Q24 -> 4000 | AE24: =SUM(AD24/Z24) -> 571.42857 | AF24: =SUM(AE24/1600) -> 0.35714286 | AG24: =SUM(320*AF24) -> 114.28571 | AH24: =SUM(AC24-AG24) -> 115.85714 | AI24: =AD24*AJ24 -> 1029.5359 | AJ24: =305/1185 -> 0.25738397 | AK24: =IF(Z24>0,AI24/Z24,0) -> 147.07655
A25: =ELEC!C25 -> 44097 | B25: 9185 | C25: =B25-B24 -> 3 | D25: 239872 | E25: =SUM(D25-D24) -> 703 | F25: =IF(C25>0,E25/C25,0) -> 234.33333 | H25: =H24 -> 9298 | I25: =IF(B25-H25<=0,"ok","oil change") -> ok | J25: =J24 -> 10698 | K25: =J25-J24 -> 0 | L25: =L24 -> 238500 | M25: =SUM(L25-L24) -> 0 | N25: =IF(K25>0,M25/K25,0) -> 0 | P25: =P24 -> 10873 | Q25: =IF(J25-P25<=0,"ok","oil change") -> ok | R25: =R24 -> 11705 | S25: =R25-R24 -> 0 | T25: =T24 -> 357658 | U25: =SUM(T25-T24) -> 0 | V25: =IF(S25>0,U25/S25,0) -> 0 | X25: =X24 -> 12609 | Y25: =IF(R25-X25<=0,"ok","oil change") -> ok | Z25: =C25+K25+S25 -> 3 | AA25: =U25+M25+E25 -> 703 | AB25: =V25+N25+F25 -> 234.33333 | AC25: =IF(Z25>0,AA25/Z25,0) -> 234.33333 | AD25: =ELEC!Q25 -> 2000 | AE25: =SUM(AD25/Z25) -> 666.66667 | AF25: =SUM(AE25/1600) -> 0.41666667 | AG25: =SUM(320*AF25) -> 133.33333 | AH25: =SUM(AC25-AG25) -> 101 | AI25: =AD25*AJ25 -> 514.76793 | AJ25: =305/1185 -> 0.25738397 | AK25: =IF(Z25>0,AI25/Z25,0) -> 171.58931
A26: =ELEC!C26 -> 44098 | B26: 9188 | C26: =B26-B25 -> 3 | D26: 240538 | E26: =SUM(D26-D25) -> 666 | F26: =IF(C26>0,E26/C26,0) -> 222 | H26: =H25 -> 9298 | I26: =IF(B26-H26<=0,"ok","oil change") -> ok | J26: 10698 | K26: =J26-J25 -> 0 | L26: =L25 -> 238500 | M26: =SUM(L26-L25) -> 0 | N26: =IF(K26>0,M26/K26,0) -> 0 | P26: =P25 -> 10873 | Q26: =IF(J26-P26<=0,"ok","oil change") -> ok | R26: =R25 -> 11705 | S26: =R26-R25 -> 0 | T26: =T25 -> 357658 | U26: =SUM(T26-T25) -> 0 | V26: =IF(S26>0,U26/S26,0) -> 0 | X26: =X25 -> 12609 | Y26: =IF(R26-X26<=0,"ok","oil change") -> ok | Z26: =C26+K26+S26 -> 3 | AA26: =U26+M26+E26 -> 666 | AB26: =V26+N26+F26 -> 222 | AC26: =IF(Z26>0,AA26/Z26,0) -> 222 | AD26: =ELEC!Q26 -> 2000 | AE26: =SUM(AD26/Z26) -> 666.66667 | AF26: =SUM(AE26/1600) -> 0.41666667 | AG26: =SUM(320*AF26) -> 133.33333 | AH26: =SUM(AC26-AG26) -> 88.666667 | AI26: =AD26*AJ26 -> 514.76793 | AJ26: =305/1185 -> 0.25738397 | AK26: =IF(Z26>0,AI26/Z26,0) -> 171.58931
A27: =ELEC!C27 -> 44099 | B27: 9191 | C27: =B27-B26 -> 3 | D27: 241366 | E27: =SUM(D27-D26) -> 828 | F27: =IF(C27>0,E27/C27,0) -> 276 | H27: =H26 -> 9298 | I27: =IF(B27-H27<=0,"ok","oil change") -> ok | J27: =J26 -> 10698 | K27: =J27-J26 -> 0 | L27: =L26 -> 238500 | M27: =SUM(L27-L26) -> 0 | N27: =IF(K27>0,M27/K27,0) -> 0 | P27: =P26 -> 10873 | Q27: =IF(J27-P27<=0,"ok","oil change") -> ok | R27: =R26 -> 11705 | S27: =R27-R26 -> 0 | T27: =T26 -> 357658 | U27: =SUM(T27-T26) -> 0 | V27: =IF(S27>0,U27/S27,0) -> 0 | X27: =X26 -> 12609 | Y27: =IF(R27-X27<=0,"ok","oil change") -> ok | Z27: =C27+K27+S27 -> 3 | AA27: =U27+M27+E27 -> 828 | AB27: =V27+N27+F27 -> 276 | AC27: =IF(Z27>0,AA27/Z27,0) -> 276 | AD27: =ELEC!Q27 -> 1000 | AE27: =SUM(AD27/Z27) -> 333.33333 | AF27: =SUM(AE27/1600) -> 0.20833333 | AG27: =SUM(320*AF27) -> 66.666667 | AH27: =SUM(AC27-AG27) -> 209.33333 | AI27: =AD27*AJ27 -> 257.38397 | AJ27: =305/1185 -> 0.25738397 | AK27: =IF(Z27>0,AI27/Z27,0) -> 85.794655
A28: =ELEC!C28 -> 44100 | B28: 9195 | C28: =B28-B27 -> 4 | D28: 242160 | E28: =SUM(D28-D27) -> 794 | F28: =IF(C28>0,E28/C28,0) -> 198.5 | H28: =H27 -> 9298 | I28: =IF(B28-H28<=0,"ok","oil change") -> ok | J28: =J27 -> 10698 | K28: =J28-J27 -> 0 | L28: =L27 -> 238500 | M28: =SUM(L28-L27) -> 0 | N28: =IF(K28>0,M28/K28,0) -> 0 | P28: =P27 -> 10873 | Q28: =IF(J28-P28<=0,"ok","oil change") -> ok | R28: =R27 -> 11705 | S28: =R28-R27 -> 0 | T28: =T27 -> 357658 | U28: =SUM(T28-T27) -> 0 | V28: =IF(S28>0,U28/S28,0) -> 0 | X28: =X27 -> 12609 | Y28: =IF(R28-X28<=0,"ok","oil change") -> ok | Z28: =C28+K28+S28 -> 4 | AA28: =U28+M28+E28 -> 794 | AB28: =V28+N28+F28 -> 198.5 | AC28: =IF(Z28>0,AA28/Z28,0) -> 198.5 | AD28: =ELEC!Q28 -> 2000 | AE28: =SUM(AD28/Z28) -> 500 | AF28: =SUM(AE28/1600) -> 0.3125 | AG28: =SUM(320*AF28) -> 100 | AH28: =SUM(AC28-AG28) -> 98.5 | AI28: =AD28*AJ28 -> 514.76793 | AJ28: =305/1185 -> 0.25738397 | AK28: =IF(Z28>0,AI28/Z28,0) -> 128.69198
A29: =ELEC!C29 -> 44101 | B29: 9196 | C29: =B29-B28 -> 1 | D29: 242497 | E29: =SUM(D29-D28) -> 337 | F29: =IF(C29>0,E29/C29,0) -> 337 | H29: =H28 -> 9298 | I29: =IF(B29-H29<=0,"ok","oil change") -> ok | J29: 10698 | K29: =J29-J28 -> 0 | L29: =L28 -> 238500 | M29: =SUM(L29-L28) -> 0 | N29: =IF(K29>0,M29/K29,0) -> 0 | P29: =P28 -> 10873 | Q29: =IF(J29-P29<=0,"ok","oil change") -> ok | R29: 11705 | S29: =R29-R28 -> 0 | T29: =T28 -> 357658 | U29: =SUM(T29-T28) -> 0 | V29: =IF(S29>0,U29/S29,0) -> 0 | X29: =X28 -> 12609 | Y29: =IF(R29-X29<=0,"ok","oil change") -> ok | Z29: =C29+K29+S29 -> 1 | AA29: =U29+M29+E29 -> 337 | AB29: =V29+N29+F29 -> 337 | AC29: =IF(Z29>0,AA29/Z29,0) -> 337 | AD29: =ELEC!Q29 -> 900 | AE29: =SUM(AD29/Z29) -> 900 | AF29: =SUM(AE29/1600) -> 0.5625 | AG29: =SUM(320*AF29) -> 180 | AH29: =SUM(AC29-AG29) -> 157 | AI29: =AD29*AJ29 -> 231.64557 | AJ29: =305/1185 -> 0.25738397 | AK29: =IF(Z29>0,AI29/Z29,0) -> 231.64557
A30: =ELEC!C30 -> 44102 | B30: 9199 | C30: =B30-B29 -> 3 | D30: 242977 | E30: =SUM(D30-D29) -> 480 | F30: =IF(C30>0,E30/C30,0) -> 160 | H30: =H29 -> 9298 | I30: =IF(B30-H30<=0,"ok","oil change") -> ok | J30: =J29 -> 10698 | K30: =J30-J29 -> 0 | L30: =L29 -> 238500 | M30: =SUM(L30-L29) -> 0 | N30: =IF(K30>0,M30/K30,0) -> 0 | P30: =P29 -> 10873 | Q30: =IF(J30-P30<=0,"ok","oil change") -> ok | R30: =R29 -> 11705 | S30: =R30-R29 -> 0 | T30: =T29 -> 357658 | U30: =SUM(T30-T29) -> 0 | V30: =IF(S30>0,U30/S30,0) -> 0 | X30: =X29 -> 12609 | Y30: =IF(R30-X30<=0,"ok","oil change") -> ok | Z30: =C30+K30+S30 -> 3 | AA30: =U30+M30+E30 -> 480 | AB30: =V30+N30+F30 -> 160 | AC30: =IF(Z30>0,AA30/Z30,0) -> 160 | AD30: =ELEC!Q30 -> 1100 | AE30: =SUM(AD30/Z30) -> 366.66667 | AF30: =SUM(AE30/1600) -> 0.22916667 | AG30: =SUM(320*AF30) -> 73.333333 | AH30: =SUM(AC30-AG30) -> 86.666667 | AI30: =AD30*AJ30 -> 283.12236 | AJ30: =305/1185 -> 0.25738397 | AK30: =IF(Z30>0,AI30/Z30,0) -> 94.374121
A31: =ELEC!C31 -> 44103 | B31: 9202 | C31: =B31-B30 -> 3 | D31: 243559 | E31: =SUM(D31-D30) -> 582 | F31: =IF(C31>0,E31/C31,0) -> 194 | H31: =H30 -> 9298 | I31: =IF(B31-H31<=0,"ok","oil change") -> ok | J31: =J30 -> 10698 | K31: =J31-J30 -> 0 | L31: =L30 -> 238500 | M31: =SUM(L31-L30) -> 0 | N31: =IF(K31>0,M31/K31,0) -> 0 | P31: =P30 -> 10873 | Q31: =IF(J31-P31<=0,"ok","oil change") -> ok | R31: =R30 -> 11705 | S31: =R31-R30 -> 0 | T31: =T30 -> 357658 | U31: =SUM(T31-T30) -> 0 | V31: =IF(S31>0,U31/S31,0) -> 0 | X31: =X30 -> 12609 | Y31: =IF(R31-X31<=0,"ok","oil change") -> ok | Z31: =C31+K31+S31 -> 3 | AA31: =U31+M31+E31 -> 582 | AB31: =V31+N31+F31 -> 194 | AC31: =IF(Z31>0,AA31/Z31,0) -> 194 | AD31: =ELEC!Q31 -> 2000 | AE31: =SUM(AD31/Z31) -> 666.66667 | AF31: =SUM(AE31/1600) -> 0.41666667 | AG31: =SUM(320*AF31) -> 133.33333 | AH31: =SUM(AC31-AG31) -> 60.666667 | AI31: =AD31*AJ31 -> 514.76793 | AJ31: =305/1185 -> 0.25738397 | AK31: =IF(Z31>0,AI31/Z31,0) -> 171.58931
A32: =ELEC!C32 -> 44104 | B32: 9208 | C32: =B32-B31 -> 6 | D32: 244563 | E32: =SUM(D32-D31) -> 1004 | F32: =IF(C32>0,E32/C32,0) -> 167.33333 | H32: =H31 -> 9298 | I32: =IF(B32-H32<=0,"ok","oil change") -> ok | J32: =J31 -> 10698 | K32: =J32-J31 -> 0 | L32: =L31 -> 238500 | M32: =SUM(L32-L31) -> 0 | N32: =IF(K32>0,M32/K32,0) -> 0 | P32: =P31 -> 10873 | Q32: =IF(J32-P32<=0,"ok","oil change") -> ok | R32: =R31 -> 11705 | S32: =R32-R31 -> 0 | T32: =T31 -> 357658 | U32: =SUM(T32-T31) -> 0 | V32: =IF(S32>0,U32/S32,0) -> 0 | X32: =X31 -> 12609 | Y32: =IF(R32-X32<=0,"ok","oil change") -> ok | Z32: =C32+K32+S32 -> 6 | AA32: =U32+M32+E32 -> 1004 | AB32: =V32+N32+F32 -> 167.33333 | AC32: =IF(Z32>0,AA32/Z32,0) -> 167.33333 | AD32: =ELEC!Q32 -> 4000 | AE32: =SUM(AD32/Z32) -> 666.66667 | AF32: =SUM(AE32/1600) -> 0.41666667 | AG32: =SUM(320*AF32) -> 133.33333 | AH32: =SUM(AC32-AG32) -> 34 | AI32: =AD32*AJ32 -> 1029.5359 | AJ32: =305/1185 -> 0.25738397 | AK32: =IF(Z32>0,AI32/Z32,0) -> 171.58931
A33: =ELEC!#REF! -> #REF! | B33: =B32 -> 9208 | C33: =B33-B32 -> 0 | D33: =D32 -> 244563 | E33: =SUM(D33-D32) -> 0 | F33: =IF(C33>0,E33/C33,0) -> 0 | H33: =H32 -> 9298 | I33: =IF(B33-H33<=0,"ok","oil change") -> ok | J33: =J32 -> 10698 | K33: =J33-J32 -> 0 | L33: =L32 -> 238500 | M33: =SUM(L33-L32) -> 0 | N33: =IF(K33>0,M33/K33,0) -> 0 | P33: =P32 -> 10873 | Q33: =IF(J33-P33<=0,"ok","oil change") -> ok | R33: =R32 -> 11705 | S33: =R33-R32 -> 0 | T33: =T32 -> 357658 | U33: =SUM(T33-T32) -> 0 | V33: =IF(S33>0,U33/S33,0) -> 0 | X33: =X32 -> 12609 | Y33: =IF(R33-X33<=0,"ok","oil change") -> ok | Z33: =C33+K33+S33 -> 0 | AA33: =U33+M33+E33 -> 0 | AB33: =V33+N33+F33 -> 0 | AC33: =IF(Z33>0,AA33/Z33,0) -> 0 | AD33: =ELEC!#REF! -> #REF! | AE33: =SUM(AD33/Z33) -> #REF! | AF33: =SUM(AE33/1600) -> #REF! | AG33: =SUM(320*AF33) -> #REF! | AH33: =SUM(AC33-AG33) -> #REF! | AI33: =AD33*AJ33 -> #REF! | AJ33: =305/1185 -> 0.25738397 | AK33: =IF(Z33>0,AI33/Z33,0) -> 0
P34: =+O34/3 -> 0 | U34: =SUM(C35:S35) -> 151 | X34: 341 | Z34: =SUM(Z3:Z32) -> 151
C35: =SUM(C3:C32) -> 96 | K35: =SUM(K3:K32) -> 0 | S35: =SUM(S3:S32) -> 55

Sheet Sheet1
A1: TOTAL CH RH | B1: TOTAL CH cons KW | C1: TOTAL ELIC KW | D1: TOTAL EDL | E1: TOTAL GEN KW | F1: GEN HR | G1: WATER IN | H1: TOTAL CT | I1: TOTAL WATER | J1: Date
