Workbook

Sheet Total
A1: Site Name | B1: Day | C1: Month | D1: Year | E1: Total Electricity Kwh | F1: Electricity Tariff ($/Kwh) | G1: Total Fuel Oil (Liters) | H1: Fuel Oil $/Liter | I1: LPG (Kg) | J1: LPG $/Kg | K1: Water Utility Supply (m3) m3 | L1: Water Utility Supply (m3) $/m3 | M1: Irrigation Water (m3) m3 | N1: Irrigation water $/m3 | O1: Room Nights
A2: Beirut | B2: 1 | C2: 10 | D2: 2020 | E2: =ELEC!N3 -> 10203 | F2: =SUM('EDl log'!T4) -> 0.040557486 | G2: =-tanks!AW6 -> 1.8 | H2: =SUM(tanks!AV6) -> 0 | I2: =('B5'!AU5)*0.51 -> -15.3 | J2: ='B5'!AX5/0.51 -> 1.5686275 | K2: =WATER!I6 -> 0 | L2: =SUM(WATER!J6) -> 0 | M2: =WATER!Q6 -> 0 | N2: 0.6 | O2: =ELEC!B3 -> 0
A3: Beirut | B3: =B2+1 -> 2 | C3: 10 | D3: 2020 | E3: =ELEC!N4 -> 10041 | F3: =SUM('EDl log'!T5) -> 0.048724119 | G3: =-tanks!AW7 -> 232 | H3: =SUM(tanks!AV7) -> 0 | I3: =('B5'!AU6)*0.51 -> 0 | J3: ='B5'!AX6/0.51 -> 1.5686275 | K3: =WATER!I7 -> 90 | L3: =SUM(WATER!J7) -> 2.688172 | M3: =WATER!Q7 -> 0 | N3: 0.6 | O3: =ELEC!B4 -> 0
A4: Beirut | B4: =B3+1 -> 3 | C4: 10 | D4: 2020 | E4: =ELEC!N5 -> 8684 | F4: =SUM('EDl log'!T6) -> 0.045868585 | G4: =-tanks!AW8 -> 116 | H4: =SUM(tanks!AV8) -> 0 | I4: =('B5'!AU7)*0.51 -> 0 | J4: ='B5'!AX7/0.51 -> 1.5686275 | K4: =WATER!I8 -> 0 | L4: =SUM(WATER!J8) -> 0 | M4: =WATER!Q8 -> 0 | N4: 0.6 | O4: =ELEC!B5 -> 0
A5: Beirut | B5: =B4+1 -> 4 | C5: 10 | D5: 2020 | E5: =ELEC!N6 -> 7992 | F5: =SUM('EDl log'!T7) -> 0.043581194 | G5: =-tanks!AW9 -> 53 | H5: =SUM(tanks!AV9) -> 0 | I5: =('B5'!AU8)*0.51 -> 0 | J5: ='B5'!AX8/0.51 -> 1.5686275 | K5: =WATER!I9 -> 98 | L5: =SUM(WATER!J9) -> 2.4687294 | M5: =WATER!Q9 -> 0 | N5: 0.6 | O5: =ELEC!B6 -> 0
A6: Beirut | B6: =B5+1 -> 5 | C6: 10 | D6: 2020 | E6: =ELEC!N7 -> 9176 | F6: =SUM('EDl log'!T8) -> 0.043506357 | G6: =-tanks!AW10 -> 96 | H6: =SUM(tanks!AV10) -> 0 | I6: =('B5'!AU9)*0.51 -> 0 | J6: ='B5'!AX9/0.51 -> 1.5686275 | K6: =WATER!I10 -> 0 | L6: =SUM(WATER!J10) -> 0 | M6: =WATER!Q10 -> 0 | N6: 0.6 | O6: =ELEC!B7 -> 0
A7: Beirut | B7: =B6+1 -> 6 | C7: 10 | D7: 2020 | E7: =ELEC!N8 -> 0 | F7: =SUM('EDl log'!T9) -> 0 | G7: =-tanks!AW11 -> 0 | H7: =SUM(tanks!AV11) -> 0 | I7: =('B5'!AU10)*0.51 -> 0 | J7: ='B5'!AX10/0.51 -> 1.5686275 | K7: =WATER!I11 -> 0 | L7: =SUM(WATER!J11) -> 0 | M7: =WATER!Q11 -> 0 | N7: 0.6 | O7: =ELEC!B8 -> 0
A8: Beirut | B8: =B7+1 -> 7 | C8: 10 | D8: 2020 | E8: =ELEC!N9 -> 0 | F8: =SUM('EDl log'!T10) -> 0 | G8: =-tanks!AW12 -> 0 | H8: =SUM(tanks!AV12) -> 0 | I8: =('B5'!AU11)*0.51 -> 0 | J8: ='B5'!AX11/0.51 -> 1.5686275 | K8: =WATER!I12 -> 0 | L8: =SUM(WATER!J12) -> 0 | M8: =WATER!Q12 -> 0 | N8: 0.6 | O8: =ELEC!B9 -> 0
A9: Beirut | B9: =B8+1 -> 8 | C9: 10 | D9: 2020 | E9: =ELEC!N10 -> 0 | F9: =SUM('EDl log'!T11) -> 0 | G9: =-tanks!AW13 -> 0 | H9: =SUM(tanks!AV13) -> 0 | I9: =('B5'!AU12)*0.51 -> 0 | J9: ='B5'!AX12/0.51 -> 1.5686275 | K9: =WATER!I13 -> 0 | L9: =SUM(WATER!J13) -> 0 | M9: =WATER!Q13 -> 0 | N9: 0.6 | O9: =ELEC!B10 -> 0
A10: Beirut | B10: =B9+1 -> 9 | C10: 10 | D10: 2020 | E10: =ELEC!N11 -> 0 | F10: =SUM('EDl log'!T12) -> 0 | G10: =-tanks!AW14 -> 0 | H10: =SUM(tanks!AV14) -> 0 | I10: =('B5'!AU13)*0.51 -> 0 | J10: ='B5'!AX13/0.51 -> 1.5686275 | K10: =WATER!I14 -> 0 | L10: =SUM(WATER!J14) -> 0 | M10: =WATER!Q14 -> 0 | N10: 0.6 | O10: =ELEC!B11 -> 0
A11: Beirut | B11: =B10+1 -> 10 | C11: 10 | D11: 2020 | E11: =ELEC!N12 -> 0 | F11: =SUM('EDl log'!T13) -> 0 | G11: =-tanks!AW15 -> 0 | H11: =SUM(tanks!AV15) -> 0 | I11: =('B5'!AU14)*0.51 -> 0 | J11: ='B5'!AX14/0.51 -> 1.5686275 | K11: =WATER!I15 -> 0 | L11: =SUM(WATER!J15) -> 0 | M11: =WATER!Q15 -> 0 | N11: 0.6 | O11: =ELEC!B12 -> 0
A12: Beirut | B12: =B11+1 -> 11 | C12: 10 | D12: 2020 | E12: =ELEC!N13 -> 0 | F12: =SUM('EDl log'!T14) -> 0 | G12: =-tanks!AW16 -> 0 | H12: =SUM(tanks!AV16) -> 0 | I12: =('B5'!AU15)*0.51 -> 0 | J12: ='B5'!AX15/0.51 -> 1.5686275 | K12: =WATER!I16 -> 0 | L12: =SUM(WATER!J16) -> 0 | M12: =WATER!Q16 -> 0 | N12: 0.6 | O12: =ELEC!B13 -> 0
A13: Beirut | B13: =B12+1 -> 12 | C13: 10 | D13: 2020 | E13: =ELEC!N14 -> 0 | F13: =SUM('EDl log'!T15) -> 0 | G13: =-tanks!AW17 -> 0 | H13: =SUM(tanks!AV17) -> 0 | I13: =('B5'!AU16)*0.51 -> 0 | J13: ='B5'!AX16/0.51 -> 1.5686275 | K13: =WATER!I17 -> 0 | L13: =SUM(WATER!J17) -> 0 | M13: =WATER!Q17 -> 0 | N13: 0.6 | O13: =ELEC!B14 -> 0
A14: Beirut | B14: =B13+1 -> 13 | C14: 10 | D14: 2020 | E14: =ELEC!N15 -> 0 | F14: =SUM('EDl log'!T16) -> 0 | G14: =-tanks!AW18 -> 0 | H14: =SUM(tanks!AV18) -> 0 | I14: =('B5'!AU17)*0.51 -> 0 | J14: ='B5'!AX17/0.51 -> 1.5686275 | K14: =WATER!I18 -> 0 | L14: =SUM(WATER!J18) -> 0 | M14: =WATER!Q18 -> 0 | N14: 0.6 | O14: =ELEC!B15 -> 0
... A32: Beirut | B32: =B31+1 -> 31 | C32: 10 | D32: 2020 | E32: =ELEC!N33 -> 0 | F32: =SUM('EDl log'!T34) -> 0 | G32: =-tanks!AW36 -> 0 | H32: =SUM(tanks!AV36) -> 0 | I32: =('B5'!AU35)*0.51 -> 0 | J32: ='B5'!AX35/0.51 -> 1.5686275 | K32: =WATER!I36 -> 0 | L32: =SUM(WATER!J36) -> 0 | M32: =WATER!Q36 -> 0 | N32: 0.6 | O32: =ELEC!B33 -> 0

Sheet Submetering
A1: Site Name | B1: Day | C1: Month | D1: Year | E1: ATS1 Kwh | F1: ATS2 Kwh | G1: ATS3 Kwh | H1: ATS4 Kwh | I1: ATS5 Kwh | J1: Guest (m3) | K1: Kitchen & Laundry (m3) | L1: Room Nights
A2: Beirut | B2: 1 | C2: 10 | D2: 2020 | E2: =ELEC!M3 -> 4538 | F2: =ELEC!K3 -> 868 | G2: =ELEC!I3 -> 884 | H2: =ELEC!E3 -> 3070 | I2: =ELEC!G3 -> 843 | J2: =WATER!Y6 -> 0 | K2: =WATER!AJ6 -> 0 | L2: =ELEC!B3 -> 0
A3: Beirut | B3: =B2+1 -> 2 | C3: 10 | D3: 2020 | E3: =ELEC!M4 -> 4024 | F3: =ELEC!K4 -> 1146 | G3: =ELEC!I4 -> 898 | H3: =ELEC!E4 -> 3146 | I3: =ELEC!G4 -> 827 | J3: =WATER!Y7 -> 21 | K3: =WATER!AJ7 -> 13 | L3: =ELEC!B4 -> 0
A4: Beirut | B4: =B3+1 -> 3 | C4: 10 | D4: 2020 | E4: =ELEC!M5 -> 3390 | F4: =ELEC!K5 -> 994 | G4: =ELEC!I5 -> 802 | H4: =ELEC!E5 -> 2750 | I4: =ELEC!G5 -> 748 | J4: =WATER!Y8 -> 11 | K4: =WATER!AJ8 -> 25 | L4: =ELEC!B5 -> 0
A5: Beirut | B5: =B4+1 -> 4 | C5: 10 | D5: 2020 | E5: =ELEC!M6 -> 3224 | F5: =ELEC!K6 -> 968 | G5: =ELEC!I6 -> 744 | H5: =ELEC!E6 -> 2345 | I5: =ELEC!G6 -> 711 | J5: =WATER!Y9 -> 0 | K5: =WATER!AJ9 -> 0 | L5: =ELEC!B6 -> 0
A6: Beirut | B6: =B5+1 -> 5 | C6: 10 | D6: 2020 | E6: =ELEC!M7 -> 3524 | F6: =ELEC!K7 -> 1138 | G6: =ELEC!I7 -> 872 | H6: =ELEC!E7 -> 2839 | I6: =ELEC!G7 -> 803 | J6: =WATER!Y10 -> 47 | K6: =WATER!AJ10 -> 21 | L6: =ELEC!B7 -> 0
A7: Beirut | B7: =B6+1 -> 6 | C7: 10 | D7: 2020 | E7: =ELEC!M8 -> 0 | F7: =ELEC!K8 -> 0 | G7: =ELEC!I8 -> 0 | H7: =ELEC!E8 -> 0 | I7: =ELEC!G8 -> 0 | J7: =WATER!Y11 -> 0 | K7: =WATER!AJ11 -> 0 | L7: =ELEC!B8 -> 0
A8: Beirut | B8: =B7+1 -> 7 | C8: 10 | D8: 2020 | E8: =ELEC!M9 -> 0 | F8: =ELEC!K9 -> 0 | G8: =ELEC!I9 -> 0 | H8: =ELEC!E9 -> 0 | I8: =ELEC!G9 -> 0 | J8: =WATER!Y12 -> 0 | K8: =WATER!AJ12 -> 0 | L8: =ELEC!B9 -> 0
A9: Beirut | B9: =B8+1 -> 8 | C9: 10 | D9: 2020 | E9: =ELEC!M10 -> 0 | F9: =ELEC!K10 -> 0 | G9: =ELEC!I10 -> 0 | H9: =ELEC!E10 -> 0 | I9: =ELEC!G10 -> 0 | J9: =WATER!Y13 -> 0 | K9: =WATER!AJ13 -> 0 | L9: =ELEC!B10 -> 0
A10: Beirut | B10: =B9+1 -> 9 | C10: 10 | D10: 2020 | E10: =ELEC!M11 -> 0 | F10: =ELEC!K11 -> 0 | G10: =ELEC!I11 -> 0 | H10: =ELEC!E11 -> 0 | I10: =ELEC!G11 -> 0 | J10: =WATER!Y14 -> 0 | K10: =WATER!AJ14 -> 0 | L10: =ELEC!B11 -> 0
A11: Beirut | B11: =B10+1 -> 10 | C11: 10 | D11: 2020 | E11: =ELEC!M12 -> 0 | F11: =ELEC!K12 -> 0 | G11: =ELEC!I12 -> 0 | H11: =ELEC!E12 -> 0 | I11: =ELEC!G12 -> 0 | J11: =WATER!Y15 -> 0 | K11: =WATER!AJ15 -> 0 | L11: =ELEC!B12 -> 0
A12: Beirut | B12: =B11+1 -> 11 | C12: 10 | D12: 2020 | E12: =ELEC!M13 -> 0 | F12: =ELEC!K13 -> 0 | G12: =ELEC!I13 -> 0 | H12: =ELEC!E13 -> 0 | I12: =ELEC!G13 -> 0 | J12: =WATER!Y16 -> 0 | K12: =WATER!AJ16 -> 0 | L12: =ELEC!B13 -> 0
A13: Beirut | B13: =B12+1 -> 12 | C13: 10 | D13: 2020 | E13: =ELEC!M14 -> 0 | F13: =ELEC!K14 -> 0 | G13: =ELEC!I14 -> 0 | H13: =ELEC!E14 -> 0 | I13: =ELEC!G14 -> 0 | J13: =WATER!Y17 -> 0 | K13: =WATER!AJ17 -> 0 | L13: =ELEC!B14 -> 0
A14: Beirut | B14: =B13+1 -> 13 | C14: 10 | D14: 2020 | E14: =ELEC!M15 -> 0 | F14: =ELEC!K15 -> 0 | G14: =ELEC!I15 -> 0 | H14: =ELEC!E15 -> 0 | I14: =ELEC!G15 -> 0 | J14: =WATER!Y18 -> 0 | K14: =WATER!AJ18 -> 0 | L14: =ELEC!B15 -> 0
... A32: Beirut | B32: =B31+1 -> 31 | C32: 10 | D32: 2020 | E32: =ELEC!M33 -> 0 | F32: =ELEC!K33 -> 0 | G32: =ELEC!I33 -> 0 | H32: =ELEC!E33 -> 0 | I32: =ELEC!G33 -> 0 | J32: =WATER!Y36 -> 0 | K32: =WATER!AJ36 -> 0 | L32: =ELEC!B33 -> 0

Sheet ELEC
A1: OOC | B1: Room OCC | D1: MDB3 | E1: MDB3/day | F1: EMDB2 | G1: EMDB2/day | H1: EMDB1 | I1: EMDB1/day | J1: MDB2 | K1: mdb2/day | L1: MDB1 | M1: MDB1/Day | N1: Total KWH | O1: KWH/Rooc | P1: Gen MHW | Q1: Gen/Day KWH | R1: EDL KWH | S1: CH1 RH | T1: RH | U1: C1h1 power | V1: CH1 Con KWH | W1: CH2 RH | X1: RH | Y1: Ch2 power | Z1: CH2 Con KWH | AA1: CH3 RH | AB1: RH | AC1: Ch3 power | AD1: CH3 Con KWH | AE1: RH total | AF1: KWH total | AG1: AVG chiller KW/Hr
A2: =[1]ELEC!$A$33 -> 0 | B2: =[2]ELEC!B32 -> 0 | C2: 44104 | D2: =[2]ELEC!D32 -> 32287200 | E2: =[2]ELEC!E32 -> 3568 | F2: =[2]ELEC!F32 -> 3872020 | G2: =[2]ELEC!G32 -> 794 | H2: =[2]ELEC!H32 -> 17670874 | I2: =[2]ELEC!I32 -> 940 | J2: =[2]ELEC!J32 -> 28719638 | K2: =[2]ELEC!K32 -> 1056 | ... AL2: =[2]ELEC!AL32 -> 0
A3: ='General information '!F6 -> 0 | B3: =SUM(230*A3) -> 0 | C3: 44105 | D3: 32290270 | E3: =D3-D2 -> 3070 | F3: 3872863 | G3: =F3-F2 -> 843 | H3: 17671758 | I3: =H3-H2 -> 884 | J3: 28720506 | K3: =J3-J2 -> 868 | L3: 23693108 | M3: =L3-L2 -> 4538 | N3: =M3+K3+I3+G3+E3 -> 10203 | O3: =IF(B3>0,N3/B3,0) -> 0 | P3: 16348 | Q3: =(P3-P2)*1000 -> 2000 | R3: =+N3-Q3 -> 8203 | S3: 9718 | T3: =S3-S2 -> 10 | U3: 336003 | V3: =U3-U2 -> 2240 | W3: 32049 | X3: =W3-W2 -> 0 | Y3: 673052 | Z3: =Y3-Y2 -> 0 | AA3: =AA2 -> 35607 | AB3: =AA3-AA2 -> 0 | AC3: =AC2 -> 899488 | AD3: =AC3-AC2 -> 0 | AE3: =AB3+X3+T3 -> 10 | AF3: =V3+Z3+AD3 -> 2240 | AG3: =IF(AE3>0,AF3/AE3,0) -> 224
A4: ='General information '!F7 -> 0 | B4: =SUM(230*A4) -> 0 | C4: 44106 | D4: 32293416 | E4: =D4-D3 -> 3146 | F4: 3873690 | G4: =F4-F3 -> 827 | H4: 17672656 | I4: =H4-H3 -> 898 | J4: 28721652 | K4: =J4-J3 -> 1146 | L4: 23697132 | M4: =L4-L3 -> 4024 | N4: =M4+K4+I4+G4+E4 -> 10041 | O4: =IF(B4>0,N4/B4,0) -> 0 | P4: 16348 | Q4: =(P4-P3)*1000 -> 0 | R4: =N4-Q4 -> 10041 | S4: 9727 | T4: =S4-S3 -> 9 | U4: 337715 | V4: =U4-U3 -> 1712 | W4: =W3 -> 32049 | X4: =W4-W3 -> 0 | Y4: =Y3 -> 673052 | Z4: =Y4-Y3 -> 0 | AA4: =AA3 -> 35607 | AB4: =AA4-AA3 -> 0 | AC4: =AC3 -> 899488 | AD4: =AC4-AC3 -> 0 | AE4: =AB4+X4+T4 -> 9 | AF4: =V4+Z4+AD4 -> 1712 | AG4: =IF(AE4>0,AF4/AE4,0) -> 190.22222
A5: ='General information '!F8 -> 0 | B5: =SUM(230*A5) -> 0 | C5: 44107 | D5: 32296166 | E5: =D5-D4 -> 2750 | F5: 3874438 | G5: =F5-F4 -> 748 | H5: 17673458 | I5: =H5-H4 -> 802 | J5: 28722646 | K5: =J5-J4 -> 994 | L5: 23700522 | M5: =L5-L4 -> 3390 | N5: =M5+K5+I5+G5+E5 -> 8684 | O5: =IF(B5>0,N5/B5,0) -> 0 | P5: 16349 | Q5: =(P5-P4)*1000 -> 1000 | R5: =N5-Q5 -> 7684 | S5: 9735 | T5: =S5-S4 -> 8 | U5: 339671 | V5: =U5-U4 -> 1956 | W5: 32049 | X5: =W5-W4 -> 0 | Y5: =Y4 -> 673052 | Z5: =Y5-Y4 -> 0 | AA5: =AA4 -> 35607 | AB5: =AA5-AA4 -> 0 | AC5: =AC4 -> 899488 | AD5: =AC5-AC4 -> 0 | AE5: =AB5+X5+T5 -> 8 | AF5: =V5+Z5+AD5 -> 1956 | AG5: =IF(AE5>0,AF5/AE5,0) -> 244.5 | AI5: =R5-'EDl log'!B3 -> -462072
A6: ='General information '!F9 -> 0 | B6: =SUM(230*A6) -> 0 | C6: 44108 | D6: 32298511 | E6: =D6-D5 -> 2345 | F6: 3875149 | G6: =F6-F5 -> 711 | H6: 17674202 | I6: =H6-H5 -> 744 | J6: 28723614 | K6: =J6-J5 -> 968 | L6: 23703746 | M6: =L6-L5 -> 3224 | N6: =M6+K6+I6+G6+E6 -> 7992 | O6: =IF(B6>0,N6/B6,0) -> 0 | P6: 16351 | Q6: =(P6-P5)*1000 -> 2000 | R6: =N6-Q6 -> 5992 | S6: 9740 | T6: =S6-S5 -> 5 | U6: 340916 | V6: =U6-U5 -> 1245 | W6: =W5 -> 32049 | X6: =W6-W5 -> 0 | Y6: =Y5 -> 673052 | Z6: =Y6-Y5 -> 0 | AA6: =AA5 -> 35607 | AB6: =AA6-AA5 -> 0 | AC6: =AC5 -> 899488 | AD6: =AC6-AC5 -> 0 | AE6: =AB6+X6+T6 -> 5 | AF6: =V6+Z6+AD6 -> 1245 | AG6: =IF(AE6>0,AF6/AE6,0) -> 249 | AI6: =R6-'EDl log'!B4 -> -468150
A7: ='General information '!F10 -> 0 | B7: =SUM(230*A7) -> 0 | C7: 44109 | D7: 32301350 | E7: =D7-D6 -> 2839 | F7: 3875952 | G7: =F7-F6 -> 803 | H7: 17675074 | I7: =H7-H6 -> 872 | J7: 28724752 | K7: =J7-J6 -> 1138 | L7: 23707270 | M7: =L7-L6 -> 3524 | N7: =M7+K7+I7+G7+E7 -> 9176 | O7: =IF(B7>0,N7/B7,0) -> 0 | P7: 16353 | Q7: =(P7-P6)*1000 -> 2000 | R7: =N7-Q7 -> 7176 | S7: 9749 | T7: =S7-S6 -> 9 | U7: 342794 | V7: =U7-U6 -> 1878 | W7: 32049 | X7: =W7-W6 -> 0 | Y7: =Y6 -> 673052 | Z7: =Y7-Y6 -> 0 | AA7: =AA6 -> 35607 | AB7: =AA7-AA6 -> 0 | AC7: =AC6 -> 899488 | AD7: =AC7-AC6 -> 0 | AE7: =AB7+X7+T7 -> 9 | AF7: =V7+Z7+AD7 -> 1878 | AG7: =IF(AE7>0,AF7/AE7,0) -> 208.66667 | AI7: =R7-'EDl log'!B5 -> -472184
A8: ='General information '!F11 -> 0 | B8: =SUM(230*A8) -> 0 | C8: 44110 | D8: =D7 -> 32301350 | E8: =D8-D7 -> 0 | F8: =F7 -> 3875952 | G8: =F8-F7 -> 0 | H8: =H7 -> 17675074 | I8: =H8-H7 -> 0 | J8: =J7 -> 28724752 | K8: =J8-J7 -> 0 | L8: =L7 -> 23707270 | M8: =L8-L7 -> 0 | N8: =M8+K8+I8+G8+E8 -> 0 | O8: =IF(B8>0,N8/B8,0) -> 0 | P8: =P7 -> 16353 | Q8: =(P8-P7)*1000 -> 0 | R8: =N8-Q8 -> 0 | S8: =S7 -> 9749 | T8: =S8-S7 -> 0 | U8: =U7 -> 342794 | V8: =U8-U7 -> 0 | W8: =W7 -> 32049 | X8: =W8-W7 -> 0 | Y8: =Y7 -> 673052 | Z8: =Y8-Y7 -> 0 | AA8: =AA7 -> 35607 | AB8: =AA8-AA7 -> 0 | AC8: =AC7 -> 899488 | AD8: =AC8-AC7 -> 0 | AE8: =AB8+X8+T8 -> 0 | AF8: =V8+Z8+AD8 -> 0 | AG8: =IF(AE8>0,AF8/AE8,0) -> 0 | AI8: =R8-'EDl log'!B6 -> -483076
A9: ='General information '!F12 -> 0 | B9: =SUM(230*A9) -> 0 | C9: 44111 | D9: =D8 -> 32301350 | E9: =D9-D8 -> 0 | F9: =F8 -> 3875952 | G9: =F9-F8 -> 0 | H9: =H8 -> 17675074 | I9: =H9-H8 -> 0 | J9: =J8 -> 28724752 | K9: =J9-J8 -> 0 | L9: =L8 -> 23707270 | M9: =L9-L8 -> 0 | N9: =M9+K9+I9+G9+E9 -> 0 | O9: =IF(B9>0,N9/B9,0) -> 0 | P9: =P8 -> 16353 | Q9: =(P9-P8)*1000 -> 0 | R9: =N9-Q9 -> 0 | S9: =S8 -> 9749 | T9: =S9-S8 -> 0 | U9: =U8 -> 342794 | V9: =U9-U8 -> 0 | W9: =W8 -> 32049 | X9: =W9-W8 -> 0 | Y9: =Y8 -> 673052 | Z9: =Y9-Y8 -> 0 | AA9: =AA8 -> 35607 | AB9: =AA9-AA8 -> 0 | AC9: =AC8 -> 899488 | AD9: =AC9-AC8 -> 0 | AE9: =AB9+X9+T9 -> 0 | AF9: =V9+Z9+AD9 -> 0 | AG9: =IF(AE9>0,AF9/AE9,0) -> 0 | AI9: =R9-'EDl log'!B7 -> -486458
A10: ='General information '!F13 -> 0 | B10: =SUM(230*A10) -> 0 | C10: 44112 | D10: =D9 -> 32301350 | E10: =D10-D9 -> 0 | F10: =F9 -> 3875952 | G10: =F10-F9 -> 0 | H10: =H9 -> 17675074 | I10: =H10-H9 -> 0 | J10: =J9 -> 28724752 | K10: =J10-J9 -> 0 | L10: =L9 -> 23707270 | M10: =L10-L9 -> 0 | N10: =M10+K10+I10+G10+E10 -> 0 | O10: =IF(B10>0,N10/B10,0) -> 0 | P10: =P9 -> 16353 | Q10: =(P10-P9)*1000 -> 0 | R10: =N10-Q10 -> 0 | S10: =S9 -> 9749 | T10: =S10-S9 -> 0 | U10: =U9 -> 342794 | V10: =U10-U9 -> 0 | W10: 32049 | X10: =W10-W9 -> 0 | Y10: =Y9 -> 673052 | Z10: =Y10-Y9 -> 0 | AA10: =AA9 -> 35607 | AB10: =AA10-AA9 -> 0 | AC10: =AC9 -> 899488 | AD10: =AC10-AC9 -> 0 | AE10: =AB10+X10+T10 -> 0 | AF10: =V10+Z10+AD10 -> 0 | AG10: =IF(AE10>0,AF10/AE10,0) -> 0 | AI10: =R10-'EDl log'!B8 -> -490415
A11: ='General information '!F14 -> 0 | B11: =SUM(230*A11) -> 0 | C11: 44113 | D11: =D10 -> 32301350 | E11: =D11-D10 -> 0 | F11: =F10 -> 3875952 | G11: =F11-F10 -> 0 | H11: =H10 -> 17675074 | I11: =H11-H10 -> 0 | J11: =J10 -> 28724752 | K11: =J11-J10 -> 0 | L11: =L10 -> 23707270 | M11: =L11-L10 -> 0 | N11: =M11+K11+I11+G11+E11 -> 0 | O11: =IF(B11>0,N11/B11,0) -> 0 | P11: =P10 -> 16353 | Q11: =(P11-P10)*1000 -> 0 | R11: =N11-Q11 -> 0 | S11: =S10 -> 9749 | T11: =S11-S10 -> 0 | U11: =U10 -> 342794 | V11: =U11-U10 -> 0 | W11: =W10 -> 32049 | X11: =W11-W10 -> 0 | Y11: =Y10 -> 673052 | Z11: =Y11-Y10 -> 0 | AA11: =AA10 -> 35607 | AB11: =AA11-AA10 -> 0 | AC11: =AC10 -> 899488 | AD11: =AC11-AC10 -> 0 | AE11: =AB11+X11+T11 -> 0 | AF11: =V11+Z11+AD11 -> 0 | AG11: =IF(AE11>0,AF11/AE11,0) -> 0 | AI11: =R11-'EDl log'!B9 -> -490415
A12: ='General information '!F15 -> 0 | B12: =SUM(230*A12) -> 0 | C12: 44114 | D12: =D11 -> 32301350 | E12: =D12-D11 -> 0 | F12: =F11 -> 3875952 | G12: =F12-F11 -> 0 | H12: =H11 -> 17675074 | I12: =H12-H11 -> 0 | J12: =J11 -> 28724752 | K12: =J12-J11 -> 0 | L12: =L11 -> 23707270 | M12: =L12-L11 -> 0 | N12: =M12+K12+I12+G12+E12 -> 0 | O12: =IF(B12>0,N12/B12,0) -> 0 | P12: =P11 -> 16353 | Q12: =(P12-P11)*1000 -> 0 | R12: =N12-Q12 -> 0 | S12: =S11 -> 9749 | T12: =S12-S11 -> 0 | U12: =U11 -> 342794 | V12: =U12-U11 -> 0 | W12: =W11 -> 32049 | X12: =W12-W11 -> 0 | Y12: =Y11 -> 673052 | Z12: =Y12-Y11 -> 0 | AA12: =AA11 -> 35607 | AB12: =AA12-AA11 -> 0 | AC12: =AC11 -> 899488 | AD12: =AC12-AC11 -> 0 | AE12: =AB12+X12+T12 -> 0 | AF12: =V12+Z12+AD12 -> 0 | AG12: =IF(AE12>0,AF12/AE12,0) -> 0 | AI12: =R12-'EDl log'!B10 -> -490415
A13: ='General information '!F16 -> 0 | B13: =SUM(230*A13) -> 0 | C13: 44115 | D13: =D12 -> 32301350 | E13: =D13-D12 -> 0 | F13: =F12 -> 3875952 | G13: =F13-F12 -> 0 | H13: =H12 -> 17675074 | I13: =H13-H12 -> 0 | J13: =J12 -> 28724752 | K13: =J13-J12 -> 0 | L13: =L12 -> 23707270 | M13: =L13-L12 -> 0 | N13: =M13+K13+I13+G13+E13 -> 0 | O13: =IF(B13>0,N13/B13,0) -> 0 | P13: =P12 -> 16353 | Q13: =(P13-P12)*1000 -> 0 | R13: =N13-Q13 -> 0 | S13: =S12 -> 9749 | T13: =S13-S12 -> 0 | U13: =U12 -> 342794 | V13: =U13-U12 -> 0 | W13: =W12 -> 32049 | X13: =W13-W12 -> 0 | Y13: =Y12 -> 673052 | Z13: =Y13-Y12 -> 0 | AA13: =AA12 -> 35607 | AB13: =AA13-AA12 -> 0 | AC13: =AC12 -> 899488 | AD13: =AC13-AC12 -> 0 | AE13: =AB13+X13+T13 -> 0 | AF13: =V13+Z13+AD13 -> 0 | AG13: =IF(AE13>0,AF13/AE13,0) -> 0 | AI13: =R13-'EDl log'!B11 -> -490415
A14: ='General information '!F17 -> 0 | B14: =SUM(230*A14) -> 0 | C14: 44116 | D14: =D13 -> 32301350 | E14: =D14-D13 -> 0 | F14: =F13 -> 3875952 | G14: =F14-F13 -> 0 | H14: =H13 -> 17675074 | I14: =H14-H13 -> 0 | J14: =J13 -> 28724752 | K14: =J14-J13 -> 0 | L14: =L13 -> 23707270 | M14: =L14-L13 -> 0 | N14: =M14+K14+I14+G14+E14 -> 0 | O14: =IF(B14>0,N14/B14,0) -> 0 | P14: =P13 -> 16353 | Q14: =(P14-P13)*1000 -> 0 | R14: =N14-Q14 -> 0 | S14: =S13 -> 9749 | T14: =S14-S13 -> 0 | U14: =U13 -> 342794 | V14: =U14-U13 -> 0 | W14: =W13 -> 32049 | X14: =W14-W13 -> 0 | Y14: =Y13 -> 673052 | Z14: =Y14-Y13 -> 0 | AA14: =AA13 -> 35607 | AB14: =AA14-AA13 -> 0 | AC14: =AC13 -> 899488 | AD14: =AC14-AC13 -> 0 | AE14: =AB14+X14+T14 -> 0 | AF14: =V14+Z14+AD14 -> 0 | AG14: =IF(AE14>0,AF14/AE14,0) -> 0 | AI14: =R14-'EDl log'!B12 -> -490415
A15: ='General information '!F18 -> 0 | B15: =SUM(230*A15) -> 0 | C15: 44117 | D15: =D14 -> 32301350 | E15: =D15-D14 -> 0 | F15: =F14 -> 3875952 | G15: =F15-F14 -> 0 | H15: =H14 -> 17675074 | I15: =H15-H14 -> 0 | J15: =J14 -> 28724752 | K15: =J15-J14 -> 0 | L15: =L14 -> 23707270 | M15: =L15-L14 -> 0 | N15: =M15+K15+I15+G15+E15 -> 0 | O15: =IF(B15>0,N15/B15,0) -> 0 | P15: =P14 -> 16353 | Q15: =(P15-P14)*1000 -> 0 | R15: =N15-Q15 -> 0 | S15: =S14 -> 9749 | T15: =S15-S14 -> 0 | U15: =U14 -> 342794 | V15: =U15-U14 -> 0 | W15: =W14 -> 32049 | X15: =W15-W14 -> 0 | Y15: =Y14 -> 673052 | Z15: =Y15-Y14 -> 0 | AA15: =AA14 -> 35607 | AB15: =AA15-AA14 -> 0 | AC15: =AC14 -> 899488 | AD15: =AC15-AC14 -> 0 | AE15: =AB15+X15+T15 -> 0 | AF15: =V15+Z15+AD15 -> 0 | AG15: =IF(AE15>0,AF15/AE15,0) -> 0 | AI15: =R15-'EDl log'!B13 -> -490415
A16: ='General information '!F19 -> 0 | B16: =SUM(230*A16) -> 0 | C16: 44118 | D16: =D15 -> 32301350 | E16: =D16-D15 -> 0 | F16: =F15 -> 3875952 | G16: =F16-F15 -> 0 | H16: =H15 -> 17675074 | I16: =H16-H15 -> 0 | J16: =J15 -> 28724752 | K16: =J16-J15 -> 0 | L16: =L15 -> 23707270 | M16: =L16-L15 -> 0 | N16: =M16+K16+I16+G16+E16 -> 0 | O16: =IF(B16>0,N16/B16,0) -> 0 | P16: =P15 -> 16353 | Q16: =(P16-P15)*1000 -> 0 | R16: =N16-Q16 -> 0 | S16: =S15 -> 9749 | T16: =S16-S15 -> 0 | U16: =U15 -> 342794 | V16: =U16-U15 -> 0 | W16: =W15 -> 32049 | X16: =W16-W15 -> 0 | Y16: =Y15 -> 673052 | Z16: =Y16-Y15 -> 0 | AA16: =AA15 -> 35607 | AB16: =AA16-AA15 -> 0 | AC16: =AC15 -> 899488 | AD16: =AC16-AC15 -> 0 | AE16: =AB16+X16+T16 -> 0 | AF16: =V16+Z16+AD16 -> 0 | AG16: =IF(AE16>0,AF16/AE16,0) -> 0 | AI16: =R16-'EDl log'!B14 -> -490415
A17: ='General information '!F20 -> 0 | B17: =SUM(230*A17) -> 0 | C17: 44119 | D17: =D16 -> 32301350 | E17: =D17-D16 -> 0 | F17: =F16 -> 3875952 | G17: =F17-F16 -> 0 | H17: =H16 -> 17675074 | I17: =H17-H16 -> 0 | J17: =J16 -> 28724752 | K17: =J17-J16 -> 0 | L17: =L16 -> 23707270 | M17: =L17-L16 -> 0 | N17: =M17+K17+I17+G17+E17 -> 0 | O17: =IF(B17>0,N17/B17,0) -> 0 | P17: =P16 -> 16353 | Q17: =(P17-P16)*1000 -> 0 | R17: =N17-Q17 -> 0 | S17: =S16 -> 9749 | T17: =S17-S16 -> 0 | U17: =U16 -> 342794 | V17: =U17-U16 -> 0 | W17: =W16 -> 32049 | X17: =W17-W16 -> 0 | Y17: =Y16 -> 673052 | Z17: =Y17-Y16 -> 0 | AA17: =AA16 -> 35607 | AB17: =AA17-AA16 -> 0 | AC17: =AC16 -> 899488 | AD17: =AC17-AC16 -> 0 | AE17: =AB17+X17+T17 -> 0 | AF17: =V17+Z17+AD17 -> 0 | AG17: =IF(AE17>0,AF17/AE17,0) -> 0 | AI17: =R17-'EDl log'!B15 -> -490415
A18: ='General information '!F21 -> 0 | B18: =SUM(230*A18) -> 0 | C18: 44120 | D18: =D17 -> 32301350 | E18: =D18-D17 -> 0 | F18: =F17 -> 3875952 | G18: =F18-F17 -> 0 | H18: =H17 -> 17675074 | I18: =H18-H17 -> 0 | J18: =J17 -> 28724752 | K18: =J18-J17 -> 0 | L18: =L17 -> 23707270 | M18: =L18-L17 -> 0 | N18: =M18+K18+I18+G18+E18 -> 0 | O18: =IF(B18>0,N18/B18,0) -> 0 | P18: =P17 -> 16353 | Q18: =(P18-P17)*1000 -> 0 | R18: =N18-Q18 -> 0 | S18: =S17 -> 9749 | T18: =S18-S17 -> 0 | U18: =U17 -> 342794 | V18: =U18-U17 -> 0 | W18: =W17 -> 32049 | X18: =W18-W17 -> 0 | Y18: =Y17 -> 673052 | Z18: =Y18-Y17 -> 0 | AA18: =AA17 -> 35607 | AB18: =AA18-AA17 -> 0 | AC18: =AC17 -> 899488 | AD18: =AC18-AC17 -> 0 | AE18: =AB18+X18+T18 -> 0 | AF18: =V18+Z18+AD18 -> 0 | AG18: =IF(AE18>0,AF18/AE18,0) -> 0 | AI18: =R18-'EDl log'!B16 -> -490415
A19: ='General information '!F22 -> 0 | B19: =SUM(230*A19) -> 0 | C19: 44121 | D19: =D18 -> 32301350 | E19: =D19-D18 -> 0 | F19: =F18 -> 3875952 | G19: =F19-F18 -> 0 | H19: =H18 -> 17675074 | I19: =H19-H18 -> 0 | J19: =J18 -> 28724752 | K19: =J19-J18 -> 0 | L19: =L18 -> 23707270 | M19: =L19-L18 -> 0 | N19: =M19+K19+I19+G19+E19 -> 0 | O19: =IF(B19>0,N19/B19,0) -> 0 | P19: =P18 -> 16353 | Q19: =(P19-P18)*1000 -> 0 | R19: =N19-Q19 -> 0 | S19: =S18 -> 9749 | T19: =S19-S18 -> 0 | U19: =U18 -> 342794 | V19: =U19-U18 -> 0 | W19: =W18 -> 32049 | X19: =W19-W18 -> 0 | Y19: =Y18 -> 673052 | Z19: =Y19-Y18 -> 0 | AA19: =AA18 -> 35607 | AB19: =AA19-AA18 -> 0 | AC19: =AC18 -> 899488 | AD19: =AC19-AC18 -> 0 | AE19: =AB19+X19+T19 -> 0 | AF19: =V19+Z19+AD19 -> 0 | AG19: =IF(AE19>0,AF19/AE19,0) -> 0 | AI19: =R19-'EDl log'!B17 -> -490415
A20: ='General information '!F23 -> 0 | B20: =SUM(230*A20) -> 0 | C20: 44122 | D20: =D19 -> 32301350 | E20: =D20-D19 -> 0 | F20: =F19 -> 3875952 | G20: =F20-F19 -> 0 | H20: =H19 -> 17675074 | I20: =H20-H19 -> 0 | J20: =J19 -> 28724752 | K20: =J20-J19 -> 0 | L20: =L19 -> 23707270 | M20: =L20-L19 -> 0 | N20: =M20+K20+I20+G20+E20 -> 0 | O20: =IF(B20>0,N20/B20,0) -> 0 | P20: =P19 -> 16353 | Q20: =(P20-P19)*1000 -> 0 | R20: =N20-Q20 -> 0 | S20: =S19 -> 9749 | T20: =S20-S19 -> 0 | U20: =U19 -> 342794 | V20: =U20-U19 -> 0 | W20: =W19 -> 32049 | X20: =W20-W19 -> 0 | Y20: =Y19 -> 673052 | Z20: =Y20-Y19 -> 0 | AA20: =AA19 -> 35607 | AB20: =AA20-AA19 -> 0 | AC20: =AC19 -> 899488 | AD20: =AC20-AC19 -> 0 | AE20: =AB20+X20+T20 -> 0 | AF20: =V20+Z20+AD20 -> 0 | AG20: =IF(AE20>0,AF20/AE20,0) -> 0 | AI20: =R20-'EDl log'!B18 -> -490415
A21: ='General information '!F24 -> 0 | B21: =SUM(230*A21) -> 0 | C21: 44123 | D21: =D20 -> 32301350 | E21: =D21-D20 -> 0 | F21: =F20 -> 3875952 | G21: =F21-F20 -> 0 | H21: =H20 -> 17675074 | I21: =H21-H20 -> 0 | J21: =J20 -> 28724752 | K21: =J21-J20 -> 0 | L21: =L20 -> 23707270 | M21: =L21-L20 -> 0 | N21: =M21+K21+I21+G21+E21 -> 0 | O21: =IF(B21>0,N21/B21,0) -> 0 | P21: =P20 -> 16353 | Q21: =(P21-P20)*1000 -> 0 | R21: =N21-Q21 -> 0 | S21: =S20 -> 9749 | T21: =S21-S20 -> 0 | U21: =U20 -> 342794 | V21: =U21-U20 -> 0 | W21: =W20 -> 32049 | X21: =W21-W20 -> 0 | Y21: =Y20 -> 673052 | Z21: =Y21-Y20 -> 0 | AA21: =AA20 -> 35607 | AB21: =AA21-AA20 -> 0 | AC21: =AC20 -> 899488 | AD21: =AC21-AC20 -> 0 | AE21: =AB21+X21+T21 -> 0 | AF21: =V21+Z21+AD21 -> 0 | AG21: =IF(AE21>0,AF21/AE21,0) -> 0 | AI21: =R21-'EDl log'!B19 -> -490415
A22: ='General information '!F25 -> 0 | B22: =SUM(230*A22) -> 0 | C22: 44124 | D22: =D21 -> 32301350 | E22: =D22-D21 -> 0 | F22: =F21 -> 3875952 | G22: =F22-F21 -> 0 | H22: =H21 -> 17675074 | I22: =H22-H21 -> 0 | J22: =J21 -> 28724752 | K22: =J22-J21 -> 0 | L22: =L21 -> 23707270 | M22: =L22-L21 -> 0 | N22: =M22+K22+I22+G22+E22 -> 0 | O22: =IF(B22>0,N22/B22,0) -> 0 | P22: =P21 -> 16353 | Q22: =(P22-P21)*1000 -> 0 | R22: =N22-Q22 -> 0 | S22: =S21 -> 9749 | T22: =S22-S21 -> 0 | U22: =U21 -> 342794 | V22: =U22-U21 -> 0 | W22: =W21 -> 32049 | X22: =W22-W21 -> 0 | Y22: =Y21 -> 673052 | Z22: =Y22-Y21 -> 0 | AA22: =AA21 -> 35607 | AB22: =AA22-AA21 -> 0 | AC22: =AC21 -> 899488 | AD22: =AC22-AC21 -> 0 | AE22: =AB22+X22+T22 -> 0 | AF22: =V22+Z22+AD22 -> 0 | AG22: =IF(AE22>0,AF22/AE22,0) -> 0 | AI22: =R22-'EDl log'!B20 -> -490415
... A33: ='General information '!F36 -> 0 | B33: =SUM(230*A33) -> 0 | C33: 44135 | D33: =D32 -> 32301350 | E33: =D33-D32 -> 0 | F33: =F32 -> 3875952 | G33: =F33-F32 -> 0 | H33: =H32 -> 17675074 | I33: =H33-H32 -> 0 | J33: =J32 -> 28724752 | K33: =J33-J32 -> 0 | L33: =L32 -> 23707270 | M33: =L33-L32 -> 0 | N33: =M33+K33+I33+G33+E33 -> 0 | O33: =IF(B33>0,N33/B33,0) -> 0 | P33: =P32 -> 16353 | Q33: =(P33-P32)*1000 -> 0 | R33: =N33-Q33 -> 0 | S33: =S32 -> 9749 | T33: =S33-S32 -> 0 | U33: =U32 -> 342794 | V33: =U33-U32 -> 0 | W33: =W32 -> 32049 | X33: =W33-W32 -> 0 | Y33: =Y32 -> 673052 | Z33: =Y33-Y32 -> 0 | AA33: =AA32 -> 35607 | AB33: =AA33-AA32 -> 0 | AC33: =AC32 -> 899488 | AD33: =AC33-AC32 -> 0 | AE33: =AB33+X33+T33 -> 0 | AF33: =V33+Z33+AD33 -> 0 | AG33: =IF(AE33>0,AF33/AE33,0) -> 0 | AI33: =R33-'EDl log'!B31 -> -490415

Sheet B5
F1: Boiler A | J1: =J36 -> 1 | K1: Boiler B | P1: Boiler C | V1: Boiler | X1: SteamA | AC1: SteamB | AH1: Steam | AI1: Boiler & steam | AL1: Total Boiler Runing H | AM1: Total Steam Runing H | AN1: GAS1 % | AO1: GAS1/L | AP1: GAS2% | AQ1: Gas2/L | AR1: GAS3% | AS1: GAS3/L | AU1: Gas Cons | AV1: Delivery | AW1: Cost/L
B2: Level Tank Gen | C2: Level tank Boiler | D2: Daily Cons Bo. | E2: Boiler litter | F2: Boiler A | G2: Run Hr a | H2: Boiler A fuel | I2: Daily consumption | J2: AVG | K2: index Run H | L2: Run Hrb | M2: Boiler B Fuel | O2: Daily consumption | P2: Boiler C | S2: Run C | U2: Total RH | V2: Total Fuel | X2: SteamA | Y2: Run SA | Z2: Steam A Conter | AA2: Liters | AC2: SteamB | AD2: Run SteamB | AE2: Steam B Conter | AF2: SB Litters | AG2: Avg | AH2: Total Fuel | AI2: Total Fuel
S3: 0
A4: =ELEC!C2 -> 44104 | B4: =[2]B5!B34 -> 251 | C4: =[2]B5!C34 -> 257 | D4: =[2]B5!D34 -> 4 | E4: =[2]B5!E34 -> 33.52 | F4: =[2]B5!F34 -> 1648 | G4: =[2]B5!G34 -> 0 | H4: =[2]B5!H34 -> 357868 | I4: =[2]B5!I34 -> 0 | ... AO4: =[2]B5!AO34 -> 1860 | AP4: 52 | AQ4: =[2]B5!AQ34 -> 1530 | AR4: =[2]B5!AR34 -> 68 | AS4: =[2]B5!AS34 -> 2040 | AT4: =[2]B5!AT34 -> 5430 | AU4: =[2]B5!AU34 -> 0 | AV4: =[2]B5!AV34 -> 0 | AW4: =[2]B5!AW34 -> 0 | AX4: =[2]B5!AX34 -> 0.8
A5: =ELEC!C3 -> 44105 | B5: 249 | C5: 255 | D5: =C4-C5 -> 2 | E5: =D5*8.38 -> 16.76 | F5: =F4 -> 1648 | G5: =F5-F4 -> 0 | H5: =H4 -> 357868 | I5: =SUM(H5-H4) -> 0 | J5: 1 | K5: =K4 -> 2110 | L5: =K5-K4 -> 0 | M5: =M4 -> 154820 | N5: =M5-M4 -> 0 | O5: =O4 -> 211.875 | P5: =P4 -> 1839 | Q5: =Q4 -> 156094 | R5: =Q5-Q4 -> 0 | S5: =SUM(P5-P4) -> 0 | T5: =SUM(S5*$T$2) -> 0 | U5: =SUM(G5+L5+S5) -> 0 | V5: =R5+N5+I5:I5 -> 0 | W5: =SUM(V5/U5) -> #DIV/0! | X5: =X4 -> 2448 | Y5: =X5-X4 -> 0 | Z5: =Z4 -> 137506 | AA5: =Z5-Z4 -> 0 | AB5: =SUM(Y5*$AB$2) -> 0 | AC5: =AC4 -> 1933 | AD5: =AC5-AC4 -> 0 | AE5: 365212 | AF5: =AE5-AE4 -> 1.8 | AG5: =IF(AD5>0,AF5/AD5,0) -> 0 | AH5: =AF5+AA5 -> 1.8 | AI5: =SUM(AH5+V5) -> 1.8 | AJ5: =-tanks!AW6 -> 1.8 | AK5: =SUM(AJ5-AI5) -> 0 | AL5: =S5+L5+G5 -> 0 | AM5: =Y5+AD5 -> 0 | AN5: =AN4 -> 62 | AO5: =(AN5/100)*3000 -> 1860 | AP5: 52 | AQ5: =(AP5/100)*3000 -> 1560 | AR5: =AR4 -> 68 | AS5: =(AR5/100)*3000 -> 2040 | AT5: =SUM(AO5+AQ5+AS5) -> 5460 | AU5: =AT4-AT5+AV5 -> -30 | AW5: 0.1 | AX5: =IF(AV5>0,AW5,AX4) -> 0.8
A6: =ELEC!C4 -> 44106 | B6: 248 | C6: 254.5 | D6: =C5-C6 -> 0.5 | E6: =D6*8.38 -> 4.19 | F6: =F5 -> 1648 | G6: =F6-F5 -> 0 | H6: =H5 -> 357868 | I6: =SUM(H6-H5) -> 0 | J6: =IF(G6>0,I6/G6,0) -> 0 | K6: 2113 | L6: =K6-K5 -> 3 | M6: 155052 | N6: =M6-M5 -> 232 | O6: =O5 -> 211.875 | P6: =P5 -> 1839 | Q6: =Q5 -> 156094 | R6: =Q6-Q5 -> 0 | S6: =SUM(P6-P5) -> 0 | T6: =SUM(S6*$T$2) -> 0 | U6: =SUM(G6+L6+S6) -> 3 | V6: =R6+N6+I6:I6 -> 232 | W6: =SUM(V6/U6) -> 77.333333 | X6: =X5 -> 2448 | Y6: =X6-X5 -> 0 | Z6: =Z5 -> 137506 | AA6: =Z6-Z5 -> 0 | AB6: =SUM(Y6*$AB$2) -> 0 | AC6: =AC5 -> 1933 | AD6: =AC6-AC5 -> 0 | AE6: =AE5 -> 365212 | AF6: =AE6-AE5 -> 0 | AG6: =IF(AD6>0,AF6/AD6,0) -> 0 | AH6: =AF6+AA6 -> 0 | AI6: =SUM(AH6+V6) -> 232 | AJ6: =-tanks!AW7 -> 232 | AK6: =SUM(AJ6-AI6) -> 0 | AL6: =S6+L6+G6 -> 3 | AM6: =Y6+AD6 -> 0 | AN6: 62 | AO6: =(AN6/100)*3000 -> 1860 | AP6: 52 | AQ6: =(AP6/100)*3000 -> 1560 | AR6: =AR5 -> 68 | AS6: =(AR6/100)*3000 -> 2040 | AT6: =SUM(AO6+AQ6+AS6) -> 5460 | AU6: =AT5-AT6+AV6 -> 0 | AX6: =IF(AV6>0,AW6,AX5) -> 0.8
A7: =ELEC!C5 -> 44107 | B7: 246.5 | C7: 251.2 | D7: =C6-C7 -> 3.3 | E7: =D7*8.38 -> 27.654 | F7: =F6 -> 1648 | G7: =F7-F6 -> 0 | H7: =H6 -> 357868 | I7: =SUM(H7-H6) -> 0 | J7: =IF(G7>0,I7/G7,0) -> 0 | K7: 2114 | L7: =K7-K6 -> 1 | M7: 155125 | N7: =M7-M6 -> 73 | O7: =O6 -> 211.875 | P7: 1839 | Q7: 156137 | R7: =Q7-Q6 -> 43 | S7: =SUM(P7-P6) -> 0 | T7: =SUM(S7*$T$2) -> 0 | U7: =SUM(G7+L7+S7) -> 1 | V7: =R7+N7+I7:I7 -> 116 | W7: =SUM(V7/U7) -> 116 | X7: =X6 -> 2448 | Y7: =X7-X6 -> 0 | Z7: =Z6 -> 137506 | AA7: =Z7-Z6 -> 0 | AB7: =SUM(Y7*$AB$2) -> 0 | AC7: =AC6 -> 1933 | AD7: =AC7-AC6 -> 0 | AE7: =AE6 -> 365212 | AF7: =AE7-AE6 -> 0 | AG7: =IF(AD7>0,AF7/AD7,0) -> 0 | AH7: =AF7+AA7 -> 0 | AI7: =SUM(AH7+V7) -> 116 | AJ7: =-tanks!AW8 -> 116 | AK7: =SUM(AJ7-AI7) -> 0 | AL7: =S7+L7+G7 -> 1 | AM7: =Y7+AD7 -> 0 | AN7: =AN6 -> 62 | AO7: =(AN7/100)*3000 -> 1860 | AP7: =AP6 -> 52 | AQ7: =(AP7/100)*3000 -> 1560 | AR7: =AR6 -> 68 | AS7: =(AR7/100)*3000 -> 2040 | AT7: =SUM(AO7+AQ7+AS7) -> 5460 | AU7: =AT6-AT7+AV7 -> 0 | AX7: =IF(AV7>0,AW7,AX6) -> 0.8
A8: =ELEC!C6 -> 44108 | B8: 244 | C8: 249 | D8: =C7-C8 -> 2.2 | E8: =D8*8.38 -> 18.436 | F8: =F7 -> 1648 | G8: =F8-F7 -> 0 | H8: =H7 -> 357868 | I8: =SUM(H8-H7) -> 0 | J8: =IF(G8>0,I8/G8,0) -> 0 | K8: 2114 | L8: =K8-K7 -> 0 | M8: 155125 | N8: =M8-M7 -> 0 | O8: =O7 -> 211.875 | P8: 1840 | Q8: 156190 | R8: =Q8-Q7 -> 53 | S8: =SUM(P8-P7) -> 1 | T8: =SUM(S8*$T$2) -> 0 | U8: =SUM(G8+L8+S8) -> 1 | V8: =R8+N8+I8:I8 -> 53 | W8: =SUM(V8/U8) -> 53 | X8: 2448 | Y8: =X8-X7 -> 0 | Z8: =Z7 -> 137506 | AA8: =Z8-Z7 -> 0 | AB8: =SUM(Y8*$AB$2) -> 0 | AC8: =AC7 -> 1933 | AD8: =AC8-AC7 -> 0 | AE8: =AE7 -> 365212 | AF8: =AE8-AE7 -> 0 | AG8: =IF(AD8>0,AF8/AD8,0) -> 0 | AH8: =AF8+AA8 -> 0 | AI8: =SUM(AH8+V8) -> 53 | AJ8: =-tanks!AW9 -> 53 | AK8: =SUM(AJ8-AI8) -> 0 | AL8: =S8+L8+G8 -> 1 | AM8: =Y8+AD8 -> 0 | AN8: =AN7 -> 62 | AO8: =(AN8/100)*3000 -> 1860 | AP8: =AP7 -> 52 | AQ8: =(AP8/100)*3000 -> 1560 | AR8: =AR7 -> 68 | AS8: =(AR8/100)*3000 -> 2040 | AT8: =SUM(AO8+AQ8+AS8) -> 5460 | AU8: =AT7-AT8+AV8 -> 0 | AX8: =IF(AV8>0,AW8,AX7) -> 0.8
A9: =ELEC!C7 -> 44109 | B9: 242 | C9: 247.3 | D9: =C8-C9 -> 1.7 | E9: =D9*8.38 -> 14.246 | F9: =F8 -> 1648 | G9: =F9-F8 -> 0 | H9: =H8 -> 357868 | I9: =SUM(H9-H8) -> 0 | J9: =IF(G9>0,I9/G9,0) -> 0 | K9: 2115 | L9: =K9-K8 -> 1 | M9: 155221 | N9: =M9-M8 -> 96 | O9: =O8 -> 211.875 | P9: =P8 -> 1840 | Q9: =Q8 -> 156190 | R9: =Q9-Q8 -> 0 | S9: =SUM(P9-P8) -> 0 | T9: =SUM(S9*$T$2) -> 0 | U9: =SUM(G9+L9+S9) -> 1 | V9: =R9+N9+I9:I9 -> 96 | W9: =SUM(V9/U9) -> 96 | X9: =X8 -> 2448 | Y9: =X9-X8 -> 0 | Z9: =Z8 -> 137506 | AA9: =Z9-Z8 -> 0 | AB9: =SUM(Y9*$AB$2) -> 0 | AC9: =AC8 -> 1933 | AD9: =AC9-AC8 -> 0 | AE9: =AE8 -> 365212 | AF9: =AE9-AE8 -> 0 | AG9: =IF(AD9>0,AF9/AD9,0) -> 0 | AH9: =AF9+AA9 -> 0 | AI9: =SUM(AH9+V9) -> 96 | AJ9: =-tanks!AW10 -> 96 | AK9: =SUM(AJ9-AI9) -> 0 | AL9: =S9+L9+G9 -> 1 | AM9: =Y9+AD9 -> 0 | AN9: =AN8 -> 62 | AO9: =(AN9/100)*3000 -> 1860 | AP9: =AP8 -> 52 | AQ9: =(AP9/100)*3000 -> 1560 | AR9: =AR8 -> 68 | AS9: =(AR9/100)*3000 -> 2040 | AT9: =SUM(AO9+AQ9+AS9) -> 5460 | AU9: =AT8-AT9+AV9 -> 0 | AX9: =IF(AV9>0,AW9,AX8) -> 0.8
A10: =ELEC!C8 -> 44110 | B10: =B9 -> 242 | C10: =C9 -> 247.3 | D10: =C9-C10 -> 0 | E10: =D10*8.38 -> 0 | F10: =F9 -> 1648 | G10: =F10-F9 -> 0 | H10: =H9 -> 357868 | I10: =SUM(H10-H9) -> 0 | J10: =IF(G10>0,I10/G10,0) -> 0 | K10: =K9 -> 2115 | L10: =K10-K9 -> 0 | M10: =M9 -> 155221 | N10: =M10-M9 -> 0 | O10: =O9 -> 211.875 | P10: =P9 -> 1840 | Q10: =Q9 -> 156190 | R10: =Q10-Q9 -> 0 | S10: =SUM(P10-P9) -> 0 | T10: =SUM(S10*$T$2) -> 0 | U10: =SUM(G10+L10+S10) -> 0 | V10: =R10+N10+I10:I10 -> 0 | W10: =SUM(V10/U10) -> #DIV/0! | X10: =X9 -> 2448 | Y10: =X10-X9 -> 0 | Z10: =Z9 -> 137506 | AA10: =Z10-Z9 -> 0 | AB10: =SUM(Y10*$AB$2) -> 0 | AC10: =AC9 -> 1933 | AD10: =AC10-AC9 -> 0 | AE10: =AE9 -> 365212 | AF10: =AE10-AE9 -> 0 | AG10: =IF(AD10>0,AF10/AD10,0) -> 0 | AH10: =AF10+AA10 -> 0 | AI10: =SUM(AH10+V10) -> 0 | AJ10: =-tanks!AW11 -> 0 | AK10: =SUM(AJ10-AI10) -> 0 | AL10: =S10+L10+G10 -> 0 | AM10: =Y10+AD10 -> 0 | AN10: =AN9 -> 62 | AO10: =(AN10/100)*3000 -> 1860 | AP10: =AP9 -> 52 | AQ10: =(AP10/100)*3000 -> 1560 | AR10: =AR9 -> 68 | AS10: =(AR10/100)*3000 -> 2040 | AT10: =SUM(AO10+AQ10+AS10) -> 5460 | AU10: =AT9-AT10+AV10 -> 0 | AX10: =IF(AV10>0,AW10,AX9) -> 0.8
A11: =ELEC!C9 -> 44111 | B11: =B10 -> 242 | C11: =C10 -> 247.3 | D11: =C10-C11 -> 0 | E11: =D11*8.38 -> 0 | F11: =F10 -> 1648 | G11: =F11-F10 -> 0 | H11: =H10 -> 357868 | I11: =SUM(H11-H10) -> 0 | J11: =IF(G11>0,I11/G11,0) -> 0 | K11: =K10 -> 2115 | L11: =K11-K10 -> 0 | M11: =M10 -> 155221 | N11: =M11-M10 -> 0 | O11: =O10 -> 211.875 | P11: =P10 -> 1840 | Q11: =Q10 -> 156190 | R11: =Q11-Q10 -> 0 | S11: =SUM(P11-P10) -> 0 | T11: =SUM(S11*$T$2) -> 0 | U11: =SUM(G11+L11+S11) -> 0 | V11: =R11+N11+I11:I11 -> 0 | W11: =SUM(V11/U11) -> #DIV/0! | X11: =X10 -> 2448 | Y11: =X11-X10 -> 0 | Z11: =Z10 -> 137506 | AA11: =Z11-Z10 -> 0 | AB11: =SUM(Y11*$AB$2) -> 0 | AC11: =AC10 -> 1933 | AD11: =AC11-AC10 -> 0 | AE11: =AE10 -> 365212 | AF11: =AE11-AE10 -> 0 | AG11: =IF(AD11>0,AF11/AD11,0) -> 0 | AH11: =AF11+AA11 -> 0 | AI11: =SUM(AH11+V11) -> 0 | AJ11: =-tanks!AW12 -> 0 | AK11: =SUM(AJ11-AI11) -> 0 | AL11: =S11+L11+G11 -> 0 | AM11: =Y11+AD11 -> 0 | AN11: =AN10 -> 62 | AO11: =(AN11/100)*3000 -> 1860 | AP11: =AP10 -> 52 | AQ11: =(AP11/100)*3000 -> 1560 | AR11: =AR10 -> 68 | AS11: =(AR11/100)*3000 -> 2040 | AT11: =SUM(AO11+AQ11+AS11) -> 5460 | AU11: =AT10-AT11+AV11 -> 0 | AX11: =IF(AV11>0,AW11,AX10) -> 0.8
A12: =ELEC!C10 -> 44112 | B12: =B11 -> 242 | C12: =C11 -> 247.3 | D12: =C11-C12 -> 0 | E12: =D12*8.38 -> 0 | F12: =F11 -> 1648 | G12: =F12-F11 -> 0 | H12: =H11 -> 357868 | I12: =SUM(H12-H11) -> 0 | J12: =IF(G12>0,I12/G12,0) -> 0 | K12: =K11 -> 2115 | L12: =K12-K11 -> 0 | M12: =M11 -> 155221 | N12: =M12-M11 -> 0 | O12: =O11 -> 211.875 | P12: =P11 -> 1840 | Q12: =Q11 -> 156190 | R12: =Q12-Q11 -> 0 | S12: =SUM(P12-P11) -> 0 | T12: =SUM(S12*$T$2) -> 0 | U12: =SUM(G12+L12+S12) -> 0 | V12: =R12+N12+I12:I12 -> 0 | W12: =SUM(V12/U12) -> #DIV/0! | X12: =X11 -> 2448 | Y12: =X12-X11 -> 0 | Z12: =Z11 -> 137506 | AA12: =Z12-Z11 -> 0 | AB12: =SUM(Y12*$AB$2) -> 0 | AC12: =AC11 -> 1933 | AD12: =AC12-AC11 -> 0 | AE12: =AE11 -> 365212 | AF12: =AE12-AE11 -> 0 | AG12: =IF(AD12>0,AF12/AD12,0) -> 0 | AH12: =AF12+AA12 -> 0 | AI12: =SUM(AH12+V12) -> 0 | AJ12: =-tanks!AW13 -> 0 | AK12: =SUM(AJ12-AI12) -> 0 | AL12: =S12+L12+G12 -> 0 | AM12: =Y12+AD12 -> 0 | AN12: =AN11 -> 62 | AO12: =(AN12/100)*3000 -> 1860 | AP12: =AP11 -> 52 | AQ12: =(AP12/100)*3000 -> 1560 | AR12: =AR11 -> 68 | AS12: =(AR12/100)*3000 -> 2040 | AT12: =SUM(AO12+AQ12+AS12) -> 5460 | AU12: =AT11-AT12+AV12 -> 0 | AX12: =IF(AV12>0,AW12,AX11) -> 0.8
A13: =ELEC!C11 -> 44113 | B13: =B12 -> 242 | C13: =C12 -> 247.3 | D13: =C12-C13 -> 0 | E13: =D13*8.38 -> 0 | F13: =F12 -> 1648 | G13: =F13-F12 -> 0 | H13: =H12 -> 357868 | I13: =SUM(H13-H12) -> 0 | J13: =IF(G13>0,I13/G13,0) -> 0 | K13: =K12 -> 2115 | L13: =K13-K12 -> 0 | M13: =M12 -> 155221 | N13: =M13-M12 -> 0 | O13: =O12 -> 211.875 | P13: =P12 -> 1840 | Q13: =Q12 -> 156190 | R13: =Q13-Q12 -> 0 | S13: =SUM(P13-P12) -> 0 | T13: =SUM(S13*$T$2) -> 0 | U13: =SUM(G13+L13+S13) -> 0 | V13: =R13+N13+I13:I13 -> 0 | W13: =SUM(V13/U13) -> #DIV/0! | X13: =X12 -> 2448 | Y13: =X13-X12 -> 0 | Z13: =Z12 -> 137506 | AA13: =Z13-Z12 -> 0 | AB13: =SUM(Y13*$AB$2) -> 0 | AC13: =AC12 -> 1933 | AD13: =AC13-AC12 -> 0 | AE13: =AE12 -> 365212 | AF13: =AE13-AE12 -> 0 | AG13: =IF(AD13>0,AF13/AD13,0) -> 0 | AH13: =AF13+AA13 -> 0 | AI13: =SUM(AH13+V13) -> 0 | AJ13: =-tanks!AW14 -> 0 | AK13: =SUM(AJ13-AI13) -> 0 | AL13: =S13+L13+G13 -> 0 | AM13: =Y13+AD13 -> 0 | AN13: =AN12 -> 62 | AO13: =(AN13/100)*3000 -> 1860 | AP13: =AP12 -> 52 | AQ13: =(AP13/100)*3000 -> 1560 | AR13: =AR12 -> 68 | AS13: =(AR13/100)*3000 -> 2040 | AT13: =SUM(AO13+AQ13+AS13) -> 5460 | AU13: =AT12-AT13+AV13 -> 0 | AX13: =IF(AV13>0,AW13,AX12) -> 0.8
A14: =ELEC!C12 -> 44114 | B14: =B13 -> 242 | C14: =C13 -> 247.3 | D14: =C13-C14 -> 0 | E14: =D14*8.38 -> 0 | F14: =F13 -> 1648 | G14: =F14-F13 -> 0 | H14: =H13 -> 357868 | I14: =SUM(H14-H13) -> 0 | J14: =IF(G14>0,I14/G14,0) -> 0 | K14: =K13 -> 2115 | L14: =K14-K13 -> 0 | M14: =M13 -> 155221 | N14: =M14-M13 -> 0 | O14: =O13 -> 211.875 | P14: =P13 -> 1840 | Q14: =Q13 -> 156190 | R14: =Q14-Q13 -> 0 | S14: =SUM(P14-P13) -> 0 | T14: =SUM(S14*$T$2) -> 0 | U14: =SUM(G14+L14+S14) -> 0 | V14: =R14+N14+I14:I14 -> 0 | W14: =SUM(V14/U14) -> #DIV/0! | X14: =X13 -> 2448 | Y14: =X14-X13 -> 0 | Z14: =Z13 -> 137506 | AA14: =Z14-Z13 -> 0 | AB14: =SUM(Y14*$AB$2) -> 0 | AC14: =AC13 -> 1933 | AD14: =AC14-AC13 -> 0 | AE14: =AE13 -> 365212 | AF14: =AE14-AE13 -> 0 | AG14: =IF(AD14>0,AF14/AD14,0) -> 0 | AH14: =AF14+AA14 -> 0 | AI14: =SUM(AH14+V14) -> 0 | AJ14: =-tanks!AW15 -> 0 | AK14: =SUM(AJ14-AI14) -> 0 | AL14: =S14+L14+G14 -> 0 | AM14: =Y14+AD14 -> 0 | AN14: =AN13 -> 62 | AO14: =(AN14/100)*3000 -> 1860 | AP14: =AP13 -> 52 | AQ14: =(AP14/100)*3000 -> 1560 | AR14: =AR13 -> 68 | AS14: =(AR14/100)*3000 -> 2040 | AT14: =SUM(AO14+AQ14+AS14) -> 5460 | AU14: =AT13-AT14+AV14 -> 0 | AX14: =IF(AV14>0,AW14,AX13) -> 0.8
A15: =ELEC!C13 -> 44115 | B15: =B14 -> 242 | C15: =C14 -> 247.3 | D15: =C14-C15 -> 0 | E15: =D15*8.38 -> 0 | F15: =F14 -> 1648 | G15: =F15-F14 -> 0 | H15: =H14 -> 357868 | I15: =SUM(H15-H14) -> 0 | J15: =IF(G15>0,I15/G15,0) -> 0 | K15: =K14 -> 2115 | L15: =K15-K14 -> 0 | M15: =M14 -> 155221 | N15: =M15-M14 -> 0 | O15: =O14 -> 211.875 | P15: =P14 -> 1840 | Q15: =Q14 -> 156190 | R15: =Q15-Q14 -> 0 | S15: =SUM(P15-P14) -> 0 | T15: =SUM(S15*$T$2) -> 0 | U15: =SUM(G15+L15+S15) -> 0 | V15: =R15+N15+I15:I15 -> 0 | W15: =SUM(V15/U15) -> #DIV/0! | X15: =X14 -> 2448 | Y15: =X15-X14 -> 0 | Z15: =Z14 -> 137506 | AA15: =Z15-Z14 -> 0 | AB15: =SUM(Y15*$AB$2) -> 0 | AC15: =AC14 -> 1933 | AD15: =AC15-AC14 -> 0 | AE15: =AE14 -> 365212 | AF15: =AE15-AE14 -> 0 | AG15: =IF(AD15>0,AF15/AD15,0) -> 0 | AH15: =AF15+AA15 -> 0 | AI15: =SUM(AH15+V15) -> 0 | AJ15: =-tanks!AW16 -> 0 | AK15: =SUM(AJ15-AI15) -> 0 | AL15: =S15+L15+G15 -> 0 | AM15: =Y15+AD15 -> 0 | AN15: =AN14 -> 62 | AO15: =(AN15/100)*3000 -> 1860 | AP15: =AP14 -> 52 | AQ15: =(AP15/100)*3000 -> 1560 | AR15: =AR14 -> 68 | AS15: =(AR15/100)*3000 -> 2040 | AT15: =SUM(AO15+AQ15+AS15) -> 5460 | AU15: =AT14-AT15+AV15 -> 0 | AX15: =IF(AV15>0,AW15,AX14) -> 0.8
A16: =ELEC!C14 -> 44116 | B16: =B15 -> 242 | C16: =C15 -> 247.3 | D16: =C15-C16 -> 0 | E16: =D16*8.38 -> 0 | F16: =F15 -> 1648 | G16: =F16-F15 -> 0 | H16: =H15 -> 357868 | I16: =SUM(H16-H15) -> 0 | J16: =IF(G16>0,I16/G16,0) -> 0 | K16: =K15 -> 2115 | L16: =K16-K15 -> 0 | M16: =M15 -> 155221 | N16: =M16-M15 -> 0 | O16: =O15 -> 211.875 | P16: =P15 -> 1840 | Q16: =Q15 -> 156190 | R16: =Q16-Q15 -> 0 | S16: =SUM(P16-P15) -> 0 | T16: =SUM(S16*$T$2) -> 0 | U16: =SUM(G16+L16+S16) -> 0 | V16: =R16+N16+I16:I16 -> 0 | W16: =SUM(V16/U16) -> #DIV/0! | X16: =X15 -> 2448 | Y16: =X16-X15 -> 0 | Z16: =Z15 -> 137506 | AA16: =Z16-Z15 -> 0 | AB16: =SUM(Y16*$AB$2) -> 0 | AC16: =AC15 -> 1933 | AD16: =AC16-AC15 -> 0 | AE16: =AE15 -> 365212 | AF16: =AE16-AE15 -> 0 | AG16: =IF(AD16>0,AF16/AD16,0) -> 0 | AH16: =AF16+AA16 -> 0 | AI16: =SUM(AH16+V16) -> 0 | AJ16: =-tanks!AW17 -> 0 | AK16: =SUM(AJ16-AI16) -> 0 | AL16: =S16+L16+G16 -> 0 | AM16: =Y16+AD16 -> 0 | AN16: =AN15 -> 62 | AO16: =(AN16/100)*3000 -> 1860 | AP16: =AP15 -> 52 | AQ16: =(AP16/100)*3000 -> 1560 | AR16: =AR15 -> 68 | AS16: =(AR16/100)*3000 -> 2040 | AT16: =SUM(AO16+AQ16+AS16) -> 5460 | AU16: =AT15-AT16+AV16 -> 0 | AX16: =IF(AV16>0,AW16,AX15) -> 0.8
A17: =ELEC!C15 -> 44117 | B17: =B16 -> 242 | C17: =C16 -> 247.3 | D17: =C16-C17 -> 0 | E17: =D17*8.38 -> 0 | F17: =F16 -> 1648 | G17: =F17-F16 -> 0 | H17: =H16 -> 357868 | I17: =SUM(H17-H16) -> 0 | J17: =IF(G17>0,I17/G17,0) -> 0 | K17: =K16 -> 2115 | L17: =K17-K16 -> 0 | M17: =M16 -> 155221 | N17: =M17-M16 -> 0 | O17: =O16 -> 211.875 | P17: =P16 -> 1840 | Q17: =Q16 -> 156190 | R17: =Q17-Q16 -> 0 | S17: =SUM(P17-P16) -> 0 | T17: =SUM(S17*$T$2) -> 0 | U17: =SUM(G17+L17+S17) -> 0 | V17: =R17+N17+I17:I17 -> 0 | X17: =X16 -> 2448 | Y17: =X17-X16 -> 0 | Z17: =Z16 -> 137506 | AA17: =Z17-Z16 -> 0 | AB17: =SUM(Y17*$AB$2) -> 0 | AC17: =AC16 -> 1933 | AD17: =AC17-AC16 -> 0 | AE17: =AE16 -> 365212 | AF17: =AE17-AE16 -> 0 | AG17: =IF(AD17>0,AF17/AD17,0) -> 0 | AH17: =AF17+AA17 -> 0 | AI17: =SUM(AH17+V17) -> 0 | AJ17: =-tanks!AW18 -> 0 | AK17: =SUM(AJ17-AI17) -> 0 | AL17: =S17+L17+G17 -> 0 | AM17: =Y17+AD17 -> 0 | AN17: =AN16 -> 62 | AO17: =(AN17/100)*3000 -> 1860 | AP17: =AP16 -> 52 | AQ17: =(AP17/100)*3000 -> 1560 | AR17: =AR16 -> 68 | AS17: =(AR17/100)*3000 -> 2040 | AT17: =SUM(AO17+AQ17+AS17) -> 5460 | AU17: =AT16-AT17+AV17 -> 0 | AX17: =IF(AV17>0,AW17,AX16) -> 0.8
A18: =ELEC!C16 -> 44118 | B18: =B17 -> 242 | C18: =C17 -> 247.3 | D18: =C17-C18 -> 0 | E18: =D18*8.38 -> 0 | F18: =F17 -> 1648 | G18: =F18-F17 -> 0 | H18: =H17 -> 357868 | I18: =SUM(H18-H17) -> 0 | J18: =IF(G18>0,I18/G18,0) -> 0 | K18: =K17 -> 2115 | L18: =K18-K17 -> 0 | M18: =M17 -> 155221 | N18: =M18-M17 -> 0 | O18: =O17 -> 211.875 | P18: =P17 -> 1840 | Q18: =Q17 -> 156190 | R18: =Q18-Q17 -> 0 | S18: =SUM(P18-P17) -> 0 | T18: =SUM(S18*$T$2) -> 0 | U18: =SUM(G18+L18+S18) -> 0 | V18: =R18+N18+I18:I18 -> 0 | X18: =X17 -> 2448 | Y18: =X18-X17 -> 0 | Z18: =Z17 -> 137506 | AA18: =Z18-Z17 -> 0 | AB18: =SUM(Y18*$AB$2) -> 0 | AC18: =AC17 -> 1933 | AD18: =AC18-AC17 -> 0 | AE18: =AE17 -> 365212 | AF18: =AE18-AE17 -> 0 | AG18: =IF(AD18>0,AF18/AD18,0) -> 0 | AH18: =AF18+AA18 -> 0 | AI18: =SUM(AH18+V18) -> 0 | AJ18: =-tanks!AW19 -> 0 | AK18: =SUM(AJ18-AI18) -> 0 | AL18: =S18+L18+G18 -> 0 | AM18: =Y18+AD18 -> 0 | AN18: =AN17 -> 62 | AO18: =(AN18/100)*3000 -> 1860 | AP18: =AP17 -> 52 | AQ18: =(AP18/100)*3000 -> 1560 | AR18: =AR17 -> 68 | AS18: =(AR18/100)*3000 -> 2040 | AT18: =SUM(AO18+AQ18+AS18) -> 5460 | AU18: =AT17-AT18+AV18 -> 0 | AX18: =IF(AV18>0,AW18,AX17) -> 0.8
A19: =ELEC!C17 -> 44119 | B19: =B18 -> 242 | C19: =C18 -> 247.3 | D19: =C18-C19 -> 0 | E19: =D19*8.38 -> 0 | F19: =F18 -> 1648 | G19: =F19-F18 -> 0 | H19: =H18 -> 357868 | I19: =SUM(H19-H18) -> 0 | J19: =IF(G19>0,I19/G19,0) -> 0 | K19: =K18 -> 2115 | L19: =K19-K18 -> 0 | M19: =M18 -> 155221 | N19: =M19-M18 -> 0 | O19: =O18 -> 211.875 | P19: =P18 -> 1840 | Q19: =Q18 -> 156190 | R19: =Q19-Q18 -> 0 | S19: =SUM(P19-P18) -> 0 | T19: =SUM(S19*$T$2) -> 0 | U19: =SUM(G19+L19+S19) -> 0 | V19: =R19+N19+I19:I19 -> 0 | X19: =X18 -> 2448 | Y19: =X19-X18 -> 0 | Z19: =Z18 -> 137506 | AA19: =Z19-Z18 -> 0 | AB19: =SUM(Y19*$AB$2) -> 0 | AC19: =AC18 -> 1933 | AD19: =AC19-AC18 -> 0 | AE19: =AE18 -> 365212 | AF19: =AE19-AE18 -> 0 | AG19: =IF(AD19>0,AF19/AD19,0) -> 0 | AH19: =AF19+AA19 -> 0 | AI19: =SUM(AH19+V19) -> 0 | AJ19: =-tanks!AW20 -> 0 | AK19: =SUM(AJ19-AI19) -> 0 | AL19: =S19+L20+G19 -> 0 | AM19: =Y19+AD19 -> 0 | AN19: =AN18 -> 62 | AO19: =(AN19/100)*3000 -> 1860 | AP19: =AP18 -> 52 | AQ19: =(AP19/100)*3000 -> 1560 | AR19: =AR18 -> 68 | AS19: =(AR19/100)*3000 -> 2040 | AT19: =SUM(AO19+AQ19+AS19) -> 5460 | AU19: =AT18-AT19+AV19 -> 0 | AX19: =IF(AV19>0,AW19,AX18) -> 0.8
A20: =ELEC!C18 -> 44120 | B20: =B19 -> 242 | C20: =C19 -> 247.3 | D20: =C19-C20 -> 0 | E20: =D20*8.38 -> 0 | F20: =F19 -> 1648 | G20: =F20-F19 -> 0 | H20: =H19 -> 357868 | I20: =SUM(H20-H19) -> 0 | J20: =IF(G20>0,I20/G20,0) -> 0 | K20: =K19 -> 2115 | L20: =K20-K19 -> 0 | M20: =M19 -> 155221 | N20: =M20-M19 -> 0 | O20: =O19 -> 211.875 | P20: =P19 -> 1840 | Q20: =Q19 -> 156190 | R20: =Q20-Q19 -> 0 | S20: =SUM(P20-P19) -> 0 | T20: =SUM(S20*$T$2) -> 0 | U20: =SUM(G20+L20+S20) -> 0 | V20: =R20+N20+I20:I20 -> 0 | X20: =X19 -> 2448 | Y20: =X20-X19 -> 0 | Z20: =Z19 -> 137506 | AA20: =Z20-Z19 -> 0 | AB20: =SUM(Y20*$AB$2) -> 0 | AC20: =AC19 -> 1933 | AD20: =AC20-AC19 -> 0 | AE20: =AE19 -> 365212 | AF20: =AE20-AE19 -> 0 | AG20: =IF(AD20>0,AF20/AD20,0) -> 0 | AH20: =AF20+AA20 -> 0 | AI20: =SUM(AH20+V20) -> 0 | AJ20: =-tanks!AW21 -> 0 | AK20: =SUM(AJ20-AI20) -> 0 | AL20: =S20+L21+G20 -> 0 | AM20: =Y20+AD20 -> 0 | AN20: =AN19 -> 62 | AO20: =(AN20/100)*3000 -> 1860 | AP20: =AP19 -> 52 | AQ20: =(AP20/100)*3000 -> 1560 | AR20: =AR19 -> 68 | AS20: =(AR20/100)*3000 -> 2040 | AT20: =SUM(AO20+AQ20+AS20) -> 5460 | AU20: =AT19-AT20+AV20 -> 0 | AX20: =IF(AV20>0,AW20,AX19) -> 0.8
A21: =ELEC!C19 -> 44121 | B21: =B20 -> 242 | C21: =C20 -> 247.3 | D21: =C20-C21 -> 0 | E21: =D21*8.38 -> 0 | F21: =F20 -> 1648 | G21: =F21-F20 -> 0 | H21: =H20 -> 357868 | I21: =SUM(H21-H20) -> 0 | J21: =IF(G21>0,I21/G21,0) -> 0 | K21: =K20 -> 2115 | L21: =K21-K20 -> 0 | M21: =M20 -> 155221 | N21: =M21-M20 -> 0 | O21: =O20 -> 211.875 | P21: =P20 -> 1840 | Q21: =Q20 -> 156190 | R21: =Q21-Q20 -> 0 | S21: =SUM(P21-P20) -> 0 | T21: =SUM(S21*$T$2) -> 0 | U21: =SUM(G21+L21+S21) -> 0 | V21: =R21+N21+I21:I21 -> 0 | X21: =X20 -> 2448 | Y21: =X21-X20 -> 0 | Z21: =Z20 -> 137506 | AA21: =Z21-Z20 -> 0 | AB21: =SUM(Y21*$AB$2) -> 0 | AC21: =AC20 -> 1933 | AD21: =AC21-AC20 -> 0 | AE21: =AE20 -> 365212 | AF21: =AE21-AE20 -> 0 | AG21: =IF(AD21>0,AF21/AD21,0) -> 0 | AH21: =AF21+AA21 -> 0 | AI21: =SUM(AH21+V21) -> 0 | AJ21: =-tanks!AW22 -> 0 | AK21: =SUM(AJ21-AI21) -> 0 | AL21: =S21+L21+G21 -> 0 | AM21: =Y21+AD21 -> 0 | AN21: =AN20 -> 62 | AO21: =(AN21/100)*3000 -> 1860 | AP21: =AP20 -> 52 | AQ21: =(AP21/100)*3000 -> 1560 | AR21: =AR20 -> 68 | AS21: =(AR21/100)*3000 -> 2040 | AT21: =SUM(AO21+AQ21+AS21) -> 5460 | AU21: =AT20-AT21+AV21 -> 0 | AX21: =IF(AV21>0,AW21,AX20) -> 0.8
A22: =ELEC!C20 -> 44122 | B22: =B21 -> 242 | C22: =C21 -> 247.3 | D22: =C21-C22 -> 0 | E22: =D22*8.38 -> 0 | F22: =F21 -> 1648 | G22: =F22-F21 -> 0 | H22: =H21 -> 357868 | I22: =SUM(H22-H21) -> 0 | J22: =IF(G22>0,I22/G22,0) -> 0 | K22: =K21 -> 2115 | L22: =K22-K21 -> 0 | M22: =M21 -> 155221 | N22: =M22-M21 -> 0 | O22: =O21 -> 211.875 | P22: =P21 -> 1840 | Q22: =Q21 -> 156190 | R22: =Q22-Q21 -> 0 | S22: =SUM(P22-P21) -> 0 | T22: =SUM(S22*$T$2) -> 0 | U22: =SUM(G22+L22+S22) -> 0 | V22: =R22+N22+I22:I22 -> 0 | X22: =X21 -> 2448 | Y22: =X22-X21 -> 0 | Z22: =Z21 -> 137506 | AA22: =Z22-Z21 -> 0 | AB22: =SUM(Y22*$AB$2) -> 0 | AC22: =AC21 -> 1933 | AD22: =AC22-AC21 -> 0 | AE22: =AE21 -> 365212 | AF22: =AE22-AE21 -> 0 | AG22: =IF(AD22>0,AF22/AD22,0) -> 0 | AH22: =AF22+AA22 -> 0 | AI22: =SUM(AH22+V22) -> 0 | AJ22: =-tanks!AW23 -> 0 | AK22: =SUM(AJ22-AI22) -> 0 | AL22: =S22+L22+G22 -> 0 | AM22: =Y22+AD22 -> 0 | AN22: =AN21 -> 62 | AO22: =(AN22/100)*3000 -> 1860 | AP22: =AP21 -> 52 | AQ22: =(AP22/100)*3000 -> 1560 | AR22: =AR21 -> 68 | AS22: =(AR22/100)*3000 -> 2040 | AT22: =SUM(AO22+AQ22+AS22) -> 5460 | AU22: =AT21-AT22+AV22 -> 0 | AX22: =IF(AV22>0,AW22,AX21) -> 0.8
A23: =ELEC!C21 -> 44123 | B23: =B22 -> 242 | C23: =C22 -> 247.3 | D23: =C22-C23 -> 0 | E23: =D23*8.38 -> 0 | F23: =F22 -> 1648 | G23: =F23-F22 -> 0 | H23: =H22 -> 357868 | I23: =SUM(H23-H22) -> 0 | J23: =IF(G23>0,I23/G23,0) -> 0 | K23: =K22 -> 2115 | L23: =K23-K22 -> 0 | M23: =M22 -> 155221 | N23: =M23-M22 -> 0 | O23: =O22 -> 211.875 | P23: =P22 -> 1840 | Q23: =Q22 -> 156190 | R23: =Q23-Q22 -> 0 | S23: =SUM(P23-P22) -> 0 | T23: =SUM(S23*$T$2) -> 0 | U23: =SUM(G23+L23+S23) -> 0 | V23: =R23+N23+I23:I23 -> 0 | X23: =X22 -> 2448 | Y23: =X23-X22 -> 0 | Z23: =Z22 -> 137506 | AA23: =Z23-Z22 -> 0 | AB23: =SUM(Y23*$AB$2) -> 0 | AC23: =AC22 -> 1933 | AD23: =AC23-AC22 -> 0 | AE23: =AE22 -> 365212 | AF23: =AE23-AE22 -> 0 | AG23: =IF(AD23>0,AF23/AD23,0) -> 0 | AH23: =AF23+AA23 -> 0 | AI23: =SUM(AH23+V23) -> 0 | AJ23: =-tanks!AW24 -> 0 | AK23: =SUM(AJ23-AI23) -> 0 | AL23: =S23+L23+G23 -> 0 | AM23: =Y23+AD23 -> 0 | AN23: =AN22 -> 62 | AO23: =(AN23/100)*3000 -> 1860 | AP23: =AP22 -> 52 | AQ23: =(AP23/100)*3000 -> 1560 | AR23: =AR22 -> 68 | AS23: =(AR23/100)*3000 -> 2040 | AT23: =SUM(AO23+AQ23+AS23) -> 5460 | AU23: =AT22-AT23+AV23 -> 0 | AX23: =IF(AV23>0,AW23,AX22) -> 0.8
A24: =ELEC!C22 -> 44124 | B24: =B23 -> 242 | C24: =C23 -> 247.3 | D24: =C23-C24 -> 0 | E24: =D24*8.38 -> 0 | F24: =F23 -> 1648 | G24: =F24-F23 -> 0 | H24: =H23 -> 357868 | I24: =SUM(H24-H23) -> 0 | J24: =IF(G24>0,I24/G24,0) -> 0 | K24: =K23 -> 2115 | L24: =K24-K23 -> 0 | M24: =M23 -> 155221 | N24: =M24-M23 -> 0 | O24: =O23 -> 211.875 | P24: =P23 -> 1840 | Q24: =Q23 -> 156190 | R24: =Q24-Q23 -> 0 | S24: =SUM(P24-P23) -> 0 | T24: =SUM(S24*$T$2) -> 0 | U24: =SUM(G24+L24+S24) -> 0 | V24: =R24+N24+I24:I24 -> 0 | X24: =X23 -> 2448 | Y24: =X24-X23 -> 0 | Z24: =Z23 -> 137506 | AA24: =Z24-Z23 -> 0 | AB24: =SUM(Y24*$AB$2) -> 0 | AC24: =AC23 -> 1933 | AD24: =AC24-AC23 -> 0 | AE24: =AE23 -> 365212 | AF24: =AE24-AE23 -> 0 | AG24: =IF(AD24>0,AF24/AD24,0) -> 0 | AH24: =AF24+AA24 -> 0 | AI24: =SUM(AH24+V24) -> 0 | AJ24: =-tanks!AW25 -> 0 | AK24: =SUM(AJ24-AI24) -> 0 | AL24: =S24+L24+G24 -> 0 | AM24: =Y24+AD24 -> 0 | AN24: =AN23 -> 62 | AO24: =(AN24/100)*3000 -> 1860 | AP24: =AP23 -> 52 | AQ24: =(AP24/100)*3000 -> 1560 | AR24: =AR23 -> 68 | AS24: =(AR24/100)*3000 -> 2040 | AT24: =SUM(AO24+AQ24+AS24) -> 5460 | AU24: =AT23-AT24+AV24 -> 0 | AX24: =IF(AV24>0,AW24,AX23) -> 0.8
A25: =ELEC!C23 -> 44125 | B25: =B24 -> 242 | C25: =C24 -> 247.3 | D25: =C24-C25 -> 0 | E25: =D25*8.38 -> 0 | F25: =F24 -> 1648 | G25: =F25-F24 -> 0 | H25: =H24 -> 357868 | I25: =SUM(H25-H24) -> 0 | J25: =IF(G25>0,I25/G25,0) -> 0 | K25: =K24 -> 2115 | L25: =K25-K24 -> 0 | M25: =M24 -> 155221 | N25: =M25-M24 -> 0 | O25: =O24 -> 211.875 | P25: =P24 -> 1840 | Q25: =Q24 -> 156190 | R25: =Q25-Q24 -> 0 | S25: =SUM(P25-P24) -> 0 | T25: =SUM(S25*$T$2) -> 0 | U25: =SUM(G25+L25+S25) -> 0 | V25: =R25+N25+I25:I25 -> 0 | X25: =X24 -> 2448 | Y25: =X25-X24 -> 0 | Z25: =Z24 -> 137506 | AA25: =Z25-Z24 -> 0 | AB25: =SUM(Y25*$AB$2) -> 0 | AC25: =AC24 -> 1933 | AD25: =AC25-AC24 -> 0 | AE25: =AE24 -> 365212 | AF25: =AE25-AE24 -> 0 | AG25: =IF(AD25>0,AF25/AD25,0) -> 0 | AH25: =AF25+AA25 -> 0 | AI25: =SUM(AH25+V25) -> 0 | AJ25: =-tanks!AW26 -> 0 | AK25: =SUM(AJ25-AI25) -> 0 | AL25: =S25+L25+G25 -> 0 | AM25: =Y25+AD25 -> 0 | AN25: =AN24 -> 62 | AO25: =(AN25/100)*3000 -> 1860 | AP25: =AP24 -> 52 | AQ25: =(AP25/100)*3000 -> 1560 | AR25: =AR24 -> 68 | AS25: =(AR25/100)*3000 -> 2040 | AT25: =SUM(AO25+AQ25+AS25) -> 5460 | AU25: =AT24-AT25+AV25 -> 0 | AX25: =IF(AV25>0,AW25,AX24) -> 0.8
A26: =ELEC!C24 -> 44126 | B26: =B25 -> 242 | C26: =C25 -> 247.3 | D26: =C25-C26 -> 0 | E26: =D26*8.38 -> 0 | F26: =F25 -> 1648 | G26: =F26-F25 -> 0 | H26: =H25 -> 357868 | I26: =SUM(H26-H25) -> 0 | J26: =IF(G26>0,I26/G26,0) -> 0 | K26: =K25 -> 2115 | L26: =K26-K25 -> 0 | M26: =M25 -> 155221 | N26: =M26-M25 -> 0 | O26: =O25 -> 211.875 | P26: =P25 -> 1840 | Q26: =Q25 -> 156190 | R26: =Q26-Q25 -> 0 | S26: =SUM(P26-P25) -> 0 | T26: =SUM(S26*$T$2) -> 0 | U26: =SUM(G26+L26+S26) -> 0 | V26: =R26+N26+I26:I26 -> 0 | X26: =X25 -> 2448 | Y26: =X26-X25 -> 0 | Z26: =Z25 -> 137506 | AA26: =Z26-Z25 -> 0 | AB26: =SUM(Y26*$AB$2) -> 0 | AC26: =AC25 -> 1933 | AD26: =AC26-AC25 -> 0 | AE26: =AE25 -> 365212 | AF26: =AE26-AE25 -> 0 | AG26: =IF(AD26>0,AF26/AD26,0) -> 0 | AH26: =AF26+AA26 -> 0 | AI26: =SUM(AH26+V26) -> 0 | AJ26: =-tanks!AW27 -> 0 | AK26: =SUM(AJ26-AI26) -> 0 | AL26: =S26+L26+G26 -> 0 | AM26: =Y26+AD26 -> 0 | AN26: =AN25 -> 62 | AO26: =(AN26/100)*3000 -> 1860 | AP26: =AP25 -> 52 | AQ26: =(AP26/100)*3000 -> 1560 | AR26: =AR25 -> 68 | AS26: =(AR26/100)*3000 -> 2040 | AT26: =SUM(AO26+AQ26+AS26) -> 5460 | AU26: =AT25-AT26+AV26 -> 0 | AX26: =IF(AV26>0,AW26,AX25) -> 0.8
A27: =ELEC!C25 -> 44127 | B27: =B26 -> 242 | C27: =C26 -> 247.3 | D27: =C26-C27 -> 0 | E27: =D27*8.38 -> 0 | F27: =F26 -> 1648 | G27: =F27-F26 -> 0 | H27: =H26 -> 357868 | I27: =SUM(H27-H26) -> 0 | J27: =IF(G27>0,I27/G27,0) -> 0 | K27: =K26 -> 2115 | L27: =K27-K26 -> 0 | M27: =M26 -> 155221 | N27: =M27-M26 -> 0 | O27: =O26 -> 211.875 | P27: =P26 -> 1840 | Q27: =Q26 -> 156190 | R27: =Q27-Q26 -> 0 | S27: =SUM(P27-P26) -> 0 | T27: =SUM(S27*$T$2) -> 0 | U27: =SUM(G27+L27+S27) -> 0 | V27: =R27+N27+I27:I27 -> 0 | X27: =X26 -> 2448 | Y27: =X27-X26 -> 0 | Z27: =Z26 -> 137506 | AA27: =Z27-Z26 -> 0 | AB27: =SUM(Y27*$AB$2) -> 0 | AC27: =AC26 -> 1933 | AD27: =AC27-AC26 -> 0 | AE27: =AE26 -> 365212 | AF27: =AE27-AE26 -> 0 | AG27: =IF(AD27>0,AF27/AD27,0) -> 0 | AH27: =AF27+AA27 -> 0 | AI27: =SUM(AH27+V27) -> 0 | AJ27: =-tanks!AW28 -> 0 | AK27: =SUM(AJ27-AI27) -> 0 | AL27: =S27+L27+G27 -> 0 | AM27: =Y27+AD27 -> 0 | AN27: =AN26 -> 62 | AO27: =(AN27/100)*3000 -> 1860 | AP27: =AP26 -> 52 | AQ27: =(AP27/100)*3000 -> 1560 | AR27: =AR26 -> 68 | AS27: =(AR27/100)*3000 -> 2040 | AT27: =SUM(AO27+AQ27+AS27) -> 5460 | AU27: =AT26-AT27+AV27 -> 0 | AX27: =IF(AV27>0,AW27,AX26) -> 0.8
A28: =ELEC!C26 -> 44128 | B28: =B27 -> 242 | C28: =C27 -> 247.3 | D28: =C27-C28 -> 0 | E28: =D28*8.38 -> 0 | F28: =F27 -> 1648 | G28: =F28-F27 -> 0 | H28: =H27 -> 357868 | I28: =SUM(H28-H27) -> 0 | J28: =IF(G28>0,I28/G28,0) -> 0 | K28: =K27 -> 2115 | L28: =K28-K27 -> 0 | M28: =M27 -> 155221 | N28: =M28-M27 -> 0 | O28: =O27 -> 211.875 | P28: =P27 -> 1840 | Q28: =Q27 -> 156190 | R28: =Q28-Q27 -> 0 | S28: =SUM(P28-P27) -> 0 | T28: =SUM(S28*$T$2) -> 0 | U28: =SUM(G28+L28+S28) -> 0 | V28: =R28+N28+I28:I28 -> 0 | X28: =X27 -> 2448 | Y28: =X28-X27 -> 0 | Z28: =Z27 -> 137506 | AA28: =Z28-Z27 -> 0 | AB28: =SUM(Y28*$AB$2) -> 0 | AC28: =AC27 -> 1933 | AD28: =AC28-AC27 -> 0 | AE28: =AE27 -> 365212 | AF28: =AE28-AE27 -> 0 | AG28: =IF(AD28>0,AF28/AD28,0) -> 0 | AH28: =AF28+AA28 -> 0 | AI28: =SUM(AH28+V28) -> 0 | AJ28: =-tanks!AW29 -> 0 | AK28: =SUM(AJ28-AI28) -> 0 | AL28: =S28+L28+G28 -> 0 | AM28: =Y28+AD28 -> 0 | AN28: =AN27 -> 62 | AO28: =(AN28/100)*3000 -> 1860 | AP28: =AP27 -> 52 | AQ28: =(AP28/100)*3000 -> 1560 | AR28: =AR27 -> 68 | AS28: =(AR28/100)*3000 -> 2040 | AT28: =SUM(AO28+AQ28+AS28) -> 5460 | AU28: =AT27-AT28+AV28 -> 0 | AX28: =IF(AV28>0,AW28,AX27) -> 0.8
A29: =ELEC!C27 -> 44129 | B29: =B28 -> 242 | C29: =C28 -> 247.3 | D29: =C28-C29 -> 0 | E29: =D29*8.38 -> 0 | F29: =F28 -> 1648 | G29: =F29-F28 -> 0 | H29: =H28 -> 357868 | I29: =SUM(H29-H28) -> 0 | J29: =IF(G29>0,I29/G29,0) -> 0 | K29: =K28 -> 2115 | L29: =K29-K28 -> 0 | M29: =M28 -> 155221 | N29: =M29-M28 -> 0 | O29: =O28 -> 211.875 | P29: =P28 -> 1840 | Q29: =Q28 -> 156190 | R29: =Q29-Q28 -> 0 | S29: =SUM(P29-P28) -> 0 | T29: =SUM(S29*$T$2) -> 0 | U29: =SUM(G29+L29+S29) -> 0 | V29: =R29+N29+I29:I29 -> 0 | X29: =X28 -> 2448 | Y29: =X29-X28 -> 0 | Z29: =Z28 -> 137506 | AA29: =Z29-Z28 -> 0 | AB29: =SUM(Y29*$AB$2) -> 0 | AC29: =AC28 -> 1933 | AD29: =AC29-AC28 -> 0 | AE29: =AE28 -> 365212 | AF29: =AE29-AE28 -> 0 | AG29: =IF(AD29>0,AF29/AD29,0) -> 0 | AH29: =AF29+AA29 -> 0 | AI29: =SUM(AH29+V29) -> 0 | AJ29: =-tanks!AW30 -> 0 | AK29: =SUM(AJ29-AI29) -> 0 | AL29: =S29+L29+G29 -> 0 | AM29: =Y29+AD29 -> 0 | AN29: =AN28 -> 62 | AO29: =(AN29/100)*3000 -> 1860 | AP29: =AP28 -> 52 | AQ29: =(AP29/100)*3000 -> 1560 | AR29: =AR28 -> 68 | AS29: =(AR29/100)*3000 -> 2040 | AT29: =SUM(AO29+AQ29+AS29) -> 5460 | AU29: =AT28-AT29+AV29 -> 0 | AX29: =IF(AV29>0,AW29,AX28) -> 0.8
A30: =ELEC!C28 -> 44130 | B30: =B29 -> 242 | C30: =C29 -> 247.3 | D30: =C29-C30 -> 0 | E30: =D30*8.38 -> 0 | F30: =F29 -> 1648 | G30: =F30-F29 -> 0 | H30: =H29 -> 357868 | I30: =SUM(H30-H29) -> 0 | J30: =IF(G30>0,I30/G30,0) -> 0 | K30: =K29 -> 2115 | L30: =K30-K29 -> 0 | M30: =M29 -> 155221 | N30: =M30-M29 -> 0 | O30: =O29 -> 211.875 | P30: =P29 -> 1840 | Q30: =Q29 -> 156190 | R30: =Q30-Q29 -> 0 | S30: =SUM(P30-P29) -> 0 | T30: =SUM(S30*$T$2) -> 0 | U30: =SUM(G30+L30+S30) -> 0 | V30: =R30+N30+I30:I30 -> 0 | X30: =X29 -> 2448 | Y30: =X30-X29 -> 0 | Z30: =Z29 -> 137506 | AA30: =Z30-Z29 -> 0 | AB30: =SUM(Y30*$AB$2) -> 0 | AC30: =AC29 -> 1933 | AD30: =AC30-AC29 -> 0 | AE30: =AE29 -> 365212 | AF30: =AE30-AE29 -> 0 | AG30: =IF(AD30>0,AF30/AD30,0) -> 0 | AH30: =AF30+AA30 -> 0 | AI30: =SUM(AH30+V30) -> 0 | AJ30: =-tanks!AW31 -> 0 | AK30: =SUM(AJ30-AI30) -> 0 | AL30: =S30+L30+G30 -> 0 | AM30: =Y30+AD30 -> 0 | AN30: =AN29 -> 62 | AO30: =(AN30/100)*3000 -> 1860 | AP30: =AP29 -> 52 | AQ30: =(AP30/100)*3000 -> 1560 | AR30: =AR29 -> 68 | AS30: =(AR30/100)*3000 -> 2040 | AT30: =SUM(AO30+AQ30+AS30) -> 5460 | AU30: =AT29-AT30+AV30 -> 0 | AX30: =IF(AV30>0,AW30,AX29) -> 0.8
A31: =ELEC!C29 -> 44131 | B31: =B30 -> 242 | C31: =C30 -> 247.3 | D31: =C30-C31 -> 0 | E31: =D31*8.38 -> 0 | F31: =F30 -> 1648 | G31: =F31-F30 -> 0 | H31: =H30 -> 357868 | I31: =SUM(H31-H30) -> 0 | J31: =IF(G31>0,I31/G31,0) -> 0 | K31: =K30 -> 2115 | L31: =K31-K30 -> 0 | M31: =M30 -> 155221 | N31: =M31-M30 -> 0 | O31: =O30 -> 211.875 | P31: =P30 -> 1840 | Q31: =Q30 -> 156190 | R31: =Q31-Q30 -> 0 | S31: =SUM(P31-P30) -> 0 | T31: =SUM(S31*$T$2) -> 0 | U31: =SUM(G31+L31+S31) -> 0 | V31: =R31+N31+I31:I31 -> 0 | X31: =X30 -> 2448 | Y31: =X31-X30 -> 0 | Z31: =Z30 -> 137506 | AA31: =Z31-Z30 -> 0 | AB31: =SUM(Y31*$AB$2) -> 0 | AC31: =AC30 -> 1933 | AD31: =AC31-AC30 -> 0 | AE31: =AE30 -> 365212 | AF31: =AE31-AE30 -> 0 | AG31: =IF(AD31>0,AF31/AD31,0) -> 0 | AH31: =AF31+AA31 -> 0 | AI31: =SUM(AH31+V31) -> 0 | AJ31: =-tanks!AW32 -> 0 | AK31: =SUM(AJ31-AI31) -> 0 | AL31: =S31+L31+G31 -> 0 | AM31: =Y31+AD31 -> 0 | AN31: =AN30 -> 62 | AO31: =(AN31/100)*3000 -> 1860 | AP31: =AP30 -> 52 | AQ31: =(AP31/100)*3000 -> 1560 | AR31: =AR30 -> 68 | AS31: =(AR31/100)*3000 -> 2040 | AT31: =SUM(AO31+AQ31+AS31) -> 5460 | AU31: =AT30-AT31+AV31 -> 0 | AX31: =IF(AV31>0,AW31,AX30) -> 0.8
A32: =ELEC!C30 -> 44132 | B32: =B31 -> 242 | C32: =C31 -> 247.3 | D32: =C31-C32 -> 0 | E32: =D32*8.38 -> 0 | F32: =F31 -> 1648 | G32: =F32-F31 -> 0 | H32: =H31 -> 357868 | I32: =SUM(H32-H31) -> 0 | J32: =IF(G32>0,I32/G32,0) -> 0 | K32: =K31 -> 2115 | L32: =K32-K31 -> 0 | M32: =M31 -> 155221 | N32: =M32-M31 -> 0 | O32: =O31 -> 211.875 | P32: =P31 -> 1840 | Q32: =Q31 -> 156190 | R32: =Q32-Q31 -> 0 | S32: =SUM(P32-P31) -> 0 | T32: =SUM(S32*$T$2) -> 0 | U32: =SUM(G32+L32+S32) -> 0 | V32: =R32+N32+I32:I32 -> 0 | X32: =X31 -> 2448 | Y32: =X32-X31 -> 0 | Z32: =Z31 -> 137506 | AA32: =Z32-Z31 -> 0 | AB32: =SUM(Y32*$AB$2) -> 0 | AC32: =AC31 -> 1933 | AD32: =AC32-AC31 -> 0 | AE32: =AE31 -> 365212 | AF32: =AE32-AE31 -> 0 | AG32: =IF(AD32>0,AF32/AD32,0) -> 0 | AH32: =AF32+AA32 -> 0 | AI32: =SUM(AH32+V32) -> 0 | AJ32: =-tanks!AW33 -> 0 | AK32: =SUM(AJ32-AI32) -> 0 | AL32: =S32+L32+G32 -> 0 | AM32: =Y32+AD32 -> 0 | AN32: =AN31 -> 62 | AO32: =(AN32/100)*3000 -> 1860 | AP32: =AP31 -> 52 | AQ32: =(AP32/100)*3000 -> 1560 | AR32: =AR31 -> 68 | AS32: =(AR32/100)*3000 -> 2040 | AT32: =SUM(AO32+AQ32+AS32) -> 5460 | AU32: =AT31-AT32+AV32 -> 0 | AX32: =IF(AV32>0,AW32,AX31) -> 0.8
... A34: =ELEC!C32 -> 44134 | B34: =B33 -> 242 | C34: =C33 -> 247.3 | D34: =C33-C34 -> 0 | E34: =D34*8.38 -> 0 | F34: =F33 -> 1648 | G34: =F34-F33 -> 0 | H34: =H33 -> 357868 | I34: =SUM(H34-H33) -> 0 | J34: =IF(G34>0,I34/G34,0) -> 0 | K34: =K33 -> 2115 | L34: =K34-K33 -> 0 | M34: =M33 -> 155221 | N34: =M34-M33 -> 0 | O34: =O33 -> 211.875 | P34: =P33 -> 1840 | Q34: =Q33 -> 156190 | R34: =Q34-Q33 -> 0 | S34: =SUM(P34-P33) -> 0 | T34: =SUM(S34*$T$2) -> 0 | U34: =SUM(G34+L34+S34) -> 0 | V34: =R34+N34+I34:I34 -> 0 | X34: =X33 -> 2448 | Y34: =X34-X33 -> 0 | Z34: =Z33 -> 137506 | AA34: =Z34-Z33 -> 0 | AB34: =SUM(Y34*$AB$2) -> 0 | AC34: =AC33 -> 1933 | AD34: =AC34-AC33 -> 0 | AE34: =AE33 -> 365212 | AF34: =AE34-AE33 -> 0 | AG34: =IF(AD34>0,AF34/AD34,0) -> 0 | AH34: =AF34+AA34 -> 0 | AI34: =SUM(AH34+V34) -> 0 | AJ34: =-tanks!AW35 -> 0 | AK34: =SUM(AJ34-AI34) -> 0 | AL34: =S34+L34+G34 -> 0 | AM34: =Y34+AD34 -> 0 | AN34: =AN33 -> 62 | AO34: =(AN34/100)*3000 -> 1860 | AP34: =AP33 -> 52 | AQ34: =(AP34/100)*3000 -> 1560 | AR34: =AR33 -> 68 | AS34: =(AR34/100)*3000 -> 2040 | AT34: =SUM(AO34+AQ34+AS34) -> 5460 | AU34: =AT33-AT34+AV34 -> 0 | AX34: =IF(AV34>0,AW34,AX33) -> 0.8
A35: =ELEC!C33 -> 44135 | B35: =B34 -> 242 | C35: =C34 -> 247.3 | D35: =C34-C35 -> 0 | E35: =D35*8.38 -> 0 | F35: =F34 -> 1648 | G35: =F35-F34 -> 0 | H35: =H34 -> 357868 | I35: =SUM(H35-H34) -> 0 | J35: =IF(G35>0,I35/G35,0) -> 0 | K35: =K34 -> 2115 | L35: =K35-K34 -> 0 | M35: =M34 -> 155221 | N35: =M35-M34 -> 0 | O35: =O34 -> 211.875 | P35: =P34 -> 1840 | Q35: =Q34 -> 156190 | R35: =Q35-Q34 -> 0 | S35: =SUM(P35-P34) -> 0 | T35: =SUM(S35*$T$2) -> 0 | U35: =SUM(G35+L35+S35) -> 0 | V35: =R35+N35+I35:I35 -> 0 | X35: =X34 -> 2448 | Y35: =X35-X34 -> 0 | Z35: =Z34 -> 137506 | AA35: =Z35-Z34 -> 0 | AB35: =SUM(Y35*$AB$2) -> 0 | AC35: =AC34 -> 1933 | AD35: =AC35-AC34 -> 0 | AE35: =AE34 -> 365212 | AF35: =AE35-AE34 -> 0 | AG35: =IF(AD35>0,AF35/AD35,0) -> 0 | AH35: =AF35+AA35 -> 0 | AI35: =SUM(AH35+V35) -> 0 | AJ35: =-tanks!AW37 -> 0 | AK35: =SUM(AJ35-AI35) -> 0 | AL35: =S35+L35+G35 -> 0 | AM35: =Y35+AD35 -> 0 | AN35: =AN34 -> 62 | AO35: =(AN35/100)*3000 -> 1860 | AP35: =AP34 -> 52 | AQ35: =(AP35/100)*3000 -> 1560 | AR35: =AR34 -> 68 | AS35: =(AR35/100)*3000 -> 2040 | AT35: =SUM(AO35+AQ35+AS35) -> 5460 | AU35: =AT34-AT35+AV35 -> 0 | AX35: =IF(AV35>0,AW35,AX34) -> 0.8
J36: =SUM(J5:J34)/(COUNT(J5:J34)-COUNTIF(J5:J34,0)) -> 1 | V36: =SUM(V5:V35) -> 497 | AE36: . | AH36: =SUM(AH5:AH35) -> 1.8 | AL36: =SUM(AL5:AL35) -> 6 | AM36: =SUM(AM5:AM35) -> 0 | AR36: Nb Delivery | AS36: =COUNT(AW5:AW34) -> 1 | AU36: =SUM(AU5:AU34) -> -30 | AV36: =SUM(AV5:AV34) -> 0 | AW36: =SUM(AW5:AW34)/AS36 -> 0.1
AH37: =AF37+AA37 -> 0 | AI37: =SUM(AI5:AI34) -> 498.8
AH38: =AF38+AA38 -> 0 | AU38: =AU36*0.51 -> -15.3 | AV38: =AV36/0.51 -> 0 | AW38: =SUM(AW5:AW34)/AS36 -> 0.1
AV39: =AV36*0.51 -> 0

Sheet WATER
D1: =SUM(G21:G35) -> 9133950 | AR1: Entrance | AT1: Tank 1 | AV1: Tank 2
AR2: Level | AW2: Quantity CM3 | AZ2: Var
A3: Date | B3: Truck | C3: Truck M3/day | D3: N0. Trucks | F3: REQ. # of trucks | G3: City | H3: City/day | I3: Total water delivery | K3: SW | L3: Cosum SW/day | M3: RO Guest/ Liter | O3: RO K&L/ Liter | Q3: TOTAL RO Production | R3: RO 1 RH | S3: RO 2 RH | T3: RO water counter | U3: RO Cons m3 | V3: Steam Boiler | W3: Steam Boiler/day | X3: Softener Guest | Y3: Guest Sotf/day | Z3: Softener K&L | AA3: K&L Soft/Day | AB3: Fire Tank Level | AC3: Fire Tank Counter | AE3: Laundry Hot Water Counter | AF3: Hot Water Cons/day | AG3: Laundry Cold Water Counter | AH3: Cold Water Cons/day | AI3: Laundry Water Total Cons | AJ3: K&L Sotf/day | AK3: Guest / day | AL3: K&L /day | AM3: Avg Outside Temp | AN3: Banquet Activity | AR3: Date | AT3: MainI | AV3: Kitchen and Laundry | AX3: Guest | AY3: Main Tank | AZ3: Kitchen and Laundry | BA3: Guest | BB3: Kitchen and Laundry | BC3: Main | BD3: Guest | BE3: Total VAR | BF3: Hotel Consumption
E4: 1.66 | AN4: Ball R | AO4: Meeting | AP4: outlet | AT4: 180 | AV4: 220 | AX4: 580 | AY4: =SUM(AT4) -> 180 | AZ4: =SUM(AV4) -> 220 | BA4: =SUM(AX4) -> 580
A5: 44104 | B5: =[2]WATER!B35 -> 109096 | C5: =[2]WATER!C35 -> 0 | D5: =[2]WATER!D35 -> 0 | E5: =[2]WATER!E35 -> 250 | F5: =[2]WATER!F35 -> 0 | G5: =[2]WATER!G35 -> 608742 | H5: =[2]WATER!H35 -> 0 | I5: =[2]WATER!I35 -> 0 | ... S5: =[2]WATER!S35 -> 0 | T5: 5127 | U5: =[2]WATER!U35 -> 3 | V5: =[2]WATER!V35 -> 452 | W5: =[2]WATER!W35 -> 0 | X5: =[2]WATER!X35 -> 147647 | Y5: =[2]WATER!Y35 -> 60 | Z5: =[2]WATER!Z35 -> 97058 | AA5: =[2]WATER!AA35 -> 23 | AB5: =[2]WATER!AB35 -> 264 | ... BG5: =[2]WATER!BG35 -> -54.1
A6: =ELEC!C3 -> 44105 | B6: =B5 -> 109096 | C6: =B6-B5 -> 0 | D6: =C6/27 -> 0 | E6: =SUM((C6*$E$4)+(7500/'EDl log'!$A$38)) -> 241.93548 | G6: =G5 -> 608742 | H6: =G6-G5 -> 0 | I6: =C6+H6 -> 0 | J6: =IF(I6>0,E6/I6,0) -> 0 | K6: 6555 | L6: 0 | M6: =M5 -> 457.44 | N6: =SUM(M6-M5) -> 0 | O6: =O5 -> 529.52 | P6: =SUM(O6-O5) -> 0 | Q6: =P6+N6 -> 0 | T6: =T5 -> 5127 | U6: =SUM(T6-T5) -> 0 | V6: =V5 -> 452 | W6: =+V6-V5 -> 0 | X6: =X5 -> 147647 | Y6: =SUM(X6-X5) -> 0 | Z6: =Z5 -> 97058 | AA6: =Z6-Z5 -> 0 | AB6: =AB5 -> 264 | AC6: =AC5 -> 698 | AD6: 0 | AE6: =AE5 -> 217.84 | AF6: =AE6-AE5 -> 0 | AG6: =AG5 -> 2176.58 | AH6: =AG6-AG5 -> 0 | AI6: =AF6+AH6 -> 0 | AJ6: =+Z6-Z5 -> 0 | AK6: =SUM(Y6-L6) -> 0 | AL6: =SUM(AJ6-W6) -> 0 | AM6: ='General information '!D6 -> 27.5 | AN6: ='General information '!H6 -> 0 | AP6: ='General information '!J6 -> 0 | AR6: =A6 -> 44105 | AS6: =AS5 -> 0.9 | AT6: 32 | AU6: =AU5 -> 1.1 | AV6: 42 | AW6: 2.9 | AX6: 43 | AY6: =AS6*AT6 -> 28.8 | AZ6: =AU6*AV6 -> 46.2 | BA6: =AW6*AX6 -> 124.7 | BB6: =AY6-AY5 -> -27.9 | BC6: =AZ6-AZ5 -> 1.1 | BD6: =BA6-BA5 -> -2.9 | BE6: =SUM(BB6:BD6) -> -29.7 | BF6: =SUM(I6-BE6) -> 29.7 | BG6: =SUM(I6-BF6) -> -29.7
A7: =ELEC!C4 -> 44106 | B7: =B6 -> 109096 | C7: =B7-B6 -> 0 | D7: =C7/27 -> 0 | E7: =SUM((C7*$E$4)+(7500/'EDl log'!$A$38)) -> 241.93548 | G7: 608832 | H7: =G7-G6 -> 90 | I7: =C7+H7 -> 90 | J7: =IF(I7>0,E7/I7,0) -> 2.688172 | K7: ='Swimming Pool quality check '!H7 -> 6555 | L7: =K7-K6 -> 0 | M7: =M6 -> 457.44 | N7: =SUM(M7-M6) -> 0 | O7: =O6 -> 529.52 | P7: =SUM(O7-O6) -> 0 | Q7: =P7+N7 -> 0 | T7: 5129 | U7: =SUM(T7-T6) -> 2 | V7: =V6 -> 452 | W7: =+V7-V6 -> 0 | X7: 147668 | Y7: =SUM(X7-X6) -> 21 | Z7: 97071 | AA7: =Z7-Z6 -> 13 | AB7: 260 | AC7: =AC6 -> 698 | AD7: =AC7-AC6 -> 0 | AE7: =AE6 -> 217.84 | AF7: =AE7-AE6 -> 0 | AG7: =AG6 -> 2176.58 | AH7: =AG7-AG6 -> 0 | AI7: =AF7+AH7 -> 0 | AJ7: =+Z7-Z6 -> 13 | AK7: =SUM(Y7-L7) -> 21 | AL7: =SUM(AJ7-W7) -> 13 | AM7: ='General information '!D7 -> 28 | AN7: ='General information '!H7 -> 0 | AP7: ='General information '!J7 -> 0 | AR7: =A7 -> 44106 | AS7: =AS6 -> 0.9 | AT7: 62 | AU7: =AU6 -> 1.1 | AV7: 33 | AW7: 2.9 | AX7: 41 | AY7: =AS7*AT7 -> 55.8 | AZ7: =AU7*AV7 -> 36.3 | BA7: =AW7*AX7 -> 118.9 | BB7: =AY7-AY6 -> 27 | BC7: =AZ7-AZ6 -> -9.9 | BD7: =BA7-BA6 -> -5.8 | BE7: =SUM(BB7:BD7) -> 11.3 | BF7: =SUM(I7-BE7) -> 78.7 | BG7: =SUM(I7-BF7) -> 11.3
A8: =ELEC!C5 -> 44107 | B8: =B7 -> 109096 | C8: =B8-B7 -> 0 | D8: =C8/27 -> 0 | E8: =SUM((C8*$E$4)+(7500/'EDl log'!$A$38)) -> 241.93548 | G8: =G7 -> 608832 | H8: =G8-G7 -> 0 | I8: =C8+H8 -> 0 | J8: =IF(I8>0,E8/I8,0) -> 0 | K8: ='Swimming Pool quality check '!H8 -> 6555 | L8: =K8-K7 -> 0 | M8: =M7 -> 457.44 | N8: =SUM(M8-M7) -> 0 | O8: =O7 -> 529.52 | P8: =SUM(O8-O7) -> 0 | Q8: =P8+N8 -> 0 | T8: 5132 | U8: =SUM(T8-T7) -> 3 | V8: =V7 -> 452 | W8: =+V8-V7 -> 0 | X8: 147679 | Y8: =SUM(X8-X7) -> 11 | Z8: 97096 | AA8: =Z8-Z7 -> 25 | AB8: =AB7 -> 260 | AC8: =AC7 -> 698 | AD8: =AC8-AC7 -> 0 | AE8: =AE7 -> 217.84 | AF8: =AE8-AE7 -> 0 | AG8: =AG7 -> 2176.58 | AH8: =AG8-AG7 -> 0 | AI8: =AF8+AH8 -> 0 | AJ8: =+Z8-Z7 -> 25 | AK8: =SUM(Y8-L8) -> 11 | AL8: =SUM(AJ8-W8) -> 25 | AM8: ='General information '!D8 -> 26.5 | AN8: ='General information '!H8 -> 0 | AP8: ='General information '!J8 -> 0 | AR8: =A8 -> 44107 | AS8: =AS7 -> 0.9 | AT8: 19 | AU8: 1.1 | AV8: 43 | AW8: 2.9 | AX8: 43 | AY8: =AS8*AT8 -> 17.1 | AZ8: =AU8*AV8 -> 47.3 | BA8: =AW8*AX8 -> 124.7 | BB8: =AY8-AY7 -> -38.7 | BC8: =AZ8-AZ7 -> 11 | BD8: =BA8-BA7 -> 5.8 | BE8: =SUM(BB8:BD8) -> -21.9 | BF8: =SUM(I8-BE8) -> 21.9 | BG8: =SUM(I8-BF8) -> -21.9
A9: =ELEC!C6 -> 44108 | B9: =B8 -> 109096 | C9: =B9-B8 -> 0 | D9: =C9/27 -> 0 | E9: =SUM((C9*$E$4)+(7500/'EDl log'!$A$38)) -> 241.93548 | G9: 608930 | H9: =G9-G8 -> 98 | I9: =C9+H9 -> 98 | J9: =IF(I9>0,E9/I9,0) -> 2.4687294 | K9: ='Swimming Pool quality check '!H9 -> 6555 | L9: =K9-K8 -> 0 | M9: =M8 -> 457.44 | N9: =SUM(M9-M8) -> 0 | O9: =O8 -> 529.52 | P9: =SUM(O9-O8) -> 0 | Q9: =P9+N9 -> 0 | T9: 5133 | U9: =SUM(T9-T8) -> 1 | V9: =V8 -> 452 | W9: =+V9-V8 -> 0 | X9: =X8 -> 147679 | Y9: =SUM(X9-X8) -> 0 | Z9: =Z8 -> 97096 | AA9: =Z9-Z8 -> 0 | AB9: =AB8 -> 260 | AC9: =AC8 -> 698 | AD9: =AC9-AC8 -> 0 | AE9: =AE8 -> 217.84 | AF9: =AE9-AE8 -> 0 | AG9: =AG8 -> 2176.58 | AH9: =AG9-AG8 -> 0 | AI9: =AF9+AH9 -> 0 | AJ9: =+Z9-Z8 -> 0 | AK9: =SUM(Y9-L9) -> 0 | AL9: =SUM(AJ9-W9) -> 0 | AM9: ='General information '!D9 -> 27 | AN9: ='General information '!H9 -> 0 | AP9: ='General information '!J9 -> 0 | AR9: =A9 -> 44108 | AS9: =AS8 -> 0.9 | AT9: 74 | AU9: =AU8 -> 1.1 | AV9: 38 | AW9: 2.9 | AX9: 42 | AY9: =AS9*AT9 -> 66.6 | AZ9: =AU9*AV9 -> 41.8 | BA9: =AW9*AX9 -> 121.8 | BB9: =AY9-AY8 -> 49.5 | BC9: =AZ9-AZ8 -> -5.5 | BD9: =BA9-BA8 -> -2.9 | BE9: =SUM(BB9:BD9) -> 41.1 | BF9: =SUM(I9-BE9) -> 56.9 | BG9: =SUM(I9-BF9) -> 41.1
A10: =ELEC!C7 -> 44109 | B10: =B9 -> 109096 | C10: =B10-B9 -> 0 | D10: =C10/27 -> 0 | E10: =SUM((C10*$E$4)+(7500/'EDl log'!$A$38)) -> 241.93548 | G10: 608930 | H10: =G10-G9 -> 0 | I10: =C10+H10 -> 0 | J10: =IF(I10>0,E10/I10,0) -> 0 | K10: ='Swimming Pool quality check '!H10 -> 6555 | L10: =K10-K9 -> 0 | M10: =M9 -> 457.44 | N10: =SUM(M10-M9) -> 0 | O10: =O9 -> 529.52 | P10: =SUM(O10-O9) -> 0 | Q10: =P10+N10 -> 0 | T10: 5135 | U10: =SUM(T10-T9) -> 2 | V10: =V9 -> 452 | W10: =+V10-V9 -> 0 | X10: 147726 | Y10: =SUM(X10-X9) -> 47 | Z10: 97117 | AA10: =Z10-Z9 -> 21 | AB10: =AB9 -> 260 | AC10: =AC9 -> 698 | AD10: =AC10-AC9 -> 0 | AE10: =AE9 -> 217.84 | AF10: =AE10-AE9 -> 0 | AG10: =AG9 -> 2176.58 | AH10: =AG10-AG9 -> 0 | AI10: =AF10+AH10 -> 0 | AJ10: =+Z10-Z9 -> 21 | AK10: =SUM(Y10-L10) -> 47 | AL10: =SUM(AJ10-W10) -> 21 | AM10: ='General information '!D10 -> 28.5 | AN10: ='General information '!H10 -> 0 | AP10: ='General information '!J10 -> 0 | AR10: =A10 -> 44109 | AS10: =AS9 -> 0.9 | AT10: 0 | AU10: =AU9 -> 1.1 | AV10: 46 | AW10: 2.9 | AX10: 48 | AY10: =AS10*AT10 -> 0 | AZ10: =AU10*AV10 -> 50.6 | BA10: =AW10*AX10 -> 139.2 | BB10: =AY10-AY9 -> -66.6 | BC10: =AZ10-AZ9 -> 8.8 | BD10: =BA10-BA9 -> 17.4 | BE10: =SUM(BB10:BD10) -> -40.4 | BF10: =SUM(I10-BE10) -> 40.4 | BG10: =SUM(I10-BF10) -> -40.4
A11: =ELEC!C8 -> 44110 | B11: =B10 -> 109096 | C11: =B11-B10 -> 0 | D11: =C11/27 -> 0 | E11: =SUM((C11*$E$4)+(7500/'EDl log'!$A$38)) -> 241.93548 | G11: =G10 -> 608930 | H11: =G11-G10 -> 0 | I11: =C11+H11 -> 0 | J11: =IF(I11>0,E11/I11,0) -> 0 | K11: ='Swimming Pool quality check '!H11 -> 6555 | L11: =K11-K10 -> 0 | M11: =M10 -> 457.44 | N11: =SUM(M11-M10) -> 0 | O11: =O10 -> 529.52 | P11: =SUM(O11-O10) -> 0 | Q11: =SUM(P11+N11) -> 0 | T11: =T10 -> 5135 | U11: =SUM(T11-T10) -> 0 | V11: =V10 -> 452 | W11: =+V11-V10 -> 0 | X11: =X10 -> 147726 | Y11: =SUM(X11-X10) -> 0 | Z11: =Z10 -> 97117 | AA11: =Z11-Z10 -> 0 | AB11: =AB10 -> 260 | AC11: =AC10 -> 698 | AD11: =AC11-AC10 -> 0 | AE11: =AE10 -> 217.84 | AF11: =AE11-AE10 -> 0 | AG11: =AG10 -> 2176.58 | AH11: =AG11-AG10 -> 0 | AI11: =AF11+AH11 -> 0 | AJ11: =+Z11-Z10 -> 0 | AK11: =SUM(Y11-L11) -> 0 | AL11: =SUM(AJ11-W11) -> 0 | AM11: ='General information '!D11 -> 0 | AN11: ='General information '!H11 -> 0 | AP11: ='General information '!J11 -> 0 | AR11: =A11 -> 44110 | AS11: =AS10 -> 0.9 | AT11: =AT10 -> 0 | AU11: =AU10 -> 1.1 | AV11: =AV10 -> 46 | AW11: 2.9 | AX11: =AX10 -> 48 | AY11: =AS11*AT11 -> 0 | AZ11: =AU11*AV11 -> 50.6 | BA11: =AW11*AX11 -> 139.2 | BB11: =AY11-AY10 -> 0 | BC11: =AZ11-AZ10 -> 0 | BD11: =BA11-BA10 -> 0 | BE11: =SUM(BB11:BD11) -> 0 | BF11: =SUM(I11-BE11) -> 0 | BG11: =SUM(I11-BF11) -> 0
A12: =ELEC!C9 -> 44111 | B12: =B11 -> 109096 | C12: =B12-B11 -> 0 | D12: =C12/27 -> 0 | E12: =SUM((C12*$E$4)+(7500/'EDl log'!$A$38)) -> 241.93548 | G12: =G11 -> 608930 | H12: =G12-G11 -> 0 | I12: =C12+H12 -> 0 | J12: =IF(I12>0,E12/I12,0) -> 0 | K12: ='Swimming Pool quality check '!H12 -> 6555 | L12: =K12-K11 -> 0 | M12: =M11 -> 457.44 | N12: =SUM(M12-M11) -> 0 | O12: =O11 -> 529.52 | P12: =SUM(O12-O11) -> 0 | Q12: =SUM(P12+N12) -> 0 | T12: =T11 -> 5135 | U12: =SUM(T12-T11) -> 0 | V12: =V11 -> 452 | W12: =+V12-V11 -> 0 | X12: =X11 -> 147726 | Y12: =SUM(X12-X11) -> 0 | Z12: =Z11 -> 97117 | AA12: =Z12-Z11 -> 0 | AB12: =AB11 -> 260 | AC12: =AC11 -> 698 | AD12: =AC12-AC11 -> 0 | AE12: =AE11 -> 217.84 | AF12: =AE12-AE11 -> 0 | AG12: =AG11 -> 2176.58 | AH12: =AG12-AG11 -> 0 | AI12: =AF12+AH12 -> 0 | AJ12: =+Z12-Z11 -> 0 | AK12: =SUM(Y12-L12) -> 0 | AL12: =SUM(AJ12-W12) -> 0 | AM12: ='General information '!D12 -> 0 | AN12: ='General information '!H12 -> 0 | AP12: ='General information '!J12 -> 0 | AR12: =A12 -> 44111 | AS12: =AS11 -> 0.9 | AT12: =AT11 -> 0 | AU12: =AU11 -> 1.1 | AV12: =AV11 -> 46 | AW12: 2.9 | AX12: =AX11 -> 48 | AY12: =AS12*AT12 -> 0 | AZ12: =AU12*AV12 -> 50.6 | BA12: =AW12*AX12 -> 139.2 | BB12: =AY12-AY11 -> 0 | BC12: =AZ12-AZ11 -> 0 | BD12: =BA12-BA11 -> 0 | BE12: =SUM(BB12:BD12) -> 0 | BF12: =SUM(I12-BE12) -> 0 | BG12: =SUM(I12-BF12) -> 0
A13: =ELEC!C10 -> 44112 | B13: =B12 -> 109096 | C13: =B13-B12 -> 0 | D13: =C13/27 -> 0 | E13: =SUM((C13*$E$4)+(7500/'EDl log'!$A$38)) -> 241.93548 | G13: =G12 -> 608930 | H13: =G13-G12 -> 0 | I13: =C13+H13 -> 0 | J13: =IF(I13>0,E13/I13,0) -> 0 | K13: ='Swimming Pool quality check '!H13 -> 6555 | L13: =K13-K12 -> 0 | M13: =M12 -> 457.44 | N13: =SUM(M13-M12) -> 0 | O13: =O12 -> 529.52 | P13: =SUM(O13-O12) -> 0 | Q13: =SUM(P13+N13) -> 0 | T13: =T12 -> 5135 | U13: =SUM(T13-T12) -> 0 | V13: =V12 -> 452 | W13: =+V13-V12 -> 0 | X13: =X12 -> 147726 | Y13: =SUM(X13-X12) -> 0 | Z13: =Z12 -> 97117 | AA13: =Z13-Z12 -> 0 | AB13: =AB12 -> 260 | AC13: =AC12 -> 698 | AD13: =AC13-AC12 -> 0 | AE13: =AE12 -> 217.84 | AF13: =AE13-AE12 -> 0 | AG13: =AG12 -> 2176.58 | AH13: =AG13-AG12 -> 0 | AI13: =AF13+AH13 -> 0 | AJ13: =+Z13-Z12 -> 0 | AK13: =SUM(Y13-L13) -> 0 | AL13: =SUM(AJ13-W13) -> 0 | AM13: ='General information '!D13 -> 0 | AN13: ='General information '!J13 -> 0 | AP13: ='General information '!J13 -> 0 | AR13: =A13 -> 44112 | AS13: =AS12 -> 0.9 | AT13: =AT12 -> 0 | AU13: =AU12 -> 1.1 | AV13: =AV12 -> 46 | AW13: 2.9 | AX13: =AX12 -> 48 | AY13: =AS13*AT13 -> 0 | AZ13: =AU13*AV13 -> 50.6 | BA13: =AW13*AX13 -> 139.2 | BB13: =AY13-AY12 -> 0 | BC13: =AZ13-AZ12 -> 0 | BD13: =BA13-BA12 -> 0 | BE13: =SUM(BB13:BD13) -> 0 | BF13: =SUM(I13-BE13) -> 0 | BG13: =SUM(I13-BF13) -> 0
A14: =ELEC!C11 -> 44113 | B14: =B13 -> 109096 | C14: =B14-B13 -> 0 | D14: =C14/27 -> 0 | E14: =SUM((C14*$E$4)+(7500/'EDl log'!$A$38)) -> 241.93548 | G14: =G13 -> 608930 | H14: =G14-G13 -> 0 | I14: =C14+H14 -> 0 | J14: =IF(I14>0,E14/I14,0) -> 0 | K14: ='Swimming Pool quality check '!H14 -> 6555 | L14: =K14-K13 -> 0 | M14: =M13 -> 457.44 | N14: =SUM(M14-M13) -> 0 | O14: =O13 -> 529.52 | P14: =SUM(O14-O13) -> 0 | Q14: =SUM(P14+N14) -> 0 | T14: =T13 -> 5135 | U14: =SUM(T14-T13) -> 0 | V14: =V13 -> 452 | W14: =+V14-V13 -> 0 | X14: =X13 -> 147726 | Y14: =SUM(X14-X13) -> 0 | Z14: =Z13 -> 97117 | AA14: =Z14-Z13 -> 0 | AB14: =AB13 -> 260 | AC14: =AC13 -> 698 | AD14: =AC14-AC13 -> 0 | AE14: =AE13 -> 217.84 | AF14: =AE14-AE13 -> 0 | AG14: =AG13 -> 2176.58 | AH14: =AG14-AG13 -> 0 | AI14: =AF14+AH14 -> 0 | AJ14: =+Z14-Z13 -> 0 | AK14: =SUM(Y14-L14) -> 0 | AL14: =SUM(AJ14-W14) -> 0 | AM14: ='General information '!D14 -> 0 | AN14: ='General information '!H14 -> 0 | AP14: ='General information '!J14 -> 0 | AR14: =A14 -> 44113 | AS14: =AS13 -> 0.9 | AT14: =AT13 -> 0 | AU14: =AU13 -> 1.1 | AV14: =AV13 -> 46 | AW14: 2.9 | AX14: =AX13 -> 48 | AY14: =AS14*AT14 -> 0 | AZ14: =AU14*AV14 -> 50.6 | BA14: =AW14*AX14 -> 139.2 | BB14: =AY14-AY13 -> 0 | BC14: =AZ14-AZ13 -> 0 | BD14: =BA14-BA13 -> 0 | BE14: =SUM(BB14:BD14) -> 0 | BF14: =SUM(I14-BE14) -> 0 | BG14: =SUM(I14-BF14) -> 0
A15: =ELEC!C12 -> 44114 | B15: =B14 -> 109096 | C15: =B15-B14 -> 0 | D15: =C15/27 -> 0 | E15: =SUM((C15*$E$4)+(7500/'EDl log'!$A$38)) -> 241.93548 | G15: =G14 -> 608930 | H15: =G15-G14 -> 0 | I15: =C15+H15 -> 0 | J15: =IF(I15>0,E15/I15,0) -> 0 | K15: ='Swimming Pool quality check '!H15 -> 6555 | L15: =K15-K14 -> 0 | M15: =M14 -> 457.44 | N15: =SUM(M15-M14) -> 0 | O15: =O14 -> 529.52 | P15: =SUM(O15-O14) -> 0 | Q15: =SUM(P15+N15) -> 0 | T15: =T14 -> 5135 | U15: =SUM(T15-T14) -> 0 | V15: =V14 -> 452 | W15: =+V15-V14 -> 0 | X15: =X14 -> 147726 | Y15: =SUM(X15-X14) -> 0 | Z15: =Z14 -> 97117 | AA15: =Z15-Z14 -> 0 | AB15: =AB14 -> 260 | AC15: =AC14 -> 698 | AD15: =AC15-AC14 -> 0 | AE15: =AE14 -> 217.84 | AF15: =AE15-AE14 -> 0 | AG15: =AG14 -> 2176.58 | AH15: =AG15-AG14 -> 0 | AI15: =AF15+AH15 -> 0 | AJ15: =+Z15-Z14 -> 0 | AK15: =SUM(Y15-L15) -> 0 | AL15: =SUM(AJ15-W15) -> 0 | AM15: ='General information '!D15 -> 0 | AN15: ='General information '!H15 -> 0 | AP15: ='General information '!J15 -> 0 | AR15: =A15 -> 44114 | AS15: =AS14 -> 0.9 | AT15: =AT14 -> 0 | AU15: =AU14 -> 1.1 | AV15: =AV14 -> 46 | AW15: 2.9 | AX15: =AX14 -> 48 | AY15: =AS15*AT15 -> 0 | AZ15: =AU15*AV15 -> 50.6 | BA15: =AW15*AX15 -> 139.2 | BB15: =AY15-AY14 -> 0 | BC15: =AZ15-AZ14 -> 0 | BD15: =BA15-BA14 -> 0 | BE15: =SUM(BB15:BD15) -> 0 | BF15: =SUM(I15-BE15) -> 0 | BG15: =SUM(I15-BF15) -> 0
A16: =ELEC!C13 -> 44115 | B16: =B15 -> 109096 | C16: =B16-B15 -> 0 | D16: =C16/27 -> 0 | E16: =SUM((C16*$E$4)+(7500/'EDl log'!$A$38)) -> 241.93548 | G16: =G15 -> 608930 | H16: =G16-G15 -> 0 | I16: =C16+H16 -> 0 | J16: =IF(I16>0,E16/I16,0) -> 0 | K16: ='Swimming Pool quality check '!H16 -> 6555 | L16: =K16-K15 -> 0 | M16: =M15 -> 457.44 | N16: =SUM(M16-M15) -> 0 | O16: =O15 -> 529.52 | P16: =SUM(O16-O15) -> 0 | Q16: =SUM(P16+N16) -> 0 | T16: =T15 -> 5135 | U16: =SUM(T16-T15) -> 0 | V16: =V15 -> 452 | W16: =+V16-V15 -> 0 | X16: =X15 -> 147726 | Y16: =SUM(X16-X15) -> 0 | Z16: =Z15 -> 97117 | AA16: =Z16-Z15 -> 0 | AB16: =AB15 -> 260 | AC16: =AC15 -> 698 | AD16: =AC16-AC15 -> 0 | AE16: =AE15 -> 217.84 | AF16: =AE16-AE15 -> 0 | AG16: =AG15 -> 2176.58 | AH16: =AG16-AG15 -> 0 | AI16: =AF16+AH16 -> 0 | AJ16: =+Z16-Z15 -> 0 | AK16: =SUM(Y16-L16) -> 0 | AL16: =SUM(AJ16-W16) -> 0 | AM16: ='General information '!D16 -> 0 | AN16: ='General information '!H16 -> 0 | AP16: ='General information '!J16 -> 0 | AR16: =A16 -> 44115 | AS16: =AS15 -> 0.9 | AT16: =AT15 -> 0 | AU16: =AU15 -> 1.1 | AV16: =AV15 -> 46 | AW16: 2.9 | AX16: =AX15 -> 48 | AY16: =AS16*AT16 -> 0 | AZ16: =AU16*AV16 -> 50.6 | BA16: =AW16*AX16 -> 139.2 | BB16: =AY16-AY15 -> 0 | BC16: =AZ16-AZ15 -> 0 | BD16: =BA16-BA15 -> 0 | BE16: =SUM(BB16:BD16) -> 0 | BF16: =SUM(I16-BE16) -> 0 | BG16: =SUM(I16-BF16) -> 0
A17: =ELEC!C14 -> 44116 | B17: =B16 -> 109096 | C17: =B17-B16 -> 0 | D17: =C17/27 -> 0 | E17: =SUM((C17*$E$4)+(7500/'EDl log'!$A$38)) -> 241.93548 | G17: =G16 -> 608930 | H17: =G17-G16 -> 0 | I17: =C17+H17 -> 0 | J17: =IF(I17>0,E17/I17,0) -> 0 | K17: ='Swimming Pool quality check '!H17 -> 6555 | L17: =K17-K16 -> 0 | M17: =M16 -> 457.44 | N17: =SUM(M17-M16) -> 0 | O17: =O16 -> 529.52 | P17: =SUM(O17-O16) -> 0 | Q17: =SUM(P17+N17) -> 0 | T17: =T16 -> 5135 | U17: =SUM(T17-T16) -> 0 | V17: =V16 -> 452 | W17: =+V17-V16 -> 0 | X17: =X16 -> 147726 | Y17: =SUM(X17-X16) -> 0 | Z17: =Z16 -> 97117 | AA17: =Z17-Z16 -> 0 | AB17: =AB16 -> 260 | AC17: =AC16 -> 698 | AD17: =AC17-AC16 -> 0 | AE17: =AE16 -> 217.84 | AF17: =AE17-AE16 -> 0 | AG17: =AG16 -> 2176.58 | AH17: =AG17-AG16 -> 0 | AI17: =AF17+AH17 -> 0 | AJ17: =+Z17-Z16 -> 0 | AK17: =SUM(Y17-L17) -> 0 | AL17: =SUM(AJ17-W17) -> 0 | AM17: ='General information '!D17 -> 0 | AN17: ='General information '!H17 -> 0 | AP17: ='General information '!J17 -> 0 | AR17: =A17 -> 44116 | AS17: =AS16 -> 0.9 | AT17: =AT16 -> 0 | AU17: =AU16 -> 1.1 | AV17: =AV16 -> 46 | AW17: 2.9 | AX17: =AX16 -> 48 | AY17: =AS17*AT17 -> 0 | AZ17: =AU17*AV17 -> 50.6 | BA17: =AW17*AX17 -> 139.2 | BB17: =AY17-AY16 -> 0 | BC17: =AZ17-AZ16 -> 0 | BD17: =BA17-BA16 -> 0 | BE17: =SUM(BB17:BD17) -> 0 | BF17: =SUM(I17-BE17) -> 0 | BG17: =SUM(I17-BF17) -> 0
A18: =ELEC!C15 -> 44117 | B18: =B17 -> 109096 | C18: =B18-B17 -> 0 | D18: =C18/27 -> 0 | E18: =SUM((C18*$E$4)+(7500/'EDl log'!$A$38)) -> 241.93548 | G18: =G17 -> 608930 | H18: =G18-G17 -> 0 | I18: =C18+H18 -> 0 | J18: =IF(I18>0,E18/I18,0) -> 0 | K18: ='Swimming Pool quality check '!H18 -> 6555 | L18: =K18-K17 -> 0 | M18: =M17 -> 457.44 | N18: =SUM(M18-M17) -> 0 | O18: =O17 -> 529.52 | P18: =SUM(O18-O17) -> 0 | Q18: =SUM(P18+N18) -> 0 | T18: =T17 -> 5135 | U18: =SUM(T18-T17) -> 0 | V18: =V17 -> 452 | W18: =+V18-V17 -> 0 | X18: =X17 -> 147726 | Y18: =SUM(X18-X17) -> 0 | Z18: =Z17 -> 97117 | AA18: =Z18-Z17 -> 0 | AB18: =AB17 -> 260 | AC18: =AC17 -> 698 | AD18: =AC18-AC17 -> 0 | AE18: =AE17 -> 217.84 | AF18: =AE18-AE17 -> 0 | AG18: =AG17 -> 2176.58 | AH18: =AG18-AG17 -> 0 | AI18: =AF18+AH18 -> 0 | AJ18: =+Z18-Z17 -> 0 | AK18: =SUM(Y18-L18) -> 0 | AL18: =SUM(AJ18-W18) -> 0 | AM18: ='General information '!D18 -> 0 | AN18: ='General information '!H18 -> 0 | AP18: ='General information '!J18 -> 0 | AR18: =A18 -> 44117 | AS18: =AS17 -> 0.9 | AT18: =AT17 -> 0 | AU18: =AU17 -> 1.1 | AV18: =AV17 -> 46 | AW18: 2.9 | AX18: =AX17 -> 48 | AY18: =AS18*AT18 -> 0 | AZ18: =AU18*AV18 -> 50.6 | BA18: =AW18*AX18 -> 139.2 | BB18: =AY18-AY17 -> 0 | BC18: =AZ18-AZ17 -> 0 | BD18: =BA18-BA17 -> 0 | BE18: =SUM(BB18:BD18) -> 0 | BF18: =SUM(I18-BE18) -> 0 | BG18: =SUM(I18-BF18) -> 0
A19: =ELEC!C16 -> 44118 | B19: =B18 -> 109096 | C19: =B19-B18 -> 0 | D19: =C19/27 -> 0 | E19: =SUM((C19*$E$4)+(7500/'EDl log'!$A$38)) -> 241.93548 | G19: =G18 -> 608930 | H19: =G19-G18 -> 0 | I19: =C19+H19 -> 0 | J19: =IF(I19>0,E19/I19,0) -> 0 | K19: ='Swimming Pool quality check '!H19 -> 6555 | L19: =K19-K18 -> 0 | M19: =M18 -> 457.44 | N19: =SUM(M19-M18) -> 0 | O19: =O18 -> 529.52 | P19: =SUM(O19-O18) -> 0 | Q19: =SUM(P19+N19) -> 0 | T19: =T18 -> 5135 | U19: =SUM(T19-T18) -> 0 | V19: =V18 -> 452 | W19: =+V19-V18 -> 0 | X19: =X18 -> 147726 | Y19: =SUM(X19-X18) -> 0 | Z19: =Z18 -> 97117 | AA19: =Z19-Z18 -> 0 | AB19: =AB18 -> 260 | AC19: =AC18 -> 698 | AD19: =AC19-AC18 -> 0 | AE19: =AE18 -> 217.84 | AF19: =AE19-AE18 -> 0 | AG19: =AG18 -> 2176.58 | AH19: =AG19-AG18 -> 0 | AI19: =AF19+AH19 -> 0 | AJ19: =+Z19-Z18 -> 0 | AK19: =SUM(Y19-L19) -> 0 | AL19: =SUM(AJ19-W19) -> 0 | AM19: ='General information '!D19 -> 0 | AN19: ='General information '!H19 -> 0 | AP19: ='General information '!J19 -> 0 | AR19: =A19 -> 44118 | AS19: =AS18 -> 0.9 | AT19: =AT18 -> 0 | AU19: =AU18 -> 1.1 | AV19: =AV18 -> 46 | AW19: 2.9 | AX19: =AX18 -> 48 | AY19: =AS19*AT19 -> 0 | AZ19: =AU19*AV19 -> 50.6 | BA19: =AW19*AX19 -> 139.2 | BB19: =AY19-AY18 -> 0 | BC19: =AZ19-AZ18 -> 0 | BD19: =BA19-BA18 -> 0 | BE19: =SUM(BB19:BD19) -> 0 | BF19: =SUM(I19-BE19) -> 0 | BG19: =SUM(I19-BF19) -> 0
A20: =ELEC!C17 -> 44119 | B20: =B19 -> 109096 | C20: =B20-B19 -> 0 | D20: =C20/27 -> 0 | E20: =SUM((C20*$E$4)+(7500/'EDl log'!$A$38)) -> 241.93548 | G20: =G19 -> 608930 | H20: =G20-G19 -> 0 | I20: =C20+H20 -> 0 | J20: =IF(I20>0,E20/I20,0) -> 0 | K20: ='Swimming Pool quality check '!H20 -> 6555 | L20: =K20-K19 -> 0 | M20: =M19 -> 457.44 | N20: =SUM(M20-M19) -> 0 | O20: =O19 -> 529.52 | P20: =SUM(O20-O19) -> 0 | Q20: =SUM(P20+N20) -> 0 | T20: =T19 -> 5135 | U20: =SUM(T20-T19) -> 0 | V20: =V19 -> 452 | W20: =+V20-V19 -> 0 | X20: =X19 -> 147726 | Y20: =SUM(X20-X19) -> 0 | Z20: =Z19 -> 97117 | AA20: =Z20-Z19 -> 0 | AB20: =AB19 -> 260 | AC20: =AC19 -> 698 | AD20: =AC20-AC19 -> 0 | AE20: =AE19 -> 217.84 | AF20: =AE20-AE19 -> 0 | AG20: =AG19 -> 2176.58 | AH20: =AG20-AG19 -> 0 | AI20: =AF20+AH20 -> 0 | AJ20: =+Z20-Z19 -> 0 | AK20: =SUM(Y20-L20) -> 0 | AL20: =SUM(AJ20-W20) -> 0 | AM20: ='General information '!D20 -> 0 | AN20: ='General information '!H20 -> 0 | AP20: ='General information '!J20 -> 0 | AR20: =A20 -> 44119 | AS20: =AS19 -> 0.9 | AT20: =AT19 -> 0 | AU20: =AU19 -> 1.1 | AV20: =AV19 -> 46 | AW20: 2.9 | AX20: =AX19 -> 48 | AY20: =AS20*AT20 -> 0 | AZ20: =AU20*AV20 -> 50.6 | BA20: =AW20*AX20 -> 139.2 | BB20: =AY20-AY19 -> 0 | BC20: =AZ20-AZ19 -> 0 | BD20: =BA20-BA19 -> 0 | BE20: =SUM(BB20:BD20) -> 0 | BF20: =SUM(I20-BE20) -> 0 | BG20: =SUM(I20-BF20) -> 0
A21: =ELEC!C18 -> 44120 | B21: =B20 -> 109096 | C21: =B21-B20 -> 0 | D21: =C21/27 -> 0 | E21: =SUM((C21*$E$4)+(7500/'EDl log'!$A$38)) -> 241.93548 | G21: =G20 -> 608930 | H21: =G21-G20 -> 0 | I21: =C21+H21 -> 0 | J21: =IF(I21>0,E21/I21,0) -> 0 | K21: ='Swimming Pool quality check '!H21 -> 6555 | L21: =K21-K20 -> 0 | M21: =M20 -> 457.44 | N21: =SUM(M21-M20) -> 0 | O21: =O20 -> 529.52 | P21: =SUM(O21-O20) -> 0 | Q21: =SUM(P21+N21) -> 0 | T21: =T20 -> 5135 | U21: =SUM(T21-T20) -> 0 | V21: =V20 -> 452 | W21: =+V21-V20 -> 0 | X21: =X20 -> 147726 | Y21: =SUM(X21-X20) -> 0 | Z21: =Z20 -> 97117 | AA21: =Z21-Z20 -> 0 | AB21: =AB20 -> 260 | AC21: =AC20 -> 698 | AD21: =AC21-AC20 -> 0 | AE21: =AE20 -> 217.84 | AF21: =AE21-AE20 -> 0 | AG21: =AG20 -> 2176.58 | AH21: =AG21-AG20 -> 0 | AI21: =AF21+AH21 -> 0 | AJ21: =+Z21-Z20 -> 0 | AK21: =SUM(Y21-L21) -> 0 | AL21: =SUM(AJ21-W21) -> 0 | AM21: ='General information '!D21 -> 0 | AN21: ='General information '!H21 -> 0 | AP21: ='General information '!J21 -> 0 | AR21: =A21 -> 44120 | AS21: =AS20 -> 0.9 | AT21: =AT20 -> 0 | AU21: =AU20 -> 1.1 | AV21: =AV20 -> 46 | AW21: 2.9 | AX21: =AX20 -> 48 | AY21: =AS21*AT21 -> 0 | AZ21: =AU21*AV21 -> 50.6 | BA21: =AW21*AX21 -> 139.2 | BB21: =AY21-AY20 -> 0 | BC21: =AZ21-AZ20 -> 0 | BD21: =BA21-BA20 -> 0 | BE21: =SUM(BB21:BD21) -> 0 | BF21: =SUM(I21-BE21) -> 0 | BG21: =SUM(I21-BF21) -> 0
A22: =ELEC!C19 -> 44121 | B22: =B21 -> 109096 | C22: =B22-B21 -> 0 | D22: =C22/27 -> 0 | E22: =SUM((C22*$E$4)+(7500/'EDl log'!$A$38)) -> 241.93548 | G22: =G21 -> 608930 | H22: =G22-G21 -> 0 | I22: =C22+H22 -> 0 | J22: =IF(I22>0,E22/I22,0) -> 0 | K22: ='Swimming Pool quality check '!H22 -> 6555 | L22: =K22-K21 -> 0 | M22: =M21 -> 457.44 | N22: =SUM(M22-M21) -> 0 | O22: =O21 -> 529.52 | P22: =SUM(O22-O21) -> 0 | Q22: =SUM(P22+N22) -> 0 | T22: =T21 -> 5135 | U22: =SUM(T22-T21) -> 0 | V22: =V21 -> 452 | W22: =+V22-V21 -> 0 | X22: =X21 -> 147726 | Y22: =SUM(X22-X21) -> 0 | Z22: =Z21 -> 97117 | AA22: =Z22-Z21 -> 0 | AB22: =AB21 -> 260 | AC22: =AC21 -> 698 | AD22: =AC22-AC21 -> 0 | AE22: =AE21 -> 217.84 | AF22: =AE22-AE21 -> 0 | AG22: =AG21 -> 2176.58 | AH22: =AG22-AG21 -> 0 | AI22: =AF22+AH22 -> 0 | AJ22: =+Z22-Z21 -> 0 | AK22: =SUM(Y22-L22) -> 0 | AL22: =SUM(AJ22-W22) -> 0 | AM22: ='General information '!D22 -> 0 | AN22: ='General information '!H22 -> 0 | AP22: ='General information '!J22 -> 0 | AR22: =A22 -> 44121 | AS22: =AS21 -> 0.9 | AT22: =AT21 -> 0 | AU22: =AU21 -> 1.1 | AV22: =AV21 -> 46 | AW22: 2.9 | AX22: =AX21 -> 48 | AY22: =AS22*AT22 -> 0 | AZ22: =AU22*AV22 -> 50.6 | BA22: =AW22*AX22 -> 139.2 | BB22: =AY22-AY21 -> 0 | BC22: =AZ22-AZ21 -> 0 | BD22: =BA22-BA21 -> 0 | BE22: =SUM(BB22:BD22) -> 0 | BF22: =SUM(I22-BE22) -> 0 | BG22: =SUM(I22-BF22) -> 0
A23: =ELEC!C20 -> 44122 | B23: =B22 -> 109096 | C23: =B23-B22 -> 0 | D23: =C23/27 -> 0 | E23: =SUM((C23*$E$4)+(7500/'EDl log'!$A$38)) -> 241.93548 | G23: =G22 -> 608930 | H23: =G23-G22 -> 0 | I23: =C23+H23 -> 0 | J23: =IF(I23>0,E23/I23,0) -> 0 | K23: ='Swimming Pool quality check '!H23 -> 6555 | L23: =K23-K22 -> 0 | M23: =M22 -> 457.44 | N23: =SUM(M23-M22) -> 0 | O23: =O22 -> 529.52 | P23: =SUM(O23-O22) -> 0 | Q23: =SUM(P23+N23) -> 0 | T23: =T22 -> 5135 | U23: =SUM(T23-T22) -> 0 | V23: =V22 -> 452 | W23: =+V23-V22 -> 0 | X23: =X22 -> 147726 | Y23: =SUM(X23-X22) -> 0 | Z23: =Z22 -> 97117 | AA23: =Z23-Z22 -> 0 | AB23: =AB22 -> 260 | AC23: =AC22 -> 698 | AD23: =AC23-AC22 -> 0 | AE23: =AE22 -> 217.84 | AF23: =AE23-AE22 -> 0 | AG23: =AG22 -> 2176.58 | AH23: =AG23-AG22 -> 0 | AI23: =AF23+AH23 -> 0 | AJ23: =+Z23-Z22 -> 0 | AK23: =SUM(Y23-L23) -> 0 | AL23: =SUM(AJ23-W23) -> 0 | AM23: ='General information '!D23 -> 0 | AN23: ='General information '!H23 -> 0 | AP23: ='General information '!J23 -> 0 | AR23: =A23 -> 44122 | AS23: =AS22 -> 0.9 | AT23: =AT22 -> 0 | AU23: =AU22 -> 1.1 | AV23: =AV22 -> 46 | AW23: 2.9 | AX23: =AX22 -> 48 | AY23: =AS23*AT23 -> 0 | AZ23: =AU23*AV23 -> 50.6 | BA23: =AW23*AX23 -> 139.2 | BB23: =AY23-AY22 -> 0 | BC23: =AZ23-AZ22 -> 0 | BD23: =BA23-BA22 -> 0 | BE23: =SUM(BB23:BD23) -> 0 | BF23: =SUM(I23-BE23) -> 0 | BG23: =SUM(I23-BF23) -> 0
A24: =ELEC!C21 -> 44123 | B24: =B23 -> 109096 | C24: =B24-B23 -> 0 | D24: =C24/27 -> 0 | E24: =SUM((C24*$E$4)+(7500/'EDl log'!$A$38)) -> 241.93548 | G24: =G23 -> 608930 | H24: =G24-G23 -> 0 | I24: =C24+H24 -> 0 | J24: =IF(I24>0,E24/I24,0) -> 0 | K24: ='Swimming Pool quality check '!H24 -> 6555 | L24: =K24-K23 -> 0 | M24: =M23 -> 457.44 | N24: =SUM(M24-M23) -> 0 | O24: =O23 -> 529.52 | P24: =SUM(O24-O23) -> 0 | Q24: =SUM(P24+N24) -> 0 | T24: =T23 -> 5135 | U24: =SUM(T24-T23) -> 0 | V24: =V23 -> 452 | W24: =+V24-V23 -> 0 | X24: =X23 -> 147726 | Y24: =SUM(X24-X23) -> 0 | Z24: =Z23 -> 97117 | AA24: =Z24-Z23 -> 0 | AB24: =AB23 -> 260 | AC24: =AC23 -> 698 | AD24: =AC24-AC23 -> 0 | AE24: =AE23 -> 217.84 | AF24: =AE24-AE23 -> 0 | AG24: =AG23 -> 2176.58 | AH24: =AG24-AG23 -> 0 | AI24: =AF24+AH24 -> 0 | AJ24: =+Z24-Z23 -> 0 | AK24: =SUM(Y24-L24) -> 0 | AL24: =SUM(AJ24-W24) -> 0 | AM24: ='General information '!D24 -> 0 | AN24: ='General information '!H24 -> 0 | AP24: ='General information '!J24 -> 0 | AR24: =A24 -> 44123 | AS24: =AS23 -> 0.9 | AT24: =AT23 -> 0 | AU24: =AU23 -> 1.1 | AV24: =AV23 -> 46 | AW24: 2.9 | AX24: =AX23 -> 48 | AY24: =AS24*AT24 -> 0 | AZ24: =AU24*AV24 -> 50.6 | BA24: =AW24*AX24 -> 139.2 | BB24: =AY24-AY23 -> 0 | BC24: =AZ24-AZ23 -> 0 | BD24: =BA24-BA23 -> 0 | BE24: =SUM(BB24:BD24) -> 0 | BF24: =SUM(I24-BE24) -> 0 | BG24: =SUM(I24-BF24) -> 0
A25: =ELEC!C22 -> 44124 | B25: =B24 -> 109096 | C25: =B25-B24 -> 0 | D25: =C25/27 -> 0 | E25: =SUM((C25*$E$4)+(7500/'EDl log'!$A$38)) -> 241.93548 | G25: =G24 -> 608930 | H25: =G25-G24 -> 0 | I25: =C25+H25 -> 0 | J25: =IF(I25>0,E25/I25,0) -> 0 | K25: ='Swimming Pool quality check '!H25 -> 6555 | L25: =K25-K24 -> 0 | M25: =M24 -> 457.44 | N25: =SUM(M25-M24) -> 0 | O25: =O24 -> 529.52 | P25: =SUM(O25-O24) -> 0 | Q25: =SUM(P25+N25) -> 0 | T25: =T24 -> 5135 | U25: =SUM(T25-T24) -> 0 | V25: =V24 -> 452 | W25: =+V25-V24 -> 0 | X25: =X24 -> 147726 | Y25: =SUM(X25-X24) -> 0 | Z25: =Z24 -> 97117 | AA25: =Z25-Z24 -> 0 | AB25: =AB24 -> 260 | AC25: =AC24 -> 698 | AD25: =AC25-AC24 -> 0 | AE25: =AE24 -> 217.84 | AF25: =AE25-AE24 -> 0 | AG25: =AG24 -> 2176.58 | AH25: =AG25-AG24 -> 0 | AI25: =AF25+AH25 -> 0 | AJ25: =+Z25-Z24 -> 0 | AK25: =SUM(Y25-L25) -> 0 | AL25: =SUM(AJ25-W25) -> 0 | AM25: ='General information '!D25 -> 0 | AN25: ='General information '!H25 -> 0 | AP25: ='General information '!J25 -> 0 | AR25: =A25 -> 44124 | AS25: =AS24 -> 0.9 | AT25: =AT24 -> 0 | AU25: =AU24 -> 1.1 | AV25: =AV24 -> 46 | AW25: 2.9 | AX25: =AX24 -> 48 | AY25: =AS25*AT25 -> 0 | AZ25: =AU25*AV25 -> 50.6 | BA25: =AW25*AX25 -> 139.2 | BB25: =AY25-AY24 -> 0 | BC25: =AZ25-AZ24 -> 0 | BD25: =BA25-BA24 -> 0 | BE25: =SUM(BB25:BD25) -> 0 | BF25: =SUM(I25-BE25) -> 0 | BG25: =SUM(I25-BF25) -> 0
... A35: =ELEC!C32 -> 44134 | B35: =B34 -> 109096 | C35: =B35-B34 -> 0 | D35: =C35/27 -> 0 | E35: =SUM((C35*$E$4)+(7500/'EDl log'!$A$38)) -> 241.93548 | G35: =G34 -> 608930 | H35: =G35-G34 -> 0 | I35: =C35+H35 -> 0 | J35: =IF(I35>0,E35/I35,0) -> 0 | K35: ='Swimming Pool quality check '!H35 -> 6555 | L35: =K35-K34 -> 0 | M35: =M34 -> 457.44 | N35: =SUM(M35-M34) -> 0 | O35: =O34 -> 529.52 | P35: =SUM(O35-O34) -> 0 | Q35: =SUM(P35+N35) -> 0 | T35: =T34 -> 5135 | U35: =SUM(T35-T34) -> 0 | V35: =V34 -> 452 | W35: =+V35-V34 -> 0 | X35: =X34 -> 147726 | Y35: =SUM(X35-X34) -> 0 | Z35: =Z34 -> 97117 | AA35: =Z35-Z34 -> 0 | AB35: =AB34 -> 260 | AC35: =AC34 -> 698 | AD35: =AC35-AC34 -> 0 | AE35: =AE34 -> 217.84 | AF35: =AE35-AE34 -> 0 | AG35: =AG34 -> 2176.58 | AH35: =AG35-AG34 -> 0 | AI35: =AF35+AH35 -> 0 | AJ35: =+Z35-Z34 -> 0 | AK35: =SUM(Y35-L35) -> 0 | AL35: =SUM(AJ35-W35) -> 0 | AM35: ='General information '!D35 -> 0 | AN35: ='General information '!H35 -> 0 | AP35: ='General information '!J35 -> 0 | AR35: =A35 -> 44134 | AS35: =AS34 -> 0.9 | AT35: =AT34 -> 0 | AU35: =AU34 -> 1.1 | AV35: =AV34 -> 46 | AW35: 2.9 | AX35: =AX34 -> 48 | AY35: =AS35*AT35 -> 0 | AZ35: =AU35*AV35 -> 50.6 | BA35: =AW35*AX35 -> 139.2 | BB35: =AY35-AY34 -> 0 | BC35: =AZ35-AZ34 -> 0 | BD35: =BA35-BA34 -> 0 | BE35: =SUM(BB35:BD35) -> 0 | BF35: =SUM(I35-BE35) -> 0 | BG35: =SUM(I35-BF35) -> 0
A36: =ELEC!C33 -> 44135 | B36: =B35 -> 109096 | C36: =B36-B35 -> 0 | D36: =C36/27 -> 0 | E36: =SUM((C36*$E$4)+(7500/'EDl log'!$A$38)) -> 241.93548 | G36: =G35 -> 608930 | H36: =G36-G35 -> 0 | I36: =C36+H36 -> 0 | J36: =IF(I36>0,E36/I36,0) -> 0 | K36: ='Swimming Pool quality check '!H36 -> 6555 | L36: =K36-K35 -> 0 | M36: =M35 -> 457.44 | N36: =SUM(M36-M35) -> 0 | O36: =O35 -> 529.52 | P36: =SUM(O36-O35) -> 0 | Q36: =SUM(P36+N36) -> 0 | T36: =T35 -> 5135 | U36: =SUM(T36-T35) -> 0 | V36: =V35 -> 452 | W36: =+V36-V35 -> 0 | X36: =X35 -> 147726 | Y36: =SUM(X36-X35) -> 0 | Z36: =Z35 -> 97117 | AA36: =Z36-Z35 -> 0 | AB36: =AB35 -> 260 | AC36: =AC35 -> 698 | AD36: =AC36-AC35 -> 0 | AE36: =AE35 -> 217.84 | AF36: =AE36-AE35 -> 0 | AG36: =AG35 -> 2176.58 | AH36: =AG36-AG35 -> 0 | AI36: =AF36+AH36 -> 0 | AJ36: =+Z36-Z35 -> 0 | AK36: =SUM(Y36-L36) -> 0 | AL36: =SUM(AJ36-W36) -> 0 | AM36: ='General information '!D37 -> 0 | AN36: ='General information '!H37 -> 0 | AP36: ='General information '!J37 -> 0 | AR36: =A36 -> 44135 | AS36: =AS35 -> 0.9 | AT36: =AT35 -> 0 | AU36: =AU35 -> 1.1 | AV36: =AV35 -> 46 | AW36: 2.9 | AX36: =AX35 -> 48 | AY36: =AS36*AT36 -> 0 | AZ36: =AU36*AV36 -> 50.6 | BA36: =AW36*AX36 -> 139.2 | BB36: =AY36-AY35 -> 0 | BC36: =AZ36-AZ35 -> 0 | BD36: =BA36-BA35 -> 0 | BE36: =SUM(BB36:BD36) -> 0 | BF36: =SUM(I36-BE36) -> 0 | BG36: =SUM(I36-BF36) -> 0
C37: =SUM(C6:C35) -> 0 | D37: =SUM(D6:D35) -> 0 | F37: =SUM(F6:F35) -> 0 | H37: =SUM(H6:H35) -> 188 | I37: =SUM(I6:I35) -> 188 | L37: =SUM(L7:L35) -> 0 | Q37: =SUM(Q5:Q35) -> 0 | U37: =SUM(U6:U35) -> 8 | Y37: =SUM(Y35,Y33,Y31,Y29,Y27,Y25,Y23,Y21,Y19,Y17,Y15,Y13,Y11,Y9,Y7+#REF!) -> #REF! | AJ37: =SUM(AJ6:AJ35) -> 59 | AK37: =SUM(Y37-L37) -> #REF! | AL37: =SUM(AL6:AL35) -> 59
C38: =+C37*1.66 -> 0 | E38: =SUM(E6:E35) -> 7258.0645 | F38: =SUM(F6:F35) -> 0 | H38: 7500 | I38: =SUM('General information '!G37/WATER!I37) -> 0 | O38: =SUM(Q37+I37) -> 188 | Z38: =SUM(Y37:AJ37) -> #REF! | AK38: =SUM(Y38-L38) -> 0
B39: =9*27 -> 243 | D39: =SUM(D21:D35) -> 0 | F39: =SUM(F6:F35) -> 0 | G39: =SUM(I37) -> 188 | H39: =SUM(H38+C38) -> 7500 | K39: =SUM(H39/G39) -> 39.893617 | AJ39: =SUM(C38-AK38) -> 0 | AM39: =SUM(AJ39/AO38) -> #DIV/0!

Sheet graphic

Sheet General information 
A1: GENERAL & HOTEL'S INFORMATION SHEET
B4: Max Temp | C4: MIN TEMP | D4: AVE TEMP | E4: AVE Humidity | F4: AVE OCC | G4: # of OCC Rooms | H4: Ball room | I4: Meeting rooms | J4: Outlets | K4: Total covers | L4: # of permenant Emp | M4: # of casuals | N4: Total # of EMP | O4: # of EMP/OCC Room
A5: =ELEC!C2 -> 44104 | B5: ='[1]General information '!B36 -> 32 | C5: ='[1]General information '!C36 -> 28 | D5: ='[1]General information '!D36 -> 30 | E5: ='[1]General information '!E36 -> 0.76 | F5: ='[1]General information '!F36 -> 0 | G5: ='[1]General information '!G36 -> 0 | H5: ='[1]General information '!H36 -> 0 | I5: ='[1]General information '!I36 -> 0 | ... O5: ='[1]General information '!O36 -> 0
A6: =ELEC!C3 -> 44105 | B6: 30 | C6: 25 | D6: =(C6+B6)/2 -> 27.5 | E6: 0.66 | F6: 0 | G6: =F6*230 -> 0 | K6: =+J6+H6 -> 0
A7: =ELEC!C4 -> 44106 | B7: 30 | C7: 26 | D7: =(C7+B7)/2 -> 28 | E7: 0.65 | F7: 0 | G7: =F7*230 -> 0 | H7: 0 | I7: 0 | J7: 0 | K7: =+J7+H7 -> 0
A8: =ELEC!C5 -> 44107 | B8: 29 | C8: 24 | D8: =(C8+B8)/2 -> 26.5 | E8: 0.57 | F8: 0 | G8: =F8*230 -> 0 | K8: =+J8+H8 -> 0
A9: =ELEC!C6 -> 44108 | B9: 29 | C9: 25 | D9: =(C9+B9)/2 -> 27 | E9: 0.45 | F9: 0 | G9: =F9*230 -> 0 | K9: =+J9+H9 -> 0
A10: =ELEC!C7 -> 44109 | B10: 31 | C10: 26 | D10: =(C10+B10)/2 -> 28.5 | E10: 0.5 | F10: 0 | G10: =F10*230 -> 0 | K10: =+J10+H10 -> 0
A11: =ELEC!C8 -> 44110 | D11: =(C11+B11)/2 -> 0 | G11: =F11*230 -> 0 | K11: =+J11+H11 -> 0
A12: =ELEC!C9 -> 44111 | D12: =(C12+B12)/2 -> 0 | G12: =F12*230 -> 0 | K12: =+J12+H12 -> 0
A13: =ELEC!C10 -> 44112 | D13: =(C13+B13)/2 -> 0 | G13: =F13*230 -> 0 | K13: =+J13+H13 -> 0
A14: =ELEC!C11 -> 44113 | D14: =(C14+B14)/2 -> 0 | G14: =F14*230 -> 0 | K14: =+J14+H14 -> 0
A15: =ELEC!C12 -> 44114 | D15: =(C15+B15)/2 -> 0 | G15: =F15*230 -> 0 | K15: =+J15+H15 -> 0
A16: =ELEC!C13 -> 44115 | D16: =(C16+B16)/2 -> 0 | G16: =F16*230 -> 0 | K16: =+J16+H16 -> 0
A17: =ELEC!C14 -> 44116 | D17: =(C17+B17)/2 -> 0 | G17: =F17*230 -> 0 | K17: =+J17+H17 -> 0
A18: =ELEC!C15 -> 44117 | D18: =(C18+B18)/2 -> 0 | G18: =F18*230 -> 0 | K18: =+J18+H18 -> 0
A19: =ELEC!C16 -> 44118 | D19: =(C19+B19)/2 -> 0 | G19: 0 | K19: =+J19+H19 -> 0
A20: =ELEC!C17 -> 44119 | D20: =(C20+B20)/2 -> 0 | G20: =F20*230 -> 0 | K20: =+J20+H20 -> 0
A21: =ELEC!C18 -> 44120 | D21: =(C21+B21)/2 -> 0 | G21: =F21*230 -> 0 | K21: =+J21+H21 -> 0
A22: =ELEC!C19 -> 44121 | D22: =(C22+B22)/2 -> 0 | G22: =F22*230 -> 0 | K22: =+J22+H22 -> 0
A23: =ELEC!C20 -> 44122 | D23: =(C23+B23)/2 -> 0 | G23: =F23*230 -> 0 | K23: =+J23+H23 -> 0
A24: =ELEC!C21 -> 44123 | D24: =(C24+B24)/2 -> 0 | G24: =F24*230 -> 0 | K24: =+J24+H24 -> 0
A25: =ELEC!C22 -> 44124 | D25: =(C25+B25)/2 -> 0 | G25: =F25*230 -> 0 | K25: =+J25+H25 -> 0
A26: =ELEC!C23 -> 44125 | D26: =(C26+B26)/2 -> 0 | G26: =F26*230 -> 0 | K26: =+J26+H26 -> 0
A27: =ELEC!C24 -> 44126 | D27: =(C27+B27)/2 -> 0 | G27: =F27*230 -> 0 | K27: =+J27+H27+I27 -> 0
A28: =ELEC!C25 -> 44127 | D28: =(C28+B28)/2 -> 0 | G28: =F28*230 -> 0 | K28: =+J28+H28+I28 -> 0
A29: =ELEC!C26 -> 44128 | D29: =(C29+B29)/2 -> 0 | G29: =F29*230 -> 0 | K29: =+J29+H29+I29 -> 0
A30: =ELEC!C27 -> 44129 | D30: =(C30+B30)/2 -> 0 | G30: =F30*230 -> 0 | K30: =+J30+H30+I30 -> 0
A31: =ELEC!C28 -> 44130 | D31: =(C31+B31)/2 -> 0 | G31: =F31*230 -> 0 | K31: =+J31+H31+I31 -> 0
A32: =ELEC!C29 -> 44131 | D32: =(C32+B32)/2 -> 0 | G32: =F32*230 -> 0 | K32: =+J32+H32+I32 -> 0
A33: =ELEC!C30 -> 44132 | D33: =(C33+B33)/2 -> 0 | G33: =F33*230 -> 0 | K33: =+J33+H33+I33 -> 0
A34: =ELEC!C31 -> 44133 | D34: =(C34+B34)/2 -> 0 | G34: =F34*230 -> 0 | K34: =+J34+H34+I34 -> 0
A35: =ELEC!C32 -> 44134 | D35: =(C35+B35)/2 -> 0 | G35: =F35*230 -> 0 | K35: =+J35+H35+I35 -> 0
A36: =ELEC!C33 -> 44135 | D36: =(C36+B36)/2 -> 0 | G36: =F36*230 -> 0 | K36: =+J36+H36+I36 -> 0
F37: =AVERAGE(F6:F35) -> 0 | G37: =SUM(G6:G35) -> 0
D38: =SUM(D6:D35)/'EDl log'!A36 -> 27.5
I41: http://www.accuweather.com/en/lb/lebanon-weather

Sheet tanks
B2: Tank 1 | D2: Tank 2 | F2: Tank 3 | H2: Tank 4 | J2: Tank 5 | L2: Tank 6 | N2: Tank 7 | P2: Tank 8 | R2: Tank 9 | T2: Tank 10 | V2: Tank 11 | Z2: Tank 1 | AB2: Tank 2 | AD2: Tank 3 | AF2: Tank 4 | AH2: Tank 5 | AJ2: Tank 6 | AL2: Tank 7
B3: 6670 | D3: =SUM(B3) -> 6670 | F3: =SUM(D3) -> 6670 | H3: =SUM(F3) -> 6670 | J3: =SUM(H3) -> 6670 | L3: =SUM(J3) -> 6670 | N3: =SUM(L3) -> 6670 | P3: =SUM(N3) -> 6670 | R3: =SUM(P3) -> 6670 | T3: =SUM(R3) -> 6670 | V3: =SUM(T3) -> 6670 | W3: =SUM(B3:V3) -> 73370 | Z3: 2800 | AB3: 2800 | AD3: 2800 | AF3: 2800 | AH3: 2800 | AJ3: 2800 | AL3: 2800 | AM3: =SUM(Z3:AL3) -> 19600 | AO3: =SUM(AM3+W3) -> 92970 | AR3: Total sotck | AS3: Diesel Cons Per day | AT3: Diesel Delivery | BE3: Genset Co | BF3: Steam | BG3: Boil | BH3: Outdoor temperature
B4: =B3/310 -> 21.516129 | D4: =SUM(B4) -> 21.516129 | F4: =SUM(D4) -> 21.516129 | H4: =SUM(F4) -> 21.516129 | J4: =SUM(H4) -> 21.516129 | L4: =SUM(J4) -> 21.516129 | N4: =SUM(L4) -> 21.516129 | P4: =SUM(N4) -> 21.516129 | R4: =SUM(P4) -> 21.516129 | T4: =SUM(R4) -> 21.516129 | V4: =SUM(T4) -> 21.516129 | Z4: =Z3/280 -> 10 | AA4: =AA3/280 -> 0 | AB4: =AB3/280 -> 10 | AC4: =AC3/280 -> 0 | AD4: =AD3/280 -> 10 | AE4: =AE3/280 -> 0 | AF4: =AF3/280 -> 10 | AG4: =AG3/280 -> 0 | ... AL4: =AL3/280 -> 10 | AT4: Delivery | AU4: Cost /L | AW4: Boiler+Steam | AX4: Generator | AZ4: Occupancy | BA4: AVE TEPM | BB4: AVE Humidity
A5: =ELEC!C2 -> 44104 | B5: =[2]tanks!B35 -> 251 | C5: =[2]tanks!C35 -> 5400.5484 | D5: =[2]tanks!D35 -> 251 | E5: =[2]tanks!E35 -> 5400.5484 | F5: =[2]tanks!F35 -> 251 | G5: =[2]tanks!G35 -> 5400.5484 | H5: =[2]tanks!H35 -> 251 | I5: =[2]tanks!I35 -> 5400.5484 | ... BG5: =[2]tanks!BG35 -> #REF! | BH5: =[3]tanks!BH36 -> 0
A6: =ELEC!C3 -> 44105 | B6: ='B5'!B5 -> 249 | C6: =B6*$B$4 -> 5357.5161 | D6: =SUM(B6) -> 249 | E6: =D6*$B$4 -> 5357.5161 | F6: =SUM(D6) -> 249 | G6: =F6*$B$4 -> 5357.5161 | H6: =SUM(F6) -> 249 | I6: =H6*$B$4 -> 5357.5161 | J6: =SUM(H6) -> 249 | K6: =J6*$B$4 -> 5357.5161 | L6: =SUM(J6) -> 249 | M6: =L6*$B$4 -> 5357.5161 | N6: =SUM(L6) -> 249 | O6: =N6*$B$4 -> 5357.5161 | P6: =SUM(N6) -> 249 | Q6: =P6*$B$4 -> 5357.5161 | R6: =SUM(P6) -> 249 | S6: =R6*$B$4 -> 5357.5161 | T6: =SUM(R6) -> 249 | U6: =T6*$B$4 -> 5357.5161 | V6: =SUM(T6) -> 249 | W6: =V6*$B$4 -> 5357.5161 | X6: =SUM(Y6/73370) -> 0.80322581 | Y6: =SUM(C6+E6+G6+I6+K6+M6+O6+Q6+S6+U6+W6) -> 58932.677 | Z6: ='B5'!C5 -> 255 | AA6: =SUM(Z6*$Z$4) -> 2550 | AB6: =SUM(Z6) -> 255 | AC6: =SUM(AB6*$Z$4) -> 2550 | AD6: =SUM(AB6) -> 255 | AE6: =SUM(AD6*$Z$4) -> 2550 | AF6: =SUM(AD6) -> 255 | AG6: =SUM(AF6*$Z$4) -> 2550 | AH6: =SUM(AF6) -> 255 | AI6: =SUM(AH6*$Z$4) -> 2550 | AJ6: =SUM(AH6) -> 255 | AK6: =SUM(AJ6*$Z$4) -> 2550 | AL6: =SUM(AJ6) -> 255 | AM6: =SUM(AL6*$Z$4) -> 2550 | AN6: =SUM(AO6/19600) -> 0.91071429 | AO6: =SUM(AA6+AC6+AE6+AG6+AI6+AK6+AM6) -> 17850 | AQ6: =SUM(AR6/92970) -> 0.8258866 | AR6: =SUM(AO6+Y6) -> 76782.677 | AS6: =SUM(AR6-AR5-AT6) -> -614.35484 | AT6: 1 | AV6: =IF(AT6>0,AU6,AV5) -> 0 | AW6: =-SUM('B5'!AI5) -> -1.8 | AX6: =-SUM(AW6-AS6) -> -612.55484 | AY6: =SUM(AX6+AW6) -> -614.35484 | AZ6: =ELEC!A3 -> 0 | BA6: ='General information '!D6 -> 27.5 | BB6: =SUM('General information '!E6) -> 0.66 | BC6: =IF(AR3>=AR6,0,1) -> 0 | BD6: 19222 | BE6: =(305/1185)*ELEC!Q4 -> 0 | BG6: =#REF!-BE6 -> #REF! | BH6: 21
A7: =ELEC!C4 -> 44106 | B7: ='B5'!B6 -> 248 | C7: =B7*$B$4 -> 5336 | D7: =SUM(B7) -> 248 | E7: =D7*$B$4 -> 5336 | F7: =SUM(D7) -> 248 | G7: =F7*$B$4 -> 5336 | H7: =SUM(F7) -> 248 | I7: =H7*$B$4 -> 5336 | J7: =SUM(H7) -> 248 | K7: =J7*$B$4 -> 5336 | L7: =SUM(J7) -> 248 | M7: =L7*$B$4 -> 5336 | N7: =SUM(L7) -> 248 | O7: =N7*$B$4 -> 5336 | P7: =SUM(N7) -> 248 | Q7: =P7*$B$4 -> 5336 | R7: =SUM(P7) -> 248 | S7: =R7*$B$4 -> 5336 | T7: =SUM(R7) -> 248 | U7: =T7*$B$4 -> 5336 | V7: =SUM(T7) -> 248 | W7: =V7*$B$4 -> 5336 | X7: =SUM(Y7/73370) -> 0.8 | Y7: =SUM(C7+E7+G7+I7+K7+M7+O7+Q7+S7+U7+W7) -> 58696 | Z7: ='B5'!C6 -> 254.5 | AA7: =SUM(Z7*$Z$4) -> 2545 | AB7: =SUM(Z7) -> 254.5 | AC7: =SUM(AB7*$Z$4) -> 2545 | AD7: =SUM(AB7) -> 254.5 | AE7: =SUM(AD7*$Z$4) -> 2545 | AF7: =SUM(AD7) -> 254.5 | AG7: =SUM(AF7*$Z$4) -> 2545 | AH7: =SUM(AF7) -> 254.5 | AI7: =SUM(AH7*$Z$4) -> 2545 | AJ7: =SUM(AH7) -> 254.5 | AK7: =SUM(AJ7*$Z$4) -> 2545 | AL7: =SUM(AJ7) -> 254.5 | AM7: =SUM(AL7*$Z$4) -> 2545 | AN7: =SUM(AO7/19600) -> 0.90892857 | AO7: =SUM(AA7+AC7+AE7+AG7+AI7+AK7+AM7) -> 17815 | AQ7: =SUM(AR7/92970) -> 0.8229644 | AR7: =SUM(AO7+Y7) -> 76511 | AS7: =SUM(AR7-AR6-AT7) -> -271.67742 | AV7: =IF(AT7>0,AU7,AV6) -> 0 | AW7: =-SUM('B5'!AI6) -> -232 | AX7: =-SUM(AW7-AS7) -> -39.677419 | AY7: =SUM(AX7+AW7) -> -271.67742 | AZ7: =ELEC!A4 -> 0 | BA7: ='General information '!D7 -> 28 | BB7: =SUM('General information '!E7) -> 0.65 | BC7: 0 | BD7: 19222 | BE7: =(305/1185)*ELEC!Q5 -> 257.38397 | BG7: =#REF!-BE7 -> #REF! | BH7: 19
A8: =ELEC!C5 -> 44107 | B8: ='B5'!B7 -> 246.5 | C8: =B8*$B$4 -> 5303.7258 | D8: =SUM(B8) -> 246.5 | E8: =D8*$B$4 -> 5303.7258 | F8: =SUM(D8) -> 246.5 | G8: =F8*$B$4 -> 5303.7258 | H8: =SUM(F8) -> 246.5 | I8: =H8*$B$4 -> 5303.7258 | J8: =SUM(H8) -> 246.5 | K8: =J8*$B$4 -> 5303.7258 | L8: =SUM(J8) -> 246.5 | M8: =L8*$B$4 -> 5303.7258 | N8: =SUM(L8) -> 246.5 | O8: =N8*$B$4 -> 5303.7258 | P8: =SUM(N8) -> 246.5 | Q8: =P8*$B$4 -> 5303.7258 | R8: =SUM(P8) -> 246.5 | S8: =R8*$B$4 -> 5303.7258 | T8: =SUM(R8) -> 246.5 | U8: =T8*$B$4 -> 5303.7258 | V8: =SUM(T8) -> 246.5 | W8: =V8*$B$4 -> 5303.7258 | X8: =SUM(Y8/73370) -> 0.79516129 | Y8: =SUM(C8+E8+G8+I8+K8+M8+O8+Q8+S8+U8+W8) -> 58340.984 | Z8: ='B5'!C7 -> 251.2 | AA8: =SUM(Z8*$Z$4) -> 2512 | AB8: =SUM(Z8) -> 251.2 | AC8: =SUM(AB8*$Z$4) -> 2512 | AD8: =SUM(AB8) -> 251.2 | AE8: =SUM(AD8*$Z$4) -> 2512 | AF8: =SUM(AD8) -> 251.2 | AG8: =SUM(AF8*$Z$4) -> 2512 | AH8: =SUM(AF8) -> 251.2 | AI8: =SUM(AH8*$Z$4) -> 2512 | AJ8: =SUM(AH8) -> 251.2 | AK8: =SUM(AJ8*$Z$4) -> 2512 | AL8: =SUM(AJ8) -> 251.2 | AM8: =SUM(AL8*$Z$4) -> 2512 | AN8: =SUM(AO8/19600) -> 0.89714286 | AO8: =SUM(AA8+AC8+AE8+AG8+AI8+AK8+AM8) -> 17584 | AQ8: =SUM(AR8/92970) -> 0.81666112 | AR8: =SUM(AO8+Y8) -> 75924.984 | AS8: =SUM(AR8-AR7-AT8) -> -586.01613 | AV8: =IF(AT8>0,AU8,AV7) -> 0 | AW8: =-SUM('B5'!AI7) -> -116 | AX8: =-SUM(AW8-AS8) -> -470.01613 | AY8: =SUM(AX8+AW8) -> -586.01613 | AZ8: =ELEC!A5 -> 0 | BA8: ='General information '!D8 -> 26.5 | BB8: =SUM('General information '!E8) -> 0.57 | BC8: =IF(AR7>=AR8,0,1) -> 0 | BD8: 19222 | BE8: =(305/1185)*ELEC!Q6 -> 514.76793 | BG8: =#REF!-BE8 -> #REF! | BH8: 16
A9: =ELEC!C6 -> 44108 | B9: ='B5'!B8 -> 244 | C9: =B9*$B$4 -> 5249.9355 | D9: =SUM(B9) -> 244 | E9: =D9*$B$4 -> 5249.9355 | F9: =SUM(D9) -> 244 | G9: =F9*$B$4 -> 5249.9355 | H9: =SUM(F9) -> 244 | I9: =H9*$B$4 -> 5249.9355 | J9: =SUM(H9) -> 244 | K9: =J9*$B$4 -> 5249.9355 | L9: =SUM(J9) -> 244 | M9: =L9*$B$4 -> 5249.9355 | N9: =SUM(L9) -> 244 | O9: =N9*$B$4 -> 5249.9355 | P9: =SUM(N9) -> 244 | Q9: =P9*$B$4 -> 5249.9355 | R9: =SUM(P9) -> 244 | S9: =R9*$B$4 -> 5249.9355 | T9: =SUM(R9) -> 244 | U9: =T9*$B$4 -> 5249.9355 | V9: =SUM(T9) -> 244 | W9: =V9*$B$4 -> 5249.9355 | X9: =SUM(Y9/73370) -> 0.78709677 | Y9: =SUM(C9+E9+G9+I9+K9+M9+O9+Q9+S9+U9+W9) -> 57749.29 | Z9: ='B5'!C8 -> 249 | AA9: =SUM(Z9*$Z$4) -> 2490 | AB9: =SUM(Z9) -> 249 | AC9: =SUM(AB9*$Z$4) -> 2490 | AD9: =SUM(AB9) -> 249 | AE9: =SUM(AD9*$Z$4) -> 2490 | AF9: =SUM(AD9) -> 249 | AG9: =SUM(AF9*$Z$4) -> 2490 | AH9: =SUM(AF9) -> 249 | AI9: =SUM(AH9*$Z$4) -> 2490 | AJ9: =SUM(AH9) -> 249 | AK9: =SUM(AJ9*$Z$4) -> 2490 | AL9: =SUM(AJ9) -> 249 | AM9: =SUM(AL9*$Z$4) -> 2490 | AN9: =SUM(AO9/19600) -> 0.88928571 | AO9: =SUM(AA9+AC9+AE9+AG9+AI9+AK9+AM9) -> 17430 | AQ9: =SUM(AR9/92970) -> 0.80864032 | AR9: =SUM(AO9+Y9) -> 75179.29 | AS9: =SUM(AR9-AR8-AT9) -> -745.69355 | AV9: =IF(AT9>0,AU9,AV8) -> 0 | AW9: =-SUM('B5'!AI8) -> -53 | AX9: =-SUM(AW9-AS9) -> -692.69355 | AY9: =SUM(AX9+AW9) -> -745.69355 | AZ9: =ELEC!A6 -> 0 | BA9: ='General information '!D9 -> 27 | BB9: =SUM('General information '!E9) -> 0.45 | BC9: =IF(AR8>=AR9,0,1) -> 0 | BD9: 19222 | BE9: =(305/1185)*ELEC!Q7 -> 514.76793 | BG9: =#REF!-BE9 -> #REF! | BH9: 18
A10: =ELEC!C7 -> 44109 | B10: ='B5'!B9 -> 242 | C10: =B10*$B$4 -> 5206.9032 | D10: =SUM(B10) -> 242 | E10: =D10*$B$4 -> 5206.9032 | F10: =SUM(D10) -> 242 | G10: =F10*$B$4 -> 5206.9032 | H10: =SUM(F10) -> 242 | I10: =H10*$B$4 -> 5206.9032 | J10: =SUM(H10) -> 242 | K10: =J10*$B$4 -> 5206.9032 | L10: =SUM(J10) -> 242 | M10: =L10*$B$4 -> 5206.9032 | N10: =SUM(L10) -> 242 | O10: =N10*$B$4 -> 5206.9032 | P10: =SUM(N10) -> 242 | Q10: =P10*$B$4 -> 5206.9032 | R10: =SUM(P10) -> 242 | S10: =R10*$B$4 -> 5206.9032 | T10: =SUM(R10) -> 242 | U10: =T10*$B$4 -> 5206.9032 | V10: =SUM(T10) -> 242 | W10: =V10*$B$4 -> 5206.9032 | X10: =SUM(Y10/73370) -> 0.78064516 | Y10: =SUM(C10+E10+G10+I10+K10+M10+O10+Q10+S10+U10+W10) -> 57275.935 | Z10: ='B5'!C9 -> 247.3 | AA10: =SUM(Z10*$Z$4) -> 2473 | AB10: =SUM(Z10) -> 247.3 | AC10: =SUM(AB10*$Z$4) -> 2473 | AD10: =SUM(AB10) -> 247.3 | AE10: =SUM(AD10*$Z$4) -> 2473 | AF10: =SUM(AD10) -> 247.3 | AG10: =SUM(AF10*$Z$4) -> 2473 | AH10: =SUM(AF10) -> 247.3 | AI10: =SUM(AH10*$Z$4) -> 2473 | AJ10: =SUM(AH10) -> 247.3 | AK10: =SUM(AJ10*$Z$4) -> 2473 | AL10: =SUM(AJ10) -> 247.3 | AM10: =SUM(AL10*$Z$4) -> 2473 | AN10: =SUM(AO10/19600) -> 0.88321429 | AO10: =SUM(AA10+AC10+AE10+AG10+AI10+AK10+AM10) -> 17311 | AQ10: =SUM(AR10/92970) -> 0.80226886 | AR10: =SUM(AO10+Y10) -> 74586.935 | AS10: =SUM(AR10-AR9-AT10) -> -592.35484 | AV10: =IF(AT10>0,AU10,AV9) -> 0 | AW10: =-SUM('B5'!AI9) -> -96 | AX10: =-SUM(AW10-AS10) -> -496.35484 | AY10: =SUM(AX10+AW10) -> -592.35484 | AZ10: =ELEC!A7 -> 0 | BA10: ='General information '!D10 -> 28.5 | BB10: =SUM('General information '!E10) -> 0.5 | BC10: =IF(AR9>=AR10,0,1) -> 0 | BD10: 19222 | BE10: =(305/1185)*ELEC!Q8 -> 0 | BG10: =#REF!-BE10 -> #REF! | BH10: 16
A11: =ELEC!C8 -> 44110 | B11: ='B5'!B10 -> 242 | C11: =B11*$B$4 -> 5206.9032 | D11: =SUM(B11) -> 242 | E11: =D11*$B$4 -> 5206.9032 | F11: =SUM(D11) -> 242 | G11: =F11*$B$4 -> 5206.9032 | H11: =SUM(F11) -> 242 | I11: =H11*$B$4 -> 5206.9032 | J11: =SUM(H11) -> 242 | K11: =J11*$B$4 -> 5206.9032 | L11: =SUM(J11) -> 242 | M11: =L11*$B$4 -> 5206.9032 | N11: =SUM(L11) -> 242 | O11: =N11*$B$4 -> 5206.9032 | P11: =SUM(N11) -> 242 | Q11: =P11*$B$4 -> 5206.9032 | R11: =SUM(P11) -> 242 | S11: =R11*$B$4 -> 5206.9032 | T11: =SUM(R11) -> 242 | U11: =T11*$B$4 -> 5206.9032 | V11: =SUM(T11) -> 242 | W11: =V11*$B$4 -> 5206.9032 | X11: =SUM(Y11/73370) -> 0.78064516 | Y11: =SUM(C11+E11+G11+I11+K11+M11+O11+Q11+S11+U11+W11) -> 57275.935 | Z11: ='B5'!C10 -> 247.3 | AA11: =SUM(Z11*$Z$4) -> 2473 | AB11: =SUM(Z11) -> 247.3 | AC11: =SUM(AB11*$Z$4) -> 2473 | AD11: =SUM(AB11) -> 247.3 | AE11: =SUM(AD11*$Z$4) -> 2473 | AF11: =SUM(AD11) -> 247.3 | AG11: =SUM(AF11*$Z$4) -> 2473 | AH11: =SUM(AF11) -> 247.3 | AI11: =SUM(AH11*$Z$4) -> 2473 | AJ11: =SUM(AH11) -> 247.3 | AK11: =SUM(AJ11*$Z$4) -> 2473 | AL11: =SUM(AJ11) -> 247.3 | AM11: =SUM(AL11*$Z$4) -> 2473 | AN11: =SUM(AO11/19600) -> 0.88321429 | AO11: =SUM(AA11+AC11+AE11+AG11+AI11+AK11+AM11) -> 17311 | AQ11: =SUM(AR11/92970) -> 0.80226886 | AR11: =SUM(AO11+Y11) -> 74586.935 | AS11: =SUM(AR11-AR10-AT11) -> 0 | AV11: =IF(AT11>0,AU11,AV10) -> 0 | AW11: =-SUM('B5'!AI10) -> 0 | AX11: =-SUM(AW11-AS11) -> 0 | AY11: =SUM(AX11+AW11) -> 0 | AZ11: =ELEC!A8 -> 0 | BA11: ='General information '!D11 -> 0 | BB11: =SUM('General information '!E11) -> 0 | BC11: =IF(AR10>=AR11,0,1) -> 0 | BD11: 19222 | BE11: =(305/1185)*ELEC!Q9 -> 0 | BG11: =#REF!-BE11 -> #REF! | BH11: 16.5
A12: =ELEC!C9 -> 44111 | B12: ='B5'!B11 -> 242 | C12: =B12*$B$4 -> 5206.9032 | D12: =SUM(B12) -> 242 | E12: =D12*$B$4 -> 5206.9032 | F12: =SUM(D12) -> 242 | G12: =F12*$B$4 -> 5206.9032 | H12: =SUM(F12) -> 242 | I12: =H12*$B$4 -> 5206.9032 | J12: =SUM(H12) -> 242 | K12: =J12*$B$4 -> 5206.9032 | L12: =SUM(J12) -> 242 | M12: =L12*$B$4 -> 5206.9032 | N12: =SUM(L12) -> 242 | O12: =N12*$B$4 -> 5206.9032 | P12: =SUM(N12) -> 242 | Q12: =P12*$B$4 -> 5206.9032 | R12: =SUM(P12) -> 242 | S12: =R12*$B$4 -> 5206.9032 | T12: =SUM(R12) -> 242 | U12: =T12*$B$4 -> 5206.9032 | V12: =SUM(T12) -> 242 | W12: =V12*$B$4 -> 5206.9032 | X12: =SUM(Y12/73370) -> 0.78064516 | Y12: =SUM(C12+E12+G12+I12+K12+M12+O12+Q12+S12+U12+W12) -> 57275.935 | Z12: ='B5'!C11 -> 247.3 | AA12: =SUM(Z12*$Z$4) -> 2473 | AB12: =SUM(Z12) -> 247.3 | AC12: =SUM(AB12*$Z$4) -> 2473 | AD12: =SUM(AB12) -> 247.3 | AE12: =SUM(AD12*$Z$4) -> 2473 | AF12: =SUM(AD12) -> 247.3 | AG12: =SUM(AF12*$Z$4) -> 2473 | AH12: =SUM(AF12) -> 247.3 | AI12: =SUM(AH12*$Z$4) -> 2473 | AJ12: =SUM(AH12) -> 247.3 | AK12: =SUM(AJ12*$Z$4) -> 2473 | AL12: =SUM(AJ12) -> 247.3 | AM12: =SUM(AL12*$Z$4) -> 2473 | AN12: =SUM(AO12/19600) -> 0.88321429 | AO12: =SUM(AA12+AC12+AE12+AG12+AI12+AK12+AM12) -> 17311 | AQ12: =SUM(AR12/92970) -> 0.80226886 | AR12: =SUM(AO12+Y12) -> 74586.935 | AS12: =SUM(AR12-AR11-AT12) -> 0 | AV12: =IF(AT12>0,AU12,AV11) -> 0 | AW12: =-SUM('B5'!AI11) -> 0 | AX12: =-SUM(AW12-AS12) -> 0 | AY12: =SUM(AX12+AW12) -> 0 | AZ12: =ELEC!A9 -> 0 | BA12: ='General information '!D12 -> 0 | BB12: =SUM('General information '!E12) -> 0 | BC12: =IF(AR11>=AR12,0,1) -> 0 | BD12: 19222 | BE12: =(305/1185)*ELEC!Q10 -> 0 | BG12: =#REF!-BE12 -> #REF! | BH12: 15.5
A13: =ELEC!C10 -> 44112 | B13: ='B5'!B12 -> 242 | C13: =B13*$B$4 -> 5206.9032 | D13: =SUM(B13) -> 242 | E13: =D13*$B$4 -> 5206.9032 | F13: =SUM(D13) -> 242 | G13: =F13*$B$4 -> 5206.9032 | H13: =SUM(F13) -> 242 | I13: =H13*$B$4 -> 5206.9032 | J13: =SUM(H13) -> 242 | K13: =J13*$B$4 -> 5206.9032 | L13: =SUM(J13) -> 242 | M13: =L13*$B$4 -> 5206.9032 | N13: =SUM(L13) -> 242 | O13: =N13*$B$4 -> 5206.9032 | P13: =SUM(N13) -> 242 | Q13: =P13*$B$4 -> 5206.9032 | R13: =SUM(P13) -> 242 | S13: =R13*$B$4 -> 5206.9032 | T13: =SUM(R13) -> 242 | U13: =T13*$B$4 -> 5206.9032 | V13: =SUM(T13) -> 242 | W13: =V13*$B$4 -> 5206.9032 | X13: =SUM(Y13/73370) -> 0.78064516 | Y13: =SUM(C13+E13+G13+I13+K13+M13+O13+Q13+S13+U13+W13) -> 57275.935 | Z13: ='B5'!C12 -> 247.3 | AA13: =SUM(Z13*$Z$4) -> 2473 | AB13: =SUM(Z13) -> 247.3 | AC13: =SUM(AB13*$Z$4) -> 2473 | AD13: =SUM(AB13) -> 247.3 | AE13: =SUM(AD13*$Z$4) -> 2473 | AF13: =SUM(AD13) -> 247.3 | AG13: =SUM(AF13*$Z$4) -> 2473 | AH13: =SUM(AF13) -> 247.3 | AI13: =SUM(AH13*$Z$4) -> 2473 | AJ13: =SUM(AH13) -> 247.3 | AK13: =SUM(AJ13*$Z$4) -> 2473 | AL13: =SUM(AJ13) -> 247.3 | AM13: =SUM(AL13*$Z$4) -> 2473 | AN13: =SUM(AO13/19600) -> 0.88321429 | AO13: =SUM(AA13+AC13+AE13+AG13+AI13+AK13+AM13) -> 17311 | AQ13: =SUM(AR13/92970) -> 0.80226886 | AR13: =SUM(AO13+Y13) -> 74586.935 | AS13: =SUM(AR13-AR12-AT13) -> 0 | AV13: =IF(AT13>0,AU13,AV12) -> 0 | AW13: =-SUM('B5'!AI12) -> 0 | AX13: =-SUM(AW13-AS13) -> 0 | AY13: =SUM(AX13+AW13) -> 0 | AZ13: =ELEC!A10 -> 0 | BA13: ='General information '!D13 -> 0 | BB13: =SUM('General information '!E13) -> 0 | BC13: =IF(AR12>=AR13,0,1) -> 0 | BD13: 19222 | BE13: =(305/1185)*ELEC!Q11 -> 0 | BG13: =#REF!-BE13 -> #REF!
A14: =ELEC!C11 -> 44113 | B14: ='B5'!B13 -> 242 | C14: =B14*$B$4 -> 5206.9032 | D14: =SUM(B14) -> 242 | E14: =D14*$B$4 -> 5206.9032 | F14: =SUM(D14) -> 242 | G14: =F14*$B$4 -> 5206.9032 | H14: =SUM(F14) -> 242 | I14: =H14*$B$4 -> 5206.9032 | J14: =SUM(H14) -> 242 | K14: =J14*$B$4 -> 5206.9032 | L14: =SUM(J14) -> 242 | M14: =L14*$B$4 -> 5206.9032 | N14: =SUM(L14) -> 242 | O14: =N14*$B$4 -> 5206.9032 | P14: =SUM(N14) -> 242 | Q14: =P14*$B$4 -> 5206.9032 | R14: =SUM(P14) -> 242 | S14: =R14*$B$4 -> 5206.9032 | T14: =SUM(R14) -> 242 | U14: =T14*$B$4 -> 5206.9032 | V14: =SUM(T14) -> 242 | W14: =V14*$B$4 -> 5206.9032 | X14: =SUM(Y14/73370) -> 0.78064516 | Y14: =SUM(C14+E14+G14+I14+K14+M14+O14+Q14+S14+U14+W14) -> 57275.935 | Z14: ='B5'!C13 -> 247.3 | AA14: =SUM(Z14*$Z$4) -> 2473 | AB14: =SUM(Z14) -> 247.3 | AC14: =SUM(AB14*$Z$4) -> 2473 | AD14: =SUM(AB14) -> 247.3 | AE14: =SUM(AD14*$Z$4) -> 2473 | AF14: =SUM(AD14) -> 247.3 | AG14: =SUM(AF14*$Z$4) -> 2473 | AH14: =SUM(AF14) -> 247.3 | AI14: =SUM(AH14*$Z$4) -> 2473 | AJ14: =SUM(AH14) -> 247.3 | AK14: =SUM(AJ14*$Z$4) -> 2473 | AL14: =SUM(AJ14) -> 247.3 | AM14: =SUM(AL14*$Z$4) -> 2473 | AN14: =SUM(AO14/19600) -> 0.88321429 | AO14: =SUM(AA14+AC14+AE14+AG14+AI14+AK14+AM14) -> 17311 | AQ14: =SUM(AR14/92970) -> 0.80226886 | AR14: =SUM(AO14+Y14) -> 74586.935 | AS14: =SUM(AR14-AR13-AT14) -> 0 | AV14: =IF(AT14>0,AU14,AV13) -> 0 | AW14: =-SUM('B5'!AI13) -> 0 | AX14: =-SUM(AW14-AS14) -> 0 | AY14: =SUM(AX14+AW14) -> 0 | AZ14: =ELEC!A11 -> 0 | BA14: ='General information '!D14 -> 0 | BB14: =SUM('General information '!E14) -> 0 | BC14: =IF(AR13>=AR14,0,1) -> 0 | BD14: 19222 | BE14: =(305/1185)*ELEC!Q12 -> 0 | BG14: =#REF!-BE14 -> #REF!
A15: =ELEC!C12 -> 44114 | B15: ='B5'!B14 -> 242 | C15: =B15*$B$4 -> 5206.9032 | D15: =SUM(B15) -> 242 | E15: =D15*$B$4 -> 5206.9032 | F15: =SUM(D15) -> 242 | G15: =F15*$B$4 -> 5206.9032 | H15: =SUM(F15) -> 242 | I15: =H15*$B$4 -> 5206.9032 | J15: =SUM(H15) -> 242 | K15: =J15*$B$4 -> 5206.9032 | L15: =SUM(J15) -> 242 | M15: =L15*$B$4 -> 5206.9032 | N15: =SUM(L15) -> 242 | O15: =N15*$B$4 -> 5206.9032 | P15: =SUM(N15) -> 242 | Q15: =P15*$B$4 -> 5206.9032 | R15: =SUM(P15) -> 242 | S15: =R15*$B$4 -> 5206.9032 | T15: =SUM(R15) -> 242 | U15: =T15*$B$4 -> 5206.9032 | V15: =SUM(T15) -> 242 | W15: =V15*$B$4 -> 5206.9032 | X15: =SUM(Y15/73370) -> 0.78064516 | Y15: =SUM(C15+E15+G15+I15+K15+M15+O15+Q15+S15+U15+W15) -> 57275.935 | Z15: ='B5'!C14 -> 247.3 | AA15: =SUM(Z15*$Z$4) -> 2473 | AB15: =SUM(Z15) -> 247.3 | AC15: =SUM(AB15*$Z$4) -> 2473 | AD15: =SUM(AB15) -> 247.3 | AE15: =SUM(AD15*$Z$4) -> 2473 | AF15: =SUM(AD15) -> 247.3 | AG15: =SUM(AF15*$Z$4) -> 2473 | AH15: =SUM(AF15) -> 247.3 | AI15: =SUM(AH15*$Z$4) -> 2473 | AJ15: =SUM(AH15) -> 247.3 | AK15: =SUM(AJ15*$Z$4) -> 2473 | AL15: =SUM(AJ15) -> 247.3 | AM15: =SUM(AL15*$Z$4) -> 2473 | AN15: =SUM(AO15/19600) -> 0.88321429 | AO15: =SUM(AA15+AC15+AE15+AG15+AI15+AK15+AM15) -> 17311 | AQ15: =SUM(AR15/92970) -> 0.80226886 | AR15: =SUM(AO15+Y15) -> 74586.935 | AS15: =SUM(AR15-AR14-AT15) -> 0 | AV15: =IF(AT15>0,AU15,AV14) -> 0 | AW15: =-SUM('B5'!AI14) -> 0 | AX15: =-SUM(AW15-AS15) -> 0 | AY15: =SUM(AX15+AW15) -> 0 | AZ15: =ELEC!A12 -> 0 | BA15: ='General information '!D15 -> 0 | BB15: =SUM('General information '!E15) -> 0 | BC15: =IF(AR14>=AR15,0,1) -> 0 | BD15: 19222 | BE15: =(305/1185)*ELEC!Q13 -> 0 | BG15: =#REF!-BE15 -> #REF!
A16: =ELEC!C13 -> 44115 | B16: ='B5'!B15 -> 242 | C16: =B16*$B$4 -> 5206.9032 | D16: =SUM(B16) -> 242 | E16: =D16*$B$4 -> 5206.9032 | F16: =SUM(D16) -> 242 | G16: =F16*$B$4 -> 5206.9032 | H16: =SUM(F16) -> 242 | I16: =H16*$B$4 -> 5206.9032 | J16: =SUM(H16) -> 242 | K16: =J16*$B$4 -> 5206.9032 | L16: =SUM(J16) -> 242 | M16: =L16*$B$4 -> 5206.9032 | N16: =SUM(L16) -> 242 | O16: =N16*$B$4 -> 5206.9032 | P16: =SUM(N16) -> 242 | Q16: =P16*$B$4 -> 5206.9032 | R16: =SUM(P16) -> 242 | S16: =R16*$B$4 -> 5206.9032 | T16: =SUM(R16) -> 242 | U16: =T16*$B$4 -> 5206.9032 | V16: =SUM(T16) -> 242 | W16: =V16*$B$4 -> 5206.9032 | X16: =SUM(Y16/73370) -> 0.78064516 | Y16: =SUM(C16+E16+G16+I16+K16+M16+O16+Q16+S16+U16+W16) -> 57275.935 | Z16: ='B5'!C15 -> 247.3 | AA16: =SUM(Z16*$Z$4) -> 2473 | AB16: =SUM(Z16) -> 247.3 | AC16: =SUM(AB16*$Z$4) -> 2473 | AD16: =SUM(AB16) -> 247.3 | AE16: =SUM(AD16*$Z$4) -> 2473 | AF16: =SUM(AD16) -> 247.3 | AG16: =SUM(AF16*$Z$4) -> 2473 | AH16: =SUM(AF16) -> 247.3 | AI16: =SUM(AH16*$Z$4) -> 2473 | AJ16: =SUM(AH16) -> 247.3 | AK16: =SUM(AJ16*$Z$4) -> 2473 | AL16: =SUM(AJ16) -> 247.3 | AM16: =SUM(AL16*$Z$4) -> 2473 | AN16: =SUM(AO16/19600) -> 0.88321429 | AO16: =SUM(AA16+AC16+AE16+AG16+AI16+AK16+AM16) -> 17311 | AQ16: =SUM(AR16/92970) -> 0.80226886 | AR16: =SUM(AO16+Y16) -> 74586.935 | AS16: =SUM(AR16-AR15-AT16) -> 0 | AV16: =IF(AT16>0,AU16,AV15) -> 0 | AW16: =-SUM('B5'!AI15) -> 0 | AX16: =-SUM(AW16-AS16) -> 0 | AY16: =SUM(AX16+AW16) -> 0 | AZ16: =ELEC!A13 -> 0 | BA16: ='General information '!D16 -> 0 | BB16: =SUM('General information '!E16) -> 0 | BC16: =IF(AR15>=AR16,0,1) -> 0 | BD16: 19222 | BE16: =(305/1185)*ELEC!Q14 -> 0 | BG16: =#REF!-BE16 -> #REF!
A17: =ELEC!C14 -> 44116 | B17: ='B5'!B16 -> 242 | C17: =B17*$B$4 -> 5206.9032 | D17: =SUM(B17) -> 242 | E17: =D17*$B$4 -> 5206.9032 | F17: =SUM(D17) -> 242 | G17: =F17*$B$4 -> 5206.9032 | H17: =SUM(F17) -> 242 | I17: =H17*$B$4 -> 5206.9032 | J17: =SUM(H17) -> 242 | K17: =J17*$B$4 -> 5206.9032 | L17: =SUM(J17) -> 242 | M17: =L17*$B$4 -> 5206.9032 | N17: =SUM(L17) -> 242 | O17: =N17*$B$4 -> 5206.9032 | P17: =SUM(N17) -> 242 | Q17: =P17*$B$4 -> 5206.9032 | R17: =SUM(P17) -> 242 | S17: =R17*$B$4 -> 5206.9032 | T17: =SUM(R17) -> 242 | U17: =T17*$B$4 -> 5206.9032 | V17: =SUM(T17) -> 242 | W17: =V17*$B$4 -> 5206.9032 | X17: =SUM(Y17/73370) -> 0.78064516 | Y17: =SUM(C17+E17+G17+I17+K17+M17+O17+Q17+S17+U17+W17) -> 57275.935 | Z17: ='B5'!C16 -> 247.3 | AA17: =SUM(Z17*$Z$4) -> 2473 | AB17: =SUM(Z17) -> 247.3 | AC17: =SUM(AB17*$Z$4) -> 2473 | AD17: =SUM(AB17) -> 247.3 | AE17: =SUM(AD17*$Z$4) -> 2473 | AF17: =SUM(AD17) -> 247.3 | AG17: =SUM(AF17*$Z$4) -> 2473 | AH17: =SUM(AF17) -> 247.3 | AI17: =SUM(AH17*$Z$4) -> 2473 | AJ17: =SUM(AH17) -> 247.3 | AK17: =SUM(AJ17*$Z$4) -> 2473 | AL17: =SUM(AJ17) -> 247.3 | AM17: =SUM(AL17*$Z$4) -> 2473 | AN17: =SUM(AO17/19600) -> 0.88321429 | AO17: =SUM(AA17+AC17+AE17+AG17+AI17+AK17+AM17) -> 17311 | AQ17: =SUM(AR17/92970) -> 0.80226886 | AR17: =SUM(AO17+Y17) -> 74586.935 | AS17: =SUM(AR17-AR16-AT17) -> 0 | AV17: =IF(AT17>0,AU17,AV16) -> 0 | AW17: =-SUM('B5'!AI16) -> 0 | AX17: =-SUM(AW17-AS17) -> 0 | AY17: =SUM(AX17+AW17) -> 0 | AZ17: =ELEC!A14 -> 0 | BA17: ='General information '!D17 -> 0 | BB17: =SUM('General information '!E17) -> 0 | BC17: =IF(AR16>=AR17,0,1) -> 0 | BD17: 19222 | BE17: =(305/1185)*ELEC!Q15 -> 0 | BG17: =#REF!-BE17 -> #REF!
A18: =ELEC!C15 -> 44117 | B18: ='B5'!B17 -> 242 | C18: =B18*$B$4 -> 5206.9032 | D18: =SUM(B18) -> 242 | E18: =D18*$B$4 -> 5206.9032 | F18: =SUM(D18) -> 242 | G18: =F18*$B$4 -> 5206.9032 | H18: =SUM(F18) -> 242 | I18: =H18*$B$4 -> 5206.9032 | J18: =SUM(H18) -> 242 | K18: =J18*$B$4 -> 5206.9032 | L18: =SUM(J18) -> 242 | M18: =L18*$B$4 -> 5206.9032 | N18: =SUM(L18) -> 242 | O18: =N18*$B$4 -> 5206.9032 | P18: =SUM(N18) -> 242 | Q18: =P18*$B$4 -> 5206.9032 | R18: =SUM(P18) -> 242 | S18: =R18*$B$4 -> 5206.9032 | T18: =SUM(R18) -> 242 | U18: =T18*$B$4 -> 5206.9032 | V18: =SUM(T18) -> 242 | W18: =V18*$B$4 -> 5206.9032 | X18: =SUM(Y18/73370) -> 0.78064516 | Y18: =SUM(C18+E18+G18+I18+K18+M18+O18+Q18+S18+U18+W18) -> 57275.935 | Z18: ='B5'!C17 -> 247.3 | AA18: =SUM(Z18*$Z$4) -> 2473 | AB18: =SUM(Z18) -> 247.3 | AC18: =SUM(AB18*$Z$4) -> 2473 | AD18: =SUM(AB18) -> 247.3 | AE18: =SUM(AD18*$Z$4) -> 2473 | AF18: =SUM(AD18) -> 247.3 | AG18: =SUM(AF18*$Z$4) -> 2473 | AH18: =SUM(AF18) -> 247.3 | AI18: =SUM(AH18*$Z$4) -> 2473 | AJ18: =SUM(AH18) -> 247.3 | AK18: =SUM(AJ18*$Z$4) -> 2473 | AL18: =SUM(AJ18) -> 247.3 | AM18: =SUM(AL18*$Z$4) -> 2473 | AN18: =SUM(AO18/19600) -> 0.88321429 | AO18: =SUM(AA18+AC18+AE18+AG18+AI18+AK18+AM18) -> 17311 | AQ18: =SUM(AR18/92970) -> 0.80226886 | AR18: =SUM(AO18+Y18) -> 74586.935 | AS18: =SUM(AR18-AR17-AT18) -> 0 | AV18: =IF(AT18>0,AU18,AV17) -> 0 | AW18: =-SUM('B5'!AI17) -> 0 | AX18: =-SUM(AW18-AS18) -> 0 | AY18: =SUM(AX18+AW18) -> 0 | AZ18: =ELEC!A15 -> 0 | BA18: ='General information '!D18 -> 0 | BB18: =SUM('General information '!E18) -> 0 | BC18: =IF(AR17>=AR18,0,1) -> 0 | BD18: 19222 | BE18: =(305/1185)*ELEC!Q16 -> 0 | BG18: =#REF!-BE18 -> #REF!
A19: =ELEC!C16 -> 44118 | B19: ='B5'!B18 -> 242 | C19: =B19*$B$4 -> 5206.9032 | D19: =SUM(B19) -> 242 | E19: =D19*$B$4 -> 5206.9032 | F19: =SUM(D19) -> 242 | G19: =F19*$B$4 -> 5206.9032 | H19: =SUM(F19) -> 242 | I19: =H19*$B$4 -> 5206.9032 | J19: =SUM(H19) -> 242 | K19: =J19*$B$4 -> 5206.9032 | L19: =SUM(J19) -> 242 | M19: =L19*$B$4 -> 5206.9032 | N19: =SUM(L19) -> 242 | O19: =N19*$B$4 -> 5206.9032 | P19: =SUM(N19) -> 242 | Q19: =P19*$B$4 -> 5206.9032 | R19: =SUM(P19) -> 242 | S19: =R19*$B$4 -> 5206.9032 | T19: =SUM(R19) -> 242 | U19: =T19*$B$4 -> 5206.9032 | V19: =SUM(T19) -> 242 | W19: =V19*$B$4 -> 5206.9032 | X19: =SUM(Y19/73370) -> 0.78064516 | Y19: =SUM(C19+E19+G19+I19+K19+M19+O19+Q19+S19+U19+W19) -> 57275.935 | Z19: ='B5'!C18 -> 247.3 | AA19: =SUM(Z19*$Z$4) -> 2473 | AB19: =SUM(Z19) -> 247.3 | AC19: =SUM(AB19*$Z$4) -> 2473 | AD19: =SUM(AB19) -> 247.3 | AE19: =SUM(AD19*$Z$4) -> 2473 | AF19: =SUM(AD19) -> 247.3 | AG19: =SUM(AF19*$Z$4) -> 2473 | AH19: =SUM(AF19) -> 247.3 | AI19: =SUM(AH19*$Z$4) -> 2473 | AJ19: =SUM(AH19) -> 247.3 | AK19: =SUM(AJ19*$Z$4) -> 2473 | AL19: =SUM(AJ19) -> 247.3 | AM19: =SUM(AL19*$Z$4) -> 2473 | AN19: =SUM(AO19/19600) -> 0.88321429 | AO19: =SUM(AA19+AC19+AE19+AG19+AI19+AK19+AM19) -> 17311 | AQ19: =SUM(AR19/92970) -> 0.80226886 | AR19: =SUM(AO19+Y19) -> 74586.935 | AS19: =SUM(AR19-AR18-AT19) -> 0 | AV19: =IF(AT19>0,AU19,AV18) -> 0 | AW19: =-SUM('B5'!AI18) -> 0 | AX19: =-SUM(AW19-AS19) -> 0 | AY19: =SUM(AX19+AW19) -> 0 | AZ19: =ELEC!A16 -> 0 | BA19: ='General information '!D19 -> 0 | BB19: =SUM('General information '!E19) -> 0 | BC19: =IF(AR18>=AR19,0,1) -> 0 | BD19: 19222 | BE19: =(305/1185)*ELEC!Q17 -> 0 | BG19: =#REF!-BE19 -> #REF!
A20: =ELEC!C17 -> 44119 | B20: ='B5'!B19 -> 242 | C20: =B20*$B$4 -> 5206.9032 | D20: =SUM(B20) -> 242 | E20: =D20*$B$4 -> 5206.9032 | F20: =SUM(D20) -> 242 | G20: =F20*$B$4 -> 5206.9032 | H20: =SUM(F20) -> 242 | I20: =H20*$B$4 -> 5206.9032 | J20: =SUM(H20) -> 242 | K20: =J20*$B$4 -> 5206.9032 | L20: =SUM(J20) -> 242 | M20: =L20*$B$4 -> 5206.9032 | N20: =SUM(L20) -> 242 | O20: =N20*$B$4 -> 5206.9032 | P20: =SUM(N20) -> 242 | Q20: =P20*$B$4 -> 5206.9032 | R20: =SUM(P20) -> 242 | S20: =R20*$B$4 -> 5206.9032 | T20: =SUM(R20) -> 242 | U20: =T20*$B$4 -> 5206.9032 | V20: =SUM(T20) -> 242 | W20: =V20*$B$4 -> 5206.9032 | X20: =SUM(Y20/73370) -> 0.78064516 | Y20: =SUM(C20+E20+G20+I20+K20+M20+O20+Q20+S20+U20+W20) -> 57275.935 | Z20: ='B5'!C19 -> 247.3 | AA20: =SUM(Z20*$Z$4) -> 2473 | AB20: =SUM(Z20) -> 247.3 | AC20: =SUM(AB20*$Z$4) -> 2473 | AD20: =SUM(AB20) -> 247.3 | AE20: =SUM(AD20*$Z$4) -> 2473 | AF20: =SUM(AD20) -> 247.3 | AG20: =SUM(AF20*$Z$4) -> 2473 | AH20: =SUM(AF20) -> 247.3 | AI20: =SUM(AH20*$Z$4) -> 2473 | AJ20: =SUM(AH20) -> 247.3 | AK20: =SUM(AJ20*$Z$4) -> 2473 | AL20: =SUM(AJ20) -> 247.3 | AM20: =SUM(AL20*$Z$4) -> 2473 | AN20: =SUM(AO20/19600) -> 0.88321429 | AO20: =SUM(AA20+AC20+AE20+AG20+AI20+AK20+AM20) -> 17311 | AQ20: =SUM(AR20/92970) -> 0.80226886 | AR20: =SUM(AO20+Y20) -> 74586.935 | AS20: =SUM(AR20-AR19-AT20) -> 0 | AV20: =IF(AT20>0,AU20,AV19) -> 0 | AW20: =-SUM('B5'!AI19) -> 0 | AX20: =-SUM(AW20-AS20) -> 0 | AY20: =SUM(AX20+AW20) -> 0 | AZ20: =ELEC!A17 -> 0 | BA20: ='General information '!D20 -> 0 | BB20: =SUM('General information '!E20) -> 0 | BC20: =IF(AR19>=AR20,0,1) -> 0 | BD20: 19222 | BE20: =(305/1185)*ELEC!Q18 -> 0 | BG20: =#REF!-BE20 -> #REF!
A21: =ELEC!C18 -> 44120 | B21: ='B5'!B20 -> 242 | C21: =B21*$B$4 -> 5206.9032 | D21: =SUM(B21) -> 242 | E21: =D21*$B$4 -> 5206.9032 | F21: =SUM(D21) -> 242 | G21: =F21*$B$4 -> 5206.9032 | H21: =SUM(F21) -> 242 | I21: =H21*$B$4 -> 5206.9032 | J21: =SUM(H21) -> 242 | K21: =J21*$B$4 -> 5206.9032 | L21: =SUM(J21) -> 242 | M21: =L21*$B$4 -> 5206.9032 | N21: =SUM(L21) -> 242 | O21: =N21*$B$4 -> 5206.9032 | P21: =SUM(N21) -> 242 | Q21: =P21*$B$4 -> 5206.9032 | R21: =SUM(P21) -> 242 | S21: =R21*$B$4 -> 5206.9032 | T21: =SUM(R21) -> 242 | U21: =T21*$B$4 -> 5206.9032 | V21: =SUM(T21) -> 242 | W21: =V21*$B$4 -> 5206.9032 | X21: =SUM(Y21/73370) -> 0.78064516 | Y21: =SUM(C21+E21+G21+I21+K21+M21+O21+Q21+S21+U21+W21) -> 57275.935 | Z21: ='B5'!C20 -> 247.3 | AA21: =SUM(Z21*$Z$4) -> 2473 | AB21: =SUM(Z21) -> 247.3 | AC21: =SUM(AB21*$Z$4) -> 2473 | AD21: =SUM(AB21) -> 247.3 | AE21: =SUM(AD21*$Z$4) -> 2473 | AF21: =SUM(AD21) -> 247.3 | AG21: =SUM(AF21*$Z$4) -> 2473 | AH21: =SUM(AF21) -> 247.3 | AI21: =SUM(AH21*$Z$4) -> 2473 | AJ21: =SUM(AH21) -> 247.3 | AK21: =SUM(AJ21*$Z$4) -> 2473 | AL21: =SUM(AJ21) -> 247.3 | AM21: =SUM(AL21*$Z$4) -> 2473 | AN21: =SUM(AO21/19600) -> 0.88321429 | AO21: =SUM(AA21+AC21+AE21+AG21+AI21+AK21+AM21) -> 17311 | AQ21: =SUM(AR21/92970) -> 0.80226886 | AR21: =SUM(AO21+Y21) -> 74586.935 | AS21: =SUM(AR21-AR20-AT21) -> 0 | AV21: =IF(AT21>0,AU21,AV20) -> 0 | AW21: =-SUM('B5'!AI20) -> 0 | AX21: =-SUM(AW21-AS21) -> 0 | AY21: =SUM(AX21+AW21) -> 0 | AZ21: =ELEC!A18 -> 0 | BA21: ='General information '!D21 -> 0 | BB21: =SUM('General information '!E21) -> 0 | BC21: =IF(AR20>=AR21,0,1) -> 0 | BD21: 19222 | BE21: =(305/1185)*ELEC!Q19 -> 0 | BG21: =#REF!-BE21 -> #REF!
A22: =ELEC!C19 -> 44121 | B22: ='B5'!B21 -> 242 | C22: =B22*$B$4 -> 5206.9032 | D22: =SUM(B22) -> 242 | E22: =D22*$B$4 -> 5206.9032 | F22: =SUM(D22) -> 242 | G22: =F22*$B$4 -> 5206.9032 | H22: =SUM(F22) -> 242 | I22: =H22*$B$4 -> 5206.9032 | J22: =SUM(H22) -> 242 | K22: =J22*$B$4 -> 5206.9032 | L22: =SUM(J22) -> 242 | M22: =L22*$B$4 -> 5206.9032 | N22: =SUM(L22) -> 242 | O22: =N22*$B$4 -> 5206.9032 | P22: =SUM(N22) -> 242 | Q22: =P22*$B$4 -> 5206.9032 | R22: =SUM(P22) -> 242 | S22: =R22*$B$4 -> 5206.9032 | T22: =SUM(R22) -> 242 | U22: =T22*$B$4 -> 5206.9032 | V22: =SUM(T22) -> 242 | W22: =V22*$B$4 -> 5206.9032 | X22: =SUM(Y22/73370) -> 0.78064516 | Y22: =SUM(C22+E22+G22+I22+K22+M22+O22+Q22+S22+U22+W22) -> 57275.935 | Z22: ='B5'!C21 -> 247.3 | AA22: =SUM(Z22*$Z$4) -> 2473 | AB22: =SUM(Z22) -> 247.3 | AC22: =SUM(AB22*$Z$4) -> 2473 | AD22: =SUM(AB22) -> 247.3 | AE22: =SUM(AD22*$Z$4) -> 2473 | AF22: =SUM(AD22) -> 247.3 | AG22: =SUM(AF22*$Z$4) -> 2473 | AH22: =SUM(AF22) -> 247.3 | AI22: =SUM(AH22*$Z$4) -> 2473 | AJ22: =SUM(AH22) -> 247.3 | AK22: =SUM(AJ22*$Z$4) -> 2473 | AL22: =SUM(AJ22) -> 247.3 | AM22: =SUM(AL22*$Z$4) -> 2473 | AN22: =SUM(AO22/19600) -> 0.88321429 | AO22: =SUM(AA22+AC22+AE22+AG22+AI22+AK22+AM22) -> 17311 | AQ22: =SUM(AR22/92970) -> 0.80226886 | AR22: =SUM(AO22+Y22) -> 74586.935 | AS22: =SUM(AR22-AR21-AT22) -> 0 | AV22: =IF(AT22>0,AU22,AV21) -> 0 | AW22: =-SUM('B5'!AI21) -> 0 | AX22: =-SUM(AW22-AS22) -> 0 | AY22: =SUM(AX22+AW22) -> 0 | AZ22: =ELEC!A19 -> 0 | BA22: ='General information '!D22 -> 0 | BB22: =SUM('General information '!E22) -> 0 | BC22: =IF(AR21>=AR22,0,1) -> 0 | BD22: 19222 | BE22: =(305/1185)*ELEC!Q20 -> 0 | BG22: =#REF!-BE22 -> #REF!
A23: =ELEC!C20 -> 44122 | B23: ='B5'!B22 -> 242 | C23: =B23*$B$4 -> 5206.9032 | D23: =SUM(B23) -> 242 | E23: =D23*$B$4 -> 5206.9032 | F23: =SUM(D23) -> 242 | G23: =F23*$B$4 -> 5206.9032 | H23: =SUM(F23) -> 242 | I23: =H23*$B$4 -> 5206.9032 | J23: =SUM(H23) -> 242 | K23: =J23*$B$4 -> 5206.9032 | L23: =SUM(J23) -> 242 | M23: =L23*$B$4 -> 5206.9032 | N23: =SUM(L23) -> 242 | O23: =N23*$B$4 -> 5206.9032 | P23: =SUM(N23) -> 242 | Q23: =P23*$B$4 -> 5206.9032 | R23: =SUM(P23) -> 242 | S23: =R23*$B$4 -> 5206.9032 | T23: =SUM(R23) -> 242 | U23: =T23*$B$4 -> 5206.9032 | V23: =SUM(T23) -> 242 | W23: =V23*$B$4 -> 5206.9032 | X23: =SUM(Y23/73370) -> 0.78064516 | Y23: =SUM(C23+E23+G23+I23+K23+M23+O23+Q23+S23+U23+W23) -> 57275.935 | Z23: ='B5'!C22 -> 247.3 | AA23: =SUM(Z23*$Z$4) -> 2473 | AB23: =SUM(Z23) -> 247.3 | AC23: =SUM(AB23*$Z$4) -> 2473 | AD23: =SUM(AB23) -> 247.3 | AE23: =SUM(AD23*$Z$4) -> 2473 | AF23: =SUM(AD23) -> 247.3 | AG23: =SUM(AF23*$Z$4) -> 2473 | AH23: =SUM(AF23) -> 247.3 | AI23: =SUM(AH23*$Z$4) -> 2473 | AJ23: =SUM(AH23) -> 247.3 | AK23: =SUM(AJ23*$Z$4) -> 2473 | AL23: =SUM(AJ23) -> 247.3 | AM23: =SUM(AL23*$Z$4) -> 2473 | AN23: =SUM(AO23/19600) -> 0.88321429 | AO23: =SUM(AA23+AC23+AE23+AG23+AI23+AK23+AM23) -> 17311 | AQ23: =SUM(AR23/92970) -> 0.80226886 | AR23: =SUM(AO23+Y23) -> 74586.935 | AS23: =SUM(AR23-AR22-AT23) -> 0 | AV23: =IF(AT23>0,AU23,AV22) -> 0 | AW23: =-SUM('B5'!AI22) -> 0 | AX23: =-SUM(AW23-AS23) -> 0 | AY23: =SUM(AX23+AW23) -> 0 | AZ23: =ELEC!A20 -> 0 | BA23: ='General information '!D23 -> 0 | BB23: =SUM('General information '!E23) -> 0 | BC23: =IF(AR22>=AR23,0,1) -> 0 | BD23: 19222 | BE23: =(305/1185)*ELEC!Q21 -> 0 | BG23: =#REF!-BE23 -> #REF!
A24: =ELEC!C21 -> 44123 | B24: ='B5'!B23 -> 242 | C24: =B24*$B$4 -> 5206.9032 | D24: =SUM(B24) -> 242 | E24: =D24*$B$4 -> 5206.9032 | F24: =SUM(D24) -> 242 | G24: =F24*$B$4 -> 5206.9032 | H24: =SUM(F24) -> 242 | I24: =H24*$B$4 -> 5206.9032 | J24: =SUM(H24) -> 242 | K24: =J24*$B$4 -> 5206.9032 | L24: =SUM(J24) -> 242 | M24: =L24*$B$4 -> 5206.9032 | N24: =SUM(L24) -> 242 | O24: =N24*$B$4 -> 5206.9032 | P24: =SUM(N24) -> 242 | Q24: =P24*$B$4 -> 5206.9032 | R24: =SUM(P24) -> 242 | S24: =R24*$B$4 -> 5206.9032 | T24: =SUM(R24) -> 242 | U24: =T24*$B$4 -> 5206.9032 | V24: =SUM(T24) -> 242 | W24: =V24*$B$4 -> 5206.9032 | X24: =SUM(Y24/73370) -> 0.78064516 | Y24: =SUM(C24+E24+G24+I24+K24+M24+O24+Q24+S24+U24+W24) -> 57275.935 | Z24: ='B5'!C23 -> 247.3 | AA24: =SUM(Z24*$Z$4) -> 2473 | AB24: =SUM(Z24) -> 247.3 | AC24: =SUM(AB24*$Z$4) -> 2473 | AD24: =SUM(AB24) -> 247.3 | AE24: =SUM(AD24*$Z$4) -> 2473 | AF24: =SUM(AD24) -> 247.3 | AG24: =SUM(AF24*$Z$4) -> 2473 | AH24: =SUM(AF24) -> 247.3 | AI24: =SUM(AH24*$Z$4) -> 2473 | AJ24: =SUM(AH24) -> 247.3 | AK24: =SUM(AJ24*$Z$4) -> 2473 | AL24: =SUM(AJ24) -> 247.3 | AM24: =SUM(AL24*$Z$4) -> 2473 | AN24: =SUM(AO24/19600) -> 0.88321429 | AO24: =SUM(AA24+AC24+AE24+AG24+AI24+AK24+AM24) -> 17311 | AQ24: =SUM(AR24/92970) -> 0.80226886 | AR24: =SUM(AO24+Y24) -> 74586.935 | AS24: =SUM(AR24-AR23-AT24) -> 0 | AV24: =IF(AT24>0,AU24,AV23) -> 0 | AW24: =-SUM('B5'!AI23) -> 0 | AX24: =-SUM(AW24-AS24) -> 0 | AY24: =SUM(AX24+AW24) -> 0 | AZ24: =ELEC!A21 -> 0 | BA24: ='General information '!D24 -> 0 | BB24: =SUM('General information '!E24) -> 0 | BC24: =IF(AR23>=AR24,0,1) -> 0 | BD24: 19222 | BE24: =(305/1185)*ELEC!Q22 -> 0 | BG24: =#REF!-BE24 -> #REF!
... A33: =ELEC!C30 -> 44132 | B33: ='B5'!B32 -> 242 | C33: =B33*$B$4 -> 5206.9032 | D33: =SUM(B33) -> 242 | E33: =D33*$B$4 -> 5206.9032 | F33: =SUM(D33) -> 242 | G33: =F33*$B$4 -> 5206.9032 | H33: =SUM(F33) -> 242 | I33: =H33*$B$4 -> 5206.9032 | J33: =SUM(H33) -> 242 | K33: =J33*$B$4 -> 5206.9032 | L33: =SUM(J33) -> 242 | M33: =L33*$B$4 -> 5206.9032 | N33: =SUM(L33) -> 242 | O33: =N33*$B$4 -> 5206.9032 | P33: =SUM(N33) -> 242 | Q33: =P33*$B$4 -> 5206.9032 | R33: =SUM(P33) -> 242 | S33: =R33*$B$4 -> 5206.9032 | T33: =SUM(R33) -> 242 | U33: =T33*$B$4 -> 5206.9032 | V33: =SUM(T33) -> 242 | W33: =V33*$B$4 -> 5206.9032 | X33: =SUM(Y33/73370) -> 0.78064516 | Y33: =SUM(C33+E33+G33+I33+K33+M33+O33+Q33+S33+U33+W33) -> 57275.935 | Z33: ='B5'!C32 -> 247.3 | AA33: =SUM(Z33*$Z$4) -> 2473 | AB33: =SUM(Z33) -> 247.3 | AC33: =SUM(AB33*$Z$4) -> 2473 | AD33: =SUM(AB33) -> 247.3 | AE33: =SUM(AD33*$Z$4) -> 2473 | AF33: =SUM(AD33) -> 247.3 | AG33: =SUM(AF33*$Z$4) -> 2473 | AH33: =SUM(AF33) -> 247.3 | AI33: =SUM(AH33*$Z$4) -> 2473 | AJ33: =SUM(AH33) -> 247.3 | AK33: =SUM(AJ33*$Z$4) -> 2473 | AL33: =SUM(AJ33) -> 247.3 | AM33: =SUM(AL33*$Z$4) -> 2473 | AN33: =SUM(AO33/19600) -> 0.88321429 | AO33: =SUM(AA33+AC33+AE33+AG33+AI33+AK33+AM33) -> 17311 | AQ33: =SUM(AR33/92970) -> 0.80226886 | AR33: =SUM(AO33+Y33) -> 74586.935 | AS33: =SUM(AR33-AR32-AT33) -> 0 | AV33: =IF(AT33>0,AU33,AV32) -> 0 | AW33: =-SUM('B5'!AI32) -> 0 | AX33: =-SUM(AW33-AS33) -> 0 | AY33: =SUM(AX33+AW33) -> 0 | AZ33: =ELEC!A30 -> 0 | BA33: ='General information '!D33 -> 0 | BB33: =SUM('General information '!E33) -> 0 | BC33: =IF(AR32>=AR33,0,1) -> 0 | BD33: 19222 | BE33: =(305/1185)*ELEC!Q31 -> 0 | BG33: =#REF!-BE33 -> #REF!
A34: =ELEC!C31 -> 44133 | B34: ='B5'!B33 -> 242 | C34: =B34*$B$4 -> 5206.9032 | D34: =SUM(B34) -> 242 | E34: =D34*$B$4 -> 5206.9032 | F34: =SUM(D34) -> 242 | G34: =F34*$B$4 -> 5206.9032 | H34: =SUM(F34) -> 242 | I34: =H34*$B$4 -> 5206.9032 | J34: =SUM(H34) -> 242 | K34: =J34*$B$4 -> 5206.9032 | L34: =SUM(J34) -> 242 | M34: =L34*$B$4 -> 5206.9032 | N34: =SUM(L34) -> 242 | O34: =N34*$B$4 -> 5206.9032 | P34: =SUM(N34) -> 242 | Q34: =P34*$B$4 -> 5206.9032 | R34: =SUM(P34) -> 242 | S34: =R34*$B$4 -> 5206.9032 | T34: =SUM(R34) -> 242 | U34: =T34*$B$4 -> 5206.9032 | V34: =SUM(T34) -> 242 | W34: =V34*$B$4 -> 5206.9032 | X34: =SUM(Y34/73370) -> 0.78064516 | Y34: =SUM(C34+E34+G34+I34+K34+M34+O34+Q34+S34+U34+W34) -> 57275.935 | Z34: ='B5'!C33 -> 247.3 | AA34: =SUM(Z34*$Z$4) -> 2473 | AB34: =SUM(Z34) -> 247.3 | AC34: =SUM(AB34*$Z$4) -> 2473 | AD34: =SUM(AB34) -> 247.3 | AE34: =SUM(AD34*$Z$4) -> 2473 | AF34: =SUM(AD34) -> 247.3 | AG34: =SUM(AF34*$Z$4) -> 2473 | AH34: =SUM(AF34) -> 247.3 | AI34: =SUM(AH34*$Z$4) -> 2473 | AJ34: =SUM(AH34) -> 247.3 | AK34: =SUM(AJ34*$Z$4) -> 2473 | AL34: =SUM(AJ34) -> 247.3 | AM34: =SUM(AL34*$Z$4) -> 2473 | AN34: =SUM(AO34/19600) -> 0.88321429 | AO34: =SUM(AA34+AC34+AE34+AG34+AI34+AK34+AM34) -> 17311 | AQ34: =SUM(AR34/92970) -> 0.80226886 | AR34: =SUM(AO34+Y34) -> 74586.935 | AS34: =SUM(AR34-AR33-AT34) -> 0 | AV34: =IF(AT34>0,AU34,AV33) -> 0 | AW34: =-SUM('B5'!AI33) -> 0 | AX34: =-SUM(AW34-AS34) -> 0 | AY34: =SUM(AX34+AW34) -> 0 | AZ34: =ELEC!A31 -> 0 | BA34: ='General information '!D34 -> 0 | BB34: =SUM('General information '!E34) -> 0 | BC34: =IF(AR33>=AR34,0,1) -> 0 | BD34: 19222 | BE34: =(305/1185)*ELEC!#REF! -> #REF! | BG34: =#REF!-BE34 -> #REF!
A35: =ELEC!C32 -> 44134 | B35: ='B5'!B34 -> 242 | C35: =B35*$B$4 -> 5206.9032 | D35: =SUM(B35) -> 242 | E35: =D35*$B$4 -> 5206.9032 | F35: =SUM(D35) -> 242 | G35: =F35*$B$4 -> 5206.9032 | H35: =SUM(F35) -> 242 | I35: =H35*$B$4 -> 5206.9032 | J35: =SUM(H35) -> 242 | K35: =J35*$B$4 -> 5206.9032 | L35: =SUM(J35) -> 242 | M35: =L35*$B$4 -> 5206.9032 | N35: =SUM(L35) -> 242 | O35: =N35*$B$4 -> 5206.9032 | P35: =SUM(N35) -> 242 | Q35: =P35*$B$4 -> 5206.9032 | R35: =SUM(P35) -> 242 | S35: =R35*$B$4 -> 5206.9032 | T35: =SUM(R35) -> 242 | U35: =T35*$B$4 -> 5206.9032 | V35: =SUM(T35) -> 242 | W35: =V35*$B$4 -> 5206.9032 | X35: =SUM(Y35/73370) -> 0.78064516 | Y35: =SUM(C35+E35+G35+I35+K35+M35+O35+Q35+S35+U35+W35) -> 57275.935 | Z35: ='B5'!C34 -> 247.3 | AA35: =SUM(Z35*$Z$4) -> 2473 | AB35: =SUM(Z35) -> 247.3 | AC35: =SUM(AB35*$Z$4) -> 2473 | AD35: =SUM(AB35) -> 247.3 | AE35: =SUM(AD35*$Z$4) -> 2473 | AF35: =SUM(AD35) -> 247.3 | AG35: =SUM(AF35*$Z$4) -> 2473 | AH35: =SUM(AF35) -> 247.3 | AI35: =SUM(AH35*$Z$4) -> 2473 | AJ35: =SUM(AH35) -> 247.3 | AK35: =SUM(AJ35*$Z$4) -> 2473 | AL35: =SUM(AJ35) -> 247.3 | AM35: =SUM(AL35*$Z$4) -> 2473 | AN35: =SUM(AO35/19600) -> 0.88321429 | AO35: =SUM(AA35+AC35+AE35+AG35+AI35+AK35+AM35) -> 17311 | AQ35: =SUM(AR35/92970) -> 0.80226886 | AR35: =SUM(AO35+Y35) -> 74586.935 | AS35: =SUM(AR35-AR34-AT35) -> 0 | AV35: =IF(AT35>0,AU35,AV34) -> 0 | AW35: =-SUM('B5'!AI34) -> 0 | AX35: =-SUM(AW35-AS35) -> 0 | AY35: =SUM(AX35+AW35) -> 0 | AZ35: =ELEC!A32 -> 0 | BA35: ='General information '!D35 -> 0 | BB35: =SUM('General information '!E35) -> 0 | BC35: =IF(AR34>=AR35,0,1) -> 0 | BD35: 19222 | BE35: =(305/1185)*ELEC!#REF! -> #REF! | BG35: =#REF!-BE35 -> #REF!
A36: =ELEC!C33 -> 44135 | B36: ='B5'!B35 -> 242 | C36: =B36*$B$4 -> 5206.9032 | D36: =SUM(B36) -> 242 | E36: =D36*$B$4 -> 5206.9032 | F36: =SUM(D36) -> 242 | G36: =F36*$B$4 -> 5206.9032 | H36: =SUM(F36) -> 242 | I36: =H36*$B$4 -> 5206.9032 | J36: =SUM(H36) -> 242 | K36: =J36*$B$4 -> 5206.9032 | L36: =SUM(J36) -> 242 | M36: =L36*$B$4 -> 5206.9032 | N36: =SUM(L36) -> 242 | O36: =N36*$B$4 -> 5206.9032 | P36: =SUM(N36) -> 242 | Q36: =P36*$B$4 -> 5206.9032 | R36: =SUM(P36) -> 242 | S36: =R36*$B$4 -> 5206.9032 | T36: =SUM(R36) -> 242 | U36: =T36*$B$4 -> 5206.9032 | V36: =SUM(T36) -> 242 | W36: =V36*$B$4 -> 5206.9032 | X36: =SUM(Y36/73370) -> 0.78064516 | Y36: =SUM(C36+E36+G36+I36+K36+M36+O36+Q36+S36+U36+W36) -> 57275.935 | Z36: ='B5'!C35 -> 247.3 | AA36: =SUM(Z36*$Z$4) -> 2473 | AB36: =SUM(Z36) -> 247.3 | AC36: =SUM(AB36*$Z$4) -> 2473 | AD36: =SUM(AB36) -> 247.3 | AE36: =SUM(AD36*$Z$4) -> 2473 | AF36: =SUM(AD36) -> 247.3 | AG36: =SUM(AF36*$Z$4) -> 2473 | AH36: =SUM(AF36) -> 247.3 | AI36: =SUM(AH36*$Z$4) -> 2473 | AJ36: =SUM(AH36) -> 247.3 | AK36: =SUM(AJ36*$Z$4) -> 2473 | AL36: =SUM(AJ36) -> 247.3 | AM36: =SUM(AL36*$Z$4) -> 2473 | AN36: =SUM(AO36/19600) -> 0.88321429 | AO36: =SUM(AA36+AC36+AE36+AG36+AI36+AK36+AM36) -> 17311 | AQ36: =SUM(AR36/92970) -> 0.80226886 | AR36: =SUM(AO36+Y36) -> 74586.935 | AS36: =SUM(AR36-AR35-AT36) -> 0 | AV36: =IF(AT36>0,AU36,AV35) -> 0 | AW36: =-SUM('B5'!AI35) -> 0 | AX36: =-SUM(AW36-AS36) -> 0 | AY36: =SUM(AX36+AW36) -> 0 | AZ36: =ELEC!A33 -> 0 | BA36: ='General information '!D36 -> 0 | BB36: =SUM('General information '!E36) -> 0 | BC36: =IF(AR35>=AR36,0,1) -> 0 | BD36: 19222 | BE36: =(305/1185)*ELEC!#REF! -> #REF! | BG36: =#REF!-BE36 -> #REF!
AR37: NB delivery | AS37: =COUNT(AT6:AT35) -> 1 | AT37: =SUM(AT6:AT35) -> 1 | AU37: =SUM(AU6:AU35)/AS37 -> 0 | AX37: =SUM(AX6:AX35) -> -2311.2968 | AY37: =SUM(AY6:AY35) -> -2810.0968
AT38: =+AT37*AU37 -> 0
AS40: =SUM(AS6:AS35)/'EDl log'!A36 -> -562.01935

Sheet Sheet1
A1: TOTAL CH RH | B1: TOTAL CH cons KW | C1: TOTAL ELIC KW | D1: TOTAL EDL | E1: TOTAL GEN KW | F1: GEN HR | G1: WATER IN | H1: TOTAL CT | I1: TOTAL WATER | J1: Date
A2: =ELEC!T3+ELEC!X1+ELEC!AB3 -> #VALUE! | B2: =ELEC!AF3 -> 2240 | C2: =ELEC!N3 -> 10203 | D2: =C2-E2 -> 8203 | E2: =ELEC!Q3 -> 2000 | F2: =GEN!Z2 -> 6 | G2: =WATER!C5+WATER!H5 -> 0 | H2: =WATER!L5 -> 0 | I2: =WATER!BC5+WATER!BD5+WATER!BE6-Sheet1!G2 -> 14.3 | J2: ='B5'!A4 -> 44104
A3: =ELEC!T4+ELEC!X2+ELEC!AB4 -> 9 | B3: =ELEC!AF4 -> 1712 | C3: =ELEC!N4 -> 10041 | D3: =C3-E3 -> 10041 | E3: =ELEC!Q4 -> 0 | F3: =GEN!Z3 -> 3 | G3: =WATER!C6+WATER!H6 -> 0 | H3: =WATER!L6 -> 0 | I3: =WATER!BC6+WATER!BD6+WATER!BE7-Sheet1!G3 -> 9.5 | J3: ='B5'!A5 -> 44105
A4: =ELEC!T5+ELEC!X5+ELEC!AB5 -> 8 | B4: =ELEC!AF5 -> 1956 | C4: =ELEC!N5 -> 8684 | D4: =C4-E4 -> 7684 | E4: =ELEC!Q5 -> 1000 | F4: =GEN!Z4 -> 0 | G4: =WATER!C7+WATER!H7 -> 90 | H4: =WATER!L7 -> 0 | I4: =WATER!BC7+WATER!BD7+WATER!BE8-Sheet1!G4 -> -127.6 | J4: ='B5'!A6 -> 44106
A5: =ELEC!T6+ELEC!X6+ELEC!AB6 -> 5 | B5: =ELEC!AF6 -> 1245 | C5: =ELEC!N6 -> 7992 | D5: =C5-E5 -> 5992 | E5: =ELEC!Q6 -> 2000 | F5: =GEN!Z5 -> 3 | G5: =WATER!C8+WATER!H8 -> 0 | H5: =WATER!L8 -> 0 | I5: =WATER!BC8+WATER!BD8+WATER!BE9-Sheet1!G5 -> 57.9 | J5: ='B5'!A7 -> 44107
A6: =ELEC!T7+ELEC!X7+ELEC!AB7 -> 9 | B6: =ELEC!AF7 -> 1878 | C6: =ELEC!N7 -> 9176 | D6: =C6-E6 -> 9176 | E6: =ELEC!Q24 -> 0 | F6: =GEN!Z6 -> 4 | G6: =WATER!C9+WATER!H9 -> 98 | H6: =WATER!L9 -> 0 | I6: =WATER!BC9+WATER!BD9+WATER!BE10-Sheet1!G6 -> -146.8 | J6: ='B5'!A8 -> 44108
A7: =ELEC!T8+ELEC!X8+ELEC!AB8 -> 0 | B7: =ELEC!AF8 -> 0 | C7: =ELEC!N8 -> 0 | D7: =C7-E7 -> 0 | E7: =ELEC!Q8 -> 0 | F7: =GEN!Z7 -> 3 | G7: =WATER!C10+WATER!H10 -> 0 | H7: =WATER!L10 -> 0 | I7: =WATER!BC10+WATER!BD10+WATER!BE11-Sheet1!G7 -> 26.2 | J7: ='B5'!A9 -> 44109
A8: =ELEC!T9+ELEC!X9+ELEC!AB9 -> 0 | B8: =ELEC!AF9 -> 0 | C8: =ELEC!N9 -> 0 | D8: =C8-E8 -> 0 | E8: =ELEC!Q9 -> 0 | F8: =GEN!Z8 -> 0 | G8: =WATER!C11+WATER!H11 -> 0 | H8: =WATER!L11 -> 0 | I8: =WATER!BC11+WATER!BD11+WATER!BE12-Sheet1!G8 -> 0 | J8: ='B5'!A10 -> 44110
A9: =ELEC!T10+ELEC!X10+ELEC!AB10 -> 0 | B9: =ELEC!AF10 -> 0 | C9: =ELEC!N10 -> 0 | D9: =C9-E9 -> 0 | E9: =ELEC!Q10 -> 0 | F9: =GEN!Z9 -> 0 | G9: =WATER!C12+WATER!H12 -> 0 | H9: =WATER!L12 -> 0 | I9: =WATER!BC12+WATER!BD12+WATER!BE13-Sheet1!G9 -> 0 | J9: ='B5'!A11 -> 44111
A10: =ELEC!T11+ELEC!X11+ELEC!AB11 -> 0 | B10: =ELEC!AF11 -> 0 | C10: =ELEC!N11 -> 0 | D10: =C10-E10 -> 0 | E10: =ELEC!Q11 -> 0 | F10: =GEN!Z10 -> 0 | G10: =WATER!C13+WATER!H13 -> 0 | H10: =WATER!L13 -> 0 | I10: =WATER!BC13+WATER!BD13+WATER!BE14-Sheet1!G10 -> 0 | J10: ='B5'!A12 -> 44112
A11: =ELEC!T12+ELEC!X12+ELEC!AB12 -> 0 | B11: =ELEC!AF12 -> 0 | C11: =ELEC!N12 -> 0 | D11: =C11-E11 -> 0 | E11: =ELEC!Q12 -> 0 | F11: =GEN!Z11 -> 0 | G11: =WATER!C14+WATER!H14 -> 0 | H11: =WATER!L14 -> 0 | I11: =WATER!BC14+WATER!BD14+WATER!BE15-Sheet1!G11 -> 0 | J11: ='B5'!A13 -> 44113
A12: =ELEC!T13+ELEC!X13+ELEC!AB13 -> 0 | B12: =ELEC!AF13 -> 0 | C12: =ELEC!N13 -> 0 | D12: =C12-E12 -> 0 | E12: =ELEC!Q13 -> 0 | F12: =GEN!Z12 -> 0 | G12: =WATER!C15+WATER!H15 -> 0 | H12: =WATER!L15 -> 0 | I12: =WATER!BC15+WATER!BD15+WATER!BE16-Sheet1!G12 -> 0 | J12: ='B5'!A14 -> 44114
A13: =ELEC!T14+ELEC!X14+ELEC!AB14 -> 0 | B13: =ELEC!AF14 -> 0 | C13: =ELEC!N14 -> 0 | D13: =C13-E13 -> 0 | E13: =ELEC!Q14 -> 0 | F13: =GEN!Z13 -> 0 | G13: =WATER!C16+WATER!H16 -> 0 | H13: =WATER!L16 -> 0 | I13: =WATER!BC16+WATER!BD16+WATER!BE17-Sheet1!G13 -> 0 | J13: ='B5'!A15 -> 44115
A14: =ELEC!T15+ELEC!X15+ELEC!AB15 -> 0 | B14: =ELEC!AF15 -> 0 | C14: =ELEC!N15 -> 0 | D14: =C14-E14 -> 0 | E14: =ELEC!Q15 -> 0 | F14: =GEN!Z14 -> 0 | G14: =WATER!C17+WATER!H17 -> 0 | H14: =WATER!L17 -> 0 | I14: =WATER!BC17+WATER!BD17+WATER!BE18-Sheet1!G14 -> 0 | J14: ='B5'!A16 -> 44116
A15: =ELEC!T16+ELEC!X16+ELEC!AB16 -> 0 | B15: =ELEC!AF16 -> 0 | C15: =ELEC!N16 -> 0 | D15: =C15-E15 -> 0 | E15: =ELEC!Q16 -> 0 | F15: =GEN!Z15 -> 0 | G15: =WATER!C18+WATER!H18 -> 0 | H15: =WATER!L18 -> 0 | I15: =WATER!BC18+WATER!BD18+WATER!BE19-Sheet1!G15 -> 0 | J15: ='B5'!A17 -> 44117
A16: =ELEC!T17+ELEC!X17+ELEC!AB17 -> 0 | B16: =ELEC!AF17 -> 0 | C16: =ELEC!N17 -> 0 | D16: =C16-E16 -> 0 | E16: =ELEC!Q17 -> 0 | F16: =GEN!Z16 -> 0 | G16: =WATER!C19+WATER!H19 -> 0 | H16: =WATER!L19 -> 0 | I16: =WATER!BC19+WATER!BD19+WATER!BE20-Sheet1!G16 -> 0 | J16: ='B5'!A18 -> 44118
A17: =ELEC!T18+ELEC!X18+ELEC!AB18 -> 0 | B17: =ELEC!AF18 -> 0 | C17: =ELEC!N18 -> 0 | D17: =C17-E17 -> 0 | E17: =ELEC!Q18 -> 0 | F17: =GEN!Z17 -> 0 | G17: =WATER!C20+WATER!H20 -> 0 | H17: =WATER!L20 -> 0 | I17: =WATER!BC20+WATER!BD20+WATER!BE21-Sheet1!G17 -> 0 | J17: ='B5'!A19 -> 44119
A18: =ELEC!T19+ELEC!X19+ELEC!AB19 -> 0 | B18: =ELEC!AF19 -> 0 | C18: =ELEC!N19 -> 0 | D18: =C18-E18 -> 0 | E18: =ELEC!Q19 -> 0 | F18: =GEN!Z18 -> 0 | G18: =WATER!C21+WATER!H21 -> 0 | H18: =WATER!L21 -> 0 | I18: =WATER!BC21+WATER!BD21+WATER!BE22-Sheet1!G18 -> 0 | J18: ='B5'!A20 -> 44120
... A29: =ELEC!T30+ELEC!X30+ELEC!AB30 -> 0 | B29: =ELEC!AF30 -> 0 | C29: =ELEC!N30 -> 0 | D29: =C29-E29 -> 0 | E29: =ELEC!Q30 -> 0 | F29: =GEN!Z29 -> 0 | G29: =WATER!C32+WATER!H32 -> 0 | H29: =WATER!L32 -> 0 | I29: =WATER!BC32+WATER!BD32+WATER!BE33-Sheet1!G29 -> 0 | J29: ='B5'!A31 -> 44131
A30: =ELEC!T31+ELEC!X31+ELEC!#REF! -> #REF! | B30: =ELEC!AF31 -> 0 | C30: =ELEC!N31 -> 0 | D30: =C30-E30 -> 0 | E30: =ELEC!Q31 -> 0 | F30: =GEN!Z30 -> 0 | G30: =WATER!C33+WATER!H33 -> 0 | H30: =WATER!L33 -> 0 | I30: =WATER!BC33+WATER!BD33+WATER!BE34-Sheet1!G30 -> 0 | J30: ='B5'!A32 -> 44132
A31: =ELEC!T32+ELEC!X32+ELEC!AB31 -> 0 | B31: =ELEC!AF32 -> 0 | C31: =ELEC!N32 -> 0 | D31: =C31-E31 -> 0 | E31: =ELEC!Q32 -> 0 | F31: =GEN!Z31 -> 0 | G31: =WATER!C34+WATER!H34 -> 0 | H31: =WATER!L34 -> 0 | I31: =WATER!BC34+WATER!BD34+WATER!BE35-Sheet1!G31 -> 0 | J31: ='B5'!A33 -> 44133
A32: =ELEC!#REF!+ELEC!#REF!+ELEC!#REF! -> #REF! | B32: =ELEC!#REF! -> #REF! | C32: =ELEC!#REF! -> #REF! | D32: =C32-E32 -> #REF! | E32: =ELEC!#REF! -> #REF! | F32: =GEN!#REF! -> #REF! | G32: =WATER!#REF!+WATER!#REF! -> #REF! | H32: =WATER!#REF! -> #REF! | I32: =WATER!#REF!+WATER!#REF!+WATER!BE37-Sheet1!G32 -> #REF!

Sheet Report
B1: Boiler Fuel | C1: Steam Fuel | D1: GEN FUEL | E1: FUEL TOTAL | F1: CT/mᶾ | G1: Water Consumption | H1: Chiller KW | I1: GEN KW | J1: EDL KW | K1: occ | L1: covers | M1: temp. C⁰ | N1: RH %
B3: ='B5'!V3 -> 0 | C3: ='B5'!AH3 -> 0 | E3: =B3+C3+D3 -> 0
A4: 42704 | B4: 810 | C4: -606.1 | D4: 1420.5021 | E4: 1624.4021 | F4: 106 | G4: -58.4 | H4: 6284 | I4: 2399 | J4: 23932 | K4: 0 | L4: 0 | M4: 0 | N4: 0
A5: ='B5'!A5 -> 44105 | B5: ='B5'!V5 -> 0 | C5: ='B5'!AH5 -> 1.8 | D5: =GEN!AI3 -> 514.76793 | E5: =B5+C5+D5 -> 516.56793 | F5: =WATER!L5 -> 0 | G5: =WATER!BG5 -> -54.1 | H5: =ELEC!AF3 -> 2240 | I5: =ELEC!Q3 -> 2000 | J5: =ELEC!R3 -> 8203
A6: ='B5'!A6 -> 44106 | B6: ='B5'!V6 -> 232 | C6: ='B5'!AH6 -> 0 | D6: =GEN!AI4 -> 0 | E6: =B6+C6+D6 -> 232 | F6: =WATER!L6 -> 0 | G6: =WATER!BG6 -> -29.7 | H6: =ELEC!AF4 -> 1712 | I6: =ELEC!Q4 -> 0 | J6: =ELEC!R4 -> 10041
A7: ='B5'!A7 -> 44107 | B7: ='B5'!V7 -> 116 | C7: ='B5'!AH7 -> 0 | D7: =GEN!AI5 -> 257.38397 | E7: =B7+C7+D7 -> 373.38397 | F7: =WATER!L7 -> 0 | G7: =WATER!BG7 -> 11.3 | H7: =ELEC!AF5 -> 1956 | I7: =ELEC!Q5 -> 1000 | J7: =ELEC!R5 -> 7684
A8: ='B5'!A8 -> 44108 | B8: ='B5'!V8 -> 53 | C8: ='B5'!AH8 -> 0 | D8: =GEN!AI6 -> 514.76793 | E8: =B8+C8+D8 -> 567.76793 | F8: =WATER!L8 -> 0 | G8: =WATER!BG8 -> -21.9 | H8: =ELEC!AF6 -> 1245 | I8: =ELEC!Q6 -> 2000 | J8: =ELEC!R6 -> 5992
A9: ='B5'!A9 -> 44109 | B9: ='B5'!V9 -> 96 | C9: ='B5'!AH9 -> 0 | D9: =GEN!AI7 -> 514.76793 | E9: =B9+C9+D9 -> 610.76793 | F9: =WATER!L9 -> 0 | G9: =WATER!BG9 -> 41.1 | H9: =ELEC!AF7 -> 1878 | I9: =ELEC!Q7 -> 2000 | J9: =ELEC!R7 -> 7176
A10: ='B5'!A10 -> 44110 | B10: ='B5'!V10 -> 0 | C10: ='B5'!AH10 -> 0 | D10: =GEN!AI8 -> 0 | E10: =B10+C10+D10 -> 0 | F10: =WATER!L10 -> 0 | G10: =WATER!BG10 -> -40.4 | H10: =ELEC!AF8 -> 0 | I10: =ELEC!Q8 -> 0 | J10: =ELEC!R8 -> 0
A11: ='B5'!A11 -> 44111 | B11: ='B5'!V11 -> 0 | C11: ='B5'!AH11 -> 0 | D11: =GEN!AI9 -> 0 | E11: =B11+C11+D11 -> 0 | F11: =WATER!L11 -> 0 | G11: =WATER!BG11 -> 0 | H11: =ELEC!AF9 -> 0 | I11: =ELEC!Q9 -> 0 | J11: =ELEC!R9 -> 0
A12: ='B5'!A12 -> 44112 | B12: ='B5'!V12 -> 0 | C12: ='B5'!AH12 -> 0 | D12: =GEN!AI10 -> 0 | E12: =B12+C12+D12 -> 0 | F12: =WATER!L12 -> 0 | G12: =WATER!BG12 -> 0 | H12: =ELEC!AF10 -> 0 | I12: =ELEC!Q10 -> 0 | J12: =ELEC!R10 -> 0
A13: ='B5'!A13 -> 44113 | B13: ='B5'!V13 -> 0 | C13: ='B5'!AH13 -> 0 | D13: =GEN!AI11 -> 0 | E13: =B13+C13+D13 -> 0 | F13: =WATER!L13 -> 0 | G13: =WATER!BG13 -> 0 | H13: =ELEC!AF11 -> 0 | I13: =ELEC!Q11 -> 0 | J13: =ELEC!R11 -> 0
A14: ='B5'!A14 -> 44114 | B14: ='B5'!V14 -> 0 | C14: ='B5'!AH14 -> 0 | D14: =GEN!AI12 -> 0 | E14: =B14+C14+D14 -> 0 | F14: =WATER!L14 -> 0 | G14: =WATER!BG14 -> 0 | H14: =ELEC!AF12 -> 0 | I14: =ELEC!Q12 -> 0 | J14: =ELEC!R12 -> 0
A15: ='B5'!A15 -> 44115 | B15: ='B5'!V15 -> 0 | C15: ='B5'!AH15 -> 0 | D15: =GEN!AI13 -> 0 | E15: =B15+C15+D15 -> 0 | F15: =WATER!L15 -> 0 | G15: =WATER!BG15 -> 0 | H15: =ELEC!AF13 -> 0 | I15: =ELEC!Q13 -> 0 | J15: =ELEC!R13 -> 0
A16: ='B5'!A16 -> 44116 | B16: ='B5'!V16 -> 0 | C16: ='B5'!AH16 -> 0 | D16: =GEN!AI14 -> 0 | E16: =B16+C16+D16 -> 0 | F16: =WATER!L16 -> 0 | G16: =WATER!BG16 -> 0 | H16: =ELEC!AF14 -> 0 | I16: =ELEC!Q14 -> 0 | J16: =ELEC!R14 -> 0
... A33: ='B5'!A33 -> 44133 | B33: ='B5'!V33 -> 0 | C33: ='B5'!AH33 -> 0 | D33: =GEN!AI31 -> 0 | E33: =B33+C33+D33 -> 0 | F33: =WATER!L33 -> 0 | G33: =WATER!BG33 -> 0 | H33: =ELEC!AF31 -> 0 | I33: =ELEC!Q31 -> 0 | J33: =ELEC!R31 -> 0
A34: ='B5'!A34 -> 44134 | B34: ='B5'!V34 -> 0 | C34: ='B5'!AH34 -> 0 | D34: =GEN!AI32 -> 0 | E34: =B34+C34+D34 -> 0 | F34: =WATER!L34 -> 0 | G34: =WATER!BG34 -> 0 | H34: =ELEC!#REF! -> #REF! | I34: =ELEC!#REF! -> #REF! | J34: =ELEC!#REF! -> #REF!

Sheet Sheet5
T3: Outdoor conditions
C4: Date | D4: Total Boiler running H | E4: AVE CONSUM | F4: Total Steam running H | G4: AVE CONSUM | H4: Total GEN running H | I4: AVE CONSUM | J4: Actual Diesel Consumption | K4: Actual Gas Consumption | L4: Total ELEC power | M4: Gen ELEC power | N4: EDL ELEC power | O4: Chillers running H | P4: Total Water delivery | Q4: Total water consumption | R4: Total water in tanks | S4: Occupancy | T4: AVE TEPM | U4: AVE Humidity
C5: 42429 | D5: ='B5'!AL4 -> 0 | E5: =D5*90 -> 0 | F5: ='B5'!AM4 -> 0 | G5: =F5*107 -> 0 | H5: =GEN!Z3 -> 3
C6: 42430 | D6: ='B5'!AL5 -> 0 | E6: =D6*90 -> 0 | F6: ='B5'!AM5 -> 0 | G6: =F6*107 -> 0
C7: 42431 | D7: ='B5'!AL6 -> 3 | E7: =D7*90 -> 270 | F7: ='B5'!AM6 -> 0 | G7: =F7*107 -> 0
C8: 42432 | D8: ='B5'!AL7 -> 1 | E8: =D8*90 -> 90 | F8: ='B5'!AM7 -> 0 | G8: =F8*107 -> 0
C9: 42433 | D9: ='B5'!AL8 -> 1 | E9: =D9*90 -> 90 | F9: ='B5'!AM8 -> 0 | G9: =F9*107 -> 0
C10: 42434 | D10: ='B5'!AL9 -> 1 | E10: =D10*90 -> 90 | F10: ='B5'!AM9 -> 0 | G10: =F10*107 -> 0
C11: 42435 | D11: ='B5'!AL10 -> 0 | E11: =D11*90 -> 0 | F11: ='B5'!AM10 -> 0 | G11: =F11*107 -> 0
C12: 42436 | D12: ='B5'!AL11 -> 0 | E12: =D12*90 -> 0 | F12: ='B5'!AM11 -> 0 | G12: =F12*107 -> 0
C13: 42437 | D13: ='B5'!AL12 -> 0 | E13: =D13*90 -> 0 | F13: ='B5'!AM12 -> 0 | G13: =F13*107 -> 0
C14: 42438 | D14: ='B5'!AL13 -> 0 | E14: =D14*90 -> 0 | F14: ='B5'!AM13 -> 0 | G14: =F14*107 -> 0
C15: 42439 | D15: ='B5'!AL14 -> 0 | E15: =D15*90 -> 0 | F15: ='B5'!AM14 -> 0 | G15: =F15*107 -> 0
C16: 42440 | D16: ='B5'!AL15 -> 0 | E16: =D16*90 -> 0 | F16: ='B5'!AM15 -> 0 | G16: =F16*107 -> 0
C17: 42441 | D17: ='B5'!AL16 -> 0 | E17: =D17*90 -> 0 | F17: ='B5'!AM16 -> 0 | G17: =F17*107 -> 0
... C35: 42459 | D35: ='B5'!AL34 -> 0 | E35: =D35*90 -> 0 | F35: ='B5'!AM34 -> 0 | G35: =F35*107 -> 0
C36: 42460 | D36: ='B5'!#REF! -> #REF! | E36: =D36*90 -> #REF! | F36: ='B5'!#REF! -> #REF! | G36: =F36*107 -> #REF!
C37: 42461 | D37: ='B5'!#REF! -> #REF! | E37: =D37*90 -> #REF! | F37: ='B5'!#REF! -> #REF! | G37: =F37*107 -> #REF!

Sheet GEN
B1: GEN1 | C1: RUN HR | D1: Fuel Counter Index | E1: Cons /day | F1: Diesel L/H | H1: next service | I1: ALARM | J1: GEN2 | K1: RUN HR | L1: Fuel Counter Index | M1: Cons /day | N1: Diesel L/H | P1: next service | Q1: ALARM | R1: GEN3 | S1: RUN HR | T1: Fuel Counter Index | U1: Cons /day | V1: Diesel L/H | X1: next service | Y1: ALARM | Z1: RH total | AA1: Gen Con /day | AB1: Total Deisel Cons/day | AC1: H /L | AD1: TOAL KW GEN | AI1: fuel Consuption | AK1: AVG KW/h
A2: =ELEC!C2 -> 44104 | B2: =[2]GEN!B32 -> 9208 | C2: =[2]GEN!C32 -> 6 | D2: =[2]GEN!D32 -> 244563 | E2: =[2]GEN!E32 -> 1004 | F2: =[2]GEN!F32 -> 167.33333 | G2: =[2]GEN!G32 -> 0 | H2: =[2]GEN!H32 -> 9298 | I2: =[2]GEN!I32 -> ok | ... AK2: =[2]GEN!AK32 -> 171.58931
A3: =ELEC!C3 -> 44105 | B3: 9211 | C3: =B3-B2 -> 3 | D3: 245152 | E3: =SUM(D3-D2) -> 589 | F3: =IF(C3>0,E3/C3,0) -> 196.33333 | G3: =[4]GEN!G32 -> 0 | H3: =H2+180 -> 9478 | I3: =IF(B3-H3<=0,"ok","oil change") -> ok | J3: =J2 -> 10698 | K3: =J3-J2 -> 0 | L3: =L2 -> 238500 | M3: =SUM(L3-L2) -> 0 | N3: =IF(K3>0,M3/K3,0) -> 0 | O3: =[4]GEN!O32 -> 0 | P3: =P2 -> 10873 | Q3: =IF(J3-P3<=0,"ok","oil change") -> ok | R3: =R2 -> 11705 | S3: =R3-R2 -> 0 | T3: 357664 | U3: =SUM(T3-T2) -> 6 | V3: =IF(S3>0,U3/S3,0) -> 0 | W3: =[4]GEN!W32 -> 0 | X3: =X2 -> 12609 | Y3: =IF(R3-X3<=0,"ok","oil change") -> ok | Z3: =C3+K3+S3 -> 3 | AA3: =U3+M3+E3 -> 595 | AB3: =V3+N3+F3 -> 196.33333 | AC3: =IF(Z3>0,AA3/Z3,0) -> 198.33333 | AD3: =ELEC!Q3 -> 2000 | AE3: =SUM(AD3/Z3) -> 666.66667 | AF3: =SUM(AE3/1600) -> 0.41666667 | AG3: =SUM(360*AF3) -> 150 | AH3: =SUM(AC3-AG3) -> 48.333333 | AI3: =AD3*AJ3 -> 514.76793 | AJ3: =305/1185 -> 0.25738397 | AK3: =AI3/Z3 -> 171.58931
A4: =ELEC!C4 -> 44106 | B4: =B3 -> 9211 | C4: =B4-B3 -> 0 | D4: =D3 -> 245152 | E4: =SUM(D4-D3) -> 0 | F4: =IF(C4>0,E4/C4,0) -> 0 | H4: =H3 -> 9478 | I4: =IF(B4-H4<=0,"ok","oil change") -> ok | J4: =J3 -> 10698 | K4: =J4-J3 -> 0 | L4: =L3 -> 238500 | M4: =SUM(L4-L3) -> 0 | N4: =IF(K4>0,M4/K4,0) -> 0 | P4: =P3 -> 10873 | Q4: =IF(J4-P4<=0,"ok","oil change") -> ok | R4: =R3 -> 11705 | S4: =R4-R3 -> 0 | T4: 357664 | U4: =SUM(T4-T3) -> 0 | V4: =IF(S4>0,U4/S4,0) -> 0 | X4: =X3 -> 12609 | Y4: =IF(R4-X4<=0,"ok","oil change") -> ok | Z4: =C4+K4+S4 -> 0 | AA4: =U4+M4+E4 -> 0 | AB4: =V4+N4+F4 -> 0 | AC4: =IF(Z4>0,AA4/Z4,0) -> 0 | AD4: =ELEC!Q4 -> 0 | AE4: =SUM(AD4/Z4) -> #DIV/0! | AF4: =SUM(AE4/1600) -> #DIV/0! | AG4: =SUM(360*AF4) -> #DIV/0! | AH4: =SUM(AC4-AG4) -> #DIV/0! | AI4: =AD4*AJ4 -> 0 | AJ4: =305/1185 -> 0.25738397 | AK4: =AI4/Z4 -> #DIV/0!
A5: =ELEC!C5 -> 44107 | B5: 9214 | C5: =B5-B4 -> 3 | D5: 245883 | E5: =SUM(D5-D4) -> 731 | F5: =IF(C5>0,E5/C5,0) -> 243.66667 | H5: =H4 -> 9478 | I5: =IF(B5-H5<=0,"ok","oil change") -> ok | J5: =J4 -> 10698 | K5: =J5-J4 -> 0 | L5: =L4 -> 238500 | M5: =SUM(L5-L4) -> 0 | N5: =IF(K5>0,M5/K5,0) -> 0 | P5: =P4 -> 10873 | Q5: =IF(J5-P5<=0,"ok","oil change") -> ok | R5: =R4 -> 11705 | S5: =R5-R4 -> 0 | T5: =T4 -> 357664 | U5: =SUM(T5-T4) -> 0 | V5: =IF(S5>0,U5/S5,0) -> 0 | X5: =X4 -> 12609 | Y5: =IF(R5-X5<=0,"ok","oil change") -> ok | Z5: =C5+K5+S5 -> 3 | AA5: =U5+M5+E5 -> 731 | AB5: =V5+N5+F5 -> 243.66667 | AC5: =IF(Z5>0,AA5/Z5,0) -> 243.66667 | AD5: =ELEC!Q5 -> 1000 | AE5: =SUM(AD5/Z5) -> 333.33333 | AF5: =SUM(AE5/1600) -> 0.20833333 | AG5: =SUM(320*AF5) -> 66.666667 | AH5: =SUM(AC5-AG5) -> 177 | AI5: =AD5*AJ5 -> 257.38397 | AJ5: =305/1185 -> 0.25738397 | AK5: =AI5/Z5 -> 85.794655
A6: =ELEC!C6 -> 44108 | B6: 9218 | C6: =B6-B5 -> 4 | D6: 246617 | E6: =SUM(D6-D5) -> 734 | F6: =IF(C6>0,E6/C6,0) -> 183.5 | H6: 9298 | I6: =IF(B6-H6<=0,"ok","oil change") -> ok | J6: =J5 -> 10698 | K6: =J6-J5 -> 0 | L6: =L5 -> 238500 | M6: =SUM(L6-L5) -> 0 | N6: =IF(K6>0,M6/K6,0) -> 0 | P6: =P5 -> 10873 | Q6: =IF(J6-P6<=0,"ok","oil change") -> ok | R6: =R5 -> 11705 | S6: =R6-R5 -> 0 | T6: =T5 -> 357664 | U6: =SUM(T6-T5) -> 0 | V6: =IF(S6>0,U6/S6,0) -> 0 | X6: =X5 -> 12609 | Y6: =IF(R6-X6<=0,"ok","oil change") -> ok | Z6: =C6+K6+S6 -> 4 | AA6: =U6+M6+E6 -> 734 | AB6: =V6+N6+F6 -> 183.5 | AC6: =IF(Z6>0,AA6/Z6,0) -> 183.5 | AD6: =ELEC!Q6 -> 2000 | AE6: =SUM(AD6/Z6) -> 500 | AF6: =SUM(AE6/1600) -> 0.3125 | AG6: =SUM(320*AF6) -> 100 | AH6: =SUM(AC6-AG6) -> 83.5 | AI6: =AD6*AJ6 -> 514.76793 | AJ6: =305/1185 -> 0.25738397 | AK6: =AI6/Z6 -> 128.69198
A7: =ELEC!C7 -> 44109 | B7: 9221 | C7: =B7-B6 -> 3 | D7: 247280 | E7: =SUM(D7-D6) -> 663 | F7: =IF(C7>0,E7/C7,0) -> 221 | H7: =H6 -> 9298 | I7: =IF(B7-H7<=0,"ok","oil change") -> ok | J7: =J6 -> 10698 | K7: =J7-J6 -> 0 | L7: =L6 -> 238500 | M7: =SUM(L7-L6) -> 0 | N7: =IF(K7>0,M7/K7,0) -> 0 | P7: =P6 -> 10873 | Q7: =IF(J7-P7<=0,"ok","oil change") -> ok | R7: 11705 | S7: =R7-R6 -> 0 | T7: =T6 -> 357664 | U7: =SUM(T7-T6) -> 0 | V7: =IF(S7>0,U7/S7,0) -> 0 | X7: =X6 -> 12609 | Y7: =IF(R7-X7<=0,"ok","oil change") -> ok | Z7: =C7+K7+S7 -> 3 | AA7: =U7+M7+E7 -> 663 | AB7: =V7+N7+F7 -> 221 | AC7: =IF(Z7>0,AA7/Z7,0) -> 221 | AD7: =ELEC!Q7 -> 2000 | AE7: =SUM(AD7/Z7) -> 666.66667 | AF7: =SUM(AE7/1600) -> 0.41666667 | AH7: =SUM(AC7-AG7) -> #VALUE! | AI7: =AD7*AJ7 -> 514.76793 | AJ7: =305/1185 -> 0.25738397 | AK7: =AI7/Z7 -> 171.58931
A8: =ELEC!C8 -> 44110 | B8: =B7 -> 9221 | C8: =B8-B7 -> 0 | D8: =D7 -> 247280 | E8: =SUM(D8-D7) -> 0 | F8: =IF(C8>0,E8/C8,0) -> 0 | H8: =H7 -> 9298 | I8: =IF(B8-H8<=0,"ok","oil change") -> ok | J8: =J7 -> 10698 | K8: =J8-J7 -> 0 | L8: =L7 -> 238500 | M8: =SUM(L8-L7) -> 0 | N8: =IF(K8>0,M8/K8,0) -> 0 | P8: =P7 -> 10873 | Q8: =IF(J8-P8<=0,"ok","oil change") -> ok | R8: =R7 -> 11705 | S8: =R8-R7 -> 0 | T8: =T7 -> 357664 | U8: =SUM(T8-T7) -> 0 | V8: =IF(S8>0,U8/S8,0) -> 0 | X8: =X7 -> 12609 | Y8: =IF(R8-X8<=0,"ok","oil change") -> ok | Z8: =C8+K8+S8 -> 0 | AA8: =U8+M8+E8 -> 0 | AB8: =V8+N8+F8 -> 0 | AC8: =IF(Z8>0,AA8/Z8,0) -> 0 | AD8: =ELEC!Q8 -> 0 | AE8: =SUM(AD8/Z8) -> #DIV/0! | AF8: =SUM(AE8/1600) -> #DIV/0! | AG8: =SUM(320*AF8) -> #DIV/0! | AH8: =SUM(AC8-AG8) -> #DIV/0! | AI8: =AD8*AJ8 -> 0 | AJ8: =305/1185 -> 0.25738397 | AK8: =AI8/Z8 -> #DIV/0!
A9: =ELEC!C9 -> 44111 | B9: =B8 -> 9221 | C9: =B9-B8 -> 0 | D9: =D8 -> 247280 | E9: =SUM(D9-D8) -> 0 | F9: =IF(C9>0,E9/C9,0) -> 0 | H9: =H8 -> 9298 | I9: =IF(B9-H9<=0,"ok","oil change") -> ok | J9: =J8 -> 10698 | K9: =J9-J8 -> 0 | L9: =L8 -> 238500 | M9: =SUM(L9-L8) -> 0 | N9: =IF(K9>0,M9/K9,0) -> 0 | P9: =P8 -> 10873 | Q9: =IF(J9-P9<=0,"ok","oil change") -> ok | R9: =R8 -> 11705 | S9: =R9-R8 -> 0 | T9: =T8 -> 357664 | U9: =SUM(T9-T8) -> 0 | V9: =IF(S9>0,U9/S9,0) -> 0 | X9: =X8 -> 12609 | Y9: =IF(R9-X9<=0,"ok","oil change") -> ok | Z9: =C9+K9+S9 -> 0 | AA9: =U9+M9+E9 -> 0 | AB9: =V9+N9+F9 -> 0 | AC9: =IF(Z9>0,AA9/Z9,0) -> 0 | AD9: =ELEC!Q9 -> 0 | AE9: =SUM(AD9/Z9) -> #DIV/0! | AF9: =SUM(AE9/1600) -> #DIV/0! | AG9: =SUM(320*AF9) -> #DIV/0! | AH9: =SUM(AC9-AG9) -> #DIV/0! | AI9: =AD9*AJ9 -> 0 | AJ9: 0.25738397 | AK9: =IF(Z9>0,AI9/Z9,0) -> 0
A10: =ELEC!C10 -> 44112 | B10: =B9 -> 9221 | C10: =B10-B9 -> 0 | D10: =D9 -> 247280 | E10: =SUM(D10-D9) -> 0 | F10: =IF(C10>0,E10/C10,0) -> 0 | H10: =H9 -> 9298 | I10: =IF(B10-H10<=0,"ok","oil change") -> ok | J10: =J9 -> 10698 | K10: =J10-J9 -> 0 | L10: =L9 -> 238500 | M10: =SUM(L10-L9) -> 0 | N10: =IF(K10>0,M10/K10,0) -> 0 | P10: 10873 | Q10: =IF(J10-P10<=0,"ok","oil change") -> ok | R10: =R9 -> 11705 | S10: =R10-R9 -> 0 | T10: =T9 -> 357664 | U10: =SUM(T10-T9) -> 0 | V10: =IF(S10>0,U10/S10,0) -> 0 | X10: =X9 -> 12609 | Y10: =IF(R10-X10<=0,"ok","oil change") -> ok | Z10: =C10+K10+S10 -> 0 | AA10: =U10+M10+E10 -> 0 | AB10: =V10+N10+F10 -> 0 | AC10: =IF(Z10>0,AA10/Z10,0) -> 0 | AD10: =ELEC!Q10 -> 0 | AE10: =SUM(AD10/Z10) -> #DIV/0! | AF10: =SUM(AE10/1600) -> #DIV/0! | AG10: =SUM(320*AF10) -> #DIV/0! | AH10: =SUM(AC10-AG10) -> #DIV/0! | AI10: =AD10*AJ10 -> 0 | AJ10: =305/1185 -> 0.25738397 | AK10: =IF(Z10>0,AI10/Z10,0) -> 0
A11: =ELEC!C11 -> 44113 | B11: =B10 -> 9221 | C11: =B11-B10 -> 0 | D11: =D10 -> 247280 | E11: =SUM(D11-D10) -> 0 | F11: =IF(C11>0,E11/C11,0) -> 0 | H11: =H10 -> 9298 | I11: =IF(B11-H11<=0,"ok","oil change") -> ok | J11: =J10 -> 10698 | K11: =J11-J10 -> 0 | L11: =L10 -> 238500 | M11: =SUM(L11-L10) -> 0 | N11: =IF(K11>0,M11/K11,0) -> 0 | P11: =P10 -> 10873 | Q11: =IF(J11-P11<=0,"ok","oil change") -> ok | R11: =R10 -> 11705 | S11: =R11-R10 -> 0 | T11: =T10 -> 357664 | U11: =SUM(T11-T10) -> 0 | V11: =IF(S11>0,U11/S11,0) -> 0 | X11: =X10 -> 12609 | Y11: =IF(R11-X11<=0,"ok","oil change") -> ok | Z11: =C11+K11+S11 -> 0 | AA11: =U11+M11+E11 -> 0 | AB11: =V11+N11+F11 -> 0 | AC11: =IF(Z11>0,AA11/Z11,0) -> 0 | AD11: =ELEC!Q11 -> 0 | AE11: =SUM(AD11/Z11) -> #DIV/0! | AF11: =SUM(AE11/1600) -> #DIV/0! | AG11: =SUM(320*AF11) -> #DIV/0! | AH11: =SUM(AC11-AG11) -> #DIV/0! | AI11: =AD11*AJ11 -> 0 | AJ11: =305/1185 -> 0.25738397 | AK11: =IF(Z11>0,AI11/Z11,0) -> 0
A12: =ELEC!C12 -> 44114 | B12: =B11 -> 9221 | C12: =B12-B11 -> 0 | D12: =D11 -> 247280 | E12: =SUM(D12-D11) -> 0 | F12: =IF(C12>0,E12/C12,0) -> 0 | H12: =H11 -> 9298 | I12: =IF(B12-H12<=0,"ok","oil change") -> ok | J12: =J11 -> 10698 | K12: =J12-J11 -> 0 | L12: =L11 -> 238500 | M12: =SUM(L12-L11) -> 0 | N12: =IF(K12>0,M12/K12,0) -> 0 | P12: =P11 -> 10873 | Q12: =IF(J12-P12<=0,"ok","oil change") -> ok | R12: =R11 -> 11705 | S12: =R12-R11 -> 0 | T12: =T11 -> 357664 | U12: =SUM(T12-T11) -> 0 | V12: =IF(S12>0,U12/S12,0) -> 0 | X12: =X11 -> 12609 | Y12: =IF(R12-X12<=0,"ok","oil change") -> ok | Z12: =C12+K12+S12 -> 0 | AA12: =U12+M12+E12 -> 0 | AB12: =V12+N12+F12 -> 0 | AC12: =IF(Z12>0,AA12/Z12,0) -> 0 | AD12: =ELEC!Q12 -> 0 | AE12: =SUM(AD12/Z12) -> #DIV/0! | AF12: =SUM(AE12/1600) -> #DIV/0! | AG12: =SUM(320*AF12) -> #DIV/0! | AH12: =SUM(AC12-AG12) -> #DIV/0! | AI12: =AD12*AJ12 -> 0 | AJ12: =305/1185 -> 0.25738397 | AK12: =IF(Z12>0,AI12/Z12,0) -> 0
A13: =ELEC!C13 -> 44115 | B13: =B12 -> 9221 | C13: =B13-B12 -> 0 | D13: =D12 -> 247280 | E13: =SUM(D13-D12) -> 0 | F13: =IF(C13>0,E13/C13,0) -> 0 | H13: =H12 -> 9298 | I13: =IF(B13-H13<=0,"ok","oil change") -> ok | J13: =J12 -> 10698 | K13: =J13-J12 -> 0 | L13: =L12 -> 238500 | M13: =SUM(L13-L12) -> 0 | N13: =IF(K13>0,M13/K13,0) -> 0 | P13: =P12 -> 10873 | Q13: =IF(J13-P13<=0,"ok","oil change") -> ok | R13: =R12 -> 11705 | S13: =R13-R12 -> 0 | T13: =T12 -> 357664 | U13: =SUM(T13-T12) -> 0 | V13: =IF(S13>0,U13/S13,0) -> 0 | X13: =X12+180 -> 12789 | Y13: =IF(R13-X13<=0,"ok","oil change") -> ok | Z13: =C13+K13+S13 -> 0 | AA13: =U13+M13+E13 -> 0 | AB13: =V13+N13+F13 -> 0 | AC13: =IF(Z13>0,AA13/Z13,0) -> 0 | AD13: =ELEC!Q13 -> 0 | AE13: =SUM(AD13/Z13) -> #DIV/0! | AF13: =SUM(AE13/1600) -> #DIV/0! | AG13: =SUM(320*AF13) -> #DIV/0! | AH13: =SUM(AC13-AG13) -> #DIV/0! | AI13: =AD13*AJ13 -> 0 | AJ13: =305/1185 -> 0.25738397 | AK13: =IF(Z13>0,AI13/Z13,0) -> 0
A14: =ELEC!C14 -> 44116 | B14: =B13 -> 9221 | C14: =B14-B13 -> 0 | D14: =D13 -> 247280 | E14: =SUM(D14-D13) -> 0 | F14: =IF(C14>0,E14/C14,0) -> 0 | H14: =H13 -> 9298 | I14: =IF(B14-H14<=0,"ok","oil change") -> ok | J14: =J13 -> 10698 | K14: =J14-J13 -> 0 | L14: =L13 -> 238500 | M14: =SUM(L14-L13) -> 0 | N14: =IF(K14>0,M14/K14,0) -> 0 | P14: =P13 -> 10873 | Q14: =IF(J14-P14<=0,"ok","oil change") -> ok | R14: =R13 -> 11705 | S14: =R14-R13 -> 0 | T14: =T13 -> 357664 | U14: =SUM(T14-T13) -> 0 | V14: =IF(S14>0,U14/S14,0) -> 0 | X14: =X13 -> 12789 | Y14: =IF(R14-X14<=0,"ok","oil change") -> ok | Z14: =C14+K14+S14 -> 0 | AA14: =U14+M14+E14 -> 0 | AB14: =V14+N14+F14 -> 0 | AC14: =IF(Z14>0,AA14/Z14,0) -> 0 | AD14: =ELEC!Q14 -> 0 | AE14: =SUM(AD14/Z14) -> #DIV/0! | AF14: =SUM(AE14/1600) -> #DIV/0! | AG14: =SUM(320*AF14) -> #DIV/0! | AH14: =SUM(AC14-AG14) -> #DIV/0! | AI14: =AD14*AJ14 -> 0 | AJ14: =305/1185 -> 0.25738397 | AK14: =IF(Z14>0,AI14/Z14,0) -> 0
A15: =ELEC!C15 -> 44117 | B15: =B14 -> 9221 | C15: =B15-B14 -> 0 | D15: =D14 -> 247280 | E15: =SUM(D15-D14) -> 0 | F15: =IF(C15>0,E15/C15,0) -> 0 | H15: =H14 -> 9298 | I15: =IF(B15-H15<=0,"ok","oil change") -> ok | J15: =J14 -> 10698 | K15: =J15-J14 -> 0 | L15: =L14 -> 238500 | M15: =SUM(L15-L14) -> 0 | N15: =IF(K15>0,M15/K15,0) -> 0 | P15: =P14 -> 10873 | Q15: =IF(J15-P15<=0,"ok","oil change") -> ok | R15: =R14 -> 11705 | S15: =R15-R14 -> 0 | T15: =T14 -> 357664 | U15: =SUM(T15-T14) -> 0 | V15: =IF(S15>0,U15/S15,0) -> 0 | X15: =X14 -> 12789 | Y15: =IF(R15-X15<=0,"ok","oil change") -> ok | Z15: =C15+K15+S15 -> 0 | AA15: =U15+M15+E15 -> 0 | AB15: =V15+N15+F15 -> 0 | AC15: =IF(Z15>0,AA15/Z15,0) -> 0 | AD15: =ELEC!Q15 -> 0 | AE15: =SUM(AD15/Z15) -> #DIV/0! | AF15: =SUM(AE15/1600) -> #DIV/0! | AG15: =SUM(320*AF15) -> #DIV/0! | AH15: =SUM(AC15-AG15) -> #DIV/0! | AI15: =AD15*AJ15 -> 0 | AJ15: =305/1185 -> 0.25738397 | AK15: =IF(Z15>0,AI15/Z15,0) -> 0
A16: =ELEC!C16 -> 44118 | B16: =B15 -> 9221 | C16: =B16-B15 -> 0 | D16: =D15 -> 247280 | E16: =SUM(D16-D15) -> 0 | F16: =IF(C16>0,E16/C16,0) -> 0 | H16: =H15 -> 9298 | I16: =IF(B16-H16<=0,"ok","oil change") -> ok | J16: =J15 -> 10698 | K16: =J16-J15 -> 0 | L16: =L15 -> 238500 | M16: =SUM(L16-L15) -> 0 | N16: =IF(K16>0,M16/K16,0) -> 0 | P16: =P15 -> 10873 | Q16: =IF(J16-P16<=0,"ok","oil change") -> ok | R16: =R15 -> 11705 | S16: =R16-R15 -> 0 | T16: =T15 -> 357664 | U16: =SUM(T16-T15) -> 0 | V16: =IF(S16>0,U16/S16,0) -> 0 | X16: =X15 -> 12789 | Y16: =IF(R16-X16<=0,"ok","oil change") -> ok | Z16: =C16+K16+S16 -> 0 | AA16: =U16+M16+E16 -> 0 | AB16: =V16+N16+F16 -> 0 | AC16: =IF(Z16>0,AA16/Z16,0) -> 0 | AD16: =ELEC!Q16 -> 0 | AE16: =SUM(AD16/Z16) -> #DIV/0! | AF16: =SUM(AE16/1600) -> #DIV/0! | AG16: =SUM(320*AF16) -> #DIV/0! | AH16: =SUM(AC16-AG16) -> #DIV/0! | AI16: =AD16*AJ16 -> 0 | AJ16: =305/1185 -> 0.25738397 | AK16: =IF(Z16>0,AI16/Z16,0) -> 0
A17: =ELEC!C17 -> 44119 | B17: =B16 -> 9221 | C17: =B17-B16 -> 0 | D17: =D16 -> 247280 | E17: =SUM(D17-D16) -> 0 | F17: =IF(C17>0,E17/C17,0) -> 0 | H17: =H16 -> 9298 | I17: =IF(B17-H17<=0,"ok","oil change") -> ok | J17: =J16 -> 10698 | K17: =J17-J16 -> 0 | L17: =L16 -> 238500 | M17: =SUM(L17-L16) -> 0 | N17: =IF(K17>0,M17/K17,0) -> 0 | P17: =P16 -> 10873 | Q17: =IF(J17-P17<=0,"ok","oil change") -> ok | R17: =R16 -> 11705 | S17: =R17-R16 -> 0 | T17: =T16 -> 357664 | U17: =SUM(T17-T16) -> 0 | V17: =IF(S17>0,U17/S17,0) -> 0 | X17: =X16 -> 12789 | Y17: =IF(R17-X17<=0,"ok","oil change") -> ok | Z17: =C17+K17+S17 -> 0 | AA17: =U17+M17+E17 -> 0 | AB17: =V17+N17+F17 -> 0 | AC17: =IF(Z17>0,AA17/Z17,0) -> 0 | AD17: =ELEC!Q17 -> 0 | AE17: =SUM(AD17/Z17) -> #DIV/0! | AF17: =SUM(AE17/1600) -> #DIV/0! | AG17: =SUM(320*AF17) -> #DIV/0! | AH17: =SUM(AC17-AG17) -> #DIV/0! | AI17: =AD17*AJ17 -> 0 | AJ17: =305/1185 -> 0.25738397 | AK17: =IF(Z17>0,AI17/Z17,0) -> 0
A18: =ELEC!C18 -> 44120 | B18: =B17 -> 9221 | C18: =B18-B17 -> 0 | D18: =D17 -> 247280 | E18: =SUM(D18-D17) -> 0 | F18: =IF(C18>0,E18/C18,0) -> 0 | H18: =H17 -> 9298 | I18: =IF(B18-H18<=0,"ok","oil change") -> ok | J18: =J17 -> 10698 | K18: =J18-J17 -> 0 | L18: =L17 -> 238500 | M18: =SUM(L18-L17) -> 0 | N18: =IF(K18>0,M18/K18,0) -> 0 | P18: =P17 -> 10873 | Q18: =IF(J18-P14<=0,"ok","oil change") -> ok | R18: =R17 -> 11705 | S18: =R18-R17 -> 0 | T18: =T17 -> 357664 | U18: =SUM(T18-T17) -> 0 | V18: =IF(S18>0,U18/S18,0) -> 0 | X18: =X17 -> 12789 | Y18: =IF(R18-X18<=0,"ok","oil change") -> ok | Z18: =C18+K18+S18 -> 0 | AA18: =U18+M18+E18 -> 0 | AB18: =V18+N18+F18 -> 0 | AC18: =IF(Z18>0,AA18/Z18,0) -> 0 | AD18: =ELEC!Q18 -> 0 | AE18: =SUM(AD18/Z18) -> #DIV/0! | AF18: =SUM(AE18/1600) -> #DIV/0! | AG18: =SUM(320*AF18) -> #DIV/0! | AH18: =SUM(AC18-AG18) -> #DIV/0! | AI18: =AD18*AJ18 -> 0 | AJ18: =305/1185 -> 0.25738397 | AK18: =IF(Z18>0,AI18/Z18,0) -> 0
A19: =ELEC!C19 -> 44121 | B19: =B18 -> 9221 | C19: =B19-B18 -> 0 | D19: =D18 -> 247280 | E19: =SUM(D19-D18) -> 0 | F19: =IF(C19>0,E19/C19,0) -> 0 | H19: =H18 -> 9298 | I19: =IF(B19-H19<=0,"ok","oil change") -> ok | J19: =J18 -> 10698 | K19: =J19-J18 -> 0 | L19: =L18 -> 238500 | M19: =SUM(L19-L18) -> 0 | N19: =IF(K19>0,M19/K19,0) -> 0 | P19: =P18 -> 10873 | Q19: =IF(J19-P19<=0,"ok","oil change") -> ok | R19: =R18 -> 11705 | S19: =R19-R18 -> 0 | T19: =T18 -> 357664 | U19: =SUM(T19-T18) -> 0 | V19: =IF(S19>0,U19/S19,0) -> 0 | X19: =X18 -> 12789 | Y19: =IF(R19-X19<=0,"ok","oil change") -> ok | Z19: =C19+K19+S19 -> 0 | AA19: =U19+M19+E19 -> 0 | AB19: =V19+N19+F19 -> 0 | AC19: =IF(Z19>0,AA19/Z19,0) -> 0 | AD19: =ELEC!Q19 -> 0 | AE19: =SUM(AD19/Z19) -> #DIV/0! | AF19: =SUM(AE19/1600) -> #DIV/0! | AG19: =SUM(320*AF19) -> #DIV/0! | AH19: =SUM(AC19-AG19) -> #DIV/0! | AI19: =AD19*AJ19 -> 0 | AJ19: =305/1185 -> 0.25738397 | AK19: =IF(Z19>0,AI19/Z19,0) -> 0
A20: =ELEC!C20 -> 44122 | B20: =B19 -> 9221 | C20: =B20-B19 -> 0 | D20: =D19 -> 247280 | E20: =SUM(D20-D19) -> 0 | F20: =IF(C20>0,E20/C20,0) -> 0 | H20: =H19 -> 9298 | I20: =IF(B20-H20<=0,"ok","oil change") -> ok | J20: =J19 -> 10698 | K20: =J20-J19 -> 0 | L20: =L19 -> 238500 | M20: =SUM(L20-L19) -> 0 | N20: =IF(K20>0,M20/K20,0) -> 0 | P20: =P19 -> 10873 | Q20: =IF(J20-P20<=0,"ok","oil change") -> ok | R20: =R19 -> 11705 | S20: =R20-R19 -> 0 | T20: =T19 -> 357664 | U20: =SUM(T20-T19) -> 0 | V20: =IF(S20>0,U20/S20,0) -> 0 | X20: =X19 -> 12789 | Y20: =IF(R20-X20<=0,"ok","oil change") -> ok | Z20: =C20+K20+S20 -> 0 | AA20: =U20+M20+E20 -> 0 | AB20: =V20+N20+F20 -> 0 | AC20: =IF(Z20>0,AA20/Z20,0) -> 0 | AD20: =ELEC!Q20 -> 0 | AE20: =SUM(AD20/Z20) -> #DIV/0! | AF20: =SUM(AE20/1600) -> #DIV/0! | AG20: =SUM(320*AF20) -> #DIV/0! | AH20: =SUM(AC20-AG20) -> #DIV/0! | AI20: =AD20*AJ20 -> 0 | AJ20: =305/1185 -> 0.25738397 | AK20: =IF(Z20>0,AI20/Z20,0) -> 0
A21: =ELEC!C21 -> 44123 | B21: =B20 -> 9221 | C21: =B21-B20 -> 0 | D21: =D20 -> 247280 | E21: =SUM(D21-D20) -> 0 | F21: =IF(C21>0,E21/C21,0) -> 0 | H21: =H20 -> 9298 | I21: =IF(B21-H21<=0,"ok","oil change") -> ok | J21: =J20 -> 10698 | K21: =J21-J20 -> 0 | L21: =L20 -> 238500 | M21: =SUM(L21-L20) -> 0 | N21: =IF(K21>0,M21/K21,0) -> 0 | P21: =P20 -> 10873 | Q21: =IF(J21-P21<=0,"ok","oil change") -> ok | R21: =R20 -> 11705 | S21: =R21-R20 -> 0 | T21: =T20 -> 357664 | U21: =SUM(T21-T20) -> 0 | V21: =IF(S21>0,U21/S21,0) -> 0 | X21: =X20 -> 12789 | Y21: =Y20 -> ok | Z21: =C21+K21+S21 -> 0 | AA21: =U21+M21+E21 -> 0 | AB21: =V21+N21+F21 -> 0 | AC21: =IF(Z21>0,AA21/Z21,0) -> 0 | AD21: =ELEC!Q21 -> 0 | AE21: =SUM(AD21/Z21) -> #DIV/0! | AF21: =SUM(AE21/1600) -> #DIV/0! | AG21: =SUM(320*AF21) -> #DIV/0! | AH21: =SUM(AC21-AG21) -> #DIV/0! | AI21: =AD21*AJ21 -> 0 | AJ21: =305/1185 -> 0.25738397 | AK21: =IF(Z21>0,AI21/Z21,0) -> 0
A22: =ELEC!C22 -> 44124 | B22: =B21 -> 9221 | C22: =B22-B21 -> 0 | D22: =D21 -> 247280 | E22: =SUM(D22-D21) -> 0 | F22: =IF(C22>0,E22/C22,0) -> 0 | H22: =H21 -> 9298 | I22: =IF(B22-H22<=0,"ok","oil change") -> ok | J22: =J21 -> 10698 | K22: =J22-J21 -> 0 | L22: =L21 -> 238500 | M22: =SUM(L22-L21) -> 0 | N22: =IF(K22>0,M22/K22,0) -> 0 | P22: =P21 -> 10873 | Q22: =IF(J22-P22<=0,"ok","oil change") -> ok | R22: =R21 -> 11705 | S22: =R22-R21 -> 0 | T22: =T21 -> 357664 | U22: =SUM(T22-T21) -> 0 | V22: =IF(S22>0,U22/S22,0) -> 0 | X22: =X21 -> 12789 | Y22: =IF(R22-X22<=0,"ok","oil change") -> ok | Z22: =C22+K22+S22 -> 0 | AA22: =U22+M22+E22 -> 0 | AB22: =V22+N22+F22 -> 0 | AC22: =IF(Z22>0,AA22/Z22,0) -> 0 | AD22: =ELEC!Q22 -> 0 | AE22: =SUM(AD22/Z22) -> #DIV/0! | AF22: =SUM(AE22/1600) -> #DIV/0! | AG22: =SUM(320*AF22) -> #DIV/0! | AH22: =SUM(AC22-AG22) -> #DIV/0! | AI22: =AD22*AJ22 -> 0 | AJ22: =305/1185 -> 0.25738397 | AK22: =IF(Z22>0,AI22/Z22,0) -> 0
A23: =ELEC!C23 -> 44125 | B23: =B22 -> 9221 | C23: =B23-B22 -> 0 | D23: =D22 -> 247280 | E23: =SUM(D23-D22) -> 0 | F23: =IF(C23>0,E23/C23,0) -> 0 | H23: =H22 -> 9298 | I23: =IF(B23-H23<=0,"ok","oil change") -> ok | J23: =J22 -> 10698 | K23: =J23-J22 -> 0 | L23: =L22 -> 238500 | M23: =SUM(L23-L22) -> 0 | N23: =IF(K23>0,M23/K23,0) -> 0 | P23: =P22 -> 10873 | Q23: =IF(J23-P23<=0,"ok","oil change") -> ok | R23: =R22 -> 11705 | S23: =R23-R22 -> 0 | T23: =T22 -> 357664 | U23: =SUM(T23-T22) -> 0 | V23: =IF(S23>0,U23/S23,0) -> 0 | X23: =X22 -> 12789 | Y23: =IF(R23-X23<=0,"ok","oil change") -> ok | Z23: =C23+K23+S23 -> 0 | AA23: =U23+M23+E23 -> 0 | AB23: =V23+N23+F23 -> 0 | AC23: =IF(Z23>0,AA23/Z23,0) -> 0 | AD23: =ELEC!Q23 -> 0 | AE23: =SUM(AD23/Z23) -> #DIV/0! | AF23: =SUM(AE23/1600) -> #DIV/0! | AG23: =SUM(320*AF23) -> #DIV/0! | AH23: =SUM(AC23-AG23) -> #DIV/0! | AI23: =AD23*AJ23 -> 0 | AJ23: =305/1185 -> 0.25738397 | AK23: =IF(Z23>0,AI23/Z23,0) -> 0
A24: =ELEC!C24 -> 44126 | B24: =B23 -> 9221 | C24: =B24-B23 -> 0 | D24: =D23 -> 247280 | E24: =SUM(D24-D23) -> 0 | F24: =IF(C24>0,E24/C24,0) -> 0 | H24: =H23 -> 9298 | I24: =IF(B24-H24<=0,"ok","oil change") -> ok | J24: =J23 -> 10698 | K24: =J24-J23 -> 0 | L24: =L23 -> 238500 | M24: =SUM(L24-L23) -> 0 | N24: =IF(K24>0,M24/K24,0) -> 0 | P24: =P23 -> 10873 | Q24: =IF(J24-P24<=0,"ok","oil change") -> ok | R24: =R23 -> 11705 | S24: =R24-R23 -> 0 | T24: =T23 -> 357664 | U24: =SUM(T24-T23) -> 0 | V24: =IF(S24>0,U24/S24,0) -> 0 | X24: =X23 -> 12789 | Y24: =IF(R24-X24<=0,"ok","oil change") -> ok | Z24: =C24+K24+S24 -> 0 | AA24: =U24+M24+E24 -> 0 | AB24: =V24+N24+F24 -> 0 | AC24: =IF(Z24>0,AA24/Z24,0) -> 0 | AD24: =ELEC!Q24 -> 0 | AE24: =SUM(AD24/Z24) -> #DIV/0! | AF24: =SUM(AE24/1600) -> #DIV/0! | AG24: =SUM(320*AF24) -> #DIV/0! | AH24: =SUM(AC24-AG24) -> #DIV/0! | AI24: =AD24*AJ24 -> 0 | AJ24: =305/1185 -> 0.25738397 | AK24: =IF(Z24>0,AI24/Z24,0) -> 0
A25: =ELEC!C25 -> 44127 | B25: =B24 -> 9221 | C25: =B25-B24 -> 0 | D25: =D24 -> 247280 | E25: =SUM(D25-D24) -> 0 | F25: =IF(C25>0,E25/C25,0) -> 0 | H25: =H24 -> 9298 | I25: =IF(B25-H25<=0,"ok","oil change") -> ok | J25: =J24 -> 10698 | K25: =J25-J24 -> 0 | L25: =L24 -> 238500 | M25: =SUM(L25-L24) -> 0 | N25: =IF(K25>0,M25/K25,0) -> 0 | P25: =P24 -> 10873 | Q25: =IF(J25-P25<=0,"ok","oil change") -> ok | R25: =R24 -> 11705 | S25: =R25-R24 -> 0 | T25: =T24 -> 357664 | U25: =SUM(T25-T24) -> 0 | V25: =IF(S25>0,U25/S25,0) -> 0 | X25: =X24 -> 12789 | Y25: =IF(R25-X25<=0,"ok","oil change") -> ok | Z25: =C25+K25+S25 -> 0 | AA25: =U25+M25+E25 -> 0 | AB25: =V25+N25+F25 -> 0 | AC25: =IF(Z25>0,AA25/Z25,0) -> 0 | AD25: =ELEC!Q25 -> 0 | AE25: =SUM(AD25/Z25) -> #DIV/0! | AF25: =SUM(AE25/1600) -> #DIV/0! | AG25: =SUM(320*AF25) -> #DIV/0! | AH25: =SUM(AC25-AG25) -> #DIV/0! | AI25: =AD25*AJ25 -> 0 | AJ25: =305/1185 -> 0.25738397 | AK25: =IF(Z25>0,AI25/Z25,0) -> 0
A26: =ELEC!C26 -> 44128 | B26: =B25 -> 9221 | C26: =B26-B25 -> 0 | D26: =D25 -> 247280 | E26: =SUM(D26-D25) -> 0 | F26: =IF(C26>0,E26/C26,0) -> 0 | H26: =H25 -> 9298 | I26: =IF(B26-H26<=0,"ok","oil change") -> ok | J26: =J25 -> 10698 | K26: =J26-J25 -> 0 | L26: =L25 -> 238500 | M26: =SUM(L26-L25) -> 0 | N26: =IF(K26>0,M26/K26,0) -> 0 | P26: =P25 -> 10873 | Q26: =IF(J26-P26<=0,"ok","oil change") -> ok | R26: =R25 -> 11705 | S26: =R26-R25 -> 0 | T26: =T25 -> 357664 | U26: =SUM(T26-T25) -> 0 | V26: =IF(S26>0,U26/S26,0) -> 0 | X26: =X25 -> 12789 | Y26: =IF(R26-X26<=0,"ok","oil change") -> ok | Z26: =C26+K26+S26 -> 0 | AA26: =U26+M26+E26 -> 0 | AB26: =V26+N26+F26 -> 0 | AC26: =IF(Z26>0,AA26/Z26,0) -> 0 | AD26: =ELEC!Q26 -> 0 | AE26: =SUM(AD26/Z26) -> #DIV/0! | AF26: =SUM(AE26/1600) -> #DIV/0! | AG26: =SUM(320*AF26) -> #DIV/0! | AH26: =SUM(AC26-AG26) -> #DIV/0! | AI26: =AD26*AJ26 -> 0 | AJ26: =305/1185 -> 0.25738397 | AK26: =IF(Z26>0,AI26/Z26,0) -> 0
A27: =ELEC!C27 -> 44129 | B27: =B26 -> 9221 | C27: =B27-B26 -> 0 | D27: =D26 -> 247280 | E27: =SUM(D27-D26) -> 0 | F27: =IF(C27>0,E27/C27,0) -> 0 | H27: =H26 -> 9298 | I27: =IF(B27-H27<=0,"ok","oil change") -> ok | J27: =J26 -> 10698 | K27: =J27-J26 -> 0 | L27: =L26 -> 238500 | M27: =SUM(L27-L26) -> 0 | N27: =IF(K27>0,M27/K27,0) -> 0 | P27: =P26 -> 10873 | Q27: =IF(J27-P27<=0,"ok","oil change") -> ok | R27: =R26 -> 11705 | S27: =R27-R26 -> 0 | T27: =T26 -> 357664 | U27: =SUM(T27-T26) -> 0 | V27: =IF(S27>0,U27/S27,0) -> 0 | X27: =X26 -> 12789 | Y27: =IF(R27-X27<=0,"ok","oil change") -> ok | Z27: =C27+K27+S27 -> 0 | AA27: =U27+M27+E27 -> 0 | AB27: =V27+N27+F27 -> 0 | AC27: =IF(Z27>0,AA27/Z27,0) -> 0 | AD27: =ELEC!Q27 -> 0 | AE27: =SUM(AD27/Z27) -> #DIV/0! | AF27: =SUM(AE27/1600) -> #DIV/0! | AG27: =SUM(320*AF27) -> #DIV/0! | AH27: =SUM(AC27-AG27) -> #DIV/0! | AI27: =AD27*AJ27 -> 0 | AJ27: =305/1185 -> 0.25738397 | AK27: =IF(Z27>0,AI27/Z27,0) -> 0
A28: =ELEC!C28 -> 44130 | B28: =B27 -> 9221 | C28: =B28-B27 -> 0 | D28: =D27 -> 247280 | E28: =SUM(D28-D27) -> 0 | F28: =IF(C28>0,E28/C28,0) -> 0 | H28: =H27 -> 9298 | I28: =IF(B28-H28<=0,"ok","oil change") -> ok | J28: =J27 -> 10698 | K28: =J28-J27 -> 0 | L28: =L27 -> 238500 | M28: =SUM(L28-L27) -> 0 | N28: =IF(K28>0,M28/K28,0) -> 0 | P28: =P27 -> 10873 | Q28: =IF(J28-P28<=0,"ok","oil change") -> ok | R28: =R27 -> 11705 | S28: =R28-R27 -> 0 | T28: =T27 -> 357664 | U28: =SUM(T28-T27) -> 0 | V28: =IF(S28>0,U28/S28,0) -> 0 | X28: =X27 -> 12789 | Y28: =IF(R28-X28<=0,"ok","oil change") -> ok | Z28: =C28+K28+S28 -> 0 | AA28: =U28+M28+E28 -> 0 | AB28: =V28+N28+F28 -> 0 | AC28: =IF(Z28>0,AA28/Z28,0) -> 0 | AD28: =ELEC!Q28 -> 0 | AE28: =SUM(AD28/Z28) -> #DIV/0! | AF28: =SUM(AE28/1600) -> #DIV/0! | AG28: =SUM(320*AF28) -> #DIV/0! | AH28: =SUM(AC28-AG28) -> #DIV/0! | AI28: =AD28*AJ28 -> 0 | AJ28: =305/1185 -> 0.25738397 | AK28: =IF(Z28>0,AI28/Z28,0) -> 0
A29: =ELEC!C29 -> 44131 | B29: =B28 -> 9221 | C29: =B29-B28 -> 0 | D29: =D28 -> 247280 | E29: =SUM(D29-D28) -> 0 | F29: =IF(C29>0,E29/C29,0) -> 0 | H29: =H28 -> 9298 | I29: =IF(B29-H29<=0,"ok","oil change") -> ok | J29: =J28 -> 10698 | K29: =J29-J28 -> 0 | L29: =L28 -> 238500 | M29: =SUM(L29-L28) -> 0 | N29: =IF(K29>0,M29/K29,0) -> 0 | P29: =P28 -> 10873 | Q29: =IF(J29-P29<=0,"ok","oil change") -> ok | R29: =R28 -> 11705 | S29: =R29-R28 -> 0 | T29: =T28 -> 357664 | U29: =SUM(T29-T28) -> 0 | V29: =IF(S29>0,U29/S29,0) -> 0 | X29: =X28 -> 12789 | Y29: =IF(R29-X29<=0,"ok","oil change") -> ok | Z29: =C29+K29+S29 -> 0 | AA29: =U29+M29+E29 -> 0 | AB29: =V29+N29+F29 -> 0 | AC29: =IF(Z29>0,AA29/Z29,0) -> 0 | AD29: =ELEC!Q29 -> 0 | AE29: =SUM(AD29/Z29) -> #DIV/0! | AF29: =SUM(AE29/1600) -> #DIV/0! | AG29: =SUM(320*AF29) -> #DIV/0! | AH29: =SUM(AC29-AG29) -> #DIV/0! | AI29: =AD29*AJ29 -> 0 | AJ29: =305/1185 -> 0.25738397 | AK29: =IF(Z29>0,AI29/Z29,0) -> 0
A30: =ELEC!C30 -> 44132 | B30: =B29 -> 9221 | C30: =B30-B29 -> 0 | D30: =D29 -> 247280 | E30: =SUM(D30-D29) -> 0 | F30: =IF(C30>0,E30/C30,0) -> 0 | H30: =H29 -> 9298 | I30: =IF(B30-H30<=0,"ok","oil change") -> ok | J30: =J29 -> 10698 | K30: =J30-J29 -> 0 | L30: =L29 -> 238500 | M30: =SUM(L30-L29) -> 0 | N30: =IF(K30>0,M30/K30,0) -> 0 | P30: =P29 -> 10873 | Q30: =IF(J30-P30<=0,"ok","oil change") -> ok | R30: =R29 -> 11705 | S30: =R30-R29 -> 0 | T30: =T29 -> 357664 | U30: =SUM(T30-T29) -> 0 | V30: =IF(S30>0,U30/S30,0) -> 0 | X30: =X29 -> 12789 | Y30: =IF(R30-X30<=0,"ok","oil change") -> ok | Z30: =C30+K30+S30 -> 0 | AA30: =U30+M30+E30 -> 0 | AB30: =V30+N30+F30 -> 0 | AC30: =IF(Z30>0,AA30/Z30,0) -> 0 | AD30: =ELEC!Q30 -> 0 | AE30: =SUM(AD30/Z30) -> #DIV/0! | AF30: =SUM(AE30/1600) -> #DIV/0! | AG30: =SUM(320*AF30) -> #DIV/0! | AH30: =SUM(AC30-AG30) -> #DIV/0! | AI30: =AD30*AJ30 -> 0 | AJ30: =305/1185 -> 0.25738397 | AK30: =IF(Z30>0,AI30/Z30,0) -> 0
A31: =ELEC!C31 -> 44133 | B31: =B30 -> 9221 | C31: =B31-B30 -> 0 | D31: =D30 -> 247280 | E31: =SUM(D31-D30) -> 0 | F31: =IF(C31>0,E31/C31,0) -> 0 | H31: =H30 -> 9298 | I31: =IF(B31-H31<=0,"ok","oil change") -> ok | J31: =J30 -> 10698 | K31: =J31-J30 -> 0 | L31: =L30 -> 238500 | M31: =SUM(L31-L30) -> 0 | N31: =IF(K31>0,M31/K31,0) -> 0 | P31: =P30 -> 10873 | Q31: =IF(J31-P31<=0,"ok","oil change") -> ok | R31: =R30 -> 11705 | S31: =R31-R30 -> 0 | T31: =T30 -> 357664 | U31: =SUM(T31-T30) -> 0 | V31: =IF(S31>0,U31/S31,0) -> 0 | X31: =X30 -> 12789 | Y31: =IF(R31-X31<=0,"ok","oil change") -> ok | Z31: =C31+K31+S31 -> 0 | AA31: =U31+M31+E31 -> 0 | AB31: =V31+N31+F31 -> 0 | AC31: =IF(Z31>0,AA31/Z31,0) -> 0 | AD31: =ELEC!Q31 -> 0 | AE31: =SUM(AD31/Z31) -> #DIV/0! | AF31: =SUM(AE31/1600) -> #DIV/0! | AG31: =SUM(320*AF31) -> #DIV/0! | AH31: =SUM(AC31-AG31) -> #DIV/0! | AI31: =AD31*AJ31 -> 0 | AJ31: =305/1185 -> 0.25738397 | AK31: =IF(Z31>0,AI31/Z31,0) -> 0
A32: =ELEC!C32 -> 44134 | B32: =B31 -> 9221 | C32: =B32-B31 -> 0 | D32: =D31 -> 247280 | E32: =SUM(D32-D31) -> 0 | F32: =IF(C32>0,E32/C32,0) -> 0 | H32: =H31 -> 9298 | I32: =IF(B32-H32<=0,"ok","oil change") -> ok | J32: =J31 -> 10698 | K32: =J32-J31 -> 0 | L32: =L31 -> 238500 | M32: =SUM(L32-L31) -> 0 | N32: =IF(K32>0,M32/K32,0) -> 0 | P32: =P31 -> 10873 | Q32: =IF(J32-P32<=0,"ok","oil change") -> ok | R32: =R31 -> 11705 | S32: =R32-R31 -> 0 | T32: =T31 -> 357664 | U32: =SUM(T32-T31) -> 0 | V32: =IF(S32>0,U32/S32,0) -> 0 | X32: =X31 -> 12789 | Y32: =IF(R32-X32<=0,"ok","oil change") -> ok | Z32: =C32+K32+S32 -> 0 | AA32: =U32+M32+E32 -> 0 | AB32: =V32+N32+F32 -> 0 | AC32: =IF(Z32>0,AA32/Z32,0) -> 0 | AD32: =ELEC!Q32 -> 0 | AE32: =SUM(AD32/Z32) -> #DIV/0! | AF32: =SUM(AE32/1600) -> #DIV/0! | AG32: =SUM(320*AF32) -> #DIV/0! | AH32: =SUM(AC32-AG32) -> #DIV/0! | AI32: =AD32*AJ32 -> 0 | AJ32: =305/1185 -> 0.25738397 | AK32: =IF(Z32>0,AI32/Z32,0) -> 0
A33: =ELEC!C33 -> 44135 | B33: =B32 -> 9221 | C33: =B33-B32 -> 0 | D33: =D32 -> 247280 | E33: =SUM(D33-D32) -> 0 | F33: =IF(C33>0,E33/C33,0) -> 0 | H33: =H32 -> 9298 | I33: =IF(B33-H33<=0,"ok","oil change") -> ok | J33: =J32 -> 10698 | K33: =J33-J32 -> 0 | L33: =L32 -> 238500 | M33: =SUM(L33-L32) -> 0 | N33: =IF(K33>0,M33/K33,0) -> 0 | P33: =P32 -> 10873 | Q33: =IF(J33-P33<=0,"ok","oil change") -> ok | R33: =R32 -> 11705 | S33: =R33-R32 -> 0 | T33: =T32 -> 357664 | U33: =SUM(T33-T32) -> 0 | V33: =IF(S33>0,U33/S33,0) -> 0 | X33: =X32 -> 12789 | Y33: =IF(R33-X33<=0,"ok","oil change") -> ok | Z33: =C33+K33+S33 -> 0 | AA33: =U33+M33+E33 -> 0 | AB33: =V33+N33+F33 -> 0 | AC33: =IF(Z33>0,AA33/Z33,0) -> 0 | AD33: =ELEC!Q33 -> 0 | AE33: =SUM(AD33/Z33) -> #DIV/0! | AF33: =SUM(AE33/1600) -> #DIV/0! | AG33: =SUM(320*AF33) -> #DIV/0! | AH33: =SUM(AC33-AG33) -> #DIV/0! | AI33: =AD33*AJ33 -> 0 | AJ33: =305/1185 -> 0.25738397 | AK33: =IF(Z33>0,AI33/Z33,0) -> 0
P34: =+O34/3 -> 0 | U34: =SUM(C35:S35) -> 13 | X34: 341 | Z34: =SUM(Z3:Z32) -> 13
C35: =SUM(C3:C32) -> 13 | K35: =SUM(K3:K32) -> 0 | S35: =SUM(S3:S32) -> 0

Sheet Swimming Pool quality check 
A1: Date | B1: Swimming Pool | E1: Jacuzzi | H1: Water meter SW Pool | I1: Cons M3 | J1: Time
B2: 1.0-1.5 | C2: 7.2-7.4 | E2: 3.5 | F2: 7.2-7.4
B3: Chl | C3: PH | D3: T C | E3: Chl | F3: PH | G3: T C
H4: 0 | M4: Counter 1 | N4: Counter 2 | O4: Total
A5: =ELEC!C2 -> 44104 | H5: 6555 | I5: ='[3]Swimming Pool quality check '!$B$36 -> 2.5 | J5: ='[5]Swimming Pool quality check '!J36 -> 0.33333333 | K5: 0 | L5: =A5 -> 44104 | M5: 6541 | N5: ='[6]Swimming Pool quality check '!N36 -> 642 | O5: ='[6]Swimming Pool quality check '!O36 -> 6836
A6: =ELEC!C3 -> 44105 | H6: 6555 | I6: =H6-H5 -> 0 | J6: 0.29166667 | L6: =A6 -> 44105 | M6: 6543 | N6: 487 | O6: =M6+N6 -> 7030
A7: =ELEC!C4 -> 44106 | H7: 6555 | I7: =H7-H6 -> 0 | J7: 0.29166667 | L7: =A7 -> 44106 | M7: 6550 | N7: 487 | O7: =M7+N7 -> 7037
A8: =ELEC!C5 -> 44107 | H8: 6555 | I8: =H8-H7 -> 0 | J8: 0.29166667 | L8: =A8 -> 44107 | M8: 6555 | N8: 487 | O8: =M8+N8 -> 7042
A9: =ELEC!C6 -> 44108 | H9: 6555 | I9: =H9-H8 -> 0 | J9: 0.29166667 | L9: =A9 -> 44108 | M9: =M8 -> 6555 | N9: 487 | O9: =M9+N9 -> 7042
A10: =ELEC!C7 -> 44109 | H10: 6555 | I10: =H10-H9 -> 0 | J10: 0.29166667 | L10: =A10 -> 44109 | M10: =M9 -> 6555 | N10: 487 | O10: =M10+N10 -> 7042
A11: =ELEC!C8 -> 44110 | H11: 6555 | I11: =H11-H10 -> 0 | J11: 0.29166667 | L11: =A11 -> 44110 | M11: =M10 -> 6555 | N11: 487 | O11: =M11+N11 -> 7042
A12: =ELEC!C9 -> 44111 | H12: 6555 | I12: =H12-H11 -> 0 | J12: 0.29166667 | L12: =A12 -> 44111 | M12: =M11 -> 6555 | N12: 487 | O12: =M12+N12 -> 7042
A13: =ELEC!C10 -> 44112 | H13: 6555 | I13: =H13-H12 -> 0 | J13: 0.29166667 | L13: =A13 -> 44112 | M13: =M12 -> 6555 | N13: 487 | O13: =M13+N13 -> 7042
A14: =ELEC!C11 -> 44113 | H14: 6555 | I14: =H14-H13 -> 0 | J14: 0.29166667 | L14: =A14 -> 44113 | M14: =M13 -> 6555 | N14: 487 | O14: =M14+N14 -> 7042
A15: =ELEC!C12 -> 44114 | H15: 6555 | I15: =H15-H14 -> 0 | J15: 0.29166667 | L15: =A15 -> 44114 | M15: =M14 -> 6555 | N15: 487 | O15: =M15+N15 -> 7042
A16: =ELEC!C13 -> 44115 | H16: 6555 | I16: =H16-H15 -> 0 | J16: 0.29166667 | L16: =A16 -> 44115 | M16: =M15 -> 6555 | N16: 487 | O16: =M16+N16 -> 7042
A17: =ELEC!C14 -> 44116 | H17: 6555 | I17: =H17-H16 -> 0 | J17: 0.29166667 | L17: =A17 -> 44116 | M17: =M16 -> 6555 | N17: 487 | O17: =M17+N17 -> 7042
A18: =ELEC!C15 -> 44117 | H18: 6555 | I18: =H18-H17 -> 0 | J18: 0.29166667 | L18: =A18 -> 44117 | M18: =M17 -> 6555 | N18: 487 | O18: =M18+N18 -> 7042
A19: =ELEC!C16 -> 44118 | H19: 6555 | I19: =H19-H18 -> 0 | J19: 0.29166667 | L19: =A19 -> 44118 | M19: =M18 -> 6555 | N19: 487 | O19: =M19+N19 -> 7042
A20: =ELEC!C17 -> 44119 | H20: 6555 | I20: =H20-H19 -> 0 | J20: 0.29166667 | L20: =A20 -> 44119 | M20: =M19 -> 6555 | N20: 487 | O20: =M20+N20 -> 7042
... A36: =ELEC!C33 -> 44135 | H36: 6555 | I36: =H36-H35 -> 0 | J36: 0.29166667 | L36: =A36 -> 44135 | M36: =M35 -> 6555 | N36: 642 | O36: =M36+N36 -> 7197

Sheet EDl log
A1: Date | B1: EDL | C1: Conso EDL KW | F1: Peak | G1: 320 | H1: Day | I1: 112 | J1: Night | K1: 80
L2: P | M2: D | N2: N | O2: fee | P2: T EDL | Q2: Gen | R2: Elc C
A3: =ELEC!C2 -> 44104 | B3: ='[2]EDl log'!B33 -> 469756 | C3: ='[2]EDl log'!C33 -> 4253 | D3: ='[2]EDl log'!D33 -> 4254 | E3: ='[2]EDl log'!E33 -> 469757 | F3: ='[2]EDl log'!F33 -> 63298 | G3: ='[2]EDl log'!G33 -> 695 | H3: ='[2]EDl log'!H33 -> 242131 | I3: ='[2]EDl log'!I33 -> 1832 | ... T3: ='[2]EDl log'!T33 -> 0.10054052 | Z3: VAT | AA3: 0.1
A4: =ELEC!C3 -> 44105 | B4: 474142 | C4: =SUM(B4-B3) -> 4386 | D4: =SUM(G4+I4+K4) -> 4379 | E4: =B3+D4 -> 474135 | F4: 63931 | G4: =F4-F3 -> 633 | H4: 244754 | I4: =H4-H3 -> 2623 | J4: 165451 | K4: =J4-J3 -> 1123 | L4: =SUM(G4*$Y$28)/1507.5 -> 134.36816 | M4: =SUM(I4*$Y$27)/1507.5 -> 194.87629 | N4: =SUM(K4*$Y$26)/1507.5 -> 59.595357 | O4: =($AC$31/$A$38)/1507.5 -> 24.968232 | P4: =SUM(L4:O4) -> 413.80803 | Q4: =SUM(-tanks!AX6*tanks!$AU$37) -> 0 | R4: =SUM(P4:Q4) -> 413.80803 | S4: =SUM(ELEC!N3) -> 10203 | T4: =IF(S4>0,R4/S4,0) -> 0.040557486 | V4: ='[7]EDl log'!V21 -> EDL | W4: 44094 | Z4: Subscription
A5: =ELEC!C4 -> 44106 | B5: 479360 | C5: =SUM(B5-B4) -> 5218 | D5: =SUM(G5+I5+K5) -> 5225 | E5: =B4+D5 -> 479367 | F5: 64751 | G5: =F5-F4 -> 820 | H5: 247413 | I5: =H5-H4 -> 2659 | J5: 167197 | K5: =J5-J4 -> 1746 | L5: =SUM(G5*$Y$28)/1507.5 -> 174.06302 | M5: =SUM(I5*$Y$27)/1507.5 -> 197.55091 | N5: =SUM(K5*$Y$26)/1507.5 -> 92.656716 | O5: =($AC$31/$A$38)/1507.5 -> 24.968232 | P5: =SUM(L5:O5) -> 489.23888 | Q5: =SUM(-tanks!AX7*tanks!$AU$37) -> 0 | R5: =SUM(P5:Q5) -> 489.23888 | S5: =SUM(ELEC!N4) -> 10041 | T5: =IF(S5>0,R5/S5,0) -> 0.048724119 | Z5: KVA | AA5: ='[6]EDl log'!AA22 -> 5000
A6: =ELEC!C5 -> 44107 | B6: 483076 | C6: =SUM(B6-B5) -> 3716 | D6: =SUM(G6+I6+K6) -> 3714 | E6: =B5+D6 -> 483074 | F6: 65640 | G6: =F6-F5 -> 889 | H6: 249049 | I6: =H6-H5 -> 1636 | J6: 168386 | K6: =J6-J5 -> 1189 | L6: =SUM(G6*$Y$28)/1507.5 -> 188.70978 | M6: =SUM(I6*$Y$27)/1507.5 -> 121.54693 | N6: =SUM(K6*$Y$26)/1507.5 -> 63.097844 | O6: =($AC$31/$A$38)/1507.5 -> 24.968232 | P6: =SUM(L6:O6) -> 398.32279 | Q6: =SUM(-tanks!AX8*tanks!$AU$37) -> 0 | R6: =SUM(P6:Q6) -> 398.32279 | S6: =SUM(ELEC!N5) -> 8684 | T6: =IF(S6>0,R6/S6,0) -> 0.045868585
A7: =ELEC!C6 -> 44108 | B7: 486458 | C7: =SUM(B7-B6) -> 3382 | D7: =SUM(G7+I7+K7) -> 3384 | E7: =B6+D7 -> 486460 | F7: 66328 | G7: =F7-F6 -> 688 | H7: 250661 | I7: =H7-H6 -> 1612 | J7: 169470 | K7: =J7-J6 -> 1084 | L7: =SUM(G7*$Y$28)/1507.5 -> 146.04312 | M7: =SUM(I7*$Y$27)/1507.5 -> 119.76385 | N7: =SUM(K7*$Y$26)/1507.5 -> 57.525705 | O7: =($AC$31/$A$38)/1507.5 -> 24.968232 | P7: =SUM(L7:O7) -> 348.3009 | Q7: =SUM(-tanks!AX9*tanks!$AU$37) -> 0 | R7: =SUM(P7:Q7) -> 348.3009 | S7: =SUM(ELEC!N6) -> 7992 | T7: =IF(S7>0,R7/S7,0) -> 0.043581194 | V7: Electricity consumption | X7: Price LL
A8: =ELEC!C7 -> 44109 | B8: 490415 | C8: =SUM(B8-B7) -> 3957 | D8: =SUM(G8+I8+K8) -> 3955 | E8: =B7+D8 -> 490413 | F8: 67070 | G8: =F8-F7 -> 742 | H8: 252839 | I8: =H8-H7 -> 2178 | J8: 170505 | K8: =J8-J7 -> 1035 | L8: =SUM(G8*$Y$28)/1507.5 -> 157.5058 | M8: =SUM(I8*$Y$27)/1507.5 -> 161.81493 | N8: =SUM(K8*$Y$26)/1507.5 -> 54.925373 | O8: =($AC$31/$A$38)/1507.5 -> 24.968232 | P8: =SUM(L8:O8) -> 399.21433 | Q8: =SUM(-tanks!AX10*tanks!$AU$37) -> 0 | R8: =SUM(P8:Q8) -> 399.21433 | S8: =SUM(ELEC!N7) -> 9176 | T8: =IF(S8>0,R8/S8,0) -> 0.043506357 | V8: Index in | W8: Index Out | Y8: Kwh Cost | Z8: K | AA8: Kwh | AB8: ='[8]EDl log'!AB25 -> Total cost LL | AC8: Fees
A9: =ELEC!C8 -> 44110 | B9: =B8 -> 490415 | C9: =SUM(B9-B8) -> 0 | D9: =SUM(G9+I9+K9) -> 0 | E9: =B8+D9 -> 490415 | F9: =F8 -> 67070 | G9: =F9-F8 -> 0 | H9: =H8 -> 252839 | I9: =H9-H8 -> 0 | J9: =J8 -> 170505 | K9: =J9-J8 -> 0 | L9: =SUM(G9*$Y$28)/1507.5 -> 0 | M9: =SUM(I9*$Y$27)/1507.5 -> 0 | N9: =SUM(K9*$Y$26)/1507.5 -> 0 | O9: =($AC$31/$A$38)/1507.5 -> 24.968232 | P9: =SUM(L9:O9) -> 24.968232 | Q9: =SUM(-tanks!AX11*tanks!$AU$37) -> 0 | R9: =SUM(P9:Q9) -> 24.968232 | S9: =SUM(ELEC!N8) -> 0 | T9: =IF(S9>0,R9/S9,0) -> 0 | V9: ='[2]EDl log'!V26 -> 119653 | W9: ='[2]EDl log'!W26 -> 164328 | X9: ='[2]EDl log'!X26 -> Night | Y9: ='[2]EDl log'!Y26 -> 80 | Z9: ='[2]EDl log'!Z26 -> 1 | AA9: ='[2]EDl log'!AA26 -> 44675 | AB9: ='[2]EDl log'!AB26 -> 3574000 | AC9: ='[2]EDl log'!AC26 -> 1033333 | AD9: ='[2]EDl log'!AD26 -> 0.37081459
A10: =ELEC!C9 -> 44111 | B10: =B9 -> 490415 | C10: =SUM(B10-B9) -> 0 | D10: =SUM(G10+I10+K10) -> 0 | E10: =B9+D10 -> 490415 | F10: =F9 -> 67070 | G10: =F10-F9 -> 0 | H10: =H9 -> 252839 | I10: =H10-H9 -> 0 | J10: =J9 -> 170505 | K10: =J10-J9 -> 0 | L10: =SUM(G10*$Y$28)/1507.5 -> 0 | M10: =SUM(I10*$Y$27)/1507.5 -> 0 | N10: =SUM(K10*$Y$26)/1507.5 -> 0 | O10: =($AC$31/$A$38)/1507.5 -> 24.968232 | P10: =SUM(L10:O10) -> 24.968232 | Q10: =SUM(-tanks!AX12*tanks!$AU$37) -> 0 | R10: =SUM(P10:Q10) -> 24.968232 | S10: =SUM(ELEC!N9) -> 0 | T10: =IF(S10>0,R10/S10,0) -> 0 | V10: ='[2]EDl log'!V27 -> 182116 | W10: ='[2]EDl log'!W27 -> 242131 | X10: ='[3]EDl log'!X27 -> day | Y10: ='[2]EDl log'!Y27 -> 112 | Z10: ='[2]EDl log'!Z27 -> 1 | AA10: ='[2]EDl log'!AA27 -> 60015 | AB10: ='[2]EDl log'!AB27 -> 6721680 | AC10: ='[2]EDl log'!AC27 -> 6200000 | AD10: ='[2]EDl log'!AD27 -> 0.49814074
A11: =ELEC!C10 -> 44112 | B11: =B10 -> 490415 | C11: =SUM(B11-B10) -> 0 | D11: =SUM(G11+I11+K11) -> 0 | E11: =B10+D11 -> 490415 | F11: =F10 -> 67070 | G11: =F11-F10 -> 0 | H11: =H10 -> 252839 | I11: =H11-H10 -> 0 | J11: =J10 -> 170505 | K11: =J11-J10 -> 0 | L11: =SUM(G11*$Y$28)/1507.5 -> 0 | M11: =SUM(I11*$Y$27)/1507.5 -> 0 | N11: =SUM(K11*$Y$26)/1507.5 -> 0 | O11: =($AC$31/$A$38)/1507.5 -> 24.968232 | P11: =SUM(L11:O11) -> 24.968232 | Q11: =SUM(-tanks!AX13*tanks!$AU$37) -> 0 | R11: =SUM(P11:Q11) -> 24.968232 | S11: =SUM(ELEC!N10) -> 0 | T11: =IF(S11>0,R11/S11,0) -> 0 | V11: ='[2]EDl log'!V28 -> 47510 | W11: ='[2]EDl log'!W28 -> 63298 | X11: ='[3]EDl log'!X28 -> Peak | Y11: ='[2]EDl log'!Y28 -> 320 | Z11: ='[2]EDl log'!Z28 -> 1 | AA11: ='[2]EDl log'!AA28 -> 15788 | AB11: ='[2]EDl log'!AB28 -> 5052160 | AC11: ='[2]EDl log'!AC28 -> 1000 | AD11: ='[2]EDl log'!AD28 -> 0.13104467
A12: =ELEC!C11 -> 44113 | B12: =B11 -> 490415 | C12: =SUM(B12-B11) -> 0 | D12: =SUM(G12+I12+K12) -> 0 | E12: =B11+D12 -> 490415 | F12: =F11 -> 67070 | G12: =F12-F11 -> 0 | H12: =H11 -> 252839 | I12: =H12-H11 -> 0 | J12: =J11 -> 170505 | K12: =J12-J11 -> 0 | L12: =SUM(G12*$Y$28)/1507.5 -> 0 | M12: =SUM(I12*$Y$27)/1507.5 -> 0 | N12: =SUM(K12*$Y$26)/1507.5 -> 0 | O12: =($AC$31/$A$38)/1507.5 -> 24.968232 | P12: =SUM(L12:O12) -> 24.968232 | Q12: =SUM(-tanks!AX14*tanks!$AU$37) -> 0 | R12: =SUM(P12:Q12) -> 24.968232 | S12: =SUM(ELEC!N11) -> 0 | T12: =IF(S12>0,R12/S12,0) -> 0 | AA12: ='[2]EDl log'!AA29 -> 120478 | AB12: ='[2]EDl log'!AB29 -> 0 | AC12: ='[2]EDl log'!AC29 -> 0
A13: =ELEC!C12 -> 44114 | B13: =B12 -> 490415 | C13: =SUM(B13-B12) -> 0 | D13: =SUM(G13+I13+K13) -> 0 | E13: =B12+D13 -> 490415 | F13: =F12 -> 67070 | G13: =F13-F12 -> 0 | H13: =H12 -> 252839 | I13: =H13-H12 -> 0 | J13: =J12 -> 170505 | K13: =J13-J12 -> 0 | L13: =SUM(G13*$Y$28)/1507.5 -> 0 | M13: =SUM(I13*$Y$27)/1507.5 -> 0 | N13: =SUM(K13*$Y$26)/1507.5 -> 0 | O13: =($AC$31/$A$38)/1507.5 -> 24.968232 | P13: =SUM(L13:O13) -> 24.968232 | Q13: =SUM(-tanks!AX15*tanks!$AU$37) -> 0 | R13: =SUM(P13:Q13) -> 24.968232 | S13: =SUM(ELEC!N12) -> 0 | T13: =IF(S13>0,R13/S13,0) -> 0 | V13: ='[6]EDl log'!V30 -> Occ % | W13: ='[2]EDl log'!W30 -> 0 | Y13: ='[3]EDl log'!Y30 -> Per G | AB13: ='[2]EDl log'!AB30 -> 15347840 | AC13: ='[2]EDl log'!AC30 -> 7234333
A14: =ELEC!C13 -> 44115 | B14: =B13 -> 490415 | C14: =SUM(B14-B13) -> 0 | D14: =SUM(G14+I14+K14) -> 0 | E14: =B13+D14 -> 490415 | F14: =F13 -> 67070 | G14: =F14-F13 -> 0 | H14: =H13 -> 252839 | I14: =H14-H13 -> 0 | J14: =J13 -> 170505 | K14: =J14-J13 -> 0 | L14: =SUM(G14*$Y$28)/1507.5 -> 0 | M14: =SUM(I14*$Y$27)/1507.5 -> 0 | N14: =SUM(K14*$Y$26)/1507.5 -> 0 | O14: =($AC$31/$A$38)/1507.5 -> 24.968232 | P14: =SUM(L14:O14) -> 24.968232 | Q14: =SUM(-tanks!AX16*tanks!$AU$37) -> 0 | R14: =SUM(P14:Q14) -> 24.968232 | S14: =SUM(ELEC!N13) -> 0 | T14: =IF(S14>0,R14/S14,0) -> 0 | V14: ='[6]EDl log'!V31 -> Gen RH | W14: ='[2]EDl log'!$W$31 -> 151 | X14: ='[2]EDl log'!$X$14 -> 5.3870968 | Y14: ='[2]EDl log'!$Y$31 -> 2.5166667 | AB14: ='[2]EDl log'!AB31 -> 22582173 | AC14: ='[2]EDl log'!AC31 -> 7234333
A15: =ELEC!C14 -> 44116 | B15: =B14 -> 490415 | C15: =SUM(B15-B14) -> 0 | D15: =SUM(G15+I15+K15) -> 0 | E15: =B14+D15 -> 490415 | F15: =F14 -> 67070 | G15: =F15-F14 -> 0 | H15: =H14 -> 252839 | I15: =H15-H14 -> 0 | J15: =J14 -> 170505 | K15: =J15-J14 -> 0 | L15: =SUM(G15*$Y$28)/1507.5 -> 0 | M15: =SUM(I15*$Y$27)/1507.5 -> 0 | N15: =SUM(K15*$Y$26)/1507.5 -> 0 | O15: =($AC$31/$A$38)/1507.5 -> 24.968232 | P15: =SUM(L15:O15) -> 24.968232 | Q15: =SUM(-tanks!AX17*tanks!$AU$37) -> 0 | R15: =SUM(P15:Q15) -> 24.968232 | S15: =SUM(ELEC!N14) -> 0 | T15: =IF(S15>0,R15/S15,0) -> 0 | V15: ='[6]EDl log'!V32 -> H Deg | W15: ='[2]EDl log'!W32 -> 0 | X15: ='[9]EDl log'!X15 -> 0 | AB15: ='[2]EDl log'!AB32 -> 0 | AC15: ='[2]EDl log'!AC32 -> 0
A16: =ELEC!C15 -> 44117 | B16: =B15 -> 490415 | C16: =SUM(B16-B15) -> 0 | D16: =SUM(G16+I16+K16) -> 0 | E16: =B15+D16 -> 490415 | F16: =F15 -> 67070 | G16: =F16-F15 -> 0 | H16: =H15 -> 252839 | I16: =H16-H15 -> 0 | J16: =J15 -> 170505 | K16: =J16-J15 -> 0 | L16: =SUM(G16*$Y$28)/1507.5 -> 0 | M16: =SUM(I16*$Y$27)/1507.5 -> 0 | N16: =SUM(K16*$Y$26)/1507.5 -> 0 | O16: =($AC$31/$A$38)/1507.5 -> 24.968232 | P16: =SUM(L16:O16) -> 24.968232 | Q16: =SUM(-tanks!AX18*tanks!$AU$37) -> 0 | R16: =SUM(P16:Q16) -> 24.968232 | S16: =SUM(ELEC!N15) -> 0 | T16: =IF(S16>0,R16/S16,0) -> 0 | V16: ='[6]EDl log'!V33 -> C Deg | W16: ='[2]EDl log'!$W$33 -> 307 | X16: ='[9]EDl log'!X16 -> 0 | Y16: ='[6]EDl log'!Y33 -> 0 | AB16: ='[2]EDl log'!AB33 -> 0 | AC16: ='[2]EDl log'!AC33 -> 0
A17: =ELEC!C16 -> 44118 | B17: =B16 -> 490415 | C17: =SUM(B17-B16) -> 0 | D17: =SUM(G17+I17+K17) -> 0 | E17: =B16+D17 -> 490415 | F17: =F16 -> 67070 | G17: =F17-F16 -> 0 | H17: =H16 -> 252839 | I17: =H17-H16 -> 0 | J17: =J16 -> 170505 | K17: =J17-J16 -> 0 | L17: =SUM(G17*$Y$28)/1507.5 -> 0 | M17: =SUM(I17*$Y$27)/1507.5 -> 0 | N17: =SUM(K17*$Y$26)/1507.5 -> 0 | O17: =($AC$31/$A$38)/1507.5 -> 24.968232 | P17: =SUM(L17:O17) -> 24.968232 | Q17: =SUM(-tanks!AX19*tanks!$AU$37) -> 0 | R17: =SUM(P17:Q17) -> 24.968232 | S17: =SUM(ELEC!N16) -> 0 | T17: =IF(S17>0,R17/S17,0) -> 0 | AB17: ='[2]EDl log'!AB34 -> 0 | AC17: ='[2]EDl log'!AC34 -> 0
A18: =ELEC!C17 -> 44119 | B18: =B17 -> 490415 | C18: =SUM(B18-B17) -> 0 | D18: =SUM(G18+I18+K18) -> 0 | E18: =B17+D18 -> 490415 | F18: =F17 -> 67070 | G18: =F18-F17 -> 0 | H18: =H17 -> 252839 | I18: =H18-H17 -> 0 | J18: =J17 -> 170505 | K18: =J18-J17 -> 0 | L18: =SUM(G18*$Y$28)/1507.5 -> 0 | M18: =SUM(I18*$Y$27)/1507.5 -> 0 | N18: =SUM(K18*$Y$26)/1507.5 -> 0 | O18: =($AC$31/$A$38)/1507.5 -> 24.968232 | P18: =SUM(L18:O18) -> 24.968232 | Q18: =SUM(-tanks!AX20*tanks!$AU$37) -> 0 | R18: =SUM(P18:Q18) -> 24.968232 | S18: =SUM(ELEC!N17) -> 0 | T18: =IF(S18>0,R18/S18,0) -> 0 | Z18: ='[6]EDl log'!Z35 -> VAT | AA18: ='[6]EDl log'!AA35 -> 0.11 | AB18: ='[2]EDl log'!AB35 -> 2484039 | AC18: ='[2]EDl log'!AC35 -> 0
A19: =ELEC!C18 -> 44120 | B19: =B18 -> 490415 | C19: =SUM(B19-B18) -> 0 | D19: =SUM(G19+I19+K19) -> 0 | E19: =B18+D19 -> 490415 | F19: =F18 -> 67070 | G19: =F19-F18 -> 0 | H19: =H18 -> 252839 | I19: =H19-H18 -> 0 | J19: =J18 -> 170505 | K19: =J19-J18 -> 0 | L19: =SUM(G19*$Y$28)/1507.5 -> 0 | M19: =SUM(I19*$Y$27)/1507.5 -> 0 | N19: =SUM(K19*$Y$26)/1507.5 -> 0 | O19: =($AC$31/$A$38)/1507.5 -> 24.968232 | P19: =SUM(L19:O19) -> 24.968232 | Q19: =SUM(-tanks!AX21*tanks!$AU$37) -> 0 | R19: =SUM(P19:Q19) -> 24.968232 | S19: =SUM(ELEC!N18) -> 0 | T19: =IF(S19>0,R19/S19,0) -> 0 | AB19: ='[2]EDl log'!AB36 -> 25066212 | AC19: ='[2]EDl log'!AC36 -> 0
A20: =ELEC!C19 -> 44121 | B20: =B19 -> 490415 | C20: =SUM(B20-B19) -> 0 | D20: =SUM(G20+I20+K20) -> 0 | E20: =B19+D20 -> 490415 | F20: =F19 -> 67070 | G20: =F20-F19 -> 0 | H20: =H19 -> 252839 | I20: =H20-H19 -> 0 | J20: =J19 -> 170505 | K20: =J20-J19 -> 0 | L20: =SUM(G20*$Y$28)/1507.5 -> 0 | M20: =SUM(I20*$Y$27)/1507.5 -> 0 | N20: =SUM(K20*$Y$26)/1507.5 -> 0 | O20: =($AC$31/$A$38)/1507.5 -> 24.968232 | P20: =SUM(L20:O20) -> 24.968232 | Q20: =SUM(-tanks!AX22*tanks!$AU$37) -> 0 | R20: =SUM(P20:Q20) -> 24.968232 | S20: =SUM(ELEC!N19) -> 0 | T20: =IF(S20>0,R20/S20,0) -> 0 | V20: Before new counter
A21: =ELEC!C20 -> 44122 | B21: =B20 -> 490415 | C21: =SUM(B21-B20) -> 0 | D21: =SUM(G21+I21+K21) -> 0 | E21: =B20+D21 -> 490415 | F21: =F20 -> 67070 | G21: =F21-F20 -> 0 | H21: =H20 -> 252839 | I21: =H21-H20 -> 0 | J21: =J20 -> 170505 | K21: =J21-J20 -> 0 | L21: =SUM(G21*$Y$28)/1507.5 -> 0 | M21: =SUM(I21*$Y$27)/1507.5 -> 0 | N21: =SUM(K21*$Y$26)/1507.5 -> 0 | O21: =($AC$31/$A$38)/1507.5 -> 24.968232 | P21: =SUM(L21:O21) -> 24.968232 | Q21: =SUM(-tanks!AX23*tanks!$AU$37) -> 0 | R21: =SUM(P21:Q21) -> 24.968232 | S21: =SUM(ELEC!N20) -> 0 | T21: =IF(S21>0,R21/S21,0) -> 0 | V21: EDL | W21: 44124 | Z21: Subscription
A22: =ELEC!C21 -> 44123 | B22: =B21 -> 490415 | C22: =SUM(B22-B21) -> 0 | D22: =SUM(G22+I22+K22) -> 0 | E22: =B21+D22 -> 490415 | F22: =F21 -> 67070 | G22: =F22-F21 -> 0 | H22: =H21 -> 252839 | I22: =H22-H21 -> 0 | J22: =J21 -> 170505 | K22: =J22-J21 -> 0 | L22: =SUM(G22*$Y$28)/1507.5 -> 0 | M22: =SUM(I22*$Y$27)/1507.5 -> 0 | N22: =SUM(K22*$Y$26)/1507.5 -> 0 | O22: =($AC$31/$A$38)/1507.5 -> 24.968232 | P22: =SUM(L22:O22) -> 24.968232 | Q22: =SUM(-tanks!AX24*tanks!$AU$37) -> 0 | R22: =SUM(P22:Q22) -> 24.968232 | S22: =SUM(ELEC!N21) -> 0 | T22: =IF(S22>0,R22/S22,0) -> 0 | Z22: KVA | AA22: 5000
A23: =ELEC!C22 -> 44124 | B23: =B22 -> 490415 | C23: =SUM(B23-B22) -> 0 | D23: =SUM(G23+I23+K23) -> 0 | E23: =B22+D23 -> 490415 | F23: =F22 -> 67070 | G23: =F23-F22 -> 0 | H23: =H22 -> 252839 | I23: =H23-H22 -> 0 | J23: =J22 -> 170505 | K23: =J23-J22 -> 0 | L23: =SUM(G23*$Y$28)/1507.5 -> 0 | M23: =SUM(I23*$Y$27)/1507.5 -> 0 | N23: =SUM(K23*$Y$26)/1507.5 -> 0 | O23: =($AC$31/$A$38)/1507.5 -> 24.968232 | P23: =SUM(L23:O23) -> 24.968232 | Q23: =SUM(-tanks!AX25*tanks!$AU$37) -> 0 | R23: =SUM(P23:Q23) -> 24.968232 | S23: =SUM(ELEC!N22) -> 0 | T23: =IF(S23>0,R23/S23,0) -> 0
A24: =ELEC!C23 -> 44125 | B24: =B23 -> 490415 | C24: =SUM(B24-B23) -> 0 | D24: =SUM(G24+I24+K24) -> 0 | E24: =B23+D24 -> 490415 | F24: =F23 -> 67070 | G24: =F24-F23 -> 0 | H24: =H23 -> 252839 | I24: =H24-H23 -> 0 | J24: =J23 -> 170505 | K24: =J24-J23 -> 0 | L24: =SUM(G24*$Y$28)/1507.5 -> 0 | M24: =SUM(I24*$Y$27)/1507.5 -> 0 | N24: =SUM(K24*$Y$26)/1507.5 -> 0 | O24: =($AC$31/$A$38)/1507.5 -> 24.968232 | P24: =SUM(L24:O24) -> 24.968232 | Q24: =SUM(-tanks!AX26*tanks!$AU$37) -> 0 | R24: =SUM(P24:Q24) -> 24.968232 | S24: =SUM(ELEC!N23) -> 0 | T24: =IF(S24>0,R24/S24,0) -> 0 | V24: Electricity consumption | X24: Price LL
A25: =ELEC!C24 -> 44126 | B25: =B24 -> 490415 | C25: =SUM(B25-B24) -> 0 | D25: =SUM(G25+I25+K25) -> 0 | E25: =B24+D25 -> 490415 | F25: =F24 -> 67070 | G25: =F25-F24 -> 0 | H25: =H24 -> 252839 | I25: =H25-H24 -> 0 | J25: =J24 -> 170505 | K25: =J25-J24 -> 0 | L25: =SUM(G25*$Y$28)/1507.5 -> 0 | M25: =SUM(I25*$Y$27)/1507.5 -> 0 | N25: =SUM(K25*$Y$26)/1507.5 -> 0 | O25: =($AC$31/$A$38)/1507.5 -> 24.968232 | P25: =SUM(L25:O25) -> 24.968232 | Q25: =SUM(-tanks!AX27*tanks!$AU$37) -> 0 | R25: =SUM(P25:Q25) -> 24.968232 | S25: =SUM(ELEC!N24) -> 0 | T25: =IF(S25>0,R25/S25,0) -> 0 | V25: Index in | W25: Index Out | Y25: Kwh Cost | Z25: K | AA25: Kwh | AB25: Total cost LL | AC25: Fees
A26: =ELEC!C25 -> 44127 | B26: =B25 -> 490415 | C26: =SUM(B26-B25) -> 0 | D26: =SUM(G26+I26+K26) -> 0 | E26: =B25+D26 -> 490415 | F26: =F25 -> 67070 | G26: =F26-F25 -> 0 | H26: =H25 -> 252839 | I26: =H26-H25 -> 0 | J26: =J25 -> 170505 | K26: =J26-J25 -> 0 | L26: =SUM(G26*$Y$28)/1507.5 -> 0 | M26: =SUM(I26*$Y$27)/1507.5 -> 0 | N26: =SUM(K26*$Y$26)/1507.5 -> 0 | O26: =($AC$31/$A$38)/1507.5 -> 24.968232 | P26: =SUM(L26:O26) -> 24.968232 | Q26: =SUM(-tanks!AX28*tanks!$AU$37) -> 0 | R26: =SUM(P26:Q26) -> 24.968232 | S26: =SUM(ELEC!N25) -> 0 | T26: =IF(S26>0,R26/S26,0) -> 0 | V26: =W9 -> 164328 | W26: =J33 -> 170505 | X26: Night | Y26: 80 | Z26: 1 | AA26: =(W26-V26)*Z26 -> 6177 | AB26: =AA26*Y26 -> 494160 | AC26: =AC9 -> 1033333 | AD26: =SUM(K37) -> 0.29899802
