Workbook

Sheet Total
A1: Site Name | B1: Day | C1: Month | D1: Year | E1: Total Electricity Kwh | F1: Electricity Tariff ($/Kwh) | G1: Total Fuel Oil (Liters) | H1: Fuel Oil $/Liter | I1: LPG (Kg) | J1: LPG $/Kg | K1: Water Utility Supply (m3) m3 | L1: Water Utility Supply (m3) $/m3 | M1: Irrigation Water (m3) m3 | N1: Irrigation water $/m3 | O1: Room Nights
A2: Beirut | B2: 1 | C2: 11 | D2: 2020 | E2: =ELEC!N3 -> 8072 | F2: =SUM('EDl log'!T4) -> 0.079822341 | G2: =-tanks!AW6 -> 205 | H2: =SUM(tanks!AV6) -> 0.5 | I2: =('B5'!AU5)*0.51 -> -45.9 | J2: ='B5'!AX5/0.51 -> 1.5686275 | K2: =WATER!I6 -> 137 | L2: =SUM(WATER!J6) -> 1.8248175 | M2: =WATER!Q6 -> 0 | N2: 0.6 | O2: =ELEC!B3 -> 0
A3: Beirut | B3: =B2+1 -> 2 | C3: 11 | D3: 2020 | E3: =ELEC!N4 -> 7352 | F3: =SUM('EDl log'!T5) -> 0.096868709 | G3: =-tanks!AW7 -> 97 | H3: =SUM(tanks!AV7) -> 0.5 | I3: =('B5'!AU6)*0.51 -> 0 | J3: ='B5'!AX6/0.51 -> 1.5686275 | K3: =WATER!I7 -> 0 | L3: =SUM(WATER!J7) -> 0 | M3: =WATER!Q7 -> 0 | N3: 0.6 | O3: =ELEC!B4 -> 0
A4: Beirut | B4: =B3+1 -> 3 | C4: 11 | D4: 2020 | E4: =ELEC!N5 -> 8515 | F4: =SUM('EDl log'!T6) -> 0.091685672 | G4: =-tanks!AW8 -> 0 | H4: =SUM(tanks!AV8) -> 0.5 | I4: =('B5'!AU7)*0.51 -> 0 | J4: ='B5'!AX7/0.51 -> 1.5686275 | K4: =WATER!I8 -> 250 | L4: =SUM(WATER!J8) -> 1.83664 | M4: =WATER!Q8 -> 0 | N4: 0.6 | O4: =ELEC!B5 -> 0
A5: Beirut | B5: =B4+1 -> 4 | C5: 11 | D5: 2020 | E5: =ELEC!N6 -> 8156 | F5: =SUM('EDl log'!T7) -> 0.11045806 | G5: =-tanks!AW9 -> 0 | H5: =SUM(tanks!AV9) -> 0.5 | I5: =('B5'!AU8)*0.51 -> 0 | J5: ='B5'!AX8/0.51 -> 1.5686275 | K5: =WATER!I9 -> 0 | L5: =SUM(WATER!J9) -> 0 | M5: =WATER!Q9 -> 0 | N5: 0.6 | O5: =ELEC!B6 -> 0
A6: Beirut | B6: =B5+1 -> 5 | C6: 11 | D6: 2020 | E6: =ELEC!N7 -> 7853.4 | F6: =SUM('EDl log'!T8) -> 0.10812479 | G6: =-tanks!AW10 -> 0 | H6: =SUM(tanks!AV10) -> 0.5 | I6: =('B5'!AU9)*0.51 -> 0 | J6: ='B5'!AX9/0.51 -> 1.5686275 | K6: =WATER!I10 -> 193 | L6: =SUM(WATER!J10) -> 1.2953368 | M6: =WATER!Q10 -> 0 | N6: 0.6 | O6: =ELEC!B7 -> 0
A7: Beirut | B7: =B6+1 -> 6 | C7: 11 | D7: 2020 | E7: =ELEC!N8 -> 7743.2 | F7: =SUM('EDl log'!T9) -> 0.099338087 | G7: =-tanks!AW11 -> 0 | H7: =SUM(tanks!AV11) -> 0.5 | I7: =('B5'!AU10)*0.51 -> 0 | J7: ='B5'!AX10/0.51 -> 1.5686275 | K7: =WATER!I11 -> 0 | L7: =SUM(WATER!J11) -> 0 | M7: =WATER!Q11 -> 0 | N7: 0.6 | O7: =ELEC!B8 -> 0
A8: Beirut | B8: =B7+1 -> 7 | C8: 11 | D8: 2020 | E8: =ELEC!N9 -> 6591.6 | F8: =SUM('EDl log'!T10) -> 0.080356136 | G8: =-tanks!AW12 -> 238 | H8: =SUM(tanks!AV12) -> 0.5 | I8: =('B5'!AU11)*0.51 -> 0 | J8: ='B5'!AX11/0.51 -> 1.5686275 | K8: =WATER!I12 -> 190 | L8: =SUM(WATER!J12) -> 1.3157895 | M8: =WATER!Q12 -> 0 | N8: 0.6 | O8: =ELEC!B9 -> 0
A9: Beirut | B9: =B8+1 -> 8 | C9: 11 | D9: 2020 | E9: =ELEC!N10 -> 7125.8 | F9: =SUM('EDl log'!T11) -> 0.092226624 | G9: =-tanks!AW13 -> 162 | H9: =SUM(tanks!AV13) -> 0.5 | I9: =('B5'!AU12)*0.51 -> 0 | J9: ='B5'!AX12/0.51 -> 1.5686275 | K9: =WATER!I13 -> 0 | L9: =SUM(WATER!J13) -> 0 | M9: =WATER!Q13 -> 0 | N9: 0.6 | O9: =ELEC!B10 -> 0
A10: Beirut | B10: =B9+1 -> 9 | C10: 11 | D10: 2020 | E10: =ELEC!N11 -> 7376 | F10: =SUM('EDl log'!T12) -> 0.088024448 | G10: =-tanks!AW14 -> 137 | H10: =SUM(tanks!AV14) -> 0.5 | I10: =('B5'!AU13)*0.51 -> 0 | J10: ='B5'!AX13/0.51 -> 1.5686275 | K10: =WATER!I14 -> 191 | L10: =SUM(WATER!J14) -> 1.3089005 | M10: =WATER!Q14 -> 0 | N10: 0.6 | O10: =ELEC!B11 -> 0
A11: Beirut | B11: =B10+1 -> 10 | C11: 11 | D11: 2020 | E11: =ELEC!N12 -> 7892 | F11: =SUM('EDl log'!T13) -> 0.08949042 | G11: =-tanks!AW15 -> 144 | H11: =SUM(tanks!AV15) -> 0.5 | I11: =('B5'!AU14)*0.51 -> 0 | J11: ='B5'!AX14/0.51 -> 1.5686275 | K11: =WATER!I15 -> 0 | L11: =SUM(WATER!J15) -> 0 | M11: =WATER!Q15 -> 0 | N11: 0.6 | O11: =ELEC!B12 -> 0
A12: Beirut | B12: =B11+1 -> 11 | C12: 11 | D12: 2020 | E12: =ELEC!N13 -> 8345 | F12: =SUM('EDl log'!T14) -> 0.077396948 | G12: =-tanks!AW16 -> 162 | H12: =SUM(tanks!AV16) -> 0.5 | I12: =('B5'!AU15)*0.51 -> 0 | J12: ='B5'!AX15/0.51 -> 1.5686275 | K12: =WATER!I16 -> 185 | L12: =SUM(WATER!J16) -> 1.3513514 | M12: =WATER!Q16 -> 0 | N12: 0.6 | O12: =ELEC!B13 -> 0
A13: Beirut | B13: =B12+1 -> 12 | C13: 11 | D13: 2020 | E13: =ELEC!N14 -> 8791 | F13: =SUM('EDl log'!T15) -> 0.08275464 | G13: =-tanks!AW17 -> 244 | H13: =SUM(tanks!AV17) -> 0.5 | I13: =('B5'!AU16)*0.51 -> 0 | J13: ='B5'!AX16/0.51 -> 1.5686275 | K13: =WATER!I17 -> 0 | L13: =SUM(WATER!J17) -> 0 | M13: =WATER!Q17 -> 0 | N13: 0.6 | O13: =ELEC!B14 -> 0
A14: Beirut | B14: =B13+1 -> 13 | C14: 11 | D14: 2020 | E14: =ELEC!N15 -> 8409 | F14: =SUM('EDl log'!T16) -> 0.087717062 | G14: =-tanks!AW18 -> 137 | H14: =SUM(tanks!AV18) -> 0.5 | I14: =('B5'!AU17)*0.51 -> 0 | J14: ='B5'!AX17/0.51 -> 1.5686275 | K14: =WATER!I18 -> 117 | L14: =SUM(WATER!J18) -> 2.1367521 | M14: =WATER!Q18 -> 0 | N14: 0.6 | O14: =ELEC!B15 -> 0
... A31: Beirut | B31: =B30+1 -> 30 | C31: 11 | D31: 2020 | E31: =ELEC!N32 -> 0 | F31: =SUM('EDl log'!T33) -> 0 | G31: =-tanks!AW35 -> 0 | H31: =SUM(tanks!AV35) -> 0.49 | I31: =('B5'!AU34)*0.51 -> 0 | J31: ='B5'!AX34/0.51 -> 1.5686275 | K31: =WATER!I35 -> 0 | L31: =SUM(WATER!J35) -> 0 | M31: =WATER!Q35 -> 0 | N31: 0.6 | O31: =ELEC!B32 -> 0
A32: Beirut

Sheet Submetering
A1: Site Name | B1: Day | C1: Month | D1: Year | E1: ATS1 Kwh | F1: ATS2 Kwh | G1: ATS3 Kwh | H1: ATS4 Kwh | I1: ATS5 Kwh | J1: Guest (m3) | K1: Kitchen & Laundry (m3) | L1: Room Nights
A2: Beirut | B2: 1 | C2: 11 | D2: 2020 | E2: =ELEC!M3 -> 1934 | F2: =ELEC!K3 -> 1146 | G2: =ELEC!I3 -> 844 | H2: =ELEC!E3 -> 3496 | I2: =ELEC!G3 -> 652 | J2: =WATER!Y6 -> 104 | K2: =WATER!AJ6 -> 0 | L2: =ELEC!B3 -> 0
A3: Beirut | B3: =B2+1 -> 2 | C3: 11 | D3: 2020 | E3: =ELEC!M4 -> 2558 | F3: =ELEC!K4 -> 944 | G3: =ELEC!I4 -> 894 | H3: =ELEC!E4 -> 2200 | I3: =ELEC!G4 -> 756 | J3: =WATER!Y7 -> 0 | K3: =WATER!AJ7 -> 0 | L3: =ELEC!B4 -> 0
A4: Beirut | B4: =B3+1 -> 3 | C4: 11 | D4: 2020 | E4: =ELEC!M5 -> 3080 | F4: =ELEC!K5 -> 1166 | G4: =ELEC!I5 -> 924 | H4: =ELEC!E5 -> 2610 | I4: =ELEC!G5 -> 735 | J4: =WATER!Y8 -> 101 | K4: =WATER!AJ8 -> 10 | L4: =ELEC!B5 -> 0
A5: Beirut | B5: =B4+1 -> 4 | C5: 11 | D5: 2020 | E5: =ELEC!M6 -> 2992 | F5: =ELEC!K6 -> 1120 | G5: =ELEC!I6 -> 894 | H5: =ELEC!E6 -> 2366 | I5: =ELEC!G6 -> 784 | J5: =WATER!Y9 -> 74 | K5: =WATER!AJ9 -> 0 | L5: =ELEC!B6 -> 0
A6: Beirut | B6: =B5+1 -> 5 | C6: 11 | D6: 2020 | E6: =ELEC!M7 -> 2876 | F6: =ELEC!K7 -> 984 | G6: =ELEC!I7 -> 846 | H6: =ELEC!E7 -> 2448 | I6: =ELEC!G7 -> 699.4 | J6: =WATER!Y10 -> 0 | K6: =WATER!AJ10 -> 28 | L6: =ELEC!B7 -> 0
A7: Beirut | B7: =B6+1 -> 6 | C7: 11 | D7: 2020 | E7: =ELEC!M8 -> 2688 | F7: =ELEC!K8 -> 996 | G7: =ELEC!I8 -> 788 | H7: =ELEC!E8 -> 2604 | I7: =ELEC!G8 -> 667.2 | J7: =WATER!Y11 -> 64 | K7: =WATER!AJ11 -> 23 | L7: =ELEC!B8 -> 0
A8: Beirut | B8: =B7+1 -> 7 | C8: 11 | D8: 2020 | E8: =ELEC!M9 -> 2208 | F8: =ELEC!K9 -> 860 | G8: =ELEC!I9 -> 780 | H8: =ELEC!E9 -> 2056 | I8: =ELEC!G9 -> 687.6 | J8: =WATER!Y12 -> 40 | K8: =WATER!AJ12 -> 0 | L8: =ELEC!B9 -> 0
A9: Beirut | B9: =B8+1 -> 8 | C9: 11 | D9: 2020 | E9: =ELEC!M10 -> 2412 | F9: =ELEC!K10 -> 940 | G9: =ELEC!I10 -> 818 | H9: =ELEC!E10 -> 2290 | I9: =ELEC!G10 -> 665.8 | J9: =WATER!Y13 -> 0 | K9: =WATER!AJ13 -> 0 | L9: =ELEC!B10 -> 0
A10: Beirut | B10: =B9+1 -> 9 | C10: 11 | D10: 2020 | E10: =ELEC!M11 -> 2168 | F10: =ELEC!K11 -> 960 | G10: =ELEC!I11 -> 828 | H10: =ELEC!E11 -> 2716 | I10: =ELEC!G11 -> 704 | J10: =WATER!Y14 -> 66 | K10: =WATER!AJ14 -> 23 | L10: =ELEC!B11 -> 0
A11: Beirut | B11: =B10+1 -> 10 | C11: 11 | D11: 2020 | E11: =ELEC!M12 -> 2416 | F11: =ELEC!K12 -> 1392 | G11: =ELEC!I12 -> 780 | H11: =ELEC!E12 -> 2638 | I11: =ELEC!G12 -> 666 | J11: =WATER!Y15 -> 66 | K11: =WATER!AJ15 -> 24 | L11: =ELEC!B12 -> 0
A12: Beirut | B12: =B11+1 -> 11 | C12: 11 | D12: 2020 | E12: =ELEC!M13 -> 1820 | F12: =ELEC!K13 -> 2468 | G12: =ELEC!I13 -> 832 | H12: =ELEC!E13 -> 2512 | I12: =ELEC!G13 -> 713 | J12: =WATER!Y16 -> 0 | K12: =WATER!AJ16 -> 0 | L12: =ELEC!B13 -> 0
A13: Beirut | B13: =B12+1 -> 12 | C13: 11 | D13: 2020 | E13: =ELEC!M14 -> 1766 | F13: =ELEC!K14 -> 2864 | G13: =ELEC!I14 -> 870 | H13: =ELEC!E14 -> 2592 | I13: =ELEC!G14 -> 699 | J13: =WATER!Y17 -> 83 | K13: =WATER!AJ17 -> 42 | L13: =ELEC!B14 -> 0
A14: Beirut | B14: =B13+1 -> 13 | C14: 11 | D14: 2020 | E14: =ELEC!M15 -> 1744 | F14: =ELEC!K15 -> 2412 | G14: =ELEC!I15 -> 850 | H14: =ELEC!E15 -> 2752 | I14: =ELEC!G15 -> 651 | J14: =WATER!Y18 -> 0 | K14: =WATER!AJ18 -> 0 | L14: =ELEC!B15 -> 0
... A31: Beirut | B31: =B30+1 -> 30 | C31: 11 | D31: 2020 | E31: =ELEC!M32 -> 0 | F31: =ELEC!K32 -> 0 | G31: =ELEC!I32 -> 0 | H31: =ELEC!E32 -> 0 | I31: =ELEC!G32 -> 0 | J31: =WATER!Y35 -> 0 | K31: =WATER!AJ35 -> 0 | L31: =ELEC!B32 -> 0
A32: Beirut

Sheet ELEC
A1: OOC | B1: Room OCC | D1: MDB3 | E1: MDB3/day | F1: EMDB2 | G1: EMDB2/day | H1: EMDB1 | I1: EMDB1/day | J1: MDB2 | K1: mdb2/day | L1: MDB1 | M1: MDB1/Day | N1: Total KWH | O1: KWH/Rooc | P1: Gen MHW | Q1: Gen/Day KWH | R1: EDL KWH | S1: CH1 RH | T1: RH | U1: C1h1 power | V1: CH1 Con KWH | W1: CH2 RH | X1: RH | Y1: Ch2 power | Z1: CH2 Con KWH | AA1: CH3 RH | AB1: RH | AC1: Ch3 power | AD1: CH3 Con KWH | AE1: RH total | AF1: KWH total | AG1: AVG chiller KW/Hr
A2: =[1]ELEC!$A$33 -> 0 | B2: =[1]ELEC!$B$33 -> 0 | C2: 44135 | D2: =[1]ELEC!D33 -> 32384050 | E2: =[1]ELEC!E33 -> 2720 | F2: =[1]ELEC!F33 -> 3896366 | G2: =[1]ELEC!G33 -> 664 | H2: =[1]ELEC!H33 -> 17701778 | I2: =[1]ELEC!I33 -> 884 | J2: =[1]ELEC!J33 -> 28760594 | K2: =[1]ELEC!K33 -> 1408 | ... AL2: =[1]ELEC!AL33 -> 0
A3: ='General information '!F6 -> 0 | B3: =SUM(230*A3) -> 0 | C3: 44136 | D3: 32387546 | E3: =D3-D2 -> 3496 | F3: 3897018 | G3: =F3-F2 -> 652 | H3: 17702622 | I3: =H3-H2 -> 844 | J3: 28761740 | K3: =J3-J2 -> 1146 | L3: 23807624 | M3: =L3-L2 -> 1934 | N3: =M3+K3+I3+G3+E3 -> 8072 | O3: =IF(B3>0,N3/B3,0) -> 0 | P3: 16405 | Q3: =(P3-P2)*1000 -> 2000 | R3: =+N3-Q3 -> 6072 | S3: 9960 | T3: =S3-S2 -> 2 | U3: 392023 | V3: =U3-U2 -> 571 | W3: 32049 | X3: =W3-W2 -> 0 | Y3: =Y2 -> 673052 | Z3: =Y3-Y2 -> 0 | AA3: 35632 | AB3: =AA3-AA2 -> 4 | AC3: 905341 | AD3: =AC3-AC2 -> 1045 | AE3: =AB3+X3+T3 -> 6 | AF3: =V3+Z3+AD3 -> 1616 | AG3: =IF(AE3>0,AF3/AE3,0) -> 269.33333
A4: ='General information '!F7 -> 0 | B4: =SUM(230*A4) -> 0 | C4: 44137 | D4: 32389746 | E4: =D4-D3 -> 2200 | F4: 3897774 | G4: =F4-F3 -> 756 | H4: 17703516 | I4: =H4-H3 -> 894 | J4: 28762684 | K4: =J4-J3 -> 944 | L4: 23810182 | M4: =L4-L3 -> 2558 | N4: =M4+K4+I4+G4+E4 -> 7352 | O4: =IF(B4>0,N4/B4,0) -> 0 | P4: =P3 -> 16405 | Q4: =(P4-P3)*1000 -> 0 | R4: =N4-Q4 -> 7352 | S4: 9963 | T4: =S4-S3 -> 3 | U4: 392986 | V4: =U4-U3 -> 963 | W4: =W3 -> 32049 | X4: =W4-W3 -> 0 | Y4: =Y3 -> 673052 | Z4: =Y4-Y3 -> 0 | AA4: =AA3 -> 35632 | AB4: =AA4-AA3 -> 0 | AC4: =AC3 -> 905341 | AD4: =AC4-AC3 -> 0 | AE4: =AB4+X4+T4 -> 3 | AF4: =V4+Z4+AD4 -> 963 | AG4: =IF(AE4>0,AF4/AE4,0) -> 321
A5: ='General information '!F8 -> 0 | B5: =SUM(230*A5) -> 0 | C5: 44138 | D5: 32392356 | E5: =D5-D4 -> 2610 | F5: 3898509 | G5: =F5-F4 -> 735 | H5: 17704440 | I5: =H5-H4 -> 924 | J5: 28763850 | K5: =J5-J4 -> 1166 | L5: 23813262 | M5: =L5-L4 -> 3080 | N5: =M5+K5+I5+G5+E5 -> 8515 | O5: =IF(B5>0,N5/B5,0) -> 0 | P5: 16407 | Q5: =(P5-P4)*1000 -> 2000 | R5: =N5-Q5 -> 6515 | S5: 9971 | T5: =S5-S4 -> 8 | U5: =U4 -> 392986 | V5: =U5-U4 -> 0 | W5: =W4 -> 32049 | X5: =W5-W4 -> 0 | Y5: =Y4 -> 673052 | Z5: =Y5-Y4 -> 0 | AA5: =AA4 -> 35632 | AB5: =AA5-AA4 -> 0 | AC5: =AC4 -> 905341 | AD5: =AC5-AC4 -> 0 | AE5: =AB5+X5+T5 -> 8 | AF5: =V5+Z5+AD5 -> 0 | AG5: =IF(AE5>0,AF5/AE5,0) -> 0 | AI5: =R5-'EDl log'!B3 -> -595675
A6: ='General information '!F9 -> 0 | B6: =SUM(230*A6) -> 0 | C6: 44139 | D6: 32394722 | E6: =D6-D5 -> 2366 | F6: 3899293 | G6: =F6-F5 -> 784 | H6: 17705334 | I6: =H6-H5 -> 894 | J6: 28764970 | K6: =J6-J5 -> 1120 | L6: 23816254 | M6: =L6-L5 -> 2992 | N6: =M6+K6+I6+G6+E6 -> 8156 | O6: =IF(B6>0,N6/B6,0) -> 0 | P6: 16409 | Q6: =(P6-P5)*1000 -> 2000 | R6: =N6-Q6 -> 6156 | S6: 9976 | T6: =S6-S5 -> 5 | U6: 395262 | V6: =U6-U5 -> 2276 | W6: =W5 -> 32049 | X6: =W6-W5 -> 0 | Y6: =Y5 -> 673052 | Z6: =Y6-Y5 -> 0 | AA6: =AA5 -> 35632 | AB6: =AA6-AA5 -> 0 | AC6: =AC5 -> 905341 | AD6: =AC6-AC5 -> 0 | AE6: =AB6+X6+T6 -> 5 | AF6: =V6+Z6+AD6 -> 2276 | AG6: =IF(AE6>0,AF6/AE6,0) -> 455.2 | AI6: =R6-'EDl log'!B4 -> -599465
A7: ='General information '!F10 -> 0 | B7: =SUM(230*A7) -> 0 | C7: 44140 | D7: 32397170 | E7: =D7-D6 -> 2448 | F7: 3899992.4 | G7: =F7-F6 -> 699.4 | H7: 17706180 | I7: =H7-H6 -> 846 | J7: 28765954 | K7: =J7-J6 -> 984 | L7: 23819130 | M7: =L7-L6 -> 2876 | N7: =M7+K7+I7+G7+E7 -> 7853.4 | O7: =IF(B7>0,N7/B7,0) -> 0 | P7: 16410 | Q7: =(P7-P6)*1000 -> 1000 | R7: =N7-Q7 -> 6853.4 | S7: 9982 | T7: =S7-S6 -> 6 | U7: 396340 | V7: =U7-U6 -> 1078 | W7: =W6 -> 32049 | X7: =W7-W6 -> 0 | Y7: =Y6 -> 673052 | Z7: =Y7-Y6 -> 0 | AA7: =AA6 -> 35632 | AB7: =AA7-AA6 -> 0 | AC7: =AC6 -> 905341 | AD7: =AC7-AC6 -> 0 | AE7: =AB7+X7+T7 -> 6 | AF7: =V7+Z7+AD7 -> 1078 | AG7: =IF(AE7>0,AF7/AE7,0) -> 179.66667 | AI7: =R7-'EDl log'!B5 -> -602619.6
A8: ='General information '!F11 -> 0 | B8: =SUM(230*A8) -> 0 | C8: 44141 | D8: 32399774 | E8: =D8-D7 -> 2604 | F8: 3900659.6 | G8: =F8-F7 -> 667.2 | H8: 17706968 | I8: =H8-H7 -> 788 | J8: 28766950 | K8: =J8-J7 -> 996 | L8: 23821818 | M8: =L8-L7 -> 2688 | N8: =M8+K8+I8+G8+E8 -> 7743.2 | O8: =IF(B8>0,N8/B8,0) -> 0 | P8: 16412 | Q8: =(P8-P7)*1000 -> 2000 | R8: =N8-Q8 -> 5743.2 | S8: 9987 | T8: =S8-S7 -> 5 | U8: 397254 | V8: =U8-U7 -> 914 | W8: =W7 -> 32049 | X8: =W8-W7 -> 0 | Y8: =Y7 -> 673052 | Z8: =Y8-Y7 -> 0 | AA8: =AA7 -> 35632 | AB8: =AA8-AA7 -> 0 | AC8: =AC7 -> 905341 | AD8: =AC8-AC7 -> 0 | AE8: =AB8+X8+T8 -> 5 | AF8: =V8+Z8+AD8 -> 914 | AG8: =IF(AE8>0,AF8/AE8,0) -> 182.8 | AI8: =R8-'EDl log'!B6 -> -607268.8
A9: ='General information '!F12 -> 0 | B9: =SUM(230*A9) -> 0 | C9: 44142 | D9: 32401830 | E9: =D9-D8 -> 2056 | F9: 3901347.2 | G9: =F9-F8 -> 687.6 | H9: 17707748 | I9: =H9-H8 -> 780 | J9: 28767810 | K9: =J9-J8 -> 860 | L9: 23824026 | M9: =L9-L8 -> 2208 | N9: =M9+K9+I9+G9+E9 -> 6591.6 | O9: =IF(B9>0,N9/B9,0) -> 0 | P9: 16412 | Q9: =(P9-P8)*1000 -> 0 | R9: =N9-Q9 -> 6591.6 | S9: 9990 | T9: =S9-S8 -> 3 | U9: 397917 | V9: =U9-U8 -> 663 | W9: =W8 -> 32049 | X9: =W9-W8 -> 0 | Y9: =Y8 -> 673052 | Z9: =Y9-Y8 -> 0 | AA9: =AA8 -> 35632 | AB9: =AA9-AA8 -> 0 | AC9: =AC8 -> 905341 | AD9: =AC9-AC8 -> 0 | AE9: =AB9+X9+T9 -> 3 | AF9: =V9+Z9+AD9 -> 663 | AG9: =IF(AE9>0,AF9/AE9,0) -> 221 | AI9: =R9-'EDl log'!B7 -> -609779.4
A10: ='General information '!F13 -> 0 | B10: =SUM(230*A10) -> 0 | C10: 44143 | D10: 32404120 | E10: =D10-D9 -> 2290 | F10: 3902013 | G10: =F10-F9 -> 665.8 | H10: 17708566 | I10: =H10-H9 -> 818 | J10: 28768750 | K10: =J10-J9 -> 940 | L10: 23826438 | M10: =L10-L9 -> 2412 | N10: =M10+K10+I10+G10+E10 -> 7125.8 | O10: =IF(B10>0,N10/B10,0) -> 0 | P10: 16414 | Q10: =(P10-P9)*1000 -> 2000 | R10: =N10-Q10 -> 5125.8 | S10: 9995 | T10: =S10-S9 -> 5 | U10: 398801 | V10: =U10-U9 -> 884 | W10: 32049 | X10: =W10-W9 -> 0 | Y10: =Y9 -> 673052 | Z10: =Y10-Y9 -> 0 | AA10: 35632 | AB10: =AA10-AA9 -> 0 | AC10: 905341 | AD10: =AC10-AC9 -> 0 | AE10: =AB10+X10+T10 -> 5 | AF10: =V10+Z10+AD10 -> 884 | AG10: =IF(AE10>0,AF10/AE10,0) -> 176.8 | AI10: =R10-'EDl log'!B8 -> -614554.2
A11: ='General information '!F14 -> 0 | B11: =SUM(230*A11) -> 0 | C11: 44144 | D11: 32406836 | E11: =D11-D10 -> 2716 | F11: 3902717 | G11: =F11-F10 -> 704 | H11: 17709394 | I11: =H11-H10 -> 828 | J11: 28769710 | K11: =J11-J10 -> 960 | L11: 23828606 | M11: =L11-L10 -> 2168 | N11: =M11+K11+I11+G11+E11 -> 7376 | O11: =IF(B11>0,N11/B11,0) -> 0 | P11: 16415 | Q11: =(P11-P10)*1000 -> 1000 | R11: =N11-Q11 -> 6376 | S11: 9998 | T11: =S11-S10 -> 3 | U11: 399403 | V11: =U11-U10 -> 602 | W11: =W10 -> 32049 | X11: =W11-W10 -> 0 | Y11: =Y10 -> 673052 | Z11: =Y11-Y10 -> 0 | AA11: 35634 | AB11: =AA11-AA10 -> 2 | AC11: 905726 | AD11: =AC11-AC10 -> 385 | AE11: =AB11+X11+T11 -> 5 | AF11: =V11+Z11+AD11 -> 987 | AG11: =IF(AE11>0,AF11/AE11,0) -> 197.4 | AI11: =R11-'EDl log'!B9 -> -616616
A12: ='General information '!F15 -> 0 | B12: =SUM(230*A12) -> 0 | C12: 44145 | D12: 32409474 | E12: =D12-D11 -> 2638 | F12: 3903383 | G12: =F12-F11 -> 666 | H12: 17710174 | I12: =H12-H11 -> 780 | J12: 28771102 | K12: =J12-J11 -> 1392 | L12: 23831022 | M12: =L12-L11 -> 2416 | N12: =M12+K12+I12+G12+E12 -> 7892 | O12: =IF(B12>0,N12/B12,0) -> 0 | P12: 16416 | Q12: =(P12-P11)*1000 -> 1000 | R12: =N12-Q12 -> 6892 | S12: 10003 | T12: =S12-S11 -> 5 | U12: 400271 | V12: =U12-U11 -> 868 | W12: =W11 -> 32049 | X12: =W12-W11 -> 0 | Y12: =Y11 -> 673052 | Z12: =Y12-Y11 -> 0 | AA12: =AA11 -> 35634 | AB12: =AA12-AA11 -> 0 | AC12: =AC11 -> 905726 | AD12: =AC12-AC11 -> 0 | AE12: =AB12+X12+T12 -> 5 | AF12: =V12+Z12+AD12 -> 868 | AG12: =IF(AE12>0,AF12/AE12,0) -> 173.6 | AI12: =R12-'EDl log'!B10 -> -619155
A13: ='General information '!F16 -> 0 | B13: =SUM(230*A13) -> 0 | C13: 44146 | D13: 32411986 | E13: =D13-D12 -> 2512 | F13: 3904096 | G13: =F13-F12 -> 713 | H13: 17711006 | I13: =H13-H12 -> 832 | J13: 28773570 | K13: =J13-J12 -> 2468 | L13: 23832842 | M13: =L13-L12 -> 1820 | N13: =M13+K13+I13+G13+E13 -> 8345 | O13: =IF(B13>0,N13/B13,0) -> 0 | P13: 16417 | Q13: =(P13-P12)*1000 -> 1000 | R13: =N13-Q13 -> 7345 | S13: =S12 -> 10003 | T13: =S13-S12 -> 0 | U13: =U12 -> 400271 | V13: =U13-U12 -> 0 | W13: 32057 | X13: =W13-W12 -> 8 | Y13: 674517 | Z13: =Y13-Y12 -> 1465 | AA13: =AA12 -> 35634 | AB13: =AA13-AA12 -> 0 | AC13: =AC12 -> 905726 | AD13: =AC13-AC12 -> 0 | AE13: =AB13+X13+T13 -> 8 | AF13: =V13+Z13+AD13 -> 1465 | AG13: =IF(AE13>0,AF13/AE13,0) -> 183.125 | AI13: =R13-'EDl log'!B11 -> -621680
A14: ='General information '!F17 -> 0 | B14: =SUM(230*A14) -> 0 | C14: 44147 | D14: 32414578 | E14: =D14-D13 -> 2592 | F14: 3904795 | G14: =F14-F13 -> 699 | H14: 17711876 | I14: =H14-H13 -> 870 | J14: 28776434 | K14: =J14-J13 -> 2864 | L14: 23834608 | M14: =L14-L13 -> 1766 | N14: =M14+K14+I14+G14+E14 -> 8791 | O14: =IF(B14>0,N14/B14,0) -> 0 | P14: 16419 | Q14: =(P14-P13)*1000 -> 2000 | R14: =N14-Q14 -> 6791 | S14: 10003 | T14: =S14-S13 -> 0 | U14: =U13 -> 400271 | V14: =U14-U13 -> 0 | W14: 32064 | X14: =W14-W13 -> 7 | Y14: 675980 | Z14: =Y14-Y13 -> 1463 | AA14: 35634 | AB14: =AA14-AA13 -> 0 | AC14: 905726 | AD14: =AC14-AC13 -> 0 | AE14: =AB14+X14+T14 -> 7 | AF14: =V14+Z14+AD14 -> 1463 | AG14: =IF(AE14>0,AF14/AE14,0) -> 209 | AI14: =R14-'EDl log'!B12 -> -625529
A15: ='General information '!F18 -> 0 | B15: =SUM(230*A15) -> 0 | C15: 44148 | D15: 32417330 | E15: =D15-D14 -> 2752 | F15: 3905446 | G15: =F15-F14 -> 651 | H15: 17712726 | I15: =H15-H14 -> 850 | J15: 28778846 | K15: =J15-J14 -> 2412 | L15: 23836352 | M15: =L15-L14 -> 1744 | N15: =M15+K15+I15+G15+E15 -> 8409 | O15: =IF(B15>0,N15/B15,0) -> 0 | P15: 16420 | Q15: =(P15-P14)*1000 -> 1000 | R15: =N15-Q15 -> 7409 | S15: =S14 -> 10003 | T15: =S15-S14 -> 0 | U15: =U14 -> 400271 | V15: =U15-U14 -> 0 | W15: 32069 | X15: =W15-W14 -> 5 | Y15: 677178 | Z15: =Y15-Y14 -> 1198 | AA15: =AA14 -> 35634 | AB15: =AA15-AA14 -> 0 | AC15: =AC14 -> 905726 | AD15: =AC15-AC14 -> 0 | AE15: =AB15+X15+T15 -> 5 | AF15: =V15+Z15+AD15 -> 1198 | AG15: =IF(AE15>0,AF15/AE15,0) -> 239.6 | AI15: =R15-'EDl log'!B13 -> -628601
A16: ='General information '!F19 -> 0 | B16: =SUM(230*A16) -> 0 | C16: 44149 | D16: 32420022 | E16: =D16-D15 -> 2692 | F16: 3906171 | G16: =F16-F15 -> 725 | H16: 17713658 | I16: =H16-H15 -> 932 | J16: 28781474 | K16: =J16-J15 -> 2628 | L16: 23838222 | M16: =L16-L15 -> 1870 | N16: =M16+K16+I16+G16+E16 -> 8847 | O16: =IF(B16>0,N16/B16,0) -> 0 | P16: 16421 | Q16: =(P16-P15)*1000 -> 1000 | R16: =N16-Q16 -> 7847 | S16: =S15 -> 10003 | T16: =S16-S15 -> 0 | U16: =U15 -> 400271 | V16: =U16-U15 -> 0 | W16: 32073 | X16: =W16-W15 -> 4 | Y16: 677987 | Z16: =Y16-Y15 -> 809 | AA16: =AA15 -> 35634 | AB16: =AA16-AA15 -> 0 | AC16: =AC15 -> 905726 | AD16: =AC16-AC15 -> 0 | AE16: =AB16+X16+T16 -> 4 | AF16: =V16+Z16+AD16 -> 809 | AG16: =IF(AE16>0,AF16/AE16,0) -> 202.25 | AI16: =R16-'EDl log'!B14 -> -631807
A17: ='General information '!F20 -> 0 | B17: =SUM(230*A17) -> 0 | C17: 44150 | D17: 32421782 | E17: =D17-D16 -> 1760 | F17: 3906733 | G17: =F17-F16 -> 562 | H17: 17714344 | I17: =H17-H16 -> 686 | J17: 28782490 | K17: =J17-J16 -> 1016 | L17: 23839940 | M17: =L17-L16 -> 1718 | N17: =M17+K17+I17+G17+E17 -> 5742 | O17: =IF(B17>0,N17/B17,0) -> 0 | P17: 16422 | Q17: =(P17-P16)*1000 -> 1000 | R17: =N17-Q17 -> 4742 | S17: 10003 | T17: =S17-S16 -> 0 | U17: =U16 -> 400271 | V17: =U17-U16 -> 0 | W17: 32076 | X17: =W17-W16 -> 3 | Y17: 678759 | Z17: =Y17-Y16 -> 772 | AA17: =AA16 -> 35634 | AB17: =AA17-AA16 -> 0 | AC17: =AC16 -> 905726 | AD17: =AC17-AC16 -> 0 | AE17: =AB17+X17+T17 -> 3 | AF17: =V17+Z17+AD17 -> 772 | AG17: =IF(AE17>0,AF17/AE17,0) -> 257.33333 | AI17: =R17-'EDl log'!B15 -> -638797
A18: ='General information '!F21 -> 0 | B18: =SUM(230*A18) -> 0 | C18: 44151 | D18: 32424010 | E18: =D18-D17 -> 2228 | F18: 3907550 | G18: =F18-F17 -> 817 | H18: 17715166 | I18: =H18-H17 -> 822 | J18: 28785078 | K18: =J18-J17 -> 2588 | L18: 23842010 | M18: =L18-L17 -> 2070 | N18: =M18+K18+I18+G18+E18 -> 8525 | O18: =IF(B18>0,N18/B18,0) -> 0 | P18: 16423 | Q18: =(P18-P17)*1000 -> 1000 | R18: =N18-Q18 -> 7525 | S18: =S17 -> 10003 | T18: =S18-S17 -> 0 | U18: =U17 -> 400271 | V18: =U18-U17 -> 0 | W18: 32084 | X18: =W18-W17 -> 8 | Y18: 680076 | Z18: =Y18-Y17 -> 1317 | AA18: =AA17 -> 35634 | AB18: =AA18-AA17 -> 0 | AC18: =AC17 -> 905726 | AD18: =AC18-AC17 -> 0 | AE18: =AB18+X18+T18 -> 8 | AF18: =V18+Z18+AD18 -> 1317 | AG18: =IF(AE18>0,AF18/AE18,0) -> 164.625 | AI18: =R18-'EDl log'!B16 -> -639660
A19: ='General information '!F22 -> 0 | B19: =SUM(230*A19) -> 0 | C19: 44152 | D19: 32426106 | E19: =D19-D18 -> 2096 | F19: 3908207 | G19: =F19-F18 -> 657 | H19: 17715956 | I19: =H19-H18 -> 790 | J19: 28787096 | K19: =J19-J18 -> 2018 | L19: 23843998 | M19: =L19-L18 -> 1988 | N19: =M19+K19+I19+G19+E19 -> 7549 | O19: =IF(B19>0,N19/B19,0) -> 0 | P19: 16425 | Q19: =(P19-P18)*1000 -> 2000 | R19: =N19-Q19 -> 5549 | S19: 10003 | T19: =S19-S18 -> 0 | U19: =U18 -> 400271 | V19: =U19-U18 -> 0 | W19: 32089 | X19: =W19-W18 -> 5 | Y19: 681018 | Z19: =Y19-Y18 -> 942 | AA19: =AA18 -> 35634 | AB19: =AA19-AA18 -> 0 | AC19: =AC18 -> 905726 | AD19: =AC19-AC18 -> 0 | AE19: =AB19+X19+T19 -> 5 | AF19: =V19+Z19+AD19 -> 942 | AG19: =IF(AE19>0,AF19/AE19,0) -> 188.4 | AI19: =R19-'EDl log'!B17 -> -645820
A20: ='General information '!F23 -> 0 | B20: =SUM(230*A20) -> 0 | C20: 44153 | D20: 32428534 | E20: =D20-D19 -> 2428 | F20: 3908916 | G20: =F20-F19 -> 709 | H20: 17716882 | I20: =H20-H19 -> 926 | J20: 28789446 | K20: =J20-J19 -> 2350 | L20: 23845990 | M20: =L20-L19 -> 1992 | N20: =M20+K20+I20+G20+E20 -> 8405 | O20: =IF(B20>0,N20/B20,0) -> 0 | P20: 16425.649 | Q20: =(P20-P19)*1000 -> 649 | R20: =N20-Q20 -> 7756 | S20: =S19 -> 10003 | T20: =S20-S19 -> 0 | U20: =U19 -> 400271 | V20: =U20-U19 -> 0 | W20: 32093 | X20: =W20-W19 -> 4 | Y20: 682060 | Z20: =Y20-Y19 -> 1042 | AA20: =AA19 -> 35634 | AB20: =AA20-AA19 -> 0 | AC20: =AC19 -> 905726 | AD20: =AC20-AC19 -> 0 | AE20: =AB20+X20+T20 -> 4 | AF20: =V20+Z20+AD20 -> 1042 | AG20: =IF(AE20>0,AF20/AE20,0) -> 260.5 | AI20: =R20-'EDl log'!B18 -> -646087
A21: ='General information '!F24 -> 0 | B21: =SUM(230*A21) -> 0 | C21: 44154 | D21: 32430898 | E21: =D21-D20 -> 2364 | F21: 3909585 | G21: =F21-F20 -> 669 | H21: 17717680 | I21: =H21-H20 -> 798 | J21: 28791668 | K21: =J21-J20 -> 2222 | L21: 23847694 | M21: =L21-L20 -> 1704 | N21: =M21+K21+I21+G21+E21 -> 7757 | O21: =IF(B21>0,N21/B21,0) -> 0 | P21: 16426.989 | Q21: =(P21-P20)*1000 -> 1340 | R21: =N21-Q21 -> 6417 | S21: =S20 -> 10003 | T21: =S21-S20 -> 0 | U21: =U20 -> 400271 | V21: =U21-U20 -> 0 | W21: 32099 | X21: =W21-W20 -> 6 | Y21: 683094 | Z21: =Y21-Y20 -> 1034 | AA21: =AA20 -> 35634 | AB21: =AA21-AA20 -> 0 | AC21: =AC20 -> 905726 | AD21: =AC21-AC20 -> 0 | AE21: =AB21+X21+T21 -> 6 | AF21: =V21+Z21+AD21 -> 1034 | AG21: =IF(AE21>0,AF21/AE21,0) -> 172.33333 | AI21: =R21-'EDl log'!B19 -> -651270
A22: ='General information '!F25 -> 0 | B22: =SUM(230*A22) -> 0 | C22: 44155 | D22: 32433444 | E22: =D22-D21 -> 2546 | F22: 3910254 | G22: =F22-F21 -> 669 | H22: 17718520 | I22: =H22-H21 -> 840 | J22: 28793966 | K22: =J22-J21 -> 2298 | L22: 23849496 | M22: =L22-L21 -> 1802 | N22: =M22+K22+I22+G22+E22 -> 8155 | O22: =IF(B22>0,N22/B22,0) -> 0 | P22: 16428.392 | Q22: =(P22-P21)*1000 -> 1403 | R22: =N22-Q22 -> 6752 | S22: =S21 -> 10003 | T22: =S22-S21 -> 0 | U22: =U21 -> 400271 | V22: =U22-U21 -> 0 | W22: 32103 | X22: =W22-W21 -> 4 | Y22: 683944 | Z22: =Y22-Y21 -> 850 | AA22: =AA21 -> 35634 | AB22: =AA22-AA21 -> 0 | AC22: =AC21 -> 905726 | AD22: =AC22-AC21 -> 0 | AE22: =AB22+X22+T22 -> 4 | AF22: =V22+Z22+AD22 -> 850 | AG22: =IF(AE22>0,AF22/AE22,0) -> 212.5 | AI22: =R22-'EDl log'!B20 -> -654451
A23: ='General information '!F26 -> 0 | B23: =SUM(230*A23) -> 0 | C23: 44156 | D23: 32435430 | E23: =D23-D22 -> 1986 | F23: 3910857 | G23: =F23-F22 -> 603 | H23: 17719320 | I23: =H23-H22 -> 800 | J23: 28795322 | K23: =J23-J22 -> 1356 | L23: 23851314 | M23: =L23-L22 -> 1818 | N23: =M23+K23+I23+G23+E23 -> 6563 | O23: =IF(B23>0,N23/B23,0) -> 0 | P23: 16429.02 | Q23: =(P23-P22)*1000 -> 628 | R23: =N23-Q23 -> 5935 | S23: =S22 -> 10003 | T23: =S23-S22 -> 0 | U23: =U22 -> 400271 | V23: =U23-U22 -> 0 | W23: 32105 | X23: =W23-W22 -> 2 | Y23: 684442 | Z23: =Y23-Y22 -> 498 | AA23: =AA22 -> 35634 | AB23: =AA23-AA22 -> 0 | AC23: =AC22 -> 905726 | AD23: =AC23-AC22 -> 0 | AE23: =AB23+X23+T23 -> 2 | AF23: =V23+Z23+AD23 -> 498 | AG23: =IF(AE23>0,AF23/AE23,0) -> 249 | AI23: =R23-'EDl log'!B21 -> -659104
A24: ='General information '!F27 -> 0 | B24: =SUM(230*A24) -> 0 | C24: 44157 | D24: 32437858 | E24: =D24-D23 -> 2428 | F24: 3911443 | G24: =F24-F23 -> 586 | H24: 17720070 | I24: =H24-H23 -> 750 | J24: 28796310 | K24: =J24-J23 -> 988 | L24: 23853678 | M24: =L24-L23 -> 2364 | N24: =M24+K24+I24+G24+E24 -> 7116 | O24: =IF(B24>0,N24/B24,0) -> 0 | P24: 16429.02 | Q24: =(P24-P23)*1000 -> 0 | R24: =N24-Q24 -> 7116 | S24: 10006 | T24: =S24-S23 -> 3 | U24: 400936 | V24: =U24-U23 -> 665 | W24: 32105 | X24: =W24-W23 -> 0 | Y24: =Y23 -> 684442 | Z24: =Y24-Y23 -> 0 | AA24: =AA23 -> 35634 | AB24: =AA24-AA23 -> 0 | AC24: =AC23 -> 905726 | AD24: =AC24-AC23 -> 0 | AE24: =AB24+X24+T24 -> 3 | AF24: =V24+Z24+AD24 -> 665 | AG24: =IF(AE24>0,AF24/AE24,0) -> 221.66667 | AI24: =R24-'EDl log'!B22 -> -661317
A25: ='General information '!F28 -> 0 | B25: =SUM(230*A25) -> 0 | C25: 44158 | D25: 32440574 | E25: =D25-D24 -> 2716 | F25: 3912110 | G25: =F25-F24 -> 667 | H25: 17720954 | I25: =H25-H24 -> 884 | J25: 28798346 | K25: =J25-J24 -> 2036 | L25: 23855784 | M25: =L25-L24 -> 2106 | N25: =M25+K25+I25+G25+E25 -> 8409 | O25: =IF(B25>0,N25/B25,0) -> 0 | P25: 16430.715 | Q25: =(P25-P24)*1000 -> 1695 | R25: =N25-Q25 -> 6714 | S25: =S24 -> 10006 | T25: =S25-S24 -> 0 | U25: =U24 -> 400936 | V25: =U25-U24 -> 0 | W25: 32109 | X25: =W25-W24 -> 4 | Y25: 685162 | Z25: =Y25-Y24 -> 720 | AA25: =AA24 -> 35634 | AB25: =AA25-AA24 -> 0 | AC25: =AC24 -> 905726 | AD25: =AC25-AC24 -> 0 | AE25: =AB25+X25+T25 -> 4 | AF25: =V25+Z25+AD25 -> 720 | AG25: =IF(AE25>0,AF25/AE25,0) -> 180 | AI25: =R25-'EDl log'!B23 -> -665208
A26: ='General information '!F29 -> 0 | B26: =SUM(230*A26) -> 0 | C26: 44159 | D26: 32442562 | E26: =D26-D25 -> 1988 | F26: 3912645 | G26: =F26-F25 -> 535 | H26: 17721626 | I26: =H26-H25 -> 672 | J26: 28799946 | K26: =J26-J25 -> 1600 | L26: 23857174 | M26: =L26-L25 -> 1390 | N26: =M26+K26+I26+G26+E26 -> 6185 | O26: =IF(B26>0,N26/B26,0) -> 0 | P26: 16432.079 | Q26: =(P26-P25)*1000 -> 1364 | R26: =N26-Q26 -> 4821 | S26: =S25 -> 10006 | T26: =S26-S25 -> 0 | U26: =U25 -> 400936 | V26: =U26-U25 -> 0 | W26: 32112 | X26: =W26-W25 -> 3 | Y26: 685785 | Z26: =Y26-Y25 -> 623 | AA26: =AA25 -> 35634 | AB26: =AA26-AA25 -> 0 | AC26: =AC25 -> 905726 | AD26: =AC26-AC25 -> 0 | AE26: =AB26+X26+T26 -> 3 | AF26: =V26+Z26+AD26 -> 623 | AG26: =IF(AE26>0,AF26/AE26,0) -> 207.66667 | AI26: =R26-'EDl log'!B24 -> -670294
A27: ='General information '!F30 -> 0 | B27: =SUM(230*A27) -> 0 | C27: 44160 | D27: 32445110 | E27: =D27-D26 -> 2548 | F27: 3913385 | G27: =F27-F26 -> 740 | H27: 17722464 | I27: =H27-H26 -> 838 | J27: 28802008 | K27: =J27-J26 -> 2062 | L27: 23858882 | M27: =L27-L26 -> 1708 | N27: =M27+K27+I27+G27+E27 -> 7896 | O27: =IF(B27>0,N27/B27,0) -> 0 | P27: 16433.6 | Q27: =(P27-P26)*1000 -> 1521 | R27: =N27-Q27 -> 6375 | S27: =S26 -> 10006 | T27: =S27-S26 -> 0 | U27: =U26 -> 400936 | V27: =U27-U26 -> 0 | W27: 32116 | X27: =W27-W26 -> 4 | Y27: 686833 | Z27: =Y27-Y26 -> 1048 | AA27: =AA26 -> 35634 | AB27: =AA27-AA26 -> 0 | AC27: =AC26 -> 905726 | AD27: =AC27-AC26 -> 0 | AE27: =AB27+X27+T27 -> 4 | AF27: =V27+Z27+AD27 -> 1048 | AG27: =IF(AE27>0,AF27/AE27,0) -> 262 | AI27: =R27-'EDl log'!B25 -> -672475
A28: ='General information '!F31 -> 0 | B28: =SUM(230*A28) -> 0 | C28: 44161 | D28: 32447302 | E28: =D28-D27 -> 2192 | F28: 3914064 | G28: =F28-F27 -> 679 | H28: 17723222 | I28: =H28-H27 -> 758 | J28: 28803336 | K28: =J28-J27 -> 1328 | L28: 23860522 | M28: =L28-L27 -> 1640 | N28: =M28+K28+I28+G28+E28 -> 6597 | O28: =IF(B28>0,N28/B28,0) -> 0 | P28: 16434.734 | Q28: =(P28-P27)*1000 -> 1134 | R28: =N28-Q28 -> 5463 | S28: =S27 -> 10006 | T28: =S28-S27 -> 0 | U28: =U27 -> 400936 | V28: =U28-U27 -> 0 | W28: 32119 | X28: =W28-W27 -> 3 | Y28: 687201 | Z28: =Y28-Y27 -> 368 | AA28: =AA27 -> 35634 | AB28: =AA28-AA27 -> 0 | AC28: =AC27 -> 905726 | AD28: =AC28-AC27 -> 0 | AE28: =AB28+X28+T28 -> 3 | AF28: =V28+Z28+AD28 -> 368 | AG28: =IF(AE28>0,AF28/AE28,0) -> 122.66667 | AI28: =R28-'EDl log'!B26 -> -676920
A29: ='General information '!F32 -> 0 | B29: =SUM(230*A29) -> 0 | C29: 44162 | D29: =D28 -> 32447302 | E29: =D29-D28 -> 0 | F29: =F28 -> 3914064 | G29: =F29-F28 -> 0 | H29: =H28 -> 17723222 | I29: =H29-H28 -> 0 | J29: =J28 -> 28803336 | K29: =J29-J28 -> 0 | L29: =L28 -> 23860522 | M29: =L29-L28 -> 0 | N29: =M29+K29+I29+G29+E29 -> 0 | O29: =IF(B29>0,N29/B29,0) -> 0 | P29: =P28 -> 16434.734 | Q29: =(P29-P28)*1000 -> 0 | R29: =N29-Q29 -> 0 | S29: =S28 -> 10006 | T29: =S29-S28 -> 0 | U29: =U28 -> 400936 | V29: =U29-U28 -> 0 | W29: =W28 -> 32119 | X29: =W29-W28 -> 0 | Y29: =Y28 -> 687201 | Z29: =Y29-Y28 -> 0 | AA29: =AA28 -> 35634 | AB29: =AA29-AA28 -> 0 | AC29: =AC28 -> 905726 | AD29: =AC29-AC28 -> 0 | AE29: =AB29+X29+T29 -> 0 | AF29: =V29+Z29+AD29 -> 0 | AG29: =IF(AE29>0,AF29/AE29,0) -> 0 | AI29: =R29-'EDl log'!B27 -> -684952
A30: ='General information '!F33 -> 0 | B30: =SUM(230*A30) -> 0 | C30: 44163 | D30: =D29 -> 32447302 | E30: =D30-D29 -> 0 | F30: =F29 -> 3914064 | G30: =F30-F29 -> 0 | H30: =H29 -> 17723222 | I30: =H30-H29 -> 0 | J30: =J29 -> 28803336 | K30: =J30-J29 -> 0 | L30: =L29 -> 23860522 | M30: =L30-L29 -> 0 | N30: =M30+K30+I30+G30+E30 -> 0 | O30: =IF(B30>0,N30/B30,0) -> 0 | P30: =P29 -> 16434.734 | Q30: =(P30-P29)*1000 -> 0 | R30: =N30-Q30 -> 0 | S30: =S29 -> 10006 | T30: =S30-S29 -> 0 | U30: =U29 -> 400936 | V30: =U30-U29 -> 0 | W30: =W29 -> 32119 | X30: =W30-W29 -> 0 | Y30: =Y29 -> 687201 | Z30: =Y30-Y29 -> 0 | AA30: =AA29 -> 35634 | AB30: =AA30-AA29 -> 0 | AC30: =AC29 -> 905726 | AD30: =AC30-AC29 -> 0 | AE30: =AB30+X30+T30 -> 0 | AF30: =V30+Z30+AD30 -> 0 | AG30: =IF(AE30>0,AF30/AE30,0) -> 0 | AI30: =R30-'EDl log'!B28 -> -688194
A31: ='General information '!F34 -> 0 | B31: =SUM(230*A31) -> 0 | C31: 44164 | D31: =D30 -> 32447302 | E31: =D31-D30 -> 0 | F31: =F30 -> 3914064 | G31: =F31-F30 -> 0 | H31: =H30 -> 17723222 | I31: =H31-H30 -> 0 | J31: =J30 -> 28803336 | K31: =J31-J30 -> 0 | L31: =L30 -> 23860522 | M31: =L31-L30 -> 0 | N31: =M31+K31+I31+G31+E31 -> 0 | O31: =IF(B31>0,N31/B31,0) -> 0 | P31: =P30 -> 16434.734 | Q31: =(P31-P30)*1000 -> 0 | R31: =N31-Q31 -> 0 | S31: =S30 -> 10006 | T31: =S31-S30 -> 0 | U31: =U30 -> 400936 | V31: =U31-U30 -> 0 | W31: =W30 -> 32119 | X31: =W31-W30 -> 0 | Y31: =Y30 -> 687201 | Z31: =Y31-Y30 -> 0 | AA31: =AA30 -> 35634 | AB31: =AA31-AA30 -> 0 | AC31: =AC30 -> 905726 | AD31: =AC31-AC30 -> 0 | AE31: =AB31+X31+T31 -> 0 | AF31: =V31+Z31+AD31 -> 0 | AG31: =IF(AE31>0,AF31/AE31,0) -> 0 | AI31: =R31-'EDl log'!B29 -> -691215
A32: ='General information '!F35 -> 0 | B32: =SUM(230*A32) -> 0 | C32: 44165 | D32: =D31 -> 32447302 | E32: =D32-D31 -> 0 | F32: =F31 -> 3914064 | G32: =F32-F31 -> 0 | H32: =H31 -> 17723222 | I32: =H32-H31 -> 0 | J32: =J31 -> 28803336 | K32: =J32-J31 -> 0 | L32: =L31 -> 23860522 | M32: =L32-L31 -> 0 | N32: =M32+K32+I32+G32+E32 -> 0 | O32: =IF(B32>0,N32/B32,0) -> 0 | P32: =P31 -> 16434.734 | Q32: =(P32-P31)*1000 -> 0 | R32: =N32-Q32 -> 0 | S32: =S31 -> 10006 | T32: =S32-S31 -> 0 | U32: =U31 -> 400936 | V32: =U32-U31 -> 0 | W32: =W31 -> 32119 | X32: =W32-W31 -> 0 | Y32: =Y31 -> 687201 | Z32: =Y32-Y31 -> 0 | AA32: =AA31 -> 35634 | AB32: =AA32-AA31 -> 0 | AC32: =AC31 -> 905726 | AD32: =AC32-AC31 -> 0 | AE32: =AB32+X32+T32 -> 0 | AF32: =V32+Z32+AD32 -> 0 | AG32: =IF(AE32>0,AF32/AE32,0) -> 0 | AI32: =R32-'EDl log'!B30 -> -691215
A33: ='General information '!F36 -> 0 | B33: =SUM(230*A33) -> 0 | C33: 44166 | D33: =D32 -> 32447302 | E33: =D33-D32 -> 0 | F33: =F32 -> 3914064 | G33: =F33-F32 -> 0 | H33: =H32 -> 17723222 | I33: =H33-H32 -> 0 | J33: =J32 -> 28803336 | K33: =J33-J32 -> 0 | L33: =L32 -> 23860522 | M33: =L33-L32 -> 0 | N33: =M33+K33+I33+G33+E33 -> 0 | O33: =IF(B33>0,N33/B33,0) -> 0 | P33: =P32 -> 16434.734 | Q33: =(P33-P32)*1000 -> 0 | R33: =N33-Q33 -> 0 | S33: =S32 -> 10006 | T33: =S33-S32 -> 0 | U33: =U32 -> 400936 | V33: =U33-U32 -> 0 | W33: =W32 -> 32119 | X33: =W33-W32 -> 0 | Y33: =Y32 -> 687201 | Z33: =Y33-Y32 -> 0 | AA33: =AA32 -> 35634 | AB33: =AA33-AA32 -> 0 | AC33: =AC32 -> 905726 | AD33: =AC33-AC32 -> 0 | AE33: =AB33+X33+T33 -> 0 | AF33: =V33+Z33+AD33 -> 0 | AG33: =IF(AE33>0,AF33/AE33,0) -> 0 | AI33: =R33-'EDl log'!B31 -> -691215

Sheet B5
F1: Boiler A | J1: =J36 -> 0.75 | K1: Boiler B | P1: Boiler C | V1: Boiler | X1: SteamA | AC1: SteamB | AH1: Steam | AI1: Boiler & steam | AL1: Total Boiler Runing H | AM1: Total Steam Runing H | AN1: GAS1 % | AO1: GAS1/L | AP1: GAS2% | AQ1: Gas2/L | AR1: GAS3% | AS1: GAS3/L | AU1: Gas Cons | AV1: Delivery | AW1: Cost/L
B2: Level Tank Gen | C2: Level tank Boiler | D2: Daily Cons Bo. | E2: Boiler litter | F2: Boiler A | G2: Run Hr a | H2: Boiler A fuel | I2: Daily consumption | J2: AVG | K2: index Run H | L2: Run Hrb | M2: Boiler B Fuel | O2: Daily consumption | P2: Boiler C | S2: Run C | U2: Total RH | V2: Total Fuel | X2: SteamA | Y2: Run SA | Z2: Steam A Conter | AA2: Liters | AC2: SteamB | AD2: Run SteamB | AE2: Steam B Conter | AF2: SB Litters | AG2: Avg | AH2: Total Fuel | AI2: Total Fuel
S3: 0
A4: =ELEC!C2 -> 44135 | B4: =[1]B5!B35 -> 243 | C4: =[1]B5!C35 -> 249 | D4: =[1]B5!D35 -> 4 | E4: =[1]B5!E35 -> 33.52 | F4: =[1]B5!F35 -> 1648 | G4: =[1]B5!G35 -> 0 | H4: =[1]B5!H35 -> 357868 | I4: =[1]B5!I35 -> 0 | ... AM4: =[1]B5!AM35 -> 0 | AN4: 67 | AO4: =[1]B5!AO35 -> 1860 | AP4: =[1]B5!AP35 -> 52 | AQ4: =[1]B5!AQ35 -> 1560 | AR4: =[1]B5!AR35 -> 68 | AS4: =[1]B5!AS35 -> 2040 | AT4: =[1]B5!AT35 -> 5460 | AU4: =[1]B5!AU35 -> 0 | AV4: =[1]B5!AV35 -> 0 | ... AX4: =[1]B5!AX35 -> 0.8
A5: =ELEC!C3 -> 44136 | B5: 241 | C5: 247 | D5: =C4-C5 -> 2 | E5: =D5*8.38 -> 16.76 | F5: 1648 | G5: =F5-F4 -> 0 | H5: 357868 | I5: =SUM(H5-H4) -> 0 | J5: 1 | K5: 2147 | L5: =K5-K4 -> 2 | M5: 157656 | N5: =M5-M4 -> 205 | O5: =O4 -> 211.875 | P5: 1854 | Q5: 157348 | R5: =Q5-Q4 -> 0 | S5: =SUM(P5-P4) -> 0 | T5: =SUM(S5*$T$2) -> 0 | U5: =SUM(G5+L5+S5) -> 2 | V5: =R5+N5+I5:I5 -> 205 | W5: =SUM(V5/U5) -> 102.5 | X5: 2448 | Y5: =X5-X4 -> 0 | Z5: 137506 | AA5: =Z5-Z4 -> 0 | AB5: =SUM(Y5*$AB$2) -> 0 | AC5: 1933 | AD5: =AC5-AC4 -> 0 | AE5: 365212 | AF5: =AE5-AE4 -> 0 | AG5: =IF(AD5>0,AF5/AD5,0) -> 0 | AH5: =AF5+AA5 -> 0 | AI5: =SUM(AH5+V5) -> 205 | AJ5: =-tanks!AW6 -> 205 | AK5: =SUM(AJ5-AI5) -> 0 | AL5: =S5+L5+G5 -> 2 | AM5: =Y5+AD5 -> 0 | AN5: 67 | AO5: =(AN5/100)*3000 -> 2010 | AP5: 55 | AQ5: =(AP5/100)*3000 -> 1650 | AR5: 63 | AS5: =(AR5/100)*3000 -> 1890 | AT5: =SUM(AO5+AQ5+AS5) -> 5550 | AU5: =AT4-AT5+AV5 -> -90 | AX5: =IF(AV5>0,AW5,AX4) -> 0.8
A6: =ELEC!C4 -> 44137 | B6: 239.2 | C6: 246 | D6: =C5-C6 -> 1 | E6: =D6*8.38 -> 8.38 | F6: 1650 | G6: =F6-F5 -> 2 | H6: 357869 | I6: =SUM(H6-H5) -> 1 | J6: =IF(G6>0,I6/G6,0) -> 0.5 | K6: 2148 | L6: =K6-K5 -> 1 | M6: 157704 | N6: =M6-M5 -> 48 | O6: =O5 -> 211.875 | P6: 1855 | Q6: 157396 | R6: =Q6-Q5 -> 48 | S6: =SUM(P6-P5) -> 1 | T6: =SUM(S6*$T$2) -> 0 | U6: =SUM(G6+L6+S6) -> 4 | V6: =R6+N6+I6:I6 -> 97 | W6: =SUM(V6/U6) -> 24.25 | X6: =X5 -> 2448 | Y6: =X6-X5 -> 0 | Z6: =Z5 -> 137506 | AA6: =Z6-Z5 -> 0 | AB6: =SUM(Y6*$AB$2) -> 0 | AC6: =AC5 -> 1933 | AD6: =AC6-AC5 -> 0 | AE6: =AE5 -> 365212 | AF6: =AE6-AE5 -> 0 | AG6: =IF(AD6>0,AF6/AD6,0) -> 0 | AH6: =AF6+AA6 -> 0 | AI6: =SUM(AH6+V6) -> 97 | AJ6: =-tanks!AW7 -> 97 | AK6: =SUM(AJ6-AI6) -> 0 | AL6: =S6+L6+G6 -> 4 | AM6: =Y6+AD6 -> 0 | AN6: 67 | AO6: =(AN6/100)*3000 -> 2010 | AP6: 55 | AQ6: =(AP6/100)*3000 -> 1650 | AR6: =AR5 -> 63 | AS6: =(AR6/100)*3000 -> 1890 | AT6: =SUM(AO6+AQ6+AS6) -> 5550 | AU6: =AT5-AT6+AV6 -> 0 | AX6: =IF(AV6>0,AW6,AX5) -> 0.8
A7: =ELEC!C5 -> 44138 | B7: 237 | C7: 243 | D7: =C6-C7 -> 3 | E7: =D7*8.38 -> 25.14 | F7: 1653 | G7: =F7-F6 -> 3 | H7: 357869 | I7: =SUM(H7-H6) -> 0 | J7: =IF(G7>0,I7/G7,0) -> 0 | K7: =K6 -> 2148 | L7: =K7-K6 -> 0 | M7: =M6 -> 157704 | N7: =M7-M6 -> 0 | O7: =O6 -> 211.875 | P7: =P6 -> 1855 | Q7: =Q6 -> 157396 | R7: =Q7-Q6 -> 0 | S7: =SUM(P7-P6) -> 0 | T7: =SUM(S7*$T$2) -> 0 | U7: =SUM(G7+L7+S7) -> 3 | V7: =R7+N7+I7:I7 -> 0 | W7: =SUM(V7/U7) -> 0 | X7: =X6 -> 2448 | Y7: =X7-X6 -> 0 | Z7: =Z6 -> 137506 | AA7: =Z7-Z6 -> 0 | AB7: =SUM(Y7*$AB$2) -> 0 | AC7: =AC6 -> 1933 | AD7: =AC7-AC6 -> 0 | AE7: =AE6 -> 365212 | AF7: =AE7-AE6 -> 0 | AG7: =IF(AD7>0,AF7/AD7,0) -> 0 | AH7: =AF7+AA7 -> 0 | AI7: =SUM(AH7+V7) -> 0 | AJ7: =-tanks!AW8 -> 0 | AK7: =SUM(AJ7-AI7) -> 0 | AL7: =S7+L7+G7 -> 3 | AM7: =Y7+AD7 -> 0 | AN7: 67 | AO7: =(AN7/100)*3000 -> 2010 | AP7: =AP6 -> 55 | AQ7: =(AP7/100)*3000 -> 1650 | AR7: =AR6 -> 63 | AS7: =(AR7/100)*3000 -> 1890 | AT7: =SUM(AO7+AQ7+AS7) -> 5550 | AU7: =AT6-AT7+AV7 -> 0 | AX7: =IF(AV7>0,AW7,AX6) -> 0.8
A8: =ELEC!C6 -> 44139 | B8: 234 | C8: 240 | D8: =C7-C8 -> 3 | E8: =D8*8.38 -> 25.14 | F8: 1656 | G8: =F8-F7 -> 3 | H8: =H7 -> 357869 | I8: =SUM(H8-H7) -> 0 | J8: =IF(G8>0,I8/G8,0) -> 0 | K8: 2148 | L8: =K8-K7 -> 0 | M8: 157704 | N8: =M8-M7 -> 0 | O8: =O7 -> 211.875 | P8: 1855 | Q8: 157396 | R8: =Q8-Q7 -> 0 | S8: =SUM(P8-P7) -> 0 | T8: =SUM(S8*$T$2) -> 0 | U8: =SUM(G8+L8+S8) -> 3 | V8: =R8+N8+I8:I8 -> 0 | W8: =SUM(V8/U8) -> 0 | X8: =X7 -> 2448 | Y8: =X8-X7 -> 0 | Z8: =Z7 -> 137506 | AA8: =Z8-Z7 -> 0 | AB8: =SUM(Y8*$AB$2) -> 0 | AC8: =AC7 -> 1933 | AD8: =AC8-AC7 -> 0 | AE8: =AE7 -> 365212 | AF8: =AE8-AE7 -> 0 | AG8: =IF(AD8>0,AF8/AD8,0) -> 0 | AH8: =AF8+AA8 -> 0 | AI8: =SUM(AH8+V8) -> 0 | AJ8: =-tanks!AW9 -> 0 | AK8: =SUM(AJ8-AI8) -> 0 | AL8: =S8+L8+G8 -> 3 | AM8: =Y8+AD8 -> 0 | AN8: =AN7 -> 67 | AO8: =(AN8/100)*3000 -> 2010 | AP8: =AP7 -> 55 | AQ8: =(AP8/100)*3000 -> 1650 | AR8: =AR7 -> 63 | AS8: =(AR8/100)*3000 -> 1890 | AT8: =SUM(AO8+AQ8+AS8) -> 5550 | AU8: =AT7-AT8+AV8 -> 0 | AX8: =IF(AV8>0,AW8,AX7) -> 0.8
A9: =ELEC!C7 -> 44140 | B9: 231 | C9: 238 | D9: =C8-C9 -> 2 | E9: =D9*8.38 -> 16.76 | F9: 1659 | G9: =F9-F8 -> 3 | H9: =H8 -> 357869 | I9: =SUM(H9-H8) -> 0 | J9: =IF(G9>0,I9/G9,0) -> 0 | K9: =K8 -> 2148 | L9: =K9-K8 -> 0 | M9: =M8 -> 157704 | N9: =M9-M8 -> 0 | O9: =O8 -> 211.875 | P9: =P8 -> 1855 | Q9: =Q8 -> 157396 | R9: =Q9-Q8 -> 0 | S9: =SUM(P9-P8) -> 0 | T9: =SUM(S9*$T$2) -> 0 | U9: =SUM(G9+L9+S9) -> 3 | V9: =R9+N9+I9:I9 -> 0 | W9: =SUM(V9/U9) -> 0 | X9: =X8 -> 2448 | Y9: =X9-X8 -> 0 | Z9: =Z8 -> 137506 | AA9: =Z9-Z8 -> 0 | AB9: =SUM(Y9*$AB$2) -> 0 | AC9: =AC8 -> 1933 | AD9: =AC9-AC8 -> 0 | AE9: =AE8 -> 365212 | AF9: =AE9-AE8 -> 0 | AG9: =IF(AD9>0,AF9/AD9,0) -> 0 | AH9: =AF9+AA9 -> 0 | AI9: =SUM(AH9+V9) -> 0 | AJ9: =-tanks!AW10 -> 0 | AK9: =SUM(AJ9-AI9) -> 0 | AL9: =S9+L9+G9 -> 3 | AM9: =Y9+AD9 -> 0 | AN9: =AN8 -> 67 | AO9: =(AN9/100)*3000 -> 2010 | AP9: =AP8 -> 55 | AQ9: =(AP9/100)*3000 -> 1650 | AR9: =AR8 -> 63 | AS9: =(AR9/100)*3000 -> 1890 | AT9: =SUM(AO9+AQ9+AS9) -> 5550 | AU9: =AT8-AT9+AV9 -> 0 | AX9: =IF(AV9>0,AW9,AX8) -> 0.8
A10: =ELEC!C8 -> 44141 | B10: 229 | C10: 235 | D10: =C9-C10 -> 3 | E10: =D10*8.38 -> 25.14 | F10: =F9 -> 1659 | G10: =F10-F9 -> 0 | H10: =H9 -> 357869 | I10: =SUM(H10-H9) -> 0 | J10: =IF(G10>0,I10/G10,0) -> 0 | K10: =K9 -> 2148 | L10: =K10-K9 -> 0 | M10: =M9 -> 157704 | N10: =M10-M9 -> 0 | O10: =O9 -> 211.875 | P10: 1856 | Q10: 157396 | R10: =Q10-Q9 -> 0 | S10: =SUM(P10-P9) -> 1 | T10: =SUM(S10*$T$2) -> 0 | U10: =SUM(G10+L10+S10) -> 1 | V10: =R10+N10+I10:I10 -> 0 | W10: =SUM(V10/U10) -> 0 | X10: =X9 -> 2448 | Y10: =X10-X9 -> 0 | Z10: =Z9 -> 137506 | AA10: =Z10-Z9 -> 0 | AB10: =SUM(Y10*$AB$2) -> 0 | AC10: =AC9 -> 1933 | AD10: =AC10-AC9 -> 0 | AE10: =AE9 -> 365212 | AF10: =AE10-AE9 -> 0 | AG10: =IF(AD10>0,AF10/AD10,0) -> 0 | AH10: =AF10+AA10 -> 0 | AI10: =SUM(AH10+V10) -> 0 | AJ10: =-tanks!AW11 -> 0 | AK10: =SUM(AJ10-AI10) -> 0 | AL10: =S10+L10+G10 -> 1 | AM10: =Y10+AD10 -> 0 | AN10: =AN9 -> 67 | AO10: =(AN10/100)*3000 -> 2010 | AP10: =AP9 -> 55 | AQ10: =(AP10/100)*3000 -> 1650 | AR10: =AR9 -> 63 | AS10: =(AR10/100)*3000 -> 1890 | AT10: =SUM(AO10+AQ10+AS10) -> 5550 | AU10: =AT9-AT10+AV10 -> 0 | AX10: =IF(AV10>0,AW10,AX9) -> 0.8
A11: =ELEC!C9 -> 44142 | B11: 227 | C11: 234 | D11: =C10-C11 -> 1 | E11: =D11*8.38 -> 8.38 | F11: 1660 | G11: =F11-F10 -> 1 | H11: =H10 -> 357869 | I11: =SUM(H11-H10) -> 0 | J11: =IF(G11>0,I11/G11,0) -> 0 | K11: =K10 -> 2148 | L11: =K11-K10 -> 0 | M11: =M10 -> 157704 | N11: =M11-M10 -> 0 | O11: =O10 -> 211.875 | P11: 1858 | Q11: 157634 | R11: =Q11-Q10 -> 238 | S11: =SUM(P11-P10) -> 2 | T11: =SUM(S11*$T$2) -> 0 | U11: =SUM(G11+L11+S11) -> 3 | V11: =R11+N11+I11:I11 -> 238 | W11: =SUM(V11/U11) -> 79.333333 | X11: =X10 -> 2448 | Y11: =X11-X10 -> 0 | Z11: =Z10 -> 137506 | AA11: =Z11-Z10 -> 0 | AB11: =SUM(Y11*$AB$2) -> 0 | AC11: =AC10 -> 1933 | AD11: =AC11-AC10 -> 0 | AE11: =AE10 -> 365212 | AF11: =AE11-AE10 -> 0 | AG11: =IF(AD11>0,AF11/AD11,0) -> 0 | AH11: =AF11+AA11 -> 0 | AI11: =SUM(AH11+V11) -> 238 | AJ11: =-tanks!AW12 -> 238 | AK11: =SUM(AJ11-AI11) -> 0 | AL11: =S11+L11+G11 -> 3 | AM11: =Y11+AD11 -> 0 | AN11: =AN10 -> 67 | AO11: =(AN11/100)*3000 -> 2010 | AP11: =AP10 -> 55 | AQ11: =(AP11/100)*3000 -> 1650 | AR11: =AR10 -> 63 | AS11: =(AR11/100)*3000 -> 1890 | AT11: =SUM(AO11+AQ11+AS11) -> 5550 | AU11: =AT10-AT11+AV11 -> 0 | AX11: =IF(AV11>0,AW11,AX10) -> 0.8
A12: =ELEC!C10 -> 44143 | B12: 225 | C12: 231 | D12: =C11-C12 -> 3 | E12: =D12*8.38 -> 25.14 | F12: 1660 | G12: =F12-F11 -> 0 | H12: =H11 -> 357869 | I12: =SUM(H12-H11) -> 0 | J12: =IF(G12>0,I12/G12,0) -> 0 | K12: =K11 -> 2148 | L12: =K12-K11 -> 0 | M12: 157707 | N12: =M12-M11 -> 3 | O12: =O11 -> 211.875 | P12: 1860 | Q12: 157793 | R12: =Q12-Q11 -> 159 | S12: =SUM(P12-P11) -> 2 | T12: =SUM(S12*$T$2) -> 0 | U12: =SUM(G12+L12+S12) -> 2 | V12: =R12+N12+I12:I12 -> 162 | W12: =SUM(V12/U12) -> 81 | X12: =X11 -> 2448 | Y12: =X12-X11 -> 0 | Z12: =Z11 -> 137506 | AA12: =Z12-Z11 -> 0 | AB12: =SUM(Y12*$AB$2) -> 0 | AC12: =AC11 -> 1933 | AD12: =AC12-AC11 -> 0 | AE12: =AE11 -> 365212 | AF12: =AE12-AE11 -> 0 | AG12: =IF(AD12>0,AF12/AD12,0) -> 0 | AH12: =AF12+AA12 -> 0 | AI12: =SUM(AH12+V12) -> 162 | AJ12: =-tanks!AW13 -> 162 | AK12: =SUM(AJ12-AI12) -> 0 | AL12: =S12+L12+G12 -> 2 | AM12: =Y12+AD12 -> 0 | AN12: =AN11 -> 67 | AO12: =(AN12/100)*3000 -> 2010 | AP12: =AP11 -> 55 | AQ12: =(AP12/100)*3000 -> 1650 | AR12: =AR11 -> 63 | AS12: =(AR12/100)*3000 -> 1890 | AT12: =SUM(AO12+AQ12+AS12) -> 5550 | AU12: =AT11-AT12+AV12 -> 0 | AX12: =IF(AV12>0,AW12,AX11) -> 0.8
A13: =ELEC!C11 -> 44144 | B13: 223 | C13: 230 | D13: =C12-C13 -> 1 | E13: =D13*8.38 -> 8.38 | F13: =F12 -> 1660 | G13: =F13-F12 -> 0 | H13: =H12 -> 357869 | I13: =SUM(H13-H12) -> 0 | J13: =IF(G13>0,I13/G13,0) -> 0 | K13: =K12 -> 2148 | L13: =K13-K12 -> 0 | M13: =M12 -> 157707 | N13: =M13-M12 -> 0 | O13: =O12 -> 211.875 | P13: 1862 | Q13: 157930 | R13: =Q13-Q12 -> 137 | S13: =SUM(P13-P12) -> 2 | T13: =SUM(S13*$T$2) -> 0 | U13: =SUM(G13+L13+S13) -> 2 | V13: =R13+N13+I13:I13 -> 137 | W13: =SUM(V13/U13) -> 68.5 | X13: =X12 -> 2448 | Y13: =X13-X12 -> 0 | Z13: =Z12 -> 137506 | AA13: =Z13-Z12 -> 0 | AB13: =SUM(Y13*$AB$2) -> 0 | AC13: =AC12 -> 1933 | AD13: =AC13-AC12 -> 0 | AE13: =AE12 -> 365212 | AF13: =AE13-AE12 -> 0 | AG13: =IF(AD13>0,AF13/AD13,0) -> 0 | AH13: =AF13+AA13 -> 0 | AI13: =SUM(AH13+V13) -> 137 | AJ13: =-tanks!AW14 -> 137 | AK13: =SUM(AJ13-AI13) -> 0 | AL13: =S13+L13+G13 -> 2 | AM13: =Y13+AD13 -> 0 | AN13: =AN12 -> 67 | AO13: =(AN13/100)*3000 -> 2010 | AP13: =AP12 -> 55 | AQ13: =(AP13/100)*3000 -> 1650 | AR13: =AR12 -> 63 | AS13: =(AR13/100)*3000 -> 1890 | AT13: =SUM(AO13+AQ13+AS13) -> 5550 | AU13: =AT12-AT13+AV13 -> 0 | AX13: =IF(AV13>0,AW13,AX12) -> 0.8
A14: =ELEC!C12 -> 44145 | B14: 221 | C14: 228 | D14: =C13-C14 -> 2 | E14: =D14*8.38 -> 16.76 | F14: 1660 | G14: =F14-F13 -> 0 | H14: =H13 -> 357869 | I14: =SUM(H14-H13) -> 0 | J14: =IF(G14>0,I14/G14,0) -> 0 | K14: =K13 -> 2148 | L14: =K14-K13 -> 0 | M14: =M13 -> 157707 | N14: =M14-M13 -> 0 | O14: =O13 -> 211.875 | P14: 1863 | Q14: 158074 | R14: =Q14-Q13 -> 144 | S14: =SUM(P14-P13) -> 1 | T14: =SUM(S14*$T$2) -> 0 | U14: =SUM(G14+L14+S14) -> 1 | V14: =R14+N14+I14:I14 -> 144 | W14: =SUM(V14/U14) -> 144 | X14: =X13 -> 2448 | Y14: =X14-X13 -> 0 | Z14: =Z13 -> 137506 | AA14: =Z14-Z13 -> 0 | AB14: =SUM(Y14*$AB$2) -> 0 | AC14: =AC13 -> 1933 | AD14: =AC14-AC13 -> 0 | AE14: =AE13 -> 365212 | AF14: =AE14-AE13 -> 0 | AG14: =IF(AD14>0,AF14/AD14,0) -> 0 | AH14: =AF14+AA14 -> 0 | AI14: =SUM(AH14+V14) -> 144 | AJ14: =-tanks!AW15 -> 144 | AK14: =SUM(AJ14-AI14) -> 0 | AL14: =S14+L14+G14 -> 1 | AM14: =Y14+AD14 -> 0 | AN14: =AN13 -> 67 | AO14: =(AN14/100)*3000 -> 2010 | AP14: =AP13 -> 55 | AQ14: =(AP14/100)*3000 -> 1650 | AR14: =AR13 -> 63 | AS14: =(AR14/100)*3000 -> 1890 | AT14: =SUM(AO14+AQ14+AS14) -> 5550 | AU14: =AT13-AT14+AV14 -> 0 | AX14: =IF(AV14>0,AW14,AX13) -> 0.8
A15: =ELEC!C13 -> 44146 | B15: 219 | C15: 226 | D15: =C14-C15 -> 2 | E15: =D15*8.38 -> 16.76 | F15: 1660 | G15: =F15-F14 -> 0 | H15: =H14 -> 357869 | I15: =SUM(H15-H14) -> 0 | J15: =IF(G15>0,I15/G15,0) -> 0 | K15: =K14 -> 2148 | L15: =K15-K14 -> 0 | M15: =M14 -> 157707 | N15: =M15-M14 -> 0 | O15: =O14 -> 211.875 | P15: 1865 | Q15: 158236 | R15: =Q15-Q14 -> 162 | S15: =SUM(P15-P14) -> 2 | T15: =SUM(S15*$T$2) -> 0 | U15: =SUM(G15+L15+S15) -> 2 | V15: =R15+N15+I15:I15 -> 162 | W15: =SUM(V15/U15) -> 81 | X15: =X14 -> 2448 | Y15: =X15-X14 -> 0 | Z15: =Z14 -> 137506 | AA15: =Z15-Z14 -> 0 | AB15: =SUM(Y15*$AB$2) -> 0 | AC15: =AC14 -> 1933 | AD15: =AC15-AC14 -> 0 | AE15: =AE14 -> 365212 | AF15: =AE15-AE14 -> 0 | AG15: =IF(AD15>0,AF15/AD15,0) -> 0 | AH15: =AF15+AA15 -> 0 | AI15: =SUM(AH15+V15) -> 162 | AJ15: =-tanks!AW16 -> 162 | AK15: =SUM(AJ15-AI15) -> 0 | AL15: =S15+L15+G15 -> 2 | AM15: =Y15+AD15 -> 0 | AN15: =AN14 -> 67 | AO15: =(AN15/100)*3000 -> 2010 | AP15: =AP14 -> 55 | AQ15: =(AP15/100)*3000 -> 1650 | AR15: =AR14 -> 63 | AS15: =(AR15/100)*3000 -> 1890 | AT15: =SUM(AO15+AQ15+AS15) -> 5550 | AU15: =AT14-AT15+AV15 -> 0 | AX15: =IF(AV15>0,AW15,AX14) -> 0.8
A16: =ELEC!C14 -> 44147 | B16: 217 | C16: 223 | D16: =C15-C16 -> 3 | E16: =D16*8.38 -> 25.14 | F16: 1660 | G16: =F16-F15 -> 0 | H16: =H15 -> 357869 | I16: =SUM(H16-H15) -> 0 | J16: =IF(G16>0,I16/G16,0) -> 0 | K16: =K15 -> 2148 | L16: =K16-K15 -> 0 | M16: =M15 -> 157707 | N16: =M16-M15 -> 0 | O16: =O15 -> 211.875 | P16: 1867 | Q16: 158400 | R16: =Q16-Q15 -> 164 | S16: =SUM(P16-P15) -> 2 | T16: =SUM(S16*$T$2) -> 0 | U16: =SUM(G16+L16+S16) -> 2 | V16: =R16+N16+I16:I16 -> 164 | W16: =SUM(V16/U16) -> 82 | X16: 2449 | Y16: =X16-X15 -> 1 | Z16: 137586 | AA16: =Z16-Z15 -> 80 | AB16: =SUM(Y16*$AB$2) -> 0 | AC16: 1933 | AD16: =AC16-AC15 -> 0 | AE16: =AE15 -> 365212 | AF16: =AE16-AE15 -> 0 | AG16: =IF(AD16>0,AF16/AD16,0) -> 0 | AH16: =AF16+AA16 -> 80 | AI16: =SUM(AH16+V16) -> 244 | AJ16: =-tanks!AW17 -> 244 | AK16: =SUM(AJ16-AI16) -> 0 | AL16: =S16+L16+G16 -> 2 | AM16: =Y16+AD16 -> 1 | AN16: =AN15 -> 67 | AO16: =(AN16/100)*3000 -> 2010 | AP16: =AP15 -> 55 | AQ16: =(AP16/100)*3000 -> 1650 | AR16: =AR15 -> 63 | AS16: =(AR16/100)*3000 -> 1890 | AT16: =SUM(AO16+AQ16+AS16) -> 5550 | AU16: =AT15-AT16+AV16 -> 0 | AX16: =IF(AV16>0,AW16,AX15) -> 0.8
A17: =ELEC!C15 -> 44148 | B17: 215 | C17: 221 | D17: =C16-C17 -> 2 | E17: =D17*8.38 -> 16.76 | F17: =F16 -> 1660 | G17: =F17-F16 -> 0 | H17: =H16 -> 357869 | I17: =SUM(H17-H16) -> 0 | J17: =IF(G17>0,I17/G17,0) -> 0 | K17: =K16 -> 2148 | L17: =K17-K16 -> 0 | M17: =M16 -> 157707 | N17: =M17-M16 -> 0 | O17: =O16 -> 211.875 | P17: 1868 | Q17: 158537 | R17: =Q17-Q16 -> 137 | S17: =SUM(P17-P16) -> 1 | T17: =SUM(S17*$T$2) -> 0 | U17: =SUM(G17+L17+S17) -> 1 | V17: =R17+N17+I17:I17 -> 137 | X17: =X16 -> 2449 | Y17: =X17-X16 -> 0 | Z17: =Z16 -> 137586 | AA17: =Z17-Z16 -> 0 | AB17: =SUM(Y17*$AB$2) -> 0 | AC17: =AC16 -> 1933 | AD17: =AC17-AC16 -> 0 | AE17: =AE16 -> 365212 | AF17: =AE17-AE16 -> 0 | AG17: =IF(AD17>0,AF17/AD17,0) -> 0 | AH17: =AF17+AA17 -> 0 | AI17: =SUM(AH17+V17) -> 137 | AJ17: =-tanks!AW18 -> 137 | AK17: =SUM(AJ17-AI17) -> 0 | AL17: =S17+L17+G17 -> 1 | AM17: =Y17+AD17 -> 0 | AN17: =AN16 -> 67 | AO17: =(AN17/100)*3000 -> 2010 | AP17: =AP16 -> 55 | AQ17: =(AP17/100)*3000 -> 1650 | AR17: =AR16 -> 63 | AS17: =(AR17/100)*3000 -> 1890 | AT17: =SUM(AO17+AQ17+AS17) -> 5550 | AU17: =AT16-AT17+AV17 -> 0 | AX17: =IF(AV17>0,AW17,AX16) -> 0.8
A18: =ELEC!C16 -> 44149 | B18: 213 | C18: 219 | D18: =C17-C18 -> 2 | E18: =D18*8.38 -> 16.76 | F18: =F17 -> 1660 | G18: =F18-F17 -> 0 | H18: =H17 -> 357869 | I18: =SUM(H18-H17) -> 0 | J18: =IF(G18>0,I18/G18,0) -> 0 | K18: =K17 -> 2148 | L18: =K18-K17 -> 0 | M18: =M17 -> 157707 | N18: =M18-M17 -> 0 | O18: 1869 | P18: 1869 | Q18: 158699 | R18: =Q18-Q17 -> 162 | S18: =SUM(P18-P17) -> 1 | T18: =SUM(S18*$T$2) -> 0 | U18: =SUM(G18+L18+S18) -> 1 | V18: =R18+N18+I18:I18 -> 162 | X18: =X17 -> 2449 | Y18: =X18-X17 -> 0 | Z18: =Z17 -> 137586 | AA18: =Z18-Z17 -> 0 | AB18: =SUM(Y18*$AB$2) -> 0 | AC18: =AC17 -> 1933 | AD18: =AC18-AC17 -> 0 | AE18: =AE17 -> 365212 | AF18: =AE18-AE17 -> 0 | AG18: =IF(AD18>0,AF18/AD18,0) -> 0 | AH18: =AF18+AA18 -> 0 | AI18: =SUM(AH18+V18) -> 162 | AJ18: =-tanks!AW19 -> 162 | AK18: =SUM(AJ18-AI18) -> 0 | AL18: =S18+L18+G18 -> 1 | AM18: =Y18+AD18 -> 0 | AN18: =AN17 -> 67 | AO18: =(AN18/100)*3000 -> 2010 | AP18: =AP17 -> 55 | AQ18: =(AP18/100)*3000 -> 1650 | AR18: 62 | AS18: =(AR18/100)*3000 -> 1860 | AT18: =SUM(AO18+AQ18+AS18) -> 5520 | AU18: =AT17-AT18+AV18 -> 30 | AX18: =IF(AV18>0,AW18,AX17) -> 0.8
A19: =ELEC!C17 -> 44150 | B19: 211 | C19: 217.3 | D19: =C18-C19 -> 1.7 | E19: =D19*8.38 -> 14.246 | F19: =F18 -> 1660 | G19: =F19-F18 -> 0 | H19: =H18 -> 357869 | I19: =SUM(H19-H18) -> 0 | J19: =IF(G19>0,I19/G19,0) -> 0 | K19: 2148 | L19: =K19-K18 -> 0 | M19: 157707 | N19: =M19-M18 -> 0 | O19: =O18 -> 1869 | P19: 1870 | Q19: 158856 | R19: =Q19-Q18 -> 157 | S19: =SUM(P19-P18) -> 1 | T19: =SUM(S19*$T$2) -> 0 | U19: =SUM(G19+L19+S19) -> 1 | V19: =R19+N19+I19:I19 -> 157 | X19: =X18 -> 2449 | Y19: =X19-X18 -> 0 | Z19: =Z18 -> 137586 | AA19: =Z19-Z18 -> 0 | AB19: =SUM(Y19*$AB$2) -> 0 | AC19: =AC18 -> 1933 | AD19: =AC19-AC18 -> 0 | AE19: =AE18 -> 365212 | AF19: =AE19-AE18 -> 0 | AG19: =IF(AD19>0,AF19/AD19,0) -> 0 | AH19: =AF19+AA19 -> 0 | AI19: =SUM(AH19+V19) -> 157 | AJ19: =-tanks!AW20 -> 157 | AK19: =SUM(AJ19-AI19) -> 0 | AL19: =S19+L19+G19 -> 1 | AM19: =Y19+AD19 -> 0 | AN19: =AN18 -> 67 | AO19: =(AN19/100)*3000 -> 2010 | AP19: =AP18 -> 55 | AQ19: =(AP19/100)*3000 -> 1650 | AR19: =AR18 -> 62 | AS19: =(AR19/100)*3000 -> 1860 | AT19: =SUM(AO19+AQ19+AS19) -> 5520 | AU19: =AT18-AT19+AV19 -> 0 | AX19: =IF(AV19>0,AW19,AX18) -> 0.8
A20: =ELEC!C18 -> 44151 | B20: 248 | C20: 254 | D20: =C19-C20 -> -36.7 | E20: =D20*8.38 -> -307.546 | F20: =F19 -> 1660 | G20: =F20-F19 -> 0 | H20: =H19 -> 357869 | I20: =SUM(H20-H19) -> 0 | J20: =IF(G20>0,I20/G20,0) -> 0 | K20: =K19 -> 2148 | L20: =K20-K19 -> 0 | M20: =M19 -> 157707 | N20: =M20-M19 -> 0 | O20: =O19 -> 1869 | P20: 1871 | Q20: 158993 | R20: =Q20-Q19 -> 137 | S20: =SUM(P20-P19) -> 1 | T20: =SUM(S20*$T$2) -> 0 | U20: =SUM(G20+L20+S20) -> 1 | V20: =R20+N20+I20:I20 -> 137 | X20: =X19 -> 2449 | Y20: =X20-X19 -> 0 | Z20: =Z19 -> 137586 | AA20: =Z20-Z19 -> 0 | AB20: =SUM(Y20*$AB$2) -> 0 | AC20: =AC19 -> 1933 | AD20: =AC20-AC19 -> 0 | AE20: =AE19 -> 365212 | AF20: =AE20-AE19 -> 0 | AG20: =IF(AD20>0,AF20/AD20,0) -> 0 | AH20: =AF20+AA20 -> 0 | AI20: =SUM(AH20+V20) -> 137 | AJ20: =-tanks!AW21 -> 137 | AK20: =SUM(AJ20-AI20) -> 0 | AL20: =S20+L20+G20 -> 1 | AM20: =Y20+AD20 -> 0 | AN20: =AN19 -> 67 | AO20: =(AN20/100)*3000 -> 2010 | AP20: =AP19 -> 55 | AQ20: =(AP20/100)*3000 -> 1650 | AR20: =AR19 -> 62 | AS20: =(AR20/100)*3000 -> 1860 | AT20: =SUM(AO20+AQ20+AS20) -> 5520 | AU20: =AT19-AT20+AV20 -> 0 | AX20: =IF(AV20>0,AW20,AX19) -> 0.8
A21: =ELEC!C19 -> 44152 | B21: 246 | C21: 252 | D21: =C20-C21 -> 2 | E21: =D21*8.38 -> 16.76 | F21: =F20 -> 1660 | G21: =F21-F20 -> 0 | H21: =H20 -> 357869 | I21: =SUM(H21-H20) -> 0 | J21: =IF(G21>0,I21/G21,0) -> 0 | K21: =K20 -> 2148 | L21: =K21-K20 -> 0 | M21: =M20 -> 157707 | N21: =M21-M20 -> 0 | O21: =O20 -> 1869 | P21: 1872 | Q21: 159153 | R21: =Q21-Q20 -> 160 | S21: =SUM(P21-P20) -> 1 | T21: =SUM(S21*$T$2) -> 0 | U21: =SUM(G21+L21+S21) -> 1 | V21: =R21+N21+I21:I21 -> 160 | X21: =X20 -> 2449 | Y21: =X21-X20 -> 0 | Z21: =Z20 -> 137586 | AA21: =Z21-Z20 -> 0 | AB21: =SUM(Y21*$AB$2) -> 0 | AC21: =AC20 -> 1933 | AD21: =AC21-AC20 -> 0 | AE21: =AE20 -> 365212 | AF21: =AE21-AE20 -> 0 | AG21: =IF(AD21>0,AF21/AD21,0) -> 0 | AH21: =AF21+AA21 -> 0 | AI21: =SUM(AH21+V21) -> 160 | AJ21: =-tanks!AW22 -> 160 | AK21: =SUM(AJ21-AI21) -> 0 | AL21: =S21+L21+G21 -> 1 | AM21: =Y21+AD21 -> 0 | AN21: =AN20 -> 67 | AO21: =(AN21/100)*3000 -> 2010 | AP21: =AP20 -> 55 | AQ21: =(AP21/100)*3000 -> 1650 | AR21: =AR20 -> 62 | AS21: =(AR21/100)*3000 -> 1860 | AT21: =SUM(AO21+AQ21+AS21) -> 5520 | AU21: =AT20-AT21+AV21 -> 0 | AX21: =IF(AV21>0,AW21,AX20) -> 0.8
A22: =ELEC!C20 -> 44153 | B22: 244 | C22: 250 | D22: =C21-C22 -> 2 | E22: =D22*8.38 -> 16.76 | F22: =F21 -> 1660 | G22: =F22-F21 -> 0 | H22: =H21 -> 357869 | I22: =SUM(H22-H21) -> 0 | J22: =IF(G22>0,I22/G22,0) -> 0 | K22: =K21 -> 2148 | L22: =K22-K21 -> 0 | M22: =M21 -> 157707 | N22: =M22-M21 -> 0 | O22: =O21 -> 1869 | P22: 1875 | Q22: 159367 | R22: =Q22-Q21 -> 214 | S22: =SUM(P22-P21) -> 3 | T22: =SUM(S22*$T$2) -> 0 | U22: =SUM(G22+L22+S22) -> 3 | V22: =R22+N22+I22:I22 -> 214 | X22: =X21 -> 2449 | Y22: =X22-X21 -> 0 | Z22: =Z21 -> 137586 | AA22: =Z22-Z21 -> 0 | AB22: =SUM(Y22*$AB$2) -> 0 | AC22: =AC21 -> 1933 | AD22: =AC22-AC21 -> 0 | AE22: =AE21 -> 365212 | AF22: =AE22-AE21 -> 0 | AG22: =IF(AD22>0,AF22/AD22,0) -> 0 | AH22: =AF22+AA22 -> 0 | AI22: =SUM(AH22+V22) -> 214 | AJ22: =-tanks!AW23 -> 214 | AK22: =SUM(AJ22-AI22) -> 0 | AL22: =S22+L22+G22 -> 3 | AM22: =Y22+AD22 -> 0 | AN22: =AN21 -> 67 | AO22: =(AN22/100)*3000 -> 2010 | AP22: =AP21 -> 55 | AQ22: =(AP22/100)*3000 -> 1650 | AR22: =AR21 -> 62 | AS22: =(AR22/100)*3000 -> 1860 | AT22: =SUM(AO22+AQ22+AS22) -> 5520 | AU22: =AT21-AT22+AV22 -> 0 | AX22: =IF(AV22>0,AW22,AX21) -> 0.8
A23: =ELEC!C21 -> 44154 | B23: 243 | C23: 249 | D23: =C22-C23 -> 1 | E23: =D23*8.38 -> 8.38 | F23: =F22 -> 1660 | G23: =F23-F22 -> 0 | H23: =H22 -> 357869 | I23: =SUM(H23-H22) -> 0 | J23: =IF(G23>0,I23/G23,0) -> 0 | K23: =K22 -> 2148 | L23: =K23-K22 -> 0 | M23: =M22 -> 157707 | N23: =M23-M22 -> 0 | O23: =O22 -> 1869 | P23: 1876 | Q23: 159480 | R23: =Q23-Q22 -> 113 | S23: =SUM(P23-P22) -> 1 | T23: =SUM(S23*$T$2) -> 0 | U23: =SUM(G23+L23+S23) -> 1 | V23: =R23+N23+I23:I23 -> 113 | X23: =X22 -> 2449 | Y23: =X23-X22 -> 0 | Z23: =Z22 -> 137586 | AA23: =Z23-Z22 -> 0 | AB23: =SUM(Y23*$AB$2) -> 0 | AC23: =AC22 -> 1933 | AD23: =AC23-AC22 -> 0 | AE23: =AE22 -> 365212 | AF23: =AE23-AE22 -> 0 | AG23: =IF(AD23>0,AF23/AD23,0) -> 0 | AH23: =AF23+AA23 -> 0 | AI23: =SUM(AH23+V23) -> 113 | AJ23: =-tanks!AW24 -> 113 | AK23: =SUM(AJ23-AI23) -> 0 | AL23: =S23+L23+G23 -> 1 | AM23: =Y23+AD23 -> 0 | AN23: =AN22 -> 67 | AO23: =(AN23/100)*3000 -> 2010 | AP23: =AP22 -> 55 | AQ23: =(AP23/100)*3000 -> 1650 | AR23: =AR22 -> 62 | AS23: =(AR23/100)*3000 -> 1860 | AT23: =SUM(AO23+AQ23+AS23) -> 5520 | AU23: =AT22-AT23+AV23 -> 0 | AX23: =IF(AV23>0,AW23,AX22) -> 0.8
A24: =ELEC!C22 -> 44155 | B24: 239 | C24: 245 | D24: =C23-C24 -> 4 | E24: =D24*8.38 -> 33.52 | F24: 1660 | G24: =F24-F23 -> 0 | H24: =H23 -> 357869 | I24: =SUM(H24-H23) -> 0 | J24: =IF(G24>0,I24/G24,0) -> 0 | K24: =K23 -> 2148 | L24: =K24-K23 -> 0 | M24: =M23 -> 157707 | N24: =M24-M23 -> 0 | O24: =O23 -> 1869 | P24: 1879 | Q24: 159675 | R24: =Q24-Q23 -> 195 | S24: =SUM(P24-P23) -> 3 | T24: =SUM(S24*$T$2) -> 0 | U24: =SUM(G24+L24+S24) -> 3 | V24: =R24+N24+I24:I24 -> 195 | X24: =X23 -> 2449 | Y24: =X24-X23 -> 0 | Z24: =Z23 -> 137586 | AA24: =Z24-Z23 -> 0 | AB24: =SUM(Y24*$AB$2) -> 0 | AC24: =AC23 -> 1933 | AD24: =AC24-AC23 -> 0 | AE24: 365262 | AF24: =AE24-AE23 -> 50 | AG24: =IF(AD24>0,AF24/AD24,0) -> 0 | AH24: =AF24+AA24 -> 50 | AI24: =SUM(AH24+V24) -> 245 | AJ24: =-tanks!AW25 -> 245 | AK24: =SUM(AJ24-AI24) -> 0 | AL24: =S24+L24+G24 -> 3 | AM24: =Y24+AD24 -> 0 | AN24: 68 | AO24: =(AN24/100)*3000 -> 2040 | AP24: =AP23 -> 55 | AQ24: =(AP24/100)*3000 -> 1650 | AR24: =AR23 -> 62 | AS24: =(AR24/100)*3000 -> 1860 | AT24: =SUM(AO24+AQ24+AS24) -> 5550 | AU24: =AT23-AT24+AV24 -> -30 | AX24: =IF(AV24>0,AW24,AX23) -> 0.8
A25: =ELEC!C23 -> 44156 | B25: 238 | C25: 244 | D25: =C24-C25 -> 1 | E25: =D25*8.38 -> 8.38 | F25: =F24 -> 1660 | G25: =F25-F24 -> 0 | H25: =H24 -> 357869 | I25: =SUM(H25-H24) -> 0 | J25: =IF(G25>0,I25/G25,0) -> 0 | K25: =K24 -> 2148 | L25: =K25-K24 -> 0 | M25: =M24 -> 157707 | N25: =M25-M24 -> 0 | O25: =O24 -> 1869 | P25: 1880 | Q25: 159812 | R25: =Q25-Q24 -> 137 | S25: =SUM(P25-P24) -> 1 | T25: =SUM(S25*$T$2) -> 0 | U25: =SUM(G25+L25+S25) -> 1 | V25: =R25+N25+I25:I25 -> 137 | X25: =X24 -> 2449 | Y25: =X25-X24 -> 0 | Z25: =Z24 -> 137586 | AA25: =Z25-Z24 -> 0 | AB25: =SUM(Y25*$AB$2) -> 0 | AC25: =AC24 -> 1933 | AD25: =AC25-AC24 -> 0 | AE25: =AE24 -> 365262 | AF25: =AE25-AE24 -> 0 | AG25: =IF(AD25>0,AF25/AD25,0) -> 0 | AH25: =AF25+AA25 -> 0 | AI25: =SUM(AH25+V25) -> 137 | AJ25: =-tanks!AW26 -> 137 | AK25: =SUM(AJ25-AI25) -> 0 | AL25: =S25+L25+G25 -> 1 | AM25: =Y25+AD25 -> 0 | AN25: =AN24 -> 68 | AO25: =(AN25/100)*3000 -> 2040 | AP25: =AP24 -> 55 | AQ25: =(AP25/100)*3000 -> 1650 | AR25: =AR24 -> 62 | AS25: =(AR25/100)*3000 -> 1860 | AT25: =SUM(AO25+AQ25+AS25) -> 5550 | AU25: =AT24-AT25+AV25 -> 0 | AX25: =IF(AV25>0,AW25,AX24) -> 0.8
A26: =ELEC!C24 -> 44157 | B26: 237 | C26: 243 | D26: =C25-C26 -> 1 | E26: =D26*8.38 -> 8.38 | F26: =F25 -> 1660 | G26: =F26-F25 -> 0 | H26: =H25 -> 357869 | I26: =SUM(H26-H25) -> 0 | J26: =IF(G26>0,I26/G26,0) -> 0 | K26: 2151 | L26: =K26-K25 -> 3 | M26: 157944 | N26: =M26-M25 -> 237 | O26: =O25 -> 1869 | P26: =P25 -> 1880 | Q26: =Q25 -> 159812 | R26: =Q26-Q25 -> 0 | S26: =SUM(P26-P25) -> 0 | T26: =SUM(S26*$T$2) -> 0 | U26: =SUM(G26+L26+S26) -> 3 | V26: =R26+N26+I26:I26 -> 237 | X26: =X25 -> 2449 | Y26: =X26-X25 -> 0 | Z26: =Z25 -> 137586 | AA26: =Z26-Z25 -> 0 | AB26: =SUM(Y26*$AB$2) -> 0 | AC26: =AC25 -> 1933 | AD26: =AC26-AC25 -> 0 | AE26: =AE25 -> 365262 | AF26: =AE26-AE25 -> 0 | AG26: =IF(AD26>0,AF26/AD26,0) -> 0 | AH26: =AF26+AA26 -> 0 | AI26: =SUM(AH26+V26) -> 237 | AJ26: =-tanks!AW27 -> 237 | AK26: =SUM(AJ26-AI26) -> 0 | AL26: =S26+L26+G26 -> 3 | AM26: =Y26+AD26 -> 0 | AN26: =AN25 -> 68 | AO26: =(AN26/100)*3000 -> 2040 | AP26: =AP25 -> 55 | AQ26: =(AP26/100)*3000 -> 1650 | AR26: =AR25 -> 62 | AS26: =(AR26/100)*3000 -> 1860 | AT26: =SUM(AO26+AQ26+AS26) -> 5550 | AU26: =AT25-AT26+AV26 -> 0 | AX26: =IF(AV26>0,AW26,AX25) -> 0.8
A27: =ELEC!C25 -> 44158 | B27: 235 | C27: 241 | D27: =C26-C27 -> 2 | E27: =D27*8.38 -> 16.76 | F27: =F26 -> 1660 | G27: =F27-F26 -> 0 | H27: =H26 -> 357869 | I27: =SUM(H27-H26) -> 0 | J27: =IF(G27>0,I27/G27,0) -> 0 | K27: 2153 | L27: =K27-K26 -> 2 | M27: 158099 | N27: =M27-M26 -> 155 | O27: =O26 -> 1869 | P27: =P26 -> 1880 | Q27: =Q26 -> 159812 | R27: =Q27-Q26 -> 0 | S27: =SUM(P27-P26) -> 0 | T27: =SUM(S27*$T$2) -> 0 | U27: =SUM(G27+L27+S27) -> 2 | V27: =R27+N27+I27:I27 -> 155 | X27: =X26 -> 2449 | Y27: =X27-X26 -> 0 | Z27: =Z26 -> 137586 | AA27: =Z27-Z26 -> 0 | AB27: =SUM(Y27*$AB$2) -> 0 | AC27: =AC26 -> 1933 | AD27: =AC27-AC26 -> 0 | AE27: =AE26 -> 365262 | AF27: =AE27-AE26 -> 0 | AG27: =IF(AD27>0,AF27/AD27,0) -> 0 | AH27: =AF27+AA27 -> 0 | AI27: =SUM(AH27+V27) -> 155 | AJ27: =-tanks!AW28 -> 155 | AK27: =SUM(AJ27-AI27) -> 0 | AL27: =S27+L27+G27 -> 2 | AM27: =Y27+AD27 -> 0 | AN27: =AN26 -> 68 | AO27: =(AN27/100)*3000 -> 2040 | AP27: =AP26 -> 55 | AQ27: =(AP27/100)*3000 -> 1650 | AR27: =AR26 -> 62 | AS27: =(AR27/100)*3000 -> 1860 | AT27: =SUM(AO27+AQ27+AS27) -> 5550 | AU27: =AT26-AT27+AV27 -> 0 | AX27: =IF(AV27>0,AW27,AX26) -> 0.8
A28: =ELEC!C26 -> 44159 | B28: 232 | C28: 238 | D28: =C27-C28 -> 3 | E28: =D28*8.38 -> 25.14 | F28: =F27 -> 1660 | G28: =F28-F27 -> 0 | H28: =H27 -> 357869 | I28: =SUM(H28-H27) -> 0 | J28: =IF(G28>0,I28/G28,0) -> 0 | K28: 2154 | L28: =K28-K27 -> 1 | M28: 158183 | N28: =M28-M27 -> 84 | O28: =O27 -> 1869 | P28: 1882 | Q28: 159910 | R28: =Q28-Q27 -> 98 | S28: =SUM(P28-P27) -> 2 | T28: =SUM(S28*$T$2) -> 0 | U28: =SUM(G28+L28+S28) -> 3 | V28: =R28+N28+I28:I28 -> 182 | X28: =X27 -> 2449 | Y28: =X28-X27 -> 0 | Z28: =Z27 -> 137586 | AA28: =Z28-Z27 -> 0 | AB28: =SUM(Y28*$AB$2) -> 0 | AC28: =AC27 -> 1933 | AD28: =AC28-AC27 -> 0 | AE28: =AE27 -> 365262 | AF28: =AE28-AE27 -> 0 | AG28: =IF(AD28>0,AF28/AD28,0) -> 0 | AH28: =AF28+AA28 -> 0 | AI28: =SUM(AH28+V28) -> 182 | AJ28: =-tanks!AW29 -> 182 | AK28: =SUM(AJ28-AI28) -> 0 | AL28: =S28+L28+G28 -> 3 | AM28: =Y28+AD28 -> 0 | AN28: =AN27 -> 68 | AO28: =(AN28/100)*3000 -> 2040 | AP28: =AP27 -> 55 | AQ28: =(AP28/100)*3000 -> 1650 | AR28: =AR27 -> 62 | AS28: =(AR28/100)*3000 -> 1860 | AT28: =SUM(AO28+AQ28+AS28) -> 5550 | AU28: =AT27-AT28+AV28 -> 0 | AX28: =IF(AV28>0,AW28,AX27) -> 0.8
A29: =ELEC!C27 -> 44160 | B29: 230 | C29: 235 | D29: =C28-C29 -> 3 | E29: =D29*8.38 -> 25.14 | F29: =F28 -> 1660 | G29: =F29-F28 -> 0 | H29: =H28 -> 357869 | I29: =SUM(H29-H28) -> 0 | J29: =IF(G29>0,I29/G29,0) -> 0 | K29: =K28 -> 2154 | L29: =K29-K28 -> 0 | M29: =M28 -> 158183 | N29: =M29-M28 -> 0 | O29: =O28 -> 1869 | P29: 1884 | Q29: 160066 | R29: =Q29-Q28 -> 156 | S29: =SUM(P29-P28) -> 2 | T29: =SUM(S29*$T$2) -> 0 | U29: =SUM(G29+L29+S29) -> 2 | V29: =R29+N29+I29:I29 -> 156 | X29: =X28 -> 2449 | Y29: =X29-X28 -> 0 | Z29: =Z28 -> 137586 | AA29: =Z29-Z28 -> 0 | AB29: =SUM(Y29*$AB$2) -> 0 | AC29: =AC28 -> 1933 | AD29: =AC29-AC28 -> 0 | AE29: =AE28 -> 365262 | AF29: =AE29-AE28 -> 0 | AG29: =IF(AD29>0,AF29/AD29,0) -> 0 | AH29: =AF29+AA29 -> 0 | AI29: =SUM(AH29+V29) -> 156 | AJ29: =-tanks!AW30 -> 156 | AK29: =SUM(AJ29-AI29) -> 0 | AL29: =S29+L29+G29 -> 2 | AM29: =Y29+AD29 -> 0 | AN29: =AN28 -> 68 | AO29: =(AN29/100)*3000 -> 2040 | AP29: =AP28 -> 55 | AQ29: =(AP29/100)*3000 -> 1650 | AR29: =AR28 -> 62 | AS29: =(AR29/100)*3000 -> 1860 | AT29: =SUM(AO29+AQ29+AS29) -> 5550 | AU29: =AT28-AT29+AV29 -> 0 | AX29: =IF(AV29>0,AW29,AX28) -> 0.8
A30: =ELEC!C28 -> 44161 | B30: 229 | C30: 234.1 | D30: =C29-C30 -> 0.9 | E30: =D30*8.38 -> 7.542 | F30: =F29 -> 1660 | G30: =F30-F29 -> 0 | H30: =H29 -> 357869 | I30: =SUM(H30-H29) -> 0 | J30: =IF(G30>0,I30/G30,0) -> 0 | K30: =K29 -> 2154 | L30: =K30-K29 -> 0 | M30: =M29 -> 158183 | N30: =M30-M29 -> 0 | O30: =O29 -> 1869 | P30: 1885 | Q30: 160163 | R30: =Q30-Q29 -> 97 | S30: =SUM(P30-P29) -> 1 | T30: =SUM(S30*$T$2) -> 0 | U30: =SUM(G30+L30+S30) -> 1 | V30: =R30+N30+I30:I30 -> 97 | X30: =X29 -> 2449 | Y30: =X30-X29 -> 0 | Z30: =Z29 -> 137586 | AA30: =Z30-Z29 -> 0 | AB30: =SUM(Y30*$AB$2) -> 0 | AC30: =AC29 -> 1933 | AD30: =AC30-AC29 -> 0 | AE30: =AE29 -> 365262 | AF30: =AE30-AE29 -> 0 | AG30: =IF(AD30>0,AF30/AD30,0) -> 0 | AH30: =AF30+AA30 -> 0 | AI30: =SUM(AH30+V30) -> 97 | AJ30: =-tanks!AW31 -> 97 | AK30: =SUM(AJ30-AI30) -> 0 | AL30: =S30+L30+G30 -> 1 | AM30: =Y30+AD30 -> 0 | AN30: =AN29 -> 68 | AO30: =(AN30/100)*3000 -> 2040 | AP30: =AP29 -> 55 | AQ30: =(AP30/100)*3000 -> 1650 | AR30: =AR29 -> 62 | AS30: =(AR30/100)*3000 -> 1860 | AT30: =SUM(AO30+AQ30+AS30) -> 5550 | AU30: =AT29-AT30+AV30 -> 0 | AX30: =IF(AV30>0,AW30,AX29) -> 0.8
A31: =ELEC!C29 -> 44162 | B31: =B30 -> 229 | C31: =C30 -> 234.1 | D31: =C30-C31 -> 0 | E31: =D31*8.38 -> 0 | F31: =F30 -> 1660 | G31: =F31-F30 -> 0 | H31: =H30 -> 357869 | I31: =SUM(H31-H30) -> 0 | J31: =IF(G31>0,I31/G31,0) -> 0 | K31: =K30 -> 2154 | L31: =K31-K30 -> 0 | M31: =M30 -> 158183 | N31: =M31-M30 -> 0 | O31: =O30 -> 1869 | P31: =P30 -> 1885 | Q31: =Q30 -> 160163 | R31: =Q31-Q30 -> 0 | S31: =SUM(P31-P30) -> 0 | T31: =SUM(S31*$T$2) -> 0 | U31: =SUM(G31+L31+S31) -> 0 | V31: =R31+N31+I31:I31 -> 0 | X31: =X30 -> 2449 | Y31: =X31-X30 -> 0 | Z31: =Z30 -> 137586 | AA31: =Z31-Z30 -> 0 | AB31: =SUM(Y31*$AB$2) -> 0 | AC31: =AC30 -> 1933 | AD31: =AC31-AC30 -> 0 | AE31: =AE30 -> 365262 | AF31: =AE31-AE30 -> 0 | AG31: =IF(AD31>0,AF31/AD31,0) -> 0 | AH31: =AF31+AA31 -> 0 | AI31: =SUM(AH31+V31) -> 0 | AJ31: =-tanks!AW32 -> 0 | AK31: =SUM(AJ31-AI31) -> 0 | AL31: =S31+L31+G31 -> 0 | AM31: =Y31+AD31 -> 0 | AN31: =AN30 -> 68 | AO31: =(AN31/100)*3000 -> 2040 | AP31: =AP30 -> 55 | AQ31: =(AP31/100)*3000 -> 1650 | AR31: =AR30 -> 62 | AS31: =(AR31/100)*3000 -> 1860 | AT31: =SUM(AO31+AQ31+AS31) -> 5550 | AU31: =AT30-AT31+AV31 -> 0 | AX31: =IF(AV31>0,AW31,AX30) -> 0.8
A32: =ELEC!C30 -> 44163 | B32: =B31 -> 229 | C32: =C31 -> 234.1 | D32: =C31-C32 -> 0 | E32: =D32*8.38 -> 0 | F32: =F31 -> 1660 | G32: =F32-F31 -> 0 | H32: =H31 -> 357869 | I32: =SUM(H32-H31) -> 0 | J32: =IF(G32>0,I32/G32,0) -> 0 | K32: =K31 -> 2154 | L32: =K32-K31 -> 0 | M32: =M31 -> 158183 | N32: =M32-M31 -> 0 | O32: =O31 -> 1869 | P32: =P31 -> 1885 | Q32: =Q31 -> 160163 | R32: =Q32-Q31 -> 0 | S32: =SUM(P32-P31) -> 0 | T32: =SUM(S32*$T$2) -> 0 | U32: =SUM(G32+L32+S32) -> 0 | V32: =R32+N32+I32:I32 -> 0 | X32: =X31 -> 2449 | Y32: =X32-X31 -> 0 | Z32: =Z31 -> 137586 | AA32: =Z32-Z31 -> 0 | AB32: =SUM(Y32*$AB$2) -> 0 | AC32: =AC31 -> 1933 | AD32: =AC32-AC31 -> 0 | AE32: =AE31 -> 365262 | AF32: =AE32-AE31 -> 0 | AG32: =IF(AD32>0,AF32/AD32,0) -> 0 | AH32: =AF32+AA32 -> 0 | AI32: =SUM(AH32+V32) -> 0 | AJ32: =-tanks!AW33 -> 0 | AK32: =SUM(AJ32-AI32) -> 0 | AL32: =S32+L32+G32 -> 0 | AM32: =Y32+AD32 -> 0 | AN32: =AN31 -> 68 | AO32: =(AN32/100)*3000 -> 2040 | AP32: =AP31 -> 55 | AQ32: =(AP32/100)*3000 -> 1650 | AR32: =AR31 -> 62 | AS32: =(AR32/100)*3000 -> 1860 | AT32: =SUM(AO32+AQ32+AS32) -> 5550 | AU32: =AT31-AT32+AV32 -> 0 | AX32: =IF(AV32>0,AW32,AX31) -> 0.8
A33: =ELEC!C31 -> 44164 | B33: =B32 -> 229 | C33: =C32 -> 234.1 | D33: =C32-C33 -> 0 | E33: =D33*8.38 -> 0 | F33: =F32 -> 1660 | G33: =F33-F32 -> 0 | H33: =H32 -> 357869 | I33: =SUM(H33-H32) -> 0 | J33: =IF(G33>0,I33/G33,0) -> 0 | K33: =K32 -> 2154 | L33: =K33-K32 -> 0 | M33: =M32 -> 158183 | N33: =M33-M32 -> 0 | O33: =O32 -> 1869 | P33: =P32 -> 1885 | Q33: =Q32 -> 160163 | R33: =Q33-Q32 -> 0 | S33: =SUM(P33-P32) -> 0 | T33: =SUM(S33*$T$2) -> 0 | U33: =SUM(G33+L33+S33) -> 0 | V33: =R33+N33+I33:I33 -> 0 | X33: =X32 -> 2449 | Y33: =X33-X32 -> 0 | Z33: =Z32 -> 137586 | AA33: =Z33-Z32 -> 0 | AB33: =SUM(Y33*$AB$2) -> 0 | AC33: =AC32 -> 1933 | AD33: =AC33-AC32 -> 0 | AE33: =AE32 -> 365262 | AF33: =AE33-AE32 -> 0 | AG33: =IF(AD33>0,AF33/AD33,0) -> 0 | AH33: =AF33+AA33 -> 0 | AI33: =SUM(AH33+V33) -> 0 | AJ33: =-tanks!AW34 -> 0 | AK33: =SUM(AJ33-AI33) -> 0 | AL33: =S33+L33+G33 -> 0 | AM33: =Y33+AD33 -> 0 | AN33: =AN32 -> 68 | AO33: =(AN33/100)*3000 -> 2040 | AP33: =AP32 -> 55 | AQ33: =(AP33/100)*3000 -> 1650 | AR33: =AR32 -> 62 | AS33: =(AR33/100)*3000 -> 1860 | AT33: =SUM(AO33+AQ33+AS33) -> 5550 | AU33: =AT32-AT33+AV33 -> 0 | AX33: =IF(AV33>0,AW33,AX32) -> 0.8
A34: =ELEC!C32 -> 44165 | B34: =B33 -> 229 | C34: =C33 -> 234.1 | D34: =C33-C34 -> 0 | E34: =D34*8.38 -> 0 | F34: =F33 -> 1660 | G34: =F34-F33 -> 0 | H34: =H33 -> 357869 | I34: =SUM(H34-H33) -> 0 | J34: =IF(G34>0,I34/G34,0) -> 0 | K34: =K33 -> 2154 | L34: =K34-K33 -> 0 | M34: =M33 -> 158183 | N34: =M34-M33 -> 0 | O34: =O33 -> 1869 | P34: =P33 -> 1885 | Q34: =Q33 -> 160163 | R34: =Q34-Q33 -> 0 | S34: =SUM(P34-P33) -> 0 | T34: =SUM(S34*$T$2) -> 0 | U34: =SUM(G34+L34+S34) -> 0 | V34: =R34+N34+I34:I34 -> 0 | X34: =X33 -> 2449 | Y34: =X34-X33 -> 0 | Z34: =Z33 -> 137586 | AA34: =Z34-Z33 -> 0 | AB34: =SUM(Y34*$AB$2) -> 0 | AC34: =AC33 -> 1933 | AD34: =AC34-AC33 -> 0 | AE34: =AE33 -> 365262 | AF34: =AE34-AE33 -> 0 | AG34: =IF(AD34>0,AF34/AD34,0) -> 0 | AH34: =AF34+AA34 -> 0 | AI34: =SUM(AH34+V34) -> 0 | AJ34: =-tanks!AW35 -> 0 | AK34: =SUM(AJ34-AI34) -> 0 | AL34: =S34+L34+G34 -> 0 | AM34: =Y34+AD34 -> 0 | AN34: =AN33 -> 68 | AO34: =(AN34/100)*3000 -> 2040 | AP34: =AP33 -> 55 | AQ34: =(AP34/100)*3000 -> 1650 | AR34: =AR33 -> 62 | AS34: =(AR34/100)*3000 -> 1860 | AT34: =SUM(AO34+AQ34+AS34) -> 5550 | AU34: =AT33-AT34+AV34 -> 0 | AX34: =IF(AV34>0,AW34,AX33) -> 0.8
A35: =ELEC!C33 -> 44166 | B35: =B34 -> 229 | C35: =C34 -> 234.1 | D35: =C34-C35 -> 0 | E35: =D35*8.38 -> 0 | F35: =F34 -> 1660 | G35: =F35-F34 -> 0 | H35: =H34 -> 357869 | I35: =SUM(H35-H34) -> 0 | J35: =IF(G35>0,I35/G35,0) -> 0 | K35: =K34 -> 2154 | L35: =K35-K34 -> 0 | M35: =M34 -> 158183 | N35: =M35-M34 -> 0 | O35: =O34 -> 1869 | P35: =P34 -> 1885 | Q35: =Q34 -> 160163 | R35: =Q35-Q34 -> 0 | S35: =SUM(P35-P34) -> 0 | T35: =SUM(S35*$T$2) -> 0 | U35: =SUM(G35+L35+S35) -> 0 | V35: =R35+N35+I35:I35 -> 0 | X35: =X34 -> 2449 | Y35: =X35-X34 -> 0 | Z35: =Z34 -> 137586 | AA35: =Z35-Z34 -> 0 | AB35: =SUM(Y35*$AB$2) -> 0 | AC35: =AC34 -> 1933 | AD35: =AC35-AC34 -> 0 | AE35: =AE34 -> 365262 | AF35: =AE35-AE34 -> 0 | AG35: =IF(AD35>0,AF35/AD35,0) -> 0 | AH35: =AF35+AA35 -> 0 | AI35: =SUM(AH35+V35) -> 0 | AJ35: =-tanks!AW36 -> 0 | AK35: =SUM(AJ35-AI35) -> 0 | AL35: =S35+L35+G35 -> 0 | AM35: =Y35+AD35 -> 0 | AN35: =AN34 -> 68 | AO35: =(AN35/100)*3000 -> 2040 | AP35: =AP34 -> 55 | AQ35: =(AP35/100)*3000 -> 1650 | AR35: =AR34 -> 62 | AS35: =(AR35/100)*3000 -> 1860 | AT35: =SUM(AO35+AQ35+AS35) -> 5550 | AU35: =AT34-AT35+AV35 -> 0 | AX35: =IF(AV35>0,AW35,AX34) -> 0.8
J36: =SUM(J5:J34)/(COUNT(J5:J34)-COUNTIF(J5:J34,0)) -> 0.75 | V36: =SUM(V5:V35) -> 3548 | AE36: . | AH36: =SUM(AH5:AH35) -> 130 | AL36: =SUM(AL5:AL35) -> 52 | AM36: =SUM(AM5:AM35) -> 1 | AR36: Nb Delivery | AS36: =COUNT(AW5:AW34) -> 0 | AU36: =SUM(AU5:AU34) -> -90 | AV36: =SUM(AV5:AV34) -> 0 | AW36: =SUM(AW5:AW34)/AS36 -> #DIV/0!
AH37: =AF37+AA37 -> 0 | AI37: =SUM(AI5:AI34) -> 3678
AH38: =AF38+AA38 -> 0 | AU38: =AU36*0.51 -> -45.9 | AV38: =AV36/0.51 -> 0 | AW38: =SUM(AW5:AW34)/AS36 -> #DIV/0!
AV39: =AV36*0.51 -> 0

Sheet WATER
D1: =SUM(G21:G35) -> 9184028 | AR1: Entrance | AT1: Tank 1 | AV1: Tank 2
AR2: Level | AW2: Quantity CM3 | AZ2: Var
A3: Date | B3: Truck | C3: Truck M3/day | D3: N0. Trucks | F3: REQ. # of trucks | G3: City | H3: City/day | I3: Total water delivery | K3: SW | L3: Cosum SW/day | M3: RO Guest/ Liter | O3: RO K&L/ Liter | Q3: TOTAL RO Production | R3: RO 1 RH | S3: RO 2 RH | T3: RO water counter | U3: RO Cons m3 | V3: Steam Boiler | W3: Steam Boiler/day | X3: Softener Guest | Y3: Guest Sotf/day | Z3: Softener K&L | AA3: K&L Soft/Day | AB3: Fire Tank Level | AC3: Fire Tank Counter | AE3: Laundry Hot Water Counter | AF3: Hot Water Cons/day | AG3: Laundry Cold Water Counter | AH3: Cold Water Cons/day | AI3: Laundry Water Total Cons | AJ3: K&L Sotf/day | AK3: Guest / day | AL3: K&L /day | AM3: Avg Outside Temp | AN3: Banquet Activity | AR3: Date | AT3: MainI | AV3: Kitchen and Laundry | AX3: Guest | AY3: Main Tank | AZ3: Kitchen and Laundry | BA3: Guest | BB3: Kitchen and Laundry | BC3: Main | BD3: Guest | BE3: Total VAR | BF3: Hotel Consumption
E4: 1.66 | AN4: Ball R | AO4: Meeting | AP4: outlet | AT4: 180 | AV4: 220 | AX4: 580 | AY4: =SUM(AT4) -> 180 | AZ4: =SUM(AV4) -> 220 | BA4: =SUM(AX4) -> 580
A5: 44135 | B5: =[1]WATER!B36 -> 109317 | C5: =[1]WATER!C36 -> 0 | D5: =[1]WATER!D36 -> 0 | E5: =[1]WATER!E36 -> 241.93548 | F5: =[1]WATER!F36 -> 0 | G5: =[1]WATER!G36 -> 610471 | H5: =[1]WATER!H36 -> 0 | I5: =[1]WATER!I36 -> 0 | ... BG5: =[1]WATER!BG36 -> -41.4
A6: =ELEC!C3 -> 44136 | B6: 109317 | C6: =B6-B5 -> 0 | D6: =C6/27 -> 0 | E6: =SUM((C6*$E$4)+(7500/'EDl log'!$A$37)) -> 250 | G6: 610608 | H6: =G6-G5 -> 137 | I6: =C6+H6 -> 137 | J6: =IF(I6>0,E6/I6,0) -> 1.8248175 | K6: ='Swimming Pool quality check '!H6 -> 6681 | L6: 0 | M6: =M5 -> 457.44 | N6: =SUM(M6-M5) -> 0 | O6: =O5 -> 529.52 | P6: =SUM(O6-O5) -> 0 | Q6: =P6+N6 -> 0 | T6: 5159 | U6: =SUM(T6-T5) -> 0 | V6: 452 | W6: =+V6-V5 -> 0 | X6: 148482 | Y6: =SUM(X6-X5) -> 104 | Z6: 97407 | AA6: =Z6-Z5 -> 0 | AB6: 260 | AC6: 698 | AD6: 0 | AE6: 227.8 | AF6: =AE6-AE5 -> 0 | AG6: 2181.28 | AH6: =AG6-AG5 -> 0 | AI6: =AF6+AH6 -> 0 | AJ6: =+Z6-Z5 -> 0 | AK6: =SUM(Y6-L6) -> 104 | AL6: =SUM(AJ6-W6) -> 0 | AM6: ='General information '!D6 -> 23 | AN6: ='General information '!H6 -> 0 | AP6: ='General information '!J6 -> 0 | AR6: =A6 -> 44136 | AS6: =AS5 -> 0.9 | AT6: 24 | AU6: =AU5 -> 1.1 | AV6: 28 | AW6: 2.9 | AX6: 22 | AY6: =AS6*AT6 -> 21.6 | AZ6: =AU6*AV6 -> 30.8 | BA6: =AW6*AX6 -> 63.8 | BB6: =AY6-AY5 -> 12.6 | BC6: =AZ6-AZ5 -> -6.6 | BD6: =BA6-BA5 -> -14.5 | BE6: =SUM(BB6:BD6) -> -8.5 | BF6: =SUM(I6-BE6) -> 145.5 | BG6: =SUM(I6-BF6) -> -8.5
A7: =ELEC!C4 -> 44137 | B7: =B6 -> 109317 | C7: =B7-B6 -> 0 | D7: =C7/27 -> 0 | E7: =SUM((C7*$E$4)+(7500/'EDl log'!$A$37)) -> 250 | G7: =G6 -> 610608 | H7: =G7-G6 -> 0 | I7: =C7+H7 -> 0 | J7: =IF(I7>0,E7/I7,0) -> 0 | K7: ='Swimming Pool quality check '!H7 -> 6684 | L7: =K7-K6 -> 3 | M7: =M6 -> 457.44 | N7: =SUM(M7-M6) -> 0 | O7: =O6 -> 529.52 | P7: =SUM(O7-O6) -> 0 | Q7: =P7+N7 -> 0 | T7: =T6 -> 5159 | U7: =SUM(T7-T6) -> 0 | V7: =V6 -> 452 | W7: =+V7-V6 -> 0 | X7: =X6 -> 148482 | Y7: =SUM(X7-X6) -> 0 | Z7: =Z6 -> 97407 | AA7: =Z7-Z6 -> 0 | AB7: =AB6 -> 260 | AC7: =AC6 -> 698 | AD7: =AC7-AC6 -> 0 | AE7: =AE6 -> 227.8 | AF7: =AE7-AE6 -> 0 | AG7: =AG6 -> 2181.28 | AH7: =AG7-AG6 -> 0 | AI7: =AF7+AH7 -> 0 | AJ7: =+Z7-Z6 -> 0 | AK7: =SUM(Y7-L7) -> -3 | AL7: =SUM(AJ7-W7) -> 0 | AM7: ='General information '!D7 -> 23.5 | AN7: ='General information '!H7 -> 0 | AP7: ='General information '!J7 -> 0 | AR7: =A7 -> 44137 | AS7: =AS6 -> 0.9 | AT7: 0 | AU7: =AU6 -> 1.1 | AV7: 24 | AW7: 2.9 | AX7: 12 | AY7: =AS7*AT7 -> 0 | AZ7: =AU7*AV7 -> 26.4 | BA7: =AW7*AX7 -> 34.8 | BB7: =AY7-AY6 -> -21.6 | BC7: =AZ7-AZ6 -> -4.4 | BD7: =BA7-BA6 -> -29 | BE7: =SUM(BB7:BD7) -> -55 | BF7: =SUM(I7-BE7) -> 55 | BG7: =SUM(I7-BF7) -> -55
A8: =ELEC!C5 -> 44138 | B8: 109443 | C8: =B8-B7 -> 126 | D8: =C8/27 -> 4.6666667 | E8: =SUM((C8*$E$4)+(7500/'EDl log'!$A$37)) -> 459.16 | G8: 610732 | H8: =G8-G7 -> 124 | I8: =C8+H8 -> 250 | J8: =IF(I8>0,E8/I8,0) -> 1.83664 | K8: ='Swimming Pool quality check '!H8 -> 6689 | L8: =K8-K7 -> 5 | M8: =M7 -> 457.44 | N8: =SUM(M8-M7) -> 0 | O8: =O7 -> 529.52 | P8: =SUM(O8-O7) -> 0 | Q8: =P8+N8 -> 0 | T8: =T7 -> 5159 | U8: =SUM(T8-T7) -> 0 | V8: =V7 -> 452 | W8: =+V8-V7 -> 0 | X8: 148583 | Y8: =SUM(X8-X7) -> 101 | Z8: 97417 | AA8: =Z8-Z7 -> 10 | AB8: =AB7 -> 260 | AC8: =AC7 -> 698 | AD8: =AC8-AC7 -> 0 | AE8: =AE7 -> 227.8 | AF8: =AE8-AE7 -> 0 | AG8: =AG7 -> 2181.28 | AH8: =AG8-AG7 -> 0 | AI8: =AF8+AH8 -> 0 | AJ8: =+Z8-Z7 -> 10 | AK8: =SUM(Y8-L8) -> 96 | AL8: =SUM(AJ8-W8) -> 10 | AM8: ='General information '!D8 -> 24 | AN8: ='General information '!H8 -> 0 | AP8: ='General information '!J8 -> 0 | AR8: =A8 -> 44138 | AS8: =AS7 -> 0.9 | AT8: 89 | AU8: 1.1 | AV8: 25 | AW8: 2.9 | AX8: 14 | AY8: =AS8*AT8 -> 80.1 | AZ8: =AU8*AV8 -> 27.5 | BA8: =AW8*AX8 -> 40.6 | BB8: =AY8-AY7 -> 80.1 | BC8: =AZ8-AZ7 -> 1.1 | BD8: =BA8-BA7 -> 5.8 | BE8: =SUM(BB8:BD8) -> 87 | BF8: =SUM(I8-BE8) -> 163 | BG8: =SUM(I8-BF8) -> 87
A9: =ELEC!C6 -> 44139 | B9: 109443 | C9: =B9-B8 -> 0 | D9: =C9/27 -> 0 | E9: =SUM((C9*$E$4)+(7500/'EDl log'!$A$37)) -> 250 | G9: 610732 | H9: =G9-G8 -> 0 | I9: =C9+H9 -> 0 | J9: =IF(I9>0,E9/I9,0) -> 0 | K9: ='Swimming Pool quality check '!H9 -> 6690 | L9: =K9-K8 -> 1 | M9: =M8 -> 457.44 | N9: =SUM(M9-M8) -> 0 | O9: =O8 -> 529.52 | P9: =SUM(O9-O8) -> 0 | Q9: =P9+N9 -> 0 | T9: 5159 | U9: =SUM(T9-T8) -> 0 | V9: =V8 -> 452 | W9: =+V9-V8 -> 0 | X9: 148657 | Y9: =SUM(X9-X8) -> 74 | Z9: =Z8 -> 97417 | AA9: =Z9-Z8 -> 0 | AB9: =AB8 -> 260 | AC9: =AC8 -> 698 | AD9: =AC9-AC8 -> 0 | AE9: =AE8 -> 227.8 | AF9: =AE9-AE8 -> 0 | AG9: =AG8 -> 2181.28 | AH9: =AG9-AG8 -> 0 | AI9: =AF9+AH9 -> 0 | AJ9: =+Z9-Z8 -> 0 | AK9: =SUM(Y9-L9) -> 73 | AL9: =SUM(AJ9-W9) -> 0 | AM9: ='General information '!D9 -> 20.5 | AN9: ='General information '!H9 -> 0 | AP9: ='General information '!J9 -> 0 | AR9: =A9 -> 44139 | AS9: =AS8 -> 0.9 | AT9: 20 | AU9: =AU8 -> 1.1 | AV9: 20 | AW9: 2.9 | AX9: 28 | AY9: =AS9*AT9 -> 18 | AZ9: =AU9*AV9 -> 22 | BA9: =AW9*AX9 -> 81.2 | BB9: =AY9-AY8 -> -62.1 | BC9: =AZ9-AZ8 -> -5.5 | BD9: =BA9-BA8 -> 40.6 | BE9: =SUM(BB9:BD9) -> -27 | BF9: =SUM(I9-BE9) -> 27 | BG9: =SUM(I9-BF9) -> -27
A10: =ELEC!C7 -> 44140 | B10: =B9 -> 109443 | C10: =B10-B9 -> 0 | D10: =C10/27 -> 0 | E10: =SUM((C10*$E$4)+(7500/'EDl log'!$A$37)) -> 250 | G10: 610925 | H10: =G10-G9 -> 193 | I10: =C10+H10 -> 193 | J10: =IF(I10>0,E10/I10,0) -> 1.2953368 | K10: ='Swimming Pool quality check '!H10 -> 6690 | L10: =K10-K9 -> 0 | M10: =M9 -> 457.44 | N10: =SUM(M10-M9) -> 0 | O10: =O9 -> 529.52 | P10: =SUM(O10-O9) -> 0 | Q10: =P10+N10 -> 0 | T10: =T9 -> 5159 | U10: =SUM(T10-T9) -> 0 | V10: =V9 -> 452 | W10: =+V10-V9 -> 0 | X10: =X9 -> 148657 | Y10: =SUM(X10-X9) -> 0 | Z10: 97445 | AA10: =Z10-Z9 -> 28 | AB10: =AB9 -> 260 | AC10: =AC9 -> 698 | AD10: =AC10-AC9 -> 0 | AE10: =AE9 -> 227.8 | AF10: =AE10-AE9 -> 0 | AG10: =AG9 -> 2181.28 | AH10: =AG10-AG9 -> 0 | AI10: =AF10+AH10 -> 0 | AJ10: =+Z10-Z9 -> 28 | AK10: =SUM(Y10-L10) -> 0 | AL10: =SUM(AJ10-W10) -> 28 | AM10: ='General information '!D10 -> 19.5 | AN10: ='General information '!H10 -> 0 | AP10: ='General information '!J10 -> 0 | AR10: =A10 -> 44140 | AS10: =AS9 -> 0.9 | AT10: 80 | AU10: =AU9 -> 1.1 | AV10: 33 | AW10: 2.9 | AX10: 32 | AY10: =AS10*AT10 -> 72 | AZ10: =AU10*AV10 -> 36.3 | BA10: =AW10*AX10 -> 92.8 | BB10: =AY10-AY9 -> 54 | BC10: =AZ10-AZ9 -> 14.3 | BD10: =BA10-BA9 -> 11.6 | BE10: =SUM(BB10:BD10) -> 79.9 | BF10: =SUM(I10-BE10) -> 113.1 | BG10: =SUM(I10-BF10) -> 79.9
A11: =ELEC!C8 -> 44141 | B11: =B10 -> 109443 | C11: =B11-B10 -> 0 | D11: =C11/27 -> 0 | E11: =SUM((C11*$E$4)+(7500/'EDl log'!$A$37)) -> 250 | G11: =G10 -> 610925 | H11: =G11-G10 -> 0 | I11: =C11+H11 -> 0 | J11: =IF(I11>0,E11/I11,0) -> 0 | K11: ='Swimming Pool quality check '!H11 -> 6699 | L11: =K11-K10 -> 9 | M11: =M10 -> 457.44 | N11: =SUM(M11-M10) -> 0 | O11: =O10 -> 529.52 | P11: =SUM(O11-O10) -> 0 | Q11: =SUM(P11+N11) -> 0 | T11: =T10 -> 5159 | U11: =SUM(T11-T10) -> 0 | V11: =V10 -> 452 | W11: =+V11-V10 -> 0 | X11: 148721 | Y11: =SUM(X11-X10) -> 64 | Z11: 97468 | AA11: =Z11-Z10 -> 23 | AB11: =AB10 -> 260 | AC11: =AC10 -> 698 | AD11: =AC11-AC10 -> 0 | AE11: =AE10 -> 227.8 | AF11: =AE11-AE10 -> 0 | AG11: =AG10 -> 2181.28 | AH11: =AG11-AG10 -> 0 | AI11: =AF11+AH11 -> 0 | AJ11: =+Z11-Z10 -> 23 | AK11: =SUM(Y11-L11) -> 55 | AL11: =SUM(AJ11-W11) -> 23 | AM11: ='General information '!D11 -> 20 | AN11: ='General information '!H11 -> 0 | AP11: ='General information '!J11 -> 0 | AR11: =A11 -> 44141 | AS11: =AS10 -> 0.9 | AT11: 23 | AU11: =AU10 -> 1.1 | AV11: 46 | AW11: 2.9 | AX11: 38 | AY11: =AS11*AT11 -> 20.7 | AZ11: =AU11*AV11 -> 50.6 | BA11: =AW11*AX11 -> 110.2 | BB11: =AY11-AY10 -> -51.3 | BC11: =AZ11-AZ10 -> 14.3 | BD11: =BA11-BA10 -> 17.4 | BE11: =SUM(BB11:BD11) -> -19.6 | BF11: =SUM(I11-BE11) -> 19.6 | BG11: =SUM(I11-BF11) -> -19.6
A12: =ELEC!C9 -> 44142 | B12: =B11 -> 109443 | C12: =B12-B11 -> 0 | D12: =C12/27 -> 0 | E12: =SUM((C12*$E$4)+(7500/'EDl log'!$A$37)) -> 250 | G12: 611115 | H12: =G12-G11 -> 190 | I12: =C12+H12 -> 190 | J12: =IF(I12>0,E12/I12,0) -> 1.3157895 | K12: ='Swimming Pool quality check '!H12 -> 6699 | L12: =K12-K11 -> 0 | M12: =M11 -> 457.44 | N12: =SUM(M12-M11) -> 0 | O12: =O11 -> 529.52 | P12: =SUM(O12-O11) -> 0 | Q12: =SUM(P12+N12) -> 0 | T12: =T11 -> 5159 | U12: =SUM(T12-T11) -> 0 | V12: =V11 -> 452 | W12: =+V12-V11 -> 0 | X12: 148761 | Y12: =SUM(X12-X11) -> 40 | Z12: 97468 | AA12: =Z12-Z11 -> 0 | AB12: =AB11 -> 260 | AC12: =AC11 -> 698 | AD12: =AC12-AC11 -> 0 | AE12: =AE11 -> 227.8 | AF12: =AE12-AE11 -> 0 | AG12: =AG11 -> 2181.28 | AH12: =AG12-AG11 -> 0 | AI12: =AF12+AH12 -> 0 | AJ12: =+Z12-Z11 -> 0 | AK12: =SUM(Y12-L12) -> 40 | AL12: =SUM(AJ12-W12) -> 0 | AM12: ='General information '!D12 -> 20.5 | AN12: ='General information '!H12 -> 0 | AP12: ='General information '!J12 -> 0 | AR12: =A12 -> 44142 | AS12: =AS11 -> 0.9 | AT12: 93 | AU12: =AU11 -> 1.1 | AV12: 41 | AW12: 2.9 | AX12: 45 | AY12: =AS12*AT12 -> 83.7 | AZ12: =AU12*AV12 -> 45.1 | BA12: =AW12*AX12 -> 130.5 | BB12: =AY12-AY11 -> 63 | BC12: =AZ12-AZ11 -> -5.5 | BD12: =BA12-BA11 -> 20.3 | BE12: =SUM(BB12:BD12) -> 77.8 | BF12: =SUM(I12-BE12) -> 112.2 | BG12: =SUM(I12-BF12) -> 77.8
A13: =ELEC!C10 -> 44143 | B13: 109443 | C13: =B13-B12 -> 0 | D13: =C13/27 -> 0 | E13: =SUM((C13*$E$4)+(7500/'EDl log'!$A$37)) -> 250 | G13: =G12 -> 611115 | H13: =G13-G12 -> 0 | I13: =C13+H13 -> 0 | J13: =IF(I13>0,E13/I13,0) -> 0 | K13: ='Swimming Pool quality check '!H13 -> 6699 | L13: =K13-K12 -> 0 | M13: =M12 -> 457.44 | N13: =SUM(M13-M12) -> 0 | O13: =O12 -> 529.52 | P13: =SUM(O13-O12) -> 0 | Q13: =SUM(P13+N13) -> 0 | T13: =T12 -> 5159 | U13: =SUM(T13-T12) -> 0 | V13: =V12 -> 452 | W13: =+V13-V12 -> 0 | X13: =X12 -> 148761 | Y13: =SUM(X13-X12) -> 0 | Z13: =Z12 -> 97468 | AA13: =Z13-Z12 -> 0 | AB13: =AB12 -> 260 | AC13: =AC12 -> 698 | AD13: =AC13-AC12 -> 0 | AE13: =AE12 -> 227.8 | AF13: =AE13-AE12 -> 0 | AG13: =AG12 -> 2181.28 | AH13: =AG13-AG12 -> 0 | AI13: =AF13+AH13 -> 0 | AJ13: =+Z13-Z12 -> 0 | AK13: =SUM(Y13-L13) -> 0 | AL13: =SUM(AJ13-W13) -> 0 | AM13: ='General information '!D13 -> 24 | AN13: ='General information '!J13 -> 0 | AP13: ='General information '!J13 -> 0 | AR13: =A13 -> 44143 | AS13: =AS12 -> 0.9 | AT13: =AT12 -> 93 | AU13: =AU12 -> 1.1 | AV13: 36 | AW13: 2.9 | AX13: 40 | AY13: =AS13*AT13 -> 83.7 | AZ13: =AU13*AV13 -> 39.6 | BA13: =AW13*AX13 -> 116 | BB13: =AY13-AY12 -> 0 | BC13: =AZ13-AZ12 -> -5.5 | BD13: =BA13-BA12 -> -14.5 | BE13: =SUM(BB13:BD13) -> -20 | BF13: =SUM(I13-BE13) -> 20 | BG13: =SUM(I13-BF13) -> -20
A14: =ELEC!C11 -> 44144 | B14: =B13 -> 109443 | C14: =B14-B13 -> 0 | D14: =C14/27 -> 0 | E14: =SUM((C14*$E$4)+(7500/'EDl log'!$A$37)) -> 250 | G14: 611306 | H14: =G14-G13 -> 191 | I14: =C14+H14 -> 191 | J14: =IF(I14>0,E14/I14,0) -> 1.3089005 | K14: ='Swimming Pool quality check '!H14 -> 6699 | L14: =K14-K13 -> 0 | M14: =M13 -> 457.44 | N14: =SUM(M14-M13) -> 0 | O14: =O13 -> 529.52 | P14: =SUM(O14-O13) -> 0 | Q14: =SUM(P14+N14) -> 0 | T14: =T13 -> 5159 | U14: =SUM(T14-T13) -> 0 | V14: =V13 -> 452 | W14: =+V14-V13 -> 0 | X14: 148827 | Y14: =SUM(X14-X13) -> 66 | Z14: 97491 | AA14: =Z14-Z13 -> 23 | AB14: =AB13 -> 260 | AC14: =AC13 -> 698 | AD14: =AC14-AC13 -> 0 | AE14: =AE13 -> 227.8 | AF14: =AE14-AE13 -> 0 | AG14: =AG13 -> 2181.28 | AH14: =AG14-AG13 -> 0 | AI14: =AF14+AH14 -> 0 | AJ14: =+Z14-Z13 -> 23 | AK14: =SUM(Y14-L14) -> 66 | AL14: =SUM(AJ14-W14) -> 23 | AM14: ='General information '!D14 -> 24.5 | AN14: ='General information '!H14 -> 0 | AP14: ='General information '!J14 -> 0 | AR14: =A14 -> 44144 | AS14: =AS13 -> 0.9 | AT14: 122 | AU14: =AU13 -> 1.1 | AV14: 49 | AW14: 2.9 | AX14: 54 | AY14: =AS14*AT14 -> 109.8 | AZ14: =AU14*AV14 -> 53.9 | BA14: =AW14*AX14 -> 156.6 | BB14: =AY14-AY13 -> 26.1 | BC14: =AZ14-AZ13 -> 14.3 | BD14: =BA14-BA13 -> 40.6 | BE14: =SUM(BB14:BD14) -> 81 | BF14: =SUM(I14-BE14) -> 110 | BG14: =SUM(I14-BF14) -> 81
A15: =ELEC!C12 -> 44145 | B15: =B14 -> 109443 | C15: =B15-B14 -> 0 | D15: =C15/27 -> 0 | E15: =SUM((C15*$E$4)+(7500/'EDl log'!$A$37)) -> 250 | G15: =G14 -> 611306 | H15: =G15-G14 -> 0 | I15: =C15+H15 -> 0 | J15: =IF(I15>0,E15/I15,0) -> 0 | K15: ='Swimming Pool quality check '!H15 -> 6699 | L15: =K15-K14 -> 0 | M15: =M14 -> 457.44 | N15: =SUM(M15-M14) -> 0 | O15: =O14 -> 529.52 | P15: =SUM(O15-O14) -> 0 | Q15: =SUM(P15+N15) -> 0 | T15: =T14 -> 5159 | U15: =SUM(T15-T14) -> 0 | V15: =V14 -> 452 | W15: =+V15-V14 -> 0 | X15: 148893 | Y15: =SUM(X15-X14) -> 66 | Z15: 97515 | AA15: =Z15-Z14 -> 24 | AB15: =AB14 -> 260 | AC15: =AC14 -> 698 | AD15: =AC15-AC14 -> 0 | AE15: =AE14 -> 227.8 | AF15: =AE15-AE14 -> 0 | AG15: =AG14 -> 2181.28 | AH15: =AG15-AG14 -> 0 | AI15: =AF15+AH15 -> 0 | AJ15: =+Z15-Z14 -> 24 | AK15: =SUM(Y15-L15) -> 66 | AL15: =SUM(AJ15-W15) -> 24 | AM15: ='General information '!D15 -> 23 | AN15: ='General information '!H15 -> 0 | AP15: ='General information '!J15 -> 0 | AR15: =A15 -> 44145 | AS15: =AS14 -> 0.9 | AT15: 15 | AU15: =AU14 -> 1.1 | AV15: 62 | AW15: 2.9 | AX15: 71 | AY15: =AS15*AT15 -> 13.5 | AZ15: =AU15*AV15 -> 68.2 | BA15: =AW15*AX15 -> 205.9 | BB15: =AY15-AY14 -> -96.3 | BC15: =AZ15-AZ14 -> 14.3 | BD15: =BA15-BA14 -> 49.3 | BE15: =SUM(BB15:BD15) -> -32.7 | BF15: =SUM(I15-BE15) -> 32.7 | BG15: =SUM(I15-BF15) -> -32.7
A16: =ELEC!C13 -> 44146 | B16: =B15 -> 109443 | C16: =B16-B15 -> 0 | D16: =C16/27 -> 0 | E16: =SUM((C16*$E$4)+(7500/'EDl log'!$A$37)) -> 250 | G16: 611491 | H16: =G16-G15 -> 185 | I16: =C16+H16 -> 185 | J16: =IF(I16>0,E16/I16,0) -> 1.3513514 | K16: ='Swimming Pool quality check '!H16 -> 6699 | L16: =K16-K15 -> 0 | M16: =M15 -> 457.44 | N16: =SUM(M16-M15) -> 0 | O16: =O15 -> 529.52 | P16: =SUM(O16-O15) -> 0 | Q16: =SUM(P16+N16) -> 0 | T16: =T15 -> 5159 | U16: =SUM(T16-T15) -> 0 | V16: =V15 -> 452 | W16: =+V16-V15 -> 0 | X16: =X15 -> 148893 | Y16: =SUM(X16-X15) -> 0 | Z16: =Z15 -> 97515 | AA16: =Z16-Z15 -> 0 | AB16: =AB15 -> 260 | AC16: =AC15 -> 698 | AD16: =AC16-AC15 -> 0 | AE16: =AE15 -> 227.8 | AF16: =AE16-AE15 -> 0 | AG16: =AG15 -> 2181.28 | AH16: =AG16-AG15 -> 0 | AI16: =AF16+AH16 -> 0 | AJ16: =+Z16-Z15 -> 0 | AK16: =SUM(Y16-L16) -> 0 | AL16: =SUM(AJ16-W16) -> 0 | AM16: ='General information '!D16 -> 22.5 | AN16: ='General information '!H16 -> 0 | AP16: ='General information '!J16 -> 0 | AR16: =A16 -> 44146 | AS16: =AS15 -> 0.9 | AT16: 123 | AU16: =AU15 -> 1.1 | AV16: 56 | AW16: 2.9 | AX16: 70 | AY16: =AS16*AT16 -> 110.7 | AZ16: =AU16*AV16 -> 61.6 | BA16: =AW16*AX16 -> 203 | BB16: =AY16-AY15 -> 97.2 | BC16: =AZ16-AZ15 -> -6.6 | BD16: =BA16-BA15 -> -2.9 | BE16: =SUM(BB16:BD16) -> 87.7 | BF16: =SUM(I16-BE16) -> 97.3 | BG16: =SUM(I16-BF16) -> 87.7
A17: =ELEC!C14 -> 44147 | B17: 109443 | C17: =B17-B16 -> 0 | D17: =C17/27 -> 0 | E17: =SUM((C17*$E$4)+(7500/'EDl log'!$A$37)) -> 250 | G17: =G16 -> 611491 | H17: =G17-G16 -> 0 | I17: =C17+H17 -> 0 | J17: =IF(I17>0,E17/I17,0) -> 0 | K17: ='Swimming Pool quality check '!H17 -> 6700 | L17: =K17-K16 -> 1 | M17: =M16 -> 457.44 | N17: =SUM(M17-M16) -> 0 | O17: =O16 -> 529.52 | P17: =SUM(O17-O16) -> 0 | Q17: =SUM(P17+N17) -> 0 | T17: =T16 -> 5159 | U17: =SUM(T17-T16) -> 0 | V17: =V16 -> 452 | W17: =+V17-V16 -> 0 | X17: 148976 | Y17: =SUM(X17-X16) -> 83 | Z17: 97557 | AA17: =Z17-Z16 -> 42 | AB17: =AB16 -> 260 | AC17: =AC16 -> 698 | AD17: =AC17-AC16 -> 0 | AE17: =AE16 -> 227.8 | AF17: =AE17-AE16 -> 0 | AG17: =AG16 -> 2181.28 | AH17: =AG17-AG16 -> 0 | AI17: =AF17+AH17 -> 0 | AJ17: =+Z17-Z16 -> 42 | AK17: =SUM(Y17-L17) -> 82 | AL17: =SUM(AJ17-W17) -> 42 | AM17: ='General information '!D17 -> 22.5 | AN17: ='General information '!H17 -> 0 | AP17: ='General information '!J17 -> 0 | AR17: =A17 -> 44147 | AS17: =AS16 -> 0.9 | AT17: 13 | AU17: =AU16 -> 1.1 | AV17: 79 | AW17: 2.9 | AX17: 88 | AY17: =AS17*AT17 -> 11.7 | AZ17: =AU17*AV17 -> 86.9 | BA17: =AW17*AX17 -> 255.2 | BB17: =AY17-AY16 -> -99 | BC17: =AZ17-AZ16 -> 25.3 | BD17: =BA17-BA16 -> 52.2 | BE17: =SUM(BB17:BD17) -> -21.5 | BF17: =SUM(I17-BE17) -> 21.5 | BG17: =SUM(I17-BF17) -> -21.5
A18: =ELEC!C15 -> 44148 | B18: =B17 -> 109443 | C18: =B18-B17 -> 0 | D18: =C18/27 -> 0 | E18: =SUM((C18*$E$4)+(7500/'EDl log'!$A$37)) -> 250 | G18: 611608 | H18: =G18-G17 -> 117 | I18: =C18+H18 -> 117 | J18: =IF(I18>0,E18/I18,0) -> 2.1367521 | K18: ='Swimming Pool quality check '!H18 -> 6700 | L18: =K18-K17 -> 0 | M18: =M17 -> 457.44 | N18: =SUM(M18-M17) -> 0 | O18: =O17 -> 529.52 | P18: =SUM(O18-O17) -> 0 | Q18: =SUM(P18+N18) -> 0 | T18: =T17 -> 5159 | U18: =SUM(T18-T17) -> 0 | V18: =V17 -> 452 | W18: =+V18-V17 -> 0 | X18: 148976 | Y18: =SUM(X18-X17) -> 0 | Z18: 97557 | AA18: =Z18-Z17 -> 0 | AB18: =AB17 -> 260 | AC18: =AC17 -> 698 | AD18: =AC18-AC17 -> 0 | AE18: =AE17 -> 227.8 | AF18: =AE18-AE17 -> 0 | AG18: =AG17 -> 2181.28 | AH18: =AG18-AG17 -> 0 | AI18: =AF18+AH18 -> 0 | AJ18: =+Z18-Z17 -> 0 | AK18: =SUM(Y18-L18) -> 0 | AL18: =SUM(AJ18-W18) -> 0 | AM18: ='General information '!D18 -> 23 | AN18: ='General information '!H18 -> 0 | AP18: ='General information '!J18 -> 0 | AR18: =A18 -> 44148 | AS18: =AS17 -> 0.9 | AT18: 82 | AU18: =AU17 -> 1.1 | AV18: 76 | AW18: 2.9 | AX18: 87 | AY18: =AS18*AT18 -> 73.8 | AZ18: =AU18*AV18 -> 83.6 | BA18: =AW18*AX18 -> 252.3 | BB18: =AY18-AY17 -> 62.1 | BC18: =AZ18-AZ17 -> -3.3 | BD18: =BA18-BA17 -> -2.9 | BE18: =SUM(BB18:BD18) -> 55.9 | BF18: =SUM(I18-BE18) -> 61.1 | BG18: =SUM(I18-BF18) -> 55.9
A19: =ELEC!C16 -> 44149 | B19: =B18 -> 109443 | C19: =B19-B18 -> 0 | D19: =C19/27 -> 0 | E19: =SUM((C19*$E$4)+(7500/'EDl log'!$A$37)) -> 250 | G19: =G18 -> 611608 | H19: =G19-G18 -> 0 | I19: =C19+H19 -> 0 | J19: =IF(I19>0,E19/I19,0) -> 0 | K19: ='Swimming Pool quality check '!H19 -> 6700 | L19: =K19-K18 -> 0 | M19: =M18 -> 457.44 | N19: =SUM(M19-M18) -> 0 | O19: =O18 -> 529.52 | P19: =SUM(O19-O18) -> 0 | Q19: =SUM(P19+N19) -> 0 | T19: =T18 -> 5159 | U19: =SUM(T19-T18) -> 0 | V19: =V18 -> 452 | W19: =+V19-V18 -> 0 | X19: 149007 | Y19: =SUM(X19-X18) -> 31 | Z19: 97569 | AA19: =Z19-Z18 -> 12 | AB19: =AB18 -> 260 | AC19: =AC18 -> 698 | AD19: =AC19-AC18 -> 0 | AE19: =AE18 -> 227.8 | AF19: =AE19-AE18 -> 0 | AG19: =AG18 -> 2181.28 | AH19: =AG19-AG18 -> 0 | AI19: =AF19+AH19 -> 0 | AJ19: =+Z19-Z18 -> 12 | AK19: =SUM(Y19-L19) -> 31 | AL19: =SUM(AJ19-W19) -> 12 | AM19: ='General information '!D19 -> 23 | AN19: ='General information '!H19 -> 0 | AP19: ='General information '!J19 -> 0 | AR19: =A19 -> 44149 | AS19: =AS18 -> 0.9 | AT19: 21 | AU19: =AU18 -> 1.1 | AV19: 79 | AW19: 2.9 | AX19: 92 | AY19: 21 | AZ19: 79 | BA19: 92 | BB19: =AY19-AY18 -> -52.8 | BC19: =AZ19-AZ18 -> -4.6 | BD19: =BA19-BA18 -> -160.3 | BE19: =SUM(BB19:BD19) -> -217.7 | BF19: =SUM(I19-BE19) -> 217.7 | BG19: =SUM(I19-BF19) -> -217.7
A20: =ELEC!C17 -> 44150 | B20: 109443 | C20: =B20-B19 -> 0 | D20: =C20/27 -> 0 | E20: =SUM((C20*$E$4)+(7500/'EDl log'!$A$37)) -> 250 | G20: 611760 | H20: =G20-G19 -> 152 | I20: =C20+H20 -> 152 | J20: =IF(I20>0,E20/I20,0) -> 1.6447368 | K20: ='Swimming Pool quality check '!H20 -> 6700 | L20: =K20-K19 -> 0 | M20: =M19 -> 457.44 | N20: =SUM(M20-M19) -> 0 | O20: =O19 -> 529.52 | P20: =SUM(O20-O19) -> 0 | Q20: =SUM(P20+N20) -> 0 | T20: =T19 -> 5159 | U20: =SUM(T20-T19) -> 0 | V20: =V19 -> 452 | W20: =+V20-V19 -> 0 | X20: =X19 -> 149007 | Y20: =SUM(X20-X19) -> 0 | Z20: =Z19 -> 97569 | AA20: =Z20-Z19 -> 0 | AB20: =AB19 -> 260 | AC20: =AC19 -> 698 | AD20: =AC20-AC19 -> 0 | AE20: =AE19 -> 227.8 | AF20: =AE20-AE19 -> 0 | AG20: =AG19 -> 2181.28 | AH20: =AG20-AG19 -> 0 | AI20: =AF20+AH20 -> 0 | AJ20: =+Z20-Z19 -> 0 | AK20: =SUM(Y20-L20) -> 0 | AL20: =SUM(AJ20-W20) -> 0 | AM20: ='General information '!D20 -> 19.5 | AN20: ='General information '!H20 -> 0 | AP20: ='General information '!J20 -> 0 | AR20: =A20 -> 44150 | AS20: =AS19 -> 0.9 | AT20: 148 | AU20: =AU19 -> 1.1 | AV20: 74 | AW20: 2.9 | AX20: 91 | AY20: =AS20*AT20 -> 133.2 | AZ20: =AU20*AV20 -> 81.4 | BA20: =AW20*AX20 -> 263.9 | BB20: =AY20-AY19 -> 112.2 | BC20: =AZ20-AZ19 -> 2.4 | BD20: =BA20-BA19 -> 171.9 | BE20: =SUM(BB20:BD20) -> 286.5 | BF20: =SUM(I20-BE20) -> -134.5 | BG20: =SUM(I20-BF20) -> 286.5
A21: =ELEC!C18 -> 44151 | B21: =B20 -> 109443 | C21: =B21-B20 -> 0 | D21: =C21/27 -> 0 | E21: =SUM((C21*$E$4)+(7500/'EDl log'!$A$37)) -> 250 | G21: 611760 | H21: =G21-G20 -> 0 | I21: =C21+H21 -> 0 | J21: =IF(I21>0,E21/I21,0) -> 0 | K21: ='Swimming Pool quality check '!H21 -> 6700 | L21: =K21-K20 -> 0 | M21: =M20 -> 457.44 | N21: =SUM(M21-M20) -> 0 | O21: =O20 -> 529.52 | P21: =SUM(O21-O20) -> 0 | Q21: =SUM(P21+N21) -> 0 | T21: =T20 -> 5159 | U21: =SUM(T21-T20) -> 0 | V21: =V20 -> 452 | W21: =+V21-V20 -> 0 | X21: 149061 | Y21: =SUM(X21-X20) -> 54 | Z21: 97616 | AA21: =Z21-Z20 -> 47 | AB21: =AB20 -> 260 | AC21: =AC20 -> 698 | AD21: =AC21-AC20 -> 0 | AE21: =AE20 -> 227.8 | AF21: =AE21-AE20 -> 0 | AG21: =AG20 -> 2181.28 | AH21: =AG21-AG20 -> 0 | AI21: =AF21+AH21 -> 0 | AJ21: =+Z21-Z20 -> 47 | AK21: =SUM(Y21-L21) -> 54 | AL21: =SUM(AJ21-W21) -> 47 | AM21: ='General information '!D21 -> 19 | AN21: ='General information '!H21 -> 0 | AP21: ='General information '!J21 -> 0 | AR21: =A21 -> 44151 | AS21: =AS20 -> 0.9 | AT21: 20 | AU21: =AU20 -> 1.1 | AV21: 107 | AW21: 2.9 | AX21: 106 | AY21: =AS21*AT21 -> 18 | AZ21: =AU21*AV21 -> 117.7 | BA21: =AW21*AX21 -> 307.4 | BB21: =AY21-AY20 -> -115.2 | BC21: =AZ21-AZ20 -> 36.3 | BD21: =BA21-BA20 -> 43.5 | BE21: =SUM(BB21:BD21) -> -35.4 | BF21: =SUM(I21-BE21) -> 35.4 | BG21: =SUM(I21-BF21) -> -35.4
A22: =ELEC!C19 -> 44152 | B22: =B21 -> 109443 | C22: =B22-B21 -> 0 | D22: =C22/27 -> 0 | E22: =SUM((C22*$E$4)+(7500/'EDl log'!$A$37)) -> 250 | G22: 611951 | H22: =G22-G21 -> 191 | I22: =C22+H22 -> 191 | J22: =IF(I22>0,E22/I22,0) -> 1.3089005 | K22: ='Swimming Pool quality check '!H22 -> 6700 | L22: =K22-K21 -> 0 | M22: =M21 -> 457.44 | N22: =SUM(M22-M21) -> 0 | O22: =O21 -> 529.52 | P22: =SUM(O22-O21) -> 0 | Q22: =SUM(P22+N22) -> 0 | T22: =T21 -> 5159 | U22: =SUM(T22-T21) -> 0 | V22: =V21 -> 452 | W22: =+V22-V21 -> 0 | X22: 149084 | Y22: =SUM(X22-X21) -> 23 | Z22: 97637 | AA22: =Z22-Z21 -> 21 | AB22: =AB21 -> 260 | AC22: =AC21 -> 698 | AD22: =AC22-AC21 -> 0 | AE22: =AE21 -> 227.8 | AF22: =AE22-AE21 -> 0 | AG22: =AG21 -> 2181.28 | AH22: =AG22-AG21 -> 0 | AI22: =AF22+AH22 -> 0 | AJ22: =+Z22-Z21 -> 21 | AK22: =SUM(Y22-L22) -> 23 | AL22: =SUM(AJ22-W22) -> 21 | AM22: ='General information '!D22 -> 18 | AN22: ='General information '!H22 -> 0 | AP22: ='General information '!J22 -> 0 | AR22: =A22 -> 44152 | AS22: =AS21 -> 0.9 | AT22: 62 | AU22: =AU21 -> 1.1 | AV22: 113 | AW22: 2.9 | AX22: 111 | AY22: =AS22*AT22 -> 55.8 | AZ22: =AU22*AV22 -> 124.3 | BA22: =AW22*AX22 -> 321.9 | BB22: =AY22-AY21 -> 37.8 | BC22: =AZ22-AZ21 -> 6.6 | BD22: =BA22-BA21 -> 14.5 | BE22: =SUM(BB22:BD22) -> 58.9 | BF22: =SUM(I22-BE22) -> 132.1 | BG22: =SUM(I22-BF22) -> 58.9
A23: =ELEC!C20 -> 44153 | B23: =B22 -> 109443 | C23: =B23-B22 -> 0 | D23: =C23/27 -> 0 | E23: =SUM((C23*$E$4)+(7500/'EDl log'!$A$37)) -> 250 | G23: 611951 | H23: =G23-G22 -> 0 | I23: =C23+H23 -> 0 | J23: =IF(I23>0,E23/I23,0) -> 0 | K23: ='Swimming Pool quality check '!H23 -> 6700 | L23: =K23-K22 -> 0 | M23: =M22 -> 457.44 | N23: =SUM(M23-M22) -> 0 | O23: =O22 -> 529.52 | P23: =SUM(O23-O22) -> 0 | Q23: =SUM(P23+N23) -> 0 | T23: =T22 -> 5159 | U23: =SUM(T23-T22) -> 0 | V23: =V22 -> 452 | W23: =+V23-V22 -> 0 | X23: 149084 | Y23: =SUM(X23-X22) -> 0 | Z23: 97637 | AA23: =Z23-Z22 -> 0 | AB23: =AB22 -> 260 | AC23: =AC22 -> 698 | AD23: =AC23-AC22 -> 0 | AE23: =AE22 -> 227.8 | AF23: =AE23-AE22 -> 0 | AG23: =AG22 -> 2181.28 | AH23: =AG23-AG22 -> 0 | AI23: =AF23+AH23 -> 0 | AJ23: =+Z23-Z22 -> 0 | AK23: =SUM(Y23-L23) -> 0 | AL23: =SUM(AJ23-W23) -> 0 | AM23: ='General information '!D23 -> 18 | AN23: ='General information '!H23 -> 0 | AP23: ='General information '!J23 -> 0 | AR23: =A23 -> 44153 | AS23: =AS22 -> 0.9 | AT23: 110 | AU23: =AU22 -> 1.1 | AV23: 105 | AW23: 2.9 | AX23: 90 | AY23: =AS23*AT23 -> 99 | AZ23: =AU23*AV23 -> 115.5 | BA23: =AW23*AX23 -> 261 | BB23: =AY23-AY22 -> 43.2 | BC23: =AZ23-AZ22 -> -8.8 | BD23: =BA23-BA22 -> -60.9 | BE23: =SUM(BB23:BD23) -> -26.5 | BF23: =SUM(I23-BE23) -> 26.5 | BG23: =SUM(I23-BF23) -> -26.5
A24: =ELEC!C21 -> 44154 | B24: =B23 -> 109443 | C24: =B24-B23 -> 0 | D24: =C24/27 -> 0 | E24: =SUM((C24*$E$4)+(7500/'EDl log'!$A$37)) -> 250 | G24: 612045 | H24: =G24-G23 -> 94 | I24: =C24+H24 -> 94 | J24: =IF(I24>0,E24/I24,0) -> 2.6595745 | K24: ='Swimming Pool quality check '!H24 -> 6700 | L24: =K24-K23 -> 0 | M24: =M23 -> 457.44 | N24: =SUM(M24-M23) -> 0 | O24: =O23 -> 529.52 | P24: =SUM(O24-O23) -> 0 | Q24: =SUM(P24+N24) -> 0 | T24: 5159 | U24: =SUM(T24-T23) -> 0 | V24: =V23 -> 452 | W24: =+V24-V23 -> 0 | X24: 149104 | Y24: =SUM(X24-X23) -> 20 | Z24: =Z23 -> 97637 | AA24: =Z24-Z23 -> 0 | AB24: 246 | AC24: =AC23 -> 698 | AD24: =AC24-AC23 -> 0 | AE24: =AE23 -> 227.8 | AF24: =AE24-AE23 -> 0 | AG24: =AG23 -> 2181.28 | AH24: =AG24-AG23 -> 0 | AI24: =AF24+AH24 -> 0 | AJ24: =+Z24-Z23 -> 0 | AK24: =SUM(Y24-L24) -> 20 | AL24: =SUM(AJ24-W24) -> 0 | AM24: ='General information '!D24 -> 18.5 | AN24: ='General information '!H24 -> 0 | AP24: ='General information '!J24 -> 0 | AR24: =A24 -> 44154 | AS24: =AS23 -> 0.9 | AT24: 89 | AU24: =AU23 -> 1.1 | AV24: 104 | AW24: 2.9 | AX24: 112 | AY24: =AS24*AT24 -> 80.1 | AZ24: =AU24*AV24 -> 114.4 | BA24: =AW24*AX24 -> 324.8 | BB24: =AY24-AY23 -> -18.9 | BC24: =AZ24-AZ23 -> -1.1 | BD24: =BA24-BA23 -> 63.8 | BE24: =SUM(BB24:BD24) -> 43.8 | BF24: =SUM(I24-BE24) -> 50.2 | BG24: =SUM(I24-BF24) -> 43.8
A25: =ELEC!C22 -> 44155 | B25: =B24 -> 109443 | C25: =B25-B24 -> 0 | D25: =C25/27 -> 0 | E25: =SUM((C25*$E$4)+(7500/'EDl log'!$A$37)) -> 250 | G25: 612045 | H25: =G25-G24 -> 0 | I25: =C25+H25 -> 0 | J25: =IF(I25>0,E25/I25,0) -> 0 | K25: ='Swimming Pool quality check '!H25 -> 6700 | L25: =K25-K24 -> 0 | M25: =M24 -> 457.44 | N25: =SUM(M25-M24) -> 0 | O25: =O24 -> 529.52 | P25: =SUM(O25-O24) -> 0 | Q25: =SUM(P25+N25) -> 0 | T25: 5160 | U25: =SUM(T25-T24) -> 1 | V25: 459 | W25: =+V25-V24 -> 7 | X25: 149168 | Y25: =SUM(X25-X24) -> 64 | Z25: 97681 | AA25: =Z25-Z24 -> 44 | AB25: =AB24 -> 246 | AC25: 699 | AD25: =AC25-AC24 -> 1 | AE25: =AE24 -> 227.8 | AF25: =AE25-AE24 -> 0 | AG25: 2181.57 | AH25: =AG25-AG24 -> 0.29 | AI25: =AF25+AH25 -> 0.29 | AJ25: =+Z25-Z24 -> 44 | AK25: =SUM(Y25-L25) -> 64 | AL25: =SUM(AJ25-W25) -> 37 | AM25: ='General information '!D25 -> 17 | AN25: ='General information '!H25 -> 0 | AP25: ='General information '!J25 -> 0 | AR25: =A25 -> 44155 | AS25: =AS24 -> 0.9 | AT25: 62 | AU25: =AU24 -> 1.1 | AV25: 126 | AW25: 2.9 | AX25: 125 | AY25: =AS25*AT25 -> 55.8 | AZ25: =AU25*AV25 -> 138.6 | BA25: =AW25*AX25 -> 362.5 | BB25: =AY25-AY24 -> -24.3 | BC25: =AZ25-AZ24 -> 24.2 | BD25: =BA25-BA24 -> 37.7 | BE25: =SUM(BB25:BD25) -> 37.6 | BF25: =SUM(I25-BE25) -> -37.6 | BG25: =SUM(I25-BF25) -> 37.6
A26: =ELEC!C23 -> 44156 | B26: =B25 -> 109443 | C26: =B26-B25 -> 0 | D26: =C26/27 -> 0 | E26: =SUM((C26*$E$4)+(7500/'EDl log'!$A$37)) -> 250 | G26: 612265 | H26: =G26-G25 -> 220 | I26: =C26+H26 -> 220 | J26: =IF(I26>0,E26/I26,0) -> 1.1363636 | K26: ='Swimming Pool quality check '!H26 -> 6700 | L26: =K26-K25 -> 0 | M26: =M25 -> 457.44 | N26: =SUM(M26-M25) -> 0 | O26: =O25 -> 529.52 | P26: =SUM(O26-O25) -> 0 | Q26: =SUM(P26+N26) -> 0 | T26: =T25 -> 5160 | U26: =SUM(T26-T25) -> 0 | V26: =V25 -> 459 | W26: =+V26-V25 -> 0 | X26: =X25 -> 149168 | Y26: =SUM(X26-X25) -> 0 | Z26: =Z25 -> 97681 | AA26: =Z26-Z25 -> 0 | AB26: 262 | AC26: 730 | AD26: =AC26-AC25 -> 31 | AE26: =AE25 -> 227.8 | AF26: =AE26-AE25 -> 0 | AG26: =AG25 -> 2181.57 | AH26: =AG26-AG25 -> 0 | AI26: =AF26+AH26 -> 0 | AJ26: =+Z26-Z25 -> 0 | AK26: =SUM(Y26-L26) -> 0 | AL26: =SUM(AJ26-W26) -> 0 | AM26: ='General information '!D26 -> 17 | AN26: ='General information '!H26 -> 0 | AP26: ='General information '!J26 -> 0 | AR26: =A26 -> 44156 | AS26: =AS25 -> 0.9 | AT26: 97 | AU26: =AU25 -> 1.1 | AV26: 120 | AW26: 2.9 | AX26: 122 | AY26: =AS26*AT26 -> 87.3 | AZ26: =AU26*AV26 -> 132 | BA26: =AW26*AX26 -> 353.8 | BB26: =AY26-AY25 -> 31.5 | BC26: =AZ26-AZ25 -> -6.6 | BD26: =BA26-BA25 -> -8.7 | BE26: =SUM(BB26:BD26) -> 16.2 | BF26: =SUM(I26-BE26) -> 203.8 | BG26: =SUM(I26-BF26) -> 16.2
A27: =ELEC!C24 -> 44157 | B27: =B26 -> 109443 | C27: =B27-B26 -> 0 | D27: =C27/27 -> 0 | E27: =SUM((C27*$E$4)+(7500/'EDl log'!$A$37)) -> 250 | G27: 612276 | H27: =G27-G26 -> 11 | I27: =C27+H27 -> 11 | J27: =IF(I27>0,E27/I27,0) -> 22.727273 | K27: ='Swimming Pool quality check '!H27 -> 6700 | L27: =K27-K26 -> 0 | M27: =M26 -> 457.44 | N27: =SUM(M27-M26) -> 0 | O27: =O26 -> 529.52 | P27: =SUM(O27-O26) -> 0 | Q27: =SUM(P27+N27) -> 0 | T27: =T26 -> 5160 | U27: =SUM(T27-T26) -> 0 | V27: =V26 -> 459 | W27: =+V27-V26 -> 0 | X27: =X26 -> 149168 | Y27: =SUM(X27-X26) -> 0 | Z27: =Z26 -> 97681 | AA27: =Z27-Z26 -> 0 | AB27: 262 | AC27: 730 | AD27: =AC27-AC26 -> 0 | AE27: =AE26 -> 227.8 | AF27: =AE27-AE26 -> 0 | AG27: =AG26 -> 2181.57 | AH27: =AG27-AG26 -> 0 | AI27: =AF27+AH27 -> 0 | AJ27: =+Z27-Z26 -> 0 | AK27: =SUM(Y27-L27) -> 0 | AL27: =SUM(AJ27-W27) -> 0 | AM27: ='General information '!D27 -> 17.5 | AN27: ='General information '!H27 -> 0 | AP27: ='General information '!J27 -> 0 | AR27: =A27 -> 44157 | AS27: =AS26 -> 0.9 | AT27: 105 | AU27: =AU26 -> 1.1 | AV27: 116 | AW27: 2.9 | AX27: 120 | AY27: =AS27*AT27 -> 94.5 | AZ27: =AU27*AV27 -> 127.6 | BA27: =AW27*AX27 -> 348 | BB27: =AY27-AY26 -> 7.2 | BC27: =AZ27-AZ26 -> -4.4 | BD27: =BA27-BA26 -> -5.8 | BE27: =SUM(BB27:BD27) -> -3 | BF27: =SUM(I27-BE27) -> 14 | BG27: =SUM(I27-BF27) -> -3
A28: =ELEC!C25 -> 44158 | B28: =B27 -> 109443 | C28: =B28-B27 -> 0 | D28: =C28/27 -> 0 | E28: =SUM((C28*$E$4)+(7500/'EDl log'!$A$37)) -> 250 | G28: 612461 | H28: =G28-G27 -> 185 | I28: =C28+H28 -> 185 | J28: =IF(I28>0,E28/I28,0) -> 1.3513514 | K28: ='Swimming Pool quality check '!H28 -> 6700 | L28: =K28-K27 -> 0 | M28: =M27 -> 457.44 | N28: =SUM(M28-M27) -> 0 | O28: =O27 -> 529.52 | P28: =SUM(O28-O27) -> 0 | Q28: =SUM(P28+N28) -> 0 | T28: =T27 -> 5160 | U28: =SUM(T28-T27) -> 0 | V28: =V27 -> 459 | W28: =+V28-V27 -> 0 | X28: 149172 | Y28: =SUM(X28-X27) -> 4 | Z28: 97728 | AA28: =Z28-Z27 -> 47 | AB28: =AB27 -> 262 | AC28: =AC27 -> 730 | AD28: =AC28-AC27 -> 0 | AE28: =AE27 -> 227.8 | AF28: =AE28-AE27 -> 0 | AG28: =AG27 -> 2181.57 | AH28: =AG28-AG27 -> 0 | AI28: =AF28+AH28 -> 0 | AJ28: =+Z28-Z27 -> 47 | AK28: =SUM(Y28-L28) -> 4 | AL28: =SUM(AJ28-W28) -> 47 | AM28: ='General information '!D28 -> 17.5 | AN28: ='General information '!H28 -> 0 | AP28: ='General information '!J28 -> 0 | AR28: =A28 -> 44158 | AS28: =AS27 -> 0.9 | AT28: 156 | AU28: =AU27 -> 1.1 | AV28: 148 | AW28: 2.9 | AX28: 116 | AY28: =AS28*AT28 -> 140.4 | AZ28: =AU28*AV28 -> 162.8 | BA28: =AW28*AX28 -> 336.4 | BB28: =AY28-AY27 -> 45.9 | BC28: =AZ28-AZ27 -> 35.2 | BD28: =BA28-BA27 -> -11.6 | BE28: =SUM(BB28:BD28) -> 69.5 | BF28: =SUM(I28-BE28) -> 115.5 | BG28: =SUM(I28-BF28) -> 69.5
A29: =ELEC!C26 -> 44159 | B29: =B28 -> 109443 | C29: =B29-B28 -> 0 | D29: =C29/27 -> 0 | E29: =SUM((C29*$E$4)+(7500/'EDl log'!$A$37)) -> 250 | G29: 612466 | H29: =G29-G28 -> 5 | I29: =C29+H29 -> 5 | J29: =IF(I29>0,E29/I29,0) -> 50 | K29: ='Swimming Pool quality check '!H29 -> 6700 | L29: =K29-K28 -> 0 | M29: =M28 -> 457.44 | N29: =SUM(M29-M28) -> 0 | O29: =O28 -> 529.52 | P29: =SUM(O29-O28) -> 0 | Q29: =SUM(P29+N29) -> 0 | T29: =T28 -> 5160 | U29: =SUM(T29-T28) -> 0 | V29: =V28 -> 459 | W29: =+V29-V28 -> 0 | X29: =X28 -> 149172 | Y29: =SUM(X29-X28) -> 0 | Z29: =Z28 -> 97728 | AA29: =Z29-Z28 -> 0 | AB29: =AB28 -> 262 | AC29: =AC28 -> 730 | AD29: =AC29-AC28 -> 0 | AE29: =AE28 -> 227.8 | AF29: =AE29-AE28 -> 0 | AG29: =AG28 -> 2181.57 | AH29: =AG29-AG28 -> 0 | AI29: =AF29+AH29 -> 0 | AJ29: =+Z29-Z28 -> 0 | AK29: =SUM(Y29-L29) -> 0 | AL29: =SUM(AJ29-W29) -> 0 | AM29: ='General information '!D29 -> 17 | AN29: ='General information '!H29 -> 0 | AP29: ='General information '!J29 -> 0 | AR29: =A29 -> 44159 | AS29: =AS28 -> 0.9 | AT29: 166 | AU29: =AU28 -> 1.1 | AV29: 144 | AW29: 2.9 | AX29: 110 | AY29: =AS29*AT29 -> 149.4 | AZ29: =AU29*AV29 -> 158.4 | BA29: =AW29*AX29 -> 319 | BB29: =AY29-AY28 -> 9 | BC29: =AZ29-AZ28 -> -4.4 | BD29: =BA29-BA28 -> -17.4 | BE29: =SUM(BB29:BD29) -> -12.8 | BF29: =SUM(I29-BE29) -> 17.8 | BG29: =SUM(I29-BF29) -> -12.8
A30: =ELEC!C27 -> 44160 | B30: =B29 -> 109443 | C30: =B30-B29 -> 0 | D30: =C30/27 -> 0 | E30: =SUM((C30*$E$4)+(7500/'EDl log'!$A$37)) -> 250 | G30: 612468 | H30: =G30-G29 -> 2 | I30: =C30+H30 -> 2 | J30: =IF(I30>0,E30/I30,0) -> 125 | K30: ='Swimming Pool quality check '!H30 -> 6700 | L30: =K30-K29 -> 0 | M30: =M29 -> 457.44 | N30: =SUM(M30-M29) -> 0 | O30: =O29 -> 529.52 | P30: =SUM(O30-O29) -> 0 | Q30: =SUM(P30+N30) -> 0 | T30: =T29 -> 5160 | U30: =SUM(T30-T29) -> 0 | V30: =V29 -> 459 | W30: =+V30-V29 -> 0 | X30: 149272 | Y30: =SUM(X30-X29) -> 100 | Z30: 97754 | AA30: =Z30-Z29 -> 26 | AB30: =AB29 -> 262 | AC30: =AC29 -> 730 | AD30: =AC30-AC29 -> 0 | AE30: =AE29 -> 227.8 | AF30: =AE30-AE29 -> 0 | AG30: =AG29 -> 2181.57 | AH30: =AG30-AG29 -> 0 | AI30: =AF30+AH30 -> 0 | AJ30: =+Z30-Z29 -> 26 | AK30: =SUM(Y30-L30) -> 100 | AL30: =SUM(AJ30-W30) -> 26 | AM30: ='General information '!D30 -> 16.5 | AN30: ='General information '!H30 -> 0 | AP30: ='General information '!J30 -> 0 | AR30: =A30 -> 44160 | AS30: =AS29 -> 0.9 | AT30: 53 | AU30: =AU29 -> 1.1 | AV30: 158 | AW30: 2.9 | AX30: 132 | AY30: =AS30*AT30 -> 47.7 | AZ30: =AU30*AV30 -> 173.8 | BA30: =AW30*AX30 -> 382.8 | BB30: =AY30-AY29 -> -101.7 | BC30: =AZ30-AZ29 -> 15.4 | BD30: =BA30-BA29 -> 63.8 | BE30: =SUM(BB30:BD30) -> -22.5 | BF30: =SUM(I30-BE30) -> 24.5 | BG30: =SUM(I30-BF30) -> -22.5
A31: =ELEC!C28 -> 44161 | B31: =B30 -> 109443 | C31: =B31-B30 -> 0 | D31: =C31/27 -> 0 | E31: =SUM((C31*$E$4)+(7500/'EDl log'!$A$37)) -> 250 | G31: =G30 -> 612468 | H31: =G31-G30 -> 0 | I31: =C31+H31 -> 0 | J31: =IF(I31>0,E31/I31,0) -> 0 | K31: ='Swimming Pool quality check '!H31 -> 6700 | L31: =K31-K30 -> 0 | M31: =M30 -> 457.44 | N31: =SUM(M31-M30) -> 0 | O31: =O30 -> 529.52 | P31: =SUM(O31-O30) -> 0 | Q31: =SUM(P31+N31) -> 0 | T31: =T30 -> 5160 | U31: =SUM(T31-T30) -> 0 | V31: =V30 -> 459 | W31: =+V31-V30 -> 0 | X31: =X30 -> 149272 | Y31: =SUM(X31-X30) -> 0 | Z31: =Z30 -> 97754 | AA31: =Z31-Z30 -> 0 | AB31: =AB30 -> 262 | AC31: =AC30 -> 730 | AD31: =AC31-AC30 -> 0 | AE31: =AE30 -> 227.8 | AF31: =AE31-AE30 -> 0 | AG31: =AG30 -> 2181.57 | AH31: =AG31-AG30 -> 0 | AI31: =AF31+AH31 -> 0 | AJ31: =+Z31-Z30 -> 0 | AK31: =SUM(Y31-L31) -> 0 | AL31: =SUM(AJ31-W31) -> 0 | AM31: ='General information '!D31 -> 16.5 | AN31: ='General information '!H31 -> 0 | AP31: ='General information '!J31 -> 0 | AR31: =A31 -> 44161 | AS31: =AS30 -> 0.9 | AT31: 51 | AU31: =AU30 -> 1.1 | AV31: 155 | AW31: 2.9 | AX31: 129 | AY31: =AS31*AT31 -> 45.9 | AZ31: =AU31*AV31 -> 170.5 | BA31: =AW31*AX31 -> 374.1 | BB31: =AY31-AY30 -> -1.8 | BC31: =AZ31-AZ30 -> -3.3 | BD31: =BA31-BA30 -> -8.7 | BE31: =SUM(BB31:BD31) -> -13.8 | BF31: =SUM(I31-BE31) -> 13.8 | BG31: =SUM(I31-BF31) -> -13.8
A32: =ELEC!C29 -> 44162 | B32: =B31 -> 109443 | C32: =B32-B31 -> 0 | D32: =C32/27 -> 0 | E32: =SUM((C32*$E$4)+(7500/'EDl log'!$A$37)) -> 250 | G32: =G31 -> 612468 | H32: =G32-G31 -> 0 | I32: =C32+H32 -> 0 | J32: =IF(I32>0,E32/I32,0) -> 0 | K32: ='Swimming Pool quality check '!H32 -> 6700 | L32: =K32-K31 -> 0 | M32: =M31 -> 457.44 | N32: =SUM(M32-M31) -> 0 | O32: =O31 -> 529.52 | P32: =SUM(O32-O31) -> 0 | Q32: =SUM(P32+N32) -> 0 | T32: =T31 -> 5160 | U32: =SUM(T32-T31) -> 0 | V32: =V31 -> 459 | W32: =+V32-V31 -> 0 | X32: =X31 -> 149272 | Y32: =SUM(X32-X31) -> 0 | Z32: =Z31 -> 97754 | AA32: =Z32-Z31 -> 0 | AB32: =AB31 -> 262 | AC32: =AC31 -> 730 | AD32: =AC32-AC31 -> 0 | AE32: =AE31 -> 227.8 | AF32: =AE32-AE31 -> 0 | AG32: =AG31 -> 2181.57 | AH32: =AG32-AG31 -> 0 | AI32: =AF32+AH32 -> 0 | AJ32: =+Z32-Z31 -> 0 | AK32: =SUM(Y32-L32) -> 0 | AL32: =SUM(AJ32-W32) -> 0 | AM32: ='General information '!D32 -> 0 | AN32: ='General information '!H32 -> 0 | AP32: ='General information '!J32 -> 0 | AR32: =A32 -> 44162 | AS32: =AS31 -> 0.9 | AT32: =AT31 -> 51 | AU32: =AU31 -> 1.1 | AV32: =AV31 -> 155 | AW32: 2.9 | AX32: =AX31 -> 129 | AY32: =AS32*AT32 -> 45.9 | AZ32: =AU32*AV32 -> 170.5 | BA32: =AW32*AX32 -> 374.1 | BB32: =AY32-AY31 -> 0 | BC32: =AZ32-AZ31 -> 0 | BD32: =BA32-BA31 -> 0 | BE32: =SUM(BB32:BD32) -> 0 | BF32: =SUM(I32-BE32) -> 0 | BG32: =SUM(I32-BF32) -> 0
A33: =ELEC!C30 -> 44163 | B33: =B32 -> 109443 | C33: =B33-B32 -> 0 | D33: =C33/27 -> 0 | E33: =SUM((C33*$E$4)+(7500/'EDl log'!$A$37)) -> 250 | G33: =G32 -> 612468 | H33: =G33-G32 -> 0 | I33: =C33+H33 -> 0 | J33: =IF(I33>0,E33/I33,0) -> 0 | K33: ='Swimming Pool quality check '!H33 -> 6700 | L33: =K33-K32 -> 0 | M33: =M32 -> 457.44 | N33: =SUM(M33-M32) -> 0 | O33: =O32 -> 529.52 | P33: =SUM(O33-O32) -> 0 | Q33: =SUM(P33+N33) -> 0 | T33: =T32 -> 5160 | U33: =SUM(T33-T32) -> 0 | V33: =V32 -> 459 | W33: =+V33-V32 -> 0 | X33: =X32 -> 149272 | Y33: =SUM(X33-X32) -> 0 | Z33: =Z32 -> 97754 | AA33: =Z33-Z32 -> 0 | AB33: =AB32 -> 262 | AC33: =AC32 -> 730 | AD33: =AC33-AC32 -> 0 | AE33: =AE32 -> 227.8 | AF33: =AE33-AE32 -> 0 | AG33: =AG32 -> 2181.57 | AH33: =AG33-AG32 -> 0 | AI33: =AF33+AH33 -> 0 | AJ33: =+Z33-Z32 -> 0 | AK33: =SUM(Y33-L33) -> 0 | AL33: =SUM(AJ33-W33) -> 0 | AM33: ='General information '!D33 -> 0 | AN33: ='General information '!H33 -> 0 | AP33: ='General information '!J33 -> 0 | AR33: =A33 -> 44163 | AS33: =AS32 -> 0.9 | AT33: =AT32 -> 51 | AU33: =AU32 -> 1.1 | AV33: =AV32 -> 155 | AW33: 2.9 | AX33: =AX32 -> 129 | AY33: =AS33*AT33 -> 45.9 | AZ33: =AU33*AV33 -> 170.5 | BA33: =AW33*AX33 -> 374.1 | BB33: =AY33-AY32 -> 0 | BC33: =AZ33-AZ32 -> 0 | BD33: =BA33-BA32 -> 0 | BE33: =SUM(BB33:BD33) -> 0 | BF33: =SUM(I33-BE33) -> 0 | BG33: =SUM(I33-BF33) -> 0
A34: =ELEC!C31 -> 44164 | B34: =B33 -> 109443 | C34: =B34-B33 -> 0 | D34: =C34/27 -> 0 | E34: =SUM((C34*$E$4)+(7500/'EDl log'!$A$37)) -> 250 | G34: =G33 -> 612468 | H34: =G34-G33 -> 0 | I34: =C34+H34 -> 0 | J34: =IF(I34>0,E34/I34,0) -> 0 | K34: ='Swimming Pool quality check '!H34 -> 6700 | L34: =K34-K33 -> 0 | M34: =M33 -> 457.44 | N34: =SUM(M34-M33) -> 0 | O34: =O33 -> 529.52 | P34: =SUM(O34-O33) -> 0 | Q34: =SUM(P34+N34) -> 0 | T34: =T33 -> 5160 | U34: =SUM(T34-T33) -> 0 | V34: =V33 -> 459 | W34: =+V34-V33 -> 0 | X34: =X33 -> 149272 | Y34: =SUM(X34-X33) -> 0 | Z34: =Z33 -> 97754 | AA34: =Z34-Z33 -> 0 | AB34: =AB33 -> 262 | AC34: =AC33 -> 730 | AD34: =AC34-AC33 -> 0 | AE34: =AE33 -> 227.8 | AF34: =AE34-AE33 -> 0 | AG34: =AG33 -> 2181.57 | AH34: =AG34-AG33 -> 0 | AI34: =AF34+AH34 -> 0 | AJ34: =+Z34-Z33 -> 0 | AK34: =SUM(Y34-L34) -> 0 | AL34: =SUM(AJ34-W34) -> 0 | AM34: ='General information '!D34 -> 0 | AN34: ='General information '!H34 -> 0 | AP34: ='General information '!J34 -> 0 | AR34: =A34 -> 44164 | AS34: =AS33 -> 0.9 | AT34: =AT33 -> 51 | AU34: =AU33 -> 1.1 | AV34: =AV33 -> 155 | AW34: 2.9 | AX34: =AX33 -> 129 | AY34: =AS34*AT34 -> 45.9 | AZ34: =AU34*AV34 -> 170.5 | BA34: =AW34*AX34 -> 374.1 | BB34: =AY34-AY33 -> 0 | BC34: =AZ34-AZ33 -> 0 | BD34: =BA34-BA33 -> 0 | BE34: =SUM(BB34:BD34) -> 0 | BF34: =SUM(I34-BE34) -> 0 | BG34: =SUM(I34-BF34) -> 0
A35: =ELEC!C32 -> 44165 | B35: =B34 -> 109443 | C35: =B35-B34 -> 0 | D35: =C35/27 -> 0 | E35: =SUM((C35*$E$4)+(7500/'EDl log'!$A$37)) -> 250 | G35: =G34 -> 612468 | H35: =G35-G34 -> 0 | I35: =C35+H35 -> 0 | J35: =IF(I35>0,E35/I35,0) -> 0 | K35: ='Swimming Pool quality check '!H35 -> 6700 | L35: =K35-K34 -> 0 | M35: =M34 -> 457.44 | N35: =SUM(M35-M34) -> 0 | O35: =O34 -> 529.52 | P35: =SUM(O35-O34) -> 0 | Q35: =SUM(P35+N35) -> 0 | T35: =T34 -> 5160 | U35: =SUM(T35-T34) -> 0 | V35: =V34 -> 459 | W35: =+V35-V34 -> 0 | X35: =X34 -> 149272 | Y35: =SUM(X35-X34) -> 0 | Z35: =Z34 -> 97754 | AA35: =Z35-Z34 -> 0 | AB35: =AB34 -> 262 | AC35: =AC34 -> 730 | AD35: =AC35-AC34 -> 0 | AE35: =AE34 -> 227.8 | AF35: =AE35-AE34 -> 0 | AG35: =AG34 -> 2181.57 | AH35: =AG35-AG34 -> 0 | AI35: =AF35+AH35 -> 0 | AJ35: =+Z35-Z34 -> 0 | AK35: =SUM(Y35-L35) -> 0 | AL35: =SUM(AJ35-W35) -> 0 | AM35: ='General information '!D35 -> 0 | AN35: ='General information '!H35 -> 0 | AP35: ='General information '!J35 -> 0 | AR35: =A35 -> 44165 | AS35: =AS34 -> 0.9 | AT35: =AT34 -> 51 | AU35: =AU34 -> 1.1 | AV35: =AV34 -> 155 | AW35: 2.9 | AX35: =AX34 -> 129 | AY35: =AS35*AT35 -> 45.9 | AZ35: =AU35*AV35 -> 170.5 | BA35: =AW35*AX35 -> 374.1 | BB35: =AY35-AY34 -> 0 | BC35: =AZ35-AZ34 -> 0 | BD35: =BA35-BA34 -> 0 | BE35: =SUM(BB35:BD35) -> 0 | BF35: =SUM(I35-BE35) -> 0 | BG35: =SUM(I35-BF35) -> 0
A36: =ELEC!C33 -> 44166 | B36: =B35 -> 109443 | C36: =B36-B35 -> 0 | D36: =C36/27 -> 0 | E36: =SUM((C36*$E$4)+(7500/'EDl log'!$A$37)) -> 250 | G36: =G35 -> 612468 | H36: =G36-G35 -> 0 | I36: =C36+H36 -> 0 | J36: =IF(I36>0,E36/I36,0) -> 0 | K36: ='Swimming Pool quality check '!H36 -> 6700 | L36: =K36-K35 -> 0 | M36: =M35 -> 457.44 | N36: =SUM(M36-M35) -> 0 | O36: =O35 -> 529.52 | P36: =SUM(O36-O35) -> 0 | Q36: =SUM(P36+N36) -> 0 | T36: =T35 -> 5160 | U36: =SUM(T36-T35) -> 0 | V36: =V35 -> 459 | W36: =+V36-V35 -> 0 | X36: =X35 -> 149272 | Y36: =SUM(X36-X35) -> 0 | Z36: =Z35 -> 97754 | AA36: =Z36-Z35 -> 0 | AB36: =AB35 -> 262 | AC36: =AC35 -> 730 | AD36: =AC36-AC35 -> 0 | AE36: =AE35 -> 227.8 | AF36: =AE36-AE35 -> 0 | AG36: =AG35 -> 2181.57 | AH36: =AG36-AG35 -> 0 | AI36: =AF36+AH36 -> 0 | AJ36: =+Z36-Z35 -> 0 | AK36: =SUM(Y36-L36) -> 0 | AL36: =SUM(AJ36-W36) -> 0 | AM36: ='General information '!D37 -> 0 | AN36: ='General information '!H37 -> 0 | AP36: ='General information '!J37 -> 0 | AR36: =A36 -> 44166 | AS36: =AS35 -> 0.9 | AT36: =AT35 -> 51 | AU36: =AU35 -> 1.1 | AV36: =AV35 -> 155 | AW36: 2.9 | AX36: =AX35 -> 129 | AY36: =AS36*AT36 -> 45.9 | AZ36: =AU36*AV36 -> 170.5 | BA36: =AW36*AX36 -> 374.1 | BB36: =AY36-AY35 -> 0 | BC36: =AZ36-AZ35 -> 0 | BD36: =BA36-BA35 -> 0 | BE36: =SUM(BB36:BD36) -> 0 | BF36: =SUM(I36-BE36) -> 0 | BG36: =SUM(I36-BF36) -> 0
C37: =SUM(C6:C35) -> 126 | D37: =SUM(D6:D35) -> 4.6666667 | F37: =SUM(F6:F35) -> 0 | H37: =SUM(H6:H35) -> 1997 | I37: =SUM(I6:I35) -> 2123 | L37: =SUM(L7:L35) -> 19 | Q37: =SUM(Q5:Q35) -> 0 | U37: =SUM(U6:U35) -> 1 | Y37: =SUM(Y35,Y33,Y31,Y29,Y27,Y25,Y23,Y21,Y19,Y17,Y15,Y13,Y11,Y9,Y7+#REF!) -> #REF! | AJ37: =SUM(AJ6:AJ35) -> 347 | AK37: =SUM(Y37-L37) -> #REF! | AL37: =SUM(AL6:AL35) -> 340
C38: =+C37*1.66 -> 209.16 | E38: =SUM(E6:E35) -> 7709.16 | F38: =SUM(F6:F35) -> 0 | H38: 7500 | I38: =SUM('General information '!G37/WATER!I37) -> 0 | O38: =SUM(Q37+I37) -> 2123 | Z38: =SUM(Y37:AJ37) -> #REF! | AK38: =SUM(Y38-L38) -> 0
B39: =9*27 -> 243 | D39: =SUM(D21:D35) -> 0 | F39: =SUM(F6:F35) -> 0 | G39: =SUM(I37) -> 2123 | H39: =SUM(H38+C38) -> 7709.16 | K39: =SUM(H39/G39) -> 3.6312577 | AJ39: =SUM(C38-AK38) -> 209.16 | AM39: =SUM(AJ39/AO38) -> #DIV/0!

Sheet graphic

Sheet General information 
A1: GENERAL & HOTEL'S INFORMATION SHEET
B4: Max Temp | C4: MIN TEMP | D4: AVE TEMP | E4: AVE Humidity | F4: AVE OCC | G4: # of OCC Rooms | H4: Ball room | I4: Meeting rooms | J4: Outlets | K4: Total covers | L4: # of permenant Emp | M4: # of casuals | N4: Total # of EMP | O4: # of EMP/OCC Room
A5: =ELEC!C2 -> 44135 | B5: ='[2]General information '!B36 -> 32 | C5: ='[2]General information '!C36 -> 28 | D5: ='[2]General information '!D36 -> 30 | E5: ='[2]General information '!E36 -> 0.76 | F5: ='[2]General information '!F36 -> 0 | G5: ='[2]General information '!G36 -> 0 | H5: ='[2]General information '!H36 -> 0 | I5: ='[2]General information '!I36 -> 0 | ... O5: ='[2]General information '!O36 -> 0
A6: =ELEC!C3 -> 44136 | B6: 25 | C6: 21 | D6: =(C6+B6)/2 -> 23 | E6: 0.73 | F6: 0 | G6: =F6*230 -> 0 | K6: =+J6+H6 -> 0
A7: =ELEC!C4 -> 44137 | B7: 26 | C7: 21 | D7: =(C7+B7)/2 -> 23.5 | E7: 0.67 | F7: 0 | G7: =F7*230 -> 0 | I7: 0 | J7: 0 | K7: =+J7+H7 -> 0
A8: =ELEC!C5 -> 44138 | B8: 26 | C8: 22 | D8: =(C8+B8)/2 -> 24 | E8: 0.61 | F8: 0 | G8: =F8*230 -> 0 | K8: =+J8+H8 -> 0
A9: =ELEC!C6 -> 44139 | B9: 22 | C9: 19 | D9: =(C9+B9)/2 -> 20.5 | E9: 0.66 | F9: 0 | G9: =F9*230 -> 0 | K9: =+J9+H9 -> 0
A10: =ELEC!C7 -> 44140 | B10: 22 | C10: 17 | D10: =(C10+B10)/2 -> 19.5 | E10: 0.67 | F10: 0 | G10: =F10*230 -> 0 | K10: =+J10+H10 -> 0
A11: =ELEC!C8 -> 44141 | B11: 22 | C11: 18 | D11: =(C11+B11)/2 -> 20 | E11: 0.6 | F11: 0 | G11: =F11*230 -> 0 | H11: 0 | I11: 0 | J11: 0 | K11: =+J11+H11 -> 0
A12: =ELEC!C9 -> 44142 | B12: 23 | C12: 18 | D12: =(C12+B12)/2 -> 20.5 | E12: 0.62 | F12: 0 | G12: =F12*230 -> 0 | H12: 0 | I12: 0 | J12: 0 | K12: =+J12+H12 -> 0
A13: =ELEC!C10 -> 44143 | B13: 27 | C13: 21 | D13: =(C13+B13)/2 -> 24 | E13: 0.45 | F13: 0 | G13: =F13*230 -> 0 | K13: =+J13+H13 -> 0
A14: =ELEC!C11 -> 44144 | B14: 27 | C14: 22 | D14: =(C14+B14)/2 -> 24.5 | E14: 0.45 | F14: 0 | G14: =F14*230 -> 0 | K14: =+J14+H14 -> 0
A15: =ELEC!C12 -> 44145 | B15: 25 | C15: 21 | D15: =(C15+B15)/2 -> 23 | E15: 0.53 | F15: 0 | G15: =F15*230 -> 0 | K15: =+J15+H15 -> 0
A16: =ELEC!C13 -> 44146 | B16: 25 | C16: 20 | D16: =(C16+B16)/2 -> 22.5 | E16: 0.6 | F16: 0 | G16: =F16*230 -> 0 | K16: =+J16+H16 -> 0
A17: =ELEC!C14 -> 44147 | B17: 25 | C17: 20 | D17: =(C17+B17)/2 -> 22.5 | E17: 0.45 | F17: 0 | G17: =F17*230 -> 0 | K17: =+J17+H17 -> 0
A18: =ELEC!C15 -> 44148 | B18: 25 | C18: 21 | D18: =(C18+B18)/2 -> 23 | E18: 0.5 | F18: 0 | G18: =F18*230 -> 0 | H18: 0 | I18: 0 | J18: 0 | K18: =+J18+H18 -> 0
A19: =ELEC!C16 -> 44149 | B19: 25 | C19: 21 | D19: =(C19+B19)/2 -> 23 | E19: 0.6 | F19: 0 | G19: 0 | K19: =+J19+H19 -> 0
A20: =ELEC!C17 -> 44150 | B20: 22 | C20: 17 | D20: =(C20+B20)/2 -> 19.5 | E20: 0.5 | F20: 0 | G20: =F20*230 -> 0 | K20: =+J20+H20 -> 0
A21: =ELEC!C18 -> 44151 | B21: 22 | C21: 16 | D21: =(C21+B21)/2 -> 19 | E21: 0.5 | F21: 0 | G21: =F21*230 -> 0 | K21: =+J21+H21 -> 0
A22: =ELEC!C19 -> 44152 | B22: 21 | C22: 15 | D22: =(C22+B22)/2 -> 18 | E22: 0.52 | F22: 0 | G22: =F22*230 -> 0 | K22: =+J22+H22 -> 0
A23: =ELEC!C20 -> 44153 | B23: 21 | C23: 15 | D23: =(C23+B23)/2 -> 18 | E23: 0.55 | F23: 0 | G23: =F23*230 -> 0 | K23: =+J23+H23 -> 0
A24: =ELEC!C21 -> 44154 | B24: 21 | C24: 16 | D24: =(C24+B24)/2 -> 18.5 | E24: 0.55 | F24: 0 | G24: =F24*230 -> 0 | H24: 0 | I24: 0 | J24: 0 | K24: =+J24+H24 -> 0
A25: =ELEC!C22 -> 44155 | B25: 19 | C25: 15 | D25: =(C25+B25)/2 -> 17 | E25: 0.73 | F25: 0 | G25: =F25*230 -> 0 | K25: =+J25+H25 -> 0
A26: =ELEC!C23 -> 44156 | B26: 19 | C26: 15 | D26: =(C26+B26)/2 -> 17 | E26: 0.65 | F26: 0 | G26: =F26*230 -> 0 | K26: =+J26+H26 -> 0
A27: =ELEC!C24 -> 44157 | B27: 19 | C27: 16 | D27: =(C27+B27)/2 -> 17.5 | E27: 0.65 | F27: 0 | G27: =F27*230 -> 0 | K27: =+J27+H27+I27 -> 0
A28: =ELEC!C25 -> 44158 | B28: 20 | C28: 15 | D28: =(C28+B28)/2 -> 17.5 | E28: 0.6 | F28: 0 | G28: =F28*230 -> 0 | K28: =+J28+H28+I28 -> 0
A29: =ELEC!C26 -> 44159 | B29: 19 | C29: 15 | D29: =(C29+B29)/2 -> 17 | E29: 0.6 | F29: 0 | G29: =F29*230 -> 0 | K29: =+J29+H29+I29 -> 0
A30: =ELEC!C27 -> 44160 | B30: 18 | C30: 15 | D30: =(C30+B30)/2 -> 16.5 | E30: 0.63 | F30: 0 | G30: =F30*230 -> 0 | K30: =+J30+H30+I30 -> 0
A31: =ELEC!C28 -> 44161 | B31: 18 | C31: 15 | D31: =(C31+B31)/2 -> 16.5 | E31: 0.6 | F31: 0 | G31: =F31*230 -> 0 | K31: =+J31+H31+I31 -> 0
A32: =ELEC!C29 -> 44162 | D32: =(C32+B32)/2 -> 0 | G32: =F32*230 -> 0 | K32: =+J32+H32+I32 -> 0
A33: =ELEC!C30 -> 44163 | D33: =(C33+B33)/2 -> 0 | G33: =F33*230 -> 0 | K33: =+J33+H33+I33 -> 0
A34: =ELEC!C31 -> 44164 | D34: =(C34+B34)/2 -> 0 | G34: =F34*230 -> 0 | K34: =+J34+H34+I34 -> 0
A35: =ELEC!C32 -> 44165 | D35: =(C35+B35)/2 -> 0 | G35: =F35*230 -> 0 | K35: =+J35+H35+I35 -> 0
A36: =ELEC!C33 -> 44166 | D36: =(C36+B36)/2 -> 0 | G36: =F36*230 -> 0 | K36: =+J36+H36+I36 -> 0
F37: =AVERAGE(F6:F35) -> 0 | G37: =SUM(G6:G35) -> 0
D38: =SUM(D6:D35)/'EDl log'!A35 -> 20.211538
I41: http://www.accuweather.com/en/lb/lebanon-weather

Sheet tanks
B2: Tank 1 | D2: Tank 2 | F2: Tank 3 | H2: Tank 4 | J2: Tank 5 | L2: Tank 6 | N2: Tank 7 | P2: Tank 8 | R2: Tank 9 | T2: Tank 10 | V2: Tank 11 | Z2: Tank 1 | AB2: Tank 2 | AD2: Tank 3 | AF2: Tank 4 | AH2: Tank 5 | AJ2: Tank 6 | AL2: Tank 7
B3: 6670 | D3: =SUM(B3) -> 6670 | F3: =SUM(D3) -> 6670 | H3: =SUM(F3) -> 6670 | J3: =SUM(H3) -> 6670 | L3: =SUM(J3) -> 6670 | N3: =SUM(L3) -> 6670 | P3: =SUM(N3) -> 6670 | R3: =SUM(P3) -> 6670 | T3: =SUM(R3) -> 6670 | V3: =SUM(T3) -> 6670 | W3: =SUM(B3:V3) -> 73370 | Z3: 2800 | AB3: 2800 | AD3: 2800 | AF3: 2800 | AH3: 2800 | AJ3: 2800 | AL3: 2800 | AM3: =SUM(Z3:AL3) -> 19600 | AO3: =SUM(AM3+W3) -> 92970 | AR3: Total sotck | AS3: Diesel Cons Per day | AT3: Diesel Delivery | BE3: Genset Co | BF3: Steam | BG3: Boil | BH3: Outdoor temperature
B4: =B3/310 -> 21.516129 | D4: =SUM(B4) -> 21.516129 | F4: =SUM(D4) -> 21.516129 | H4: =SUM(F4) -> 21.516129 | J4: =SUM(H4) -> 21.516129 | L4: =SUM(J4) -> 21.516129 | N4: =SUM(L4) -> 21.516129 | P4: =SUM(N4) -> 21.516129 | R4: =SUM(P4) -> 21.516129 | T4: =SUM(R4) -> 21.516129 | V4: =SUM(T4) -> 21.516129 | Z4: =Z3/280 -> 10 | AA4: =AA3/280 -> 0 | AB4: =AB3/280 -> 10 | AC4: =AC3/280 -> 0 | AD4: =AD3/280 -> 10 | AE4: =AE3/280 -> 0 | AF4: =AF3/280 -> 10 | AG4: =AG3/280 -> 0 | ... AL4: =AL3/280 -> 10 | AT4: Delivery | AU4: Cost /L | AW4: Boiler+Steam | AX4: Generator | AZ4: Occupancy | BA4: AVE TEPM | BB4: AVE Humidity
A5: =ELEC!C2 -> 44135 | B5: =[1]tanks!B36 -> 243 | C5: =[1]tanks!C36 -> 5228.4194 | D5: =[1]tanks!D36 -> 243 | E5: =[1]tanks!E36 -> 5228.4194 | F5: =[1]tanks!F36 -> 243 | G5: =[1]tanks!G36 -> 5228.4194 | H5: =[1]tanks!H36 -> 243 | I5: =[1]tanks!I36 -> 5228.4194 | ... BB5: =[1]tanks!BB36 -> 0.25 | BC5: =[3]tanks!BC35 -> 0 | BD5: =[3]tanks!BD35 -> 19222 | BE5: =[3]tanks!BE35 -> #REF! | BF5: =[3]tanks!BF35 -> 0 | BG5: =[3]tanks!BG35 -> #REF! | BH5: =[4]tanks!BH36 -> 0
A6: =ELEC!C3 -> 44136 | B6: ='B5'!B5 -> 241 | C6: =B6*$B$4 -> 5185.3871 | D6: =SUM(B6) -> 241 | E6: =D6*$B$4 -> 5185.3871 | F6: =SUM(D6) -> 241 | G6: =F6*$B$4 -> 5185.3871 | H6: =SUM(F6) -> 241 | I6: =H6*$B$4 -> 5185.3871 | J6: =SUM(H6) -> 241 | K6: =J6*$B$4 -> 5185.3871 | L6: =SUM(J6) -> 241 | M6: =L6*$B$4 -> 5185.3871 | N6: =SUM(L6) -> 241 | O6: =N6*$B$4 -> 5185.3871 | P6: =SUM(N6) -> 241 | Q6: =P6*$B$4 -> 5185.3871 | R6: =SUM(P6) -> 241 | S6: =R6*$B$4 -> 5185.3871 | T6: =SUM(R6) -> 241 | U6: =T6*$B$4 -> 5185.3871 | V6: =SUM(T6) -> 241 | W6: =V6*$B$4 -> 5185.3871 | X6: =SUM(Y6/73370) -> 0.77741935 | Y6: =SUM(C6+E6+G6+I6+K6+M6+O6+Q6+S6+U6+W6) -> 57039.258 | Z6: ='B5'!C5 -> 247 | AA6: =SUM(Z6*$Z$4) -> 2470 | AB6: =SUM(Z6) -> 247 | AC6: =SUM(AB6*$Z$4) -> 2470 | AD6: =SUM(AB6) -> 247 | AE6: =SUM(AD6*$Z$4) -> 2470 | AF6: =SUM(AD6) -> 247 | AG6: =SUM(AF6*$Z$4) -> 2470 | AH6: =SUM(AF6) -> 247 | AI6: =SUM(AH6*$Z$4) -> 2470 | AJ6: =SUM(AH6) -> 247 | AK6: =SUM(AJ6*$Z$4) -> 2470 | AL6: =SUM(AJ6) -> 247 | AM6: =SUM(AL6*$Z$4) -> 2470 | AN6: =SUM(AO6/19600) -> 0.88214286 | AO6: =SUM(AA6+AC6+AE6+AG6+AI6+AK6+AM6) -> 17290 | AQ6: =SUM(AR6/92970) -> 0.79949724 | AR6: =SUM(AO6+Y6) -> 74329.258 | AS6: =SUM(AR6-AR5-AT6) -> -613.35484 | AV6: =IF(AT6>0,AU6,AV5) -> 0.5 | AW6: =-SUM('B5'!AI5) -> -205 | AX6: =-SUM(AW6-AS6) -> -408.35484 | AY6: =SUM(AX6+AW6) -> -613.35484 | AZ6: =ELEC!A3 -> 0 | BA6: ='General information '!D6 -> 23 | BB6: =SUM('General information '!E6) -> 0.73 | BC6: =IF(AR3>=AR6,0,1) -> 0 | BD6: 19222 | BE6: =(305/1185)*ELEC!Q4 -> 0 | BG6: =#REF!-BE6 -> #REF! | BH6: 21
A7: =ELEC!C4 -> 44137 | B7: ='B5'!B6 -> 239.2 | C7: =B7*$B$4 -> 5146.6581 | D7: =SUM(B7) -> 239.2 | E7: =D7*$B$4 -> 5146.6581 | F7: =SUM(D7) -> 239.2 | G7: =F7*$B$4 -> 5146.6581 | H7: =SUM(F7) -> 239.2 | I7: =H7*$B$4 -> 5146.6581 | J7: =SUM(H7) -> 239.2 | K7: =J7*$B$4 -> 5146.6581 | L7: =SUM(J7) -> 239.2 | M7: =L7*$B$4 -> 5146.6581 | N7: =SUM(L7) -> 239.2 | O7: =N7*$B$4 -> 5146.6581 | P7: =SUM(N7) -> 239.2 | Q7: =P7*$B$4 -> 5146.6581 | R7: =SUM(P7) -> 239.2 | S7: =R7*$B$4 -> 5146.6581 | T7: =SUM(R7) -> 239.2 | U7: =T7*$B$4 -> 5146.6581 | V7: =SUM(T7) -> 239.2 | W7: =V7*$B$4 -> 5146.6581 | X7: =SUM(Y7/73370) -> 0.7716129 | Y7: =SUM(C7+E7+G7+I7+K7+M7+O7+Q7+S7+U7+W7) -> 56613.239 | Z7: ='B5'!C6 -> 246 | AA7: =SUM(Z7*$Z$4) -> 2460 | AB7: =SUM(Z7) -> 246 | AC7: =SUM(AB7*$Z$4) -> 2460 | AD7: =SUM(AB7) -> 246 | AE7: =SUM(AD7*$Z$4) -> 2460 | AF7: =SUM(AD7) -> 246 | AG7: =SUM(AF7*$Z$4) -> 2460 | AH7: =SUM(AF7) -> 246 | AI7: =SUM(AH7*$Z$4) -> 2460 | AJ7: =SUM(AH7) -> 246 | AK7: =SUM(AJ7*$Z$4) -> 2460 | AL7: =SUM(AJ7) -> 246 | AM7: =SUM(AL7*$Z$4) -> 2460 | AN7: =SUM(AO7/19600) -> 0.87857143 | AO7: =SUM(AA7+AC7+AE7+AG7+AI7+AK7+AM7) -> 17220 | AQ7: =SUM(AR7/92970) -> 0.79416197 | AR7: =SUM(AO7+Y7) -> 73833.239 | AS7: =SUM(AR7-AR6-AT7) -> -496.01935 | AV7: =IF(AT7>0,AU7,AV6) -> 0.5 | AW7: =-SUM('B5'!AI6) -> -97 | AX7: =-SUM(AW7-AS7) -> -399.01935 | AY7: =SUM(AX7+AW7) -> -496.01935 | AZ7: =ELEC!A4 -> 0 | BA7: ='General information '!D7 -> 23.5 | BB7: =SUM('General information '!E7) -> 0.67 | BC7: 0 | BD7: 19222 | BE7: =(305/1185)*ELEC!Q5 -> 514.76793 | BG7: =#REF!-BE7 -> #REF! | BH7: 19
A8: =ELEC!C5 -> 44138 | B8: ='B5'!B7 -> 237 | C8: =B8*$B$4 -> 5099.3226 | D8: =SUM(B8) -> 237 | E8: =D8*$B$4 -> 5099.3226 | F8: =SUM(D8) -> 237 | G8: =F8*$B$4 -> 5099.3226 | H8: =SUM(F8) -> 237 | I8: =H8*$B$4 -> 5099.3226 | J8: =SUM(H8) -> 237 | K8: =J8*$B$4 -> 5099.3226 | L8: =SUM(J8) -> 237 | M8: =L8*$B$4 -> 5099.3226 | N8: =SUM(L8) -> 237 | O8: =N8*$B$4 -> 5099.3226 | P8: =SUM(N8) -> 237 | Q8: =P8*$B$4 -> 5099.3226 | R8: =SUM(P8) -> 237 | S8: =R8*$B$4 -> 5099.3226 | T8: =SUM(R8) -> 237 | U8: =T8*$B$4 -> 5099.3226 | V8: =SUM(T8) -> 237 | W8: =V8*$B$4 -> 5099.3226 | X8: =SUM(Y8/73370) -> 0.76451613 | Y8: =SUM(C8+E8+G8+I8+K8+M8+O8+Q8+S8+U8+W8) -> 56092.548 | Z8: ='B5'!C7 -> 243 | AA8: =SUM(Z8*$Z$4) -> 2430 | AB8: =SUM(Z8) -> 243 | AC8: =SUM(AB8*$Z$4) -> 2430 | AD8: =SUM(AB8) -> 243 | AE8: =SUM(AD8*$Z$4) -> 2430 | AF8: =SUM(AD8) -> 243 | AG8: =SUM(AF8*$Z$4) -> 2430 | AH8: =SUM(AF8) -> 243 | AI8: =SUM(AH8*$Z$4) -> 2430 | AJ8: =SUM(AH8) -> 243 | AK8: =SUM(AJ8*$Z$4) -> 2430 | AL8: =SUM(AJ8) -> 243 | AM8: =SUM(AL8*$Z$4) -> 2430 | AN8: =SUM(AO8/19600) -> 0.86785714 | AO8: =SUM(AA8+AC8+AE8+AG8+AI8+AK8+AM8) -> 17010 | AQ8: =SUM(AR8/92970) -> 0.78630255 | AR8: =SUM(AO8+Y8) -> 73102.548 | AS8: =SUM(AR8-AR7-AT8) -> -730.69032 | AV8: =IF(AT8>0,AU8,AV7) -> 0.5 | AW8: =-SUM('B5'!AI7) -> 0 | AX8: =-SUM(AW8-AS8) -> -730.69032 | AY8: =SUM(AX8+AW8) -> -730.69032 | AZ8: =ELEC!A5 -> 0 | BA8: ='General information '!D8 -> 24 | BB8: =SUM('General information '!E8) -> 0.61 | BC8: =IF(AR7>=AR8,0,1) -> 0 | BD8: 19222 | BE8: =(305/1185)*ELEC!Q6 -> 514.76793 | BG8: =#REF!-BE8 -> #REF! | BH8: 16
A9: =ELEC!C6 -> 44139 | B9: ='B5'!B8 -> 234 | C9: =B9*$B$4 -> 5034.7742 | D9: =SUM(B9) -> 234 | E9: =D9*$B$4 -> 5034.7742 | F9: =SUM(D9) -> 234 | G9: =F9*$B$4 -> 5034.7742 | H9: =SUM(F9) -> 234 | I9: =H9*$B$4 -> 5034.7742 | J9: =SUM(H9) -> 234 | K9: =J9*$B$4 -> 5034.7742 | L9: =SUM(J9) -> 234 | M9: =L9*$B$4 -> 5034.7742 | N9: =SUM(L9) -> 234 | O9: =N9*$B$4 -> 5034.7742 | P9: =SUM(N9) -> 234 | Q9: =P9*$B$4 -> 5034.7742 | R9: =SUM(P9) -> 234 | S9: =R9*$B$4 -> 5034.7742 | T9: =SUM(R9) -> 234 | U9: =T9*$B$4 -> 5034.7742 | V9: =SUM(T9) -> 234 | W9: =V9*$B$4 -> 5034.7742 | X9: =SUM(Y9/73370) -> 0.75483871 | Y9: =SUM(C9+E9+G9+I9+K9+M9+O9+Q9+S9+U9+W9) -> 55382.516 | Z9: ='B5'!C8 -> 240 | AA9: =SUM(Z9*$Z$4) -> 2400 | AB9: =SUM(Z9) -> 240 | AC9: =SUM(AB9*$Z$4) -> 2400 | AD9: =SUM(AB9) -> 240 | AE9: =SUM(AD9*$Z$4) -> 2400 | AF9: =SUM(AD9) -> 240 | AG9: =SUM(AF9*$Z$4) -> 2400 | AH9: =SUM(AF9) -> 240 | AI9: =SUM(AH9*$Z$4) -> 2400 | AJ9: =SUM(AH9) -> 240 | AK9: =SUM(AJ9*$Z$4) -> 2400 | AL9: =SUM(AJ9) -> 240 | AM9: =SUM(AL9*$Z$4) -> 2400 | AN9: =SUM(AO9/19600) -> 0.85714286 | AO9: =SUM(AA9+AC9+AE9+AG9+AI9+AK9+AM9) -> 16800 | AQ9: =SUM(AR9/92970) -> 0.77640654 | AR9: =SUM(AO9+Y9) -> 72182.516 | AS9: =SUM(AR9-AR8-AT9) -> -920.03226 | AV9: =IF(AT9>0,AU9,AV8) -> 0.5 | AW9: =-SUM('B5'!AI8) -> 0 | AX9: =-SUM(AW9-AS9) -> -920.03226 | AY9: =SUM(AX9+AW9) -> -920.03226 | AZ9: =ELEC!A6 -> 0 | BA9: ='General information '!D9 -> 20.5 | BB9: =SUM('General information '!E9) -> 0.66 | BC9: =IF(AR8>=AR9,0,1) -> 0 | BD9: 19222 | BE9: =(305/1185)*ELEC!Q7 -> 257.38397 | BG9: =#REF!-BE9 -> #REF! | BH9: 18
A10: =ELEC!C7 -> 44140 | B10: ='B5'!B9 -> 231 | C10: =B10*$B$4 -> 4970.2258 | D10: =SUM(B10) -> 231 | E10: =D10*$B$4 -> 4970.2258 | F10: =SUM(D10) -> 231 | G10: =F10*$B$4 -> 4970.2258 | H10: =SUM(F10) -> 231 | I10: =H10*$B$4 -> 4970.2258 | J10: =SUM(H10) -> 231 | K10: =J10*$B$4 -> 4970.2258 | L10: =SUM(J10) -> 231 | M10: =L10*$B$4 -> 4970.2258 | N10: =SUM(L10) -> 231 | O10: =N10*$B$4 -> 4970.2258 | P10: =SUM(N10) -> 231 | Q10: =P10*$B$4 -> 4970.2258 | R10: =SUM(P10) -> 231 | S10: =R10*$B$4 -> 4970.2258 | T10: =SUM(R10) -> 231 | U10: =T10*$B$4 -> 4970.2258 | V10: =SUM(T10) -> 231 | W10: =V10*$B$4 -> 4970.2258 | X10: =SUM(Y10/73370) -> 0.74516129 | Y10: =SUM(C10+E10+G10+I10+K10+M10+O10+Q10+S10+U10+W10) -> 54672.484 | Z10: ='B5'!C9 -> 238 | AA10: =SUM(Z10*$Z$4) -> 2380 | AB10: =SUM(Z10) -> 238 | AC10: =SUM(AB10*$Z$4) -> 2380 | AD10: =SUM(AB10) -> 238 | AE10: =SUM(AD10*$Z$4) -> 2380 | AF10: =SUM(AD10) -> 238 | AG10: =SUM(AF10*$Z$4) -> 2380 | AH10: =SUM(AF10) -> 238 | AI10: =SUM(AH10*$Z$4) -> 2380 | AJ10: =SUM(AH10) -> 238 | AK10: =SUM(AJ10*$Z$4) -> 2380 | AL10: =SUM(AJ10) -> 238 | AM10: =SUM(AL10*$Z$4) -> 2380 | AN10: =SUM(AO10/19600) -> 0.85 | AO10: =SUM(AA10+AC10+AE10+AG10+AI10+AK10+AM10) -> 16660 | AQ10: =SUM(AR10/92970) -> 0.76726346 | AR10: =SUM(AO10+Y10) -> 71332.484 | AS10: =SUM(AR10-AR9-AT10) -> -850.03226 | AV10: =IF(AT10>0,AU10,AV9) -> 0.5 | AW10: =-SUM('B5'!AI9) -> 0 | AX10: =-SUM(AW10-AS10) -> -850.03226 | AY10: =SUM(AX10+AW10) -> -850.03226 | AZ10: =ELEC!A7 -> 0 | BA10: ='General information '!D10 -> 19.5 | BB10: =SUM('General information '!E10) -> 0.67 | BC10: =IF(AR9>=AR10,0,1) -> 0 | BD10: 19222 | BE10: =(305/1185)*ELEC!Q8 -> 514.76793 | BG10: =#REF!-BE10 -> #REF! | BH10: 16
A11: =ELEC!C8 -> 44141 | B11: ='B5'!B10 -> 229 | C11: =B11*$B$4 -> 4927.1935 | D11: =SUM(B11) -> 229 | E11: =D11*$B$4 -> 4927.1935 | F11: =SUM(D11) -> 229 | G11: =F11*$B$4 -> 4927.1935 | H11: =SUM(F11) -> 229 | I11: =H11*$B$4 -> 4927.1935 | J11: =SUM(H11) -> 229 | K11: =J11*$B$4 -> 4927.1935 | L11: =SUM(J11) -> 229 | M11: =L11*$B$4 -> 4927.1935 | N11: =SUM(L11) -> 229 | O11: =N11*$B$4 -> 4927.1935 | P11: =SUM(N11) -> 229 | Q11: =P11*$B$4 -> 4927.1935 | R11: =SUM(P11) -> 229 | S11: =R11*$B$4 -> 4927.1935 | T11: =SUM(R11) -> 229 | U11: =T11*$B$4 -> 4927.1935 | V11: =SUM(T11) -> 229 | W11: =V11*$B$4 -> 4927.1935 | X11: =SUM(Y11/73370) -> 0.73870968 | Y11: =SUM(C11+E11+G11+I11+K11+M11+O11+Q11+S11+U11+W11) -> 54199.129 | Z11: ='B5'!C10 -> 235 | AA11: =SUM(Z11*$Z$4) -> 2350 | AB11: =SUM(Z11) -> 235 | AC11: =SUM(AB11*$Z$4) -> 2350 | AD11: =SUM(AB11) -> 235 | AE11: =SUM(AD11*$Z$4) -> 2350 | AF11: =SUM(AD11) -> 235 | AG11: =SUM(AF11*$Z$4) -> 2350 | AH11: =SUM(AF11) -> 235 | AI11: =SUM(AH11*$Z$4) -> 2350 | AJ11: =SUM(AH11) -> 235 | AK11: =SUM(AJ11*$Z$4) -> 2350 | AL11: =SUM(AJ11) -> 235 | AM11: =SUM(AL11*$Z$4) -> 2350 | AN11: =SUM(AO11/19600) -> 0.83928571 | AO11: =SUM(AA11+AC11+AE11+AG11+AI11+AK11+AM11) -> 16450 | AQ11: =SUM(AR11/92970) -> 0.75991319 | AR11: =SUM(AO11+Y11) -> 70649.129 | AS11: =SUM(AR11-AR10-AT11) -> -683.35484 | AV11: =IF(AT11>0,AU11,AV10) -> 0.5 | AW11: =-SUM('B5'!AI10) -> 0 | AX11: =-SUM(AW11-AS11) -> -683.35484 | AY11: =SUM(AX11+AW11) -> -683.35484 | AZ11: =ELEC!A8 -> 0 | BA11: ='General information '!D11 -> 20 | BB11: =SUM('General information '!E11) -> 0.6 | BC11: =IF(AR10>=AR11,0,1) -> 0 | BD11: 19222 | BE11: =(305/1185)*ELEC!Q9 -> 0 | BG11: =#REF!-BE11 -> #REF! | BH11: 16.5
A12: =ELEC!C9 -> 44142 | B12: ='B5'!B11 -> 227 | C12: =B12*$B$4 -> 4884.1613 | D12: =SUM(B12) -> 227 | E12: =D12*$B$4 -> 4884.1613 | F12: =SUM(D12) -> 227 | G12: =F12*$B$4 -> 4884.1613 | H12: =SUM(F12) -> 227 | I12: =H12*$B$4 -> 4884.1613 | J12: =SUM(H12) -> 227 | K12: =J12*$B$4 -> 4884.1613 | L12: =SUM(J12) -> 227 | M12: =L12*$B$4 -> 4884.1613 | N12: =SUM(L12) -> 227 | O12: =N12*$B$4 -> 4884.1613 | P12: =SUM(N12) -> 227 | Q12: =P12*$B$4 -> 4884.1613 | R12: =SUM(P12) -> 227 | S12: =R12*$B$4 -> 4884.1613 | T12: =SUM(R12) -> 227 | U12: =T12*$B$4 -> 4884.1613 | V12: =SUM(T12) -> 227 | W12: =V12*$B$4 -> 4884.1613 | X12: =SUM(Y12/73370) -> 0.73225806 | Y12: =SUM(C12+E12+G12+I12+K12+M12+O12+Q12+S12+U12+W12) -> 53725.774 | Z12: ='B5'!C11 -> 234 | AA12: =SUM(Z12*$Z$4) -> 2340 | AB12: =SUM(Z12) -> 234 | AC12: =SUM(AB12*$Z$4) -> 2340 | AD12: =SUM(AB12) -> 234 | AE12: =SUM(AD12*$Z$4) -> 2340 | AF12: =SUM(AD12) -> 234 | AG12: =SUM(AF12*$Z$4) -> 2340 | AH12: =SUM(AF12) -> 234 | AI12: =SUM(AH12*$Z$4) -> 2340 | AJ12: =SUM(AH12) -> 234 | AK12: =SUM(AJ12*$Z$4) -> 2340 | AL12: =SUM(AJ12) -> 234 | AM12: =SUM(AL12*$Z$4) -> 2340 | AN12: =SUM(AO12/19600) -> 0.83571429 | AO12: =SUM(AA12+AC12+AE12+AG12+AI12+AK12+AM12) -> 16380 | AQ12: =SUM(AR12/92970) -> 0.75406878 | AR12: =SUM(AO12+Y12) -> 70105.774 | AS12: =SUM(AR12-AR11-AT12) -> -543.35484 | AV12: =IF(AT12>0,AU12,AV11) -> 0.5 | AW12: =-SUM('B5'!AI11) -> -238 | AX12: =-SUM(AW12-AS12) -> -305.35484 | AY12: =SUM(AX12+AW12) -> -543.35484 | AZ12: =ELEC!A9 -> 0 | BA12: ='General information '!D12 -> 20.5 | BB12: =SUM('General information '!E12) -> 0.62 | BC12: =IF(AR11>=AR12,0,1) -> 0 | BD12: 19222 | BE12: =(305/1185)*ELEC!Q10 -> 514.76793 | BG12: =#REF!-BE12 -> #REF! | BH12: 15.5
A13: =ELEC!C10 -> 44143 | B13: ='B5'!B12 -> 225 | C13: =B13*$B$4 -> 4841.129 | D13: =SUM(B13) -> 225 | E13: =D13*$B$4 -> 4841.129 | F13: =SUM(D13) -> 225 | G13: =F13*$B$4 -> 4841.129 | H13: =SUM(F13) -> 225 | I13: =H13*$B$4 -> 4841.129 | J13: =SUM(H13) -> 225 | K13: =J13*$B$4 -> 4841.129 | L13: =SUM(J13) -> 225 | M13: =L13*$B$4 -> 4841.129 | N13: =SUM(L13) -> 225 | O13: =N13*$B$4 -> 4841.129 | P13: =SUM(N13) -> 225 | Q13: =P13*$B$4 -> 4841.129 | R13: =SUM(P13) -> 225 | S13: =R13*$B$4 -> 4841.129 | T13: =SUM(R13) -> 225 | U13: =T13*$B$4 -> 4841.129 | V13: =SUM(T13) -> 225 | W13: =V13*$B$4 -> 4841.129 | X13: =SUM(Y13/73370) -> 0.72580645 | Y13: =SUM(C13+E13+G13+I13+K13+M13+O13+Q13+S13+U13+W13) -> 53252.419 | Z13: ='B5'!C12 -> 231 | AA13: =SUM(Z13*$Z$4) -> 2310 | AB13: =SUM(Z13) -> 231 | AC13: =SUM(AB13*$Z$4) -> 2310 | AD13: =SUM(AB13) -> 231 | AE13: =SUM(AD13*$Z$4) -> 2310 | AF13: =SUM(AD13) -> 231 | AG13: =SUM(AF13*$Z$4) -> 2310 | AH13: =SUM(AF13) -> 231 | AI13: =SUM(AH13*$Z$4) -> 2310 | AJ13: =SUM(AH13) -> 231 | AK13: =SUM(AJ13*$Z$4) -> 2310 | AL13: =SUM(AJ13) -> 231 | AM13: =SUM(AL13*$Z$4) -> 2310 | AN13: =SUM(AO13/19600) -> 0.825 | AO13: =SUM(AA13+AC13+AE13+AG13+AI13+AK13+AM13) -> 16170 | AQ13: =SUM(AR13/92970) -> 0.7467185 | AR13: =SUM(AO13+Y13) -> 69422.419 | AS13: =SUM(AR13-AR12-AT13) -> -683.35484 | AV13: =IF(AT13>0,AU13,AV12) -> 0.5 | AW13: =-SUM('B5'!AI12) -> -162 | AX13: =-SUM(AW13-AS13) -> -521.35484 | AY13: =SUM(AX13+AW13) -> -683.35484 | AZ13: =ELEC!A10 -> 0 | BA13: ='General information '!D13 -> 24 | BB13: =SUM('General information '!E13) -> 0.45 | BC13: =IF(AR12>=AR13,0,1) -> 0 | BD13: 19222 | BE13: =(305/1185)*ELEC!Q11 -> 257.38397 | BG13: =#REF!-BE13 -> #REF!
A14: =ELEC!C11 -> 44144 | B14: ='B5'!B13 -> 223 | C14: =B14*$B$4 -> 4798.0968 | D14: =SUM(B14) -> 223 | E14: =D14*$B$4 -> 4798.0968 | F14: =SUM(D14) -> 223 | G14: =F14*$B$4 -> 4798.0968 | H14: =SUM(F14) -> 223 | I14: =H14*$B$4 -> 4798.0968 | J14: =SUM(H14) -> 223 | K14: =J14*$B$4 -> 4798.0968 | L14: =SUM(J14) -> 223 | M14: =L14*$B$4 -> 4798.0968 | N14: =SUM(L14) -> 223 | O14: =N14*$B$4 -> 4798.0968 | P14: =SUM(N14) -> 223 | Q14: =P14*$B$4 -> 4798.0968 | R14: =SUM(P14) -> 223 | S14: =R14*$B$4 -> 4798.0968 | T14: =SUM(R14) -> 223 | U14: =T14*$B$4 -> 4798.0968 | V14: =SUM(T14) -> 223 | W14: =V14*$B$4 -> 4798.0968 | X14: =SUM(Y14/73370) -> 0.71935484 | Y14: =SUM(C14+E14+G14+I14+K14+M14+O14+Q14+S14+U14+W14) -> 52779.065 | Z14: ='B5'!C13 -> 230 | AA14: =SUM(Z14*$Z$4) -> 2300 | AB14: =SUM(Z14) -> 230 | AC14: =SUM(AB14*$Z$4) -> 2300 | AD14: =SUM(AB14) -> 230 | AE14: =SUM(AD14*$Z$4) -> 2300 | AF14: =SUM(AD14) -> 230 | AG14: =SUM(AF14*$Z$4) -> 2300 | AH14: =SUM(AF14) -> 230 | AI14: =SUM(AH14*$Z$4) -> 2300 | AJ14: =SUM(AH14) -> 230 | AK14: =SUM(AJ14*$Z$4) -> 2300 | AL14: =SUM(AJ14) -> 230 | AM14: =SUM(AL14*$Z$4) -> 2300 | AN14: =SUM(AO14/19600) -> 0.82142857 | AO14: =SUM(AA14+AC14+AE14+AG14+AI14+AK14+AM14) -> 16100 | AQ14: =SUM(AR14/92970) -> 0.74087409 | AR14: =SUM(AO14+Y14) -> 68879.065 | AS14: =SUM(AR14-AR13-AT14) -> -543.35484 | AV14: =IF(AT14>0,AU14,AV13) -> 0.5 | AW14: =-SUM('B5'!AI13) -> -137 | AX14: =-SUM(AW14-AS14) -> -406.35484 | AY14: =SUM(AX14+AW14) -> -543.35484 | AZ14: =ELEC!A11 -> 0 | BA14: ='General information '!D14 -> 24.5 | BB14: =SUM('General information '!E14) -> 0.45 | BC14: =IF(AR13>=AR14,0,1) -> 0 | BD14: 19222 | BE14: =(305/1185)*ELEC!Q12 -> 257.38397 | BG14: =#REF!-BE14 -> #REF!
A15: =ELEC!C12 -> 44145 | B15: ='B5'!B14 -> 221 | C15: =B15*$B$4 -> 4755.0645 | D15: =SUM(B15) -> 221 | E15: =D15*$B$4 -> 4755.0645 | F15: =SUM(D15) -> 221 | G15: =F15*$B$4 -> 4755.0645 | H15: =SUM(F15) -> 221 | I15: =H15*$B$4 -> 4755.0645 | J15: =SUM(H15) -> 221 | K15: =J15*$B$4 -> 4755.0645 | L15: =SUM(J15) -> 221 | M15: =L15*$B$4 -> 4755.0645 | N15: =SUM(L15) -> 221 | O15: =N15*$B$4 -> 4755.0645 | P15: =SUM(N15) -> 221 | Q15: =P15*$B$4 -> 4755.0645 | R15: =SUM(P15) -> 221 | S15: =R15*$B$4 -> 4755.0645 | T15: =SUM(R15) -> 221 | U15: =T15*$B$4 -> 4755.0645 | V15: =SUM(T15) -> 221 | W15: =V15*$B$4 -> 4755.0645 | X15: =SUM(Y15/73370) -> 0.71290323 | Y15: =SUM(C15+E15+G15+I15+K15+M15+O15+Q15+S15+U15+W15) -> 52305.71 | Z15: ='B5'!C14 -> 228 | AA15: =SUM(Z15*$Z$4) -> 2280 | AB15: =SUM(Z15) -> 228 | AC15: =SUM(AB15*$Z$4) -> 2280 | AD15: =SUM(AB15) -> 228 | AE15: =SUM(AD15*$Z$4) -> 2280 | AF15: =SUM(AD15) -> 228 | AG15: =SUM(AF15*$Z$4) -> 2280 | AH15: =SUM(AF15) -> 228 | AI15: =SUM(AH15*$Z$4) -> 2280 | AJ15: =SUM(AH15) -> 228 | AK15: =SUM(AJ15*$Z$4) -> 2280 | AL15: =SUM(AJ15) -> 228 | AM15: =SUM(AL15*$Z$4) -> 2280 | AN15: =SUM(AO15/19600) -> 0.81428571 | AO15: =SUM(AA15+AC15+AE15+AG15+AI15+AK15+AM15) -> 15960 | AQ15: =SUM(AR15/92970) -> 0.73427675 | AR15: =SUM(AO15+Y15) -> 68265.71 | AS15: =SUM(AR15-AR14-AT15) -> -613.35484 | AV15: =IF(AT15>0,AU15,AV14) -> 0.5 | AW15: =-SUM('B5'!AI14) -> -144 | AX15: =-SUM(AW15-AS15) -> -469.35484 | AY15: =SUM(AX15+AW15) -> -613.35484 | AZ15: =ELEC!A12 -> 0 | BA15: ='General information '!D15 -> 23 | BB15: =SUM('General information '!E15) -> 0.53 | BC15: =IF(AR14>=AR15,0,1) -> 0 | BD15: 19222 | BE15: =(305/1185)*ELEC!Q13 -> 257.38397 | BG15: =#REF!-BE15 -> #REF!
A16: =ELEC!C13 -> 44146 | B16: ='B5'!B15 -> 219 | C16: =B16*$B$4 -> 4712.0323 | D16: =SUM(B16) -> 219 | E16: =D16*$B$4 -> 4712.0323 | F16: =SUM(D16) -> 219 | G16: =F16*$B$4 -> 4712.0323 | H16: =SUM(F16) -> 219 | I16: =H16*$B$4 -> 4712.0323 | J16: =SUM(H16) -> 219 | K16: =J16*$B$4 -> 4712.0323 | L16: =SUM(J16) -> 219 | M16: =L16*$B$4 -> 4712.0323 | N16: =SUM(L16) -> 219 | O16: =N16*$B$4 -> 4712.0323 | P16: =SUM(N16) -> 219 | Q16: =P16*$B$4 -> 4712.0323 | R16: =SUM(P16) -> 219 | S16: =R16*$B$4 -> 4712.0323 | T16: =SUM(R16) -> 219 | U16: =T16*$B$4 -> 4712.0323 | V16: =SUM(T16) -> 219 | W16: =V16*$B$4 -> 4712.0323 | X16: =SUM(Y16/73370) -> 0.70645161 | Y16: =SUM(C16+E16+G16+I16+K16+M16+O16+Q16+S16+U16+W16) -> 51832.355 | Z16: ='B5'!C15 -> 226 | AA16: =SUM(Z16*$Z$4) -> 2260 | AB16: =SUM(Z16) -> 226 | AC16: =SUM(AB16*$Z$4) -> 2260 | AD16: =SUM(AB16) -> 226 | AE16: =SUM(AD16*$Z$4) -> 2260 | AF16: =SUM(AD16) -> 226 | AG16: =SUM(AF16*$Z$4) -> 2260 | AH16: =SUM(AF16) -> 226 | AI16: =SUM(AH16*$Z$4) -> 2260 | AJ16: =SUM(AH16) -> 226 | AK16: =SUM(AJ16*$Z$4) -> 2260 | AL16: =SUM(AJ16) -> 226 | AM16: =SUM(AL16*$Z$4) -> 2260 | AN16: =SUM(AO16/19600) -> 0.80714286 | AO16: =SUM(AA16+AC16+AE16+AG16+AI16+AK16+AM16) -> 15820 | AQ16: =SUM(AR16/92970) -> 0.72767941 | AR16: =SUM(AO16+Y16) -> 67652.355 | AS16: =SUM(AR16-AR15-AT16) -> -613.35484 | AV16: =IF(AT16>0,AU16,AV15) -> 0.5 | AW16: =-SUM('B5'!AI15) -> -162 | AX16: =-SUM(AW16-AS16) -> -451.35484 | AY16: =SUM(AX16+AW16) -> -613.35484 | AZ16: =ELEC!A13 -> 0 | BA16: ='General information '!D16 -> 22.5 | BB16: =SUM('General information '!E16) -> 0.6 | BC16: =IF(AR15>=AR16,0,1) -> 0 | BD16: 19222 | BE16: =(305/1185)*ELEC!Q14 -> 514.76793 | BG16: =#REF!-BE16 -> #REF!
A17: =ELEC!C14 -> 44147 | B17: ='B5'!B16 -> 217 | C17: =B17*$B$4 -> 4669 | D17: =SUM(B17) -> 217 | E17: =D17*$B$4 -> 4669 | F17: =SUM(D17) -> 217 | G17: =F17*$B$4 -> 4669 | H17: =SUM(F17) -> 217 | I17: =H17*$B$4 -> 4669 | J17: =SUM(H17) -> 217 | K17: =J17*$B$4 -> 4669 | L17: =SUM(J17) -> 217 | M17: =L17*$B$4 -> 4669 | N17: =SUM(L17) -> 217 | O17: =N17*$B$4 -> 4669 | P17: =SUM(N17) -> 217 | Q17: =P17*$B$4 -> 4669 | R17: =SUM(P17) -> 217 | S17: =R17*$B$4 -> 4669 | T17: =SUM(R17) -> 217 | U17: =T17*$B$4 -> 4669 | V17: =SUM(T17) -> 217 | W17: =V17*$B$4 -> 4669 | X17: =SUM(Y17/73370) -> 0.7 | Y17: =SUM(C17+E17+G17+I17+K17+M17+O17+Q17+S17+U17+W17) -> 51359 | Z17: ='B5'!C16 -> 223 | AA17: =SUM(Z17*$Z$4) -> 2230 | AB17: =SUM(Z17) -> 223 | AC17: =SUM(AB17*$Z$4) -> 2230 | AD17: =SUM(AB17) -> 223 | AE17: =SUM(AD17*$Z$4) -> 2230 | AF17: =SUM(AD17) -> 223 | AG17: =SUM(AF17*$Z$4) -> 2230 | AH17: =SUM(AF17) -> 223 | AI17: =SUM(AH17*$Z$4) -> 2230 | AJ17: =SUM(AH17) -> 223 | AK17: =SUM(AJ17*$Z$4) -> 2230 | AL17: =SUM(AJ17) -> 223 | AM17: =SUM(AL17*$Z$4) -> 2230 | AN17: =SUM(AO17/19600) -> 0.79642857 | AO17: =SUM(AA17+AC17+AE17+AG17+AI17+AK17+AM17) -> 15610 | AQ17: =SUM(AR17/92970) -> 0.72032914 | AR17: =SUM(AO17+Y17) -> 66969 | AS17: =SUM(AR17-AR16-AT17) -> -683.35484 | AV17: =IF(AT17>0,AU17,AV16) -> 0.5 | AW17: =-SUM('B5'!AI16) -> -244 | AX17: =-SUM(AW17-AS17) -> -439.35484 | AY17: =SUM(AX17+AW17) -> -683.35484 | AZ17: =ELEC!A14 -> 0 | BA17: ='General information '!D17 -> 22.5 | BB17: =SUM('General information '!E17) -> 0.45 | BC17: =IF(AR16>=AR17,0,1) -> 0 | BD17: 19222 | BE17: =(305/1185)*ELEC!Q15 -> 257.38397 | BG17: =#REF!-BE17 -> #REF!
A18: =ELEC!C15 -> 44148 | B18: ='B5'!B17 -> 215 | C18: =B18*$B$4 -> 4625.9677 | D18: =SUM(B18) -> 215 | E18: =D18*$B$4 -> 4625.9677 | F18: =SUM(D18) -> 215 | G18: =F18*$B$4 -> 4625.9677 | H18: =SUM(F18) -> 215 | I18: =H18*$B$4 -> 4625.9677 | J18: =SUM(H18) -> 215 | K18: =J18*$B$4 -> 4625.9677 | L18: =SUM(J18) -> 215 | M18: =L18*$B$4 -> 4625.9677 | N18: =SUM(L18) -> 215 | O18: =N18*$B$4 -> 4625.9677 | P18: =SUM(N18) -> 215 | Q18: =P18*$B$4 -> 4625.9677 | R18: =SUM(P18) -> 215 | S18: =R18*$B$4 -> 4625.9677 | T18: =SUM(R18) -> 215 | U18: =T18*$B$4 -> 4625.9677 | V18: =SUM(T18) -> 215 | W18: =V18*$B$4 -> 4625.9677 | X18: =SUM(Y18/73370) -> 0.69354839 | Y18: =SUM(C18+E18+G18+I18+K18+M18+O18+Q18+S18+U18+W18) -> 50885.645 | Z18: ='B5'!C17 -> 221 | AA18: =SUM(Z18*$Z$4) -> 2210 | AB18: =SUM(Z18) -> 221 | AC18: =SUM(AB18*$Z$4) -> 2210 | AD18: =SUM(AB18) -> 221 | AE18: =SUM(AD18*$Z$4) -> 2210 | AF18: =SUM(AD18) -> 221 | AG18: =SUM(AF18*$Z$4) -> 2210 | AH18: =SUM(AF18) -> 221 | AI18: =SUM(AH18*$Z$4) -> 2210 | AJ18: =SUM(AH18) -> 221 | AK18: =SUM(AJ18*$Z$4) -> 2210 | AL18: =SUM(AJ18) -> 221 | AM18: =SUM(AL18*$Z$4) -> 2210 | AN18: =SUM(AO18/19600) -> 0.78928571 | AO18: =SUM(AA18+AC18+AE18+AG18+AI18+AK18+AM18) -> 15470 | AQ18: =SUM(AR18/92970) -> 0.7137318 | AR18: =SUM(AO18+Y18) -> 66355.645 | AS18: =SUM(AR18-AR17-AT18) -> -613.35484 | AV18: =IF(AT18>0,AU18,AV17) -> 0.5 | AW18: =-SUM('B5'!AI17) -> -137 | AX18: =-SUM(AW18-AS18) -> -476.35484 | AY18: =SUM(AX18+AW18) -> -613.35484 | AZ18: =ELEC!A15 -> 0 | BA18: ='General information '!D18 -> 23 | BB18: =SUM('General information '!E18) -> 0.5 | BC18: =IF(AR17>=AR18,0,1) -> 0 | BD18: 19222 | BE18: =(305/1185)*ELEC!Q16 -> 257.38397 | BG18: =#REF!-BE18 -> #REF!
A19: =ELEC!C16 -> 44149 | B19: ='B5'!B18 -> 213 | C19: =B19*$B$4 -> 4582.9355 | D19: =SUM(B19) -> 213 | E19: =D19*$B$4 -> 4582.9355 | F19: =SUM(D19) -> 213 | G19: =F19*$B$4 -> 4582.9355 | H19: =SUM(F19) -> 213 | I19: =H19*$B$4 -> 4582.9355 | J19: =SUM(H19) -> 213 | K19: =J19*$B$4 -> 4582.9355 | L19: =SUM(J19) -> 213 | M19: =L19*$B$4 -> 4582.9355 | N19: =SUM(L19) -> 213 | O19: =N19*$B$4 -> 4582.9355 | P19: =SUM(N19) -> 213 | Q19: =P19*$B$4 -> 4582.9355 | R19: =SUM(P19) -> 213 | S19: =R19*$B$4 -> 4582.9355 | T19: =SUM(R19) -> 213 | U19: =T19*$B$4 -> 4582.9355 | V19: =SUM(T19) -> 213 | W19: =V19*$B$4 -> 4582.9355 | X19: =SUM(Y19/73370) -> 0.68709677 | Y19: =SUM(C19+E19+G19+I19+K19+M19+O19+Q19+S19+U19+W19) -> 50412.29 | Z19: ='B5'!C18 -> 219 | AA19: =SUM(Z19*$Z$4) -> 2190 | AB19: =SUM(Z19) -> 219 | AC19: =SUM(AB19*$Z$4) -> 2190 | AD19: =SUM(AB19) -> 219 | AE19: =SUM(AD19*$Z$4) -> 2190 | AF19: =SUM(AD19) -> 219 | AG19: =SUM(AF19*$Z$4) -> 2190 | AH19: =SUM(AF19) -> 219 | AI19: =SUM(AH19*$Z$4) -> 2190 | AJ19: =SUM(AH19) -> 219 | AK19: =SUM(AJ19*$Z$4) -> 2190 | AL19: =SUM(AJ19) -> 219 | AM19: =SUM(AL19*$Z$4) -> 2190 | AN19: =SUM(AO19/19600) -> 0.78214286 | AO19: =SUM(AA19+AC19+AE19+AG19+AI19+AK19+AM19) -> 15330 | AQ19: =SUM(AR19/92970) -> 0.70713446 | AR19: =SUM(AO19+Y19) -> 65742.29 | AS19: =SUM(AR19-AR18-AT19) -> -613.35484 | AV19: =IF(AT19>0,AU19,AV18) -> 0.5 | AW19: =-SUM('B5'!AI18) -> -162 | AX19: =-SUM(AW19-AS19) -> -451.35484 | AY19: =SUM(AX19+AW19) -> -613.35484 | AZ19: =ELEC!A16 -> 0 | BA19: ='General information '!D19 -> 23 | BB19: =SUM('General information '!E19) -> 0.6 | BC19: =IF(AR18>=AR19,0,1) -> 0 | BD19: 19222 | BE19: =(305/1185)*ELEC!Q17 -> 257.38397 | BG19: =#REF!-BE19 -> #REF!
A20: =ELEC!C17 -> 44150 | B20: ='B5'!B19 -> 211 | C20: =B20*$B$4 -> 4539.9032 | D20: =SUM(B20) -> 211 | E20: =D20*$B$4 -> 4539.9032 | F20: =SUM(D20) -> 211 | G20: =F20*$B$4 -> 4539.9032 | H20: =SUM(F20) -> 211 | I20: =H20*$B$4 -> 4539.9032 | J20: =SUM(H20) -> 211 | K20: =J20*$B$4 -> 4539.9032 | L20: =SUM(J20) -> 211 | M20: =L20*$B$4 -> 4539.9032 | N20: =SUM(L20) -> 211 | O20: =N20*$B$4 -> 4539.9032 | P20: =SUM(N20) -> 211 | Q20: =P20*$B$4 -> 4539.9032 | R20: =SUM(P20) -> 211 | S20: =R20*$B$4 -> 4539.9032 | T20: =SUM(R20) -> 211 | U20: =T20*$B$4 -> 4539.9032 | V20: =SUM(T20) -> 211 | W20: =V20*$B$4 -> 4539.9032 | X20: =SUM(Y20/73370) -> 0.68064516 | Y20: =SUM(C20+E20+G20+I20+K20+M20+O20+Q20+S20+U20+W20) -> 49938.935 | Z20: ='B5'!C19 -> 217.3 | AA20: =SUM(Z20*$Z$4) -> 2173 | AB20: =SUM(Z20) -> 217.3 | AC20: =SUM(AB20*$Z$4) -> 2173 | AD20: =SUM(AB20) -> 217.3 | AE20: =SUM(AD20*$Z$4) -> 2173 | AF20: =SUM(AD20) -> 217.3 | AG20: =SUM(AF20*$Z$4) -> 2173 | AH20: =SUM(AF20) -> 217.3 | AI20: =SUM(AH20*$Z$4) -> 2173 | AJ20: =SUM(AH20) -> 217.3 | AK20: =SUM(AJ20*$Z$4) -> 2173 | AL20: =SUM(AJ20) -> 217.3 | AM20: =SUM(AL20*$Z$4) -> 2173 | AN20: =SUM(AO20/19600) -> 0.77607143 | AO20: =SUM(AA20+AC20+AE20+AG20+AI20+AK20+AM20) -> 15211 | AQ20: =SUM(AR20/92970) -> 0.70076299 | AR20: =SUM(AO20+Y20) -> 65149.935 | AS20: =SUM(AR20-AR19-AT20) -> -592.35484 | AV20: =IF(AT20>0,AU20,AV19) -> 0.5 | AW20: =-SUM('B5'!AI19) -> -157 | AX20: =-SUM(AW20-AS20) -> -435.35484 | AY20: =SUM(AX20+AW20) -> -592.35484 | AZ20: =ELEC!A17 -> 0 | BA20: ='General information '!D20 -> 19.5 | BB20: =SUM('General information '!E20) -> 0.5 | BC20: =IF(AR19>=AR20,0,1) -> 0 | BD20: 19222 | BE20: =(305/1185)*ELEC!Q18 -> 257.38397 | BG20: =#REF!-BE20 -> #REF!
A21: =ELEC!C18 -> 44151 | B21: ='B5'!B20 -> 248 | C21: =B21*$B$4 -> 5336 | D21: =SUM(B21) -> 248 | E21: =D21*$B$4 -> 5336 | F21: =SUM(D21) -> 248 | G21: =F21*$B$4 -> 5336 | H21: =SUM(F21) -> 248 | I21: =H21*$B$4 -> 5336 | J21: =SUM(H21) -> 248 | K21: =J21*$B$4 -> 5336 | L21: =SUM(J21) -> 248 | M21: =L21*$B$4 -> 5336 | N21: =SUM(L21) -> 248 | O21: =N21*$B$4 -> 5336 | P21: =SUM(N21) -> 248 | Q21: =P21*$B$4 -> 5336 | R21: =SUM(P21) -> 248 | S21: =R21*$B$4 -> 5336 | T21: =SUM(R21) -> 248 | U21: =T21*$B$4 -> 5336 | V21: =SUM(T21) -> 248 | W21: =V21*$B$4 -> 5336 | X21: =SUM(Y21/73370) -> 0.8 | Y21: =SUM(C21+E21+G21+I21+K21+M21+O21+Q21+S21+U21+W21) -> 58696 | Z21: ='B5'!C20 -> 254 | AA21: =SUM(Z21*$Z$4) -> 2540 | AB21: =SUM(Z21) -> 254 | AC21: =SUM(AB21*$Z$4) -> 2540 | AD21: =SUM(AB21) -> 254 | AE21: =SUM(AD21*$Z$4) -> 2540 | AF21: =SUM(AD21) -> 254 | AG21: =SUM(AF21*$Z$4) -> 2540 | AH21: =SUM(AF21) -> 254 | AI21: =SUM(AH21*$Z$4) -> 2540 | AJ21: =SUM(AH21) -> 254 | AK21: =SUM(AJ21*$Z$4) -> 2540 | AL21: =SUM(AJ21) -> 254 | AM21: =SUM(AL21*$Z$4) -> 2540 | AN21: =SUM(AO21/19600) -> 0.90714286 | AO21: =SUM(AA21+AC21+AE21+AG21+AI21+AK21+AM21) -> 17780 | AQ21: =SUM(AR21/92970) -> 0.82258793 | AR21: =SUM(AO21+Y21) -> 76476 | AS21: =SUM(AR21-AR20-AT21) -> 1162.0645 | AT21: 10164 | AU21: 0.49 | AV21: =IF(AT21>0,AU21,AV20) -> 0.49 | AW21: =-SUM('B5'!AI20) -> -137 | AX21: =-SUM(AW21-AS21) -> 1299.0645 | AY21: =SUM(AX21+AW21) -> 1162.0645 | AZ21: =ELEC!A18 -> 0 | BA21: ='General information '!D21 -> 19 | BB21: =SUM('General information '!E21) -> 0.5 | BC21: =IF(AR20>=AR21,0,1) -> 1 | BD21: 19222 | BE21: =(305/1185)*ELEC!Q19 -> 514.76793 | BG21: =#REF!-BE21 -> #REF!
A22: =ELEC!C19 -> 44152 | B22: ='B5'!B21 -> 246 | C22: =B22*$B$4 -> 5292.9677 | D22: =SUM(B22) -> 246 | E22: =D22*$B$4 -> 5292.9677 | F22: =SUM(D22) -> 246 | G22: =F22*$B$4 -> 5292.9677 | H22: =SUM(F22) -> 246 | I22: =H22*$B$4 -> 5292.9677 | J22: =SUM(H22) -> 246 | K22: =J22*$B$4 -> 5292.9677 | L22: =SUM(J22) -> 246 | M22: =L22*$B$4 -> 5292.9677 | N22: =SUM(L22) -> 246 | O22: =N22*$B$4 -> 5292.9677 | P22: =SUM(N22) -> 246 | Q22: =P22*$B$4 -> 5292.9677 | R22: =SUM(P22) -> 246 | S22: =R22*$B$4 -> 5292.9677 | T22: =SUM(R22) -> 246 | U22: =T22*$B$4 -> 5292.9677 | V22: =SUM(T22) -> 246 | W22: =V22*$B$4 -> 5292.9677 | X22: =SUM(Y22/73370) -> 0.79354839 | Y22: =SUM(C22+E22+G22+I22+K22+M22+O22+Q22+S22+U22+W22) -> 58222.645 | Z22: ='B5'!C21 -> 252 | AA22: =SUM(Z22*$Z$4) -> 2520 | AB22: =SUM(Z22) -> 252 | AC22: =SUM(AB22*$Z$4) -> 2520 | AD22: =SUM(AB22) -> 252 | AE22: =SUM(AD22*$Z$4) -> 2520 | AF22: =SUM(AD22) -> 252 | AG22: =SUM(AF22*$Z$4) -> 2520 | AH22: =SUM(AF22) -> 252 | AI22: =SUM(AH22*$Z$4) -> 2520 | AJ22: =SUM(AH22) -> 252 | AK22: =SUM(AJ22*$Z$4) -> 2520 | AL22: =SUM(AJ22) -> 252 | AM22: =SUM(AL22*$Z$4) -> 2520 | AN22: =SUM(AO22/19600) -> 0.9 | AO22: =SUM(AA22+AC22+AE22+AG22+AI22+AK22+AM22) -> 17640 | AQ22: =SUM(AR22/92970) -> 0.81599059 | AR22: =SUM(AO22+Y22) -> 75862.645 | AS22: =SUM(AR22-AR21-AT22) -> -613.35484 | AV22: =IF(AT22>0,AU22,AV21) -> 0.49 | AW22: =-SUM('B5'!AI21) -> -160 | AX22: =-SUM(AW22-AS22) -> -453.35484 | AY22: =SUM(AX22+AW22) -> -613.35484 | AZ22: =ELEC!A19 -> 0 | BA22: ='General information '!D22 -> 18 | BB22: =SUM('General information '!E22) -> 0.52 | BC22: =IF(AR21>=AR22,0,1) -> 0 | BD22: 19222 | BE22: =(305/1185)*ELEC!Q20 -> 167.04219 | BG22: =#REF!-BE22 -> #REF!
A23: =ELEC!C20 -> 44153 | B23: ='B5'!B22 -> 244 | C23: =B23*$B$4 -> 5249.9355 | D23: =SUM(B23) -> 244 | E23: =D23*$B$4 -> 5249.9355 | F23: =SUM(D23) -> 244 | G23: =F23*$B$4 -> 5249.9355 | H23: =SUM(F23) -> 244 | I23: =H23*$B$4 -> 5249.9355 | J23: =SUM(H23) -> 244 | K23: =J23*$B$4 -> 5249.9355 | L23: =SUM(J23) -> 244 | M23: =L23*$B$4 -> 5249.9355 | N23: =SUM(L23) -> 244 | O23: =N23*$B$4 -> 5249.9355 | P23: =SUM(N23) -> 244 | Q23: =P23*$B$4 -> 5249.9355 | R23: =SUM(P23) -> 244 | S23: =R23*$B$4 -> 5249.9355 | T23: =SUM(R23) -> 244 | U23: =T23*$B$4 -> 5249.9355 | V23: =SUM(T23) -> 244 | W23: =V23*$B$4 -> 5249.9355 | X23: =SUM(Y23/73370) -> 0.78709677 | Y23: =SUM(C23+E23+G23+I23+K23+M23+O23+Q23+S23+U23+W23) -> 57749.29 | Z23: ='B5'!C22 -> 250 | AA23: =SUM(Z23*$Z$4) -> 2500 | AB23: =SUM(Z23) -> 250 | AC23: =SUM(AB23*$Z$4) -> 2500 | AD23: =SUM(AB23) -> 250 | AE23: =SUM(AD23*$Z$4) -> 2500 | AF23: =SUM(AD23) -> 250 | AG23: =SUM(AF23*$Z$4) -> 2500 | AH23: =SUM(AF23) -> 250 | AI23: =SUM(AH23*$Z$4) -> 2500 | AJ23: =SUM(AH23) -> 250 | AK23: =SUM(AJ23*$Z$4) -> 2500 | AL23: =SUM(AJ23) -> 250 | AM23: =SUM(AL23*$Z$4) -> 2500 | AN23: =SUM(AO23/19600) -> 0.89285714 | AO23: =SUM(AA23+AC23+AE23+AG23+AI23+AK23+AM23) -> 17500 | AQ23: =SUM(AR23/92970) -> 0.80939325 | AR23: =SUM(AO23+Y23) -> 75249.29 | AS23: =SUM(AR23-AR22-AT23) -> -613.35484 | AV23: =IF(AT23>0,AU23,AV22) -> 0.49 | AW23: =-SUM('B5'!AI22) -> -214 | AX23: =-SUM(AW23-AS23) -> -399.35484 | AY23: =SUM(AX23+AW23) -> -613.35484 | AZ23: =ELEC!A20 -> 0 | BA23: ='General information '!D23 -> 18 | BB23: =SUM('General information '!E23) -> 0.55 | BC23: =IF(AR22>=AR23,0,1) -> 0 | BD23: 19222 | BE23: =(305/1185)*ELEC!Q21 -> 344.89451 | BG23: =#REF!-BE23 -> #REF!
A24: =ELEC!C21 -> 44154 | B24: ='B5'!B23 -> 243 | C24: =B24*$B$4 -> 5228.4194 | D24: =SUM(B24) -> 243 | E24: =D24*$B$4 -> 5228.4194 | F24: =SUM(D24) -> 243 | G24: =F24*$B$4 -> 5228.4194 | H24: =SUM(F24) -> 243 | I24: =H24*$B$4 -> 5228.4194 | J24: =SUM(H24) -> 243 | K24: =J24*$B$4 -> 5228.4194 | L24: =SUM(J24) -> 243 | M24: =L24*$B$4 -> 5228.4194 | N24: =SUM(L24) -> 243 | O24: =N24*$B$4 -> 5228.4194 | P24: =SUM(N24) -> 243 | Q24: =P24*$B$4 -> 5228.4194 | R24: =SUM(P24) -> 243 | S24: =R24*$B$4 -> 5228.4194 | T24: =SUM(R24) -> 243 | U24: =T24*$B$4 -> 5228.4194 | V24: =SUM(T24) -> 243 | W24: =V24*$B$4 -> 5228.4194 | X24: =SUM(Y24/73370) -> 0.78387097 | Y24: =SUM(C24+E24+G24+I24+K24+M24+O24+Q24+S24+U24+W24) -> 57512.613 | Z24: ='B5'!C23 -> 249 | AA24: =SUM(Z24*$Z$4) -> 2490 | AB24: =SUM(Z24) -> 249 | AC24: =SUM(AB24*$Z$4) -> 2490 | AD24: =SUM(AB24) -> 249 | AE24: =SUM(AD24*$Z$4) -> 2490 | AF24: =SUM(AD24) -> 249 | AG24: =SUM(AF24*$Z$4) -> 2490 | AH24: =SUM(AF24) -> 249 | AI24: =SUM(AH24*$Z$4) -> 2490 | AJ24: =SUM(AH24) -> 249 | AK24: =SUM(AJ24*$Z$4) -> 2490 | AL24: =SUM(AJ24) -> 249 | AM24: =SUM(AL24*$Z$4) -> 2490 | AN24: =SUM(AO24/19600) -> 0.88928571 | AO24: =SUM(AA24+AC24+AE24+AG24+AI24+AK24+AM24) -> 17430 | AQ24: =SUM(AR24/92970) -> 0.80609458 | AR24: =SUM(AO24+Y24) -> 74942.613 | AS24: =SUM(AR24-AR23-AT24) -> -306.67742 | AV24: =IF(AT24>0,AU24,AV23) -> 0.49 | AW24: =-SUM('B5'!AI23) -> -113 | AX24: =-SUM(AW24-AS24) -> -193.67742 | AY24: =SUM(AX24+AW24) -> -306.67742 | AZ24: =ELEC!A21 -> 0 | BA24: ='General information '!D24 -> 18.5 | BB24: =SUM('General information '!E24) -> 0.55 | BC24: =IF(AR23>=AR24,0,1) -> 0 | BD24: 19222 | BE24: =(305/1185)*ELEC!Q22 -> 361.1097 | BG24: =#REF!-BE24 -> #REF!
A25: =ELEC!C22 -> 44155 | B25: ='B5'!B24 -> 239 | C25: =B25*$B$4 -> 5142.3548 | D25: =SUM(B25) -> 239 | E25: =D25*$B$4 -> 5142.3548 | F25: =SUM(D25) -> 239 | G25: =F25*$B$4 -> 5142.3548 | H25: =SUM(F25) -> 239 | I25: =H25*$B$4 -> 5142.3548 | J25: =SUM(H25) -> 239 | K25: =J25*$B$4 -> 5142.3548 | L25: =SUM(J25) -> 239 | M25: =L25*$B$4 -> 5142.3548 | N25: =SUM(L25) -> 239 | O25: =N25*$B$4 -> 5142.3548 | P25: =SUM(N25) -> 239 | Q25: =P25*$B$4 -> 5142.3548 | R25: =SUM(P25) -> 239 | S25: =R25*$B$4 -> 5142.3548 | T25: =SUM(R25) -> 239 | U25: =T25*$B$4 -> 5142.3548 | V25: =SUM(T25) -> 239 | W25: =V25*$B$4 -> 5142.3548 | X25: =SUM(Y25/73370) -> 0.77096774 | Y25: =SUM(C25+E25+G25+I25+K25+M25+O25+Q25+S25+U25+W25) -> 56565.903 | Z25: ='B5'!C24 -> 245 | AA25: =SUM(Z25*$Z$4) -> 2450 | AB25: =SUM(Z25) -> 245 | AC25: =SUM(AB25*$Z$4) -> 2450 | AD25: =SUM(AB25) -> 245 | AE25: =SUM(AD25*$Z$4) -> 2450 | AF25: =SUM(AD25) -> 245 | AG25: =SUM(AF25*$Z$4) -> 2450 | AH25: =SUM(AF25) -> 245 | AI25: =SUM(AH25*$Z$4) -> 2450 | AJ25: =SUM(AH25) -> 245 | AK25: =SUM(AJ25*$Z$4) -> 2450 | AL25: =SUM(AJ25) -> 245 | AM25: =SUM(AL25*$Z$4) -> 2450 | AN25: =SUM(AO25/19600) -> 0.875 | AO25: =SUM(AA25+AC25+AE25+AG25+AI25+AK25+AM25) -> 17150 | AQ25: =SUM(AR25/92970) -> 0.79289989 | AR25: =SUM(AO25+Y25) -> 73715.903 | AS25: =SUM(AR25-AR24-AT25) -> -1226.7097 | AV25: =IF(AT25>0,AU25,AV24) -> 0.49 | AW25: =-SUM('B5'!AI24) -> -245 | AX25: =-SUM(AW25-AS25) -> -981.70968 | AY25: =SUM(AX25+AW25) -> -1226.7097 | AZ25: =ELEC!A22 -> 0 | BA25: ='General information '!D25 -> 17 | BB25: =SUM('General information '!E25) -> 0.73 | BC25: =IF(AR24>=AR25,0,1) -> 0 | BD25: 19222 | BE25: =(305/1185)*ELEC!Q23 -> 161.63713 | BG25: =#REF!-BE25 -> #REF!
A26: =ELEC!C23 -> 44156 | B26: ='B5'!B25 -> 238 | C26: =B26*$B$4 -> 5120.8387 | D26: =SUM(B26) -> 238 | E26: =D26*$B$4 -> 5120.8387 | F26: =SUM(D26) -> 238 | G26: =F26*$B$4 -> 5120.8387 | H26: =SUM(F26) -> 238 | I26: =H26*$B$4 -> 5120.8387 | J26: =SUM(H26) -> 238 | K26: =J26*$B$4 -> 5120.8387 | L26: =SUM(J26) -> 238 | M26: =L26*$B$4 -> 5120.8387 | N26: =SUM(L26) -> 238 | O26: =N26*$B$4 -> 5120.8387 | P26: =SUM(N26) -> 238 | Q26: =P26*$B$4 -> 5120.8387 | R26: =SUM(P26) -> 238 | S26: =R26*$B$4 -> 5120.8387 | T26: =SUM(R26) -> 238 | U26: =T26*$B$4 -> 5120.8387 | V26: =SUM(T26) -> 238 | W26: =V26*$B$4 -> 5120.8387 | X26: =SUM(Y26/73370) -> 0.76774194 | Y26: =SUM(C26+E26+G26+I26+K26+M26+O26+Q26+S26+U26+W26) -> 56329.226 | Z26: ='B5'!C25 -> 244 | AA26: =SUM(Z26*$Z$4) -> 2440 | AB26: =SUM(Z26) -> 244 | AC26: =SUM(AB26*$Z$4) -> 2440 | AD26: =SUM(AB26) -> 244 | AE26: =SUM(AD26*$Z$4) -> 2440 | AF26: =SUM(AD26) -> 244 | AG26: =SUM(AF26*$Z$4) -> 2440 | AH26: =SUM(AF26) -> 244 | AI26: =SUM(AH26*$Z$4) -> 2440 | AJ26: =SUM(AH26) -> 244 | AK26: =SUM(AJ26*$Z$4) -> 2440 | AL26: =SUM(AJ26) -> 244 | AM26: =SUM(AL26*$Z$4) -> 2440 | AN26: =SUM(AO26/19600) -> 0.87142857 | AO26: =SUM(AA26+AC26+AE26+AG26+AI26+AK26+AM26) -> 17080 | AQ26: =SUM(AR26/92970) -> 0.78960122 | AR26: =SUM(AO26+Y26) -> 73409.226 | AS26: =SUM(AR26-AR25-AT26) -> -306.67742 | AV26: =IF(AT26>0,AU26,AV25) -> 0.49 | AW26: =-SUM('B5'!AI25) -> -137 | AX26: =-SUM(AW26-AS26) -> -169.67742 | AY26: =SUM(AX26+AW26) -> -306.67742 | AZ26: =ELEC!A23 -> 0 | BA26: ='General information '!D26 -> 17 | BB26: =SUM('General information '!E26) -> 0.65 | BC26: =IF(AR25>=AR26,0,1) -> 0 | BD26: 19222 | BE26: =(305/1185)*ELEC!Q24 -> 0 | BG26: =#REF!-BE26 -> #REF!
A27: =ELEC!C24 -> 44157 | B27: ='B5'!B26 -> 237 | C27: =B27*$B$4 -> 5099.3226 | D27: =SUM(B27) -> 237 | E27: =D27*$B$4 -> 5099.3226 | F27: =SUM(D27) -> 237 | G27: =F27*$B$4 -> 5099.3226 | H27: =SUM(F27) -> 237 | I27: =H27*$B$4 -> 5099.3226 | J27: =SUM(H27) -> 237 | K27: =J27*$B$4 -> 5099.3226 | L27: =SUM(J27) -> 237 | M27: =L27*$B$4 -> 5099.3226 | N27: =SUM(L27) -> 237 | O27: =N27*$B$4 -> 5099.3226 | P27: =SUM(N27) -> 237 | Q27: =P27*$B$4 -> 5099.3226 | R27: =SUM(P27) -> 237 | S27: =R27*$B$4 -> 5099.3226 | T27: =SUM(R27) -> 237 | U27: =T27*$B$4 -> 5099.3226 | V27: =SUM(T27) -> 237 | W27: =V27*$B$4 -> 5099.3226 | X27: =SUM(Y27/73370) -> 0.76451613 | Y27: =SUM(C27+E27+G27+I27+K27+M27+O27+Q27+S27+U27+W27) -> 56092.548 | Z27: ='B5'!C26 -> 243 | AA27: =SUM(Z27*$Z$4) -> 2430 | AB27: =SUM(Z27) -> 243 | AC27: =SUM(AB27*$Z$4) -> 2430 | AD27: =SUM(AB27) -> 243 | AE27: =SUM(AD27*$Z$4) -> 2430 | AF27: =SUM(AD27) -> 243 | AG27: =SUM(AF27*$Z$4) -> 2430 | AH27: =SUM(AF27) -> 243 | AI27: =SUM(AH27*$Z$4) -> 2430 | AJ27: =SUM(AH27) -> 243 | AK27: =SUM(AJ27*$Z$4) -> 2430 | AL27: =SUM(AJ27) -> 243 | AM27: =SUM(AL27*$Z$4) -> 2430 | AN27: =SUM(AO27/19600) -> 0.86785714 | AO27: =SUM(AA27+AC27+AE27+AG27+AI27+AK27+AM27) -> 17010 | AQ27: =SUM(AR27/92970) -> 0.78630255 | AR27: =SUM(AO27+Y27) -> 73102.548 | AS27: =SUM(AR27-AR26-AT27) -> -306.67742 | AV27: =IF(AT27>0,AU27,AV26) -> 0.49 | AW27: =-SUM('B5'!AI26) -> -237 | AX27: =-SUM(AW27-AS27) -> -69.677419 | AY27: =SUM(AX27+AW27) -> -306.67742 | AZ27: =ELEC!A24 -> 0 | BA27: ='General information '!D27 -> 17.5 | BB27: =SUM('General information '!E27) -> 0.65 | BC27: =IF(AR26>=AR27,0,1) -> 0 | BD27: 19222 | BE27: =(305/1185)*ELEC!Q25 -> 436.26582 | BG27: =#REF!-BE27 -> #REF!
A28: =ELEC!C25 -> 44158 | B28: ='B5'!B27 -> 235 | C28: =B28*$B$4 -> 5056.2903 | D28: =SUM(B28) -> 235 | E28: =D28*$B$4 -> 5056.2903 | F28: =SUM(D28) -> 235 | G28: =F28*$B$4 -> 5056.2903 | H28: =SUM(F28) -> 235 | I28: =H28*$B$4 -> 5056.2903 | J28: =SUM(H28) -> 235 | K28: =J28*$B$4 -> 5056.2903 | L28: =SUM(J28) -> 235 | M28: =L28*$B$4 -> 5056.2903 | N28: =SUM(L28) -> 235 | O28: =N28*$B$4 -> 5056.2903 | P28: =SUM(N28) -> 235 | Q28: =P28*$B$4 -> 5056.2903 | R28: =SUM(P28) -> 235 | S28: =R28*$B$4 -> 5056.2903 | T28: =SUM(R28) -> 235 | U28: =T28*$B$4 -> 5056.2903 | V28: =SUM(T28) -> 235 | W28: =V28*$B$4 -> 5056.2903 | X28: =SUM(Y28/73370) -> 0.75806452 | Y28: =SUM(C28+E28+G28+I28+K28+M28+O28+Q28+S28+U28+W28) -> 55619.194 | Z28: ='B5'!C27 -> 241 | AA28: =SUM(Z28*$Z$4) -> 2410 | AB28: =SUM(Z28) -> 241 | AC28: =SUM(AB28*$Z$4) -> 2410 | AD28: =SUM(AB28) -> 241 | AE28: =SUM(AD28*$Z$4) -> 2410 | AF28: =SUM(AD28) -> 241 | AG28: =SUM(AF28*$Z$4) -> 2410 | AH28: =SUM(AF28) -> 241 | AI28: =SUM(AH28*$Z$4) -> 2410 | AJ28: =SUM(AH28) -> 241 | AK28: =SUM(AJ28*$Z$4) -> 2410 | AL28: =SUM(AJ28) -> 241 | AM28: =SUM(AL28*$Z$4) -> 2410 | AN28: =SUM(AO28/19600) -> 0.86071429 | AO28: =SUM(AA28+AC28+AE28+AG28+AI28+AK28+AM28) -> 16870 | AQ28: =SUM(AR28/92970) -> 0.77970521 | AR28: =SUM(AO28+Y28) -> 72489.194 | AS28: =SUM(AR28-AR27-AT28) -> -613.35484 | AV28: =IF(AT28>0,AU28,AV27) -> 0.49 | AW28: =-SUM('B5'!AI27) -> -155 | AX28: =-SUM(AW28-AS28) -> -458.35484 | AY28: =SUM(AX28+AW28) -> -613.35484 | AZ28: =ELEC!A25 -> 0 | BA28: ='General information '!D28 -> 17.5 | BB28: =SUM('General information '!E28) -> 0.6 | BC28: =IF(AR27>=AR28,0,1) -> 0 | BD28: 19222 | BE28: =(305/1185)*ELEC!Q26 -> 351.07173 | BG28: =#REF!-BE28 -> #REF!
A29: =ELEC!C26 -> 44159 | B29: ='B5'!B28 -> 232 | C29: =B29*$B$4 -> 4991.7419 | D29: =SUM(B29) -> 232 | E29: =D29*$B$4 -> 4991.7419 | F29: =SUM(D29) -> 232 | G29: =F29*$B$4 -> 4991.7419 | H29: =SUM(F29) -> 232 | I29: =H29*$B$4 -> 4991.7419 | J29: =SUM(H29) -> 232 | K29: =J29*$B$4 -> 4991.7419 | L29: =SUM(J29) -> 232 | M29: =L29*$B$4 -> 4991.7419 | N29: =SUM(L29) -> 232 | O29: =N29*$B$4 -> 4991.7419 | P29: =SUM(N29) -> 232 | Q29: =P29*$B$4 -> 4991.7419 | R29: =SUM(P29) -> 232 | S29: =R29*$B$4 -> 4991.7419 | T29: =SUM(R29) -> 232 | U29: =T29*$B$4 -> 4991.7419 | V29: =SUM(T29) -> 232 | W29: =V29*$B$4 -> 4991.7419 | X29: =SUM(Y29/73370) -> 0.7483871 | Y29: =SUM(C29+E29+G29+I29+K29+M29+O29+Q29+S29+U29+W29) -> 54909.161 | Z29: ='B5'!C28 -> 238 | AA29: =SUM(Z29*$Z$4) -> 2380 | AB29: =SUM(Z29) -> 238 | AC29: =SUM(AB29*$Z$4) -> 2380 | AD29: =SUM(AB29) -> 238 | AE29: =SUM(AD29*$Z$4) -> 2380 | AF29: =SUM(AD29) -> 238 | AG29: =SUM(AF29*$Z$4) -> 2380 | AH29: =SUM(AF29) -> 238 | AI29: =SUM(AH29*$Z$4) -> 2380 | AJ29: =SUM(AH29) -> 238 | AK29: =SUM(AJ29*$Z$4) -> 2380 | AL29: =SUM(AJ29) -> 238 | AM29: =SUM(AL29*$Z$4) -> 2380 | AN29: =SUM(AO29/19600) -> 0.85 | AO29: =SUM(AA29+AC29+AE29+AG29+AI29+AK29+AM29) -> 16660 | AQ29: =SUM(AR29/92970) -> 0.7698092 | AR29: =SUM(AO29+Y29) -> 71569.161 | AS29: =SUM(AR29-AR28-AT29) -> -920.03226 | AV29: =IF(AT29>0,AU29,AV28) -> 0.49 | AW29: =-SUM('B5'!AI28) -> -182 | AX29: =-SUM(AW29-AS29) -> -738.03226 | AY29: =SUM(AX29+AW29) -> -920.03226 | AZ29: =ELEC!A26 -> 0 | BA29: ='General information '!D29 -> 17 | BB29: =SUM('General information '!E29) -> 0.6 | BC29: =IF(AR28>=AR29,0,1) -> 0 | BD29: 19222 | BE29: =(305/1185)*ELEC!Q27 -> 391.48101 | BG29: =#REF!-BE29 -> #REF!
A30: =ELEC!C27 -> 44160 | B30: ='B5'!B29 -> 230 | C30: =B30*$B$4 -> 4948.7097 | D30: =SUM(B30) -> 230 | E30: =D30*$B$4 -> 4948.7097 | F30: =SUM(D30) -> 230 | G30: =F30*$B$4 -> 4948.7097 | H30: =SUM(F30) -> 230 | I30: =H30*$B$4 -> 4948.7097 | J30: =SUM(H30) -> 230 | K30: =J30*$B$4 -> 4948.7097 | L30: =SUM(J30) -> 230 | M30: =L30*$B$4 -> 4948.7097 | N30: =SUM(L30) -> 230 | O30: =N30*$B$4 -> 4948.7097 | P30: =SUM(N30) -> 230 | Q30: =P30*$B$4 -> 4948.7097 | R30: =SUM(P30) -> 230 | S30: =R30*$B$4 -> 4948.7097 | T30: =SUM(R30) -> 230 | U30: =T30*$B$4 -> 4948.7097 | V30: =SUM(T30) -> 230 | W30: =V30*$B$4 -> 4948.7097 | X30: =SUM(Y30/73370) -> 0.74193548 | Y30: =SUM(C30+E30+G30+I30+K30+M30+O30+Q30+S30+U30+W30) -> 54435.806 | Z30: ='B5'!C29 -> 235 | AA30: =SUM(Z30*$Z$4) -> 2350 | AB30: =SUM(Z30) -> 235 | AC30: =SUM(AB30*$Z$4) -> 2350 | AD30: =SUM(AB30) -> 235 | AE30: =SUM(AD30*$Z$4) -> 2350 | AF30: =SUM(AD30) -> 235 | AG30: =SUM(AF30*$Z$4) -> 2350 | AH30: =SUM(AF30) -> 235 | AI30: =SUM(AH30*$Z$4) -> 2350 | AJ30: =SUM(AH30) -> 235 | AK30: =SUM(AJ30*$Z$4) -> 2350 | AL30: =SUM(AJ30) -> 235 | AM30: =SUM(AL30*$Z$4) -> 2350 | AN30: =SUM(AO30/19600) -> 0.83928571 | AO30: =SUM(AA30+AC30+AE30+AG30+AI30+AK30+AM30) -> 16450 | AQ30: =SUM(AR30/92970) -> 0.76245893 | AR30: =SUM(AO30+Y30) -> 70885.806 | AS30: =SUM(AR30-AR29-AT30) -> -683.35484 | AV30: =IF(AT30>0,AU30,AV29) -> 0.49 | AW30: =-SUM('B5'!AI29) -> -156 | AX30: =-SUM(AW30-AS30) -> -527.35484 | AY30: =SUM(AX30+AW30) -> -683.35484 | AZ30: =ELEC!A27 -> 0 | BA30: ='General information '!D30 -> 16.5 | BB30: =SUM('General information '!E30) -> 0.63 | BC30: =IF(AR29>=AR30,0,1) -> 0 | BD30: 19222 | BE30: =(305/1185)*ELEC!Q28 -> 291.87342 | BG30: =#REF!-BE30 -> #REF!
A31: =ELEC!C28 -> 44161 | B31: ='B5'!B30 -> 229 | C31: =B31*$B$4 -> 4927.1935 | D31: =SUM(B31) -> 229 | E31: =D31*$B$4 -> 4927.1935 | F31: =SUM(D31) -> 229 | G31: =F31*$B$4 -> 4927.1935 | H31: =SUM(F31) -> 229 | I31: =H31*$B$4 -> 4927.1935 | J31: =SUM(H31) -> 229 | K31: =J31*$B$4 -> 4927.1935 | L31: =SUM(J31) -> 229 | M31: =L31*$B$4 -> 4927.1935 | N31: =SUM(L31) -> 229 | O31: =N31*$B$4 -> 4927.1935 | P31: =SUM(N31) -> 229 | Q31: =P31*$B$4 -> 4927.1935 | R31: =SUM(P31) -> 229 | S31: =R31*$B$4 -> 4927.1935 | T31: =SUM(R31) -> 229 | U31: =T31*$B$4 -> 4927.1935 | V31: =SUM(T31) -> 229 | W31: =V31*$B$4 -> 4927.1935 | X31: =SUM(Y31/73370) -> 0.73870968 | Y31: =SUM(C31+E31+G31+I31+K31+M31+O31+Q31+S31+U31+W31) -> 54199.129 | Z31: ='B5'!C30 -> 234.1 | AA31: =SUM(Z31*$Z$4) -> 2341 | AB31: =SUM(Z31) -> 234.1 | AC31: =SUM(AB31*$Z$4) -> 2341 | AD31: =SUM(AB31) -> 234.1 | AE31: =SUM(AD31*$Z$4) -> 2341 | AF31: =SUM(AD31) -> 234.1 | AG31: =SUM(AF31*$Z$4) -> 2341 | AH31: =SUM(AF31) -> 234.1 | AI31: =SUM(AH31*$Z$4) -> 2341 | AJ31: =SUM(AH31) -> 234.1 | AK31: =SUM(AJ31*$Z$4) -> 2341 | AL31: =SUM(AJ31) -> 234.1 | AM31: =SUM(AL31*$Z$4) -> 2341 | AN31: =SUM(AO31/19600) -> 0.83607143 | AO31: =SUM(AA31+AC31+AE31+AG31+AI31+AK31+AM31) -> 16387 | AQ31: =SUM(AR31/92970) -> 0.75923555 | AR31: =SUM(AO31+Y31) -> 70586.129 | AS31: =SUM(AR31-AR30-AT31) -> -299.67742 | AV31: =IF(AT31>0,AU31,AV30) -> 0.49 | AW31: =-SUM('B5'!AI30) -> -97 | AX31: =-SUM(AW31-AS31) -> -202.67742 | AY31: =SUM(AX31+AW31) -> -299.67742 | AZ31: =ELEC!A28 -> 0 | BA31: ='General information '!D31 -> 16.5 | BB31: =SUM('General information '!E31) -> 0.6 | BC31: =IF(AR30>=AR31,0,1) -> 0 | BD31: 19222 | BE31: =(305/1185)*ELEC!Q29 -> 0 | BG31: =#REF!-BE31 -> #REF!
A32: =ELEC!C29 -> 44162 | B32: ='B5'!B31 -> 229 | C32: =B32*$B$4 -> 4927.1935 | D32: =SUM(B32) -> 229 | E32: =D32*$B$4 -> 4927.1935 | F32: =SUM(D32) -> 229 | G32: =F32*$B$4 -> 4927.1935 | H32: =SUM(F32) -> 229 | I32: =H32*$B$4 -> 4927.1935 | J32: =SUM(H32) -> 229 | K32: =J32*$B$4 -> 4927.1935 | L32: =SUM(J32) -> 229 | M32: =L32*$B$4 -> 4927.1935 | N32: =SUM(L32) -> 229 | O32: =N32*$B$4 -> 4927.1935 | P32: =SUM(N32) -> 229 | Q32: =P32*$B$4 -> 4927.1935 | R32: =SUM(P32) -> 229 | S32: =R32*$B$4 -> 4927.1935 | T32: =SUM(R32) -> 229 | U32: =T32*$B$4 -> 4927.1935 | V32: =SUM(T32) -> 229 | W32: =V32*$B$4 -> 4927.1935 | X32: =SUM(Y32/73370) -> 0.73870968 | Y32: =SUM(C32+E32+G32+I32+K32+M32+O32+Q32+S32+U32+W32) -> 54199.129 | Z32: ='B5'!C31 -> 234.1 | AA32: =SUM(Z32*$Z$4) -> 2341 | AB32: =SUM(Z32) -> 234.1 | AC32: =SUM(AB32*$Z$4) -> 2341 | AD32: =SUM(AB32) -> 234.1 | AE32: =SUM(AD32*$Z$4) -> 2341 | AF32: =SUM(AD32) -> 234.1 | AG32: =SUM(AF32*$Z$4) -> 2341 | AH32: =SUM(AF32) -> 234.1 | AI32: =SUM(AH32*$Z$4) -> 2341 | AJ32: =SUM(AH32) -> 234.1 | AK32: =SUM(AJ32*$Z$4) -> 2341 | AL32: =SUM(AJ32) -> 234.1 | AM32: =SUM(AL32*$Z$4) -> 2341 | AN32: =SUM(AO32/19600) -> 0.83607143 | AO32: =SUM(AA32+AC32+AE32+AG32+AI32+AK32+AM32) -> 16387 | AQ32: =SUM(AR32/92970) -> 0.75923555 | AR32: =SUM(AO32+Y32) -> 70586.129 | AS32: =SUM(AR32-AR31-AT32) -> 0 | AV32: =IF(AT32>0,AU32,AV31) -> 0.49 | AW32: =-SUM('B5'!AI31) -> 0 | AX32: =-SUM(AW32-AS32) -> 0 | AY32: =SUM(AX32+AW32) -> 0 | AZ32: =ELEC!A29 -> 0 | BA32: ='General information '!D32 -> 0 | BB32: =SUM('General information '!E32) -> 0 | BC32: =IF(AR31>=AR32,0,1) -> 0 | BD32: 19222 | BE32: =(305/1185)*ELEC!Q30 -> 0 | BG32: =#REF!-BE32 -> #REF!
A33: =ELEC!C30 -> 44163 | B33: ='B5'!B32 -> 229 | C33: =B33*$B$4 -> 4927.1935 | D33: =SUM(B33) -> 229 | E33: =D33*$B$4 -> 4927.1935 | F33: =SUM(D33) -> 229 | G33: =F33*$B$4 -> 4927.1935 | H33: =SUM(F33) -> 229 | I33: =H33*$B$4 -> 4927.1935 | J33: =SUM(H33) -> 229 | K33: =J33*$B$4 -> 4927.1935 | L33: =SUM(J33) -> 229 | M33: =L33*$B$4 -> 4927.1935 | N33: =SUM(L33) -> 229 | O33: =N33*$B$4 -> 4927.1935 | P33: =SUM(N33) -> 229 | Q33: =P33*$B$4 -> 4927.1935 | R33: =SUM(P33) -> 229 | S33: =R33*$B$4 -> 4927.1935 | T33: =SUM(R33) -> 229 | U33: =T33*$B$4 -> 4927.1935 | V33: =SUM(T33) -> 229 | W33: =V33*$B$4 -> 4927.1935 | X33: =SUM(Y33/73370) -> 0.73870968 | Y33: =SUM(C33+E33+G33+I33+K33+M33+O33+Q33+S33+U33+W33) -> 54199.129 | Z33: ='B5'!C32 -> 234.1 | AA33: =SUM(Z33*$Z$4) -> 2341 | AB33: =SUM(Z33) -> 234.1 | AC33: =SUM(AB33*$Z$4) -> 2341 | AD33: =SUM(AB33) -> 234.1 | AE33: =SUM(AD33*$Z$4) -> 2341 | AF33: =SUM(AD33) -> 234.1 | AG33: =SUM(AF33*$Z$4) -> 2341 | AH33: =SUM(AF33) -> 234.1 | AI33: =SUM(AH33*$Z$4) -> 2341 | AJ33: =SUM(AH33) -> 234.1 | AK33: =SUM(AJ33*$Z$4) -> 2341 | AL33: =SUM(AJ33) -> 234.1 | AM33: =SUM(AL33*$Z$4) -> 2341 | AN33: =SUM(AO33/19600) -> 0.83607143 | AO33: =SUM(AA33+AC33+AE33+AG33+AI33+AK33+AM33) -> 16387 | AQ33: =SUM(AR33/92970) -> 0.75923555 | AR33: =SUM(AO33+Y33) -> 70586.129 | AS33: =SUM(AR33-AR32-AT33) -> 0 | AV33: =IF(AT33>0,AU33,AV32) -> 0.49 | AW33: =-SUM('B5'!AI32) -> 0 | AX33: =-SUM(AW33-AS33) -> 0 | AY33: =SUM(AX33+AW33) -> 0 | AZ33: =ELEC!A30 -> 0 | BA33: ='General information '!D33 -> 0 | BB33: =SUM('General information '!E33) -> 0 | BC33: =IF(AR32>=AR33,0,1) -> 0 | BD33: 19222 | BE33: =(305/1185)*ELEC!Q31 -> 0 | BG33: =#REF!-BE33 -> #REF!
A34: =ELEC!C31 -> 44164 | B34: ='B5'!B33 -> 229 | C34: =B34*$B$4 -> 4927.1935 | D34: =SUM(B34) -> 229 | E34: =D34*$B$4 -> 4927.1935 | F34: =SUM(D34) -> 229 | G34: =F34*$B$4 -> 4927.1935 | H34: =SUM(F34) -> 229 | I34: =H34*$B$4 -> 4927.1935 | J34: =SUM(H34) -> 229 | K34: =J34*$B$4 -> 4927.1935 | L34: =SUM(J34) -> 229 | M34: =L34*$B$4 -> 4927.1935 | N34: =SUM(L34) -> 229 | O34: =N34*$B$4 -> 4927.1935 | P34: =SUM(N34) -> 229 | Q34: =P34*$B$4 -> 4927.1935 | R34: =SUM(P34) -> 229 | S34: =R34*$B$4 -> 4927.1935 | T34: =SUM(R34) -> 229 | U34: =T34*$B$4 -> 4927.1935 | V34: =SUM(T34) -> 229 | W34: =V34*$B$4 -> 4927.1935 | X34: =SUM(Y34/73370) -> 0.73870968 | Y34: =SUM(C34+E34+G34+I34+K34+M34+O34+Q34+S34+U34+W34) -> 54199.129 | Z34: ='B5'!C33 -> 234.1 | AA34: =SUM(Z34*$Z$4) -> 2341 | AB34: =SUM(Z34) -> 234.1 | AC34: =SUM(AB34*$Z$4) -> 2341 | AD34: =SUM(AB34) -> 234.1 | AE34: =SUM(AD34*$Z$4) -> 2341 | AF34: =SUM(AD34) -> 234.1 | AG34: =SUM(AF34*$Z$4) -> 2341 | AH34: =SUM(AF34) -> 234.1 | AI34: =SUM(AH34*$Z$4) -> 2341 | AJ34: =SUM(AH34) -> 234.1 | AK34: =SUM(AJ34*$Z$4) -> 2341 | AL34: =SUM(AJ34) -> 234.1 | AM34: =SUM(AL34*$Z$4) -> 2341 | AN34: =SUM(AO34/19600) -> 0.83607143 | AO34: =SUM(AA34+AC34+AE34+AG34+AI34+AK34+AM34) -> 16387 | AQ34: =SUM(AR34/92970) -> 0.75923555 | AR34: =SUM(AO34+Y34) -> 70586.129 | AS34: =SUM(AR34-AR33-AT34) -> 0 | AV34: =IF(AT34>0,AU34,AV33) -> 0.49 | AW34: =-SUM('B5'!AI33) -> 0 | AX34: =-SUM(AW34-AS34) -> 0 | AY34: =SUM(AX34+AW34) -> 0 | AZ34: =ELEC!A31 -> 0 | BA34: ='General information '!D34 -> 0 | BB34: =SUM('General information '!E34) -> 0 | BC34: =IF(AR33>=AR34,0,1) -> 0 | BD34: 19222 | BE34: =(305/1185)*ELEC!#REF! -> #REF! | BG34: =#REF!-BE34 -> #REF!
A35: =ELEC!C32 -> 44165 | B35: ='B5'!B34 -> 229 | C35: =B35*$B$4 -> 4927.1935 | D35: =SUM(B35) -> 229 | E35: =D35*$B$4 -> 4927.1935 | F35: =SUM(D35) -> 229 | G35: =F35*$B$4 -> 4927.1935 | H35: =SUM(F35) -> 229 | I35: =H35*$B$4 -> 4927.1935 | J35: =SUM(H35) -> 229 | K35: =J35*$B$4 -> 4927.1935 | L35: =SUM(J35) -> 229 | M35: =L35*$B$4 -> 4927.1935 | N35: =SUM(L35) -> 229 | O35: =N35*$B$4 -> 4927.1935 | P35: =SUM(N35) -> 229 | Q35: =P35*$B$4 -> 4927.1935 | R35: =SUM(P35) -> 229 | S35: =R35*$B$4 -> 4927.1935 | T35: =SUM(R35) -> 229 | U35: =T35*$B$4 -> 4927.1935 | V35: =SUM(T35) -> 229 | W35: =V35*$B$4 -> 4927.1935 | X35: =SUM(Y35/73370) -> 0.73870968 | Y35: =SUM(C35+E35+G35+I35+K35+M35+O35+Q35+S35+U35+W35) -> 54199.129 | Z35: ='B5'!C34 -> 234.1 | AA35: =SUM(Z35*$Z$4) -> 2341 | AB35: =SUM(Z35) -> 234.1 | AC35: =SUM(AB35*$Z$4) -> 2341 | AD35: =SUM(AB35) -> 234.1 | AE35: =SUM(AD35*$Z$4) -> 2341 | AF35: =SUM(AD35) -> 234.1 | AG35: =SUM(AF35*$Z$4) -> 2341 | AH35: =SUM(AF35) -> 234.1 | AI35: =SUM(AH35*$Z$4) -> 2341 | AJ35: =SUM(AH35) -> 234.1 | AK35: =SUM(AJ35*$Z$4) -> 2341 | AL35: =SUM(AJ35) -> 234.1 | AM35: =SUM(AL35*$Z$4) -> 2341 | AN35: =SUM(AO35/19600) -> 0.83607143 | AO35: =SUM(AA35+AC35+AE35+AG35+AI35+AK35+AM35) -> 16387 | AQ35: =SUM(AR35/92970) -> 0.75923555 | AR35: =SUM(AO35+Y35) -> 70586.129 | AS35: =SUM(AR35-AR34-AT35) -> 0 | AV35: =IF(AT35>0,AU35,AV34) -> 0.49 | AW35: =-SUM('B5'!AI34) -> 0 | AX35: =-SUM(AW35-AS35) -> 0 | AY35: =SUM(AX35+AW35) -> 0 | AZ35: =ELEC!A32 -> 0 | BA35: ='General information '!D35 -> 0 | BB35: =SUM('General information '!E35) -> 0 | BC35: =IF(AR34>=AR35,0,1) -> 0 | BD35: 19222 | BE35: =(305/1185)*ELEC!#REF! -> #REF! | BG35: =#REF!-BE35 -> #REF!
A36: =ELEC!C33 -> 44166 | B36: ='B5'!B35 -> 229 | C36: =B36*$B$4 -> 4927.1935 | D36: =SUM(B36) -> 229 | E36: =D36*$B$4 -> 4927.1935 | F36: =SUM(D36) -> 229 | G36: =F36*$B$4 -> 4927.1935 | H36: =SUM(F36) -> 229 | I36: =H36*$B$4 -> 4927.1935 | J36: =SUM(H36) -> 229 | K36: =J36*$B$4 -> 4927.1935 | L36: =SUM(J36) -> 229 | M36: =L36*$B$4 -> 4927.1935 | N36: =SUM(L36) -> 229 | O36: =N36*$B$4 -> 4927.1935 | P36: =SUM(N36) -> 229 | Q36: =P36*$B$4 -> 4927.1935 | R36: =SUM(P36) -> 229 | S36: =R36*$B$4 -> 4927.1935 | T36: =SUM(R36) -> 229 | U36: =T36*$B$4 -> 4927.1935 | V36: =SUM(T36) -> 229 | W36: =V36*$B$4 -> 4927.1935 | X36: =SUM(Y36/73370) -> 0.73870968 | Y36: =SUM(C36+E36+G36+I36+K36+M36+O36+Q36+S36+U36+W36) -> 54199.129 | Z36: ='B5'!C35 -> 234.1 | AA36: =SUM(Z36*$Z$4) -> 2341 | AB36: =SUM(Z36) -> 234.1 | AC36: =SUM(AB36*$Z$4) -> 2341 | AD36: =SUM(AB36) -> 234.1 | AE36: =SUM(AD36*$Z$4) -> 2341 | AF36: =SUM(AD36) -> 234.1 | AG36: =SUM(AF36*$Z$4) -> 2341 | AH36: =SUM(AF36) -> 234.1 | AI36: =SUM(AH36*$Z$4) -> 2341 | AJ36: =SUM(AH36) -> 234.1 | AK36: =SUM(AJ36*$Z$4) -> 2341 | AL36: =SUM(AJ36) -> 234.1 | AM36: =SUM(AL36*$Z$4) -> 2341 | AN36: =SUM(AO36/19600) -> 0.83607143 | AO36: =SUM(AA36+AC36+AE36+AG36+AI36+AK36+AM36) -> 16387 | AQ36: =SUM(AR36/92970) -> 0.75923555 | AR36: =SUM(AO36+Y36) -> 70586.129 | AS36: =SUM(AR36-AR35-AT36) -> 0 | AV36: =IF(AT36>0,AU36,AV35) -> 0.49 | AW36: =-SUM('B5'!AI35) -> 0 | AX36: =-SUM(AW36-AS36) -> 0 | AY36: =SUM(AX36+AW36) -> 0 | AZ36: =ELEC!A33 -> 0 | BA36: ='General information '!D36 -> 0 | BB36: =SUM('General information '!E36) -> 0 | BC36: =IF(AR35>=AR36,0,1) -> 0 | BD36: 19222 | BE36: =(305/1185)*ELEC!#REF! -> #REF! | BG36: =#REF!-BE36 -> #REF!
AR37: NB delivery | AS37: =COUNT(AT6:AT36) -> 1 | AT37: =SUM(AT6:AT36) -> 10164 | AU37: =SUM(AU6:AU36)/AS37 -> 0.49 | AX37: =SUM(AX6:AX35) -> -10842.484 | AY37: =SUM(AY6:AY35) -> -14520.484
AT38: =+AT37*AU37 -> 4980.36
AS40: =SUM(AS6:AS35)/'EDl log'!A35 -> -558.48015

Sheet Sheet1
A1: TOTAL CH RH | B1: TOTAL CH cons KW | C1: TOTAL ELIC KW | D1: TOTAL EDL | E1: TOTAL GEN KW | F1: GEN HR | G1: WATER IN | H1: TOTAL CT | I1: TOTAL WATER | J1: Date
A2: =ELEC!T3+ELEC!X1+ELEC!AB3 -> #VALUE! | B2: =ELEC!AF3 -> 1616 | C2: =ELEC!N3 -> 8072 | D2: =C2-E2 -> 6072 | E2: =ELEC!Q3 -> 2000 | F2: =GEN!Z2 -> 3 | G2: =WATER!C5+WATER!H5 -> 0 | H2: =WATER!L5 -> 17 | I2: =WATER!BC5+WATER!BD5+WATER!BE6-Sheet1!G2 -> -10.3 | J2: ='B5'!A4 -> 44135
A3: =ELEC!T4+ELEC!X2+ELEC!AB4 -> 3 | B3: =ELEC!AF4 -> 963 | C3: =ELEC!N4 -> 7352 | D3: =C3-E3 -> 7352 | E3: =ELEC!Q4 -> 0 | F3: =GEN!Z3 -> 3 | G3: =WATER!C6+WATER!H6 -> 137 | H3: =WATER!L6 -> 0 | I3: =WATER!BC6+WATER!BD6+WATER!BE7-Sheet1!G3 -> -213.1 | J3: ='B5'!A5 -> 44136
A4: =ELEC!T5+ELEC!X5+ELEC!AB5 -> 8 | B4: =ELEC!AF5 -> 0 | C4: =ELEC!N5 -> 8515 | D4: =C4-E4 -> 6515 | E4: =ELEC!Q5 -> 2000 | F4: =GEN!Z4 -> 0 | G4: =WATER!C7+WATER!H7 -> 0 | H4: =WATER!L7 -> 3 | I4: =WATER!BC7+WATER!BD7+WATER!BE8-Sheet1!G4 -> 53.6 | J4: ='B5'!A6 -> 44137
A5: =ELEC!T6+ELEC!X6+ELEC!AB6 -> 5 | B5: =ELEC!AF6 -> 2276 | C5: =ELEC!N6 -> 8156 | D5: =C5-E5 -> 6156 | E5: =ELEC!Q6 -> 2000 | F5: =GEN!Z5 -> 3 | G5: =WATER!C8+WATER!H8 -> 250 | H5: =WATER!L8 -> 5 | I5: =WATER!BC8+WATER!BD8+WATER!BE9-Sheet1!G5 -> -270.1 | J5: ='B5'!A7 -> 44138
A6: =ELEC!T7+ELEC!X7+ELEC!AB7 -> 6 | B6: =ELEC!AF7 -> 1078 | C6: =ELEC!N7 -> 7853.4 | D6: =C6-E6 -> 7853.4 | E6: =ELEC!Q24 -> 0 | F6: =GEN!Z6 -> 4 | G6: =WATER!C9+WATER!H9 -> 0 | H6: =WATER!L9 -> 1 | I6: =WATER!BC9+WATER!BD9+WATER!BE10-Sheet1!G6 -> 115 | J6: ='B5'!A8 -> 44139
A7: =ELEC!T8+ELEC!X8+ELEC!AB8 -> 5 | B7: =ELEC!AF8 -> 914 | C7: =ELEC!N8 -> 7743.2 | D7: =C7-E7 -> 5743.2 | E7: =ELEC!Q8 -> 2000 | F7: =GEN!Z7 -> 3 | G7: =WATER!C10+WATER!H10 -> 193 | H7: =WATER!L10 -> 0 | I7: =WATER!BC10+WATER!BD10+WATER!BE11-Sheet1!G7 -> -186.7 | J7: ='B5'!A9 -> 44140
A8: =ELEC!T9+ELEC!X9+ELEC!AB9 -> 3 | B8: =ELEC!AF9 -> 663 | C8: =ELEC!N9 -> 6591.6 | D8: =C8-E8 -> 6591.6 | E8: =ELEC!Q9 -> 0 | F8: =GEN!Z8 -> 3 | G8: =WATER!C11+WATER!H11 -> 0 | H8: =WATER!L11 -> 9 | I8: =WATER!BC11+WATER!BD11+WATER!BE12-Sheet1!G8 -> 109.5 | J8: ='B5'!A10 -> 44141
A9: =ELEC!T10+ELEC!X10+ELEC!AB10 -> 5 | B9: =ELEC!AF10 -> 884 | C9: =ELEC!N10 -> 7125.8 | D9: =C9-E9 -> 5125.8 | E9: =ELEC!Q10 -> 2000 | F9: =GEN!Z9 -> 3 | G9: =WATER!C12+WATER!H12 -> 190 | H9: =WATER!L12 -> 0 | I9: =WATER!BC12+WATER!BD12+WATER!BE13-Sheet1!G9 -> -195.2 | J9: ='B5'!A11 -> 44142
A10: =ELEC!T11+ELEC!X11+ELEC!AB11 -> 5 | B10: =ELEC!AF11 -> 987 | C10: =ELEC!N11 -> 7376 | D10: =C10-E10 -> 6376 | E10: =ELEC!Q11 -> 1000 | F10: =GEN!Z10 -> 3 | G10: =WATER!C13+WATER!H13 -> 0 | H10: =WATER!L13 -> 0 | I10: =WATER!BC13+WATER!BD13+WATER!BE14-Sheet1!G10 -> 61 | J10: ='B5'!A12 -> 44143
A11: =ELEC!T12+ELEC!X12+ELEC!AB12 -> 5 | B11: =ELEC!AF12 -> 868 | C11: =ELEC!N12 -> 7892 | D11: =C11-E11 -> 6892 | E11: =ELEC!Q12 -> 1000 | F11: =GEN!Z11 -> 3 | G11: =WATER!C14+WATER!H14 -> 191 | H11: =WATER!L14 -> 0 | I11: =WATER!BC14+WATER!BD14+WATER!BE15-Sheet1!G11 -> -168.8 | J11: ='B5'!A13 -> 44144
A12: =ELEC!T13+ELEC!X13+ELEC!AB13 -> 8 | B12: =ELEC!AF13 -> 1465 | C12: =ELEC!N13 -> 8345 | D12: =C12-E12 -> 7345 | E12: =ELEC!Q13 -> 1000 | F12: =GEN!Z12 -> 1 | G12: =WATER!C15+WATER!H15 -> 0 | H12: =WATER!L15 -> 0 | I12: =WATER!BC15+WATER!BD15+WATER!BE16-Sheet1!G12 -> 151.3 | J12: ='B5'!A14 -> 44145
A13: =ELEC!T14+ELEC!X14+ELEC!AB14 -> 7 | B13: =ELEC!AF14 -> 1463 | C13: =ELEC!N14 -> 8791 | D13: =C13-E13 -> 6791 | E13: =ELEC!Q14 -> 2000 | F13: =GEN!Z13 -> 3 | G13: =WATER!C16+WATER!H16 -> 185 | H13: =WATER!L16 -> 0 | I13: =WATER!BC16+WATER!BD16+WATER!BE17-Sheet1!G13 -> -216 | J13: ='B5'!A15 -> 44146
A14: =ELEC!T15+ELEC!X15+ELEC!AB15 -> 5 | B14: =ELEC!AF15 -> 1198 | C14: =ELEC!N15 -> 8409 | D14: =C14-E14 -> 7409 | E14: =ELEC!Q15 -> 1000 | F14: =GEN!Z14 -> 4 | G14: =WATER!C17+WATER!H17 -> 0 | H14: =WATER!L17 -> 1 | I14: =WATER!BC17+WATER!BD17+WATER!BE18-Sheet1!G14 -> 133.4 | J14: ='B5'!A16 -> 44147
A15: =ELEC!T16+ELEC!X16+ELEC!AB16 -> 4 | B15: =ELEC!AF16 -> 809 | C15: =ELEC!N16 -> 8847 | D15: =C15-E15 -> 7847 | E15: =ELEC!Q16 -> 1000 | F15: =GEN!Z15 -> 3 | G15: =WATER!C18+WATER!H18 -> 117 | H15: =WATER!L18 -> 0 | I15: =WATER!BC18+WATER!BD18+WATER!BE19-Sheet1!G15 -> -340.9 | J15: ='B5'!A17 -> 44148
A16: =ELEC!T17+ELEC!X17+ELEC!AB17 -> 3 | B16: =ELEC!AF17 -> 772 | C16: =ELEC!N17 -> 5742 | D16: =C16-E16 -> 4742 | E16: =ELEC!Q17 -> 1000 | F16: =GEN!Z16 -> 1 | G16: =WATER!C19+WATER!H19 -> 0 | H16: =WATER!L19 -> 0 | I16: =WATER!BC19+WATER!BD19+WATER!BE20-Sheet1!G16 -> 121.6 | J16: ='B5'!A18 -> 44149
A17: =ELEC!T18+ELEC!X18+ELEC!AB18 -> 8 | B17: =ELEC!AF18 -> 1317 | C17: =ELEC!N18 -> 8525 | D17: =C17-E17 -> 7525 | E17: =ELEC!Q18 -> 1000 | F17: =GEN!Z17 -> 4 | G17: =WATER!C20+WATER!H20 -> 152 | H17: =WATER!L20 -> 0 | I17: =WATER!BC20+WATER!BD20+WATER!BE21-Sheet1!G17 -> -13.1 | J17: ='B5'!A19 -> 44150
A18: =ELEC!T19+ELEC!X19+ELEC!AB19 -> 5 | B18: =ELEC!AF19 -> 942 | C18: =ELEC!N19 -> 7549 | D18: =C18-E18 -> 5549 | E18: =ELEC!Q19 -> 2000 | F18: =GEN!Z18 -> 3 | G18: =WATER!C21+WATER!H21 -> 0 | H18: =WATER!L21 -> 0 | I18: =WATER!BC21+WATER!BD21+WATER!BE22-Sheet1!G18 -> 138.7 | J18: ='B5'!A20 -> 44151
... A29: =ELEC!T30+ELEC!X30+ELEC!AB30 -> 0 | B29: =ELEC!AF30 -> 0 | C29: =ELEC!N30 -> 0 | D29: =C29-E29 -> 0 | E29: =ELEC!Q30 -> 0 | F29: =GEN!Z29 -> 0 | G29: =WATER!C32+WATER!H32 -> 0 | H29: =WATER!L32 -> 0 | I29: =WATER!BC32+WATER!BD32+WATER!BE33-Sheet1!G29 -> 0 | J29: ='B5'!A31 -> 44162
A30: =ELEC!T31+ELEC!X31+ELEC!#REF! -> #REF! | B30: =ELEC!AF31 -> 0 | C30: =ELEC!N31 -> 0 | D30: =C30-E30 -> 0 | E30: =ELEC!Q31 -> 0 | F30: =GEN!Z30 -> 0 | G30: =WATER!C33+WATER!H33 -> 0 | H30: =WATER!L33 -> 0 | I30: =WATER!BC33+WATER!BD33+WATER!BE34-Sheet1!G30 -> 0 | J30: ='B5'!A32 -> 44163
A31: =ELEC!T32+ELEC!X32+ELEC!AB31 -> 0 | B31: =ELEC!AF32 -> 0 | C31: =ELEC!N32 -> 0 | D31: =C31-E31 -> 0 | E31: =ELEC!Q32 -> 0 | F31: =GEN!Z31 -> 0 | G31: =WATER!C34+WATER!H34 -> 0 | H31: =WATER!L34 -> 0 | I31: =WATER!BC34+WATER!BD34+WATER!BE35-Sheet1!G31 -> 0 | J31: ='B5'!A33 -> 44164
A32: =ELEC!#REF!+ELEC!#REF!+ELEC!#REF! -> #REF! | B32: =ELEC!#REF! -> #REF! | C32: =ELEC!#REF! -> #REF! | D32: =C32-E32 -> #REF! | E32: =ELEC!#REF! -> #REF! | F32: =GEN!#REF! -> #REF! | G32: =WATER!#REF!+WATER!#REF! -> #REF! | H32: =WATER!#REF! -> #REF! | I32: =WATER!#REF!+WATER!#REF!+WATER!BE37-Sheet1!G32 -> #REF!

Sheet Report
B1: Boiler Fuel | C1: Steam Fuel | D1: GEN FUEL | E1: FUEL TOTAL | F1: CT/mᶾ | G1: Water Consumption | H1: Chiller KW | I1: GEN KW | J1: EDL KW | K1: occ | L1: covers | M1: temp. C⁰ | N1: RH %
B3: ='B5'!V3 -> 0 | C3: ='B5'!AH3 -> 0 | E3: =B3+C3+D3 -> 0
A4: 42704 | B4: 810 | C4: -606.1 | D4: 1420.5021 | E4: 1624.4021 | F4: 106 | G4: -58.4 | H4: 6284 | I4: 2399 | J4: 23932 | K4: 0 | L4: 0 | M4: 0 | N4: 0
A5: ='B5'!A5 -> 44136 | B5: ='B5'!V5 -> 205 | C5: ='B5'!AH5 -> 0 | D5: =GEN!AI3 -> 514.76793 | E5: =B5+C5+D5 -> 719.76793 | F5: =WATER!L5 -> 17 | G5: =WATER!BG5 -> -41.4 | H5: =ELEC!AF3 -> 1616 | I5: =ELEC!Q3 -> 2000 | J5: =ELEC!R3 -> 6072
A6: ='B5'!A6 -> 44137 | B6: ='B5'!V6 -> 97 | C6: ='B5'!AH6 -> 0 | D6: =GEN!AI4 -> 0 | E6: =B6+C6+D6 -> 97 | F6: =WATER!L6 -> 0 | G6: =WATER!BG6 -> -8.5 | H6: =ELEC!AF4 -> 963 | I6: =ELEC!Q4 -> 0 | J6: =ELEC!R4 -> 7352
A7: ='B5'!A7 -> 44138 | B7: ='B5'!V7 -> 0 | C7: ='B5'!AH7 -> 0 | D7: =GEN!AI5 -> 514.76793 | E7: =B7+C7+D7 -> 514.76793 | F7: =WATER!L7 -> 3 | G7: =WATER!BG7 -> -55 | H7: =ELEC!AF5 -> 0 | I7: =ELEC!Q5 -> 2000 | J7: =ELEC!R5 -> 6515
A8: ='B5'!A8 -> 44139 | B8: ='B5'!V8 -> 0 | C8: ='B5'!AH8 -> 0 | D8: =GEN!AI6 -> 514.76793 | E8: =B8+C8+D8 -> 514.76793 | F8: =WATER!L8 -> 5 | G8: =WATER!BG8 -> 87 | H8: =ELEC!AF6 -> 2276 | I8: =ELEC!Q6 -> 2000 | J8: =ELEC!R6 -> 6156
A9: ='B5'!A9 -> 44140 | B9: ='B5'!V9 -> 0 | C9: ='B5'!AH9 -> 0 | D9: =GEN!AI7 -> 257.38397 | E9: =B9+C9+D9 -> 257.38397 | F9: =WATER!L9 -> 1 | G9: =WATER!BG9 -> -27 | H9: =ELEC!AF7 -> 1078 | I9: =ELEC!Q7 -> 1000 | J9: =ELEC!R7 -> 6853.4
A10: ='B5'!A10 -> 44141 | B10: ='B5'!V10 -> 0 | C10: ='B5'!AH10 -> 0 | D10: =GEN!AI8 -> 514.76793 | E10: =B10+C10+D10 -> 514.76793 | F10: =WATER!L10 -> 0 | G10: =WATER!BG10 -> 79.9 | H10: =ELEC!AF8 -> 914 | I10: =ELEC!Q8 -> 2000 | J10: =ELEC!R8 -> 5743.2
A11: ='B5'!A11 -> 44142 | B11: ='B5'!V11 -> 238 | C11: ='B5'!AH11 -> 0 | D11: =GEN!AI9 -> 0 | E11: =B11+C11+D11 -> 238 | F11: =WATER!L11 -> 9 | G11: =WATER!BG11 -> -19.6 | H11: =ELEC!AF9 -> 663 | I11: =ELEC!Q9 -> 0 | J11: =ELEC!R9 -> 6591.6
A12: ='B5'!A12 -> 44143 | B12: ='B5'!V12 -> 162 | C12: ='B5'!AH12 -> 0 | D12: =GEN!AI10 -> 514.76793 | E12: =B12+C12+D12 -> 676.76793 | F12: =WATER!L12 -> 0 | G12: =WATER!BG12 -> 77.8 | H12: =ELEC!AF10 -> 884 | I12: =ELEC!Q10 -> 2000 | J12: =ELEC!R10 -> 5125.8
A13: ='B5'!A13 -> 44144 | B13: ='B5'!V13 -> 137 | C13: ='B5'!AH13 -> 0 | D13: =GEN!AI11 -> 257.38397 | E13: =B13+C13+D13 -> 394.38397 | F13: =WATER!L13 -> 0 | G13: =WATER!BG13 -> -20 | H13: =ELEC!AF11 -> 987 | I13: =ELEC!Q11 -> 1000 | J13: =ELEC!R11 -> 6376
A14: ='B5'!A14 -> 44145 | B14: ='B5'!V14 -> 144 | C14: ='B5'!AH14 -> 0 | D14: =GEN!AI12 -> 257.38397 | E14: =B14+C14+D14 -> 401.38397 | F14: =WATER!L14 -> 0 | G14: =WATER!BG14 -> 81 | H14: =ELEC!AF12 -> 868 | I14: =ELEC!Q12 -> 1000 | J14: =ELEC!R12 -> 6892
A15: ='B5'!A15 -> 44146 | B15: ='B5'!V15 -> 162 | C15: ='B5'!AH15 -> 0 | D15: =GEN!AI13 -> 257.38397 | E15: =B15+C15+D15 -> 419.38397 | F15: =WATER!L15 -> 0 | G15: =WATER!BG15 -> -32.7 | H15: =ELEC!AF13 -> 1465 | I15: =ELEC!Q13 -> 1000 | J15: =ELEC!R13 -> 7345
A16: ='B5'!A16 -> 44147 | B16: ='B5'!V16 -> 164 | C16: ='B5'!AH16 -> 80 | D16: =GEN!AI14 -> 514.76793 | E16: =B16+C16+D16 -> 758.76793 | F16: =WATER!L16 -> 0 | G16: =WATER!BG16 -> 87.7 | H16: =ELEC!AF14 -> 1463 | I16: =ELEC!Q14 -> 2000 | J16: =ELEC!R14 -> 6791
... A33: ='B5'!A33 -> 44164 | B33: ='B5'!V33 -> 0 | C33: ='B5'!AH33 -> 0 | D33: =GEN!AI31 -> 0 | E33: =B33+C33+D33 -> 0 | F33: =WATER!L33 -> 0 | G33: =WATER!BG33 -> 0 | H33: =ELEC!AF31 -> 0 | I33: =ELEC!Q31 -> 0 | J33: =ELEC!R31 -> 0
A34: ='B5'!A34 -> 44165 | B34: ='B5'!V34 -> 0 | C34: ='B5'!AH34 -> 0 | D34: =GEN!AI32 -> 0 | E34: =B34+C34+D34 -> 0 | F34: =WATER!L34 -> 0 | G34: =WATER!BG34 -> 0 | H34: =ELEC!#REF! -> #REF! | I34: =ELEC!#REF! -> #REF! | J34: =ELEC!#REF! -> #REF!

Sheet Sheet5
T3: Outdoor conditions
C4: Date | D4: Total Boiler running H | E4: AVE CONSUM | F4: Total Steam running H | G4: AVE CONSUM | H4: Total GEN running H | I4: AVE CONSUM | J4: Actual Diesel Consumption | K4: Actual Gas Consumption | L4: Total ELEC power | M4: Gen ELEC power | N4: EDL ELEC power | O4: Chillers running H | P4: Total Water delivery | Q4: Total water consumption | R4: Total water in tanks | S4: Occupancy | T4: AVE TEPM | U4: AVE Humidity
C5: 42429 | D5: ='B5'!AL4 -> 1 | E5: =D5*90 -> 90 | F5: ='B5'!AM4 -> 0 | G5: =F5*107 -> 0 | H5: =GEN!Z3 -> 3
C6: 42430 | D6: ='B5'!AL5 -> 2 | E6: =D6*90 -> 180 | F6: ='B5'!AM5 -> 0 | G6: =F6*107 -> 0
C7: 42431 | D7: ='B5'!AL6 -> 4 | E7: =D7*90 -> 360 | F7: ='B5'!AM6 -> 0 | G7: =F7*107 -> 0
C8: 42432 | D8: ='B5'!AL7 -> 3 | E8: =D8*90 -> 270 | F8: ='B5'!AM7 -> 0 | G8: =F8*107 -> 0
C9: 42433 | D9: ='B5'!AL8 -> 3 | E9: =D9*90 -> 270 | F9: ='B5'!AM8 -> 0 | G9: =F9*107 -> 0
C10: 42434 | D10: ='B5'!AL9 -> 3 | E10: =D10*90 -> 270 | F10: ='B5'!AM9 -> 0 | G10: =F10*107 -> 0
C11: 42435 | D11: ='B5'!AL10 -> 1 | E11: =D11*90 -> 90 | F11: ='B5'!AM10 -> 0 | G11: =F11*107 -> 0
C12: 42436 | D12: ='B5'!AL11 -> 3 | E12: =D12*90 -> 270 | F12: ='B5'!AM11 -> 0 | G12: =F12*107 -> 0
C13: 42437 | D13: ='B5'!AL12 -> 2 | E13: =D13*90 -> 180 | F13: ='B5'!AM12 -> 0 | G13: =F13*107 -> 0
C14: 42438 | D14: ='B5'!AL13 -> 2 | E14: =D14*90 -> 180 | F14: ='B5'!AM13 -> 0 | G14: =F14*107 -> 0
C15: 42439 | D15: ='B5'!AL14 -> 1 | E15: =D15*90 -> 90 | F15: ='B5'!AM14 -> 0 | G15: =F15*107 -> 0
C16: 42440 | D16: ='B5'!AL15 -> 2 | E16: =D16*90 -> 180 | F16: ='B5'!AM15 -> 0 | G16: =F16*107 -> 0
C17: 42441 | D17: ='B5'!AL16 -> 2 | E17: =D17*90 -> 180 | F17: ='B5'!AM16 -> 1 | G17: =F17*107 -> 107
... C35: 42459 | D35: ='B5'!AL34 -> 0 | E35: =D35*90 -> 0 | F35: ='B5'!AM34 -> 0 | G35: =F35*107 -> 0
C36: 42460 | D36: ='B5'!#REF! -> #REF! | E36: =D36*90 -> #REF! | F36: ='B5'!#REF! -> #REF! | G36: =F36*107 -> #REF!
C37: 42461 | D37: ='B5'!#REF! -> #REF! | E37: =D37*90 -> #REF! | F37: ='B5'!#REF! -> #REF! | G37: =F37*107 -> #REF!

Sheet GEN
B1: GEN1 | C1: RUN HR | D1: Fuel Counter Index | E1: Cons /day | F1: Diesel L/H | H1: next service | I1: ALARM | J1: GEN2 | K1: RUN HR | L1: Fuel Counter Index | M1: Cons /day | N1: Diesel L/H | P1: next service | Q1: ALARM | R1: GEN3 | S1: RUN HR | T1: Fuel Counter Index | U1: Cons /day | V1: Diesel L/H | X1: next service | Y1: ALARM | Z1: RH total | AA1: Gen Con /day | AB1: Total Deisel Cons/day | AC1: H /L | AD1: TOAL KW GEN | AI1: fuel Consuption | AK1: AVG KW/h
A2: =ELEC!C2 -> 44135 | B2: =[1]GEN!B33 -> 9314 | C2: =[1]GEN!C33 -> 3 | D2: =[1]GEN!D33 -> 267366 | E2: =[1]GEN!E33 -> 689 | F2: =[1]GEN!F33 -> 229.66667 | G2: =[1]GEN!G33 -> 0 | H2: =[1]GEN!H33 -> 9298 | I2: =[1]GEN!I33 -> oil change | ... K2: =[1]GEN!K33 -> 0 | L2: 357691 | M2: =[1]GEN!M33 -> 0 | N2: =[1]GEN!N33 -> 0 | O2: =[1]GEN!O33 -> 0 | P2: =[1]GEN!P33 -> 10873 | Q2: =[1]GEN!Q33 -> ok | R2: =[1]GEN!R33 -> 11705 | S2: =[1]GEN!S33 -> 0 | T2: =[1]GEN!T33 -> 357690 | ... W2: =[1]GEN!W33 -> 0 | X2: 11781 | Y2: =[1]GEN!Y33 -> ok | Z2: =[1]GEN!Z33 -> 3 | AA2: =[1]GEN!AA33 -> 689 | AB2: =[1]GEN!AB33 -> 229.66667 | AC2: =[1]GEN!AC33 -> 229.66667 | AD2: =[1]GEN!AD33 -> 1000 | AE2: =[1]GEN!AE33 -> 333.33333 | AF2: =[1]GEN!AF33 -> 0.20833333 | ... AK2: =[1]GEN!AK33 -> 85.794655
A3: =ELEC!C3 -> 44136 | B3: 9317 | C3: =B3-B2 -> 3 | D3: 267985 | E3: =SUM(D3-D2) -> 619 | F3: =IF(C3>0,E3/C3,0) -> 206.33333 | G3: =[5]GEN!G32 -> 0 | H3: 9298 | I3: =IF(B3-H3<=0,"ok","oil change") -> oil change | J3: 10698 | K3: =J3-J2 -> 0 | L3: =L2 -> 357691 | M3: =SUM(L3-L2) -> 0 | N3: =IF(K3>0,M3/K3,0) -> 0 | O3: =[5]GEN!O32 -> 0 | P3: =P2 -> 10873 | Q3: =IF(J3-P3<=0,"ok","oil change") -> ok | R3: 11705 | S3: =R3-R2 -> 0 | T3: =T2 -> 357690 | U3: =SUM(T3-T2) -> 0 | V3: =IF(S3>0,U3/S3,0) -> 0 | W3: =[5]GEN!W32 -> 0 | X3: =X2 -> 11781 | Y3: =IF(R3-X3<=0,"ok","oil change") -> ok | Z3: =C3+K3+S3 -> 3 | AA3: =U3+M3+E3 -> 619 | AB3: =V3+N3+F3 -> 206.33333 | AC3: =IF(Z3>0,AA3/Z3,0) -> 206.33333 | AD3: =ELEC!Q3 -> 2000 | AE3: =SUM(AD3/Z3) -> 666.66667 | AF3: =SUM(AE3/1600) -> 0.41666667 | AG3: =SUM(360*AF3) -> 150 | AH3: =SUM(AC3-AG3) -> 56.333333 | AI3: =AD3*AJ3 -> 514.76793 | AJ3: =305/1185 -> 0.25738397 | AK3: =AI3/Z3 -> 171.58931
A4: =ELEC!C4 -> 44137 | B4: =B3 -> 9317 | C4: =B4-B3 -> 0 | D4: =D3 -> 267985 | E4: =SUM(D4-D3) -> 0 | F4: =IF(C4>0,E4/C4,0) -> 0 | H4: =H3 -> 9298 | I4: =IF(B4-H4<=0,"ok","oil change") -> oil change | J4: =J3 -> 10698 | K4: =J4-J3 -> 0 | L4: =L3 -> 357691 | M4: =SUM(L4-L3) -> 0 | N4: =IF(K4>0,M4/K4,0) -> 0 | P4: =P3 -> 10873 | Q4: =IF(J4-P4<=0,"ok","oil change") -> ok | R4: =R3 -> 11705 | S4: =R4-R3 -> 0 | T4: =T3 -> 357690 | U4: =SUM(T4-T3) -> 0 | V4: =IF(S4>0,U4/S4,0) -> 0 | X4: =X3 -> 11781 | Y4: =IF(R4-X4<=0,"ok","oil change") -> ok | Z4: =C4+K4+S4 -> 0 | AA4: =U4+M4+E4 -> 0 | AB4: =V4+N4+F4 -> 0 | AC4: =IF(Z4>0,AA4/Z4,0) -> 0 | AD4: =ELEC!Q4 -> 0 | AE4: =SUM(AD4/Z4) -> #DIV/0! | AF4: =SUM(AE4/1600) -> #DIV/0! | AG4: =SUM(360*AF4) -> #DIV/0! | AH4: =SUM(AC4-AG4) -> #DIV/0! | AI4: =AD4*AJ4 -> 0 | AJ4: =305/1185 -> 0.25738397 | AK4: =AI4/Z4 -> #DIV/0!
A5: =ELEC!C5 -> 44138 | B5: =B4 -> 9317 | C5: =B5-B4 -> 0 | D5: 267985 | E5: =SUM(D5-D4) -> 0 | F5: =IF(C5>0,E5/C5,0) -> 0 | H5: =H4 -> 9298 | I5: =IF(B5-H5<=0,"ok","oil change") -> oil change | J5: =J4 -> 10698 | K5: =J5-J4 -> 0 | L5: =L4 -> 357691 | M5: =SUM(L5-L4) -> 0 | N5: =IF(K5>0,M5/K5,0) -> 0 | P5: =P4 -> 10873 | Q5: =IF(J5-P5<=0,"ok","oil change") -> ok | R5: 11708 | S5: =R5-R4 -> 3 | T5: 358340 | U5: =SUM(T5-T4) -> 650 | V5: =IF(S5>0,U5/S5,0) -> 216.66667 | X5: =X4 -> 11781 | Y5: =IF(R5-X5<=0,"ok","oil change") -> ok | Z5: =C5+K5+S5 -> 3 | AA5: =U5+M5+E5 -> 650 | AB5: =V5+N5+F5 -> 216.66667 | AC5: =IF(Z5>0,AA5/Z5,0) -> 216.66667 | AD5: =ELEC!Q5 -> 2000 | AE5: =SUM(AD5/Z5) -> 666.66667 | AF5: =SUM(AE5/1600) -> 0.41666667 | AG5: =SUM(320*AF5) -> 133.33333 | AH5: =SUM(AC5-AG5) -> 83.333333 | AI5: =AD5*AJ5 -> 514.76793 | AJ5: =305/1185 -> 0.25738397 | AK5: =AI5/Z5 -> 171.58931
A6: =ELEC!C6 -> 44139 | B6: 9319 | C6: =B6-B5 -> 2 | D6: 268430 | E6: =SUM(D6-D5) -> 445 | F6: =IF(C6>0,E6/C6,0) -> 222.5 | H6: =H5 -> 9298 | I6: =IF(B6-H6<=0,"ok","oil change") -> oil change | J6: 10698 | K6: =J6-J5 -> 0 | L6: =L5 -> 357691 | M6: =SUM(L6-L5) -> 0 | N6: =IF(K6>0,M6/K6,0) -> 0 | P6: =P5 -> 10873 | Q6: =IF(J6-P6<=0,"ok","oil change") -> ok | R6: 11710 | S6: =R6-R5 -> 2 | T6: 358671 | U6: =SUM(T6-T5) -> 331 | V6: =IF(S6>0,U6/S6,0) -> 165.5 | X6: =X5 -> 11781 | Y6: =IF(R6-X6<=0,"ok","oil change") -> ok | Z6: =C6+K6+S6 -> 4 | AA6: =U6+M6+E6 -> 776 | AB6: =V6+N6+F6 -> 388 | AC6: =IF(Z6>0,AA6/Z6,0) -> 194 | AD6: =ELEC!Q6 -> 2000 | AE6: =SUM(AD6/Z6) -> 500 | AF6: =SUM(AE6/1600) -> 0.3125 | AG6: =SUM(320*AF6) -> 100 | AH6: =SUM(AC6-AG6) -> 94 | AI6: =AD6*AJ6 -> 514.76793 | AJ6: =305/1185 -> 0.25738397 | AK6: =AI6/Z6 -> 128.69198
A7: =ELEC!C7 -> 44140 | B7: =B6 -> 9319 | C7: =B7-B6 -> 0 | D7: =D6 -> 268430 | E7: =SUM(D7-D6) -> 0 | F7: =IF(C7>0,E7/C7,0) -> 0 | H7: =H6 -> 9298 | I7: =IF(B7-H7<=0,"ok","oil change") -> oil change | J7: =J6 -> 10698 | K7: =J7-J6 -> 0 | L7: =L6 -> 357691 | M7: =SUM(L7-L6) -> 0 | N7: =IF(K7>0,M7/K7,0) -> 0 | P7: =P6 -> 10873 | Q7: =IF(J7-P7<=0,"ok","oil change") -> ok | R7: 11713 | S7: =R7-R6 -> 3 | T7: 359433 | U7: =SUM(T7-T6) -> 762 | V7: =IF(S7>0,U7/S7,0) -> 254 | X7: =X6 -> 11781 | Y7: =IF(R7-X7<=0,"ok","oil change") -> ok | Z7: =C7+K7+S7 -> 3 | AA7: =U7+M7+E7 -> 762 | AB7: =V7+N7+F7 -> 254 | AC7: =IF(Z7>0,AA7/Z7,0) -> 254 | AD7: =ELEC!Q7 -> 1000 | AE7: =SUM(AD7/Z7) -> 333.33333 | AF7: =SUM(AE7/1600) -> 0.20833333 | AH7: =SUM(AC7-AG7) -> #VALUE! | AI7: =AD7*AJ7 -> 257.38397 | AJ7: =305/1185 -> 0.25738397 | AK7: =AI7/Z7 -> 85.794655
A8: =ELEC!C8 -> 44141 | B8: =B7 -> 9319 | C8: =B8-B7 -> 0 | D8: =D7 -> 268430 | E8: =SUM(D8-D7) -> 0 | F8: =IF(C8>0,E8/C8,0) -> 0 | H8: =H7 -> 9298 | I8: =IF(B8-H8<=0,"ok","oil change") -> oil change | J8: =J7 -> 10698 | K8: =J8-J7 -> 0 | L8: =L7 -> 357691 | M8: =SUM(L8-L7) -> 0 | N8: =IF(K8>0,M8/K8,0) -> 0 | P8: =P7 -> 10873 | Q8: =IF(J8-P8<=0,"ok","oil change") -> ok | R8: 11716 | S8: =R8-R7 -> 3 | T8: 360186.3 | U8: =SUM(T8-T7) -> 753.3 | V8: =IF(S8>0,U8/S8,0) -> 251.1 | X8: =X7 -> 11781 | Y8: =IF(R8-X8<=0,"ok","oil change") -> ok | Z8: =C8+K8+S8 -> 3 | AA8: =U8+M8+E8 -> 753.3 | AB8: =V8+N8+F8 -> 251.1 | AC8: =IF(Z8>0,AA8/Z8,0) -> 251.1 | AD8: =ELEC!Q8 -> 2000 | AE8: =SUM(AD8/Z8) -> 666.66667 | AF8: =SUM(AE8/1600) -> 0.41666667 | AG8: =SUM(320*AF8) -> 133.33333 | AH8: =SUM(AC8-AG8) -> 117.76667 | AI8: =AD8*AJ8 -> 514.76793 | AJ8: =305/1185 -> 0.25738397 | AK8: =AI8/Z8 -> 171.58931
A9: =ELEC!C9 -> 44142 | B9: =B8 -> 9319 | C9: =B9-B8 -> 0 | D9: =D8 -> 268430 | E9: =SUM(D9-D8) -> 0 | F9: =IF(C9>0,E9/C9,0) -> 0 | H9: =H8 -> 9298 | I9: =IF(B9-H9<=0,"ok","oil change") -> oil change | J9: =J8 -> 10698 | K9: =J9-J8 -> 0 | L9: =L8 -> 357691 | M9: =SUM(L9-L8) -> 0 | N9: =IF(K9>0,M9/K9,0) -> 0 | P9: =P8 -> 10873 | Q9: =IF(J9-P9<=0,"ok","oil change") -> ok | R9: 11719 | S9: =R9-R8 -> 3 | T9: 361137.4 | U9: =SUM(T9-T8) -> 951.1 | V9: =IF(S9>0,U9/S9,0) -> 317.03333 | X9: =X8 -> 11781 | Y9: =IF(R9-X9<=0,"ok","oil change") -> ok | Z9: =C9+K9+S9 -> 3 | AA9: =U9+M9+E9 -> 951.1 | AB9: =V9+N9+F9 -> 317.03333 | AC9: =IF(Z9>0,AA9/Z9,0) -> 317.03333 | AD9: =ELEC!Q9 -> 0 | AE9: =SUM(AD9/Z9) -> 0 | AF9: =SUM(AE9/1600) -> 0 | AG9: =SUM(320*AF9) -> 0 | AH9: =SUM(AC9-AG9) -> 317.03333 | AI9: =AD9*AJ9 -> 0 | AJ9: 0.25738397 | AK9: =IF(Z9>0,AI9/Z9,0) -> 0
A10: =ELEC!C10 -> 44143 | B10: 9319 | C10: =B10-B9 -> 0 | D10: 268430 | E10: =SUM(D10-D9) -> 0 | F10: =IF(C10>0,E10/C10,0) -> 0 | H10: =H9 -> 9298 | I10: =IF(B10-H10<=0,"ok","oil change") -> oil change | J10: 10698 | K10: =J10-J9 -> 0 | L10: =L9 -> 357691 | M10: =SUM(L10-L9) -> 0 | N10: =IF(K10>0,M10/K10,0) -> 0 | P10: 10873 | Q10: =IF(J10-P10<=0,"ok","oil change") -> ok | R10: 11722 | S10: =R10-R9 -> 3 | T10: 361915 | U10: =SUM(T10-T9) -> 777.6 | V10: =IF(S10>0,U10/S10,0) -> 259.2 | X10: =X9 -> 11781 | Y10: =IF(R10-X10<=0,"ok","oil change") -> ok | Z10: =C10+K10+S10 -> 3 | AA10: =U10+M10+E10 -> 777.6 | AB10: =V10+N10+F10 -> 259.2 | AC10: =IF(Z10>0,AA10/Z10,0) -> 259.2 | AD10: =ELEC!Q10 -> 2000 | AE10: =SUM(AD10/Z10) -> 666.66667 | AF10: =SUM(AE10/1600) -> 0.41666667 | AG10: =SUM(320*AF10) -> 133.33333 | AH10: =SUM(AC10-AG10) -> 125.86667 | AI10: =AD10*AJ10 -> 514.76793 | AJ10: =305/1185 -> 0.25738397 | AK10: =IF(Z10>0,AI10/Z10,0) -> 171.58931
A11: =ELEC!C11 -> 44144 | B11: =B10 -> 9319 | C11: =B11-B10 -> 0 | D11: =D10 -> 268430 | E11: =SUM(D11-D10) -> 0 | F11: =IF(C11>0,E11/C11,0) -> 0 | H11: =H10 -> 9298 | I11: =IF(B11-H11<=0,"ok","oil change") -> oil change | J11: =J10 -> 10698 | K11: =J11-J10 -> 0 | L11: =L10 -> 357691 | M11: =SUM(L11-L10) -> 0 | N11: =IF(K11>0,M11/K11,0) -> 0 | P11: =P10 -> 10873 | Q11: =IF(J11-P11<=0,"ok","oil change") -> ok | R11: 11725 | S11: =R11-R10 -> 3 | T11: 362694 | U11: =SUM(T11-T10) -> 779 | V11: =IF(S11>0,U11/S11,0) -> 259.66667 | X11: =X10 -> 11781 | Y11: =IF(R11-X11<=0,"ok","oil change") -> ok | Z11: =C11+K11+S11 -> 3 | AA11: =U11+M11+E11 -> 779 | AB11: =V11+N11+F11 -> 259.66667 | AC11: =IF(Z11>0,AA11/Z11,0) -> 259.66667 | AD11: =ELEC!Q11 -> 1000 | AE11: =SUM(AD11/Z11) -> 333.33333 | AF11: =SUM(AE11/1600) -> 0.20833333 | AG11: =SUM(320*AF11) -> 66.666667 | AH11: =SUM(AC11-AG11) -> 193 | AI11: =AD11*AJ11 -> 257.38397 | AJ11: =305/1185 -> 0.25738397 | AK11: =IF(Z11>0,AI11/Z11,0) -> 85.794655
A12: =ELEC!C12 -> 44145 | B12: =B11 -> 9319 | C12: =B12-B11 -> 0 | D12: =D11 -> 268430 | E12: =SUM(D12-D11) -> 0 | F12: =IF(C12>0,E12/C12,0) -> 0 | H12: =H11 -> 9298 | I12: =IF(B12-H12<=0,"ok","oil change") -> oil change | J12: =J11 -> 10698 | K12: =J12-J11 -> 0 | L12: =L11 -> 357691 | M12: =SUM(L12-L11) -> 0 | N12: =IF(K12>0,M12/K12,0) -> 0 | P12: =P11 -> 10873 | Q12: =IF(J12-P12<=0,"ok","oil change") -> ok | R12: 11726 | S12: =R12-R11 -> 1 | T12: 363022 | U12: =SUM(T12-T11) -> 328 | V12: =IF(S12>0,U12/S12,0) -> 328 | X12: =X11 -> 11781 | Y12: =IF(R12-X12<=0,"ok","oil change") -> ok | Z12: =C12+K12+S12 -> 1 | AA12: =U12+M12+E12 -> 328 | AB12: =V12+N12+F12 -> 328 | AC12: =IF(Z12>0,AA12/Z12,0) -> 328 | AD12: =ELEC!Q12 -> 1000 | AE12: =SUM(AD12/Z12) -> 1000 | AF12: =SUM(AE12/1600) -> 0.625 | AG12: =SUM(320*AF12) -> 200 | AH12: =SUM(AC12-AG12) -> 128 | AI12: =AD12*AJ12 -> 257.38397 | AJ12: =305/1185 -> 0.25738397 | AK12: =IF(Z12>0,AI12/Z12,0) -> 257.38397
A13: =ELEC!C13 -> 44146 | B13: =B12 -> 9319 | C13: =B13-B12 -> 0 | D13: =D12 -> 268430 | E13: =SUM(D13-D12) -> 0 | F13: =IF(C13>0,E13/C13,0) -> 0 | H13: =H12 -> 9298 | I13: =IF(B13-H13<=0,"ok","oil change") -> oil change | J13: =J12 -> 10698 | K13: =J13-J12 -> 0 | L13: =L12 -> 357691 | M13: =SUM(L13-L12) -> 0 | N13: =IF(K13>0,M13/K13,0) -> 0 | P13: =P12 -> 10873 | Q13: =IF(J13-P13<=0,"ok","oil change") -> ok | R13: 11729 | S13: =R13-R12 -> 3 | T13: 363823 | U13: =SUM(T13-T12) -> 801 | V13: =IF(S13>0,U13/S13,0) -> 267 | X13: =X12+180 -> 11961 | Y13: =IF(R13-X13<=0,"ok","oil change") -> ok | Z13: =C13+K13+S13 -> 3 | AA13: =U13+M13+E13 -> 801 | AB13: =V13+N13+F13 -> 267 | AC13: =IF(Z13>0,AA13/Z13,0) -> 267 | AD13: =ELEC!Q13 -> 1000 | AE13: =SUM(AD13/Z13) -> 333.33333 | AF13: =SUM(AE13/1600) -> 0.20833333 | AG13: =SUM(320*AF13) -> 66.666667 | AH13: =SUM(AC13-AG13) -> 200.33333 | AI13: =AD13*AJ13 -> 257.38397 | AJ13: =305/1185 -> 0.25738397 | AK13: =IF(Z13>0,AI13/Z13,0) -> 85.794655
A14: =ELEC!C14 -> 44147 | B14: =B13 -> 9319 | C14: =B14-B13 -> 0 | D14: 268431 | E14: =SUM(D14-D13) -> 1 | F14: =IF(C14>0,E14/C14,0) -> 0 | H14: =H13 -> 9298 | I14: =IF(B14-H14<=0,"ok","oil change") -> oil change | J14: =J13 -> 10698 | K14: =J14-J13 -> 0 | L14: =L13 -> 357691 | M14: =SUM(L14-L13) -> 0 | N14: =IF(K14>0,M14/K14,0) -> 0 | P14: =P13 -> 10873 | Q14: =IF(J14-P14<=0,"ok","oil change") -> ok | R14: 11733 | S14: =R14-R13 -> 4 | T14: 364617 | U14: =SUM(T14-T13) -> 794 | V14: =IF(S14>0,U14/S14,0) -> 198.5 | X14: =X13 -> 11961 | Y14: =IF(R14-X14<=0,"ok","oil change") -> ok | Z14: =C14+K14+S14 -> 4 | AA14: =U14+M14+E14 -> 795 | AB14: =V14+N14+F14 -> 198.5 | AC14: =IF(Z14>0,AA14/Z14,0) -> 198.75 | AD14: =ELEC!Q14 -> 2000 | AE14: =SUM(AD14/Z14) -> 500 | AF14: =SUM(AE14/1600) -> 0.3125 | AG14: =SUM(320*AF14) -> 100 | AH14: =SUM(AC14-AG14) -> 98.75 | AI14: =AD14*AJ14 -> 514.76793 | AJ14: =305/1185 -> 0.25738397 | AK14: =IF(Z14>0,AI14/Z14,0) -> 128.69198
A15: =ELEC!C15 -> 44148 | B15: =B14 -> 9319 | C15: =B15-B14 -> 0 | D15: =D14 -> 268431 | E15: =SUM(D15-D14) -> 0 | F15: =IF(C15>0,E15/C15,0) -> 0 | H15: =H14 -> 9298 | I15: =IF(B15-H15<=0,"ok","oil change") -> oil change | J15: =J14 -> 10698 | K15: =J15-J14 -> 0 | L15: =L14 -> 357691 | M15: =SUM(L15-L14) -> 0 | N15: =IF(K15>0,M15/K15,0) -> 0 | P15: =P14 -> 10873 | Q15: =IF(J15-P15<=0,"ok","oil change") -> ok | R15: 11736 | S15: =R15-R14 -> 3 | T15: 365406 | U15: =SUM(T15-T14) -> 789 | V15: =IF(S15>0,U15/S15,0) -> 263 | X15: =X14 -> 11961 | Y15: =IF(R15-X15<=0,"ok","oil change") -> ok | Z15: =C15+K15+S15 -> 3 | AA15: =U15+M15+E15 -> 789 | AB15: =V15+N15+F15 -> 263 | AC15: =IF(Z15>0,AA15/Z15,0) -> 263 | AD15: =ELEC!Q15 -> 1000 | AE15: =SUM(AD15/Z15) -> 333.33333 | AF15: =SUM(AE15/1600) -> 0.20833333 | AG15: =SUM(320*AF15) -> 66.666667 | AH15: =SUM(AC15-AG15) -> 196.33333 | AI15: =AD15*AJ15 -> 257.38397 | AJ15: =305/1185 -> 0.25738397 | AK15: =IF(Z15>0,AI15/Z15,0) -> 85.794655
