Workbook

Sheet Total
A1: Site Name | B1: Day | C1: Month | D1: Year | E1: Total Electricity Kwh | F1: Electricity Tariff ($/Kwh) | G1: LPG (Kg) | H1: LPG $/Kg | I1: Water Utility Supply (m3) m3 | J1: Water Utility Supply (m3) $/m3 | K1: Room Nights | L1: Utilities day cost dh
A2: Serengeti | B2: 1 | C2: 11 | D2: 2020 | E2: ='UTILITY REPORT 1'!F3 -> 2415 | F2: =('UTILITY REPORT 1'!E3*'UTILITY REPORT 1'!D3)/'UTILITY REPORT 1'!F3 -> 0.39587992 | G2: 57.42 | H2: 2.165 | I2: =IF('UTILITY REPORT 1'!G3<0,"0",'UTILITY REPORT 1'!G3) -> 54 | J2: 0 | K2: ='UTILITY REPORT 1'!C3 -> 3 | L2: =E2*F2+G2*H2+#REF!*#REF!+I2*J2 -> #REF!
A3: Serengeti | B3: =B2+1 -> 2 | C3: 11 | D3: 2020 | E3: ='UTILITY REPORT 1'!F4 -> 2617 | F3: =('UTILITY REPORT 1'!E4*'UTILITY REPORT 1'!D4)/'UTILITY REPORT 1'!F4 -> 0.42335499 | G3: =IF('Utility summery'!M7<0,"0",'Utility summery'!M7) -> 57.42 | H3: 2.165 | I3: =IF('UTILITY REPORT 1'!G4<0,"0",'UTILITY REPORT 1'!G4) -> 48 | J3: 0 | K3: ='UTILITY REPORT 1'!C4 -> 5 | L3: =E3*F3+G3*H3+#REF!*#REF!+I3*J3 -> #REF!
A4: Serengeti | B4: =B3+1 -> 3 | C4: 11 | D4: 2020 | E4: ='UTILITY REPORT 1'!F5 -> 2592 | F4: =('UTILITY REPORT 1'!E5*'UTILITY REPORT 1'!D5)/'UTILITY REPORT 1'!F5 -> 0.44945602 | G4: =IF('Utility summery'!M8<0,"0",'Utility summery'!M8) -> 50.16 | H4: 2.165 | I4: =IF('UTILITY REPORT 1'!G5<0,"0",'UTILITY REPORT 1'!G5) -> 81 | J4: 0 | K4: ='UTILITY REPORT 1'!C5 -> 7 | L4: =E4*F4+G4*H4+#REF!*#REF!+I4*J4 -> #REF!
A5: Serengeti | B5: =B4+1 -> 4 | C5: 11 | D5: 2020 | E5: ='UTILITY REPORT 1'!F6 -> 2655 | F5: =('UTILITY REPORT 1'!E6*'UTILITY REPORT 1'!D6)/'UTILITY REPORT 1'!F6 -> 0.39410546 | G5: =IF('Utility summery'!M9<0,"0",'Utility summery'!M9) -> 57.816 | H5: 2.165 | I5: =IF('UTILITY REPORT 1'!G6<0,"0",'UTILITY REPORT 1'!G6) -> 50 | J5: 0 | K5: ='UTILITY REPORT 1'!C6 -> 6 | L5: =E5*F5+G5*H5+#REF!*#REF!+I5*J5 -> #REF!
A6: Serengeti | B6: =B5+1 -> 5 | C6: 11 | D6: 2020 | E6: ='UTILITY REPORT 1'!F7 -> 2595 | F6: =('UTILITY REPORT 1'!E7*'UTILITY REPORT 1'!D7)/'UTILITY REPORT 1'!F7 -> 0.4077842 | G6: =IF('Utility summery'!M10<0,"0",'Utility summery'!M10) -> 59.972 | H6: 2.165 | I6: =IF('UTILITY REPORT 1'!G7<0,"0",'UTILITY REPORT 1'!G7) -> 58 | J6: 0 | K6: ='UTILITY REPORT 1'!C7 -> 3 | L6: =E6*F6+G6*H6+#REF!*#REF!+I6*J6 -> #REF!
A7: Serengeti | B7: =B6+1 -> 6 | C7: 11 | D7: 2020 | E7: ='UTILITY REPORT 1'!F8 -> 2217 | F7: =('UTILITY REPORT 1'!E8*'UTILITY REPORT 1'!D8)/'UTILITY REPORT 1'!F8 -> 0.4464682 | G7: =IF('Utility summery'!M11<0,"0",'Utility summery'!M11) -> 52.976 | H7: 2.165 | I7: =IF('UTILITY REPORT 1'!G8<0,"0",'UTILITY REPORT 1'!G8) -> 62 | J7: 0 | K7: ='UTILITY REPORT 1'!C8 -> 6 | L7: =E7*F7+G7*H7+#REF!*#REF!+I7*J7 -> #REF!
A8: Serengeti | B8: =B7+1 -> 7 | C8: 11 | D8: 2020 | E8: ='UTILITY REPORT 1'!F9 -> 2479 | F8: =('UTILITY REPORT 1'!E9*'UTILITY REPORT 1'!D9)/'UTILITY REPORT 1'!F9 -> 0.38424768 | G8: =IF('Utility summery'!M12<0,"0",'Utility summery'!M12) -> 75.68 | H8: 2.165 | I8: =IF('UTILITY REPORT 1'!G9<0,"0",'UTILITY REPORT 1'!G9) -> 83 | J8: 0 | K8: ='UTILITY REPORT 1'!C9 -> 5 | L8: =E8*F8+G8*H8+#REF!*#REF!+I8*J8 -> #REF!
A9: Serengeti | B9: =B8+1 -> 8 | C9: 11 | D9: 2020 | E9: ='UTILITY REPORT 1'!F10 -> 2341 | F9: =('UTILITY REPORT 1'!E10*'UTILITY REPORT 1'!D10)/'UTILITY REPORT 1'!F10 -> 0.43765912 | G9: =IF('Utility summery'!M13<0,"0",'Utility summery'!M13) -> 51.7 | H9: 2.165 | I9: =IF('UTILITY REPORT 1'!G10<0,"0",'UTILITY REPORT 1'!G10) -> 63 | J9: 0 | K9: ='UTILITY REPORT 1'!C10 -> 1 | L9: =E9*F9+G9*H9+#REF!*#REF!+I9*J9 -> #REF!
A10: Serengeti | B10: =B9+1 -> 9 | C10: 11 | D10: 2020 | E10: ='UTILITY REPORT 1'!F11 -> 2360 | F10: =('UTILITY REPORT 1'!E11*'UTILITY REPORT 1'!D11)/'UTILITY REPORT 1'!F11 -> 0.44400424 | G10: =IF('Utility summery'!M14<0,"0",'Utility summery'!M14) -> 53.592 | H10: 2.165 | I10: =IF('UTILITY REPORT 1'!G11<0,"0",'UTILITY REPORT 1'!G11) -> 46 | J10: 0 | K10: ='UTILITY REPORT 1'!C11 -> 2 | L10: =E10*F10+G10*H10+#REF!*#REF!+I10*J10 -> #REF!
A11: Serengeti | B11: =B10+1 -> 10 | C11: 11 | D11: 2020 | E11: ='UTILITY REPORT 1'!F12 -> 2323 | F11: =('UTILITY REPORT 1'!E12*'UTILITY REPORT 1'!D12)/'UTILITY REPORT 1'!F12 -> 0.40174344 | G11: =IF('Utility summery'!M15<0,"0",'Utility summery'!M15) -> 23.54 | H11: 2.165 | I11: =IF('UTILITY REPORT 1'!G12<0,"0",'UTILITY REPORT 1'!G12) -> 53 | J11: 0 | K11: ='UTILITY REPORT 1'!C12 -> 4 | L11: =E11*F11+G11*H11+#REF!*#REF!+I11*J11 -> #REF!
A12: Serengeti | B12: =B11+1 -> 11 | C12: 11 | D12: 2020 | E12: ='UTILITY REPORT 1'!F13 -> 2283 | F12: =('UTILITY REPORT 1'!E13*'UTILITY REPORT 1'!D13)/'UTILITY REPORT 1'!F13 -> 0.41271572 | G12: =IF('Utility summery'!M16<0,"0",'Utility summery'!M16) -> 75.328 | H12: 2.165 | I12: =IF('UTILITY REPORT 1'!G13<0,"0",'UTILITY REPORT 1'!G13) -> 63 | J12: 0 | K12: ='UTILITY REPORT 1'!C13 -> 6 | L12: =E12*F12+G12*H12+#REF!*#REF!+I12*J12 -> #REF!
A13: Serengeti | B13: =B12+1 -> 12 | C13: 11 | D13: 2020 | E13: ='UTILITY REPORT 1'!F14 -> 2328 | F13: =('UTILITY REPORT 1'!E14*'UTILITY REPORT 1'!D14)/'UTILITY REPORT 1'!F14 -> 0.465189 | G13: =IF('Utility summery'!M17<0,"0",'Utility summery'!M17) -> 54.164 | H13: 2.165 | I13: =IF('UTILITY REPORT 1'!G14<0,"0",'UTILITY REPORT 1'!G14) -> 48 | J13: 0 | K13: ='UTILITY REPORT 1'!C14 -> 5 | L13: =E13*F13+G13*H13+#REF!*#REF!+I13*J13 -> #REF!
A14: Serengeti | B14: =B13+1 -> 13 | C14: 11 | D14: 2020 | E14: ='UTILITY REPORT 1'!F15 -> 2362 | F14: =('UTILITY REPORT 1'!E15*'UTILITY REPORT 1'!D15)/'UTILITY REPORT 1'!F15 -> 0.40613463 | G14: =IF('Utility summery'!M18<0,"0",'Utility summery'!M18) -> 68.508 | H14: 2.165 | I14: =IF('UTILITY REPORT 1'!G15<0,"0",'UTILITY REPORT 1'!G15) -> 62 | J14: 0 | K14: ='UTILITY REPORT 1'!C15 -> 7 | L14: =E14*F14+G14*H14+#REF!*#REF!+I14*J14 -> #REF!
... A28: Serengeti | B28: =B27+1 -> 27 | C28: 11 | D28: 2020 | E28: ='UTILITY REPORT 1'!F29 -> 2395 | F28: =('UTILITY REPORT 1'!E29*'UTILITY REPORT 1'!D29)/'UTILITY REPORT 1'!F29 -> 0.42654697 | G28: =IF('Utility summery'!M32<0,"0",'Utility summery'!M32) -> 42.372 | H28: 2.165 | I28: =IF('UTILITY REPORT 1'!G29<0,"0",'UTILITY REPORT 1'!G29) -> 47 | J28: 0 | K28: ='UTILITY REPORT 1'!C29 -> 0 | L28: =E28*F28+G28*H28+#REF!*#REF!+I28*J28 -> #REF!
A29: Serengeti | B29: =B28+1 -> 28 | C29: 11 | D29: 2020 | E29: 2395 | F29: 0.43 | G29: =IF('Utility summery'!M33<0,"0",'Utility summery'!M33) -> 67.716 | H29: 2.165 | I29: =IF('UTILITY REPORT 1'!G30<0,"0",'UTILITY REPORT 1'!G30) -> 45 | J29: 0 | K29: ='UTILITY REPORT 1'!C30 -> 0 | L29: =E29*F29+G29*H29+#REF!*#REF!+I29*J29 -> #REF!
A30: Serengeti | B30: =B29+1 -> 29 | C30: 11 | D30: 2020 | E30: ='UTILITY REPORT 1'!F31 -> 2264 | F30: =('UTILITY REPORT 1'!E31*'UTILITY REPORT 1'!D31)/'UTILITY REPORT 1'!F31 -> 0.42375 | G30: =IF('Utility summery'!M34<0,"0",'Utility summery'!M34) -> 28.996 | H30: 2.165 | I30: =IF('UTILITY REPORT 1'!G31<0,"0",'UTILITY REPORT 1'!G31) -> 62 | J30: 0 | K30: ='UTILITY REPORT 1'!C31 -> 0 | L30: =E30*F30+G30*H30+#REF!*#REF!+I30*J30 -> #REF!
A31: Serengeti | B31: 30 | C31: 11 | D31: 2020 | E31: 2264 | F31: 0.42 | G31: =IF('Utility summery'!M35<0,"0",'Utility summery'!M35) -> 67.848 | H31: 2.165 | I31: =IF('UTILITY REPORT 1'!G32<0,"0",'UTILITY REPORT 1'!G32) -> 46 | J31: 0 | K31: ='UTILITY REPORT 1'!C32 -> 0 | L31: =E31*F31+G31*H31+#REF!*#REF!+I31*J31 -> #REF!

Sheet Submetering
A1: Site Name | B1: Day | C1: Month | D1: Year | E1: Transport Consumption (LT) | F1: Generators Consumption (LT) | G1: Total Electricity Kwh | H1: Kitchen (KWh) | I1: Laundry (KWh) | J1: STP (M3) | K1: RO prodution (M3) | L1: Amani Restaurant (M3) | M1: Kitchen (M3) | N1: Laundry (M3) | O1: Laundry (M3) | P1: Total water Consumption (M3) | Q1: Borehole #1 (M3) | R1: Borehole #2 (M3) | S1: Borehole #3 (M3) | T1: Borehole #4 (M3) | U1: Borehole #5 (M3) | V1: Borehole #6 (M3) | W1: Total Bore holes production (M3) | X1: Room Nights
A2: Serengeti | B2: 1 | C2: 11 | D2: 2020 | E2: ='UTILITY REPORT 1'!I3 -> 0 | F2: ='UTILITY REPORT 1'!E3 -> 956.05 | G2: ='UTILITY REPORT 1'!F3 -> 2415 | H2: =IF('Kit report'!F4<0,"0",'Kit report'!F4) -> 204 | I2: =IF('Kit report'!X4<0,"0",'Kit report'!X4) -> 140 | J2: =IF('Utility summery'!H6<0,"0",'Utility summery'!H6) -> 36 | K2: =IF('UTILITY REPORT 1'!H3<0,"0",'UTILITY REPORT 1'!H3) -> 41 | L2: ='Water-Meter'!K6 -> 0 | M2: ='Water-Meter'!H6 -> 0 | N2: ='Water-Meter'!Q6 -> 5 | O2: =K2*E2+H2*I2+#REF!*#REF!+J2*L2 -> #REF! | P2: ='Water-Meter'!E6 -> 54 | Q2: =IF('Water-Meter'!U6<0,"0",'Water-Meter'!U6) -> 0 | R2: =IF('Water-Meter'!X6<0,"0",'Water-Meter'!X6) -> 0 | S2: =IF('Water-Meter'!AA6<0,"0",'Water-Meter'!AA6) -> 1 | T2: =IF('Water-Meter'!AD6<0,"0",'Water-Meter'!AD6) -> 19 | U2: =IF('Water-Meter'!AG6<0,"0",'Water-Meter'!AG6) -> 0 | V2: =IF('Water-Meter'!AJ6<0,"0",'Water-Meter'!AJ6) -> 22 | W2: ='Water-Meter'!AN6 -> 42 | X2: =Total!K2 -> 3
A3: Serengeti | B3: =B2+1 -> 2 | C3: 11 | D3: 2020 | E3: ='UTILITY REPORT 1'!I4 -> 0 | F3: ='UTILITY REPORT 1'!E4 -> 1107.92 | G3: ='UTILITY REPORT 1'!F4 -> 2617 | H3: =IF('Kit report'!F5<0,"0",'Kit report'!F5) -> 216 | I3: =IF('Kit report'!X5<0,"0",'Kit report'!X5) -> 220 | J3: =IF('Utility summery'!H7<0,"0",'Utility summery'!H7) -> 26 | K3: =IF('UTILITY REPORT 1'!H4<0,"0",'UTILITY REPORT 1'!H4) -> 48 | L3: ='Water-Meter'!K7 -> 1 | M3: ='Water-Meter'!H7 -> 0 | N3: ='Water-Meter'!Q7 -> 3 | O3: =K3*E3+H3*I3+#REF!*#REF!+J3*L3 -> #REF! | P3: ='Water-Meter'!E7 -> 48 | Q3: =IF('Water-Meter'!U7<0,"0",'Water-Meter'!U7) -> 61 | R3: =IF('Water-Meter'!X7<0,"0",'Water-Meter'!X7) -> 0 | S3: =IF('Water-Meter'!AA7<0,"0",'Water-Meter'!AA7) -> 0 | T3: =IF('Water-Meter'!AD7<0,"0",'Water-Meter'!AD7) -> 19 | U3: =IF('Water-Meter'!AG7<0,"0",'Water-Meter'!AG7) -> 0 | V3: =IF('Water-Meter'!AJ7<0,"0",'Water-Meter'!AJ7) -> 23 | W3: ='Water-Meter'!AN7 -> 103 | X3: =Total!K3 -> 5
A4: Serengeti | B4: =B3+1 -> 3 | C4: 11 | D4: 2020 | E4: ='UTILITY REPORT 1'!I5 -> 0 | F4: ='UTILITY REPORT 1'!E5 -> 1164.99 | G4: ='UTILITY REPORT 1'!F5 -> 2592 | H4: =IF('Kit report'!F6<0,"0",'Kit report'!F6) -> 216 | I4: =IF('Kit report'!X6<0,"0",'Kit report'!X6) -> 100 | J4: =IF('Utility summery'!H8<0,"0",'Utility summery'!H8) -> 26 | K4: =IF('UTILITY REPORT 1'!H5<0,"0",'UTILITY REPORT 1'!H5) -> 48 | L4: ='Water-Meter'!K8 -> 2 | M4: ='Water-Meter'!H8 -> 0 | N4: ='Water-Meter'!Q8 -> 11 | O4: =K4*E4+H4*I4+#REF!*#REF!+J4*L4 -> #REF! | P4: ='Water-Meter'!E8 -> 81 | Q4: =IF('Water-Meter'!U8<0,"0",'Water-Meter'!U8) -> 85 | R4: =IF('Water-Meter'!X8<0,"0",'Water-Meter'!X8) -> 0 | S4: =IF('Water-Meter'!AA8<0,"0",'Water-Meter'!AA8) -> 31 | T4: =IF('Water-Meter'!AD8<0,"0",'Water-Meter'!AD8) -> 18 | U4: =IF('Water-Meter'!AG8<0,"0",'Water-Meter'!AG8) -> 0 | V4: =IF('Water-Meter'!AJ8<0,"0",'Water-Meter'!AJ8) -> 21 | W4: ='Water-Meter'!AN8 -> 155 | X4: =Total!K4 -> 7
A5: Serengeti | B5: =B4+1 -> 4 | C5: 11 | D5: 2020 | E5: ='UTILITY REPORT 1'!I6 -> 0 | F5: ='UTILITY REPORT 1'!E6 -> 1046.35 | G5: ='UTILITY REPORT 1'!F6 -> 2655 | H5: =IF('Kit report'!F7<0,"0",'Kit report'!F7) -> 228 | I5: =IF('Kit report'!X7<0,"0",'Kit report'!X7) -> 60 | J5: =IF('Utility summery'!H9<0,"0",'Utility summery'!H9) -> 45 | K5: =IF('UTILITY REPORT 1'!H6<0,"0",'UTILITY REPORT 1'!H6) -> 77 | L5: ='Water-Meter'!K9 -> 1 | M5: ='Water-Meter'!H9 -> 0 | N5: ='Water-Meter'!Q9 -> 9 | O5: =K5*E5+H5*I5+#REF!*#REF!+J5*L5 -> #REF! | P5: ='Water-Meter'!E9 -> 50 | Q5: =IF('Water-Meter'!U9<0,"0",'Water-Meter'!U9) -> 81 | R5: =IF('Water-Meter'!X9<0,"0",'Water-Meter'!X9) -> 0 | S5: =IF('Water-Meter'!AA9<0,"0",'Water-Meter'!AA9) -> 48 | T5: =IF('Water-Meter'!AD9<0,"0",'Water-Meter'!AD9) -> 18 | U5: =IF('Water-Meter'!AG9<0,"0",'Water-Meter'!AG9) -> 0 | V5: =IF('Water-Meter'!AJ9<0,"0",'Water-Meter'!AJ9) -> 22 | W5: ='Water-Meter'!AN9 -> 169 | X5: =Total!K5 -> 6
A6: Serengeti | B6: =B5+1 -> 5 | C6: 11 | D6: 2020 | E6: ='UTILITY REPORT 1'!I7 -> 0 | F6: ='UTILITY REPORT 1'!E7 -> 1058.2 | G6: ='UTILITY REPORT 1'!F7 -> 2595 | H6: =IF('Kit report'!F8<0,"0",'Kit report'!F8) -> 168 | I6: =IF('Kit report'!X8<0,"0",'Kit report'!X8) -> 160 | J6: =IF('Utility summery'!H10<0,"0",'Utility summery'!H10) -> 46 | K6: =IF('UTILITY REPORT 1'!H7<0,"0",'UTILITY REPORT 1'!H7) -> 13 | L6: ='Water-Meter'!K10 -> 1 | M6: ='Water-Meter'!H10 -> 0 | N6: ='Water-Meter'!Q10 -> 10 | O6: =K6*E6+H6*I6+#REF!*#REF!+J6*L6 -> #REF! | P6: ='Water-Meter'!E10 -> 58 | Q6: =IF('Water-Meter'!U10<0,"0",'Water-Meter'!U10) -> 87 | R6: =IF('Water-Meter'!X10<0,"0",'Water-Meter'!X10) -> 0 | S6: =IF('Water-Meter'!AA10<0,"0",'Water-Meter'!AA10) -> 0 | T6: =IF('Water-Meter'!AD10<0,"0",'Water-Meter'!AD10) -> 19 | U6: =IF('Water-Meter'!AG10<0,"0",'Water-Meter'!AG10) -> 0 | V6: =IF('Water-Meter'!AJ10<0,"0",'Water-Meter'!AJ10) -> 13 | W6: ='Water-Meter'!AN10 -> 119 | X6: =Total!K6 -> 3
A7: Serengeti | B7: =B6+1 -> 6 | C7: 11 | D7: 2020 | E7: ='UTILITY REPORT 1'!I8 -> 0 | F7: ='UTILITY REPORT 1'!E8 -> 989.82 | G7: ='UTILITY REPORT 1'!F8 -> 2217 | H7: =IF('Kit report'!F9<0,"0",'Kit report'!F9) -> 240 | I7: =IF('Kit report'!X9<0,"0",'Kit report'!X9) -> 40 | J7: =IF('Utility summery'!H11<0,"0",'Utility summery'!H11) -> 45 | K7: =IF('UTILITY REPORT 1'!H8<0,"0",'UTILITY REPORT 1'!H8) -> 47 | L7: ='Water-Meter'!K11 -> 0 | M7: ='Water-Meter'!H11 -> 0 | N7: ='Water-Meter'!Q11 -> 10 | O7: =K7*E7+H7*I7+#REF!*#REF!+J7*L7 -> #REF! | P7: ='Water-Meter'!E11 -> 62 | Q7: =IF('Water-Meter'!U11<0,"0",'Water-Meter'!U11) -> 15 | R7: =IF('Water-Meter'!X11<0,"0",'Water-Meter'!X11) -> 0 | S7: =IF('Water-Meter'!AA11<0,"0",'Water-Meter'!AA11) -> 0 | T7: =IF('Water-Meter'!AD11<0,"0",'Water-Meter'!AD11) -> 19 | U7: =IF('Water-Meter'!AG11<0,"0",'Water-Meter'!AG11) -> 0 | V7: =IF('Water-Meter'!AJ11<0,"0",'Water-Meter'!AJ11) -> 0 | W7: ='Water-Meter'!AN11 -> 34 | X7: =Total!K7 -> 6
A8: Serengeti | B8: =B7+1 -> 7 | C8: 11 | D8: 2020 | E8: ='UTILITY REPORT 1'!I9 -> 0 | F8: ='UTILITY REPORT 1'!E9 -> 952.55 | G8: ='UTILITY REPORT 1'!F9 -> 2479 | H8: =IF('Kit report'!F10<0,"0",'Kit report'!F10) -> 132 | I8: =IF('Kit report'!X10<0,"0",'Kit report'!X10) -> 160 | J8: =IF('Utility summery'!H12<0,"0",'Utility summery'!H12) -> 46 | K8: =IF('UTILITY REPORT 1'!H9<0,"0",'UTILITY REPORT 1'!H9) -> 45 | L8: ='Water-Meter'!K12 -> 1 | M8: ='Water-Meter'!H12 -> 0 | N8: ='Water-Meter'!Q12 -> 9 | O8: =K8*E8+H8*I8+#REF!*#REF!+J8*L8 -> #REF! | P8: ='Water-Meter'!E12 -> 83 | Q8: =IF('Water-Meter'!U12<0,"0",'Water-Meter'!U12) -> 58 | R8: =IF('Water-Meter'!X12<0,"0",'Water-Meter'!X12) -> 0 | S8: =IF('Water-Meter'!AA12<0,"0",'Water-Meter'!AA12) -> 22 | T8: =IF('Water-Meter'!AD12<0,"0",'Water-Meter'!AD12) -> 18 | U8: =IF('Water-Meter'!AG12<0,"0",'Water-Meter'!AG12) -> 0 | V8: =IF('Water-Meter'!AJ12<0,"0",'Water-Meter'!AJ12) -> 16 | W8: ='Water-Meter'!AN12 -> 114 | X8: =Total!K8 -> 5
A9: Serengeti | B9: =B8+1 -> 8 | C9: 11 | D9: 2020 | E9: ='UTILITY REPORT 1'!I10 -> 0 | F9: ='UTILITY REPORT 1'!E10 -> 1024.56 | G9: ='UTILITY REPORT 1'!F10 -> 2341 | H9: =IF('Kit report'!F11<0,"0",'Kit report'!F11) -> 156 | I9: =IF('Kit report'!X11<0,"0",'Kit report'!X11) -> 120 | J9: =IF('Utility summery'!H13<0,"0",'Utility summery'!H13) -> 46 | K9: =IF('UTILITY REPORT 1'!H10<0,"0",'UTILITY REPORT 1'!H10) -> 51 | L9: ='Water-Meter'!K13 -> 0 | M9: ='Water-Meter'!H13 -> 0 | N9: ='Water-Meter'!Q13 -> 13 | O9: =K9*E9+H9*I9+#REF!*#REF!+J9*L9 -> #REF! | P9: ='Water-Meter'!E13 -> 63 | Q9: =IF('Water-Meter'!U13<0,"0",'Water-Meter'!U13) -> 88 | R9: =IF('Water-Meter'!X13<0,"0",'Water-Meter'!X13) -> 0 | S9: =IF('Water-Meter'!AA13<0,"0",'Water-Meter'!AA13) -> 64 | T9: =IF('Water-Meter'!AD13<0,"0",'Water-Meter'!AD13) -> 19 | U9: =IF('Water-Meter'!AG13<0,"0",'Water-Meter'!AG13) -> 0 | V9: =IF('Water-Meter'!AJ13<0,"0",'Water-Meter'!AJ13) -> 26 | W9: ='Water-Meter'!AN13 -> 197 | X9: =Total!K9 -> 1
A10: Serengeti | B10: =B9+1 -> 9 | C10: 11 | D10: 2020 | E10: ='UTILITY REPORT 1'!I11 -> 0 | F10: ='UTILITY REPORT 1'!E11 -> 1047.85 | G10: ='UTILITY REPORT 1'!F11 -> 2360 | H10: =IF('Kit report'!F12<0,"0",'Kit report'!F12) -> 192 | I10: =IF('Kit report'!X12<0,"0",'Kit report'!X12) -> 120 | J10: =IF('Utility summery'!H14<0,"0",'Utility summery'!H14) -> 41 | K10: =IF('UTILITY REPORT 1'!H11<0,"0",'UTILITY REPORT 1'!H11) -> 47 | L10: ='Water-Meter'!K14 -> 2 | M10: ='Water-Meter'!H14 -> 0 | N10: ='Water-Meter'!Q14 -> 8 | O10: =K10*E10+H10*I10+#REF!*#REF!+J10*L10 -> #REF! | P10: ='Water-Meter'!E14 -> 46 | Q10: =IF('Water-Meter'!U14<0,"0",'Water-Meter'!U14) -> 76 | R10: =IF('Water-Meter'!X14<0,"0",'Water-Meter'!X14) -> 0 | S10: =IF('Water-Meter'!AA14<0,"0",'Water-Meter'!AA14) -> 47 | T10: =IF('Water-Meter'!AD14<0,"0",'Water-Meter'!AD14) -> 18 | U10: =IF('Water-Meter'!AG14<0,"0",'Water-Meter'!AG14) -> 0 | V10: =IF('Water-Meter'!AJ14<0,"0",'Water-Meter'!AJ14) -> 22 | W10: ='Water-Meter'!AN14 -> 163 | X10: =Total!K10 -> 2
A11: Serengeti | B11: =B10+1 -> 10 | C11: 11 | D11: 2020 | E11: ='UTILITY REPORT 1'!I12 -> 0 | F11: ='UTILITY REPORT 1'!E12 -> 933.25 | G11: ='UTILITY REPORT 1'!F12 -> 2323 | H11: =IF('Kit report'!F13<0,"0",'Kit report'!F13) -> 192 | I11: =IF('Kit report'!X13<0,"0",'Kit report'!X13) -> 100 | J11: =IF('Utility summery'!H15<0,"0",'Utility summery'!H15) -> 44 | K11: =IF('UTILITY REPORT 1'!H12<0,"0",'UTILITY REPORT 1'!H12) -> 49 | L11: ='Water-Meter'!K15 -> 1 | M11: ='Water-Meter'!H15 -> 0 | N11: ='Water-Meter'!Q15 -> 11 | O11: =K11*E11+H11*I11+#REF!*#REF!+J11*L11 -> #REF! | P11: ='Water-Meter'!E15 -> 53 | Q11: =IF('Water-Meter'!U15<0,"0",'Water-Meter'!U15) -> 86 | R11: =IF('Water-Meter'!X15<0,"0",'Water-Meter'!X15) -> 0 | S11: =IF('Water-Meter'!AA15<0,"0",'Water-Meter'!AA15) -> 56 | T11: =IF('Water-Meter'!AD15<0,"0",'Water-Meter'!AD15) -> 17 | U11: =IF('Water-Meter'!AG15<0,"0",'Water-Meter'!AG15) -> 0 | V11: =IF('Water-Meter'!AJ15<0,"0",'Water-Meter'!AJ15) -> 23 | W11: ='Water-Meter'!AN15 -> 182 | X11: =Total!K11 -> 4
A12: Serengeti | B12: =B11+1 -> 11 | C12: 11 | D12: 2020 | E12: ='UTILITY REPORT 1'!I13 -> 0 | F12: ='UTILITY REPORT 1'!E13 -> 942.23 | G12: ='UTILITY REPORT 1'!F13 -> 2283 | H12: =IF('Kit report'!F14<0,"0",'Kit report'!F14) -> 204 | I12: =IF('Kit report'!X14<0,"0",'Kit report'!X14) -> 60 | J12: =IF('Utility summery'!H16<0,"0",'Utility summery'!H16) -> 44 | K12: =IF('UTILITY REPORT 1'!H13<0,"0",'UTILITY REPORT 1'!H13) -> 46 | L12: ='Water-Meter'!K16 -> 1 | M12: ='Water-Meter'!H16 -> 0 | N12: ='Water-Meter'!Q16 -> 5 | O12: =K12*E12+H12*I12+#REF!*#REF!+J12*L12 -> #REF! | P12: ='Water-Meter'!E16 -> 63 | Q12: =IF('Water-Meter'!U16<0,"0",'Water-Meter'!U16) -> 85 | R12: =IF('Water-Meter'!X16<0,"0",'Water-Meter'!X16) -> 0 | S12: =IF('Water-Meter'!AA16<0,"0",'Water-Meter'!AA16) -> 55 | T12: =IF('Water-Meter'!AD16<0,"0",'Water-Meter'!AD16) -> 19 | U12: =IF('Water-Meter'!AG16<0,"0",'Water-Meter'!AG16) -> 0 | V12: =IF('Water-Meter'!AJ16<0,"0",'Water-Meter'!AJ16) -> 23 | W12: ='Water-Meter'!AN16 -> 182 | X12: =Total!K12 -> 6
A13: Serengeti | B13: =B12+1 -> 12 | C13: 11 | D13: 2020 | E13: ='UTILITY REPORT 1'!I14 -> 0 | F13: ='UTILITY REPORT 1'!E14 -> 1082.96 | G13: ='UTILITY REPORT 1'!F14 -> 2328 | H13: =IF('Kit report'!F15<0,"0",'Kit report'!F15) -> 204 | I13: =IF('Kit report'!X15<0,"0",'Kit report'!X15) -> 200 | J13: =IF('Utility summery'!H17<0,"0",'Utility summery'!H17) -> 43 | K13: =IF('UTILITY REPORT 1'!H14<0,"0",'UTILITY REPORT 1'!H14) -> 43 | L13: ='Water-Meter'!K17 -> 1 | M13: ='Water-Meter'!H17 -> 0 | N13: ='Water-Meter'!Q17 -> 3 | O13: =K13*E13+H13*I13+#REF!*#REF!+J13*L13 -> #REF! | P13: ='Water-Meter'!E17 -> 48 | Q13: =IF('Water-Meter'!U17<0,"0",'Water-Meter'!U17) -> 2 | R13: =IF('Water-Meter'!X17<0,"0",'Water-Meter'!X17) -> 0 | S13: =IF('Water-Meter'!AA17<0,"0",'Water-Meter'!AA17) -> 55 | T13: =IF('Water-Meter'!AD17<0,"0",'Water-Meter'!AD17) -> 18 | U13: =IF('Water-Meter'!AG17<0,"0",'Water-Meter'!AG17) -> 0 | V13: =IF('Water-Meter'!AJ17<0,"0",'Water-Meter'!AJ17) -> 23 | W13: ='Water-Meter'!AN17 -> 98 | X13: =Total!K13 -> 5
A14: Serengeti | B14: =B13+1 -> 13 | C14: 11 | D14: 2020 | E14: ='UTILITY REPORT 1'!I15 -> 0 | F14: ='UTILITY REPORT 1'!E15 -> 959.29 | G14: ='UTILITY REPORT 1'!F15 -> 2362 | H14: =IF('Kit report'!F16<0,"0",'Kit report'!F16) -> 216 | I14: =IF('Kit report'!X16<0,"0",'Kit report'!X16) -> 80 | J14: =IF('Utility summery'!H18<0,"0",'Utility summery'!H18) -> 41 | K14: =IF('UTILITY REPORT 1'!H15<0,"0",'UTILITY REPORT 1'!H15) -> 42 | L14: ='Water-Meter'!K18 -> 1 | M14: ='Water-Meter'!H18 -> 0 | N14: ='Water-Meter'!Q18 -> 4 | O14: =K14*E14+H14*I14+#REF!*#REF!+J14*L14 -> #REF! | P14: ='Water-Meter'!E18 -> 62 | Q14: =IF('Water-Meter'!U18<0,"0",'Water-Meter'!U18) -> 0 | R14: =IF('Water-Meter'!X18<0,"0",'Water-Meter'!X18) -> 0 | S14: =IF('Water-Meter'!AA18<0,"0",'Water-Meter'!AA18) -> 57 | T14: =IF('Water-Meter'!AD18<0,"0",'Water-Meter'!AD18) -> 19 | U14: =IF('Water-Meter'!AG18<0,"0",'Water-Meter'!AG18) -> 0 | V14: =IF('Water-Meter'!AJ18<0,"0",'Water-Meter'!AJ18) -> 22 | W14: ='Water-Meter'!AN18 -> 98 | X14: =Total!K14 -> 7
... A30: Serengeti | B30: =B29+1 -> 29 | C30: 11 | D30: 2020 | E30: ='UTILITY REPORT 1'!I31 -> 0 | F30: ='UTILITY REPORT 1'!E31 -> 959.37 | G30: ='UTILITY REPORT 1'!F31 -> 2264 | H30: =IF('Kit report'!F32<0,"0",'Kit report'!F32) -> 204 | I30: =IF('Kit report'!X32<0,"0",'Kit report'!X32) -> 160 | J30: =IF('Utility summery'!H34<0,"0",'Utility summery'!H34) -> 37 | K30: =IF('UTILITY REPORT 1'!H31<0,"0",'UTILITY REPORT 1'!H31) -> 44 | L30: ='Water-Meter'!K34 -> 1 | M30: ='Water-Meter'!H34 -> 0 | N30: ='Water-Meter'!Q34 -> 4 | O30: =K30*E30+H30*I30+#REF!*#REF!+J30*L30 -> #REF! | P30: ='Water-Meter'!E34 -> 62 | Q30: =IF('Water-Meter'!U34<0,"0",'Water-Meter'!U34) -> 0 | R30: =IF('Water-Meter'!X34<0,"0",'Water-Meter'!X34) -> 0 | S30: =IF('Water-Meter'!AA34<0,"0",'Water-Meter'!AA34) -> 54 | T30: =IF('Water-Meter'!AD34<0,"0",'Water-Meter'!AD34) -> 20 | U30: =IF('Water-Meter'!AG34<0,"0",'Water-Meter'!AG34) -> 0 | V30: =IF('Water-Meter'!AJ34<0,"0",'Water-Meter'!AJ34) -> 22 | W30: ='Water-Meter'!AN34 -> 96 | X30: =Total!K30 -> 0
A31: Serengeti | B31: 30 | C31: 11 | D31: 2020 | E31: ='UTILITY REPORT 1'!I32 -> 0 | F31: ='UTILITY REPORT 1'!E32 -> 923.68 | G31: ='UTILITY REPORT 1'!F32 -> 0 | H31: =IF('Kit report'!F33<0,"0",'Kit report'!F33) -> 168 | I31: =IF('Kit report'!X33<0,"0",'Kit report'!X33) -> 140 | J31: =IF('Utility summery'!H35<0,"0",'Utility summery'!H35) -> 34 | K31: =IF('UTILITY REPORT 1'!H32<0,"0",'UTILITY REPORT 1'!H32) -> 41 | L31: ='Water-Meter'!K35 -> 1 | M31: ='Water-Meter'!H35 -> 0 | N31: ='Water-Meter'!Q35 -> 2 | O31: =K31*E31+H31*I31+#REF!*#REF!+J31*L31 -> #REF! | P31: ='Water-Meter'!E35 -> 46 | Q31: =IF('Water-Meter'!U35<0,"0",'Water-Meter'!U35) -> 0 | R31: =IF('Water-Meter'!X35<0,"0",'Water-Meter'!X35) -> 0 | S31: =IF('Water-Meter'!AA35<0,"0",'Water-Meter'!AA35) -> 55 | T31: =IF('Water-Meter'!AD35<0,"0",'Water-Meter'!AD35) -> 19 | U31: =IF('Water-Meter'!AG35<0,"0",'Water-Meter'!AG35) -> 0 | V31: =IF('Water-Meter'!AJ35<0,"0",'Water-Meter'!AJ35) -> 23 | W31: ='Water-Meter'!AN35 -> 97 | X31: =Total!K31 -> 0

Sheet UTILITY REPORT 1
A1: UTILITY REPORT
A2: Date | B2: % | C2: Guest Rooms Occupied | D2: Diesel cost Per Liter ($) | E2: Diesel consumption (LT) | F2: Power production (KW) | G2: Water consumption (M3) | H2: RO prodution (M3) | I2: Transport Consupmtion (LT)
A3: =Gen!B11 -> 44136 | B3: =Gen!C11 -> 0.026 | C3: ='Summery Report'!E5 -> 3 | D3: 1 | E3: =Gen!T11 -> 956.05 | F3: =Gen!U11 -> 2415 | G3: ='Water-Meter'!E6 -> 54 | H3: ='Utility report '!AC6 -> 41 | I3: =Gen!AL11 -> 0
A4: =Gen!B12 -> 44137 | B4: =Gen!C12 -> 0.0519 | C4: ='Summery Report'!E6 -> 5 | D4: 1 | E4: =Gen!T12 -> 1107.92 | F4: =Gen!U12 -> 2617 | G4: ='Water-Meter'!E7 -> 48 | H4: ='Utility report '!AC7 -> 48 | I4: =Gen!AL12 -> 0
A5: =Gen!B13 -> 44138 | B5: =Gen!C13 -> 0.0779 | C5: ='Summery Report'!E7 -> 7 | D5: 1 | E5: =Gen!T13 -> 1164.99 | F5: =Gen!U13 -> 2592 | G5: ='Water-Meter'!E8 -> 81 | H5: ='Utility report '!AC8 -> 48 | I5: =Gen!AL13 -> 0
A6: =Gen!B14 -> 44139 | B6: =Gen!C14 -> 0.0649 | C6: ='Summery Report'!E8 -> 6 | D6: 1 | E6: =Gen!T14 -> 1046.35 | F6: =Gen!U14 -> 2655 | G6: ='Water-Meter'!E9 -> 50 | H6: ='Utility report '!AC9 -> 77 | I6: =Gen!AL14 -> 0
A7: =Gen!B15 -> 44140 | B7: =Gen!C15 -> 0.026 | C7: ='Summery Report'!E9 -> 3 | D7: 1 | E7: =Gen!T15 -> 1058.2 | F7: =Gen!U15 -> 2595 | G7: ='Water-Meter'!E10 -> 58 | H7: ='Utility report '!AC10 -> 13 | I7: =Gen!AL15 -> 0
A8: =Gen!B16 -> 44141 | B8: =Gen!C16 -> 0.0649 | C8: ='Summery Report'!E10 -> 6 | D8: 1 | E8: =Gen!T16 -> 989.82 | F8: =Gen!U16 -> 2217 | G8: ='Water-Meter'!E11 -> 62 | H8: ='Utility report '!AC11 -> 47 | I8: =Gen!AL16 -> 0
A9: =Gen!B17 -> 44142 | B9: =Gen!C17 -> 0.0519 | C9: ='Summery Report'!E11 -> 5 | D9: 1 | E9: =Gen!T17 -> 952.55 | F9: =Gen!U17 -> 2479 | G9: ='Water-Meter'!E12 -> 83 | H9: ='Utility report '!AC12 -> 45 | I9: =Gen!AL17 -> 0
A10: =Gen!B18 -> 44143 | B10: =Gen!C18 -> 0 | C10: ='Summery Report'!E12 -> 1 | D10: 1 | E10: =Gen!T18 -> 1024.56 | F10: =Gen!U18 -> 2341 | G10: ='Water-Meter'!E13 -> 63 | H10: ='Utility report '!AC13 -> 51 | I10: =Gen!AL18 -> 0
A11: =Gen!B19 -> 44144 | B11: =Gen!C19 -> 0.013 | C11: ='Summery Report'!E13 -> 2 | D11: 1 | E11: =Gen!T19 -> 1047.85 | F11: =Gen!U19 -> 2360 | G11: ='Water-Meter'!E14 -> 46 | H11: ='Utility report '!AC14 -> 47 | I11: =Gen!AL19 -> 0
A12: =Gen!B20 -> 44145 | B12: =Gen!C20 -> 0.039 | C12: ='Summery Report'!E14 -> 4 | D12: 1 | E12: =Gen!T20 -> 933.25 | F12: =Gen!U20 -> 2323 | G12: ='Water-Meter'!E15 -> 53 | H12: ='Utility report '!AC15 -> 49 | I12: =Gen!AL20 -> 0
A13: =Gen!B21 -> 44146 | B13: =Gen!C21 -> 0.0649 | C13: ='Summery Report'!E15 -> 6 | D13: 1 | E13: =Gen!T21 -> 942.23 | F13: =Gen!U21 -> 2283 | G13: ='Water-Meter'!E16 -> 63 | H13: ='Utility report '!AC16 -> 46 | I13: =Gen!AL21 -> 0
A14: =Gen!B22 -> 44147 | B14: =Gen!C22 -> 0.05 | C14: ='Summery Report'!E16 -> 5 | D14: 1 | E14: =Gen!T22 -> 1082.96 | F14: =Gen!U22 -> 2328 | G14: ='Water-Meter'!E17 -> 48 | H14: ='Utility report '!AC17 -> 43 | I14: =Gen!AL22 -> 0
... A33: =Gen!B41 -> 44166 | B33: =Gen!C41 -> 0 | C33: ='Summery Report'!E35 -> 0 | D33: 1 | E33: =Gen!T41 -> 0 | F33: =Gen!U41 -> 0 | G33: ='Water-Meter'!E36 -> 0 | H33: ='Utility report '!AC36 -> -41932 | I33: =Gen!AL41 -> 0
B34: =Gen!C42 -> 0 | C34: ='Summery Report'!E36 -> 0 | D34: 2 | E34: =Gen!T42 -> 0 | F34: =Gen!U42 -> 0 | G34: ='Water-Meter'!E37 -> 0 | H34: ='Utility report '!AC37 -> 0 | I34: =Gen!AL42 -> 0

Sheet Utility summery
A4: Date | B4: Room Occupied | C4: Electricity Units Generated KW | D4: Diseal | G4: Water | J4: Gas | N4: Cost of utilites
D5: Generator | E5: Transport | F5: Total | G5: RO | H5: STP | I5: Total Consumption | J5: 2 ton | K5: 1 Ton | L5: 1 Ton | M5: Total consumption | N5: Electricity /1.4$/liter | O5: Diseal for Transport | P5: Gas /2.38$/Kg | Q5: Total HLP Cost | R5: Electricity Cost/Room $ | S5: cost/Room $
A6: =Gen!B11 -> 44136 | B6: ='Summery Report'!E5 -> 3 | C6: =Gen!V11 -> 0.39587992 | D6: =Gen!U11 -> 2415 | E6: =Gen!AL11 -> 0 | F6: =Gen!AT11 -> 0 | G6: ='Utility report '!AC6 -> 41 | H6: ='Utility report '!AE6 -> 36 | I6: ='Water-Meter'!E6 -> 54 | J6: ='Lpg (2)'!B10 -> 30 | K6: ='Lpg (2)'!C10 -> 85 | L6: ='Lpg (2)'!D10 -> 85 | M6: ='Lpg (2)'!G10 -> 0 | O6: =E6 -> 0 | P6: ='[1]Lpg (2)'!#REF! -> #REF! | Q6: ='[1]Summery Report'!#REF! -> #REF! | R6: =N6/B6 -> 0 | S6: =Q6/B6 -> #REF!
A7: =Gen!B12 -> 44137 | B7: ='Summery Report'!E6 -> 5 | C7: =Gen!V12 -> 0.42335499 | D7: =Gen!U12 -> 2617 | E7: =Gen!AL12 -> 0 | F7: =Gen!AT12 -> 0 | G7: ='Utility report '!AC7 -> 48 | H7: ='Utility report '!AE7 -> 26 | I7: ='Water-Meter'!E7 -> 48 | J7: ='Lpg (2)'!B11 -> 25 | K7: ='Lpg (2)'!C11 -> 85 | L7: ='Lpg (2)'!D11 -> 85 | M7: ='Lpg (2)'!G11 -> 57.42 | N7: =D7*1.4 -> 3663.8 | O7: =E7*1.4 -> 0 | P7: ='[1]Lpg (2)'!#REF! -> #REF! | Q7: ='[1]Summery Report'!#REF! -> #REF! | R7: =N7/B7 -> 732.76 | S7: =Q7/B7 -> #REF!
A8: =Gen!B13 -> 44138 | B8: ='Summery Report'!E7 -> 7 | C8: =Gen!V13 -> 0.44945602 | D8: =Gen!U13 -> 2592 | E8: =Gen!AL13 -> 0 | F8: =Gen!AT13 -> 0 | G8: ='Utility report '!AC8 -> 48 | H8: ='Utility report '!AE8 -> 26 | I8: ='Water-Meter'!E8 -> 81 | J8: ='Lpg (2)'!B12 -> 22 | K8: ='Lpg (2)'!C12 -> 85 | L8: ='Lpg (2)'!D12 -> 85 | M8: ='Lpg (2)'!G12 -> 50.16 | N8: =D8*1.4 -> 3628.8 | O8: =E8*1.4 -> 0 | P8: ='[1]Lpg (2)'!#REF! -> #REF! | Q8: ='[1]Summery Report'!#REF! -> #REF! | R8: =N8/B8 -> 518.4 | S8: =Q8/B8 -> #REF!
A9: =Gen!B14 -> 44139 | B9: ='Summery Report'!E8 -> 6 | C9: =Gen!V14 -> 0.39410546 | D9: =Gen!U14 -> 2655 | E9: =Gen!AL14 -> 0 | F9: =Gen!AT14 -> 0 | G9: ='Utility report '!AC9 -> 77 | H9: ='Utility report '!AE9 -> 45 | I9: ='Water-Meter'!E9 -> 50 | J9: ='Lpg (2)'!B13 -> 20 | K9: ='Lpg (2)'!C13 -> 85 | L9: ='Lpg (2)'!D13 -> 85 | M9: ='Lpg (2)'!G13 -> 57.816 | N9: =D9*1.4 -> 3717 | O9: =E9*1.4 -> 0 | P9: ='[1]Lpg (2)'!#REF! -> #REF! | Q9: ='[1]Summery Report'!#REF! -> #REF! | R9: =N9/B9 -> 619.5 | S9: =Q9/B9 -> #REF!
A10: =Gen!B15 -> 44140 | B10: ='Summery Report'!E9 -> 3 | C10: =Gen!V15 -> 0.4077842 | D10: =Gen!U15 -> 2595 | E10: =Gen!AL15 -> 0 | F10: =Gen!AT15 -> 0 | G10: ='Utility report '!AC10 -> 13 | H10: ='Utility report '!AE10 -> 46 | I10: ='Water-Meter'!E10 -> 58 | J10: ='Lpg (2)'!B14 -> 19 | K10: ='Lpg (2)'!C14 -> 85 | L10: ='Lpg (2)'!D14 -> 85 | M10: ='Lpg (2)'!G14 -> 59.972 | N10: =D10*1.4 -> 3633 | O10: =E10*1.4 -> 0 | P10: ='[1]Lpg (2)'!#REF! -> #REF! | Q10: ='[1]Summery Report'!#REF! -> #REF! | R10: =N10/B10 -> 1211 | S10: =Q10/B10 -> #REF!
A11: =Gen!B16 -> 44141 | B11: ='Summery Report'!E10 -> 6 | C11: =Gen!V16 -> 0.4464682 | D11: =Gen!U16 -> 2217 | E11: =Gen!AL16 -> 0 | F11: =Gen!AT16 -> 0 | G11: ='Utility report '!AC11 -> 47 | H11: ='Utility report '!AE11 -> 45 | I11: ='Water-Meter'!E11 -> 62 | J11: ='Lpg (2)'!B15 -> 18 | K11: ='Lpg (2)'!C15 -> 85 | L11: ='Lpg (2)'!D15 -> 85 | M11: ='Lpg (2)'!G15 -> 52.976 | N11: =D11*1.4 -> 3103.8 | O11: =E11*1.4 -> 0 | P11: ='[1]Lpg (2)'!#REF! -> #REF! | Q11: ='[1]Summery Report'!#REF! -> #REF! | R11: =N11/B11 -> 517.3 | S11: =Q11/B11 -> #REF!
A12: =Gen!B17 -> 44142 | B12: ='Summery Report'!E11 -> 5 | C12: =Gen!V17 -> 0.38424768 | D12: =Gen!U17 -> 2479 | E12: =Gen!AL17 -> 0 | F12: =Gen!AT17 -> 0 | G12: ='Utility report '!AC12 -> 45 | H12: ='Utility report '!AE12 -> 46 | I12: ='Water-Meter'!E12 -> 83 | J12: ='Lpg (2)'!B16 -> 85 | K12: ='Lpg (2)'!C16 -> 85 | L12: ='Lpg (2)'!D16 -> 85 | M12: ='Lpg (2)'!G16 -> 75.68 | N12: =D12*1.4 -> 3470.6 | O12: =E12*1.4 -> 0 | P12: ='[1]Lpg (2)'!#REF! -> #REF! | Q12: ='[1]Summery Report'!#REF! -> #REF! | R12: =N12/B12 -> 694.12 | S12: =Q12/B12 -> #REF!
A13: =Gen!B18 -> 44143 | B13: ='Summery Report'!E12 -> 1 | C13: =Gen!V18 -> 0.43765912 | D13: =Gen!U18 -> 2341 | E13: =Gen!AL18 -> 0 | F13: =Gen!AT18 -> 0 | G13: ='Utility report '!AC13 -> 51 | H13: ='Utility report '!AE13 -> 46 | I13: ='Water-Meter'!E13 -> 63 | J13: ='Lpg (2)'!B17 -> 85 | K13: ='Lpg (2)'!C17 -> 83 | L13: ='Lpg (2)'!D17 -> 85 | M13: ='Lpg (2)'!G17 -> 51.7 | N13: =D13*1.4 -> 3277.4 | O13: =E13*1.4 -> 0 | P13: ='[1]Lpg (2)'!#REF! -> #REF! | Q13: ='[1]Summery Report'!#REF! -> #REF! | R13: =N13/B13 -> 3277.4 | S13: =Q13/B13 -> #REF!
A14: =Gen!B19 -> 44144 | B14: ='Summery Report'!E13 -> 2 | C14: =Gen!V19 -> 0.44400424 | D14: =Gen!U19 -> 2360 | E14: =Gen!AL19 -> 0 | F14: =Gen!AT19 -> 0 | G14: ='Utility report '!AC14 -> 47 | H14: ='Utility report '!AE14 -> 41 | I14: ='Water-Meter'!E14 -> 46 | J14: ='Lpg (2)'!B18 -> 85 | K14: ='Lpg (2)'!C18 -> 82 | L14: ='Lpg (2)'!D18 -> 85 | M14: ='Lpg (2)'!G18 -> 53.592 | N14: =D14*1.4 -> 3304 | O14: =E14*1.4 -> 0 | P14: ='[1]Lpg (2)'!#REF! -> #REF! | Q14: ='[1]Summery Report'!#REF! -> #REF! | R14: =N14/B14 -> 1652 | S14: =Q14/B14 -> #REF!
A15: =Gen!B20 -> 44145 | B15: ='Summery Report'!E14 -> 4 | C15: =Gen!V20 -> 0.40174344 | D15: =Gen!U20 -> 2323 | E15: =Gen!AL20 -> 0 | F15: =Gen!AT20 -> 0 | G15: ='Utility report '!AC15 -> 49 | H15: ='Utility report '!AE15 -> 44 | I15: ='Water-Meter'!E15 -> 53 | J15: ='Lpg (2)'!B19 -> 85 | K15: ='Lpg (2)'!C19 -> 80 | L15: ='Lpg (2)'!D19 -> 85 | M15: ='Lpg (2)'!G19 -> 23.54 | N15: =D15*1.4 -> 3252.2 | O15: =E15*1.4 -> 0 | P15: ='[1]Lpg (2)'!#REF! -> #REF! | Q15: ='[1]Summery Report'!#REF! -> #REF! | R15: =N15/B15 -> 813.05 | S15: =Q15/B15 -> #REF!
A16: =Gen!B21 -> 44146 | B16: ='Summery Report'!E15 -> 6 | C16: =Gen!V21 -> 0.41271572 | D16: =Gen!U21 -> 2283 | E16: =Gen!AL21 -> 0 | F16: =Gen!AT21 -> 0 | G16: ='Utility report '!AC16 -> 46 | H16: ='Utility report '!AE16 -> 44 | I16: ='Water-Meter'!E16 -> 63 | J16: ='Lpg (2)'!B20 -> 85 | K16: ='Lpg (2)'!C20 -> 72 | L16: ='Lpg (2)'!D20 -> 85 | M16: ='Lpg (2)'!G20 -> 75.328 | N16: =D16*1.4 -> 3196.2 | O16: =E16*1.4 -> 0 | P16: ='[1]Lpg (2)'!#REF! -> #REF! | Q16: ='[1]Summery Report'!#REF! -> #REF! | R16: =N16/B16 -> 532.7 | S16: =Q16/B16 -> #REF!
A17: =Gen!B22 -> 44147 | B17: ='Summery Report'!E16 -> 5 | C17: =Gen!V22 -> 0.465189 | D17: =Gen!U22 -> 2328 | E17: =Gen!AL22 -> 0 | F17: =Gen!AT22 -> 0 | G17: ='Utility report '!AC17 -> 43 | H17: ='Utility report '!AE17 -> 43 | I17: ='Water-Meter'!E17 -> 48 | J17: ='Lpg (2)'!B21 -> 85 | K17: ='Lpg (2)'!C22 -> 61 | L17: ='Lpg (2)'!D21 -> 85 | M17: ='Lpg (2)'!G21 -> 54.164 | N17: =D17*1.4 -> 3259.2 | O17: =E17*1.4 -> 0 | P17: ='[1]Lpg (2)'!#REF! -> #REF! | Q17: ='[1]Summery Report'!#REF! -> #REF! | R17: =N17/B17 -> 651.84 | S17: =Q17/B17 -> #REF!
A18: =Gen!B23 -> 44148 | B18: ='Summery Report'!E17 -> 7 | C18: =Gen!V23 -> 0.40613463 | D18: =Gen!U23 -> 2362 | E18: =Gen!AL23 -> 0 | F18: =Gen!AT23 -> 0 | G18: ='Utility report '!AC18 -> 42 | H18: ='Utility report '!AE18 -> 41 | I18: ='Water-Meter'!E18 -> 62 | J18: ='Lpg (2)'!B22 -> 85 | K18: ='Lpg (2)'!C23 -> 57 | L18: ='Lpg (2)'!D22 -> 85 | M18: ='Lpg (2)'!G22 -> 68.508 | N18: =D18*1.4 -> 3306.8 | O18: =E18*1.4 -> 0 | P18: ='[1]Lpg (2)'!#REF! -> #REF! | Q18: ='[1]Summery Report'!#REF! -> #REF! | R18: =N18/B18 -> 472.4 | S18: =Q18/B18 -> #REF!
A19: =Gen!B24 -> 44149 | B19: ='Summery Report'!E18 -> 15 | C19: =Gen!V24 -> 0.40457563 | D19: =Gen!U24 -> 2380 | E19: =Gen!AL24 -> 0 | F19: =Gen!AT24 -> 0 | G19: ='Utility report '!AC19 -> 42 | H19: ='Utility report '!AE19 -> 45 | I19: ='Water-Meter'!E19 -> 52 | J19: ='Lpg (2)'!B23 -> 85 | K19: ='Lpg (2)'!C24 -> 53 | L19: ='Lpg (2)'!D23 -> 85 | M19: ='Lpg (2)'!G23 -> 69.344 | N19: =D19*1.4 -> 3332 | O19: =E19*1.4 -> 0 | P19: ='[1]Lpg (2)'!#REF! -> #REF! | Q19: ='[1]Summery Report'!#REF! -> #REF! | R19: =N19/B19 -> 222.13333 | S19: =Q19/B19 -> #REF!
A20: =Gen!B25 -> 44150 | B20: ='Summery Report'!E19 -> 13 | C20: =Gen!V25 -> 0.45146341 | D20: =Gen!U25 -> 2337 | E20: =Gen!AL25 -> 0 | F20: =Gen!AT25 -> 0 | G20: ='Utility report '!AC20 -> 39 | H20: ='Utility report '!AE20 -> 43 | I20: ='Water-Meter'!E20 -> 78 | J20: ='Lpg (2)'!B24 -> 85 | K20: ='Lpg (2)'!C25 -> 45 | L20: ='Lpg (2)'!D24 -> 85 | M20: ='Lpg (2)'!G24 -> 95.392 | N20: =D20*1.4 -> 3271.8 | O20: =E20*1.4 -> 0 | P20: ='[1]Lpg (2)'!#REF! -> #REF! | Q20: ='[1]Summery Report'!#REF! -> #REF! | R20: =N20/B20 -> 251.67692 | S20: =Q20/B20 -> #REF!
A21: =Gen!B26 -> 44151 | B21: ='Summery Report'!E20 -> 12 | C21: =Gen!V26 -> 0.4577188 | D21: =Gen!U26 -> 2468 | E21: =Gen!AL26 -> 0 | F21: =Gen!AT26 -> 0 | G21: ='Utility report '!AC21 -> 37 | H21: ='Utility report '!AE21 -> 52 | I21: ='Water-Meter'!E21 -> 52 | J21: ='Lpg (2)'!B25 -> 85 | K21: ='Lpg (2)'!C25 -> 45 | L21: ='Lpg (2)'!D25 -> 85 | M21: ='Lpg (2)'!G25 -> 82.764 | N21: =D21*1.4 -> 3455.2 | O21: =E21*1.4 -> 0 | P21: ='[1]Lpg (2)'!#REF! -> #REF! | Q21: ='[1]Summery Report'!#REF! -> #REF! | R21: =N21/B21 -> 287.93333 | S21: =Q21/B21 -> #REF!
A22: =Gen!B27 -> 44152 | B22: ='Summery Report'!E21 -> 0 | C22: =Gen!V27 -> 0.4099647 | D22: =Gen!U27 -> 2266 | E22: =Gen!AL27 -> 0 | F22: =Gen!AT27 -> 0 | G22: ='Utility report '!AC22 -> 32 | H22: ='Utility report '!AE22 -> 10 | I22: ='Water-Meter'!E22 -> 53 | J22: ='Lpg (2)'!B26 -> 85 | K22: ='Lpg (2)'!C26 -> 42 | L22: ='Lpg (2)'!D26 -> 85 | M22: ='Lpg (2)'!G26 -> 77.572 | N22: =D22*1.4 -> 3172.4 | O22: =E22*1.4 -> 0 | P22: ='[1]Lpg (2)'!#REF! -> #REF! | Q22: ='[1]Summery Report'!#REF! -> #REF! | R22: =N22/B22 -> #DIV/0! | S22: =Q22/B22 -> #REF!
A23: =Gen!B28 -> 44153 | B23: ='Summery Report'!E22 -> 0 | C23: =Gen!V28 -> 0.41586322 | D23: =Gen!U28 -> 2398 | E23: =Gen!AL28 -> 0 | F23: =Gen!AT28 -> 0 | G23: ='Utility report '!AC23 -> 28 | H23: ='Utility report '!AE23 -> 13 | I23: ='Water-Meter'!E23 -> 51 | J23: ='Lpg (2)'!B27 -> 85 | K23: ='Lpg (2)'!C27 -> 35 | L23: ='Lpg (2)'!D27 -> 85 | M23: ='Lpg (2)'!G27 -> 75.284 | N23: =D23*1.4 -> 3357.2 | O23: =E23*1.4 -> 0 | P23: ='[1]Lpg (2)'!#REF! -> #REF! | Q23: ='[1]Summery Report'!#REF! -> #REF! | R23: =N23/B23 -> #DIV/0! | S23: =Q23/B23 -> #REF!
A24: =Gen!B29 -> 44154 | B24: ='Summery Report'!E23 -> 0 | C24: =Gen!V29 -> 0.40265559 | D24: =Gen!U29 -> 2587 | E24: =Gen!AL29 -> 0 | F24: =Gen!AT29 -> 0 | G24: ='Utility report '!AC24 -> 25 | H24: ='Utility report '!AE24 -> 35 | I24: ='Water-Meter'!E24 -> 127 | J24: ='Lpg (2)'!B28 -> 85 | K24: ='Lpg (2)'!C28 -> 31 | L24: ='Lpg (2)'!D28 -> 85 | M24: ='Lpg (2)'!G28 -> 73.524 | N24: =D24*1.4 -> 3621.8 | O24: =E24*1.4 -> 0 | P24: ='[1]Lpg (2)'!#REF! -> #REF! | Q24: ='[1]Summery Report'!#REF! -> #REF! | R24: =N24/B24 -> #DIV/0! | S24: =Q24/B24 -> #REF!
A25: =Gen!B30 -> 44155 | B25: ='Summery Report'!E24 -> 0 | C25: =Gen!V30 -> 0.38775463 | D25: =Gen!U30 -> 2592 | E25: =Gen!AL30 -> 0 | F25: =Gen!AT30 -> 0 | G25: ='Utility report '!AC25 -> 25 | H25: ='Utility report '!AE25 -> 37 | I25: ='Water-Meter'!E25 -> 46 | J25: ='Lpg (2)'!B29 -> 85 | K25: ='Lpg (2)'!C29 -> 25 | L25: ='Lpg (2)'!D29 -> 85 | M25: ='Lpg (2)'!G29 -> 99.176 | N25: =D25*1.4 -> 3628.8 | O25: =E25*1.4 -> 0 | P25: ='[1]Lpg (2)'!#REF! -> #REF! | Q25: ='[1]Summery Report'!#REF! -> #REF! | R25: =N25/B25 -> #DIV/0! | S25: =Q25/B25 -> #REF!
A26: =Gen!B31 -> 44156 | B26: ='Summery Report'!E25 -> 0 | C26: =Gen!V31 -> 0.4135578 | D26: =Gen!U31 -> 2673 | E26: =Gen!AL31 -> 0 | F26: =Gen!AT31 -> 0 | G26: ='Utility report '!AC26 -> 23 | H26: ='Utility report '!AE26 -> 35 | I26: ='Water-Meter'!E26 -> 47 | J26: ='Lpg (2)'!B30 -> 85 | K26: ='Lpg (2)'!C30 -> 20 | L26: ='Lpg (2)'!D30 -> 85 | M26: ='Lpg (2)'!G30 -> 85.36 | N26: =D26*1.4 -> 3742.2 | O26: =E26*1.4 -> 0 | P26: ='[1]Lpg (2)'!#REF! -> #REF! | Q26: ='[1]Summery Report'!#REF! -> #REF! | R26: =N26/B26 -> #DIV/0! | S26: =Q26/B26 -> #REF!
A27: =Gen!B32 -> 44157 | B27: ='Summery Report'!E26 -> 0 | C27: =Gen!V32 -> 0.40388395 | D27: =Gen!U32 -> 2585 | E27: =Gen!AL32 -> 0 | F27: =Gen!AT32 -> 0 | G27: ='Utility report '!AC27 -> 0 | H27: ='Utility report '!AE27 -> 35 | I27: ='Water-Meter'!E27 -> 51 | J27: ='Lpg (2)'!B31 -> 85 | K27: ='Lpg (2)'!C31 -> 15 | L27: ='Lpg (2)'!D31 -> 85 | M27: ='Lpg (2)'!G31 -> 86.548 | N27: =D27*1.4 -> 3619 | O27: =E27*1.4 -> 0 | P27: ='[1]Lpg (2)'!#REF! -> #REF! | Q27: ='[1]Summery Report'!#REF! -> #REF! | R27: =N27/B27 -> #DIV/0! | S27: =Q27/B27 -> #REF!
A28: =Gen!B33 -> 44158 | B28: ='Summery Report'!E27 -> 0 | C28: =Gen!V33 -> 0.41547739 | D28: =Gen!U33 -> 2587 | E28: =Gen!AL33 -> 0 | F28: =Gen!AT33 -> 0 | G28: ='Utility report '!AC28 -> 24 | H28: ='Utility report '!AE28 -> 36 | I28: ='Water-Meter'!E28 -> 61 | J28: ='Lpg (2)'!B32 -> 85 | K28: ='Lpg (2)'!C32 -> 11 | L28: ='Lpg (2)'!D32 -> 85 | M28: ='Lpg (2)'!G32 -> 65.736 | N28: =D28*1.4 -> 3621.8 | O28: =E28*1.4 -> 0 | P28: ='[1]Lpg (2)'!#REF! -> #REF! | Q28: ='[1]Summery Report'!#REF! -> #REF! | R28: =N28/B28 -> #DIV/0! | S28: =Q28/B28 -> #REF!
A29: =Gen!B34 -> 44159 | B29: ='Summery Report'!E28 -> 0 | C29: =Gen!V34 -> 0.42898569 | D29: =Gen!U34 -> 2376 | E29: =Gen!AL34 -> 0 | F29: =Gen!AT34 -> 0 | G29: ='Utility report '!AC29 -> 35 | H29: ='Utility report '!AE29 -> 35 | I29: ='Water-Meter'!E29 -> 49 | J29: ='Lpg (2)'!B33 -> 85 | K29: ='Lpg (2)'!C33 -> 9 | L29: ='Lpg (2)'!D33 -> 85 | M29: ='Lpg (2)'!G33 -> 64.108 | N29: =D29*1.4 -> 3326.4 | O29: =E29*1.4 -> 0 | P29: ='[1]Lpg (2)'!#REF! -> #REF! | Q29: ='[1]Summery Report'!#REF! -> #REF! | R29: =N29/B29 -> #DIV/0! | S29: =Q29/B29 -> #REF!
A30: =Gen!B35 -> 44160 | B30: ='Summery Report'!E29 -> 0 | C30: =Gen!V35 -> 0.43357839 | D30: =Gen!U35 -> 2258 | E30: =Gen!AL35 -> 0 | F30: =Gen!AT35 -> 0 | G30: ='Utility report '!AC30 -> 39 | H30: ='Utility report '!AE30 -> 33 | I30: ='Water-Meter'!E30 -> 50 | J30: ='Lpg (2)'!B34 -> 85 | K30: ='Lpg (2)'!C34 -> 5 | L30: ='Lpg (2)'!D34 -> 85 | M30: ='Lpg (2)'!G34 -> 80.344 | N30: =D30*1.4 -> 3161.2 | O30: =E30*1.4 -> 0 | P30: ='[1]Lpg (2)'!#REF! -> #REF! | Q30: ='[1]Summery Report'!#REF! -> #REF! | R30: =N30/B30 -> #DIV/0! | S30: =Q30/B30 -> #REF!
A31: =Gen!B36 -> 44161 | B31: ='Summery Report'!E30 -> 0 | C31: =Gen!V36 -> 0.41160089 | D31: =Gen!U36 -> 2255 | E31: =Gen!AL36 -> 0 | F31: =Gen!AT36 -> 0 | G31: ='Utility report '!AC31 -> 46 | H31: ='Utility report '!AE31 -> 35 | I31: ='Water-Meter'!E31 -> 56 | J31: ='Lpg (2)'!B35 -> 85 | K31: ='Lpg (2)'!C35 -> 3 | L31: ='Lpg (2)'!D35 -> 85 | M31: ='Lpg (2)'!G35 -> 78.716 | N31: =D31*1.4 -> 3157 | O31: =E31*1.4 -> 0 | P31: ='[1]Lpg (2)'!#REF! -> #REF! | Q31: ='[1]Summery Report'!#REF! -> #REF! | R31: =N31/B31 -> #DIV/0! | S31: =Q31/B31 -> #REF!
A32: =Gen!B37 -> 44162 | B32: ='Summery Report'!E31 -> 0 | C32: =Gen!V37 -> 0.42654697 | D32: =Gen!U37 -> 2395 | E32: =Gen!AL37 -> 0 | F32: =Gen!AT37 -> 0 | G32: ='Utility report '!AC32 -> 46 | H32: ='Utility report '!AE32 -> 32 | I32: ='Water-Meter'!E32 -> 47 | J32: ='Lpg (2)'!B36 -> 85 | K32: ='Lpg (2)'!C36 -> 2 | L32: ='Lpg (2)'!D36 -> 85 | M32: ='Lpg (2)'!G36 -> 42.372 | N32: =D32*1.4 -> 3353 | O32: =E32*1.4 -> 0 | P32: ='[1]Lpg (2)'!#REF! -> #REF! | Q32: ='[1]Summery Report'!#REF! -> #REF! | R32: =N32/B32 -> #DIV/0! | S32: =Q32/B32 -> #REF!
... A36: =Gen!B41 -> 44166 | B36: ='Summery Report'!E35 -> 0 | C36: =Gen!V41 -> #DIV/0! | D36: =Gen!U41 -> 0 | E36: =Gen!AL41 -> 0 | F36: =Gen!AT41 -> 0 | G36: ='Utility report '!AC36 -> -41932 | H36: ='Utility report '!AE36 -> -207823 | I36: ='Water-Meter'!E36 -> 0 | J36: ='Lpg (2)'!B40 -> 0 | K36: ='Lpg (2)'!C40 -> 0 | L36: ='Lpg (2)'!D40 -> 0 | M36: ='Lpg (2)'!G40 -> -323055.44 | N36: =D36*1.4 -> 0 | O36: =E36*1.4 -> 0 | P36: ='[1]Lpg (2)'!#REF! -> #REF! | Q36: ='[1]Summery Report'!#REF! -> #REF! | R36: =N36/B36 -> #DIV/0! | S36: =Q36/B36 -> #REF!
A37: =Gen!B42 -> 0 | B37: ='Summery Report'!E36 -> 0 | C37: =Gen!V42 -> 0 | D37: =Gen!U42 -> 0 | E37: =Gen!AL42 -> 0 | F37: =Gen!AT42 -> 0 | G37: ='Utility report '!AC37 -> 0 | H37: ='Utility report '!AE37 -> 0 | I37: ='Water-Meter'!E37 -> 0 | J37: ='Lpg (2)'!B41 -> 0 | K37: ='Lpg (2)'!C41 -> 0 | L37: ='Lpg (2)'!D41 -> 0 | M37: ='Lpg (2)'!G41 -> 0 | Q37: ='[1]Summery Report'!#REF! -> #REF! | R37: =N37/B37 -> #DIV/0! | S37: =Q37/B37 -> #REF!
A39: Total | B39: =SUM(B7:B37) -> 97 | C39: =SUM(C7:C35) -> #DIV/0! | D39: =SUM(D7:D35) -> 65573 | E39: =SUM(E7:E35) -> 0 | F39: =SUM(F7:F35) -> 0 | G39: =SUM(G7:G35) -> 1126 | H39: =SUM(H7:H35) -> 1073 | I39: =SUM(I7:I35) -> 1690 | J39: =SUM(J7:J35) -> 2144 | ... S39: =SUM(S7:S35) -> #REF!

Sheet Utility report 
A1: DAILY UTILITY REPORT NOVEMBER 2020
A2: Date | B2: Total occupancy | H2: Diesel balance LTS | I2: Diesel Deliveries | J2: Gen.Diesel consumption LTS | L2: Total Diesel consumption LTS | M2: Water Meter reading | N2: Water consumption m³ | O2: R.O WATER PRODUCTION LTRS + TIME | AA2: Total RO production | AB2: RO Meter reading | AD2: 0 | AE2: STP | AF2: GAS TANK A | AG2: GAS TANK B | AH2: GAS TANK C | AI2: Total Gas Tanks | AJ2: Kg /day | AK2: TOTAL GAS cons.
A3: Rate Tsh /$ | B3: 1640 | C3: Diesel cost / lits | D3: 2175 | F3: =SUM(D3/B3) -> 1.3262195 | H3: =Gen!D11 -> 32519.1 | K3: Transport consumption | M3: Balance | O3: PLANT NO 1 | S3: PLANT NO 2 | W3: PLANT NO 3 | AA3: /day | AB3: Balance | AD3: 0 | AE3: Production | AF3: Capacity | AG3: Capacity | AH3: Capacity | AI3: Kg | AJ3: /day | AK3: /day
B4: Rooms OCC | C4: % | D4: Guest Rooms Occ | F4: Electricity Production Cost /Room Occ by guest | G4: All Cost /Room Occ by guest | O4: Flow M3 | P4: Reading Hours Meter | Q4: Hrs | R4: total production M3 | S4: Flow M3 | T4: Reading Hours Meter | U4: Hrs | V4: total production M3 | W4: Flow M3 | X4: READING HOURS METER | Y4: Hrs | Z4: total production M3 | AA4: M3 | AC4: M3 | AE4: M3 | AF4: 2000 | AG4: 1000 | AH4: 1000 | AI4: =SUM([2]Sheet1!$AA$36) -> 950 | AJ4: Kg | AK4: M3
P5: 19032 | T5: 17126 | X5: 25503 | AB5: 40765 | AD5: 206714 | AF5: 0.85 | AG5: 0.85 | AH5: 0.85
A6: =Gen!B11 -> 44136 | B6: ='Summery Report'!E5 -> 3 | C6: =Gen!C11 -> 0.026 | D6: ='Summery Report'!E5 -> 3 | E6: =SUM(F3) -> 1.3262195 | F6: =SUM(J6*E6)/D6 -> 1067.6067 | G6: =SUM(L6*E6)/D6 -> 1067.6067 | H6: =Gen!D11 -> 32519.1 | I6: =Gen!F11 -> 0 | J6: =Gen!U11 -> 2415 | K6: =Gen!AL11 -> 0 | L6: =SUM(J6:K6) -> 2415 | M6: ='Water-Meter'!K46 -> 524.55387 | N6: ='Water-Meter'!E6 -> 54 | P6: 19032 | Q6: =SUM(P6-P5) -> 0 | R6: =SUM(Q6*O6) -> 0 | T6: 17126 | U6: =T6-T5 -> 0 | V6: - | W6: 2.3 | X6: 25523 | Y6: =X6-X5 -> 20 | Z6: =Y6-Y5 -> 20 | AA6: =Z6-Z5 -> 20 | AB6: 40806 | AC6: =AB6-AB5 -> 41 | AD6: 206750 | AE6: =AD6-AD5 -> 36 | AF6: ='Lpg (2)'!B10*2000/85 -> 705.88235 | AG6: ='Lpg (2)'!C10*1000/85 -> 1000 | AH6: ='Lpg (2)'!D10*1000/85 -> 1000 | AI6: =SUM(AF6*2000)+(AG6*1000)+(AH6*1000) -> 3411764.7 | AJ6: =SUM(AI5-AI6) -> -3411764.7
A7: =Gen!B12 -> 44137 | B7: ='Summery Report'!E6 -> 5 | C7: =Gen!C12 -> 0.0519 | D7: ='Summery Report'!E6 -> 5 | E7: =SUM(E6) -> 1.3262195 | F7: =SUM(J7*E7)/D7 -> 694.14329 | G7: =SUM(L7*E7)/D7 -> 694.14329 | H7: =Gen!D12 -> 31563.05 | I7: =Gen!F12 -> 0 | J7: =Gen!U12 -> 2617 | K7: =Gen!AL12 -> 0 | L7: =SUM(J7:K7) -> 2617 | M7: ='Water-Meter'!K47 -> 416.41124 | N7: ='Water-Meter'!E7 -> 48 | P7: 19032 | Q7: =SUM(P7-P6) -> 0 | R7: =SUM(Q7*O7) -> 0 | T7: 17126 | U7: =T7-T6 -> 0 | V7: =SUM(U7*S7) -> 0 | W7: 2.3 | X7: 25548 | Y7: =X7-X6 -> 25 | Z7: =SUM(Y7*W7) -> 57.5 | AA7: =SUM(Z7*X9) -> 1471770 | AB7: 40854 | AC7: =AB7-AB6 -> 48 | AD7: 206776 | AE7: =AD7-AD6 -> 26 | AF7: ='Lpg (2)'!B11*2000/85 -> 588.23529 | AG7: ='Lpg (2)'!C11*1000/85 -> 1000 | AH7: ='Lpg (2)'!D11*1000/85 -> 1000 | AI7: =SUM(AF6*2000)+(AG7*1000)+(AH7*1000) -> 3411764.7 | AJ7: =SUM(AI6-AI7) -> 0
A8: =Gen!B13 -> 44138 | B8: ='Summery Report'!E7 -> 7 | C8: =Gen!C13 -> 0.0779 | D8: ='Summery Report'!E7 -> 7 | E8: =SUM(E7) -> 1.3262195 | F8: =SUM(J8*E8)/D8 -> 491.08014 | G8: =SUM(L8*E8)/D8 -> 491.08014 | H8: =Gen!D13 -> 30433.51 | I8: =Gen!F13 -> 0 | J8: =Gen!U13 -> 2592 | K8: =Gen!AL13 -> 0 | L8: =SUM(J8:K8) -> 2592 | M8: ='Water-Meter'!K48 -> 420.68537 | N8: ='Water-Meter'!E8 -> 81 | P8: 19032 | Q8: =SUM(P8-P7) -> 0 | R8: =SUM(Q8*O8) -> 0 | T8: 17126 | U8: =T8-T7 -> 0 | V8: =SUM(U8*S8) -> 0 | W8: 2.3 | X8: 25572 | Y8: =X8-X7 -> 24 | Z8: =SUM(Y8*W8) -> 55.2 | AA8: =SUM(Z8*X10) -> 1414113.6 | AB8: 40902 | AC8: =AB8-AB7 -> 48 | AD8: 206802 | AE8: =AD8-AD7 -> 26 | AF8: ='Lpg (2)'!B12*2000/85 -> 517.64706 | AG8: ='Lpg (2)'!C12*1000/85 -> 1000 | AH8: ='Lpg (2)'!D12*1000/85 -> 1000 | AI8: =SUM(AF7*2000)+(AG8*1000)+(AH8*1000) -> 3176470.6 | AJ8: =SUM(AI7-AI8) -> 235294.12
A9: =Gen!B14 -> 44139 | B9: ='Summery Report'!E8 -> 6 | C9: =Gen!C14 -> 0.0649 | D9: ='Summery Report'!E8 -> 6 | E9: =SUM(E8) -> 1.3262195 | F9: =SUM(J9*E9)/D9 -> 586.85213 | G9: =SUM(L9*E9)/D9 -> 586.85213 | H9: =Gen!D14 -> 47230.25 | I9: =Gen!F14 -> 18000 | J9: =Gen!U14 -> 2655 | K9: =Gen!AL14 -> 0 | L9: =SUM(J9:K9) -> 2655 | M9: ='Water-Meter'!K49 -> 446.25444 | N9: ='Water-Meter'!E9 -> 50 | P9: 19032 | Q9: =SUM(P9-P8) -> 0 | R9: =SUM(Q9*O9) -> 0 | T9: 17126 | U9: =T9-T8 -> 0 | V9: =SUM(U9*S9) -> 0 | W9: 2.3 | X9: 25596 | Y9: =X9-X8 -> 24 | Z9: =SUM(Y9*W9) -> 55.2 | AA9: =SUM(Z9*X11) -> 1415438.4 | AB9: 40979 | AC9: =AB9-AB8 -> 77 | AD9: 206847 | AE9: =AD9-AD8 -> 45 | AF9: ='Lpg (2)'!B13*2000/85 -> 470.58824 | AG9: ='Lpg (2)'!C13*1000/85 -> 1000 | AH9: ='Lpg (2)'!D13*1000/85 -> 1000 | AI9: =SUM(AF8*2000)+(AG9*1000)+(AH9*1000) -> 3035294.1 | AJ9: =SUM(AI8-AI9) -> 141176.47
A10: =Gen!B15 -> 44140 | B10: ='Summery Report'!E9 -> 3 | C10: =Gen!C15 -> 0.026 | D10: ='Summery Report'!E9 -> 3 | E10: =SUM(E9) -> 1.3262195 | F10: =SUM(J10*E10)/D10 -> 1147.1799 | G10: =SUM(L10*E10)/D10 -> 1147.1799 | H10: =Gen!D15 -> 46132.8 | I10: =Gen!F15 -> 0 | J10: =Gen!U15 -> 2595 | K10: =Gen!AL15 -> 0 | L10: =SUM(J10:K10) -> 2595 | M10: ='Water-Meter'!K50 -> 533.57756 | N10: ='Water-Meter'!E10 -> 58 | P10: 19032 | Q10: =SUM(P10-P9) -> 0 | R10: =SUM(Q10*O10) -> 0 | T10: 17126 | U10: =T10-T9 -> 0 | V10: =SUM(U10*S10) -> 0 | W10: 2.1 | X10: 25618 | Y10: =X10-X9 -> 22 | Z10: =SUM(Y10*W10) -> 46.2 | AA10: =SUM(Z10*X12) -> 1185723 | AB10: 40992 | AC10: =AB10-AB9 -> 13 | AD10: 206893 | AE10: =AD10-AD9 -> 46 | AF10: ='Lpg (2)'!B14*2000/85 -> 447.05882 | AG10: ='Lpg (2)'!C14*1000/85 -> 1000 | AH10: ='Lpg (2)'!D14*1000/85 -> 1000 | AI10: =SUM(AF9*2000)+(AG10*1000)+(AH10*1000) -> 2941176.5 | AJ10: =SUM(AI9-AI10) -> 94117.647
A11: =Gen!B16 -> 44141 | B11: ='Summery Report'!E10 -> 6 | C11: =Gen!C16 -> 0.0649 | D11: ='Summery Report'!E10 -> 6 | E11: =SUM(E10) -> 1.3262195 | F11: =SUM(J11*E11)/D11 -> 490.03811 | G11: =SUM(L11*E11)/D11 -> 490.03811 | H11: =Gen!D16 -> 45014.45 | I11: =Gen!F16 -> 0 | J11: =Gen!U16 -> 2217 | K11: =Gen!AL16 -> 0 | L11: =SUM(J11:K11) -> 2217 | M11: ='Water-Meter'!K51 -> 553.0753 | N11: ='Water-Meter'!E11 -> 62 | P11: 19032 | Q11: =SUM(P11-P10) -> 0 | R11: =SUM(Q11*O11) -> 0 | T11: 17126 | U11: =T11-T10 -> 0 | V11: =SUM(U11*S11) -> 0 | W11: 2.1 | X11: 25642 | Y11: =X11-X10 -> 24 | Z11: =SUM(Y11*W11) -> 50.4 | AA11: =SUM(Z11*X13) -> 1294725.6 | AB11: 41039 | AC11: =AB11-AB10 -> 47 | AD11: 206938 | AE11: =AD11-AD10 -> 45 | AF11: ='Lpg (2)'!B15*2000/85 -> 423.52941 | AG11: ='Lpg (2)'!C15*1000/85 -> 1000 | AH11: ='Lpg (2)'!D15*1000/85 -> 1000 | AI11: =SUM(AF10*2000)+(AG11*1000)+(AH11*1000) -> 2894117.6 | AJ11: =SUM(AI10-AI11) -> 47058.824
A12: =Gen!B17 -> 44142 | B12: ='Summery Report'!E11 -> 5 | C12: =Gen!C17 -> 0.0519 | D12: ='Summery Report'!E11 -> 5 | E12: =SUM(E11) -> 1.3262195 | F12: =SUM(J12*E12)/D12 -> 657.53963 | G12: =SUM(L12*E12)/D12 -> 657.53963 | H12: =Gen!D17 -> 43932.63 | I12: =Gen!F17 -> 0 | J12: =Gen!U17 -> 2479 | K12: =Gen!AL17 -> 0 | L12: =SUM(J12:K12) -> 2479 | M12: ='Water-Meter'!K52 -> 466.9685 | N12: ='Water-Meter'!E12 -> 83 | P12: 19032 | Q12: =SUM(P12-P11) -> 0 | R12: =SUM(Q12*O12) -> 0 | T12: 17126 | U12: =T12-T11 -> 0 | V12: =SUM(U12*S12) -> 0 | W12: 2.3 | X12: 25665 | Y12: =X12-X11 -> 23 | Z12: =SUM(Y12*W12) -> 52.9 | AA12: =SUM(Z12*X14) -> 1360164.8 | AB12: 41084 | AC12: =AB12-AB11 -> 45 | AD12: 206984 | AE12: =AD12-AD11 -> 46 | AF12: ='Lpg (2)'!B16*2000/85 -> 2000 | AG12: ='Lpg (2)'!C16*1000/85 -> 1000 | AH12: ='Lpg (2)'!D16*1000/85 -> 1000 | AI12: =SUM(AF11*2000)+(AG12*1000)+(AH12*1000) -> 2847058.8 | AJ12: =SUM(AI11-AI12) -> 47058.824
A13: =Gen!B18 -> 44143 | B13: ='Summery Report'!E12 -> 1 | C13: =Gen!C18 -> 0 | D13: ='Summery Report'!E12 -> 1 | E13: =SUM(E12) -> 1.3262195 | F13: =SUM(J13*E13)/D13 -> 3104.6799 | G13: =SUM(L13*E13)/D13 -> 3104.6799 | H13: =Gen!D18 -> 42971.68 | I13: =Gen!F18 -> 0 | J13: =Gen!U18 -> 2341 | K13: =Gen!AL18 -> 0 | L13: =SUM(J13:K13) -> 2341 | M13: ='Water-Meter'!K53 -> 419.71089 | N13: ='Water-Meter'!E13 -> 63 | P13: 19032 | Q13: =SUM(P13-P12) -> 0 | R13: =SUM(Q13*O13) -> 0 | T13: 17126 | U13: =T13-T12 -> 0 | V13: =SUM(U13*S13) -> 0 | W13: 2.3 | X13: 25689 | Y13: =X13-X12 -> 24 | Z13: =SUM(Y13*W13) -> 55.2 | AA13: =SUM(Z13*X15) -> 1420627.2 | AB13: 41135 | AC13: =AB13-AB12 -> 51 | AD13: 207030 | AE13: =AD13-AD12 -> 46 | AF13: ='Lpg (2)'!B17*2000/85 -> 2000 | AG13: ='Lpg (2)'!C17*1000/85 -> 976.47059 | AH13: ='Lpg (2)'!D17*1000/85 -> 1000 | AI13: =SUM(AF12*2000)+(AG13*1000)+(AH13*1000) -> 5976470.6 | AJ13: =SUM(AI12-AI13) -> -3129411.8
A14: =Gen!B19 -> 44144 | B14: ='Summery Report'!E13 -> 2 | C14: =Gen!C19 -> 0.013 | D14: ='Summery Report'!E13 -> 2 | E14: =SUM(E13) -> 1.3262195 | F14: =SUM(J14*E14)/D14 -> 1564.939 | G14: =SUM(L14*E14)/D14 -> 1564.939 | H14: =Gen!D19 -> 41947.12 | I14: =Gen!F19 -> 0 | J14: =Gen!U19 -> 2360 | K14: =Gen!AL19 -> 0 | L14: =SUM(J14:K14) -> 2360 | M14: ='Water-Meter'!K54 -> 458.54699 | N14: ='Water-Meter'!E14 -> 46 | P14: 19032 | Q14: =SUM(P14-P13) -> 0 | R14: =SUM(Q14*O14) -> 0 | T14: 17126 | U14: =T14-T13 -> 0 | V14: =SUM(U14*S14) -> 0 | W14: 2.4 | X14: 25712 | Y14: =X14-X13 -> 23 | Z14: =SUM(Y14*W14) -> 55.2 | AA14: =SUM(Z14*X16) -> 1421952 | AB14: 41182 | AC14: =AB14-AB13 -> 47 | AD14: 207071 | AE14: =AD14-AD13 -> 41 | AF14: ='Lpg (2)'!B18*2000/85 -> 2000 | AG14: ='Lpg (2)'!C18*1000/85 -> 964.70588 | AH14: ='Lpg (2)'!D18*1000/85 -> 1000 | AI14: =SUM(AF13*2000)+(AG14*1000)+(AH14*1000) -> 5964705.9 | AJ14: =SUM(AI13-AI14) -> 11764.706
A15: =Gen!B20 -> 44145 | B15: ='Summery Report'!E14 -> 4 | C15: =Gen!C20 -> 0.039 | D15: ='Summery Report'!E14 -> 4 | E15: =SUM(E14) -> 1.3262195 | F15: =SUM(J15*E15)/D15 -> 770.20198 | G15: =SUM(L15*E15)/D15 -> 770.20198 | H15: =Gen!D20 -> 40854.97 | I15: =Gen!F20 -> 0 | J15: =Gen!U20 -> 2323 | K15: =Gen!AL20 -> 0 | L15: =SUM(J15:K15) -> 2323 | M15: ='Water-Meter'!K55 -> 514.39422 | N15: ='Water-Meter'!E15 -> 53 | P15: 19032 | Q15: =SUM(P15-P14) -> 0 | R15: =SUM(Q15*O15) -> 0 | T15: 17126 | U15: =T15-T14 -> 0 | V15: =SUM(U15*S15) -> 0 | W15: 2.2 | X15: 25736 | Y15: =X15-X14 -> 24 | Z15: =SUM(Y15*W15) -> 52.8 | AA15: =SUM(Z15*X17) -> 1361395.2 | AB15: 41231 | AC15: =AB15-AB14 -> 49 | AD15: 207115 | AE15: =AD15-AD14 -> 44 | AF15: ='Lpg (2)'!B19*2000/85 -> 2000 | AG15: ='Lpg (2)'!C19*1000/85 -> 941.17647 | AH15: ='Lpg (2)'!D19*1000/85 -> 1000 | AI15: =SUM(AF15*2000)+(AG15*1000)+(AH15*1000) -> 5941176.5 | AJ15: =SUM(AI14-AI15) -> 23529.412
A16: =Gen!B21 -> 44146 | B16: ='Summery Report'!E15 -> 6 | C16: =Gen!C21 -> 0.0649 | D16: ='Summery Report'!E15 -> 6 | E16: =SUM(E15) -> 1.3262195 | F16: =SUM(J16*E16)/D16 -> 504.62652 | G16: =SUM(L16*E16)/D16 -> 504.62652 | H16: =Gen!D21 -> 39872.98 | I16: =Gen!F21 -> 0 | J16: =Gen!U21 -> 2283 | K16: =Gen!AL21 -> 0 | L16: =SUM(J16:K16) -> 2283 | M16: ='Water-Meter'!K56 -> 580.01324 | N16: ='Water-Meter'!E16 -> 63 | P16: 19032 | Q16: =SUM(P16-P15) -> 0 | R16: =SUM(Q16*O16) -> 0 | T16: 17126 | U16: =T16-T15 -> 0 | V16: =SUM(U16*S16) -> 0 | W16: 2.2 | X16: 25760 | Y16: =X16-X15 -> 24 | Z16: =SUM(Y16*W16) -> 52.8 | AA16: =SUM(Z16*X18) -> 1362662.4 | AB16: 41277 | AC16: =AB16-AB15 -> 46 | AD16: 207159 | AE16: =AD16-AD15 -> 44 | AF16: ='Lpg (2)'!B20*2000/85 -> 2000 | AG16: ='Lpg (2)'!C20*1000/85 -> 847.05882 | AH16: ='Lpg (2)'!D20*1000/85 -> 1000 | AI16: =SUM(AF16*2000)+(AG16*1000)+(AH16*1000) -> 5847058.8 | AJ16: =SUM(AI15-AI16) -> 94117.647
A17: =Gen!B22 -> 44147 | B17: ='Summery Report'!E16 -> 5 | C17: =Gen!C22 -> 0.05 | D17: ='Summery Report'!E16 -> 5 | E17: =SUM(E16) -> 1.3262195 | F17: =SUM(J17*E17)/D17 -> 617.4878 | G17: =SUM(L17*E17)/D17 -> 617.4878 | H17: =Gen!D22 -> 38906.7 | I17: =Gen!F22 -> 0 | J17: =Gen!U22 -> 2328 | K17: =Gen!AL22 -> 0 | L17: =SUM(J17:K17) -> 2328 | M17: ='Water-Meter'!K57 -> 588.12919 | N17: ='Water-Meter'!E17 -> 48 | P17: 19032 | Q17: =SUM(P18-P16) -> 0 | R17: =SUM(Q17*O17) -> 0 | T17: 17126 | U17: =T17-T16 -> 0 | V17: =SUM(U17*S17) -> 0 | W17: 2.2 | X17: 25784 | Y17: =X17-X16 -> 24 | Z17: =SUM(Y17*W17) -> 52.8 | AA17: =SUM(Z17*X19) -> 1363929.6 | AB17: 41320 | AC17: =AB17-AB16 -> 43 | AD17: 207202 | AE17: =AD17-AD16 -> 43 | AF17: ='Lpg (2)'!B21*2000/85 -> 2000 | AG17: ='Lpg (2)'!C21*1000/85 -> 823.52941 | AH17: ='Lpg (2)'!D21*1000/85 -> 1000 | AI17: =SUM(AF17*2000)+(AG17*1000)+(AH17*1000) -> 5823529.4 | AJ17: =SUM(AI16-AI17) -> 23529.412
A18: =Gen!B23 -> 44148 | B18: ='Summery Report'!E17 -> 7 | C18: =Gen!C23 -> 0.0519 | D18: ='Summery Report'!E17 -> 7 | E18: =SUM(E17) -> 1.3262195 | F18: =SUM(J18*E18)/D18 -> 447.50436 | G18: =SUM(L18*E18)/D18 -> 447.50436 | H18: =Gen!D23 -> 37780.34 | I18: =Gen!F23 -> 0 | J18: =Gen!U23 -> 2362 | K18: =Gen!AL23 -> 0 | L18: =SUM(J18:K18) -> 2362 | M18: ='Water-Meter'!K58 -> 555.65602 | N18: ='Water-Meter'!E18 -> 62 | P18: 19032 | R18: =SUM(Q18*O18) -> 0 | T18: 17126 | U18: =T18-T17 -> 0 | V18: =SUM(U18*S18) -> 0 | W18: 2.2 | X18: 25808 | Y18: =X18-X17 -> 24 | Z18: =SUM(Y18*W18) -> 52.8 | AA18: =SUM(Z18*X20) -> 1365196.8 | AB18: 41362 | AC18: =AB18-AB17 -> 42 | AD18: 207243 | AE18: =AD18-AD17 -> 41 | AF18: ='Lpg (2)'!B22*2000/85 -> 2000 | AG18: ='Lpg (2)'!C22*1000/85 -> 717.64706 | AH18: ='Lpg (2)'!D22*1000/85 -> 1000 | AI18: =SUM(AF18*2000)+(AG18*1000)+(AH18*1000) -> 5717647.1 | AJ18: =SUM(AI17-AI18) -> 105882.35
A19: =Gen!B24 -> 44149 | B19: ='Summery Report'!E18 -> 15 | C19: =Gen!C24 -> 0.1818 | D19: ='Summery Report'!E18 -> 15 | E19: =SUM(E18) -> 1.3262195 | F19: =SUM(J19*E19)/D19 -> 210.42683 | G19: =SUM(L19*E19)/D19 -> 210.42683 | H19: =Gen!D24 -> 36687.05 | I19: =Gen!F24 -> 0 | J19: =Gen!U24 -> 2380 | K19: =Gen!AL24 -> 0 | L19: =SUM(J19:K19) -> 2380 | M19: ='Water-Meter'!K59 -> 530.42896 | N19: ='Water-Meter'!E19 -> 52 | P19: 19032 | R19: =SUM(Q19*O19) -> 0 | T19: 17126 | U19: =T19-T18 -> 0 | V19: =SUM(U19*S19) -> 0 | W19: 2.2 | X19: 25832 | Y19: =X19-X18 -> 24 | Z19: =SUM(Y19*W19) -> 52.8 | AA19: =SUM(Z19*X21) -> 1366464 | AB19: 41404 | AC19: =AB19-AB18 -> 42 | AD19: 207288 | AE19: =AD19-AD18 -> 45 | AF19: ='Lpg (2)'!B23*2000/85 -> 2000 | AG19: ='Lpg (2)'!C23*1000/85 -> 670.58824 | AH19: ='Lpg (2)'!D23*1000/85 -> 1000 | AI19: =SUM(AF19*2000)+(AG19*1000)+(AH19*1000) -> 5670588.2 | AJ19: =SUM(AI18-AI19) -> 47058.824
A20: =Gen!B25 -> 44150 | B20: ='Summery Report'!E19 -> 13 | C20: =Gen!C25 -> 0.1429 | D20: ='Summery Report'!E19 -> 13 | E20: =SUM(E19) -> 1.3262195 | F20: =SUM(J20*E20)/D20 -> 238.41346 | G20: =SUM(L20*E20)/D20 -> 238.41346 | H20: =Gen!D25 -> 35724.16 | I20: =Gen!F25 -> 0 | J20: =Gen!U25 -> 2337 | K20: =Gen!AL25 -> 0 | L20: =SUM(J20:K20) -> 2337 | M20: ='Water-Meter'!K60 -> 493.88787 | N20: ='Water-Meter'!E20 -> 78 | P20: 19032 | Q20: =SUM(P20-P19) -> 0 | R20: =SUM(Q20*O20) -> 0 | T20: 17126 | U20: =T20-T19 -> 0 | V20: =SUM(U20*S20) -> 0 | W20: 2 | X20: 25856 | Y20: =X20-X19 -> 24 | Z20: =SUM(Y20*W20) -> 48 | AA20: =SUM(Z20*X22) -> 1243392 | AB20: 41443 | AC20: =AB20-AB19 -> 39 | AD20: 207331 | AE20: =AD20-AD19 -> 43 | AF20: ='Lpg (2)'!B24*2000/85 -> 2000 | AG20: ='Lpg (2)'!C24*1000/85 -> 623.52941 | AH20: ='Lpg (2)'!D24*1000/85 -> 1000 | AI20: =SUM(AF20*2000)+(AG20*1000)+(AH20*1000) -> 5623529.4 | AJ20: =SUM(AI19-AI20) -> 47058.824
A21: =Gen!B26 -> 44151 | B21: ='Summery Report'!E20 -> 12 | C21: =Gen!C26 -> 0.1299 | D21: ='Summery Report'!E20 -> 12 | E21: =SUM(E20) -> 1.3262195 | F21: =SUM(J21*E21)/D21 -> 272.75915 | G21: =SUM(L21*E21)/D21 -> 272.75915 | H21: =Gen!D26 -> 34509.83 | I21: =Gen!F26 -> 0 | J21: =Gen!U26 -> 2468 | K21: =Gen!AL26 -> 0 | L21: =SUM(J21:K21) -> 2468 | M21: ='Water-Meter'!K61 -> 478.03633 | N21: ='Water-Meter'!E21 -> 52 | P21: 19032 | Q21: =SUM(P21-P20) -> 0 | R21: =SUM(Q21*O21) -> 0 | T21: 17126 | U21: =T22-T20 -> 0 | V21: =SUM(U21*S21) -> 0 | W21: 2 | X21: 25880 | Y21: =X21-X20 -> 24 | Z21: =SUM(Y21*W21) -> 48 | AA21: =SUM(Z21*X23) -> 1244544 | AB21: 41480 | AC21: =AB21-AB20 -> 37 | AD21: 207383 | AE21: =AD21-AD20 -> 52 | AF21: ='Lpg (2)'!B25*2000/85 -> 2000 | AG21: ='Lpg (2)'!C25*1000/85 -> 529.41176 | AH21: ='Lpg (2)'!D25*1000/85 -> 1000 | AI21: =SUM(AF21*2000)+(AG21*1000)+(AH21*1000) -> 5529411.8 | AJ21: =SUM(AI20-AI21) -> 94117.647
A22: =Gen!B27 -> 44152 | B22: ='Summery Report'!E21 -> 0 | C22: =Gen!C27 -> 0.03 | D22: ='Summery Report'!E21 -> 0 | E22: =SUM(E21) -> 1.3262195 | F22: =SUM(J22*E22)/D22 -> #DIV/0! | G22: =SUM(L22*E22)/D22 -> #DIV/0! | H22: =Gen!D27 -> 33312.67 | I22: =Gen!F27 -> 0 | J22: =Gen!U27 -> 2266 | K22: =Gen!AL27 -> 0 | L22: =SUM(J22:K22) -> 2266 | M22: ='Water-Meter'!K62 -> 415.70893 | N22: ='Water-Meter'!E22 -> 53 | P22: 19032 | Q22: =SUM(P22-P21) -> 0 | R22: =SUM(Q22*O22) -> 0 | T22: 17126 | U22: =T23-T21 -> 0 | V22: =SUM(U22*S22) -> 0 | W22: 2 | X22: 25904 | Y22: =X22-X21 -> 24 | Z22: =SUM(Y22*W22) -> 48 | AA22: =SUM(Z22*X24) -> 1245696 | AB22: 41512 | AC22: =AB22-AB21 -> 32 | AD22: 207393 | AE22: =AD22-AD21 -> 10 | AF22: ='Lpg (2)'!B26*2000/85 -> 2000 | AG22: ='Lpg (2)'!C26*1000/85 -> 494.11765 | AH22: ='Lpg (2)'!D26*1000/85 -> 1000 | AI22: =SUM(AF22*2000)+(AG22*1000)+(AH22*1000) -> 5494117.6 | AJ22: =SUM(AI21-AI22) -> 35294.118
A23: =Gen!B28 -> 44153 | B23: ='Summery Report'!E22 -> 0 | C23: =Gen!C28 -> 0.104 | D23: ='Summery Report'!E22 -> 0 | E23: =SUM(E22) -> 1.3262195 | F23: =SUM(J23*E23)/D23 -> #DIV/0! | G23: =SUM(L23*E23)/D23 -> #DIV/0! | H23: =Gen!D28 -> 47383.69 | I23: =Gen!F28 -> 15000 | J23: =Gen!U28 -> 2398 | K23: =Gen!AL28 -> 0 | L23: =SUM(J23:K23) -> 2398 | M23: ='Water-Meter'!K63 -> 441.45293 | N23: ='Water-Meter'!E23 -> 51 | P23: 19032 | Q23: =SUM(P23-P22) -> 0 | R23: =SUM(Q23*O23) -> 0 | T23: 17126 | U23: =T24-T22 -> 0 | V23: =SUM(U23*S23) -> 0 | W23: 2 | X23: 25928 | Y23: =X23-X22 -> 24 | Z23: =SUM(Y23*W23) -> 48 | AA23: =SUM(Z23*X25) -> 1246704 | AB23: 41540 | AC23: =AB23-AB22 -> 28 | AD23: 207406 | AE23: =AD23-AD22 -> 13 | AF23: ='Lpg (2)'!B27*2000/85 -> 2000 | AG23: ='Lpg (2)'!C27*1000/85 -> 411.76471 | AH23: ='Lpg (2)'!D27*1000/85 -> 1000 | AI23: =SUM(AF23*2000)+(AG23*1000)+(AH23*1000) -> 5411764.7 | AJ23: =SUM(AI22-AI23) -> 82352.941
A24: =Gen!B29 -> 44154 | B24: ='Summery Report'!E23 -> 0 | C24: =Gen!C29 -> 0.052 | D24: ='Summery Report'!E23 -> 0 | E24: =SUM(E23) -> 1.3262195 | F24: =SUM(J24*E24)/D24 -> #DIV/0! | G24: =SUM(L24*E24)/D24 -> #DIV/0! | H24: =Gen!D29 -> 46363.86 | I24: =Gen!F29 -> 0 | J24: =Gen!U29 -> 2587 | K24: =Gen!AL29 -> 0 | L24: =SUM(J24:K24) -> 2587 | M24: ='Water-Meter'!K64 -> 419.12192 | N24: ='Water-Meter'!E24 -> 127 | P24: 19032 | Q24: =SUM(P24-P23) -> 0 | R24: =SUM(Q24*O24) -> 0 | T24: 17126 | U24: =T24-T23 -> 0 | V24: =SUM(U24*S24) -> 0 | W24: 1.5 | X24: 25952 | Y24: =X24-X23 -> 24 | Z24: =SUM(Y24*W24) -> 36 | AA24: =SUM(Z24*X26) -> 936000 | AB24: 41565 | AC24: =AB24-AB23 -> 25 | AD24: 207441 | AE24: =AD24-AD23 -> 35 | AF24: ='Lpg (2)'!B28*2000/85 -> 2000 | AG24: ='Lpg (2)'!C28*1000/85 -> 364.70588 | AH24: ='Lpg (2)'!D28*1000/85 -> 1000 | AI24: =SUM(AF24*2000)+(AG24*1000)+(AH24*1000) -> 5364705.9 | AJ24: =SUM(AI23-AI24) -> 47058.824
A25: =Gen!B30 -> 44155 | B25: ='Summery Report'!E24 -> 0 | C25: =Gen!C30 -> 0.052 | D25: ='Summery Report'!E24 -> 0 | E25: =SUM(E24) -> 1.3262195 | F25: =SUM(J25*E25)/D25 -> #DIV/0! | G25: =SUM(L25*E25)/D25 -> #DIV/0! | H25: =Gen!D30 -> 45244.14 | I25: =Gen!F30 -> 0 | J25: =Gen!U30 -> 2592 | K25: =Gen!AL30 -> 0 | L25: =SUM(J25:K25) -> 2592 | M25: ='Water-Meter'!K65 -> 384.22555 | N25: ='Water-Meter'!E25 -> 46 | P25: 19032 | Q25: =SUM(P25-P24) -> 0 | R25: =SUM(Q25*O25) -> 0 | T25: 17126 | U25: =T25-T24 -> 0 | V25: =SUM(U25*S25) -> 0 | W25: 1.5 | X25: 25973 | Y25: =X25-X24 -> 21 | Z25: =SUM(Y25*W25) -> 31.5 | AA25: =SUM(Z25*X27) -> 819000 | AB25: 41590 | AC25: =AB25-AB24 -> 25 | AD25: 207478 | AE25: =AD25-AD24 -> 37 | AF25: ='Lpg (2)'!B29*2000/85 -> 2000 | AG25: ='Lpg (2)'!C29*1000/85 -> 294.11765 | AH25: ='Lpg (2)'!D29*1000/85 -> 1000 | AI25: =SUM(AF25*2000)+(AG25*1000)+(AH25*1000) -> 5294117.6 | AJ25: =SUM(AI24-AI25) -> 70588.235
A26: =Gen!B31 -> 44156 | B26: ='Summery Report'!E25 -> 0 | C26: =Gen!C31 -> 0.065 | D26: ='Summery Report'!E25 -> 0 | E26: =SUM(E25) -> 1.3262195 | F26: =SUM(J26*E26)/D26 -> #DIV/0! | G26: =SUM(L26*E26)/D26 -> #DIV/0! | H26: =Gen!D31 -> 44239.08 | I26: =Gen!F31 -> 0 | J26: =Gen!U31 -> 2673 | K26: =Gen!AL31 -> 0 | L26: =SUM(J26:K26) -> 2673 | M26: ='Water-Meter'!K66 -> 408.37459 | N26: ='Water-Meter'!E26 -> 47 | P26: 19032 | Q26: =SUM(P26-P25) -> 0 | R26: =SUM(Q26*O26) -> 0 | T26: 17126 | U26: =T26-T25 -> 0 | V26: =SUM(U26*S26) -> 0 | W26: 0.9 | X26: 26000 | Y26: =X26-X25 -> 27 | Z26: =SUM(Y26*W26) -> 24.3 | AA26: =SUM(Z26*X28) -> 632286 | AB26: 41613 | AC26: =AB26-AB25 -> 23 | AD26: 207513 | AE26: =AD26-AD25 -> 35 | AF26: ='Lpg (2)'!B30*2000/85 -> 2000 | AG26: ='Lpg (2)'!C30*1000/85 -> 235.29412 | AH26: ='Lpg (2)'!D30*1000/85 -> 1000 | AI26: =SUM(AF26*2000)+(AG26*1000)+(AH26*1000) -> 5235294.1 | AJ26: =SUM(AI25-AI26) -> 58823.529
A27: =Gen!B32 -> 44157 | B27: ='Summery Report'!E26 -> 0 | C27: =Gen!C32 -> 0.1 | D27: ='Summery Report'!E26 -> 0 | E27: =SUM(E26) -> 1.3262195 | F27: =SUM(J27*E27)/D27 -> #DIV/0! | G27: =SUM(L27*E27)/D27 -> #DIV/0! | H27: =Gen!D32 -> 42936.25 | I27: =Gen!F32 -> 0 | J27: =Gen!U32 -> 2585 | K27: =Gen!AL32 -> 0 | L27: =SUM(J27:K27) -> 2585 | M27: ='Water-Meter'!K67 -> 467.96764 | N27: ='Water-Meter'!E27 -> 51 | P27: 19032 | Q27: =SUM(P27-P26) -> 0 | R27: =SUM(Q27*O27) -> 0 | T27: 17126 | U27: =T27-T26 -> 0 | V27: =SUM(U27*S27) -> 0 | W27: 0.9 | X27: 26000 | Y27: =X27-X26 -> 0 | Z27: =SUM(Y27*W27) -> 0 | AA27: =SUM(Z27*X29) -> 0 | AB27: 41613 | AC27: =AB27-AB26 -> 0 | AD27: 207548 | AE27: =AD27-AD26 -> 35 | AF27: ='Lpg (2)'!B31*2000/85 -> 2000 | AG27: ='Lpg (2)'!C31*1000/85 -> 176.47059 | AH27: ='Lpg (2)'!D31*1000/85 -> 1000 | AI27: =SUM(AF27*2000)+(AG27*1000)+(AH27*1000) -> 5176470.6 | AJ27: =SUM(AI26-AI27) -> 58823.529
A28: =Gen!B33 -> 44158 | B28: ='Summery Report'!E27 -> 0 | C28: =Gen!C33 -> 0.065 | D28: ='Summery Report'!E27 -> 0 | E28: =SUM(E27) -> 1.3262195 | F28: =SUM(J28*E28)/D28 -> #DIV/0! | G28: =SUM(L28*E28)/D28 -> #DIV/0! | H28: =Gen!D33 -> 41883.06 | I28: =Gen!F33 -> 0 | J28: =Gen!U33 -> 2587 | K28: =Gen!AL33 -> 0 | L28: =SUM(J28:K28) -> 2587 | M28: ='Water-Meter'!K68 -> 560.37328 | N28: ='Water-Meter'!E28 -> 61 | P28: 19032 | Q28: =SUM(P28-P27) -> 0 | R28: =SUM(Q28*O28) -> 0 | T28: 17126 | U28: =T28-T27 -> 0 | V28: =SUM(U28*S28) -> 0 | W28: 0.9 | X28: 26020 | Y28: =X28-X27 -> 20 | Z28: =SUM(Y28*W28) -> 18 | AA28: =SUM(Z28*X30) -> 469206 | AB28: 41637 | AC28: =SUM(AB28-AB27) -> 24 | AD28: 207584 | AE28: =AD28-AD27 -> 36 | AF28: ='Lpg (2)'!B32*2000/85 -> 2000 | AG28: ='Lpg (2)'!C32*1000/85 -> 129.41176 | AH28: ='Lpg (2)'!D32*1000/85 -> 1000 | AI28: =SUM(AF28*2000)+(AG28*1000)+(AH28*1000) -> 5129411.8 | AJ28: =SUM(AI27-AI28) -> 47058.824
A29: =Gen!B34 -> 44159 | B29: ='Summery Report'!E28 -> 0 | C29: =Gen!C34 -> 0.065 | D29: ='Summery Report'!E28 -> 0 | E29: =SUM(E28) -> 1.3262195 | F29: =SUM(J29*E29)/D29 -> #DIV/0! | G29: =SUM(L29*E29)/D29 -> #DIV/0! | H29: =Gen!D34 -> 40808.22 | I29: =Gen!F34 -> 0 | J29: =Gen!U34 -> 2376 | K29: =Gen!AL34 -> 0 | L29: =SUM(J29:K29) -> 2376 | M29: ='Water-Meter'!K69 -> 527.50874 | N29: ='Water-Meter'!E29 -> 49 | P29: 19032 | Q29: =SUM(P29-P28) -> 0 | R29: =SUM(Q29*O29) -> 0 | T29: 17126 | U29: =T29-T28 -> 0 | V29: =SUM(U29*S29) -> 0 | W29: 1.5 | X29: 26044 | Y29: =X29-X28 -> 24 | Z29: =SUM(Y29*W29) -> 36 | AA29: =SUM(Z29*X31) -> 939276 | AB29: 41672 | AC29: =SUM(AB29-AB28) -> 35 | AD29: 207619 | AE29: =AD29-AD28 -> 35 | AF29: ='Lpg (2)'!B33*2000/85 -> 2000 | AG29: ='Lpg (2)'!C33*1000/85 -> 105.88235 | AH29: ='Lpg (2)'!D33*1000/85 -> 1000 | AI29: =SUM(AF29*2000)+(AG29*1000)+(AH29*1000) -> 5105882.4 | AJ29: =SUM(AI28-AI29) -> 23529.412
A30: =Gen!B35 -> 44160 | B30: ='Summery Report'!E29 -> 0 | C30: =Gen!C35 -> 0.039 | D30: ='Summery Report'!E29 -> 0 | E30: =SUM(E29) -> 1.3262195 | F30: =SUM(J30*E30)/D30 -> #DIV/0! | G30: =SUM(L30*E30)/D30 -> #DIV/0! | H30: =Gen!D35 -> 39721.95 | I30: =Gen!F35 -> 0 | J30: =Gen!U35 -> 2258 | K30: =Gen!AL35 -> 0 | L30: =SUM(J30:K30) -> 2258 | M30: ='Water-Meter'!K70 -> 492.05576 | N30: ='Water-Meter'!E30 -> 50 | P30: 19032 | Q30: =SUM(P30-P29) -> 0 | R30: =SUM(Q30*O30) -> 0 | T30: 17126 | U30: =T30-T29 -> 0 | V30: =SUM(U30*S30) -> 0 | W30: 2 | X30: 26067 | Y30: =X30-X29 -> 23 | Z30: =SUM(Y30*W30) -> 46 | AA30: =SUM(Z30*X32) -> 1201290 | AB30: 41711 | AC30: =SUM(AB30-AB29) -> 39 | AD30: 207652 | AE30: =AD30-AD29 -> 33 | AF30: ='Lpg (2)'!B34*2000/85 -> 2000 | AG30: ='Lpg (2)'!C34*1000/85 -> 58.823529 | AH30: ='Lpg (2)'!D34*1000/85 -> 1000 | AI30: =SUM(AF30*2000)+(AG30*1000)+(AH30*1000) -> 5058823.5 | AJ30: =SUM(AI29-AI30) -> 47058.824
A31: =Gen!B36 -> 44161 | B31: ='Summery Report'!E30 -> 0 | C31: =Gen!C36 -> 0.013 | D31: ='Summery Report'!E30 -> 0 | E31: =SUM(E30) -> 1.3262195 | F31: =SUM(J31*E31)/D31 -> #DIV/0! | G31: =SUM(L31*E31)/D31 -> #DIV/0! | H31: =Gen!D36 -> 38722.61 | I31: =Gen!F36 -> 0 | J31: =Gen!U36 -> 2255 | K31: =Gen!AL36 -> 0 | L31: =SUM(J31:K31) -> 2255 | M31: ='Water-Meter'!K71 -> 506.18685 | N31: ='Water-Meter'!E31 -> 56 | P31: 19032 | Q31: =SUM(P31-P30) -> 0 | R31: =SUM(Q31*O31) -> 0 | T31: 17126 | U31: =T31-T30 -> 0 | V31: =SUM(U31*S31) -> 0 | W31: 2 | X31: 26091 | Y31: =X31-X30 -> 24 | Z31: =SUM(Y31*W31) -> 48 | AA31: =SUM(Z31*X33) -> 1254672 | AB31: 41757 | AC31: =SUM(AB31-AB30) -> 46 | AD31: 207687 | AE31: =AD31-AD30 -> 35 | AF31: ='Lpg (2)'!B35*2000/85 -> 2000 | AG31: ='Lpg (2)'!C35*1000/85 -> 35.294118 | AH31: ='Lpg (2)'!D35*1000/85 -> 1000 | AI31: =SUM(AF31*2000)+(AG31*1000)+(AH31*1000) -> 5035294.1 | AJ31: =SUM(AI30-AI31) -> 23529.412
A32: =Gen!B37 -> 44162 | B32: ='Summery Report'!E31 -> 0 | C32: =Gen!C37 -> 0.01 | D32: ='Summery Report'!E31 -> 0 | E32: =SUM(E31) -> 1.3262195 | F32: =SUM(J32*E32)/D32 -> #DIV/0! | G32: =SUM(L32*E32)/D32 -> #DIV/0! | H32: =Gen!D37 -> 37794.45 | I32: =Gen!F37 -> 0 | J32: =Gen!U37 -> 2395 | K32: =Gen!AL37 -> 0 | L32: =SUM(J32:K32) -> 2395 | M32: ='Water-Meter'!K72 -> 552.38451 | N32: ='Water-Meter'!E32 -> 47 | P32: 19032 | Q32: =SUM(P32-P31) -> 0 | R32: =SUM(Q32*O32) -> 0 | T32: 17126 | U32: =T32-T31 -> 0 | V32: =SUM(U32*S32) -> 0 | W32: 2 | X32: 26115 | Y32: =X32-X31 -> 24 | Z32: =SUM(Y32*W32) -> 48 | AA32: =SUM(Z32*X34) -> 1255824 | AB32: 41803 | AC32: =SUM(AB32-AB31) -> 46 | AD32: 207719 | AE32: =AD32-AD31 -> 32 | AF32: ='Lpg (2)'!B36*2000/85 -> 2000 | AG32: ='Lpg (2)'!C36*1000/85 -> 23.529412 | AH32: ='Lpg (2)'!D36*1000/85 -> 1000 | AI32: =SUM(AF32*2000)+(AG32*1000)+(AH32*1000) -> 5023529.4 | AJ32: =SUM(AI31-AI32) -> 11764.706
A33: =Gen!B38 -> 44163 | B33: ='Summery Report'!E32 -> 0 | C33: =Gen!C38 -> 0.026 | D33: ='Summery Report'!E32 -> 0 | E33: =SUM(E32) -> 1.3262195 | F33: =SUM(J33*E33)/D33 -> #DIV/0! | G33: =SUM(L33*E33)/D33 -> #DIV/0! | H33: =Gen!D38 -> 36735.49 | I33: =Gen!F38 -> 0 | J33: =Gen!U38 -> 0 | K33: =Gen!AL38 -> 0 | L33: =SUM(J33:K33) -> 0 | M33: ='Water-Meter'!K73 -> 601.00381 | N33: ='Water-Meter'!E33 -> 45 | P33: 19032 | Q33: =SUM(P33-P32) -> 0 | R33: =SUM(Q33*O33) -> 0 | T33: 17126 | U33: =T33-T32 -> 0 | V33: =SUM(U33*S33) -> 0 | W33: 2 | X33: 26139 | Y33: =X33-X32 -> 24 | Z33: =SUM(Y33*W33) -> 48 | AA33: =SUM(Z33*X35) -> 1256976 | AB33: 41847 | AC33: =SUM(AB33-AB32) -> 44 | AD33: 207752 | AE33: =AD33-AD32 -> 33 | AF33: ='Lpg (2)'!B37*2000/85 -> 2000 | AG33: ='Lpg (2)'!C37*1000/85 -> 11.764706 | AH33: ='Lpg (2)'!D37*1000/85 -> 1000 | AI33: =SUM(AF33*2000)+(AG33*1000)+(AH33*1000) -> 5011764.7 | AJ33: =SUM(AI32-AI33) -> 11764.706
A34: =Gen!B39 -> 44164 | B34: ='Summery Report'!E33 -> 0 | C34: =Gen!C39 -> 0.026 | D34: ='Summery Report'!E33 -> 0 | E34: =SUM(E33) -> 1.3262195 | F34: =SUM(J34*E34)/D34 -> #DIV/0! | G34: =SUM(L34*E34)/D34 -> #DIV/0! | H34: =Gen!D39 -> 35765.87 | I34: =Gen!F39 -> 0 | J34: =Gen!U39 -> 2264 | K34: =Gen!AL39 -> 0 | L34: =SUM(J34:K34) -> 2264 | M34: ='Water-Meter'!K74 -> 583.75136 | N34: ='Water-Meter'!E34 -> 62 | P34: 19032 | Q34: =SUM(P34-P33) -> 0 | R34: =SUM(Q34*O34) -> 0 | T34: 17126 | U34: =T34-T33 -> 0 | V34: =SUM(U34*S34) -> 0 | W34: 2 | X34: 26163 | Y34: =X34-X33 -> 24 | Z34: =SUM(Y34*W34) -> 48 | AA34: =SUM(Z34*X36) -> 0 | AB34: 41891 | AC34: =SUM(AB34-AB33) -> 44 | AD34: 207789 | AE34: =AD34-AD33 -> 37 | AF34: ='Lpg (2)'!B38*2000/85 -> 2000 | AG34: ='Lpg (2)'!C38*1000/85 -> 0 | AH34: ='Lpg (2)'!D38*1000/85 -> 1000 | AI34: =SUM(AF34*2000)+(AG34*1000)+(AH34*1000) -> 5000000 | AJ34: =SUM(AI33-AI34) -> 11764.706
A35: =Gen!B40 -> 44165 | B35: ='Summery Report'!E34 -> 0 | C35: =Gen!C40 -> 0.039 | D35: ='Summery Report'!E34 -> 0 | E35: =SUM(E34) -> 1.3262195 | F35: =SUM(J35*E35)/D35 -> #DIV/0! | G35: =SUM(L35*E35)/D35 -> #DIV/0! | H35: =Gen!D40 -> 34767.9 | I35: =Gen!F40 -> 0 | J35: =Gen!U40 -> 0 | K35: =Gen!AL40 -> 0 | L35: =SUM(J35:K35) -> 0 | M35: ='Water-Meter'!K75 -> 555.20703 | N35: ='Water-Meter'!E35 -> 46 | P35: 19032 | Q35: =SUM(P35-P34) -> 0 | R35: =SUM(Q35*O35) -> 0 | T35: 17126 | U35: =T35-T34 -> 0 | V35: =SUM(U35*S35) -> 0 | W35: 2 | X35: 26187 | Y35: =X35-X34 -> 24 | Z35: =SUM(Y35*W35) -> 48 | AA35: =SUM(Z35*X37) -> 0 | AB35: 41932 | AC35: =SUM(AB35-AB34) -> 41 | AD35: 207823 | AE35: =AD35-AD34 -> 34 | AF35: ='Lpg (2)'!B39*2000/85 -> 2000 | AG35: ='Lpg (2)'!C39*1000/85 -> 0 | AH35: ='Lpg (2)'!D39*1000/85 -> 988.23529 | AI35: =SUM(AF35*2000)+(AG35*1000)+(AH35*1000) -> 4988235.3 | AJ35: =SUM(AI34-AI35) -> 11764.706
A36: =Gen!B41 -> 44166 | B36: ='Summery Report'!E35 -> 0 | C36: =Gen!C41 -> 0 | D36: ='Summery Report'!E35 -> 0 | E36: =SUM(E35) -> 1.3262195 | F36: =SUM(J36*E36)/D36 -> #DIV/0! | G36: =SUM(L36*E36)/D36 -> #DIV/0! | H36: =Gen!D41 -> 33526.22 | I36: =Gen!F41 -> 0 | J36: =Gen!U41 -> 0 | K36: =Gen!AL41 -> 0 | L36: =SUM(J36:K36) -> 0 | M36: ='Water-Meter'!K76 -> 541.07503 | N36: ='Water-Meter'!E36 -> 0 | Q36: =SUM(P36-P35) -> -19032 | R36: =SUM(Q36*O36) -> 0 | U36: =T36-T35 -> -17126 | V36: =SUM(U36*S36) -> 0 | Y36: =X36-X35 -> -26187 | Z36: =SUM(Y36*W36) -> 0 | AA36: =SUM(Z36*X38) -> 0 | AC36: =SUM(AB36-AB35) -> -41932 | AE36: =AD36-AD35 -> -207823 | AF36: ='Lpg (2)'!B40*2000/85 -> 0 | AG36: ='Lpg (2)'!C40*1000/85 -> 0 | AH36: ='Lpg (2)'!D40*1000/85 -> 0 | AI36: =SUM(AF36*1000)+(AG36*1000)+(AH36*2000) -> 0 | AJ36: =SUM(AI35-AI36) -> 4988235.3
A37: =Gen!B42 -> 0 | B37: 0 | J37: =SUM(J6:J36) -> 67988 | L37: =SUM(J37:K37) -> 67988 | M37: ='Water-Meter'!K77 -> 0 | N37: ='Water-Meter'!E37 -> 0 | Q37: =SUM(P37-P36) -> 0 | R37: =SUM(Q37*O37) -> 0 | U37: =T37-T36 -> 0 | V37: =SUM(U37*S37) -> 0 | Y37: =X37-X36 -> 0 | Z37: =SUM(Y37*W37) -> 0 | AA37: =SUM(Z37*X39) -> 0 | AC37: =SUM(AB37-AB36) -> 0 | AE37: =AD37-AD36 -> 0 | AF37: ='Lpg (2)'!B41*2000/85 -> 0 | AG37: ='Lpg (2)'!C41*1000/85 -> 0 | AH37: ='Lpg (2)'!D41*1000/85 -> 0 | AJ37: =SUM(AI36-AI37) -> 0

Sheet Kit report
B1: KITCHEN THREE PHASE KWH METER READING | H1: KITCHEN WATER METER READING | M1: AMANI Restaurant WATER METER READING | T1: LAUNDRY THREE PHASE KWH METER READING | Y1: LAUNDRY WATER METER READING
A2: Occ % | B2: DATE | C2: READING TIME | D2: METER READING OPEN | E2: METER READING ClOSE | F2: UNIT USED Kwh | H2: DATE | I2: READING TIME | J2: METER READING OPEN Cbm | K2: METER READING ClOSE Cbm | L2: UNIT USED Cbm | M2: DATE | N2: READING TIME | O2: METER READING OPEN Cbm | P2: METER READING ClOSE Cbm | Q2: UNIT USED Cbm | R2: Cost Per day Elct+Water $ | S2: % as per the total Lodge consumption | T2: DATE | U2: READING TIME | V2: METER READING OPEN (Kwh) | W2: METER READING ClOSE (Kwh) | X2: UNIT USED Kwh | Y2: DATE | Z2: READING TIME | AA2: METER READING OPEN Cbm | AB2: METER READING ClOSE Cbm | AC2: UNIT USED Cbm
A3: =Gen!B11 -> 44136 | B3: Close Last Month | E3: 8902.2 | F3: X120 | H3: Close Last Month | J3: ='Water-Meter'!G5 -> 38000 | K3: ='Water-Meter'!G5 -> 38000 | M3: Close Last Month | O3: ='Water-Meter'!J5 -> 8086 | P3: ='Water-Meter'!J5 -> 8086 | T3: Close Last Month | W3: 7845.7 | X3: =(W3-V3)*200 -> 1569140 | Y3: Close Last Month
A4: =Gen!C11 -> 0.026 | B4: =Gen!B11 -> 44136 | D4: =E3 -> 8902.2 | E4: 8903.9 | F4: =SUM(E4-D4)*120 -> 204 | H4: =B4 -> 44136 | J4: ='Water-Meter'!G6 -> 38000 | K4: ='Water-Meter'!G6 -> 38000 | L4: =SUM(K4-J4) -> 0 | M4: =H4 -> 44136 | O4: ='Water-Meter'!J6 -> 8086 | P4: ='Water-Meter'!J6 -> 8086 | Q4: =N4-O3 -> -8086 | R4: =SUM(Q4/1615) -> -5.0068111 | S4: =Gen!U11 -> 2415 | T4: =M4 -> 44136 | V4: =W3 -> 7845.7 | W4: 7846.4 | X4: =(W4-V4)*200 -> 140 | Y4: =T4 -> 44136 | AB4: ='Water-Meter'!P6 -> 20406 | AC4: =AA4-AB3 -> 0
A5: =Gen!C12 -> 0.0519 | B5: =Gen!B12 -> 44137 | D5: =E4 -> 8903.9 | E5: 8905.7 | F5: =SUM(E5-D5)*120 -> 216 | H5: =B5 -> 44137 | J5: ='Water-Meter'!G7 -> 38000 | K5: ='Water-Meter'!G7 -> 38000 | L5: =SUM(K5-J5) -> 0 | M5: =H5 -> 44137 | O5: ='Water-Meter'!J7 -> 8087 | P5: ='Water-Meter'!J7 -> 8087 | Q5: =N5-O4 -> -8086 | R5: =SUM(Q5/1615) -> -5.0068111 | S5: =Gen!U12 -> 2617 | T5: =M5 -> 44137 | V5: =W4 -> 7846.4 | W5: 7847.5 | X5: =(W5-V5)*200 -> 220 | Y5: =T5 -> 44137 | AB5: ='Water-Meter'!P7 -> 20409 | AC5: =AA5-AB4 -> -20406
A6: =Gen!C13 -> 0.0779 | B6: =Gen!B13 -> 44138 | D6: =E5 -> 8905.7 | E6: 8907.5 | F6: =SUM(E6-D6)*120 -> 216 | H6: =B6 -> 44138 | J6: ='Water-Meter'!G8 -> 38000 | K6: ='Water-Meter'!G8 -> 38000 | L6: =SUM(K6-J6) -> 0 | M6: =H6 -> 44138 | O6: ='Water-Meter'!J8 -> 8089 | P6: ='Water-Meter'!J8 -> 8089 | Q6: =N6-O5 -> -8087 | R6: =SUM(Q6/1615) -> -5.0074303 | S6: =Gen!U13 -> 2592 | T6: =M6 -> 44138 | V6: =W5 -> 7847.5 | W6: 7848 | X6: =(W6-V6)*200 -> 100 | Y6: =T6 -> 44138 | AB6: ='Water-Meter'!P8 -> 20420 | AC6: =AA6-AB5 -> -20409
A7: =Gen!C14 -> 0.0649 | B7: =Gen!B14 -> 44139 | D7: =E6 -> 8907.5 | E7: 8909.4 | F7: =SUM(E7-D7)*120 -> 228 | H7: =B7 -> 44139 | J7: ='Water-Meter'!G9 -> 38000 | K7: ='Water-Meter'!G9 -> 38000 | L7: =SUM(K7-J7) -> 0 | M7: =H7 -> 44139 | O7: ='Water-Meter'!J9 -> 8090 | P7: ='Water-Meter'!J9 -> 8090 | Q7: =N7-O6 -> -8089 | R7: =SUM(Q7/1615) -> -5.0086687 | S7: =Gen!U14 -> 2655 | T7: =M7 -> 44139 | V7: =W6 -> 7848 | W7: 7848.3 | X7: =(W7-V7)*200 -> 60 | Y7: =T7 -> 44139 | AB7: ='Water-Meter'!P9 -> 20429 | AC7: =AA7-AB6 -> -20420
A8: =Gen!C15 -> 0.026 | B8: =Gen!B15 -> 44140 | D8: =E7 -> 8909.4 | E8: 8910.8 | F8: =SUM(E8-D8)*120 -> 168 | H8: =B8 -> 44140 | J8: ='Water-Meter'!G10 -> 38000 | K8: ='Water-Meter'!G10 -> 38000 | L8: =SUM(K8-J8) -> 0 | M8: =H8 -> 44140 | O8: ='Water-Meter'!J10 -> 8091 | P8: ='Water-Meter'!J10 -> 8091 | Q8: =N8-O7 -> -8090 | R8: =SUM(Q8/1615) -> -5.0092879 | S8: =Gen!U15 -> 2595 | T8: =M8 -> 44140 | V8: =W7 -> 7848.3 | W8: 7849.1 | X8: =(W8-V8)*200 -> 160 | Y8: =T8 -> 44140 | AB8: ='Water-Meter'!P10 -> 20439 | AC8: =AA8-AB7 -> -20429
A9: =Gen!C16 -> 0.0649 | B9: =Gen!B16 -> 44141 | D9: =E8 -> 8910.8 | E9: 8912.8 | F9: =SUM(E9-D9)*120 -> 240 | H9: =B9 -> 44141 | J9: ='Water-Meter'!G11 -> 38000 | K9: ='Water-Meter'!G11 -> 38000 | L9: =SUM(K9-J9) -> 0 | M9: =H9 -> 44141 | O9: ='Water-Meter'!J11 -> 8091 | P9: ='Water-Meter'!J11 -> 8091 | Q9: =N9-O8 -> -8091 | R9: =SUM(Q9/1615) -> -5.0099071 | S9: =Gen!U16 -> 2217 | T9: =M9 -> 44141 | V9: =W8 -> 7849.1 | W9: 7849.3 | X9: =(W9-V9)*200 -> 40 | Y9: =T9 -> 44141 | AB9: ='Water-Meter'!P11 -> 20449 | AC9: =AA9-AB8 -> -20439
A10: =Gen!C17 -> 0.0519 | B10: =Gen!B17 -> 44142 | D10: =E9 -> 8912.8 | E10: 8913.9 | F10: =SUM(E10-D10)*120 -> 132 | H10: =B10 -> 44142 | J10: ='Water-Meter'!G12 -> 38000 | K10: ='Water-Meter'!G12 -> 38000 | L10: =SUM(K10-J10) -> 0 | M10: =H10 -> 44142 | O10: ='Water-Meter'!J12 -> 8092 | P10: ='Water-Meter'!J12 -> 8092 | Q10: =N10-O9 -> -8091 | R10: =SUM(Q10/1615) -> -5.0099071 | S10: =Gen!U17 -> 2479 | T10: =M10 -> 44142 | V10: =W9 -> 7849.3 | W10: 7850.1 | X10: =(W10-V10)*200 -> 160 | Y10: =T10 -> 44142 | AB10: ='Water-Meter'!P12 -> 20458 | AC10: =AA10-AB9 -> -20449
A11: =Gen!C18 -> 0 | B11: =Gen!B18 -> 44143 | D11: =E10 -> 8913.9 | E11: 8915.2 | F11: =SUM(E11-D11)*120 -> 156 | H11: =B11 -> 44143 | J11: ='Water-Meter'!G13 -> 38000 | K11: ='Water-Meter'!G13 -> 38000 | L11: =SUM(K11-J11) -> 0 | M11: =H11 -> 44143 | O11: ='Water-Meter'!J13 -> 8092 | P11: ='Water-Meter'!J13 -> 8092 | Q11: =N11-O10 -> -8092 | R11: =SUM(Q11/1615) -> -5.0105263 | S11: =Gen!U18 -> 2341 | T11: =M11 -> 44143 | V11: =W10 -> 7850.1 | W11: 7850.7 | X11: =(W11-V11)*200 -> 120 | Y11: =T11 -> 44143 | AB11: ='Water-Meter'!P13 -> 20471 | AC11: =AA11-AB10 -> -20458
A12: =Gen!C19 -> 0.013 | B12: =Gen!B19 -> 44144 | D12: =E11 -> 8915.2 | E12: 8916.8 | F12: =SUM(E12-D12)*120 -> 192 | H12: =B12 -> 44144 | J12: ='Water-Meter'!G14 -> 38000 | K12: ='Water-Meter'!G14 -> 38000 | L12: =SUM(K12-J12) -> 0 | M12: =H12 -> 44144 | O12: ='Water-Meter'!J14 -> 8094 | P12: ='Water-Meter'!J14 -> 8094 | Q12: =N12-O11 -> -8092 | R12: =SUM(Q12/1615) -> -5.0105263 | S12: =Gen!U19 -> 2360 | T12: =M12 -> 44144 | V12: =W11 -> 7850.7 | W12: 7851.3 | X12: =(W12-V12)*200 -> 120 | Y12: =T12 -> 44144 | AB12: ='Water-Meter'!P14 -> 20479 | AC12: =AA12-AB11 -> -20471
A13: =Gen!C20 -> 0.039 | B13: =Gen!B20 -> 44145 | D13: =E12 -> 8916.8 | E13: 8918.4 | F13: =SUM(E13-D13)*120 -> 192 | H13: =B13 -> 44145 | J13: ='Water-Meter'!G15 -> 38000 | K13: ='Water-Meter'!G15 -> 38000 | L13: =SUM(K13-J13) -> 0 | M13: =H13 -> 44145 | O13: ='Water-Meter'!J15 -> 8095 | P13: ='Water-Meter'!J15 -> 8095 | Q13: =N13-O12 -> -8094 | R13: =SUM(Q13/1615) -> -5.0117647 | S13: =Gen!U20 -> 2323 | T13: =M13 -> 44145 | V13: =W12 -> 7851.3 | W13: 7851.8 | X13: =(W13-V13)*200 -> 100 | Y13: =T13 -> 44145 | AB13: ='Water-Meter'!P15 -> 20490 | AC13: =AA13-AB12 -> -20479
A14: =Gen!C21 -> 0.0649 | B14: =Gen!B21 -> 44146 | D14: =E13 -> 8918.4 | E14: 8920.1 | F14: =SUM(E14-D14)*120 -> 204 | H14: =B14 -> 44146 | J14: ='Water-Meter'!G16 -> 38000 | K14: ='Water-Meter'!G16 -> 38000 | L14: =SUM(K14-J14) -> 0 | M14: =H14 -> 44146 | O14: ='Water-Meter'!J16 -> 8096 | P14: ='Water-Meter'!J16 -> 8096 | Q14: 8095 | R14: =SUM(Q14/1615) -> 5.0123839 | S14: =Gen!U21 -> 2283 | T14: =M14 -> 44146 | V14: =W13 -> 7851.8 | W14: 7852.1 | X14: =(W14-V14)*200 -> 60 | Y14: =T14 -> 44146 | AB14: ='Water-Meter'!P16 -> 20495 | AC14: 20490
A15: =Gen!C22 -> 0.05 | B15: =Gen!B22 -> 44147 | D15: =E14 -> 8920.1 | E15: 8921.8 | F15: =SUM(E15-D15)*120 -> 204 | H15: =B15 -> 44147 | J15: ='Water-Meter'!G17 -> 38000 | K15: ='Water-Meter'!G17 -> 38000 | L15: =SUM(K15-J15) -> 0 | M15: =H15 -> 44147 | O15: ='Water-Meter'!J17 -> 8097 | P15: ='Water-Meter'!J17 -> 8097 | Q15: =N15-O14 -> -8096 | R15: =SUM(Q15/1615) -> -5.0130031 | S15: =Gen!U22 -> 2328 | T15: =M15 -> 44147 | V15: =W14 -> 7852.1 | W15: 7853.1 | X15: =(W15-V15)*200 -> 200 | Y15: =T15 -> 44147 | AB15: ='Water-Meter'!P17 -> 20498 | AC15: =AA15-AB14 -> -20495
A16: =Gen!C23 -> 0.0519 | B16: =Gen!B23 -> 44148 | D16: =E15 -> 8921.8 | E16: 8923.6 | F16: =SUM(E16-D16)*120 -> 216 | H16: =B16 -> 44148 | J16: ='Water-Meter'!G18 -> 38000 | K16: ='Water-Meter'!G18 -> 38000 | L16: =SUM(K16-J16) -> 0 | M16: =H16 -> 44148 | O16: ='Water-Meter'!J18 -> 8098 | P16: ='Water-Meter'!J18 -> 8098 | Q16: =N16-O15 -> -8097 | R16: =SUM(Q16/1615) -> -5.0136223 | S16: =Gen!U23 -> 2362 | T16: =M16 -> 44148 | V16: =W15 -> 7853.1 | W16: 7853.5 | X16: =(W16-V16)*200 -> 80 | Y16: =T16 -> 44148 | AB16: ='Water-Meter'!P18 -> 20502 | AC16: =AA16-AB15 -> -20498
A17: =Gen!C24 -> 0.1818 | B17: =Gen!B24 -> 44149 | D17: =E16 -> 8923.6 | E17: 8925.4 | F17: =SUM(E17-D17)*120 -> 216 | H17: =B17 -> 44149 | J17: ='Water-Meter'!G19 -> 38000 | K17: ='Water-Meter'!G19 -> 38000 | L17: =SUM(K17-J17) -> 0 | M17: =H17 -> 44149 | O17: ='Water-Meter'!J19 -> 8099 | P17: ='Water-Meter'!J19 -> 8099 | Q17: =N17-O16 -> -8098 | R17: =SUM(Q17/1615) -> -5.0142415 | S17: =Gen!U24 -> 2380 | T17: =M17 -> 44149 | V17: =W16 -> 7853.5 | W17: 7854.2 | X17: =(W17-V17)*200 -> 140 | Y17: =T17 -> 44149 | AB17: ='Water-Meter'!P19 -> 20507 | AC17: =AA17-AB16 -> -20502
A18: =Gen!C25 -> 0.1429 | B18: =Gen!B25 -> 44150 | D18: =E17 -> 8925.4 | E18: 8927.3 | F18: =SUM(E18-D18)*120 -> 228 | H18: =B18 -> 44150 | J18: ='Water-Meter'!G20 -> 38000 | K18: ='Water-Meter'!G20 -> 38000 | L18: =SUM(K18-J18) -> 0 | M18: =H18 -> 44150 | O18: ='Water-Meter'!J20 -> 8100 | P18: ='Water-Meter'!J20 -> 8100 | Q18: =N18-O17 -> -8099 | R18: =SUM(Q18/1615) -> -5.0148607 | S18: =Gen!U25 -> 2337 | T18: =M18 -> 44150 | V18: =W17 -> 7854.2 | W18: 7854.7 | X18: =(W18-V18)*200 -> 100 | Y18: =T18 -> 44150 | AB18: ='Water-Meter'!P20 -> 20511 | AC18: =AA18-AB17 -> -20507
A19: =Gen!C26 -> 0.1299 | B19: =Gen!B26 -> 44151 | D19: =E18 -> 8927.3 | E19: 8929.5 | F19: =SUM(E19-D19)*120 -> 264 | H19: =B19 -> 44151 | J19: ='Water-Meter'!G21 -> 38000 | K19: ='Water-Meter'!G21 -> 38000 | L19: =SUM(K19-J19) -> 0 | M19: =H19 -> 44151 | O19: ='Water-Meter'!J21 -> 8101 | P19: ='Water-Meter'!J21 -> 8101 | Q19: =N19-O18 -> -8100 | R19: =SUM(Q19/1615) -> -5.0154799 | S19: =Gen!U26 -> 2468 | T19: =M19 -> 44151 | V19: =W18 -> 7854.7 | W19: 7855.6 | X19: =(W19-V19)*200 -> 180 | Y19: =T19 -> 44151 | AB19: ='Water-Meter'!P21 -> 20512 | AC19: =AA19-AB18 -> -20511
A20: =Gen!C27 -> 0.03 | B20: =Gen!B27 -> 44152 | D20: =E19 -> 8929.5 | E20: 8931.5 | F20: =SUM(E20-D20)*120 -> 240 | H20: =B20 -> 44152 | J20: ='Water-Meter'!G22 -> 38000 | K20: ='Water-Meter'!G22 -> 38000 | L20: =SUM(K20-J20) -> 0 | M20: =H20 -> 44152 | O20: ='Water-Meter'!J22 -> 8102 | P20: ='Water-Meter'!J22 -> 8102 | Q20: =N20-O19 -> -8101 | R20: =SUM(Q20/1615) -> -5.0160991 | S20: =Gen!U27 -> 2266 | T20: =M20 -> 44152 | V20: =W19 -> 7855.6 | W20: 7856 | X20: =(W20-V20)*200 -> 80 | Y20: =T20 -> 44152 | AB20: ='Water-Meter'!P22 -> 20514 | AC20: =AA20-AB19 -> -20512
A21: =Gen!C28 -> 0.104 | B21: =Gen!B28 -> 44153 | D21: =E20 -> 8931.5 | E21: 8933.5 | F21: =SUM(E21-D21)*120 -> 240 | H21: =B21 -> 44153 | J21: ='Water-Meter'!G23 -> 38000 | K21: ='Water-Meter'!G23 -> 38000 | L21: =SUM(K21-J21) -> 0 | M21: =H21 -> 44153 | O21: ='Water-Meter'!J23 -> 8103 | P21: ='Water-Meter'!J23 -> 8103 | Q21: =N21-O20 -> -8102 | R21: =SUM(Q21/1615) -> -5.0167183 | S21: =Gen!U28 -> 2398 | T21: =M21 -> 44153 | V21: =W20 -> 7856 | W21: 7857.1 | X21: =(W21-V21)*200 -> 220 | Y21: =T21 -> 44153 | AB21: ='Water-Meter'!P23 -> 20517 | AC21: =AA21-AB20 -> -20514
A22: =Gen!C29 -> 0.052 | B22: =Gen!B29 -> 44154 | D22: =E21 -> 8933.5 | E22: 8935.6 | F22: =SUM(E22-D22)*120 -> 252 | H22: =B22 -> 44154 | J22: ='Water-Meter'!G24 -> 38000 | K22: ='Water-Meter'!G24 -> 38000 | L22: =SUM(K22-J22) -> 0 | M22: =H22 -> 44154 | O22: ='Water-Meter'!J24 -> 8105 | P22: ='Water-Meter'!J24 -> 8105 | Q22: =N22-O21 -> -8103 | R22: =SUM(Q22/1615) -> -5.0173375 | S22: =Gen!U29 -> 2587 | T22: =M22 -> 44154 | V22: =W21 -> 7857.1 | W22: 7857.7 | X22: =(W22-V22)*200 -> 120 | Y22: =T22 -> 44154 | AB22: ='Water-Meter'!P24 -> 20522 | AC22: =AA22-AB21 -> -20517
A23: =Gen!C30 -> 0.052 | B23: =Gen!B30 -> 44155 | D23: =E22 -> 8935.6 | E23: 8937.6 | F23: =SUM(E23-D23)*120 -> 240 | H23: =B23 -> 44155 | J23: ='Water-Meter'!G25 -> 38000 | K23: ='Water-Meter'!G26 -> 38000 | L23: =SUM(K23-J23) -> 0 | M23: =H23 -> 44155 | O23: ='Water-Meter'!J25 -> 8106 | P23: ='Water-Meter'!J25 -> 8106 | Q23: =N23-O22 -> -8105 | R23: =SUM(Q23/1615) -> -5.0185759 | S23: =Gen!U30 -> 2592 | T23: =M23 -> 44155 | V23: =W22 -> 7857.7 | W23: 7858.1 | X23: =(W23-V23)*200 -> 80 | Y23: =T23 -> 44155 | AB23: ='Water-Meter'!P25 -> 20523 | AC23: =AA23-AB22 -> -20522
A24: =Gen!C31 -> 0.065 | B24: =Gen!B31 -> 44156 | D24: =SUM(E23) -> 8937.6 | E24: 8939.7 | F24: =SUM(E24-D24)*120 -> 252 | H24: =B24 -> 44156 | J24: ='Water-Meter'!G26 -> 38000 | K24: ='Water-Meter'!G27 -> 38000 | L24: =SUM(K24-J24) -> 0 | M24: =H24 -> 44156 | O24: ='Water-Meter'!J26 -> 8107 | P24: ='Water-Meter'!J26 -> 8107 | Q24: =N24-O23 -> -8106 | R24: =SUM(Q24/1615) -> -5.019195 | S24: =Gen!U31 -> 2673 | T24: 5835.7 | V24: =W23 -> 7858.1 | W24: 7859.1 | X24: =(W24-V24)*200 -> 200 | Y24: =T24 -> 5835.7 | AB24: ='Water-Meter'!P26 -> 20527 | AC24: =AA24-AB23 -> -20523
A25: =Gen!C32 -> 0.1 | B25: =Gen!B32 -> 44157 | D25: =SUM(E24) -> 8939.7 | E25: 8941.7 | F25: =SUM(E25-D25)*120 -> 240 | H25: =B25 -> 44157 | J25: ='Water-Meter'!G27 -> 38000 | K25: ='Water-Meter'!G28 -> 38000 | L25: =SUM(K25-J25) -> 0 | M25: =H25 -> 44157 | O25: ='Water-Meter'!J27 -> 8108 | P25: ='Water-Meter'!J27 -> 8108 | Q25: =N25-O24 -> -8107 | R25: =SUM(Q25/1615) -> -5.0198142 | S25: =Gen!U32 -> 2585 | T25: =M25 -> 44157 | V25: =W24 -> 7859.1 | W25: 7860.1 | X25: =(W25-V25)*200 -> 200 | Y25: =T25 -> 44157 | AB25: ='Water-Meter'!P27 -> 20533 | AC25: =AA25-AB24 -> -20527
A26: =Gen!C33 -> 0.065 | B26: =Gen!B33 -> 44158 | D26: =SUM(E25) -> 8941.7 | E26: 8943.6 | F26: =SUM(E26-D26)*120 -> 228 | H26: =B26 -> 44158 | J26: ='Water-Meter'!G28 -> 38000 | K26: ='Water-Meter'!G29 -> 38000 | L26: =SUM(K26-J26) -> 0 | M26: =H26 -> 44158 | O26: ='Water-Meter'!J28 -> 8109 | P26: ='Water-Meter'!J28 -> 8109 | Q26: =N26-O25 -> -8108 | R26: =SUM(Q26/1615) -> -5.0204334 | S26: =Gen!U33 -> 2587 | T26: =M26 -> 44158 | V26: =W25 -> 7860.1 | W26: 7861.1 | X26: =(W26-V26)*200 -> 200 | Y26: =T26 -> 44158 | AB26: ='Water-Meter'!P28 -> 20537 | AC26: =AA26-AB25 -> -20533
A27: =Gen!C34 -> 0.065 | B27: =Gen!B34 -> 44159 | D27: =SUM(E26) -> 8943.6 | E27: 8945.6 | F27: =SUM(E27-D27)*120 -> 240 | H27: =B27 -> 44159 | J27: ='Water-Meter'!G29 -> 38000 | K27: ='Water-Meter'!G30 -> 38000 | L27: =SUM(K27-J27) -> 0 | M27: =H27 -> 44159 | O27: ='Water-Meter'!J29 -> 8110 | P27: ='Water-Meter'!J29 -> 8110 | Q27: =N27-O26 -> -8109 | R27: =SUM(Q27/1615) -> -5.0210526 | S27: =Gen!U34 -> 2376 | T27: =M27 -> 44159 | V27: =W26 -> 7861.1 | W27: 7861.5 | X27: =(W27-V27)*200 -> 80 | Y27: =T27 -> 44159 | AB27: ='Water-Meter'!P29 -> 20541 | AC27: =AA27-AB26 -> -20537
A28: =Gen!C35 -> 0.039 | B28: =Gen!B35 -> 44160 | D28: =SUM(E27) -> 8945.6 | E28: 8947.6 | F28: =SUM(E28-D28)*120 -> 240 | H28: =B28 -> 44160 | J28: ='Water-Meter'!G30 -> 38000 | K28: ='Water-Meter'!G31 -> 38000 | L28: =SUM(K28-J28) -> 0 | M28: =H28 -> 44160 | O28: ='Water-Meter'!J30 -> 8111 | P28: ='Water-Meter'!J30 -> 8111 | Q28: =N28-O27 -> -8110 | R28: =SUM(Q28/1615) -> -5.0216718 | S28: =Gen!U35 -> 2258 | T28: =M28 -> 44160 | V28: =W27 -> 7861.5 | W28: 7861.7 | X28: =(W28-V28)*200 -> 40 | Y28: =T28 -> 44160 | AB28: ='Water-Meter'!P30 -> 20544 | AC28: =AA28-AB27 -> -20541
A29: =Gen!C36 -> 0.013 | B29: =Gen!B36 -> 44161 | D29: =SUM(E28) -> 8947.6 | E29: 8949.3 | F29: =SUM(E29-D29)*120 -> 204 | H29: =B29 -> 44161 | J29: ='Water-Meter'!G31 -> 38000 | K29: ='Water-Meter'!G32 -> 38000 | L29: =SUM(K29-J29) -> 0 | M29: =H29 -> 44161 | O29: ='Water-Meter'!J31 -> 8112 | P29: ='Water-Meter'!J31 -> 8112 | Q29: =N29-O28 -> -8111 | R29: =SUM(Q29/1615) -> -5.022291 | S29: =Gen!U36 -> 2255 | T29: =M29 -> 44161 | V29: =W28 -> 7861.7 | W29: 7862.5 | X29: =(W29-V29)*200 -> 160 | Y29: =T29 -> 44161 | AB29: ='Water-Meter'!P31 -> 20546 | AC29: =AA29-AB28 -> -20544
A30: =Gen!C37 -> 0.01 | B30: =Gen!B37 -> 44162 | D30: =SUM(E29) -> 8949.3 | E30: 8951.1 | F30: =SUM(E30-D30)*120 -> 216 | H30: =B30 -> 44162 | J30: ='Water-Meter'!G32 -> 38000 | K30: ='Water-Meter'!G33 -> 38000 | L30: =SUM(K30-J30) -> 0 | M30: =H30 -> 44162 | O30: ='Water-Meter'!J32 -> 8113 | P30: ='Water-Meter'!J32 -> 8113 | Q30: =N30-O29 -> -8112 | R30: =SUM(Q30/1615) -> -5.0229102 | S30: =Gen!U37 -> 2395 | T30: =M30 -> 44162 | V30: =W29 -> 7862.5 | W30: 7863.1 | X30: =(W30-V30)*200 -> 120 | Y30: =T30 -> 44162 | AB30: ='Water-Meter'!P32 -> 20549 | AC30: =AA30-AB29 -> -20546
A31: =Gen!C38 -> 0.026 | B31: =Gen!B38 -> 44163 | D31: =SUM(E30) -> 8951.1 | E31: 8952.4 | F31: =SUM(E31-D31)*120 -> 156 | H31: =B31 -> 44163 | J31: ='Water-Meter'!G33 -> 38000 | K31: ='Water-Meter'!G34 -> 38000 | L31: =SUM(K31-J31) -> 0 | M31: =H31 -> 44163 | O31: ='Water-Meter'!J33 -> 8114 | P31: ='Water-Meter'!J33 -> 8114 | Q31: =N31-O30 -> -8113 | R31: =SUM(Q31/1615) -> -5.0235294 | S31: =Gen!U38 -> 0 | T31: =M31 -> 44163 | V31: =W30 -> 7863.1 | W31: 7863.8 | X31: =(W31-V31)*200 -> 140 | Y31: =T31 -> 44163 | AB31: ='Water-Meter'!P33 -> 20552 | AC31: =AA31-AB30 -> -20549
A32: =Gen!C39 -> 0.026 | B32: =Gen!B39 -> 44164 | D32: =SUM(E31) -> 8952.4 | E32: 8954.1 | F32: =SUM(E32-D32)*120 -> 204 | H32: =B32 -> 44164 | J32: ='Water-Meter'!G34 -> 38000 | K32: ='Water-Meter'!G34 -> 38000 | L32: =SUM(K32-J32) -> 0 | M32: =H32 -> 44164 | O32: ='Water-Meter'!J34 -> 8115 | P32: ='Water-Meter'!J34 -> 8115 | Q32: =N32-O31 -> -8114 | R32: =SUM(Q32/1615) -> -5.0241486 | S32: =Gen!U39 -> 2264 | T32: =M32 -> 44164 | V32: =W31 -> 7863.8 | W32: 7864.6 | X32: =(W32-V32)*200 -> 160 | Y32: =T32 -> 44164 | AB32: ='Water-Meter'!P34 -> 20556 | AC32: =AA32-AB31 -> -20552
A33: =Gen!C40 -> 0.039 | B33: =Gen!B40 -> 44165 | D33: =SUM(E32) -> 8954.1 | E33: 8955.5 | F33: =SUM(E33-D33)*120 -> 168 | H33: =B33 -> 44165 | J33: ='Water-Meter'!G35 -> 38000 | K33: ='Water-Meter'!G35 -> 38000 | L33: =SUM(K33-J33) -> 0 | M33: =H33 -> 44165 | O33: ='Water-Meter'!J35 -> 8116 | P33: ='Water-Meter'!J35 -> 8116 | Q33: =N33-O32 -> -8115 | R33: =SUM(Q33/1615) -> -5.0247678 | S33: =Gen!U40 -> 0 | T33: =M33 -> 44165 | V33: =W32 -> 7864.6 | W33: 7865.3 | X33: =(W33-V33)*200 -> 140 | Y33: =T33 -> 44165 | AB33: ='Water-Meter'!P35 -> 20558 | AC33: =AA33-AB32 -> -20556
A34: =Gen!C41 -> 0 | B34: =Gen!B41 -> 44166 | D34: =SUM(E33) -> 8955.5 | F34: =SUM(E34-D34)*120 -> -1074660 | H34: =B34 -> 44166 | J34: ='Water-Meter'!G36 -> 0 | K34: ='Water-Meter'!G36 -> 0 | L34: =SUM(K34-J34) -> 0 | M34: =H34 -> 44166 | O34: ='Water-Meter'!J36 -> 0 | P34: ='Water-Meter'!J36 -> 0 | Q34: =N34-O33 -> -8116 | R34: =SUM(Q34/1615) -> -5.025387 | S34: =Gen!U41 -> 0 | T34: =M34 -> 44166 | V34: =SUM(W33) -> 7865.3 | X34: =(W34-V34)*200 -> -1573060 | Y34: =T34 -> 44166 | AB34: ='Water-Meter'!P36 -> 0 | AC34: =AA34-AB33 -> -20558
A35: =[1]Gen!B42 -> #REF! | B35: =[1]Gen!A42 -> #REF! | D35: =SUM(E34) -> 0 | F35: =SUM(F4:F6) -> 636 | H35: =B35 -> #REF! | J35: =SUM(K34) -> 0 | K35: ='Water-Meter'!G37 -> 0 | L35: =SUM(L5:L34) -> 0 | M35: =H35 -> #REF! | P35: ='Water-Meter'!J37 -> 0 | Q35: =N35-O34 -> 0 | R35: =SUM(Q35/1615) -> 0 | S35: =Gen!U42 -> 0 | T35: =M35 -> #REF! | V35: =SUM(W34) -> 0 | X35: =(W35-V35)*200 -> 0 | Y35: =T35 -> #REF! | AB35: ='Water-Meter'!P37 -> 0 | AC35: =AA35-AB34 -> 0
X36: =SUM(X4:X6) -> 460

Sheet Summery Report
A2: Generator and Diseal Summry Report October 2020
A4: Date | B4: Gen Set Hours Working | C4: Occ% | D4: Total OCC Room | E4: Guest Room Occ | F4: Total Kwh Generated | G4: Diesel consumed by Gen (Ltrs) | H4: Diesel consumed by Vehicle (Ltrs) | I4: Total diesel consumed (Ltrs) | J4: Balance stock of Diesel (Ltrs) | K4: Water consumed | L4: Gas consumed (KG)
A5: =Gen!B11 -> 44136 | B5: ='Daily report Gen'!Z6 -> 26 | C5: =Gen!C11 -> 0.026 | D5: =E5 -> 3 | E5: 3 | F5: =Gen!V11 -> 0.39587992 | G5: =Gen!U9 -> 0 | H5: =Gen!AL11 -> 0 | I5: =SUM(G5:H5) -> 0 | J5: =Gen!D11 -> 32519.1 | K5: ='Water-Meter'!E6 -> 54 | L5: ='Lpg (2)'!G10 -> 0 | M5: =SUM(#REF!-#REF!) -> #REF!
A6: =Gen!B12 -> 44137 | B6: ='Daily report Gen'!Z7 -> 23 | C6: =Gen!C12 -> 0.0519 | D6: =E6 -> 5 | E6: 5 | F6: =Gen!V12 -> 0.42335499 | G6: =Gen!U10 -> 0 | H6: =Gen!AL12 -> 0 | I6: =SUM(G6:H6) -> 0 | J6: =Gen!D12 -> 31563.05 | K6: ='Water-Meter'!E7 -> 48 | L6: ='Lpg (2)'!G11 -> 57.42 | M6: =SUM(#REF!-#REF!) -> #REF!
A7: =Gen!B13 -> 44138 | B7: ='Daily report Gen'!Z8 -> 24 | C7: =Gen!C13 -> 0.0779 | D7: =E7 -> 7 | E7: 7 | F7: =Gen!V13 -> 0.44945602 | G7: =Gen!U11 -> 2415 | H7: =Gen!AL13 -> 0 | I7: =SUM(G7:H7) -> 2415 | J7: =Gen!D13 -> 30433.51 | K7: ='Water-Meter'!E8 -> 81 | L7: ='Lpg (2)'!G12 -> 50.16 | M7: =SUM(#REF!-#REF!) -> #REF!
A8: =Gen!B14 -> 44139 | B8: ='Daily report Gen'!Z9 -> 24 | C8: =Gen!C14 -> 0.0649 | D8: =E8 -> 6 | E8: 6 | F8: =Gen!V14 -> 0.39410546 | G8: =Gen!U12 -> 2617 | H8: =Gen!AL14 -> 0 | I8: =SUM(G8:H8) -> 2617 | J8: =Gen!D14 -> 47230.25 | K8: ='Water-Meter'!E9 -> 50 | L8: ='Lpg (2)'!G13 -> 57.816 | M8: =SUM(#REF!-#REF!) -> #REF!
A9: =Gen!B15 -> 44140 | B9: ='Daily report Gen'!Z10 -> 26 | C9: =Gen!C15 -> 0.026 | D9: =E9 -> 3 | E9: 3 | F9: =Gen!V15 -> 0.4077842 | G9: =Gen!U13 -> 2592 | H9: =Gen!AL15 -> 0 | I9: =SUM(G9:H9) -> 2592 | J9: =Gen!D15 -> 46132.8 | K9: ='Water-Meter'!E10 -> 58 | L9: ='Lpg (2)'!G14 -> 59.972 | M9: =SUM(#REF!-#REF!) -> #REF!
A10: =Gen!B16 -> 44141 | B10: ='Daily report Gen'!Z11 -> 25 | C10: =Gen!C16 -> 0.0649 | D10: =E10 -> 6 | E10: 6 | F10: =Gen!V16 -> 0.4464682 | G10: =Gen!U14 -> 2655 | H10: =Gen!AL16 -> 0 | I10: =SUM(G10:H10) -> 2655 | J10: =Gen!D16 -> 45014.45 | K10: ='Water-Meter'!E11 -> 62 | L10: ='Lpg (2)'!G15 -> 52.976 | M10: =SUM(#REF!-#REF!) -> #REF!
A11: =Gen!B17 -> 44142 | B11: ='Daily report Gen'!Z12 -> 25 | C11: =Gen!C17 -> 0.0519 | D11: =E11 -> 5 | E11: 5 | F11: =Gen!V17 -> 0.38424768 | G11: =Gen!U15 -> 2595 | H11: =Gen!AL17 -> 0 | I11: =SUM(G11:H11) -> 2595 | J11: =Gen!D17 -> 43932.63 | K11: ='Water-Meter'!E12 -> 83 | L11: ='Lpg (2)'!G16 -> 75.68 | M11: =SUM(#REF!-#REF!) -> #REF!
A12: =Gen!B18 -> 44143 | B12: ='Daily report Gen'!Z13 -> 25 | C12: =Gen!C18 -> 0 | D12: =E12 -> 1 | E12: 1 | F12: =Gen!V18 -> 0.43765912 | G12: =Gen!U16 -> 2217 | H12: =Gen!AL18 -> 0 | I12: =SUM(G12:H12) -> 2217 | J12: =Gen!D18 -> 42971.68 | K12: ='Water-Meter'!E13 -> 63 | L12: ='Lpg (2)'!G17 -> 51.7 | M12: =SUM(#REF!-#REF!) -> #REF!
A13: =Gen!B19 -> 44144 | B13: ='Daily report Gen'!Z14 -> 25 | C13: =Gen!C19 -> 0.013 | D13: =E13 -> 2 | E13: 2 | F13: =Gen!V19 -> 0.44400424 | G13: =Gen!U17 -> 2479 | H13: =Gen!AL19 -> 0 | I13: =SUM(G13:H13) -> 2479 | J13: =Gen!D19 -> 41947.12 | K13: ='Water-Meter'!E14 -> 46 | L13: ='Lpg (2)'!G18 -> 53.592 | M13: =SUM(#REF!-#REF!) -> #REF!
A14: =Gen!B20 -> 44145 | B14: ='Daily report Gen'!Z15 -> 12 | C14: =Gen!C20 -> 0.039 | D14: =E14 -> 4 | E14: 4 | F14: =Gen!V20 -> 0.40174344 | G14: =Gen!U18 -> 2341 | H14: =Gen!AL20 -> 0 | I14: =SUM(G14:H14) -> 2341 | J14: =Gen!D20 -> 40854.97 | K14: ='Water-Meter'!E15 -> 53 | L14: ='Lpg (2)'!G19 -> 23.54 | M14: =SUM(#REF!-#REF!) -> #REF!
A15: =Gen!B21 -> 44146 | B15: ='Daily report Gen'!Z16 -> 35 | C15: =Gen!C21 -> 0.0649 | D15: =E15 -> 6 | E15: 6 | F15: =Gen!V21 -> 0.41271572 | G15: =Gen!U19 -> 2360 | H15: =Gen!AL21 -> 0 | I15: =SUM(G15:H15) -> 2360 | J15: =Gen!D21 -> 39872.98 | K15: ='Water-Meter'!E16 -> 63 | L15: ='Lpg (2)'!G20 -> 75.328 | M15: =SUM(#REF!-#REF!) -> #REF!
A16: =Gen!B22 -> 44147 | B16: ='Daily report Gen'!Z17 -> 25 | C16: =Gen!C22 -> 0.05 | D16: =E16 -> 5 | E16: 5 | F16: =Gen!V22 -> 0.465189 | G16: =Gen!U20 -> 2323 | H16: =Gen!AL22 -> 0 | I16: =SUM(G16:H16) -> 2323 | J16: =Gen!D22 -> 38906.7 | K16: ='Water-Meter'!E17 -> 48 | L16: ='Lpg (2)'!G21 -> 54.164 | M16: =SUM(#REF!-#REF!) -> #REF!
... A20: =Gen!B26 -> 44151 | B20: ='Daily report Gen'!Z21 -> 25 | C20: =Gen!C26 -> 0.1299 | D20: =E20 -> 12 | E20: 12 | F20: =Gen!V26 -> 0.4577188 | G20: =Gen!U24 -> 2380 | H20: =Gen!AL26 -> 0 | I20: =SUM(G20:H20) -> 2380 | J20: =Gen!D26 -> 34509.83 | K20: ='Water-Meter'!E21 -> 52 | L20: ='Lpg (2)'!G25 -> 82.764 | M20: =SUM(#REF!-#REF!) -> #REF!
A21: =Gen!B27 -> 44152 | B21: ='Daily report Gen'!Z22 -> 24 | C21: =Gen!C27 -> 0.03 | D21: =E21 -> 0 | F21: =Gen!V27 -> 0.4099647 | G21: =Gen!U25 -> 2337 | H21: =Gen!AL27 -> 0 | I21: =SUM(G21:H21) -> 2337 | J21: =Gen!D27 -> 33312.67 | K21: ='Water-Meter'!E22 -> 53 | L21: ='Lpg (2)'!G26 -> 77.572 | M21: =SUM(#REF!-#REF!) -> #REF!
A22: =Gen!B28 -> 44153 | B22: ='Daily report Gen'!Z23 -> 24 | C22: =Gen!C28 -> 0.104 | D22: =E22 -> 0 | F22: =Gen!V28 -> 0.41586322 | G22: =Gen!U26 -> 2468 | H22: =Gen!AL28 -> 0 | I22: =SUM(G22:H22) -> 2468 | J22: =Gen!D28 -> 47383.69 | K22: ='Water-Meter'!E23 -> 51 | L22: ='Lpg (2)'!G27 -> 75.284 | M22: =SUM(#REF!-#REF!) -> #REF!
A23: =Gen!B29 -> 44154 | B23: ='Daily report Gen'!Z24 -> 24 | C23: =Gen!C29 -> 0.052 | D23: =E23 -> 0 | F23: =Gen!V29 -> 0.40265559 | G23: =Gen!U27 -> 2266 | H23: =Gen!AL29 -> 0 | I23: =SUM(G23:H23) -> 2266 | J23: =Gen!D29 -> 46363.86 | K23: ='Water-Meter'!E24 -> 127 | L23: ='Lpg (2)'!G28 -> 73.524 | M23: =SUM(#REF!-#REF!) -> #REF!
A24: =Gen!B30 -> 44155 | B24: ='Daily report Gen'!Z25 -> 25 | C24: =Gen!C30 -> 0.052 | D24: =E24 -> 0 | F24: =Gen!V30 -> 0.38775463 | G24: =Gen!U28 -> 2398 | H24: =Gen!AL30 -> 0 | I24: =SUM(G24:H24) -> 2398 | J24: =Gen!D30 -> 45244.14 | K24: ='Water-Meter'!E25 -> 46 | L24: ='Lpg (2)'!G29 -> 99.176 | M24: =SUM(#REF!-#REF!) -> #REF!
A25: =Gen!B31 -> 44156 | B25: ='Daily report Gen'!Z26 -> 26 | C25: =Gen!C31 -> 0.065 | D25: =E25 -> 0 | F25: =Gen!V31 -> 0.4135578 | G25: =Gen!U29 -> 2587 | H25: =Gen!AL31 -> 0 | I25: =SUM(G25:H25) -> 2587 | J25: =Gen!D31 -> 44239.08 | K25: ='Water-Meter'!E26 -> 47 | L25: ='Lpg (2)'!G30 -> 85.36 | M25: =SUM(#REF!-#REF!) -> #REF!
A26: =Gen!B32 -> 44157 | B26: ='Daily report Gen'!Z27 -> 24 | C26: =Gen!C32 -> 0.1 | D26: =E26 -> 0 | F26: =Gen!V32 -> 0.40388395 | G26: =Gen!U30 -> 2592 | H26: =Gen!AL32 -> 0 | I26: =SUM(G26:H26) -> 2592 | J26: =Gen!D32 -> 42936.25 | K26: ='Water-Meter'!E27 -> 51 | L26: ='Lpg (2)'!G31 -> 86.548 | M26: =SUM(#REF!-#REF!) -> #REF!
A27: =Gen!B33 -> 44158 | B27: ='Daily report Gen'!Z28 -> 24 | C27: =Gen!C33 -> 0.065 | D27: =E27 -> 0 | F27: =Gen!V33 -> 0.41547739 | G27: =Gen!U31 -> 2673 | H27: =Gen!AL33 -> 0 | I27: =SUM(G27:H27) -> 2673 | J27: =Gen!D33 -> 41883.06 | K27: ='Water-Meter'!E28 -> 61 | L27: ='Lpg (2)'!G32 -> 65.736 | M27: =SUM(#REF!-#REF!) -> #REF!
A28: =Gen!B34 -> 44159 | B28: ='Daily report Gen'!Z29 -> 24 | C28: =Gen!C34 -> 0.065 | D28: =E28 -> 0 | F28: =Gen!V34 -> 0.42898569 | G28: =Gen!U32 -> 2585 | H28: =Gen!AL34 -> 0 | I28: =SUM(G28:H28) -> 2585 | J28: =Gen!D34 -> 40808.22 | K28: ='Water-Meter'!E29 -> 49 | L28: ='Lpg (2)'!G33 -> 64.108 | M28: =SUM(#REF!-#REF!) -> #REF!
A29: =Gen!B35 -> 44160 | B29: ='Daily report Gen'!Z30 -> 24 | C29: =Gen!C35 -> 0.039 | D29: =E29 -> 0 | F29: =Gen!V35 -> 0.43357839 | G29: =Gen!U33 -> 2587 | H29: =Gen!AL35 -> 0 | I29: =SUM(G29:H29) -> 2587 | J29: =Gen!D35 -> 39721.95 | K29: ='Water-Meter'!E30 -> 50 | L29: ='Lpg (2)'!G34 -> 80.344 | M29: =SUM(#REF!-#REF!) -> #REF!
A30: =Gen!B36 -> 44161 | B30: ='Daily report Gen'!Z31 -> 24 | C30: =Gen!C36 -> 0.013 | D30: =E30 -> 0 | F30: =Gen!V36 -> 0.41160089 | G30: =Gen!U34 -> 2376 | H30: =Gen!AL36 -> 0 | I30: =SUM(G30:H30) -> 2376 | J30: =Gen!D36 -> 38722.61 | K30: ='Water-Meter'!E31 -> 56 | L30: ='Lpg (2)'!G35 -> 78.716 | M30: =SUM(#REF!-#REF!) -> #REF!
A31: =Gen!B37 -> 44162 | B31: ='Daily report Gen'!Z32 -> 25 | C31: =Gen!C37 -> 0.01 | D31: =E31 -> 0 | F31: =Gen!V37 -> 0.42654697 | G31: =Gen!U35 -> 2258 | H31: =Gen!AL37 -> 0 | I31: =SUM(G31:H31) -> 2258 | J31: =Gen!D37 -> 37794.45 | K31: ='Water-Meter'!E32 -> 47 | L31: ='Lpg (2)'!G36 -> 42.372 | M31: =SUM(#REF!-#REF!) -> #REF!
A32: =Gen!B38 -> 44163 | B32: ='Daily report Gen'!Z33 -> 25 | C32: =Gen!C38 -> 0.026 | D32: =E32 -> 0 | F32: =Gen!V38 -> #DIV/0! | G32: =Gen!U36 -> 2255 | H32: =Gen!AL38 -> 0 | I32: =SUM(G32:H32) -> 2255 | J32: =Gen!D38 -> 36735.49 | K32: ='Water-Meter'!E33 -> 45 | L32: ='Lpg (2)'!G37 -> 67.716 | M32: =SUM(#REF!-#REF!) -> #REF!
... A34: =Gen!B40 -> 44165 | B34: ='Daily report Gen'!Z35 -> 24 | C34: =Gen!C40 -> 0.039 | D34: =E34 -> 0 | F34: =Gen!V40 -> #DIV/0! | G34: =Gen!U38 -> 0 | H34: =Gen!AL40 -> 0 | I34: =SUM(G34:H34) -> 0 | J34: =Gen!D40 -> 34767.9 | K34: ='Water-Meter'!E35 -> 46 | L34: ='Lpg (2)'!G39 -> 67.848 | M34: =SUM(#REF!-#REF!) -> #REF!
A35: =Gen!B41 -> 44166 | B35: ='Daily report Gen'!Z36 -> -155892 | C35: =Gen!C41 -> 0 | D35: =E35 -> 0 | F35: =Gen!V39 -> 0.42375 | G35: =Gen!U39 -> 2264 | H35: =Gen!AL41 -> 0 | I35: =SUM(G35:H35) -> 2264 | J35: =Gen!D41 -> 33526.22 | K35: ='Water-Meter'!E36 -> 0 | L35: ='Lpg (2)'!G40 -> -323055.44 | M35: =SUM(#REF!-#REF!) -> #REF!
A36: =Gen!B42 -> 0 | B36: ='Daily report Gen'!Z37 -> 0 | C36: =Gen!C42 -> 0 | D36: =E36 -> 0 | F36: =Gen!V40 -> #DIV/0! | G36: =Gen!U40 -> 0 | H36: =Gen!AL42 -> 0 | I36: =SUM(G36:H36) -> 0 | J36: =Gen!D42 -> 33526.22 | K36: ='Water-Meter'!E37 -> 0 | L36: ='Lpg (2)'!G41 -> 0

Sheet Daily report Gen
A1: =A6 -> 44136
K3: GENERATOR NO.1 | N3: GENERATOR NO.2 | Q3: GENERATOR NO.4 | T3: GENERATOR NO.5 | W3: GENERATOR NO.6
A4: DATE | B4: OCC% | C4: D-TANK A | D4: D-TANK B | E4: DELIVERY DATE | F4: DELIVERY | G4: ISSUED-VEHICLE | H4: OTHERS | I4: M-R LV PANEL 1. KW-HR | J4: M-R LV PANEL 2. KW-HR | K4: OPEN HRS READING | L4: CLOSE HRS READING | M4: RUNNING HRS | N4: OPEN HRS READING | O4: CLOSE HRS READING | P4: RUNNING HRS | Q4: OPEN HRS READING | R4: CLOSE HRS READING | S4: RUNNING HRS | T4: OPEN HRS READING | U4: CLOSE HRS READING | V4: RUNNING HRS | W4: OPEN HRS READING | X4: CLOSE HRS READING | Y4: RUNNING HRS | Z4: TOTAL RUNNING HRS | AA4: MAX KW | AB4: MIN-KW | AC4: TOTAL DIESEL CONS.
I5: 311462 | J5: 20697.5 | L5: 35368 | O5: 30278 | R5: 35756 | U5: 32563 | X5: 21192
A6: =Gen!B11 -> 44136 | B6: =Gen!C11 -> 0.026 | C6: 11879.5 | D6: 21840.2 | G6: 58.61 | I6: 31150.9 | J6: 20700.5 | K6: =L5 -> 35368 | L6: 35381 | M6: =L6-K6 -> 13 | N6: =O5 -> 30278 | O6: 30278 | P6: =O6-N6 -> 0 | Q6: =R5 -> 35756 | R6: 35756 | S6: =R6-Q6 -> 0 | T6: =U5 -> 32563 | U6: 32563 | V6: =U6-T6 -> 0 | W6: =X5 -> 21192 | X6: 21205 | Y6: =X6-W6 -> 13 | Z6: =Y6+V6+S6+P6+M6 -> 26 | AA6: 230 | AB6: 125 | AC6: =Gen!AS11 -> 956.05
A7: =Gen!B12 -> 44137 | B7: =Gen!C12 -> 0.0519 | C7: 9664.24 | D7: 21840.2 | G7: 21.62 | I7: 31153.9 | J7: 20703.7 | K7: =L6 -> 35381 | L7: 35391 | M7: =L7-K7 -> 10 | N7: =O6 -> 30278 | O7: 30278 | P7: =O7-N7 -> 0 | Q7: =R6 -> 35756 | R7: 35756 | S7: =R7-Q7 -> 0 | T7: =U6 -> 32563 | U7: 32576 | V7: =U7-T7 -> 13 | W7: =X6 -> 21205 | X7: 21205 | Y7: =X7-W7 -> 0 | Z7: =Y7+V7+S7+P7+M7 -> 23 | AA7: 210 | AB7: 121 | AC7: =Gen!AS12 -> 1129.54
A8: =Gen!B13 -> 44138 | B8: =Gen!C13 -> 0.0779 | C8: 8593.31 | D8: 21840.2 | G8: 38.27 | I8: 31157.5 | J8: 20707.1 | K8: =L7 -> 35391 | L8: 35391 | M8: =L8-K8 -> 0 | N8: =O7 -> 30278 | O8: 30290 | P8: =O8-N8 -> 12 | Q8: =R7 -> 35756 | R8: 35756 | S8: =R8-Q8 -> 0 | T8: =U7 -> 32576 | U8: 32576 | V8: =U8-T8 -> 0 | W8: =X7 -> 21205 | X8: 21217 | Y8: =X8-W8 -> 12 | Z8: =Y8+V8+S8+P8+M8 -> 24 | AA8: 225 | AB8: 120 | AC8: =Gen!AS13 -> 1203.26
A9: =Gen!B14 -> 44139 | B9: =Gen!C14 -> 0.0649 | C9: 7390.05 | D9: 21840.2 | F9: 18000 | G9: 51.1 | I9: 31161.3 | J9: 20710.7 | K9: =L8 -> 35391 | L9: 35391 | M9: =L9-K9 -> 0 | N9: =O8 -> 30290 | O9: 30301 | P9: =O9-N9 -> 11 | Q9: =R8 -> 35756 | R9: 35756 | S9: =R9-Q9 -> 0 | T9: =U8 -> 32576 | U9: 32589 | V9: =U9-T9 -> 13 | W9: =X8 -> 21217 | X9: 21217 | Y9: =X9-W9 -> 0 | Z9: =Y9+V9+S9+P9+M9 -> 24 | AA9: 230 | AB9: 115 | AC9: =Gen!AS14 -> 1097.45
A10: =Gen!B15 -> 44140 | B10: =Gen!C15 -> 0.026 | C10: 24292.6 | D10: 21840.2 | G10: 60.15 | I10: 31165.4 | J10: 20713.9 | K10: =L9 -> 35391 | L10: 35391 | M10: =L10-K10 -> 0 | N10: =O9 -> 30301 | O10: 30301 | P10: =O10-N10 -> 0 | Q10: =R9 -> 35756 | R10: 35764 | S10: =R10-Q10 -> 8 | T10: =U9 -> 32589 | U10: 32607 | V10: =U10-T10 -> 18 | W10: =X9 -> 21217 | X10: 21217 | Y10: =X10-W10 -> 0 | Z10: =Y10+V10+S10+P10+M10 -> 26 | AA10: 224 | AB10: 119 | AC10: =Gen!AS15 -> 1118.35
A11: =Gen!B16 -> 44141 | B11: =Gen!C16 -> 0.0649 | C11: 23174.25 | D11: 21840.2 | G11: 92 | I11: 31168.7 | J11: 20716.9 | K11: =L10 -> 35391 | L11: 35391 | M11: =L11-K11 -> 0 | N11: =O10 -> 30301 | O11: 30312 | P11: =O11-N11 -> 11 | Q11: =R10 -> 35764 | R11: 35764 | S11: =R11-Q11 -> 0 | T11: =U10 -> 32607 | U11: 32608 | V11: =U11-T11 -> 1 | W11: =X10 -> 21217 | X11: 21230 | Y11: =X11-W11 -> 13 | Z11: =Y11+V11+S11+P11+M11 -> 25 | AA11: 225 | AB11: 120 | AC11: =Gen!AS16 -> 1081.82
A12: =Gen!B17 -> 44142 | B12: =Gen!C17 -> 0.0519 | C12: 22092.43 | D12: 21840.2 | I12: 31117.2 | J12: 20719.1 | K12: =L11 -> 35391 | L12: 35391 | M12: =L12-K12 -> 0 | N12: =O11 -> 30312 | O12: 30325 | P12: =O12-N12 -> 13 | Q12: =R11 -> 35764 | R12: 35764 | S12: =R12-Q12 -> 0 | T12: =U11 -> 32608 | U12: 32620 | V12: =U12-T12 -> 12 | W12: =X11 -> 21230 | X12: 21230 | Y12: =X12-W12 -> 0 | Z12: =Y12+V12+S12+P12+M12 -> 25 | AA12: 210 | AB12: 120 | AC12: =Gen!AS17 -> 960.95
A13: =Gen!B18 -> 44143 | B13: =Gen!C18 -> 0 | C13: 20887.65 | D13: 21840.2 | I13: 31176.1 | J13: 20723.1 | K13: =L12 -> 35391 | L13: 35391 | M13: =L13-K13 -> 0 | N13: =O12 -> 30325 | O13: 30325 | P13: =O13-N13 -> 0 | Q13: =R12 -> 35764 | R13: 35773 | S13: =R13-Q13 -> 9 | T13: =U12 -> 32620 | U13: 32620 | V13: =U13-T13 -> 0 | W13: =X12 -> 21230 | X13: 21246 | Y13: =X13-W13 -> 16 | Z13: =Y13+V13+S13+P13+M13 -> 25 | AA13: 226 | AB13: 109 | AC13: =Gen!AS18 -> 1024.56
A14: =Gen!B19 -> 44144 | B14: =Gen!C19 -> 0.013 | C14: 20106.92 | D14: 21840.2 | G14: 44.3 | I14: 31179.7 | J14: 20726.2 | K14: =L13 -> 35391 | L14: 35391 | M14: =L14-K14 -> 0 | N14: =O13 -> 30325 | O14: 30336 | P14: =O14-N14 -> 11 | Q14: =R13 -> 35773 | R14: 35773 | S14: =R14-Q14 -> 0 | T14: =U13 -> 32620 | U14: 32633 | V14: =U14-T14 -> 13 | W14: =X13 -> 21246 | X14: 21247 | Y14: =X14-W14 -> 1 | Z14: =Y14+V14+S14+P14+M14 -> 25 | AA14: 220 | AB14: 110 | AC14: =Gen!AS19 -> 1092.15
A15: =Gen!B20 -> 44145 | B15: =Gen!C20 -> 0.039 | C15: 19014.77 | D15: 21840.2 | I15: 31183.2 | J15: 20729.3 | K15: =L14 -> 35391 | L15: 35391 | M15: =L15-K15 -> 0 | N15: =O14 -> 30336 | O15: 30348 | P15: =O15-N15 -> 12 | Q15: =R14 -> 35773 | R15: 35773 | S15: =R15-Q15 -> 0 | T15: =U14 -> 32633 | U15: 32633 | V15: =U15-T15 -> 0 | W15: =X14 -> 21247 | X15: 21247 | Y15: =X15-W15 -> 0 | Z15: =Y15+V15+S15+P15+M15 -> 12 | AA15: 230 | AB15: 120 | AC15: =Gen!AS20 -> 981.99
A16: =Gen!B21 -> 44146 | B16: =Gen!C21 -> 0.0649 | C16: 18081.52 | D16: 21840.2 | G16: 24.05 | I16: 31186.5 | J16: 20732.5 | K16: =L15 -> 35391 | L16: 35391 | M16: =L16-K16 -> 0 | N16: =O15 -> 30348 | O16: 30348 | P16: =O16-N16 -> 0 | Q16: =R15 -> 35773 | R16: 35773 | S16: =R16-Q16 -> 0 | T16: =U15 -> 32633 | U16: 32645 | V16: =U16-T16 -> 12 | W16: =X15 -> 21247 | X16: 21270 | Y16: =X16-W16 -> 23 | Z16: =Y16+V16+S16+P16+M16 -> 35 | AA16: 219 | AB16: 120 | AC16: =Gen!AS21 -> 966.28
A17: =Gen!B22 -> 44147 | B17: =Gen!C22 -> 0.05 | C17: 17066.5 | D17: 21840.2 | G17: 43.4 | I17: 31190.1 | J17: 20735.5 | K17: =L16 -> 35391 | L17: 35391 | M17: =L17-K17 -> 0 | N17: =O16 -> 30348 | O17: 30361 | P17: =O17-N17 -> 13 | Q17: =R16 -> 35773 | R17: 35773 | S17: =R17-Q17 -> 0 | T17: =U16 -> 32645 | U17: 32645 | V17: =U17-T17 -> 0 | W17: =X16 -> 21270 | X17: 21282 | Y17: =X17-W17 -> 12 | Z17: =Y17+V17+S17+P17+M17 -> 25 | AA17: 220 | AB17: 120 | AC17: =Gen!AS22 -> 1126.36
A18: =Gen!B23 -> 44148 | B18: =Gen!C23 -> 0.0519 | C18: 15940.14 | D18: 21840.2 | G18: 134 | I18: 31193.7 | J18: 20738.6 | K18: =L17 -> 35391 | L18: 35391 | M18: =L18-K18 -> 0 | N18: =O17 -> 30361 | O18: 30374 | P18: =O18-N18 -> 13 | Q18: =R17 -> 35773 | R18: 35773 | S18: =R18-Q18 -> 0 | T18: =U17 -> 32645 | U18: 32658 | V18: =U18-T18 -> 13 | W18: =X17 -> 21282 | X18: 21282 | Y18: =X18-W18 -> 0 | Z18: =Y18+V18+S18+P18+M18 -> 26 | AA18: 224 | AB18: 198 | AC18: =Gen!AS23 -> 1093.29
A19: =Gen!B24 -> 44149 | B19: =Gen!C24 -> 0.1818 | C19: 14843.85 | D19: 21840.2 | I19: 31197.8 | J19: 20742.9 | K19: =L18 -> 35391 | L19: 35391 | M19: =L19-K19 -> 0 | N19: =O18 -> 30374 | O19: 30387 | P19: =O19-N19 -> 13 | Q19: =R18 -> 35773 | R19: 35773 | S19: =R19-Q19 -> 0 | T19: =U18 -> 32658 | U19: 32667 | V19: =U19-T19 -> 9 | W19: =X18 -> 21282 | X19: 21282 | Y19: =X19-W19 -> 0 | Z19: =Y19+V19+S19+P19+M19 -> 22 | AA19: 230 | AB19: 120 | AC19: =Gen!AS24 -> 962.89
A20: =Gen!B25 -> 44150 | B20: =Gen!C25 -> 0.1429 | C20: 13873.96 | D20: 21840.2 | G20: 159.26 | I20: 31201.7 | J20: 20745 | K20: =L19 -> 35391 | L20: 35391 | M20: =L20-K20 -> 0 | N20: =O19 -> 30387 | O20: 30387 | P20: =O20-N20 -> 0 | Q20: =R19 -> 35773 | R20: 35773 | S20: =R20-Q20 -> 0 | T20: =U19 -> 32667 | U20: 32679 | V20: =U20-T20 -> 12 | W20: =X19 -> 21282 | X20: 21296 | Y20: =X20-W20 -> 14 | Z20: =Y20+V20+S20+P20+M20 -> 26 | AA20: 225 | AB20: 180 | AC20: =Gen!AS25 -> 1214.33
A21: =Gen!B26 -> 44151 | B21: =Gen!C26 -> 0.1299 | C21: 12659.63 | D21: 21840.2 | G21: 67.51 | I21: 31205.7 | J21: 20748.1 | K21: =L20 -> 35391 | L21: 35391 | M21: =L21-K21 -> 0 | N21: =O20 -> 30387 | O21: 30400 | P21: =O21-N21 -> 13 | Q21: =R20 -> 35773 | R21: 35773 | S21: =R21-Q21 -> 0 | T21: =U20 -> 32679 | U21: 32679 | V21: =U21-T21 -> 0 | W21: =X20 -> 21296 | X21: 21308 | Y21: =X21-W21 -> 12 | Z21: =Y21+V21+S21+P21+M21 -> 25 | AA21: 218 | AB21: 199 | AC21: =Gen!AS26 -> 1197.16
A22: =Gen!B27 -> 44152 | B22: =Gen!C27 -> 0.03 | C22: 11462.47 | D22: 21840.2 | I22: 31209.3 | J22: 20750.7 | K22: =L21 -> 35391 | L22: 35391 | M22: =L22-K22 -> 0 | N22: =O21 -> 30400 | O22: 30413 | P22: =O22-N22 -> 13 | Q22: =R21 -> 35773 | R22: 35773 | S22: =R22-Q22 -> 0 | T22: =U21 -> 32679 | U22: 32690 | V22: =U22-T22 -> 11 | W22: =X21 -> 21308 | X22: 21308 | Y22: =X22-W22 -> 0 | Z22: =Y22+V22+S22+P22+M22 -> 24 | AA22: 220 | AB22: 190 | AC22: =Gen!AS27 -> 928.98
A23: =Gen!B28 -> 44153 | B23: =Gen!C28 -> 0.104 | C23: 10533.49 | D23: 21840.2 | G23: 22.59 | I23: 31213.3 | J23: 20753.6 | K23: =L22 -> 35391 | L23: 35391 | M23: =L23-K23 -> 0 | N23: =O22 -> 30413 | O23: 30425 | P23: =O23-N23 -> 12 | Q23: =R22 -> 35773 | R23: 35773 | S23: =R23-Q23 -> 0 | T23: =U22 -> 32690 | U23: 32690 | V23: =U23-T23 -> 0 | W23: =X22 -> 21308 | X23: 21320 | Y23: =X23-W23 -> 12 | Z23: =Y23+V23+S23+P23+M23 -> 24 | AA23: 221 | AB23: 189 | AC23: =Gen!AS28 -> 1019.83
A24: =Gen!B29 -> 44154 | B24: =Gen!C29 -> 0.052 | C24: 24513.66 | D24: 21840.2 | G24: 78.05 | I24: 31217.2 | J24: 20756.9 | K24: =L23 -> 35391 | L24: 35391 | M24: =L24-K24 -> 0 | N24: =O23 -> 30425 | O24: 30436 | P24: =O24-N24 -> 11 | Q24: =R23 -> 35773 | R24: 35773 | S24: =R24-Q24 -> 0 | T24: =U23 -> 32690 | U24: 32703 | V24: =U24-T24 -> 13 | W24: =X23 -> 21320 | X24: 21320 | Y24: =X24-W24 -> 0 | Z24: =Y24+V24+S24+P24+M24 -> 24 | AA24: 220 | AB24: 140 | AC24: =Gen!AS29 -> 1119.72
A25: =Gen!B30 -> 44155 | B25: =Gen!C30 -> 0.052 | C25: 23393.94 | D25: 21840.2 | I25: 31221.1 | J25: 20760.3 | K25: =L24 -> 35391 | L25: 35391 | M25: =L25-K25 -> 0 | N25: =O24 -> 30436 | O25: 30449 | P25: =O25-N25 -> 13 | Q25: =R24 -> 35773 | R25: 35773 | S25: =R25-Q25 -> 0 | T25: =U24 -> 32703 | U25: 32703 | V25: =U25-T25 -> 0 | W25: =X24 -> 21320 | X25: 21332 | Y25: =X25-W25 -> 12 | Z25: =Y25+V25+S25+P25+M25 -> 25 | AA25: 218 | AB25: 164 | AC25: =Gen!AS30 -> 1005.06
A26: =Gen!B31 -> 44156 | B26: =Gen!C31 -> 0.065 | C26: 22388.88 | D26: 21840.2 | G26: 197.39 | I26: 31225.1 | J26: 20763.8 | K26: =L25 -> 35391 | L26: 35391 | M26: =L26-K26 -> 0 | N26: =O25 -> 30449 | O26: 30449 | P26: =O26-N26 -> 0 | Q26: =R25 -> 35773 | R26: 35787 | S26: =R26-Q26 -> 14 | T26: =U25 -> 32703 | U26: 32715 | V26: =U26-T26 -> 12 | W26: =X25 -> 21332 | X26: 21332 | Y26: =X26-W26 -> 0 | Z26: =Y26+V26+S26+P26+M26 -> 26 | AA26: 221 | AB26: 173 | AC26: =Gen!AS31 -> 1302.83
A27: =Gen!B32 -> 44157 | B27: =Gen!C32 -> 0.1 | C27: 21086.05 | D27: 21840.2 | G27: 9.15 | I27: 31229 | J27: 20767 | K27: =L26 -> 35391 | L27: 35391 | M27: =L27-K27 -> 0 | N27: =O26 -> 30449 | O27: 30449 | P27: =O27-N27 -> 0 | Q27: =R26 -> 35787 | R27: 35798 | S27: =R27-Q27 -> 11 | T27: =U26 -> 32715 | U27: 32728 | V27: =U27-T27 -> 13 | W27: =X26 -> 21332 | X27: 21332 | Y27: =X27-W27 -> 0 | Z27: =Y27+V27+S27+P27+M27 -> 24 | AA27: 225 | AB27: 140 | AC27: =Gen!AS32 -> 1053.19
A28: =Gen!B33 -> 44158 | B28: =Gen!C33 -> 0.065 | C28: 20032.86 | D28: 21840.2 | I28: 31233.2 | J28: 20770.2 | K28: =L27 -> 35391 | L28: 35391 | M28: =L28-K28 -> 0 | N28: =O27 -> 30449 | O28: 30449 | P28: =O28-N28 -> 0 | Q28: =R27 -> 35798 | R28: 35798 | S28: =R28-Q28 -> 0 | T28: =U27 -> 32728 | U28: 32728 | V28: =U28-T28 -> 0 | W28: =X27 -> 21332 | X28: 21356 | Y28: =X28-W28 -> 24 | Z28: =Y28+V28+S28+P28+M28 -> 24 | AA28: 200 | AB28: 161 | AC28: =Gen!AS33 -> 1074.84
A29: =Gen!B34 -> 44159 | B29: =Gen!C34 -> 0.065 | C29: 18958.02 | D29: 21840.2 | G29: 67 | I29: 31236.8 | J29: 20773.4 | K29: =L28 -> 35391 | L29: 35391 | M29: =L29-K29 -> 0 | N29: =O28 -> 30449 | O29: 30449 | P29: =O29-N29 -> 0 | Q29: =R28 -> 35798 | R29: 35822 | S29: =R29-Q29 -> 24 | T29: =U28 -> 32728 | U29: 32728 | V29: =U29-T29 -> 0 | W29: =X28 -> 21356 | X29: 21356 | Y29: =X29-W29 -> 0 | Z29: =Y29+V29+S29+P29+M29 -> 24 | AA29: 210 | AB29: 140 | AC29: =Gen!AS34 -> 1086.27
A30: =Gen!B35 -> 44160 | B30: =Gen!C35 -> 0.039 | C30: 17871.75 | D30: 21840.2 | G30: 20.32 | I30: 31240.3 | J30: 20776.5 | K30: =L29 -> 35391 | L30: 35391 | M30: =L30-K30 -> 0 | N30: =O29 -> 30449 | O30: 30473 | P30: =O30-N30 -> 24 | Q30: =R29 -> 35822 | R30: 35822 | S30: =R30-Q30 -> 0 | T30: =U29 -> 32728 | U30: 32728 | V30: =U30-T30 -> 0 | W30: =X29 -> 21356 | X30: 21356 | Y30: =X30-W30 -> 0 | Z30: =Y30+V30+S30+P30+M30 -> 24 | AA30: 198 | AB30: 120 | AC30: =Gen!AS35 -> 999.34
A31: =Gen!B36 -> 44161 | B31: =Gen!C36 -> 0.013 | C31: 16872.41 | D31: 21840.2 | I31: 31243.9 | J31: 20779.4 | K31: =L30 -> 35391 | L31: 35391 | M31: =L31-K31 -> 0 | N31: =O30 -> 30473 | O31: 30473 | P31: =O31-N31 -> 0 | Q31: =R30 -> 35822 | R31: 35822 | S31: =R31-Q31 -> 0 | T31: =U30 -> 32728 | U31: 32728 | V31: =U31-T31 -> 0 | W31: =X30 -> 21356 | X31: 21380 | Y31: =X31-W31 -> 24 | Z31: =Y31+V31+S31+P31+M31 -> 24 | AA31: 199 | AB31: 120 | AC31: =Gen!AS36 -> 928.16
A32: =Gen!B37 -> 44162 | B32: =Gen!C37 -> 0.01 | C32: 15944.25 | D32: 21840.2 | G32: 37.38 | I32: 31247.6 | J32: 20782.5 | K32: =L31 -> 35391 | L32: 35391 | M32: =L32-K32 -> 0 | N32: =O31 -> 30473 | O32: 30473 | P32: =O32-N32 -> 0 | Q32: =R31 -> 35822 | R32: 35822 | S32: =R32-Q32 -> 0 | T32: =U31 -> 32728 | U32: 32753 | V32: =U32-T32 -> 25 | W32: =X31 -> 21380 | X32: 21380 | Y32: =X32-W32 -> 0 | Z32: =Y32+V32+S32+P32+M32 -> 25 | AA32: 197 | AB32: 130 | AC32: =Gen!AS37 -> 1058.96
A33: =Gen!B38 -> 44163 | B33: =Gen!C38 -> 0.026 | C33: 14885.29 | D33: 21840.2 | I33: 31251.1 | J33: 20785.4 | K33: =L32 -> 35391 | L33: 35391 | M33: =L33-K33 -> 0 | N33: =O32 -> 30473 | O33: 30480 | P33: =O33-N33 -> 7 | Q33: =R32 -> 35822 | R33: 35840 | S33: =R33-Q33 -> 18 | T33: =U32 -> 32753 | U33: 32753 | V33: =U33-T33 -> 0 | W33: =X32 -> 21380 | X33: 21380 | Y33: =X33-W33 -> 0 | Z33: =Y33+V33+S33+P33+M33 -> 25 | AA33: 198 | AB33: 125 | AC33: =Gen!AS38 -> 969.62
A34: =Gen!B39 -> 44164 | B34: =Gen!C39 -> 0.026 | C34: 13915.67 | D34: 21840.2 | G34: 38.6 | I34: 31254.7 | J34: 20788.3 | K34: =L33 -> 35391 | L34: 35391 | M34: =L34-K34 -> 0 | N34: =O33 -> 30480 | O34: 30480 | P34: =O34-N34 -> 0 | Q34: =R33 -> 35840 | R34: 35840 | S34: =R34-Q34 -> 0 | T34: =U33 -> 32753 | U34: 32753 | V34: =U34-T34 -> 0 | W34: =X33 -> 21380 | X34: 21404 | Y34: =X34-W34 -> 24 | Z34: =Y34+V34+S34+P34+M34 -> 24 | AA34: 200 | AB34: 131 | AC34: =Gen!AS39 -> 997.97
A35: =Gen!B40 -> 44165 | B35: =Gen!C40 -> 0.039 | C35: 12917.71 | D35: 21840.2 | G35: 318 | I35: 31258.1 | J35: 20791.7 | K35: =L34 -> 35391 | L35: 35391 | M35: =L35-K35 -> 0 | N35: =O34 -> 30480 | O35: 30480 | P35: =O35-N35 -> 0 | Q35: =R34 -> 35840 | R35: 35840 | S35: =R35-Q35 -> 0 | T35: =U34 -> 32753 | U35: 32777 | V35: =U35-T35 -> 24 | W35: =X34 -> 21404 | X35: 21404 | Y35: =X35-W35 -> 0 | Z35: =Y35+V35+S35+P35+M35 -> 24 | AA35: 199 | AB35: 125 | AC35: =Gen!AS40 -> 1241.68
A36: =Gen!B41 -> 44166 | B36: =Gen!C41 -> 0 | C36: 11686.02 | D36: 21840.2 | K36: =L35 -> 35391 | M36: =L36-K36 -> -35391 | N36: =O35 -> 30480 | P36: =O36-N36 -> -30480 | Q36: =R35 -> 35840 | S36: =R36-Q36 -> -35840 | T36: =U35 -> 32777 | V36: =U36-T36 -> -32777 | W36: =X35 -> 21404 | Y36: =X36-W36 -> -21404 | Z36: =Y36+V36+S36+P36+M36 -> -155892 | AC36: =Gen!AS41 -> 0
A37: =Gen!B42 -> 0 | B37: =Gen!C42 -> 0 | K37: =L36 -> 0 | M37: =L37-K37 -> 0 | N37: =O36 -> 0 | P37: =O37-N37 -> 0 | Q37: =R36 -> 0 | S37: =R37-Q37 -> 0 | T37: =U36 -> 0 | V37: =U37-T37 -> 0 | W37: =X36 -> 0 | Y37: =X37-W37 -> 0 | Z37: =Y37+V37+S37+P37+M37 -> 0 | AC37: =Gen!AS42 -> 0

Sheet Gen
E2: HLP REPORT OCTOBER 2020
G6: BILILA LODGE INVESTMENT LIMITED | W6: 1 | X6: 2 | Y6: 3 | Z6: 4 | AA6: 5 | AB6: 6 | AC6: 7 | AD6: 8 | AE6: 9 | AF6: 10 | AG6: 11
G7: Diesel Consumed by 500KVA Generator | N7: 500KVA Generator KWh | W7: Safari-STAFF | X7: Safari-STAFF | Y7: Lc/swg/gust | Z7: Eng pikcup | AA7: VIP Safari Car | AB7: GX Guest | AC7: GX Guest | AD7: T/Hillux/pur | AE7: TATA | AF7: MAN | AG7: F/Truck | AH7: Incenerator | AI7: A&K | AJ7: OTHER | AK7: TOTAL CO
B8: Date | C8: Occupancy % | D8: OPENING | E8: Received | F8: Schedule delivery | G8: Company | H8: 1 | I8: 2 | J8: 3 | K8: 4 | L8: 5 | M8: 6 | N8: 1 | O8: 2 | P8: 3 | Q8: 4 | R8: 5 | S8: 6 | T8: Total Diseal Consumed | U8: Total Kwh generated | V8: Average Diesel/Kwh | W8: T 128 AXJ | X8: T 134 AXJ | Y8: T 499 AXG | Z8: T 217 CHV | AA8: T 214 CHV | AB8: T 139 AXE | AC8: T 242 AXN | AD8: T 476 AWZ | AE8: T 226 AUQ | AF8: T 308 CLD | AG8: T 852 AWU | AH8: Machine ENG | AI8: Vehicle | AJ8: Vehicle | AS8: Total Diseal Consumed Gen & Vehicle | AT8: Total cost /Day (TSH) | AU8: BALANCE
D9: 32519.1 | T9: =SUM(G9:M9) -> 0 | U9: =SUM(N9:S9) -> 0 | AS9: =SUM(AK9+T9) -> 0 | AU9: 38784.7
T10: =SUM(G10:M10) -> 0 | U10: =SUM(N10:S10) -> 0 | V10: =SUM(O10:T10) -> 0 | AK10: =SUM(W10:AJ10) -> 0 | AS10: =SUM(AK10+T10) -> 0
B11: 44136 | C11: 0.026 | D11: =SUM(D9+E11) -> 32519.1 | H11: 432.45 | M11: 523.6 | N11: 1083 | S11: 1332 | T11: =SUM(G11:M11) -> 956.05 | U11: =SUM(N11:S11) -> 2415 | V11: =T11/U11 -> 0.39587992 | AK11: =SUM(W11:AJ11) -> 0 | AS11: =SUM(AK11+T11) -> 956.05 | AT11: =AS11*AV11 -> 0 | AU11: =D11 -> 32519.1
B12: 44137 | C12: 0.0519 | D12: =SUM(D11-AS11+E12) -> 31563.05 | H12: 443.5 | L12: 664.42 | N12: 1069 | R12: 1548 | T12: =SUM(G12:M12) -> 1107.92 | U12: =SUM(N12:S12) -> 2617 | V12: =T12/U12 -> 0.42335499 | X12: 21.62 | AK12: =SUM(W12:AJ12) -> 21.62 | AS12: =SUM(AK12+T12) -> 1129.54 | AT12: =AS12*AV12 -> 0 | AU12: =D12 -> 31563.05
B13: 44138 | C13: 0.0779 | D13: =SUM(D12-AS12+E13) -> 30433.51 | I13: 578.93 | M13: 586.06 | O13: 1213 | S13: 1379 | T13: =SUM(G13:M13) -> 1164.99 | U13: =SUM(N13:S13) -> 2592 | V13: =T13/U13 -> 0.44945602 | Y13: 23.27 | AJ13: 15 | AK13: =SUM(W13:AJ13) -> 38.27 | AS13: =SUM(AK13+T13) -> 1203.26 | AT13: =AS13*AV13 -> 0 | AU13: =D13 -> 30433.51
B14: 44139 | C14: 0.0649 | D14: =SUM(D13-AS13+E14) -> 47230.25 | E14: 18000 | F14: 18000 | G14: Puma | I14: 410.01 | L14: 636.34 | O14: 1191 | R14: 1464 | T14: =SUM(G14:M14) -> 1046.35 | U14: =SUM(N14:S14) -> 2655 | V14: =T14/U14 -> 0.39410546 | X14: 51.1 | AK14: =SUM(W14:AJ14) -> 51.1 | AS14: =SUM(AK14+T14) -> 1097.45 | AT14: =AS14*AV14 -> 0 | AU14: =D14 -> 47230.25
B15: 44140 | C15: 0.026 | D15: =SUM(D14-AS14+E15) -> 46132.8 | K15: 270.4 | L15: 787.8 | Q15: 705 | R15: 1890 | T15: =SUM(G15:M15) -> 1058.2 | U15: =SUM(N15:S15) -> 2595 | V15: =T15/U15 -> 0.4077842 | Y15: 11.15 | AI15: 49 | AK15: =SUM(W15:AJ15) -> 60.15 | AS15: =SUM(AK15+T15) -> 1118.35 | AT15: =AS15*AV15 -> 0 | AU15: =D15 -> 46132.8
B16: 44141 | C16: 0.0649 | D16: =SUM(D15-AS15+E16) -> 45014.45 | I16: 449.26 | M16: 540.56 | O16: 906 | S16: 1311 | T16: =SUM(G16:M16) -> 989.82 | U16: =SUM(N16:S16) -> 2217 | V16: =T16/U16 -> 0.4464682 | AI16: 92 | AK16: =SUM(W16:AJ16) -> 92 | AS16: =SUM(AK16+T16) -> 1081.82 | AT16: =AS16*AV16 -> 0 | AU16: =D16 -> 45014.45
B17: 44142 | C17: 0.0519 | D17: =SUM(D16-AS16+E17) -> 43932.63 | I17: 401.96 | L17: 550.59 | O17: 1177 | R17: 1302 | T17: =SUM(G17:M17) -> 952.55 | U17: =SUM(N17:S17) -> 2479 | V17: =T17/U17 -> 0.38424768 | Y17: 8.4 | AK17: =SUM(W17:AJ17) -> 8.4 | AS17: =SUM(AK17+T17) -> 960.95 | AT17: =AS17*AV17 -> 0 | AU17: =D17 -> 43932.63
B18: 44143 | C18: 0 | D18: =SUM(D17-AS17+E18) -> 42971.68 | K18: 389.57 | M18: 634.99 | Q18: 823 | S18: 1518 | T18: =SUM(G18:M18) -> 1024.56 | U18: =SUM(N18:S18) -> 2341 | V18: =T18/U18 -> 0.43765912 | AK18: =SUM(W18:AJ18) -> 0 | AS18: =SUM(AK18+T18) -> 1024.56 | AT18: =AS18*AV18 -> 0 | AU18: =D18 -> 42971.68
B19: 44144 | C19: 0.013 | D19: =SUM(D18-AS18+E19) -> 41947.12 | I19: 556.63 | L19: 491.22 | O19: 1188 | R19: 1172 | T19: =SUM(G19:M19) -> 1047.85 | U19: =SUM(N19:S19) -> 2360 | V19: =T19/U19 -> 0.44400424 | X19: 44.3 | AK19: =SUM(W19:AJ19) -> 44.3 | AS19: =SUM(AK19+T19) -> 1092.15 | AT19: =AS19*AV19 -> 0 | AU19: =D19 -> 41947.12
B20: 44145 | C20: 0.039 | D20: =SUM(D19-AS19+E20) -> 40854.97 | I20: 386.94 | M20: 546.31 | O20: 1114 | S20: 1209 | T20: =SUM(G20:M20) -> 933.25 | U20: =SUM(N20:S20) -> 2323 | V20: =T20/U20 -> 0.40174344 | AE20: 48.74 | AK20: =SUM(W20:AJ20) -> 48.74 | AS20: =SUM(AK20+T20) -> 981.99 | AT20: =AS20*AV20 -> 0 | AU20: =D20 -> 40854.97
B21: 44146 | C21: 0.0649 | D21: =SUM(D20-AS20+E21) -> 39872.98 | L21: 487.43 | M21: 454.8 | R21: 1095 | S21: 1188 | T21: =SUM(G21:M21) -> 942.23 | U21: =SUM(N21:S21) -> 2283 | V21: =T21/U21 -> 0.41271572 | Y21: 24.05 | AK21: =SUM(W21:AJ21) -> 24.05 | AS21: =SUM(AK21+T21) -> 966.28 | AT21: =AS21*AV21 -> 0 | AU21: =D21 -> 39872.98
B22: 44147 | C22: 0.05 | D22: =SUM(D21-AS21+E22) -> 38906.7 | I22: 550.39 | M22: 532.57 | O22: 1131 | S22: 1197 | T22: =SUM(G22:M22) -> 1082.96 | U22: =SUM(N22:S22) -> 2328 | V22: =T22/U22 -> 0.465189 | AD22: 43.4 | AK22: =SUM(W22:AJ22) -> 43.4 | AS22: =SUM(AK22+T22) -> 1126.36 | AT22: =AS22*AV22 -> 0 | AU22: =D22 -> 38906.7
B23: 44148 | C23: 0.0519 | D23: =SUM(D22-AS22+E23) -> 37780.34 | I23: 442.78 | L23: 516.51 | O23: 1156 | R23: 1206 | T23: =SUM(G23:M23) -> 959.29 | U23: =SUM(N23:S23) -> 2362 | V23: =T23/U23 -> 0.40613463 | AI23: 134 | AK23: =SUM(W23:AJ23) -> 134 | AS23: =SUM(AK23+T23) -> 1093.29 | AT23: =AS23*AV23 -> 0 | AU23: =D23 -> 37780.34
B24: 44149 | C24: 0.1818 | D24: =SUM(D23-AS23+E24) -> 36687.05 | I24: 501.61 | L24: 461.28 | O24: 1268 | R24: 1112 | T24: =SUM(G24:M24) -> 962.89 | U24: =SUM(N24:S24) -> 2380 | V24: =T24/U24 -> 0.40457563 | AK24: =SUM(W24:AJ24) -> 0 | AS24: =SUM(AK24+T24) -> 962.89 | AT24: =AS24*AV24 -> 0 | AU24: =D24 -> 36687.05
B25: 44150 | C25: 0.1429 | D25: =SUM(D24-AS24+E25) -> 35724.16 | L25: 453.26 | M25: 601.81 | R25: 1046 | S25: 1291 | T25: =SUM(G25:M25) -> 1055.07 | U25: =SUM(N25:S25) -> 2337 | V25: =T25/U25 -> 0.45146341 | Z25: 44.26 | AI25: 115 | AK25: =SUM(W25:AJ25) -> 159.26 | AS25: =SUM(AK25+T25) -> 1214.33 | AT25: =AS25*AV25 -> 0 | AU25: =D25 -> 35724.16
B26: 44151 | C26: 0.1299 | D26: =SUM(D25-AS25+E26) -> 34509.83 | I26: 546.58 | M26: 583.07 | O26: 1144 | S26: 1324 | T26: =SUM(G26:M26) -> 1129.65 | U26: =SUM(N26:S26) -> 2468 | V26: =T26/U26 -> 0.4577188 | X26: 57.1 | Y26: 10.41 | AK26: =SUM(W26:AJ26) -> 67.51 | AS26: =SUM(AK26+T26) -> 1197.16 | AT26: =AS26*AV26 -> 0 | AU26: =D26 -> 34509.83
B27: 44152 | C27: 0.03 | D27: =SUM(D26-AS26+E27) -> 33312.67 | I27: 435.19 | L27: 493.79 | O27: 1086 | R27: 1180 | T27: =SUM(G27:M27) -> 928.98 | U27: =SUM(N27:S27) -> 2266 | V27: =T27/U27 -> 0.4099647 | AK27: =SUM(W27:AJ27) -> 0 | AS27: =SUM(AK27+T27) -> 928.98 | AT27: =AS27*AV27 -> 0 | AU27: =D27 -> 33312.67
B28: 44153 | C28: 0.104 | D28: =SUM(D27-AS27+E28) -> 47383.69 | E28: 15000 | F28: 15000 | G28: Raha | I28: 486.24 | M28: 511 | O28: 1159 | R28: 1239 | T28: =SUM(G28:M28) -> 997.24 | U28: =SUM(N28:S28) -> 2398 | V28: =T28/U28 -> 0.41586322 | Y28: 22.59 | AK28: =SUM(W28:AJ28) -> 22.59 | AS28: =SUM(AK28+T28) -> 1019.83 | AT28: =AS28*AV28 -> 0 | AU28: =D28 -> 47383.69
B29: 44154 | C29: 0.052 | D29: =SUM(D28-AS28+E29) -> 46363.86 | I29: 419.43 | L29: 622.24 | O29: 1073 | R29: 1514 | T29: =SUM(G29:M29) -> 1041.67 | U29: =SUM(N29:S29) -> 2587 | V29: =T29/U29 -> 0.40265559 | X29: 33.73 | Y29: 9.54 | AA29: 34.78 | AK29: =SUM(W29:AJ29) -> 78.05 | AS29: =SUM(AK29+T29) -> 1119.72 | AT29: =AS29*AV29 -> 0 | AU29: =D29 -> 46363.86
B30: 44155 | C30: 0.052 | D30: =SUM(D29-AS29+E30) -> 45244.14 | I30: 444.85 | M30: 560.21 | O30: 1384 | R30: 1208 | T30: =SUM(G30:M30) -> 1005.06 | U30: =SUM(N30:S30) -> 2592 | V30: =T30/U30 -> 0.38775463 | AK30: =SUM(W30:AJ30) -> 0 | AS30: =SUM(AK30+T30) -> 1005.06 | AT30: =AS30*AV30 -> 0 | AU30: =D30 -> 45244.14
B31: 44156 | C31: 0.065 | D31: =SUM(D30-AS30+E31) -> 44239.08 | K31: 518.17 | L31: 587.27 | Q31: 1223 | R31: 1450 | T31: =SUM(G31:M31) -> 1105.44 | U31: =SUM(N31:S31) -> 2673 | V31: =T31/U31 -> 0.4135578 | Y31: 8.23 | AC31: 72.16 | AI31: 117 | AK31: =SUM(W31:AJ31) -> 197.39 | AS31: =SUM(AK31+T31) -> 1302.83 | AT31: =AS31*AV31 -> 0 | AU31: =D31 -> 44239.08
B32: 44157 | C32: 0.1 | D32: =SUM(D31-AS31+E32) -> 42936.25 | K32: 524.58 | L32: 519.46 | Q32: 1340 | R32: 1245 | T32: =SUM(G32:M32) -> 1044.04 | U32: =SUM(N32:S32) -> 2585 | V32: =T32/U32 -> 0.40388395 | Y32: 9.15 | AK32: =SUM(W32:AJ32) -> 9.15 | AS32: =SUM(AK32+T32) -> 1053.19 | AT32: =AS32*AV32 -> 0 | AU32: =D32 -> 42936.25
B33: 44158 | C33: 0.065 | D33: =SUM(D32-AS32+E33) -> 41883.06 | M33: 1074.84 | S33: 2587 | T33: =SUM(G33:M33) -> 1074.84 | U33: =SUM(N33:S33) -> 2587 | V33: =T33/U33 -> 0.41547739 | AK33: =SUM(W33:AJ33) -> 0 | AS33: =SUM(AK33+T33) -> 1074.84 | AT33: =AS33*AV33 -> 0 | AU33: =D33 -> 41883.06
B34: 44159 | C34: 0.065 | D34: =SUM(D33-AS33+E34) -> 40808.22 | K34: 1019.27 | Q34: 2376 | T34: =SUM(G34:M34) -> 1019.27 | U34: =SUM(N34:S34) -> 2376 | V34: =T34/U34 -> 0.42898569 | AI34: 67 | AK34: =SUM(W34:AJ34) -> 67 | AS34: =SUM(AK34+T34) -> 1086.27 | AT34: =AS34*AV34 -> 0 | AU34: =D34 -> 40808.22
B35: 44160 | C35: 0.039 | D35: =SUM(D34-AS34+E35) -> 39721.95 | I35: 979.02 | O35: 2258 | T35: =SUM(G35:M35) -> 979.02 | U35: =SUM(N35:S35) -> 2258 | V35: =T35/U35 -> 0.43357839 | X35: 20.32 | AK35: =SUM(W35:AJ35) -> 20.32 | AS35: =SUM(AK35+T35) -> 999.34 | AT35: =AS35*AV35 -> 0 | AU35: =D35 -> 39721.95
B36: 44161 | C36: 0.013 | D36: =SUM(D35-AS35+E36) -> 38722.61 | M36: 928.16 | S36: 2255 | T36: =SUM(G36:M36) -> 928.16 | U36: =SUM(N36:S36) -> 2255 | V36: =T36/U36 -> 0.41160089 | AK36: =SUM(W36:AJ36) -> 0 | AS36: =SUM(AK36+T36) -> 928.16 | AT36: =AS36*AV36 -> 0 | AU36: =D36 -> 38722.61
B37: 44162 | C37: 0.01 | D37: =SUM(D36-AS36+E37) -> 37794.45 | L37: 1021.58 | R37: 2395 | T37: =SUM(G37:M37) -> 1021.58 | U37: =SUM(N37:S37) -> 2395 | V37: =T37/U37 -> 0.42654697 | AD37: 37.38 | AK37: =SUM(W37:AJ37) -> 37.38 | AS37: =SUM(AK37+T37) -> 1058.96 | AT37: =AS37*AV37 -> 0 | AU37: =D37 -> 37794.45
B38: 44163 | C38: 0.026 | D38: =SUM(D37-AS37+E38) -> 36735.49 | I38: 246.71 | K38: 722.91 | T38: =SUM(G38:M38) -> 969.62 | U38: =SUM(N38:S38) -> 0 | V38: =T38/U38 -> #DIV/0! | AK38: =SUM(W38:AJ38) -> 0 | AS38: =SUM(AK38+T38) -> 969.62 | AT38: =AS38*AV38 -> 0 | AU38: =D38 -> 36735.49
B39: 44164 | C39: 0.026 | D39: =SUM(D38-AS38+E39) -> 35765.87 | M39: 959.37 | S39: 2264 | T39: =SUM(G39:M39) -> 959.37 | U39: =SUM(N39:S39) -> 2264 | V39: =T39/U39 -> 0.42375 | AA39: 38.6 | AK39: =SUM(W39:AJ39) -> 38.6 | AS39: =SUM(AK39+T39) -> 997.97 | AT39: =AS39*AV39 -> 0 | AU39: =D39 -> 35765.87
B40: 44165 | C40: 0.039 | D40: =SUM(D39-AS39+E40) -> 34767.9 | L40: 923.68 | T40: =SUM(G40:M40) -> 923.68 | U40: =SUM(N40:S40) -> 0 | V40: =T40/U40 -> #DIV/0! | AI40: 318 | AK40: =SUM(W40:AJ40) -> 318 | AS40: =SUM(AK40+T40) -> 1241.68 | AT40: =AS40*AV40 -> 0 | AU40: =D40 -> 34767.9
B41: 44166 | D41: =SUM(D40-AS40+E41) -> 33526.22 | T41: =SUM(G41:M41) -> 0 | U41: =SUM(N41:S41) -> 0 | V41: =T41/U41 -> #DIV/0! | AK41: =SUM(W41:AJ41) -> 0 | AS41: =SUM(AK41+T41) -> 0 | AT41: =AS41*AV41 -> 0 | AU41: =D41 -> 33526.22
D42: =SUM(D41-AS41+E42) -> 33526.22 | T42: =SUM(G42:M42) -> 0 | U42: =SUM(N42:S42) -> 0 | AK42: =SUM(W42:AJ42) -> 0 | AS42: =SUM(AK42+T42) -> 0 | AT42: =AS42*AV42 -> 0 | AU42: =D42 -> 33526.22
B43: BF | C43: =AVERAGE(C11:C42) -> 0.05743 | D43: =SUM(D42-AS42+E43) -> 33526.22 | T43: =SUM(G43:M43) -> 0 | U43: =SUM(N43:S43) -> 0 | AK43: =SUM(W43:AJ43) -> 0 | AS43: =SUM(AK43+T43) -> 0 | AT43: =AS43*AV43 -> 0 | AU43: =D43 -> 33526.22
T44: =SUM(G44:M44) -> 0 | AK44: =SUM(W44:AJ44) -> 0 | AS44: =T44+AK44 -> 0 | AT44: =AS44*AV44 -> 0
E45: =SUM(E11:E44) -> 33000 | F45: =SUM(F11:F42) -> 33000 | G45: =SUM(G11:G44) -> 0 | H45: =SUM(H11:H44) -> 875.95 | I45: =SUM(I11:I44) -> 7836.53 | J45: =SUM(J11:J44) -> 0 | K45: =SUM(K11:K44) -> 3444.9 | L45: =SUM(L11:L44) -> 9216.87 | M45: =SUM(M11:M44) -> 9037.35 | N45: =SUM(N11:N44) -> 2152 | ... P45: =SUM(P11:P44) -> 0 | Q45: =SUM(Q11:Q43) -> 6467 | R45: =SUM(R11:R44) -> 22066 | S45: =SUM(S11:S44) -> 18855 | T45: =SUM(H45:M45) -> 30411.6 | U45: =SUM(N45:S45) -> 67988 | V45: =SUM(V11:V42) -> #DIV/0! | W45: =SUM(W9:W44) -> 0 | X45: =SUM(X9:X44) -> 228.17 | Y45: =SUM(Y9:Y44) -> 126.79 | Z45: =SUM(Z9:Z44) -> 44.26 | AA45: =SUM(AA9:AA44) -> 73.38 | AB45: =SUM(AB9:AB44) -> 0 | AC45: =SUM(AC9:AC44) -> 72.16 | AD45: =SUM(AD10:AD44) -> 80.78 | AE45: =SUM(AE10:AE44) -> 48.74 | AF45: =SUM(AF9:AF44) -> 0 | AG45: =SUM(AG9:AG44) -> 0 | AH45: =SUM(AH9:AH44) -> 0 | AI45: =SUM(AI9:AI43) -> 892 | AJ45: =SUM(AJ9:AJ39) -> 15 | AK45: =SUM(AK9:AK44) -> 1581.28 | AS45: =SUM(AS11:AS43) -> 31992.88 | AT45: =SUM(AT11:AT44) -> 0
B46: Nb Day
T47: =AVERAGE(T11:T41) -> 981.01935 | U47: =T45*2315 -> 70402854 | V47: TZS | AS47: =AS45*2143 -> 68560742 | AT47: TZS
B48: Av. Occ | U48: =U47/2289 -> 30757.035 | V48: USD | AS48: =AS47/2289 -> 29952.268 | AT48: USD
C50: A & K VEHICLES | I50: MAULY VEHICLES | O50: GREEN LAND VEHICLES | U50: OTHERS VEHICLES
C51: Date | D51: Vehicles | E51: Liters | F51: Driver name | G51: Authority manager | I51: Date | J51: Vehicles | K51: Liters | L51: Driver name | M51: Authority manager | O51: Date | P51: Vehicles | Q51: Liters | R51: Driver name | S51: Authorized Manager | U51: Date | V51: Vehicles | W51: Liters | X51: Driver name | Y51: Athorized Manager | Z51: Reasons
C52: 44140 | D52: T132CWQ | E52: 49 | F52: Dolnad | G52: Huruma | Z52: Cash paid
C53: 44141 | D53: T364AHF | E53: 92 | F53: Osmn | G53: Huruma
C54: 44148 | D54: T391DRQ | E54: 134 | F54: Nuru | G54: Huruma
C55: 44150 | D55: T111CWQ | E55: 94 | F55: Eliakim | G55: Huruma
C56: 44150 | D56: T391DQR | E56: 21 | F56: Nuru | G56: Huruma
C57: 44156 | D57: T880DKQ | E57: 117 | F57: Kessi | G57: Huruma
C58: 44159 | D58: T391DQR | E58: 67 | F58: Gudluck | G58: Huruma
C59: 44165 | D59: T111CWQ | E59: 58 | F59: Siraji | G59: Huruma
C60: 44165 | D60: T391DQR | E60: 66 | F60: Gudluck | G60: Huruma
C61: 44165 | D61: T880DKQ | E61: 56 | F61: Kessi | G61: Huruma
C62: 44165 | D62: T132CWQ | E62: 138 | F62: Mosses | G62: Huruma

Sheet Energy Graph
A1: Date | B1: Usage KW | C1: Occ % | D1: Cost per room Total Occ | E1: Cost per room Guest Occ
A2: =Gen!B11 -> 44136 | B2: =SUM('[1]Summery Report'!F5) -> 5669 | C2: =SUM('[1]Summery Report'!C5) -> 0.623 | D2: =SUM('[1]Summery Report'!#REF!) -> #REF! | E2: =SUM('[1]Summery Report'!#REF!) -> #REF! | F2: 0.1
A3: =Gen!B12 -> 44137 | B3: =SUM('[1]Summery Report'!F6) -> 6159 | C3: =SUM('[1]Summery Report'!C6) -> 0.779 | D3: =SUM('[1]Summery Report'!#REF!) -> #REF! | E3: =SUM('[1]Summery Report'!#REF!) -> #REF! | F3: 0.1375
A4: =Gen!B13 -> 44138 | B4: =SUM('[1]Summery Report'!F7) -> 6580 | C4: =SUM('[1]Summery Report'!C7) -> 0.532 | D4: =SUM('[1]Summery Report'!#REF!) -> #REF! | E4: =SUM('[1]Summery Report'!#REF!) -> #REF! | F4: 0.0875
A5: =Gen!B14 -> 44139 | B5: =SUM('[1]Summery Report'!F8) -> 6223 | C5: =SUM('[1]Summery Report'!C8) -> 0.61 | D5: =SUM('[1]Summery Report'!#REF!) -> #REF! | E5: =SUM('[1]Summery Report'!#REF!) -> #REF! | F5: 0.225
A6: =Gen!B15 -> 44140 | B6: =SUM('[1]Summery Report'!F9) -> 5984 | C6: =SUM('[1]Summery Report'!C9) -> 0.688 | D6: =SUM('[1]Summery Report'!#REF!) -> #REF! | E6: =SUM('[1]Summery Report'!#REF!) -> #REF! | F6: 0.2
A7: =Gen!B16 -> 44141 | B7: =SUM('[1]Summery Report'!F10) -> 6103 | C7: =SUM('[1]Summery Report'!C10) -> 0.532 | D7: =SUM('[1]Summery Report'!#REF!) -> #REF! | E7: =SUM('[1]Summery Report'!#REF!) -> #REF! | F7: 0.35
A8: =Gen!B17 -> 44142 | B8: =SUM('[1]Summery Report'!F11) -> 5576 | C8: =SUM('[1]Summery Report'!C11) -> 0.753 | D8: =SUM('[1]Summery Report'!#REF!) -> #REF! | E8: =SUM('[1]Summery Report'!#REF!) -> #REF! | F8: 0.375
A9: =Gen!B18 -> 44143 | B9: =SUM('[1]Summery Report'!F12) -> 5532 | C9: =SUM('[1]Summery Report'!C12) -> 0.156 | D9: =SUM('[1]Summery Report'!#REF!) -> #REF! | E9: =SUM('[1]Summery Report'!#REF!) -> #REF! | F9: 0.325
A10: =Gen!B19 -> 44144 | B10: =SUM('[1]Summery Report'!F13) -> 6233 | C10: =SUM('[1]Summery Report'!C13) -> 0.442 | D10: =SUM('[1]Summery Report'!#REF!) -> #REF! | E10: =SUM('[1]Summery Report'!#REF!) -> #REF! | F10: 0.75
A11: =Gen!B20 -> 44145 | B11: =SUM('[1]Summery Report'!F14) -> 6063 | C11: =SUM('[1]Summery Report'!C14) -> 0.325 | D11: =SUM('[1]Summery Report'!#REF!) -> #REF! | E11: =SUM('[1]Summery Report'!#REF!) -> #REF! | F11: 0.7625
A12: =Gen!B21 -> 44146 | B12: =SUM('[1]Summery Report'!F15) -> 5967 | C12: =SUM('[1]Summery Report'!C15) -> 0.455 | D12: =SUM('[1]Summery Report'!#REF!) -> #REF! | E12: =SUM('[1]Summery Report'!#REF!) -> #REF! | F12: 0.1625
A13: =Gen!B22 -> 44147 | B13: =SUM('[1]Summery Report'!F16) -> 5863 | C13: =SUM('[1]Summery Report'!C16) -> 0.416 | D13: =SUM('[1]Summery Report'!#REF!) -> #REF! | E13: =SUM('[1]Summery Report'!#REF!) -> #REF! | F13: 0.1125
... A32: =Gen!B41 -> 44166 | B32: =SUM('[1]Summery Report'!F35) -> 0 | C32: =SUM('[1]Summery Report'!C35) -> 0 | D32: =SUM('[1]Summery Report'!#REF!) -> #REF! | E32: =SUM('[1]Summery Report'!#REF!) -> #REF! | F32: 0.175
A33: =Gen!B42 -> 0 | B33: =[1]Gen!S41 -> 0

Sheet Lpg (2)
C3: Four Sasons Safari Lodge Serengeti
G6: VALUE | H6: Cost
A7: DATE | B7: A | C7: B | D7: C | F7: Meter Reading | G7: Total | H7: Occu | I7: No.of | J7: Kg
B8: 2Ton% | C8: 1Ton (%) | D8: 1Ton% | F8: consumption | G8: Consumption Kg | H8: % | I8: pax | J8: per pax
F9: 72984.95
A10: =Gen!B11 -> 44136 | B10: 30 | C10: 85 | D10: 85 | F10: 72984.95 | G10: =(F10-F9)*4.4 -> 0 | H10: =Gen!C11 -> 0.026 | I10: =SUM(F10/H10) -> 2807113.5 | J10: =SUM(G10/I10) -> 0
A11: =Gen!B12 -> 44137 | B11: 25 | C11: 85 | D11: 85 | E11: 85 | F11: 72998 | G11: =(F11-F10)*4.4 -> 57.42 | H11: =Gen!C12 -> 0.0519 | I11: =SUM(F11/H11) -> 1406512.5 | J11: =SUM(G11/I11) -> 4.0824379e-05
A12: =Gen!B13 -> 44138 | B12: 22 | C12: 85 | D12: 85 | F12: 73009.4 | G12: =(F12-F11)*4.4 -> 50.16 | H12: =Gen!C13 -> 0.0779 | I12: =SUM(F12/H12) -> 937219.51 | J12: =SUM(G12/I12) -> 5.3520012e-05
A13: =Gen!B14 -> 44139 | B13: 20 | C13: 85 | D13: 85 | F13: 73022.54 | G13: =(F13-F12)*4.4 -> 57.816 | H13: =Gen!C14 -> 0.0649 | I13: =SUM(F13/H13) -> 1125154.7 | J13: =SUM(G13/I13) -> 5.1384934e-05
A14: =Gen!B15 -> 44140 | B14: 19 | C14: 85 | D14: 85 | F14: 73036.17 | G14: =(F14-F13)*4.4 -> 59.972 | H14: =Gen!C15 -> 0.026 | I14: =SUM(F14/H14) -> 2809083.5 | J14: =SUM(G14/I14) -> 2.1349312e-05
A15: =Gen!B16 -> 44141 | B15: 18 | C15: 85 | D15: 85 | F15: 73048.21 | G15: =(F15-F14)*4.4 -> 52.976 | H15: =Gen!C16 -> 0.0649 | I15: =SUM(F15/H15) -> 1125550.2 | J15: =SUM(G15/I15) -> 4.7066758e-05
A16: =Gen!B17 -> 44142 | B16: 85 | C16: 85 | D16: 85 | F16: 73065.41 | G16: =(F16-F15)*4.4 -> 75.68 | H16: =Gen!C17 -> 0.0519 | I16: =SUM(F16/H16) -> 1407811.4 | J16: =SUM(G16/I16) -> 5.3757202e-05
A17: =Gen!B18 -> 44143 | B17: 85 | C17: 83 | D17: 85 | F17: 73077.16 | G17: =(F17-F16)*4.4 -> 51.7 | H17: =Gen!C18 -> 0 | I17: =SUM(F17/H17) -> #DIV/0! | J17: =SUM(G17/I17) -> #DIV/0!
A18: =Gen!B19 -> 44144 | B18: 85 | C18: 82 | D18: 85 | F18: 73089.34 | G18: =(F18-F17)*4.4 -> 53.592 | H18: =Gen!C19 -> 0.013 | I18: =SUM(F18/H18) -> 5622256.9 | J18: =SUM(G18/I18) -> 9.5321151e-06
A19: =Gen!B20 -> 44145 | B19: 85 | C19: 80 | D19: 85 | F19: 73094.69 | G19: =(F19-F18)*4.4 -> 23.54 | H19: =Gen!C20 -> 0.039 | I19: =SUM(F19/H19) -> 1874222.8 | J19: =SUM(G19/I19) -> 1.2559873e-05
A20: =Gen!B21 -> 44146 | B20: 85 | C20: 72 | D20: 85 | F20: 73111.81 | G20: =(F20-F19)*4.4 -> 75.328 | H20: =Gen!C21 -> 0.0649 | I20: =SUM(F20/H20) -> 1126530.2 | J20: =SUM(G20/I20) -> 6.6867271e-05
A21: =Gen!B22 -> 44147 | B21: 85 | C21: 70 | D21: 85 | F21: 73124.12 | G21: =(F21-F20)*4.4 -> 54.164 | H21: =Gen!C22 -> 0.05 | I21: =SUM(F21/H21) -> 1462482.4 | J21: =SUM(G21/I21) -> 3.7035659e-05
A22: =Gen!B23 -> 44148 | B22: 85 | C22: 61 | D22: 85 | F22: 73139.69 | G22: =(F22-F21)*4.4 -> 68.508 | H22: =Gen!C23 -> 0.0519 | I22: =SUM(F22/H22) -> 1409242.6 | J22: =SUM(G22/I22) -> 4.8613348e-05
A23: =Gen!B24 -> 44149 | B23: 85 | C23: 57 | D23: 85 | F23: 73155.45 | G23: =(F23-F22)*4.4 -> 69.344 | H23: =Gen!C24 -> 0.1818 | I23: =SUM(F23/H23) -> 402395.21 | J23: =SUM(G23/I23) -> 0.00017232809
... A31: =Gen!B32 -> 44157 | B31: 85 | C31: 15 | D31: 85 | F31: 73309 | G31: =(F31-F30)*4.4 -> 86.548 | H31: =Gen!C32 -> 0.1 | I31: =SUM(F31/H31) -> 733090 | J31: =SUM(G31/I31) -> 0.00011805917
A32: =Gen!B33 -> 44158 | B32: 85 | C32: 11 | D32: 85 | E32: 85 | F32: 73323.94 | G32: =(F32-F31)*4.4 -> 65.736 | H32: =Gen!C33 -> 0.065 | I32: =SUM(F32/H32) -> 1128060.6 | J32: =SUM(G32/I32) -> 5.8273464e-05
A33: =Gen!B34 -> 44159 | B33: 85 | C33: 9 | D33: 85 | F33: 73338.51 | G33: =(F33-F32)*4.4 -> 64.108 | H33: =Gen!C34 -> 0.065 | I33: =SUM(F33/H33) -> 1128284.8 | J33: =SUM(G33/I33) -> 5.6818989e-05
A34: =Gen!B35 -> 44160 | B34: 85 | C34: 5 | D34: 85 | F34: 73356.77 | G34: =(F34-F33)*4.4 -> 80.344 | H34: =Gen!C35 -> 0.039 | I34: =SUM(F34/H34) -> 1880942.8 | J34: =SUM(G34/I34) -> 4.2714749e-05
A35: =Gen!B36 -> 44161 | B35: 85 | C35: 3 | D35: 85 | F35: 73374.66 | G35: =(F35-F34)*4.4 -> 78.716 | H35: =Gen!C36 -> 0.013 | I35: =SUM(F35/H35) -> 5644204.6 | J35: =SUM(G35/I35) -> 1.3946341e-05
A36: =Gen!B37 -> 44162 | B36: 85 | C36: 2 | D36: 85 | F36: 73384.29 | G36: =(F36-F35)*4.4 -> 42.372 | H36: =Gen!C37 -> 0.01 | I36: =SUM(F36/H36) -> 7338429 | J36: =SUM(G36/I36) -> 5.7739879e-06
A37: =Gen!B38 -> 44163 | B37: 85 | C37: 1 | D37: 85 | F37: 73399.68 | G37: =(F37-F36)*4.4 -> 67.716 | H37: =Gen!C38 -> 0.026 | I37: =SUM(F37/H37) -> 2823064.6 | J37: =SUM(G37/I37) -> 2.3986699e-05
A38: =Gen!B39 -> 44164 | B38: 85 | C38: 0 | D38: 85 | F38: 73406.27 | G38: =(F38-F37)*4.4 -> 28.996 | H38: =Gen!C39 -> 0.026 | I38: =SUM(F38/H38) -> 2823318.1 | J38: =SUM(G38/I38) -> 1.0270185e-05
A39: =Gen!B40 -> 44165 | B39: 85 | C39: 0 | D39: 84 | F39: 73421.69 | G39: =(F39-F38)*4.4 -> 67.848 | H39: =Gen!C40 -> 0.039 | I39: =SUM(F39/H39) -> 1882607.4 | J39: =SUM(G39/I39) -> 3.6039377e-05
A40: =Gen!B41 -> 44166 | G40: =(F40-F39)*4.4 -> -323055.44 | H40: =Gen!C41 -> 0 | I40: =SUM(F40/H40) -> #DIV/0! | J40: =SUM(G40/I40) -> #DIV/0!
A41: =Gen!B42 -> 0 | H41: =Gen!C42 -> 0 | I41: =SUM(F41/H41) -> #DIV/0!
C42: TOTAL USAGE | E42: =SUM(E10:E40) -> 170 | F42: =SUM(F10:F40) -> 2195895.7 | G42: =SUM(G10:G40) -> -321133.78
B45: TANK A | D45: TANK B | G45: TANK C

Sheet LPG_Graph
A1: Date | B1: Usage KG | C1: Occ %
A2: =Gen!B11 -> 44136 | B2: ='[1]Lpg (2)'!G10 -> 197.56 | C2: =SUM([1]Gen!B11) -> 0.623
A3: =Gen!B12 -> 44137 | B3: ='[1]Lpg (2)'!G11 -> 131.956 | C3: =SUM([1]Gen!B12) -> 0.779
A4: =Gen!B13 -> 44138 | B4: ='[1]Lpg (2)'!G12 -> 117.48 | C4: =SUM([1]Gen!B13) -> 0.532
A5: =Gen!B14 -> 44139 | B5: ='[1]Lpg (2)'!G13 -> 102.96 | C5: =SUM([1]Gen!B14) -> 0.61
A6: =Gen!B15 -> 44140 | B6: ='[1]Lpg (2)'!G14 -> 101.816 | C6: =SUM([1]Gen!B15) -> 0.688
A7: =Gen!B16 -> 44141 | B7: ='[1]Lpg (2)'!G15 -> 106.92 | C7: =SUM([1]Gen!B16) -> 0.532
A8: =Gen!B17 -> 44142 | B8: ='[1]Lpg (2)'!G16 -> 116.732 | C8: =SUM([1]Gen!B17) -> 0.753
A9: =Gen!B18 -> 44143 | B9: ='[1]Lpg (2)'!G17 -> 105.732 | C9: =SUM([1]Gen!B18) -> 0.156
A10: =Gen!B19 -> 44144 | B10: ='[1]Lpg (2)'!G18 -> 114.4 | C10: =SUM([1]Gen!B19) -> 0.442
A11: =Gen!B20 -> 44145 | B11: ='[1]Lpg (2)'!G19 -> 102.08 | C11: =SUM([1]Gen!B20) -> 0.325
A12: =Gen!B21 -> 44146 | B12: ='[1]Lpg (2)'!G20 -> 105.292 | C12: =SUM([1]Gen!B21) -> 0.455
A13: =Gen!B22 -> 44147 | B13: ='[1]Lpg (2)'!G21 -> 114.664 | C13: =SUM([1]Gen!B22) -> 0.416
... A32: =Gen!B41 -> 44166 | B32: ='[1]Lpg (2)'!G40 -> 0 | C32: =SUM([1]Gen!B41) -> #REF!

Sheet Water-Meter
A1: Four Seasons Safari Lodge Serengeti - Water Report
C2: Main Meter | F2: KITCHEN | I2: Amani café | L2: Main SW POOL | O2: Laundry | S2: BORE HOLE NO.1 METER READING | V2: BORE HOLE NO.2 METER READING | Y2: BORE HOLE NO.3 METER READING | AB2: BORE HOLE NO.4 METER READING | AE2: BORE HOLE NO.5 METER READING | AH2: BORE HOLE NO.6 METER READING | AK2: RAIN WATER - METER READING | AN2: TOTAL WATER PRODUCTION
A3: DATE | C3: Open Bal | D3: Final | E3: consumption | F3: Open Bal | G3: Final | H3: consumption | I3: Open Bal | J3: Final | K3: consumption | L3: Open Bal | M3: Final | N3: consumption | O3: Open Bal | P3: Final | Q3: consumption | R3: Total consumption
S4: OPEN | T4: FINAL | U4: PROD. | V4: OPEN | W4: FINAL | X4: PROD. | Y4: OPEN | Z4: FINAL | AA4: PROD. | AB4: OPEN | AC4: FINAL | AD4: M3 | AE4: OPEN | AF4: FINAL | AG4: M3 | AH4: OPEN | AI4: FINAL | AJ4: M3 | AK4: OPEN | AL4: FINAL | AM4: M3
C5: =D4 -> 0 | D5: 243230 | E5: =IF((D5-D4)<0,"0",(D5-D4)) -> 243230 | F5: =G4 -> 0 | G5: 38000 | H5: 0 | I5: =J4 -> 0 | J5: 8086 | K5: =J5-J4 -> 8086 | L5: =M4 -> 0 | M5: 12907 | N5: 0 | O5: =P4 -> 0 | P5: 20401 | Q5: =IF((P5-P4)<0,"0",(P5-P4)) -> 20401 | T5: 60573 | V5: =W4 -> FINAL | W5: 73031 | X5: 0 | Y5: =Z4 -> FINAL | Z5: 85188 | AA5: 0 | AB5: =AC4 -> FINAL | AC5: 16234 | AE5: =AF4 -> FINAL | AF5: 18300 | AG5: 0 | AH5: =AI4 -> FINAL | AI5: 26621 | AK5: =AL4 -> FINAL
A6: =Gen!B11 -> 44136 | C6: =D5 -> 243230 | D6: 243284 | E6: =IF((D6-D5)<0,"0",(D6-D5)) -> 54 | F6: =G5 -> 38000 | G6: 38000 | H6: =IF((G6-G5)<0,"0",(G6-G5)) -> 0 | I6: =J5 -> 8086 | J6: 8086 | K6: =J6-J5 -> 0 | L6: =M5 -> 12907 | M6: 12907 | N6: =IF((M6-M5)<0,"0",(M6-M5)) -> 0 | O6: =P5 -> 20401 | P6: 20406 | Q6: =IF((P6-P5)<0,"0",(P6-P5)) -> 5 | S6: =T5 -> 60573 | T6: 60573 | U6: =IF((T6-T5)<0,"0",(T6-T5)) -> 0 | V6: =W5 -> 73031 | W6: 73031 | X6: =IF((W6-W5)<0,"0",(W6-W5)) -> 0 | Y6: =Z5 -> 85188 | Z6: 85189 | AA6: =IF((Z6-Z5)<0,"0",(Z6-Z5)) -> 1 | AB6: =AC5 -> 16234 | AC6: 16253 | AD6: =IF((AC6-AC5)<0,"0",(AC6-AC5)) -> 19 | AE6: =AF5 -> 18300 | AF6: 18300 | AG6: =IF((AF6-AF5)<0,"0",(AF6-AF5)) -> 0 | AH6: =AI5 -> 26621 | AI6: 26643 | AJ6: =IF((AI6-AI5)<0,"0",(AI6-AI5)) -> 22 | AK6: =AL5 -> 0 | AM6: =IF((AL6-AL5)<0,"0",(AL6-AL5)) -> 0 | AN6: =U6+X6+AA6+AD6+AG6+AJ6+AM6 -> 42
A7: =Gen!B12 -> 44137 | C7: =D6 -> 243284 | D7: 243332 | E7: =IF((D7-D6)<0,"0",(D7-D6)) -> 48 | F7: =G6 -> 38000 | G7: 38000 | H7: =IF((G7-G6)<0,"0",(G7-G6)) -> 0 | I7: =J6 -> 8086 | J7: 8087 | K7: =J7-J6 -> 1 | L7: =M6 -> 12907 | M7: 12907 | N7: =IF((M7-M6)<0,"0",(M7-M6)) -> 0 | O7: =P6 -> 20406 | P7: 20409 | Q7: =IF((P7-P6)<0,"0",(P7-P6)) -> 3 | S7: =T6 -> 60573 | T7: 60634 | U7: =IF((T7-T6)<0,"0",(T7-T6)) -> 61 | V7: =W6 -> 73031 | W7: 73031 | X7: =IF((W7-W6)<0,"0",(W7-W6)) -> 0 | Y7: =Z6 -> 85189 | Z7: 85189 | AA7: =IF((Z7-Z6)<0,"0",(Z7-Z6)) -> 0 | AB7: =AC6 -> 16253 | AC7: 16272 | AD7: =IF((AC7-AC6)<0,"0",(AC7-AC6)) -> 19 | AE7: =AF6 -> 18300 | AF7: 18300 | AG7: =IF((AF7-AF6)<0,"0",(AF7-AF6)) -> 0 | AH7: =AI6 -> 26643 | AI7: 26666 | AJ7: =IF((AI7-AI6)<0,"0",(AI7-AI6)) -> 23 | AK7: =AL6 -> 0 | AM7: =IF((AL7-AL6)<0,"0",(AL7-AL6)) -> 0 | AN7: =U7+X7+AA7+AD7+AG7+AJ7+AM7 -> 103
A8: =Gen!B13 -> 44138 | C8: =D7 -> 243332 | D8: 243413 | E8: =IF((D8-D7)<0,"0",(D8-D7)) -> 81 | F8: =G7 -> 38000 | G8: 38000 | H8: =IF((G8-G7)<0,"0",(G8-G7)) -> 0 | I8: =J7 -> 8087 | J8: 8089 | K8: =J8-J7 -> 2 | L8: =M7 -> 12907 | M8: 12907 | N8: =IF((M8-M7)<0,"0",(M8-M7)) -> 0 | O8: =P7 -> 20409 | P8: 20420 | Q8: =IF((P8-P7)<0,"0",(P8-P7)) -> 11 | S8: =T7 -> 60634 | T8: 60719 | U8: =IF((T8-T7)<0,"0",(T8-T7)) -> 85 | V8: =W7 -> 73031 | W8: 73031 | X8: =IF((W8-W7)<0,"0",(W8-W7)) -> 0 | Y8: =Z7 -> 85189 | Z8: 85220 | AA8: =IF((Z8-Z7)<0,"0",(Z8-Z7)) -> 31 | AB8: =AC7 -> 16272 | AC8: 16290 | AD8: =IF((AC8-AC7)<0,"0",(AC8-AC7)) -> 18 | AE8: =AF7 -> 18300 | AF8: 18300 | AG8: =IF((AF8-AF7)<0,"0",(AF8-AF7)) -> 0 | AH8: =AI7 -> 26666 | AI8: 26687 | AJ8: =IF((AI8-AI7)<0,"0",(AI8-AI7)) -> 21 | AK8: =AL7 -> 0 | AM8: =IF((AL8-AL7)<0,"0",(AL8-AL7)) -> 0 | AN8: =U8+X8+AA8+AD8+AG8+AJ8+AM8 -> 155
A9: =Gen!B14 -> 44139 | C9: =D8 -> 243413 | D9: 243463 | E9: =IF((D9-D8)<0,"0",(D9-D8)) -> 50 | F9: =G8 -> 38000 | G9: 38000 | H9: =IF((G9-G8)<0,"0",(G9-G8)) -> 0 | I9: =J8 -> 8089 | J9: 8090 | K9: =J9-J8 -> 1 | L9: =M8 -> 12907 | M9: 12907 | N9: =IF((M9-M8)<0,"0",(M9-M8)) -> 0 | O9: =P8 -> 20420 | P9: 20429 | Q9: =IF((P9-P8)<0,"0",(P9-P8)) -> 9 | S9: =T8 -> 60719 | T9: 60800 | U9: =IF((T9-T8)<0,"0",(T9-T8)) -> 81 | V9: =W8 -> 73031 | W9: 73031 | X9: =IF((W9-W8)<0,"0",(W9-W8)) -> 0 | Y9: =Z8 -> 85220 | Z9: 85268 | AA9: =IF((Z9-Z8)<0,"0",(Z9-Z8)) -> 48 | AB9: =AC8 -> 16290 | AC9: 16308 | AD9: =IF((AC9-AC8)<0,"0",(AC9-AC8)) -> 18 | AE9: =AF8 -> 18300 | AF9: 18300 | AG9: =IF((AF9-AF8)<0,"0",(AF9-AF8)) -> 0 | AH9: =AI9 -> 26709 | AI9: 26709 | AJ9: =IF((AI9-AI8)<0,"0",(AI9-AI8)) -> 22 | AK9: =AL8 -> 0 | AM9: =IF((AL9-AL8)<0,"0",(AL9-AL8)) -> 0 | AN9: =U9+X9+AA9+AD9+AG9+AJ9+AM9 -> 169
A10: =Gen!B15 -> 44140 | C10: =D9 -> 243463 | D10: 243521 | E10: =IF((D10-D9)<0,"0",(D10-D9)) -> 58 | F10: =G9 -> 38000 | G10: 38000 | H10: =IF((G10-G9)<0,"0",(G10-G9)) -> 0 | I10: =J9 -> 8090 | J10: 8091 | K10: =IF((J10-J9)<0,"0",(J10-J9)) -> 1 | L10: =M9 -> 12907 | M10: 12907 | N10: =IF((M10-M9)<0,"0",(M10-M9)) -> 0 | O10: =P9 -> 20429 | P10: 20439 | Q10: =IF((P10-P9)<0,"0",(P10-P9)) -> 10 | S10: =T9 -> 60800 | T10: 60887 | U10: =IF((T10-T9)<0,"0",(T10-T9)) -> 87 | V10: =W9 -> 73031 | W10: 73031 | X10: =IF((W10-W9)<0,"0",(W10-W9)) -> 0 | Y10: =Z9 -> 85268 | Z10: 85268 | AA10: =IF((Z10-Z9)<0,"0",(Z10-Z9)) -> 0 | AB10: =AC9 -> 16308 | AC10: 16327 | AD10: =IF((AC10-AC9)<0,"0",(AC10-AC9)) -> 19 | AE10: =AF9 -> 18300 | AF10: 18300 | AG10: =IF((AF10-AF9)<0,"0",(AF10-AF9)) -> 0 | AH10: =AI9 -> 26709 | AI10: 26722 | AJ10: =IF((AI10-AI9)<0,"0",(AI10-AI9)) -> 13 | AK10: =AL9 -> 0 | AM10: =IF((AL10-AL9)<0,"0",(AL10-AL9)) -> 0 | AN10: =U10+X10+AA10+AD10+AG10+AJ10+AM10 -> 119
A11: =Gen!B16 -> 44141 | C11: =D10 -> 243521 | D11: 243583 | E11: =IF((D11-D10)<0,"0",(D11-D10)) -> 62 | F11: =G10 -> 38000 | G11: 38000 | H11: =IF((G11-G10)<0,"0",(G11-G10)) -> 0 | I11: =J10 -> 8091 | J11: 8091 | K11: =IF((J11-J10)<0,"0",(J11-J10)) -> 0 | L11: =M10 -> 12907 | M11: 12907 | N11: =IF((M11-M10)<0,"0",(M11-M10)) -> 0 | O11: =P10 -> 20439 | P11: 20449 | Q11: =IF((P11-P10)<0,"0",(P11-P10)) -> 10 | S11: =T10 -> 60887 | T11: 60902 | U11: =IF((T11-T10)<0,"0",(T11-T10)) -> 15 | V11: =W10 -> 73031 | W11: 73031 | X11: =IF((W11-W10)<0,"0",(W11-W10)) -> 0 | Y11: =Z10 -> 85268 | Z11: 85268 | AA11: =IF((Z11-Z10)<0,"0",(Z11-Z10)) -> 0 | AB11: =AC10 -> 16327 | AC11: 16346 | AD11: =IF((AC11-AC10)<0,"0",(AC11-AC10)) -> 19 | AE11: =AF11 -> 18300 | AF11: 18300 | AG11: =IF((AF11-AF10)<0,"0",(AF11-AF10)) -> 0 | AH11: =AI10 -> 26722 | AI11: 26722 | AJ11: =IF((AI11-AI10)<0,"0",(AI11-AI10)) -> 0 | AK11: =AL10 -> 0 | AM11: =IF((AL11-AL10)<0,"0",(AL11-AL10)) -> 0 | AN11: =U11+X11+AA11+AD11+AG11+AJ11+AM11 -> 34
A12: =Gen!B17 -> 44142 | C12: =D11 -> 243583 | D12: 243666 | E12: =IF((D12-D11)<0,"0",(D12-D11)) -> 83 | F12: =G11 -> 38000 | G12: 38000 | H12: =IF((G12-G11)<0,"0",(G12-G11)) -> 0 | I12: =J11 -> 8091 | J12: 8092 | K12: =IF((J12-J11)<0,"0",(J12-J11)) -> 1 | L12: =M11 -> 12907 | M12: 12907 | N12: =IF((M12-M11)<0,"0",(M12-M11)) -> 0 | O12: =P11 -> 20449 | P12: 20458 | Q12: =IF((P12-P11)<0,"0",(P12-P11)) -> 9 | S12: =T11 -> 60902 | T12: 60960 | U12: =IF((T12-T11)<0,"0",(T12-T11)) -> 58 | V12: =W11 -> 73031 | W12: 73031 | X12: =IF((W12-W11)<0,"0",(W12-W11)) -> 0 | Y12: =Z11 -> 85268 | Z12: 85290 | AA12: =IF((Z12-Z11)<0,"0",(Z12-Z11)) -> 22 | AB12: =AC11 -> 16346 | AC12: 16364 | AD12: =IF((AC12-AC11)<0,"0",(AC12-AC11)) -> 18 | AE12: =AF12 -> 18300 | AF12: 18300 | AG12: =IF((AF12-AF11)<0,"0",(AF12-AF11)) -> 0 | AH12: =AI11 -> 26722 | AI12: 26738 | AJ12: =IF((AI12-AI11)<0,"0",(AI12-AI11)) -> 16 | AK12: =AL11 -> 0 | AM12: =IF((AL12-AL11)<0,"0",(AL12-AL11)) -> 0 | AN12: =U12+X12+AA12+AD12+AG12+AJ12+AM12 -> 114
A13: =Gen!B18 -> 44143 | C13: =D12 -> 243666 | D13: 243729 | E13: =IF((D13-D12)<0,"0",(D13-D12)) -> 63 | F13: =G12 -> 38000 | G13: 38000 | H13: =IF((G13-G12)<0,"0",(G13-G12)) -> 0 | I13: =J12 -> 8092 | J13: 8092 | K13: =IF((J13-J12)<0,"0",(J13-J12)) -> 0 | L13: =M12 -> 12907 | M13: 12907 | N13: =IF((M13-M12)<0,"0",(M13-M12)) -> 0 | O13: =P12 -> 20458 | P13: 20471 | Q13: =IF((P13-P12)<0,"0",(P13-P12)) -> 13 | S13: =T12 -> 60960 | T13: 61048 | U13: =IF((T13-T12)<0,"0",(T13-T12)) -> 88 | V13: =W12 -> 73031 | W13: 73031 | X13: =IF((W13-W12)<0,"0",(W13-W12)) -> 0 | Y13: =Z12 -> 85290 | Z13: 85354 | AA13: =IF((Z13-Z12)<0,"0",(Z13-Z12)) -> 64 | AB13: =AC12 -> 16364 | AC13: 16383 | AD13: =IF((AC13-AC12)<0,"0",(AC13-AC12)) -> 19 | AE13: =AF13 -> 18300 | AF13: 18300 | AG13: =IF((AF13-AF12)<0,"0",(AF13-AF12)) -> 0 | AH13: =AI12 -> 26738 | AI13: 26764 | AJ13: =IF((AI13-AI12)<0,"0",(AI13-AI12)) -> 26 | AK13: =AL12 -> 0 | AM13: =IF((AL13-AL12)<0,"0",(AL13-AL12)) -> 0 | AN13: =U13+X13+AA13+AD13+AG13+AJ13+AM13 -> 197
A14: =Gen!B19 -> 44144 | C14: =D13 -> 243729 | D14: 243775 | E14: =IF((D14-D13)<0,"0",(D14-D13)) -> 46 | F14: =G13 -> 38000 | G14: 38000 | H14: =IF((G14-G13)<0,"0",(G14-G13)) -> 0 | I14: =J13 -> 8092 | J14: 8094 | K14: =IF((J14-J13)<0,"0",(J14-J13)) -> 2 | L14: =M13 -> 12907 | M14: 12907 | N14: =IF((M14-M13)<0,"0",(M14-M13)) -> 0 | O14: =P13 -> 20471 | P14: 20479 | Q14: =IF((P14-P13)<0,"0",(P14-P13)) -> 8 | S14: =T13 -> 61048 | T14: 61124 | U14: =IF((T14-T13)<0,"0",(T14-T13)) -> 76 | V14: =W13 -> 73031 | W14: 73031 | X14: =IF((W14-W13)<0,"0",(W14-W13)) -> 0 | Y14: =Z13 -> 85354 | Z14: 85401 | AA14: =IF((Z14-Z13)<0,"0",(Z14-Z13)) -> 47 | AB14: =AC13 -> 16383 | AC14: 16401 | AD14: =IF((AC14-AC13)<0,"0",(AC14-AC13)) -> 18 | AE14: =AF14 -> 18300 | AF14: 18300 | AG14: =IF((AF14-AF13)<0,"0",(AF14-AF13)) -> 0 | AH14: =AI13 -> 26764 | AI14: 26786 | AJ14: =IF((AI14-AI13)<0,"0",(AI14-AI13)) -> 22 | AK14: =AL13 -> 0 | AM14: =IF((AL14-AL13)<0,"0",(AL14-AL13)) -> 0 | AN14: =U14+X14+AA14+AD14+AG14+AJ14+AM14 -> 163
A15: =Gen!B20 -> 44145 | C15: =D14 -> 243775 | D15: 243828 | E15: =IF((D15-D14)<0,"0",(D15-D14)) -> 53 | F15: =G14 -> 38000 | G15: 38000 | H15: =IF((G15-G14)<0,"0",(G15-G14)) -> 0 | I15: =J14 -> 8094 | J15: 8095 | K15: =IF((J15-J14)<0,"0",(J15-J14)) -> 1 | L15: =M14 -> 12907 | M15: 12907 | N15: =IF((M15-M14)<0,"0",(M15-M14)) -> 0 | O15: =P14 -> 20479 | P15: 20490 | Q15: =IF((P15-P14)<0,"0",(P15-P14)) -> 11 | S15: =T14 -> 61124 | T15: 61210 | U15: =IF((T15-T14)<0,"0",(T15-T14)) -> 86 | V15: =W14 -> 73031 | W15: 73031 | X15: =IF((W15-W14)<0,"0",(W15-W14)) -> 0 | Y15: =Z14 -> 85401 | Z15: 85457 | AA15: =IF((Z15-Z14)<0,"0",(Z15-Z14)) -> 56 | AB15: =AC14 -> 16401 | AC15: 16418 | AD15: =IF((AC15-AC14)<0,"0",(AC15-AC14)) -> 17 | AE15: =AF15 -> 18300 | AF15: 18300 | AG15: =IF((AF15-AF14)<0,"0",(AF15-AF14)) -> 0 | AH15: =AI14 -> 26786 | AI15: 26809 | AJ15: =IF((AI15-AI14)<0,"0",(AI15-AI14)) -> 23 | AK15: =AL14 -> 0 | AM15: =IF((AL15-AL14)<0,"0",(AL15-AL14)) -> 0 | AN15: =U15+X15+AA15+AD15+AG15+AJ15+AM15 -> 182
A16: =Gen!B21 -> 44146 | C16: =D15 -> 243828 | D16: 243891 | E16: =IF((D16-D15)<0,"0",(D16-D15)) -> 63 | F16: =G15 -> 38000 | G16: 38000 | H16: =IF((G16-G15)<0,"0",(G16-G15)) -> 0 | I16: =J15 -> 8095 | J16: 8096 | K16: =IF((J16-J15)<0,"0",(J16-J15)) -> 1 | L16: =M15 -> 12907 | M16: 12907 | N16: =IF((M16-M15)<0,"0",(M16-M15)) -> 0 | O16: =P15 -> 20490 | P16: 20495 | Q16: =IF((P16-P15)<0,"0",(P16-P15)) -> 5 | S16: =T15 -> 61210 | T16: 61295 | U16: =IF((T16-T15)<0,"0",(T16-T15)) -> 85 | V16: =W15 -> 73031 | W16: 73031 | X16: =IF((W16-W15)<0,"0",(W16-W15)) -> 0 | Y16: =Z15 -> 85457 | Z16: 85512 | AA16: =IF((Z16-Z15)<0,"0",(Z16-Z15)) -> 55 | AB16: =AC15 -> 16418 | AC16: 16437 | AD16: =IF((AC16-AC15)<0,"0",(AC16-AC15)) -> 19 | AE16: =AF16 -> 18300 | AF16: 18300 | AG16: =IF((AF16-AF15)<0,"0",(AF16-AF15)) -> 0 | AH16: =AI15 -> 26809 | AI16: 26832 | AJ16: =IF((AI16-AI15)<0,"0",(AI16-AI15)) -> 23 | AK16: =AL15 -> 0 | AM16: =IF((AL16-AL15)<0,"0",(AL16-AL15)) -> 0 | AN16: =U16+X16+AA16+AD16+AG16+AJ16+AM16 -> 182
A17: =Gen!B22 -> 44147 | C17: =D16 -> 243891 | D17: 243939 | E17: =IF((D17-D16)<0,"0",(D17-D16)) -> 48 | F17: =G16 -> 38000 | G17: 38000 | H17: =IF((G17-G16)<0,"0",(G17-G16)) -> 0 | I17: =J16 -> 8096 | J17: 8097 | K17: =IF((J17-J16)<0,"0",(J17-J16)) -> 1 | L17: =M16 -> 12907 | M17: 12907 | N17: =IF((M17-M16)<0,"0",(M17-M16)) -> 0 | O17: =P16 -> 20495 | P17: 20498 | Q17: =IF((P17-P16)<0,"0",(P17-P16)) -> 3 | S17: =T16 -> 61295 | T17: 61297 | U17: =IF((T17-T16)<0,"0",(T17-T16)) -> 2 | V17: =W16 -> 73031 | W17: 73031 | X17: =IF((W17-W16)<0,"0",(W17-W16)) -> 0 | Y17: =Z16 -> 85512 | Z17: 85567 | AA17: =IF((Z17-Z16)<0,"0",(Z17-Z16)) -> 55 | AB17: =AC16 -> 16437 | AC17: 16455 | AD17: =IF((AC17-AC16)<0,"0",(AC17-AC16)) -> 18 | AE17: =AF17 -> 18300 | AF17: 18300 | AG17: =IF((AF17-AF16)<0,"0",(AF17-AF16)) -> 0 | AH17: =AI16 -> 26832 | AI17: 26855 | AJ17: =IF((AI17-AI16)<0,"0",(AI17-AI16)) -> 23 | AK17: =AL16 -> 0 | AM17: =IF((AL17-AL16)<0,"0",(AL17-AL16)) -> 0 | AN17: =U17+X17+AA17+AD17+AG17+AJ17+AM17 -> 98
A18: =Gen!B23 -> 44148 | C18: =D17 -> 243939 | D18: 244001 | E18: =IF((D18-D17)<0,"0",(D18-D17)) -> 62 | F18: =G17 -> 38000 | G18: 38000 | H18: =IF((G18-G17)<0,"0",(G18-G17)) -> 0 | J18: 8098 | K18: =IF((J18-J17)<0,"0",(J18-J17)) -> 1 | L18: =M17 -> 12907 | M18: 12907 | N18: =IF((M18-M17)<0,"0",(M18-M17)) -> 0 | O18: =P17 -> 20498 | P18: 20502 | Q18: =IF((P18-P17)<0,"0",(P18-P17)) -> 4 | S18: =T17 -> 61297 | T18: 61297 | U18: =IF((T18-T17)<0,"0",(T18-T17)) -> 0 | V18: =W17 -> 73031 | W18: 73031 | X18: =IF((W18-W17)<0,"0",(W18-W17)) -> 0 | Y18: =Z17 -> 85567 | Z18: 85624 | AA18: =IF((Z18-Z17)<0,"0",(Z18-Z17)) -> 57 | AB18: =AC17 -> 16455 | AC18: 16474 | AD18: =IF((AC18-AC17)<0,"0",(AC18-AC17)) -> 19 | AE18: =AF18 -> 18300 | AF18: 18300 | AG18: =IF((AF18-AF17)<0,"0",(AF18-AF17)) -> 0 | AH18: =AI17 -> 26855 | AI18: 26877 | AJ18: =IF((AI18-AI17)<0,"0",(AI18-AI17)) -> 22 | AK18: =AL17 -> 0 | AM18: =IF((AL18-AL17)<0,"0",(AL18-AL17)) -> 0 | AN18: =U18+X18+AA18+AD18+AG18+AJ18+AM18 -> 98
A19: =Gen!B24 -> 44149 | C19: =D18 -> 244001 | D19: 244053 | E19: =IF((D19-D18)<0,"0",(D19-D18)) -> 52 | F19: =G18 -> 38000 | G19: 38000 | H19: =IF((G19-G18)<0,"0",(G19-G18)) -> 0 | I19: =J18 -> 8098 | J19: 8099 | K19: =IF((J19-J18)<0,"0",(J19-J18)) -> 1 | L19: =M18 -> 12907 | M19: 12907 | N19: =IF((M19-M18)<0,"0",(M19-M18)) -> 0 | O19: =P18 -> 20502 | P19: 20507 | Q19: =IF((P19-P18)<0,"0",(P19-P18)) -> 5 | S19: =T18 -> 61297 | T19: 61297 | U19: =IF((T19-T18)<0,"0",(T19-T18)) -> 0 | V19: =W18 -> 73031 | W19: 73031 | X19: =IF((W19-W18)<0,"0",(W19-W18)) -> 0 | Y19: =Z18 -> 85624 | Z19: 85679 | AA19: =IF((Z19-Z18)<0,"0",(Z19-Z18)) -> 55 | AB19: =AC18 -> 16474 | AC19: 16493 | AD19: =IF((AC19-AC18)<0,"0",(AC19-AC18)) -> 19 | AE19: =AF19 -> 18300 | AF19: 18300 | AG19: =IF((AF19-AF18)<0,"0",(AF19-AF18)) -> 0 | AH19: =AI18 -> 26877 | AI19: 26899 | AJ19: =IF((AI19-AI18)<0,"0",(AI19-AI18)) -> 22 | AK19: =AL18 -> 0 | AM19: =IF((AL19-AL18)<0,"0",(AL19-AL18)) -> 0 | AN19: =U19+X19+AA19+AD19+AG19+AJ19+AM19 -> 96
A20: =Gen!B25 -> 44150 | C20: =D19 -> 244053 | D20: 244131 | E20: =IF((D20-D19)<0,"0",(D20-D19)) -> 78 | F20: =G19 -> 38000 | G20: 38000 | H20: =IF((G20-G19)<0,"0",(G20-G19)) -> 0 | I20: =J19 -> 8099 | J20: 8100 | K20: =IF((J20-J19)<0,"0",(J20-J19)) -> 1 | L20: =M19 -> 12907 | M20: 12907 | N20: =IF((M20-M19)<0,"0",(M20-M19)) -> 0 | O20: =P19 -> 20507 | P20: 20511 | Q20: =IF((P20-P19)<0,"0",(P20-P19)) -> 4 | S20: =T19 -> 61297 | T20: 61297 | U20: =IF((T20-T19)<0,"0",(T20-T19)) -> 0 | V20: =W19 -> 73031 | W20: 73031 | X20: =IF((W20-W19)<0,"0",(W20-W19)) -> 0 | Y20: =Z19 -> 85679 | Z20: 85734 | AA20: =IF((Z20-Z19)<0,"0",(Z20-Z19)) -> 55 | AB20: =AC19 -> 16493 | AC20: 16511 | AD20: =IF((AC20-AC19)<0,"0",(AC20-AC19)) -> 18 | AE20: =AF20 -> 18300 | AF20: 18300 | AG20: =IF((AF20-AF19)<0,"0",(AF20-AF19)) -> 0 | AH20: =AI19 -> 26899 | AI20: 26921 | AJ20: =IF((AI20-AI19)<0,"0",(AI20-AI19)) -> 22 | AK20: =AL19 -> 0 | AM20: =IF((AL20-AL19)<0,"0",(AL20-AL19)) -> 0 | AN20: =U20+X20+AA20+AD20+AG20+AJ20+AM20 -> 95
A21: =Gen!B26 -> 44151 | C21: =D20 -> 244131 | D21: 244183 | E21: =IF((D21-D20)<0,"0",(D21-D20)) -> 52 | F21: =G20 -> 38000 | G21: 38000 | H21: =IF((G21-G20)<0,"0",(G21-G20)) -> 0 | I21: =J20 -> 8100 | J21: 8101 | K21: =IF((J21-J20)<0,"0",(J21-J20)) -> 1 | L21: =M20 -> 12907 | M21: 12907 | N21: =IF((M21-M20)<0,"0",(M21-M20)) -> 0 | O21: =P20 -> 20511 | P21: 20512 | Q21: =IF((P21-P20)<0,"0",(P21-P20)) -> 1 | S21: =T20 -> 61297 | T21: 61297 | U21: =IF((T21-T20)<0,"0",(T21-T20)) -> 0 | V21: =W20 -> 73031 | W21: 73031 | X21: =IF((W21-W20)<0,"0",(W21-W20)) -> 0 | Y21: =Z20 -> 85734 | Z21: 85786 | AA21: =IF((Z21-Z20)<0,"0",(Z21-Z20)) -> 52 | AB21: =AC20 -> 16511 | AC21: 16530 | AD21: =IF((AC21-AC20)<0,"0",(AC21-AC20)) -> 19 | AE21: =AF20 -> 18300 | AF21: 18300 | AG21: =IF((AF21-AF20)<0,"0",(AF21-AF20)) -> 0 | AH21: =AI20 -> 26921 | AI21: 26945 | AJ21: =IF((AI21-AI20)<0,"0",(AI21-AI20)) -> 24 | AK21: =AL20 -> 0 | AM21: =IF((AL21-AL20)<0,"0",(AL21-AL20)) -> 0 | AN21: =U21+X21+AA21+AD21+AG21+AJ21+AM21 -> 95
A22: =Gen!B27 -> 44152 | C22: =D21 -> 244183 | D22: 244236 | E22: =IF((D22-D21)<0,"0",(D22-D21)) -> 53 | F22: =G21 -> 38000 | G22: 38000 | H22: =IF((G22-G21)<0,"0",(G22-G21)) -> 0 | I22: =J21 -> 8101 | J22: 8102 | K22: =IF((J22-J21)<0,"0",(J22-J21)) -> 1 | L22: =M21 -> 12907 | M22: 12907 | N22: =IF((M22-M21)<0,"0",(M22-M21)) -> 0 | O22: =P21 -> 20512 | P22: 20514 | Q22: =IF((P22-P21)<0,"0",(P22-P21)) -> 2 | S22: =T21 -> 61297 | T22: 61297 | U22: =IF((T22-T21)<0,"0",(T22-T21)) -> 0 | V22: =W21 -> 73031 | W22: 73031 | X22: =IF((W22-W21)<0,"0",(W22-W21)) -> 0 | Y22: =Z21 -> 85786 | Z22: 85797 | AA22: =IF((Z22-Z21)<0,"0",(Z22-Z21)) -> 11 | AB22: =AC21 -> 16530 | AC22: 16549 | AD22: =IF((AC22-AC21)<0,"0",(AC22-AC21)) -> 19 | AE22: =AF21 -> 18300 | AF22: 18300 | AG22: =IF((AF22-AF21)<0,"0",(AF22-AF21)) -> 0 | AH22: =AI21 -> 26945 | AI22: 26968 | AJ22: =IF((AI22-AI21)<0,"0",(AI22-AI21)) -> 23 | AK22: =AL21 -> 0 | AM22: =IF((AL22-AL21)<0,"0",(AL22-AL21)) -> 0 | AN22: =U22+X22+AA22+AD22+AG22+AJ22+AM22 -> 53
A23: =Gen!B28 -> 44153 | C23: =D22 -> 244236 | D23: 244287 | E23: =IF((D23-D22)<0,"0",(D23-D22)) -> 51 | F23: =G22 -> 38000 | G23: 38000 | H23: =IF((G23-G22)<0,"0",(G23-G22)) -> 0 | I23: =J22 -> 8102 | J23: 8103 | K23: =IF((J23-J22)<0,"0",(J23-J22)) -> 1 | L23: =M22 -> 12907 | M23: 12907 | N23: =IF((M23-M22)<0,"0",(M23-M22)) -> 0 | O23: =P22 -> 20514 | P23: 20517 | Q23: =IF((P23-P22)<0,"0",(P23-P22)) -> 3 | S23: =T22 -> 61297 | T23: 61297 | U23: =IF((T23-T22)<0,"0",(T23-T22)) -> 0 | V23: =W22 -> 73031 | W23: 73031 | X23: =IF((W24-W22)<0,"0",(W24-W22)) -> 0 | Y23: =Z22 -> 85797 | Z23: 85835 | AA23: =IF((Z23-Z22)<0,"0",(Z23-Z22)) -> 38 | AB23: =AC22 -> 16549 | AC23: 16566 | AD23: =IF((AC23-AC22)<0,"0",(AC23-AC22)) -> 17 | AE23: =AF22 -> 18300 | AF23: 18300 | AG23: =IF((AF23-AF22)<0,"0",(AF23-AF22)) -> 0 | AH23: =AI22 -> 26968 | AI23: 26992 | AJ23: =IF((AI23-AI22)<0,"0",(AI23-AI22)) -> 24 | AK23: =AL22 -> 0 | AM23: =IF((AL23-AL22)<0,"0",(AL23-AL22)) -> 0 | AN23: =U23+X23+AA23+AD23+AG23+AJ23+AM23 -> 79
A24: =Gen!B29 -> 44154 | C24: =D23 -> 244287 | D24: 244414 | E24: =IF((D24-D23)<0,"0",(D24-D23)) -> 127 | F24: =G23 -> 38000 | G24: 38000 | H24: =IF((G24-G23)<0,"0",(G24-G23)) -> 0 | I24: =J23 -> 8103 | J24: 8105 | K24: =IF((J24-J23)<0,"0",(J24-J23)) -> 2 | L24: =M23 -> 12907 | M24: 12907 | N24: =IF((M24-M23)<0,"0",(M24-M23)) -> 0 | O24: =P23 -> 20517 | P24: 20522 | Q24: =IF((P24-P23)<0,"0",(P24-P23)) -> 5 | S24: =T23 -> 61297 | T24: 61352 | U24: =IF((T24-T23)<0,"0",(T24-T23)) -> 55 | V24: =W24 -> 73031 | W24: 73031 | X24: =IF((W25-W23)<0,"0",(W25-W23)) -> 0 | Y24: =Z23 -> 85835 | Z24: 85900 | AA24: =IF((Z24-Z23)<0,"0",(Z24-Z23)) -> 65 | AB24: =AC23 -> 16566 | AC24: 16583 | AD24: =IF((AC24-AC23)<0,"0",(AC24-AC23)) -> 17 | AE24: =AF23 -> 18300 | AF24: 18300 | AG24: =IF((AF24-AF23)<0,"0",(AF24-AF23)) -> 0 | AH24: =AI23 -> 26992 | AI24: 27016 | AJ24: =IF((AI24-AI23)<0,"0",(AI24-AI23)) -> 24 | AK24: =AL23 -> 0 | AM24: =IF((AL24-AL23)<0,"0",(AL24-AL23)) -> 0 | AN24: =U24+X24+AA24+AD24+AG24+AJ24+AM24 -> 161
A25: =Gen!B30 -> 44155 | C25: =D24 -> 244414 | D25: 244460 | E25: =IF((D25-D24)<0,"0",(D25-D24)) -> 46 | F25: =G24 -> 38000 | G25: 38000 | H25: =IF((G26-G24)<0,"0",(G26-G24)) -> 0 | I25: =J24 -> 8105 | J25: 8106 | K25: =IF((J25-J24)<0,"0",(J25-J24)) -> 1 | L25: =M24 -> 12907 | M25: 12907 | N25: =IF((M25-M24)<0,"0",(M25-M24)) -> 0 | O25: =P24 -> 20522 | P25: 20523 | Q25: =IF((P25-P24)<0,"0",(P25-P24)) -> 1 | S25: =T24 -> 61352 | T25: 61438 | U25: =IF((T25-T24)<0,"0",(T25-T24)) -> 86 | V25: =#REF! -> #REF! | W25: 73031 | X25: =IF((W26-W24)<0,"0",(W26-W24)) -> 0 | Y25: =Z24 -> 85900 | Z25: 85949 | AA25: =IF((Z25-Z24)<0,"0",(Z25-Z24)) -> 49 | AB25: =AC24 -> 16583 | AC25: 16600 | AD25: =IF((AC25-AC24)<0,"0",(AC25-AC24)) -> 17 | AE25: =AF24 -> 18300 | AF25: 18300 | AG25: =IF((AF25-AF24)<0,"0",(AF25-AF24)) -> 0 | AH25: =AI24 -> 27016 | AI25: 27041 | AJ25: =IF((AI25-AI24)<0,"0",(AI25-AI24)) -> 25 | AK25: =AL24 -> 0 | AM25: =IF((AL25-AL24)<0,"0",(AL25-AL24)) -> 0 | AN25: =U25+X25+AA25+AD25+AG25+AJ25+AM25 -> 177
A26: =Gen!B31 -> 44156 | C26: =D25 -> 244460 | D26: 244507 | E26: =IF((D26-D25)<0,"0",(D26-D25)) -> 47 | F26: =G26 -> 38000 | G26: 38000 | H26: =IF((G27-G25)<0,"0",(G27-G25)) -> 0 | I26: =J25 -> 8106 | J26: 8107 | K26: =IF((J26-J25)<0,"0",(J26-J25)) -> 1 | L26: =M25 -> 12907 | M26: 12907 | N26: =IF((M26-M25)<0,"0",(M26-M25)) -> 0 | O26: =P25 -> 20523 | P26: 20527 | Q26: =IF((P26-P25)<0,"0",(P26-P25)) -> 4 | S26: =T25 -> 61438 | T26: 61515 | U26: =IF((T26-T25)<0,"0",(T26-T25)) -> 77 | V26: =W25 -> 73031 | W26: 73031 | X26: =IF((W27-W25)<0,"0",(W27-W25)) -> 0 | Y26: =Z25 -> 85949 | Z26: 85999 | AA26: =IF((Z26-Z25)<0,"0",(Z26-Z25)) -> 50 | AB26: =AC25 -> 16600 | AC26: 16618 | AD26: =IF((AC26-AC25)<0,"0",(AC26-AC25)) -> 18 | AE26: =AF25 -> 18300 | AF26: 18300 | AG26: =IF((AF26-AF25)<0,"0",(AF26-AF25)) -> 0 | AH26: =AI25 -> 27041 | AI26: 27065 | AJ26: =IF((AI26-AI25)<0,"0",(AI26-AI25)) -> 24 | AK26: =AL25 -> 0 | AM26: =IF((AL26-AL25)<0,"0",(AL26-AL25)) -> 0 | AN26: =U26+X26+AA26+AD26+AG26+AJ26+AM26 -> 169
A27: =Gen!B32 -> 44157 | C27: =D26 -> 244507 | D27: 244558 | E27: =IF((D27-D26)<0,"0",(D27-D26)) -> 51 | F27: =G27 -> 38000 | G27: 38000 | H27: =IF((G28-G26)<0,"0",(G28-G26)) -> 0 | I27: =J26 -> 8107 | J27: 8108 | K27: =IF((J27-J26)<0,"0",(J27-J26)) -> 1 | L27: =M26 -> 12907 | M27: 12907 | N27: =IF((M27-M26)<0,"0",(M27-M26)) -> 0 | O27: =P26 -> 20527 | P27: 20533 | Q27: =IF((P27-P26)<0,"0",(P27-P26)) -> 6 | S27: =T26 -> 61515 | T27: 61604 | U27: =IF((T27-T26)<0,"0",(T27-T26)) -> 89 | V27: =W26 -> 73031 | W27: 73031 | X27: =IF((W28-W26)<0,"0",(W28-W26)) -> 0 | Y27: =Z26 -> 85999 | Z27: 86067 | AA27: =IF((Z27-Z26)<0,"0",(Z27-Z26)) -> 68 | AB27: =AC26 -> 16618 | AC27: 16637 | AD27: =IF((AC27-AC26)<0,"0",(AC27-AC26)) -> 19 | AE27: =AF26 -> 18300 | AF27: 18300 | AG27: =IF((AF27-AF26)<0,"0",(AF27-AF26)) -> 0 | AH27: =AI26 -> 27065 | AI27: 27085 | AJ27: =IF((AI27-AI26)<0,"0",(AI27-AI26)) -> 20 | AK27: =AL26 -> 0 | AM27: =IF((AL27-AL26)<0,"0",(AL27-AL26)) -> 0 | AN27: =U27+X27+AA27+AD27+AG27+AJ27+AM27 -> 196
A28: =Gen!B33 -> 44158 | C28: =D27 -> 244558 | D28: 244619 | E28: =IF((D28-D27)<0,"0",(D28-D27)) -> 61 | F28: =G28 -> 38000 | G28: 38000 | H28: =IF((G28-G27)<0,"0",(G28-G27)) -> 0 | I28: =J27 -> 8108 | J28: 8109 | K28: =IF((J28-J27)<0,"0",(J28-J27)) -> 1 | L28: =M27 -> 12907 | M28: 12907 | N28: =IF((M28-M27)<0,"0",(M28-M27)) -> 0 | O28: =P27 -> 20533 | P28: 20537 | Q28: =IF((P28-P27)<0,"0",(P28-P27)) -> 4 | S28: =T27 -> 61604 | T28: 61628 | U28: =IF((T28-T27)<0,"0",(T28-T27)) -> 24 | V28: =W27 -> 73031 | W28: 73031 | X28: =IF((W29-W27)<0,"0",(W29-W27)) -> 0 | Y28: =Z27 -> 86067 | Z28: 86122 | AA28: =IF((Z28-Z27)<0,"0",(Z28-Z27)) -> 55 | AB28: =AC27 -> 16637 | AC28: 16655 | AD28: =IF((AC28-AC27)<0,"0",(AC28-AC27)) -> 18 | AE28: =AF27 -> 18300 | AF28: 18300 | AG28: =IF((AF28-AF27)<0,"0",(AF28-AF27)) -> 0 | AH28: =AI27 -> 27085 | AI28: 27108 | AJ28: =IF((AI28-AI27)<0,"0",(AI28-AI27)) -> 23 | AK28: =AL27 -> 0 | AM28: =IF((AL28-AL27)<0,"0",(AL28-AL27)) -> 0 | AN28: =U28+X28+AA28+AD28+AG28+AJ28+AM28 -> 120
A29: =Gen!B34 -> 44159 | C29: =D28 -> 244619 | D29: 244668 | E29: =IF((D29-D28)<0,"0",(D29-D28)) -> 49 | F29: =G29 -> 38000 | G29: 38000 | H29: =IF((G29-G28)<0,"0",(G29-G28)) -> 0 | I29: =J28 -> 8109 | J29: 8110 | K29: =IF((J29-J28)<0,"0",(J29-J28)) -> 1 | L29: =M28 -> 12907 | M29: 12907 | N29: =IF((M29-M28)<0,"0",(M29-M28)) -> 0 | O29: =P28 -> 20537 | P29: 20541 | Q29: =IF((P29-P28)<0,"0",(P29-P28)) -> 4 | S29: =T28 -> 61628 | T29: 61628 | U29: =IF((T29-T28)<0,"0",(T29-T28)) -> 0 | V29: =W28 -> 73031 | W29: 73031 | X29: =IF((W29-W28)<0,"0",(W29-W28)) -> 0 | Y29: =Z28 -> 86122 | Z29: 86177 | AA29: =IF((Z29-Z28)<0,"0",(Z29-Z28)) -> 55 | AB29: =AC28 -> 16655 | AC29: 16674 | AD29: =IF((AC29-AC28)<0,"0",(AC29-AC28)) -> 19 | AE29: =AF28 -> 18300 | AF29: 18300 | AG29: =IF((AF29-AF28)<0,"0",(AF29-AF28)) -> 0 | AH29: =AI28 -> 27108 | AI29: 27132 | AJ29: =IF((AI29-AI28)<0,"0",(AI29-AI28)) -> 24 | AK29: =AL28 -> 0 | AM29: =IF((AL29-AL28)<0,"0",(AL29-AL28)) -> 0 | AN29: =U29+X29+AA29+AD29+AG29+AJ29+AM29 -> 98
A30: =Gen!B35 -> 44160 | C30: =D29 -> 244668 | D30: 244718 | E30: =IF((D30-D29)<0,"0",(D30-D29)) -> 50 | F30: =G30 -> 38000 | G30: 38000 | H30: =IF((G30-G29)<0,"0",(G30-G29)) -> 0 | I30: =J29 -> 8110 | J30: 8111 | K30: =IF((J30-J29)<0,"0",(J30-J29)) -> 1 | L30: =M29 -> 12907 | M30: 12907 | N30: =IF((M30-M29)<0,"0",(M30-M29)) -> 0 | O30: =P29 -> 20541 | P30: 20544 | Q30: =IF((P30-P29)<0,"0",(P30-P29)) -> 3 | S30: =T29 -> 61628 | T30: 61697 | U30: =IF((T30-T29)<0,"0",(T30-T29)) -> 69 | V30: =W29 -> 73031 | W30: 73031 | X30: =IF((W30-W29)<0,"0",(W30-W29)) -> 0 | Y30: =Z29 -> 86177 | Z30: 86233 | AA30: =IF((Z30-Z29)<0,"0",(Z30-Z29)) -> 56 | AB30: =AC29 -> 16674 | AC30: 16691 | AD30: =IF((AC30-AC29)<0,"0",(AC30-AC29)) -> 17 | AE30: =AF29 -> 18300 | AF30: 18300 | AG30: =IF((AF30-AF29)<0,"0",(AF30-AF29)) -> 0 | AH30: =AI29 -> 27132 | AI30: 27154 | AJ30: =IF((AI30-AI29)<0,"0",(AI30-AI29)) -> 22 | AK30: =AL29 -> 0 | AM30: =IF((AL30-AL29)<0,"0",(AL30-AL29)) -> 0 | AN30: =U30+X30+AA30+AD30+AG30+AJ30+AM30 -> 164
A31: =Gen!B36 -> 44161 | C31: =D30 -> 244718 | D31: 244774 | E31: =IF((D31-D30)<0,"0",(D31-D30)) -> 56 | F31: =G31 -> 38000 | G31: 38000 | H31: =IF((G31-G30)<0,"0",(G31-G30)) -> 0 | I31: =J30 -> 8111 | J31: 8112 | K31: =IF((J31-J30)<0,"0",(J31-J30)) -> 1 | L31: =M30 -> 12907 | M31: 12907 | N31: =IF((M31-M30)<0,"0",(M31-M30)) -> 0 | O31: =P30 -> 20544 | P31: 20546 | Q31: =IF((P31-P30)<0,"0",(P31-P30)) -> 2 | S31: =T30 -> 61697 | T31: 61780 | U31: =IF((T31-T30)<0,"0",(T31-T30)) -> 83 | V31: =W30 -> 73031 | W31: 73031 | X31: =IF((W31-W30)<0,"0",(W31-W30)) -> 0 | Y31: =Z30 -> 86233 | Z31: 86288 | AA31: =IF((Z31-Z30)<0,"0",(Z31-Z30)) -> 55 | AB31: =AC30 -> 16691 | AC31: 16709 | AD31: =IF((AC31-AC30)<0,"0",(AC31-AC30)) -> 18 | AE31: =AF30 -> 18300 | AF31: 18300 | AG31: =IF((AF31-AF30)<0,"0",(AF31-AF30)) -> 0 | AH31: =AI30 -> 27154 | AI31: 27177 | AJ31: =IF((AI31-AI30)<0,"0",(AI31-AI30)) -> 23 | AK31: =AL30 -> 0 | AM31: =IF((AL31-AL30)<0,"0",(AL31-AL30)) -> 0 | AN31: =U31+X31+AA31+AD31+AG31+AJ31+AM31 -> 179
A32: =Gen!B37 -> 44162 | B32: 10/27//2009 | C32: =D31 -> 244774 | D32: 244821 | E32: =IF((D32-D31)<0,"0",(D32-D31)) -> 47 | F32: =G31 -> 38000 | G32: 38000 | H32: =IF((G32-G31)<0,"0",(G32-G31)) -> 0 | I32: =J31 -> 8112 | J32: 8113 | K32: =IF((J32-J31)<0,"0",(J32-J31)) -> 1 | L32: =M31 -> 12907 | M32: 12907 | N32: =IF((M32-M31)<0,"0",(M32-M31)) -> 0 | O32: =P31 -> 20546 | P32: 20549 | Q32: =IF((P32-P31)<0,"0",(P32-P31)) -> 3 | S32: =T31 -> 61780 | T32: 61863 | U32: =IF((T32-T31)<0,"0",(T32-T31)) -> 83 | V32: =W31 -> 73031 | W32: 73031 | X32: =IF((W32-W31)<0,"0",(W32-W31)) -> 0 | Y32: =Z31 -> 86288 | Z32: 86342 | AA32: =IF((Z32-Z31)<0,"0",(Z32-Z31)) -> 54 | AB32: =AC31 -> 16709 | AC32: 16727 | AD32: =IF((AC32-AC31)<0,"0",(AC32-AC31)) -> 18 | AE32: =AF31 -> 18300 | AF32: 18300 | AG32: =IF((AF32-AF31)<0,"0",(AF32-AF31)) -> 0 | AH32: =AI31 -> 27177 | AI32: 27201 | AJ32: =IF((AI32-AI31)<0,"0",(AI32-AI31)) -> 24 | AK32: =AL31 -> 0 | AM32: =IF((AL32-AL31)<0,"0",(AL32-AL31)) -> 0 | AN32: =U32+X32+AA32+AD32+AG32+AJ32+AM32 -> 179
A33: =Gen!B38 -> 44163 | C33: =D32 -> 244821 | D33: 244866 | E33: =IF((D33-D32)<0,"0",(D33-D32)) -> 45 | F33: =G32 -> 38000 | G33: 38000 | H33: =IF((G33-G32)<0,"0",(G33-G32)) -> 0 | I33: =J32 -> 8113 | J33: 8114 | K33: =IF((J33-J32)<0,"0",(J33-J32)) -> 1 | L33: =M32 -> 12907 | M33: 12907 | N33: =IF((M33-M32)<0,"0",(M33-M32)) -> 0 | O33: =P32 -> 20549 | P33: 20552 | Q33: =IF((P33-P32)<0,"0",(P33-P32)) -> 3 | S33: =T32 -> 61863 | T33: 61904 | U33: =IF((T33-T32)<0,"0",(T33-T32)) -> 41 | V33: =W32 -> 73031 | W33: 73031 | X33: =IF((W33-W32)<0,"0",(W33-W32)) -> 0 | Y33: =Z32 -> 86342 | Z33: 86396 | AA33: =IF((Z33-Z32)<0,"0",(Z33-Z32)) -> 54 | AB33: =AC32 -> 16727 | AC33: 16744 | AD33: =IF((AC33-AC32)<0,"0",(AC33-AC32)) -> 17 | AE33: =AF32 -> 18300 | AF33: 18300 | AG33: =IF((AF33-AF32)<0,"0",(AF33-AF32)) -> 0 | AH33: =AI32 -> 27201 | AI33: 27224 | AJ33: =IF((AI33-AI32)<0,"0",(AI33-AI32)) -> 23 | AK33: =AL32 -> 0 | AM33: =IF((AL33-AL32)<0,"0",(AL33-AL32)) -> 0 | AN33: =U33+X33+AA33+AD33+AG33+AJ33+AM33 -> 135
A34: =Gen!B39 -> 44164 | C34: =D33 -> 244866 | D34: 244928 | E34: =IF((D34-D33)<0,"0",(D34-D33)) -> 62 | F34: =G33 -> 38000 | G34: 38000 | H34: =IF((G34-G33)<0,"0",(G34-G33)) -> 0 | I34: =J33 -> 8114 | J34: 8115 | K34: =IF((J34-J33)<0,"0",(J34-J33)) -> 1 | L34: =M33 -> 12907 | M34: 12907 | N34: =IF((M34-M33)<0,"0",(M34-M33)) -> 0 | O34: =P33 -> 20552 | P34: 20556 | Q34: =IF((P34-P33)<0,"0",(P34-P33)) -> 4 | S34: =T33 -> 61904 | T34: 61904 | U34: =IF((T34-T33)<0,"0",(T34-T33)) -> 0 | V34: =W33 -> 73031 | W34: 73031 | X34: =IF((W34-W33)<0,"0",(W34-W33)) -> 0 | Y34: =Z33 -> 86396 | Z34: 86450 | AA34: =IF((Z34-Z33)<0,"0",(Z34-Z33)) -> 54 | AB34: =AC33 -> 16744 | AC34: 16764 | AD34: =IF((AC34-AC33)<0,"0",(AC34-AC33)) -> 20 | AE34: =AF33 -> 18300 | AF34: 18300 | AG34: =IF((AF34-AF33)<0,"0",(AF34-AF33)) -> 0 | AH34: =AI33 -> 27224 | AI34: 27246 | AJ34: =IF((AI34-AI33)<0,"0",(AI34-AI33)) -> 22 | AK34: =AL33 -> 0 | AM34: =IF((AL34-AL33)<0,"0",(AL34-AL33)) -> 0 | AN34: =U34+X34+AA34+AD34+AG34+AJ34+AM34 -> 96
A35: =Gen!B40 -> 44165 | C35: =D34 -> 244928 | D35: 244974 | E35: =IF((D35-D34)<0,"0",(D35-D34)) -> 46 | F35: =G34 -> 38000 | G35: 38000 | H35: =IF((G35-G34)<0,"0",(G35-G34)) -> 0 | I35: =J34 -> 8115 | J35: 8116 | K35: =IF((J35-J34)<0,"0",(J35-J34)) -> 1 | L35: =M34 -> 12907 | M35: 12907 | N35: =IF((M35-M34)<0,"0",(M35-M34)) -> 0 | O35: =P34 -> 20556 | P35: 20558 | Q35: =IF((P35-P34)<0,"0",(P35-P34)) -> 2 | S35: =T34 -> 61904 | T35: 61904 | U35: =IF((T35-T34)<0,"0",(T35-T34)) -> 0 | V35: =W34 -> 73031 | W35: 73031 | X35: =IF((W35-W34)<0,"0",(W35-W34)) -> 0 | Y35: =Z34 -> 86450 | Z35: 86505 | AA35: =IF((Z35-Z34)<0,"0",(Z35-Z34)) -> 55 | AB35: =AC34 -> 16764 | AC35: 16783 | AD35: =IF((AC35-AC34)<0,"0",(AC35-AC34)) -> 19 | AE35: =AF34 -> 18300 | AF35: 18300 | AG35: =IF((AF35-AF34)<0,"0",(AF35-AF34)) -> 0 | AH35: =AI34 -> 27246 | AI35: 27269 | AJ35: =IF((AI35-AI34)<0,"0",(AI35-AI34)) -> 23 | AK35: =AL34 -> 0 | AM35: =IF((AL35-AL34)<0,"0",(AL35-AL34)) -> 0 | AN35: =U35+X35+AA35+AD35+AG35+AJ35+AM35 -> 97
A36: =Gen!B41 -> 44166 | C36: =D35 -> 244974 | E36: =IF((D36-D35)<0,"0",(D36-D35)) -> 0 | F36: =G35 -> 38000 | H36: =IF((G36-G35)<0,"0",(G36-G35)) -> 0 | I36: =J35 -> 8116 | K36: =IF((J36-J35)<0,"0",(J36-J35)) -> 0 | L36: =M35 -> 12907 | N36: =IF((M36-M35)<0,"0",(M36-M35)) -> 0 | O36: =P35 -> 20558 | Q36: =IF((P36-P35)<0,"0",(P36-P35)) -> 0 | S36: =T35 -> 61904 | U36: =IF((T36-T35)<0,"0",(T36-T35)) -> 0 | V36: =W35 -> 73031 | X36: =IF((W36-W35)<0,"0",(W36-W35)) -> 0 | Y36: =Z35 -> 86505 | AA36: =IF((Z36-Z35)<0,"0",(Z36-Z35)) -> 0 | AB36: =AC35 -> 16783 | AD36: =IF((AC36-AC35)<0,"0",(AC36-AC35)) -> 0 | AE36: =AF35 -> 18300 | AG36: =IF((AF36-AF35)<0,"0",(AF36-AF35)) -> 0 | AH36: =AI35 -> 27269 | AJ36: =IF((AI36-AI35)<0,"0",(AI36-AI35)) -> 0 | AK36: =AL35 -> 0 | AM36: =IF((AL36-AL35)<0,"0",(AL36-AL35)) -> 0 | AN36: =U36+X36+AA36+AD36+AG36+AJ36+AM36 -> 0
A37: =Gen!B42 -> 0 | C37: =D36 -> 0 | E37: =IF((D37-D36)<0,"0",(D37-D36)) -> 0 | F37: =G36 -> 0 | H37: =IF((G37-G36)<0,"0",(G37-G36)) -> 0 | I37: =J36 -> 0 | K37: =IF((J37-J36)<0,"0",(J37-J36)) -> 0 | L37: =M36 -> 0 | N37: =IF((M37-M36)<0,"0",(M37-M36)) -> 0 | O37: =P36 -> 0 | Q37: =IF((P37-P36)<0,"0",(P37-P36)) -> 0 | S37: =T36 -> 0 | U37: =IF((T37-T36)<0,"0",(T37-T36)) -> 0 | V37: =W36 -> 0 | X37: =IF((W37-W36)<0,"0",(W37-W36)) -> 0 | Y37: =Z36 -> 0 | AA37: =IF((Z37-Z36)<0,"0",(Z37-Z36)) -> 0 | AB37: =AC36 -> 0 | AD37: =IF((AC37-AC36)<0,"0",(AC37-AC36)) -> 0 | AE37: =AF36 -> 0 | AG37: =IF((AF37-AF36)<0,"0",(AF37-AF36)) -> 0 | AH37: =AI36 -> 0 | AJ37: =IF((AI37-AI36)<0,"0",(AI37-AI36)) -> 0 | AK37: =AL36 -> 0 | AM37: =IF((AL37-AL36)<0,"0",(AL37-AL36)) -> 0 | AN37: =U38+X38+AA38+AD38+AG38+AJ38+AM38 -> 1331
C38: TOTAL USAGE | E38: =SUM(E6:E36) -> 1744 | F38: KL | H38: =SUM(H6:H37) -> 0 | K38: =SUM(K6:K37) -> 30 | N38: =M38-M37 -> 0 | Q38: =P38-O38 -> 0 | R38: =E38 -> 1744 | U38: =SUM(U6:U37) -> 1331 | AJ38: =IF((AI39-AI37)<0,"0",(AI39-AI37)) -> 0 | AN38: =U38+X38+AA38+AD38+AG38+AJ38+AM38 -> 1331
C42: WATER TANK LEVEL
C43: RAW WATER TANK NO.1 | E43: RAW WATER TANK NO.2 | G43: TREATED WATER TANK | I43: TREATED -HILL TANK | K43: TOTAL WATER AVAILABLE
C44: CAPACITY 217 m³ | E44: CAPACITY 92 m³ | G44: CAPACITY 146 m³ | I44: CAPACITY 213 m³
C45: cm | D45: m³ | E45: cm | F45: m³ | H45: m³ | J45: m³ | K45: m³
A46: =Gen!B11 -> 44136 | C46: 308 | D46: =C46*217/300 -> 222.78667 | E46: 285 | F46: =E46*92/305 -> 85.967213 | G46: 40 | H46: =G46*146/383 -> 15.248042 | I46: 290 | J46: =I46*213/308 -> 200.55195 | K46: =D46+F46+H46+J46 -> 524.55387
A47: =Gen!B12 -> 44137 | C47: 136 | D47: =C47*217/300 -> 98.373333 | E47: 100 | F47: =E47*92/305 -> 30.163934 | G47: 220 | H47: =G47*146/383 -> 83.86423 | I47: 295 | J47: =I47*213/308 -> 204.00974 | K47: =D47+F47+H47+J47 -> 416.41124
A48: =Gen!B13 -> 44138 | C48: 128 | D48: =C48*217/300 -> 92.586667 | E48: 96 | F48: =E48*92/305 -> 28.957377 | G48: 255 | H48: =G48*146/383 -> 97.206266 | I48: 292 | J48: =I48*213/308 -> 201.93506 | K48: =D48+F48+H48+J48 -> 420.68537
A49: =Gen!B14 -> 44139 | C49: 190 | D49: =C49*217/300 -> 137.43333 | E49: 155 | F49: =E49*92/305 -> 46.754098 | G49: 165 | H49: =G49*146/383 -> 62.898172 | I49: 288 | J49: =I49*213/308 -> 199.16883 | K49: =D49+F49+H49+J49 -> 446.25444
A50: =Gen!B15 -> 44140 | C50: 276 | D50: =C50*217/300 -> 199.64 | E50: 240 | F50: =E50*92/305 -> 72.393443 | G50: 160 | H50: =G50*146/383 -> 60.992167 | I50: 290 | J50: =I50*213/308 -> 200.55195 | K50: =D50+F50+H50+J50 -> 533.57756
A51: =Gen!B16 -> 44141 | C51: 300 | D51: =C51*217/300 -> 217 | E51: 285 | F51: =E51*92/305 -> 85.967213 | G51: 130 | H51: =G51*146/383 -> 49.556136 | I51: 290 | J51: =I51*213/308 -> 200.55195 | K51: =D51+F51+H51+J51 -> 553.0753
A52: =Gen!B17 -> 44142 | C52: 246 | D52: =C52*217/300 -> 177.94 | E52: 210 | F52: =E52*92/305 -> 63.344262 | G52: 75 | H52: =G52*146/383 -> 28.590078 | I52: 285 | J52: =I52*213/308 -> 197.09416 | K52: =D52+F52+H52+J52 -> 466.9685
A53: =Gen!B18 -> 44143 | C53: 180 | D53: =C53*217/300 -> 130.2 | E53: 145 | F53: =E53*92/305 -> 43.737705 | G53: 115 | H53: =G53*146/383 -> 43.83812 | I53: 292 | J53: =I53*213/308 -> 201.93506 | K53: =D53+F53+H53+J53 -> 419.71089
A54: =Gen!B19 -> 44144 | C54: 170 | D54: =C54*217/300 -> 122.96667 | E54: 134 | F54: =E54*92/305 -> 40.419672 | G54: 250 | H54: =G54*146/383 -> 95.300261 | I54: 289 | J54: =I54*213/308 -> 199.86039 | K54: =D54+F54+H54+J54 -> 458.54699
A55: =Gen!B20 -> 44145 | C55: 215 | D55: =C55*217/300 -> 155.51667 | E55: 175 | F55: =E55*92/305 -> 52.786885 | G55: 295 | H55: =G55*146/383 -> 112.45431 | I55: 280 | J55: =I55*213/308 -> 193.63636 | K55: =D55+F55+H55+J55 -> 514.39422
A56: =Gen!B21 -> 44146 | C56: 276 | D56: =C56*217/300 -> 199.64 | E56: 240 | F56: =E56*92/305 -> 72.393443 | G56: 280 | H56: =G56*146/383 -> 106.73629 | I56: 291 | J56: =I56*213/308 -> 201.24351 | K56: =D56+F56+H56+J56 -> 580.01324
A57: =Gen!B22 -> 44147 | C57: 300 | D57: =C57*217/300 -> 217 | E57: 290 | F57: =E57*92/305 -> 87.47541 | G57: 218 | H57: =G57*146/383 -> 83.101828 | I57: 290 | J57: =I57*213/308 -> 200.55195 | K57: =D57+F57+H57+J57 -> 588.12919
... A76: =Gen!B41 -> 44166 | C76: 261 | D76: =C76*217/300 -> 188.79 | E76: 225 | F76: =E76*92/305 -> 67.868852 | G76: 220 | H76: =G76*146/383 -> 83.86423 | I76: 290 | J76: =I76*213/308 -> 200.55195 | K76: =D76+F76+H76+J76 -> 541.07503
A77: =Gen!B42 -> 0 | D77: =C77*217/300 -> 0 | F77: =E77*92/305 -> 0 | H77: =G77*146/383 -> 0 | J77: =I77*213/308 -> 0 | K77: =D77+F77+H77+J77 -> 0
A78: =Gen!B43 -> BF

Sheet Water_Graph 
A1: Date | B1: Usage | C1: Occ %
A2: =Gen!B11 -> 44136 | B2: =SUM('[1]Water-Meter'!R10) -> #REF! | C2: =SUM([1]Gen!B11) -> 0.623
A3: =Gen!B12 -> 44137 | B3: =SUM('[1]Water-Meter'!R11) -> #REF! | C3: =SUM([1]Gen!B12) -> 0.779
A4: =Gen!B13 -> 44138 | B4: =SUM('[1]Water-Meter'!R12) -> #REF! | C4: =SUM([1]Gen!B13) -> 0.532
A5: =Gen!B14 -> 44139 | B5: =SUM('[1]Water-Meter'!R13) -> #REF! | C5: =SUM([1]Gen!B14) -> 0.61
A6: =Gen!B15 -> 44140 | B6: =SUM('[1]Water-Meter'!R14) -> #REF! | C6: =SUM([1]Gen!B15) -> 0.688
A7: =Gen!B16 -> 44141 | B7: =SUM('[1]Water-Meter'!R15) -> #REF! | C7: =SUM([1]Gen!B16) -> 0.532
A8: =Gen!B17 -> 44142 | B8: =SUM('[1]Water-Meter'!R16) -> #REF! | C8: =SUM([1]Gen!B17) -> 0.753
A9: =Gen!B18 -> 44143 | B9: =SUM('[1]Water-Meter'!R17) -> #REF! | C9: =SUM([1]Gen!B18) -> 0.156
A10: =Gen!B19 -> 44144 | B10: =SUM('[1]Water-Meter'!R18) -> #REF! | C10: =SUM([1]Gen!B19) -> 0.442
A11: =Gen!B20 -> 44145 | B11: =SUM('[1]Water-Meter'!R19) -> #REF! | C11: =SUM([1]Gen!B20) -> 0.325
A12: =Gen!B21 -> 44146 | B12: =SUM('[1]Water-Meter'!R20) -> #REF! | C12: =SUM([1]Gen!B21) -> 0.455
A13: =Gen!B22 -> 44147 | B13: =SUM('[1]Water-Meter'!R21) -> #REF! | C13: =SUM([1]Gen!B22) -> 0.416
... A32: =Gen!B41 -> 44166 | B32: =SUM('[1]Water-Meter'!R40) -> #REF! | C32: =SUM([1]Gen!B41) -> #REF!

Sheet Sheet1
A2: Generator and Diseal Summry Report | Q2: 2209.85 | R2: Diesel Cost | S2: Rate$ | T2: 1584
M3: % of Gas balance in Tank | P3: % of Dieasel balance in Tank | Q3: HLP Cost (TSH) | V3: Total Cost (TSH) | W3: Consumption Guest Occ% | AA3: Budget Cost Per Room occ
A4: Date | B4: Gen Set Hours Working | C4: Occ% | D4: Total OCC Room | E4: Guest Room Occ | F4: Total Kwh Generated | G4: Diseal consumed by Gen (Ltrs) | H4: Diseal consumed by Veichel (Ltrs) | I4: Total diseal consumed (Ltrs) | J4: Balance stock of Diseal (Ltrs) | K4: Water consumed | L4: Gas consumed (KG) | M4: 3 | N4: 2 | O4: 1 | Q4: Electricity | R4: Cost per Room Total OOC Usd | S4: Cost per Room Guest OOC Usd | T4: Water | U4: Gas
A5: =Gen!B11 -> 44136 | B5: 0 | C5: =Gen!C11 -> 0.026 | D5: =SUM(77*C5) -> 2.002 | F5: =Gen!V11 -> 0.39587992 | G5: =Gen!U11 -> 2415 | H5: =[1]Gen!#REF! -> #REF! | I5: =SUM(G5:H5) -> #REF! | J5: =[1]Gen!AT11 -> 47806.65 | K5: ='Water-Meter'!E6 -> 54 | L5: ='Lpg (2)'!G10 -> 0 | M5: =#REF! -> #REF! | N5: =#REF! -> #REF! | O5: =#REF! -> #REF! | P5: =J5/52000 -> 0.91935865 | Q5: =I5*Q2 -> #REF! | R5: =SUM(Q5/D5)/X5 -> #REF! | S5: =SUM(Q5/E5)/X5 -> #REF! | T5: =(K5*102)/X5 -> 3.4772727 | U5: =SUM(L5*1963)/X5 -> 0 | V5: =SUM(Q5+T5+U5) -> #REF! | W5: =SUM(V5/E5)/T2 -> #REF! | X5: =SUM(T2) -> 1584 | Y5: 106 | Z5: =SUM(Y5-S5) -> #REF! | AA5: 106
A6: =Gen!B12 -> 44137 | B6: 0 | C6: =Gen!C12 -> 0.0519 | D6: =SUM(77*C6) -> 3.9963 | F6: =Gen!V12 -> 0.42335499 | G6: =Gen!U12 -> 2617 | H6: =[1]Gen!#REF! -> #REF! | I6: =SUM(G6:H6) -> #REF! | J6: =[1]Gen!AT12 -> 45423.89 | K6: ='Water-Meter'!E7 -> 48 | L6: ='Lpg (2)'!G11 -> 57.42 | M6: =#REF! -> #REF! | N6: =#REF! -> #REF! | O6: =#REF! -> #REF! | P6: =J6/52000 -> 0.87353635 | Q6: =I6*Q2 -> #REF! | R6: =SUM(Q6/D6)/X6 -> #REF! | S6: =SUM(Q6/E6)/X6 -> #REF! | T6: =(K6*102)/X6 -> 3.0909091 | U6: =SUM(L6*1963)/X6 -> 71.15875 | V6: =SUM(Q6+T6+U6) -> #REF! | W6: =SUM(V6/E6)/T2 -> #REF! | X6: =SUM(X5) -> 1584 | Y6: 106 | Z6: =SUM(Y6-S6) -> #REF!
A7: =Gen!B13 -> 44138 | B7: 0 | C7: =Gen!C13 -> 0.0779 | D7: =SUM(77*C7) -> 5.9983 | F7: =Gen!V13 -> 0.44945602 | G7: =Gen!U13 -> 2592 | H7: =[1]Gen!#REF! -> #REF! | I7: =SUM(G7:H7) -> #REF! | J7: =[1]Gen!AT13 -> 42919.59 | K7: ='Water-Meter'!E8 -> 81 | L7: ='Lpg (2)'!G12 -> 50.16 | M7: =#REF! -> #REF! | N7: =#REF! -> #REF! | O7: =#REF! -> #REF! | P7: =J7/52000 -> 0.82537673 | Q7: =I7*Q2 -> #REF! | R7: =SUM(Q7/D7)/X7 -> #REF! | S7: =SUM(Q7/E7)/X7 -> #REF! | T7: =(K7*102)/X7 -> 5.2159091 | U7: =SUM(L7*1963)/X7 -> 62.161667 | V7: =SUM(Q7+T7+U7) -> #REF! | W7: =SUM(V7/E7)/T2 -> #REF! | X7: =SUM(X6) -> 1584 | Y7: 106 | Z7: =SUM(Y7-S7) -> #REF!
A8: =Gen!B14 -> 44139 | B8: 0 | C8: =Gen!C14 -> 0.0649 | D8: =SUM(77*C8) -> 4.9973 | F8: =Gen!V14 -> 0.39410546 | G8: =Gen!U14 -> 2655 | H8: =[1]Gen!AJ9 -> #REF! | I8: =SUM(G8:H8) -> #REF! | J8: =[1]Gen!AT14 -> 40258.94 | K8: ='Water-Meter'!E9 -> 50 | L8: ='Lpg (2)'!G13 -> 57.816 | M8: =#REF! -> #REF! | N8: =#REF! -> #REF! | O8: =#REF! -> #REF! | P8: =J8/52000 -> 0.77421038 | Q8: =I8*Q2 -> #REF! | R8: =SUM(Q8/D8)/X8 -> #REF! | S8: =SUM(Q8/E8)/X8 -> #REF! | T8: =(K8*102)/X8 -> 3.219697 | U8: =SUM(L8*1963)/X8 -> 71.6495 | V8: =SUM(Q8+T8+U8) -> #REF! | W8: =SUM(V8/E8)/T2 -> #REF! | X8: =SUM(X7) -> 1584 | Y8: 106 | Z8: =SUM(Y8-S8) -> #REF!
A9: =Gen!B15 -> 44140 | B9: 0 | C9: =Gen!C15 -> 0.026 | D9: =SUM(77*C9) -> 2.002 | F9: =Gen!V15 -> 0.4077842 | G9: =Gen!U15 -> 2595 | H9: =[1]Gen!AJ10 -> 0 | I9: =SUM(G9:H9) -> 2595 | J9: =[1]Gen!AT15 -> 37525.21 | K9: ='Water-Meter'!E10 -> 58 | L9: ='Lpg (2)'!G14 -> 59.972 | M9: =#REF! -> #REF! | N9: =#REF! -> #REF! | O9: =#REF! -> #REF! | P9: =J9/52000 -> 0.72163865 | Q9: =I9*Q2 -> 5734560.8 | R9: =SUM(Q9/D9)/X9 -> 1808.3434 | S9: =SUM(Q9/E9)/X9 -> #DIV/0! | T9: =(K9*102)/X9 -> 3.7348485 | U9: =SUM(L9*1963)/X9 -> 74.321361 | V9: =SUM(Q9+T9+U9) -> 5734638.8 | W9: =SUM(V9/E9)/T2 -> #DIV/0! | X9: =SUM(X8) -> 1584 | Y9: 106 | Z9: =SUM(Y9-S9) -> #DIV/0!
A10: =Gen!B16 -> 44141 | B10: 0 | C10: =Gen!C16 -> 0.0649 | D10: =SUM(77*C10) -> 4.9973 | F10: =Gen!V16 -> 0.4464682 | G10: =Gen!U16 -> 2217 | H10: =[1]Gen!#REF! -> #REF! | I10: =SUM(G10:H10) -> #REF! | J10: =[1]Gen!AT16 -> 35107.69 | K10: ='Water-Meter'!E11 -> 62 | L10: ='Lpg (2)'!G15 -> 52.976 | M10: =#REF! -> #REF! | N10: =#REF! -> #REF! | O10: =#REF! -> #REF! | P10: =J10/52000 -> 0.67514788 | Q10: =I10*Q2 -> #REF! | R10: =SUM(Q10/D10)/X10 -> #REF! | S10: =SUM(Q10/E10)/X10 -> #REF! | T10: =(K10*102)/X10 -> 3.9924242 | U10: =SUM(L10*1963)/X10 -> 65.651444 | V10: =SUM(Q10+T10+U10) -> #REF! | W10: =SUM(V10/E10)/T2 -> #REF! | X10: =SUM(X9) -> 1584 | Y10: 106 | Z10: =SUM(Y10-S10) -> #REF!
A11: =Gen!B17 -> 44142 | B11: 0 | C11: =Gen!C17 -> 0.0519 | D11: =SUM(77*C11) -> 3.9963 | F11: =Gen!V17 -> 0.38424768 | G11: =Gen!U17 -> 2479 | H11: =[1]Gen!AJ25 -> 80.56 | I11: =SUM(G11:H11) -> 2559.56 | J11: =[1]Gen!AT17 -> 47513.14 | K11: ='Water-Meter'!E12 -> 83 | L11: ='Lpg (2)'!G16 -> 75.68 | M11: =#REF! -> #REF! | N11: =#REF! -> #REF! | O11: =#REF! -> #REF! | P11: =J11/52000 -> 0.91371423 | Q11: =I11*Q2 -> 5656243.7 | R11: =SUM(Q11/D11)/X11 -> 893.54175 | S11: =SUM(Q11/E11)/X11 -> #DIV/0! | T11: =(K11*102)/X11 -> 5.344697 | U11: =SUM(L11*1963)/X11 -> 93.787778 | V11: =SUM(Q11+T11+U11) -> 5656342.8 | W11: =SUM(V11/E11)/T2 -> #DIV/0! | X11: =SUM(X10) -> 1584 | Y11: 106 | Z11: =SUM(Y11-S11) -> #DIV/0!
A12: =Gen!B18 -> 44143 | B12: 0 | C12: =Gen!C18 -> 0 | D12: =SUM(77*C12) -> 0 | F12: =Gen!V18 -> 0.43765912 | G12: =Gen!U18 -> 2341 | H12: =[1]Gen!#REF! -> #REF! | I12: =SUM(G12:H12) -> #REF! | J12: =[1]Gen!AT18 -> 45161.89 | K12: ='Water-Meter'!E13 -> 63 | L12: ='Lpg (2)'!G17 -> 51.7 | M12: =#REF! -> #REF! | N12: =#REF! -> #REF! | O12: =#REF! -> #REF! | P12: =J12/52000 -> 0.86849788 | Q12: =I12*Q2 -> #REF! | R12: =SUM(Q12/D12)/X12 -> #REF! | S12: =SUM(Q12/E12)/X12 -> #REF! | T12: =(K12*102)/X12 -> 4.0568182 | U12: =SUM(L12*1963)/X12 -> 64.070139 | V12: =SUM(Q12+T12+U12) -> #REF! | W12: =SUM(V12/E12)/T2 -> #REF! | X12: =SUM(X11) -> 1584 | Y12: 106 | Z12: =SUM(Y12-S12) -> #REF!
A13: =Gen!B19 -> 44144 | B13: 0 | C13: =Gen!C19 -> 0.013 | D13: =SUM(77*C13) -> 1.001 | F13: =Gen!V19 -> 0.44400424 | G13: =Gen!U19 -> 2360 | H13: =[1]Gen!#REF! -> #REF! | I13: =SUM(G13:H13) -> #REF! | J13: =[1]Gen!AT19 -> 42825.48 | K13: ='Water-Meter'!E14 -> 46 | L13: ='Lpg (2)'!G18 -> 53.592 | M13: =#REF! -> #REF! | N13: =#REF! -> #REF! | O13: =#REF! -> #REF! | P13: =J13/52000 -> 0.82356692 | Q13: =I13*Q2 -> #REF! | R13: =SUM(Q13/D13)/X13 -> #REF! | S13: =SUM(Q13/E13)/X13 -> #REF! | T13: =(K13*102)/X13 -> 2.9621212 | U13: =SUM(L13*1963)/X13 -> 66.414833 | V13: =SUM(Q13+T13+U13) -> #REF! | W13: =SUM(V13/E13)/T2 -> #REF! | X13: =SUM(X12) -> 1584 | Y13: 106 | Z13: =SUM(Y13-S13) -> #REF!
A14: =Gen!B20 -> 44145 | B14: 0 | C14: =Gen!C20 -> 0.039 | D14: =SUM(77*C14) -> 3.003 | F14: =Gen!V20 -> 0.40174344 | G14: =Gen!U20 -> 2323 | H14: =[1]Gen!#REF! -> #REF! | I14: =SUM(G14:H14) -> #REF! | J14: =[1]Gen!AT20 -> 40110.38 | K14: ='Water-Meter'!E15 -> 53 | L14: ='Lpg (2)'!G19 -> 23.54 | M14: =#REF! -> #REF! | N14: =#REF! -> #REF! | O14: =#REF! -> #REF! | P14: =J14/52000 -> 0.77135346 | Q14: =I14*Q2 -> #REF! | R14: =SUM(Q14/D14)/X14 -> #REF! | S14: =SUM(Q14/E14)/X14 -> #REF! | T14: =(K14*102)/X14 -> 3.4128788 | U14: =SUM(L14*1963)/X14 -> 29.172361 | V14: =SUM(Q14+T14+U14) -> #REF! | W14: =SUM(V14/E14)/T2 -> #REF! | X14: =SUM(X13) -> 1584 | Y14: 106 | Z14: =SUM(Y14-S14) -> #REF!
A15: =Gen!B21 -> 44146 | B15: 0 | C15: =Gen!C21 -> 0.0649 | D15: =SUM(77*C15) -> 4.9973 | F15: =Gen!V21 -> 0.41271572 | G15: =Gen!U21 -> 2283 | H15: =[1]Gen!#REF! -> #REF! | I15: =SUM(G15:H15) -> #REF! | J15: =[1]Gen!AT21 -> 37540.57 | K15: ='Water-Meter'!E16 -> 63 | L15: ='Lpg (2)'!G20 -> 75.328 | M15: =#REF! -> #REF! | N15: =#REF! -> #REF! | O15: =#REF! -> #REF! | P15: =J15/52000 -> 0.72193404 | Q15: =I15*Q2 -> #REF! | R15: =SUM(Q15/D15)/X15 -> #REF! | S15: =SUM(Q15/E15)/X15 -> #REF! | T15: =(K15*102)/X15 -> 4.0568182 | U15: =SUM(L15*1963)/X15 -> 93.351556 | V15: =SUM(Q15+T15+U15) -> #REF! | W15: =SUM(V15/E15)/T2 -> #REF! | X15: =SUM(X14) -> 1584 | Y15: 106 | Z15: =SUM(Y15-S15) -> #REF!
A16: =Gen!B22 -> 44147 | B16: 0 | C16: =Gen!C22 -> 0.05 | D16: =SUM(77*C16) -> 3.85 | F16: =Gen!V22 -> 0.465189 | G16: =Gen!U22 -> 2328 | H16: =[1]Gen!#REF! -> #REF! | I16: =SUM(G16:H16) -> #REF! | J16: =[1]Gen!AT22 -> 34967.29 | K16: ='Water-Meter'!E17 -> 48 | L16: ='Lpg (2)'!G21 -> 54.164 | M16: =#REF! -> #REF! | N16: =#REF! -> #REF! | O16: =#REF! -> #REF! | P16: =J16/52000 -> 0.67244788 | Q16: =I16*Q2 -> #REF! | R16: =SUM(Q16/D16)/X16 -> #REF! | S16: =SUM(Q16/E16)/X16 -> #REF! | T16: =(K16*102)/X16 -> 3.0909091 | U16: =SUM(L16*1963)/X16 -> 67.123694 | V16: =SUM(Q16+T16+U16) -> #REF! | W16: =SUM(V16/E16)/T2 -> #REF! | X16: =SUM(X15) -> 1584 | Y16: 106 | Z16: =SUM(Y16-S16) -> #REF!
A17: =Gen!B23 -> 44148 | B17: 0 | C17: =Gen!C23 -> 0.0519 | D17: =SUM(77*C17) -> 3.9963 | F17: =Gen!V23 -> 0.40613463 | G17: =Gen!U23 -> 2362 | H17: =[1]Gen!#REF! -> #REF! | I17: =SUM(G17:H17) -> #REF! | J17: =[1]Gen!AT23 -> 32228.76 | K17: ='Water-Meter'!E18 -> 62 | L17: ='Lpg (2)'!G22 -> 68.508 | M17: =#REF! -> #REF! | N17: =#REF! -> #REF! | O17: =#REF! -> #REF! | P17: =J17/52000 -> 0.61978385 | Q17: =I17*Q2 -> #REF! | R17: =SUM(Q17/D17)/X17 -> #REF! | S17: =SUM(Q17/E17)/X17 -> #REF! | T17: =(K17*102)/X17 -> 3.9924242 | U17: =SUM(L17*1963)/X17 -> 84.89975 | V17: =SUM(Q17+T17+U17) -> #REF! | W17: =SUM(V17/E17)/T2 -> #REF! | X17: =SUM(X16) -> 1584 | Y17: 106 | Z17: =SUM(Y17-S17) -> #REF!
A18: =Gen!B24 -> 44149 | B18: 0 | C18: =Gen!C24 -> 0.1818 | D18: =SUM(77*C18) -> 13.9986 | F18: =Gen!V24 -> 0.40457563 | G18: =Gen!U24 -> 2380 | H18: =[1]Gen!AJ27 -> 597.9 | I18: =SUM(G18:H18) -> 2977.9 | J18: =[1]Gen!AT24 -> 29915.45 | K18: ='Water-Meter'!E19 -> 52 | L18: ='Lpg (2)'!G23 -> 69.344 | M18: =#REF! -> #REF! | N18: =#REF! -> #REF! | O18: =#REF! -> #REF! | P18: =J18/52000 -> 0.57529712 | Q18: =I18*Q2 -> 6580712.3 | R18: =SUM(Q18/D18)/X18 -> 296.77897 | S18: =SUM(Q18/E18)/X18 -> #DIV/0! | T18: =(K18*102)/X18 -> 3.3484848 | U18: =SUM(L18*1963)/X18 -> 85.935778 | V18: =SUM(Q18+T18+U18) -> 6580801.6 | W18: =SUM(V18/E18)/T2 -> #DIV/0! | X18: =SUM(X17) -> 1584 | Y18: 106 | Z18: =SUM(Y18-S18) -> #DIV/0!
A19: =Gen!B25 -> 44150 | B19: 0 | C19: =Gen!C25 -> 0.1429 | D19: =SUM(77*C19) -> 11.0033 | F19: =Gen!V25 -> 0.45146341 | G19: =Gen!U25 -> 2337 | H19: =[1]Gen!AJ28 -> 227.73 | I19: =SUM(G19:H19) -> 2564.73 | J19: =[1]Gen!AT25 -> 42248.24 | K19: ='Water-Meter'!E20 -> 78 | L19: ='Lpg (2)'!G24 -> 95.392 | M19: =#REF! -> #REF! | N19: =#REF! -> #REF! | O19: =#REF! -> #REF! | P19: =J19/52000 -> 0.81246615 | Q19: =I19*Q2 -> 5667668.6 | R19: =SUM(Q19/D19)/X19 -> 325.18186 | S19: =SUM(Q19/E19)/X19 -> #DIV/0! | T19: =(K19*102)/X19 -> 5.0227273 | U19: =SUM(L19*1963)/X19 -> 118.21622 | V19: =SUM(Q19+T19+U19) -> 5667791.8 | W19: =SUM(V19/E19)/T2 -> #DIV/0! | X19: =SUM(X18) -> 1584 | Y19: 106 | Z19: =SUM(Y19-S19) -> #DIV/0!
A20: =Gen!B26 -> 44151 | B20: 0 | C20: =Gen!C26 -> 0.1299 | D20: =SUM(77*C20) -> 10.0023 | F20: =Gen!V26 -> 0.4577188 | G20: =Gen!U26 -> 2468 | H20: =[1]Gen!AJ29 -> 88.29 | I20: =SUM(G20:H20) -> 2556.29 | J20: =[1]Gen!AT26 -> 39497.37 | K20: ='Water-Meter'!E21 -> 52 | L20: ='Lpg (2)'!G25 -> 82.764 | M20: =#REF! -> #REF! | N20: =#REF! -> #REF! | O20: =#REF! -> #REF! | P20: =J20/52000 -> 0.75956481 | Q20: =I20*Q2 -> 5649017.5 | R20: =SUM(Q20/D20)/X20 -> 356.54788 | S20: =SUM(Q20/E20)/X20 -> #DIV/0! | T20: =(K20*102)/X20 -> 3.3484848 | U20: =SUM(L20*1963)/X20 -> 102.56675 | V20: =SUM(Q20+T20+U20) -> 5649123.4 | W20: =SUM(V20/E20)/T2 -> #DIV/0! | X20: =SUM(X19) -> 1584 | Y20: 106 | Z20: =SUM(Y20-S20) -> #DIV/0!
A21: =Gen!B27 -> 44152 | B21: 0 | C21: =Gen!C27 -> 0.03 | D21: =SUM(77*C21) -> 2.31 | F21: =Gen!V27 -> 0.4099647 | G21: =Gen!U27 -> 2266 | H21: =[1]Gen!AJ30 -> 783.92 | I21: =SUM(G21:H21) -> 3049.92 | J21: =[1]Gen!AT27 -> 36688.35 | K21: ='Water-Meter'!E22 -> 53 | L21: ='Lpg (2)'!G26 -> 77.572 | M21: =#REF! -> #REF! | N21: =#REF! -> #REF! | O21: =#REF! -> #REF! | P21: =J21/52000 -> 0.70554519 | Q21: =I21*Q2 -> 6739865.7 | R21: =SUM(Q21/D21)/X21 -> 1841.9765 | S21: =SUM(Q21/E21)/X21 -> #DIV/0! | T21: =(K21*102)/X21 -> 3.4128788 | U21: =SUM(L21*1963)/X21 -> 96.132472 | V21: =SUM(Q21+T21+U21) -> 6739965.3 | W21: =SUM(V21/E21)/T2 -> #DIV/0! | X21: =SUM(X20) -> 1584 | Y21: 106 | Z21: =SUM(Y21-S21) -> #DIV/0!
A22: =Gen!B28 -> 44153 | B22: 0 | C22: =Gen!C28 -> 0.104 | D22: =SUM(77*C22) -> 8.008 | F22: =Gen!V28 -> 0.41586322 | G22: =Gen!U28 -> 2398 | H22: =[1]Gen!#REF! -> #REF! | I22: =SUM(G22:H22) -> #REF! | J22: =[1]Gen!AT28 -> 33769.34 | K22: ='Water-Meter'!E23 -> 51 | L22: ='Lpg (2)'!G27 -> 75.284 | M22: =#REF! -> #REF! | N22: =#REF! -> #REF! | O22: =#REF! -> #REF! | P22: =J22/52000 -> 0.64941038 | Q22: =I22*Q2 -> #REF! | R22: =SUM(Q22/D22)/X22 -> #REF! | S22: =SUM(Q22/E22)/X22 -> #REF! | T22: =(K22*102)/X22 -> 3.2840909 | U22: =SUM(L22*1963)/X22 -> 93.297028 | V22: =SUM(Q22+T22+U22) -> #REF! | W22: =SUM(V22/E22)/T2 -> #REF! | X22: =SUM(X21) -> 1584 | Y22: 106 | Z22: =SUM(Y22-S22) -> #REF!
A23: =Gen!B29 -> 44154 | B23: 0 | C23: =Gen!C29 -> 0.052 | D23: =SUM(77*C23) -> 4.004 | F23: =Gen!V29 -> 0.40265559 | G23: =Gen!U29 -> 2587 | H23: =[1]Gen!#REF! -> #REF! | I23: =SUM(G23:H23) -> #REF! | J23: =[1]Gen!AT29 -> 31336.77 | K23: ='Water-Meter'!E24 -> 127 | L23: ='Lpg (2)'!G28 -> 73.524 | M23: =#REF! -> #REF! | N23: =#REF! -> #REF! | O23: =#REF! -> #REF! | P23: =J23/52000 -> 0.60263019 | Q23: =I23*Q2 -> #REF! | R23: =SUM(Q23/D23)/X23 -> #REF! | S23: =SUM(Q23/E23)/X23 -> #REF! | T23: =(K23*102)/X23 -> 8.1780303 | U23: =SUM(L23*1963)/X23 -> 91.115917 | V23: =SUM(Q23+T23+U23) -> #REF! | W23: =SUM(V23/E23)/T2 -> #REF! | X23: =SUM(X22) -> 1584 | Y23: 106 | Z23: =SUM(Y23-S23) -> #REF!
A24: =Gen!B30 -> 44155 | B24: 0 | C24: =Gen!C30 -> 0.052 | D24: =SUM(77*C24) -> 4.004 | F24: =Gen!V30 -> 0.38775463 | G24: =Gen!U30 -> 2592 | H24: =[1]Gen!#REF! -> #REF! | I24: =SUM(G24:H24) -> #REF! | J24: =[1]Gen!AT30 -> 29403.3 | K24: ='Water-Meter'!E25 -> 46 | L24: ='Lpg (2)'!G29 -> 99.176 | M24: =#REF! -> #REF! | N24: =#REF! -> #REF! | O24: =#REF! -> #REF! | P24: =J24/52000 -> 0.56544808 | Q24: =I24*Q2 -> #REF! | R24: =SUM(Q24/D24)/X24 -> #REF! | S24: =SUM(Q24/E24)/X24 -> #REF! | T24: =(K24*102)/X24 -> 2.9621212 | U24: =SUM(L24*1963)/X24 -> 122.90561 | V24: =SUM(Q24+T24+U24) -> #REF! | W24: =SUM(V24/E24)/T2 -> #REF! | X24: =SUM(X23) -> 1584 | Y24: 106 | Z24: =SUM(Y24-S24) -> #REF!
A25: =Gen!B31 -> 44156 | B25: 0 | C25: =Gen!C31 -> 0.065 | D25: =SUM(77*C25) -> 5.005 | F25: =Gen!V31 -> 0.4135578 | G25: =Gen!U31 -> 2673 | H25: =[1]Gen!AJ31 -> 172.05 | I25: =SUM(G25:H25) -> 2845.05 | J25: =[1]Gen!AT31 -> 41422.37 | K25: ='Water-Meter'!E26 -> 47 | L25: ='Lpg (2)'!G30 -> 85.36 | M25: =#REF! -> #REF! | N25: =#REF! -> #REF! | O25: =#REF! -> #REF! | P25: =J25/52000 -> 0.79658404 | Q25: =I25*Q2 -> 6287133.7 | R25: =SUM(Q25/D25)/X25 -> 793.03698 | S25: =SUM(Q25/E25)/X25 -> #DIV/0! | T25: =(K25*102)/X25 -> 3.0265152 | U25: =SUM(L25*1963)/X25 -> 105.78389 | V25: =SUM(Q25+T25+U25) -> 6287242.6 | W25: =SUM(V25/E25)/T2 -> #DIV/0! | X25: =SUM(X24) -> 1584 | Y25: 106 | Z25: =SUM(Y25-S25) -> #DIV/0!
A26: =Gen!B32 -> 44157 | B26: 0 | C26: =Gen!C32 -> 0.1 | D26: =SUM(77*C26) -> 7.7 | F26: =Gen!V32 -> 0.40388395 | G26: =Gen!U32 -> 2585 | H26: =[1]Gen!AJ32 -> 18.63 | I26: =SUM(G26:H26) -> 2603.63 | J26: =[1]Gen!AT32 -> 38988.16 | K26: ='Water-Meter'!E27 -> 51 | L26: ='Lpg (2)'!G31 -> 86.548 | M26: =#REF! -> #REF! | N26: =#REF! -> #REF! | O26: =#REF! -> #REF! | P26: =J26/52000 -> 0.74977231 | Q26: =I26*Q2 -> 5753631.8 | R26: =SUM(Q26/D26)/X26 -> 471.73289 | S26: =SUM(Q26/E26)/X26 -> #DIV/0! | T26: =(K26*102)/X26 -> 3.2840909 | U26: =SUM(L26*1963)/X26 -> 107.25614 | V26: =SUM(Q26+T26+U26) -> 5753742.3 | W26: =SUM(V26/E26)/T2 -> #DIV/0! | X26: =SUM(X25) -> 1584 | Y26: 106 | Z26: =SUM(Y26-S26) -> #DIV/0!
A27: =Gen!B33 -> 44158 | B27: 0 | C27: =Gen!C33 -> 0.065 | D27: =SUM(77*C27) -> 5.005 | F27: =Gen!V33 -> 0.41547739 | G27: =Gen!U33 -> 2587 | H27: =[1]Gen!AJ33 -> 311.34 | I27: =SUM(G27:H27) -> 2898.34 | J27: =[1]Gen!AT33 -> 36682.67 | K27: ='Water-Meter'!E28 -> 61 | L27: ='Lpg (2)'!G32 -> 65.736 | M27: =#REF! -> #REF! | N27: =#REF! -> #REF! | O27: =#REF! -> #REF! | P27: =J27/52000 -> 0.70543596 | Q27: =I27*Q2 -> 6404896.6 | R27: =SUM(Q27/D27)/X27 -> 807.89118 | S27: =SUM(Q27/E27)/X27 -> #DIV/0! | T27: =(K27*102)/X27 -> 3.9280303 | U27: =SUM(L27*1963)/X27 -> 81.4645 | V27: =SUM(Q27+T27+U27) -> 6404982 | W27: =SUM(V27/E27)/T2 -> #DIV/0! | X27: =SUM(X26) -> 1584 | Y27: 106 | Z27: =SUM(Y27-S27) -> #DIV/0!
A28: =Gen!B34 -> 44159 | B28: 0 | C28: =Gen!C34 -> 0.065 | D28: =SUM(77*C28) -> 5.005 | F28: =Gen!V34 -> 0.42898569 | G28: =Gen!U34 -> 2376 | H28: =[1]Gen!AJ34 -> 380.7 | I28: =SUM(G28:H28) -> 2756.7 | J28: =[1]Gen!AT34 -> 44223.03 | K28: ='Water-Meter'!E29 -> 49 | L28: ='Lpg (2)'!G33 -> 64.108 | M28: =#REF! -> #REF! | N28: =#REF! -> #REF! | O28: =#REF! -> #REF! | P28: =J28/52000 -> 0.85044288 | Q28: =I28*Q2 -> 6091893.5 | R28: =SUM(Q28/D28)/X28 -> 768.41006 | S28: =SUM(Q28/E28)/X28 -> #DIV/0! | T28: =(K28*102)/X28 -> 3.155303 | U28: =SUM(L28*1963)/X28 -> 79.446972 | V28: =SUM(Q28+T28+U28) -> 6091976.1 | W28: =SUM(V28/E28)/T2 -> #DIV/0! | X28: =SUM(X27) -> 1584 | Y28: 106 | Z28: =SUM(Y28-S28) -> #DIV/0!
A29: =Gen!B35 -> 44160 | B29: 0 | C29: =Gen!C35 -> 0.039 | D29: =SUM(77*C29) -> 3.003 | F29: =Gen!V35 -> 0.43357839 | G29: =Gen!U35 -> 2258 | H29: =[1]Gen!AJ35 -> 273.37 | I29: =SUM(G29:H29) -> 2531.37 | J29: =[1]Gen!AT35 -> 41629.06 | K29: ='Water-Meter'!E30 -> 50 | L29: ='Lpg (2)'!G34 -> 80.344 | M29: =#REF! -> #REF! | N29: =#REF! -> #REF! | O29: =#REF! -> #REF! | P29: =J29/52000 -> 0.80055885 | Q29: =I29*Q2 -> 5593948 | R29: =SUM(Q29/D29)/X29 -> 1176.0016 | S29: =SUM(Q29/E29)/X29 -> #DIV/0! | T29: =(K29*102)/X29 -> 3.219697 | U29: =SUM(L29*1963)/X29 -> 99.567722 | V29: =SUM(Q29+T29+U29) -> 5594050.8 | W29: =SUM(V29/E29)/T2 -> #DIV/0! | X29: =SUM(X28) -> 1584 | Y29: 106 | Z29: =SUM(Y29-S29) -> #DIV/0!
A30: =Gen!B36 -> 44161 | B30: 0 | C30: =Gen!C36 -> 0.013 | D30: =SUM(77*C30) -> 1.001 | F30: =Gen!V36 -> 0.41160089 | G30: =Gen!U36 -> 2255 | H30: =[1]Gen!AJ36 -> 396.56 | I30: =SUM(G30:H30) -> 2651.56 | J30: =[1]Gen!AT36 -> 39251.17 | K30: ='Water-Meter'!E31 -> 56 | L30: ='Lpg (2)'!G35 -> 78.716 | M30: =#REF! -> #REF! | N30: =#REF! -> #REF! | O30: =#REF! -> #REF! | P30: =J30/52000 -> 0.75483019 | Q30: =I30*Q2 -> 5859549.9 | R30: =SUM(Q30/D30)/X30 -> 3695.5153 | S30: =SUM(Q30/E30)/X30 -> #DIV/0! | T30: =(K30*102)/X30 -> 3.6060606 | U30: =SUM(L30*1963)/X30 -> 97.550194 | V30: =SUM(Q30+T30+U30) -> 5859651 | W30: =SUM(V30/E30)/T2 -> #DIV/0! | X30: =SUM(X29) -> 1584 | Y30: 106 | Z30: =SUM(Y30-S30) -> #DIV/0!
A31: =Gen!B37 -> 44162 | B31: 0 | C31: =Gen!C37 -> 0.01 | D31: =SUM(77*C31) -> 0.77 | F31: =Gen!V37 -> 0.42654697 | G31: =Gen!U37 -> 2395 | H31: =[1]Gen!AJ37 -> 280.63 | I31: =SUM(G31:H31) -> 2675.63 | J31: =[1]Gen!AT37 -> 36384.37 | K31: ='Water-Meter'!E32 -> 47 | L31: ='Lpg (2)'!G36 -> 42.372 | M31: =#REF! -> #REF! | N31: =#REF! -> #REF! | O31: =#REF! -> #REF! | P31: =J31/52000 -> 0.69969942 | Q31: =I31*Q2 -> 5912741 | R31: =SUM(Q31/D31)/X31 -> 4847.7805 | S31: =SUM(Q31/E31)/X31 -> #DIV/0! | T31: =(K31*102)/X31 -> 3.0265152 | U31: =SUM(L31*1963)/X31 -> 52.51025 | V31: =SUM(Q31+T31+U31) -> 5912796.5 | W31: =SUM(V31/E31)/T2 -> #DIV/0! | X31: =SUM(X30) -> 1584 | Y31: 106 | Z31: =SUM(Y31-S31) -> #DIV/0!
