Workbook

Sheet TOTAL
A1: Site Name | B1: Day | C1: Month | D1: Year | E1: Total Electricity Kwh | F1: Electricity Tariff ($/Kwh) | G1: Natural Gas (m3) | H1: Natural Gas $/m3 | I1: Water Utility Supply (m3) m3 | J1: Water Utility Supply (m3) $/m3 | K1: Room Nights | L1: Total Guests | M1: Utilities day cost dh
A2: Guangzhou | B2: 1 | C2: 11 | D2: 2020 | E2: =SUBMETERING!O5+SUBMETERING!M5 -> 38868 | F2: 0.675169 | G2: =SUBMETERING!E5+SUBMETERING!G5+SUBMETERING!I5+SUBMETERING!K5 -> 4710 | H2: 3.95 | I2: =SUBMETERING!S5 -> 175 | J2: 3.46 | K2: =(SUBMETERING!D5/100)*344 -> 197.0088 | L2: ='[1]Consommation mensuel énergie'!E10 -> 0 | M2: =E2*F2+G2*H2+#REF!*#REF!+I2*J2 -> #REF!
A3: Guangzhou | B3: =B2+1 -> 2 | C3: 11 | D3: 2020 | E3: =SUBMETERING!O6+SUBMETERING!M6 -> 37043 | F3: =F2 -> 0.675169 | G3: =SUBMETERING!E6+SUBMETERING!G6+SUBMETERING!I6+SUBMETERING!K6 -> 5550 | H3: =H2 -> 3.95 | I3: =SUBMETERING!S6 -> 160 | J3: =J2 -> 3.46 | K3: =(SUBMETERING!D6/100)*344 -> 243.0016 | L3: ='[1]Consommation mensuel énergie'!E11 -> 0 | M3: =E3*F3+G3*H3+#REF!*#REF!+I3*J3 -> #REF!
A4: Guangzhou | B4: =B3+1 -> 3 | C4: 11 | D4: 2020 | E4: =SUBMETERING!O7+SUBMETERING!M7 -> 36649 | F4: =F3 -> 0.675169 | G4: =SUBMETERING!E7+SUBMETERING!G7+SUBMETERING!I7+SUBMETERING!K7 -> 5988 | H4: =H3 -> 3.95 | I4: =SUBMETERING!S7 -> 198 | J4: =J3 -> 3.46 | K4: =(SUBMETERING!D7/100)*344 -> 267.0128 | L4: ='[1]Consommation mensuel énergie'!E12 -> 0 | M4: =E4*F4+G4*H4+#REF!*#REF!+I4*J4 -> #REF!
A5: Guangzhou | B5: =B4+1 -> 4 | C5: 11 | D5: 2020 | E5: =SUBMETERING!O8+SUBMETERING!M8 -> 33821 | F5: =F4 -> 0.675169 | G5: =SUBMETERING!E8+SUBMETERING!G8+SUBMETERING!I8+SUBMETERING!K8 -> 5886 | H5: =H4 -> 3.95 | I5: =SUBMETERING!S8 -> 199 | J5: =J4 -> 3.46 | K5: =(SUBMETERING!D8/100)*344 -> 248.9872 | L5: ='[1]Consommation mensuel énergie'!E13 -> 0 | M5: =E5*F5+G5*H5+#REF!*#REF!+I5*J5 -> #REF!
A6: Guangzhou | B6: =B5+1 -> 5 | C6: 11 | D6: 2020 | E6: =SUBMETERING!O9+SUBMETERING!M9 -> 36977 | F6: =F5 -> 0.675169 | G6: =SUBMETERING!E9+SUBMETERING!G9+SUBMETERING!I9+SUBMETERING!K9 -> 5584 | H6: =H5 -> 3.95 | I6: =SUBMETERING!S9 -> 211 | J6: =J5 -> 3.46 | K6: =(SUBMETERING!D9/100)*344 -> 304.9904 | L6: ='[1]Consommation mensuel énergie'!E14 -> 0 | M6: =E6*F6+G6*H6+#REF!*#REF!+I6*J6 -> #REF!
A7: Guangzhou | B7: =B6+1 -> 6 | C7: 11 | D7: 2020 | E7: =SUBMETERING!O10+SUBMETERING!M10 -> 41065 | F7: =F6 -> 0.675169 | G7: =SUBMETERING!E10+SUBMETERING!G10+SUBMETERING!I10+SUBMETERING!K10 -> 5566 | H7: =H6 -> 3.95 | I7: =SUBMETERING!S10 -> 202 | J7: =J6 -> 3.46 | K7: =(SUBMETERING!D10/100)*344 -> 309.8064 | L7: ='[1]Consommation mensuel énergie'!E15 -> 0 | M7: =E7*F7+G7*H7+#REF!*#REF!+I7*J7 -> #REF!
A8: Guangzhou | B8: =B7+1 -> 7 | C8: 11 | D8: 2020 | E8: =SUBMETERING!O11+SUBMETERING!M11 -> 40690 | F8: =F7 -> 0.675169 | G8: =SUBMETERING!E11+SUBMETERING!G11+SUBMETERING!I11+SUBMETERING!K11 -> 5510 | H8: =H7 -> 3.95 | I8: =SUBMETERING!S11 -> 220 | J8: =J7 -> 3.46 | K8: =(SUBMETERING!D11/100)*344 -> 322.9472 | L8: ='[1]Consommation mensuel énergie'!E16 -> 0 | M8: =E8*F8+G8*H8+#REF!*#REF!+I8*J8 -> #REF!
A9: Guangzhou | B9: =B8+1 -> 8 | C9: 11 | D9: 2020 | E9: =SUBMETERING!O12+SUBMETERING!M12 -> 37626 | F9: =F8 -> 0.675169 | G9: =SUBMETERING!E12+SUBMETERING!G12+SUBMETERING!I12+SUBMETERING!K12 -> 5346 | H9: =H8 -> 3.95 | I9: =SUBMETERING!S12 -> 210 | J9: =J8 -> 3.46 | K9: =(SUBMETERING!D12/100)*344 -> 214.0024 | L9: ='[1]Consommation mensuel énergie'!E17 -> 0 | M9: =E9*F9+G9*H9+#REF!*#REF!+I9*J9 -> #REF!
A10: Guangzhou | B10: =B9+1 -> 9 | C10: 11 | D10: 2020 | E10: =SUBMETERING!O13+SUBMETERING!M13 -> 36495 | F10: =F9 -> 0.675169 | G10: =SUBMETERING!E13+SUBMETERING!G13+SUBMETERING!I13+SUBMETERING!K13 -> 5112 | H10: =H9 -> 3.95 | I10: =SUBMETERING!S13 -> 190 | J10: =J9 -> 3.46 | K10: =(SUBMETERING!D13/100)*344 -> 231.9936 | L10: ='[1]Consommation mensuel énergie'!E18 -> 0 | M10: =E10*F10+G10*H10+#REF!*#REF!+I10*J10 -> #REF!
A11: Guangzhou | B11: =B10+1 -> 10 | C11: 11 | D11: 2020 | E11: =SUBMETERING!O14+SUBMETERING!M14 -> 35571 | F11: =F10 -> 0.675169 | G11: =SUBMETERING!E14+SUBMETERING!G14+SUBMETERING!I14+SUBMETERING!K14 -> 5456 | H11: =H10 -> 3.95 | I11: =SUBMETERING!S14 -> 170 | J11: =J10 -> 3.46 | K11: =(SUBMETERING!D14/100)*344 -> 250.0192 | L11: ='[1]Consommation mensuel énergie'!E19 -> 0 | M11: =E11*F11+G11*H11+#REF!*#REF!+I11*J11 -> #REF!
A12: Guangzhou | B12: =B11+1 -> 11 | C12: 11 | D12: 2020 | E12: =SUBMETERING!O15+SUBMETERING!M15 -> 36829 | F12: =F11 -> 0.675169 | G12: =SUBMETERING!E15+SUBMETERING!G15+SUBMETERING!I15+SUBMETERING!K15 -> 5498 | H12: =H11 -> 3.95 | I12: =SUBMETERING!S15 -> 170 | J12: =J11 -> 3.46 | K12: =(SUBMETERING!D15/100)*344 -> 315.0008 | L12: ='[1]Consommation mensuel énergie'!E20 -> 0 | M12: =E12*F12+G12*H12+#REF!*#REF!+I12*J12 -> #REF!
A13: Guangzhou | B13: =B12+1 -> 12 | C13: 11 | D13: 2020 | E13: =SUBMETERING!O16+SUBMETERING!M16 -> 36939 | F13: =F12 -> 0.675169 | G13: =SUBMETERING!E16+SUBMETERING!G16+SUBMETERING!I16+SUBMETERING!K16 -> 6016 | H13: =H12 -> 3.95 | I13: =SUBMETERING!S16 -> 191 | J13: =J12 -> 3.46 | K13: =(SUBMETERING!D16/100)*344 -> 329.0016 | L13: ='[1]Consommation mensuel énergie'!E21 -> 0 | M13: =E13*F13+G13*H13+#REF!*#REF!+I13*J13 -> #REF!
A14: Guangzhou | B14: =B13+1 -> 13 | C14: 11 | D14: 2020 | E14: =SUBMETERING!O17+SUBMETERING!M17 -> 37342 | F14: =F13 -> 0.675169 | G14: =SUBMETERING!E17+SUBMETERING!G17+SUBMETERING!I17+SUBMETERING!K17 -> 5850 | H14: =H13 -> 3.95 | I14: =SUBMETERING!S17 -> 194 | J14: =J13 -> 3.46 | K14: =(SUBMETERING!D17/100)*344 -> 328.004 | L14: ='[1]Consommation mensuel énergie'!E22 -> 0 | M14: =E14*F14+G14*H14+#REF!*#REF!+I14*J14 -> #REF!
... A31: Guangzhou | B31: =B30+1 -> 30 | C31: 11 | D31: 2020 | E31: =SUBMETERING!O34+SUBMETERING!M34 -> 28629 | F31: =F30 -> 0.675169 | G31: =SUBMETERING!E34+SUBMETERING!G34+SUBMETERING!I34+SUBMETERING!K34 -> 5948 | H31: =H30 -> 3.95 | I31: =SUBMETERING!S34 -> 160 | J31: =J30 -> 3.46 | K31: =(SUBMETERING!D34/100)*344 -> 239.0112 | L31: ='[1]Consommation mensuel énergie'!E39 -> 0 | M31: =E31*F31+G31*H31+#REF!*#REF!+I31*J31 -> #REF!

Sheet SUBMETERING
A1: UTILITIES CONSUMPTION REPORT(2020-11) 电费从2019年8月1号开始下降改为0.675169/Kwh，天然气从2020年9月1号开始下降改为3.95/m³2020年裙楼空调冷量价格为291.66/Mw.h+每天固定人工等1655.02元
A2: DATE 日期 | B2: Out door Temp℃ 户外 温度 | C2: Event Cover 宴会 人数 | D2: RoomOcc.% 客房率 | E2: Kitchen Gas 厨房天然气 (RMB3.95/m³) | G2: Boiler Gas 锅炉天然气(蒸汽) (RMB3.95/m³) | I2: Boiler Gas 锅炉天然气(热水) (RMB3.95/m³) | K2: General Gas 总天然气 (RMB3.95/m³) | M2: Chiller Electricity Consumption 空调主机用电量 (RMB0.675169/Kwh) | O2: General electricity 总电量(*10000)(RMB0.675169/Kwh) | Q2: Podium AC Consumption 裙楼空调用量 (Mw/h)Rmb291.66/MwH+1655.02/天 | S2: Water Consumption 水用量 | U2: Daily Total Utility Expense(RMB) 每日能耗总费用
S3: domestic Water 生活水RMB3.46/m3
E4: Totalgas (m³) | F4: Total RMB | G4: Totalgas (m³) | H4: Total RMB | I4: Totalgas(m³) | J4: Total RMB | K4: Totalgas (m³) | L4: Total RMB | M4: Total electric (KWH) | N4: Total RMB | O4: Total electric (KWH) | P4: Total RMB | Q4: Total (Mw/h0 | R4: Total RMB | S4: Total Water (m3) | T4: Total RMB
A5: 1 | B5: 19/28 | C5: 0 | D5: 57.27 | E5: =SUM(厨房燃气!BH7) -> 523 | F5: =IF(E5>0,E5*3.95,0) -> 2065.85 | G5: =SUM(厨房燃气!BJ7) -> 916 | H5: =IF(G5>0,G5*3.95,0) -> 3618.2 | I5: =SUM('B1 & 102F 锅炉房'!G7) -> 916 | J5: =IF(I5>0,I5*3.95,0) -> 3618.2 | K5: =SUM(I5+G5+E5) -> 2355 | L5: =IF(K5>0,K5*3.95,0) -> 9302.25 | M5: =SUM(主塔楼空调用电量!V4) -> 8068 | N5: =M5*0.675169 -> 5447.2635 | O5: =SUM('68F 高压F13&F30'!F7) -> 30800 | P5: =IF(O5>0,O5*0.675169) -> 20795.205 | Q5: =SUM(裙楼空调用量!L4) -> 11 | R5: =IF(Q5*417>0,Q5*291.66+1655.02) -> 4863.28 | S5: =SUM('B4 水表'!C7) -> 175 | T5: =S5*3.46 -> 605.5 | U5: =SUM(L5+P5+R5+T5) -> 35566.235
A6: 2 | B6: 19/28 | C6: 665 | D6: 70.64 | E6: =SUM(厨房燃气!BH8) -> 516 | F6: =IF(E6>0,E6*3.95,0) -> 2038.2 | G6: =SUM('B1 & 102F 锅炉房'!C8) -> 1479 | H6: =IF(G6>0,G6*3.95,0) -> 5842.05 | I6: =SUM('B1 & 102F 锅炉房'!G8) -> 780 | J6: =IF(I6>0,I6*3.95,0) -> 3081 | K6: =SUM(I6+G6+E6) -> 2775 | L6: =IF(K6>0,K6*3.95,0) -> 10961.25 | M6: =SUM(主塔楼空调用电量!V5) -> 7743 | N6: =M6*0.675169 -> 5227.8336 | O6: =SUM('68F 高压F13&F30'!F8) -> 29300 | P6: =IF(O6>0,O6*0.675169) -> 19782.452 | Q6: =SUM(裙楼空调用量!L5) -> 15 | R6: =IF(Q6*417>0,Q6*291.66+1655.02) -> 6029.92 | S6: =SUM('B4 水表'!C8) -> 160 | T6: =S6*3.46 -> 553.6 | U6: =SUM(L6+P6+R6+T6) -> 37327.222
A7: 3 | B7: 19/28 | C7: 320 | D7: 77.62 | E7: =SUM(厨房燃气!BH9) -> 526 | F7: =IF(E7>0,E7*3.95,0) -> 2077.7 | G7: =SUM('B1 & 102F 锅炉房'!C9) -> 1614 | H7: =IF(G7>0,G7*3.95,0) -> 6375.3 | I7: =SUM('B1 & 102F 锅炉房'!G9) -> 854 | J7: =IF(I7>0,I7*3.95,0) -> 3373.3 | K7: =SUM(I7+G7+E7) -> 2994 | L7: =IF(K7>0,K7*3.95,0) -> 11826.3 | M7: =SUM(主塔楼空调用电量!V6) -> 7049 | N7: =M7*0.675169 -> 4759.2663 | O7: =SUM('68F 高压F13&F30'!F9) -> 29600 | P7: =IF(O7>0,O7*0.675169) -> 19985.002 | Q7: =SUM(裙楼空调用量!L6) -> 19 | R7: =IF(Q7*417>0,Q7*291.66+1655.02) -> 7196.56 | S7: =SUM('B4 水表'!C9) -> 198 | T7: =S7*3.46 -> 685.08 | U7: =SUM(L7+P7+R7+T7) -> 39692.942
A8: 4 | B8: 20/28 | C8: 100 | D8: 72.38 | E8: =SUM(厨房燃气!BH10) -> 637 | F8: =IF(E8>0,E8*3.95,0) -> 2516.15 | G8: =SUM('B1 & 102F 锅炉房'!C10) -> 1440 | H8: =IF(G8>0,G8*3.95,0) -> 5688 | I8: =SUM('B1 & 102F 锅炉房'!G10) -> 866 | J8: =IF(I8>0,I8*3.95,0) -> 3420.7 | K8: =SUM(I8+G8+E8) -> 2943 | L8: =IF(K8>0,K8*3.95,0) -> 11624.85 | M8: =SUM(主塔楼空调用电量!V7) -> 5921 | N8: =M8*0.675169 -> 3997.6756 | O8: =SUM('68F 高压F13&F30'!F10) -> 27900 | P8: =IF(O8>0,O8*0.675169) -> 18837.215 | Q8: =SUM(裙楼空调用量!L7) -> 15 | R8: =IF(Q8*417>0,Q8*291.66+1655.02) -> 6029.92 | S8: =SUM('B4 水表'!C10) -> 199 | T8: =S8*3.46 -> 688.54 | U8: =SUM(L8+P8+R8+T8) -> 37180.525
A9: 5 | B9: 21/30 | C9: 1083 | D9: 88.66 | E9: =SUM(厨房燃气!BH11) -> 604 | F9: =IF(E9>0,E9*3.95,0) -> 2385.8 | G9: =SUM('B1 & 102F 锅炉房'!C11) -> 1303 | H9: =IF(G9>0,G9*3.95,0) -> 5146.85 | I9: =SUM('B1 & 102F 锅炉房'!G11) -> 885 | J9: =IF(I9>0,I9*3.95,0) -> 3495.75 | K9: =SUM(I9+G9+E9) -> 2792 | L9: =IF(K9>0,K9*3.95,0) -> 11028.4 | M9: =SUM(主塔楼空调用电量!V8) -> 7177 | N9: =M9*0.675169 -> 4845.6879 | O9: =SUM('68F 高压F13&F30'!F11) -> 29800 | P9: =IF(O9>0,O9*0.675169) -> 20120.036 | Q9: =SUM(裙楼空调用量!L8) -> 12 | R9: =IF(Q9*417>0,Q9*291.66+1655.02) -> 5154.94 | S9: =SUM('B4 水表'!C11) -> 211 | T9: =S9*3.46 -> 730.06 | U9: =SUM(L9+P9+R9+T9) -> 37033.436
A10: 6 | B10: 21/29 | C10: 707 | D10: 90.06 | E10: =SUM(厨房燃气!BH12) -> 640 | F10: =IF(E10>0,E10*3.95,0) -> 2528 | G10: =SUM('B1 & 102F 锅炉房'!C12) -> 1319 | H10: =IF(G10>0,G10*3.95,0) -> 5210.05 | I10: =SUM('B1 & 102F 锅炉房'!G12) -> 824 | J10: =IF(I10>0,I10*3.95,0) -> 3254.8 | K10: =SUM(I10+G10+E10) -> 2783 | L10: =IF(K10>0,K10*3.95,0) -> 10992.85 | M10: =SUM(主塔楼空调用电量!V9) -> 8465 | N10: =M10*0.675169 -> 5715.3056 | O10: =SUM('68F 高压F13&F30'!F12) -> 32600 | P10: =IF(O10>0,O10*0.675169) -> 22010.509 | Q10: =SUM(裙楼空调用量!L9) -> 20 | R10: =IF(Q10*417>0,Q10*291.66+1655.02) -> 7488.22 | S10: =SUM('B4 水表'!C12) -> 202 | T10: =S10*3.46 -> 698.92 | U10: =SUM(L10+P10+R10+T10) -> 41190.499
A11: 7 | B11: 19/28 | C11: 0 | D11: 93.88 | E11: =SUM(厨房燃气!BH13) -> 576 | F11: =IF(E11>0,E11*3.95,0) -> 2275.2 | G11: =SUM('B1 & 102F 锅炉房'!C13) -> 1305 | H11: =IF(G11>0,G11*3.95,0) -> 5154.75 | I11: =SUM('B1 & 102F 锅炉房'!G13) -> 874 | J11: =IF(I11>0,I11*3.95,0) -> 3452.3 | K11: =SUM(I11+G11+E11) -> 2755 | L11: =IF(K11>0,K11*3.95,0) -> 10882.25 | M11: =SUM(主塔楼空调用电量!V10) -> 8090 | N11: =M11*0.675169 -> 5462.1172 | O11: =SUM('68F 高压F13&F30'!F13) -> 32600 | P11: =IF(O11>0,O11*0.675169) -> 22010.509 | Q11: =SUM(裙楼空调用量!L10) -> 15 | R11: =IF(Q11*417>0,Q11*291.66+1655.02) -> 6029.92 | S11: =SUM('B4 水表'!C13) -> 220 | T11: =S11*3.46 -> 761.2 | U11: =SUM(L11+P11+R11+T11) -> 39683.879
A12: 8 | B12: 19/28 | C12: 34 | D12: 62.21 | E12: =SUM(厨房燃气!BH14) -> 529 | F12: =IF(E12>0,E12*3.95,0) -> 2089.55 | G12: =SUM('B1 & 102F 锅炉房'!C14) -> 1285 | H12: =IF(G12>0,G12*3.95,0) -> 5075.75 | I12: =SUM('B1 & 102F 锅炉房'!G14) -> 859 | J12: =IF(I12>0,I12*3.95,0) -> 3393.05 | K12: =SUM(I12+G12+E12) -> 2673 | L12: =IF(K12>0,K12*3.95,0) -> 10558.35 | M12: =SUM(主塔楼空调用电量!V11) -> 8526 | N12: =M12*0.675169 -> 5756.4909 | O12: =SUM('68F 高压F13&F30'!F14) -> 29100 | P12: =IF(O12>0,O12*0.675169) -> 19647.418 | Q12: =SUM(裙楼空调用量!L11) -> 12 | R12: =IF(Q12*417>0,Q12*291.66+1655.02) -> 5154.94 | S12: =SUM('B4 水表'!C14) -> 210 | T12: =S12*3.46 -> 726.6 | U12: =SUM(L12+P12+R12+T12) -> 36087.308
A13: 9 | B13: 17/26 | C13: 349 | D13: 67.44 | E13: =SUM(厨房燃气!BH15) -> 474 | F13: =IF(E13>0,E13*3.95,0) -> 1872.3 | G13: =SUM('B1 & 102F 锅炉房'!C15) -> 1313 | H13: =IF(G13>0,G13*3.95,0) -> 5186.35 | I13: =SUM('B1 & 102F 锅炉房'!G15) -> 769 | J13: =IF(I13>0,I13*3.95,0) -> 3037.55 | K13: =SUM(I13+G13+E13) -> 2556 | L13: =IF(K13>0,K13*3.95,0) -> 10096.2 | M13: =SUM(主塔楼空调用电量!V12) -> 7195 | N13: =M13*0.675169 -> 4857.841 | O13: =SUM('68F 高压F13&F30'!F15) -> 29300 | P13: =IF(O13>0,O13*0.675169) -> 19782.452 | Q13: =SUM(裙楼空调用量!L12) -> 14 | R13: =IF(Q13*417>0,Q13*291.66+1655.02) -> 5738.26 | S13: =SUM('B4 水表'!C15) -> 190 | T13: =S13*3.46 -> 657.4 | U13: =SUM(L13+P13+R13+T13) -> 36274.312
A14: 10 | B14: 17/28 | C14: 192 | D14: 72.68 | E14: =SUM(厨房燃气!BH16) -> 645 | F14: =IF(E14>0,E14*3.95,0) -> 2547.75 | G14: =SUM('B1 & 102F 锅炉房'!C16) -> 1293 | H14: =IF(G14>0,G14*3.95,0) -> 5107.35 | I14: =SUM('B1 & 102F 锅炉房'!G16) -> 790 | J14: =IF(I14>0,I14*3.95,0) -> 3120.5 | K14: =SUM(I14+G14+E14) -> 2728 | L14: =IF(K14>0,K14*3.95,0) -> 10775.6 | M14: =SUM(主塔楼空调用电量!V13) -> 6571 | N14: =M14*0.675169 -> 4436.5355 | O14: =SUM('68F 高压F13&F30'!F16) -> 29000 | P14: =IF(O14>0,O14*0.675169) -> 19579.901 | Q14: =SUM(裙楼空调用量!L13) -> 12 | R14: =IF(Q14*417>0,Q14*291.66+1655.02) -> 5154.94 | S14: =SUM('B4 水表'!C16) -> 170 | T14: =S14*3.46 -> 588.2 | U14: =SUM(L14+P14+R14+T14) -> 36098.641
A15: 11 | B15: 16/28 | C15: 1418 | D15: 91.57 | E15: =SUM(厨房燃气!BH17) -> 567 | F15: =IF(E15>0,E15*3.95,0) -> 2239.65 | G15: =SUM('B1 & 102F 锅炉房'!C17) -> 1391 | H15: =IF(G15>0,G15*3.95,0) -> 5494.45 | I15: =SUM('B1 & 102F 锅炉房'!G17) -> 791 | J15: =IF(I15>0,I15*3.95,0) -> 3124.45 | K15: =SUM(I15+G15+E15) -> 2749 | L15: =IF(K15>0,K15*3.95,0) -> 10858.55 | M15: =SUM(主塔楼空调用电量!V14) -> 7329 | N15: =M15*0.675169 -> 4948.3136 | O15: =SUM('68F 高压F13&F30'!F17) -> 29500 | P15: =IF(O15>0,O15*0.675169) -> 19917.486 | Q15: =SUM(裙楼空调用量!L14) -> 13 | R15: =IF(Q15*417>0,Q15*291.66+1655.02) -> 5446.6 | S15: =SUM('B4 水表'!C17) -> 170 | T15: =S15*3.46 -> 588.2 | U15: =SUM(L15+P15+R15+T15) -> 36810.836
A16: 12 | B16: 17/27 | C16: 678 | D16: 95.64 | E16: =SUM(厨房燃气!BH18) -> 831 | F16: =IF(E16>0,E16*3.95,0) -> 3282.45 | G16: =SUM('B1 & 102F 锅炉房'!C18) -> 1368 | H16: =IF(G16>0,G16*3.95,0) -> 5403.6 | I16: =SUM('B1 & 102F 锅炉房'!G18) -> 809 | J16: =IF(I16>0,I16*3.95,0) -> 3195.55 | K16: =SUM(I16+G16+E16) -> 3008 | L16: =IF(K16>0,K16*3.95,0) -> 11881.6 | M16: =SUM(主塔楼空调用电量!V15) -> 6839 | N16: =M16*0.675169 -> 4617.4808 | O16: =SUM('68F 高压F13&F30'!F18) -> 30100 | P16: =IF(O16>0,O16*0.675169) -> 20322.587 | Q16: =SUM(裙楼空调用量!L15) -> 16 | R16: =IF(Q16*417>0,Q16*291.66+1655.02) -> 6321.58 | S16: =SUM('B4 水表'!C18) -> 191 | T16: =S16*3.46 -> 660.86 | U16: =SUM(L16+P16+R16+T16) -> 39186.627
A17: 13 | B17: 19/24 | C17: 474 | D17: 95.35 | E17: =SUM(厨房燃气!BH19) -> 652 | F17: =IF(E17>0,E17*3.95,0) -> 2575.4 | G17: =SUM('B1 & 102F 锅炉房'!C19) -> 1428 | H17: =IF(G17>0,G17*3.95,0) -> 5640.6 | I17: =SUM('B1 & 102F 锅炉房'!G19) -> 845 | J17: =IF(I17>0,I17*3.95,0) -> 3337.75 | K17: =SUM(I17+G17+E17) -> 2925 | L17: =IF(K17>0,K17*3.95,0) -> 11553.75 | M17: =SUM(主塔楼空调用电量!V16) -> 7042 | N17: =M17*0.675169 -> 4754.5401 | O17: =SUM('68F 高压F13&F30'!F19) -> 30300 | P17: =IF(O17>0,O17*0.675169) -> 20457.621 | Q17: =SUM(裙楼空调用量!L16) -> 17 | R17: =IF(Q17*417>0,Q17*291.66+1655.02) -> 6613.24 | S17: =SUM('B4 水表'!C19) -> 194 | T17: =S17*3.46 -> 671.24 | U17: =SUM(L17+P17+R17+T17) -> 39295.851
... A20: 16 | B20: 20/29 | C20: 353 | D20: 92.15 | E20: =SUM(厨房燃气!BH22) -> 614 | F20: =IF(E20>0,E20*3.95,0) -> 2425.3 | G20: =SUM('B1 & 102F 锅炉房'!C22) -> 1443 | H20: =IF(G20>0,G20*3.95,0) -> 5699.85 | I20: =SUM('B1 & 102F 锅炉房'!G22) -> 883 | J20: =IF(I20>0,I20*3.95,0) -> 3487.85 | K20: =SUM(I20+G20+E20) -> 2940 | L20: =IF(K20>0,K20*3.95,0) -> 11613 | M20: =SUM(主塔楼空调用电量!V19) -> 8396 | N20: =M20*0.675169 -> 5668.7189 | O20: =SUM('68F 高压F13&F30'!F22) -> 30300 | P20: =IF(O20>0,O20*0.675169) -> 20457.621 | Q20: =SUM(裙楼空调用量!L19) -> 19 | R20: =IF(Q20*417>0,Q20*291.66+1655.02) -> 7196.56 | S20: =SUM('B4 水表'!C22) -> 173 | T20: =S20*3.46 -> 598.58 | U20: =SUM(L20+P20+R20+T20) -> 39865.761
A21: 17 | B21: 22/27 | C21: 502 | D21: 89.83 | E21: =SUM(厨房燃气!BH23) -> 698 | F21: =IF(E21>0,E21*3.95,0) -> 2757.1 | G21: =SUM('B1 & 102F 锅炉房'!C23) -> 1514 | H21: =IF(G21>0,G21*3.95,0) -> 5980.3 | I21: =SUM('B1 & 102F 锅炉房'!G23) -> 855 | J21: =IF(I21>0,I21*3.95,0) -> 3377.25 | K21: =SUM(E21+G21+I21) -> 3067 | L21: =IF(K21>0,K21*3.95,0) -> 12114.65 | M21: =SUM(主塔楼空调用电量!V20) -> 8056 | N21: =M21*0.675169 -> 5439.1615 | O21: =SUM('68F 高压F13&F30'!F23) -> 31700 | P21: =IF(O21>0,O21*0.675169) -> 21402.857 | Q21: =SUM(裙楼空调用量!L20) -> 19 | R21: =IF(Q21*417>0,Q21*291.66+1655.02) -> 7196.56 | S21: =SUM('B4 水表'!C23) -> 180 | T21: =S21*3.46 -> 622.8 | U21: =SUM(L21+P21+R21+T21) -> 41336.867
A22: 18 | B22: 23/30 | C22: 703 | D22: 97.38 | E22: =SUM(厨房燃气!BH24) -> 744 | F22: =IF(E22>0,E22*3.95,0) -> 2938.8 | G22: =SUM('B1 & 102F 锅炉房'!C24) -> 1504 | H22: =IF(G22>0,G22*3.95,0) -> 5940.8 | I22: =SUM('B1 & 102F 锅炉房'!G24) -> 846 | J22: =IF(I22>0,I22*3.95,0) -> 3341.7 | K22: =SUM(I22+G22+E22) -> 3094 | L22: =IF(K22>0,K22*3.95,0) -> 12221.3 | M22: =SUM(主塔楼空调用电量!V21) -> 8808 | N22: =M22*0.675169 -> 5946.8886 | O22: =SUM('68F 高压F13&F30'!F24) -> 32200 | P22: =IF(O22>0,O22*0.675169) -> 21740.442 | Q22: =SUM(裙楼空调用量!L21) -> 22 | R22: =IF(Q22*417>0,Q22*291.66+1655.02) -> 8071.54 | S22: =SUM('B4 水表'!C24) -> 158 | T22: =S22*3.46 -> 546.68 | U22: =SUM(L22+P22+R22+T22) -> 42579.962
A23: 19 | B23: 24/31 | C23: 686 | D23: 97.96 | E23: =SUM(厨房燃气!BH25) -> 685 | F23: =IF(E23>0,E23*3.95,0) -> 2705.75 | G23: =SUM('B1 & 102F 锅炉房'!C25) -> 1469 | H23: =IF(G23>0,G23*3.95,0) -> 5802.55 | I23: =SUM('B1 & 102F 锅炉房'!G25) -> 824 | J23: =IF(I23>0,I23*3.95,0) -> 3254.8 | K23: =SUM(I23+G23+E23) -> 2978 | L23: =IF(K23>0,K23*3.95,0) -> 11763.1 | M23: =SUM(主塔楼空调用电量!V22) -> 9415 | N23: =M23*0.675169 -> 6356.7161 | O23: =SUM('68F 高压F13&F30'!F25) -> 33100 | P23: =IF(O23>0,O23*0.675169) -> 22348.094 | Q23: =SUM(裙楼空调用量!L22) -> 25 | R23: =IF(Q23*417>0,Q23*291.66+1655.02) -> 8946.52 | S23: =SUM('B4 水表'!C25) -> 177 | T23: =S23*3.46 -> 612.42 | U23: =SUM(L23+P23+R23+T23) -> 43670.134
A24: 20 | B24: 23/29 | C24: 1020 | D24: 100 | E24: =SUM(厨房燃气!BH26) -> 961 | F24: =IF(E24>0,E24*3.95,0) -> 3795.95 | G24: =SUM('B1 & 102F 锅炉房'!C26) -> 1561 | H24: =IF(G24>0,G24*3.95,0) -> 6165.95 | I24: =SUM('B1 & 102F 锅炉房'!G26) -> 745 | J24: =IF(I24>0,I24*3.95,0) -> 2942.75 | K24: =SUM(I24+G24+E24) -> 3267 | L24: =IF(K24>0,K24*3.95,0) -> 12904.65 | M24: =SUM(主塔楼空调用电量!V23) -> 9959 | N24: =M24*0.675169 -> 6724.0081 | O24: =SUM('68F 高压F13&F30'!F26) -> 33500 | P24: =IF(O24>0,O24*0.675169) -> 22618.161 | Q24: =SUM(裙楼空调用量!L23) -> 21 | R24: =IF(Q24*417>0,Q24*291.66+1655.02) -> 7779.88 | S24: =SUM('B4 水表'!C26) -> 202 | T24: =S24*3.46 -> 698.92 | U24: =SUM(L24+P24+R24+T24) -> 44001.611
A25: 21 | B25: 19/29 | C25: 934 | D25: 98.54 | E25: =SUM(厨房燃气!BH27) -> 909 | F25: =IF(E25>0,E25*3.95,0) -> 3590.55 | G25: =SUM('B1 & 102F 锅炉房'!C27) -> 1523 | H25: =IF(G25>0,G25*3.95,0) -> 6015.85 | I25: =SUM('B1 & 102F 锅炉房'!G27) -> 859 | J25: =IF(I25>0,I25*3.95,0) -> 3393.05 | K25: =SUM(I25+G25+E25) -> 3291 | L25: =IF(K25>0,K25*3.95,0) -> 12999.45 | M25: =SUM(主塔楼空调用电量!V24) -> 9142 | N25: =M25*0.675169 -> 6172.395 | O25: =SUM('68F 高压F13&F30'!F27) -> 33600 | P25: =IF(O25>0,O25*0.675169) -> 22685.678 | Q25: =SUM(裙楼空调用量!L24) -> 21 | R25: =IF(Q25*417>0,Q25*291.66+1655.02) -> 7779.88 | S25: =SUM('B4 水表'!C27) -> 179 | T25: =S25*3.46 -> 619.34 | U25: =SUM(L25+P25+R25+T25) -> 44084.348
A26: 22 | B26: 18/27 | C26: 390 | D26: 74.85 | E26: =SUM(厨房燃气!BH28) -> 767 | F26: =IF(E26>0,E26*3.95,0) -> 3029.65 | G26: =SUM('B1 & 102F 锅炉房'!C28) -> 1463 | H26: =IF(G26>0,G26*3.95,0) -> 5778.85 | I26: =SUM('B1 & 102F 锅炉房'!G28) -> 933 | J26: =IF(I26>0,I26*3.95,0) -> 3685.35 | K26: =SUM(I26+G26+E26) -> 3163 | L26: =IF(K26>0,K26*3.95,0) -> 12493.85 | M26: =SUM(主塔楼空调用电量!V25) -> 9752 | N26: =M26*0.675169 -> 6584.2481 | O26: =SUM('68F 高压F13&F30'!F28) -> 34200 | P26: =IF(O26>0,O26*0.675169) -> 23090.78 | Q26: =SUM(裙楼空调用量!L25) -> 21 | R26: =IF(Q26*417>0,Q26*291.66+1655.02) -> 7779.88 | S26: =SUM('B4 水表'!C28) -> 218 | T26: =S26*3.46 -> 754.28 | U26: =SUM(L26+P26+R26+T26) -> 44118.79
A27: 23 | B27: 19/26 | C27: 600 | D27: 78.78 | E27: =SUM(厨房燃气!BH29) -> 597 | F27: =IF(E27>0,E27*3.95,0) -> 2358.15 | G27: =SUM('B1 & 102F 锅炉房'!C29) -> 1414 | H27: =IF(G27>0,G27*3.95,0) -> 5585.3 | I27: =SUM('B1 & 102F 锅炉房'!G29) -> 835 | J27: =IF(I27>0,I27*3.95,0) -> 3298.25 | K27: =SUM(I27+G27+E27) -> 2846 | L27: =IF(K27>0,K27*3.95,0) -> 11241.7 | M27: =SUM(主塔楼空调用电量!V26) -> 6896 | N27: =M27*0.675169 -> 4655.9654 | O27: =SUM('68F 高压F13&F30'!F29) -> 29200 | P27: =IF(O27>0,O27*0.675169) -> 19714.935 | Q27: =SUM(裙楼空调用量!L26) -> 18 | R27: =IF(Q27*417>0,Q27*291.66+1655.02) -> 6904.9 | S27: =SUM('B4 水表'!C29) -> 202 | T27: =S27*3.46 -> 698.92 | U27: =SUM(L27+P27+R27+T27) -> 38560.455
A28: 24 | B28: 19/28 | C28: 820 | D28: 88.08 | E28: =SUM(厨房燃气!BH30) -> 790 | F28: =IF(E28>0,E28*3.95,0) -> 3120.5 | G28: =SUM('B1 & 102F 锅炉房'!C30) -> 1430 | H28: =IF(G28>0,G28*3.95,0) -> 5648.5 | I28: =SUM('B1 & 102F 锅炉房'!G30) -> 821 | J28: =IF(I28>0,I28*3.95,0) -> 3242.95 | K28: =SUM(I28+G28+E28) -> 3041 | L28: =IF(K28>0,K28*3.95,0) -> 12011.95 | M28: =SUM(主塔楼空调用电量!V27) -> 9461 | N28: =M28*0.675169 -> 6387.7739 | O28: =SUM('68F 高压F13&F30'!F30) -> 28300 | P28: =IF(O28>0,O28*0.675169) -> 19107.283 | Q28: =SUM(裙楼空调用量!L27) -> 19 | R28: =IF(Q28*417>0,Q28*291.66+1655.02) -> 7196.56 | S28: =SUM('B4 水表'!C30) -> 181 | T28: =S28*3.46 -> 626.26 | U28: =SUM(L28+P28+R28+T28) -> 38942.053
A29: 25 | B29: 16/28 | C29: 200 | D29: 95.06 | E29: =SUM(厨房燃气!BH31) -> 746 | F29: =IF(E29>0,E29*3.95,0) -> 2946.7 | G29: =SUM('B1 & 102F 锅炉房'!C31) -> 1423 | H29: =IF(G29>0,G29*3.95,0) -> 5620.85 | I29: =SUM('B1 & 102F 锅炉房'!G31) -> 908 | J29: =IF(I29>0,I29*3.95,0) -> 3586.6 | K29: =SUM(I29+G29+E29) -> 3077 | L29: =IF(K29>0,K29*3.95,0) -> 12154.15 | M29: =SUM(主塔楼空调用电量!V28) -> 7907 | N29: =M29*0.675169 -> 5338.5613 | O29: =SUM('68F 高压F13&F30'!F31) -> 37600 | P29: =IF(O29>0,O29*0.675169) -> 25386.354 | Q29: =SUM(裙楼空调用量!L28) -> 20 | R29: =IF(Q29*417>0,Q29*291.66+1655.02) -> 7488.22 | S29: =SUM('B4 水表'!C31) -> 211 | T29: =S29*3.46 -> 730.06 | U29: =SUM(L29+P29+R29+T29) -> 45758.784
A30: 26 | B30: 14/26 | C30: 400 | D30: 96.51 | E30: =SUM(厨房燃气!BH32) -> 690 | F30: =IF(E30>0,E30*3.95,0) -> 2725.5 | G30: =SUM('B1 & 102F 锅炉房'!C32) -> 1484 | H30: =IF(G30>0,G30*3.95,0) -> 5861.8 | I30: =SUM('B1 & 102F 锅炉房'!G32) -> 858 | J30: =IF(I30>0,I30*3.95,0) -> 3389.1 | K30: =SUM(I30+G30+E30) -> 3032 | L30: =IF(K30>0,K30*3.95,0) -> 11976.4 | M30: =SUM(主塔楼空调用电量!V29) -> 8158 | N30: =M30*0.675169 -> 5508.0287 | O30: =SUM('68F 高压F13&F30'!F32) -> 30400 | P30: =IF(O30>0,O30*0.675169) -> 20525.138 | Q30: =SUM(裙楼空调用量!L29) -> 16 | R30: =IF(Q30*417>0,Q30*291.66+1655.02) -> 6321.58 | S30: =SUM('B4 水表'!C32) -> 169 | T30: =S30*3.46 -> 584.74 | U30: =SUM(L30+P30+R30+T30) -> 39407.858
A31: 27 | B31: 13/23 | C31: 1728 | D31: 94.19 | E31: =SUM(厨房燃气!BH33) -> 762 | F31: =IF(E31>0,E31*3.95,0) -> 3009.9 | G31: =SUM('B1 & 102F 锅炉房'!C33) -> 1486 | H31: =IF(G31>0,G31*3.95,0) -> 5869.7 | I31: =SUM('B1 & 102F 锅炉房'!G33) -> 888 | J31: =IF(I31>0,I31*3.95,0) -> 3507.6 | K31: =SUM(I31+G31+E31) -> 3136 | L31: =IF(K31>0,K31*3.95,0) -> 12387.2 | M31: =SUM(主塔楼空调用电量!V30) -> 7118 | N31: =M31*0.675169 -> 4805.8529 | O31: =SUM('68F 高压F13&F30'!F33) -> 31100 | P31: =IF(O31>0,O31*0.675169) -> 20997.756 | Q31: =SUM(裙楼空调用量!L30) -> 16 | R31: =IF(Q31*417>0,Q31*291.66+1655.02) -> 6321.58 | S31: =SUM('B4 水表'!C33) -> 208 | T31: =S31*3.46 -> 719.68 | U31: =SUM(L31+P31+R31+T31) -> 40426.216
A32: 28 | B32: 13/23 | C32: 2030 | D32: 92.73 | E32: =SUM(厨房燃气!BH34) -> 866 | F32: =IF(E32>0,E32*3.95,0) -> 3420.7 | G32: =SUM('B1 & 102F 锅炉房'!C34) -> 1475 | H32: =IF(G32>0,G32*3.95,0) -> 5826.25 | I32: =SUM('B1 & 102F 锅炉房'!G34) -> 942 | J32: =IF(I32>0,I32*3.95,0) -> 3720.9 | K32: =SUM(I32+G32+E32) -> 3283 | L32: =IF(K32>0,K32*3.95,0) -> 12967.85 | M32: =SUM(主塔楼空调用电量!V31) -> 5541 | N32: =M32*0.675169 -> 3741.1114 | O32: =SUM('68F 高压F13&F30'!F34) -> 29700 | P32: =IF(O32>0,O32*0.675169) -> 20052.519 | Q32: =SUM(裙楼空调用量!L31) -> 17 | R32: =IF(Q32*417>0,Q32*291.66+1655.02) -> 6613.24 | S32: =SUM('B4 水表'!C34) -> 181 | T32: =S32*3.46 -> 626.26 | U32: =SUM(L32+P32+R32+T32) -> 40259.869
A33: 29 | B33: 13/23 | C33: 573 | D33: 80.23 | E33: =SUM(厨房燃气!BH35) -> 790 | F33: =IF(E33>0,E33*3.95,0) -> 3120.5 | G33: =SUM('B1 & 102F 锅炉房'!C35) -> 1540 | H33: =IF(G33>0,G33*3.95,0) -> 6083 | I33: =SUM('B1 & 102F 锅炉房'!G35) -> 926 | J33: =IF(I33>0,I33*3.95,0) -> 3657.7 | K33: =SUM(I33+G33+E33) -> 3256 | L33: =IF(K33>0,K33*3.95,0) -> 12861.2 | M33: =SUM(主塔楼空调用电量!V32) -> 4754 | N33: =M33*0.675169 -> 3209.7534 | O33: =SUM('68F 高压F13&F30'!F35) -> 26800 | P33: =IF(O33>0,O33*0.675169) -> 18094.529 | Q33: =SUM(裙楼空调用量!L32) -> 14 | R33: =IF(Q33*417>0,Q33*291.66+1655.02) -> 5738.26 | S33: =SUM('B4 水表'!C35) -> 129 | T33: =S33*3.46 -> 446.34 | U33: =SUM(L33+P33+R33+T33) -> 37140.329
A34: 30 | B34: 14/24 | C34: 111 | D34: 69.48 | E34: =SUM(厨房燃气!BH36) -> 553 | F34: =IF(E34>0,E34*3.95,0) -> 2184.35 | G34: =SUM('B1 & 102F 锅炉房'!C36) -> 1524 | H34: =IF(G34>0,G34*3.95,0) -> 6019.8 | I34: =SUM('B1 & 102F 锅炉房'!G36) -> 897 | J34: =IF(I34>0,I34*3.95,0) -> 3543.15 | K34: =SUM(I34+G34+E34) -> 2974 | L34: =IF(K34>0,K34*3.95,0) -> 11747.3 | M34: =SUM(主塔楼空调用电量!V33) -> 5129 | N34: =M34*0.675169 -> 3462.9418 | O34: =SUM('68F 高压F13&F30'!F36) -> 23500 | P34: =IF(O34>0,O34*0.675169) -> 15866.471 | Q34: =SUM(裙楼空调用量!L33) -> 10 | R34: =IF(Q34*417>0,Q34*291.66+1655.02) -> 4571.62 | S34: =SUM('B4 水表'!C36) -> 160 | T34: =S34*3.46 -> 553.6 | U34: =SUM(L34+P34+R34+T34) -> 32738.991
A35: 31 | E35: =SUM(厨房燃气!BH37) -> -1429775 | F35: =IF(E35>0,E35*4.17,0) -> 0 | G35: =SUM('B1 & 102F 锅炉房'!C37) -> -4650224 | H35: =IF(G35>0,G35*4.17,0) -> 0 | I35: =SUM('B1 & 102F 锅炉房'!G37) -> -3318810 | J35: =IF(I35>0,I35*4.17,0) -> 0 | K35: =SUM(I35+G35+E35) -> -9398809 | L35: =IF(K35>0,K35*4.17,0) -> 0 | M35: =SUM(主塔楼空调用电量!V34) -> -12489927 | N35: =M35*0.675169 -> -8432811.5 | O35: =SUM('68F 高压F13&F30'!F37) -> -27926200 | P35: =IF(O35>0,O35*0.675169) -> FALSE | Q35: =SUM(裙楼空调用量!L34) -> -54653 | R35: =IF(Q35*417>0,Q35*291.66+1655.02) -> FALSE | S35: =SUM('B4 水表'!C37) -> -1706520 | T35: =S35*3.7287 -> -6363101.1 | U35: =SUM(L35+P35+R35+T35) -> -6363101.1
A36: Aver.
A37: Total | E37: =SUM(E5:E34) -> 20253 | F37: =SUM(F5:F34) -> 79999.35 | G37: =SUM(G5:G34) -> 42558 | H37: =SUM(H5:H34) -> 168104.1 | I37: =SUM(I5:I34) -> 25748 | J37: =SUM(J5:J34) -> 101704.6 | K37: =SUM(K5:K34) -> 88559 | L37: =SUM(L5:L34) -> 349808.05 | ... U37: =SUM(U5:U34) -> 1181802.8

Sheet 68F 高压F13&F30
A1: 广州四季酒店用电统计表 | G1: 电费从2019年8月1号开始下降改为0.675169元一度
A2: 44136 | F2: 单价 | G2: 0.675169
A4: 日期 | B4: 68F高压F13 | D4: 68F高压F30 | F4: 总用电量(Kwh) | G4: 费用(元)
B5: 仪表读数 | C5: 用电量(Kwh) | D5: 仪表读数 | E5: 用电量(Kwh)
A6: 44135 | B6: 1560.67 | C6: =SUM(B6-B5)*10000 -> #VALUE! | D6: 1140.53 | E6: =SUM(D6-D5)*10000 -> #VALUE! | F6: =C6+E6 -> #VALUE! | G6: =F6*0.675169 -> #VALUE!
A7: 44136 | B7: 1562.34 | C7: =SUM(B7-B6)*10000 -> 16700 | D7: 1141.94 | E7: =SUM(D7-D6)*10000 -> 14100 | F7: =C7+E7 -> 30800 | G7: =F7*0.675169 -> 20795.205
A8: 44137 | B8: 1563.95 | C8: =SUM(B8-B7)*10000 -> 16100 | D8: 1143.26 | E8: =SUM(D8-D7)*10000 -> 13200 | F8: =C8+E8 -> 29300 | G8: =F8*0.675169 -> 19782.452
A9: 44138 | B9: 1565.68 | C9: =SUM(B9-B8)*10000 -> 17300 | D9: 1144.49 | E9: =SUM(D9-D8)*10000 -> 12300 | F9: =C9+E9 -> 29600 | G9: =F9*0.675169 -> 19985.002
A10: 44139 | B10: 1567.36 | C10: =SUM(B10-B9)*10000 -> 16800 | D10: 1145.6 | E10: =SUM(D10-D9)*10000 -> 11100 | F10: =C10+E10 -> 27900 | G10: =F10*0.675169 -> 18837.215
A11: 44140 | B11: 1569.03 | C11: =SUM(B11-B10)*10000 -> 16700 | D11: 1146.91 | E11: =SUM(D11-D10)*10000 -> 13100 | F11: =C11+E11 -> 29800 | G11: =F11*0.675169 -> 20120.036
A12: 44141 | B12: 1570.69 | C12: =SUM(B12-B11)*10000 -> 16600 | D12: 1148.51 | E12: =SUM(D12-D11)*10000 -> 16000 | F12: =C12+E12 -> 32600 | G12: =F12*0.675169 -> 22010.509
A13: 44142 | B13: 1572.33 | C13: =SUM(B13-B12)*10000 -> 16400 | D13: 1150.13 | E13: =SUM(D13-D12)*10000 -> 16200 | F13: =C13+E13 -> 32600 | G13: =F13*0.675169 -> 22010.509
A14: 44143 | B14: 1573.82 | C14: =SUM(B14-B13)*10000 -> 14900 | D14: 1151.55 | E14: =SUM(D14-D13)*10000 -> 14200 | F14: =C14+E14 -> 29100 | G14: =F14*0.675169 -> 19647.418
A15: 44144 | B15: 1575.44 | C15: =SUM(B15-B14)*10000 -> 16200 | D15: 1152.86 | E15: =SUM(D15-D14)*10000 -> 13100 | F15: =C15+E15 -> 29300 | G15: =F15*0.675169 -> 19782.452
A16: 44145 | B16: 1577.15 | C16: =SUM(B16-B15)*10000 -> 17100 | D16: 1154.05 | E16: =SUM(D16-D15)*10000 -> 11900 | F16: =C16+E16 -> 29000 | G16: =F16*0.675169 -> 19579.901
A17: 44146 | B17: 1578.7 | C17: =SUM(B17-B16)*10000 -> 15500 | D17: 1155.45 | E17: =SUM(D17-D16)*10000 -> 14000 | F17: =C17+E17 -> 29500 | G17: =F17*0.675169 -> 19917.486
... A36: 44165 | B36: 1610 | C36: =SUM(B36-B35)*10000 -> 12400 | D36: 1182.62 | E36: =SUM(D36-D35)*10000 -> 11100 | F36: =C36+E36 -> 23500 | G36: =F36*0.675169 -> 15866.471
C37: =SUM(B37-B36)*10000 -> -16100000 | E37: =SUM(D37-D36)*10000 -> -11826200 | F37: =C37+E37 -> -27926200 | G37: =F37*0.675169 -> -18854905
C38: =SUM(C7:C36) -> 493300 | E38: =SUM(E7:E36) -> 420900 | F38: =SUM(F7:F36) -> 914200 | G38: =SUM(G7:G36) -> 617239.5
A39: 小合计 | C39: =SUM(C7:C36) -> 493300 | E39: =SUM(E7:E36) -> 420900 | F39: =SUM(F38) -> 914200 | G39: =SUM(G38) -> 617239.5
F40: 不含税金额 | G40: =+G39/1.17 -> 527555.13

Sheet B1 & 102F 锅炉房
A1: 广州四季酒店燃气统计表 | H1: 单价 | I1: 4.17 | J1: 从2018年6月1号起 | K1: 阶梯区间 （万立方米/年） | L1: <=1 | M1: (1,10] | N1: (100,500] | O1: >500
A2: 2020年11 | H2: 单价 | I2: 4.25 | K2: 价格（元/立方米） | L2: 4.15 | M2: 4.1 | N2: 3.8 | O2: 3.4
K3: 从2019年7月1号起
A4: 日期 | B4: B1锅炉房 | E4: 每日费用 | F4: 102F锅炉房 | I4: 每日费用 | J4: 总费用
B5: 仪表读数 | C5: 用气量(m3) | D5: 机械表读数 | F5: 仪表读数 | G5: 用气量(m3) | H5: 机械表读数
A6: 44135 | B6: 4607221 | C6: =B6-B5 -> #VALUE! | E6: =C6*3.95 -> #VALUE! | F6: 3293062 | G6: =F6-F5 -> #VALUE! | I6: =G6*3.95 -> #VALUE! | J6: =E6+I6 -> #VALUE!
A7: 44136 | B7: 4608582 | C7: =B7-B6 -> 1361 | E7: =C7*3.95 -> 5375.95 | F7: 3293978 | G7: =F7-F6 -> 916 | I7: =G7*3.95 -> 3618.2 | J7: =E7+I7 -> 8994.15
A8: 44137 | B8: 4610061 | C8: =B8-B7 -> 1479 | E8: =C8*3.95 -> 5842.05 | F8: 3294758 | G8: =F8-F7 -> 780 | I8: =G8*3.95 -> 3081 | J8: =E8+I8 -> 8923.05
A9: 44138 | B9: 4611675 | C9: =B9-B8 -> 1614 | E9: =C9*3.95 -> 6375.3 | F9: 3295612 | G9: =F9-F8 -> 854 | I9: =G9*3.95 -> 3373.3 | J9: =E9+I9 -> 9748.6
A10: 44139 | B10: 4613115 | C10: =B10-B9 -> 1440 | E10: =C10*3.95 -> 5688 | F10: 3296478 | G10: =F10-F9 -> 866 | I10: =G10*3.95 -> 3420.7 | J10: =E10+I10 -> 9108.7
A11: 44140 | B11: 4614418 | C11: =B11-B10 -> 1303 | E11: =C11*3.95 -> 5146.85 | F11: 3297363 | G11: =F11-F10 -> 885 | I11: =G11*3.95 -> 3495.75 | J11: =E11+I11 -> 8642.6
A12: 44141 | B12: 4615737 | C12: =B12-B11 -> 1319 | E12: =C12*3.95 -> 5210.05 | F12: 3298187 | G12: =F12-F11 -> 824 | I12: =G12*3.95 -> 3254.8 | J12: =E12+I12 -> 8464.85
A13: 44142 | B13: 4617042 | C13: =B13-B12 -> 1305 | E13: =C13*3.95 -> 5154.75 | F13: 3299061 | G13: =F13-F12 -> 874 | I13: =G13*3.95 -> 3452.3 | J13: =E13+I13 -> 8607.05
A14: 44143 | B14: 4618327 | C14: =B14-B13 -> 1285 | E14: =C14*3.95 -> 5075.75 | F14: 3299920 | G14: =F14-F13 -> 859 | I14: =G14*3.95 -> 3393.05 | J14: =E14+I14 -> 8468.8
A15: 44144 | B15: 4619640 | C15: =B15-B14 -> 1313 | E15: =C15*3.95 -> 5186.35 | F15: 3300689 | G15: =F15-F14 -> 769 | I15: =G15*3.95 -> 3037.55 | J15: =E15+I15 -> 8223.9
A16: 44145 | B16: 4620933 | C16: =B16-B15 -> 1293 | E16: =C16*3.95 -> 5107.35 | F16: 3301479 | G16: =F16-F15 -> 790 | I16: =G16*3.95 -> 3120.5 | J16: =E16+I16 -> 8227.85
A17: 44146 | B17: 4622324 | C17: =B17-B16 -> 1391 | E17: =C17*3.95 -> 5494.45 | F17: 3302270 | G17: =F17-F16 -> 791 | I17: =G17*3.95 -> 3124.45 | J17: =E17+I17 -> 8618.9
... A36: 44165 | B36: 4650224 | C36: =B36-B35 -> 1524 | E36: =C36*3.95 -> 6019.8 | F36: 3318810 | G36: =F36-F35 -> 897 | I36: =G36*3.95 -> 3543.15 | J36: =E36+I36 -> 9562.95
C37: =B37-B36 -> -4650224 | E37: =C37*4.17 -> -19391434 | G37: =F37-F36 -> -3318810 | I37: =G37*4.17 -> -13839438 | J37: =E37+I37 -> -33230872
A38: 合计 | C38: =SUM(C7:C36) -> 43003 | E38: =SUM(E7:E36) -> 169861.85 | G38: =SUM(G7:G36) -> 25748 | I38: =SUM(I6:I36) -> #VALUE! | J38: =SUM(J6:J36) -> #VALUE!

Sheet B4 水表
A1: 广州四季酒店用水统计表
A2: 44136 | C2: 单价 | D2: 3.46
A4: 日期 | B4: B4酒店总表 | C4: 用水量(m3) | D4: 费用(元)
B5: 仪表读数
A6: 44135 | B6: 1700865 | C6: =(B6-B5) -> #VALUE! | D6: =C6*3.46 -> #VALUE!
A7: 44136 | B7: 1701040 | C7: =(B7-B6) -> 175 | D7: =C7*3.46 -> 605.5
A8: 44137 | B8: 1701200 | C8: =(B8-B7) -> 160 | D8: =C8*3.46 -> 553.6
A9: 44138 | B9: 1701398 | C9: =(B9-B8) -> 198 | D9: =C9*3.46 -> 685.08
A10: 44139 | B10: 1701597 | C10: =(B10-B9) -> 199 | D10: =C10*3.46 -> 688.54
A11: 44140 | B11: 1701808 | C11: =(B11-B10) -> 211 | D11: =C11*3.46 -> 730.06
A12: 44141 | B12: 1702010 | C12: =(B12-B11) -> 202 | D12: =C12*3.46 -> 698.92
A13: 44142 | B13: 1702230 | C13: =(B13-B12) -> 220 | D13: =C13*3.46 -> 761.2
A14: 44143 | B14: 1702440 | C14: =(B14-B13) -> 210 | D14: =C14*3.46 -> 726.6
A15: 44144 | B15: 1702630 | C15: =(B15-B14) -> 190 | D15: =C15*3.46 -> 657.4
A16: 44145 | B16: 1702800 | C16: =(B16-B15) -> 170 | D16: =C16*3.46 -> 588.2
A17: 44146 | B17: 1702970 | C17: =(B17-B16) -> 170 | D17: =C17*3.46 -> 588.2
... A36: 44165 | B36: 1706520 | C36: =(B36-B35) -> 160 | D36: =C36*3.46 -> 553.6
C37: =(B37-B36) -> -1706520 | D37: =C37*3.6951 -> -6305762.1
A38: 合计 | C38: =SUM(C7:C36) -> 5655 | D38: =SUM(D6:D36) -> #VALUE!

Sheet 68厨房
A1: 广州四季酒店燃气统计表
A2: 44136
A4: 日期 | B4: 68F员工厨房 | K4: 总费用(元)
B5: 然气机械表读数 | C5: 然气电子表读数 | D5: 用气量(m3) | E5: 每日金额 | F5: 用电仪表读数 （动力） | G5: 用电仪表读数 （冷库） | H5: 照明 (无电表，每天记120kw/h) | I5: 用电量 | J5: 每日金额
A6: 44135 | B6: 388272 | C6: 13613 | D6: =(B6-B5) -> #VALUE! | E6: =D6*3.95 -> #VALUE! | F6: 688099 | G6: 261293 | H6: 120 | I6: =SUM(F6-F5+G6-G5+H6) -> #VALUE! | J6: =I6*0.675169 -> #VALUE! | K6: =E6+J6 -> #VALUE!
A7: 44136 | B7: 388423 | C7: 13462 | D7: =(B7-B6) -> 151 | E7: =D7*3.95 -> 596.45 | F7: 688494 | G7: 261376 | H7: 120 | I7: =SUM(F7-F6+G7-G6+H7) -> 598 | J7: =I7*0.675169 -> 403.75106 | K7: =E7+J7 -> 1000.2011
A8: 44137 | B8: 388593 | C8: 13293 | D8: =(B8-B7) -> 170 | E8: =D8*3.95 -> 671.5 | F8: 688903 | G8: 261461 | H8: 120 | I8: =SUM(F8-F7+G8-G7+H8) -> 614 | J8: =I8*0.675169 -> 414.55377 | K8: =E8+J8 -> 1086.0538
A9: 44138 | B9: 388744 | C9: 13142 | D9: =(B9-B8) -> 151 | E9: =D9*3.95 -> 596.45 | F9: 689305 | G9: 261532 | H9: 120 | I9: =SUM(F9-F8+G9-G8+H9) -> 593 | J9: =I9*0.675169 -> 400.37522 | K9: =E9+J9 -> 996.82522
A10: 44139 | B10: 388925 | C10: 12960 | D10: =(B10-B9) -> 181 | E10: =D10*3.95 -> 714.95 | F10: 689726 | G10: 261613 | H10: 120 | I10: =SUM(F10-F9+G10-G9+H10) -> 622 | J10: =I10*0.675169 -> 419.95512 | K10: =E10+J10 -> 1134.9051
A11: 44140 | B11: 389116 | C11: 12769 | D11: =(B11-B10) -> 191 | E11: =D11*3.95 -> 754.45 | F11: 690133 | G11: 261697 | H11: 120 | I11: =SUM(F11-F10+G11-G10+H11) -> 611 | J11: =I11*0.675169 -> 412.52826 | K11: =E11+J11 -> 1166.9783
A12: 44141 | B12: =厨房燃气!AA12 -> 389305 | C12: =厨房燃气!AB12 -> 12580 | D12: =(B12-B11) -> 189 | E12: =D12*3.95 -> 746.55 | F12: 690556 | G12: 261781 | H12: 120 | I12: =SUM(F12-F11+G12-G11+H12) -> 627 | J12: =I12*0.675169 -> 423.33096 | K12: =E12+J12 -> 1169.881
A13: 44142 | B13: =厨房燃气!AA13 -> 389452 | C13: =厨房燃气!AB13 -> 12433 | D13: =(B13-B12) -> 147 | E13: =D13*3.95 -> 580.65 | F13: 690949 | G13: 261862 | H13: 120 | I13: =SUM(F13-F12+G13-G12+H13) -> 594 | J13: =I13*0.675169 -> 401.05039 | K13: =E13+J13 -> 981.70039
A14: 44143 | B14: =厨房燃气!AA14 -> 389599 | C14: =厨房燃气!AB14 -> 12286 | D14: =(B14-B13) -> 147 | E14: =D14*3.95 -> 580.65 | F14: 691341 | G14: 261934 | H14: 120 | I14: =SUM(F14-F13+G14-G13+H14) -> 584 | J14: =I14*0.675169 -> 394.2987 | K14: =E14+J14 -> 974.9487
A15: 44144 | B15: =厨房燃气!AA15 -> 389752 | C15: =厨房燃气!AB15 -> 12133 | D15: =(B15-B14) -> 153 | E15: =D15*3.95 -> 604.35 | F15: 691786 | G15: 262010 | H15: 120 | I15: =SUM(F15-F14+G15-G14+H15) -> 641 | J15: =I15*0.675169 -> 432.78333 | K15: =E15+J15 -> 1037.1333
A16: 44145 | B16: =厨房燃气!AA16 -> 389919 | C16: =厨房燃气!AB16 -> 11966 | D16: =(B16-B15) -> 167 | E16: =D16*3.95 -> 659.65 | F16: 692242 | G16: 262087 | H16: 120 | I16: =SUM(F16-F15+G16-G15+H16) -> 653 | J16: =I16*0.675169 -> 440.88536 | K16: =E16+J16 -> 1100.5354
A17: 44146 | B17: =厨房燃气!AA17 -> 390119 | C17: =厨房燃气!AB17 -> 11766 | D17: =(B17-B16) -> 200 | E17: =D17*3.95 -> 790 | F17: 692707 | G17: 262166 | H17: 120 | I17: =SUM(F17-F16+G17-G16+H17) -> 664 | J17: =I17*0.675169 -> 448.31222 | K17: =E17+J17 -> 1238.3122
A18: 44147 | B18: 390314 | C18: 11571 | D18: =(B18-B17) -> 195 | E18: =D18*3.95 -> 770.25 | F18: 693206 | G18: 262240 | H18: 120 | I18: =SUM(F18-F17+G18-G17+H18) -> 693 | J18: =I18*0.675169 -> 467.89212 | K18: =E18+J18 -> 1238.1421
A19: 44148 | B19: 390489 | C19: 11397 | D19: =(B19-B18) -> 175 | E19: =D19*3.95 -> 691.25 | F19: 693676 | G19: 262312 | H19: 120 | I19: =SUM(F19-F18+G19-G18+H19) -> 662 | J19: =I19*0.675169 -> 446.96188 | K19: =E19+J19 -> 1138.2119
A20: 44149 | B20: 390635 | C20: 11250 | D20: =(B20-B19) -> 146 | E20: =D20*3.95 -> 576.7 | F20: 694163 | G20: 262312 | H20: 120 | I20: =SUM(F20-F19+G20-G19+H20) -> 607 | J20: =I20*0.675169 -> 409.82758 | K20: =E20+J20 -> 986.52758
A21: 44150 | B21: 390798 | C21: 11087 | D21: =(B21-B20) -> 163 | E21: =D21*3.95 -> 643.85 | F21: 694310 | G21: 262457 | H21: 120 | I21: =SUM(F21-F20+G21-G20+H21) -> 412 | J21: =I21*0.675169 -> 278.16963 | K21: =E21+J21 -> 922.01963
A22: 44151 | B22: 390993 | C22: 10892 | D22: =(B22-B21) -> 195 | E22: =D22*3.95 -> 770.25 | F22: 695091 | G22: 262527 | H22: 120 | I22: =SUM(F22-F21+G22-G21+H22) -> 971 | J22: =I22*0.675169 -> 655.5891 | K22: =E22+J22 -> 1425.8391
A23: 44152 | B23: 391160 | C23: 10726 | D23: =(B23-B22) -> 167 | E23: =D23*3.95 -> 659.65 | F23: 695579 | G23: 262598 | H23: 120 | I23: =SUM(F23-F22+G23-G22+H23) -> 679 | J23: =I23*0.675169 -> 458.43975 | K23: =E23+J23 -> 1118.0898
A24: 44153 | B24: 391355 | C24: 10531 | D24: =(B24-B23) -> 195 | E24: =D24*3.95 -> 770.25 | F24: 696099 | G24: 262674 | H24: 120 | I24: =SUM(F24-F23+G24-G23+H24) -> 716 | J24: =I24*0.675169 -> 483.421 | K24: =E24+J24 -> 1253.671
A25: 44154 | B25: 391545 | C25: 10341 | D25: =(B25-B24) -> 190 | E25: =D25*3.95 -> 750.5 | F25: 696620 | G25: 262754 | H25: 120 | I25: =SUM(F25-F24+G25-G24+H25) -> 721 | J25: =I25*0.675169 -> 486.79685 | K25: =E25+J25 -> 1237.2968
A26: 44155 | B26: 391734 | C26: 10151 | D26: =(B26-B25) -> 189 | E26: =D26*3.95 -> 746.55 | F26: 697100 | G26: 262825 | H26: 120 | I26: =SUM(F26-F25+G26-G25+H26) -> 671 | J26: =I26*0.675169 -> 453.0384 | K26: =E26+J26 -> 1199.5884
A27: 44156 | B27: 391901 | C27: 9984 | D27: =(B27-B26) -> 167 | E27: =D27*3.95 -> 659.65 | F27: 697640 | G27: 262894 | H27: 120 | I27: =SUM(F27-F26+G27-G26+H27) -> 729 | J27: =I27*0.675169 -> 492.1982 | K27: =E27+J27 -> 1151.8482
A28: 44157 | B28: 392061 | C28: 9824 | D28: =(B28-B27) -> 160 | E28: =D28*3.95 -> 632 | F28: 698185 | G28: 262962 | H28: 120 | I28: =SUM(F28-F27+G28-G27+H28) -> 733 | J28: =I28*0.675169 -> 494.89888 | K28: =E28+J28 -> 1126.8989
A29: 44158 | B29: 392217 | C29: 9668 | D29: =(B29-B28) -> 156 | E29: =D29*3.95 -> 616.2 | F29: 698713 | G29: 263042 | H29: 120 | I29: =SUM(F29-F28+G29-G28+H29) -> 728 | J29: =I29*0.675169 -> 491.52303 | K29: =E29+J29 -> 1107.723
... A31: 44160 | B31: 392578 | C31: 14307 | D31: =(B31-B30) -> 189 | E31: =D31*3.95 -> 746.55 | F31: 699758 | G31: 263187 | H31: 120 | I31: =SUM(F31-F30+G31-G30+H31) -> 718 | J31: =I31*0.675169 -> 484.77134 | K31: =E31+J31 -> 1231.3213
A32: 44161 | B32: 392769 | C32: 14116 | D32: =(B32-B31) -> 191 | E32: =D32*3.95 -> 754.45 | F32: 700317 | G32: 263269 | H32: 120 | I32: =F32-F31+G32-G31+H33 -> 761 | J32: =I32*0.675169 -> 513.80361 | K32: =E32+J32 -> 1268.2536
A33: 44162 | B33: =厨房燃气!AA33 -> 392925 | C33: =厨房燃气!AB33 -> 13960 | D33: =(B33-B32) -> 156 | E33: =D33*3.95 -> 616.2 | F33: 700847 | G33: 263343 | H33: 120 | I33: =SUM(F33-F32+G33-G32+H33) -> 724 | J33: =I33*0.675169 -> 488.82236 | K33: =E33+J33 -> 1105.0224
A34: 44163 | B34: =厨房燃气!AA34 -> 393124 | C34: =厨房燃气!AB34 -> 13761 | D34: =(B34-B33) -> 199 | E34: =D34*3.95 -> 786.05 | F34: 701406 | G34: 263418 | H34: 120 | I34: =SUM(F34-F33+G34-G33+H34) -> 754 | J34: =I34*0.675169 -> 509.07743 | K34: =E34+J34 -> 1295.1274
A35: 44164 | B35: =厨房燃气!AA35 -> 393312 | C35: =厨房燃气!AB35 -> 13573 | D35: =(B35-B34) -> 188 | E35: =D35*3.95 -> 742.6 | F35: 701957 | G35: 263486 | H35: 120 | I35: =SUM(F35-F34+G35-G34+H35) -> 739 | J35: =I35*0.675169 -> 498.94989 | K35: =E35+J35 -> 1241.5499
A36: 44165 | B36: =厨房燃气!AA36 -> 393487 | C36: =厨房燃气!AB36 -> 13399 | D36: =(B36-B35) -> 175 | E36: =D36*3.95 -> 691.25 | F36: 702531 | G36: 263558 | H36: 120 | I36: =SUM(F36-F35+G36-G35+H36) -> 766 | J36: =I36*0.675169 -> 517.17945 | K36: =E36+J36 -> 1208.4295
D37: =(B37-B36) -> -393487 | E37: =D37*4.17 -> -1640840.8 | H37: 120 | I37: =SUM(F37-F36+G37-G36+H37) -> -965969 | J37: =I37*0.675169 -> -652192.32 | K37: =E37+J37 -> -2293033.1
A38: 合计 | D38: =SUM(D7:D36) -> 5215 | K38: =SUM(K7:K36) -> 34303.155

Sheet 厨房燃气
A1: 广州四季酒店燃气统计表
A2: 44136 | B2: 单价 | C2: 4.25
A4: 日期 | B4: P1F宴会厨房 | G4: P2F员工厨房 | L4: P3宴会烧烤间 | Q4: P3F宴会厨房 | V4: P4F宴会厨房 | AA4: 68F员工厨房 | AF4: 70F大堂吧厨房 | AK4: 71F中餐厨房 | AP4: 72F意珍厨房 | AU4: 99F行政厨房 | AZ4: 100F百鲜汇厨房 | BE4: 总用气量(m3) | BF4: 总费用(元) | BH4: 酒店厨房总用气量(m3) | BI4: B1F锅炉房 (m3) | BJ4: 102F锅炉房 (m3) | BK4: 酒店煤气总用气量(m3)
B5: 机械表读数 | C5: 电子表读数 | D5: 用气量(m3) | E5: 每日金额 | F5: 充值记录 | G5: 机械表读数 | H5: 电子表读数 | I5: 用气量(m3) | J5: 每日金额 | K5: 充值记录 | L5: 机械表读数 | M5: 电子表读数 | N5: 用气量(m3) | O5: 每日金额 | P5: 充值记录 | Q5: 机械表读数 | R5: 电子表读数 | S5: 用气量(m3) | T5: 每日金额 | U5: 充值记录 | V5: 机械表读数 | W5: 电子表读数 | X5: 用气量(m3) | Y5: 每日金额 | Z5: 充值记录 | AA5: 机械表读数 | AB5: 电子表读数 | AC5: 用气量(m3) | AD5: 每日金额 | AE5: 充值记录 | AF5: 机械表读数 | AG5: 电子表读数 | AH5: 用气量(m3) | AI5: 每日金额 | AJ5: 充值记录 | AK5: 机械表读数 | AL5: 电子表读数 | AM5: 用气量(m3) | AN5: 每日金额 | AO5: 充值记录 | AP5: 机械表读数 | AQ5: 电子表读数 | AR5: 用气量(m3) | AS5: 每日金额 | AT5: 充值记录 | AU5: 机械表读数 | AV5: 电子表读数 | AW5: 用气量(m3) | AX5: 每日金额 | AY5: 充值记录 | AZ5: 机械表读数 | BA5: 电子表读数 | BB5: 用气量(m3) | BC5: 每日金额 | BD5: 充值记录
A6: 44135 | B6: 67783 | C6: 2133 | D6: =B6-B5 -> #VALUE! | E6: =D6*3.95 -> #VALUE! | I6: =(G6-G5) -> #VALUE! | J6: =I6*4.25 -> #VALUE! | L6: 101264 | M6: 2293 | N6: =(L6-L5) -> #VALUE! | O6: =N6*3.95 -> #VALUE! | Q6: 152674 | R6: 5523 | S6: =(Q6-Q5) -> #VALUE! | T6: =S6*3.95 -> #VALUE! | V6: 19833 | W6: 3332 | X6: =(V6-V5) -> #VALUE! | Y6: =X6*3.95 -> #VALUE! | AA6: 388272 | AB6: 13613 | AC6: =(AA6-AA5) -> #VALUE! | AD6: =AC6*3.95 -> #VALUE! | AF6: 63684 | AG6: 2754 | AH6: =(AF6-AF5) -> #VALUE! | AI6: =AH6*3.95 -> #VALUE! | AK6: 514148 | AL6: 13958 | AM6: =(AK6-AK5) -> #VALUE! | AN6: =AM6*3.95 -> #VALUE! | AP6: 6417 | AQ6: 12788 | AR6: =(AP6-AP5) -> #VALUE! | AS6: =AR6*3.95 -> #VALUE! | AU6: 20108 | AV6: 2717 | AW6: =AU6-AU5 -> #VALUE! | AX6: =AW6*3.95 -> #VALUE! | AZ6: 75339 | BA6: 4945 | BB6: =(AZ6-AZ5) -> #VALUE! | BC6: =BB6*3.95 -> #VALUE! | BE6: =D6+I6+N6+S6+X6+AC6+AH6+AM6+AR6+AW6+BB6 -> #VALUE! | BF6: =E6+J6+O6+T6+Y6+AD6+AI6+AN6+AS6+AX6+BC6 -> #VALUE! | BH6: =BE6 -> #VALUE! | BI6: ='B1 & 102F 锅炉房'!C6 -> #VALUE! | BJ6: ='B1 & 102F 锅炉房'!G6 -> #VALUE! | BK6: =SUM(BH6+BI6+BJ6) -> #VALUE!
A7: 44136 | B7: 67790 | C7: 2125 | D7: =B7-B6 -> 7 | E7: =D7*3.95 -> 27.65 | I7: =(G7-G6) -> 0 | J7: =I7*4.25 -> 0 | L7: 101300 | M7: 2257 | N7: =L7-L6 -> 36 | O7: =N7*3.95 -> 142.2 | Q7: 152674 | R7: 5523 | S7: =(Q7-Q6) -> 0 | T7: =S7*3.95 -> 0 | V7: 19836 | W7: 3329 | X7: =(V7-V6) -> 3 | Y7: =X7*3.95 -> 11.85 | AA7: 388423 | AB7: 13462 | AC7: =(AA7-AA6) -> 151 | AD7: =AC7*3.95 -> 596.45 | AF7: 63686 | AG7: 2752 | AH7: =(AF7-AF6) -> 2 | AI7: =AH7*3.95 -> 7.9 | AK7: 514312 | AL7: 13794 | AM7: =(AK7-AK6) -> 164 | AN7: =AM7*3.95 -> 647.8 | AP7: 6542 | AQ7: 12662 | AR7: =(AP7-AP6) -> 125 | AS7: =AR7*3.95 -> 493.75 | AU7: 20123 | AV7: 2701 | AW7: =AU7-AU6 -> 15 | AX7: =AW7*3.95 -> 59.25 | AZ7: 75359 | BA7: 4925 | BB7: =(AZ7-AZ6) -> 20 | BC7: =BB7*3.95 -> 79 | BE7: =D7+I7+N7+S7+X7+AC7+AH7+AM7+AR7+AW7+BB7 -> 523 | BF7: =E7+J7+O7+T7+Y7+AD7+AI7+AN7+AS7+AX7+BC7 -> 2065.85 | BH7: =SUM(BE7) -> 523 | BI7: ='B1 & 102F 锅炉房'!C7 -> 1361 | BJ7: ='B1 & 102F 锅炉房'!G7 -> 916 | BK7: =SUM(BH7+BI7+BJ7) -> 2800
A8: 44137 | B8: 67823 | C8: 2093 | D8: =B8-B7 -> 33 | E8: =D8*3.95 -> 130.35 | I8: =(G8-G7) -> 0 | J8: =I8*4.25 -> 0 | L8: 101319 | M8: 2238 | N8: =L8-L7 -> 19 | O8: =N8*3.95 -> 75.05 | Q8: 152674 | R8: 5523 | S8: =(Q8-Q7) -> 0 | T8: =S8*3.95 -> 0 | V8: 19850 | W8: 3315 | X8: =(V8-V7) -> 14 | Y8: =X8*3.95 -> 55.3 | AA8: 388593 | AB8: 13293 | AC8: =(AA8-AA7) -> 170 | AD8: =AC8*3.95 -> 671.5 | AF8: 63690 | AG8: 2748 | AH8: =(AF8-AF7) -> 4 | AI8: =AH8*3.95 -> 15.8 | AK8: 514453 | AL8: 13653 | AM8: =(AK8-AK7) -> 141 | AN8: =AM8*3.95 -> 556.95 | AP8: 6670 | AQ8: 12535 | AR8: =(AP8-AP7) -> 128 | AS8: =AR8*3.95 -> 505.6 | AU8: 20129 | AV8: 2695 | AW8: =AU8-AU7 -> 6 | AX8: =AW8*3.95 -> 23.7 | AZ8: 75360 | BA8: 4925 | BB8: =(AZ8-AZ7) -> 1 | BC8: =BB8*3.95 -> 3.95 | BE8: =D8+I8+N8+S8+X8+AC8+AH8+AM8+AR8+AW8+BB8 -> 516 | BF8: =E8+J8+O8+T8+Y8+AD8+AI8+AN8+AS8+AX8+BC8 -> 2038.2 | BH8: =SUM(BE8) -> 516 | BI8: ='B1 & 102F 锅炉房'!C8 -> 1479 | BJ8: ='B1 & 102F 锅炉房'!G8 -> 780 | BK8: =SUM(BH8+BI8+BJ8) -> 2775
A9: 44138 | B9: 67837 | C9: 2078 | D9: =B9-B8 -> 14 | E9: =D9*3.95 -> 55.3 | I9: =(G9-G8) -> 0 | J9: =I9*4.25 -> 0 | L9: 101341 | M9: 2215 | N9: =L9-L8 -> 22 | O9: =N9*3.95 -> 86.9 | Q9: 152674 | R9: 5523 | S9: =(Q9-Q8) -> 0 | T9: =S9*3.95 -> 0 | V9: 19856 | W9: 3309 | X9: =(V9-V8) -> 6 | Y9: =X9*3.95 -> 23.7 | AA9: 388744 | AB9: 13142 | AC9: =(AA9-AA8) -> 151 | AD9: =AC9*3.95 -> 596.45 | AF9: 63694 | AG9: 2744 | AH9: =(AF9-AF8) -> 4 | AI9: =AH9*3.95 -> 15.8 | AK9: 514613 | AL9: 13493 | AM9: =(AK9-AK8) -> 160 | AN9: =AM9*3.95 -> 632 | AP9: 6804 | AQ9: 12401 | AR9: =(AP9-AP8) -> 134 | AS9: =AR9*3.95 -> 529.3 | AU9: 20138 | AV9: 2686 | AW9: =AU9-AU8 -> 9 | AX9: =AW9*3.95 -> 35.55 | AZ9: 75386 | BA9: 4897 | BB9: =(AZ9-AZ8) -> 26 | BC9: =BB9*3.95 -> 102.7 | BE9: =D9+I9+N9+S9+X9+AC9+AH9+AM9+AR9+AW9+BB9 -> 526 | BF9: =E9+J9+O9+T9+Y9+AD9+AI9+AN9+AS9+AX9+BC9 -> 2077.7 | BH9: =SUM(BE9) -> 526 | BI9: ='B1 & 102F 锅炉房'!C9 -> 1614 | BJ9: ='B1 & 102F 锅炉房'!G9 -> 854 | BK9: =SUM(BH9+BI9+BJ9) -> 2994
A10: 44139 | B10: 67854 | C10: 2062 | D10: =B10-B9 -> 17 | E10: =D10*3.95 -> 67.15 | I10: =(G10-G9) -> 0 | J10: =I10*4.25 -> 0 | L10: 101363 | M10: 2194 | N10: =(L10-L9) -> 22 | O10: =N10*3.95 -> 86.9 | Q10: 152689 | R10: 5507 | S10: =(Q10-Q9) -> 15 | T10: =S10*3.95 -> 59.25 | V10: 19895 | W10: 3270 | X10: =(V10-V9) -> 39 | Y10: =X10*3.95 -> 154.05 | AA10: 388925 | AB10: 12960 | AC10: =(AA10-AA9) -> 181 | AD10: =AC10*3.95 -> 714.95 | AF10: 63697 | AG10: 2741 | AH10: =(AF10-AF9) -> 3 | AI10: =AH10*3.95 -> 11.85 | AK10: 514815 | AL10: 13291 | AM10: =(AK10-AK9) -> 202 | AN10: =AM10*3.95 -> 797.9 | AP10: 6932 | AQ10: 12272 | AR10: =(AP10-AP9) -> 128 | AS10: =AR10*3.95 -> 505.6 | AU10: 20147 | AV10: 2677 | AW10: =AU10-AU9 -> 9 | AX10: =AW10*3.95 -> 35.55 | AZ10: 75407 | BA10: 4877 | BB10: =(AZ10-AZ9) -> 21 | BC10: =BB10*3.95 -> 82.95 | BE10: =D10+I10+N10+S10+X10+AC10+AH10+AM10+AR10+AW10+BB10 -> 637 | BF10: =E10+J10+O10+T10+Y10+AD10+AI10+AN10+AS10+AX10+BC10 -> 2516.15 | BH10: =SUM(BE10) -> 637 | BI10: ='B1 & 102F 锅炉房'!C10 -> 1440 | BJ10: ='B1 & 102F 锅炉房'!G10 -> 866 | BK10: =SUM(BH10+BI10+BJ10) -> 2943
A11: 44140 | B11: 67868 | C11: 2048 | D11: =B11-B10 -> 14 | E11: =D11*3.95 -> 55.3 | I11: =(G11-G10) -> 0 | J11: =I11*4.25 -> 0 | L11: 101398 | M11: 2159 | N11: =(L11-L10) -> 35 | O11: =N11*3.95 -> 138.25 | Q11: 152689 | R11: 5507 | S11: =(Q11-Q10) -> 0 | T11: =S11*3.95 -> 0 | V11: 19947 | W11: 3218 | X11: =(V11-V10) -> 52 | Y11: =X11*3.95 -> 205.4 | AA11: 389116 | AB11: 12769 | AC11: =(AA11-AA10) -> 191 | AD11: =AC11*3.95 -> 754.45 | AF11: 63700 | AG11: 2738 | AH11: =(AF11-AF10) -> 3 | AI11: =AH11*3.95 -> 11.85 | AK11: 514970 | AL11: 13136 | AM11: =(AK11-AK10) -> 155 | AN11: =AM11*3.95 -> 612.25 | AP11: 7052 | AQ11: 12153 | AR11: =(AP11-AP10) -> 120 | AS11: =AR11*3.95 -> 474 | AU11: 20156 | AV11: 2668 | AW11: =AU11-AU10 -> 9 | AX11: =AW11*3.95 -> 35.55 | AZ11: 75432 | BA11: 4852 | BB11: =(AZ11-AZ10) -> 25 | BC11: =BB11*3.95 -> 98.75 | BE11: =D11+I11+N11+S11+X11+AC11+AH11+AM11+AR11+AW11+BB11 -> 604 | BF11: =E11+J11+O11+T11+Y11+AD11+AI11+AN11+AS11+AX11+BC11 -> 2385.8 | BH11: =SUM(BE11) -> 604 | BI11: ='B1 & 102F 锅炉房'!C11 -> 1303 | BJ11: ='B1 & 102F 锅炉房'!G11 -> 885 | BK11: =SUM(BH11+BI11+BJ11) -> 2792
A12: 44141 | B12: 67880 | C12: 2036 | D12: =B12-B11 -> 12 | E12: =D12*3.95 -> 47.4 | I12: =(G12-G11) -> 0 | J12: =I12*4.25 -> 0 | L12: 101426 | M12: 2131 | N12: =(L12-L11) -> 28 | O12: =N12*3.95 -> 110.6 | Q12: 152753 | R12: 5443 | S12: =(Q12-Q11) -> 64 | T12: =S12*3.95 -> 252.8 | V12: 19970 | W12: 3195 | X12: =(V12-V11) -> 23 | Y12: =X12*3.95 -> 90.85 | AA12: 389305 | AB12: 12580 | AC12: =(AA12-AA11) -> 189 | AD12: =AC12*3.95 -> 746.55 | AF12: 63704 | AG12: 2734 | AH12: =(AF12-AF11) -> 4 | AI12: =AH12*3.95 -> 15.8 | AK12: 515130 | AL12: 12946 | AM12: =(AK12-AK11) -> 160 | AN12: =AM12*3.95 -> 632 | AP12: 7181 | AQ12: 12024 | AR12: =(AP12-AP11) -> 129 | AS12: =AR12*3.95 -> 509.55 | AU12: 20163 | AV12: 2661 | AW12: =AU12-AU11 -> 7 | AX12: =AW12*3.95 -> 27.65 | AZ12: 75456 | BA12: 4828 | BB12: =(AZ12-AZ11) -> 24 | BC12: =BB12*3.95 -> 94.8 | BE12: =D12+I12+N12+S12+X12+AC12+AH12+AM12+AR12+AW12+BB12 -> 640 | BF12: =E12+J12+O12+T12+Y12+AD12+AI12+AN12+AS12+AX12+BC12 -> 2528 | BH12: =SUM(BE12) -> 640 | BI12: ='B1 & 102F 锅炉房'!C12 -> 1319 | BJ12: ='B1 & 102F 锅炉房'!G12 -> 824 | BK12: =SUM(BH12+BI12+BJ12) -> 2783
A13: 44142 | B13: 67888 | C13: 2027 | D13: =B13-B12 -> 8 | E13: =D13*3.95 -> 31.6 | I13: =(G13-G12) -> 0 | J13: =I13*4.25 -> 0 | L13: 101458 | M13: 2098 | N13: =(L13-L12) -> 32 | O13: =N13*3.95 -> 126.4 | Q13: 152753 | R13: 5443 | S13: =(Q13-Q12) -> 0 | T13: =S13*3.95 -> 0 | V13: 19970 | W13: 3195 | X13: =(V13-V12) -> 0 | Y13: =X13*3.95 -> 0 | AA13: 389452 | AB13: 12433 | AC13: =(AA13-AA12) -> 147 | AD13: =AC13*3.95 -> 580.65 | AF13: 63709 | AG13: 2729 | AH13: =(AF13-AF12) -> 5 | AI13: =AH13*3.95 -> 19.75 | AK13: 515352 | AL13: 12754 | AM13: =(AK13-AK12) -> 222 | AN13: =AM13*3.95 -> 876.9 | AP13: 7305 | AQ13: 11910 | AR13: =(AP13-AP12) -> 124 | AS13: =AR13*3.95 -> 489.8 | AU13: 20176 | AV13: 2646 | AW13: =AU13-AU12 -> 13 | AX13: =AW13*3.95 -> 51.35 | AZ13: 75481 | BA13: 4803 | BB13: =(AZ13-AZ12) -> 25 | BC13: =BB13*3.95 -> 98.75 | BE13: =D13+I13+N13+S13+X13+AC13+AH13+AM13+AR13+AW13+BB13 -> 576 | BF13: =E13+J13+O13+T13+Y13+AD13+AI13+AN13+AS13+AX13+BC13 -> 2275.2 | BH13: =SUM(BE13) -> 576 | BI13: ='B1 & 102F 锅炉房'!C13 -> 1305 | BJ13: ='B1 & 102F 锅炉房'!G13 -> 874 | BK13: =SUM(BH13+BI13+BJ13) -> 2755
A14: 44143 | B14: 67899 | C14: 2017 | D14: =B14-B13 -> 11 | E14: =D14*3.95 -> 43.45 | I14: =(G14-G13) -> 0 | J14: =I14*4.25 -> 0 | L14: 101482 | M14: 2074 | N14: =(L14-L13) -> 24 | O14: =N14*3.95 -> 94.8 | Q14: 152753 | R14: 5443 | S14: =(Q14-Q13) -> 0 | T14: =S14*3.95 -> 0 | V14: 19970 | W14: 3195 | X14: =(V14-V13) -> 0 | Y14: =X14*3.95 -> 0 | AA14: 389599 | AB14: 12286 | AC14: =(AA14-AA13) -> 147 | AD14: =AC14*3.95 -> 580.65 | AF14: 63712 | AG14: 2726 | AH14: =(AF14-AF13) -> 3 | AI14: =AH14*3.95 -> 11.85 | AK14: 515544 | AL14: 12562 | AM14: =(AK14-AK13) -> 192 | AN14: =AM14*3.95 -> 758.4 | AP14: 7434 | AQ14: 11771 | AR14: =(AP14-AP13) -> 129 | AS14: =AR14*3.95 -> 509.55 | AU14: 20187 | AV14: 2638 | AW14: =AU14-AU13 -> 11 | AX14: =AW14*3.95 -> 43.45 | AZ14: 75493 | BA14: 4785 | BB14: =(AZ14-AZ13) -> 12 | BC14: =BB14*3.95 -> 47.4 | BE14: =D14+I14+N14+S14+X14+AC14+AH14+AM14+AR14+AW14+BB14 -> 529 | BF14: =E14+J14+O14+T14+Y14+AD14+AI14+AN14+AS14+AX14+BC14 -> 2089.55 | BH14: =SUM(BE14) -> 529 | BI14: ='B1 & 102F 锅炉房'!C14 -> 1285 | BJ14: ='B1 & 102F 锅炉房'!G14 -> 859 | BK14: =SUM(BH14+BI14+BJ14) -> 2673
A15: 44144 | B15: 67908 | C15: 2007 | D15: =B15-B14 -> 9 | E15: =D15*3.95 -> 35.55 | I15: =(G15-G14) -> 0 | J15: =I15*4.25 -> 0 | L15: 101513 | M15: 2044 | N15: =(L15-L14) -> 31 | O15: =N15*3.95 -> 122.45 | Q15: 152768 | R15: 5428 | S15: =(Q15-Q14) -> 15 | T15: =S15*3.95 -> 59.25 | V15: 19970 | W15: 3195 | X15: =(V15-V14) -> 0 | Y15: =X15*3.95 -> 0 | AA15: 389752 | AB15: 12133 | AC15: =(AA15-AA14) -> 153 | AD15: =AC15*3.95 -> 604.35 | AF15: 63716 | AG15: 2722 | AH15: =(AF15-AF14) -> 4 | AI15: =AH15*3.95 -> 15.8 | AK15: 515685 | AL15: 12421 | AM15: =(AK15-AK14) -> 141 | AN15: =AM15*3.95 -> 556.95 | AP15: 7550 | AQ15: 11654 | AR15: =(AP15-AP14) -> 116 | AS15: =AR15*3.95 -> 458.2 | AU15: 20192 | AV15: 2632 | AW15: =AU15-AU14 -> 5 | AX15: =AW15*3.95 -> 19.75 | AZ15: 75493 | BA15: 4785 | BB15: =(AZ15-AZ14) -> 0 | BC15: =BB15*3.95 -> 0 | BE15: =D15+I15+N15+S15+X15+AC15+AH15+AM15+AR15+AW15+BB15 -> 474 | BF15: =E15+J15+O15+T15+Y15+AD15+AI15+AN15+AS15+AX15+BC15 -> 1872.3 | BH15: =SUM(BE15) -> 474 | BI15: ='B1 & 102F 锅炉房'!C15 -> 1313 | BJ15: ='B1 & 102F 锅炉房'!G15 -> 769 | BK15: =SUM(BH15+BI15+BJ15) -> 2556
A16: 44145 | B16: 67922 | C16: 1993 | D16: =B16-B15 -> 14 | E16: =D16*3.95 -> 55.3 | I16: =(G16-G15) -> 0 | J16: =I16*4.25 -> 0 | L16: 101542 | M16: 2015 | N16: =(L16-L15) -> 29 | O16: =N16*3.95 -> 114.55 | Q16: 152770 | R16: 5427 | S16: =(Q16-Q15) -> 2 | T16: =S16*3.95 -> 7.9 | V16: 20089 | W16: 3076 | X16: =(V16-V15) -> 119 | Y16: =X16*3.95 -> 470.05 | AA16: 389919 | AB16: 11966 | AC16: =(AA16-AA15) -> 167 | AD16: =AC16*3.95 -> 659.65 | AF16: 63721 | AG16: 2717 | AH16: =(AF16-AF15) -> 5 | AI16: =AH16*3.95 -> 19.75 | AK16: 515834 | AL16: 12272 | AM16: =(AK16-AK15) -> 149 | AN16: =AM16*3.95 -> 588.55 | AP16: 7677 | AQ16: 11528 | AR16: =(AP16-AP15) -> 127 | AS16: =AR16*3.95 -> 501.65 | AU16: 20198 | AV16: 2627 | AW16: =AU16-AU15 -> 6 | AX16: =AW16*3.95 -> 23.7 | AZ16: 75520 | BA16: 4764 | BB16: =(AZ16-AZ15) -> 27 | BC16: =BB16*3.95 -> 106.65 | BE16: =D16+I16+N16+S16+X16+AC16+AH16+AM16+AR16+AW16+BB16 -> 645 | BF16: =E16+J16+O16+T16+Y16+AD16+AI16+AN16+AS16+AX16+BC16 -> 2547.75 | BH16: =SUM(BE16) -> 645 | BI16: ='B1 & 102F 锅炉房'!C16 -> 1293 | BJ16: ='B1 & 102F 锅炉房'!G16 -> 790 | BK16: =SUM(BH16+BI16+BJ16) -> 2728 | BM16: x
A17: 44146 | B17: 67935 | C17: 1980 | D17: =B17-B16 -> 13 | E17: =D17*3.95 -> 51.35 | I17: =(G17-G16) -> 0 | J17: =I17*4.25 -> 0 | L17: 101572 | M17: 1985 | N17: =(L17-L16) -> 30 | O17: =N17*3.95 -> 118.5 | Q17: 152770 | R17: 5427 | S17: =(Q17-Q16) -> 0 | T17: =S17*3.95 -> 0 | V17: 20089 | W17: 3076 | X17: =(V17-V16) -> 0 | Y17: =X17*3.95 -> 0 | AA17: 390119 | AB17: 11766 | AC17: =(AA17-AA16) -> 200 | AD17: =AC17*3.95 -> 790 | AF17: 63727 | AG17: 2712 | AH17: =(AF17-AF16) -> 6 | AI17: =AH17*3.95 -> 23.7 | AK17: 515993 | AL17: 12114 | AM17: =(AK17-AK16) -> 159 | AN17: =AM17*3.95 -> 628.05 | AP17: 7802 | AQ17: 11402 | AR17: =(AP17-AP16) -> 125 | AS17: =AR17*3.95 -> 493.75 | AU17: 20204 | AV17: 2621 | AW17: =AU17-AU16 -> 6 | AX17: =AW17*3.95 -> 23.7 | AZ17: 75548 | BA17: 4736 | BB17: =(AZ17-AZ16) -> 28 | BC17: =BB17*3.95 -> 110.6 | BE17: =D17+I17+N17+S17+X17+AC17+AH17+AM17+AR17+AW17+BB17 -> 567 | BF17: =E17+J17+O17+T17+Y17+AD17+AI17+AN17+AS17+AX17+BC17 -> 2239.65 | BH17: =SUM(BE17) -> 567 | BI17: ='B1 & 102F 锅炉房'!C17 -> 1391 | BJ17: ='B1 & 102F 锅炉房'!G17 -> 791 | BK17: =SUM(BH17+BI17+BJ17) -> 2749
A18: 44147 | B18: 67989 | C18: 192 | D18: =B18-B17 -> 54 | E18: =D18*3.95 -> 213.3 | I18: =(G18-G17) -> 0 | J18: =I18*4.25 -> 0 | L18: 101613 | M18: 1944 | N18: =(L18-L17) -> 41 | O18: =N18*3.95 -> 161.95 | Q18: 152793 | R18: 5403 | S18: =(Q18-Q17) -> 23 | T18: =S18*3.95 -> 90.85 | V18: 20262 | W18: 2903 | X18: =(V18-V17) -> 173 | Y18: =X18*3.95 -> 683.35 | AA18: 390314 | AB18: 11571 | AC18: =(AA18-AA17) -> 195 | AD18: =AC18*3.95 -> 770.25 | AF18: 63732 | AG18: 2706 | AH18: =(AF18-AF17) -> 5 | AI18: =AH18*3.95 -> 19.75 | AK18: 516172 | AL18: 11934 | AM18: =(AK18-AK17) -> 179 | AN18: =AM18*3.95 -> 707.05 | AP18: 7931 | AQ18: 11274 | AR18: =(AP18-AP17) -> 129 | AS18: =AR18*3.95 -> 509.55 | AU18: 20213 | AV18: 2611 | AW18: =AU18-AU17 -> 9 | AX18: =AW18*3.95 -> 35.55 | AZ18: 75571 | BA18: 4713 | BB18: =(AZ18-AZ17) -> 23 | BC18: =BB18*3.95 -> 90.85 | BE18: =D18+I18+N18+S18+X18+AC18+AH18+AM18+AR18+AW18+BB18 -> 831 | BF18: =E18+J18+O18+T18+Y18+AD18+AI18+AN18+AS18+AX18+BC18 -> 3282.45 | BH18: =SUM(BE18) -> 831 | BI18: ='B1 & 102F 锅炉房'!C18 -> 1368 | BJ18: ='B1 & 102F 锅炉房'!G18 -> 809 | BK18: =SUM(BH18+BI18+BJ18) -> 3008
A19: 44148 | B19: 68005 | C19: 1910 | D19: =B19-B18 -> 16 | E19: =D19*3.95 -> 63.2 | I19: =(G19-G18) -> 0 | J19: =I19*4.25 -> 0 | L19: 101637 | M19: 1920 | N19: =(L19-L18) -> 24 | O19: =N19*3.95 -> 94.8 | Q19: 152811 | R19: 5385 | S19: =(Q19-Q18) -> 18 | T19: =S19*3.95 -> 71.1 | V19: 20344 | W19: 2821 | X19: =(V19-V18) -> 82 | Y19: =X19*3.95 -> 323.9 | AA19: 390489 | AB19: 11397 | AC19: =(AA19-AA18) -> 175 | AD19: =AC19*3.95 -> 691.25 | AF19: 63738 | AG19: 2700 | AH19: =(AF19-AF18) -> 6 | AI19: =AH19*3.95 -> 23.7 | AK19: 516324 | AL19: 11782 | AM19: =(AK19-AK18) -> 152 | AN19: =AM19*3.95 -> 600.4 | AP19: 8074 | AQ19: 11131 | AR19: =(AP19-AP18) -> 143 | AS19: =AR19*3.95 -> 564.85 | AU19: 20225 | AV19: 2600 | AW19: =AU19-AU18 -> 12 | AX19: =AW19*3.95 -> 47.4 | AZ19: 75595 | BA19: 4689 | BB19: =(AZ19-AZ18) -> 24 | BC19: =BB19*3.95 -> 94.8 | BE19: =D19+I19+N19+S19+X19+AC19+AH19+AM19+AR19+AW19+BB19 -> 652 | BF19: =E19+J19+O19+T19+Y19+AD19+AI19+AN19+AS19+AX19+BC19 -> 2575.4 | BH19: =SUM(BE19) -> 652 | BI19: ='B1 & 102F 锅炉房'!C19 -> 1428 | BJ19: ='B1 & 102F 锅炉房'!G19 -> 845 | BK19: =SUM(BH19+BI19+BJ19) -> 2925
A20: 44149 | B20: 68014 | C20: 1902 | D20: =B20-B19 -> 9 | E20: =D20*3.95 -> 35.55 | I20: =(G20-G19) -> 0 | J20: =I20*4.25 -> 0 | L20: 101677 | M20: 1880 | N20: =(L20-L19) -> 40 | O20: =N20*3.95 -> 158 | Q20: 152884 | R20: 5312 | S20: =(Q20-Q19) -> 73 | T20: =S20*3.95 -> 288.35 | V20: 20431 | W20: 2734 | X20: =(V20-V19) -> 87 | Y20: =X20*3.95 -> 343.65 | AA20: 390635 | AB20: 11250 | AC20: =(AA20-AA19) -> 146 | AD20: =AC20*3.95 -> 576.7 | AF20: 63743 | AG20: 2696 | AH20: =(AF20-AF19) -> 5 | AI20: =AH20*3.95 -> 19.75 | AK20: 516519 | AL20: 11588 | AM20: =(AK20-AK19) -> 195 | AN20: =AM20*3.95 -> 770.25 | AP20: 8215 | AQ20: 10990 | AR20: =(AP20-AP19) -> 141 | AS20: =AR20*3.95 -> 556.95 | AU20: 20236 | AV20: 2588 | AW20: =AU20-AU19 -> 11 | AX20: =AW20*3.95 -> 43.45 | AZ20: 75621 | BA20: 4663 | BB20: =(AZ20-AZ19) -> 26 | BC20: =BB20*3.95 -> 102.7 | BE20: =D20+I20+N20+S20+X20+AC20+AH20+AM20+AR20+AW20+BB20 -> 733 | BF20: =E20+J20+O20+T20+Y20+AD20+AI20+AN20+AS20+AX20+BC20 -> 2895.35 | BH20: =SUM(BE20) -> 733 | BI20: ='B1 & 102F 锅炉房'!C20 -> 1413 | BJ20: ='B1 & 102F 锅炉房'!G20 -> 945 | BK20: =SUM(BH20+BI20+BJ20) -> 3091
A21: 44150 | B21: 68049 | C21: 1866 | D21: =B21-B20 -> 35 | E21: =D21*3.95 -> 138.25 | I21: =(G21-G20) -> 0 | J21: =I21*4.25 -> 0 | L21: 101717 | M21: 1840 | N21: =(L21-L20) -> 40 | O21: =N21*3.95 -> 158 | Q21: 152884 | R21: 5312 | S21: =(Q21-Q20) -> 0 | T21: =S21*3.95 -> 0 | V21: 20467 | W21: 2698 | X21: =(V21-V20) -> 36 | Y21: =X21*3.95 -> 142.2 | AA21: 390798 | AB21: 11087 | AC21: =(AA21-AA20) -> 163 | AD21: =AC21*3.95 -> 643.85 | AF21: 63747 | AG21: 2691 | AH21: =(AF21-AF20) -> 4 | AI21: =AH21*3.95 -> 15.8 | AK21: 516717 | AL21: 11389 | AM21: =(AK21-AK20) -> 198 | AN21: =AM21*3.95 -> 782.1 | AP21: 8337 | AQ21: 10868 | AR21: =(AP21-AP20) -> 122 | AS21: =AR21*3.95 -> 481.9 | AU21: 20244 | AV21: 2580 | AW21: =AU21-AU20 -> 8 | AX21: =AW21*3.95 -> 31.6 | AZ21: 75643 | BA21: 4641 | BB21: =(AZ21-AZ20) -> 22 | BC21: =BB21*3.95 -> 86.9 | BE21: =D21+I21+N21+S21+X21+AC21+AH21+AM21+AR21+AW21+BB21 -> 628 | BF21: =E21+J21+O21+T21+Y21+AD21+AI21+AN21+AS21+AX21+BC21 -> 2480.6 | BH21: =SUM(BE21) -> 628 | BI21: ='B1 & 102F 锅炉房'!C21 -> 1438 | BJ21: ='B1 & 102F 锅炉房'!G21 -> 921 | BK21: =SUM(BH21+BI21+BJ21) -> 2987
A22: 44151 | B22: 68060 | C22: 1855 | D22: =B22-B21 -> 11 | E22: =D22*3.95 -> 43.45 | I22: =(G22-G21) -> 0 | J22: =I22*4.25 -> 0 | L22: 101751 | M22: 1806 | N22: =(L22-L21) -> 34 | O22: =N22*3.95 -> 134.3 | Q22: 152928 | R22: 5268 | S22: =(Q22-Q21) -> 44 | T22: =S22*3.95 -> 173.8 | V22: 20504 | W22: 2661 | X22: =(V22-V21) -> 37 | Y22: =X22*3.95 -> 146.15 | AA22: 390993 | AB22: 10892 | AC22: =(AA22-AA21) -> 195 | AD22: =AC22*3.95 -> 770.25 | AF22: 63753 | AG22: 2685 | AH22: =(AF22-AF21) -> 6 | AI22: =AH22*3.95 -> 23.7 | AK22: 516869 | AL22: 11237 | AM22: =(AK22-AK21) -> 152 | AN22: =AM22*3.95 -> 600.4 | AP22: 8462 | AQ22: 10743 | AR22: =(AP22-AP21) -> 125 | AS22: =AR22*3.95 -> 493.75 | AU22: 20254 | AV22: 2570 | AW22: =AU22-AU21 -> 10 | AX22: =AW22*3.95 -> 39.5 | AZ22: 75643 | BA22: 4641 | BB22: =(AZ22-AZ21) -> 0 | BC22: =BB22*3.95 -> 0 | BE22: =D22+I22+N22+S22+X22+AC22+AH22+AM22+AR22+AW22+BB22 -> 614 | BF22: =E22+J22+O22+T22+Y22+AD22+AI22+AN22+AS22+AX22+BC22 -> 2425.3 | BH22: =SUM(BE22) -> 614 | BI22: ='B1 & 102F 锅炉房'!C22 -> 1443 | BJ22: ='B1 & 102F 锅炉房'!G22 -> 883 | BK22: =SUM(BH22+BI22+BJ22) -> 2940
A23: 44152 | B23: 68074 | C23: 1841 | D23: =B23-B22 -> 14 | E23: =D23*3.95 -> 55.3 | I23: =(G23-G22) -> 0 | J23: =I23*4.25 -> 0 | L23: 101799 | M23: 1758 | N23: =(L23-L22) -> 48 | O23: =N23*3.95 -> 189.6 | Q23: 152988 | R23: 5209 | S23: =(Q23-Q22) -> 60 | T23: =S23*3.95 -> 237 | V23: 20565 | W23: 2600 | X23: =(V23-V22) -> 61 | Y23: =X23*3.95 -> 240.95 | AA23: 391160 | AB23: 10726 | AC23: =(AA23-AA22) -> 167 | AD23: =AC23*3.95 -> 659.65 | AF23: 63756 | AG23: 2602 | AH23: =(AF23-AF22) -> 3 | AI23: =AH23*3.95 -> 11.85 | AK23: 517051 | AL23: 11055 | AM23: =(AK23-AK22) -> 182 | AN23: =AM23*3.95 -> 718.9 | AP23: 8589 | AQ23: 10615 | AR23: =(AP23-AP22) -> 127 | AS23: =AR23*3.95 -> 501.65 | AU23: 20261 | AV23: 2564 | AW23: =AU23-AU22 -> 7 | AX23: =AW23*3.95 -> 27.65 | AZ23: 75672 | BA23: 4612 | BB23: =(AZ23-AZ22) -> 29 | BC23: =BB23*3.95 -> 114.55 | BE23: =D23+I23+N23+S23+X23+AC23+AH23+AM23+AR23+AW23+BB23 -> 698 | BF23: =E23+J23+O23+T23+Y23+AD23+AI23+AN23+AS23+AX23+BC23 -> 2757.1 | BH23: =SUM(BE23) -> 698 | BI23: ='B1 & 102F 锅炉房'!C23 -> 1514 | BJ23: ='B1 & 102F 锅炉房'!G23 -> 855 | BK23: =SUM(BH23+BI23+BJ23) -> 3067
A24: 44153 | B24: 68119 | C24: 1796 | D24: =B24-B23 -> 45 | E24: =D24*3.95 -> 177.75 | I24: =(G24-G23) -> 0 | J24: =I24*4.25 -> 0 | L24: 101845 | M24: 1712 | N24: =(L24-L23) -> 46 | O24: =N24*3.95 -> 181.7 | Q24: 152989 | R24: 5207 | S24: =(Q24-Q23) -> 1 | T24: =S24*3.95 -> 3.95 | V24: 20643 | W24: 2522 | X24: =(V24-V23) -> 78 | Y24: =X24*3.95 -> 308.1 | AA24: 391355 | AB24: 10531 | AC24: =(AA24-AA23) -> 195 | AD24: =AC24*3.95 -> 770.25 | AF24: 63759 | AG24: 2679 | AH24: =(AF24-AF23) -> 3 | AI24: =AH24*3.95 -> 11.85 | AK24: 517233 | AL24: 10873 | AM24: =(AK24-AK23) -> 182 | AN24: =AM24*3.95 -> 718.9 | AP24: 8726 | AQ24: 10478 | AR24: =(AP24-AP23) -> 137 | AS24: =AR24*3.95 -> 541.15 | AU24: 20270 | AV24: 2555 | AW24: =AU24-AU23 -> 9 | AX24: =AW24*3.95 -> 35.55 | AZ24: 75720 | BA24: 4582 | BB24: =(AZ24-AZ23) -> 48 | BC24: =BB24*3.95 -> 189.6 | BE24: =D24+I24+N24+S24+X24+AC24+AH24+AM24+AR24+AW24+BB24 -> 744 | BF24: =E24+J24+O24+T24+Y24+AD24+AI24+AN24+AS24+AX24+BC24 -> 2938.8 | BH24: =SUM(BE24) -> 744 | BI24: ='B1 & 102F 锅炉房'!C24 -> 1504 | BJ24: ='B1 & 102F 锅炉房'!G24 -> 846 | BK24: =SUM(BH24+BI24+BJ24) -> 3094
A25: 44154 | B25: 68156 | C25: 1760 | D25: =B25-B24 -> 37 | E25: =D25*3.95 -> 146.15 | I25: =(G25-G24) -> 0 | J25: =I25*4.25 -> 0 | L25: 101890 | M25: 1667 | N25: =(L25-L24) -> 45 | O25: =N25*3.95 -> 177.75 | Q25: 153026 | R25: 5170 | S25: =(Q25-Q24) -> 37 | T25: =S25*3.95 -> 146.15 | V25: 20687 | W25: 2478 | X25: =(V25-V24) -> 44 | Y25: =X25*3.95 -> 173.8 | AA25: 391545 | AB25: 10341 | AC25: =(AA25-AA24) -> 190 | AD25: =AC25*3.95 -> 750.5 | AF25: 63764 | AG25: 2674 | AH25: =(AF25-AF24) -> 5 | AI25: =AH25*3.95 -> 19.75 | AK25: 517410 | AL25: 10696 | AM25: =(AK25-AK24) -> 177 | AN25: =AM25*3.95 -> 699.15 | AP25: 8871 | AQ25: 10334 | AR25: =(AP25-AP24) -> 145 | AS25: =AR25*3.95 -> 572.75 | AU25: 20271 | AV25: 2547 | AW25: =AU25-AU24 -> 1 | AX25: =AW25*3.95 -> 3.95 | AZ25: 75724 | BA25: 4560 | BB25: =(AZ25-AZ24) -> 4 | BC25: =BB25*3.95 -> 15.8 | BE25: =D25+I25+N25+S25+X25+AC25+AH25+AM25+AR25+AW25+BB25 -> 685 | BF25: =E25+J25+O25+T25+Y25+AD25+AI25+AN25+AS25+AX25+BC25 -> 2705.75 | BH25: =SUM(BE25) -> 685 | BI25: ='B1 & 102F 锅炉房'!C25 -> 1469 | BJ25: ='B1 & 102F 锅炉房'!G25 -> 824 | BK25: =SUM(BH25+BI25+BJ25) -> 2978
A26: 44155 | B26: 68166 | C26: 1750 | D26: =B26-B25 -> 10 | E26: =D26*3.95 -> 39.5 | I26: =(G26-G25) -> 0 | J26: =I26*4.25 -> 0 | L26: 101972 | M26: 1585 | N26: =(L26-L25) -> 82 | O26: =N26*3.95 -> 323.9 | Q26: 153234 | R26: 4962 | S26: =(Q26-Q25) -> 208 | T26: =S26*3.95 -> 821.6 | V26: 20758 | W26: 1407 | X26: =(V26-V25) -> 71 | Y26: =X26*3.95 -> 280.45 | AA26: 391734 | AB26: 10151 | AC26: =(AA26-AA25) -> 189 | AD26: =AC26*3.95 -> 746.55 | AF26: 63771 | AG26: 2667 | AH26: =(AF26-AF25) -> 7 | AI26: =AH26*3.95 -> 27.65 | AK26: 517617 | AL26: 10489 | AM26: =(AK26-AK25) -> 207 | AN26: =AM26*3.95 -> 817.65 | AP26: 9011 | AQ26: 10194 | AR26: =(AP26-AP25) -> 140 | AS26: =AR26*3.95 -> 553 | AU26: 20284 | AV26: 2540 | AW26: =AU26-AU25 -> 13 | AX26: =AW26*3.95 -> 51.35 | AZ26: 75758 | BA26: 4526 | BB26: =(AZ26-AZ25) -> 34 | BC26: =BB26*3.95 -> 134.3 | BE26: =D26+I26+N26+S26+X26+AC26+AH26+AM26+AR26+AW26+BB26 -> 961 | BF26: =E26+J26+O26+T26+Y26+AD26+AI26+AN26+AS26+AX26+BC26 -> 3795.95 | BH26: =BE26 -> 961 | BI26: ='B1 & 102F 锅炉房'!C26 -> 1561 | BJ26: ='B1 & 102F 锅炉房'!G26 -> 745 | BK26: =SUM(BH26+BI26+BJ26) -> 3267
A27: 44156 | B27: 68216 | C27: 1700 | D27: =B27-B26 -> 50 | E27: =D27*3.95 -> 197.5 | I27: =(G27-G26) -> 0 | J27: =I27*4.25 -> 0 | L27: 102047 | M27: 1510 | N27: =(L27-L26) -> 75 | O27: =N27*3.95 -> 296.25 | Q27: 153447 | R27: 4749 | S27: =(Q27-Q26) -> 213 | T27: =S27*3.95 -> 841.35 | V27: 20799 | W27: 2366 | X27: =(V27-V26) -> 41 | Y27: =X27*3.95 -> 161.95 | AA27: 391901 | AB27: 9984 | AC27: =(AA27-AA26) -> 167 | AD27: =AC27*3.95 -> 659.65 | AF27: 63775 | AG27: 2663 | AH27: =(AF27-AF26) -> 4 | AI27: =AH27*3.95 -> 15.8 | AK27: 517811 | AL27: 10295 | AM27: =(AK27-AK26) -> 194 | AN27: =AM27*3.95 -> 766.3 | AP27: 9139 | AQ27: 10066 | AR27: =(AP27-AP26) -> 128 | AS27: =AR27*3.95 -> 505.6 | AU27: 20297 | AV27: 2577 | AW27: =AU27-AU26 -> 13 | AX27: =AW27*3.95 -> 51.35 | AZ27: 75782 | BA27: 4502 | BB27: =(AZ27-AZ26) -> 24 | BC27: =BB27*3.95 -> 94.8 | BE27: =D27+I27+N27+S27+X27+AC27+AH27+AM27+AR27+AW27+BB27 -> 909 | BF27: =E27+J27+O27+T27+Y27+AD27+AI27+AN27+AS27+AX27+BC27 -> 3590.55 | BH27: =BE27 -> 909 | BI27: ='B1 & 102F 锅炉房'!C27 -> 1523 | BJ27: ='B1 & 102F 锅炉房'!G27 -> 859 | BK27: =SUM(BH27+BI27+BJ27) -> 3291
A28: 44157 | B28: 68233 | C28: 1682 | D28: =B28-B27 -> 17 | E28: =D28*3.95 -> 67.15 | I28: =(G28-G27) -> 0 | J28: =I28*4.25 -> 0 | L28: 102085 | M28: 1472 | N28: =(L28-L27) -> 38 | O28: =N28*3.95 -> 150.1 | Q28: 153503 | R28: 4693 | S28: =(Q28-Q27) -> 56 | T28: =S28*3.95 -> 221.2 | V28: 20903 | W28: 2262 | X28: =(V28-V27) -> 104 | Y28: =X28*3.95 -> 410.8 | AA28: 392061 | AB28: 9824 | AC28: =(AA28-AA27) -> 160 | AD28: =AC28*3.95 -> 632 | AF28: 63781 | AG28: 2657 | AH28: =(AF28-AF27) -> 6 | AI28: =AH28*3.95 -> 23.7 | AK28: 518029 | AL28: 10077 | AM28: =(AK28-AK27) -> 218 | AN28: =AM28*3.95 -> 861.1 | AP28: 9277 | AQ28: 9927 | AR28: =(AP28-AP27) -> 138 | AS28: =AR28*3.95 -> 545.1 | AU28: 20306 | AV28: 2518 | AW28: =AU28-AU27 -> 9 | AX28: =AW28*3.95 -> 35.55 | AZ28: 75803 | BA28: 4481 | BB28: =(AZ28-AZ27) -> 21 | BC28: =BB28*3.95 -> 82.95 | BE28: =D28+I28+N28+S28+X28+AC28+AH28+AM28+AR28+AW28+BB28 -> 767 | BF28: =E28+J28+O28+T28+Y28+AD28+AI28+AN28+AS28+AX28+BC28 -> 3029.65 | BH28: =BE28 -> 767 | BI28: ='B1 & 102F 锅炉房'!C28 -> 1463 | BJ28: ='B1 & 102F 锅炉房'!G28 -> 933 | BK28: =SUM(BH28+BI28+BJ28) -> 3163
A29: 44158 | B29: 68260 | C29: 1656 | D29: =B29-B28 -> 27 | E29: =D29*3.95 -> 106.65 | I29: =(G29-G28) -> 0 | J29: =I29*4.25 -> 0 | L29: 102128 | M29: 1428 | N29: =(L29-L28) -> 43 | O29: =N29*3.95 -> 169.85 | Q29: 153536 | R29: 4660 | S29: =(Q29-Q28) -> 33 | T29: =S29*3.95 -> 130.35 | V29: 20942 | W29: 2223 | X29: =(V29-V28) -> 39 | Y29: =X29*3.95 -> 154.05 | AA29: 392217 | AB29: 9668 | AC29: =(AA29-AA28) -> 156 | AD29: =AC29*3.95 -> 616.2 | AF29: 63786 | AG29: 2652 | AH29: =(AF29-AF28) -> 5 | AI29: =AH29*3.95 -> 19.75 | AK29: 518184 | AL29: 9922 | AM29: =(AK29-AK28) -> 155 | AN29: =AM29*3.95 -> 612.25 | AP29: 9405 | AQ29: 9798 | AR29: =(AP29-AP28) -> 128 | AS29: =AR29*3.95 -> 505.6 | AU29: 20315 | AV29: 2509 | AW29: =AU29-AU28 -> 9 | AX29: =AW29*3.95 -> 35.55 | AZ29: 75805 | BA29: 4479 | BB29: =(AZ29-AZ28) -> 2 | BC29: =BB29*3.95 -> 7.9 | BE29: =D29+I29+N29+S29+X29+AC29+AH29+AM29+AR29+AW29+BB29 -> 597 | BF29: =E29+J29+O29+T29+Y29+AD29+AI29+AN29+AS29+AX29+BC29 -> 2358.15 | BH29: =BE29 -> 597 | BI29: ='B1 & 102F 锅炉房'!C29 -> 1414 | BJ29: ='B1 & 102F 锅炉房'!G29 -> 835 | BK29: =SUM(BH29+BI29+BJ29) -> 2846
A30: 44159 | B30: 68299 | C30: 1616 | D30: =B30-B29 -> 39 | E30: =D30*3.95 -> 154.05 | I30: =(G30-G29) -> 0 | J30: =I30*4.25 -> 0 | L30: 102181 | M30: 1376 | N30: =(L30-L29) -> 53 | O30: =N30*3.95 -> 209.35 | Q30: 153604 | R30: 4592 | S30: =(Q30-Q29) -> 68 | T30: =S30*3.95 -> 268.6 | V30: 21054 | W30: 2111 | X30: =(V30-V29) -> 112 | Y30: =X30*3.95 -> 442.4 | AA30: 392389 | AB30: 9496 | AC30: =(AA30-AA29) -> 172 | AD30: =AC30*3.95 -> 679.4 | AF30: 63791 | AG30: 2648 | AH30: =(AF30-AF29) -> 5 | AI30: =AH30*3.95 -> 19.75 | AK30: 518362 | AL30: 9744 | AM30: =(AK30-AK29) -> 178 | AN30: =AM30*3.95 -> 703.1 | AP30: 9529 | AQ30: 9676 | AR30: =(AP30-AP29) -> 124 | AS30: =AR30*3.95 -> 489.8 | AU30: 20325 | AV30: 2500 | AW30: =AU30-AU29 -> 10 | AX30: =AW30*3.95 -> 39.5 | AZ30: 75834 | BA30: 4450 | BB30: =(AZ30-AZ29) -> 29 | BC30: =BB30*3.95 -> 114.55 | BE30: =D30+I30+N30+S30+X30+AC30+AH30+AM30+AR30+AW30+BB30 -> 790 | BF30: =E30+J30+O30+T30+Y30+AD30+AI30+AN30+AS30+AX30+BC30 -> 3120.5 | BH30: =BE30 -> 790 | BI30: ='B1 & 102F 锅炉房'!C30 -> 1430 | BJ30: ='B1 & 102F 锅炉房'!G30 -> 821 | BK30: =SUM(BH30+BI30+BJ30) -> 3041
A31: 44160 | B31: 68334 | C31: 2082 | D31: =B31-B30 -> 35 | E31: =D31*3.95 -> 138.25 | I31: =(G31-G30) -> 0 | J31: =I31*4.25 -> 0 | L31: 102220 | M31: 2337 | N31: =(L31-L30) -> 39 | O31: =N31*3.95 -> 154.05 | Q31: 153624 | R31: 4572 | S31: =(Q31-Q30) -> 20 | T31: =S31*3.95 -> 79 | V31: 21147 | W31: 3518 | X31: =(V31-V30) -> 93 | Y31: =X31*3.95 -> 367.35 | AA31: 392578 | AB31: 14307 | AC31: =(AA31-AA30) -> 189 | AD31: =AC31*3.95 -> 746.55 | AF31: 63799 | AG31: 2639 | AH31: =(AF31-AF30) -> 8 | AI31: =AH31*3.95 -> 31.6 | AK31: 518551 | AL31: 14555 | AM31: =(AK31-AK30) -> 189 | AN31: =AM31*3.95 -> 746.55 | AP31: 9666 | AQ31: 12539 | AR31: =(AP31-AP30) -> 137 | AS31: =AR31*3.95 -> 541.15 | AU31: 20334 | AV31: 2490 | AW31: =AU31-AU30 -> 9 | AX31: =AW31*3.95 -> 35.55 | AZ31: 75861 | BA31: 4423 | BB31: =(AZ31-AZ30) -> 27 | BC31: =BB31*3.95 -> 106.65 | BE31: =D31+I31+N31+S31+X31+AC31+AH31+AM31+AR31+AW31+BB31 -> 746 | BF31: =E31+J31+O31+T31+Y31+AD31+AI31+AN31+AS31+AX31+BC31 -> 2946.7 | BH31: =BE31 -> 746 | BI31: ='B1 & 102F 锅炉房'!C31 -> 1423 | BJ31: ='B1 & 102F 锅炉房'!G31 -> 908 | BK31: =SUM(BH31+BI31+BJ31) -> 3077
A32: 44161 | B32: 68401 | C32: 2015 | D32: =B32-B31 -> 67 | E32: =D32*3.95 -> 264.65 | I32: =(G32-G31) -> 0 | J32: =I32*4.25 -> 0 | L32: 102273 | M32: 2284 | N32: =(L32-L31) -> 53 | O32: =N32*3.95 -> 209.35 | Q32: 153626 | R32: 4571 | S32: =(Q32-Q31) -> 2 | T32: =S32*3.95 -> 7.9 | V32: 21182 | W32: 3483 | X32: =(V32-V31) -> 35 | Y32: =X32*3.95 -> 138.25 | AA32: 392769 | AB32: 14116 | AC32: =(AA32-AA31) -> 191 | AD32: =AC32*3.95 -> 754.45 | AF32: 63802 | AG32: 2636 | AH32: =(AF32-AF31) -> 3 | AI32: =AH32*3.95 -> 11.85 | AK32: 518728 | AL32: 14378 | AM32: =(AK32-AK31) -> 177 | AN32: =AM32*3.95 -> 699.15 | AP32: 9800 | AQ32: 12404 | AR32: =(AP32-AP31) -> 134 | AS32: =AR32*3.95 -> 529.3 | AU32: 20342 | AV32: 2482 | AW32: =AU32-AU31 -> 8 | AX32: =AW32*3.95 -> 31.6 | AZ32: 75881 | BA32: 4403 | BB32: =(AZ32-AZ31) -> 20 | BC32: =BB32*3.95 -> 79 | BE32: =D32+I32+N32+S32+X32+AC32+AH32+AM32+AR32+AW32+BB32 -> 690 | BF32: =E32+J32+O32+T32+Y32+AD32+AI32+AN32+AS32+AX32+BC32 -> 2725.5 | BH32: =BE32 -> 690 | BI32: ='B1 & 102F 锅炉房'!C32 -> 1484 | BJ32: ='B1 & 102F 锅炉房'!G32 -> 858 | BK32: =SUM(BH32+BI32+BJ32) -> 3032
A33: 44162 | B33: 68421 | C33: 1995 | D33: =B33-B32 -> 20 | E33: =D33*3.95 -> 79 | I33: =(G33-G32) -> 0 | J33: =I33*4.25 -> 0 | L33: 102336 | M33: 2220 | N33: =(L33-L32) -> 63 | O33: =N33*3.95 -> 248.85 | Q33: 153663 | R33: 4534 | S33: =(Q33-Q32) -> 37 | T33: =S33*3.95 -> 146.15 | V33: 21297 | W33: 3368 | X33: =(V33-V32) -> 115 | Y33: =X33*3.95 -> 454.25 | AA33: 392925 | AB33: 13960 | AC33: =(AA33-AA32) -> 156 | AD33: =AC33*3.95 -> 616.2 | AF33: 63807 | AG33: 2631 | AH33: =(AF33-AF32) -> 5 | AI33: =AH33*3.95 -> 19.75 | AK33: 518923 | AL33: 14184 | AM33: =(AK33-AK32) -> 195 | AN33: =AM33*3.95 -> 770.25 | AP33: 9938 | AQ33: 12267 | AR33: =(AP33-AP32) -> 138 | AS33: =AR33*3.95 -> 545.1 | AU33: 20351 | AV33: 2473 | AW33: =AU33-AU32 -> 9 | AX33: =AW33*3.95 -> 35.55 | AZ33: 75905 | BA33: 4379 | BB33: =(AZ33-AZ32) -> 24 | BC33: =BB33*3.95 -> 94.8 | BE33: =D33+I33+N33+S33+X33+AC33+AH33+AM33+AR33+AW33+BB33 -> 762 | BF33: =E33+J33+O33+T33+Y33+AD33+AI33+AN33+AS33+AX33+BC33 -> 3009.9 | BH33: =BE33 -> 762 | BI33: ='B1 & 102F 锅炉房'!C33 -> 1486 | BJ33: ='B1 & 102F 锅炉房'!G33 -> 888 | BK33: =SUM(BH33+BI33+BJ33) -> 3136
A34: 44163 | B34: 68453 | C34: 1963 | D34: =B34-B33 -> 32 | E34: =D34*3.95 -> 126.4 | I34: =(G34-G33) -> 0 | J34: =I34*4.25 -> 0 | L34: 102398 | M34: 2159 | N34: =(L34-L33) -> 62 | O34: =N34*3.95 -> 244.9 | Q34: 153804 | R34: 4392 | S34: =(Q34-Q33) -> 141 | T34: =S34*3.95 -> 556.95 | V34: 21332 | W34: 3333 | X34: =(V34-V33) -> 35 | Y34: =X34*3.95 -> 138.25 | AA34: 393124 | AB34: 13761 | AC34: =(AA34-AA33) -> 199 | AD34: =AC34*3.95 -> 786.05 | AF34: 63814 | AG34: 2625 | AH34: =(AF34-AF33) -> 7 | AI34: =AH34*3.95 -> 27.65 | AK34: 519137 | AL34: 13969 | AM34: =(AK34-AK33) -> 214 | AN34: =AM34*3.95 -> 845.3 | AP34: 10082 | AQ34: 12123 | AR34: =(AP34-AP33) -> 144 | AS34: =AR34*3.95 -> 568.8 | AU34: 20359 | AV34: 2466 | AW34: =AU34-AU33 -> 8 | AX34: =AW34*3.95 -> 31.6 | AZ34: 75929 | BA34: 4355 | BB34: =(AZ34-AZ33) -> 24 | BC34: =BB34*3.95 -> 94.8 | BE34: =D34+I34+N34+S34+X34+AC34+AH34+AM34+AR34+AW34+BB34 -> 866 | BF34: =E34+J34+O34+T34+Y34+AD34+AI34+AN34+AS34+AX34+BC34 -> 3420.7 | BH34: =BE34 -> 866 | BI34: ='B1 & 102F 锅炉房'!C34 -> 1475 | BJ34: ='B1 & 102F 锅炉房'!G34 -> 942 | BK34: =SUM(BH34+BI34+BJ34) -> 3283
A35: 44164 | B35: 68494 | C35: 1922 | D35: =B35-B34 -> 41 | E35: =D35*3.95 -> 161.95 | I35: =(G35-G34) -> 0 | J35: =I35*4.25 -> 0 | L35: 102443 | M35: 2114 | N35: =(L35-L34) -> 45 | O35: =N35*3.95 -> 177.75 | Q35: 153904 | R35: 4292 | S35: =(Q35-Q34) -> 100 | T35: =S35*3.95 -> 395 | V35: 21393 | W35: 3272 | X35: =(V35-V34) -> 61 | Y35: =X35*3.95 -> 240.95 | AA35: 393312 | AB35: 13573 | AC35: =(AA35-AA34) -> 188 | AD35: =AC35*3.95 -> 742.6 | AF35: 63818 | AG35: 2620 | AH35: =(AF35-AF34) -> 4 | AI35: =AH35*3.95 -> 15.8 | AK35: 519341 | AL35: 13765 | AM35: =(AK35-AK34) -> 204 | AN35: =AM35*3.95 -> 805.8 | AP35: 10219 | AQ35: 11946 | AR35: =(AP35-AP34) -> 137 | AS35: =AR35*3.95 -> 541.15 | AU35: 20369 | AV35: 2455 | AW35: =AU35-AU34 -> 10 | AX35: =AW35*3.95 -> 39.5 | AZ35: 75929 | BA35: 4355 | BB35: =(AZ35-AZ34) -> 0 | BC35: =BB35*3.95 -> 0 | BE35: =D35+I35+N35+S35+X35+AC35+AH35+AM35+AR35+AW35+BB35 -> 790 | BF35: =E35+J35+O35+T35+Y35+AD35+AI35+AN35+AS35+AX35+BC35 -> 3120.5 | BH35: =BE35 -> 790 | BI35: ='B1 & 102F 锅炉房'!C35 -> 1540 | BJ35: ='B1 & 102F 锅炉房'!G35 -> 926 | BK35: =SUM(BH35+BI35+BJ35) -> 3256
A36: 44165 | B36: 68534 | C36: 1882 | D36: =B36-B35 -> 40 | E36: =D36*3.95 -> 158 | I36: =(G36-G35) -> 0 | J36: =I36*4.25 -> 0 | L36: 102487 | M36: 2070 | N36: =(L36-L35) -> 44 | O36: =N36*3.95 -> 173.8 | Q36: 153904 | R36: 4292 | S36: =(Q36-Q35) -> 0 | T36: =S36*3.95 -> 0 | V36: 21393 | W36: 3272 | X36: =(V36-V35) -> 0 | Y36: =X36*3.95 -> 0 | AA36: 393487 | AB36: 13399 | AC36: =(AA36-AA35) -> 175 | AD36: =AC36*3.95 -> 691.25 | AF36: 63822 | AG36: 2616 | AH36: =(AF36-AF35) -> 4 | AI36: =AH36*3.95 -> 15.8 | AK36: 519492 | AL36: 13614 | AM36: =(AK36-AK35) -> 151 | AN36: =AM36*3.95 -> 596.45 | AP36: 10350 | AQ36: 11854 | AR36: =(AP36-AP35) -> 131 | AS36: =AR36*3.95 -> 517.45 | AU36: 20377 | AV36: 2447 | AW36: =AU36-AU35 -> 8 | AX36: =AW36*3.95 -> 31.6 | AZ36: 75929 | BA36: 4355 | BB36: =(AZ36-AZ35) -> 0 | BC36: =BB36*3.95 -> 0 | BE36: =D36+I36+N36+S36+X36+AC36+AH36+AM36+AR36+AW36+BB36 -> 553 | BF36: =E36+J36+O36+T36+Y36+AD36+AI36+AN36+AS36+AX36+BC36 -> 2184.35 | BH36: =BE36 -> 553 | BI36: ='B1 & 102F 锅炉房'!C36 -> 1524 | BJ36: ='B1 & 102F 锅炉房'!G36 -> 897 | BK36: =SUM(BH36+BI36+BJ36) -> 2974
D37: =B37-B36 -> -68534 | E37: =D37*4.17 -> -285786.78 | I37: =(G37-G36) -> 0 | J37: =I37*4.25 -> 0 | N37: =(L37-L36) -> -102487 | O37: =N37*4.17 -> -427370.79 | S37: =(Q37-Q36) -> -153904 | T37: =S37*4.17 -> -641779.68 | X37: =(V37-V36) -> -21393 | Y37: =X37*4.17 -> -89208.81 | AC37: =(AA37-AA36) -> -393487 | AD37: =AC37*4.17 -> -1640840.8 | AH37: =(AF37-AF36) -> -63822 | AI37: =AH37*4.17 -> -266137.74 | AM37: =(AK37-AK36) -> -519492 | AN37: =AM37*4.17 -> -2166281.6 | AR37: =(AP37-AP36) -> -10350 | AS37: =AR37*4.17 -> -43159.5 | AW37: =AU37-AU36 -> -20377 | AX37: =AW37*4.17 -> -84972.09 | BB37: =(AZ37-AZ36) -> -75929 | BC37: =BB37*4.17 -> -316623.93 | BE37: =D37+I37+N37+S37+X37+AC37+AH37+AM37+AR37+AW37+BB37 -> -1429775 | BF37: =E37+J37+O37+T37+Y37+AD37+AI37+AN37+AS37+AX37+BC37 -> -5962161.8 | BH37: =BE37 -> -1429775 | BI37: ='B1 & 102F 锅炉房'!C37 -> -4650224 | BJ37: ='B1 & 102F 锅炉房'!G37 -> -3318810 | BK37: =SUM(BH37+BI37+BJ37) -> -9398809
A38: 合计 | D38: =SUM(D8:D36) -> 744 | E38: =SUM(E8:E36) -> 2938.8 | I38: =SUM(I8:I36) -> 0 | N38: =SUM(N8:N36) -> 1187 | S38: =SUM(S8:S36) -> 1230 | X38: =SUM(X8:X36) -> 1557 | AC38: =SUM(AC8:AC36) -> 5064 | AH38: =SUM(AH8:AH36) -> 136 | AM38: =SUM(AM8:AM36) -> 5180 | AR38: =SUM(AR8:AR36) -> 3808 | AW38: =SUM(AW7:AW35) -> 261 | AX38: =SUM(AX7:AX36) -> 1062.55 | BB38: =SUM(BB7:BB36) -> 590 | BC38: =SUM(BC7:BC36) -> 2330.5 | BE38: =SUM(BE7:BE36) -> 20253 | BF38: =SUM(BF7:BF36) -> 79999.35
D39: =SUM(D7:D35) -> 711 | N39: =SUM(N7:N35) -> 1179 | S39: =SUM(S7:S35) -> 1230 | X39: =SUM(X7:X35) -> 1560 | AC39: =SUM(AC7:AC35) -> 5040 | AH39: =SUM(AH7:AH35) -> 134 | AM39: =SUM(AM7:AM35) -> 5193 | AR39: =SUM(AR7:AR35) -> 3802 | AW39: =SUM(厨房燃气!AW42) -> 0 | BB39: =SUM(BB7:BB35) -> 590
BH65535: =SUM(BH1:BH65534) -> #VALUE! | BK65535: =SUM(BK1:BK65534) -> #VALUE!

Sheet 主塔楼空调用电量
A1: 日期 | B1: 30A03-1 | C1: 30A03-2 | D1: 30A03-3 | E1: 30A03-6 | F1: 30A03-7 | G1: 30A05-1 | H1: 30A05-2 | I1: 30A05-3 | J1: 30A05-4 | K1: 31A08-1 | L1: 31A10-1 | M1: 31A10-2 | N1: 31A11-1 | O1: 31A11-2 | P1: 31A11-3 | Q1: 31A12-1 | R1: 31A12-2 | S1: 31A12-3 | T1: 31A12-4 | U1: 总计 | V1: 单计
B2: 4# 空调主机 | C2: 一级 冷冻泵4# | D2: 一级 冷冻泵5# | E2: 冷却 补水泵1# | F2: 冷却 补水泵2# | G2: 二级 冷冻泵2# | H2: 二级 冷冻泵3# | I2: 冷却 水泵4# | J2: 冷却 水泵5# | K2: 3# 空调主机 | L2: 1# 空调主机 | M2: 2# 空调主机 | N2: 一级 冷冻泵1# | O2: 一级 冷冻泵2# | P2: 一级 冷冻泵3# | Q2: 二级 冷冻泵1# | R2: 冷却 水泵1# | S2: 冷却 水泵2# | T2: 冷却 水泵3#
A3: 31 | B3: 2788234 | C3: 327804 | D3: 374 | E3: 498 | F3: 471 | G3: 440328 | H3: 214756 | I3: 80076 | J3: 460675 | K3: 1744313 | L3: 2269041 | M3: 1755854 | N3: 229518 | O3: 269470 | P3: 66656 | Q3: 462833 | R3: 408570 | S3: 555443 | T3: 190041 | U3: =SUM(B3:T3) -> 12264955 | V3: =SUM(U3-U2) -> 12264955
A4: 1 | B4: 2790396 | C4: 328021 | D4: 374 | E4: 499 | F4: 471 | G4: 440849 | H4: 214756 | I4: 80076 | J4: 461087 | K4: 1744368 | L4: 2269041 | M4: 1759312 | N4: 229827 | O4: 269480 | P4: 66656 | Q4: 463104 | R4: 408570 | S4: 555458 | T4: 190678 | U4: =SUM(B4:T4) -> 12273023 | V4: =SUM(U4-U3) -> 8068
A5: 2 | B5: 2792591 | C5: 328252 | D5: 374 | E5: 499 | F5: 471 | G5: 441417 | H5: 214756 | I5: 80076 | J5: 461522 | K5: 1747160 | L5: 2269041 | M5: 1759774 | N5: 229827 | O5: 269785 | P5: 66675 | Q5: 463306 | R5: 408570 | S5: 555516 | T5: 191154 | U5: =SUM(B5:T5) -> 12280766 | V5: =SUM(U5-U4) -> 7743
A6: 3 | B6: 2795261 | C6: 328542 | D6: 374 | E6: 499 | F6: 471 | G6: 442043 | H6: 214756 | I6: 80076 | J6: 462072 | K6: 1749298 | L6: 2269041 | M6: 1759774 | N6: 230013 | O6: 269785 | P6: 66675 | Q6: 463468 | R6: 408570 | S6: 555566 | T6: 191531 | U6: =SUM(B6:T6) -> 12287815 | V6: =SUM(U6-U5) -> 7049
A7: 4 | B7: 2798167 | C7: 328871 | D7: 374 | E7: 499 | F7: 471 | G7: 442331 | H7: 214756 | I7: 80076 | J7: 462694 | K7: 1749298 | L7: 2269041 | M7: 1760811 | N7: 230013 | O7: 269785 | P7: 66795 | Q7: 463945 | R7: 408570 | S7: 555566 | T7: 191673 | U7: =SUM(B7:T7) -> 12293736 | V7: =SUM(U7-U6) -> 5921
A8: 5 | B8: 2800688 | C8: 329140 | D8: 374 | E8: 499 | F8: 471 | G8: 442681 | H8: 214756 | I8: 80076 | J8: 463200 | K8: 1750897 | L8: 2269044 | M8: 1761558 | N8: 230013 | O8: 269873 | P8: 66951 | Q8: 464372 | R8: 408570 | S8: 555802 | T8: 191948 | U8: =SUM(B8:T8) -> 12300913 | V8: =SUM(U8-U7) -> 7177
A9: 6 | B9: 2802796 | C9: 329326 | D9: 374 | E9: 499 | F9: 471 | G9: 442708 | H9: 214756 | I9: 80076 | J9: 463617 | K9: 1754857 | L9: 2269044 | M9: 1761653 | N9: 230013 | O9: 270019 | P9: 66951 | Q9: 465179 | R9: 408570 | S9: 555802 | T9: 192667 | U9: =SUM(B9:T9) -> 12309378 | V9: =SUM(U9-U8) -> 8465
A10: 7 | B10: 2804273 | C10: 329529 | D10: 374 | E10: 499 | F10: 471 | G10: 443034 | H10: 214756 | I10: 80076 | J10: 463930 | K10: 1759258 | L10: 2269044 | M10: 1761876 | N10: 230227 | O10: 270422 | P10: 67001 | Q10: 465659 | R10: 408570 | S10: 555802 | T10: 192667 | U10: =SUM(B10:T10) -> 12317468 | V10: =SUM(U10-U9) -> 8090
A11: 8 | B11: 2805726 | C11: 329687 | D11: 374 | E11: 501 | F11: 473 | G11: 443496 | H11: 214756 | I11: 80076 | J11: 464228 | K11: 1763224 | L11: 2269044 | M11: 1761876 | N11: 230227 | O11: 270422 | P11: 67401 | Q11: 465945 | R11: 408570 | S11: 555802 | T11: 194166 | U11: =SUM(B11:T11) -> 12325994 | V11: =SUM(U11-U10) -> 8526
A12: 9 | B12: 2807915 | C12: 329940 | D12: 374 | E12: 501 | F12: 473 | G12: 443775 | H12: 214756 | I12: 80076 | J12: 464724 | K12: 1765891 | L12: 2269044 | M12: 1761876 | N12: 230509 | O12: 270422 | P12: 67421 | Q12: 466462 | R12: 408570 | S12: 555802 | T12: 194658 | U12: =SUM(B12:T12) -> 12333189 | V12: =SUM(U12-U11) -> 7195
A13: 10 | B13: 2810546 | C13: 330255 | D13: 374 | E13: 501 | F13: 473 | G13: 444282 | H13: 214756 | I13: 80076 | J13: 465320 | K13: 1765891 | L13: 2269044 | M13: 1763592 | N13: 230611 | O13: 270479 | P13: 67436 | Q13: 466756 | R13: 408570 | S13: 556140 | T13: 194658 | U13: =SUM(B13:T13) -> 12339760 | V13: =SUM(U13-U12) -> 6571
A14: 11 | B14: 2812364 | C14: 330480 | D14: 374 | E14: 501 | F14: 473 | G14: 444549 | H14: 214756 | I14: 80076 | J14: 465744 | K14: 1769100 | L14: 2269044 | M14: 1763592 | N14: 230611 | O14: 270682 | P14: 67544 | Q14: 467264 | R14: 408570 | S14: 556707 | T14: 194658 | U14: =SUM(B14:T14) -> 12347089 | V14: =SUM(U14-U13) -> 7329
... A33: 30 | B33: 2853745 | C33: 335261 | D33: 374 | E33: 506 | F33: 478 | G33: 450772 | H33: 214756 | I33: 80076 | J33: 470892 | K33: 1796275 | L33: 2269044 | M33: 1796063 | N33: 233281 | O33: 273364 | P33: 68118 | Q33: 475442 | R33: 408955 | S33: 564310 | T33: 198215 | U33: =SUM(B33:T33) -> 12489927 | V33: =SUM(U33-U32) -> 5129
A34: 31 | U34: =SUM(B34:T34) -> 0 | V34: =SUM(U34-U33) -> -12489927

Sheet 裙楼空调用量
B1: 裙楼空调用量 | D1: 裙楼冷库用量 | F1: JK6-1 | H1: JK6-2 | J1: JK6-3 | L1: 裙楼空调总计
A2: 日期 | B2: 读 数 | C2: 用量(Mw/h) | D2: 读 数 | F2: 读 数 | G2: 用量(Mw/h) | H2: 读 数 | I2: 用量(Mw/h) | J2: 读 数 | K2: 用量(Mw/h) | L2: 总用量(Mw/h) | M2: 空调水费用（RMB）单价：37 | N2: 空调电费用（RMB）单价：380 | O2: 空调总费用（RMB）单价：380 | P2: 物业抄表人 | Q2: 四季抄表人 | R2: 44013
A3: 31 | B3: 51917 | C3: =B3-B2 -> #VALUE! | D3: 2237 | E3: =D3-D2 -> #VALUE! | F3: 1167 | H3: 1554 | J3: 786 | L3: =C3+E3 -> #VALUE! | M3: =L3*37 -> #VALUE! | N3: =L3*380 -> #VALUE! | O3: =M3+N3 -> #VALUE!
A4: 1 | B4: 51927 | C4: =B4-B3 -> 10 | D4: 2238 | E4: =D4-D3 -> 1 | L4: =C4+E4+G4+I4+K4 -> 11 | M4: =L4*37 -> 407 | N4: =L4*380 -> 4180 | O4: =M4+N4 -> 4587
A5: 2 | B5: 51940 | C5: =B5-B4 -> 13 | D5: 2240 | E5: =D5-D4 -> 2 | L5: =C5+E5+G5+I5+K5 -> 15 | M5: =L5*37 -> 555 | N5: =L5*380 -> 5700 | O5: =M5+N5 -> 6255
A6: 3 | B6: 51958 | C6: =B6-B5 -> 18 | D6: 2241 | E6: =D6-D5 -> 1 | L6: =C6+E6+G6+I6+K6 -> 19 | M6: =L6*37 -> 703 | N6: =L6*380 -> 7220 | O6: =M6+N6 -> 7923
A7: 4 | B7: 51971 | C7: =B7-B6 -> 13 | D7: 2243 | E7: =D7-D6 -> 2 | L7: =C7+E7+G7+I7+K7 -> 15 | M7: =L7*37 -> 555 | N7: =L7*380 -> 5700 | O7: =M7+N7 -> 6255
A8: 5 | B8: 51982 | C8: =B8-B7 -> 11 | D8: 2244 | E8: =D8-D7 -> 1 | L8: =C8+E8+G8+I8+K8 -> 12 | M8: =L8*37 -> 444 | N8: =L8*380 -> 4560 | O8: =M8+N8 -> 5004
A9: 6 | B9: 52000 | C9: =B9-B8 -> 18 | D9: 2246 | E9: =D9-D8 -> 2 | L9: =C9+E9+G9+I9+K9 -> 20 | M9: =L9*37 -> 740 | N9: =L9*380 -> 7600 | O9: =M9+N9 -> 8340
A10: 7 | B10: 52014 | C10: =B10-B9 -> 14 | D10: 2247 | E10: =D10-D9 -> 1 | L10: =C10+E10+G10+I10+K10 -> 15 | M10: =L10*37 -> 555 | N10: =L10*380 -> 5700 | O10: =M10+N10 -> 6255
A11: 8 | B11: 52025 | C11: =B11-B10 -> 11 | D11: 2248 | E11: =D11-D10 -> 1 | L11: =C11+E11+G11+I11+K11 -> 12 | M11: =L11*37 -> 444 | N11: =L11*380 -> 4560 | O11: =M11+N11 -> 5004
A12: 9 | B12: 52037 | C12: =B12-B11 -> 12 | D12: 2250 | E12: =D12-D11 -> 2 | F12: 1175 | H12: 1575 | J12: 786 | L12: =C12+E12+G12+I12+K12 -> 14 | M12: =L12*37 -> 518 | N12: =L12*380 -> 5320 | O12: =M12+N12 -> 5838
A13: 10 | B13: 52048 | C13: =B13-B12 -> 11 | D13: 2251 | E13: =D13-D12 -> 1 | L13: =C13+E13+G13+I13+K13 -> 12 | M13: =L13*37 -> 444 | N13: =L13*380 -> 4560 | O13: =M13+N13 -> 5004
A14: 11 | B14: 52059 | C14: =B14-B13 -> 11 | D14: 2253 | E14: =D14-D13 -> 2 | L14: =C14+E14+G14+I14+K14 -> 13 | M14: =L14*37 -> 481 | N14: =L14*380 -> 4940 | O14: =M14+N14 -> 5421
A15: 12 | B15: 52074 | C15: =B15-B14 -> 15 | D15: 2254 | E15: =D15-D14 -> 1 | L15: =C15+E15+G15+I15+K15 -> 16 | M15: =L15*37 -> 592 | N15: =L15*380 -> 6080 | O15: =M15+N15 -> 6672
A16: 13 | B16: 52089 | C16: =B16-B15 -> 15 | D16: 2256 | E16: =D16-D15 -> 2 | L16: =C16+E16+G16+I16+K16 -> 17 | M16: =L16*37 -> 629 | N16: =L16*380 -> 6460 | O16: =M16+N16 -> 7089
A17: 14 | B17: 52103 | C17: =B17-B16 -> 14 | D17: 2257 | E17: =D17-D16 -> 1 | L17: =C17+E17+G17+I17+K17 -> 15 | M17: =L17*37 -> 555 | N17: =L17*380 -> 5700 | O17: =M17+N17 -> 6255
A18: 15 | B18: 52116 | C18: =B18-B17 -> 13 | D18: 2259 | E18: =D18-D17 -> 2 | L18: =C18+E18+G18+I18+K18 -> 15 | M18: =L18*37 -> 555 | N18: =L18*380 -> 5700 | O18: =M18+N18 -> 6255
A19: 16 | B19: 52134 | C19: =B19-B18 -> 18 | D19: 2260 | E19: =D19-D18 -> 1 | L19: =C19+E19+G19+I19+K19 -> 19 | M19: =L19*37 -> 703 | N19: =L19*380 -> 7220 | O19: =M19+N19 -> 7923
A20: 17 | B20: 52152 | C20: =B20-B19 -> 18 | D20: 2261 | E20: =D20-D19 -> 1 | L20: =C20+E20+G20+I20+K20 -> 19 | M20: =L20*37 -> 703 | N20: =L20*380 -> 7220 | O20: =M20+N20 -> 7923
A21: 18 | B21: 52172 | C21: =B21-B20 -> 20 | D21: 2263 | E21: =D21-D20 -> 2 | L21: =C21+E21+G21+I21+K21 -> 22 | M21: =L21*37 -> 814 | N21: =L21*380 -> 8360 | O21: =M21+N21 -> 9174
A22: 19 | B22: 52195 | C22: =B22-B21 -> 23 | D22: 2265 | E22: =D22-D21 -> 2 | L22: =C22+E22+G22+I22+K22 -> 25 | M22: =L22*37 -> 925 | N22: =L22*380 -> 9500 | O22: =M22+N22 -> 10425
A23: 20 | B23: 52215 | C23: =B23-B22 -> 20 | D23: 2266 | E23: =D23-D22 -> 1 | L23: =C23+E23+G23+I23+K23 -> 21 | M23: =L23*37 -> 777 | N23: =L23*380 -> 7980 | O23: =M23+N23 -> 8757
A24: 21 | B24: 52234 | C24: =B24-B23 -> 19 | D24: 2268 | E24: =D24-D23 -> 2 | L24: =C24+E24+G24+I24+K24 -> 21 | M24: =L24*37 -> 777 | N24: =L24*380 -> 7980 | O24: =M24+N24 -> 8757
... A33: 30 | B33: 52372 | C33: =B33-B32 -> 9 | D33: 2281 | E33: =D33-D32 -> 1 | L33: =C33+E33+G33+I33+K33 -> 10 | M33: =L33*37 -> 370 | N33: =L33*380 -> 3800 | O33: =M33+N33 -> 4170
A34: 31 | C34: =B34-B33 -> -52372 | E34: =D34-D33 -> -2281 | L34: =C34+E34 -> -54653 | M34: =L34*37 -> -2022161 | N34: =L34*380 -> -20768140 | O34: =M34+N34 -> -22790301

Sheet Compatibility Report
B1: Compatibility Report for 2018.xls
B2: Run on 01/01/2018 0:50
B4: The following features in this workbook are not supported by earlier versions of Excel. These features may be lost or degraded when you save this workbook in an earlier file format.
B6: Minor loss of fidelity | E6: # of occurrences
B8: Some formulas in this workbook are linked to other workbooks that are closed. When these formulas are recalculated in earlier versions of Excel without opening the linked workbooks, characters beyond the 255-character limit cannot be returned. | E8: 20
E9: '煤气充值'!B6:C6
E10: '煤气充值'!G6:H6
E11: '煤气充值'!L6:M6
E12: '煤气充值'!Q6:R6
E13: '煤气充值'!AA6:AB6
E14: '煤气充值'!AF6:AG6
E15: '煤气充值'!AK6:AL6
E16: '煤气充值'!AP6:AQ6
E17: '煤气充值'!AU6:AV6
E18: '煤气充值'!AZ6:BA6
B20: Some cells or styles in this workbook contain formatting that is not supported by the selected file format. These formats will be converted to the closest format available. | E20: 138

Sheet 付款申请书
A2: PAYMENT REQUEST
M3: 付款申请书
AA4: No
AA5: 号码
A6: Pay To: | Q6: Payment Method | AA6: Date
A7: 付给 | Q7: Bank transfer 银行转帐 | X7: √ | AA7: 日期 | AE7: 月份
Q8: Cheque 支票 | AA8: Amount
Q9: Cash现金 | AA9: 金额 | AE9: =AF25 -> 0
A11: PAYMENT DETAIL | Y11: AMOUNT金额
A12: Date日期 | D12: Invoice #发票号 | H12: Description 内容 | U12: GL Code 科目 | Y12: Foreign $外币 | AC12: Ex. Rate | AF12: CNY人民币
A13: 43070 | H13: 裙楼后勤办公室用电
W25: Grand Total合计 | AF25: =SUM(AF13:AI24) -> 0
A27: AUTHORISATION
A28: Prepared By: 部门审批 | I28: Checked By:财务部审查 | R28: Reviewed By:财务总监审核 | AA28: Approved By:总经理批准
A32: Department | I32: Accounts Officer | R32: Director of Finance | AA32: General Manager
