Workbook

Sheet Total
A1: Site Name | B1: Day | C1: Month | D1: Year | E1: Total Electricity Kwh | F1: Electricity Tariff ($/Kwh) | G1: Total Fuel Oil (Liters) | H1: Fuel Oil $/Liter | I1: LPG (Kg) | J1: LPG $/Kg | K1: Water Utility Supply (m3) m3 | L1: Water Utility Supply (m3) $/m3 | M1: Irrigation Water (m3) m3 | N1: Irrigation water $/m3 | O1: Room Nights
A2: Beirut | B2: 1 | C2: 1 | D2: 2021 | E2: =ELEC!N3 -> 6404.4 | F2: =SUM('EDl log'!T4) -> 0.093949341 | G2: =-tanks!AW6 -> 467.6 | H2: =SUM(tanks!AV6) -> 0.1 | I2: =('B5'!AU5)*0.51 -> 0 | J2: ='B5'!AX5/0.51 -> 1.5686275 | K2: =WATER!I6 -> 0 | L2: =SUM(WATER!J6) -> 0 | M2: =WATER!Q6 -> 0 | N2: 0.6 | O2: =ELEC!B3 -> 0
A3: Beirut | B3: =B2+1 -> 2 | C3: 1 | D3: 2021 | E3: =ELEC!N4 -> 6622 | F3: =SUM('EDl log'!T5) -> 0.084333644 | G3: =-tanks!AW7 -> 234 | H3: =SUM(tanks!AV7) -> 0.1 | I3: =('B5'!AU6)*0.51 -> 0 | J3: ='B5'!AX6/0.51 -> 1.5686275 | K3: =WATER!I7 -> 0 | L3: =SUM(WATER!J7) -> 0 | M3: =WATER!Q7 -> 0 | N3: 0.6 | O3: =ELEC!B4 -> 0
A4: Beirut | B4: =B3+1 -> 3 | C4: 1 | D4: 2021 | E4: =ELEC!N5 -> 6753 | F4: =SUM('EDl log'!T6) -> 0.089263909 | G4: =-tanks!AW8 -> 289 | H4: =SUM(tanks!AV8) -> 0.1 | I4: =('B5'!AU7)*0.51 -> 0 | J4: ='B5'!AX7/0.51 -> 1.5686275 | K4: =WATER!I8 -> 0 | L4: =SUM(WATER!J8) -> 0 | M4: =WATER!Q8 -> 0 | N4: 0.6 | O4: =ELEC!B5 -> 0
A5: Beirut | B5: =B4+1 -> 4 | C5: 1 | D5: 2021 | E5: =ELEC!N6 -> 6587 | F5: =SUM('EDl log'!T7) -> 0.096457613 | G5: =-tanks!AW9 -> 314 | H5: =SUM(tanks!AV9) -> 0.1 | I5: =('B5'!AU8)*0.51 -> 0 | J5: ='B5'!AX8/0.51 -> 1.5686275 | K5: =WATER!I9 -> 0 | L5: =SUM(WATER!J9) -> 0 | M5: =WATER!Q9 -> 0 | N5: 0.6 | O5: =ELEC!B6 -> 0
A6: Beirut | B6: =B5+1 -> 5 | C6: 1 | D6: 2021 | E6: =ELEC!N7 -> 5932 | F6: =SUM('EDl log'!T8) -> 0.017181491 | G6: =-tanks!AW10 -> 391 | H6: =SUM(tanks!AV10) -> 0.674 | I6: =('B5'!AU9)*0.51 -> 0 | J6: ='B5'!AX9/0.51 -> 1.5686275 | K6: =WATER!I10 -> 0 | L6: =SUM(WATER!J10) -> 0 | M6: =WATER!Q10 -> 0 | N6: 0.6 | O6: =ELEC!B7 -> 0
A7: Beirut | B7: =B6+1 -> 6 | C7: 1 | D7: 2021 | E7: =ELEC!N8 -> 5977 | F7: =SUM('EDl log'!T9) -> 0.083584348 | G7: =-tanks!AW11 -> 311 | H7: =SUM(tanks!AV11) -> 0.674 | I7: =('B5'!AU10)*0.51 -> 0 | J7: ='B5'!AX10/0.51 -> 1.5686275 | K7: =WATER!I11 -> 0 | L7: =SUM(WATER!J11) -> 0 | M7: =WATER!Q11 -> 0 | N7: 0.6 | O7: =ELEC!B8 -> 0
A8: Beirut | B8: =B7+1 -> 7 | C8: 1 | D8: 2021 | E8: =ELEC!N9 -> 6551.2 | F8: =SUM('EDl log'!T10) -> 0.099245072 | G8: =-tanks!AW12 -> 279 | H8: =SUM(tanks!AV12) -> 0.674 | I8: =('B5'!AU11)*0.51 -> 0 | J8: ='B5'!AX11/0.51 -> 1.5686275 | K8: =WATER!I12 -> 0 | L8: =SUM(WATER!J12) -> 0 | M8: =WATER!Q12 -> 0 | N8: 0.6 | O8: =ELEC!B9 -> 0
A9: Beirut | B9: =B8+1 -> 8 | C9: 1 | D9: 2021 | E9: =ELEC!N10 -> 6289.8 | F9: =SUM('EDl log'!T11) -> 0.081623986 | G9: =-tanks!AW13 -> 333.4 | H9: =SUM(tanks!AV13) -> 0.674 | I9: =('B5'!AU12)*0.51 -> 0 | J9: ='B5'!AX12/0.51 -> 1.5686275 | K9: =WATER!I13 -> 0 | L9: =SUM(WATER!J13) -> 0 | M9: =WATER!Q13 -> 0 | N9: 0.6 | O9: =ELEC!B10 -> 0
A10: Beirut | B10: =B9+1 -> 9 | C10: 1 | D10: 2021 | E10: =ELEC!N11 -> 7008 | F10: =SUM('EDl log'!T12) -> 0.087597788 | G10: =-tanks!AW14 -> 236 | H10: =SUM(tanks!AV14) -> 0.674 | I10: =('B5'!AU13)*0.51 -> 0 | J10: ='B5'!AX13/0.51 -> 1.5686275 | K10: =WATER!I14 -> 0 | L10: =SUM(WATER!J14) -> 0 | M10: =WATER!Q14 -> 0 | N10: 0.6 | O10: =ELEC!B11 -> 0
A11: Beirut | B11: =B10+1 -> 10 | C11: 1 | D11: 2021 | E11: =ELEC!N12 -> 7276 | F11: =SUM('EDl log'!T13) -> 0.11594008 | G11: =-tanks!AW15 -> 236 | H11: =SUM(tanks!AV15) -> 0.674 | I11: =('B5'!AU14)*0.51 -> 0 | J11: ='B5'!AX14/0.51 -> 1.5686275 | K11: =WATER!I15 -> 0 | L11: =SUM(WATER!J15) -> 0 | M11: =WATER!Q15 -> 0 | N11: 0.6 | O11: =ELEC!B12 -> 0
A12: Beirut | B12: =B11+1 -> 11 | C12: 1 | D12: 2021 | E12: =ELEC!N13 -> 7236 | F12: =SUM('EDl log'!T14) -> 0.098706635 | G12: =-tanks!AW16 -> 253 | H12: =SUM(tanks!AV16) -> 0.674 | I12: =('B5'!AU15)*0.51 -> 0 | J12: ='B5'!AX15/0.51 -> 1.5686275 | K12: =WATER!I16 -> 0 | L12: =SUM(WATER!J16) -> 0 | M12: =WATER!Q16 -> 0 | N12: 0.6 | O12: =ELEC!B13 -> 0
A13: Beirut | B13: =B12+1 -> 12 | C13: 1 | D13: 2021 | E13: =ELEC!N14 -> 5643 | F13: =SUM('EDl log'!T15) -> 0.092903396 | G13: =-tanks!AW17 -> 234 | H13: =SUM(tanks!AV17) -> 0.674 | I13: =('B5'!AU16)*0.51 -> 0 | J13: ='B5'!AX16/0.51 -> 1.5686275 | K13: =WATER!I17 -> 0 | L13: =SUM(WATER!J17) -> 0 | M13: =WATER!Q17 -> 0 | N13: 0.6 | O13: =ELEC!B14 -> 0
A14: Beirut | B14: =B13+1 -> 13 | C14: 1 | D14: 2021 | E14: =ELEC!N15 -> 0 | F14: =SUM('EDl log'!T16) -> 0 | G14: =-tanks!AW18 -> 0 | H14: =SUM(tanks!AV18) -> 0.674 | I14: =('B5'!AU17)*0.51 -> 0 | J14: ='B5'!AX17/0.51 -> 1.5686275 | K14: =WATER!I18 -> 0 | L14: =SUM(WATER!J18) -> 0 | M14: =WATER!Q18 -> 0 | N14: 0.6 | O14: =ELEC!B15 -> 0
... A29: Beirut | B29: =B28+1 -> 28 | C29: 1 | D29: 2021 | E29: =ELEC!N30 -> 0 | F29: =SUM('EDl log'!T31) -> 0 | G29: =-tanks!AW33 -> 0 | H29: =SUM(tanks!AV33) -> 0.674 | I29: =('B5'!AU32)*0.51 -> 0 | J29: ='B5'!AX32/0.51 -> 1.5686275 | K29: =WATER!I33 -> 0 | L29: =SUM(WATER!J33) -> 0 | M29: =WATER!Q33 -> 0 | N29: 0.6 | O29: =ELEC!B30 -> 0

Sheet Submetering
A1: Site Name | B1: Day | C1: Month | D1: Year | E1: ATS1 Kwh | F1: ATS2 Kwh | G1: ATS3 Kwh | H1: ATS4 Kwh | I1: ATS5 Kwh | J1: Guest (m3) | K1: Kitchen & Laundry (m3) | L1: Room Nights
A2: Beirut | B2: 1 | C2: 1 | D2: 2021 | E2: =ELEC!M3 -> 1898 | F2: =ELEC!K3 -> 970 | G2: =ELEC!I3 -> 874 | H2: =ELEC!E3 -> 2060 | I2: =ELEC!G3 -> 602.4 | J2: =WATER!Y6 -> 0 | K2: =WATER!AJ6 -> 0 | L2: =ELEC!B3 -> 0
A3: Beirut | B3: =B2+1 -> 2 | C3: 1 | D3: 2021 | E3: =ELEC!M4 -> 2070 | F3: =ELEC!K4 -> 912 | G3: =ELEC!I4 -> 812 | H3: =ELEC!E4 -> 2192 | I3: =ELEC!G4 -> 636 | J3: =WATER!Y7 -> 0 | K3: =WATER!AJ7 -> 0 | L3: =ELEC!B4 -> 0
A4: Beirut | B4: =B3+1 -> 3 | C4: 1 | D4: 2021 | E4: =ELEC!M5 -> 1956 | F4: =ELEC!K5 -> 928 | G4: =ELEC!I5 -> 820 | H4: =ELEC!E5 -> 2410 | I4: =ELEC!G5 -> 639 | J4: =WATER!Y8 -> 0 | K4: =WATER!AJ8 -> 0 | L4: =ELEC!B5 -> 0
A5: Beirut | B5: =B4+1 -> 4 | C5: 1 | D5: 2021 | E5: =ELEC!M6 -> 1846 | F5: =ELEC!K6 -> 956 | G5: =ELEC!I6 -> 840 | H5: =ELEC!E6 -> 2294 | I5: =ELEC!G6 -> 651 | J5: =WATER!Y9 -> 0 | K5: =WATER!AJ9 -> 0 | L5: =ELEC!B6 -> 0
A6: Beirut | B6: =B5+1 -> 5 | C6: 1 | D6: 2021 | E6: =ELEC!M7 -> 1612 | F6: =ELEC!K7 -> 916 | G6: =ELEC!I7 -> 740 | H6: =ELEC!E7 -> 2056 | I6: =ELEC!G7 -> 608 | J6: =WATER!Y10 -> 0 | K6: =WATER!AJ10 -> 0 | L6: =ELEC!B7 -> 0
A7: Beirut | B7: =B6+1 -> 6 | C7: 1 | D7: 2021 | E7: =ELEC!M8 -> 1658 | F7: =ELEC!K8 -> 902 | G7: =ELEC!I8 -> 800 | H7: =ELEC!E8 -> 1952 | I7: =ELEC!G8 -> 665 | J7: =WATER!Y11 -> 0 | K7: =WATER!AJ11 -> 0 | L7: =ELEC!B8 -> 0
A8: Beirut | B8: =B7+1 -> 7 | C8: 1 | D8: 2021 | E8: =ELEC!M9 -> 1976 | F8: =ELEC!K9 -> 1446 | G8: =ELEC!I9 -> 816 | H8: =ELEC!E9 -> 1710 | I8: =ELEC!G9 -> 603.2 | J8: =WATER!Y12 -> 0 | K8: =WATER!AJ12 -> 0 | L8: =ELEC!B9 -> 0
A9: Beirut | B9: =B8+1 -> 8 | C9: 1 | D9: 2021 | E9: =ELEC!M10 -> 1758 | F9: =ELEC!K10 -> 1470 | G9: =ELEC!I10 -> 796 | H9: =ELEC!E10 -> 1662 | I9: =ELEC!G10 -> 603.8 | J9: =WATER!Y13 -> 0 | K9: =WATER!AJ13 -> 0 | L9: =ELEC!B10 -> 0
A10: Beirut | B10: =B9+1 -> 9 | C10: 1 | D10: 2021 | E10: =ELEC!M11 -> 1638 | F10: =ELEC!K11 -> 1918 | G10: =ELEC!I11 -> 876 | H10: =ELEC!E11 -> 1908 | I10: =ELEC!G11 -> 668 | J10: =WATER!Y14 -> 0 | K10: =WATER!AJ14 -> 0 | L10: =ELEC!B11 -> 0
A11: Beirut | B11: =B10+1 -> 10 | C11: 1 | D11: 2021 | E11: =ELEC!M12 -> 1680 | F11: =ELEC!K12 -> 2182 | G11: =ELEC!I12 -> 832 | H11: =ELEC!E12 -> 1948 | I11: =ELEC!G12 -> 634 | J11: =WATER!Y15 -> 0 | K11: =WATER!AJ15 -> 0 | L11: =ELEC!B12 -> 0
A12: Beirut | B12: =B11+1 -> 11 | C12: 1 | D12: 2021 | E12: =ELEC!M13 -> 1740 | F12: =ELEC!K13 -> 2034 | G12: =ELEC!I13 -> 888 | H12: =ELEC!E13 -> 1926 | I12: =ELEC!G13 -> 648 | J12: =WATER!Y16 -> 0 | K12: =WATER!AJ16 -> 0 | L12: =ELEC!B13 -> 0
A13: Beirut | B13: =B12+1 -> 12 | C13: 1 | D13: 2021 | E13: =ELEC!M14 -> 1352 | F13: =ELEC!K14 -> 1496 | G13: =ELEC!I14 -> 764 | H13: =ELEC!E14 -> 1422 | I13: =ELEC!G14 -> 609 | J13: =WATER!Y17 -> 0 | K13: =WATER!AJ17 -> 0 | L13: =ELEC!B14 -> 0
A14: Beirut | B14: =B13+1 -> 13 | C14: 1 | D14: 2021 | E14: =ELEC!M15 -> 0 | F14: =ELEC!K15 -> 0 | G14: =ELEC!I15 -> 0 | H14: =ELEC!E15 -> 0 | I14: =ELEC!G15 -> 0 | J14: =WATER!Y18 -> 0 | K14: =WATER!AJ18 -> 0 | L14: =ELEC!B15 -> 0
... A29: Beirut | B29: =B28+1 -> 28 | C29: 1 | D29: 2021 | E29: =ELEC!M30 -> 0 | F29: =ELEC!K30 -> 0 | G29: =ELEC!I30 -> 0 | H29: =ELEC!E30 -> 0 | I29: =ELEC!G30 -> 0 | J29: =WATER!Y33 -> 0 | K29: =WATER!AJ33 -> 0 | L29: =ELEC!B30 -> 0

Sheet ELEC
A1: OOC | B1: Room OCC | D1: MDB3 | E1: MDB3/day | F1: EMDB2 | G1: EMDB2/day | H1: EMDB1 | I1: EMDB1/day | J1: MDB2 | K1: mdb2/day | L1: MDB1 | M1: MDB1/Day | N1: Total KWH | O1: KWH/Rooc | P1: Gen MHW | Q1: Gen/Day KWH | R1: EDL KWH | S1: CH1 RH | T1: RH | U1: C1h1 power | V1: CH1 Con KWH | W1: CH2 RH | X1: RH | Y1: Ch2 power | Z1: CH2 Con KWH | AA1: CH3 RH | AB1: RH | AC1: Ch3 power | AD1: CH3 Con KWH | AE1: RH total | AF1: KWH total | AG1: AVG chiller KW/Hr
A2: =[1]ELEC!A33 -> 0 | B2: =[1]ELEC!B33 -> 0 | C2: =[2]ELEC!$C$33 -> 44227 | D2: =[2]ELEC!D33 -> 32583138 | E2: =[2]ELEC!E33 -> 2268 | F2: =[2]ELEC!F33 -> 3954026.6 | G2: =[2]ELEC!G33 -> 559 | H2: =[2]ELEC!H33 -> 17779688 | I2: =[2]ELEC!I33 -> 842 | J2: =[2]ELEC!J33 -> 28877552 | K2: =[2]ELEC!K33 -> 1066 | ... AG2: =[2]ELEC!AG33 -> 159.25 | AH2: =[1]ELEC!AH33 -> 0 | AI2: =[1]ELEC!AI33 -> -770946 | AJ2: =[1]ELEC!AJ33 -> 0 | AK2: =[1]ELEC!AK33 -> 0 | AL2: =[1]ELEC!AL33 -> 0 | AM2: =[1]ELEC!AM33 -> 0 | AN2: =[1]ELEC!AN33 -> 0 | AO2: =[1]ELEC!AO33 -> 0 | ... DD2: =[1]ELEC!DD33 -> 0
A3: ='General information '!F6 -> 0 | B3: =SUM(230*A3) -> 0 | C3: 44228 | D3: 32585198 | E3: =D3-D2 -> 2060 | F3: 3954629 | G3: =F3-F2 -> 602.4 | H3: 17780562 | I3: =H3-H2 -> 874 | J3: 28878522 | K3: =J3-J2 -> 970 | L3: 23999456 | M3: =L3-L2 -> 1898 | N3: =M3+K3+I3+G3+E3 -> 6404.4 | O3: =IF(B3>0,N3/B3,0) -> 0 | P3: 16577.595 | Q3: =(P3-P2)*1000 -> 1968 | R3: =+N3-Q3 -> 4436.4 | S3: =S2 -> 10118 | T3: =S3-S2 -> 0 | U3: =U2 -> 420722 | V3: =U3-U2 -> 0 | W3: =W2 -> 32167 | X3: =W3-W2 -> 0 | Y3: =Y2 -> 696352 | Z3: =Y3-Y2 -> 0 | AA3: 35673 | AB3: =AA3-AA2 -> 2 | AC3: 912749 | AD3: =AC3-AC2 -> 397 | AE3: =AB3+X3+T3 -> 2 | AF3: =V3+Z3+AD3 -> 397 | AG3: =IF(AE3>0,AF3/AE3,0) -> 198.5
A4: ='General information '!F7 -> 0 | B4: =SUM(230*A4) -> 0 | C4: 44229 | D4: 32587390 | E4: =D4-D3 -> 2192 | F4: 3955265 | G4: =F4-F3 -> 636 | H4: 17781374 | I4: =H4-H3 -> 812 | J4: 28879434 | K4: =J4-J3 -> 912 | L4: 24001526 | M4: =L4-L3 -> 2070 | N4: =M4+K4+I4+G4+E4 -> 6622 | O4: =IF(B4>0,N4/B4,0) -> 0 | P4: 16579.85 | Q4: =(P4-P3)*1000 -> 2255 | R4: =N4-Q4 -> 4367 | S4: =S3 -> 10118 | T4: =S4-S3 -> 0 | U4: =U3 -> 420722 | V4: =U4-U3 -> 0 | W4: =W3 -> 32167 | X4: =W4-W3 -> 0 | Y4: =Y3 -> 696352 | Z4: =Y4-Y3 -> 0 | AA4: 35677 | AB4: =AA4-AA3 -> 4 | AC4: 913263 | AD4: =AC4-AC3 -> 514 | AE4: =AB4+X4+T4 -> 4 | AF4: =V4+Z4+AD4 -> 514 | AG4: =IF(AE4>0,AF4/AE4,0) -> 128.5
A5: ='General information '!F8 -> 0 | B5: =SUM(230*A5) -> 0 | C5: 44230 | D5: 32589800 | E5: =D5-D4 -> 2410 | F5: 3955904 | G5: =F5-F4 -> 639 | H5: 17782194 | I5: =H5-H4 -> 820 | J5: 28880362 | K5: =J5-J4 -> 928 | L5: 24003482 | M5: =L5-L4 -> 1956 | N5: =M5+K5+I5+G5+E5 -> 6753 | O5: =IF(B5>0,N5/B5,0) -> 0 | P5: 16582.771 | Q5: =(P5-P4)*1000 -> 2921 | R5: =N5-Q5 -> 3832 | S5: =S4 -> 10118 | T5: =S5-S4 -> 0 | U5: =U4 -> 420722 | V5: =U5-U4 -> 0 | W5: =W4 -> 32167 | X5: =W5-W4 -> 0 | Y5: =Y4 -> 696352 | Z5: =Y5-Y4 -> 0 | AA5: 35680 | AB5: =AA5-AA4 -> 3 | AC5: 913951 | AD5: =AC5-AC4 -> 688 | AE5: =AB5+X5+T5 -> 3 | AF5: =V5+Z5+AD5 -> 688 | AG5: =IF(AE5>0,AF5/AE5,0) -> 229.33333 | AI5: =R5-'EDl log'!B3 -> -849794
A6: ='General information '!F9 -> 0 | B6: =SUM(230*A6) -> 0 | C6: 44231 | D6: 32592094 | E6: =D6-D5 -> 2294 | F6: 3956555 | G6: =F6-F5 -> 651 | H6: 17783034 | I6: =H6-H5 -> 840 | J6: 28881318 | K6: =J6-J5 -> 956 | L6: 24005328 | M6: =L6-L5 -> 1846 | N6: =M6+K6+I6+G6+E6 -> 6587 | O6: =IF(B6>0,N6/B6,0) -> 0 | P6: 16585.395 | Q6: =(P6-P5)*1000 -> 2624 | R6: =N6-Q6 -> 3963 | S6: =S5 -> 10118 | T6: =S6-S5 -> 0 | U6: =U5 -> 420722 | V6: =U6-U5 -> 0 | W6: =W5 -> 32167 | X6: =W6-W5 -> 0 | Y6: =Y5 -> 696352 | Z6: =Y6-Y5 -> 0 | AA6: 35684 | AB6: =AA6-AA5 -> 4 | AC6: 914499 | AD6: =AC6-AC5 -> 548 | AE6: =AB6+X6+T6 -> 4 | AF6: =V6+Z6+AD6 -> 548 | AG6: =IF(AE6>0,AF6/AE6,0) -> 137 | AI6: =R6-'EDl log'!B4 -> -852163
A7: ='General information '!F10 -> 0 | B7: =SUM(230*A7) -> 0 | C7: 44232 | D7: 32594150 | E7: =D7-D6 -> 2056 | F7: 3957163 | G7: =F7-F6 -> 608 | H7: 17783774 | I7: =H7-H6 -> 740 | J7: 28882234 | K7: =J7-J6 -> 916 | L7: 24006940 | M7: =L7-L6 -> 1612 | N7: =M7+K7+I7+G7+E7 -> 5932 | O7: =IF(B7>0,N7/B7,0) -> 0 | P7: 16587.36 | Q7: =(P7-P6)*1000 -> 1965 | R7: =N7-Q7 -> 3967 | S7: =S6 -> 10118 | T7: =S7-S6 -> 0 | U7: =U6 -> 420722 | V7: =U7-U6 -> 0 | W7: =W6 -> 32167 | X7: =W7-W6 -> 0 | Y7: =Y6 -> 696352 | Z7: =Y7-Y6 -> 0 | AA7: 35687 | AB7: =AA7-AA6 -> 3 | AC7: 914939 | AD7: =AC7-AC6 -> 440 | AE7: =AB7+X7+T7 -> 3 | AF7: =V7+Z7+AD7 -> 440 | AG7: =IF(AE7>0,AF7/AE7,0) -> 146.66667 | AI7: =R7-'EDl log'!B5 -> -854387
A8: ='General information '!F11 -> 0 | B8: =SUM(230*A8) -> 0 | C8: 44233 | D8: 32596102 | E8: =D8-D7 -> 1952 | F8: 3957828 | G8: =F8-F7 -> 665 | H8: 17784574 | I8: =H8-H7 -> 800 | J8: 28883136 | K8: =J8-J7 -> 902 | L8: 24008598 | M8: =L8-L7 -> 1658 | N8: =M8+K8+I8+G8+E8 -> 5977 | O8: =IF(B8>0,N8/B8,0) -> 0 | P8: 16589.054 | Q8: =(P8-P7)*1000 -> 1694 | R8: =N8-Q8 -> 4283 | S8: =S7 -> 10118 | T8: =S8-S7 -> 0 | U8: =U7 -> 420722 | V8: =U8-U7 -> 0 | W8: =W7 -> 32167 | X8: =W8-W7 -> 0 | Y8: =Y7 -> 696352 | Z8: =Y8-Y7 -> 0 | AA8: 35689 | AB8: =AA8-AA7 -> 2 | AC8: 915313 | AD8: =AC8-AC7 -> 374 | AE8: =AB8+X8+T8 -> 2 | AF8: =V8+Z8+AD8 -> 374 | AG8: =IF(AE8>0,AF8/AE8,0) -> 187 | AI8: =R8-'EDl log'!B6 -> -856158
A9: ='General information '!F12 -> 0 | B9: =SUM(230*A9) -> 0 | C9: 44234 | D9: 32597812 | E9: =D9-D8 -> 1710 | F9: 3958431.2 | G9: =F9-F8 -> 603.2 | H9: 17785390 | I9: =H9-H8 -> 816 | J9: 28884582 | K9: =J9-J8 -> 1446 | L9: 24010574 | M9: =L9-L8 -> 1976 | N9: =M9+K9+I9+G9+E9 -> 6551.2 | O9: =IF(B9>0,N9/B9,0) -> 0 | P9: 16591.098 | Q9: =(P9-P8)*1000 -> 2044 | R9: =N9-Q9 -> 4507.2 | S9: =S8 -> 10118 | T9: =S9-S8 -> 0 | U9: =U8 -> 420722 | V9: =U9-U8 -> 0 | W9: 32169 | X9: =W9-W8 -> 2 | Y9: 696833 | Z9: =Y9-Y8 -> 481 | AA9: =AA8 -> 35689 | AB9: =AA9-AA8 -> 0 | AC9: 915313 | AD9: =AC9-AC8 -> 0 | AE9: =AB9+X9+T9 -> 2 | AF9: =V9+Z9+AD9 -> 481 | AG9: =IF(AE9>0,AF9/AE9,0) -> 240.5 | AI9: =R9-'EDl log'!B7 -> -858088.8
A10: ='General information '!F13 -> 0 | B10: =SUM(230*A10) -> 0 | C10: 44235 | D10: 32599474 | E10: =D10-D9 -> 1662 | F10: 3959035 | G10: =F10-F9 -> 603.8 | H10: 17786186 | I10: =H10-H9 -> 796 | J10: 28886052 | K10: =J10-J9 -> 1470 | L10: 24012332 | M10: =L10-L9 -> 1758 | N10: =M10+K10+I10+G10+E10 -> 6289.8 | O10: =IF(B10>0,N10/B10,0) -> 0 | P10: 16593.143 | Q10: =(P10-P9)*1000 -> 2045 | R10: =N10-Q10 -> 4244.8 | S10: =S9 -> 10118 | T10: =S10-S9 -> 0 | U10: =U9 -> 420722 | V10: =U10-U9 -> 0 | W10: 32172 | X10: =W10-W9 -> 3 | Y10: 697351 | Z10: =Y10-Y9 -> 518 | AA10: =AA9 -> 35689 | AB10: =AA10-AA9 -> 0 | AC10: =AC9 -> 915313 | AD10: =AC10-AC9 -> 0 | AE10: =AB10+X10+T10 -> 3 | AF10: =V10+Z10+AD10 -> 518 | AG10: =IF(AE10>0,AF10/AE10,0) -> 172.66667 | AI10: =R10-'EDl log'!B8 -> -860497.2
A11: ='General information '!F14 -> 0 | B11: =SUM(230*A11) -> 0 | C11: 44236 | D11: 32601382 | E11: =D11-D10 -> 1908 | F11: 3959703 | G11: =F11-F10 -> 668 | H11: 17787062 | I11: =H11-H10 -> 876 | J11: 28887970 | K11: =J11-J10 -> 1918 | L11: 24013970 | M11: =L11-L10 -> 1638 | N11: =M11+K11+I11+G11+E11 -> 7008 | O11: =IF(B11>0,N11/B11,0) -> 0 | P11: 16596.579 | Q11: =(P11-P10)*1000 -> 3436 | R11: =N11-Q11 -> 3572 | S11: =S10 -> 10118 | T11: =S11-S10 -> 0 | U11: =U10 -> 420722 | V11: =U11-U10 -> 0 | W11: 32176 | X11: =W11-W10 -> 4 | Y11: 698227 | Z11: =Y11-Y10 -> 876 | AA11: =AA10 -> 35689 | AB11: =AA11-AA10 -> 0 | AC11: =AC10 -> 915313 | AD11: =AC11-AC10 -> 0 | AE11: =AB11+X11+T11 -> 4 | AF11: =V11+Z11+AD11 -> 876 | AG11: =IF(AE11>0,AF11/AE11,0) -> 219 | AI11: =R11-'EDl log'!B9 -> -863499
A12: ='General information '!F15 -> 0 | B12: =SUM(230*A12) -> 0 | C12: 44237 | D12: 32603330 | E12: =D12-D11 -> 1948 | F12: 3960337 | G12: =F12-F11 -> 634 | H12: 17787894 | I12: =H12-H11 -> 832 | J12: 28890152 | K12: =J12-J11 -> 2182 | L12: 24015650 | M12: =L12-L11 -> 1680 | N12: =M12+K12+I12+G12+E12 -> 7276 | O12: =IF(B12>0,N12/B12,0) -> 0 | P12: 16601.021 | Q12: =(P12-P11)*1000 -> 4442 | R12: =N12-Q12 -> 2834 | S12: =S11 -> 10118 | T12: =S12-S11 -> 0 | U12: =U11 -> 420722 | V12: =U12-U11 -> 0 | W12: 32182 | X12: =W12-W11 -> 6 | Y12: 699173 | Z12: =Y12-Y11 -> 946 | AA12: 35689 | AB12: =AA12-AA11 -> 0 | AC12: =AC11 -> 915313 | AD12: =AC12-AC11 -> 0 | AE12: =AB12+X12+T12 -> 6 | AF12: =V12+Z12+AD12 -> 946 | AG12: =IF(AE12>0,AF12/AE12,0) -> 157.66667 | AI12: =R12-'EDl log'!B10 -> -866646
A13: ='General information '!F16 -> 0 | B13: =SUM(230*A13) -> 0 | C13: 44238 | D13: 32605256 | E13: =D13-D12 -> 1926 | F13: 3960985 | G13: =F13-F12 -> 648 | H13: 17788782 | I13: =H13-H12 -> 888 | J13: 28892186 | K13: =J13-J12 -> 2034 | L13: 24017390 | M13: =L13-L12 -> 1740 | N13: =M13+K13+I13+G13+E13 -> 7236 | O13: =IF(B13>0,N13/B13,0) -> 0 | P13: 16605.02 | Q13: =(P13-P12)*1000 -> 3999 | R13: =N13-Q13 -> 3237 | S13: =S12 -> 10118 | T13: =S13-S12 -> 0 | U13: =U12 -> 420722 | V13: =U13-U12 -> 0 | W13: 32187 | X13: =W13-W12 -> 5 | Y13: 699988 | Z13: =Y13-Y12 -> 815 | AA13: =AA12 -> 35689 | AB13: =AA13-AA12 -> 0 | AC13: =AC12 -> 915313 | AD13: =AC13-AC12 -> 0 | AE13: =AB13+X13+T13 -> 5 | AF13: =V13+Z13+AD13 -> 815 | AG13: =IF(AE13>0,AF13/AE13,0) -> 163 | AI13: =R13-'EDl log'!B11 -> -868526
A14: ='General information '!F17 -> 0 | B14: =SUM(230*A14) -> 0 | C14: 44239 | D14: 32606678 | E14: =D14-D13 -> 1422 | F14: 3961594 | G14: =F14-F13 -> 609 | H14: 17789546 | I14: =H14-H13 -> 764 | J14: 28893682 | K14: =J14-J13 -> 1496 | L14: 24018742 | M14: =L14-L13 -> 1352 | N14: =M14+K14+I14+G14+E14 -> 5643 | O14: =IF(B14>0,N14/B14,0) -> 0 | P14: 16607.648 | Q14: =(P14-P13)*1000 -> 2628 | R14: =N14-Q14 -> 3015 | S14: =S13 -> 10118 | T14: =S14-S13 -> 0 | U14: =U13 -> 420722 | V14: =U14-U13 -> 0 | W14: 32191 | X14: =W14-W13 -> 4 | Y14: 700543 | Z14: =Y14-Y13 -> 555 | AA14: =AA13 -> 35689 | AB14: =AA14-AA13 -> 0 | AC14: =AC13 -> 915313 | AD14: =AC14-AC13 -> 0 | AE14: =AB14+X14+T14 -> 4 | AF14: =V14+Z14+AD14 -> 555 | AG14: =IF(AE14>0,AF14/AE14,0) -> 138.75 | AI14: =R14-'EDl log'!B12 -> -870707
A15: ='General information '!F18 -> 0 | B15: =SUM(230*A15) -> 0 | C15: 44240 | D15: =D14 -> 32606678 | E15: =D15-D14 -> 0 | F15: =F14 -> 3961594 | G15: =F15-F14 -> 0 | H15: =H14 -> 17789546 | I15: =H15-H14 -> 0 | J15: =J14 -> 28893682 | K15: =J15-J14 -> 0 | L15: =L14 -> 24018742 | M15: =L15-L14 -> 0 | N15: =M15+K15+I15+G15+E15 -> 0 | O15: =IF(B15>0,N15/B15,0) -> 0 | P15: =P14 -> 16607.648 | Q15: =(P15-P14)*1000 -> 0 | R15: =N15-Q15 -> 0 | S15: =S14 -> 10118 | T15: =S15-S14 -> 0 | U15: =U14 -> 420722 | V15: =U15-U14 -> 0 | W15: =W14 -> 32191 | X15: =W15-W14 -> 0 | Y15: =Y14 -> 700543 | Z15: =Y15-Y14 -> 0 | AA15: =AA14 -> 35689 | AB15: =AA15-AA14 -> 0 | AC15: =AC14 -> 915313 | AD15: =AC15-AC14 -> 0 | AE15: =AB15+X15+T15 -> 0 | AF15: =V15+Z15+AD15 -> 0 | AG15: =IF(AE15>0,AF15/AE15,0) -> 0 | AI15: =R15-'EDl log'!B13 -> -875296
A16: ='General information '!F19 -> 0 | B16: =SUM(230*A16) -> 0 | C16: 44241 | D16: =D15 -> 32606678 | E16: =D16-D15 -> 0 | F16: =F15 -> 3961594 | G16: =F16-F15 -> 0 | H16: =H15 -> 17789546 | I16: =H16-H15 -> 0 | J16: =J15 -> 28893682 | K16: =J16-J15 -> 0 | L16: =L15 -> 24018742 | M16: =L16-L15 -> 0 | N16: =M16+K16+I16+G16+E16 -> 0 | O16: =IF(B16>0,N16/B16,0) -> 0 | P16: =P15 -> 16607.648 | Q16: =(P16-P15)*1000 -> 0 | R16: =N16-Q16 -> 0 | S16: =S15 -> 10118 | T16: =S16-S15 -> 0 | U16: =U15 -> 420722 | V16: =U16-U15 -> 0 | W16: =W15 -> 32191 | X16: =W16-W15 -> 0 | Y16: =Y15 -> 700543 | Z16: =Y16-Y15 -> 0 | AA16: =AA15 -> 35689 | AB16: =AA16-AA15 -> 0 | AC16: =AC15 -> 915313 | AD16: =AC16-AC15 -> 0 | AE16: =AB16+X16+T16 -> 0 | AF16: =V16+Z16+AD16 -> 0 | AG16: =IF(AE16>0,AF16/AE16,0) -> 0 | AI16: =R16-'EDl log'!B14 -> -877076
A17: ='General information '!F20 -> 0 | B17: =SUM(230*A17) -> 0 | C17: 44242 | D17: =D16 -> 32606678 | E17: =D17-D16 -> 0 | F17: =F16 -> 3961594 | G17: =F17-F16 -> 0 | H17: =H16 -> 17789546 | I17: =H17-H16 -> 0 | J17: =J16 -> 28893682 | K17: =J17-J16 -> 0 | L17: =L16 -> 24018742 | M17: =L17-L16 -> 0 | N17: =M17+K17+I17+G17+E17 -> 0 | O17: =IF(B17>0,N17/B17,0) -> 0 | P17: =P16 -> 16607.648 | Q17: =(P17-P16)*1000 -> 0 | R17: =N17-Q17 -> 0 | S17: =S16 -> 10118 | T17: =S17-S16 -> 0 | U17: =U16 -> 420722 | V17: =U17-U16 -> 0 | W17: =W16 -> 32191 | X17: =W17-W16 -> 0 | Y17: =Y16 -> 700543 | Z17: =Y17-Y16 -> 0 | AA17: =AA16 -> 35689 | AB17: =AA17-AA16 -> 0 | AC17: =AC16 -> 915313 | AD17: =AC17-AC16 -> 0 | AE17: =AB17+X17+T17 -> 0 | AF17: =V17+Z17+AD17 -> 0 | AG17: =IF(AE17>0,AF17/AE17,0) -> 0 | AI17: =R17-'EDl log'!B15 -> -878743
A18: ='General information '!F21 -> 0 | B18: =SUM(230*A18) -> 0 | C18: 44243 | D18: =D17 -> 32606678 | E18: =D18-D17 -> 0 | F18: =F17 -> 3961594 | G18: =F18-F17 -> 0 | H18: =H17 -> 17789546 | I18: =H18-H17 -> 0 | J18: =J17 -> 28893682 | K18: =J18-J17 -> 0 | L18: =L17 -> 24018742 | M18: =L18-L17 -> 0 | N18: =M18+K18+I18+G18+E18 -> 0 | O18: =IF(B18>0,N18/B18,0) -> 0 | P18: =P17 -> 16607.648 | Q18: =(P18-P17)*1000 -> 0 | R18: =N18-Q18 -> 0 | S18: =S17 -> 10118 | T18: =S18-S17 -> 0 | U18: =U17 -> 420722 | V18: =U18-U17 -> 0 | W18: =W17 -> 32191 | X18: =W18-W17 -> 0 | Y18: =Y17 -> 700543 | Z18: =Y18-Y17 -> 0 | AA18: =AA17 -> 35689 | AB18: =AA18-AA17 -> 0 | AC18: =AC17 -> 915313 | AD18: =AC18-AC17 -> 0 | AE18: =AB18+X18+T18 -> 0 | AF18: =V18+Z18+AD18 -> 0 | AG18: =IF(AE18>0,AF18/AE18,0) -> 0 | AI18: =R18-'EDl log'!B16 -> -878743
A19: ='General information '!F22 -> 0 | B19: =SUM(230*A19) -> 0 | C19: 44244 | D19: =D18 -> 32606678 | E19: =D19-D18 -> 0 | F19: =F18 -> 3961594 | G19: =F19-F18 -> 0 | H19: =H18 -> 17789546 | I19: =H19-H18 -> 0 | J19: =J18 -> 28893682 | K19: =J19-J18 -> 0 | L19: =L18 -> 24018742 | M19: =L19-L18 -> 0 | N19: =M19+K19+I19+G19+E19 -> 0 | O19: =IF(B19>0,N19/B19,0) -> 0 | P19: =P18 -> 16607.648 | Q19: =(P19-P18)*1000 -> 0 | R19: =N19-Q19 -> 0 | S19: =S18 -> 10118 | T19: =S19-S18 -> 0 | U19: =U18 -> 420722 | V19: =U19-U18 -> 0 | W19: =W18 -> 32191 | X19: =W19-W18 -> 0 | Y19: =Y18 -> 700543 | Z19: =Y19-Y18 -> 0 | AA19: =AA18 -> 35689 | AB19: =AA19-AA18 -> 0 | AC19: =AC18 -> 915313 | AD19: =AC19-AC18 -> 0 | AE19: =AB19+X19+T19 -> 0 | AF19: =V19+Z19+AD19 -> 0 | AG19: =IF(AE19>0,AF19/AE19,0) -> 0 | AI19: =R19-'EDl log'!B17 -> -878743
A20: ='General information '!F23 -> 0 | B20: =SUM(230*A20) -> 0 | C20: 44245 | D20: =D19 -> 32606678 | E20: =D20-D19 -> 0 | F20: =F19 -> 3961594 | G20: =F20-F19 -> 0 | H20: =H19 -> 17789546 | I20: =H20-H19 -> 0 | J20: =J19 -> 28893682 | K20: =J20-J19 -> 0 | L20: =L19 -> 24018742 | M20: =L20-L19 -> 0 | N20: =M20+K20+I20+G20+E20 -> 0 | O20: =IF(B20>0,N20/B20,0) -> 0 | P20: =P19 -> 16607.648 | Q20: =(P20-P19)*1000 -> 0 | R20: =N20-Q20 -> 0 | S20: =S19 -> 10118 | T20: =S20-S19 -> 0 | U20: =U19 -> 420722 | V20: =U20-U19 -> 0 | W20: =W19 -> 32191 | X20: =W20-W19 -> 0 | Y20: =Y19 -> 700543 | Z20: =Y20-Y19 -> 0 | AA20: =AA19 -> 35689 | AB20: =AA20-AA19 -> 0 | AC20: =AC19 -> 915313 | AD20: =AC20-AC19 -> 0 | AE20: =AB20+X20+T20 -> 0 | AF20: =V20+Z20+AD20 -> 0 | AG20: =IF(AE20>0,AF20/AE20,0) -> 0 | AI20: =R20-'EDl log'!B18 -> -878743
A21: ='General information '!F24 -> 0 | B21: =SUM(230*A21) -> 0 | C21: 44246 | D21: =D20 -> 32606678 | E21: =D21-D20 -> 0 | F21: =F20 -> 3961594 | G21: =F21-F20 -> 0 | H21: =H20 -> 17789546 | I21: =H21-H20 -> 0 | J21: =J20 -> 28893682 | K21: =J21-J20 -> 0 | L21: =L20 -> 24018742 | M21: =L21-L20 -> 0 | N21: =M21+K21+I21+G21+E21 -> 0 | O21: =IF(B21>0,N21/B21,0) -> 0 | P21: =P20 -> 16607.648 | Q21: =(P21-P20)*1000 -> 0 | R21: =N21-Q21 -> 0 | S21: =S20 -> 10118 | T21: =S21-S20 -> 0 | U21: =U20 -> 420722 | V21: =U21-U20 -> 0 | W21: =W20 -> 32191 | X21: =W21-W20 -> 0 | Y21: =Y20 -> 700543 | Z21: =Y21-Y20 -> 0 | AA21: =AA20 -> 35689 | AB21: =AA21-AA20 -> 0 | AC21: =AC20 -> 915313 | AD21: =AC21-AC20 -> 0 | AE21: =AB21+X21+T21 -> 0 | AF21: =V21+Z21+AD21 -> 0 | AG21: =IF(AE21>0,AF21/AE21,0) -> 0 | AI21: =R21-'EDl log'!B19 -> -878743
A22: ='General information '!F25 -> 0 | B22: =SUM(230*A22) -> 0 | C22: 44247 | D22: =D21 -> 32606678 | E22: =D22-D21 -> 0 | F22: =F21 -> 3961594 | G22: =F22-F21 -> 0 | H22: =H21 -> 17789546 | I22: =H22-H21 -> 0 | J22: =J21 -> 28893682 | K22: =J22-J21 -> 0 | L22: =L21 -> 24018742 | M22: =L22-L21 -> 0 | N22: =M22+K22+I22+G22+E22 -> 0 | O22: =IF(B22>0,N22/B22,0) -> 0 | P22: =P21 -> 16607.648 | Q22: =(P22-P21)*1000 -> 0 | R22: =N22-Q22 -> 0 | S22: =S21 -> 10118 | T22: =S22-S21 -> 0 | U22: =U21 -> 420722 | V22: =U22-U21 -> 0 | W22: =W21 -> 32191 | X22: =W22-W21 -> 0 | Y22: =Y21 -> 700543 | Z22: =Y22-Y21 -> 0 | AA22: =AA21 -> 35689 | AB22: =AA22-AA21 -> 0 | AC22: =AC21 -> 915313 | AD22: =AC22-AC21 -> 0 | AE22: =AB22+X22+T22 -> 0 | AF22: =V22+Z22+AD22 -> 0 | AG22: =IF(AE22>0,AF22/AE22,0) -> 0 | AI22: =R22-'EDl log'!B20 -> -878743
A23: ='General information '!F26 -> 0 | B23: =SUM(230*A23) -> 0 | C23: 44248 | D23: =D22 -> 32606678 | E23: =D23-D22 -> 0 | F23: =F22 -> 3961594 | G23: =F23-F22 -> 0 | H23: =H22 -> 17789546 | I23: =H23-H22 -> 0 | J23: =J22 -> 28893682 | K23: =J23-J22 -> 0 | L23: =L22 -> 24018742 | M23: =L23-L22 -> 0 | N23: =M23+K23+I23+G23+E23 -> 0 | O23: =IF(B23>0,N23/B23,0) -> 0 | P23: =P22 -> 16607.648 | Q23: =(P23-P22)*1000 -> 0 | R23: =N23-Q23 -> 0 | S23: =S22 -> 10118 | T23: =S23-S22 -> 0 | U23: =U22 -> 420722 | V23: =U23-U22 -> 0 | W23: =W22 -> 32191 | X23: =W23-W22 -> 0 | Y23: =Y22 -> 700543 | Z23: =Y23-Y22 -> 0 | AA23: =AA22 -> 35689 | AB23: =AA23-AA22 -> 0 | AC23: =AC22 -> 915313 | AD23: =AC23-AC22 -> 0 | AE23: =AB23+X23+T23 -> 0 | AF23: =V23+Z23+AD23 -> 0 | AG23: =IF(AE23>0,AF23/AE23,0) -> 0 | AI23: =R23-'EDl log'!B21 -> -878743
A24: ='General information '!F27 -> 0 | B24: =SUM(230*A24) -> 0 | C24: 44249 | D24: =D23 -> 32606678 | E24: =D24-D23 -> 0 | F24: =F23 -> 3961594 | G24: =F24-F23 -> 0 | H24: =H23 -> 17789546 | I24: =H24-H23 -> 0 | J24: =J23 -> 28893682 | K24: =J24-J23 -> 0 | L24: =L23 -> 24018742 | M24: =L24-L23 -> 0 | N24: =M24+K24+I24+G24+E24 -> 0 | O24: =IF(B24>0,N24/B24,0) -> 0 | P24: =P23 -> 16607.648 | Q24: =(P24-P23)*1000 -> 0 | R24: =N24-Q24 -> 0 | S24: =S23 -> 10118 | T24: =S24-S23 -> 0 | U24: =U23 -> 420722 | V24: =U24-U23 -> 0 | W24: =W23 -> 32191 | X24: =W24-W23 -> 0 | Y24: =Y23 -> 700543 | Z24: =Y24-Y23 -> 0 | AA24: =AA23 -> 35689 | AB24: =AA24-AA23 -> 0 | AC24: =AC23 -> 915313 | AD24: =AC24-AC23 -> 0 | AE24: =AB24+X24+T24 -> 0 | AF24: =V24+Z24+AD24 -> 0 | AG24: =IF(AE24>0,AF24/AE24,0) -> 0 | AI24: =R24-'EDl log'!B22 -> -878743
A25: ='General information '!F28 -> 0 | B25: =SUM(230*A25) -> 0 | C25: 44250 | D25: =D24 -> 32606678 | E25: =D25-D24 -> 0 | F25: =F24 -> 3961594 | G25: =F25-F24 -> 0 | H25: =H24 -> 17789546 | I25: =H25-H24 -> 0 | J25: =J24 -> 28893682 | K25: =J25-J24 -> 0 | L25: =L24 -> 24018742 | M25: =L25-L24 -> 0 | N25: =M25+K25+I25+G25+E25 -> 0 | O25: =IF(B25>0,N25/B25,0) -> 0 | P25: =P24 -> 16607.648 | Q25: =(P25-P24)*1000 -> 0 | R25: =N25-Q25 -> 0 | S25: =S24 -> 10118 | T25: =S25-S24 -> 0 | U25: =U24 -> 420722 | V25: =U25-U24 -> 0 | W25: =W24 -> 32191 | X25: =W25-W24 -> 0 | Y25: =Y24 -> 700543 | Z25: =Y25-Y24 -> 0 | AA25: =AA24 -> 35689 | AB25: =AA25-AA24 -> 0 | AC25: =AC24 -> 915313 | AD25: =AC25-AC24 -> 0 | AE25: =AB25+X25+T25 -> 0 | AF25: =V25+Z25+AD25 -> 0 | AG25: =IF(AE25>0,AF25/AE25,0) -> 0 | AI25: =R25-'EDl log'!B23 -> -878743
A26: ='General information '!F29 -> 0 | B26: =SUM(230*A26) -> 0 | C26: 44251 | D26: =D25 -> 32606678 | E26: =D26-D25 -> 0 | F26: =F25 -> 3961594 | G26: =F26-F25 -> 0 | H26: =H25 -> 17789546 | I26: =H26-H25 -> 0 | J26: =J25 -> 28893682 | K26: =J26-J25 -> 0 | L26: =L25 -> 24018742 | M26: =L26-L25 -> 0 | N26: =M26+K26+I26+G26+E26 -> 0 | O26: =IF(B26>0,N26/B26,0) -> 0 | P26: =P25 -> 16607.648 | Q26: =(P26-P25)*1000 -> 0 | R26: =N26-Q26 -> 0 | S26: =S25 -> 10118 | T26: =S26-S25 -> 0 | U26: =U25 -> 420722 | V26: =U26-U25 -> 0 | W26: =W25 -> 32191 | X26: =W26-W25 -> 0 | Y26: =Y25 -> 700543 | Z26: =Y26-Y25 -> 0 | AA26: =AA25 -> 35689 | AB26: =AA26-AA25 -> 0 | AC26: =AC25 -> 915313 | AD26: =AC26-AC25 -> 0 | AE26: =AB26+X26+T26 -> 0 | AF26: =V26+Z26+AD26 -> 0 | AG26: =IF(AE26>0,AF26/AE26,0) -> 0 | AI26: =R26-'EDl log'!B24 -> -878743
... A30: ='General information '!F33 -> 0 | B30: =SUM(230*A30) -> 0 | C30: 44255 | D30: =D29 -> 32606678 | E30: =D30-D29 -> 0 | F30: =F29 -> 3961594 | G30: =F30-F29 -> 0 | H30: =H29 -> 17789546 | I30: =H30-H29 -> 0 | J30: =J29 -> 28893682 | K30: =J30-J29 -> 0 | L30: =L29 -> 24018742 | M30: =L30-L29 -> 0 | N30: =M30+K30+I30+G30+E30 -> 0 | O30: =IF(B30>0,N30/B30,0) -> 0 | P30: =P29 -> 16607.648 | Q30: =(P30-P29)*1000 -> 0 | R30: =N30-Q30 -> 0 | S30: =S29 -> 10118 | T30: =S30-S29 -> 0 | U30: =U29 -> 420722 | V30: =U30-U29 -> 0 | W30: =W29 -> 32191 | X30: =W30-W29 -> 0 | Y30: =Y29 -> 700543 | Z30: =Y30-Y29 -> 0 | AA30: =AA29 -> 35689 | AB30: =AA30-AA29 -> 0 | AC30: =AC29 -> 915313 | AD30: =AC30-AC29 -> 0 | AE30: =AB30+X30+T30 -> 0 | AF30: =V30+Z30+AD30 -> 0 | AG30: =IF(AE30>0,AF30/AE30,0) -> 0 | AI30: =R30-'EDl log'!B28 -> -878743

Sheet B5
F1: Boiler A | J1: =J33 -> 64.625 | K1: Boiler B | P1: Boiler C | V1: Boiler | X1: SteamA | AC1: SteamB | AH1: Steam | AI1: Boiler & steam | AL1: Total Boiler Runing H | AM1: Total Steam Runing H | AN1: GAS1 % | AO1: GAS1/L | AP1: GAS2% | AQ1: Gas2/L | AR1: GAS3% | AS1: GAS3/L | AU1: Gas Cons | AV1: Delivery | AW1: Cost/L
B2: Level Tank Gen | C2: Level tank Boiler | D2: Daily Cons Bo. | E2: Boiler litter | F2: Boiler A | G2: Run Hr a | H2: Boiler A fuel | I2: Daily consumption | J2: AVG | K2: index Run H | L2: Run Hrb | M2: Boiler B Fuel | O2: Daily consumption | P2: Boiler C | S2: Run C | U2: Total RH | V2: Total Fuel | X2: SteamA | Y2: Run SA | Z2: Steam A Conter | AA2: Liters | AC2: SteamB | AD2: Run SteamB | AE2: Steam B Conter | AF2: SB Litters | AG2: Avg | AH2: Total Fuel | AI2: Total Fuel
S3: 0
A4: =ELEC!C2 -> 44227 | B4: =[2]B5!B35 -> 236 | C4: =[2]B5!C35 -> 242 | D4: =[2]B5!D35 -> 3 | E4: =[2]B5!E35 -> 25.14 | F4: =[2]B5!F35 -> 1715 | G4: =[2]B5!G35 -> 0 | H4: =[2]B5!H35 -> 3991 | I4: =[2]B5!I35 -> 0 | ... AU4: =[2]B5!AU35 -> 0 | AV4: 0.1 | AW4: 0.1 | AX4: =[2]B5!AX35 -> 0.8
A5: =ELEC!C3 -> 44228 | B5: 232 | C5: 238 | D5: =C4-C5 -> 4 | E5: =D5*8.38 -> 33.52 | F5: 1717 | G5: =F5-F4 -> 2 | H5: 4147 | I5: =SUM(H5-H4) -> 156 | J5: 1 | K5: =K4 -> 2216 | L5: =K5-K4 -> 0 | M5: =M4 -> 162924 | N5: =M5-M4 -> 0 | O5: =O4 -> 1869 | P5: 1966 | Q5: 166371 | R5: =Q5-Q4 -> 192 | S5: =SUM(P5-P4) -> 2 | T5: =SUM(S5*$T$2) -> 0 | U5: =SUM(G5+L5+S5) -> 4 | V5: =R5+N5+I5:I5 -> 348 | W5: =SUM(V5/U5) -> 87 | X5: 2453 | Y5: =X5-X4 -> 1 | Z5: 137950.7 | AA5: =Z5-Z4 -> 119.6 | AB5: =SUM(Y5*$AB$2) -> 0 | AC5: =AC4 -> 1934 | AD5: =AC5-AC4 -> 0 | AE5: =AE4 -> 365317 | AF5: =AE5-AE4 -> 0 | AG5: =IF(AD5>0,AF5/AD5,0) -> 0 | AH5: =AF5+AA5 -> 119.6 | AI5: =SUM(AH5+V5) -> 467.6 | AJ5: =-tanks!AW6 -> 467.6 | AK5: =SUM(AJ5-AI5) -> 0 | AL5: =S5+L5+G5 -> 4 | AM5: =Y5+AD5 -> 1 | AN5: =AN4 -> 67 | AO5: =(AN5/100)*3000 -> 2010 | AP5: =AP4 -> 55 | AQ5: =(AP5/100)*3000 -> 1650 | AR5: =AR4 -> 61 | AS5: =(AR5/100)*3000 -> 1830 | AT5: =SUM(AO5+AQ5+AS5) -> 5490 | AU5: =AT4-AT5+AV5 -> 0 | AX5: =IF(AV5>0,AW5,AX4) -> 0.8
A6: =ELEC!C4 -> 44229 | B6: 229 | C6: 235 | D6: =C5-C6 -> 3 | E6: =D6*8.38 -> 25.14 | F6: 1719 | G6: =F6-F5 -> 2 | H6: 4287 | I6: =SUM(H6-H5) -> 140 | J6: =IF(G6>0,I6/G6,0) -> 70 | K6: 2218 | L6: =K6-K5 -> 2 | M6: 163018 | N6: =M6-M5 -> 94 | O6: =O5 -> 1869 | P6: =P5 -> 1966 | Q6: =Q5 -> 166371 | R6: =Q6-Q5 -> 0 | S6: =SUM(P6-P5) -> 0 | T6: =SUM(S6*$T$2) -> 0 | U6: =SUM(G6+L6+S6) -> 4 | V6: =R6+N6+I6:I6 -> 234 | W6: =SUM(V6/U6) -> 58.5 | X6: =X5 -> 2453 | Y6: =X6-X5 -> 0 | Z6: =Z5 -> 137950.7 | AA6: =Z6-Z5 -> 0 | AB6: =SUM(Y6*$AB$2) -> 0 | AC6: =AC5 -> 1934 | AD6: =AC6-AC5 -> 0 | AE6: =AE5 -> 365317 | AF6: =AE6-AE5 -> 0 | AG6: =IF(AD6>0,AF6/AD6,0) -> 0 | AH6: =AF6+AA6 -> 0 | AI6: =SUM(AH6+V6) -> 234 | AJ6: =-tanks!AW7 -> 234 | AK6: =SUM(AJ6-AI6) -> 0 | AL6: =S6+L6+G6 -> 4 | AM6: =Y6+AD6 -> 0 | AN6: =AN5 -> 67 | AO6: =(AN6/100)*3000 -> 2010 | AP6: =AP5 -> 55 | AQ6: =(AP6/100)*3000 -> 1650 | AR6: =AR5 -> 61 | AS6: =(AR6/100)*3000 -> 1830 | AT6: =SUM(AO6+AQ6+AS6) -> 5490 | AU6: =AT5-AT6+AV6 -> 0 | AX6: =IF(AV6>0,AW6,AX5) -> 0.8
A7: =ELEC!C5 -> 44230 | B7: 225 | C7: 231 | D7: =C6-C7 -> 4 | E7: =D7*8.38 -> 33.52 | F7: =F6 -> 1719 | G7: =F7-F6 -> 0 | H7: =H6 -> 4287 | I7: =SUM(H7-H6) -> 0 | J7: =IF(G7>0,I7/G7,0) -> 0 | K7: 2220 | L7: =K7-K6 -> 2 | M7: 163181 | N7: =M7-M6 -> 163 | O7: =O6 -> 1869 | P7: 1968 | Q7: 166462 | R7: =Q7-Q6 -> 91 | S7: =SUM(P7-P6) -> 2 | T7: =SUM(S7*$T$2) -> 0 | U7: =SUM(G7+L7+S7) -> 4 | V7: =R7+N7+I7:I7 -> 254 | W7: =SUM(V7/U7) -> 63.5 | X7: =X6 -> 2453 | Y7: =X7-X6 -> 0 | Z7: =Z6 -> 137950.7 | AA7: =Z7-Z6 -> 0 | AB7: =SUM(Y7*$AB$2) -> 0 | AC7: =AC6 -> 1934 | AD7: =AC7-AC6 -> 0 | AE7: 365352 | AF7: =AE7-AE6 -> 35 | AG7: =IF(AD7>0,AF7/AD7,0) -> 0 | AH7: =AF7+AA7 -> 35 | AI7: =SUM(AH7+V7) -> 289 | AJ7: =-tanks!AW8 -> 289 | AK7: =SUM(AJ7-AI7) -> 0 | AL7: =S7+L7+G7 -> 4 | AM7: =Y7+AD7 -> 0 | AN7: =AN6 -> 67 | AO7: =(AN7/100)*3000 -> 2010 | AP7: =AP6 -> 55 | AQ7: =(AP7/100)*3000 -> 1650 | AR7: =AR6 -> 61 | AS7: =(AR7/100)*3000 -> 1830 | AT7: =SUM(AO7+AQ7+AS7) -> 5490 | AU7: =AT6-AT7+AV7 -> 0 | AX7: =IF(AV7>0,AW7,AX6) -> 0.8
A8: =ELEC!C6 -> 44231 | B8: 221 | C8: 227 | D8: =C7-C8 -> 4 | E8: =D8*8.38 -> 33.52 | F8: 1721 | G8: =F8-F7 -> 2 | H8: 4416 | I8: =SUM(H8-H7) -> 129 | J8: =IF(G8>0,I8/G8,0) -> 64.5 | K8: =K7 -> 2220 | L8: =K8-K7 -> 0 | M8: =M7 -> 163181 | N8: =M8-M7 -> 0 | O8: =O7 -> 1869 | P8: 1970 | Q8: 166647 | R8: =Q8-Q7 -> 185 | S8: =SUM(P8-P7) -> 2 | T8: =SUM(S8*$T$2) -> 0 | U8: =SUM(G8+L8+S8) -> 4 | V8: =R8+N8+I8:I8 -> 314 | W8: =SUM(V8/U8) -> 78.5 | X8: =X7 -> 2453 | Y8: =X8-X7 -> 0 | Z8: =Z7 -> 137950.7 | AA8: =Z8-Z7 -> 0 | AB8: =SUM(Y8*$AB$2) -> 0 | AC8: =AC7 -> 1934 | AD8: =AC8-AC7 -> 0 | AE8: =AE7 -> 365352 | AF8: =AE8-AE7 -> 0 | AG8: =IF(AD8>0,AF8/AD8,0) -> 0 | AH8: =AF8+AA8 -> 0 | AI8: =SUM(AH8+V8) -> 314 | AJ8: =-tanks!AW9 -> 314 | AK8: =SUM(AJ8-AI8) -> 0 | AL8: =S8+L8+G8 -> 4 | AM8: =Y8+AD8 -> 0 | AN8: =AN7 -> 67 | AO8: =(AN8/100)*3000 -> 2010 | AP8: =AP7 -> 55 | AQ8: =(AP8/100)*3000 -> 1650 | AR8: =AR7 -> 61 | AS8: =(AR8/100)*3000 -> 1830 | AT8: =SUM(AO8+AQ8+AS8) -> 5490 | AU8: =AT7-AT8+AV8 -> 0 | AX8: =IF(AV8>0,AW8,AX7) -> 0.8
A9: =ELEC!C7 -> 44232 | B9: 247 | C9: 252 | D9: =C8-C9 -> -25 | E9: =D9*8.38 -> -209.5 | F9: 1724 | G9: =F9-F8 -> 3 | H9: 4626 | I9: =SUM(H9-H8) -> 210 | J9: =IF(G9>0,I9/G9,0) -> 70 | K9: 2222 | L9: =K9-K8 -> 2 | M9: 163362 | N9: =M9-M8 -> 181 | O9: =O8 -> 1869 | P9: =P8 -> 1970 | Q9: =Q8 -> 166647 | R9: =Q9-Q8 -> 0 | S9: =SUM(P9-P8) -> 0 | T9: =SUM(S9*$T$2) -> 0 | U9: =SUM(G9+L9+S9) -> 5 | V9: =R9+N9+I9:I9 -> 391 | W9: =SUM(V9/U9) -> 78.2 | X9: =X8 -> 2453 | Y9: =X9-X8 -> 0 | Z9: =Z8 -> 137950.7 | AA9: =Z9-Z8 -> 0 | AB9: =SUM(Y9*$AB$2) -> 0 | AC9: 1934 | AD9: =AC9-AC8 -> 0 | AE9: =AE8 -> 365352 | AF9: =AE9-AE8 -> 0 | AG9: =IF(AD9>0,AF9/AD9,0) -> 0 | AH9: =AF9+AA9 -> 0 | AI9: =SUM(AH9+V9) -> 391 | AJ9: =-tanks!AW10 -> 391 | AK9: =SUM(AJ9-AI9) -> 0 | AL9: =S9+L9+G9 -> 5 | AM9: =Y9+AD9 -> 0 | AN9: =AN8 -> 67 | AO9: =(AN9/100)*3000 -> 2010 | AP9: =AP8 -> 55 | AQ9: =(AP9/100)*3000 -> 1650 | AR9: =AR8 -> 61 | AS9: =(AR9/100)*3000 -> 1830 | AT9: =SUM(AO9+AQ9+AS9) -> 5490 | AU9: =AT8-AT9+AV9 -> 0 | AX9: =IF(AV9>0,AW9,AX8) -> 0.8
A10: =ELEC!C8 -> 44233 | B10: 244 | C10: 250 | D10: =C9-C10 -> 2 | E10: =D10*8.38 -> 16.76 | F10: =F9 -> 1724 | G10: =F10-F9 -> 0 | H10: =H9 -> 4626 | I10: =SUM(H10-H9) -> 0 | J10: =IF(G10>0,I10/G10,0) -> 0 | K10: 2224 | L10: =K10-K9 -> 2 | M10: 163480 | N10: =M10-M9 -> 118 | O10: =O9 -> 1869 | P10: 1973 | Q10: 166840 | R10: =Q10-Q9 -> 193 | S10: =SUM(P10-P9) -> 3 | T10: =SUM(S10*$T$2) -> 0 | U10: =SUM(G10+L10+S10) -> 5 | V10: =R10+N10+I10:I10 -> 311 | W10: =SUM(V10/U10) -> 62.2 | X10: =X9 -> 2453 | Y10: =X10-X9 -> 0 | Z10: =Z9 -> 137950.7 | AA10: =Z10-Z9 -> 0 | AB10: =SUM(Y10*$AB$2) -> 0 | AC10: =AC9 -> 1934 | AD10: =AC10-AC9 -> 0 | AE10: =AE9 -> 365352 | AF10: =AE10-AE9 -> 0 | AG10: =IF(AD10>0,AF10/AD10,0) -> 0 | AH10: =AF10+AA10 -> 0 | AI10: =SUM(AH10+V10) -> 311 | AJ10: =-tanks!AW11 -> 311 | AK10: =SUM(AJ10-AI10) -> 0 | AL10: =S10+L10+G10 -> 5 | AM10: =Y10+AD10 -> 0 | AN10: =AN9 -> 67 | AO10: =(AN10/100)*3000 -> 2010 | AP10: =AP9 -> 55 | AQ10: =(AP10/100)*3000 -> 1650 | AR10: =AR9 -> 61 | AS10: =(AR10/100)*3000 -> 1830 | AT10: =SUM(AO10+AQ10+AS10) -> 5490 | AU10: =AT9-AT10+AV10 -> 0 | AX10: =IF(AV10>0,AW10,AX9) -> 0.8
A11: =ELEC!C9 -> 44234 | B11: 240 | C11: 246 | D11: =C10-C11 -> 4 | E11: =D11*8.38 -> 33.52 | F11: 1725 | G11: =F11-F10 -> 1 | H11: 4721 | I11: =SUM(H11-H10) -> 95 | J11: =IF(G11>0,I11/G11,0) -> 95 | K11: =K10 -> 2224 | L11: =K11-K10 -> 0 | M11: =M10 -> 163480 | N11: =M11-M10 -> 0 | O11: =O10 -> 1869 | P11: 1975 | Q11: 167024 | R11: =Q11-Q10 -> 184 | S11: =SUM(P11-P10) -> 2 | T11: =SUM(S11*$T$2) -> 0 | U11: =SUM(G11+L11+S11) -> 3 | V11: =R11+N11+I11:I11 -> 279 | W11: =SUM(V11/U11) -> 93 | X11: =X10 -> 2453 | Y11: =X11-X10 -> 0 | Z11: =Z10 -> 137950.7 | AA11: =Z11-Z10 -> 0 | AB11: =SUM(Y11*$AB$2) -> 0 | AC11: =AC10 -> 1934 | AD11: =AC11-AC10 -> 0 | AE11: =AE10 -> 365352 | AF11: =AE11-AE10 -> 0 | AG11: =IF(AD11>0,AF11/AD11,0) -> 0 | AH11: =AF11+AA11 -> 0 | AI11: =SUM(AH11+V11) -> 279 | AJ11: =-tanks!AW12 -> 279 | AK11: =SUM(AJ11-AI11) -> 0 | AL11: =S11+L11+G11 -> 3 | AM11: =Y11+AD11 -> 0 | AN11: =AN10 -> 67 | AO11: =(AN11/100)*3000 -> 2010 | AP11: =AP10 -> 55 | AQ11: =(AP11/100)*3000 -> 1650 | AR11: =AR10 -> 61 | AS11: =(AR11/100)*3000 -> 1830 | AT11: =SUM(AO11+AQ11+AS11) -> 5490 | AU11: =AT10-AT11+AV11 -> 0 | AX11: =IF(AV11>0,AW11,AX10) -> 0.8
A12: =ELEC!C10 -> 44235 | B12: 237 | C12: 243 | D12: =C11-C12 -> 3 | E12: =D12*8.38 -> 25.14 | F12: 1727 | G12: =F12-F11 -> 2 | H12: 4872 | I12: =SUM(H12-H11) -> 151 | J12: =IF(G12>0,I12/G12,0) -> 75.5 | K12: 2225 | L12: =K12-K11 -> 1 | M12: 163585 | N12: =M12-M11 -> 105 | O12: =O11 -> 1869 | P12: =P11 -> 1975 | Q12: =Q11 -> 167024 | R12: =Q12-Q11 -> 0 | S12: =SUM(P12-P11) -> 0 | T12: =SUM(S12*$T$2) -> 0 | U12: =SUM(G12+L12+S12) -> 3 | V12: =R12+N12+I12:I12 -> 256 | W12: =SUM(V12/U12) -> 85.333333 | X12: 2454 | Y12: =X12-X11 -> 1 | Z12: 138028.1 | AA12: =Z12-Z11 -> 77.4 | AB12: =SUM(Y12*$AB$2) -> 0 | AC12: =AC11 -> 1934 | AD12: =AC12-AC11 -> 0 | AE12: =AE11 -> 365352 | AF12: =AE12-AE11 -> 0 | AG12: =IF(AD12>0,AF12/AD12,0) -> 0 | AH12: =AF12+AA12 -> 77.4 | AI12: =SUM(AH12+V12) -> 333.4 | AJ12: =-tanks!AW13 -> 333.4 | AK12: =SUM(AJ12-AI12) -> 0 | AL12: =S12+L12+G12 -> 3 | AM12: =Y12+AD12 -> 1 | AN12: =AN11 -> 67 | AO12: =(AN12/100)*3000 -> 2010 | AP12: =AP11 -> 55 | AQ12: =(AP12/100)*3000 -> 1650 | AR12: =AR11 -> 61 | AS12: =(AR12/100)*3000 -> 1830 | AT12: =SUM(AO12+AQ12+AS12) -> 5490 | AU12: =AT11-AT12+AV12 -> 0 | AX12: =IF(AV12>0,AW12,AX11) -> 0.8
A13: =ELEC!C11 -> 44236 | B13: 233 | C13: 239 | D13: =C12-C13 -> 4 | E13: =D13*8.38 -> 33.52 | F13: =F12 -> 1727 | G13: =F13-F12 -> 0 | H13: =H12 -> 4872 | I13: =SUM(H13-H12) -> 0 | J13: =IF(G13>0,I13/G13,0) -> 0 | K13: 2227 | L13: =K13-K12 -> 2 | M13: 163735 | N13: =M13-M12 -> 150 | O13: =O12 -> 1869 | P13: 1976 | Q13: 167110 | R13: =Q13-Q12 -> 86 | S13: =SUM(P13-P12) -> 1 | T13: =SUM(S13*$T$2) -> 0 | U13: =SUM(G13+L13+S13) -> 3 | V13: =R13+N13+I13:I13 -> 236 | W13: =SUM(V13/U13) -> 78.666667 | X13: =X12 -> 2454 | Y13: =X13-X12 -> 0 | Z13: =Z12 -> 138028.1 | AA13: =Z13-Z12 -> 0 | AB13: =SUM(Y13*$AB$2) -> 0 | AC13: =AC12 -> 1934 | AD13: =AC13-AC12 -> 0 | AE13: =AE12 -> 365352 | AF13: =AE13-AE12 -> 0 | AG13: =IF(AD13>0,AF13/AD13,0) -> 0 | AH13: =AF13+AA13 -> 0 | AI13: =SUM(AH13+V13) -> 236 | AJ13: =-tanks!AW14 -> 236 | AK13: =SUM(AJ13-AI13) -> 0 | AL13: =S13+L13+G13 -> 3 | AM13: =Y13+AD13 -> 0 | AN13: =AN12 -> 67 | AO13: =(AN13/100)*3000 -> 2010 | AP13: =AP12 -> 55 | AQ13: =(AP13/100)*3000 -> 1650 | AR13: =AR12 -> 61 | AS13: =(AR13/100)*3000 -> 1830 | AT13: =SUM(AO13+AQ13+AS13) -> 5490 | AU13: =AT12-AT13+AV13 -> 0 | AX13: =IF(AV13>0,AW13,AX12) -> 0.8
A14: =ELEC!C12 -> 44237 | B14: 227 | C14: 233 | D14: =C13-C14 -> 6 | E14: =D14*8.38 -> 50.28 | F14: 1728 | G14: =F14-F13 -> 1 | H14: 4957 | I14: =SUM(H14-H13) -> 85 | J14: =IF(G14>0,I14/G14,0) -> 85 | K14: =K13 -> 2227 | L14: =K14-K13 -> 0 | M14: =M13 -> 163735 | N14: =M14-M13 -> 0 | O14: =O13 -> 1869 | P14: 1978 | Q14: 167261 | R14: =Q14-Q13 -> 151 | S14: =SUM(P14-P13) -> 2 | T14: =SUM(S14*$T$2) -> 0 | U14: =SUM(G14+L14+S14) -> 3 | V14: =R14+N14+I14:I14 -> 236 | W14: =SUM(V14/U14) -> 78.666667 | X14: =X13 -> 2454 | Y14: =X14-X13 -> 0 | Z14: =Z13 -> 138028.1 | AA14: =Z14-Z13 -> 0 | AB14: =SUM(Y14*$AB$2) -> 0 | AC14: =AC13 -> 1934 | AD14: =AC14-AC13 -> 0 | AE14: =AE13 -> 365352 | AF14: =AE14-AE13 -> 0 | AG14: =IF(AD14>0,AF14/AD14,0) -> 0 | AH14: =AF14+AA14 -> 0 | AI14: =SUM(AH14+V14) -> 236 | AJ14: =-tanks!AW15 -> 236 | AK14: =SUM(AJ14-AI14) -> 0 | AL14: =S14+L14+G14 -> 3 | AM14: =Y14+AD14 -> 0 | AN14: =AN13 -> 67 | AO14: =(AN14/100)*3000 -> 2010 | AP14: =AP13 -> 55 | AQ14: =(AP14/100)*3000 -> 1650 | AR14: =AR13 -> 61 | AS14: =(AR14/100)*3000 -> 1830 | AT14: =SUM(AO14+AQ14+AS14) -> 5490 | AU14: =AT13-AT14+AV14 -> 0 | AX14: =IF(AV14>0,AW14,AX13) -> 0.8
A15: =ELEC!C13 -> 44238 | B15: 222 | C15: 228 | D15: =C14-C15 -> 5 | E15: =D15*8.38 -> 41.9 | F15: 1731 | G15: =F15-F14 -> 3 | H15: 5125 | I15: =SUM(H15-H14) -> 168 | J15: =IF(G15>0,I15/G15,0) -> 56 | K15: 2228 | L15: =K15-K14 -> 1 | M15: 163820 | N15: =M15-M14 -> 85 | O15: =O14 -> 1869 | P15: =P14 -> 1978 | Q15: =Q14 -> 167261 | R15: =Q15-Q14 -> 0 | S15: =SUM(P15-P14) -> 0 | T15: =SUM(S15*$T$2) -> 0 | U15: =SUM(G15+L15+S15) -> 4 | V15: =R15+N15+I15:I15 -> 253 | W15: =SUM(V15/U15) -> 63.25 | X15: =X14 -> 2454 | Y15: =X15-X14 -> 0 | Z15: =Z14 -> 138028.1 | AA15: =Z15-Z14 -> 0 | AB15: =SUM(Y15*$AB$2) -> 0 | AC15: =AC14 -> 1934 | AD15: =AC15-AC14 -> 0 | AE15: =AE14 -> 365352 | AF15: =AE15-AE14 -> 0 | AG15: =IF(AD15>0,AF15/AD15,0) -> 0 | AH15: =AF15+AA15 -> 0 | AI15: =SUM(AH15+V15) -> 253 | AJ15: =-tanks!AW16 -> 253 | AK15: =SUM(AJ15-AI15) -> 0 | AL15: =S15+L15+G15 -> 4 | AM15: =Y15+AD15 -> 0 | AN15: =AN14 -> 67 | AO15: =(AN15/100)*3000 -> 2010 | AP15: =AP14 -> 55 | AQ15: =(AP15/100)*3000 -> 1650 | AR15: =AR14 -> 61 | AS15: =(AR15/100)*3000 -> 1830 | AT15: =SUM(AO15+AQ15+AS15) -> 5490 | AU15: =AT14-AT15+AV15 -> 0 | AX15: =IF(AV15>0,AW15,AX14) -> 0.8
A16: =ELEC!C14 -> 44239 | B16: 219 | C16: 224 | D16: =C15-C16 -> 4 | E16: =D16*8.38 -> 33.52 | F16: 1731 | G16: =F16-F15 -> 0 | H16: =H15 -> 5125 | I16: =SUM(H16-H15) -> 0 | J16: =IF(G16>0,I16/G16,0) -> 0 | K16: 2230 | L16: =K16-K15 -> 2 | M16: 163965 | N16: =M16-M15 -> 145 | O16: =O15 -> 1869 | P16: 1979 | Q16: 167350 | R16: =Q16-Q15 -> 89 | S16: =SUM(P16-P15) -> 1 | T16: =SUM(S16*$T$2) -> 0 | U16: =SUM(G16+L16+S16) -> 3 | V16: =R16+N16+I16:I16 -> 234 | W16: =SUM(V16/U16) -> 78 | X16: =X15 -> 2454 | Y16: =X16-X15 -> 0 | Z16: =Z15 -> 138028.1 | AA16: =Z16-Z15 -> 0 | AB16: =SUM(Y16*$AB$2) -> 0 | AC16: =AC15 -> 1934 | AD16: =AC16-AC15 -> 0 | AE16: =AE15 -> 365352 | AF16: =AE16-AE15 -> 0 | AG16: =IF(AD16>0,AF16/AD16,0) -> 0 | AH16: =AF16+AA16 -> 0 | AI16: =SUM(AH16+V16) -> 234 | AJ16: =-tanks!AW17 -> 234 | AK16: =SUM(AJ16-AI16) -> 0 | AL16: =S16+L16+G16 -> 3 | AM16: =Y16+AD16 -> 0 | AN16: =AN15 -> 67 | AO16: =(AN16/100)*3000 -> 2010 | AP16: =AP15 -> 55 | AQ16: =(AP16/100)*3000 -> 1650 | AR16: =AR15 -> 61 | AS16: =(AR16/100)*3000 -> 1830 | AT16: =SUM(AO16+AQ16+AS16) -> 5490 | AU16: =AT15-AT16+AV16 -> 0 | AX16: =IF(AV16>0,AW16,AX15) -> 0.8
A17: =ELEC!C15 -> 44240 | B17: =B16 -> 219 | C17: =C16 -> 224 | D17: =C16-C17 -> 0 | E17: =D17*8.38 -> 0 | F17: =F16 -> 1731 | G17: =F17-F16 -> 0 | H17: =H16 -> 5125 | I17: =SUM(H17-H16) -> 0 | J17: =IF(G17>0,I17/G17,0) -> 0 | K17: =K16 -> 2230 | L17: =K17-K16 -> 0 | M17: =M16 -> 163965 | N17: =M17-M16 -> 0 | O17: =O16 -> 1869 | P17: =P16 -> 1979 | Q17: =Q16 -> 167350 | R17: =Q17-Q16 -> 0 | S17: =SUM(P17-P16) -> 0 | T17: =SUM(S17*$T$2) -> 0 | U17: =SUM(G17+L17+S17) -> 0 | V17: =R17+N17+I17:I17 -> 0 | X17: =X16 -> 2454 | Y17: =X17-X16 -> 0 | Z17: =Z16 -> 138028.1 | AA17: =Z17-Z16 -> 0 | AB17: =SUM(Y17*$AB$2) -> 0 | AC17: =AC16 -> 1934 | AD17: =AC17-AC16 -> 0 | AE17: =AE16 -> 365352 | AF17: =AE17-AE16 -> 0 | AG17: =IF(AD17>0,AF17/AD17,0) -> 0 | AH17: =AF17+AA17 -> 0 | AI17: =SUM(AH17+V17) -> 0 | AJ17: =-tanks!AW18 -> 0 | AK17: =SUM(AJ17-AI17) -> 0 | AL17: =S17+L17+G17 -> 0 | AM17: =Y17+AD17 -> 0 | AN17: =AN16 -> 67 | AO17: =(AN17/100)*3000 -> 2010 | AP17: =AP16 -> 55 | AQ17: =(AP17/100)*3000 -> 1650 | AR17: =AR16 -> 61 | AS17: =(AR17/100)*3000 -> 1830 | AT17: =SUM(AO17+AQ17+AS17) -> 5490 | AU17: =AT16-AT17+AV17 -> 0 | AX17: =IF(AV17>0,AW17,AX16) -> 0.8
A18: =ELEC!C16 -> 44241 | B18: =B17 -> 219 | C18: =C17 -> 224 | D18: =C17-C18 -> 0 | E18: =D18*8.38 -> 0 | F18: =F17 -> 1731 | G18: =F18-F17 -> 0 | H18: =H17 -> 5125 | I18: =SUM(H18-H17) -> 0 | J18: =IF(G18>0,I18/G18,0) -> 0 | K18: =K17 -> 2230 | L18: =K18-K17 -> 0 | M18: =M17 -> 163965 | N18: =M18-M17 -> 0 | O18: 1869 | P18: =P17 -> 1979 | Q18: =Q17 -> 167350 | R18: =Q18-Q17 -> 0 | S18: =SUM(P18-P17) -> 0 | T18: =SUM(S18*$T$2) -> 0 | U18: =SUM(G18+L18+S18) -> 0 | V18: =R18+N18+I18:I18 -> 0 | X18: =X17 -> 2454 | Y18: =X18-X17 -> 0 | Z18: =Z17 -> 138028.1 | AA18: =Z18-Z17 -> 0 | AB18: =SUM(Y18*$AB$2) -> 0 | AC18: =AC17 -> 1934 | AD18: =AC18-AC17 -> 0 | AE18: =AE17 -> 365352 | AF18: =AE18-AE17 -> 0 | AG18: =IF(AD18>0,AF18/AD18,0) -> 0 | AH18: =AF18+AA18 -> 0 | AI18: =SUM(AH18+V18) -> 0 | AJ18: =-tanks!AW19 -> 0 | AK18: =SUM(AJ18-AI18) -> 0 | AL18: =S18+L18+G18 -> 0 | AM18: =Y18+AD18 -> 0 | AN18: =AN17 -> 67 | AO18: =(AN18/100)*3000 -> 2010 | AP18: =AP17 -> 55 | AQ18: =(AP18/100)*3000 -> 1650 | AR18: =AR17 -> 61 | AS18: =(AR18/100)*3000 -> 1830 | AT18: =SUM(AO18+AQ18+AS18) -> 5490 | AU18: =AT17-AT18+AV18 -> 0 | AX18: =IF(AV18>0,AW18,AX17) -> 0.8
A19: =ELEC!C17 -> 44242 | B19: =B18 -> 219 | C19: =C18 -> 224 | D19: =C18-C19 -> 0 | E19: =D19*8.38 -> 0 | F19: =F18 -> 1731 | G19: =F19-F18 -> 0 | H19: =H18 -> 5125 | I19: =SUM(H19-H18) -> 0 | J19: =IF(G19>0,I19/G19,0) -> 0 | K19: =K18 -> 2230 | L19: =K19-K18 -> 0 | M19: =M18 -> 163965 | N19: =M19-M18 -> 0 | O19: =O18 -> 1869 | P19: =P18 -> 1979 | Q19: =Q18 -> 167350 | R19: =Q19-Q18 -> 0 | S19: =SUM(P19-P18) -> 0 | T19: =SUM(S19*$T$2) -> 0 | U19: =SUM(G19+L19+S19) -> 0 | V19: =R19+N19+I19:I19 -> 0 | X19: =X18 -> 2454 | Y19: =X19-X18 -> 0 | Z19: =Z18 -> 138028.1 | AA19: =Z19-Z18 -> 0 | AB19: =SUM(Y19*$AB$2) -> 0 | AC19: =AC18 -> 1934 | AD19: =AC19-AC18 -> 0 | AE19: =AE18 -> 365352 | AF19: =AE19-AE18 -> 0 | AG19: =IF(AD19>0,AF19/AD19,0) -> 0 | AH19: =AF19+AA19 -> 0 | AI19: =SUM(AH19+V19) -> 0 | AJ19: =-tanks!AW20 -> 0 | AK19: =SUM(AJ19-AI19) -> 0 | AL19: =S19+L19+G19 -> 0 | AM19: =Y19+AD19 -> 0 | AN19: =AN18 -> 67 | AO19: =(AN19/100)*3000 -> 2010 | AP19: =AP18 -> 55 | AQ19: =(AP19/100)*3000 -> 1650 | AR19: =AR18 -> 61 | AS19: =(AR19/100)*3000 -> 1830 | AT19: =SUM(AO19+AQ19+AS19) -> 5490 | AU19: =AT18-AT19+AV19 -> 0 | AX19: =IF(AV19>0,AW19,AX18) -> 0.8
A20: =ELEC!C18 -> 44243 | B20: =B19 -> 219 | C20: =C19 -> 224 | D20: =C19-C20 -> 0 | E20: =D20*8.38 -> 0 | F20: =F19 -> 1731 | G20: =F20-F19 -> 0 | H20: =H19 -> 5125 | I20: =SUM(H20-H19) -> 0 | J20: =IF(G20>0,I20/G20,0) -> 0 | K20: =K19 -> 2230 | L20: =K20-K19 -> 0 | M20: =M19 -> 163965 | N20: =M20-M19 -> 0 | O20: =O19 -> 1869 | P20: =P19 -> 1979 | Q20: =Q19 -> 167350 | R20: =Q20-Q19 -> 0 | S20: =SUM(P20-P19) -> 0 | T20: =SUM(S20*$T$2) -> 0 | U20: =SUM(G20+L20+S20) -> 0 | V20: =R20+N20+I20:I20 -> 0 | X20: =X19 -> 2454 | Y20: =X20-X19 -> 0 | Z20: =Z19 -> 138028.1 | AA20: =Z20-Z19 -> 0 | AB20: =SUM(Y20*$AB$2) -> 0 | AC20: =AC19 -> 1934 | AD20: =AC20-AC19 -> 0 | AE20: =AE19 -> 365352 | AF20: =AE20-AE19 -> 0 | AG20: =IF(AD20>0,AF20/AD20,0) -> 0 | AH20: =AF20+AA20 -> 0 | AI20: =SUM(AH20+V20) -> 0 | AJ20: =-tanks!AW21 -> 0 | AK20: =SUM(AJ20-AI20) -> 0 | AL20: =S20+L20+G20 -> 0 | AM20: =Y20+AD20 -> 0 | AN20: =AN19 -> 67 | AO20: =(AN20/100)*3000 -> 2010 | AP20: =AP19 -> 55 | AQ20: =(AP20/100)*3000 -> 1650 | AR20: =AR19 -> 61 | AS20: =(AR20/100)*3000 -> 1830 | AT20: =SUM(AO20+AQ20+AS20) -> 5490 | AU20: =AT19-AT20+AV20 -> 0 | AX20: =IF(AV20>0,AW20,AX19) -> 0.8
A21: =ELEC!C19 -> 44244 | B21: =B20 -> 219 | C21: =C20 -> 224 | D21: =C20-C21 -> 0 | E21: =D21*8.38 -> 0 | F21: =F20 -> 1731 | G21: =F21-F20 -> 0 | H21: =H20 -> 5125 | I21: =SUM(H21-H20) -> 0 | J21: =IF(G21>0,I21/G21,0) -> 0 | K21: =K20 -> 2230 | L21: =K21-K20 -> 0 | M21: =M20 -> 163965 | N21: =M21-M20 -> 0 | O21: =O20 -> 1869 | P21: =P20 -> 1979 | Q21: =Q20 -> 167350 | R21: =Q21-Q20 -> 0 | S21: =SUM(P21-P20) -> 0 | T21: =SUM(S21*$T$2) -> 0 | U21: =SUM(G21+L21+S21) -> 0 | V21: =R21+N21+I21:I21 -> 0 | X21: =X20 -> 2454 | Y21: =X21-X20 -> 0 | Z21: =Z20 -> 138028.1 | AA21: =Z21-Z20 -> 0 | AB21: =SUM(Y21*$AB$2) -> 0 | AC21: =AC20 -> 1934 | AD21: =AC21-AC20 -> 0 | AE21: =AE20 -> 365352 | AF21: =AE21-AE20 -> 0 | AG21: =IF(AD21>0,AF21/AD21,0) -> 0 | AH21: =AF21+AA21 -> 0 | AI21: =SUM(AH21+V21) -> 0 | AJ21: =-tanks!AW22 -> 0 | AK21: =SUM(AJ21-AI21) -> 0 | AL21: =S21+L21+G21 -> 0 | AM21: =Y21+AD21 -> 0 | AN21: =AN20 -> 67 | AO21: =(AN21/100)*3000 -> 2010 | AP21: =AP20 -> 55 | AQ21: =(AP21/100)*3000 -> 1650 | AR21: =AR20 -> 61 | AS21: =(AR21/100)*3000 -> 1830 | AT21: =SUM(AO21+AQ21+AS21) -> 5490 | AU21: =AT20-AT21+AV21 -> 0 | AX21: =IF(AV21>0,AW21,AX20) -> 0.8
A22: =ELEC!C20 -> 44245 | B22: =B21 -> 219 | C22: =C21 -> 224 | D22: =C21-C22 -> 0 | E22: =D22*8.38 -> 0 | F22: =F21 -> 1731 | G22: =F22-F21 -> 0 | H22: =H21 -> 5125 | I22: =SUM(H22-H21) -> 0 | J22: =IF(G22>0,I22/G22,0) -> 0 | K22: =K21 -> 2230 | L22: =K22-K21 -> 0 | M22: =M21 -> 163965 | N22: =M22-M21 -> 0 | O22: =O21 -> 1869 | P22: =P21 -> 1979 | Q22: =Q21 -> 167350 | R22: =Q22-Q21 -> 0 | S22: =SUM(P22-P21) -> 0 | T22: =SUM(S22*$T$2) -> 0 | U22: =SUM(G22+L22+S22) -> 0 | V22: =R22+N22+I22:I22 -> 0 | X22: =X21 -> 2454 | Y22: =X22-X21 -> 0 | Z22: =Z21 -> 138028.1 | AA22: =Z22-Z21 -> 0 | AB22: =SUM(Y22*$AB$2) -> 0 | AC22: =AC21 -> 1934 | AD22: =AC22-AC21 -> 0 | AE22: =AE21 -> 365352 | AF22: =AE22-AE21 -> 0 | AG22: =IF(AD22>0,AF22/AD22,0) -> 0 | AH22: =AF22+AA22 -> 0 | AI22: =SUM(AH22+V22) -> 0 | AJ22: =-tanks!AW23 -> 0 | AK22: =SUM(AJ22-AI22) -> 0 | AL22: =S22+L22+G22 -> 0 | AM22: =Y22+AD22 -> 0 | AN22: =AN21 -> 67 | AO22: =(AN22/100)*3000 -> 2010 | AP22: =AP21 -> 55 | AQ22: =(AP22/100)*3000 -> 1650 | AR22: =AR21 -> 61 | AS22: =(AR22/100)*3000 -> 1830 | AT22: =SUM(AO22+AQ22+AS22) -> 5490 | AU22: =AT21-AT22+AV22 -> 0 | AX22: =IF(AV22>0,AW22,AX21) -> 0.8
A23: =[3]ELEC!C21 -> 44215 | B23: =B22 -> 219 | C23: =C22 -> 224 | D23: =C22-C23 -> 0 | E23: =D23*8.38 -> 0 | F23: =F22 -> 1731 | G23: =F23-F22 -> 0 | H23: =H22 -> 5125 | I23: =SUM(H23-H22) -> 0 | J23: =IF(G23>0,I23/G23,0) -> 0 | K23: =K22 -> 2230 | L23: =K23-K22 -> 0 | M23: =M22 -> 163965 | N23: =M23-M22 -> 0 | O23: =O22 -> 1869 | P23: =P22 -> 1979 | Q23: =Q22 -> 167350 | R23: =Q23-Q22 -> 0 | S23: =SUM(P23-P22) -> 0 | T23: =SUM(S23*$T$2) -> 0 | U23: =SUM(G23+L23+S23) -> 0 | V23: =R23+N23+I23:I23 -> 0 | X23: =X22 -> 2454 | Y23: =X23-X22 -> 0 | Z23: =Z22 -> 138028.1 | AA23: =Z23-Z22 -> 0 | AB23: =SUM(Y23*$AB$2) -> 0 | AC23: =AC22 -> 1934 | AD23: =AC23-AC22 -> 0 | AE23: =AE22 -> 365352 | AF23: =AE23-AE22 -> 0 | AG23: =IF(AD23>0,AF23/AD23,0) -> 0 | AH23: =AF23+AA23 -> 0 | AI23: =SUM(AH23+V23) -> 0 | AJ23: =-[3]tanks!AW24 -> 231 | AK23: =SUM(AJ23-AI23) -> 231 | AL23: =S23+L23+G23 -> 0 | AM23: =Y23+AD23 -> 0 | AN23: =AN22 -> 67 | AO23: =(AN23/100)*3000 -> 2010 | AP23: =AP22 -> 55 | AQ23: =(AP23/100)*3000 -> 1650 | AR23: =AR22 -> 61 | AS23: =(AR23/100)*3000 -> 1830 | AT23: =SUM(AO23+AQ23+AS23) -> 5490 | AU23: =AT22-AT23+AV23 -> 0 | AX23: =IF(AV23>0,AW23,AX22) -> 0.8
A24: =ELEC!C22 -> 44247 | B24: =B23 -> 219 | C24: =C23 -> 224 | D24: =C23-C24 -> 0 | E24: =D24*8.38 -> 0 | F24: =F23 -> 1731 | G24: =F24-F23 -> 0 | H24: =H23 -> 5125 | I24: =SUM(H24-H23) -> 0 | J24: =IF(G24>0,I24/G24,0) -> 0 | K24: =K23 -> 2230 | L24: =K24-K23 -> 0 | M24: =M23 -> 163965 | N24: =M24-M23 -> 0 | O24: =O23 -> 1869 | P24: =P23 -> 1979 | Q24: =Q23 -> 167350 | R24: =Q24-Q23 -> 0 | S24: =SUM(P24-P23) -> 0 | T24: =SUM(S24*$T$2) -> 0 | U24: =SUM(G24+L24+S24) -> 0 | V24: =R24+N24+I24:I24 -> 0 | X24: =X23 -> 2454 | Y24: =X24-X23 -> 0 | Z24: =Z23 -> 138028.1 | AA24: =Z24-Z23 -> 0 | AB24: =SUM(Y24*$AB$2) -> 0 | AC24: =AC23 -> 1934 | AD24: =AC24-AC23 -> 0 | AE24: =AE23 -> 365352 | AF24: =AE24-AE23 -> 0 | AG24: =IF(AD24>0,AF24/AD24,0) -> 0 | AH24: =AF24+AA24 -> 0 | AI24: =SUM(AH24+V24) -> 0 | AJ24: =-tanks!AW25 -> 0 | AK24: =SUM(AJ24-AI24) -> 0 | AL24: =S24+L24+G24 -> 0 | AM24: =Y24+AD24 -> 0 | AN24: =AN23 -> 67 | AO24: =(AN24/100)*3000 -> 2010 | AP24: =AP23 -> 55 | AQ24: =(AP24/100)*3000 -> 1650 | AR24: =AR23 -> 61 | AS24: =(AR24/100)*3000 -> 1830 | AT24: =SUM(AO24+AQ24+AS24) -> 5490 | AU24: =AT23-AT24+AV24 -> 0 | AX24: =IF(AV24>0,AW24,AX23) -> 0.8
A25: =ELEC!C23 -> 44248 | B25: =B24 -> 219 | C25: =C24 -> 224 | D25: =C24-C25 -> 0 | E25: =D25*8.38 -> 0 | F25: =F24 -> 1731 | G25: =F25-F24 -> 0 | H25: =H24 -> 5125 | I25: =SUM(H25-H24) -> 0 | J25: =IF(G25>0,I25/G25,0) -> 0 | K25: =K24 -> 2230 | L25: =K25-K24 -> 0 | M25: =M24 -> 163965 | N25: =M25-M24 -> 0 | O25: =O24 -> 1869 | P25: =P24 -> 1979 | Q25: =Q24 -> 167350 | R25: =Q25-Q24 -> 0 | S25: =SUM(P25-P24) -> 0 | T25: =SUM(S25*$T$2) -> 0 | U25: =SUM(G25+L25+S25) -> 0 | V25: =R25+N25+I25:I25 -> 0 | X25: =X24 -> 2454 | Y25: =X25-X24 -> 0 | Z25: =Z24 -> 138028.1 | AA25: =Z25-Z24 -> 0 | AB25: =SUM(Y25*$AB$2) -> 0 | AC25: =AC24 -> 1934 | AD25: =AC25-AC24 -> 0 | AE25: =AE24 -> 365352 | AF25: =AE25-AE24 -> 0 | AG25: =IF(AD25>0,AF25/AD25,0) -> 0 | AH25: =AF25+AA25 -> 0 | AI25: =SUM(AH25+V25) -> 0 | AJ25: =-tanks!AW26 -> 0 | AK25: =SUM(AJ25-AI25) -> 0 | AL25: =S25+L25+G25 -> 0 | AM25: =Y25+AD25 -> 0 | AN25: =AN24 -> 67 | AO25: =(AN25/100)*3000 -> 2010 | AP25: =AP24 -> 55 | AQ25: =(AP25/100)*3000 -> 1650 | AR25: =AR24 -> 61 | AS25: =(AR25/100)*3000 -> 1830 | AT25: =SUM(AO25+AQ25+AS25) -> 5490 | AU25: =AT24-AT25+AV25 -> 0 | AX25: =IF(AV25>0,AW25,AX24) -> 0.8
A26: =ELEC!C24 -> 44249 | B26: =B25 -> 219 | C26: =C25 -> 224 | D26: =C25-C26 -> 0 | E26: =D26*8.38 -> 0 | F26: =F25 -> 1731 | G26: =F26-F25 -> 0 | H26: =H25 -> 5125 | I26: =SUM(H26-H25) -> 0 | J26: =IF(G26>0,I26/G26,0) -> 0 | K26: =K25 -> 2230 | L26: =K26-K25 -> 0 | M26: =M25 -> 163965 | N26: =M26-M25 -> 0 | O26: =O25 -> 1869 | P26: =P25 -> 1979 | Q26: =Q25 -> 167350 | R26: =Q26-Q25 -> 0 | S26: =SUM(P26-P25) -> 0 | T26: =SUM(S26*$T$2) -> 0 | U26: =SUM(G26+L26+S26) -> 0 | V26: =R26+N26+I26:I26 -> 0 | X26: =X25 -> 2454 | Y26: =X26-X25 -> 0 | Z26: =Z25 -> 138028.1 | AA26: =Z26-Z25 -> 0 | AB26: =SUM(Y26*$AB$2) -> 0 | AC26: =AC25 -> 1934 | AD26: =AC26-AC25 -> 0 | AE26: =AE25 -> 365352 | AF26: =AE26-AE25 -> 0 | AG26: =IF(AD26>0,AF26/AD26,0) -> 0 | AH26: =AF26+AA26 -> 0 | AI26: =SUM(AH26+V26) -> 0 | AJ26: =-tanks!AW27 -> 0 | AK26: =SUM(AJ26-AI26) -> 0 | AL26: =S26+L26+G26 -> 0 | AM26: =Y26+AD26 -> 0 | AN26: =AN25 -> 67 | AO26: =(AN26/100)*3000 -> 2010 | AP26: =AP25 -> 55 | AQ26: =(AP26/100)*3000 -> 1650 | AR26: =AR25 -> 61 | AS26: =(AR26/100)*3000 -> 1830 | AT26: =SUM(AO26+AQ26+AS26) -> 5490 | AU26: =AT25-AT26+AV26 -> 0 | AX26: =IF(AV26>0,AW26,AX25) -> 0.8
A27: =ELEC!C25 -> 44250 | B27: =B26 -> 219 | C27: =C26 -> 224 | D27: =C26-C27 -> 0 | E27: =D27*8.38 -> 0 | F27: =F26 -> 1731 | G27: =F27-F26 -> 0 | H27: =H26 -> 5125 | I27: =SUM(H27-H26) -> 0 | J27: =IF(G27>0,I27/G27,0) -> 0 | K27: =K26 -> 2230 | L27: =K27-K26 -> 0 | M27: =M26 -> 163965 | N27: =M27-M26 -> 0 | O27: =O26 -> 1869 | P27: =P26 -> 1979 | Q27: =Q26 -> 167350 | R27: =Q27-Q26 -> 0 | S27: =SUM(P27-P26) -> 0 | T27: =SUM(S27*$T$2) -> 0 | U27: =SUM(G27+L27+S27) -> 0 | V27: =R27+N27+I27:I27 -> 0 | X27: =X26 -> 2454 | Y27: =X27-X26 -> 0 | Z27: =Z26 -> 138028.1 | AA27: =Z27-Z26 -> 0 | AB27: =SUM(Y27*$AB$2) -> 0 | AC27: =AC26 -> 1934 | AD27: =AC27-AC26 -> 0 | AE27: =AE26 -> 365352 | AF27: =AE27-AE26 -> 0 | AG27: =IF(AD27>0,AF27/AD27,0) -> 0 | AH27: =AF27+AA27 -> 0 | AI27: =SUM(AH27+V27) -> 0 | AJ27: =-tanks!AW28 -> 0 | AK27: =SUM(AJ27-AI27) -> 0 | AL27: =S27+L27+G27 -> 0 | AM27: =Y27+AD27 -> 0 | AN27: =AN26 -> 67 | AO27: =(AN27/100)*3000 -> 2010 | AP27: =AP26 -> 55 | AQ27: =(AP27/100)*3000 -> 1650 | AR27: =AR26 -> 61 | AS27: =(AR27/100)*3000 -> 1830 | AT27: =SUM(AO27+AQ27+AS27) -> 5490 | AU27: =AT26-AT27+AV27 -> 0 | AX27: =IF(AV27>0,AW27,AX26) -> 0.8
A28: =ELEC!C26 -> 44251 | B28: =B27 -> 219 | C28: =C27 -> 224 | D28: =C27-C28 -> 0 | E28: =D28*8.38 -> 0 | F28: =F27 -> 1731 | G28: =F28-F27 -> 0 | H28: =H27 -> 5125 | I28: =SUM(H28-H27) -> 0 | J28: =IF(G28>0,I28/G28,0) -> 0 | K28: =K27 -> 2230 | L28: =K28-K27 -> 0 | M28: =M27 -> 163965 | N28: =M28-M27 -> 0 | O28: =O27 -> 1869 | P28: =P27 -> 1979 | Q28: =Q27 -> 167350 | R28: =Q28-Q27 -> 0 | S28: =SUM(P28-P27) -> 0 | T28: =SUM(S28*$T$2) -> 0 | U28: =SUM(G28+L28+S28) -> 0 | V28: =R28+N28+I28:I28 -> 0 | X28: =X27 -> 2454 | Y28: =X28-X27 -> 0 | Z28: =Z27 -> 138028.1 | AA28: =Z28-Z27 -> 0 | AB28: =SUM(Y28*$AB$2) -> 0 | AC28: =AC27 -> 1934 | AD28: =AC28-AC27 -> 0 | AE28: =AE27 -> 365352 | AF28: =AE28-AE27 -> 0 | AG28: =IF(AD28>0,AF28/AD28,0) -> 0 | AH28: =AF28+AA28 -> 0 | AI28: =SUM(AH28+V28) -> 0 | AJ28: =-tanks!AW29 -> 0 | AK28: =SUM(AJ28-AI28) -> 0 | AL28: =S28+L28+G28 -> 0 | AM28: =Y28+AD28 -> 0 | AN28: =AN27 -> 67 | AO28: =(AN28/100)*3000 -> 2010 | AP28: =AP27 -> 55 | AQ28: =(AP28/100)*3000 -> 1650 | AR28: =AR27 -> 61 | AS28: =(AR28/100)*3000 -> 1830 | AT28: =SUM(AO28+AQ28+AS28) -> 5490 | AU28: =AT27-AT28+AV28 -> 0 | AX28: =IF(AV28>0,AW28,AX27) -> 0.8
A29: =ELEC!C27 -> 44252 | B29: =B28 -> 219 | C29: =C28 -> 224 | D29: =C28-C29 -> 0 | E29: =D29*8.38 -> 0 | F29: =F28 -> 1731 | G29: =F29-F28 -> 0 | H29: =H28 -> 5125 | I29: =SUM(H29-H28) -> 0 | J29: =IF(G29>0,I29/G29,0) -> 0 | K29: =K28 -> 2230 | L29: =K29-K28 -> 0 | M29: =M28 -> 163965 | N29: =M29-M28 -> 0 | O29: =O28 -> 1869 | P29: =P28 -> 1979 | Q29: =Q28 -> 167350 | R29: =Q29-Q28 -> 0 | S29: =SUM(P29-P28) -> 0 | T29: =SUM(S29*$T$2) -> 0 | U29: =SUM(G29+L29+S29) -> 0 | V29: =R29+N29+I29:I29 -> 0 | X29: =X28 -> 2454 | Y29: =X29-X28 -> 0 | Z29: =Z28 -> 138028.1 | AA29: =Z29-Z28 -> 0 | AB29: =SUM(Y29*$AB$2) -> 0 | AC29: =AC28 -> 1934 | AD29: =AC29-AC28 -> 0 | AE29: =AE28 -> 365352 | AF29: =AE29-AE28 -> 0 | AG29: =IF(AD29>0,AF29/AD29,0) -> 0 | AH29: =AF29+AA29 -> 0 | AI29: =SUM(AH29+V29) -> 0 | AJ29: =-tanks!AW30 -> 0 | AK29: =SUM(AJ29-AI29) -> 0 | AL29: =S29+L29+G29 -> 0 | AM29: =Y29+AD29 -> 0 | AN29: =AN28 -> 67 | AO29: =(AN29/100)*3000 -> 2010 | AP29: =AP28 -> 55 | AQ29: =(AP29/100)*3000 -> 1650 | AR29: =AR28 -> 61 | AS29: =(AR29/100)*3000 -> 1830 | AT29: =SUM(AO29+AQ29+AS29) -> 5490 | AU29: =AT28-AT29+AV29 -> 0 | AX29: =IF(AV29>0,AW29,AX28) -> 0.8
A30: =ELEC!C28 -> 44253 | B30: =B29 -> 219 | C30: =C29 -> 224 | D30: =C29-C30 -> 0 | E30: =D30*8.38 -> 0 | F30: =F29 -> 1731 | G30: =F30-F29 -> 0 | H30: =H29 -> 5125 | I30: =SUM(H30-H29) -> 0 | J30: =IF(G30>0,I30/G30,0) -> 0 | K30: =K29 -> 2230 | L30: =K30-K29 -> 0 | M30: =M29 -> 163965 | N30: =M30-M29 -> 0 | O30: =O29 -> 1869 | P30: =P29 -> 1979 | Q30: =Q29 -> 167350 | R30: =Q30-Q29 -> 0 | S30: =SUM(P30-P29) -> 0 | T30: =SUM(S30*$T$2) -> 0 | U30: =SUM(G30+L30+S30) -> 0 | V30: =R30+N30+I30:I30 -> 0 | X30: =X29 -> 2454 | Y30: =X30-X29 -> 0 | Z30: =Z29 -> 138028.1 | AA30: =Z30-Z29 -> 0 | AB30: =SUM(Y30*$AB$2) -> 0 | AC30: =AC29 -> 1934 | AD30: =AC30-AC29 -> 0 | AE30: =AE29 -> 365352 | AF30: =AE30-AE29 -> 0 | AG30: =IF(AD30>0,AF30/AD30,0) -> 0 | AH30: =AF30+AA30 -> 0 | AI30: =SUM(AH30+V30) -> 0 | AJ30: =-tanks!AW31 -> 0 | AK30: =SUM(AJ30-AI30) -> 0 | AL30: =S30+L30+G30 -> 0 | AM30: =Y30+AD30 -> 0 | AN30: =AN29 -> 67 | AO30: =(AN30/100)*3000 -> 2010 | AP30: =AP29 -> 55 | AQ30: =(AP30/100)*3000 -> 1650 | AR30: =AR29 -> 61 | AS30: =(AR30/100)*3000 -> 1830 | AT30: =SUM(AO30+AQ30+AS30) -> 5490 | AU30: =AT29-AT30+AV30 -> 0 | AX30: =IF(AV30>0,AW30,AX29) -> 0.8
A31: =ELEC!C29 -> 44254 | B31: =B30 -> 219 | C31: =C30 -> 224 | D31: =C30-C31 -> 0 | E31: =D31*8.38 -> 0 | F31: =F30 -> 1731 | G31: =F31-F30 -> 0 | H31: =H30 -> 5125 | I31: =SUM(H31-H30) -> 0 | J31: =IF(G31>0,I31/G31,0) -> 0 | K31: =K30 -> 2230 | L31: =K31-K30 -> 0 | M31: =M30 -> 163965 | N31: =M31-M30 -> 0 | O31: =O30 -> 1869 | P31: =P30 -> 1979 | Q31: =Q30 -> 167350 | R31: =Q31-Q30 -> 0 | S31: =SUM(P31-P30) -> 0 | T31: =SUM(S31*$T$2) -> 0 | U31: =SUM(G31+L31+S31) -> 0 | V31: =R31+N31+I31:I31 -> 0 | X31: =X30 -> 2454 | Y31: =X31-X30 -> 0 | Z31: =Z30 -> 138028.1 | AA31: =Z31-Z30 -> 0 | AB31: =SUM(Y31*$AB$2) -> 0 | AC31: =AC30 -> 1934 | AD31: =AC31-AC30 -> 0 | AE31: =AE30 -> 365352 | AF31: =AE31-AE30 -> 0 | AG31: =IF(AD31>0,AF31/AD31,0) -> 0 | AH31: =AF31+AA31 -> 0 | AI31: =SUM(AH31+V31) -> 0 | AJ31: =-tanks!AW32 -> 0 | AK31: =SUM(AJ31-AI31) -> 0 | AL31: =S31+L31+G31 -> 0 | AM31: =Y31+AD31 -> 0 | AN31: =AN30 -> 67 | AO31: =(AN31/100)*3000 -> 2010 | AP31: =AP30 -> 55 | AQ31: =(AP31/100)*3000 -> 1650 | AR31: =AR30 -> 61 | AS31: =(AR31/100)*3000 -> 1830 | AT31: =SUM(AO31+AQ31+AS31) -> 5490 | AU31: =AT30-AT31+AV31 -> 0 | AX31: =IF(AV31>0,AW31,AX30) -> 0.8
A32: =ELEC!C30 -> 44255 | B32: =B31 -> 219 | C32: =C31 -> 224 | D32: =C31-C32 -> 0 | E32: =D32*8.38 -> 0 | F32: =F31 -> 1731 | G32: =F32-F31 -> 0 | H32: =H31 -> 5125 | I32: =SUM(H32-H31) -> 0 | J32: =IF(G32>0,I32/G32,0) -> 0 | K32: =K31 -> 2230 | L32: =K32-K31 -> 0 | M32: =M31 -> 163965 | N32: =M32-M31 -> 0 | O32: =O31 -> 1869 | P32: =P31 -> 1979 | Q32: =Q31 -> 167350 | R32: =Q32-Q31 -> 0 | S32: =SUM(P32-P31) -> 0 | T32: =SUM(S32*$T$2) -> 0 | U32: =SUM(G32+L32+S32) -> 0 | V32: =R32+N32+I32:I32 -> 0 | X32: =X31 -> 2454 | Y32: =X32-X31 -> 0 | Z32: =Z31 -> 138028.1 | AA32: =Z32-Z31 -> 0 | AB32: =SUM(Y32*$AB$2) -> 0 | AC32: =AC31 -> 1934 | AD32: =AC32-AC31 -> 0 | AE32: =AE31 -> 365352 | AF32: =AE32-AE31 -> 0 | AG32: =IF(AD32>0,AF32/AD32,0) -> 0 | AH32: =AF32+AA32 -> 0 | AI32: =SUM(AH32+V32) -> 0 | AJ32: =-tanks!AW33 -> 0 | AK32: =SUM(AJ32-AI32) -> 0 | AL32: =S32+L32+G32 -> 0 | AM32: =Y32+AD32 -> 0 | AN32: =AN31 -> 67 | AO32: =(AN32/100)*3000 -> 2010 | AP32: =AP31 -> 55 | AQ32: =(AP32/100)*3000 -> 1650 | AR32: =AR31 -> 61 | AS32: =(AR32/100)*3000 -> 1830 | AT32: =SUM(AO32+AQ32+AS32) -> 5490 | AU32: =AT31-AT32+AV32 -> 0 | AX32: =IF(AV32>0,AW32,AX31) -> 0.8
J33: =SUM(J5:J32)/(COUNT(J5:J32)-COUNTIF(J5:J32,0)) -> 64.625 | V33: =SUM(V5:V32) -> 3346 | AE33: . | AH33: =SUM(AH5:AH32) -> 232 | AL33: =SUM(AL5:AL32) -> 45 | AM33: =SUM(AM5:AM32) -> 2 | AR33: Nb Delivery | AS33: =COUNT(AW5:AW32) -> 0 | AU33: =SUM(AU5:AU32) -> 0 | AV33: =SUM(AV5:AV32) -> 0 | AW33: =SUM(AW5:AW32)/AS33 -> #DIV/0!
AH34: =AF34+AA34 -> 0 | AI34: =SUM(AI5:AI32) -> 3578
AH35: =AF35+AA35 -> 0 | AU35: =AU33*0.51 -> 0 | AV35: =AV33/0.51 -> 0 | AW35: =SUM(AW5:AW32)/AS33 -> #DIV/0!
AV36: =AV33*0.51 -> 0

Sheet WATER
D1: =SUM(G21:G33) -> 7999862 | AR1: Entrance | AT1: Tank 1 | AV1: Tank 2
AR2: Level | AW2: Quantity CM3 | AZ2: Var
A3: Date | B3: Truck | C3: Truck M3/day | D3: N0. Trucks | F3: REQ. # of trucks | G3: City | H3: City/day | I3: Total water delivery | K3: SW | L3: Cosum SW/day | M3: RO Guest/ Liter | O3: RO K&L/ Liter | Q3: TOTAL RO Production | R3: RO 1 RH | S3: RO 2 RH | T3: RO water counter | U3: RO Cons m3 | V3: Steam Boiler | W3: Steam Boiler/day | X3: Softener Guest | Y3: Guest Sotf/day | Z3: Softener K&L | AA3: K&L Soft/Day | AB3: Fire Tank Level | AC3: Fire Tank Counter | AE3: Laundry Hot Water Counter | AF3: Hot Water Cons/day | AG3: Laundry Cold Water Counter | AH3: Cold Water Cons/day | AI3: Laundry Water Total Cons | AJ3: K&L Sotf/day | AK3: Guest / day | AL3: K&L /day | AM3: Avg Outside Temp | AN3: Banquet Activity | AR3: Date | AT3: MainI | AV3: Kitchen and Laundry | AX3: Guest | AY3: Main Tank | AZ3: Kitchen and Laundry | BA3: Guest | BB3: Kitchen and Laundry | BC3: Main | BD3: Guest | BE3: Total VAR | BF3: Hotel Consumption
E4: 1.66 | AN4: Ball R | AO4: Meeting | AP4: outlet | AT4: 180 | AV4: 220 | AX4: 580 | AY4: =SUM(AT4) -> 180 | AZ4: =SUM(AV4) -> 220 | BA4: =SUM(AX4) -> 580
A5: =ELEC!C2 -> 44227 | B5: =[2]WATER!B36 -> 109443 | C5: =[2]WATER!C36 -> 0 | D5: =[2]WATER!D36 -> 0 | E5: =[2]WATER!E36 -> 241.93548 | F5: =[2]WATER!F36 -> 0 | G5: =[2]WATER!G36 -> 615374 | H5: =[2]WATER!H36 -> 0 | I5: =[2]WATER!I36 -> 0 | ... BG5: =[2]WATER!BG36 -> -5.1
A6: =ELEC!C3 -> 44228 | B6: =B5 -> 109443 | C6: =B6-B5 -> 0 | D6: =C6/27 -> 0 | E6: =SUM((C6*$E$4)+(7500/'EDl log'!$A$34)) -> 267.85714 | G6: 615374 | H6: =G6-G5 -> 0 | I6: =C6+H6 -> 0 | J6: =IF(I6>0,E6/I6,0) -> 0 | K6: ='Swimming Pool quality check '!H6 -> 6716 | L6: 0 | M6: =M5 -> 457.44 | N6: =SUM(M6-M5) -> 0 | O6: =O5 -> 529.52 | P6: =SUM(O6-O5) -> 0 | Q6: =P6+N6 -> 0 | T6: 5165 | U6: =SUM(T6-T5) -> 1 | V6: 460 | W6: =+V6-V5 -> 0 | X6: 150077 | Y6: =SUM(X6-X5) -> 0 | Z6: =Z5 -> 98262 | AA6: =Z6-Z5 -> 0 | AB6: =AB5 -> 256 | AC6: =AC5 -> 731 | AD6: 0 | AE6: =AE5 -> 227.8 | AF6: =AE6-AE5 -> 0 | AG6: =AG5 -> 2181.57 | AH6: =AG6-AG5 -> 0 | AI6: =AF6+AH6 -> 0 | AJ6: =+Z6-Z5 -> 0 | AK6: =SUM(Y6-L6) -> 0 | AL6: =SUM(AJ6-W6) -> 0 | AM6: ='General information '!D6 -> 18.5 | AN6: ='General information '!H6 -> 0 | AP6: ='General information '!J6 -> 0 | AR6: =A6 -> 44228 | AS6: =AS5 -> 0.9 | AT6: 150 | AU6: =AU5 -> 1.1 | AV6: 148 | AW6: 2.9 | AX6: 165 | AY6: =AS6*AT6 -> 135 | AZ6: =AU6*AV6 -> 162.8 | BA6: =AW6*AX6 -> 478.5 | BB6: =AY6-AY5 -> -28.8 | BC6: =AZ6-AZ5 -> -2.2 | BD6: =BA6-BA5 -> -2.9 | BE6: =SUM(BB6:BD6) -> -33.9 | BF6: =SUM(I6-BE6) -> 33.9 | BG6: =SUM(I6-BF6) -> -33.9
A7: =ELEC!C4 -> 44229 | B7: =B6 -> 109443 | C7: =B7-B6 -> 0 | D7: =C7/27 -> 0 | E7: =SUM((C7*$E$4)+(7500/'EDl log'!$A$34)) -> 267.85714 | G7: =G6 -> 615374 | H7: =G7-G6 -> 0 | I7: =C7+H7 -> 0 | J7: =IF(I7>0,E7/I7,0) -> 0 | K7: ='Swimming Pool quality check '!H7 -> 6716 | L7: =K7-K6 -> 0 | M7: =M6 -> 457.44 | N7: =SUM(M7-M6) -> 0 | O7: =O6 -> 529.52 | P7: =SUM(O7-O6) -> 0 | Q7: =P7+N7 -> 0 | T7: =T6 -> 5165 | U7: =SUM(T7-T6) -> 0 | V7: =V6 -> 460 | W7: =+V7-V6 -> 0 | X7: =X6 -> 150077 | Y7: =SUM(X7-X6) -> 0 | Z7: =Z6 -> 98262 | AA7: =Z7-Z6 -> 0 | AB7: =AB6 -> 256 | AC7: =AC6 -> 731 | AD7: =AC7-AC6 -> 0 | AE7: =AE6 -> 227.8 | AF7: =AE7-AE6 -> 0 | AG7: =AG6 -> 2181.57 | AH7: =AG7-AG6 -> 0 | AI7: =AF7+AH7 -> 0 | AJ7: =+Z7-Z6 -> 0 | AK7: =SUM(Y7-L7) -> 0 | AL7: =SUM(AJ7-W7) -> 0 | AM7: ='General information '!D7 -> 20 | AN7: ='General information '!H7 -> 0 | AP7: ='General information '!J7 -> 0 | AR7: =A7 -> 44229 | AS7: =AS6 -> 0.9 | AT7: 150 | AU7: =AU6 -> 1.1 | AV7: 143 | AW7: 2.9 | AX7: 163 | AY7: =AS7*AT7 -> 135 | AZ7: =AU7*AV7 -> 157.3 | BA7: =AW7*AX7 -> 472.7 | BB7: =AY7-AY6 -> 0 | BC7: =AZ7-AZ6 -> -5.5 | BD7: =BA7-BA6 -> -5.8 | BE7: =SUM(BB7:BD7) -> -11.3 | BF7: =SUM(I7-BE7) -> 11.3 | BG7: =SUM(I7-BF7) -> -11.3
A8: =ELEC!C5 -> 44230 | B8: =B7 -> 109443 | C8: =B8-B7 -> 0 | D8: =C8/27 -> 0 | E8: =SUM((C8*$E$4)+(7500/'EDl log'!$A$34)) -> 267.85714 | G8: =G7 -> 615374 | H8: =G8-G7 -> 0 | I8: =C8+H8 -> 0 | J8: =IF(I8>0,E8/I8,0) -> 0 | K8: ='Swimming Pool quality check '!H8 -> 6716 | L8: =K8-K7 -> 0 | M8: =M7 -> 457.44 | N8: =SUM(M8-M7) -> 0 | O8: =O7 -> 529.52 | P8: =SUM(O8-O7) -> 0 | Q8: =P8+N8 -> 0 | T8: =T7 -> 5165 | U8: =SUM(T8-T7) -> 0 | V8: 461 | W8: =+V8-V7 -> 1 | X8: =X7 -> 150077 | Y8: =SUM(X8-X7) -> 0 | Z8: =Z7 -> 98262 | AA8: =Z8-Z7 -> 0 | AB8: =AB7 -> 256 | AC8: =AC7 -> 731 | AD8: =AC8-AC7 -> 0 | AE8: =AE7 -> 227.8 | AF8: =AE8-AE7 -> 0 | AG8: =AG7 -> 2181.57 | AH8: =AG8-AG7 -> 0 | AI8: =AF8+AH8 -> 0 | AJ8: =+Z8-Z7 -> 0 | AK8: =SUM(Y8-L8) -> 0 | AL8: =SUM(AJ8-W8) -> -1 | AM8: ='General information '!D8 -> 17.5 | AN8: ='General information '!H8 -> 0 | AP8: ='General information '!J8 -> 0 | AR8: =A8 -> 44230 | AS8: =AS7 -> 0.9 | AT8: 146 | AU8: 1.1 | AV8: 140 | AW8: 2.9 | AX8: 162 | AY8: =AS8*AT8 -> 131.4 | AZ8: =AU8*AV8 -> 154 | BA8: =AW8*AX8 -> 469.8 | BB8: =AY8-AY7 -> -3.6 | BC8: =AZ8-AZ7 -> -3.3 | BD8: =BA8-BA7 -> -2.9 | BE8: =SUM(BB8:BD8) -> -9.8 | BF8: =SUM(I8-BE8) -> 9.8 | BG8: =SUM(I8-BF8) -> -9.8
A9: =ELEC!C6 -> 44231 | B9: =B8 -> 109443 | C9: =B9-B8 -> 0 | D9: =C9/27 -> 0 | E9: =SUM((C9*$E$4)+(7500/'EDl log'!$A$34)) -> 267.85714 | G9: =G8 -> 615374 | H9: =G9-G8 -> 0 | I9: =C9+H9 -> 0 | J9: =IF(I9>0,E9/I9,0) -> 0 | K9: ='Swimming Pool quality check '!H9 -> 6716 | L9: =K9-K8 -> 0 | M9: =M8 -> 457.44 | N9: =SUM(M9-M8) -> 0 | O9: =O8 -> 529.52 | P9: =SUM(O9-O8) -> 0 | Q9: =P9+N9 -> 0 | T9: =T8 -> 5165 | U9: =SUM(T9-T8) -> 0 | V9: =V8 -> 461 | W9: =+V9-V8 -> 0 | X9: =X8 -> 150077 | Y9: =SUM(X9-X8) -> 0 | Z9: =Z8 -> 98262 | AA9: =Z9-Z8 -> 0 | AB9: =AB8 -> 256 | AC9: =AC8 -> 731 | AD9: =AC9-AC8 -> 0 | AE9: =AE8 -> 227.8 | AF9: =AE9-AE8 -> 0 | AG9: =AG8 -> 2181.57 | AH9: =AG9-AG8 -> 0 | AI9: =AF9+AH9 -> 0 | AJ9: =+Z9-Z8 -> 0 | AK9: =SUM(Y9-L9) -> 0 | AL9: =SUM(AJ9-W9) -> 0 | AM9: ='General information '!D9 -> 17.5 | AN9: ='General information '!H9 -> 0 | AP9: ='General information '!J9 -> 0 | AR9: =A9 -> 44231 | AS9: =AS8 -> 0.9 | AT9: =AT8 -> 146 | AU9: =AU8 -> 1.1 | AV9: 136 | AW9: 2.9 | AX9: 157 | AY9: =AS9*AT9 -> 131.4 | AZ9: =AU9*AV9 -> 149.6 | BA9: =AW9*AX9 -> 455.3 | BB9: =AY9-AY8 -> 0 | BC9: =AZ9-AZ8 -> -4.4 | BD9: =BA9-BA8 -> -14.5 | BE9: =SUM(BB9:BD9) -> -18.9 | BF9: =SUM(I9-BE9) -> 18.9 | BG9: =SUM(I9-BF9) -> -18.9
A10: =ELEC!C7 -> 44232 | B10: =B9 -> 109443 | C10: =B10-B9 -> 0 | D10: =C10/27 -> 0 | E10: =SUM((C10*$E$4)+(7500/'EDl log'!$A$34)) -> 267.85714 | G10: =G9 -> 615374 | H10: =G10-G9 -> 0 | I10: =C10+H10 -> 0 | J10: =IF(I10>0,E10/I10,0) -> 0 | K10: ='Swimming Pool quality check '!H10 -> 6715 | L10: =K10-K9 -> -1 | M10: =M9 -> 457.44 | N10: =SUM(M10-M9) -> 0 | O10: =O9 -> 529.52 | P10: =SUM(O10-O9) -> 0 | Q10: =P10+N10 -> 0 | T10: =T9 -> 5165 | U10: =SUM(T10-T9) -> 0 | V10: =V9 -> 461 | W10: =+V10-V9 -> 0 | X10: =X9 -> 150077 | Y10: =SUM(X10-X9) -> 0 | Z10: =Z9 -> 98262 | AA10: =Z10-Z9 -> 0 | AB10: =AB9 -> 256 | AC10: =AC9 -> 731 | AD10: =AC10-AC9 -> 0 | AE10: =AE9 -> 227.8 | AF10: =AE10-AE9 -> 0 | AG10: =AG9 -> 2181.57 | AH10: =AG10-AG9 -> 0 | AI10: =AF10+AH10 -> 0 | AJ10: =+Z10-Z9 -> 0 | AK10: =SUM(Y10-L10) -> 1 | AL10: =SUM(AJ10-W10) -> 0 | AM10: ='General information '!D10 -> 17.5 | AN10: ='General information '!H10 -> 0 | AP10: ='General information '!J10 -> 0 | AR10: =A10 -> 44232 | AS10: =AS9 -> 0.9 | AT10: 146 | AU10: =AU9 -> 1.1 | AV10: 133 | AW10: 2.9 | AX10: 151 | AY10: =AS10*AT10 -> 131.4 | AZ10: =AU10*AV10 -> 146.3 | BA10: =AW10*AX10 -> 437.9 | BB10: =AY10-AY9 -> 0 | BC10: =AZ10-AZ9 -> -3.3 | BD10: =BA10-BA9 -> -17.4 | BE10: =SUM(BB10:BD10) -> -20.7 | BF10: =SUM(I10-BE10) -> 20.7 | BG10: =SUM(I10-BF10) -> -20.7
A11: =ELEC!C8 -> 44233 | B11: =B10 -> 109443 | C11: =B11-B10 -> 0 | D11: =C11/27 -> 0 | E11: =SUM((C11*$E$4)+(7500/'EDl log'!$A$34)) -> 267.85714 | G11: =G10 -> 615374 | H11: =G11-G10 -> 0 | I11: =C11+H11 -> 0 | J11: =IF(I11>0,E11/I11,0) -> 0 | K11: ='Swimming Pool quality check '!H11 -> 6715.5 | L11: =K11-K10 -> 0.5 | M11: =M10 -> 457.44 | N11: =SUM(M11-M10) -> 0 | O11: =O10 -> 529.52 | P11: =SUM(O11-O10) -> 0 | Q11: =SUM(P11+N11) -> 0 | T11: =T10 -> 5165 | U11: =SUM(T11-T10) -> 0 | V11: =V10 -> 461 | W11: =+V11-V10 -> 0 | X11: =X10 -> 150077 | Y11: =SUM(X11-X10) -> 0 | Z11: =Z10 -> 98262 | AA11: =Z11-Z10 -> 0 | AB11: =AB10 -> 256 | AC11: =AC10 -> 731 | AD11: =AC11-AC10 -> 0 | AE11: =AE10 -> 227.8 | AF11: =AE11-AE10 -> 0 | AG11: =AG10 -> 2181.57 | AH11: =AG11-AG10 -> 0 | AI11: =AF11+AH11 -> 0 | AJ11: =+Z11-Z10 -> 0 | AK11: =SUM(Y11-L11) -> -0.5 | AL11: =SUM(AJ11-W11) -> 0 | AM11: ='General information '!D11 -> 17 | AN11: ='General information '!H11 -> 0 | AP11: ='General information '!J11 -> 0 | AR11: =A11 -> 44233 | AS11: =AS10 -> 0.9 | AT11: =AT10 -> 146 | AU11: =AU10 -> 1.1 | AV11: 130 | AW11: 2.9 | AX11: 147 | AY11: =AS11*AT11 -> 131.4 | AZ11: =AU11*AV11 -> 143 | BA11: =AW11*AX11 -> 426.3 | BB11: =AY11-AY10 -> 0 | BC11: =AZ11-AZ10 -> -3.3 | BD11: =BA11-BA10 -> -11.6 | BE11: =SUM(BB11:BD11) -> -14.9 | BF11: =SUM(I11-BE11) -> 14.9 | BG11: =SUM(I11-BF11) -> -14.9
A12: =ELEC!C9 -> 44234 | B12: =B11 -> 109443 | C12: =B12-B11 -> 0 | D12: =C12/27 -> 0 | E12: =SUM((C12*$E$4)+(7500/'EDl log'!$A$34)) -> 267.85714 | G12: =G11 -> 615374 | H12: =G12-G11 -> 0 | I12: =C12+H12 -> 0 | J12: =IF(I12>0,E12/I12,0) -> 0 | K12: ='Swimming Pool quality check '!H12 -> 6716 | L12: =K12-K11 -> 0.5 | M12: =M11 -> 457.44 | N12: =SUM(M12-M11) -> 0 | O12: =O11 -> 529.52 | P12: =SUM(O12-O11) -> 0 | Q12: =SUM(P12+N12) -> 0 | T12: =T11 -> 5165 | U12: =SUM(T12-T11) -> 0 | V12: =V11 -> 461 | W12: =+V12-V11 -> 0 | X12: =X11 -> 150077 | Y12: =SUM(X12-X11) -> 0 | Z12: =Z11 -> 98262 | AA12: =Z12-Z11 -> 0 | AB12: =AB11 -> 256 | AC12: =AC11 -> 731 | AD12: =AC12-AC11 -> 0 | AE12: =AE11 -> 227.8 | AF12: =AE12-AE11 -> 0 | AG12: =AG11 -> 2181.57 | AH12: =AG12-AG11 -> 0 | AI12: =AF12+AH12 -> 0 | AJ12: =+Z12-Z11 -> 0 | AK12: =SUM(Y12-L12) -> -0.5 | AL12: =SUM(AJ12-W12) -> 0 | AM12: ='General information '!D12 -> 19 | AN12: ='General information '!H12 -> 0 | AP12: ='General information '!J12 -> 0 | AR12: =A12 -> 44234 | AS12: =AS11 -> 0.9 | AT12: 146 | AU12: =AU11 -> 1.1 | AV12: 128 | AW12: 2.9 | AX12: 143 | AY12: =AS12*AT12 -> 131.4 | AZ12: =AU12*AV12 -> 140.8 | BA12: =AW12*AX12 -> 414.7 | BB12: =AY12-AY11 -> 0 | BC12: =AZ12-AZ11 -> -2.2 | BD12: =BA12-BA11 -> -11.6 | BE12: =SUM(BB12:BD12) -> -13.8 | BF12: =SUM(I12-BE12) -> 13.8 | BG12: =SUM(I12-BF12) -> -13.8
A13: =ELEC!C10 -> 44235 | B13: =B12 -> 109443 | C13: =B13-B12 -> 0 | D13: =C13/27 -> 0 | E13: =SUM((C13*$E$4)+(7500/'EDl log'!$A$34)) -> 267.85714 | G13: =G12 -> 615374 | H13: =G13-G12 -> 0 | I13: =C13+H13 -> 0 | J13: =IF(I13>0,E13/I13,0) -> 0 | K13: ='Swimming Pool quality check '!H13 -> 6717 | L13: =K13-K12 -> 1 | M13: =M12 -> 457.44 | N13: =SUM(M13-M12) -> 0 | O13: =O12 -> 529.52 | P13: =SUM(O13-O12) -> 0 | Q13: =SUM(P13+N13) -> 0 | T13: =T12 -> 5165 | U13: =SUM(T13-T12) -> 0 | V13: =V12 -> 461 | W13: =+V13-V12 -> 0 | X13: =X12 -> 150077 | Y13: =SUM(X13-X12) -> 0 | Z13: =Z12 -> 98262 | AA13: =Z13-Z12 -> 0 | AB13: =AB12 -> 256 | AC13: =AC12 -> 731 | AD13: =AC13-AC12 -> 0 | AE13: =AE12 -> 227.8 | AF13: =AE13-AE12 -> 0 | AG13: =AG12 -> 2181.57 | AH13: =AG13-AG12 -> 0 | AI13: =AF13+AH13 -> 0 | AJ13: =+Z13-Z12 -> 0 | AK13: =SUM(Y13-L13) -> -1 | AL13: =SUM(AJ13-W13) -> 0 | AM13: ='General information '!D13 -> 21 | AN13: ='General information '!J13 -> 0 | AP13: ='General information '!J13 -> 0 | AR13: =A13 -> 44235 | AS13: =AS12 -> 0.9 | AT13: =AT12 -> 146 | AU13: =AU12 -> 1.1 | AV13: 126 | AW13: 2.9 | AX13: 140 | AY13: =AS13*AT13 -> 131.4 | AZ13: =AU13*AV13 -> 138.6 | BA13: =AW13*AX13 -> 406 | BB13: =AY13-AY12 -> 0 | BC13: =AZ13-AZ12 -> -2.2 | BD13: =BA13-BA12 -> -8.7 | BE13: =SUM(BB13:BD13) -> -10.9 | BF13: =SUM(I13-BE13) -> 10.9 | BG13: =SUM(I13-BF13) -> -10.9
A14: =ELEC!C11 -> 44236 | B14: =B13 -> 109443 | C14: =B14-B13 -> 0 | D14: =C14/27 -> 0 | E14: =SUM((C14*$E$4)+(7500/'EDl log'!$A$34)) -> 267.85714 | G14: =G13 -> 615374 | H14: =G14-G13 -> 0 | I14: =C14+H14 -> 0 | J14: =IF(I14>0,E14/I14,0) -> 0 | K14: ='Swimming Pool quality check '!H14 -> 6718 | L14: =K14-K13 -> 1 | M14: =M13 -> 457.44 | N14: =SUM(M14-M13) -> 0 | O14: =O13 -> 529.52 | P14: =SUM(O14-O13) -> 0 | Q14: =SUM(P14+N14) -> 0 | T14: =T13 -> 5165 | U14: =SUM(T14-T13) -> 0 | V14: =V13 -> 461 | W14: =+V14-V13 -> 0 | X14: =X13 -> 150077 | Y14: =SUM(X14-X13) -> 0 | Z14: =Z13 -> 98262 | AA14: =Z14-Z13 -> 0 | AB14: =AB13 -> 256 | AC14: =AC13 -> 731 | AD14: =AC14-AC13 -> 0 | AE14: =AE13 -> 227.8 | AF14: =AE14-AE13 -> 0 | AG14: =AG13 -> 2181.57 | AH14: =AG14-AG13 -> 0 | AI14: =AF14+AH14 -> 0 | AJ14: =+Z14-Z13 -> 0 | AK14: =SUM(Y14-L14) -> -1 | AL14: =SUM(AJ14-W14) -> 0 | AM14: ='General information '!D14 -> 19.5 | AN14: ='General information '!H14 -> 0 | AP14: ='General information '!J14 -> 0 | AR14: =A14 -> 44236 | AS14: =AS13 -> 0.9 | AT14: =AT13 -> 146 | AU14: =AU13 -> 1.1 | AV14: 122 | AW14: 2.9 | AX14: 137 | AY14: =AS14*AT14 -> 131.4 | AZ14: =AU14*AV14 -> 134.2 | BA14: =AW14*AX14 -> 397.3 | BB14: =AY14-AY13 -> 0 | BC14: =AZ14-AZ13 -> -4.4 | BD14: =BA14-BA13 -> -8.7 | BE14: =SUM(BB14:BD14) -> -13.1 | BF14: =SUM(I14-BE14) -> 13.1 | BG14: =SUM(I14-BF14) -> -13.1
A15: =ELEC!C12 -> 44237 | B15: =B14 -> 109443 | C15: =B15-B14 -> 0 | D15: =C15/27 -> 0 | E15: =SUM((C15*$E$4)+(7500/'EDl log'!$A$34)) -> 267.85714 | G15: =G14 -> 615374 | H15: =G15-G14 -> 0 | I15: =C15+H15 -> 0 | J15: =IF(I15>0,E15/I15,0) -> 0 | K15: ='Swimming Pool quality check '!H15 -> 6718 | L15: =K15-K14 -> 0 | M15: =M14 -> 457.44 | N15: =SUM(M15-M14) -> 0 | O15: =O14 -> 529.52 | P15: =SUM(O15-O14) -> 0 | Q15: =SUM(P15+N15) -> 0 | T15: =T14 -> 5165 | U15: =SUM(T15-T14) -> 0 | V15: =V14 -> 461 | W15: =+V15-V14 -> 0 | X15: =X14 -> 150077 | Y15: =SUM(X15-X14) -> 0 | Z15: =Z14 -> 98262 | AA15: =Z15-Z14 -> 0 | AB15: =AB14 -> 256 | AC15: =AC14 -> 731 | AD15: =AC15-AC14 -> 0 | AE15: =AE14 -> 227.8 | AF15: =AE15-AE14 -> 0 | AG15: =AG14 -> 2181.57 | AH15: =AG15-AG14 -> 0 | AI15: =AF15+AH15 -> 0 | AJ15: =+Z15-Z14 -> 0 | AK15: =SUM(Y15-L15) -> 0 | AL15: =SUM(AJ15-W15) -> 0 | AM15: ='General information '!D15 -> 16.5 | AN15: ='General information '!H15 -> 0 | AP15: ='General information '!J15 -> 0 | AR15: =A15 -> 44237 | AS15: =AS14 -> 0.9 | AT15: =AT14 -> 146 | AU15: =AU14 -> 1.1 | AV15: 119 | AW15: 2.9 | AX15: 135 | AY15: =AS15*AT15 -> 131.4 | AZ15: =AU15*AV15 -> 130.9 | BA15: =AW15*AX15 -> 391.5 | BB15: =AY15-AY14 -> 0 | BC15: =AZ15-AZ14 -> -3.3 | BD15: =BA15-BA14 -> -5.8 | BE15: =SUM(BB15:BD15) -> -9.1 | BF15: =SUM(I15-BE15) -> 9.1 | BG15: =SUM(I15-BF15) -> -9.1
A16: =ELEC!C13 -> 44238 | B16: =B15 -> 109443 | C16: =B16-B15 -> 0 | D16: =C16/27 -> 0 | E16: =SUM((C16*$E$4)+(7500/'EDl log'!$A$34)) -> 267.85714 | G16: =G15 -> 615374 | H16: =G16-G15 -> 0 | I16: =C16+H16 -> 0 | J16: =IF(I16>0,E16/I16,0) -> 0 | K16: ='Swimming Pool quality check '!H16 -> 6718 | L16: =K16-K15 -> 0 | M16: =M15 -> 457.44 | N16: =SUM(M16-M15) -> 0 | O16: =O15 -> 529.52 | P16: =SUM(O16-O15) -> 0 | Q16: =SUM(P16+N16) -> 0 | T16: =T15 -> 5165 | U16: =SUM(T16-T15) -> 0 | V16: =V15 -> 461 | W16: =+V16-V15 -> 0 | X16: =X15 -> 150077 | Y16: =SUM(X16-X15) -> 0 | Z16: =Z15 -> 98262 | AA16: =Z16-Z15 -> 0 | AB16: =AB15 -> 256 | AC16: =AC15 -> 731 | AD16: =AC16-AC15 -> 0 | AE16: =AE15 -> 227.8 | AF16: =AE16-AE15 -> 0 | AG16: =AG15 -> 2181.57 | AH16: =AG16-AG15 -> 0 | AI16: =AF16+AH16 -> 0 | AJ16: =+Z16-Z15 -> 0 | AK16: =SUM(Y16-L16) -> 0 | AL16: =SUM(AJ16-W16) -> 0 | AM16: ='General information '!D16 -> 15.5 | AN16: ='General information '!H16 -> 0 | AP16: ='General information '!J16 -> 0 | AR16: =A16 -> 44238 | AS16: =AS15 -> 0.9 | AT16: =AT15 -> 146 | AU16: =AU15 -> 1.1 | AV16: 114 | AW16: 2.9 | AX16: 133 | AY16: =AS16*AT16 -> 131.4 | AZ16: =AU16*AV16 -> 125.4 | BA16: =AW16*AX16 -> 385.7 | BB16: =AY16-AY15 -> 0 | BC16: =AZ16-AZ15 -> -5.5 | BD16: =BA16-BA15 -> -5.8 | BE16: =SUM(BB16:BD16) -> -11.3 | BF16: =SUM(I16-BE16) -> 11.3 | BG16: =SUM(I16-BF16) -> -11.3
A17: =ELEC!C14 -> 44239 | B17: =B16 -> 109443 | C17: =B17-B16 -> 0 | D17: =C17/27 -> 0 | E17: =SUM((C17*$E$4)+(7500/'EDl log'!$A$34)) -> 267.85714 | G17: =G16 -> 615374 | H17: =G17-G16 -> 0 | I17: =C17+H17 -> 0 | J17: =IF(I17>0,E17/I17,0) -> 0 | K17: ='Swimming Pool quality check '!H17 -> 6718 | L17: =K17-K16 -> 0 | M17: =M16 -> 457.44 | N17: =SUM(M17-M16) -> 0 | O17: =O16 -> 529.52 | P17: =SUM(O17-O16) -> 0 | Q17: =SUM(P17+N17) -> 0 | T17: =T16 -> 5165 | U17: =SUM(T17-T16) -> 0 | V17: =V16 -> 461 | W17: =+V17-V16 -> 0 | X17: =X16 -> 150077 | Y17: =SUM(X17-X16) -> 0 | Z17: =Z16 -> 98262 | AA17: =Z17-Z16 -> 0 | AB17: =AB16 -> 256 | AC17: =AC16 -> 731 | AD17: =AC17-AC16 -> 0 | AE17: =AE16 -> 227.8 | AF17: =AE17-AE16 -> 0 | AG17: =AG16 -> 2181.57 | AH17: =AG17-AG16 -> 0 | AI17: =AF17+AH17 -> 0 | AJ17: =+Z17-Z16 -> 0 | AK17: =SUM(Y17-L17) -> 0 | AL17: =SUM(AJ17-W17) -> 0 | AM17: ='General information '!D17 -> 15.5 | AN17: ='General information '!H17 -> 0 | AP17: ='General information '!J17 -> 0 | AR17: =A17 -> 44239 | AS17: =AS16 -> 0.9 | AT17: =AT16 -> 146 | AU17: =AU16 -> 1.1 | AV17: 110 | AW17: 2.9 | AX17: 130 | AY17: =AS17*AT17 -> 131.4 | AZ17: =AU17*AV17 -> 121 | BA17: =AW17*AX17 -> 377 | BB17: =AY17-AY16 -> 0 | BC17: =AZ17-AZ16 -> -4.4 | BD17: =BA17-BA16 -> -8.7 | BE17: =SUM(BB17:BD17) -> -13.1 | BF17: =SUM(I17-BE17) -> 13.1 | BG17: =SUM(I17-BF17) -> -13.1
A18: =ELEC!C15 -> 44240 | B18: =B17 -> 109443 | C18: =B18-B17 -> 0 | D18: =C18/27 -> 0 | E18: =SUM((C18*$E$4)+(7500/'EDl log'!$A$34)) -> 267.85714 | G18: =G17 -> 615374 | H18: =G18-G17 -> 0 | I18: =C18+H18 -> 0 | J18: =IF(I18>0,E18/I18,0) -> 0 | K18: ='Swimming Pool quality check '!H18 -> 6718 | L18: =K18-K17 -> 0 | M18: =M17 -> 457.44 | N18: =SUM(M18-M17) -> 0 | O18: =O17 -> 529.52 | P18: =SUM(O18-O17) -> 0 | Q18: =SUM(P18+N18) -> 0 | T18: =T17 -> 5165 | U18: =SUM(T18-T17) -> 0 | V18: =V17 -> 461 | W18: =+V18-V17 -> 0 | X18: =X17 -> 150077 | Y18: =SUM(X18-X17) -> 0 | Z18: =Z17 -> 98262 | AA18: =Z18-Z17 -> 0 | AB18: =AB17 -> 256 | AC18: =AC17 -> 731 | AD18: =AC18-AC17 -> 0 | AE18: =AE17 -> 227.8 | AF18: =AE18-AE17 -> 0 | AG18: =AG17 -> 2181.57 | AH18: =AG18-AG17 -> 0 | AI18: =AF18+AH18 -> 0 | AJ18: =+Z18-Z17 -> 0 | AK18: =SUM(Y18-L18) -> 0 | AL18: =SUM(AJ18-W18) -> 0 | AM18: ='General information '!D18 -> 0 | AN18: ='General information '!H18 -> 0 | AP18: ='General information '!J18 -> 0 | AR18: =A18 -> 44240 | AS18: =AS17 -> 0.9 | AT18: =AT17 -> 146 | AU18: =AU17 -> 1.1 | AV18: =AV17 -> 110 | AW18: 2.9 | AX18: =AX17 -> 130 | AY18: =AS18*AT18 -> 131.4 | AZ18: =AU18*AV18 -> 121 | BA18: =AW18*AX18 -> 377 | BB18: =AY18-AY17 -> 0 | BC18: =AZ18-AZ17 -> 0 | BD18: =BA18-BA17 -> 0 | BE18: =SUM(BB18:BD18) -> 0 | BF18: =SUM(I18-BE18) -> 0 | BG18: =SUM(I18-BF18) -> 0
A19: =ELEC!C16 -> 44241 | B19: =B18 -> 109443 | C19: =B19-B18 -> 0 | D19: =C19/27 -> 0 | E19: =SUM((C19*$E$4)+(7500/'EDl log'!$A$34)) -> 267.85714 | G19: =G18 -> 615374 | H19: =G19-G18 -> 0 | I19: =C19+H19 -> 0 | J19: =IF(I19>0,E19/I19,0) -> 0 | K19: ='Swimming Pool quality check '!H19 -> 6718 | L19: =K19-K18 -> 0 | M19: =M18 -> 457.44 | N19: =SUM(M19-M18) -> 0 | O19: =O18 -> 529.52 | P19: =SUM(O19-O18) -> 0 | Q19: =SUM(P19+N19) -> 0 | T19: =T18 -> 5165 | U19: =SUM(T19-T18) -> 0 | V19: =V18 -> 461 | W19: =+V19-V18 -> 0 | X19: =X18 -> 150077 | Y19: =SUM(X19-X18) -> 0 | Z19: =Z18 -> 98262 | AA19: =Z19-Z18 -> 0 | AB19: =AB18 -> 256 | AC19: =AC18 -> 731 | AD19: =AC19-AC18 -> 0 | AE19: =AE18 -> 227.8 | AF19: =AE19-AE18 -> 0 | AG19: =AG18 -> 2181.57 | AH19: =AG19-AG18 -> 0 | AI19: =AF19+AH19 -> 0 | AJ19: =+Z19-Z18 -> 0 | AK19: =SUM(Y19-L19) -> 0 | AL19: =SUM(AJ19-W19) -> 0 | AM19: ='General information '!D19 -> 0 | AN19: ='General information '!H19 -> 0 | AP19: ='General information '!J19 -> 0 | AR19: =A19 -> 44241 | AS19: =AS18 -> 0.9 | AT19: =AT18 -> 146 | AU19: =AU18 -> 1.1 | AV19: =AV18 -> 110 | AW19: 2.9 | AX19: =AX18 -> 130 | AY19: =AS19*AT19 -> 131.4 | AZ19: =AU19*AV19 -> 121 | BA19: =AW19*AX19 -> 377 | BB19: =AY19-AY18 -> 0 | BC19: =AZ19-AZ18 -> 0 | BD19: =BA19-BA18 -> 0 | BE19: =SUM(BB19:BD19) -> 0 | BF19: =SUM(I19-BE19) -> 0 | BG19: =SUM(I19-BF19) -> 0
A20: =ELEC!C17 -> 44242 | B20: =B19 -> 109443 | C20: =B20-B19 -> 0 | D20: =C20/27 -> 0 | E20: =SUM((C20*$E$4)+(7500/'EDl log'!$A$34)) -> 267.85714 | G20: =G19 -> 615374 | H20: =G20-G19 -> 0 | I20: =C20+H20 -> 0 | J20: =IF(I20>0,E20/I20,0) -> 0 | K20: ='Swimming Pool quality check '!H20 -> 6718 | L20: =K20-K19 -> 0 | M20: =M19 -> 457.44 | N20: =SUM(M20-M19) -> 0 | O20: =O19 -> 529.52 | P20: =SUM(O20-O19) -> 0 | Q20: =SUM(P20+N20) -> 0 | T20: =T19 -> 5165 | U20: =SUM(T20-T19) -> 0 | V20: =V19 -> 461 | W20: =+V20-V19 -> 0 | X20: =X19 -> 150077 | Y20: =SUM(X20-X19) -> 0 | Z20: =Z19 -> 98262 | AA20: =Z20-Z19 -> 0 | AB20: =AB19 -> 256 | AC20: =AC19 -> 731 | AD20: =AC20-AC19 -> 0 | AE20: =AE19 -> 227.8 | AF20: =AE20-AE19 -> 0 | AG20: =AG19 -> 2181.57 | AH20: =AG20-AG19 -> 0 | AI20: =AF20+AH20 -> 0 | AJ20: =+Z20-Z19 -> 0 | AK20: =SUM(Y20-L20) -> 0 | AL20: =SUM(AJ20-W20) -> 0 | AM20: ='General information '!D20 -> 0 | AN20: ='General information '!H20 -> 0 | AP20: ='General information '!J20 -> 0 | AR20: =A20 -> 44242 | AS20: =AS19 -> 0.9 | AT20: =AT19 -> 146 | AU20: =AU19 -> 1.1 | AV20: =AV19 -> 110 | AW20: 2.9 | AX20: =AX19 -> 130 | AY20: =AS20*AT20 -> 131.4 | AZ20: =AU20*AV20 -> 121 | BA20: =AW20*AX20 -> 377 | BB20: =AY20-AY19 -> 0 | BC20: =AZ20-AZ19 -> 0 | BD20: =BA20-BA19 -> 0 | BE20: =SUM(BB20:BD20) -> 0 | BF20: =SUM(I20-BE20) -> 0 | BG20: =SUM(I20-BF20) -> 0
A21: =ELEC!C18 -> 44243 | B21: =B20 -> 109443 | C21: =B21-B20 -> 0 | D21: =C21/27 -> 0 | E21: =SUM((C21*$E$4)+(7500/'EDl log'!$A$34)) -> 267.85714 | G21: =G20 -> 615374 | H21: =G21-G20 -> 0 | I21: =C21+H21 -> 0 | J21: =IF(I21>0,E21/I21,0) -> 0 | K21: ='Swimming Pool quality check '!H21 -> 6718 | L21: =K21-K20 -> 0 | M21: =M20 -> 457.44 | N21: =SUM(M21-M20) -> 0 | O21: =O20 -> 529.52 | P21: =SUM(O21-O20) -> 0 | Q21: =SUM(P21+N21) -> 0 | T21: =T20 -> 5165 | U21: =SUM(T21-T20) -> 0 | V21: =V20 -> 461 | W21: =+V21-V20 -> 0 | X21: =X20 -> 150077 | Y21: =SUM(X21-X20) -> 0 | Z21: =Z20 -> 98262 | AA21: =Z21-Z20 -> 0 | AB21: =AB20 -> 256 | AC21: =AC20 -> 731 | AD21: =AC21-AC20 -> 0 | AE21: =AE20 -> 227.8 | AF21: =AE21-AE20 -> 0 | AG21: =AG20 -> 2181.57 | AH21: =AG21-AG20 -> 0 | AI21: =AF21+AH21 -> 0 | AJ21: =+Z21-Z20 -> 0 | AK21: =SUM(Y21-L21) -> 0 | AL21: =SUM(AJ21-W21) -> 0 | AM21: ='General information '!D21 -> 0 | AN21: ='General information '!H21 -> 0 | AP21: ='General information '!J21 -> 0 | AR21: =A21 -> 44243 | AS21: =AS20 -> 0.9 | AT21: =AT20 -> 146 | AU21: =AU20 -> 1.1 | AV21: =AV20 -> 110 | AW21: 2.9 | AX21: =AX20 -> 130 | AY21: =AS21*AT21 -> 131.4 | AZ21: =AU21*AV21 -> 121 | BA21: =AW21*AX21 -> 377 | BB21: =AY21-AY20 -> 0 | BC21: =AZ21-AZ20 -> 0 | BD21: =BA21-BA20 -> 0 | BE21: =SUM(BB21:BD21) -> 0 | BF21: =SUM(I21-BE21) -> 0 | BG21: =SUM(I21-BF21) -> 0
A22: =ELEC!C19 -> 44244 | B22: =B21 -> 109443 | C22: =B22-B21 -> 0 | D22: =C22/27 -> 0 | E22: =SUM((C22*$E$4)+(7500/'EDl log'!$A$34)) -> 267.85714 | G22: =G21 -> 615374 | H22: =G22-G21 -> 0 | I22: =C22+H22 -> 0 | J22: =IF(I22>0,E22/I22,0) -> 0 | K22: ='Swimming Pool quality check '!H22 -> 6718 | L22: =K22-K21 -> 0 | M22: =M21 -> 457.44 | N22: =SUM(M22-M21) -> 0 | O22: =O21 -> 529.52 | P22: =SUM(O22-O21) -> 0 | Q22: =SUM(P22+N22) -> 0 | T22: =T21 -> 5165 | U22: =SUM(T22-T21) -> 0 | V22: =V21 -> 461 | W22: =+V22-V21 -> 0 | X22: =X21 -> 150077 | Y22: =SUM(X22-X21) -> 0 | Z22: =Z21 -> 98262 | AA22: =Z22-Z21 -> 0 | AB22: =AB21 -> 256 | AC22: =AC21 -> 731 | AD22: =AC22-AC21 -> 0 | AE22: =AE21 -> 227.8 | AF22: =AE22-AE21 -> 0 | AG22: =AG21 -> 2181.57 | AH22: =AG22-AG21 -> 0 | AI22: =AF22+AH22 -> 0 | AJ22: =+Z22-Z21 -> 0 | AK22: =SUM(Y22-L22) -> 0 | AL22: =SUM(AJ22-W22) -> 0 | AM22: ='General information '!D22 -> 0 | AN22: ='General information '!H22 -> 0 | AP22: ='General information '!J22 -> 0 | AR22: =A22 -> 44244 | AS22: =AS21 -> 0.9 | AT22: =AT21 -> 146 | AU22: =AU21 -> 1.1 | AV22: =AV21 -> 110 | AW22: 2.9 | AX22: =AX21 -> 130 | AY22: =AS22*AT22 -> 131.4 | AZ22: =AU22*AV22 -> 121 | BA22: =AW22*AX22 -> 377 | BB22: =AY22-AY21 -> 0 | BC22: =AZ22-AZ21 -> 0 | BD22: =BA22-BA21 -> 0 | BE22: =SUM(BB22:BD22) -> 0 | BF22: =SUM(I22-BE22) -> 0 | BG22: =SUM(I22-BF22) -> 0
A23: =ELEC!C20 -> 44245 | B23: =B22 -> 109443 | C23: =B23-B22 -> 0 | D23: =C23/27 -> 0 | E23: =SUM((C23*$E$4)+(7500/'EDl log'!$A$34)) -> 267.85714 | G23: =G22 -> 615374 | H23: =G23-G22 -> 0 | I23: =C23+H23 -> 0 | J23: =IF(I23>0,E23/I23,0) -> 0 | K23: ='Swimming Pool quality check '!H23 -> 6718 | L23: =K23-K22 -> 0 | M23: =M22 -> 457.44 | N23: =SUM(M23-M22) -> 0 | O23: =O22 -> 529.52 | P23: =SUM(O23-O22) -> 0 | Q23: =SUM(P23+N23) -> 0 | T23: =T22 -> 5165 | U23: =SUM(T23-T22) -> 0 | V23: =V22 -> 461 | W23: =+V23-V22 -> 0 | X23: =X22 -> 150077 | Y23: =SUM(X23-X22) -> 0 | Z23: =Z22 -> 98262 | AA23: =Z23-Z22 -> 0 | AB23: =AB22 -> 256 | AC23: =AC22 -> 731 | AD23: =AC23-AC22 -> 0 | AE23: =AE22 -> 227.8 | AF23: =AE23-AE22 -> 0 | AG23: =AG22 -> 2181.57 | AH23: =AG23-AG22 -> 0 | AI23: =AF23+AH23 -> 0 | AJ23: =+Z23-Z22 -> 0 | AK23: =SUM(Y23-L23) -> 0 | AL23: =SUM(AJ23-W23) -> 0 | AM23: ='General information '!D23 -> 0 | AN23: ='General information '!H23 -> 0 | AP23: ='General information '!J23 -> 0 | AR23: =A23 -> 44245 | AS23: =AS22 -> 0.9 | AT23: =AT22 -> 146 | AU23: =AU22 -> 1.1 | AV23: =AV22 -> 110 | AW23: 2.9 | AX23: =AX22 -> 130 | AY23: =AS23*AT23 -> 131.4 | AZ23: =AU23*AV23 -> 121 | BA23: =AW23*AX23 -> 377 | BB23: =AY23-AY22 -> 0 | BC23: =AZ23-AZ22 -> 0 | BD23: =BA23-BA22 -> 0 | BE23: =SUM(BB23:BD23) -> 0 | BF23: =SUM(I23-BE23) -> 0 | BG23: =SUM(I23-BF23) -> 0
A24: =ELEC!C21 -> 44246 | B24: =B23 -> 109443 | C24: =B24-B23 -> 0 | D24: =C24/27 -> 0 | E24: =SUM((C24*$E$4)+(7500/'[3]EDl log'!$A$37)) -> 241.93548 | G24: =G23 -> 615374 | H24: =G24-G23 -> 0 | I24: =C24+H24 -> 0 | J24: =IF(I24>0,E24/I24,0) -> 0 | K24: ='[3]Swimming Pool quality check '!H24 -> 6713 | L24: =K24-K23 -> -5 | M24: =M23 -> 457.44 | N24: =SUM(M24-M23) -> 0 | O24: =O23 -> 529.52 | P24: =SUM(O24-O23) -> 0 | Q24: =SUM(P24+N24) -> 0 | T24: =T23 -> 5165 | U24: =SUM(T24-T23) -> 0 | V24: =V23 -> 461 | W24: =+V24-V23 -> 0 | X24: =X23 -> 150077 | Y24: =SUM(X24-X23) -> 0 | Z24: =Z23 -> 98262 | AA24: =Z24-Z23 -> 0 | AB24: =AB23 -> 256 | AC24: =AC23 -> 731 | AD24: =AC24-AC23 -> 0 | AE24: =AE23 -> 227.8 | AF24: =AE24-AE23 -> 0 | AG24: =AG23 -> 2181.57 | AH24: =AG24-AG23 -> 0 | AI24: =AF24+AH24 -> 0 | AJ24: =+Z24-Z23 -> 0 | AK24: =SUM(Y24-L24) -> 5 | AL24: =SUM(AJ24-W24) -> 0 | AM24: ='[3]General information '!D24 -> 13.5 | AN24: ='[3]General information '!H24 -> 0 | AP24: ='[3]General information '!J24 -> 0 | AR24: =A24 -> 44246 | AS24: =AS23 -> 0.9 | AT24: =AT23 -> 146 | AU24: =AU23 -> 1.1 | AV24: =AV23 -> 110 | AW24: 2.9 | AX24: =AX23 -> 130 | AY24: =AS24*AT24 -> 131.4 | AZ24: =AU24*AV24 -> 121 | BA24: =AW24*AX24 -> 377 | BB24: =AY24-AY23 -> 0 | BC24: =AZ24-AZ23 -> 0 | BD24: =BA24-BA23 -> 0 | BE24: =SUM(BB24:BD24) -> 0 | BF24: =SUM(I24-BE24) -> 0 | BG24: =SUM(I24-BF24) -> 0
A25: =ELEC!C22 -> 44247 | B25: =B24 -> 109443 | C25: =B25-B24 -> 0 | D25: =C25/27 -> 0 | E25: =SUM((C25*$E$4)+(7500/'EDl log'!$A$34)) -> 267.85714 | G25: =G24 -> 615374 | H25: =G25-G24 -> 0 | I25: =C25+H25 -> 0 | J25: =IF(I25>0,E25/I25,0) -> 0 | K25: ='Swimming Pool quality check '!H25 -> 6718 | L25: =K25-K24 -> 5 | M25: =M24 -> 457.44 | N25: =SUM(M25-M24) -> 0 | O25: =O24 -> 529.52 | P25: =SUM(O25-O24) -> 0 | Q25: =SUM(P25+N25) -> 0 | T25: =T24 -> 5165 | U25: =SUM(T25-T24) -> 0 | V25: =V24 -> 461 | W25: =+V25-V24 -> 0 | X25: =X24 -> 150077 | Y25: =SUM(X25-X24) -> 0 | Z25: =Z24 -> 98262 | AA25: =Z25-Z24 -> 0 | AB25: =AB24 -> 256 | AC25: =AC24 -> 731 | AD25: =AC25-AC24 -> 0 | AE25: =AE24 -> 227.8 | AF25: =AE25-AE24 -> 0 | AG25: =AG24 -> 2181.57 | AH25: =AG25-AG24 -> 0 | AI25: =AF25+AH25 -> 0 | AJ25: =+Z25-Z24 -> 0 | AK25: =SUM(Y25-L25) -> -5 | AL25: =SUM(AJ25-W25) -> 0 | AM25: ='General information '!D25 -> 0 | AN25: ='General information '!H25 -> 0 | AP25: ='General information '!J25 -> 0 | AR25: =A25 -> 44247 | AS25: =AS24 -> 0.9 | AT25: =AT24 -> 146 | AU25: =AU24 -> 1.1 | AV25: =AV24 -> 110 | AW25: 2.9 | AX25: =AX24 -> 130 | AY25: =AS25*AT25 -> 131.4 | AZ25: =AU25*AV25 -> 121 | BA25: =AW25*AX25 -> 377 | BB25: =AY25-AY24 -> 0 | BC25: =AZ25-AZ24 -> 0 | BD25: =BA25-BA24 -> 0 | BE25: =SUM(BB25:BD25) -> 0 | BF25: =SUM(I25-BE25) -> 0 | BG25: =SUM(I25-BF25) -> 0
A26: =ELEC!C23 -> 44248 | B26: =B25 -> 109443 | C26: =B26-B25 -> 0 | D26: =C26/27 -> 0 | E26: =SUM((C26*$E$4)+(7500/'EDl log'!$A$34)) -> 267.85714 | G26: =G25 -> 615374 | H26: =G26-G25 -> 0 | I26: =C26+H26 -> 0 | J26: =IF(I26>0,E26/I26,0) -> 0 | K26: ='Swimming Pool quality check '!H26 -> 6718 | L26: =K26-K25 -> 0 | M26: =M25 -> 457.44 | N26: =SUM(M26-M25) -> 0 | O26: =O25 -> 529.52 | P26: =SUM(O26-O25) -> 0 | Q26: =SUM(P26+N26) -> 0 | T26: =T25 -> 5165 | U26: =SUM(T26-T25) -> 0 | V26: =V25 -> 461 | W26: =+V26-V25 -> 0 | X26: =X25 -> 150077 | Y26: =SUM(X26-X25) -> 0 | Z26: =Z25 -> 98262 | AA26: =Z26-Z25 -> 0 | AB26: =AB25 -> 256 | AC26: =AC25 -> 731 | AD26: =AC26-AC25 -> 0 | AE26: =AE25 -> 227.8 | AF26: =AE26-AE25 -> 0 | AG26: =AG25 -> 2181.57 | AH26: =AG26-AG25 -> 0 | AI26: =AF26+AH26 -> 0 | AJ26: =+Z26-Z25 -> 0 | AK26: =SUM(Y26-L26) -> 0 | AL26: =SUM(AJ26-W26) -> 0 | AM26: ='General information '!D26 -> 0 | AN26: ='General information '!H26 -> 0 | AP26: ='General information '!J26 -> 0 | AR26: =A26 -> 44248 | AS26: =AS25 -> 0.9 | AT26: =AT25 -> 146 | AU26: =AU25 -> 1.1 | AV26: =AV25 -> 110 | AW26: 2.9 | AX26: =AX25 -> 130 | AY26: =AS26*AT26 -> 131.4 | AZ26: =AU26*AV26 -> 121 | BA26: =AW26*AX26 -> 377 | BB26: =AY26-AY25 -> 0 | BC26: =AZ26-AZ25 -> 0 | BD26: =BA26-BA25 -> 0 | BE26: =SUM(BB26:BD26) -> 0 | BF26: =SUM(I26-BE26) -> 0 | BG26: =SUM(I26-BF26) -> 0
A27: =ELEC!C24 -> 44249 | B27: =B26 -> 109443 | C27: =B27-B26 -> 0 | D27: =C27/27 -> 0 | E27: =SUM((C27*$E$4)+(7500/'EDl log'!$A$34)) -> 267.85714 | G27: =G26 -> 615374 | H27: =G27-G26 -> 0 | I27: =C27+H27 -> 0 | J27: =IF(I27>0,E27/I27,0) -> 0 | K27: ='Swimming Pool quality check '!H27 -> 6718 | L27: =K27-K26 -> 0 | M27: =M26 -> 457.44 | N27: =SUM(M27-M26) -> 0 | O27: =O26 -> 529.52 | P27: =SUM(O27-O26) -> 0 | Q27: =SUM(P27+N27) -> 0 | T27: =T26 -> 5165 | U27: =SUM(T27-T26) -> 0 | V27: =V26 -> 461 | W27: =+V27-V26 -> 0 | X27: =X26 -> 150077 | Y27: =SUM(X27-X26) -> 0 | Z27: =Z26 -> 98262 | AA27: =Z27-Z26 -> 0 | AB27: =AB26 -> 256 | AC27: =AC26 -> 731 | AD27: =AC27-AC26 -> 0 | AE27: =AE26 -> 227.8 | AF27: =AE27-AE26 -> 0 | AG27: =AG26 -> 2181.57 | AH27: =AG27-AG26 -> 0 | AI27: =AF27+AH27 -> 0 | AJ27: =+Z27-Z26 -> 0 | AK27: =SUM(Y27-L27) -> 0 | AL27: =SUM(AJ27-W27) -> 0 | AM27: ='General information '!D27 -> 0 | AN27: ='General information '!H27 -> 0 | AP27: ='General information '!J27 -> 0 | AR27: =A27 -> 44249 | AS27: =AS26 -> 0.9 | AT27: =AT26 -> 146 | AU27: =AU26 -> 1.1 | AV27: =AV26 -> 110 | AW27: 2.9 | AX27: =AX26 -> 130 | AY27: =AS27*AT27 -> 131.4 | AZ27: =AU27*AV27 -> 121 | BA27: =AW27*AX27 -> 377 | BB27: =AY27-AY26 -> 0 | BC27: =AZ27-AZ26 -> 0 | BD27: =BA27-BA26 -> 0 | BE27: =SUM(BB27:BD27) -> 0 | BF27: =SUM(I27-BE27) -> 0 | BG27: =SUM(I27-BF27) -> 0
A28: =ELEC!C25 -> 44250 | B28: =B27 -> 109443 | C28: =B28-B27 -> 0 | D28: =C28/27 -> 0 | E28: =SUM((C28*$E$4)+(7500/'EDl log'!$A$34)) -> 267.85714 | G28: =G27 -> 615374 | H28: =G28-G27 -> 0 | I28: =C28+H28 -> 0 | J28: =IF(I28>0,E28/I28,0) -> 0 | K28: ='Swimming Pool quality check '!H28 -> 6718 | L28: =K28-K27 -> 0 | M28: =M27 -> 457.44 | N28: =SUM(M28-M27) -> 0 | O28: =O27 -> 529.52 | P28: =SUM(O28-O27) -> 0 | Q28: =SUM(P28+N28) -> 0 | T28: =T27 -> 5165 | U28: =SUM(T28-T27) -> 0 | V28: =V27 -> 461 | W28: =+V28-V27 -> 0 | X28: =X27 -> 150077 | Y28: =SUM(X28-X27) -> 0 | Z28: =Z27 -> 98262 | AA28: =Z28-Z27 -> 0 | AB28: =AB27 -> 256 | AC28: =AC27 -> 731 | AD28: =AC28-AC27 -> 0 | AE28: =AE27 -> 227.8 | AF28: =AE28-AE27 -> 0 | AG28: =AG27 -> 2181.57 | AH28: =AG28-AG27 -> 0 | AI28: =AF28+AH28 -> 0 | AJ28: =+Z28-Z27 -> 0 | AK28: =SUM(Y28-L28) -> 0 | AL28: =SUM(AJ28-W28) -> 0 | AM28: ='General information '!D28 -> 0 | AN28: ='General information '!H28 -> 0 | AP28: ='General information '!J28 -> 0 | AR28: =A28 -> 44250 | AS28: =AS27 -> 0.9 | AT28: =AT27 -> 146 | AU28: =AU27 -> 1.1 | AV28: =AV27 -> 110 | AW28: 2.9 | AX28: =AX27 -> 130 | AY28: =AS28*AT28 -> 131.4 | AZ28: =AU28*AV28 -> 121 | BA28: =AW28*AX28 -> 377 | BB28: =AY28-AY27 -> 0 | BC28: =AZ28-AZ27 -> 0 | BD28: =BA28-BA27 -> 0 | BE28: =SUM(BB28:BD28) -> 0 | BF28: =SUM(I28-BE28) -> 0 | BG28: =SUM(I28-BF28) -> 0
A29: =ELEC!C26 -> 44251 | B29: =B28 -> 109443 | C29: =B29-B28 -> 0 | D29: =C29/27 -> 0 | E29: =SUM((C29*$E$4)+(7500/'EDl log'!$A$34)) -> 267.85714 | G29: =G28 -> 615374 | H29: =G29-G28 -> 0 | I29: =C29+H29 -> 0 | J29: =IF(I29>0,E29/I29,0) -> 0 | K29: ='Swimming Pool quality check '!H29 -> 6718 | L29: =K29-K28 -> 0 | M29: =M28 -> 457.44 | N29: =SUM(M29-M28) -> 0 | O29: =O28 -> 529.52 | P29: =SUM(O29-O28) -> 0 | Q29: =SUM(P29+N29) -> 0 | T29: =T28 -> 5165 | U29: =SUM(T29-T28) -> 0 | V29: =V28 -> 461 | W29: =+V29-V28 -> 0 | X29: =X28 -> 150077 | Y29: =SUM(X29-X28) -> 0 | Z29: =Z28 -> 98262 | AA29: =Z29-Z28 -> 0 | AB29: =AB28 -> 256 | AC29: =AC28 -> 731 | AD29: =AC29-AC28 -> 0 | AE29: =AE28 -> 227.8 | AF29: =AE29-AE28 -> 0 | AG29: =AG28 -> 2181.57 | AH29: =AG29-AG28 -> 0 | AI29: =AF29+AH29 -> 0 | AJ29: =+Z29-Z28 -> 0 | AK29: =SUM(Y29-L29) -> 0 | AL29: =SUM(AJ29-W29) -> 0 | AM29: ='General information '!D29 -> 0 | AN29: ='General information '!H29 -> 0 | AP29: ='General information '!J29 -> 0 | AR29: =A29 -> 44251 | AS29: =AS28 -> 0.9 | AT29: =AT28 -> 146 | AU29: =AU28 -> 1.1 | AV29: =AV28 -> 110 | AW29: 2.9 | AX29: =AX28 -> 130 | AY29: =AS29*AT29 -> 131.4 | AZ29: =AU29*AV29 -> 121 | BA29: =AW29*AX29 -> 377 | BB29: =AY29-AY28 -> 0 | BC29: =AZ29-AZ28 -> 0 | BD29: =BA29-BA28 -> 0 | BE29: =SUM(BB29:BD29) -> 0 | BF29: =SUM(I29-BE29) -> 0 | BG29: =SUM(I29-BF29) -> 0
A30: =ELEC!C27 -> 44252 | B30: =B29 -> 109443 | C30: =B30-B29 -> 0 | D30: =C30/27 -> 0 | E30: =SUM((C30*$E$4)+(7500/'EDl log'!$A$34)) -> 267.85714 | G30: =G29 -> 615374 | H30: =G30-G29 -> 0 | I30: =C30+H30 -> 0 | J30: =IF(I30>0,E30/I30,0) -> 0 | K30: ='Swimming Pool quality check '!H30 -> 6718 | L30: =K30-K29 -> 0 | M30: =M29 -> 457.44 | N30: =SUM(M30-M29) -> 0 | O30: =O29 -> 529.52 | P30: =SUM(O30-O29) -> 0 | Q30: =SUM(P30+N30) -> 0 | T30: =T29 -> 5165 | U30: =SUM(T30-T29) -> 0 | V30: =V29 -> 461 | W30: =+V30-V29 -> 0 | X30: =X29 -> 150077 | Y30: =SUM(X30-X29) -> 0 | Z30: =Z29 -> 98262 | AA30: =Z30-Z29 -> 0 | AB30: =AB29 -> 256 | AC30: =AC29 -> 731 | AD30: =AC30-AC29 -> 0 | AE30: =AE29 -> 227.8 | AF30: =AE30-AE29 -> 0 | AG30: =AG29 -> 2181.57 | AH30: =AG30-AG29 -> 0 | AI30: =AF30+AH30 -> 0 | AJ30: =+Z30-Z29 -> 0 | AK30: =SUM(Y30-L30) -> 0 | AL30: =SUM(AJ30-W30) -> 0 | AM30: ='General information '!D30 -> 0 | AN30: ='General information '!H30 -> 0 | AP30: ='General information '!J30 -> 0 | AR30: =A30 -> 44252 | AS30: =AS29 -> 0.9 | AT30: =AT29 -> 146 | AU30: =AU29 -> 1.1 | AV30: =AV29 -> 110 | AW30: 2.9 | AX30: =AX29 -> 130 | AY30: =AS30*AT30 -> 131.4 | AZ30: =AU30*AV30 -> 121 | BA30: =AW30*AX30 -> 377 | BB30: =AY30-AY29 -> 0 | BC30: =AZ30-AZ29 -> 0 | BD30: =BA30-BA29 -> 0 | BE30: =SUM(BB30:BD30) -> 0 | BF30: =SUM(I30-BE30) -> 0 | BG30: =SUM(I30-BF30) -> 0
A31: =ELEC!C28 -> 44253 | B31: =B30 -> 109443 | C31: =B31-B30 -> 0 | D31: =C31/27 -> 0 | E31: =SUM((C31*$E$4)+(7500/'EDl log'!$A$34)) -> 267.85714 | G31: =G30 -> 615374 | H31: =G31-G30 -> 0 | I31: =C31+H31 -> 0 | J31: =IF(I31>0,E31/I31,0) -> 0 | K31: ='Swimming Pool quality check '!H31 -> 6718 | L31: =K31-K30 -> 0 | M31: =M30 -> 457.44 | N31: =SUM(M31-M30) -> 0 | O31: =O30 -> 529.52 | P31: =SUM(O31-O30) -> 0 | Q31: =SUM(P31+N31) -> 0 | T31: =T30 -> 5165 | U31: =SUM(T31-T30) -> 0 | V31: =V30 -> 461 | W31: =+V31-V30 -> 0 | X31: =X30 -> 150077 | Y31: =SUM(X31-X30) -> 0 | Z31: =Z30 -> 98262 | AA31: =Z31-Z30 -> 0 | AB31: =AB30 -> 256 | AC31: =AC30 -> 731 | AD31: =AC31-AC30 -> 0 | AE31: =AE30 -> 227.8 | AF31: =AE31-AE30 -> 0 | AG31: =AG30 -> 2181.57 | AH31: =AG31-AG30 -> 0 | AI31: =AF31+AH31 -> 0 | AJ31: =+Z31-Z30 -> 0 | AK31: =SUM(Y31-L31) -> 0 | AL31: =SUM(AJ31-W31) -> 0 | AM31: ='General information '!D31 -> 0 | AN31: ='General information '!H31 -> 0 | AP31: ='General information '!J31 -> 0 | AR31: =A31 -> 44253 | AS31: =AS30 -> 0.9 | AT31: =AT30 -> 146 | AU31: =AU30 -> 1.1 | AV31: =AV30 -> 110 | AW31: 2.9 | AX31: =AX30 -> 130 | AY31: =AS31*AT31 -> 131.4 | AZ31: =AU31*AV31 -> 121 | BA31: =AW31*AX31 -> 377 | BB31: =AY31-AY30 -> 0 | BC31: =AZ31-AZ30 -> 0 | BD31: =BA31-BA30 -> 0 | BE31: =SUM(BB31:BD31) -> 0 | BF31: =SUM(I31-BE31) -> 0 | BG31: =SUM(I31-BF31) -> 0
A32: =ELEC!C29 -> 44254 | B32: =B31 -> 109443 | C32: =B32-B31 -> 0 | D32: =C32/27 -> 0 | E32: =SUM((C32*$E$4)+(7500/'EDl log'!$A$34)) -> 267.85714 | G32: =G31 -> 615374 | H32: =G32-G31 -> 0 | I32: =C32+H32 -> 0 | J32: =IF(I32>0,E32/I32,0) -> 0 | K32: ='Swimming Pool quality check '!H32 -> 6718 | L32: =K32-K31 -> 0 | M32: =M31 -> 457.44 | N32: =SUM(M32-M31) -> 0 | O32: =O31 -> 529.52 | P32: =SUM(O32-O31) -> 0 | Q32: =SUM(P32+N32) -> 0 | T32: =T31 -> 5165 | U32: =SUM(T32-T31) -> 0 | V32: =V31 -> 461 | W32: =+V32-V31 -> 0 | X32: =X31 -> 150077 | Y32: =SUM(X32-X31) -> 0 | Z32: =Z31 -> 98262 | AA32: =Z32-Z31 -> 0 | AB32: =AB31 -> 256 | AC32: =AC31 -> 731 | AD32: =AC32-AC31 -> 0 | AE32: =AE31 -> 227.8 | AF32: =AE32-AE31 -> 0 | AG32: =AG31 -> 2181.57 | AH32: =AG32-AG31 -> 0 | AI32: =AF32+AH32 -> 0 | AJ32: =+Z32-Z31 -> 0 | AK32: =SUM(Y32-L32) -> 0 | AL32: =SUM(AJ32-W32) -> 0 | AM32: ='General information '!D32 -> 0 | AN32: ='General information '!H32 -> 0 | AP32: ='General information '!J32 -> 0 | AR32: =A32 -> 44254 | AS32: =AS31 -> 0.9 | AT32: =AT31 -> 146 | AU32: =AU31 -> 1.1 | AV32: =AV31 -> 110 | AW32: 2.9 | AX32: =AX31 -> 130 | AY32: =AS32*AT32 -> 131.4 | AZ32: =AU32*AV32 -> 121 | BA32: =AW32*AX32 -> 377 | BB32: =AY32-AY31 -> 0 | BC32: =AZ32-AZ31 -> 0 | BD32: =BA32-BA31 -> 0 | BE32: =SUM(BB32:BD32) -> 0 | BF32: =SUM(I32-BE32) -> 0 | BG32: =SUM(I32-BF32) -> 0
A33: =ELEC!C30 -> 44255 | B33: =B32 -> 109443 | C33: =B33-B32 -> 0 | D33: =C33/27 -> 0 | E33: =SUM((C33*$E$4)+(7500/'EDl log'!$A$34)) -> 267.85714 | G33: =G32 -> 615374 | H33: =G33-G32 -> 0 | I33: =C33+H33 -> 0 | J33: =IF(I33>0,E33/I33,0) -> 0 | K33: ='Swimming Pool quality check '!H33 -> 6718 | L33: =K33-K32 -> 0 | M33: =M32 -> 457.44 | N33: =SUM(M33-M32) -> 0 | O33: =O32 -> 529.52 | P33: =SUM(O33-O32) -> 0 | Q33: =SUM(P33+N33) -> 0 | T33: =T32 -> 5165 | U33: =SUM(T33-T32) -> 0 | V33: =V32 -> 461 | W33: =+V33-V32 -> 0 | X33: =X32 -> 150077 | Y33: =SUM(X33-X32) -> 0 | Z33: =Z32 -> 98262 | AA33: =Z33-Z32 -> 0 | AB33: =AB32 -> 256 | AC33: =AC32 -> 731 | AD33: =AC33-AC32 -> 0 | AE33: =AE32 -> 227.8 | AF33: =AE33-AE32 -> 0 | AG33: =AG32 -> 2181.57 | AH33: =AG33-AG32 -> 0 | AI33: =AF33+AH33 -> 0 | AJ33: =+Z33-Z32 -> 0 | AK33: =SUM(Y33-L33) -> 0 | AL33: =SUM(AJ33-W33) -> 0 | AM33: ='General information '!D33 -> 0 | AN33: ='General information '!H33 -> 0 | AP33: ='General information '!J33 -> 0 | AR33: =A33 -> 44255 | AS33: =AS32 -> 0.9 | AT33: =AT32 -> 146 | AU33: =AU32 -> 1.1 | AV33: =AV32 -> 110 | AW33: 2.9 | AX33: =AX32 -> 130 | AY33: =AS33*AT33 -> 131.4 | AZ33: =AU33*AV33 -> 121 | BA33: =AW33*AX33 -> 377 | BB33: =AY33-AY32 -> 0 | BC33: =AZ33-AZ32 -> 0 | BD33: =BA33-BA32 -> 0 | BE33: =SUM(BB33:BD33) -> 0 | BF33: =SUM(I33-BE33) -> 0 | BG33: =SUM(I33-BF33) -> 0
C34: =SUM(C6:C33) -> 0 | D34: =SUM(D6:D33) -> 0 | F34: =SUM(F6:F33) -> 0 | H34: =SUM(H6:H33) -> 0 | I34: =SUM(I6:I33) -> 0 | L34: =SUM(L7:L33) -> 2 | Q34: =SUM(Q5:Q33) -> 0 | U34: =SUM(U6:U33) -> 1 | Y34: =SUM(#REF!,Y33,Y31,Y29,Y27,Y25,Y23,Y21,Y19,Y17,Y15,Y13,Y11,Y9,Y7,#REF!) -> #REF! | AJ34: =SUM(AJ6:AJ33) -> 0 | AK34: =SUM(Y34-L34) -> #REF! | AL34: =SUM(AL6:AL33) -> -1
C35: =+C34*1.66 -> 0 | E35: =SUM(E6:E33) -> 7474.0783 | F35: =SUM(F6:F33) -> 0 | H35: 7500 | I35: =SUM('General information '!G34/WATER!I34) -> #DIV/0! | O35: =SUM(Q34+I34) -> 0 | Z35: =SUM(Y34:AJ34) -> #REF! | AK35: =SUM(Y35-L35) -> 0
B36: =9*27 -> 243 | D36: =SUM(D6:D33) -> 0 | F36: =SUM(F6:F33) -> 0 | G36: =SUM(I34) -> 0 | H36: =SUM(H35+C35) -> 7500 | K36: =SUM(H36/G36) -> #DIV/0! | AJ36: =SUM(C35-AK35) -> 0 | AM36: =SUM(AJ36/AO35) -> #DIV/0!

Sheet graphic

Sheet General information 
A1: GENERAL & HOTEL'S INFORMATION SHEET
B4: Max Temp | C4: MIN TEMP | D4: AVE TEMP | E4: AVE Humidity | F4: AVE OCC | G4: # of OCC Rooms | H4: Ball room | I4: Meeting rooms | J4: Outlets | K4: Total covers | L4: # of permenant Emp | M4: # of casuals | N4: Total # of EMP | O4: # of EMP/OCC Room
A5: =ELEC!C2 -> 44227 | B5: 19 | C5: 14 | D5: ='[1]General information '!D36 -> 18 | E5: ='[1]General information '!E36 -> 0.55 | F5: ='[1]General information '!F36 -> 0 | G5: ='[1]General information '!G36 -> 0 | H5: ='[1]General information '!H36 -> 0 | I5: ='[1]General information '!I36 -> 0 | J5: ='[1]General information '!J36 -> 0 | K5: ='[1]General information '!K36 -> 0 | ... O5: ='[1]General information '!O36 -> 0
A6: =ELEC!C3 -> 44228 | B6: 21 | C6: 16 | D6: =(C6+B6)/2 -> 18.5 | E6: 0.65 | F6: 0 | G6: =F6*230 -> 0 | H6: 0 | I6: 0 | J6: 0 | K6: =+J6+H6 -> 0
A7: =ELEC!C4 -> 44229 | B7: 23 | C7: 17 | D7: =(C7+B7)/2 -> 20 | E7: 0.56 | F7: 0 | G7: =F7*230 -> 0 | H7: 0 | I7: 0 | J7: 0 | K7: =+J7+H7 -> 0
A8: =ELEC!C5 -> 44230 | B8: 20 | C8: 15 | D8: =(C8+B8)/2 -> 17.5 | E8: 0.69 | F8: 0 | G8: =F8*230 -> 0 | H8: 0 | I8: 0 | J8: 0 | K8: =+J8+H8 -> 0
A9: =ELEC!C6 -> 44231 | B9: 20 | C9: 15 | D9: =(C9+B9)/2 -> 17.5 | E9: 0.73 | F9: 0 | G9: =F9*230 -> 0 | H9: 0 | I9: 0 | J9: 0 | K9: =+J9+H9 -> 0
A10: =ELEC!C7 -> 44232 | B10: 20 | C10: 15 | D10: =(C10+B10)/2 -> 17.5 | E10: 0.6 | F10: 0 | G10: =F10*230 -> 0 | H10: 0 | I10: 0 | J10: 0 | K10: =+J10+H10 -> 0
A11: =ELEC!C8 -> 44233 | B11: 19 | C11: 15 | D11: =(C11+B11)/2 -> 17 | E11: 0.7 | F11: 0 | G11: =F11*230 -> 0 | H11: 0 | I11: 0 | J11: 0 | K11: =+J11+H11 -> 0
A12: =ELEC!C9 -> 44234 | B12: 21 | C12: 17 | D12: =(C12+B12)/2 -> 19 | E12: 0.63 | F12: 0 | G12: =F12*230 -> 0 | H12: 0 | I12: 0 | J12: 0 | K12: =+J12+H12 -> 0
A13: =ELEC!C10 -> 44235 | B13: 23 | C13: 19 | D13: =(C13+B13)/2 -> 21 | E13: 0.55 | F13: 0 | G13: =F13*230 -> 0 | H13: 0 | I13: 0 | J13: 0 | K13: =+J13+H13 -> 0
A14: =ELEC!C11 -> 44236 | B14: 21 | C14: 18 | D14: =(C14+B14)/2 -> 19.5 | E14: 0.63 | F14: 0 | G14: =F14*230 -> 0 | H14: 0 | I14: 0 | J14: 0 | K14: =+J14+H14 -> 0
A15: =ELEC!C12 -> 44237 | B15: 19 | C15: 14 | D15: =(C15+B15)/2 -> 16.5 | E15: 0.61 | F15: 0 | G15: =F15*230 -> 0 | H15: 0 | I15: 0 | J15: 0 | K15: =+J15+H15 -> 0
A16: =ELEC!C13 -> 44238 | B16: 18 | C16: 13 | D16: =(C16+B16)/2 -> 15.5 | E16: 0.72 | F16: 0 | G16: =F16*230 -> 0 | H16: 0 | I16: 0 | J16: 0 | K16: =+J16+H16 -> 0
A17: =ELEC!C14 -> 44239 | B17: 18 | C17: 13 | D17: =(C17+B17)/2 -> 15.5 | E17: 0.51 | F17: 0 | G17: =F17*230 -> 0 | H17: 0 | I17: 0 | J17: 0 | K17: =+J17+H17 -> 0
A18: =ELEC!C15 -> 44240 | D18: =(C18+B18)/2 -> 0 | G18: =F18*230 -> 0 | H18: 0 | I18: 0 | J18: 0 | K18: =+J18+H18 -> 0
A19: =ELEC!C16 -> 44241 | D19: =(C19+B19)/2 -> 0 | G19: =F19*230 -> 0 | H19: 0 | I19: 0 | J19: 0 | K19: =+J19+H19 -> 0
A20: =ELEC!C17 -> 44242 | D20: =(C20+B20)/2 -> 0 | G20: =F20*230 -> 0 | H20: 0 | I20: 0 | J20: 0 | K20: =+J20+H20 -> 0
A21: =ELEC!C18 -> 44243 | D21: =(C21+B21)/2 -> 0 | G21: =F21*230 -> 0 | H21: 0 | I21: 0 | J21: 0 | K21: =+J21+H21 -> 0
A22: =ELEC!C19 -> 44244 | D22: =(C22+B22)/2 -> 0 | G22: =F22*230 -> 0 | H22: 0 | I22: 0 | J22: 0 | K22: =+J22+H22 -> 0
A23: =ELEC!C20 -> 44245 | D23: =(C23+B23)/2 -> 0 | G23: =F23*230 -> 0 | H23: 0 | I23: 0 | J23: 0 | K23: =+J23+H23 -> 0
A24: =ELEC!C21 -> 44246 | D24: =(C24+B24)/2 -> 0 | G24: =F24*230 -> 0 | H24: 0 | I24: 0 | J24: 0 | K24: =+J24+H24 -> 0
A25: =ELEC!C22 -> 44247 | D25: =(C25+B25)/2 -> 0 | G25: =F25*230 -> 0 | H25: 0 | I25: 0 | J25: 0 | K25: =+J25+H25 -> 0
A26: =ELEC!C23 -> 44248 | D26: =(C26+B26)/2 -> 0 | G26: =F26*230 -> 0 | H26: 0 | I26: 0 | J26: 0 | K26: =+J26+H26 -> 0
A27: =ELEC!C24 -> 44249 | D27: =(C27+B27)/2 -> 0 | G27: =F27*230 -> 0 | H27: 0 | I27: 0 | J27: 0 | K27: =+J27+H27+I27 -> 0
A28: =ELEC!C25 -> 44250 | D28: =(C28+B28)/2 -> 0 | G28: =F28*230 -> 0 | H28: 0 | I28: 0 | J28: 0 | K28: =+J28+H28+I28 -> 0
A29: =ELEC!C26 -> 44251 | D29: =(C29+B29)/2 -> 0 | G29: =F29*230 -> 0 | H29: 0 | I29: 0 | J29: 0 | K29: =+J29+H29+I29 -> 0
A30: =ELEC!C27 -> 44252 | D30: =(C30+B30)/2 -> 0 | G30: =F30*230 -> 0 | H30: 0 | I30: 0 | J30: 0 | K30: =+J30+H30+I30 -> 0
A31: =ELEC!C28 -> 44253 | D31: =(C31+B31)/2 -> 0 | G31: =F31*230 -> 0 | H31: 0 | I31: 0 | J31: 0 | K31: =+J31+H31+I31 -> 0
A32: =ELEC!C29 -> 44254 | D32: =(C32+B32)/2 -> 0 | G32: =F32*230 -> 0 | H32: 0 | I32: 0 | J32: 0 | K32: =+J32+H32+I32 -> 0
A33: =ELEC!C30 -> 44255 | D33: =(C33+B33)/2 -> 0 | G33: =F33*230 -> 0 | H33: 0 | I33: 0 | J33: 0 | K33: =+J33+H33+I33 -> 0
F34: =AVERAGE(F6:F33) -> 0 | G34: =SUM(G6:G33) -> 0
D35: =SUM(D6:D33)/'EDl log'!A32 -> 17.916667
I38: http://www.accuweather.com/en/lb/lebanon-weather

Sheet tanks
B2: Tank 1 | D2: Tank 2 | F2: Tank 3 | H2: Tank 4 | J2: Tank 5 | L2: Tank 6 | N2: Tank 7 | P2: Tank 8 | R2: Tank 9 | T2: Tank 10 | V2: Tank 11 | Z2: Tank 1 | AB2: Tank 2 | AD2: Tank 3 | AF2: Tank 4 | AH2: Tank 5 | AJ2: Tank 6 | AL2: Tank 7
B3: 6670 | D3: =SUM(B3) -> 6670 | F3: =SUM(D3) -> 6670 | H3: =SUM(F3) -> 6670 | J3: =SUM(H3) -> 6670 | L3: =SUM(J3) -> 6670 | N3: =SUM(L3) -> 6670 | P3: =SUM(N3) -> 6670 | R3: =SUM(P3) -> 6670 | T3: =SUM(R3) -> 6670 | V3: =SUM(T3) -> 6670 | W3: =SUM(B3:V3) -> 73370 | Z3: 2800 | AB3: 2800 | AD3: 2800 | AF3: 2800 | AH3: 2800 | AJ3: 2800 | AL3: 2800 | AM3: =SUM(Z3:AL3) -> 19600 | AO3: =SUM(AM3+W3) -> 92970 | AR3: Total sotck | AS3: Diesel Cons Per day | AT3: Diesel Delivery | BE3: Genset Co | BF3: Steam | BG3: Boil | BH3: Outdoor temperature
B4: =B3/310 -> 21.516129 | D4: =SUM(B4) -> 21.516129 | F4: =SUM(D4) -> 21.516129 | H4: =SUM(F4) -> 21.516129 | J4: =SUM(H4) -> 21.516129 | L4: =SUM(J4) -> 21.516129 | N4: =SUM(L4) -> 21.516129 | P4: =SUM(N4) -> 21.516129 | R4: =SUM(P4) -> 21.516129 | T4: =SUM(R4) -> 21.516129 | V4: =SUM(T4) -> 21.516129 | Z4: =Z3/280 -> 10 | AA4: =AA3/280 -> 0 | AB4: =AB3/280 -> 10 | AC4: =AC3/280 -> 0 | AD4: =AD3/280 -> 10 | AE4: =AE3/280 -> 0 | AF4: =AF3/280 -> 10 | AG4: =AG3/280 -> 0 | ... AL4: =AL3/280 -> 10 | AT4: Delivery | AU4: Cost /L | AW4: Boiler+Steam | AX4: Generator | AZ4: Occupancy | BA4: AVE TEPM | BB4: AVE Humidity
A5: =ELEC!C2 -> 44227 | B5: =[2]tanks!B36 -> 236 | C5: =[2]tanks!C36 -> 5077.8065 | D5: =[2]tanks!D36 -> 236 | E5: =[2]tanks!E36 -> 5077.8065 | F5: =[2]tanks!F36 -> 236 | G5: =[2]tanks!G36 -> 5077.8065 | H5: =[2]tanks!H36 -> 236 | I5: =[2]tanks!I36 -> 5077.8065 | ... AO5: =[2]tanks!AO36 -> 16940 | AP5: =[1]tanks!AP36 -> 0 | AQ5: =[2]tanks!AQ36 -> 0.78300388 | AR5: =[2]tanks!AR36 -> 72795.871 | AS5: =[2]tanks!AS36 -> -920.03226 | AT5: =[2]tanks!AT36 -> 0 | AU5: =[2]tanks!AU36 -> 0 | AV5: =[2]tanks!AV36 -> 0.67 | AW5: =[2]tanks!AW36 -> -267 | AX5: =[2]tanks!AX36 -> -653.03226 | ... BB5: =[2]tanks!BB36 -> 0.56 | BC5: =[1]tanks!BC36 -> 0 | BD5: =[1]tanks!BD36 -> 19222 | BE5: =[1]tanks!BE36 -> #REF! | BF5: =[1]tanks!BF36 -> 0 | BG5: =[1]tanks!BG36 -> #REF! | BH5: =[4]tanks!BH36 -> 0
A6: =ELEC!C3 -> 44228 | B6: ='B5'!B5 -> 232 | C6: =B6*$B$4 -> 4991.7419 | D6: =SUM(B6) -> 232 | E6: =D6*$B$4 -> 4991.7419 | F6: =SUM(D6) -> 232 | G6: =F6*$B$4 -> 4991.7419 | H6: =SUM(F6) -> 232 | I6: =H6*$B$4 -> 4991.7419 | J6: =SUM(H6) -> 232 | K6: =J6*$B$4 -> 4991.7419 | L6: =SUM(J6) -> 232 | M6: =L6*$B$4 -> 4991.7419 | N6: =SUM(L6) -> 232 | O6: =N6*$B$4 -> 4991.7419 | P6: =SUM(N6) -> 232 | Q6: =P6*$B$4 -> 4991.7419 | R6: =SUM(P6) -> 232 | S6: =R6*$B$4 -> 4991.7419 | T6: =SUM(R6) -> 232 | U6: =T6*$B$4 -> 4991.7419 | V6: =SUM(T6) -> 232 | W6: =V6*$B$4 -> 4991.7419 | X6: =SUM(Y6/73370) -> 0.7483871 | Y6: =SUM(C6+E6+G6+I6+K6+M6+O6+Q6+S6+U6+W6) -> 54909.161 | Z6: ='B5'!C5 -> 238 | AA6: =SUM(Z6*$Z$4) -> 2380 | AB6: =SUM(Z6) -> 238 | AC6: =SUM(AB6*$Z$4) -> 2380 | AD6: =SUM(AB6) -> 238 | AE6: =SUM(AD6*$Z$4) -> 2380 | AF6: =SUM(AD6) -> 238 | AG6: =SUM(AF6*$Z$4) -> 2380 | AH6: =SUM(AF6) -> 238 | AI6: =SUM(AH6*$Z$4) -> 2380 | AJ6: =SUM(AH6) -> 238 | AK6: =SUM(AJ6*$Z$4) -> 2380 | AL6: =SUM(AJ6) -> 238 | AM6: =SUM(AL6*$Z$4) -> 2380 | AN6: =SUM(AO6/19600) -> 0.85 | AO6: =SUM(AA6+AC6+AE6+AG6+AI6+AK6+AM6) -> 16660 | AQ6: =SUM(AR6/92970) -> 0.7698092 | AR6: =SUM(AO6+Y6) -> 71569.161 | AS6: =SUM(AR6-AR5-AT6) -> -1226.8097 | AT6: 0.1 | AU6: 0.1 | AV6: =IF(AT6>0,AU6,AV5) -> 0.1 | AW6: =-SUM('B5'!AI5) -> -467.6 | AX6: =-SUM(AW6-AS6) -> -759.20968 | AY6: =SUM(AX6+AW6) -> -1226.8097 | AZ6: =ELEC!A3 -> 0 | BA6: ='General information '!D6 -> 18.5 | BB6: =SUM('General information '!E6) -> 0.65 | BC6: =IF(AR3>=AR6,0,1) -> 0 | BD6: 19222 | BE6: =(305/1185)*ELEC!Q4 -> 580.40084 | BG6: =#REF!-BE6 -> #REF! | BH6: 21
A7: =ELEC!C4 -> 44229 | B7: ='B5'!B6 -> 229 | C7: =B7*$B$4 -> 4927.1935 | D7: =SUM(B7) -> 229 | E7: =D7*$B$4 -> 4927.1935 | F7: =SUM(D7) -> 229 | G7: =F7*$B$4 -> 4927.1935 | H7: =SUM(F7) -> 229 | I7: =H7*$B$4 -> 4927.1935 | J7: =SUM(H7) -> 229 | K7: =J7*$B$4 -> 4927.1935 | L7: =SUM(J7) -> 229 | M7: =L7*$B$4 -> 4927.1935 | N7: =SUM(L7) -> 229 | O7: =N7*$B$4 -> 4927.1935 | P7: =SUM(N7) -> 229 | Q7: =P7*$B$4 -> 4927.1935 | R7: =SUM(P7) -> 229 | S7: =R7*$B$4 -> 4927.1935 | T7: =SUM(R7) -> 229 | U7: =T7*$B$4 -> 4927.1935 | V7: =SUM(T7) -> 229 | W7: =V7*$B$4 -> 4927.1935 | X7: =SUM(Y7/73370) -> 0.73870968 | Y7: =SUM(C7+E7+G7+I7+K7+M7+O7+Q7+S7+U7+W7) -> 54199.129 | Z7: ='B5'!C6 -> 235 | AA7: =SUM(Z7*$Z$4) -> 2350 | AB7: =SUM(Z7) -> 235 | AC7: =SUM(AB7*$Z$4) -> 2350 | AD7: =SUM(AB7) -> 235 | AE7: =SUM(AD7*$Z$4) -> 2350 | AF7: =SUM(AD7) -> 235 | AG7: =SUM(AF7*$Z$4) -> 2350 | AH7: =SUM(AF7) -> 235 | AI7: =SUM(AH7*$Z$4) -> 2350 | AJ7: =SUM(AH7) -> 235 | AK7: =SUM(AJ7*$Z$4) -> 2350 | AL7: =SUM(AJ7) -> 235 | AM7: =SUM(AL7*$Z$4) -> 2350 | AN7: =SUM(AO7/19600) -> 0.83928571 | AO7: =SUM(AA7+AC7+AE7+AG7+AI7+AK7+AM7) -> 16450 | AQ7: =SUM(AR7/92970) -> 0.75991319 | AR7: =SUM(AO7+Y7) -> 70649.129 | AS7: =SUM(AR7-AR6-AT7) -> -920.03226 | AV7: =IF(AT7>0,AU7,AV6) -> 0.1 | AW7: =-SUM('B5'!AI6) -> -234 | AX7: =-SUM(AW7-AS7) -> -686.03226 | AY7: =SUM(AX7+AW7) -> -920.03226 | AZ7: =ELEC!A4 -> 0 | BA7: ='General information '!D7 -> 20 | BB7: =SUM('General information '!E7) -> 0.56 | BC7: 0 | BD7: 19222 | BE7: =(305/1185)*ELEC!Q5 -> 751.81857 | BG7: =#REF!-BE7 -> #REF! | BH7: 19
A8: =ELEC!C5 -> 44230 | B8: ='B5'!B7 -> 225 | C8: =B8*$B$4 -> 4841.129 | D8: =SUM(B8) -> 225 | E8: =D8*$B$4 -> 4841.129 | F8: =SUM(D8) -> 225 | G8: =F8*$B$4 -> 4841.129 | H8: =SUM(F8) -> 225 | I8: =H8*$B$4 -> 4841.129 | J8: =SUM(H8) -> 225 | K8: =J8*$B$4 -> 4841.129 | L8: =SUM(J8) -> 225 | M8: =L8*$B$4 -> 4841.129 | N8: =SUM(L8) -> 225 | O8: =N8*$B$4 -> 4841.129 | P8: =SUM(N8) -> 225 | Q8: =P8*$B$4 -> 4841.129 | R8: =SUM(P8) -> 225 | S8: =R8*$B$4 -> 4841.129 | T8: =SUM(R8) -> 225 | U8: =T8*$B$4 -> 4841.129 | V8: =SUM(T8) -> 225 | W8: =V8*$B$4 -> 4841.129 | X8: =SUM(Y8/73370) -> 0.72580645 | Y8: =SUM(C8+E8+G8+I8+K8+M8+O8+Q8+S8+U8+W8) -> 53252.419 | Z8: ='B5'!C7 -> 231 | AA8: =SUM(Z8*$Z$4) -> 2310 | AB8: =SUM(Z8) -> 231 | AC8: =SUM(AB8*$Z$4) -> 2310 | AD8: =SUM(AB8) -> 231 | AE8: =SUM(AD8*$Z$4) -> 2310 | AF8: =SUM(AD8) -> 231 | AG8: =SUM(AF8*$Z$4) -> 2310 | AH8: =SUM(AF8) -> 231 | AI8: =SUM(AH8*$Z$4) -> 2310 | AJ8: =SUM(AH8) -> 231 | AK8: =SUM(AJ8*$Z$4) -> 2310 | AL8: =SUM(AJ8) -> 231 | AM8: =SUM(AL8*$Z$4) -> 2310 | AN8: =SUM(AO8/19600) -> 0.825 | AO8: =SUM(AA8+AC8+AE8+AG8+AI8+AK8+AM8) -> 16170 | AQ8: =SUM(AR8/92970) -> 0.7467185 | AR8: =SUM(AO8+Y8) -> 69422.419 | AS8: =SUM(AR8-AR7-AT8) -> -1226.7097 | AV8: =IF(AT8>0,AU8,AV7) -> 0.1 | AW8: =-SUM('B5'!AI7) -> -289 | AX8: =-SUM(AW8-AS8) -> -937.70968 | AY8: =SUM(AX8+AW8) -> -1226.7097 | AZ8: =ELEC!A5 -> 0 | BA8: ='General information '!D8 -> 17.5 | BB8: =SUM('General information '!E8) -> 0.69 | BC8: =IF(AR7>=AR8,0,1) -> 0 | BD8: 19222 | BE8: =(305/1185)*ELEC!Q6 -> 675.37553 | BG8: =#REF!-BE8 -> #REF! | BH8: 16
A9: =ELEC!C6 -> 44231 | B9: ='B5'!B8 -> 221 | C9: =B9*$B$4 -> 4755.0645 | D9: =SUM(B9) -> 221 | E9: =D9*$B$4 -> 4755.0645 | F9: =SUM(D9) -> 221 | G9: =F9*$B$4 -> 4755.0645 | H9: =SUM(F9) -> 221 | I9: =H9*$B$4 -> 4755.0645 | J9: =SUM(H9) -> 221 | K9: =J9*$B$4 -> 4755.0645 | L9: =SUM(J9) -> 221 | M9: =L9*$B$4 -> 4755.0645 | N9: =SUM(L9) -> 221 | O9: =N9*$B$4 -> 4755.0645 | P9: =SUM(N9) -> 221 | Q9: =P9*$B$4 -> 4755.0645 | R9: =SUM(P9) -> 221 | S9: =R9*$B$4 -> 4755.0645 | T9: =SUM(R9) -> 221 | U9: =T9*$B$4 -> 4755.0645 | V9: =SUM(T9) -> 221 | W9: =V9*$B$4 -> 4755.0645 | X9: =SUM(Y9/73370) -> 0.71290323 | Y9: =SUM(C9+E9+G9+I9+K9+M9+O9+Q9+S9+U9+W9) -> 52305.71 | Z9: ='B5'!C8 -> 227 | AA9: =SUM(Z9*$Z$4) -> 2270 | AB9: =SUM(Z9) -> 227 | AC9: =SUM(AB9*$Z$4) -> 2270 | AD9: =SUM(AB9) -> 227 | AE9: =SUM(AD9*$Z$4) -> 2270 | AF9: =SUM(AD9) -> 227 | AG9: =SUM(AF9*$Z$4) -> 2270 | AH9: =SUM(AF9) -> 227 | AI9: =SUM(AH9*$Z$4) -> 2270 | AJ9: =SUM(AH9) -> 227 | AK9: =SUM(AJ9*$Z$4) -> 2270 | AL9: =SUM(AJ9) -> 227 | AM9: =SUM(AL9*$Z$4) -> 2270 | AN9: =SUM(AO9/19600) -> 0.81071429 | AO9: =SUM(AA9+AC9+AE9+AG9+AI9+AK9+AM9) -> 15890 | AQ9: =SUM(AR9/92970) -> 0.73352382 | AR9: =SUM(AO9+Y9) -> 68195.71 | AS9: =SUM(AR9-AR8-AT9) -> -1226.7097 | AV9: =IF(AT9>0,AU9,AV8) -> 0.1 | AW9: =-SUM('B5'!AI8) -> -314 | AX9: =-SUM(AW9-AS9) -> -912.70968 | AY9: =SUM(AX9+AW9) -> -1226.7097 | AZ9: =ELEC!A6 -> 0 | BA9: ='General information '!D9 -> 17.5 | BB9: =SUM('General information '!E9) -> 0.73 | BC9: =IF(AR8>=AR9,0,1) -> 0 | BD9: 19222 | BE9: =(305/1185)*ELEC!Q7 -> 505.75949 | BG9: =#REF!-BE9 -> #REF! | BH9: 18
A10: =ELEC!C7 -> 44232 | B10: ='B5'!B9 -> 247 | C10: =B10*$B$4 -> 5314.4839 | D10: =SUM(B10) -> 247 | E10: =D10*$B$4 -> 5314.4839 | F10: =SUM(D10) -> 247 | G10: =F10*$B$4 -> 5314.4839 | H10: =SUM(F10) -> 247 | I10: =H10*$B$4 -> 5314.4839 | J10: =SUM(H10) -> 247 | K10: =J10*$B$4 -> 5314.4839 | L10: =SUM(J10) -> 247 | M10: =L10*$B$4 -> 5314.4839 | N10: =SUM(L10) -> 247 | O10: =N10*$B$4 -> 5314.4839 | P10: =SUM(N10) -> 247 | Q10: =P10*$B$4 -> 5314.4839 | R10: =SUM(P10) -> 247 | S10: =R10*$B$4 -> 5314.4839 | T10: =SUM(R10) -> 247 | U10: =T10*$B$4 -> 5314.4839 | V10: =SUM(T10) -> 247 | W10: =V10*$B$4 -> 5314.4839 | X10: =SUM(Y10/73370) -> 0.79677419 | Y10: =SUM(C10+E10+G10+I10+K10+M10+O10+Q10+S10+U10+W10) -> 58459.323 | Z10: ='B5'!C9 -> 252 | AA10: =SUM(Z10*$Z$4) -> 2520 | AB10: =SUM(Z10) -> 252 | AC10: =SUM(AB10*$Z$4) -> 2520 | AD10: =SUM(AB10) -> 252 | AE10: =SUM(AD10*$Z$4) -> 2520 | AF10: =SUM(AD10) -> 252 | AG10: =SUM(AF10*$Z$4) -> 2520 | AH10: =SUM(AF10) -> 252 | AI10: =SUM(AH10*$Z$4) -> 2520 | AJ10: =SUM(AH10) -> 252 | AK10: =SUM(AJ10*$Z$4) -> 2520 | AL10: =SUM(AJ10) -> 252 | AM10: =SUM(AL10*$Z$4) -> 2520 | AN10: =SUM(AO10/19600) -> 0.9 | AO10: =SUM(AA10+AC10+AE10+AG10+AI10+AK10+AM10) -> 17640 | AQ10: =SUM(AR10/92970) -> 0.81853633 | AR10: =SUM(AO10+Y10) -> 76099.323 | AS10: =SUM(AR10-AR9-AT10) -> 53.612903 | AT10: 7850 | AU10: 0.674 | AV10: =IF(AT10>0,AU10,AV9) -> 0.674 | AW10: =-SUM('B5'!AI9) -> -391 | AX10: =-SUM(AW10-AS10) -> 444.6129 | AY10: =SUM(AX10+AW10) -> 53.612903 | AZ10: =ELEC!A7 -> 0 | BA10: ='General information '!D10 -> 17.5 | BB10: =SUM('General information '!E10) -> 0.6 | BC10: =IF(AR9>=AR10,0,1) -> 1 | BD10: 19222 | BE10: =(305/1185)*ELEC!Q8 -> 436.00844 | BG10: =#REF!-BE10 -> #REF! | BH10: 16
A11: =ELEC!C8 -> 44233 | B11: ='B5'!B10 -> 244 | C11: =B11*$B$4 -> 5249.9355 | D11: =SUM(B11) -> 244 | E11: =D11*$B$4 -> 5249.9355 | F11: =SUM(D11) -> 244 | G11: =F11*$B$4 -> 5249.9355 | H11: =SUM(F11) -> 244 | I11: =H11*$B$4 -> 5249.9355 | J11: =SUM(H11) -> 244 | K11: =J11*$B$4 -> 5249.9355 | L11: =SUM(J11) -> 244 | M11: =L11*$B$4 -> 5249.9355 | N11: =SUM(L11) -> 244 | O11: =N11*$B$4 -> 5249.9355 | P11: =SUM(N11) -> 244 | Q11: =P11*$B$4 -> 5249.9355 | R11: =SUM(P11) -> 244 | S11: =R11*$B$4 -> 5249.9355 | T11: =SUM(R11) -> 244 | U11: =T11*$B$4 -> 5249.9355 | V11: =SUM(T11) -> 244 | W11: =V11*$B$4 -> 5249.9355 | X11: =SUM(Y11/73370) -> 0.78709677 | Y11: =SUM(C11+E11+G11+I11+K11+M11+O11+Q11+S11+U11+W11) -> 57749.29 | Z11: ='B5'!C10 -> 250 | AA11: =SUM(Z11*$Z$4) -> 2500 | AB11: =SUM(Z11) -> 250 | AC11: =SUM(AB11*$Z$4) -> 2500 | AD11: =SUM(AB11) -> 250 | AE11: =SUM(AD11*$Z$4) -> 2500 | AF11: =SUM(AD11) -> 250 | AG11: =SUM(AF11*$Z$4) -> 2500 | AH11: =SUM(AF11) -> 250 | AI11: =SUM(AH11*$Z$4) -> 2500 | AJ11: =SUM(AH11) -> 250 | AK11: =SUM(AJ11*$Z$4) -> 2500 | AL11: =SUM(AJ11) -> 250 | AM11: =SUM(AL11*$Z$4) -> 2500 | AN11: =SUM(AO11/19600) -> 0.89285714 | AO11: =SUM(AA11+AC11+AE11+AG11+AI11+AK11+AM11) -> 17500 | AQ11: =SUM(AR11/92970) -> 0.80939325 | AR11: =SUM(AO11+Y11) -> 75249.29 | AS11: =SUM(AR11-AR10-AT11) -> -850.03226 | AV11: =IF(AT11>0,AU11,AV10) -> 0.674 | AW11: =-SUM('B5'!AI10) -> -311 | AX11: =-SUM(AW11-AS11) -> -539.03226 | AY11: =SUM(AX11+AW11) -> -850.03226 | AZ11: =ELEC!A8 -> 0 | BA11: ='General information '!D11 -> 17 | BB11: =SUM('General information '!E11) -> 0.7 | BC11: =IF(AR10>=AR11,0,1) -> 0 | BD11: 19222 | BE11: =(305/1185)*ELEC!Q9 -> 526.09283 | BG11: =#REF!-BE11 -> #REF! | BH11: 16.5
A12: =ELEC!C9 -> 44234 | B12: ='B5'!B11 -> 240 | C12: =B12*$B$4 -> 5163.871 | D12: =SUM(B12) -> 240 | E12: =D12*$B$4 -> 5163.871 | F12: =SUM(D12) -> 240 | G12: =F12*$B$4 -> 5163.871 | H12: =SUM(F12) -> 240 | I12: =H12*$B$4 -> 5163.871 | J12: =SUM(H12) -> 240 | K12: =J12*$B$4 -> 5163.871 | L12: =SUM(J12) -> 240 | M12: =L12*$B$4 -> 5163.871 | N12: =SUM(L12) -> 240 | O12: =N12*$B$4 -> 5163.871 | P12: =SUM(N12) -> 240 | Q12: =P12*$B$4 -> 5163.871 | R12: =SUM(P12) -> 240 | S12: =R12*$B$4 -> 5163.871 | T12: =SUM(R12) -> 240 | U12: =T12*$B$4 -> 5163.871 | V12: =SUM(T12) -> 240 | W12: =V12*$B$4 -> 5163.871 | X12: =SUM(Y12/73370) -> 0.77419355 | Y12: =SUM(C12+E12+G12+I12+K12+M12+O12+Q12+S12+U12+W12) -> 56802.581 | Z12: ='B5'!C11 -> 246 | AA12: =SUM(Z12*$Z$4) -> 2460 | AB12: =SUM(Z12) -> 246 | AC12: =SUM(AB12*$Z$4) -> 2460 | AD12: =SUM(AB12) -> 246 | AE12: =SUM(AD12*$Z$4) -> 2460 | AF12: =SUM(AD12) -> 246 | AG12: =SUM(AF12*$Z$4) -> 2460 | AH12: =SUM(AF12) -> 246 | AI12: =SUM(AH12*$Z$4) -> 2460 | AJ12: =SUM(AH12) -> 246 | AK12: =SUM(AJ12*$Z$4) -> 2460 | AL12: =SUM(AJ12) -> 246 | AM12: =SUM(AL12*$Z$4) -> 2460 | AN12: =SUM(AO12/19600) -> 0.87857143 | AO12: =SUM(AA12+AC12+AE12+AG12+AI12+AK12+AM12) -> 17220 | AQ12: =SUM(AR12/92970) -> 0.79619857 | AR12: =SUM(AO12+Y12) -> 74022.581 | AS12: =SUM(AR12-AR11-AT12) -> -1226.7097 | AV12: =IF(AT12>0,AU12,AV11) -> 0.674 | AW12: =-SUM('B5'!AI11) -> -279 | AX12: =-SUM(AW12-AS12) -> -947.70968 | AY12: =SUM(AX12+AW12) -> -1226.7097 | AZ12: =ELEC!A9 -> 0 | BA12: ='General information '!D12 -> 19 | BB12: =SUM('General information '!E12) -> 0.63 | BC12: =IF(AR11>=AR12,0,1) -> 0 | BD12: 19222 | BE12: =(305/1185)*ELEC!Q10 -> 526.35021 | BG12: =#REF!-BE12 -> #REF! | BH12: 15.5
A13: =ELEC!C10 -> 44235 | B13: ='B5'!B12 -> 237 | C13: =B13*$B$4 -> 5099.3226 | D13: =SUM(B13) -> 237 | E13: =D13*$B$4 -> 5099.3226 | F13: =SUM(D13) -> 237 | G13: =F13*$B$4 -> 5099.3226 | H13: =SUM(F13) -> 237 | I13: =H13*$B$4 -> 5099.3226 | J13: =SUM(H13) -> 237 | K13: =J13*$B$4 -> 5099.3226 | L13: =SUM(J13) -> 237 | M13: =L13*$B$4 -> 5099.3226 | N13: =SUM(L13) -> 237 | O13: =N13*$B$4 -> 5099.3226 | P13: =SUM(N13) -> 237 | Q13: =P13*$B$4 -> 5099.3226 | R13: =SUM(P13) -> 237 | S13: =R13*$B$4 -> 5099.3226 | T13: =SUM(R13) -> 237 | U13: =T13*$B$4 -> 5099.3226 | V13: =SUM(T13) -> 237 | W13: =V13*$B$4 -> 5099.3226 | X13: =SUM(Y13/73370) -> 0.76451613 | Y13: =SUM(C13+E13+G13+I13+K13+M13+O13+Q13+S13+U13+W13) -> 56092.548 | Z13: ='B5'!C12 -> 243 | AA13: =SUM(Z13*$Z$4) -> 2430 | AB13: =SUM(Z13) -> 243 | AC13: =SUM(AB13*$Z$4) -> 2430 | AD13: =SUM(AB13) -> 243 | AE13: =SUM(AD13*$Z$4) -> 2430 | AF13: =SUM(AD13) -> 243 | AG13: =SUM(AF13*$Z$4) -> 2430 | AH13: =SUM(AF13) -> 243 | AI13: =SUM(AH13*$Z$4) -> 2430 | AJ13: =SUM(AH13) -> 243 | AK13: =SUM(AJ13*$Z$4) -> 2430 | AL13: =SUM(AJ13) -> 243 | AM13: =SUM(AL13*$Z$4) -> 2430 | AN13: =SUM(AO13/19600) -> 0.86785714 | AO13: =SUM(AA13+AC13+AE13+AG13+AI13+AK13+AM13) -> 17010 | AQ13: =SUM(AR13/92970) -> 0.78630255 | AR13: =SUM(AO13+Y13) -> 73102.548 | AS13: =SUM(AR13-AR12-AT13) -> -920.03226 | AV13: =IF(AT13>0,AU13,AV12) -> 0.674 | AW13: =-SUM('B5'!AI12) -> -333.4 | AX13: =-SUM(AW13-AS13) -> -586.63226 | AY13: =SUM(AX13+AW13) -> -920.03226 | AZ13: =ELEC!A10 -> 0 | BA13: ='General information '!D13 -> 21 | BB13: =SUM('General information '!E13) -> 0.55 | BC13: =IF(AR12>=AR13,0,1) -> 0 | BD13: 19222 | BE13: =(305/1185)*ELEC!Q11 -> 884.37131 | BG13: =#REF!-BE13 -> #REF!
A14: =ELEC!C11 -> 44236 | B14: ='B5'!B13 -> 233 | C14: =B14*$B$4 -> 5013.2581 | D14: =SUM(B14) -> 233 | E14: =D14*$B$4 -> 5013.2581 | F14: =SUM(D14) -> 233 | G14: =F14*$B$4 -> 5013.2581 | H14: =SUM(F14) -> 233 | I14: =H14*$B$4 -> 5013.2581 | J14: =SUM(H14) -> 233 | K14: =J14*$B$4 -> 5013.2581 | L14: =SUM(J14) -> 233 | M14: =L14*$B$4 -> 5013.2581 | N14: =SUM(L14) -> 233 | O14: =N14*$B$4 -> 5013.2581 | P14: =SUM(N14) -> 233 | Q14: =P14*$B$4 -> 5013.2581 | R14: =SUM(P14) -> 233 | S14: =R14*$B$4 -> 5013.2581 | T14: =SUM(R14) -> 233 | U14: =T14*$B$4 -> 5013.2581 | V14: =SUM(T14) -> 233 | W14: =V14*$B$4 -> 5013.2581 | X14: =SUM(Y14/73370) -> 0.7516129 | Y14: =SUM(C14+E14+G14+I14+K14+M14+O14+Q14+S14+U14+W14) -> 55145.839 | Z14: ='B5'!C13 -> 239 | AA14: =SUM(Z14*$Z$4) -> 2390 | AB14: =SUM(Z14) -> 239 | AC14: =SUM(AB14*$Z$4) -> 2390 | AD14: =SUM(AB14) -> 239 | AE14: =SUM(AD14*$Z$4) -> 2390 | AF14: =SUM(AD14) -> 239 | AG14: =SUM(AF14*$Z$4) -> 2390 | AH14: =SUM(AF14) -> 239 | AI14: =SUM(AH14*$Z$4) -> 2390 | AJ14: =SUM(AH14) -> 239 | AK14: =SUM(AJ14*$Z$4) -> 2390 | AL14: =SUM(AJ14) -> 239 | AM14: =SUM(AL14*$Z$4) -> 2390 | AN14: =SUM(AO14/19600) -> 0.85357143 | AO14: =SUM(AA14+AC14+AE14+AG14+AI14+AK14+AM14) -> 16730 | AQ14: =SUM(AR14/92970) -> 0.77310787 | AR14: =SUM(AO14+Y14) -> 71875.839 | AS14: =SUM(AR14-AR13-AT14) -> -1226.7097 | AV14: =IF(AT14>0,AU14,AV13) -> 0.674 | AW14: =-SUM('B5'!AI13) -> -236 | AX14: =-SUM(AW14-AS14) -> -990.70968 | AY14: =SUM(AX14+AW14) -> -1226.7097 | AZ14: =ELEC!A11 -> 0 | BA14: ='General information '!D14 -> 19.5 | BB14: =SUM('General information '!E14) -> 0.63 | BC14: =IF(AR13>=AR14,0,1) -> 0 | BD14: 19222 | BE14: =(305/1185)*ELEC!Q12 -> 1143.2996 | BG14: =#REF!-BE14 -> #REF!
A15: =ELEC!C12 -> 44237 | B15: ='B5'!B14 -> 227 | C15: =B15*$B$4 -> 4884.1613 | D15: =SUM(B15) -> 227 | E15: =D15*$B$4 -> 4884.1613 | F15: =SUM(D15) -> 227 | G15: =F15*$B$4 -> 4884.1613 | H15: =SUM(F15) -> 227 | I15: =H15*$B$4 -> 4884.1613 | J15: =SUM(H15) -> 227 | K15: =J15*$B$4 -> 4884.1613 | L15: =SUM(J15) -> 227 | M15: =L15*$B$4 -> 4884.1613 | N15: =SUM(L15) -> 227 | O15: =N15*$B$4 -> 4884.1613 | P15: =SUM(N15) -> 227 | Q15: =P15*$B$4 -> 4884.1613 | R15: =SUM(P15) -> 227 | S15: =R15*$B$4 -> 4884.1613 | T15: =SUM(R15) -> 227 | U15: =T15*$B$4 -> 4884.1613 | V15: =SUM(T15) -> 227 | W15: =V15*$B$4 -> 4884.1613 | X15: =SUM(Y15/73370) -> 0.73225806 | Y15: =SUM(C15+E15+G15+I15+K15+M15+O15+Q15+S15+U15+W15) -> 53725.774 | Z15: ='B5'!C14 -> 233 | AA15: =SUM(Z15*$Z$4) -> 2330 | AB15: =SUM(Z15) -> 233 | AC15: =SUM(AB15*$Z$4) -> 2330 | AD15: =SUM(AB15) -> 233 | AE15: =SUM(AD15*$Z$4) -> 2330 | AF15: =SUM(AD15) -> 233 | AG15: =SUM(AF15*$Z$4) -> 2330 | AH15: =SUM(AF15) -> 233 | AI15: =SUM(AH15*$Z$4) -> 2330 | AJ15: =SUM(AH15) -> 233 | AK15: =SUM(AJ15*$Z$4) -> 2330 | AL15: =SUM(AJ15) -> 233 | AM15: =SUM(AL15*$Z$4) -> 2330 | AN15: =SUM(AO15/19600) -> 0.83214286 | AO15: =SUM(AA15+AC15+AE15+AG15+AI15+AK15+AM15) -> 16310 | AQ15: =SUM(AR15/92970) -> 0.75331585 | AR15: =SUM(AO15+Y15) -> 70035.774 | AS15: =SUM(AR15-AR14-AT15) -> -1840.0645 | AV15: =IF(AT15>0,AU15,AV14) -> 0.674 | AW15: =-SUM('B5'!AI14) -> -236 | AX15: =-SUM(AW15-AS15) -> -1604.0645 | AY15: =SUM(AX15+AW15) -> -1840.0645 | AZ15: =ELEC!A12 -> 0 | BA15: ='General information '!D15 -> 16.5 | BB15: =SUM('General information '!E15) -> 0.61 | BC15: =IF(AR14>=AR15,0,1) -> 0 | BD15: 19222 | BE15: =(305/1185)*ELEC!Q13 -> 1029.2785 | BG15: =#REF!-BE15 -> #REF!
A16: =ELEC!C13 -> 44238 | B16: ='B5'!B15 -> 222 | C16: =B16*$B$4 -> 4776.5806 | D16: =SUM(B16) -> 222 | E16: =D16*$B$4 -> 4776.5806 | F16: =SUM(D16) -> 222 | G16: =F16*$B$4 -> 4776.5806 | H16: =SUM(F16) -> 222 | I16: =H16*$B$4 -> 4776.5806 | J16: =SUM(H16) -> 222 | K16: =J16*$B$4 -> 4776.5806 | L16: =SUM(J16) -> 222 | M16: =L16*$B$4 -> 4776.5806 | N16: =SUM(L16) -> 222 | O16: =N16*$B$4 -> 4776.5806 | P16: =SUM(N16) -> 222 | Q16: =P16*$B$4 -> 4776.5806 | R16: =SUM(P16) -> 222 | S16: =R16*$B$4 -> 4776.5806 | T16: =SUM(R16) -> 222 | U16: =T16*$B$4 -> 4776.5806 | V16: =SUM(T16) -> 222 | W16: =V16*$B$4 -> 4776.5806 | X16: =SUM(Y16/73370) -> 0.71612903 | Y16: =SUM(C16+E16+G16+I16+K16+M16+O16+Q16+S16+U16+W16) -> 52542.387 | Z16: ='B5'!C15 -> 228 | AA16: =SUM(Z16*$Z$4) -> 2280 | AB16: =SUM(Z16) -> 228 | AC16: =SUM(AB16*$Z$4) -> 2280 | AD16: =SUM(AB16) -> 228 | AE16: =SUM(AD16*$Z$4) -> 2280 | AF16: =SUM(AD16) -> 228 | AG16: =SUM(AF16*$Z$4) -> 2280 | AH16: =SUM(AF16) -> 228 | AI16: =SUM(AH16*$Z$4) -> 2280 | AJ16: =SUM(AH16) -> 228 | AK16: =SUM(AJ16*$Z$4) -> 2280 | AL16: =SUM(AJ16) -> 228 | AM16: =SUM(AL16*$Z$4) -> 2280 | AN16: =SUM(AO16/19600) -> 0.81428571 | AO16: =SUM(AA16+AC16+AE16+AG16+AI16+AK16+AM16) -> 15960 | AQ16: =SUM(AR16/92970) -> 0.73682249 | AR16: =SUM(AO16+Y16) -> 68502.387 | AS16: =SUM(AR16-AR15-AT16) -> -1533.3871 | AV16: =IF(AT16>0,AU16,AV15) -> 0.674 | AW16: =-SUM('B5'!AI15) -> -253 | AX16: =-SUM(AW16-AS16) -> -1280.3871 | AY16: =SUM(AX16+AW16) -> -1533.3871 | AZ16: =ELEC!A13 -> 0 | BA16: ='General information '!D16 -> 15.5 | BB16: =SUM('General information '!E16) -> 0.72 | BC16: =IF(AR15>=AR16,0,1) -> 0 | BD16: 19222 | BE16: =(305/1185)*ELEC!Q14 -> 676.40506 | BG16: =#REF!-BE16 -> #REF!
A17: =ELEC!C14 -> 44239 | B17: ='B5'!B16 -> 219 | C17: =B17*$B$4 -> 4712.0323 | D17: =SUM(B17) -> 219 | E17: =D17*$B$4 -> 4712.0323 | F17: =SUM(D17) -> 219 | G17: =F17*$B$4 -> 4712.0323 | H17: =SUM(F17) -> 219 | I17: =H17*$B$4 -> 4712.0323 | J17: =SUM(H17) -> 219 | K17: =J17*$B$4 -> 4712.0323 | L17: =SUM(J17) -> 219 | M17: =L17*$B$4 -> 4712.0323 | N17: =SUM(L17) -> 219 | O17: =N17*$B$4 -> 4712.0323 | P17: =SUM(N17) -> 219 | Q17: =P17*$B$4 -> 4712.0323 | R17: =SUM(P17) -> 219 | S17: =R17*$B$4 -> 4712.0323 | T17: =SUM(R17) -> 219 | U17: =T17*$B$4 -> 4712.0323 | V17: =SUM(T17) -> 219 | W17: =V17*$B$4 -> 4712.0323 | X17: =SUM(Y17/73370) -> 0.70645161 | Y17: =SUM(C17+E17+G17+I17+K17+M17+O17+Q17+S17+U17+W17) -> 51832.355 | Z17: ='B5'!C16 -> 224 | AA17: =SUM(Z17*$Z$4) -> 2240 | AB17: =SUM(Z17) -> 224 | AC17: =SUM(AB17*$Z$4) -> 2240 | AD17: =SUM(AB17) -> 224 | AE17: =SUM(AD17*$Z$4) -> 2240 | AF17: =SUM(AD17) -> 224 | AG17: =SUM(AF17*$Z$4) -> 2240 | AH17: =SUM(AF17) -> 224 | AI17: =SUM(AH17*$Z$4) -> 2240 | AJ17: =SUM(AH17) -> 224 | AK17: =SUM(AJ17*$Z$4) -> 2240 | AL17: =SUM(AJ17) -> 224 | AM17: =SUM(AL17*$Z$4) -> 2240 | AN17: =SUM(AO17/19600) -> 0.8 | AO17: =SUM(AA17+AC17+AE17+AG17+AI17+AK17+AM17) -> 15680 | AQ17: =SUM(AR17/92970) -> 0.72617355 | AR17: =SUM(AO17+Y17) -> 67512.355 | AS17: =SUM(AR17-AR16-AT17) -> -990.03226 | AV17: =IF(AT17>0,AU17,AV16) -> 0.674 | AW17: =-SUM('B5'!AI16) -> -234 | AX17: =-SUM(AW17-AS17) -> -756.03226 | AY17: =SUM(AX17+AW17) -> -990.03226 | AZ17: =ELEC!A14 -> 0 | BA17: ='General information '!D17 -> 15.5 | BB17: =SUM('General information '!E17) -> 0.51 | BC17: =IF(AR16>=AR17,0,1) -> 0 | BD17: 19222 | BE17: =(305/1185)*ELEC!Q15 -> 0 | BG17: =#REF!-BE17 -> #REF!
A18: =ELEC!C15 -> 44240 | B18: ='B5'!B17 -> 219 | C18: =B18*$B$4 -> 4712.0323 | D18: =SUM(B18) -> 219 | E18: =D18*$B$4 -> 4712.0323 | F18: =SUM(D18) -> 219 | G18: =F18*$B$4 -> 4712.0323 | H18: =SUM(F18) -> 219 | I18: =H18*$B$4 -> 4712.0323 | J18: =SUM(H18) -> 219 | K18: =J18*$B$4 -> 4712.0323 | L18: =SUM(J18) -> 219 | M18: =L18*$B$4 -> 4712.0323 | N18: =SUM(L18) -> 219 | O18: =N18*$B$4 -> 4712.0323 | P18: =SUM(N18) -> 219 | Q18: =P18*$B$4 -> 4712.0323 | R18: =SUM(P18) -> 219 | S18: =R18*$B$4 -> 4712.0323 | T18: =SUM(R18) -> 219 | U18: =T18*$B$4 -> 4712.0323 | V18: =SUM(T18) -> 219 | W18: =V18*$B$4 -> 4712.0323 | X18: =SUM(Y18/73370) -> 0.70645161 | Y18: =SUM(C18+E18+G18+I18+K18+M18+O18+Q18+S18+U18+W18) -> 51832.355 | Z18: ='B5'!C17 -> 224 | AA18: =SUM(Z18*$Z$4) -> 2240 | AB18: =SUM(Z18) -> 224 | AC18: =SUM(AB18*$Z$4) -> 2240 | AD18: =SUM(AB18) -> 224 | AE18: =SUM(AD18*$Z$4) -> 2240 | AF18: =SUM(AD18) -> 224 | AG18: =SUM(AF18*$Z$4) -> 2240 | AH18: =SUM(AF18) -> 224 | AI18: =SUM(AH18*$Z$4) -> 2240 | AJ18: =SUM(AH18) -> 224 | AK18: =SUM(AJ18*$Z$4) -> 2240 | AL18: =SUM(AJ18) -> 224 | AM18: =SUM(AL18*$Z$4) -> 2240 | AN18: =SUM(AO18/19600) -> 0.8 | AO18: =SUM(AA18+AC18+AE18+AG18+AI18+AK18+AM18) -> 15680 | AQ18: =SUM(AR18/92970) -> 0.72617355 | AR18: =SUM(AO18+Y18) -> 67512.355 | AS18: =SUM(AR18-AR17-AT18) -> 0 | AV18: =IF(AT18>0,AU18,AV17) -> 0.674 | AW18: =-SUM('B5'!AI17) -> 0 | AX18: =-SUM(AW18-AS18) -> 0 | AY18: =SUM(AX18+AW18) -> 0 | AZ18: =ELEC!A15 -> 0 | BA18: ='General information '!D18 -> 0 | BB18: =SUM('General information '!E18) -> 0 | BC18: =IF(AR17>=AR18,0,1) -> 0 | BD18: 19222 | BE18: =(305/1185)*ELEC!Q16 -> 0 | BG18: =#REF!-BE18 -> #REF!
A19: =ELEC!C16 -> 44241 | B19: ='B5'!B18 -> 219 | C19: =B19*$B$4 -> 4712.0323 | D19: =SUM(B19) -> 219 | E19: =D19*$B$4 -> 4712.0323 | F19: =SUM(D19) -> 219 | G19: =F19*$B$4 -> 4712.0323 | H19: =SUM(F19) -> 219 | I19: =H19*$B$4 -> 4712.0323 | J19: =SUM(H19) -> 219 | K19: =J19*$B$4 -> 4712.0323 | L19: =SUM(J19) -> 219 | M19: =L19*$B$4 -> 4712.0323 | N19: =SUM(L19) -> 219 | O19: =N19*$B$4 -> 4712.0323 | P19: =SUM(N19) -> 219 | Q19: =P19*$B$4 -> 4712.0323 | R19: =SUM(P19) -> 219 | S19: =R19*$B$4 -> 4712.0323 | T19: =SUM(R19) -> 219 | U19: =T19*$B$4 -> 4712.0323 | V19: =SUM(T19) -> 219 | W19: =V19*$B$4 -> 4712.0323 | X19: =SUM(Y19/73370) -> 0.70645161 | Y19: =SUM(C19+E19+G19+I19+K19+M19+O19+Q19+S19+U19+W19) -> 51832.355 | Z19: ='B5'!C18 -> 224 | AA19: =SUM(Z19*$Z$4) -> 2240 | AB19: =SUM(Z19) -> 224 | AC19: =SUM(AB19*$Z$4) -> 2240 | AD19: =SUM(AB19) -> 224 | AE19: =SUM(AD19*$Z$4) -> 2240 | AF19: =SUM(AD19) -> 224 | AG19: =SUM(AF19*$Z$4) -> 2240 | AH19: =SUM(AF19) -> 224 | AI19: =SUM(AH19*$Z$4) -> 2240 | AJ19: =SUM(AH19) -> 224 | AK19: =SUM(AJ19*$Z$4) -> 2240 | AL19: =SUM(AJ19) -> 224 | AM19: =SUM(AL19*$Z$4) -> 2240 | AN19: =SUM(AO19/19600) -> 0.8 | AO19: =SUM(AA19+AC19+AE19+AG19+AI19+AK19+AM19) -> 15680 | AQ19: =SUM(AR19/92970) -> 0.72617355 | AR19: =SUM(AO19+Y19) -> 67512.355 | AS19: =SUM(AR19-AR18-AT19) -> 0 | AV19: =IF(AT19>0,AU19,AV18) -> 0.674 | AW19: =-SUM('B5'!AI18) -> 0 | AX19: =-SUM(AW19-AS19) -> 0 | AY19: =SUM(AX19+AW19) -> 0 | AZ19: =ELEC!A16 -> 0 | BA19: ='General information '!D19 -> 0 | BB19: =SUM('General information '!E19) -> 0 | BC19: =IF(AR18>=AR19,0,1) -> 0 | BD19: 19222 | BE19: =(305/1185)*ELEC!Q17 -> 0 | BG19: =#REF!-BE19 -> #REF!
A20: =ELEC!C17 -> 44242 | B20: ='B5'!B19 -> 219 | C20: =B20*$B$4 -> 4712.0323 | D20: =SUM(B20) -> 219 | E20: =D20*$B$4 -> 4712.0323 | F20: =SUM(D20) -> 219 | G20: =F20*$B$4 -> 4712.0323 | H20: =SUM(F20) -> 219 | I20: =H20*$B$4 -> 4712.0323 | J20: =SUM(H20) -> 219 | K20: =J20*$B$4 -> 4712.0323 | L20: =SUM(J20) -> 219 | M20: =L20*$B$4 -> 4712.0323 | N20: =SUM(L20) -> 219 | O20: =N20*$B$4 -> 4712.0323 | P20: =SUM(N20) -> 219 | Q20: =P20*$B$4 -> 4712.0323 | R20: =SUM(P20) -> 219 | S20: =R20*$B$4 -> 4712.0323 | T20: =SUM(R20) -> 219 | U20: =T20*$B$4 -> 4712.0323 | V20: =SUM(T20) -> 219 | W20: =V20*$B$4 -> 4712.0323 | X20: =SUM(Y20/73370) -> 0.70645161 | Y20: =SUM(C20+E20+G20+I20+K20+M20+O20+Q20+S20+U20+W20) -> 51832.355 | Z20: ='B5'!C19 -> 224 | AA20: =SUM(Z20*$Z$4) -> 2240 | AB20: =SUM(Z20) -> 224 | AC20: =SUM(AB20*$Z$4) -> 2240 | AD20: =SUM(AB20) -> 224 | AE20: =SUM(AD20*$Z$4) -> 2240 | AF20: =SUM(AD20) -> 224 | AG20: =SUM(AF20*$Z$4) -> 2240 | AH20: =SUM(AF20) -> 224 | AI20: =SUM(AH20*$Z$4) -> 2240 | AJ20: =SUM(AH20) -> 224 | AK20: =SUM(AJ20*$Z$4) -> 2240 | AL20: =SUM(AJ20) -> 224 | AM20: =SUM(AL20*$Z$4) -> 2240 | AN20: =SUM(AO20/19600) -> 0.8 | AO20: =SUM(AA20+AC20+AE20+AG20+AI20+AK20+AM20) -> 15680 | AQ20: =SUM(AR20/92970) -> 0.72617355 | AR20: =SUM(AO20+Y20) -> 67512.355 | AS20: =SUM(AR20-AR19-AT20) -> 0 | AV20: =IF(AT20>0,AU20,AV19) -> 0.674 | AW20: =-SUM('B5'!AI19) -> 0 | AX20: =-SUM(AW20-AS20) -> 0 | AY20: =SUM(AX20+AW20) -> 0 | AZ20: =ELEC!A17 -> 0 | BA20: ='General information '!D20 -> 0 | BB20: =SUM('General information '!E20) -> 0 | BC20: =IF(AR19>=AR20,0,1) -> 0 | BD20: 19222 | BE20: =(305/1185)*ELEC!Q18 -> 0 | BG20: =#REF!-BE20 -> #REF!
A21: =ELEC!C18 -> 44243 | B21: ='B5'!B20 -> 219 | C21: =B21*$B$4 -> 4712.0323 | D21: =SUM(B21) -> 219 | E21: =D21*$B$4 -> 4712.0323 | F21: =SUM(D21) -> 219 | G21: =F21*$B$4 -> 4712.0323 | H21: =SUM(F21) -> 219 | I21: =H21*$B$4 -> 4712.0323 | J21: =SUM(H21) -> 219 | K21: =J21*$B$4 -> 4712.0323 | L21: =SUM(J21) -> 219 | M21: =L21*$B$4 -> 4712.0323 | N21: =SUM(L21) -> 219 | O21: =N21*$B$4 -> 4712.0323 | P21: =SUM(N21) -> 219 | Q21: =P21*$B$4 -> 4712.0323 | R21: =SUM(P21) -> 219 | S21: =R21*$B$4 -> 4712.0323 | T21: =SUM(R21) -> 219 | U21: =T21*$B$4 -> 4712.0323 | V21: =SUM(T21) -> 219 | W21: =V21*$B$4 -> 4712.0323 | X21: =SUM(Y21/73370) -> 0.70645161 | Y21: =SUM(C21+E21+G21+I21+K21+M21+O21+Q21+S21+U21+W21) -> 51832.355 | Z21: ='B5'!C20 -> 224 | AA21: =SUM(Z21*$Z$4) -> 2240 | AB21: =SUM(Z21) -> 224 | AC21: =SUM(AB21*$Z$4) -> 2240 | AD21: =SUM(AB21) -> 224 | AE21: =SUM(AD21*$Z$4) -> 2240 | AF21: =SUM(AD21) -> 224 | AG21: =SUM(AF21*$Z$4) -> 2240 | AH21: =SUM(AF21) -> 224 | AI21: =SUM(AH21*$Z$4) -> 2240 | AJ21: =SUM(AH21) -> 224 | AK21: =SUM(AJ21*$Z$4) -> 2240 | AL21: =SUM(AJ21) -> 224 | AM21: =SUM(AL21*$Z$4) -> 2240 | AN21: =SUM(AO21/19600) -> 0.8 | AO21: =SUM(AA21+AC21+AE21+AG21+AI21+AK21+AM21) -> 15680 | AQ21: =SUM(AR21/92970) -> 0.72617355 | AR21: =SUM(AO21+Y21) -> 67512.355 | AS21: =SUM(AR21-AR20-AT21) -> 0 | AV21: =IF(AT21>0,AU21,AV20) -> 0.674 | AW21: =-SUM('B5'!AI20) -> 0 | AX21: =-SUM(AW21-AS21) -> 0 | AY21: =SUM(AX21+AW21) -> 0 | AZ21: =ELEC!A18 -> 0 | BA21: ='General information '!D21 -> 0 | BB21: =SUM('General information '!E21) -> 0 | BC21: =IF(AR20>=AR21,0,1) -> 0 | BD21: 19222 | BE21: =(305/1185)*ELEC!Q19 -> 0 | BG21: =#REF!-BE21 -> #REF!
A22: =ELEC!C19 -> 44244 | B22: ='B5'!B21 -> 219 | C22: =B22*$B$4 -> 4712.0323 | D22: =SUM(B22) -> 219 | E22: =D22*$B$4 -> 4712.0323 | F22: =SUM(D22) -> 219 | G22: =F22*$B$4 -> 4712.0323 | H22: =SUM(F22) -> 219 | I22: =H22*$B$4 -> 4712.0323 | J22: =SUM(H22) -> 219 | K22: =J22*$B$4 -> 4712.0323 | L22: =SUM(J22) -> 219 | M22: =L22*$B$4 -> 4712.0323 | N22: =SUM(L22) -> 219 | O22: =N22*$B$4 -> 4712.0323 | P22: =SUM(N22) -> 219 | Q22: =P22*$B$4 -> 4712.0323 | R22: =SUM(P22) -> 219 | S22: =R22*$B$4 -> 4712.0323 | T22: =SUM(R22) -> 219 | U22: =T22*$B$4 -> 4712.0323 | V22: =SUM(T22) -> 219 | W22: =V22*$B$4 -> 4712.0323 | X22: =SUM(Y22/73370) -> 0.70645161 | Y22: =SUM(C22+E22+G22+I22+K22+M22+O22+Q22+S22+U22+W22) -> 51832.355 | Z22: ='B5'!C21 -> 224 | AA22: =SUM(Z22*$Z$4) -> 2240 | AB22: =SUM(Z22) -> 224 | AC22: =SUM(AB22*$Z$4) -> 2240 | AD22: =SUM(AB22) -> 224 | AE22: =SUM(AD22*$Z$4) -> 2240 | AF22: =SUM(AD22) -> 224 | AG22: =SUM(AF22*$Z$4) -> 2240 | AH22: =SUM(AF22) -> 224 | AI22: =SUM(AH22*$Z$4) -> 2240 | AJ22: =SUM(AH22) -> 224 | AK22: =SUM(AJ22*$Z$4) -> 2240 | AL22: =SUM(AJ22) -> 224 | AM22: =SUM(AL22*$Z$4) -> 2240 | AN22: =SUM(AO22/19600) -> 0.8 | AO22: =SUM(AA22+AC22+AE22+AG22+AI22+AK22+AM22) -> 15680 | AQ22: =SUM(AR22/92970) -> 0.72617355 | AR22: =SUM(AO22+Y22) -> 67512.355 | AS22: =SUM(AR22-AR21-AT22) -> 0 | AV22: =IF(AT22>0,AU22,AV21) -> 0.674 | AW22: =-SUM('B5'!AI21) -> 0 | AX22: =-SUM(AW22-AS22) -> 0 | AY22: =SUM(AX22+AW22) -> 0 | AZ22: =ELEC!A19 -> 0 | BA22: ='General information '!D22 -> 0 | BB22: =SUM('General information '!E22) -> 0 | BC22: =IF(AR21>=AR22,0,1) -> 0 | BD22: 19222 | BE22: =(305/1185)*ELEC!Q20 -> 0 | BG22: =#REF!-BE22 -> #REF!
A23: =ELEC!C20 -> 44245 | B23: ='B5'!B22 -> 219 | C23: =B23*$B$4 -> 4712.0323 | D23: =SUM(B23) -> 219 | E23: =D23*$B$4 -> 4712.0323 | F23: =SUM(D23) -> 219 | G23: =F23*$B$4 -> 4712.0323 | H23: =SUM(F23) -> 219 | I23: =H23*$B$4 -> 4712.0323 | J23: =SUM(H23) -> 219 | K23: =J23*$B$4 -> 4712.0323 | L23: =SUM(J23) -> 219 | M23: =L23*$B$4 -> 4712.0323 | N23: =SUM(L23) -> 219 | O23: =N23*$B$4 -> 4712.0323 | P23: =SUM(N23) -> 219 | Q23: =P23*$B$4 -> 4712.0323 | R23: =SUM(P23) -> 219 | S23: =R23*$B$4 -> 4712.0323 | T23: =SUM(R23) -> 219 | U23: =T23*$B$4 -> 4712.0323 | V23: =SUM(T23) -> 219 | W23: =V23*$B$4 -> 4712.0323 | X23: =SUM(Y23/73370) -> 0.70645161 | Y23: =SUM(C23+E23+G23+I23+K23+M23+O23+Q23+S23+U23+W23) -> 51832.355 | Z23: ='B5'!C22 -> 224 | AA23: =SUM(Z23*$Z$4) -> 2240 | AB23: =SUM(Z23) -> 224 | AC23: =SUM(AB23*$Z$4) -> 2240 | AD23: =SUM(AB23) -> 224 | AE23: =SUM(AD23*$Z$4) -> 2240 | AF23: =SUM(AD23) -> 224 | AG23: =SUM(AF23*$Z$4) -> 2240 | AH23: =SUM(AF23) -> 224 | AI23: =SUM(AH23*$Z$4) -> 2240 | AJ23: =SUM(AH23) -> 224 | AK23: =SUM(AJ23*$Z$4) -> 2240 | AL23: =SUM(AJ23) -> 224 | AM23: =SUM(AL23*$Z$4) -> 2240 | AN23: =SUM(AO23/19600) -> 0.8 | AO23: =SUM(AA23+AC23+AE23+AG23+AI23+AK23+AM23) -> 15680 | AQ23: =SUM(AR23/92970) -> 0.72617355 | AR23: =SUM(AO23+Y23) -> 67512.355 | AS23: =SUM(AR23-AR22-AT23) -> 0 | AV23: =IF(AT23>0,AU23,AV22) -> 0.674 | AW23: =-SUM('B5'!AI22) -> 0 | AX23: =-SUM(AW23-AS23) -> 0 | AY23: =SUM(AX23+AW23) -> 0 | AZ23: =ELEC!A20 -> 0 | BA23: ='General information '!D23 -> 0 | BB23: =SUM('General information '!E23) -> 0 | BC23: =IF(AR22>=AR23,0,1) -> 0 | BD23: 19222 | BE23: =(305/1185)*ELEC!Q21 -> 0 | BG23: =#REF!-BE23 -> #REF!
A24: =ELEC!C21 -> 44246 | B24: ='B5'!B23 -> 219 | C24: =B24*$B$4 -> 4712.0323 | D24: =SUM(B24) -> 219 | E24: =D24*$B$4 -> 4712.0323 | F24: =SUM(D24) -> 219 | G24: =F24*$B$4 -> 4712.0323 | H24: =SUM(F24) -> 219 | I24: =H24*$B$4 -> 4712.0323 | J24: =SUM(H24) -> 219 | K24: =J24*$B$4 -> 4712.0323 | L24: =SUM(J24) -> 219 | M24: =L24*$B$4 -> 4712.0323 | N24: =SUM(L24) -> 219 | O24: =N24*$B$4 -> 4712.0323 | P24: =SUM(N24) -> 219 | Q24: =P24*$B$4 -> 4712.0323 | R24: =SUM(P24) -> 219 | S24: =R24*$B$4 -> 4712.0323 | T24: =SUM(R24) -> 219 | U24: =T24*$B$4 -> 4712.0323 | V24: =SUM(T24) -> 219 | W24: =V24*$B$4 -> 4712.0323 | X24: =SUM(Y24/73370) -> 0.70645161 | Y24: =SUM(C24+E24+G24+I24+K24+M24+O24+Q24+S24+U24+W24) -> 51832.355 | Z24: ='B5'!C23 -> 224 | AA24: =SUM(Z24*$Z$4) -> 2240 | AB24: =SUM(Z24) -> 224 | AC24: =SUM(AB24*$Z$4) -> 2240 | AD24: =SUM(AB24) -> 224 | AE24: =SUM(AD24*$Z$4) -> 2240 | AF24: =SUM(AD24) -> 224 | AG24: =SUM(AF24*$Z$4) -> 2240 | AH24: =SUM(AF24) -> 224 | AI24: =SUM(AH24*$Z$4) -> 2240 | AJ24: =SUM(AH24) -> 224 | AK24: =SUM(AJ24*$Z$4) -> 2240 | AL24: =SUM(AJ24) -> 224 | AM24: =SUM(AL24*$Z$4) -> 2240 | AN24: =SUM(AO24/19600) -> 0.8 | AO24: =SUM(AA24+AC24+AE24+AG24+AI24+AK24+AM24) -> 15680 | AQ24: =SUM(AR24/92970) -> 0.72617355 | AR24: =SUM(AO24+Y24) -> 67512.355 | AS24: =SUM(AR24-AR23-AT24) -> 0 | AV24: =IF(AT24>0,AU24,AV23) -> 0.674 | AW24: =-SUM('B5'!AI23) -> 0 | AX24: =-SUM(AW24-AS24) -> 0 | AY24: =SUM(AX24+AW24) -> 0 | AZ24: =ELEC!A21 -> 0 | BA24: ='General information '!D24 -> 0 | BB24: =SUM('General information '!E24) -> 0 | BC24: =IF(AR23>=AR24,0,1) -> 0 | BD24: 19222 | BE24: =(305/1185)*ELEC!Q22 -> 0 | BG24: =#REF!-BE24 -> #REF!
... A32: =ELEC!C29 -> 44254 | B32: ='B5'!B31 -> 219 | C32: =B32*$B$4 -> 4712.0323 | D32: =SUM(B32) -> 219 | E32: =D32*$B$4 -> 4712.0323 | F32: =SUM(D32) -> 219 | G32: =F32*$B$4 -> 4712.0323 | H32: =SUM(F32) -> 219 | I32: =H32*$B$4 -> 4712.0323 | J32: =SUM(H32) -> 219 | K32: =J32*$B$4 -> 4712.0323 | L32: =SUM(J32) -> 219 | M32: =L32*$B$4 -> 4712.0323 | N32: =SUM(L32) -> 219 | O32: =N32*$B$4 -> 4712.0323 | P32: =SUM(N32) -> 219 | Q32: =P32*$B$4 -> 4712.0323 | R32: =SUM(P32) -> 219 | S32: =R32*$B$4 -> 4712.0323 | T32: =SUM(R32) -> 219 | U32: =T32*$B$4 -> 4712.0323 | V32: =SUM(T32) -> 219 | W32: =V32*$B$4 -> 4712.0323 | X32: =SUM(Y32/73370) -> 0.70645161 | Y32: =SUM(C32+E32+G32+I32+K32+M32+O32+Q32+S32+U32+W32) -> 51832.355 | Z32: ='B5'!C31 -> 224 | AA32: =SUM(Z32*$Z$4) -> 2240 | AB32: =SUM(Z32) -> 224 | AC32: =SUM(AB32*$Z$4) -> 2240 | AD32: =SUM(AB32) -> 224 | AE32: =SUM(AD32*$Z$4) -> 2240 | AF32: =SUM(AD32) -> 224 | AG32: =SUM(AF32*$Z$4) -> 2240 | AH32: =SUM(AF32) -> 224 | AI32: =SUM(AH32*$Z$4) -> 2240 | AJ32: =SUM(AH32) -> 224 | AK32: =SUM(AJ32*$Z$4) -> 2240 | AL32: =SUM(AJ32) -> 224 | AM32: =SUM(AL32*$Z$4) -> 2240 | AN32: =SUM(AO32/19600) -> 0.8 | AO32: =SUM(AA32+AC32+AE32+AG32+AI32+AK32+AM32) -> 15680 | AQ32: =SUM(AR32/92970) -> 0.72617355 | AR32: =SUM(AO32+Y32) -> 67512.355 | AS32: =SUM(AR32-AR31-AT32) -> 0 | AV32: =IF(AT32>0,AU32,AV31) -> 0.674 | AW32: =-SUM('B5'!AI31) -> 0 | AX32: =-SUM(AW32-AS32) -> 0 | AY32: =SUM(AX32+AW32) -> 0 | AZ32: =ELEC!A29 -> 0 | BA32: ='General information '!D32 -> 0 | BB32: =SUM('General information '!E32) -> 0 | BC32: =IF(AR31>=AR32,0,1) -> 0 | BD32: 19222 | BE32: =(305/1185)*ELEC!Q30 -> 0 | BG32: =#REF!-BE32 -> #REF!
A33: =ELEC!C30 -> 44255 | B33: ='B5'!B32 -> 219 | C33: =B33*$B$4 -> 4712.0323 | D33: =SUM(B33) -> 219 | E33: =D33*$B$4 -> 4712.0323 | F33: =SUM(D33) -> 219 | G33: =F33*$B$4 -> 4712.0323 | H33: =SUM(F33) -> 219 | I33: =H33*$B$4 -> 4712.0323 | J33: =SUM(H33) -> 219 | K33: =J33*$B$4 -> 4712.0323 | L33: =SUM(J33) -> 219 | M33: =L33*$B$4 -> 4712.0323 | N33: =SUM(L33) -> 219 | O33: =N33*$B$4 -> 4712.0323 | P33: =SUM(N33) -> 219 | Q33: =P33*$B$4 -> 4712.0323 | R33: =SUM(P33) -> 219 | S33: =R33*$B$4 -> 4712.0323 | T33: =SUM(R33) -> 219 | U33: =T33*$B$4 -> 4712.0323 | V33: =SUM(T33) -> 219 | W33: =V33*$B$4 -> 4712.0323 | X33: =SUM(Y33/73370) -> 0.70645161 | Y33: =SUM(C33+E33+G33+I33+K33+M33+O33+Q33+S33+U33+W33) -> 51832.355 | Z33: ='B5'!C32 -> 224 | AA33: =SUM(Z33*$Z$4) -> 2240 | AB33: =SUM(Z33) -> 224 | AC33: =SUM(AB33*$Z$4) -> 2240 | AD33: =SUM(AB33) -> 224 | AE33: =SUM(AD33*$Z$4) -> 2240 | AF33: =SUM(AD33) -> 224 | AG33: =SUM(AF33*$Z$4) -> 2240 | AH33: =SUM(AF33) -> 224 | AI33: =SUM(AH33*$Z$4) -> 2240 | AJ33: =SUM(AH33) -> 224 | AK33: =SUM(AJ33*$Z$4) -> 2240 | AL33: =SUM(AJ33) -> 224 | AM33: =SUM(AL33*$Z$4) -> 2240 | AN33: =SUM(AO33/19600) -> 0.8 | AO33: =SUM(AA33+AC33+AE33+AG33+AI33+AK33+AM33) -> 15680 | AQ33: =SUM(AR33/92970) -> 0.72617355 | AR33: =SUM(AO33+Y33) -> 67512.355 | AS33: =SUM(AR33-AR32-AT33) -> 0 | AV33: =IF(AT33>0,AU33,AV32) -> 0.674 | AW33: =-SUM('B5'!AI32) -> 0 | AX33: =-SUM(AW33-AS33) -> 0 | AY33: =SUM(AX33+AW33) -> 0 | AZ33: =ELEC!A30 -> 0 | BA33: ='General information '!D33 -> 0 | BB33: =SUM('General information '!E33) -> 0 | BC33: =IF(AR32>=AR33,0,1) -> 0 | BD33: 19222 | BE33: =(305/1185)*ELEC!#REF! -> #REF! | BG33: =#REF!-BE33 -> #REF!
AR34: NB delivery | AS34: =COUNT(AT6:AT33) -> 2 | AT34: =SUM(AT6:AT33) -> 7850.1 | AU34: =SUM(AU6:AU33)/AS34 -> 0.387 | AX34: =SUM(AX6:AX33) -> -9555.6161 | AY34: =SUM(AY6:AY33) -> -13133.616
AT35: =+AT34*AU34 -> 3037.9887
AS37: =SUM(AS6:AS33)/'EDl log'!A32 -> -1094.468

Sheet Sheet1
A1: TOTAL CH RH | B1: TOTAL CH cons KW | C1: TOTAL ELIC KW | D1: TOTAL EDL | E1: TOTAL GEN KW | F1: GEN HR | G1: WATER IN | H1: TOTAL CT | I1: TOTAL WATER | J1: Date
A2: =ELEC!T3+ELEC!X1+ELEC!AB3 -> #VALUE! | B2: =ELEC!AF3 -> 397 | C2: =ELEC!N3 -> 6404.4 | D2: =C2-E2 -> 4436.4 | E2: =ELEC!Q3 -> 1968 | F2: =GEN!Z2 -> 3 | G2: =WATER!C5+WATER!H5 -> 0 | H2: =WATER!L5 -> 0 | I2: =WATER!BC5+WATER!BD5+WATER!BE6-Sheet1!G2 -> -39 | J2: ='B5'!A4 -> 44227
A3: =ELEC!T4+ELEC!X2+ELEC!AB4 -> 4 | B3: =ELEC!AF4 -> 514 | C3: =ELEC!N4 -> 6622 | D3: =C3-E3 -> 4367 | E3: =ELEC!Q4 -> 2255 | F3: =GEN!Z3 -> 3 | G3: =WATER!C6+WATER!H6 -> 0 | H3: =WATER!L6 -> 0 | I3: =WATER!BC6+WATER!BD6+WATER!BE7-Sheet1!G3 -> -16.4 | J3: ='B5'!A5 -> 44228
A4: =ELEC!T5+ELEC!X5+ELEC!AB5 -> 3 | B4: =ELEC!AF5 -> 688 | C4: =ELEC!N5 -> 6753 | D4: =C4-E4 -> 3832 | E4: =ELEC!Q5 -> 2921 | F4: =GEN!Z4 -> 4 | G4: =WATER!C7+WATER!H7 -> 0 | H4: =WATER!L7 -> 0 | I4: =WATER!BC7+WATER!BD7+WATER!BE8-Sheet1!G4 -> -21.1 | J4: ='B5'!A6 -> 44229
A5: =ELEC!T6+ELEC!X6+ELEC!AB6 -> 4 | B5: =ELEC!AF6 -> 548 | C5: =ELEC!N6 -> 6587 | D5: =C5-E5 -> 3963 | E5: =ELEC!Q6 -> 2624 | F5: =GEN!Z5 -> 4 | G5: =WATER!C8+WATER!H8 -> 0 | H5: =WATER!L8 -> 0 | I5: =WATER!BC8+WATER!BD8+WATER!BE9-Sheet1!G5 -> -25.1 | J5: ='B5'!A7 -> 44230
A6: =ELEC!T7+ELEC!X7+ELEC!AB7 -> 3 | B6: =ELEC!AF7 -> 440 | C6: =ELEC!N7 -> 5932 | D6: =C6-E6 -> 5932 | E6: =ELEC!Q24 -> 0 | F6: =GEN!Z6 -> 4 | G6: =WATER!C9+WATER!H9 -> 0 | H6: =WATER!L9 -> 0 | I6: =WATER!BC9+WATER!BD9+WATER!BE10-Sheet1!G6 -> -39.6 | J6: ='B5'!A8 -> 44231
A7: =ELEC!T8+ELEC!X8+ELEC!AB8 -> 2 | B7: =ELEC!AF8 -> 374 | C7: =ELEC!N8 -> 5977 | D7: =C7-E7 -> 4283 | E7: =ELEC!Q8 -> 1694 | F7: =GEN!Z7 -> 3 | G7: =WATER!C10+WATER!H10 -> 0 | H7: =WATER!L10 -> -1 | I7: =WATER!BC10+WATER!BD10+WATER!BE11-Sheet1!G7 -> -35.6 | J7: ='B5'!A9 -> 44232
A8: =ELEC!T9+ELEC!X9+ELEC!AB9 -> 2 | B8: =ELEC!AF9 -> 481 | C8: =ELEC!N9 -> 6551.2 | D8: =C8-E8 -> 4507.2 | E8: =ELEC!Q9 -> 2044 | F8: =GEN!Z8 -> 3 | G8: =WATER!C11+WATER!H11 -> 0 | H8: =WATER!L11 -> 0.5 | I8: =WATER!BC11+WATER!BD11+WATER!BE12-Sheet1!G8 -> -28.7 | J8: ='B5'!A10 -> 44233
A9: =ELEC!T10+ELEC!X10+ELEC!AB10 -> 3 | B9: =ELEC!AF10 -> 518 | C9: =ELEC!N10 -> 6289.8 | D9: =C9-E9 -> 4244.8 | E9: =ELEC!Q10 -> 2045 | F9: =GEN!Z9 -> 3 | G9: =WATER!C12+WATER!H12 -> 0 | H9: =WATER!L12 -> 0.5 | I9: =WATER!BC12+WATER!BD12+WATER!BE13-Sheet1!G9 -> -24.7 | J9: ='B5'!A11 -> 44234
A10: =ELEC!T11+ELEC!X11+ELEC!AB11 -> 4 | B10: =ELEC!AF11 -> 876 | C10: =ELEC!N11 -> 7008 | D10: =C10-E10 -> 3572 | E10: =ELEC!Q11 -> 3436 | F10: =GEN!Z10 -> 3 | G10: =WATER!C13+WATER!H13 -> 0 | H10: =WATER!L13 -> 1 | I10: =WATER!BC13+WATER!BD13+WATER!BE14-Sheet1!G10 -> -24 | J10: ='B5'!A12 -> 44235
A11: =ELEC!T12+ELEC!X12+ELEC!AB12 -> 6 | B11: =ELEC!AF12 -> 946 | C11: =ELEC!N12 -> 7276 | D11: =C11-E11 -> 2834 | E11: =ELEC!Q12 -> 4442 | F11: =GEN!Z11 -> 5 | G11: =WATER!C14+WATER!H14 -> 0 | H11: =WATER!L14 -> 1 | I11: =WATER!BC14+WATER!BD14+WATER!BE15-Sheet1!G11 -> -22.2 | J11: ='B5'!A13 -> 44236
A12: =ELEC!T13+ELEC!X13+ELEC!AB13 -> 5 | B12: =ELEC!AF13 -> 815 | C12: =ELEC!N13 -> 7236 | D12: =C12-E12 -> 3237 | E12: =ELEC!Q13 -> 3999 | F12: =GEN!Z12 -> 7 | G12: =WATER!C15+WATER!H15 -> 0 | H12: =WATER!L15 -> 0 | I12: =WATER!BC15+WATER!BD15+WATER!BE16-Sheet1!G12 -> -20.4 | J12: ='B5'!A14 -> 44237
A13: =ELEC!T14+ELEC!X14+ELEC!AB14 -> 4 | B13: =ELEC!AF14 -> 555 | C13: =ELEC!N14 -> 5643 | D13: =C13-E13 -> 3015 | E13: =ELEC!Q14 -> 2628 | F13: =GEN!Z13 -> 6 | G13: =WATER!C16+WATER!H16 -> 0 | H13: =WATER!L16 -> 0 | I13: =WATER!BC16+WATER!BD16+WATER!BE17-Sheet1!G13 -> -24.4 | J13: ='B5'!A15 -> 44238
A14: =ELEC!T15+ELEC!X15+ELEC!AB15 -> 0 | B14: =ELEC!AF15 -> 0 | C14: =ELEC!N15 -> 0 | D14: =C14-E14 -> 0 | E14: =ELEC!Q15 -> 0 | F14: =GEN!Z14 -> 5 | G14: =WATER!C17+WATER!H17 -> 0 | H14: =WATER!L17 -> 0 | I14: =WATER!BC17+WATER!BD17+WATER!BE18-Sheet1!G14 -> -13.1 | J14: ='B5'!A16 -> 44239
A15: =ELEC!T16+ELEC!X16+ELEC!AB16 -> 0 | B15: =ELEC!AF16 -> 0 | C15: =ELEC!N16 -> 0 | D15: =C15-E15 -> 0 | E15: =ELEC!Q16 -> 0 | F15: =GEN!Z15 -> 0 | G15: =WATER!C18+WATER!H18 -> 0 | H15: =WATER!L18 -> 0 | I15: =WATER!BC18+WATER!BD18+WATER!BE19-Sheet1!G15 -> 0 | J15: ='B5'!A17 -> 44240
A16: =ELEC!T17+ELEC!X17+ELEC!AB17 -> 0 | B16: =ELEC!AF17 -> 0 | C16: =ELEC!N17 -> 0 | D16: =C16-E16 -> 0 | E16: =ELEC!Q17 -> 0 | F16: =GEN!Z16 -> 0 | G16: =WATER!C19+WATER!H19 -> 0 | H16: =WATER!L19 -> 0 | I16: =WATER!BC19+WATER!BD19+WATER!BE20-Sheet1!G16 -> 0 | J16: ='B5'!A18 -> 44241
A17: =ELEC!T18+ELEC!X18+ELEC!AB18 -> 0 | B17: =ELEC!AF18 -> 0 | C17: =ELEC!N18 -> 0 | D17: =C17-E17 -> 0 | E17: =ELEC!Q18 -> 0 | F17: =GEN!Z17 -> 0 | G17: =WATER!C20+WATER!H20 -> 0 | H17: =WATER!L20 -> 0 | I17: =WATER!BC20+WATER!BD20+WATER!BE21-Sheet1!G17 -> 0 | J17: ='B5'!A19 -> 44242
A18: =ELEC!T19+ELEC!X19+ELEC!AB19 -> 0 | B18: =ELEC!AF19 -> 0 | C18: =ELEC!N19 -> 0 | D18: =C18-E18 -> 0 | E18: =ELEC!Q19 -> 0 | F18: =GEN!Z18 -> 0 | G18: =WATER!C21+WATER!H21 -> 0 | H18: =WATER!L21 -> 0 | I18: =WATER!BC21+WATER!BD21+WATER!BE22-Sheet1!G18 -> 0 | J18: ='B5'!A20 -> 44243
... A29: =ELEC!T30+ELEC!X30+ELEC!AB30 -> 0 | B29: =ELEC!AF30 -> 0 | C29: =ELEC!N30 -> 0 | D29: =C29-E29 -> 0 | E29: =ELEC!Q30 -> 0 | F29: =GEN!Z29 -> 0 | G29: =WATER!C32+WATER!H32 -> 0 | H29: =WATER!L32 -> 0 | I29: =WATER!BC32+WATER!BD32+WATER!BE33-Sheet1!G29 -> 0 | J29: ='B5'!A31 -> 44254
A30: =ELEC!#REF!+ELEC!#REF!+ELEC!#REF! -> #REF! | B30: =ELEC!#REF! -> #REF! | C30: =ELEC!#REF! -> #REF! | D30: =C30-E30 -> #REF! | E30: =ELEC!#REF! -> #REF! | F30: =GEN!Z30 -> 0 | G30: =WATER!C33+WATER!H33 -> 0 | H30: =WATER!L33 -> 0 | I30: =WATER!BC33+WATER!BD33+WATER!#REF!-Sheet1!G30 -> #REF! | J30: ='B5'!A32 -> 44255
A31: =ELEC!#REF!+ELEC!#REF!+ELEC!#REF! -> #REF! | B31: =ELEC!#REF! -> #REF! | C31: =ELEC!#REF! -> #REF! | D31: =C31-E31 -> #REF! | E31: =ELEC!#REF! -> #REF! | F31: =GEN!#REF! -> #REF! | G31: =WATER!#REF!+WATER!#REF! -> #REF! | H31: =WATER!#REF! -> #REF! | I31: =WATER!#REF!+WATER!#REF!+WATER!#REF!-Sheet1!G31 -> #REF! | J31: ='B5'!#REF! -> #REF!
A32: =ELEC!#REF!+ELEC!#REF!+ELEC!#REF! -> #REF! | B32: =ELEC!#REF! -> #REF! | C32: =ELEC!#REF! -> #REF! | D32: =C32-E32 -> #REF! | E32: =ELEC!#REF! -> #REF! | F32: =GEN!#REF! -> #REF! | G32: =WATER!#REF!+WATER!#REF! -> #REF! | H32: =WATER!#REF! -> #REF! | I32: =WATER!#REF!+WATER!#REF!+WATER!BE34-Sheet1!G32 -> #REF!

Sheet Report
B1: Boiler Fuel | C1: Steam Fuel | D1: GEN FUEL | E1: FUEL TOTAL | F1: CT/mᶾ | G1: Water Consumption | H1: Chiller KW | I1: GEN KW | J1: EDL KW | K1: occ | L1: covers | M1: temp. C⁰ | N1: RH %
B3: ='B5'!V3 -> 0 | C3: ='B5'!AH3 -> 0 | E3: =B3+C3+D3 -> 0
A4: 42704 | B4: 810 | C4: -606.1 | D4: 1420.5021 | E4: 1624.4021 | F4: 106 | G4: -58.4 | H4: 6284 | I4: 2399 | J4: 23932 | K4: 0 | L4: 0 | M4: 0 | N4: 0
A5: ='B5'!A5 -> 44228 | B5: ='B5'!V5 -> 348 | C5: ='B5'!AH5 -> 119.6 | D5: =GEN!AI3 -> 506.53165 | E5: =B5+C5+D5 -> 974.13165 | F5: =WATER!L5 -> 0 | G5: =WATER!BG5 -> -5.1 | H5: =ELEC!AF3 -> 397 | I5: =ELEC!Q3 -> 1968 | J5: =ELEC!R3 -> 4436.4
A6: ='B5'!A6 -> 44229 | B6: ='B5'!V6 -> 234 | C6: ='B5'!AH6 -> 0 | D6: =GEN!AI4 -> 580.40084 | E6: =B6+C6+D6 -> 814.40084 | F6: =WATER!L6 -> 0 | G6: =WATER!BG6 -> -33.9 | H6: =ELEC!AF4 -> 514 | I6: =ELEC!Q4 -> 2255 | J6: =ELEC!R4 -> 4367
A7: ='B5'!A7 -> 44230 | B7: ='B5'!V7 -> 254 | C7: ='B5'!AH7 -> 35 | D7: =GEN!AI5 -> 751.81857 | E7: =B7+C7+D7 -> 1040.8186 | F7: =WATER!L7 -> 0 | G7: =WATER!BG7 -> -11.3 | H7: =ELEC!AF5 -> 688 | I7: =ELEC!Q5 -> 2921 | J7: =ELEC!R5 -> 3832
A8: ='B5'!A8 -> 44231 | B8: ='B5'!V8 -> 314 | C8: ='B5'!AH8 -> 0 | D8: =GEN!AI6 -> 675.37553 | E8: =B8+C8+D8 -> 989.37553 | F8: =WATER!L8 -> 0 | G8: =WATER!BG8 -> -9.8 | H8: =ELEC!AF6 -> 548 | I8: =ELEC!Q6 -> 2624 | J8: =ELEC!R6 -> 3963
A9: ='B5'!A9 -> 44232 | B9: ='B5'!V9 -> 391 | C9: ='B5'!AH9 -> 0 | D9: =GEN!AI7 -> 505.75949 | E9: =B9+C9+D9 -> 896.75949 | F9: =WATER!L9 -> 0 | G9: =WATER!BG9 -> -18.9 | H9: =ELEC!AF7 -> 440 | I9: =ELEC!Q7 -> 1965 | J9: =ELEC!R7 -> 3967
A10: ='B5'!A10 -> 44233 | B10: ='B5'!V10 -> 311 | C10: ='B5'!AH10 -> 0 | D10: =GEN!AI8 -> 436.00844 | E10: =B10+C10+D10 -> 747.00844 | F10: =WATER!L10 -> -1 | G10: =WATER!BG10 -> -20.7 | H10: =ELEC!AF8 -> 374 | I10: =ELEC!Q8 -> 1694 | J10: =ELEC!R8 -> 4283
A11: ='B5'!A11 -> 44234 | B11: ='B5'!V11 -> 279 | C11: ='B5'!AH11 -> 0 | D11: =GEN!AI9 -> 526.09283 | E11: =B11+C11+D11 -> 805.09283 | F11: =WATER!L11 -> 0.5 | G11: =WATER!BG11 -> -14.9 | H11: =ELEC!AF9 -> 481 | I11: =ELEC!Q9 -> 2044 | J11: =ELEC!R9 -> 4507.2
A12: ='B5'!A12 -> 44235 | B12: ='B5'!V12 -> 256 | C12: ='B5'!AH12 -> 77.4 | D12: =GEN!AI10 -> 526.35021 | E12: =B12+C12+D12 -> 859.75021 | F12: =WATER!L12 -> 0.5 | G12: =WATER!BG12 -> -13.8 | H12: =ELEC!AF10 -> 518 | I12: =ELEC!Q10 -> 2045 | J12: =ELEC!R10 -> 4244.8
A13: ='B5'!A13 -> 44236 | B13: ='B5'!V13 -> 236 | C13: ='B5'!AH13 -> 0 | D13: =GEN!AI11 -> 884.37131 | E13: =B13+C13+D13 -> 1120.3713 | F13: =WATER!L13 -> 1 | G13: =WATER!BG13 -> -10.9 | H13: =ELEC!AF11 -> 876 | I13: =ELEC!Q11 -> 3436 | J13: =ELEC!R11 -> 3572
A14: ='B5'!A14 -> 44237 | B14: ='B5'!V14 -> 236 | C14: ='B5'!AH14 -> 0 | D14: =GEN!AI12 -> 1143.2996 | E14: =B14+C14+D14 -> 1379.2996 | F14: =WATER!L14 -> 1 | G14: =WATER!BG14 -> -13.1 | H14: =ELEC!AF12 -> 946 | I14: =ELEC!Q12 -> 4442 | J14: =ELEC!R12 -> 2834
A15: ='B5'!A15 -> 44238 | B15: ='B5'!V15 -> 253 | C15: ='B5'!AH15 -> 0 | D15: =GEN!AI13 -> 1029.2785 | E15: =B15+C15+D15 -> 1282.2785 | F15: =WATER!L15 -> 0 | G15: =WATER!BG15 -> -9.1 | H15: =ELEC!AF13 -> 815 | I15: =ELEC!Q13 -> 3999 | J15: =ELEC!R13 -> 3237
A16: ='B5'!A16 -> 44239 | B16: ='B5'!V16 -> 234 | C16: ='B5'!AH16 -> 0 | D16: =GEN!AI14 -> 676.40506 | E16: =B16+C16+D16 -> 910.40506 | F16: =WATER!L16 -> 0 | G16: =WATER!BG16 -> -11.3 | H16: =ELEC!AF14 -> 555 | I16: =ELEC!Q14 -> 2628 | J16: =ELEC!R14 -> 3015
... A32: ='B5'!A32 -> 44255 | B32: ='B5'!V32 -> 0 | C32: ='B5'!AH32 -> 0 | D32: =GEN!AI30 -> 0 | E32: =B32+C32+D32 -> 0 | F32: =WATER!L32 -> 0 | G32: =WATER!BG32 -> 0 | H32: =ELEC!AF30 -> 0 | I32: =ELEC!Q30 -> 0 | J32: =ELEC!R30 -> 0
A33: ='B5'!#REF! -> #REF! | B33: ='B5'!#REF! -> #REF! | C33: ='B5'!#REF! -> #REF! | D33: =GEN!#REF! -> #REF! | E33: =B33+C33+D33 -> #REF! | F33: =WATER!L33 -> 0 | G33: =WATER!BG33 -> 0 | H33: =ELEC!#REF! -> #REF! | I33: =ELEC!#REF! -> #REF! | J33: =ELEC!#REF! -> #REF!
A34: ='B5'!#REF! -> #REF! | B34: ='B5'!#REF! -> #REF! | C34: ='B5'!#REF! -> #REF! | D34: =GEN!#REF! -> #REF! | E34: =B34+C34+D34 -> #REF! | F34: =WATER!#REF! -> #REF! | G34: =WATER!#REF! -> #REF! | H34: =ELEC!#REF! -> #REF! | I34: =ELEC!#REF! -> #REF! | J34: =ELEC!#REF! -> #REF!

Sheet Sheet5
T3: Outdoor conditions
C4: Date | D4: Total Boiler running H | E4: AVE CONSUM | F4: Total Steam running H | G4: AVE CONSUM | H4: Total GEN running H | I4: AVE CONSUM | J4: Actual Diesel Consumption | K4: Actual Gas Consumption | L4: Total ELEC power | M4: Gen ELEC power | N4: EDL ELEC power | O4: Chillers running H | P4: Total Water delivery | Q4: Total water consumption | R4: Total water in tanks | S4: Occupancy | T4: AVE TEPM | U4: AVE Humidity
C5: 42429 | D5: ='B5'!AL4 -> 3 | E5: =D5*90 -> 270 | F5: ='B5'!AM4 -> 0 | G5: =F5*107 -> 0 | H5: =GEN!Z3 -> 3
C6: 42430 | D6: ='B5'!AL5 -> 4 | E6: =D6*90 -> 360 | F6: ='B5'!AM5 -> 1 | G6: =F6*107 -> 107
C7: 42431 | D7: ='B5'!AL6 -> 4 | E7: =D7*90 -> 360 | F7: ='B5'!AM6 -> 0 | G7: =F7*107 -> 0
C8: 42432 | D8: ='B5'!AL7 -> 4 | E8: =D8*90 -> 360 | F8: ='B5'!AM7 -> 0 | G8: =F8*107 -> 0
C9: 42433 | D9: ='B5'!AL8 -> 4 | E9: =D9*90 -> 360 | F9: ='B5'!AM8 -> 0 | G9: =F9*107 -> 0
C10: 42434 | D10: ='B5'!AL9 -> 5 | E10: =D10*90 -> 450 | F10: ='B5'!AM9 -> 0 | G10: =F10*107 -> 0
C11: 42435 | D11: ='B5'!AL10 -> 5 | E11: =D11*90 -> 450 | F11: ='B5'!AM10 -> 0 | G11: =F11*107 -> 0
C12: 42436 | D12: ='B5'!AL11 -> 3 | E12: =D12*90 -> 270 | F12: ='B5'!AM11 -> 0 | G12: =F12*107 -> 0
C13: 42437 | D13: ='B5'!AL12 -> 3 | E13: =D13*90 -> 270 | F13: ='B5'!AM12 -> 1 | G13: =F13*107 -> 107
C14: 42438 | D14: ='B5'!AL13 -> 3 | E14: =D14*90 -> 270 | F14: ='B5'!AM13 -> 0 | G14: =F14*107 -> 0
C15: 42439 | D15: ='B5'!AL14 -> 3 | E15: =D15*90 -> 270 | F15: ='B5'!AM14 -> 0 | G15: =F15*107 -> 0
C16: 42440 | D16: ='B5'!AL15 -> 4 | E16: =D16*90 -> 360 | F16: ='B5'!AM15 -> 0 | G16: =F16*107 -> 0
C17: 42441 | D17: ='B5'!AL16 -> 3 | E17: =D17*90 -> 270 | F17: ='B5'!AM16 -> 0 | G17: =F17*107 -> 0
... C33: 42457 | D33: ='B5'!AL32 -> 0 | E33: =D33*90 -> 0 | F33: ='B5'!AM32 -> 0 | G33: =F33*107 -> 0
C34: 42458 | D34: ='B5'!#REF! -> #REF! | E34: =D34*90 -> #REF! | F34: ='B5'!#REF! -> #REF! | G34: =F34*107 -> #REF!
C35: 42459 | D35: ='B5'!#REF! -> #REF! | E35: =D35*90 -> #REF! | F35: ='B5'!#REF! -> #REF! | G35: =F35*107 -> #REF!
C36: 42460 | D36: ='B5'!#REF! -> #REF! | E36: =D36*90 -> #REF! | F36: ='B5'!#REF! -> #REF! | G36: =F36*107 -> #REF!
C37: 42461 | D37: ='B5'!#REF! -> #REF! | E37: =D37*90 -> #REF! | F37: ='B5'!#REF! -> #REF! | G37: =F37*107 -> #REF!

Sheet GEN
B1: GEN1 | C1: RUN HR | D1: Fuel Counter Index | E1: Cons /day | F1: Diesel L/H | H1: next service | I1: ALARM | J1: GEN2 | K1: RUN HR | L1: Fuel Counter Index | M1: Cons /day | N1: Diesel L/H | P1: next service | Q1: ALARM | R1: GEN3 | S1: RUN HR | T1: Fuel Counter Index | U1: Cons /day | V1: Diesel L/H | X1: next service | Y1: ALARM | Z1: RH total | AA1: Gen Con /day | AB1: Total Deisel Cons/day | AC1: H /L | AD1: TOAL KW GEN | AI1: fuel Consuption | AK1: AVG KW/h
A2: =ELEC!C2 -> 44227 | B2: =[2]GEN!B33 -> 9538 | C2: =[2]GEN!C33 -> 3 | D2: =[2]GEN!D33 -> 311030.8 | E2: =[2]GEN!E33 -> 521.8 | F2: =[2]GEN!F33 -> 173.93333 | G2: =[2]GEN!G33 -> 0 | H2: 9729 | I2: =[2]GEN!I33 -> ok | J2: =[2]GEN!J33 -> 10698 | K2: =[2]GEN!K33 -> 0 | L2: =[2]GEN!L33 -> 357691 | M2: =[2]GEN!M33 -> 0 | N2: =[2]GEN!N33 -> 0 | O2: =[2]GEN!O33 -> 0 | P2: =[2]GEN!P33 -> 10873 | ... W2: =[2]GEN!W33 -> 0 | X2: 11898 | Y2: =[2]GEN!Y33 -> ok | Z2: =[2]GEN!Z33 -> 3 | AA2: =[2]GEN!AA33 -> 521.8 | AB2: =[2]GEN!AB33 -> 173.93333 | AC2: =[2]GEN!AC33 -> 173.93333 | AD2: =[2]GEN!AD33 -> 2007 | AE2: =[2]GEN!AE33 -> 669 | AF2: =[2]GEN!AF33 -> 0.418125 | ... AK2: =[2]GEN!AK33 -> 172.18987
A3: =ELEC!C3 -> 44228 | B3: 9541 | C3: =B3-B2 -> 3 | D3: 311569 | E3: =SUM(D3-D2) -> 538.2 | F3: =IF(C3>0,E3/C3,0) -> 179.4 | G3: =[5]GEN!G32 -> 0 | H3: =H2 -> 9729 | I3: =IF(B3-H3<=0,"ok","oil change") -> ok | J3: =J2 -> 10698 | K3: =J3-J2 -> 0 | L3: =L2 -> 357691 | M3: =SUM(L3-L2) -> 0 | N3: =IF(K3>0,M3/K3,0) -> 0 | O3: =[5]GEN!O32 -> 0 | P3: =P2 -> 10873 | Q3: =IF(J3-P3<=0,"ok","oil change") -> ok | R3: =R2 -> 11798 | S3: =R3-R2 -> 0 | T3: =T2 -> 379229 | U3: =SUM(T3-T2) -> 0 | V3: =IF(S3>0,U3/S3,0) -> 0 | W3: =[5]GEN!W32 -> 0 | X3: =X2 -> 11898 | Y3: =IF(R3-X3<=0,"ok","oil change") -> ok | Z3: =C3+K3+S3 -> 3 | AA3: =U3+M3+E3 -> 538.2 | AB3: =V3+N3+F3 -> 179.4 | AC3: =IF(Z3>0,AA3/Z3,0) -> 179.4 | AD3: =ELEC!Q3 -> 1968 | AE3: =SUM(AD3/Z3) -> 656 | AF3: =SUM(AE3/1600) -> 0.41 | AG3: =SUM(360*AF3) -> 147.6 | AH3: =SUM(AC3-AG3) -> 31.8 | AI3: =AD3*AJ3 -> 506.53165 | AJ3: =305/1185 -> 0.25738397 | AK3: =AI3/Z3 -> 168.84388
A4: =ELEC!C4 -> 44229 | B4: 9545 | C4: =B4-B3 -> 4 | D4: 312307 | E4: =SUM(D4-D3) -> 738 | F4: =IF(C4>0,E4/C4,0) -> 184.5 | H4: =H3 -> 9729 | I4: =IF(B4-H4<=0,"ok","oil change") -> ok | J4: =J3 -> 10698 | K4: =J4-J3 -> 0 | L4: =L3 -> 357691 | M4: =SUM(L4-L3) -> 0 | N4: =IF(K4>0,M4/K4,0) -> 0 | P4: =P3 -> 10873 | Q4: =IF(J4-P4<=0,"ok","oil change") -> ok | R4: =R3 -> 11798 | S4: =R4-R3 -> 0 | T4: =T3 -> 379229 | U4: =SUM(T4-T3) -> 0 | V4: =IF(S4>0,U4/S4,0) -> 0 | X4: =X3 -> 11898 | Y4: =IF(R4-X4<=0,"ok","oil change") -> ok | Z4: =C4+K4+S4 -> 4 | AA4: =U4+M4+E4 -> 738 | AB4: =V4+N4+F4 -> 184.5 | AC4: =IF(Z4>0,AA4/Z4,0) -> 184.5 | AD4: =ELEC!Q4 -> 2255 | AE4: =SUM(AD4/Z4) -> 563.75 | AF4: =SUM(AE4/1600) -> 0.35234375 | AG4: =SUM(360*AF4) -> 126.84375 | AH4: =SUM(AC4-AG4) -> 57.65625 | AI4: =AD4*AJ4 -> 580.40084 | AJ4: =305/1185 -> 0.25738397 | AK4: =AI4/Z4 -> 145.10021
A5: =ELEC!C5 -> 44230 | B5: 9549 | C5: =B5-B4 -> 4 | D5: 312999 | E5: =SUM(D5-D4) -> 692 | F5: =IF(C5>0,E5/C5,0) -> 173 | H5: =H4 -> 9729 | I5: =IF(B5-H5<=0,"ok","oil change") -> ok | J5: =J4 -> 10698 | K5: =J5-J4 -> 0 | L5: =L4 -> 357691 | M5: =SUM(L5-L4) -> 0 | N5: =IF(K5>0,M5/K5,0) -> 0 | P5: =P4 -> 10873 | Q5: =IF(J5-P5<=0,"ok","oil change") -> ok | R5: =R4 -> 11798 | S5: =R5-R4 -> 0 | T5: =T4 -> 379229 | U5: =SUM(T5-T4) -> 0 | V5: =IF(S5>0,U5/S5,0) -> 0 | X5: =X4 -> 11898 | Y5: =IF(R5-X5<=0,"ok","oil change") -> ok | Z5: =C5+K5+S5 -> 4 | AA5: =U5+M5+E5 -> 692 | AB5: =V5+N5+F5 -> 173 | AC5: =IF(Z5>0,AA5/Z5,0) -> 173 | AD5: =ELEC!Q5 -> 2921 | AE5: =SUM(AD5/Z5) -> 730.25 | AF5: =SUM(AE5/1600) -> 0.45640625 | AG5: =SUM(320*AF5) -> 146.05 | AH5: =SUM(AC5-AG5) -> 26.95 | AI5: =AD5*AJ5 -> 751.81857 | AJ5: =305/1185 -> 0.25738397 | AK5: =AI5/Z5 -> 187.95464
A6: =ELEC!C6 -> 44231 | B6: 9553 | C6: =B6-B5 -> 4 | D6: 313688 | E6: =SUM(D6-D5) -> 689 | F6: =IF(C6>0,E6/C6,0) -> 172.25 | H6: =H5 -> 9729 | I6: =IF(B6-H6<=0,"ok","oil change") -> ok | J6: =J5 -> 10698 | K6: =J6-J5 -> 0 | L6: =L5 -> 357691 | M6: =SUM(L6-L5) -> 0 | N6: =IF(K6>0,M6/K6,0) -> 0 | P6: =P5 -> 10873 | Q6: =IF(J6-P6<=0,"ok","oil change") -> ok | R6: =R5 -> 11798 | S6: =R6-R5 -> 0 | T6: =T5 -> 379229 | U6: =SUM(T6-T5) -> 0 | V6: =IF(S6>0,U6/S6,0) -> 0 | X6: =X5 -> 11898 | Y6: =IF(R6-X6<=0,"ok","oil change") -> ok | Z6: =C6+K6+S6 -> 4 | AA6: =U6+M6+E6 -> 689 | AB6: =V6+N6+F6 -> 172.25 | AC6: =IF(Z6>0,AA6/Z6,0) -> 172.25 | AD6: =ELEC!Q6 -> 2624 | AE6: =SUM(AD6/Z6) -> 656 | AF6: =SUM(AE6/1600) -> 0.41 | AG6: =SUM(320*AF6) -> 131.2 | AH6: =SUM(AC6-AG6) -> 41.05 | AI6: =AD6*AJ6 -> 675.37553 | AJ6: =305/1185 -> 0.25738397 | AK6: =AI6/Z6 -> 168.84388
A7: =ELEC!C7 -> 44232 | B7: 9556 | C7: =B7-B6 -> 3 | D7: 314232 | E7: =SUM(D7-D6) -> 544 | F7: =IF(C7>0,E7/C7,0) -> 181.33333 | H7: =H6 -> 9729 | I7: =IF(B7-H7<=0,"ok","oil change") -> ok | J7: =J6 -> 10698 | K7: =J7-J6 -> 0 | L7: =L6 -> 357691 | M7: =SUM(L7-L6) -> 0 | N7: =IF(K7>0,M7/K7,0) -> 0 | P7: =P6 -> 10873 | Q7: =IF(J7-P7<=0,"ok","oil change") -> ok | R7: 11798 | S7: =R7-R6 -> 0 | T7: =T6 -> 379229 | U7: =SUM(T7-T6) -> 0 | V7: =IF(S7>0,U7/S7,0) -> 0 | X7: =X6 -> 11898 | Y7: =IF(R7-X7<=0,"ok","oil change") -> ok | Z7: =C7+K7+S7 -> 3 | AA7: =U7+M7+E7 -> 544 | AB7: =V7+N7+F7 -> 181.33333 | AC7: =IF(Z7>0,AA7/Z7,0) -> 181.33333 | AD7: =ELEC!Q7 -> 1965 | AE7: =SUM(AD7/Z7) -> 655 | AF7: =SUM(AE7/1600) -> 0.409375 | AH7: =SUM(AC7-AG7) -> #VALUE! | AI7: =AD7*AJ7 -> 505.75949 | AJ7: =305/1185 -> 0.25738397 | AK7: =AI7/Z7 -> 168.5865
A8: =ELEC!C8 -> 44233 | B8: 9559 | C8: =B8-B7 -> 3 | D8: 314706 | E8: =SUM(D8-D7) -> 474 | F8: =IF(C8>0,E8/C8,0) -> 158 | H8: =H7 -> 9729 | I8: =IF(B8-H8<=0,"ok","oil change") -> ok | J8: =J7 -> 10698 | K8: =J8-J7 -> 0 | L8: =L7 -> 357691 | M8: =SUM(L8-L7) -> 0 | N8: =IF(K8>0,M8/K8,0) -> 0 | P8: =P7 -> 10873 | Q8: =IF(J8-P8<=0,"ok","oil change") -> ok | R8: =R7 -> 11798 | S8: =R8-R7 -> 0 | T8: =T7 -> 379229 | U8: =SUM(T8-T7) -> 0 | V8: =IF(S8>0,U8/S8,0) -> 0 | X8: =X7 -> 11898 | Y8: =IF(R8-X8<=0,"ok","oil change") -> ok | Z8: =C8+K8+S8 -> 3 | AA8: =U8+M8+E8 -> 474 | AB8: =V8+N8+F8 -> 158 | AC8: =IF(Z8>0,AA8/Z8,0) -> 158 | AD8: =ELEC!Q8 -> 1694 | AE8: =SUM(AD8/Z8) -> 564.66667 | AF8: =SUM(AE8/1600) -> 0.35291667 | AG8: =SUM(320*AF8) -> 112.93333 | AH8: =SUM(AC8-AG8) -> 45.066667 | AI8: =AD8*AJ8 -> 436.00844 | AJ8: =305/1185 -> 0.25738397 | AK8: =AI8/Z8 -> 145.33615
A9: =ELEC!C9 -> 44234 | B9: 9562 | C9: =B9-B8 -> 3 | D9: 315186 | E9: =SUM(D9-D8) -> 480 | F9: =IF(C9>0,E9/C9,0) -> 160 | H9: 9729 | I9: =IF(B9-H9<=0,"ok","oil change") -> ok | J9: =J8 -> 10698 | K9: =J9-J8 -> 0 | L9: =L8 -> 357691 | M9: =SUM(L9-L8) -> 0 | N9: =IF(K9>0,M9/K9,0) -> 0 | P9: =P8 -> 10873 | Q9: =IF(J9-P9<=0,"ok","oil change") -> ok | R9: =R8 -> 11798 | S9: =R9-R8 -> 0 | T9: =T8 -> 379229 | U9: =SUM(T9-T8) -> 0 | V9: =IF(S9>0,U9/S9,0) -> 0 | X9: =X8 -> 11898 | Y9: =IF(R9-X9<=0,"ok","oil change") -> ok | Z9: =C9+K9+S9 -> 3 | AA9: =U9+M9+E9 -> 480 | AB9: =V9+N9+F9 -> 160 | AC9: =IF(Z9>0,AA9/Z9,0) -> 160 | AD9: =ELEC!Q9 -> 2044 | AE9: =SUM(AD9/Z9) -> 681.33333 | AF9: =SUM(AE9/1600) -> 0.42583333 | AG9: =SUM(320*AF9) -> 136.26667 | AH9: =SUM(AC9-AG9) -> 23.733333 | AI9: =AD9*AJ9 -> 526.09283 | AJ9: 0.25738397 | AK9: =IF(Z9>0,AI9/Z9,0) -> 175.36428
A10: =ELEC!C10 -> 44235 | B10: 9565 | C10: =B10-B9 -> 3 | D10: 315670 | E10: =SUM(D10-D9) -> 484 | F10: =IF(C10>0,E10/C10,0) -> 161.33333 | H10: =H9 -> 9729 | I10: =IF(B10-H10<=0,"ok","oil change") -> ok | J10: =J9 -> 10698 | K10: =J10-J9 -> 0 | L10: =L9 -> 357691 | M10: =SUM(L10-L9) -> 0 | N10: =IF(K10>0,M10/K10,0) -> 0 | P10: =P9 -> 10873 | Q10: =IF(J10-P10<=0,"ok","oil change") -> ok | R10: =R9 -> 11798 | S10: =R10-R9 -> 0 | T10: =T9 -> 379229 | U10: =SUM(T10-T9) -> 0 | V10: =IF(S10>0,U10/S10,0) -> 0 | X10: =X9 -> 11898 | Y10: =IF(R10-X10<=0,"ok","oil change") -> ok | Z10: =C10+K10+S10 -> 3 | AA10: =U10+M10+E10 -> 484 | AB10: =V10+N10+F10 -> 161.33333 | AC10: =IF(Z10>0,AA10/Z10,0) -> 161.33333 | AD10: =ELEC!Q10 -> 2045 | AE10: =SUM(AD10/Z10) -> 681.66667 | AF10: =SUM(AE10/1600) -> 0.42604167 | AG10: =SUM(320*AF10) -> 136.33333 | AH10: =SUM(AC10-AG10) -> 25 | AI10: =AD10*AJ10 -> 526.35021 | AJ10: =305/1185 -> 0.25738397 | AK10: =IF(Z10>0,AI10/Z10,0) -> 175.45007
A11: =ELEC!C11 -> 44236 | B11: 9570 | C11: =B11-B10 -> 5 | D11: 316363 | E11: =SUM(D11-D10) -> 693 | F11: =IF(C11>0,E11/C11,0) -> 138.6 | H11: =H10 -> 9729 | I11: =IF(B11-H11<=0,"ok","oil change") -> ok | J11: =J10 -> 10698 | K11: =J11-J10 -> 0 | L11: =L10 -> 357691 | M11: =SUM(L11-L10) -> 0 | N11: =IF(K11>0,M11/K11,0) -> 0 | P11: =P10 -> 10873 | Q11: =IF(J11-P11<=0,"ok","oil change") -> ok | R11: =R10 -> 11798 | S11: =R11-R10 -> 0 | T11: =T10 -> 379229 | U11: =SUM(T11-T10) -> 0 | V11: =IF(S11>0,U11/S11,0) -> 0 | X11: =X10 -> 11898 | Y11: =IF(R11-X11<=0,"ok","oil change") -> ok | Z11: =C11+K11+S11 -> 5 | AA11: =U11+M11+E11 -> 693 | AB11: =V11+N11+F11 -> 138.6 | AC11: =IF(Z11>0,AA11/Z11,0) -> 138.6 | AD11: =ELEC!Q11 -> 3436 | AE11: =SUM(AD11/Z11) -> 687.2 | AF11: =SUM(AE11/1600) -> 0.4295 | AG11: =SUM(320*AF11) -> 137.44 | AH11: =SUM(AC11-AG11) -> 1.16 | AI11: =AD11*AJ11 -> 884.37131 | AJ11: =305/1185 -> 0.25738397 | AK11: =IF(Z11>0,AI11/Z11,0) -> 176.87426
A12: =ELEC!C12 -> 44237 | B12: 9577 | C12: =B12-B11 -> 7 | D12: 317389 | E12: =SUM(D12-D11) -> 1026 | F12: =IF(C12>0,E12/C12,0) -> 146.57143 | H12: =H11 -> 9729 | I12: =IF(B12-H12<=0,"ok","oil change") -> ok | J12: =J11 -> 10698 | K12: =J12-J11 -> 0 | L12: =L11 -> 357691 | M12: =SUM(L12-L11) -> 0 | N12: =IF(K12>0,M12/K12,0) -> 0 | P12: =P11 -> 10873 | Q12: =IF(J12-P12<=0,"ok","oil change") -> ok | R12: =R11 -> 11798 | S12: =R12-R11 -> 0 | T12: =T11 -> 379229 | U12: =SUM(T12-T11) -> 0 | V12: =IF(S12>0,U12/S12,0) -> 0 | X12: =X11 -> 11898 | Y12: =IF(R12-X12<=0,"ok","oil change") -> ok | Z12: =C12+K12+S12 -> 7 | AA12: =U12+M12+E12 -> 1026 | AB12: =V12+N12+F12 -> 146.57143 | AC12: =IF(Z12>0,AA12/Z12,0) -> 146.57143 | AD12: =ELEC!Q12 -> 4442 | AE12: =SUM(AD12/Z12) -> 634.57143 | AF12: =SUM(AE12/1600) -> 0.39660714 | AG12: =SUM(320*AF12) -> 126.91429 | AH12: =SUM(AC12-AG12) -> 19.657143 | AI12: =AD12*AJ12 -> 1143.2996 | AJ12: =305/1185 -> 0.25738397 | AK12: =IF(Z12>0,AI12/Z12,0) -> 163.32851
A13: =ELEC!C13 -> 44238 | B13: 9580 | C13: =B13-B12 -> 3 | D13: 317818 | E13: =SUM(D13-D12) -> 429 | F13: =IF(C13>0,E13/C13,0) -> 143 | H13: =H12 -> 9729 | I13: =IF(B13-H13<=0,"ok","oil change") -> ok | J13: =J12 -> 10698 | K13: =J13-J12 -> 0 | L13: =L12 -> 357691 | M13: =SUM(L13-L12) -> 0 | N13: =IF(K13>0,M13/K13,0) -> 0 | P13: =P12 -> 10873 | Q13: =IF(J13-P13<=0,"ok","oil change") -> ok | R13: 11801 | S13: =R13-R12 -> 3 | T13: =T12+429 -> 379658 | U13: =SUM(T13-T12) -> 429 | V13: =IF(S13>0,U13/S13,0) -> 143 | X13: =X12 -> 11898 | Y13: =IF(R13-X13<=0,"ok","oil change") -> ok | Z13: =C13+K13+S13 -> 6 | AA13: =U13+M13+E13 -> 858 | AB13: =V13+N13+F13 -> 286 | AC13: =IF(Z13>0,AA13/Z13,0) -> 143 | AD13: =ELEC!Q13 -> 3999 | AE13: =SUM(AD13/Z13) -> 666.5 | AF13: =SUM(AE13/1600) -> 0.4165625 | AG13: =SUM(320*AF13) -> 133.3 | AH13: =SUM(AC13-AG13) -> 9.7 | AI13: =AD13*AJ13 -> 1029.2785 | AJ13: =305/1185 -> 0.25738397 | AK13: =IF(Z13>0,AI13/Z13,0) -> 171.54641
A14: =ELEC!C14 -> 44239 | B14: 9584 | C14: =B14-B13 -> 4 | D14: 318396 | E14: =SUM(D14-D13) -> 578 | F14: =IF(C14>0,E14/C14,0) -> 144.5 | H14: =H13 -> 9729 | I14: =IF(B14-H14<=0,"ok","oil change") -> ok | J14: =J13 -> 10698 | K14: =J14-J13 -> 0 | L14: =L13 -> 357691 | M14: =SUM(L14-L13) -> 0 | N14: =IF(K14>0,M14/K14,0) -> 0 | P14: =P13 -> 10873 | Q14: =IF(J14-P14<=0,"ok","oil change") -> ok | R14: 11802 | S14: =R14-R13 -> 1 | T14: =T13+120 -> 379778 | U14: =SUM(T14-T13) -> 120 | V14: =IF(S14>0,U14/S14,0) -> 120 | X14: =X13 -> 11898 | Y14: =IF(R14-X14<=0,"ok","oil change") -> ok | Z14: =C14+K14+S14 -> 5 | AA14: =U14+M14+E14 -> 698 | AB14: =V14+N14+F14 -> 264.5 | AC14: =IF(Z14>0,AA14/Z14,0) -> 139.6 | AD14: =ELEC!Q14 -> 2628 | AE14: =SUM(AD14/Z14) -> 525.6 | AF14: =SUM(AE14/1600) -> 0.3285 | AG14: =SUM(320*AF14) -> 105.12 | AH14: =SUM(AC14-AG14) -> 34.48 | AI14: =AD14*AJ14 -> 676.40506 | AJ14: =305/1185 -> 0.25738397 | AK14: =IF(Z14>0,AI14/Z14,0) -> 135.28101
A15: =ELEC!C15 -> 44240 | B15: =B14 -> 9584 | C15: =B15-B14 -> 0 | D15: =D14 -> 318396 | E15: =SUM(D15-D14) -> 0 | F15: =IF(C15>0,E15/C15,0) -> 0 | H15: =H14 -> 9729 | I15: =IF(B15-H15<=0,"ok","oil change") -> ok | J15: =J14 -> 10698 | K15: =J15-J14 -> 0 | L15: =L14 -> 357691 | M15: =SUM(L15-L14) -> 0 | N15: =IF(K15>0,M15/K15,0) -> 0 | P15: =P14 -> 10873 | Q15: =IF(J15-P15<=0,"ok","oil change") -> ok | R15: =R14 -> 11802 | S15: =R15-R14 -> 0 | T15: =T14 -> 379778 | U15: =SUM(T15-T14) -> 0 | V15: =IF(S15>0,U15/S15,0) -> 0 | X15: =X14 -> 11898 | Y15: =IF(R15-X15<=0,"ok","oil change") -> ok | Z15: =C15+K15+S15 -> 0 | AA15: =U15+M15+E15 -> 0 | AB15: =V15+N15+F15 -> 0 | AC15: =IF(Z15>0,AA15/Z15,0) -> 0 | AD15: =ELEC!Q15 -> 0 | AE15: =SUM(AD15/Z15) -> #DIV/0! | AF15: =SUM(AE15/1600) -> #DIV/0! | AG15: =SUM(320*AF15) -> #DIV/0! | AH15: =SUM(AC15-AG15) -> #DIV/0! | AI15: =AD15*AJ15 -> 0 | AJ15: =305/1185 -> 0.25738397 | AK15: =IF(Z15>0,AI15/Z15,0) -> 0
A16: =ELEC!C16 -> 44241 | B16: =B15 -> 9584 | C16: =B16-B15 -> 0 | D16: =D15 -> 318396 | E16: =SUM(D16-D15) -> 0 | F16: =IF(C16>0,E16/C16,0) -> 0 | H16: =H15 -> 9729 | I16: =IF(B16-H16<=0,"ok","oil change") -> ok | J16: =J15 -> 10698 | K16: =J16-J15 -> 0 | L16: =L15 -> 357691 | M16: =SUM(L16-L15) -> 0 | N16: =IF(K16>0,M16/K16,0) -> 0 | P16: =P15 -> 10873 | Q16: =IF(J16-P16<=0,"ok","oil change") -> ok | R16: =R15 -> 11802 | S16: =R16-R15 -> 0 | T16: =T15 -> 379778 | U16: =SUM(T16-T15) -> 0 | V16: =IF(S16>0,U16/S16,0) -> 0 | X16: =X15 -> 11898 | Y16: =IF(R16-X16<=0,"ok","oil change") -> ok | Z16: =C16+K16+S16 -> 0 | AA16: =U16+M16+E16 -> 0 | AB16: =V16+N16+F16 -> 0 | AC16: =IF(Z16>0,AA16/Z16,0) -> 0 | AD16: =ELEC!Q16 -> 0 | AE16: =SUM(AD16/Z16) -> #DIV/0! | AF16: =SUM(AE16/1600) -> #DIV/0! | AG16: =SUM(320*AF16) -> #DIV/0! | AH16: =SUM(AC16-AG16) -> #DIV/0! | AI16: =AD16*AJ16 -> 0 | AJ16: =305/1185 -> 0.25738397 | AK16: =IF(Z16>0,AI16/Z16,0) -> 0
A17: =ELEC!C17 -> 44242 | B17: =B16 -> 9584 | C17: =B17-B16 -> 0 | D17: =D16 -> 318396 | E17: =SUM(D17-D16) -> 0 | F17: =IF(C17>0,E17/C17,0) -> 0 | H17: =H16 -> 9729 | I17: =IF(B17-H17<=0,"ok","oil change") -> ok | J17: =J16 -> 10698 | K17: =J17-J16 -> 0 | L17: =L16 -> 357691 | M17: =SUM(L17-L16) -> 0 | N17: =IF(K17>0,M17/K17,0) -> 0 | P17: =P16 -> 10873 | Q17: =IF(J17-P17<=0,"ok","oil change") -> ok | R17: =R16 -> 11802 | S17: =R17-R16 -> 0 | T17: =T16 -> 379778 | U17: =SUM(T17-T16) -> 0 | V17: =IF(S17>0,U17/S17,0) -> 0 | X17: =X16 -> 11898 | Y17: =IF(R17-X17<=0,"ok","oil change") -> ok | Z17: =C17+K17+S17 -> 0 | AA17: =U17+M17+E17 -> 0 | AB17: =V17+N17+F17 -> 0 | AC17: =IF(Z17>0,AA17/Z17,0) -> 0 | AD17: =ELEC!Q17 -> 0 | AE17: =SUM(AD17/Z17) -> #DIV/0! | AF17: =SUM(AE17/1600) -> #DIV/0! | AG17: =SUM(320*AF17) -> #DIV/0! | AH17: =SUM(AC17-AG17) -> #DIV/0! | AI17: =AD17*AJ17 -> 0 | AJ17: =305/1185 -> 0.25738397 | AK17: =IF(Z17>0,AI17/Z17,0) -> 0
A18: =ELEC!C18 -> 44243 | B18: =B17 -> 9584 | C18: =B18-B17 -> 0 | D18: =D17 -> 318396 | E18: =SUM(D18-D17) -> 0 | F18: =IF(C18>0,E18/C18,0) -> 0 | H18: =H17 -> 9729 | I18: =IF(B18-H18<=0,"ok","oil change") -> ok | J18: =J17 -> 10698 | K18: =J18-J17 -> 0 | L18: =L17 -> 357691 | M18: =SUM(L18-L17) -> 0 | N18: =IF(K18>0,M18/K18,0) -> 0 | P18: =P17 -> 10873 | Q18: =IF(J18-P14<=0,"ok","oil change") -> ok | R18: =R17 -> 11802 | S18: =R18-R17 -> 0 | T18: =T17 -> 379778 | U18: =SUM(T18-T17) -> 0 | V18: =IF(S18>0,U18/S18,0) -> 0 | X18: =X17 -> 11898 | Y18: =IF(R18-X18<=0,"ok","oil change") -> ok | Z18: =C18+K18+S18 -> 0 | AA18: =U18+M18+E18 -> 0 | AB18: =V18+N18+F18 -> 0 | AC18: =IF(Z18>0,AA18/Z18,0) -> 0 | AD18: =ELEC!Q18 -> 0 | AE18: =SUM(AD18/Z18) -> #DIV/0! | AF18: =SUM(AE18/1600) -> #DIV/0! | AG18: =SUM(320*AF18) -> #DIV/0! | AH18: =SUM(AC18-AG18) -> #DIV/0! | AI18: =AD18*AJ18 -> 0 | AJ18: =305/1185 -> 0.25738397 | AK18: =IF(Z18>0,AI18/Z18,0) -> 0
A19: =ELEC!C19 -> 44244 | B19: =B18 -> 9584 | C19: =B19-B18 -> 0 | D19: =D18 -> 318396 | E19: =SUM(D19-D18) -> 0 | F19: =IF(C19>0,E19/C19,0) -> 0 | H19: =H18 -> 9729 | I19: =IF(B19-H19<=0,"ok","oil change") -> ok | J19: =J18 -> 10698 | K19: =J19-J18 -> 0 | L19: =L18 -> 357691 | M19: =SUM(L19-L18) -> 0 | N19: =IF(K19>0,M19/K19,0) -> 0 | P19: =P18 -> 10873 | Q19: =IF(J19-P19<=0,"ok","oil change") -> ok | R19: =R18 -> 11802 | S19: =R19-R18 -> 0 | T19: =T18 -> 379778 | U19: =SUM(T19-T18) -> 0 | V19: =IF(S19>0,U19/S19,0) -> 0 | X19: =X18 -> 11898 | Y19: =IF(R19-X19<=0,"ok","oil change") -> ok | Z19: =C19+K19+S19 -> 0 | AA19: =U19+M19+E19 -> 0 | AB19: =V19+N19+F19 -> 0 | AC19: =IF(Z19>0,AA19/Z19,0) -> 0 | AD19: =ELEC!Q19 -> 0 | AE19: =SUM(AD19/Z19) -> #DIV/0! | AF19: =SUM(AE19/1600) -> #DIV/0! | AG19: =SUM(320*AF19) -> #DIV/0! | AH19: =SUM(AC19-AG19) -> #DIV/0! | AI19: =AD19*AJ19 -> 0 | AJ19: =305/1185 -> 0.25738397 | AK19: =IF(Z19>0,AI19/Z19,0) -> 0
A20: =ELEC!C20 -> 44245 | B20: =B19 -> 9584 | C20: =B20-B19 -> 0 | D20: =D19 -> 318396 | E20: =SUM(D20-D19) -> 0 | F20: =IF(C20>0,E20/C20,0) -> 0 | H20: =H19 -> 9729 | I20: =IF(B20-H20<=0,"ok","oil change") -> ok | J20: =J19 -> 10698 | K20: =J20-J19 -> 0 | L20: =L19 -> 357691 | M20: =SUM(L20-L19) -> 0 | N20: =IF(K20>0,M20/K20,0) -> 0 | P20: =P19 -> 10873 | Q20: =IF(J20-P20<=0,"ok","oil change") -> ok | R20: =R19 -> 11802 | S20: =R20-R19 -> 0 | T20: =T19 -> 379778 | U20: =SUM(T20-T19) -> 0 | V20: =IF(S20>0,U20/S20,0) -> 0 | X20: =X19 -> 11898 | Y20: =IF(R20-X20<=0,"ok","oil change") -> ok | Z20: =C20+K20+S20 -> 0 | AA20: =U20+M20+E20 -> 0 | AB20: =V20+N20+F20 -> 0 | AC20: =IF(Z20>0,AA20/Z20,0) -> 0 | AD20: =ELEC!Q20 -> 0 | AE20: =SUM(AD20/Z20) -> #DIV/0! | AF20: =SUM(AE20/1600) -> #DIV/0! | AG20: =SUM(320*AF20) -> #DIV/0! | AH20: =SUM(AC20-AG20) -> #DIV/0! | AI20: =AD20*AJ20 -> 0 | AJ20: =305/1185 -> 0.25738397 | AK20: =IF(Z20>0,AI20/Z20,0) -> 0
A21: =ELEC!C21 -> 44246 | B21: =B20 -> 9584 | C21: =B21-B20 -> 0 | D21: =D20 -> 318396 | E21: =SUM(D21-D20) -> 0 | F21: =IF(C21>0,E21/C21,0) -> 0 | H21: =H20 -> 9729 | I21: =IF(B21-H21<=0,"ok","oil change") -> ok | J21: =J20 -> 10698 | K21: =J21-J20 -> 0 | L21: =L20 -> 357691 | M21: =SUM(L21-L20) -> 0 | N21: =IF(K21>0,M21/K21,0) -> 0 | P21: =P20 -> 10873 | Q21: =IF(J21-P21<=0,"ok","oil change") -> ok | R21: =R20 -> 11802 | S21: =R21-R20 -> 0 | T21: =T20 -> 379778 | U21: =SUM(T21-T20) -> 0 | V21: =IF(S21>0,U21/S21,0) -> 0 | X21: =X20 -> 11898 | Y21: =Y20 -> ok | Z21: =C21+K21+S21 -> 0 | AA21: =U21+M21+E21 -> 0 | AB21: =V21+N21+F21 -> 0 | AC21: =IF(Z21>0,AA21/Z21,0) -> 0 | AD21: =ELEC!Q21 -> 0 | AE21: =SUM(AD21/Z21) -> #DIV/0! | AF21: =SUM(AE21/1600) -> #DIV/0! | AG21: =SUM(320*AF21) -> #DIV/0! | AH21: =SUM(AC21-AG21) -> #DIV/0! | AI21: =AD21*AJ21 -> 0 | AJ21: =305/1185 -> 0.25738397 | AK21: =IF(Z21>0,AI21/Z21,0) -> 0
A22: =ELEC!C22 -> 44247 | B22: =B21 -> 9584 | C22: =B22-B21 -> 0 | D22: =D21 -> 318396 | E22: =SUM(D22-D21) -> 0 | F22: =IF(C22>0,E22/C22,0) -> 0 | H22: =H21 -> 9729 | I22: =IF(B22-H22<=0,"ok","oil change") -> ok | J22: =J21 -> 10698 | K22: =J22-J21 -> 0 | L22: =L21 -> 357691 | M22: =SUM(L22-L21) -> 0 | N22: =IF(K22>0,M22/K22,0) -> 0 | P22: =P21 -> 10873 | Q22: =IF(J22-P22<=0,"ok","oil change") -> ok | R22: =R21 -> 11802 | S22: =R22-R21 -> 0 | T22: =T21 -> 379778 | U22: =SUM(T22-T21) -> 0 | V22: =IF(S22>0,U22/S22,0) -> 0 | X22: =X21 -> 11898 | Y22: =IF(R22-X22<=0,"ok","oil change") -> ok | Z22: =C22+K22+S22 -> 0 | AA22: =U22+M22+E22 -> 0 | AB22: =V22+N22+F22 -> 0 | AC22: =IF(Z22>0,AA22/Z22,0) -> 0 | AD22: =ELEC!Q22 -> 0 | AE22: =SUM(AD22/Z22) -> #DIV/0! | AF22: =SUM(AE22/1600) -> #DIV/0! | AG22: =SUM(320*AF22) -> #DIV/0! | AH22: =SUM(AC22-AG22) -> #DIV/0! | AI22: =AD22*AJ22 -> 0 | AJ22: =305/1185 -> 0.25738397 | AK22: =IF(Z22>0,AI22/Z22,0) -> 0
A23: =ELEC!C23 -> 44248 | B23: =B22 -> 9584 | C23: =B23-B22 -> 0 | D23: =D22 -> 318396 | E23: =SUM(D23-D22) -> 0 | F23: =IF(C23>0,E23/C23,0) -> 0 | H23: =H22 -> 9729 | I23: =IF(B23-H23<=0,"ok","oil change") -> ok | J23: =J22 -> 10698 | K23: =J23-J22 -> 0 | L23: =L22 -> 357691 | M23: =SUM(L23-L22) -> 0 | N23: =IF(K23>0,M23/K23,0) -> 0 | P23: =P22 -> 10873 | Q23: =IF(J23-P23<=0,"ok","oil change") -> ok | R23: =R22 -> 11802 | S23: =R23-R22 -> 0 | T23: =T22 -> 379778 | U23: =SUM(T23-T22) -> 0 | V23: =IF(S23>0,U23/S23,0) -> 0 | X23: =X22 -> 11898 | Y23: =IF(R23-X23<=0,"ok","oil change") -> ok | Z23: =C23+K23+S23 -> 0 | AA23: =U23+M23+E23 -> 0 | AB23: =V23+N23+F23 -> 0 | AC23: =IF(Z23>0,AA23/Z23,0) -> 0 | AD23: =ELEC!Q23 -> 0 | AE23: =SUM(AD23/Z23) -> #DIV/0! | AF23: =SUM(AE23/1600) -> #DIV/0! | AG23: =SUM(320*AF23) -> #DIV/0! | AH23: =SUM(AC23-AG23) -> #DIV/0! | AI23: =AD23*AJ23 -> 0 | AJ23: =305/1185 -> 0.25738397 | AK23: =IF(Z23>0,AI23/Z23,0) -> 0
A24: =ELEC!C24 -> 44249 | B24: =B23 -> 9584 | C24: =B24-B23 -> 0 | D24: =D23 -> 318396 | E24: =SUM(D24-D23) -> 0 | F24: =IF(C24>0,E24/C24,0) -> 0 | H24: =H23 -> 9729 | I24: =IF(B24-H24<=0,"ok","oil change") -> ok | J24: =J23 -> 10698 | K24: =J24-J23 -> 0 | L24: =L23 -> 357691 | M24: =SUM(L24-L23) -> 0 | N24: =IF(K24>0,M24/K24,0) -> 0 | P24: =P23 -> 10873 | Q24: =IF(J24-P24<=0,"ok","oil change") -> ok | R24: =R23 -> 11802 | S24: =R24-R23 -> 0 | T24: =T23 -> 379778 | U24: =SUM(T24-T23) -> 0 | V24: =IF(S24>0,U24/S24,0) -> 0 | X24: =X23 -> 11898 | Y24: =IF(R24-X24<=0,"ok","oil change") -> ok | Z24: =C24+K24+S24 -> 0 | AA24: =U24+M24+E24 -> 0 | AB24: =V24+N24+F24 -> 0 | AC24: =IF(Z24>0,AA24/Z24,0) -> 0 | AD24: =ELEC!Q24 -> 0 | AE24: =SUM(AD24/Z24) -> #DIV/0! | AF24: =SUM(AE24/1600) -> #DIV/0! | AG24: =SUM(320*AF24) -> #DIV/0! | AH24: =SUM(AC24-AG24) -> #DIV/0! | AI24: =AD24*AJ24 -> 0 | AJ24: =305/1185 -> 0.25738397 | AK24: =IF(Z24>0,AI24/Z24,0) -> 0
A25: =ELEC!C25 -> 44250 | B25: =B24 -> 9584 | C25: =B25-B24 -> 0 | D25: =D24 -> 318396 | E25: =SUM(D25-D24) -> 0 | F25: =IF(C25>0,E25/C25,0) -> 0 | H25: =H24 -> 9729 | I25: =IF(B25-H25<=0,"ok","oil change") -> ok | J25: =J24 -> 10698 | K25: =J25-J24 -> 0 | L25: =L24 -> 357691 | M25: =SUM(L25-L24) -> 0 | N25: =IF(K25>0,M25/K25,0) -> 0 | P25: =P24 -> 10873 | Q25: =IF(J25-P25<=0,"ok","oil change") -> ok | R25: =R24 -> 11802 | S25: =R25-R24 -> 0 | T25: =T24 -> 379778 | U25: =SUM(T25-T24) -> 0 | V25: =IF(S25>0,U25/S25,0) -> 0 | X25: =X24 -> 11898 | Y25: =IF(R25-X25<=0,"ok","oil change") -> ok | Z25: =C25+K25+S25 -> 0 | AA25: =U25+M25+E25 -> 0 | AB25: =V25+N25+F25 -> 0 | AC25: =IF(Z25>0,AA25/Z25,0) -> 0 | AD25: =ELEC!Q25 -> 0 | AE25: =SUM(AD25/Z25) -> #DIV/0! | AF25: =SUM(AE25/1600) -> #DIV/0! | AG25: =SUM(320*AF25) -> #DIV/0! | AH25: =SUM(AC25-AG25) -> #DIV/0! | AI25: =AD25*AJ25 -> 0 | AJ25: =305/1185 -> 0.25738397 | AK25: =IF(Z25>0,AI25/Z25,0) -> 0
A26: =ELEC!C26 -> 44251 | B26: =B25 -> 9584 | C26: =B26-B25 -> 0 | D26: =D25 -> 318396 | E26: =SUM(D26-D25) -> 0 | F26: =IF(C26>0,E26/C26,0) -> 0 | H26: =H25 -> 9729 | I26: =IF(B26-H26<=0,"ok","oil change") -> ok | J26: =J25 -> 10698 | K26: =J26-J25 -> 0 | L26: =L25 -> 357691 | M26: =SUM(L26-L25) -> 0 | N26: =IF(K26>0,M26/K26,0) -> 0 | P26: =P25 -> 10873 | Q26: =IF(J26-P26<=0,"ok","oil change") -> ok | R26: =R25 -> 11802 | S26: =R26-R25 -> 0 | T26: =T25 -> 379778 | U26: =SUM(T26-T25) -> 0 | V26: =IF(S26>0,U26/S26,0) -> 0 | X26: =X25 -> 11898 | Y26: =IF(R26-X26<=0,"ok","oil change") -> ok | Z26: =C26+K26+S26 -> 0 | AA26: =U26+M26+E26 -> 0 | AB26: =V26+N26+F26 -> 0 | AC26: =IF(Z26>0,AA26/Z26,0) -> 0 | AD26: =ELEC!Q26 -> 0 | AE26: =SUM(AD26/Z26) -> #DIV/0! | AF26: =SUM(AE26/1600) -> #DIV/0! | AG26: =SUM(320*AF26) -> #DIV/0! | AH26: =SUM(AC26-AG26) -> #DIV/0! | AI26: =AD26*AJ26 -> 0 | AJ26: =305/1185 -> 0.25738397 | AK26: =IF(Z26>0,AI26/Z26,0) -> 0
A27: =ELEC!C27 -> 44252 | B27: =B26 -> 9584 | C27: =B27-B26 -> 0 | D27: =D26 -> 318396 | E27: =SUM(D27-D26) -> 0 | F27: =IF(C27>0,E27/C27,0) -> 0 | H27: =H26 -> 9729 | I27: =IF(B27-H27<=0,"ok","oil change") -> ok | J27: =J26 -> 10698 | K27: =J27-J26 -> 0 | L27: =L26 -> 357691 | M27: =SUM(L27-L26) -> 0 | N27: =IF(K27>0,M27/K27,0) -> 0 | P27: =P26 -> 10873 | Q27: =IF(J27-P27<=0,"ok","oil change") -> ok | R27: =R26 -> 11802 | S27: =R27-R26 -> 0 | T27: =T26 -> 379778 | U27: =SUM(T27-T26) -> 0 | V27: =IF(S27>0,U27/S27,0) -> 0 | X27: =X26 -> 11898 | Y27: =IF(R27-X27<=0,"ok","oil change") -> ok | Z27: =C27+K27+S27 -> 0 | AA27: =U27+M27+E27 -> 0 | AB27: =V27+N27+F27 -> 0 | AC27: =IF(Z27>0,AA27/Z27,0) -> 0 | AD27: =ELEC!Q27 -> 0 | AE27: =SUM(AD27/Z27) -> #DIV/0! | AF27: =SUM(AE27/1600) -> #DIV/0! | AG27: =SUM(320*AF27) -> #DIV/0! | AH27: =SUM(AC27-AG27) -> #DIV/0! | AI27: =AD27*AJ27 -> 0 | AJ27: =305/1185 -> 0.25738397 | AK27: =IF(Z27>0,AI27/Z27,0) -> 0
A28: =ELEC!C28 -> 44253 | B28: =B27 -> 9584 | C28: =B28-B27 -> 0 | D28: =D27 -> 318396 | E28: =SUM(D28-D27) -> 0 | F28: =IF(C28>0,E28/C28,0) -> 0 | H28: =H27 -> 9729 | I28: =IF(B28-H28<=0,"ok","oil change") -> ok | J28: =J27 -> 10698 | K28: =J28-J27 -> 0 | L28: =L27 -> 357691 | M28: =SUM(L28-L27) -> 0 | N28: =IF(K28>0,M28/K28,0) -> 0 | P28: =P27 -> 10873 | Q28: =IF(J28-P28<=0,"ok","oil change") -> ok | R28: =R27 -> 11802 | S28: =R28-R27 -> 0 | T28: =T27 -> 379778 | U28: =SUM(T28-T27) -> 0 | V28: =IF(S28>0,U28/S28,0) -> 0 | X28: =X27 -> 11898 | Y28: =IF(R28-X28<=0,"ok","oil change") -> ok | Z28: =C28+K28+S28 -> 0 | AA28: =U28+M28+E28 -> 0 | AB28: =V28+N28+F28 -> 0 | AC28: =IF(Z28>0,AA28/Z28,0) -> 0 | AD28: =ELEC!Q28 -> 0 | AE28: =SUM(AD28/Z28) -> #DIV/0! | AF28: =SUM(AE28/1600) -> #DIV/0! | AG28: =SUM(320*AF28) -> #DIV/0! | AH28: =SUM(AC28-AG28) -> #DIV/0! | AI28: =AD28*AJ28 -> 0 | AJ28: =305/1185 -> 0.25738397 | AK28: =IF(Z28>0,AI28/Z28,0) -> 0
A29: =ELEC!C29 -> 44254 | B29: =B28 -> 9584 | C29: =B29-B28 -> 0 | D29: =D28 -> 318396 | E29: =SUM(D29-D28) -> 0 | F29: =IF(C29>0,E29/C29,0) -> 0 | H29: =H28 -> 9729 | I29: =IF(B29-H29<=0,"ok","oil change") -> ok | J29: =J28 -> 10698 | K29: =J29-J28 -> 0 | L29: =L28 -> 357691 | M29: =SUM(L29-L28) -> 0 | N29: =IF(K29>0,M29/K29,0) -> 0 | P29: =P28 -> 10873 | Q29: =IF(J29-P29<=0,"ok","oil change") -> ok | R29: =R28 -> 11802 | S29: =R29-R28 -> 0 | T29: =T28 -> 379778 | U29: =SUM(T29-T28) -> 0 | V29: =IF(S29>0,U29/S29,0) -> 0 | X29: =X28 -> 11898 | Y29: =IF(R29-X29<=0,"ok","oil change") -> ok | Z29: =C29+K29+S29 -> 0 | AA29: =U29+M29+E29 -> 0 | AB29: =V29+N29+F29 -> 0 | AC29: =IF(Z29>0,AA29/Z29,0) -> 0 | AD29: =ELEC!Q29 -> 0 | AE29: =SUM(AD29/Z29) -> #DIV/0! | AF29: =SUM(AE29/1600) -> #DIV/0! | AG29: =SUM(320*AF29) -> #DIV/0! | AH29: =SUM(AC29-AG29) -> #DIV/0! | AI29: =AD29*AJ29 -> 0 | AJ29: =305/1185 -> 0.25738397 | AK29: =IF(Z29>0,AI29/Z29,0) -> 0
A30: =ELEC!C30 -> 44255 | B30: =B29 -> 9584 | C30: =B30-B29 -> 0 | D30: =D29 -> 318396 | E30: =SUM(D30-D29) -> 0 | F30: =IF(C30>0,E30/C30,0) -> 0 | H30: =H29 -> 9729 | I30: =IF(B30-H30<=0,"ok","oil change") -> ok | J30: =J29 -> 10698 | K30: =J30-J29 -> 0 | L30: =L29 -> 357691 | M30: =SUM(L30-L29) -> 0 | N30: =IF(K30>0,M30/K30,0) -> 0 | P30: =P29 -> 10873 | Q30: =IF(J30-P30<=0,"ok","oil change") -> ok | R30: =R29 -> 11802 | S30: =R30-R29 -> 0 | T30: =T29 -> 379778 | U30: =SUM(T30-T29) -> 0 | V30: =IF(S30>0,U30/S30,0) -> 0 | X30: =X29 -> 11898 | Y30: =IF(R30-X30<=0,"ok","oil change") -> ok | Z30: =C30+K30+S30 -> 0 | AA30: =U30+M30+E30 -> 0 | AB30: =V30+N30+F30 -> 0 | AC30: =IF(Z30>0,AA30/Z30,0) -> 0 | AD30: =ELEC!Q30 -> 0 | AE30: =SUM(AD30/Z30) -> #DIV/0! | AF30: =SUM(AE30/1600) -> #DIV/0! | AG30: =SUM(320*AF30) -> #DIV/0! | AH30: =SUM(AC30-AG30) -> #DIV/0! | AI30: =AD30*AJ30 -> 0 | AJ30: =305/1185 -> 0.25738397 | AK30: =IF(Z30>0,AI30/Z30,0) -> 0
P31: =+O31/3 -> 0 | U31: =SUM(C32:S32) -> 50 | X31: 341 | Z31: =SUM(Z3:Z30) -> 50
C32: =SUM(C3:C30) -> 46 | K32: =SUM(K3:K30) -> 0 | S32: =SUM(S3:S30) -> 4

Sheet EDl log
A1: Date | B1: EDL | C1: Conso EDL KW | F1: Peak | G1: 320 | H1: Day | I1: 112 | J1: Night | K1: 80
L2: P | M2: D | N2: N | O2: fee | P2: T EDL | Q2: Gen | R2: Elc C
A3: =ELEC!C2 -> 44227 | B3: ='[2]EDl log'!B34 -> 853626 | C3: ='[2]EDl log'!C34 -> 2345 | D3: ='[2]EDl log'!D34 -> 2346 | E3: ='[2]EDl log'!E34 -> 853627 | F3: 128729 | G3: ='[2]EDl log'!G34 -> 446 | H3: 426042 | I3: ='[2]EDl log'!I34 -> 935 | J3: 298855 | K3: ='[2]EDl log'!K34 -> 965 | L3: ='[2]EDl log'!L34 -> 94.6733 | M3: ='[2]EDl log'!M34 -> 69.466003 | N3: ='[2]EDl log'!N34 -> 51.210614 | O3: ='[2]EDl log'!O34 -> 154.80304 | P3: ='[2]EDl log'!P34 -> 370.15296 | Q3: ='[2]EDl log'!Q34 -> 431.00129 | R3: ='[2]EDl log'!R34 -> 801.15425 | ... T3: ='[2]EDl log'!T34 -> 0.12622566 | Z3: VAT | AA3: 0.1
A4: =ELEC!C3 -> 44228 | B4: 856126 | C4: =SUM(B4-B3) -> 2500 | D4: =SUM(G4+I4+K4) -> 2499 | E4: =B3+D4 -> 856125 | F4: 129225 | G4: =F4-F3 -> 496 | H4: 427118 | I4: =H4-H3 -> 1076 | J4: 299782 | K4: =J4-J3 -> 927 | L4: =SUM(G4*$Y$28)/1507.5 -> 105.2869 | M4: =SUM(I4*$Y$27)/1507.5 -> 79.941625 | N4: =SUM(K4*$Y$26)/1507.5 -> 49.19403 | O4: =($AC$31/$A$34)/1507.5 -> 73.452462 | P4: =SUM(L4:O4) -> 307.87502 | Q4: =SUM(-tanks!AX6*tanks!$AU$34) -> 293.81415 | R4: =SUM(P4:Q4) -> 601.68916 | S4: =SUM(ELEC!N3) -> 6404.4 | T4: =IF(S4>0,R4/S4,0) -> 0.093949341 | V4: ='[6]EDl log'!V21 -> EDL | W4: 44197 | Z4: Subscription
A5: =ELEC!C4 -> 44229 | B5: 858354 | C5: =SUM(B5-B4) -> 2228 | D5: =SUM(G5+I5+K5) -> 2229 | E5: =B4+D5 -> 858355 | F5: 129716 | G5: =F5-F4 -> 491 | H5: 428204 | I5: =H5-H4 -> 1086 | J5: 300434 | K5: =J5-J4 -> 652 | L5: =SUM(G5*$Y$28)/1507.5 -> 104.22554 | M5: =SUM(I5*$Y$27)/1507.5 -> 80.684577 | N5: =SUM(K5*$Y$26)/1507.5 -> 34.600332 | O5: =($AC$31/$A$34)/1507.5 -> 73.452462 | P5: =SUM(L5:O5) -> 292.96291 | Q5: =SUM(-tanks!AX7*tanks!$AU$34) -> 265.49448 | R5: =SUM(P5:Q5) -> 558.45739 | S5: =SUM(ELEC!N4) -> 6622 | T5: =IF(S5>0,R5/S5,0) -> 0.084333644 | Z5: KVA | AA5: ='[7]EDl log'!AA22 -> 5000
A6: =ELEC!C5 -> 44230 | B6: 860441 | C6: =SUM(B6-B5) -> 2087 | D6: =SUM(G6+I6+K6) -> 2086 | E6: =B5+D6 -> 860440 | F6: 129935 | G6: =F6-F5 -> 219 | H6: 429188 | I6: =H6-H5 -> 984 | J6: 301317 | K6: =J6-J5 -> 883 | L6: =SUM(G6*$Y$28)/1507.5 -> 46.487562 | M6: =SUM(I6*$Y$27)/1507.5 -> 73.106468 | N6: =SUM(K6*$Y$26)/1507.5 -> 46.859038 | O6: =($AC$31/$A$34)/1507.5 -> 73.452462 | P6: =SUM(L6:O6) -> 239.90553 | Q6: =SUM(-tanks!AX8*tanks!$AU$34) -> 362.89365 | R6: =SUM(P6:Q6) -> 602.79918 | S6: =SUM(ELEC!N5) -> 6753 | T6: =IF(S6>0,R6/S6,0) -> 0.089263909
A7: =ELEC!C6 -> 44231 | B7: 862596 | C7: =SUM(B7-B6) -> 2155 | D7: =SUM(G7+I7+K7) -> 2155 | E7: =B6+D7 -> 862596 | F7: 130413 | G7: =F7-F6 -> 478 | H7: 430047 | I7: =H7-H6 -> 859 | J7: 302135 | K7: =J7-J6 -> 818 | L7: =SUM(G7*$Y$28)/1507.5 -> 101.466 | M7: =SUM(I7*$Y$27)/1507.5 -> 63.819569 | N7: =SUM(K7*$Y$26)/1507.5 -> 43.409619 | O7: =($AC$31/$A$34)/1507.5 -> 73.452462 | P7: =SUM(L7:O7) -> 282.14765 | Q7: =SUM(-tanks!AX9*tanks!$AU$34) -> 353.21865 | R7: =SUM(P7:Q7) -> 635.3663 | S7: =SUM(ELEC!N6) -> 6587 | T7: =IF(S7>0,R7/S7,0) -> 0.096457613 | V7: Electricity consumption | X7: Price LL
A8: =ELEC!C7 -> 44232 | B8: 864742 | C8: =SUM(B8-B7) -> 2146 | D8: =SUM(G8+I8+K8) -> 2147 | E8: =B7+D8 -> 864743 | F8: 130838 | G8: =F8-F7 -> 425 | H8: 430939 | I8: =H8-H7 -> 892 | J8: 302965 | K8: =J8-J7 -> 830 | L8: =SUM(G8*$Y$28)/1507.5 -> 90.215589 | M8: =SUM(I8*$Y$27)/1507.5 -> 66.27131 | N8: =SUM(K8*$Y$26)/1507.5 -> 44.046434 | O8: =($AC$31/$A$34)/1507.5 -> 73.452462 | P8: =SUM(L8:O8) -> 273.9858 | Q8: =SUM(-tanks!AX10*tanks!$AU$34) -> -172.06519 | R8: =SUM(P8:Q8) -> 101.9206 | S8: =SUM(ELEC!N7) -> 5932 | T8: =IF(S8>0,R8/S8,0) -> 0.017181491 | V8: Index in | W8: Index Out | Y8: Kwh Cost | Z8: K | AA8: Kwh | AB8: ='[8]EDl log'!AB25 -> Total cost LL | AC8: Fees
A9: =ELEC!C8 -> 44233 | B9: 867071 | C9: =SUM(B9-B8) -> 2329 | D9: =SUM(G9+I9+K9) -> 2329 | E9: =B8+D9 -> 867071 | F9: 131316 | G9: =F9-F8 -> 478 | H9: 431779 | I9: =H9-H8 -> 840 | J9: 303976 | K9: =J9-J8 -> 1011 | L9: =SUM(G9*$Y$28)/1507.5 -> 101.466 | M9: =SUM(I9*$Y$27)/1507.5 -> 62.40796 | N9: =SUM(K9*$Y$26)/1507.5 -> 53.651741 | O9: =($AC$31/$A$34)/1507.5 -> 73.452462 | P9: =SUM(L9:O9) -> 290.97817 | Q9: =SUM(-tanks!AX11*tanks!$AU$34) -> 208.60548 | R9: =SUM(P9:Q9) -> 499.58365 | S9: =SUM(ELEC!N8) -> 5977 | T9: =IF(S9>0,R9/S9,0) -> 0.083584348 | V9: ='[2]EDl log'!V26 -> 271580 | W9: ='[2]EDl log'!W26 -> 297890 | X9: ='[2]EDl log'!X26 -> Night | Y9: ='[2]EDl log'!Y26 -> 80 | Z9: ='[2]EDl log'!Z26 -> 1 | AA9: ='[2]EDl log'!AA26 -> 26310 | AB9: ='[2]EDl log'!AB26 -> 2104800 | AC9: ='[2]EDl log'!AC26 -> 1033333 | AD9: ='[2]EDl log'!AD26 -> 0.37186936
A10: =ELEC!C9 -> 44234 | B10: 869480 | C10: =SUM(B10-B9) -> 2409 | D10: =SUM(G10+I10+K10) -> 2408 | E10: =B9+D10 -> 869479 | F10: 131674 | G10: =F10-F9 -> 358 | H10: 432965 | I10: =H10-H9 -> 1186 | J10: 304840 | K10: =J10-J9 -> 864 | L10: =SUM(G10*$Y$28)/1507.5 -> 75.993367 | M10: =SUM(I10*$Y$27)/1507.5 -> 88.114096 | N10: =SUM(K10*$Y$26)/1507.5 -> 45.850746 | O10: =($AC$31/$A$34)/1507.5 -> 73.452462 | P10: =SUM(L10:O10) -> 283.41067 | Q10: =SUM(-tanks!AX12*tanks!$AU$34) -> 366.76365 | R10: =SUM(P10:Q10) -> 650.17432 | S10: =SUM(ELEC!N9) -> 6551.2 | T10: =IF(S10>0,R10/S10,0) -> 0.099245072 | V10: ='[2]EDl log'!V27 -> 393641 | W10: ='[2]EDl log'!W27 -> 425107 | X10: ='[2]EDl log'!X27 -> day | Y10: ='[2]EDl log'!Y27 -> 112 | Z10: ='[2]EDl log'!Z27 -> 1 | AA10: ='[2]EDl log'!AA27 -> 31466 | AB10: ='[2]EDl log'!AB27 -> 3524192 | AC10: ='[2]EDl log'!AC27 -> 6200000 | AD10: ='[2]EDl log'!AD27 -> 0.44290106
A11: =ELEC!C10 -> 44235 | B11: 871763 | C11: =SUM(B11-B10) -> 2283 | D11: =SUM(G11+I11+K11) -> 2293 | E11: =B10+D11 -> 871773 | F11: 132118 | G11: =F11-F10 -> 444 | H11: 433933 | I11: =H11-H10 -> 968 | J11: 305721 | K11: =J11-J10 -> 881 | L11: =SUM(G11*$Y$28)/1507.5 -> 94.248756 | M11: =SUM(I11*$Y$27)/1507.5 -> 71.917745 | N11: =SUM(K11*$Y$26)/1507.5 -> 46.752902 | O11: =($AC$31/$A$34)/1507.5 -> 73.452462 | P11: =SUM(L11:O11) -> 286.37187 | Q11: =SUM(-tanks!AX13*tanks!$AU$34) -> 227.02668 | R11: =SUM(P11:Q11) -> 513.39855 | S11: =SUM(ELEC!N10) -> 6289.8 | T11: =IF(S11>0,R11/S11,0) -> 0.081623986 | V11: ='[2]EDl log'!V28 -> 115015 | W11: ='[2]EDl log'!W28 -> 128283 | X11: ='[2]EDl log'!X28 -> Peak | Y11: ='[2]EDl log'!Y28 -> 320 | Z11: ='[2]EDl log'!Z28 -> 1 | AA11: ='[2]EDl log'!AA28 -> 13268 | AB11: ='[2]EDl log'!AB28 -> 4245760 | AC11: ='[2]EDl log'!AC28 -> 1000 | AD11: ='[2]EDl log'!AD28 -> 0.18524368 | AE11: =SUM(AB11*5%) -> 212288 | AF11: =SUM(AE11/7)*31 -> 940132.57
A12: =ELEC!C11 -> 44236 | B12: 873722 | C12: =SUM(B12-B11) -> 1959 | D12: =SUM(G12+I12+K12) -> 1950 | E12: =B11+D12 -> 873713 | F12: 132337 | G12: =F12-F11 -> 219 | H12: 434813 | I12: =H12-H11 -> 880 | J12: 306572 | K12: =J12-J11 -> 851 | L12: =SUM(G12*$Y$28)/1507.5 -> 46.487562 | M12: =SUM(I12*$Y$27)/1507.5 -> 65.379768 | N12: =SUM(K12*$Y$26)/1507.5 -> 45.160862 | O12: =($AC$31/$A$34)/1507.5 -> 73.452462 | P12: =SUM(L12:O12) -> 230.48065 | Q12: =SUM(-tanks!AX14*tanks!$AU$34) -> 383.40465 | R12: =SUM(P12:Q12) -> 613.8853 | S12: =SUM(ELEC!N11) -> 7008 | T12: =IF(S12>0,R12/S12,0) -> 0.087597788 | Z12: ='[9]EDl log'!Z29 -> 0 | AA12: ='[2]EDl log'!AA29 -> 71044 | AB12: ='[1]EDl log'!AB29 -> 0 | AC12: ='[1]EDl log'!AC29 -> 0 | AD12: ='[1]EDl log'!AD29 -> 0
A13: =ELEC!C12 -> 44237 | B13: 875296 | C13: =SUM(B13-B12) -> 1574 | D13: =SUM(G13+I13+K13) -> 1573 | E13: =B12+D13 -> 875295 | F13: 132662 | G13: =F13-F12 -> 325 | H13: 435479 | I13: =H13-H12 -> 666 | J13: 307154 | K13: =J13-J12 -> 582 | L13: =SUM(G13*$Y$28)/1507.5 -> 68.988391 | M13: =SUM(I13*$Y$27)/1507.5 -> 49.480597 | N13: =SUM(K13*$Y$26)/1507.5 -> 30.885572 | O13: =($AC$31/$A$34)/1507.5 -> 73.452462 | P13: =SUM(L13:O13) -> 222.80702 | Q13: =SUM(-tanks!AX15*tanks!$AU$34) -> 620.77297 | R13: =SUM(P13:Q13) -> 843.57999 | S13: =SUM(ELEC!N12) -> 7276 | T13: =IF(S13>0,R13/S13,0) -> 0.11594008 | V13: ='[7]EDl log'!V30 -> Occ % | W13: ='[2]EDl log'!W30 -> 0 | Y13: ='[4]EDl log'!Y30 -> Per G | AB13: ='[2]EDl log'!AB30 -> 9874752 | AC13: ='[2]EDl log'!AC30 -> 7234333
A14: =ELEC!C13 -> 44238 | B14: 877076 | C14: =SUM(B14-B13) -> 1780 | D14: =SUM(G14+I14+K14) -> 1780 | E14: =B13+D14 -> 877076 | F14: 132888 | G14: =F14-F13 -> 226 | H14: 436178 | I14: =H14-H13 -> 699 | J14: 308009 | K14: =J14-J13 -> 855 | L14: =SUM(G14*$Y$28)/1507.5 -> 47.973466 | M14: =SUM(I14*$Y$27)/1507.5 -> 51.932338 | N14: =SUM(K14*$Y$26)/1507.5 -> 45.373134 | O14: =($AC$31/$A$34)/1507.5 -> 73.452462 | P14: =SUM(L14:O14) -> 218.7314 | Q14: =SUM(-tanks!AX16*tanks!$AU$34) -> 495.50981 | R14: =SUM(P14:Q14) -> 714.24121 | S14: =SUM(ELEC!N13) -> 7236 | T14: =IF(S14>0,R14/S14,0) -> 0.098706635 | V14: ='[7]EDl log'!V31 -> Gen RH | W14: ='[2]EDl log'!W31 -> 112 | X14: ='[1]EDl log'!X31 -> 3.7419355 | Y14: ='[1]EDl log'!Y31 -> 1.8709677 | AB14: ='[2]EDl log'!AB31 -> 17109085 | AC14: ='[2]EDl log'!AC31 -> 7234333
A15: =ELEC!C14 -> 44239 | B15: 878743 | C15: =SUM(B15-B14) -> 1667 | D15: =SUM(G15+I15+K15) -> 1666 | E15: =B14+D15 -> 878742 | F15: 133233 | G15: =F15-F14 -> 345 | H15: 436879 | I15: =H15-H14 -> 701 | J15: 308629 | K15: =J15-J14 -> 620 | L15: =SUM(G15*$Y$28)/1507.5 -> 73.233831 | M15: =SUM(I15*$Y$27)/1507.5 -> 52.080929 | N15: =SUM(K15*$Y$26)/1507.5 -> 32.902156 | O15: =($AC$31/$A$34)/1507.5 -> 73.452462 | P15: =SUM(L15:O15) -> 231.66938 | Q15: =SUM(-tanks!AX17*tanks!$AU$34) -> 292.58448 | R15: =SUM(P15:Q15) -> 524.25386 | S15: =SUM(ELEC!N14) -> 5643 | T15: =IF(S15>0,R15/S15,0) -> 0.092903396 | V15: ='[7]EDl log'!V32 -> H Deg | W15: ='[2]EDl log'!W32 -> 0 | X15: ='[10]EDl log'!X15 -> #REF! | AB15: ='[1]EDl log'!AB32 -> 0 | AC15: ='[1]EDl log'!AC32 -> 0
A16: =ELEC!C15 -> 44240 | B16: =B15 -> 878743 | C16: =SUM(B16-B15) -> 0 | D16: =SUM(G16+I16+K16) -> 0 | E16: =B15+D16 -> 878743 | F16: =F15 -> 133233 | G16: =F16-F15 -> 0 | H16: =H15 -> 436879 | I16: =H16-H15 -> 0 | J16: =J15 -> 308629 | K16: =J16-J15 -> 0 | L16: =SUM(G16*$Y$28)/1507.5 -> 0 | M16: =SUM(I16*$Y$27)/1507.5 -> 0 | N16: =SUM(K16*$Y$26)/1507.5 -> 0 | O16: =($AC$31/$A$34)/1507.5 -> 73.452462 | P16: =SUM(L16:O16) -> 73.452462 | Q16: =SUM(-tanks!AX18*tanks!$AU$34) -> 0 | R16: =SUM(P16:Q16) -> 73.452462 | S16: =SUM(ELEC!N15) -> 0 | T16: =IF(S16>0,R16/S16,0) -> 0 | V16: ='[7]EDl log'!V33 -> C Deg | W16: ='[2]EDl log'!W33 -> 0 | X16: ='[10]EDl log'!X16 -> 0 | Y16: ='[7]EDl log'!Y33 -> #REF! | AB16: ='[1]EDl log'!AB33 -> 0 | AC16: ='[1]EDl log'!AC33 -> 0
A17: =ELEC!C16 -> 44241 | B17: =B16 -> 878743 | C17: =SUM(B17-B16) -> 0 | D17: =SUM(G17+I17+K17) -> 0 | E17: =B16+D17 -> 878743 | F17: =F16 -> 133233 | G17: =F17-F16 -> 0 | H17: =H16 -> 436879 | I17: =H17-H16 -> 0 | J17: =J16 -> 308629 | K17: =J17-J16 -> 0 | L17: =SUM(G17*$Y$28)/1507.5 -> 0 | M17: =SUM(I17*$Y$27)/1507.5 -> 0 | N17: =SUM(K17*$Y$26)/1507.5 -> 0 | O17: =($AC$31/$A$34)/1507.5 -> 73.452462 | P17: =SUM(L17:O17) -> 73.452462 | Q17: =SUM(-tanks!AX19*tanks!$AU$34) -> 0 | R17: =SUM(P17:Q17) -> 73.452462 | S17: =SUM(ELEC!N16) -> 0 | T17: =IF(S17>0,R17/S17,0) -> 0 | Z17: Vat | AA17: ='[2]EDl log'!AA34 -> 0.11 | AB17: ='[2]EDl log'!AB34 -> 1881999.4 | AC17: ='[1]EDl log'!AC34 -> 0
A18: =ELEC!C17 -> 44242 | B18: =B17 -> 878743 | C18: =SUM(B18-B17) -> 0 | D18: =SUM(G18+I18+K18) -> 0 | E18: =B17+D18 -> 878743 | F18: =F17 -> 133233 | G18: =F18-F17 -> 0 | H18: =H17 -> 436879 | I18: =H18-H17 -> 0 | J18: =J17 -> 308629 | K18: =J18-J17 -> 0 | L18: =SUM(G18*$Y$28)/1507.5 -> 0 | M18: =SUM(I18*$Y$27)/1507.5 -> 0 | N18: =SUM(K18*$Y$26)/1507.5 -> 0 | O18: =($AC$31/$A$34)/1507.5 -> 73.452462 | P18: =SUM(L18:O18) -> 73.452462 | Q18: =SUM(-tanks!AX20*tanks!$AU$34) -> 0 | R18: =SUM(P18:Q18) -> 73.452462 | S18: =SUM(ELEC!N17) -> 0 | T18: =IF(S18>0,R18/S18,0) -> 0 | AB18: ='[2]EDl log'!AB35 -> 18991084 | AC18: ='[1]EDl log'!AC35 -> 0
A19: =ELEC!C18 -> 44243 | B19: =B18 -> 878743 | C19: =SUM(B19-B18) -> 0 | D19: =SUM(G19+I19+K19) -> 0 | E19: =B18+D19 -> 878743 | F19: =F18 -> 133233 | G19: =F19-F18 -> 0 | H19: =H18 -> 436879 | I19: =H19-H18 -> 0 | J19: =J18 -> 308629 | K19: =J19-J18 -> 0 | L19: =SUM(G19*$Y$28)/1507.5 -> 0 | M19: =SUM(I19*$Y$27)/1507.5 -> 0 | N19: =SUM(K19*$Y$26)/1507.5 -> 0 | O19: =($AC$31/$A$34)/1507.5 -> 73.452462 | P19: =SUM(L19:O19) -> 73.452462 | Q19: =SUM(-tanks!AX21*tanks!$AU$34) -> 0 | R19: =SUM(P19:Q19) -> 73.452462 | S19: =SUM(ELEC!N18) -> 0 | T19: =IF(S19>0,R19/S19,0) -> 0 | AB19: ='[2]EDl log'!AB36 -> 11349.31 | AC19: ='[1]EDl log'!AC36 -> 0
A20: =ELEC!C19 -> 44244 | B20: =B19 -> 878743 | C20: =SUM(B20-B19) -> 0 | D20: =SUM(G20+I20+K20) -> 0 | E20: =B19+D20 -> 878743 | F20: =F19 -> 133233 | G20: =F20-F19 -> 0 | H20: =H19 -> 436879 | I20: =H20-H19 -> 0 | J20: =J19 -> 308629 | K20: =J20-J19 -> 0 | L20: =SUM(G20*$Y$28)/1507.5 -> 0 | M20: =SUM(I20*$Y$27)/1507.5 -> 0 | N20: =SUM(K20*$Y$26)/1507.5 -> 0 | O20: =($AC$31/$A$34)/1507.5 -> 73.452462 | P20: =SUM(L20:O20) -> 73.452462 | Q20: =SUM(-tanks!AX22*tanks!$AU$34) -> 0 | R20: =SUM(P20:Q20) -> 73.452462 | S20: =SUM(ELEC!N19) -> 0 | T20: =IF(S20>0,R20/S20,0) -> 0 | V20: Before new counter
