Workbook

Sheet Total
A1: Site Name | B1: Day | C1: Month | D1: Year | E1: Total Electricity Kwh | F1: Electricity Tariff ($/Kwh) | G1: LPG (Kg) | H1: LPG $/Kg | I1: Water Utility Supply (m3) m3 | J1: Water Utility Supply (m3) $/m3 | K1: Room Nights | L1: Utilities day cost dh
A2: Serengeti | B2: 1 | C2: 1 | D2: 2021 | E2: ='UTILITY REPORT 1'!F3 -> 2906 | F2: =('UTILITY REPORT 1'!E3*'UTILITY REPORT 1'!D3)/'UTILITY REPORT 1'!F3 -> 0.41609085 | G2: =IF('Utility summery'!M6<0,"0",'Utility summery'!M6) -> 74734.36 | H2: 0 | I2: =IF('UTILITY REPORT 1'!G3<0,"0",'UTILITY REPORT 1'!G3) -> 58 | J2: 0 | K2: ='UTILITY REPORT 1'!C3 -> 10.39 | L2: =E2*F2+G2*H2+#REF!*#REF!+I2*J2 -> #REF!
A3: Serengeti | B3: =B2+1 -> 2 | C3: 1 | D3: 2021 | E3: ='UTILITY REPORT 1'!F4 -> 2849 | F3: =('UTILITY REPORT 1'!E4*'UTILITY REPORT 1'!D4)/'UTILITY REPORT 1'!F4 -> 0.41187785 | G3: =IF('Utility summery'!M7<0,"0",'Utility summery'!M7) -> 74755.84 | H3: 0 | I3: =IF('UTILITY REPORT 1'!G4<0,"0",'UTILITY REPORT 1'!G4) -> 56 | J3: 0 | K3: ='UTILITY REPORT 1'!C4 -> 5.19 | L3: =E3*F3+G3*H3+#REF!*#REF!+I3*J3 -> #REF!
A4: Serengeti | B4: =B3+1 -> 3 | C4: 1 | D4: 2021 | E4: ='UTILITY REPORT 1'!F5 -> 2599 | F4: =('UTILITY REPORT 1'!E5*'UTILITY REPORT 1'!D5)/'UTILITY REPORT 1'!F5 -> 0.42344748 | G4: =IF('Utility summery'!M8<0,"0",'Utility summery'!M8) -> 74775.21 | H4: 0 | I4: =IF('UTILITY REPORT 1'!G5<0,"0",'UTILITY REPORT 1'!G5) -> 46 | J4: 0 | K4: ='UTILITY REPORT 1'!C5 -> 3.9 | L4: =E4*F4+G4*H4+#REF!*#REF!+I4*J4 -> #REF!
A5: Serengeti | B5: =B4+1 -> 4 | C5: 1 | D5: 2021 | E5: ='UTILITY REPORT 1'!F6 -> 2681 | F5: =('UTILITY REPORT 1'!E6*'UTILITY REPORT 1'!D6)/'UTILITY REPORT 1'!F6 -> 0.40830287 | G5: =IF('Utility summery'!M9<0,"0",'Utility summery'!M9) -> 74796.53 | H5: 0 | I5: =IF('UTILITY REPORT 1'!G6<0,"0",'UTILITY REPORT 1'!G6) -> 52 | J5: 0 | K5: ='UTILITY REPORT 1'!C6 -> 3.9 | L5: =E5*F5+G5*H5+#REF!*#REF!+I5*J5 -> #REF!
A6: Serengeti | B6: =B5+1 -> 5 | C6: 1 | D6: 2021 | E6: ='UTILITY REPORT 1'!F7 -> 3008 | F6: =('UTILITY REPORT 1'!E7*'UTILITY REPORT 1'!D7)/'UTILITY REPORT 1'!F7 -> 0.4168883 | G6: =IF('Utility summery'!M10<0,"0",'Utility summery'!M10) -> 74818 | H6: 0 | I6: =IF('UTILITY REPORT 1'!G7<0,"0",'UTILITY REPORT 1'!G7) -> 45 | J6: 0 | K6: ='UTILITY REPORT 1'!C7 -> 5.19 | L6: =E6*F6+G6*H6+#REF!*#REF!+I6*J6 -> #REF!
A7: Serengeti | B7: =B6+1 -> 6 | C7: 1 | D7: 2021 | E7: ='UTILITY REPORT 1'!F8 -> 2354 | F7: =('UTILITY REPORT 1'!E8*'UTILITY REPORT 1'!D8)/'UTILITY REPORT 1'!F8 -> 0.40222175 | G7: =IF('Utility summery'!M11<0,"0",'Utility summery'!M11) -> 74828.57 | H7: 0 | I7: =IF('UTILITY REPORT 1'!G8<0,"0",'UTILITY REPORT 1'!G8) -> 45 | J7: 0 | K7: ='UTILITY REPORT 1'!C8 -> 7.79 | L7: =E7*F7+G7*H7+#REF!*#REF!+I7*J7 -> #REF!
A8: Serengeti | B8: =B7+1 -> 7 | C8: 1 | D8: 2021 | E8: ='UTILITY REPORT 1'!F9 -> 2780 | F8: =('UTILITY REPORT 1'!E9*'UTILITY REPORT 1'!D9)/'UTILITY REPORT 1'!F9 -> 0.4110036 | G8: =IF('Utility summery'!M12<0,"0",'Utility summery'!M12) -> 74845.13 | H8: 0 | I8: =IF('UTILITY REPORT 1'!G9<0,"0",'UTILITY REPORT 1'!G9) -> 58 | J8: 0 | K8: ='UTILITY REPORT 1'!C9 -> 7.79 | L8: =E8*F8+G8*H8+#REF!*#REF!+I8*J8 -> #REF!
A9: Serengeti | B9: =B8+1 -> 8 | C9: 1 | D9: 2021 | E9: ='UTILITY REPORT 1'!F10 -> 2545 | F9: =('UTILITY REPORT 1'!E10*'UTILITY REPORT 1'!D10)/'UTILITY REPORT 1'!F10 -> 0.41171316 | G9: =IF('Utility summery'!M13<0,"0",'Utility summery'!M13) -> 74862.53 | H9: 0 | I9: =IF('UTILITY REPORT 1'!G10<0,"0",'UTILITY REPORT 1'!G10) -> 45 | J9: 0 | K9: ='UTILITY REPORT 1'!C10 -> 5.19 | L9: =E9*F9+G9*H9+#REF!*#REF!+I9*J9 -> #REF!
A10: Serengeti | B10: =B9+1 -> 9 | C10: 1 | D10: 2021 | E10: ='UTILITY REPORT 1'!F11 -> 2653 | F10: =('UTILITY REPORT 1'!E11*'UTILITY REPORT 1'!D11)/'UTILITY REPORT 1'!F11 -> 0.42860912 | G10: =IF('Utility summery'!M14<0,"0",'Utility summery'!M14) -> 74882.6 | H10: 0 | I10: =IF('UTILITY REPORT 1'!G11<0,"0",'UTILITY REPORT 1'!G11) -> 60 | J10: 0 | K10: ='UTILITY REPORT 1'!C11 -> 10 | L10: =E10*F10+G10*H10+#REF!*#REF!+I10*J10 -> #REF!
A11: Serengeti | B11: =B10+1 -> 10 | C11: 1 | D11: 2021 | E11: ='UTILITY REPORT 1'!F12 -> 2493 | F11: =('UTILITY REPORT 1'!E12*'UTILITY REPORT 1'!D12)/'UTILITY REPORT 1'!F12 -> 0.42092659 | G11: =IF('Utility summery'!M15<0,"0",'Utility summery'!M15) -> 74901.7 | H11: 0 | I11: =IF('UTILITY REPORT 1'!G12<0,"0",'UTILITY REPORT 1'!G12) -> 57 | J11: 0 | K11: ='UTILITY REPORT 1'!C12 -> 10.39 | L11: =E11*F11+G11*H11+#REF!*#REF!+I11*J11 -> #REF!
A12: Serengeti | B12: =B11+1 -> 11 | C12: 1 | D12: 2021 | E12: ='UTILITY REPORT 1'!F13 -> 2528 | F12: =('UTILITY REPORT 1'!E13*'UTILITY REPORT 1'!D13)/'UTILITY REPORT 1'!F13 -> 0.41895174 | G12: =IF('Utility summery'!M16<0,"0",'Utility summery'!M16) -> 74919.52 | H12: 0 | I12: =IF('UTILITY REPORT 1'!G13<0,"0",'UTILITY REPORT 1'!G13) -> 49 | J12: 0 | K12: ='UTILITY REPORT 1'!C13 -> 11.69 | L12: =E12*F12+G12*H12+#REF!*#REF!+I12*J12 -> #REF!
A13: Serengeti | B13: =B12+1 -> 12 | C13: 1 | D13: 2021 | E13: ='UTILITY REPORT 1'!F14 -> 2703 | F13: =('UTILITY REPORT 1'!E14*'UTILITY REPORT 1'!D14)/'UTILITY REPORT 1'!F14 -> 0.41330004 | G13: =IF('Utility summery'!M17<0,"0",'Utility summery'!M17) -> 74960.75 | H13: 0 | I13: =IF('UTILITY REPORT 1'!G14<0,"0",'UTILITY REPORT 1'!G14) -> 52 | J13: 0 | K13: ='UTILITY REPORT 1'!C14 -> 23.38 | L13: =E13*F13+G13*H13+#REF!*#REF!+I13*J13 -> #REF!
A14: Serengeti | B14: =B13+1 -> 13 | C14: 1 | D14: 2021 | E14: ='UTILITY REPORT 1'!F15 -> 2690 | F14: =('UTILITY REPORT 1'!E15*'UTILITY REPORT 1'!D15)/'UTILITY REPORT 1'!F15 -> 0.42059108 | G14: =IF('Utility summery'!M18<0,"0",'Utility summery'!M18) -> 74975 | H14: 0 | I14: =IF('UTILITY REPORT 1'!G15<0,"0",'UTILITY REPORT 1'!G15) -> 58 | J14: 0 | K14: ='UTILITY REPORT 1'!C15 -> 22.08 | L14: =E14*F14+G14*H14+#REF!*#REF!+I14*J14 -> #REF!
... A30: Serengeti | B30: =B29+1 -> 29 | C30: 1 | D30: 2021 | E30: ='UTILITY REPORT 1'!F31 -> 0 | F30: =('UTILITY REPORT 1'!E31*'UTILITY REPORT 1'!D31)/'UTILITY REPORT 1'!F31 -> #DIV/0! | G30: =IF('Utility summery'!M34<0,"0",'Utility summery'!M34) -> 0 | H30: 0 | I30: =IF('UTILITY REPORT 1'!G31<0,"0",'UTILITY REPORT 1'!G31) -> 0 | J30: 0 | K30: ='UTILITY REPORT 1'!C31 -> 0 | L30: =E30*F30+G30*H30+#REF!*#REF!+I30*J30 -> #DIV/0!
A31: Serengeti | B31: 30 | C31: 1 | D31: 2021 | E31: ='UTILITY REPORT 1'!F32 -> 0 | F31: =('UTILITY REPORT 1'!E32*'UTILITY REPORT 1'!D32)/'UTILITY REPORT 1'!F32 -> #DIV/0! | G31: =IF('Utility summery'!M35<0,"0",'Utility summery'!M35) -> 0 | H31: 0 | I31: =IF('UTILITY REPORT 1'!G32<0,"0",'UTILITY REPORT 1'!G32) -> 0 | J31: 0 | K31: ='UTILITY REPORT 1'!C32 -> 0 | L31: =E31*F31+G31*H31+#REF!*#REF!+I31*J31 -> #DIV/0!
A32: Serengeti | B32: 31 | C32: 1 | D32: 2021 | E32: ='UTILITY REPORT 1'!F33 -> 0 | F32: =('UTILITY REPORT 1'!E33*'UTILITY REPORT 1'!D33)/'UTILITY REPORT 1'!F33 -> #DIV/0! | G32: =IF('Utility summery'!M36<0,"0",'Utility summery'!M36) -> 0 | H32: 0 | I32: =IF('UTILITY REPORT 1'!G33<0,"0",'UTILITY REPORT 1'!G33) -> 0 | J32: 0 | K32: ='UTILITY REPORT 1'!C33 -> 0

Sheet Submetering
A1: Site Name | B1: Day | C1: Month | D1: Year | E1: Transport Consumption (LT) | F1: Generators Consumption (LT) | G1: Total Electricity Kwh | H1: Kitchen (KWh) | I1: Laundry (KWh) | J1: STP (M3) | K1: RO prodution (M3) | L1: Amani Restaurant (M3) | M1: Kitchen (M3) | N1: Laundry (M3) | O1: Laundry (M3) | P1: Total water Consumption (M3) | Q1: Borehole #1 (M3) | R1: Borehole #2 (M3) | S1: Borehole #3 (M3) | T1: Borehole #4 (M3) | U1: Borehole #5 (M3) | V1: Borehole #6 (M3) | W1: Total Bore holes production (M3) | X1: Room Nights
A2: Serengeti | B2: 1 | C2: 2 | D2: 2021 | E2: ='UTILITY REPORT 1'!I3 -> 97.65 | F2: ='UTILITY REPORT 1'!E3 -> 1209.16 | G2: ='UTILITY REPORT 1'!F3 -> 2906 | H2: =IF('Kit report'!F4<0,"0",'Kit report'!F4) -> 252 | I2: =IF('Kit report'!X4<0,"0",'Kit report'!X4) -> 320 | J2: =IF('Utility summery'!H6<0,"0",'Utility summery'!H6) -> 35 | K2: =IF('UTILITY REPORT 1'!H3<0,"0",'UTILITY REPORT 1'!H3) -> 49 | L2: ='Water-Meter'!K6 -> 0 | M2: ='Water-Meter'!H6 -> 0 | N2: ='Water-Meter'!Q6 -> 5 | O2: =K2*E2+H2*I2+#REF!*#REF!+J2*L2 -> #REF! | P2: ='Water-Meter'!E6 -> 58 | Q2: =IF('Water-Meter'!U6<0,"0",'Water-Meter'!U6) -> 82 | R2: =IF('Water-Meter'!X6<0,"0",'Water-Meter'!X6) -> 0 | S2: =IF('Water-Meter'!AA6<0,"0",'Water-Meter'!AA6) -> 82 | T2: =IF('Water-Meter'!AD6<0,"0",'Water-Meter'!AD6) -> 17 | U2: =IF('Water-Meter'!AG6<0,"0",'Water-Meter'!AG6) -> 0 | V2: =IF('Water-Meter'!AJ6<0,"0",'Water-Meter'!AJ6) -> 26 | W2: ='Water-Meter'!AN6 -> 207 | X2: =Total!K2 -> 10.39
A3: Serengeti | B3: =B2+1 -> 2 | C3: 2 | D3: 2021 | E3: ='UTILITY REPORT 1'!I4 -> 0 | F3: ='UTILITY REPORT 1'!E4 -> 1173.44 | G3: ='UTILITY REPORT 1'!F4 -> 2849 | H3: =IF('Kit report'!F5<0,"0",'Kit report'!F5) -> 228 | I3: =IF('Kit report'!X5<0,"0",'Kit report'!X5) -> 360 | J3: =IF('Utility summery'!H7<0,"0",'Utility summery'!H7) -> 43 | K3: =IF('UTILITY REPORT 1'!H4<0,"0",'UTILITY REPORT 1'!H4) -> 26 | L3: ='Water-Meter'!K7 -> 0 | M3: ='Water-Meter'!H7 -> 0 | N3: ='Water-Meter'!Q7 -> 5 | O3: =K3*E3+H3*I3+#REF!*#REF!+J3*L3 -> #REF! | P3: ='Water-Meter'!E7 -> 56 | Q3: =IF('Water-Meter'!U7<0,"0",'Water-Meter'!U7) -> 0 | R3: =IF('Water-Meter'!X7<0,"0",'Water-Meter'!X7) -> 0 | S3: =IF('Water-Meter'!AA7<0,"0",'Water-Meter'!AA7) -> 94 | T3: =IF('Water-Meter'!AD7<0,"0",'Water-Meter'!AD7) -> 13 | U3: =IF('Water-Meter'!AG7<0,"0",'Water-Meter'!AG7) -> 0 | V3: =IF('Water-Meter'!AJ7<0,"0",'Water-Meter'!AJ7) -> 26 | W3: ='Water-Meter'!AN7 -> 133 | X3: =Total!K3 -> 5.19
A4: Serengeti | B4: =B3+1 -> 3 | C4: 2 | D4: 2021 | E4: ='UTILITY REPORT 1'!I5 -> 77.57 | F4: ='UTILITY REPORT 1'!E5 -> 1100.54 | G4: ='UTILITY REPORT 1'!F5 -> 2599 | H4: =IF('Kit report'!F6<0,"0",'Kit report'!F6) -> 252 | I4: =IF('Kit report'!X6<0,"0",'Kit report'!X6) -> 220 | J4: =IF('Utility summery'!H8<0,"0",'Utility summery'!H8) -> 76 | K4: =IF('UTILITY REPORT 1'!H5<0,"0",'UTILITY REPORT 1'!H5) -> 49 | L4: ='Water-Meter'!K8 -> 0 | M4: ='Water-Meter'!H8 -> 0 | N4: ='Water-Meter'!Q8 -> 3 | O4: =K4*E4+H4*I4+#REF!*#REF!+J4*L4 -> #REF! | P4: ='Water-Meter'!E8 -> 46 | Q4: =IF('Water-Meter'!U8<0,"0",'Water-Meter'!U8) -> 0 | R4: =IF('Water-Meter'!X8<0,"0",'Water-Meter'!X8) -> 0 | S4: =IF('Water-Meter'!AA8<0,"0",'Water-Meter'!AA8) -> 50 | T4: =IF('Water-Meter'!AD8<0,"0",'Water-Meter'!AD8) -> 16 | U4: =IF('Water-Meter'!AG8<0,"0",'Water-Meter'!AG8) -> 0 | V4: =IF('Water-Meter'!AJ8<0,"0",'Water-Meter'!AJ8) -> 26 | W4: ='Water-Meter'!AN8 -> 92 | X4: =Total!K4 -> 3.9
A5: Serengeti | B5: =B4+1 -> 4 | C5: 2 | D5: 2021 | E5: ='UTILITY REPORT 1'!I6 -> 120.29 | F5: ='UTILITY REPORT 1'!E6 -> 1094.66 | G5: ='UTILITY REPORT 1'!F6 -> 2681 | H5: =IF('Kit report'!F7<0,"0",'Kit report'!F7) -> 228 | I5: =IF('Kit report'!X7<0,"0",'Kit report'!X7) -> 280 | J5: =IF('Utility summery'!H9<0,"0",'Utility summery'!H9) -> 70 | K5: =IF('UTILITY REPORT 1'!H6<0,"0",'UTILITY REPORT 1'!H6) -> 49 | L5: ='Water-Meter'!K9 -> 0 | M5: ='Water-Meter'!H9 -> 0 | N5: ='Water-Meter'!Q9 -> 7 | O5: =K5*E5+H5*I5+#REF!*#REF!+J5*L5 -> #REF! | P5: ='Water-Meter'!E9 -> 52 | Q5: =IF('Water-Meter'!U9<0,"0",'Water-Meter'!U9) -> 0 | R5: =IF('Water-Meter'!X9<0,"0",'Water-Meter'!X9) -> 0 | S5: =IF('Water-Meter'!AA9<0,"0",'Water-Meter'!AA9) -> 51 | T5: =IF('Water-Meter'!AD9<0,"0",'Water-Meter'!AD9) -> 17 | U5: =IF('Water-Meter'!AG9<0,"0",'Water-Meter'!AG9) -> 0 | V5: =IF('Water-Meter'!AJ9<0,"0",'Water-Meter'!AJ9) -> 26 | W5: ='Water-Meter'!AN9 -> 94 | X5: =Total!K5 -> 3.9
A6: Serengeti | B6: =B5+1 -> 5 | C6: 2 | D6: 2021 | E6: ='UTILITY REPORT 1'!I7 -> 96.64 | F6: ='UTILITY REPORT 1'!E7 -> 1254 | G6: ='UTILITY REPORT 1'!F7 -> 3008 | H6: =IF('Kit report'!F8<0,"0",'Kit report'!F8) -> 264 | I6: =IF('Kit report'!X8<0,"0",'Kit report'!X8) -> 340 | J6: =IF('Utility summery'!H10<0,"0",'Utility summery'!H10) -> 25 | K6: =IF('UTILITY REPORT 1'!H7<0,"0",'UTILITY REPORT 1'!H7) -> 38 | L6: ='Water-Meter'!K10 -> 0 | M6: ='Water-Meter'!H10 -> 0 | N6: ='Water-Meter'!Q10 -> 5 | O6: =K6*E6+H6*I6+#REF!*#REF!+J6*L6 -> #REF! | P6: ='Water-Meter'!E10 -> 45 | Q6: =IF('Water-Meter'!U10<0,"0",'Water-Meter'!U10) -> 0 | R6: =IF('Water-Meter'!X10<0,"0",'Water-Meter'!X10) -> 0 | S6: =IF('Water-Meter'!AA10<0,"0",'Water-Meter'!AA10) -> 50 | T6: =IF('Water-Meter'!AD10<0,"0",'Water-Meter'!AD10) -> 17 | U6: =IF('Water-Meter'!AG10<0,"0",'Water-Meter'!AG10) -> 0 | V6: =IF('Water-Meter'!AJ10<0,"0",'Water-Meter'!AJ10) -> 26 | W6: ='Water-Meter'!AN10 -> 93 | X6: =Total!K6 -> 5.19
A7: Serengeti | B7: =B6+1 -> 6 | C7: 2 | D7: 2021 | E7: ='UTILITY REPORT 1'!I8 -> 68.41 | F7: ='UTILITY REPORT 1'!E8 -> 946.83 | G7: ='UTILITY REPORT 1'!F8 -> 2354 | H7: =IF('Kit report'!F9<0,"0",'Kit report'!F9) -> 204 | I7: =IF('Kit report'!X9<0,"0",'Kit report'!X9) -> 160 | J7: =IF('Utility summery'!H11<0,"0",'Utility summery'!H11) -> 36 | K7: =IF('UTILITY REPORT 1'!H8<0,"0",'UTILITY REPORT 1'!H8) -> 34 | L7: ='Water-Meter'!K11 -> 0 | M7: ='Water-Meter'!H11 -> 0 | N7: ='Water-Meter'!Q11 -> 2 | O7: =K7*E7+H7*I7+#REF!*#REF!+J7*L7 -> #REF! | P7: ='Water-Meter'!E11 -> 45 | Q7: =IF('Water-Meter'!U11<0,"0",'Water-Meter'!U11) -> 0 | R7: =IF('Water-Meter'!X11<0,"0",'Water-Meter'!X11) -> 0 | S7: =IF('Water-Meter'!AA11<0,"0",'Water-Meter'!AA11) -> 45 | T7: =IF('Water-Meter'!AD11<0,"0",'Water-Meter'!AD11) -> 17 | U7: =IF('Water-Meter'!AG11<0,"0",'Water-Meter'!AG11) -> 0 | V7: =IF('Water-Meter'!AJ11<0,"0",'Water-Meter'!AJ11) -> 26 | W7: ='Water-Meter'!AN11 -> 88 | X7: =Total!K7 -> 7.79
A8: Serengeti | B8: =B7+1 -> 7 | C8: 2 | D8: 2021 | E8: ='UTILITY REPORT 1'!I9 -> 0 | F8: ='UTILITY REPORT 1'!E9 -> 1142.59 | G8: ='UTILITY REPORT 1'!F9 -> 2780 | H8: =IF('Kit report'!F10<0,"0",'Kit report'!F10) -> 240 | I8: =IF('Kit report'!X10<0,"0",'Kit report'!X10) -> 420 | J8: =IF('Utility summery'!H12<0,"0",'Utility summery'!H12) -> 53 | K8: =IF('UTILITY REPORT 1'!H9<0,"0",'UTILITY REPORT 1'!H9) -> 98 | L8: ='Water-Meter'!K12 -> 0 | M8: ='Water-Meter'!H12 -> 0 | N8: ='Water-Meter'!Q12 -> 3 | O8: =K8*E8+H8*I8+#REF!*#REF!+J8*L8 -> #REF! | P8: ='Water-Meter'!E12 -> 58 | Q8: =IF('Water-Meter'!U12<0,"0",'Water-Meter'!U12) -> 0 | R8: =IF('Water-Meter'!X12<0,"0",'Water-Meter'!X12) -> 0 | S8: =IF('Water-Meter'!AA12<0,"0",'Water-Meter'!AA12) -> 40 | T8: =IF('Water-Meter'!AD12<0,"0",'Water-Meter'!AD12) -> 17 | U8: =IF('Water-Meter'!AG12<0,"0",'Water-Meter'!AG12) -> 0 | V8: =IF('Water-Meter'!AJ12<0,"0",'Water-Meter'!AJ12) -> 33 | W8: ='Water-Meter'!AN12 -> 90 | X8: =Total!K8 -> 7.79
A9: Serengeti | B9: =B8+1 -> 8 | C9: 2 | D9: 2021 | E9: ='UTILITY REPORT 1'!I10 -> 70.37 | F9: ='UTILITY REPORT 1'!E10 -> 1047.81 | G9: ='UTILITY REPORT 1'!F10 -> 2545 | H9: =IF('Kit report'!F11<0,"0",'Kit report'!F11) -> 216 | I9: =IF('Kit report'!X11<0,"0",'Kit report'!X11) -> 320 | J9: =IF('Utility summery'!H13<0,"0",'Utility summery'!H13) -> 25 | K9: =IF('UTILITY REPORT 1'!H10<0,"0",'UTILITY REPORT 1'!H10) -> 0 | L9: ='Water-Meter'!K13 -> 0 | M9: ='Water-Meter'!H13 -> 0 | N9: ='Water-Meter'!Q13 -> 6 | O9: =K9*E9+H9*I9+#REF!*#REF!+J9*L9 -> #REF! | P9: ='Water-Meter'!E13 -> 45 | Q9: =IF('Water-Meter'!U13<0,"0",'Water-Meter'!U13) -> 0 | R9: =IF('Water-Meter'!X13<0,"0",'Water-Meter'!X13) -> 0 | S9: =IF('Water-Meter'!AA13<0,"0",'Water-Meter'!AA13) -> 32 | T9: =IF('Water-Meter'!AD13<0,"0",'Water-Meter'!AD13) -> 12 | U9: =IF('Water-Meter'!AG13<0,"0",'Water-Meter'!AG13) -> 0 | V9: =IF('Water-Meter'!AJ13<0,"0",'Water-Meter'!AJ13) -> 17 | W9: ='Water-Meter'!AN13 -> 61 | X9: =Total!K9 -> 5.19
A10: Serengeti | B10: =B9+1 -> 9 | C10: 2 | D10: 2021 | E10: ='UTILITY REPORT 1'!I11 -> 130.19 | F10: ='UTILITY REPORT 1'!E11 -> 1137.1 | G10: ='UTILITY REPORT 1'!F11 -> 2653 | H10: =IF('Kit report'!F12<0,"0",'Kit report'!F12) -> 216 | I10: =IF('Kit report'!X12<0,"0",'Kit report'!X12) -> 280 | J10: =IF('Utility summery'!H14<0,"0",'Utility summery'!H14) -> 36 | K10: =IF('UTILITY REPORT 1'!H11<0,"0",'UTILITY REPORT 1'!H11) -> 144 | L10: ='Water-Meter'!K14 -> 0 | M10: ='Water-Meter'!H14 -> 0 | N10: ='Water-Meter'!Q14 -> 3 | O10: =K10*E10+H10*I10+#REF!*#REF!+J10*L10 -> #REF! | P10: ='Water-Meter'!E14 -> 60 | Q10: =IF('Water-Meter'!U14<0,"0",'Water-Meter'!U14) -> 0 | R10: =IF('Water-Meter'!X14<0,"0",'Water-Meter'!X14) -> 0 | S10: =IF('Water-Meter'!AA14<0,"0",'Water-Meter'!AA14) -> 43 | T10: =IF('Water-Meter'!AD14<0,"0",'Water-Meter'!AD14) -> 15 | U10: =IF('Water-Meter'!AG14<0,"0",'Water-Meter'!AG14) -> 0 | V10: =IF('Water-Meter'!AJ14<0,"0",'Water-Meter'!AJ14) -> 24 | W10: ='Water-Meter'!AN14 -> 82 | X10: =Total!K10 -> 10
A11: Serengeti | B11: =B10+1 -> 10 | C11: 2 | D11: 2021 | E11: ='UTILITY REPORT 1'!I12 -> 0 | F11: ='UTILITY REPORT 1'!E12 -> 1049.37 | G11: ='UTILITY REPORT 1'!F12 -> 2493 | H11: =IF('Kit report'!F13<0,"0",'Kit report'!F13) -> 216 | I11: =IF('Kit report'!X13<0,"0",'Kit report'!X13) -> 220 | J11: =IF('Utility summery'!H15<0,"0",'Utility summery'!H15) -> 36 | K11: =IF('UTILITY REPORT 1'!H12<0,"0",'UTILITY REPORT 1'!H12) -> 0 | L11: ='Water-Meter'!K15 -> 0 | M11: ='Water-Meter'!H15 -> 0 | N11: ='Water-Meter'!Q15 -> 4 | O11: =K11*E11+H11*I11+#REF!*#REF!+J11*L11 -> #REF! | P11: ='Water-Meter'!E15 -> 57 | Q11: =IF('Water-Meter'!U15<0,"0",'Water-Meter'!U15) -> 0 | R11: =IF('Water-Meter'!X15<0,"0",'Water-Meter'!X15) -> 0 | S11: =IF('Water-Meter'!AA15<0,"0",'Water-Meter'!AA15) -> 37 | T11: =IF('Water-Meter'!AD15<0,"0",'Water-Meter'!AD15) -> 17 | U11: =IF('Water-Meter'!AG15<0,"0",'Water-Meter'!AG15) -> 0 | V11: =IF('Water-Meter'!AJ15<0,"0",'Water-Meter'!AJ15) -> 23 | W11: ='Water-Meter'!AN15 -> 77 | X11: =Total!K11 -> 10.39
A12: Serengeti | B12: =B11+1 -> 11 | C12: 2 | D12: 2021 | E12: ='UTILITY REPORT 1'!I13 -> 66.43 | F12: ='UTILITY REPORT 1'!E13 -> 1059.11 | G12: ='UTILITY REPORT 1'!F13 -> 2528 | H12: =IF('Kit report'!F14<0,"0",'Kit report'!F14) -> 240 | I12: =IF('Kit report'!X14<0,"0",'Kit report'!X14) -> 260 | J12: =IF('Utility summery'!H16<0,"0",'Utility summery'!H16) -> 75 | K12: =IF('UTILITY REPORT 1'!H13<0,"0",'UTILITY REPORT 1'!H13) -> 100 | L12: ='Water-Meter'!K16 -> 0 | M12: ='Water-Meter'!H16 -> 0 | N12: ='Water-Meter'!Q16 -> 4 | O12: =K12*E12+H12*I12+#REF!*#REF!+J12*L12 -> #REF! | P12: ='Water-Meter'!E16 -> 49 | Q12: =IF('Water-Meter'!U16<0,"0",'Water-Meter'!U16) -> 0 | R12: =IF('Water-Meter'!X16<0,"0",'Water-Meter'!X16) -> 0 | S12: =IF('Water-Meter'!AA16<0,"0",'Water-Meter'!AA16) -> 9 | T12: =IF('Water-Meter'!AD16<0,"0",'Water-Meter'!AD16) -> 14 | U12: =IF('Water-Meter'!AG16<0,"0",'Water-Meter'!AG16) -> 0 | V12: =IF('Water-Meter'!AJ16<0,"0",'Water-Meter'!AJ16) -> 29 | W12: ='Water-Meter'!AN16 -> 52 | X12: =Total!K12 -> 11.69
A13: Serengeti | B13: =B12+1 -> 12 | C13: 2 | D13: 2021 | E13: ='UTILITY REPORT 1'!I14 -> 116 | F13: ='UTILITY REPORT 1'!E14 -> 1117.15 | G13: ='UTILITY REPORT 1'!F14 -> 2703 | H13: =IF('Kit report'!F15<0,"0",'Kit report'!F15) -> 264 | I13: =IF('Kit report'!X15<0,"0",'Kit report'!X15) -> 260 | J13: =IF('Utility summery'!H17<0,"0",'Utility summery'!H17) -> 55 | K13: =IF('UTILITY REPORT 1'!H14<0,"0",'UTILITY REPORT 1'!H14) -> 0 | L13: ='Water-Meter'!K17 -> 0 | M13: ='Water-Meter'!H17 -> 0 | N13: ='Water-Meter'!Q17 -> 3 | O13: =K13*E13+H13*I13+#REF!*#REF!+J13*L13 -> #REF! | P13: ='Water-Meter'!E17 -> 52 | Q13: =IF('Water-Meter'!U17<0,"0",'Water-Meter'!U17) -> 0 | R13: =IF('Water-Meter'!X17<0,"0",'Water-Meter'!X17) -> 0 | S13: =IF('Water-Meter'!AA17<0,"0",'Water-Meter'!AA17) -> 0 | T13: =IF('Water-Meter'!AD17<0,"0",'Water-Meter'!AD17) -> 16 | U13: =IF('Water-Meter'!AG17<0,"0",'Water-Meter'!AG17) -> 0 | V13: =IF('Water-Meter'!AJ17<0,"0",'Water-Meter'!AJ17) -> 23 | W13: ='Water-Meter'!AN17 -> 39 | X13: =Total!K13 -> 23.38
A14: Serengeti | B14: =B13+1 -> 13 | C14: 2 | D14: 2021 | E14: ='UTILITY REPORT 1'!I15 -> 474.14 | F14: ='UTILITY REPORT 1'!E15 -> 1131.39 | G14: ='UTILITY REPORT 1'!F15 -> 2690 | H14: =IF('Kit report'!F16<0,"0",'Kit report'!F16) -> 252 | I14: =IF('Kit report'!X16<0,"0",'Kit report'!X16) -> 180 | J14: =IF('Utility summery'!H18<0,"0",'Utility summery'!H18) -> 46 | K14: =IF('UTILITY REPORT 1'!H15<0,"0",'UTILITY REPORT 1'!H15) -> 0 | L14: ='Water-Meter'!K18 -> 0 | M14: ='Water-Meter'!H18 -> 0 | N14: ='Water-Meter'!Q18 -> 2 | O14: =K14*E14+H14*I14+#REF!*#REF!+J14*L14 -> #REF! | P14: ='Water-Meter'!E18 -> 58 | Q14: =IF('Water-Meter'!U18<0,"0",'Water-Meter'!U18) -> 0 | R14: =IF('Water-Meter'!X18<0,"0",'Water-Meter'!X18) -> 0 | S14: =IF('Water-Meter'!AA18<0,"0",'Water-Meter'!AA18) -> 0 | T14: =IF('Water-Meter'!AD18<0,"0",'Water-Meter'!AD18) -> 16 | U14: =IF('Water-Meter'!AG18<0,"0",'Water-Meter'!AG18) -> 0 | V14: =IF('Water-Meter'!AJ18<0,"0",'Water-Meter'!AJ18) -> 28 | W14: ='Water-Meter'!AN18 -> 44 | X14: =Total!K14 -> 22.08
... A30: Serengeti | B30: =B29+1 -> 29 | C30: 2 | D30: 2021 | E30: ='UTILITY REPORT 1'!I31 -> 0 | F30: ='UTILITY REPORT 1'!E31 -> 0 | G30: ='UTILITY REPORT 1'!F31 -> 0 | H30: =IF('Kit report'!F32<0,"0",'Kit report'!F32) -> 0 | I30: =IF('Kit report'!X32<0,"0",'Kit report'!X32) -> 0 | J30: =IF('Utility summery'!H34<0,"0",'Utility summery'!H34) -> 0 | K30: =IF('UTILITY REPORT 1'!H31<0,"0",'UTILITY REPORT 1'!H31) -> 0 | L30: ='Water-Meter'!K34 -> 0 | M30: ='Water-Meter'!H34 -> 0 | N30: ='Water-Meter'!Q34 -> 0 | O30: =K30*E30+H30*I30+#REF!*#REF!+J30*L30 -> #REF! | P30: ='Water-Meter'!E34 -> 0 | Q30: =IF('Water-Meter'!U34<0,"0",'Water-Meter'!U34) -> 0 | R30: =IF('Water-Meter'!X34<0,"0",'Water-Meter'!X34) -> 0 | S30: =IF('Water-Meter'!AA34<0,"0",'Water-Meter'!AA34) -> 0 | T30: =IF('Water-Meter'!AD34<0,"0",'Water-Meter'!AD34) -> 0 | U30: =IF('Water-Meter'!AG34<0,"0",'Water-Meter'!AG34) -> 0 | V30: =IF('Water-Meter'!AJ34<0,"0",'Water-Meter'!AJ34) -> 0 | W30: ='Water-Meter'!AN34 -> 0 | X30: =Total!K30 -> 0
A31: Serengeti | B31: 30 | C31: 2 | D31: 2021 | E31: ='UTILITY REPORT 1'!I32 -> 0 | F31: ='UTILITY REPORT 1'!E32 -> 0 | G31: ='UTILITY REPORT 1'!F32 -> 0 | H31: =IF('Kit report'!F33<0,"0",'Kit report'!F33) -> 0 | I31: =IF('Kit report'!X33<0,"0",'Kit report'!X33) -> 0 | J31: =IF('Utility summery'!H35<0,"0",'Utility summery'!H35) -> 0 | K31: =IF('UTILITY REPORT 1'!H32<0,"0",'UTILITY REPORT 1'!H32) -> 0 | L31: ='Water-Meter'!K35 -> 0 | M31: ='Water-Meter'!H35 -> 0 | N31: ='Water-Meter'!Q35 -> 0 | O31: =K31*E31+H31*I31+#REF!*#REF!+J31*L31 -> #REF! | P31: ='Water-Meter'!E35 -> 0 | Q31: =IF('Water-Meter'!U35<0,"0",'Water-Meter'!U35) -> 0 | R31: =IF('Water-Meter'!X35<0,"0",'Water-Meter'!X35) -> 0 | S31: =IF('Water-Meter'!AA35<0,"0",'Water-Meter'!AA35) -> 0 | T31: =IF('Water-Meter'!AD35<0,"0",'Water-Meter'!AD35) -> 0 | U31: =IF('Water-Meter'!AG35<0,"0",'Water-Meter'!AG35) -> 0 | V31: =IF('Water-Meter'!AJ35<0,"0",'Water-Meter'!AJ35) -> 0 | W31: ='Water-Meter'!AN35 -> 0 | X31: =Total!K31 -> 0
A32: Serengeti | B32: 31 | C32: 2 | D32: 2021 | E32: ='UTILITY REPORT 1'!I33 -> 0 | F32: ='UTILITY REPORT 1'!E33 -> 0 | G32: ='UTILITY REPORT 1'!F33 -> 0 | H32: =IF('Kit report'!F34<0,"0",'Kit report'!F34) -> 0 | I32: =IF('Kit report'!X34<0,"0",'Kit report'!X34) -> 0 | J32: =IF('Utility summery'!H36<0,"0",'Utility summery'!H36) -> 0 | K32: =IF('UTILITY REPORT 1'!H33<0,"0",'UTILITY REPORT 1'!H33) -> 0 | L32: ='Water-Meter'!K36 -> 0 | M32: ='Water-Meter'!H36 -> 0 | N32: ='Water-Meter'!Q36 -> 0 | P32: ='Water-Meter'!E36 -> 0 | Q32: =IF('Water-Meter'!U36<0,"0",'Water-Meter'!U36) -> 0 | R32: =IF('Water-Meter'!X36<0,"0",'Water-Meter'!X36) -> 0 | S32: =IF('Water-Meter'!AA36<0,"0",'Water-Meter'!AA36) -> 0 | T32: =IF('Water-Meter'!AD36<0,"0",'Water-Meter'!AD36) -> 0 | U32: =IF('Water-Meter'!AG36<0,"0",'Water-Meter'!AG36) -> 0 | V32: =IF('Water-Meter'!AJ36<0,"0",'Water-Meter'!AJ36) -> 0 | W32: ='Water-Meter'!AN36 -> 0 | X32: =Total!K32 -> 0

Sheet UTILITY REPORT 1
A1: UTILITY REPORT
A2: Date | B2: % | C2: Guest Rooms Occupied | D2: Diesel cost Per Liter ($) | E2: Diesel consumption (LT) | F2: Power production (KW) | G2: Water consumption (M3) | H2: RO prodution (M3) | I2: Transport Consupmtion (LT)
A3: =Gen!A11 -> 44228 | B3: =Gen!B11 -> 0.091 | C3: ='Summery Report'!E5 -> 10.39 | D3: 1 | E3: =Gen!S11 -> 1209.16 | F3: =Gen!T11 -> 2906 | G3: ='Water-Meter'!E6 -> 58 | H3: ='Utility report '!AC6 -> 49 | I3: =Gen!AJ11 -> 97.65
A4: =Gen!A12 -> 44229 | B4: =Gen!B12 -> 0.065 | C4: ='Summery Report'!E6 -> 5.19 | D4: 1 | E4: =Gen!S12 -> 1173.44 | F4: =Gen!T12 -> 2849 | G4: ='Water-Meter'!E7 -> 56 | H4: ='Utility report '!AC7 -> 26 | I4: =Gen!AJ12 -> 0
A5: =Gen!A13 -> 44230 | B5: =Gen!B13 -> 0.039 | C5: ='Summery Report'!E7 -> 3.9 | D5: 1 | E5: =Gen!S13 -> 1100.54 | F5: =Gen!T13 -> 2599 | G5: ='Water-Meter'!E8 -> 46 | H5: ='Utility report '!AC8 -> 49 | I5: =Gen!AJ13 -> 77.57
A6: =Gen!A14 -> 44231 | B6: =Gen!B14 -> 0.039 | C6: ='Summery Report'!E8 -> 3.9 | D6: 1 | E6: =Gen!S14 -> 1094.66 | F6: =Gen!T14 -> 2681 | G6: ='Water-Meter'!E9 -> 52 | H6: ='Utility report '!AC9 -> 49 | I6: =Gen!AJ14 -> 120.29
A7: =Gen!A15 -> 44232 | B7: =Gen!B15 -> 0.0519 | C7: ='Summery Report'!E9 -> 5.19 | D7: 1 | E7: =Gen!S15 -> 1254 | F7: =Gen!T15 -> 3008 | G7: ='Water-Meter'!E10 -> 45 | H7: ='Utility report '!AC10 -> 38 | I7: =Gen!AJ15 -> 96.64
A8: =Gen!A16 -> 44233 | B8: =Gen!B16 -> 0.0779 | C8: ='Summery Report'!E10 -> 7.79 | D8: 1 | E8: =Gen!S16 -> 946.83 | F8: =Gen!T16 -> 2354 | G8: ='Water-Meter'!E11 -> 45 | H8: ='Utility report '!AC11 -> 34 | I8: =Gen!AJ16 -> 68.41
A9: =Gen!A17 -> 44234 | B9: =Gen!B17 -> 0.0779 | C9: ='Summery Report'!E11 -> 7.79 | D9: 1 | E9: =Gen!S17 -> 1142.59 | F9: =Gen!T17 -> 2780 | G9: ='Water-Meter'!E12 -> 58 | H9: ='Utility report '!AC12 -> 98 | I9: =Gen!AJ17 -> 0
A10: =Gen!A18 -> 44235 | B10: =Gen!B18 -> 0.0519 | C10: ='Summery Report'!E12 -> 5.19 | D10: 1 | E10: =Gen!S18 -> 1047.81 | F10: =Gen!T18 -> 2545 | G10: ='Water-Meter'!E13 -> 45 | H10: ='Utility report '!AC13 -> 0 | I10: =Gen!AJ18 -> 70.37
A11: =Gen!A19 -> 44236 | B11: =Gen!B19 -> 0.1039 | C11: ='Summery Report'!E13 -> 10 | D11: 1 | E11: =Gen!S19 -> 1137.1 | F11: =Gen!T19 -> 2653 | G11: ='Water-Meter'!E14 -> 60 | H11: ='Utility report '!AC14 -> 144 | I11: =Gen!AJ19 -> 130.19
A12: =Gen!A20 -> 44237 | B12: =Gen!B20 -> 0.1039 | C12: ='Summery Report'!E14 -> 10.39 | D12: 1 | E12: =Gen!S20 -> 1049.37 | F12: =Gen!T20 -> 2493 | G12: ='Water-Meter'!E15 -> 57 | H12: ='Utility report '!AC15 -> 0 | I12: =Gen!AJ20 -> 0
A13: =Gen!A21 -> 44238 | B13: =Gen!B21 -> 0.1169 | C13: ='Summery Report'!E15 -> 11.69 | D13: 1 | E13: =Gen!S21 -> 1059.11 | F13: =Gen!T21 -> 2528 | G13: ='Water-Meter'!E16 -> 49 | H13: ='Utility report '!AC16 -> 100 | I13: =Gen!AJ21 -> 66.43
A14: =Gen!A22 -> 44239 | B14: =Gen!B22 -> 0.2338 | C14: ='Summery Report'!E16 -> 23.38 | D14: 1 | E14: =Gen!S22 -> 1117.15 | F14: =Gen!T22 -> 2703 | G14: ='Water-Meter'!E17 -> 52 | H14: ='Utility report '!AC17 -> 0 | I14: =Gen!AJ22 -> 116
... A33: =Gen!A41 -> 0 | B33: =Gen!B41 -> 0 | C33: ='Summery Report'!E35 -> 0 | D33: 1 | E33: =Gen!S41 -> 0 | F33: =Gen!T41 -> 0 | G33: ='Water-Meter'!E36 -> 0 | H33: ='Utility report '!AC36 -> 0 | I33: =Gen!AJ41 -> 0
B34: =Gen!B42 -> 0 | C34: ='Summery Report'!E36 -> 0 | D34: 2 | E34: =Gen!S42 -> 0 | F34: =Gen!T42 -> 0 | G34: ='Water-Meter'!E37 -> 0 | H34: ='Utility report '!AC37 -> 0 | I34: =Gen!AK42 -> 0

Sheet Utility summery
A4: Date | B4: Room Occupied | C4: Electricity Units Generated KW | D4: Diseal | G4: Water | J4: Gas | N4: Cost of utilites
D5: Generator | E5: Transport | F5: Total | G5: RO | H5: STP | I5: Total Consumption | J5: 2 ton | K5: 1 Ton | L5: 1 Ton | M5: Total consumption | N5: Electricity /1.4$/liter | O5: Diseal for Transport | P5: Gas /2.38$/Kg | Q5: Total HLP Cost | R5: Electricity Cost/Room $ | S5: cost/Room $
A6: =Gen!A11 -> 44228 | B6: ='Summery Report'!E5 -> 10.39 | C6: =Gen!U11 -> 0.41609085 | D6: =Gen!T11 -> 2906 | E6: =Gen!AK11 -> 0 | F6: =Gen!AS11 -> 0 | G6: ='Utility report '!AC6 -> 49 | H6: ='Utility report '!AE6 -> 35 | I6: ='Water-Meter'!E6 -> 58 | J6: ='Lpg (2)'!B10 -> 82 | K6: ='Lpg (2)'!C10 -> 0 | L6: ='Lpg (2)'!D10 -> 0 | M6: ='Lpg (2)'!G10 -> 74734.36 | O6: =E6 -> 0 | P6: ='[1]Lpg (2)'!#REF! -> #REF! | Q6: ='[1]Summery Report'!#REF! -> #REF! | R6: =N6/B6 -> 0 | S6: =Q6/B6 -> #REF!
A7: =Gen!A12 -> 44229 | B7: ='Summery Report'!E6 -> 5.19 | C7: =Gen!U12 -> 0.41187785 | D7: =Gen!T12 -> 2849 | E7: =Gen!AK12 -> 0 | F7: =Gen!AS12 -> 0 | G7: ='Utility report '!AC7 -> 26 | H7: ='Utility report '!AE7 -> 43 | I7: ='Water-Meter'!E7 -> 56 | J7: ='Lpg (2)'!B11 -> 81 | K7: ='Lpg (2)'!C11 -> 0 | L7: ='Lpg (2)'!D11 -> 0 | M7: ='Lpg (2)'!G11 -> 74755.84 | N7: =D7*1.4 -> 3988.6 | O7: =E7*1.4 -> 0 | P7: ='[1]Lpg (2)'!#REF! -> #REF! | Q7: ='[1]Summery Report'!#REF! -> #REF! | R7: =N7/B7 -> 768.51638 | S7: =Q7/B7 -> #REF!
A8: =Gen!A13 -> 44230 | B8: ='Summery Report'!E7 -> 3.9 | C8: =Gen!U13 -> 0.42344748 | D8: =Gen!T13 -> 2599 | E8: =Gen!AK13 -> 0 | F8: =Gen!AS13 -> 0 | G8: ='Utility report '!AC8 -> 49 | H8: ='Utility report '!AE8 -> 76 | I8: ='Water-Meter'!E8 -> 46 | J8: ='Lpg (2)'!B12 -> 76 | K8: ='Lpg (2)'!C12 -> 0 | L8: ='Lpg (2)'!D12 -> 0 | M8: ='Lpg (2)'!G12 -> 74775.21 | N8: =D8*1.4 -> 3638.6 | O8: =E8*1.4 -> 0 | P8: ='[1]Lpg (2)'!#REF! -> #REF! | Q8: ='[1]Summery Report'!#REF! -> #REF! | R8: =N8/B8 -> 932.97436 | S8: =Q8/B8 -> #REF!
A9: =Gen!A14 -> 44231 | B9: ='Summery Report'!E8 -> 3.9 | C9: =Gen!U14 -> 0.40830287 | D9: =Gen!T14 -> 2681 | E9: =Gen!AK14 -> 0 | F9: =Gen!AS14 -> 0 | G9: ='Utility report '!AC9 -> 49 | H9: ='Utility report '!AE9 -> 70 | I9: ='Water-Meter'!E9 -> 52 | J9: ='Lpg (2)'!B13 -> 74 | K9: ='Lpg (2)'!C13 -> 0 | L9: ='Lpg (2)'!D13 -> 0 | M9: ='Lpg (2)'!G13 -> 74796.53 | N9: =D9*1.4 -> 3753.4 | O9: =E9*1.4 -> 0 | P9: ='[1]Lpg (2)'!#REF! -> #REF! | Q9: ='[1]Summery Report'!#REF! -> #REF! | R9: =N9/B9 -> 962.41026 | S9: =Q9/B9 -> #REF!
A10: =Gen!A15 -> 44232 | B10: ='Summery Report'!E9 -> 5.19 | C10: =Gen!U15 -> 0.4168883 | D10: =Gen!T15 -> 3008 | E10: =Gen!AK15 -> 0 | F10: =Gen!AS15 -> 0 | G10: ='Utility report '!AC10 -> 38 | H10: ='Utility report '!AE10 -> 25 | I10: ='Water-Meter'!E10 -> 45 | J10: ='Lpg (2)'!B14 -> 72 | K10: ='Lpg (2)'!C14 -> 0 | L10: ='Lpg (2)'!D14 -> 0 | M10: ='Lpg (2)'!G14 -> 74818 | N10: =D10*1.4 -> 4211.2 | O10: =E10*1.4 -> 0 | P10: ='[1]Lpg (2)'!#REF! -> #REF! | Q10: ='[1]Summery Report'!#REF! -> #REF! | R10: =N10/B10 -> 811.40655 | S10: =Q10/B10 -> #REF!
A11: =Gen!A16 -> 44233 | B11: ='Summery Report'!E10 -> 7.79 | C11: =Gen!U16 -> 0.40222175 | D11: =Gen!T16 -> 2354 | E11: =Gen!AK16 -> 0 | F11: =Gen!AS16 -> 0 | G11: ='Utility report '!AC11 -> 34 | H11: ='Utility report '!AE11 -> 36 | I11: ='Water-Meter'!E11 -> 45 | J11: ='Lpg (2)'!B15 -> 70 | K11: ='Lpg (2)'!C15 -> 0 | L11: ='Lpg (2)'!D15 -> 0 | M11: ='Lpg (2)'!G15 -> 74828.57 | N11: =D11*1.4 -> 3295.6 | O11: =E11*1.4 -> 0 | P11: ='[1]Lpg (2)'!#REF! -> #REF! | Q11: ='[1]Summery Report'!#REF! -> #REF! | R11: =N11/B11 -> 423.0552 | S11: =Q11/B11 -> #REF!
A12: =Gen!A17 -> 44234 | B12: ='Summery Report'!E11 -> 7.79 | C12: =Gen!U17 -> 0.4110036 | D12: =Gen!T17 -> 2780 | E12: =Gen!AK17 -> 0 | F12: =Gen!AS17 -> 0 | G12: ='Utility report '!AC12 -> 98 | H12: ='Utility report '!AE12 -> 53 | I12: ='Water-Meter'!E12 -> 58 | J12: ='Lpg (2)'!B16 -> 69 | K12: ='Lpg (2)'!C16 -> 0 | L12: ='Lpg (2)'!D16 -> 0 | M12: ='Lpg (2)'!G16 -> 74845.13 | N12: =D12*1.4 -> 3892 | O12: =E12*1.4 -> 0 | P12: ='[1]Lpg (2)'!#REF! -> #REF! | Q12: ='[1]Summery Report'!#REF! -> #REF! | R12: =N12/B12 -> 499.61489 | S12: =Q12/B12 -> #REF!
A13: =Gen!A18 -> 44235 | B13: ='Summery Report'!E12 -> 5.19 | C13: =Gen!U18 -> 0.41171316 | D13: =Gen!T18 -> 2545 | E13: =Gen!AK18 -> 0 | F13: =Gen!AS18 -> 0 | G13: ='Utility report '!AC13 -> 0 | H13: ='Utility report '!AE13 -> 25 | I13: ='Water-Meter'!E13 -> 45 | J13: ='Lpg (2)'!B17 -> 65 | K13: ='Lpg (2)'!C17 -> 0 | L13: ='Lpg (2)'!D17 -> 0 | M13: ='Lpg (2)'!G17 -> 74862.53 | N13: =D13*1.4 -> 3563 | O13: =E13*1.4 -> 0 | P13: ='[1]Lpg (2)'!#REF! -> #REF! | Q13: ='[1]Summery Report'!#REF! -> #REF! | R13: =N13/B13 -> 686.51252 | S13: =Q13/B13 -> #REF!
A14: =Gen!A19 -> 44236 | B14: ='Summery Report'!E13 -> 10 | C14: =Gen!U19 -> 0.42860912 | D14: =Gen!T19 -> 2653 | E14: =Gen!AK19 -> 0 | F14: =Gen!AS19 -> 0 | G14: ='Utility report '!AC14 -> 144 | H14: ='Utility report '!AE14 -> 36 | I14: ='Water-Meter'!E14 -> 60 | J14: ='Lpg (2)'!B18 -> 64 | K14: ='Lpg (2)'!C18 -> 0 | L14: ='Lpg (2)'!D18 -> 0 | M14: ='Lpg (2)'!G18 -> 74882.6 | N14: =D14*1.4 -> 3714.2 | O14: =E14*1.4 -> 0 | P14: ='[1]Lpg (2)'!#REF! -> #REF! | Q14: ='[1]Summery Report'!#REF! -> #REF! | R14: =N14/B14 -> 371.42 | S14: =Q14/B14 -> #REF!
A15: =Gen!A20 -> 44237 | B15: ='Summery Report'!E14 -> 10.39 | C15: =Gen!U20 -> 0.42092659 | D15: =Gen!T20 -> 2493 | E15: =Gen!AK20 -> 0 | F15: =Gen!AS20 -> 0 | G15: ='Utility report '!AC15 -> 0 | H15: ='Utility report '!AE15 -> 36 | I15: ='Water-Meter'!E15 -> 57 | J15: ='Lpg (2)'!B19 -> 61 | K15: ='Lpg (2)'!C19 -> 0 | L15: ='Lpg (2)'!D19 -> 0 | M15: ='Lpg (2)'!G19 -> 74901.7 | N15: =D15*1.4 -> 3490.2 | O15: =E15*1.4 -> 0 | P15: ='[1]Lpg (2)'!#REF! -> #REF! | Q15: ='[1]Summery Report'!#REF! -> #REF! | R15: =N15/B15 -> 335.91915 | S15: =Q15/B15 -> #REF!
A16: =Gen!A21 -> 44238 | B16: ='Summery Report'!E15 -> 11.69 | C16: =Gen!U21 -> 0.41895174 | D16: =Gen!T21 -> 2528 | E16: =Gen!AK21 -> 0 | F16: =Gen!AS21 -> 0 | G16: ='Utility report '!AC16 -> 100 | H16: ='Utility report '!AE16 -> 75 | I16: ='Water-Meter'!E16 -> 49 | J16: ='Lpg (2)'!B20 -> 60 | K16: ='Lpg (2)'!C20 -> 0 | L16: ='Lpg (2)'!D20 -> 0 | M16: ='Lpg (2)'!G20 -> 74919.52 | N16: =D16*1.4 -> 3539.2 | O16: =E16*1.4 -> 0 | P16: ='[1]Lpg (2)'!#REF! -> #REF! | Q16: ='[1]Summery Report'!#REF! -> #REF! | R16: =N16/B16 -> 302.75449 | S16: =Q16/B16 -> #REF!
A17: =Gen!A22 -> 44239 | B17: ='Summery Report'!E16 -> 23.38 | C17: =Gen!U22 -> 0.41330004 | D17: =Gen!T22 -> 2703 | E17: =Gen!AK22 -> 0 | F17: =Gen!AS22 -> 0 | G17: ='Utility report '!AC17 -> 0 | H17: ='Utility report '!AE17 -> 55 | I17: ='Water-Meter'!E17 -> 52 | J17: ='Lpg (2)'!B21 -> 55 | K17: ='Lpg (2)'!C22 -> 0 | L17: ='Lpg (2)'!D21 -> 0 | M17: ='Lpg (2)'!G21 -> 74960.75 | N17: =D17*1.4 -> 3784.2 | O17: =E17*1.4 -> 0 | P17: ='[1]Lpg (2)'!#REF! -> #REF! | Q17: ='[1]Summery Report'!#REF! -> #REF! | R17: =N17/B17 -> 161.85629 | S17: =Q17/B17 -> #REF!
A18: =Gen!A23 -> 44240 | B18: ='Summery Report'!E17 -> 22.08 | C18: =Gen!U23 -> 0.42059108 | D18: =Gen!T23 -> 2690 | E18: =Gen!AK23 -> 0 | F18: =Gen!AS23 -> 0 | G18: ='Utility report '!AC18 -> 0 | H18: ='Utility report '!AE18 -> 46 | I18: ='Water-Meter'!E18 -> 58 | J18: ='Lpg (2)'!B22 -> 54 | K18: ='Lpg (2)'!C23 -> 0 | L18: ='Lpg (2)'!D22 -> 0 | M18: ='Lpg (2)'!G22 -> 74975 | N18: =D18*1.4 -> 3766 | O18: =E18*1.4 -> 0 | P18: ='[1]Lpg (2)'!#REF! -> #REF! | Q18: ='[1]Summery Report'!#REF! -> #REF! | R18: =N18/B18 -> 170.56159 | S18: =Q18/B18 -> #REF!
A19: =Gen!A24 -> 44241 | B19: ='Summery Report'!E18 -> 19.48 | C19: =Gen!U24 -> 0.42069955 | D19: =Gen!T24 -> 2859 | E19: =Gen!AK24 -> 0 | F19: =Gen!AS24 -> 0 | G19: ='Utility report '!AC19 -> 88 | H19: ='Utility report '!AE19 -> 49 | I19: ='Water-Meter'!E19 -> 54 | J19: ='Lpg (2)'!B23 -> 51 | K19: ='Lpg (2)'!C24 -> 0 | L19: ='Lpg (2)'!D23 -> 0 | M19: ='Lpg (2)'!G23 -> 74968 | N19: =D19*1.4 -> 4002.6 | O19: =E19*1.4 -> 0 | P19: ='[1]Lpg (2)'!#REF! -> #REF! | Q19: ='[1]Summery Report'!#REF! -> #REF! | R19: =N19/B19 -> 205.47228 | S19: =Q19/B19 -> #REF!
A20: =Gen!A25 -> 44242 | B20: ='Summery Report'!E19 -> 12.99 | C20: =Gen!U25 -> 0.41529021 | D20: =Gen!T25 -> 2860 | E20: =Gen!AK25 -> 0 | F20: =Gen!AS25 -> 0 | G20: ='Utility report '!AC20 -> 98 | H20: ='Utility report '!AE20 -> 55 | I20: ='Water-Meter'!E20 -> 56 | J20: ='Lpg (2)'!B24 -> 50 | K20: ='Lpg (2)'!C25 -> 0 | L20: ='Lpg (2)'!D24 -> 0 | M20: ='Lpg (2)'!G24 -> 74980 | N20: =D20*1.4 -> 4004 | O20: =E20*1.4 -> 0 | P20: ='[1]Lpg (2)'!#REF! -> #REF! | Q20: ='[1]Summery Report'!#REF! -> #REF! | R20: =N20/B20 -> 308.23711 | S20: =Q20/B20 -> #REF!
A21: =Gen!A26 -> 44243 | B21: ='Summery Report'!E20 -> 9.09 | C21: =Gen!U26 -> 0.41954097 | D21: =Gen!T26 -> 2636 | E21: =Gen!AK26 -> 0 | F21: =Gen!AS26 -> 0 | G21: ='Utility report '!AC21 -> 34 | H21: ='Utility report '!AE21 -> 32 | I21: ='Water-Meter'!E21 -> 45 | J21: ='Lpg (2)'!B25 -> 50 | K21: ='Lpg (2)'!C25 -> 0 | L21: ='Lpg (2)'!D25 -> 0 | M21: ='Lpg (2)'!G25 -> 74998 | N21: =D21*1.4 -> 3690.4 | O21: =E21*1.4 -> 0 | P21: ='[1]Lpg (2)'!#REF! -> #REF! | Q21: ='[1]Summery Report'!#REF! -> #REF! | R21: =N21/B21 -> 405.9846 | S21: =Q21/B21 -> #REF!
A22: =Gen!A27 -> 44244 | B22: ='Summery Report'!E21 -> 11.69 | C22: =Gen!U27 -> 0.40314794 | D22: =Gen!T27 -> 2643 | E22: =Gen!AK27 -> 0 | F22: =Gen!AS27 -> 0 | G22: ='Utility report '!AC22 -> 34 | H22: ='Utility report '!AE22 -> 48 | I22: ='Water-Meter'!E22 -> 48 | J22: ='Lpg (2)'!B26 -> 51 | K22: ='Lpg (2)'!C26 -> 85 | L22: ='Lpg (2)'!D26 -> 85 | M22: ='Lpg (2)'!G26 -> 75012 | N22: =D22*1.4 -> 3700.2 | O22: =E22*1.4 -> 0 | P22: ='[1]Lpg (2)'!#REF! -> #REF! | Q22: ='[1]Summery Report'!#REF! -> #REF! | R22: =N22/B22 -> 316.52695 | S22: =Q22/B22 -> #REF!
A23: =Gen!A28 -> 44245 | B23: ='Summery Report'!E22 -> 11.69 | C23: =Gen!U28 -> 0.38842198 | D23: =Gen!T28 -> 2839 | E23: =Gen!AK28 -> 0 | F23: =Gen!AS28 -> 0 | G23: ='Utility report '!AC23 -> 33 | H23: ='Utility report '!AE23 -> 36 | I23: ='Water-Meter'!E23 -> 53 | J23: ='Lpg (2)'!B27 -> 50 | K23: ='Lpg (2)'!C27 -> 85 | L23: ='Lpg (2)'!D27 -> 85 | M23: ='Lpg (2)'!G27 -> 75027 | N23: =D23*1.4 -> 3974.6 | O23: =E23*1.4 -> 0 | P23: ='[1]Lpg (2)'!#REF! -> #REF! | Q23: ='[1]Summery Report'!#REF! -> #REF! | R23: =N23/B23 -> 340 | S23: =Q23/B23 -> #REF!
A24: =Gen!A29 -> 44246 | B24: ='Summery Report'!E23 -> 15.58 | C24: =Gen!U29 -> 0.41286096 | D24: =Gen!T29 -> 2992 | E24: =Gen!AK29 -> 0 | F24: =Gen!AS29 -> 0 | G24: ='Utility report '!AC24 -> 35 | H24: ='Utility report '!AE24 -> 23 | I24: ='Water-Meter'!E24 -> 65 | J24: ='Lpg (2)'!B28 -> 49 | K24: ='Lpg (2)'!C28 -> 85 | L24: ='Lpg (2)'!D28 -> 85 | M24: ='Lpg (2)'!G28 -> 75047.38 | N24: =D24*1.4 -> 4188.8 | O24: =E24*1.4 -> 0 | P24: ='[1]Lpg (2)'!#REF! -> #REF! | Q24: ='[1]Summery Report'!#REF! -> #REF! | R24: =N24/B24 -> 268.85751 | S24: =Q24/B24 -> #REF!
A25: =Gen!A30 -> 44247 | B25: ='Summery Report'!E24 -> 14.29 | C25: =Gen!U30 -> #DIV/0! | D25: =Gen!T30 -> 0 | E25: =Gen!AK30 -> 0 | F25: =Gen!AS30 -> 0 | G25: ='Utility report '!AC25 -> -46744 | H25: ='Utility report '!AE25 -> -211864 | I25: ='Water-Meter'!E25 -> 0 | J25: ='Lpg (2)'!B29 -> 47 | K25: ='Lpg (2)'!C29 -> 85 | L25: ='Lpg (2)'!D29 -> 85 | M25: ='Lpg (2)'!G29 -> 75065.86 | N25: =D25*1.4 -> 0 | O25: =E25*1.4 -> 0 | P25: ='[1]Lpg (2)'!#REF! -> #REF! | Q25: ='[1]Summery Report'!#REF! -> #REF! | R25: =N25/B25 -> 0 | S25: =Q25/B25 -> #REF!
A26: =Gen!A31 -> 44248 | B26: ='Summery Report'!E25 -> 0 | C26: =Gen!U31 -> #DIV/0! | D26: =Gen!T31 -> 0 | E26: =Gen!AK31 -> 0 | F26: =Gen!AS31 -> 0 | G26: ='Utility report '!AC26 -> 0 | H26: ='Utility report '!AE26 -> 0 | I26: ='Water-Meter'!E26 -> 0 | J26: ='Lpg (2)'!B30 -> 0 | K26: ='Lpg (2)'!C30 -> 0 | L26: ='Lpg (2)'!D30 -> 0 | M26: ='Lpg (2)'!G30 -> 0 | N26: =D26*1.4 -> 0 | O26: =E26*1.4 -> 0 | P26: ='[1]Lpg (2)'!#REF! -> #REF! | Q26: ='[1]Summery Report'!#REF! -> #REF! | R26: =N26/B26 -> #DIV/0! | S26: =Q26/B26 -> #REF!
A27: =Gen!A32 -> 44249 | B27: ='Summery Report'!E26 -> 0 | C27: =Gen!U32 -> #DIV/0! | D27: =Gen!T32 -> 0 | E27: =Gen!AK32 -> 0 | F27: =Gen!AS32 -> 0 | G27: ='Utility report '!AC27 -> 0 | H27: ='Utility report '!AE27 -> 0 | I27: ='Water-Meter'!E27 -> 0 | J27: ='Lpg (2)'!B31 -> 0 | K27: ='Lpg (2)'!C31 -> 0 | L27: ='Lpg (2)'!D31 -> 0 | M27: ='Lpg (2)'!G31 -> 0 | N27: =D27*1.4 -> 0 | O27: =E27*1.4 -> 0 | P27: ='[1]Lpg (2)'!#REF! -> #REF! | Q27: ='[1]Summery Report'!#REF! -> #REF! | R27: =N27/B27 -> #DIV/0! | S27: =Q27/B27 -> #REF!
A28: =Gen!A33 -> 44250 | B28: ='Summery Report'!E27 -> 0 | C28: =Gen!U33 -> #DIV/0! | D28: =Gen!T33 -> 0 | E28: =Gen!AK33 -> 0 | F28: =Gen!AS33 -> 0 | G28: ='Utility report '!AC28 -> 0 | H28: ='Utility report '!AE28 -> 0 | I28: ='Water-Meter'!E28 -> 0 | J28: ='Lpg (2)'!B32 -> 0 | K28: ='Lpg (2)'!C32 -> 0 | L28: ='Lpg (2)'!D32 -> 0 | M28: ='Lpg (2)'!G32 -> 0 | N28: =D28*1.4 -> 0 | O28: =E28*1.4 -> 0 | P28: ='[1]Lpg (2)'!#REF! -> #REF! | Q28: ='[1]Summery Report'!#REF! -> #REF! | R28: =N28/B28 -> #DIV/0! | S28: =Q28/B28 -> #REF!
A29: =Gen!A34 -> 44251 | B29: ='Summery Report'!E28 -> 0 | C29: =Gen!U34 -> #DIV/0! | D29: =Gen!T34 -> 0 | E29: =Gen!AK34 -> 0 | F29: =Gen!AS34 -> 0 | G29: ='Utility report '!AC29 -> 0 | H29: ='Utility report '!AE29 -> 0 | I29: ='Water-Meter'!E29 -> 0 | J29: ='Lpg (2)'!B33 -> 0 | K29: ='Lpg (2)'!C33 -> 0 | L29: ='Lpg (2)'!D33 -> 0 | M29: ='Lpg (2)'!G33 -> 0 | N29: =D29*1.4 -> 0 | O29: =E29*1.4 -> 0 | P29: ='[1]Lpg (2)'!#REF! -> #REF! | Q29: ='[1]Summery Report'!#REF! -> #REF! | R29: =N29/B29 -> #DIV/0! | S29: =Q29/B29 -> #REF!
A30: =Gen!A35 -> 44252 | B30: ='Summery Report'!E29 -> 0 | C30: =Gen!U35 -> #DIV/0! | D30: =Gen!T35 -> 0 | E30: =Gen!AK35 -> 0 | F30: =Gen!AS35 -> 0 | G30: ='Utility report '!AC30 -> 0 | H30: ='Utility report '!AE30 -> 0 | I30: ='Water-Meter'!E30 -> 0 | J30: ='Lpg (2)'!B34 -> 0 | K30: ='Lpg (2)'!C34 -> 0 | L30: ='Lpg (2)'!D34 -> 0 | M30: ='Lpg (2)'!G34 -> 0 | N30: =D30*1.4 -> 0 | O30: =E30*1.4 -> 0 | P30: ='[1]Lpg (2)'!#REF! -> #REF! | Q30: ='[1]Summery Report'!#REF! -> #REF! | R30: =N30/B30 -> #DIV/0! | S30: =Q30/B30 -> #REF!
A31: =Gen!A36 -> 44253 | B31: ='Summery Report'!E30 -> 0 | C31: =Gen!U36 -> #DIV/0! | D31: =Gen!T36 -> 0 | E31: =Gen!AK36 -> 0 | F31: =Gen!AS36 -> 0 | G31: ='Utility report '!AC31 -> 0 | H31: ='Utility report '!AE31 -> 0 | I31: ='Water-Meter'!E31 -> 0 | J31: ='Lpg (2)'!B35 -> 0 | K31: ='Lpg (2)'!C35 -> 0 | L31: ='Lpg (2)'!D35 -> 0 | M31: ='Lpg (2)'!G35 -> 0 | N31: =D31*1.4 -> 0 | O31: =E31*1.4 -> 0 | P31: ='[1]Lpg (2)'!#REF! -> #REF! | Q31: ='[1]Summery Report'!#REF! -> #REF! | R31: =N31/B31 -> #DIV/0! | S31: =Q31/B31 -> #REF!
A32: =Gen!A37 -> 44254 | B32: ='Summery Report'!E31 -> 0 | C32: =Gen!U37 -> #DIV/0! | D32: =Gen!T37 -> 0 | E32: =Gen!AK37 -> 0 | F32: =Gen!AS37 -> 0 | G32: ='Utility report '!AC32 -> 0 | H32: ='Utility report '!AE32 -> 0 | I32: ='Water-Meter'!E32 -> 0 | J32: ='Lpg (2)'!B36 -> 0 | K32: ='Lpg (2)'!C36 -> 0 | L32: ='Lpg (2)'!D36 -> 0 | M32: ='Lpg (2)'!G36 -> 0 | N32: =D32*1.4 -> 0 | O32: =E32*1.4 -> 0 | P32: ='[1]Lpg (2)'!#REF! -> #REF! | Q32: ='[1]Summery Report'!#REF! -> #REF! | R32: =N32/B32 -> #DIV/0! | S32: =Q32/B32 -> #REF!
... A36: =Gen!A41 -> 0 | B36: ='Summery Report'!E35 -> 0 | C36: =Gen!U41 -> #DIV/0! | D36: =Gen!T41 -> 0 | E36: =Gen!AK41 -> 0 | F36: =Gen!AS41 -> 0 | G36: ='Utility report '!AC36 -> 0 | H36: ='Utility report '!AE36 -> 0 | I36: ='Water-Meter'!E36 -> 0 | J36: ='Lpg (2)'!B40 -> 0 | K36: ='Lpg (2)'!C40 -> 0 | L36: ='Lpg (2)'!D40 -> 0 | M36: ='Lpg (2)'!G40 -> 0 | N36: =D36*1.4 -> 0 | O36: =E36*1.4 -> 0 | P36: ='[1]Lpg (2)'!#REF! -> #REF! | Q36: ='[1]Summery Report'!#REF! -> #REF! | R36: =N36/B36 -> #DIV/0! | S36: =Q36/B36 -> #REF!
A37: =Gen!A42 -> 0 | B37: ='Summery Report'!E36 -> 0 | C37: =Gen!U42 -> 0 | D37: =Gen!T42 -> 0 | E37: =Gen!AK42 -> 0 | F37: =Gen!AS42 -> 0 | G37: ='Utility report '!AC37 -> 0 | H37: ='Utility report '!AE37 -> 0 | I37: ='Water-Meter'!E37 -> 0 | J37: ='Lpg (2)'!B41 -> 0 | K37: ='Lpg (2)'!C41 -> 0 | L37: ='Lpg (2)'!D41 -> 0 | M37: ='Lpg (2)'!G41 -> 0 | Q37: ='[1]Summery Report'!#REF! -> #REF! | R37: =N37/B37 -> #DIV/0! | S37: =Q37/B37 -> #REF!
A39: Total | B39: =SUM(B7:B37) -> 211.3 | C39: =SUM(C7:C35) -> #DIV/0! | D39: =SUM(D7:D35) -> 48712 | E39: =SUM(E7:E35) -> 0 | F39: =SUM(F7:F35) -> 0 | G39: =SUM(G7:G35) -> -45884 | H39: =SUM(H7:H35) -> -211045 | I39: =SUM(I7:I35) -> 944 | J39: =SUM(J7:J35) -> 1149 | ... S39: =SUM(S7:S35) -> #REF!

Sheet Utility report 
A1: =A6 -> 44228
A2: Date | B2: Total occupancy | H2: Diesel balance LTS | I2: Diesel Deliveries | J2: Gen.Diesel consumption LTS | L2: Total Diesel consumption LTS | M2: Water Meter reading | N2: Water consumption m³ | O2: R.O WATER PRODUCTION LTRS + TIME | AA2: Total RO production | AB2: RO Meter reading | AD2: 0 | AE2: STP | AF2: GAS TANK A | AG2: GAS TANK B | AH2: GAS TANK C | AI2: Total Gas Tanks | AJ2: Kg /day | AK2: TOTAL GAS cons.
A3: Rate Tsh /$ | B3: 1640 | C3: Diesel cost / lits | D3: 2175 | F3: =SUM(D3/B3) -> 1.3262195 | H3: =Gen!C11 -> 35132.06 | K3: Transport consumption | M3: Balance | O3: PLANT NO 1 | S3: PLANT NO 2 | W3: PLANT NO 3 | AA3: /day | AB3: Balance | AD3: 0 | AE3: Production | AF3: Capacity | AG3: Capacity | AH3: Capacity | AI3: Kg | AJ3: /day | AK3: /day
B4: Rooms OCC | C4: % | D4: Guest Rooms Occ | F4: Electricity Production Cost /Room Occ by guest | G4: All Cost /Room Occ by guest | O4: Flow M3 | P4: Reading Hours Meter | Q4: Hrs | R4: total production M3 | S4: Flow M3 | T4: Reading Hours Meter | U4: Hrs | V4: total production M3 | W4: Flow M3 | X4: READING HOURS METER | Y4: Hrs | Z4: total production M3 | AA4: M3 | AC4: M3 | AE4: M3 | AF4: 2000 | AG4: 1000 | AH4: 1000 | AI4: =SUM([2]Sheet1!$AA$36) -> 950 | AJ4: Kg | AK4: M3
P5: 19032 | T5: 17522 | X5: 27013 | AB5: 45835 | AD5: 211010 | AF5: 0.85 | AG5: 0.85 | AH5: 0.85
A6: =Gen!A11 -> 44228 | B6: ='Summery Report'!E5 -> 10.39 | C6: =Gen!B11 -> 0.091 | D6: ='Summery Report'!E5 -> 10.39 | E6: =SUM(F3) -> 1.3262195 | F6: =SUM(J6*E6)/D6 -> 370.933 | G6: =SUM(L6*E6)/D6 -> 370.933 | H6: =Gen!C11 -> 35132.06 | I6: =Gen!E11 -> 0 | J6: =Gen!T11 -> 2906 | K6: =Gen!AK11 -> 0 | L6: =SUM(J6:K6) -> 2906 | M6: ='Water-Meter'!K46 -> 520.57466 | N6: ='Water-Meter'!E6 -> 58 | P6: 19032 | Q6: =SUM(P6-P5) -> 0 | R6: =SUM(Q6*O6) -> 0 | S6: 6.5 | T6: 17522 | U6: =T6-T5 -> 0 | V6: - | W6: 2.2 | X6: 27028 | Y6: =X6-X5 -> 15 | Z6: =Y6-Y5 -> 15 | AA6: =Z6-Z5 -> 15 | AB6: 45884 | AC6: =AB6-AB5 -> 49 | AD6: 211045 | AE6: =AD6-AD5 -> 35 | AF6: ='Lpg (2)'!B10*2000/85 -> 1929.4118 | AG6: ='Lpg (2)'!C10*1000/85 -> 0 | AH6: ='Lpg (2)'!D10*1000/85 -> 0 | AI6: =SUM(AF6*2000)+(AG6*1000)+(AH6*1000) -> 3858823.5 | AJ6: =SUM(AI5-AI6) -> -3858823.5
A7: =Gen!A12 -> 44229 | B7: ='Summery Report'!E6 -> 5.19 | C7: =Gen!B12 -> 0.065 | D7: ='Summery Report'!E6 -> 5.19 | E7: =SUM(E6) -> 1.3262195 | F7: =SUM(J7*E7)/D7 -> 728.0153 | G7: =SUM(L7*E7)/D7 -> 728.0153 | H7: =Gen!C12 -> 48625.25 | I7: =Gen!E12 -> 0 | J7: =Gen!T12 -> 2849 | K7: =Gen!AK12 -> 0 | L7: =SUM(J7:K7) -> 2849 | M7: ='Water-Meter'!K47 -> 618.98986 | N7: ='Water-Meter'!E7 -> 56 | P7: 19032 | Q7: =SUM(P7-P6) -> 0 | R7: =SUM(Q7*O7) -> 0 | S7: 6.5 | T7: 17522 | U7: =T7-T6 -> 0 | V7: =SUM(U7*S7) -> 0 | W7: 2.2 | X7: 27052 | Y7: =X7-X6 -> 24 | Z7: =SUM(Y7*W7) -> 52.8 | AA7: =SUM(Z7*X9) -> 1430880 | AB7: 45910 | AC7: =AB7-AB6 -> 26 | AD7: 211088 | AE7: =AD7-AD6 -> 43 | AF7: ='Lpg (2)'!B11*2000/85 -> 1905.8824 | AG7: ='Lpg (2)'!C11*1000/85 -> 0 | AH7: ='Lpg (2)'!D11*1000/85 -> 0 | AI7: =SUM(AF6*2000)+(AG7*1000)+(AH7*1000) -> 3858823.5 | AJ7: =SUM(AI6-AI7) -> 0
A8: =Gen!A13 -> 44230 | B8: ='Summery Report'!E7 -> 3.9 | C8: =Gen!B13 -> 0.039 | D8: ='Summery Report'!E7 -> 3.9 | E8: =SUM(E7) -> 1.3262195 | F8: =SUM(J8*E8)/D8 -> 883.80629 | G8: =SUM(L8*E8)/D8 -> 883.80629 | H8: =Gen!C13 -> 47451.81 | I8: =Gen!E13 -> 0 | J8: =Gen!T13 -> 2599 | K8: =Gen!AK13 -> 0 | L8: =SUM(J8:K8) -> 2599 | M8: ='Water-Meter'!K48 -> 590.65149 | N8: ='Water-Meter'!E8 -> 46 | P8: 19032 | Q8: =SUM(P8-P7) -> 0 | R8: =SUM(Q8*O8) -> 0 | S8: 6.5 | T8: 17522 | U8: =T8-T7 -> 0 | V8: =SUM(U8*S8) -> 0 | W8: 2.2 | X8: 27076.11 | Y8: =X8-X7 -> 24.11 | Z8: =SUM(Y8*W8) -> 53.042 | AA8: =SUM(Z8*X10) -> 1438711.2 | AB8: 45959 | AC8: =AB8-AB7 -> 49 | AD8: 211164 | AE8: =AD8-AD7 -> 76 | AF8: ='Lpg (2)'!B12*2000/85 -> 1788.2353 | AG8: ='Lpg (2)'!C12*1000/85 -> 0 | AH8: ='Lpg (2)'!D12*1000/85 -> 0 | AI8: =SUM(AF7*2000)+(AG8*1000)+(AH8*1000) -> 3811764.7 | AJ8: =SUM(AI7-AI8) -> 47058.824
A9: =Gen!A14 -> 44231 | B9: ='Summery Report'!E8 -> 3.9 | C9: =Gen!B14 -> 0.039 | D9: ='Summery Report'!E8 -> 3.9 | E9: =SUM(E8) -> 1.3262195 | F9: =SUM(J9*E9)/D9 -> 911.6909 | G9: =SUM(L9*E9)/D9 -> 911.6909 | H9: =Gen!C14 -> 46273.7 | I9: =Gen!E14 -> 0 | J9: =Gen!T14 -> 2681 | K9: =Gen!AK14 -> 0 | L9: =SUM(J9:K9) -> 2681 | M9: ='Water-Meter'!K49 -> 571.96521 | N9: ='Water-Meter'!E9 -> 52 | P9: 19032 | Q9: =SUM(P9-P8) -> 0 | R9: =SUM(Q9*O9) -> 0 | S9: 6.5 | T9: 17522 | U9: =T9-T8 -> 0 | V9: =SUM(U9*S9) -> 0 | W9: 2.2 | X9: 27100 | Y9: =X9-X8 -> 23.89 | Z9: =SUM(Y9*W9) -> 52.558 | AA9: =SUM(Z9*X11) -> 1426844.6 | AB9: 46008 | AC9: =AB9-AB8 -> 49 | AD9: 211234 | AE9: =AD9-AD8 -> 70 | AF9: ='Lpg (2)'!B13*2000/85 -> 1741.1765 | AG9: ='Lpg (2)'!C13*1000/85 -> 0 | AH9: ='Lpg (2)'!D13*1000/85 -> 0 | AI9: =SUM(AF8*2000)+(AG9*1000)+(AH9*1000) -> 3576470.6 | AJ9: =SUM(AI8-AI9) -> 235294.12
A10: =Gen!A15 -> 44232 | B10: ='Summery Report'!E9 -> 5.19 | C10: =Gen!B15 -> 0.0519 | D10: ='Summery Report'!E9 -> 5.19 | E10: =SUM(E9) -> 1.3262195 | F10: =SUM(J10*E10)/D10 -> 768.64514 | G10: =SUM(L10*E10)/D10 -> 768.64514 | H10: =Gen!C15 -> 45058.75 | I10: =Gen!E15 -> 0 | J10: =Gen!T15 -> 3008 | K10: =Gen!AK15 -> 0 | L10: =SUM(J10:K10) -> 3008 | M10: ='Water-Meter'!K50 -> 575.19119 | N10: ='Water-Meter'!E10 -> 45 | P10: 19032 | Q10: =SUM(P10-P9) -> 0 | R10: =SUM(Q10*O10) -> 0 | S10: 6.5 | T10: 17522 | U10: =T10-T9 -> 0 | V10: =SUM(U10*S10) -> 0 | W10: 2.2 | X10: 27124 | Y10: =X10-X9 -> 24 | Z10: =SUM(Y10*W10) -> 52.8 | AA10: =SUM(Z10*X12) -> 1433784 | AB10: 46046 | AC10: =AB10-AB9 -> 38 | AD10: 211259 | AE10: =AD10-AD9 -> 25 | AF10: ='Lpg (2)'!B14*2000/85 -> 1694.1176 | AG10: ='Lpg (2)'!C14*1000/85 -> 0 | AH10: ='Lpg (2)'!D14*1000/85 -> 0 | AI10: =SUM(AF9*2000)+(AG10*1000)+(AH10*1000) -> 3482352.9 | AJ10: =SUM(AI9-AI10) -> 94117.647
A11: =Gen!A16 -> 44233 | B11: ='Summery Report'!E10 -> 7.79 | C11: =Gen!B16 -> 0.0779 | D11: ='Summery Report'!E10 -> 7.79 | E11: =SUM(E10) -> 1.3262195 | F11: =SUM(J11*E11)/D11 -> 400.76004 | G11: =SUM(L11*E11)/D11 -> 400.76004 | H11: =Gen!C16 -> 43708.11 | I11: =Gen!E16 -> 0 | J11: =Gen!T16 -> 2354 | K11: =Gen!AK16 -> 0 | L11: =SUM(J11:K11) -> 2354 | M11: ='Water-Meter'!K51 -> 571.8416 | N11: ='Water-Meter'!E11 -> 45 | P11: 19032 | Q11: =SUM(P11-P10) -> 0 | R11: =SUM(Q11*O11) -> 0 | S11: 6.5 | T11: 17522 | U11: =T11-T10 -> 0 | V11: =SUM(U11*S11) -> 0 | W11: 2.2 | X11: 27148 | Y11: =X11-X10 -> 24 | Z11: =SUM(Y11*W11) -> 52.8 | AA11: =SUM(Z11*X13) -> 1433784 | AB11: 46080 | AC11: =AB11-AB10 -> 34 | AD11: 211295 | AE11: =AD11-AD10 -> 36 | AF11: ='Lpg (2)'!B15*2000/85 -> 1647.0588 | AG11: ='Lpg (2)'!C15*1000/85 -> 0 | AH11: ='Lpg (2)'!D15*1000/85 -> 0 | AI11: =SUM(AF10*2000)+(AG11*1000)+(AH11*1000) -> 3388235.3 | AJ11: =SUM(AI10-AI11) -> 94117.647
A12: =Gen!A17 -> 44234 | B12: ='Summery Report'!E11 -> 7.79 | C12: =Gen!B17 -> 0.0779 | D12: ='Summery Report'!E11 -> 7.79 | E12: =SUM(E11) -> 1.3262195 | F12: =SUM(J12*E12)/D12 -> 473.28501 | G12: =SUM(L12*E12)/D12 -> 473.28501 | H12: =Gen!C17 -> 42692.87 | I12: =Gen!E17 -> 0 | J12: =Gen!T17 -> 2780 | K12: =Gen!AK17 -> 0 | L12: =SUM(J12:K12) -> 2780 | M12: ='Water-Meter'!K52 -> 563.99248 | N12: ='Water-Meter'!E12 -> 58 | P12: 19032 | Q12: =SUM(P12-P11) -> 0 | R12: =SUM(Q12*O12) -> 0 | S12: 6.5 | T12: 17539 | U12: =T12-T11 -> 17 | V12: =SUM(U12*S12) -> 110.5 | W12: 2.2 | X12: 27155 | Y12: =X12-X11 -> 7 | Z12: =SUM(Y12*W12) -> 15.4 | AA12: =SUM(Z12*X14) -> 418187 | AB12: 46178 | AC12: =AB12-AB11 -> 98 | AD12: 211348 | AE12: =AD12-AD11 -> 53 | AF12: ='Lpg (2)'!B16*2000/85 -> 1623.5294 | AG12: ='Lpg (2)'!C16*1000/85 -> 0 | AH12: ='Lpg (2)'!D16*1000/85 -> 0 | AI12: =SUM(AF11*2000)+(AG12*1000)+(AH12*1000) -> 3294117.6 | AJ12: =SUM(AI11-AI12) -> 94117.647
A13: =Gen!A18 -> 44235 | B13: ='Summery Report'!E12 -> 5.19 | C13: =Gen!B18 -> 0.0519 | D13: ='Summery Report'!E12 -> 5.19 | E13: =SUM(E12) -> 1.3262195 | F13: =SUM(J13*E13)/D13 -> 650.33307 | G13: =SUM(L13*E13)/D13 -> 650.33307 | H13: =Gen!C18 -> 41550.28 | I13: =Gen!E18 -> 0 | J13: =Gen!T18 -> 2545 | K13: =Gen!AK18 -> 0 | L13: =SUM(J13:K13) -> 2545 | M13: ='Water-Meter'!K53 -> 528.1818 | N13: ='Water-Meter'!E13 -> 45 | P13: 19032 | Q13: =SUM(P13-P12) -> 0 | R13: =SUM(Q13*O13) -> 0 | S13: 6.5 | T13: 17539 | U13: =T13-T12 -> 0 | V13: =SUM(U13*S13) -> 0 | W13: 2.2 | X13: 27155 | Y13: =X13-X12 -> 0 | Z13: =SUM(Y13*W13) -> 0 | AA13: =SUM(Z13*X15) -> 0 | AB13: 46178 | AC13: =AB13-AB12 -> 0 | AD13: 211373 | AE13: =AD13-AD12 -> 25 | AF13: ='Lpg (2)'!B17*2000/85 -> 1529.4118 | AG13: ='Lpg (2)'!C17*1000/85 -> 0 | AH13: ='Lpg (2)'!D17*1000/85 -> 0 | AI13: =SUM(AF12*2000)+(AG13*1000)+(AH13*1000) -> 3247058.8 | AJ13: =SUM(AI12-AI13) -> 47058.824
A14: =Gen!A19 -> 44236 | B14: ='Summery Report'!E13 -> 10 | C14: =Gen!B19 -> 0.1039 | D14: ='Summery Report'!E13 -> 10 | E14: =SUM(E13) -> 1.3262195 | F14: =SUM(J14*E14)/D14 -> 351.84604 | G14: =SUM(L14*E14)/D14 -> 351.84604 | H14: =Gen!C19 -> 40432.1 | I14: =Gen!E19 -> 0 | J14: =Gen!T19 -> 2653 | K14: =Gen!AK19 -> 0 | L14: =SUM(J14:K14) -> 2653 | M14: ='Water-Meter'!K54 -> 577.41205 | N14: ='Water-Meter'!E14 -> 60 | P14: 19032 | Q14: =SUM(P14-P13) -> 0 | R14: =SUM(Q14*O14) -> 0 | S14: 6.5 | T14: 17554 | U14: =T14-T13 -> 15 | V14: =SUM(U14*S14) -> 97.5 | W14: 2.2 | X14: 27155 | Y14: =X14-X13 -> 0 | Z14: =SUM(Y14*W14) -> 0 | AA14: =SUM(Z14*X16) -> 0 | AB14: 46322 | AC14: =AB14-AB13 -> 144 | AD14: 211409 | AE14: =AD14-AD13 -> 36 | AF14: ='Lpg (2)'!B18*2000/85 -> 1505.8824 | AG14: ='Lpg (2)'!C18*1000/85 -> 0 | AH14: ='Lpg (2)'!D18*1000/85 -> 0 | AI14: =SUM(AF13*2000)+(AG14*1000)+(AH14*1000) -> 3058823.5 | AJ14: =SUM(AI13-AI14) -> 188235.29
A15: =Gen!A20 -> 44237 | B15: ='Summery Report'!E14 -> 10.39 | C15: =Gen!B20 -> 0.1039 | D15: ='Summery Report'!E14 -> 10.39 | E15: =SUM(E14) -> 1.3262195 | F15: =SUM(J15*E15)/D15 -> 318.2161 | G15: =SUM(L15*E15)/D15 -> 318.2161 | H15: =Gen!C20 -> 39164.81 | I15: =Gen!E20 -> 0 | J15: =Gen!T20 -> 2493 | K15: =Gen!AK20 -> 0 | L15: =SUM(J15:K15) -> 2493 | M15: ='Water-Meter'!K55 -> 443.44953 | N15: ='Water-Meter'!E15 -> 57 | P15: 19032 | Q15: =SUM(P15-P14) -> 0 | R15: =SUM(Q15*O15) -> 0 | S15: 6.5 | T15: 17554 | U15: =T15-T14 -> 0 | V15: =SUM(U15*S15) -> 0 | W15: 2.2 | X15: 27155 | Y15: =X15-X14 -> 0 | Z15: =SUM(Y15*W15) -> 0 | AA15: =SUM(Z15*X17) -> 0 | AB15: 46322 | AC15: =AB15-AB14 -> 0 | AD15: 211445 | AE15: =AD15-AD14 -> 36 | AF15: ='Lpg (2)'!B19*2000/85 -> 1435.2941 | AG15: ='Lpg (2)'!C19*1000/85 -> 0 | AH15: ='Lpg (2)'!D19*1000/85 -> 0 | AI15: =SUM(AF15*2000)+(AG15*1000)+(AH15*1000) -> 2870588.2 | AJ15: =SUM(AI14-AI15) -> 188235.29
A16: =Gen!A21 -> 44238 | B16: ='Summery Report'!E15 -> 11.69 | C16: =Gen!B21 -> 0.1169 | D16: ='Summery Report'!E15 -> 11.69 | E16: =SUM(E15) -> 1.3262195 | F16: =SUM(J16*E16)/D16 -> 286.79922 | G16: =SUM(L16*E16)/D16 -> 286.79922 | H16: =Gen!C21 -> 38115.44 | I16: =Gen!E21 -> 0 | J16: =Gen!T21 -> 2528 | K16: =Gen!AK21 -> 0 | L16: =SUM(J16:K16) -> 2528 | M16: ='Water-Meter'!K56 -> 440.60668 | N16: ='Water-Meter'!E16 -> 49 | P16: 19032 | Q16: =SUM(P16-P15) -> 0 | R16: =SUM(Q16*O16) -> 0 | S16: 6.5 | T16: 17571 | U16: =T16-T15 -> 17 | V16: =SUM(U16*S16) -> 110.5 | W16: 2.2 | X16: 27155 | Y16: =X16-X15 -> 0 | Z16: =SUM(Y16*W16) -> 0 | AA16: =SUM(Z16*X18) -> 0 | AB16: 46422 | AC16: =AB16-AB15 -> 100 | AD16: 211520 | AE16: =AD16-AD15 -> 75 | AF16: ='Lpg (2)'!B20*2000/85 -> 1411.7647 | AG16: ='Lpg (2)'!C20*1000/85 -> 0 | AH16: ='Lpg (2)'!D20*1000/85 -> 0 | AI16: =SUM(AF16*2000)+(AG16*1000)+(AH16*1000) -> 2823529.4 | AJ16: =SUM(AI15-AI16) -> 47058.824
A17: =Gen!A22 -> 44239 | B17: ='Summery Report'!E16 -> 23.38 | C17: =Gen!B22 -> 0.2338 | D17: ='Summery Report'!E16 -> 23.38 | E17: =SUM(E16) -> 1.3262195 | F17: =SUM(J17*E17)/D17 -> 153.3264 | G17: =SUM(L17*E17)/D17 -> 153.3264 | H17: =Gen!C22 -> 36989.9 | I17: =Gen!E22 -> 0 | J17: =Gen!T22 -> 2703 | K17: =Gen!AK22 -> 0 | L17: =SUM(J17:K17) -> 2703 | M17: ='Water-Meter'!K57 -> 488.84997 | N17: ='Water-Meter'!E17 -> 52 | P17: 19032 | Q17: =SUM(P18-P16) -> 0 | R17: =SUM(Q17*O17) -> 0 | S17: 6.5 | T17: 17571 | U17: =T17-T16 -> 0 | V17: =SUM(U17*S17) -> 0 | W17: 2.2 | X17: 27155 | Y17: =X17-X16 -> 0 | Z17: =SUM(Y17*W17) -> 0 | AA17: =SUM(Z17*X19) -> 0 | AB17: 46422 | AC17: =AB17-AB16 -> 0 | AD17: 211575 | AE17: =AD17-AD16 -> 55 | AF17: ='Lpg (2)'!B21*2000/85 -> 1294.1176 | AG17: ='Lpg (2)'!C21*1000/85 -> 0 | AH17: ='Lpg (2)'!D21*1000/85 -> 0 | AI17: =SUM(AF17*2000)+(AG17*1000)+(AH17*1000) -> 2588235.3 | AJ17: =SUM(AI16-AI17) -> 235294.12
A18: =Gen!A23 -> 44240 | B18: ='Summery Report'!E17 -> 22.08 | C18: =Gen!B23 -> 0.2208 | D18: ='Summery Report'!E17 -> 22.08 | E18: =SUM(E17) -> 1.3262195 | F18: =SUM(J18*E18)/D18 -> 161.57294 | G18: =SUM(L18*E18)/D18 -> 161.57294 | H18: =Gen!C23 -> 35756.75 | I18: =Gen!E23 -> 15000 | J18: =Gen!T23 -> 2690 | K18: =Gen!AK23 -> 0 | L18: =SUM(J18:K18) -> 2690 | M18: ='Water-Meter'!K58 -> 473.97031 | N18: ='Water-Meter'!E18 -> 58 | P18: 19032 | R18: =SUM(Q18*O18) -> 0 | S18: 6.5 | T18: 17588 | U18: =T18-T17 -> 17 | V18: =SUM(U18*S19) -> 110.5 | W18: 2.2 | X18: 27155 | Y18: =X18-X17 -> 0 | Z18: =SUM(Y18*W18) -> 0 | AA18: =SUM(Z18*X20) -> 0 | AB18: 46422 | AC18: =AB18-AB17 -> 0 | AD18: 211621 | AE18: =AD18-AD17 -> 46 | AF18: ='Lpg (2)'!B22*2000/85 -> 1270.5882 | AG18: ='Lpg (2)'!C22*1000/85 -> 0 | AH18: ='Lpg (2)'!D22*1000/85 -> 0 | AI18: =SUM(AF18*2000)+(AG18*1000)+(AH18*1000) -> 2541176.5 | AJ18: =SUM(AI17-AI18) -> 47058.824
A19: =Gen!A24 -> 44241 | B19: ='Summery Report'!E18 -> 19.48 | C19: =Gen!B24 -> 0.1948 | D19: ='Summery Report'!E18 -> 19.48 | E19: =SUM(E18) -> 1.3262195 | F19: =SUM(J19*E19)/D19 -> 194.64382 | G19: =SUM(L19*E19)/D19 -> 194.64382 | H19: =Gen!C24 -> 34151.22 | I19: =Gen!E24 -> 0 | J19: =Gen!T24 -> 2859 | K19: =Gen!AK24 -> 0 | L19: =SUM(J19:K19) -> 2859 | M19: ='Water-Meter'!K59 -> 419.49228 | N19: ='Water-Meter'!E19 -> 54 | P19: 19032 | R19: =SUM(Q19*O19) -> 0 | S19: 6.5 | T19: 17588 | U19: =T19-T18 -> 0 | V19: =SUM(U19*#REF!) -> #REF! | W19: 2.3 | X19: 27170 | Y19: =X19-X18 -> 15 | Z19: =SUM(Y19*W19) -> 34.5 | AA19: =SUM(Z19*X21) -> 939021 | AB19: 46510 | AC19: =AB19-AB18 -> 88 | AD19: 211670 | AE19: =AD19-AD18 -> 49 | AF19: ='Lpg (2)'!B23*2000/85 -> 1200 | AG19: ='Lpg (2)'!C23*1000/85 -> 0 | AH19: ='Lpg (2)'!D23*1000/85 -> 0 | AI19: =SUM(AF19*2000)+(AG19*1000)+(AH19*1000) -> 2400000 | AJ19: =SUM(AI18-AI19) -> 141176.47
A20: =Gen!A25 -> 44242 | B20: ='Summery Report'!E19 -> 12.99 | C20: =Gen!B25 -> 0.1299 | D20: ='Summery Report'!E19 -> 12.99 | E20: =SUM(E19) -> 1.3262195 | F20: =SUM(J20*E20)/D20 -> 291.9929 | G20: =SUM(L20*E20)/D20 -> 291.9929 | H20: =Gen!C25 -> 32796.44 | I20: =Gen!E25 -> 0 | J20: =Gen!T25 -> 2860 | K20: =Gen!AK25 -> 0 | L20: =SUM(J20:K20) -> 2860 | M20: ='Water-Meter'!K60 -> 373.01954 | N20: ='Water-Meter'!E20 -> 56 | P20: 19032 | Q20: =SUM(P20-P19) -> 0 | R20: =SUM(Q20*O20) -> 0 | S20: 6.5 | T20: 17588 | U20: =T20-T19 -> 0 | V20: =SUM(U20*S20) -> 0 | W20: 2.3 | X20: 27195 | Y20: =X20-X19 -> 25 | Z20: =SUM(Y20*W20) -> 57.5 | AA20: =SUM(Z20*X22) -> 1566415 | AB20: 46608 | AC20: =AB20-AB19 -> 98 | AD20: 211725 | AE20: =AD20-AD19 -> 55 | AF20: ='Lpg (2)'!B24*2000/85 -> 1176.4706 | AG20: ='Lpg (2)'!C24*1000/85 -> 0 | AH20: ='Lpg (2)'!D24*1000/85 -> 0 | AI20: =SUM(AF20*2000)+(AG20*1000)+(AH20*1000) -> 2352941.2 | AJ20: =SUM(AI19-AI20) -> 47058.824
A21: =Gen!A26 -> 44243 | B21: ='Summery Report'!E20 -> 9.09 | C21: =Gen!B26 -> 0.0909 | D21: ='Summery Report'!E20 -> 9.09 | E21: =SUM(E20) -> 1.3262195 | F21: =SUM(J21*E21)/D21 -> 384.58907 | G21: =SUM(L21*E21)/D21 -> 384.58907 | H21: =Gen!C26 -> 31573.62 | I21: =Gen!E26 -> 0 | J21: =Gen!T26 -> 2636 | K21: =Gen!AK26 -> 0 | L21: =SUM(J21:K21) -> 2636 | M21: ='Water-Meter'!K61 -> 442.26249 | N21: ='Water-Meter'!E21 -> 45 | P21: 19032 | Q21: =SUM(P21-P20) -> 0 | R21: =SUM(Q21*O21) -> 0 | S21: 6.5 | T21: 17588 | U21: =T22-T20 -> 0 | V21: =SUM(U21*S21) -> 0 | W21: 2.3 | X21: 27218 | Y21: =X21-X20 -> 23 | Z21: =SUM(Y21*W21) -> 52.9 | AA21: =SUM(Z21*X23) -> 1442371.4 | AB21: 46642 | AC21: =AB21-AB20 -> 34 | AD21: 211757 | AE21: =AD21-AD20 -> 32 | AF21: ='Lpg (2)'!B25*2000/85 -> 1176.4706 | AG21: ='Lpg (2)'!C25*1000/85 -> 0 | AH21: ='Lpg (2)'!D25*1000/85 -> 0 | AI21: =SUM(AF21*2000)+(AG21*1000)+(AH21*1000) -> 2352941.2 | AJ21: =SUM(AI20-AI21) -> 0
A22: =Gen!A27 -> 44244 | B22: ='Summery Report'!E21 -> 11.69 | C22: =Gen!B27 -> 0.1169 | D22: ='Summery Report'!E21 -> 11.69 | E22: =SUM(E21) -> 1.3262195 | F22: =SUM(J22*E22)/D22 -> 299.84587 | G22: =SUM(L22*E22)/D22 -> 299.84587 | H22: =Gen!C27 -> 45277.76 | I22: =Gen!E27 -> 0 | J22: =Gen!T27 -> 2643 | K22: =Gen!AK27 -> 0 | L22: =SUM(J22:K22) -> 2643 | M22: ='Water-Meter'!K62 -> 427.39732 | N22: ='Water-Meter'!E22 -> 48 | P22: 19032 | Q22: =SUM(P22-P21) -> 0 | R22: =SUM(Q22*O22) -> 0 | S22: 6.5 | T22: 17588 | U22: =T23-T21 -> 0 | V22: =SUM(U22*S22) -> 0 | W22: 2 | X22: 27242 | Y22: =X22-X21 -> 24 | Z22: =SUM(Y22*W22) -> 48 | AA22: =SUM(Z22*X24) -> 1309968 | AB22: 46676 | AC22: =AB22-AB21 -> 34 | AD22: 211805 | AE22: =AD22-AD21 -> 48 | AF22: ='Lpg (2)'!B26*2000/85 -> 1200 | AG22: ='Lpg (2)'!C26*1000/85 -> 1000 | AH22: ='Lpg (2)'!D26*1000/85 -> 1000 | AI22: =SUM(AF22*2000)+(AG22*1000)+(AH22*1000) -> 4400000 | AJ22: =SUM(AI21-AI22) -> -2047058.8
A23: =Gen!A28 -> 44245 | B23: ='Summery Report'!E22 -> 11.69 | C23: =Gen!B28 -> 0.1169 | D23: ='Summery Report'!E22 -> 11.69 | E23: =SUM(E22) -> 1.3262195 | F23: =SUM(J23*E23)/D23 -> 322.08188 | G23: =SUM(L23*E23)/D23 -> 322.08188 | H23: =Gen!C28 -> 43962.94 | I23: =Gen!E28 -> 0 | J23: =Gen!T28 -> 2839 | K23: =Gen!AK28 -> 0 | L23: =SUM(J23:K23) -> 2839 | M23: ='Water-Meter'!K63 -> 402.40273 | N23: ='Water-Meter'!E23 -> 53 | P23: 19032 | Q23: =SUM(P23-P22) -> 0 | R23: =SUM(Q23*O23) -> 0 | S23: 6.5 | T23: 17588 | U23: =T24-T22 -> 0 | V23: =SUM(U23*S23) -> 0 | W23: 2 | X23: 27266 | Y23: =X23-X22 -> 24 | Z23: =SUM(Y23*W23) -> 48 | AA23: =SUM(Z23*X25) -> 0 | AB23: 46709 | AC23: =AB23-AB22 -> 33 | AD23: 211841 | AE23: =AD23-AD22 -> 36 | AF23: ='Lpg (2)'!B27*2000/85 -> 1176.4706 | AG23: ='Lpg (2)'!C27*1000/85 -> 1000 | AH23: ='Lpg (2)'!D27*1000/85 -> 1000 | AI23: =SUM(AF23*2000)+(AG23*1000)+(AH23*1000) -> 4352941.2 | AJ23: =SUM(AI22-AI23) -> 47058.824
A24: =Gen!A29 -> 44246 | B24: ='Summery Report'!E23 -> 15.58 | C24: =Gen!B29 -> 0.1558 | D24: ='Summery Report'!E23 -> 15.58 | E24: =SUM(E23) -> 1.3262195 | F24: =SUM(J24*E24)/D24 -> 254.68863 | G24: =SUM(L24*E24)/D24 -> 254.68863 | H24: =Gen!C29 -> 42260.88 | I24: =Gen!E29 -> 0 | J24: =Gen!T29 -> 2992 | K24: =Gen!AK29 -> 0 | L24: =SUM(J24:K24) -> 2992 | M24: ='Water-Meter'!K64 -> 399.55263 | N24: ='Water-Meter'!E24 -> 65 | P24: 19032 | Q24: =SUM(P24-P23) -> 0 | R24: =SUM(Q24*O24) -> 0 | S24: 6.5 | T24: 17588 | U24: =T24-T23 -> 0 | V24: =SUM(U24*S24) -> 0 | W24: 2 | X24: 27291 | Y24: =X24-X23 -> 25 | Z24: =SUM(Y24*W24) -> 50 | AA24: =SUM(Z24*X26) -> 0 | AB24: 46744 | AC24: =AB24-AB23 -> 35 | AD24: 211864 | AE24: =AD24-AD23 -> 23 | AF24: ='Lpg (2)'!B28*2000/85 -> 1152.9412 | AG24: ='Lpg (2)'!C28*1000/85 -> 1000 | AH24: ='Lpg (2)'!D28*1000/85 -> 1000 | AI24: =SUM(AF24*2000)+(AG24*1000)+(AH24*1000) -> 4305882.4 | AJ24: =SUM(AI23-AI24) -> 47058.824
A25: =Gen!A30 -> 44247 | B25: ='Summery Report'!E24 -> 14.29 | C25: =Gen!B30 -> 0.1429 | D25: ='Summery Report'!E24 -> 14.29 | E25: =SUM(E24) -> 1.3262195 | F25: =SUM(J25*E25)/D25 -> 0 | G25: =SUM(L25*E25)/D25 -> 0 | H25: =Gen!C30 -> 41025.6 | I25: =Gen!E30 -> 0 | J25: =Gen!T30 -> 0 | K25: =Gen!AK30 -> 0 | L25: =SUM(J25:K25) -> 0 | M25: ='Water-Meter'!K65 -> 501.92378 | N25: ='Water-Meter'!E25 -> 0 | Q25: =SUM(P25-P24) -> -19032 | R25: =SUM(Q25*O25) -> 0 | U25: =T25-T24 -> -17588 | V25: =SUM(U25*S25) -> 0 | Y25: =X25-X24 -> -27291 | Z25: =SUM(Y25*W25) -> 0 | AA25: =SUM(Z25*X27) -> 0 | AC25: =AB25-AB24 -> -46744 | AE25: =AD25-AD24 -> -211864 | AF25: ='Lpg (2)'!B29*2000/85 -> 1105.8824 | AG25: ='Lpg (2)'!C29*1000/85 -> 1000 | AH25: ='Lpg (2)'!D29*1000/85 -> 1000 | AI25: =SUM(AF25*2000)+(AG25*1000)+(AH25*1000) -> 4211764.7 | AJ25: =SUM(AI24-AI25) -> 94117.647
A26: =Gen!A31 -> 44248 | B26: ='Summery Report'!E25 -> 0 | C26: =Gen!B31 -> 0 | D26: ='Summery Report'!E25 -> 0 | E26: =SUM(E25) -> 1.3262195 | F26: =SUM(J26*E26)/D26 -> #DIV/0! | G26: =SUM(L26*E26)/D26 -> #DIV/0! | H26: =Gen!C31 -> 41025.6 | I26: =Gen!E31 -> 0 | J26: =Gen!T31 -> 0 | K26: =Gen!AK31 -> 0 | L26: =SUM(J26:K26) -> 0 | M26: ='Water-Meter'!K66 -> 0 | N26: ='Water-Meter'!E26 -> 0 | Q26: =SUM(P26-P25) -> 0 | R26: =SUM(Q26*O26) -> 0 | U26: =T26-T25 -> 0 | V26: =SUM(U26*S26) -> 0 | Y26: =X26-X25 -> 0 | Z26: =SUM(Y26*W26) -> 0 | AA26: =SUM(Z26*X28) -> 0 | AC26: =AB26-AB25 -> 0 | AE26: =AD26-AD25 -> 0 | AF26: ='Lpg (2)'!B30*2000/85 -> 0 | AG26: ='Lpg (2)'!C30*1000/85 -> 0 | AH26: ='Lpg (2)'!D30*1000/85 -> 0 | AI26: =SUM(AF26*2000)+(AG26*1000)+(AH26*1000) -> 0 | AJ26: =SUM(AI25-AI26) -> 4211764.7
A27: =Gen!A32 -> 44249 | B27: ='Summery Report'!E26 -> 0 | C27: =Gen!B32 -> 0 | D27: ='Summery Report'!E26 -> 0 | E27: =SUM(E26) -> 1.3262195 | F27: =SUM(J27*E27)/D27 -> #DIV/0! | G27: =SUM(L27*E27)/D27 -> #DIV/0! | H27: =Gen!C32 -> 41025.6 | I27: =Gen!E32 -> 0 | J27: =Gen!T32 -> 0 | K27: =Gen!AK32 -> 0 | L27: =SUM(J27:K27) -> 0 | M27: ='Water-Meter'!K67 -> 0 | N27: ='Water-Meter'!E27 -> 0 | Q27: =SUM(P27-P26) -> 0 | R27: =SUM(Q27*O27) -> 0 | U27: =T27-T26 -> 0 | V27: =SUM(U27*S27) -> 0 | Y27: =X27-X26 -> 0 | Z27: =SUM(Y27*W27) -> 0 | AA27: =SUM(Z27*X29) -> 0 | AC27: =AB27-AB26 -> 0 | AE27: =AD27-AD26 -> 0 | AF27: ='Lpg (2)'!B31*2000/85 -> 0 | AG27: ='Lpg (2)'!C31*1000/85 -> 0 | AH27: ='Lpg (2)'!D31*1000/85 -> 0 | AI27: =SUM(AF27*2000)+(AG27*1000)+(AH27*1000) -> 0 | AJ27: =SUM(AI26-AI27) -> 0
A28: =Gen!A33 -> 44250 | B28: ='Summery Report'!E27 -> 0 | C28: =Gen!B33 -> 0 | D28: ='Summery Report'!E27 -> 0 | E28: =SUM(E27) -> 1.3262195 | F28: =SUM(J28*E28)/D28 -> #DIV/0! | G28: =SUM(L28*E28)/D28 -> #DIV/0! | H28: =Gen!C33 -> 41025.6 | I28: =Gen!E33 -> 0 | J28: =Gen!T33 -> 0 | K28: =Gen!AK33 -> 0 | L28: =SUM(J28:K28) -> 0 | M28: ='Water-Meter'!K68 -> 0 | N28: ='Water-Meter'!E28 -> 0 | Q28: =SUM(P28-P27) -> 0 | R28: =SUM(Q28*O28) -> 0 | U28: =T28-T27 -> 0 | V28: =SUM(U28*S28) -> 0 | Y28: =X28-X27 -> 0 | Z28: =SUM(Y28*W28) -> 0 | AA28: =SUM(Z28*X30) -> 0 | AC28: =SUM(AB28-AB27) -> 0 | AE28: =AD28-AD27 -> 0 | AF28: ='Lpg (2)'!B32*2000/85 -> 0 | AG28: ='Lpg (2)'!C32*1000/85 -> 0 | AH28: ='Lpg (2)'!D32*1000/85 -> 0 | AI28: =SUM(AF28*2000)+(AG28*1000)+(AH28*1000) -> 0 | AJ28: =SUM(AI27-AI28) -> 0
A29: =Gen!A34 -> 44251 | B29: ='Summery Report'!E28 -> 0 | C29: =Gen!B34 -> 0 | D29: ='Summery Report'!E28 -> 0 | E29: =SUM(E28) -> 1.3262195 | F29: =SUM(J29*E29)/D29 -> #DIV/0! | G29: =SUM(L29*E29)/D29 -> #DIV/0! | H29: =Gen!C34 -> 41025.6 | I29: =Gen!E34 -> 0 | J29: =Gen!T34 -> 0 | K29: =Gen!AK34 -> 0 | L29: =SUM(J29:K29) -> 0 | M29: ='Water-Meter'!K69 -> 0 | N29: ='Water-Meter'!E29 -> 0 | Q29: =SUM(P29-P28) -> 0 | R29: =SUM(Q29*O29) -> 0 | U29: =T29-T28 -> 0 | V29: =SUM(U29*S29) -> 0 | Y29: =X29-X28 -> 0 | Z29: =SUM(Y29*W29) -> 0 | AA29: =SUM(Z29*X31) -> 0 | AC29: =SUM(AB29-AB28) -> 0 | AE29: =AD29-AD28 -> 0 | AF29: ='Lpg (2)'!B33*2000/85 -> 0 | AG29: ='Lpg (2)'!C33*1000/85 -> 0 | AH29: ='Lpg (2)'!D33*1000/85 -> 0 | AI29: =SUM(AF29*2000)+(AG29*1000)+(AH29*1000) -> 0 | AJ29: =SUM(AI28-AI29) -> 0
A30: =Gen!A35 -> 44252 | B30: ='Summery Report'!E29 -> 0 | C30: =Gen!B35 -> 0 | D30: ='Summery Report'!E29 -> 0 | E30: =SUM(E29) -> 1.3262195 | F30: =SUM(J30*E30)/D30 -> #DIV/0! | G30: =SUM(L30*E30)/D30 -> #DIV/0! | H30: =Gen!C35 -> 41025.6 | I30: =Gen!E35 -> 0 | J30: =Gen!T35 -> 0 | K30: =Gen!AK35 -> 0 | L30: =SUM(J30:K30) -> 0 | M30: ='Water-Meter'!K70 -> 0 | N30: ='Water-Meter'!E30 -> 0 | Q30: =SUM(P30-P29) -> 0 | R30: =SUM(Q30*O30) -> 0 | U30: =T30-T29 -> 0 | V30: =SUM(U30*S30) -> 0 | Y30: =X30-X29 -> 0 | Z30: =SUM(Y30*W30) -> 0 | AA30: =SUM(Z30*X32) -> 0 | AC30: =SUM(AB30-AB29) -> 0 | AE30: =AD30-AD29 -> 0 | AF30: ='Lpg (2)'!B34*2000/85 -> 0 | AG30: ='Lpg (2)'!C34*1000/85 -> 0 | AH30: ='Lpg (2)'!D34*1000/85 -> 0 | AI30: =SUM(AF30*2000)+(AG30*1000)+(AH30*1000) -> 0 | AJ30: =SUM(AI29-AI30) -> 0
A31: =Gen!A36 -> 44253 | B31: ='Summery Report'!E30 -> 0 | C31: =Gen!B36 -> 0 | D31: ='Summery Report'!E30 -> 0 | E31: =SUM(E30) -> 1.3262195 | F31: =SUM(J31*E31)/D31 -> #DIV/0! | G31: =SUM(L31*E31)/D31 -> #DIV/0! | H31: =Gen!C36 -> 41025.6 | I31: =Gen!E36 -> 15000 | J31: =Gen!T36 -> 0 | K31: =Gen!AK36 -> 0 | L31: =SUM(J31:K31) -> 0 | M31: ='Water-Meter'!K71 -> 0 | N31: ='Water-Meter'!E31 -> 0 | Q31: =SUM(P31-P30) -> 0 | R31: =SUM(Q31*O31) -> 0 | U31: =T31-T30 -> 0 | V31: =SUM(U31*S31) -> 0 | Y31: =X31-X30 -> 0 | Z31: =SUM(Y31*W31) -> 0 | AA31: =SUM(Z31*X33) -> 0 | AC31: =SUM(AB31-AB30) -> 0 | AE31: =AD31-AD30 -> 0 | AF31: ='Lpg (2)'!B35*2000/85 -> 0 | AG31: ='Lpg (2)'!C35*1000/85 -> 0 | AH31: ='Lpg (2)'!D35*1000/85 -> 0 | AI31: =SUM(AF31*2000)+(AG31*1000)+(AH31*1000) -> 0 | AJ31: =SUM(AI30-AI31) -> 0
A32: =Gen!A37 -> 44254 | B32: ='Summery Report'!E31 -> 0 | C32: =Gen!B37 -> 0 | D32: ='Summery Report'!E31 -> 0 | E32: =SUM(E31) -> 1.3262195 | F32: =SUM(J32*E32)/D32 -> #DIV/0! | G32: =SUM(L32*E32)/D32 -> #DIV/0! | H32: =Gen!C37 -> 41025.6 | I32: =Gen!E37 -> 0 | J32: =Gen!T37 -> 0 | K32: =Gen!AK37 -> 0 | L32: =SUM(J32:K32) -> 0 | M32: ='Water-Meter'!K72 -> 0 | N32: ='Water-Meter'!E32 -> 0 | Q32: =SUM(P32-P31) -> 0 | R32: =SUM(Q32*O32) -> 0 | U32: =T32-T31 -> 0 | V32: =SUM(U32*S32) -> 0 | Y32: =X32-X31 -> 0 | Z32: =SUM(Y32*W32) -> 0 | AA32: =SUM(Z32*X34) -> 0 | AC32: =SUM(AB32-AB31) -> 0 | AE32: =AD32-AD31 -> 0 | AF32: ='Lpg (2)'!B36*2000/85 -> 0 | AG32: ='Lpg (2)'!C36*1000/85 -> 0 | AH32: ='Lpg (2)'!D36*1000/85 -> 0 | AI32: =SUM(AF32*2000)+(AG32*1000)+(AH32*1000) -> 0 | AJ32: =SUM(AI31-AI32) -> 0
A33: =Gen!A38 -> 44255 | B33: ='Summery Report'!E32 -> 0 | C33: =Gen!B38 -> 0 | D33: ='Summery Report'!E32 -> 0 | E33: =SUM(E32) -> 1.3262195 | F33: =SUM(J33*E33)/D33 -> #DIV/0! | G33: =SUM(L33*E33)/D33 -> #DIV/0! | H33: =Gen!C38 -> 41025.6 | I33: =Gen!E38 -> 0 | J33: =Gen!T38 -> 0 | K33: =Gen!AK38 -> 0 | L33: =SUM(J33:K33) -> 0 | M33: ='Water-Meter'!K73 -> 0 | N33: ='Water-Meter'!E33 -> 0 | Q33: =SUM(P33-P32) -> 0 | R33: =SUM(Q33*O33) -> 0 | U33: =T33-T32 -> 0 | V33: =SUM(U33*S33) -> 0 | Y33: =X33-X32 -> 0 | Z33: =SUM(Y33*W33) -> 0 | AA33: =SUM(Z33*X35) -> 0 | AC33: =SUM(AB33-AB32) -> 0 | AE33: =AD33-AD32 -> 0 | AF33: ='Lpg (2)'!B37*2000/85 -> 0 | AG33: ='Lpg (2)'!C37*1000/85 -> 0 | AH33: ='Lpg (2)'!D37*1000/85 -> 0 | AI33: =SUM(AF33*2000)+(AG33*1000)+(AH33*1000) -> 0 | AJ33: =SUM(AI32-AI33) -> 0
A34: =Gen!A39 -> 0 | B34: ='Summery Report'!E33 -> 0 | C34: =Gen!B39 -> 0 | D34: ='Summery Report'!E33 -> 0 | E34: =SUM(E33) -> 1.3262195 | F34: =SUM(J34*E34)/D34 -> #DIV/0! | G34: =SUM(L34*E34)/D34 -> #DIV/0! | H34: =Gen!C39 -> 41025.6 | I34: =Gen!E39 -> 0 | J34: =Gen!T39 -> 0 | K34: =Gen!AK39 -> 0 | L34: =SUM(J34:K34) -> 0 | M34: ='Water-Meter'!K74 -> 0 | N34: ='Water-Meter'!E34 -> 0 | Q34: =SUM(P34-P33) -> 0 | R34: =SUM(Q34*O34) -> 0 | U34: =T34-T33 -> 0 | V34: =SUM(U34*S34) -> 0 | Y34: =X34-X33 -> 0 | Z34: =SUM(Y34*W34) -> 0 | AA34: =SUM(Z34*X36) -> 0 | AC34: =SUM(AB34-AB33) -> 0 | AE34: =AD34-AD33 -> 0 | AF34: ='Lpg (2)'!B38*2000/85 -> 0 | AG34: ='Lpg (2)'!C38*1000/85 -> 0 | AH34: ='Lpg (2)'!D38*1000/85 -> 0 | AI34: =SUM(AF34*2000)+(AG34*1000)+(AH34*1000) -> 0 | AJ34: =SUM(AI33-AI34) -> 0
A35: =Gen!A40 -> 0 | B35: ='Summery Report'!E34 -> 0 | C35: =Gen!B40 -> 0 | D35: ='Summery Report'!E34 -> 0 | E35: =SUM(E34) -> 1.3262195 | F35: =SUM(J35*E35)/D35 -> #DIV/0! | G35: =SUM(L35*E35)/D35 -> #DIV/0! | H35: =Gen!C40 -> 41025.6 | I35: =Gen!E40 -> 0 | J35: =Gen!T40 -> 0 | K35: =Gen!AK40 -> 0 | L35: =SUM(J35:K35) -> 0 | M35: ='Water-Meter'!K75 -> 0 | N35: ='Water-Meter'!E35 -> 0 | Q35: =SUM(P35-P34) -> 0 | R35: =SUM(Q35*O35) -> 0 | U35: =T35-T34 -> 0 | V35: =SUM(U35*S35) -> 0 | Y35: =X35-X34 -> 0 | Z35: =SUM(Y35*W35) -> 0 | AA35: =SUM(Z35*X37) -> 0 | AC35: =SUM(AB35-AB34) -> 0 | AE35: =AD35-AD34 -> 0 | AF35: ='Lpg (2)'!B39*2000/85 -> 0 | AG35: ='Lpg (2)'!C39*1000/85 -> 0 | AH35: ='Lpg (2)'!D39*1000/85 -> 0 | AI35: =SUM(AF35*2000)+(AG35*1000)+(AH35*1000) -> 0 | AJ35: =SUM(AI34-AI35) -> 0
A36: =Gen!A41 -> 0 | B36: ='Summery Report'!E35 -> 0 | C36: =Gen!B41 -> 0 | D36: ='Summery Report'!E35 -> 0 | E36: =SUM(E35) -> 1.3262195 | F36: =SUM(J36*E36)/D36 -> #DIV/0! | G36: =SUM(L36*E36)/D36 -> #DIV/0! | H36: =Gen!C41 -> 41025.6 | I36: =Gen!E41 -> 0 | J36: =Gen!T41 -> 0 | K36: =Gen!AK41 -> 0 | L36: =SUM(J36:K36) -> 0 | M36: ='Water-Meter'!K76 -> 0 | N36: ='Water-Meter'!E36 -> 0 | Q36: =SUM(P36-P35) -> 0 | R36: =SUM(Q36*O36) -> 0 | U36: =T36-T35 -> 0 | V36: =SUM(U36*S36) -> 0 | Y36: =X36-X35 -> 0 | Z36: =SUM(Y36*W36) -> 0 | AA36: =SUM(Z36*X38) -> 0 | AC36: =SUM(AB36-AB35) -> 0 | AE36: =AD36-AD35 -> 0 | AF36: ='Lpg (2)'!B40*2000/85 -> 0 | AG36: ='Lpg (2)'!C40*1000/85 -> 0 | AH36: ='Lpg (2)'!D40*1000/85 -> 0 | AI36: =SUM(AF36*1000)+(AG36*1000)+(AH36*2000) -> 0 | AJ36: =SUM(AI35-AI36) -> 0
A37: =Gen!A42 -> 0 | B37: 0 | J37: =SUM(J6:J36) -> 51618 | L37: =SUM(J37:K37) -> 51618 | M37: ='Water-Meter'!K77 -> 0 | N37: ='Water-Meter'!E37 -> 0 | Q37: =SUM(P37-P36) -> 0 | R37: =SUM(Q37*O37) -> 0 | U37: =T37-T36 -> 0 | V37: =SUM(U37*S37) -> 0 | Y37: =X37-X36 -> 0 | Z37: =SUM(Y37*W37) -> 0 | AA37: =SUM(Z37*X39) -> 0 | AC37: =SUM(AB37-AB36) -> 0 | AE37: =AD37-AD36 -> 0 | AF37: ='Lpg (2)'!B41*2000/85 -> 0 | AG37: ='Lpg (2)'!C41*1000/85 -> 0 | AH37: ='Lpg (2)'!D41*1000/85 -> 0 | AJ37: =SUM(AI36-AI37) -> 0

Sheet Kit report
B1: KITCHEN THREE PHASE KWH METER READING | H1: KITCHEN WATER METER READING | M1: AMANI Restaurant WATER METER READING | T1: LAUNDRY THREE PHASE KWH METER READING | Y1: LAUNDRY WATER METER READING
A2: Occ % | B2: DATE | C2: READING TIME | D2: METER READING OPEN | E2: METER READING ClOSE | F2: UNIT USED Kwh | H2: DATE | I2: READING TIME | J2: METER READING OPEN Cbm | K2: METER READING ClOSE Cbm | L2: UNIT USED Cbm | M2: DATE | N2: READING TIME | O2: METER READING OPEN Cbm | P2: METER READING ClOSE Cbm | Q2: UNIT USED Cbm | R2: Cost Per day Elct+Water $ | S2: % as per the total Lodge consumption | T2: DATE | U2: READING TIME | V2: METER READING OPEN (Kwh) | W2: METER READING ClOSE (Kwh) | X2: UNIT USED Kwh | Y2: DATE | Z2: READING TIME | AA2: METER READING OPEN Cbm | AB2: METER READING ClOSE Cbm | AC2: UNIT USED Cbm
A3: =Gen!A11 -> 44228 | B3: Close Last Month | E3: ='[3]Kit report'!$E$34 -> 9077.8 | F3: X120 | H3: Close Last Month | J3: ='Water-Meter'!G5 -> 0 | K3: ='Water-Meter'!G5 -> 0 | M3: Close Last Month | T3: Close Last Month | W3: ='[3]Kit report'!$W$34 -> 7987.2 | X3: =(W3-V3)*200 -> 1597440 | Y3: Close Last Month
A4: =Gen!B11 -> 0.091 | B4: =Gen!A11 -> 44228 | D4: =E3 -> 9077.8 | E4: 9079.9 | F4: =SUM(E4-D4)*120 -> 252 | H4: =B4 -> 44228 | J4: ='Water-Meter'!G6 -> 0 | K4: ='Water-Meter'!G6 -> 0 | L4: =SUM(K4-J4) -> 0 | M4: =H4 -> 44228 | P4: ='Water-Meter'!J6 -> 8243 | S4: =Gen!T11 -> 2906 | T4: =M4 -> 44228 | V4: =W3 -> 7987.2 | W4: 7988.8 | X4: =(W4-V4)*200 -> 320 | Y4: =T4 -> 44228 | AB4: ='Water-Meter'!P6 -> 20893 | AC4: =AA4-AB3 -> 0
A5: =Gen!B12 -> 0.065 | B5: =Gen!A12 -> 44229 | D5: =E4 -> 9079.9 | E5: 9081.8 | F5: =SUM(E5-D5)*120 -> 228 | H5: =B5 -> 44229 | J5: ='Water-Meter'!G7 -> 0 | K5: ='Water-Meter'!G7 -> 0 | L5: =SUM(K5-J5) -> 0 | M5: =H5 -> 44229 | P5: ='Water-Meter'!J7 -> 8245 | S5: =Gen!T12 -> 2849 | T5: =M5 -> 44229 | V5: =W4 -> 7988.8 | W5: 7990.6 | X5: =(W5-V5)*200 -> 360 | Y5: =T5 -> 44229 | AB5: ='Water-Meter'!P7 -> 20898 | AC5: =AA5-AB4 -> -20893
A6: =Gen!B13 -> 0.039 | B6: =Gen!A13 -> 44230 | D6: =E5 -> 9081.8 | E6: 9083.9 | F6: =SUM(E6-D6)*120 -> 252 | H6: =B6 -> 44230 | J6: ='Water-Meter'!G8 -> 0 | K6: ='Water-Meter'!G8 -> 0 | L6: =SUM(K6-J6) -> 0 | M6: =H6 -> 44230 | P6: ='Water-Meter'!J8 -> 8246 | S6: =Gen!T13 -> 2599 | T6: =M6 -> 44230 | V6: =W5 -> 7990.6 | W6: 7991.7 | X6: =(W6-V6)*200 -> 220 | Y6: =T6 -> 44230 | AB6: ='Water-Meter'!P8 -> 20901 | AC6: =AA6-AB5 -> -20898
A7: =Gen!B14 -> 0.039 | B7: =Gen!A14 -> 44231 | D7: =E6 -> 9083.9 | E7: 9085.8 | F7: =SUM(E7-D7)*120 -> 228 | H7: =B7 -> 44231 | J7: ='Water-Meter'!G9 -> 0 | K7: ='Water-Meter'!G9 -> 0 | L7: =SUM(K7-J7) -> 0 | M7: =H7 -> 44231 | P7: ='Water-Meter'!J9 -> 8248 | S7: =Gen!T14 -> 2681 | T7: =M7 -> 44231 | V7: =W6 -> 7991.7 | W7: 7993.1 | X7: =(W7-V7)*200 -> 280 | Y7: =T7 -> 44231 | AB7: ='Water-Meter'!P9 -> 20908 | AC7: =AA7-AB6 -> -20901
A8: =Gen!B15 -> 0.0519 | B8: =Gen!A15 -> 44232 | D8: =E7 -> 9085.8 | E8: 9088 | F8: =SUM(E8-D8)*120 -> 264 | H8: =B8 -> 44232 | J8: ='Water-Meter'!G10 -> 0 | K8: ='Water-Meter'!G10 -> 0 | L8: =SUM(K8-J8) -> 0 | M8: =H8 -> 44232 | P8: ='Water-Meter'!J10 -> 8249 | S8: =Gen!T15 -> 3008 | T8: =M8 -> 44232 | V8: =W7 -> 7993.1 | W8: 7994.8 | X8: =(W8-V8)*200 -> 340 | Y8: =T8 -> 44232 | AB8: ='Water-Meter'!P10 -> 20913 | AC8: =AA8-AB7 -> -20908
A9: =Gen!B16 -> 0.0779 | B9: =Gen!A16 -> 44233 | D9: =E8 -> 9088 | E9: 9089.7 | F9: =SUM(E9-D9)*120 -> 204 | H9: =B9 -> 44233 | J9: ='Water-Meter'!G11 -> 0 | K9: ='Water-Meter'!G11 -> 0 | L9: =SUM(K9-J9) -> 0 | M9: =H9 -> 44233 | P9: ='Water-Meter'!J11 -> 8251 | S9: =Gen!T16 -> 2354 | T9: =M9 -> 44233 | V9: =W8 -> 7994.8 | W9: 7995.6 | X9: =(W9-V9)*200 -> 160 | Y9: =T9 -> 44233 | AB9: ='Water-Meter'!P11 -> 20915 | AC9: =AA9-AB8 -> -20913
A10: =Gen!B17 -> 0.0779 | B10: =Gen!A17 -> 44234 | D10: =E9 -> 9089.7 | E10: 9091.7 | F10: =SUM(E10-D10)*120 -> 240 | H10: =B10 -> 44234 | J10: ='Water-Meter'!G12 -> 0 | K10: ='Water-Meter'!G12 -> 0 | L10: =SUM(K10-J10) -> 0 | M10: =H10 -> 44234 | P10: ='Water-Meter'!J12 -> 8254 | S10: =Gen!T17 -> 2780 | T10: =M10 -> 44234 | V10: =W9 -> 7995.6 | W10: 7997.7 | X10: =(W10-V10)*200 -> 420 | Y10: =T10 -> 44234 | AB10: ='Water-Meter'!P12 -> 20918 | AC10: =AA10-AB9 -> -20915
A11: =Gen!B18 -> 0.0519 | B11: =Gen!A18 -> 44235 | D11: =E10 -> 9091.7 | E11: 9093.5 | F11: =SUM(E11-D11)*120 -> 216 | H11: =B11 -> 44235 | J11: ='Water-Meter'!G13 -> 0 | K11: ='Water-Meter'!G13 -> 0 | L11: =SUM(K11-J11) -> 0 | M11: =H11 -> 44235 | P11: ='Water-Meter'!J13 -> 8257 | S11: =Gen!T18 -> 2545 | T11: =M11 -> 44235 | V11: =W10 -> 7997.7 | W11: 7999.3 | X11: =(W11-V11)*200 -> 320 | Y11: =T11 -> 44235 | AB11: ='Water-Meter'!P13 -> 20924 | AC11: =AA11-AB10 -> -20918
A12: =Gen!B19 -> 0.1039 | B12: =Gen!A19 -> 44236 | D12: =E11 -> 9093.5 | E12: 9095.3 | F12: =SUM(E12-D12)*120 -> 216 | H12: =B12 -> 44236 | J12: ='Water-Meter'!G14 -> 0 | K12: ='Water-Meter'!G14 -> 0 | L12: =SUM(K12-J12) -> 0 | M12: =H12 -> 44236 | P12: ='Water-Meter'!J14 -> 8259 | S12: =Gen!T19 -> 2653 | T12: =M12 -> 44236 | V12: =W11 -> 7999.3 | W12: 8000.7 | X12: =(W12-V12)*200 -> 280 | Y12: =T12 -> 44236 | AB12: ='Water-Meter'!P14 -> 20927 | AC12: =AA12-AB11 -> -20924
A13: =Gen!B20 -> 0.1039 | B13: =Gen!A20 -> 44237 | D13: =E12 -> 9095.3 | E13: 9097.1 | F13: =SUM(E13-D13)*120 -> 216 | H13: =B13 -> 44237 | J13: ='Water-Meter'!G15 -> 0 | K13: ='Water-Meter'!G15 -> 0 | L13: =SUM(K13-J13) -> 0 | M13: =H13 -> 44237 | P13: ='Water-Meter'!J15 -> 8260 | S13: =Gen!T20 -> 2493 | T13: =M13 -> 44237 | V13: =W12 -> 8000.7 | W13: 8001.8 | X13: =(W13-V13)*200 -> 220 | Y13: =T13 -> 44237 | AB13: ='Water-Meter'!P15 -> 20931 | AC13: =AA13-AB12 -> -20927
A14: =Gen!B21 -> 0.1169 | B14: =Gen!A21 -> 44238 | D14: =E13 -> 9097.1 | E14: 9099.1 | F14: =SUM(E14-D14)*120 -> 240 | H14: =B14 -> 44238 | J14: ='Water-Meter'!G16 -> 0 | K14: ='Water-Meter'!G16 -> 0 | L14: =SUM(K14-J14) -> 0 | M14: =H14 -> 44238 | P14: ='Water-Meter'!J16 -> 8261 | S14: =Gen!T21 -> 2528 | T14: =M14 -> 44238 | V14: =W13 -> 8001.8 | W14: 8003.1 | X14: =(W14-V14)*200 -> 260 | Y14: =T14 -> 44238 | AB14: ='Water-Meter'!P16 -> 20935 | AC14: 20490
A15: =Gen!B22 -> 0.2338 | B15: =Gen!A22 -> 44239 | D15: =E14 -> 9099.1 | E15: 9101.3 | F15: =SUM(E15-D15)*120 -> 264 | H15: =B15 -> 44239 | J15: ='Water-Meter'!G17 -> 0 | K15: ='Water-Meter'!G17 -> 0 | L15: =SUM(K15-J15) -> 0 | M15: =H15 -> 44239 | P15: ='Water-Meter'!J17 -> 8263 | S15: =Gen!T22 -> 2703 | T15: =M15 -> 44239 | V15: =W14 -> 8003.1 | W15: 8004.4 | X15: =(W15-V15)*200 -> 260 | Y15: =T15 -> 44239 | AB15: ='Water-Meter'!P17 -> 20938 | AC15: =AA15-AB14 -> -20935
A16: =Gen!B23 -> 0.2208 | B16: =Gen!A23 -> 44240 | D16: =E15 -> 9101.3 | E16: 9103.4 | F16: =SUM(E16-D16)*120 -> 252 | H16: =B16 -> 44240 | J16: ='Water-Meter'!G18 -> 0 | K16: ='Water-Meter'!G18 -> 0 | L16: =SUM(K16-J16) -> 0 | M16: =H16 -> 44240 | P16: ='Water-Meter'!J18 -> 8264 | S16: =Gen!T23 -> 2690 | T16: =M16 -> 44240 | V16: =W15 -> 8004.4 | W16: 8005.3 | X16: =(W16-V16)*200 -> 180 | Y16: =T16 -> 44240 | AB16: ='Water-Meter'!P18 -> 20940 | AC16: =AA16-AB15 -> -20938
A17: =Gen!B24 -> 0.1948 | B17: =Gen!A24 -> 44241 | D17: =E16 -> 9103.4 | E17: 9105.8 | F17: =SUM(E17-D17)*120 -> 288 | H17: =B17 -> 44241 | J17: ='Water-Meter'!G19 -> 0 | K17: ='Water-Meter'!G19 -> 0 | L17: =SUM(K17-J17) -> 0 | M17: =H17 -> 44241 | P17: ='Water-Meter'!J19 -> 8265 | S17: =Gen!T24 -> 2859 | T17: =M17 -> 44241 | V17: =W16 -> 8005.3 | W17: 8007.1 | X17: =(W17-V17)*200 -> 360 | Y17: =T17 -> 44241 | AB17: ='Water-Meter'!P19 -> 20942 | AC17: =AA17-AB16 -> -20940
A18: =Gen!B25 -> 0.1299 | B18: =Gen!A25 -> 44242 | D18: =E17 -> 9105.8 | E18: 9108.1 | F18: =SUM(E18-D18)*120 -> 276 | H18: =B18 -> 44242 | J18: ='Water-Meter'!G20 -> 0 | K18: ='Water-Meter'!G20 -> 0 | L18: =SUM(K18-J18) -> 0 | M18: =H18 -> 44242 | P18: ='Water-Meter'!J20 -> 8267 | S18: =Gen!T25 -> 2860 | T18: =M18 -> 44242 | V18: =W17 -> 8007.1 | W18: 8008.7 | X18: =(W18-V18)*200 -> 320 | Y18: =T18 -> 44242 | AB18: ='Water-Meter'!P20 -> 20952 | AC18: =AA18-AB17 -> -20942
A19: =Gen!B26 -> 0.0909 | B19: =Gen!A26 -> 44243 | D19: =E18 -> 9108.1 | E19: 9110.2 | F19: =SUM(E19-D19)*120 -> 252 | H19: =B19 -> 44243 | J19: ='Water-Meter'!G21 -> 0 | K19: ='Water-Meter'!G21 -> 0 | L19: =SUM(K19-J19) -> 0 | M19: =H19 -> 44243 | P19: ='Water-Meter'!J21 -> 8268 | S19: =Gen!T26 -> 2636 | T19: =M19 -> 44243 | V19: =W18 -> 8008.7 | W19: 8010.5 | X19: =(W19-V19)*200 -> 360 | Y19: =T19 -> 44243 | AB19: ='Water-Meter'!P21 -> 20955 | AC19: =AA19-AB18 -> -20952
A20: =Gen!B27 -> 0.1169 | B20: =Gen!A27 -> 44244 | D20: =E19 -> 9110.2 | E20: 9112.6 | F20: =SUM(E20-D20)*120 -> 288 | H20: =B20 -> 44244 | J20: ='Water-Meter'!G22 -> 0 | K20: ='Water-Meter'!G22 -> 0 | L20: =SUM(K20-J20) -> 0 | M20: =H20 -> 44244 | P20: ='Water-Meter'!J22 -> 8270 | S20: =Gen!T27 -> 2643 | T20: =M20 -> 44244 | V20: =W19 -> 8010.5 | W20: 8011.4 | X20: =(W20-V20)*200 -> 180 | Y20: =T20 -> 44244 | AB20: ='Water-Meter'!P22 -> 20958 | AC20: =AA20-AB19 -> -20955
A21: =Gen!B28 -> 0.1169 | B21: =Gen!A28 -> 44245 | D21: =E20 -> 9112.6 | E21: 9114.9 | F21: =SUM(E21-D21)*120 -> 276 | H21: =B21 -> 44245 | J21: ='Water-Meter'!G23 -> 0 | K21: ='Water-Meter'!G23 -> 0 | L21: =SUM(K21-J21) -> 0 | M21: =H21 -> 44245 | P21: ='Water-Meter'!J23 -> 8271 | S21: =Gen!T28 -> 2839 | T21: =M21 -> 44245 | V21: =W20 -> 8011.4 | W21: 8013.2 | X21: =(W21-V21)*200 -> 360 | Y21: =T21 -> 44245 | AB21: ='Water-Meter'!P23 -> 20964 | AC21: =AA21-AB20 -> -20958
A22: =Gen!B29 -> 0.1558 | B22: =Gen!A29 -> 44246 | D22: =E21 -> 9114.9 | E22: 9117.4 | F22: =SUM(E22-D22)*120 -> 300 | H22: =B22 -> 44246 | J22: ='Water-Meter'!G24 -> 0 | K22: ='Water-Meter'!G24 -> 0 | L22: =SUM(K22-J22) -> 0 | M22: =H22 -> 44246 | P22: ='Water-Meter'!J24 -> 8273 | S22: =Gen!T29 -> 2992 | T22: =M22 -> 44246 | V22: =W21 -> 8013.2 | W22: 8015.2 | X22: =(W22-V22)*200 -> 400 | Y22: =T22 -> 44246 | AB22: ='Water-Meter'!P24 -> 20968 | AC22: =AA22-AB21 -> -20964
A23: =Gen!B30 -> 0.1429 | B23: =Gen!A30 -> 44247 | D23: =E22 -> 9117.4 | F23: =SUM(E23-D23)*120 -> -1094088 | H23: =B23 -> 44247 | J23: ='Water-Meter'!G25 -> 0 | K23: ='Water-Meter'!G26 -> 0 | L23: =SUM(K23-J23) -> 0 | M23: =H23 -> 44247 | P23: ='Water-Meter'!J25 -> 0 | S23: =Gen!T30 -> 0 | T23: =M23 -> 44247 | V23: =W22 -> 8015.2 | X23: =(W23-V23)*200 -> -1603040 | Y23: =T23 -> 44247 | AB23: ='Water-Meter'!P25 -> 0 | AC23: =AA23-AB22 -> -20968
A24: =Gen!B31 -> 0 | B24: =Gen!A31 -> 44248 | D24: =SUM(E23) -> 0 | F24: =SUM(E24-D24)*120 -> 0 | H24: =B24 -> 44248 | J24: ='Water-Meter'!G26 -> 0 | K24: ='Water-Meter'!G27 -> 0 | L24: =SUM(K24-J24) -> 0 | M24: =H24 -> 44248 | P24: ='Water-Meter'!J26 -> 0 | S24: =Gen!T31 -> 0 | T24: 5835.7 | V24: =W23 -> 0 | X24: =(W24-V24)*200 -> 0 | Y24: =T24 -> 5835.7 | AB24: ='Water-Meter'!P26 -> 0 | AC24: =AA24-AB23 -> 0
A25: =Gen!B32 -> 0 | B25: =Gen!A32 -> 44249 | D25: =SUM(E24) -> 0 | F25: =SUM(E25-D25)*120 -> 0 | H25: =B25 -> 44249 | J25: ='Water-Meter'!G27 -> 0 | K25: ='Water-Meter'!G28 -> 0 | L25: =SUM(K25-J25) -> 0 | M25: =H25 -> 44249 | P25: ='Water-Meter'!J27 -> 0 | S25: =Gen!T32 -> 0 | T25: =M25 -> 44249 | V25: =W24 -> 0 | X25: =(W25-V25)*200 -> 0 | Y25: =T25 -> 44249 | AB25: ='Water-Meter'!P27 -> 0 | AC25: =AA25-AB24 -> 0
A26: =Gen!B33 -> 0 | B26: =Gen!A33 -> 44250 | D26: =SUM(E25) -> 0 | F26: =SUM(E26-D26)*120 -> 0 | H26: =B26 -> 44250 | J26: ='Water-Meter'!G28 -> 0 | K26: ='Water-Meter'!G29 -> 0 | L26: =SUM(K26-J26) -> 0 | M26: =H26 -> 44250 | P26: ='Water-Meter'!J28 -> 0 | S26: =Gen!T33 -> 0 | T26: =M26 -> 44250 | V26: =W25 -> 0 | X26: =(W26-V26)*200 -> 0 | Y26: =T26 -> 44250 | AB26: ='Water-Meter'!P28 -> 0 | AC26: =AA26-AB25 -> 0
A27: =Gen!B34 -> 0 | B27: =Gen!A34 -> 44251 | D27: =SUM(E26) -> 0 | F27: =SUM(E27-D27)*120 -> 0 | H27: =B27 -> 44251 | J27: ='Water-Meter'!G29 -> 0 | K27: ='Water-Meter'!G30 -> 0 | L27: =SUM(K27-J27) -> 0 | M27: =H27 -> 44251 | P27: ='Water-Meter'!J29 -> 0 | S27: =Gen!T34 -> 0 | T27: =M27 -> 44251 | V27: =W26 -> 0 | X27: =(W27-V27)*200 -> 0 | Y27: =T27 -> 44251 | AB27: ='Water-Meter'!P29 -> 0 | AC27: =AA27-AB26 -> 0
A28: =Gen!B35 -> 0 | B28: =Gen!A35 -> 44252 | D28: =SUM(E27) -> 0 | F28: =SUM(E28-D28)*120 -> 0 | H28: =B28 -> 44252 | J28: ='Water-Meter'!G30 -> 0 | K28: ='Water-Meter'!G31 -> 0 | L28: =SUM(K28-J28) -> 0 | M28: =H28 -> 44252 | P28: ='Water-Meter'!J30 -> 0 | S28: =Gen!T35 -> 0 | T28: =M28 -> 44252 | V28: =W27 -> 0 | X28: =(W28-V28)*200 -> 0 | Y28: =T28 -> 44252 | AB28: ='Water-Meter'!P30 -> 0 | AC28: =AA28-AB27 -> 0
A29: =Gen!B36 -> 0 | B29: =Gen!A36 -> 44253 | D29: =SUM(E28) -> 0 | F29: =SUM(E29-D29)*120 -> 0 | H29: =B29 -> 44253 | J29: ='Water-Meter'!G31 -> 0 | K29: ='Water-Meter'!G32 -> 0 | L29: =SUM(K29-J29) -> 0 | M29: =H29 -> 44253 | P29: ='Water-Meter'!J31 -> 0 | S29: =Gen!T36 -> 0 | T29: =M29 -> 44253 | V29: =W28 -> 0 | X29: =(W29-V29)*200 -> 0 | Y29: =T29 -> 44253 | AB29: ='Water-Meter'!P31 -> 0 | AC29: =AA29-AB28 -> 0
A30: =Gen!B37 -> 0 | B30: =Gen!A37 -> 44254 | D30: =SUM(E29) -> 0 | F30: =SUM(E30-D30)*120 -> 0 | H30: =B30 -> 44254 | J30: ='Water-Meter'!G32 -> 0 | K30: ='Water-Meter'!G33 -> 0 | L30: =SUM(K30-J30) -> 0 | M30: =H30 -> 44254 | P30: ='Water-Meter'!J32 -> 0 | S30: =Gen!T37 -> 0 | T30: =M30 -> 44254 | V30: =W29 -> 0 | X30: =(W30-V30)*200 -> 0 | Y30: =T30 -> 44254 | AB30: ='Water-Meter'!P32 -> 0 | AC30: =AA30-AB29 -> 0
A31: =Gen!B38 -> 0 | B31: =Gen!A38 -> 44255 | D31: =SUM(E30) -> 0 | F31: =SUM(E31-D31)*120 -> 0 | H31: =B31 -> 44255 | J31: ='Water-Meter'!G33 -> 0 | K31: ='Water-Meter'!G34 -> 0 | L31: =SUM(K31-J31) -> 0 | M31: =H31 -> 44255 | P31: ='Water-Meter'!J33 -> 0 | S31: =Gen!T38 -> 0 | T31: =M31 -> 44255 | V31: =W30 -> 0 | X31: =(W31-V31)*200 -> 0 | Y31: =T31 -> 44255 | AB31: ='Water-Meter'!P33 -> 0 | AC31: =AA31-AB30 -> 0
A32: =Gen!B39 -> 0 | B32: =Gen!A39 -> 0 | D32: =SUM(E31) -> 0 | F32: =SUM(E32-D32)*120 -> 0 | H32: =B32 -> 0 | J32: ='Water-Meter'!G34 -> 0 | K32: ='Water-Meter'!G34 -> 0 | L32: =SUM(K32-J32) -> 0 | M32: =H32 -> 0 | P32: ='Water-Meter'!J34 -> 0 | S32: =Gen!T39 -> 0 | T32: =M32 -> 0 | V32: =W31 -> 0 | X32: =(W32-V32)*200 -> 0 | Y32: =T32 -> 0 | AB32: ='Water-Meter'!P34 -> 0 | AC32: =AA32-AB31 -> 0
A33: =Gen!B40 -> 0 | B33: =Gen!A40 -> 0 | D33: =SUM(E32) -> 0 | F33: =SUM(E33-D33)*120 -> 0 | H33: =B33 -> 0 | J33: ='Water-Meter'!G35 -> 0 | K33: ='Water-Meter'!G35 -> 0 | L33: =SUM(K33-J33) -> 0 | M33: =H33 -> 0 | P33: ='Water-Meter'!J35 -> 0 | S33: =Gen!T40 -> 0 | T33: =M33 -> 0 | V33: =W32 -> 0 | X33: =(W33-V33)*200 -> 0 | Y33: =T33 -> 0 | AB33: ='Water-Meter'!P35 -> 0 | AC33: =AA33-AB32 -> 0
A34: =Gen!B41 -> 0 | B34: =Gen!A41 -> 0 | D34: =SUM(E33) -> 0 | F34: =SUM(E34-D34)*120 -> 0 | H34: =B34 -> 0 | J34: ='Water-Meter'!G36 -> 0 | K34: ='Water-Meter'!G36 -> 0 | L34: =SUM(K34-J34) -> 0 | M34: =H34 -> 0 | P34: ='Water-Meter'!J36 -> 0 | S34: =Gen!T41 -> 0 | T34: =M34 -> 0 | V34: =SUM(W33) -> 0 | X34: =(W34-V34)*200 -> 0 | Y34: =T34 -> 0 | AB34: ='Water-Meter'!P36 -> 0 | AC34: =AA34-AB33 -> 0
A35: =[1]Gen!B42 -> #REF! | B35: =[1]Gen!A42 -> #REF! | D35: =SUM(E34) -> 0 | F35: =SUM(F4:F6) -> 732 | H35: =B35 -> #REF! | J35: =SUM(K34) -> 0 | K35: ='Water-Meter'!G37 -> 0 | L35: =SUM(L5:L34) -> 0 | M35: =H35 -> #REF! | P35: ='Water-Meter'!J37 -> 0 | S35: =Gen!T42 -> 0 | T35: =M35 -> #REF! | V35: =SUM(W34) -> 0 | X35: =(W35-V35)*200 -> 0 | Y35: =T35 -> #REF! | AB35: ='Water-Meter'!P37 -> 0 | AC35: =AA35-AB34 -> 0
X36: =SUM(X4:X6) -> 900

Sheet Summery Report
A1: =A5 -> 44228
A4: Date | B4: Gen Set Hours Working | C4: Occ% | D4: Total OCC Room | E4: Guest Room Occ | F4: Total Kwh Generated | G4: Diesel consumed by Gen (Ltrs) | H4: Diesel consumed by Vehicle (Ltrs) | I4: Total diesel consumed (Ltrs) | J4: Balance stock of Diesel (Ltrs) | K4: Water consumed | L4: Gas consumed (KG)
A5: =Gen!A11 -> 44228 | B5: ='Daily report Gen'!Z6 -> 157480 | C5: =Gen!B11 -> 0.091 | D5: =E5 -> 10.39 | E5: 10.39 | F5: =Gen!U11 -> 0.41609085 | G5: =Gen!T9 -> 0 | H5: =Gen!AK11 -> 0 | I5: =SUM(G5:H5) -> 0 | J5: =Gen!C11 -> 35132.06 | K5: ='Water-Meter'!E6 -> 58 | L5: ='Lpg (2)'!G10 -> 74734.36 | M5: =SUM(#REF!-#REF!) -> #REF!
A6: =Gen!A12 -> 44229 | B6: ='Daily report Gen'!Z7 -> 24 | C6: =Gen!B12 -> 0.065 | D6: =E6 -> 5.19 | E6: 5.19 | F6: =Gen!U12 -> 0.41187785 | G6: =Gen!T10 -> 0 | H6: =Gen!AK12 -> 0 | I6: =SUM(G6:H6) -> 0 | J6: =Gen!C12 -> 48625.25 | K6: ='Water-Meter'!E7 -> 56 | L6: ='Lpg (2)'!G11 -> 74755.84 | M6: =SUM(#REF!-#REF!) -> #REF!
A7: =Gen!A13 -> 44230 | B7: ='Daily report Gen'!Z8 -> 25 | C7: =Gen!B13 -> 0.039 | D7: =E7 -> 3.9 | E7: 3.9 | F7: =Gen!U13 -> 0.42344748 | G7: =Gen!T11 -> 2906 | H7: =Gen!AK13 -> 0 | I7: =SUM(G7:H7) -> 2906 | J7: =Gen!C13 -> 47451.81 | K7: ='Water-Meter'!E8 -> 46 | L7: ='Lpg (2)'!G12 -> 74775.21 | M7: =SUM(#REF!-#REF!) -> #REF!
A8: =Gen!A14 -> 44231 | B8: ='Daily report Gen'!Z9 -> 23 | C8: =Gen!B14 -> 0.039 | D8: =E8 -> 3.9 | E8: 3.9 | F8: =Gen!U14 -> 0.40830287 | G8: =Gen!T12 -> 2849 | H8: =Gen!AK14 -> 0 | I8: =SUM(G8:H8) -> 2849 | J8: =Gen!C14 -> 46273.7 | K8: ='Water-Meter'!E9 -> 52 | L8: ='Lpg (2)'!G13 -> 74796.53 | M8: =SUM(#REF!-#REF!) -> #REF!
A9: =Gen!A15 -> 44232 | B9: ='Daily report Gen'!Z10 -> 52 | C9: =Gen!B15 -> 0.0519 | D9: =E9 -> 5.19 | E9: 5.19 | F9: =Gen!U15 -> 0.4168883 | G9: =Gen!T13 -> 2599 | H9: =Gen!AK15 -> 0 | I9: =SUM(G9:H9) -> 2599 | J9: =Gen!C15 -> 45058.75 | K9: ='Water-Meter'!E10 -> 45 | L9: ='Lpg (2)'!G14 -> 74818 | M9: =SUM(#REF!-#REF!) -> #REF!
A10: =Gen!A16 -> 44233 | B10: ='Daily report Gen'!Z11 -> 22 | C10: =Gen!B16 -> 0.0779 | D10: =E10 -> 7.79 | E10: 7.79 | F10: =Gen!U16 -> 0.40222175 | G10: =Gen!T14 -> 2681 | H10: =Gen!AK16 -> 0 | I10: =SUM(G10:H10) -> 2681 | J10: =Gen!C16 -> 43708.11 | K10: ='Water-Meter'!E11 -> 45 | L10: ='Lpg (2)'!G15 -> 74828.57 | M10: =SUM(#REF!-#REF!) -> #REF!
A11: =Gen!A17 -> 44234 | B11: ='Daily report Gen'!Z12 -> 25 | C11: =Gen!B17 -> 0.0779 | D11: =E11 -> 7.79 | E11: 7.79 | F11: =Gen!U17 -> 0.4110036 | G11: =Gen!T15 -> 3008 | H11: =Gen!AK17 -> 0 | I11: =SUM(G11:H11) -> 3008 | J11: =Gen!C17 -> 42692.87 | K11: ='Water-Meter'!E12 -> 58 | L11: ='Lpg (2)'!G16 -> 74845.13 | M11: =SUM(#REF!-#REF!) -> #REF!
A12: =Gen!A18 -> 44235 | B12: ='Daily report Gen'!Z13 -> 25 | C12: =Gen!B18 -> 0.0519 | D12: =E12 -> 5.19 | E12: 5.19 | F12: =Gen!U18 -> 0.41171316 | G12: =Gen!T16 -> 2354 | H12: =Gen!AK18 -> 0 | I12: =SUM(G12:H12) -> 2354 | J12: =Gen!C18 -> 41550.28 | K12: ='Water-Meter'!E13 -> 45 | L12: ='Lpg (2)'!G17 -> 74862.53 | M12: =SUM(#REF!-#REF!) -> #REF!
A13: =Gen!A19 -> 44236 | B13: ='Daily report Gen'!Z14 -> #REF! | C13: =Gen!B19 -> 0.1039 | D13: =E13 -> 10 | E13: 10 | F13: =Gen!U19 -> 0.42860912 | G13: =Gen!T17 -> 2780 | H13: =Gen!AK19 -> 0 | I13: =SUM(G13:H13) -> 2780 | J13: =Gen!C19 -> 40432.1 | K13: ='Water-Meter'!E14 -> 60 | L13: ='Lpg (2)'!G18 -> 74882.6 | M13: =SUM(#REF!-#REF!) -> #REF!
A14: =Gen!A20 -> 44237 | B14: ='Daily report Gen'!Z15 -> #REF! | C14: =Gen!B20 -> 0.1039 | D14: =E14 -> 10.39 | E14: 10.39 | F14: =Gen!U20 -> 0.42092659 | G14: =Gen!T18 -> 2545 | H14: =Gen!AK20 -> 0 | I14: =SUM(G14:H14) -> 2545 | J14: =Gen!C20 -> 39164.81 | K14: ='Water-Meter'!E15 -> 57 | L14: ='Lpg (2)'!G19 -> 74901.7 | M14: =SUM(#REF!-#REF!) -> #REF!
A15: =Gen!A21 -> 44238 | B15: ='Daily report Gen'!Z16 -> 24 | C15: =Gen!B21 -> 0.1169 | D15: =E15 -> 11.69 | E15: 11.69 | F15: =Gen!U21 -> 0.41895174 | G15: =Gen!T19 -> 2653 | H15: =Gen!AK21 -> 0 | I15: =SUM(G15:H15) -> 2653 | J15: =Gen!C21 -> 38115.44 | K15: ='Water-Meter'!E16 -> 49 | L15: ='Lpg (2)'!G20 -> 74919.52 | M15: =SUM(#REF!-#REF!) -> #REF!
A16: =Gen!A22 -> 44239 | B16: ='Daily report Gen'!Z17 -> 24 | C16: =Gen!B22 -> 0.2338 | D16: =E16 -> 23.38 | E16: 23.38 | F16: =Gen!U22 -> 0.41330004 | G16: =Gen!T20 -> 2493 | H16: =Gen!AK22 -> 0 | I16: =SUM(G16:H16) -> 2493 | J16: =Gen!C22 -> 36989.9 | K16: ='Water-Meter'!E17 -> 52 | L16: ='Lpg (2)'!G21 -> 74960.75 | M16: =SUM(#REF!-#REF!) -> #REF!
... A24: =Gen!A30 -> 44247 | B24: ='Daily report Gen'!Z25 -> -157942 | C24: =Gen!B30 -> 0.1429 | D24: =E24 -> 14.29 | E24: 14.29 | F24: =Gen!U30 -> #DIV/0! | G24: =Gen!T28 -> 2839 | H24: =Gen!AK30 -> 0 | I24: =SUM(G24:H24) -> 2839 | J24: =Gen!C30 -> 41025.6 | K24: ='Water-Meter'!E25 -> 0 | L24: ='Lpg (2)'!G29 -> 75065.86 | M24: =SUM(#REF!-#REF!) -> #REF!
A25: =Gen!A31 -> 44248 | B25: ='Daily report Gen'!Z26 -> 0 | C25: =Gen!B31 -> 0 | D25: =E25 -> 0 | F25: =Gen!U31 -> #DIV/0! | G25: =Gen!T29 -> 2992 | H25: =Gen!AK31 -> 0 | I25: =SUM(G25:H25) -> 2992 | J25: =Gen!C31 -> 41025.6 | K25: ='Water-Meter'!E26 -> 0 | L25: ='Lpg (2)'!G30 -> 0 | M25: =SUM(#REF!-#REF!) -> #REF!
A26: =Gen!A32 -> 44249 | B26: ='Daily report Gen'!Z27 -> 0 | C26: =Gen!B32 -> 0 | D26: =E26 -> 0 | F26: =Gen!U32 -> #DIV/0! | G26: =Gen!T30 -> 0 | H26: =Gen!AK32 -> 0 | I26: =SUM(G26:H26) -> 0 | J26: =Gen!C32 -> 41025.6 | K26: ='Water-Meter'!E27 -> 0 | L26: ='Lpg (2)'!G31 -> 0 | M26: =SUM(#REF!-#REF!) -> #REF!
A27: =Gen!A33 -> 44250 | B27: ='Daily report Gen'!Z28 -> 0 | C27: =Gen!B33 -> 0 | D27: =E27 -> 0 | F27: =Gen!U33 -> #DIV/0! | G27: =Gen!T31 -> 0 | H27: =Gen!AK33 -> 0 | I27: =SUM(G27:H27) -> 0 | J27: =Gen!C33 -> 41025.6 | K27: ='Water-Meter'!E28 -> 0 | L27: ='Lpg (2)'!G32 -> 0 | M27: =SUM(#REF!-#REF!) -> #REF!
A28: =Gen!A34 -> 44251 | B28: ='Daily report Gen'!Z29 -> 0 | C28: =Gen!B34 -> 0 | D28: =E28 -> 0 | F28: =Gen!U34 -> #DIV/0! | G28: =Gen!T32 -> 0 | H28: =Gen!AK34 -> 0 | I28: =SUM(G28:H28) -> 0 | J28: =Gen!C34 -> 41025.6 | K28: ='Water-Meter'!E29 -> 0 | L28: ='Lpg (2)'!G33 -> 0 | M28: =SUM(#REF!-#REF!) -> #REF!
A29: =Gen!A35 -> 44252 | B29: ='Daily report Gen'!Z30 -> 0 | C29: =Gen!B35 -> 0 | D29: =E29 -> 0 | F29: =Gen!U35 -> #DIV/0! | G29: =Gen!T33 -> 0 | H29: =Gen!AK35 -> 0 | I29: =SUM(G29:H29) -> 0 | J29: =Gen!C35 -> 41025.6 | K29: ='Water-Meter'!E30 -> 0 | L29: ='Lpg (2)'!G34 -> 0 | M29: =SUM(#REF!-#REF!) -> #REF!
A30: =Gen!A36 -> 44253 | B30: ='Daily report Gen'!Z31 -> 0 | C30: =Gen!B36 -> 0 | D30: =E30 -> 0 | F30: =Gen!U36 -> #DIV/0! | G30: =Gen!T34 -> 0 | H30: =Gen!AK36 -> 0 | I30: =SUM(G30:H30) -> 0 | J30: =Gen!C36 -> 41025.6 | K30: ='Water-Meter'!E31 -> 0 | L30: ='Lpg (2)'!G35 -> 0 | M30: =SUM(#REF!-#REF!) -> #REF!
A31: =Gen!A37 -> 44254 | B31: ='Daily report Gen'!Z32 -> 0 | C31: =Gen!B37 -> 0 | D31: =E31 -> 0 | F31: =Gen!U37 -> #DIV/0! | G31: =Gen!T35 -> 0 | H31: =Gen!AK37 -> 0 | I31: =SUM(G31:H31) -> 0 | J31: =Gen!C37 -> 41025.6 | K31: ='Water-Meter'!E32 -> 0 | L31: ='Lpg (2)'!G36 -> 0 | M31: =SUM(#REF!-#REF!) -> #REF!
A32: =Gen!A38 -> 44255 | B32: ='Daily report Gen'!Z33 -> 0 | C32: =Gen!B38 -> 0 | D32: =E32 -> 0 | F32: =Gen!U38 -> #DIV/0! | G32: =Gen!T36 -> 0 | H32: =Gen!AK38 -> 0 | I32: =SUM(G32:H32) -> 0 | J32: =Gen!C38 -> 41025.6 | K32: ='Water-Meter'!E33 -> 0 | L32: ='Lpg (2)'!G37 -> 0 | M32: =SUM(#REF!-#REF!) -> #REF!
A33: =Gen!A39 -> 0 | B33: ='Daily report Gen'!Z34 -> 0 | C33: =Gen!B39 -> 0 | D33: =E33 -> 0 | F33: =Gen!U39 -> #DIV/0! | G33: =Gen!T37 -> 0 | H33: =Gen!AK39 -> 0 | I33: =SUM(G33:H33) -> 0 | J33: =Gen!C39 -> 41025.6 | K33: ='Water-Meter'!E34 -> 0 | L33: ='Lpg (2)'!G38 -> 0 | M33: =SUM(#REF!-#REF!) -> #REF!
A34: =Gen!A40 -> 0 | B34: ='Daily report Gen'!Z35 -> 0 | C34: =Gen!B40 -> 0 | D34: =E34 -> 0 | F34: =Gen!U40 -> #DIV/0! | G34: =Gen!T38 -> 0 | H34: =Gen!AK40 -> 0 | I34: =SUM(G34:H34) -> 0 | J34: =Gen!C40 -> 41025.6 | K34: ='Water-Meter'!E35 -> 0 | L34: ='Lpg (2)'!G39 -> 0 | M34: =SUM(#REF!-#REF!) -> #REF!
A35: =Gen!A41 -> 0 | B35: ='Daily report Gen'!Z36 -> 0 | C35: =Gen!B41 -> 0 | D35: =E35 -> 0 | F35: =Gen!U39 -> #DIV/0! | G35: =Gen!T39 -> 0 | H35: =Gen!AK41 -> 0 | I35: =SUM(G35:H35) -> 0 | J35: =Gen!C41 -> 41025.6 | K35: ='Water-Meter'!E36 -> 0 | L35: ='Lpg (2)'!G40 -> 0 | M35: =SUM(#REF!-#REF!) -> #REF!
A36: =Gen!A42 -> 0 | B36: ='Daily report Gen'!Z37 -> 0 | C36: =Gen!B42 -> 0 | D36: =E36 -> 0 | F36: =Gen!U40 -> #DIV/0! | G36: =Gen!T40 -> 0 | H36: =Gen!AK42 -> 0 | I36: =SUM(G36:H36) -> 0 | J36: =Gen!C42 -> 41025.6 | K36: ='Water-Meter'!E37 -> 0 | L36: ='Lpg (2)'!G41 -> 0

Sheet Daily report Gen
A1: =A6 -> 44228
K3: GENERATOR NO.1 | N3: GENERATOR NO.2 | Q3: GENERATOR NO.4 | T3: GENERATOR NO.5 | W3: GENERATOR NO.6
A4: DATE | B4: OCC% | C4: D-TANK A | D4: D-TANK B | E4: DELIVERY DATE | F4: DELIVERY | G4: ISSUED-VEHICLE | H4: OTHERS | I4: M-R LV PANEL 1. KW-HR | J4: M-R LV PANEL 2. KW-HR | K4: OPEN HRS READING | L4: CLOSE HRS READING | M4: RUNNING HRS | N4: OPEN HRS READING | O4: CLOSE HRS READING | P4: RUNNING HRS | Q4: OPEN HRS READING | R4: CLOSE HRS READING | S4: RUNNING HRS | T4: OPEN HRS READING | U4: CLOSE HRS READING | V4: RUNNING HRS | W4: OPEN HRS READING | X4: CLOSE HRS READING | Y4: RUNNING HRS | Z4: TOTAL RUNNING HRS | AA4: MAX KW | AB4: MIN-KW | AC4: TOTAL DIESEL CONS.
A6: =Gen!A11 -> 44228 | B6: =Gen!B11 -> 0.091 | C6: 21669.19 | D6: 17143.12 | I6: 31575.2 | J6: 21019.6 | K6: =L5 -> 0 | L6: 35778 | M6: =L6-K6 -> 35778 | N6: =O5 -> 0 | O6: 30687 | P6: =O6-N6 -> 30687 | Q6: =R5 -> 0 | R6: 35974 | S6: =R6-Q6 -> 35974 | T6: =U5 -> 0 | U6: 33197 | V6: =U6-T6 -> 33197 | W6: =X5 -> 0 | X6: 21844 | Y6: =X6-W6 -> 21844 | Z6: =Y6+V6+S6+P6+M6 -> 157480 | AA6: 225 | AB6: 215 | AC6: =Gen!AR11 -> 1306.81
A7: =Gen!A12 -> 44229 | B7: =Gen!B12 -> 0.065 | C7: 19310.84 | D7: 17143.12 | I7: 31579.7 | J7: 21023.4 | K7: =L6 -> 35778 | L7: 35802 | M7: =L7-K7 -> 24 | N7: =O6 -> 30687 | O7: 30687 | P7: =O7-N7 -> 0 | Q7: =R6 -> 35974 | R7: 35974 | S7: =R7-Q7 -> 0 | T7: =U6 -> 33197 | U7: 33197 | V7: =U7-T7 -> 0 | W7: =X6 -> 21844 | X7: 21844 | Y7: =X7-W7 -> 0 | Z7: =Y7+V7+S7+P7+M7 -> 24 | AA7: 220 | AB7: 210 | AC7: =Gen!AR12 -> 1173.44
A8: =Gen!A13 -> 44230 | B8: =Gen!B13 -> 0.039 | C8: 25000 | D8: 22273 | I8: 31588.7 | J8: 21030.1 | K8: =L7 -> 35802 | L8: 35802 | M8: =L8-K8 -> 0 | N8: =O7 -> 30687 | O8: 30687 | P8: =O8-N8 -> 0 | Q8: =R7 -> 35974 | R8: 35974 | S8: =R8-Q8 -> 0 | T8: =U7 -> 33197 | U8: 33222 | V8: =U8-T8 -> 25 | W8: =X7 -> 21844 | X8: 21844 | Y8: =X8-W8 -> 0 | Z8: =Y8+V8+S8+P8+M8 -> 25 | AA8: 200 | AB8: 150 | AC8: =Gen!AR13 -> 1178.11
A9: =Gen!A14 -> 44231 | B9: =Gen!B14 -> 0.039 | C9: 24000 | D9: 22273 | I9: 31593.2 | J9: 21033.4 | K9: =L8 -> 35802 | L9: 35802 | M9: =L9-K9 -> 0 | N9: =O8 -> 30687 | O9: 30710 | P9: =O9-N9 -> 23 | Q9: =R8 -> 35974 | R9: 35974 | S9: =R9-Q9 -> 0 | T9: =U8 -> 33222 | U9: 33222 | V9: =U9-T9 -> 0 | W9: =X8 -> 21844 | X9: 21844 | Y9: =X9-W9 -> 0 | Z9: =Y9+V9+S9+P9+M9 -> 23 | AA9: 210 | AB9: 115 | AC9: =Gen!AR14 -> 1214.95
A10: =Gen!A15 -> 44232 | B10: =Gen!B15 -> 0.0519 | C10: 22786 | D10: 22273 | G10: 0.97 | I10: 31598.4 | J10: 21037 | K10: =L9 -> 35802 | L10: 35802 | M10: =L10-K10 -> 0 | N10: =O9 -> 30710 | O10: 30710 | P10: =O10-N10 -> 0 | Q10: =R9 -> 35974 | R10: 36005 | S10: =R10-Q10 -> 31 | T10: =U9 -> 33222 | U10: 33222 | V10: =U10-T10 -> 0 | W10: =X9 -> 21844 | X10: 21865 | Y10: =X10-W10 -> 21 | Z10: =Y10+V10+S10+P10+M10 -> 52 | AA10: 220 | AB10: 116 | AC10: =Gen!AR15 -> 1350.64
A11: =Gen!A16 -> 44233 | B11: =Gen!B16 -> 0.0779 | C11: 21435.11 | D11: 22273 | G11: 68.41 | I11: 31602.2 | J11: 21039.9 | K11: =L10 -> 35802 | L11: 35802 | M11: =L11-K11 -> 0 | N11: =O10 -> 30710 | O11: 30710 | P11: =O11-N11 -> 0 | Q11: =R10 -> 36005 | R11: 36005 | S11: =R11-Q11 -> 0 | T11: =U10 -> 33222 | U11: 33222 | V11: =U11-T11 -> 0 | W11: =X10 -> 21865 | X11: 21887 | Y11: =X11-W11 -> 22 | Z11: =Y11+V11+S11+P11+M11 -> 22 | AA11: 210 | AB11: 130 | AC11: =Gen!AR16 -> 1015.24
A12: =Gen!A17 -> 44234 | B12: =Gen!B17 -> 0.0779 | C12: 20419.87 | D12: 22273 | I12: 31607.9 | J12: 21043.2 | K12: =L11 -> 35802 | L12: 35802 | M12: =L12-K12 -> 0 | N12: =O11 -> 30710 | O12: 30735 | P12: =O12-N12 -> 25 | Q12: =R11 -> 36005 | R12: 36005 | S12: =R12-Q12 -> 0 | T12: =U11 -> 33222 | U12: 33222 | V12: =U12-T12 -> 0 | W12: =X11 -> 21887 | X12: 21887 | Y12: =X12-W12 -> 0 | Z12: =Y12+V12+S12+P12+M12 -> 25 | AA12: 215 | AB12: 120 | AC12: =Gen!AR17 -> 1142.59
A13: =Gen!A18 -> 44235 | B13: =Gen!B18 -> 0.0519 | C13: 19277.28 | D13: 22273 | G13: 70.37 | I13: 31611.3 | J13: 21046.1 | K13: =L12 -> 35802 | L13: 35802 | M13: =L13-K13 -> 0 | N13: =O12 -> 30735 | O13: 30735 | P13: =O14-N13 -> 0 | Q13: =R12 -> 36005 | R13: 36005 | S13: =R13-Q13 -> 0 | T13: =U12 -> 33222 | U13: 33247 | V13: =U13-T13 -> 25 | W13: =X12 -> 21887 | X13: 21887 | Y13: =X13-W13 -> 0 | Z13: =Y13+V13+S13+P13+M13 -> 25 | AA13: 220 | AB13: 125 | AC13: =Gen!AR18 -> 1118.18
A14: =Gen!A19 -> 44236 | B14: =Gen!B19 -> 0.1039 | C14: 18159.1 | D14: 22273 | G14: 130.19 | I14: 31615.6 | J14: 21049.5 | K14: =L13 -> 35802 | L14: 35827 | M14: =L14-K14 -> 25 | N14: =O14 -> 30735 | O14: 30735 | P14: =#REF!-N14 -> #REF! | Q14: =R13 -> 36005 | R14: 36005 | S14: =R14-Q14 -> 0 | T14: =U13 -> 33247 | U14: 33247 | V14: =U14-T14 -> 0 | W14: =X13 -> 21887 | X14: 21887 | Y14: =X14-W14 -> 0 | Z14: =Y14+V14+S14+P14+M14 -> #REF! | AA14: 200 | AB14: 120 | AC14: =Gen!AR19 -> 1267.29
A15: =Gen!A20 -> 44237 | B15: =Gen!B20 -> 0.1039 | C15: 16891.81 | D15: 22273 | I15: 31619.8 | J15: 21052.6 | K15: =L14 -> 35827 | L15: 35827 | M15: =L15-K15 -> 0 | N15: =#REF! -> #REF! | O15: 30735 | P15: =O15-N15 -> #REF! | Q15: =R14 -> 36005 | R15: 36030 | S15: =R15-Q15 -> 25 | T15: =U14 -> 33247 | U15: 33247 | V15: =U15-T15 -> 0 | W15: =X14 -> 21887 | X15: 21887 | Y15: =X15-W15 -> 0 | Z15: =Y15+V15+S15+P15+M15 -> #REF! | AA15: 200 | AB15: 125 | AC15: =Gen!AR20 -> 1049.37
A16: =Gen!A21 -> 44238 | B16: =Gen!B21 -> 0.1169 | C16: 15842.44 | D16: 22273 | G16: 66.43 | I16: 31624 | J16: 21055.7 | K16: =L15 -> 35827 | L16: 35827 | M16: =L16-K16 -> 0 | N16: =O15 -> 30735 | O16: 30735 | P16: =O16-N16 -> 0 | Q16: =R15 -> 36030 | R16: 36030 | S16: =R16-Q16 -> 0 | T16: =U15 -> 33247 | U16: 33247 | V16: =U16-T16 -> 0 | W16: =X15 -> 21887 | X16: 21911 | Y16: =X16-W16 -> 24 | Z16: =Y16+V16+S16+P16+M16 -> 24 | AA16: 210 | AB16: 125 | AC16: =Gen!AR21 -> 1125.54
A17: =Gen!A22 -> 44239 | B17: =Gen!B22 -> 0.2338 | C17: 14716.9 | D17: 22273 | G17: 116 | I17: 31628.5 | J17: 21059.1 | K17: =L16 -> 35827 | L17: 35827 | M17: =L17-K17 -> 0 | N17: =O16 -> 30735 | O17: 30759 | P17: =O17-N17 -> 24 | Q17: =R16 -> 36030 | R17: 36030 | S17: =R17-Q17 -> 0 | T17: =U16 -> 33247 | U17: 33247 | V17: =U17-T17 -> 0 | W17: =X16 -> 21911 | X17: 21911 | Y17: =X17-W17 -> 0 | Z17: =Y17+V17+S17+P17+M17 -> 24 | AA17: 215 | AB17: 120 | AC17: =Gen!AR22 -> 1233.15
A18: =Gen!A23 -> 44240 | B18: =Gen!B23 -> 0.2208 | C18: 13483.75 | D18: 22273 | G18: 474.14 | I18: 31632.9 | J18: 21062.6 | K18: =L17 -> 35827 | L18: 35827 | M18: =L18-K18 -> 0 | N18: =O17 -> 30759 | O18: 30759 | P18: =O18-N18 -> 0 | Q18: =R17 -> 36030 | R18: 36030 | S18: =R18-Q18 -> 0 | T18: =U17 -> 33247 | U18: 33271 | V18: =U18-T18 -> 24 | W18: =X17 -> 21911 | X18: 21911 | Y18: =X18-W18 -> 0 | Z18: =Y18+V18+S18+P18+M18 -> 24 | AA18: 220 | AB18: 125 | AC18: =Gen!AR23 -> 1605.53
A19: =Gen!A24 -> 44241 | B19: =Gen!B24 -> 0.1948 | C19: 11878.22 | D19: 22273 | G19: 152 | I19: 31638 | J19: 21066.9 | K19: =L18 -> 35827 | L19: 35851 | M19: =L19-K19 -> 24 | N19: =O18 -> 30759 | O19: 30759 | P19: =O19-N19 -> 0 | Q19: =R18 -> 36030 | R19: 36030 | S19: =R19-Q19 -> 0 | T19: =U18 -> 33271 | U19: 33271 | V19: =U19-T19 -> 0 | W19: =X18 -> 21911 | X19: 21911 | Y19: =X19-W19 -> 0 | Z19: =Y19+V19+S19+P19+M19 -> 24 | AA19: 230 | AB19: 125 | AC19: =Gen!AR24 -> 1354.78
A20: =Gen!A25 -> 44242 | B20: =Gen!B25 -> 0.1299 | C20: 10523.44 | D20: 22273 | G20: 35.09 | I20: 31642.8 | J20: 21069.5 | K20: =L19 -> 35851 | L20: 35851 | M20: =L20-K20 -> 0 | N20: =O19 -> 30759 | O20: 30759 | P20: =O20-N20 -> 0 | Q20: =R19 -> 36030 | R20: 36054 | S20: =R20-Q20 -> 24 | T20: =U19 -> 33271 | U20: 33271 | V20: =U20-T20 -> 0 | W20: =X19 -> 21911 | X20: 21911 | Y20: =X20-W20 -> 0 | Z20: =Y20+V20+S20+P20+M20 -> 24 | AA20: 235 | AB20: 130 | AC20: =Gen!AR25 -> 1222.82
A21: =Gen!A26 -> 44243 | B21: =Gen!B26 -> 0.0909 | C21: 9300.62 | D21: 22273 | G21: 189.95 | I21: 31647.5 | J21: 21072.5 | K21: =L20 -> 35851 | L21: 35851 | M21: =L21-K21 -> 0 | N21: =O20 -> 30759 | O21: 30759 | P21: =O21-N21 -> 0 | Q21: =R20 -> 36054 | R21: 36054 | S21: =R21-Q21 -> 0 | T21: =U20 -> 33271 | U21: 33271 | V21: =U21-T21 -> 0 | W21: =X20 -> 21911 | X21: 21935 | Y21: =X21-W21 -> 24 | Z21: =Y21+V21+S21+P21+M21 -> 24 | AA21: 220 | AB21: 120 | AC21: =Gen!AR26 -> 1295.86
A22: =Gen!A27 -> 44244 | B22: =Gen!B27 -> 0.1169 | C22: 23004.76 | D22: 22273 | G22: 249.3 | I22: 31651.9 | J22: 21075.8 | K22: =L21 -> 35851 | L22: 35851 | M22: =L22-K22 -> 0 | N22: =O21 -> 30759 | O22: 30783 | P22: =O22-N22 -> 24 | Q22: =R21 -> 36054 | R22: 36054 | S22: =R22-Q22 -> 0 | T22: =U21 -> 33271 | U22: 33271 | V22: =U22-T22 -> 0 | W22: =X21 -> 21935 | X22: 21935 | Y22: =X22-W22 -> 0 | Z22: =Y22+V22+S22+P22+M22 -> 24 | AA22: 218 | AB22: 113 | AC22: =Gen!AR27 -> 1314.82
A23: =Gen!A28 -> 44245 | B23: =Gen!B28 -> 0.1169 | C23: 21689.94 | D23: 22273 | G23: 599.33 | I23: 31656.6 | J23: 21079.3 | K23: =L22 -> 35851 | L23: 35875 | M23: =L23-K23 -> 24 | N23: =O22 -> 30783 | O23: 30783 | P23: =O23-N23 -> 0 | Q23: =R22 -> 36054 | R23: 36054 | S23: =R23-Q23 -> 0 | T23: =U22 -> 33271 | U23: 33271 | V23: =U23-T23 -> 0 | W23: =X22 -> 21935 | X23: 21935 | Y23: =X23-W23 -> 0 | Z23: =Y23+V23+S23+P23+M23 -> 24 | AA23: 220 | AB23: 120 | AC23: =Gen!AR28 -> 1702.06
A24: =Gen!A29 -> 44246 | B24: =Gen!B29 -> 0.1558 | C24: 19987.88 | D24: 22273 | I24: 31661.5 | J24: 21083.1 | K24: =L23 -> 35875 | L24: 35875 | M24: =L24-K24 -> 0 | N24: =O23 -> 30783 | O24: 30783 | P24: =O24-N24 -> 0 | Q24: =R23 -> 36054 | R24: 36054 | S24: =R24-Q24 -> 0 | T24: =U23 -> 33271 | U24: 33295 | V24: =U24-T24 -> 24 | W24: =X23 -> 21935 | X24: 21935 | Y24: =X24-W24 -> 0 | Z24: =Y24+V24+S24+P24+M24 -> 24 | AA24: 225 | AB24: 130 | AC24: =Gen!AR29 -> 1235.28
A25: =Gen!A30 -> 44247 | B25: =Gen!B30 -> 0.1429 | C25: 18752.6 | D25: 22273 | K25: =L24 -> 35875 | M25: =L25-K25 -> -35875 | N25: =O24 -> 30783 | P25: =O25-N25 -> -30783 | Q25: =R24 -> 36054 | S25: =R25-Q25 -> -36054 | T25: =U24 -> 33295 | V25: =U25-T25 -> -33295 | W25: =X24 -> 21935 | Y25: =X25-W25 -> -21935 | Z25: =Y25+V25+S25+P25+M25 -> -157942 | AC25: =Gen!AR30 -> 0
A26: =Gen!A31 -> 44248 | B26: =Gen!B31 -> 0 | K26: =L25 -> 0 | M26: =L26-K26 -> 0 | N26: =O25 -> 0 | P26: =O26-N26 -> 0 | Q26: =R25 -> 0 | S26: =R26-Q26 -> 0 | T26: =U25 -> 0 | V26: =U26-T26 -> 0 | W26: =X25 -> 0 | Y26: =X26-W26 -> 0 | Z26: =Y26+V26+S26+P26+M26 -> 0 | AC26: =Gen!AR31 -> 0
A27: =Gen!A32 -> 44249 | B27: =Gen!B32 -> 0 | K27: =L26 -> 0 | M27: =L27-K27 -> 0 | N27: =O26 -> 0 | P27: =O27-N27 -> 0 | Q27: =R26 -> 0 | S27: =R27-Q27 -> 0 | T27: =U26 -> 0 | V27: =U27-T27 -> 0 | W27: =X26 -> 0 | Y27: =X27-W27 -> 0 | Z27: =Y27+V27+S27+P27+M27 -> 0 | AC27: =Gen!AR32 -> 0
A28: =Gen!A33 -> 44250 | B28: =Gen!B33 -> 0 | K28: =L27 -> 0 | M28: =L28-K28 -> 0 | N28: =O27 -> 0 | P28: =O28-N28 -> 0 | Q28: =R27 -> 0 | S28: =R28-Q28 -> 0 | T28: =U27 -> 0 | V28: =U28-T28 -> 0 | W28: =X27 -> 0 | Y28: =X28-W28 -> 0 | Z28: =Y28+V28+S28+P28+M28 -> 0 | AC28: =Gen!AR33 -> 0
A29: =Gen!A34 -> 44251 | B29: =Gen!B34 -> 0 | K29: =L28 -> 0 | M29: =L29-K29 -> 0 | N29: =O28 -> 0 | P29: =O29-N29 -> 0 | Q29: =R28 -> 0 | S29: =R29-Q29 -> 0 | T29: =U28 -> 0 | V29: =U29-T29 -> 0 | W29: =X28 -> 0 | Y29: =X29-W29 -> 0 | Z29: =Y29+V29+S29+P29+M29 -> 0 | AC29: =Gen!AR34 -> 0
A30: =Gen!A35 -> 44252 | B30: =Gen!B35 -> 0 | K30: =L29 -> 0 | M30: =L30-K30 -> 0 | N30: =O29 -> 0 | P30: =O30-N30 -> 0 | Q30: =R29 -> 0 | S30: =R30-Q30 -> 0 | T30: =U29 -> 0 | V30: =U30-T30 -> 0 | W30: =X29 -> 0 | Y30: =X30-W30 -> 0 | Z30: =Y30+V30+S30+P30+M30 -> 0 | AC30: =Gen!AR35 -> 0
A31: =Gen!A36 -> 44253 | B31: =Gen!B36 -> 0 | K31: =L30 -> 0 | M31: =L31-K31 -> 0 | N31: =O30 -> 0 | P31: =O31-N31 -> 0 | Q31: =R30 -> 0 | S31: =R31-Q31 -> 0 | T31: =U30 -> 0 | V31: =U31-T31 -> 0 | W31: =X30 -> 0 | Y31: =X31-W31 -> 0 | Z31: =Y31+V31+S31+P31+M31 -> 0 | AC31: =Gen!AR36 -> 0
A32: =Gen!A37 -> 44254 | B32: =Gen!B37 -> 0 | K32: =L31 -> 0 | M32: =L32-K32 -> 0 | N32: =O31 -> 0 | P32: =O32-N32 -> 0 | Q32: =R31 -> 0 | S32: =R32-Q32 -> 0 | T32: =U31 -> 0 | V32: =U32-T32 -> 0 | W32: =X31 -> 0 | Y32: =X32-W32 -> 0 | Z32: =Y32+V32+S32+P32+M32 -> 0 | AC32: =Gen!AR37 -> 0
A33: =Gen!A38 -> 44255 | B33: =Gen!B38 -> 0 | K33: =L32 -> 0 | M33: =L33-K33 -> 0 | N33: =O32 -> 0 | P33: =O33-N33 -> 0 | Q33: =R32 -> 0 | S33: =R33-Q33 -> 0 | T33: =U32 -> 0 | V33: =U33-T33 -> 0 | W33: =X32 -> 0 | Y33: =X33-W33 -> 0 | Z33: =Y33+V33+S33+P33+M33 -> 0 | AC33: =Gen!AR38 -> 0
A34: =Gen!A39 -> 0 | B34: =Gen!B39 -> 0 | K34: =L33 -> 0 | M34: =L34-K34 -> 0 | N34: =O33 -> 0 | P34: =O34-N34 -> 0 | Q34: =R33 -> 0 | S34: =R34-Q34 -> 0 | T34: =U33 -> 0 | V34: =U34-T34 -> 0 | W34: =X33 -> 0 | Y34: =X34-W34 -> 0 | Z34: =Y34+V34+S34+P34+M34 -> 0 | AC34: =Gen!AR39 -> 0
A35: =Gen!A40 -> 0 | B35: =Gen!B40 -> 0 | K35: =L34 -> 0 | M35: =L35-K35 -> 0 | N35: =O34 -> 0 | P35: =O35-N35 -> 0 | Q35: =R34 -> 0 | S35: =R35-Q35 -> 0 | T35: =U34 -> 0 | V35: =U35-T35 -> 0 | W35: =X34 -> 0 | Y35: =X35-W35 -> 0 | Z35: =Y35+V35+S35+P35+M35 -> 0 | AC35: =Gen!AR40 -> 0
A36: =Gen!A41 -> 0 | B36: =Gen!B41 -> 0 | K36: =L35 -> 0 | M36: =L36-K36 -> 0 | N36: =O35 -> 0 | P36: =O36-N36 -> 0 | Q36: =R35 -> 0 | S36: =R36-Q36 -> 0 | T36: =U35 -> 0 | V36: =U36-T36 -> 0 | W36: =X35 -> 0 | Y36: =X36-W36 -> 0 | Z36: =Y36+V36+S36+P36+M36 -> 0 | AC36: =Gen!AR41 -> 0
A37: =Gen!A42 -> 0 | B37: =Gen!B42 -> 0 | K37: =L36 -> 0 | M37: =L37-K37 -> 0 | N37: =O36 -> 0 | P37: =O37-N37 -> 0 | Q37: =R36 -> 0 | S37: =R37-Q37 -> 0 | T37: =U36 -> 0 | V37: =U37-T37 -> 0 | W37: =X36 -> 0 | Y37: =X37-W37 -> 0 | Z37: =Y37+V37+S37+P37+M37 -> 0 | AC37: =Gen!AR42 -> 0

Sheet Gen
D2: =A11 -> 44228
F6: BILILA LODGE INVESTMENT LIMITED | V6: 1 | W6: 2 | X6: 3 | Y6: 4 | Z6: 5 | AA6: 6 | AB6: 7 | AC6: 8 | AD6: 9 | AE6: 10 | AF6: 11
F7: Diesel Consumed by 500KVA Generator | M7: 500KVA Generator KWh | V7: Safari-STAFF | W7: Safari-STAFF | X7: Lc/swg/gust | Y7: Eng pikcup | Z7: VIP Safari Car | AA7: GX Guest | AB7: GX Guest | AC7: T/Hillux/pur | AD7: TATA | AE7: MAN | AF7: F/Truck | AG7: Incenerator | AH7: A&K | AI7: OTHER | AJ7: TOTAL CO
A8: Date | B8: Occupancy % | C8: OPENING | D8: Received | E8: Schedule delivery | F8: Company | G8: 1 | H8: 2 | I8: 3 | J8: 4 | K8: 5 | L8: 6 | M8: 1 | N8: 2 | O8: 3 | P8: 4 | Q8: 5 | R8: 6 | S8: Total Diseal Consumed | T8: Total Kwh generated | U8: Average Diesel/Kwh | V8: T 128 AXJ | W8: T 134 AXJ | X8: T 499 AXG | Y8: T 217 CHV | Z8: T 214 CHV | AA8: T 139 AXE | AB8: T 242 AXN | AC8: T 476 AWZ | AD8: T 226 AUQ | AE8: T 308 CLD | AF8: T 852 AWU | AG8: Machine ENG | AH8: Vehicle | AI8: Vehicle | AR8: Total Diseal Consumed Gen & Vehicle | AS8: Total cost /Day (TSH) | AT8: BALANCE
C9: 35132.06 | S9: =SUM(F9:L9) -> 0 | T9: =SUM(M9:R9) -> 0 | AR9: =SUM(AJ9+S9) -> 0 | AT9: 38784.7
S10: =SUM(F10:L10) -> 0 | T10: =SUM(M10:R10) -> 0 | U10: =SUM(N10:S10) -> 0 | AJ10: =SUM(V10:AI10) -> 0 | AR10: =SUM(AJ10+S10) -> 0
A11: 44228 | B11: 0.091 | C11: =SUM(C9+D11) -> 35132.06 | J11: 147.3 | L11: 1061.86 | P11: 388 | R11: 2518 | S11: =SUM(F11:L11) -> 1209.16 | T11: =SUM(M11:R11) -> 2906 | U11: =S11/T11 -> 0.41609085 | W11: 34.4 | X11: 63.25 | AJ11: =SUM(V11:AI11) -> 97.65 | AR11: =SUM(AJ11+S11) -> 1306.81 | AS11: =AR11*AU11 -> 0 | AT11: =C11 -> 35132.06
A12: 44229 | B12: 0.065 | C12: =SUM(C11-AR11+D12) -> 48625.25 | D12: 14800 | G12: 1173.44 | M12: 2849 | S12: =SUM(F12:L12) -> 1173.44 | T12: =SUM(M12:R12) -> 2849 | U12: =S12/T12 -> 0.41187785 | AJ12: =SUM(V12:AI12) -> 0 | AR12: =SUM(AJ12+S12) -> 1173.44 | AS12: =AR12*AU12 -> 0 | AT12: =C12 -> 48625.25
A13: 44230 | B13: 0.039 | C13: =SUM(C12-AR12+D13) -> 47451.81 | K13: 1100.54 | Q13: 2599 | S13: =SUM(F13:L13) -> 1100.54 | T13: =SUM(M13:R13) -> 2599 | U13: =S13/T13 -> 0.42344748 | X13: 42.18 | Y13: 35.39 | AJ13: =SUM(V13:AI13) -> 77.57 | AR13: =SUM(AJ13+S13) -> 1178.11 | AS13: =AR13*AU13 -> 0 | AT13: =C13 -> 47451.81
A14: 44231 | B14: 0.039 | C14: =SUM(C13-AR13+D14) -> 46273.7 | H14: 1094.66 | N14: 2681 | S14: =SUM(F14:L14) -> 1094.66 | T14: =SUM(M14:R14) -> 2681 | U14: =S14/T14 -> 0.40830287 | W14: 55.46 | Z14: 64.83 | AJ14: =SUM(V14:AI14) -> 120.29 | AR14: =SUM(AJ14+S14) -> 1214.95 | AS14: =AR14*AU14 -> 0 | AT14: =C14 -> 46273.7
A15: 44232 | B15: 0.0519 | C15: =SUM(C14-AR14+D15) -> 45058.75 | J15: 1254 | P15: 3008 | S15: =SUM(F15:L15) -> 1254 | T15: =SUM(M15:R15) -> 3008 | U15: =S15/T15 -> 0.4168883 | W15: 75.24 | X15: 21.4 | AJ15: =SUM(V15:AI15) -> 96.64 | AR15: =SUM(AJ15+S15) -> 1350.64 | AS15: =AR15*AU15 -> 0 | AT15: =C15 -> 45058.75
A16: 44233 | B16: 0.0779 | C16: =SUM(C15-AR15+D16) -> 43708.11 | L16: 946.83 | R16: 2354 | S16: =SUM(F16:L16) -> 946.83 | T16: =SUM(M16:R16) -> 2354 | U16: =S16/T16 -> 0.40222175 | AB16: 68.41 | AJ16: =SUM(V16:AI16) -> 68.41 | AR16: =SUM(AJ16+S16) -> 1015.24 | AS16: =AR16*AU16 -> 0 | AT16: =C16 -> 43708.11
A17: 44234 | B17: 0.0779 | C17: =SUM(C16-AR16+D17) -> 42692.87 | H17: 1142.59 | N17: 2780 | S17: =SUM(F17:L17) -> 1142.59 | T17: =SUM(M17:R17) -> 2780 | U17: =S17/T17 -> 0.4110036 | AJ17: =SUM(V17:AI17) -> 0 | AR17: =SUM(AJ17+S17) -> 1142.59 | AS17: =AR17*AU17 -> 0 | AT17: =C17 -> 42692.87
A18: 44235 | B18: 0.0519 | C18: =SUM(C17-AR17+D18) -> 41550.28 | K18: 1047.81 | Q18: 2545 | S18: =SUM(F18:L18) -> 1047.81 | T18: =SUM(M18:R18) -> 2545 | U18: =S18/T18 -> 0.41171316 | AB18: 10.87 | AC18: 59.5 | AJ18: =SUM(V18:AI18) -> 70.37 | AR18: =SUM(AJ18+S18) -> 1118.18 | AS18: =AR18*AU18 -> 0 | AT18: =C18 -> 41550.28
A19: 44236 | B19: 0.1039 | C19: =SUM(C18-AR18+D19) -> 40432.1 | G19: 1137.1 | M19: 2653 | S19: =SUM(F19:L19) -> 1137.1 | T19: =SUM(M19:R19) -> 2653 | U19: =S19/T19 -> 0.42860912 | W19: 54.2 | Z19: 75.99 | AJ19: =SUM(V19:AI19) -> 130.19 | AR19: =SUM(AJ19+S19) -> 1267.29 | AS19: =AR19*AU19 -> 0 | AT19: =C19 -> 40432.1
A20: 44237 | B20: 0.1039 | C20: =SUM(C19-AR19+D20) -> 39164.81 | J20: 1049.37 | P20: 2493 | S20: =SUM(F20:L20) -> 1049.37 | T20: =SUM(M20:R20) -> 2493 | U20: =S20/T20 -> 0.42092659 | AJ20: =SUM(V20:AI20) -> 0 | AR20: =SUM(AJ20+S20) -> 1049.37 | AS20: =AR20*AU20 -> 0 | AT20: =C20 -> 39164.81
A21: 44238 | B21: 0.1169 | C21: =SUM(C20-AR20+D21) -> 38115.44 | L21: 1059.11 | R21: 2528 | S21: =SUM(F21:L21) -> 1059.11 | T21: =SUM(M21:R21) -> 2528 | U21: =S21/T21 -> 0.41895174 | W21: 39.58 | Z21: 26.85 | AJ21: =SUM(V21:AI21) -> 66.43 | AR21: =SUM(AJ21+S21) -> 1125.54 | AS21: =AR21*AU21 -> 0 | AT21: =C21 -> 38115.44
A22: 44239 | B22: 0.2338 | C22: =SUM(C21-AR21+D22) -> 36989.9 | H22: 1117.15 | N22: 2703 | S22: =SUM(F22:L22) -> 1117.15 | T22: =SUM(M22:R22) -> 2703 | U22: =S22/T22 -> 0.41330004 | X22: 45.5 | AB22: 70.5 | AJ22: =SUM(V22:AI22) -> 116 | AR22: =SUM(AJ22+S22) -> 1233.15 | AS22: =AR22*AU22 -> 0 | AT22: =C22 -> 36989.9
A23: 44240 | B23: 0.2208 | C23: =SUM(C22-AR22+D23) -> 35756.75 | E23: 15000 | F23: Raha | K23: 1131.39 | Q23: 2690 | S23: =SUM(F23:L23) -> 1131.39 | T23: =SUM(M23:R23) -> 2690 | U23: =S23/T23 -> 0.42059108 | Z23: 49.82 | AC23: 25.32 | AH23: 244 | AI23: 155 | AJ23: =SUM(V23:AI23) -> 474.14 | AR23: =SUM(AJ23+S23) -> 1605.53 | AS23: =AR23*AU23 -> 0 | AT23: =C23 -> 35756.75
A24: 44241 | B24: 0.1948 | C24: =SUM(C23-AR23+D24) -> 34151.22 | G24: 1202.78 | M24: 2859 | S24: =SUM(F24:L24) -> 1202.78 | T24: =SUM(M24:R24) -> 2859 | U24: =S24/T24 -> 0.42069955 | AH24: 152 | AJ24: =SUM(V24:AI24) -> 152 | AR24: =SUM(AJ24+S24) -> 1354.78 | AS24: =AR24*AU24 -> 0 | AT24: =C24 -> 34151.22
A25: 44242 | B25: 0.1299 | C25: =SUM(C24-AR24+D25) -> 32796.44 | J25: 1187.73 | P25: 2860 | S25: =SUM(F25:L25) -> 1187.73 | T25: =SUM(M25:R25) -> 2860 | U25: =S25/T25 -> 0.41529021 | X25: 35.09 | AJ25: =SUM(V25:AI25) -> 35.09 | AR25: =SUM(AJ25+S25) -> 1222.82 | AS25: =AR25*AU25 -> 0 | AT25: =C25 -> 32796.44
A26: 44243 | B26: 0.0909 | C26: =SUM(C25-AR25+D26) -> 31573.62 | L26: 1105.91 | R26: 2636 | S26: =SUM(F26:L26) -> 1105.91 | T26: =SUM(M26:R26) -> 2636 | U26: =S26/T26 -> 0.41954097 | Z26: 73.95 | AH26: 116 | AJ26: =SUM(V26:AI26) -> 189.95 | AR26: =SUM(AJ26+S26) -> 1295.86 | AS26: =AR26*AU26 -> 0 | AT26: =C26 -> 31573.62
A27: 44244 | B27: 0.1169 | C27: =SUM(C26-AR26+D27) -> 45277.76 | D27: 15000 | H27: 1065.52 | N27: 2643 | S27: =SUM(F27:L27) -> 1065.52 | T27: =SUM(M27:R27) -> 2643 | U27: =S27/T27 -> 0.40314794 | W27: 40.08 | AD27: 169.22 | AI27: 40 | AJ27: =SUM(V27:AI27) -> 249.3 | AR27: =SUM(AJ27+S27) -> 1314.82 | AS27: =AR27*AU27 -> 0 | AT27: =C27 -> 45277.76
A28: 44245 | B28: 0.1169 | C28: =SUM(C27-AR27+D28) -> 43962.94 | G28: 1102.73 | M28: 2839 | S28: =SUM(F28:L28) -> 1102.73 | T28: =SUM(M28:R28) -> 2839 | U28: =S28/T28 -> 0.38842198 | AG28: 599.33 | AJ28: =SUM(V28:AI28) -> 599.33 | AR28: =SUM(AJ28+S28) -> 1702.06 | AS28: =AR28*AU28 -> 0 | AT28: =C28 -> 43962.94
A29: 44246 | B29: 0.1558 | C29: =SUM(C28-AR28+D29) -> 42260.88 | K29: 1235.28 | Q29: 2992 | S29: =SUM(F29:L29) -> 1235.28 | T29: =SUM(M29:R29) -> 2992 | U29: =S29/T29 -> 0.41286096 | AJ29: =SUM(V29:AI29) -> 0 | AR29: =SUM(AJ29+S29) -> 1235.28 | AS29: =AR29*AU29 -> 0 | AT29: =C29 -> 42260.88
A30: 44247 | B30: 0.1429 | C30: =SUM(C29-AR29+D30) -> 41025.6 | S30: =SUM(F30:L30) -> 0 | T30: =SUM(M30:R30) -> 0 | U30: =S30/T30 -> #DIV/0! | AJ30: =SUM(V30:AI30) -> 0 | AR30: =SUM(AJ30+S30) -> 0 | AS30: =AR30*AU30 -> 0 | AT30: =C30 -> 41025.6
A31: 44248 | C31: =SUM(C30-AR30+D31) -> 41025.6 | S31: =SUM(F31:L31) -> 0 | T31: =SUM(M31:R31) -> 0 | U31: =S31/T31 -> #DIV/0! | AJ31: =SUM(V31:AI31) -> 0 | AR31: =SUM(AJ31+S31) -> 0 | AS31: =AR31*AU31 -> 0 | AT31: =C31 -> 41025.6
A32: 44249 | C32: =SUM(C31-AR31+D32) -> 41025.6 | S32: =SUM(F32:L32) -> 0 | T32: =SUM(M32:R32) -> 0 | U32: =S32/T32 -> #DIV/0! | AJ32: =SUM(V32:AI32) -> 0 | AR32: =SUM(AJ32+S32) -> 0 | AS32: =AR32*AU32 -> 0 | AT32: =C32 -> 41025.6
A33: 44250 | C33: =SUM(C32-AR32+D33) -> 41025.6 | S33: =SUM(F33:L33) -> 0 | T33: =SUM(M33:R33) -> 0 | U33: =S33/T33 -> #DIV/0! | AJ33: =SUM(V33:AI33) -> 0 | AR33: =SUM(AJ33+S33) -> 0 | AS33: =AR33*AU33 -> 0 | AT33: =C33 -> 41025.6
A34: 44251 | C34: =SUM(C33-AR33+D34) -> 41025.6 | S34: =SUM(F34:L34) -> 0 | T34: =SUM(M34:R34) -> 0 | U34: =S34/T34 -> #DIV/0! | AJ34: =SUM(V34:AI34) -> 0 | AR34: =SUM(AJ34+S34) -> 0 | AS34: =AR34*AU34 -> 0 | AT34: =C34 -> 41025.6
A35: 44252 | C35: =SUM(C34-AR34+D35) -> 41025.6 | S35: =SUM(F35:L35) -> 0 | T35: =SUM(M35:R35) -> 0 | U35: =S35/T35 -> #DIV/0! | AJ35: =SUM(V35:AI35) -> 0 | AR35: =SUM(AJ35+S35) -> 0 | AS35: =AR35*AU35 -> 0 | AT35: =C35 -> 41025.6
A36: 44253 | C36: =SUM(C35-AR35+D36) -> 41025.6 | E36: 15000 | F36: Raha | S36: =SUM(F36:L36) -> 0 | T36: =SUM(M36:R36) -> 0 | U36: =S36/T36 -> #DIV/0! | AJ36: =SUM(V36:AI36) -> 0 | AR36: =SUM(AJ36+S36) -> 0 | AS36: =AR36*AU36 -> 0 | AT36: =C36 -> 41025.6
A37: 44254 | C37: =SUM(C36-AR36+D37) -> 41025.6 | S37: =SUM(F37:L37) -> 0 | T37: =SUM(M37:R37) -> 0 | U37: =S37/T37 -> #DIV/0! | AJ37: =SUM(V37:AI37) -> 0 | AR37: =SUM(AJ37+S37) -> 0 | AS37: =AR37*AU37 -> 0 | AT37: =C37 -> 41025.6
A38: 44255 | C38: =SUM(C37-AR37+D38) -> 41025.6 | S38: =SUM(F38:L38) -> 0 | T38: =SUM(M38:R38) -> 0 | U38: =S38/T38 -> #DIV/0! | AJ38: =SUM(V38:AI38) -> 0 | AR38: =SUM(AJ38+S38) -> 0 | AS38: =AR38*AU38 -> 0 | AT38: =C38 -> 41025.6
C39: =SUM(C38-AR38+D39) -> 41025.6 | S39: =SUM(F39:L39) -> 0 | T39: =SUM(M39:R39) -> 0 | U39: =S39/T39 -> #DIV/0! | AJ39: =SUM(V39:AI39) -> 0 | AR39: =SUM(AJ39+S39) -> 0 | AS39: =AR39*AU39 -> 0 | AT39: =C39 -> 41025.6
C40: =SUM(C39-AR39+D40) -> 41025.6 | S40: =SUM(F40:L40) -> 0 | T40: =SUM(M40:R40) -> 0 | U40: =S40/T40 -> #DIV/0! | AJ40: =SUM(V40:AI40) -> 0 | AR40: =SUM(AJ40+S40) -> 0 | AS40: =AR40*AU40 -> 0 | AT40: =C40 -> 41025.6
C41: =SUM(C40-AR40+D41) -> 41025.6 | S41: =SUM(F41:L41) -> 0 | T41: =SUM(M41:R41) -> 0 | U41: =S41/T41 -> #DIV/0! | AJ41: =SUM(V41:AI41) -> 0 | AR41: =SUM(AJ41+S41) -> 0 | AS41: =AR41*AU41 -> 0 | AT41: =C41 -> 41025.6
C42: =SUM(C41-AR41+D42) -> 41025.6 | S42: =SUM(F42:L42) -> 0 | T42: =SUM(M42:R42) -> 0 | AJ42: =SUM(V42:AI42) -> 0 | AR42: =SUM(AJ42+S42) -> 0 | AS42: =AR42*AU42 -> 0 | AT42: =C42 -> 41025.6
A43: BF | B43: =AVERAGE(B11:B42) -> 0.11105 | C43: =SUM(C42-AR42+D43) -> 41025.6 | S43: =SUM(F43:L43) -> 0 | T43: =SUM(M43:R43) -> 0 | AJ43: =SUM(V43:AI43) -> 0 | AR43: =SUM(AJ43+S43) -> 0 | AS43: =AR43*AU43 -> 0 | AT43: =C43 -> 41025.6
S44: =SUM(F44:L44) -> 0 | T44: =SUM(M44:R44) -> 0 | AJ44: =SUM(V44:AI44) -> 0 | AR44: =S44+AJ44 -> 0 | AS44: =AR44*AU44 -> 0
D45: =SUM(D11:D44) -> 29800 | E45: =SUM(E11:E42) -> 30000 | F45: =SUM(F11:F44) -> 0 | G45: =SUM(G11:G44) -> 4616.05 | H45: =SUM(H11:H44) -> 4419.92 | I45: =SUM(I11:I44) -> 0 | J45: =SUM(J11:J44) -> 3638.4 | K45: =SUM(K11:K44) -> 4515.02 | L45: =SUM(L11:L44) -> 4173.71 | M45: =SUM(M11:M44) -> 11200 | ... O45: =SUM(O11:O44) -> 0 | P45: =SUM(P11:P43) -> 8749 | Q45: =SUM(Q11:Q44) -> 10826 | R45: =SUM(R11:R44) -> 10036 | S45: =SUM(G45:L45) -> 21363.1 | T45: =SUM(M45:R45) -> 51618 | U45: =SUM(U11:U42) -> #DIV/0! | V45: =SUM(V9:V44) -> 0 | W45: =SUM(W9:W44) -> 298.96 | X45: =SUM(X9:X44) -> 207.42 | Y45: =SUM(Y9:Y44) -> 35.39 | Z45: =SUM(Z9:Z44) -> 291.44 | AA45: =SUM(AA9:AA44) -> 0 | AB45: =SUM(AB9:AB44) -> 149.78 | AC45: =SUM(AC10:AC44) -> 84.82 | AD45: =SUM(AD10:AD44) -> 169.22 | AE45: =SUM(AE9:AE44) -> 0 | AF45: =SUM(AF9:AF44) -> 0 | AG45: =SUM(AG9:AG44) -> 599.33 | AH45: =SUM(AH9:AH43) -> 512 | AI45: =SUM(AI9:AI39) -> 195 | AJ45: =SUM(AJ9:AJ44) -> 2543.36 | AR45: =SUM(AR11:AR43) -> 23906.46 | AS45: =SUM(AS11:AS44) -> 0
A46: Nb Day
S47: =AVERAGE(S11:S41) -> 689.13226 | T47: =S45*2315 -> 49455576 | U47: TZS | AR47: =AR45*2143 -> 51231544 | AS47: TZS
A48: Av. Occ | T48: =T47/2289 -> 21605.756 | U48: USD | AR48: =AR47/2289 -> 22381.627 | AS48: USD
B50: A & K VEHICLES | H50: MAULY VEHICLES | N50: GREEN LAND VEHICLES | T50: OTHERS VEHICLES | AE50: 1306.81
B51: Date | C51: Vehicles | D51: Liters | E51: Driver name | F51: Authority manager | H51: Date | I51: Vehicles | J51: Liters | K51: Driver name | L51: Authority manager | N51: Date | O51: Vehicles | P51: Liters | Q51: Driver name | R51: Authorized Manager | T51: Date | U51: Vehicles | V51: Liters | W51: Driver name | X51: Athorized Manager | Y51: Reasons | AE51: 1173.44
B52: 44240 | C52: T391DQR | D52: 134 | E52: Mtui | F52: Elihiruma | N52: 44240 | O52: T594DLP | P52: 81 | Q52: David | R52: Elihuruma | Y52: Cash paid
B53: 44240 | C53: T882DKQ | D53: 110 | E53: Lucas | F53: Elihiruma | N53: 44240 | O53: T635CAV | P53: 74 | Q53: Julias | R53: Elihuruma | AE53: =SUM(AE50:AE52) -> 2480.25
B54: 44241 | C54: T106CWQ | D54: 152 | E54: Siraji | F54: Elihiruma | N54: 44244 | O54: T594DLP | P54: 40 | Q54: David | R54: Elihuruma | AE54: 47250
B55: 44243 | C55: T840DDW | D55: 116 | E55: Siraji | F55: Elihiruma | AE55: =SUM(AE53:AE54) -> 49730.25

Sheet Energy Graph
A1: Date | B1: Usage KW | C1: Occ % | D1: Cost per room Total Occ | E1: Cost per room Guest Occ
A2: =Gen!A11 -> 44228 | B2: =SUM('[1]Summery Report'!F5) -> 5669 | C2: =SUM('[1]Summery Report'!C5) -> 0.623 | D2: =SUM('[1]Summery Report'!#REF!) -> #REF! | E2: =SUM('[1]Summery Report'!#REF!) -> #REF! | F2: 0.1
A3: =Gen!A12 -> 44229 | B3: =SUM('[1]Summery Report'!F6) -> 6159 | C3: =SUM('[1]Summery Report'!C6) -> 0.779 | D3: =SUM('[1]Summery Report'!#REF!) -> #REF! | E3: =SUM('[1]Summery Report'!#REF!) -> #REF! | F3: 0.1375
A4: =Gen!A13 -> 44230 | B4: =SUM('[1]Summery Report'!F7) -> 6580 | C4: =SUM('[1]Summery Report'!C7) -> 0.532 | D4: =SUM('[1]Summery Report'!#REF!) -> #REF! | E4: =SUM('[1]Summery Report'!#REF!) -> #REF! | F4: 0.0875
A5: =Gen!A14 -> 44231 | B5: =SUM('[1]Summery Report'!F8) -> 6223 | C5: =SUM('[1]Summery Report'!C8) -> 0.61 | D5: =SUM('[1]Summery Report'!#REF!) -> #REF! | E5: =SUM('[1]Summery Report'!#REF!) -> #REF! | F5: 0.225
A6: =Gen!A15 -> 44232 | B6: =SUM('[1]Summery Report'!F9) -> 5984 | C6: =SUM('[1]Summery Report'!C9) -> 0.688 | D6: =SUM('[1]Summery Report'!#REF!) -> #REF! | E6: =SUM('[1]Summery Report'!#REF!) -> #REF! | F6: 0.2
A7: =Gen!A16 -> 44233 | B7: =SUM('[1]Summery Report'!F10) -> 6103 | C7: =SUM('[1]Summery Report'!C10) -> 0.532 | D7: =SUM('[1]Summery Report'!#REF!) -> #REF! | E7: =SUM('[1]Summery Report'!#REF!) -> #REF! | F7: 0.35
A8: =Gen!A17 -> 44234 | B8: =SUM('[1]Summery Report'!F11) -> 5576 | C8: =SUM('[1]Summery Report'!C11) -> 0.753 | D8: =SUM('[1]Summery Report'!#REF!) -> #REF! | E8: =SUM('[1]Summery Report'!#REF!) -> #REF! | F8: 0.375
A9: =Gen!A18 -> 44235 | B9: =SUM('[1]Summery Report'!F12) -> 5532 | C9: =SUM('[1]Summery Report'!C12) -> 0.156 | D9: =SUM('[1]Summery Report'!#REF!) -> #REF! | E9: =SUM('[1]Summery Report'!#REF!) -> #REF! | F9: 0.325
A10: =Gen!A19 -> 44236 | B10: =SUM('[1]Summery Report'!F13) -> 6233 | C10: =SUM('[1]Summery Report'!C13) -> 0.442 | D10: =SUM('[1]Summery Report'!#REF!) -> #REF! | E10: =SUM('[1]Summery Report'!#REF!) -> #REF! | F10: 0.75
A11: =Gen!A20 -> 44237 | B11: =SUM('[1]Summery Report'!F14) -> 6063 | C11: =SUM('[1]Summery Report'!C14) -> 0.325 | D11: =SUM('[1]Summery Report'!#REF!) -> #REF! | E11: =SUM('[1]Summery Report'!#REF!) -> #REF! | F11: 0.7625
A12: =Gen!A21 -> 44238 | B12: =SUM('[1]Summery Report'!F15) -> 5967 | C12: =SUM('[1]Summery Report'!C15) -> 0.455 | D12: =SUM('[1]Summery Report'!#REF!) -> #REF! | E12: =SUM('[1]Summery Report'!#REF!) -> #REF! | F12: 0.1625
A13: =Gen!A22 -> 44239 | B13: =SUM('[1]Summery Report'!F16) -> 5863 | C13: =SUM('[1]Summery Report'!C16) -> 0.416 | D13: =SUM('[1]Summery Report'!#REF!) -> #REF! | E13: =SUM('[1]Summery Report'!#REF!) -> #REF! | F13: 0.1125
... A32: =Gen!A41 -> 0 | B32: =SUM('[1]Summery Report'!F35) -> 0 | C32: =SUM('[1]Summery Report'!C35) -> 0 | D32: =SUM('[1]Summery Report'!#REF!) -> #REF! | E32: =SUM('[1]Summery Report'!#REF!) -> #REF! | F32: 0.175
A33: =Gen!A42 -> 0 | B33: =[1]Gen!S41 -> 0

Sheet Lpg (2)
C3: Four Sasons Safari Lodge Serengeti
G6: VALUE | H6: Cost
A7: DATE | B7: A | C7: B | D7: C | F7: Meter Reading | G7: Total | H7: Occu | I7: No.of | J7: Kg
B8: 2Ton% | C8: 1Ton (%) | D8: 1Ton% | F8: consumption | G8: Consumption Kg | H8: % | I8: pax | J8: per pax
H9: 0.077
A10: 44228 | B10: 82 | C10: 0 | D10: 0 | G10: 74734.36
A11: 44229 | B11: 81 | C11: 0 | D11: 0 | G11: 74755.84
A12: 44230 | B12: 76 | C12: 0 | D12: 0 | G12: 74775.21
A13: 44231 | B13: 74 | C13: 0 | D13: 0 | G13: 74796.53
A14: 44232 | B14: 72 | C14: 0 | D14: 0 | G14: 74818
A15: 44233 | B15: 70 | C15: 0 | D15: 0 | G15: 74828.57
A16: 44234 | B16: 69 | C16: 0 | D16: 0 | G16: 74845.13
A17: 44235 | B17: 65 | C17: 0 | D17: 0 | G17: 74862.53
A18: 44236 | B18: 64 | C18: 0 | D18: 0 | G18: 74882.6
A19: 44237 | B19: 61 | C19: 0 | D19: 0 | G19: 74901.7
A20: 44238 | B20: 60 | C20: 0 | D20: 0 | G20: 74919.52
A21: 44239 | B21: 55 | C21: 0 | D21: 0 | G21: 74960.75
... A29: 44247 | B29: 47 | C29: 85 | D29: 85 | G29: 75065.86
A30: 44248
A31: 44249
A32: 44250
A33: 44251
A34: 44252
A35: 44253
A36: 44254
A37: 44255
C42: TOTAL USAGE | E42: =SUM(E10:E40) -> 0 | F42: =SUM(F10:F40) -> 0 | G42: =SUM(G10:G40) -> 1498154

Sheet LPG_Graph
A1: Date | B1: Usage KG | C1: Occ %
A2: =Gen!A11 -> 44228 | B2: ='[1]Lpg (2)'!G10 -> 197.56 | C2: =SUM([1]Gen!B11) -> 0.623
A3: =Gen!A12 -> 44229 | B3: ='[1]Lpg (2)'!G11 -> 131.956 | C3: =SUM([1]Gen!B12) -> 0.779
A4: =Gen!A13 -> 44230 | B4: ='[1]Lpg (2)'!G12 -> 117.48 | C4: =SUM([1]Gen!B13) -> 0.532
A5: =Gen!A14 -> 44231 | B5: ='[1]Lpg (2)'!G13 -> 102.96 | C5: =SUM([1]Gen!B14) -> 0.61
A6: =Gen!A15 -> 44232 | B6: ='[1]Lpg (2)'!G14 -> 101.816 | C6: =SUM([1]Gen!B15) -> 0.688
A7: =Gen!A16 -> 44233 | B7: ='[1]Lpg (2)'!G15 -> 106.92 | C7: =SUM([1]Gen!B16) -> 0.532
A8: =Gen!A17 -> 44234 | B8: ='[1]Lpg (2)'!G16 -> 116.732 | C8: =SUM([1]Gen!B17) -> 0.753
A9: =Gen!A18 -> 44235 | B9: ='[1]Lpg (2)'!G17 -> 105.732 | C9: =SUM([1]Gen!B18) -> 0.156
A10: =Gen!A19 -> 44236 | B10: ='[1]Lpg (2)'!G18 -> 114.4 | C10: =SUM([1]Gen!B19) -> 0.442
A11: =Gen!A20 -> 44237 | B11: ='[1]Lpg (2)'!G19 -> 102.08 | C11: =SUM([1]Gen!B20) -> 0.325
A12: =Gen!A21 -> 44238 | B12: ='[1]Lpg (2)'!G20 -> 105.292 | C12: =SUM([1]Gen!B21) -> 0.455
A13: =Gen!A22 -> 44239 | B13: ='[1]Lpg (2)'!G21 -> 114.664 | C13: =SUM([1]Gen!B22) -> 0.416
... A32: =Gen!A41 -> 0 | B32: ='[1]Lpg (2)'!G40 -> 0 | C32: =SUM([1]Gen!B41) -> #REF!

Sheet Water-Meter
A1: Four Seasons Safari Lodge Serengeti - Water Report
C2: Main Meter | F2: KITCHEN | I2: Amani café | L2: Main SW POOL | O2: Laundry | S2: BORE HOLE NO.1 METER READING | V2: BORE HOLE NO.2 METER READING | Y2: BORE HOLE NO.3 METER READING | AB2: BORE HOLE NO.4 METER READING | AE2: BORE HOLE NO.5 METER READING | AH2: BORE HOLE NO.6 METER READING | AK2: RAIN WATER - METER READING | AN2: TOTAL WATER PRODUCTION
A3: DATE | C3: Open Bal | D3: Final | E3: consumption | F3: Open Bal | G3: Final | H3: consumption | I3: Open Bal | J3: Final | K3: consumption | L3: Open Bal | M3: Final | N3: consumption | O3: Open Bal | P3: Final | Q3: consumption | R3: Total consumption
S4: OPEN | T4: FINAL | U4: PROD. | V4: OPEN | W4: FINAL | X4: PROD. | Y4: OPEN | Z4: FINAL | AA4: PROD. | AB4: OPEN | AC4: FINAL | AD4: M3 | AE4: OPEN | AF4: FINAL | AG4: M3 | AH4: OPEN | AI4: FINAL | AJ4: M3 | AK4: OPEN | AL4: FINAL | AM4: M3
C5: =D4 -> 0 | D5: 249358 | E5: =IF((D5-D4)<0,"0",(D5-D4)) -> 249358 | F5: =G4 -> 0 | H5: 0 | I5: =J4 -> 0 | J5: 8241 | L5: =M4 -> 0 | N5: 0 | O5: =P4 -> 0 | P5: 20888 | Q5: =IF((P5-P4)<0,"0",(P5-P4)) -> 20888 | T5: 64582 | V5: =W4 -> FINAL | W5: 73031 | X5: 0 | Y5: =Z4 -> FINAL | Z5: 89012 | AA5: 0 | AB5: =AC4 -> FINAL | AC5: 17837 | AE5: =AF4 -> FINAL | AF5: 18300 | AG5: 0 | AH5: =AI4 -> FINAL | AI5: 28766 | AK5: =AL4 -> FINAL
A6: =Gen!A11 -> 44228 | C6: =D5 -> 249358 | D6: 249416 | E6: =IF((D6-D5)<0,"0",(D6-D5)) -> 58 | F6: =G5 -> 0 | H6: =IF((G6-G5)<0,"0",(G6-G5)) -> 0 | I6: =J5 -> 8241 | J6: 8243 | L6: =M5 -> 0 | N6: =IF((M6-M5)<0,"0",(M6-M5)) -> 0 | O6: =P5 -> 20888 | P6: 20893 | Q6: =IF((P6-P5)<0,"0",(P6-P5)) -> 5 | T6: 64664 | U6: =IF((T6-T5)<0,"0",(T6-T5)) -> 82 | V6: =W5 -> 73031 | W6: 73031 | X6: =IF((W6-W5)<0,"0",(W6-W5)) -> 0 | Y6: =Z5 -> 89012 | Z6: 89094 | AA6: =IF((Z6-Z5)<0,"0",(Z6-Z5)) -> 82 | AB6: =AC5 -> 17837 | AC6: 17854 | AD6: =IF((AC6-AC5)<0,"0",(AC6-AC5)) -> 17 | AE6: =AF5 -> 18300 | AF6: 18300 | AG6: =IF((AF6-AF5)<0,"0",(AF6-AF5)) -> 0 | AH6: =AI5 -> 28766 | AI6: 28792 | AJ6: =IF((AI6-AI5)<0,"0",(AI6-AI5)) -> 26 | AK6: =AL5 -> 0 | AM6: =IF((AL6-AL5)<0,"0",(AL6-AL5)) -> 0 | AN6: =U6+X6+AA6+AD6+AG6+AJ6+AM6 -> 207
A7: =Gen!A12 -> 44229 | C7: =D6 -> 249416 | D7: 249472 | E7: =IF((D7-D6)<0,"0",(D7-D6)) -> 56 | F7: =G6 -> 0 | H7: =IF((G7-G6)<0,"0",(G7-G6)) -> 0 | I7: =J6 -> 8243 | J7: 8245 | L7: =M6 -> 0 | N7: =IF((M7-M6)<0,"0",(M7-M6)) -> 0 | O7: =P6 -> 20893 | P7: 20898 | Q7: =IF((P7-P6)<0,"0",(P7-P6)) -> 5 | T7: 64664 | U7: =IF((T7-T6)<0,"0",(T7-T6)) -> 0 | V7: =W6 -> 73031 | W7: 73031 | X7: =IF((W7-W6)<0,"0",(W7-W6)) -> 0 | Y7: =Z6 -> 89094 | Z7: 89188 | AA7: =IF((Z7-Z6)<0,"0",(Z7-Z6)) -> 94 | AB7: =AC6 -> 17854 | AC7: 17867 | AD7: =IF((AC7-AC6)<0,"0",(AC7-AC6)) -> 13 | AE7: =AF6 -> 18300 | AF7: 18300 | AG7: =IF((AF7-AF6)<0,"0",(AF7-AF6)) -> 0 | AH7: =AI6 -> 28792 | AI7: 28818 | AJ7: =IF((AI7-AI6)<0,"0",(AI7-AI6)) -> 26 | AK7: =AL6 -> 0 | AM7: =IF((AL7-AL6)<0,"0",(AL7-AL6)) -> 0 | AN7: =U7+X7+AA7+AD7+AG7+AJ7+AM7 -> 133
A8: =Gen!A13 -> 44230 | C8: =D7 -> 249472 | D8: 249518 | E8: =IF((D8-D7)<0,"0",(D8-D7)) -> 46 | F8: =G7 -> 0 | H8: =IF((G8-G7)<0,"0",(G8-G7)) -> 0 | I8: =J7 -> 8245 | J8: 8246 | L8: =M7 -> 0 | N8: =IF((M8-M7)<0,"0",(M8-M7)) -> 0 | O8: =P7 -> 20898 | P8: 20901 | Q8: =IF((P8-P7)<0,"0",(P8-P7)) -> 3 | T8: 64064 | U8: =IF((T8-T7)<0,"0",(T8-T7)) -> 0 | V8: =W7 -> 73031 | W8: 73031 | X8: =IF((W8-W7)<0,"0",(W8-W7)) -> 0 | Y8: =Z7 -> 89188 | Z8: 89238 | AA8: =IF((Z8-Z7)<0,"0",(Z8-Z7)) -> 50 | AB8: =AC7 -> 17867 | AC8: 17883 | AD8: =IF((AC8-AC7)<0,"0",(AC8-AC7)) -> 16 | AE8: =AF7 -> 18300 | AF8: 18300 | AG8: =IF((AF8-AF7)<0,"0",(AF8-AF7)) -> 0 | AH8: =AI7 -> 28818 | AI8: 28844 | AJ8: =IF((AI8-AI7)<0,"0",(AI8-AI7)) -> 26 | AK8: =AL7 -> 0 | AM8: =IF((AL8-AL7)<0,"0",(AL8-AL7)) -> 0 | AN8: =U8+X8+AA8+AD8+AG8+AJ8+AM8 -> 92
A9: =Gen!A14 -> 44231 | C9: =D8 -> 249518 | D9: 249570 | E9: =IF((D9-D8)<0,"0",(D9-D8)) -> 52 | F9: =G8 -> 0 | H9: =IF((G9-G8)<0,"0",(G9-G8)) -> 0 | I9: =J8 -> 8246 | J9: 8248 | L9: =M8 -> 0 | N9: =IF((M9-M8)<0,"0",(M9-M8)) -> 0 | O9: =P8 -> 20901 | P9: 20908 | Q9: =IF((P9-P8)<0,"0",(P9-P8)) -> 7 | T9: 64064 | U9: =IF((T9-T8)<0,"0",(T9-T8)) -> 0 | V9: =W8 -> 73031 | W9: 73031 | X9: =IF((W9-W8)<0,"0",(W9-W8)) -> 0 | Y9: =Z8 -> 89238 | Z9: 89289 | AA9: =IF((Z9-Z8)<0,"0",(Z9-Z8)) -> 51 | AB9: =AC8 -> 17883 | AC9: 17900 | AD9: =IF((AC9-AC8)<0,"0",(AC9-AC8)) -> 17 | AE9: =AF8 -> 18300 | AF9: 18300 | AG9: =IF((AF9-AF8)<0,"0",(AF9-AF8)) -> 0 | AH9: =AI9 -> 28870 | AI9: 28870 | AJ9: =IF((AI9-AI8)<0,"0",(AI9-AI8)) -> 26 | AK9: =AL8 -> 0 | AM9: =IF((AL9-AL8)<0,"0",(AL9-AL8)) -> 0 | AN9: =U9+X9+AA9+AD9+AG9+AJ9+AM9 -> 94
A10: =Gen!A15 -> 44232 | C10: =D9 -> 249570 | D10: 249615 | E10: =IF((D10-D9)<0,"0",(D10-D9)) -> 45 | F10: =G9 -> 0 | H10: =IF((G10-G9)<0,"0",(G10-G9)) -> 0 | I10: =J9 -> 8248 | J10: 8249 | L10: =M9 -> 0 | N10: =IF((M10-M9)<0,"0",(M10-M9)) -> 0 | O10: =P9 -> 20908 | P10: 20913 | Q10: =IF((P10-P9)<0,"0",(P10-P9)) -> 5 | T10: 64064 | U10: =IF((T10-T9)<0,"0",(T10-T9)) -> 0 | V10: =W9 -> 73031 | W10: 73031 | X10: =IF((W10-W9)<0,"0",(W10-W9)) -> 0 | Y10: =Z9 -> 89289 | Z10: 89339 | AA10: =IF((Z10-Z9)<0,"0",(Z10-Z9)) -> 50 | AB10: =AC9 -> 17900 | AC10: 17917 | AD10: =IF((AC10-AC9)<0,"0",(AC10-AC9)) -> 17 | AE10: =AF9 -> 18300 | AF10: 18300 | AG10: =IF((AF10-AF9)<0,"0",(AF10-AF9)) -> 0 | AH10: =AI9 -> 28870 | AI10: 28896 | AJ10: =IF((AI10-AI9)<0,"0",(AI10-AI9)) -> 26 | AK10: =AL9 -> 0 | AM10: =IF((AL10-AL9)<0,"0",(AL10-AL9)) -> 0 | AN10: =U10+X10+AA10+AD10+AG10+AJ10+AM10 -> 93
A11: =Gen!A16 -> 44233 | C11: =D10 -> 249615 | D11: 249660 | E11: =IF((D11-D10)<0,"0",(D11-D10)) -> 45 | F11: =G10 -> 0 | H11: =IF((G11-G10)<0,"0",(G11-G10)) -> 0 | I11: =J10 -> 8249 | J11: 8251 | L11: =M10 -> 0 | N11: =IF((M11-M10)<0,"0",(M11-M10)) -> 0 | O11: =P10 -> 20913 | P11: 20915 | Q11: =IF((P11-P10)<0,"0",(P11-P10)) -> 2 | T11: 64064 | U11: =IF((T11-T10)<0,"0",(T11-T10)) -> 0 | V11: =W10 -> 73031 | W11: 73031 | X11: =IF((W11-W10)<0,"0",(W11-W10)) -> 0 | Y11: =Z10 -> 89339 | Z11: 89384 | AA11: =IF((Z11-Z10)<0,"0",(Z11-Z10)) -> 45 | AB11: =AC10 -> 17917 | AC11: 17934 | AD11: =IF((AC11-AC10)<0,"0",(AC11-AC10)) -> 17 | AE11: =AF11 -> 18300 | AF11: 18300 | AG11: =IF((AF11-AF10)<0,"0",(AF11-AF10)) -> 0 | AH11: =AI10 -> 28896 | AI11: 28922 | AJ11: =IF((AI11-AI10)<0,"0",(AI11-AI10)) -> 26 | AK11: =AL10 -> 0 | AM11: =IF((AL11-AL10)<0,"0",(AL11-AL10)) -> 0 | AN11: =U11+X11+AA11+AD11+AG11+AJ11+AM11 -> 88
A12: =Gen!A17 -> 44234 | C12: =D11 -> 249660 | D12: 249718 | E12: =IF((D12-D11)<0,"0",(D12-D11)) -> 58 | F12: =G11 -> 0 | H12: =IF((G12-G11)<0,"0",(G12-G11)) -> 0 | I12: =J11 -> 8251 | J12: 8254 | L12: =M11 -> 0 | N12: =IF((M12-M11)<0,"0",(M12-M11)) -> 0 | O12: =P11 -> 20915 | P12: 20918 | Q12: =IF((P12-P11)<0,"0",(P12-P11)) -> 3 | T12: 64064 | U12: =IF((T12-T11)<0,"0",(T12-T11)) -> 0 | V12: =W11 -> 73031 | W12: 73031 | X12: =IF((W12-W11)<0,"0",(W12-W11)) -> 0 | Y12: =Z11 -> 89384 | Z12: 89424 | AA12: =IF((Z12-Z11)<0,"0",(Z12-Z11)) -> 40 | AB12: =AC11 -> 17934 | AC12: 17951 | AD12: =IF((AC12-AC11)<0,"0",(AC12-AC11)) -> 17 | AE12: =AF12 -> 18300 | AF12: 18300 | AG12: =IF((AF12-AF11)<0,"0",(AF12-AF11)) -> 0 | AH12: =AI11 -> 28922 | AI12: 28955 | AJ12: =IF((AI12-AI11)<0,"0",(AI12-AI11)) -> 33 | AK12: =AL11 -> 0 | AM12: =IF((AL12-AL11)<0,"0",(AL12-AL11)) -> 0 | AN12: =U12+X12+AA12+AD12+AG12+AJ12+AM12 -> 90
A13: =Gen!A18 -> 44235 | C13: =D12 -> 249718 | D13: 249763 | E13: =IF((D13-D12)<0,"0",(D13-D12)) -> 45 | F13: =G12 -> 0 | H13: =IF((G13-G12)<0,"0",(G13-G12)) -> 0 | I13: =J12 -> 8254 | J13: 8257 | L13: =M12 -> 0 | N13: =IF((M13-M12)<0,"0",(M13-M12)) -> 0 | O13: =P12 -> 20918 | P13: 20924 | Q13: =IF((P13-P12)<0,"0",(P13-P12)) -> 6 | T13: 64064 | U13: =IF((T13-T12)<0,"0",(T13-T12)) -> 0 | V13: =W12 -> 73031 | W13: 73031 | X13: =IF((W13-W12)<0,"0",(W13-W12)) -> 0 | Y13: =Z12 -> 89424 | Z13: 89456 | AA13: =IF((Z13-Z12)<0,"0",(Z13-Z12)) -> 32 | AB13: =AC12 -> 17951 | AC13: 17963 | AD13: =IF((AC13-AC12)<0,"0",(AC13-AC12)) -> 12 | AE13: =AF13 -> 18300 | AF13: 18300 | AG13: =IF((AF13-AF12)<0,"0",(AF13-AF12)) -> 0 | AH13: =AI12 -> 28955 | AI13: 28972 | AJ13: =IF((AI13-AI12)<0,"0",(AI13-AI12)) -> 17 | AK13: =AL12 -> 0 | AM13: =IF((AL13-AL12)<0,"0",(AL13-AL12)) -> 0 | AN13: =U13+X13+AA13+AD13+AG13+AJ13+AM13 -> 61
A14: =Gen!A19 -> 44236 | C14: =D13 -> 249763 | D14: 249823 | E14: =IF((D14-D13)<0,"0",(D14-D13)) -> 60 | F14: =G13 -> 0 | H14: =IF((G14-G13)<0,"0",(G14-G13)) -> 0 | I14: =J13 -> 8257 | J14: 8259 | L14: =M13 -> 0 | N14: =IF((M14-M13)<0,"0",(M14-M13)) -> 0 | O14: =P13 -> 20924 | P14: 20927 | Q14: =IF((P14-P13)<0,"0",(P14-P13)) -> 3 | T14: 64064 | U14: =IF((T14-T13)<0,"0",(T14-T13)) -> 0 | V14: =W13 -> 73031 | W14: 73031 | X14: =IF((W14-W13)<0,"0",(W14-W13)) -> 0 | Y14: =Z13 -> 89456 | Z14: 89499 | AA14: =IF((Z14-Z13)<0,"0",(Z14-Z13)) -> 43 | AB14: =AC13 -> 17963 | AC14: 17978 | AD14: =IF((AC14-AC13)<0,"0",(AC14-AC13)) -> 15 | AE14: =AF14 -> 18300 | AF14: 18300 | AG14: =IF((AF14-AF13)<0,"0",(AF14-AF13)) -> 0 | AH14: =AI13 -> 28972 | AI14: 28996 | AJ14: =IF((AI14-AI13)<0,"0",(AI14-AI13)) -> 24 | AK14: =AL13 -> 0 | AM14: =IF((AL14-AL13)<0,"0",(AL14-AL13)) -> 0 | AN14: =U14+X14+AA14+AD14+AG14+AJ14+AM14 -> 82
A15: =Gen!A20 -> 44237 | C15: =D14 -> 249823 | D15: 249880 | E15: =IF((D15-D14)<0,"0",(D15-D14)) -> 57 | F15: =G14 -> 0 | H15: =IF((G15-G14)<0,"0",(G15-G14)) -> 0 | I15: =J14 -> 8259 | J15: 8260 | L15: =M14 -> 0 | N15: =IF((M15-M14)<0,"0",(M15-M14)) -> 0 | O15: =P14 -> 20927 | P15: 20931 | Q15: =IF((P15-P14)<0,"0",(P15-P14)) -> 4 | T15: 64064 | U15: =IF((T15-T14)<0,"0",(T15-T14)) -> 0 | V15: =W14 -> 73031 | W15: 73031 | X15: =IF((W15-W14)<0,"0",(W15-W14)) -> 0 | Y15: =Z14 -> 89499 | Z15: 89536 | AA15: =IF((Z15-Z14)<0,"0",(Z15-Z14)) -> 37 | AB15: =AC14 -> 17978 | AC15: 17995 | AD15: =IF((AC15-AC14)<0,"0",(AC15-AC14)) -> 17 | AE15: =AF15 -> 18300 | AF15: 18300 | AG15: =IF((AF15-AF14)<0,"0",(AF15-AF14)) -> 0 | AH15: =AI14 -> 28996 | AI15: 29019 | AJ15: =IF((AI15-AI14)<0,"0",(AI15-AI14)) -> 23 | AK15: =AL14 -> 0 | AM15: =IF((AL15-AL14)<0,"0",(AL15-AL14)) -> 0 | AN15: =U15+X15+AA15+AD15+AG15+AJ15+AM15 -> 77
A16: =Gen!A21 -> 44238 | C16: =D15 -> 249880 | D16: 249929 | E16: =IF((D16-D15)<0,"0",(D16-D15)) -> 49 | F16: =G15 -> 0 | H16: =IF((G16-G15)<0,"0",(G16-G15)) -> 0 | I16: =J15 -> 8260 | J16: 8261 | L16: =M15 -> 0 | N16: =IF((M16-M15)<0,"0",(M16-M15)) -> 0 | O16: =P15 -> 20931 | P16: 20935 | Q16: =IF((P16-P15)<0,"0",(P16-P15)) -> 4 | T16: 64064 | U16: =IF((T16-T15)<0,"0",(T16-T15)) -> 0 | V16: =W15 -> 73031 | W16: 73031 | X16: =IF((W16-W15)<0,"0",(W16-W15)) -> 0 | Y16: =Z15 -> 89536 | Z16: 89545 | AA16: =IF((Z16-Z15)<0,"0",(Z16-Z15)) -> 9 | AB16: =AC15 -> 17995 | AC16: 18009 | AD16: =IF((AC16-AC15)<0,"0",(AC16-AC15)) -> 14 | AE16: =AF16 -> 18300 | AF16: 18300 | AG16: =IF((AF16-AF15)<0,"0",(AF16-AF15)) -> 0 | AH16: =AI15 -> 29019 | AI16: 29048 | AJ16: =IF((AI16-AI15)<0,"0",(AI16-AI15)) -> 29 | AK16: =AL15 -> 0 | AM16: =IF((AL16-AL15)<0,"0",(AL16-AL15)) -> 0 | AN16: =U16+X16+AA16+AD16+AG16+AJ16+AM16 -> 52
A17: =Gen!A22 -> 44239 | C17: =D16 -> 249929 | D17: 249981 | E17: =IF((D17-D16)<0,"0",(D17-D16)) -> 52 | F17: =G16 -> 0 | H17: =IF((G17-G16)<0,"0",(G17-G16)) -> 0 | I17: =J16 -> 8261 | J17: 8263 | L17: =M16 -> 0 | N17: =IF((M17-M16)<0,"0",(M17-M16)) -> 0 | O17: =P16 -> 20935 | P17: 20938 | Q17: =IF((P17-P16)<0,"0",(P17-P16)) -> 3 | T17: 64064 | U17: =IF((T17-T16)<0,"0",(T17-T16)) -> 0 | V17: =W16 -> 73031 | W17: 73031 | X17: =IF((W17-W16)<0,"0",(W17-W16)) -> 0 | Y17: =Z16 -> 89545 | Z17: 89545 | AA17: =IF((Z17-Z16)<0,"0",(Z17-Z16)) -> 0 | AB17: =AC16 -> 18009 | AC17: 18025 | AD17: =IF((AC17-AC16)<0,"0",(AC17-AC16)) -> 16 | AE17: =AF17 -> 18300 | AF17: 18300 | AG17: =IF((AF17-AF16)<0,"0",(AF17-AF16)) -> 0 | AH17: =AI16 -> 29048 | AI17: 29071 | AJ17: =IF((AI17-AI16)<0,"0",(AI17-AI16)) -> 23 | AK17: =AL16 -> 0 | AM17: =IF((AL17-AL16)<0,"0",(AL17-AL16)) -> 0 | AN17: =U17+X17+AA17+AD17+AG17+AJ17+AM17 -> 39
A18: =Gen!A23 -> 44240 | C18: =D17 -> 249981 | D18: 250039 | E18: =IF((D18-D17)<0,"0",(D18-D17)) -> 58 | F18: =G17 -> 0 | H18: =IF((G18-G17)<0,"0",(G18-G17)) -> 0 | I18: =J17 -> 8263 | J18: 8264 | L18: =M17 -> 0 | N18: =IF((M18-M17)<0,"0",(M18-M17)) -> 0 | O18: =P17 -> 20938 | P18: 20940 | Q18: =IF((P18-P17)<0,"0",(P18-P17)) -> 2 | T18: 64064 | U18: =IF((T18-T17)<0,"0",(T18-T17)) -> 0 | V18: =W17 -> 73031 | W18: 73031 | X18: =IF((W18-W17)<0,"0",(W18-W17)) -> 0 | Y18: =Z17 -> 89545 | Z18: 89545 | AA18: =IF((Z18-Z17)<0,"0",(Z18-Z17)) -> 0 | AB18: =AC17 -> 18025 | AC18: 18041 | AD18: =IF((AC18-AC17)<0,"0",(AC18-AC17)) -> 16 | AE18: =AF18 -> 18300 | AF18: 18300 | AG18: =IF((AF18-AF17)<0,"0",(AF18-AF17)) -> 0 | AH18: =AI17 -> 29071 | AI18: 29099 | AJ18: =IF((AI18-AI17)<0,"0",(AI18-AI17)) -> 28 | AK18: =AL17 -> 0 | AM18: =IF((AL18-AL17)<0,"0",(AL18-AL17)) -> 0 | AN18: =U18+X18+AA18+AD18+AG18+AJ18+AM18 -> 44
A19: =Gen!A24 -> 44241 | C19: =D18 -> 250039 | D19: 250093 | E19: =IF((D19-D18)<0,"0",(D19-D18)) -> 54 | F19: =G18 -> 0 | H19: =IF((G19-G18)<0,"0",(G19-G18)) -> 0 | I19: =J18 -> 8264 | J19: 8265 | L19: =M18 -> 0 | N19: =IF((M19-M18)<0,"0",(M19-M18)) -> 0 | O19: =P18 -> 20940 | P19: 20942 | Q19: =IF((P19-P18)<0,"0",(P19-P18)) -> 2 | T19: 64064 | U19: =IF((T19-T18)<0,"0",(T19-T18)) -> 0 | V19: =W18 -> 73031 | W19: 73031 | X19: =IF((W19-W18)<0,"0",(W19-W18)) -> 0 | Y19: =Z18 -> 89545 | Z19: 89587 | AA19: =IF((Z19-Z18)<0,"0",(Z19-Z18)) -> 42 | AB19: =AC18 -> 18041 | AC19: 18055 | AD19: =IF((AC19-AC18)<0,"0",(AC19-AC18)) -> 14 | AE19: =AF19 -> 18300 | AF19: 18300 | AG19: =IF((AF19-AF18)<0,"0",(AF19-AF18)) -> 0 | AH19: =AI18 -> 29099 | AI19: 29124 | AJ19: =IF((AI19-AI18)<0,"0",(AI19-AI18)) -> 25 | AK19: =AL18 -> 0 | AM19: =IF((AL19-AL18)<0,"0",(AL19-AL18)) -> 0 | AN19: =U19+X19+AA19+AD19+AG19+AJ19+AM19 -> 81
A20: =Gen!A25 -> 44242 | C20: =D19 -> 250093 | D20: 250149 | E20: =IF((D20-D19)<0,"0",(D20-D19)) -> 56 | F20: =G19 -> 0 | H20: =IF((G20-G19)<0,"0",(G20-G19)) -> 0 | I20: =J19 -> 8265 | J20: 8267 | L20: =M19 -> 0 | N20: =IF((M20-M19)<0,"0",(M20-M19)) -> 0 | O20: =P19 -> 20942 | P20: 20952 | Q20: =IF((P20-P19)<0,"0",(P20-P19)) -> 10 | T20: 64064 | U20: =IF((T20-T19)<0,"0",(T20-T19)) -> 0 | V20: =W19 -> 73031 | W20: 73031 | X20: =IF((W20-W19)<0,"0",(W20-W19)) -> 0 | Y20: =Z19 -> 89587 | Z20: 89640 | AA20: =IF((Z20-Z19)<0,"0",(Z20-Z19)) -> 53 | AB20: =AC19 -> 18055 | AC20: 18072 | AD20: =IF((AC20-AC19)<0,"0",(AC20-AC19)) -> 17 | AE20: =AF20 -> 18300 | AF20: 18300 | AG20: =IF((AF20-AF19)<0,"0",(AF20-AF19)) -> 0 | AH20: =AI19 -> 29124 | AI20: 29150 | AJ20: =IF((AI20-AI19)<0,"0",(AI20-AI19)) -> 26 | AK20: =AL19 -> 0 | AM20: =IF((AL20-AL19)<0,"0",(AL20-AL19)) -> 0 | AN20: =U20+X20+AA20+AD20+AG20+AJ20+AM20 -> 96
A21: =Gen!A26 -> 44243 | C21: =D20 -> 250149 | D21: 250194 | E21: =IF((D21-D20)<0,"0",(D21-D20)) -> 45 | F21: =G20 -> 0 | H21: =IF((G21-G20)<0,"0",(G21-G20)) -> 0 | I21: =J20 -> 8267 | J21: 8268 | L21: =M20 -> 0 | N21: =IF((M21-M20)<0,"0",(M21-M20)) -> 0 | O21: =P20 -> 20952 | P21: 20955 | Q21: =IF((P21-P20)<0,"0",(P21-P20)) -> 3 | T21: 64064 | U21: =IF((T21-T20)<0,"0",(T21-T20)) -> 0 | V21: =W20 -> 73031 | W21: 73031 | X21: =IF((W21-W20)<0,"0",(W21-W20)) -> 0 | Y21: =Z20 -> 89640 | Z21: 89647 | AA21: =IF((Z21-Z20)<0,"0",(Z21-Z20)) -> 7 | AB21: =AC20 -> 18072 | AC21: 18088 | AD21: =IF((AC21-AC20)<0,"0",(AC21-AC20)) -> 16 | AE21: =AF20 -> 18300 | AF21: 18300 | AG21: =IF((AF21-AF20)<0,"0",(AF21-AF20)) -> 0 | AH21: =AI20 -> 29150 | AI21: 29176 | AJ21: =IF((AI21-AI20)<0,"0",(AI21-AI20)) -> 26 | AK21: =AL20 -> 0 | AM21: =IF((AL21-AL20)<0,"0",(AL21-AL20)) -> 0 | AN21: =U21+X21+AA21+AD21+AG21+AJ21+AM21 -> 49
A22: =Gen!A27 -> 44244 | C22: =D21 -> 250194 | D22: 250242 | E22: =IF((D22-D21)<0,"0",(D22-D21)) -> 48 | F22: =G21 -> 0 | H22: =IF((G22-G21)<0,"0",(G22-G21)) -> 0 | I22: =J21 -> 8268 | J22: 8270 | L22: =M21 -> 0 | N22: =IF((M22-M21)<0,"0",(M22-M21)) -> 0 | O22: =P21 -> 20955 | P22: 20958 | Q22: =IF((P22-P21)<0,"0",(P22-P21)) -> 3 | T22: 64064 | U22: =IF((T22-T21)<0,"0",(T22-T21)) -> 0 | V22: =W21 -> 73031 | W22: 73031 | X22: =IF((W22-W21)<0,"0",(W22-W21)) -> 0 | Y22: =Z21 -> 89647 | Z22: 89647 | AA22: =IF((Z22-Z21)<0,"0",(Z22-Z21)) -> 0 | AB22: =AC21 -> 18088 | AC22: 18103 | AD22: =IF((AC22-AC21)<0,"0",(AC22-AC21)) -> 15 | AE22: =AF21 -> 18300 | AF22: 18300 | AG22: =IF((AF22-AF21)<0,"0",(AF22-AF21)) -> 0 | AH22: =AI21 -> 29176 | AI22: 29202 | AJ22: =IF((AI22-AI21)<0,"0",(AI22-AI21)) -> 26 | AK22: =AL21 -> 0 | AM22: =IF((AL22-AL21)<0,"0",(AL22-AL21)) -> 0 | AN22: =U22+X22+AA22+AD22+AG22+AJ22+AM22 -> 41
A23: =Gen!A28 -> 44245 | C23: =D22 -> 250242 | D23: 250295 | E23: =IF((D23-D22)<0,"0",(D23-D22)) -> 53 | F23: =G22 -> 0 | H23: =IF((G23-G22)<0,"0",(G23-G22)) -> 0 | I23: =J22 -> 8270 | J23: 8271 | L23: =M22 -> 0 | N23: =IF((M23-M22)<0,"0",(M23-M22)) -> 0 | O23: =P22 -> 20958 | P23: 20964 | Q23: =IF((P23-P22)<0,"0",(P23-P22)) -> 6 | T23: 64064 | U23: =IF((T23-T22)<0,"0",(T23-T22)) -> 0 | V23: =W22 -> 73031 | W23: 73031 | X23: =IF((W23-W22)<0,"0",(W23-W22)) -> 0 | Y23: =Z22 -> 89647 | Z23: 89701 | AA23: =IF((Z23-Z22)<0,"0",(Z23-Z22)) -> 54 | AB23: =AC22 -> 18103 | AC23: 18119 | AD23: =IF((AC23-AC22)<0,"0",(AC23-AC22)) -> 16 | AE23: =AF22 -> 18300 | AF23: 18300 | AG23: =IF((AF23-AF22)<0,"0",(AF23-AF22)) -> 0 | AH23: =AI22 -> 29202 | AI23: 29227 | AJ23: =IF((AI23-AI22)<0,"0",(AI23-AI22)) -> 25 | AK23: =AL22 -> 0 | AM23: =IF((AL23-AL22)<0,"0",(AL23-AL22)) -> 0 | AN23: =U23+X23+AA23+AD23+AG23+AJ23+AM23 -> 95
A24: =Gen!A29 -> 44246 | C24: =D23 -> 250295 | D24: 250360 | E24: =IF((D24-D23)<0,"0",(D24-D23)) -> 65 | F24: =G23 -> 0 | H24: =IF((G24-G23)<0,"0",(G24-G23)) -> 0 | I24: =J23 -> 8271 | J24: 8273 | L24: =M23 -> 0 | N24: =IF((M24-M23)<0,"0",(M24-M23)) -> 0 | O24: =P23 -> 20964 | P24: 20968 | Q24: =IF((P24-P23)<0,"0",(P24-P23)) -> 4 | T24: 64154 | U24: =IF((T24-T23)<0,"0",(T24-T23)) -> 90 | V24: =W23 -> 73031 | W24: 73031 | X24: =IF((W24-W23)<0,"0",(W24-W23)) -> 0 | Y24: =Z23 -> 89701 | Z24: 89757 | AA24: =IF((Z24-Z23)<0,"0",(Z24-Z23)) -> 56 | AB24: =AC23 -> 18119 | AC24: 18135 | AD24: =IF((AC24-AC23)<0,"0",(AC24-AC23)) -> 16 | AE24: =AF23 -> 18300 | AF24: 18300 | AG24: =IF((AF24-AF23)<0,"0",(AF24-AF23)) -> 0 | AH24: =AI23 -> 29227 | AI24: 29253 | AJ24: =IF((AI24-AI23)<0,"0",(AI24-AI23)) -> 26 | AK24: =AL23 -> 0 | AM24: =IF((AL24-AL23)<0,"0",(AL24-AL23)) -> 0 | AN24: =U24+X24+AA24+AD24+AG24+AJ24+AM24 -> 188
A25: =Gen!A30 -> 44247 | C25: =D24 -> 250360 | E25: =IF((D25-D24)<0,"0",(D25-D24)) -> 0 | F25: =G24 -> 0 | H25: =IF((G26-G24)<0,"0",(G26-G24)) -> 0 | I25: =J24 -> 8273 | L25: =M24 -> 0 | N25: =IF((M25-M24)<0,"0",(M25-M24)) -> 0 | O25: =P24 -> 20968 | Q25: =IF((P25-P24)<0,"0",(P25-P24)) -> 0 | U25: =IF((T25-T24)<0,"0",(T25-T24)) -> 0 | V25: =W24 -> 73031 | X25: =IF((W25-W24)<0,"0",(W25-W24)) -> 0 | Y25: =Z24 -> 89757 | AA25: =IF((Z25-Z24)<0,"0",(Z25-Z24)) -> 0 | AB25: =AC24 -> 18135 | AD25: =IF((AC25-AC24)<0,"0",(AC25-AC24)) -> 0 | AE25: =AF24 -> 18300 | AG25: =IF((AF25-AF24)<0,"0",(AF25-AF24)) -> 0 | AH25: =AI24 -> 29253 | AJ25: =IF((AI25-AI24)<0,"0",(AI25-AI24)) -> 0 | AK25: =AL24 -> 0 | AM25: =IF((AL25-AL24)<0,"0",(AL25-AL24)) -> 0 | AN25: =U25+X25+AA25+AD25+AG25+AJ25+AM25 -> 0
A26: =Gen!A31 -> 44248 | C26: =D25 -> 0 | E26: =IF((D26-D25)<0,"0",(D26-D25)) -> 0 | F26: =G26 -> 0 | H26: =IF((G27-G25)<0,"0",(G27-G25)) -> 0 | I26: =J25 -> 0 | L26: =M25 -> 0 | N26: =IF((M26-M25)<0,"0",(M26-M25)) -> 0 | O26: =P25 -> 0 | Q26: =IF((P26-P25)<0,"0",(P26-P25)) -> 0 | U26: =IF((T26-T25)<0,"0",(T26-T25)) -> 0 | V26: =W25 -> 0 | X26: =IF((W26-W25)<0,"0",(W26-W25)) -> 0 | Y26: =Z25 -> 0 | AA26: =IF((Z26-Z25)<0,"0",(Z26-Z25)) -> 0 | AB26: =AC25 -> 0 | AD26: =IF((AC26-AC25)<0,"0",(AC26-AC25)) -> 0 | AE26: =AF25 -> 0 | AG26: =IF((AF26-AF25)<0,"0",(AF26-AF25)) -> 0 | AH26: =AI25 -> 0 | AJ26: =IF((AI26-AI25)<0,"0",(AI26-AI25)) -> 0 | AK26: =AL25 -> 0 | AM26: =IF((AL26-AL25)<0,"0",(AL26-AL25)) -> 0 | AN26: =U26+X26+AA26+AD26+AG26+AJ26+AM26 -> 0
A27: =Gen!A32 -> 44249 | C27: =D26 -> 0 | E27: =IF((D27-D26)<0,"0",(D27-D26)) -> 0 | F27: =G27 -> 0 | H27: =IF((G28-G26)<0,"0",(G28-G26)) -> 0 | I27: =J26 -> 0 | L27: =M26 -> 0 | N27: =IF((M27-M26)<0,"0",(M27-M26)) -> 0 | O27: =P26 -> 0 | Q27: =IF((P27-P26)<0,"0",(P27-P26)) -> 0 | U27: =IF((T27-T26)<0,"0",(T27-T26)) -> 0 | V27: =W26 -> 0 | X27: =IF((W27-W26)<0,"0",(W27-W26)) -> 0 | Y27: =Z26 -> 0 | AA27: =IF((Z27-Z26)<0,"0",(Z27-Z26)) -> 0 | AB27: =AC26 -> 0 | AD27: =IF((AC27-AC26)<0,"0",(AC27-AC26)) -> 0 | AE27: =AF26 -> 0 | AG27: =IF((AF27-AF26)<0,"0",(AF27-AF26)) -> 0 | AH27: =AI26 -> 0 | AJ27: =IF((AI27-AI26)<0,"0",(AI27-AI26)) -> 0 | AK27: =AL26 -> 0 | AM27: =IF((AL27-AL26)<0,"0",(AL27-AL26)) -> 0 | AN27: =U27+X27+AA27+AD27+AG27+AJ27+AM27 -> 0
A28: =Gen!A33 -> 44250 | C28: =D27 -> 0 | E28: =IF((D28-D27)<0,"0",(D28-D27)) -> 0 | F28: =G28 -> 0 | H28: =IF((G28-G27)<0,"0",(G28-G27)) -> 0 | I28: =J27 -> 0 | L28: =M27 -> 0 | N28: =IF((M28-M27)<0,"0",(M28-M27)) -> 0 | O28: =P27 -> 0 | Q28: =IF((P28-P27)<0,"0",(P28-P27)) -> 0 | U28: =IF((T28-T27)<0,"0",(T28-T27)) -> 0 | V28: =W27 -> 0 | X28: =IF((W28-W27)<0,"0",(W28-W27)) -> 0 | Y28: =Z27 -> 0 | AA28: =IF((Z28-Z27)<0,"0",(Z28-Z27)) -> 0 | AB28: =AC27 -> 0 | AD28: =IF((AC28-AC27)<0,"0",(AC28-AC27)) -> 0 | AE28: =AF27 -> 0 | AG28: =IF((AF28-AF27)<0,"0",(AF28-AF27)) -> 0 | AH28: =AI27 -> 0 | AJ28: =IF((AI28-AI27)<0,"0",(AI28-AI27)) -> 0 | AK28: =AL27 -> 0 | AM28: =IF((AL28-AL27)<0,"0",(AL28-AL27)) -> 0 | AN28: =U28+X28+AA28+AD28+AG28+AJ28+AM28 -> 0
A29: =Gen!A34 -> 44251 | C29: =D28 -> 0 | E29: =IF((D29-D28)<0,"0",(D29-D28)) -> 0 | F29: =G29 -> 0 | H29: =IF((G29-G28)<0,"0",(G29-G28)) -> 0 | I29: =J28 -> 0 | L29: =M28 -> 0 | N29: =IF((M29-M28)<0,"0",(M29-M28)) -> 0 | O29: =P28 -> 0 | Q29: =IF((P29-P28)<0,"0",(P29-P28)) -> 0 | U29: =IF((T29-T28)<0,"0",(T29-T28)) -> 0 | V29: =W28 -> 0 | X29: =IF((W29-W28)<0,"0",(W29-W28)) -> 0 | Y29: =Z28 -> 0 | AA29: =IF((Z29-Z28)<0,"0",(Z29-Z28)) -> 0 | AB29: =AC28 -> 0 | AD29: =IF((AC29-AC28)<0,"0",(AC29-AC28)) -> 0 | AE29: =AF28 -> 0 | AG29: =IF((AF29-AF28)<0,"0",(AF29-AF28)) -> 0 | AH29: =AI28 -> 0 | AJ29: =IF((AI29-AI28)<0,"0",(AI29-AI28)) -> 0 | AK29: =AL28 -> 0 | AM29: =IF((AL29-AL28)<0,"0",(AL29-AL28)) -> 0 | AN29: =U29+X29+AA29+AD29+AG29+AJ29+AM29 -> 0
A30: =Gen!A35 -> 44252 | C30: =D29 -> 0 | E30: =IF((D30-D29)<0,"0",(D30-D29)) -> 0 | F30: =G30 -> 0 | H30: =IF((G30-G29)<0,"0",(G30-G29)) -> 0 | I30: =J29 -> 0 | L30: =M29 -> 0 | N30: =IF((M30-M29)<0,"0",(M30-M29)) -> 0 | O30: =P29 -> 0 | Q30: =IF((P30-P29)<0,"0",(P30-P29)) -> 0 | U30: =IF((T30-T29)<0,"0",(T30-T29)) -> 0 | V30: =W29 -> 0 | X30: =IF((W30-W29)<0,"0",(W30-W29)) -> 0 | Y30: =Z29 -> 0 | AA30: =IF((Z30-Z29)<0,"0",(Z30-Z29)) -> 0 | AB30: =AC29 -> 0 | AD30: =IF((AC30-AC29)<0,"0",(AC30-AC29)) -> 0 | AE30: =AF29 -> 0 | AG30: =IF((AF30-AF29)<0,"0",(AF30-AF29)) -> 0 | AH30: =AI29 -> 0 | AJ30: =IF((AI30-AI29)<0,"0",(AI30-AI29)) -> 0 | AK30: =AL29 -> 0 | AM30: =IF((AL30-AL29)<0,"0",(AL30-AL29)) -> 0 | AN30: =U30+X30+AA30+AD30+AG30+AJ30+AM30 -> 0
A31: =Gen!A36 -> 44253 | C31: =D30 -> 0 | E31: =IF((D31-D30)<0,"0",(D31-D30)) -> 0 | F31: =G31 -> 0 | H31: =IF((G31-G30)<0,"0",(G31-G30)) -> 0 | I31: =J30 -> 0 | K31: =IF((J31-J30)<0,"0",(J31-J30)) -> 0 | L31: =M30 -> 0 | N31: =IF((M31-M30)<0,"0",(M31-M30)) -> 0 | O31: =P30 -> 0 | Q31: =IF((P31-P30)<0,"0",(P31-P30)) -> 0 | U31: =IF((T31-T30)<0,"0",(T31-T30)) -> 0 | V31: =W30 -> 0 | X31: =IF((W31-W30)<0,"0",(W31-W30)) -> 0 | Y31: =Z30 -> 0 | AA31: =IF((Z31-Z30)<0,"0",(Z31-Z30)) -> 0 | AB31: =AC30 -> 0 | AD31: =IF((AC31-AC30)<0,"0",(AC31-AC30)) -> 0 | AE31: =AF30 -> 0 | AG31: =IF((AF31-AF30)<0,"0",(AF31-AF30)) -> 0 | AH31: =AI30 -> 0 | AJ31: =IF((AI31-AI30)<0,"0",(AI31-AI30)) -> 0 | AK31: =AL30 -> 0 | AM31: =IF((AL31-AL30)<0,"0",(AL31-AL30)) -> 0 | AN31: =U31+X31+AA31+AD31+AG31+AJ31+AM31 -> 0
A32: =Gen!A37 -> 44254 | B32: 10/27//2009 | C32: =D31 -> 0 | E32: =IF((D32-D31)<0,"0",(D32-D31)) -> 0 | F32: =G31 -> 0 | H32: =IF((G32-G31)<0,"0",(G32-G31)) -> 0 | I32: =J31 -> 0 | K32: =IF((J32-J31)<0,"0",(J32-J31)) -> 0 | L32: =M31 -> 0 | N32: =IF((M32-M31)<0,"0",(M32-M31)) -> 0 | O32: =P31 -> 0 | Q32: =IF((P32-P31)<0,"0",(P32-P31)) -> 0 | U32: =IF((T32-T31)<0,"0",(T32-T31)) -> 0 | V32: =W31 -> 0 | X32: =IF((W32-W31)<0,"0",(W32-W31)) -> 0 | Y32: =Z31 -> 0 | AA32: =IF((Z32-Z31)<0,"0",(Z32-Z31)) -> 0 | AB32: =AC31 -> 0 | AD32: =IF((AC32-AC31)<0,"0",(AC32-AC31)) -> 0 | AE32: =AF31 -> 0 | AG32: =IF((AF32-AF31)<0,"0",(AF32-AF31)) -> 0 | AH32: =AI31 -> 0 | AJ32: =IF((AI32-AI31)<0,"0",(AI32-AI31)) -> 0 | AK32: =AL31 -> 0 | AM32: =IF((AL32-AL31)<0,"0",(AL32-AL31)) -> 0 | AN32: =U32+X32+AA32+AD32+AG32+AJ32+AM32 -> 0
A33: =Gen!A38 -> 44255 | C33: =D32 -> 0 | E33: =IF((D33-D32)<0,"0",(D33-D32)) -> 0 | F33: =G32 -> 0 | H33: =IF((G33-G32)<0,"0",(G33-G32)) -> 0 | I33: =J32 -> 0 | K33: =IF((J33-J32)<0,"0",(J33-J32)) -> 0 | L33: =M32 -> 0 | N33: =IF((M33-M32)<0,"0",(M33-M32)) -> 0 | O33: =P32 -> 0 | Q33: =IF((P33-P32)<0,"0",(P33-P32)) -> 0 | U33: =IF((T33-T32)<0,"0",(T33-T32)) -> 0 | V33: =W32 -> 0 | X33: =IF((W33-W32)<0,"0",(W33-W32)) -> 0 | Y33: =Z32 -> 0 | AA33: =IF((Z33-Z32)<0,"0",(Z33-Z32)) -> 0 | AB33: =AC32 -> 0 | AD33: =IF((AC33-AC32)<0,"0",(AC33-AC32)) -> 0 | AE33: =AF32 -> 0 | AG33: =IF((AF33-AF32)<0,"0",(AF33-AF32)) -> 0 | AH33: =AI32 -> 0 | AJ33: =IF((AI33-AI32)<0,"0",(AI33-AI32)) -> 0 | AK33: =AL32 -> 0 | AM33: =IF((AL33-AL32)<0,"0",(AL33-AL32)) -> 0 | AN33: =U33+X33+AA33+AD33+AG33+AJ33+AM33 -> 0
A34: =Gen!A39 -> 0 | C34: =D33 -> 0 | E34: =IF((D34-D33)<0,"0",(D34-D33)) -> 0 | F34: =G33 -> 0 | H34: =IF((G34-G33)<0,"0",(G34-G33)) -> 0 | I34: =J33 -> 0 | K34: =IF((J34-J33)<0,"0",(J34-J33)) -> 0 | L34: =M33 -> 0 | N34: =IF((M34-M33)<0,"0",(M34-M33)) -> 0 | O34: =P33 -> 0 | Q34: =IF((P34-P33)<0,"0",(P34-P33)) -> 0 | U34: =IF((T34-T33)<0,"0",(T34-T33)) -> 0 | V34: =W33 -> 0 | X34: =IF((W34-W33)<0,"0",(W34-W33)) -> 0 | Y34: =Z33 -> 0 | AA34: =IF((Z34-Z33)<0,"0",(Z34-Z33)) -> 0 | AB34: =AC33 -> 0 | AD34: =IF((AC34-AC33)<0,"0",(AC34-AC33)) -> 0 | AE34: =AF33 -> 0 | AG34: =IF((AF34-AF33)<0,"0",(AF34-AF33)) -> 0 | AH34: =AI33 -> 0 | AJ34: =IF((AI34-AI33)<0,"0",(AI34-AI33)) -> 0 | AK34: =AL33 -> 0 | AM34: =IF((AL34-AL33)<0,"0",(AL34-AL33)) -> 0 | AN34: =U34+X34+AA34+AD34+AG34+AJ34+AM34 -> 0
A35: =Gen!A40 -> 0 | C35: =D34 -> 0 | E35: =IF((D35-D34)<0,"0",(D35-D34)) -> 0 | F35: =G34 -> 0 | H35: =IF((G35-G34)<0,"0",(G35-G34)) -> 0 | I35: =J34 -> 0 | K35: =IF((J35-J34)<0,"0",(J35-J34)) -> 0 | L35: =M34 -> 0 | N35: =IF((M35-M34)<0,"0",(M35-M34)) -> 0 | O35: =P34 -> 0 | Q35: =IF((P35-P34)<0,"0",(P35-P34)) -> 0 | S35: =T34 -> 0 | U35: =IF((T35-T34)<0,"0",(T35-T34)) -> 0 | V35: =W34 -> 0 | X35: =IF((W35-W34)<0,"0",(W35-W34)) -> 0 | Y35: =Z34 -> 0 | AA35: =IF((Z35-Z34)<0,"0",(Z35-Z34)) -> 0 | AB35: =AC34 -> 0 | AD35: =IF((AC35-AC34)<0,"0",(AC35-AC34)) -> 0 | AE35: =AF34 -> 0 | AG35: =IF((AF35-AF34)<0,"0",(AF35-AF34)) -> 0 | AH35: =AI34 -> 0 | AJ35: =IF((AI35-AI34)<0,"0",(AI35-AI34)) -> 0 | AK35: =AL34 -> 0 | AM35: =IF((AL35-AL34)<0,"0",(AL35-AL34)) -> 0 | AN35: =U35+X35+AA35+AD35+AG35+AJ35+AM35 -> 0
A36: =Gen!A41 -> 0 | C36: =D35 -> 0 | E36: =IF((D36-D35)<0,"0",(D36-D35)) -> 0 | F36: =G35 -> 0 | H36: =IF((G36-G35)<0,"0",(G36-G35)) -> 0 | I36: =J35 -> 0 | K36: =IF((J36-J35)<0,"0",(J36-J35)) -> 0 | L36: =M35 -> 0 | N36: =IF((M36-M35)<0,"0",(M36-M35)) -> 0 | O36: =P35 -> 0 | Q36: =IF((P36-P35)<0,"0",(P36-P35)) -> 0 | S36: =T35 -> 0 | U36: =IF((T36-T35)<0,"0",(T36-T35)) -> 0 | V36: =W35 -> 0 | X36: =IF((W36-W35)<0,"0",(W36-W35)) -> 0 | Y36: =Z35 -> 0 | AA36: =IF((Z36-Z35)<0,"0",(Z36-Z35)) -> 0 | AB36: =AC35 -> 0 | AD36: =IF((AC36-AC35)<0,"0",(AC36-AC35)) -> 0 | AE36: =AF35 -> 0 | AG36: =IF((AF36-AF35)<0,"0",(AF36-AF35)) -> 0 | AH36: =AI35 -> 0 | AJ36: =IF((AI36-AI35)<0,"0",(AI36-AI35)) -> 0 | AK36: =AL35 -> 0 | AM36: =IF((AL36-AL35)<0,"0",(AL36-AL35)) -> 0 | AN36: =U36+X36+AA36+AD36+AG36+AJ36+AM36 -> 0
A37: =Gen!A42 -> 0 | C37: =D36 -> 0 | E37: =IF((D37-D36)<0,"0",(D37-D36)) -> 0 | F37: =G36 -> 0 | H37: =IF((G37-G36)<0,"0",(G37-G36)) -> 0 | I37: =J36 -> 0 | K37: =IF((J37-J36)<0,"0",(J37-J36)) -> 0 | L37: =M36 -> 0 | N37: =IF((M37-M36)<0,"0",(M37-M36)) -> 0 | O37: =P36 -> 0 | Q37: =IF((P37-P36)<0,"0",(P37-P36)) -> 0 | S37: =T36 -> 0 | U37: =IF((T37-T36)<0,"0",(T37-T36)) -> 0 | V37: =W36 -> 0 | X37: =IF((W37-W36)<0,"0",(W37-W36)) -> 0 | Y37: =Z36 -> 0 | AA37: =IF((Z37-Z36)<0,"0",(Z37-Z36)) -> 0 | AB37: =AC36 -> 0 | AD37: =IF((AC37-AC36)<0,"0",(AC37-AC36)) -> 0 | AE37: =AF36 -> 0 | AG37: =IF((AF37-AF36)<0,"0",(AF37-AF36)) -> 0 | AH37: =AI36 -> 0 | AJ37: =IF((AI37-AI36)<0,"0",(AI37-AI36)) -> 0 | AK37: =AL36 -> 0 | AM37: =IF((AL37-AL36)<0,"0",(AL37-AL36)) -> 0 | AN37: =U38+X38+AA38+AD38+AG38+AJ38+AM38 -> 172
C38: TOTAL USAGE | E38: =SUM(E6:E36) -> 1002 | F38: KL | H38: =SUM(H6:H37) -> 0 | K38: =SUM(K6:K37) -> 0 | N38: =M38-M37 -> 0 | Q38: =P38-O38 -> 0 | R38: =E38 -> 1002 | U38: =SUM(U6:U37) -> 172 | AJ38: =IF((AI39-AI37)<0,"0",(AI39-AI37)) -> 0 | AN38: =U38+X38+AA38+AD38+AG38+AJ38+AM38 -> 172
C42: WATER TANK LEVEL
C43: RAW WATER TANK NO.1 | E43: RAW WATER TANK NO.2 | G43: TREATED WATER TANK | I43: TREATED -HILL TANK | K43: TOTAL WATER AVAILABLE
C44: CAPACITY 217 m³ | E44: CAPACITY 92 m³ | G44: CAPACITY 146 m³ | I44: CAPACITY 213 m³
C45: cm | D45: m³ | E45: cm | F45: m³ | H45: m³ | J45: m³ | K45: m³
A46: =Gen!A11 -> 44228 | C46: 215 | D46: =C46*217/300 -> 155.51667 | E46: 180 | F46: =E46*92/305 -> 54.295082 | G46: 300 | H46: =G46*146/383 -> 114.36031 | I46: 284 | J46: =I46*213/308 -> 196.4026 | K46: =D46+F46+H46+J46 -> 520.57466
A47: =Gen!A12 -> 44229 | C47: 300 | D47: =C47*217/300 -> 217 | E47: 295 | F47: =E47*92/305 -> 88.983607 | G47: 295 | H47: =G47*146/383 -> 112.45431 | I47: 290 | J47: =I47*213/308 -> 200.55195 | K47: =D47+F47+H47+J47 -> 618.98986
A48: =Gen!A13 -> 44230 | C48: 300 | D48: =C48*217/300 -> 217 | E48: 270 | F48: =E48*92/305 -> 81.442623 | G48: 235 | H48: =G48*146/383 -> 89.582245 | I48: 293 | J48: =I48*213/308 -> 202.62662 | K48: =D48+F48+H48+J48 -> 590.65149
A49: =Gen!A14 -> 44231 | C49: 285 | D49: =C49*217/300 -> 206.15 | E49: 275 | F49: =E49*92/305 -> 82.95082 | G49: 225 | H49: =G49*146/383 -> 85.770235 | I49: 285 | J49: =I49*213/308 -> 197.09416 | K49: =D49+F49+H49+J49 -> 571.96521
A50: =Gen!A15 -> 44232 | C50: 300 | D50: =C50*217/300 -> 217 | E50: 275 | F50: =E50*92/305 -> 82.95082 | G50: 205 | H50: =G50*146/383 -> 78.146214 | I50: 285 | J50: =I50*213/308 -> 197.09416 | K50: =D50+F50+H50+J50 -> 575.19119
A51: =Gen!A16 -> 44233 | C51: 300 | D51: =C51*217/300 -> 217 | E51: 280 | F51: =E51*92/305 -> 84.459016 | G51: 185 | H51: =G51*146/383 -> 70.522193 | I51: 289 | J51: =I51*213/308 -> 199.86039 | K51: =D51+F51+H51+J51 -> 571.8416
A52: =Gen!A17 -> 44234 | C52: 308 | D52: =C52*217/300 -> 222.78667 | E52: 275 | F52: =E52*92/305 -> 82.95082 | G52: 155 | H52: =G52*146/383 -> 59.086162 | I52: 288 | J52: =I52*213/308 -> 199.16883 | K52: =D52+F52+H52+J52 -> 563.99248
A53: =Gen!A18 -> 44235 | C53: 215 | D53: =C53*217/300 -> 155.51667 | E53: 180 | F53: =E53*92/305 -> 54.295082 | G53: 300 | H53: =G53*146/383 -> 114.36031 | I53: 295 | J53: =I53*213/308 -> 204.00974 | K53: =D53+F53+H53+J53 -> 528.1818
A54: =Gen!A19 -> 44236 | C54: 285 | D54: =C54*217/300 -> 206.15 | E54: 250 | F54: =E54*92/305 -> 75.409836 | G54: 250 | H54: =G54*146/383 -> 95.300261 | I54: 290 | J54: =I54*213/308 -> 200.55195 | K54: =D54+F54+H54+J54 -> 577.41205
A55: =Gen!A20 -> 44237 | C55: 136 | D55: =C55*217/300 -> 98.373333 | E55: 100 | F55: =E55*92/305 -> 30.163934 | G55: 300 | H55: =G55*146/383 -> 114.36031 | I55: 285 | J55: =I56*213/308 -> 200.55195 | K55: =D55+F55+H55+J55 -> 443.44953
A56: =Gen!A21 -> 44238 | C56: 185 | D56: =C56*217/300 -> 133.81667 | E56: 150 | F56: =E56*92/305 -> 45.245902 | G56: 160 | H56: =G56*146/383 -> 60.992167 | I56: 290 | J56: =I57*213/308 -> 200.55195 | K56: =D56+F56+H56+J56 -> 440.60668
A57: =Gen!A22 -> 44239 | C57: 180 | D57: =C57*217/300 -> 130.2 | E57: 145 | F57: =E57*92/305 -> 43.737705 | G57: 300 | H57: =G57*146/383 -> 114.36031 | I57: 290 | J57: =I57*213/308 -> 200.55195 | K57: =D57+F57+H57+J57 -> 488.84997
A58: =Gen!A23 -> 44240 | C58: 215 | D58: =C58*217/300 -> 155.51667 | E58: 180 | F58: =E58*92/305 -> 54.295082 | G58: 185 | H58: =G58*146/383 -> 70.522193 | I58: 280 | J58: =I58*213/308 -> 193.63636 | K58: =D58+F58+H58+J58 -> 473.97031
A59: =Gen!A24 -> 44241 | C59: 116 | D59: =C59*217/300 -> 83.906667 | E59: 80 | F59: =E59*92/305 -> 24.131148 | G59: 300 | H59: =G59*146/383 -> 114.36031 | I59: 285 | J59: =I59*213/308 -> 197.09416 | K59: =D59+F59+H59+J59 -> 419.49228
A60: =Gen!A25 -> 44242 | C60: 165 | D60: =C60*217/300 -> 119.35 | E60: 110 | F60: =E60*92/305 -> 33.180328 | G60: 270 | H60: =G60*146/383 -> 102.92428 | I60: 170 | J60: =I60*213/308 -> 117.56494 | K60: =D60+F60+H60+J60 -> 373.01954
A61: =Gen!A26 -> 44243 | C61: 180 | D61: =C61*217/300 -> 130.2 | E61: 145 | F61: =E61*92/305 -> 43.737705 | G61: 205 | H61: =G61*146/383 -> 78.146214 | I61: 275 | J61: =I61*213/308 -> 190.17857 | K61: =D61+F61+H61+J61 -> 442.26249
A62: =Gen!A27 -> 44244 | C62: 177 | D62: =C62*217/300 -> 128.03 | E62: 142 | F62: =E62*92/305 -> 42.832787 | G62: 165 | H62: =G62*146/383 -> 62.898172 | I62: 280 | J62: =I62*213/308 -> 193.63636 | K62: =D62+F62+H62+J62 -> 427.39732
A63: =Gen!A28 -> 44245 | C63: 160 | D63: =C63*217/300 -> 115.73333 | E63: 125 | F63: =E63*92/305 -> 37.704918 | G63: 127 | H63: =G63*146/383 -> 48.412533 | I63: 290 | J63: =I63*213/308 -> 200.55195 | K63: =D63+F63+H63+J63 -> 402.40273
A64: =Gen!A29 -> 44246 | C64: 191 | D64: =C64*217/300 -> 138.15667 | E64: 135 | F64: =E64*92/305 -> 40.721311 | G64: 80 | H64: =G64*146/383 -> 30.496084 | I64: 275 | J64: =I64*213/308 -> 190.17857 | K64: =D64+F64+H64+J64 -> 399.55263
A65: =Gen!A30 -> 44247 | C65: 300 | D65: =C65*217/300 -> 217 | E65: 290 | F65: =E65*92/305 -> 87.47541 | G65: 10 | H65: =G65*146/383 -> 3.8120104 | I65: 280 | J65: =I65*213/308 -> 193.63636 | K65: =D65+F65+H65+J65 -> 501.92378
A66: =Gen!A31 -> 44248 | D66: =C66*217/300 -> 0 | F66: =E66*92/305 -> 0 | H66: =G66*146/383 -> 0 | J66: =I66*213/308 -> 0 | K66: =D66+F66+H66+J66 -> 0
A67: =Gen!A32 -> 44249 | D67: =C67*217/300 -> 0 | F67: =E67*92/305 -> 0 | H67: =G67*146/383 -> 0 | J67: =I67*213/308 -> 0 | K67: =D67+F67+H67+J67 -> 0
A68: =Gen!A33 -> 44250 | D68: =C68*217/300 -> 0 | F68: =E68*92/305 -> 0 | H68: =G68*146/383 -> 0 | J68: =I68*213/308 -> 0 | K68: =D68+F68+H68+J68 -> 0
A69: =Gen!A34 -> 44251 | D69: =C69*217/300 -> 0 | F69: =E69*92/305 -> 0 | H69: =G69*146/383 -> 0 | J69: =I69*213/308 -> 0 | K69: =D69+F69+H69+J69 -> 0
A70: =Gen!A35 -> 44252 | D70: =C70*217/300 -> 0 | F70: =E70*92/305 -> 0 | H70: =G70*146/383 -> 0 | J70: =I70*213/308 -> 0 | K70: =D70+F70+H70+J70 -> 0
A71: =Gen!A36 -> 44253 | D71: =C71*217/300 -> 0 | F71: =E71*92/305 -> 0 | H71: =G71*146/383 -> 0 | J71: =I71*213/308 -> 0 | K71: =D71+F71+H71+J71 -> 0
A72: =Gen!A37 -> 44254 | D72: =C72*217/300 -> 0 | F72: =E72*92/305 -> 0 | H72: =G72*146/383 -> 0 | J72: =I72*213/308 -> 0 | K72: =D72+F72+H72+J72 -> 0
A73: =Gen!A38 -> 44255 | D73: =C73*217/300 -> 0 | F73: =E73*92/305 -> 0 | H73: =G73*146/383 -> 0 | J73: =I73*213/308 -> 0 | K73: =D73+F73+H73+J73 -> 0
A74: =Gen!A39 -> 0 | D74: =C74*217/300 -> 0 | F74: =E74*92/305 -> 0 | H74: =G74*146/383 -> 0 | J74: =I74*213/308 -> 0 | K74: =D74+F74+H74+J74 -> 0
A75: =Gen!A40 -> 0 | D75: =C75*217/300 -> 0 | F75: =E75*92/305 -> 0 | H75: =G75*146/383 -> 0 | J75: =I75*213/308 -> 0 | K75: =D75+F75+H75+J75 -> 0
A76: =Gen!A41 -> 0 | D76: =C76*217/300 -> 0 | F76: =E76*92/305 -> 0 | H76: =G76*146/383 -> 0 | J76: =I76*213/308 -> 0 | K76: =D76+F76+H76+J76 -> 0
A77: =Gen!A42 -> 0 | D77: =C77*217/300 -> 0 | F77: =E77*92/305 -> 0 | H77: =G77*146/383 -> 0 | J77: =I77*213/308 -> 0 | K77: =D77+F77+H77+J77 -> 0
A78: =Gen!A43 -> BF

Sheet Water_Graph 
A1: Date | B1: Usage | C1: Occ %
A2: =Gen!A11 -> 44228 | B2: =SUM('[1]Water-Meter'!R10) -> #REF! | C2: =SUM([1]Gen!B11) -> 0.623
A3: =Gen!A12 -> 44229 | B3: =SUM('[1]Water-Meter'!R11) -> #REF! | C3: =SUM([1]Gen!B12) -> 0.779
A4: =Gen!A13 -> 44230 | B4: =SUM('[1]Water-Meter'!R12) -> #REF! | C4: =SUM([1]Gen!B13) -> 0.532
A5: =Gen!A14 -> 44231 | B5: =SUM('[1]Water-Meter'!R13) -> #REF! | C5: =SUM([1]Gen!B14) -> 0.61
A6: =Gen!A15 -> 44232 | B6: =SUM('[1]Water-Meter'!R14) -> #REF! | C6: =SUM([1]Gen!B15) -> 0.688
A7: =Gen!A16 -> 44233 | B7: =SUM('[1]Water-Meter'!R15) -> #REF! | C7: =SUM([1]Gen!B16) -> 0.532
A8: =Gen!A17 -> 44234 | B8: =SUM('[1]Water-Meter'!R16) -> #REF! | C8: =SUM([1]Gen!B17) -> 0.753
A9: =Gen!A18 -> 44235 | B9: =SUM('[1]Water-Meter'!R17) -> #REF! | C9: =SUM([1]Gen!B18) -> 0.156
A10: =Gen!A19 -> 44236 | B10: =SUM('[1]Water-Meter'!R18) -> #REF! | C10: =SUM([1]Gen!B19) -> 0.442
A11: =Gen!A20 -> 44237 | B11: =SUM('[1]Water-Meter'!R19) -> #REF! | C11: =SUM([1]Gen!B20) -> 0.325
A12: =Gen!A21 -> 44238 | B12: =SUM('[1]Water-Meter'!R20) -> #REF! | C12: =SUM([1]Gen!B21) -> 0.455
A13: =Gen!A22 -> 44239 | B13: =SUM('[1]Water-Meter'!R21) -> #REF! | C13: =SUM([1]Gen!B22) -> 0.416
... A32: =Gen!A41 -> 0 | B32: =SUM('[1]Water-Meter'!R40) -> #REF! | C32: =SUM([1]Gen!B41) -> #REF!

Sheet Sheet1
A2: Generator and Diseal Summry Report | Q2: 2209.85 | R2: Diesel Cost | S2: Rate$ | T2: 1584
M3: % of Gas balance in Tank | P3: % of Dieasel balance in Tank | Q3: HLP Cost (TSH) | V3: Total Cost (TSH) | W3: Consumption Guest Occ% | AA3: Budget Cost Per Room occ
A4: Date | B4: Gen Set Hours Working | C4: Occ% | D4: Total OCC Room | E4: Guest Room Occ | F4: Total Kwh Generated | G4: Diseal consumed by Gen (Ltrs) | H4: Diseal consumed by Veichel (Ltrs) | I4: Total diseal consumed (Ltrs) | J4: Balance stock of Diseal (Ltrs) | K4: Water consumed | L4: Gas consumed (KG) | M4: 3 | N4: 2 | O4: 1 | Q4: Electricity | R4: Cost per Room Total OOC Usd | S4: Cost per Room Guest OOC Usd | T4: Water | U4: Gas
A5: =Gen!A11 -> 44228 | B5: 0 | C5: =Gen!B11 -> 0.091 | D5: =SUM(77*C5) -> 7.007 | F5: =Gen!U11 -> 0.41609085 | G5: =Gen!T11 -> 2906 | H5: =[1]Gen!#REF! -> #REF! | I5: =SUM(G5:H5) -> #REF! | J5: =[1]Gen!AT11 -> 47806.65 | K5: ='Water-Meter'!E6 -> 58 | L5: ='Lpg (2)'!G10 -> 74734.36 | M5: =#REF! -> #REF! | N5: =#REF! -> #REF! | O5: =#REF! -> #REF! | P5: =J5/52000 -> 0.91935865 | Q5: =I5*Q2 -> #REF! | R5: =SUM(Q5/D5)/X5 -> #REF! | S5: =SUM(Q5/E5)/X5 -> #REF! | T5: =(K5*102)/X5 -> 3.7348485 | U5: =SUM(L5*1963)/X5 -> 92615.877 | V5: =SUM(Q5+T5+U5) -> #REF! | W5: =SUM(V5/E5)/T2 -> #REF! | X5: =SUM(T2) -> 1584 | Y5: 106 | Z5: =SUM(Y5-S5) -> #REF! | AA5: 106
A6: =Gen!A12 -> 44229 | B6: 0 | C6: =Gen!B12 -> 0.065 | D6: =SUM(77*C6) -> 5.005 | F6: =Gen!U12 -> 0.41187785 | G6: =Gen!T12 -> 2849 | H6: =[1]Gen!#REF! -> #REF! | I6: =SUM(G6:H6) -> #REF! | J6: =[1]Gen!AT12 -> 45423.89 | K6: ='Water-Meter'!E7 -> 56 | L6: ='Lpg (2)'!G11 -> 74755.84 | M6: =#REF! -> #REF! | N6: =#REF! -> #REF! | O6: =#REF! -> #REF! | P6: =J6/52000 -> 0.87353635 | Q6: =I6*Q2 -> #REF! | R6: =SUM(Q6/D6)/X6 -> #REF! | S6: =SUM(Q6/E6)/X6 -> #REF! | T6: =(K6*102)/X6 -> 3.6060606 | U6: =SUM(L6*1963)/X6 -> 92642.496 | V6: =SUM(Q6+T6+U6) -> #REF! | W6: =SUM(V6/E6)/T2 -> #REF! | X6: =SUM(X5) -> 1584 | Y6: 106 | Z6: =SUM(Y6-S6) -> #REF!
A7: =Gen!A13 -> 44230 | B7: 0 | C7: =Gen!B13 -> 0.039 | D7: =SUM(77*C7) -> 3.003 | F7: =Gen!U13 -> 0.42344748 | G7: =Gen!T13 -> 2599 | H7: =[1]Gen!#REF! -> #REF! | I7: =SUM(G7:H7) -> #REF! | J7: =[1]Gen!AT13 -> 42919.59 | K7: ='Water-Meter'!E8 -> 46 | L7: ='Lpg (2)'!G12 -> 74775.21 | M7: =#REF! -> #REF! | N7: =#REF! -> #REF! | O7: =#REF! -> #REF! | P7: =J7/52000 -> 0.82537673 | Q7: =I7*Q2 -> #REF! | R7: =SUM(Q7/D7)/X7 -> #REF! | S7: =SUM(Q7/E7)/X7 -> #REF! | T7: =(K7*102)/X7 -> 2.9621212 | U7: =SUM(L7*1963)/X7 -> 92666.501 | V7: =SUM(Q7+T7+U7) -> #REF! | W7: =SUM(V7/E7)/T2 -> #REF! | X7: =SUM(X6) -> 1584 | Y7: 106 | Z7: =SUM(Y7-S7) -> #REF!
A8: =Gen!A14 -> 44231 | B8: 0 | C8: =Gen!B14 -> 0.039 | D8: =SUM(77*C8) -> 3.003 | F8: =Gen!U14 -> 0.40830287 | G8: =Gen!T14 -> 2681 | H8: =[1]Gen!AJ9 -> #REF! | I8: =SUM(G8:H8) -> #REF! | J8: =[1]Gen!AT14 -> 40258.94 | K8: ='Water-Meter'!E9 -> 52 | L8: ='Lpg (2)'!G13 -> 74796.53 | M8: =#REF! -> #REF! | N8: =#REF! -> #REF! | O8: =#REF! -> #REF! | P8: =J8/52000 -> 0.77421038 | Q8: =I8*Q2 -> #REF! | R8: =SUM(Q8/D8)/X8 -> #REF! | S8: =SUM(Q8/E8)/X8 -> #REF! | T8: =(K8*102)/X8 -> 3.3484848 | U8: =SUM(L8*1963)/X8 -> 92692.922 | V8: =SUM(Q8+T8+U8) -> #REF! | W8: =SUM(V8/E8)/T2 -> #REF! | X8: =SUM(X7) -> 1584 | Y8: 106 | Z8: =SUM(Y8-S8) -> #REF!
A9: =Gen!A15 -> 44232 | B9: 0 | C9: =Gen!B15 -> 0.0519 | D9: =SUM(77*C9) -> 3.9963 | F9: =Gen!U15 -> 0.4168883 | G9: =Gen!T15 -> 3008 | H9: =[1]Gen!AJ10 -> 0 | I9: =SUM(G9:H9) -> 3008 | J9: =[1]Gen!AT15 -> 37525.21 | K9: ='Water-Meter'!E10 -> 45 | L9: ='Lpg (2)'!G14 -> 74818 | M9: =#REF! -> #REF! | N9: =#REF! -> #REF! | O9: =#REF! -> #REF! | P9: =J9/52000 -> 0.72163865 | Q9: =I9*Q2 -> 6647228.8 | R9: =SUM(Q9/D9)/X9 -> 1050.092 | S9: =SUM(Q9/E9)/X9 -> #DIV/0! | T9: =(K9*102)/X9 -> 2.8977273 | U9: =SUM(L9*1963)/X9 -> 92719.529 | V9: =SUM(Q9+T9+U9) -> 6739951.2 | W9: =SUM(V9/E9)/T2 -> #DIV/0! | X9: =SUM(X8) -> 1584 | Y9: 106 | Z9: =SUM(Y9-S9) -> #DIV/0!
A10: =Gen!A16 -> 44233 | B10: 0 | C10: =Gen!B16 -> 0.0779 | D10: =SUM(77*C10) -> 5.9983 | F10: =Gen!U16 -> 0.40222175 | G10: =Gen!T16 -> 2354 | H10: =[1]Gen!#REF! -> #REF! | I10: =SUM(G10:H10) -> #REF! | J10: =[1]Gen!AT16 -> 35107.69 | K10: ='Water-Meter'!E11 -> 45 | L10: ='Lpg (2)'!G15 -> 74828.57 | M10: =#REF! -> #REF! | N10: =#REF! -> #REF! | O10: =#REF! -> #REF! | P10: =J10/52000 -> 0.67514788 | Q10: =I10*Q2 -> #REF! | R10: =SUM(Q10/D10)/X10 -> #REF! | S10: =SUM(Q10/E10)/X10 -> #REF! | T10: =(K10*102)/X10 -> 2.8977273 | U10: =SUM(L10*1963)/X10 -> 92732.628 | V10: =SUM(Q10+T10+U10) -> #REF! | W10: =SUM(V10/E10)/T2 -> #REF! | X10: =SUM(X9) -> 1584 | Y10: 106 | Z10: =SUM(Y10-S10) -> #REF!
A11: =Gen!A17 -> 44234 | B11: 0 | C11: =Gen!B17 -> 0.0779 | D11: =SUM(77*C11) -> 5.9983 | F11: =Gen!U17 -> 0.4110036 | G11: =Gen!T17 -> 2780 | H11: =[1]Gen!AJ25 -> 80.56 | I11: =SUM(G11:H11) -> 2860.56 | J11: =[1]Gen!AT17 -> 47513.14 | K11: ='Water-Meter'!E12 -> 58 | L11: ='Lpg (2)'!G16 -> 74845.13 | M11: =#REF! -> #REF! | N11: =#REF! -> #REF! | O11: =#REF! -> #REF! | P11: =J11/52000 -> 0.91371423 | Q11: =I11*Q2 -> 6321408.5 | R11: =SUM(Q11/D11)/X11 -> 665.31987 | S11: =SUM(Q11/E11)/X11 -> #DIV/0! | T11: =(K11*102)/X11 -> 3.7348485 | U11: =SUM(L11*1963)/X11 -> 92753.15 | V11: =SUM(Q11+T11+U11) -> 6414165.4 | W11: =SUM(V11/E11)/T2 -> #DIV/0! | X11: =SUM(X10) -> 1584 | Y11: 106 | Z11: =SUM(Y11-S11) -> #DIV/0!
A12: =Gen!A18 -> 44235 | B12: 0 | C12: =Gen!B18 -> 0.0519 | D12: =SUM(77*C12) -> 3.9963 | F12: =Gen!U18 -> 0.41171316 | G12: =Gen!T18 -> 2545 | H12: =[1]Gen!#REF! -> #REF! | I12: =SUM(G12:H12) -> #REF! | J12: =[1]Gen!AT18 -> 45161.89 | K12: ='Water-Meter'!E13 -> 45 | L12: ='Lpg (2)'!G17 -> 74862.53 | M12: =#REF! -> #REF! | N12: =#REF! -> #REF! | O12: =#REF! -> #REF! | P12: =J12/52000 -> 0.86849788 | Q12: =I12*Q2 -> #REF! | R12: =SUM(Q12/D12)/X12 -> #REF! | S12: =SUM(Q12/E12)/X12 -> #REF! | T12: =(K12*102)/X12 -> 2.8977273 | U12: =SUM(L12*1963)/X12 -> 92774.714 | V12: =SUM(Q12+T12+U12) -> #REF! | W12: =SUM(V12/E12)/T2 -> #REF! | X12: =SUM(X11) -> 1584 | Y12: 106 | Z12: =SUM(Y12-S12) -> #REF!
A13: =Gen!A19 -> 44236 | B13: 0 | C13: =Gen!B19 -> 0.1039 | D13: =SUM(77*C13) -> 8.0003 | F13: =Gen!U19 -> 0.42860912 | G13: =Gen!T19 -> 2653 | H13: =[1]Gen!#REF! -> #REF! | I13: =SUM(G13:H13) -> #REF! | J13: =[1]Gen!AT19 -> 42825.48 | K13: ='Water-Meter'!E14 -> 60 | L13: ='Lpg (2)'!G18 -> 74882.6 | M13: =#REF! -> #REF! | N13: =#REF! -> #REF! | O13: =#REF! -> #REF! | P13: =J13/52000 -> 0.82356692 | Q13: =I13*Q2 -> #REF! | R13: =SUM(Q13/D13)/X13 -> #REF! | S13: =SUM(Q13/E13)/X13 -> #REF! | T13: =(K13*102)/X13 -> 3.8636364 | U13: =SUM(L13*1963)/X13 -> 92799.586 | V13: =SUM(Q13+T13+U13) -> #REF! | W13: =SUM(V13/E13)/T2 -> #REF! | X13: =SUM(X12) -> 1584 | Y13: 106 | Z13: =SUM(Y13-S13) -> #REF!
A14: =Gen!A20 -> 44237 | B14: 0 | C14: =Gen!B20 -> 0.1039 | D14: =SUM(77*C14) -> 8.0003 | F14: =Gen!U20 -> 0.42092659 | G14: =Gen!T20 -> 2493 | H14: =[1]Gen!#REF! -> #REF! | I14: =SUM(G14:H14) -> #REF! | J14: =[1]Gen!AT20 -> 40110.38 | K14: ='Water-Meter'!E15 -> 57 | L14: ='Lpg (2)'!G19 -> 74901.7 | M14: =#REF! -> #REF! | N14: =#REF! -> #REF! | O14: =#REF! -> #REF! | P14: =J14/52000 -> 0.77135346 | Q14: =I14*Q2 -> #REF! | R14: =SUM(Q14/D14)/X14 -> #REF! | S14: =SUM(Q14/E14)/X14 -> #REF! | T14: =(K14*102)/X14 -> 3.6704545 | U14: =SUM(L14*1963)/X14 -> 92823.256 | V14: =SUM(Q14+T14+U14) -> #REF! | W14: =SUM(V14/E14)/T2 -> #REF! | X14: =SUM(X13) -> 1584 | Y14: 106 | Z14: =SUM(Y14-S14) -> #REF!
A15: =Gen!A21 -> 44238 | B15: 0 | C15: =Gen!B21 -> 0.1169 | D15: =SUM(77*C15) -> 9.0013 | F15: =Gen!U21 -> 0.41895174 | G15: =Gen!T21 -> 2528 | H15: =[1]Gen!#REF! -> #REF! | I15: =SUM(G15:H15) -> #REF! | J15: =[1]Gen!AT21 -> 37540.57 | K15: ='Water-Meter'!E16 -> 49 | L15: ='Lpg (2)'!G20 -> 74919.52 | M15: =#REF! -> #REF! | N15: =#REF! -> #REF! | O15: =#REF! -> #REF! | P15: =J15/52000 -> 0.72193404 | Q15: =I15*Q2 -> #REF! | R15: =SUM(Q15/D15)/X15 -> #REF! | S15: =SUM(Q15/E15)/X15 -> #REF! | T15: =(K15*102)/X15 -> 3.155303 | U15: =SUM(L15*1963)/X15 -> 92845.339 | V15: =SUM(Q15+T15+U15) -> #REF! | W15: =SUM(V15/E15)/T2 -> #REF! | X15: =SUM(X14) -> 1584 | Y15: 106 | Z15: =SUM(Y15-S15) -> #REF!
A16: =Gen!A22 -> 44239 | B16: 0 | C16: =Gen!B22 -> 0.2338 | D16: =SUM(77*C16) -> 18.0026 | F16: =Gen!U22 -> 0.41330004 | G16: =Gen!T22 -> 2703 | H16: =[1]Gen!#REF! -> #REF! | I16: =SUM(G16:H16) -> #REF! | J16: =[1]Gen!AT22 -> 34967.29 | K16: ='Water-Meter'!E17 -> 52 | L16: ='Lpg (2)'!G21 -> 74960.75 | M16: =#REF! -> #REF! | N16: =#REF! -> #REF! | O16: =#REF! -> #REF! | P16: =J16/52000 -> 0.67244788 | Q16: =I16*Q2 -> #REF! | R16: =SUM(Q16/D16)/X16 -> #REF! | S16: =SUM(Q16/E16)/X16 -> #REF! | T16: =(K16*102)/X16 -> 3.3484848 | U16: =SUM(L16*1963)/X16 -> 92896.435 | V16: =SUM(Q16+T16+U16) -> #REF! | W16: =SUM(V16/E16)/T2 -> #REF! | X16: =SUM(X15) -> 1584 | Y16: 106 | Z16: =SUM(Y16-S16) -> #REF!
A17: =Gen!A23 -> 44240 | B17: 0 | C17: =Gen!B23 -> 0.2208 | D17: =SUM(77*C17) -> 17.0016 | F17: =Gen!U23 -> 0.42059108 | G17: =Gen!T23 -> 2690 | H17: =[1]Gen!#REF! -> #REF! | I17: =SUM(G17:H17) -> #REF! | J17: =[1]Gen!AT23 -> 32228.76 | K17: ='Water-Meter'!E18 -> 58 | L17: ='Lpg (2)'!G22 -> 74975 | M17: =#REF! -> #REF! | N17: =#REF! -> #REF! | O17: =#REF! -> #REF! | P17: =J17/52000 -> 0.61978385 | Q17: =I17*Q2 -> #REF! | R17: =SUM(Q17/D17)/X17 -> #REF! | S17: =SUM(Q17/E17)/X17 -> #REF! | T17: =(K17*102)/X17 -> 3.7348485 | U17: =SUM(L17*1963)/X17 -> 92914.094 | V17: =SUM(Q17+T17+U17) -> #REF! | W17: =SUM(V17/E17)/T2 -> #REF! | X17: =SUM(X16) -> 1584 | Y17: 106 | Z17: =SUM(Y17-S17) -> #REF!
A18: =Gen!A24 -> 44241 | B18: 0 | C18: =Gen!B24 -> 0.1948 | D18: =SUM(77*C18) -> 14.9996 | F18: =Gen!U24 -> 0.42069955 | G18: =Gen!T24 -> 2859 | H18: =[1]Gen!AJ27 -> 597.9 | I18: =SUM(G18:H18) -> 3456.9 | J18: =[1]Gen!AT24 -> 29915.45 | K18: ='Water-Meter'!E19 -> 54 | L18: ='Lpg (2)'!G23 -> 74968 | M18: =#REF! -> #REF! | N18: =#REF! -> #REF! | O18: =#REF! -> #REF! | P18: =J18/52000 -> 0.57529712 | Q18: =I18*Q2 -> 7639230.5 | R18: =SUM(Q18/D18)/X18 -> 321.52501 | S18: =SUM(Q18/E18)/X18 -> #DIV/0! | T18: =(K18*102)/X18 -> 3.4772727 | U18: =SUM(L18*1963)/X18 -> 92905.419 | V18: =SUM(Q18+T18+U18) -> 7732139.4 | W18: =SUM(V18/E18)/T2 -> #DIV/0! | X18: =SUM(X17) -> 1584 | Y18: 106 | Z18: =SUM(Y18-S18) -> #DIV/0!
A19: =Gen!A25 -> 44242 | B19: 0 | C19: =Gen!B25 -> 0.1299 | D19: =SUM(77*C19) -> 10.0023 | F19: =Gen!U25 -> 0.41529021 | G19: =Gen!T25 -> 2860 | H19: =[1]Gen!AJ28 -> 227.73 | I19: =SUM(G19:H19) -> 3087.73 | J19: =[1]Gen!AT25 -> 42248.24 | K19: ='Water-Meter'!E20 -> 56 | L19: ='Lpg (2)'!G24 -> 74980 | M19: =#REF! -> #REF! | N19: =#REF! -> #REF! | O19: =#REF! -> #REF! | P19: =J19/52000 -> 0.81246615 | Q19: =I19*Q2 -> 6823420.1 | R19: =SUM(Q19/D19)/X19 -> 430.67242 | S19: =SUM(Q19/E19)/X19 -> #DIV/0! | T19: =(K19*102)/X19 -> 3.6060606 | U19: =SUM(L19*1963)/X19 -> 92920.29 | V19: =SUM(Q19+T19+U19) -> 6916344 | W19: =SUM(V19/E19)/T2 -> #DIV/0! | X19: =SUM(X18) -> 1584 | Y19: 106 | Z19: =SUM(Y19-S19) -> #DIV/0!
A20: =Gen!A26 -> 44243 | B20: 0 | C20: =Gen!B26 -> 0.0909 | D20: =SUM(77*C20) -> 6.9993 | F20: =Gen!U26 -> 0.41954097 | G20: =Gen!T26 -> 2636 | H20: =[1]Gen!AJ29 -> 88.29 | I20: =SUM(G20:H20) -> 2724.29 | J20: =[1]Gen!AT26 -> 39497.37 | K20: ='Water-Meter'!E21 -> 45 | L20: ='Lpg (2)'!G25 -> 74998 | M20: =#REF! -> #REF! | N20: =#REF! -> #REF! | O20: =#REF! -> #REF! | P20: =J20/52000 -> 0.75956481 | Q20: =I20*Q2 -> 6020272.3 | R20: =SUM(Q20/D20)/X20 -> 543.00815 | S20: =SUM(Q20/E20)/X20 -> #DIV/0! | T20: =(K20*102)/X20 -> 2.8977273 | U20: =SUM(L20*1963)/X20 -> 92942.597 | V20: =SUM(Q20+T20+U20) -> 6113217.8 | W20: =SUM(V20/E20)/T2 -> #DIV/0! | X20: =SUM(X19) -> 1584 | Y20: 106 | Z20: =SUM(Y20-S20) -> #DIV/0!
A21: =Gen!A27 -> 44244 | B21: 0 | C21: =Gen!B27 -> 0.1169 | D21: =SUM(77*C21) -> 9.0013 | F21: =Gen!U27 -> 0.40314794 | G21: =Gen!T27 -> 2643 | H21: =[1]Gen!AJ30 -> 783.92 | I21: =SUM(G21:H21) -> 3426.92 | J21: =[1]Gen!AT27 -> 36688.35 | K21: ='Water-Meter'!E22 -> 48 | L21: ='Lpg (2)'!G26 -> 75012 | M21: =#REF! -> #REF! | N21: =#REF! -> #REF! | O21: =#REF! -> #REF! | P21: =J21/52000 -> 0.70554519 | Q21: =I21*Q2 -> 7572979.2 | R21: =SUM(Q21/D21)/X21 -> 531.13675 | S21: =SUM(Q21/E21)/X21 -> #DIV/0! | T21: =(K21*102)/X21 -> 3.0909091 | U21: =SUM(L21*1963)/X21 -> 92959.947 | V21: =SUM(Q21+T21+U21) -> 7665942.2 | W21: =SUM(V21/E21)/T2 -> #DIV/0! | X21: =SUM(X20) -> 1584 | Y21: 106 | Z21: =SUM(Y21-S21) -> #DIV/0!
A22: =Gen!A28 -> 44245 | B22: 0 | C22: =Gen!B28 -> 0.1169 | D22: =SUM(77*C22) -> 9.0013 | F22: =Gen!U28 -> 0.38842198 | G22: =Gen!T28 -> 2839 | H22: =[1]Gen!#REF! -> #REF! | I22: =SUM(G22:H22) -> #REF! | J22: =[1]Gen!AT28 -> 33769.34 | K22: ='Water-Meter'!E23 -> 53 | L22: ='Lpg (2)'!G27 -> 75027 | M22: =#REF! -> #REF! | N22: =#REF! -> #REF! | O22: =#REF! -> #REF! | P22: =J22/52000 -> 0.64941038 | Q22: =I22*Q2 -> #REF! | R22: =SUM(Q22/D22)/X22 -> #REF! | S22: =SUM(Q22/E22)/X22 -> #REF! | T22: =(K22*102)/X22 -> 3.4128788 | U22: =SUM(L22*1963)/X22 -> 92978.536 | V22: =SUM(Q22+T22+U22) -> #REF! | W22: =SUM(V22/E22)/T2 -> #REF! | X22: =SUM(X21) -> 1584 | Y22: 106 | Z22: =SUM(Y22-S22) -> #REF!
A23: =Gen!A29 -> 44246 | B23: 0 | C23: =Gen!B29 -> 0.1558 | D23: =SUM(77*C23) -> 11.9966 | F23: =Gen!U29 -> 0.41286096 | G23: =Gen!T29 -> 2992 | H23: =[1]Gen!#REF! -> #REF! | I23: =SUM(G23:H23) -> #REF! | J23: =[1]Gen!AT29 -> 31336.77 | K23: ='Water-Meter'!E24 -> 65 | L23: ='Lpg (2)'!G28 -> 75047.38 | M23: =#REF! -> #REF! | N23: =#REF! -> #REF! | O23: =#REF! -> #REF! | P23: =J23/52000 -> 0.60263019 | Q23: =I23*Q2 -> #REF! | R23: =SUM(Q23/D23)/X23 -> #REF! | S23: =SUM(Q23/E23)/X23 -> #REF! | T23: =(K23*102)/X23 -> 4.1856061 | U23: =SUM(L23*1963)/X23 -> 93003.792 | V23: =SUM(Q23+T23+U23) -> #REF! | W23: =SUM(V23/E23)/T2 -> #REF! | X23: =SUM(X22) -> 1584 | Y23: 106 | Z23: =SUM(Y23-S23) -> #REF!
A24: =Gen!A30 -> 44247 | B24: 0 | C24: =Gen!B30 -> 0.1429 | D24: =SUM(77*C24) -> 11.0033 | F24: =Gen!U30 -> #DIV/0! | G24: =Gen!T30 -> 0 | H24: =[1]Gen!#REF! -> #REF! | I24: =SUM(G24:H24) -> #REF! | J24: =[1]Gen!AT30 -> 29403.3 | K24: ='Water-Meter'!E25 -> 0 | L24: ='Lpg (2)'!G29 -> 75065.86 | M24: =#REF! -> #REF! | N24: =#REF! -> #REF! | O24: =#REF! -> #REF! | P24: =J24/52000 -> 0.56544808 | Q24: =I24*Q2 -> #REF! | R24: =SUM(Q24/D24)/X24 -> #REF! | S24: =SUM(Q24/E24)/X24 -> #REF! | T24: =(K24*102)/X24 -> 0 | U24: =SUM(L24*1963)/X24 -> 93026.694 | V24: =SUM(Q24+T24+U24) -> #REF! | W24: =SUM(V24/E24)/T2 -> #REF! | X24: =SUM(X23) -> 1584 | Y24: 106 | Z24: =SUM(Y24-S24) -> #REF!
A25: =Gen!A31 -> 44248 | B25: 0 | C25: =Gen!B31 -> 0 | D25: =SUM(77*C25) -> 0 | F25: =Gen!U31 -> #DIV/0! | G25: =Gen!T31 -> 0 | H25: =[1]Gen!AJ31 -> 172.05 | I25: =SUM(G25:H25) -> 172.05 | J25: =[1]Gen!AT31 -> 41422.37 | K25: ='Water-Meter'!E26 -> 0 | L25: ='Lpg (2)'!G30 -> 0 | M25: =#REF! -> #REF! | N25: =#REF! -> #REF! | O25: =#REF! -> #REF! | P25: =J25/52000 -> 0.79658404 | Q25: =I25*Q2 -> 380204.69 | R25: =SUM(Q25/D25)/X25 -> #DIV/0! | S25: =SUM(Q25/E25)/X25 -> #DIV/0! | T25: =(K25*102)/X25 -> 0 | U25: =SUM(L25*1963)/X25 -> 0 | V25: =SUM(Q25+T25+U25) -> 380204.69 | W25: =SUM(V25/E25)/T2 -> #DIV/0! | X25: =SUM(X24) -> 1584 | Y25: 106 | Z25: =SUM(Y25-S25) -> #DIV/0!
A26: =Gen!A32 -> 44249 | B26: 0 | C26: =Gen!B32 -> 0 | D26: =SUM(77*C26) -> 0 | F26: =Gen!U32 -> #DIV/0! | G26: =Gen!T32 -> 0 | H26: =[1]Gen!AJ32 -> 18.63 | I26: =SUM(G26:H26) -> 18.63 | J26: =[1]Gen!AT32 -> 38988.16 | K26: ='Water-Meter'!E27 -> 0 | L26: ='Lpg (2)'!G31 -> 0 | M26: =#REF! -> #REF! | N26: =#REF! -> #REF! | O26: =#REF! -> #REF! | P26: =J26/52000 -> 0.74977231 | Q26: =I26*Q2 -> 41169.505 | R26: =SUM(Q26/D26)/X26 -> #DIV/0! | S26: =SUM(Q26/E26)/X26 -> #DIV/0! | T26: =(K26*102)/X26 -> 0 | U26: =SUM(L26*1963)/X26 -> 0 | V26: =SUM(Q26+T26+U26) -> 41169.505 | W26: =SUM(V26/E26)/T2 -> #DIV/0! | X26: =SUM(X25) -> 1584 | Y26: 106 | Z26: =SUM(Y26-S26) -> #DIV/0!
A27: =Gen!A33 -> 44250 | B27: 0 | C27: =Gen!B33 -> 0 | D27: =SUM(77*C27) -> 0 | F27: =Gen!U33 -> #DIV/0! | G27: =Gen!T33 -> 0 | H27: =[1]Gen!AJ33 -> 311.34 | I27: =SUM(G27:H27) -> 311.34 | J27: =[1]Gen!AT33 -> 36682.67 | K27: ='Water-Meter'!E28 -> 0 | L27: ='Lpg (2)'!G32 -> 0 | M27: =#REF! -> #REF! | N27: =#REF! -> #REF! | O27: =#REF! -> #REF! | P27: =J27/52000 -> 0.70543596 | Q27: =I27*Q2 -> 688014.7 | R27: =SUM(Q27/D27)/X27 -> #DIV/0! | S27: =SUM(Q27/E27)/X27 -> #DIV/0! | T27: =(K27*102)/X27 -> 0 | U27: =SUM(L27*1963)/X27 -> 0 | V27: =SUM(Q27+T27+U27) -> 688014.7 | W27: =SUM(V27/E27)/T2 -> #DIV/0! | X27: =SUM(X26) -> 1584 | Y27: 106 | Z27: =SUM(Y27-S27) -> #DIV/0!
A28: =Gen!A34 -> 44251 | B28: 0 | C28: =Gen!B34 -> 0 | D28: =SUM(77*C28) -> 0 | F28: =Gen!U34 -> #DIV/0! | G28: =Gen!T34 -> 0 | H28: =[1]Gen!AJ34 -> 380.7 | I28: =SUM(G28:H28) -> 380.7 | J28: =[1]Gen!AT34 -> 44223.03 | K28: ='Water-Meter'!E29 -> 0 | L28: ='Lpg (2)'!G33 -> 0 | M28: =#REF! -> #REF! | N28: =#REF! -> #REF! | O28: =#REF! -> #REF! | P28: =J28/52000 -> 0.85044288 | Q28: =I28*Q2 -> 841289.89 | R28: =SUM(Q28/D28)/X28 -> #DIV/0! | S28: =SUM(Q28/E28)/X28 -> #DIV/0! | T28: =(K28*102)/X28 -> 0 | U28: =SUM(L28*1963)/X28 -> 0 | V28: =SUM(Q28+T28+U28) -> 841289.89 | W28: =SUM(V28/E28)/T2 -> #DIV/0! | X28: =SUM(X27) -> 1584 | Y28: 106 | Z28: =SUM(Y28-S28) -> #DIV/0!
A29: =Gen!A35 -> 44252 | B29: 0 | C29: =Gen!B35 -> 0 | D29: =SUM(77*C29) -> 0 | F29: =Gen!U35 -> #DIV/0! | G29: =Gen!T35 -> 0 | H29: =[1]Gen!AJ35 -> 273.37 | I29: =SUM(G29:H29) -> 273.37 | J29: =[1]Gen!AT35 -> 41629.06 | K29: ='Water-Meter'!E30 -> 0 | L29: ='Lpg (2)'!G34 -> 0 | M29: =#REF! -> #REF! | N29: =#REF! -> #REF! | O29: =#REF! -> #REF! | P29: =J29/52000 -> 0.80055885 | Q29: =I29*Q2 -> 604106.69 | R29: =SUM(Q29/D29)/X29 -> #DIV/0! | S29: =SUM(Q29/E29)/X29 -> #DIV/0! | T29: =(K29*102)/X29 -> 0 | U29: =SUM(L29*1963)/X29 -> 0 | V29: =SUM(Q29+T29+U29) -> 604106.69 | W29: =SUM(V29/E29)/T2 -> #DIV/0! | X29: =SUM(X28) -> 1584 | Y29: 106 | Z29: =SUM(Y29-S29) -> #DIV/0!
A30: =Gen!A36 -> 44253 | B30: 0 | C30: =Gen!B36 -> 0 | D30: =SUM(77*C30) -> 0 | F30: =Gen!U36 -> #DIV/0! | G30: =Gen!T36 -> 0 | H30: =[1]Gen!AJ36 -> 396.56 | I30: =SUM(G30:H30) -> 396.56 | J30: =[1]Gen!AT36 -> 39251.17 | K30: ='Water-Meter'!E31 -> 0 | L30: ='Lpg (2)'!G35 -> 0 | M30: =#REF! -> #REF! | N30: =#REF! -> #REF! | O30: =#REF! -> #REF! | P30: =J30/52000 -> 0.75483019 | Q30: =I30*Q2 -> 876338.12 | R30: =SUM(Q30/D30)/X30 -> #DIV/0! | S30: =SUM(Q30/E30)/X30 -> #DIV/0! | T30: =(K30*102)/X30 -> 0 | U30: =SUM(L30*1963)/X30 -> 0 | V30: =SUM(Q30+T30+U30) -> 876338.12 | W30: =SUM(V30/E30)/T2 -> #DIV/0! | X30: =SUM(X29) -> 1584 | Y30: 106 | Z30: =SUM(Y30-S30) -> #DIV/0!
A31: =Gen!A37 -> 44254 | B31: 0 | C31: =Gen!B37 -> 0 | D31: =SUM(77*C31) -> 0 | F31: =Gen!U37 -> #DIV/0! | G31: =Gen!T37 -> 0 | H31: =[1]Gen!AJ37 -> 280.63 | I31: =SUM(G31:H31) -> 280.63 | J31: =[1]Gen!AT37 -> 36384.37 | K31: ='Water-Meter'!E32 -> 0 | L31: ='Lpg (2)'!G36 -> 0 | M31: =#REF! -> #REF! | N31: =#REF! -> #REF! | O31: =#REF! -> #REF! | P31: =J31/52000 -> 0.69969942 | Q31: =I31*Q2 -> 620150.21 | R31: =SUM(Q31/D31)/X31 -> #DIV/0! | S31: =SUM(Q31/E31)/X31 -> #DIV/0! | T31: =(K31*102)/X31 -> 0 | U31: =SUM(L31*1963)/X31 -> 0 | V31: =SUM(Q31+T31+U31) -> 620150.21 | W31: =SUM(V31/E31)/T2 -> #DIV/0! | X31: =SUM(X30) -> 1584 | Y31: 106 | Z31: =SUM(Y31-S31) -> #DIV/0!
A32: =Gen!A38 -> 44255 | B32: 0 | C32: =Gen!B38 -> 0 | D32: =SUM(77*C32) -> 0 | F32: =Gen!U38 -> #DIV/0! | G32: =Gen!T38 -> 0 | H32: =[1]Gen!AJ38 -> 0 | I32: =SUM(G32:H32) -> 0 | J32: =[1]Gen!AT38 -> 33780 | K32: ='Water-Meter'!E33 -> 0 | L32: ='Lpg (2)'!G37 -> 0 | M32: =#REF! -> #REF! | N32: =#REF! -> #REF! | O32: =#REF! -> #REF! | P32: =J32/52000 -> 0.64961538 | Q32: =I32*Q2 -> 0 | R32: =SUM(Q32/D32)/X32 -> #DIV/0! | S32: =SUM(Q32/E32)/X32 -> #DIV/0! | T32: =(K32*102)/X32 -> 0 | U32: =SUM(L32*1963)/X32 -> 0 | V32: =SUM(Q32+T32+U32) -> 0 | W32: =SUM(V32/E32)/T2 -> #DIV/0! | X32: =SUM(X31) -> 1584 | Y32: 106 | Z32: =SUM(Y32-S32) -> #DIV/0!
A33: =Gen!A39 -> 0 | B33: 0 | C33: =Gen!B39 -> 0 | D33: =SUM(77*C33) -> 0 | F33: =Gen!U39 -> #DIV/0! | G33: =Gen!T39 -> 0 | H33: =[1]Gen!AJ39 -> 0 | I33: =SUM(G33:H33) -> 0 | J33: =[1]Gen!AT39 -> 33780 | K33: ='Water-Meter'!E34 -> 0 | L33: ='Lpg (2)'!G38 -> 0 | M33: =#REF! -> #REF! | N33: =#REF! -> #REF! | O33: =#REF! -> #REF! | P33: =J33/52000 -> 0.64961538 | Q33: =I33*Q2 -> 0 | R33: =SUM(Q33/D33)/X33 -> #DIV/0! | S33: =SUM(Q33/E33)/X33 -> #DIV/0! | T33: =(K33*102)/X33 -> 0 | U33: =SUM(L33*1963)/X33 -> 0 | V33: =SUM(Q33+T33+U33) -> 0 | W33: =SUM(V33/E33)/T2 -> #DIV/0! | X33: =SUM(X32) -> 1584 | Y33: 106 | Z33: =SUM(Y33-S33) -> #DIV/0!
A34: =Gen!A40 -> 0 | B34: 0 | C34: =Gen!B40 -> 0 | D34: =SUM(77*C34) -> 0 | F34: =Gen!U40 -> #DIV/0! | G34: =Gen!T40 -> 0 | H34: =[1]Gen!AJ40 -> 0 | I34: =SUM(G34:H34) -> 0 | J34: =[1]Gen!AT40 -> 33780 | K34: ='Water-Meter'!E35 -> 0 | L34: ='Lpg (2)'!G39 -> 0 | M34: =#REF! -> #REF! | N34: =#REF! -> #REF! | O34: =#REF! -> #REF! | P34: =J34/52000 -> 0.64961538 | Q34: =I34*Q2 -> 0 | R34: =SUM(Q34/D34)/X34 -> #DIV/0! | S34: =SUM(Q34/E34)/X34 -> #DIV/0! | T34: =(K34*102)/X34 -> 0 | U34: =SUM(L34*1963)/X34 -> 0 | V34: =SUM(Q34+T34+U34) -> 0 | W34: =SUM(V34/E34)/T2 -> #DIV/0! | X34: =SUM(X33) -> 1584 | Y34: 106 | Z34: =SUM(Y34-S34) -> #DIV/0!
A35: =Gen!A41 -> 0 | B35: 0 | C35: =Gen!B41 -> 0 | D35: =SUM(77*C35) -> 0 | F35: =Gen!U41 -> #DIV/0! | G35: =Gen!T41 -> 0 | H35: =[1]Gen!AJ41 -> 0 | I35: =SUM(G35:H35) -> 0 | J35: =[1]Gen!AT41 -> 33780 | K35: ='Water-Meter'!E36 -> 0 | L35: ='Lpg (2)'!G40 -> 0 | M35: =#REF! -> #REF! | N35: =#REF! -> #REF! | O35: =#REF! -> #REF! | P35: =J35/52000 -> 0.64961538 | Q35: =I35*Q2 -> 0 | R35: =SUM(Q35/D35)/X35 -> #DIV/0! | S35: =SUM(Q35/E35)/X35 -> #DIV/0! | T35: =(K35*102)/X35 -> 0 | U35: =SUM(L35*1963)/X35 -> 0 | V35: =SUM(Q35+T35+U35) -> 0 | W35: =SUM(V35/E35)/T2 -> #DIV/0! | X35: =SUM(X34) -> 1584 | Y35: 106 | Z35: =SUM(Y35-S35) -> #DIV/0!
K36: ='Water-Meter'!E37 -> 0 | Q36: =I36*2057.79 -> 0 | V36: =SUM(Q36+T36+U36) -> 0
K37: ='Water-Meter'!E38 -> 1002 | S37: =SUM(S5:S16)/[1]Gen!A47 -> #REF!
B38: =SUM(B5:B37)/[1]Gen!A47 -> #REF! | M38: =0.5*2057.79 -> 1028.895
B39: =SUM(B38*[1]Gen!A47) -> #REF! | C39: =SUM(B39/250) -> #REF! | M39: =M38/1500 -> 0.68593 | O39: =(24*2.2)*2 -> 105.6 | P39: =O39*1029 -> 108662.4 | R39: Over budget | S39: =SUM(S37-Y35) -> #REF!
P40: =P39/K5 -> 1873.4897

Sheet VODACOM AND AIRTEL
A1: VODACOM AND AIRTEL KWH METER READING
B2: VODACOM TOWER | E2: AIRTEL TOWER
A3: DATE | B3: OPEN METER READING | C3: CLOSE METER READING | D3: UNIT CONSUMED | E3: OPEN METER READING | F3: CLOSE METER READING | G3: UNIT CONSUMED
A4: 43101 | B4: 46071 | C4: 48188 | D4: 2117 | E4: 216654 | F4: 218779 | G4: 2125
A5: 43132 | B5: =C4 -> 48188 | C5: 50066 | D5: =C5-B5 -> 1878 | E5: =F4 -> 218779 | F5: 220744 | G5: =F5-E5 -> 1965
A6: 43160 | B6: =C5 -> 50066 | C6: 51916 | D6: =C6-B6 -> 1850 | E6: =F5 -> 220744 | F6: 222873 | G6: =F6-E6 -> 2129
A7: 43191 | B7: =C6 -> 51916 | C7: 53641 | D7: =C7-B7 -> 1725 | E7: =F6 -> 222873 | F7: 224922 | G7: =F7-E7 -> 2049
A8: 43221 | B8: =C7 -> 53641 | C8: 55409 | D8: =C8-B8 -> 1768 | E8: =F7 -> 224922 | F8: 227063 | G8: =F8-E8 -> 2141
A9: 43252 | B9: =C8 -> 55409 | C9: 57396 | D9: =C9-B9 -> 1987 | E9: =F8 -> 227063 | F9: 229163 | G9: =F9-E9 -> 2100
A10: 43282 | B10: =C9 -> 57396 | C10: 59391 | D10: =C10-B10 -> 1995 | E10: =F9 -> 229163 | F10: 231359 | G10: =F10-E10 -> 2196
A11: 43313 | B11: =C10 -> 59391 | C11: 61427 | D11: =C11-B11 -> 2036 | E11: =F10 -> 231359 | F11: 233548 | G11: =F11-E11 -> 2189
A12: 43344 | B12: =C11 -> 61427 | C12: 63464 | D12: =C12-B12 -> 2037 | E12: =F11 -> 233548 | F12: 235653 | G12: =F12-E12 -> 2105
A13: 43374 | B13: =C12 -> 63464 | C13: 65577 | D13: =C13-B13 -> 2113 | E13: =F12 -> 235653 | F13: 237802 | G13: =F13-E13 -> 2149
A14: 43405 | B14: =C13 -> 65577 | C14: 67714 | D14: =C14-B14 -> 2137 | E14: =F13 -> 237802 | F14: 239883 | G14: =F14-E14 -> 2081
A15: 43435 | B15: =C14 -> 67714 | C15: 69886 | D15: =C15-B15 -> 2172 | E15: =F14 -> 239883 | F15: 242023 | G15: =F15-E15 -> 2140
A16: 43466 | B16: =C15 -> 69886 | C16: 72120 | D16: =C16-B16 -> 2234 | E16: =F15 -> 242023 | F16: 244252 | G16: =F16-E16 -> 2229
... A36: 44075 | B36: =C35 -> 111576 | C36: 113681 | D36: =C36-B36 -> 2105 | E36: =F35 -> 285683 | F36: 287829 | G36: =F36-E36 -> 2146
A37: 44105 | B37: =C36 -> 113681 | D37: =C37-B37 -> -113681 | E37: =F36 -> 287829 | G37: =F37-E37 -> -287829
A38: 44136 | B38: =C37 -> 0 | D38: =C38-B38 -> 0 | E38: =F37 -> 0 | G38: =F38-E38 -> 0
A39: 44166 | B39: =C38 -> 0 | D39: =C39-B39 -> 0 | E39: =F38 -> 0 | G39: =F39-E39 -> 0
A40: 44197 | B40: =C39 -> 0 | D40: =C40-B40 -> 0 | E40: =F39 -> 0 | G40: =F40-E40 -> 0
A41: 44228 | B41: =C40 -> 0 | D41: =C41-B41 -> 0 | E41: =F40 -> 0 | G41: =F41-E41 -> 0
A42: 44256 | B42: =C41 -> 0 | D42: =C42-B42 -> 0 | E42: =F41 -> 0 | G42: =F42-E42 -> 0
A43: 44287 | B43: =C42 -> 0 | D43: =C43-B43 -> 0 | E43: =F42 -> 0 | G43: =F43-E43 -> 0
A44: 44317 | B44: =C43 -> 0 | D44: =C44-B44 -> 0 | E44: =F43 -> 0 | G44: =F44-E44 -> 0
A45: 44348 | B45: =C44 -> 0 | D45: =C45-B45 -> 0 | E45: =F44 -> 0 | G45: =F45-E45 -> 0
A46: 44378 | B46: =C45 -> 0 | D46: =C46-B46 -> 0 | E46: =F45 -> 0 | G46: =F46-E46 -> 0
A47: 44409 | B47: =C46 -> 0 | D47: =C47-B47 -> 0 | E47: =F46 -> 0 | G47: =F47-E47 -> 0
A48: 44440 | B48: =C47 -> 0 | D48: =C48-B48 -> 0 | E48: =F47 -> 0 | G48: =F48-E48 -> 0
... A75: 44896 | B75: =C74 -> 0 | D75: =C75-B75 -> 0 | E75: =F74 -> 0 | G75: =F75-E75 -> 0

Sheet FUEL METER READING
A1: FUEL METER 1 READNG | H1: FUEL METER 2 READING
A2: DATE | B2: OPEN METER READING | C2: CLOSE METER READING | D2: Diesel consumed | E2: HLP-GENSETS | F2: DIFFERENCE | G2: OPEN METER | H2: CLOSE METER | I2: DIESEL CONSUMED | J2: HLP-VEHICLES | K2: DIFFERENCE | L2: TOTAL DIESEL CONS.
A3: 43101 | B3: 6476953 | C3: 6542879 | D3: 65926 | E3: 65927.77 | F3: -1.77 | G3: 52890 | H3: 59763 | I3: 6873 | J3: 6874.87 | K3: -1.87 | L3: 72799
A4: 43132 | B4: =C3 -> 6542879 | C4: 6604433 | D4: =C4-B4 -> 61554 | E4: 61553.03 | F4: =D4-E4 -> 0.97 | G4: =H3 -> 59763 | H4: 66652 | I4: =H4-G4 -> 6889 | J4: 6890.89 | K4: =I4-J4 -> -1.89 | L4: =I4+D4 -> 68443
A5: 43160 | B5: =C4 -> 6604433 | C5: 6660226 | D5: =C5-B5 -> 55793 | E5: 55792.75 | F5: =D5-E5 -> 0.25 | G5: =H4 -> 66652 | H5: 77607 | I5: =H5-G5 -> 10955 | J5: 10955.45 | K5: =I5-J5 -> -0.45 | L5: =I5+D5 -> 66748
A6: 43191 | B6: =C5 -> 6660226 | C6: 6714539 | D6: =C6-B6 -> 54313 | E6: 54312.28 | F6: =D6-E6 -> 0.72 | G6: =H5 -> 77607 | H6: 82271 | I6: =H6-G6 -> 4664 | J6: 4665.22 | K6: =I6-J6 -> -1.22 | L6: =I6+D6 -> 58977
A7: 43221 | B7: =C6 -> 6714539 | C7: 6774547 | D7: =C7-B7 -> 60008 | E7: 60007.47 | F7: =D7-E7 -> 0.53 | G7: =H6 -> 82271 | H7: 88664 | I7: =H7-G7 -> 6393 | J7: 6392.14 | K7: =I7-J7 -> 0.86 | L7: =I7+D7 -> 66401
A8: 43252 | B8: =C7 -> 6774547 | C8: 6845214 | D8: =C8-B8 -> 70667 | E8: 70666.29 | F8: =D8-E8 -> 0.71 | G8: =H7 -> 88664 | H8: 99683 | I8: =H8-G8 -> 11019 | J8: 11020.51 | K8: =I8-J8 -> -1.51 | L8: =I8+D8 -> 81686
A9: 43282 | B9: =C8 -> 6845214 | C9: 6921964 | D9: =C9-B9 -> 76750 | E9: 76750.25 | F9: =D9-E9 -> -0.25 | G9: =H8 -> 99683 | H9: 107936 | I9: =H9-G9 -> 8253 | J9: 8252.24 | K9: =I9-J9 -> 0.76 | L9: =I9+D9 -> 85003
A10: 43313 | B10: =C9 -> 6921964 | C10: 7001142 | D10: =C10-B10 -> 79178 | E10: 79179.56 | F10: =D10-E10 -> -1.56 | G10: =H9 -> 107936 | H10: 116730 | I10: =H10-G10 -> 8794 | J10: 8793.12 | K10: =I10-J10 -> 0.88 | L10: =I10+D10 -> 87972
A11: 43344 | B11: =C10 -> 7001142 | C11: 7074217 | D11: =C11-B11 -> 73075 | E11: 73076.96 | F11: =D11-E11 -> -1.96 | G11: =H10 -> 116730 | H11: 127346 | I11: =H11-G11 -> 10616 | J11: 10615.37 | K11: =I11-J11 -> 0.63 | L11: =I11+D11 -> 83691
A12: 43374 | B12: =C11 -> 7074217 | C12: 7154506 | D12: =C12-B12 -> 80289 | E12: 80287.84 | F12: =D12-E12 -> 1.16 | G12: =H11 -> 127346 | H12: 134840 | I12: =H12-G12 -> 7494 | J12: 7493.99 | K12: =I12-J12 -> 0.01 | L12: =I12+D12 -> 87783
A13: 43405 | B13: =C12 -> 7154506 | C13: 7225359 | D13: =C13-B13 -> 70853 | E13: 70852.88 | F13: =D13-E13 -> 0.12 | G13: =H12 -> 134840 | H13: 145302 | I13: =H13-G13 -> 10462 | J13: 10462.7 | K13: =I13-J13 -> -0.7 | L13: =I13+D13 -> 81315
A14: 43435 | B14: =C13 -> 7225359 | C14: 7296581 | D14: =C14-B14 -> 71222 | E14: 71221.22 | F14: =D14-E14 -> 0.78 | G14: =H13 -> 145302 | H14: 154999 | I14: =H14-G14 -> 9697 | J14: 9696.8 | K14: =I14-J14 -> 0.2 | L14: =I14+D14 -> 80919
A15: 43466 | B15: =C14 -> 7296581 | C15: 7366625 | D15: =C15-B15 -> 70044 | E15: 70042.86 | F15: =D15-E15 -> 1.14 | G15: =H14 -> 154999 | H15: 161103 | I15: =H15-G15 -> 6104 | J15: 6107.32 | K15: =I15-J15 -> -3.32 | L15: =I15+D15 -> 76148
... A36: 44105 | B36: =C35 -> 8454371 | C36: 8470098 | D36: =C36-B36 -> 15727 | E36: 15726.66 | F36: =D36-E36 -> 0.34 | G36: =H35 -> 270861 | H36: 271447 | I36: =H36-G36 -> 586 | J36: 585.84 | K36: =I36-J36 -> 0.16 | L36: =I36+D36 -> 16313
A37: 44136 | B37: =C36 -> 8470098 | D37: =C37-B37 -> -8470098 | F37: =D37-E37 -> -8470098 | G37: =H36 -> 271447 | I37: =H37-G37 -> -271447 | K37: =I37-J37 -> -271447 | L37: =I37+D37 -> -8741545
A38: 44166 | B38: =C37 -> 0 | D38: =C38-B38 -> 0 | F38: =D38-E38 -> 0 | G38: =H37 -> 0 | I38: =H38-G38 -> 0 | K38: =I38-J38 -> 0 | L38: =I38+D38 -> 0
A39: 44197 | B39: =C38 -> 0 | D39: =C39-B39 -> 0 | F39: =D39-E39 -> 0 | G39: =H38 -> 0 | I39: =H39-G39 -> 0 | K39: =I39-J39 -> 0 | L39: =I39+D39 -> 0
A40: 44228 | B40: =C39 -> 0 | D40: =C40-B40 -> 0 | F40: =D40-E40 -> 0 | G40: =H39 -> 0 | I40: =H40-G40 -> 0 | K40: =I40-J40 -> 0 | L40: =I40+D40 -> 0
A41: 44256 | B41: =C40 -> 0 | D41: =C41-B41 -> 0 | F41: =D41-E41 -> 0 | G41: =H40 -> 0 | I41: =H41-G41 -> 0 | K41: =I41-J41 -> 0 | L41: =I41+D41 -> 0
A42: 44287 | B42: =C41 -> 0 | D42: =C42-B42 -> 0 | F42: =D42-E42 -> 0 | G42: =H41 -> 0 | I42: =H42-G42 -> 0 | K42: =I42-J42 -> 0 | L42: =I42+D42 -> 0
A43: 44317 | B43: =C42 -> 0 | D43: =C43-B43 -> 0 | F43: =D43-E43 -> 0 | G43: =H42 -> 0 | I43: =H43-G43 -> 0 | K43: =I43-J43 -> 0 | L43: =I43+D43 -> 0
A44: 44348 | B44: =C43 -> 0 | D44: =C44-B44 -> 0 | F44: =D44-E44 -> 0 | G44: =H43 -> 0 | I44: =H44-G44 -> 0 | K44: =I44-J44 -> 0 | L44: =I44+D44 -> 0
A45: 44378 | B45: =C44 -> 0 | D45: =C45-B45 -> 0 | F45: =D45-E45 -> 0 | G45: =H44 -> 0 | I45: =H45-G45 -> 0 | K45: =I45-J45 -> 0 | L45: =I45+D45 -> 0
A46: 44409 | B46: =C45 -> 0 | D46: =C46-B46 -> 0 | F46: =D46-E46 -> 0 | G46: =H45 -> 0 | I46: =H46-G46 -> 0 | K46: =I46-J46 -> 0 | L46: =I46+D46 -> 0
A47: 44440 | B47: =C46 -> 0 | D47: =C47-B47 -> 0 | F47: =D47-E47 -> 0 | G47: =H46 -> 0 | I47: =H47-G47 -> 0 | K47: =I47-J47 -> 0 | L47: =I47+D47 -> 0
A48: 44470 | B48: =C47 -> 0 | D48: =C48-B48 -> 0 | F48: =D48-E48 -> 0 | G48: =H47 -> 0 | I48: =H48-G48 -> 0 | K48: =I48-J48 -> 0 | L48: =I48+D48 -> 0
... A74: 44896 | B74: =C73 -> 0 | D74: =C74-B74 -> 0 | F74: =D74-E74 -> 0 | G74: =H73 -> 0 | I74: =H74-G74 -> 0 | K74: =I74-J74 -> 0 | L74: =I74+D74 -> 0
B91: DIESEL PUMP 01 READINGS | H91: DIESEL PUMP 02 READINGS

Sheet Daily utility report 
A1: DAILY UTILITIES REPORT
A2: =A5 -> 44228
A3: DATE | B3: OCC % | D3: GENERATOR FUEL (LTR) | F3: WATER (M³) | I3: ELECTRICAL (Kwh)
C4: VEHICLE CONSUMPTION | D4: CONSUMPTION | E4: BALANCE | F4: CONSUMPTION | G4: BOREHOLE PRODUCTION | H4: RO PRODUCTION | I4: KITCHEN | J4: LAUNDRY
A5: =Gen!A11 -> 44228 | B5: =Gen!B11 -> 0.091 | C5: =Gen!AJ11 -> 97.65 | D5: =Gen!S11 -> 1209.16 | E5: =Gen!C11 -> 35132.06 | F5: ='Water-Meter'!E6 -> 58 | G5: ='Water-Meter'!AN6 -> 207 | H5: ='Utility report '!AC6 -> 49 | I5: ='Kit report'!F4 -> 252 | J5: ='Kit report'!X4 -> 320
A6: =Gen!A12 -> 44229 | B6: =Gen!B12 -> 0.065 | C6: =Gen!AJ12 -> 0 | D6: =Gen!S12 -> 1173.44 | E6: =Gen!C12 -> 48625.25 | F6: ='Water-Meter'!E7 -> 56 | G6: ='Water-Meter'!AN7 -> 133 | H6: ='Utility report '!AC7 -> 26 | I6: ='Kit report'!F5 -> 228 | J6: ='Kit report'!X5 -> 360
A7: =Gen!A13 -> 44230 | B7: =Gen!B13 -> 0.039 | C7: =Gen!AJ13 -> 77.57 | D7: =Gen!S13 -> 1100.54 | E7: =Gen!C13 -> 47451.81 | F7: ='Water-Meter'!E8 -> 46 | G7: ='Water-Meter'!AN8 -> 92 | H7: ='Utility report '!AC8 -> 49 | I7: ='Kit report'!F6 -> 252 | J7: ='Kit report'!X6 -> 220
A8: =Gen!A14 -> 44231 | B8: =Gen!B14 -> 0.039 | C8: =Gen!AJ14 -> 120.29 | D8: =Gen!S14 -> 1094.66 | E8: =Gen!C14 -> 46273.7 | F8: ='Water-Meter'!E9 -> 52 | G8: ='Water-Meter'!AN9 -> 94 | H8: ='Utility report '!AC9 -> 49 | I8: ='Kit report'!F7 -> 228 | J8: ='Kit report'!X7 -> 280
A9: =Gen!A15 -> 44232 | B9: =Gen!B15 -> 0.0519 | C9: =Gen!AJ15 -> 96.64 | D9: =Gen!S15 -> 1254 | E9: =Gen!C15 -> 45058.75 | F9: ='Water-Meter'!E10 -> 45 | G9: ='Water-Meter'!AN10 -> 93 | H9: ='Utility report '!AC10 -> 38 | I9: ='Kit report'!F8 -> 264 | J9: ='Kit report'!X8 -> 340
A10: =Gen!A16 -> 44233 | B10: =Gen!B16 -> 0.0779 | C10: =Gen!AJ16 -> 68.41 | D10: =Gen!S16 -> 946.83 | E10: =Gen!C16 -> 43708.11 | F10: ='Water-Meter'!E11 -> 45 | G10: ='Water-Meter'!AN11 -> 88 | H10: ='Utility report '!AC11 -> 34 | I10: ='Kit report'!F9 -> 204 | J10: ='Kit report'!X9 -> 160
A11: =Gen!A17 -> 44234 | B11: =Gen!B17 -> 0.0779 | C11: =Gen!AJ17 -> 0 | D11: =Gen!S17 -> 1142.59 | E11: =Gen!C17 -> 42692.87 | F11: ='Water-Meter'!E12 -> 58 | G11: ='Water-Meter'!AN12 -> 90 | H11: ='Utility report '!AC12 -> 98 | I11: ='Kit report'!F10 -> 240 | J11: ='Kit report'!X10 -> 420
A12: =Gen!A18 -> 44235 | B12: =Gen!B18 -> 0.0519 | C12: =Gen!AJ18 -> 70.37 | D12: =Gen!S18 -> 1047.81 | E12: =Gen!C18 -> 41550.28 | F12: ='Water-Meter'!E13 -> 45 | G12: ='Water-Meter'!AN13 -> 61 | H12: ='Utility report '!AC13 -> 0 | I12: ='Kit report'!F11 -> 216 | J12: ='Kit report'!X11 -> 320
A13: =Gen!A19 -> 44236 | B13: =Gen!B19 -> 0.1039 | C13: =Gen!AJ19 -> 130.19 | D13: =Gen!S19 -> 1137.1 | E13: =Gen!C19 -> 40432.1 | F13: ='Water-Meter'!E14 -> 60 | G13: ='Water-Meter'!AN14 -> 82 | H13: ='Utility report '!AC14 -> 144 | I13: ='Kit report'!F12 -> 216 | J13: ='Kit report'!X12 -> 280
A14: =Gen!A20 -> 44237 | B14: =Gen!B20 -> 0.1039 | C14: =Gen!AJ20 -> 0 | D14: =Gen!S20 -> 1049.37 | E14: =Gen!C20 -> 39164.81 | F14: ='Water-Meter'!E15 -> 57 | G14: ='Water-Meter'!AN15 -> 77 | H14: ='Utility report '!AC15 -> 0 | I14: ='Kit report'!F13 -> 216 | J14: ='Kit report'!X13 -> 220
