Workbook

Sheet Total
A1: Site Name | B1: Day | C1: Month | D1: Year | E1: Total Electricity Kwh | F1: Electricity Tariff ($/Kwh) | G1: Total Fuel Oil (Liters) | H1: Fuel Oil $/Liter | I1: LPG (Kg) | J1: LPG $/Kg | K1: Water Utility Supply (m3) m3 | L1: Water Utility Supply (m3) $/m3 | M1: Irrigation Water (m3) m3 | N1: Irrigation water $/m3 | O1: Room Nights
A2: Beirut | B2: 1 | C2: 3 | D2: 2021 | E2: =ELEC!N3 -> 8408 | F2: =SUM('EDl log'!T4) -> 0.29691552 | G2: =-tanks!AW6 -> 420.2 | H2: =SUM(tanks!AV6) -> 0.74 | I2: =('B5'!AU5)*0.51 -> 0 | J2: ='B5'!AX5/0.51 -> 1.5686275 | K2: =WATER!I6 -> 0 | L2: =SUM(WATER!J6) -> 0 | M2: =WATER!Q6 -> 0 | N2: 0.6 | O2: =ELEC!B3 -> 0
A3: Beirut | B3: =B2+1 -> 2 | C3: 3 | D3: 2021 | E3: =ELEC!N4 -> 9041 | F3: =SUM('EDl log'!T5) -> 0.19346639 | G3: =-tanks!AW7 -> 351 | H3: =SUM(tanks!AV7) -> 0.74 | I3: =('B5'!AU6)*0.51 -> 0 | J3: ='B5'!AX6/0.51 -> 1.5686275 | K3: =WATER!I7 -> 0 | L3: =SUM(WATER!J7) -> 0 | M3: =WATER!Q7 -> 0 | N3: 0.6 | O3: =ELEC!B4 -> 0
A4: Beirut | B4: =B3+1 -> 3 | C4: 3 | D4: 2021 | E4: =ELEC!N5 -> 7715 | F4: =SUM('EDl log'!T6) -> 0.18676973 | G4: =-tanks!AW8 -> 216 | H4: =SUM(tanks!AV8) -> 0.74 | I4: =('B5'!AU7)*0.51 -> 0 | J4: ='B5'!AX7/0.51 -> 1.5686275 | K4: =WATER!I8 -> 0 | L4: =SUM(WATER!J8) -> 0 | M4: =WATER!Q8 -> 0 | N4: 0.6 | O4: =ELEC!B5 -> 0
A5: Beirut | B5: =B4+1 -> 4 | C5: 3 | D5: 2021 | E5: =ELEC!N6 -> 7405 | F5: =SUM('EDl log'!T7) -> 0.18329353 | G5: =-tanks!AW9 -> 312 | H5: =SUM(tanks!AV9) -> 0.74 | I5: =('B5'!AU8)*0.51 -> 0 | J5: ='B5'!AX8/0.51 -> 1.5686275 | K5: =WATER!I9 -> 0 | L5: =SUM(WATER!J9) -> 0 | M5: =WATER!Q9 -> 0 | N5: 0.6 | O5: =ELEC!B6 -> 0
A6: Beirut | B6: =B5+1 -> 5 | C6: 3 | D6: 2021 | E6: =ELEC!N7 -> 7744 | F6: =SUM('EDl log'!T8) -> 0.057264162 | G6: =-tanks!AW10 -> 238 | H6: =SUM(tanks!AV10) -> 0.78 | I6: =('B5'!AU9)*0.51 -> 0 | J6: ='B5'!AX9/0.51 -> 1.5686275 | K6: =WATER!I10 -> 0 | L6: =SUM(WATER!J10) -> 0 | M6: =WATER!Q10 -> 0 | N6: 0.6 | O6: =ELEC!B7 -> 0
A7: Beirut | B7: =B6+1 -> 6 | C7: 3 | D7: 2021 | E7: =ELEC!N8 -> 7618 | F7: =SUM('EDl log'!T9) -> 0.18653433 | G7: =-tanks!AW11 -> 228 | H7: =SUM(tanks!AV11) -> 0.78 | I7: =('B5'!AU10)*0.51 -> 0 | J7: ='B5'!AX10/0.51 -> 1.5686275 | K7: =WATER!I11 -> 0 | L7: =SUM(WATER!J11) -> 0 | M7: =WATER!Q11 -> 0 | N7: 0.6 | O7: =ELEC!B8 -> 0
A8: Beirut | B8: =B7+1 -> 7 | C8: 3 | D8: 2021 | E8: =ELEC!N9 -> 6359 | F8: =SUM('EDl log'!T10) -> 0.12014925 | G8: =-tanks!AW12 -> 230 | H8: =SUM(tanks!AV12) -> 0.78 | I8: =('B5'!AU11)*0.51 -> 0 | J8: ='B5'!AX11/0.51 -> 1.5686275 | K8: =WATER!I12 -> 0 | L8: =SUM(WATER!J12) -> 0 | M8: =WATER!Q12 -> 0 | N8: 0.6 | O8: =ELEC!B9 -> 0
A9: Beirut | B9: =B8+1 -> 8 | C9: 3 | D9: 2021 | E9: =ELEC!N10 -> 6832 | F9: =SUM('EDl log'!T11) -> 0.15584548 | G9: =-tanks!AW13 -> 290 | H9: =SUM(tanks!AV13) -> 0.78 | I9: =('B5'!AU12)*0.51 -> 0 | J9: ='B5'!AX12/0.51 -> 1.5686275 | K9: =WATER!I13 -> 0 | L9: =SUM(WATER!J13) -> 0 | M9: =WATER!Q13 -> 0 | N9: 0.6 | O9: =ELEC!B10 -> 0
A10: Beirut | B10: =B9+1 -> 9 | C10: 3 | D10: 2021 | E10: =ELEC!N11 -> 0 | F10: =SUM('EDl log'!T12) -> 0 | G10: =-tanks!AW14 -> 0 | H10: =SUM(tanks!AV14) -> 0.78 | I10: =('B5'!AU13)*0.51 -> 0 | J10: ='B5'!AX13/0.51 -> 1.5686275 | K10: =WATER!I14 -> 0 | L10: =SUM(WATER!J14) -> 0 | M10: =WATER!Q14 -> 0 | N10: 0.6 | O10: =ELEC!B11 -> 0
A11: Beirut | B11: =B10+1 -> 10 | C11: 3 | D11: 2021 | E11: =ELEC!N12 -> 0 | F11: =SUM('EDl log'!T13) -> 0 | G11: =-tanks!AW15 -> 0 | H11: =SUM(tanks!AV15) -> 0.78 | I11: =('B5'!AU14)*0.51 -> 0 | J11: ='B5'!AX14/0.51 -> 1.5686275 | K11: =WATER!I15 -> 0 | L11: =SUM(WATER!J15) -> 0 | M11: =WATER!Q15 -> 0 | N11: 0.6 | O11: =ELEC!B12 -> 0
A12: Beirut | B12: =B11+1 -> 11 | C12: 3 | D12: 2021 | E12: =ELEC!N13 -> 0 | F12: =SUM('EDl log'!T14) -> 0 | G12: =-tanks!AW16 -> 0 | H12: =SUM(tanks!AV16) -> 0.78 | I12: =('B5'!AU15)*0.51 -> 0 | J12: ='B5'!AX15/0.51 -> 1.5686275 | K12: =WATER!I16 -> 0 | L12: =SUM(WATER!J16) -> 0 | M12: =WATER!Q16 -> 0 | N12: 0.6 | O12: =ELEC!B13 -> 0
A13: Beirut | B13: =B12+1 -> 12 | C13: 3 | D13: 2021 | E13: =ELEC!N14 -> 0 | F13: =SUM('EDl log'!T15) -> 0 | G13: =-tanks!AW17 -> 0 | H13: =SUM(tanks!AV17) -> 0.78 | I13: =('B5'!AU16)*0.51 -> 0 | J13: ='B5'!AX16/0.51 -> 1.5686275 | K13: =WATER!I17 -> 0 | L13: =SUM(WATER!J17) -> 0 | M13: =WATER!Q17 -> 0 | N13: 0.6 | O13: =ELEC!B14 -> 0
A14: Beirut | B14: =B13+1 -> 13 | C14: 3 | D14: 2021 | E14: =ELEC!N15 -> 0 | F14: =SUM('EDl log'!T16) -> 0 | G14: =-tanks!AW18 -> 0 | H14: =SUM(tanks!AV18) -> 0.78 | I14: =('B5'!AU17)*0.51 -> 0 | J14: ='B5'!AX17/0.51 -> 1.5686275 | K14: =WATER!I18 -> 0 | L14: =SUM(WATER!J18) -> 0 | M14: =WATER!Q18 -> 0 | N14: 0.6 | O14: =ELEC!B15 -> 0
... A28: Beirut | B28: =B27+1 -> 27 | C28: 3 | D28: 2021 | E28: =ELEC!N29 -> 0 | F28: =SUM('EDl log'!T30) -> 0 | G28: =-tanks!AW32 -> 0 | H28: =SUM(tanks!AV32) -> 0.78 | I28: =('B5'!AU31)*0.51 -> 0 | J28: ='B5'!AX31/0.51 -> 1.5686275 | K28: =WATER!I32 -> 0 | L28: =SUM(WATER!J32) -> 0 | M28: =WATER!Q32 -> 0 | N28: 0.6 | O28: =ELEC!B29 -> 0
A29: Beirut | B29: =B28+1 -> 28 | C29: 3 | D29: 2021 | E29: =ELEC!N30 -> 0 | F29: =SUM('EDl log'!T34) -> 0 | G29: =-tanks!AW33 -> 0 | H29: =SUM(tanks!AV33) -> 0.78 | I29: =('B5'!AU32)*0.51 -> 0 | J29: ='B5'!AX32/0.51 -> 1.5686275 | K29: =WATER!I33 -> 0 | L29: =SUM(WATER!J33) -> 0 | M29: =WATER!Q33 -> 0 | N29: 0.6 | O29: =ELEC!B30 -> 0
A30: Beirut | B30: =B29+1 -> 29 | C30: 3 | D30: 2021 | E30: =ELEC!N31 -> 0 | F30: =SUM('EDl log'!T32) -> 0 | G30: =-tanks!AW34 -> 0 | H30: =SUM(tanks!AV34) -> 0.78 | I30: =('B5'!AU33)*0.51 -> 0 | J30: ='B5'!AX33/0.51 -> 1.5686275 | K30: =WATER!I34 -> 0 | L30: =SUM(WATER!J34) -> 0 | M30: =WATER!Q34 -> 0 | N30: 0.6 | O30: =ELEC!B31 -> 0
A31: Beirut | B31: =B30+1 -> 30 | C31: 3 | D31: 2021 | E31: =ELEC!N32 -> 0 | F31: =SUM('EDl log'!T33) -> 0 | G31: =-tanks!AW35 -> 0 | H31: =SUM(tanks!AV35) -> 0.78 | I31: =('B5'!AU34)*0.51 -> 0 | J31: ='B5'!AX34/0.51 -> 1.5686275 | K31: =WATER!I35 -> 0 | L31: =SUM(WATER!J35) -> 0 | M31: =WATER!Q35 -> 0 | N31: 0.6 | O31: =ELEC!B32 -> 0
A32: Beirut | B32: =B31+1 -> 31 | C32: 3 | D32: 2021 | E32: =ELEC!N33 -> 0 | F32: =SUM('EDl log'!T37) -> 0 | G32: =-tanks!AW36 -> 0 | H32: =SUM(tanks!AV36) -> 0.78 | I32: =('B5'!AU35)*0.51 -> 0 | J32: ='B5'!AX35/0.51 -> 1.5686275 | K32: =WATER!I36 -> 0 | L32: =SUM(WATER!J36) -> 0 | M32: =WATER!Q36 -> 0 | N32: 0.6 | O32: =ELEC!B33 -> 0

Sheet Submetering
A1: Site Name | B1: Day | C1: Month | D1: Year | E1: ATS1 Kwh | F1: ATS2 Kwh | G1: ATS3 Kwh | H1: ATS4 Kwh | I1: ATS5 Kwh | J1: Guest (m3) | K1: Kitchen & Laundry (m3) | L1: Room Nights
A2: Beirut | B2: 1 | C2: 3 | D2: 2021 | E2: =ELEC!M3 -> 2408 | F2: =ELEC!K3 -> 1676 | G2: =ELEC!I3 -> 928 | H2: =ELEC!E3 -> 2697 | I2: =ELEC!G3 -> 699 | J2: =WATER!Y6 -> 0 | K2: =WATER!AJ6 -> 0 | L2: =ELEC!B3 -> 0
A3: Beirut | B3: =B2+1 -> 2 | C3: 3 | D3: 2021 | E3: =ELEC!M4 -> 2568 | F3: =ELEC!K4 -> 1428 | G3: =ELEC!I4 -> 938 | H3: =ELEC!E4 -> 3467 | I3: =ELEC!G4 -> 640 | J3: =WATER!Y7 -> 0 | K3: =WATER!AJ7 -> 0 | L3: =ELEC!B4 -> 0
A4: Beirut | B4: =B3+1 -> 3 | C4: 3 | D4: 2021 | E4: =ELEC!M5 -> 1992 | F4: =ELEC!K5 -> 1192 | G4: =ELEC!I5 -> 902 | H4: =ELEC!E5 -> 2976 | I4: =ELEC!G5 -> 653 | J4: =WATER!Y8 -> 0 | K4: =WATER!AJ8 -> 0 | L4: =ELEC!B5 -> 0
A5: Beirut | B5: =B4+1 -> 4 | C5: 3 | D5: 2021 | E5: =ELEC!M6 -> 1952 | F5: =ELEC!K6 -> 1152 | G5: =ELEC!I6 -> 900 | H5: =ELEC!E6 -> 2760 | I5: =ELEC!G6 -> 641 | J5: =WATER!Y9 -> 0 | K5: =WATER!AJ9 -> 0 | L5: =ELEC!B6 -> 0
A6: Beirut | B6: =B5+1 -> 5 | C6: 3 | D6: 2021 | E6: =ELEC!M7 -> 1822 | F6: =ELEC!K7 -> 1132 | G6: =ELEC!I7 -> 916 | H6: =ELEC!E7 -> 3292 | I6: =ELEC!G7 -> 582 | J6: =WATER!Y10 -> 0 | K6: =WATER!AJ10 -> 0 | L6: =ELEC!B7 -> 0
A7: Beirut | B7: =B6+1 -> 6 | C7: 3 | D7: 2021 | E7: =ELEC!M8 -> 1966 | F7: =ELEC!K8 -> 1168 | G7: =ELEC!I8 -> 870 | H7: =ELEC!E8 -> 3066 | I7: =ELEC!G8 -> 548 | J7: =WATER!Y11 -> 0 | K7: =WATER!AJ11 -> 0 | L7: =ELEC!B8 -> 0
A8: Beirut | B8: =B7+1 -> 7 | C8: 3 | D8: 2021 | E8: =ELEC!M9 -> 1752 | F8: =ELEC!K9 -> 926 | G8: =ELEC!I9 -> 858 | H8: =ELEC!E9 -> 2250 | I8: =ELEC!G9 -> 573 | J8: =WATER!Y12 -> 0 | K8: =WATER!AJ12 -> 0 | L8: =ELEC!B9 -> 0
A9: Beirut | B9: =B8+1 -> 8 | C9: 3 | D9: 2021 | E9: =ELEC!M10 -> 1668 | F9: =ELEC!K10 -> 1002 | G9: =ELEC!I10 -> 836 | H9: =ELEC!E10 -> 2724 | I9: =ELEC!G10 -> 602 | J9: =WATER!Y13 -> 0 | K9: =WATER!AJ13 -> 0 | L9: =ELEC!B10 -> 0
A10: Beirut | B10: =B9+1 -> 9 | C10: 3 | D10: 2021 | E10: =ELEC!M11 -> 0 | F10: =ELEC!K11 -> 0 | G10: =ELEC!I11 -> 0 | H10: =ELEC!E11 -> 0 | I10: =ELEC!G11 -> 0 | J10: =WATER!Y14 -> 0 | K10: =WATER!AJ14 -> 0 | L10: =ELEC!B11 -> 0
A11: Beirut | B11: =B10+1 -> 10 | C11: 3 | D11: 2021 | E11: =ELEC!M12 -> 0 | F11: =ELEC!K12 -> 0 | G11: =ELEC!I12 -> 0 | H11: =ELEC!E12 -> 0 | I11: =ELEC!G12 -> 0 | J11: =WATER!Y15 -> 0 | K11: =WATER!AJ15 -> 0 | L11: =ELEC!B12 -> 0
A12: Beirut | B12: =B11+1 -> 11 | C12: 3 | D12: 2021 | E12: =ELEC!M13 -> 0 | F12: =ELEC!K13 -> 0 | G12: =ELEC!I13 -> 0 | H12: =ELEC!E13 -> 0 | I12: =ELEC!G13 -> 0 | J12: =WATER!Y16 -> 0 | K12: =WATER!AJ16 -> 0 | L12: =ELEC!B13 -> 0
A13: Beirut | B13: =B12+1 -> 12 | C13: 3 | D13: 2021 | E13: =ELEC!M14 -> 0 | F13: =ELEC!K14 -> 0 | G13: =ELEC!I14 -> 0 | H13: =ELEC!E14 -> 0 | I13: =ELEC!G14 -> 0 | J13: =WATER!Y17 -> 0 | K13: =WATER!AJ17 -> 0 | L13: =ELEC!B14 -> 0
A14: Beirut | B14: =B13+1 -> 13 | C14: 3 | D14: 2021 | E14: =ELEC!M15 -> 0 | F14: =ELEC!K15 -> 0 | G14: =ELEC!I15 -> 0 | H14: =ELEC!E15 -> 0 | I14: =ELEC!G15 -> 0 | J14: =WATER!Y18 -> 0 | K14: =WATER!AJ18 -> 0 | L14: =ELEC!B15 -> 0
... A32: Beirut | B32: =B31+1 -> 31 | C32: 3 | D32: 2021 | E32: =ELEC!M33 -> 0 | F32: =ELEC!K33 -> 0 | G32: =ELEC!I33 -> 0 | H32: =ELEC!E33 -> 0 | I32: =ELEC!G33 -> 0 | J32: =WATER!Y36 -> 0 | K32: =WATER!AJ36 -> 0 | L32: =ELEC!B33 -> 0

Sheet ELEC
A1: OOC | B1: Room OCC | D1: MDB3 | E1: MDB3/day | F1: EMDB2 | G1: EMDB2/day | H1: EMDB1 | I1: EMDB1/day | J1: MDB2 | K1: mdb2/day | L1: MDB1 | M1: MDB1/Day | N1: Total KWH | O1: KWH/Rooc | P1: Gen MHW | Q1: Gen/Day KWH | R1: EDL KWH | S1: CH1 RH | T1: RH | U1: C1h1 power | V1: CH1 Con KWH | W1: CH2 RH | X1: RH | Y1: Ch2 power | Z1: CH2 Con KWH | AA1: CH3 RH | AB1: RH | AC1: Ch3 power | AD1: CH3 Con KWH | AE1: RH total | AF1: KWH total | AG1: AVG chiller KW/Hr
A2: =[1]ELEC!A30 -> 0 | B2: =[2]ELEC!B33 -> 0 | C2: =[1]ELEC!$C$30 -> 44255 | D2: =[1]ELEC!D30 -> 32641226 | E2: =[1]ELEC!E30 -> 1904 | F2: =[1]ELEC!F30 -> 3971481 | G2: =[1]ELEC!G30 -> 621 | H2: =[1]ELEC!H30 -> 17803738 | I2: =[1]ELEC!I30 -> 908 | J2: =[1]ELEC!J30 -> 28920206 | K2: =[1]ELEC!K30 -> 1956 | ... CZ2: =[1]ELEC!CZ30 -> 0 | DA2: =[2]ELEC!DA33 -> 0 | DB2: =[2]ELEC!DB33 -> 0 | DC2: =[2]ELEC!DC33 -> 0 | DD2: =[2]ELEC!DD33 -> 0
A3: ='General information '!F6 -> 0 | B3: =SUM(230*A3) -> 0 | C3: 44256 | D3: 32643923 | E3: =D3-D2 -> 2697 | F3: 3972180 | G3: =F3-F2 -> 699 | H3: 17804666 | I3: =H3-H2 -> 928 | J3: 28921882 | K3: =J3-J2 -> 1676 | L3: 24055550 | M3: =L3-L2 -> 2408 | N3: =M3+K3+I3+G3+E3 -> 8408 | O3: =IF(B3>0,N3/B3,0) -> 0 | P3: 16685.501 | Q3: =(P3-P2)*1000 -> 6164 | R3: =+N3-Q3 -> 2244 | S3: =S2 -> 10128 | T3: =S3-S2 -> 0 | U3: =U2 -> 422437 | V3: =U3-U2 -> 0 | W3: 32246 | X3: =W3-W2 -> 2 | Y3: 708475 | Z3: =Y3-Y2 -> 334 | AA3: 35699 | AB3: =AA3-AA2 -> 2 | AC3: 916997 | AD3: =AC3-AC2 -> 341 | AE3: =AB3+X3+T3 -> 4 | AF3: =V3+Z3+AD3 -> 675 | AG3: =IF(AE3>0,AF3/AE3,0) -> 168.75
A4: ='General information '!F7 -> 0 | B4: =SUM(230*A4) -> 0 | C4: 44257 | D4: 32647390 | E4: =D4-D3 -> 3467 | F4: 3972820 | G4: =F4-F3 -> 640 | H4: 17805604 | I4: =H4-H3 -> 938 | J4: 28923310 | K4: =J4-J3 -> 1428 | L4: 24058118 | M4: =L4-L3 -> 2568 | N4: =M4+K4+I4+G4+E4 -> 9041 | O4: =IF(B4>0,N4/B4,0) -> 0 | P4: 16692.837 | Q4: =(P4-P3)*1000 -> 7336 | R4: =N4-Q4 -> 1705 | S4: =S3 -> 10128 | T4: =S4-S3 -> 0 | U4: =U3 -> 422437 | V4: =U4-U3 -> 0 | W4: =W3 -> 32246 | X4: =W4-W3 -> 0 | Y4: =Y3 -> 708475 | Z4: =Y4-Y3 -> 0 | AA4: 35704 | AB4: =AA4-AA3 -> 5 | AC4: 917856 | AD4: =AC4-AC3 -> 859 | AE4: =AB4+X4+T4 -> 5 | AF4: =V4+Z4+AD4 -> 859 | AG4: =IF(AE4>0,AF4/AE4,0) -> 171.8
A5: ='General information '!F8 -> 0 | B5: =SUM(230*A5) -> 0 | C5: 44258 | D5: 32650366 | E5: =D5-D4 -> 2976 | F5: 3973473 | G5: =F5-F4 -> 653 | H5: 17806506 | I5: =H5-H4 -> 902 | J5: 28924502 | K5: =J5-J4 -> 1192 | L5: 24060110 | M5: =L5-L4 -> 1992 | N5: =M5+K5+I5+G5+E5 -> 7715 | O5: =IF(B5>0,N5/B5,0) -> 0 | P5: 16697.687 | Q5: =(P5-P4)*1000 -> 4850 | R5: =N5-Q5 -> 2865 | S5: =S4 -> 10128 | T5: =S5-S4 -> 0 | U5: =U4 -> 422437 | V5: =U5-U4 -> 0 | W5: =W4 -> 32246 | X5: =W5-W4 -> 0 | Y5: =Y4 -> 708475 | Z5: =Y5-Y4 -> 0 | AA5: 35709 | AB5: =AA5-AA4 -> 5 | AC5: 918536 | AD5: =AC5-AC4 -> 680 | AE5: =AB5+X5+T5 -> 5 | AF5: =V5+Z5+AD5 -> 680 | AG5: =IF(AE5>0,AF5/AE5,0) -> 136 | AI5: =R5-'EDl log'!B3 -> -902113
A6: ='General information '!F9 -> 0 | B6: =SUM(230*A6) -> 0 | C6: 44259 | D6: 32653126 | E6: =D6-D5 -> 2760 | F6: 3974114 | G6: =F6-F5 -> 641 | H6: 17807406 | I6: =H6-H5 -> 900 | J6: 28925654 | K6: =J6-J5 -> 1152 | L6: 24062062 | M6: =L6-L5 -> 1952 | N6: =M6+K6+I6+G6+E6 -> 7405 | O6: =IF(B6>0,N6/B6,0) -> 0 | P6: 16701.182 | Q6: =(P6-P5)*1000 -> 3495 | R6: =N6-Q6 -> 3910 | S6: =S5 -> 10128 | T6: =S6-S5 -> 0 | U6: =U5 -> 422437 | V6: =U6-U5 -> 0 | W6: =W5 -> 32246 | X6: =W6-W5 -> 0 | Y6: =Y5 -> 708475 | Z6: =Y6-Y5 -> 0 | AA6: 35712 | AB6: =AA6-AA5 -> 3 | AC6: 919105 | AD6: =AC6-AC5 -> 569 | AE6: =AB6+X6+T6 -> 3 | AF6: =V6+Z6+AD6 -> 569 | AG6: =IF(AE6>0,AF6/AE6,0) -> 189.66667 | AI6: =R6-'EDl log'!B4 -> -902318
A7: ='General information '!F10 -> 0 | B7: =SUM(230*A7) -> 0 | C7: 44260 | D7: 32656418 | E7: =D7-D6 -> 3292 | F7: 3974696 | G7: =F7-F6 -> 582 | H7: 17808322 | I7: =H7-H6 -> 916 | J7: 28926786 | K7: =J7-J6 -> 1132 | L7: 24063884 | M7: =L7-L6 -> 1822 | N7: =M7+K7+I7+G7+E7 -> 7744 | O7: =IF(B7>0,N7/B7,0) -> 0 | P7: 16705.77 | Q7: =(P7-P6)*1000 -> 4588 | R7: =N7-Q7 -> 3156 | S7: 10128 | T7: =S7-S6 -> 0 | U7: =U6 -> 422437 | V7: =U7-U6 -> 0 | W7: 32246 | X7: =W7-W6 -> 0 | Y7: =Y6 -> 708475 | Z7: =Y7-Y6 -> 0 | AA7: 35717 | AB7: =AA7-AA6 -> 5 | AC7: 919927 | AD7: =AC7-AC6 -> 822 | AE7: =AB7+X7+T7 -> 5 | AF7: =V7+Z7+AD7 -> 822 | AG7: =IF(AE7>0,AF7/AE7,0) -> 164.4 | AI7: =R7-'EDl log'!B5 -> -904028
A8: ='General information '!F11 -> 0 | B8: =SUM(230*A8) -> 0 | C8: 44261 | D8: 32659484 | E8: =D8-D7 -> 3066 | F8: 3975244 | G8: =F8-F7 -> 548 | H8: 17809192 | I8: =H8-H7 -> 870 | J8: 28927954 | K8: =J8-J7 -> 1168 | L8: 24065850 | M8: =L8-L7 -> 1966 | N8: =M8+K8+I8+G8+E8 -> 7618 | O8: =IF(B8>0,N8/B8,0) -> 0 | P8: 16710.65 | Q8: =(P8-P7)*1000 -> 4880 | R8: =N8-Q8 -> 2738 | S8: =S7 -> 10128 | T8: =S8-S7 -> 0 | U8: =U7 -> 422437 | V8: =U8-U7 -> 0 | W8: =W7 -> 32246 | X8: =W8-W7 -> 0 | Y8: =Y7 -> 708475 | Z8: =Y8-Y7 -> 0 | AA8: 35721 | AB8: =AA8-AA7 -> 4 | AC8: 920665 | AD8: =AC8-AC7 -> 738 | AE8: =AB8+X8+T8 -> 4 | AF8: =V8+Z8+AD8 -> 738 | AG8: =IF(AE8>0,AF8/AE8,0) -> 184.5 | AI8: =R8-'EDl log'!B6 -> -906015
A9: ='General information '!F12 -> 0 | B9: =SUM(230*A9) -> 0 | C9: 44262 | D9: 32661734 | E9: =D9-D8 -> 2250 | F9: 3975817 | G9: =F9-F8 -> 573 | H9: 17810050 | I9: =H9-H8 -> 858 | J9: 28928880 | K9: =J9-J8 -> 926 | L9: 24067602 | M9: =L9-L8 -> 1752 | N9: =M9+K9+I9+G9+E9 -> 6359 | O9: =IF(B9>0,N9/B9,0) -> 0 | P9: 16712.709 | Q9: =(P9-P8)*1000 -> 2059 | R9: =N9-Q9 -> 4300 | S9: =S8 -> 10128 | T9: =S9-S8 -> 0 | U9: =U8 -> 422437 | V9: =U9-U8 -> 0 | W9: =W8 -> 32246 | X9: =W9-W8 -> 0 | Y9: =Y8 -> 708475 | Z9: =Y9-Y8 -> 0 | AA9: 35724 | AB9: =AA9-AA8 -> 3 | AC9: 921046 | AD9: =AC9-AC8 -> 381 | AE9: =AB9+X9+T9 -> 3 | AF9: =V9+Z9+AD9 -> 381 | AG9: =IF(AE9>0,AF9/AE9,0) -> 127 | AI9: =R9-'EDl log'!B7 -> -906552
A10: ='General information '!F13 -> 0 | B10: =SUM(230*A10) -> 0 | C10: 44263 | D10: 32664458 | E10: =D10-D9 -> 2724 | F10: 3976419 | G10: =F10-F9 -> 602 | H10: 17810886 | I10: =H10-H9 -> 836 | J10: 28929882 | K10: =J10-J9 -> 1002 | L10: 24069270 | M10: =L10-L9 -> 1668 | N10: =M10+K10+I10+G10+E10 -> 6832 | O10: =IF(B10>0,N10/B10,0) -> 0 | P10: 16715.519 | Q10: =(P10-P9)*1000 -> 2810 | R10: =N10-Q10 -> 4022 | S10: =S9 -> 10128 | T10: =S10-S9 -> 0 | U10: =U9 -> 422437 | V10: =U10-U9 -> 0 | W10: =W9 -> 32246 | X10: =W10-W9 -> 0 | Y10: =Y9 -> 708475 | Z10: =Y10-Y9 -> 0 | AA10: 35727 | AB10: =AA10-AA9 -> 3 | AC10: 921652 | AD10: =AC10-AC9 -> 606 | AE10: =AB10+X10+T10 -> 3 | AF10: =V10+Z10+AD10 -> 606 | AG10: =IF(AE10>0,AF10/AE10,0) -> 202 | AI10: =R10-'EDl log'!B8 -> -908545
A11: ='General information '!F14 -> 0 | B11: =SUM(230*A11) -> 0 | C11: 44264 | D11: =D10 -> 32664458 | E11: =D11-D10 -> 0 | F11: =F10 -> 3976419 | G11: =F11-F10 -> 0 | H11: =H10 -> 17810886 | I11: =H11-H10 -> 0 | J11: =J10 -> 28929882 | K11: =J11-J10 -> 0 | L11: =L10 -> 24069270 | M11: =L11-L10 -> 0 | N11: =M11+K11+I11+G11+E11 -> 0 | O11: =IF(B11>0,N11/B11,0) -> 0 | P11: =P10 -> 16715.519 | Q11: =(P11-P10)*1000 -> 0 | R11: =N11-Q11 -> 0 | S11: =S10 -> 10128 | T11: =S11-S10 -> 0 | U11: =U10 -> 422437 | V11: =U11-U10 -> 0 | W11: =W10 -> 32246 | X11: =W11-W10 -> 0 | Y11: =Y10 -> 708475 | Z11: =Y11-Y10 -> 0 | AA11: =AA10 -> 35727 | AB11: =AA11-AA10 -> 0 | AC11: =AC10 -> 921652 | AD11: =AC11-AC10 -> 0 | AE11: =AB11+X11+T11 -> 0 | AF11: =V11+Z11+AD11 -> 0 | AG11: =IF(AE11>0,AF11/AE11,0) -> 0 | AI11: =R11-'EDl log'!B9 -> -914077
A12: ='General information '!F15 -> 0 | B12: =SUM(230*A12) -> 0 | C12: 44265 | D12: =D11 -> 32664458 | E12: =D12-D11 -> 0 | F12: =F11 -> 3976419 | G12: =F12-F11 -> 0 | H12: =H11 -> 17810886 | I12: =H12-H11 -> 0 | J12: =J11 -> 28929882 | K12: =J12-J11 -> 0 | L12: =L11 -> 24069270 | M12: =L12-L11 -> 0 | N12: =M12+K12+I12+G12+E12 -> 0 | O12: =IF(B12>0,N12/B12,0) -> 0 | P12: =P11 -> 16715.519 | Q12: =(P12-P11)*1000 -> 0 | R12: =N12-Q12 -> 0 | S12: =S11 -> 10128 | T12: =S12-S11 -> 0 | U12: =U11 -> 422437 | V12: =U12-U11 -> 0 | W12: =W11 -> 32246 | X12: =W12-W11 -> 0 | Y12: =Y11 -> 708475 | Z12: =Y12-Y11 -> 0 | AA12: =AA11 -> 35727 | AB12: =AA12-AA11 -> 0 | AC12: =AC11 -> 921652 | AD12: =AC12-AC11 -> 0 | AE12: =AB12+X12+T12 -> 0 | AF12: =V12+Z12+AD12 -> 0 | AG12: =IF(AE12>0,AF12/AE12,0) -> 0 | AI12: =R12-'EDl log'!B10 -> -916365
A13: ='General information '!F16 -> 0 | B13: =SUM(230*A13) -> 0 | C13: 44266 | D13: =D12 -> 32664458 | E13: =D13-D12 -> 0 | F13: =F12 -> 3976419 | G13: =F13-F12 -> 0 | H13: =H12 -> 17810886 | I13: =H13-H12 -> 0 | J13: =J12 -> 28929882 | K13: =J13-J12 -> 0 | L13: =L12 -> 24069270 | M13: =L13-L12 -> 0 | N13: =M13+K13+I13+G13+E13 -> 0 | O13: =IF(B13>0,N13/B13,0) -> 0 | P13: =P12 -> 16715.519 | Q13: =(P13-P12)*1000 -> 0 | R13: =N13-Q13 -> 0 | S13: =S12 -> 10128 | T13: =S13-S12 -> 0 | U13: =U12 -> 422437 | V13: =U13-U12 -> 0 | W13: =W12 -> 32246 | X13: =W13-W12 -> 0 | Y13: =Y12 -> 708475 | Z13: =Y13-Y12 -> 0 | AA13: =AA12 -> 35727 | AB13: =AA13-AA12 -> 0 | AC13: =AC12 -> 921652 | AD13: =AC13-AC12 -> 0 | AE13: =AB13+X13+T13 -> 0 | AF13: =V13+Z13+AD13 -> 0 | AG13: =IF(AE13>0,AF13/AE13,0) -> 0 | AI13: =R13-'EDl log'!B11 -> -918520
A14: ='General information '!F17 -> 0 | B14: =SUM(230*A14) -> 0 | C14: 44267 | D14: =D13 -> 32664458 | E14: =D14-D13 -> 0 | F14: =F13 -> 3976419 | G14: =F14-F13 -> 0 | H14: =H13 -> 17810886 | I14: =H14-H13 -> 0 | J14: =J13 -> 28929882 | K14: =J14-J13 -> 0 | L14: =L13 -> 24069270 | M14: =L14-L13 -> 0 | N14: =M14+K14+I14+G14+E14 -> 0 | O14: =IF(B14>0,N14/B14,0) -> 0 | P14: =P13 -> 16715.519 | Q14: =(P14-P13)*1000 -> 0 | R14: =N14-Q14 -> 0 | S14: =S13 -> 10128 | T14: =S14-S13 -> 0 | U14: =U13 -> 422437 | V14: =U14-U13 -> 0 | W14: =W13 -> 32246 | X14: =W14-W13 -> 0 | Y14: =Y13 -> 708475 | Z14: =Y14-Y13 -> 0 | AA14: =AA13 -> 35727 | AB14: =AA14-AA13 -> 0 | AC14: =AC13 -> 921652 | AD14: =AC14-AC13 -> 0 | AE14: =AB14+X14+T14 -> 0 | AF14: =V14+Z14+AD14 -> 0 | AG14: =IF(AE14>0,AF14/AE14,0) -> 0 | AI14: =R14-'EDl log'!B12 -> -918520
A15: ='General information '!F18 -> 0 | B15: =SUM(230*A15) -> 0 | C15: 44268 | D15: =D14 -> 32664458 | E15: =D15-D14 -> 0 | F15: =F14 -> 3976419 | G15: =F15-F14 -> 0 | H15: =H14 -> 17810886 | I15: =H15-H14 -> 0 | J15: =J14 -> 28929882 | K15: =J15-J14 -> 0 | L15: =L14 -> 24069270 | M15: =L15-L14 -> 0 | N15: =M15+K15+I15+G15+E15 -> 0 | O15: =IF(B15>0,N15/B15,0) -> 0 | P15: =P14 -> 16715.519 | Q15: =(P15-P14)*1000 -> 0 | R15: =N15-Q15 -> 0 | S15: =S14 -> 10128 | T15: =S15-S14 -> 0 | U15: =U14 -> 422437 | V15: =U15-U14 -> 0 | W15: =W14 -> 32246 | X15: =W15-W14 -> 0 | Y15: =Y14 -> 708475 | Z15: =Y15-Y14 -> 0 | AA15: =AA14 -> 35727 | AB15: =AA15-AA14 -> 0 | AC15: =AC14 -> 921652 | AD15: =AC15-AC14 -> 0 | AE15: =AB15+X15+T15 -> 0 | AF15: =V15+Z15+AD15 -> 0 | AG15: =IF(AE15>0,AF15/AE15,0) -> 0 | AI15: =R15-'EDl log'!B13 -> -918520
A16: ='General information '!F19 -> 0 | B16: =SUM(230*A16) -> 0 | C16: 44269 | D16: =D15 -> 32664458 | E16: =D16-D15 -> 0 | F16: =F15 -> 3976419 | G16: =F16-F15 -> 0 | H16: =H15 -> 17810886 | I16: =H16-H15 -> 0 | J16: =J15 -> 28929882 | K16: =J16-J15 -> 0 | L16: =L15 -> 24069270 | M16: =L16-L15 -> 0 | N16: =M16+K16+I16+G16+E16 -> 0 | O16: =IF(B16>0,N16/B16,0) -> 0 | P16: =P15 -> 16715.519 | Q16: =(P16-P15)*1000 -> 0 | R16: =N16-Q16 -> 0 | S16: =S15 -> 10128 | T16: =S16-S15 -> 0 | U16: =U15 -> 422437 | V16: =U16-U15 -> 0 | W16: =W15 -> 32246 | X16: =W16-W15 -> 0 | Y16: =Y15 -> 708475 | Z16: =Y16-Y15 -> 0 | AA16: =AA15 -> 35727 | AB16: =AA16-AA15 -> 0 | AC16: =AC15 -> 921652 | AD16: =AC16-AC15 -> 0 | AE16: =AB16+X16+T16 -> 0 | AF16: =V16+Z16+AD16 -> 0 | AG16: =IF(AE16>0,AF16/AE16,0) -> 0 | AI16: =R16-'EDl log'!B14 -> -918520
A17: ='General information '!F20 -> 0 | B17: =SUM(230*A17) -> 0 | C17: 44270 | D17: =D16 -> 32664458 | E17: =D17-D16 -> 0 | F17: =F16 -> 3976419 | G17: =F17-F16 -> 0 | H17: =H16 -> 17810886 | I17: =H17-H16 -> 0 | J17: =J16 -> 28929882 | K17: =J17-J16 -> 0 | L17: =L16 -> 24069270 | M17: =L17-L16 -> 0 | N17: =M17+K17+I17+G17+E17 -> 0 | O17: =IF(B17>0,N17/B17,0) -> 0 | P17: =P16 -> 16715.519 | Q17: =(P17-P16)*1000 -> 0 | R17: =N17-Q17 -> 0 | S17: =S16 -> 10128 | T17: =S17-S16 -> 0 | U17: =U16 -> 422437 | V17: =U17-U16 -> 0 | W17: =W16 -> 32246 | X17: =W17-W16 -> 0 | Y17: =Y16 -> 708475 | Z17: =Y17-Y16 -> 0 | AA17: =AA16 -> 35727 | AB17: =AA17-AA16 -> 0 | AC17: =AC16 -> 921652 | AD17: =AC17-AC16 -> 0 | AE17: =AB17+X17+T17 -> 0 | AF17: =V17+Z17+AD17 -> 0 | AG17: =IF(AE17>0,AF17/AE17,0) -> 0 | AI17: =R17-'EDl log'!B15 -> -918520
A18: ='General information '!F21 -> 0 | B18: =SUM(230*A18) -> 0 | C18: 44271 | D18: =D17 -> 32664458 | E18: =D18-D17 -> 0 | F18: =F17 -> 3976419 | G18: =F18-F17 -> 0 | H18: =H17 -> 17810886 | I18: =H18-H17 -> 0 | J18: =J17 -> 28929882 | K18: =J18-J17 -> 0 | L18: =L17 -> 24069270 | M18: =L18-L17 -> 0 | N18: =M18+K18+I18+G18+E18 -> 0 | O18: =IF(B18>0,N18/B18,0) -> 0 | P18: =P17 -> 16715.519 | Q18: =(P18-P17)*1000 -> 0 | R18: =N18-Q18 -> 0 | S18: =S17 -> 10128 | T18: =S18-S17 -> 0 | U18: =U17 -> 422437 | V18: =U18-U17 -> 0 | W18: =W17 -> 32246 | X18: =W18-W17 -> 0 | Y18: =Y17 -> 708475 | Z18: =Y18-Y17 -> 0 | AA18: =AA17 -> 35727 | AB18: =AA18-AA17 -> 0 | AC18: =AC17 -> 921652 | AD18: =AC18-AC17 -> 0 | AE18: =AB18+X18+T18 -> 0 | AF18: =V18+Z18+AD18 -> 0 | AG18: =IF(AE18>0,AF18/AE18,0) -> 0 | AI18: =R18-'EDl log'!B16 -> -918520
A19: ='General information '!F22 -> 0 | B19: =SUM(230*A19) -> 0 | C19: 44272 | D19: =D18 -> 32664458 | E19: =D19-D18 -> 0 | F19: =F18 -> 3976419 | G19: =F19-F18 -> 0 | H19: =H18 -> 17810886 | I19: =H19-H18 -> 0 | J19: =J18 -> 28929882 | K19: =J19-J18 -> 0 | L19: =L18 -> 24069270 | M19: =L19-L18 -> 0 | N19: =M19+K19+I19+G19+E19 -> 0 | O19: =IF(B19>0,N19/B19,0) -> 0 | P19: =P18 -> 16715.519 | Q19: =(P19-P18)*1000 -> 0 | R19: =N19-Q19 -> 0 | S19: =S18 -> 10128 | T19: =S19-S18 -> 0 | U19: =U18 -> 422437 | V19: =U19-U18 -> 0 | W19: =W18 -> 32246 | X19: =W19-W18 -> 0 | Y19: =Y18 -> 708475 | Z19: =Y19-Y18 -> 0 | AA19: =AA18 -> 35727 | AB19: =AA19-AA18 -> 0 | AC19: =AC18 -> 921652 | AD19: =AC19-AC18 -> 0 | AE19: =AB19+X19+T19 -> 0 | AF19: =V19+Z19+AD19 -> 0 | AG19: =IF(AE19>0,AF19/AE19,0) -> 0 | AI19: =R19-'EDl log'!B17 -> -918520
A20: ='General information '!F23 -> 0 | B20: =SUM(230*A20) -> 0 | C20: 44273 | D20: =D19 -> 32664458 | E20: =D20-D19 -> 0 | F20: =F19 -> 3976419 | G20: =F20-F19 -> 0 | H20: =H19 -> 17810886 | I20: =H20-H19 -> 0 | J20: =J19 -> 28929882 | K20: =J20-J19 -> 0 | L20: =L19 -> 24069270 | M20: =L20-L19 -> 0 | N20: =M20+K20+I20+G20+E20 -> 0 | O20: =IF(B20>0,N20/B20,0) -> 0 | P20: =P19 -> 16715.519 | Q20: =(P20-P19)*1000 -> 0 | R20: =N20-Q20 -> 0 | S20: =S19 -> 10128 | T20: =S20-S19 -> 0 | U20: =U19 -> 422437 | V20: =U20-U19 -> 0 | W20: =W19 -> 32246 | X20: =W20-W19 -> 0 | Y20: =Y19 -> 708475 | Z20: =Y20-Y19 -> 0 | AA20: =AA19 -> 35727 | AB20: =AA20-AA19 -> 0 | AC20: =AC19 -> 921652 | AD20: =AC20-AC19 -> 0 | AE20: =AB20+X20+T20 -> 0 | AF20: =V20+Z20+AD20 -> 0 | AG20: =IF(AE20>0,AF20/AE20,0) -> 0 | AI20: =R20-'EDl log'!B18 -> -918520
A21: ='General information '!F24 -> 0 | B21: =SUM(230*A21) -> 0 | C21: 44274 | D21: =D20 -> 32664458 | E21: =D21-D20 -> 0 | F21: =F20 -> 3976419 | G21: =F21-F20 -> 0 | H21: =H20 -> 17810886 | I21: =H21-H20 -> 0 | J21: =J20 -> 28929882 | K21: =J21-J20 -> 0 | L21: =L20 -> 24069270 | M21: =L21-L20 -> 0 | N21: =M21+K21+I21+G21+E21 -> 0 | O21: =IF(B21>0,N21/B21,0) -> 0 | P21: =P20 -> 16715.519 | Q21: =(P21-P20)*1000 -> 0 | R21: =N21-Q21 -> 0 | S21: =S20 -> 10128 | T21: =S21-S20 -> 0 | U21: =U20 -> 422437 | V21: =U21-U20 -> 0 | W21: =W20 -> 32246 | X21: =W21-W20 -> 0 | Y21: =Y20 -> 708475 | Z21: =Y21-Y20 -> 0 | AA21: =AA20 -> 35727 | AB21: =AA21-AA20 -> 0 | AC21: =AC20 -> 921652 | AD21: =AC21-AC20 -> 0 | AE21: =AB21+X21+T21 -> 0 | AF21: =V21+Z21+AD21 -> 0 | AG21: =IF(AE21>0,AF21/AE21,0) -> 0 | AI21: =R21-'EDl log'!B19 -> -918520
A22: ='General information '!F25 -> 0 | B22: =SUM(230*A22) -> 0 | C22: 44275 | D22: =D21 -> 32664458 | E22: =D22-D21 -> 0 | F22: =F21 -> 3976419 | G22: =F22-F21 -> 0 | H22: =H21 -> 17810886 | I22: =H22-H21 -> 0 | J22: =J21 -> 28929882 | K22: =J22-J21 -> 0 | L22: =L21 -> 24069270 | M22: =L22-L21 -> 0 | N22: =M22+K22+I22+G22+E22 -> 0 | O22: =IF(B22>0,N22/B22,0) -> 0 | P22: =P21 -> 16715.519 | Q22: =(P22-P21)*1000 -> 0 | R22: =N22-Q22 -> 0 | S22: =S21 -> 10128 | T22: =S22-S21 -> 0 | U22: =U21 -> 422437 | V22: =U22-U21 -> 0 | W22: =W21 -> 32246 | X22: =W22-W21 -> 0 | Y22: =Y21 -> 708475 | Z22: =Y22-Y21 -> 0 | AA22: =AA21 -> 35727 | AB22: =AA22-AA21 -> 0 | AC22: =AC21 -> 921652 | AD22: =AC22-AC21 -> 0 | AE22: =AB22+X22+T22 -> 0 | AF22: =V22+Z22+AD22 -> 0 | AG22: =IF(AE22>0,AF22/AE22,0) -> 0 | AI22: =R22-'EDl log'!B20 -> -918520
... A30: ='General information '!F33 -> 0 | B30: =SUM(230*A30) -> 0 | C30: 44283 | D30: =D29 -> 32664458 | E30: =D30-D29 -> 0 | F30: =F29 -> 3976419 | G30: =F30-F29 -> 0 | H30: =H29 -> 17810886 | I30: =H30-H29 -> 0 | J30: =J29 -> 28929882 | K30: =J30-J29 -> 0 | L30: =L29 -> 24069270 | M30: =L30-L29 -> 0 | N30: =M30+K30+I30+G30+E30 -> 0 | O30: =IF(B30>0,N30/B30,0) -> 0 | P30: =P29 -> 16715.519 | Q30: =(P30-P29)*1000 -> 0 | R30: =N30-Q30 -> 0 | S30: =S29 -> 10128 | T30: =S30-S29 -> 0 | U30: =U29 -> 422437 | V30: =U30-U29 -> 0 | W30: =W29 -> 32246 | X30: =W30-W29 -> 0 | Y30: =Y29 -> 708475 | Z30: =Y30-Y29 -> 0 | AA30: =AA29 -> 35727 | AB30: =AA30-AA29 -> 0 | AC30: =AC29 -> 921652 | AD30: =AC30-AC29 -> 0 | AE30: =AB30+X30+T30 -> 0 | AF30: =V30+Z30+AD30 -> 0 | AG30: =IF(AE30>0,AF30/AE30,0) -> 0 | AI30: =R30-'EDl log'!B28 -> -918520
C31: 44284 | D31: =D30 -> 32664458 | E31: =D31-D30 -> 0 | F31: =F30 -> 3976419 | G31: =F31-F30 -> 0 | H31: =H30 -> 17810886 | I31: =H31-H30 -> 0 | J31: =J30 -> 28929882 | K31: =J31-J30 -> 0 | L31: =L30 -> 24069270 | M31: =L31-L30 -> 0 | N31: =M31+K31+I31+G31+E31 -> 0 | O31: =IF(B31>0,N31/B31,0) -> 0 | P31: =P30 -> 16715.519 | Q31: =(P31-P30)*1000 -> 0 | R31: =N31-Q31 -> 0 | S31: =S30 -> 10128 | T31: =S31-S30 -> 0 | U31: =U30 -> 422437 | V31: =U31-U30 -> 0 | W31: =W30 -> 32246 | X31: =W31-W30 -> 0 | Y31: =Y30 -> 708475 | Z31: =Y31-Y30 -> 0 | AA31: =AA30 -> 35727 | AB31: =AA31-AA30 -> 0 | AC31: =AC30 -> 921652 | AD31: =AC31-AC30 -> 0 | AE31: =AB31+X31+T31 -> 0 | AF31: =V31+Z31+AD31 -> 0 | AG31: =IF(AE31>0,AF31/AE31,0) -> 0 | AI31: =R31-'EDl log'!B29 -> -918520
C32: 44285 | D32: =D31 -> 32664458 | E32: =D32-D31 -> 0 | F32: =F31 -> 3976419 | G32: =F32-F31 -> 0 | H32: =H31 -> 17810886 | I32: =H32-H31 -> 0 | J32: =J31 -> 28929882 | K32: =J32-J31 -> 0 | L32: =L31 -> 24069270 | M32: =L32-L31 -> 0 | N32: =M32+K32+I32+G32+E32 -> 0 | O32: =IF(B32>0,N32/B32,0) -> 0 | P32: =P31 -> 16715.519 | Q32: =(P32-P31)*1000 -> 0 | R32: =N32-Q32 -> 0 | S32: =S31 -> 10128 | T32: =S32-S31 -> 0 | U32: =U31 -> 422437 | V32: =U32-U31 -> 0 | W32: =W31 -> 32246 | X32: =W32-W31 -> 0 | Y32: =Y31 -> 708475 | Z32: =Y32-Y31 -> 0 | AA32: =AA31 -> 35727 | AB32: =AA32-AA31 -> 0 | AC32: =AC31 -> 921652 | AD32: =AC32-AC31 -> 0 | AE32: =AB32+X32+T32 -> 0 | AF32: =V32+Z32+AD32 -> 0 | AG32: =IF(AE32>0,AF32/AE32,0) -> 0 | AI32: =R32-'EDl log'!B30 -> -918520
C33: 44286 | D33: =D32 -> 32664458 | E33: =D33-D32 -> 0 | F33: =F32 -> 3976419 | G33: =F33-F32 -> 0 | H33: =H32 -> 17810886 | I33: =H33-H32 -> 0 | J33: =J32 -> 28929882 | K33: =J33-J32 -> 0 | L33: =L32 -> 24069270 | M33: =L33-L32 -> 0 | N33: =M33+K33+I33+G33+E33 -> 0 | O33: =IF(B33>0,N33/B33,0) -> 0 | P33: =P32 -> 16715.519 | Q33: =(P33-P32)*1000 -> 0 | R33: =N33-Q33 -> 0 | S33: =S32 -> 10128 | T33: =S33-S32 -> 0 | U33: =U32 -> 422437 | V33: =U33-U32 -> 0 | W33: =W32 -> 32246 | X33: =W33-W32 -> 0 | Y33: =Y32 -> 708475 | Z33: =Y33-Y32 -> 0 | AA33: =AA32 -> 35727 | AB33: =AA33-AA32 -> 0 | AC33: =AC32 -> 921652 | AD33: =AC33-AC32 -> 0 | AE33: =AB33+X33+T33 -> 0 | AF33: =V33+Z33+AD33 -> 0 | AG33: =IF(AE33>0,AF33/AE33,0) -> 0 | AI33: =R33-'EDl log'!B31 -> -918520

Sheet B5
F1: Boiler A | J1: =J37 -> 58.694444 | K1: Boiler B | P1: Boiler C | V1: Boiler | X1: SteamA | AC1: SteamB | AH1: Steam | AI1: Boiler & steam | AL1: Total Boiler Runing H | AM1: Total Steam Runing H | AN1: GAS1 % | AO1: GAS1/L | AP1: GAS2% | AQ1: Gas2/L | AR1: GAS3% | AS1: GAS3/L | AU1: Gas Cons | AV1: Delivery | AW1: Cost/L
B2: Level Tank Gen | C2: Level tank Boiler | D2: Daily Cons Bo. | E2: Boiler litter | F2: Boiler A | G2: Run Hr a | H2: Boiler A fuel | I2: Daily consumption | J2: AVG | K2: index Run H | L2: Run Hrb | M2: Boiler B Fuel | O2: Daily consumption | P2: Boiler C | S2: Run C | U2: Total RH | V2: Total Fuel | X2: SteamA | Y2: Run SA | Z2: Steam A Conter | AA2: Liters | AC2: SteamB | AD2: Run SteamB | AE2: Steam B Conter | AF2: SB Litters | AG2: Avg | AH2: Total Fuel | AI2: Total Fuel
S3: 0
A4: =ELEC!C2 -> 44255 | B4: =[1]B5!B32 -> 218 | C4: =[1]B5!C32 -> 225 | D4: =[1]B5!D32 -> 6 | E4: =[1]B5!E32 -> 50.28 | F4: =[1]B5!F32 -> 1749 | G4: =[1]B5!G32 -> 0 | H4: =[1]B5!H32 -> 6488 | I4: =[1]B5!I32 -> 26 | ... AX4: =[1]B5!AX32 -> 0.8
A5: =ELEC!C3 -> 44256 | B5: 209 | C5: 206 | D5: =C4-C5 -> 19 | E5: =D5*8.38 -> 159.22 | F5: 1752 | G5: =F5-F4 -> 3 | H5: 6668 | I5: =SUM(H5-H4) -> 180 | J5: 1 | K5: =K4 -> 2246 | L5: =K5-K4 -> 0 | M5: =M4 -> 165218 | N5: =M5-M4 -> 0 | O5: =O4 -> 1869 | P5: 2002 | Q5: 169047 | R5: =Q5-Q4 -> 64 | S5: =SUM(P5-P4) -> 1 | T5: =SUM(S5*$T$2) -> 0 | U5: =SUM(G5+L5+S5) -> 4 | V5: =R5+N5+I5:I5 -> 244 | W5: =SUM(V5/U5) -> 61 | X5: 2459 | Y5: =X5-X4 -> 3 | Z5: 138315 | AA5: =Z5-Z4 -> 176.2 | AB5: =SUM(Y5*$AB$2) -> 0 | AC5: =AC4 -> 1935 | AD5: =AC5-AC4 -> 0 | AE5: =AE4 -> 365429 | AF5: =AE5-AE4 -> 0 | AG5: =IF(AD5>0,AF5/AD5,0) -> 0 | AH5: =AF5+AA5 -> 176.2 | AI5: =SUM(AH5+V5) -> 420.2 | AJ5: =-tanks!AW6 -> 420.2 | AK5: =SUM(AJ5-AI5) -> 0 | AL5: =S5+L5+G5 -> 4 | AM5: =Y5+AD5 -> 3 | AN5: =AN4 -> 67 | AO5: =(AN5/100)*3000 -> 2010 | AP5: =AP4 -> 55 | AQ5: =(AP5/100)*3000 -> 1650 | AR5: =AR4 -> 61 | AS5: =(AR5/100)*3000 -> 1830 | AT5: =SUM(AO5+AQ5+AS5) -> 5490 | AU5: =AT4-AT5+AV5 -> 0 | AX5: =IF(AV5>0,AW5,AX4) -> 0.8
A6: =ELEC!C4 -> 44257 | B6: 199 | C6: 205 | D6: =C5-C6 -> 1 | E6: =D6*8.38 -> 8.38 | F6: 1753 | G6: =F6-F5 -> 1 | H6: 6720 | I6: =SUM(H6-H5) -> 52 | J6: =IF(G6>0,I6/G6,0) -> 52 | K6: 2248 | L6: =K6-K5 -> 2 | M6: 165407 | N6: =M6-M5 -> 189 | O6: =O5 -> 1869 | P6: =P5 -> 2002 | Q6: =Q5 -> 169047 | R6: =Q6-Q5 -> 0 | S6: =SUM(P6-P5) -> 0 | T6: =SUM(S6*$T$2) -> 0 | U6: =SUM(G6+L6+S6) -> 3 | V6: =R6+N6+I6:I6 -> 241 | W6: =SUM(V6/U6) -> 80.333333 | X6: 2461 | Y6: =X6-X5 -> 2 | Z6: 138425 | AA6: =Z6-Z5 -> 110 | AB6: =SUM(Y6*$AB$2) -> 0 | AC6: =AC5 -> 1935 | AD6: =AC6-AC5 -> 0 | AE6: =AE5 -> 365429 | AF6: =AE6-AE5 -> 0 | AG6: =IF(AD6>0,AF6/AD6,0) -> 0 | AH6: =AF6+AA6 -> 110 | AI6: =SUM(AH6+V6) -> 351 | AJ6: =-tanks!AW7 -> 351 | AK6: =SUM(AJ6-AI6) -> 0 | AL6: =S6+L6+G6 -> 3 | AM6: =Y6+AD6 -> 2 | AN6: =AN5 -> 67 | AO6: =(AN6/100)*3000 -> 2010 | AP6: =AP5 -> 55 | AQ6: =(AP6/100)*3000 -> 1650 | AR6: =AR5 -> 61 | AS6: =(AR6/100)*3000 -> 1830 | AT6: =SUM(AO6+AQ6+AS6) -> 5490 | AU6: =AT5-AT6+AV6 -> 0 | AX6: =IF(AV6>0,AW6,AX5) -> 0.8
A7: =ELEC!C5 -> 44258 | B7: 193 | C7: 199 | D7: =C6-C7 -> 6 | E7: =D7*8.38 -> 50.28 | F7: =F6 -> 1753 | G7: =F7-F6 -> 0 | H7: =H6 -> 6720 | I7: =SUM(H7-H6) -> 0 | J7: =IF(G7>0,I7/G7,0) -> 0 | K7: 2249 | L7: =K7-K6 -> 1 | M7: 165481 | N7: =M7-M6 -> 74 | O7: =O6 -> 1869 | P7: 2004 | Q7: 169189 | R7: =Q7-Q6 -> 142 | S7: =SUM(P7-P6) -> 2 | T7: =SUM(S7*$T$2) -> 0 | U7: =SUM(G7+L7+S7) -> 3 | V7: =R7+N7+I7:I7 -> 216 | W7: =SUM(V7/U7) -> 72 | X7: =X6 -> 2461 | Y7: =X7-X6 -> 0 | Z7: =Z6 -> 138425 | AA7: =Z7-Z6 -> 0 | AB7: =SUM(Y7*$AB$2) -> 0 | AC7: =AC6 -> 1935 | AD7: =AC7-AC6 -> 0 | AE7: =AE6 -> 365429 | AF7: =AE7-AE6 -> 0 | AG7: =IF(AD7>0,AF7/AD7,0) -> 0 | AH7: =AF7+AA7 -> 0 | AI7: =SUM(AH7+V7) -> 216 | AJ7: =-tanks!AW8 -> 216 | AK7: =SUM(AJ7-AI7) -> 0 | AL7: =S7+L7+G7 -> 3 | AM7: =Y7+AD7 -> 0 | AN7: =AN6 -> 67 | AO7: =(AN7/100)*3000 -> 2010 | AP7: =AP6 -> 55 | AQ7: =(AP7/100)*3000 -> 1650 | AR7: =AR6 -> 61 | AS7: =(AR7/100)*3000 -> 1830 | AT7: =SUM(AO7+AQ7+AS7) -> 5490 | AU7: =AT6-AT7+AV7 -> 0 | AX7: =IF(AV7>0,AW7,AX6) -> 0.8
A8: =ELEC!C6 -> 44259 | B8: 187 | C8: 194 | D8: =C7-C8 -> 5 | E8: =D8*8.38 -> 41.9 | F8: 1755 | G8: =F8-F7 -> 2 | H8: 6869 | I8: =SUM(H8-H7) -> 149 | J8: =IF(G8>0,I8/G8,0) -> 74.5 | K8: =K7 -> 2249 | L8: =K8-K7 -> 0 | M8: =M7 -> 165481 | N8: =M8-M7 -> 0 | O8: =O7 -> 1869 | P8: 2005 | Q8: 169314 | R8: =Q8-Q7 -> 125 | S8: =SUM(P8-P7) -> 1 | T8: =SUM(S8*$T$2) -> 0 | U8: =SUM(G8+L8+S8) -> 3 | V8: =R8+N8+I8:I8 -> 274 | W8: =SUM(V8/U8) -> 91.333333 | X8: =X7 -> 2461 | Y8: =X8-X7 -> 0 | Z8: =Z7 -> 138425 | AA8: =Z8-Z7 -> 0 | AB8: =SUM(Y8*$AB$2) -> 0 | AC8: =AC7 -> 1935 | AD8: =AC8-AC7 -> 0 | AE8: 365467 | AF8: =AE8-AE7 -> 38 | AG8: =IF(AD8>0,AF8/AD8,0) -> 0 | AH8: =AF8+AA8 -> 38 | AI8: =SUM(AH8+V8) -> 312 | AJ8: =-tanks!AW9 -> 312 | AK8: =SUM(AJ8-AI8) -> 0 | AL8: =S8+L8+G8 -> 3 | AM8: =Y8+AD8 -> 0 | AN8: =AN7 -> 67 | AO8: =(AN8/100)*3000 -> 2010 | AP8: =AP7 -> 55 | AQ8: =(AP8/100)*3000 -> 1650 | AR8: =AR7 -> 61 | AS8: =(AR8/100)*3000 -> 1830 | AT8: =SUM(AO8+AQ8+AS8) -> 5490 | AU8: =AT7-AT8+AV8 -> 0 | AX8: =IF(AV8>0,AW8,AX7) -> 0.8
A9: =ELEC!C7 -> 44260 | B9: 208 | C9: 214 | D9: =C8-C9 -> -20 | E9: =D9*8.38 -> -167.6 | F9: 1756 | G9: =F9-F8 -> 1 | H9: 6937 | I9: =SUM(H9-H8) -> 68 | J9: =IF(G9>0,I9/G9,0) -> 68 | K9: 2251 | L9: =K9-K8 -> 2 | M9: 165621 | N9: =M9-M8 -> 140 | O9: =O8 -> 1869 | P9: 2006 | Q9: 169344 | R9: =Q9-Q8 -> 30 | S9: =SUM(P9-P8) -> 1 | T9: =SUM(S9*$T$2) -> 0 | U9: =SUM(G9+L9+S9) -> 4 | V9: =R9+N9+I9:I9 -> 238 | W9: =SUM(V9/U9) -> 59.5 | X9: =X8 -> 2461 | Y9: =X9-X8 -> 0 | Z9: =Z8 -> 138425 | AA9: =Z9-Z8 -> 0 | AB9: =SUM(Y9*$AB$2) -> 0 | AC9: =AC8 -> 1935 | AD9: =AC9-AC8 -> 0 | AE9: =AE8 -> 365467 | AF9: =AE9-AE8 -> 0 | AG9: =IF(AD9>0,AF9/AD9,0) -> 0 | AH9: =AF9+AA9 -> 0 | AI9: =SUM(AH9+V9) -> 238 | AJ9: =-tanks!AW10 -> 238 | AK9: =SUM(AJ9-AI9) -> 0 | AL9: =S9+L9+G9 -> 4 | AM9: =Y9+AD9 -> 0 | AN9: =AN8 -> 67 | AO9: =(AN9/100)*3000 -> 2010 | AP9: =AP8 -> 55 | AQ9: =(AP9/100)*3000 -> 1650 | AR9: =AR8 -> 61 | AS9: =(AR9/100)*3000 -> 1830 | AT9: =SUM(AO9+AQ9+AS9) -> 5490 | AU9: =AT8-AT9+AV9 -> 0 | AX9: =IF(AV9>0,AW9,AX8) -> 0.8
A10: =ELEC!C8 -> 44261 | B10: 202 | C10: 208 | D10: =C9-C10 -> 6 | E10: =D10*8.38 -> 50.28 | F10: =F9 -> 1756 | G10: =F10-F9 -> 0 | H10: 6975 | I10: =SUM(H10-H9) -> 38 | J10: =IF(G10>0,I10/G10,0) -> 0 | K10: 2252 | L10: =K10-K9 -> 1 | M10: 165709 | N10: =M10-M9 -> 88 | O10: =O9 -> 1869 | P10: 2007 | Q10: 169446 | R10: =Q10-Q9 -> 102 | S10: =SUM(P10-P9) -> 1 | T10: =SUM(S10*$T$2) -> 0 | U10: =SUM(G10+L10+S10) -> 2 | V10: =R10+N10+I10:I10 -> 228 | W10: =SUM(V10/U10) -> 114 | X10: =X9 -> 2461 | Y10: =X10-X9 -> 0 | Z10: =Z9 -> 138425 | AA10: =Z10-Z9 -> 0 | AB10: =SUM(Y10*$AB$2) -> 0 | AC10: =AC9 -> 1935 | AD10: =AC10-AC9 -> 0 | AE10: =AE9 -> 365467 | AF10: =AE10-AE9 -> 0 | AG10: =IF(AD10>0,AF10/AD10,0) -> 0 | AH10: =AF10+AA10 -> 0 | AI10: =SUM(AH10+V10) -> 228 | AJ10: =-tanks!AW11 -> 228 | AK10: =SUM(AJ10-AI10) -> 0 | AL10: =S10+L10+G10 -> 2 | AM10: =Y10+AD10 -> 0 | AN10: =AN9 -> 67 | AO10: =(AN10/100)*3000 -> 2010 | AP10: =AP9 -> 55 | AQ10: =(AP10/100)*3000 -> 1650 | AR10: =AR9 -> 61 | AS10: =(AR10/100)*3000 -> 1830 | AT10: =SUM(AO10+AQ10+AS10) -> 5490 | AU10: =AT9-AT10+AV10 -> 0 | AX10: =IF(AV10>0,AW10,AX9) -> 0.8
A11: =ELEC!C9 -> 44262 | B11: 199 | C11: 205 | D11: =C10-C11 -> 3 | E11: =D11*8.38 -> 25.14 | F11: 1759 | G11: =F11-F10 -> 3 | H11: 7205 | I11: =SUM(H11-H10) -> 230 | J11: =IF(G11>0,I11/G11,0) -> 76.666667 | K11: =K10 -> 2252 | L11: =K11-K10 -> 0 | M11: =M10 -> 165709 | N11: =M11-M10 -> 0 | O11: =O10 -> 1869 | P11: =P10 -> 2007 | Q11: =Q10 -> 169446 | R11: =Q11-Q10 -> 0 | S11: =SUM(P11-P10) -> 0 | T11: =SUM(S11*$T$2) -> 0 | U11: =SUM(G11+L11+S11) -> 3 | V11: =R11+N11+I11:I11 -> 230 | W11: =SUM(V11/U11) -> 76.666667 | X11: =X10 -> 2461 | Y11: =X11-X10 -> 0 | Z11: =Z10 -> 138425 | AA11: =Z11-Z10 -> 0 | AB11: =SUM(Y11*$AB$2) -> 0 | AC11: =AC10 -> 1935 | AD11: =AC11-AC10 -> 0 | AE11: =AE10 -> 365467 | AF11: =AE11-AE10 -> 0 | AG11: =IF(AD11>0,AF11/AD11,0) -> 0 | AH11: =AF11+AA11 -> 0 | AI11: =SUM(AH11+V11) -> 230 | AJ11: =-tanks!AW12 -> 230 | AK11: =SUM(AJ11-AI11) -> 0 | AL11: =S11+L11+G11 -> 3 | AM11: =Y11+AD11 -> 0 | AN11: =AN10 -> 67 | AO11: =(AN11/100)*3000 -> 2010 | AP11: =AP10 -> 55 | AQ11: =(AP11/100)*3000 -> 1650 | AR11: =AR10 -> 61 | AS11: =(AR11/100)*3000 -> 1830 | AT11: =SUM(AO11+AQ11+AS11) -> 5490 | AU11: =AT10-AT11+AV11 -> 0 | AX11: =IF(AV11>0,AW11,AX10) -> 0.8
A12: =ELEC!C10 -> 44263 | B12: 194.5 | C12: 201 | D12: =C11-C12 -> 4 | E12: =D12*8.38 -> 33.52 | F12: 1760 | G12: =F12-F11 -> 1 | H12: 7285 | I12: =SUM(H12-H11) -> 80 | J12: =IF(G12>0,I12/G12,0) -> 80 | K12: 2254 | L12: =K12-K11 -> 2 | M12: 165849 | N12: =M12-M11 -> 140 | O12: =O11 -> 1869 | P12: 2008 | Q12: 169516 | R12: =Q12-Q11 -> 70 | S12: =SUM(P12-P11) -> 1 | T12: =SUM(S12*$T$2) -> 0 | U12: =SUM(G12+L12+S12) -> 4 | V12: =R12+N12+I12:I12 -> 290 | W12: =SUM(V12/U12) -> 72.5 | X12: =X11 -> 2461 | Y12: =X12-X11 -> 0 | Z12: =Z11 -> 138425 | AA12: =Z12-Z11 -> 0 | AB12: =SUM(Y12*$AB$2) -> 0 | AC12: =AC11 -> 1935 | AD12: =AC12-AC11 -> 0 | AE12: =AE11 -> 365467 | AF12: =AE12-AE11 -> 0 | AG12: =IF(AD12>0,AF12/AD12,0) -> 0 | AH12: =AF12+AA12 -> 0 | AI12: =SUM(AH12+V12) -> 290 | AJ12: =-tanks!AW13 -> 290 | AK12: =SUM(AJ12-AI12) -> 0 | AL12: =S12+L12+G12 -> 4 | AM12: =Y12+AD12 -> 0 | AN12: =AN11 -> 67 | AO12: =(AN12/100)*3000 -> 2010 | AP12: =AP11 -> 55 | AQ12: =(AP12/100)*3000 -> 1650 | AR12: =AR11 -> 61 | AS12: =(AR12/100)*3000 -> 1830 | AT12: =SUM(AO12+AQ12+AS12) -> 5490 | AU12: =AT11-AT12+AV12 -> 0 | AX12: =IF(AV12>0,AW12,AX11) -> 0.8
A13: =ELEC!C11 -> 44264 | B13: =B12 -> 194.5 | C13: =C12 -> 201 | D13: =C12-C13 -> 0 | E13: =D13*8.38 -> 0 | F13: =F12 -> 1760 | G13: =F13-F12 -> 0 | H13: =H12 -> 7285 | I13: =SUM(H13-H12) -> 0 | J13: =IF(G13>0,I13/G13,0) -> 0 | K13: =K12 -> 2254 | L13: =K13-K12 -> 0 | M13: =M12 -> 165849 | N13: =M13-M12 -> 0 | O13: =O12 -> 1869 | P13: =P12 -> 2008 | Q13: =Q12 -> 169516 | R13: =Q13-Q12 -> 0 | S13: =SUM(P13-P12) -> 0 | T13: =SUM(S13*$T$2) -> 0 | U13: =SUM(G13+L13+S13) -> 0 | V13: =R13+N13+I13:I13 -> 0 | W13: =SUM(V13/U13) -> #DIV/0! | X13: =X12 -> 2461 | Y13: =X13-X12 -> 0 | Z13: =Z12 -> 138425 | AA13: =Z13-Z12 -> 0 | AB13: =SUM(Y13*$AB$2) -> 0 | AC13: =AC12 -> 1935 | AD13: =AC13-AC12 -> 0 | AE13: =AE12 -> 365467 | AF13: =AE13-AE12 -> 0 | AG13: =IF(AD13>0,AF13/AD13,0) -> 0 | AH13: =AF13+AA13 -> 0 | AI13: =SUM(AH13+V13) -> 0 | AJ13: =-tanks!AW14 -> 0 | AK13: =SUM(AJ13-AI13) -> 0 | AL13: =S13+L13+G13 -> 0 | AM13: =Y13+AD13 -> 0 | AN13: =AN12 -> 67 | AO13: =(AN13/100)*3000 -> 2010 | AP13: =AP12 -> 55 | AQ13: =(AP13/100)*3000 -> 1650 | AR13: =AR12 -> 61 | AS13: =(AR13/100)*3000 -> 1830 | AT13: =SUM(AO13+AQ13+AS13) -> 5490 | AU13: =AT12-AT13+AV13 -> 0 | AX13: =IF(AV13>0,AW13,AX12) -> 0.8
A14: =ELEC!C12 -> 44265 | B14: =B13 -> 194.5 | C14: =C13 -> 201 | D14: =C13-C14 -> 0 | E14: =D14*8.38 -> 0 | F14: =F13 -> 1760 | G14: =F14-F13 -> 0 | H14: =H13 -> 7285 | I14: =SUM(H14-H13) -> 0 | J14: =IF(G14>0,I14/G14,0) -> 0 | K14: =K13 -> 2254 | L14: =K14-K13 -> 0 | M14: =M13 -> 165849 | N14: =M14-M13 -> 0 | O14: =O13 -> 1869 | P14: =P13 -> 2008 | Q14: =Q13 -> 169516 | R14: =Q14-Q13 -> 0 | S14: =SUM(P14-P13) -> 0 | T14: =SUM(S14*$T$2) -> 0 | U14: =SUM(G14+L14+S14) -> 0 | V14: =R14+N14+I14:I14 -> 0 | W14: =SUM(V14/U14) -> #DIV/0! | X14: =X13 -> 2461 | Y14: =X14-X13 -> 0 | Z14: =Z13 -> 138425 | AA14: =Z14-Z13 -> 0 | AB14: =SUM(Y14*$AB$2) -> 0 | AC14: =AC13 -> 1935 | AD14: =AC14-AC13 -> 0 | AE14: =AE13 -> 365467 | AF14: =AE14-AE13 -> 0 | AG14: =IF(AD14>0,AF14/AD14,0) -> 0 | AH14: =AF14+AA14 -> 0 | AI14: =SUM(AH14+V14) -> 0 | AJ14: =-tanks!AW15 -> 0 | AK14: =SUM(AJ14-AI14) -> 0 | AL14: =S14+L14+G14 -> 0 | AM14: =Y14+AD14 -> 0 | AN14: =AN13 -> 67 | AO14: =(AN14/100)*3000 -> 2010 | AP14: =AP13 -> 55 | AQ14: =(AP14/100)*3000 -> 1650 | AR14: =AR13 -> 61 | AS14: =(AR14/100)*3000 -> 1830 | AT14: =SUM(AO14+AQ14+AS14) -> 5490 | AU14: =AT13-AT14+AV14 -> 0 | AX14: =IF(AV14>0,AW14,AX13) -> 0.8
A15: =ELEC!C13 -> 44266 | B15: =B14 -> 194.5 | C15: =C14 -> 201 | D15: =C14-C15 -> 0 | E15: =D15*8.38 -> 0 | F15: =F14 -> 1760 | G15: =F15-F14 -> 0 | H15: =H14 -> 7285 | I15: =SUM(H15-H14) -> 0 | J15: =IF(G15>0,I15/G15,0) -> 0 | K15: =K14 -> 2254 | L15: =K15-K14 -> 0 | M15: =M14 -> 165849 | N15: =M15-M14 -> 0 | O15: =O14 -> 1869 | P15: =P14 -> 2008 | Q15: =Q14 -> 169516 | R15: =Q15-Q14 -> 0 | S15: =SUM(P15-P14) -> 0 | T15: =SUM(S15*$T$2) -> 0 | U15: =SUM(G15+L15+S15) -> 0 | V15: =R15+N15+I15:I15 -> 0 | W15: =SUM(V15/U15) -> #DIV/0! | X15: =X14 -> 2461 | Y15: =X15-X14 -> 0 | Z15: =Z14 -> 138425 | AA15: =Z15-Z14 -> 0 | AB15: =SUM(Y15*$AB$2) -> 0 | AC15: =AC14 -> 1935 | AD15: =AC15-AC14 -> 0 | AE15: =AE14 -> 365467 | AF15: =AE15-AE14 -> 0 | AG15: =IF(AD15>0,AF15/AD15,0) -> 0 | AH15: =AF15+AA15 -> 0 | AI15: =SUM(AH15+V15) -> 0 | AJ15: =-tanks!AW16 -> 0 | AK15: =SUM(AJ15-AI15) -> 0 | AL15: =S15+L15+G15 -> 0 | AM15: =Y15+AD15 -> 0 | AN15: =AN14 -> 67 | AO15: =(AN15/100)*3000 -> 2010 | AP15: =AP14 -> 55 | AQ15: =(AP15/100)*3000 -> 1650 | AR15: =AR14 -> 61 | AS15: =(AR15/100)*3000 -> 1830 | AT15: =SUM(AO15+AQ15+AS15) -> 5490 | AU15: =AT14-AT15+AV15 -> 0 | AX15: =IF(AV15>0,AW15,AX14) -> 0.8
A16: =ELEC!C14 -> 44267 | B16: =B15 -> 194.5 | C16: =C15 -> 201 | D16: =C15-C16 -> 0 | E16: =D16*8.38 -> 0 | F16: =F15 -> 1760 | G16: =F16-F15 -> 0 | H16: =H15 -> 7285 | I16: =SUM(H16-H15) -> 0 | J16: =IF(G16>0,I16/G16,0) -> 0 | K16: =K15 -> 2254 | L16: =K16-K15 -> 0 | M16: =M15 -> 165849 | N16: =M16-M15 -> 0 | O16: =O15 -> 1869 | P16: =P15 -> 2008 | Q16: =Q15 -> 169516 | R16: =Q16-Q15 -> 0 | S16: =SUM(P16-P15) -> 0 | T16: =SUM(S16*$T$2) -> 0 | U16: =SUM(G16+L16+S16) -> 0 | V16: =R16+N16+I16:I16 -> 0 | W16: =SUM(V16/U16) -> #DIV/0! | X16: =X15 -> 2461 | Y16: =X16-X15 -> 0 | Z16: =Z15 -> 138425 | AA16: =Z16-Z15 -> 0 | AB16: =SUM(Y16*$AB$2) -> 0 | AC16: =AC15 -> 1935 | AD16: =AC16-AC15 -> 0 | AE16: =AE15 -> 365467 | AF16: =AE16-AE15 -> 0 | AG16: =IF(AD16>0,AF16/AD16,0) -> 0 | AH16: =AF16+AA16 -> 0 | AI16: =SUM(AH16+V16) -> 0 | AJ16: =-tanks!AW17 -> 0 | AK16: =SUM(AJ16-AI16) -> 0 | AL16: =S16+L16+G16 -> 0 | AM16: =Y16+AD16 -> 0 | AN16: =AN15 -> 67 | AO16: =(AN16/100)*3000 -> 2010 | AP16: =AP15 -> 55 | AQ16: =(AP16/100)*3000 -> 1650 | AR16: =AR15 -> 61 | AS16: =(AR16/100)*3000 -> 1830 | AT16: =SUM(AO16+AQ16+AS16) -> 5490 | AU16: =AT15-AT16+AV16 -> 0 | AX16: =IF(AV16>0,AW16,AX15) -> 0.8
A17: =ELEC!C15 -> 44268 | B17: =B16 -> 194.5 | C17: =C16 -> 201 | D17: =C16-C17 -> 0 | E17: =D17*8.38 -> 0 | F17: =F16 -> 1760 | G17: =F17-F16 -> 0 | H17: =H16 -> 7285 | I17: =SUM(H17-H16) -> 0 | J17: =IF(G17>0,I17/G17,0) -> 0 | K17: =K16 -> 2254 | L17: =K17-K16 -> 0 | M17: =M16 -> 165849 | N17: =M17-M16 -> 0 | O17: =O16 -> 1869 | P17: =P16 -> 2008 | Q17: =Q16 -> 169516 | R17: =Q17-Q16 -> 0 | S17: =SUM(P17-P16) -> 0 | T17: =SUM(S17*$T$2) -> 0 | U17: =SUM(G17+L17+S17) -> 0 | V17: =R17+N17+I17:I17 -> 0 | X17: =X16 -> 2461 | Y17: =X17-X16 -> 0 | Z17: =Z16 -> 138425 | AA17: =Z17-Z16 -> 0 | AB17: =SUM(Y17*$AB$2) -> 0 | AC17: =AC16 -> 1935 | AD17: =AC17-AC16 -> 0 | AE17: =AE16 -> 365467 | AF17: =AE17-AE16 -> 0 | AG17: =IF(AD17>0,AF17/AD17,0) -> 0 | AH17: =AF17+AA17 -> 0 | AI17: =SUM(AH17+V17) -> 0 | AJ17: =-tanks!AW18 -> 0 | AK17: =SUM(AJ17-AI17) -> 0 | AL17: =S17+L17+G17 -> 0 | AM17: =Y17+AD17 -> 0 | AN17: =AN16 -> 67 | AO17: =(AN17/100)*3000 -> 2010 | AP17: =AP16 -> 55 | AQ17: =(AP17/100)*3000 -> 1650 | AR17: =AR16 -> 61 | AS17: =(AR17/100)*3000 -> 1830 | AT17: =SUM(AO17+AQ17+AS17) -> 5490 | AU17: =AT16-AT17+AV17 -> 0 | AX17: =IF(AV17>0,AW17,AX16) -> 0.8
A18: =ELEC!C16 -> 44269 | B18: =B17 -> 194.5 | C18: =C17 -> 201 | D18: =C17-C18 -> 0 | E18: =D18*8.38 -> 0 | F18: =F17 -> 1760 | G18: =F18-F17 -> 0 | H18: =H17 -> 7285 | I18: =SUM(H18-H17) -> 0 | J18: =IF(G18>0,I18/G18,0) -> 0 | K18: =K17 -> 2254 | L18: =K18-K17 -> 0 | M18: =M17 -> 165849 | N18: =M18-M17 -> 0 | O18: 1869 | P18: =P17 -> 2008 | Q18: =Q17 -> 169516 | R18: =Q18-Q17 -> 0 | S18: =SUM(P18-P17) -> 0 | T18: =SUM(S18*$T$2) -> 0 | U18: =SUM(G18+L18+S18) -> 0 | V18: =R18+N18+I18:I18 -> 0 | X18: =X17 -> 2461 | Y18: =X18-X17 -> 0 | Z18: =Z17 -> 138425 | AA18: =Z18-Z17 -> 0 | AB18: =SUM(Y18*$AB$2) -> 0 | AC18: =AC17 -> 1935 | AD18: =AC18-AC17 -> 0 | AE18: =AE17 -> 365467 | AF18: =AE18-AE17 -> 0 | AG18: =IF(AD18>0,AF18/AD18,0) -> 0 | AH18: =AF18+AA18 -> 0 | AI18: =SUM(AH18+V18) -> 0 | AJ18: =-tanks!AW19 -> 0 | AK18: =SUM(AJ18-AI18) -> 0 | AL18: =S18+L18+G18 -> 0 | AM18: =Y18+AD18 -> 0 | AN18: =AN17 -> 67 | AO18: =(AN18/100)*3000 -> 2010 | AP18: =AP17 -> 55 | AQ18: =(AP18/100)*3000 -> 1650 | AR18: =AR17 -> 61 | AS18: =(AR18/100)*3000 -> 1830 | AT18: =SUM(AO18+AQ18+AS18) -> 5490 | AU18: =AT17-AT18+AV18 -> 0 | AX18: =IF(AV18>0,AW18,AX17) -> 0.8
A19: =ELEC!C17 -> 44270 | B19: =B18 -> 194.5 | C19: =C18 -> 201 | D19: =C18-C19 -> 0 | E19: =D19*8.38 -> 0 | F19: =F18 -> 1760 | G19: =F19-F18 -> 0 | H19: =H18 -> 7285 | I19: =SUM(H19-H18) -> 0 | J19: =IF(G19>0,I19/G19,0) -> 0 | K19: =K18 -> 2254 | L19: =K19-K18 -> 0 | M19: =M18 -> 165849 | N19: =M19-M18 -> 0 | O19: =O18 -> 1869 | P19: =P18 -> 2008 | Q19: =Q18 -> 169516 | R19: =Q19-Q18 -> 0 | S19: =SUM(P19-P18) -> 0 | T19: =SUM(S19*$T$2) -> 0 | U19: =SUM(G19+L19+S19) -> 0 | V19: =R19+N19+I19:I19 -> 0 | X19: =X18 -> 2461 | Y19: =X19-X18 -> 0 | Z19: =Z18 -> 138425 | AA19: =Z19-Z18 -> 0 | AB19: =SUM(Y19*$AB$2) -> 0 | AC19: =AC18 -> 1935 | AD19: =AC19-AC18 -> 0 | AE19: =AE18 -> 365467 | AF19: =AE19-AE18 -> 0 | AG19: =IF(AD19>0,AF19/AD19,0) -> 0 | AH19: =AF19+AA19 -> 0 | AI19: =SUM(AH19+V19) -> 0 | AJ19: =-tanks!AW20 -> 0 | AK19: =SUM(AJ19-AI19) -> 0 | AL19: =S19+L19+G19 -> 0 | AM19: =Y19+AD19 -> 0 | AN19: =AN18 -> 67 | AO19: =(AN19/100)*3000 -> 2010 | AP19: =AP18 -> 55 | AQ19: =(AP19/100)*3000 -> 1650 | AR19: =AR18 -> 61 | AS19: =(AR19/100)*3000 -> 1830 | AT19: =SUM(AO19+AQ19+AS19) -> 5490 | AU19: =AT18-AT19+AV19 -> 0 | AX19: =IF(AV19>0,AW19,AX18) -> 0.8
A20: =ELEC!C18 -> 44271 | B20: =B19 -> 194.5 | C20: =C19 -> 201 | D20: =C19-C20 -> 0 | E20: =D20*8.38 -> 0 | F20: =F19 -> 1760 | G20: =F20-F19 -> 0 | H20: =H19 -> 7285 | I20: =SUM(H20-H19) -> 0 | J20: =IF(G20>0,I20/G20,0) -> 0 | K20: =K19 -> 2254 | L20: =K20-K19 -> 0 | M20: =M19 -> 165849 | N20: =M20-M19 -> 0 | O20: =O19 -> 1869 | P20: =P19 -> 2008 | Q20: =Q19 -> 169516 | R20: =Q20-Q19 -> 0 | S20: =SUM(P20-P19) -> 0 | T20: =SUM(S20*$T$2) -> 0 | U20: =SUM(G20+L20+S20) -> 0 | V20: =R20+N20+I20:I20 -> 0 | X20: =X19 -> 2461 | Y20: =X20-X19 -> 0 | Z20: =Z19 -> 138425 | AA20: =Z20-Z19 -> 0 | AB20: =SUM(Y20*$AB$2) -> 0 | AC20: =AC19 -> 1935 | AD20: =AC20-AC19 -> 0 | AE20: =AE19 -> 365467 | AF20: =AE20-AE19 -> 0 | AG20: =IF(AD20>0,AF20/AD20,0) -> 0 | AH20: =AF20+AA20 -> 0 | AI20: =SUM(AH20+V20) -> 0 | AJ20: =-tanks!AW21 -> 0 | AK20: =SUM(AJ20-AI20) -> 0 | AL20: =S20+L20+G20 -> 0 | AM20: =Y20+AD20 -> 0 | AN20: =AN19 -> 67 | AO20: =(AN20/100)*3000 -> 2010 | AP20: =AP19 -> 55 | AQ20: =(AP20/100)*3000 -> 1650 | AR20: =AR19 -> 61 | AS20: =(AR20/100)*3000 -> 1830 | AT20: =SUM(AO20+AQ20+AS20) -> 5490 | AU20: =AT19-AT20+AV20 -> 0 | AX20: =IF(AV20>0,AW20,AX19) -> 0.8
A21: =ELEC!C19 -> 44272 | B21: =B20 -> 194.5 | C21: =C20 -> 201 | D21: =C20-C21 -> 0 | E21: =D21*8.38 -> 0 | F21: =F20 -> 1760 | G21: =F21-F20 -> 0 | H21: =H20 -> 7285 | I21: =SUM(H21-H20) -> 0 | J21: =IF(G21>0,I21/G21,0) -> 0 | K21: =K20 -> 2254 | L21: =K21-K20 -> 0 | M21: =M20 -> 165849 | N21: =M21-M20 -> 0 | O21: =O20 -> 1869 | P21: =P20 -> 2008 | Q21: =Q20 -> 169516 | R21: =Q21-Q20 -> 0 | S21: =SUM(P21-P20) -> 0 | T21: =SUM(S21*$T$2) -> 0 | U21: =SUM(G21+L21+S21) -> 0 | V21: =R21+N21+I21:I21 -> 0 | X21: =X20 -> 2461 | Y21: =X21-X20 -> 0 | Z21: =Z20 -> 138425 | AA21: =Z21-Z20 -> 0 | AB21: =SUM(Y21*$AB$2) -> 0 | AC21: =AC20 -> 1935 | AD21: =AC21-AC20 -> 0 | AE21: =AE20 -> 365467 | AF21: =AE21-AE20 -> 0 | AG21: =IF(AD21>0,AF21/AD21,0) -> 0 | AH21: =AF21+AA21 -> 0 | AI21: =SUM(AH21+V21) -> 0 | AJ21: =-tanks!AW22 -> 0 | AK21: =SUM(AJ21-AI21) -> 0 | AL21: =S21+L21+G21 -> 0 | AM21: =Y21+AD21 -> 0 | AN21: =AN20 -> 67 | AO21: =(AN21/100)*3000 -> 2010 | AP21: =AP20 -> 55 | AQ21: =(AP21/100)*3000 -> 1650 | AR21: =AR20 -> 61 | AS21: =(AR21/100)*3000 -> 1830 | AT21: =SUM(AO21+AQ21+AS21) -> 5490 | AU21: =AT20-AT21+AV21 -> 0 | AX21: =IF(AV21>0,AW21,AX20) -> 0.8
A22: =ELEC!C20 -> 44273 | B22: =B21 -> 194.5 | C22: =C21 -> 201 | D22: =C21-C22 -> 0 | E22: =D22*8.38 -> 0 | F22: =F21 -> 1760 | G22: =F22-F21 -> 0 | H22: =H21 -> 7285 | I22: =SUM(H22-H21) -> 0 | J22: =IF(G22>0,I22/G22,0) -> 0 | K22: =K21 -> 2254 | L22: =K22-K21 -> 0 | M22: =M21 -> 165849 | N22: =M22-M21 -> 0 | O22: =O21 -> 1869 | P22: =P21 -> 2008 | Q22: =Q21 -> 169516 | R22: =Q22-Q21 -> 0 | S22: =SUM(P22-P21) -> 0 | T22: =SUM(S22*$T$2) -> 0 | U22: =SUM(G22+L22+S22) -> 0 | V22: =R22+N22+I22:I22 -> 0 | X22: =X21 -> 2461 | Y22: =X22-X21 -> 0 | Z22: =Z21 -> 138425 | AA22: =Z22-Z21 -> 0 | AB22: =SUM(Y22*$AB$2) -> 0 | AC22: =AC21 -> 1935 | AD22: =AC22-AC21 -> 0 | AE22: =AE21 -> 365467 | AF22: =AE22-AE21 -> 0 | AG22: =IF(AD22>0,AF22/AD22,0) -> 0 | AH22: =AF22+AA22 -> 0 | AI22: =SUM(AH22+V22) -> 0 | AJ22: =-tanks!AW23 -> 0 | AK22: =SUM(AJ22-AI22) -> 0 | AL22: =S22+L22+G22 -> 0 | AM22: =Y22+AD22 -> 0 | AN22: =AN21 -> 67 | AO22: =(AN22/100)*3000 -> 2010 | AP22: =AP21 -> 55 | AQ22: =(AP22/100)*3000 -> 1650 | AR22: =AR21 -> 61 | AS22: =(AR22/100)*3000 -> 1830 | AT22: =SUM(AO22+AQ22+AS22) -> 5490 | AU22: =AT21-AT22+AV22 -> 0 | AX22: =IF(AV22>0,AW22,AX21) -> 0.8
A23: =[3]ELEC!C21 -> 44215 | B23: =B22 -> 194.5 | C23: =C22 -> 201 | D23: =C22-C23 -> 0 | E23: =D23*8.38 -> 0 | F23: =F22 -> 1760 | G23: =F23-F22 -> 0 | H23: =H22 -> 7285 | I23: =SUM(H23-H22) -> 0 | J23: =IF(G23>0,I23/G23,0) -> 0 | K23: =K22 -> 2254 | L23: =K23-K22 -> 0 | M23: =M22 -> 165849 | N23: =M23-M22 -> 0 | O23: =O22 -> 1869 | P23: =P22 -> 2008 | Q23: =Q22 -> 169516 | R23: =Q23-Q22 -> 0 | S23: =SUM(P23-P22) -> 0 | T23: =SUM(S23*$T$2) -> 0 | U23: =SUM(G23+L23+S23) -> 0 | V23: =R23+N23+I23:I23 -> 0 | X23: =X22 -> 2461 | Y23: =X23-X22 -> 0 | Z23: =Z22 -> 138425 | AA23: =Z23-Z22 -> 0 | AB23: =SUM(Y23*$AB$2) -> 0 | AC23: =AC22 -> 1935 | AD23: =AC23-AC22 -> 0 | AE23: =AE22 -> 365467 | AF23: =AE23-AE22 -> 0 | AG23: =IF(AD23>0,AF23/AD23,0) -> 0 | AH23: =AF23+AA23 -> 0 | AI23: =SUM(AH23+V23) -> 0 | AJ23: =-tanks!AW24 -> 0 | AK23: =SUM(AJ23-AI23) -> 0 | AL23: =S23+L23+G23 -> 0 | AM23: =Y23+AD23 -> 0 | AN23: =AN22 -> 67 | AO23: =(AN23/100)*3000 -> 2010 | AP23: =AP22 -> 55 | AQ23: =(AP23/100)*3000 -> 1650 | AR23: =AR22 -> 61 | AS23: =(AR23/100)*3000 -> 1830 | AT23: =SUM(AO23+AQ23+AS23) -> 5490 | AU23: =AT22-AT23+AV23 -> 0 | AX23: =IF(AV23>0,AW23,AX22) -> 0.8
A24: =ELEC!C22 -> 44275 | B24: =B23 -> 194.5 | C24: =C23 -> 201 | D24: =C23-C24 -> 0 | E24: =D24*8.38 -> 0 | F24: =F23 -> 1760 | G24: =F24-F23 -> 0 | H24: =H23 -> 7285 | I24: =SUM(H24-H23) -> 0 | J24: =IF(G24>0,I24/G24,0) -> 0 | K24: =K23 -> 2254 | L24: =K24-K23 -> 0 | M24: =M23 -> 165849 | N24: =M24-M23 -> 0 | O24: =O23 -> 1869 | P24: =P23 -> 2008 | Q24: =Q23 -> 169516 | R24: =Q24-Q23 -> 0 | S24: =SUM(P24-P23) -> 0 | T24: =SUM(S24*$T$2) -> 0 | U24: =SUM(G24+L24+S24) -> 0 | V24: =R24+N24+I24:I24 -> 0 | X24: =X23 -> 2461 | Y24: =X24-X23 -> 0 | Z24: =Z23 -> 138425 | AA24: =Z24-Z23 -> 0 | AB24: =SUM(Y24*$AB$2) -> 0 | AC24: =AC23 -> 1935 | AD24: =AC24-AC23 -> 0 | AE24: =AE23 -> 365467 | AF24: =AE24-AE23 -> 0 | AG24: =IF(AD24>0,AF24/AD24,0) -> 0 | AH24: =AF24+AA24 -> 0 | AI24: =SUM(AH24+V24) -> 0 | AJ24: =-tanks!AW25 -> 0 | AK24: =SUM(AJ24-AI24) -> 0 | AL24: =S24+L24+G24 -> 0 | AM24: =Y24+AD24 -> 0 | AN24: =AN23 -> 67 | AO24: =(AN24/100)*3000 -> 2010 | AP24: =AP23 -> 55 | AQ24: =(AP24/100)*3000 -> 1650 | AR24: =AR23 -> 61 | AS24: =(AR24/100)*3000 -> 1830 | AT24: =SUM(AO24+AQ24+AS24) -> 5490 | AU24: =AT23-AT24+AV24 -> 0 | AX24: =IF(AV24>0,AW24,AX23) -> 0.8
A25: =ELEC!C23 -> 44276 | B25: =B24 -> 194.5 | C25: =C24 -> 201 | D25: =C24-C25 -> 0 | E25: =D25*8.38 -> 0 | F25: =F24 -> 1760 | G25: =F25-F24 -> 0 | H25: =H24 -> 7285 | I25: =SUM(H25-H24) -> 0 | J25: =IF(G25>0,I25/G25,0) -> 0 | K25: =K24 -> 2254 | L25: =K25-K24 -> 0 | M25: =M24 -> 165849 | N25: =M25-M24 -> 0 | O25: =O24 -> 1869 | P25: =P24 -> 2008 | Q25: =Q24 -> 169516 | R25: =Q25-Q24 -> 0 | S25: =SUM(P25-P24) -> 0 | T25: =SUM(S25*$T$2) -> 0 | U25: =SUM(G25+L25+S25) -> 0 | V25: =R25+N25+I25:I25 -> 0 | X25: =X24 -> 2461 | Y25: =X25-X24 -> 0 | Z25: =Z24 -> 138425 | AA25: =Z25-Z24 -> 0 | AB25: =SUM(Y25*$AB$2) -> 0 | AC25: =AC24 -> 1935 | AD25: =AC25-AC24 -> 0 | AE25: =AE24 -> 365467 | AF25: =AE25-AE24 -> 0 | AG25: =IF(AD25>0,AF25/AD25,0) -> 0 | AH25: =AF25+AA25 -> 0 | AI25: =SUM(AH25+V25) -> 0 | AJ25: =-tanks!AW26 -> 0 | AK25: =SUM(AJ25-AI25) -> 0 | AL25: =S25+L25+G25 -> 0 | AM25: =Y25+AD25 -> 0 | AN25: =AN24 -> 67 | AO25: =(AN25/100)*3000 -> 2010 | AP25: =AP24 -> 55 | AQ25: =(AP25/100)*3000 -> 1650 | AR25: =AR24 -> 61 | AS25: =(AR25/100)*3000 -> 1830 | AT25: =SUM(AO25+AQ25+AS25) -> 5490 | AU25: =AT24-AT25+AV25 -> 0 | AX25: =IF(AV25>0,AW25,AX24) -> 0.8
A26: =ELEC!C24 -> 44277 | B26: =B25 -> 194.5 | C26: =C25 -> 201 | D26: =C25-C26 -> 0 | E26: =D26*8.38 -> 0 | F26: =F25 -> 1760 | G26: =F26-F25 -> 0 | H26: =H25 -> 7285 | I26: =SUM(H26-H25) -> 0 | J26: =IF(G26>0,I26/G26,0) -> 0 | K26: =K25 -> 2254 | L26: =K26-K25 -> 0 | M26: =M25 -> 165849 | N26: =M26-M25 -> 0 | O26: =O25 -> 1869 | P26: =P25 -> 2008 | Q26: =Q25 -> 169516 | R26: =Q26-Q25 -> 0 | S26: =SUM(P26-P25) -> 0 | T26: =SUM(S26*$T$2) -> 0 | U26: =SUM(G26+L26+S26) -> 0 | V26: =R26+N26+I26:I26 -> 0 | X26: =X25 -> 2461 | Y26: =X26-X25 -> 0 | Z26: =Z25 -> 138425 | AA26: =Z26-Z25 -> 0 | AB26: =SUM(Y26*$AB$2) -> 0 | AC26: =AC25 -> 1935 | AD26: =AC26-AC25 -> 0 | AE26: =AE25 -> 365467 | AF26: =AE26-AE25 -> 0 | AG26: =IF(AD26>0,AF26/AD26,0) -> 0 | AH26: =AF26+AA26 -> 0 | AI26: =SUM(AH26+V26) -> 0 | AJ26: =-tanks!AW27 -> 0 | AK26: =SUM(AJ26-AI26) -> 0 | AL26: =S26+L26+G26 -> 0 | AM26: =Y26+AD26 -> 0 | AN26: =AN25 -> 67 | AO26: =(AN26/100)*3000 -> 2010 | AP26: =AP25 -> 55 | AQ26: =(AP26/100)*3000 -> 1650 | AR26: =AR25 -> 61 | AS26: =(AR26/100)*3000 -> 1830 | AT26: =SUM(AO26+AQ26+AS26) -> 5490 | AU26: =AT25-AT26+AV26 -> 0 | AX26: =IF(AV26>0,AW26,AX25) -> 0.8
A27: =ELEC!C25 -> 44278 | B27: =B26 -> 194.5 | C27: =C26 -> 201 | D27: =C26-C27 -> 0 | E27: =D27*8.38 -> 0 | F27: =F26 -> 1760 | G27: =F27-F26 -> 0 | H27: =H26 -> 7285 | I27: =SUM(H27-H26) -> 0 | J27: =IF(G27>0,I27/G27,0) -> 0 | K27: =K26 -> 2254 | L27: =K27-K26 -> 0 | M27: =M26 -> 165849 | N27: =M27-M26 -> 0 | O27: =O26 -> 1869 | P27: =P26 -> 2008 | Q27: =Q26 -> 169516 | R27: =Q27-Q26 -> 0 | S27: =SUM(P27-P26) -> 0 | T27: =SUM(S27*$T$2) -> 0 | U27: =SUM(G27+L27+S27) -> 0 | V27: =R27+N27+I27:I27 -> 0 | X27: =X26 -> 2461 | Y27: =X27-X26 -> 0 | Z27: =Z26 -> 138425 | AA27: =Z27-Z26 -> 0 | AB27: =SUM(Y27*$AB$2) -> 0 | AC27: =AC26 -> 1935 | AD27: =AC27-AC26 -> 0 | AE27: =AE26 -> 365467 | AF27: =AE27-AE26 -> 0 | AG27: =IF(AD27>0,AF27/AD27,0) -> 0 | AH27: =AF27+AA27 -> 0 | AI27: =SUM(AH27+V27) -> 0 | AJ27: =-tanks!AW28 -> 0 | AK27: =SUM(AJ27-AI27) -> 0 | AL27: =S27+L27+G27 -> 0 | AM27: =Y27+AD27 -> 0 | AN27: =AN26 -> 67 | AO27: =(AN27/100)*3000 -> 2010 | AP27: =AP26 -> 55 | AQ27: =(AP27/100)*3000 -> 1650 | AR27: =AR26 -> 61 | AS27: =(AR27/100)*3000 -> 1830 | AT27: =SUM(AO27+AQ27+AS27) -> 5490 | AU27: =AT26-AT27+AV27 -> 0 | AX27: =IF(AV27>0,AW27,AX26) -> 0.8
A28: =ELEC!C26 -> 44279 | B28: =B27 -> 194.5 | C28: =C27 -> 201 | D28: =C27-C28 -> 0 | E28: =D28*8.38 -> 0 | F28: =F27 -> 1760 | G28: =F28-F27 -> 0 | H28: =H27 -> 7285 | I28: =SUM(H28-H27) -> 0 | J28: =IF(G28>0,I28/G28,0) -> 0 | K28: =K27 -> 2254 | L28: =K28-K27 -> 0 | M28: =M27 -> 165849 | N28: =M28-M27 -> 0 | O28: =O27 -> 1869 | P28: =P27 -> 2008 | Q28: =Q27 -> 169516 | R28: =Q28-Q27 -> 0 | S28: =SUM(P28-P27) -> 0 | T28: =SUM(S28*$T$2) -> 0 | U28: =SUM(G28+L28+S28) -> 0 | V28: =R28+N28+I28:I28 -> 0 | X28: =X27 -> 2461 | Y28: =X28-X27 -> 0 | Z28: =Z27 -> 138425 | AA28: =Z28-Z27 -> 0 | AB28: =SUM(Y28*$AB$2) -> 0 | AC28: =AC27 -> 1935 | AD28: =AC28-AC27 -> 0 | AE28: =AE27 -> 365467 | AF28: =AE28-AE27 -> 0 | AG28: =IF(AD28>0,AF28/AD28,0) -> 0 | AH28: =AF28+AA28 -> 0 | AI28: =SUM(AH28+V28) -> 0 | AJ28: =-tanks!AW29 -> 0 | AK28: =SUM(AJ28-AI28) -> 0 | AL28: =S28+L28+G28 -> 0 | AM28: =Y28+AD28 -> 0 | AN28: =AN27 -> 67 | AO28: =(AN28/100)*3000 -> 2010 | AP28: =AP27 -> 55 | AQ28: =(AP28/100)*3000 -> 1650 | AR28: =AR27 -> 61 | AS28: =(AR28/100)*3000 -> 1830 | AT28: =SUM(AO28+AQ28+AS28) -> 5490 | AU28: =AT27-AT28+AV28 -> 0 | AX28: =IF(AV28>0,AW28,AX27) -> 0.8
A29: =ELEC!C27 -> 44280 | B29: =B28 -> 194.5 | C29: =C28 -> 201 | D29: =C28-C29 -> 0 | E29: =D29*8.38 -> 0 | F29: =F28 -> 1760 | G29: =F29-F28 -> 0 | H29: =H28 -> 7285 | I29: =SUM(H29-H28) -> 0 | J29: =IF(G29>0,I29/G29,0) -> 0 | K29: =K28 -> 2254 | L29: =K29-K28 -> 0 | M29: =M28 -> 165849 | N29: =M29-M28 -> 0 | O29: =O28 -> 1869 | P29: =P28 -> 2008 | Q29: =Q28 -> 169516 | R29: =Q29-Q28 -> 0 | S29: =SUM(P29-P28) -> 0 | T29: =SUM(S29*$T$2) -> 0 | U29: =SUM(G29+L29+S29) -> 0 | V29: =R29+N29+I29:I29 -> 0 | X29: =X28 -> 2461 | Y29: =X29-X28 -> 0 | Z29: =Z28 -> 138425 | AA29: =Z29-Z28 -> 0 | AB29: =SUM(Y29*$AB$2) -> 0 | AC29: =AC28 -> 1935 | AD29: =AC29-AC28 -> 0 | AE29: =AE28 -> 365467 | AF29: =AE29-AE28 -> 0 | AG29: =IF(AD29>0,AF29/AD29,0) -> 0 | AH29: =AF29+AA29 -> 0 | AI29: =SUM(AH29+V29) -> 0 | AJ29: =-tanks!AW30 -> 0 | AK29: =SUM(AJ29-AI29) -> 0 | AL29: =S29+L29+G29 -> 0 | AM29: =Y29+AD29 -> 0 | AN29: =AN28 -> 67 | AO29: =(AN29/100)*3000 -> 2010 | AP29: =AP28 -> 55 | AQ29: =(AP29/100)*3000 -> 1650 | AR29: =AR28 -> 61 | AS29: =(AR29/100)*3000 -> 1830 | AT29: =SUM(AO29+AQ29+AS29) -> 5490 | AU29: =AT28-AT29+AV29 -> 0 | AX29: =IF(AV29>0,AW29,AX28) -> 0.8
A30: =ELEC!C28 -> 44281 | B30: =B29 -> 194.5 | C30: =C29 -> 201 | D30: =C29-C30 -> 0 | E30: =D30*8.38 -> 0 | F30: =F29 -> 1760 | G30: =F30-F29 -> 0 | H30: =H29 -> 7285 | I30: =SUM(H30-H29) -> 0 | J30: =IF(G30>0,I30/G30,0) -> 0 | K30: =K29 -> 2254 | L30: =K30-K29 -> 0 | M30: =M29 -> 165849 | N30: =M30-M29 -> 0 | O30: =O29 -> 1869 | P30: =P29 -> 2008 | Q30: =Q29 -> 169516 | R30: =Q30-Q29 -> 0 | S30: =SUM(P30-P29) -> 0 | T30: =SUM(S30*$T$2) -> 0 | U30: =SUM(G30+L30+S30) -> 0 | V30: =R30+N30+I30:I30 -> 0 | X30: =X29 -> 2461 | Y30: =X30-X29 -> 0 | Z30: =Z29 -> 138425 | AA30: =Z30-Z29 -> 0 | AB30: =SUM(Y30*$AB$2) -> 0 | AC30: =AC29 -> 1935 | AD30: =AC30-AC29 -> 0 | AE30: =AE29 -> 365467 | AF30: =AE30-AE29 -> 0 | AG30: =IF(AD30>0,AF30/AD30,0) -> 0 | AH30: =AF30+AA30 -> 0 | AI30: =SUM(AH30+V30) -> 0 | AJ30: =-tanks!AW31 -> 0 | AK30: =SUM(AJ30-AI30) -> 0 | AL30: =S30+L30+G30 -> 0 | AM30: =Y30+AD30 -> 0 | AN30: =AN29 -> 67 | AO30: =(AN30/100)*3000 -> 2010 | AP30: =AP29 -> 55 | AQ30: =(AP30/100)*3000 -> 1650 | AR30: =AR29 -> 61 | AS30: =(AR30/100)*3000 -> 1830 | AT30: =SUM(AO30+AQ30+AS30) -> 5490 | AU30: =AT29-AT30+AV30 -> 0 | AX30: =IF(AV30>0,AW30,AX29) -> 0.8
A31: =ELEC!C29 -> 44282 | B31: =B30 -> 194.5 | C31: =C30 -> 201 | D31: =C30-C31 -> 0 | E31: =D31*8.38 -> 0 | F31: =F30 -> 1760 | G31: =F31-F30 -> 0 | H31: =H30 -> 7285 | I31: =SUM(H31-H30) -> 0 | J31: =IF(G31>0,I31/G31,0) -> 0 | K31: =K30 -> 2254 | L31: =K31-K30 -> 0 | M31: =M30 -> 165849 | N31: =M31-M30 -> 0 | O31: =O30 -> 1869 | P31: =P30 -> 2008 | Q31: =Q30 -> 169516 | R31: =Q31-Q30 -> 0 | S31: =SUM(P31-P30) -> 0 | T31: =SUM(S31*$T$2) -> 0 | U31: =SUM(G31+L31+S31) -> 0 | V31: =R31+N31+I31:I31 -> 0 | X31: =X30 -> 2461 | Y31: =X31-X30 -> 0 | Z31: =Z30 -> 138425 | AA31: =Z31-Z30 -> 0 | AB31: =SUM(Y31*$AB$2) -> 0 | AC31: =AC30 -> 1935 | AD31: =AC31-AC30 -> 0 | AE31: =AE30 -> 365467 | AF31: =AE31-AE30 -> 0 | AG31: =IF(AD31>0,AF31/AD31,0) -> 0 | AH31: =AF31+AA31 -> 0 | AI31: =SUM(AH31+V31) -> 0 | AJ31: =-tanks!AW32 -> 0 | AK31: =SUM(AJ31-AI31) -> 0 | AL31: =S31+L31+G31 -> 0 | AM31: =Y31+AD31 -> 0 | AN31: =AN30 -> 67 | AO31: =(AN31/100)*3000 -> 2010 | AP31: =AP30 -> 55 | AQ31: =(AP31/100)*3000 -> 1650 | AR31: =AR30 -> 61 | AS31: =(AR31/100)*3000 -> 1830 | AT31: =SUM(AO31+AQ31+AS31) -> 5490 | AU31: =AT30-AT31+AV31 -> 0 | AX31: =IF(AV31>0,AW31,AX30) -> 0.8
A32: =ELEC!C30 -> 44283 | B32: =B31 -> 194.5 | C32: =C31 -> 201 | D32: =C31-C32 -> 0 | E32: =D32*8.38 -> 0 | F32: =F31 -> 1760 | G32: =F32-F31 -> 0 | H32: =H31 -> 7285 | I32: =SUM(H32-H31) -> 0 | J32: =IF(G32>0,I32/G32,0) -> 0 | K32: =K31 -> 2254 | L32: =K32-K31 -> 0 | M32: =M31 -> 165849 | N32: =M32-M31 -> 0 | O32: =O31 -> 1869 | P32: =P31 -> 2008 | Q32: =Q31 -> 169516 | R32: =Q32-Q31 -> 0 | S32: =SUM(P32-P31) -> 0 | T32: =SUM(S32*$T$2) -> 0 | U32: =SUM(G32+L32+S32) -> 0 | V32: =R32+N32+I32:I32 -> 0 | X32: =X31 -> 2461 | Y32: =X32-X31 -> 0 | Z32: =Z31 -> 138425 | AA32: =Z32-Z31 -> 0 | AB32: =SUM(Y32*$AB$2) -> 0 | AC32: =AC31 -> 1935 | AD32: =AC32-AC31 -> 0 | AE32: =AE31 -> 365467 | AF32: =AE32-AE31 -> 0 | AG32: =IF(AD32>0,AF32/AD32,0) -> 0 | AH32: =AF32+AA32 -> 0 | AI32: =SUM(AH32+V32) -> 0 | AJ32: =-tanks!AW33 -> 0 | AK32: =SUM(AJ32-AI32) -> 0 | AL32: =S32+L32+G32 -> 0 | AM32: =Y32+AD32 -> 0 | AN32: =AN31 -> 67 | AO32: =(AN32/100)*3000 -> 2010 | AP32: =AP31 -> 55 | AQ32: =(AP32/100)*3000 -> 1650 | AR32: =AR31 -> 61 | AS32: =(AR32/100)*3000 -> 1830 | AT32: =SUM(AO32+AQ32+AS32) -> 5490 | AU32: =AT31-AT32+AV32 -> 0 | AX32: =IF(AV32>0,AW32,AX31) -> 0.8
A33: =ELEC!C31 -> 44284 | B33: =B32 -> 194.5 | C33: =C32 -> 201 | D33: =C32-C33 -> 0 | E33: =D33*8.38 -> 0 | F33: =F32 -> 1760 | G33: =F33-F32 -> 0 | H33: =H32 -> 7285 | I33: =SUM(H33-H32) -> 0 | J33: =IF(G33>0,I33/G33,0) -> 0 | K33: =K32 -> 2254 | L33: =K33-K32 -> 0 | M33: =M32 -> 165849 | N33: =M33-M32 -> 0 | O33: =O32 -> 1869 | P33: =P32 -> 2008 | Q33: =Q32 -> 169516 | R33: =Q33-Q32 -> 0 | S33: =SUM(P33-P32) -> 0 | T33: =SUM(S33*$T$2) -> 0 | U33: =SUM(G33+L33+S33) -> 0 | V33: =R33+N33+I33:I33 -> 0 | X33: =X32 -> 2461 | Y33: =X33-X32 -> 0 | Z33: =Z32 -> 138425 | AA33: =Z33-Z32 -> 0 | AB33: =SUM(Y33*$AB$2) -> 0 | AC33: =AC32 -> 1935 | AD33: =AC33-AC32 -> 0 | AE33: =AE32 -> 365467 | AF33: =AE33-AE32 -> 0 | AG33: =IF(AD33>0,AF33/AD33,0) -> 0 | AH33: =AF33+AA33 -> 0 | AI33: =SUM(AH33+V33) -> 0 | AJ33: =-tanks!AW34 -> 0 | AK33: =SUM(AJ33-AI33) -> 0 | AL33: =S33+L33+G33 -> 0 | AM33: =Y33+AD33 -> 0 | AN33: =AN32 -> 67 | AO33: =(AN33/100)*3000 -> 2010 | AP33: =AP32 -> 55 | AQ33: =(AP33/100)*3000 -> 1650 | AR33: =AR32 -> 61 | AS33: =(AR33/100)*3000 -> 1830 | AT33: =SUM(AO33+AQ33+AS33) -> 5490 | AU33: =AT32-AT33+AV33 -> 0 | AX33: =IF(AV33>0,AW33,AX32) -> 0.8
A34: =ELEC!C32 -> 44285 | B34: =B33 -> 194.5 | C34: =C33 -> 201 | D34: =C33-C34 -> 0 | E34: =D34*8.38 -> 0 | F34: =F33 -> 1760 | G34: =F34-F33 -> 0 | H34: =H33 -> 7285 | I34: =SUM(H34-H33) -> 0 | J34: =IF(G34>0,I34/G34,0) -> 0 | K34: =K33 -> 2254 | L34: =K34-K33 -> 0 | M34: =M33 -> 165849 | N34: =M34-M33 -> 0 | O34: =O33 -> 1869 | P34: =P33 -> 2008 | Q34: =Q33 -> 169516 | R34: =Q34-Q33 -> 0 | S34: =SUM(P34-P33) -> 0 | T34: =SUM(S34*$T$2) -> 0 | U34: =SUM(G34+L34+S34) -> 0 | V34: =R34+N34+I34:I34 -> 0 | X34: =X33 -> 2461 | Y34: =X34-X33 -> 0 | Z34: =Z33 -> 138425 | AA34: =Z34-Z33 -> 0 | AB34: =SUM(Y34*$AB$2) -> 0 | AC34: =AC33 -> 1935 | AD34: =AC34-AC33 -> 0 | AE34: =AE33 -> 365467 | AF34: =AE34-AE33 -> 0 | AG34: =IF(AD34>0,AF34/AD34,0) -> 0 | AH34: =AF34+AA34 -> 0 | AI34: =SUM(AH34+V34) -> 0 | AJ34: =-tanks!AW35 -> 0 | AK34: =SUM(AJ34-AI34) -> 0 | AL34: =S34+L34+G34 -> 0 | AM34: =Y34+AD34 -> 0 | AN34: =AN33 -> 67 | AO34: =(AN34/100)*3000 -> 2010 | AP34: =AP33 -> 55 | AQ34: =(AP34/100)*3000 -> 1650 | AR34: =AR33 -> 61 | AS34: =(AR34/100)*3000 -> 1830 | AT34: =SUM(AO34+AQ34+AS34) -> 5490 | AU34: =AT33-AT34+AV34 -> 0 | AX34: =IF(AV34>0,AW34,AX33) -> 0.8
A35: =ELEC!C33 -> 44286 | B35: =B34 -> 194.5 | C35: =C34 -> 201 | D35: =C34-C35 -> 0 | E35: =D35*8.38 -> 0 | F35: =F34 -> 1760 | G35: =F35-F34 -> 0 | H35: =H34 -> 7285 | I35: =SUM(H35-H34) -> 0 | J35: =IF(G35>0,I35/G35,0) -> 0 | K35: =K34 -> 2254 | L35: =K35-K34 -> 0 | M35: =M34 -> 165849 | N35: =M35-M34 -> 0 | O35: =O34 -> 1869 | P35: =P34 -> 2008 | Q35: =Q34 -> 169516 | R35: =Q35-Q34 -> 0 | S35: =SUM(P35-P34) -> 0 | T35: =SUM(S35*$T$2) -> 0 | U35: =SUM(G35+L35+S35) -> 0 | V35: =R35+N35+I35:I35 -> 0 | X35: =X34 -> 2461 | Y35: =X35-X34 -> 0 | Z35: =Z34 -> 138425 | AA35: =Z35-Z34 -> 0 | AB35: =SUM(Y35*$AB$2) -> 0 | AC35: =AC34 -> 1935 | AD35: =AC35-AC34 -> 0 | AE35: =AE34 -> 365467 | AF35: =AE35-AE34 -> 0 | AG35: =IF(AD35>0,AF35/AD35,0) -> 0 | AH35: =AF35+AA35 -> 0 | AI35: =SUM(AH35+V35) -> 0 | AJ35: =-tanks!AW36 -> 0 | AK35: =SUM(AJ35-AI35) -> 0 | AL35: =S35+L35+G35 -> 0 | AM35: =Y35+AD35 -> 0 | AN35: =AN34 -> 67 | AO35: =(AN35/100)*3000 -> 2010 | AP35: =AP34 -> 55 | AQ35: =(AP35/100)*3000 -> 1650 | AR35: =AR34 -> 61 | AS35: =(AR35/100)*3000 -> 1830 | AT35: =SUM(AO35+AQ35+AS35) -> 5490 | AU35: =AT34-AT35+AV35 -> 0 | AX35: =IF(AV35>0,AW35,AX34) -> 0.8
J37: =SUM(J5:J32)/(COUNT(J5:J32)-COUNTIF(J5:J32,0)) -> 58.694444 | V37: =SUM(V5:V32) -> 1961 | AE37: . | AH37: =SUM(AH5:AH32) -> 324.2 | AL37: =SUM(AL5:AL32) -> 26 | AM37: =SUM(AM5:AM32) -> 5 | AR37: Nb Delivery | AS37: =COUNT(AW5:AW32) -> 0 | AU37: =SUM(AU5:AU32) -> 0 | AV37: =SUM(AV5:AV32) -> 0 | AW37: =SUM(AW5:AW32)/AS37 -> #DIV/0!
AH38: =AF38+AA38 -> 0 | AI38: =SUM(AI5:AI32) -> 2285.2
AH39: =AF39+AA39 -> 0 | AU39: =AU37*0.51 -> 0 | AV39: =AV37/0.51 -> 0 | AW39: =SUM(AW5:AW32)/AS37 -> #DIV/0!
AV40: =AV37*0.51 -> 0

Sheet WATER
D1: =SUM(G21:G33) -> 8009976 | AR1: Entrance | AT1: Tank 1 | AV1: Tank 2
AR2: Level | AW2: Quantity CM3 | AZ2: Var
A3: Date | B3: Truck | C3: Truck M3/day | D3: N0. Trucks | F3: REQ. # of trucks | G3: City | H3: City/day | I3: Total water delivery | K3: SW | L3: Cosum SW/day | M3: RO Guest/ Liter | O3: RO K&L/ Liter | Q3: TOTAL RO Production | R3: RO 1 RH | S3: RO 2 RH | T3: RO water counter | U3: RO Cons m3 | V3: Steam Boiler | W3: Steam Boiler/day | X3: Softener Guest | Y3: Guest Sotf/day | Z3: Softener K&L | AA3: K&L Soft/Day | AB3: Fire Tank Level | AC3: Fire Tank Counter | AE3: Laundry Hot Water Counter | AF3: Hot Water Cons/day | AG3: Laundry Cold Water Counter | AH3: Cold Water Cons/day | AI3: Laundry Water Total Cons | AJ3: K&L Sotf/day | AK3: Guest / day | AL3: K&L /day | AM3: Avg Outside Temp | AN3: Banquet Activity | AR3: Date | AT3: MainI | AV3: Kitchen and Laundry | AX3: Guest | AY3: Main Tank | AZ3: Kitchen and Laundry | BA3: Guest | BB3: Kitchen and Laundry | BC3: Main | BD3: Guest | BE3: Total VAR | BF3: Hotel Consumption
E4: 1.66 | AN4: Ball R | AO4: Meeting | AP4: outlet | AT4: 180 | AV4: 220 | AX4: 580 | AY4: =SUM(AT4) -> 180 | AZ4: =SUM(AV4) -> 220 | BA4: =SUM(AX4) -> 580
A5: =ELEC!C2 -> 44255 | B5: =[1]WATER!B33 -> 109443 | C5: =[1]WATER!C33 -> 0 | D5: =[1]WATER!D33 -> 0 | E5: =[1]WATER!E33 -> 267.85714 | F5: =[1]WATER!F33 -> 0 | G5: =[1]WATER!G33 -> 616152 | H5: =[1]WATER!H33 -> 0 | I5: =[1]WATER!I33 -> 0 | ... BG5: =[1]WATER!BG33 -> -11.6
A6: =ELEC!C3 -> 44256 | B6: =B5 -> 109443 | C6: =B6-B5 -> 0 | D6: =C6/27 -> 0 | E6: =SUM((C6*$E$4)+(7500/'EDl log'!$A$37)) -> 241.93548 | G6: =G5 -> 616152 | H6: =G6-G5 -> 0 | I6: =C6+H6 -> 0 | J6: =IF(I6>0,E6/I6,0) -> 0 | K6: ='Swimming Pool quality check '!H6 -> 6721 | L6: 0 | M6: =M5 -> 457.44 | N6: =SUM(M6-M5) -> 0 | O6: =O5 -> 529.52 | P6: =SUM(O6-O5) -> 0 | Q6: =P6+N6 -> 0 | T6: =T5 -> 5167 | U6: =SUM(T6-T5) -> 0 | V6: 461 | W6: =+V6-V5 -> 0 | X6: =X5 -> 150365 | Y6: =SUM(X6-X5) -> 0 | Z6: =Z5 -> 98681 | AA6: =Z6-Z5 -> 0 | AB6: 251 | AC6: =AC5 -> 731 | AD6: 0 | AE6: 229.03 | AF6: =AE6-AE5 -> 0.87 | AG6: 2198.54 | AH6: =AG6-AG5 -> 16.34 | AI6: =AF6+AH6 -> 17.21 | AJ6: =+Z6-Z5 -> 0 | AK6: =SUM(Y6-L6) -> 0 | AL6: =SUM(AJ6-W6) -> 0 | AM6: ='General information '!D6 -> 16 | AN6: ='General information '!H6 -> 0 | AP6: ='General information '!J6 -> 0 | AR6: =A6 -> 44256 | AS6: =AS5 -> 0.9 | AT6: 84 | AU6: =AU5 -> 1.1 | AV6: 146 | AW6: 2.9 | AX6: 167 | AY6: =AS6*AT6 -> 75.6 | AZ6: =AU6*AV6 -> 160.6 | BA6: =AW6*AX6 -> 484.3 | BB6: =AY6-AY5 -> 0.9 | BC6: =AZ6-AZ5 -> -27.5 | BD6: =BA6-BA5 -> 5.8 | BE6: =SUM(BB6:BD6) -> -20.8 | BF6: =SUM(I6-BE6) -> 20.8 | BG6: =SUM(I6-BF6) -> -20.8
A7: =ELEC!C4 -> 44257 | B7: =B6 -> 109443 | C7: =B7-B6 -> 0 | D7: =C7/27 -> 0 | E7: =SUM((C7*$E$4)+(7500/'EDl log'!$A$37)) -> 241.93548 | G7: =G6 -> 616152 | H7: =G7-G6 -> 0 | I7: =C7+H7 -> 0 | J7: =IF(I7>0,E7/I7,0) -> 0 | K7: ='Swimming Pool quality check '!H7 -> 6721 | L7: =K7-K6 -> 0 | M7: =M6 -> 457.44 | N7: =SUM(M7-M6) -> 0 | O7: =O6 -> 529.52 | P7: =SUM(O7-O6) -> 0 | Q7: =P7+N7 -> 0 | T7: =T6 -> 5167 | U7: =SUM(T7-T6) -> 0 | V7: =V6 -> 461 | W7: =+V7-V6 -> 0 | X7: =X6 -> 150365 | Y7: =SUM(X7-X6) -> 0 | Z7: =Z6 -> 98681 | AA7: =Z7-Z6 -> 0 | AB7: =AB6 -> 251 | AC7: =AC6 -> 731 | AD7: =AC7-AC6 -> 0 | AE7: =AE6 -> 229.03 | AF7: =AE7-AE6 -> 0 | AG7: =AG6 -> 2198.54 | AH7: =AG7-AG6 -> 0 | AI7: =AF7+AH7 -> 0 | AJ7: =+Z7-Z6 -> 0 | AK7: =SUM(Y7-L7) -> 0 | AL7: =SUM(AJ7-W7) -> 0 | AM7: ='General information '!D7 -> 15.5 | AN7: ='General information '!H7 -> 0 | AP7: ='General information '!J7 -> 0 | AR7: =A7 -> 44257 | AS7: =AS6 -> 0.9 | AT7: 77 | AU7: =AU6 -> 1.1 | AV7: 138 | AW7: 2.9 | AX7: 164 | AY7: =AS7*AT7 -> 69.3 | AZ7: =AU7*AV7 -> 151.8 | BA7: =AW7*AX7 -> 475.6 | BB7: =AY7-AY6 -> -6.3 | BC7: =AZ7-AZ6 -> -8.8 | BD7: =BA7-BA6 -> -8.7 | BE7: =SUM(BB7:BD7) -> -23.8 | BF7: =SUM(I7-BE7) -> 23.8 | BG7: =SUM(I7-BF7) -> -23.8
A8: =ELEC!C5 -> 44258 | B8: =B7 -> 109443 | C8: =B8-B7 -> 0 | D8: =C8/27 -> 0 | E8: =SUM((C8*$E$4)+(7500/'EDl log'!$A$37)) -> 241.93548 | G8: =G7 -> 616152 | H8: =G8-G7 -> 0 | I8: =C8+H8 -> 0 | J8: =IF(I8>0,E8/I8,0) -> 0 | K8: ='Swimming Pool quality check '!H8 -> 6721 | L8: =K8-K7 -> 0 | M8: =M7 -> 457.44 | N8: =SUM(M8-M7) -> 0 | O8: =O7 -> 529.52 | P8: =SUM(O8-O7) -> 0 | Q8: =P8+N8 -> 0 | T8: =T7 -> 5167 | U8: =SUM(T8-T7) -> 0 | V8: =V7 -> 461 | W8: =+V8-V7 -> 0 | X8: =X7 -> 150365 | Y8: =SUM(X8-X7) -> 0 | Z8: =Z7 -> 98681 | AA8: =Z8-Z7 -> 0 | AB8: =AB7 -> 251 | AC8: =AC7 -> 731 | AD8: =AC8-AC7 -> 0 | AE8: =AE7 -> 229.03 | AF8: =AE8-AE7 -> 0 | AG8: =AG7 -> 2198.54 | AH8: =AG8-AG7 -> 0 | AI8: =AF8+AH8 -> 0 | AJ8: =+Z8-Z7 -> 0 | AK8: =SUM(Y8-L8) -> 0 | AL8: =SUM(AJ8-W8) -> 0 | AM8: ='General information '!D8 -> 15.5 | AN8: ='General information '!H8 -> 0 | AP8: ='General information '!J8 -> 0 | AR8: =A8 -> 44258 | AS8: =AS7 -> 0.9 | AT8: =AT7 -> 77 | AU8: 1.1 | AV8: 124 | AW8: 2.9 | AX8: 158 | AY8: =AS8*AT8 -> 69.3 | AZ8: =AU8*AV8 -> 136.4 | BA8: =AW8*AX8 -> 458.2 | BB8: =AY8-AY7 -> 0 | BC8: =AZ8-AZ7 -> -15.4 | BD8: =BA8-BA7 -> -17.4 | BE8: =SUM(BB8:BD8) -> -32.8 | BF8: =SUM(I8-BE8) -> 32.8 | BG8: =SUM(I8-BF8) -> -32.8
A9: =ELEC!C6 -> 44259 | B9: =B8 -> 109443 | C9: =B9-B8 -> 0 | D9: =C9/27 -> 0 | E9: =SUM((C9*$E$4)+(7500/'EDl log'!$A$37)) -> 241.93548 | G9: =G8 -> 616152 | H9: =G9-G8 -> 0 | I9: =C9+H9 -> 0 | J9: =IF(I9>0,E9/I9,0) -> 0 | K9: ='Swimming Pool quality check '!H9 -> 6723 | L9: =K9-K8 -> 2 | M9: =M8 -> 457.44 | N9: =SUM(M9-M8) -> 0 | O9: =O8 -> 529.52 | P9: =SUM(O9-O8) -> 0 | Q9: =P9+N9 -> 0 | T9: =T8 -> 5167 | U9: =SUM(T9-T8) -> 0 | V9: =V8 -> 461 | W9: =+V9-V8 -> 0 | X9: =X8 -> 150365 | Y9: =SUM(X9-X8) -> 0 | Z9: =Z8 -> 98681 | AA9: =Z9-Z8 -> 0 | AB9: =AB8 -> 251 | AC9: =AC8 -> 731 | AD9: =AC9-AC8 -> 0 | AE9: =AE8 -> 229.03 | AF9: =AE9-AE8 -> 0 | AG9: =AG8 -> 2198.54 | AH9: =AG9-AG8 -> 0 | AI9: =AF9+AH9 -> 0 | AJ9: =+Z9-Z8 -> 0 | AK9: =SUM(Y9-L9) -> -2 | AL9: =SUM(AJ9-W9) -> 0 | AM9: ='General information '!D9 -> 15.5 | AN9: ='General information '!H9 -> 0 | AP9: ='General information '!J9 -> 0 | AR9: =A9 -> 44259 | AS9: =AS8 -> 0.9 | AT9: 77 | AU9: =AU8 -> 1.1 | AV9: 130 | AW9: 2.9 | AX9: 156 | AY9: =AS9*AT9 -> 69.3 | AZ9: =AU9*AV9 -> 143 | BA9: =AW9*AX9 -> 452.4 | BB9: =AY9-AY8 -> 0 | BC9: =AZ9-AZ8 -> 6.6 | BD9: =BA9-BA8 -> -5.8 | BE9: =SUM(BB9:BD9) -> 0.8 | BF9: =SUM(I9-BE9) -> -0.8 | BG9: =SUM(I9-BF9) -> 0.8
A10: =ELEC!C7 -> 44260 | B10: =B9 -> 109443 | C10: =B10-B9 -> 0 | D10: =C10/27 -> 0 | E10: =SUM((C10*$E$4)+(7500/'EDl log'!$A$37)) -> 241.93548 | G10: =G9 -> 616152 | H10: =G10-G9 -> 0 | I10: =C10+H10 -> 0 | J10: =IF(I10>0,E10/I10,0) -> 0 | K10: ='Swimming Pool quality check '!H10 -> 6723 | L10: =K10-K9 -> 0 | M10: =M9 -> 457.44 | N10: =SUM(M10-M9) -> 0 | O10: =O9 -> 529.52 | P10: =SUM(O10-O9) -> 0 | Q10: =P10+N10 -> 0 | T10: =T9 -> 5167 | U10: =SUM(T10-T9) -> 0 | V10: =V9 -> 461 | W10: =+V10-V9 -> 0 | X10: =X9 -> 150365 | Y10: =SUM(X10-X9) -> 0 | Z10: =Z9 -> 98681 | AA10: =Z10-Z9 -> 0 | AB10: =AB9 -> 251 | AC10: =AC9 -> 731 | AD10: =AC10-AC9 -> 0 | AE10: =AE9 -> 229.03 | AF10: =AE10-AE9 -> 0 | AG10: =AG9 -> 2198.54 | AH10: =AG10-AG9 -> 0 | AI10: =AF10+AH10 -> 0 | AJ10: =+Z10-Z9 -> 0 | AK10: =SUM(Y10-L10) -> 0 | AL10: =SUM(AJ10-W10) -> 0 | AM10: ='General information '!D10 -> 15.5 | AN10: ='General information '!H10 -> 0 | AP10: ='General information '!J10 -> 0 | AR10: =A10 -> 44260 | AS10: =AS9 -> 0.9 | AT10: =AT9 -> 77 | AU10: =AU9 -> 1.1 | AV10: 126 | AW10: 2.9 | AX10: =AX9 -> 156 | AY10: =AS10*AT10 -> 69.3 | AZ10: =AU10*AV10 -> 138.6 | BA10: =AW10*AX10 -> 452.4 | BB10: =AY10-AY9 -> 0 | BC10: =AZ10-AZ9 -> -4.4 | BD10: =BA10-BA9 -> 0 | BE10: =SUM(BB10:BD10) -> -4.4 | BF10: =SUM(I10-BE10) -> 4.4 | BG10: =SUM(I10-BF10) -> -4.4
A11: =ELEC!C8 -> 44261 | B11: =B10 -> 109443 | C11: =B11-B10 -> 0 | D11: =C11/27 -> 0 | E11: =SUM((C11*$E$4)+(7500/'EDl log'!$A$37)) -> 241.93548 | G11: =G10 -> 616152 | H11: =G11-G10 -> 0 | I11: =C11+H11 -> 0 | J11: =IF(I11>0,E11/I11,0) -> 0 | K11: ='Swimming Pool quality check '!H11 -> 6725 | L11: =K11-K10 -> 2 | M11: =M10 -> 457.44 | N11: =SUM(M11-M10) -> 0 | O11: =O10 -> 529.52 | P11: =SUM(O11-O10) -> 0 | Q11: =SUM(P11+N11) -> 0 | T11: =T10 -> 5167 | U11: =SUM(T11-T10) -> 0 | V11: =V10 -> 461 | W11: =+V11-V10 -> 0 | X11: =X10 -> 150365 | Y11: =SUM(X11-X10) -> 0 | Z11: =Z10 -> 98681 | AA11: =Z11-Z10 -> 0 | AB11: =AB10 -> 251 | AC11: =AC10 -> 731 | AD11: =AC11-AC10 -> 0 | AE11: =AE10 -> 229.03 | AF11: =AE11-AE10 -> 0 | AG11: =AG10 -> 2198.54 | AH11: =AG11-AG10 -> 0 | AI11: =AF11+AH11 -> 0 | AJ11: =+Z11-Z10 -> 0 | AK11: =SUM(Y11-L11) -> -2 | AL11: =SUM(AJ11-W11) -> 0 | AM11: ='General information '!D11 -> 16 | AN11: ='General information '!H11 -> 0 | AP11: ='General information '!J11 -> 0 | AR11: =A11 -> 44261 | AS11: =AS10 -> 0.9 | AT11: =AT10 -> 77 | AU11: =AU10 -> 1.1 | AV11: 124 | AW11: 2.9 | AX11: 155 | AY11: =AS11*AT11 -> 69.3 | AZ11: =AU11*AV11 -> 136.4 | BA11: =AW11*AX11 -> 449.5 | BB11: =AY11-AY10 -> 0 | BC11: =AZ11-AZ10 -> -2.2 | BD11: =BA11-BA10 -> -2.9 | BE11: =SUM(BB11:BD11) -> -5.1 | BF11: =SUM(I11-BE11) -> 5.1 | BG11: =SUM(I11-BF11) -> -5.1
A12: =ELEC!C9 -> 44262 | B12: =B11 -> 109443 | C12: =B12-B11 -> 0 | D12: =C12/27 -> 0 | E12: =SUM((C12*$E$4)+(7500/'EDl log'!$A$37)) -> 241.93548 | G12: =G11 -> 616152 | H12: =G12-G11 -> 0 | I12: =C12+H12 -> 0 | J12: =IF(I12>0,E12/I12,0) -> 0 | K12: ='Swimming Pool quality check '!H12 -> 6726 | L12: =K12-K11 -> 1 | M12: =M11 -> 457.44 | N12: =SUM(M12-M11) -> 0 | O12: =O11 -> 529.52 | P12: =SUM(O12-O11) -> 0 | Q12: =SUM(P12+N12) -> 0 | T12: =T11 -> 5167 | U12: =SUM(T12-T11) -> 0 | V12: =V11 -> 461 | W12: =+V12-V11 -> 0 | X12: =X11 -> 150365 | Y12: =SUM(X12-X11) -> 0 | Z12: =Z11 -> 98681 | AA12: =Z12-Z11 -> 0 | AB12: =AB11 -> 251 | AC12: =AC11 -> 731 | AD12: =AC12-AC11 -> 0 | AE12: =AE11 -> 229.03 | AF12: =AE12-AE11 -> 0 | AG12: =AG11 -> 2198.54 | AH12: =AG12-AG11 -> 0 | AI12: =AF12+AH12 -> 0 | AJ12: =+Z12-Z11 -> 0 | AK12: =SUM(Y12-L12) -> -1 | AL12: =SUM(AJ12-W12) -> 0 | AM12: ='General information '!D12 -> 16.5 | AN12: ='General information '!H12 -> 0 | AP12: ='General information '!J12 -> 0 | AR12: =A12 -> 44262 | AS12: =AS11 -> 0.9 | AT12: =AT11 -> 77 | AU12: =AU11 -> 1.1 | AV12: 121 | AW12: 2.9 | AX12: 152 | AY12: =AS12*AT12 -> 69.3 | AZ12: =AU12*AV12 -> 133.1 | BA12: =AW12*AX12 -> 440.8 | BB12: =AY12-AY11 -> 0 | BC12: =AZ12-AZ11 -> -3.3 | BD12: =BA12-BA11 -> -8.7 | BE12: =SUM(BB12:BD12) -> -12 | BF12: =SUM(I12-BE12) -> 12 | BG12: =SUM(I12-BF12) -> -12
A13: =ELEC!C10 -> 44263 | B13: =B12 -> 109443 | C13: =B13-B12 -> 0 | D13: =C13/27 -> 0 | E13: =SUM((C13*$E$4)+(7500/'EDl log'!$A$37)) -> 241.93548 | G13: =G12 -> 616152 | H13: =G13-G12 -> 0 | I13: =C13+H13 -> 0 | J13: =IF(I13>0,E13/I13,0) -> 0 | K13: ='Swimming Pool quality check '!H13 -> 6726 | L13: =K13-K12 -> 0 | M13: =M12 -> 457.44 | N13: =SUM(M13-M12) -> 0 | O13: =O12 -> 529.52 | P13: =SUM(O13-O12) -> 0 | Q13: =SUM(P13+N13) -> 0 | T13: =T12 -> 5167 | U13: =SUM(T13-T12) -> 0 | V13: =V12 -> 461 | W13: =+V13-V12 -> 0 | X13: =X12 -> 150365 | Y13: =SUM(X13-X12) -> 0 | Z13: =Z12 -> 98681 | AA13: =Z13-Z12 -> 0 | AB13: =AB12 -> 251 | AC13: =AC12 -> 731 | AD13: =AC13-AC12 -> 0 | AE13: =AE12 -> 229.03 | AF13: =AE13-AE12 -> 0 | AG13: =AG12 -> 2198.54 | AH13: =AG13-AG12 -> 0 | AI13: =AF13+AH13 -> 0 | AJ13: =+Z13-Z12 -> 0 | AK13: =SUM(Y13-L13) -> 0 | AL13: =SUM(AJ13-W13) -> 0 | AM13: ='General information '!D13 -> 18 | AN13: ='General information '!J13 -> 0 | AP13: ='General information '!J13 -> 0 | AR13: =A13 -> 44263 | AS13: =AS12 -> 0.9 | AT13: =AT12 -> 77 | AU13: =AU12 -> 1.1 | AV13: 118 | AW13: 2.9 | AX13: 149 | AY13: =AS13*AT13 -> 69.3 | AZ13: =AU13*AV13 -> 129.8 | BA13: =AW13*AX13 -> 432.1 | BB13: =AY13-AY12 -> 0 | BC13: =AZ13-AZ12 -> -3.3 | BD13: =BA13-BA12 -> -8.7 | BE13: =SUM(BB13:BD13) -> -12 | BF13: =SUM(I13-BE13) -> 12 | BG13: =SUM(I13-BF13) -> -12
A14: =ELEC!C11 -> 44264 | B14: =B13 -> 109443 | C14: =B14-B13 -> 0 | D14: =C14/27 -> 0 | E14: =SUM((C14*$E$4)+(7500/'EDl log'!$A$37)) -> 241.93548 | G14: =G13 -> 616152 | H14: =G14-G13 -> 0 | I14: =C14+H14 -> 0 | J14: =IF(I14>0,E14/I14,0) -> 0 | K14: ='Swimming Pool quality check '!H14 -> 6726 | L14: =K14-K13 -> 0 | M14: =M13 -> 457.44 | N14: =SUM(M14-M13) -> 0 | O14: =O13 -> 529.52 | P14: =SUM(O14-O13) -> 0 | Q14: =SUM(P14+N14) -> 0 | T14: =T13 -> 5167 | U14: =SUM(T14-T13) -> 0 | V14: =V13 -> 461 | W14: =+V14-V13 -> 0 | X14: =X13 -> 150365 | Y14: =SUM(X14-X13) -> 0 | Z14: =Z13 -> 98681 | AA14: =Z14-Z13 -> 0 | AB14: =AB13 -> 251 | AC14: =AC13 -> 731 | AD14: =AC14-AC13 -> 0 | AE14: =AE13 -> 229.03 | AF14: =AE14-AE13 -> 0 | AG14: =AG13 -> 2198.54 | AH14: =AG14-AG13 -> 0 | AI14: =AF14+AH14 -> 0 | AJ14: =+Z14-Z13 -> 0 | AK14: =SUM(Y14-L14) -> 0 | AL14: =SUM(AJ14-W14) -> 0 | AM14: ='General information '!D14 -> 0 | AN14: ='General information '!H14 -> 0 | AP14: ='General information '!J14 -> 0 | AR14: =A14 -> 44264 | AS14: =AS13 -> 0.9 | AT14: =AT13 -> 77 | AU14: =AU13 -> 1.1 | AV14: =AV13 -> 118 | AW14: 2.9 | AX14: =AX13 -> 149 | AY14: =AS14*AT14 -> 69.3 | AZ14: =AU14*AV14 -> 129.8 | BA14: =AW14*AX14 -> 432.1 | BB14: =AY14-AY13 -> 0 | BC14: =AZ14-AZ13 -> 0 | BD14: =BA14-BA13 -> 0 | BE14: =SUM(BB14:BD14) -> 0 | BF14: =SUM(I14-BE14) -> 0 | BG14: =SUM(I14-BF14) -> 0
A15: =ELEC!C12 -> 44265 | B15: =B14 -> 109443 | C15: =B15-B14 -> 0 | D15: =C15/27 -> 0 | E15: =SUM((C15*$E$4)+(7500/'EDl log'!$A$37)) -> 241.93548 | G15: =G14 -> 616152 | H15: =G15-G14 -> 0 | I15: =C15+H15 -> 0 | J15: =IF(I15>0,E15/I15,0) -> 0 | K15: ='Swimming Pool quality check '!H15 -> 6726 | L15: =K15-K14 -> 0 | M15: =M14 -> 457.44 | N15: =SUM(M15-M14) -> 0 | O15: =O14 -> 529.52 | P15: =SUM(O15-O14) -> 0 | Q15: =SUM(P15+N15) -> 0 | T15: =T14 -> 5167 | U15: =SUM(T15-T14) -> 0 | V15: =V14 -> 461 | W15: =+V15-V14 -> 0 | X15: =X14 -> 150365 | Y15: =SUM(X15-X14) -> 0 | Z15: =Z14 -> 98681 | AA15: =Z15-Z14 -> 0 | AB15: =AB14 -> 251 | AC15: =AC14 -> 731 | AD15: =AC15-AC14 -> 0 | AE15: =AE14 -> 229.03 | AF15: =AE15-AE14 -> 0 | AG15: =AG14 -> 2198.54 | AH15: =AG15-AG14 -> 0 | AI15: =AF15+AH15 -> 0 | AJ15: =+Z15-Z14 -> 0 | AK15: =SUM(Y15-L15) -> 0 | AL15: =SUM(AJ15-W15) -> 0 | AM15: ='General information '!D15 -> 0 | AN15: ='General information '!H15 -> 0 | AP15: ='General information '!J15 -> 0 | AR15: =A15 -> 44265 | AS15: =AS14 -> 0.9 | AT15: =AT14 -> 77 | AU15: =AU14 -> 1.1 | AV15: =AV14 -> 118 | AW15: 2.9 | AX15: =AX14 -> 149 | AY15: =AS15*AT15 -> 69.3 | AZ15: =AU15*AV15 -> 129.8 | BA15: =AW15*AX15 -> 432.1 | BB15: =AY15-AY14 -> 0 | BC15: =AZ15-AZ14 -> 0 | BD15: =BA15-BA14 -> 0 | BE15: =SUM(BB15:BD15) -> 0 | BF15: =SUM(I15-BE15) -> 0 | BG15: =SUM(I15-BF15) -> 0
A16: =ELEC!C13 -> 44266 | B16: =B15 -> 109443 | C16: =B16-B15 -> 0 | D16: =C16/27 -> 0 | E16: =SUM((C16*$E$4)+(7500/'EDl log'!$A$37)) -> 241.93548 | G16: =G15 -> 616152 | H16: =G16-G15 -> 0 | I16: =C16+H16 -> 0 | J16: =IF(I16>0,E16/I16,0) -> 0 | K16: ='Swimming Pool quality check '!H16 -> 6726 | L16: =K16-K15 -> 0 | M16: =M15 -> 457.44 | N16: =SUM(M16-M15) -> 0 | O16: =O15 -> 529.52 | P16: =SUM(O16-O15) -> 0 | Q16: =SUM(P16+N16) -> 0 | T16: =T15 -> 5167 | U16: =SUM(T16-T15) -> 0 | V16: =V15 -> 461 | W16: =+V16-V15 -> 0 | X16: =X15 -> 150365 | Y16: =SUM(X16-X15) -> 0 | Z16: =Z15 -> 98681 | AA16: =Z16-Z15 -> 0 | AB16: =AB15 -> 251 | AC16: =AC15 -> 731 | AD16: =AC16-AC15 -> 0 | AE16: =AE15 -> 229.03 | AF16: =AE16-AE15 -> 0 | AG16: =AG15 -> 2198.54 | AH16: =AG16-AG15 -> 0 | AI16: =AF16+AH16 -> 0 | AJ16: =+Z16-Z15 -> 0 | AK16: =SUM(Y16-L16) -> 0 | AL16: =SUM(AJ16-W16) -> 0 | AM16: ='General information '!D16 -> 0 | AN16: ='General information '!H16 -> 0 | AP16: ='General information '!J16 -> 0 | AR16: =A16 -> 44266 | AS16: =AS15 -> 0.9 | AT16: =AT15 -> 77 | AU16: =AU15 -> 1.1 | AV16: =AV15 -> 118 | AW16: 2.9 | AX16: =AX15 -> 149 | AY16: =AS16*AT16 -> 69.3 | AZ16: =AU16*AV16 -> 129.8 | BA16: =AW16*AX16 -> 432.1 | BB16: =AY16-AY15 -> 0 | BC16: =AZ16-AZ15 -> 0 | BD16: =BA16-BA15 -> 0 | BE16: =SUM(BB16:BD16) -> 0 | BF16: =SUM(I16-BE16) -> 0 | BG16: =SUM(I16-BF16) -> 0
A17: =ELEC!C14 -> 44267 | B17: =B16 -> 109443 | C17: =B17-B16 -> 0 | D17: =C17/27 -> 0 | E17: =SUM((C17*$E$4)+(7500/'EDl log'!$A$37)) -> 241.93548 | G17: =G16 -> 616152 | H17: =G17-G16 -> 0 | I17: =C17+H17 -> 0 | J17: =IF(I17>0,E17/I17,0) -> 0 | K17: ='Swimming Pool quality check '!H17 -> 6726 | L17: =K17-K16 -> 0 | M17: =M16 -> 457.44 | N17: =SUM(M17-M16) -> 0 | O17: =O16 -> 529.52 | P17: =SUM(O17-O16) -> 0 | Q17: =SUM(P17+N17) -> 0 | T17: =T16 -> 5167 | U17: =SUM(T17-T16) -> 0 | V17: =V16 -> 461 | W17: =+V17-V16 -> 0 | X17: =X16 -> 150365 | Y17: =SUM(X17-X16) -> 0 | Z17: =Z16 -> 98681 | AA17: =Z17-Z16 -> 0 | AB17: =AB16 -> 251 | AC17: =AC16 -> 731 | AD17: =AC17-AC16 -> 0 | AE17: =AE16 -> 229.03 | AF17: =AE17-AE16 -> 0 | AG17: =AG16 -> 2198.54 | AH17: =AG17-AG16 -> 0 | AI17: =AF17+AH17 -> 0 | AJ17: =+Z17-Z16 -> 0 | AK17: =SUM(Y17-L17) -> 0 | AL17: =SUM(AJ17-W17) -> 0 | AM17: ='General information '!D17 -> 0 | AN17: ='General information '!H17 -> 0 | AP17: ='General information '!J17 -> 0 | AR17: =A17 -> 44267 | AS17: =AS16 -> 0.9 | AT17: =AT16 -> 77 | AU17: =AU16 -> 1.1 | AV17: =AV16 -> 118 | AW17: 2.9 | AX17: =AX16 -> 149 | AY17: =AS17*AT17 -> 69.3 | AZ17: =AU17*AV17 -> 129.8 | BA17: =AW17*AX17 -> 432.1 | BB17: =AY17-AY16 -> 0 | BC17: =AZ17-AZ16 -> 0 | BD17: =BA17-BA16 -> 0 | BE17: =SUM(BB17:BD17) -> 0 | BF17: =SUM(I17-BE17) -> 0 | BG17: =SUM(I17-BF17) -> 0
A18: =ELEC!C15 -> 44268 | B18: =B17 -> 109443 | C18: =B18-B17 -> 0 | D18: =C18/27 -> 0 | E18: =SUM((C18*$E$4)+(7500/'EDl log'!$A$37)) -> 241.93548 | G18: =G17 -> 616152 | H18: =G18-G17 -> 0 | I18: =C18+H18 -> 0 | J18: =IF(I18>0,E18/I18,0) -> 0 | K18: ='Swimming Pool quality check '!H18 -> 6726 | L18: =K18-K17 -> 0 | M18: =M17 -> 457.44 | N18: =SUM(M18-M17) -> 0 | O18: =O17 -> 529.52 | P18: =SUM(O18-O17) -> 0 | Q18: =SUM(P18+N18) -> 0 | T18: =T17 -> 5167 | U18: =SUM(T18-T17) -> 0 | V18: =V17 -> 461 | W18: =+V18-V17 -> 0 | X18: =X17 -> 150365 | Y18: =SUM(X18-X17) -> 0 | Z18: =Z17 -> 98681 | AA18: =Z18-Z17 -> 0 | AB18: =AB17 -> 251 | AC18: =AC17 -> 731 | AD18: =AC18-AC17 -> 0 | AE18: =AE17 -> 229.03 | AF18: =AE18-AE17 -> 0 | AG18: =AG17 -> 2198.54 | AH18: =AG18-AG17 -> 0 | AI18: =AF18+AH18 -> 0 | AJ18: =+Z18-Z17 -> 0 | AK18: =SUM(Y18-L18) -> 0 | AL18: =SUM(AJ18-W18) -> 0 | AM18: ='General information '!D18 -> 0 | AN18: ='General information '!H18 -> 0 | AP18: ='General information '!J18 -> 0 | AR18: =A18 -> 44268 | AS18: =AS17 -> 0.9 | AT18: =AT17 -> 77 | AU18: =AU17 -> 1.1 | AV18: =AV17 -> 118 | AW18: 2.9 | AX18: =AX17 -> 149 | AY18: =AS18*AT18 -> 69.3 | AZ18: =AU18*AV18 -> 129.8 | BA18: =AW18*AX18 -> 432.1 | BB18: =AY18-AY17 -> 0 | BC18: =AZ18-AZ17 -> 0 | BD18: =BA18-BA17 -> 0 | BE18: =SUM(BB18:BD18) -> 0 | BF18: =SUM(I18-BE18) -> 0 | BG18: =SUM(I18-BF18) -> 0
A19: =ELEC!C16 -> 44269 | B19: =B18 -> 109443 | C19: =B19-B18 -> 0 | D19: =C19/27 -> 0 | E19: =SUM((C19*$E$4)+(7500/'EDl log'!$A$37)) -> 241.93548 | G19: =G18 -> 616152 | H19: =G19-G18 -> 0 | I19: =C19+H19 -> 0 | J19: =IF(I19>0,E19/I19,0) -> 0 | K19: ='Swimming Pool quality check '!H19 -> 6726 | L19: =K19-K18 -> 0 | M19: =M18 -> 457.44 | N19: =SUM(M19-M18) -> 0 | O19: =O18 -> 529.52 | P19: =SUM(O19-O18) -> 0 | Q19: =SUM(P19+N19) -> 0 | T19: =T18 -> 5167 | U19: =SUM(T19-T18) -> 0 | V19: =V18 -> 461 | W19: =+V19-V18 -> 0 | X19: =X18 -> 150365 | Y19: =SUM(X19-X18) -> 0 | Z19: =Z18 -> 98681 | AA19: =Z19-Z18 -> 0 | AB19: =AB18 -> 251 | AC19: =AC18 -> 731 | AD19: =AC19-AC18 -> 0 | AE19: =AE18 -> 229.03 | AF19: =AE19-AE18 -> 0 | AG19: =AG18 -> 2198.54 | AH19: =AG19-AG18 -> 0 | AI19: =AF19+AH19 -> 0 | AJ19: =+Z19-Z18 -> 0 | AK19: =SUM(Y19-L19) -> 0 | AL19: =SUM(AJ19-W19) -> 0 | AM19: ='General information '!D19 -> 0 | AN19: ='General information '!H19 -> 0 | AP19: ='General information '!J19 -> 0 | AR19: =A19 -> 44269 | AS19: =AS18 -> 0.9 | AT19: =AT18 -> 77 | AU19: =AU18 -> 1.1 | AV19: =AV18 -> 118 | AW19: 2.9 | AX19: =AX18 -> 149 | AY19: =AS19*AT19 -> 69.3 | AZ19: =AU19*AV19 -> 129.8 | BA19: =AW19*AX19 -> 432.1 | BB19: =AY19-AY18 -> 0 | BC19: =AZ19-AZ18 -> 0 | BD19: =BA19-BA18 -> 0 | BE19: =SUM(BB19:BD19) -> 0 | BF19: =SUM(I19-BE19) -> 0 | BG19: =SUM(I19-BF19) -> 0
A20: =ELEC!C17 -> 44270 | B20: =B19 -> 109443 | C20: =B20-B19 -> 0 | D20: =C20/27 -> 0 | E20: =SUM((C20*$E$4)+(7500/'EDl log'!$A$37)) -> 241.93548 | G20: =G19 -> 616152 | H20: =G20-G19 -> 0 | I20: =C20+H20 -> 0 | J20: =IF(I20>0,E20/I20,0) -> 0 | K20: ='Swimming Pool quality check '!H20 -> 6726 | L20: =K20-K19 -> 0 | M20: =M19 -> 457.44 | N20: =SUM(M20-M19) -> 0 | O20: =O19 -> 529.52 | P20: =SUM(O20-O19) -> 0 | Q20: =SUM(P20+N20) -> 0 | T20: =T19 -> 5167 | U20: =SUM(T20-T19) -> 0 | V20: =V19 -> 461 | W20: =+V20-V19 -> 0 | X20: =X19 -> 150365 | Y20: =SUM(X20-X19) -> 0 | Z20: =Z19 -> 98681 | AA20: =Z20-Z19 -> 0 | AB20: =AB19 -> 251 | AC20: =AC19 -> 731 | AD20: =AC20-AC19 -> 0 | AE20: =AE19 -> 229.03 | AF20: =AE20-AE19 -> 0 | AG20: =AG19 -> 2198.54 | AH20: =AG20-AG19 -> 0 | AI20: =AF20+AH20 -> 0 | AJ20: =+Z20-Z19 -> 0 | AK20: =SUM(Y20-L20) -> 0 | AL20: =SUM(AJ20-W20) -> 0 | AM20: ='General information '!D20 -> 0 | AN20: ='General information '!H20 -> 0 | AP20: ='General information '!J20 -> 0 | AR20: =A20 -> 44270 | AS20: =AS19 -> 0.9 | AT20: =AT19 -> 77 | AU20: =AU19 -> 1.1 | AV20: =AV19 -> 118 | AW20: 2.9 | AX20: =AX19 -> 149 | AY20: =AS20*AT20 -> 69.3 | AZ20: =AU20*AV20 -> 129.8 | BA20: =AW20*AX20 -> 432.1 | BB20: =AY20-AY19 -> 0 | BC20: =AZ20-AZ19 -> 0 | BD20: =BA20-BA19 -> 0 | BE20: =SUM(BB20:BD20) -> 0 | BF20: =SUM(I20-BE20) -> 0 | BG20: =SUM(I20-BF20) -> 0
A21: =ELEC!C18 -> 44271 | B21: =B20 -> 109443 | C21: =B21-B20 -> 0 | D21: =C21/27 -> 0 | E21: =SUM((C21*$E$4)+(7500/'EDl log'!$A$37)) -> 241.93548 | G21: =G20 -> 616152 | H21: =G21-G20 -> 0 | I21: =C21+H21 -> 0 | J21: =IF(I21>0,E21/I21,0) -> 0 | K21: ='Swimming Pool quality check '!H21 -> 6726 | L21: =K21-K20 -> 0 | M21: =M20 -> 457.44 | N21: =SUM(M21-M20) -> 0 | O21: =O20 -> 529.52 | P21: =SUM(O21-O20) -> 0 | Q21: =SUM(P21+N21) -> 0 | T21: =T20 -> 5167 | U21: =SUM(T21-T20) -> 0 | V21: =V20 -> 461 | W21: =+V21-V20 -> 0 | X21: =X20 -> 150365 | Y21: =SUM(X21-X20) -> 0 | Z21: =Z20 -> 98681 | AA21: =Z21-Z20 -> 0 | AB21: =AB20 -> 251 | AC21: =AC20 -> 731 | AD21: =AC21-AC20 -> 0 | AE21: =AE20 -> 229.03 | AF21: =AE21-AE20 -> 0 | AG21: =AG20 -> 2198.54 | AH21: =AG21-AG20 -> 0 | AI21: =AF21+AH21 -> 0 | AJ21: =+Z21-Z20 -> 0 | AK21: =SUM(Y21-L21) -> 0 | AL21: =SUM(AJ21-W21) -> 0 | AM21: ='General information '!D21 -> 0 | AN21: ='General information '!H21 -> 0 | AP21: ='General information '!J21 -> 0 | AR21: =A21 -> 44271 | AS21: =AS20 -> 0.9 | AT21: =AT20 -> 77 | AU21: =AU20 -> 1.1 | AV21: =AV20 -> 118 | AW21: 2.9 | AX21: =AX20 -> 149 | AY21: =AS21*AT21 -> 69.3 | AZ21: =AU21*AV21 -> 129.8 | BA21: =AW21*AX21 -> 432.1 | BB21: =AY21-AY20 -> 0 | BC21: =AZ21-AZ20 -> 0 | BD21: =BA21-BA20 -> 0 | BE21: =SUM(BB21:BD21) -> 0 | BF21: =SUM(I21-BE21) -> 0 | BG21: =SUM(I21-BF21) -> 0
A22: =ELEC!C19 -> 44272 | B22: =B21 -> 109443 | C22: =B22-B21 -> 0 | D22: =C22/27 -> 0 | E22: =SUM((C22*$E$4)+(7500/'EDl log'!$A$37)) -> 241.93548 | G22: =G21 -> 616152 | H22: =G22-G21 -> 0 | I22: =C22+H22 -> 0 | J22: =IF(I22>0,E22/I22,0) -> 0 | K22: ='Swimming Pool quality check '!H22 -> 6726 | L22: =K22-K21 -> 0 | M22: =M21 -> 457.44 | N22: =SUM(M22-M21) -> 0 | O22: =O21 -> 529.52 | P22: =SUM(O22-O21) -> 0 | Q22: =SUM(P22+N22) -> 0 | T22: =T21 -> 5167 | U22: =SUM(T22-T21) -> 0 | V22: =V21 -> 461 | W22: =+V22-V21 -> 0 | X22: =X21 -> 150365 | Y22: =SUM(X22-X21) -> 0 | Z22: =Z21 -> 98681 | AA22: =Z22-Z21 -> 0 | AB22: =AB21 -> 251 | AC22: =AC21 -> 731 | AD22: =AC22-AC21 -> 0 | AE22: =AE21 -> 229.03 | AF22: =AE22-AE21 -> 0 | AG22: =AG21 -> 2198.54 | AH22: =AG22-AG21 -> 0 | AI22: =AF22+AH22 -> 0 | AJ22: =+Z22-Z21 -> 0 | AK22: =SUM(Y22-L22) -> 0 | AL22: =SUM(AJ22-W22) -> 0 | AM22: ='General information '!D22 -> 0 | AN22: ='General information '!H22 -> 0 | AP22: ='General information '!J22 -> 0 | AR22: =A22 -> 44272 | AS22: =AS21 -> 0.9 | AT22: =AT21 -> 77 | AU22: =AU21 -> 1.1 | AV22: =AV21 -> 118 | AW22: 2.9 | AX22: =AX21 -> 149 | AY22: =AS22*AT22 -> 69.3 | AZ22: =AU22*AV22 -> 129.8 | BA22: =AW22*AX22 -> 432.1 | BB22: =AY22-AY21 -> 0 | BC22: =AZ22-AZ21 -> 0 | BD22: =BA22-BA21 -> 0 | BE22: =SUM(BB22:BD22) -> 0 | BF22: =SUM(I22-BE22) -> 0 | BG22: =SUM(I22-BF22) -> 0
A23: =ELEC!C20 -> 44273 | B23: =B22 -> 109443 | C23: =B23-B22 -> 0 | D23: =C23/27 -> 0 | E23: =SUM((C23*$E$4)+(7500/'EDl log'!$A$37)) -> 241.93548 | G23: =G22 -> 616152 | H23: =G23-G22 -> 0 | I23: =C23+H23 -> 0 | J23: =IF(I23>0,E23/I23,0) -> 0 | K23: ='Swimming Pool quality check '!H23 -> 6726 | L23: =K23-K22 -> 0 | M23: =M22 -> 457.44 | N23: =SUM(M23-M22) -> 0 | O23: =O22 -> 529.52 | P23: =SUM(O23-O22) -> 0 | Q23: =SUM(P23+N23) -> 0 | T23: =T22 -> 5167 | U23: =SUM(T23-T22) -> 0 | V23: =V22 -> 461 | W23: =+V23-V22 -> 0 | X23: =X22 -> 150365 | Y23: =SUM(X23-X22) -> 0 | Z23: =Z22 -> 98681 | AA23: =Z23-Z22 -> 0 | AB23: =AB22 -> 251 | AC23: =AC22 -> 731 | AD23: =AC23-AC22 -> 0 | AE23: =AE22 -> 229.03 | AF23: =AE23-AE22 -> 0 | AG23: =AG22 -> 2198.54 | AH23: =AG23-AG22 -> 0 | AI23: =AF23+AH23 -> 0 | AJ23: =+Z23-Z22 -> 0 | AK23: =SUM(Y23-L23) -> 0 | AL23: =SUM(AJ23-W23) -> 0 | AM23: ='General information '!D23 -> 0 | AN23: ='General information '!H23 -> 0 | AP23: ='General information '!J23 -> 0 | AR23: =A23 -> 44273 | AS23: =AS22 -> 0.9 | AT23: =AT22 -> 77 | AU23: =AU22 -> 1.1 | AV23: =AV22 -> 118 | AW23: 2.9 | AX23: =AX22 -> 149 | AY23: =AS23*AT23 -> 69.3 | AZ23: =AU23*AV23 -> 129.8 | BA23: =AW23*AX23 -> 432.1 | BB23: =AY23-AY22 -> 0 | BC23: =AZ23-AZ22 -> 0 | BD23: =BA23-BA22 -> 0 | BE23: =SUM(BB23:BD23) -> 0 | BF23: =SUM(I23-BE23) -> 0 | BG23: =SUM(I23-BF23) -> 0
A24: =ELEC!C21 -> 44274 | B24: =B23 -> 109443 | C24: =B24-B23 -> 0 | D24: =C24/27 -> 0 | E24: =SUM((C24*$E$4)+(7500/'[3]EDl log'!$A$37)) -> 241.93548 | G24: =G23 -> 616152 | H24: =G24-G23 -> 0 | I24: =C24+H24 -> 0 | J24: =IF(I24>0,E24/I24,0) -> 0 | K24: ='[3]Swimming Pool quality check '!H24 -> 6713 | L24: =K24-K23 -> -13 | M24: =M23 -> 457.44 | N24: =SUM(M24-M23) -> 0 | O24: =O23 -> 529.52 | P24: =SUM(O24-O23) -> 0 | Q24: =SUM(P24+N24) -> 0 | T24: =T23 -> 5167 | U24: =SUM(T24-T23) -> 0 | V24: =V23 -> 461 | W24: =+V24-V23 -> 0 | X24: =X23 -> 150365 | Y24: =SUM(X24-X23) -> 0 | Z24: =Z23 -> 98681 | AA24: =Z24-Z23 -> 0 | AB24: =AB23 -> 251 | AC24: =AC23 -> 731 | AD24: =AC24-AC23 -> 0 | AE24: =AE23 -> 229.03 | AF24: =AE24-AE23 -> 0 | AG24: =AG23 -> 2198.54 | AH24: =AG24-AG23 -> 0 | AI24: =AF24+AH24 -> 0 | AJ24: =+Z24-Z23 -> 0 | AK24: =SUM(Y24-L24) -> 13 | AL24: =SUM(AJ24-W24) -> 0 | AM24: ='[3]General information '!D24 -> 13.5 | AN24: ='[3]General information '!H24 -> 0 | AP24: ='[3]General information '!J24 -> 0 | AR24: =A24 -> 44274 | AS24: =AS23 -> 0.9 | AT24: =AT23 -> 77 | AU24: =AU23 -> 1.1 | AV24: =AV23 -> 118 | AW24: 2.9 | AX24: =AX23 -> 149 | AY24: =AS24*AT24 -> 69.3 | AZ24: =AU24*AV24 -> 129.8 | BA24: =AW24*AX24 -> 432.1 | BB24: =AY24-AY23 -> 0 | BC24: =AZ24-AZ23 -> 0 | BD24: =BA24-BA23 -> 0 | BE24: =SUM(BB24:BD24) -> 0 | BF24: =SUM(I24-BE24) -> 0 | BG24: =SUM(I24-BF24) -> 0
A25: =ELEC!C22 -> 44275 | B25: =B24 -> 109443 | C25: =B25-B24 -> 0 | D25: =C25/27 -> 0 | E25: =SUM((C25*$E$4)+(7500/'EDl log'!$A$37)) -> 241.93548 | G25: =G24 -> 616152 | H25: =G25-G24 -> 0 | I25: =C25+H25 -> 0 | J25: =IF(I25>0,E25/I25,0) -> 0 | K25: ='Swimming Pool quality check '!H25 -> 6726 | L25: =K25-K24 -> 13 | M25: =M24 -> 457.44 | N25: =SUM(M25-M24) -> 0 | O25: =O24 -> 529.52 | P25: =SUM(O25-O24) -> 0 | Q25: =SUM(P25+N25) -> 0 | T25: =T24 -> 5167 | U25: =SUM(T25-T24) -> 0 | V25: =V24 -> 461 | W25: =+V25-V24 -> 0 | X25: =X24 -> 150365 | Y25: =SUM(X25-X24) -> 0 | Z25: =Z24 -> 98681 | AA25: =Z25-Z24 -> 0 | AB25: =AB24 -> 251 | AC25: =AC24 -> 731 | AD25: =AC25-AC24 -> 0 | AE25: =AE24 -> 229.03 | AF25: =AE25-AE24 -> 0 | AG25: =AG24 -> 2198.54 | AH25: =AG25-AG24 -> 0 | AI25: =AF25+AH25 -> 0 | AJ25: =+Z25-Z24 -> 0 | AK25: =SUM(Y25-L25) -> -13 | AL25: =SUM(AJ25-W25) -> 0 | AM25: ='General information '!D25 -> 0 | AN25: ='General information '!H25 -> 0 | AP25: ='General information '!J25 -> 0 | AR25: =A25 -> 44275 | AS25: =AS24 -> 0.9 | AT25: =AT24 -> 77 | AU25: =AU24 -> 1.1 | AV25: =AV24 -> 118 | AW25: 2.9 | AX25: =AX24 -> 149 | AY25: =AS25*AT25 -> 69.3 | AZ25: =AU25*AV25 -> 129.8 | BA25: =AW25*AX25 -> 432.1 | BB25: =AY25-AY24 -> 0 | BC25: =AZ25-AZ24 -> 0 | BD25: =BA25-BA24 -> 0 | BE25: =SUM(BB25:BD25) -> 0 | BF25: =SUM(I25-BE25) -> 0 | BG25: =SUM(I25-BF25) -> 0
A26: =ELEC!C23 -> 44276 | B26: =B25 -> 109443 | C26: =B26-B25 -> 0 | D26: =C26/27 -> 0 | E26: =SUM((C26*$E$4)+(7500/'EDl log'!$A$37)) -> 241.93548 | G26: =G25 -> 616152 | H26: =G26-G25 -> 0 | I26: =C26+H26 -> 0 | J26: =IF(I26>0,E26/I26,0) -> 0 | K26: ='Swimming Pool quality check '!H26 -> 6726 | L26: =K26-K25 -> 0 | M26: =M25 -> 457.44 | N26: =SUM(M26-M25) -> 0 | O26: =O25 -> 529.52 | P26: =SUM(O26-O25) -> 0 | Q26: =SUM(P26+N26) -> 0 | T26: =T25 -> 5167 | U26: =SUM(T26-T25) -> 0 | V26: =V25 -> 461 | W26: =+V26-V25 -> 0 | X26: =X25 -> 150365 | Y26: =SUM(X26-X25) -> 0 | Z26: =Z25 -> 98681 | AA26: =Z26-Z25 -> 0 | AB26: =AB25 -> 251 | AC26: =AC25 -> 731 | AD26: =AC26-AC25 -> 0 | AE26: =AE25 -> 229.03 | AF26: =AE26-AE25 -> 0 | AG26: =AG25 -> 2198.54 | AH26: =AG26-AG25 -> 0 | AI26: =AF26+AH26 -> 0 | AJ26: =+Z26-Z25 -> 0 | AK26: =SUM(Y26-L26) -> 0 | AL26: =SUM(AJ26-W26) -> 0 | AM26: ='General information '!D26 -> 0 | AN26: ='General information '!H26 -> 0 | AP26: ='General information '!J26 -> 0 | AR26: =A26 -> 44276 | AS26: =AS25 -> 0.9 | AT26: =AT25 -> 77 | AU26: =AU25 -> 1.1 | AV26: =AV25 -> 118 | AW26: 2.9 | AX26: =AX25 -> 149 | AY26: =AS26*AT26 -> 69.3 | AZ26: =AU26*AV26 -> 129.8 | BA26: =AW26*AX26 -> 432.1 | BB26: =AY26-AY25 -> 0 | BC26: =AZ26-AZ25 -> 0 | BD26: =BA26-BA25 -> 0 | BE26: =SUM(BB26:BD26) -> 0 | BF26: =SUM(I26-BE26) -> 0 | BG26: =SUM(I26-BF26) -> 0
A27: =ELEC!C24 -> 44277 | B27: =B26 -> 109443 | C27: =B27-B26 -> 0 | D27: =C27/27 -> 0 | E27: =SUM((C27*$E$4)+(7500/'EDl log'!$A$37)) -> 241.93548 | G27: =G26 -> 616152 | H27: =G27-G26 -> 0 | I27: =C27+H27 -> 0 | J27: =IF(I27>0,E27/I27,0) -> 0 | K27: ='Swimming Pool quality check '!H27 -> 6726 | L27: =K27-K26 -> 0 | M27: =M26 -> 457.44 | N27: =SUM(M27-M26) -> 0 | O27: =O26 -> 529.52 | P27: =SUM(O27-O26) -> 0 | Q27: =SUM(P27+N27) -> 0 | T27: =T26 -> 5167 | U27: =SUM(T27-T26) -> 0 | V27: =V26 -> 461 | W27: =+V27-V26 -> 0 | X27: =X26 -> 150365 | Y27: =SUM(X27-X26) -> 0 | Z27: =Z26 -> 98681 | AA27: =Z27-Z26 -> 0 | AB27: =AB26 -> 251 | AC27: =AC26 -> 731 | AD27: =AC27-AC26 -> 0 | AE27: =AE26 -> 229.03 | AF27: =AE27-AE26 -> 0 | AG27: =AG26 -> 2198.54 | AH27: =AG27-AG26 -> 0 | AI27: =AF27+AH27 -> 0 | AJ27: =+Z27-Z26 -> 0 | AK27: =SUM(Y27-L27) -> 0 | AL27: =SUM(AJ27-W27) -> 0 | AM27: ='General information '!D27 -> 0 | AN27: ='General information '!H27 -> 0 | AP27: ='General information '!J27 -> 0 | AR27: =A27 -> 44277 | AS27: =AS26 -> 0.9 | AT27: =AT26 -> 77 | AU27: =AU26 -> 1.1 | AV27: =AV26 -> 118 | AW27: 2.9 | AX27: =AX26 -> 149 | AY27: =AS27*AT27 -> 69.3 | AZ27: =AU27*AV27 -> 129.8 | BA27: =AW27*AX27 -> 432.1 | BB27: =AY27-AY26 -> 0 | BC27: =AZ27-AZ26 -> 0 | BD27: =BA27-BA26 -> 0 | BE27: =SUM(BB27:BD27) -> 0 | BF27: =SUM(I27-BE27) -> 0 | BG27: =SUM(I27-BF27) -> 0
A28: =ELEC!C25 -> 44278 | B28: =B27 -> 109443 | C28: =B28-B27 -> 0 | D28: =C28/27 -> 0 | E28: =SUM((C28*$E$4)+(7500/'EDl log'!$A$37)) -> 241.93548 | G28: =G27 -> 616152 | H28: =G28-G27 -> 0 | I28: =C28+H28 -> 0 | J28: =IF(I28>0,E28/I28,0) -> 0 | K28: ='Swimming Pool quality check '!H28 -> 6726 | L28: =K28-K27 -> 0 | M28: =M27 -> 457.44 | N28: =SUM(M28-M27) -> 0 | O28: =O27 -> 529.52 | P28: =SUM(O28-O27) -> 0 | Q28: =SUM(P28+N28) -> 0 | T28: =T27 -> 5167 | U28: =SUM(T28-T27) -> 0 | V28: =V27 -> 461 | W28: =+V28-V27 -> 0 | X28: =X27 -> 150365 | Y28: =SUM(X28-X27) -> 0 | Z28: =Z27 -> 98681 | AA28: =Z28-Z27 -> 0 | AB28: =AB27 -> 251 | AC28: =AC27 -> 731 | AD28: =AC28-AC27 -> 0 | AE28: =AE27 -> 229.03 | AF28: =AE28-AE27 -> 0 | AG28: =AG27 -> 2198.54 | AH28: =AG28-AG27 -> 0 | AI28: =AF28+AH28 -> 0 | AJ28: =+Z28-Z27 -> 0 | AK28: =SUM(Y28-L28) -> 0 | AL28: =SUM(AJ28-W28) -> 0 | AM28: ='General information '!D28 -> 0 | AN28: ='General information '!H28 -> 0 | AP28: ='General information '!J28 -> 0 | AR28: =A28 -> 44278 | AS28: =AS27 -> 0.9 | AT28: =AT27 -> 77 | AU28: =AU27 -> 1.1 | AV28: =AV27 -> 118 | AW28: 2.9 | AX28: =AX27 -> 149 | AY28: =AS28*AT28 -> 69.3 | AZ28: =AU28*AV28 -> 129.8 | BA28: =AW28*AX28 -> 432.1 | BB28: =AY28-AY27 -> 0 | BC28: =AZ28-AZ27 -> 0 | BD28: =BA28-BA27 -> 0 | BE28: =SUM(BB28:BD28) -> 0 | BF28: =SUM(I28-BE28) -> 0 | BG28: =SUM(I28-BF28) -> 0
A29: =ELEC!C26 -> 44279 | B29: =B28 -> 109443 | C29: =B29-B28 -> 0 | D29: =C29/27 -> 0 | E29: =SUM((C29*$E$4)+(7500/'EDl log'!$A$37)) -> 241.93548 | G29: =G28 -> 616152 | H29: =G29-G28 -> 0 | I29: =C29+H29 -> 0 | J29: =IF(I29>0,E29/I29,0) -> 0 | K29: ='Swimming Pool quality check '!H29 -> 6726 | L29: =K29-K28 -> 0 | M29: =M28 -> 457.44 | N29: =SUM(M29-M28) -> 0 | O29: =O28 -> 529.52 | P29: =SUM(O29-O28) -> 0 | Q29: =SUM(P29+N29) -> 0 | T29: =T28 -> 5167 | U29: =SUM(T29-T28) -> 0 | V29: =V28 -> 461 | W29: =+V29-V28 -> 0 | X29: =X28 -> 150365 | Y29: =SUM(X29-X28) -> 0 | Z29: =Z28 -> 98681 | AA29: =Z29-Z28 -> 0 | AB29: =AB28 -> 251 | AC29: =AC28 -> 731 | AD29: =AC29-AC28 -> 0 | AE29: =AE28 -> 229.03 | AF29: =AE29-AE28 -> 0 | AG29: =AG28 -> 2198.54 | AH29: =AG29-AG28 -> 0 | AI29: =AF29+AH29 -> 0 | AJ29: =+Z29-Z28 -> 0 | AK29: =SUM(Y29-L29) -> 0 | AL29: =SUM(AJ29-W29) -> 0 | AM29: ='General information '!D29 -> 0 | AN29: ='General information '!H29 -> 0 | AP29: ='General information '!J29 -> 0 | AR29: =A29 -> 44279 | AS29: =AS28 -> 0.9 | AT29: =AT28 -> 77 | AU29: =AU28 -> 1.1 | AV29: =AV28 -> 118 | AW29: 2.9 | AX29: =AX28 -> 149 | AY29: =AS29*AT29 -> 69.3 | AZ29: =AU29*AV29 -> 129.8 | BA29: =AW29*AX29 -> 432.1 | BB29: =AY29-AY28 -> 0 | BC29: =AZ29-AZ28 -> 0 | BD29: =BA29-BA28 -> 0 | BE29: =SUM(BB29:BD29) -> 0 | BF29: =SUM(I29-BE29) -> 0 | BG29: =SUM(I29-BF29) -> 0
A30: =ELEC!C27 -> 44280 | B30: =B29 -> 109443 | C30: =B30-B29 -> 0 | D30: =C30/27 -> 0 | E30: =SUM((C30*$E$4)+(7500/'EDl log'!$A$37)) -> 241.93548 | G30: =G29 -> 616152 | H30: =G30-G29 -> 0 | I30: =C30+H30 -> 0 | J30: =IF(I30>0,E30/I30,0) -> 0 | K30: ='Swimming Pool quality check '!H30 -> 6726 | L30: =K30-K29 -> 0 | M30: =M29 -> 457.44 | N30: =SUM(M30-M29) -> 0 | O30: =O29 -> 529.52 | P30: =SUM(O30-O29) -> 0 | Q30: =SUM(P30+N30) -> 0 | T30: =T29 -> 5167 | U30: =SUM(T30-T29) -> 0 | V30: =V29 -> 461 | W30: =+V30-V29 -> 0 | X30: =X29 -> 150365 | Y30: =SUM(X30-X29) -> 0 | Z30: =Z29 -> 98681 | AA30: =Z30-Z29 -> 0 | AB30: =AB29 -> 251 | AC30: =AC29 -> 731 | AD30: =AC30-AC29 -> 0 | AE30: =AE29 -> 229.03 | AF30: =AE30-AE29 -> 0 | AG30: =AG29 -> 2198.54 | AH30: =AG30-AG29 -> 0 | AI30: =AF30+AH30 -> 0 | AJ30: =+Z30-Z29 -> 0 | AK30: =SUM(Y30-L30) -> 0 | AL30: =SUM(AJ30-W30) -> 0 | AM30: ='General information '!D30 -> 0 | AN30: ='General information '!H30 -> 0 | AP30: ='General information '!J30 -> 0 | AR30: =A30 -> 44280 | AS30: =AS29 -> 0.9 | AT30: =AT29 -> 77 | AU30: =AU29 -> 1.1 | AV30: =AV29 -> 118 | AW30: 2.9 | AX30: =AX29 -> 149 | AY30: =AS30*AT30 -> 69.3 | AZ30: =AU30*AV30 -> 129.8 | BA30: =AW30*AX30 -> 432.1 | BB30: =AY30-AY29 -> 0 | BC30: =AZ30-AZ29 -> 0 | BD30: =BA30-BA29 -> 0 | BE30: =SUM(BB30:BD30) -> 0 | BF30: =SUM(I30-BE30) -> 0 | BG30: =SUM(I30-BF30) -> 0
A31: =ELEC!C28 -> 44281 | B31: =B30 -> 109443 | C31: =B31-B30 -> 0 | D31: =C31/27 -> 0 | E31: =SUM((C31*$E$4)+(7500/'EDl log'!$A$37)) -> 241.93548 | G31: =G30 -> 616152 | H31: =G31-G30 -> 0 | I31: =C31+H31 -> 0 | J31: =IF(I31>0,E31/I31,0) -> 0 | K31: ='Swimming Pool quality check '!H31 -> 6726 | L31: =K31-K30 -> 0 | M31: =M30 -> 457.44 | N31: =SUM(M31-M30) -> 0 | O31: =O30 -> 529.52 | P31: =SUM(O31-O30) -> 0 | Q31: =SUM(P31+N31) -> 0 | T31: =T30 -> 5167 | U31: =SUM(T31-T30) -> 0 | V31: =V30 -> 461 | W31: =+V31-V30 -> 0 | X31: =X30 -> 150365 | Y31: =SUM(X31-X30) -> 0 | Z31: =Z30 -> 98681 | AA31: =Z31-Z30 -> 0 | AB31: =AB30 -> 251 | AC31: =AC30 -> 731 | AD31: =AC31-AC30 -> 0 | AE31: =AE30 -> 229.03 | AF31: =AE31-AE30 -> 0 | AG31: =AG30 -> 2198.54 | AH31: =AG31-AG30 -> 0 | AI31: =AF31+AH31 -> 0 | AJ31: =+Z31-Z30 -> 0 | AK31: =SUM(Y31-L31) -> 0 | AL31: =SUM(AJ31-W31) -> 0 | AM31: ='General information '!D31 -> 0 | AN31: ='General information '!H31 -> 0 | AP31: ='General information '!J31 -> 0 | AR31: =A31 -> 44281 | AS31: =AS30 -> 0.9 | AT31: =AT30 -> 77 | AU31: =AU30 -> 1.1 | AV31: =AV30 -> 118 | AW31: 2.9 | AX31: =AX30 -> 149 | AY31: =AS31*AT31 -> 69.3 | AZ31: =AU31*AV31 -> 129.8 | BA31: =AW31*AX31 -> 432.1 | BB31: =AY31-AY30 -> 0 | BC31: =AZ31-AZ30 -> 0 | BD31: =BA31-BA30 -> 0 | BE31: =SUM(BB31:BD31) -> 0 | BF31: =SUM(I31-BE31) -> 0 | BG31: =SUM(I31-BF31) -> 0
A32: =ELEC!C29 -> 44282 | B32: =B31 -> 109443 | C32: =B32-B31 -> 0 | D32: =C32/27 -> 0 | E32: =SUM((C32*$E$4)+(7500/'EDl log'!$A$37)) -> 241.93548 | G32: =G31 -> 616152 | H32: =G32-G31 -> 0 | I32: =C32+H32 -> 0 | J32: =IF(I32>0,E32/I32,0) -> 0 | K32: ='Swimming Pool quality check '!H32 -> 6726 | L32: =K32-K31 -> 0 | M32: =M31 -> 457.44 | N32: =SUM(M32-M31) -> 0 | O32: =O31 -> 529.52 | P32: =SUM(O32-O31) -> 0 | Q32: =SUM(P32+N32) -> 0 | T32: =T31 -> 5167 | U32: =SUM(T32-T31) -> 0 | V32: =V31 -> 461 | W32: =+V32-V31 -> 0 | X32: =X31 -> 150365 | Y32: =SUM(X32-X31) -> 0 | Z32: =Z31 -> 98681 | AA32: =Z32-Z31 -> 0 | AB32: =AB31 -> 251 | AC32: =AC31 -> 731 | AD32: =AC32-AC31 -> 0 | AE32: =AE31 -> 229.03 | AF32: =AE32-AE31 -> 0 | AG32: =AG31 -> 2198.54 | AH32: =AG32-AG31 -> 0 | AI32: =AF32+AH32 -> 0 | AJ32: =+Z32-Z31 -> 0 | AK32: =SUM(Y32-L32) -> 0 | AL32: =SUM(AJ32-W32) -> 0 | AM32: ='General information '!D32 -> 0 | AN32: ='General information '!H32 -> 0 | AP32: ='General information '!J32 -> 0 | AR32: =A32 -> 44282 | AS32: =AS31 -> 0.9 | AT32: =AT31 -> 77 | AU32: =AU31 -> 1.1 | AV32: =AV31 -> 118 | AW32: 2.9 | AX32: =AX31 -> 149 | AY32: =AS32*AT32 -> 69.3 | AZ32: =AU32*AV32 -> 129.8 | BA32: =AW32*AX32 -> 432.1 | BB32: =AY32-AY31 -> 0 | BC32: =AZ32-AZ31 -> 0 | BD32: =BA32-BA31 -> 0 | BE32: =SUM(BB32:BD32) -> 0 | BF32: =SUM(I32-BE32) -> 0 | BG32: =SUM(I32-BF32) -> 0
A33: =ELEC!C30 -> 44283 | B33: =B32 -> 109443 | C33: =B33-B32 -> 0 | D33: =C33/27 -> 0 | E33: =SUM((C33*$E$4)+(7500/'EDl log'!$A$37)) -> 241.93548 | G33: =G32 -> 616152 | H33: =G33-G32 -> 0 | I33: =C33+H33 -> 0 | J33: =IF(I33>0,E33/I33,0) -> 0 | K33: ='Swimming Pool quality check '!H33 -> 6726 | L33: =K33-K32 -> 0 | M33: =M32 -> 457.44 | N33: =SUM(M33-M32) -> 0 | O33: =O32 -> 529.52 | P33: =SUM(O33-O32) -> 0 | Q33: =SUM(P33+N33) -> 0 | T33: =T32 -> 5167 | U33: =SUM(T33-T32) -> 0 | V33: =V32 -> 461 | W33: =+V33-V32 -> 0 | X33: =X32 -> 150365 | Y33: =SUM(X33-X32) -> 0 | Z33: =Z32 -> 98681 | AA33: =Z33-Z32 -> 0 | AB33: =AB32 -> 251 | AC33: =AC32 -> 731 | AD33: =AC33-AC32 -> 0 | AE33: =AE32 -> 229.03 | AF33: =AE33-AE32 -> 0 | AG33: =AG32 -> 2198.54 | AH33: =AG33-AG32 -> 0 | AI33: =AF33+AH33 -> 0 | AJ33: =+Z33-Z32 -> 0 | AK33: =SUM(Y33-L33) -> 0 | AL33: =SUM(AJ33-W33) -> 0 | AM33: ='General information '!D33 -> 0 | AN33: ='General information '!H33 -> 0 | AP33: ='General information '!J33 -> 0 | AR33: =A33 -> 44283 | AS33: =AS32 -> 0.9 | AT33: =AT32 -> 77 | AU33: =AU32 -> 1.1 | AV33: =AV32 -> 118 | AW33: 2.9 | AX33: =AX32 -> 149 | AY33: =AS33*AT33 -> 69.3 | AZ33: =AU33*AV33 -> 129.8 | BA33: =AW33*AX33 -> 432.1 | BB33: =AY33-AY32 -> 0 | BC33: =AZ33-AZ32 -> 0 | BD33: =BA33-BA32 -> 0 | BE33: =SUM(BB33:BD33) -> 0 | BF33: =SUM(I33-BE33) -> 0 | BG33: =SUM(I33-BF33) -> 0
A34: =ELEC!C31 -> 44284 | B34: =B33 -> 109443 | C34: =B34-B33 -> 0 | D34: =C34/27 -> 0 | E34: =SUM((C34*$E$4)+(7500/'EDl log'!$A$37)) -> 241.93548 | G34: =G33 -> 616152 | H34: =G34-G33 -> 0 | I34: =C34+H34 -> 0 | J34: =IF(I34>0,E34/I34,0) -> 0 | K34: ='Swimming Pool quality check '!H34 -> 6726 | L34: =K34-K33 -> 0 | M34: =M33 -> 457.44 | N34: =SUM(M34-M33) -> 0 | O34: =O33 -> 529.52 | P34: =SUM(O34-O33) -> 0 | Q34: =SUM(P34+N34) -> 0 | T34: =T33 -> 5167 | U34: =SUM(T34-T33) -> 0 | V34: =V33 -> 461 | W34: =+V34-V33 -> 0 | X34: =X33 -> 150365 | Y34: =SUM(X34-X33) -> 0 | Z34: =Z33 -> 98681 | AA34: =Z34-Z33 -> 0 | AB34: =AB33 -> 251 | AC34: =AC33 -> 731 | AD34: =AC34-AC33 -> 0 | AE34: =AE33 -> 229.03 | AF34: =AE34-AE33 -> 0 | AG34: =AG33 -> 2198.54 | AH34: =AG34-AG33 -> 0 | AI34: =AF34+AH34 -> 0 | AJ34: =+Z34-Z33 -> 0 | AK34: =SUM(Y34-L34) -> 0 | AL34: =SUM(AJ34-W34) -> 0 | AM34: ='General information '!D34 -> 0 | AN34: ='General information '!H34 -> 0 | AP34: ='General information '!J34 -> 0 | AR34: =A34 -> 44284 | AS34: =AS33 -> 0.9 | AT34: =AT33 -> 77 | AU34: =AU33 -> 1.1 | AV34: =AV33 -> 118 | AW34: 2.9 | AX34: =AX33 -> 149 | AY34: =AS34*AT34 -> 69.3 | AZ34: =AU34*AV34 -> 129.8 | BA34: =AW34*AX34 -> 432.1 | BB34: =AY34-AY33 -> 0 | BC34: =AZ34-AZ33 -> 0 | BD34: =BA34-BA33 -> 0 | BE34: =SUM(BB34:BD34) -> 0 | BF34: =SUM(I34-BE34) -> 0 | BG34: =SUM(I34-BF34) -> 0
A35: =ELEC!C32 -> 44285 | B35: =B34 -> 109443 | C35: =B35-B34 -> 0 | D35: =C35/27 -> 0 | E35: =SUM((C35*$E$4)+(7500/'EDl log'!$A$37)) -> 241.93548 | G35: =G34 -> 616152 | H35: =G35-G34 -> 0 | I35: =C35+H35 -> 0 | J35: =IF(I35>0,E35/I35,0) -> 0 | K35: ='Swimming Pool quality check '!H35 -> 6726 | L35: =K35-K34 -> 0 | M35: =M34 -> 457.44 | N35: =SUM(M35-M34) -> 0 | O35: =O34 -> 529.52 | P35: =SUM(O35-O34) -> 0 | Q35: =SUM(P35+N35) -> 0 | T35: =T34 -> 5167 | U35: =SUM(T35-T34) -> 0 | V35: =V34 -> 461 | W35: =+V35-V34 -> 0 | X35: =X34 -> 150365 | Y35: =SUM(X35-X34) -> 0 | Z35: =Z34 -> 98681 | AA35: =Z35-Z34 -> 0 | AB35: =AB34 -> 251 | AC35: =AC34 -> 731 | AD35: =AC35-AC34 -> 0 | AE35: =AE34 -> 229.03 | AF35: =AE35-AE34 -> 0 | AG35: =AG34 -> 2198.54 | AH35: =AG35-AG34 -> 0 | AI35: =AF35+AH35 -> 0 | AJ35: =+Z35-Z34 -> 0 | AK35: =SUM(Y35-L35) -> 0 | AL35: =SUM(AJ35-W35) -> 0 | AM35: ='General information '!D35 -> 0 | AN35: ='General information '!H35 -> 0 | AP35: ='General information '!J35 -> 0 | AR35: =A35 -> 44285 | AS35: =AS34 -> 0.9 | AT35: =AT34 -> 77 | AU35: =AU34 -> 1.1 | AV35: =AV34 -> 118 | AW35: 2.9 | AX35: =AX34 -> 149 | AY35: =AS35*AT35 -> 69.3 | AZ35: =AU35*AV35 -> 129.8 | BA35: =AW35*AX35 -> 432.1 | BB35: =AY35-AY34 -> 0 | BC35: =AZ35-AZ34 -> 0 | BD35: =BA35-BA34 -> 0 | BE35: =SUM(BB35:BD35) -> 0 | BF35: =SUM(I35-BE35) -> 0 | BG35: =SUM(I35-BF35) -> 0
A36: =ELEC!C33 -> 44286 | B36: =B35 -> 109443 | C36: =B36-B35 -> 0 | D36: =C36/27 -> 0 | E36: =SUM((C36*$E$4)+(7500/'EDl log'!$A$37)) -> 241.93548 | G36: =G35 -> 616152 | H36: =G36-G35 -> 0 | I36: =C36+H36 -> 0 | J36: =IF(I36>0,E36/I36,0) -> 0 | K36: ='Swimming Pool quality check '!H36 -> 6726 | L36: =K36-K35 -> 0 | M36: =M35 -> 457.44 | N36: =SUM(M36-M35) -> 0 | O36: =O35 -> 529.52 | P36: =SUM(O36-O35) -> 0 | Q36: =SUM(P36+N36) -> 0 | T36: =T35 -> 5167 | U36: =SUM(T36-T35) -> 0 | V36: =V35 -> 461 | W36: =+V36-V35 -> 0 | X36: =X35 -> 150365 | Y36: =SUM(X36-X35) -> 0 | Z36: =Z35 -> 98681 | AA36: =Z36-Z35 -> 0 | AB36: =AB35 -> 251 | AC36: =AC35 -> 731 | AD36: =AC36-AC35 -> 0 | AE36: =AE35 -> 229.03 | AF36: =AE36-AE35 -> 0 | AG36: =AG35 -> 2198.54 | AH36: =AG36-AG35 -> 0 | AI36: =AF36+AH36 -> 0 | AJ36: =+Z36-Z35 -> 0 | AK36: =SUM(Y36-L36) -> 0 | AL36: =SUM(AJ36-W36) -> 0 | AM36: ='General information '!D36 -> 0 | AN36: ='General information '!H36 -> 0 | AP36: ='General information '!J36 -> 0 | AR36: =A36 -> 44286 | AS36: =AS35 -> 0.9 | AT36: =AT35 -> 77 | AU36: =AU35 -> 1.1 | AV36: =AV35 -> 118 | AW36: 2.9 | AX36: =AX35 -> 149 | AY36: =AS36*AT36 -> 69.3 | AZ36: =AU36*AV36 -> 129.8 | BA36: =AW36*AX36 -> 432.1 | BB36: =AY36-AY35 -> 0 | BC36: =AZ36-AZ35 -> 0 | BD36: =BA36-BA35 -> 0 | BE36: =SUM(BB36:BD36) -> 0 | BF36: =SUM(I36-BE36) -> 0 | BG36: =SUM(I36-BF36) -> 0
C37: =SUM(C6:C33) -> 0 | D37: =SUM(D6:D33) -> 0 | F37: =SUM(F6:F33) -> 0 | H37: =SUM(H6:H33) -> 0 | I37: =SUM(I6:I33) -> 0 | L37: =SUM(L7:L33) -> 5 | Q37: =SUM(Q5:Q33) -> 0 | U37: =SUM(U6:U33) -> 0 | Y37: =SUM(#REF!,Y33,Y31,Y29,Y27,Y25,Y23,Y21,Y19,Y17,Y15,Y13,Y11,Y9,Y7,#REF!) -> #REF! | AJ37: =SUM(AJ6:AJ33) -> 0 | AK37: =SUM(Y37-L37) -> #REF! | AL37: =SUM(AL6:AL33) -> 0
C38: =+C37*1.66 -> 0 | E38: =SUM(E6:E33) -> 6774.1935 | F38: =SUM(F6:F33) -> 0 | H38: 7500 | I38: =SUM('General information '!G37/WATER!I37) -> #DIV/0! | O38: =SUM(Q37+I37) -> 0 | Z38: =SUM(Y37:AJ37) -> #REF! | AK38: =SUM(Y38-L38) -> 0
B39: =9*27 -> 243 | D39: =SUM(D6:D33) -> 0 | F39: =SUM(F6:F33) -> 0 | G39: =SUM(I37) -> 0 | H39: =SUM(H38+C38) -> 7500 | K39: =SUM(H39/G39) -> #DIV/0! | AJ39: =SUM(C38-AK38) -> 0 | AM39: =SUM(AJ39/AO38) -> #DIV/0!

Sheet graphic

Sheet General information 
A1: GENERAL & HOTEL'S INFORMATION SHEET
B4: Max Temp | C4: MIN TEMP | D4: AVE TEMP | E4: AVE Humidity | F4: AVE OCC | G4: # of OCC Rooms | H4: Ball room | I4: Meeting rooms | J4: Outlets | K4: Total covers | L4: # of permenant Emp | M4: # of casuals | N4: Total # of EMP | O4: # of EMP/OCC Room
A5: =ELEC!C2 -> 44255 | B5: 19 | C5: 14 | D5: ='[2]General information '!D36 -> 18 | E5: ='[2]General information '!E36 -> 0.55 | F5: ='[2]General information '!F36 -> 0 | G5: ='[2]General information '!G36 -> 0 | H5: ='[2]General information '!H36 -> 0 | I5: ='[2]General information '!I36 -> 0 | J5: ='[2]General information '!J36 -> 0 | K5: ='[2]General information '!K36 -> 0 | ... O5: ='[2]General information '!O36 -> 0
A6: =ELEC!C3 -> 44256 | B6: 18 | C6: 14 | D6: =(C6+B6)/2 -> 16 | E6: 0.69 | F6: 0 | G6: =F6*230 -> 0 | H6: 0 | I6: 0 | J6: 0 | K6: =+J6+H6 -> 0
A7: =ELEC!C4 -> 44257 | B7: 18 | C7: 13 | D7: =(C7+B7)/2 -> 15.5 | E7: 0.64 | F7: 0 | G7: =F7*230 -> 0 | H7: 0 | I7: 0 | J7: 0 | K7: =+J7+H7 -> 0
A8: =ELEC!C5 -> 44258 | B8: 18 | C8: 13 | D8: =(C8+B8)/2 -> 15.5 | E8: 0.65 | F8: 0 | G8: =F8*230 -> 0 | H8: 0 | I8: 0 | J8: 0 | K8: =+J8+H8 -> 0
A9: =ELEC!C6 -> 44259 | B9: 18 | C9: 13 | D9: =(C9+B9)/2 -> 15.5 | E9: 0.59 | F9: 0 | G9: =F9*230 -> 0 | H9: 0 | I9: 0 | J9: 0 | K9: =+J9+H9 -> 0
A10: =ELEC!C7 -> 44260 | B10: 19 | C10: 12 | D10: =(C10+B10)/2 -> 15.5 | E10: 0.64 | F10: 0 | G10: =F10*230 -> 0 | H10: 0 | I10: 0 | J10: 0 | K10: =+J10+H10 -> 0
A11: =ELEC!C8 -> 44261 | B11: 18 | C11: 14 | D11: =(C11+B11)/2 -> 16 | E11: 0.67 | F11: 0 | G11: =F11*230 -> 0 | H11: 0 | I11: 0 | J11: 0 | K11: =+J11+H11 -> 0
A12: =ELEC!C9 -> 44262 | B12: 19 | C12: 14 | D12: =(C12+B12)/2 -> 16.5 | E12: 0.65 | F12: 0 | G12: =F12*230 -> 0 | H12: 0 | I12: 0 | J12: 0 | K12: =+J12+H12 -> 0
A13: =ELEC!C10 -> 44263 | B13: 20 | C13: 16 | D13: =(C13+B13)/2 -> 18 | E13: 0.76 | F13: 0 | G13: =F13*230 -> 0 | H13: 0 | I13: 0 | J13: 0 | K13: =+J13+H13 -> 0
A14: =ELEC!C11 -> 44264 | D14: =(C14+B14)/2 -> 0 | F14: 0 | G14: =F14*230 -> 0 | H14: 0 | I14: 0 | J14: 0 | K14: =+J14+H14 -> 0
A15: =ELEC!C12 -> 44265 | D15: =(C15+B15)/2 -> 0 | F15: 0 | G15: =F15*230 -> 0 | H15: 0 | I15: 0 | J15: 0 | K15: =+J15+H15 -> 0
A16: =ELEC!C13 -> 44266 | D16: =(C16+B16)/2 -> 0 | F16: 0 | G16: =F16*230 -> 0 | H16: 0 | I16: 0 | J16: 0 | K16: =+J16+H16 -> 0
A17: =ELEC!C14 -> 44267 | D17: =(C17+B17)/2 -> 0 | F17: 0 | G17: =F17*230 -> 0 | H17: 0 | I17: 0 | J17: 0 | K17: =+J17+H17 -> 0
A18: =ELEC!C15 -> 44268 | D18: =(C18+B18)/2 -> 0 | F18: 0 | G18: =F18*230 -> 0 | H18: 0 | I18: 0 | J18: 0 | K18: =+J18+H18 -> 0
A19: =ELEC!C16 -> 44269 | D19: =(C19+B19)/2 -> 0 | F19: 0 | G19: =F19*230 -> 0 | H19: 0 | I19: 0 | J19: 0 | K19: =+J19+H19 -> 0
A20: =ELEC!C17 -> 44270 | D20: =(C20+B20)/2 -> 0 | F20: 0 | G20: =F20*230 -> 0 | H20: 0 | I20: 0 | J20: 0 | K20: =+J20+H20 -> 0
A21: =ELEC!C18 -> 44271 | D21: =(C21+B21)/2 -> 0 | F21: 0 | G21: =F21*230 -> 0 | H21: 0 | I21: 0 | J21: 0 | K21: =+J21+H21 -> 0
A22: =ELEC!C19 -> 44272 | D22: =(C22+B22)/2 -> 0 | F22: 0 | G22: =F22*230 -> 0 | H22: 0 | I22: 0 | J22: 0 | K22: =+J22+H22 -> 0
A23: =ELEC!C20 -> 44273 | D23: =(C23+B23)/2 -> 0 | F23: 0 | G23: =F23*230 -> 0 | H23: 0 | I23: 0 | J23: 0 | K23: =+J23+H23 -> 0
A24: =ELEC!C21 -> 44274 | D24: =(C24+B24)/2 -> 0 | F24: 0 | G24: =F24*230 -> 0 | H24: 0 | I24: 0 | J24: 0 | K24: =+J24+H24 -> 0
A25: =ELEC!C22 -> 44275 | D25: =(C25+B25)/2 -> 0 | F25: 0 | G25: =F25*230 -> 0 | H25: 0 | I25: 0 | J25: 0 | K25: =+J25+H25 -> 0
A26: =ELEC!C23 -> 44276 | D26: =(C26+B26)/2 -> 0 | F26: 0 | G26: =F26*230 -> 0 | H26: 0 | I26: 0 | J26: 0 | K26: =+J26+H26 -> 0
A27: =ELEC!C24 -> 44277 | D27: =(C27+B27)/2 -> 0 | F27: 0 | G27: =F27*230 -> 0 | H27: 0 | I27: 0 | J27: 0 | K27: =+J27+H27+I27 -> 0
A28: =ELEC!C25 -> 44278 | D28: =(C28+B28)/2 -> 0 | F28: 0 | G28: =F28*230 -> 0 | H28: 0 | I28: 0 | J28: 0 | K28: =+J28+H28+I28 -> 0
A29: =ELEC!C26 -> 44279 | D29: =(C29+B29)/2 -> 0 | F29: 0 | G29: =F29*230 -> 0 | H29: 0 | I29: 0 | J29: 0 | K29: =+J29+H29+I29 -> 0
A30: =ELEC!C27 -> 44280 | D30: =(C30+B30)/2 -> 0 | F30: 0 | G30: =F30*230 -> 0 | H30: 0 | I30: 0 | J30: 0 | K30: =+J30+H30+I30 -> 0
A31: =ELEC!C28 -> 44281 | D31: =(C31+B31)/2 -> 0 | F31: 0 | G31: =F31*230 -> 0 | H31: 0 | I31: 0 | J31: 0 | K31: =+J31+H31+I31 -> 0
A32: =ELEC!C29 -> 44282 | D32: =(C32+B32)/2 -> 0 | F32: 0 | G32: =F32*230 -> 0 | H32: 0 | I32: 0 | J32: 0 | K32: =+J32+H32+I32 -> 0
A33: =ELEC!C30 -> 44283 | D33: =(C33+B33)/2 -> 0 | F33: 0 | G33: =F33*230 -> 0 | H33: 0 | I33: 0 | J33: 0 | K33: =+J33+H33+I33 -> 0
A34: =ELEC!C31 -> 44284 | D34: =(C34+B34)/2 -> 0 | F34: 0 | G34: =F34*230 -> 0 | H34: 0 | I34: 0 | J34: 0 | K34: =+J34+H34+I34 -> 0
A35: =ELEC!C32 -> 44285 | D35: =(C35+B35)/2 -> 0 | F35: 0 | G35: =F35*230 -> 0 | H35: 0 | I35: 0 | J35: 0 | K35: =+J35+H35+I35 -> 0
A36: =ELEC!C33 -> 44286 | D36: =(C36+B36)/2 -> 0 | F36: 0 | G36: =F36*230 -> 0 | H36: 0 | I36: 0 | J36: 0 | K36: =+J36+H36+I36 -> 0
F37: =AVERAGE(F6:F33) -> 0 | G37: =SUM(G6:G33) -> 0
D38: =SUM(D6:D33)/'EDl log'!A35 -> 16.0625
I41: http://www.accuweather.com/en/lb/lebanon-weather

Sheet tanks
B2: Tank 1 | D2: Tank 2 | F2: Tank 3 | H2: Tank 4 | J2: Tank 5 | L2: Tank 6 | N2: Tank 7 | P2: Tank 8 | R2: Tank 9 | T2: Tank 10 | V2: Tank 11 | Z2: Tank 1 | AB2: Tank 2 | AD2: Tank 3 | AF2: Tank 4 | AH2: Tank 5 | AJ2: Tank 6 | AL2: Tank 7
B3: 6670 | D3: =SUM(B3) -> 6670 | F3: =SUM(D3) -> 6670 | H3: =SUM(F3) -> 6670 | J3: =SUM(H3) -> 6670 | L3: =SUM(J3) -> 6670 | N3: =SUM(L3) -> 6670 | P3: =SUM(N3) -> 6670 | R3: =SUM(P3) -> 6670 | T3: =SUM(R3) -> 6670 | V3: =SUM(T3) -> 6670 | W3: =SUM(B3:V3) -> 73370 | Z3: 2800 | AB3: 2800 | AD3: 2800 | AF3: 2800 | AH3: 2800 | AJ3: 2800 | AL3: 2800 | AM3: =SUM(Z3:AL3) -> 19600 | AO3: =SUM(AM3+W3) -> 92970 | AR3: Total sotck | AS3: Diesel Cons Per day | AT3: Diesel Delivery | BE3: Genset Co | BF3: Steam | BG3: Boil | BH3: Outdoor temperature
B4: =B3/310 -> 21.516129 | D4: =SUM(B4) -> 21.516129 | F4: =SUM(D4) -> 21.516129 | H4: =SUM(F4) -> 21.516129 | J4: =SUM(H4) -> 21.516129 | L4: =SUM(J4) -> 21.516129 | N4: =SUM(L4) -> 21.516129 | P4: =SUM(N4) -> 21.516129 | R4: =SUM(P4) -> 21.516129 | T4: =SUM(R4) -> 21.516129 | V4: =SUM(T4) -> 21.516129 | Z4: =Z3/280 -> 10 | AA4: =AA3/280 -> 0 | AB4: =AB3/280 -> 10 | AC4: =AC3/280 -> 0 | AD4: =AD3/280 -> 10 | AE4: =AE3/280 -> 0 | AF4: =AF3/280 -> 10 | AG4: =AG3/280 -> 0 | ... AL4: =AL3/280 -> 10 | AT4: Delivery | AU4: Cost /L | AW4: Boiler+Steam | AX4: Generator | AZ4: Occupancy | BA4: AVE TEPM | BB4: AVE Humidity
A5: =ELEC!C2 -> 44255 | B5: =[1]tanks!B33 -> 218 | C5: =[1]tanks!C33 -> 4690.5161 | D5: =[1]tanks!D33 -> 218 | E5: =[1]tanks!E33 -> 4690.5161 | F5: =[1]tanks!F33 -> 218 | G5: =[1]tanks!G33 -> 4690.5161 | H5: =[1]tanks!H33 -> 218 | I5: =[1]tanks!I33 -> 4690.5161 | ... BB5: =[1]tanks!BB33 -> 0.68 | BC5: =[2]tanks!BC36 -> 0 | BD5: =[2]tanks!BD36 -> 19222 | BE5: =[2]tanks!BE36 -> #REF! | BF5: =[2]tanks!BF36 -> 0 | BG5: =[2]tanks!BG36 -> #REF! | BH5: =[4]tanks!BH36 -> 0
A6: =ELEC!C3 -> 44256 | B6: ='B5'!B5 -> 209 | C6: =B6*$B$4 -> 4496.871 | D6: =SUM(B6) -> 209 | E6: =D6*$B$4 -> 4496.871 | F6: =SUM(D6) -> 209 | G6: =F6*$B$4 -> 4496.871 | H6: =SUM(F6) -> 209 | I6: =H6*$B$4 -> 4496.871 | J6: =SUM(H6) -> 209 | K6: =J6*$B$4 -> 4496.871 | L6: =SUM(J6) -> 209 | M6: =L6*$B$4 -> 4496.871 | N6: =SUM(L6) -> 209 | O6: =N6*$B$4 -> 4496.871 | P6: =SUM(N6) -> 209 | Q6: =P6*$B$4 -> 4496.871 | R6: =SUM(P6) -> 209 | S6: =R6*$B$4 -> 4496.871 | T6: =SUM(R6) -> 209 | U6: =T6*$B$4 -> 4496.871 | V6: =SUM(T6) -> 209 | W6: =V6*$B$4 -> 4496.871 | X6: =SUM(Y6/73370) -> 0.67419355 | Y6: =SUM(C6+E6+G6+I6+K6+M6+O6+Q6+S6+U6+W6) -> 49465.581 | Z6: ='B5'!C5 -> 206 | AA6: =SUM(Z6*$Z$4) -> 2060 | AB6: =SUM(Z6) -> 206 | AC6: =SUM(AB6*$Z$4) -> 2060 | AD6: =SUM(AB6) -> 206 | AE6: =SUM(AD6*$Z$4) -> 2060 | AF6: =SUM(AD6) -> 206 | AG6: =SUM(AF6*$Z$4) -> 2060 | AH6: =SUM(AF6) -> 206 | AI6: =SUM(AH6*$Z$4) -> 2060 | AJ6: =SUM(AH6) -> 206 | AK6: =SUM(AJ6*$Z$4) -> 2060 | AL6: =SUM(AJ6) -> 206 | AM6: =SUM(AL6*$Z$4) -> 2060 | AN6: =SUM(AO6/19600) -> 0.73571429 | AO6: =SUM(AA6+AC6+AE6+AG6+AI6+AK6+AM6) -> 14420 | AQ6: =SUM(AR6/92970) -> 0.68716339 | AR6: =Y6+AO6 -> 63885.581 | AS6: =SUM(AR6-AR5-AT6) -> -3460.0968 | AV6: =IF(AT6>0,AU6,AV5) -> 0.74 | AW6: =-SUM('B5'!AI5) -> -420.2 | AX6: =-SUM(AW6-AS6) -> -3039.8968 | AY6: =SUM(AX6+AW6) -> -3460.0968 | AZ6: =ELEC!A3 -> 0 | BA6: ='General information '!D6 -> 16 | BB6: =SUM('General information '!E6) -> 0.69 | BC6: =IF(AR3>=AR6,0,1) -> 0 | BD6: 19222 | BE6: =(305/1185)*ELEC!Q4 -> 1888.1688 | BG6: =#REF!-BE6 -> #REF! | BH6: 21
A7: =ELEC!C4 -> 44257 | B7: ='B5'!B6 -> 199 | C7: =B7*$B$4 -> 4281.7097 | D7: =SUM(B7) -> 199 | E7: =D7*$B$4 -> 4281.7097 | F7: =SUM(D7) -> 199 | G7: =F7*$B$4 -> 4281.7097 | H7: =SUM(F7) -> 199 | I7: =H7*$B$4 -> 4281.7097 | J7: =SUM(H7) -> 199 | K7: =J7*$B$4 -> 4281.7097 | L7: =SUM(J7) -> 199 | M7: =L7*$B$4 -> 4281.7097 | N7: =SUM(L7) -> 199 | O7: =N7*$B$4 -> 4281.7097 | P7: =SUM(N7) -> 199 | Q7: =P7*$B$4 -> 4281.7097 | R7: =SUM(P7) -> 199 | S7: =R7*$B$4 -> 4281.7097 | T7: =SUM(R7) -> 199 | U7: =T7*$B$4 -> 4281.7097 | V7: =SUM(T7) -> 199 | W7: =V7*$B$4 -> 4281.7097 | X7: =SUM(Y7/73370) -> 0.64193548 | Y7: =SUM(C7+E7+G7+I7+K7+M7+O7+Q7+S7+U7+W7) -> 47098.806 | Z7: ='B5'!C6 -> 205 | AA7: =SUM(Z7*$Z$4) -> 2050 | AB7: =SUM(Z7) -> 205 | AC7: =SUM(AB7*$Z$4) -> 2050 | AD7: =SUM(AB7) -> 205 | AE7: =SUM(AD7*$Z$4) -> 2050 | AF7: =SUM(AD7) -> 205 | AG7: =SUM(AF7*$Z$4) -> 2050 | AH7: =SUM(AF7) -> 205 | AI7: =SUM(AH7*$Z$4) -> 2050 | AJ7: =SUM(AH7) -> 205 | AK7: =SUM(AJ7*$Z$4) -> 2050 | AL7: =SUM(AJ7) -> 205 | AM7: =SUM(AL7*$Z$4) -> 2050 | AN7: =SUM(AO7/19600) -> 0.73214286 | AO7: =SUM(AA7+AC7+AE7+AG7+AI7+AK7+AM7) -> 14350 | AQ7: =SUM(AR7/92970) -> 0.66095306 | AR7: =Y7+AO7 -> 61448.806 | AS7: =SUM(AR7-AR6-AT7) -> -2436.7742 | AV7: =IF(AT7>0,AU7,AV6) -> 0.74 | AW7: =-SUM('B5'!AI6) -> -351 | AX7: =-SUM(AW7-AS7) -> -2085.7742 | AY7: =SUM(AX7+AW7) -> -2436.7742 | AZ7: =ELEC!A4 -> 0 | BA7: ='General information '!D7 -> 15.5 | BB7: =SUM('General information '!E7) -> 0.64 | BC7: 0 | BD7: 19222 | BE7: =(305/1185)*ELEC!Q5 -> 1248.3122 | BG7: =#REF!-BE7 -> #REF! | BH7: 19
A8: =ELEC!C5 -> 44258 | B8: ='B5'!B7 -> 193 | C8: =B8*$B$4 -> 4152.6129 | D8: =SUM(B8) -> 193 | E8: =D8*$B$4 -> 4152.6129 | F8: =SUM(D8) -> 193 | G8: =F8*$B$4 -> 4152.6129 | H8: =SUM(F8) -> 193 | I8: =H8*$B$4 -> 4152.6129 | J8: =SUM(H8) -> 193 | K8: =J8*$B$4 -> 4152.6129 | L8: =SUM(J8) -> 193 | M8: =L8*$B$4 -> 4152.6129 | N8: =SUM(L8) -> 193 | O8: =N8*$B$4 -> 4152.6129 | P8: =SUM(N8) -> 193 | Q8: =P8*$B$4 -> 4152.6129 | R8: =SUM(P8) -> 193 | S8: =R8*$B$4 -> 4152.6129 | T8: =SUM(R8) -> 193 | U8: =T8*$B$4 -> 4152.6129 | V8: =SUM(T8) -> 193 | W8: =V8*$B$4 -> 4152.6129 | X8: =SUM(Y8/73370) -> 0.62258065 | Y8: =SUM(C8+E8+G8+I8+K8+M8+O8+Q8+S8+U8+W8) -> 45678.742 | Z8: ='B5'!C7 -> 199 | AA8: =SUM(Z8*$Z$4) -> 1990 | AB8: =SUM(Z8) -> 199 | AC8: =SUM(AB8*$Z$4) -> 1990 | AD8: =SUM(AB8) -> 199 | AE8: =SUM(AD8*$Z$4) -> 1990 | AF8: =SUM(AD8) -> 199 | AG8: =SUM(AF8*$Z$4) -> 1990 | AH8: =SUM(AF8) -> 199 | AI8: =SUM(AH8*$Z$4) -> 1990 | AJ8: =SUM(AH8) -> 199 | AK8: =SUM(AJ8*$Z$4) -> 1990 | AL8: =SUM(AJ8) -> 199 | AM8: =SUM(AL8*$Z$4) -> 1990 | AN8: =SUM(AO8/19600) -> 0.71071429 | AO8: =SUM(AA8+AC8+AE8+AG8+AI8+AK8+AM8) -> 13930 | AQ8: =SUM(AR8/92970) -> 0.64116104 | AR8: =Y8+AO8 -> 59608.742 | AS8: =SUM(AR8-AR7-AT8) -> -1840.0645 | AV8: =IF(AT8>0,AU8,AV7) -> 0.74 | AW8: =-SUM('B5'!AI7) -> -216 | AX8: =-SUM(AW8-AS8) -> -1624.0645 | AY8: =SUM(AX8+AW8) -> -1840.0645 | AZ8: =ELEC!A5 -> 0 | BA8: ='General information '!D8 -> 15.5 | BB8: =SUM('General information '!E8) -> 0.65 | BC8: =IF(AR7>=AR8,0,1) -> 0 | BD8: 19222 | BE8: =(305/1185)*ELEC!Q6 -> 899.55696 | BG8: =#REF!-BE8 -> #REF! | BH8: 16
A9: =ELEC!C6 -> 44259 | B9: ='B5'!B8 -> 187 | C9: =B9*$B$4 -> 4023.5161 | D9: =SUM(B9) -> 187 | E9: =D9*$B$4 -> 4023.5161 | F9: =SUM(D9) -> 187 | G9: =F9*$B$4 -> 4023.5161 | H9: =SUM(F9) -> 187 | I9: =H9*$B$4 -> 4023.5161 | J9: =SUM(H9) -> 187 | K9: =J9*$B$4 -> 4023.5161 | L9: =SUM(J9) -> 187 | M9: =L9*$B$4 -> 4023.5161 | N9: =SUM(L9) -> 187 | O9: =N9*$B$4 -> 4023.5161 | P9: =SUM(N9) -> 187 | Q9: =P9*$B$4 -> 4023.5161 | R9: =SUM(P9) -> 187 | S9: =R9*$B$4 -> 4023.5161 | T9: =SUM(R9) -> 187 | U9: =T9*$B$4 -> 4023.5161 | V9: =SUM(T9) -> 187 | W9: =V9*$B$4 -> 4023.5161 | X9: =SUM(Y9/73370) -> 0.60322581 | Y9: =SUM(C9+E9+G9+I9+K9+M9+O9+Q9+S9+U9+W9) -> 44258.677 | Z9: ='B5'!C8 -> 194 | AA9: =SUM(Z9*$Z$4) -> 1940 | AB9: =SUM(Z9) -> 194 | AC9: =SUM(AB9*$Z$4) -> 1940 | AD9: =SUM(AB9) -> 194 | AE9: =SUM(AD9*$Z$4) -> 1940 | AF9: =SUM(AD9) -> 194 | AG9: =SUM(AF9*$Z$4) -> 1940 | AH9: =SUM(AF9) -> 194 | AI9: =SUM(AH9*$Z$4) -> 1940 | AJ9: =SUM(AH9) -> 194 | AK9: =SUM(AJ9*$Z$4) -> 1940 | AL9: =SUM(AJ9) -> 194 | AM9: =SUM(AL9*$Z$4) -> 1940 | AN9: =SUM(AO9/19600) -> 0.69285714 | AO9: =SUM(AA9+AC9+AE9+AG9+AI9+AK9+AM9) -> 13580 | AQ9: =SUM(AR9/92970) -> 0.62212195 | AR9: =Y9+AO9 -> 57838.677 | AS9: =SUM(AR9-AR8-AT9) -> -1770.0645 | AV9: =IF(AT9>0,AU9,AV8) -> 0.74 | AW9: =-SUM('B5'!AI8) -> -312 | AX9: =-SUM(AW9-AS9) -> -1458.0645 | AY9: =SUM(AX9+AW9) -> -1770.0645 | AZ9: =ELEC!A6 -> 0 | BA9: ='General information '!D9 -> 15.5 | BB9: =SUM('General information '!E9) -> 0.59 | BC9: =IF(AR8>=AR9,0,1) -> 0 | BD9: 19222 | BE9: =(305/1185)*ELEC!Q7 -> 1180.8776 | BG9: =#REF!-BE9 -> #REF! | BH9: 18
A10: =ELEC!C7 -> 44260 | B10: ='B5'!B9 -> 208 | C10: =B10*$B$4 -> 4475.3548 | D10: =SUM(B10) -> 208 | E10: =D10*$B$4 -> 4475.3548 | F10: =SUM(D10) -> 208 | G10: =F10*$B$4 -> 4475.3548 | H10: =SUM(F10) -> 208 | I10: =H10*$B$4 -> 4475.3548 | J10: =SUM(H10) -> 208 | K10: =J10*$B$4 -> 4475.3548 | L10: =SUM(J10) -> 208 | M10: =L10*$B$4 -> 4475.3548 | N10: =SUM(L10) -> 208 | O10: =N10*$B$4 -> 4475.3548 | P10: =SUM(N10) -> 208 | Q10: =P10*$B$4 -> 4475.3548 | R10: =SUM(P10) -> 208 | S10: =R10*$B$4 -> 4475.3548 | T10: =SUM(R10) -> 208 | U10: =T10*$B$4 -> 4475.3548 | V10: =SUM(T10) -> 208 | W10: =V10*$B$4 -> 4475.3548 | X10: =SUM(Y10/73370) -> 0.67096774 | Y10: =SUM(C10+E10+G10+I10+K10+M10+O10+Q10+S10+U10+W10) -> 49228.903 | Z10: ='B5'!C9 -> 214 | AA10: =SUM(Z10*$Z$4) -> 2140 | AB10: =SUM(Z10) -> 214 | AC10: =SUM(AB10*$Z$4) -> 2140 | AD10: =SUM(AB10) -> 214 | AE10: =SUM(AD10*$Z$4) -> 2140 | AF10: =SUM(AD10) -> 214 | AG10: =SUM(AF10*$Z$4) -> 2140 | AH10: =SUM(AF10) -> 214 | AI10: =SUM(AH10*$Z$4) -> 2140 | AJ10: =SUM(AH10) -> 214 | AK10: =SUM(AJ10*$Z$4) -> 2140 | AL10: =SUM(AJ10) -> 214 | AM10: =SUM(AL10*$Z$4) -> 2140 | AN10: =SUM(AO10/19600) -> 0.76428571 | AO10: =SUM(AA10+AC10+AE10+AG10+AI10+AK10+AM10) -> 14980 | AQ10: =SUM(AR10/92970) -> 0.6906411 | AR10: =Y10+AO10 -> 64208.903 | AS10: =SUM(AR10-AR9-AT10) -> -580.77419 | AT10: 6951 | AU10: 0.78 | AV10: =IF(AT10>0,AU10,AV9) -> 0.78 | AW10: =-SUM('B5'!AI9) -> -238 | AX10: =-SUM(AW10-AS10) -> -342.77419 | AY10: =SUM(AX10+AW10) -> -580.77419 | AZ10: =ELEC!A7 -> 0 | BA10: ='General information '!D10 -> 15.5 | BB10: =SUM('General information '!E10) -> 0.64 | BC10: =IF(AR9>=AR10,0,1) -> 1 | BD10: 19222 | BE10: =(305/1185)*ELEC!Q8 -> 1256.0338 | BG10: =#REF!-BE10 -> #REF! | BH10: 16
A11: =ELEC!C8 -> 44261 | B11: ='B5'!B10 -> 202 | C11: =B11*$B$4 -> 4346.2581 | D11: =SUM(B11) -> 202 | E11: =D11*$B$4 -> 4346.2581 | F11: =SUM(D11) -> 202 | G11: =F11*$B$4 -> 4346.2581 | H11: =SUM(F11) -> 202 | I11: =H11*$B$4 -> 4346.2581 | J11: =SUM(H11) -> 202 | K11: =J11*$B$4 -> 4346.2581 | L11: =SUM(J11) -> 202 | M11: =L11*$B$4 -> 4346.2581 | N11: =SUM(L11) -> 202 | O11: =N11*$B$4 -> 4346.2581 | P11: =SUM(N11) -> 202 | Q11: =P11*$B$4 -> 4346.2581 | R11: =SUM(P11) -> 202 | S11: =R11*$B$4 -> 4346.2581 | T11: =SUM(R11) -> 202 | U11: =T11*$B$4 -> 4346.2581 | V11: =SUM(T11) -> 202 | W11: =V11*$B$4 -> 4346.2581 | X11: =SUM(Y11/73370) -> 0.6516129 | Y11: =SUM(C11+E11+G11+I11+K11+M11+O11+Q11+S11+U11+W11) -> 47808.839 | Z11: ='B5'!C10 -> 208 | AA11: =SUM(Z11*$Z$4) -> 2080 | AB11: =SUM(Z11) -> 208 | AC11: =SUM(AB11*$Z$4) -> 2080 | AD11: =SUM(AB11) -> 208 | AE11: =SUM(AD11*$Z$4) -> 2080 | AF11: =SUM(AD11) -> 208 | AG11: =SUM(AF11*$Z$4) -> 2080 | AH11: =SUM(AF11) -> 208 | AI11: =SUM(AH11*$Z$4) -> 2080 | AJ11: =SUM(AH11) -> 208 | AK11: =SUM(AJ11*$Z$4) -> 2080 | AL11: =SUM(AJ11) -> 208 | AM11: =SUM(AL11*$Z$4) -> 2080 | AN11: =SUM(AO11/19600) -> 0.74285714 | AO11: =SUM(AA11+AC11+AE11+AG11+AI11+AK11+AM11) -> 14560 | AQ11: =SUM(AR11/92970) -> 0.67084908 | AR11: =Y11+AO11 -> 62368.839 | AS11: =SUM(AR11-AR10-AT11) -> -1840.0645 | AV11: =IF(AT11>0,AU11,AV10) -> 0.78 | AW11: =-SUM('B5'!AI10) -> -228 | AX11: =-SUM(AW11-AS11) -> -1612.0645 | AY11: =SUM(AX11+AW11) -> -1840.0645 | AZ11: =ELEC!A8 -> 0 | BA11: ='General information '!D11 -> 16 | BB11: =SUM('General information '!E11) -> 0.67 | BC11: =IF(AR10>=AR11,0,1) -> 0 | BD11: 19222 | BE11: =(305/1185)*ELEC!Q9 -> 529.95359 | BG11: =#REF!-BE11 -> #REF! | BH11: 16.5
A12: =ELEC!C9 -> 44262 | B12: ='B5'!B11 -> 199 | C12: =B12*$B$4 -> 4281.7097 | D12: =SUM(B12) -> 199 | E12: =D12*$B$4 -> 4281.7097 | F12: =SUM(D12) -> 199 | G12: =F12*$B$4 -> 4281.7097 | H12: =SUM(F12) -> 199 | I12: =H12*$B$4 -> 4281.7097 | J12: =SUM(H12) -> 199 | K12: =J12*$B$4 -> 4281.7097 | L12: =SUM(J12) -> 199 | M12: =L12*$B$4 -> 4281.7097 | N12: =SUM(L12) -> 199 | O12: =N12*$B$4 -> 4281.7097 | P12: =SUM(N12) -> 199 | Q12: =P12*$B$4 -> 4281.7097 | R12: =SUM(P12) -> 199 | S12: =R12*$B$4 -> 4281.7097 | T12: =SUM(R12) -> 199 | U12: =T12*$B$4 -> 4281.7097 | V12: =SUM(T12) -> 199 | W12: =V12*$B$4 -> 4281.7097 | X12: =SUM(Y12/73370) -> 0.64193548 | Y12: =SUM(C12+E12+G12+I12+K12+M12+O12+Q12+S12+U12+W12) -> 47098.806 | Z12: ='B5'!C11 -> 205 | AA12: =SUM(Z12*$Z$4) -> 2050 | AB12: =SUM(Z12) -> 205 | AC12: =SUM(AB12*$Z$4) -> 2050 | AD12: =SUM(AB12) -> 205 | AE12: =SUM(AD12*$Z$4) -> 2050 | AF12: =SUM(AD12) -> 205 | AG12: =SUM(AF12*$Z$4) -> 2050 | AH12: =SUM(AF12) -> 205 | AI12: =SUM(AH12*$Z$4) -> 2050 | AJ12: =SUM(AH12) -> 205 | AK12: =SUM(AJ12*$Z$4) -> 2050 | AL12: =SUM(AJ12) -> 205 | AM12: =SUM(AL12*$Z$4) -> 2050 | AN12: =SUM(AO12/19600) -> 0.73214286 | AO12: =SUM(AA12+AC12+AE12+AG12+AI12+AK12+AM12) -> 14350 | AQ12: =SUM(AR12/92970) -> 0.66095306 | AR12: =Y12+AO12 -> 61448.806 | AS12: =SUM(AR12-AR11-AT12) -> -920.03226 | AV12: =IF(AT12>0,AU12,AV11) -> 0.78 | AW12: =-SUM('B5'!AI11) -> -230 | AX12: =-SUM(AW12-AS12) -> -690.03226 | AY12: =SUM(AX12+AW12) -> -920.03226 | AZ12: =ELEC!A9 -> 0 | BA12: ='General information '!D12 -> 16.5 | BB12: =SUM('General information '!E12) -> 0.65 | BC12: =IF(AR11>=AR12,0,1) -> 0 | BD12: 19222 | BE12: =(305/1185)*ELEC!Q10 -> 723.24895 | BG12: =#REF!-BE12 -> #REF! | BH12: 15.5
A13: =ELEC!C10 -> 44263 | B13: ='B5'!B12 -> 194.5 | C13: =B13*$B$4 -> 4184.8871 | D13: =SUM(B13) -> 194.5 | E13: =D13*$B$4 -> 4184.8871 | F13: =SUM(D13) -> 194.5 | G13: =F13*$B$4 -> 4184.8871 | H13: =SUM(F13) -> 194.5 | I13: =H13*$B$4 -> 4184.8871 | J13: =SUM(H13) -> 194.5 | K13: =J13*$B$4 -> 4184.8871 | L13: =SUM(J13) -> 194.5 | M13: =L13*$B$4 -> 4184.8871 | N13: =SUM(L13) -> 194.5 | O13: =N13*$B$4 -> 4184.8871 | P13: =SUM(N13) -> 194.5 | Q13: =P13*$B$4 -> 4184.8871 | R13: =SUM(P13) -> 194.5 | S13: =R13*$B$4 -> 4184.8871 | T13: =SUM(R13) -> 194.5 | U13: =T13*$B$4 -> 4184.8871 | V13: =SUM(T13) -> 194.5 | W13: =V13*$B$4 -> 4184.8871 | X13: =SUM(Y13/73370) -> 0.62741935 | Y13: =SUM(C13+E13+G13+I13+K13+M13+O13+Q13+S13+U13+W13) -> 46033.758 | Z13: ='B5'!C12 -> 201 | AA13: =SUM(Z13*$Z$4) -> 2010 | AB13: =SUM(Z13) -> 201 | AC13: =SUM(AB13*$Z$4) -> 2010 | AD13: =SUM(AB13) -> 201 | AE13: =SUM(AD13*$Z$4) -> 2010 | AF13: =SUM(AD13) -> 201 | AG13: =SUM(AF13*$Z$4) -> 2010 | AH13: =SUM(AF13) -> 201 | AI13: =SUM(AH13*$Z$4) -> 2010 | AJ13: =SUM(AH13) -> 201 | AK13: =SUM(AJ13*$Z$4) -> 2010 | AL13: =SUM(AJ13) -> 201 | AM13: =SUM(AL13*$Z$4) -> 2010 | AN13: =SUM(AO13/19600) -> 0.71785714 | AO13: =SUM(AA13+AC13+AE13+AG13+AI13+AK13+AM13) -> 14070 | AQ13: =SUM(AR13/92970) -> 0.64648551 | AR13: =Y13+AO13 -> 60103.758 | AS13: =SUM(AR13-AR12-AT13) -> -1345.0484 | AV13: =IF(AT13>0,AU13,AV12) -> 0.78 | AW13: =-SUM('B5'!AI12) -> -290 | AX13: =-SUM(AW13-AS13) -> -1055.0484 | AY13: =SUM(AX13+AW13) -> -1345.0484 | AZ13: =ELEC!A10 -> 0 | BA13: ='General information '!D13 -> 18 | BB13: =SUM('General information '!E13) -> 0.76 | BC13: =IF(AR12>=AR13,0,1) -> 0 | BD13: 19222 | BE13: =(305/1185)*ELEC!Q11 -> 0 | BG13: =#REF!-BE13 -> #REF!
A14: =ELEC!C11 -> 44264 | B14: ='B5'!B13 -> 194.5 | C14: =B14*$B$4 -> 4184.8871 | D14: =SUM(B14) -> 194.5 | E14: =D14*$B$4 -> 4184.8871 | F14: =SUM(D14) -> 194.5 | G14: =F14*$B$4 -> 4184.8871 | H14: =SUM(F14) -> 194.5 | I14: =H14*$B$4 -> 4184.8871 | J14: =SUM(H14) -> 194.5 | K14: =J14*$B$4 -> 4184.8871 | L14: =SUM(J14) -> 194.5 | M14: =L14*$B$4 -> 4184.8871 | N14: =SUM(L14) -> 194.5 | O14: =N14*$B$4 -> 4184.8871 | P14: =SUM(N14) -> 194.5 | Q14: =P14*$B$4 -> 4184.8871 | R14: =SUM(P14) -> 194.5 | S14: =R14*$B$4 -> 4184.8871 | T14: =SUM(R14) -> 194.5 | U14: =T14*$B$4 -> 4184.8871 | V14: =SUM(T14) -> 194.5 | W14: =V14*$B$4 -> 4184.8871 | X14: =SUM(Y14/73370) -> 0.62741935 | Y14: =SUM(C14+E14+G14+I14+K14+M14+O14+Q14+S14+U14+W14) -> 46033.758 | Z14: ='B5'!C13 -> 201 | AA14: =SUM(Z14*$Z$4) -> 2010 | AB14: =SUM(Z14) -> 201 | AC14: =SUM(AB14*$Z$4) -> 2010 | AD14: =SUM(AB14) -> 201 | AE14: =SUM(AD14*$Z$4) -> 2010 | AF14: =SUM(AD14) -> 201 | AG14: =SUM(AF14*$Z$4) -> 2010 | AH14: =SUM(AF14) -> 201 | AI14: =SUM(AH14*$Z$4) -> 2010 | AJ14: =SUM(AH14) -> 201 | AK14: =SUM(AJ14*$Z$4) -> 2010 | AL14: =SUM(AJ14) -> 201 | AM14: =SUM(AL14*$Z$4) -> 2010 | AN14: =SUM(AO14/19600) -> 0.71785714 | AO14: =SUM(AA14+AC14+AE14+AG14+AI14+AK14+AM14) -> 14070 | AQ14: =SUM(AR14/92970) -> 0.64648551 | AR14: =Y14+AO14 -> 60103.758 | AS14: =SUM(AR14-AR13-AT14) -> 0 | AV14: =IF(AT14>0,AU14,AV13) -> 0.78 | AW14: =-SUM('B5'!AI13) -> 0 | AX14: =-SUM(AW14-AS14) -> 0 | AY14: =SUM(AX14+AW14) -> 0 | AZ14: =ELEC!A11 -> 0 | BA14: ='General information '!D14 -> 0 | BB14: =SUM('General information '!E14) -> 0 | BC14: =IF(AR13>=AR14,0,1) -> 0 | BD14: 19222 | BE14: =(305/1185)*ELEC!Q12 -> 0 | BG14: =#REF!-BE14 -> #REF!
A15: =ELEC!C12 -> 44265 | B15: ='B5'!B14 -> 194.5 | C15: =B15*$B$4 -> 4184.8871 | D15: =SUM(B15) -> 194.5 | E15: =D15*$B$4 -> 4184.8871 | F15: =SUM(D15) -> 194.5 | G15: =F15*$B$4 -> 4184.8871 | H15: =SUM(F15) -> 194.5 | I15: =H15*$B$4 -> 4184.8871 | J15: =SUM(H15) -> 194.5 | K15: =J15*$B$4 -> 4184.8871 | L15: =SUM(J15) -> 194.5 | M15: =L15*$B$4 -> 4184.8871 | N15: =SUM(L15) -> 194.5 | O15: =N15*$B$4 -> 4184.8871 | P15: =SUM(N15) -> 194.5 | Q15: =P15*$B$4 -> 4184.8871 | R15: =SUM(P15) -> 194.5 | S15: =R15*$B$4 -> 4184.8871 | T15: =SUM(R15) -> 194.5 | U15: =T15*$B$4 -> 4184.8871 | V15: =SUM(T15) -> 194.5 | W15: =V15*$B$4 -> 4184.8871 | X15: =SUM(Y15/73370) -> 0.62741935 | Y15: =SUM(C15+E15+G15+I15+K15+M15+O15+Q15+S15+U15+W15) -> 46033.758 | Z15: ='B5'!C14 -> 201 | AA15: =SUM(Z15*$Z$4) -> 2010 | AB15: =SUM(Z15) -> 201 | AC15: =SUM(AB15*$Z$4) -> 2010 | AD15: =SUM(AB15) -> 201 | AE15: =SUM(AD15*$Z$4) -> 2010 | AF15: =SUM(AD15) -> 201 | AG15: =SUM(AF15*$Z$4) -> 2010 | AH15: =SUM(AF15) -> 201 | AI15: =SUM(AH15*$Z$4) -> 2010 | AJ15: =SUM(AH15) -> 201 | AK15: =SUM(AJ15*$Z$4) -> 2010 | AL15: =SUM(AJ15) -> 201 | AM15: =SUM(AL15*$Z$4) -> 2010 | AN15: =SUM(AO15/19600) -> 0.71785714 | AO15: =SUM(AA15+AC15+AE15+AG15+AI15+AK15+AM15) -> 14070 | AQ15: =SUM(AR15/92970) -> 0.64648551 | AR15: =Y15+AO15 -> 60103.758 | AS15: =SUM(AR15-AR14-AT15) -> 0 | AV15: =IF(AT15>0,AU15,AV14) -> 0.78 | AW15: =-SUM('B5'!AI14) -> 0 | AX15: =-SUM(AW15-AS15) -> 0 | AY15: =SUM(AX15+AW15) -> 0 | AZ15: =ELEC!A12 -> 0 | BA15: ='General information '!D15 -> 0 | BB15: =SUM('General information '!E15) -> 0 | BC15: =IF(AR14>=AR15,0,1) -> 0 | BD15: 19222 | BE15: =(305/1185)*ELEC!Q13 -> 0 | BG15: =#REF!-BE15 -> #REF!
A16: =ELEC!C13 -> 44266 | B16: ='B5'!B15 -> 194.5 | C16: =B16*$B$4 -> 4184.8871 | D16: =SUM(B16) -> 194.5 | E16: =D16*$B$4 -> 4184.8871 | F16: =SUM(D16) -> 194.5 | G16: =F16*$B$4 -> 4184.8871 | H16: =SUM(F16) -> 194.5 | I16: =H16*$B$4 -> 4184.8871 | J16: =SUM(H16) -> 194.5 | K16: =J16*$B$4 -> 4184.8871 | L16: =SUM(J16) -> 194.5 | M16: =L16*$B$4 -> 4184.8871 | N16: =SUM(L16) -> 194.5 | O16: =N16*$B$4 -> 4184.8871 | P16: =SUM(N16) -> 194.5 | Q16: =P16*$B$4 -> 4184.8871 | R16: =SUM(P16) -> 194.5 | S16: =R16*$B$4 -> 4184.8871 | T16: =SUM(R16) -> 194.5 | U16: =T16*$B$4 -> 4184.8871 | V16: =SUM(T16) -> 194.5 | W16: =V16*$B$4 -> 4184.8871 | X16: =SUM(Y16/73370) -> 0.62741935 | Y16: =SUM(C16+E16+G16+I16+K16+M16+O16+Q16+S16+U16+W16) -> 46033.758 | Z16: ='B5'!C15 -> 201 | AA16: =SUM(Z16*$Z$4) -> 2010 | AB16: =SUM(Z16) -> 201 | AC16: =SUM(AB16*$Z$4) -> 2010 | AD16: =SUM(AB16) -> 201 | AE16: =SUM(AD16*$Z$4) -> 2010 | AF16: =SUM(AD16) -> 201 | AG16: =SUM(AF16*$Z$4) -> 2010 | AH16: =SUM(AF16) -> 201 | AI16: =SUM(AH16*$Z$4) -> 2010 | AJ16: =SUM(AH16) -> 201 | AK16: =SUM(AJ16*$Z$4) -> 2010 | AL16: =SUM(AJ16) -> 201 | AM16: =SUM(AL16*$Z$4) -> 2010 | AN16: =SUM(AO16/19600) -> 0.71785714 | AO16: =SUM(AA16+AC16+AE16+AG16+AI16+AK16+AM16) -> 14070 | AQ16: =SUM(AR16/92970) -> 0.64648551 | AR16: =Y16+AO16 -> 60103.758 | AS16: =SUM(AR16-AR15-AT16) -> 0 | AV16: =IF(AT16>0,AU16,AV15) -> 0.78 | AW16: =-SUM('B5'!AI15) -> 0 | AX16: =-SUM(AW16-AS16) -> 0 | AY16: =SUM(AX16+AW16) -> 0 | AZ16: =ELEC!A13 -> 0 | BA16: ='General information '!D16 -> 0 | BB16: =SUM('General information '!E16) -> 0 | BC16: =IF(AR15>=AR16,0,1) -> 0 | BD16: 19222 | BE16: =(305/1185)*ELEC!Q14 -> 0 | BG16: =#REF!-BE16 -> #REF!
A17: =ELEC!C14 -> 44267 | B17: ='B5'!B16 -> 194.5 | C17: =B17*$B$4 -> 4184.8871 | D17: =SUM(B17) -> 194.5 | E17: =D17*$B$4 -> 4184.8871 | F17: =SUM(D17) -> 194.5 | G17: =F17*$B$4 -> 4184.8871 | H17: =SUM(F17) -> 194.5 | I17: =H17*$B$4 -> 4184.8871 | J17: =SUM(H17) -> 194.5 | K17: =J17*$B$4 -> 4184.8871 | L17: =SUM(J17) -> 194.5 | M17: =L17*$B$4 -> 4184.8871 | N17: =SUM(L17) -> 194.5 | O17: =N17*$B$4 -> 4184.8871 | P17: =SUM(N17) -> 194.5 | Q17: =P17*$B$4 -> 4184.8871 | R17: =SUM(P17) -> 194.5 | S17: =R17*$B$4 -> 4184.8871 | T17: =SUM(R17) -> 194.5 | U17: =T17*$B$4 -> 4184.8871 | V17: =SUM(T17) -> 194.5 | W17: =V17*$B$4 -> 4184.8871 | X17: =SUM(Y17/73370) -> 0.62741935 | Y17: =SUM(C17+E17+G17+I17+K17+M17+O17+Q17+S17+U17+W17) -> 46033.758 | Z17: ='B5'!C16 -> 201 | AA17: =SUM(Z17*$Z$4) -> 2010 | AB17: =SUM(Z17) -> 201 | AC17: =SUM(AB17*$Z$4) -> 2010 | AD17: =SUM(AB17) -> 201 | AE17: =SUM(AD17*$Z$4) -> 2010 | AF17: =SUM(AD17) -> 201 | AG17: =SUM(AF17*$Z$4) -> 2010 | AH17: =SUM(AF17) -> 201 | AI17: =SUM(AH17*$Z$4) -> 2010 | AJ17: =SUM(AH17) -> 201 | AK17: =SUM(AJ17*$Z$4) -> 2010 | AL17: =SUM(AJ17) -> 201 | AM17: =SUM(AL17*$Z$4) -> 2010 | AN17: =SUM(AO17/19600) -> 0.71785714 | AO17: =SUM(AA17+AC17+AE17+AG17+AI17+AK17+AM17) -> 14070 | AQ17: =SUM(AR17/92970) -> 0.64648551 | AR17: =Y17+AO17 -> 60103.758 | AS17: =SUM(AR17-AR16-AT17) -> 0 | AV17: =IF(AT17>0,AU17,AV16) -> 0.78 | AW17: =-SUM('B5'!AI16) -> 0 | AX17: =-SUM(AW17-AS17) -> 0 | AY17: =SUM(AX17+AW17) -> 0 | AZ17: =ELEC!A14 -> 0 | BA17: ='General information '!D17 -> 0 | BB17: =SUM('General information '!E17) -> 0 | BC17: =IF(AR16>=AR17,0,1) -> 0 | BD17: 19222 | BE17: =(305/1185)*ELEC!Q15 -> 0 | BG17: =#REF!-BE17 -> #REF!
A18: =ELEC!C15 -> 44268 | B18: ='B5'!B17 -> 194.5 | C18: =B18*$B$4 -> 4184.8871 | D18: =SUM(B18) -> 194.5 | E18: =D18*$B$4 -> 4184.8871 | F18: =SUM(D18) -> 194.5 | G18: =F18*$B$4 -> 4184.8871 | H18: =SUM(F18) -> 194.5 | I18: =H18*$B$4 -> 4184.8871 | J18: =SUM(H18) -> 194.5 | K18: =J18*$B$4 -> 4184.8871 | L18: =SUM(J18) -> 194.5 | M18: =L18*$B$4 -> 4184.8871 | N18: =SUM(L18) -> 194.5 | O18: =N18*$B$4 -> 4184.8871 | P18: =SUM(N18) -> 194.5 | Q18: =P18*$B$4 -> 4184.8871 | R18: =SUM(P18) -> 194.5 | S18: =R18*$B$4 -> 4184.8871 | T18: =SUM(R18) -> 194.5 | U18: =T18*$B$4 -> 4184.8871 | V18: =SUM(T18) -> 194.5 | W18: =V18*$B$4 -> 4184.8871 | X18: =SUM(Y18/73370) -> 0.62741935 | Y18: =SUM(C18+E18+G18+I18+K18+M18+O18+Q18+S18+U18+W18) -> 46033.758 | Z18: ='B5'!C17 -> 201 | AA18: =SUM(Z18*$Z$4) -> 2010 | AB18: =SUM(Z18) -> 201 | AC18: =SUM(AB18*$Z$4) -> 2010 | AD18: =SUM(AB18) -> 201 | AE18: =SUM(AD18*$Z$4) -> 2010 | AF18: =SUM(AD18) -> 201 | AG18: =SUM(AF18*$Z$4) -> 2010 | AH18: =SUM(AF18) -> 201 | AI18: =SUM(AH18*$Z$4) -> 2010 | AJ18: =SUM(AH18) -> 201 | AK18: =SUM(AJ18*$Z$4) -> 2010 | AL18: =SUM(AJ18) -> 201 | AM18: =SUM(AL18*$Z$4) -> 2010 | AN18: =SUM(AO18/19600) -> 0.71785714 | AO18: =SUM(AA18+AC18+AE18+AG18+AI18+AK18+AM18) -> 14070 | AQ18: =SUM(AR18/92970) -> 0.64648551 | AR18: =Y18+AO18 -> 60103.758 | AS18: =SUM(AR18-AR17-AT18) -> 0 | AV18: =IF(AT18>0,AU18,AV17) -> 0.78 | AW18: =-SUM('B5'!AI17) -> 0 | AX18: =-SUM(AW18-AS18) -> 0 | AY18: =SUM(AX18+AW18) -> 0 | AZ18: =ELEC!A15 -> 0 | BA18: ='General information '!D18 -> 0 | BB18: =SUM('General information '!E18) -> 0 | BC18: =IF(AR17>=AR18,0,1) -> 0 | BD18: 19222 | BE18: =(305/1185)*ELEC!Q16 -> 0 | BG18: =#REF!-BE18 -> #REF!
A19: =ELEC!C16 -> 44269 | B19: ='B5'!B18 -> 194.5 | C19: =B19*$B$4 -> 4184.8871 | D19: =SUM(B19) -> 194.5 | E19: =D19*$B$4 -> 4184.8871 | F19: =SUM(D19) -> 194.5 | G19: =F19*$B$4 -> 4184.8871 | H19: =SUM(F19) -> 194.5 | I19: =H19*$B$4 -> 4184.8871 | J19: =SUM(H19) -> 194.5 | K19: =J19*$B$4 -> 4184.8871 | L19: =SUM(J19) -> 194.5 | M19: =L19*$B$4 -> 4184.8871 | N19: =SUM(L19) -> 194.5 | O19: =N19*$B$4 -> 4184.8871 | P19: =SUM(N19) -> 194.5 | Q19: =P19*$B$4 -> 4184.8871 | R19: =SUM(P19) -> 194.5 | S19: =R19*$B$4 -> 4184.8871 | T19: =SUM(R19) -> 194.5 | U19: =T19*$B$4 -> 4184.8871 | V19: =SUM(T19) -> 194.5 | W19: =V19*$B$4 -> 4184.8871 | X19: =SUM(Y19/73370) -> 0.62741935 | Y19: =SUM(C19+E19+G19+I19+K19+M19+O19+Q19+S19+U19+W19) -> 46033.758 | Z19: ='B5'!C18 -> 201 | AA19: =SUM(Z19*$Z$4) -> 2010 | AB19: =SUM(Z19) -> 201 | AC19: =SUM(AB19*$Z$4) -> 2010 | AD19: =SUM(AB19) -> 201 | AE19: =SUM(AD19*$Z$4) -> 2010 | AF19: =SUM(AD19) -> 201 | AG19: =SUM(AF19*$Z$4) -> 2010 | AH19: =SUM(AF19) -> 201 | AI19: =SUM(AH19*$Z$4) -> 2010 | AJ19: =SUM(AH19) -> 201 | AK19: =SUM(AJ19*$Z$4) -> 2010 | AL19: =SUM(AJ19) -> 201 | AM19: =SUM(AL19*$Z$4) -> 2010 | AN19: =SUM(AO19/19600) -> 0.71785714 | AO19: =SUM(AA19+AC19+AE19+AG19+AI19+AK19+AM19) -> 14070 | AQ19: =SUM(AR19/92970) -> 0.64648551 | AR19: =Y19+AO19 -> 60103.758 | AS19: =SUM(AR19-AR18-AT19) -> 0 | AV19: =IF(AT19>0,AU19,AV18) -> 0.78 | AW19: =-SUM('B5'!AI18) -> 0 | AX19: =-SUM(AW19-AS19) -> 0 | AY19: =SUM(AX19+AW19) -> 0 | AZ19: =ELEC!A16 -> 0 | BA19: ='General information '!D19 -> 0 | BB19: =SUM('General information '!E19) -> 0 | BC19: =IF(AR18>=AR19,0,1) -> 0 | BD19: 19222 | BE19: =(305/1185)*ELEC!Q17 -> 0 | BG19: =#REF!-BE19 -> #REF!
A20: =ELEC!C17 -> 44270 | B20: ='B5'!B19 -> 194.5 | C20: =B20*$B$4 -> 4184.8871 | D20: =SUM(B20) -> 194.5 | E20: =D20*$B$4 -> 4184.8871 | F20: =SUM(D20) -> 194.5 | G20: =F20*$B$4 -> 4184.8871 | H20: =SUM(F20) -> 194.5 | I20: =H20*$B$4 -> 4184.8871 | J20: =SUM(H20) -> 194.5 | K20: =J20*$B$4 -> 4184.8871 | L20: =SUM(J20) -> 194.5 | M20: =L20*$B$4 -> 4184.8871 | N20: =SUM(L20) -> 194.5 | O20: =N20*$B$4 -> 4184.8871 | P20: =SUM(N20) -> 194.5 | Q20: =P20*$B$4 -> 4184.8871 | R20: =SUM(P20) -> 194.5 | S20: =R20*$B$4 -> 4184.8871 | T20: =SUM(R20) -> 194.5 | U20: =T20*$B$4 -> 4184.8871 | V20: =SUM(T20) -> 194.5 | W20: =V20*$B$4 -> 4184.8871 | X20: =SUM(Y20/73370) -> 0.62741935 | Y20: =SUM(C20+E20+G20+I20+K20+M20+O20+Q20+S20+U20+W20) -> 46033.758 | Z20: ='B5'!C19 -> 201 | AA20: =SUM(Z20*$Z$4) -> 2010 | AB20: =SUM(Z20) -> 201 | AC20: =SUM(AB20*$Z$4) -> 2010 | AD20: =SUM(AB20) -> 201 | AE20: =SUM(AD20*$Z$4) -> 2010 | AF20: =SUM(AD20) -> 201 | AG20: =SUM(AF20*$Z$4) -> 2010 | AH20: =SUM(AF20) -> 201 | AI20: =SUM(AH20*$Z$4) -> 2010 | AJ20: =SUM(AH20) -> 201 | AK20: =SUM(AJ20*$Z$4) -> 2010 | AL20: =SUM(AJ20) -> 201 | AM20: =SUM(AL20*$Z$4) -> 2010 | AN20: =SUM(AO20/19600) -> 0.71785714 | AO20: =SUM(AA20+AC20+AE20+AG20+AI20+AK20+AM20) -> 14070 | AQ20: =SUM(AR20/92970) -> 0.64648551 | AR20: =Y20+AO20 -> 60103.758 | AS20: =SUM(AR20-AR19-AT20) -> 0 | AV20: =IF(AT20>0,AU20,AV19) -> 0.78 | AW20: =-SUM('B5'!AI19) -> 0 | AX20: =-SUM(AW20-AS20) -> 0 | AY20: =SUM(AX20+AW20) -> 0 | AZ20: =ELEC!A17 -> 0 | BA20: ='General information '!D20 -> 0 | BB20: =SUM('General information '!E20) -> 0 | BC20: =IF(AR19>=AR20,0,1) -> 0 | BD20: 19222 | BE20: =(305/1185)*ELEC!Q18 -> 0 | BG20: =#REF!-BE20 -> #REF!
A21: =ELEC!C18 -> 44271 | B21: ='B5'!B20 -> 194.5 | C21: =B21*$B$4 -> 4184.8871 | D21: =SUM(B21) -> 194.5 | E21: =D21*$B$4 -> 4184.8871 | F21: =SUM(D21) -> 194.5 | G21: =F21*$B$4 -> 4184.8871 | H21: =SUM(F21) -> 194.5 | I21: =H21*$B$4 -> 4184.8871 | J21: =SUM(H21) -> 194.5 | K21: =J21*$B$4 -> 4184.8871 | L21: =SUM(J21) -> 194.5 | M21: =L21*$B$4 -> 4184.8871 | N21: =SUM(L21) -> 194.5 | O21: =N21*$B$4 -> 4184.8871 | P21: =SUM(N21) -> 194.5 | Q21: =P21*$B$4 -> 4184.8871 | R21: =SUM(P21) -> 194.5 | S21: =R21*$B$4 -> 4184.8871 | T21: =SUM(R21) -> 194.5 | U21: =T21*$B$4 -> 4184.8871 | V21: =SUM(T21) -> 194.5 | W21: =V21*$B$4 -> 4184.8871 | X21: =SUM(Y21/73370) -> 0.62741935 | Y21: =SUM(C21+E21+G21+I21+K21+M21+O21+Q21+S21+U21+W21) -> 46033.758 | Z21: ='B5'!C20 -> 201 | AA21: =SUM(Z21*$Z$4) -> 2010 | AB21: =SUM(Z21) -> 201 | AC21: =SUM(AB21*$Z$4) -> 2010 | AD21: =SUM(AB21) -> 201 | AE21: =SUM(AD21*$Z$4) -> 2010 | AF21: =SUM(AD21) -> 201 | AG21: =SUM(AF21*$Z$4) -> 2010 | AH21: =SUM(AF21) -> 201 | AI21: =SUM(AH21*$Z$4) -> 2010 | AJ21: =SUM(AH21) -> 201 | AK21: =SUM(AJ21*$Z$4) -> 2010 | AL21: =SUM(AJ21) -> 201 | AM21: =SUM(AL21*$Z$4) -> 2010 | AN21: =SUM(AO21/19600) -> 0.71785714 | AO21: =SUM(AA21+AC21+AE21+AG21+AI21+AK21+AM21) -> 14070 | AQ21: =SUM(AR21/92970) -> 0.64648551 | AR21: =Y21+AO21 -> 60103.758 | AS21: =SUM(AR21-AR20-AT21) -> 0 | AV21: =IF(AT21>0,AU21,AV20) -> 0.78 | AW21: =-SUM('B5'!AI20) -> 0 | AX21: =-SUM(AW21-AS21) -> 0 | AY21: =SUM(AX21+AW21) -> 0 | AZ21: =ELEC!A18 -> 0 | BA21: ='General information '!D21 -> 0 | BB21: =SUM('General information '!E21) -> 0 | BC21: =IF(AR20>=AR21,0,1) -> 0 | BD21: 19222 | BE21: =(305/1185)*ELEC!Q19 -> 0 | BG21: =#REF!-BE21 -> #REF!
A22: =ELEC!C19 -> 44272 | B22: ='B5'!B21 -> 194.5 | C22: =B22*$B$4 -> 4184.8871 | D22: =SUM(B22) -> 194.5 | E22: =D22*$B$4 -> 4184.8871 | F22: =SUM(D22) -> 194.5 | G22: =F22*$B$4 -> 4184.8871 | H22: =SUM(F22) -> 194.5 | I22: =H22*$B$4 -> 4184.8871 | J22: =SUM(H22) -> 194.5 | K22: =J22*$B$4 -> 4184.8871 | L22: =SUM(J22) -> 194.5 | M22: =L22*$B$4 -> 4184.8871 | N22: =SUM(L22) -> 194.5 | O22: =N22*$B$4 -> 4184.8871 | P22: =SUM(N22) -> 194.5 | Q22: =P22*$B$4 -> 4184.8871 | R22: =SUM(P22) -> 194.5 | S22: =R22*$B$4 -> 4184.8871 | T22: =SUM(R22) -> 194.5 | U22: =T22*$B$4 -> 4184.8871 | V22: =SUM(T22) -> 194.5 | W22: =V22*$B$4 -> 4184.8871 | X22: =SUM(Y22/73370) -> 0.62741935 | Y22: =SUM(C22+E22+G22+I22+K22+M22+O22+Q22+S22+U22+W22) -> 46033.758 | Z22: ='B5'!C21 -> 201 | AA22: =SUM(Z22*$Z$4) -> 2010 | AB22: =SUM(Z22) -> 201 | AC22: =SUM(AB22*$Z$4) -> 2010 | AD22: =SUM(AB22) -> 201 | AE22: =SUM(AD22*$Z$4) -> 2010 | AF22: =SUM(AD22) -> 201 | AG22: =SUM(AF22*$Z$4) -> 2010 | AH22: =SUM(AF22) -> 201 | AI22: =SUM(AH22*$Z$4) -> 2010 | AJ22: =SUM(AH22) -> 201 | AK22: =SUM(AJ22*$Z$4) -> 2010 | AL22: =SUM(AJ22) -> 201 | AM22: =SUM(AL22*$Z$4) -> 2010 | AN22: =SUM(AO22/19600) -> 0.71785714 | AO22: =SUM(AA22+AC22+AE22+AG22+AI22+AK22+AM22) -> 14070 | AQ22: =SUM(AR22/92970) -> 0.64648551 | AR22: =Y22+AO22 -> 60103.758 | AS22: =SUM(AR22-AR21-AT22) -> 0 | AV22: =IF(AT22>0,AU22,AV21) -> 0.78 | AW22: =-SUM('B5'!AI21) -> 0 | AX22: =-SUM(AW22-AS22) -> 0 | AY22: =SUM(AX22+AW22) -> 0 | AZ22: =ELEC!A19 -> 0 | BA22: ='General information '!D22 -> 0 | BB22: =SUM('General information '!E22) -> 0 | BC22: =IF(AR21>=AR22,0,1) -> 0 | BD22: 19222 | BE22: =(305/1185)*ELEC!Q20 -> 0 | BG22: =#REF!-BE22 -> #REF!
A23: =ELEC!C20 -> 44273 | B23: ='B5'!B22 -> 194.5 | C23: =B23*$B$4 -> 4184.8871 | D23: =SUM(B23) -> 194.5 | E23: =D23*$B$4 -> 4184.8871 | F23: =SUM(D23) -> 194.5 | G23: =F23*$B$4 -> 4184.8871 | H23: =SUM(F23) -> 194.5 | I23: =H23*$B$4 -> 4184.8871 | J23: =SUM(H23) -> 194.5 | K23: =J23*$B$4 -> 4184.8871 | L23: =SUM(J23) -> 194.5 | M23: =L23*$B$4 -> 4184.8871 | N23: =SUM(L23) -> 194.5 | O23: =N23*$B$4 -> 4184.8871 | P23: =SUM(N23) -> 194.5 | Q23: =P23*$B$4 -> 4184.8871 | R23: =SUM(P23) -> 194.5 | S23: =R23*$B$4 -> 4184.8871 | T23: =SUM(R23) -> 194.5 | U23: =T23*$B$4 -> 4184.8871 | V23: =SUM(T23) -> 194.5 | W23: =V23*$B$4 -> 4184.8871 | X23: =SUM(Y23/73370) -> 0.62741935 | Y23: =SUM(C23+E23+G23+I23+K23+M23+O23+Q23+S23+U23+W23) -> 46033.758 | Z23: ='B5'!C22 -> 201 | AA23: =SUM(Z23*$Z$4) -> 2010 | AB23: =SUM(Z23) -> 201 | AC23: =SUM(AB23*$Z$4) -> 2010 | AD23: =SUM(AB23) -> 201 | AE23: =SUM(AD23*$Z$4) -> 2010 | AF23: =SUM(AD23) -> 201 | AG23: =SUM(AF23*$Z$4) -> 2010 | AH23: =SUM(AF23) -> 201 | AI23: =SUM(AH23*$Z$4) -> 2010 | AJ23: =SUM(AH23) -> 201 | AK23: =SUM(AJ23*$Z$4) -> 2010 | AL23: =SUM(AJ23) -> 201 | AM23: =SUM(AL23*$Z$4) -> 2010 | AN23: =SUM(AO23/19600) -> 0.71785714 | AO23: =SUM(AA23+AC23+AE23+AG23+AI23+AK23+AM23) -> 14070 | AQ23: =SUM(AR23/92970) -> 0.64648551 | AR23: =Y23+AO23 -> 60103.758 | AS23: =SUM(AR23-AR22-AT23) -> 0 | AV23: =IF(AT23>0,AU23,AV22) -> 0.78 | AW23: =-SUM('B5'!AI22) -> 0 | AX23: =-SUM(AW23-AS23) -> 0 | AY23: =SUM(AX23+AW23) -> 0 | AZ23: =ELEC!A20 -> 0 | BA23: ='General information '!D23 -> 0 | BB23: =SUM('General information '!E23) -> 0 | BC23: =IF(AR22>=AR23,0,1) -> 0 | BD23: 19222 | BE23: =(305/1185)*ELEC!Q21 -> 0 | BG23: =#REF!-BE23 -> #REF!
A24: =ELEC!C21 -> 44274 | B24: ='B5'!B23 -> 194.5 | C24: =B24*$B$4 -> 4184.8871 | D24: =SUM(B24) -> 194.5 | E24: =D24*$B$4 -> 4184.8871 | F24: =SUM(D24) -> 194.5 | G24: =F24*$B$4 -> 4184.8871 | H24: =SUM(F24) -> 194.5 | I24: =H24*$B$4 -> 4184.8871 | J24: =SUM(H24) -> 194.5 | K24: =J24*$B$4 -> 4184.8871 | L24: =SUM(J24) -> 194.5 | M24: =L24*$B$4 -> 4184.8871 | N24: =SUM(L24) -> 194.5 | O24: =N24*$B$4 -> 4184.8871 | P24: =SUM(N24) -> 194.5 | Q24: =P24*$B$4 -> 4184.8871 | R24: =SUM(P24) -> 194.5 | S24: =R24*$B$4 -> 4184.8871 | T24: =SUM(R24) -> 194.5 | U24: =T24*$B$4 -> 4184.8871 | V24: =SUM(T24) -> 194.5 | W24: =V24*$B$4 -> 4184.8871 | X24: =SUM(Y24/73370) -> 0.62741935 | Y24: =SUM(C24+E24+G24+I24+K24+M24+O24+Q24+S24+U24+W24) -> 46033.758 | Z24: ='B5'!C23 -> 201 | AA24: =SUM(Z24*$Z$4) -> 2010 | AB24: =SUM(Z24) -> 201 | AC24: =SUM(AB24*$Z$4) -> 2010 | AD24: =SUM(AB24) -> 201 | AE24: =SUM(AD24*$Z$4) -> 2010 | AF24: =SUM(AD24) -> 201 | AG24: =SUM(AF24*$Z$4) -> 2010 | AH24: =SUM(AF24) -> 201 | AI24: =SUM(AH24*$Z$4) -> 2010 | AJ24: =SUM(AH24) -> 201 | AK24: =SUM(AJ24*$Z$4) -> 2010 | AL24: =SUM(AJ24) -> 201 | AM24: =SUM(AL24*$Z$4) -> 2010 | AN24: =SUM(AO24/19600) -> 0.71785714 | AO24: =SUM(AA24+AC24+AE24+AG24+AI24+AK24+AM24) -> 14070 | AQ24: =SUM(AR24/92970) -> 0.64648551 | AR24: =Y24+AO24 -> 60103.758 | AS24: =SUM(AR24-AR23-AT24) -> 0 | AV24: =IF(AT24>0,AU24,AV23) -> 0.78 | AW24: =-SUM('B5'!AI23) -> 0 | AX24: =-SUM(AW24-AS24) -> 0 | AY24: =SUM(AX24+AW24) -> 0 | AZ24: =ELEC!A21 -> 0 | BA24: ='General information '!D24 -> 0 | BB24: =SUM('General information '!E24) -> 0 | BC24: =IF(AR23>=AR24,0,1) -> 0 | BD24: 19222 | BE24: =(305/1185)*ELEC!Q22 -> 0 | BG24: =#REF!-BE24 -> #REF!
... A32: =ELEC!C29 -> 44282 | B32: ='B5'!B31 -> 194.5 | C32: =B32*$B$4 -> 4184.8871 | D32: =SUM(B32) -> 194.5 | E32: =D32*$B$4 -> 4184.8871 | F32: =SUM(D32) -> 194.5 | G32: =F32*$B$4 -> 4184.8871 | H32: =SUM(F32) -> 194.5 | I32: =H32*$B$4 -> 4184.8871 | J32: =SUM(H32) -> 194.5 | K32: =J32*$B$4 -> 4184.8871 | L32: =SUM(J32) -> 194.5 | M32: =L32*$B$4 -> 4184.8871 | N32: =SUM(L32) -> 194.5 | O32: =N32*$B$4 -> 4184.8871 | P32: =SUM(N32) -> 194.5 | Q32: =P32*$B$4 -> 4184.8871 | R32: =SUM(P32) -> 194.5 | S32: =R32*$B$4 -> 4184.8871 | T32: =SUM(R32) -> 194.5 | U32: =T32*$B$4 -> 4184.8871 | V32: =SUM(T32) -> 194.5 | W32: =V32*$B$4 -> 4184.8871 | X32: =SUM(Y32/73370) -> 0.62741935 | Y32: =SUM(C32+E32+G32+I32+K32+M32+O32+Q32+S32+U32+W32) -> 46033.758 | Z32: ='B5'!C31 -> 201 | AA32: =SUM(Z32*$Z$4) -> 2010 | AB32: =SUM(Z32) -> 201 | AC32: =SUM(AB32*$Z$4) -> 2010 | AD32: =SUM(AB32) -> 201 | AE32: =SUM(AD32*$Z$4) -> 2010 | AF32: =SUM(AD32) -> 201 | AG32: =SUM(AF32*$Z$4) -> 2010 | AH32: =SUM(AF32) -> 201 | AI32: =SUM(AH32*$Z$4) -> 2010 | AJ32: =SUM(AH32) -> 201 | AK32: =SUM(AJ32*$Z$4) -> 2010 | AL32: =SUM(AJ32) -> 201 | AM32: =SUM(AL32*$Z$4) -> 2010 | AN32: =SUM(AO32/19600) -> 0.71785714 | AO32: =SUM(AA32+AC32+AE32+AG32+AI32+AK32+AM32) -> 14070 | AQ32: =SUM(AR32/92970) -> 0.64648551 | AR32: =Y32+AO32 -> 60103.758 | AS32: =SUM(AR32-AR31-AT32) -> 0 | AV32: =IF(AT32>0,AU32,AV31) -> 0.78 | AW32: =-SUM('B5'!AI31) -> 0 | AX32: =-SUM(AW32-AS32) -> 0 | AY32: =SUM(AX32+AW32) -> 0 | AZ32: =ELEC!A29 -> 0 | BA32: ='General information '!D32 -> 0 | BB32: =SUM('General information '!E32) -> 0 | BC32: =IF(AR31>=AR32,0,1) -> 0 | BD32: 19222 | BE32: =(305/1185)*ELEC!Q30 -> 0 | BG32: =#REF!-BE32 -> #REF!
A33: =ELEC!C30 -> 44283 | B33: ='B5'!B32 -> 194.5 | C33: =B33*$B$4 -> 4184.8871 | D33: =SUM(B33) -> 194.5 | E33: =D33*$B$4 -> 4184.8871 | F33: =SUM(D33) -> 194.5 | G33: =F33*$B$4 -> 4184.8871 | H33: =SUM(F33) -> 194.5 | I33: =H33*$B$4 -> 4184.8871 | J33: =SUM(H33) -> 194.5 | K33: =J33*$B$4 -> 4184.8871 | L33: =SUM(J33) -> 194.5 | M33: =L33*$B$4 -> 4184.8871 | N33: =SUM(L33) -> 194.5 | O33: =N33*$B$4 -> 4184.8871 | P33: =SUM(N33) -> 194.5 | Q33: =P33*$B$4 -> 4184.8871 | R33: =SUM(P33) -> 194.5 | S33: =R33*$B$4 -> 4184.8871 | T33: =SUM(R33) -> 194.5 | U33: =T33*$B$4 -> 4184.8871 | V33: =SUM(T33) -> 194.5 | W33: =V33*$B$4 -> 4184.8871 | X33: =SUM(Y33/73370) -> 0.62741935 | Y33: =SUM(C33+E33+G33+I33+K33+M33+O33+Q33+S33+U33+W33) -> 46033.758 | Z33: ='B5'!C32 -> 201 | AA33: =SUM(Z33*$Z$4) -> 2010 | AB33: =SUM(Z33) -> 201 | AC33: =SUM(AB33*$Z$4) -> 2010 | AD33: =SUM(AB33) -> 201 | AE33: =SUM(AD33*$Z$4) -> 2010 | AF33: =SUM(AD33) -> 201 | AG33: =SUM(AF33*$Z$4) -> 2010 | AH33: =SUM(AF33) -> 201 | AI33: =SUM(AH33*$Z$4) -> 2010 | AJ33: =SUM(AH33) -> 201 | AK33: =SUM(AJ33*$Z$4) -> 2010 | AL33: =SUM(AJ33) -> 201 | AM33: =SUM(AL33*$Z$4) -> 2010 | AN33: =SUM(AO33/19600) -> 0.71785714 | AO33: =SUM(AA33+AC33+AE33+AG33+AI33+AK33+AM33) -> 14070 | AQ33: =SUM(AR33/92970) -> 0.64648551 | AR33: =Y33+AO33 -> 60103.758 | AS33: =SUM(AR33-AR32-AT33) -> 0 | AV33: =IF(AT33>0,AU33,AV32) -> 0.78 | AW33: =-SUM('B5'!AI32) -> 0 | AX33: =-SUM(AW33-AS33) -> 0 | AY33: =SUM(AX33+AW33) -> 0 | AZ33: =ELEC!A30 -> 0 | BA33: ='General information '!D33 -> 0 | BB33: =SUM('General information '!E33) -> 0 | BC33: =IF(AR32>=AR33,0,1) -> 0 | BD33: 19222 | BE33: =(305/1185)*ELEC!#REF! -> #REF! | BG33: =#REF!-BE33 -> #REF!
A34: =ELEC!C31 -> 44284 | B34: ='B5'!B33 -> 194.5 | C34: =B34*$B$4 -> 4184.8871 | D34: =SUM(B34) -> 194.5 | E34: =D34*$B$4 -> 4184.8871 | F34: =SUM(D34) -> 194.5 | G34: =F34*$B$4 -> 4184.8871 | H34: =SUM(F34) -> 194.5 | I34: =H34*$B$4 -> 4184.8871 | J34: =SUM(H34) -> 194.5 | K34: =J34*$B$4 -> 4184.8871 | L34: =SUM(J34) -> 194.5 | M34: =L34*$B$4 -> 4184.8871 | N34: =SUM(L34) -> 194.5 | O34: =N34*$B$4 -> 4184.8871 | P34: =SUM(N34) -> 194.5 | Q34: =P34*$B$4 -> 4184.8871 | R34: =SUM(P34) -> 194.5 | S34: =R34*$B$4 -> 4184.8871 | T34: =SUM(R34) -> 194.5 | U34: =T34*$B$4 -> 4184.8871 | V34: =SUM(T34) -> 194.5 | W34: =V34*$B$4 -> 4184.8871 | X34: =SUM(Y34/73370) -> 0.62741935 | Y34: =SUM(C34+E34+G34+I34+K34+M34+O34+Q34+S34+U34+W34) -> 46033.758 | Z34: ='B5'!C33 -> 201 | AA34: =SUM(Z34*$Z$4) -> 2010 | AB34: =SUM(Z34) -> 201 | AC34: =SUM(AB34*$Z$4) -> 2010 | AD34: =SUM(AB34) -> 201 | AE34: =SUM(AD34*$Z$4) -> 2010 | AF34: =SUM(AD34) -> 201 | AG34: =SUM(AF34*$Z$4) -> 2010 | AH34: =SUM(AF34) -> 201 | AI34: =SUM(AH34*$Z$4) -> 2010 | AJ34: =SUM(AH34) -> 201 | AK34: =SUM(AJ34*$Z$4) -> 2010 | AL34: =SUM(AJ34) -> 201 | AM34: =SUM(AL34*$Z$4) -> 2010 | AN34: =SUM(AO34/19600) -> 0.71785714 | AO34: =SUM(AA34+AC34+AE34+AG34+AI34+AK34+AM34) -> 14070 | AQ34: =SUM(AR34/92970) -> 0.64648551 | AR34: =Y34+AO34 -> 60103.758 | AS34: =SUM(AR34-AR33-AT34) -> 0 | AV34: =IF(AT34>0,AU34,AV33) -> 0.78 | AW34: =-SUM('B5'!AI33) -> 0 | AX34: =-SUM(AW34-AS34) -> 0 | AY34: =SUM(AX34+AW34) -> 0 | AZ34: =ELEC!A31 -> 0 | BA34: ='General information '!D34 -> 0 | BB34: =SUM('General information '!E34) -> 0
A35: =ELEC!C32 -> 44285 | B35: ='B5'!B34 -> 194.5 | C35: =B35*$B$4 -> 4184.8871 | D35: =SUM(B35) -> 194.5 | E35: =D35*$B$4 -> 4184.8871 | F35: =SUM(D35) -> 194.5 | G35: =F35*$B$4 -> 4184.8871 | H35: =SUM(F35) -> 194.5 | I35: =H35*$B$4 -> 4184.8871 | J35: =SUM(H35) -> 194.5 | K35: =J35*$B$4 -> 4184.8871 | L35: =SUM(J35) -> 194.5 | M35: =L35*$B$4 -> 4184.8871 | N35: =SUM(L35) -> 194.5 | O35: =N35*$B$4 -> 4184.8871 | P35: =SUM(N35) -> 194.5 | Q35: =P35*$B$4 -> 4184.8871 | R35: =SUM(P35) -> 194.5 | S35: =R35*$B$4 -> 4184.8871 | T35: =SUM(R35) -> 194.5 | U35: =T35*$B$4 -> 4184.8871 | V35: =SUM(T35) -> 194.5 | W35: =V35*$B$4 -> 4184.8871 | X35: =SUM(Y35/73370) -> 0.62741935 | Y35: =SUM(C35+E35+G35+I35+K35+M35+O35+Q35+S35+U35+W35) -> 46033.758 | Z35: ='B5'!C34 -> 201 | AA35: =SUM(Z35*$Z$4) -> 2010 | AB35: =SUM(Z35) -> 201 | AC35: =SUM(AB35*$Z$4) -> 2010 | AD35: =SUM(AB35) -> 201 | AE35: =SUM(AD35*$Z$4) -> 2010 | AF35: =SUM(AD35) -> 201 | AG35: =SUM(AF35*$Z$4) -> 2010 | AH35: =SUM(AF35) -> 201 | AI35: =SUM(AH35*$Z$4) -> 2010 | AJ35: =SUM(AH35) -> 201 | AK35: =SUM(AJ35*$Z$4) -> 2010 | AL35: =SUM(AJ35) -> 201 | AM35: =SUM(AL35*$Z$4) -> 2010 | AN35: =SUM(AO35/19600) -> 0.71785714 | AO35: =SUM(AA35+AC35+AE35+AG35+AI35+AK35+AM35) -> 14070 | AQ35: =SUM(AR35/92970) -> 0.64648551 | AR35: =Y35+AO35 -> 60103.758 | AS35: =SUM(AR35-AR34-AT35) -> 0 | AV35: =IF(AT35>0,AU35,AV34) -> 0.78 | AW35: =-SUM('B5'!AI34) -> 0 | AX35: =-SUM(AW35-AS35) -> 0 | AY35: =SUM(AX35+AW35) -> 0 | AZ35: =ELEC!A32 -> 0 | BA35: ='General information '!D35 -> 0 | BB35: =SUM('General information '!E35) -> 0
A36: =ELEC!C33 -> 44286 | B36: ='B5'!B35 -> 194.5 | C36: =B36*$B$4 -> 4184.8871 | D36: =SUM(B36) -> 194.5 | E36: =D36*$B$4 -> 4184.8871 | F36: =SUM(D36) -> 194.5 | G36: =F36*$B$4 -> 4184.8871 | H36: =SUM(F36) -> 194.5 | I36: =H36*$B$4 -> 4184.8871 | J36: =SUM(H36) -> 194.5 | K36: =J36*$B$4 -> 4184.8871 | L36: =SUM(J36) -> 194.5 | M36: =L36*$B$4 -> 4184.8871 | N36: =SUM(L36) -> 194.5 | O36: =N36*$B$4 -> 4184.8871 | P36: =SUM(N36) -> 194.5 | Q36: =P36*$B$4 -> 4184.8871 | R36: =SUM(P36) -> 194.5 | S36: =R36*$B$4 -> 4184.8871 | T36: =SUM(R36) -> 194.5 | U36: =T36*$B$4 -> 4184.8871 | V36: =SUM(T36) -> 194.5 | W36: =V36*$B$4 -> 4184.8871 | X36: =SUM(Y36/73370) -> 0.62741935 | Y36: =SUM(C36+E36+G36+I36+K36+M36+O36+Q36+S36+U36+W36) -> 46033.758 | Z36: ='B5'!C35 -> 201 | AA36: =SUM(Z36*$Z$4) -> 2010 | AB36: =SUM(Z36) -> 201 | AC36: =SUM(AB36*$Z$4) -> 2010 | AD36: =SUM(AB36) -> 201 | AE36: =SUM(AD36*$Z$4) -> 2010 | AF36: =SUM(AD36) -> 201 | AG36: =SUM(AF36*$Z$4) -> 2010 | AH36: =SUM(AF36) -> 201 | AI36: =SUM(AH36*$Z$4) -> 2010 | AJ36: =SUM(AH36) -> 201 | AK36: =SUM(AJ36*$Z$4) -> 2010 | AL36: =SUM(AJ36) -> 201 | AM36: =SUM(AL36*$Z$4) -> 2010 | AN36: =SUM(AO36/19600) -> 0.71785714 | AO36: =SUM(AA36+AC36+AE36+AG36+AI36+AK36+AM36) -> 14070 | AQ36: =SUM(AR36/92970) -> 0.64648551 | AR36: =Y36+AO36 -> 60103.758 | AS36: =SUM(AR36-AR35-AT36) -> 0 | AV36: =IF(AT36>0,AU36,AV35) -> 0.78 | AW36: =-SUM('B5'!AI35) -> 0 | AX36: =-SUM(AW36-AS36) -> 0 | AY36: =SUM(AX36+AW36) -> 0 | AZ36: =ELEC!A33 -> 0 | BA36: ='General information '!D36 -> 0 | BB36: =SUM('General information '!E36) -> 0 | BC36: =IF(AR33>=AR36,0,1) -> 0 | BD36: 19222 | BE36: =(305/1185)*ELEC!#REF! -> #REF! | BG36: =#REF!-BE36 -> #REF!
AR37: NB delivery | AS37: =COUNT(AT6:AT33) -> 1 | AT37: =SUM(AT6:AT33) -> 6951 | AU37: =SUM(AU6:AU33)/AS37 -> 0.78 | AX37: =SUM(AX6:AX33) -> -11907.719 | AY37: =SUM(AY6:AY33) -> -14192.919
AT38: =+AT37*AU37 -> 5421.78
AS40: =SUM(AS6:AS33)/'EDl log'!A35 -> -1774.1149

Sheet Sheet1
A1: TOTAL CH RH | B1: TOTAL CH cons KW | C1: TOTAL ELIC KW | D1: TOTAL EDL | E1: TOTAL GEN KW | F1: GEN HR | G1: WATER IN | H1: TOTAL CT | I1: TOTAL WATER | J1: Date
A2: =ELEC!T3+ELEC!X1+ELEC!AB3 -> #VALUE! | B2: =ELEC!AF3 -> 675 | C2: =ELEC!N3 -> 8408 | D2: =C2-E2 -> 2244 | E2: =ELEC!Q3 -> 6164 | F2: =GEN!Z2 -> 13 | G2: =WATER!C5+WATER!H5 -> 0 | H2: =WATER!L5 -> 0 | I2: =WATER!BC5+WATER!BD5+WATER!BE6-Sheet1!G2 -> -28.8 | J2: ='B5'!A4 -> 44255
A3: =ELEC!T4+ELEC!X2+ELEC!AB4 -> 9 | B3: =ELEC!AF4 -> 859 | C3: =ELEC!N4 -> 9041 | D3: =C3-E3 -> 1705 | E3: =ELEC!Q4 -> 7336 | F3: =GEN!Z3 -> 12 | G3: =WATER!C6+WATER!H6 -> 0 | H3: =WATER!L6 -> 0 | I3: =WATER!BC6+WATER!BD6+WATER!BE7-Sheet1!G3 -> -45.5 | J3: ='B5'!A5 -> 44256
A4: =ELEC!T5+ELEC!X5+ELEC!AB5 -> 5 | B4: =ELEC!AF5 -> 680 | C4: =ELEC!N5 -> 7715 | D4: =C4-E4 -> 2865 | E4: =ELEC!Q5 -> 4850 | F4: =GEN!Z4 -> 15 | G4: =WATER!C7+WATER!H7 -> 0 | H4: =WATER!L7 -> 0 | I4: =WATER!BC7+WATER!BD7+WATER!BE8-Sheet1!G4 -> -50.3 | J4: ='B5'!A6 -> 44257
A5: =ELEC!T6+ELEC!X6+ELEC!AB6 -> 3 | B5: =ELEC!AF6 -> 569 | C5: =ELEC!N6 -> 7405 | D5: =C5-E5 -> 3910 | E5: =ELEC!Q6 -> 3495 | F5: =GEN!Z5 -> 9 | G5: =WATER!C8+WATER!H8 -> 0 | H5: =WATER!L8 -> 0 | I5: =WATER!BC8+WATER!BD8+WATER!BE9-Sheet1!G5 -> -32 | J5: ='B5'!A7 -> 44258
A6: =ELEC!T7+ELEC!X7+ELEC!AB7 -> 5 | B6: =ELEC!AF7 -> 822 | C6: =ELEC!N7 -> 7744 | D6: =C6-E6 -> 7744 | E6: =ELEC!Q24 -> 0 | F6: =GEN!Z6 -> 6 | G6: =WATER!C9+WATER!H9 -> 0 | H6: =WATER!L9 -> 2 | I6: =WATER!BC9+WATER!BD9+WATER!BE10-Sheet1!G6 -> -3.6 | J6: ='B5'!A8 -> 44259
A7: =ELEC!T8+ELEC!X8+ELEC!AB8 -> 4 | B7: =ELEC!AF8 -> 738 | C7: =ELEC!N8 -> 7618 | D7: =C7-E7 -> 2738 | E7: =ELEC!Q8 -> 4880 | F7: =GEN!Z7 -> 7 | G7: =WATER!C10+WATER!H10 -> 0 | H7: =WATER!L10 -> 0 | I7: =WATER!BC10+WATER!BD10+WATER!BE11-Sheet1!G7 -> -9.5 | J7: ='B5'!A9 -> 44260
A8: =ELEC!T9+ELEC!X9+ELEC!AB9 -> 3 | B8: =ELEC!AF9 -> 381 | C8: =ELEC!N9 -> 6359 | D8: =C8-E8 -> 4300 | E8: =ELEC!Q9 -> 2059 | F8: =GEN!Z8 -> 9.3 | G8: =WATER!C11+WATER!H11 -> 0 | H8: =WATER!L11 -> 2 | I8: =WATER!BC11+WATER!BD11+WATER!BE12-Sheet1!G8 -> -17.1 | J8: ='B5'!A10 -> 44261
A9: =ELEC!T10+ELEC!X10+ELEC!AB10 -> 3 | B9: =ELEC!AF10 -> 606 | C9: =ELEC!N10 -> 6832 | D9: =C9-E9 -> 4022 | E9: =ELEC!Q10 -> 2810 | F9: =GEN!Z9 -> 3.7 | G9: =WATER!C12+WATER!H12 -> 0 | H9: =WATER!L12 -> 1 | I9: =WATER!BC12+WATER!BD12+WATER!BE13-Sheet1!G9 -> -24 | J9: ='B5'!A11 -> 44262
A10: =ELEC!T11+ELEC!X11+ELEC!AB11 -> 0 | B10: =ELEC!AF11 -> 0 | C10: =ELEC!N11 -> 0 | D10: =C10-E10 -> 0 | E10: =ELEC!Q11 -> 0 | F10: =GEN!Z10 -> 5 | G10: =WATER!C13+WATER!H13 -> 0 | H10: =WATER!L13 -> 0 | I10: =WATER!BC13+WATER!BD13+WATER!BE14-Sheet1!G10 -> -12 | J10: ='B5'!A12 -> 44263
A11: =ELEC!T12+ELEC!X12+ELEC!AB12 -> 0 | B11: =ELEC!AF12 -> 0 | C11: =ELEC!N12 -> 0 | D11: =C11-E11 -> 0 | E11: =ELEC!Q12 -> 0 | F11: =GEN!Z11 -> 0 | G11: =WATER!C14+WATER!H14 -> 0 | H11: =WATER!L14 -> 0 | I11: =WATER!BC14+WATER!BD14+WATER!BE15-Sheet1!G11 -> 0 | J11: ='B5'!A13 -> 44264
A12: =ELEC!T13+ELEC!X13+ELEC!AB13 -> 0 | B12: =ELEC!AF13 -> 0 | C12: =ELEC!N13 -> 0 | D12: =C12-E12 -> 0 | E12: =ELEC!Q13 -> 0 | F12: =GEN!Z12 -> 0 | G12: =WATER!C15+WATER!H15 -> 0 | H12: =WATER!L15 -> 0 | I12: =WATER!BC15+WATER!BD15+WATER!BE16-Sheet1!G12 -> 0 | J12: ='B5'!A14 -> 44265
A13: =ELEC!T14+ELEC!X14+ELEC!AB14 -> 0 | B13: =ELEC!AF14 -> 0 | C13: =ELEC!N14 -> 0 | D13: =C13-E13 -> 0 | E13: =ELEC!Q14 -> 0 | F13: =GEN!Z13 -> 0 | G13: =WATER!C16+WATER!H16 -> 0 | H13: =WATER!L16 -> 0 | I13: =WATER!BC16+WATER!BD16+WATER!BE17-Sheet1!G13 -> 0 | J13: ='B5'!A15 -> 44266
A14: =ELEC!T15+ELEC!X15+ELEC!AB15 -> 0 | B14: =ELEC!AF15 -> 0 | C14: =ELEC!N15 -> 0 | D14: =C14-E14 -> 0 | E14: =ELEC!Q15 -> 0 | F14: =GEN!Z14 -> 0 | G14: =WATER!C17+WATER!H17 -> 0 | H14: =WATER!L17 -> 0 | I14: =WATER!BC17+WATER!BD17+WATER!BE18-Sheet1!G14 -> 0 | J14: ='B5'!A16 -> 44267
A15: =ELEC!T16+ELEC!X16+ELEC!AB16 -> 0 | B15: =ELEC!AF16 -> 0 | C15: =ELEC!N16 -> 0 | D15: =C15-E15 -> 0 | E15: =ELEC!Q16 -> 0 | F15: =GEN!Z15 -> 0 | G15: =WATER!C18+WATER!H18 -> 0 | H15: =WATER!L18 -> 0 | I15: =WATER!BC18+WATER!BD18+WATER!BE19-Sheet1!G15 -> 0 | J15: ='B5'!A17 -> 44268
A16: =ELEC!T17+ELEC!X17+ELEC!AB17 -> 0 | B16: =ELEC!AF17 -> 0 | C16: =ELEC!N17 -> 0 | D16: =C16-E16 -> 0 | E16: =ELEC!Q17 -> 0 | F16: =GEN!Z16 -> 0 | G16: =WATER!C19+WATER!H19 -> 0 | H16: =WATER!L19 -> 0 | I16: =WATER!BC19+WATER!BD19+WATER!BE20-Sheet1!G16 -> 0 | J16: ='B5'!A18 -> 44269
A17: =ELEC!T18+ELEC!X18+ELEC!AB18 -> 0 | B17: =ELEC!AF18 -> 0 | C17: =ELEC!N18 -> 0 | D17: =C17-E17 -> 0 | E17: =ELEC!Q18 -> 0 | F17: =GEN!Z17 -> 0 | G17: =WATER!C20+WATER!H20 -> 0 | H17: =WATER!L20 -> 0 | I17: =WATER!BC20+WATER!BD20+WATER!BE21-Sheet1!G17 -> 0 | J17: ='B5'!A19 -> 44270
A18: =ELEC!T19+ELEC!X19+ELEC!AB19 -> 0 | B18: =ELEC!AF19 -> 0 | C18: =ELEC!N19 -> 0 | D18: =C18-E18 -> 0 | E18: =ELEC!Q19 -> 0 | F18: =GEN!Z18 -> 0 | G18: =WATER!C21+WATER!H21 -> 0 | H18: =WATER!L21 -> 0 | I18: =WATER!BC21+WATER!BD21+WATER!BE22-Sheet1!G18 -> 0 | J18: ='B5'!A20 -> 44271
... A29: =ELEC!T30+ELEC!X30+ELEC!AB30 -> 0 | B29: =ELEC!AF30 -> 0 | C29: =ELEC!N30 -> 0 | D29: =C29-E29 -> 0 | E29: =ELEC!Q30 -> 0 | F29: =GEN!Z29 -> 0 | G29: =WATER!C32+WATER!H32 -> 0 | H29: =WATER!L32 -> 0 | I29: =WATER!BC32+WATER!BD32+WATER!BE33-Sheet1!G29 -> 0 | J29: ='B5'!A31 -> 44282
A30: =ELEC!#REF!+ELEC!#REF!+ELEC!#REF! -> #REF! | B30: =ELEC!#REF! -> #REF! | C30: =ELEC!#REF! -> #REF! | D30: =C30-E30 -> #REF! | E30: =ELEC!#REF! -> #REF! | F30: =GEN!Z30 -> 0 | G30: =WATER!C33+WATER!H33 -> 0 | H30: =WATER!L33 -> 0 | I30: =WATER!BC33+WATER!BD33+WATER!#REF!-Sheet1!G30 -> #REF! | J30: ='B5'!A32 -> 44283
A31: =ELEC!#REF!+ELEC!#REF!+ELEC!#REF! -> #REF! | B31: =ELEC!#REF! -> #REF! | C31: =ELEC!#REF! -> #REF! | D31: =C31-E31 -> #REF! | E31: =ELEC!#REF! -> #REF! | F31: =GEN!#REF! -> #REF! | G31: =WATER!#REF!+WATER!#REF! -> #REF! | H31: =WATER!#REF! -> #REF! | I31: =WATER!#REF!+WATER!#REF!+WATER!#REF!-Sheet1!G31 -> #REF! | J31: ='B5'!#REF! -> #REF!
A32: =ELEC!#REF!+ELEC!#REF!+ELEC!#REF! -> #REF! | B32: =ELEC!#REF! -> #REF! | C32: =ELEC!#REF! -> #REF! | D32: =C32-E32 -> #REF! | E32: =ELEC!#REF! -> #REF! | F32: =GEN!#REF! -> #REF! | G32: =WATER!#REF!+WATER!#REF! -> #REF! | H32: =WATER!#REF! -> #REF! | I32: =WATER!#REF!+WATER!#REF!+WATER!BE37-Sheet1!G32 -> #REF!

Sheet Report
B1: Boiler Fuel | C1: Steam Fuel | D1: GEN FUEL | E1: FUEL TOTAL | F1: CT/mᶾ | G1: Water Consumption | H1: Chiller KW | I1: GEN KW | J1: EDL KW | K1: occ | L1: covers | M1: temp. C⁰ | N1: RH %
B3: ='B5'!V3 -> 0 | C3: ='B5'!AH3 -> 0 | E3: =B3+C3+D3 -> 0
A4: 42704 | B4: 810 | C4: -606.1 | D4: 1420.5021 | E4: 1624.4021 | F4: 106 | G4: -58.4 | H4: 6284 | I4: 2399 | J4: 23932 | K4: 0 | L4: 0 | M4: 0 | N4: 0
A5: ='B5'!A5 -> 44256 | B5: ='B5'!V5 -> 244 | C5: ='B5'!AH5 -> 176.2 | D5: =GEN!AI3 -> 1586.5148 | E5: =B5+C5+D5 -> 2006.7148 | F5: =WATER!L5 -> 0 | G5: =WATER!BG5 -> -11.6 | H5: =ELEC!AF3 -> 675 | I5: =ELEC!Q3 -> 6164 | J5: =ELEC!R3 -> 2244
A6: ='B5'!A6 -> 44257 | B6: ='B5'!V6 -> 241 | C6: ='B5'!AH6 -> 110 | D6: =GEN!AI4 -> 1888.1688 | E6: =B6+C6+D6 -> 2239.1688 | F6: =WATER!L6 -> 0 | G6: =WATER!BG6 -> -20.8 | H6: =ELEC!AF4 -> 859 | I6: =ELEC!Q4 -> 7336 | J6: =ELEC!R4 -> 1705
A7: ='B5'!A7 -> 44258 | B7: ='B5'!V7 -> 216 | C7: ='B5'!AH7 -> 0 | D7: =GEN!AI5 -> 1248.3122 | E7: =B7+C7+D7 -> 1464.3122 | F7: =WATER!L7 -> 0 | G7: =WATER!BG7 -> -23.8 | H7: =ELEC!AF5 -> 680 | I7: =ELEC!Q5 -> 4850 | J7: =ELEC!R5 -> 2865
A8: ='B5'!A8 -> 44259 | B8: ='B5'!V8 -> 274 | C8: ='B5'!AH8 -> 38 | D8: =GEN!AI6 -> 899.55696 | E8: =B8+C8+D8 -> 1211.557 | F8: =WATER!L8 -> 0 | G8: =WATER!BG8 -> -32.8 | H8: =ELEC!AF6 -> 569 | I8: =ELEC!Q6 -> 3495 | J8: =ELEC!R6 -> 3910
A9: ='B5'!A9 -> 44260 | B9: ='B5'!V9 -> 238 | C9: ='B5'!AH9 -> 0 | D9: =GEN!AI7 -> 1180.8776 | E9: =B9+C9+D9 -> 1418.8776 | F9: =WATER!L9 -> 2 | G9: =WATER!BG9 -> 0.8 | H9: =ELEC!AF7 -> 822 | I9: =ELEC!Q7 -> 4588 | J9: =ELEC!R7 -> 3156
A10: ='B5'!A10 -> 44261 | B10: ='B5'!V10 -> 228 | C10: ='B5'!AH10 -> 0 | D10: =GEN!AI8 -> 1256.0338 | E10: =B10+C10+D10 -> 1484.0338 | F10: =WATER!L10 -> 0 | G10: =WATER!BG10 -> -4.4 | H10: =ELEC!AF8 -> 738 | I10: =ELEC!Q8 -> 4880 | J10: =ELEC!R8 -> 2738
A11: ='B5'!A11 -> 44262 | B11: ='B5'!V11 -> 230 | C11: ='B5'!AH11 -> 0 | D11: =GEN!AI9 -> 529.95359 | E11: =B11+C11+D11 -> 759.95359 | F11: =WATER!L11 -> 2 | G11: =WATER!BG11 -> -5.1 | H11: =ELEC!AF9 -> 381 | I11: =ELEC!Q9 -> 2059 | J11: =ELEC!R9 -> 4300
A12: ='B5'!A12 -> 44263 | B12: ='B5'!V12 -> 290 | C12: ='B5'!AH12 -> 0 | D12: =GEN!AI10 -> 723.24895 | E12: =B12+C12+D12 -> 1013.2489 | F12: =WATER!L12 -> 1 | G12: =WATER!BG12 -> -12 | H12: =ELEC!AF10 -> 606 | I12: =ELEC!Q10 -> 2810 | J12: =ELEC!R10 -> 4022
A13: ='B5'!A13 -> 44264 | B13: ='B5'!V13 -> 0 | C13: ='B5'!AH13 -> 0 | D13: =GEN!AI11 -> 0 | E13: =B13+C13+D13 -> 0 | F13: =WATER!L13 -> 0 | G13: =WATER!BG13 -> -12 | H13: =ELEC!AF11 -> 0 | I13: =ELEC!Q11 -> 0 | J13: =ELEC!R11 -> 0
A14: ='B5'!A14 -> 44265 | B14: ='B5'!V14 -> 0 | C14: ='B5'!AH14 -> 0 | D14: =GEN!AI12 -> 0 | E14: =B14+C14+D14 -> 0 | F14: =WATER!L14 -> 0 | G14: =WATER!BG14 -> 0 | H14: =ELEC!AF12 -> 0 | I14: =ELEC!Q12 -> 0 | J14: =ELEC!R12 -> 0
A15: ='B5'!A15 -> 44266 | B15: ='B5'!V15 -> 0 | C15: ='B5'!AH15 -> 0 | D15: =GEN!AI13 -> 0 | E15: =B15+C15+D15 -> 0 | F15: =WATER!L15 -> 0 | G15: =WATER!BG15 -> 0 | H15: =ELEC!AF13 -> 0 | I15: =ELEC!Q13 -> 0 | J15: =ELEC!R13 -> 0
A16: ='B5'!A16 -> 44267 | B16: ='B5'!V16 -> 0 | C16: ='B5'!AH16 -> 0 | D16: =GEN!AI14 -> 0 | E16: =B16+C16+D16 -> 0 | F16: =WATER!L16 -> 0 | G16: =WATER!BG16 -> 0 | H16: =ELEC!AF14 -> 0 | I16: =ELEC!Q14 -> 0 | J16: =ELEC!R14 -> 0
... A32: ='B5'!A32 -> 44283 | B32: ='B5'!V32 -> 0 | C32: ='B5'!AH32 -> 0 | D32: =GEN!AI30 -> 0 | E32: =B32+C32+D32 -> 0 | F32: =WATER!L32 -> 0 | G32: =WATER!BG32 -> 0 | H32: =ELEC!AF30 -> 0 | I32: =ELEC!Q30 -> 0 | J32: =ELEC!R30 -> 0
A33: ='B5'!#REF! -> #REF! | B33: ='B5'!#REF! -> #REF! | C33: ='B5'!#REF! -> #REF! | D33: =GEN!#REF! -> #REF! | E33: =B33+C33+D33 -> #REF! | F33: =WATER!L33 -> 0 | G33: =WATER!BG33 -> 0 | H33: =ELEC!#REF! -> #REF! | I33: =ELEC!#REF! -> #REF! | J33: =ELEC!#REF! -> #REF!
A34: ='B5'!#REF! -> #REF! | B34: ='B5'!#REF! -> #REF! | C34: ='B5'!#REF! -> #REF! | D34: =GEN!#REF! -> #REF! | E34: =B34+C34+D34 -> #REF! | F34: =WATER!#REF! -> #REF! | G34: =WATER!#REF! -> #REF! | H34: =ELEC!#REF! -> #REF! | I34: =ELEC!#REF! -> #REF! | J34: =ELEC!#REF! -> #REF!

Sheet Sheet5
T3: Outdoor conditions
C4: Date | D4: Total Boiler running H | E4: AVE CONSUM | F4: Total Steam running H | G4: AVE CONSUM | H4: Total GEN running H | I4: AVE CONSUM | J4: Actual Diesel Consumption | K4: Actual Gas Consumption | L4: Total ELEC power | M4: Gen ELEC power | N4: EDL ELEC power | O4: Chillers running H | P4: Total Water delivery | Q4: Total water consumption | R4: Total water in tanks | S4: Occupancy | T4: AVE TEPM | U4: AVE Humidity
C5: 42429 | D5: ='B5'!AL4 -> 3 | E5: =D5*90 -> 270 | F5: ='B5'!AM4 -> 0 | G5: =F5*107 -> 0 | H5: =GEN!Z3 -> 12
C6: 42430 | D6: ='B5'!AL5 -> 4 | E6: =D6*90 -> 360 | F6: ='B5'!AM5 -> 3 | G6: =F6*107 -> 321
C7: 42431 | D7: ='B5'!AL6 -> 3 | E7: =D7*90 -> 270 | F7: ='B5'!AM6 -> 2 | G7: =F7*107 -> 214
C8: 42432 | D8: ='B5'!AL7 -> 3 | E8: =D8*90 -> 270 | F8: ='B5'!AM7 -> 0 | G8: =F8*107 -> 0
C9: 42433 | D9: ='B5'!AL8 -> 3 | E9: =D9*90 -> 270 | F9: ='B5'!AM8 -> 0 | G9: =F9*107 -> 0
C10: 42434 | D10: ='B5'!AL9 -> 4 | E10: =D10*90 -> 360 | F10: ='B5'!AM9 -> 0 | G10: =F10*107 -> 0
C11: 42435 | D11: ='B5'!AL10 -> 2 | E11: =D11*90 -> 180 | F11: ='B5'!AM10 -> 0 | G11: =F11*107 -> 0
C12: 42436 | D12: ='B5'!AL11 -> 3 | E12: =D12*90 -> 270 | F12: ='B5'!AM11 -> 0 | G12: =F12*107 -> 0
C13: 42437 | D13: ='B5'!AL12 -> 4 | E13: =D13*90 -> 360 | F13: ='B5'!AM12 -> 0 | G13: =F13*107 -> 0
C14: 42438 | D14: ='B5'!AL13 -> 0 | E14: =D14*90 -> 0 | F14: ='B5'!AM13 -> 0 | G14: =F14*107 -> 0
C15: 42439 | D15: ='B5'!AL14 -> 0 | E15: =D15*90 -> 0 | F15: ='B5'!AM14 -> 0 | G15: =F15*107 -> 0
C16: 42440 | D16: ='B5'!AL15 -> 0 | E16: =D16*90 -> 0 | F16: ='B5'!AM15 -> 0 | G16: =F16*107 -> 0
C17: 42441 | D17: ='B5'!AL16 -> 0 | E17: =D17*90 -> 0 | F17: ='B5'!AM16 -> 0 | G17: =F17*107 -> 0
... C33: 42457 | D33: ='B5'!AL32 -> 0 | E33: =D33*90 -> 0 | F33: ='B5'!AM32 -> 0 | G33: =F33*107 -> 0
C34: 42458 | D34: ='B5'!#REF! -> #REF! | E34: =D34*90 -> #REF! | F34: ='B5'!#REF! -> #REF! | G34: =F34*107 -> #REF!
C35: 42459 | D35: ='B5'!#REF! -> #REF! | E35: =D35*90 -> #REF! | F35: ='B5'!#REF! -> #REF! | G35: =F35*107 -> #REF!
C36: 42460 | D36: ='B5'!#REF! -> #REF! | E36: =D36*90 -> #REF! | F36: ='B5'!#REF! -> #REF! | G36: =F36*107 -> #REF!
C37: 42461 | D37: ='B5'!#REF! -> #REF! | E37: =D37*90 -> #REF! | F37: ='B5'!#REF! -> #REF! | G37: =F37*107 -> #REF!

Sheet GEN
B1: GEN1 | C1: RUN HR | D1: Fuel Counter Index | E1: Cons /day | F1: Diesel L/H | H1: next service | I1: ALARM | J1: GEN2 | K1: RUN HR | L1: Fuel Counter Index | M1: Cons /day | N1: Diesel L/H | P1: next service | Q1: ALARM | R1: GEN3 | S1: RUN HR | T1: Fuel Counter Index | U1: Cons /day | V1: Diesel L/H | X1: next service | Y1: ALARM | Z1: RH total | AA1: Gen Con /day | AB1: Total Deisel Cons/day | AC1: H /L | AD1: TOAL KW GEN | AI1: fuel Consuption | AK1: AVG KW/h
A2: =ELEC!C2 -> 44255 | B2: =[1]GEN!B30 -> 9649 | C2: =[1]GEN!C30 -> 0 | D2: =[1]GEN!D30 -> 333321 | E2: =[1]GEN!E30 -> 0 | F2: =[1]GEN!F30 -> 0 | G2: =[1]GEN!G30 -> 0 | H2: =[1]GEN!H30 -> 9729 | I2: =[1]GEN!I30 -> ok | ... AK2: =[1]GEN!AK30 -> 110.08114
A3: =ELEC!C3 -> 44256 | B3: =B2 -> 9649 | C3: =B3-B2 -> 0 | D3: =D2 -> 333321 | E3: =SUM(D3-D2) -> 0 | F3: =IF(C3>0,E3/C3,0) -> 0 | G3: =[5]GEN!G32 -> 0 | H3: =H2 -> 9729 | I3: =IF(B3-H3<=0,"ok","oil change") -> ok | J3: =J2 -> 10698 | K3: =J3-J2 -> 0 | L3: =L2 -> 357691 | M3: =SUM(L3-L2) -> 0 | N3: =IF(K3>0,M3/K3,0) -> 0 | O3: =[5]GEN!O32 -> 0 | P3: =P2 -> 10873 | Q3: =IF(J3-P3<=0,"ok","oil change") -> ok | R3: 11888 | S3: =R3-R2 -> 12 | T3: =T2+U3 -> 397688 | U3: =V3*S3 -> 2400 | V3: 200 | W3: =[5]GEN!W32 -> 0 | X3: =X2 -> 11898 | Y3: =IF(R3-X3<=0,"ok","oil change") -> ok | Z3: =C3+K3+S3 -> 12 | AA3: =U3+M3+E3 -> 2400 | AB3: =V3+N3+F3 -> 200 | AC3: =IF(Z3>0,AA3/Z3,0) -> 200 | AD3: =ELEC!Q3 -> 6164 | AE3: =SUM(AD3/Z3) -> 513.66667 | AF3: =SUM(AE3/1600) -> 0.32104167 | AG3: =SUM(360*AF3) -> 115.575 | AH3: =SUM(AC3-AG3) -> 84.425 | AI3: =AD3*AJ3 -> 1586.5148 | AJ3: =305/1185 -> 0.25738397 | AK3: =AI3/Z3 -> 132.20956
A4: =ELEC!C4 -> 44257 | B4: =B3 -> 9649 | C4: =B4-B3 -> 0 | D4: =D3 -> 333321 | E4: =SUM(D4-D3) -> 0 | F4: =IF(C4>0,E4/C4,0) -> 0 | H4: =H3 -> 9729 | I4: =IF(B4-H4<=0,"ok","oil change") -> ok | J4: =J3 -> 10698 | K4: =J4-J3 -> 0 | L4: =L3 -> 357691 | M4: =SUM(L4-L3) -> 0 | N4: =IF(K4>0,M4/K4,0) -> 0 | P4: =P3 -> 10873 | Q4: =IF(J4-P4<=0,"ok","oil change") -> ok | R4: 11903 | S4: =R4-R3 -> 15 | T4: =T3+U4 -> 400688 | U4: =V4*S4 -> 3000 | V4: 200 | X4: =X3 -> 11898 | Y4: =IF(R4-X4<=0,"ok","oil change") -> oil change | Z4: =C4+K4+S4 -> 15 | AA4: =U4+M4+E4 -> 3000 | AB4: =V4+N4+F4 -> 200 | AC4: =IF(Z4>0,AA4/Z4,0) -> 200 | AD4: =ELEC!Q4 -> 7336 | AE4: =SUM(AD4/Z4) -> 489.06667 | AF4: =SUM(AE4/1600) -> 0.30566667 | AG4: =SUM(360*AF4) -> 110.04 | AH4: =SUM(AC4-AG4) -> 89.96 | AI4: =AD4*AJ4 -> 1888.1688 | AJ4: =305/1185 -> 0.25738397 | AK4: =AI4/Z4 -> 125.87792
A5: =ELEC!C5 -> 44258 | B5: =B4 -> 9649 | C5: =B5-B4 -> 0 | D5: =D4 -> 333321 | E5: =SUM(D5-D4) -> 0 | F5: =IF(C5>0,E5/C5,0) -> 0 | H5: =H4 -> 9729 | I5: =IF(B5-H5<=0,"ok","oil change") -> ok | J5: =J4 -> 10698 | K5: =J5-J4 -> 0 | L5: =L4 -> 357691 | M5: =SUM(L5-L4) -> 0 | N5: =IF(K5>0,M5/K5,0) -> 0 | P5: =P4 -> 10873 | Q5: =IF(J5-P5<=0,"ok","oil change") -> ok | R5: 11912 | S5: =R5-R4 -> 9 | T5: =T4+U5 -> 402488 | U5: =V5*S5 -> 1800 | V5: 200 | X5: =X4 -> 11898 | Y5: =IF(R5-X5<=0,"ok","oil change") -> oil change | Z5: =C5+K5+S5 -> 9 | AA5: =U5+M5+E5 -> 1800 | AB5: =V5+N5+F5 -> 200 | AC5: =IF(Z5>0,AA5/Z5,0) -> 200 | AD5: =ELEC!Q5 -> 4850 | AE5: =SUM(AD5/Z5) -> 538.88889 | AF5: =SUM(AE5/1600) -> 0.33680556 | AG5: =SUM(320*AF5) -> 107.77778 | AH5: =SUM(AC5-AG5) -> 92.222222 | AI5: =AD5*AJ5 -> 1248.3122 | AJ5: =305/1185 -> 0.25738397 | AK5: =AI5/Z5 -> 138.70136
A6: =ELEC!C6 -> 44259 | B6: =B5 -> 9649 | C6: =B6-B5 -> 0 | D6: =D5 -> 333321 | E6: =SUM(D6-D5) -> 0 | F6: =IF(C6>0,E6/C6,0) -> 0 | H6: =H5 -> 9729 | I6: =IF(B6-H6<=0,"ok","oil change") -> ok | J6: =J5 -> 10698 | K6: =J6-J5 -> 0 | L6: =L5 -> 357691 | M6: =SUM(L6-L5) -> 0 | N6: =IF(K6>0,M6/K6,0) -> 0 | P6: =P5 -> 10873 | Q6: =IF(J6-P6<=0,"ok","oil change") -> ok | R6: 11918 | S6: =R6-R5 -> 6 | T6: =T5+U6 -> 403988 | U6: =V6*S6 -> 1500 | V6: 250 | X6: =X5 -> 11898 | Y6: =IF(R6-X6<=0,"ok","oil change") -> oil change | Z6: =C6+K6+S6 -> 6 | AA6: =U6+M6+E6 -> 1500 | AB6: =V6+N6+F6 -> 250 | AC6: =IF(Z6>0,AA6/Z6,0) -> 250 | AD6: =ELEC!Q6 -> 3495 | AE6: =SUM(AD6/Z6) -> 582.5 | AF6: =SUM(AE6/1600) -> 0.3640625 | AG6: =SUM(320*AF6) -> 116.5 | AH6: =SUM(AC6-AG6) -> 133.5 | AI6: =AD6*AJ6 -> 899.55696 | AJ6: =305/1185 -> 0.25738397 | AK6: =AI6/Z6 -> 149.92616
A7: =ELEC!C7 -> 44260 | B7: =B6 -> 9649 | C7: =B7-B6 -> 0 | D7: =D6 -> 333321 | E7: =SUM(D7-D6) -> 0 | F7: =IF(C7>0,E7/C7,0) -> 0 | H7: =H6 -> 9729 | I7: =IF(B7-H7<=0,"ok","oil change") -> ok | J7: =J6 -> 10698 | K7: =J7-J6 -> 0 | L7: =L6 -> 357691 | M7: =SUM(L7-L6) -> 0 | N7: =IF(K7>0,M7/K7,0) -> 0 | P7: =P6 -> 10873 | Q7: =IF(J7-P7<=0,"ok","oil change") -> ok | R7: 11925 | S7: =R7-R6 -> 7 | T7: =T6+U7 -> 405738 | U7: =V7*S7 -> 1750 | V7: 250 | X7: =X6 -> 11898 | Y7: =IF(R7-X7<=0,"ok","oil change") -> oil change | Z7: =C7+K7+S7 -> 7 | AA7: =U7+M7+E7 -> 1750 | AB7: =V7+N7+F7 -> 250 | AC7: =IF(Z7>0,AA7/Z7,0) -> 250 | AD7: =ELEC!Q7 -> 4588 | AE7: =SUM(AD7/Z7) -> 655.42857 | AF7: =SUM(AE7/1600) -> 0.40964286 | AH7: =SUM(AC7-AG7) -> #VALUE! | AI7: =AD7*AJ7 -> 1180.8776 | AJ7: =305/1185 -> 0.25738397 | AK7: =AI7/Z7 -> 168.69681
A8: =ELEC!C8 -> 44261 | B8: =B7 -> 9649 | C8: =B8-B7 -> 0 | D8: =D7 -> 333321 | E8: =SUM(D8-D7) -> 0 | F8: =IF(C8>0,E8/C8,0) -> 0 | H8: =H7 -> 9729 | I8: =IF(B8-H8<=0,"ok","oil change") -> ok | J8: =J7 -> 10698 | K8: =J8-J7 -> 0 | L8: =L7 -> 357691 | M8: =SUM(L8-L7) -> 0 | N8: =IF(K8>0,M8/K8,0) -> 0 | P8: =P7 -> 10873 | Q8: =IF(J8-P8<=0,"ok","oil change") -> ok | R8: 11934.3 | S8: =R8-R7 -> 9.3 | T8: 407988 | U8: =V8*S8 -> 2325 | V8: 250 | X8: =X7 -> 11898 | Y8: =IF(R8-X8<=0,"ok","oil change") -> oil change | Z8: =C8+K8+S8 -> 9.3 | AA8: =U8+M8+E8 -> 2325 | AB8: =V8+N8+F8 -> 250 | AC8: =IF(Z8>0,AA8/Z8,0) -> 250 | AD8: =ELEC!Q8 -> 4880 | AE8: =SUM(AD8/Z8) -> 524.73118 | AF8: =SUM(AE8/1600) -> 0.32795699 | AG8: =SUM(320*AF8) -> 104.94624 | AH8: =SUM(AC8-AG8) -> 145.05376 | AI8: =AD8*AJ8 -> 1256.0338 | AJ8: =305/1185 -> 0.25738397 | AK8: =AI8/Z8 -> 135.05739
A9: =ELEC!C9 -> 44262 | B9: 9649 | C9: =B9-B8 -> 0 | D9: 333323 | E9: =SUM(D9-D8) -> 2 | F9: =IF(C9>0,E9/C9,0) -> 0 | H9: 9729 | I9: =IF(B9-H9<=0,"ok","oil change") -> ok | J9: =J8 -> 10698 | K9: =J9-J8 -> 0 | L9: =L8 -> 357691 | M9: =SUM(L9-L8) -> 0 | N9: =IF(K9>0,M9/K9,0) -> 0 | P9: =P8 -> 10873 | Q9: =IF(J9-P9<=0,"ok","oil change") -> ok | R9: 11938 | S9: =R9-R8 -> 3.7 | T9: 409913 | U9: =V9*S9 -> 925 | V9: 250 | X9: =X8 -> 11898 | Y9: =IF(R9-X9<=0,"ok","oil change") -> oil change | Z9: =C9+K9+S9 -> 3.7 | AA9: =U9+M9+E9 -> 927 | AB9: =V9+N9+F9 -> 250 | AC9: =IF(Z9>0,AA9/Z9,0) -> 250.54054 | AD9: =ELEC!Q9 -> 2059 | AE9: =SUM(AD9/Z9) -> 556.48649 | AF9: =SUM(AE9/1600) -> 0.34780405 | AG9: =SUM(320*AF9) -> 111.2973 | AH9: =SUM(AC9-AG9) -> 139.24324 | AI9: =AD9*AJ9 -> 529.95359 | AJ9: 0.25738397 | AK9: =IF(Z9>0,AI9/Z9,0) -> 143.2307
A10: =ELEC!C10 -> 44263 | B10: =B9 -> 9649 | C10: =B10-B9 -> 0 | D10: =D9 -> 333323 | E10: =SUM(D10-D9) -> 0 | F10: =IF(C10>0,E10/C10,0) -> 0 | H10: =H9 -> 9729 | I10: =IF(B10-H10<=0,"ok","oil change") -> ok | J10: =J9 -> 10698 | K10: =J10-J9 -> 0 | L10: =L9 -> 357691 | M10: =SUM(L10-L9) -> 0 | N10: =IF(K10>0,M10/K10,0) -> 0 | P10: =P9 -> 10873 | Q10: =IF(J10-P10<=0,"ok","oil change") -> ok | R10: 11943 | S10: =R10-R9 -> 5 | T10: =T9+U10 -> 411163 | U10: =V10*S10 -> 1250 | V10: 250 | X10: =X9 -> 11898 | Y10: =IF(R10-X10<=0,"ok","oil change") -> oil change | Z10: =C10+K10+S10 -> 5 | AA10: =U10+M10+E10 -> 1250 | AB10: =V10+N10+F10 -> 250 | AC10: =IF(Z10>0,AA10/Z10,0) -> 250 | AD10: =ELEC!Q10 -> 2810 | AE10: =SUM(AD10/Z10) -> 562 | AF10: =SUM(AE10/1600) -> 0.35125 | AG10: =SUM(320*AF10) -> 112.4 | AH10: =SUM(AC10-AG10) -> 137.6 | AI10: =AD10*AJ10 -> 723.24895 | AJ10: =305/1185 -> 0.25738397 | AK10: =IF(Z10>0,AI10/Z10,0) -> 144.64979
A11: =ELEC!C11 -> 44264 | B11: =B10 -> 9649 | C11: =B11-B10 -> 0 | D11: =D10 -> 333323 | E11: =SUM(D11-D10) -> 0 | F11: =IF(C11>0,E11/C11,0) -> 0 | H11: =H10 -> 9729 | I11: =IF(B11-H11<=0,"ok","oil change") -> ok | J11: =J10 -> 10698 | K11: =J11-J10 -> 0 | L11: =L10 -> 357691 | M11: =SUM(L11-L10) -> 0 | N11: =IF(K11>0,M11/K11,0) -> 0 | P11: =P10 -> 10873 | Q11: =IF(J11-P11<=0,"ok","oil change") -> ok | R11: =R10 -> 11943 | S11: =R11-R10 -> 0 | T11: =T10+U11 -> 411163 | U11: =V11*S11 -> 0 | V11: 250 | X11: =X10 -> 11898 | Y11: =IF(R11-X11<=0,"ok","oil change") -> oil change | Z11: =C11+K11+S11 -> 0 | AA11: =U11+M11+E11 -> 0 | AB11: =V11+N11+F11 -> 250 | AC11: =IF(Z11>0,AA11/Z11,0) -> 0 | AD11: =ELEC!Q11 -> 0 | AE11: =SUM(AD11/Z11) -> #DIV/0! | AF11: =SUM(AE11/1600) -> #DIV/0! | AG11: =SUM(320*AF11) -> #DIV/0! | AH11: =SUM(AC11-AG11) -> #DIV/0! | AI11: =AD11*AJ11 -> 0 | AJ11: =305/1185 -> 0.25738397 | AK11: =IF(Z11>0,AI11/Z11,0) -> 0
A12: =ELEC!C12 -> 44265 | B12: =B11 -> 9649 | C12: =B12-B11 -> 0 | D12: =D11 -> 333323 | E12: =SUM(D12-D11) -> 0 | F12: =IF(C12>0,E12/C12,0) -> 0 | H12: =H11 -> 9729 | I12: =IF(B12-H12<=0,"ok","oil change") -> ok | J12: =J11 -> 10698 | K12: =J12-J11 -> 0 | L12: =L11 -> 357691 | M12: =SUM(L12-L11) -> 0 | N12: =IF(K12>0,M12/K12,0) -> 0 | P12: =P11 -> 10873 | Q12: =IF(J12-P12<=0,"ok","oil change") -> ok | R12: =R11 -> 11943 | S12: =R12-R11 -> 0 | T12: =T11+U12 -> 411163 | U12: =V12*S12 -> 0 | V12: 250 | X12: =X11 -> 11898 | Y12: =IF(R12-X12<=0,"ok","oil change") -> oil change | Z12: =C12+K12+S12 -> 0 | AA12: =U12+M12+E12 -> 0 | AB12: =V12+N12+F12 -> 250 | AC12: =IF(Z12>0,AA12/Z12,0) -> 0 | AD12: =ELEC!Q12 -> 0 | AE12: =SUM(AD12/Z12) -> #DIV/0! | AF12: =SUM(AE12/1600) -> #DIV/0! | AG12: =SUM(320*AF12) -> #DIV/0! | AH12: =SUM(AC12-AG12) -> #DIV/0! | AI12: =AD12*AJ12 -> 0 | AJ12: =305/1185 -> 0.25738397 | AK12: =IF(Z12>0,AI12/Z12,0) -> 0
A13: =ELEC!C13 -> 44266 | B13: =B12 -> 9649 | C13: =B13-B12 -> 0 | D13: =D12 -> 333323 | E13: =SUM(D13-D12) -> 0 | F13: =IF(C13>0,E13/C13,0) -> 0 | H13: =H12 -> 9729 | I13: =IF(B13-H13<=0,"ok","oil change") -> ok | J13: =J12 -> 10698 | K13: =J13-J12 -> 0 | L13: =L12 -> 357691 | M13: =SUM(L13-L12) -> 0 | N13: =IF(K13>0,M13/K13,0) -> 0 | P13: =P12 -> 10873 | Q13: =IF(J13-P13<=0,"ok","oil change") -> ok | R13: =R12 -> 11943 | S13: =R13-R12 -> 0 | T13: =T12+U13 -> 411163 | U13: =V13*S13 -> 0 | V13: 250 | X13: =X12 -> 11898 | Y13: =IF(R13-X13<=0,"ok","oil change") -> oil change | Z13: =C13+K13+S13 -> 0 | AA13: =U13+M13+E13 -> 0 | AB13: =V13+N13+F13 -> 250 | AC13: =IF(Z13>0,AA13/Z13,0) -> 0 | AD13: =ELEC!Q13 -> 0 | AE13: =SUM(AD13/Z13) -> #DIV/0! | AF13: =SUM(AE13/1600) -> #DIV/0! | AG13: =SUM(320*AF13) -> #DIV/0! | AH13: =SUM(AC13-AG13) -> #DIV/0! | AI13: =AD13*AJ13 -> 0 | AJ13: =305/1185 -> 0.25738397 | AK13: =IF(Z13>0,AI13/Z13,0) -> 0
A14: =ELEC!C14 -> 44267 | B14: =B13 -> 9649 | C14: =B14-B13 -> 0 | D14: =D13 -> 333323 | E14: =SUM(D14-D13) -> 0 | F14: =IF(C14>0,E14/C14,0) -> 0 | H14: =H13 -> 9729 | I14: =IF(B14-H14<=0,"ok","oil change") -> ok | J14: =J13 -> 10698 | K14: =J14-J13 -> 0 | L14: =L13 -> 357691 | M14: =SUM(L14-L13) -> 0 | N14: =IF(K14>0,M14/K14,0) -> 0 | P14: =P13 -> 10873 | Q14: =IF(J14-P14<=0,"ok","oil change") -> ok | R14: =R13 -> 11943 | S14: =R14-R13 -> 0 | T14: =T13+U14 -> 411163 | U14: =V14*S14 -> 0 | V14: 250 | X14: =X13 -> 11898 | Y14: =IF(R14-X14<=0,"ok","oil change") -> oil change | Z14: =C14+K14+S14 -> 0 | AA14: =U14+M14+E14 -> 0 | AB14: =V14+N14+F14 -> 250 | AC14: =IF(Z14>0,AA14/Z14,0) -> 0 | AD14: =ELEC!Q14 -> 0 | AE14: =SUM(AD14/Z14) -> #DIV/0! | AF14: =SUM(AE14/1600) -> #DIV/0! | AG14: =SUM(320*AF14) -> #DIV/0! | AH14: =SUM(AC14-AG14) -> #DIV/0! | AI14: =AD14*AJ14 -> 0 | AJ14: =305/1185 -> 0.25738397 | AK14: =IF(Z14>0,AI14/Z14,0) -> 0
A15: =ELEC!C15 -> 44268 | B15: =B14 -> 9649 | C15: =B15-B14 -> 0 | D15: =D14 -> 333323 | E15: =SUM(D15-D14) -> 0 | F15: =IF(C15>0,E15/C15,0) -> 0 | H15: =H14 -> 9729 | I15: =IF(B15-H15<=0,"ok","oil change") -> ok | J15: =J14 -> 10698 | K15: =J15-J14 -> 0 | L15: =L14 -> 357691 | M15: =SUM(L15-L14) -> 0 | N15: =IF(K15>0,M15/K15,0) -> 0 | P15: =P14 -> 10873 | Q15: =IF(J15-P15<=0,"ok","oil change") -> ok | R15: =R14 -> 11943 | S15: =R15-R14 -> 0 | T15: =T14+U15 -> 411163 | U15: =V15*S15 -> 0 | V15: 250 | X15: =X14 -> 11898 | Y15: =IF(R15-X15<=0,"ok","oil change") -> oil change | Z15: =C15+K15+S15 -> 0 | AA15: =U15+M15+E15 -> 0 | AB15: =V15+N15+F15 -> 250 | AC15: =IF(Z15>0,AA15/Z15,0) -> 0 | AD15: =ELEC!Q15 -> 0 | AE15: =SUM(AD15/Z15) -> #DIV/0! | AF15: =SUM(AE15/1600) -> #DIV/0! | AG15: =SUM(320*AF15) -> #DIV/0! | AH15: =SUM(AC15-AG15) -> #DIV/0! | AI15: =AD15*AJ15 -> 0 | AJ15: =305/1185 -> 0.25738397 | AK15: =IF(Z15>0,AI15/Z15,0) -> 0
A16: =ELEC!C16 -> 44269 | B16: =B15 -> 9649 | C16: =B16-B15 -> 0 | D16: =D15 -> 333323 | E16: =SUM(D16-D15) -> 0 | F16: =IF(C16>0,E16/C16,0) -> 0 | H16: =H15 -> 9729 | I16: =IF(B16-H16<=0,"ok","oil change") -> ok | J16: =J15 -> 10698 | K16: =J16-J15 -> 0 | L16: =L15 -> 357691 | M16: =SUM(L16-L15) -> 0 | N16: =IF(K16>0,M16/K16,0) -> 0 | P16: =P15 -> 10873 | Q16: =IF(J16-P16<=0,"ok","oil change") -> ok | R16: =R15 -> 11943 | S16: =R16-R15 -> 0 | T16: =T15+U16 -> 411163 | U16: =V16*S16 -> 0 | V16: 250 | X16: =X15 -> 11898 | Y16: =IF(R16-X16<=0,"ok","oil change") -> oil change | Z16: =C16+K16+S16 -> 0 | AA16: =U16+M16+E16 -> 0 | AB16: =V16+N16+F16 -> 250 | AC16: =IF(Z16>0,AA16/Z16,0) -> 0 | AD16: =ELEC!Q16 -> 0 | AE16: =SUM(AD16/Z16) -> #DIV/0! | AF16: =SUM(AE16/1600) -> #DIV/0! | AG16: =SUM(320*AF16) -> #DIV/0! | AH16: =SUM(AC16-AG16) -> #DIV/0! | AI16: =AD16*AJ16 -> 0 | AJ16: =305/1185 -> 0.25738397 | AK16: =IF(Z16>0,AI16/Z16,0) -> 0
A17: =ELEC!C17 -> 44270 | B17: =B16 -> 9649 | C17: =B17-B16 -> 0 | D17: =D16 -> 333323 | E17: =SUM(D17-D16) -> 0 | F17: =IF(C17>0,E17/C17,0) -> 0 | H17: =H16 -> 9729 | I17: =IF(B17-H17<=0,"ok","oil change") -> ok | J17: =J16 -> 10698 | K17: =J17-J16 -> 0 | L17: =L16 -> 357691 | M17: =SUM(L17-L16) -> 0 | N17: =IF(K17>0,M17/K17,0) -> 0 | P17: =P16 -> 10873 | Q17: =IF(J17-P17<=0,"ok","oil change") -> ok | R17: =R16 -> 11943 | S17: =R17-R16 -> 0 | T17: =T16+U17 -> 411163 | U17: =V17*S17 -> 0 | V17: =IF(S17>0,U17/S17,0) -> 0 | X17: =X16 -> 11898 | Y17: =IF(R17-X17<=0,"ok","oil change") -> oil change | Z17: =C17+K17+S17 -> 0 | AA17: =U17+M17+E17 -> 0 | AB17: =V17+N17+F17 -> 0 | AC17: =IF(Z17>0,AA17/Z17,0) -> 0 | AD17: =ELEC!Q17 -> 0 | AE17: =SUM(AD17/Z17) -> #DIV/0! | AF17: =SUM(AE17/1600) -> #DIV/0! | AG17: =SUM(320*AF17) -> #DIV/0! | AH17: =SUM(AC17-AG17) -> #DIV/0! | AI17: =AD17*AJ17 -> 0 | AJ17: =305/1185 -> 0.25738397 | AK17: =IF(Z17>0,AI17/Z17,0) -> 0
A18: =ELEC!C18 -> 44271 | B18: =B17 -> 9649 | C18: =B18-B17 -> 0 | D18: =D17 -> 333323 | E18: =SUM(D18-D17) -> 0 | F18: =IF(C18>0,E18/C18,0) -> 0 | H18: =H17 -> 9729 | I18: =IF(B18-H18<=0,"ok","oil change") -> ok | J18: =J17 -> 10698 | K18: =J18-J17 -> 0 | L18: =L17 -> 357691 | M18: =SUM(L18-L17) -> 0 | N18: =IF(K18>0,M18/K18,0) -> 0 | P18: =P17 -> 10873 | Q18: =IF(J18-P14<=0,"ok","oil change") -> ok | R18: =R17 -> 11943 | S18: =R18-R17 -> 0 | T18: =T17+U18 -> 411163 | U18: =V18*S18 -> 0 | V18: =IF(S18>0,U18/S18,0) -> 0 | X18: =X17 -> 11898 | Y18: =IF(R18-X18<=0,"ok","oil change") -> oil change | Z18: =C18+K18+S18 -> 0 | AA18: =U18+M18+E18 -> 0 | AB18: =V18+N18+F18 -> 0 | AC18: =IF(Z18>0,AA18/Z18,0) -> 0 | AD18: =ELEC!Q18 -> 0 | AE18: =SUM(AD18/Z18) -> #DIV/0! | AF18: =SUM(AE18/1600) -> #DIV/0! | AG18: =SUM(320*AF18) -> #DIV/0! | AH18: =SUM(AC18-AG18) -> #DIV/0! | AI18: =AD18*AJ18 -> 0 | AJ18: =305/1185 -> 0.25738397 | AK18: =IF(Z18>0,AI18/Z18,0) -> 0
A19: =ELEC!C19 -> 44272 | B19: =B18 -> 9649 | C19: =B19-B18 -> 0 | D19: =D18 -> 333323 | E19: =SUM(D19-D18) -> 0 | F19: =IF(C19>0,E19/C19,0) -> 0 | H19: =H18 -> 9729 | I19: =IF(B19-H19<=0,"ok","oil change") -> ok | J19: =J18 -> 10698 | K19: =J19-J18 -> 0 | L19: =L18 -> 357691 | M19: =SUM(L19-L18) -> 0 | N19: =IF(K19>0,M19/K19,0) -> 0 | P19: =P18 -> 10873 | Q19: =IF(J19-P19<=0,"ok","oil change") -> ok | R19: =R18 -> 11943 | S19: =R19-R18 -> 0 | T19: =T18+U19 -> 411163 | U19: =V19*S19 -> 0 | V19: =IF(S19>0,U19/S19,0) -> 0 | X19: =X18 -> 11898 | Y19: =IF(R19-X19<=0,"ok","oil change") -> oil change | Z19: =C19+K19+S19 -> 0 | AA19: =U19+M19+E19 -> 0 | AB19: =V19+N19+F19 -> 0 | AC19: =IF(Z19>0,AA19/Z19,0) -> 0 | AD19: =ELEC!Q19 -> 0 | AE19: =SUM(AD19/Z19) -> #DIV/0! | AF19: =SUM(AE19/1600) -> #DIV/0! | AG19: =SUM(320*AF19) -> #DIV/0! | AH19: =SUM(AC19-AG19) -> #DIV/0! | AI19: =AD19*AJ19 -> 0 | AJ19: =305/1185 -> 0.25738397 | AK19: =IF(Z19>0,AI19/Z19,0) -> 0
A20: =ELEC!C20 -> 44273 | B20: =B19 -> 9649 | C20: =B20-B19 -> 0 | D20: =D19 -> 333323 | E20: =SUM(D20-D19) -> 0 | F20: =IF(C20>0,E20/C20,0) -> 0 | H20: =H19 -> 9729 | I20: =IF(B20-H20<=0,"ok","oil change") -> ok | J20: =J19 -> 10698 | K20: =J20-J19 -> 0 | L20: =L19 -> 357691 | M20: =SUM(L20-L19) -> 0 | N20: =IF(K20>0,M20/K20,0) -> 0 | P20: =P19 -> 10873 | Q20: =IF(J20-P20<=0,"ok","oil change") -> ok | R20: =R19 -> 11943 | S20: =R20-R19 -> 0 | T20: =T19+U20 -> 411163 | U20: =V20*S20 -> 0 | V20: =IF(S20>0,U20/S20,0) -> 0 | X20: =X19 -> 11898 | Y20: =IF(R20-X20<=0,"ok","oil change") -> oil change | Z20: =C20+K20+S20 -> 0 | AA20: =U20+M20+E20 -> 0 | AB20: =V20+N20+F20 -> 0 | AC20: =IF(Z20>0,AA20/Z20,0) -> 0 | AD20: =ELEC!Q20 -> 0 | AE20: =SUM(AD20/Z20) -> #DIV/0! | AF20: =SUM(AE20/1600) -> #DIV/0! | AG20: =SUM(320*AF20) -> #DIV/0! | AH20: =SUM(AC20-AG20) -> #DIV/0! | AI20: =AD20*AJ20 -> 0 | AJ20: =305/1185 -> 0.25738397 | AK20: =IF(Z20>0,AI20/Z20,0) -> 0
A21: =ELEC!C21 -> 44274 | B21: =B20 -> 9649 | C21: =B21-B20 -> 0 | D21: =D20 -> 333323 | E21: =SUM(D21-D20) -> 0 | F21: =IF(C21>0,E21/C21,0) -> 0 | H21: =H20 -> 9729 | I21: =IF(B21-H21<=0,"ok","oil change") -> ok | J21: =J20 -> 10698 | K21: =J21-J20 -> 0 | L21: =L20 -> 357691 | M21: =SUM(L21-L20) -> 0 | N21: =IF(K21>0,M21/K21,0) -> 0 | P21: =P20 -> 10873 | Q21: =IF(J21-P21<=0,"ok","oil change") -> ok | R21: =R20 -> 11943 | S21: =R21-R20 -> 0 | T21: =T20+U21 -> 411163 | U21: =V21*S21 -> 0 | V21: =IF(S21>0,U21/S21,0) -> 0 | X21: =X20 -> 11898 | Y21: =Y20 -> oil change | Z21: =C21+K21+S21 -> 0 | AA21: =U21+M21+E21 -> 0 | AB21: =V21+N21+F21 -> 0 | AC21: =IF(Z21>0,AA21/Z21,0) -> 0 | AD21: =ELEC!Q21 -> 0 | AE21: =SUM(AD21/Z21) -> #DIV/0! | AF21: =SUM(AE21/1600) -> #DIV/0! | AG21: =SUM(320*AF21) -> #DIV/0! | AH21: =SUM(AC21-AG21) -> #DIV/0! | AI21: =AD21*AJ21 -> 0 | AJ21: =305/1185 -> 0.25738397 | AK21: =IF(Z21>0,AI21/Z21,0) -> 0
A22: =ELEC!C22 -> 44275 | B22: =B21 -> 9649 | C22: =B22-B21 -> 0 | D22: =D21 -> 333323 | E22: =150*C22 -> 0 | F22: =IF(C22>0,E22/C22,0) -> 0 | H22: =H21 -> 9729 | I22: =IF(B22-H22<=0,"ok","oil change") -> ok | J22: =J21 -> 10698 | K22: =J22-J21 -> 0 | L22: =L21 -> 357691 | M22: =SUM(L22-L21) -> 0 | N22: =IF(K22>0,M22/K22,0) -> 0 | P22: =P21 -> 10873 | Q22: =IF(J22-P22<=0,"ok","oil change") -> ok | R22: =R21 -> 11943 | S22: =R22-R21 -> 0 | T22: =T21+U22 -> 411163 | U22: =V22*S22 -> 0 | V22: =IF(S22>0,U22/S22,0) -> 0 | X22: =X21 -> 11898 | Y22: =IF(R22-X22<=0,"ok","oil change") -> oil change | Z22: =C22+K22+S22 -> 0 | AA22: =U22+M22+E22 -> 0 | AB22: =V22+N22+F22 -> 0 | AC22: =IF(Z22>0,AA22/Z22,0) -> 0 | AD22: =ELEC!Q22 -> 0 | AE22: =SUM(AD22/Z22) -> #DIV/0! | AF22: =SUM(AE22/1600) -> #DIV/0! | AG22: =SUM(320*AF22) -> #DIV/0! | AH22: =SUM(AC22-AG22) -> #DIV/0! | AI22: =AD22*AJ22 -> 0 | AJ22: =305/1185 -> 0.25738397 | AK22: =IF(Z22>0,AI22/Z22,0) -> 0
A23: =ELEC!C23 -> 44276 | B23: =B22 -> 9649 | C23: =B23-B22 -> 0 | D23: =D22 -> 333323 | E23: =150*C23 -> 0 | F23: =IF(C23>0,E23/C23,0) -> 0 | H23: =H22 -> 9729 | I23: =IF(B23-H23<=0,"ok","oil change") -> ok | J23: =J22 -> 10698 | K23: =J23-J22 -> 0 | L23: =L22 -> 357691 | M23: =SUM(L23-L22) -> 0 | N23: =IF(K23>0,M23/K23,0) -> 0 | P23: =P22 -> 10873 | Q23: =IF(J23-P23<=0,"ok","oil change") -> ok | R23: =R22 -> 11943 | S23: =R23-R22 -> 0 | T23: =T22+U23 -> 411163 | U23: =V23*S23 -> 0 | V23: =IF(S23>0,U23/S23,0) -> 0 | X23: =X22 -> 11898 | Y23: =IF(R23-X23<=0,"ok","oil change") -> oil change | Z23: =C23+K23+S23 -> 0 | AA23: =U23+M23+E23 -> 0 | AB23: =V23+N23+F23 -> 0 | AC23: =IF(Z23>0,AA23/Z23,0) -> 0 | AD23: =ELEC!Q23 -> 0 | AE23: =SUM(AD23/Z23) -> #DIV/0! | AF23: =SUM(AE23/1600) -> #DIV/0! | AG23: =SUM(320*AF23) -> #DIV/0! | AH23: =SUM(AC23-AG23) -> #DIV/0! | AI23: =AD23*AJ23 -> 0 | AJ23: =305/1185 -> 0.25738397 | AK23: =IF(Z23>0,AI23/Z23,0) -> 0
A24: =ELEC!C24 -> 44277 | B24: =B23 -> 9649 | C24: =B24-B23 -> 0 | D24: =D23 -> 333323 | E24: =SUM(D24-D23) -> 0 | F24: =IF(C24>0,E24/C24,0) -> 0 | H24: =H23 -> 9729 | I24: =IF(B24-H24<=0,"ok","oil change") -> ok | J24: =J23 -> 10698 | K24: =J24-J23 -> 0 | L24: =L23 -> 357691 | M24: =SUM(L24-L23) -> 0 | N24: =IF(K24>0,M24/K24,0) -> 0 | P24: =P23 -> 10873 | Q24: =IF(J24-P24<=0,"ok","oil change") -> ok | R24: =R23 -> 11943 | S24: =R24-R23 -> 0 | T24: =T23+U24 -> 411163 | U24: =V24*S24 -> 0 | V24: =IF(S24>0,U24/S24,0) -> 0 | X24: =X23 -> 11898 | Y24: =IF(R24-X24<=0,"ok","oil change") -> oil change | Z24: =C24+K24+S24 -> 0 | AA24: =U24+M24+E24 -> 0 | AB24: =V24+N24+F24 -> 0 | AC24: =IF(Z24>0,AA24/Z24,0) -> 0 | AD24: =ELEC!Q24 -> 0 | AE24: =SUM(AD24/Z24) -> #DIV/0! | AF24: =SUM(AE24/1600) -> #DIV/0! | AG24: =SUM(320*AF24) -> #DIV/0! | AH24: =SUM(AC24-AG24) -> #DIV/0! | AI24: =AD24*AJ24 -> 0 | AJ24: =305/1185 -> 0.25738397 | AK24: =IF(Z24>0,AI24/Z24,0) -> 0
A25: =ELEC!C25 -> 44278 | B25: =B24 -> 9649 | C25: =B25-B24 -> 0 | D25: =D24 -> 333323 | E25: =SUM(D25-D24) -> 0 | F25: =IF(C25>0,E25/C25,0) -> 0 | H25: =H24 -> 9729 | I25: =IF(B25-H25<=0,"ok","oil change") -> ok | J25: =J24 -> 10698 | K25: =J25-J24 -> 0 | L25: =L24 -> 357691 | M25: =SUM(L25-L24) -> 0 | N25: =IF(K25>0,M25/K25,0) -> 0 | P25: =P24 -> 10873 | Q25: =IF(J25-P25<=0,"ok","oil change") -> ok | R25: =R24 -> 11943 | S25: =R25-R24 -> 0 | T25: =T24+U25 -> 411163 | U25: =V25*S25 -> 0 | V25: =IF(S25>0,U25/S25,0) -> 0 | X25: =X24 -> 11898 | Y25: =IF(R25-X25<=0,"ok","oil change") -> oil change | Z25: =C25+K25+S25 -> 0 | AA25: =U25+M25+E25 -> 0 | AB25: =V25+N25+F25 -> 0 | AC25: =IF(Z25>0,AA25/Z25,0) -> 0 | AD25: =ELEC!Q25 -> 0 | AE25: =SUM(AD25/Z25) -> #DIV/0! | AF25: =SUM(AE25/1600) -> #DIV/0! | AG25: =SUM(320*AF25) -> #DIV/0! | AH25: =SUM(AC25-AG25) -> #DIV/0! | AI25: =AD25*AJ25 -> 0 | AJ25: =305/1185 -> 0.25738397 | AK25: =IF(Z25>0,AI25/Z25,0) -> 0
A26: =ELEC!C26 -> 44279 | B26: =B25 -> 9649 | C26: =B26-B25 -> 0 | D26: =D25 -> 333323 | E26: =SUM(D26-D25) -> 0 | F26: =IF(C26>0,E26/C26,0) -> 0 | H26: =H25 -> 9729 | I26: =IF(B26-H26<=0,"ok","oil change") -> ok | J26: =J25 -> 10698 | K26: =J26-J25 -> 0 | L26: =L25 -> 357691 | M26: =SUM(L26-L25) -> 0 | N26: =IF(K26>0,M26/K26,0) -> 0 | P26: =P25 -> 10873 | Q26: =IF(J26-P26<=0,"ok","oil change") -> ok | R26: =R25 -> 11943 | S26: =R26-R25 -> 0 | T26: =T25+U26 -> 411163 | U26: =V26*S26 -> 0 | V26: =IF(S26>0,U26/S26,0) -> 0 | X26: =X25 -> 11898 | Y26: =IF(R26-X26<=0,"ok","oil change") -> oil change | Z26: =C26+K26+S26 -> 0 | AA26: =U26+M26+E26 -> 0 | AB26: =V26+N26+F26 -> 0 | AC26: =IF(Z26>0,AA26/Z26,0) -> 0 | AD26: =ELEC!Q26 -> 0 | AE26: =SUM(AD26/Z26) -> #DIV/0! | AF26: =SUM(AE26/1600) -> #DIV/0! | AG26: =SUM(320*AF26) -> #DIV/0! | AH26: =SUM(AC26-AG26) -> #DIV/0! | AI26: =AD26*AJ26 -> 0 | AJ26: =305/1185 -> 0.25738397 | AK26: =IF(Z26>0,AI26/Z26,0) -> 0
A27: =ELEC!C27 -> 44280 | B27: =B26 -> 9649 | C27: =B27-B26 -> 0 | D27: =D26 -> 333323 | E27: =SUM(D27-D26) -> 0 | F27: =IF(C27>0,E27/C27,0) -> 0 | H27: =H26 -> 9729 | I27: =IF(B27-H27<=0,"ok","oil change") -> ok | J27: =J26 -> 10698 | K27: =J27-J26 -> 0 | L27: =L26 -> 357691 | M27: =SUM(L27-L26) -> 0 | N27: =IF(K27>0,M27/K27,0) -> 0 | P27: =P26 -> 10873 | Q27: =IF(J27-P27<=0,"ok","oil change") -> ok | R27: =R26 -> 11943 | S27: =R27-R26 -> 0 | T27: =T26+U27 -> 411163 | U27: =V27*S27 -> 0 | V27: =IF(S27>0,U27/S27,0) -> 0 | X27: =X26 -> 11898 | Y27: =IF(R27-X27<=0,"ok","oil change") -> oil change | Z27: =C27+K27+S27 -> 0 | AA27: =U27+M27+E27 -> 0 | AB27: =V27+N27+F27 -> 0 | AC27: =IF(Z27>0,AA27/Z27,0) -> 0 | AD27: =ELEC!Q27 -> 0 | AE27: =SUM(AD27/Z27) -> #DIV/0! | AF27: =SUM(AE27/1600) -> #DIV/0! | AG27: =SUM(320*AF27) -> #DIV/0! | AH27: =SUM(AC27-AG27) -> #DIV/0! | AI27: =AD27*AJ27 -> 0 | AJ27: =305/1185 -> 0.25738397 | AK27: =IF(Z27>0,AI27/Z27,0) -> 0
A28: =ELEC!C28 -> 44281 | B28: =B27 -> 9649 | C28: =B28-B27 -> 0 | D28: =D27 -> 333323 | E28: =SUM(D28-D27) -> 0 | F28: =IF(C28>0,E28/C28,0) -> 0 | H28: =H27 -> 9729 | I28: =IF(B28-H28<=0,"ok","oil change") -> ok | J28: =J27 -> 10698 | K28: =J28-J27 -> 0 | L28: =L27 -> 357691 | M28: =SUM(L28-L27) -> 0 | N28: =IF(K28>0,M28/K28,0) -> 0 | P28: =P27 -> 10873 | Q28: =IF(J28-P28<=0,"ok","oil change") -> ok | R28: =R27 -> 11943 | S28: =R28-R27 -> 0 | T28: =T27+U28 -> 411163 | U28: =V28*S28 -> 0 | V28: =IF(S28>0,U28/S28,0) -> 0 | X28: =X27 -> 11898 | Y28: =IF(R28-X28<=0,"ok","oil change") -> oil change | Z28: =C28+K28+S28 -> 0 | AA28: =U28+M28+E28 -> 0 | AB28: =V28+N28+F28 -> 0 | AC28: =IF(Z28>0,AA28/Z28,0) -> 0 | AD28: =ELEC!Q28 -> 0 | AE28: =SUM(AD28/Z28) -> #DIV/0! | AF28: =SUM(AE28/1600) -> #DIV/0! | AG28: =SUM(320*AF28) -> #DIV/0! | AH28: =SUM(AC28-AG28) -> #DIV/0! | AI28: =AD28*AJ28 -> 0 | AJ28: =305/1185 -> 0.25738397 | AK28: =IF(Z28>0,AI28/Z28,0) -> 0
A29: =ELEC!C29 -> 44282 | B29: =B28 -> 9649 | C29: =B29-B28 -> 0 | D29: =D28 -> 333323 | E29: =SUM(D29-D28) -> 0 | F29: =IF(C29>0,E29/C29,0) -> 0 | H29: =H28 -> 9729 | I29: =IF(B29-H29<=0,"ok","oil change") -> ok | J29: =J28 -> 10698 | K29: =J29-J28 -> 0 | L29: =L28 -> 357691 | M29: =SUM(L29-L28) -> 0 | N29: =IF(K29>0,M29/K29,0) -> 0 | P29: =P28 -> 10873 | Q29: =IF(J29-P29<=0,"ok","oil change") -> ok | R29: =R28 -> 11943 | S29: =R29-R28 -> 0 | T29: =T28+U29 -> 411163 | U29: =V29*S29 -> 0 | V29: =IF(S29>0,U29/S29,0) -> 0 | X29: =X28 -> 11898 | Y29: =IF(R29-X29<=0,"ok","oil change") -> oil change | Z29: =C29+K29+S29 -> 0 | AA29: =U29+M29+E29 -> 0 | AB29: =V29+N29+F29 -> 0 | AC29: =IF(Z29>0,AA29/Z29,0) -> 0 | AD29: =ELEC!Q29 -> 0 | AE29: =SUM(AD29/Z29) -> #DIV/0! | AF29: =SUM(AE29/1600) -> #DIV/0! | AG29: =SUM(320*AF29) -> #DIV/0! | AH29: =SUM(AC29-AG29) -> #DIV/0! | AI29: =AD29*AJ29 -> 0 | AJ29: =305/1185 -> 0.25738397 | AK29: =IF(Z29>0,AI29/Z29,0) -> 0
A30: =ELEC!C30 -> 44283 | B30: =B29 -> 9649 | C30: =B30-B29 -> 0 | D30: =D29 -> 333323 | E30: =SUM(D30-D29) -> 0 | F30: =IF(C30>0,E30/C30,0) -> 0 | H30: =H29 -> 9729 | I30: =IF(B30-H30<=0,"ok","oil change") -> ok | J30: =J29 -> 10698 | K30: =J30-J29 -> 0 | L30: =L29 -> 357691 | M30: =SUM(L30-L29) -> 0 | N30: =IF(K30>0,M30/K30,0) -> 0 | P30: =P29 -> 10873 | Q30: =IF(J30-P30<=0,"ok","oil change") -> ok | R30: =R29 -> 11943 | S30: =R30-R29 -> 0 | T30: =T29+U30 -> 411163 | U30: =V30*S30 -> 0 | V30: =IF(S30>0,U30/S30,0) -> 0 | X30: =X29 -> 11898 | Y30: =IF(R30-X30<=0,"ok","oil change") -> oil change | Z30: =C30+K30+S30 -> 0 | AA30: =U30+M30+E30 -> 0 | AB30: =V30+N30+F30 -> 0 | AC30: =IF(Z30>0,AA30/Z30,0) -> 0 | AD30: =ELEC!Q30 -> 0 | AE30: =SUM(AD30/Z30) -> #DIV/0! | AF30: =SUM(AE30/1600) -> #DIV/0! | AG30: =SUM(320*AF30) -> #DIV/0! | AH30: =SUM(AC30-AG30) -> #DIV/0! | AI30: =AD30*AJ30 -> 0 | AJ30: =305/1185 -> 0.25738397 | AK30: =IF(Z30>0,AI30/Z30,0) -> 0
A31: =ELEC!C31 -> 44284 | B31: =B30 -> 9649 | C31: =B31-B30 -> 0 | D31: =D30 -> 333323 | E31: =SUM(D31-D30) -> 0 | F31: =IF(C31>0,E31/C31,0) -> 0 | H31: =H30 -> 9729 | I31: =IF(B31-H31<=0,"ok","oil change") -> ok | J31: =J30 -> 10698 | K31: =J31-J30 -> 0 | L31: =L30 -> 357691 | M31: =SUM(L31-L30) -> 0 | N31: =IF(K31>0,M31/K31,0) -> 0 | P31: =P30 -> 10873 | Q31: =IF(J31-P31<=0,"ok","oil change") -> ok | R31: =R30 -> 11943 | S31: =R31-R30 -> 0 | T31: =T30+U31 -> 411163 | U31: =V31*S31 -> 0 | V31: =IF(S31>0,U31/S31,0) -> 0 | X31: =X30 -> 11898 | Y31: =IF(R31-X31<=0,"ok","oil change") -> oil change | Z31: =C31+K31+S31 -> 0 | AA31: =U31+M31+E31 -> 0 | AB31: =V31+N31+F31 -> 0 | AC31: =IF(Z31>0,AA31/Z31,0) -> 0 | AD31: =ELEC!Q31 -> 0 | AE31: =SUM(AD31/Z31) -> #DIV/0! | AF31: =SUM(AE31/1600) -> #DIV/0! | AG31: =SUM(320*AF31) -> #DIV/0! | AH31: =SUM(AC31-AG31) -> #DIV/0! | AI31: =AD31*AJ31 -> 0 | AJ31: =305/1185 -> 0.25738397 | AK31: =IF(Z31>0,AI31/Z31,0) -> 0
