Workbook

Sheet Total
A1: Site Name | B1: Day | C1: Month | D1: Year | E1: Total Electricity Kwh | F1: Electricity Tariff ($/Kwh) | G1: Total Fuel Oil (Liters) | H1: Fuel Oil $/Liter | I1: LPG (Kg) | J1: LPG $/Kg | K1: Water Utility Supply (m3) m3 | L1: Water Utility Supply (m3) $/m3 | M1: Irrigation Water (m3) m3 | N1: Irrigation water $/m3 | O1: Room Nights
A2: Beirut | B2: 1 | C2: 4 | D2: 2021 | E2: =ELEC!N3 -> 10627 | F2: =SUM('EDl log'!T4) -> 0.15397996 | G2: =-tanks!AW6 -> 359 | H2: =SUM(tanks!AV6) -> 0.96 | I2: =('B5'!AU5)*0.51 -> 0 | J2: ='B5'!AX5/0.51 -> 1.5686275 | K2: =WATER!I6 -> 0 | L2: =SUM(WATER!J6) -> 0 | M2: =WATER!Q6 -> 0 | N2: 0.6 | O2: =ELEC!B3 -> 0
A3: Beirut | B3: =B2+1 -> 2 | C3: 4 | D3: 2021 | E3: =ELEC!N4 -> 8566 | F3: =SUM('EDl log'!T5) -> 0.36446978 | G3: =-tanks!AW7 -> 298 | H3: =SUM(tanks!AV7) -> 0.96 | I3: =('B5'!AU6)*0.51 -> 0 | J3: ='B5'!AX6/0.51 -> 1.5686275 | K3: =WATER!I7 -> 0 | L3: =SUM(WATER!J7) -> 0 | M3: =WATER!Q7 -> 0 | N3: 0.6 | O3: =ELEC!B4 -> 0
A4: Beirut | B4: =B3+1 -> 3 | C4: 4 | D4: 2021 | E4: =ELEC!N5 -> 9686 | F4: =SUM('EDl log'!T6) -> 0.3283817 | G4: =-tanks!AW8 -> 287 | H4: =SUM(tanks!AV8) -> 0.96 | I4: =('B5'!AU7)*0.51 -> 0 | J4: ='B5'!AX7/0.51 -> 1.5686275 | K4: =WATER!I8 -> 0 | L4: =SUM(WATER!J8) -> 0 | M4: =WATER!Q8 -> 0 | N4: 0.6 | O4: =ELEC!B5 -> 0
A5: Beirut | B5: =B4+1 -> 4 | C5: 4 | D5: 2021 | E5: =ELEC!N6 -> 9198 | F5: =SUM('EDl log'!T7) -> 0.34102969 | G5: =-tanks!AW9 -> 290 | H5: =SUM(tanks!AV9) -> 0.96 | I5: =('B5'!AU8)*0.51 -> 0 | J5: ='B5'!AX8/0.51 -> 1.5686275 | K5: =WATER!I9 -> 54 | L5: =SUM(WATER!J9) -> 4.6296296 | M5: =WATER!Q9 -> 0 | N5: 0.6 | O5: =ELEC!B6 -> 0
A6: Beirut | B6: =B5+1 -> 5 | C6: 4 | D6: 2021 | E6: =ELEC!N7 -> 9569 | F6: =SUM('EDl log'!T8) -> 0.26208634 | G6: =-tanks!AW10 -> 404 | H6: =SUM(tanks!AV10) -> 0.96 | I6: =('B5'!AU9)*0.51 -> 0 | J6: ='B5'!AX9/0.51 -> 1.5686275 | K6: =WATER!I10 -> 100 | L6: =SUM(WATER!J10) -> 2.5 | M6: =WATER!Q10 -> 0 | N6: 0.6 | O6: =ELEC!B7 -> 0
A7: Beirut | B7: =B6+1 -> 6 | C7: 4 | D7: 2021 | E7: =ELEC!N8 -> 10832 | F7: =SUM('EDl log'!T9) -> 0.29715327 | G7: =-tanks!AW11 -> 308 | H7: =SUM(tanks!AV11) -> 0.96 | I7: =('B5'!AU10)*0.51 -> 0 | J7: ='B5'!AX10/0.51 -> 1.5686275 | K7: =WATER!I11 -> 0 | L7: =SUM(WATER!J11) -> 0 | M7: =WATER!Q11 -> 0 | N7: 0.6 | O7: =ELEC!B8 -> 0
A8: Beirut | B8: =B7+1 -> 7 | C8: 4 | D8: 2021 | E8: =ELEC!N9 -> 8792 | F8: =SUM('EDl log'!T10) -> -0.032783652 | G8: =-tanks!AW12 -> 287 | H8: =SUM(tanks!AV12) -> 0.96 | I8: =('B5'!AU11)*0.51 -> 0 | J8: ='B5'!AX11/0.51 -> 1.5686275 | K8: =WATER!I12 -> 28 | L8: =SUM(WATER!J12) -> 8.9285714 | M8: =WATER!Q12 -> 0 | N8: 0.6 | O8: =ELEC!B9 -> 0
A9: Beirut | B9: =B8+1 -> 8 | C9: 4 | D9: 2021 | E9: =ELEC!N10 -> 8207 | F9: =SUM('EDl log'!T11) -> 0.2129289 | G9: =-tanks!AW13 -> 416 | H9: =SUM(tanks!AV13) -> 0.96 | I9: =('B5'!AU12)*0.51 -> 0 | J9: ='B5'!AX12/0.51 -> 1.5686275 | K9: =WATER!I13 -> 0 | L9: =SUM(WATER!J13) -> 0 | M9: =WATER!Q13 -> 0 | N9: 0.6 | O9: =ELEC!B10 -> 0
A10: Beirut | B10: =B9+1 -> 9 | C10: 4 | D10: 2021 | E10: =ELEC!N11 -> 7584 | F10: =SUM('EDl log'!T12) -> 0.19166069 | G10: =-tanks!AW14 -> 326 | H10: =SUM(tanks!AV14) -> 0.96 | I10: =('B5'!AU13)*0.51 -> 0 | J10: ='B5'!AX13/0.51 -> 1.5686275 | K10: =WATER!I14 -> 211 | L10: =SUM(WATER!J14) -> 1.1848341 | M10: =WATER!Q14 -> 0 | N10: 0.6 | O10: =ELEC!B11 -> 0
A11: Beirut | B11: =B10+1 -> 10 | C11: 4 | D11: 2021 | E11: =ELEC!N12 -> 6883 | F11: =SUM('EDl log'!T13) -> 0.23950285 | G11: =-tanks!AW15 -> 409 | H11: =SUM(tanks!AV15) -> 0.96 | I11: =('B5'!AU14)*0.51 -> 0 | J11: ='B5'!AX14/0.51 -> 1.5686275 | K11: =WATER!I15 -> 0 | L11: =SUM(WATER!J15) -> 0 | M11: =WATER!Q15 -> 0 | N11: 0.6 | O11: =ELEC!B12 -> 0
A12: Beirut | B12: =B11+1 -> 11 | C12: 4 | D12: 2021 | E12: =ELEC!N13 -> 6760.8 | F12: =SUM('EDl log'!T14) -> 0.17657196 | G12: =-tanks!AW16 -> 368 | H12: =SUM(tanks!AV16) -> 0.96 | I12: =('B5'!AU15)*0.51 -> 0 | J12: ='B5'!AX15/0.51 -> 1.5686275 | K12: =WATER!I16 -> 5 | L12: =SUM(WATER!J16) -> 50 | M12: =WATER!Q16 -> 0 | N12: 0.6 | O12: =ELEC!B13 -> 0
A13: Beirut | B13: =B12+1 -> 12 | C13: 4 | D13: 2021 | E13: =ELEC!N14 -> 7293.2 | F13: =SUM('EDl log'!T15) -> 0.26227485 | G13: =-tanks!AW17 -> 367 | H13: =SUM(tanks!AV17) -> 0.96 | I13: =('B5'!AU16)*0.51 -> 0 | J13: ='B5'!AX16/0.51 -> 1.5686275 | K13: =WATER!I17 -> 0 | L13: =SUM(WATER!J17) -> 0 | M13: =WATER!Q17 -> 0 | N13: 0.6 | O13: =ELEC!B14 -> 0
A14: Beirut | B14: =B13+1 -> 13 | C14: 4 | D14: 2021 | E14: =ELEC!N15 -> 6843 | F14: =SUM('EDl log'!T16) -> 0.24010536 | G14: =-tanks!AW18 -> 113 | H14: =SUM(tanks!AV18) -> 0.96 | I14: =('B5'!AU17)*0.51 -> 0 | J14: ='B5'!AX17/0.51 -> 1.5686275 | K14: =WATER!I18 -> 0 | L14: =SUM(WATER!J18) -> 0 | M14: =WATER!Q18 -> 0 | N14: 0.6 | O14: =ELEC!B15 -> 0
... A31: Beirut | B31: =B30+1 -> 30 | C31: 4 | D31: 2021 | E31: =ELEC!N32 -> 0 | F31: =SUM('EDl log'!T33) -> 0 | G31: =-tanks!AW35 -> 0 | H31: =SUM(tanks!AV35) -> 0.93 | I31: =('B5'!AU34)*0.51 -> 0 | J31: ='B5'!AX34/0.51 -> 1.5686275 | K31: =WATER!I35 -> 0 | L31: =SUM(WATER!J35) -> 0 | M31: =WATER!Q35 -> 0 | N31: 0.6 | O31: =ELEC!B32 -> 0

Sheet Submetering
A1: Site Name | B1: Day | C1: Month | D1: Year | E1: ATS1 Kwh | F1: ATS2 Kwh | G1: ATS3 Kwh | H1: ATS4 Kwh | I1: ATS5 Kwh | J1: Guest (m3) | K1: Kitchen & Laundry (m3) | L1: Room Nights
A2: Beirut | B2: 1 | C2: 4 | D2: 2021 | E2: =ELEC!M3 -> 4066 | F2: =ELEC!K3 -> 1692 | G2: =ELEC!I3 -> 1006 | H2: =ELEC!E3 -> 3148 | I2: =ELEC!G3 -> 715 | J2: =WATER!Y6 -> 0 | K2: =WATER!AJ6 -> 0 | L2: =ELEC!B3 -> 0
A3: Beirut | B3: =B2+1 -> 2 | C3: 4 | D3: 2021 | E3: =ELEC!M4 -> 2420 | F3: =ELEC!K4 -> 1836 | G3: =ELEC!I4 -> 838 | H3: =ELEC!E4 -> 2912 | I3: =ELEC!G4 -> 560 | J3: =WATER!Y7 -> 64 | K3: =WATER!AJ7 -> 20 | L3: =ELEC!B4 -> 0
A4: Beirut | B4: =B3+1 -> 3 | C4: 4 | D4: 2021 | E4: =ELEC!M5 -> 2272 | F4: =ELEC!K5 -> 2844 | G4: =ELEC!I5 -> 838 | H4: =ELEC!E5 -> 3110 | I4: =ELEC!G5 -> 622 | J4: =WATER!Y8 -> 0 | K4: =WATER!AJ8 -> 0 | L4: =ELEC!B5 -> 0
A5: Beirut | B5: =B4+1 -> 4 | C5: 4 | D5: 2021 | E5: =ELEC!M6 -> 2340 | F5: =ELEC!K6 -> 1680 | G5: =ELEC!I6 -> 1054 | H5: =ELEC!E6 -> 3590 | I5: =ELEC!G6 -> 534 | J5: =WATER!Y9 -> 0 | K5: =WATER!AJ9 -> 0 | L5: =ELEC!B6 -> 0
A6: Beirut | B6: =B5+1 -> 5 | C6: 4 | D6: 2021 | E6: =ELEC!M7 -> 2120 | F6: =ELEC!K7 -> 2528 | G6: =ELEC!I7 -> 944 | H6: =ELEC!E7 -> 3232 | I6: =ELEC!G7 -> 745 | J6: =WATER!Y10 -> 12 | K6: =WATER!AJ10 -> 4 | L6: =ELEC!B7 -> 0
A7: Beirut | B7: =B6+1 -> 6 | C7: 4 | D7: 2021 | E7: =ELEC!M8 -> 2152 | F7: =ELEC!K8 -> 2220 | G7: =ELEC!I8 -> 938 | H7: =ELEC!E8 -> 4856 | I7: =ELEC!G8 -> 666 | J7: =WATER!Y11 -> 0 | K7: =WATER!AJ11 -> 0 | L7: =ELEC!B8 -> 0
A8: Beirut | B8: =B7+1 -> 7 | C8: 4 | D8: 2021 | E8: =ELEC!M9 -> 1656 | F8: =ELEC!K9 -> 1678 | G8: =ELEC!I9 -> 898 | H8: =ELEC!E9 -> 3864 | I8: =ELEC!G9 -> 696 | J8: =WATER!Y12 -> 0 | K8: =WATER!AJ12 -> 2 | L8: =ELEC!B9 -> 0
A9: Beirut | B9: =B8+1 -> 8 | C9: 4 | D9: 2021 | E9: =ELEC!M10 -> 1662 | F9: =ELEC!K10 -> 2522 | G9: =ELEC!I10 -> 870 | H9: =ELEC!E10 -> 2382 | I9: =ELEC!G10 -> 771 | J9: =WATER!Y13 -> 102 | K9: =WATER!AJ13 -> 37 | L9: =ELEC!B10 -> 0
A10: Beirut | B10: =B9+1 -> 9 | C10: 4 | D10: 2021 | E10: =ELEC!M11 -> 1656 | F10: =ELEC!K11 -> 1358 | G10: =ELEC!I11 -> 918 | H10: =ELEC!E11 -> 2910 | I10: =ELEC!G11 -> 742 | J10: =WATER!Y14 -> 0 | K10: =WATER!AJ14 -> 0 | L10: =ELEC!B11 -> 0
A11: Beirut | B11: =B10+1 -> 10 | C11: 4 | D11: 2021 | E11: =ELEC!M12 -> 1918 | F11: =ELEC!K12 -> 1238 | G11: =ELEC!I12 -> 936 | H11: =ELEC!E12 -> 2068 | I11: =ELEC!G12 -> 723 | J11: =WATER!Y15 -> 0 | K11: =WATER!AJ15 -> 0 | L11: =ELEC!B12 -> 0
A12: Beirut | B12: =B11+1 -> 11 | C12: 4 | D12: 2021 | E12: =ELEC!M13 -> 1688 | F12: =ELEC!K13 -> 1249 | G12: =ELEC!I13 -> 848 | H12: =ELEC!E13 -> 2320 | I12: =ELEC!G13 -> 655.8 | J12: =WATER!Y16 -> 0 | K12: =WATER!AJ16 -> 0 | L12: =ELEC!B13 -> 0
A13: Beirut | B13: =B12+1 -> 12 | C13: 4 | D13: 2021 | E13: =ELEC!M14 -> 1608 | F13: =ELEC!K14 -> 1323 | G13: =ELEC!I14 -> 802 | H13: =ELEC!E14 -> 2920 | I13: =ELEC!G14 -> 640.2 | J13: =WATER!Y17 -> 0 | K13: =WATER!AJ17 -> 0 | L13: =ELEC!B14 -> 0
A14: Beirut | B14: =B13+1 -> 13 | C14: 4 | D14: 2021 | E14: =ELEC!M15 -> 1576 | F14: =ELEC!K15 -> 1280 | G14: =ELEC!I15 -> 794 | H14: =ELEC!E15 -> 2584 | I14: =ELEC!G15 -> 609 | J14: =WATER!Y18 -> 0 | K14: =WATER!AJ18 -> 0 | L14: =ELEC!B15 -> 0
... A31: Beirut | B31: =B30+1 -> 30 | C31: 4 | D31: 2021 | E31: =ELEC!M32 -> 0 | F31: =ELEC!K32 -> 0 | G31: =ELEC!I32 -> 0 | H31: =ELEC!E32 -> 0 | I31: =ELEC!G32 -> 0 | J31: =WATER!Y35 -> 0 | K31: =WATER!AJ35 -> 0 | L31: =ELEC!B32 -> 0
D46: .

Sheet ELEC
A1: OOC | B1: Room OCC | D1: MDB3 | E1: MDB3/day | F1: EMDB2 | G1: EMDB2/day | H1: EMDB1 | I1: EMDB1/day | J1: MDB2 | K1: mdb2/day | L1: MDB1 | M1: MDB1/Day | N1: Total KWH | O1: KWH/Rooc | P1: Gen MHW | Q1: Gen/Day KWH | R1: EDL KWH | S1: CH1 RH | T1: RH | U1: C1h1 power | V1: CH1 Con KWH | W1: CH2 RH | X1: RH | Y1: Ch2 power | Z1: CH2 Con KWH | AA1: CH3 RH | AB1: RH | AC1: Ch3 power | AD1: CH3 Con KWH | AE1: RH total | AF1: KWH total | AG1: AVG chiller KW/Hr
A2: =[1]ELEC!A30 -> 0 | B2: =[2]ELEC!B33 -> 0 | C2: 44286 | D2: =[3]ELEC!D33 -> 32737038 | E2: =[3]ELEC!E33 -> 3610 | F2: =[3]ELEC!F33 -> 3990693 | G2: =[3]ELEC!G33 -> 632 | H2: =[3]ELEC!H33 -> 17830854 | I2: =[3]ELEC!I33 -> 974 | J2: =[3]ELEC!J33 -> 28959514 | K2: =[3]ELEC!K33 -> 1686 | ... AL2: =[3]ELEC!AL33 -> 0 | AM2: =[1]ELEC!AM30 -> 0 | AN2: =[1]ELEC!AN30 -> 0 | AO2: =[1]ELEC!AO30 -> 0 | AP2: =[1]ELEC!AP30 -> 0 | AQ2: =[1]ELEC!AQ30 -> 0 | AR2: =[1]ELEC!AR30 -> 0 | AS2: =[1]ELEC!AS30 -> 0 | AT2: =[1]ELEC!AT30 -> 0 | ... CZ2: =[1]ELEC!CZ30 -> 0 | DA2: =[2]ELEC!DA33 -> 0 | DB2: =[2]ELEC!DB33 -> 0 | DC2: =[2]ELEC!DC33 -> 0 | DD2: =[2]ELEC!DD33 -> 0
A3: ='General information '!F6 -> 0 | B3: =SUM(230*A3) -> 0 | C3: 44287 | D3: 32740186 | E3: =D3-D2 -> 3148 | F3: 3991408 | G3: =F3-F2 -> 715 | H3: 17831860 | I3: =H3-H2 -> 1006 | J3: 28961206 | K3: =J3-J2 -> 1692 | L3: 24125630 | M3: =L3-L2 -> 4066 | N3: =M3+K3+I3+G3+E3 -> 10627 | O3: =IF(B3>0,N3/B3,0) -> 0 | P3: 16844.05 | Q3: =(P3-P2)*1000 -> 9208 | R3: =+N3-Q3 -> 1419 | S3: 10175 | T3: =S3-S2 -> 8 | U3: 429166 | V3: =U3-U2 -> 1217 | W3: =W2 -> 32247 | X3: =W3-W2 -> 0 | Y3: =Y2 -> 708695 | Z3: =Y3-Y2 -> 0 | AA3: =AA2 -> 35814 | AB3: =AA3-AA2 -> 0 | AC3: =AC2 -> 936218 | AD3: =AC3-AC2 -> 0 | AE3: =AB3+X3+T3 -> 8 | AF3: =V3+Z3+AD3 -> 1217 | AG3: =IF(AE3>0,AF3/AE3,0) -> 152.125
A4: ='General information '!F7 -> 0 | B4: =SUM(230*A4) -> 0 | C4: 44288 | D4: 32743098 | E4: =D4-D3 -> 2912 | F4: 3991968 | G4: =F4-F3 -> 560 | H4: 17832698 | I4: =H4-H3 -> 838 | J4: 28963042 | K4: =J4-J3 -> 1836 | L4: 24128050 | M4: =L4-L3 -> 2420 | N4: =M4+K4+I4+G4+E4 -> 8566 | O4: =IF(B4>0,N4/B4,0) -> 0 | P4: 16851.772 | Q4: =(P4-P3)*1000 -> 7722 | R4: =N4-Q4 -> 844 | S4: =S3 -> 10175 | T4: =S4-S3 -> 0 | U4: =U3 -> 429166 | V4: =U4-U3 -> 0 | W4: 32249 | X4: =W4-W3 -> 2 | Y4: 709120 | Z4: =Y4-Y3 -> 425 | AA4: 35815 | AB4: =AA4-AA3 -> 1 | AC4: 936339 | AD4: =AC4-AC3 -> 121 | AE4: =AB4+X4+T4 -> 3 | AF4: =V4+Z4+AD4 -> 546 | AG4: =IF(AE4>0,AF4/AE4,0) -> 182
A5: ='General information '!F8 -> 0 | B5: =SUM(230*A5) -> 0 | C5: 44289 | D5: 32746208 | E5: =D5-D4 -> 3110 | F5: 3992590 | G5: =F5-F4 -> 622 | H5: 17833536 | I5: =H5-H4 -> 838 | J5: 28965886 | K5: =J5-J4 -> 2844 | L5: 24130322 | M5: =L5-L4 -> 2272 | N5: =M5+K5+I5+G5+E5 -> 9686 | O5: =IF(B5>0,N5/B5,0) -> 0 | P5: 16860.034 | Q5: =(P5-P4)*1000 -> 8262 | R5: =N5-Q5 -> 1424 | S5: =S4 -> 10175 | T5: =S5-S4 -> 0 | U5: =U4 -> 429166 | V5: =U5-U4 -> 0 | W5: 32257 | X5: =W5-W4 -> 8 | Y5: 710354 | Z5: =Y5-Y4 -> 1234 | AA5: =AA4 -> 35815 | AB5: =AA5-AA4 -> 0 | AC5: =AC4 -> 936339 | AD5: =AC5-AC4 -> 0 | AE5: =AB5+X5+T5 -> 8 | AF5: =V5+Z5+AD5 -> 1234 | AG5: =IF(AE5>0,AF5/AE5,0) -> 154.25 | AI5: =R5-'EDl log'!B3 -> -955232
A6: ='General information '!F9 -> 0 | B6: =SUM(230*A6) -> 0 | C6: 44290 | D6: 32749798 | E6: =D6-D5 -> 3590 | F6: 3993124 | G6: =F6-F5 -> 534 | H6: 17834590 | I6: =H6-H5 -> 1054 | J6: 28967566 | K6: =J6-J5 -> 1680 | L6: 24132662 | M6: =L6-L5 -> 2340 | N6: =M6+K6+I6+G6+E6 -> 9198 | O6: =IF(B6>0,N6/B6,0) -> 0 | P6: 16867.975 | Q6: =(P6-P5)*1000 -> 7941 | R6: =N6-Q6 -> 1257 | S6: =S5 -> 10175 | T6: =S6-S5 -> 0 | U6: =U5 -> 429166 | V6: =U6-U5 -> 0 | W6: 32258 | X6: =W6-W5 -> 1 | Y6: 710563 | Z6: =Y6-Y5 -> 209 | AA6: 35819 | AB6: =AA6-AA5 -> 4 | AC6: 936894 | AD6: =AC6-AC5 -> 555 | AE6: =AB6+X6+T6 -> 5 | AF6: =V6+Z6+AD6 -> 764 | AG6: =IF(AE6>0,AF6/AE6,0) -> 152.8 | AI6: =R6-'EDl log'!B4 -> -956254
A7: ='General information '!F10 -> 0 | B7: =SUM(230*A7) -> 0 | C7: 44291 | D7: 32753030 | E7: =D7-D6 -> 3232 | F7: 3993869 | G7: =F7-F6 -> 745 | H7: 17835534 | I7: =H7-H6 -> 944 | J7: 28970094 | K7: =J7-J6 -> 2528 | L7: 24134782 | M7: =L7-L6 -> 2120 | N7: =M7+K7+I7+G7+E7 -> 9569 | O7: =IF(B7>0,N7/B7,0) -> 0 | P7: 16875.518 | Q7: =(P7-P6)*1000 -> 7543 | R7: =N7-Q7 -> 2026 | S7: =S6 -> 10175 | T7: =S7-S6 -> 0 | U7: =U6 -> 429166 | V7: =U7-U6 -> 0 | W7: 32263 | X7: =W7-W6 -> 5 | Y7: 711420 | Z7: =Y7-Y6 -> 857 | AA7: 35820 | AB7: =AA7-AA6 -> 1 | AC7: 937184 | AD7: =AC7-AC6 -> 290 | AE7: =AB7+X7+T7 -> 6 | AF7: =V7+Z7+AD7 -> 1147 | AG7: =IF(AE7>0,AF7/AE7,0) -> 191.16667 | AI7: =R7-'EDl log'!B5 -> -956097
A8: ='General information '!F11 -> 0 | B8: =SUM(230*A8) -> 0 | C8: 44292 | D8: 32757886 | E8: =D8-D7 -> 4856 | F8: 3994535 | G8: =F8-F7 -> 666 | H8: 17836472 | I8: =H8-H7 -> 938 | J8: 28972314 | K8: =J8-J7 -> 2220 | L8: 24136934 | M8: =L8-L7 -> 2152 | N8: =M8+K8+I8+G8+E8 -> 10832 | O8: =IF(B8>0,N8/B8,0) -> 0 | P8: 16884.382 | Q8: =(P8-P7)*1000 -> 8864 | R8: =N8-Q8 -> 1968 | S8: =S7 -> 10175 | T8: =S8-S7 -> 0 | U8: =U7 -> 429166 | V8: =U8-U7 -> 0 | W8: 32264 | X8: =W8-W7 -> 1 | Y8: 711752 | Z8: =Y8-Y7 -> 332 | AA8: 35829 | AB8: =AA8-AA7 -> 9 | AC8: 938828 | AD8: =AC8-AC7 -> 1644 | AE8: =AB8+X8+T8 -> 10 | AF8: =V8+Z8+AD8 -> 1976 | AG8: =IF(AE8>0,AF8/AE8,0) -> 197.6 | AI8: =R8-'EDl log'!B6 -> -957001
A9: ='General information '!F12 -> 0 | B9: =SUM(230*A9) -> 0 | C9: 44293 | D9: 32761750 | E9: =D9-D8 -> 3864 | F9: 3995231 | G9: =F9-F8 -> 696 | H9: 17837370 | I9: =H9-H8 -> 898 | J9: 28973992 | K9: =J9-J8 -> 1678 | L9: 24138590 | M9: =L9-L8 -> 1656 | N9: =M9+K9+I9+G9+E9 -> 8792 | O9: =IF(B9>0,N9/B9,0) -> 0 | P9: 16889.852 | Q9: =(P9-P8)*1000 -> 5470 | R9: =N9-Q9 -> 3322 | S9: =S8 -> 10175 | T9: =S9-S8 -> 0 | U9: =U8 -> 429166 | V9: =U9-U8 -> 0 | W9: =W8 -> 32264 | X9: =W9-W8 -> 0 | Y9: =Y8 -> 711752 | Z9: =Y9-Y8 -> 0 | AA9: 35835 | AB9: =AA9-AA8 -> 6 | AC9: 940208 | AD9: =AC9-AC8 -> 1380 | AE9: =AB9+X9+T9 -> 6 | AF9: =V9+Z9+AD9 -> 1380 | AG9: =IF(AE9>0,AF9/AE9,0) -> 230 | AI9: =R9-'EDl log'!B7 -> -956336
A10: ='General information '!F13 -> 0 | B10: =SUM(230*A10) -> 0 | C10: 44294 | D10: 32764132 | E10: =D10-D9 -> 2382 | F10: 3996002 | G10: =F10-F9 -> 771 | H10: 17838240 | I10: =H10-H9 -> 870 | J10: 28976514 | K10: =J10-J9 -> 2522 | L10: 24140252 | M10: =L10-L9 -> 1662 | N10: =M10+K10+I10+G10+E10 -> 8207 | O10: =IF(B10>0,N10/B10,0) -> 0 | P10: 16894.339 | Q10: =(P10-P9)*1000 -> 4487 | R10: =N10-Q10 -> 3720 | S10: =S9 -> 10175 | T10: =S10-S9 -> 0 | U10: =U9 -> 429166 | V10: =U10-U9 -> 0 | W10: 32270 | X10: =W10-W9 -> 6 | Y10: 712865 | Z10: =Y10-Y9 -> 1113 | AA10: =AA9 -> 35835 | AB10: =AA10-AA9 -> 0 | AC10: =AC9 -> 940208 | AD10: =AC10-AC9 -> 0 | AE10: =AB10+X10+T10 -> 6 | AF10: =V10+Z10+AD10 -> 1113 | AG10: =IF(AE10>0,AF10/AE10,0) -> 185.5 | AI10: =R10-'EDl log'!B8 -> -957419
A11: ='General information '!F14 -> 0 | B11: =SUM(230*A11) -> 0 | C11: 44295 | D11: 32767042 | E11: =D11-D10 -> 2910 | F11: 3996744 | G11: =F11-F10 -> 742 | H11: 17839158 | I11: =H11-H10 -> 918 | J11: 28977872 | K11: =J11-J10 -> 1358 | L11: 24141908 | M11: =L11-L10 -> 1656 | N11: =M11+K11+I11+G11+E11 -> 7584 | O11: =IF(B11>0,N11/B11,0) -> 0 | P11: 16898.479 | Q11: =(P11-P10)*1000 -> 4140 | R11: =N11-Q11 -> 3444 | S11: =S10 -> 10175 | T11: =S11-S10 -> 0 | U11: =U10 -> 429166 | V11: =U11-U10 -> 0 | W11: =W10 -> 32270 | X11: =W11-W10 -> 0 | Y11: =Y10 -> 712865 | Z11: =Y11-Y10 -> 0 | AA11: 35839 | AB11: =AA11-AA10 -> 4 | AC11: 940903 | AD11: =AC11-AC10 -> 695 | AE11: =AB11+X11+T11 -> 4 | AF11: =V11+Z11+AD11 -> 695 | AG11: =IF(AE11>0,AF11/AE11,0) -> 173.75 | AI11: =R11-'EDl log'!B9 -> -958520
A12: ='General information '!F15 -> 0 | B12: =SUM(230*A12) -> 0 | C12: 44296 | D12: 32769110 | E12: =D12-D11 -> 2068 | F12: 3997467 | G12: =F12-F11 -> 723 | H12: 17840094 | I12: =H12-H11 -> 936 | J12: 28979110 | K12: =J12-J11 -> 1238 | L12: 24143826 | M12: =L12-L11 -> 1918 | N12: =M12+K12+I12+G12+E12 -> 6883 | O12: =IF(B12>0,N12/B12,0) -> 0 | P12: 16901.314 | Q12: =(P12-P11)*1000 -> 2835 | R12: =N12-Q12 -> 4048 | S12: =S11 -> 10175 | T12: =S12-S11 -> 0 | U12: =U11 -> 429166 | V12: =U12-U11 -> 0 | W12: =W11 -> 32270 | X12: =W12-W11 -> 0 | Y12: =Y11 -> 712865 | Z12: =Y12-Y11 -> 0 | AA12: 35841 | AB12: =AA12-AA11 -> 2 | AC12: 941299 | AD12: =AC12-AC11 -> 396 | AE12: =AB12+X12+T12 -> 2 | AF12: =V12+Z12+AD12 -> 396 | AG12: =IF(AE12>0,AF12/AE12,0) -> 198 | AI12: =R12-'EDl log'!B10 -> -959610
A13: ='General information '!F16 -> 0 | B13: =SUM(230*A13) -> 0 | C13: 44297 | D13: 32771430 | E13: =D13-D12 -> 2320 | F13: 3998122.8 | G13: =F13-F12 -> 655.8 | H13: 17840942 | I13: =H13-H12 -> 848 | J13: 28980359 | K13: =J13-J12 -> 1249 | L13: 24145514 | M13: =L13-L12 -> 1688 | N13: =M13+K13+I13+G13+E13 -> 6760.8 | O13: =IF(B13>0,N13/B13,0) -> 0 | P13: 16904.397 | Q13: =(P13-P12)*1000 -> 3083 | R13: =N13-Q13 -> 3677.8 | S13: =S12 -> 10175 | T13: =S13-S12 -> 0 | U13: =U12 -> 429166 | V13: =U13-U12 -> 0 | W13: =W12 -> 32270 | X13: =W13-W12 -> 0 | Y13: =Y12 -> 712865 | Z13: =Y13-Y12 -> 0 | AA13: 35844 | AB13: =AA13-AA12 -> 3 | AC13: 941856 | AD13: =AC13-AC12 -> 557 | AE13: =AB13+X13+T13 -> 3 | AF13: =V13+Z13+AD13 -> 557 | AG13: =IF(AE13>0,AF13/AE13,0) -> 185.66667 | AI13: =R13-'EDl log'!B11 -> -961997.2
A14: ='General information '!F17 -> 0 | B14: =SUM(230*A14) -> 0 | C14: 44298 | D14: 32774350 | E14: =D14-D13 -> 2920 | F14: 3998763 | G14: =F14-F13 -> 640.2 | H14: 17841744 | I14: =H14-H13 -> 802 | J14: 28981682 | K14: =J14-J13 -> 1323 | L14: 24147122 | M14: =L14-L13 -> 1608 | N14: =M14+K14+I14+G14+E14 -> 7293.2 | O14: =IF(B14>0,N14/B14,0) -> 0 | P14: 16908.744 | Q14: =(P14-P13)*1000 -> 4347 | R14: =N14-Q14 -> 2946.2 | S14: =S13 -> 10175 | T14: =S14-S13 -> 0 | U14: =U13 -> 429166 | V14: =U14-U13 -> 0 | W14: =W13 -> 32270 | X14: =W14-W13 -> 0 | Y14: =Y13 -> 712865 | Z14: =Y14-Y13 -> 0 | AA14: 35848 | AB14: =AA14-AA13 -> 4 | AC14: 942587 | AD14: =AC14-AC13 -> 731 | AE14: =AB14+X14+T14 -> 4 | AF14: =V14+Z14+AD14 -> 731 | AG14: =IF(AE14>0,AF14/AE14,0) -> 182.75 | AI14: =R14-'EDl log'!B12 -> -964589.8
A15: ='General information '!F18 -> 0 | B15: =SUM(230*A15) -> 0 | C15: 44299 | D15: 32776934 | E15: =D15-D14 -> 2584 | F15: 3999372 | G15: =F15-F14 -> 609 | H15: 17842538 | I15: =H15-H14 -> 794 | J15: 28982962 | K15: =J15-J14 -> 1280 | L15: 24148698 | M15: =L15-L14 -> 1576 | N15: =M15+K15+I15+G15+E15 -> 6843 | O15: =IF(B15>0,N15/B15,0) -> 0 | P15: 16912 | Q15: =(P15-P14)*1000 -> 3256 | R15: =N15-Q15 -> 3587 | S15: =S14 -> 10175 | T15: =S15-S14 -> 0 | U15: =U14 -> 429166 | V15: =U15-U14 -> 0 | W15: =W14 -> 32270 | X15: =W15-W14 -> 0 | Y15: =Y14 -> 712865 | Z15: =Y15-Y14 -> 0 | AA15: 35852 | AB15: =AA15-AA14 -> 4 | AC15: 943255 | AD15: =AC15-AC14 -> 668 | AE15: =AB15+X15+T15 -> 4 | AF15: =V15+Z15+AD15 -> 668 | AG15: =IF(AE15>0,AF15/AE15,0) -> 167 | AI15: =R15-'EDl log'!B13 -> -966120
A16: ='General information '!F19 -> 0 | B16: =SUM(230*A16) -> 0 | C16: 44300 | D16: 32778910 | E16: =D16-D15 -> 1976 | F16: 4000042 | G16: =F16-F15 -> 670 | H16: 17843334 | I16: =H16-H15 -> 796 | J16: 28984462 | K16: =J16-J15 -> 1500 | L16: 24150556 | M16: =L16-L15 -> 1858 | N16: =M16+K16+I16+G16+E16 -> 6800 | O16: =IF(B16>0,N16/B16,0) -> 0 | P16: 16915 | Q16: =(P16-P15)*1000 -> 3000 | R16: =N16-Q16 -> 3800 | S16: =S15 -> 10175 | T16: =S16-S15 -> 0 | U16: =U15 -> 429166 | V16: =U16-U15 -> 0 | W16: 32272 | X16: =W16-W15 -> 2 | Y16: 713410 | Z16: =Y16-Y15 -> 545 | AA16: =AA15 -> 35852 | AB16: =AA16-AA15 -> 0 | AC16: =AC15 -> 943255 | AD16: =AC16-AC15 -> 0 | AE16: =AB16+X16+T16 -> 2 | AF16: =V16+Z16+AD16 -> 545 | AG16: =IF(AE16>0,AF16/AE16,0) -> 272.5 | AI16: =R16-'EDl log'!B14 -> -967898
A17: ='General information '!F20 -> 0 | B17: =SUM(230*A17) -> 0 | C17: 44301 | D17: 32781494 | E17: =D17-D16 -> 2584 | F17: 4000629 | G17: =F17-F16 -> 587 | H17: 17844118 | I17: =H17-H16 -> 784 | J17: 28986530 | K17: =J17-J16 -> 2068 | L17: 24152120 | M17: =L17-L16 -> 1564 | N17: =M17+K17+I17+G17+E17 -> 7587 | O17: =IF(B17>0,N17/B17,0) -> 0 | P17: 16920 | Q17: =(P17-P16)*1000 -> 5000 | R17: =N17-Q17 -> 2587 | S17: =S16 -> 10175 | T17: =S17-S16 -> 0 | U17: =U16 -> 429166 | V17: =U17-U16 -> 0 | W17: 32276 | X17: =W17-W16 -> 4 | Y17: 714183 | Z17: =Y17-Y16 -> 773 | AA17: =AA16 -> 35852 | AB17: =AA17-AA16 -> 0 | AC17: =AC16 -> 943255 | AD17: =AC17-AC16 -> 0 | AE17: =AB17+X17+T17 -> 4 | AF17: =V17+Z17+AD17 -> 773 | AG17: =IF(AE17>0,AF17/AE17,0) -> 193.25 | AI17: =R17-'EDl log'!B15 -> -970705
A18: ='General information '!F21 -> 0 | B18: =SUM(230*A18) -> 0 | C18: 44302 | D18: =D17 -> 32781494 | E18: =D18-D17 -> 0 | F18: =F17 -> 4000629 | G18: =F18-F17 -> 0 | H18: =H17 -> 17844118 | I18: =H18-H17 -> 0 | J18: =J17 -> 28986530 | K18: =J18-J17 -> 0 | L18: =L17 -> 24152120 | M18: =L18-L17 -> 0 | N18: =M18+K18+I18+G18+E18 -> 0 | O18: =IF(B18>0,N18/B18,0) -> 0 | P18: =P17 -> 16920 | Q18: =(P18-P17)*1000 -> 0 | R18: =N18-Q18 -> 0 | S18: =S17 -> 10175 | T18: =S18-S17 -> 0 | U18: =U17 -> 429166 | V18: =U18-U17 -> 0 | W18: =W17 -> 32276 | X18: =W18-W17 -> 0 | Y18: =Y17 -> 714183 | Z18: =Y18-Y17 -> 0 | AA18: =AA17 -> 35852 | AB18: =AA18-AA17 -> 0 | AC18: =AC17 -> 943255 | AD18: =AC18-AC17 -> 0 | AE18: =AB18+X18+T18 -> 0 | AF18: =V18+Z18+AD18 -> 0 | AG18: =IF(AE18>0,AF18/AE18,0) -> 0 | AI18: =R18-'EDl log'!B16 -> -975030
A19: ='General information '!F22 -> 0 | B19: =SUM(230*A19) -> 0 | C19: 44303 | D19: =D18 -> 32781494 | E19: =D19-D18 -> 0 | F19: =F18 -> 4000629 | G19: =F19-F18 -> 0 | H19: =H18 -> 17844118 | I19: =H19-H18 -> 0 | J19: =J18 -> 28986530 | K19: =J19-J18 -> 0 | L19: =L18 -> 24152120 | M19: =L19-L18 -> 0 | N19: =M19+K19+I19+G19+E19 -> 0 | O19: =IF(B19>0,N19/B19,0) -> 0 | P19: =P18 -> 16920 | Q19: =(P19-P18)*1000 -> 0 | R19: =N19-Q19 -> 0 | S19: =S18 -> 10175 | T19: =S19-S18 -> 0 | U19: =U18 -> 429166 | V19: =U19-U18 -> 0 | W19: =W18 -> 32276 | X19: =W19-W18 -> 0 | Y19: =Y18 -> 714183 | Z19: =Y19-Y18 -> 0 | AA19: =AA18 -> 35852 | AB19: =AA19-AA18 -> 0 | AC19: =AC18 -> 943255 | AD19: =AC19-AC18 -> 0 | AE19: =AB19+X19+T19 -> 0 | AF19: =V19+Z19+AD19 -> 0 | AG19: =IF(AE19>0,AF19/AE19,0) -> 0 | AI19: =R19-'EDl log'!B17 -> -976859
A20: ='General information '!F23 -> 0 | B20: =SUM(230*A20) -> 0 | C20: 44304 | D20: =D19 -> 32781494 | E20: =D20-D19 -> 0 | F20: =F19 -> 4000629 | G20: =F20-F19 -> 0 | H20: =H19 -> 17844118 | I20: =H20-H19 -> 0 | J20: =J19 -> 28986530 | K20: =J20-J19 -> 0 | L20: =L19 -> 24152120 | M20: =L20-L19 -> 0 | N20: =M20+K20+I20+G20+E20 -> 0 | O20: =IF(B20>0,N20/B20,0) -> 0 | P20: =P19 -> 16920 | Q20: =(P20-P19)*1000 -> 0 | R20: =N20-Q20 -> 0 | S20: =S19 -> 10175 | T20: =S20-S19 -> 0 | U20: =U19 -> 429166 | V20: =U20-U19 -> 0 | W20: =W19 -> 32276 | X20: =W20-W19 -> 0 | Y20: =Y19 -> 714183 | Z20: =Y20-Y19 -> 0 | AA20: =AA19 -> 35852 | AB20: =AA20-AA19 -> 0 | AC20: =AC19 -> 943255 | AD20: =AC20-AC19 -> 0 | AE20: =AB20+X20+T20 -> 0 | AF20: =V20+Z20+AD20 -> 0 | AG20: =IF(AE20>0,AF20/AE20,0) -> 0 | AI20: =R20-'EDl log'!B18 -> -978719
A21: ='General information '!F24 -> 0 | B21: =SUM(230*A21) -> 0 | C21: 44305 | D21: =D20 -> 32781494 | E21: =D21-D20 -> 0 | F21: =F20 -> 4000629 | G21: =F21-F20 -> 0 | H21: =H20 -> 17844118 | I21: =H21-H20 -> 0 | J21: =J20 -> 28986530 | K21: =J21-J20 -> 0 | L21: =L20 -> 24152120 | M21: =L21-L20 -> 0 | N21: =M21+K21+I21+G21+E21 -> 0 | O21: =IF(B21>0,N21/B21,0) -> 0 | P21: =P20 -> 16920 | Q21: =(P21-P20)*1000 -> 0 | R21: =N21-Q21 -> 0 | S21: =S20 -> 10175 | T21: =S21-S20 -> 0 | U21: =U20 -> 429166 | V21: =U21-U20 -> 0 | W21: =W20 -> 32276 | X21: =W21-W20 -> 0 | Y21: =Y20 -> 714183 | Z21: =Y21-Y20 -> 0 | AA21: =AA20 -> 35852 | AB21: =AA21-AA20 -> 0 | AC21: =AC20 -> 943255 | AD21: =AC21-AC20 -> 0 | AE21: =AB21+X21+T21 -> 0 | AF21: =V21+Z21+AD21 -> 0 | AG21: =IF(AE21>0,AF21/AE21,0) -> 0 | AI21: =R21-'EDl log'!B19 -> -978719
A22: ='General information '!F25 -> 0 | B22: =SUM(230*A22) -> 0 | C22: 44306 | D22: =D21 -> 32781494 | E22: =D22-D21 -> 0 | F22: =F21 -> 4000629 | G22: =F22-F21 -> 0 | H22: =H21 -> 17844118 | I22: =H22-H21 -> 0 | J22: =J21 -> 28986530 | K22: =J22-J21 -> 0 | L22: =L21 -> 24152120 | M22: =L22-L21 -> 0 | N22: =M22+K22+I22+G22+E22 -> 0 | O22: =IF(B22>0,N22/B22,0) -> 0 | P22: =P21 -> 16920 | Q22: =(P22-P21)*1000 -> 0 | R22: =N22-Q22 -> 0 | S22: =S21 -> 10175 | T22: =S22-S21 -> 0 | U22: =U21 -> 429166 | V22: =U22-U21 -> 0 | W22: =W21 -> 32276 | X22: =W22-W21 -> 0 | Y22: =Y21 -> 714183 | Z22: =Y22-Y21 -> 0 | AA22: =AA21 -> 35852 | AB22: =AA22-AA21 -> 0 | AC22: =AC21 -> 943255 | AD22: =AC22-AC21 -> 0 | AE22: =AB22+X22+T22 -> 0 | AF22: =V22+Z22+AD22 -> 0 | AG22: =IF(AE22>0,AF22/AE22,0) -> 0 | AI22: =R22-'EDl log'!B20 -> -978719
A23: ='General information '!F26 -> 0 | B23: =SUM(230*A23) -> 0 | C23: 44307 | D23: =D22 -> 32781494 | E23: =D23-D22 -> 0 | F23: =F22 -> 4000629 | G23: =F23-F22 -> 0 | H23: =H22 -> 17844118 | I23: =H23-H22 -> 0 | J23: =J22 -> 28986530 | K23: =J23-J22 -> 0 | L23: =L22 -> 24152120 | M23: =L23-L22 -> 0 | N23: =M23+K23+I23+G23+E23 -> 0 | O23: =IF(B23>0,N23/B23,0) -> 0 | P23: =P22 -> 16920 | Q23: =(P23-P22)*1000 -> 0 | R23: =N23-Q23 -> 0 | S23: =S22 -> 10175 | T23: =S23-S22 -> 0 | U23: =U22 -> 429166 | V23: =U23-U22 -> 0 | W23: =W22 -> 32276 | X23: =W23-W22 -> 0 | Y23: =Y22 -> 714183 | Z23: =Y23-Y22 -> 0 | AA23: =AA22 -> 35852 | AB23: =AA23-AA22 -> 0 | AC23: =AC22 -> 943255 | AD23: =AC23-AC22 -> 0 | AE23: =AB23+X23+T23 -> 0 | AF23: =V23+Z23+AD23 -> 0 | AG23: =IF(AE23>0,AF23/AE23,0) -> 0 | AI23: =R23-'EDl log'!B21 -> -978719
A24: ='General information '!F27 -> 0 | B24: =SUM(230*A24) -> 0 | C24: 44308 | D24: =D23 -> 32781494 | E24: =D24-D23 -> 0 | F24: =F23 -> 4000629 | G24: =F24-F23 -> 0 | H24: =H23 -> 17844118 | I24: =H24-H23 -> 0 | J24: =J23 -> 28986530 | K24: =J24-J23 -> 0 | L24: =L23 -> 24152120 | M24: =L24-L23 -> 0 | N24: =M24+K24+I24+G24+E24 -> 0 | O24: =IF(B24>0,N24/B24,0) -> 0 | P24: =P23 -> 16920 | Q24: =(P24-P23)*1000 -> 0 | R24: =N24-Q24 -> 0 | S24: =S23 -> 10175 | T24: =S24-S23 -> 0 | U24: =U23 -> 429166 | V24: =U24-U23 -> 0 | W24: =W23 -> 32276 | X24: =W24-W23 -> 0 | Y24: =Y23 -> 714183 | Z24: =Y24-Y23 -> 0 | AA24: =AA23 -> 35852 | AB24: =AA24-AA23 -> 0 | AC24: =AC23 -> 943255 | AD24: =AC24-AC23 -> 0 | AE24: =AB24+X24+T24 -> 0 | AF24: =V24+Z24+AD24 -> 0 | AG24: =IF(AE24>0,AF24/AE24,0) -> 0 | AI24: =R24-'EDl log'!B22 -> -978719
A25: ='General information '!F28 -> 0 | B25: =SUM(230*A25) -> 0 | C25: 44309 | D25: =D24 -> 32781494 | E25: =D25-D24 -> 0 | F25: =F24 -> 4000629 | G25: =F25-F24 -> 0 | H25: =H24 -> 17844118 | I25: =H25-H24 -> 0 | J25: =J24 -> 28986530 | K25: =J25-J24 -> 0 | L25: =L24 -> 24152120 | M25: =L25-L24 -> 0 | N25: =M25+K25+I25+G25+E25 -> 0 | O25: =IF(B25>0,N25/B25,0) -> 0 | P25: =P24 -> 16920 | Q25: =(P25-P24)*1000 -> 0 | R25: =N25-Q25 -> 0 | S25: =S24 -> 10175 | T25: =S25-S24 -> 0 | U25: =U24 -> 429166 | V25: =U25-U24 -> 0 | W25: =W24 -> 32276 | X25: =W25-W24 -> 0 | Y25: =Y24 -> 714183 | Z25: =Y25-Y24 -> 0 | AA25: =AA24 -> 35852 | AB25: =AA25-AA24 -> 0 | AC25: =AC24 -> 943255 | AD25: =AC25-AC24 -> 0 | AE25: =AB25+X25+T25 -> 0 | AF25: =V25+Z25+AD25 -> 0 | AG25: =IF(AE25>0,AF25/AE25,0) -> 0 | AI25: =R25-'EDl log'!B23 -> -978719
A26: ='General information '!F29 -> 0 | B26: =SUM(230*A26) -> 0 | C26: 44310 | D26: =D25 -> 32781494 | E26: =D26-D25 -> 0 | F26: =F25 -> 4000629 | G26: =F26-F25 -> 0 | H26: =H25 -> 17844118 | I26: =H26-H25 -> 0 | J26: =J25 -> 28986530 | K26: =J26-J25 -> 0 | L26: =L25 -> 24152120 | M26: =L26-L25 -> 0 | N26: =M26+K26+I26+G26+E26 -> 0 | O26: =IF(B26>0,N26/B26,0) -> 0 | P26: =P25 -> 16920 | Q26: =(P26-P25)*1000 -> 0 | R26: =N26-Q26 -> 0 | S26: =S25 -> 10175 | T26: =S26-S25 -> 0 | U26: =U25 -> 429166 | V26: =U26-U25 -> 0 | W26: =W25 -> 32276 | X26: =W26-W25 -> 0 | Y26: =Y25 -> 714183 | Z26: =Y26-Y25 -> 0 | AA26: =AA25 -> 35852 | AB26: =AA26-AA25 -> 0 | AC26: =AC25 -> 943255 | AD26: =AC26-AC25 -> 0 | AE26: =AB26+X26+T26 -> 0 | AF26: =V26+Z26+AD26 -> 0 | AG26: =IF(AE26>0,AF26/AE26,0) -> 0 | AI26: =R26-'EDl log'!B24 -> -978719
A27: ='General information '!F30 -> 0 | B27: =SUM(230*A27) -> 0 | C27: 44311 | D27: =D26 -> 32781494 | E27: =D27-D26 -> 0 | F27: =F26 -> 4000629 | G27: =F27-F26 -> 0 | H27: =H26 -> 17844118 | I27: =H27-H26 -> 0 | J27: =J26 -> 28986530 | K27: =J27-J26 -> 0 | L27: =L26 -> 24152120 | M27: =L27-L26 -> 0 | N27: =M27+K27+I27+G27+E27 -> 0 | O27: =IF(B27>0,N27/B27,0) -> 0 | P27: =P26 -> 16920 | Q27: =(P27-P26)*1000 -> 0 | R27: =N27-Q27 -> 0 | S27: =S26 -> 10175 | T27: =S27-S26 -> 0 | U27: =U26 -> 429166 | V27: =U27-U26 -> 0 | W27: =W26 -> 32276 | X27: =W27-W26 -> 0 | Y27: =Y26 -> 714183 | Z27: =Y27-Y26 -> 0 | AA27: =AA26 -> 35852 | AB27: =AA27-AA26 -> 0 | AC27: =AC26 -> 943255 | AD27: =AC27-AC26 -> 0 | AE27: =AB27+X27+T27 -> 0 | AF27: =V27+Z27+AD27 -> 0 | AG27: =IF(AE27>0,AF27/AE27,0) -> 0 | AI27: =R27-'EDl log'!B25 -> -978719
A28: ='General information '!F31 -> 0 | B28: =SUM(230*A28) -> 0 | C28: 44312 | D28: =D27 -> 32781494 | E28: =D28-D27 -> 0 | F28: =F27 -> 4000629 | G28: =F28-F27 -> 0 | H28: =H27 -> 17844118 | I28: =H28-H27 -> 0 | J28: =J27 -> 28986530 | K28: =J28-J27 -> 0 | L28: =L27 -> 24152120 | M28: =L28-L27 -> 0 | N28: =M28+K28+I28+G28+E28 -> 0 | O28: =IF(B28>0,N28/B28,0) -> 0 | P28: =P27 -> 16920 | Q28: =(P28-P27)*1000 -> 0 | R28: =N28-Q28 -> 0 | S28: =S27 -> 10175 | T28: =S28-S27 -> 0 | U28: =U27 -> 429166 | V28: =U28-U27 -> 0 | W28: =W27 -> 32276 | X28: =W28-W27 -> 0 | Y28: =Y27 -> 714183 | Z28: =Y28-Y27 -> 0 | AA28: =AA27 -> 35852 | AB28: =AA28-AA27 -> 0 | AC28: =AC27 -> 943255 | AD28: =AC28-AC27 -> 0 | AE28: =AB28+X28+T28 -> 0 | AF28: =V28+Z28+AD28 -> 0 | AG28: =IF(AE28>0,AF28/AE28,0) -> 0 | AI28: =R28-'EDl log'!B26 -> -978719
A29: ='General information '!F32 -> 0 | B29: =SUM(230*A29) -> 0 | C29: 44313 | D29: =D28 -> 32781494 | E29: =D29-D28 -> 0 | F29: =F28 -> 4000629 | G29: =F29-F28 -> 0 | H29: =H28 -> 17844118 | I29: =H29-H28 -> 0 | J29: =J28 -> 28986530 | K29: =J29-J28 -> 0 | L29: =L28 -> 24152120 | M29: =L29-L28 -> 0 | N29: =M29+K29+I29+G29+E29 -> 0 | O29: =IF(B29>0,N29/B29,0) -> 0 | P29: =P28 -> 16920 | Q29: =(P29-P28)*1000 -> 0 | R29: =N29-Q29 -> 0 | S29: =S28 -> 10175 | T29: =S29-S28 -> 0 | U29: =U28 -> 429166 | V29: =U29-U28 -> 0 | W29: =W28 -> 32276 | X29: =W29-W28 -> 0 | Y29: =Y28 -> 714183 | Z29: =Y29-Y28 -> 0 | AA29: =AA28 -> 35852 | AB29: =AA29-AA28 -> 0 | AC29: =AC28 -> 943255 | AD29: =AC29-AC28 -> 0 | AE29: =AB29+X29+T29 -> 0 | AF29: =V29+Z29+AD29 -> 0 | AG29: =IF(AE29>0,AF29/AE29,0) -> 0 | AI29: =R29-'EDl log'!B27 -> -978719
... A32: ='General information '!F35 -> 0 | B32: =SUM(230*A32) -> 0 | C32: 44316 | D32: =D31 -> 32781494 | E32: =D32-D31 -> 0 | F32: =F31 -> 4000629 | G32: =F32-F31 -> 0 | H32: =H31 -> 17844118 | I32: =H32-H31 -> 0 | J32: =J31 -> 28986530 | K32: =J32-J31 -> 0 | L32: =L31 -> 24152120 | M32: =L32-L31 -> 0 | N32: =M32+K32+I32+G32+E32 -> 0 | O32: =IF(B32>0,N32/B32,0) -> 0 | P32: =P31 -> 16920 | Q32: =(P32-P31)*1000 -> 0 | R32: =N32-Q32 -> 0 | S32: =S31 -> 10175 | T32: =S32-S31 -> 0 | U32: =U31 -> 429166 | V32: =U32-U31 -> 0 | W32: =W31 -> 32276 | X32: =W32-W31 -> 0 | Y32: =Y31 -> 714183 | Z32: =Y32-Y31 -> 0 | AA32: =AA31 -> 35852 | AB32: =AA32-AA31 -> 0 | AC32: =AC31 -> 943255 | AD32: =AC32-AC31 -> 0 | AE32: =AB32+X32+T32 -> 0 | AF32: =V32+Z32+AD32 -> 0 | AG32: =IF(AE32>0,AF32/AE32,0) -> 0 | AI32: =R32-'EDl log'!B30 -> -978719

Sheet B5
F1: Boiler A | J1: =J36 -> 76.183333 | K1: Boiler B | P1: Boiler C | V1: Boiler | X1: SteamA | AC1: SteamB | AH1: Steam | AI1: Boiler & steam | AL1: Total Boiler Runing H | AM1: Total Steam Runing H | AN1: GAS1 % | AO1: GAS1/L | AP1: GAS2% | AQ1: Gas2/L | AR1: GAS3% | AS1: GAS3/L | AU1: Gas Cons | AV1: Delivery | AW1: Cost/L
B2: Level Tank Gen | C2: Level tank Boiler | D2: Daily Cons Bo. | E2: Boiler litter | F2: Boiler A | G2: Run Hr a | H2: Boiler A fuel | I2: Daily consumption | J2: AVG | K2: index Run H | L2: Run Hrb | M2: Boiler B Fuel | O2: Daily consumption | P2: Boiler C | S2: Run C | U2: Total RH | V2: Total Fuel | X2: SteamA | Y2: Run SA | Z2: Steam A Conter | AA2: Liters | AC2: SteamB | AD2: Run SteamB | AE2: Steam B Conter | AF2: SB Litters | AG2: Avg | AH2: Total Fuel | AI2: Total Fuel
S3: 0
A4: =ELEC!C2 -> 44286 | B4: =[3]B5!B35 -> 216 | C4: =[3]B5!C35 -> 223 | D4: =[3]B5!D35 -> 12 | E4: =[3]B5!E35 -> 100.56 | F4: =[3]B5!F35 -> 1795 | G4: =[3]B5!G35 -> 3 | H4: =[3]B5!H35 -> 9885 | I4: =[3]B5!I35 -> 203 | ... AX4: =[3]B5!AX35 -> 0.8
A5: =ELEC!C3 -> 44287 | B5: 230 | C5: 237 | D5: =C4-C5 -> -14 | E5: =D5*8.38 -> -117.32 | F5: 1797 | G5: =F5-F4 -> 2 | H5: 10038 | I5: =SUM(H5-H4) -> 153 | J5: 1 | K5: 2288 | L5: =K5-K4 -> 3 | M5: 168501 | N5: =M5-M4 -> 206 | O5: =O4 -> 1869 | P5: =P4 -> 2046 | Q5: =Q4 -> 172429 | R5: =Q5-Q4 -> 0 | S5: =SUM(P5-P4) -> 0 | T5: =SUM(S5*$T$2) -> 0 | U5: =SUM(G5+L5+S5) -> 5 | V5: =R5+N5+I5:I5 -> 359 | W5: =SUM(V5/U5) -> 71.8 | X5: =X4 -> 2463 | Y5: =X5-X4 -> 0 | Z5: =Z4 -> 138550 | AA5: =Z5-Z4 -> 0 | AB5: =SUM(Y5*$AB$2) -> 0 | AC5: =AC4 -> 1936 | AD5: =AC5-AC4 -> 0 | AE5: =AE4 -> 365520.8 | AF5: =AE5-AE4 -> 0 | AG5: =IF(AD5>0,AF5/AD5,0) -> 0 | AH5: =AF5+AA5 -> 0 | AI5: =SUM(AH5+V5) -> 359 | AJ5: =-tanks!AW6 -> 359 | AK5: =SUM(AJ5-AI5) -> 0 | AL5: =S5+L5+G5 -> 5 | AM5: =Y5+AD5 -> 0 | AN5: =AN4 -> 67 | AO5: =(AN5/100)*3000 -> 2010 | AP5: =AP4 -> 55 | AQ5: =(AP5/100)*3000 -> 1650 | AR5: =AR4 -> 61 | AS5: =(AR5/100)*3000 -> 1830 | AT5: =SUM(AO5+AQ5+AS5) -> 5490 | AU5: =AT4-AT5+AV5 -> 0 | AX5: =IF(AV5>0,AW5,AX4) -> 0.8
A6: =ELEC!C4 -> 44288 | B6: 219 | C6: 226 | D6: =C5-C6 -> 11 | E6: =D6*8.38 -> 92.18 | F6: =F5 -> 1797 | G6: =F6-F5 -> 0 | H6: =H5 -> 10038 | I6: =SUM(H6-H5) -> 0 | J6: =IF(G6>0,I6/G6,0) -> 0 | K6: 2290 | L6: =K6-K5 -> 2 | M6: 168619 | N6: =M6-M5 -> 118 | O6: =O5 -> 1869 | P6: 2049 | Q6: 172609 | R6: =Q6-Q5 -> 180 | S6: =SUM(P6-P5) -> 3 | T6: =SUM(S6*$T$2) -> 0 | U6: =SUM(G6+L6+S6) -> 5 | V6: =R6+N6+I6:I6 -> 298 | W6: =SUM(V6/U6) -> 59.6 | X6: =X5 -> 2463 | Y6: =X6-X5 -> 0 | Z6: =Z5 -> 138550 | AA6: =Z6-Z5 -> 0 | AB6: =SUM(Y6*$AB$2) -> 0 | AC6: =AC5 -> 1936 | AD6: =AC6-AC5 -> 0 | AE6: =AE5 -> 365520.8 | AF6: =AE6-AE5 -> 0 | AG6: =IF(AD6>0,AF6/AD6,0) -> 0 | AH6: =AF6+AA6 -> 0 | AI6: =SUM(AH6+V6) -> 298 | AJ6: =-tanks!AW7 -> 298 | AK6: =SUM(AJ6-AI6) -> 0 | AL6: =S6+L6+G6 -> 5 | AM6: =Y6+AD6 -> 0 | AN6: =AN5 -> 67 | AO6: =(AN6/100)*3000 -> 2010 | AP6: =AP5 -> 55 | AQ6: =(AP6/100)*3000 -> 1650 | AR6: =AR5 -> 61 | AS6: =(AR6/100)*3000 -> 1830 | AT6: =SUM(AO6+AQ6+AS6) -> 5490 | AU6: =AT5-AT6+AV6 -> 0 | AX6: =IF(AV6>0,AW6,AX5) -> 0.8
A7: =ELEC!C5 -> 44289 | B7: 208 | C7: 215 | D7: =C6-C7 -> 11 | E7: =D7*8.38 -> 92.18 | F7: 1799 | G7: =F7-F6 -> 2 | H7: 10207 | I7: =SUM(H7-H6) -> 169 | J7: =IF(G7>0,I7/G7,0) -> 84.5 | K7: =K6 -> 2290 | L7: =K7-K6 -> 0 | M7: =M6 -> 168619 | N7: =M7-M6 -> 0 | O7: =O6 -> 1869 | P7: 2050 | Q7: 172727 | R7: =Q7-Q6 -> 118 | S7: =SUM(P7-P6) -> 1 | T7: =SUM(S7*$T$2) -> 0 | U7: =SUM(G7+L7+S7) -> 3 | V7: =R7+N7+I7:I7 -> 287 | W7: =SUM(V7/U7) -> 95.666667 | X7: =X6 -> 2463 | Y7: =X7-X6 -> 0 | Z7: =Z6 -> 138550 | AA7: =Z7-Z6 -> 0 | AB7: =SUM(Y7*$AB$2) -> 0 | AC7: =AC6 -> 1936 | AD7: =AC7-AC6 -> 0 | AE7: =AE6 -> 365520.8 | AF7: =AE7-AE6 -> 0 | AG7: =IF(AD7>0,AF7/AD7,0) -> 0 | AH7: =AF7+AA7 -> 0 | AI7: =SUM(AH7+V7) -> 287 | AJ7: =-tanks!AW8 -> 287 | AK7: =SUM(AJ7-AI7) -> 0 | AL7: =S7+L7+G7 -> 3 | AM7: =Y7+AD7 -> 0 | AN7: =AN6 -> 67 | AO7: =(AN7/100)*3000 -> 2010 | AP7: =AP6 -> 55 | AQ7: =(AP7/100)*3000 -> 1650 | AR7: =AR6 -> 61 | AS7: =(AR7/100)*3000 -> 1830 | AT7: =SUM(AO7+AQ7+AS7) -> 5490 | AU7: =AT6-AT7+AV7 -> 0 | AX7: =IF(AV7>0,AW7,AX6) -> 0.8
A8: =ELEC!C6 -> 44290 | B8: 197 | C8: 204 | D8: =C7-C8 -> 11 | E8: =D8*8.38 -> 92.18 | F8: 1801 | G8: =F8-F7 -> 2 | H8: 10338 | I8: =SUM(H8-H7) -> 131 | J8: =IF(G8>0,I8/G8,0) -> 65.5 | K8: 2292 | L8: =K8-K7 -> 2 | M8: 168778 | N8: =M8-M7 -> 159 | O8: =O7 -> 1869 | P8: 2050 | Q8: =Q7 -> 172727 | R8: =Q8-Q7 -> 0 | S8: =SUM(P8-P7) -> 0 | T8: =SUM(S8*$T$2) -> 0 | U8: =SUM(G8+L8+S8) -> 4 | V8: =R8+N8+I8:I8 -> 290 | W8: =SUM(V8/U8) -> 72.5 | X8: =X7 -> 2463 | Y8: =X8-X7 -> 0 | Z8: =Z7 -> 138550 | AA8: =Z8-Z7 -> 0 | AB8: =SUM(Y8*$AB$2) -> 0 | AC8: =AC7 -> 1936 | AD8: =AC8-AC7 -> 0 | AE8: =AE7 -> 365520.8 | AF8: =AE8-AE7 -> 0 | AG8: =IF(AD8>0,AF8/AD8,0) -> 0 | AH8: =AF8+AA8 -> 0 | AI8: =SUM(AH8+V8) -> 290 | AJ8: =-tanks!AW9 -> 290 | AK8: =SUM(AJ8-AI8) -> 0 | AL8: =S8+L8+G8 -> 4 | AM8: =Y8+AD8 -> 0 | AN8: =AN7 -> 67 | AO8: =(AN8/100)*3000 -> 2010 | AP8: =AP7 -> 55 | AQ8: =(AP8/100)*3000 -> 1650 | AR8: =AR7 -> 61 | AS8: =(AR8/100)*3000 -> 1830 | AT8: =SUM(AO8+AQ8+AS8) -> 5490 | AU8: =AT7-AT8+AV8 -> 0 | AX8: =IF(AV8>0,AW8,AX7) -> 0.8
A9: =ELEC!C7 -> 44291 | B9: 188 | C9: 195 | D9: =C8-C9 -> 9 | E9: =D9*8.38 -> 75.42 | F9: =F8 -> 1801 | G9: =F9-F8 -> 0 | H9: =H8 -> 10338 | I9: =SUM(H9-H8) -> 0 | J9: =IF(G9>0,I9/G9,0) -> 0 | K9: 2293 | L9: =K9-K8 -> 1 | M9: 168927 | N9: =M9-M8 -> 149 | O9: =O8 -> 1869 | P9: 2052 | Q9: 172900 | R9: =Q9-Q8 -> 173 | S9: =SUM(P9-P8) -> 2 | T9: =SUM(S9*$T$2) -> 0 | U9: =SUM(G9+L9+S9) -> 3 | V9: =R9+N9+I9:I9 -> 322 | W9: =SUM(V9/U9) -> 107.33333 | X9: 2464 | Y9: =X9-X8 -> 1 | Z9: 138632 | AA9: =Z9-Z8 -> 82 | AB9: =SUM(Y9*$AB$2) -> 0 | AC9: =AC8 -> 1936 | AD9: =AC9-AC8 -> 0 | AE9: =AE8 -> 365520.8 | AF9: =AE9-AE8 -> 0 | AG9: =IF(AD9>0,AF9/AD9,0) -> 0 | AH9: =AF9+AA9 -> 82 | AI9: =SUM(AH9+V9) -> 404 | AJ9: =-tanks!AW10 -> 404 | AK9: =SUM(AJ9-AI9) -> 0 | AL9: =S9+L9+G9 -> 3 | AM9: =Y9+AD9 -> 1 | AN9: =AN8 -> 67 | AO9: =(AN9/100)*3000 -> 2010 | AP9: =AP8 -> 55 | AQ9: =(AP9/100)*3000 -> 1650 | AR9: =AR8 -> 61 | AS9: =(AR9/100)*3000 -> 1830 | AT9: =SUM(AO9+AQ9+AS9) -> 5490 | AU9: =AT8-AT9+AV9 -> 0 | AX9: =IF(AV9>0,AW9,AX8) -> 0.8
A10: =ELEC!C8 -> 44292 | B10: 177 | C10: 183 | D10: =C9-C10 -> 12 | E10: =D10*8.38 -> 100.56 | F10: 1803 | G10: =F10-F9 -> 2 | H10: 10506 | I10: =SUM(H10-H9) -> 168 | J10: =IF(G10>0,I10/G10,0) -> 84 | K10: =K9 -> 2293 | L10: =K10-K9 -> 0 | M10: =M9 -> 168927 | N10: =M10-M9 -> 0 | O10: =O9 -> 1869 | P10: 2054 | Q10: 173040 | R10: =Q10-Q9 -> 140 | S10: =SUM(P10-P9) -> 2 | T10: =SUM(S10*$T$2) -> 0 | U10: =SUM(G10+L10+S10) -> 4 | V10: =R10+N10+I10:I10 -> 308 | W10: =SUM(V10/U10) -> 77 | X10: =X9 -> 2464 | Y10: =X10-X9 -> 0 | Z10: =Z9 -> 138632 | AA10: =Z10-Z9 -> 0 | AB10: =SUM(Y10*$AB$2) -> 0 | AC10: =AC9 -> 1936 | AD10: =AC10-AC9 -> 0 | AE10: =AE9 -> 365520.8 | AF10: =AE10-AE9 -> 0 | AG10: =IF(AD10>0,AF10/AD10,0) -> 0 | AH10: =AF10+AA10 -> 0 | AI10: =SUM(AH10+V10) -> 308 | AJ10: =-tanks!AW11 -> 308 | AK10: =SUM(AJ10-AI10) -> 0 | AL10: =S10+L10+G10 -> 4 | AM10: =Y10+AD10 -> 0 | AN10: =AN9 -> 67 | AO10: =(AN10/100)*3000 -> 2010 | AP10: =AP9 -> 55 | AQ10: =(AP10/100)*3000 -> 1650 | AR10: =AR9 -> 61 | AS10: =(AR10/100)*3000 -> 1830 | AT10: =SUM(AO10+AQ10+AS10) -> 5490 | AU10: =AT9-AT10+AV10 -> 0 | AX10: =IF(AV10>0,AW10,AX9) -> 0.8
A11: =ELEC!C9 -> 44293 | B11: 228 | C11: 235 | D11: =C10-C11 -> -52 | E11: =D11*8.38 -> -435.76 | F11: 1805 | G11: =F11-F10 -> 2 | H11: 10625 | I11: =SUM(H11-H10) -> 119 | J11: =IF(G11>0,I11/G11,0) -> 59.5 | K11: 2296 | L11: =K11-K10 -> 3 | M11: 169095 | N11: =M11-M10 -> 168 | O11: =O10 -> 1869 | P11: =P10 -> 2054 | Q11: =Q10 -> 173040 | R11: =Q11-Q10 -> 0 | S11: =SUM(P11-P10) -> 0 | T11: =SUM(S11*$T$2) -> 0 | U11: =SUM(G11+L11+S11) -> 5 | V11: =R11+N11+I11:I11 -> 287 | W11: =SUM(V11/U11) -> 57.4 | X11: =X10 -> 2464 | Y11: =X11-X10 -> 0 | Z11: =Z10 -> 138632 | AA11: =Z11-Z10 -> 0 | AB11: =SUM(Y11*$AB$2) -> 0 | AC11: =AC10 -> 1936 | AD11: =AC11-AC10 -> 0 | AE11: =AE10 -> 365520.8 | AF11: =AE11-AE10 -> 0 | AG11: =IF(AD11>0,AF11/AD11,0) -> 0 | AH11: =AF11+AA11 -> 0 | AI11: =SUM(AH11+V11) -> 287 | AJ11: =-tanks!AW12 -> 287 | AK11: =SUM(AJ11-AI11) -> 0 | AL11: =S11+L11+G11 -> 5 | AM11: =Y11+AD11 -> 0 | AN11: =AN10 -> 67 | AO11: =(AN11/100)*3000 -> 2010 | AP11: =AP10 -> 55 | AQ11: =(AP11/100)*3000 -> 1650 | AR11: =AR10 -> 61 | AS11: =(AR11/100)*3000 -> 1830 | AT11: =SUM(AO11+AQ11+AS11) -> 5490 | AU11: =AT10-AT11+AV11 -> 0 | AX11: =IF(AV11>0,AW11,AX10) -> 0.8
A12: =ELEC!C10 -> 44294 | B12: 222 | C12: 228 | D12: =C11-C12 -> 7 | E12: =D12*8.38 -> 58.66 | F12: =F11 -> 1805 | G12: =F12-F11 -> 0 | H12: =H11 -> 10625 | I12: =SUM(H12-H11) -> 0 | J12: =IF(G12>0,I12/G12,0) -> 0 | K12: 2297 | L12: =K12-K11 -> 1 | M12: 169228 | N12: =M12-M11 -> 133 | O12: =O11 -> 1869 | P12: 2057 | Q12: 173215 | R12: =Q12-Q11 -> 175 | S12: =SUM(P12-P11) -> 3 | T12: =SUM(S12*$T$2) -> 0 | U12: =SUM(G12+L12+S12) -> 4 | V12: =R12+N12+I12:I12 -> 308 | W12: =SUM(V12/U12) -> 77 | X12: 2465 | Y12: =X12-X11 -> 1 | Z12: 138740 | AA12: =Z12-Z11 -> 108 | AB12: =SUM(Y12*$AB$2) -> 0 | AC12: =AC11 -> 1936 | AD12: =AC12-AC11 -> 0 | AE12: =AE11 -> 365520.8 | AF12: =AE12-AE11 -> 0 | AG12: =IF(AD12>0,AF12/AD12,0) -> 0 | AH12: =AF12+AA12 -> 108 | AI12: =SUM(AH12+V12) -> 416 | AJ12: =-tanks!AW13 -> 416 | AK12: =SUM(AJ12-AI12) -> 0 | AL12: =S12+L12+G12 -> 4 | AM12: =Y12+AD12 -> 1 | AN12: =AN11 -> 67 | AO12: =(AN12/100)*3000 -> 2010 | AP12: =AP11 -> 55 | AQ12: =(AP12/100)*3000 -> 1650 | AR12: =AR11 -> 61 | AS12: =(AR12/100)*3000 -> 1830 | AT12: =SUM(AO12+AQ12+AS12) -> 5490 | AU12: =AT11-AT12+AV12 -> 0 | AX12: =IF(AV12>0,AW12,AX11) -> 0.8
A13: =ELEC!C11 -> 44295 | B13: 217 | C13: 223 | D13: =C12-C13 -> 5 | E13: =D13*8.38 -> 41.9 | F13: 1808 | G13: =F13-F12 -> 3 | H13: 10857 | I13: =SUM(H13-H12) -> 232 | J13: =IF(G13>0,I13/G13,0) -> 77.333333 | K13: =K12 -> 2297 | L13: =K13-K12 -> 0 | M13: =M12 -> 169228 | N13: =M13-M12 -> 0 | O13: =O12 -> 1869 | P13: 2058 | Q13: 173309 | R13: =Q13-Q12 -> 94 | S13: =SUM(P13-P12) -> 1 | T13: =SUM(S13*$T$2) -> 0 | U13: =SUM(G13+L13+S13) -> 4 | V13: =R13+N13+I13:I13 -> 326 | W13: =SUM(V13/U13) -> 81.5 | X13: =X12 -> 2465 | Y13: =X13-X12 -> 0 | Z13: =Z12 -> 138740 | AA13: =Z13-Z12 -> 0 | AB13: =SUM(Y13*$AB$2) -> 0 | AC13: =AC12 -> 1936 | AD13: =AC13-AC12 -> 0 | AE13: =AE12 -> 365520.8 | AF13: =AE13-AE12 -> 0 | AG13: =IF(AD13>0,AF13/AD13,0) -> 0 | AH13: =AF13+AA13 -> 0 | AI13: =SUM(AH13+V13) -> 326 | AJ13: =-tanks!AW14 -> 326 | AK13: =SUM(AJ13-AI13) -> 0 | AL13: =S13+L13+G13 -> 4 | AM13: =Y13+AD13 -> 0 | AN13: =AN12 -> 67 | AO13: =(AN13/100)*3000 -> 2010 | AP13: =AP12 -> 55 | AQ13: =(AP13/100)*3000 -> 1650 | AR13: =AR12 -> 61 | AS13: =(AR13/100)*3000 -> 1830 | AT13: =SUM(AO13+AQ13+AS13) -> 5490 | AU13: =AT12-AT13+AV13 -> 0 | AX13: =IF(AV13>0,AW13,AX12) -> 0.8
A14: =ELEC!C12 -> 44296 | B14: 211 | C14: 218 | D14: =C13-C14 -> 5 | E14: =D14*8.38 -> 41.9 | F14: 1809 | G14: =F14-F13 -> 1 | H14: 10998 | I14: =SUM(H14-H13) -> 141 | J14: =IF(G14>0,I14/G14,0) -> 141 | K14: 2301 | L14: =K14-K13 -> 4 | M14: 169496 | N14: =M14-M13 -> 268 | O14: =O13 -> 1869 | P14: =P13 -> 2058 | Q14: =Q13 -> 173309 | R14: =Q14-Q13 -> 0 | S14: =SUM(P14-P13) -> 0 | T14: =SUM(S14*$T$2) -> 0 | U14: =SUM(G14+L14+S14) -> 5 | V14: =R14+N14+I14:I14 -> 409 | W14: =SUM(V14/U14) -> 81.8 | X14: =X13 -> 2465 | Y14: =X14-X13 -> 0 | Z14: =Z13 -> 138740 | AA14: =Z14-Z13 -> 0 | AB14: =SUM(Y14*$AB$2) -> 0 | AC14: =AC13 -> 1936 | AD14: =AC14-AC13 -> 0 | AE14: =AE13 -> 365520.8 | AF14: =AE14-AE13 -> 0 | AG14: =IF(AD14>0,AF14/AD14,0) -> 0 | AH14: =AF14+AA14 -> 0 | AI14: =SUM(AH14+V14) -> 409 | AJ14: =-tanks!AW15 -> 409 | AK14: =SUM(AJ14-AI14) -> 0 | AL14: =S14+L14+G14 -> 5 | AM14: =Y14+AD14 -> 0 | AN14: =AN13 -> 67 | AO14: =(AN14/100)*3000 -> 2010 | AP14: =AP13 -> 55 | AQ14: =(AP14/100)*3000 -> 1650 | AR14: =AR13 -> 61 | AS14: =(AR14/100)*3000 -> 1830 | AT14: =SUM(AO14+AQ14+AS14) -> 5490 | AU14: =AT13-AT14+AV14 -> 0 | AX14: =IF(AV14>0,AW14,AX13) -> 0.8
A15: =ELEC!C13 -> 44297 | B15: 207 | C15: 213 | D15: =C14-C15 -> 5 | E15: =D15*8.38 -> 41.9 | F15: =F14 -> 1809 | G15: =F15-F14 -> 0 | H15: =H14 -> 10998 | I15: =SUM(H15-H14) -> 0 | J15: =IF(G15>0,I15/G15,0) -> 0 | K15: 2302 | L15: =K15-K14 -> 1 | M15: 169624 | N15: =M15-M14 -> 128 | O15: =O14 -> 1869 | P15: 2061 | Q15: 173549 | R15: =Q15-Q14 -> 240 | S15: =SUM(P15-P14) -> 3 | T15: =SUM(S15*$T$2) -> 0 | U15: =SUM(G15+L15+S15) -> 4 | V15: =R15+N15+I15:I15 -> 368 | W15: =SUM(V15/U15) -> 92 | X15: =X14 -> 2465 | Y15: =X15-X14 -> 0 | Z15: =Z14 -> 138740 | AA15: =Z15-Z14 -> 0 | AB15: =SUM(Y15*$AB$2) -> 0 | AC15: =AC14 -> 1936 | AD15: =AC15-AC14 -> 0 | AE15: =AE14 -> 365520.8 | AF15: =AE15-AE14 -> 0 | AG15: =IF(AD15>0,AF15/AD15,0) -> 0 | AH15: =AF15+AA15 -> 0 | AI15: =SUM(AH15+V15) -> 368 | AJ15: =-tanks!AW16 -> 368 | AK15: =SUM(AJ15-AI15) -> 0 | AL15: =S15+L15+G15 -> 4 | AM15: =Y15+AD15 -> 0 | AN15: =AN14 -> 67 | AO15: =(AN15/100)*3000 -> 2010 | AP15: =AP14 -> 55 | AQ15: =(AP15/100)*3000 -> 1650 | AR15: =AR14 -> 61 | AS15: =(AR15/100)*3000 -> 1830 | AT15: =SUM(AO15+AQ15+AS15) -> 5490 | AU15: =AT14-AT15+AV15 -> 0 | AX15: =IF(AV15>0,AW15,AX14) -> 0.8
A16: =ELEC!C14 -> 44298 | B16: 200 | C16: 207 | D16: =C15-C16 -> 6 | E16: =D16*8.38 -> 50.28 | F16: 1813 | G16: =F16-F15 -> 4 | H16: 11248 | I16: =SUM(H16-H15) -> 250 | J16: =IF(G16>0,I16/G16,0) -> 62.5 | K16: =K15 -> 2302 | L16: =K16-K15 -> 0 | M16: =M15 -> 169624 | N16: =M16-M15 -> 0 | O16: =O15 -> 1869 | P16: 2063 | Q16: 173666 | R16: =Q16-Q15 -> 117 | S16: =SUM(P16-P15) -> 2 | T16: =SUM(S16*$T$2) -> 0 | U16: =SUM(G16+L16+S16) -> 6 | V16: =R16+N16+I16:I16 -> 367 | W16: =SUM(V16/U16) -> 61.166667 | X16: =X15 -> 2465 | Y16: =X16-X15 -> 0 | Z16: =Z15 -> 138740 | AA16: =Z16-Z15 -> 0 | AB16: =SUM(Y16*$AB$2) -> 0 | AC16: =AC15 -> 1936 | AD16: =AC16-AC15 -> 0 | AE16: =AE15 -> 365520.8 | AF16: =AE16-AE15 -> 0 | AG16: =IF(AD16>0,AF16/AD16,0) -> 0 | AH16: =AF16+AA16 -> 0 | AI16: =SUM(AH16+V16) -> 367 | AJ16: =-tanks!AW17 -> 367 | AK16: =SUM(AJ16-AI16) -> 0 | AL16: =S16+L16+G16 -> 6 | AM16: =Y16+AD16 -> 0 | AN16: =AN15 -> 67 | AO16: =(AN16/100)*3000 -> 2010 | AP16: =AP15 -> 55 | AQ16: =(AP16/100)*3000 -> 1650 | AR16: =AR15 -> 61 | AS16: =(AR16/100)*3000 -> 1830 | AT16: =SUM(AO16+AQ16+AS16) -> 5490 | AU16: =AT15-AT16+AV16 -> 0 | AX16: =IF(AV16>0,AW16,AX15) -> 0.8
A17: =ELEC!C15 -> 44299 | B17: 195 | C17: 202 | D17: =C16-C17 -> 5 | E17: =D17*8.38 -> 41.9 | F17: 1814 | G17: =F17-F16 -> 1 | H17: 11361 | I17: =SUM(H17-H16) -> 113 | J17: =IF(G17>0,I17/G17,0) -> 113 | K17: 2305 | L17: 169842 | M17: =M16 -> 169624 | N17: =M17-M16 -> 0 | O17: =O16 -> 1869 | P17: =P16 -> 2063 | Q17: =Q16 -> 173666 | R17: =Q17-Q16 -> 0 | S17: =SUM(P17-P16) -> 0 | T17: =SUM(S17*$T$2) -> 0 | U17: =SUM(G17+L17+S17) -> 169843 | V17: =R17+N17+I17:I17 -> 113 | X17: =X16 -> 2465 | Y17: =X17-X16 -> 0 | Z17: =Z16 -> 138740 | AA17: =Z17-Z16 -> 0 | AB17: =SUM(Y17*$AB$2) -> 0 | AC17: =AC16 -> 1936 | AD17: =AC17-AC16 -> 0 | AE17: =AE16 -> 365520.8 | AF17: =AE17-AE16 -> 0 | AG17: =IF(AD17>0,AF17/AD17,0) -> 0 | AH17: =AF17+AA17 -> 0 | AI17: =SUM(AH17+V17) -> 113 | AJ17: =-tanks!AW18 -> 113 | AK17: =SUM(AJ17-AI17) -> 0 | AL17: =S17+L17+G17 -> 169843 | AM17: =Y17+AD17 -> 0 | AN17: =AN16 -> 67 | AO17: =(AN17/100)*3000 -> 2010 | AP17: =AP16 -> 55 | AQ17: =(AP17/100)*3000 -> 1650 | AR17: =AR16 -> 61 | AS17: =(AR17/100)*3000 -> 1830 | AT17: =SUM(AO17+AQ17+AS17) -> 5490 | AU17: =AT16-AT17+AV17 -> 0 | AX17: =IF(AV17>0,AW17,AX16) -> 0.8
A18: =ELEC!C16 -> 44300 | B18: 246 | C18: 252 | D18: =C17-C18 -> -50 | E18: =D18*8.38 -> -419 | F18: =F17 -> 1814 | G18: =F18-F17 -> 0 | H18: =H17 -> 11361 | I18: =SUM(H18-H17) -> 0 | J18: =IF(G18>0,I18/G18,0) -> 0 | K18: 2306 | L18: =K18-K17 -> 1 | M18: 169940 | N18: =M18-M17 -> 316 | O18: 1869 | P18: 2066 | Q18: 173941 | R18: =Q18-Q17 -> 275 | S18: =SUM(P18-P17) -> 3 | T18: =SUM(S18*$T$2) -> 0 | U18: =SUM(G18+L18+S18) -> 4 | V18: =R18+N18+I18:I18 -> 591 | X18: =X17 -> 2465 | Y18: =X18-X17 -> 0 | Z18: =Z17 -> 138740 | AA18: =Z18-Z17 -> 0 | AB18: =SUM(Y18*$AB$2) -> 0 | AC18: =AC17 -> 1936 | AD18: =AC18-AC17 -> 0 | AE18: =AE17 -> 365520.8 | AF18: =AE18-AE17 -> 0 | AG18: =IF(AD18>0,AF18/AD18,0) -> 0 | AH18: =AF18+AA18 -> 0 | AI18: =SUM(AH18+V18) -> 591 | AJ18: =-tanks!AW19 -> 591 | AK18: =SUM(AJ18-AI18) -> 0 | AL18: =S18+L18+G18 -> 4 | AM18: =Y18+AD18 -> 0 | AN18: =AN17 -> 67 | AO18: =(AN18/100)*3000 -> 2010 | AP18: =AP17 -> 55 | AQ18: =(AP18/100)*3000 -> 1650 | AR18: =AR17 -> 61 | AS18: =(AR18/100)*3000 -> 1830 | AT18: =SUM(AO18+AQ18+AS18) -> 5490 | AU18: =AT17-AT18+AV18 -> 0 | AX18: =IF(AV18>0,AW18,AX17) -> 0.8
A19: =ELEC!C17 -> 44301 | B19: 240 | C19: 247 | D19: =C18-C19 -> 5 | E19: =D19*8.38 -> 41.9 | F19: 1816 | G19: =F19-F18 -> 2 | H19: 11508 | I19: =SUM(H19-H18) -> 147 | J19: =IF(G19>0,I19/G19,0) -> 73.5 | K19: =K18 -> 2306 | L19: =K19-K18 -> 0 | M19: =M18 -> 169940 | N19: =M19-M18 -> 0 | O19: =O18 -> 1869 | P19: 2068 | Q19: 174085 | R19: =Q19-Q18 -> 144 | S19: =SUM(P19-P18) -> 2 | T19: =SUM(S19*$T$2) -> 0 | U19: =SUM(G19+L19+S19) -> 4 | V19: =R19+N19+I19:I19 -> 291 | X19: =X18 -> 2465 | Y19: =X19-X18 -> 0 | Z19: =Z18 -> 138740 | AA19: =Z19-Z18 -> 0 | AB19: =SUM(Y19*$AB$2) -> 0 | AC19: =AC18 -> 1936 | AD19: =AC19-AC18 -> 0 | AE19: =AE18 -> 365520.8 | AF19: =AE19-AE18 -> 0 | AG19: =IF(AD19>0,AF19/AD19,0) -> 0 | AH19: =AF19+AA19 -> 0 | AI19: =SUM(AH19+V19) -> 291 | AJ19: =-tanks!AW20 -> 291 | AK19: =SUM(AJ19-AI19) -> 0 | AL19: =S19+L19+G19 -> 4 | AM19: =Y19+AD19 -> 0 | AN19: =AN18 -> 67 | AO19: =(AN19/100)*3000 -> 2010 | AP19: =AP18 -> 55 | AQ19: =(AP19/100)*3000 -> 1650 | AR19: =AR18 -> 61 | AS19: =(AR19/100)*3000 -> 1830 | AT19: =SUM(AO19+AQ19+AS19) -> 5490 | AU19: =AT18-AT19+AV19 -> 0 | AX19: =IF(AV19>0,AW19,AX18) -> 0.8
A20: =ELEC!C18 -> 44302 | B20: =B19 -> 240 | C20: =C19 -> 247 | D20: =C19-C20 -> 0 | E20: =D20*8.38 -> 0 | F20: =F19 -> 1816 | G20: =F20-F19 -> 0 | H20: =H19 -> 11508 | I20: =SUM(H20-H19) -> 0 | J20: =IF(G20>0,I20/G20,0) -> 0 | K20: =K19 -> 2306 | L20: =K20-K19 -> 0 | M20: =M19 -> 169940 | N20: =M20-M19 -> 0 | O20: =O19 -> 1869 | P20: =P19 -> 2068 | Q20: =Q19 -> 174085 | R20: =Q20-Q19 -> 0 | S20: =SUM(P20-P19) -> 0 | T20: =SUM(S20*$T$2) -> 0 | U20: =SUM(G20+L20+S20) -> 0 | V20: =R20+N20+I20:I20 -> 0 | X20: =X19 -> 2465 | Y20: =X20-X19 -> 0 | Z20: =Z19 -> 138740 | AA20: =Z20-Z19 -> 0 | AB20: =SUM(Y20*$AB$2) -> 0 | AC20: =AC19 -> 1936 | AD20: =AC20-AC19 -> 0 | AE20: =AE19 -> 365520.8 | AF20: =AE20-AE19 -> 0 | AG20: =IF(AD20>0,AF20/AD20,0) -> 0 | AH20: =AF20+AA20 -> 0 | AI20: =SUM(AH20+V20) -> 0 | AJ20: =-tanks!AW21 -> 0 | AK20: =SUM(AJ20-AI20) -> 0 | AL20: =S20+L20+G20 -> 0 | AM20: =Y20+AD20 -> 0 | AN20: =AN19 -> 67 | AO20: =(AN20/100)*3000 -> 2010 | AP20: =AP19 -> 55 | AQ20: =(AP20/100)*3000 -> 1650 | AR20: =AR19 -> 61 | AS20: =(AR20/100)*3000 -> 1830 | AT20: =SUM(AO20+AQ20+AS20) -> 5490 | AU20: =AT19-AT20+AV20 -> 0 | AX20: =IF(AV20>0,AW20,AX19) -> 0.8
A21: =ELEC!C19 -> 44303 | B21: =B20 -> 240 | C21: =C20 -> 247 | D21: =C20-C21 -> 0 | E21: =D21*8.38 -> 0 | F21: =F20 -> 1816 | G21: =F21-F20 -> 0 | H21: =H20 -> 11508 | I21: =SUM(H21-H20) -> 0 | J21: =IF(G21>0,I21/G21,0) -> 0 | K21: =K20 -> 2306 | L21: =K21-K20 -> 0 | M21: =M20 -> 169940 | N21: =M21-M20 -> 0 | O21: =O20 -> 1869 | P21: =P20 -> 2068 | Q21: =Q20 -> 174085 | R21: =Q21-Q20 -> 0 | S21: =SUM(P21-P20) -> 0 | T21: =SUM(S21*$T$2) -> 0 | U21: =SUM(G21+L21+S21) -> 0 | V21: =R21+N21+I21:I21 -> 0 | X21: =X20 -> 2465 | Y21: =X21-X20 -> 0 | Z21: =Z20 -> 138740 | AA21: =Z21-Z20 -> 0 | AB21: =SUM(Y21*$AB$2) -> 0 | AC21: =AC20 -> 1936 | AD21: =AC21-AC20 -> 0 | AE21: =AE20 -> 365520.8 | AF21: =AE21-AE20 -> 0 | AG21: =IF(AD21>0,AF21/AD21,0) -> 0 | AH21: =AF21+AA21 -> 0 | AI21: =SUM(AH21+V21) -> 0 | AJ21: =-tanks!AW22 -> 0 | AK21: =SUM(AJ21-AI21) -> 0 | AL21: =S21+L21+G21 -> 0 | AM21: =Y21+AD21 -> 0 | AN21: =AN20 -> 67 | AO21: =(AN21/100)*3000 -> 2010 | AP21: =AP20 -> 55 | AQ21: =(AP21/100)*3000 -> 1650 | AR21: =AR20 -> 61 | AS21: =(AR21/100)*3000 -> 1830 | AT21: =SUM(AO21+AQ21+AS21) -> 5490 | AU21: =AT20-AT21+AV21 -> 0 | AX21: =IF(AV21>0,AW21,AX20) -> 0.8
A22: =ELEC!C20 -> 44304 | B22: =B21 -> 240 | C22: =C21 -> 247 | D22: =C21-C22 -> 0 | E22: =D22*8.38 -> 0 | F22: =F21 -> 1816 | G22: =F22-F21 -> 0 | H22: =H21 -> 11508 | I22: =SUM(H22-H21) -> 0 | J22: =IF(G22>0,I22/G22,0) -> 0 | K22: =K21 -> 2306 | L22: =K22-K21 -> 0 | M22: =M21 -> 169940 | N22: =M22-M21 -> 0 | O22: =O21 -> 1869 | P22: =P21 -> 2068 | Q22: =Q21 -> 174085 | R22: =Q22-Q21 -> 0 | S22: =SUM(P22-P21) -> 0 | T22: =SUM(S22*$T$2) -> 0 | U22: =SUM(G22+L22+S22) -> 0 | V22: =R22+N22+I22:I22 -> 0 | X22: =X21 -> 2465 | Y22: =X22-X21 -> 0 | Z22: =Z21 -> 138740 | AA22: =Z22-Z21 -> 0 | AB22: =SUM(Y22*$AB$2) -> 0 | AC22: =AC21 -> 1936 | AD22: =AC22-AC21 -> 0 | AE22: =AE21 -> 365520.8 | AF22: =AE22-AE21 -> 0 | AG22: =IF(AD22>0,AF22/AD22,0) -> 0 | AH22: =AF22+AA22 -> 0 | AI22: =SUM(AH22+V22) -> 0 | AJ22: =-tanks!AW23 -> 0 | AK22: =SUM(AJ22-AI22) -> 0 | AL22: =S22+L22+G22 -> 0 | AM22: =Y22+AD22 -> 0 | AN22: =AN21 -> 67 | AO22: =(AN22/100)*3000 -> 2010 | AP22: =AP21 -> 55 | AQ22: =(AP22/100)*3000 -> 1650 | AR22: =AR21 -> 61 | AS22: =(AR22/100)*3000 -> 1830 | AT22: =SUM(AO22+AQ22+AS22) -> 5490 | AU22: =AT21-AT22+AV22 -> 0 | AX22: =IF(AV22>0,AW22,AX21) -> 0.8
A23: =ELEC!C21 -> 44305 | B23: =B22 -> 240 | C23: =C22 -> 247 | D23: =C22-C23 -> 0 | E23: =D23*8.38 -> 0 | F23: =F22 -> 1816 | G23: =F23-F22 -> 0 | H23: =H22 -> 11508 | I23: =SUM(H23-H22) -> 0 | J23: =IF(G23>0,I23/G23,0) -> 0 | K23: =K22 -> 2306 | L23: =K23-K22 -> 0 | M23: =M22 -> 169940 | N23: =M23-M22 -> 0 | O23: =O22 -> 1869 | P23: =P22 -> 2068 | Q23: =Q22 -> 174085 | R23: =Q23-Q22 -> 0 | S23: =SUM(P23-P22) -> 0 | T23: =SUM(S23*$T$2) -> 0 | U23: =SUM(G23+L23+S23) -> 0 | V23: =R23+N23+I23:I23 -> 0 | X23: =X22 -> 2465 | Y23: =X23-X22 -> 0 | Z23: =Z22 -> 138740 | AA23: =Z23-Z22 -> 0 | AB23: =SUM(Y23*$AB$2) -> 0 | AC23: =AC22 -> 1936 | AD23: =AC23-AC22 -> 0 | AE23: =AE22 -> 365520.8 | AF23: =AE23-AE22 -> 0 | AG23: =IF(AD23>0,AF23/AD23,0) -> 0 | AH23: =AF23+AA23 -> 0 | AI23: =SUM(AH23+V23) -> 0 | AJ23: =-tanks!AW24 -> 0 | AK23: =SUM(AJ23-AI23) -> 0 | AL23: =S23+L23+G23 -> 0 | AM23: =Y23+AD23 -> 0 | AN23: =AN22 -> 67 | AO23: =(AN23/100)*3000 -> 2010 | AP23: =AP22 -> 55 | AQ23: =(AP23/100)*3000 -> 1650 | AR23: =AR22 -> 61 | AS23: =(AR23/100)*3000 -> 1830 | AT23: =SUM(AO23+AQ23+AS23) -> 5490 | AU23: =AT22-AT23+AV23 -> 0 | AX23: =IF(AV23>0,AW23,AX22) -> 0.8
A24: =ELEC!C22 -> 44306 | B24: =B23 -> 240 | C24: =C23 -> 247 | D24: =C23-C24 -> 0 | E24: =D24*8.38 -> 0 | F24: =F23 -> 1816 | G24: =F24-F23 -> 0 | H24: =H23 -> 11508 | I24: =SUM(H24-H23) -> 0 | J24: =IF(G24>0,I24/G24,0) -> 0 | K24: =K23 -> 2306 | L24: =K24-K23 -> 0 | M24: =M23 -> 169940 | N24: =M24-M23 -> 0 | O24: =O23 -> 1869 | P24: =P23 -> 2068 | Q24: =Q23 -> 174085 | R24: =Q24-Q23 -> 0 | S24: =SUM(P24-P23) -> 0 | T24: =SUM(S24*$T$2) -> 0 | U24: =SUM(G24+L24+S24) -> 0 | V24: =R24+N24+I24:I24 -> 0 | X24: =X23 -> 2465 | Y24: =X24-X23 -> 0 | Z24: =Z23 -> 138740 | AA24: =Z24-Z23 -> 0 | AB24: =SUM(Y24*$AB$2) -> 0 | AC24: =AC23 -> 1936 | AD24: =AC24-AC23 -> 0 | AE24: =AE23 -> 365520.8 | AF24: =AE24-AE23 -> 0 | AG24: =IF(AD24>0,AF24/AD24,0) -> 0 | AH24: =AF24+AA24 -> 0 | AI24: =SUM(AH24+V24) -> 0 | AJ24: =-tanks!AW25 -> 0 | AK24: =SUM(AJ24-AI24) -> 0 | AL24: =S24+L24+G24 -> 0 | AM24: =Y24+AD24 -> 0 | AN24: =AN23 -> 67 | AO24: =(AN24/100)*3000 -> 2010 | AP24: =AP23 -> 55 | AQ24: =(AP24/100)*3000 -> 1650 | AR24: =AR23 -> 61 | AS24: =(AR24/100)*3000 -> 1830 | AT24: =SUM(AO24+AQ24+AS24) -> 5490 | AU24: =AT23-AT24+AV24 -> 0 | AX24: =IF(AV24>0,AW24,AX23) -> 0.8
A25: =ELEC!C23 -> 44307 | B25: =B24 -> 240 | C25: =C24 -> 247 | D25: =C24-C25 -> 0 | E25: =D25*8.38 -> 0 | F25: =F24 -> 1816 | G25: =F25-F24 -> 0 | H25: =H24 -> 11508 | I25: =SUM(H25-H24) -> 0 | J25: =IF(G25>0,I25/G25,0) -> 0 | K25: =K24 -> 2306 | L25: =K25-K24 -> 0 | M25: =M24 -> 169940 | N25: =M25-M24 -> 0 | O25: =O24 -> 1869 | P25: =P24 -> 2068 | Q25: =Q24 -> 174085 | R25: =Q25-Q24 -> 0 | S25: =SUM(P25-P24) -> 0 | T25: =SUM(S25*$T$2) -> 0 | U25: =SUM(G25+L25+S25) -> 0 | V25: =R25+N25+I25:I25 -> 0 | X25: =X24 -> 2465 | Y25: =X25-X24 -> 0 | Z25: =Z24 -> 138740 | AA25: =Z25-Z24 -> 0 | AB25: =SUM(Y25*$AB$2) -> 0 | AC25: =AC24 -> 1936 | AD25: =AC25-AC24 -> 0 | AE25: =AE24 -> 365520.8 | AF25: =AE25-AE24 -> 0 | AG25: =IF(AD25>0,AF25/AD25,0) -> 0 | AH25: =AF25+AA25 -> 0 | AI25: =SUM(AH25+V25) -> 0 | AJ25: =-tanks!AW26 -> 0 | AK25: =SUM(AJ25-AI25) -> 0 | AL25: =S25+L25+G25 -> 0 | AM25: =Y25+AD25 -> 0 | AN25: =AN24 -> 67 | AO25: =(AN25/100)*3000 -> 2010 | AP25: =AP24 -> 55 | AQ25: =(AP25/100)*3000 -> 1650 | AR25: =AR24 -> 61 | AS25: =(AR25/100)*3000 -> 1830 | AT25: =SUM(AO25+AQ25+AS25) -> 5490 | AU25: =AT24-AT25+AV25 -> 0 | AX25: =IF(AV25>0,AW25,AX24) -> 0.8
A26: =ELEC!C24 -> 44308 | B26: =B25 -> 240 | C26: =C25 -> 247 | D26: =C25-C26 -> 0 | E26: =D26*8.38 -> 0 | F26: =F25 -> 1816 | G26: =F26-F25 -> 0 | H26: =H25 -> 11508 | I26: =SUM(H26-H25) -> 0 | J26: =IF(G26>0,I26/G26,0) -> 0 | K26: =K25 -> 2306 | L26: =K26-K25 -> 0 | M26: =M25 -> 169940 | N26: =M26-M25 -> 0 | O26: =O25 -> 1869 | P26: =P25 -> 2068 | Q26: =Q25 -> 174085 | R26: =Q26-Q25 -> 0 | S26: =SUM(P26-P25) -> 0 | T26: =SUM(S26*$T$2) -> 0 | U26: =SUM(G26+L26+S26) -> 0 | V26: =R26+N26+I26:I26 -> 0 | X26: =X25 -> 2465 | Y26: =X26-X25 -> 0 | Z26: =Z25 -> 138740 | AA26: =Z26-Z25 -> 0 | AB26: =SUM(Y26*$AB$2) -> 0 | AC26: =AC25 -> 1936 | AD26: =AC26-AC25 -> 0 | AE26: =AE25 -> 365520.8 | AF26: =AE26-AE25 -> 0 | AG26: =IF(AD26>0,AF26/AD26,0) -> 0 | AH26: =AF26+AA26 -> 0 | AI26: =SUM(AH26+V26) -> 0 | AJ26: =-tanks!AW27 -> 0 | AK26: =SUM(AJ26-AI26) -> 0 | AL26: =S26+L26+G26 -> 0 | AM26: =Y26+AD26 -> 0 | AN26: =AN25 -> 67 | AO26: =(AN26/100)*3000 -> 2010 | AP26: =AP25 -> 55 | AQ26: =(AP26/100)*3000 -> 1650 | AR26: =AR25 -> 61 | AS26: =(AR26/100)*3000 -> 1830 | AT26: =SUM(AO26+AQ26+AS26) -> 5490 | AU26: =AT25-AT26+AV26 -> 0 | AX26: =IF(AV26>0,AW26,AX25) -> 0.8
A27: =ELEC!C25 -> 44309 | B27: =B26 -> 240 | C27: =C26 -> 247 | D27: =C26-C27 -> 0 | E27: =D27*8.38 -> 0 | F27: =F26 -> 1816 | G27: =F27-F26 -> 0 | H27: =H26 -> 11508 | I27: =SUM(H27-H26) -> 0 | J27: =IF(G27>0,I27/G27,0) -> 0 | K27: =K26 -> 2306 | L27: =K27-K26 -> 0 | M27: =M26 -> 169940 | N27: =M27-M26 -> 0 | O27: =O26 -> 1869 | P27: =P26 -> 2068 | Q27: =Q26 -> 174085 | R27: =Q27-Q26 -> 0 | S27: =SUM(P27-P26) -> 0 | T27: =SUM(S27*$T$2) -> 0 | U27: =SUM(G27+L27+S27) -> 0 | V27: =R27+N27+I27:I27 -> 0 | X27: =X26 -> 2465 | Y27: =X27-X26 -> 0 | Z27: =Z26 -> 138740 | AA27: =Z27-Z26 -> 0 | AB27: =SUM(Y27*$AB$2) -> 0 | AC27: =AC26 -> 1936 | AD27: =AC27-AC26 -> 0 | AE27: =AE26 -> 365520.8 | AF27: =AE27-AE26 -> 0 | AG27: =IF(AD27>0,AF27/AD27,0) -> 0 | AH27: =AF27+AA27 -> 0 | AI27: =SUM(AH27+V27) -> 0 | AJ27: =-tanks!AW28 -> 0 | AK27: =SUM(AJ27-AI27) -> 0 | AL27: =S27+L27+G27 -> 0 | AM27: =Y27+AD27 -> 0 | AN27: =AN26 -> 67 | AO27: =(AN27/100)*3000 -> 2010 | AP27: =AP26 -> 55 | AQ27: =(AP27/100)*3000 -> 1650 | AR27: =AR26 -> 61 | AS27: =(AR27/100)*3000 -> 1830 | AT27: =SUM(AO27+AQ27+AS27) -> 5490 | AU27: =AT26-AT27+AV27 -> 0 | AX27: =IF(AV27>0,AW27,AX26) -> 0.8
A28: =ELEC!C26 -> 44310 | B28: =B27 -> 240 | C28: =C27 -> 247 | D28: =C27-C28 -> 0 | E28: =D28*8.38 -> 0 | F28: =F27 -> 1816 | G28: =F28-F27 -> 0 | H28: =H27 -> 11508 | I28: =SUM(H28-H27) -> 0 | J28: =IF(G28>0,I28/G28,0) -> 0 | K28: =K27 -> 2306 | L28: =K28-K27 -> 0 | M28: =M27 -> 169940 | N28: =M28-M27 -> 0 | O28: =O27 -> 1869 | P28: =P27 -> 2068 | Q28: =Q27 -> 174085 | R28: =Q28-Q27 -> 0 | S28: =SUM(P28-P27) -> 0 | T28: =SUM(S28*$T$2) -> 0 | U28: =SUM(G28+L28+S28) -> 0 | V28: =R28+N28+I28:I28 -> 0 | X28: =X27 -> 2465 | Y28: =X28-X27 -> 0 | Z28: =Z27 -> 138740 | AA28: =Z28-Z27 -> 0 | AB28: =SUM(Y28*$AB$2) -> 0 | AC28: =AC27 -> 1936 | AD28: =AC28-AC27 -> 0 | AE28: =AE27 -> 365520.8 | AF28: =AE28-AE27 -> 0 | AG28: =IF(AD28>0,AF28/AD28,0) -> 0 | AH28: =AF28+AA28 -> 0 | AI28: =SUM(AH28+V28) -> 0 | AJ28: =-tanks!AW29 -> 0 | AK28: =SUM(AJ28-AI28) -> 0 | AL28: =S28+L28+G28 -> 0 | AM28: =Y28+AD28 -> 0 | AN28: =AN27 -> 67 | AO28: =(AN28/100)*3000 -> 2010 | AP28: =AP27 -> 55 | AQ28: =(AP28/100)*3000 -> 1650 | AR28: =AR27 -> 61 | AS28: =(AR28/100)*3000 -> 1830 | AT28: =SUM(AO28+AQ28+AS28) -> 5490 | AU28: =AT27-AT28+AV28 -> 0 | AX28: =IF(AV28>0,AW28,AX27) -> 0.8
A29: =ELEC!C27 -> 44311 | B29: =B28 -> 240 | C29: =C28 -> 247 | D29: =C28-C29 -> 0 | E29: =D29*8.38 -> 0 | F29: =F28 -> 1816 | G29: =F29-F28 -> 0 | H29: =H28 -> 11508 | I29: =SUM(H29-H28) -> 0 | J29: =IF(G29>0,I29/G29,0) -> 0 | K29: =K28 -> 2306 | L29: =K29-K28 -> 0 | M29: =M28 -> 169940 | N29: =M29-M28 -> 0 | O29: =O28 -> 1869 | P29: =P28 -> 2068 | Q29: =Q28 -> 174085 | R29: =Q29-Q28 -> 0 | S29: =SUM(P29-P28) -> 0 | T29: =SUM(S29*$T$2) -> 0 | U29: =SUM(G29+L29+S29) -> 0 | V29: =R29+N29+I29:I29 -> 0 | X29: =X28 -> 2465 | Y29: =X29-X28 -> 0 | Z29: =Z28 -> 138740 | AA29: =Z29-Z28 -> 0 | AB29: =SUM(Y29*$AB$2) -> 0 | AC29: =AC28 -> 1936 | AD29: =AC29-AC28 -> 0 | AE29: =AE28 -> 365520.8 | AF29: =AE29-AE28 -> 0 | AG29: =IF(AD29>0,AF29/AD29,0) -> 0 | AH29: =AF29+AA29 -> 0 | AI29: =SUM(AH29+V29) -> 0 | AJ29: =-tanks!AW30 -> 0 | AK29: =SUM(AJ29-AI29) -> 0 | AL29: =S29+L29+G29 -> 0 | AM29: =Y29+AD29 -> 0 | AN29: =AN28 -> 67 | AO29: =(AN29/100)*3000 -> 2010 | AP29: =AP28 -> 55 | AQ29: =(AP29/100)*3000 -> 1650 | AR29: =AR28 -> 61 | AS29: =(AR29/100)*3000 -> 1830 | AT29: =SUM(AO29+AQ29+AS29) -> 5490 | AU29: =AT28-AT29+AV29 -> 0 | AX29: =IF(AV29>0,AW29,AX28) -> 0.8
A30: =ELEC!C28 -> 44312 | B30: =B29 -> 240 | C30: =C29 -> 247 | D30: =C29-C30 -> 0 | E30: =D30*8.38 -> 0 | F30: =F29 -> 1816 | G30: =F30-F29 -> 0 | H30: =H29 -> 11508 | I30: =SUM(H30-H29) -> 0 | J30: =IF(G30>0,I30/G30,0) -> 0 | K30: =K29 -> 2306 | L30: =K30-K29 -> 0 | M30: =M29 -> 169940 | N30: =M30-M29 -> 0 | O30: =O29 -> 1869 | P30: =P29 -> 2068 | Q30: =Q29 -> 174085 | R30: =Q30-Q29 -> 0 | S30: =SUM(P30-P29) -> 0 | T30: =SUM(S30*$T$2) -> 0 | U30: =SUM(G30+L30+S30) -> 0 | V30: =R30+N30+I30:I30 -> 0 | X30: =X29 -> 2465 | Y30: =X30-X29 -> 0 | Z30: =Z29 -> 138740 | AA30: =Z30-Z29 -> 0 | AB30: =SUM(Y30*$AB$2) -> 0 | AC30: =AC29 -> 1936 | AD30: =AC30-AC29 -> 0 | AE30: =AE29 -> 365520.8 | AF30: =AE30-AE29 -> 0 | AG30: =IF(AD30>0,AF30/AD30,0) -> 0 | AH30: =AF30+AA30 -> 0 | AI30: =SUM(AH30+V30) -> 0 | AJ30: =-tanks!AW31 -> 0 | AK30: =SUM(AJ30-AI30) -> 0 | AL30: =S30+L30+G30 -> 0 | AM30: =Y30+AD30 -> 0 | AN30: =AN29 -> 67 | AO30: =(AN30/100)*3000 -> 2010 | AP30: =AP29 -> 55 | AQ30: =(AP30/100)*3000 -> 1650 | AR30: =AR29 -> 61 | AS30: =(AR30/100)*3000 -> 1830 | AT30: =SUM(AO30+AQ30+AS30) -> 5490 | AU30: =AT29-AT30+AV30 -> 0 | AX30: =IF(AV30>0,AW30,AX29) -> 0.8
A31: =ELEC!C29 -> 44313 | B31: =B30 -> 240 | C31: =C30 -> 247 | D31: =C30-C31 -> 0 | E31: =D31*8.38 -> 0 | F31: =F30 -> 1816 | G31: =F31-F30 -> 0 | H31: =H30 -> 11508 | I31: =SUM(H31-H30) -> 0 | J31: =IF(G31>0,I31/G31,0) -> 0 | K31: =K30 -> 2306 | L31: =K31-K30 -> 0 | M31: =M30 -> 169940 | N31: =M31-M30 -> 0 | O31: =O30 -> 1869 | P31: =P30 -> 2068 | Q31: =Q30 -> 174085 | R31: =Q31-Q30 -> 0 | S31: =SUM(P31-P30) -> 0 | T31: =SUM(S31*$T$2) -> 0 | U31: =SUM(G31+L31+S31) -> 0 | V31: =R31+N31+I31:I31 -> 0 | X31: =X30 -> 2465 | Y31: =X31-X30 -> 0 | Z31: =Z30 -> 138740 | AA31: =Z31-Z30 -> 0 | AB31: =SUM(Y31*$AB$2) -> 0 | AC31: =AC30 -> 1936 | AD31: =AC31-AC30 -> 0 | AE31: =AE30 -> 365520.8 | AF31: =AE31-AE30 -> 0 | AG31: =IF(AD31>0,AF31/AD31,0) -> 0 | AH31: =AF31+AA31 -> 0 | AI31: =SUM(AH31+V31) -> 0 | AJ31: =-tanks!AW32 -> 0 | AK31: =SUM(AJ31-AI31) -> 0 | AL31: =S31+L31+G31 -> 0 | AM31: =Y31+AD31 -> 0 | AN31: =AN30 -> 67 | AO31: =(AN31/100)*3000 -> 2010 | AP31: =AP30 -> 55 | AQ31: =(AP31/100)*3000 -> 1650 | AR31: =AR30 -> 61 | AS31: =(AR31/100)*3000 -> 1830 | AT31: =SUM(AO31+AQ31+AS31) -> 5490 | AU31: =AT30-AT31+AV31 -> 0 | AX31: =IF(AV31>0,AW31,AX30) -> 0.8
... A34: =ELEC!C32 -> 44316 | B34: =B33 -> 240 | C34: =C33 -> 247 | D34: =C33-C34 -> 0 | E34: =D34*8.38 -> 0 | F34: =F33 -> 1816 | G34: =F34-F33 -> 0 | H34: =H33 -> 11508 | I34: =SUM(H34-H33) -> 0 | J34: =IF(G34>0,I34/G34,0) -> 0 | K34: =K33 -> 2306 | L34: =K34-K33 -> 0 | M34: =M33 -> 169940 | N34: =M34-M33 -> 0 | O34: =O33 -> 1869 | P34: =P33 -> 2068 | Q34: =Q33 -> 174085 | R34: =Q34-Q33 -> 0 | S34: =SUM(P34-P33) -> 0 | T34: =SUM(S34*$T$2) -> 0 | U34: =SUM(G34+L34+S34) -> 0 | V34: =R34+N34+I34:I34 -> 0 | X34: =X33 -> 2465 | Y34: =X34-X33 -> 0 | Z34: =Z33 -> 138740 | AA34: =Z34-Z33 -> 0 | AB34: =SUM(Y34*$AB$2) -> 0 | AC34: =AC33 -> 1936 | AD34: =AC34-AC33 -> 0 | AE34: =AE33 -> 365520.8 | AF34: =AE34-AE33 -> 0 | AG34: =IF(AD34>0,AF34/AD34,0) -> 0 | AH34: =AF34+AA34 -> 0 | AI34: =SUM(AH34+V34) -> 0 | AJ34: =-tanks!AW35 -> 0 | AK34: =SUM(AJ34-AI34) -> 0 | AL34: =S34+L34+G34 -> 0 | AM34: =Y34+AD34 -> 0 | AN34: =AN33 -> 67 | AO34: =(AN34/100)*3000 -> 2010 | AP34: =AP33 -> 55 | AQ34: =(AP34/100)*3000 -> 1650 | AR34: =AR33 -> 61 | AS34: =(AR34/100)*3000 -> 1830 | AT34: =SUM(AO34+AQ34+AS34) -> 5490 | AU34: =AT33-AT34+AV34 -> 0 | AX34: =IF(AV34>0,AW34,AX33) -> 0.8
J36: =SUM(J5:J32)/(COUNT(J5:J32)-COUNTIF(J5:J32,0)) -> 76.183333 | V36: =SUM(V5:V32) -> 4924 | AE36: . | AH36: =SUM(AH5:AH32) -> 190 | AL36: =SUM(AL5:AL32) -> 169903 | AM36: =SUM(AM5:AM32) -> 2 | AR36: Nb Delivery | AS36: =COUNT(AW5:AW32) -> 0 | AU36: =SUM(AU5:AU32) -> 0 | AV36: =SUM(AV5:AV32) -> 0 | AW36: =SUM(AW5:AW32)/AS36 -> #DIV/0!
AH37: =AF37+AA37 -> 0 | AI37: =SUM(AI5:AI32) -> 5114
AH38: =AF38+AA38 -> 0 | AU38: =AU36*0.51 -> 0 | AV38: =AV36/0.51 -> 0 | AW38: =SUM(AW5:AW32)/AS36 -> #DIV/0!
AV39: =AV36*0.51 -> 0

Sheet WATER
D1: =SUM(G21:G33) -> 8039993 | AR1: Entrance | AT1: Tank 1 | AV1: Tank 2
AR2: Level | AW2: Quantity CM3 | AZ2: Var
A3: Date | B3: Truck | C3: Truck M3/day | D3: N0. Trucks | F3: REQ. # of trucks | G3: City | H3: City/day | I3: Total water delivery | K3: SW | L3: Cosum SW/day | M3: RO Guest/ Liter | O3: RO K&L/ Liter | Q3: TOTAL RO Production | R3: RO 1 RH | S3: RO 2 RH | T3: RO water counter | U3: RO Cons m3 | V3: Steam Boiler | W3: Steam Boiler/day | X3: Softener Guest | Y3: Guest Sotf/day | Z3: Softener K&L | AA3: K&L Soft/Day | AB3: Fire Tank Level | AC3: Fire Tank Counter | AE3: Laundry Hot Water Counter | AF3: Hot Water Cons/day | AG3: Laundry Cold Water Counter | AH3: Cold Water Cons/day | AI3: Laundry Water Total Cons | AJ3: K&L Sotf/day | AK3: Guest / day | AL3: K&L /day | AM3: Avg Outside Temp | AN3: Banquet Activity | AR3: Date | AT3: MainI | AV3: Kitchen and Laundry | AX3: Guest | AY3: Main Tank | AZ3: Kitchen and Laundry | BA3: Guest | BB3: Kitchen and Laundry | BC3: Main | BD3: Guest | BE3: Total VAR | BF3: Hotel Consumption
E4: 1.66 | AN4: Ball R | AO4: Meeting | AP4: outlet | AT4: 180 | AV4: 220 | AX4: 580 | AY4: =SUM(AT4) -> 180 | AZ4: =SUM(AV4) -> 220 | BA4: =SUM(AX4) -> 580
A5: =ELEC!C2 -> 44286 | B5: =[3]WATER!B36 -> 109443 | C5: =[3]WATER!C36 -> 0 | D5: =[3]WATER!D36 -> 0 | E5: =[3]WATER!E36 -> 241.93548 | F5: =[3]WATER!F36 -> 0 | G5: =[3]WATER!G36 -> 618063 | H5: =[3]WATER!H36 -> 0 | I5: =[3]WATER!I36 -> 0 | ... BG5: =[3]WATER!BG36 -> -15.8
A6: =ELEC!C3 -> 44287 | B6: =B5 -> 109443 | C6: =B6-B5 -> 0 | D6: =C6/27 -> 0 | E6: =SUM((C6*$E$4)+(7500/'EDl log'!$A$36)) -> 250 | G6: =G5 -> 618063 | H6: =G6-G5 -> 0 | I6: =C6+H6 -> 0 | J6: =IF(I6>0,E6/I6,0) -> 0 | K6: ='Swimming Pool quality check '!H6 -> 6733 | L6: 0 | M6: =M5 -> 457.44 | N6: =SUM(M6-M5) -> 0 | O6: =O5 -> 529.52 | P6: =SUM(O6-O5) -> 0 | Q6: =P6+N6 -> 0 | T6: =T5 -> 5171 | U6: =SUM(T6-T5) -> 0 | V6: =V5 -> 469 | W6: =+V6-V5 -> 0 | X6: 151220 | Y6: =SUM(X6-X5) -> 0 | Z6: =Z5 -> 98697 | AA6: =Z6-Z5 -> 0 | AB6: =AB5 -> 261 | AC6: =AC5 -> 731 | AD6: 0 | AE6: =AE5 -> 229.03 | AF6: =AE6-AE5 -> 0 | AG6: 2199.36 | AH6: =AG6-AG5 -> 0.82 | AI6: =AF6+AH6 -> 0.82 | AJ6: =+Z6-Z5 -> 0 | AK6: =SUM(Y6-L6) -> 0 | AL6: =SUM(AJ6-W6) -> 0 | AM6: ='General information '!D6 -> 14.5 | AN6: ='General information '!H6 -> 0 | AP6: ='General information '!J6 -> 0 | AR6: =A6 -> 44287 | AS6: =AS5 -> 0.9 | AT6: 179 | AU6: =AU5 -> 1.1 | AV6: 187 | AW6: 2.9 | AX6: 172 | AY6: =AS6*AT6 -> 161.1 | AZ6: =AU6*AV6 -> 205.7 | BA6: =AW6*AX6 -> 498.8 | BB6: =AY6-AY5 -> 1.8 | BC6: =AZ6-AZ5 -> -3.3 | BD6: =BA6-BA5 -> -23.2 | BE6: =SUM(BB6:BD6) -> -24.7 | BF6: =SUM(I6-BE6) -> 24.7 | BG6: =SUM(I6-BF6) -> -24.7
A7: =ELEC!C4 -> 44288 | B7: =B6 -> 109443 | C7: =B7-B6 -> 0 | D7: =C7/27 -> 0 | E7: =SUM((C7*$E$4)+(7500/'EDl log'!$A$36)) -> 250 | G7: =G6 -> 618063 | H7: =G7-G6 -> 0 | I7: =C7+H7 -> 0 | J7: =IF(I7>0,E7/I7,0) -> 0 | K7: ='Swimming Pool quality check '!H7 -> 6733 | L7: =K7-K6 -> 0 | M7: =M6 -> 457.44 | N7: =SUM(M7-M6) -> 0 | O7: =O6 -> 529.52 | P7: =SUM(O7-O6) -> 0 | Q7: =P7+N7 -> 0 | T7: =T6 -> 5171 | U7: =SUM(T7-T6) -> 0 | V7: =V6 -> 469 | W7: =+V7-V6 -> 0 | X7: 151284 | Y7: =SUM(X7-X6) -> 64 | Z7: 98717 | AA7: =Z7-Z6 -> 20 | AB7: =AB6 -> 261 | AC7: =AC6 -> 731 | AD7: =AC7-AC6 -> 0 | AE7: =AE6 -> 229.03 | AF7: =AE7-AE6 -> 0 | AG7: =AG6 -> 2199.36 | AH7: =AG7-AG6 -> 0 | AI7: =AF7+AH7 -> 0 | AJ7: =+Z7-Z6 -> 20 | AK7: =SUM(Y7-L7) -> 64 | AL7: =SUM(AJ7-W7) -> 20 | AM7: ='General information '!D7 -> 13.5 | AN7: ='General information '!H7 -> 0 | AP7: ='General information '!J7 -> 0 | AR7: =A7 -> 44288 | AS7: =AS6 -> 0.9 | AT7: 90 | AU7: =AU6 -> 1.1 | AV7: 198 | AW7: 2.9 | AX7: 186 | AY7: =AS7*AT7 -> 81 | AZ7: =AU7*AV7 -> 217.8 | BA7: =AW7*AX7 -> 539.4 | BB7: =AY7-AY6 -> -80.1 | BC7: =AZ7-AZ6 -> 12.1 | BD7: =BA7-BA6 -> 40.6 | BE7: =SUM(BB7:BD7) -> -27.4 | BF7: =SUM(I7-BE7) -> 27.4 | BG7: =SUM(I7-BF7) -> -27.4
A8: =ELEC!C5 -> 44289 | B8: =B7 -> 109443 | C8: =B8-B7 -> 0 | D8: =C8/27 -> 0 | E8: =SUM((C8*$E$4)+(7500/'EDl log'!$A$36)) -> 250 | G8: =G7 -> 618063 | H8: =G8-G7 -> 0 | I8: =C8+H8 -> 0 | J8: =IF(I8>0,E8/I8,0) -> 0 | K8: ='Swimming Pool quality check '!H8 -> 6734 | L8: =K8-K7 -> 1 | M8: =M7 -> 457.44 | N8: =SUM(M8-M7) -> 0 | O8: =O7 -> 529.52 | P8: =SUM(O8-O7) -> 0 | Q8: =P8+N8 -> 0 | T8: =T7 -> 5171 | U8: =SUM(T8-T7) -> 0 | V8: =V7 -> 469 | W8: =+V8-V7 -> 0 | X8: =X7 -> 151284 | Y8: =SUM(X8-X7) -> 0 | Z8: 98717 | AA8: =Z8-Z7 -> 0 | AB8: =AB7 -> 261 | AC8: =AC7 -> 731 | AD8: =AC8-AC7 -> 0 | AE8: =AE7 -> 229.03 | AF8: =AE8-AE7 -> 0 | AG8: =AG7 -> 2199.36 | AH8: =AG8-AG7 -> 0 | AI8: =AF8+AH8 -> 0 | AJ8: =+Z8-Z7 -> 0 | AK8: =SUM(Y8-L8) -> -1 | AL8: =SUM(AJ8-W8) -> 0 | AM8: ='General information '!D8 -> 17 | AN8: ='General information '!H8 -> 0 | AP8: ='General information '!J8 -> 0 | AR8: =A8 -> 44289 | AS8: =AS7 -> 0.9 | AT8: =AT7 -> 90 | AU8: 1.1 | AV8: 196 | AW8: 2.9 | AX8: 185 | AY8: =AS8*AT8 -> 81 | AZ8: =AU8*AV8 -> 215.6 | BA8: =AW8*AX8 -> 536.5 | BB8: =AY8-AY7 -> 0 | BC8: =AZ8-AZ7 -> -2.2 | BD8: =BA8-BA7 -> -2.9 | BE8: =SUM(BB8:BD8) -> -5.1 | BF8: =SUM(I8-BE8) -> 5.1 | BG8: =SUM(I8-BF8) -> -5.1
A9: =ELEC!C6 -> 44290 | B9: =B8 -> 109443 | C9: =B9-B8 -> 0 | D9: =C9/27 -> 0 | E9: =SUM((C9*$E$4)+(7500/'EDl log'!$A$36)) -> 250 | G9: 618117 | H9: =G9-G8 -> 54 | I9: =C9+H9 -> 54 | J9: =IF(I9>0,E9/I9,0) -> 4.6296296 | K9: ='Swimming Pool quality check '!H9 -> 6736 | L9: =K9-K8 -> 2 | M9: =M8 -> 457.44 | N9: =SUM(M9-M8) -> 0 | O9: =O8 -> 529.52 | P9: =SUM(O9-O8) -> 0 | Q9: =P9+N9 -> 0 | T9: =T8 -> 5171 | U9: =SUM(T9-T8) -> 0 | V9: =V8 -> 469 | W9: =+V9-V8 -> 0 | X9: 151284 | Y9: =SUM(X9-X8) -> 0 | Z9: =Z8 -> 98717 | AA9: =Z9-Z8 -> 0 | AB9: =AB8 -> 261 | AC9: =AC8 -> 731 | AD9: =AC9-AC8 -> 0 | AE9: =AE8 -> 229.03 | AF9: =AE9-AE8 -> 0 | AG9: =AG8 -> 2199.36 | AH9: =AG9-AG8 -> 0 | AI9: =AF9+AH9 -> 0 | AJ9: =+Z9-Z8 -> 0 | AK9: =SUM(Y9-L9) -> -2 | AL9: =SUM(AJ9-W9) -> 0 | AM9: ='General information '!D9 -> 16.5 | AN9: ='General information '!H9 -> 0 | AP9: ='General information '!J9 -> 0 | AR9: =A9 -> 44290 | AS9: =AS8 -> 0.9 | AT9: 95 | AU9: =AU8 -> 1.1 | AV9: 185 | AW9: 2.9 | AX9: 182 | AY9: =AS9*AT9 -> 85.5 | AZ9: =AU9*AV9 -> 203.5 | BA9: =AW9*AX9 -> 527.8 | BB9: =AY9-AY8 -> 4.5 | BC9: =AZ9-AZ8 -> -12.1 | BD9: =BA9-BA8 -> -8.7 | BE9: =SUM(BB9:BD9) -> -16.3 | BF9: =SUM(I9-BE9) -> 70.3 | BG9: =SUM(I9-BF9) -> -16.3
A10: =ELEC!C7 -> 44291 | B10: =B9 -> 109443 | C10: =B10-B9 -> 0 | D10: =C10/27 -> 0 | E10: =SUM((C10*$E$4)+(7500/'EDl log'!$A$36)) -> 250 | G10: 618217 | H10: =G10-G9 -> 100 | I10: =C10+H10 -> 100 | J10: =IF(I10>0,E10/I10,0) -> 2.5 | K10: ='Swimming Pool quality check '!H10 -> 6736 | L10: =K10-K9 -> 0 | M10: =M9 -> 457.44 | N10: =SUM(M10-M9) -> 0 | O10: =O9 -> 529.52 | P10: =SUM(O10-O9) -> 0 | Q10: =P10+N10 -> 0 | T10: =T9 -> 5171 | U10: =SUM(T10-T9) -> 0 | V10: =V9 -> 469 | W10: =+V10-V9 -> 0 | X10: 151296 | Y10: =SUM(X10-X9) -> 12 | Z10: 98721 | AA10: =Z10-Z9 -> 4 | AB10: =AB9 -> 261 | AC10: =AC9 -> 731 | AD10: =AC10-AC9 -> 0 | AE10: =AE9 -> 229.03 | AF10: =AE10-AE9 -> 0 | AG10: =AG9 -> 2199.36 | AH10: =AG10-AG9 -> 0 | AI10: =AF10+AH10 -> 0 | AJ10: =+Z10-Z9 -> 4 | AK10: =SUM(Y10-L10) -> 12 | AL10: =SUM(AJ10-W10) -> 4 | AM10: ='General information '!D10 -> 17 | AN10: ='General information '!H10 -> 0 | AP10: ='General information '!J10 -> 0 | AR10: =A10 -> 44291 | AS10: =AS9 -> 0.9 | AT10: 148 | AU10: =AU9 -> 1.1 | AV10: 194 | AW10: 2.9 | AX10: 180 | AY10: =AS10*AT10 -> 133.2 | AZ10: =AU10*AV10 -> 213.4 | BA10: =AW10*AX10 -> 522 | BB10: =AY10-AY9 -> 47.7 | BC10: =AZ10-AZ9 -> 9.9 | BD10: =BA10-BA9 -> -5.8 | BE10: =SUM(BB10:BD10) -> 51.8 | BF10: =SUM(I10-BE10) -> 48.2 | BG10: =SUM(I10-BF10) -> 51.8
A11: =ELEC!C8 -> 44292 | B11: =B10 -> 109443 | C11: =B11-B10 -> 0 | D11: =C11/27 -> 0 | E11: =SUM((C11*$E$4)+(7500/'EDl log'!$A$36)) -> 250 | G11: =G10 -> 618217 | H11: =G11-G10 -> 0 | I11: =C11+H11 -> 0 | J11: =IF(I11>0,E11/I11,0) -> 0 | K11: ='Swimming Pool quality check '!H11 -> 6738 | L11: =K11-K10 -> 2 | M11: =M10 -> 457.44 | N11: =SUM(M11-M10) -> 0 | O11: =O10 -> 529.52 | P11: =SUM(O11-O10) -> 0 | Q11: =SUM(P11+N11) -> 0 | T11: =T10 -> 5171 | U11: =SUM(T11-T10) -> 0 | V11: =V10 -> 469 | W11: =+V11-V10 -> 0 | X11: =X10 -> 151296 | Y11: =SUM(X11-X10) -> 0 | Z11: =Z10 -> 98721 | AA11: =Z11-Z10 -> 0 | AB11: =AB10 -> 261 | AC11: =AC10 -> 731 | AD11: =AC11-AC10 -> 0 | AE11: =AE10 -> 229.03 | AF11: =AE11-AE10 -> 0 | AG11: =AG10 -> 2199.36 | AH11: =AG11-AG10 -> 0 | AI11: =AF11+AH11 -> 0 | AJ11: =+Z11-Z10 -> 0 | AK11: =SUM(Y11-L11) -> -2 | AL11: =SUM(AJ11-W11) -> 0 | AM11: ='General information '!D11 -> 22.5 | AN11: ='General information '!H11 -> 0 | AP11: ='General information '!J11 -> 0 | AR11: =A11 -> 44292 | AS11: =AS10 -> 0.9 | AT11: =AT10 -> 148 | AU11: =AU10 -> 1.1 | AV11: 191 | AW11: 2.9 | AX11: 174 | AY11: =AS11*AT11 -> 133.2 | AZ11: =AU11*AV11 -> 210.1 | BA11: =AW11*AX11 -> 504.6 | BB11: =AY11-AY10 -> 0 | BC11: =AZ11-AZ10 -> -3.3 | BD11: =BA11-BA10 -> -17.4 | BE11: =SUM(BB11:BD11) -> -20.7 | BF11: =SUM(I11-BE11) -> 20.7 | BG11: =SUM(I11-BF11) -> -20.7
A12: =ELEC!C9 -> 44293 | B12: =B11 -> 109443 | C12: =B12-B11 -> 0 | D12: =C12/27 -> 0 | E12: =SUM((C12*$E$4)+(7500/'EDl log'!$A$36)) -> 250 | G12: 618245 | H12: =G12-G11 -> 28 | I12: =C12+H12 -> 28 | J12: =IF(I12>0,E12/I12,0) -> 8.9285714 | K12: ='Swimming Pool quality check '!H12 -> 6738 | L12: =K12-K11 -> 0 | M12: =M11 -> 457.44 | N12: =SUM(M12-M11) -> 0 | O12: =O11 -> 529.52 | P12: =SUM(O12-O11) -> 0 | Q12: =SUM(P12+N12) -> 0 | T12: =T11 -> 5171 | U12: =SUM(T12-T11) -> 0 | V12: =V11 -> 469 | W12: =+V12-V11 -> 0 | X12: =X11 -> 151296 | Y12: =SUM(X12-X11) -> 0 | Z12: 98723 | AA12: =Z12-Z11 -> 2 | AB12: =AB11 -> 261 | AC12: =AC11 -> 731 | AD12: =AC12-AC11 -> 0 | AE12: =AE11 -> 229.03 | AF12: =AE12-AE11 -> 0 | AG12: =AG11 -> 2199.36 | AH12: =AG12-AG11 -> 0 | AI12: =AF12+AH12 -> 0 | AJ12: =+Z12-Z11 -> 2 | AK12: =SUM(Y12-L12) -> 0 | AL12: =SUM(AJ12-W12) -> 2 | AM12: ='General information '!D12 -> 21.5 | AN12: ='General information '!H12 -> 0 | AP12: ='General information '!J12 -> 0 | AR12: =A12 -> 44293 | AS12: =AS11 -> 0.9 | AT12: 172 | AU12: =AU11 -> 1.1 | AV12: 193 | AW12: 2.9 | AX12: 172 | AY12: =AS12*AT12 -> 154.8 | AZ12: =AU12*AV12 -> 212.3 | BA12: =AW12*AX12 -> 498.8 | BB12: =AY12-AY11 -> 21.6 | BC12: =AZ12-AZ11 -> 2.2 | BD12: =BA12-BA11 -> -5.8 | BE12: =SUM(BB12:BD12) -> 18 | BF12: =SUM(I12-BE12) -> 10 | BG12: =SUM(I12-BF12) -> 18
A13: =ELEC!C10 -> 44294 | B13: =B12 -> 109443 | C13: =B13-B12 -> 0 | D13: =C13/27 -> 0 | E13: =SUM((C13*$E$4)+(7500/'EDl log'!$A$36)) -> 250 | G13: =G12 -> 618245 | H13: =G13-G12 -> 0 | I13: =C13+H13 -> 0 | J13: =IF(I13>0,E13/I13,0) -> 0 | K13: ='Swimming Pool quality check '!H13 -> 6738 | L13: =K13-K12 -> 0 | M13: =M12 -> 457.44 | N13: =SUM(M13-M12) -> 0 | O13: =O12 -> 529.52 | P13: =SUM(O13-O12) -> 0 | Q13: =SUM(P13+N13) -> 0 | T13: =T12 -> 5171 | U13: =SUM(T13-T12) -> 0 | V13: 470 | W13: =+V13-V12 -> 1 | X13: 151398 | Y13: =SUM(X13-X12) -> 102 | Z13: 98760 | AA13: =Z13-Z12 -> 37 | AB13: =AB12 -> 261 | AC13: =AC12 -> 731 | AD13: =AC13-AC12 -> 0 | AE13: =AE12 -> 229.03 | AF13: =AE13-AE12 -> 0 | AG13: =AG12 -> 2199.36 | AH13: =AG13-AG12 -> 0 | AI13: =AF13+AH13 -> 0 | AJ13: =+Z13-Z12 -> 37 | AK13: =SUM(Y13-L13) -> 102 | AL13: =SUM(AJ13-W13) -> 36 | AM13: ='General information '!D13 -> 18.5 | AN13: ='General information '!J13 -> 0 | AP13: ='General information '!J13 -> 0 | AR13: =A13 -> 44294 | AS13: =AS12 -> 0.9 | AT13: 38 | AU13: =AU12 -> 1.1 | AV13: 202 | AW13: 2.9 | AX13: 194 | AY13: =AS13*AT13 -> 34.2 | AZ13: =AU13*AV13 -> 222.2 | BA13: =AW13*AX13 -> 562.6 | BB13: =AY13-AY12 -> -120.6 | BC13: =AZ13-AZ12 -> 9.9 | BD13: =BA13-BA12 -> 63.8 | BE13: =SUM(BB13:BD13) -> -46.9 | BF13: =SUM(I13-BE13) -> 46.9 | BG13: =SUM(I13-BF13) -> -46.9
A14: =ELEC!C11 -> 44295 | B14: =B13 -> 109443 | C14: =B14-B13 -> 0 | D14: =C14/27 -> 0 | E14: =SUM((C14*$E$4)+(7500/'EDl log'!$A$36)) -> 250 | G14: 618456 | H14: =G14-G13 -> 211 | I14: =C14+H14 -> 211 | J14: =IF(I14>0,E14/I14,0) -> 1.1848341 | K14: ='Swimming Pool quality check '!H14 -> 6738 | L14: =K14-K13 -> 0 | M14: =M13 -> 457.44 | N14: =SUM(M14-M13) -> 0 | O14: =O13 -> 529.52 | P14: =SUM(O14-O13) -> 0 | Q14: =SUM(P14+N14) -> 0 | T14: =T13 -> 5171 | U14: =SUM(T14-T13) -> 0 | V14: =V13 -> 470 | W14: =+V14-V13 -> 0 | X14: =X13 -> 151398 | Y14: =SUM(X14-X13) -> 0 | Z14: 98760 | AA14: =Z14-Z13 -> 0 | AB14: =AB13 -> 261 | AC14: =AC13 -> 731 | AD14: =AC14-AC13 -> 0 | AE14: =AE13 -> 229.03 | AF14: =AE14-AE13 -> 0 | AG14: =AG13 -> 2199.36 | AH14: =AG14-AG13 -> 0 | AI14: =AF14+AH14 -> 0 | AJ14: =+Z14-Z13 -> 0 | AK14: =SUM(Y14-L14) -> 0 | AL14: =SUM(AJ14-W14) -> 0 | AM14: ='General information '!D14 -> 18 | AN14: ='General information '!H14 -> 0 | AP14: ='General information '!J14 -> 0 | AR14: =A14 -> 44295 | AS14: =AS13 -> 0.9 | AT14: 153 | AU14: =AU13 -> 1.1 | AV14: 200 | AW14: 2.9 | AX14: 190 | AY14: =AS14*AT14 -> 137.7 | AZ14: =AU14*AV14 -> 220 | BA14: =AW14*AX14 -> 551 | BB14: =AY14-AY13 -> 103.5 | BC14: =AZ14-AZ13 -> -2.2 | BD14: =BA14-BA13 -> -11.6 | BE14: =SUM(BB14:BD14) -> 89.7 | BF14: =SUM(I14-BE14) -> 121.3 | BG14: =SUM(I14-BF14) -> 89.7
A15: =ELEC!C12 -> 44296 | B15: =B14 -> 109443 | C15: =B15-B14 -> 0 | D15: =C15/27 -> 0 | E15: =SUM((C15*$E$4)+(7500/'EDl log'!$A$36)) -> 250 | G15: =G14 -> 618456 | H15: =G15-G14 -> 0 | I15: =C15+H15 -> 0 | J15: =IF(I15>0,E15/I15,0) -> 0 | K15: ='Swimming Pool quality check '!H15 -> 6738 | L15: =K15-K14 -> 0 | M15: =M14 -> 457.44 | N15: =SUM(M15-M14) -> 0 | O15: =O14 -> 529.52 | P15: =SUM(O15-O14) -> 0 | Q15: =SUM(P15+N15) -> 0 | T15: =T14 -> 5171 | U15: =SUM(T15-T14) -> 0 | V15: =V14 -> 470 | W15: =+V15-V14 -> 0 | X15: =X14 -> 151398 | Y15: =SUM(X15-X14) -> 0 | Z15: 98760 | AA15: =Z15-Z14 -> 0 | AB15: =AB14 -> 261 | AC15: =AC14 -> 731 | AD15: =AC15-AC14 -> 0 | AE15: 229.28 | AF15: =AE15-AE14 -> 0.25 | AG15: 2209.02 | AH15: =AG15-AG14 -> 9.66 | AI15: =AF15+AH15 -> 9.91 | AJ15: =+Z15-Z14 -> 0 | AK15: =SUM(Y15-L15) -> 0 | AL15: =SUM(AJ15-W15) -> 0 | AM15: ='General information '!D15 -> 15 | AN15: ='General information '!H15 -> 0 | AP15: ='General information '!J15 -> 0 | AR15: =A15 -> 44296 | AS15: =AS14 -> 0.9 | AT15: 5 | AU15: =AU14 -> 1.1 | AV15: 196 | AW15: 2.9 | AX15: 188 | AY15: =AS15*AT15 -> 4.5 | AZ15: =AU15*AV15 -> 215.6 | BA15: =AW15*AX15 -> 545.2 | BB15: =AY15-AY14 -> -133.2 | BC15: =AZ15-AZ14 -> -4.4 | BD15: =BA15-BA14 -> -5.8 | BE15: =SUM(BB15:BD15) -> -143.4 | BF15: =SUM(I15-BE15) -> 143.4 | BG15: =SUM(I15-BF15) -> -143.4
A16: =ELEC!C13 -> 44297 | B16: =B15 -> 109443 | C16: =B16-B15 -> 0 | D16: =C16/27 -> 0 | E16: =SUM((C16*$E$4)+(7500/'EDl log'!$A$36)) -> 250 | G16: 618461 | H16: =G16-G15 -> 5 | I16: =C16+H16 -> 5 | J16: =IF(I16>0,E16/I16,0) -> 50 | K16: ='Swimming Pool quality check '!H16 -> 6738 | L16: =K16-K15 -> 0 | M16: =M15 -> 457.44 | N16: =SUM(M16-M15) -> 0 | O16: =O15 -> 529.52 | P16: =SUM(O16-O15) -> 0 | Q16: =SUM(P16+N16) -> 0 | T16: =T15 -> 5171 | U16: =SUM(T16-T15) -> 0 | V16: =V15 -> 470 | W16: =+V16-V15 -> 0 | X16: =X15 -> 151398 | Y16: =SUM(X16-X15) -> 0 | Z16: 98760 | AA16: =Z16-Z15 -> 0 | AB16: =AB15 -> 261 | AC16: =AC15 -> 731 | AD16: =AC16-AC15 -> 0 | AE16: =AE15 -> 229.28 | AF16: =AE16-AE15 -> 0 | AG16: =AG15 -> 2209.02 | AH16: =AG16-AG15 -> 0 | AI16: =AF16+AH16 -> 0 | AJ16: =+Z16-Z15 -> 0 | AK16: =SUM(Y16-L16) -> 0 | AL16: =SUM(AJ16-W16) -> 0 | AM16: ='General information '!D16 -> 14.5 | AN16: ='General information '!H16 -> 0 | AP16: ='General information '!J16 -> 0 | AR16: =A16 -> 44297 | AS16: =AS15 -> 0.9 | AT16: 146 | AU16: =AU15 -> 1.1 | AV16: 190 | AW16: 2.9 | AX16: 186 | AY16: =AS16*AT16 -> 131.4 | AZ16: =AU16*AV16 -> 209 | BA16: =AW16*AX16 -> 539.4 | BB16: =AY16-AY15 -> 126.9 | BC16: =AZ16-AZ15 -> -6.6 | BD16: =BA16-BA15 -> -5.8 | BE16: =SUM(BB16:BD16) -> 114.5 | BF16: =SUM(I16-BE16) -> -109.5 | BG16: =SUM(I16-BF16) -> 114.5
A17: =ELEC!C14 -> 44298 | B17: =B16 -> 109443 | C17: =B17-B16 -> 0 | D17: =C17/27 -> 0 | E17: =SUM((C17*$E$4)+(7500/'EDl log'!$A$36)) -> 250 | G17: =G16 -> 618461 | H17: =G17-G16 -> 0 | I17: =C17+H17 -> 0 | J17: =IF(I17>0,E17/I17,0) -> 0 | K17: ='Swimming Pool quality check '!H17 -> 6738 | L17: =K17-K16 -> 0 | M17: =M16 -> 457.44 | N17: =SUM(M17-M16) -> 0 | O17: =O16 -> 529.52 | P17: =SUM(O17-O16) -> 0 | Q17: =SUM(P17+N17) -> 0 | T17: =T16 -> 5171 | U17: =SUM(T17-T16) -> 0 | V17: =V16 -> 470 | W17: =+V17-V16 -> 0 | X17: =X16 -> 151398 | Y17: =SUM(X17-X16) -> 0 | Z17: =Z16 -> 98760 | AA17: =Z17-Z16 -> 0 | AB17: =AB16 -> 261 | AC17: =AC16 -> 731 | AD17: =AC17-AC16 -> 0 | AE17: =AE16 -> 229.28 | AF17: =AE17-AE16 -> 0 | AG17: =AG16 -> 2209.02 | AH17: =AG17-AG16 -> 0 | AI17: =AF17+AH17 -> 0 | AJ17: =+Z17-Z16 -> 0 | AK17: =SUM(Y17-L17) -> 0 | AL17: =SUM(AJ17-W17) -> 0 | AM17: ='General information '!D17 -> 14.5 | AN17: ='General information '!H17 -> 0 | AP17: ='General information '!J17 -> 0 | AR17: =A17 -> 44298 | AS17: =AS16 -> 0.9 | AT17: =AT16 -> 146 | AU17: =AU16 -> 1.1 | AV17: 186 | AW17: 2.9 | AX17: 183 | AY17: =AS17*AT17 -> 131.4 | AZ17: =AU17*AV17 -> 204.6 | BA17: =AW17*AX17 -> 530.7 | BB17: =AY17-AY16 -> 0 | BC17: =AZ17-AZ16 -> -4.4 | BD17: =BA17-BA16 -> -8.7 | BE17: =SUM(BB17:BD17) -> -13.1 | BF17: =SUM(I17-BE17) -> 13.1 | BG17: =SUM(I17-BF17) -> -13.1
A18: =ELEC!C15 -> 44299 | B18: =B17 -> 109443 | C18: =B18-B17 -> 0 | D18: =C18/27 -> 0 | E18: =SUM((C18*$E$4)+(7500/'EDl log'!$A$36)) -> 250 | G18: =G17 -> 618461 | H18: =G18-G17 -> 0 | I18: =C18+H18 -> 0 | J18: =IF(I18>0,E18/I18,0) -> 0 | K18: ='Swimming Pool quality check '!H18 -> 6740 | L18: =K18-K17 -> 2 | M18: =M17 -> 457.44 | N18: =SUM(M18-M17) -> 0 | O18: =O17 -> 529.52 | P18: =SUM(O18-O17) -> 0 | Q18: =SUM(P18+N18) -> 0 | T18: =T17 -> 5171 | U18: =SUM(T18-T17) -> 0 | V18: =V17 -> 470 | W18: =+V18-V17 -> 0 | X18: =X17 -> 151398 | Y18: =SUM(X18-X17) -> 0 | Z18: =Z17 -> 98760 | AA18: =Z18-Z17 -> 0 | AB18: =AB17 -> 261 | AC18: =AC17 -> 731 | AD18: =AC18-AC17 -> 0 | AE18: =AE17 -> 229.28 | AF18: =AE18-AE17 -> 0 | AG18: =AG17 -> 2209.02 | AH18: =AG18-AG17 -> 0 | AI18: =AF18+AH18 -> 0 | AJ18: =+Z18-Z17 -> 0 | AK18: =SUM(Y18-L18) -> -2 | AL18: =SUM(AJ18-W18) -> 0 | AM18: ='General information '!D18 -> 14.5 | AN18: ='General information '!H18 -> 0 | AP18: ='General information '!J18 -> 0 | AR18: =A18 -> 44299 | AS18: =AS17 -> 0.9 | AT18: 146 | AU18: =AU17 -> 1.1 | AV18: 194 | AW18: 2.9 | AX18: 177 | AY18: =AS18*AT18 -> 131.4 | AZ18: =AU18*AV18 -> 213.4 | BA18: =AW18*AX18 -> 513.3 | BB18: =AY18-AY17 -> 0 | BC18: =AZ18-AZ17 -> 8.8 | BD18: =BA18-BA17 -> -17.4 | BE18: =SUM(BB18:BD18) -> -8.6 | BF18: =SUM(I18-BE18) -> 8.6 | BG18: =SUM(I18-BF18) -> -8.6
A19: =ELEC!C16 -> 44300 | B19: =B18 -> 109443 | C19: =B19-B18 -> 0 | D19: =C19/27 -> 0 | E19: =SUM((C19*$E$4)+(7500/'EDl log'!$A$36)) -> 250 | G19: =G18 -> 618461 | H19: =G19-G18 -> 0 | I19: =C19+H19 -> 0 | J19: =IF(I19>0,E19/I19,0) -> 0 | K19: ='Swimming Pool quality check '!H19 -> 6741 | L19: =K19-K18 -> 1 | M19: =M18 -> 457.44 | N19: =SUM(M19-M18) -> 0 | O19: =O18 -> 529.52 | P19: =SUM(O19-O18) -> 0 | Q19: =SUM(P19+N19) -> 0 | T19: =T18 -> 5171 | U19: =SUM(T19-T18) -> 0 | V19: =V18 -> 470 | W19: =+V19-V18 -> 0 | X19: =X18 -> 151398 | Y19: =SUM(X19-X18) -> 0 | Z19: =Z18 -> 98760 | AA19: =Z19-Z18 -> 0 | AB19: =AB18 -> 261 | AC19: =AC18 -> 731 | AD19: =AC19-AC18 -> 0 | AE19: =AE18 -> 229.28 | AF19: =AE19-AE18 -> 0 | AG19: =AG18 -> 2209.02 | AH19: =AG19-AG18 -> 0 | AI19: =AF19+AH19 -> 0 | AJ19: =+Z19-Z18 -> 0 | AK19: =SUM(Y19-L19) -> -1 | AL19: =SUM(AJ19-W19) -> 0 | AM19: ='General information '!D19 -> 16 | AN19: ='General information '!H19 -> 0 | AP19: ='General information '!J19 -> 0 | AR19: =A19 -> 44300 | AS19: =AS18 -> 0.9 | AT19: =AT18 -> 146 | AU19: =AU18 -> 1.1 | AV19: 191 | AW19: 2.9 | AX19: 175 | AY19: =AS19*AT19 -> 131.4 | AZ19: =AU19*AV19 -> 210.1 | BA19: =AW19*AX19 -> 507.5 | BB19: =AY19-AY18 -> 0 | BC19: =AZ19-AZ18 -> -3.3 | BD19: =BA19-BA18 -> -5.8 | BE19: =SUM(BB19:BD19) -> -9.1 | BF19: =SUM(I19-BE19) -> 9.1 | BG19: =SUM(I19-BF19) -> -9.1
A20: =ELEC!C17 -> 44301 | B20: =B19 -> 109443 | C20: =B20-B19 -> 0 | D20: =C20/27 -> 0 | E20: =SUM((C20*$E$4)+(7500/'EDl log'!$A$36)) -> 250 | G20: =G19 -> 618461 | H20: =G20-G19 -> 0 | I20: =C20+H20 -> 0 | J20: =IF(I20>0,E20/I20,0) -> 0 | K20: ='Swimming Pool quality check '!H20 -> 6741 | L20: =K20-K19 -> 0 | M20: =M19 -> 457.44 | N20: =SUM(M20-M19) -> 0 | O20: =O19 -> 529.52 | P20: =SUM(O20-O19) -> 0 | Q20: =SUM(P20+N20) -> 0 | T20: =T19 -> 5171 | U20: =SUM(T20-T19) -> 0 | V20: =V19 -> 470 | W20: =+V20-V19 -> 0 | X20: =X19 -> 151398 | Y20: =SUM(X20-X19) -> 0 | Z20: =Z19 -> 98760 | AA20: =Z20-Z19 -> 0 | AB20: =AB19 -> 261 | AC20: =AC19 -> 731 | AD20: =AC20-AC19 -> 0 | AE20: =AE19 -> 229.28 | AF20: =AE20-AE19 -> 0 | AG20: =AG19 -> 2209.02 | AH20: =AG20-AG19 -> 0 | AI20: =AF20+AH20 -> 0 | AJ20: =+Z20-Z19 -> 0 | AK20: =SUM(Y20-L20) -> 0 | AL20: =SUM(AJ20-W20) -> 0 | AM20: ='General information '!D20 -> 19 | AN20: ='General information '!H20 -> 0 | AP20: ='General information '!J20 -> 0 | AR20: =A20 -> 44301 | AS20: =AS19 -> 0.9 | AT20: =AT19 -> 146 | AU20: =AU19 -> 1.1 | AV20: 190 | AW20: 2.9 | AX20: 170 | AY20: =AS20*AT20 -> 131.4 | AZ20: =AU20*AV20 -> 209 | BA20: =AW20*AX20 -> 493 | BB20: =AY20-AY19 -> 0 | BC20: =AZ20-AZ19 -> -1.1 | BD20: =BA20-BA19 -> -14.5 | BE20: =SUM(BB20:BD20) -> -15.6 | BF20: =SUM(I20-BE20) -> 15.6 | BG20: =SUM(I20-BF20) -> -15.6
A21: =ELEC!C18 -> 44302 | B21: =B20 -> 109443 | C21: =B21-B20 -> 0 | D21: =C21/27 -> 0 | E21: =SUM((C21*$E$4)+(7500/'EDl log'!$A$36)) -> 250 | G21: =G20 -> 618461 | H21: =G21-G20 -> 0 | I21: =C21+H21 -> 0 | J21: =IF(I21>0,E21/I21,0) -> 0 | K21: ='Swimming Pool quality check '!H21 -> 6741 | L21: =K21-K20 -> 0 | M21: =M20 -> 457.44 | N21: =SUM(M21-M20) -> 0 | O21: =O20 -> 529.52 | P21: =SUM(O21-O20) -> 0 | Q21: =SUM(P21+N21) -> 0 | T21: =T20 -> 5171 | U21: =SUM(T21-T20) -> 0 | V21: =V20 -> 470 | W21: =+V21-V20 -> 0 | X21: =X20 -> 151398 | Y21: =SUM(X21-X20) -> 0 | Z21: =Z20 -> 98760 | AA21: =Z21-Z20 -> 0 | AB21: =AB20 -> 261 | AC21: =AC20 -> 731 | AD21: =AC21-AC20 -> 0 | AE21: =AE20 -> 229.28 | AF21: =AE21-AE20 -> 0 | AG21: =AG20 -> 2209.02 | AH21: =AG21-AG20 -> 0 | AI21: =AF21+AH21 -> 0 | AJ21: =+Z21-Z20 -> 0 | AK21: =SUM(Y21-L21) -> 0 | AL21: =SUM(AJ21-W21) -> 0 | AM21: ='General information '!D21 -> 0 | AN21: ='General information '!H21 -> 0 | AP21: ='General information '!J21 -> 0 | AR21: =A21 -> 44302 | AS21: =AS20 -> 0.9 | AT21: =AT20 -> 146 | AU21: =AU20 -> 1.1 | AV21: =AV20 -> 190 | AW21: 2.9 | AX21: =AX20 -> 170 | AY21: =AS21*AT21 -> 131.4 | AZ21: =AU21*AV21 -> 209 | BA21: =AW21*AX21 -> 493 | BB21: =AY21-AY20 -> 0 | BC21: =AZ21-AZ20 -> 0 | BD21: =BA21-BA20 -> 0 | BE21: =SUM(BB21:BD21) -> 0 | BF21: =SUM(I21-BE21) -> 0 | BG21: =SUM(I21-BF21) -> 0
A22: =ELEC!C19 -> 44303 | B22: =B21 -> 109443 | C22: =B22-B21 -> 0 | D22: =C22/27 -> 0 | E22: =SUM((C22*$E$4)+(7500/'EDl log'!$A$36)) -> 250 | G22: =G21 -> 618461 | H22: =G22-G21 -> 0 | I22: =C22+H22 -> 0 | J22: =IF(I22>0,E22/I22,0) -> 0 | K22: ='Swimming Pool quality check '!H22 -> 6741 | L22: =K22-K21 -> 0 | M22: =M21 -> 457.44 | N22: =SUM(M22-M21) -> 0 | O22: =O21 -> 529.52 | P22: =SUM(O22-O21) -> 0 | Q22: =SUM(P22+N22) -> 0 | T22: =T21 -> 5171 | U22: =SUM(T22-T21) -> 0 | V22: =V21 -> 470 | W22: =+V22-V21 -> 0 | X22: =X21 -> 151398 | Y22: =SUM(X22-X21) -> 0 | Z22: =Z21 -> 98760 | AA22: =Z22-Z21 -> 0 | AB22: =AB21 -> 261 | AC22: =AC21 -> 731 | AD22: =AC22-AC21 -> 0 | AE22: =AE21 -> 229.28 | AF22: =AE22-AE21 -> 0 | AG22: =AG21 -> 2209.02 | AH22: =AG22-AG21 -> 0 | AI22: =AF22+AH22 -> 0 | AJ22: =+Z22-Z21 -> 0 | AK22: =SUM(Y22-L22) -> 0 | AL22: =SUM(AJ22-W22) -> 0 | AM22: ='General information '!D22 -> 0 | AN22: ='General information '!H22 -> 0 | AP22: ='General information '!J22 -> 0 | AR22: =A22 -> 44303 | AS22: =AS21 -> 0.9 | AT22: =AT21 -> 146 | AU22: =AU21 -> 1.1 | AV22: =AV21 -> 190 | AW22: 2.9 | AX22: =AX21 -> 170 | AY22: =AS22*AT22 -> 131.4 | AZ22: =AU22*AV22 -> 209 | BA22: =AW22*AX22 -> 493 | BB22: =AY22-AY21 -> 0 | BC22: =AZ22-AZ21 -> 0 | BD22: =BA22-BA21 -> 0 | BE22: =SUM(BB22:BD22) -> 0 | BF22: =SUM(I22-BE22) -> 0 | BG22: =SUM(I22-BF22) -> 0
A23: =ELEC!C20 -> 44304 | B23: =B22 -> 109443 | C23: =B23-B22 -> 0 | D23: =C23/27 -> 0 | E23: =SUM((C23*$E$4)+(7500/'EDl log'!$A$36)) -> 250 | G23: =G22 -> 618461 | H23: =G23-G22 -> 0 | I23: =C23+H23 -> 0 | J23: =IF(I23>0,E23/I23,0) -> 0 | K23: ='Swimming Pool quality check '!H23 -> 6741 | L23: =K23-K22 -> 0 | M23: =M22 -> 457.44 | N23: =SUM(M23-M22) -> 0 | O23: =O22 -> 529.52 | P23: =SUM(O23-O22) -> 0 | Q23: =SUM(P23+N23) -> 0 | T23: =T22 -> 5171 | U23: =SUM(T23-T22) -> 0 | V23: =V22 -> 470 | W23: =+V23-V22 -> 0 | X23: =X22 -> 151398 | Y23: =SUM(X23-X22) -> 0 | Z23: =Z22 -> 98760 | AA23: =Z23-Z22 -> 0 | AB23: =AB22 -> 261 | AC23: =AC22 -> 731 | AD23: =AC23-AC22 -> 0 | AE23: =AE22 -> 229.28 | AF23: =AE23-AE22 -> 0 | AG23: =AG22 -> 2209.02 | AH23: =AG23-AG22 -> 0 | AI23: =AF23+AH23 -> 0 | AJ23: =+Z23-Z22 -> 0 | AK23: =SUM(Y23-L23) -> 0 | AL23: =SUM(AJ23-W23) -> 0 | AM23: ='General information '!D23 -> 0 | AN23: ='General information '!H23 -> 0 | AP23: ='General information '!J23 -> 0 | AR23: =A23 -> 44304 | AS23: =AS22 -> 0.9 | AT23: =AT22 -> 146 | AU23: =AU22 -> 1.1 | AV23: =AV22 -> 190 | AW23: 2.9 | AX23: =AX22 -> 170 | AY23: =AS23*AT23 -> 131.4 | AZ23: =AU23*AV23 -> 209 | BA23: =AW23*AX23 -> 493 | BB23: =AY23-AY22 -> 0 | BC23: =AZ23-AZ22 -> 0 | BD23: =BA23-BA22 -> 0 | BE23: =SUM(BB23:BD23) -> 0 | BF23: =SUM(I23-BE23) -> 0 | BG23: =SUM(I23-BF23) -> 0
A24: =ELEC!C21 -> 44305 | B24: =B23 -> 109443 | C24: =B24-B23 -> 0 | D24: =C24/27 -> 0 | E24: =SUM((C24*$E$4)+(7500/'[4]EDl log'!$A$37)) -> 241.93548 | G24: =G23 -> 618461 | H24: =G24-G23 -> 0 | I24: =C24+H24 -> 0 | J24: =IF(I24>0,E24/I24,0) -> 0 | K24: ='[4]Swimming Pool quality check '!H24 -> 6713 | L24: =K24-K23 -> -28 | M24: =M23 -> 457.44 | N24: =SUM(M24-M23) -> 0 | O24: =O23 -> 529.52 | P24: =SUM(O24-O23) -> 0 | Q24: =SUM(P24+N24) -> 0 | T24: =T23 -> 5171 | U24: =SUM(T24-T23) -> 0 | V24: =V23 -> 470 | W24: =+V24-V23 -> 0 | X24: =X23 -> 151398 | Y24: =SUM(X24-X23) -> 0 | Z24: =Z23 -> 98760 | AA24: =Z24-Z23 -> 0 | AB24: =AB23 -> 261 | AC24: =AC23 -> 731 | AD24: =AC24-AC23 -> 0 | AE24: =AE23 -> 229.28 | AF24: =AE24-AE23 -> 0 | AG24: =AG23 -> 2209.02 | AH24: =AG24-AG23 -> 0 | AI24: =AF24+AH24 -> 0 | AJ24: =+Z24-Z23 -> 0 | AK24: =SUM(Y24-L24) -> 28 | AL24: =SUM(AJ24-W24) -> 0 | AM24: ='[4]General information '!D24 -> 13.5 | AN24: ='[4]General information '!H24 -> 0 | AP24: ='[4]General information '!J24 -> 0 | AR24: =A24 -> 44305 | AS24: =AS23 -> 0.9 | AT24: =AT23 -> 146 | AU24: =AU23 -> 1.1 | AV24: =AV23 -> 190 | AW24: 2.9 | AX24: =AX23 -> 170 | AY24: =AS24*AT24 -> 131.4 | AZ24: =AU24*AV24 -> 209 | BA24: =AW24*AX24 -> 493 | BB24: =AY24-AY23 -> 0 | BC24: =AZ24-AZ23 -> 0 | BD24: =BA24-BA23 -> 0 | BE24: =SUM(BB24:BD24) -> 0 | BF24: =SUM(I24-BE24) -> 0 | BG24: =SUM(I24-BF24) -> 0
A25: =ELEC!C22 -> 44306 | B25: =B24 -> 109443 | C25: =B25-B24 -> 0 | D25: =C25/27 -> 0 | E25: =SUM((C25*$E$4)+(7500/'EDl log'!$A$36)) -> 250 | G25: =G24 -> 618461 | H25: =G25-G24 -> 0 | I25: =C25+H25 -> 0 | J25: =IF(I25>0,E25/I25,0) -> 0 | K25: ='Swimming Pool quality check '!H25 -> 6741 | L25: =K25-K24 -> 28 | M25: =M24 -> 457.44 | N25: =SUM(M25-M24) -> 0 | O25: =O24 -> 529.52 | P25: =SUM(O25-O24) -> 0 | Q25: =SUM(P25+N25) -> 0 | T25: =T24 -> 5171 | U25: =SUM(T25-T24) -> 0 | V25: =V24 -> 470 | W25: =+V25-V24 -> 0 | X25: =X24 -> 151398 | Y25: =SUM(X25-X24) -> 0 | Z25: =Z24 -> 98760 | AA25: =Z25-Z24 -> 0 | AB25: =AB24 -> 261 | AC25: =AC24 -> 731 | AD25: =AC25-AC24 -> 0 | AE25: =AE24 -> 229.28 | AF25: =AE25-AE24 -> 0 | AG25: =AG24 -> 2209.02 | AH25: =AG25-AG24 -> 0 | AI25: =AF25+AH25 -> 0 | AJ25: =+Z25-Z24 -> 0 | AK25: =SUM(Y25-L25) -> -28 | AL25: =SUM(AJ25-W25) -> 0 | AM25: ='General information '!D25 -> 0 | AN25: ='General information '!H25 -> 0 | AP25: ='General information '!J25 -> 0 | AR25: =A25 -> 44306 | AS25: =AS24 -> 0.9 | AT25: =AT24 -> 146 | AU25: =AU24 -> 1.1 | AV25: =AV24 -> 190 | AW25: 2.9 | AX25: =AX24 -> 170 | AY25: =AS25*AT25 -> 131.4 | AZ25: =AU25*AV25 -> 209 | BA25: =AW25*AX25 -> 493 | BB25: =AY25-AY24 -> 0 | BC25: =AZ25-AZ24 -> 0 | BD25: =BA25-BA24 -> 0 | BE25: =SUM(BB25:BD25) -> 0 | BF25: =SUM(I25-BE25) -> 0 | BG25: =SUM(I25-BF25) -> 0
A26: =ELEC!C23 -> 44307 | B26: =B25 -> 109443 | C26: =B26-B25 -> 0 | D26: =C26/27 -> 0 | E26: =SUM((C26*$E$4)+(7500/'EDl log'!$A$36)) -> 250 | G26: =G25 -> 618461 | H26: =G26-G25 -> 0 | I26: =C26+H26 -> 0 | J26: =IF(I26>0,E26/I26,0) -> 0 | K26: ='Swimming Pool quality check '!H26 -> 6741 | L26: =K26-K25 -> 0 | M26: =M25 -> 457.44 | N26: =SUM(M26-M25) -> 0 | O26: =O25 -> 529.52 | P26: =SUM(O26-O25) -> 0 | Q26: =SUM(P26+N26) -> 0 | T26: =T25 -> 5171 | U26: =SUM(T26-T25) -> 0 | V26: =V25 -> 470 | W26: =+V26-V25 -> 0 | X26: =X25 -> 151398 | Y26: =SUM(X26-X25) -> 0 | Z26: =Z25 -> 98760 | AA26: =Z26-Z25 -> 0 | AB26: =AB25 -> 261 | AC26: =AC25 -> 731 | AD26: =AC26-AC25 -> 0 | AE26: =AE25 -> 229.28 | AF26: =AE26-AE25 -> 0 | AG26: =AG25 -> 2209.02 | AH26: =AG26-AG25 -> 0 | AI26: =AF26+AH26 -> 0 | AJ26: =+Z26-Z25 -> 0 | AK26: =SUM(Y26-L26) -> 0 | AL26: =SUM(AJ26-W26) -> 0 | AM26: ='General information '!D26 -> 0 | AN26: ='General information '!H26 -> 0 | AP26: ='General information '!J26 -> 0 | AR26: =A26 -> 44307 | AS26: =AS25 -> 0.9 | AT26: =AT25 -> 146 | AU26: =AU25 -> 1.1 | AV26: =AV25 -> 190 | AW26: 2.9 | AX26: =AX25 -> 170 | AY26: =AS26*AT26 -> 131.4 | AZ26: =AU26*AV26 -> 209 | BA26: =AW26*AX26 -> 493 | BB26: =AY26-AY25 -> 0 | BC26: =AZ26-AZ25 -> 0 | BD26: =BA26-BA25 -> 0 | BE26: =SUM(BB26:BD26) -> 0 | BF26: =SUM(I26-BE26) -> 0 | BG26: =SUM(I26-BF26) -> 0
A27: =ELEC!C24 -> 44308 | B27: =B26 -> 109443 | C27: =B27-B26 -> 0 | D27: =C27/27 -> 0 | E27: =SUM((C27*$E$4)+(7500/'EDl log'!$A$36)) -> 250 | G27: =G26 -> 618461 | H27: =G27-G26 -> 0 | I27: =C27+H27 -> 0 | J27: =IF(I27>0,E27/I27,0) -> 0 | K27: ='Swimming Pool quality check '!H27 -> 6741 | L27: =K27-K26 -> 0 | M27: =M26 -> 457.44 | N27: =SUM(M27-M26) -> 0 | O27: =O26 -> 529.52 | P27: =SUM(O27-O26) -> 0 | Q27: =SUM(P27+N27) -> 0 | T27: =T26 -> 5171 | U27: =SUM(T27-T26) -> 0 | V27: =V26 -> 470 | W27: =+V27-V26 -> 0 | X27: =X26 -> 151398 | Y27: =SUM(X27-X26) -> 0 | Z27: =Z26 -> 98760 | AA27: =Z27-Z26 -> 0 | AB27: =AB26 -> 261 | AC27: =AC26 -> 731 | AD27: =AC27-AC26 -> 0 | AE27: =AE26 -> 229.28 | AF27: =AE27-AE26 -> 0 | AG27: =AG26 -> 2209.02 | AH27: =AG27-AG26 -> 0 | AI27: =AF27+AH27 -> 0 | AJ27: =+Z27-Z26 -> 0 | AK27: =SUM(Y27-L27) -> 0 | AL27: =SUM(AJ27-W27) -> 0 | AM27: ='General information '!D27 -> 0 | AN27: ='General information '!H27 -> 0 | AP27: ='General information '!J27 -> 0 | AR27: =A27 -> 44308 | AS27: =AS26 -> 0.9 | AT27: =AT26 -> 146 | AU27: =AU26 -> 1.1 | AV27: =AV26 -> 190 | AW27: 2.9 | AX27: =AX26 -> 170 | AY27: =AS27*AT27 -> 131.4 | AZ27: =AU27*AV27 -> 209 | BA27: =AW27*AX27 -> 493 | BB27: =AY27-AY26 -> 0 | BC27: =AZ27-AZ26 -> 0 | BD27: =BA27-BA26 -> 0 | BE27: =SUM(BB27:BD27) -> 0 | BF27: =SUM(I27-BE27) -> 0 | BG27: =SUM(I27-BF27) -> 0
A28: =ELEC!C25 -> 44309 | B28: =B27 -> 109443 | C28: =B28-B27 -> 0 | D28: =C28/27 -> 0 | E28: =SUM((C28*$E$4)+(7500/'EDl log'!$A$36)) -> 250 | G28: =G27 -> 618461 | H28: =G28-G27 -> 0 | I28: =C28+H28 -> 0 | J28: =IF(I28>0,E28/I28,0) -> 0 | K28: ='Swimming Pool quality check '!H28 -> 6741 | L28: =K28-K27 -> 0 | M28: =M27 -> 457.44 | N28: =SUM(M28-M27) -> 0 | O28: =O27 -> 529.52 | P28: =SUM(O28-O27) -> 0 | Q28: =SUM(P28+N28) -> 0 | T28: =T27 -> 5171 | U28: =SUM(T28-T27) -> 0 | V28: =V27 -> 470 | W28: =+V28-V27 -> 0 | X28: =X27 -> 151398 | Y28: =SUM(X28-X27) -> 0 | Z28: =Z27 -> 98760 | AA28: =Z28-Z27 -> 0 | AB28: =AB27 -> 261 | AC28: =AC27 -> 731 | AD28: =AC28-AC27 -> 0 | AE28: =AE27 -> 229.28 | AF28: =AE28-AE27 -> 0 | AG28: =AG27 -> 2209.02 | AH28: =AG28-AG27 -> 0 | AI28: =AF28+AH28 -> 0 | AJ28: =+Z28-Z27 -> 0 | AK28: =SUM(Y28-L28) -> 0 | AL28: =SUM(AJ28-W28) -> 0 | AM28: ='General information '!D28 -> 0 | AN28: ='General information '!H28 -> 0 | AP28: ='General information '!J28 -> 0 | AR28: =A28 -> 44309 | AS28: =AS27 -> 0.9 | AT28: =AT27 -> 146 | AU28: =AU27 -> 1.1 | AV28: =AV27 -> 190 | AW28: 2.9 | AX28: =AX27 -> 170 | AY28: =AS28*AT28 -> 131.4 | AZ28: =AU28*AV28 -> 209 | BA28: =AW28*AX28 -> 493 | BB28: =AY28-AY27 -> 0 | BC28: =AZ28-AZ27 -> 0 | BD28: =BA28-BA27 -> 0 | BE28: =SUM(BB28:BD28) -> 0 | BF28: =SUM(I28-BE28) -> 0 | BG28: =SUM(I28-BF28) -> 0
A29: =ELEC!C26 -> 44310 | B29: =B28 -> 109443 | C29: =B29-B28 -> 0 | D29: =C29/27 -> 0 | E29: =SUM((C29*$E$4)+(7500/'EDl log'!$A$36)) -> 250 | G29: =G28 -> 618461 | H29: =G29-G28 -> 0 | I29: =C29+H29 -> 0 | J29: =IF(I29>0,E29/I29,0) -> 0 | K29: ='Swimming Pool quality check '!H29 -> 6741 | L29: =K29-K28 -> 0 | M29: =M28 -> 457.44 | N29: =SUM(M29-M28) -> 0 | O29: =O28 -> 529.52 | P29: =SUM(O29-O28) -> 0 | Q29: =SUM(P29+N29) -> 0 | T29: =T28 -> 5171 | U29: =SUM(T29-T28) -> 0 | V29: =V28 -> 470 | W29: =+V29-V28 -> 0 | X29: =X28 -> 151398 | Y29: =SUM(X29-X28) -> 0 | Z29: =Z28 -> 98760 | AA29: =Z29-Z28 -> 0 | AB29: =AB28 -> 261 | AC29: =AC28 -> 731 | AD29: =AC29-AC28 -> 0 | AE29: =AE28 -> 229.28 | AF29: =AE29-AE28 -> 0 | AG29: =AG28 -> 2209.02 | AH29: =AG29-AG28 -> 0 | AI29: =AF29+AH29 -> 0 | AJ29: =+Z29-Z28 -> 0 | AK29: =SUM(Y29-L29) -> 0 | AL29: =SUM(AJ29-W29) -> 0 | AM29: ='General information '!D29 -> 0 | AN29: ='General information '!H29 -> 0 | AP29: ='General information '!J29 -> 0 | AR29: =A29 -> 44310 | AS29: =AS28 -> 0.9 | AT29: =AT28 -> 146 | AU29: =AU28 -> 1.1 | AV29: =AV28 -> 190 | AW29: 2.9 | AX29: =AX28 -> 170 | AY29: =AS29*AT29 -> 131.4 | AZ29: =AU29*AV29 -> 209 | BA29: =AW29*AX29 -> 493 | BB29: =AY29-AY28 -> 0 | BC29: =AZ29-AZ28 -> 0 | BD29: =BA29-BA28 -> 0 | BE29: =SUM(BB29:BD29) -> 0 | BF29: =SUM(I29-BE29) -> 0 | BG29: =SUM(I29-BF29) -> 0
A30: =ELEC!C27 -> 44311 | B30: =B29 -> 109443 | C30: =B30-B29 -> 0 | D30: =C30/27 -> 0 | E30: =SUM((C30*$E$4)+(7500/'EDl log'!$A$36)) -> 250 | G30: =G29 -> 618461 | H30: =G30-G29 -> 0 | I30: =C30+H30 -> 0 | J30: =IF(I30>0,E30/I30,0) -> 0 | K30: ='Swimming Pool quality check '!H30 -> 6741 | L30: =K30-K29 -> 0 | M30: =M29 -> 457.44 | N30: =SUM(M30-M29) -> 0 | O30: =O29 -> 529.52 | P30: =SUM(O30-O29) -> 0 | Q30: =SUM(P30+N30) -> 0 | T30: =T29 -> 5171 | U30: =SUM(T30-T29) -> 0 | V30: =V29 -> 470 | W30: =+V30-V29 -> 0 | X30: =X29 -> 151398 | Y30: =SUM(X30-X29) -> 0 | Z30: =Z29 -> 98760 | AA30: =Z30-Z29 -> 0 | AB30: =AB29 -> 261 | AC30: =AC29 -> 731 | AD30: =AC30-AC29 -> 0 | AE30: =AE29 -> 229.28 | AF30: =AE30-AE29 -> 0 | AG30: =AG29 -> 2209.02 | AH30: =AG30-AG29 -> 0 | AI30: =AF30+AH30 -> 0 | AJ30: =+Z30-Z29 -> 0 | AK30: =SUM(Y30-L30) -> 0 | AL30: =SUM(AJ30-W30) -> 0 | AM30: ='General information '!D30 -> 0 | AN30: ='General information '!H30 -> 0 | AP30: ='General information '!J30 -> 0 | AR30: =A30 -> 44311 | AS30: =AS29 -> 0.9 | AT30: =AT29 -> 146 | AU30: =AU29 -> 1.1 | AV30: =AV29 -> 190 | AW30: 2.9 | AX30: =AX29 -> 170 | AY30: =AS30*AT30 -> 131.4 | AZ30: =AU30*AV30 -> 209 | BA30: =AW30*AX30 -> 493 | BB30: =AY30-AY29 -> 0 | BC30: =AZ30-AZ29 -> 0 | BD30: =BA30-BA29 -> 0 | BE30: =SUM(BB30:BD30) -> 0 | BF30: =SUM(I30-BE30) -> 0 | BG30: =SUM(I30-BF30) -> 0
A31: =ELEC!C28 -> 44312 | B31: =B30 -> 109443 | C31: =B31-B30 -> 0 | D31: =C31/27 -> 0 | E31: =SUM((C31*$E$4)+(7500/'EDl log'!$A$36)) -> 250 | G31: =G30 -> 618461 | H31: =G31-G30 -> 0 | I31: =C31+H31 -> 0 | J31: =IF(I31>0,E31/I31,0) -> 0 | K31: ='Swimming Pool quality check '!H31 -> 6741 | L31: =K31-K30 -> 0 | M31: =M30 -> 457.44 | N31: =SUM(M31-M30) -> 0 | O31: =O30 -> 529.52 | P31: =SUM(O31-O30) -> 0 | Q31: =SUM(P31+N31) -> 0 | T31: =T30 -> 5171 | U31: =SUM(T31-T30) -> 0 | V31: =V30 -> 470 | W31: =+V31-V30 -> 0 | X31: =X30 -> 151398 | Y31: =SUM(X31-X30) -> 0 | Z31: =Z30 -> 98760 | AA31: =Z31-Z30 -> 0 | AB31: =AB30 -> 261 | AC31: =AC30 -> 731 | AD31: =AC31-AC30 -> 0 | AE31: =AE30 -> 229.28 | AF31: =AE31-AE30 -> 0 | AG31: =AG30 -> 2209.02 | AH31: =AG31-AG30 -> 0 | AI31: =AF31+AH31 -> 0 | AJ31: =+Z31-Z30 -> 0 | AK31: =SUM(Y31-L31) -> 0 | AL31: =SUM(AJ31-W31) -> 0 | AM31: ='General information '!D31 -> 0 | AN31: ='General information '!H31 -> 0 | AP31: ='General information '!J31 -> 0 | AR31: =A31 -> 44312 | AS31: =AS30 -> 0.9 | AT31: =AT30 -> 146 | AU31: =AU30 -> 1.1 | AV31: =AV30 -> 190 | AW31: 2.9 | AX31: =AX30 -> 170 | AY31: =AS31*AT31 -> 131.4 | AZ31: =AU31*AV31 -> 209 | BA31: =AW31*AX31 -> 493 | BB31: =AY31-AY30 -> 0 | BC31: =AZ31-AZ30 -> 0 | BD31: =BA31-BA30 -> 0 | BE31: =SUM(BB31:BD31) -> 0 | BF31: =SUM(I31-BE31) -> 0 | BG31: =SUM(I31-BF31) -> 0
A32: =ELEC!C29 -> 44313 | B32: =B31 -> 109443 | C32: =B32-B31 -> 0 | D32: =C32/27 -> 0 | E32: =SUM((C32*$E$4)+(7500/'EDl log'!$A$36)) -> 250 | G32: =G31 -> 618461 | H32: =G32-G31 -> 0 | I32: =C32+H32 -> 0 | J32: =IF(I32>0,E32/I32,0) -> 0 | K32: ='Swimming Pool quality check '!H32 -> 6741 | L32: =K32-K31 -> 0 | M32: =M31 -> 457.44 | N32: =SUM(M32-M31) -> 0 | O32: =O31 -> 529.52 | P32: =SUM(O32-O31) -> 0 | Q32: =SUM(P32+N32) -> 0 | T32: =T31 -> 5171 | U32: =SUM(T32-T31) -> 0 | V32: =V31 -> 470 | W32: =+V32-V31 -> 0 | X32: =X31 -> 151398 | Y32: =SUM(X32-X31) -> 0 | Z32: =Z31 -> 98760 | AA32: =Z32-Z31 -> 0 | AB32: =AB31 -> 261 | AC32: =AC31 -> 731 | AD32: =AC32-AC31 -> 0 | AE32: =AE31 -> 229.28 | AF32: =AE32-AE31 -> 0 | AG32: =AG31 -> 2209.02 | AH32: =AG32-AG31 -> 0 | AI32: =AF32+AH32 -> 0 | AJ32: =+Z32-Z31 -> 0 | AK32: =SUM(Y32-L32) -> 0 | AL32: =SUM(AJ32-W32) -> 0 | AM32: ='General information '!D32 -> 0 | AN32: ='General information '!H32 -> 0 | AP32: ='General information '!J32 -> 0 | AR32: =A32 -> 44313 | AS32: =AS31 -> 0.9 | AT32: =AT31 -> 146 | AU32: =AU31 -> 1.1 | AV32: =AV31 -> 190 | AW32: 2.9 | AX32: =AX31 -> 170 | AY32: =AS32*AT32 -> 131.4 | AZ32: =AU32*AV32 -> 209 | BA32: =AW32*AX32 -> 493 | BB32: =AY32-AY31 -> 0 | BC32: =AZ32-AZ31 -> 0 | BD32: =BA32-BA31 -> 0 | BE32: =SUM(BB32:BD32) -> 0 | BF32: =SUM(I32-BE32) -> 0 | BG32: =SUM(I32-BF32) -> 0
A33: =ELEC!C30 -> 44314 | B33: =B32 -> 109443 | C33: =B33-B32 -> 0 | D33: =C33/27 -> 0 | E33: =SUM((C33*$E$4)+(7500/'EDl log'!$A$36)) -> 250 | G33: =G32 -> 618461 | H33: =G33-G32 -> 0 | I33: =C33+H33 -> 0 | J33: =IF(I33>0,E33/I33,0) -> 0 | K33: ='Swimming Pool quality check '!H33 -> 6741 | L33: =K33-K32 -> 0 | M33: =M32 -> 457.44 | N33: =SUM(M33-M32) -> 0 | O33: =O32 -> 529.52 | P33: =SUM(O33-O32) -> 0 | Q33: =SUM(P33+N33) -> 0 | T33: =T32 -> 5171 | U33: =SUM(T33-T32) -> 0 | V33: =V32 -> 470 | W33: =+V33-V32 -> 0 | X33: =X32 -> 151398 | Y33: =SUM(X33-X32) -> 0 | Z33: =Z32 -> 98760 | AA33: =Z33-Z32 -> 0 | AB33: =AB32 -> 261 | AC33: =AC32 -> 731 | AD33: =AC33-AC32 -> 0 | AE33: =AE32 -> 229.28 | AF33: =AE33-AE32 -> 0 | AG33: =AG32 -> 2209.02 | AH33: =AG33-AG32 -> 0 | AI33: =AF33+AH33 -> 0 | AJ33: =+Z33-Z32 -> 0 | AK33: =SUM(Y33-L33) -> 0 | AL33: =SUM(AJ33-W33) -> 0 | AM33: ='General information '!D33 -> 0 | AN33: ='General information '!H33 -> 0 | AP33: ='General information '!J33 -> 0 | AR33: =A33 -> 44314 | AS33: =AS32 -> 0.9 | AT33: =AT32 -> 146 | AU33: =AU32 -> 1.1 | AV33: =AV32 -> 190 | AW33: 2.9 | AX33: =AX32 -> 170 | AY33: =AS33*AT33 -> 131.4 | AZ33: =AU33*AV33 -> 209 | BA33: =AW33*AX33 -> 493 | BB33: =AY33-AY32 -> 0 | BC33: =AZ33-AZ32 -> 0 | BD33: =BA33-BA32 -> 0 | BE33: =SUM(BB33:BD33) -> 0 | BF33: =SUM(I33-BE33) -> 0 | BG33: =SUM(I33-BF33) -> 0
A34: =ELEC!C31 -> 44315 | B34: =B33 -> 109443 | C34: =B34-B33 -> 0 | D34: =C34/27 -> 0 | E34: =SUM((C34*$E$4)+(7500/'EDl log'!$A$36)) -> 250 | G34: =G33 -> 618461 | H34: =G34-G33 -> 0 | I34: =C34+H34 -> 0 | J34: =IF(I34>0,E34/I34,0) -> 0 | K34: ='Swimming Pool quality check '!H34 -> 6741 | L34: =K34-K33 -> 0 | M34: =M33 -> 457.44 | N34: =SUM(M34-M33) -> 0 | O34: =O33 -> 529.52 | P34: =SUM(O34-O33) -> 0 | Q34: =SUM(P34+N34) -> 0 | T34: =T33 -> 5171 | U34: =SUM(T34-T33) -> 0 | V34: =V33 -> 470 | W34: =+V34-V33 -> 0 | X34: =X33 -> 151398 | Y34: =SUM(X34-X33) -> 0 | Z34: =Z33 -> 98760 | AA34: =Z34-Z33 -> 0 | AB34: =AB33 -> 261 | AC34: =AC33 -> 731 | AD34: =AC34-AC33 -> 0 | AE34: =AE33 -> 229.28 | AF34: =AE34-AE33 -> 0 | AG34: =AG33 -> 2209.02 | AH34: =AG34-AG33 -> 0 | AI34: =AF34+AH34 -> 0 | AJ34: =+Z34-Z33 -> 0 | AK34: =SUM(Y34-L34) -> 0 | AL34: =SUM(AJ34-W34) -> 0 | AM34: ='General information '!D34 -> 0 | AN34: ='General information '!H34 -> 0 | AP34: ='General information '!J34 -> 0 | AR34: =A34 -> 44315 | AS34: =AS33 -> 0.9 | AT34: =AT33 -> 146 | AU34: =AU33 -> 1.1 | AV34: =AV33 -> 190 | AW34: 2.9 | AX34: =AX33 -> 170 | AY34: =AS34*AT34 -> 131.4 | AZ34: =AU34*AV34 -> 209 | BA34: =AW34*AX34 -> 493 | BB34: =AY34-AY33 -> 0 | BC34: =AZ34-AZ33 -> 0 | BD34: =BA34-BA33 -> 0 | BE34: =SUM(BB34:BD34) -> 0 | BF34: =SUM(I34-BE34) -> 0 | BG34: =SUM(I34-BF34) -> 0
A35: =ELEC!C32 -> 44316 | B35: =B34 -> 109443 | C35: =B35-B34 -> 0 | D35: =C35/27 -> 0 | E35: =SUM((C35*$E$4)+(7500/'EDl log'!$A$36)) -> 250 | G35: =G34 -> 618461 | H35: =G35-G34 -> 0 | I35: =C35+H35 -> 0 | J35: =IF(I35>0,E35/I35,0) -> 0 | K35: ='Swimming Pool quality check '!H35 -> 6741 | L35: =K35-K34 -> 0 | M35: =M34 -> 457.44 | N35: =SUM(M35-M34) -> 0 | O35: =O34 -> 529.52 | P35: =SUM(O35-O34) -> 0 | Q35: =SUM(P35+N35) -> 0 | T35: =T34 -> 5171 | U35: =SUM(T35-T34) -> 0 | V35: =V34 -> 470 | W35: =+V35-V34 -> 0 | X35: =X34 -> 151398 | Y35: =SUM(X35-X34) -> 0 | Z35: =Z34 -> 98760 | AA35: =Z35-Z34 -> 0 | AB35: =AB34 -> 261 | AC35: =AC34 -> 731 | AD35: =AC35-AC34 -> 0 | AE35: =AE34 -> 229.28 | AF35: =AE35-AE34 -> 0 | AG35: =AG34 -> 2209.02 | AH35: =AG35-AG34 -> 0 | AI35: =AF35+AH35 -> 0 | AJ35: =+Z35-Z34 -> 0 | AK35: =SUM(Y35-L35) -> 0 | AL35: =SUM(AJ35-W35) -> 0 | AM35: ='General information '!D35 -> 0 | AN35: ='General information '!H35 -> 0 | AP35: ='General information '!J35 -> 0 | AR35: =A35 -> 44316 | AS35: =AS34 -> 0.9 | AT35: =AT34 -> 146 | AU35: =AU34 -> 1.1 | AV35: =AV34 -> 190 | AW35: 2.9 | AX35: =AX34 -> 170 | AY35: =AS35*AT35 -> 131.4 | AZ35: =AU35*AV35 -> 209 | BA35: =AW35*AX35 -> 493 | BB35: =AY35-AY34 -> 0 | BC35: =AZ35-AZ34 -> 0 | BD35: =BA35-BA34 -> 0 | BE35: =SUM(BB35:BD35) -> 0 | BF35: =SUM(I35-BE35) -> 0 | BG35: =SUM(I35-BF35) -> 0
C36: =SUM(C6:C33) -> 0 | D36: =SUM(D6:D33) -> 0 | F36: =SUM(F6:F33) -> 0 | H36: =SUM(H6:H33) -> 398 | I36: =SUM(I6:I33) -> 398 | L36: =SUM(L7:L33) -> 8 | Q36: =SUM(Q5:Q33) -> 0 | U36: =SUM(U6:U33) -> 0 | Y36: =SUM(#REF!,Y33,Y31,Y29,Y27,Y25,Y23,Y21,Y19,Y17,Y15,Y13,Y11,Y9,Y7,#REF!) -> #REF! | AJ36: =SUM(AJ6:AJ33) -> 63 | AK36: =SUM(Y36-L36) -> #REF! | AL36: =SUM(AL6:AL33) -> 62
C37: =+C36*1.66 -> 0 | E37: =SUM(E6:E33) -> 6991.9355 | F37: =SUM(F6:F33) -> 0 | H37: 7500 | I37: =SUM('General information '!G36/WATER!I36) -> 0 | O37: =SUM(Q36+I36) -> 398 | Z37: =SUM(Y36:AJ36) -> #REF! | AK37: =SUM(Y37-L37) -> 0
B38: =9*27 -> 243 | D38: =SUM(D6:D33) -> 0 | F38: =SUM(F6:F33) -> 0 | G38: =SUM(I36) -> 398 | H38: =SUM(H37+C37) -> 7500 | K38: =SUM(H38/G38) -> 18.844221 | AJ38: =SUM(C37-AK37) -> 0 | AM38: =SUM(AJ38/AO37) -> #DIV/0!

Sheet graphic

Sheet General information 
A1: GENERAL & HOTEL'S INFORMATION SHEET
B4: Max Temp | C4: MIN TEMP | D4: AVE TEMP | E4: AVE Humidity | F4: AVE OCC | G4: # of OCC Rooms | H4: Ball room | I4: Meeting rooms | J4: Outlets | K4: Total covers | L4: # of permenant Emp | M4: # of casuals | N4: Total # of EMP | O4: # of EMP/OCC Room
A5: =ELEC!C2 -> 44286 | B5: ='[3]General information '!B36 -> 18 | C5: ='[3]General information '!C36 -> 13 | D5: ='[3]General information '!D36 -> 15.5 | E5: ='[3]General information '!E36 -> 0.65 | F5: ='[3]General information '!F36 -> 0 | G5: ='[3]General information '!G36 -> 0 | H5: ='[3]General information '!H36 -> 0 | I5: ='[3]General information '!I36 -> 0 | ... O5: ='[3]General information '!O36 -> 0
A6: =ELEC!C3 -> 44287 | B6: 17 | C6: 12 | D6: =(C6+B6)/2 -> 14.5 | E6: 0.65 | F6: 0 | G6: =F6*230 -> 0 | H6: 0 | I6: 0 | J6: 0 | K6: =+J6+H6 -> 0
A7: =ELEC!C4 -> 44288 | B7: 15 | C7: 12 | D7: =(C7+B7)/2 -> 13.5 | E7: 0.67 | F7: 0 | G7: =F7*230 -> 0 | H7: 0 | I7: 0 | J7: 0 | K7: =+J7+H7 -> 0
A8: =ELEC!C5 -> 44289 | B8: 19 | C8: 15 | D8: =(C8+B8)/2 -> 17 | E8: 0.59 | F8: 0 | G8: =F8*230 -> 0 | H8: 0 | I8: 0 | J8: 0 | K8: =+J8+H8 -> 0
A9: =ELEC!C6 -> 44290 | B9: 18 | C9: 15 | D9: =(C9+B9)/2 -> 16.5 | E9: 0.65 | F9: 0 | G9: =F9*230 -> 0 | H9: 0 | I9: 0 | J9: 0 | K9: =+J9+H9 -> 0
A10: =ELEC!C7 -> 44291 | B10: 19 | C10: 15 | D10: =(C10+B10)/2 -> 17 | E10: 0.67 | F10: 0 | G10: =F10*230 -> 0 | H10: 0 | I10: 0 | J10: 0 | K10: =+J10+H10 -> 0
A11: =ELEC!C8 -> 44292 | B11: 30 | C11: 15 | D11: =(C11+B11)/2 -> 22.5 | E11: 0.54 | F11: 0 | G11: =F11*230 -> 0 | H11: 0 | I11: 0 | J11: 0 | K11: =+J11+H11 -> 0
A12: =ELEC!C9 -> 44293 | B12: 24 | C12: 19 | D12: =(C12+B12)/2 -> 21.5 | E12: 0.63 | F12: 0 | G12: =F12*230 -> 0 | H12: 0 | I12: 0 | J12: 0 | K12: =+J12+H12 -> 0
A13: =ELEC!C10 -> 44294 | B13: 20 | C13: 17 | D13: =(C13+B13)/2 -> 18.5 | E13: 0.81 | F13: 0 | G13: =F13*230 -> 0 | H13: 0 | I13: 0 | J13: 0 | K13: =+J13+H13 -> 0
A14: =ELEC!C11 -> 44295 | B14: 20 | C14: 16 | D14: =(C14+B14)/2 -> 18 | E14: 0.66 | F14: 0 | G14: =F14*230 -> 0 | H14: 0 | I14: 0 | J14: 0 | K14: =+J14+H14 -> 0
A15: =ELEC!C12 -> 44296 | B15: 16 | C15: 14 | D15: =(C15+B15)/2 -> 15 | E15: 0.56 | F15: 0 | G15: =F15*230 -> 0 | H15: 0 | I15: 0 | J15: 0 | K15: =+J15+H15 -> 0
A16: =ELEC!C13 -> 44297 | B16: 17 | C16: 12 | D16: =(C16+B16)/2 -> 14.5 | E16: 0.58 | F16: 0 | G16: =F16*230 -> 0 | H16: 0 | I16: 0 | J16: 0 | K16: =+J16+H16 -> 0
A17: =ELEC!C14 -> 44298 | B17: 16 | C17: 13 | D17: =(C17+B17)/2 -> 14.5 | E17: 0.71 | F17: 0 | G17: =F17*230 -> 0 | H17: 0 | I17: 0 | J17: 0 | K17: =+J17+H17 -> 0
... A20: =ELEC!C17 -> 44301 | B20: 24 | C20: 14 | D20: =(C20+B20)/2 -> 19 | E20: 0.62 | F20: 0 | G20: =F20*230 -> 0 | H20: 0 | I20: 0 | J20: 0 | K20: =+J20+H20 -> 0
A21: =ELEC!C18 -> 44302 | D21: =(C21+B21)/2 -> 0 | G21: =F21*230 -> 0 | H21: 0 | I21: 0 | J21: 0 | K21: =+J21+H21 -> 0
A22: =ELEC!C19 -> 44303 | D22: =(C22+B22)/2 -> 0 | G22: =F22*230 -> 0 | H22: 0 | I22: 0 | J22: 0 | K22: =+J22+H22 -> 0
A23: =ELEC!C20 -> 44304 | D23: =(C23+B23)/2 -> 0 | G23: =F23*230 -> 0 | H23: 0 | I23: 0 | J23: 0 | K23: =+J23+H23 -> 0
A24: =ELEC!C21 -> 44305 | D24: =(C24+B24)/2 -> 0 | G24: =F24*230 -> 0 | H24: 0 | I24: 0 | J24: 0 | K24: =+J24+H24 -> 0
A25: =ELEC!C22 -> 44306 | D25: =(C25+B25)/2 -> 0 | G25: =F25*230 -> 0 | H25: 0 | I25: 0 | J25: 0 | K25: =+J25+H25 -> 0
A26: =ELEC!C23 -> 44307 | D26: =(C26+B26)/2 -> 0 | G26: =F26*230 -> 0 | H26: 0 | I26: 0 | J26: 0 | K26: =+J26+H26 -> 0
A27: =ELEC!C24 -> 44308 | D27: =(C27+B27)/2 -> 0 | G27: =F27*230 -> 0 | H27: 0 | I27: 0 | J27: 0 | K27: =+J27+H27+I27 -> 0
A28: =ELEC!C25 -> 44309 | D28: =(C28+B28)/2 -> 0 | G28: =F28*230 -> 0 | H28: 0 | I28: 0 | J28: 0 | K28: =+J28+H28+I28 -> 0
A29: =ELEC!C26 -> 44310 | D29: =(C29+B29)/2 -> 0 | G29: =F29*230 -> 0 | H29: 0 | I29: 0 | J29: 0 | K29: =+J29+H29+I29 -> 0
A30: =ELEC!C27 -> 44311 | D30: =(C30+B30)/2 -> 0 | G30: =F30*230 -> 0 | H30: 0 | I30: 0 | J30: 0 | K30: =+J30+H30+I30 -> 0
A31: =ELEC!C28 -> 44312 | D31: =(C31+B31)/2 -> 0 | G31: =F31*230 -> 0 | H31: 0 | I31: 0 | J31: 0 | K31: =+J31+H31+I31 -> 0
A32: =ELEC!C29 -> 44313 | D32: =(C32+B32)/2 -> 0 | G32: =F32*230 -> 0 | H32: 0 | I32: 0 | J32: 0 | K32: =+J32+H32+I32 -> 0
A33: =ELEC!C30 -> 44314 | D33: =(C33+B33)/2 -> 0 | G33: =F33*230 -> 0 | H33: 0 | I33: 0 | J33: 0 | K33: =+J33+H33+I33 -> 0
A34: =ELEC!C31 -> 44315 | D34: =(C34+B34)/2 -> 0 | G34: =F34*230 -> 0 | H34: 0 | I34: 0 | J34: 0 | K34: =+J34+H34+I34 -> 0
A35: =ELEC!C32 -> 44316 | D35: =(C35+B35)/2 -> 0 | G35: =F35*230 -> 0 | H35: 0 | I35: 0 | J35: 0 | K35: =+J35+H35+I35 -> 0
F36: =AVERAGE(F6:F33) -> 0 | G36: =SUM(G6:G33) -> 0
D37: =SUM(D6:D33)/'EDl log'!A34 -> 16.833333
I40: http://www.accuweather.com/en/lb/lebanon-weather

Sheet tanks
B2: Tank 1 | D2: Tank 2 | F2: Tank 3 | H2: Tank 4 | J2: Tank 5 | L2: Tank 6 | N2: Tank 7 | P2: Tank 8 | R2: Tank 9 | T2: Tank 10 | V2: Tank 11 | Z2: Tank 1 | AB2: Tank 2 | AD2: Tank 3 | AF2: Tank 4 | AH2: Tank 5 | AJ2: Tank 6 | AL2: Tank 7
B3: 6670 | D3: =SUM(B3) -> 6670 | F3: =SUM(D3) -> 6670 | H3: =SUM(F3) -> 6670 | J3: =SUM(H3) -> 6670 | L3: =SUM(J3) -> 6670 | N3: =SUM(L3) -> 6670 | P3: =SUM(N3) -> 6670 | R3: =SUM(P3) -> 6670 | T3: =SUM(R3) -> 6670 | V3: =SUM(T3) -> 6670 | W3: =SUM(B3:V3) -> 73370 | Z3: 2800 | AB3: 2800 | AD3: 2800 | AF3: 2800 | AH3: 2800 | AJ3: 2800 | AL3: 2800 | AM3: =SUM(Z3:AL3) -> 19600 | AO3: =SUM(AM3+W3) -> 92970 | AR3: Total sotck | AS3: Diesel Cons Per day | AT3: Diesel Delivery | BE3: Genset Co | BF3: Steam | BG3: Boil | BH3: Outdoor temperature
B4: =B3/310 -> 21.516129 | D4: =SUM(B4) -> 21.516129 | F4: =SUM(D4) -> 21.516129 | H4: =SUM(F4) -> 21.516129 | J4: =SUM(H4) -> 21.516129 | L4: =SUM(J4) -> 21.516129 | N4: =SUM(L4) -> 21.516129 | P4: =SUM(N4) -> 21.516129 | R4: =SUM(P4) -> 21.516129 | T4: =SUM(R4) -> 21.516129 | V4: =SUM(T4) -> 21.516129 | Z4: =Z3/280 -> 10 | AA4: =AA3/280 -> 0 | AB4: =AB3/280 -> 10 | AC4: =AC3/280 -> 0 | AD4: =AD3/280 -> 10 | AE4: =AE3/280 -> 0 | AF4: =AF3/280 -> 10 | AG4: =AG3/280 -> 0 | ... AL4: =AL3/280 -> 10 | AT4: Delivery | AU4: Cost /L | AW4: Boiler+Steam | AX4: Generator | AZ4: Occupancy | BA4: AVE TEPM | BB4: AVE Humidity
A5: =ELEC!C2 -> 44286 | B5: =[3]tanks!B36 -> 216 | C5: =[3]tanks!C36 -> 4647.4839 | D5: =[3]tanks!D36 -> 216 | E5: =[3]tanks!E36 -> 4647.4839 | F5: =[3]tanks!F36 -> 216 | G5: =[3]tanks!G36 -> 4647.4839 | H5: =[3]tanks!H36 -> 216 | I5: =[3]tanks!I36 -> 4647.4839 | ... AO5: =[3]tanks!AO36 -> 15610 | AP5: =[1]tanks!AP33 -> 0 | AQ5: =[3]tanks!AQ36 -> 0.7177834 | AR5: =[3]tanks!AR36 -> 66732.323 | AS5: =[3]tanks!AS36 -> -3916.8065 | AT5: =[3]tanks!AT36 -> 0 | AU5: =[3]tanks!AU36 -> 0 | AV5: =[3]tanks!AV36 -> 0.996 | AW5: =[3]tanks!AW36 -> -385 | AX5: =[3]tanks!AX36 -> -3531.8065 | ... BB5: =[3]tanks!BB36 -> 0.65 | BC5: =[2]tanks!BC36 -> 0 | BD5: =[2]tanks!BD36 -> 19222 | BE5: =[2]tanks!BE36 -> #REF! | BF5: =[2]tanks!BF36 -> 0 | BG5: =[2]tanks!BG36 -> #REF! | BH5: =[5]tanks!BH36 -> 0
A6: =ELEC!C3 -> 44287 | B6: ='B5'!B5 -> 230 | C6: =B6*$B$4 -> 4948.7097 | D6: =SUM(B6) -> 230 | E6: =D6*$B$4 -> 4948.7097 | F6: =SUM(D6) -> 230 | G6: =F6*$B$4 -> 4948.7097 | H6: =SUM(F6) -> 230 | I6: =H6*$B$4 -> 4948.7097 | J6: =SUM(H6) -> 230 | K6: =J6*$B$4 -> 4948.7097 | L6: =SUM(J6) -> 230 | M6: =L6*$B$4 -> 4948.7097 | N6: =SUM(L6) -> 230 | O6: =N6*$B$4 -> 4948.7097 | P6: =SUM(N6) -> 230 | Q6: =P6*$B$4 -> 4948.7097 | R6: =SUM(P6) -> 230 | S6: =R6*$B$4 -> 4948.7097 | T6: =SUM(R6) -> 230 | U6: =T6*$B$4 -> 4948.7097 | V6: =SUM(T6) -> 230 | W6: =V6*$B$4 -> 4948.7097 | X6: =SUM(Y6/73370) -> 0.74193548 | Y6: =SUM(C6+E6+G6+I6+K6+M6+O6+Q6+S6+U6+W6) -> 54435.806 | Z6: ='B5'!C5 -> 237 | AA6: =SUM(Z6*$Z$4) -> 2370 | AB6: =SUM(Z6) -> 237 | AC6: =SUM(AB6*$Z$4) -> 2370 | AD6: =SUM(AB6) -> 237 | AE6: =SUM(AD6*$Z$4) -> 2370 | AF6: =SUM(AD6) -> 237 | AG6: =SUM(AF6*$Z$4) -> 2370 | AH6: =SUM(AF6) -> 237 | AI6: =SUM(AH6*$Z$4) -> 2370 | AJ6: =SUM(AH6) -> 237 | AK6: =SUM(AJ6*$Z$4) -> 2370 | AL6: =SUM(AJ6) -> 237 | AM6: =SUM(AL6*$Z$4) -> 2370 | AN6: =SUM(AO6/19600) -> 0.84642857 | AO6: =SUM(AA6+AC6+AE6+AG6+AI6+AK6+AM6) -> 16590 | AQ6: =SUM(AR6/92970) -> 0.76396479 | AR6: =Y6+AO6 -> 71025.806 | AS6: =SUM(AR6-AR5-AT6) -> -1851.5161 | AT6: 6145 | AU6: 0.96 | AV6: =IF(AT6>0,AU6,AV5) -> 0.96 | AW6: =-SUM('B5'!AI5) -> -359 | AX6: =-SUM(AW6-AS6) -> -1492.5161 | AY6: =SUM(AX6+AW6) -> -1851.5161 | AZ6: =ELEC!A3 -> 0 | BA6: ='General information '!D6 -> 14.5 | BB6: =SUM('General information '!E6) -> 0.65 | BC6: =IF(AR3>=AR6,0,1) -> 0 | BD6: 19222 | BE6: =(305/1185)*ELEC!Q4 -> 1987.519 | BG6: =#REF!-BE6 -> #REF! | BH6: 21 | BI6: 12 | BJ6: =AX6/BI6 -> -124.37634 | BK6: =GEN!AF3 -> 0.28775
A7: =ELEC!C4 -> 44288 | B7: ='B5'!B6 -> 219 | C7: =B7*$B$4 -> 4712.0323 | D7: =SUM(B7) -> 219 | E7: =D7*$B$4 -> 4712.0323 | F7: =SUM(D7) -> 219 | G7: =F7*$B$4 -> 4712.0323 | H7: =SUM(F7) -> 219 | I7: =H7*$B$4 -> 4712.0323 | J7: =SUM(H7) -> 219 | K7: =J7*$B$4 -> 4712.0323 | L7: =SUM(J7) -> 219 | M7: =L7*$B$4 -> 4712.0323 | N7: =SUM(L7) -> 219 | O7: =N7*$B$4 -> 4712.0323 | P7: =SUM(N7) -> 219 | Q7: =P7*$B$4 -> 4712.0323 | R7: =SUM(P7) -> 219 | S7: =R7*$B$4 -> 4712.0323 | T7: =SUM(R7) -> 219 | U7: =T7*$B$4 -> 4712.0323 | V7: =SUM(T7) -> 219 | W7: =V7*$B$4 -> 4712.0323 | X7: =SUM(Y7/73370) -> 0.70645161 | Y7: =SUM(C7+E7+G7+I7+K7+M7+O7+Q7+S7+U7+W7) -> 51832.355 | Z7: ='B5'!C6 -> 226 | AA7: =SUM(Z7*$Z$4) -> 2260 | AB7: =SUM(Z7) -> 226 | AC7: =SUM(AB7*$Z$4) -> 2260 | AD7: =SUM(AB7) -> 226 | AE7: =SUM(AD7*$Z$4) -> 2260 | AF7: =SUM(AD7) -> 226 | AG7: =SUM(AF7*$Z$4) -> 2260 | AH7: =SUM(AF7) -> 226 | AI7: =SUM(AH7*$Z$4) -> 2260 | AJ7: =SUM(AH7) -> 226 | AK7: =SUM(AJ7*$Z$4) -> 2260 | AL7: =SUM(AJ7) -> 226 | AM7: =SUM(AL7*$Z$4) -> 2260 | AN7: =SUM(AO7/19600) -> 0.80714286 | AO7: =SUM(AA7+AC7+AE7+AG7+AI7+AK7+AM7) -> 15820 | AQ7: =SUM(AR7/92970) -> 0.72767941 | AR7: =Y7+AO7 -> 67652.355 | AS7: =SUM(AR7-AR6-AT7) -> -3373.4516 | AV7: =IF(AT7>0,AU7,AV6) -> 0.96 | AW7: =-SUM('B5'!AI6) -> -298 | AX7: =-SUM(AW7-AS7) -> -3075.4516 | AY7: =SUM(AX7+AW7) -> -3373.4516 | AZ7: =ELEC!A4 -> 0 | BA7: ='General information '!D7 -> 13.5 | BB7: =SUM('General information '!E7) -> 0.67 | BC7: 0 | BD7: 19222 | BE7: =(305/1185)*ELEC!Q5 -> 2126.5063 | BG7: =#REF!-BE7 -> #REF! | BH7: 19 | BI7: 15 | BJ7: =AX7/BI7 -> -205.03011 | BK7: =GEN!AF4 -> 0.34473214
A8: =ELEC!C5 -> 44289 | B8: ='B5'!B7 -> 208 | C8: =B8*$B$4 -> 4475.3548 | D8: =SUM(B8) -> 208 | E8: =D8*$B$4 -> 4475.3548 | F8: =SUM(D8) -> 208 | G8: =F8*$B$4 -> 4475.3548 | H8: =SUM(F8) -> 208 | I8: =H8*$B$4 -> 4475.3548 | J8: =SUM(H8) -> 208 | K8: =J8*$B$4 -> 4475.3548 | L8: =SUM(J8) -> 208 | M8: =L8*$B$4 -> 4475.3548 | N8: =SUM(L8) -> 208 | O8: =N8*$B$4 -> 4475.3548 | P8: =SUM(N8) -> 208 | Q8: =P8*$B$4 -> 4475.3548 | R8: =SUM(P8) -> 208 | S8: =R8*$B$4 -> 4475.3548 | T8: =SUM(R8) -> 208 | U8: =T8*$B$4 -> 4475.3548 | V8: =SUM(T8) -> 208 | W8: =V8*$B$4 -> 4475.3548 | X8: =SUM(Y8/73370) -> 0.67096774 | Y8: =SUM(C8+E8+G8+I8+K8+M8+O8+Q8+S8+U8+W8) -> 49228.903 | Z8: ='B5'!C7 -> 215 | AA8: =SUM(Z8*$Z$4) -> 2150 | AB8: =SUM(Z8) -> 215 | AC8: =SUM(AB8*$Z$4) -> 2150 | AD8: =SUM(AB8) -> 215 | AE8: =SUM(AD8*$Z$4) -> 2150 | AF8: =SUM(AD8) -> 215 | AG8: =SUM(AF8*$Z$4) -> 2150 | AH8: =SUM(AF8) -> 215 | AI8: =SUM(AH8*$Z$4) -> 2150 | AJ8: =SUM(AH8) -> 215 | AK8: =SUM(AJ8*$Z$4) -> 2150 | AL8: =SUM(AJ8) -> 215 | AM8: =SUM(AL8*$Z$4) -> 2150 | AN8: =SUM(AO8/19600) -> 0.76785714 | AO8: =SUM(AA8+AC8+AE8+AG8+AI8+AK8+AM8) -> 15050 | AQ8: =SUM(AR8/92970) -> 0.69139403 | AR8: =Y8+AO8 -> 64278.903 | AS8: =SUM(AR8-AR7-AT8) -> -3373.4516 | AV8: =IF(AT8>0,AU8,AV7) -> 0.96 | AW8: =-SUM('B5'!AI7) -> -287 | AX8: =-SUM(AW8-AS8) -> -3086.4516 | AY8: =SUM(AX8+AW8) -> -3373.4516 | AZ8: =ELEC!A5 -> 0 | BA8: ='General information '!D8 -> 17 | BB8: =SUM('General information '!E8) -> 0.59 | BC8: =IF(AR7>=AR8,0,1) -> 0 | BD8: 19222 | BE8: =(305/1185)*ELEC!Q6 -> 2043.8861 | BG8: =#REF!-BE8 -> #REF! | BH8: 16 | BI8: 9 | BJ8: =AX8/BI8 -> -342.93907 | BK8: =GEN!AF5 -> 0.34425
A9: =ELEC!C6 -> 44290 | B9: ='B5'!B8 -> 197 | C9: =B9*$B$4 -> 4238.6774 | D9: =SUM(B9) -> 197 | E9: =D9*$B$4 -> 4238.6774 | F9: =SUM(D9) -> 197 | G9: =F9*$B$4 -> 4238.6774 | H9: =SUM(F9) -> 197 | I9: =H9*$B$4 -> 4238.6774 | J9: =SUM(H9) -> 197 | K9: =J9*$B$4 -> 4238.6774 | L9: =SUM(J9) -> 197 | M9: =L9*$B$4 -> 4238.6774 | N9: =SUM(L9) -> 197 | O9: =N9*$B$4 -> 4238.6774 | P9: =SUM(N9) -> 197 | Q9: =P9*$B$4 -> 4238.6774 | R9: =SUM(P9) -> 197 | S9: =R9*$B$4 -> 4238.6774 | T9: =SUM(R9) -> 197 | U9: =T9*$B$4 -> 4238.6774 | V9: =SUM(T9) -> 197 | W9: =V9*$B$4 -> 4238.6774 | X9: =SUM(Y9/73370) -> 0.63548387 | Y9: =SUM(C9+E9+G9+I9+K9+M9+O9+Q9+S9+U9+W9) -> 46625.452 | Z9: ='B5'!C8 -> 204 | AA9: =SUM(Z9*$Z$4) -> 2040 | AB9: =SUM(Z9) -> 204 | AC9: =SUM(AB9*$Z$4) -> 2040 | AD9: =SUM(AB9) -> 204 | AE9: =SUM(AD9*$Z$4) -> 2040 | AF9: =SUM(AD9) -> 204 | AG9: =SUM(AF9*$Z$4) -> 2040 | AH9: =SUM(AF9) -> 204 | AI9: =SUM(AH9*$Z$4) -> 2040 | AJ9: =SUM(AH9) -> 204 | AK9: =SUM(AJ9*$Z$4) -> 2040 | AL9: =SUM(AJ9) -> 204 | AM9: =SUM(AL9*$Z$4) -> 2040 | AN9: =SUM(AO9/19600) -> 0.72857143 | AO9: =SUM(AA9+AC9+AE9+AG9+AI9+AK9+AM9) -> 14280 | AQ9: =SUM(AR9/92970) -> 0.65510865 | AR9: =Y9+AO9 -> 60905.452 | AS9: =SUM(AR9-AR8-AT9) -> -3373.4516 | AV9: =IF(AT9>0,AU9,AV8) -> 0.96 | AW9: =-SUM('B5'!AI8) -> -290 | AX9: =-SUM(AW9-AS9) -> -3083.4516 | AY9: =SUM(AX9+AW9) -> -3373.4516 | AZ9: =ELEC!A6 -> 0 | BA9: ='General information '!D9 -> 16.5 | BB9: =SUM('General information '!E9) -> 0.65 | BC9: =IF(AR8>=AR9,0,1) -> 0 | BD9: 19222 | BE9: =(305/1185)*ELEC!Q7 -> 1941.4473 | BG9: =#REF!-BE9 -> #REF! | BH9: 18 | BI9: 6 | BJ9: =AX9/BI9 -> -513.9086 | BK9: =GEN!AF6 -> 0.27572917
A10: =ELEC!C7 -> 44291 | B10: ='B5'!B9 -> 188 | C10: =B10*$B$4 -> 4045.0323 | D10: =SUM(B10) -> 188 | E10: =D10*$B$4 -> 4045.0323 | F10: =SUM(D10) -> 188 | G10: =F10*$B$4 -> 4045.0323 | H10: =SUM(F10) -> 188 | I10: =H10*$B$4 -> 4045.0323 | J10: =SUM(H10) -> 188 | K10: =J10*$B$4 -> 4045.0323 | L10: =SUM(J10) -> 188 | M10: =L10*$B$4 -> 4045.0323 | N10: =SUM(L10) -> 188 | O10: =N10*$B$4 -> 4045.0323 | P10: =SUM(N10) -> 188 | Q10: =P10*$B$4 -> 4045.0323 | R10: =SUM(P10) -> 188 | S10: =R10*$B$4 -> 4045.0323 | T10: =SUM(R10) -> 188 | U10: =T10*$B$4 -> 4045.0323 | V10: =SUM(T10) -> 188 | W10: =V10*$B$4 -> 4045.0323 | X10: =SUM(Y10/73370) -> 0.60645161 | Y10: =SUM(C10+E10+G10+I10+K10+M10+O10+Q10+S10+U10+W10) -> 44495.355 | Z10: ='B5'!C9 -> 195 | AA10: =SUM(Z10*$Z$4) -> 1950 | AB10: =SUM(Z10) -> 195 | AC10: =SUM(AB10*$Z$4) -> 1950 | AD10: =SUM(AB10) -> 195 | AE10: =SUM(AD10*$Z$4) -> 1950 | AF10: =SUM(AD10) -> 195 | AG10: =SUM(AF10*$Z$4) -> 1950 | AH10: =SUM(AF10) -> 195 | AI10: =SUM(AH10*$Z$4) -> 1950 | AJ10: =SUM(AH10) -> 195 | AK10: =SUM(AJ10*$Z$4) -> 1950 | AL10: =SUM(AJ10) -> 195 | AM10: =SUM(AL10*$Z$4) -> 1950 | AN10: =SUM(AO10/19600) -> 0.69642857 | AO10: =SUM(AA10+AC10+AE10+AG10+AI10+AK10+AM10) -> 13650 | AQ10: =SUM(AR10/92970) -> 0.62542062 | AR10: =Y10+AO10 -> 58145.355 | AS10: =SUM(AR10-AR9-AT10) -> -2760.0968 | AV10: =IF(AT10>0,AU10,AV9) -> 0.96 | AW10: =-SUM('B5'!AI9) -> -404 | AX10: =-SUM(AW10-AS10) -> -2356.0968 | AY10: =SUM(AX10+AW10) -> -2760.0968 | AZ10: =ELEC!A7 -> 0 | BA10: ='General information '!D10 -> 17 | BB10: =SUM('General information '!E10) -> 0.67 | BC10: =IF(AR9>=AR10,0,1) -> 0 | BD10: 19222 | BE10: =(305/1185)*ELEC!Q8 -> 2281.4515 | BG10: =#REF!-BE10 -> #REF! | BH10: 16 | BI10: 7 | BJ10: =AX10/BI10 -> -336.58525 | BK10: =GEN!AF7 -> 0.31429167
A11: =ELEC!C8 -> 44292 | B11: ='B5'!B10 -> 177 | C11: =B11*$B$4 -> 3808.3548 | D11: =SUM(B11) -> 177 | E11: =D11*$B$4 -> 3808.3548 | F11: =SUM(D11) -> 177 | G11: =F11*$B$4 -> 3808.3548 | H11: =SUM(F11) -> 177 | I11: =H11*$B$4 -> 3808.3548 | J11: =SUM(H11) -> 177 | K11: =J11*$B$4 -> 3808.3548 | L11: =SUM(J11) -> 177 | M11: =L11*$B$4 -> 3808.3548 | N11: =SUM(L11) -> 177 | O11: =N11*$B$4 -> 3808.3548 | P11: =SUM(N11) -> 177 | Q11: =P11*$B$4 -> 3808.3548 | R11: =SUM(P11) -> 177 | S11: =R11*$B$4 -> 3808.3548 | T11: =SUM(R11) -> 177 | U11: =T11*$B$4 -> 3808.3548 | V11: =SUM(T11) -> 177 | W11: =V11*$B$4 -> 3808.3548 | X11: =SUM(Y11/73370) -> 0.57096774 | Y11: =SUM(C11+E11+G11+I11+K11+M11+O11+Q11+S11+U11+W11) -> 41891.903 | Z11: ='B5'!C10 -> 183 | AA11: =SUM(Z11*$Z$4) -> 1830 | AB11: =SUM(Z11) -> 183 | AC11: =SUM(AB11*$Z$4) -> 1830 | AD11: =SUM(AB11) -> 183 | AE11: =SUM(AD11*$Z$4) -> 1830 | AF11: =SUM(AD11) -> 183 | AG11: =SUM(AF11*$Z$4) -> 1830 | AH11: =SUM(AF11) -> 183 | AI11: =SUM(AH11*$Z$4) -> 1830 | AJ11: =SUM(AH11) -> 183 | AK11: =SUM(AJ11*$Z$4) -> 1830 | AL11: =SUM(AJ11) -> 183 | AM11: =SUM(AL11*$Z$4) -> 1830 | AN11: =SUM(AO11/19600) -> 0.65357143 | AO11: =SUM(AA11+AC11+AE11+AG11+AI11+AK11+AM11) -> 12810 | AQ11: =SUM(AR11/92970) -> 0.58838231 | AR11: =Y11+AO11 -> 54701.903 | AS11: =SUM(AR11-AR10-AT11) -> -3443.4516 | AV11: =IF(AT11>0,AU11,AV10) -> 0.96 | AW11: =-SUM('B5'!AI10) -> -308 | AX11: =-SUM(AW11-AS11) -> -3135.4516 | AY11: =SUM(AX11+AW11) -> -3443.4516 | AZ11: =ELEC!A8 -> 0 | BA11: ='General information '!D11 -> 22.5 | BB11: =SUM('General information '!E11) -> 0.54 | BC11: =IF(AR10>=AR11,0,1) -> 0 | BD11: 19222 | BE11: =(305/1185)*ELEC!Q9 -> 1407.8903 | BG11: =#REF!-BE11 -> #REF! | BH11: 16.5 | BI11: 9.3 | BJ11: =AX11/BI11 -> -337.14533 | BK11: =GEN!AF8 -> 0.39571429
A12: =ELEC!C9 -> 44293 | B12: ='B5'!B11 -> 228 | C12: =B12*$B$4 -> 4905.6774 | D12: =SUM(B12) -> 228 | E12: =D12*$B$4 -> 4905.6774 | F12: =SUM(D12) -> 228 | G12: =F12*$B$4 -> 4905.6774 | H12: =SUM(F12) -> 228 | I12: =H12*$B$4 -> 4905.6774 | J12: =SUM(H12) -> 228 | K12: =J12*$B$4 -> 4905.6774 | L12: =SUM(J12) -> 228 | M12: =L12*$B$4 -> 4905.6774 | N12: =SUM(L12) -> 228 | O12: =N12*$B$4 -> 4905.6774 | P12: =SUM(N12) -> 228 | Q12: =P12*$B$4 -> 4905.6774 | R12: =SUM(P12) -> 228 | S12: =R12*$B$4 -> 4905.6774 | T12: =SUM(R12) -> 228 | U12: =T12*$B$4 -> 4905.6774 | V12: =SUM(T12) -> 228 | W12: =V12*$B$4 -> 4905.6774 | X12: =SUM(Y12/73370) -> 0.73548387 | Y12: =SUM(C12+E12+G12+I12+K12+M12+O12+Q12+S12+U12+W12) -> 53962.452 | Z12: ='B5'!C11 -> 235 | AA12: =SUM(Z12*$Z$4) -> 2350 | AB12: =SUM(Z12) -> 235 | AC12: =SUM(AB12*$Z$4) -> 2350 | AD12: =SUM(AB12) -> 235 | AE12: =SUM(AD12*$Z$4) -> 2350 | AF12: =SUM(AD12) -> 235 | AG12: =SUM(AF12*$Z$4) -> 2350 | AH12: =SUM(AF12) -> 235 | AI12: =SUM(AH12*$Z$4) -> 2350 | AJ12: =SUM(AH12) -> 235 | AK12: =SUM(AJ12*$Z$4) -> 2350 | AL12: =SUM(AJ12) -> 235 | AM12: =SUM(AL12*$Z$4) -> 2350 | AN12: =SUM(AO12/19600) -> 0.83928571 | AO12: =SUM(AA12+AC12+AE12+AG12+AI12+AK12+AM12) -> 16450 | AQ12: =SUM(AR12/92970) -> 0.75736745 | AR12: =Y12+AO12 -> 70412.452 | AS12: =SUM(AR12-AR11-AT12) -> 350.54839 | AT12: 15360 | AU12: 0.96 | AV12: =IF(AT12>0,AU12,AV11) -> 0.96 | AW12: =-SUM('B5'!AI11) -> -287 | AX12: =-SUM(AW12-AS12) -> 637.54839 | AY12: =SUM(AX12+AW12) -> 350.54839 | AZ12: =ELEC!A9 -> 0 | BA12: ='General information '!D12 -> 21.5 | BB12: =SUM('General information '!E12) -> 0.63 | BC12: =IF(AR11>=AR12,0,1) -> 1 | BD12: 19222 | BE12: =(305/1185)*ELEC!Q10 -> 1154.8819 | BG12: =#REF!-BE12 -> #REF! | BH12: 15.5 | BI12: 3.7 | BJ12: =AX12/BI12 -> 172.31037 | BK12: =GEN!AF9 -> 0.42734375
A13: =ELEC!C10 -> 44294 | B13: ='B5'!B12 -> 222 | C13: =B13*$B$4 -> 4776.5806 | D13: =SUM(B13) -> 222 | E13: =D13*$B$4 -> 4776.5806 | F13: =SUM(D13) -> 222 | G13: =F13*$B$4 -> 4776.5806 | H13: =SUM(F13) -> 222 | I13: =H13*$B$4 -> 4776.5806 | J13: =SUM(H13) -> 222 | K13: =J13*$B$4 -> 4776.5806 | L13: =SUM(J13) -> 222 | M13: =L13*$B$4 -> 4776.5806 | N13: =SUM(L13) -> 222 | O13: =N13*$B$4 -> 4776.5806 | P13: =SUM(N13) -> 222 | Q13: =P13*$B$4 -> 4776.5806 | R13: =SUM(P13) -> 222 | S13: =R13*$B$4 -> 4776.5806 | T13: =SUM(R13) -> 222 | U13: =T13*$B$4 -> 4776.5806 | V13: =SUM(T13) -> 222 | W13: =V13*$B$4 -> 4776.5806 | X13: =SUM(Y13/73370) -> 0.71612903 | Y13: =SUM(C13+E13+G13+I13+K13+M13+O13+Q13+S13+U13+W13) -> 52542.387 | Z13: ='B5'!C12 -> 228 | AA13: =SUM(Z13*$Z$4) -> 2280 | AB13: =SUM(Z13) -> 228 | AC13: =SUM(AB13*$Z$4) -> 2280 | AD13: =SUM(AB13) -> 228 | AE13: =SUM(AD13*$Z$4) -> 2280 | AF13: =SUM(AD13) -> 228 | AG13: =SUM(AF13*$Z$4) -> 2280 | AH13: =SUM(AF13) -> 228 | AI13: =SUM(AH13*$Z$4) -> 2280 | AJ13: =SUM(AH13) -> 228 | AK13: =SUM(AJ13*$Z$4) -> 2280 | AL13: =SUM(AJ13) -> 228 | AM13: =SUM(AL13*$Z$4) -> 2280 | AN13: =SUM(AO13/19600) -> 0.81428571 | AO13: =SUM(AA13+AC13+AE13+AG13+AI13+AK13+AM13) -> 15960 | AQ13: =SUM(AR13/92970) -> 0.73682249 | AR13: =Y13+AO13 -> 68502.387 | AS13: =SUM(AR13-AR12-AT13) -> -1910.0645 | AV13: =IF(AT13>0,AU13,AV12) -> 0.96 | AW13: =-SUM('B5'!AI12) -> -416 | AX13: =-SUM(AW13-AS13) -> -1494.0645 | AY13: =SUM(AX13+AW13) -> -1910.0645 | AZ13: =ELEC!A10 -> 0 | BA13: ='General information '!D13 -> 18.5 | BB13: =SUM('General information '!E13) -> 0.81 | BC13: =IF(AR12>=AR13,0,1) -> 0 | BD13: 19222 | BE13: =(305/1185)*ELEC!Q11 -> 1065.5696 | BG13: =#REF!-BE13 -> #REF! | BI13: 5 | BJ13: =AX13/BI13 -> -298.8129 | BK13: =GEN!AF10 -> 0.400625
A14: =ELEC!C11 -> 44295 | B14: ='B5'!B13 -> 217 | C14: =B14*$B$4 -> 4669 | D14: =SUM(B14) -> 217 | E14: =D14*$B$4 -> 4669 | F14: =SUM(D14) -> 217 | G14: =F14*$B$4 -> 4669 | H14: =SUM(F14) -> 217 | I14: =H14*$B$4 -> 4669 | J14: =SUM(H14) -> 217 | K14: =J14*$B$4 -> 4669 | L14: =SUM(J14) -> 217 | M14: =L14*$B$4 -> 4669 | N14: =SUM(L14) -> 217 | O14: =N14*$B$4 -> 4669 | P14: =SUM(N14) -> 217 | Q14: =P14*$B$4 -> 4669 | R14: =SUM(P14) -> 217 | S14: =R14*$B$4 -> 4669 | T14: =SUM(R14) -> 217 | U14: =T14*$B$4 -> 4669 | V14: =SUM(T14) -> 217 | W14: =V14*$B$4 -> 4669 | X14: =SUM(Y14/73370) -> 0.7 | Y14: =SUM(C14+E14+G14+I14+K14+M14+O14+Q14+S14+U14+W14) -> 51359 | Z14: ='B5'!C13 -> 223 | AA14: =SUM(Z14*$Z$4) -> 2230 | AB14: =SUM(Z14) -> 223 | AC14: =SUM(AB14*$Z$4) -> 2230 | AD14: =SUM(AB14) -> 223 | AE14: =SUM(AD14*$Z$4) -> 2230 | AF14: =SUM(AD14) -> 223 | AG14: =SUM(AF14*$Z$4) -> 2230 | AH14: =SUM(AF14) -> 223 | AI14: =SUM(AH14*$Z$4) -> 2230 | AJ14: =SUM(AH14) -> 223 | AK14: =SUM(AJ14*$Z$4) -> 2230 | AL14: =SUM(AJ14) -> 223 | AM14: =SUM(AL14*$Z$4) -> 2230 | AN14: =SUM(AO14/19600) -> 0.79642857 | AO14: =SUM(AA14+AC14+AE14+AG14+AI14+AK14+AM14) -> 15610 | AQ14: =SUM(AR14/92970) -> 0.72032914 | AR14: =Y14+AO14 -> 66969 | AS14: =SUM(AR14-AR13-AT14) -> -1533.3871 | AV14: =IF(AT14>0,AU14,AV13) -> 0.96 | AW14: =-SUM('B5'!AI13) -> -326 | AX14: =-SUM(AW14-AS14) -> -1207.3871 | AY14: =SUM(AX14+AW14) -> -1533.3871 | AZ14: =ELEC!A11 -> 0 | BA14: ='General information '!D14 -> 18 | BB14: =SUM('General information '!E14) -> 0.66 | BC14: =IF(AR13>=AR14,0,1) -> 0 | BD14: 19222 | BE14: =(305/1185)*ELEC!Q12 -> 729.68354 | BG14: =#REF!-BE14 -> #REF! | BI14: 3 | BJ14: =AX14/BI14 -> -402.46237 | BK14: =GEN!AF11 -> 0.43125
A15: =ELEC!C12 -> 44296 | B15: ='B5'!B14 -> 211 | C15: =B15*$B$4 -> 4539.9032 | D15: =SUM(B15) -> 211 | E15: =D15*$B$4 -> 4539.9032 | F15: =SUM(D15) -> 211 | G15: =F15*$B$4 -> 4539.9032 | H15: =SUM(F15) -> 211 | I15: =H15*$B$4 -> 4539.9032 | J15: =SUM(H15) -> 211 | K15: =J15*$B$4 -> 4539.9032 | L15: =SUM(J15) -> 211 | M15: =L15*$B$4 -> 4539.9032 | N15: =SUM(L15) -> 211 | O15: =N15*$B$4 -> 4539.9032 | P15: =SUM(N15) -> 211 | Q15: =P15*$B$4 -> 4539.9032 | R15: =SUM(P15) -> 211 | S15: =R15*$B$4 -> 4539.9032 | T15: =SUM(R15) -> 211 | U15: =T15*$B$4 -> 4539.9032 | V15: =SUM(T15) -> 211 | W15: =V15*$B$4 -> 4539.9032 | X15: =SUM(Y15/73370) -> 0.68064516 | Y15: =SUM(C15+E15+G15+I15+K15+M15+O15+Q15+S15+U15+W15) -> 49938.935 | Z15: ='B5'!C14 -> 218 | AA15: =SUM(Z15*$Z$4) -> 2180 | AB15: =SUM(Z15) -> 218 | AC15: =SUM(AB15*$Z$4) -> 2180 | AD15: =SUM(AB15) -> 218 | AE15: =SUM(AD15*$Z$4) -> 2180 | AF15: =SUM(AD15) -> 218 | AG15: =SUM(AF15*$Z$4) -> 2180 | AH15: =SUM(AF15) -> 218 | AI15: =SUM(AH15*$Z$4) -> 2180 | AJ15: =SUM(AH15) -> 218 | AK15: =SUM(AJ15*$Z$4) -> 2180 | AL15: =SUM(AJ15) -> 218 | AM15: =SUM(AL15*$Z$4) -> 2180 | AN15: =SUM(AO15/19600) -> 0.77857143 | AO15: =SUM(AA15+AC15+AE15+AG15+AI15+AK15+AM15) -> 15260 | AQ15: =SUM(AR15/92970) -> 0.70129005 | AR15: =Y15+AO15 -> 65198.935 | AS15: =SUM(AR15-AR14-AT15) -> -1770.0645 | AV15: =IF(AT15>0,AU15,AV14) -> 0.96 | AW15: =-SUM('B5'!AI14) -> -409 | AX15: =-SUM(AW15-AS15) -> -1361.0645 | AY15: =SUM(AX15+AW15) -> -1770.0645 | AZ15: =ELEC!A12 -> 0 | BA15: ='General information '!D15 -> 15 | BB15: =SUM('General information '!E15) -> 0.56 | BC15: =IF(AR14>=AR15,0,1) -> 0 | BD15: 19222 | BE15: =(305/1185)*ELEC!Q13 -> 793.51477 | BG15: =#REF!-BE15 -> #REF! | BI15: 4 | BJ15: =AX15/BI15 -> -340.26613 | BK15: =GEN!AF12 -> 0.253125
A16: =ELEC!C13 -> 44297 | B16: ='B5'!B15 -> 207 | C16: =B16*$B$4 -> 4453.8387 | D16: =SUM(B16) -> 207 | E16: =D16*$B$4 -> 4453.8387 | F16: =SUM(D16) -> 207 | G16: =F16*$B$4 -> 4453.8387 | H16: =SUM(F16) -> 207 | I16: =H16*$B$4 -> 4453.8387 | J16: =SUM(H16) -> 207 | K16: =J16*$B$4 -> 4453.8387 | L16: =SUM(J16) -> 207 | M16: =L16*$B$4 -> 4453.8387 | N16: =SUM(L16) -> 207 | O16: =N16*$B$4 -> 4453.8387 | P16: =SUM(N16) -> 207 | Q16: =P16*$B$4 -> 4453.8387 | R16: =SUM(P16) -> 207 | S16: =R16*$B$4 -> 4453.8387 | T16: =SUM(R16) -> 207 | U16: =T16*$B$4 -> 4453.8387 | V16: =SUM(T16) -> 207 | W16: =V16*$B$4 -> 4453.8387 | X16: =SUM(Y16/73370) -> 0.66774194 | Y16: =SUM(C16+E16+G16+I16+K16+M16+O16+Q16+S16+U16+W16) -> 48992.226 | Z16: ='B5'!C15 -> 213 | AA16: =SUM(Z16*$Z$4) -> 2130 | AB16: =SUM(Z16) -> 213 | AC16: =SUM(AB16*$Z$4) -> 2130 | AD16: =SUM(AB16) -> 213 | AE16: =SUM(AD16*$Z$4) -> 2130 | AF16: =SUM(AD16) -> 213 | AG16: =SUM(AF16*$Z$4) -> 2130 | AH16: =SUM(AF16) -> 213 | AI16: =SUM(AH16*$Z$4) -> 2130 | AJ16: =SUM(AH16) -> 213 | AK16: =SUM(AJ16*$Z$4) -> 2130 | AL16: =SUM(AJ16) -> 213 | AM16: =SUM(AL16*$Z$4) -> 2130 | AN16: =SUM(AO16/19600) -> 0.76071429 | AO16: =SUM(AA16+AC16+AE16+AG16+AI16+AK16+AM16) -> 14910 | AQ16: =SUM(AR16/92970) -> 0.68734243 | AR16: =Y16+AO16 -> 63902.226 | AS16: =SUM(AR16-AR15-AT16) -> -1296.7097 | AV16: =IF(AT16>0,AU16,AV15) -> 0.96 | AW16: =-SUM('B5'!AI15) -> -368 | AX16: =-SUM(AW16-AS16) -> -928.70968 | AY16: =SUM(AX16+AW16) -> -1296.7097 | AZ16: =ELEC!A13 -> 0 | BA16: ='General information '!D16 -> 14.5 | BB16: =SUM('General information '!E16) -> 0.58 | BC16: =IF(AR15>=AR16,0,1) -> 0 | BD16: 19222 | BE16: =(305/1185)*ELEC!Q14 -> 1118.8481 | BG16: =#REF!-BE16 -> #REF! | BI16: 3 | BJ16: =AX16/BI16 -> -309.56989 | BK16: =GEN!AF13 -> 0.32114583
A17: =ELEC!C14 -> 44298 | B17: ='B5'!B16 -> 200 | C17: =B17*$B$4 -> 4303.2258 | D17: =SUM(B17) -> 200 | E17: =D17*$B$4 -> 4303.2258 | F17: =SUM(D17) -> 200 | G17: =F17*$B$4 -> 4303.2258 | H17: =SUM(F17) -> 200 | I17: =H17*$B$4 -> 4303.2258 | J17: =SUM(H17) -> 200 | K17: =J17*$B$4 -> 4303.2258 | L17: =SUM(J17) -> 200 | M17: =L17*$B$4 -> 4303.2258 | N17: =SUM(L17) -> 200 | O17: =N17*$B$4 -> 4303.2258 | P17: =SUM(N17) -> 200 | Q17: =P17*$B$4 -> 4303.2258 | R17: =SUM(P17) -> 200 | S17: =R17*$B$4 -> 4303.2258 | T17: =SUM(R17) -> 200 | U17: =T17*$B$4 -> 4303.2258 | V17: =SUM(T17) -> 200 | W17: =V17*$B$4 -> 4303.2258 | X17: =SUM(Y17/73370) -> 0.64516129 | Y17: =SUM(C17+E17+G17+I17+K17+M17+O17+Q17+S17+U17+W17) -> 47335.484 | Z17: ='B5'!C16 -> 207 | AA17: =SUM(Z17*$Z$4) -> 2070 | AB17: =SUM(Z17) -> 207 | AC17: =SUM(AB17*$Z$4) -> 2070 | AD17: =SUM(AB17) -> 207 | AE17: =SUM(AD17*$Z$4) -> 2070 | AF17: =SUM(AD17) -> 207 | AG17: =SUM(AF17*$Z$4) -> 2070 | AH17: =SUM(AF17) -> 207 | AI17: =SUM(AH17*$Z$4) -> 2070 | AJ17: =SUM(AH17) -> 207 | AK17: =SUM(AJ17*$Z$4) -> 2070 | AL17: =SUM(AJ17) -> 207 | AM17: =SUM(AL17*$Z$4) -> 2070 | AN17: =SUM(AO17/19600) -> 0.73928571 | AO17: =SUM(AA17+AC17+AE17+AG17+AI17+AK17+AM17) -> 14490 | AQ17: =SUM(AR17/92970) -> 0.66500467 | AR17: =Y17+AO17 -> 61825.484 | AS17: =SUM(AR17-AR16-AT17) -> -2076.7419 | AV17: =IF(AT17>0,AU17,AV16) -> 0.96 | AW17: =-SUM('B5'!AI16) -> -367 | AX17: =-SUM(AW17-AS17) -> -1709.7419 | AY17: =SUM(AX17+AW17) -> -2076.7419 | AZ17: =ELEC!A14 -> 0 | BA17: ='General information '!D17 -> 14.5 | BB17: =SUM('General information '!E17) -> 0.71 | BC17: =IF(AR16>=AR17,0,1) -> 0 | BD17: 19222 | BE17: =(305/1185)*ELEC!Q15 -> 838.04219 | BG17: =#REF!-BE17 -> #REF!
A18: =ELEC!C15 -> 44299 | B18: ='B5'!B17 -> 195 | C18: =B18*$B$4 -> 4195.6452 | D18: =SUM(B18) -> 195 | E18: =D18*$B$4 -> 4195.6452 | F18: =SUM(D18) -> 195 | G18: =F18*$B$4 -> 4195.6452 | H18: =SUM(F18) -> 195 | I18: =H18*$B$4 -> 4195.6452 | J18: =SUM(H18) -> 195 | K18: =J18*$B$4 -> 4195.6452 | L18: =SUM(J18) -> 195 | M18: =L18*$B$4 -> 4195.6452 | N18: =SUM(L18) -> 195 | O18: =N18*$B$4 -> 4195.6452 | P18: =SUM(N18) -> 195 | Q18: =P18*$B$4 -> 4195.6452 | R18: =SUM(P18) -> 195 | S18: =R18*$B$4 -> 4195.6452 | T18: =SUM(R18) -> 195 | U18: =T18*$B$4 -> 4195.6452 | V18: =SUM(T18) -> 195 | W18: =V18*$B$4 -> 4195.6452 | X18: =SUM(Y18/73370) -> 0.62903226 | Y18: =SUM(C18+E18+G18+I18+K18+M18+O18+Q18+S18+U18+W18) -> 46152.097 | Z18: ='B5'!C17 -> 202 | AA18: =SUM(Z18*$Z$4) -> 2020 | AB18: =SUM(Z18) -> 202 | AC18: =SUM(AB18*$Z$4) -> 2020 | AD18: =SUM(AB18) -> 202 | AE18: =SUM(AD18*$Z$4) -> 2020 | AF18: =SUM(AD18) -> 202 | AG18: =SUM(AF18*$Z$4) -> 2020 | AH18: =SUM(AF18) -> 202 | AI18: =SUM(AH18*$Z$4) -> 2020 | AJ18: =SUM(AH18) -> 202 | AK18: =SUM(AJ18*$Z$4) -> 2020 | AL18: =SUM(AJ18) -> 202 | AM18: =SUM(AL18*$Z$4) -> 2020 | AN18: =SUM(AO18/19600) -> 0.72142857 | AO18: =SUM(AA18+AC18+AE18+AG18+AI18+AK18+AM18) -> 14140 | AQ18: =SUM(AR18/92970) -> 0.64851131 | AR18: =Y18+AO18 -> 60292.097 | AS18: =SUM(AR18-AR17-AT18) -> -1533.3871 | AV18: =IF(AT18>0,AU18,AV17) -> 0.96 | AW18: =-SUM('B5'!AI17) -> -113 | AX18: =-SUM(AW18-AS18) -> -1420.3871 | AY18: =SUM(AX18+AW18) -> -1533.3871 | AZ18: =ELEC!A15 -> 0 | BA18: ='General information '!D18 -> 14.5 | BB18: =SUM('General information '!E18) -> 0.53 | BC18: =IF(AR17>=AR18,0,1) -> 0 | BD18: 19222 | BE18: =(305/1185)*ELEC!Q16 -> 772.1519 | BG18: =#REF!-BE18 -> #REF!
A19: =ELEC!C16 -> 44300 | B19: ='B5'!B18 -> 246 | C19: =B19*$B$4 -> 5292.9677 | D19: =SUM(B19) -> 246 | E19: =D19*$B$4 -> 5292.9677 | F19: =SUM(D19) -> 246 | G19: =F19*$B$4 -> 5292.9677 | H19: =SUM(F19) -> 246 | I19: =H19*$B$4 -> 5292.9677 | J19: =SUM(H19) -> 246 | K19: =J19*$B$4 -> 5292.9677 | L19: =SUM(J19) -> 246 | M19: =L19*$B$4 -> 5292.9677 | N19: =SUM(L19) -> 246 | O19: =N19*$B$4 -> 5292.9677 | P19: =SUM(N19) -> 246 | Q19: =P19*$B$4 -> 5292.9677 | R19: =SUM(P19) -> 246 | S19: =R19*$B$4 -> 5292.9677 | T19: =SUM(R19) -> 246 | U19: =T19*$B$4 -> 5292.9677 | V19: =SUM(T19) -> 246 | W19: =V19*$B$4 -> 5292.9677 | X19: =SUM(Y19/73370) -> 0.79354839 | Y19: =SUM(C19+E19+G19+I19+K19+M19+O19+Q19+S19+U19+W19) -> 58222.645 | Z19: ='B5'!C18 -> 252 | AA19: =SUM(Z19*$Z$4) -> 2520 | AB19: =SUM(Z19) -> 252 | AC19: =SUM(AB19*$Z$4) -> 2520 | AD19: =SUM(AB19) -> 252 | AE19: =SUM(AD19*$Z$4) -> 2520 | AF19: =SUM(AD19) -> 252 | AG19: =SUM(AF19*$Z$4) -> 2520 | AH19: =SUM(AF19) -> 252 | AI19: =SUM(AH19*$Z$4) -> 2520 | AJ19: =SUM(AH19) -> 252 | AK19: =SUM(AJ19*$Z$4) -> 2520 | AL19: =SUM(AJ19) -> 252 | AM19: =SUM(AL19*$Z$4) -> 2520 | AN19: =SUM(AO19/19600) -> 0.9 | AO19: =SUM(AA19+AC19+AE19+AG19+AI19+AK19+AM19) -> 17640 | AQ19: =SUM(AR19/92970) -> 0.81599059 | AR19: =Y19+AO19 -> 75862.645 | AS19: =SUM(AR19-AR18-AT19) -> 1025.5484 | AT19: 14545 | AU19: 0.93 | AV19: =IF(AT19>0,AU19,AV18) -> 0.93 | AW19: =-SUM('B5'!AI18) -> -591 | AX19: =-SUM(AW19-AS19) -> 1616.5484 | AY19: =SUM(AX19+AW19) -> 1025.5484 | AZ19: =ELEC!A16 -> 0 | BA19: ='General information '!D19 -> 16 | BB19: =SUM('General information '!E19) -> 0.53 | BC19: =IF(AR18>=AR19,0,1) -> 1 | BD19: 19222 | BE19: =(305/1185)*ELEC!Q17 -> 1286.9198 | BG19: =#REF!-BE19 -> #REF!
A20: =ELEC!C17 -> 44301 | B20: ='B5'!B19 -> 240 | C20: =B20*$B$4 -> 5163.871 | D20: =SUM(B20) -> 240 | E20: =D20*$B$4 -> 5163.871 | F20: =SUM(D20) -> 240 | G20: =F20*$B$4 -> 5163.871 | H20: =SUM(F20) -> 240 | I20: =H20*$B$4 -> 5163.871 | J20: =SUM(H20) -> 240 | K20: =J20*$B$4 -> 5163.871 | L20: =SUM(J20) -> 240 | M20: =L20*$B$4 -> 5163.871 | N20: =SUM(L20) -> 240 | O20: =N20*$B$4 -> 5163.871 | P20: =SUM(N20) -> 240 | Q20: =P20*$B$4 -> 5163.871 | R20: =SUM(P20) -> 240 | S20: =R20*$B$4 -> 5163.871 | T20: =SUM(R20) -> 240 | U20: =T20*$B$4 -> 5163.871 | V20: =SUM(T20) -> 240 | W20: =V20*$B$4 -> 5163.871 | X20: =SUM(Y20/73370) -> 0.77419355 | Y20: =SUM(C20+E20+G20+I20+K20+M20+O20+Q20+S20+U20+W20) -> 56802.581 | Z20: ='B5'!C19 -> 247 | AA20: =SUM(Z20*$Z$4) -> 2470 | AB20: =SUM(Z20) -> 247 | AC20: =SUM(AB20*$Z$4) -> 2470 | AD20: =SUM(AB20) -> 247 | AE20: =SUM(AD20*$Z$4) -> 2470 | AF20: =SUM(AD20) -> 247 | AG20: =SUM(AF20*$Z$4) -> 2470 | AH20: =SUM(AF20) -> 247 | AI20: =SUM(AH20*$Z$4) -> 2470 | AJ20: =SUM(AH20) -> 247 | AK20: =SUM(AJ20*$Z$4) -> 2470 | AL20: =SUM(AJ20) -> 247 | AM20: =SUM(AL20*$Z$4) -> 2470 | AN20: =SUM(AO20/19600) -> 0.88214286 | AO20: =SUM(AA20+AC20+AE20+AG20+AI20+AK20+AM20) -> 17290 | AQ20: =SUM(AR20/92970) -> 0.7969515 | AR20: =Y20+AO20 -> 74092.581 | AS20: =SUM(AR20-AR19-AT20) -> -1770.0645 | AV20: =IF(AT20>0,AU20,AV19) -> 0.93 | AW20: =-SUM('B5'!AI19) -> -291 | AX20: =-SUM(AW20-AS20) -> -1479.0645 | AY20: =SUM(AX20+AW20) -> -1770.0645 | AZ20: =ELEC!A17 -> 0 | BA20: ='General information '!D20 -> 19 | BB20: =SUM('General information '!E20) -> 0.62 | BC20: =IF(AR19>=AR20,0,1) -> 0 | BD20: 19222 | BE20: =(305/1185)*ELEC!Q18 -> 0 | BG20: =#REF!-BE20 -> #REF!
A21: =ELEC!C18 -> 44302 | B21: ='B5'!B20 -> 240 | C21: =B21*$B$4 -> 5163.871 | D21: =SUM(B21) -> 240 | E21: =D21*$B$4 -> 5163.871 | F21: =SUM(D21) -> 240 | G21: =F21*$B$4 -> 5163.871 | H21: =SUM(F21) -> 240 | I21: =H21*$B$4 -> 5163.871 | J21: =SUM(H21) -> 240 | K21: =J21*$B$4 -> 5163.871 | L21: =SUM(J21) -> 240 | M21: =L21*$B$4 -> 5163.871 | N21: =SUM(L21) -> 240 | O21: =N21*$B$4 -> 5163.871 | P21: =SUM(N21) -> 240 | Q21: =P21*$B$4 -> 5163.871 | R21: =SUM(P21) -> 240 | S21: =R21*$B$4 -> 5163.871 | T21: =SUM(R21) -> 240 | U21: =T21*$B$4 -> 5163.871 | V21: =SUM(T21) -> 240 | W21: =V21*$B$4 -> 5163.871 | X21: =SUM(Y21/73370) -> 0.77419355 | Y21: =SUM(C21+E21+G21+I21+K21+M21+O21+Q21+S21+U21+W21) -> 56802.581 | Z21: ='B5'!C20 -> 247 | AA21: =SUM(Z21*$Z$4) -> 2470 | AB21: =SUM(Z21) -> 247 | AC21: =SUM(AB21*$Z$4) -> 2470 | AD21: =SUM(AB21) -> 247 | AE21: =SUM(AD21*$Z$4) -> 2470 | AF21: =SUM(AD21) -> 247 | AG21: =SUM(AF21*$Z$4) -> 2470 | AH21: =SUM(AF21) -> 247 | AI21: =SUM(AH21*$Z$4) -> 2470 | AJ21: =SUM(AH21) -> 247 | AK21: =SUM(AJ21*$Z$4) -> 2470 | AL21: =SUM(AJ21) -> 247 | AM21: =SUM(AL21*$Z$4) -> 2470 | AN21: =SUM(AO21/19600) -> 0.88214286 | AO21: =SUM(AA21+AC21+AE21+AG21+AI21+AK21+AM21) -> 17290 | AQ21: =SUM(AR21/92970) -> 0.7969515 | AR21: =Y21+AO21 -> 74092.581 | AS21: =SUM(AR21-AR20-AT21) -> 0 | AV21: =IF(AT21>0,AU21,AV20) -> 0.93 | AW21: =-SUM('B5'!AI20) -> 0 | AX21: =-SUM(AW21-AS21) -> 0 | AY21: =SUM(AX21+AW21) -> 0 | AZ21: =ELEC!A18 -> 0 | BA21: ='General information '!D21 -> 0 | BB21: =SUM('General information '!E21) -> 0 | BC21: =IF(AR20>=AR21,0,1) -> 0 | BD21: 19222 | BE21: =(305/1185)*ELEC!Q19 -> 0 | BG21: =#REF!-BE21 -> #REF!
A22: =ELEC!C19 -> 44303 | B22: ='B5'!B21 -> 240 | C22: =B22*$B$4 -> 5163.871 | D22: =SUM(B22) -> 240 | E22: =D22*$B$4 -> 5163.871 | F22: =SUM(D22) -> 240 | G22: =F22*$B$4 -> 5163.871 | H22: =SUM(F22) -> 240 | I22: =H22*$B$4 -> 5163.871 | J22: =SUM(H22) -> 240 | K22: =J22*$B$4 -> 5163.871 | L22: =SUM(J22) -> 240 | M22: =L22*$B$4 -> 5163.871 | N22: =SUM(L22) -> 240 | O22: =N22*$B$4 -> 5163.871 | P22: =SUM(N22) -> 240 | Q22: =P22*$B$4 -> 5163.871 | R22: =SUM(P22) -> 240 | S22: =R22*$B$4 -> 5163.871 | T22: =SUM(R22) -> 240 | U22: =T22*$B$4 -> 5163.871 | V22: =SUM(T22) -> 240 | W22: =V22*$B$4 -> 5163.871 | X22: =SUM(Y22/73370) -> 0.77419355 | Y22: =SUM(C22+E22+G22+I22+K22+M22+O22+Q22+S22+U22+W22) -> 56802.581 | Z22: ='B5'!C21 -> 247 | AA22: =SUM(Z22*$Z$4) -> 2470 | AB22: =SUM(Z22) -> 247 | AC22: =SUM(AB22*$Z$4) -> 2470 | AD22: =SUM(AB22) -> 247 | AE22: =SUM(AD22*$Z$4) -> 2470 | AF22: =SUM(AD22) -> 247 | AG22: =SUM(AF22*$Z$4) -> 2470 | AH22: =SUM(AF22) -> 247 | AI22: =SUM(AH22*$Z$4) -> 2470 | AJ22: =SUM(AH22) -> 247 | AK22: =SUM(AJ22*$Z$4) -> 2470 | AL22: =SUM(AJ22) -> 247 | AM22: =SUM(AL22*$Z$4) -> 2470 | AN22: =SUM(AO22/19600) -> 0.88214286 | AO22: =SUM(AA22+AC22+AE22+AG22+AI22+AK22+AM22) -> 17290 | AQ22: =SUM(AR22/92970) -> 0.7969515 | AR22: =Y22+AO22 -> 74092.581 | AS22: =SUM(AR22-AR21-AT22) -> 0 | AV22: =IF(AT22>0,AU22,AV21) -> 0.93 | AW22: =-SUM('B5'!AI21) -> 0 | AX22: =-SUM(AW22-AS22) -> 0 | AY22: =SUM(AX22+AW22) -> 0 | AZ22: =ELEC!A19 -> 0 | BA22: ='General information '!D22 -> 0 | BB22: =SUM('General information '!E22) -> 0 | BC22: =IF(AR21>=AR22,0,1) -> 0 | BD22: 19222 | BE22: =(305/1185)*ELEC!Q20 -> 0 | BG22: =#REF!-BE22 -> #REF!
A23: =ELEC!C20 -> 44304 | B23: ='B5'!B22 -> 240 | C23: =B23*$B$4 -> 5163.871 | D23: =SUM(B23) -> 240 | E23: =D23*$B$4 -> 5163.871 | F23: =SUM(D23) -> 240 | G23: =F23*$B$4 -> 5163.871 | H23: =SUM(F23) -> 240 | I23: =H23*$B$4 -> 5163.871 | J23: =SUM(H23) -> 240 | K23: =J23*$B$4 -> 5163.871 | L23: =SUM(J23) -> 240 | M23: =L23*$B$4 -> 5163.871 | N23: =SUM(L23) -> 240 | O23: =N23*$B$4 -> 5163.871 | P23: =SUM(N23) -> 240 | Q23: =P23*$B$4 -> 5163.871 | R23: =SUM(P23) -> 240 | S23: =R23*$B$4 -> 5163.871 | T23: =SUM(R23) -> 240 | U23: =T23*$B$4 -> 5163.871 | V23: =SUM(T23) -> 240 | W23: =V23*$B$4 -> 5163.871 | X23: =SUM(Y23/73370) -> 0.77419355 | Y23: =SUM(C23+E23+G23+I23+K23+M23+O23+Q23+S23+U23+W23) -> 56802.581 | Z23: ='B5'!C22 -> 247 | AA23: =SUM(Z23*$Z$4) -> 2470 | AB23: =SUM(Z23) -> 247 | AC23: =SUM(AB23*$Z$4) -> 2470 | AD23: =SUM(AB23) -> 247 | AE23: =SUM(AD23*$Z$4) -> 2470 | AF23: =SUM(AD23) -> 247 | AG23: =SUM(AF23*$Z$4) -> 2470 | AH23: =SUM(AF23) -> 247 | AI23: =SUM(AH23*$Z$4) -> 2470 | AJ23: =SUM(AH23) -> 247 | AK23: =SUM(AJ23*$Z$4) -> 2470 | AL23: =SUM(AJ23) -> 247 | AM23: =SUM(AL23*$Z$4) -> 2470 | AN23: =SUM(AO23/19600) -> 0.88214286 | AO23: =SUM(AA23+AC23+AE23+AG23+AI23+AK23+AM23) -> 17290 | AQ23: =SUM(AR23/92970) -> 0.7969515 | AR23: =Y23+AO23 -> 74092.581 | AS23: =SUM(AR23-AR22-AT23) -> 0 | AV23: =IF(AT23>0,AU23,AV22) -> 0.93 | AW23: =-SUM('B5'!AI22) -> 0 | AX23: =-SUM(AW23-AS23) -> 0 | AY23: =SUM(AX23+AW23) -> 0 | AZ23: =ELEC!A20 -> 0 | BA23: ='General information '!D23 -> 0 | BB23: =SUM('General information '!E23) -> 0 | BC23: =IF(AR22>=AR23,0,1) -> 0 | BD23: 19222 | BE23: =(305/1185)*ELEC!Q21 -> 0 | BG23: =#REF!-BE23 -> #REF!
A24: =ELEC!C21 -> 44305 | B24: ='B5'!B23 -> 240 | C24: =B24*$B$4 -> 5163.871 | D24: =SUM(B24) -> 240 | E24: =D24*$B$4 -> 5163.871 | F24: =SUM(D24) -> 240 | G24: =F24*$B$4 -> 5163.871 | H24: =SUM(F24) -> 240 | I24: =H24*$B$4 -> 5163.871 | J24: =SUM(H24) -> 240 | K24: =J24*$B$4 -> 5163.871 | L24: =SUM(J24) -> 240 | M24: =L24*$B$4 -> 5163.871 | N24: =SUM(L24) -> 240 | O24: =N24*$B$4 -> 5163.871 | P24: =SUM(N24) -> 240 | Q24: =P24*$B$4 -> 5163.871 | R24: =SUM(P24) -> 240 | S24: =R24*$B$4 -> 5163.871 | T24: =SUM(R24) -> 240 | U24: =T24*$B$4 -> 5163.871 | V24: =SUM(T24) -> 240 | W24: =V24*$B$4 -> 5163.871 | X24: =SUM(Y24/73370) -> 0.77419355 | Y24: =SUM(C24+E24+G24+I24+K24+M24+O24+Q24+S24+U24+W24) -> 56802.581 | Z24: ='B5'!C23 -> 247 | AA24: =SUM(Z24*$Z$4) -> 2470 | AB24: =SUM(Z24) -> 247 | AC24: =SUM(AB24*$Z$4) -> 2470 | AD24: =SUM(AB24) -> 247 | AE24: =SUM(AD24*$Z$4) -> 2470 | AF24: =SUM(AD24) -> 247 | AG24: =SUM(AF24*$Z$4) -> 2470 | AH24: =SUM(AF24) -> 247 | AI24: =SUM(AH24*$Z$4) -> 2470 | AJ24: =SUM(AH24) -> 247 | AK24: =SUM(AJ24*$Z$4) -> 2470 | AL24: =SUM(AJ24) -> 247 | AM24: =SUM(AL24*$Z$4) -> 2470 | AN24: =SUM(AO24/19600) -> 0.88214286 | AO24: =SUM(AA24+AC24+AE24+AG24+AI24+AK24+AM24) -> 17290 | AQ24: =SUM(AR24/92970) -> 0.7969515 | AR24: =Y24+AO24 -> 74092.581 | AS24: =SUM(AR24-AR23-AT24) -> 0 | AV24: =IF(AT24>0,AU24,AV23) -> 0.93 | AW24: =-SUM('B5'!AI23) -> 0 | AX24: =-SUM(AW24-AS24) -> 0 | AY24: =SUM(AX24+AW24) -> 0 | AZ24: =ELEC!A21 -> 0 | BA24: ='General information '!D24 -> 0 | BB24: =SUM('General information '!E24) -> 0 | BC24: =IF(AR23>=AR24,0,1) -> 0 | BD24: 19222 | BE24: =(305/1185)*ELEC!Q22 -> 0 | BG24: =#REF!-BE24 -> #REF!
A25: =ELEC!C22 -> 44306 | B25: ='B5'!B24 -> 240 | C25: =B25*$B$4 -> 5163.871 | D25: =SUM(B25) -> 240 | E25: =D25*$B$4 -> 5163.871 | F25: =SUM(D25) -> 240 | G25: =F25*$B$4 -> 5163.871 | H25: =SUM(F25) -> 240 | I25: =H25*$B$4 -> 5163.871 | J25: =SUM(H25) -> 240 | K25: =J25*$B$4 -> 5163.871 | L25: =SUM(J25) -> 240 | M25: =L25*$B$4 -> 5163.871 | N25: =SUM(L25) -> 240 | O25: =N25*$B$4 -> 5163.871 | P25: =SUM(N25) -> 240 | Q25: =P25*$B$4 -> 5163.871 | R25: =SUM(P25) -> 240 | S25: =R25*$B$4 -> 5163.871 | T25: =SUM(R25) -> 240 | U25: =T25*$B$4 -> 5163.871 | V25: =SUM(T25) -> 240 | W25: =V25*$B$4 -> 5163.871 | X25: =SUM(Y25/73370) -> 0.77419355 | Y25: =SUM(C25+E25+G25+I25+K25+M25+O25+Q25+S25+U25+W25) -> 56802.581 | Z25: ='B5'!C24 -> 247 | AA25: =SUM(Z25*$Z$4) -> 2470 | AB25: =SUM(Z25) -> 247 | AC25: =SUM(AB25*$Z$4) -> 2470 | AD25: =SUM(AB25) -> 247 | AE25: =SUM(AD25*$Z$4) -> 2470 | AF25: =SUM(AD25) -> 247 | AG25: =SUM(AF25*$Z$4) -> 2470 | AH25: =SUM(AF25) -> 247 | AI25: =SUM(AH25*$Z$4) -> 2470 | AJ25: =SUM(AH25) -> 247 | AK25: =SUM(AJ25*$Z$4) -> 2470 | AL25: =SUM(AJ25) -> 247 | AM25: =SUM(AL25*$Z$4) -> 2470 | AN25: =SUM(AO25/19600) -> 0.88214286 | AO25: =SUM(AA25+AC25+AE25+AG25+AI25+AK25+AM25) -> 17290 | AQ25: =SUM(AR25/92970) -> 0.7969515 | AR25: =Y25+AO25 -> 74092.581 | AS25: =SUM(AR25-AR24-AT25) -> 0 | AV25: =IF(AT25>0,AU25,AV24) -> 0.93 | AW25: =-SUM('B5'!AI24) -> 0 | AX25: =-SUM(AW25-AS25) -> 0 | AY25: =SUM(AX25+AW25) -> 0 | AZ25: =ELEC!A22 -> 0 | BA25: ='General information '!D25 -> 0 | BB25: =SUM('General information '!E25) -> 0 | BC25: =IF(AR24>=AR25,0,1) -> 0 | BD25: 19222 | BE25: =(305/1185)*ELEC!Q23 -> 0 | BG25: =#REF!-BE25 -> #REF!
A26: =ELEC!C23 -> 44307 | B26: ='B5'!B25 -> 240 | C26: =B26*$B$4 -> 5163.871 | D26: =SUM(B26) -> 240 | E26: =D26*$B$4 -> 5163.871 | F26: =SUM(D26) -> 240 | G26: =F26*$B$4 -> 5163.871 | H26: =SUM(F26) -> 240 | I26: =H26*$B$4 -> 5163.871 | J26: =SUM(H26) -> 240 | K26: =J26*$B$4 -> 5163.871 | L26: =SUM(J26) -> 240 | M26: =L26*$B$4 -> 5163.871 | N26: =SUM(L26) -> 240 | O26: =N26*$B$4 -> 5163.871 | P26: =SUM(N26) -> 240 | Q26: =P26*$B$4 -> 5163.871 | R26: =SUM(P26) -> 240 | S26: =R26*$B$4 -> 5163.871 | T26: =SUM(R26) -> 240 | U26: =T26*$B$4 -> 5163.871 | V26: =SUM(T26) -> 240 | W26: =V26*$B$4 -> 5163.871 | X26: =SUM(Y26/73370) -> 0.77419355 | Y26: =SUM(C26+E26+G26+I26+K26+M26+O26+Q26+S26+U26+W26) -> 56802.581 | Z26: ='B5'!C25 -> 247 | AA26: =SUM(Z26*$Z$4) -> 2470 | AB26: =SUM(Z26) -> 247 | AC26: =SUM(AB26*$Z$4) -> 2470 | AD26: =SUM(AB26) -> 247 | AE26: =SUM(AD26*$Z$4) -> 2470 | AF26: =SUM(AD26) -> 247 | AG26: =SUM(AF26*$Z$4) -> 2470 | AH26: =SUM(AF26) -> 247 | AI26: =SUM(AH26*$Z$4) -> 2470 | AJ26: =SUM(AH26) -> 247 | AK26: =SUM(AJ26*$Z$4) -> 2470 | AL26: =SUM(AJ26) -> 247 | AM26: =SUM(AL26*$Z$4) -> 2470 | AN26: =SUM(AO26/19600) -> 0.88214286 | AO26: =SUM(AA26+AC26+AE26+AG26+AI26+AK26+AM26) -> 17290 | AQ26: =SUM(AR26/92970) -> 0.7969515 | AR26: =Y26+AO26 -> 74092.581 | AS26: =SUM(AR26-AR25-AT26) -> 0 | AV26: =IF(AT26>0,AU26,AV25) -> 0.93 | AW26: =-SUM('B5'!AI25) -> 0 | AX26: =-SUM(AW26-AS26) -> 0 | AY26: =SUM(AX26+AW26) -> 0 | AZ26: =ELEC!A23 -> 0 | BA26: ='General information '!D26 -> 0 | BB26: =SUM('General information '!E26) -> 0 | BC26: =IF(AR25>=AR26,0,1) -> 0 | BD26: 19222 | BE26: =(305/1185)*ELEC!Q24 -> 0 | BG26: =#REF!-BE26 -> #REF!
A27: =ELEC!C24 -> 44308 | B27: ='B5'!B26 -> 240 | C27: =B27*$B$4 -> 5163.871 | D27: =SUM(B27) -> 240 | E27: =D27*$B$4 -> 5163.871 | F27: =SUM(D27) -> 240 | G27: =F27*$B$4 -> 5163.871 | H27: =SUM(F27) -> 240 | I27: =H27*$B$4 -> 5163.871 | J27: =SUM(H27) -> 240 | K27: =J27*$B$4 -> 5163.871 | L27: =SUM(J27) -> 240 | M27: =L27*$B$4 -> 5163.871 | N27: =SUM(L27) -> 240 | O27: =N27*$B$4 -> 5163.871 | P27: =SUM(N27) -> 240 | Q27: =P27*$B$4 -> 5163.871 | R27: =SUM(P27) -> 240 | S27: =R27*$B$4 -> 5163.871 | T27: =SUM(R27) -> 240 | U27: =T27*$B$4 -> 5163.871 | V27: =SUM(T27) -> 240 | W27: =V27*$B$4 -> 5163.871 | X27: =SUM(Y27/73370) -> 0.77419355 | Y27: =SUM(C27+E27+G27+I27+K27+M27+O27+Q27+S27+U27+W27) -> 56802.581 | Z27: ='B5'!C26 -> 247 | AA27: =SUM(Z27*$Z$4) -> 2470 | AB27: =SUM(Z27) -> 247 | AC27: =SUM(AB27*$Z$4) -> 2470 | AD27: =SUM(AB27) -> 247 | AE27: =SUM(AD27*$Z$4) -> 2470 | AF27: =SUM(AD27) -> 247 | AG27: =SUM(AF27*$Z$4) -> 2470 | AH27: =SUM(AF27) -> 247 | AI27: =SUM(AH27*$Z$4) -> 2470 | AJ27: =SUM(AH27) -> 247 | AK27: =SUM(AJ27*$Z$4) -> 2470 | AL27: =SUM(AJ27) -> 247 | AM27: =SUM(AL27*$Z$4) -> 2470 | AN27: =SUM(AO27/19600) -> 0.88214286 | AO27: =SUM(AA27+AC27+AE27+AG27+AI27+AK27+AM27) -> 17290 | AQ27: =SUM(AR27/92970) -> 0.7969515 | AR27: =Y27+AO27 -> 74092.581 | AS27: =SUM(AR27-AR26-AT27) -> 0 | AV27: =IF(AT27>0,AU27,AV26) -> 0.93 | AW27: =-SUM('B5'!AI26) -> 0 | AX27: =-SUM(AW27-AS27) -> 0 | AY27: =SUM(AX27+AW27) -> 0 | AZ27: =ELEC!A24 -> 0 | BA27: ='General information '!D27 -> 0 | BB27: =SUM('General information '!E27) -> 0 | BC27: =IF(AR26>=AR27,0,1) -> 0 | BD27: 19222 | BE27: =(305/1185)*ELEC!Q25 -> 0 | BG27: =#REF!-BE27 -> #REF!
A28: =ELEC!C25 -> 44309 | B28: ='B5'!B27 -> 240 | C28: =B28*$B$4 -> 5163.871 | D28: =SUM(B28) -> 240 | E28: =D28*$B$4 -> 5163.871 | F28: =SUM(D28) -> 240 | G28: =F28*$B$4 -> 5163.871 | H28: =SUM(F28) -> 240 | I28: =H28*$B$4 -> 5163.871 | J28: =SUM(H28) -> 240 | K28: =J28*$B$4 -> 5163.871 | L28: =SUM(J28) -> 240 | M28: =L28*$B$4 -> 5163.871 | N28: =SUM(L28) -> 240 | O28: =N28*$B$4 -> 5163.871 | P28: =SUM(N28) -> 240 | Q28: =P28*$B$4 -> 5163.871 | R28: =SUM(P28) -> 240 | S28: =R28*$B$4 -> 5163.871 | T28: =SUM(R28) -> 240 | U28: =T28*$B$4 -> 5163.871 | V28: =SUM(T28) -> 240 | W28: =V28*$B$4 -> 5163.871 | X28: =SUM(Y28/73370) -> 0.77419355 | Y28: =SUM(C28+E28+G28+I28+K28+M28+O28+Q28+S28+U28+W28) -> 56802.581 | Z28: ='B5'!C27 -> 247 | AA28: =SUM(Z28*$Z$4) -> 2470 | AB28: =SUM(Z28) -> 247 | AC28: =SUM(AB28*$Z$4) -> 2470 | AD28: =SUM(AB28) -> 247 | AE28: =SUM(AD28*$Z$4) -> 2470 | AF28: =SUM(AD28) -> 247 | AG28: =SUM(AF28*$Z$4) -> 2470 | AH28: =SUM(AF28) -> 247 | AI28: =SUM(AH28*$Z$4) -> 2470 | AJ28: =SUM(AH28) -> 247 | AK28: =SUM(AJ28*$Z$4) -> 2470 | AL28: =SUM(AJ28) -> 247 | AM28: =SUM(AL28*$Z$4) -> 2470 | AN28: =SUM(AO28/19600) -> 0.88214286 | AO28: =SUM(AA28+AC28+AE28+AG28+AI28+AK28+AM28) -> 17290 | AQ28: =SUM(AR28/92970) -> 0.7969515 | AR28: =Y28+AO28 -> 74092.581 | AS28: =SUM(AR28-AR27-AT28) -> 0 | AV28: =IF(AT28>0,AU28,AV27) -> 0.93 | AW28: =-SUM('B5'!AI27) -> 0 | AX28: =-SUM(AW28-AS28) -> 0 | AY28: =SUM(AX28+AW28) -> 0 | AZ28: =ELEC!A25 -> 0 | BA28: ='General information '!D28 -> 0 | BB28: =SUM('General information '!E28) -> 0 | BC28: =IF(AR27>=AR28,0,1) -> 0 | BD28: 19222 | BE28: =(305/1185)*ELEC!Q26 -> 0 | BG28: =#REF!-BE28 -> #REF!
A29: =ELEC!C26 -> 44310 | B29: ='B5'!B28 -> 240 | C29: =B29*$B$4 -> 5163.871 | D29: =SUM(B29) -> 240 | E29: =D29*$B$4 -> 5163.871 | F29: =SUM(D29) -> 240 | G29: =F29*$B$4 -> 5163.871 | H29: =SUM(F29) -> 240 | I29: =H29*$B$4 -> 5163.871 | J29: =SUM(H29) -> 240 | K29: =J29*$B$4 -> 5163.871 | L29: =SUM(J29) -> 240 | M29: =L29*$B$4 -> 5163.871 | N29: =SUM(L29) -> 240 | O29: =N29*$B$4 -> 5163.871 | P29: =SUM(N29) -> 240 | Q29: =P29*$B$4 -> 5163.871 | R29: =SUM(P29) -> 240 | S29: =R29*$B$4 -> 5163.871 | T29: =SUM(R29) -> 240 | U29: =T29*$B$4 -> 5163.871 | V29: =SUM(T29) -> 240 | W29: =V29*$B$4 -> 5163.871 | X29: =SUM(Y29/73370) -> 0.77419355 | Y29: =SUM(C29+E29+G29+I29+K29+M29+O29+Q29+S29+U29+W29) -> 56802.581 | Z29: ='B5'!C28 -> 247 | AA29: =SUM(Z29*$Z$4) -> 2470 | AB29: =SUM(Z29) -> 247 | AC29: =SUM(AB29*$Z$4) -> 2470 | AD29: =SUM(AB29) -> 247 | AE29: =SUM(AD29*$Z$4) -> 2470 | AF29: =SUM(AD29) -> 247 | AG29: =SUM(AF29*$Z$4) -> 2470 | AH29: =SUM(AF29) -> 247 | AI29: =SUM(AH29*$Z$4) -> 2470 | AJ29: =SUM(AH29) -> 247 | AK29: =SUM(AJ29*$Z$4) -> 2470 | AL29: =SUM(AJ29) -> 247 | AM29: =SUM(AL29*$Z$4) -> 2470 | AN29: =SUM(AO29/19600) -> 0.88214286 | AO29: =SUM(AA29+AC29+AE29+AG29+AI29+AK29+AM29) -> 17290 | AQ29: =SUM(AR29/92970) -> 0.7969515 | AR29: =Y29+AO29 -> 74092.581 | AS29: =SUM(AR29-AR28-AT29) -> 0 | AV29: =IF(AT29>0,AU29,AV28) -> 0.93 | AW29: =-SUM('B5'!AI28) -> 0 | AX29: =-SUM(AW29-AS29) -> 0 | AY29: =SUM(AX29+AW29) -> 0 | AZ29: =ELEC!A26 -> 0 | BA29: ='General information '!D29 -> 0 | BB29: =SUM('General information '!E29) -> 0 | BC29: =IF(AR28>=AR29,0,1) -> 0 | BD29: 19222 | BE29: =(305/1185)*ELEC!Q27 -> 0 | BG29: =#REF!-BE29 -> #REF!
A30: =ELEC!C27 -> 44311 | B30: ='B5'!B29 -> 240 | C30: =B30*$B$4 -> 5163.871 | D30: =SUM(B30) -> 240 | E30: =D30*$B$4 -> 5163.871 | F30: =SUM(D30) -> 240 | G30: =F30*$B$4 -> 5163.871 | H30: =SUM(F30) -> 240 | I30: =H30*$B$4 -> 5163.871 | J30: =SUM(H30) -> 240 | K30: =J30*$B$4 -> 5163.871 | L30: =SUM(J30) -> 240 | M30: =L30*$B$4 -> 5163.871 | N30: =SUM(L30) -> 240 | O30: =N30*$B$4 -> 5163.871 | P30: =SUM(N30) -> 240 | Q30: =P30*$B$4 -> 5163.871 | R30: =SUM(P30) -> 240 | S30: =R30*$B$4 -> 5163.871 | T30: =SUM(R30) -> 240 | U30: =T30*$B$4 -> 5163.871 | V30: =SUM(T30) -> 240 | W30: =V30*$B$4 -> 5163.871 | X30: =SUM(Y30/73370) -> 0.77419355 | Y30: =SUM(C30+E30+G30+I30+K30+M30+O30+Q30+S30+U30+W30) -> 56802.581 | Z30: ='B5'!C29 -> 247 | AA30: =SUM(Z30*$Z$4) -> 2470 | AB30: =SUM(Z30) -> 247 | AC30: =SUM(AB30*$Z$4) -> 2470 | AD30: =SUM(AB30) -> 247 | AE30: =SUM(AD30*$Z$4) -> 2470 | AF30: =SUM(AD30) -> 247 | AG30: =SUM(AF30*$Z$4) -> 2470 | AH30: =SUM(AF30) -> 247 | AI30: =SUM(AH30*$Z$4) -> 2470 | AJ30: =SUM(AH30) -> 247 | AK30: =SUM(AJ30*$Z$4) -> 2470 | AL30: =SUM(AJ30) -> 247 | AM30: =SUM(AL30*$Z$4) -> 2470 | AN30: =SUM(AO30/19600) -> 0.88214286 | AO30: =SUM(AA30+AC30+AE30+AG30+AI30+AK30+AM30) -> 17290 | AQ30: =SUM(AR30/92970) -> 0.7969515 | AR30: =Y30+AO30 -> 74092.581 | AS30: =SUM(AR30-AR29-AT30) -> 0 | AV30: =IF(AT30>0,AU30,AV29) -> 0.93 | AW30: =-SUM('B5'!AI29) -> 0 | AX30: =-SUM(AW30-AS30) -> 0 | AY30: =SUM(AX30+AW30) -> 0 | AZ30: =ELEC!A27 -> 0 | BA30: ='General information '!D30 -> 0 | BB30: =SUM('General information '!E30) -> 0 | BC30: =IF(AR29>=AR30,0,1) -> 0 | BD30: 19222 | BE30: =(305/1185)*ELEC!Q28 -> 0 | BG30: =#REF!-BE30 -> #REF!
A31: =ELEC!C28 -> 44312 | B31: ='B5'!B30 -> 240 | C31: =B31*$B$4 -> 5163.871 | D31: =SUM(B31) -> 240 | E31: =D31*$B$4 -> 5163.871 | F31: =SUM(D31) -> 240 | G31: =F31*$B$4 -> 5163.871 | H31: =SUM(F31) -> 240 | I31: =H31*$B$4 -> 5163.871 | J31: =SUM(H31) -> 240 | K31: =J31*$B$4 -> 5163.871 | L31: =SUM(J31) -> 240 | M31: =L31*$B$4 -> 5163.871 | N31: =SUM(L31) -> 240 | O31: =N31*$B$4 -> 5163.871 | P31: =SUM(N31) -> 240 | Q31: =P31*$B$4 -> 5163.871 | R31: =SUM(P31) -> 240 | S31: =R31*$B$4 -> 5163.871 | T31: =SUM(R31) -> 240 | U31: =T31*$B$4 -> 5163.871 | V31: =SUM(T31) -> 240 | W31: =V31*$B$4 -> 5163.871 | X31: =SUM(Y31/73370) -> 0.77419355 | Y31: =SUM(C31+E31+G31+I31+K31+M31+O31+Q31+S31+U31+W31) -> 56802.581 | Z31: ='B5'!C30 -> 247 | AA31: =SUM(Z31*$Z$4) -> 2470 | AB31: =SUM(Z31) -> 247 | AC31: =SUM(AB31*$Z$4) -> 2470 | AD31: =SUM(AB31) -> 247 | AE31: =SUM(AD31*$Z$4) -> 2470 | AF31: =SUM(AD31) -> 247 | AG31: =SUM(AF31*$Z$4) -> 2470 | AH31: =SUM(AF31) -> 247 | AI31: =SUM(AH31*$Z$4) -> 2470 | AJ31: =SUM(AH31) -> 247 | AK31: =SUM(AJ31*$Z$4) -> 2470 | AL31: =SUM(AJ31) -> 247 | AM31: =SUM(AL31*$Z$4) -> 2470 | AN31: =SUM(AO31/19600) -> 0.88214286 | AO31: =SUM(AA31+AC31+AE31+AG31+AI31+AK31+AM31) -> 17290 | AQ31: =SUM(AR31/92970) -> 0.7969515 | AR31: =Y31+AO31 -> 74092.581 | AS31: =SUM(AR31-AR30-AT31) -> 0 | AV31: =IF(AT31>0,AU31,AV30) -> 0.93 | AW31: =-SUM('B5'!AI30) -> 0 | AX31: =-SUM(AW31-AS31) -> 0 | AY31: =SUM(AX31+AW31) -> 0 | AZ31: =ELEC!A28 -> 0 | BA31: ='General information '!D31 -> 0 | BB31: =SUM('General information '!E31) -> 0 | BC31: =IF(AR30>=AR31,0,1) -> 0 | BD31: 19222 | BE31: =(305/1185)*ELEC!Q29 -> 0 | BG31: =#REF!-BE31 -> #REF!
A32: =ELEC!C29 -> 44313 | B32: ='B5'!B31 -> 240 | C32: =B32*$B$4 -> 5163.871 | D32: =SUM(B32) -> 240 | E32: =D32*$B$4 -> 5163.871 | F32: =SUM(D32) -> 240 | G32: =F32*$B$4 -> 5163.871 | H32: =SUM(F32) -> 240 | I32: =H32*$B$4 -> 5163.871 | J32: =SUM(H32) -> 240 | K32: =J32*$B$4 -> 5163.871 | L32: =SUM(J32) -> 240 | M32: =L32*$B$4 -> 5163.871 | N32: =SUM(L32) -> 240 | O32: =N32*$B$4 -> 5163.871 | P32: =SUM(N32) -> 240 | Q32: =P32*$B$4 -> 5163.871 | R32: =SUM(P32) -> 240 | S32: =R32*$B$4 -> 5163.871 | T32: =SUM(R32) -> 240 | U32: =T32*$B$4 -> 5163.871 | V32: =SUM(T32) -> 240 | W32: =V32*$B$4 -> 5163.871 | X32: =SUM(Y32/73370) -> 0.77419355 | Y32: =SUM(C32+E32+G32+I32+K32+M32+O32+Q32+S32+U32+W32) -> 56802.581 | Z32: ='B5'!C31 -> 247 | AA32: =SUM(Z32*$Z$4) -> 2470 | AB32: =SUM(Z32) -> 247 | AC32: =SUM(AB32*$Z$4) -> 2470 | AD32: =SUM(AB32) -> 247 | AE32: =SUM(AD32*$Z$4) -> 2470 | AF32: =SUM(AD32) -> 247 | AG32: =SUM(AF32*$Z$4) -> 2470 | AH32: =SUM(AF32) -> 247 | AI32: =SUM(AH32*$Z$4) -> 2470 | AJ32: =SUM(AH32) -> 247 | AK32: =SUM(AJ32*$Z$4) -> 2470 | AL32: =SUM(AJ32) -> 247 | AM32: =SUM(AL32*$Z$4) -> 2470 | AN32: =SUM(AO32/19600) -> 0.88214286 | AO32: =SUM(AA32+AC32+AE32+AG32+AI32+AK32+AM32) -> 17290 | AQ32: =SUM(AR32/92970) -> 0.7969515 | AR32: =Y32+AO32 -> 74092.581 | AS32: =SUM(AR32-AR31-AT32) -> 0 | AV32: =IF(AT32>0,AU32,AV31) -> 0.93 | AW32: =-SUM('B5'!AI31) -> 0 | AX32: =-SUM(AW32-AS32) -> 0 | AY32: =SUM(AX32+AW32) -> 0 | AZ32: =ELEC!A29 -> 0 | BA32: ='General information '!D32 -> 0 | BB32: =SUM('General information '!E32) -> 0 | BC32: =IF(AR31>=AR32,0,1) -> 0 | BD32: 19222 | BE32: =(305/1185)*ELEC!Q30 -> 0 | BG32: =#REF!-BE32 -> #REF!
A33: =ELEC!C30 -> 44314 | B33: ='B5'!B32 -> 240 | C33: =B33*$B$4 -> 5163.871 | D33: =SUM(B33) -> 240 | E33: =D33*$B$4 -> 5163.871 | F33: =SUM(D33) -> 240 | G33: =F33*$B$4 -> 5163.871 | H33: =SUM(F33) -> 240 | I33: =H33*$B$4 -> 5163.871 | J33: =SUM(H33) -> 240 | K33: =J33*$B$4 -> 5163.871 | L33: =SUM(J33) -> 240 | M33: =L33*$B$4 -> 5163.871 | N33: =SUM(L33) -> 240 | O33: =N33*$B$4 -> 5163.871 | P33: =SUM(N33) -> 240 | Q33: =P33*$B$4 -> 5163.871 | R33: =SUM(P33) -> 240 | S33: =R33*$B$4 -> 5163.871 | T33: =SUM(R33) -> 240 | U33: =T33*$B$4 -> 5163.871 | V33: =SUM(T33) -> 240 | W33: =V33*$B$4 -> 5163.871 | X33: =SUM(Y33/73370) -> 0.77419355 | Y33: =SUM(C33+E33+G33+I33+K33+M33+O33+Q33+S33+U33+W33) -> 56802.581 | Z33: ='B5'!C32 -> 247 | AA33: =SUM(Z33*$Z$4) -> 2470 | AB33: =SUM(Z33) -> 247 | AC33: =SUM(AB33*$Z$4) -> 2470 | AD33: =SUM(AB33) -> 247 | AE33: =SUM(AD33*$Z$4) -> 2470 | AF33: =SUM(AD33) -> 247 | AG33: =SUM(AF33*$Z$4) -> 2470 | AH33: =SUM(AF33) -> 247 | AI33: =SUM(AH33*$Z$4) -> 2470 | AJ33: =SUM(AH33) -> 247 | AK33: =SUM(AJ33*$Z$4) -> 2470 | AL33: =SUM(AJ33) -> 247 | AM33: =SUM(AL33*$Z$4) -> 2470 | AN33: =SUM(AO33/19600) -> 0.88214286 | AO33: =SUM(AA33+AC33+AE33+AG33+AI33+AK33+AM33) -> 17290 | AQ33: =SUM(AR33/92970) -> 0.7969515 | AR33: =Y33+AO33 -> 74092.581 | AS33: =SUM(AR33-AR32-AT33) -> 0 | AV33: =IF(AT33>0,AU33,AV32) -> 0.93 | AW33: =-SUM('B5'!AI32) -> 0 | AX33: =-SUM(AW33-AS33) -> 0 | AY33: =SUM(AX33+AW33) -> 0 | AZ33: =ELEC!A30 -> 0 | BA33: ='General information '!D33 -> 0 | BB33: =SUM('General information '!E33) -> 0 | BC33: =IF(AR32>=AR33,0,1) -> 0 | BD33: 19222 | BE33: =(305/1185)*ELEC!#REF! -> #REF! | BG33: =#REF!-BE33 -> #REF!
A34: =ELEC!C31 -> 44315 | B34: ='B5'!B33 -> 240 | C34: =B34*$B$4 -> 5163.871 | D34: =SUM(B34) -> 240 | E34: =D34*$B$4 -> 5163.871 | F34: =SUM(D34) -> 240 | G34: =F34*$B$4 -> 5163.871 | H34: =SUM(F34) -> 240 | I34: =H34*$B$4 -> 5163.871 | J34: =SUM(H34) -> 240 | K34: =J34*$B$4 -> 5163.871 | L34: =SUM(J34) -> 240 | M34: =L34*$B$4 -> 5163.871 | N34: =SUM(L34) -> 240 | O34: =N34*$B$4 -> 5163.871 | P34: =SUM(N34) -> 240 | Q34: =P34*$B$4 -> 5163.871 | R34: =SUM(P34) -> 240 | S34: =R34*$B$4 -> 5163.871 | T34: =SUM(R34) -> 240 | U34: =T34*$B$4 -> 5163.871 | V34: =SUM(T34) -> 240 | W34: =V34*$B$4 -> 5163.871 | X34: =SUM(Y34/73370) -> 0.77419355 | Y34: =SUM(C34+E34+G34+I34+K34+M34+O34+Q34+S34+U34+W34) -> 56802.581 | Z34: ='B5'!C33 -> 247 | AA34: =SUM(Z34*$Z$4) -> 2470 | AB34: =SUM(Z34) -> 247 | AC34: =SUM(AB34*$Z$4) -> 2470 | AD34: =SUM(AB34) -> 247 | AE34: =SUM(AD34*$Z$4) -> 2470 | AF34: =SUM(AD34) -> 247 | AG34: =SUM(AF34*$Z$4) -> 2470 | AH34: =SUM(AF34) -> 247 | AI34: =SUM(AH34*$Z$4) -> 2470 | AJ34: =SUM(AH34) -> 247 | AK34: =SUM(AJ34*$Z$4) -> 2470 | AL34: =SUM(AJ34) -> 247 | AM34: =SUM(AL34*$Z$4) -> 2470 | AN34: =SUM(AO34/19600) -> 0.88214286 | AO34: =SUM(AA34+AC34+AE34+AG34+AI34+AK34+AM34) -> 17290 | AQ34: =SUM(AR34/92970) -> 0.7969515 | AR34: =Y34+AO34 -> 74092.581 | AS34: =SUM(AR34-AR33-AT34) -> 0 | AV34: =IF(AT34>0,AU34,AV33) -> 0.93 | AW34: =-SUM('B5'!AI33) -> 0 | AX34: =-SUM(AW34-AS34) -> 0 | AY34: =SUM(AX34+AW34) -> 0 | AZ34: =ELEC!A31 -> 0 | BA34: ='General information '!D34 -> 0 | BB34: =SUM('General information '!E34) -> 0
A35: =ELEC!C32 -> 44316 | B35: ='B5'!B34 -> 240 | C35: =B35*$B$4 -> 5163.871 | D35: =SUM(B35) -> 240 | E35: =D35*$B$4 -> 5163.871 | F35: =SUM(D35) -> 240 | G35: =F35*$B$4 -> 5163.871 | H35: =SUM(F35) -> 240 | I35: =H35*$B$4 -> 5163.871 | J35: =SUM(H35) -> 240 | K35: =J35*$B$4 -> 5163.871 | L35: =SUM(J35) -> 240 | M35: =L35*$B$4 -> 5163.871 | N35: =SUM(L35) -> 240 | O35: =N35*$B$4 -> 5163.871 | P35: =SUM(N35) -> 240 | Q35: =P35*$B$4 -> 5163.871 | R35: =SUM(P35) -> 240 | S35: =R35*$B$4 -> 5163.871 | T35: =SUM(R35) -> 240 | U35: =T35*$B$4 -> 5163.871 | V35: =SUM(T35) -> 240 | W35: =V35*$B$4 -> 5163.871 | X35: =SUM(Y35/73370) -> 0.77419355 | Y35: =SUM(C35+E35+G35+I35+K35+M35+O35+Q35+S35+U35+W35) -> 56802.581 | Z35: ='B5'!C34 -> 247 | AA35: =SUM(Z35*$Z$4) -> 2470 | AB35: =SUM(Z35) -> 247 | AC35: =SUM(AB35*$Z$4) -> 2470 | AD35: =SUM(AB35) -> 247 | AE35: =SUM(AD35*$Z$4) -> 2470 | AF35: =SUM(AD35) -> 247 | AG35: =SUM(AF35*$Z$4) -> 2470 | AH35: =SUM(AF35) -> 247 | AI35: =SUM(AH35*$Z$4) -> 2470 | AJ35: =SUM(AH35) -> 247 | AK35: =SUM(AJ35*$Z$4) -> 2470 | AL35: =SUM(AJ35) -> 247 | AM35: =SUM(AL35*$Z$4) -> 2470 | AN35: =SUM(AO35/19600) -> 0.88214286 | AO35: =SUM(AA35+AC35+AE35+AG35+AI35+AK35+AM35) -> 17290 | AQ35: =SUM(AR35/92970) -> 0.7969515 | AR35: =Y35+AO35 -> 74092.581 | AS35: =SUM(AR35-AR34-AT35) -> 0 | AV35: =IF(AT35>0,AU35,AV34) -> 0.93 | AW35: =-SUM('B5'!AI34) -> 0 | AX35: =-SUM(AW35-AS35) -> 0 | AY35: =SUM(AX35+AW35) -> 0 | AZ35: =ELEC!A32 -> 0 | BA35: ='General information '!D35 -> 0 | BB35: =SUM('General information '!E35) -> 0
AR36: NB delivery | AS36: =COUNT(AT6:AT33) -> 3 | AT36: =SUM(AT6:AT33) -> 36050 | AU36: =SUM(AU6:AU33)/AS36 -> 0.95 | AX36: =SUM(AX6:AX33) -> -23575.742 | AY36: =SUM(AY6:AY33) -> -28689.742
AT37: =+AT36*AU36 -> 34247.5
AS39: =SUM(AS6:AS33)/'EDl log'!A34 -> -1912.6495
AX40: 43309
AX41: =AX36/AX40 -> -0.54436126

Sheet Sheet1
A1: TOTAL CH RH | B1: TOTAL CH cons KW | C1: TOTAL ELIC KW | D1: TOTAL EDL | E1: TOTAL GEN KW | F1: GEN HR | G1: WATER IN | H1: TOTAL CT | I1: TOTAL WATER | J1: Date
A2: =ELEC!T3+ELEC!X1+ELEC!AB3 -> #VALUE! | B2: =ELEC!AF3 -> 1217 | C2: =ELEC!N3 -> 10627 | D2: =C2-E2 -> 1419 | E2: =ELEC!Q3 -> 9208 | F2: =GEN!Z2 -> 19 | G2: =WATER!C5+WATER!H5 -> 0 | H2: =WATER!L5 -> 0 | I2: =WATER!BC5+WATER!BD5+WATER!BE6-Sheet1!G2 -> -39.6 | J2: ='B5'!A4 -> 44286
A3: =ELEC!T4+ELEC!X2+ELEC!AB4 -> 1 | B3: =ELEC!AF4 -> 546 | C3: =ELEC!N4 -> 8566 | D3: =C3-E3 -> 844 | E3: =ELEC!Q4 -> 7722 | F3: =GEN!Z3 -> 20 | G3: =WATER!C6+WATER!H6 -> 0 | H3: =WATER!L6 -> 0 | I3: =WATER!BC6+WATER!BD6+WATER!BE7-Sheet1!G3 -> -53.9 | J3: ='B5'!A5 -> 44287
A4: =ELEC!T5+ELEC!X5+ELEC!AB5 -> 8 | B4: =ELEC!AF5 -> 1234 | C4: =ELEC!N5 -> 9686 | D4: =C4-E4 -> 1424 | E4: =ELEC!Q5 -> 8262 | F4: =GEN!Z4 -> 14 | G4: =WATER!C7+WATER!H7 -> 0 | H4: =WATER!L7 -> 0 | I4: =WATER!BC7+WATER!BD7+WATER!BE8-Sheet1!G4 -> 47.6 | J4: ='B5'!A6 -> 44288
A5: =ELEC!T6+ELEC!X6+ELEC!AB6 -> 5 | B5: =ELEC!AF6 -> 764 | C5: =ELEC!N6 -> 9198 | D5: =C5-E5 -> 1257 | E5: =ELEC!Q6 -> 7941 | F5: =GEN!Z5 -> 15 | G5: =WATER!C8+WATER!H8 -> 0 | H5: =WATER!L8 -> 1 | I5: =WATER!BC8+WATER!BD8+WATER!BE9-Sheet1!G5 -> -21.4 | J5: ='B5'!A7 -> 44289
A6: =ELEC!T7+ELEC!X7+ELEC!AB7 -> 6 | B6: =ELEC!AF7 -> 1147 | C6: =ELEC!N7 -> 9569 | D6: =C6-E6 -> 9569 | E6: =ELEC!Q24 -> 0 | F6: =GEN!Z6 -> 18 | G6: =WATER!C9+WATER!H9 -> 54 | H6: =WATER!L9 -> 2 | I6: =WATER!BC9+WATER!BD9+WATER!BE10-Sheet1!G6 -> -23 | J6: ='B5'!A8 -> 44290
A7: =ELEC!T8+ELEC!X8+ELEC!AB8 -> 10 | B7: =ELEC!AF8 -> 1976 | C7: =ELEC!N8 -> 10832 | D7: =C7-E7 -> 1968 | E7: =ELEC!Q8 -> 8864 | F7: =GEN!Z7 -> 15 | G7: =WATER!C10+WATER!H10 -> 100 | H7: =WATER!L10 -> 0 | I7: =WATER!BC10+WATER!BD10+WATER!BE11-Sheet1!G7 -> -116.6 | J7: ='B5'!A9 -> 44291
A8: =ELEC!T9+ELEC!X9+ELEC!AB9 -> 6 | B8: =ELEC!AF9 -> 1380 | C8: =ELEC!N9 -> 8792 | D8: =C8-E8 -> 3322 | E8: =ELEC!Q9 -> 5470 | F8: =GEN!Z8 -> 14 | G8: =WATER!C11+WATER!H11 -> 0 | H8: =WATER!L11 -> 2 | I8: =WATER!BC11+WATER!BD11+WATER!BE12-Sheet1!G8 -> -2.7 | J8: ='B5'!A10 -> 44292
A9: =ELEC!T10+ELEC!X10+ELEC!AB10 -> 6 | B9: =ELEC!AF10 -> 1113 | C9: =ELEC!N10 -> 8207 | D9: =C9-E9 -> 3720 | E9: =ELEC!Q10 -> 4487 | F9: =GEN!Z9 -> 8 | G9: =WATER!C12+WATER!H12 -> 28 | H9: =WATER!L12 -> 0 | I9: =WATER!BC12+WATER!BD12+WATER!BE13-Sheet1!G9 -> -78.5 | J9: ='B5'!A11 -> 44293
A10: =ELEC!T11+ELEC!X11+ELEC!AB11 -> 4 | B10: =ELEC!AF11 -> 695 | C10: =ELEC!N11 -> 7584 | D10: =C10-E10 -> 3444 | E10: =ELEC!Q11 -> 4140 | F10: =GEN!Z10 -> 7 | G10: =WATER!C13+WATER!H13 -> 0 | H10: =WATER!L13 -> 0 | I10: =WATER!BC13+WATER!BD13+WATER!BE14-Sheet1!G10 -> 163.4 | J10: ='B5'!A12 -> 44294
A11: =ELEC!T12+ELEC!X12+ELEC!AB12 -> 2 | B11: =ELEC!AF12 -> 396 | C11: =ELEC!N12 -> 6883 | D11: =C11-E11 -> 4048 | E11: =ELEC!Q12 -> 2835 | F11: =GEN!Z11 -> 6 | G11: =WATER!C14+WATER!H14 -> 211 | H11: =WATER!L14 -> 0 | I11: =WATER!BC14+WATER!BD14+WATER!BE15-Sheet1!G11 -> -368.2 | J11: ='B5'!A13 -> 44295
A12: =ELEC!T13+ELEC!X13+ELEC!AB13 -> 3 | B12: =ELEC!AF13 -> 557 | C12: =ELEC!N13 -> 6760.8 | D12: =C12-E12 -> 3677.8 | E12: =ELEC!Q13 -> 3083 | F12: =GEN!Z12 -> 7 | G12: =WATER!C15+WATER!H15 -> 0 | H12: =WATER!L15 -> 0 | I12: =WATER!BC15+WATER!BD15+WATER!BE16-Sheet1!G12 -> 104.3 | J12: ='B5'!A14 -> 44296
A13: =ELEC!T14+ELEC!X14+ELEC!AB14 -> 4 | B13: =ELEC!AF14 -> 731 | C13: =ELEC!N14 -> 7293.2 | D13: =C13-E13 -> 2946.2 | E13: =ELEC!Q14 -> 4347 | F13: =GEN!Z13 -> 6 | G13: =WATER!C16+WATER!H16 -> 5 | H13: =WATER!L16 -> 0 | I13: =WATER!BC16+WATER!BD16+WATER!BE17-Sheet1!G13 -> -30.5 | J13: ='B5'!A15 -> 44297
A14: =ELEC!T15+ELEC!X15+ELEC!AB15 -> 4 | B14: =ELEC!AF15 -> 668 | C14: =ELEC!N15 -> 6843 | D14: =C14-E14 -> 3587 | E14: =ELEC!Q15 -> 3256 | F14: =GEN!Z14 -> 8 | G14: =WATER!C17+WATER!H17 -> 0 | H14: =WATER!L17 -> 0 | I14: =WATER!BC17+WATER!BD17+WATER!BE18-Sheet1!G14 -> -21.7 | J14: ='B5'!A16 -> 44298
A15: =ELEC!T16+ELEC!X16+ELEC!AB16 -> 2 | B15: =ELEC!AF16 -> 545 | C15: =ELEC!N16 -> 6800 | D15: =C15-E15 -> 3800 | E15: =ELEC!Q16 -> 3000 | F15: =GEN!Z15 -> 6 | G15: =WATER!C18+WATER!H18 -> 0 | H15: =WATER!L18 -> 2 | I15: =WATER!BC18+WATER!BD18+WATER!BE19-Sheet1!G15 -> -17.7 | J15: ='B5'!A17 -> 44299
A16: =ELEC!T17+ELEC!X17+ELEC!AB17 -> 4 | B16: =ELEC!AF17 -> 773 | C16: =ELEC!N17 -> 7587 | D16: =C16-E16 -> 2587 | E16: =ELEC!Q17 -> 5000 | F16: =GEN!Z16 -> 6 | G16: =WATER!C19+WATER!H19 -> 0 | H16: =WATER!L19 -> 1 | I16: =WATER!BC19+WATER!BD19+WATER!BE20-Sheet1!G16 -> -24.7 | J16: ='B5'!A18 -> 44300
A17: =ELEC!T18+ELEC!X18+ELEC!AB18 -> 0 | B17: =ELEC!AF18 -> 0 | C17: =ELEC!N18 -> 0 | D17: =C17-E17 -> 0 | E17: =ELEC!Q18 -> 0 | F17: =GEN!Z17 -> 8 | G17: =WATER!C20+WATER!H20 -> 0 | H17: =WATER!L20 -> 0 | I17: =WATER!BC20+WATER!BD20+WATER!BE21-Sheet1!G17 -> -15.6 | J17: ='B5'!A19 -> 44301
A18: =ELEC!T19+ELEC!X19+ELEC!AB19 -> 0 | B18: =ELEC!AF19 -> 0 | C18: =ELEC!N19 -> 0 | D18: =C18-E18 -> 0 | E18: =ELEC!Q19 -> 0 | F18: =GEN!Z18 -> 0 | G18: =WATER!C21+WATER!H21 -> 0 | H18: =WATER!L21 -> 0 | I18: =WATER!BC21+WATER!BD21+WATER!BE22-Sheet1!G18 -> 0 | J18: ='B5'!A20 -> 44302
... A29: =ELEC!T30+ELEC!X30+ELEC!AB30 -> 0 | B29: =ELEC!AF30 -> 0 | C29: =ELEC!N30 -> 0 | D29: =C29-E29 -> 0 | E29: =ELEC!Q30 -> 0 | F29: =GEN!Z29 -> 0 | G29: =WATER!C32+WATER!H32 -> 0 | H29: =WATER!L32 -> 0 | I29: =WATER!BC32+WATER!BD32+WATER!BE33-Sheet1!G29 -> 0 | J29: ='B5'!A31 -> 44313
A30: =ELEC!#REF!+ELEC!#REF!+ELEC!#REF! -> #REF! | B30: =ELEC!#REF! -> #REF! | C30: =ELEC!#REF! -> #REF! | D30: =C30-E30 -> #REF! | E30: =ELEC!#REF! -> #REF! | F30: =GEN!Z30 -> 0 | G30: =WATER!C33+WATER!H33 -> 0 | H30: =WATER!L33 -> 0 | I30: =WATER!BC33+WATER!BD33+WATER!#REF!-Sheet1!G30 -> #REF! | J30: ='B5'!A32 -> 44314
A31: =ELEC!#REF!+ELEC!#REF!+ELEC!#REF! -> #REF! | B31: =ELEC!#REF! -> #REF! | C31: =ELEC!#REF! -> #REF! | D31: =C31-E31 -> #REF! | E31: =ELEC!#REF! -> #REF! | F31: =GEN!#REF! -> #REF! | G31: =WATER!#REF!+WATER!#REF! -> #REF! | H31: =WATER!#REF! -> #REF! | I31: =WATER!#REF!+WATER!#REF!+WATER!#REF!-Sheet1!G31 -> #REF! | J31: ='B5'!#REF! -> #REF!
A32: =ELEC!#REF!+ELEC!#REF!+ELEC!#REF! -> #REF! | B32: =ELEC!#REF! -> #REF! | C32: =ELEC!#REF! -> #REF! | D32: =C32-E32 -> #REF! | E32: =ELEC!#REF! -> #REF! | F32: =GEN!#REF! -> #REF! | G32: =WATER!#REF!+WATER!#REF! -> #REF! | H32: =WATER!#REF! -> #REF! | I32: =WATER!#REF!+WATER!#REF!+WATER!BE36-Sheet1!G32 -> #REF!

Sheet Report
B1: Boiler Fuel | C1: Steam Fuel | D1: GEN FUEL | E1: FUEL TOTAL | F1: CT/mᶾ | G1: Water Consumption | H1: Chiller KW | I1: GEN KW | J1: EDL KW | K1: occ | L1: covers | M1: temp. C⁰ | N1: RH %
B3: ='B5'!V3 -> 0 | C3: ='B5'!AH3 -> 0 | E3: =B3+C3+D3 -> 0
A4: 42704 | B4: 810 | C4: -606.1 | D4: 1420.5021 | E4: 1624.4021 | F4: 106 | G4: -58.4 | H4: 6284 | I4: 2399 | J4: 23932 | K4: 0 | L4: 0 | M4: 0 | N4: 0
A5: ='B5'!A5 -> 44287 | B5: ='B5'!V5 -> 359 | C5: ='B5'!AH5 -> 0 | D5: =GEN!AI3 -> 2369.9916 | E5: =B5+C5+D5 -> 2728.9916 | F5: =WATER!L5 -> 0 | G5: =WATER!BG5 -> -15.8 | H5: =ELEC!AF3 -> 1217 | I5: =ELEC!Q3 -> 9208 | J5: =ELEC!R3 -> 1419
A6: ='B5'!A6 -> 44288 | B6: ='B5'!V6 -> 298 | C6: ='B5'!AH6 -> 0 | D6: =GEN!AI4 -> 1987.519 | E6: =B6+C6+D6 -> 2285.519 | F6: =WATER!L6 -> 0 | G6: =WATER!BG6 -> -24.7 | H6: =ELEC!AF4 -> 546 | I6: =ELEC!Q4 -> 7722 | J6: =ELEC!R4 -> 844
A7: ='B5'!A7 -> 44289 | B7: ='B5'!V7 -> 287 | C7: ='B5'!AH7 -> 0 | D7: =GEN!AI5 -> 2126.5063 | E7: =B7+C7+D7 -> 2413.5063 | F7: =WATER!L7 -> 0 | G7: =WATER!BG7 -> -27.4 | H7: =ELEC!AF5 -> 1234 | I7: =ELEC!Q5 -> 8262 | J7: =ELEC!R5 -> 1424
A8: ='B5'!A8 -> 44290 | B8: ='B5'!V8 -> 290 | C8: ='B5'!AH8 -> 0 | D8: =GEN!AI6 -> 2043.8861 | E8: =B8+C8+D8 -> 2333.8861 | F8: =WATER!L8 -> 1 | G8: =WATER!BG8 -> -5.1 | H8: =ELEC!AF6 -> 764 | I8: =ELEC!Q6 -> 7941 | J8: =ELEC!R6 -> 1257
A9: ='B5'!A9 -> 44291 | B9: ='B5'!V9 -> 322 | C9: ='B5'!AH9 -> 82 | D9: =GEN!AI7 -> 1941.4473 | E9: =B9+C9+D9 -> 2345.4473 | F9: =WATER!L9 -> 2 | G9: =WATER!BG9 -> -16.3 | H9: =ELEC!AF7 -> 1147 | I9: =ELEC!Q7 -> 7543 | J9: =ELEC!R7 -> 2026
A10: ='B5'!A10 -> 44292 | B10: ='B5'!V10 -> 308 | C10: ='B5'!AH10 -> 0 | D10: =GEN!AI8 -> 2281.4515 | E10: =B10+C10+D10 -> 2589.4515 | F10: =WATER!L10 -> 0 | G10: =WATER!BG10 -> 51.8 | H10: =ELEC!AF8 -> 1976 | I10: =ELEC!Q8 -> 8864 | J10: =ELEC!R8 -> 1968
A11: ='B5'!A11 -> 44293 | B11: ='B5'!V11 -> 287 | C11: ='B5'!AH11 -> 0 | D11: =GEN!AI9 -> 1407.8903 | E11: =B11+C11+D11 -> 1694.8903 | F11: =WATER!L11 -> 2 | G11: =WATER!BG11 -> -20.7 | H11: =ELEC!AF9 -> 1380 | I11: =ELEC!Q9 -> 5470 | J11: =ELEC!R9 -> 3322
A12: ='B5'!A12 -> 44294 | B12: ='B5'!V12 -> 308 | C12: ='B5'!AH12 -> 108 | D12: =GEN!AI10 -> 1154.8819 | E12: =B12+C12+D12 -> 1570.8819 | F12: =WATER!L12 -> 0 | G12: =WATER!BG12 -> 18 | H12: =ELEC!AF10 -> 1113 | I12: =ELEC!Q10 -> 4487 | J12: =ELEC!R10 -> 3720
A13: ='B5'!A13 -> 44295 | B13: ='B5'!V13 -> 326 | C13: ='B5'!AH13 -> 0 | D13: =GEN!AI11 -> 1065.5696 | E13: =B13+C13+D13 -> 1391.5696 | F13: =WATER!L13 -> 0 | G13: =WATER!BG13 -> -46.9 | H13: =ELEC!AF11 -> 695 | I13: =ELEC!Q11 -> 4140 | J13: =ELEC!R11 -> 3444
A14: ='B5'!A14 -> 44296 | B14: ='B5'!V14 -> 409 | C14: ='B5'!AH14 -> 0 | D14: =GEN!AI12 -> 729.68354 | E14: =B14+C14+D14 -> 1138.6835 | F14: =WATER!L14 -> 0 | G14: =WATER!BG14 -> 89.7 | H14: =ELEC!AF12 -> 396 | I14: =ELEC!Q12 -> 2835 | J14: =ELEC!R12 -> 4048
A15: ='B5'!A15 -> 44297 | B15: ='B5'!V15 -> 368 | C15: ='B5'!AH15 -> 0 | D15: =GEN!AI13 -> 793.51477 | E15: =B15+C15+D15 -> 1161.5148 | F15: =WATER!L15 -> 0 | G15: =WATER!BG15 -> -143.4 | H15: =ELEC!AF13 -> 557 | I15: =ELEC!Q13 -> 3083 | J15: =ELEC!R13 -> 3677.8
A16: ='B5'!A16 -> 44298 | B16: ='B5'!V16 -> 367 | C16: ='B5'!AH16 -> 0 | D16: =GEN!AI14 -> 1118.8481 | E16: =B16+C16+D16 -> 1485.8481 | F16: =WATER!L16 -> 0 | G16: =WATER!BG16 -> 114.5 | H16: =ELEC!AF14 -> 731 | I16: =ELEC!Q14 -> 4347 | J16: =ELEC!R14 -> 2946.2
... A32: ='B5'!A32 -> 44314 | B32: ='B5'!V32 -> 0 | C32: ='B5'!AH32 -> 0 | D32: =GEN!AI30 -> 0 | E32: =B32+C32+D32 -> 0 | F32: =WATER!L32 -> 0 | G32: =WATER!BG32 -> 0 | H32: =ELEC!AF30 -> 0 | I32: =ELEC!Q30 -> 0 | J32: =ELEC!R30 -> 0
A33: ='B5'!#REF! -> #REF! | B33: ='B5'!#REF! -> #REF! | C33: ='B5'!#REF! -> #REF! | D33: =GEN!#REF! -> #REF! | E33: =B33+C33+D33 -> #REF! | F33: =WATER!L33 -> 0 | G33: =WATER!BG33 -> 0 | H33: =ELEC!#REF! -> #REF! | I33: =ELEC!#REF! -> #REF! | J33: =ELEC!#REF! -> #REF!
A34: ='B5'!#REF! -> #REF! | B34: ='B5'!#REF! -> #REF! | C34: ='B5'!#REF! -> #REF! | D34: =GEN!#REF! -> #REF! | E34: =B34+C34+D34 -> #REF! | F34: =WATER!#REF! -> #REF! | G34: =WATER!#REF! -> #REF! | H34: =ELEC!#REF! -> #REF! | I34: =ELEC!#REF! -> #REF! | J34: =ELEC!#REF! -> #REF!

Sheet Sheet5
T3: Outdoor conditions
C4: Date | D4: Total Boiler running H | E4: AVE CONSUM | F4: Total Steam running H | G4: AVE CONSUM | H4: Total GEN running H | I4: AVE CONSUM | J4: Actual Diesel Consumption | K4: Actual Gas Consumption | L4: Total ELEC power | M4: Gen ELEC power | N4: EDL ELEC power | O4: Chillers running H | P4: Total Water delivery | Q4: Total water consumption | R4: Total water in tanks | S4: Occupancy | T4: AVE TEPM | U4: AVE Humidity
C5: 42429 | D5: ='B5'!AL4 -> 5 | E5: =D5*90 -> 450 | F5: ='B5'!AM4 -> 0 | G5: =F5*107 -> 0 | H5: =GEN!Z3 -> 20
C6: 42430 | D6: ='B5'!AL5 -> 5 | E6: =D6*90 -> 450 | F6: ='B5'!AM5 -> 0 | G6: =F6*107 -> 0
C7: 42431 | D7: ='B5'!AL6 -> 5 | E7: =D7*90 -> 450 | F7: ='B5'!AM6 -> 0 | G7: =F7*107 -> 0
C8: 42432 | D8: ='B5'!AL7 -> 3 | E8: =D8*90 -> 270 | F8: ='B5'!AM7 -> 0 | G8: =F8*107 -> 0
C9: 42433 | D9: ='B5'!AL8 -> 4 | E9: =D9*90 -> 360 | F9: ='B5'!AM8 -> 0 | G9: =F9*107 -> 0
C10: 42434 | D10: ='B5'!AL9 -> 3 | E10: =D10*90 -> 270 | F10: ='B5'!AM9 -> 1 | G10: =F10*107 -> 107
C11: 42435 | D11: ='B5'!AL10 -> 4 | E11: =D11*90 -> 360 | F11: ='B5'!AM10 -> 0 | G11: =F11*107 -> 0
C12: 42436 | D12: ='B5'!AL11 -> 5 | E12: =D12*90 -> 450 | F12: ='B5'!AM11 -> 0 | G12: =F12*107 -> 0
C13: 42437 | D13: ='B5'!AL12 -> 4 | E13: =D13*90 -> 360 | F13: ='B5'!AM12 -> 1 | G13: =F13*107 -> 107
C14: 42438 | D14: ='B5'!AL13 -> 4 | E14: =D14*90 -> 360 | F14: ='B5'!AM13 -> 0 | G14: =F14*107 -> 0
C15: 42439 | D15: ='B5'!AL14 -> 5 | E15: =D15*90 -> 450 | F15: ='B5'!AM14 -> 0 | G15: =F15*107 -> 0
C16: 42440 | D16: ='B5'!AL15 -> 4 | E16: =D16*90 -> 360 | F16: ='B5'!AM15 -> 0 | G16: =F16*107 -> 0
C17: 42441 | D17: ='B5'!AL16 -> 6 | E17: =D17*90 -> 540 | F17: ='B5'!AM16 -> 0 | G17: =F17*107 -> 0
... C33: 42457 | D33: ='B5'!AL32 -> 0 | E33: =D33*90 -> 0 | F33: ='B5'!AM32 -> 0 | G33: =F33*107 -> 0
C34: 42458 | D34: ='B5'!#REF! -> #REF! | E34: =D34*90 -> #REF! | F34: ='B5'!#REF! -> #REF! | G34: =F34*107 -> #REF!
C35: 42459 | D35: ='B5'!#REF! -> #REF! | E35: =D35*90 -> #REF! | F35: ='B5'!#REF! -> #REF! | G35: =F35*107 -> #REF!
C36: 42460 | D36: ='B5'!#REF! -> #REF! | E36: =D36*90 -> #REF! | F36: ='B5'!#REF! -> #REF! | G36: =F36*107 -> #REF!
C37: 42461 | D37: ='B5'!#REF! -> #REF! | E37: =D37*90 -> #REF! | F37: ='B5'!#REF! -> #REF! | G37: =F37*107 -> #REF!

Sheet GEN
B1: GEN1 | C1: RUN HR | D1: Fuel Counter Index | E1: Cons /day | F1: Diesel L/H | H1: next service | I1: ALARM | J1: GEN2 | K1: RUN HR | L1: Fuel Counter Index | M1: Cons /day | N1: Diesel L/H | P1: next service | Q1: ALARM | R1: GEN3 | S1: RUN HR | T1: Fuel Counter Index | U1: Cons /day | V1: Diesel L/H | X1: next service | Y1: ALARM | Z1: RH total | AA1: Gen Con /day | AB1: Total Deisel Cons/day | AC1: H /L | AD1: TOAL KW GEN | AI1: fuel Consuption | AK1: AVG KW/h
A2: =ELEC!C2 -> 44286 | B2: =[3]GEN!B33 -> 9772 | C2: =[3]GEN!C33 -> 7 | D2: =[3]GEN!D33 -> 361982 | E2: =[3]GEN!E33 -> 1767 | F2: =[3]GEN!F33 -> 252.42857 | G2: =[3]GEN!G33 -> 0 | H2: =[3]GEN!H33 -> 9729 | I2: =[3]GEN!I33 -> oil change | ... AA2: =[3]GEN!AA33 -> 4767 | AB2: =[1]GEN!AB30 -> 250 | AC2: =[3]GEN!AC33 -> 250.89474 | AD2: =[3]GEN!AD33 -> 9980 | AE2: =[3]GEN!AE33 -> 525.26316 | AF2: =[3]GEN!AF33 -> 0.32828947 | AG2: =[3]GEN!AG33 -> 105.05263 | AH2: =[3]GEN!AH33 -> 145.84211 | AI2: =[3]GEN!AI33 -> 2568.692 | AJ2: =[3]GEN!AJ33 -> 0.25738397 | AK2: =[3]GEN!AK33 -> 135.19431
A3: =ELEC!C3 -> 44287 | B3: 9782 | C3: =B3-B2 -> 10 | D3: 364660 | E3: =SUM(D3-D2) -> 2678 | F3: =IF(C3>0,E3/C3,0) -> 267.8 | G3: =[6]GEN!G32 -> 0 | H3: =H2 -> 9729 | I3: =IF(B3-H3<=0,"ok","oil change") -> oil change | J3: =J2 -> 10698 | K3: =J3-J2 -> 0 | L3: =L2 -> 357691 | M3: =SUM(L3-L2) -> 0 | N3: =IF(K3>0,M3/K3,0) -> 0 | O3: =[6]GEN!O32 -> 0 | P3: =P2 -> 10873 | Q3: =IF(J3-P3<=0,"ok","oil change") -> ok | R3: 12041 | S3: =R3-R2 -> 10 | T3: =436413+U3 -> 438913 | U3: =V3*S3 -> 2500 | V3: 250 | W3: =[6]GEN!W32 -> 0 | X3: =X2 -> 11898 | Y3: =IF(R3-X3<=0,"ok","oil change") -> oil change | Z3: =C3+K3+S3 -> 20 | AA3: =U3+M3+E3 -> 5178 | AB3: =V3+N3+F3 -> 517.8 | AC3: =IF(Z3>0,AA3/Z3,0) -> 258.9 | AD3: =ELEC!Q3 -> 9208 | AE3: =SUM(AD3/Z3) -> 460.4 | AF3: =SUM(AE3/1600) -> 0.28775 | AG3: =SUM(360*AF3) -> 103.59 | AH3: =SUM(AC3-AG3) -> 155.31 | AI3: =AD3*AJ3 -> 2369.9916 | AJ3: =305/1185 -> 0.25738397 | AK3: =AI3/Z3 -> 118.49958
A4: =ELEC!C4 -> 44288 | B4: 9795 | C4: =B4-B3 -> 13 | D4: 368388 | E4: =SUM(D4-D3) -> 3728 | F4: =IF(C4>0,E4/C4,0) -> 286.76923 | H4: 9934 | I4: =IF(B4-H4<=0,"ok","oil change") -> ok | J4: =J3 -> 10698 | K4: =J4-J3 -> 0 | L4: =L3 -> 357691 | M4: =SUM(L4-L3) -> 0 | N4: =IF(K4>0,M4/K4,0) -> 0 | P4: =P3 -> 10873 | Q4: =IF(J4-P4<=0,"ok","oil change") -> ok | R4: 12042 | S4: =R4-R3 -> 1 | T4: =436413+U4 -> 436663 | U4: =V4*S4 -> 250 | V4: 250 | X4: 12192 | Y4: =IF(R4-X4<=0,"ok","oil change") -> ok | Z4: =C4+K4+S4 -> 14 | AA4: =U4+M4+E4 -> 3978 | AB4: =V4+N4+F4 -> 536.76923 | AC4: =IF(Z4>0,AA4/Z4,0) -> 284.14286 | AD4: =ELEC!Q4 -> 7722 | AE4: =SUM(AD4/Z4) -> 551.57143 | AF4: =SUM(AE4/1600) -> 0.34473214 | AG4: =SUM(360*AF4) -> 124.10357 | AH4: =SUM(AC4-AG4) -> 160.03929 | AI4: =AD4*AJ4 -> 1987.519 | AJ4: =305/1185 -> 0.25738397 | AK4: =AI4/Z4 -> 141.96564
A5: =ELEC!C5 -> 44289 | B5: 9809 | C5: =B5-B4 -> 14 | D5: 371590 | E5: =SUM(D5-D4) -> 3202 | F5: =IF(C5>0,E5/C5,0) -> 228.71429 | H5: =H4 -> 9934 | I5: =IF(B5-H5<=0,"ok","oil change") -> ok | J5: =J4 -> 10698 | K5: =J5-J4 -> 0 | L5: =L4 -> 357691 | M5: =SUM(L5-L4) -> 0 | N5: =IF(K5>0,M5/K5,0) -> 0 | P5: =P4 -> 10873 | Q5: =IF(J5-P5<=0,"ok","oil change") -> ok | R5: 12043 | S5: =R5-R4 -> 1 | T5: =436413+U5 -> 436663 | U5: =V5*S5 -> 250 | V5: 250 | X5: =X4 -> 12192 | Y5: =IF(R5-X5<=0,"ok","oil change") -> ok | Z5: =C5+K5+S5 -> 15 | AA5: =U5+M5+E5 -> 3452 | AB5: =V5+N5+F5 -> 478.71429 | AC5: =IF(Z5>0,AA5/Z5,0) -> 230.13333 | AD5: =ELEC!Q5 -> 8262 | AE5: =SUM(AD5/Z5) -> 550.8 | AF5: =SUM(AE5/1600) -> 0.34425 | AG5: =SUM(320*AF5) -> 110.16 | AH5: =SUM(AC5-AG5) -> 119.97333 | AI5: =AD5*AJ5 -> 2126.5063 | AJ5: =305/1185 -> 0.25738397 | AK5: =AI5/Z5 -> 141.76709
A6: =ELEC!C6 -> 44290 | B6: 9809 | C6: =B6-B5 -> 0 | D6: =D5 -> 371590 | E6: =SUM(D6-D5) -> 0 | F6: =IF(C6>0,E6/C6,0) -> 0 | H6: =H5 -> 9934 | I6: =IF(B6-H6<=0,"ok","oil change") -> ok | J6: =J5 -> 10698 | K6: =J6-J5 -> 0 | L6: =L5 -> 357691 | M6: =SUM(L6-L5) -> 0 | N6: =IF(K6>0,M6/K6,0) -> 0 | P6: =P5 -> 10873 | Q6: =IF(J6-P6<=0,"ok","oil change") -> ok | R6: 12061 | S6: =R6-R5 -> 18 | T6: =436413+U6 -> 440913 | U6: =V6*S6 -> 4500 | V6: 250 | X6: =X5 -> 12192 | Y6: =IF(R6-X6<=0,"ok","oil change") -> ok | Z6: =C6+K6+S6 -> 18 | AA6: =U6+M6+E6 -> 4500 | AB6: =V6+N6+F6 -> 250 | AC6: =IF(Z6>0,AA6/Z6,0) -> 250 | AD6: =ELEC!Q6 -> 7941 | AE6: =SUM(AD6/Z6) -> 441.16667 | AF6: =SUM(AE6/1600) -> 0.27572917 | AG6: =SUM(320*AF6) -> 88.233333 | AH6: =SUM(AC6-AG6) -> 161.76667 | AI6: =AD6*AJ6 -> 2043.8861 | AJ6: =305/1185 -> 0.25738397 | AK6: =AI6/Z6 -> 113.54923
A7: =ELEC!C7 -> 44291 | B7: 9809 | C7: =B7-B6 -> 0 | D7: =D6 -> 371590 | E7: =SUM(D7-D6) -> 0 | F7: =IF(C7>0,E7/C7,0) -> 0 | H7: =H6 -> 9934 | I7: =IF(B7-H7<=0,"ok","oil change") -> ok | J7: =J6 -> 10698 | K7: =J7-J6 -> 0 | L7: =L6 -> 357691 | M7: =SUM(L7-L6) -> 0 | N7: =IF(K7>0,M7/K7,0) -> 0 | P7: =P6 -> 10873 | Q7: =IF(J7-P7<=0,"ok","oil change") -> ok | R7: 12076 | S7: =R7-R6 -> 15 | T7: =436413+U7 -> 440163 | U7: =V7*S7 -> 3750 | V7: 250 | X7: =X6 -> 12192 | Y7: =IF(R7-X7<=0,"ok","oil change") -> ok | Z7: =C7+K7+S7 -> 15 | AA7: =U7+M7+E7 -> 3750 | AB7: =V7+N7+F7 -> 250 | AC7: =IF(Z7>0,AA7/Z7,0) -> 250 | AD7: =ELEC!Q7 -> 7543 | AE7: =SUM(AD7/Z7) -> 502.86667 | AF7: =SUM(AE7/1600) -> 0.31429167 | AH7: =SUM(AC7-AG7) -> #VALUE! | AI7: =AD7*AJ7 -> 1941.4473 | AJ7: =305/1185 -> 0.25738397 | AK7: =AI7/Z7 -> 129.42982
A8: =ELEC!C8 -> 44292 | B8: =B7 -> 9809 | C8: =B8-B7 -> 0 | D8: =D7 -> 371590 | E8: =SUM(D8-D7) -> 0 | F8: =IF(C8>0,E8/C8,0) -> 0 | H8: =H7 -> 9934 | I8: =IF(B8-H8<=0,"ok","oil change") -> ok | J8: =J7 -> 10698 | K8: =J8-J7 -> 0 | L8: =L7 -> 357691 | M8: =SUM(L8-L7) -> 0 | N8: =IF(K8>0,M8/K8,0) -> 0 | P8: =P7 -> 10873 | Q8: =IF(J8-P8<=0,"ok","oil change") -> ok | R8: 12090 | S8: =R8-R7 -> 14 | T8: =436413+U8 -> 439913 | U8: =V8*S8 -> 3500 | V8: 250 | X8: =X7 -> 12192 | Y8: =IF(R8-X8<=0,"ok","oil change") -> ok | Z8: =C8+K8+S8 -> 14 | AA8: =U8+M8+E8 -> 3500 | AB8: =V8+N8+F8 -> 250 | AC8: =IF(Z8>0,AA8/Z8,0) -> 250 | AD8: =ELEC!Q8 -> 8864 | AE8: =SUM(AD8/Z8) -> 633.14286 | AF8: =SUM(AE8/1600) -> 0.39571429 | AG8: =SUM(320*AF8) -> 126.62857 | AH8: =SUM(AC8-AG8) -> 123.37143 | AI8: =AD8*AJ8 -> 2281.4515 | AJ8: =305/1185 -> 0.25738397 | AK8: =AI8/Z8 -> 162.96082
A9: =ELEC!C9 -> 44293 | B9: =B8 -> 9809 | C9: =B9-B8 -> 0 | D9: =D8 -> 371590 | E9: =SUM(D9-D8) -> 0 | F9: =IF(C9>0,E9/C9,0) -> 0 | H9: =H8 -> 9934 | I9: =IF(B9-H9<=0,"ok","oil change") -> ok | J9: =J8 -> 10698 | K9: =J9-J8 -> 0 | L9: =L8 -> 357691 | M9: =SUM(L9-L8) -> 0 | N9: =IF(K9>0,M9/K9,0) -> 0 | P9: =P8 -> 10873 | Q9: =IF(J9-P9<=0,"ok","oil change") -> ok | R9: 12098 | S9: =R9-R8 -> 8 | T9: =436413+U9 -> 438413 | U9: =V9*S9 -> 2000 | V9: 250 | X9: =X8 -> 12192 | Y9: =IF(R9-X9<=0,"ok","oil change") -> ok | Z9: =C9+K9+S9 -> 8 | AA9: =U9+M9+E9 -> 2000 | AB9: =V9+N9+F9 -> 250 | AC9: =IF(Z9>0,AA9/Z9,0) -> 250 | AD9: =ELEC!Q9 -> 5470 | AE9: =SUM(AD9/Z9) -> 683.75 | AF9: =SUM(AE9/1600) -> 0.42734375 | AG9: =SUM(320*AF9) -> 136.75 | AH9: =SUM(AC9-AG9) -> 113.25 | AI9: =AD9*AJ9 -> 1407.8903 | AJ9: 0.25738397 | AK9: =IF(Z9>0,AI9/Z9,0) -> 175.98629
A10: =ELEC!C10 -> 44294 | B10: =B9 -> 9809 | C10: =B10-B9 -> 0 | D10: =D9 -> 371590 | E10: =SUM(D10-D9) -> 0 | F10: =IF(C10>0,E10/C10,0) -> 0 | H10: =H9 -> 9934 | I10: =IF(B10-H10<=0,"ok","oil change") -> ok | J10: =J9 -> 10698 | K10: =J10-J9 -> 0 | L10: =L9 -> 357691 | M10: =SUM(L10-L9) -> 0 | N10: =IF(K10>0,M10/K10,0) -> 0 | P10: =P9 -> 10873 | Q10: =IF(J10-P10<=0,"ok","oil change") -> ok | R10: 12105 | S10: =R10-R9 -> 7 | T10: =436413+U10 -> 438163 | U10: =V10*S10 -> 1750 | V10: 250 | X10: =X9 -> 12192 | Y10: =IF(R10-X10<=0,"ok","oil change") -> ok | Z10: =C10+K10+S10 -> 7 | AA10: =U10+M10+E10 -> 1750 | AB10: =V10+N10+F10 -> 250 | AC10: =IF(Z10>0,AA10/Z10,0) -> 250 | AD10: =ELEC!Q10 -> 4487 | AE10: =SUM(AD10/Z10) -> 641 | AF10: =SUM(AE10/1600) -> 0.400625 | AG10: =SUM(320*AF10) -> 128.2 | AH10: =SUM(AC10-AG10) -> 121.8 | AI10: =AD10*AJ10 -> 1154.8819 | AJ10: =305/1185 -> 0.25738397 | AK10: =IF(Z10>0,AI10/Z10,0) -> 164.98312
A11: =ELEC!C11 -> 44295 | B11: =B10 -> 9809 | C11: =B11-B10 -> 0 | D11: =D10 -> 371590 | E11: =SUM(D11-D10) -> 0 | F11: =IF(C11>0,E11/C11,0) -> 0 | H11: =H10 -> 9934 | I11: =IF(B11-H11<=0,"ok","oil change") -> ok | J11: =J10 -> 10698 | K11: =J11-J10 -> 0 | L11: =L10 -> 357691 | M11: =SUM(L11-L10) -> 0 | N11: =IF(K11>0,M11/K11,0) -> 0 | P11: =P10 -> 10873 | Q11: =IF(J11-P11<=0,"ok","oil change") -> ok | R11: 12111 | S11: =R11-R10 -> 6 | T11: =436413+U11 -> 437913 | U11: =V11*S11 -> 1500 | V11: 250 | X11: =X10 -> 12192 | Y11: =IF(R11-X11<=0,"ok","oil change") -> ok | Z11: =C11+K11+S11 -> 6 | AA11: =U11+M11+E11 -> 1500 | AB11: =V11+N11+F11 -> 250 | AC11: =IF(Z11>0,AA11/Z11,0) -> 250 | AD11: =ELEC!Q11 -> 4140 | AE11: =SUM(AD11/Z11) -> 690 | AF11: =SUM(AE11/1600) -> 0.43125 | AG11: =SUM(320*AF11) -> 138 | AH11: =SUM(AC11-AG11) -> 112 | AI11: =AD11*AJ11 -> 1065.5696 | AJ11: =305/1185 -> 0.25738397 | AK11: =IF(Z11>0,AI11/Z11,0) -> 177.59494
A12: =ELEC!C12 -> 44296 | B12: =B11 -> 9809 | C12: =B12-B11 -> 0 | D12: =D11 -> 371590 | E12: =SUM(D12-D11) -> 0 | F12: =IF(C12>0,E12/C12,0) -> 0 | H12: =H11 -> 9934 | I12: =IF(B12-H12<=0,"ok","oil change") -> ok | J12: =J11 -> 10698 | K12: =J12-J11 -> 0 | L12: =L11 -> 357691 | M12: =SUM(L12-L11) -> 0 | N12: =IF(K12>0,M12/K12,0) -> 0 | P12: =P11 -> 10873 | Q12: =IF(J12-P12<=0,"ok","oil change") -> ok | R12: 12118 | S12: =R12-R11 -> 7 | T12: =436413+U12 -> 438163 | U12: =V12*S12 -> 1750 | V12: 250 | X12: =X11 -> 12192 | Y12: =IF(R12-X12<=0,"ok","oil change") -> ok | Z12: =C12+K12+S12 -> 7 | AA12: =U12+M12+E12 -> 1750 | AB12: =V12+N12+F12 -> 250 | AC12: =IF(Z12>0,AA12/Z12,0) -> 250 | AD12: =ELEC!Q12 -> 2835 | AE12: =SUM(AD12/Z12) -> 405 | AF12: =SUM(AE12/1600) -> 0.253125 | AG12: =SUM(320*AF12) -> 81 | AH12: =SUM(AC12-AG12) -> 169 | AI12: =AD12*AJ12 -> 729.68354 | AJ12: =305/1185 -> 0.25738397 | AK12: =IF(Z12>0,AI12/Z12,0) -> 104.24051
A13: =ELEC!C13 -> 44297 | B13: =B12 -> 9809 | C13: =B13-B12 -> 0 | D13: =D12 -> 371590 | E13: =SUM(D13-D12) -> 0 | F13: =IF(C13>0,E13/C13,0) -> 0 | H13: =H12 -> 9934 | I13: =IF(B13-H13<=0,"ok","oil change") -> ok | J13: =J12 -> 10698 | K13: =J13-J12 -> 0 | L13: =L12 -> 357691 | M13: =SUM(L13-L12) -> 0 | N13: =IF(K13>0,M13/K13,0) -> 0 | P13: =P12 -> 10873 | Q13: =IF(J13-P13<=0,"ok","oil change") -> ok | R13: 12124 | S13: =R13-R12 -> 6 | T13: =436413+U13 -> 437913 | U13: =V13*S13 -> 1500 | V13: 250 | X13: =X12 -> 12192 | Y13: =IF(R13-X13<=0,"ok","oil change") -> ok | Z13: =C13+K13+S13 -> 6 | AA13: =U13+M13+E13 -> 1500 | AB13: =V13+N13+F13 -> 250 | AC13: =IF(Z13>0,AA13/Z13,0) -> 250 | AD13: =ELEC!Q13 -> 3083 | AE13: =SUM(AD13/Z13) -> 513.83333 | AF13: =SUM(AE13/1600) -> 0.32114583 | AG13: =SUM(320*AF13) -> 102.76667 | AH13: =SUM(AC13-AG13) -> 147.23333 | AI13: =AD13*AJ13 -> 793.51477 | AJ13: =305/1185 -> 0.25738397 | AK13: =IF(Z13>0,AI13/Z13,0) -> 132.25246
A14: =ELEC!C14 -> 44298 | B14: =B13 -> 9809 | C14: =B14-B13 -> 0 | D14: =D13 -> 371590 | E14: =SUM(D14-D13) -> 0 | F14: =IF(C14>0,E14/C14,0) -> 0 | H14: =H13 -> 9934 | I14: =IF(B14-H14<=0,"ok","oil change") -> ok | J14: =J13 -> 10698 | K14: =J14-J13 -> 0 | L14: =L13 -> 357691 | M14: =SUM(L14-L13) -> 0 | N14: =IF(K14>0,M14/K14,0) -> 0 | P14: =P13 -> 10873 | Q14: =IF(J14-P14<=0,"ok","oil change") -> ok | R14: 12132 | S14: =R14-R13 -> 8 | T14: =436413+U14 -> 438413 | U14: =V14*S14 -> 2000 | V14: 250 | X14: =X13 -> 12192 | Y14: =IF(R14-X14<=0,"ok","oil change") -> ok | Z14: =C14+K14+S14 -> 8 | AA14: =U14+M14+E14 -> 2000 | AB14: =V14+N14+F14 -> 250 | AC14: =IF(Z14>0,AA14/Z14,0) -> 250 | AD14: =ELEC!Q14 -> 4347 | AE14: =SUM(AD14/Z14) -> 543.375 | AF14: =SUM(AE14/1600) -> 0.33960937 | AG14: =SUM(320*AF14) -> 108.675 | AH14: =SUM(AC14-AG14) -> 141.325 | AI14: =AD14*AJ14 -> 1118.8481 | AJ14: =305/1185 -> 0.25738397 | AK14: =IF(Z14>0,AI14/Z14,0) -> 139.85601
A15: =ELEC!C15 -> 44299 | B15: 9812 | C15: =B15-B14 -> 3 | D15: 372220 | E15: =SUM(D15-D14) -> 630 | F15: =IF(C15>0,E15/C15,0) -> 210 | H15: =H14 -> 9934 | I15: =IF(B15-H15<=0,"ok","oil change") -> ok | J15: =J14 -> 10698 | K15: =J15-J14 -> 0 | L15: =L14 -> 357691 | M15: =SUM(L15-L14) -> 0 | N15: =IF(K15>0,M15/K15,0) -> 0 | P15: =P14 -> 10873 | Q15: =IF(J15-P15<=0,"ok","oil change") -> ok | R15: 12135 | S15: =R15-R14 -> 3 | T15: =436413+U15 -> 437163 | U15: =V15*S15 -> 750 | V15: 250 | X15: =X14 -> 12192 | Y15: =IF(R15-X15<=0,"ok","oil change") -> ok | Z15: =C15+K15+S15 -> 6 | AA15: =U15+M15+E15 -> 1380 | AB15: =V15+N15+F15 -> 460 | AC15: =IF(Z15>0,AA15/Z15,0) -> 230 | AD15: =ELEC!Q15 -> 3256 | AE15: =SUM(AD15/Z15) -> 542.66667 | AF15: =SUM(AE15/1600) -> 0.33916667 | AG15: =SUM(320*AF15) -> 108.53333 | AH15: =SUM(AC15-AG15) -> 121.46667 | AI15: =AD15*AJ15 -> 838.04219 | AJ15: =305/1185 -> 0.25738397 | AK15: =IF(Z15>0,AI15/Z15,0) -> 139.6737
A16: =ELEC!C16 -> 44300 | B16: 9818 | C16: =B16-B15 -> 6 | D16: 373994 | E16: =SUM(D16-D15) -> 1774 | F16: =IF(C16>0,E16/C16,0) -> 295.66667 | H16: =H15 -> 9934 | I16: =IF(B16-H16<=0,"ok","oil change") -> ok | J16: =J15 -> 10698 | K16: =J16-J15 -> 0 | L16: =L15 -> 357691 | M16: =SUM(L16-L15) -> 0 | N16: =IF(K16>0,M16/K16,0) -> 0 | P16: =P15 -> 10873 | Q16: =IF(J16-P16<=0,"ok","oil change") -> ok | R16: =R15 -> 12135 | S16: =R16-R15 -> 0 | T16: =436413+U16 -> 436413 | U16: =V16*S16 -> 0 | V16: 250 | X16: =X15 -> 12192 | Y16: =IF(R16-X16<=0,"ok","oil change") -> ok | Z16: =C16+K16+S16 -> 6 | AA16: =U16+M16+E16 -> 1774 | AB16: =V16+N16+F16 -> 545.66667 | AC16: =IF(Z16>0,AA16/Z16,0) -> 295.66667 | AD16: =ELEC!Q16 -> 3000 | AE16: =SUM(AD16/Z16) -> 500 | AF16: =SUM(AE16/1600) -> 0.3125 | AG16: =SUM(320*AF16) -> 100 | AH16: =SUM(AC16-AG16) -> 195.66667 | AI16: =AD16*AJ16 -> 772.1519 | AJ16: =305/1185 -> 0.25738397 | AK16: =IF(Z16>0,AI16/Z16,0) -> 128.69198
A17: =ELEC!C17 -> 44301 | B17: 9826 | C17: =B17-B16 -> 8 | D17: 375483 | E17: =SUM(D17-D16) -> 1489 | F17: =IF(C17>0,E17/C17,0) -> 186.125 | H17: =H16 -> 9934 | I17: =IF(B17-H17<=0,"ok","oil change") -> ok | J17: =J16 -> 10698 | K17: =J17-J16 -> 0 | L17: =L16 -> 357691 | M17: =SUM(L17-L16) -> 0 | N17: =IF(K17>0,M17/K17,0) -> 0 | P17: =P16 -> 10873 | Q17: =IF(J17-P17<=0,"ok","oil change") -> ok | R17: =R16 -> 12135 | S17: =R17-R16 -> 0 | T17: =436413+U17 -> 436413 | U17: =V17*S17 -> 0 | V17: 250 | X17: =X16 -> 12192 | Y17: =IF(R17-X17<=0,"ok","oil change") -> ok | Z17: =C17+K17+S17 -> 8 | AA17: =U17+M17+E17 -> 1489 | AB17: =V17+N17+F17 -> 436.125 | AC17: =IF(Z17>0,AA17/Z17,0) -> 186.125 | AD17: =ELEC!Q17 -> 5000 | AE17: =SUM(AD17/Z17) -> 625 | AF17: =SUM(AE17/1600) -> 0.390625 | AG17: =SUM(320*AF17) -> 125 | AH17: =SUM(AC17-AG17) -> 61.125 | AI17: =AD17*AJ17 -> 1286.9198 | AJ17: =305/1185 -> 0.25738397 | AK17: =IF(Z17>0,AI17/Z17,0) -> 160.86498
A18: =ELEC!C18 -> 44302 | B18: =B17 -> 9826 | C18: =B18-B17 -> 0 | D18: =D17 -> 375483 | E18: =SUM(D18-D17) -> 0 | F18: =IF(C18>0,E18/C18,0) -> 0 | H18: =H17 -> 9934 | I18: =IF(B18-H18<=0,"ok","oil change") -> ok | J18: =J17 -> 10698 | K18: =J18-J17 -> 0 | L18: =L17 -> 357691 | M18: =SUM(L18-L17) -> 0 | N18: =IF(K18>0,M18/K18,0) -> 0 | P18: =P17 -> 10873 | Q18: =IF(J18-P14<=0,"ok","oil change") -> ok | R18: =R17 -> 12135 | S18: =R18-R17 -> 0 | T18: =436413+U18 -> 436413 | U18: =V18*S18 -> 0 | V18: 250 | X18: =X17 -> 12192 | Y18: =IF(R18-X18<=0,"ok","oil change") -> ok | Z18: =C18+K18+S18 -> 0 | AA18: =U18+M18+E18 -> 0 | AB18: =V18+N18+F18 -> 250 | AC18: =IF(Z18>0,AA18/Z18,0) -> 0 | AD18: =ELEC!Q18 -> 0 | AE18: =SUM(AD18/Z18) -> #DIV/0! | AF18: =SUM(AE18/1600) -> #DIV/0! | AG18: =SUM(320*AF18) -> #DIV/0! | AH18: =SUM(AC18-AG18) -> #DIV/0! | AI18: =AD18*AJ18 -> 0 | AJ18: =305/1185 -> 0.25738397 | AK18: =IF(Z18>0,AI18/Z18,0) -> 0
A19: =ELEC!C19 -> 44303 | B19: =B18 -> 9826 | C19: =B19-B18 -> 0 | D19: =D18 -> 375483 | E19: =SUM(D19-D18) -> 0 | F19: =IF(C19>0,E19/C19,0) -> 0 | H19: =H18 -> 9934 | I19: =IF(B19-H19<=0,"ok","oil change") -> ok | J19: =J18 -> 10698 | K19: =J19-J18 -> 0 | L19: =L18 -> 357691 | M19: =SUM(L19-L18) -> 0 | N19: =IF(K19>0,M19/K19,0) -> 0 | P19: =P18 -> 10873 | Q19: =IF(J19-P19<=0,"ok","oil change") -> ok | R19: =R18 -> 12135 | S19: =R19-R18 -> 0 | T19: =436413+U19 -> 436413 | U19: =V19*S19 -> 0 | V19: 250 | X19: =X18 -> 12192 | Y19: =IF(R19-X19<=0,"ok","oil change") -> ok | Z19: =C19+K19+S19 -> 0 | AA19: =U19+M19+E19 -> 0 | AB19: =V19+N19+F19 -> 250 | AC19: =IF(Z19>0,AA19/Z19,0) -> 0 | AD19: =ELEC!Q19 -> 0 | AE19: =SUM(AD19/Z19) -> #DIV/0! | AF19: =SUM(AE19/1600) -> #DIV/0! | AG19: =SUM(320*AF19) -> #DIV/0! | AH19: =SUM(AC19-AG19) -> #DIV/0! | AI19: =AD19*AJ19 -> 0 | AJ19: =305/1185 -> 0.25738397 | AK19: =IF(Z19>0,AI19/Z19,0) -> 0
A20: =ELEC!C20 -> 44304 | B20: =B19 -> 9826 | C20: =B20-B19 -> 0 | D20: =D19 -> 375483 | E20: =SUM(D20-D19) -> 0 | F20: =IF(C20>0,E20/C20,0) -> 0 | H20: =H19 -> 9934 | I20: =IF(B20-H20<=0,"ok","oil change") -> ok | J20: =J19 -> 10698 | K20: =J20-J19 -> 0 | L20: =L19 -> 357691 | M20: =SUM(L20-L19) -> 0 | N20: =IF(K20>0,M20/K20,0) -> 0 | P20: =P19 -> 10873 | Q20: =IF(J20-P20<=0,"ok","oil change") -> ok | R20: =R19 -> 12135 | S20: =R20-R19 -> 0 | T20: =436413+U20 -> 436413 | U20: =V20*S20 -> 0 | V20: 250 | X20: =X19 -> 12192 | Y20: =IF(R20-X20<=0,"ok","oil change") -> ok | Z20: =C20+K20+S20 -> 0 | AA20: =U20+M20+E20 -> 0 | AB20: =V20+N20+F20 -> 250 | AC20: =IF(Z20>0,AA20/Z20,0) -> 0 | AD20: =ELEC!Q20 -> 0 | AE20: =SUM(AD20/Z20) -> #DIV/0! | AF20: =SUM(AE20/1600) -> #DIV/0! | AG20: =SUM(320*AF20) -> #DIV/0! | AH20: =SUM(AC20-AG20) -> #DIV/0! | AI20: =AD20*AJ20 -> 0 | AJ20: =305/1185 -> 0.25738397 | AK20: =IF(Z20>0,AI20/Z20,0) -> 0
A21: =ELEC!C21 -> 44305 | B21: =B20 -> 9826 | C21: =B21-B20 -> 0 | D21: =D20 -> 375483 | E21: =SUM(D21-D20) -> 0 | F21: =IF(C21>0,E21/C21,0) -> 0 | H21: =H20 -> 9934 | I21: =IF(B21-H21<=0,"ok","oil change") -> ok | J21: =J20 -> 10698 | K21: =J21-J20 -> 0 | L21: =L20 -> 357691 | M21: =SUM(L21-L20) -> 0 | N21: =IF(K21>0,M21/K21,0) -> 0 | P21: =P20 -> 10873 | Q21: =IF(J21-P21<=0,"ok","oil change") -> ok | R21: =R20 -> 12135 | S21: =R21-R20 -> 0 | T21: =436413+U21 -> 436413 | U21: =V21*S21 -> 0 | V21: 250 | X21: =X20 -> 12192 | Y21: =Y20 -> ok | Z21: =C21+K21+S21 -> 0 | AA21: =U21+M21+E21 -> 0 | AB21: =V21+N21+F21 -> 250 | AC21: =IF(Z21>0,AA21/Z21,0) -> 0 | AD21: =ELEC!Q21 -> 0 | AE21: =SUM(AD21/Z21) -> #DIV/0! | AF21: =SUM(AE21/1600) -> #DIV/0! | AG21: =SUM(320*AF21) -> #DIV/0! | AH21: =SUM(AC21-AG21) -> #DIV/0! | AI21: =AD21*AJ21 -> 0 | AJ21: =305/1185 -> 0.25738397 | AK21: =IF(Z21>0,AI21/Z21,0) -> 0
A22: =ELEC!C22 -> 44306 | B22: =B21 -> 9826 | C22: =B22-B21 -> 0 | D22: =D21 -> 375483 | E22: =150*C22 -> 0 | F22: =IF(C22>0,E22/C22,0) -> 0 | H22: =H21 -> 9934 | I22: =IF(B22-H22<=0,"ok","oil change") -> ok | J22: =J21 -> 10698 | K22: =J22-J21 -> 0 | L22: =L21 -> 357691 | M22: =SUM(L22-L21) -> 0 | N22: =IF(K22>0,M22/K22,0) -> 0 | P22: =P21 -> 10873 | Q22: =IF(J22-P22<=0,"ok","oil change") -> ok | R22: =R21 -> 12135 | S22: =R22-R21 -> 0 | T22: =436413+U22 -> 436413 | U22: =V22*S22 -> 0 | V22: 250 | X22: =X21 -> 12192 | Y22: =IF(R22-X22<=0,"ok","oil change") -> ok | Z22: =C22+K22+S22 -> 0 | AA22: =U22+M22+E22 -> 0 | AB22: =V22+N22+F22 -> 250 | AC22: =IF(Z22>0,AA22/Z22,0) -> 0 | AD22: =ELEC!Q22 -> 0 | AE22: =SUM(AD22/Z22) -> #DIV/0! | AF22: =SUM(AE22/1600) -> #DIV/0! | AG22: =SUM(320*AF22) -> #DIV/0! | AH22: =SUM(AC22-AG22) -> #DIV/0! | AI22: =AD22*AJ22 -> 0 | AJ22: =305/1185 -> 0.25738397 | AK22: =IF(Z22>0,AI22/Z22,0) -> 0
A23: =ELEC!C23 -> 44307 | B23: =B22 -> 9826 | C23: =B23-B22 -> 0 | D23: =D22 -> 375483 | E23: =150*C23 -> 0 | F23: =IF(C23>0,E23/C23,0) -> 0 | H23: =H22 -> 9934 | I23: =IF(B23-H23<=0,"ok","oil change") -> ok | J23: =J22 -> 10698 | K23: =J23-J22 -> 0 | L23: =L22 -> 357691 | M23: =SUM(L23-L22) -> 0 | N23: =IF(K23>0,M23/K23,0) -> 0 | P23: =P22 -> 10873 | Q23: =IF(J23-P23<=0,"ok","oil change") -> ok | R23: =R22 -> 12135 | S23: =R23-R22 -> 0 | T23: =436413+U23 -> 436413 | U23: =V23*S23 -> 0 | V23: 250 | X23: =X22 -> 12192 | Y23: =IF(R23-X23<=0,"ok","oil change") -> ok | Z23: =C23+K23+S23 -> 0 | AA23: =U23+M23+E23 -> 0 | AB23: =V23+N23+F23 -> 250 | AC23: =IF(Z23>0,AA23/Z23,0) -> 0 | AD23: =ELEC!Q23 -> 0 | AE23: =SUM(AD23/Z23) -> #DIV/0! | AF23: =SUM(AE23/1600) -> #DIV/0! | AG23: =SUM(320*AF23) -> #DIV/0! | AH23: =SUM(AC23-AG23) -> #DIV/0! | AI23: =AD23*AJ23 -> 0 | AJ23: =305/1185 -> 0.25738397 | AK23: =IF(Z23>0,AI23/Z23,0) -> 0
