Workbook

Sheet Total
A1: Site Name | B1: Day | C1: Month | D1: Year | E1: Total Electricity Kwh | F1: Electricity Tariff ($/Kwh) | G1: LPG (Kg) | H1: LPG $/Kg | I1: Water Utility Supply (m3) m3 | J1: Water Utility Supply (m3) $/m3 | K1: Room Nights | L1: Utilities day cost dh
A2: Serengeti | B2: 1 | C2: 4 | D2: 2021 | E2: ='UTILITY REPORT 1'!F3 -> 3175 | F2: =('UTILITY REPORT 1'!E3*'UTILITY REPORT 1'!D3)/'UTILITY REPORT 1'!F3 -> 0.41777953 | G2: =IF('Utility summery'!M6<0,"0",'Utility summery'!M6) -> 84.48 | H2: 0 | I2: =IF('UTILITY REPORT 1'!G3<0,"0",'UTILITY REPORT 1'!G3) -> 89 | J2: 0 | K2: ='UTILITY REPORT 1'!C3 -> 1.3 | L2: =E2*F2+G2*H2+#REF!*#REF!+I2*J2 -> #REF!
A3: Serengeti | B3: =B2+1 -> 2 | C3: 4 | D3: 2021 | E3: ='UTILITY REPORT 1'!F4 -> 3187 | F3: =('UTILITY REPORT 1'!E4*'UTILITY REPORT 1'!D4)/'UTILITY REPORT 1'!F4 -> 0.41067775 | G3: =IF('Utility summery'!M7<0,"0",'Utility summery'!M7) -> 86.548 | H3: 0 | I3: =IF('UTILITY REPORT 1'!G4<0,"0",'UTILITY REPORT 1'!G4) -> 117 | J3: 0 | K3: ='UTILITY REPORT 1'!C4 -> 2.6 | L3: =E3*F3+G3*H3+#REF!*#REF!+I3*J3 -> #REF!
A4: Serengeti | B4: =B3+1 -> 3 | C4: 4 | D4: 2021 | E4: ='UTILITY REPORT 1'!F5 -> 3546 | F4: =('UTILITY REPORT 1'!E5*'UTILITY REPORT 1'!D5)/'UTILITY REPORT 1'!F5 -> 0.4022758 | G4: =IF('Utility summery'!M8<0,"0",'Utility summery'!M8) -> 88.968 | H4: 0 | I4: =IF('UTILITY REPORT 1'!G5<0,"0",'UTILITY REPORT 1'!G5) -> 167 | J4: 0 | K4: ='UTILITY REPORT 1'!C5 -> 2.6 | L4: =E4*F4+G4*H4+#REF!*#REF!+I4*J4 -> #REF!
A5: Serengeti | B5: =B4+1 -> 4 | C5: 4 | D5: 2021 | E5: ='UTILITY REPORT 1'!F6 -> 3328 | F5: =('UTILITY REPORT 1'!E6*'UTILITY REPORT 1'!D6)/'UTILITY REPORT 1'!F6 -> 0.40958834 | G5: =IF('Utility summery'!M9<0,"0",'Utility summery'!M9) -> 86.372 | H5: 0 | I5: =IF('UTILITY REPORT 1'!G6<0,"0",'UTILITY REPORT 1'!G6) -> 70 | J5: 0 | K5: ='UTILITY REPORT 1'!C6 -> 5.19 | L5: =E5*F5+G5*H5+#REF!*#REF!+I5*J5 -> #REF!
A6: Serengeti | B6: =B5+1 -> 5 | C6: 4 | D6: 2021 | E6: ='UTILITY REPORT 1'!F7 -> 3250 | F6: =('UTILITY REPORT 1'!E7*'UTILITY REPORT 1'!D7)/'UTILITY REPORT 1'!F7 -> 0.40968615 | G6: =IF('Utility summery'!M10<0,"0",'Utility summery'!M10) -> 88.528 | H6: 0 | I6: =IF('UTILITY REPORT 1'!G7<0,"0",'UTILITY REPORT 1'!G7) -> 59 | J6: 0 | K6: ='UTILITY REPORT 1'!C7 -> 7.79 | L6: =E6*F6+G6*H6+#REF!*#REF!+I6*J6 -> #REF!
A7: Serengeti | B7: =B6+1 -> 6 | C7: 4 | D7: 2021 | E7: ='UTILITY REPORT 1'!F8 -> 3070 | F7: =('UTILITY REPORT 1'!E8*'UTILITY REPORT 1'!D8)/'UTILITY REPORT 1'!F8 -> 0.41273616 | G7: =IF('Utility summery'!M11<0,"0",'Utility summery'!M11) -> 82.896 | H7: 0 | I7: =IF('UTILITY REPORT 1'!G8<0,"0",'UTILITY REPORT 1'!G8) -> 210 | J7: 0 | K7: ='UTILITY REPORT 1'!C8 -> 5.19 | L7: =E7*F7+G7*H7+#REF!*#REF!+I7*J7 -> #REF!
A8: Serengeti | B8: =B7+1 -> 7 | C8: 4 | D8: 2021 | E8: ='UTILITY REPORT 1'!F9 -> 3363 | F8: =('UTILITY REPORT 1'!E9*'UTILITY REPORT 1'!D9)/'UTILITY REPORT 1'!F9 -> 0.40155219 | G8: =IF('Utility summery'!M12<0,"0",'Utility summery'!M12) -> 80.212 | H8: 0 | I8: =IF('UTILITY REPORT 1'!G9<0,"0",'UTILITY REPORT 1'!G9) -> 60 | J8: 0 | K8: ='UTILITY REPORT 1'!C9 -> 11.69 | L8: =E8*F8+G8*H8+#REF!*#REF!+I8*J8 -> #REF!
A9: Serengeti | B9: =B8+1 -> 8 | C9: 4 | D9: 2021 | E9: ='UTILITY REPORT 1'!F10 -> 3146 | F9: =('UTILITY REPORT 1'!E10*'UTILITY REPORT 1'!D10)/'UTILITY REPORT 1'!F10 -> 0.40188175 | G9: =IF('Utility summery'!M13<0,"0",'Utility summery'!M13) -> 83.996 | H9: 0 | I9: =IF('UTILITY REPORT 1'!G10<0,"0",'UTILITY REPORT 1'!G10) -> 75 | J9: 0 | K9: ='UTILITY REPORT 1'!C10 -> 12.99 | L9: =E9*F9+G9*H9+#REF!*#REF!+I9*J9 -> #REF!
A10: Serengeti | B10: =B9+1 -> 9 | C10: 4 | D10: 2021 | E10: ='UTILITY REPORT 1'!F11 -> 3314 | F10: =('UTILITY REPORT 1'!E11*'UTILITY REPORT 1'!D11)/'UTILITY REPORT 1'!F11 -> 0.3941732 | G10: =IF('Utility summery'!M14<0,"0",'Utility summery'!M14) -> 44 | H10: 0 | I10: =IF('UTILITY REPORT 1'!G11<0,"0",'UTILITY REPORT 1'!G11) -> 47 | J10: 0 | K10: ='UTILITY REPORT 1'!C11 -> 15.58 | L10: =E10*F10+G10*H10+#REF!*#REF!+I10*J10 -> #REF!
A11: Serengeti | B11: =B10+1 -> 10 | C11: 4 | D11: 2021 | E11: ='UTILITY REPORT 1'!F12 -> 3168 | F11: =('UTILITY REPORT 1'!E12*'UTILITY REPORT 1'!D12)/'UTILITY REPORT 1'!F12 -> 0.39324811 | G11: =IF('Utility summery'!M15<0,"0",'Utility summery'!M15) -> 88 | H11: 0 | I11: =IF('UTILITY REPORT 1'!G12<0,"0",'UTILITY REPORT 1'!G12) -> 46 | J11: 0 | K11: ='UTILITY REPORT 1'!C12 -> 15.58 | L11: =E11*F11+G11*H11+#REF!*#REF!+I11*J11 -> #REF!
A12: Serengeti | B12: =B11+1 -> 11 | C12: 4 | D12: 2021 | E12: ='UTILITY REPORT 1'!F13 -> 3237 | F12: =('UTILITY REPORT 1'!E13*'UTILITY REPORT 1'!D13)/'UTILITY REPORT 1'!F13 -> 0.3966574 | G12: =IF('Utility summery'!M16<0,"0",'Utility summery'!M16) -> 57.244 | H12: 0 | I12: =IF('UTILITY REPORT 1'!G13<0,"0",'UTILITY REPORT 1'!G13) -> 50 | J12: 0 | K12: ='UTILITY REPORT 1'!C13 -> 11.69 | L12: =E12*F12+G12*H12+#REF!*#REF!+I12*J12 -> #REF!
A13: Serengeti | B13: =B12+1 -> 12 | C13: 4 | D13: 2021 | E13: ='UTILITY REPORT 1'!F14 -> 3269 | F13: =('UTILITY REPORT 1'!E14*'UTILITY REPORT 1'!D14)/'UTILITY REPORT 1'!F14 -> 0.35691343 | G13: =IF('Utility summery'!M17<0,"0",'Utility summery'!M17) -> 64.328 | H13: 0 | I13: =IF('UTILITY REPORT 1'!G14<0,"0",'UTILITY REPORT 1'!G14) -> 61 | J13: 0 | K13: ='UTILITY REPORT 1'!C14 -> 12.99 | L13: =E13*F13+G13*H13+#REF!*#REF!+I13*J13 -> #REF!
A14: Serengeti | B14: =B13+1 -> 13 | C14: 4 | D14: 2021 | E14: ='UTILITY REPORT 1'!F15 -> 2665 | F14: =('UTILITY REPORT 1'!E15*'UTILITY REPORT 1'!D15)/'UTILITY REPORT 1'!F15 -> 0.40665666 | G14: =IF('Utility summery'!M18<0,"0",'Utility summery'!M18) -> 63.228 | H14: 0 | I14: =IF('UTILITY REPORT 1'!G15<0,"0",'UTILITY REPORT 1'!G15) -> 181 | J14: 0 | K14: ='UTILITY REPORT 1'!C15 -> 14.29 | L14: =E14*F14+G14*H14+#REF!*#REF!+I14*J14 -> #REF!
... A30: Serengeti | B30: =B29+1 -> 29 | C30: 4 | D30: 2021 | E30: ='UTILITY REPORT 1'!F31 -> 2813 | F30: =('UTILITY REPORT 1'!E31*'UTILITY REPORT 1'!D31)/'UTILITY REPORT 1'!F31 -> 0.39306079 | G30: =IF('Utility summery'!M34<0,"0",'Utility summery'!M34) -> 62.348 | H30: 0 | I30: =IF('UTILITY REPORT 1'!G31<0,"0",'UTILITY REPORT 1'!G31) -> 53 | J30: 0 | K30: ='UTILITY REPORT 1'!C31 -> 0 | L30: =E30*F30+G30*H30+#REF!*#REF!+I30*J30 -> #REF!
A31: Serengeti | B31: 30 | C31: 4 | D31: 2021 | E31: ='UTILITY REPORT 1'!F32 -> 2731 | F31: =('UTILITY REPORT 1'!E32*'UTILITY REPORT 1'!D32)/'UTILITY REPORT 1'!F32 -> 0.40999268 | G31: =IF('Utility summery'!M35<0,"0",'Utility summery'!M35) -> 62.656 | H31: 0 | I31: =IF('UTILITY REPORT 1'!G32<0,"0",'UTILITY REPORT 1'!G32) -> 58 | J31: 0 | K31: ='UTILITY REPORT 1'!C32 -> 0 | L31: =E31*F31+G31*H31+#REF!*#REF!+I31*J31 -> #REF!
A32: Serengeti | B32: 31 | C32: 4 | D32: 2021 | E32: ='UTILITY REPORT 1'!F33 -> 0 | F32: =('UTILITY REPORT 1'!E33*'UTILITY REPORT 1'!D33)/'UTILITY REPORT 1'!F33 -> #DIV/0! | G32: =IF('Utility summery'!M36<0,"0",'Utility summery'!M36) -> 57.024 | H32: 0 | I32: =IF('UTILITY REPORT 1'!G33<0,"0",'UTILITY REPORT 1'!G33) -> 0 | J32: 0 | K32: ='UTILITY REPORT 1'!C33 -> 0

Sheet Submetering
A1: Site Name | B1: Day | C1: Month | D1: Year | E1: Transport Consumption (LT) | F1: Generators Consumption (LT) | G1: Total Electricity Kwh | H1: Kitchen (KWh) | I1: Laundry (KWh) | J1: STP (M3) | K1: RO prodution (M3) | L1: Amani Restaurant (M3) | M1: Kitchen (M3) | N1: Laundry (M3) | O1: Laundry (M3) | P1: Total water Consumption (M3) | Q1: Borehole #1 (M3) | R1: Borehole #2 (M3) | S1: Borehole #3 (M3) | T1: Borehole #4 (M3) | U1: Borehole #5 (M3) | V1: Borehole #6 (M3) | W1: Total Bore holes production (M3) | X1: Room Nights
A2: Serengeti | B2: 1 | C2: 4 | D2: 2021 | E2: ='UTILITY REPORT 1'!I3 -> 145.43 | F2: ='UTILITY REPORT 1'!E3 -> 1326.45 | G2: ='UTILITY REPORT 1'!F3 -> 3175 | H2: =IF('Kit report'!F4<0,"0",'Kit report'!F4) -> 240 | I2: =IF('Kit report'!X4<0,"0",'Kit report'!X4) -> 400 | J2: =IF('Utility summery'!H6<0,"0",'Utility summery'!H6) -> 72 | K2: =IF('UTILITY REPORT 1'!H3<0,"0",'UTILITY REPORT 1'!H3) -> 0 | L2: ='Water-Meter'!K6 -> 2 | M2: ='Water-Meter'!H6 -> 0 | N2: ='Water-Meter'!Q6 -> 7 | O2: =K2*E2+H2*I2+#REF!*#REF!+J2*L2 -> #REF! | P2: ='Water-Meter'!E6 -> 89 | Q2: =IF('Water-Meter'!U6<0,"0",'Water-Meter'!U6) -> 81 | R2: =IF('Water-Meter'!X6<0,"0",'Water-Meter'!X6) -> 0 | S2: =IF('Water-Meter'!AA6<0,"0",'Water-Meter'!AA6) -> 0 | T2: =IF('Water-Meter'!AD6<0,"0",'Water-Meter'!AD6) -> 15 | U2: =IF('Water-Meter'!AG6<0,"0",'Water-Meter'!AG6) -> 0 | V2: =IF('Water-Meter'!AJ6<0,"0",'Water-Meter'!AJ6) -> 26 | W2: ='Water-Meter'!AN6 -> 122 | X2: =Total!K2 -> 1.3
A3: Serengeti | B3: =B2+1 -> 2 | C3: 4 | D3: 2021 | E3: ='UTILITY REPORT 1'!I4 -> 224.9 | F3: ='UTILITY REPORT 1'!E4 -> 1308.83 | G3: ='UTILITY REPORT 1'!F4 -> 3187 | H3: =IF('Kit report'!F5<0,"0",'Kit report'!F5) -> 360 | I3: =IF('Kit report'!X5<0,"0",'Kit report'!X5) -> 600 | J3: =IF('Utility summery'!H7<0,"0",'Utility summery'!H7) -> 81 | K3: =IF('UTILITY REPORT 1'!H4<0,"0",'UTILITY REPORT 1'!H4) -> 0 | L3: ='Water-Meter'!K7 -> 2 | M3: ='Water-Meter'!H7 -> 0 | N3: ='Water-Meter'!Q7 -> 4 | O3: =K3*E3+H3*I3+#REF!*#REF!+J3*L3 -> #REF! | P3: ='Water-Meter'!E7 -> 117 | Q3: =IF('Water-Meter'!U7<0,"0",'Water-Meter'!U7) -> 80 | R3: =IF('Water-Meter'!X7<0,"0",'Water-Meter'!X7) -> 0 | S3: =IF('Water-Meter'!AA7<0,"0",'Water-Meter'!AA7) -> 0 | T3: =IF('Water-Meter'!AD7<0,"0",'Water-Meter'!AD7) -> 17 | U3: =IF('Water-Meter'!AG7<0,"0",'Water-Meter'!AG7) -> 0 | V3: =IF('Water-Meter'!AJ7<0,"0",'Water-Meter'!AJ7) -> 30 | W3: ='Water-Meter'!AN7 -> 127 | X3: =Total!K3 -> 2.6
A4: Serengeti | B4: =B3+1 -> 3 | C4: 4 | D4: 2021 | E4: ='UTILITY REPORT 1'!I5 -> 139.29 | F4: ='UTILITY REPORT 1'!E5 -> 1426.47 | G4: ='UTILITY REPORT 1'!F5 -> 3546 | H4: =IF('Kit report'!F6<0,"0",'Kit report'!F6) -> 324 | I4: =IF('Kit report'!X6<0,"0",'Kit report'!X6) -> 400 | J4: =IF('Utility summery'!H8<0,"0",'Utility summery'!H8) -> 74 | K4: =IF('UTILITY REPORT 1'!H5<0,"0",'UTILITY REPORT 1'!H5) -> 0 | L4: ='Water-Meter'!K8 -> 2 | M4: ='Water-Meter'!H8 -> 0 | N4: ='Water-Meter'!Q8 -> 5 | O4: =K4*E4+H4*I4+#REF!*#REF!+J4*L4 -> #REF! | P4: ='Water-Meter'!E8 -> 167 | Q4: =IF('Water-Meter'!U8<0,"0",'Water-Meter'!U8) -> 88 | R4: =IF('Water-Meter'!X8<0,"0",'Water-Meter'!X8) -> 0 | S4: =IF('Water-Meter'!AA8<0,"0",'Water-Meter'!AA8) -> 52 | T4: =IF('Water-Meter'!AD8<0,"0",'Water-Meter'!AD8) -> 15 | U4: =IF('Water-Meter'!AG8<0,"0",'Water-Meter'!AG8) -> 0 | V4: =IF('Water-Meter'!AJ8<0,"0",'Water-Meter'!AJ8) -> 17 | W4: ='Water-Meter'!AN8 -> 172 | X4: =Total!K4 -> 2.6
A5: Serengeti | B5: =B4+1 -> 4 | C5: 4 | D5: 2021 | E5: ='UTILITY REPORT 1'!I6 -> 0 | F5: ='UTILITY REPORT 1'!E6 -> 1363.11 | G5: ='UTILITY REPORT 1'!F6 -> 3328 | H5: =IF('Kit report'!F7<0,"0",'Kit report'!F7) -> 300 | I5: =IF('Kit report'!X7<0,"0",'Kit report'!X7) -> 360 | J5: =IF('Utility summery'!H9<0,"0",'Utility summery'!H9) -> 77 | K5: =IF('UTILITY REPORT 1'!H6<0,"0",'UTILITY REPORT 1'!H6) -> 0 | L5: ='Water-Meter'!K9 -> 1 | M5: ='Water-Meter'!H9 -> 0 | N5: ='Water-Meter'!Q9 -> 4 | O5: =K5*E5+H5*I5+#REF!*#REF!+J5*L5 -> #REF! | P5: ='Water-Meter'!E9 -> 70 | Q5: =IF('Water-Meter'!U9<0,"0",'Water-Meter'!U9) -> 83 | R5: =IF('Water-Meter'!X9<0,"0",'Water-Meter'!X9) -> 0 | S5: =IF('Water-Meter'!AA9<0,"0",'Water-Meter'!AA9) -> 48 | T5: =IF('Water-Meter'!AD9<0,"0",'Water-Meter'!AD9) -> 17 | U5: =IF('Water-Meter'!AG9<0,"0",'Water-Meter'!AG9) -> 0 | V5: =IF('Water-Meter'!AJ9<0,"0",'Water-Meter'!AJ9) -> 38 | W5: ='Water-Meter'!AN9 -> 186 | X5: =Total!K5 -> 5.19
A6: Serengeti | B6: =B5+1 -> 5 | C6: 4 | D6: 2021 | E6: ='UTILITY REPORT 1'!I7 -> 218.51 | F6: ='UTILITY REPORT 1'!E7 -> 1331.48 | G6: ='UTILITY REPORT 1'!F7 -> 3250 | H6: =IF('Kit report'!F8<0,"0",'Kit report'!F8) -> 300 | I6: =IF('Kit report'!X8<0,"0",'Kit report'!X8) -> 440 | J6: =IF('Utility summery'!H10<0,"0",'Utility summery'!H10) -> 72 | K6: =IF('UTILITY REPORT 1'!H7<0,"0",'UTILITY REPORT 1'!H7) -> 0 | L6: ='Water-Meter'!K10 -> 2 | M6: ='Water-Meter'!H10 -> 0 | N6: ='Water-Meter'!Q10 -> 4 | O6: =K6*E6+H6*I6+#REF!*#REF!+J6*L6 -> #REF! | P6: ='Water-Meter'!E10 -> 59 | Q6: =IF('Water-Meter'!U10<0,"0",'Water-Meter'!U10) -> 80 | R6: =IF('Water-Meter'!X10<0,"0",'Water-Meter'!X10) -> 0 | S6: =IF('Water-Meter'!AA10<0,"0",'Water-Meter'!AA10) -> 45 | T6: =IF('Water-Meter'!AD10<0,"0",'Water-Meter'!AD10) -> 15 | U6: =IF('Water-Meter'!AG10<0,"0",'Water-Meter'!AG10) -> 0 | V6: =IF('Water-Meter'!AJ10<0,"0",'Water-Meter'!AJ10) -> 26 | W6: ='Water-Meter'!AN10 -> 166 | X6: =Total!K6 -> 7.79
A7: Serengeti | B7: =B6+1 -> 6 | C7: 4 | D7: 2021 | E7: ='UTILITY REPORT 1'!I8 -> 42.44 | F7: ='UTILITY REPORT 1'!E8 -> 1267.1 | G7: ='UTILITY REPORT 1'!F8 -> 3070 | H7: =IF('Kit report'!F9<0,"0",'Kit report'!F9) -> 312 | I7: =IF('Kit report'!X9<0,"0",'Kit report'!X9) -> 500 | J7: =IF('Utility summery'!H11<0,"0",'Utility summery'!H11) -> 82 | K7: =IF('UTILITY REPORT 1'!H8<0,"0",'UTILITY REPORT 1'!H8) -> 0 | L7: ='Water-Meter'!K11 -> 1 | M7: ='Water-Meter'!H11 -> 0 | N7: ='Water-Meter'!Q11 -> 8 | O7: =K7*E7+H7*I7+#REF!*#REF!+J7*L7 -> #REF! | P7: ='Water-Meter'!E11 -> 210 | Q7: =IF('Water-Meter'!U11<0,"0",'Water-Meter'!U11) -> 82 | R7: =IF('Water-Meter'!X11<0,"0",'Water-Meter'!X11) -> 0 | S7: =IF('Water-Meter'!AA11<0,"0",'Water-Meter'!AA11) -> 50 | T7: =IF('Water-Meter'!AD11<0,"0",'Water-Meter'!AD11) -> 18 | U7: =IF('Water-Meter'!AG11<0,"0",'Water-Meter'!AG11) -> 0 | V7: =IF('Water-Meter'!AJ11<0,"0",'Water-Meter'!AJ11) -> 28 | W7: ='Water-Meter'!AN11 -> 178 | X7: =Total!K7 -> 5.19
A8: Serengeti | B8: =B7+1 -> 7 | C8: 4 | D8: 2021 | E8: ='UTILITY REPORT 1'!I9 -> 119.14 | F8: ='UTILITY REPORT 1'!E9 -> 1350.42 | G8: ='UTILITY REPORT 1'!F9 -> 3363 | H8: =IF('Kit report'!F10<0,"0",'Kit report'!F10) -> 288 | I8: =IF('Kit report'!X10<0,"0",'Kit report'!X10) -> 380 | J8: =IF('Utility summery'!H12<0,"0",'Utility summery'!H12) -> 76 | K8: =IF('UTILITY REPORT 1'!H9<0,"0",'UTILITY REPORT 1'!H9) -> 101 | L8: ='Water-Meter'!K12 -> 2 | M8: ='Water-Meter'!H12 -> 0 | N8: ='Water-Meter'!Q12 -> 3 | O8: =K8*E8+H8*I8+#REF!*#REF!+J8*L8 -> #REF! | P8: ='Water-Meter'!E12 -> 60 | Q8: =IF('Water-Meter'!U12<0,"0",'Water-Meter'!U12) -> 81 | R8: =IF('Water-Meter'!X12<0,"0",'Water-Meter'!X12) -> 0 | S8: =IF('Water-Meter'!AA12<0,"0",'Water-Meter'!AA12) -> 47 | T8: =IF('Water-Meter'!AD12<0,"0",'Water-Meter'!AD12) -> 16 | U8: =IF('Water-Meter'!AG12<0,"0",'Water-Meter'!AG12) -> 0 | V8: =IF('Water-Meter'!AJ12<0,"0",'Water-Meter'!AJ12) -> 28 | W8: ='Water-Meter'!AN12 -> 172 | X8: =Total!K8 -> 11.69
A9: Serengeti | B9: =B8+1 -> 8 | C9: 4 | D9: 2021 | E9: ='UTILITY REPORT 1'!I10 -> 156.32 | F9: ='UTILITY REPORT 1'!E10 -> 1264.32 | G9: ='UTILITY REPORT 1'!F10 -> 3146 | H9: =IF('Kit report'!F11<0,"0",'Kit report'!F11) -> 276 | I9: =IF('Kit report'!X11<0,"0",'Kit report'!X11) -> 360 | J9: =IF('Utility summery'!H13<0,"0",'Utility summery'!H13) -> 82 | K9: =IF('UTILITY REPORT 1'!H10<0,"0",'UTILITY REPORT 1'!H10) -> 12 | L9: ='Water-Meter'!K13 -> 2 | M9: ='Water-Meter'!H13 -> 0 | N9: ='Water-Meter'!Q13 -> 6 | O9: =K9*E9+H9*I9+#REF!*#REF!+J9*L9 -> #REF! | P9: ='Water-Meter'!E13 -> 75 | Q9: =IF('Water-Meter'!U13<0,"0",'Water-Meter'!U13) -> 82 | R9: =IF('Water-Meter'!X13<0,"0",'Water-Meter'!X13) -> 0 | S9: =IF('Water-Meter'!AA13<0,"0",'Water-Meter'!AA13) -> 48 | T9: =IF('Water-Meter'!AD13<0,"0",'Water-Meter'!AD13) -> 16 | U9: =IF('Water-Meter'!AG13<0,"0",'Water-Meter'!AG13) -> 0 | V9: =IF('Water-Meter'!AJ13<0,"0",'Water-Meter'!AJ13) -> 27 | W9: ='Water-Meter'!AN13 -> 173 | X9: =Total!K9 -> 12.99
A10: Serengeti | B10: =B9+1 -> 9 | C10: 4 | D10: 2021 | E10: ='UTILITY REPORT 1'!I11 -> 302.11 | F10: ='UTILITY REPORT 1'!E11 -> 1306.29 | G10: ='UTILITY REPORT 1'!F11 -> 3314 | H10: =IF('Kit report'!F12<0,"0",'Kit report'!F12) -> 240 | I10: =IF('Kit report'!X12<0,"0",'Kit report'!X12) -> 420 | J10: =IF('Utility summery'!H14<0,"0",'Utility summery'!H14) -> 78 | K10: =IF('UTILITY REPORT 1'!H11<0,"0",'UTILITY REPORT 1'!H11) -> 0 | L10: ='Water-Meter'!K14 -> 1 | M10: ='Water-Meter'!H14 -> 0 | N10: ='Water-Meter'!Q14 -> 4 | O10: =K10*E10+H10*I10+#REF!*#REF!+J10*L10 -> #REF! | P10: ='Water-Meter'!E14 -> 47 | Q10: =IF('Water-Meter'!U14<0,"0",'Water-Meter'!U14) -> 81 | R10: =IF('Water-Meter'!X14<0,"0",'Water-Meter'!X14) -> 0 | S10: =IF('Water-Meter'!AA14<0,"0",'Water-Meter'!AA14) -> 1 | T10: =IF('Water-Meter'!AD14<0,"0",'Water-Meter'!AD14) -> 16 | U10: =IF('Water-Meter'!AG14<0,"0",'Water-Meter'!AG14) -> 0 | V10: =IF('Water-Meter'!AJ14<0,"0",'Water-Meter'!AJ14) -> 28 | W10: ='Water-Meter'!AN14 -> 126 | X10: =Total!K10 -> 15.58
A11: Serengeti | B11: =B10+1 -> 10 | C11: 4 | D11: 2021 | E11: ='UTILITY REPORT 1'!I12 -> 112 | F11: ='UTILITY REPORT 1'!E12 -> 1245.81 | G11: ='UTILITY REPORT 1'!F12 -> 3168 | H11: =IF('Kit report'!F13<0,"0",'Kit report'!F13) -> 216 | I11: =IF('Kit report'!X13<0,"0",'Kit report'!X13) -> 260 | J11: =IF('Utility summery'!H15<0,"0",'Utility summery'!H15) -> 77 | K11: =IF('UTILITY REPORT 1'!H12<0,"0",'UTILITY REPORT 1'!H12) -> 0 | L11: ='Water-Meter'!K15 -> 2 | M11: ='Water-Meter'!H15 -> 0 | N11: ='Water-Meter'!Q15 -> 3 | O11: =K11*E11+H11*I11+#REF!*#REF!+J11*L11 -> #REF! | P11: ='Water-Meter'!E15 -> 46 | Q11: =IF('Water-Meter'!U15<0,"0",'Water-Meter'!U15) -> 0 | R11: =IF('Water-Meter'!X15<0,"0",'Water-Meter'!X15) -> 0 | S11: =IF('Water-Meter'!AA15<0,"0",'Water-Meter'!AA15) -> 0 | T11: =IF('Water-Meter'!AD15<0,"0",'Water-Meter'!AD15) -> 17 | U11: =IF('Water-Meter'!AG15<0,"0",'Water-Meter'!AG15) -> 0 | V11: =IF('Water-Meter'!AJ15<0,"0",'Water-Meter'!AJ15) -> 27 | W11: ='Water-Meter'!AN15 -> 44 | X11: =Total!K11 -> 15.58
A12: Serengeti | B12: =B11+1 -> 11 | C12: 4 | D12: 2021 | E12: ='UTILITY REPORT 1'!I13 -> 25 | F12: ='UTILITY REPORT 1'!E13 -> 1283.98 | G12: ='UTILITY REPORT 1'!F13 -> 3237 | H12: =IF('Kit report'!F14<0,"0",'Kit report'!F14) -> 216 | I12: =IF('Kit report'!X14<0,"0",'Kit report'!X14) -> 280 | J12: =IF('Utility summery'!H16<0,"0",'Utility summery'!H16) -> 50 | K12: =IF('UTILITY REPORT 1'!H13<0,"0",'UTILITY REPORT 1'!H13) -> 0 | L12: ='Water-Meter'!K16 -> 2 | M12: ='Water-Meter'!H16 -> 0 | N12: ='Water-Meter'!Q16 -> 3 | O12: =K12*E12+H12*I12+#REF!*#REF!+J12*L12 -> #REF! | P12: ='Water-Meter'!E16 -> 50 | Q12: =IF('Water-Meter'!U16<0,"0",'Water-Meter'!U16) -> 0 | R12: =IF('Water-Meter'!X16<0,"0",'Water-Meter'!X16) -> 0 | S12: =IF('Water-Meter'!AA16<0,"0",'Water-Meter'!AA16) -> 0 | T12: =IF('Water-Meter'!AD16<0,"0",'Water-Meter'!AD16) -> 17 | U12: =IF('Water-Meter'!AG16<0,"0",'Water-Meter'!AG16) -> 0 | V12: =IF('Water-Meter'!AJ16<0,"0",'Water-Meter'!AJ16) -> 26 | W12: ='Water-Meter'!AN16 -> 43 | X12: =Total!K12 -> 11.69
A13: Serengeti | B13: =B12+1 -> 12 | C13: 4 | D13: 2021 | E13: ='UTILITY REPORT 1'!I14 -> 250.64 | F13: ='UTILITY REPORT 1'!E14 -> 1166.75 | G13: ='UTILITY REPORT 1'!F14 -> 3269 | H13: =IF('Kit report'!F15<0,"0",'Kit report'!F15) -> 240 | I13: =IF('Kit report'!X15<0,"0",'Kit report'!X15) -> 240 | J13: =IF('Utility summery'!H17<0,"0",'Utility summery'!H17) -> 46 | K13: =IF('UTILITY REPORT 1'!H14<0,"0",'UTILITY REPORT 1'!H14) -> 0 | L13: ='Water-Meter'!K17 -> 1 | M13: ='Water-Meter'!H17 -> 0 | N13: ='Water-Meter'!Q17 -> 6 | O13: =K13*E13+H13*I13+#REF!*#REF!+J13*L13 -> #REF! | P13: ='Water-Meter'!E17 -> 61 | Q13: =IF('Water-Meter'!U17<0,"0",'Water-Meter'!U17) -> 0 | R13: =IF('Water-Meter'!X17<0,"0",'Water-Meter'!X17) -> 0 | S13: =IF('Water-Meter'!AA17<0,"0",'Water-Meter'!AA17) -> 0 | T13: =IF('Water-Meter'!AD17<0,"0",'Water-Meter'!AD17) -> 16 | U13: =IF('Water-Meter'!AG17<0,"0",'Water-Meter'!AG17) -> 0 | V13: =IF('Water-Meter'!AJ17<0,"0",'Water-Meter'!AJ17) -> 33 | W13: ='Water-Meter'!AN17 -> 49 | X13: =Total!K13 -> 12.99
A14: Serengeti | B14: =B13+1 -> 13 | C14: 4 | D14: 2021 | E14: ='UTILITY REPORT 1'!I15 -> 22.54 | F14: ='UTILITY REPORT 1'!E15 -> 1083.74 | G14: ='UTILITY REPORT 1'!F15 -> 2665 | H14: =IF('Kit report'!F16<0,"0",'Kit report'!F16) -> 216 | I14: =IF('Kit report'!X16<0,"0",'Kit report'!X16) -> 300 | J14: =IF('Utility summery'!H18<0,"0",'Utility summery'!H18) -> 42 | K14: =IF('UTILITY REPORT 1'!H15<0,"0",'UTILITY REPORT 1'!H15) -> 0 | L14: ='Water-Meter'!K18 -> 1 | M14: ='Water-Meter'!H18 -> 0 | N14: ='Water-Meter'!Q18 -> 2 | O14: =K14*E14+H14*I14+#REF!*#REF!+J14*L14 -> #REF! | P14: ='Water-Meter'!E18 -> 181 | Q14: =IF('Water-Meter'!U18<0,"0",'Water-Meter'!U18) -> 0 | R14: =IF('Water-Meter'!X18<0,"0",'Water-Meter'!X18) -> 0 | S14: =IF('Water-Meter'!AA18<0,"0",'Water-Meter'!AA18) -> 0 | T14: =IF('Water-Meter'!AD18<0,"0",'Water-Meter'!AD18) -> 16 | U14: =IF('Water-Meter'!AG18<0,"0",'Water-Meter'!AG18) -> 0 | V14: =IF('Water-Meter'!AJ18<0,"0",'Water-Meter'!AJ18) -> 29 | W14: ='Water-Meter'!AN18 -> 45 | X14: =Total!K14 -> 14.29
... A30: Serengeti | B30: =B29+1 -> 29 | C30: 4 | D30: 2021 | E30: ='UTILITY REPORT 1'!I31 -> 243.48 | F30: ='UTILITY REPORT 1'!E31 -> 1105.68 | G30: ='UTILITY REPORT 1'!F31 -> 2813 | H30: =IF('Kit report'!F32<0,"0",'Kit report'!F32) -> 288 | I30: =IF('Kit report'!X32<0,"0",'Kit report'!X32) -> 340 | J30: =IF('Utility summery'!H34<0,"0",'Utility summery'!H34) -> 42 | K30: =IF('UTILITY REPORT 1'!H31<0,"0",'UTILITY REPORT 1'!H31) -> 30 | L30: ='Water-Meter'!K34 -> 1 | M30: ='Water-Meter'!H34 -> 0 | N30: ='Water-Meter'!Q34 -> 6 | O30: =K30*E30+H30*I30+#REF!*#REF!+J30*L30 -> #REF! | P30: ='Water-Meter'!E34 -> 53 | Q30: =IF('Water-Meter'!U34<0,"0",'Water-Meter'!U34) -> 0 | R30: =IF('Water-Meter'!X34<0,"0",'Water-Meter'!X34) -> 0 | S30: =IF('Water-Meter'!AA34<0,"0",'Water-Meter'!AA34) -> 0 | T30: =IF('Water-Meter'!AD34<0,"0",'Water-Meter'!AD34) -> 16 | U30: =IF('Water-Meter'!AG34<0,"0",'Water-Meter'!AG34) -> 0 | V30: =IF('Water-Meter'!AJ34<0,"0",'Water-Meter'!AJ34) -> 29 | W30: ='Water-Meter'!AN34 -> 45 | X30: =Total!K30 -> 0
A31: Serengeti | B31: 30 | C31: 4 | D31: 2021 | E31: ='UTILITY REPORT 1'!I32 -> 274.32 | F31: ='UTILITY REPORT 1'!E32 -> 1119.69 | G31: ='UTILITY REPORT 1'!F32 -> 2731 | H31: =IF('Kit report'!F33<0,"0",'Kit report'!F33) -> 276 | I31: =IF('Kit report'!X33<0,"0",'Kit report'!X33) -> 400 | J31: =IF('Utility summery'!H35<0,"0",'Utility summery'!H35) -> 44 | K31: =IF('UTILITY REPORT 1'!H32<0,"0",'UTILITY REPORT 1'!H32) -> 35 | L31: ='Water-Meter'!K35 -> 1 | M31: ='Water-Meter'!H35 -> 0 | N31: ='Water-Meter'!Q35 -> 3 | O31: =K31*E31+H31*I31+#REF!*#REF!+J31*L31 -> #REF! | P31: ='Water-Meter'!E35 -> 58 | Q31: =IF('Water-Meter'!U35<0,"0",'Water-Meter'!U35) -> 0 | R31: =IF('Water-Meter'!X35<0,"0",'Water-Meter'!X35) -> 0 | S31: =IF('Water-Meter'!AA35<0,"0",'Water-Meter'!AA35) -> 0 | T31: =IF('Water-Meter'!AD35<0,"0",'Water-Meter'!AD35) -> 17 | U31: =IF('Water-Meter'!AG35<0,"0",'Water-Meter'!AG35) -> 0 | V31: =IF('Water-Meter'!AJ35<0,"0",'Water-Meter'!AJ35) -> 30 | W31: ='Water-Meter'!AN35 -> 47 | X31: =Total!K31 -> 0
A32: Serengeti | B32: 31 | C32: 4 | D32: 2021 | E32: ='UTILITY REPORT 1'!I33 -> 0 | F32: ='UTILITY REPORT 1'!E33 -> 0 | G32: ='UTILITY REPORT 1'!F33 -> 0 | H32: =IF('Kit report'!F34<0,"0",'Kit report'!F34) -> 0 | I32: =IF('Kit report'!X34<0,"0",'Kit report'!X34) -> 0 | J32: =IF('Utility summery'!H36<0,"0",'Utility summery'!H36) -> 0 | K32: =IF('UTILITY REPORT 1'!H33<0,"0",'UTILITY REPORT 1'!H33) -> 0 | L32: ='Water-Meter'!K36 -> 0 | M32: ='Water-Meter'!H36 -> 0 | N32: ='Water-Meter'!Q36 -> 0 | P32: ='Water-Meter'!E36 -> 0 | Q32: =IF('Water-Meter'!U36<0,"0",'Water-Meter'!U36) -> 0 | R32: =IF('Water-Meter'!X36<0,"0",'Water-Meter'!X36) -> 0 | S32: =IF('Water-Meter'!AA36<0,"0",'Water-Meter'!AA36) -> 0 | T32: =IF('Water-Meter'!AD36<0,"0",'Water-Meter'!AD36) -> 0 | U32: =IF('Water-Meter'!AG36<0,"0",'Water-Meter'!AG36) -> 0 | V32: =IF('Water-Meter'!AJ36<0,"0",'Water-Meter'!AJ36) -> 0 | W32: ='Water-Meter'!AN36 -> 0 | X32: =Total!K32 -> 0

Sheet UTILITY REPORT 1
A1: UTILITY REPORT
A2: Date | B2: % | C2: Guest Rooms Occupied | D2: Diesel cost Per Liter ($) | E2: Diesel consumption (LT) | F2: Power production (KW) | G2: Water consumption (M3) | H2: RO prodution (M3) | I2: Transport Consupmtion (LT)
A3: =Gen!A11 -> 44287 | B3: =Gen!B11 -> 0.156 | C3: ='Summery Report'!E5 -> 1.3 | D3: 1 | E3: =Gen!S11 -> 1326.45 | F3: =Gen!T11 -> 3175 | G3: ='Water-Meter'!E6 -> 89 | H3: ='Utility report '!AC6 -> 0 | I3: =Gen!AJ11 -> 145.43
A4: =Gen!A12 -> 44288 | B4: =Gen!B12 -> 0.169 | C4: ='Summery Report'!E6 -> 2.6 | D4: 1 | E4: =Gen!S12 -> 1308.83 | F4: =Gen!T12 -> 3187 | G4: ='Water-Meter'!E7 -> 117 | H4: ='Utility report '!AC7 -> 0 | I4: =Gen!AJ12 -> 224.9
A5: =Gen!A13 -> 44289 | B5: =Gen!B13 -> 0.23 | C5: ='Summery Report'!E7 -> 2.6 | D5: 1 | E5: =Gen!S13 -> 1426.47 | F5: =Gen!T13 -> 3546 | G5: ='Water-Meter'!E8 -> 167 | H5: ='Utility report '!AC8 -> 0 | I5: =Gen!AJ13 -> 139.29
A6: =Gen!A14 -> 44290 | B6: =Gen!B14 -> 0.247 | C6: ='Summery Report'!E8 -> 5.19 | D6: 1 | E6: =Gen!S14 -> 1363.11 | F6: =Gen!T14 -> 3328 | G6: ='Water-Meter'!E9 -> 70 | H6: ='Utility report '!AC9 -> 0 | I6: =Gen!AJ14 -> 0
A7: =Gen!A15 -> 44291 | B7: =Gen!B15 -> 0.13 | C7: ='Summery Report'!E9 -> 7.79 | D7: 1 | E7: =Gen!S15 -> 1331.48 | F7: =Gen!T15 -> 3250 | G7: ='Water-Meter'!E10 -> 59 | H7: ='Utility report '!AC10 -> 0 | I7: =Gen!AJ15 -> 218.51
A8: =Gen!A16 -> 44292 | B8: =Gen!B16 -> 0.091 | C8: ='Summery Report'!E10 -> 5.19 | D8: 1 | E8: =Gen!S16 -> 1267.1 | F8: =Gen!T16 -> 3070 | G8: ='Water-Meter'!E11 -> 210 | H8: ='Utility report '!AC11 -> 0 | I8: =Gen!AJ16 -> 42.44
A9: =Gen!A17 -> 44293 | B9: =Gen!B17 -> 0.065 | C9: ='Summery Report'!E11 -> 11.69 | D9: 1 | E9: =Gen!S17 -> 1350.42 | F9: =Gen!T17 -> 3363 | G9: ='Water-Meter'!E12 -> 60 | H9: ='Utility report '!AC12 -> 101 | I9: =Gen!AJ17 -> 119.14
A10: =Gen!A18 -> 44294 | B10: =Gen!B18 -> 0.091 | C10: ='Summery Report'!E12 -> 12.99 | D10: 1 | E10: =Gen!S18 -> 1264.32 | F10: =Gen!T18 -> 3146 | G10: ='Water-Meter'!E13 -> 75 | H10: ='Utility report '!AC13 -> 12 | I10: =Gen!AJ18 -> 156.32
A11: =Gen!A19 -> 44295 | B11: =Gen!B19 -> 0.065 | C11: ='Summery Report'!E13 -> 15.58 | D11: 1 | E11: =Gen!S19 -> 1306.29 | F11: =Gen!T19 -> 3314 | G11: ='Water-Meter'!E14 -> 47 | H11: ='Utility report '!AC14 -> 0 | I11: =Gen!AJ19 -> 302.11
A12: =Gen!A20 -> 44296 | B12: =Gen!B20 -> 0.052 | C12: ='Summery Report'!E14 -> 15.58 | D12: 1 | E12: =Gen!S20 -> 1245.81 | F12: =Gen!T20 -> 3168 | G12: ='Water-Meter'!E15 -> 46 | H12: ='Utility report '!AC15 -> 0 | I12: =Gen!AJ20 -> 112
A13: =Gen!A21 -> 44297 | B13: =Gen!B21 -> 0.104 | C13: ='Summery Report'!E15 -> 11.69 | D13: 1 | E13: =Gen!S21 -> 1283.98 | F13: =Gen!T21 -> 3237 | G13: ='Water-Meter'!E16 -> 50 | H13: ='Utility report '!AC16 -> 0 | I13: =Gen!AJ21 -> 25
A14: =Gen!A22 -> 44298 | B14: =Gen!B22 -> 0.104 | C14: ='Summery Report'!E16 -> 12.99 | D14: 1 | E14: =Gen!S22 -> 1166.75 | F14: =Gen!T22 -> 3269 | G14: ='Water-Meter'!E17 -> 61 | H14: ='Utility report '!AC17 -> 0 | I14: =Gen!AJ22 -> 250.64
... A33: =Gen!A41 -> 0 | B33: =Gen!B41 -> 0 | C33: ='Summery Report'!E35 -> 0 | D33: 1 | E33: =Gen!S41 -> 0 | F33: =Gen!T41 -> 0 | G33: ='Water-Meter'!E36 -> 0 | H33: ='Utility report '!AC36 -> -977 | I33: =Gen!AJ41 -> 0
B34: =Gen!B42 -> 0 | C34: ='Summery Report'!E36 -> 0 | D34: 2 | E34: =Gen!S42 -> 0 | F34: =Gen!T42 -> 0 | G34: ='Water-Meter'!E37 -> 0 | H34: ='Utility report '!AC37 -> 0 | I34: =Gen!AK42 -> 0

Sheet Utility summery
A4: Date | B4: Room Occupied | C4: Electricity Units Generated KW | D4: Diseal | G4: Water | J4: Gas | N4: Cost of utilites
D5: Generator | E5: Transport | F5: Total | G5: RO | H5: STP | I5: Total Consumption | J5: 2 ton | K5: 1 Ton | L5: 1 Ton | M5: Total consumption | N5: Electricity /1.4$/liter | O5: Diseal for Transport | P5: Gas /2.38$/Kg | Q5: Total HLP Cost | R5: Electricity Cost/Room $ | S5: cost/Room $
A6: =Gen!A11 -> 44287 | B6: ='Summery Report'!E5 -> 1.3 | C6: =Gen!U11 -> 0.41777953 | D6: =Gen!T11 -> 3175 | E6: =Gen!AK11 -> 0 | F6: =Gen!AS11 -> 0 | G6: ='Utility report '!AC6 -> 0 | H6: ='Utility report '!AE6 -> 72 | I6: ='Water-Meter'!E6 -> 89 | J6: ='Lpg (2)'!B10 -> 0 | K6: ='Lpg (2)'!C10 -> 15 | L6: ='Lpg (2)'!D10 -> 85 | M6: ='Lpg (2)'!G10 -> 84.48 | O6: =E6 -> 0 | P6: ='[1]Lpg (2)'!#REF! -> #REF! | Q6: ='[1]Summery Report'!#REF! -> #REF! | R6: =N6/B6 -> 0 | S6: =Q6/B6 -> #REF!
A7: =Gen!A12 -> 44288 | B7: ='Summery Report'!E6 -> 2.6 | C7: =Gen!U12 -> 0.41067775 | D7: =Gen!T12 -> 3187 | E7: =Gen!AK12 -> 0 | F7: =Gen!AS12 -> 0 | G7: ='Utility report '!AC7 -> 0 | H7: ='Utility report '!AE7 -> 81 | I7: ='Water-Meter'!E7 -> 117 | J7: ='Lpg (2)'!B11 -> 0 | K7: ='Lpg (2)'!C11 -> 10 | L7: ='Lpg (2)'!D11 -> 85 | M7: ='Lpg (2)'!G11 -> 86.548 | N7: =D7*1.4 -> 4461.8 | O7: =E7*1.4 -> 0 | P7: ='[1]Lpg (2)'!#REF! -> #REF! | Q7: ='[1]Summery Report'!#REF! -> #REF! | R7: =N7/B7 -> 1716.0769 | S7: =Q7/B7 -> #REF!
A8: =Gen!A13 -> 44289 | B8: ='Summery Report'!E7 -> 2.6 | C8: =Gen!U13 -> 0.4022758 | D8: =Gen!T13 -> 3546 | E8: =Gen!AK13 -> 0 | F8: =Gen!AS13 -> 0 | G8: ='Utility report '!AC8 -> 0 | H8: ='Utility report '!AE8 -> 74 | I8: ='Water-Meter'!E8 -> 167 | J8: ='Lpg (2)'!B12 -> 0 | K8: ='Lpg (2)'!C12 -> 3 | L8: ='Lpg (2)'!D12 -> 85 | M8: ='Lpg (2)'!G12 -> 88.968 | N8: =D8*1.4 -> 4964.4 | O8: =E8*1.4 -> 0 | P8: ='[1]Lpg (2)'!#REF! -> #REF! | Q8: ='[1]Summery Report'!#REF! -> #REF! | R8: =N8/B8 -> 1909.3846 | S8: =Q8/B8 -> #REF!
A9: =Gen!A14 -> 44290 | B9: ='Summery Report'!E8 -> 5.19 | C9: =Gen!U14 -> 0.40958834 | D9: =Gen!T14 -> 3328 | E9: =Gen!AK14 -> 0 | F9: =Gen!AS14 -> 0 | G9: ='Utility report '!AC9 -> 0 | H9: ='Utility report '!AE9 -> 77 | I9: ='Water-Meter'!E9 -> 70 | J9: ='Lpg (2)'!B13 -> 0 | K9: ='Lpg (2)'!C13 -> 0 | L9: ='Lpg (2)'!D13 -> 83 | M9: ='Lpg (2)'!G13 -> 86.372 | N9: =D9*1.4 -> 4659.2 | O9: =E9*1.4 -> 0 | P9: ='[1]Lpg (2)'!#REF! -> #REF! | Q9: ='[1]Summery Report'!#REF! -> #REF! | R9: =N9/B9 -> 897.7264 | S9: =Q9/B9 -> #REF!
A10: =Gen!A15 -> 44291 | B10: ='Summery Report'!E9 -> 7.79 | C10: =Gen!U15 -> 0.40968615 | D10: =Gen!T15 -> 3250 | E10: =Gen!AK15 -> 0 | F10: =Gen!AS15 -> 0 | G10: ='Utility report '!AC10 -> 0 | H10: ='Utility report '!AE10 -> 72 | I10: ='Water-Meter'!E10 -> 59 | J10: ='Lpg (2)'!B14 -> 0 | K10: ='Lpg (2)'!C14 -> 0 | L10: ='Lpg (2)'!D14 -> 82 | M10: ='Lpg (2)'!G14 -> 88.528 | N10: =D10*1.4 -> 4550 | O10: =E10*1.4 -> 0 | P10: ='[1]Lpg (2)'!#REF! -> #REF! | Q10: ='[1]Summery Report'!#REF! -> #REF! | R10: =N10/B10 -> 584.08216 | S10: =Q10/B10 -> #REF!
A11: =Gen!A16 -> 44292 | B11: ='Summery Report'!E10 -> 5.19 | C11: =Gen!U16 -> 0.41273616 | D11: =Gen!T16 -> 3070 | E11: =Gen!AK16 -> 0 | F11: =Gen!AS16 -> 0 | G11: ='Utility report '!AC11 -> 0 | H11: ='Utility report '!AE11 -> 82 | I11: ='Water-Meter'!E11 -> 210 | J11: ='Lpg (2)'!B15 -> 0 | K11: ='Lpg (2)'!C15 -> 0 | L11: ='Lpg (2)'!D15 -> 81 | M11: ='Lpg (2)'!G15 -> 82.896 | N11: =D11*1.4 -> 4298 | O11: =E11*1.4 -> 0 | P11: ='[1]Lpg (2)'!#REF! -> #REF! | Q11: ='[1]Summery Report'!#REF! -> #REF! | R11: =N11/B11 -> 828.13102 | S11: =Q11/B11 -> #REF!
A12: =Gen!A17 -> 44293 | B12: ='Summery Report'!E11 -> 11.69 | C12: =Gen!U17 -> 0.40155219 | D12: =Gen!T17 -> 3363 | E12: =Gen!AK17 -> 0 | F12: =Gen!AS17 -> 0 | G12: ='Utility report '!AC12 -> 101 | H12: ='Utility report '!AE12 -> 76 | I12: ='Water-Meter'!E12 -> 60 | J12: ='Lpg (2)'!B16 -> 0 | K12: ='Lpg (2)'!C16 -> 0 | L12: ='Lpg (2)'!D16 -> 80 | M12: ='Lpg (2)'!G16 -> 80.212 | N12: =D12*1.4 -> 4708.2 | O12: =E12*1.4 -> 0 | P12: ='[1]Lpg (2)'!#REF! -> #REF! | Q12: ='[1]Summery Report'!#REF! -> #REF! | R12: =N12/B12 -> 402.75449 | S12: =Q12/B12 -> #REF!
A13: =Gen!A18 -> 44294 | B13: ='Summery Report'!E12 -> 12.99 | C13: =Gen!U18 -> 0.40188175 | D13: =Gen!T18 -> 3146 | E13: =Gen!AK18 -> 0 | F13: =Gen!AS18 -> 0 | G13: ='Utility report '!AC13 -> 12 | H13: ='Utility report '!AE13 -> 82 | I13: ='Water-Meter'!E13 -> 75 | J13: ='Lpg (2)'!B17 -> 0 | K13: ='Lpg (2)'!C17 -> 0 | L13: ='Lpg (2)'!D17 -> 80 | M13: ='Lpg (2)'!G17 -> 83.996 | N13: =D13*1.4 -> 4404.4 | O13: =E13*1.4 -> 0 | P13: ='[1]Lpg (2)'!#REF! -> #REF! | Q13: ='[1]Summery Report'!#REF! -> #REF! | R13: =N13/B13 -> 339.06082 | S13: =Q13/B13 -> #REF!
A14: =Gen!A19 -> 44295 | B14: ='Summery Report'!E13 -> 15.58 | C14: =Gen!U19 -> 0.3941732 | D14: =Gen!T19 -> 3314 | E14: =Gen!AK19 -> 0 | F14: =Gen!AS19 -> 0 | G14: ='Utility report '!AC14 -> 0 | H14: ='Utility report '!AE14 -> 78 | I14: ='Water-Meter'!E14 -> 47 | J14: ='Lpg (2)'!B18 -> 85 | K14: ='Lpg (2)'!C18 -> 85 | L14: ='Lpg (2)'!D18 -> 79 | M14: ='Lpg (2)'!G18 -> 44 | N14: =D14*1.4 -> 4639.6 | O14: =E14*1.4 -> 0 | P14: ='[1]Lpg (2)'!#REF! -> #REF! | Q14: ='[1]Summery Report'!#REF! -> #REF! | R14: =N14/B14 -> 297.79204 | S14: =Q14/B14 -> #REF!
A15: =Gen!A20 -> 44296 | B15: ='Summery Report'!E14 -> 15.58 | C15: =Gen!U20 -> 0.39324811 | D15: =Gen!T20 -> 3168 | E15: =Gen!AK20 -> 0 | F15: =Gen!AS20 -> 0 | G15: ='Utility report '!AC15 -> 0 | H15: ='Utility report '!AE15 -> 77 | I15: ='Water-Meter'!E15 -> 46 | J15: ='Lpg (2)'!B19 -> 85 | K15: ='Lpg (2)'!C19 -> 85 | L15: ='Lpg (2)'!D19 -> 79 | M15: ='Lpg (2)'!G19 -> 88 | N15: =D15*1.4 -> 4435.2 | O15: =E15*1.4 -> 0 | P15: ='[1]Lpg (2)'!#REF! -> #REF! | Q15: ='[1]Summery Report'!#REF! -> #REF! | R15: =N15/B15 -> 284.67266 | S15: =Q15/B15 -> #REF!
A16: =Gen!A21 -> 44297 | B16: ='Summery Report'!E15 -> 11.69 | C16: =Gen!U21 -> 0.3966574 | D16: =Gen!T21 -> 3237 | E16: =Gen!AK21 -> 0 | F16: =Gen!AS21 -> 0 | G16: ='Utility report '!AC16 -> 0 | H16: ='Utility report '!AE16 -> 50 | I16: ='Water-Meter'!E16 -> 50 | J16: ='Lpg (2)'!B20 -> 85 | K16: ='Lpg (2)'!C20 -> 85 | L16: ='Lpg (2)'!D20 -> 75 | M16: ='Lpg (2)'!G20 -> 57.244 | N16: =D16*1.4 -> 4531.8 | O16: =E16*1.4 -> 0 | P16: ='[1]Lpg (2)'!#REF! -> #REF! | Q16: ='[1]Summery Report'!#REF! -> #REF! | R16: =N16/B16 -> 387.66467 | S16: =Q16/B16 -> #REF!
A17: =Gen!A22 -> 44298 | B17: ='Summery Report'!E16 -> 12.99 | C17: =Gen!U22 -> 0.35691343 | D17: =Gen!T22 -> 3269 | E17: =Gen!AK22 -> 0 | F17: =Gen!AS22 -> 0 | G17: ='Utility report '!AC17 -> 0 | H17: ='Utility report '!AE17 -> 46 | I17: ='Water-Meter'!E17 -> 61 | J17: ='Lpg (2)'!B21 -> 85 | K17: ='Lpg (2)'!C22 -> 85 | L17: ='Lpg (2)'!D21 -> 65 | M17: ='Lpg (2)'!G21 -> 64.328 | N17: =D17*1.4 -> 4576.6 | O17: =E17*1.4 -> 0 | P17: ='[1]Lpg (2)'!#REF! -> #REF! | Q17: ='[1]Summery Report'!#REF! -> #REF! | R17: =N17/B17 -> 352.31717 | S17: =Q17/B17 -> #REF!
A18: =Gen!A23 -> 44299 | B18: ='Summery Report'!E17 -> 14.29 | C18: =Gen!U23 -> 0.40665666 | D18: =Gen!T23 -> 2665 | E18: =Gen!AK23 -> 0 | F18: =Gen!AS23 -> 0 | G18: ='Utility report '!AC18 -> -48865 | H18: ='Utility report '!AE18 -> 42 | I18: ='Water-Meter'!E18 -> 181 | J18: ='Lpg (2)'!B22 -> 85 | K18: ='Lpg (2)'!C23 -> 85 | L18: ='Lpg (2)'!D22 -> 60 | M18: ='Lpg (2)'!G22 -> 63.228 | N18: =D18*1.4 -> 3731 | O18: =E18*1.4 -> 0 | P18: ='[1]Lpg (2)'!#REF! -> #REF! | Q18: ='[1]Summery Report'!#REF! -> #REF! | R18: =N18/B18 -> 261.09167 | S18: =Q18/B18 -> #REF!
A19: =Gen!A24 -> 44300 | B19: ='Summery Report'!E18 -> 14.29 | C19: =Gen!U24 -> 0.40256905 | D19: =Gen!T24 -> 2643 | E19: =Gen!AK24 -> 0 | F19: =Gen!AS24 -> 0 | G19: ='Utility report '!AC19 -> 177 | H19: ='Utility report '!AE19 -> 44 | I19: ='Water-Meter'!E19 -> 46 | J19: ='Lpg (2)'!B23 -> 85 | K19: ='Lpg (2)'!C24 -> 85 | L19: ='Lpg (2)'!D23 -> 55 | M19: ='Lpg (2)'!G23 -> 59.708 | N19: =D19*1.4 -> 3700.2 | O19: =E19*1.4 -> 0 | P19: ='[1]Lpg (2)'!#REF! -> #REF! | Q19: ='[1]Summery Report'!#REF! -> #REF! | R19: =N19/B19 -> 258.93632 | S19: =Q19/B19 -> #REF!
A20: =Gen!A25 -> 44301 | B20: ='Summery Report'!E19 -> 9.09 | C20: =Gen!U25 -> 0.40148205 | D20: =Gen!T25 -> 2618 | E20: =Gen!AK25 -> 0 | F20: =Gen!AS25 -> 0 | G20: ='Utility report '!AC20 -> 35 | H20: ='Utility report '!AE20 -> 45 | I20: ='Water-Meter'!E20 -> 47 | J20: ='Lpg (2)'!B24 -> 85 | K20: ='Lpg (2)'!C25 -> 85 | L20: ='Lpg (2)'!D24 -> 51 | M20: ='Lpg (2)'!G24 -> 59.092 | N20: =D20*1.4 -> 3665.2 | O20: =E20*1.4 -> 0 | P20: ='[1]Lpg (2)'!#REF! -> #REF! | Q20: ='[1]Summery Report'!#REF! -> #REF! | R20: =N20/B20 -> 403.21232 | S20: =Q20/B20 -> #REF!
A21: =Gen!A26 -> 44302 | B21: ='Summery Report'!E20 -> 7.79 | C21: =Gen!U26 -> 0.40802435 | D21: =Gen!T26 -> 2546 | E21: =Gen!AK26 -> 0 | F21: =Gen!AS26 -> 0 | G21: ='Utility report '!AC21 -> 38 | H21: ='Utility report '!AE21 -> 42 | I21: ='Water-Meter'!E21 -> 40 | J21: ='Lpg (2)'!B25 -> 85 | K21: ='Lpg (2)'!C25 -> 85 | L21: ='Lpg (2)'!D25 -> 49 | M21: ='Lpg (2)'!G25 -> 44 | N21: =D21*1.4 -> 3564.4 | O21: =E21*1.4 -> 0 | P21: ='[1]Lpg (2)'!#REF! -> #REF! | Q21: ='[1]Summery Report'!#REF! -> #REF! | R21: =N21/B21 -> 457.56098 | S21: =Q21/B21 -> #REF!
A22: =Gen!A27 -> 44303 | B22: ='Summery Report'!E21 -> 6.49 | C22: =Gen!U27 -> 0.4093467 | D22: =Gen!T27 -> 2694 | E22: =Gen!AK27 -> 0 | F22: =Gen!AS27 -> 0 | G22: ='Utility report '!AC22 -> 38 | H22: ='Utility report '!AE22 -> 45 | I22: ='Water-Meter'!E22 -> 52 | J22: ='Lpg (2)'!B26 -> 85 | K22: ='Lpg (2)'!C26 -> 85 | L22: ='Lpg (2)'!D26 -> 45 | M22: ='Lpg (2)'!G26 -> 56.848 | N22: =D22*1.4 -> 3771.6 | O22: =E22*1.4 -> 0 | P22: ='[1]Lpg (2)'!#REF! -> #REF! | Q22: ='[1]Summery Report'!#REF! -> #REF! | R22: =N22/B22 -> 581.14022 | S22: =Q22/B22 -> #REF!
A23: =Gen!A28 -> 44304 | B23: ='Summery Report'!E22 -> 0 | C23: =Gen!U28 -> 0.41046143 | D23: =Gen!T28 -> 2839 | E23: =Gen!AK28 -> 0 | F23: =Gen!AS28 -> 0 | G23: ='Utility report '!AC23 -> 38 | H23: ='Utility report '!AE23 -> 46 | I23: ='Water-Meter'!E23 -> 53 | J23: ='Lpg (2)'!B27 -> 85 | K23: ='Lpg (2)'!C27 -> 85 | L23: ='Lpg (2)'!D27 -> 40 | M23: ='Lpg (2)'!G27 -> 61.952 | N23: =D23*1.4 -> 3974.6 | O23: =E23*1.4 -> 0 | P23: ='[1]Lpg (2)'!#REF! -> #REF! | Q23: ='[1]Summery Report'!#REF! -> #REF! | R23: =N23/B23 -> #DIV/0! | S23: =Q23/B23 -> #REF!
A24: =Gen!A29 -> 44305 | B24: ='Summery Report'!E23 -> 0 | C24: =Gen!U29 -> 0.42041712 | D24: =Gen!T29 -> 2733 | E24: =Gen!AK29 -> 0 | F24: =Gen!AS29 -> 0 | G24: ='Utility report '!AC24 -> 37 | H24: ='Utility report '!AE24 -> 49 | I24: ='Water-Meter'!E24 -> 58 | J24: ='Lpg (2)'!B28 -> 85 | K24: ='Lpg (2)'!C28 -> 85 | L24: ='Lpg (2)'!D28 -> 35 | M24: ='Lpg (2)'!G28 -> 67.804 | N24: =D24*1.4 -> 3826.2 | O24: =E24*1.4 -> 0 | P24: ='[1]Lpg (2)'!#REF! -> #REF! | Q24: ='[1]Summery Report'!#REF! -> #REF! | R24: =N24/B24 -> #DIV/0! | S24: =Q24/B24 -> #REF!
A25: =Gen!A30 -> 44306 | B25: ='Summery Report'!E24 -> 0 | C25: =Gen!U30 -> 0.41581933 | D25: =Gen!T30 -> 2856 | E25: =Gen!AK30 -> 0 | F25: =Gen!AS30 -> 0 | G25: ='Utility report '!AC25 -> 130 | H25: ='Utility report '!AE25 -> 40 | I25: ='Water-Meter'!E25 -> 66 | J25: ='Lpg (2)'!B29 -> 85 | K25: ='Lpg (2)'!C29 -> 85 | L25: ='Lpg (2)'!D29 -> 31 | M25: ='Lpg (2)'!G29 -> 65.956 | N25: =D25*1.4 -> 3998.4 | O25: =E25*1.4 -> 0 | P25: ='[1]Lpg (2)'!#REF! -> #REF! | Q25: ='[1]Summery Report'!#REF! -> #REF! | R25: =N25/B25 -> #DIV/0! | S25: =Q25/B25 -> #REF!
A26: =Gen!A31 -> 44307 | B26: ='Summery Report'!E25 -> 0 | C26: =Gen!U31 -> 0.41387407 | D26: =Gen!T31 -> 2700 | E26: =Gen!AK31 -> 0 | F26: =Gen!AS31 -> 0 | G26: ='Utility report '!AC26 -> 56 | H26: ='Utility report '!AE26 -> 45 | I26: ='Water-Meter'!E26 -> 47 | J26: ='Lpg (2)'!B30 -> 85 | K26: ='Lpg (2)'!C30 -> 85 | L26: ='Lpg (2)'!D30 -> 27 | M26: ='Lpg (2)'!G30 -> 65.56 | N26: =D26*1.4 -> 3780 | O26: =E26*1.4 -> 0 | P26: ='[1]Lpg (2)'!#REF! -> #REF! | Q26: ='[1]Summery Report'!#REF! -> #REF! | R26: =N26/B26 -> #DIV/0! | S26: =Q26/B26 -> #REF!
A27: =Gen!A32 -> 44308 | B27: ='Summery Report'!E26 -> 0 | C27: =Gen!U32 -> 0.41092943 | D27: =Gen!T32 -> 2593 | E27: =Gen!AK32 -> 0 | F27: =Gen!AS32 -> 0 | G27: ='Utility report '!AC27 -> 0 | H27: ='Utility report '!AE27 -> 46 | I27: ='Water-Meter'!E27 -> 50 | J27: ='Lpg (2)'!B31 -> 85 | K27: ='Lpg (2)'!C31 -> 85 | L27: ='Lpg (2)'!D31 -> 25 | M27: ='Lpg (2)'!G31 -> 58.212 | N27: =D27*1.4 -> 3630.2 | O27: =E27*1.4 -> 0 | P27: ='[1]Lpg (2)'!#REF! -> #REF! | Q27: ='[1]Summery Report'!#REF! -> #REF! | R27: =N27/B27 -> #DIV/0! | S27: =Q27/B27 -> #REF!
A28: =Gen!A33 -> 44309 | B28: ='Summery Report'!E27 -> 0 | C28: =Gen!U33 -> 0.40950696 | D28: =Gen!T33 -> 2657 | E28: =Gen!AK33 -> 0 | F28: =Gen!AS33 -> 0 | G28: ='Utility report '!AC28 -> 38 | H28: ='Utility report '!AE28 -> 29 | I28: ='Water-Meter'!E28 -> 47 | J28: ='Lpg (2)'!B32 -> 85 | K28: ='Lpg (2)'!C32 -> 85 | L28: ='Lpg (2)'!D32 -> 20 | M28: ='Lpg (2)'!G32 -> 41.14 | N28: =D28*1.4 -> 3719.8 | O28: =E28*1.4 -> 0 | P28: ='[1]Lpg (2)'!#REF! -> #REF! | Q28: ='[1]Summery Report'!#REF! -> #REF! | R28: =N28/B28 -> #DIV/0! | S28: =Q28/B28 -> #REF!
A29: =Gen!A34 -> 44310 | B29: ='Summery Report'!E28 -> 0 | C29: =Gen!U34 -> 0.39966527 | D29: =Gen!T34 -> 2629 | E29: =Gen!AK34 -> 0 | F29: =Gen!AS34 -> 0 | G29: ='Utility report '!AC29 -> 37 | H29: ='Utility report '!AE29 -> 45 | I29: ='Water-Meter'!E29 -> 56 | J29: ='Lpg (2)'!B33 -> 85 | K29: ='Lpg (2)'!C33 -> 85 | L29: ='Lpg (2)'!D33 -> 17 | M29: ='Lpg (2)'!G33 -> 62.788 | N29: =D29*1.4 -> 3680.6 | O29: =E29*1.4 -> 0 | P29: ='[1]Lpg (2)'!#REF! -> #REF! | Q29: ='[1]Summery Report'!#REF! -> #REF! | R29: =N29/B29 -> #DIV/0! | S29: =Q29/B29 -> #REF!
A30: =Gen!A35 -> 44311 | B30: ='Summery Report'!E29 -> 0 | C30: =Gen!U35 -> 0.39691349 | D30: =Gen!T35 -> 2890 | E30: =Gen!AK35 -> 0 | F30: =Gen!AS35 -> 0 | G30: ='Utility report '!AC30 -> 131 | H30: ='Utility report '!AE30 -> 46 | I30: ='Water-Meter'!E30 -> 46 | J30: ='Lpg (2)'!B34 -> 85 | K30: ='Lpg (2)'!C34 -> 85 | L30: ='Lpg (2)'!D34 -> 15 | M30: ='Lpg (2)'!G34 -> 66.132 | N30: =D30*1.4 -> 4046 | O30: =E30*1.4 -> 0 | P30: ='[1]Lpg (2)'!#REF! -> #REF! | Q30: ='[1]Summery Report'!#REF! -> #REF! | R30: =N30/B30 -> #DIV/0! | S30: =Q30/B30 -> #REF!
A31: =Gen!A36 -> 44312 | B31: ='Summery Report'!E30 -> 0 | C31: =Gen!U36 -> 0.41366407 | D31: =Gen!T36 -> 2691 | E31: =Gen!AK36 -> 0 | F31: =Gen!AS36 -> 0 | G31: ='Utility report '!AC31 -> 9 | H31: ='Utility report '!AE31 -> 45 | I31: ='Water-Meter'!E31 -> 53 | J31: ='Lpg (2)'!B35 -> 85 | K31: ='Lpg (2)'!C35 -> 85 | L31: ='Lpg (2)'!D35 -> 10 | M31: ='Lpg (2)'!G35 -> 66.352 | N31: =D31*1.4 -> 3767.4 | O31: =E31*1.4 -> 0 | P31: ='[1]Lpg (2)'!#REF! -> #REF! | Q31: ='[1]Summery Report'!#REF! -> #REF! | R31: =N31/B31 -> #DIV/0! | S31: =Q31/B31 -> #REF!
A32: =Gen!A37 -> 44313 | B32: ='Summery Report'!E31 -> 0 | C32: =Gen!U37 -> 0.40857666 | D32: =Gen!T37 -> 2733 | E32: =Gen!AK37 -> 0 | F32: =Gen!AS37 -> 0 | G32: ='Utility report '!AC32 -> 35 | H32: ='Utility report '!AE32 -> 40 | I32: ='Water-Meter'!E32 -> 43 | J32: ='Lpg (2)'!B36 -> 85 | K32: ='Lpg (2)'!C36 -> 85 | L32: ='Lpg (2)'!D36 -> 7 | M32: ='Lpg (2)'!G36 -> 68.508 | N32: =D32*1.4 -> 3826.2 | O32: =E32*1.4 -> 0 | P32: ='[1]Lpg (2)'!#REF! -> #REF! | Q32: ='[1]Summery Report'!#REF! -> #REF! | R32: =N32/B32 -> #DIV/0! | S32: =Q32/B32 -> #REF!
... A36: =Gen!A41 -> 0 | B36: ='Summery Report'!E35 -> 0 | C36: =Gen!U41 -> #DIV/0! | D36: =Gen!T41 -> 0 | E36: =Gen!AK41 -> 0 | F36: =Gen!AS41 -> 0 | G36: ='Utility report '!AC36 -> -977 | H36: ='Utility report '!AE36 -> -215686 | I36: ='Water-Meter'!E36 -> 0 | J36: ='Lpg (2)'!B40 -> 85 | K36: ='Lpg (2)'!C40 -> 85 | L36: ='Lpg (2)'!D40 -> 1 | M36: ='Lpg (2)'!G40 -> 57.024 | N36: =D36*1.4 -> 0 | O36: =E36*1.4 -> 0 | P36: ='[1]Lpg (2)'!#REF! -> #REF! | Q36: ='[1]Summery Report'!#REF! -> #REF! | R36: =N36/B36 -> #DIV/0! | S36: =Q36/B36 -> #REF!
A37: =Gen!A42 -> 0 | B37: ='Summery Report'!E36 -> 0 | C37: =Gen!U42 -> 0 | D37: =Gen!T42 -> 0 | E37: =Gen!AK42 -> 0 | F37: =Gen!AS42 -> 0 | G37: ='Utility report '!AC37 -> 0 | H37: ='Utility report '!AE37 -> 0 | I37: ='Water-Meter'!E37 -> 0 | J37: ='Lpg (2)'!B41 -> 0 | K37: ='Lpg (2)'!C41 -> 0 | L37: ='Lpg (2)'!D41 -> 0 | M37: ='Lpg (2)'!G41 -> -335483.76 | Q37: ='[1]Summery Report'!#REF! -> #REF! | R37: =N37/B37 -> #DIV/0! | S37: =Q37/B37 -> #REF!
A39: Total | B39: =SUM(B7:B37) -> 155.84 | C39: =SUM(C7:C35) -> 11.74995 | D39: =SUM(D7:D35) -> 84634 | E39: =SUM(E7:E35) -> 0 | F39: =SUM(F7:F35) -> 0 | G39: =SUM(G7:G35) -> -47800 | H39: =SUM(H7:H35) -> 1604 | I39: =SUM(I7:I35) -> 2019 | J39: =SUM(J7:J35) -> 1870 | ... S39: =SUM(S7:S35) -> #REF!

Sheet Utility report 
A1: =A6 -> 44287
A2: Date | B2: Total occupancy | H2: Diesel balance LTS | I2: Diesel Deliveries | J2: Gen.Diesel consumption LTS | L2: Total Diesel consumption LTS | M2: Water Meter reading | N2: Water consumption m³ | O2: R.O WATER PRODUCTION LTRS + TIME | AA2: Total RO production | AB2: RO Meter reading | AD2: 0 | AE2: STP | AF2: GAS TANK A | AG2: GAS TANK B | AH2: GAS TANK C | AI2: Total Gas Tanks | AJ2: Kg /day | AK2: TOTAL GAS cons.
A3: Rate Tsh /$ | B3: 1640 | C3: Diesel cost / lits | D3: 2175 | F3: =SUM(D3/B3) -> 1.3262195 | H3: =Gen!C11 -> 34515.97 | K3: Transport consumption | M3: Balance | O3: PLANT NO 1 | S3: PLANT NO 2 | W3: PLANT NO 3 | AA3: /day | AB3: Balance | AD3: 0 | AE3: Production | AF3: Capacity | AG3: Capacity | AH3: Capacity | AI3: Kg | AJ3: /day | AK3: /day
B4: Rooms OCC | C4: % | D4: Guest Rooms Occ | F4: Electricity Production Cost /Room Occ by guest | G4: All Cost /Room Occ by guest | O4: Flow M3 | P4: Reading Hours Meter | Q4: Hrs | R4: total production M3 | S4: Flow M3 | T4: Reading Hours Meter | U4: Hrs | V4: total production M3 | W4: Flow M3 | X4: READING HOURS METER | Y4: Hrs | Z4: total production M3 | AA4: M3 | AC4: M3 | AE4: M3 | AF4: 2000 | AG4: 1000 | AH4: 1000 | AI4: =SUM([2]Sheet1!$AA$36) -> 950 | AJ4: Kg | AK4: M3
P5: 19032 | T5: 17812 | AB5: 48777 | AD5: 214010 | AF5: 0.85 | AG5: 0.85 | AH5: 0.85
A6: =Gen!A11 -> 44287 | B6: ='Summery Report'!E5 -> 1.3 | C6: =Gen!B11 -> 0.156 | D6: ='Summery Report'!E5 -> 1.3 | E6: =SUM(F3) -> 1.3262195 | F6: =SUM(J6*E6)/D6 -> 3239.0361 | G6: =SUM(L6*E6)/D6 -> 3239.0361 | H6: =Gen!C11 -> 34515.97 | I6: =Gen!E11 -> 0 | J6: =Gen!T11 -> 3175 | K6: =Gen!AK11 -> 0 | L6: =SUM(J6:K6) -> 3175 | M6: ='Water-Meter'!K46 -> 479.98747 | N6: ='Water-Meter'!E6 -> 89 | P6: 19032 | Q6: =SUM(P6-P5) -> 0 | R6: =SUM(Q6*O6) -> 0 | S6: 6.2 | T6: 17812 | U6: =T6-T5 -> 0 | V6: - | W6: 1.8 | X6: 27671 | Y6: =X6-X5 -> 27671 | Z6: =Y6-Y5 -> 27671 | AA6: =Z6-Z5 -> 27671 | AB6: 48777 | AC6: =AB6-AB5 -> 0 | AD6: 214082 | AE6: =AD6-AD5 -> 72 | AF6: ='Lpg (2)'!B10*2000/85 -> 0 | AG6: ='Lpg (2)'!C10*1000/85 -> 176.47059 | AH6: ='Lpg (2)'!D10*1000/85 -> 1000 | AI6: =SUM(AF6*2000)+(AG6*1000)+(AH6*1000) -> 1176470.6 | AJ6: =SUM(AI5-AI6) -> -1176470.6
A7: =Gen!A12 -> 44288 | B7: ='Summery Report'!E6 -> 2.6 | C7: =Gen!B12 -> 0.169 | D7: ='Summery Report'!E6 -> 2.6 | E7: =SUM(E6) -> 1.3262195 | F7: =SUM(J7*E7)/D7 -> 1625.6391 | G7: =SUM(L7*E7)/D7 -> 1625.6391 | H7: =Gen!C12 -> 33044.09 | I7: =Gen!E12 -> 0 | J7: =Gen!T12 -> 3187 | K7: =Gen!AK12 -> 0 | L7: =SUM(J7:K7) -> 3187 | M7: ='Water-Meter'!K47 -> 402.50327 | N7: ='Water-Meter'!E7 -> 117 | P7: 19032 | Q7: =SUM(P7-P6) -> 0 | R7: =SUM(Q7*O7) -> 0 | S7: 6.2 | T7: 17812 | U7: =T7-T6 -> 0 | V7: =SUM(U7*S7) -> 0 | W7: 1.8 | X7: 27695 | Y7: =X7-X6 -> 24 | Z7: =SUM(Y7*W7) -> 43.2 | AA7: =SUM(Z7*X9) -> 1198497.6 | AB7: 48777 | AC7: =AB7-AB6 -> 0 | AD7: 214163 | AE7: =AD7-AD6 -> 81 | AF7: ='Lpg (2)'!B11*2000/85 -> 0 | AG7: ='Lpg (2)'!C11*1000/85 -> 117.64706 | AH7: ='Lpg (2)'!D11*1000/85 -> 1000 | AI7: =SUM(AF6*2000)+(AG7*1000)+(AH7*1000) -> 1117647.1 | AJ7: =SUM(AI6-AI7) -> 58823.529
A8: =Gen!A13 -> 44289 | B8: ='Summery Report'!E7 -> 2.6 | C8: =Gen!B13 -> 0.23 | D8: ='Summery Report'!E7 -> 2.6 | E8: =SUM(E7) -> 1.3262195 | F8: =SUM(J8*E8)/D8 -> 1808.7594 | G8: =SUM(L8*E8)/D8 -> 1808.7594 | H8: =Gen!C13 -> 31510.36 | I8: =Gen!E13 -> 0 | J8: =Gen!T13 -> 3546 | K8: =Gen!AK13 -> 0 | L8: =SUM(J8:K8) -> 3546 | M8: ='Water-Meter'!K48 -> 446.34286 | N8: ='Water-Meter'!E8 -> 167 | P8: 19032 | Q8: =SUM(P8-P7) -> 0 | R8: =SUM(Q8*O8) -> 0 | S8: 6.2 | T8: 17812 | U8: =T8-T7 -> 0 | V8: =SUM(U8*S8) -> 0 | W8: 1.8 | X8: 27719 | Y8: =X8-X7 -> 24 | Z8: =SUM(Y8*W8) -> 43.2 | AA8: =SUM(Z8*X10) -> 1198497.6 | AB8: 48777 | AC8: =AB8-AB7 -> 0 | AD8: 214237 | AE8: =AD8-AD7 -> 74 | AF8: ='Lpg (2)'!B12*2000/85 -> 0 | AG8: ='Lpg (2)'!C12*1000/85 -> 35.294118 | AH8: ='Lpg (2)'!D12*1000/85 -> 1000 | AI8: =SUM(AF7*2000)+(AG8*1000)+(AH8*1000) -> 1035294.1 | AJ8: =SUM(AI7-AI8) -> 82352.941
A9: =Gen!A14 -> 44290 | B9: ='Summery Report'!E8 -> 5.19 | C9: =Gen!B14 -> 0.247 | D9: ='Summery Report'!E8 -> 5.19 | E9: =SUM(E8) -> 1.3262195 | F9: =SUM(J9*E9)/D9 -> 850.4159 | G9: =SUM(L9*E9)/D9 -> 850.4159 | H9: =Gen!C14 -> 29944.6 | I9: =Gen!E14 -> 0 | J9: =Gen!T14 -> 3328 | K9: =Gen!AK14 -> 0 | L9: =SUM(J9:K9) -> 3328 | M9: ='Water-Meter'!K49 -> 340.52161 | N9: ='Water-Meter'!E9 -> 70 | P9: 19032 | Q9: =SUM(P9-P8) -> 0 | R9: =SUM(Q9*O9) -> 0 | S9: 6.2 | T9: 17812 | U9: =T9-T8 -> 0 | V9: =SUM(U9*S9) -> 0 | W9: 1.8 | X9: 27743 | Y9: =X9-X8 -> 24 | Z9: =SUM(Y9*W11) -> 43.2 | AA9: =SUM(Z9*X11) -> 1198497.6 | AB9: 48777 | AC9: =AB9-AB8 -> 0 | AD9: 214314 | AE9: =AD9-AD8 -> 77 | AF9: ='Lpg (2)'!B13*2000/85 -> 0 | AG9: ='Lpg (2)'!C13*1000/85 -> 0 | AH9: ='Lpg (2)'!D13*1000/85 -> 976.47059 | AI9: =SUM(AF8*2000)+(AG9*1000)+(AH9*1000) -> 976470.59 | AJ9: =SUM(AI8-AI9) -> 58823.529
A10: =Gen!A15 -> 44291 | B10: ='Summery Report'!E9 -> 7.79 | C10: =Gen!B15 -> 0.13 | D10: ='Summery Report'!E9 -> 7.79 | E10: =SUM(E9) -> 1.3262195 | F10: =SUM(J10*E10)/D10 -> 553.30082 | G10: =SUM(L10*E10)/D10 -> 553.30082 | H10: =Gen!C15 -> 28581.49 | I10: =Gen!E15 -> 0 | J10: =Gen!T15 -> 3250 | K10: =Gen!AK15 -> 0 | L10: =SUM(J10:K10) -> 3250 | M10: ='Water-Meter'!K50 -> 422.68192 | N10: ='Water-Meter'!E10 -> 59 | P10: 19032 | Q10: =SUM(P10-P9) -> 0 | R10: =SUM(Q10*O10) -> 0 | S10: 6.2 | T10: 17828 | U10: =T10-T9 -> 16 | V10: =SUM(U10*S10) -> 99.2 | W10: 1.8 | X10: 27743 | Y10: =X10-X9 -> 0 | Z10: =SUM(Y10*W10) -> 0 | AA10: =SUM(Z10*X12) -> 0 | AB10: 48777 | AC10: =AB10-AB9 -> 0 | AD10: 214386 | AE10: =AD10-AD9 -> 72 | AF10: ='Lpg (2)'!B14*2000/85 -> 0 | AG10: ='Lpg (2)'!C14*1000/85 -> 0 | AH10: ='Lpg (2)'!D14*1000/85 -> 964.70588 | AI10: =SUM(AF9*2000)+(AG10*1000)+(AH10*1000) -> 964705.88 | AJ10: =SUM(AI9-AI10) -> 11764.706
A11: =Gen!A16 -> 44292 | B11: ='Summery Report'!E10 -> 5.19 | C11: =Gen!B16 -> 0.091 | D11: ='Summery Report'!E10 -> 5.19 | E11: =SUM(E10) -> 1.3262195 | F11: =SUM(J11*E11)/D11 -> 784.48823 | G11: =SUM(L11*E11)/D11 -> 784.48823 | H11: =Gen!C16 -> 27031.5 | I11: =Gen!E16 -> 15000 | J11: =Gen!T16 -> 3070 | K11: =Gen!AK16 -> 0 | L11: =SUM(J11:K11) -> 3070 | M11: ='Water-Meter'!K51 -> 393.46238 | N11: ='Water-Meter'!E11 -> 210 | P11: 19032 | Q11: =SUM(P11-P10) -> 0 | R11: =SUM(Q11*O11) -> 0 | S11: 6.2 | T11: 17828 | U11: =T11-T10 -> 0 | V11: =SUM(U11*S11) -> 0 | W11: 1.8 | X11: 27743 | Y11: =X11-X10 -> 0 | Z11: =SUM(Y11*#REF!) -> #REF! | AA11: =SUM(Z11*X13) -> #REF! | AB11: 48777 | AC11: =AB11-AB10 -> 0 | AD11: 214468 | AE11: =AD11-AD10 -> 82 | AF11: ='Lpg (2)'!B15*2000/85 -> 0 | AG11: ='Lpg (2)'!C15*1000/85 -> 0 | AH11: ='Lpg (2)'!D15*1000/85 -> 952.94118 | AI11: =SUM(AF10*2000)+(AG11*1000)+(AH11*1000) -> 952941.18 | AJ11: =SUM(AI10-AI11) -> 11764.706
A12: =Gen!A17 -> 44293 | B12: ='Summery Report'!E11 -> 11.69 | C12: =Gen!B17 -> 0.065 | D12: ='Summery Report'!E11 -> 11.69 | E12: =SUM(E11) -> 1.3262195 | F12: =SUM(J12*E12)/D12 -> 381.52919 | G12: =SUM(L12*E12)/D12 -> 381.52919 | H12: =Gen!C17 -> 43721.96 | I12: =Gen!E17 -> 0 | J12: =Gen!T17 -> 3363 | K12: =Gen!AK17 -> 0 | L12: =SUM(J12:K12) -> 3363 | M12: ='Water-Meter'!K52 -> 451.42807 | N12: ='Water-Meter'!E12 -> 60 | P12: 19032 | Q12: =SUM(P12-P11) -> 0 | R12: =SUM(Q12*O12) -> 0 | S12: 6.2 | T12: 17852 | U12: =T12-T11 -> 24 | V12: =SUM(U12*S12) -> 148.8 | W12: 1.8 | X12: 27743 | Y12: =X12-X11 -> 0 | Z12: =SUM(Y12*W12) -> 0 | AA12: =SUM(Z12*X14) -> 0 | AB12: 48878 | AC12: =AB12-AB11 -> 101 | AD12: 214544 | AE12: =AD12-AD11 -> 76 | AF12: ='Lpg (2)'!B16*2000/85 -> 0 | AG12: ='Lpg (2)'!C16*1000/85 -> 0 | AH12: ='Lpg (2)'!D16*1000/85 -> 941.17647 | AI12: =SUM(AF11*2000)+(AG12*1000)+(AH12*1000) -> 941176.47 | AJ12: =SUM(AI11-AI12) -> 11764.706
A13: =Gen!A18 -> 44294 | B13: ='Summery Report'!E12 -> 12.99 | C13: =Gen!B18 -> 0.091 | D13: ='Summery Report'!E12 -> 12.99 | E13: =SUM(E12) -> 1.3262195 | F13: =SUM(J13*E13)/D13 -> 321.19219 | G13: =SUM(L13*E13)/D13 -> 321.19219 | H13: =Gen!C18 -> 42252.4 | I13: =Gen!E18 -> 0 | J13: =Gen!T18 -> 3146 | K13: =Gen!AK18 -> 0 | L13: =SUM(J13:K13) -> 3146 | M13: ='Water-Meter'!K53 -> 514.42482 | N13: ='Water-Meter'!E13 -> 75 | P13: 19032 | Q13: =SUM(P13-P12) -> 0 | R13: =SUM(Q13*O13) -> 0 | S13: 6.2 | T13: 17859 | U13: =T13-T12 -> 7 | V13: =SUM(U13*S13) -> 43.4 | W13: 1.8 | X13: 27743 | Y13: =X13-X12 -> 0 | Z13: =SUM(Y13*W13) -> 0 | AA13: =SUM(Z13*X15) -> 0 | AB13: 48890 | AC13: =AB13-AB12 -> 12 | AD13: 214626 | AE13: =AD13-AD12 -> 82 | AF13: ='Lpg (2)'!B17*2000/85 -> 0 | AG13: ='Lpg (2)'!C17*1000/85 -> 0 | AH13: ='Lpg (2)'!D17*1000/85 -> 941.17647 | AI13: =SUM(AF12*2000)+(AG13*1000)+(AH13*1000) -> 941176.47 | AJ13: =SUM(AI12-AI13) -> 0
A14: =Gen!A19 -> 44295 | B14: ='Summery Report'!E13 -> 15.58 | C14: =Gen!B19 -> 0.065 | D14: ='Summery Report'!E13 -> 15.58 | E14: =SUM(E13) -> 1.3262195 | F14: =SUM(J14*E14)/D14 -> 282.0983 | G14: =SUM(L14*E14)/D14 -> 282.0983 | H14: =Gen!C19 -> 40831.76 | I14: =Gen!E19 -> 0 | J14: =Gen!T19 -> 3314 | K14: =Gen!AK19 -> 0 | L14: =SUM(J14:K14) -> 3314 | M14: ='Water-Meter'!K54 -> 588.89186 | N14: ='Water-Meter'!E14 -> 47 | P14: 19032 | Q14: =SUM(P14-P13) -> 0 | R14: =SUM(Q14*O14) -> 0 | S14: 6.2 | T14: 17869 | U14: =T14-T13 -> 10 | V14: =SUM(U14*S14) -> 62 | W14: 1.8 | X14: 27752 | Y14: =X14-X13 -> 9 | Z14: =SUM(Y14*W14) -> 16.2 | AA14: =SUM(Z14*X16) -> 450214.2 | AB14: 48890 | AC14: =AB14-AB13 -> 0 | AD14: 214704 | AE14: =AD14-AD13 -> 78 | AF14: ='Lpg (2)'!B18*2000/85 -> 2000 | AG14: ='Lpg (2)'!C18*1000/85 -> 1000 | AH14: ='Lpg (2)'!D18*1000/85 -> 929.41176 | AI14: =SUM(AF13*2000)+(AG14*1000)+(AH14*1000) -> 1929411.8 | AJ14: =SUM(AI13-AI14) -> -988235.29
A15: =Gen!A20 -> 44296 | B15: ='Summery Report'!E14 -> 15.58 | C15: =Gen!B20 -> 0.052 | D15: ='Summery Report'!E14 -> 15.58 | E15: =SUM(E14) -> 1.3262195 | F15: =SUM(J15*E15)/D15 -> 269.67031 | G15: =SUM(L15*E15)/D15 -> 269.67031 | H15: =Gen!C20 -> 39223.36 | I15: =Gen!E20 -> 0 | J15: =Gen!T20 -> 3168 | K15: =Gen!AK20 -> 0 | L15: =SUM(J15:K15) -> 3168 | M15: ='Water-Meter'!K55 -> 617.48167 | N15: ='Water-Meter'!E15 -> 46 | P15: 19032 | Q15: =SUM(P15-P14) -> 0 | R15: =SUM(Q15*O15) -> 0 | S15: 6.2 | T15: 17869 | U15: =T15-T14 -> 0 | V15: =SUM(U15*S15) -> 0 | W15: 1.8 | X15: 27767 | Y15: =X15-X14 -> 15 | Z15: =SUM(Y15*W15) -> 27 | AA15: =SUM(Z15*X17) -> 751005 | AB15: 48890 | AC15: =AB15-AB14 -> 0 | AD15: 214781 | AE15: =AD15-AD14 -> 77 | AF15: ='Lpg (2)'!B19*2000/85 -> 2000 | AG15: ='Lpg (2)'!C19*1000/85 -> 1000 | AH15: ='Lpg (2)'!D19*1000/85 -> 929.41176 | AI15: =SUM(AF15*2000)+(AG15*1000)+(AH15*1000) -> 5929411.8 | AJ15: =SUM(AI14-AI15) -> -4000000
A16: =Gen!A21 -> 44297 | B16: ='Summery Report'!E15 -> 11.69 | C16: =Gen!B21 -> 0.104 | D16: ='Summery Report'!E15 -> 11.69 | E16: =SUM(E15) -> 1.3262195 | F16: =SUM(J16*E16)/D16 -> 367.23461 | G16: =SUM(L16*E16)/D16 -> 367.23461 | H16: =Gen!C21 -> 37865.55 | I16: =Gen!E21 -> 0 | J16: =Gen!T21 -> 3237 | K16: =Gen!AK21 -> 0 | L16: =SUM(J16:K16) -> 3237 | M16: ='Water-Meter'!K56 -> 582.16665 | N16: ='Water-Meter'!E16 -> 50 | P16: 19032 | Q16: =SUM(P16-P15) -> 0 | R16: =SUM(Q16*O16) -> 0 | S16: 6.2 | T16: 17869 | U16: =T16-T15 -> 0 | V16: =SUM(U16*S16) -> 0 | W16: 1.8 | X16: 27791 | Y16: =X16-X15 -> 24 | Z16: =SUM(Y16*W16) -> 43.2 | AA16: =SUM(Z16*X18) -> 1202515.2 | AB16: 48890 | AC16: =AB16-AB15 -> 0 | AD16: 214831 | AE16: =AD16-AD15 -> 50 | AF16: ='Lpg (2)'!B20*2000/85 -> 2000 | AG16: ='Lpg (2)'!C20*1000/85 -> 1000 | AH16: ='Lpg (2)'!D20*1000/85 -> 882.35294 | AI16: =SUM(AF16*2000)+(AG16*1000)+(AH16*1000) -> 5882352.9 | AJ16: =SUM(AI15-AI16) -> 47058.824
A17: =Gen!A22 -> 44298 | B17: ='Summery Report'!E16 -> 12.99 | C17: =Gen!B22 -> 0.104 | D17: ='Summery Report'!E16 -> 12.99 | E17: =SUM(E16) -> 1.3262195 | F17: =SUM(J17*E17)/D17 -> 333.74993 | G17: =SUM(L17*E17)/D17 -> 333.74993 | H17: =Gen!C22 -> 36556.57 | I17: =Gen!E22 -> 0 | J17: =Gen!T22 -> 3269 | K17: =Gen!AK22 -> 0 | L17: =SUM(J17:K17) -> 3269 | M17: ='Water-Meter'!K57 -> 546.81756 | N17: ='Water-Meter'!E17 -> 61 | P17: 19032 | Q17: =SUM(P18-P16) -> 0 | R17: =SUM(Q17*O17) -> 0 | S17: 6.2 | T17: 17869 | U17: =T17-T16 -> 0 | V17: =SUM(U17*S17) -> 0 | W17: 1.8 | X17: 27815 | Y17: =X17-X16 -> 24 | Z17: =SUM(Y17*W17) -> 43.2 | AA17: =SUM(Z17*X19) -> 1202515.2 | AB17: 48890 | AC17: =AB17-AB16 -> 0 | AD17: 214877 | AE17: =AD17-AD16 -> 46 | AF17: ='Lpg (2)'!B21*2000/85 -> 2000 | AG17: ='Lpg (2)'!C21*1000/85 -> 1000 | AH17: ='Lpg (2)'!D21*1000/85 -> 764.70588 | AI17: =SUM(AF17*2000)+(AG17*1000)+(AH17*1000) -> 5764705.9 | AJ17: =SUM(AI16-AI17) -> 117647.06
A18: =Gen!A23 -> 44299 | B18: ='Summery Report'!E17 -> 14.29 | C18: =Gen!B23 -> 0.013 | D18: ='Summery Report'!E17 -> 14.29 | E18: =SUM(E17) -> 1.3262195 | F18: =SUM(J18*E18)/D18 -> 247.33205 | G18: =SUM(L18*E18)/D18 -> 247.33205 | H18: =Gen!C23 -> 35139.18 | I18: =Gen!E23 -> 0 | J18: =Gen!T23 -> 2665 | K18: =Gen!AK23 -> 0 | L18: =SUM(J18:K18) -> 2665 | M18: ='Water-Meter'!K58 -> 502.23159 | N18: ='Water-Meter'!E18 -> 181 | P18: 19032 | R18: =SUM(Q18*O18) -> 0 | S18: 6.2 | T18: 17869 | U18: =T18-T17 -> 0 | V18: =SUM(U18*S18) -> 0 | W18: 1.8 | X18: 27836 | Y18: =X18-X17 -> 21 | Z18: =SUM(Y18*W18) -> 37.8 | AA18: =SUM(Z18*X20) -> 1052994.6 | AB18: 25 | AC18: =AB18-AB17 -> -48865 | AD18: 214919 | AE18: =AD18-AD17 -> 42 | AF18: ='Lpg (2)'!B22*2000/85 -> 2000 | AG18: ='Lpg (2)'!C22*1000/85 -> 1000 | AH18: ='Lpg (2)'!D22*1000/85 -> 705.88235 | AI18: =SUM(AF18*2000)+(AG18*1000)+(AH18*1000) -> 5705882.4 | AJ18: =SUM(AI17-AI18) -> 58823.529
A19: =Gen!A24 -> 44300 | B19: ='Summery Report'!E18 -> 14.29 | C19: =Gen!B24 -> 0 | D19: ='Summery Report'!E18 -> 14.29 | E19: =SUM(E18) -> 1.3262195 | F19: =SUM(J19*E19)/D19 -> 245.29028 | G19: =SUM(L19*E19)/D19 -> 245.29028 | H19: =Gen!C24 -> 34032.9 | I19: =Gen!E24 -> 0 | J19: =Gen!T24 -> 2643 | K19: =Gen!AK24 -> 0 | L19: =SUM(J19:K19) -> 2643 | M19: ='Water-Meter'!K59 -> 356.75911 | N19: ='Water-Meter'!E19 -> 46 | P19: 19032 | R19: =SUM(Q19*O19) -> 0 | S19: 6.2 | T19: 17893 | U19: =T19-T18 -> 24 | V19: =SUM(U19*S19) -> 148.8 | W19: 1.8 | X19: 27836 | Y19: =X19-X18 -> 0 | Z19: =SUM(Y19*W19) -> 0 | AA19: =SUM(Z19*X21) -> 0 | AB19: 202 | AC19: =AB19-AB18 -> 177 | AD19: 214963 | AE19: =AD19-AD18 -> 44 | AF19: ='Lpg (2)'!B23*2000/85 -> 2000 | AG19: ='Lpg (2)'!C23*1000/85 -> 1000 | AH19: ='Lpg (2)'!D23*1000/85 -> 647.05882 | AI19: =SUM(AF19*2000)+(AG19*1000)+(AH19*1000) -> 5647058.8 | AJ19: =SUM(AI18-AI19) -> 58823.529
A20: =Gen!A25 -> 44301 | B20: ='Summery Report'!E19 -> 9.09 | C20: =Gen!B25 -> 0 | D20: ='Summery Report'!E19 -> 9.09 | E20: =SUM(E19) -> 1.3262195 | F20: =SUM(J20*E20)/D20 -> 381.96289 | G20: =SUM(L20*E20)/D20 -> 381.96289 | H20: =Gen!C25 -> 32808.42 | I20: =Gen!E25 -> 0 | J20: =Gen!T25 -> 2618 | K20: =Gen!AK25 -> 0 | L20: =SUM(J20:K20) -> 2618 | M20: ='Water-Meter'!K60 -> 349.48946 | N20: ='Water-Meter'!E20 -> 47 | P20: 19032 | Q20: =SUM(#REF!-P20) -> #REF! | R20: =SUM(Q20*O20) -> #REF! | S20: 6.2 | T20: 17893 | U20: =T20-T19 -> 0 | V20: =SUM(U20*S20) -> 0 | W20: 1.8 | X20: 27857 | Y20: =X20-X19 -> 21 | Z20: =SUM(Y20*W20) -> 37.8 | AA20: =SUM(Z20*X22) -> 1054809 | AB20: 237 | AC20: =AB20-AB19 -> 35 | AD20: 215008 | AE20: =AD20-AD19 -> 45 | AF20: ='Lpg (2)'!B24*2000/85 -> 2000 | AG20: ='Lpg (2)'!C24*1000/85 -> 1000 | AH20: ='Lpg (2)'!D24*1000/85 -> 600 | AI20: =SUM(AF20*2000)+(AG20*1000)+(AH20*1000) -> 5600000 | AJ20: =SUM(AI19-AI20) -> 47058.824
A21: =Gen!A26 -> 44302 | B21: ='Summery Report'!E20 -> 7.79 | C21: =Gen!B26 -> 0 | D21: ='Summery Report'!E20 -> 7.79 | E21: =SUM(E20) -> 1.3262195 | F21: =SUM(J21*E21)/D21 -> 433.44735 | G21: =SUM(L21*E21)/D21 -> 433.44735 | H21: =Gen!C26 -> 31655.43 | I21: =Gen!E26 -> 0 | J21: =Gen!T26 -> 2546 | K21: =Gen!AK26 -> 0 | L21: =SUM(J21:K21) -> 2546 | M21: ='Water-Meter'!K61 -> 442.38384 | N21: ='Water-Meter'!E21 -> 40 | P21: 19032 | Q21: =SUM(P21-#REF!) -> #REF! | R21: =SUM(Q21*O21) -> #REF! | S21: 6.2 | T21: 17893 | U21: =T22-T20 -> 0 | V21: =SUM(U21*S21) -> 0 | W21: 1.8 | X21: 27881 | Y21: =X21-X20 -> 24 | Z21: =SUM(Y21*W21) -> 43.2 | AA21: =SUM(Z21*X23) -> 1206532.8 | AB21: 275 | AC21: =AB21-AB20 -> 38 | AD21: 215050 | AE21: =AD21-AD20 -> 42 | AF21: ='Lpg (2)'!B25*2000/85 -> 2000 | AG21: ='Lpg (2)'!C25*1000/85 -> 1000 | AH21: ='Lpg (2)'!D25*1000/85 -> 576.47059 | AI21: =SUM(AF21*2000)+(AG21*1000)+(AH21*1000) -> 5576470.6 | AJ21: =SUM(AI20-AI21) -> 23529.412
A22: =Gen!A27 -> 44303 | B22: ='Summery Report'!E21 -> 6.49 | C22: =Gen!B27 -> 0.013 | D22: ='Summery Report'!E21 -> 6.49 | E22: =SUM(E21) -> 1.3262195 | F22: =SUM(J22*E22)/D22 -> 550.51392 | G22: =SUM(L22*E22)/D22 -> 550.51392 | H22: =Gen!C27 -> 30616.6 | I22: =Gen!E27 -> 0 | J22: =Gen!T27 -> 2694 | K22: =Gen!AK27 -> 0 | L22: =SUM(J22:K22) -> 2694 | M22: ='Water-Meter'!K62 -> 460.85304 | N22: ='Water-Meter'!E22 -> 52 | P22: 19032 | Q22: =SUM(P22-P21) -> 0 | R22: =SUM(Q22*O22) -> 0 | S22: 6.2 | T22: 17893 | U22: =T23-T21 -> 0 | V22: =SUM(U22*S22) -> 0 | W22: 1.8 | X22: 27905 | Y22: =X22-X21 -> 24 | Z22: =SUM(Y22*W22) -> 43.2 | AA22: =SUM(Z22*X24) -> 1207569.6 | AB22: 313 | AC22: =AB22-AB21 -> 38 | AD22: 215095 | AE22: =AD22-AD21 -> 45 | AF22: ='Lpg (2)'!B26*2000/85 -> 2000 | AG22: ='Lpg (2)'!C26*1000/85 -> 1000 | AH22: ='Lpg (2)'!D26*1000/85 -> 529.41176 | AI22: =SUM(AF22*2000)+(AG22*1000)+(AH22*1000) -> 5529411.8 | AJ22: =SUM(AI21-AI22) -> 47058.824
A23: =Gen!A28 -> 44304 | B23: ='Summery Report'!E22 -> 0 | C23: =Gen!B28 -> 0.039 | D23: ='Summery Report'!E22 -> 0 | E23: =SUM(E22) -> 1.3262195 | F23: =SUM(J23*E23)/D23 -> #DIV/0! | G23: =SUM(L23*E23)/D23 -> #DIV/0! | H23: =Gen!C28 -> 29367.51 | I23: =Gen!E28 -> 0 | J23: =Gen!T28 -> 2839 | K23: =Gen!AK28 -> 0 | L23: =SUM(J23:K23) -> 2839 | M23: ='Water-Meter'!K63 -> 499.96316 | N23: ='Water-Meter'!E23 -> 53 | P23: 19032 | Q23: =SUM(P23-P22) -> 0 | R23: =SUM(Q23*O23) -> 0 | S23: 6.2 | T23: 17893 | U23: =T24-T22 -> 0 | V23: =SUM(U23*S23) -> 0 | W23: 1.8 | X23: 27929 | Y23: =X23-X22 -> 24 | Z23: =SUM(Y23*W24) -> 43.2 | AA23: =SUM(Z23*X25) -> 1207958.4 | AB23: 351 | AC23: =AB23-AB22 -> 38 | AD23: 215141 | AE23: =AD23-AD22 -> 46 | AF23: ='Lpg (2)'!B27*2000/85 -> 2000 | AG23: ='Lpg (2)'!C27*1000/85 -> 1000 | AH23: ='Lpg (2)'!D27*1000/85 -> 470.58824 | AI23: =SUM(AF23*2000)+(AG23*1000)+(AH23*1000) -> 5470588.2 | AJ23: =SUM(AI22-AI23) -> 58823.529
A24: =Gen!A29 -> 44305 | B24: ='Summery Report'!E23 -> 0 | C24: =Gen!B29 -> 0.065 | D24: ='Summery Report'!E23 -> 0 | E24: =SUM(E23) -> 1.3262195 | F24: =SUM(J24*E24)/D24 -> #DIV/0! | G24: =SUM(L24*E24)/D24 -> #DIV/0! | H24: =Gen!C29 -> 28202.21 | I24: =Gen!E29 -> 0 | J24: =Gen!T29 -> 2733 | K24: =Gen!AK29 -> 0 | L24: =SUM(J24:K24) -> 2733 | M24: ='Water-Meter'!K64 -> 560.76227 | N24: ='Water-Meter'!E24 -> 58 | P24: 19032 | Q24: =SUM(P24-P23) -> 0 | R24: =SUM(Q24*O24) -> 0 | S24: 6.2 | T24: 17893 | U24: =T24-T23 -> 0 | V24: =SUM(U24*S24) -> 0 | W24: 1.8 | X24: 27953 | Y24: =X24-X23 -> 24 | Z24: =SUM(Y24*#REF!) -> #REF! | AA24: =SUM(Z24*X26) -> #REF! | AB24: 388 | AC24: =AB24-AB23 -> 37 | AD24: 215190 | AE24: =AD24-AD23 -> 49 | AF24: ='Lpg (2)'!B28*2000/85 -> 2000 | AG24: ='Lpg (2)'!C28*1000/85 -> 1000 | AH24: ='Lpg (2)'!D28*1000/85 -> 411.76471 | AI24: =SUM(AF24*2000)+(AG24*1000)+(AH24*1000) -> 5411764.7 | AJ24: =SUM(AI23-AI24) -> 58823.529
A25: =Gen!A30 -> 44306 | B25: ='Summery Report'!E24 -> 0 | C25: =Gen!B30 -> 0.052 | D25: ='Summery Report'!E24 -> 0 | E25: =SUM(E24) -> 1.3262195 | F25: =SUM(J25*E25)/D25 -> #DIV/0! | G25: =SUM(L25*E25)/D25 -> #DIV/0! | H25: =Gen!C30 -> 26707 | I25: =Gen!E30 -> 15000 | J25: =Gen!T30 -> 2856 | K25: =Gen!AK30 -> 0 | L25: =SUM(J25:K25) -> 2856 | M25: ='Water-Meter'!K65 -> 499.23769 | N25: ='Water-Meter'!E25 -> 66 | P25: 19032 | Q25: =SUM(P25-P24) -> 0 | R25: =SUM(Q25*O25) -> 0 | S25: 6.2 | T25: 17909 | U25: =T25-T24 -> 16 | V25: =SUM(U25*S25) -> 99.2 | W25: 1.8 | X25: 27962 | Y25: =X25-X24 -> 9 | Z25: =SUM(Y25*W25) -> 16.2 | AA25: =SUM(Z25*X27) -> 452984.4 | AB25: 518 | AC25: =AB25-AB24 -> 130 | AD25: 215230 | AE25: =AD25-AD24 -> 40 | AF25: ='Lpg (2)'!B29*2000/85 -> 2000 | AG25: ='Lpg (2)'!C29*1000/85 -> 1000 | AH25: ='Lpg (2)'!D29*1000/85 -> 364.70588 | AI25: =SUM(AF25*2000)+(AG25*1000)+(AH25*1000) -> 5364705.9 | AJ25: =SUM(AI24-AI25) -> 47058.824
A26: =Gen!A31 -> 44307 | B26: ='Summery Report'!E25 -> 0 | C26: =Gen!B31 -> 0.026 | D26: ='Summery Report'!E25 -> 0 | E26: =SUM(E25) -> 1.3262195 | F26: =SUM(J26*E26)/D26 -> #DIV/0! | G26: =SUM(L26*E26)/D26 -> #DIV/0! | H26: =Gen!C31 -> 25451.96 | I26: =Gen!E31 -> 0 | J26: =Gen!T31 -> 2700 | K26: =Gen!AK31 -> 0 | L26: =SUM(J26:K26) -> 2700 | M26: ='Water-Meter'!K66 -> 431.38915 | N26: ='Water-Meter'!E26 -> 47 | P26: 19032 | Q26: =SUM(P26-P25) -> 0 | R26: =SUM(Q26*O26) -> 0 | S26: 6.2 | T26: 17917 | U26: =T26-T25 -> 8 | V26: =SUM(U26*S26) -> 49.6 | W26: 1.8 | X26: 27962 | Y26: =X26-X25 -> 0 | Z26: =SUM(Y26*W26) -> 0 | AA26: =SUM(Z26*X28) -> 0 | AB26: 574 | AC26: =AB26-AB25 -> 56 | AD26: 215275 | AE26: =AD26-AD25 -> 45 | AF26: ='Lpg (2)'!B30*2000/85 -> 2000 | AG26: ='Lpg (2)'!C30*1000/85 -> 1000 | AH26: ='Lpg (2)'!D30*1000/85 -> 317.64706 | AI26: =SUM(AF26*2000)+(AG26*1000)+(AH26*1000) -> 5317647.1 | AJ26: =SUM(AI25-AI26) -> 47058.824
A27: =Gen!A32 -> 44308 | B27: ='Summery Report'!E26 -> 0 | C27: =Gen!B32 -> 0 | D27: ='Summery Report'!E26 -> 0 | E27: =SUM(E26) -> 1.3262195 | F27: =SUM(J27*E27)/D27 -> #DIV/0! | G27: =SUM(L27*E27)/D27 -> #DIV/0! | H27: =Gen!C32 -> 39117.1 | I27: =Gen!E32 -> 0 | J27: =Gen!T32 -> 2593 | K27: =Gen!AK32 -> 0 | L27: =SUM(J27:K27) -> 2593 | M27: ='Water-Meter'!K67 -> 388.703 | N27: ='Water-Meter'!E27 -> 50 | P27: 19032 | Q27: =SUM(P27-P26) -> 0 | R27: =SUM(Q27*O27) -> 0 | S27: 6.2 | T27: 17917 | U27: =T27-T26 -> 0 | V27: =SUM(U27*S27) -> 0 | W27: 1.8 | X27: 27962 | Y27: =X27-X26 -> 0 | Z27: =SUM(Y27*W27) -> 0 | AA27: =SUM(Z27*X29) -> 0 | AB27: 574 | AC27: =AB27-AB26 -> 0 | AD27: 215321 | AE27: =AD27-AD26 -> 46 | AF27: ='Lpg (2)'!B31*2000/85 -> 2000 | AG27: ='Lpg (2)'!C31*1000/85 -> 1000 | AH27: ='Lpg (2)'!D31*1000/85 -> 294.11765 | AI27: =SUM(AF27*2000)+(AG27*1000)+(AH27*1000) -> 5294117.6 | AJ27: =SUM(AI26-AI27) -> 23529.412
A28: =Gen!A33 -> 44309 | B28: ='Summery Report'!E27 -> 0 | C28: =Gen!B33 -> 0.013 | D28: ='Summery Report'!E27 -> 0 | E28: =SUM(E27) -> 1.3262195 | F28: =SUM(J28*E28)/D28 -> #DIV/0! | G28: =SUM(L28*E28)/D28 -> #DIV/0! | H28: =Gen!C33 -> 37996.63 | I28: =Gen!E33 -> 0 | J28: =Gen!T33 -> 2657 | K28: =Gen!AK33 -> 0 | L28: =SUM(J28:K28) -> 2657 | M28: ='Water-Meter'!K68 -> 456.41934 | N28: ='Water-Meter'!E28 -> 47 | P28: 19032 | Q28: =SUM(P28-P27) -> 0 | R28: =SUM(Q28*O28) -> 0 | S28: 6.2 | T28: 17917 | U28: =T28-T27 -> 0 | V28: =SUM(U28*S28) -> 0 | W28: 1.8 | X28: 27986 | Y28: =X28-X27 -> 24 | Z28: =SUM(Y28*W28) -> 43.2 | AA28: =SUM(Z28*X30) -> 1210377.6 | AB28: 612 | AC28: =SUM(AB28-AB27) -> 38 | AD28: 215350 | AE28: =AD28-AD27 -> 29 | AF28: ='Lpg (2)'!B32*2000/85 -> 2000 | AG28: ='Lpg (2)'!C32*1000/85 -> 1000 | AH28: ='Lpg (2)'!D32*1000/85 -> 235.29412 | AI28: =SUM(AF28*2000)+(AG28*1000)+(AH28*1000) -> 5235294.1 | AJ28: =SUM(AI27-AI28) -> 58823.529
A29: =Gen!A34 -> 44310 | B29: ='Summery Report'!E28 -> 0 | C29: =Gen!B34 -> 0.026 | D29: ='Summery Report'!E28 -> 0 | E29: =SUM(E28) -> 1.3262195 | F29: =SUM(J29*E29)/D29 -> #DIV/0! | G29: =SUM(L29*E29)/D29 -> #DIV/0! | H29: =Gen!C34 -> 36768.5 | I29: =Gen!E34 -> 0 | J29: =Gen!T34 -> 2629 | K29: =Gen!AK34 -> 0 | L29: =SUM(J29:K29) -> 2629 | M29: ='Water-Meter'!K69 -> 509.22034 | N29: ='Water-Meter'!E29 -> 56 | P29: 19032 | Q29: =SUM(P29-P28) -> 0 | R29: =SUM(Q29*O29) -> 0 | S29: 6.2 | T29: 17917 | U29: =T29-T28 -> 0 | V29: =SUM(U29*S29) -> 0 | W29: 1.8 | X29: 28010 | Y29: =X29-X28 -> 24 | Z29: =SUM(Y29*W29) -> 43.2 | AA29: =SUM(Z29*X31) -> 1210636.8 | AB29: 649 | AC29: =SUM(AB29-AB28) -> 37 | AD29: 215395 | AE29: =AD29-AD28 -> 45 | AF29: ='Lpg (2)'!B33*2000/85 -> 2000 | AG29: ='Lpg (2)'!C33*1000/85 -> 1000 | AH29: ='Lpg (2)'!D33*1000/85 -> 200 | AI29: =SUM(AF29*2000)+(AG29*1000)+(AH29*1000) -> 5200000 | AJ29: =SUM(AI28-AI29) -> 35294.118
A30: =Gen!A35 -> 44311 | B30: ='Summery Report'!E29 -> 0 | C30: =Gen!B35 -> 0.052 | D30: ='Summery Report'!E29 -> 0 | E30: =SUM(E29) -> 1.3262195 | F30: =SUM(J30*E30)/D30 -> #DIV/0! | G30: =SUM(L30*E30)/D30 -> #DIV/0! | H30: =Gen!C35 -> 35570.78 | I30: =Gen!E35 -> 0 | J30: =Gen!T35 -> 2890 | K30: =Gen!AK35 -> 0 | L30: =SUM(J30:K30) -> 2890 | M30: ='Water-Meter'!K70 -> 512.65138 | N30: ='Water-Meter'!E30 -> 46 | P30: 19032 | Q30: =SUM(P30-P29) -> 0 | R30: =SUM(Q30*O30) -> 0 | S30: 6.2 | T30: 17933 | U30: =T30-T29 -> 16 | V30: =SUM(U30*S30) -> 99.2 | W30: 1.7 | X30: 28018 | Y30: =X30-X29 -> 8 | Z30: =SUM(Y30*W30) -> 13.6 | AA30: =SUM(Z30*X32) -> 381398.4 | AB30: 780 | AC30: =SUM(AB30-AB29) -> 131 | AD30: 215441 | AE30: =AD30-AD29 -> 46 | AF30: ='Lpg (2)'!B34*2000/85 -> 2000 | AG30: ='Lpg (2)'!C34*1000/85 -> 1000 | AH30: ='Lpg (2)'!D34*1000/85 -> 176.47059 | AI30: =SUM(AF30*2000)+(AG30*1000)+(AH30*1000) -> 5176470.6 | AJ30: =SUM(AI29-AI30) -> 23529.412
A31: =Gen!A36 -> 44312 | B31: ='Summery Report'!E30 -> 0 | C31: =Gen!B36 -> 0.052 | D31: ='Summery Report'!E30 -> 0 | E31: =SUM(E30) -> 1.3262195 | F31: =SUM(J31*E31)/D31 -> #DIV/0! | G31: =SUM(L31*E31)/D31 -> #DIV/0! | H31: =Gen!C36 -> 34319.66 | I31: =Gen!E36 -> 0 | J31: =Gen!T36 -> 2691 | K31: =Gen!AK36 -> 0 | L31: =SUM(J31:K31) -> 2691 | M31: ='Water-Meter'!K71 -> 560.59805 | N31: ='Water-Meter'!E31 -> 53 | P31: 19032 | Q31: =SUM(P31-P30) -> 0 | R31: =SUM(Q31*O31) -> 0 | S31: 6.2 | T31: 17933 | U31: =T31-T30 -> 0 | V31: =SUM(U31*S31) -> 0 | W31: 1.7 | X31: 28024 | Y31: =X31-X30 -> 6 | Z31: =SUM(Y31*W31) -> 10.2 | AA31: =SUM(Z31*X33) -> 286171.2 | AB31: 789 | AC31: =SUM(AB31-AB30) -> 9 | AD31: 215486 | AE31: =AD31-AD30 -> 45 | AF31: ='Lpg (2)'!B35*2000/85 -> 2000 | AG31: ='Lpg (2)'!C35*1000/85 -> 1000 | AH31: ='Lpg (2)'!D35*1000/85 -> 117.64706 | AI31: =SUM(AF31*2000)+(AG31*1000)+(AH31*1000) -> 5117647.1 | AJ31: =SUM(AI30-AI31) -> 58823.529
A32: =Gen!A37 -> 44313 | B32: ='Summery Report'!E31 -> 0 | C32: =Gen!B37 -> 0.036 | D32: ='Summery Report'!E31 -> 0 | E32: =SUM(E31) -> 1.3262195 | F32: =SUM(J32*E32)/D32 -> #DIV/0! | G32: =SUM(L32*E32)/D32 -> #DIV/0! | H32: =Gen!C37 -> 32937.43 | I32: =Gen!E37 -> 0 | J32: =Gen!T37 -> 2733 | K32: =Gen!AK37 -> 0 | L32: =SUM(J32:K32) -> 2733 | M32: ='Water-Meter'!K72 -> 534.41426 | N32: ='Water-Meter'!E32 -> 43 | O32: 1.9 | P32: 19038 | Q32: =SUM(P32-P31) -> 6 | R32: =SUM(Q32*O32) -> 11.4 | S32: 6.2 | T32: 17933 | U32: =T32-T31 -> 0 | V32: =SUM(U32*S32) -> 0 | W32: 1.7 | X32: 28044 | Y32: =X32-X31 -> 20 | Z32: =SUM(Y32*W32) -> 34 | AA32: =SUM(Z32*X34) -> 954618 | AB32: 824 | AC32: =SUM(AB32-AB31) -> 35 | AD32: 215526 | AE32: =AD32-AD31 -> 40 | AF32: ='Lpg (2)'!B36*2000/85 -> 2000 | AG32: ='Lpg (2)'!C36*1000/85 -> 1000 | AH32: ='Lpg (2)'!D36*1000/85 -> 82.352941 | AI32: =SUM(AF32*2000)+(AG32*1000)+(AH32*1000) -> 5082352.9 | AJ32: =SUM(AI31-AI32) -> 35294.118
A33: =Gen!A38 -> 44314 | B33: ='Summery Report'!E32 -> 0 | C33: =Gen!B38 -> 0.039 | D33: ='Summery Report'!E32 -> 0 | E33: =SUM(E32) -> 1.3262195 | F33: =SUM(J33*E33)/D33 -> #DIV/0! | G33: =SUM(L33*E33)/D33 -> #DIV/0! | H33: =Gen!C38 -> 31790.06 | I33: =Gen!E38 -> 0 | J33: =Gen!T38 -> 2725 | K33: =Gen!AK38 -> 0 | L33: =SUM(J33:K33) -> 2725 | M33: ='Water-Meter'!K73 -> 494.91436 | N33: ='Water-Meter'!E33 -> 61 | O33: 1.9 | P33: 19038 | Q33: =SUM(P33-P32) -> 0 | R33: =SUM(Q33*O33) -> 0 | S33: 6.2 | T33: 17942 | U33: =T33-T32 -> 9 | V33: =SUM(U33*S33) -> 55.8 | W33: 1.7 | X33: 28056 | Y33: =X33-X32 -> 12 | Z33: =SUM(Y33*W33) -> 20.4 | AA33: =SUM(Z33*X35) -> 573260.4 | AB33: 912 | AC33: =SUM(AB33-AB32) -> 88 | AD33: 215600 | AE33: =AD33-AD32 -> 74 | AF33: ='Lpg (2)'!B37*2000/85 -> 2000 | AG33: ='Lpg (2)'!C37*1000/85 -> 1000 | AH33: ='Lpg (2)'!D37*1000/85 -> 58.823529 | AI33: =SUM(AF33*2000)+(AG33*1000)+(AH33*1000) -> 5058823.5 | AJ33: =SUM(AI32-AI33) -> 23529.412
A34: =Gen!A39 -> 44315 | B34: ='Summery Report'!E33 -> 0 | C34: =Gen!B39 -> 0.026 | D34: ='Summery Report'!E33 -> 0 | E34: =SUM(E33) -> 1.3262195 | F34: =SUM(J34*E34)/D34 -> #DIV/0! | G34: =SUM(L34*E34)/D34 -> #DIV/0! | H34: =Gen!C39 -> 30603.73 | I34: =Gen!E39 -> 0 | J34: =Gen!T39 -> 2813 | K34: =Gen!AK39 -> 0 | L34: =SUM(J34:K34) -> 2813 | M34: ='Water-Meter'!K74 -> 492.06046 | N34: ='Water-Meter'!E34 -> 53 | O34: 1.9 | P34: 19038 | Q34: =SUM(P34-P33) -> 0 | R34: =SUM(Q34*O34) -> 0 | S34: 6.2 | T34: 17942 | U34: =T34-T33 -> 0 | V34: =SUM(U34*S34) -> 0 | W34: 1.7 | X34: 28077 | Y34: =X34-X33 -> 21 | Z34: =SUM(Y34*W34) -> 35.7 | AA34: =SUM(Z34*X36) -> 0 | AB34: 942 | AC34: =SUM(AB34-AB33) -> 30 | AD34: 215642 | AE34: =AD34-AD33 -> 42 | AF34: ='Lpg (2)'!B38*2000/85 -> 2000 | AG34: ='Lpg (2)'!C38*1000/85 -> 1000 | AH34: ='Lpg (2)'!D38*1000/85 -> 35.294118 | AI34: =SUM(AF34*2000)+(AG34*1000)+(AH34*1000) -> 5035294.1 | AJ34: =SUM(AI33-AI34) -> 23529.412
A35: =Gen!A40 -> 44316 | B35: ='Summery Report'!E34 -> 0 | C35: =Gen!B40 -> 0.01 | D35: ='Summery Report'!E34 -> 0 | E35: =SUM(E34) -> 1.3262195 | F35: =SUM(J35*E35)/D35 -> #DIV/0! | G35: =SUM(L35*E35)/D35 -> #DIV/0! | H35: =Gen!C40 -> 29254.57 | I35: =Gen!E40 -> 0 | J35: =Gen!T40 -> 2731 | K35: =Gen!AK40 -> 0 | L35: =SUM(J35:K35) -> 2731 | M35: ='Water-Meter'!K75 -> 417.47408 | N35: ='Water-Meter'!E35 -> 58 | O35: 1.9 | P35: 19038 | Q35: =SUM(P35-P34) -> 0 | R35: =SUM(Q35*O35) -> 0 | S35: 6.2 | T35: 17942 | U35: =T35-T34 -> 0 | V35: =SUM(U35*S35) -> 0 | W35: 1.7 | X35: 28101 | Y35: =X35-X34 -> 24 | Z35: =SUM(Y35*W35) -> 40.8 | AA35: =SUM(Z35*X37) -> 0 | AB35: 977 | AC35: =SUM(AB35-AB34) -> 35 | AD35: 215686 | AE35: =AD35-AD34 -> 44 | AF35: ='Lpg (2)'!B39*2000/85 -> 2000 | AG35: ='Lpg (2)'!C39*1000/85 -> 1000 | AH35: ='Lpg (2)'!D39*1000/85 -> 23.529412 | AI35: =SUM(AF35*2000)+(AG35*1000)+(AH35*1000) -> 5023529.4 | AJ35: =SUM(AI34-AI35) -> 11764.706
A36: =Gen!A41 -> 0 | B36: ='Summery Report'!E35 -> 0 | C36: =Gen!B41 -> 0 | D36: ='Summery Report'!E35 -> 0 | E36: =SUM(E35) -> 1.3262195 | F36: =SUM(J36*E36)/D36 -> #DIV/0! | G36: =SUM(L36*E36)/D36 -> #DIV/0! | H36: =Gen!C41 -> 27860.56 | I36: =Gen!E41 -> 0 | J36: =Gen!T41 -> 0 | K36: =Gen!AK41 -> 0 | L36: =SUM(J36:K36) -> 0 | M36: ='Water-Meter'!K76 -> 0 | N36: ='Water-Meter'!E36 -> 0 | Q36: =SUM(P36-P35) -> -19038 | R36: =SUM(Q36*O36) -> 0 | U36: =T36-T35 -> -17942 | V36: =SUM(U36*S36) -> 0 | Y36: =X36-X35 -> -28101 | Z36: =SUM(Y36*W36) -> 0 | AA36: =SUM(Z36*X38) -> 0 | AC36: =SUM(AB36-AB35) -> -977 | AE36: =AD36-AD35 -> -215686 | AF36: ='Lpg (2)'!B40*2000/85 -> 2000 | AG36: ='Lpg (2)'!C40*1000/85 -> 1000 | AH36: ='Lpg (2)'!D40*1000/85 -> 11.764706 | AI36: =SUM(AF36*1000)+(AG36*1000)+(AH36*2000) -> 3023529.4 | AJ36: =SUM(AI35-AI36) -> 2000000
A37: =Gen!A42 -> 0 | B37: 0 | J37: =SUM(J6:J36) -> 87809 | L37: =SUM(J37:K37) -> 87809 | M37: ='Water-Meter'!K77 -> 0 | N37: ='Water-Meter'!E37 -> 0 | Q37: =SUM(P37-P36) -> 0 | R37: =SUM(Q37*O37) -> 0 | U37: =T37-T36 -> 0 | V37: =SUM(U37*S37) -> 0 | Y37: =X37-X36 -> 0 | Z37: =SUM(Y37*W37) -> 0 | AA37: =SUM(Z37*X39) -> 0 | AC37: =SUM(AB37-AB36) -> 0 | AE37: =AD37-AD36 -> 0 | AF37: ='Lpg (2)'!B41*2000/85 -> 0 | AG37: ='Lpg (2)'!C41*1000/85 -> 0 | AH37: ='Lpg (2)'!D41*1000/85 -> 0 | AJ37: =SUM(AI36-AI37) -> 3023529.4

Sheet Kit report
B1: KITCHEN THREE PHASE KWH METER READING | H1: KITCHEN WATER METER READING | M1: AMANI Restaurant WATER METER READING | T1: LAUNDRY THREE PHASE KWH METER READING | Y1: LAUNDRY WATER METER READING
A2: Occ % | B2: DATE | C2: READING TIME | D2: METER READING OPEN | E2: METER READING ClOSE | F2: UNIT USED Kwh | H2: DATE | I2: READING TIME | J2: METER READING OPEN Cbm | K2: METER READING ClOSE Cbm | L2: UNIT USED Cbm | M2: DATE | N2: READING TIME | O2: METER READING OPEN Cbm | P2: METER READING ClOSE Cbm | Q2: UNIT USED Cbm | R2: Cost Per day Elct+Water $ | S2: % as per the total Lodge consumption | T2: DATE | U2: READING TIME | V2: METER READING OPEN (Kwh) | W2: METER READING ClOSE (Kwh) | X2: UNIT USED Kwh | Y2: DATE | Z2: READING TIME | AA2: METER READING OPEN Cbm | AB2: METER READING ClOSE Cbm | AC2: UNIT USED Cbm
A3: =Gen!A11 -> 44287 | B3: Close Last Month | E3: 9204 | F3: X120 | H3: Close Last Month | J3: ='Water-Meter'!G5 -> 75790 | K3: ='Water-Meter'!G5 -> 75790 | M3: Close Last Month | P3: ='Water-Meter'!J5 -> 8362 | T3: Close Last Month | W3: 8073 | X3: =(W3-V3)*200 -> 1614600 | Y3: Close Last Month
A4: =Gen!B11 -> 0.156 | B4: =Gen!A11 -> 44287 | D4: =E3 -> 9204 | E4: 9206 | F4: =SUM(E4-D4)*120 -> 240 | H4: =B4 -> 44287 | J4: ='Water-Meter'!G6 -> 75790 | K4: ='Water-Meter'!G6 -> 75790 | L4: =SUM(K4-J4) -> 0 | M4: =H4 -> 44287 | P4: ='Water-Meter'!J6 -> 8364 | Q4: =N4-O3 -> 0 | R4: =SUM(Q4/1615) -> 0 | S4: =Gen!T11 -> 3175 | T4: =M4 -> 44287 | V4: =W3 -> 8073 | W4: 8075 | X4: =(W4-V4)*200 -> 400 | Y4: =T4 -> 44287 | AB4: ='Water-Meter'!P6 -> 21117 | AC4: =AA4-AB3 -> 0
A5: =Gen!B12 -> 0.169 | B5: =Gen!A12 -> 44288 | D5: =E4 -> 9206 | E5: 9209 | F5: =SUM(E5-D5)*120 -> 360 | H5: =B5 -> 44288 | J5: ='Water-Meter'!G7 -> 75790 | K5: ='Water-Meter'!G7 -> 75790 | L5: =SUM(K5-J5) -> 0 | M5: =H5 -> 44288 | P5: ='Water-Meter'!J7 -> 8366 | Q5: =N5-O4 -> 0 | R5: =SUM(Q5/1615) -> 0 | S5: =Gen!T12 -> 3187 | T5: =M5 -> 44288 | V5: =W4 -> 8075 | W5: 8078 | X5: =(W5-V5)*200 -> 600 | Y5: =T5 -> 44288 | AB5: ='Water-Meter'!P7 -> 21121 | AC5: =AA5-AB4 -> -21117
A6: =Gen!B13 -> 0.23 | B6: =Gen!A13 -> 44289 | D6: =E5 -> 9209 | E6: 9211.7 | F6: =SUM(E6-D6)*120 -> 324 | H6: =B6 -> 44289 | J6: ='Water-Meter'!G8 -> 75790 | K6: ='Water-Meter'!G8 -> 75790 | L6: =SUM(K6-J6) -> 0 | M6: =H6 -> 44289 | P6: ='Water-Meter'!J8 -> 8368 | Q6: =N6-O5 -> 0 | R6: =SUM(Q6/1615) -> 0 | S6: =Gen!T13 -> 3546 | T6: =M6 -> 44289 | V6: =W5 -> 8078 | W6: 8080 | X6: =(W6-V6)*200 -> 400 | Y6: =T6 -> 44289 | AB6: ='Water-Meter'!P8 -> 21126 | AC6: =AA6-AB5 -> -21121
A7: =Gen!B14 -> 0.247 | B7: =Gen!A14 -> 44290 | D7: =E6 -> 9211.7 | E7: 9214.2 | F7: =SUM(E7-D7)*120 -> 300 | H7: =B7 -> 44290 | J7: ='Water-Meter'!G9 -> 75790 | K7: ='Water-Meter'!G9 -> 75790 | L7: =SUM(K7-J7) -> 0 | M7: =H7 -> 44290 | P7: ='Water-Meter'!J9 -> 8369 | Q7: =N7-O6 -> 0 | R7: =SUM(Q7/1615) -> 0 | S7: =Gen!T14 -> 3328 | T7: =M7 -> 44290 | V7: =W6 -> 8080 | W7: 8081.8 | X7: =(W7-V7)*200 -> 360 | Y7: =T7 -> 44290 | AB7: ='Water-Meter'!P9 -> 21130 | AC7: =AA7-AB6 -> -21126
A8: =Gen!B15 -> 0.13 | B8: =Gen!A15 -> 44291 | D8: =E7 -> 9214.2 | E8: 9216.7 | F8: =SUM(E8-D8)*120 -> 300 | H8: =B8 -> 44291 | J8: ='Water-Meter'!G10 -> 75790 | K8: ='Water-Meter'!G10 -> 75790 | L8: =SUM(K8-J8) -> 0 | M8: =H8 -> 44291 | P8: ='Water-Meter'!J10 -> 8371 | Q8: =N8-O7 -> 0 | R8: =SUM(Q8/1615) -> 0 | S8: =Gen!T15 -> 3250 | T8: =M8 -> 44291 | V8: =W7 -> 8081.8 | W8: 8084 | X8: =(W8-V8)*200 -> 440 | Y8: =T8 -> 44291 | AB8: ='Water-Meter'!P10 -> 21134 | AC8: =AA8-AB7 -> -21130
A9: =Gen!B16 -> 0.091 | B9: =Gen!A16 -> 44292 | D9: =E8 -> 9216.7 | E9: 9219.3 | F9: =SUM(E9-D9)*120 -> 312 | H9: =B9 -> 44292 | J9: ='Water-Meter'!G11 -> 75790 | K9: ='Water-Meter'!G11 -> 75790 | L9: =SUM(K9-J9) -> 0 | M9: =H9 -> 44292 | P9: ='Water-Meter'!J11 -> 8372 | Q9: =N9-O8 -> 0 | R9: =SUM(Q9/1615) -> 0 | S9: =Gen!T16 -> 3070 | T9: =M9 -> 44292 | V9: =W8 -> 8084 | W9: 8086.5 | X9: =(W9-V9)*200 -> 500 | Y9: =T9 -> 44292 | AB9: ='Water-Meter'!P11 -> 21142 | AC9: =AA9-AB8 -> -21134
A10: =Gen!B17 -> 0.065 | B10: =Gen!A17 -> 44293 | D10: =E9 -> 9219.3 | E10: 9221.7 | F10: =SUM(E10-D10)*120 -> 288 | H10: =B10 -> 44293 | J10: ='Water-Meter'!G12 -> 75790 | K10: ='Water-Meter'!G12 -> 75790 | L10: =SUM(K10-J10) -> 0 | M10: =H10 -> 44293 | P10: ='Water-Meter'!J12 -> 8374 | Q10: =N10-O9 -> 0 | R10: =SUM(Q10/1615) -> 0 | S10: =Gen!T17 -> 3363 | T10: =M10 -> 44293 | V10: =W9 -> 8086.5 | W10: 8088.4 | X10: =(W10-V10)*200 -> 380 | Y10: =T10 -> 44293 | AB10: ='Water-Meter'!P12 -> 21145 | AC10: =AA10-AB9 -> -21142
A11: =Gen!B18 -> 0.091 | B11: =Gen!A18 -> 44294 | D11: =E10 -> 9221.7 | E11: 9224 | F11: =SUM(E11-D11)*120 -> 276 | H11: =B11 -> 44294 | J11: ='Water-Meter'!G13 -> 75790 | K11: ='Water-Meter'!G13 -> 75790 | L11: =SUM(K11-J11) -> 0 | M11: =H11 -> 44294 | P11: ='Water-Meter'!J13 -> 8376 | Q11: =N11-O10 -> 0 | R11: =SUM(Q11/1615) -> 0 | S11: =Gen!T18 -> 3146 | T11: =M11 -> 44294 | V11: =W10 -> 8088.4 | W11: 8090.2 | X11: =(W11-V11)*200 -> 360 | Y11: =T11 -> 44294 | AB11: ='Water-Meter'!P13 -> 21151 | AC11: =AA11-AB10 -> -21145
A12: =Gen!B19 -> 0.065 | B12: =Gen!A19 -> 44295 | D12: =E11 -> 9224 | E12: 9226 | F12: =SUM(E12-D12)*120 -> 240 | H12: =B12 -> 44295 | J12: ='Water-Meter'!G14 -> 75790 | K12: ='Water-Meter'!G14 -> 75790 | L12: =SUM(K12-J12) -> 0 | M12: =H12 -> 44295 | P12: ='Water-Meter'!J14 -> 8377 | Q12: =N12-O11 -> 0 | R12: =SUM(Q12/1615) -> 0 | S12: =Gen!T19 -> 3314 | T12: =M12 -> 44295 | V12: =W11 -> 8090.2 | W12: 8092.3 | X12: =(W12-V12)*200 -> 420 | Y12: =T12 -> 44295 | AB12: ='Water-Meter'!P14 -> 21155 | AC12: =AA12-AB11 -> -21151
A13: =Gen!B20 -> 0.052 | B13: =Gen!A20 -> 44296 | D13: =E12 -> 9226 | E13: 9227.8 | F13: =SUM(E13-D13)*120 -> 216 | H13: =B13 -> 44296 | J13: ='Water-Meter'!G15 -> 75790 | K13: ='Water-Meter'!G15 -> 75790 | L13: =SUM(K13-J13) -> 0 | M13: =H13 -> 44296 | P13: ='Water-Meter'!J15 -> 8379 | Q13: =N13-O12 -> 0 | R13: =SUM(Q13/1615) -> 0 | S13: =Gen!T20 -> 3168 | T13: =M13 -> 44296 | V13: =W12 -> 8092.3 | W13: 8093.6 | X13: =(W13-V13)*200 -> 260 | Y13: =T13 -> 44296 | AB13: ='Water-Meter'!P15 -> 21158 | AC13: =AA13-AB12 -> -21155
A14: =Gen!B21 -> 0.104 | B14: =Gen!A21 -> 44297 | D14: =E13 -> 9227.8 | E14: 9229.6 | F14: =SUM(E14-D14)*120 -> 216 | H14: =B14 -> 44297 | J14: ='Water-Meter'!G16 -> 75790 | K14: ='Water-Meter'!G16 -> 75790 | L14: =SUM(K14-J14) -> 0 | M14: =H14 -> 44297 | P14: ='Water-Meter'!J16 -> 8381 | Q14: 8095 | R14: =SUM(Q14/1615) -> 5.0123839 | S14: =Gen!T21 -> 3237 | T14: =M14 -> 44297 | V14: =W13 -> 8093.6 | W14: 8095 | X14: =(W14-V14)*200 -> 280 | Y14: =T14 -> 44297 | AB14: ='Water-Meter'!P16 -> 21161 | AC14: 20490
A15: =Gen!B22 -> 0.104 | B15: =Gen!A22 -> 44298 | D15: =E14 -> 9229.6 | E15: 9231.6 | F15: =SUM(E15-D15)*120 -> 240 | H15: =B15 -> 44298 | J15: ='Water-Meter'!G17 -> 75790 | K15: ='Water-Meter'!G17 -> 75790 | L15: =SUM(K15-J15) -> 0 | M15: =H15 -> 44298 | P15: ='Water-Meter'!J17 -> 8382 | Q15: =N15-O14 -> 0 | R15: =SUM(Q15/1615) -> 0 | S15: =Gen!T22 -> 3269 | T15: =M15 -> 44298 | V15: =W14 -> 8095 | W15: 8096.2 | X15: =(W15-V15)*200 -> 240 | Y15: =T15 -> 44298 | AB15: ='Water-Meter'!P17 -> 21167 | AC15: =AA15-AB14 -> -21161
A16: =Gen!B23 -> 0.013 | B16: =Gen!A23 -> 44299 | D16: =E15 -> 9231.6 | E16: 9233.4 | F16: =SUM(E16-D16)*120 -> 216 | H16: =B16 -> 44299 | J16: ='Water-Meter'!G18 -> 75790 | K16: ='Water-Meter'!G18 -> 75790 | L16: =SUM(K16-J16) -> 0 | M16: =H16 -> 44299 | P16: ='Water-Meter'!J18 -> 8383 | Q16: =N16-O15 -> 0 | R16: =SUM(Q16/1615) -> 0 | S16: =Gen!T23 -> 2665 | T16: =M16 -> 44299 | V16: =W15 -> 8096.2 | W16: 8097.7 | X16: =(W16-V16)*200 -> 300 | Y16: =T16 -> 44299 | AB16: ='Water-Meter'!P18 -> 21169 | AC16: =AA16-AB15 -> -21167
A17: =Gen!B24 -> 0 | B17: =Gen!A24 -> 44300 | D17: =E16 -> 9233.4 | E17: 9235.3 | F17: =SUM(E17-D17)*120 -> 228 | H17: =B17 -> 44300 | J17: ='Water-Meter'!G19 -> 75790 | K17: ='Water-Meter'!G19 -> 75790 | L17: =SUM(K17-J17) -> 0 | M17: =H17 -> 44300 | P17: ='Water-Meter'!J19 -> 8384 | Q17: =N17-O16 -> 0 | R17: =SUM(Q17/1615) -> 0 | S17: =Gen!T24 -> 2643 | T17: =M17 -> 44300 | V17: =W16 -> 8097.7 | W17: 8098.6 | X17: =(W17-V17)*200 -> 180 | Y17: =T17 -> 44300 | AB17: ='Water-Meter'!P19 -> 21171 | AC17: =AA17-AB16 -> -21169
A18: =Gen!B25 -> 0 | B18: =Gen!A25 -> 44301 | D18: =E17 -> 9235.3 | E18: 9237.1 | F18: =SUM(E18-D18)*120 -> 216 | H18: =B18 -> 44301 | J18: ='Water-Meter'!G20 -> 75790 | K18: ='Water-Meter'!G20 -> 75790 | L18: =SUM(K18-J18) -> 0 | M18: =H18 -> 44301 | O18: ='Water-Meter'!J20 -> 8385 | P18: ='Water-Meter'!J20 -> 8385 | Q18: =N18-O17 -> 0 | R18: =SUM(Q18/1615) -> 0 | S18: =Gen!T25 -> 2618 | T18: =M18 -> 44301 | V18: =W17 -> 8098.6 | W18: 8100.1 | X18: =(W18-V18)*200 -> 300 | Y18: =T18 -> 44301 | AB18: ='Water-Meter'!P20 -> 21176 | AC18: =AA18-AB17 -> -21171
A19: =Gen!B26 -> 0 | B19: =Gen!A26 -> 44302 | D19: =E18 -> 9237.1 | E19: 9238.8 | F19: =SUM(E19-D19)*120 -> 204 | H19: =B19 -> 44302 | J19: ='Water-Meter'!G21 -> 75790 | K19: ='Water-Meter'!G21 -> 75790 | L19: =SUM(K19-J19) -> 0 | M19: =H19 -> 44302 | O19: ='Water-Meter'!J21 -> 8387 | P19: ='Water-Meter'!J21 -> 8387 | Q19: =N19-O18 -> -8385 | R19: =SUM(Q19/1615) -> -5.1919505 | S19: =Gen!T26 -> 2546 | T19: =M19 -> 44302 | V19: =W18 -> 8100.1 | W19: 8101.1 | X19: =(W19-V19)*200 -> 200 | Y19: =T19 -> 44302 | AB19: ='Water-Meter'!P21 -> 21178 | AC19: =AA19-AB18 -> -21176
A20: =Gen!B27 -> 0.013 | B20: =Gen!A27 -> 44303 | D20: =E19 -> 9238.8 | E20: 9240.8 | F20: =SUM(E20-D20)*120 -> 240 | H20: =B20 -> 44303 | J20: ='Water-Meter'!G22 -> 75790 | K20: ='Water-Meter'!G22 -> 75790 | L20: =SUM(K20-J20) -> 0 | M20: =H20 -> 44303 | O20: ='Water-Meter'!J22 -> 8389 | P20: ='Water-Meter'!J22 -> 8389 | Q20: =N20-O19 -> -8387 | R20: =SUM(Q20/1615) -> -5.1931889 | S20: =Gen!T27 -> 2694 | T20: =M20 -> 44303 | V20: =W19 -> 8101.1 | W20: 8101.9 | X20: =(W20-V20)*200 -> 160 | Y20: =T20 -> 44303 | AB20: ='Water-Meter'!P22 -> 21183 | AC20: =AA20-AB19 -> -21178
A21: =Gen!B28 -> 0.039 | B21: =Gen!A28 -> 44304 | D21: =E20 -> 9240.8 | E21: 9242.9 | F21: =SUM(E21-D21)*120 -> 252 | H21: =B21 -> 44304 | J21: ='Water-Meter'!G23 -> 75790 | K21: ='Water-Meter'!G23 -> 75790 | L21: =SUM(K21-J21) -> 0 | M21: =H21 -> 44304 | O21: ='Water-Meter'!J23 -> 8390 | P21: ='Water-Meter'!J23 -> 8390 | Q21: =N21-O20 -> -8389 | R21: =SUM(Q21/1615) -> -5.1944272 | S21: =Gen!T28 -> 2839 | T21: =M21 -> 44304 | V21: =W20 -> 8101.9 | W21: 8103.3 | X21: =(W21-V21)*200 -> 280 | Y21: =T21 -> 44304 | AB21: ='Water-Meter'!P23 -> 21187 | AC21: =AA21-AB20 -> -21183
A22: =Gen!B29 -> 0.065 | B22: =Gen!A29 -> 44305 | D22: =E21 -> 9242.9 | E22: 9245 | F22: =SUM(E22-D22)*120 -> 252 | H22: =B22 -> 44305 | J22: ='Water-Meter'!G24 -> 75790 | K22: ='Water-Meter'!G24 -> 75790 | L22: =SUM(K22-J22) -> 0 | M22: =H22 -> 44305 | O22: ='Water-Meter'!J24 -> 8391 | P22: ='Water-Meter'!J24 -> 8391 | Q22: =N22-O21 -> -8390 | R22: =SUM(Q22/1615) -> -5.1950464 | S22: =Gen!T29 -> 2733 | T22: =M22 -> 44305 | V22: =W21 -> 8103.3 | W22: 8104.6 | X22: =(W22-V22)*200 -> 260 | Y22: =T22 -> 44305 | AB22: ='Water-Meter'!P24 -> 21191 | AC22: =AA22-AB21 -> -21187
A23: =Gen!B30 -> 0.052 | B23: =Gen!A30 -> 44306 | D23: =E22 -> 9245 | E23: 9247.1 | F23: =SUM(E23-D23)*120 -> 252 | H23: =B23 -> 44306 | J23: ='Water-Meter'!G25 -> 75790 | K23: ='Water-Meter'!G26 -> 75790 | L23: =SUM(K23-J23) -> 0 | M23: =H23 -> 44306 | O23: ='Water-Meter'!J25 -> 8392 | P23: ='Water-Meter'!J25 -> 8392 | Q23: =N23-O22 -> -8391 | R23: =SUM(Q23/1615) -> -5.1956656 | S23: =Gen!T30 -> 2856 | T23: =M23 -> 44306 | V23: =W22 -> 8104.6 | W23: 8105.8 | X23: =(W23-V23)*200 -> 240 | Y23: =T23 -> 44306 | AB23: ='Water-Meter'!P25 -> 21194 | AC23: =AA23-AB22 -> -21191
A24: =Gen!B31 -> 0.026 | B24: =Gen!A31 -> 44307 | D24: =SUM(E23) -> 9247.1 | E24: 9249 | F24: =SUM(E24-D24)*120 -> 228 | H24: =B24 -> 44307 | J24: ='Water-Meter'!G26 -> 75790 | K24: ='Water-Meter'!G27 -> 75790 | L24: =SUM(K24-J24) -> 0 | M24: =H24 -> 44307 | O24: ='Water-Meter'!J26 -> 8395 | P24: ='Water-Meter'!J26 -> 8395 | Q24: =N24-O23 -> -8392 | R24: =SUM(Q24/1615) -> -5.1962848 | S24: =Gen!T31 -> 2700 | T24: =M24 -> 44307 | V24: =W23 -> 8105.8 | W24: 8107.2 | X24: =(W24-V24)*200 -> 280 | Y24: =T24 -> 44307 | AB24: ='Water-Meter'!P26 -> 21197 | AC24: =AA24-AB23 -> -21194
A25: =Gen!B32 -> 0 | B25: =Gen!A32 -> 44308 | D25: =SUM(E24) -> 9249 | E25: 9250.9 | F25: =SUM(E25-D25)*120 -> 228 | H25: =B25 -> 44308 | J25: ='Water-Meter'!G27 -> 75790 | K25: ='Water-Meter'!G28 -> 75790 | L25: =SUM(K25-J25) -> 0 | M25: =H25 -> 44308 | O25: ='Water-Meter'!J27 -> 8397 | P25: ='Water-Meter'!J27 -> 8397 | Q25: =N25-O24 -> -8395 | R25: =SUM(Q25/1615) -> -5.1981424 | S25: =Gen!T32 -> 2593 | T25: =M25 -> 44308 | V25: =W24 -> 8107.2 | W25: 8108.9 | X25: =(W25-V25)*200 -> 340 | Y25: =T25 -> 44308 | AB25: ='Water-Meter'!P27 -> 21203 | AC25: =AA25-AB24 -> -21197
A26: =Gen!B33 -> 0.013 | B26: =Gen!A33 -> 44309 | D26: =SUM(E25) -> 9250.9 | E26: 9252.9 | F26: =SUM(E26-D26)*120 -> 240 | H26: =B26 -> 44309 | J26: ='Water-Meter'!G28 -> 75790 | K26: ='Water-Meter'!G29 -> 75790 | L26: =SUM(K26-J26) -> 0 | M26: =H26 -> 44309 | O26: ='Water-Meter'!J28 -> 8398 | P26: ='Water-Meter'!J28 -> 8398 | Q26: =N26-O25 -> -8397 | R26: =SUM(Q26/1615) -> -5.1993808 | S26: =Gen!T33 -> 2657 | T26: =M26 -> 44309 | V26: =W25 -> 8108.9 | W26: 8110.6 | X26: =(W26-V26)*200 -> 340 | Y26: =T26 -> 44309 | AB26: ='Water-Meter'!P28 -> 21205 | AC26: =AA26-AB25 -> -21203
A27: =Gen!B34 -> 0.026 | B27: =Gen!A34 -> 44310 | D27: =SUM(E26) -> 9252.9 | E27: 9255 | F27: =SUM(E27-D27)*120 -> 252 | H27: =B27 -> 44310 | J27: ='Water-Meter'!G29 -> 75790 | K27: ='Water-Meter'!G30 -> 75790 | L27: =SUM(K27-J27) -> 0 | M27: =H27 -> 44310 | O27: ='Water-Meter'!J29 -> 8399 | P27: ='Water-Meter'!J29 -> 8399 | Q27: =N27-O26 -> -8398 | R27: =SUM(Q27/1615) -> -5.2 | S27: =Gen!T34 -> 2629 | T27: =M27 -> 44310 | V27: =W26 -> 8110.6 | W27: 8111.3 | X27: =(W27-V27)*200 -> 140 | Y27: =T27 -> 44310 | AB27: ='Water-Meter'!P29 -> 21205 | AC27: =AA27-AB26 -> -21205
A28: =Gen!B35 -> 0.052 | B28: =Gen!A35 -> 44311 | D28: =SUM(E27) -> 9255 | E28: 9257.5 | F28: =SUM(E28-D28)*120 -> 300 | H28: =B28 -> 44311 | J28: ='Water-Meter'!G30 -> 75790 | K28: ='Water-Meter'!G31 -> 75790 | L28: =SUM(K28-J28) -> 0 | M28: =H28 -> 44311 | O28: ='Water-Meter'!J30 -> 8401 | P28: ='Water-Meter'!J30 -> 8401 | Q28: =N28-O27 -> -8399 | R28: =SUM(Q28/1615) -> -5.2006192 | S28: =Gen!T35 -> 2890 | T28: =M28 -> 44311 | V28: =W27 -> 8111.3 | W28: 8112.7 | X28: =(W28-V28)*200 -> 280 | Y28: =T28 -> 44311 | AB28: ='Water-Meter'!P30 -> 21209 | AC28: =AA28-AB27 -> -21205
A29: =Gen!B36 -> 0.052 | B29: =Gen!A36 -> 44312 | D29: =SUM(E28) -> 9257.5 | E29: 9259.8 | F29: =SUM(E29-D29)*120 -> 276 | H29: =B29 -> 44312 | J29: ='Water-Meter'!G31 -> 75790 | K29: ='Water-Meter'!G32 -> 75790 | L29: =SUM(K29-J29) -> 0 | M29: =H29 -> 44312 | O29: ='Water-Meter'!J31 -> 8404 | P29: ='Water-Meter'!J31 -> 8404 | Q29: =N29-O28 -> -8401 | R29: =SUM(Q29/1615) -> -5.2018576 | S29: =Gen!T36 -> 2691 | T29: =M29 -> 44312 | V29: =W28 -> 8112.7 | W29: 8113.8 | X29: =(W29-V29)*200 -> 220 | Y29: =T29 -> 44312 | AB29: ='Water-Meter'!P31 -> 21213 | AC29: =AA29-AB28 -> -21209
A30: =Gen!B37 -> 0.036 | B30: =Gen!A37 -> 44313 | D30: =SUM(E29) -> 9259.8 | E30: 9262.2 | F30: =SUM(E30-D30)*120 -> 288 | H30: =B30 -> 44313 | J30: ='Water-Meter'!G32 -> 75790 | K30: ='Water-Meter'!G33 -> 75790 | L30: =SUM(K30-J30) -> 0 | M30: =H30 -> 44313 | O30: ='Water-Meter'!J32 -> 8406 | P30: ='Water-Meter'!J32 -> 8406 | Q30: =N30-O29 -> -8404 | R30: =SUM(Q30/1615) -> -5.2037152 | S30: =Gen!T37 -> 2733 | T30: =M30 -> 44313 | V30: =W29 -> 8113.8 | W30: 8115.2 | X30: =(W30-V30)*200 -> 280 | Y30: =T30 -> 44313 | AB30: ='Water-Meter'!P32 -> 21217 | AC30: =AA30-AB29 -> -21213
A31: =Gen!B38 -> 0.039 | B31: =Gen!A38 -> 44314 | D31: =SUM(E30) -> 9262.2 | E31: 9264.4 | F31: =SUM(E31-D31)*120 -> 264 | H31: =B31 -> 44314 | J31: ='Water-Meter'!G33 -> 75790 | K31: ='Water-Meter'!G34 -> 75790 | L31: =SUM(K31-J31) -> 0 | M31: =H31 -> 44314 | O31: ='Water-Meter'!J33 -> 8408 | P31: ='Water-Meter'!J33 -> 8408 | Q31: =N31-O30 -> -8406 | R31: =SUM(Q31/1615) -> -5.2049536 | S31: =Gen!T38 -> 2725 | T31: =M31 -> 44314 | V31: =W30 -> 8115.2 | W31: 8116.2 | X31: =(W31-V31)*200 -> 200 | Y31: =T31 -> 44314 | AB31: ='Water-Meter'!P33 -> 21221 | AC31: =AA31-AB30 -> -21217
A32: =Gen!B39 -> 0.026 | B32: =Gen!A39 -> 44315 | D32: =SUM(E31) -> 9264.4 | E32: 9266.8 | F32: =SUM(E32-D32)*120 -> 288 | H32: =B32 -> 44315 | J32: ='Water-Meter'!G34 -> 75790 | K32: ='Water-Meter'!G34 -> 75790 | L32: =SUM(K32-J32) -> 0 | M32: =H32 -> 44315 | O32: ='Water-Meter'!J34 -> 8409 | P32: ='Water-Meter'!J34 -> 8409 | Q32: =N32-O31 -> -8408 | R32: =SUM(Q32/1615) -> -5.206192 | S32: =Gen!T39 -> 2813 | T32: =M32 -> 44315 | V32: =W31 -> 8116.2 | W32: 8117.9 | X32: =(W32-V32)*200 -> 340 | Y32: =T32 -> 44315 | AB32: ='Water-Meter'!P34 -> 21227 | AC32: =AA32-AB31 -> -21221
A33: =Gen!B40 -> 0.01 | B33: =Gen!A40 -> 44316 | D33: =SUM(E32) -> 9266.8 | E33: 9269.1 | F33: =SUM(E33-D33)*120 -> 276 | H33: =B33 -> 44316 | J33: ='Water-Meter'!G35 -> 75790 | K33: ='Water-Meter'!G35 -> 75790 | L33: =SUM(K33-J33) -> 0 | M33: =H33 -> 44316 | O33: ='Water-Meter'!J35 -> 8410 | P33: ='Water-Meter'!J35 -> 8410 | Q33: =N33-O32 -> -8409 | R33: =SUM(Q33/1615) -> -5.2068111 | S33: =Gen!T40 -> 2731 | T33: =M33 -> 44316 | V33: =W32 -> 8117.9 | W33: 8119.9 | X33: =(W33-V33)*200 -> 400 | Y33: =T33 -> 44316 | AB33: ='Water-Meter'!P35 -> 21230 | AC33: =AA33-AB32 -> -21227
A34: =Gen!B41 -> 0 | D34: =SUM(E33) -> 9269.1 | F34: =SUM(E34-D34)*120 -> -1112292 | H34: =B34 -> 0 | J34: ='Water-Meter'!G36 -> 0 | K34: ='Water-Meter'!G36 -> 0 | L34: =SUM(K34-J34) -> 0 | M34: =H34 -> 0 | O34: ='Water-Meter'!J36 -> 0 | P34: ='Water-Meter'!J36 -> 0 | Q34: =N34-O33 -> -8410 | R34: =SUM(Q34/1615) -> -5.2074303 | S34: =Gen!T41 -> 0 | T34: =M34 -> 0 | V34: =SUM(W33) -> 8119.9 | X34: =(W34-V34)*200 -> -1623980 | Y34: =T34 -> 0 | AB34: ='Water-Meter'!P36 -> 0 | AC34: =AA34-AB33 -> -21230
A35: =[1]Gen!B42 -> #REF! | B35: =[1]Gen!A42 -> #REF! | D35: =SUM(E34) -> 0 | F35: =SUM(F4:F6) -> 924 | H35: =B35 -> #REF! | J35: =SUM(K34) -> 0 | K35: ='Water-Meter'!G37 -> 0 | L35: =SUM(L5:L34) -> 0 | M35: =H35 -> #REF! | P35: ='Water-Meter'!J37 -> 0 | Q35: =N35-O34 -> 0 | R35: =SUM(Q35/1615) -> 0 | S35: =Gen!T42 -> 0 | T35: =M35 -> #REF! | V35: =SUM(W34) -> 0 | X35: =(W35-V35)*200 -> 0 | Y35: =T35 -> #REF! | AB35: ='Water-Meter'!P37 -> 0 | AC35: =AA35-AB34 -> 0
X36: =SUM(X4:X6) -> 1400

Sheet Summery Report
A1: =A5 -> 44287
A4: Date | B4: Gen Set Hours Working | C4: Occ% | D4: Total OCC Room | E4: Guest Room Occ | F4: Total Kwh Generated | G4: Diesel consumed by Gen (Ltrs) | H4: Diesel consumed by Vehicle (Ltrs) | I4: Total diesel consumed (Ltrs) | J4: Balance stock of Diesel (Ltrs) | K4: Water consumed | L4: Gas consumed (KG)
A5: =Gen!A11 -> 44287 | B5: ='Daily report Gen'!Z6 -> 24 | C5: =Gen!B11 -> 0.156 | D5: =E5 -> 1.3 | E5: 1.3 | F5: =Gen!U11 -> 0.41777953 | G5: =Gen!T9 -> 0 | H5: =Gen!AK11 -> 0 | I5: =SUM(G5:H5) -> 0 | J5: =Gen!C11 -> 34515.97 | K5: ='Water-Meter'!E6 -> 89 | L5: ='Lpg (2)'!G10 -> 84.48 | M5: =SUM(#REF!-#REF!) -> #REF!
A6: =Gen!A12 -> 44288 | B6: ='Daily report Gen'!Z7 -> 48 | C6: =Gen!B12 -> 0.169 | D6: =E6 -> 2.6 | E6: 2.6 | F6: =Gen!U12 -> 0.41067775 | G6: =Gen!T10 -> 0 | H6: =Gen!AK12 -> 0 | I6: =SUM(G6:H6) -> 0 | J6: =Gen!C12 -> 33044.09 | K6: ='Water-Meter'!E7 -> 117 | L6: ='Lpg (2)'!G11 -> 86.548 | M6: =SUM(#REF!-#REF!) -> #REF!
A7: =Gen!A13 -> 44289 | B7: ='Daily report Gen'!Z8 -> 25 | C7: =Gen!B13 -> 0.23 | D7: =E7 -> 2.6 | E7: 2.6 | F7: =Gen!U13 -> 0.4022758 | G7: =Gen!T11 -> 3175 | H7: =Gen!AK13 -> 0 | I7: =SUM(G7:H7) -> 3175 | J7: =Gen!C13 -> 31510.36 | K7: ='Water-Meter'!E8 -> 167 | L7: ='Lpg (2)'!G12 -> 88.968 | M7: =SUM(#REF!-#REF!) -> #REF!
A8: =Gen!A14 -> 44290 | B8: ='Daily report Gen'!Z9 -> 24 | C8: =Gen!B14 -> 0.247 | D8: =E8 -> 5.19 | E8: 5.19 | F8: =Gen!U14 -> 0.40958834 | G8: =Gen!T12 -> 3187 | H8: =Gen!AK14 -> 0 | I8: =SUM(G8:H8) -> 3187 | J8: =Gen!C14 -> 29944.6 | K8: ='Water-Meter'!E9 -> 70 | L8: ='Lpg (2)'!G13 -> 86.372 | M8: =SUM(#REF!-#REF!) -> #REF!
A9: =Gen!A15 -> 44291 | B9: ='Daily report Gen'!Z10 -> 24 | C9: =Gen!B15 -> 0.13 | D9: =E9 -> 7.79 | E9: 7.79 | F9: =Gen!U15 -> 0.40968615 | G9: =Gen!T13 -> 3546 | H9: =Gen!AK15 -> 0 | I9: =SUM(G9:H9) -> 3546 | J9: =Gen!C15 -> 28581.49 | K9: ='Water-Meter'!E10 -> 59 | L9: ='Lpg (2)'!G14 -> 88.528 | M9: =SUM(#REF!-#REF!) -> #REF!
A10: =Gen!A16 -> 44292 | B10: ='Daily report Gen'!Z11 -> 25 | C10: =Gen!B16 -> 0.091 | D10: =E10 -> 5.19 | E10: 5.19 | F10: =Gen!U16 -> 0.41273616 | G10: =Gen!T14 -> 3328 | H10: =Gen!AK16 -> 0 | I10: =SUM(G10:H10) -> 3328 | J10: =Gen!C16 -> 27031.5 | K10: ='Water-Meter'!E11 -> 210 | L10: ='Lpg (2)'!G15 -> 82.896 | M10: =SUM(#REF!-#REF!) -> #REF!
A11: =Gen!A17 -> 44293 | B11: ='Daily report Gen'!Z12 -> 24 | C11: =Gen!B17 -> 0.065 | D11: =E11 -> 11.69 | E11: 11.69 | F11: =Gen!U17 -> 0.40155219 | G11: =Gen!T15 -> 3250 | H11: =Gen!AK17 -> 0 | I11: =SUM(G11:H11) -> 3250 | J11: =Gen!C17 -> 43721.96 | K11: ='Water-Meter'!E12 -> 60 | L11: ='Lpg (2)'!G16 -> 80.212 | M11: =SUM(#REF!-#REF!) -> #REF!
A12: =Gen!A18 -> 44294 | B12: ='Daily report Gen'!Z13 -> 24 | C12: =Gen!B18 -> 0.091 | D12: =E12 -> 12.99 | E12: 12.99 | F12: =Gen!U18 -> 0.40188175 | G12: =Gen!T16 -> 3070 | H12: =Gen!AK18 -> 0 | I12: =SUM(G12:H12) -> 3070 | J12: =Gen!C18 -> 42252.4 | K12: ='Water-Meter'!E13 -> 75 | L12: ='Lpg (2)'!G17 -> 83.996 | M12: =SUM(#REF!-#REF!) -> #REF!
A13: =Gen!A19 -> 44295 | B13: ='Daily report Gen'!Z14 -> 49 | C13: =Gen!B19 -> 0.065 | D13: =E13 -> 15.58 | E13: 15.58 | F13: =Gen!U19 -> 0.3941732 | G13: =Gen!T17 -> 3363 | H13: =Gen!AK19 -> 0 | I13: =SUM(G13:H13) -> 3363 | J13: =Gen!C19 -> 40831.76 | K13: ='Water-Meter'!E14 -> 47 | L13: ='Lpg (2)'!G18 -> 44 | M13: =SUM(#REF!-#REF!) -> #REF!
A14: =Gen!A20 -> 44296 | B14: ='Daily report Gen'!Z15 -> #REF! | C14: =Gen!B20 -> 0.052 | D14: =E14 -> 15.58 | E14: 15.58 | F14: =Gen!U20 -> 0.39324811 | G14: =Gen!T18 -> 3146 | H14: =Gen!AK20 -> 0 | I14: =SUM(G14:H14) -> 3146 | J14: =Gen!C20 -> 39223.36 | K14: ='Water-Meter'!E15 -> 46 | L14: ='Lpg (2)'!G19 -> 88 | M14: =SUM(#REF!-#REF!) -> #REF!
A15: =Gen!A21 -> 44297 | B15: ='Daily report Gen'!Z16 -> 25 | C15: =Gen!B21 -> 0.104 | D15: =E15 -> 11.69 | E15: 11.69 | F15: =Gen!U21 -> 0.3966574 | G15: =Gen!T19 -> 3314 | H15: =Gen!AK21 -> 0 | I15: =SUM(G15:H15) -> 3314 | J15: =Gen!C21 -> 37865.55 | K15: ='Water-Meter'!E16 -> 50 | L15: ='Lpg (2)'!G20 -> 57.244 | M15: =SUM(#REF!-#REF!) -> #REF!
A16: =Gen!A22 -> 44298 | B16: ='Daily report Gen'!Z17 -> 24 | C16: =Gen!B22 -> 0.104 | D16: =E16 -> 12.99 | E16: 12.99 | F16: =Gen!U22 -> 0.35691343 | G16: =Gen!T20 -> 3168 | H16: =Gen!AK22 -> 0 | I16: =SUM(G16:H16) -> 3168 | J16: =Gen!C22 -> 36556.57 | K16: ='Water-Meter'!E17 -> 61 | L16: ='Lpg (2)'!G21 -> 64.328 | M16: =SUM(#REF!-#REF!) -> #REF!
... A21: =Gen!A27 -> 44303 | B21: ='Daily report Gen'!Z22 -> 25 | C21: =Gen!B27 -> 0.013 | D21: =E21 -> 6.49 | E21: 6.49 | F21: =Gen!U27 -> 0.4093467 | G21: =Gen!T25 -> 2618 | H21: =Gen!AK27 -> 0 | I21: =SUM(G21:H21) -> 2618 | J21: =Gen!C27 -> 30616.6 | K21: ='Water-Meter'!E22 -> 52 | L21: ='Lpg (2)'!G26 -> 56.848 | M21: =SUM(#REF!-#REF!) -> #REF!
A22: =Gen!A28 -> 44304 | B22: ='Daily report Gen'!Z23 -> 24 | C22: =Gen!B28 -> 0.039 | D22: =E22 -> 0 | F22: =Gen!U28 -> 0.41046143 | G22: =Gen!T26 -> 2546 | H22: =Gen!AK28 -> 0 | I22: =SUM(G22:H22) -> 2546 | J22: =Gen!C28 -> 29367.51 | K22: ='Water-Meter'!E23 -> 53 | L22: ='Lpg (2)'!G27 -> 61.952 | M22: =SUM(#REF!-#REF!) -> #REF!
A23: =Gen!A29 -> 44305 | B23: ='Daily report Gen'!Z24 -> 24 | C23: =Gen!B29 -> 0.065 | D23: =E23 -> 0 | F23: =Gen!U29 -> 0.42041712 | G23: =Gen!T27 -> 2694 | H23: =Gen!AK29 -> 0 | I23: =SUM(G23:H23) -> 2694 | J23: =Gen!C29 -> 28202.21 | K23: ='Water-Meter'!E24 -> 58 | L23: ='Lpg (2)'!G28 -> 67.804 | M23: =SUM(#REF!-#REF!) -> #REF!
A24: =Gen!A30 -> 44306 | B24: ='Daily report Gen'!Z25 -> 24 | C24: =Gen!B30 -> 0.052 | D24: =E24 -> 0 | F24: =Gen!U30 -> 0.41581933 | G24: =Gen!T28 -> 2839 | H24: =Gen!AK30 -> 0 | I24: =SUM(G24:H24) -> 2839 | J24: =Gen!C30 -> 26707 | K24: ='Water-Meter'!E25 -> 66 | L24: ='Lpg (2)'!G29 -> 65.956 | M24: =SUM(#REF!-#REF!) -> #REF!
A25: =Gen!A31 -> 44307 | B25: ='Daily report Gen'!Z26 -> 24 | C25: =Gen!B31 -> 0.026 | D25: =E25 -> 0 | F25: =Gen!U31 -> 0.41387407 | G25: =Gen!T29 -> 2733 | H25: =Gen!AK31 -> 0 | I25: =SUM(G25:H25) -> 2733 | J25: =Gen!C31 -> 25451.96 | K25: ='Water-Meter'!E26 -> 47 | L25: ='Lpg (2)'!G30 -> 65.56 | M25: =SUM(#REF!-#REF!) -> #REF!
A26: =Gen!A32 -> 44308 | B26: ='Daily report Gen'!Z27 -> 24 | C26: =Gen!B32 -> 0 | D26: =E26 -> 0 | F26: =Gen!U32 -> 0.41092943 | G26: =Gen!T30 -> 2856 | H26: =Gen!AK32 -> 0 | I26: =SUM(G26:H26) -> 2856 | J26: =Gen!C32 -> 39117.1 | K26: ='Water-Meter'!E27 -> 50 | L26: ='Lpg (2)'!G31 -> 58.212 | M26: =SUM(#REF!-#REF!) -> #REF!
A27: =Gen!A33 -> 44309 | B27: ='Daily report Gen'!Z28 -> 24 | C27: =Gen!B33 -> 0.013 | D27: =E27 -> 0 | F27: =Gen!U33 -> 0.40950696 | G27: =Gen!T31 -> 2700 | H27: =Gen!AK33 -> 0 | I27: =SUM(G27:H27) -> 2700 | J27: =Gen!C33 -> 37996.63 | K27: ='Water-Meter'!E28 -> 47 | L27: ='Lpg (2)'!G32 -> 41.14 | M27: =SUM(#REF!-#REF!) -> #REF!
A28: =Gen!A34 -> 44310 | B28: ='Daily report Gen'!Z29 -> 24 | C28: =Gen!B34 -> 0.026 | D28: =E28 -> 0 | F28: =Gen!U34 -> 0.39966527 | G28: =Gen!T32 -> 2593 | H28: =Gen!AK34 -> 0 | I28: =SUM(G28:H28) -> 2593 | J28: =Gen!C34 -> 36768.5 | K28: ='Water-Meter'!E29 -> 56 | L28: ='Lpg (2)'!G33 -> 62.788 | M28: =SUM(#REF!-#REF!) -> #REF!
A29: =Gen!A35 -> 44311 | B29: ='Daily report Gen'!Z30 -> 24 | C29: =Gen!B35 -> 0.052 | D29: =E29 -> 0 | F29: =Gen!U35 -> 0.39691349 | G29: =Gen!T33 -> 2657 | H29: =Gen!AK35 -> 0 | I29: =SUM(G29:H29) -> 2657 | J29: =Gen!C35 -> 35570.78 | K29: ='Water-Meter'!E30 -> 46 | L29: ='Lpg (2)'!G34 -> 66.132 | M29: =SUM(#REF!-#REF!) -> #REF!
A30: =Gen!A36 -> 44312 | B30: ='Daily report Gen'!Z31 -> 25 | C30: =Gen!B36 -> 0.052 | D30: =E30 -> 0 | F30: =Gen!U36 -> 0.41366407 | G30: =Gen!T34 -> 2629 | H30: =Gen!AK36 -> 0 | I30: =SUM(G30:H30) -> 2629 | J30: =Gen!C36 -> 34319.66 | K30: ='Water-Meter'!E31 -> 53 | L30: ='Lpg (2)'!G35 -> 66.352 | M30: =SUM(#REF!-#REF!) -> #REF!
A31: =Gen!A37 -> 44313 | B31: ='Daily report Gen'!Z32 -> 24 | C31: =Gen!B37 -> 0.036 | D31: =E31 -> 0 | F31: =Gen!U37 -> 0.40857666 | G31: =Gen!T35 -> 2890 | H31: =Gen!AK37 -> 0 | I31: =SUM(G31:H31) -> 2890 | J31: =Gen!C37 -> 32937.43 | K31: ='Water-Meter'!E32 -> 43 | L31: ='Lpg (2)'!G36 -> 68.508 | M31: =SUM(#REF!-#REF!) -> #REF!
A32: =Gen!A38 -> 44314 | B32: ='Daily report Gen'!Z33 -> 25 | C32: =Gen!B38 -> 0.039 | D32: =E32 -> 0 | F32: =Gen!U38 -> 0.4296 | G32: =Gen!T36 -> 2691 | H32: =Gen!AK38 -> 0 | I32: =SUM(G32:H32) -> 2691 | J32: =Gen!C38 -> 31790.06 | K32: ='Water-Meter'!E33 -> 61 | L32: ='Lpg (2)'!G37 -> 66.484 | M32: =SUM(#REF!-#REF!) -> #REF!
A33: =Gen!A39 -> 44315 | B33: ='Daily report Gen'!Z34 -> #REF! | C33: =Gen!B39 -> 0.026 | D33: =E33 -> 0 | F33: =Gen!U39 -> 0.39306079 | G33: =Gen!T37 -> 2733 | H33: =Gen!AK39 -> 0 | I33: =SUM(G33:H33) -> 2733 | J33: =Gen!C39 -> 30603.73 | K33: ='Water-Meter'!E34 -> 53 | L33: ='Lpg (2)'!G38 -> 62.348 | M33: =SUM(#REF!-#REF!) -> #REF!
A34: =Gen!A40 -> 44316 | B34: ='Daily report Gen'!Z35 -> #REF! | C34: =Gen!B40 -> 0.01 | D34: =E34 -> 0 | F34: =Gen!U40 -> 0.40999268 | G34: =Gen!T38 -> 2725 | H34: =Gen!AK40 -> 0 | I34: =SUM(G34:H34) -> 2725 | J34: =Gen!C40 -> 29254.57 | K34: ='Water-Meter'!E35 -> 58 | L34: ='Lpg (2)'!G39 -> 62.656 | M34: =SUM(#REF!-#REF!) -> #REF!
A35: =Gen!A41 -> 0 | B35: ='Daily report Gen'!Z36 -> -159641 | C35: =Gen!B41 -> 0 | D35: =E35 -> 0 | F35: =Gen!U39 -> 0.39306079 | G35: =Gen!T39 -> 2813 | H35: =Gen!AK41 -> 0 | I35: =SUM(G35:H35) -> 2813 | J35: =Gen!C41 -> 27860.56 | K35: ='Water-Meter'!E36 -> 0 | L35: ='Lpg (2)'!G40 -> 57.024 | M35: =SUM(#REF!-#REF!) -> #REF!
A36: =Gen!A42 -> 0 | B36: ='Daily report Gen'!Z37 -> 0 | C36: =Gen!B42 -> 0 | D36: =E36 -> 0 | F36: =Gen!U40 -> 0.40999268 | G36: =Gen!T40 -> 2731 | H36: =Gen!AK42 -> 0 | I36: =SUM(G36:H36) -> 2731 | J36: =Gen!C42 -> 27860.56 | K36: ='Water-Meter'!E37 -> 0 | L36: ='Lpg (2)'!G41 -> -335483.76

Sheet Daily report Gen
A1: =A6 -> 44287
K3: GENERATOR NO.1 | N3: GENERATOR NO.2 | Q3: GENERATOR NO.4 | T3: GENERATOR NO.5 | W3: GENERATOR NO.6
A4: DATE | B4: OCC% | C4: D-TANK A | D4: D-TANK B | E4: DELIVERY DATE | F4: DELIVERY | G4: ISSUED-VEHICLE | H4: OTHERS | I4: M-R LV PANEL 1. KW-HR | J4: M-R LV PANEL 2. KW-HR | K4: OPEN HRS READING | L4: CLOSE HRS READING | M4: RUNNING HRS | N4: OPEN HRS READING | O4: CLOSE HRS READING | P4: RUNNING HRS | Q4: OPEN HRS READING | R4: CLOSE HRS READING | S4: RUNNING HRS | T4: OPEN HRS READING | U4: CLOSE HRS READING | V4: RUNNING HRS | W4: OPEN HRS READING | X4: CLOSE HRS READING | Y4: RUNNING HRS | Z4: TOTAL RUNNING HRS | AA4: MAX KW | AB4: MIN-KW | AC4: TOTAL DIESEL CONS.
C5: 13853.38 | D5: 22273 | I5: 31842.2 | J5: 21219.4 | L5: 36091 | O5: 31003 | R5: 36296 | U5: 33466 | X5: 22034
A6: =Gen!A11 -> 44287 | B6: 0.156 | C6: 12242.97 | D6: 22273 | I6: 31847.2 | J6: 21223.7 | K6: =L5 -> 36091 | L6: 36091 | M6: =L6-K6 -> 0 | N6: =O5 -> 31003 | O6: 31003 | P6: =O6-N6 -> 0 | Q6: =R5 -> 36296 | R6: 36296 | S6: =R6-Q6 -> 0 | T6: =U5 -> 33466 | U6: 33490 | V6: =U6-T6 -> 24 | W6: =X5 -> 22034 | X6: 22034 | Y6: =X6-W6 -> 0 | Z6: =Y6+V6+S6+P6+M6 -> 24 | AA6: 250 | AB6: 175 | AC6: =Gen!AR11 -> 1471.88
A7: =Gen!A12 -> 44288 | B7: 0.169 | C7: 10771.09 | D7: 22273 | I7: 31852.7 | J7: 21227.1 | K7: =L6 -> 36091 | L7: 36091 | M7: =L7-K7 -> 0 | N7: =O6 -> 31003 | O7: 31027 | P7: =O7-N7 -> 24 | Q7: =R6 -> 36296 | R7: 36320 | S7: =R7-Q7 -> 24 | T7: =U6 -> 33490 | U7: 33490 | V7: =U7-T7 -> 0 | W7: =X6 -> 22034 | X7: 22034 | Y7: =X7-W7 -> 0 | Z7: =Y7+V7+S7+P7+M7 -> 48 | AA7: 245 | AB7: 155 | AC7: =Gen!AR12 -> 1533.73
A8: =Gen!A13 -> 44289 | B8: 0.23 | C8: 9237.36 | D8: 22273 | G8: 139.29 | I8: 31858.2 | J8: 21230.9 | K8: =L7 -> 36091 | L8: 36116 | M8: =L8-K8 -> 25 | N8: =O7 -> 31027 | O8: 31027 | P8: =O8-N8 -> 0 | Q8: =R7 -> 36320 | R8: 36320 | S8: =R8-Q8 -> 0 | T8: =U7 -> 33490 | U8: 33490 | V8: =U8-T8 -> 0 | W8: =X7 -> 22034 | X8: 22034 | Y8: =X8-W8 -> 0 | Z8: =Y8+V8+S8+P8+M8 -> 25 | AA8: 240 | AB8: 168 | AC8: =Gen!AR13 -> 1565.76
A9: =Gen!A14 -> 44290 | B9: 0.247 | C9: 7917.58 | D9: 22273 | I9: 31863.8 | J9: 21235.5 | K9: =L8 -> 36116 | L9: 36116 | M9: =L9-K9 -> 0 | N9: =O8 -> 31027 | O9: 31027 | P9: =O9-N9 -> 0 | Q9: =R8 -> 36320 | R9: 36320 | S9: =R9-Q9 -> 0 | T9: =U8 -> 33490 | U9: 33514 | V9: =U9-T9 -> 24 | W9: =X8 -> 22034 | X9: 22034 | Y9: =X9-W9 -> 0 | Z9: =Y9+V9+S9+P9+M9 -> 24 | AA9: 260 | AB9: 187 | AC9: =Gen!AR14 -> 1363.11
A10: =Gen!A15 -> 44291 | B10: 0.13 | C10: 6308.49 | D10: 22273 | G10: 218.51 | I10: 31869.2 | J10: 21239.8 | K10: =L9 -> 36116 | L10: 36116 | M10: =L10-K10 -> 0 | N10: =O9 -> 31027 | O10: 31027 | P10: =O10-N10 -> 0 | Q10: =R9 -> 36320 | R10: 36344 | S10: =R10-Q10 -> 24 | T10: =U9 -> 33514 | U10: 33514 | V10: =U10-T10 -> 0 | W10: =X9 -> 22034 | X10: 22034 | Y10: =X10-W10 -> 0 | Z10: =Y10+V10+S10+P10+M10 -> 24 | AA10: 265 | AB10: 145 | AC10: =Gen!AR15 -> 1549.99
A11: =Gen!A16 -> 44292 | B11: 0.091 | C11: 4758.5 | D11: 22273 | G11: 42.44 | I11: 31874.5 | J11: 21244.1 | K11: =L10 -> 36116 | L11: 36116 | M11: =L11-K11 -> 0 | N11: =O10 -> 31027 | O11: 31052 | P11: =O11-N11 -> 25 | Q11: =R10 -> 36344 | R11: 36344 | S11: =R11-Q11 -> 0 | T11: =U10 -> 33514 | U11: 33514 | V11: =U11-T11 -> 0 | W11: =X10 -> 22034 | X11: 22034 | Y11: =X11-W11 -> 0 | Z11: =Y11+V11+S11+P11+M11 -> 25 | AA11: 245 | AB11: 135 | AC11: =Gen!AR16 -> 1309.54
A12: =Gen!A17 -> 44293 | B12: 0.065 | C12: 3448.96 | D12: 22273 | G12: 117.14 | I12: 31879.8 | J12: 21247.6 | K12: =L11 -> 36116 | L12: 36140 | M12: =L12-K12 -> 24 | N12: =O11 -> 31052 | O12: 31052 | P12: =O12-N12 -> 0 | Q12: =R11 -> 36344 | R12: 36344 | S12: =R12-Q12 -> 0 | T12: =U11 -> 33514 | U12: 33514 | V12: =U12-T12 -> 0 | W12: =X11 -> 22034 | X12: 22034 | Y12: =X12-W12 -> 0 | Z12: =Y12+V12+S12+P12+M12 -> 24 | AA12: 260 | AB12: 138 | AC12: =Gen!AR17 -> 1469.56
A13: =Gen!A18 -> 44294 | B13: 0.091 | C13: 19981.4 | D13: 22273 | G13: 156.32 | I13: 31884.9 | J13: 21252.1 | K13: =L12 -> 36140 | L13: 36140 | M13: =L13-K13 -> 0 | N13: =O12 -> 31052 | O13: 31052 | P13: =O14-N13 -> 0 | Q13: =R12 -> 36344 | R13: 36368 | S13: =R13-Q13 -> 24 | T13: =U12 -> 33514 | U13: 33514 | V13: =U13-T13 -> 0 | W13: =X12 -> 22034 | X13: 22034 | Y13: =X13-W13 -> 0 | Z13: =Y13+V13+S13+P13+M13 -> 24 | AA13: 250 | AB13: 125 | AC13: =Gen!AR18 -> 1420.64
A14: =Gen!A19 -> 44295 | B14: 0.065 | C14: 18558.76 | D14: 22273 | G14: 302.12 | I14: 31889.7 | J14: 21256.3 | K14: =L13 -> 36140 | L14: 36140 | M14: =L14-K14 -> 0 | N14: =O14 -> 31052 | O14: 31052 | P14: =O15-N14 -> 24 | Q14: =R13 -> 36368 | R14: 36368 | S14: =R14-Q14 -> 0 | T14: =U13 -> 33514 | U14: 33539 | V14: =U14-T14 -> 25 | W14: =X13 -> 22034 | X14: 22034 | Y14: =X14-W14 -> 0 | Z14: =Y14+V14+S14+P14+M14 -> 49 | AA14: 245 | AB14: 145 | AC14: =Gen!AR19 -> 1608.4
A15: =Gen!A20 -> 44296 | B15: 0.052 | C15: 16950.36 | D15: 22273 | G15: 112 | I15: 31894.5 | J15: 21260.8 | K15: =L14 -> 36140 | L15: 36140 | M15: =L15-K15 -> 0 | N15: =#REF! -> #REF! | O15: 31076 | P15: =O16-N15 -> #REF! | Q15: =R14 -> 36368 | R15: 36368 | S15: =R15-Q15 -> 0 | T15: =U14 -> 33539 | U15: 33539 | V15: =U15-T15 -> 0 | W15: =X14 -> 22034 | X15: 22034 | Y15: =X15-W15 -> 0 | Z15: =Y15+V15+S15+P15+M15 -> #REF! | AA15: 250 | AB15: 145 | AC15: =Gen!AR20 -> 1357.81
A16: =Gen!A21 -> 44297 | B16: 0.104 | C16: 15592.55 | D16: 22273 | G16: 25 | I16: 31899.2 | J16: 21265.1 | K16: =L15 -> 36140 | L16: 36165 | M16: =L16-K16 -> 25 | N16: =O15 -> 31076 | O16: 31076 | P16: =O16-N16 -> 0 | Q16: =R15 -> 36368 | R16: 36368 | S16: =R16-Q16 -> 0 | T16: =U15 -> 33539 | U16: 33539 | V16: =U16-T16 -> 0 | W16: =X15 -> 22034 | X16: 22034 | Y16: =X16-W16 -> 0 | Z16: =Y16+V16+S16+P16+M16 -> 25 | AA16: 240 | AB16: 130 | AC16: =Gen!AR21 -> 1308.98
A17: =Gen!A22 -> 44298 | B17: 0.104 | C17: 14283.57 | D17: 22273 | G17: 250.64 | I17: 31903.9 | J17: 21269.5 | K17: =L16 -> 36165 | L17: 36165 | M17: =L17-K17 -> 0 | N17: =O16 -> 31076 | O17: 31076 | P17: =O17-N17 -> 0 | Q17: =R16 -> 36368 | R17: 36392 | S17: =R17-Q17 -> 24 | T17: =U16 -> 33539 | U17: 33539 | V17: =U17-T17 -> 0 | W17: =X16 -> 22034 | X17: 22034 | Y17: =X17-W17 -> 0 | Z17: =Y17+V17+S17+P17+M17 -> 24 | AA17: 245 | AB17: 125 | AC17: =Gen!AR22 -> 1417.39
A18: =Gen!A23 -> 44299 | B18: 0.013 | C18: 12866.18 | D18: 22273 | G18: 22.54 | I18: 31908.7 | J18: 21273.9 | K18: =L17 -> 36165 | L18: 36165 | M18: =L18-K18 -> 0 | N18: =O17 -> 31076 | O18: 31076 | P18: =O18-N18 -> 0 | Q18: =R17 -> 36392 | R18: 36392 | S18: =R18-Q18 -> 0 | T18: =U17 -> 33539 | U18: 33563 | V18: =U18-T18 -> 24 | W18: =X17 -> 22034 | X18: 22034 | Y18: =X18-W18 -> 0 | Z18: =Y18+V18+S18+P18+M18 -> 24 | AA18: 240 | AB18: 125 | AC18: =Gen!AR23 -> 1106.28
A19: =Gen!A24 -> 44300 | B19: 0 | C19: 11759.9 | D19: 22273 | G19: 160.49 | I19: 31913.7 | J19: 21276.9 | K19: =L18 -> 36165 | L19: 36165 | M19: =L19-K19 -> 0 | N19: =O18 -> 31076 | O19: 31100 | P19: =O19-N19 -> 24 | Q19: =R18 -> 36392 | R19: 36392 | S19: =R19-Q19 -> 0 | T19: =U18 -> 33563 | U19: 33563 | V19: =U19-T19 -> 0 | W19: =X18 -> 22034 | X19: 22034 | Y19: =X19-W19 -> 0 | Z19: =Y19+V19+S19+P19+M19 -> 24 | AA19: 235 | AB19: 120 | AC19: =Gen!AR24 -> 1224.48
A20: =Gen!A25 -> 44301 | B20: 0 | C20: 10535.42 | D20: 22273 | G20: 101.91 | I20: 31917.3 | J20: 21280.2 | K20: =L19 -> 36165 | L20: 36189 | M20: =L20-K20 -> 24 | N20: =O19 -> 31100 | O20: 31100 | P20: =O20-N20 -> 0 | Q20: =R19 -> 36392 | R20: 36392 | S20: =R20-Q20 -> 0 | T20: =U19 -> 33563 | U20: 33563 | V20: =U20-T20 -> 0 | W20: =X19 -> 22034 | X20: 22034 | Y20: =X20-W20 -> 0 | Z20: =Y20+V20+S20+P20+M20 -> 24 | AA20: 230 | AB20: 120 | AC20: =Gen!AR25 -> 1152.99
A21: =Gen!A26 -> 44302 | B21: 0 | C21: 9382.43 | D21: 22273 | I21: 31921.6 | J21: 21283.1 | K21: =L20 -> 36189 | L21: 36189 | M21: =L21-K21 -> 0 | N21: =O20 -> 31100 | O21: 31100 | P21: =O21-N21 -> 0 | Q21: =R20 -> 36392 | R21: 36392 | S21: =R21-Q21 -> 0 | T21: =U20 -> 33563 | U21: 33587 | V21: =U21-T21 -> 24 | W21: =X20 -> 22034 | X21: 22034 | Y21: =X21-W21 -> 0 | Z21: =Y21+V21+S21+P21+M21 -> 24 | AA21: 220 | AB21: 125 | AC21: =Gen!AR26 -> 1038.83
A22: =Gen!A27 -> 44303 | B22: 0.013 | C22: 8343.6 | D22: 22273 | G22: 146.31 | I22: 31925.8 | J22: 21286.1 | K22: =L21 -> 36189 | L22: 36189 | M22: =L22-K22 -> 0 | N22: =O21 -> 31100 | O22: 31125 | P22: =O22-N22 -> 25 | Q22: =R21 -> 36392 | R22: 36392 | S22: =R22-Q22 -> 0 | T22: =U21 -> 33587 | U22: 33587 | V22: =U22-T22 -> 0 | W22: =X21 -> 22034 | X22: 22034 | Y22: =X22-W22 -> 0 | Z22: =Y22+V22+S22+P22+M22 -> 25 | AA22: 225 | AB22: 120 | AC22: =Gen!AR27 -> 1249.09
A23: =Gen!A28 -> 44304 | B23: 0.039 | C23: 7094.51 | D23: 22273 | I23: 31930.4 | J23: 21289.2 | K23: =L22 -> 36189 | L23: 36189 | M23: =L23-K23 -> 0 | N23: =O22 -> 31125 | O23: 31125 | P23: =O23-N23 -> 0 | Q23: =R22 -> 36392 | R23: 36416 | S23: =R23-Q23 -> 24 | T23: =U22 -> 33587 | U23: 33587 | V23: =U23-T23 -> 0 | W23: =X22 -> 22034 | X23: 22034 | Y23: =X23-W23 -> 0 | Z23: =Y23+V23+S23+P23+M23 -> 24 | AA23: 220 | AB23: 122 | AC23: =Gen!AR28 -> 1165.3
A24: =Gen!A29 -> 44305 | B24: 0.065 | C24: 5929.21 | D24: 22273 | G24: 346.21 | I24: 31935 | J24: 21292.6 | K24: =L23 -> 36189 | L24: 36213 | M24: =L24-K24 -> 24 | N24: =O23 -> 31125 | O24: 31125 | P24: =O24-N24 -> 0 | Q24: =R23 -> 36416 | R24: 36416 | S24: =R24-Q24 -> 0 | T24: =U23 -> 33587 | U24: 33587 | V24: =U24-T24 -> 0 | W24: =X23 -> 22034 | X24: 22034 | Y24: =X24-W24 -> 0 | Z24: =Y24+V24+S24+P24+M24 -> 24 | AA24: 215 | AB24: 120 | AC24: =Gen!AR29 -> 1495.21
A25: =Gen!A30 -> 44306 | B25: 0.052 | C25: 4434 | D25: 22273 | G25: 67.46 | I25: 31939.8 | J25: 21295.7 | K25: =L24 -> 36213 | L25: 36213 | M25: =L25-K25 -> 0 | N25: =O24 -> 31125 | O25: 31125 | P25: =O25-N25 -> 0 | Q25: =R24 -> 36416 | R25: 36416 | S25: =R25-Q25 -> 0 | T25: =U24 -> 33587 | U25: 33611 | V25: =U25-T25 -> 24 | W25: =X24 -> 22034 | X25: 22034 | Y25: =X25-W25 -> 0 | Z25: =Y25+V25+S25+P25+M25 -> 24 | AA25: 226 | AB25: 130 | AC25: =Gen!AR30 -> 1255.04
A26: =Gen!A31 -> 44307 | B26: 0.026 | C26: 3178.96 | D26: 22273 | G26: 17.4 | I26: 31944.7 | J26: 21298.9 | K26: =L25 -> 36213 | L26: 36213 | M26: =L26-K26 -> 0 | N26: =O25 -> 31125 | O26: 31149 | P26: =O26-N26 -> 24 | Q26: =R25 -> 36416 | R26: 36416 | S26: =R26-Q26 -> 0 | T26: =U25 -> 33611 | U26: 33611 | V26: =U26-T26 -> 0 | W26: =X25 -> 22034 | X26: 22034 | Y26: =X26-W26 -> 0 | Z26: =Y26+V26+S26+P26+M26 -> 24 | AA26: 225 | AB26: 125 | AC26: =Gen!AR31 -> 1134.86
A27: =Gen!A32 -> 44308 | B27: 0 | C27: 16844.01 | D27: 22273 | G27: 54.93 | I27: 31949.3 | J27: 21301.8 | K27: =L26 -> 36213 | L27: 36213 | M27: =L27-K27 -> 0 | N27: =O26 -> 31149 | O27: 31149 | P27: =O27-N27 -> 0 | Q27: =R26 -> 36416 | R27: 36440 | S27: =R27-Q27 -> 24 | T27: =U26 -> 33611 | U27: 33611 | V27: =U27-T27 -> 0 | W27: =X26 -> 22034 | X27: 22034 | Y27: =X27-W27 -> 0 | Z27: =Y27+V27+S27+P27+M27 -> 24 | AA27: 210 | AB27: 120 | AC27: =Gen!AR32 -> 1120.47
A28: =Gen!A33 -> 44309 | B28: 0.013 | C28: 15723.63 | D28: 22273 | G28: 140.07 | I28: 31953.9 | J28: 21304.6 | K28: =L27 -> 36213 | L28: 36237 | M28: =L28-K28 -> 24 | N28: =O27 -> 31149 | O28: 31149 | P28: =O28-N28 -> 0 | Q28: =R27 -> 36440 | R28: 36440 | S28: =R28-Q28 -> 0 | T28: =U27 -> 33611 | U28: 33611 | V28: =U28-T28 -> 0 | W28: =X27 -> 22034 | X28: 22034 | Y28: =X28-W28 -> 0 | Z28: =Y28+V28+S28+P28+M28 -> 24 | AA28: 205 | AB28: 120 | AC28: =Gen!AR33 -> 1228.13
A29: =Gen!A34 -> 44310 | B29: 0.026 | C29: 14495.5 | D29: 22273 | G29: 147 | I29: 31958.5 | J29: 21307.6 | K29: =L28 -> 36237 | L29: 36237 | M29: =L29-K29 -> 0 | N29: =O28 -> 31149 | O29: 31149 | P29: =O29-N29 -> 0 | Q29: =R28 -> 36440 | R29: 36440 | S29: =R29-Q29 -> 0 | T29: =U28 -> 33611 | U29: 33635 | V29: =U29-T29 -> 24 | W29: =X28 -> 22034 | X29: 22034 | Y29: =X29-W29 -> 0 | Z29: =Y29+V29+S29+P29+M29 -> 24 | AA29: 200 | AB29: 115 | AC29: =Gen!AR34 -> 1197.72
A30: =Gen!A35 -> 44311 | B30: 0.052 | C30: 13297.78 | D30: 22273 | G30: 104.04 | I30: 31962.7 | J30: 21310.5 | K30: =L29 -> 36237 | L30: 36237 | M30: =L30-K30 -> 0 | N30: =O29 -> 31149 | O30: 31173 | P30: =O30-N30 -> 24 | Q30: =R29 -> 36440 | R30: 36440 | S30: =R30-Q30 -> 0 | T30: =U29 -> 33635 | U30: 33635 | V30: =U30-T30 -> 0 | W30: =X29 -> 22034 | X30: 22034 | Y30: =X30-W30 -> 0 | Z30: =Y30+V30+S30+P30+M30 -> 24 | AA30: 215 | AB30: 120 | AC30: =Gen!AR35 -> 1251.12
A31: =Gen!A36 -> 44312 | B31: 0.052 | C31: 12046.66 | D31: 22273 | G31: 269.06 | I31: 31967.6 | J31: 21313.9 | K31: =L30 -> 36237 | L31: 36237 | M31: =L31-K31 -> 0 | N31: =O30 -> 31173 | O31: 31173 | P31: =O31-N31 -> 0 | Q31: =R30 -> 36440 | R31: 36465 | S31: =R31-Q31 -> 25 | T31: =U30 -> 33635 | U31: 33635 | V31: =U31-T31 -> 0 | W31: =X30 -> 22034 | X31: 22034 | Y31: =X31-W31 -> 0 | Z31: =Y31+V31+S31+P31+M31 -> 25 | AA31: 230 | AB31: 130 | AC31: =Gen!AR36 -> 1382.23
A32: =Gen!A37 -> 44313 | B32: 0.036 | C32: 10666.43 | D32: 22273 | G32: 30.73 | I32: 31972.2 | J32: 21316.9 | K32: =L31 -> 36237 | L32: 36261 | M32: =L32-K32 -> 24 | N32: =O31 -> 31173 | O32: 31173 | P32: =O32-N32 -> 0 | Q32: =R31 -> 36465 | R32: 36465 | S32: =R32-Q32 -> 0 | T32: =U31 -> 33635 | U32: 33635 | V32: =U32-T32 -> 0 | W32: =X31 -> 22034 | X32: 22034 | Y32: =X32-W32 -> 0 | Z32: =Y32+V32+S32+P32+M32 -> 24 | AA32: 220 | AB32: 110 | AC32: =Gen!AR37 -> 1147.37
A33: =Gen!A38 -> 44314 | B33: 0.039 | C33: 9519.06 | D33: 22273 | G33: 15.67 | I33: 31977.1 | J33: 21319.8 | K33: =L32 -> 36261 | L33: 36261 | M33: =L33-K33 -> 0 | N33: =O32 -> 31173 | O33: 31173 | P33: =O33-N33 -> 0 | Q33: =R32 -> 36465 | R33: 36465 | S33: =R34-Q33 -> 0 | T33: =U32 -> 33635 | U33: 33660 | V33: =U33-T33 -> 25 | W33: =X32 -> 22034 | X33: 22034 | Y33: =X33-W33 -> 0 | Z33: =Y33+V33+S33+P33+M33 -> 25 | AA33: 230 | AB33: 120 | AC33: =Gen!AR38 -> 1186.33
A34: =Gen!A39 -> 44315 | B34: 0.026 | C34: 8332.73 | D34: 22273 | G34: 243.48 | I34: 31981.7 | J34: 21322.9 | K34: =L33 -> 36261 | L34: 36261 | M34: =L34-K34 -> 0 | N34: =O33 -> 31173 | O34: 31197 | P34: =O34-N34 -> 24 | Q34: =R34 -> 36465 | R34: 36465 | S34: =#REF!-Q34 -> #REF! | T34: =U33 -> 33660 | U34: 33660 | V34: =U34-T34 -> 0 | W34: =X33 -> 22034 | X34: 22034 | Y34: =X34-W34 -> 0 | Z34: =Y34+V34+S34+P34+M34 -> #REF! | AA34: 225 | AB34: 130 | AC34: =Gen!AR39 -> 1349.16
A35: =Gen!A40 -> 44316 | B35: 0.01 | C35: 6983.57 | D35: 22273 | G35: 274.32 | I35: 31986.6 | J35: 21325.8 | K35: =L34 -> 36261 | L35: 36261 | M35: =L35-K35 -> 0 | N35: =O34 -> 31197 | O35: 31197 | P35: =O35-N35 -> 0 | Q35: =#REF! -> #REF! | R35: 36489 | S35: =R35-Q35 -> #REF! | T35: =U34 -> 33660 | U35: 33660 | V35: =U35-T35 -> 0 | W35: =X34 -> 22034 | X35: 22034 | Y35: =X35-W35 -> 0 | Z35: =Y35+V35+S35+P35+M35 -> #REF! | AA35: 250 | AB35: 130 | AC35: =Gen!AR40 -> 1394.01
A36: =Gen!A41 -> 0 | C36: 5587.56 | D36: 22273 | I36: 31991.4 | J36: 21328.7 | K36: =L35 -> 36261 | M36: =L36-K36 -> -36261 | N36: =O35 -> 31197 | P36: =O36-N36 -> -31197 | Q36: =R35 -> 36489 | S36: =R36-Q36 -> -36489 | T36: =U35 -> 33660 | V36: =U36-T36 -> -33660 | W36: =X35 -> 22034 | Y36: =X36-W36 -> -22034 | Z36: =Y36+V36+S36+P36+M36 -> -159641 | AC36: =Gen!AR41 -> 0
A37: =Gen!A42 -> 0 | B37: =Gen!B42 -> 0 | K37: =L36 -> 0 | M37: =L37-K37 -> 0 | N37: =O36 -> 0 | P37: =O37-N37 -> 0 | Q37: =R36 -> 0 | S37: =R37-Q37 -> 0 | T37: =U36 -> 0 | V37: =U37-T37 -> 0 | W37: =X36 -> 0 | Y37: =X37-W37 -> 0 | Z37: =Y37+V37+S37+P37+M37 -> 0 | AC37: =Gen!AR42 -> 0

Sheet Gen
D2: =A11 -> 44287
F6: BILILA LODGE INVESTMENT LIMITED | V6: 1 | W6: 2 | X6: 3 | Y6: 4 | Z6: 5 | AA6: 6 | AB6: 7 | AC6: 8 | AD6: 9 | AE6: 10 | AF6: 11
F7: Diesel Consumed by 500KVA Generator | M7: 500KVA Generator KWh | V7: Safari-STAFF | W7: Safari-STAFF | X7: Lc/swg/gust | Y7: Eng pikcup | Z7: VIP Safari Car | AA7: GX Guest | AB7: GX Guest | AC7: T/Hillux/pur | AD7: TATA | AE7: MAN | AF7: F/Truck | AG7: Incenerator | AH7: A&K | AI7: OTHER | AJ7: TOTAL CO
A8: Date | B8: Occupancy % | C8: OPENING | D8: Received | E8: Schedule delivery | F8: Company | G8: 1 | H8: 2 | I8: 3 | J8: 4 | K8: 5 | L8: 6 | M8: 1 | N8: 2 | O8: 3 | P8: 4 | Q8: 5 | R8: 6 | S8: Total Diseal Consumed | T8: Total Kwh generated | U8: Average Diesel/Kwh | V8: T 128 AXJ | W8: T 134 AXJ | X8: T 499 AXG | Y8: T 217 CHV | Z8: T 214 CHV | AA8: T 139 AXE | AB8: T 242 AXN | AC8: T 476 AWZ | AD8: T 226 AUQ | AE8: T 308 CLD | AF8: T 852 AWU | AG8: Machine ENG | AH8: Vehicle | AI8: Vehicle | AR8: Total Diseal Consumed Gen & Vehicle | AS8: Total cost /Day (TSH) | AT8: BALANCE
C9: =[4]Gen!$C$43 -> 34515.97 | S9: =SUM(F9:L9) -> 0 | T9: =SUM(M9:R9) -> 0 | AR9: =SUM(AJ9+S9) -> 0 | AT9: 38784.7
S10: =SUM(F10:L10) -> 0 | T10: =SUM(M10:R10) -> 0 | U10: =SUM(N10:S10) -> 0 | AJ10: =SUM(V10:AI10) -> 0 | AR10: =SUM(AJ10+S10) -> 0
A11: 44287 | B11: 0.156 | C11: =SUM(C9+D11) -> 34515.97 | H11: 1326.45 | N11: 3175 | S11: =SUM(F11:L11) -> 1326.45 | T11: =SUM(M11:R11) -> 3175 | U11: =S11/T11 -> 0.41777953 | X11: 34.9 | Z11: 110.53 | AJ11: =SUM(V11:AI11) -> 145.43 | AR11: =SUM(AJ11+S11) -> 1471.88 | AS11: =AR11*AU11 -> 0 | AT11: =C11 -> 34515.97
A12: 44288 | B12: 0.169 | C12: =SUM(C11-AR11+D12) -> 33044.09 | J12: 1308.83 | P12: 3187 | S12: =SUM(F12:L12) -> 1308.83 | T12: =SUM(M12:R12) -> 3187 | U12: =S12/T12 -> 0.41067775 | AC12: 54.9 | AH12: 20 | AI12: 150 | AJ12: =SUM(V12:AI12) -> 224.9 | AR12: =SUM(AJ12+S12) -> 1533.73 | AS12: =AR12*AU12 -> 0 | AT12: =C12 -> 33044.09
A13: 44289 | B13: 0.23 | C13: =SUM(C12-AR12+D13) -> 31510.36 | G13: 1426.47 | M13: 3546 | S13: =SUM(F13:L13) -> 1426.47 | T13: =SUM(M13:R13) -> 3546 | U13: =S13/T13 -> 0.4022758 | X13: 59.09 | AI13: 80.2 | AJ13: =SUM(V13:AI13) -> 139.29 | AR13: =SUM(AJ13+S13) -> 1565.76 | AS13: =AR13*AU13 -> 0 | AT13: =C13 -> 31510.36
A14: 44290 | B14: 0.247 | C14: =SUM(C13-AR13+D14) -> 29944.6 | K14: 1363.11 | Q14: 3328 | S14: =SUM(F14:L14) -> 1363.11 | T14: =SUM(M14:R14) -> 3328 | U14: =S14/T14 -> 0.40958834 | AJ14: =SUM(V14:AI14) -> 0 | AR14: =SUM(AJ14+S14) -> 1363.11 | AS14: =AR14*AU14 -> 0 | AT14: =C14 -> 29944.6
A15: 44291 | B15: 0.13 | C15: =SUM(C14-AR14+D15) -> 28581.49 | J15: 1331.48 | P15: 3250 | S15: =SUM(F15:L15) -> 1331.48 | T15: =SUM(M15:R15) -> 3250 | U15: =S15/T15 -> 0.40968615 | X15: 23.51 | Z15: 115 | AH15: 80 | AJ15: =SUM(V15:AI15) -> 218.51 | AR15: =SUM(AJ15+S15) -> 1549.99 | AS15: =AR15*AU15 -> 0 | AT15: =C15 -> 28581.49
A16: 44292 | B16: 0.091 | C16: =SUM(C15-AR15+D16) -> 27031.5 | E16: 15000 | F16: RAHA | H16: 1267.1 | M16: 3070 | S16: =SUM(F16:L16) -> 1267.1 | T16: =SUM(M16:R16) -> 3070 | U16: =S16/T16 -> 0.41273616 | X16: 42.44 | AJ16: =SUM(V16:AI16) -> 42.44 | AR16: =SUM(AJ16+S16) -> 1309.54 | AS16: =AR16*AU16 -> 0 | AT16: =C16 -> 27031.5
A17: 44293 | B17: 0.065 | C17: =SUM(C16-AR16+D17) -> 43721.96 | D17: 18000 | G17: 1350.42 | M17: 3363 | S17: =SUM(F17:L17) -> 1350.42 | T17: =SUM(M17:R17) -> 3363 | U17: =S17/T17 -> 0.40155219 | X17: 10.14 | AH17: 109 | AJ17: =SUM(V17:AI17) -> 119.14 | AR17: =SUM(AJ17+S17) -> 1469.56 | AS17: =AR17*AU17 -> 0 | AT17: =C17 -> 43721.96
A18: 44294 | B18: 0.091 | C18: =SUM(C17-AR17+D18) -> 42252.4 | J18: 1264.32 | P18: 3146 | S18: =SUM(F18:L18) -> 1264.32 | T18: =SUM(M18:R18) -> 3146 | U18: =S18/T18 -> 0.40188175 | Z18: 60.32 | AH18: 96 | AJ18: =SUM(V18:AI18) -> 156.32 | AR18: =SUM(AJ18+S18) -> 1420.64 | AS18: =AR18*AU18 -> 0 | AT18: =C18 -> 42252.4
A19: 44295 | B19: 0.065 | C19: =SUM(C18-AR18+D19) -> 40831.76 | K19: 1306.29 | Q19: 3314 | S19: =SUM(F19:L19) -> 1306.29 | T19: =SUM(M19:R19) -> 3314 | U19: =S19/T19 -> 0.3941732 | X19: 65.01 | Z19: 78.1 | AH19: 159 | AJ19: =SUM(V19:AI19) -> 302.11 | AR19: =SUM(AJ19+S19) -> 1608.4 | AS19: =AR19*AU19 -> 0 | AT19: =C19 -> 40831.76
A20: 44296 | B20: 0.052 | C20: =SUM(C19-AR19+D20) -> 39223.36 | H20: 1245.81 | N20: 3168 | S20: =SUM(F20:L20) -> 1245.81 | T20: =SUM(M20:R20) -> 3168 | U20: =S20/T20 -> 0.39324811 | AH20: 112 | AJ20: =SUM(V20:AI20) -> 112 | AR20: =SUM(AJ20+S20) -> 1357.81 | AS20: =AR20*AU20 -> 0 | AT20: =C20 -> 39223.36
A21: 44297 | B21: 0.104 | C21: =SUM(C20-AR20+D21) -> 37865.55 | G21: 1283.98 | M21: 3237 | S21: =SUM(F21:L21) -> 1283.98 | T21: =SUM(M21:R21) -> 3237 | U21: =S21/T21 -> 0.3966574 | AH21: 25 | AJ21: =SUM(V21:AI21) -> 25 | AR21: =SUM(AJ21+S21) -> 1308.98 | AS21: =AR21*AU21 -> 0 | AT21: =C21 -> 37865.55
A22: 44298 | B22: 0.104 | C22: =SUM(C21-AR21+D22) -> 36556.57 | J22: 1166.75 | P22: 3269 | S22: =SUM(F22:L22) -> 1166.75 | T22: =SUM(M22:R22) -> 3269 | U22: =S22/T22 -> 0.35691343 | X22: 37.14 | Y22: 213.5 | AJ22: =SUM(V22:AI22) -> 250.64 | AR22: =SUM(AJ22+S22) -> 1417.39 | AS22: =AR22*AU22 -> 0 | AT22: =C22 -> 36556.57
A23: 44299 | B23: 0.013 | C23: =SUM(C22-AR22+D23) -> 35139.18 | K23: 1083.74 | Q23: 2665 | S23: =SUM(F23:L23) -> 1083.74 | T23: =SUM(M23:R23) -> 2665 | U23: =S23/T23 -> 0.40665666 | X23: 22.54 | AJ23: =SUM(V23:AI23) -> 22.54 | AR23: =SUM(AJ23+S23) -> 1106.28 | AS23: =AR23*AU23 -> 0 | AT23: =C23 -> 35139.18
A24: 44300 | B24: 0 | C24: =SUM(C23-AR23+D24) -> 34032.9 | H24: 1063.99 | N24: 2643 | S24: =SUM(F24:L24) -> 1063.99 | T24: =SUM(M24:R24) -> 2643 | U24: =S24/T24 -> 0.40256905 | X24: 13.49 | AH24: 147 | AJ24: =SUM(V24:AI24) -> 160.49 | AR24: =SUM(AJ24+S24) -> 1224.48 | AS24: =AR24*AU24 -> 0 | AT24: =C24 -> 34032.9
A25: 44301 | B25: 0 | C25: =SUM(C24-AR24+D25) -> 32808.42 | G25: 1051.08 | M25: 2618 | S25: =SUM(F25:L25) -> 1051.08 | T25: =SUM(M25:R25) -> 2618 | U25: =S25/T25 -> 0.40148205 | X25: 17.65 | Z25: 84.26 | AJ25: =SUM(V25:AI25) -> 101.91 | AR25: =SUM(AJ25+S25) -> 1152.99 | AS25: =AR25*AU25 -> 0 | AT25: =C25 -> 32808.42
A26: 44302 | B26: 0 | C26: =SUM(C25-AR25+D26) -> 31655.43 | K26: 1038.83 | Q26: 2546 | S26: =SUM(F26:L26) -> 1038.83 | T26: =SUM(M26:R26) -> 2546 | U26: =S26/T26 -> 0.40802435 | AJ26: =SUM(V26:AI26) -> 0 | AR26: =SUM(AJ26+S26) -> 1038.83 | AS26: =AR26*AU26 -> 0 | AT26: =C26 -> 31655.43
A27: 44303 | B27: 0.013 | C27: =SUM(C26-AR26+D27) -> 30616.6 | H27: 1102.78 | N27: 2694 | S27: =SUM(F27:L27) -> 1102.78 | T27: =SUM(M27:R27) -> 2694 | U27: =S27/T27 -> 0.4093467 | X27: 79.65 | AB27: 66.66 | AJ27: =SUM(V27:AI27) -> 146.31 | AR27: =SUM(AJ27+S27) -> 1249.09 | AS27: =AR27*AU27 -> 0 | AT27: =C27 -> 30616.6
A28: 44304 | B28: 0.039 | C28: =SUM(C27-AR27+D28) -> 29367.51 | J28: 1165.3 | P28: 2839 | S28: =SUM(F28:L28) -> 1165.3 | T28: =SUM(M28:R28) -> 2839 | U28: =S28/T28 -> 0.41046143 | AJ28: =SUM(V28:AI28) -> 0 | AR28: =SUM(AJ28+S28) -> 1165.3 | AS28: =AR28*AU28 -> 0 | AT28: =C28 -> 29367.51
A29: 44305 | B29: 0.065 | C29: =SUM(C28-AR28+D29) -> 28202.21 | G29: 1149 | M29: 2733 | S29: =SUM(F29:L29) -> 1149 | T29: =SUM(M29:R29) -> 2733 | U29: =S29/T29 -> 0.42041712 | X29: 24.72 | Z29: 85.63 | AD29: 130.86 | AH29: 105 | AJ29: =SUM(V29:AI29) -> 346.21 | AR29: =SUM(AJ29+S29) -> 1495.21 | AS29: =AR29*AU29 -> 0 | AT29: =C29 -> 28202.21
A30: 44306 | B30: 0.052 | C30: =SUM(C29-AR29+D30) -> 26707 | E30: 15000 | F30: RAHA | K30: 1187.58 | Q30: 2856 | S30: =SUM(F30:L30) -> 1187.58 | T30: =SUM(M30:R30) -> 2856 | U30: =S30/T30 -> 0.41581933 | AC30: 67.46 | AJ30: =SUM(V30:AI30) -> 67.46 | AR30: =SUM(AJ30+S30) -> 1255.04 | AS30: =AR30*AU30 -> 0 | AT30: =C30 -> 26707
A31: 44307 | B31: 0.026 | C31: =SUM(C30-AR30+D31) -> 25451.96 | H31: 1117.46 | N31: 2700 | S31: =SUM(F31:L31) -> 1117.46 | T31: =SUM(M31:R31) -> 2700 | U31: =S31/T31 -> 0.41387407 | X31: 17.4 | AJ31: =SUM(V31:AI31) -> 17.4 | AR31: =SUM(AJ31+S31) -> 1134.86 | AS31: =AR31*AU31 -> 0 | AT31: =C31 -> 25451.96
A32: 44308 | B32: 0 | C32: =SUM(C31-AR31+D32) -> 39117.1 | D32: 14800 | J32: 1065.54 | P32: 2593 | S32: =SUM(F32:L32) -> 1065.54 | T32: =SUM(M32:R32) -> 2593 | U32: =S32/T32 -> 0.41092943 | X32: 13.16 | Z32: 41.77 | AJ32: =SUM(V32:AI32) -> 54.93 | AR32: =SUM(AJ32+S32) -> 1120.47 | AS32: =AR32*AU32 -> 0 | AT32: =C32 -> 39117.1
A33: 44309 | B33: 0.013 | C33: =SUM(C32-AR32+D33) -> 37996.63 | G33: 1088.06 | M33: 2657 | S33: =SUM(F33:L33) -> 1088.06 | T33: =SUM(M33:R33) -> 2657 | U33: =S33/T33 -> 0.40950696 | X33: 61.94 | Z33: 78.13 | AJ33: =SUM(V33:AI33) -> 140.07 | AR33: =SUM(AJ33+S33) -> 1228.13 | AS33: =AR33*AU33 -> 0 | AT33: =C33 -> 37996.63
A34: 44310 | B34: 0.026 | C34: =SUM(C33-AR33+D34) -> 36768.5 | K34: 1050.72 | Q34: 2629 | S34: =SUM(F34:L34) -> 1050.72 | T34: =SUM(M34:R34) -> 2629 | U34: =S34/T34 -> 0.39966527 | AH34: 147 | AJ34: =SUM(V34:AI34) -> 147 | AR34: =SUM(AJ34+S34) -> 1197.72 | AS34: =AR34*AU34 -> 0 | AT34: =C34 -> 36768.5
A35: 44311 | B35: 0.052 | C35: =SUM(C34-AR34+D35) -> 35570.78 | H35: 1147.08 | N35: 2890 | S35: =SUM(F35:L35) -> 1147.08 | T35: =SUM(M35:R35) -> 2890 | U35: =S35/T35 -> 0.39691349 | AE35: 104.04 | AJ35: =SUM(V35:AI35) -> 104.04 | AR35: =SUM(AJ35+S35) -> 1251.12 | AS35: =AR35*AU35 -> 0 | AT35: =C35 -> 35570.78
A36: 44312 | B36: 0.052 | C36: =SUM(C35-AR35+D36) -> 34319.66 | J36: 1113.17 | P36: 2691 | S36: =SUM(F36:L36) -> 1113.17 | T36: =SUM(M36:R36) -> 2691 | U36: =S36/T36 -> 0.41366407 | Z36: 62.67 | AC36: 47.39 | AH36: 159 | AJ36: =SUM(V36:AI36) -> 269.06 | AR36: =SUM(AJ36+S36) -> 1382.23 | AS36: =AR36*AU36 -> 0 | AT36: =C36 -> 34319.66
A37: 44313 | B37: 0.036 | C37: =SUM(C36-AR36+D37) -> 32937.43 | G37: 1116.64 | M37: 2733 | S37: =SUM(F37:L37) -> 1116.64 | T37: =SUM(M37:R37) -> 2733 | U37: =S37/T37 -> 0.40857666 | X37: 30.73 | AJ37: =SUM(V37:AI37) -> 30.73 | AR37: =SUM(AJ37+S37) -> 1147.37 | AS37: =AR37*AU37 -> 0 | AT37: =C37 -> 32937.43
A38: 44314 | B38: 0.039 | C38: =SUM(C37-AR37+D38) -> 31790.06 | K38: 1170.66 | Q38: 2725 | S38: =SUM(F38:L38) -> 1170.66 | T38: =SUM(M38:R38) -> 2725 | U38: =S38/T38 -> 0.4296 | AC38: 15.67 | AJ38: =SUM(V38:AI38) -> 15.67 | AR38: =SUM(AJ38+S38) -> 1186.33 | AS38: =AR38*AU38 -> 0 | AT38: =C38 -> 31790.06
A39: 44315 | B39: 0.026 | C39: =SUM(C38-AR38+D39) -> 30603.73 | H39: 1105.68 | N39: 2813 | S39: =SUM(F39:L39) -> 1105.68 | T39: =SUM(M39:R39) -> 2813 | U39: =S39/T39 -> 0.39306079 | X39: 50.16 | Z39: 29.32 | AH39: 164 | AJ39: =SUM(V39:AI39) -> 243.48 | AR39: =SUM(AJ39+S39) -> 1349.16 | AS39: =AR39*AU39 -> 0 | AT39: =C39 -> 30603.73
A40: 44316 | B40: 0.01 | C40: =SUM(C39-AR39+D40) -> 29254.57 | J40: 1119.69 | P40: 2731 | S40: =SUM(F40:L40) -> 1119.69 | T40: =SUM(M40:R40) -> 2731 | U40: =S40/T40 -> 0.40999268 | X40: 63.16 | Z40: 80.16 | AH40: 131 | AJ40: =SUM(V40:AI40) -> 274.32 | AR40: =SUM(AJ40+S40) -> 1394.01 | AS40: =AR40*AU40 -> 0 | AT40: =C40 -> 29254.57
C41: =SUM(C40-AR40+D41) -> 27860.56 | S41: =SUM(F41:L41) -> 0 | T41: =SUM(M41:R41) -> 0 | U41: =S41/T41 -> #DIV/0! | AJ41: =SUM(V41:AI41) -> 0 | AR41: =SUM(AJ41+S41) -> 0 | AS41: =AR41*AU41 -> 0 | AT41: =C41 -> 27860.56
C42: =SUM(C41-AR41+D42) -> 27860.56 | S42: =SUM(F42:L42) -> 0 | T42: =SUM(M42:R42) -> 0 | AJ42: =SUM(V42:AI42) -> 0 | AR42: =SUM(AJ42+S42) -> 0 | AS42: =AR42*AU42 -> 0 | AT42: =C42 -> 27860.56
A43: BF | B43: =AVERAGE(B11:B42) -> 0.065533333 | C43: =SUM(C42-AR42+D43) -> 27860.56 | S43: =SUM(F43:L43) -> 0 | T43: =SUM(M43:R43) -> 0 | AJ43: =SUM(V43:AI43) -> 0 | AR43: =SUM(AJ43+S43) -> 0 | AS43: =AR43*AU43 -> 0 | AT43: =C43 -> 27860.56
S44: =SUM(F44:L44) -> 0 | T44: =SUM(M44:R44) -> 0 | AJ44: =SUM(V44:AI44) -> 0 | AR44: =S44+AJ44 -> 0 | AS44: =AR44*AU44 -> 0
D45: =SUM(D11:D44) -> 32800 | E45: =SUM(E11:E42) -> 30000 | F45: =SUM(F11:F44) -> 0 | G45: =SUM(G11:G44) -> 8465.65 | H45: =SUM(H11:H44) -> 9376.35 | I45: =SUM(I11:I44) -> 0 | J45: =SUM(J11:J44) -> 9535.08 | K45: =SUM(K11:K44) -> 8200.93 | L45: =SUM(L11:L44) -> 0 | M45: =SUM(M11:M44) -> 23957 | ... O45: =SUM(O11:O44) -> 0 | P45: =SUM(P11:P43) -> 23706 | Q45: =SUM(Q11:Q44) -> 20063 | R45: =SUM(R11:R44) -> 0 | S45: =SUM(G45:L45) -> 35578.01 | T45: =SUM(M45:R45) -> 87809 | U45: =SUM(U11:U42) -> #DIV/0! | V45: =SUM(V9:V44) -> 0 | W45: =SUM(W9:W44) -> 0 | X45: =SUM(X9:X44) -> 666.83 | Y45: =SUM(Y9:Y44) -> 213.5 | Z45: =SUM(Z9:Z44) -> 825.89 | AA45: =SUM(AA9:AA44) -> 0 | AB45: =SUM(AB9:AB44) -> 66.66 | AC45: =SUM(AC10:AC44) -> 185.42 | AD45: =SUM(AD10:AD44) -> 130.86 | AE45: =SUM(AE9:AE44) -> 104.04 | AF45: =SUM(AF9:AF44) -> 0 | AG45: =SUM(AG9:AG44) -> 0 | AH45: =SUM(AH9:AH43) -> 1454 | AI45: =SUM(AI9:AI39) -> 230.2 | AJ45: =SUM(AJ9:AJ44) -> 3877.4 | AR45: =SUM(AR11:AR43) -> 39455.41 | AS45: =SUM(AS11:AS44) -> 0
A46: Nb Day
S47: =AVERAGE(S11:S41) -> 1147.6777 | T47: =S45*2315 -> 82363093 | U47: TZS | AR47: =AR45*2143 -> 84552944 | AS47: TZS
A48: Av. Occ | T48: =T47/2289 -> 35982.129 | U48: USD | AR48: =AR47/2289 -> 36938.813 | AS48: USD
B50: A & K VEHICLES | H50: MAULY VEHICLES | N50: GREEN LAND VEHICLES | T50: OTHERS VEHICLES
B51: Date | C51: Vehicles | D51: Liters | E51: Driver name | F51: Authority manager | H51: Date | I51: Vehicles | J51: Liters | K51: Driver name | L51: Authority manager | N51: Date | O51: Vehicles | P51: Liters | Q51: Driver name | R51: Authorized Manager | T51: Date | U51: Vehicles | V51: Liters | W51: Driver name | X51: Athorized Manager | Y51: Reasons
B52: 44288 | C52: T880DKQ | D52: 20 | E52: Gurisha | F52: Noel | N52: 44288 | O52: T165DKR | P52: 150 | Q52: Chande | R52: Noel | T52: 44289 | U52: T899DUQ | V52: 50 | W52: Abdul | X52: Noel | Y52: paid
B53: 44291 | C53: T111CWQ | D53: 80 | E53: Wolfgang | F53: Noel | T53: 44289 | U53: T248AUV | V53: 30 | W53: Deo | X53: Noel | Y53: paid
B54: 44293 | C54: T840DDW | D54: 109 | E54: Godlisen | F54: Noel
B55: 44294 | C55: T106CWQ | D55: 96 | E55: Kessi | F55: Noel
B56: 44295 | C56: T880DKQ | D56: 104 | E56: Hassan | F56: Noel
B57: 44295 | C57: T364AHF | D57: 39 | E57: Hassan | F57: Noel
B58: 44295 | C58: T880DKQ | D58: 16 | E58: Hassan | F58: Noel
B59: 44296 | C59: T132CWQ | D59: 112 | E59: Othuman | F59: Noel
B60: 44297 | C60: T882DKQ | D60: 25 | E60: Gudlack | F60: Noel
B61: 44300 | C61: T391DKR | D61: 126 | E61: Kaswa | F61: Noel
B62: 44300 | C62: T364AHF | D62: 21 | E62: Kaswa | F62: Noel
B63: 44305 | C63: T840DDW | D63: 105 | E63: Godlisen | F63: Noel
B64: 44310 | C64: T132CWQ | D64: 147 | E64: Othuman | F64: Noel
B65: 44312 | C65: T882DKQ | D65: 159 | E65: Gudlack | F65: Noel
... B71: 44316 | C71: T106CWQ | D71: 15 | E71: Othuman | F71: Noel

Sheet Energy Graph
A1: Date | B1: Usage KW | C1: Occ % | D1: Cost per room Total Occ | E1: Cost per room Guest Occ
A2: =Gen!A11 -> 44287 | B2: =SUM('[1]Summery Report'!F5) -> 5669 | C2: =SUM('[1]Summery Report'!C5) -> 0.623 | D2: =SUM('[1]Summery Report'!#REF!) -> #REF! | E2: =SUM('[1]Summery Report'!#REF!) -> #REF! | F2: 0.1
A3: =Gen!A12 -> 44288 | B3: =SUM('[1]Summery Report'!F6) -> 6159 | C3: =SUM('[1]Summery Report'!C6) -> 0.779 | D3: =SUM('[1]Summery Report'!#REF!) -> #REF! | E3: =SUM('[1]Summery Report'!#REF!) -> #REF! | F3: 0.1375
A4: =Gen!A13 -> 44289 | B4: =SUM('[1]Summery Report'!F7) -> 6580 | C4: =SUM('[1]Summery Report'!C7) -> 0.532 | D4: =SUM('[1]Summery Report'!#REF!) -> #REF! | E4: =SUM('[1]Summery Report'!#REF!) -> #REF! | F4: 0.0875
A5: =Gen!A14 -> 44290 | B5: =SUM('[1]Summery Report'!F8) -> 6223 | C5: =SUM('[1]Summery Report'!C8) -> 0.61 | D5: =SUM('[1]Summery Report'!#REF!) -> #REF! | E5: =SUM('[1]Summery Report'!#REF!) -> #REF! | F5: 0.225
A6: =Gen!A15 -> 44291 | B6: =SUM('[1]Summery Report'!F9) -> 5984 | C6: =SUM('[1]Summery Report'!C9) -> 0.688 | D6: =SUM('[1]Summery Report'!#REF!) -> #REF! | E6: =SUM('[1]Summery Report'!#REF!) -> #REF! | F6: 0.2
A7: =Gen!A16 -> 44292 | B7: =SUM('[1]Summery Report'!F10) -> 6103 | C7: =SUM('[1]Summery Report'!C10) -> 0.532 | D7: =SUM('[1]Summery Report'!#REF!) -> #REF! | E7: =SUM('[1]Summery Report'!#REF!) -> #REF! | F7: 0.35
A8: =Gen!A17 -> 44293 | B8: =SUM('[1]Summery Report'!F11) -> 5576 | C8: =SUM('[1]Summery Report'!C11) -> 0.753 | D8: =SUM('[1]Summery Report'!#REF!) -> #REF! | E8: =SUM('[1]Summery Report'!#REF!) -> #REF! | F8: 0.375
A9: =Gen!A18 -> 44294 | B9: =SUM('[1]Summery Report'!F12) -> 5532 | C9: =SUM('[1]Summery Report'!C12) -> 0.156 | D9: =SUM('[1]Summery Report'!#REF!) -> #REF! | E9: =SUM('[1]Summery Report'!#REF!) -> #REF! | F9: 0.325
A10: =Gen!A19 -> 44295 | B10: =SUM('[1]Summery Report'!F13) -> 6233 | C10: =SUM('[1]Summery Report'!C13) -> 0.442 | D10: =SUM('[1]Summery Report'!#REF!) -> #REF! | E10: =SUM('[1]Summery Report'!#REF!) -> #REF! | F10: 0.75
A11: =Gen!A20 -> 44296 | B11: =SUM('[1]Summery Report'!F14) -> 6063 | C11: =SUM('[1]Summery Report'!C14) -> 0.325 | D11: =SUM('[1]Summery Report'!#REF!) -> #REF! | E11: =SUM('[1]Summery Report'!#REF!) -> #REF! | F11: 0.7625
A12: =Gen!A21 -> 44297 | B12: =SUM('[1]Summery Report'!F15) -> 5967 | C12: =SUM('[1]Summery Report'!C15) -> 0.455 | D12: =SUM('[1]Summery Report'!#REF!) -> #REF! | E12: =SUM('[1]Summery Report'!#REF!) -> #REF! | F12: 0.1625
A13: =Gen!A22 -> 44298 | B13: =SUM('[1]Summery Report'!F16) -> 5863 | C13: =SUM('[1]Summery Report'!C16) -> 0.416 | D13: =SUM('[1]Summery Report'!#REF!) -> #REF! | E13: =SUM('[1]Summery Report'!#REF!) -> #REF! | F13: 0.1125
... A32: =Gen!A41 -> 0 | B32: =SUM('[1]Summery Report'!F35) -> 0 | C32: =SUM('[1]Summery Report'!C35) -> 0 | D32: =SUM('[1]Summery Report'!#REF!) -> #REF! | E32: =SUM('[1]Summery Report'!#REF!) -> #REF! | F32: 0.175
A33: =Gen!A42 -> 0 | B33: =[1]Gen!S41 -> 0

Sheet Lpg (2)
C3: Four Sasons Safari Lodge Serengeti
G6: VALUE | H6: Cost
A7: DATE | B7: A | C7: B | D7: C | F7: Meter Reading | G7: Total | H7: Occu | I7: No.of | J7: Kg
B8: 2Ton% | C8: 1Ton (%) | D8: 1Ton% | F8: consumption | G8: Consumption Kg | H8: % | I8: pax | J8: per pax
F9: 75771
A10: =Gen!A11 -> 44287 | B10: 0 | C10: 15 | D10: 85 | F10: 75790.2 | G10: =(F10-F9)*4.4 -> 84.48 | H10: =[5]Gen!B11 -> 0.077 | I10: =SUM(F10/H10) -> 984288.31 | J10: =SUM(G10/I10) -> 8.5828511e-05
A11: =Gen!A12 -> 44288 | B11: 0 | C11: 10 | D11: 85 | F11: 75809.87 | G11: =(F11-F10)*4.4 -> 86.548 | H11: =[5]Gen!B12 -> 0.091 | I11: =SUM(F11/H11) -> 833075.49 | J11: =SUM(G11/I11) -> 0.00010388974
A12: =Gen!A13 -> 44289 | B12: 0 | C12: 3 | D12: 85 | F12: 75830.09 | G12: =(F12-F11)*4.4 -> 88.968 | H12: =[5]Gen!B13 -> 0.013 | I12: =SUM(F12/H12) -> 5833083.8 | J12: =SUM(G12/I12) -> 1.5252309e-05
A13: =Gen!A14 -> 44290 | B13: 0 | C13: 0 | D13: 83 | F13: 75849.72 | G13: =(F13-F12)*4.4 -> 86.372 | H13: =[5]Gen!B14 -> 0.013 | I13: =SUM(F13/H13) -> 5834593.8 | J13: =SUM(G13/I13) -> 1.480343e-05
A14: =Gen!A15 -> 44291 | B14: 0 | C14: 0 | D14: 82 | F14: 75869.84 | G14: =(F14-F13)*4.4 -> 88.528 | H14: =[5]Gen!B15 -> 0.01 | I14: =SUM(F14/H14) -> 7586984 | J14: =SUM(G14/I14) -> 1.1668405e-05
A15: =Gen!A16 -> 44292 | B15: 0 | C15: 0 | D15: 81 | F15: 75888.68 | G15: =(F15-F14)*4.4 -> 82.896 | H15: =[5]Gen!B16 -> 0.01 | I15: =SUM(F15/H15) -> 7588868 | J15: =SUM(G15/I15) -> 1.0923368e-05
A16: =Gen!A17 -> 44293 | B16: 0 | C16: 0 | D16: 80 | F16: 75906.91 | G16: =(F16-F15)*4.4 -> 80.212 | H16: =[5]Gen!B17 -> 0.01 | I16: =SUM(F16/H16) -> 7590691 | J16: =SUM(G16/I16) -> 1.0567154e-05
A17: =Gen!A18 -> 44294 | B17: 0 | C17: 0 | D17: 80 | F17: 75926 | G17: =(F17-F16)*4.4 -> 83.996 | H17: =[5]Gen!B18 -> 0.01 | I17: =SUM(F17/H17) -> 7592600 | J17: =SUM(G17/I17) -> 1.1062877e-05
A18: =Gen!A19 -> 44295 | B18: 85 | C18: 85 | D18: 79 | F18: 75936 | G18: =(F18-F17)*4.4 -> 44 | H18: =[5]Gen!B19 -> 0.01 | I18: =SUM(F18/H18) -> 7593600 | J18: =SUM(G18/I18) -> 5.7943531e-06
A19: =Gen!A20 -> 44296 | B19: 85 | C19: 85 | D19: 79 | F19: 75956 | G19: =(F19-F18)*4.4 -> 88 | H19: =[5]Gen!B20 -> 0.01 | I19: =SUM(F19/H19) -> 7595600 | J19: =SUM(G19/I19) -> 1.1585655e-05
A20: =Gen!A21 -> 44297 | B20: 85 | C20: 85 | D20: 75 | F20: 75969.01 | G20: =(F20-F19)*4.4 -> 57.244 | H20: =[5]Gen!B21 -> 0.01 | I20: =SUM(F20/H20) -> 7596901 | J20: =SUM(G20/I20) -> 7.5351778e-06
A21: =Gen!A22 -> 44298 | B21: 85 | C21: 85 | D21: 65 | F21: 75983.63 | G21: =(F21-F20)*4.4 -> 64.328 | H21: =[5]Gen!B22 -> 0.03 | I21: =SUM(F21/H21) -> 2532787.7 | J21: =SUM(G21/I21) -> 2.5398102e-05
... A40: =Gen!A41 -> 0 | B40: 85 | C40: 85 | D40: 1 | F40: 76246.31 | G40: =(F40-F39)*4.4 -> 57.024 | H40: =[5]Gen!B41 -> 0.6369 | I40: =SUM(F40/H40) -> 119714.73 | J40: =SUM(G40/I40) -> 0.00047633237
G41: =(F41-F40)*4.4 -> -335483.76 | H41: =[5]Gen!B42 -> 0 | I41: =SUM(F41/H41) -> #DIV/0!
C42: TOTAL USAGE | E42: =SUM(E10:E40) -> 0 | F42: =SUM(F10:F41) -> 2356994.1 | G42: =SUM(G10:G40) -> 2091.364 | H42: =[5]Gen!B43 -> 0.18598065
B58: GAS TANK A | D58: GAS TANK B | G58: GAS TANK C

Sheet LPG_Graph
A1: Date | B1: Usage KG | C1: Occ %
A2: =Gen!A11 -> 44287 | B2: ='[1]Lpg (2)'!G10 -> 197.56 | C2: =SUM([1]Gen!B11) -> 0.623
A3: =Gen!A12 -> 44288 | B3: ='[1]Lpg (2)'!G11 -> 131.956 | C3: =SUM([1]Gen!B12) -> 0.779
A4: =Gen!A13 -> 44289 | B4: ='[1]Lpg (2)'!G12 -> 117.48 | C4: =SUM([1]Gen!B13) -> 0.532
A5: =Gen!A14 -> 44290 | B5: ='[1]Lpg (2)'!G13 -> 102.96 | C5: =SUM([1]Gen!B14) -> 0.61
A6: =Gen!A15 -> 44291 | B6: ='[1]Lpg (2)'!G14 -> 101.816 | C6: =SUM([1]Gen!B15) -> 0.688
A7: =Gen!A16 -> 44292 | B7: ='[1]Lpg (2)'!G15 -> 106.92 | C7: =SUM([1]Gen!B16) -> 0.532
A8: =Gen!A17 -> 44293 | B8: ='[1]Lpg (2)'!G16 -> 116.732 | C8: =SUM([1]Gen!B17) -> 0.753
A9: =Gen!A18 -> 44294 | B9: ='[1]Lpg (2)'!G17 -> 105.732 | C9: =SUM([1]Gen!B18) -> 0.156
A10: =Gen!A19 -> 44295 | B10: ='[1]Lpg (2)'!G18 -> 114.4 | C10: =SUM([1]Gen!B19) -> 0.442
A11: =Gen!A20 -> 44296 | B11: ='[1]Lpg (2)'!G19 -> 102.08 | C11: =SUM([1]Gen!B20) -> 0.325
A12: =Gen!A21 -> 44297 | B12: ='[1]Lpg (2)'!G20 -> 105.292 | C12: =SUM([1]Gen!B21) -> 0.455
A13: =Gen!A22 -> 44298 | B13: ='[1]Lpg (2)'!G21 -> 114.664 | C13: =SUM([1]Gen!B22) -> 0.416
... A32: =Gen!A41 -> 0 | B32: ='[1]Lpg (2)'!G40 -> 0 | C32: =SUM([1]Gen!B41) -> #REF!

Sheet Water-Meter
A1: Four Seasons Safari Lodge Serengeti - Water Report
C2: Main Meter | F2: KITCHEN | I2: Amani café | L2: Main SW POOL | O2: Laundry | S2: BORE HOLE NO.1 METER READING | V2: BORE HOLE NO.2 METER READING | Y2: BORE HOLE NO.3 METER READING | AB2: BORE HOLE NO.4 METER READING | AE2: BORE HOLE NO.5 METER READING | AH2: BORE HOLE NO.6 METER READING | AK2: RAIN WATER - METER READING | AN2: TOTAL WATER PRODUCTION
A3: DATE | C3: Open Bal | D3: Final | E3: consumption | F3: Open Bal | G3: Final | H3: consumption | I3: Open Bal | J3: Final | K3: consumption | L3: Open Bal | M3: Final | N3: consumption | O3: Open Bal | P3: Final | Q3: consumption | R3: Total consumption
S4: OPEN | T4: FINAL | U4: PROD. | V4: OPEN | W4: FINAL | X4: PROD. | Y4: OPEN | Z4: FINAL | AA4: PROD. | AB4: OPEN | AC4: FINAL | AD4: M3 | AE4: OPEN | AF4: FINAL | AG4: M3 | AH4: OPEN | AI4: FINAL | AJ4: M3 | AK4: OPEN | AL4: FINAL | AM4: M3
C5: =D4 -> 0 | D5: 252644 | E5: =IF((D5-D4)<0,"0",(D5-D4)) -> 252644 | F5: =G4 -> 0 | G5: 75790 | H5: 0 | I5: =J4 -> 0 | J5: 8362 | K5: =J5-J4 -> 8362 | L5: =M4 -> 0 | N5: 0 | O5: =P4 -> 0 | P5: 21110 | Q5: =IF((P5-P4)<0,"0",(P5-P4)) -> 21110 | T5: 67456 | V5: =W4 -> FINAL | W5: 73031 | X5: 0 | Y5: =Z4 -> FINAL | Z5: 89838 | AA5: 0 | AB5: =AC4 -> FINAL | AC5: 18773 | AE5: =AF4 -> FINAL | AF5: 18300 | AG5: 0 | AH5: =AI4 -> FINAL | AI5: 30309 | AK5: =AL4 -> FINAL
A6: =Gen!A11 -> 44287 | C6: =D5 -> 252644 | D6: 252733 | E6: =IF((D6-D5)<0,"0",(D6-D5)) -> 89 | F6: =G5 -> 75790 | G6: 75790 | H6: =IF((G6-G5)<0,"0",(G6-G5)) -> 0 | I6: =J5 -> 8362 | J6: 8364 | K6: =J6-J5 -> 2 | L6: =M5 -> 0 | N6: =IF((M6-M5)<0,"0",(M6-M5)) -> 0 | O6: =P5 -> 21110 | P6: 21117 | Q6: =IF((P6-P5)<0,"0",(P6-P5)) -> 7 | S6: =T5 -> 67456 | T6: 67537 | U6: =IF((T6-T5)<0,"0",(T6-T5)) -> 81 | V6: =W5 -> 73031 | W6: 73031 | X6: =IF((W6-W5)<0,"0",(W6-W5)) -> 0 | Y6: =Z5 -> 89838 | Z6: 89838 | AA6: =IF((Z6-Z5)<0,"0",(Z6-Z5)) -> 0 | AB6: =AC5 -> 18773 | AC6: 18788 | AD6: =IF((AC6-AC5)<0,"0",(AC6-AC5)) -> 15 | AE6: =AF5 -> 18300 | AF6: 18300 | AG6: =IF((AF6-AF5)<0,"0",(AF6-AF5)) -> 0 | AH6: =AI5 -> 30309 | AI6: 30335 | AJ6: =IF((AI6-AI5)<0,"0",(AI6-AI5)) -> 26 | AK6: =AL5 -> 0 | AM6: =IF((AL6-AL5)<0,"0",(AL6-AL5)) -> 0 | AN6: =U6+X6+AA6+AD6+AG6+AJ6+AM6 -> 122
A7: =Gen!A12 -> 44288 | C7: =D6 -> 252733 | D7: 252850 | E7: =IF((D7-D6)<0,"0",(D7-D6)) -> 117 | F7: =G6 -> 75790 | G7: 75790 | H7: =IF((G7-G6)<0,"0",(G7-G6)) -> 0 | I7: =J6 -> 8364 | J7: 8366 | K7: =J7-J6 -> 2 | L7: =M6 -> 0 | N7: =IF((M7-M6)<0,"0",(M7-M6)) -> 0 | O7: =P6 -> 21117 | P7: 21121 | Q7: =IF((P7-P6)<0,"0",(P7-P6)) -> 4 | S7: =T6 -> 67537 | T7: 67617 | U7: =IF((T7-T6)<0,"0",(T7-T6)) -> 80 | V7: =W6 -> 73031 | W7: 73031 | X7: =IF((W7-W6)<0,"0",(W7-W6)) -> 0 | Y7: =Z6 -> 89838 | Z7: 89838 | AA7: =IF((Z7-Z6)<0,"0",(Z7-Z6)) -> 0 | AB7: =AC6 -> 18788 | AC7: 18805 | AD7: =IF((AC7-AC6)<0,"0",(AC7-AC6)) -> 17 | AE7: =AF6 -> 18300 | AF7: 18300 | AG7: =IF((AF7-AF6)<0,"0",(AF7-AF6)) -> 0 | AH7: =AI6 -> 30335 | AI7: 30365 | AJ7: =IF((AI7-AI6)<0,"0",(AI7-AI6)) -> 30 | AK7: =AL6 -> 0 | AM7: =IF((AL7-AL6)<0,"0",(AL7-AL6)) -> 0 | AN7: =U7+X7+AA7+AD7+AG7+AJ7+AM7 -> 127
A8: =Gen!A13 -> 44289 | C8: =D7 -> 252850 | D8: 253017 | E8: =IF((D8-D7)<0,"0",(D8-D7)) -> 167 | F8: =G7 -> 75790 | G8: 75790 | H8: =IF((G8-G7)<0,"0",(G8-G7)) -> 0 | I8: =J7 -> 8366 | J8: 8368 | K8: =J8-J7 -> 2 | L8: =M7 -> 0 | N8: =IF((M8-M7)<0,"0",(M8-M7)) -> 0 | O8: =P7 -> 21121 | P8: 21126 | Q8: =IF((P8-P7)<0,"0",(P8-P7)) -> 5 | S8: =T7 -> 67617 | T8: 67705 | U8: =IF((T8-T7)<0,"0",(T8-T7)) -> 88 | V8: =W7 -> 73031 | W8: 73031 | X8: =IF((W8-W7)<0,"0",(W8-W7)) -> 0 | Y8: =Z7 -> 89838 | Z8: 89890 | AA8: =IF((Z8-Z7)<0,"0",(Z8-Z7)) -> 52 | AB8: =AC7 -> 18805 | AC8: 18820 | AD8: =IF((AC8-AC7)<0,"0",(AC8-AC7)) -> 15 | AE8: =AF7 -> 18300 | AF8: 18300 | AG8: =IF((AF8-AF7)<0,"0",(AF8-AF7)) -> 0 | AH8: =AI7 -> 30365 | AI8: 30382 | AJ8: =IF((AI8-AI7)<0,"0",(AI8-AI7)) -> 17 | AK8: =AL7 -> 0 | AM8: =IF((AL8-AL7)<0,"0",(AL8-AL7)) -> 0 | AN8: =U8+X8+AA8+AD8+AG8+AJ8+AM8 -> 172
A9: =Gen!A14 -> 44290 | C9: =D8 -> 253017 | D9: 253087 | E9: =IF((D9-D8)<0,"0",(D9-D8)) -> 70 | F9: =G8 -> 75790 | G9: 75790 | H9: =IF((G9-G8)<0,"0",(G9-G8)) -> 0 | I9: =J8 -> 8368 | J9: 8369 | K9: =J9-J8 -> 1 | L9: =M8 -> 0 | N9: =IF((M9-M8)<0,"0",(M9-M8)) -> 0 | O9: =P8 -> 21126 | P9: 21130 | Q9: =IF((P9-P8)<0,"0",(P9-P8)) -> 4 | S9: =T8 -> 67705 | T9: 67788 | U9: =IF((T9-T8)<0,"0",(T9-T8)) -> 83 | V9: =W8 -> 73031 | W9: 73031 | X9: =IF((W9-W8)<0,"0",(W9-W8)) -> 0 | Y9: =Z8 -> 89890 | Z9: 89938 | AA9: =IF((Z9-Z8)<0,"0",(Z9-Z8)) -> 48 | AB9: =AC8 -> 18820 | AC9: 18837 | AD9: =IF((AC9-AC8)<0,"0",(AC9-AC8)) -> 17 | AE9: =AF8 -> 18300 | AF9: 18300 | AG9: =IF((AF9-AF8)<0,"0",(AF9-AF8)) -> 0 | AH9: =AI9 -> 30420 | AI9: 30420 | AJ9: =IF((AI9-AI8)<0,"0",(AI9-AI8)) -> 38 | AK9: =AL8 -> 0 | AM9: =IF((AL9-AL8)<0,"0",(AL9-AL8)) -> 0 | AN9: =U9+X9+AA9+AD9+AG9+AJ9+AM9 -> 186
A10: =Gen!A15 -> 44291 | C10: =D9 -> 253087 | D10: 253146 | E10: =IF((D10-D9)<0,"0",(D10-D9)) -> 59 | F10: =G9 -> 75790 | G10: 75790 | H10: =IF((G10-G9)<0,"0",(G10-G9)) -> 0 | I10: =J9 -> 8369 | J10: 8371 | K10: =J10-J9 -> 2 | L10: =M9 -> 0 | N10: =IF((M10-M9)<0,"0",(M10-M9)) -> 0 | O10: =P9 -> 21130 | P10: 21134 | Q10: =IF((P10-P9)<0,"0",(P10-P9)) -> 4 | S10: =T9 -> 67788 | T10: 67868 | U10: =IF((T10-T9)<0,"0",(T10-T9)) -> 80 | V10: =W9 -> 73031 | W10: 73031 | X10: =IF((W10-W9)<0,"0",(W10-W9)) -> 0 | Y10: =Z9 -> 89938 | Z10: 89983 | AA10: =IF((Z10-Z9)<0,"0",(Z10-Z9)) -> 45 | AB10: =AC9 -> 18837 | AC10: 18852 | AD10: =IF((AC10-AC9)<0,"0",(AC10-AC9)) -> 15 | AE10: =AF9 -> 18300 | AF10: 18300 | AG10: =IF((AF10-AF9)<0,"0",(AF10-AF9)) -> 0 | AH10: =AI9 -> 30420 | AI10: 30446 | AJ10: =IF((AI10-AI9)<0,"0",(AI10-AI9)) -> 26 | AK10: =AL9 -> 0 | AM10: =IF((AL10-AL9)<0,"0",(AL10-AL9)) -> 0 | AN10: =U10+X10+AA10+AD10+AG10+AJ10+AM10 -> 166
A11: =Gen!A16 -> 44292 | C11: =D10 -> 253146 | D11: 253356 | E11: =IF((D11-D10)<0,"0",(D11-D10)) -> 210 | F11: =G10 -> 75790 | G11: 75790 | H11: =IF((G11-G10)<0,"0",(G11-G10)) -> 0 | I11: =J10 -> 8371 | J11: 8372 | K11: =J11-J10 -> 1 | L11: =M10 -> 0 | N11: =IF((M11-M10)<0,"0",(M11-M10)) -> 0 | O11: =P10 -> 21134 | P11: 21142 | Q11: =IF((P11-P10)<0,"0",(P11-P10)) -> 8 | S11: =T10 -> 67868 | T11: 67950 | U11: =IF((T11-T10)<0,"0",(T11-T10)) -> 82 | V11: =W10 -> 73031 | W11: 73031 | X11: =IF((W11-W10)<0,"0",(W11-W10)) -> 0 | Y11: =Z10 -> 89983 | Z11: 90033 | AA11: =IF((Z11-Z10)<0,"0",(Z11-Z10)) -> 50 | AB11: =AC10 -> 18852 | AC11: 18870 | AD11: =IF((AC11-AC10)<0,"0",(AC11-AC10)) -> 18 | AE11: =AF11 -> 18300 | AF11: 18300 | AG11: =IF((AF11-AF10)<0,"0",(AF11-AF10)) -> 0 | AH11: =AI10 -> 30446 | AI11: 30474 | AJ11: =IF((AI11-AI10)<0,"0",(AI11-AI10)) -> 28 | AK11: =AL10 -> 0 | AM11: =IF((AL11-AL10)<0,"0",(AL11-AL10)) -> 0 | AN11: =U11+X11+AA11+AD11+AG11+AJ11+AM11 -> 178
A12: =Gen!A17 -> 44293 | C12: =D11 -> 253356 | D12: 253416 | E12: =IF((D12-D11)<0,"0",(D12-D11)) -> 60 | F12: =G11 -> 75790 | G12: 75790 | H12: =IF((G12-G11)<0,"0",(G12-G11)) -> 0 | I12: =J11 -> 8372 | J12: 8374 | K12: =J12-J11 -> 2 | L12: =M11 -> 0 | N12: =IF((M12-M11)<0,"0",(M12-M11)) -> 0 | O12: =P11 -> 21142 | P12: 21145 | Q12: =IF((P12-P11)<0,"0",(P12-P11)) -> 3 | S12: =T11 -> 67950 | T12: 68031 | U12: =IF((T12-T11)<0,"0",(T12-T11)) -> 81 | V12: =W11 -> 73031 | W12: 73031 | X12: =IF((W12-W11)<0,"0",(W12-W11)) -> 0 | Y12: =Z11 -> 90033 | Z12: 90080 | AA12: =IF((Z12-Z11)<0,"0",(Z12-Z11)) -> 47 | AB12: =AC11 -> 18870 | AC12: 18886 | AD12: =IF((AC12-AC11)<0,"0",(AC12-AC11)) -> 16 | AE12: =AF12 -> 18300 | AF12: 18300 | AG12: =IF((AF12-AF11)<0,"0",(AF12-AF11)) -> 0 | AH12: =AI11 -> 30474 | AI12: 30502 | AJ12: =IF((AI12-AI11)<0,"0",(AI12-AI11)) -> 28 | AK12: =AL11 -> 0 | AM12: =IF((AL12-AL11)<0,"0",(AL12-AL11)) -> 0 | AN12: =U12+X12+AA12+AD12+AG12+AJ12+AM12 -> 172
A13: =Gen!A18 -> 44294 | C13: =D12 -> 253416 | D13: 253491 | E13: =IF((D13-D12)<0,"0",(D13-D12)) -> 75 | F13: =G12 -> 75790 | G13: 75790 | H13: =IF((G13-G12)<0,"0",(G13-G12)) -> 0 | I13: =J12 -> 8374 | J13: 8376 | K13: =J13-J12 -> 2 | L13: =M12 -> 0 | N13: =IF((M13-M12)<0,"0",(M13-M12)) -> 0 | O13: =P12 -> 21145 | P13: 21151 | Q13: =IF((P13-P12)<0,"0",(P13-P12)) -> 6 | S13: =T12 -> 68031 | T13: 68113 | U13: =IF((T13-T12)<0,"0",(T13-T12)) -> 82 | V13: =W12 -> 73031 | W13: 73031 | X13: =IF((W13-W12)<0,"0",(W13-W12)) -> 0 | Y13: =Z12 -> 90080 | Z13: 90128 | AA13: =IF((Z13-Z12)<0,"0",(Z13-Z12)) -> 48 | AB13: =AC12 -> 18886 | AC13: 18902 | AD13: =IF((AC13-AC12)<0,"0",(AC13-AC12)) -> 16 | AE13: =AF13 -> 18300 | AF13: 18300 | AG13: =IF((AF13-AF12)<0,"0",(AF13-AF12)) -> 0 | AH13: =AI12 -> 30502 | AI13: 30529 | AJ13: =IF((AI13-AI12)<0,"0",(AI13-AI12)) -> 27 | AK13: =AL12 -> 0 | AM13: =IF((AL13-AL12)<0,"0",(AL13-AL12)) -> 0 | AN13: =U13+X13+AA13+AD13+AG13+AJ13+AM13 -> 173
A14: =Gen!A19 -> 44295 | C14: =D13 -> 253491 | D14: 253538 | E14: =IF((D14-D13)<0,"0",(D14-D13)) -> 47 | F14: =G13 -> 75790 | G14: 75790 | H14: =IF((G14-G13)<0,"0",(G14-G13)) -> 0 | I14: =J13 -> 8376 | J14: 8377 | K14: =IF((J14-J13)<0,"0",(J14-J13)) -> 1 | L14: =M13 -> 0 | N14: =IF((M14-M13)<0,"0",(M14-M13)) -> 0 | O14: =P13 -> 21151 | P14: 21155 | Q14: =IF((P14-P13)<0,"0",(P14-P13)) -> 4 | S14: =T13 -> 68113 | T14: 68194 | U14: =IF((T14-T13)<0,"0",(T14-T13)) -> 81 | V14: =W13 -> 73031 | W14: 73031 | X14: =IF((W14-W13)<0,"0",(W14-W13)) -> 0 | Y14: =Z13 -> 90128 | Z14: 90129 | AA14: =IF((Z14-Z13)<0,"0",(Z14-Z13)) -> 1 | AB14: =AC13 -> 18902 | AC14: 18918 | AD14: =IF((AC14-AC13)<0,"0",(AC14-AC13)) -> 16 | AE14: =AF14 -> 18300 | AF14: 18300 | AG14: =IF((AF14-AF13)<0,"0",(AF14-AF13)) -> 0 | AH14: =AI13 -> 30529 | AI14: 30557 | AJ14: =IF((AI14-AI13)<0,"0",(AI14-AI13)) -> 28 | AK14: =AL13 -> 0 | AM14: =IF((AL14-AL13)<0,"0",(AL14-AL13)) -> 0 | AN14: =U14+X14+AA14+AD14+AG14+AJ14+AM14 -> 126
A15: =Gen!A20 -> 44296 | C15: =D14 -> 253538 | D15: 253584 | E15: =IF((D15-D14)<0,"0",(D15-D14)) -> 46 | F15: =G14 -> 75790 | G15: 75790 | H15: =IF((G15-G14)<0,"0",(G15-G14)) -> 0 | I15: =J14 -> 8377 | J15: 8379 | K15: =IF((J15-J14)<0,"0",(J15-J14)) -> 2 | L15: =M14 -> 0 | N15: =IF((M15-M14)<0,"0",(M15-M14)) -> 0 | O15: =P14 -> 21155 | P15: 21158 | Q15: =IF((P15-P14)<0,"0",(P15-P14)) -> 3 | S15: =T14 -> 68194 | T15: 68194 | U15: =IF((T15-T14)<0,"0",(T15-T14)) -> 0 | V15: =W14 -> 73031 | W15: 73031 | X15: =IF((W15-W14)<0,"0",(W15-W14)) -> 0 | Y15: =Z14 -> 90129 | Z15: 90129 | AA15: =IF((Z15-Z14)<0,"0",(Z15-Z14)) -> 0 | AB15: =AC14 -> 18918 | AC15: 18935 | AD15: =IF((AC15-AC14)<0,"0",(AC15-AC14)) -> 17 | AE15: =AF15 -> 18300 | AF15: 18300 | AG15: =IF((AF15-AF14)<0,"0",(AF15-AF14)) -> 0 | AH15: =AI14 -> 30557 | AI15: 30584 | AJ15: =IF((AI15-AI14)<0,"0",(AI15-AI14)) -> 27 | AK15: =AL14 -> 0 | AM15: =IF((AL15-AL14)<0,"0",(AL15-AL14)) -> 0 | AN15: =U15+X15+AA15+AD15+AG15+AJ15+AM15 -> 44
A16: =Gen!A21 -> 44297 | C16: =D15 -> 253584 | D16: 253634 | E16: =IF((D16-D15)<0,"0",(D16-D15)) -> 50 | F16: =G15 -> 75790 | G16: 75790 | H16: =IF((G16-G15)<0,"0",(G16-G15)) -> 0 | I16: =J15 -> 8379 | J16: 8381 | K16: =IF((J16-J15)<0,"0",(J16-J15)) -> 2 | L16: =M15 -> 0 | N16: =IF((M16-M15)<0,"0",(M16-M15)) -> 0 | O16: =P15 -> 21158 | P16: 21161 | Q16: =IF((P16-P15)<0,"0",(P16-P15)) -> 3 | S16: =T15 -> 68194 | T16: 68194 | U16: =IF((T16-T15)<0,"0",(T16-T15)) -> 0 | V16: =W15 -> 73031 | W16: 73031 | X16: =IF((W16-W15)<0,"0",(W16-W15)) -> 0 | Y16: =Z15 -> 90129 | Z16: 90129 | AA16: =IF((Z16-Z15)<0,"0",(Z16-Z15)) -> 0 | AB16: =AC15 -> 18935 | AC16: 18952 | AD16: =IF((AC16-AC15)<0,"0",(AC16-AC15)) -> 17 | AE16: =AF16 -> 18300 | AF16: 18300 | AG16: =IF((AF16-AF15)<0,"0",(AF16-AF15)) -> 0 | AH16: =AI15 -> 30584 | AI16: 30610 | AJ16: =IF((AI16-AI15)<0,"0",(AI16-AI15)) -> 26 | AK16: =AL15 -> 0 | AM16: =IF((AL16-AL15)<0,"0",(AL16-AL15)) -> 0 | AN16: =U16+X16+AA16+AD16+AG16+AJ16+AM16 -> 43
A17: =Gen!A22 -> 44298 | C17: =D16 -> 253634 | D17: 253695 | E17: =IF((D17-D16)<0,"0",(D17-D16)) -> 61 | F17: =G16 -> 75790 | G17: 75790 | H17: =IF((G17-G16)<0,"0",(G17-G16)) -> 0 | I17: =J16 -> 8381 | J17: 8382 | K17: =IF((J17-J16)<0,"0",(J17-J16)) -> 1 | L17: =M16 -> 0 | N17: =IF((M17-M16)<0,"0",(M17-M16)) -> 0 | O17: =P16 -> 21161 | P17: 21167 | Q17: =IF((P17-P16)<0,"0",(P17-P16)) -> 6 | S17: =T16 -> 68194 | T17: 68194 | U17: =IF((T17-T16)<0,"0",(T17-T16)) -> 0 | V17: =W16 -> 73031 | W17: 73031 | X17: =IF((W17-W16)<0,"0",(W17-W16)) -> 0 | Y17: =Z16 -> 90129 | Z17: 90129 | AA17: =IF((Z17-Z16)<0,"0",(Z17-Z16)) -> 0 | AB17: =AC16 -> 18952 | AC17: 18968 | AD17: =IF((AC17-AC16)<0,"0",(AC17-AC16)) -> 16 | AE17: =AF17 -> 18300 | AF17: 18300 | AG17: =IF((AF17-AF16)<0,"0",(AF17-AF16)) -> 0 | AH17: =AI16 -> 30610 | AI17: 30643 | AJ17: =IF((AI17-AI16)<0,"0",(AI17-AI16)) -> 33 | AK17: =AL16 -> 0 | AM17: =IF((AL17-AL16)<0,"0",(AL17-AL16)) -> 0 | AN17: =U17+X17+AA17+AD17+AG17+AJ17+AM17 -> 49
A18: =Gen!A23 -> 44299 | C18: =D17 -> 253695 | D18: 253876 | E18: =IF((D18-D17)<0,"0",(D18-D17)) -> 181 | F18: =G17 -> 75790 | G18: 75790 | H18: =IF((G18-G17)<0,"0",(G18-G17)) -> 0 | J18: 8383 | K18: =IF((J18-J17)<0,"0",(J18-J17)) -> 1 | L18: =M17 -> 0 | N18: =IF((M18-M17)<0,"0",(M18-M17)) -> 0 | O18: =P17 -> 21167 | P18: 21169 | Q18: =IF((P18-P17)<0,"0",(P18-P17)) -> 2 | S18: =T17 -> 68194 | T18: 68194 | U18: =IF((T18-T17)<0,"0",(T18-T17)) -> 0 | V18: =W17 -> 73031 | W18: 73031 | X18: =IF((W18-W17)<0,"0",(W18-W17)) -> 0 | Y18: =Z17 -> 90129 | Z18: 90129 | AA18: =IF((Z18-Z17)<0,"0",(Z18-Z17)) -> 0 | AB18: =AC17 -> 18968 | AC18: 18984 | AD18: =IF((AC18-AC17)<0,"0",(AC18-AC17)) -> 16 | AE18: =AF18 -> 18300 | AF18: 18300 | AG18: =IF((AF18-AF17)<0,"0",(AF18-AF17)) -> 0 | AH18: =AI17 -> 30643 | AI18: 30672 | AJ18: =IF((AI18-AI17)<0,"0",(AI18-AI17)) -> 29 | AK18: =AL17 -> 0 | AM18: =IF((AL18-AL17)<0,"0",(AL18-AL17)) -> 0 | AN18: =U18+X18+AA18+AD18+AG18+AJ18+AM18 -> 45
A19: =Gen!A24 -> 44300 | C19: =D18 -> 253876 | D19: 253922 | E19: =IF((D19-D18)<0,"0",(D19-D18)) -> 46 | F19: =G18 -> 75790 | G19: 75790 | H19: =IF((G19-G18)<0,"0",(G19-G18)) -> 0 | I19: =J18 -> 8383 | J19: 8384 | K19: =IF((J19-J18)<0,"0",(J19-J18)) -> 1 | L19: =M18 -> 0 | N19: =IF((M19-M18)<0,"0",(M19-M18)) -> 0 | O19: =P18 -> 21169 | P19: 21171 | Q19: =IF((P19-P18)<0,"0",(P19-P18)) -> 2 | S19: =T18 -> 68194 | T19: 68283 | U19: =IF((T19-T18)<0,"0",(T19-T18)) -> 89 | V19: =W18 -> 73031 | W19: 73031 | X19: =IF((W19-W18)<0,"0",(W19-W18)) -> 0 | Y19: =Z18 -> 90129 | Z19: 90129 | AA19: =IF((Z19-Z18)<0,"0",(Z19-Z18)) -> 0 | AB19: =AC18 -> 18984 | AC19: 19001 | AD19: =IF((AC19-AC18)<0,"0",(AC19-AC18)) -> 17 | AE19: =AF19 -> 18300 | AF19: 18300 | AG19: =IF((AF19-AF18)<0,"0",(AF19-AF18)) -> 0 | AH19: =AI18 -> 30672 | AI19: 30691 | AJ19: =IF((AI19-AI18)<0,"0",(AI19-AI18)) -> 19 | AK19: =AL18 -> 0 | AM19: =IF((AL19-AL18)<0,"0",(AL19-AL18)) -> 0 | AN19: =U19+X19+AA19+AD19+AG19+AJ19+AM19 -> 125
A20: =Gen!A25 -> 44301 | C20: =D19 -> 253922 | D20: 253969 | E20: =IF((D20-D19)<0,"0",(D20-D19)) -> 47 | F20: =G19 -> 75790 | G20: 75790 | H20: =IF((G20-G19)<0,"0",(G20-G19)) -> 0 | I20: =J19 -> 8384 | J20: 8385 | K20: =IF((J20-J19)<0,"0",(J20-J19)) -> 1 | L20: =M19 -> 0 | N20: =IF((M20-M19)<0,"0",(M20-M19)) -> 0 | O20: =P19 -> 21171 | P20: 21176 | Q20: =IF((P20-P19)<0,"0",(P20-P19)) -> 5 | S20: =T19 -> 68283 | T20: 68365 | U20: =IF((T20-T19)<0,"0",(T20-T19)) -> 82 | V20: =W19 -> 73031 | W20: 73031 | X20: =IF((W20-W19)<0,"0",(W20-W19)) -> 0 | Y20: =Z19 -> 90129 | Z20: 90129 | AA20: =IF((Z20-Z19)<0,"0",(Z20-Z19)) -> 0 | AB20: =AC19 -> 19001 | AC20: 19017 | AD20: =IF((AC20-AC19)<0,"0",(AC20-AC19)) -> 16 | AE20: =AF20 -> 18300 | AF20: 18300 | AG20: =IF((AF20-AF19)<0,"0",(AF20-AF19)) -> 0 | AH20: =AI19 -> 30691 | AI20: 30730 | AJ20: =IF((AI20-AI19)<0,"0",(AI20-AI19)) -> 39 | AK20: =AL19 -> 0 | AM20: =IF((AL20-AL19)<0,"0",(AL20-AL19)) -> 0 | AN20: =U20+X20+AA20+AD20+AG20+AJ20+AM20 -> 137
A21: =Gen!A26 -> 44302 | C21: =D20 -> 253969 | D21: 254009 | E21: =IF((D21-D20)<0,"0",(D21-D20)) -> 40 | F21: =G20 -> 75790 | G21: 75790 | H21: =IF((G21-G20)<0,"0",(G21-G20)) -> 0 | I21: =J20 -> 8385 | J21: 8387 | K21: =IF((J21-J20)<0,"0",(J21-J20)) -> 2 | L21: =M20 -> 0 | N21: =IF((M21-M20)<0,"0",(M21-M20)) -> 0 | O21: =P20 -> 21176 | P21: 21178 | Q21: =IF((P21-P20)<0,"0",(P21-P20)) -> 2 | S21: =T20 -> 68365 | T21: 68447 | U21: =IF((T21-T20)<0,"0",(T21-T20)) -> 82 | V21: =W20 -> 73031 | W21: 73031 | X21: =IF((W21-W20)<0,"0",(W21-W20)) -> 0 | Y21: =Z20 -> 90129 | Z21: 90129 | AA21: =IF((Z21-Z20)<0,"0",(Z21-Z20)) -> 0 | AB21: =AC20 -> 19017 | AC21: 19034 | AD21: =IF((AC21-AC20)<0,"0",(AC21-AC20)) -> 17 | AE21: =AF20 -> 18300 | AF21: 18300 | AG21: =IF((AF21-AF20)<0,"0",(AF21-AF20)) -> 0 | AH21: =AI20 -> 30730 | AI21: 30759 | AJ21: =IF((AI21-AI20)<0,"0",(AI21-AI20)) -> 29 | AK21: =AL20 -> 0 | AM21: =IF((AL21-AL20)<0,"0",(AL21-AL20)) -> 0 | AN21: =U21+X21+AA21+AD21+AG21+AJ21+AM21 -> 128
A22: =Gen!A27 -> 44303 | C22: =D21 -> 254009 | D22: 254061 | E22: =IF((D22-D21)<0,"0",(D22-D21)) -> 52 | F22: =G21 -> 75790 | G22: 75790 | H22: =IF((G22-G21)<0,"0",(G22-G21)) -> 0 | I22: =J21 -> 8387 | J22: 8389 | K22: =IF((J22-J21)<0,"0",(J22-J21)) -> 2 | L22: =M21 -> 0 | N22: =IF((M22-M21)<0,"0",(M22-M21)) -> 0 | O22: =P21 -> 21178 | P22: 21183 | Q22: =IF((P22-P21)<0,"0",(P22-P21)) -> 5 | S22: =T21 -> 68447 | T22: 68528 | U22: =IF((T22-T21)<0,"0",(T22-T21)) -> 81 | V22: =W21 -> 73031 | W22: 73031 | X22: =IF((W22-W21)<0,"0",(W22-W21)) -> 0 | Y22: =Z21 -> 90129 | Z22: 90129 | AA22: =IF((Z22-Z21)<0,"0",(Z22-Z21)) -> 0 | AB22: =AC21 -> 19034 | AC22: 19050 | AD22: =IF((AC22-AC21)<0,"0",(AC22-AC21)) -> 16 | AE22: =AF21 -> 18300 | AF22: 18300 | AG22: =IF((AF22-AF21)<0,"0",(AF22-AF21)) -> 0 | AH22: =AI21 -> 30759 | AI22: 30787 | AJ22: =IF((AI22-AI21)<0,"0",(AI22-AI21)) -> 28 | AK22: =AL21 -> 0 | AM22: =IF((AL22-AL21)<0,"0",(AL22-AL21)) -> 0 | AN22: =U22+X22+AA22+AD22+AG22+AJ22+AM22 -> 125
A23: =Gen!A28 -> 44304 | C23: =D22 -> 254061 | D23: 254114 | E23: =IF((D23-D22)<0,"0",(D23-D22)) -> 53 | F23: =G22 -> 75790 | G23: 75790 | H23: =IF((G23-G22)<0,"0",(G23-G22)) -> 0 | I23: =J22 -> 8389 | J23: 8390 | K23: =IF((J23-J22)<0,"0",(J23-J22)) -> 1 | L23: =M22 -> 0 | N23: =IF((M23-M22)<0,"0",(M23-M22)) -> 0 | O23: =P22 -> 21183 | P23: 21187 | Q23: =IF((P23-P22)<0,"0",(P23-P22)) -> 4 | S23: =T22 -> 68528 | T23: 68609 | U23: =IF((T23-T22)<0,"0",(T23-T22)) -> 81 | V23: =W22 -> 73031 | W23: 73031 | X23: =IF((W23-W22)<0,"0",(W23-W22)) -> 0 | Y23: =Z22 -> 90129 | Z23: 90129 | AA23: =IF((Z23-Z22)<0,"0",(Z23-Z22)) -> 0 | AB23: =AC22 -> 19050 | AC23: 19067 | AD23: =IF((AC23-AC22)<0,"0",(AC23-AC22)) -> 17 | AE23: =AF22 -> 18300 | AF23: 18300 | AG23: =IF((AF23-AF22)<0,"0",(AF23-AF22)) -> 0 | AH23: =AI22 -> 30787 | AI23: 30814 | AJ23: =IF((AI23-AI22)<0,"0",(AI23-AI22)) -> 27 | AK23: =AL22 -> 0 | AM23: =IF((AL23-AL22)<0,"0",(AL23-AL22)) -> 0 | AN23: =U23+X23+AA23+AD23+AG23+AJ23+AM23 -> 125
A24: =Gen!A29 -> 44305 | C24: =D23 -> 254114 | D24: 254172 | E24: =IF((D24-D23)<0,"0",(D24-D23)) -> 58 | F24: =G23 -> 75790 | G24: 75790 | H24: =IF((G24-G23)<0,"0",(G24-G23)) -> 0 | I24: =J23 -> 8390 | J24: 8391 | K24: =IF((J24-J23)<0,"0",(J24-J23)) -> 1 | L24: =M23 -> 0 | N24: =IF((M24-M23)<0,"0",(M24-M23)) -> 0 | O24: =P23 -> 21187 | P24: 21191 | Q24: =IF((P24-P23)<0,"0",(P24-P23)) -> 4 | S24: =T23 -> 68609 | T24: 68609 | U24: =IF((T24-T23)<0,"0",(T24-T23)) -> 0 | V24: =W23 -> 73031 | W24: 73031 | X24: =IF((W24-W23)<0,"0",(W24-W23)) -> 0 | Y24: =Z23 -> 90129 | Z24: 90129 | AA24: =IF((Z24-Z23)<0,"0",(Z24-Z23)) -> 0 | AB24: =AC23 -> 19067 | AC24: 19083 | AD24: =IF((AC24-AC23)<0,"0",(AC24-AC23)) -> 16 | AE24: =AF23 -> 18300 | AF24: 18300 | AG24: =IF((AF24-AF23)<0,"0",(AF24-AF23)) -> 0 | AH24: =AI23 -> 30814 | AI24: 30844 | AJ24: =IF((AI24-AI23)<0,"0",(AI24-AI23)) -> 30 | AK24: =AL23 -> 0 | AM24: =IF((AL24-AL23)<0,"0",(AL24-AL23)) -> 0 | AN24: =U24+X24+AA24+AD24+AG24+AJ24+AM24 -> 46
A25: =Gen!A30 -> 44306 | C25: =D24 -> 254172 | D25: 254238 | E25: =IF((D25-D24)<0,"0",(D25-D24)) -> 66 | F25: =G24 -> 75790 | G25: 75790 | H25: =IF((G26-G24)<0,"0",(G26-G24)) -> 0 | I25: =J24 -> 8391 | J25: 8392 | K25: =IF((J25-J24)<0,"0",(J25-J24)) -> 1 | L25: =M24 -> 0 | N25: =IF((M25-M24)<0,"0",(M25-M24)) -> 0 | O25: =P24 -> 21191 | P25: 21194 | Q25: =IF((P25-P24)<0,"0",(P25-P24)) -> 3 | S25: =T24 -> 68609 | T25: 68609 | U25: =IF((T25-T24)<0,"0",(T25-T24)) -> 0 | V25: =W24 -> 73031 | W25: 73031 | X25: =IF((W25-W24)<0,"0",(W25-W24)) -> 0 | Y25: =Z24 -> 90129 | Z25: 90129 | AA25: =IF((Z25-Z24)<0,"0",(Z25-Z24)) -> 0 | AB25: =AC24 -> 19083 | AC25: 19099 | AD25: =IF((AC25-AC24)<0,"0",(AC25-AC24)) -> 16 | AE25: =AF24 -> 18300 | AF25: 18300 | AG25: =IF((AF25-AF24)<0,"0",(AF25-AF24)) -> 0 | AH25: =AI24 -> 30844 | AI25: 30872 | AJ25: =IF((AI25-AI24)<0,"0",(AI25-AI24)) -> 28 | AK25: =AL24 -> 0 | AM25: =IF((AL25-AL24)<0,"0",(AL25-AL24)) -> 0 | AN25: =U25+X25+AA25+AD25+AG25+AJ25+AM25 -> 44
A26: =Gen!A31 -> 44307 | C26: =D25 -> 254238 | D26: 254285 | E26: =IF((D26-D25)<0,"0",(D26-D25)) -> 47 | F26: =G26 -> 75790 | G26: 75790 | H26: =IF((G27-G25)<0,"0",(G27-G25)) -> 0 | I26: =J25 -> 8392 | J26: 8395 | K26: =IF((J26-J25)<0,"0",(J26-J25)) -> 3 | L26: =M25 -> 0 | N26: =IF((M26-M25)<0,"0",(M26-M25)) -> 0 | O26: =P25 -> 21194 | P26: 21197 | Q26: =IF((P26-P25)<0,"0",(P26-P25)) -> 3 | S26: =T25 -> 68609 | T26: 68609 | U26: =IF((T26-T25)<0,"0",(T26-T25)) -> 0 | V26: =W25 -> 73031 | W26: 73031 | X26: =IF((W26-W25)<0,"0",(W26-W25)) -> 0 | Y26: =Z25 -> 90129 | Z26: 90129 | AA26: =IF((Z26-Z25)<0,"0",(Z26-Z25)) -> 0 | AB26: =AC25 -> 19099 | AC26: 19116 | AD26: =IF((AC26-AC25)<0,"0",(AC26-AC25)) -> 17 | AE26: =AF25 -> 18300 | AF26: 18300 | AG26: =IF((AF26-AF25)<0,"0",(AF26-AF25)) -> 0 | AH26: =AI25 -> 30872 | AI26: 30901 | AJ26: =IF((AI26-AI25)<0,"0",(AI26-AI25)) -> 29 | AK26: =AL25 -> 0 | AM26: =IF((AL26-AL25)<0,"0",(AL26-AL25)) -> 0 | AN26: =U26+X26+AA26+AD26+AG26+AJ26+AM26 -> 46
A27: =Gen!A32 -> 44308 | C27: =D26 -> 254285 | D27: 254335 | E27: =IF((D27-D26)<0,"0",(D27-D26)) -> 50 | F27: =G27 -> 75790 | G27: 75790 | H27: =IF((G28-G26)<0,"0",(G28-G26)) -> 0 | I27: =J26 -> 8395 | J27: 8397 | K27: =IF((J27-J26)<0,"0",(J27-J26)) -> 2 | L27: =M26 -> 0 | N27: =IF((M27-M26)<0,"0",(M27-M26)) -> 0 | O27: =P26 -> 21197 | P27: 21203 | Q27: =IF((P27-P26)<0,"0",(P27-P26)) -> 6 | S27: =T26 -> 68609 | T27: 68670 | U27: =IF((T27-T26)<0,"0",(T27-T26)) -> 61 | V27: =W26 -> 73031 | W27: 73031 | X27: =IF((W27-W26)<0,"0",(W27-W26)) -> 0 | Y27: =Z26 -> 90129 | Z27: 90129 | AA27: =IF((Z27-Z26)<0,"0",(Z27-Z26)) -> 0 | AB27: =AC26 -> 19116 | AC27: 19132 | AD27: =IF((AC27-AC26)<0,"0",(AC27-AC26)) -> 16 | AE27: =AF26 -> 18300 | AF27: 18300 | AG27: =IF((AF27-AF26)<0,"0",(AF27-AF26)) -> 0 | AH27: =AI26 -> 30901 | AI27: 30929 | AJ27: =IF((AI27-AI26)<0,"0",(AI27-AI26)) -> 28 | AK27: =AL26 -> 0 | AM27: =IF((AL27-AL26)<0,"0",(AL27-AL26)) -> 0 | AN27: =U27+X27+AA27+AD27+AG27+AJ27+AM27 -> 105
A28: =Gen!A33 -> 44309 | C28: =D27 -> 254335 | D28: 254382 | E28: =IF((D28-D27)<0,"0",(D28-D27)) -> 47 | F28: =G28 -> 75790 | G28: 75790 | H28: =IF((G28-G27)<0,"0",(G28-G27)) -> 0 | I28: =J27 -> 8397 | J28: 8398 | K28: =IF((J28-J27)<0,"0",(J28-J27)) -> 1 | L28: =M27 -> 0 | N28: =IF((M28-M27)<0,"0",(M28-M27)) -> 0 | O28: =P27 -> 21203 | P28: 21205 | Q28: =IF((P28-P27)<0,"0",(P28-P27)) -> 2 | S28: =T27 -> 68670 | T28: 68752 | U28: =IF((T28-T27)<0,"0",(T28-T27)) -> 82 | V28: =W27 -> 73031 | W28: 73031 | X28: =IF((W28-W27)<0,"0",(W28-W27)) -> 0 | Y28: =Z27 -> 90129 | Z28: 90129 | AA28: =IF((Z28-Z27)<0,"0",(Z28-Z27)) -> 0 | AB28: =AC27 -> 19132 | AC28: 19148 | AD28: =IF((AC28-AC27)<0,"0",(AC28-AC27)) -> 16 | AE28: =AF27 -> 18300 | AF28: 18300 | AG28: =IF((AF28-AF27)<0,"0",(AF28-AF27)) -> 0 | AH28: =AI27 -> 30929 | AI28: 30959 | AJ28: =IF((AI28-AI27)<0,"0",(AI28-AI27)) -> 30 | AK28: =AL27 -> 0 | AM28: =IF((AL28-AL27)<0,"0",(AL28-AL27)) -> 0 | AN28: =U28+X28+AA28+AD28+AG28+AJ28+AM28 -> 128
A29: =Gen!A34 -> 44310 | C29: =D28 -> 254382 | D29: 254438 | E29: =IF((D29-D28)<0,"0",(D29-D28)) -> 56 | F29: =G29 -> 75790 | G29: 75790 | H29: =IF((G29-G28)<0,"0",(G29-G28)) -> 0 | I29: =J28 -> 8398 | J29: 8399 | K29: =IF((J29-J28)<0,"0",(J29-J28)) -> 1 | L29: =M28 -> 0 | N29: =IF((M29-M28)<0,"0",(M29-M28)) -> 0 | O29: =P28 -> 21205 | P29: 21205 | Q29: =IF((P29-P28)<0,"0",(P29-P28)) -> 0 | S29: =T28 -> 68752 | T29: 68835 | U29: =IF((T29-T28)<0,"0",(T29-T28)) -> 83 | V29: =W28 -> 73031 | W29: 73031 | X29: =IF((W29-W28)<0,"0",(W29-W28)) -> 0 | Y29: =Z28 -> 90129 | Z29: 90129 | AA29: =IF((Z29-Z28)<0,"0",(Z29-Z28)) -> 0 | AB29: =AC28 -> 19148 | AC29: 19165 | AD29: =IF((AC29-AC28)<0,"0",(AC29-AC28)) -> 17 | AE29: =AF28 -> 18300 | AF29: 18300 | AG29: =IF((AF29-AF28)<0,"0",(AF29-AF28)) -> 0 | AH29: =AI28 -> 30959 | AI29: 30987 | AJ29: =IF((AI29-AI28)<0,"0",(AI29-AI28)) -> 28 | AK29: =AL28 -> 0 | AM29: =IF((AL29-AL28)<0,"0",(AL29-AL28)) -> 0 | AN29: =U29+X29+AA29+AD29+AG29+AJ29+AM29 -> 128
A30: =Gen!A35 -> 44311 | C30: =D29 -> 254438 | D30: 254484 | E30: =IF((D30-D29)<0,"0",(D30-D29)) -> 46 | F30: =G30 -> 75790 | G30: 75790 | H30: =IF((G30-G29)<0,"0",(G30-G29)) -> 0 | I30: =J29 -> 8399 | J30: 8401 | K30: =IF((J30-J29)<0,"0",(J30-J29)) -> 2 | L30: =M29 -> 0 | N30: =IF((M30-M29)<0,"0",(M30-M29)) -> 0 | O30: =P29 -> 21205 | P30: 21209 | Q30: =IF((P30-P29)<0,"0",(P30-P29)) -> 4 | S30: =T29 -> 68835 | T30: 68916 | U30: =IF((T30-T29)<0,"0",(T30-T29)) -> 81 | V30: =W29 -> 73031 | W30: 73031 | X30: =IF((W31-W29)<0,"0",(W31-W29)) -> 0 | Y30: =Z29 -> 90129 | Z30: 90129 | AA30: =IF((Z30-Z29)<0,"0",(Z30-Z29)) -> 0 | AB30: =AC29 -> 19165 | AC30: 19181 | AD30: =IF((AC30-AC29)<0,"0",(AC30-AC29)) -> 16 | AE30: =AF29 -> 18300 | AF30: 18300 | AG30: =IF((AF30-AF29)<0,"0",(AF30-AF29)) -> 0 | AH30: =AI29 -> 30987 | AI30: 31017 | AJ30: =IF((AI30-AI29)<0,"0",(AI30-AI29)) -> 30 | AK30: =AL29 -> 0 | AM30: =IF((AL30-AL29)<0,"0",(AL30-AL29)) -> 0 | AN30: =U30+X30+AA30+AD30+AG30+AJ30+AM30 -> 127
A31: =Gen!A36 -> 44312 | C31: =D30 -> 254484 | D31: 254537 | E31: =IF((D31-D30)<0,"0",(D31-D30)) -> 53 | F31: =G31 -> 75790 | G31: 75790 | H31: =IF((G31-G30)<0,"0",(G31-G30)) -> 0 | I31: =J30 -> 8401 | J31: 8404 | K31: =IF((J31-J30)<0,"0",(J31-J30)) -> 3 | L31: =M30 -> 0 | N31: =IF((M31-M30)<0,"0",(M31-M30)) -> 0 | O31: =P30 -> 21209 | P31: 21213 | Q31: =IF((P31-P30)<0,"0",(P31-P30)) -> 4 | S31: =T30 -> 68916 | T31: 68997 | U31: =IF((T31-T30)<0,"0",(T31-T30)) -> 81 | V31: =W31 -> 73031 | W31: 73031 | X31: =IF((#REF!-W31)<0,"0",(#REF!-W31)) -> #REF! | Y31: =Z30 -> 90129 | Z31: 90129 | AA31: =IF((Z31-Z30)<0,"0",(Z31-Z30)) -> 0 | AB31: =AC30 -> 19181 | AC31: 19198 | AD31: =IF((AC31-AC30)<0,"0",(AC31-AC30)) -> 17 | AE31: =AF30 -> 18300 | AF31: 18300 | AG31: =IF((AF31-AF30)<0,"0",(AF31-AF30)) -> 0 | AH31: =AI30 -> 31017 | AI31: 31045 | AJ31: =IF((AI31-AI30)<0,"0",(AI31-AI30)) -> 28 | AK31: =AL30 -> 0 | AM31: =IF((AL31-AL30)<0,"0",(AL31-AL30)) -> 0 | AN31: =U31+X31+AA31+AD31+AG31+AJ31+AM31 -> #REF!
A32: =Gen!A37 -> 44313 | B32: 10/27//2009 | C32: =D31 -> 254537 | D32: 254580 | E32: =IF((D32-D31)<0,"0",(D32-D31)) -> 43 | F32: =G31 -> 75790 | G32: 75790 | H32: =IF((G32-G31)<0,"0",(G32-G31)) -> 0 | I32: =J31 -> 8404 | J32: 8406 | K32: =IF((J32-J31)<0,"0",(J32-J31)) -> 2 | L32: =M31 -> 0 | N32: =IF((M32-M31)<0,"0",(M32-M31)) -> 0 | O32: =P31 -> 21213 | P32: 21217 | Q32: =IF((P32-P31)<0,"0",(P32-P31)) -> 4 | S32: =T31 -> 68997 | T32: 68997 | U32: =IF((T32-T31)<0,"0",(T32-T31)) -> 0 | V32: =#REF! -> #REF! | W32: 73031 | X32: =IF((W32-#REF!)<0,"0",(W32-#REF!)) -> #REF! | Y32: =Z31 -> 90129 | Z32: 90129 | AA32: =IF((Z32-Z31)<0,"0",(Z32-Z31)) -> 0 | AB32: =AC31 -> 19198 | AC32: 19214 | AD32: =IF((AC32-AC31)<0,"0",(AC32-AC31)) -> 16 | AE32: =AF31 -> 18300 | AF32: 18300 | AG32: =IF((AF32-AF31)<0,"0",(AF32-AF31)) -> 0 | AH32: =AI31 -> 31045 | AI32: 31074 | AJ32: =IF((AI32-AI31)<0,"0",(AI32-AI31)) -> 29 | AK32: =AL31 -> 0 | AM32: =IF((AL32-AL31)<0,"0",(AL32-AL31)) -> 0 | AN32: =U32+X32+AA32+AD32+AG32+AJ32+AM32 -> #REF!
A33: =Gen!A38 -> 44314 | C33: =D32 -> 254580 | D33: 254641 | E33: =IF((D33-D32)<0,"0",(D33-D32)) -> 61 | F33: =G32 -> 75790 | G33: 75790 | H33: =IF((G33-G32)<0,"0",(G33-G32)) -> 0 | I33: =J32 -> 8406 | J33: 8408 | K33: =IF((J33-J32)<0,"0",(J33-J32)) -> 2 | L33: =M32 -> 0 | N33: =IF((M33-M32)<0,"0",(M33-M32)) -> 0 | O33: =P32 -> 21217 | P33: 21221 | Q33: =IF((P33-P32)<0,"0",(P33-P32)) -> 4 | S33: =T32 -> 68997 | T33: 68997 | U33: =IF((T33-T32)<0,"0",(T33-T32)) -> 0 | V33: =W32 -> 73031 | W33: 73031 | X33: =IF((W33-W32)<0,"0",(W33-W32)) -> 0 | Y33: =Z32 -> 90129 | Z33: 90129 | AA33: =IF((Z33-Z32)<0,"0",(Z33-Z32)) -> 0 | AB33: =AC32 -> 19214 | AC33: 19230 | AD33: =IF((AC33-AC32)<0,"0",(AC33-AC32)) -> 16 | AE33: =AF32 -> 18300 | AF33: 18300 | AG33: =IF((AF33-AF32)<0,"0",(AF33-AF32)) -> 0 | AH33: =AI32 -> 31074 | AI33: 31098 | AJ33: =IF((AI33-AI32)<0,"0",(AI33-AI32)) -> 24 | AK33: =AL32 -> 0 | AM33: =IF((AL33-AL32)<0,"0",(AL33-AL32)) -> 0 | AN33: =U33+X33+AA33+AD33+AG33+AJ33+AM33 -> 40
A34: =Gen!A39 -> 44315 | C34: =D33 -> 254641 | D34: 254694 | E34: =IF((D34-D33)<0,"0",(D34-D33)) -> 53 | F34: =G33 -> 75790 | G34: 75790 | H34: =IF((G34-G33)<0,"0",(G34-G33)) -> 0 | I34: =J33 -> 8408 | J34: 8409 | K34: =IF((J34-J33)<0,"0",(J34-J33)) -> 1 | L34: =M33 -> 0 | N34: =IF((M34-M33)<0,"0",(M34-M33)) -> 0 | O34: =P33 -> 21221 | P34: 21227 | Q34: =IF((P34-P33)<0,"0",(P34-P33)) -> 6 | S34: =T33 -> 68997 | T34: 68997 | U34: =IF((T34-T33)<0,"0",(T34-T33)) -> 0 | V34: =W33 -> 73031 | W34: 73031 | X34: =IF((W34-W33)<0,"0",(W34-W33)) -> 0 | Y34: =Z33 -> 90129 | Z34: 90129 | AA34: =IF((Z34-Z33)<0,"0",(Z34-Z33)) -> 0 | AB34: =AC33 -> 19230 | AC34: 19246 | AD34: =IF((AC34-AC33)<0,"0",(AC34-AC33)) -> 16 | AE34: =AF33 -> 18300 | AF34: 18300 | AG34: =IF((AF34-AF33)<0,"0",(AF34-AF33)) -> 0 | AH34: =AI33 -> 31098 | AI34: 31127 | AJ34: =IF((AI34-AI33)<0,"0",(AI34-AI33)) -> 29 | AK34: =AL33 -> 0 | AM34: =IF((AL34-AL33)<0,"0",(AL34-AL33)) -> 0 | AN34: =U34+X34+AA34+AD34+AG34+AJ34+AM34 -> 45
A35: =Gen!A40 -> 44316 | C35: =D34 -> 254694 | D35: 254752 | E35: =IF((D35-D34)<0,"0",(D35-D34)) -> 58 | F35: =G34 -> 75790 | G35: 75790 | H35: =IF((G35-G34)<0,"0",(G35-G34)) -> 0 | I35: =J34 -> 8409 | J35: 8410 | K35: =IF((J35-J34)<0,"0",(J35-J34)) -> 1 | L35: =M34 -> 0 | N35: =IF((M35-M34)<0,"0",(M35-M34)) -> 0 | O35: =P34 -> 21227 | P35: 21230 | Q35: =IF((P35-P34)<0,"0",(P35-P34)) -> 3 | S35: =T34 -> 68997 | T35: 68997 | U35: =IF((T35-T34)<0,"0",(T35-T34)) -> 0 | V35: =W34 -> 73031 | W35: 73031 | X35: =IF((W36-W34)<0,"0",(W36-W34)) -> 0 | Y35: =Z34 -> 90129 | Z35: 90129 | AA35: =IF((Z35-Z34)<0,"0",(Z35-Z34)) -> 0 | AB35: =AC34 -> 19246 | AC35: 19263 | AD35: =IF((AC35-AC34)<0,"0",(AC35-AC34)) -> 17 | AE35: =AF34 -> 18300 | AF35: 18300 | AG35: =IF((AF35-AF34)<0,"0",(AF35-AF34)) -> 0 | AH35: =AI34 -> 31127 | AI35: 31157 | AJ35: =IF((AI35-AI34)<0,"0",(AI35-AI34)) -> 30 | AK35: =AL34 -> 0 | AM35: =IF((AL35-AL34)<0,"0",(AL35-AL34)) -> 0 | AN35: =U35+X35+AA35+AD35+AG35+AJ35+AM35 -> 47
A36: =Gen!A41 -> 0 | C36: =D35 -> 254752 | E36: =IF((D36-D35)<0,"0",(D36-D35)) -> 0 | F36: =G35 -> 75790 | H36: =IF((G36-G35)<0,"0",(G36-G35)) -> 0 | I36: =J35 -> 8410 | K36: =IF((J36-J35)<0,"0",(J36-J35)) -> 0 | L36: =M35 -> 0 | N36: =IF((M36-M35)<0,"0",(M36-M35)) -> 0 | O36: =P35 -> 21230 | Q36: =IF((P36-P35)<0,"0",(P36-P35)) -> 0 | S36: =T35 -> 68997 | U36: =IF((T36-T35)<0,"0",(T36-T35)) -> 0 | V36: =W36 -> 0 | X36: =IF((W37-W35)<0,"0",(W37-W35)) -> 0 | Y36: =Z35 -> 90129 | AA36: =IF((Z36-Z35)<0,"0",(Z36-Z35)) -> 0 | AB36: =AC35 -> 19263 | AD36: =IF((AC36-AC35)<0,"0",(AC36-AC35)) -> 0 | AE36: =AF35 -> 18300 | AG36: =IF((AF36-AF35)<0,"0",(AF36-AF35)) -> 0 | AH36: =AI35 -> 31157 | AJ36: =IF((AI36-AI35)<0,"0",(AI36-AI35)) -> 0 | AK36: =AL35 -> 0 | AM36: =IF((AL36-AL35)<0,"0",(AL36-AL35)) -> 0 | AN36: =U36+X36+AA36+AD36+AG36+AJ36+AM36 -> 0
A37: =Gen!A42 -> 0 | C37: =D36 -> 0 | E37: =IF((D37-D36)<0,"0",(D37-D36)) -> 0 | F37: =G36 -> 0 | H37: =IF((G37-G36)<0,"0",(G37-G36)) -> 0 | I37: =J36 -> 0 | K37: =IF((J37-J36)<0,"0",(J37-J36)) -> 0 | L37: =M36 -> 0 | N37: =IF((M37-M36)<0,"0",(M37-M36)) -> 0 | O37: =P36 -> 0 | Q37: =IF((P37-P36)<0,"0",(P37-P36)) -> 0 | S37: =T36 -> 0 | U37: =IF((T37-T36)<0,"0",(T37-T36)) -> 0 | V37: =#REF! -> #REF! | X37: =IF((W37-#REF!)<0,"0",(W37-#REF!)) -> #REF! | Y37: =Z36 -> 0 | AA37: =IF((Z37-Z36)<0,"0",(Z37-Z36)) -> 0 | AB37: =AC36 -> 0 | AD37: =IF((AC37-AC36)<0,"0",(AC37-AC36)) -> 0 | AE37: =AF36 -> 0 | AG37: =IF((AF37-AF36)<0,"0",(AF37-AF36)) -> 0 | AH37: =AI36 -> 0 | AJ37: =IF((AI37-AI36)<0,"0",(AI37-AI36)) -> 0 | AK37: =AL36 -> 0 | AM37: =IF((AL37-AL36)<0,"0",(AL37-AL36)) -> 0 | AN37: =U38+X38+AA38+AD38+AG38+AJ38+AM38 -> 1541
C38: TOTAL USAGE | E38: =SUM(E6:E36) -> 2108 | F38: KL | H38: =SUM(H6:H37) -> 0 | K38: =SUM(K6:K37) -> 48 | N38: =M38-M37 -> 0 | Q38: =P38-O38 -> 0 | R38: =E38 -> 2108 | U38: =SUM(U6:U37) -> 1541 | AJ38: =IF((AI39-AI37)<0,"0",(AI39-AI37)) -> 0 | AN38: =U38+X38+AA38+AD38+AG38+AJ38+AM38 -> 1541
C42: WATER TANK LEVEL
C43: RAW WATER TANK NO.1 | E43: RAW WATER TANK NO.2 | G43: TREATED WATER TANK | I43: TREATED -HILL TANK | K43: TOTAL WATER AVAILABLE
C44: CAPACITY 217 m³ | E44: CAPACITY 92 m³ | G44: CAPACITY 146 m³ | I44: CAPACITY 213 m³
C45: cm | D45: m³ | E45: cm | F45: m³ | H45: m³ | J45: m³ | K45: m³
A46: =Gen!A11 -> 44287 | C46: 229 | D46: =C46*217/300 -> 165.64333 | E46: 194 | F46: =E46*92/305 -> 58.518033 | G46: 145 | H46: =G46*146/383 -> 55.274151 | I46: 290 | J46: =I46*213/308 -> 200.55195 | K46: =D46+F46+H46+J46 -> 479.98747
A47: =Gen!A12 -> 44288 | C47: 125 | D47: =C47*217/300 -> 90.416667 | E47: 90 | F47: =E47*92/305 -> 27.147541 | G47: 225 | H47: =G47*146/383 -> 85.770235 | I47: 288 | J47: =I47*213/308 -> 199.16883 | K47: =D47+F47+H47+J47 -> 402.50327
A48: =Gen!A13 -> 44289 | C48: 140 | D48: =C48*217/300 -> 101.26667 | E48: 100 | F48: =E48*92/305 -> 30.163934 | G48: 300 | H48: =G48*146/383 -> 114.36031 | I48: 290 | J48: =I48*213/308 -> 200.55195 | K48: =D48+F48+H48+J48 -> 446.34286
A49: =Gen!A14 -> 44290 | C49: 145 | D49: =C49*217/300 -> 104.88333 | E49: 110 | F49: =E49*92/305 -> 33.180328 | G49: 5 | H49: =G49*146/383 -> 1.9060052 | I49: 290 | J49: =I49*213/308 -> 200.55195 | K49: =D49+F49+H49+J49 -> 340.52161
A50: =Gen!A15 -> 44291 | C50: 276 | D50: =C50*217/300 -> 199.64 | E50: 240 | F50: =E50*92/305 -> 72.393443 | G50: 114 | H50: =G50*146/383 -> 43.456919 | I50: 155 | J50: =I50*213/308 -> 107.19156 | K50: =D50+F50+H50+J50 -> 422.68192
A51: =Gen!A16 -> 44292 | C51: 100 | D51: =C51*217/300 -> 72.333333 | E51: 55 | F51: =E51*92/305 -> 16.590164 | G51: 300 | H51: =G51*146/383 -> 114.36031 | I51: 275 | J51: =I51*213/308 -> 190.17857 | K51: =D51+F51+H51+J51 -> 393.46238
A52: =Gen!A17 -> 44293 | C52: 238 | D52: =C52*217/300 -> 172.15333 | E52: 202 | F52: =E52*92/305 -> 60.931148 | G52: 63 | H52: =G52*146/383 -> 24.015666 | I52: 281 | J52: =I52*213/308 -> 194.32792 | K52: =D52+F52+H52+J52 -> 451.42807
A53: =Gen!A18 -> 44294 | C53: 209 | D53: =C53*217/300 -> 151.17667 | E53: 174 | F53: =E53*92/305 -> 52.485246 | G53: 300 | H53: =G53*146/383 -> 114.36031 | I53: 284 | J53: =I53*213/308 -> 196.4026 | K53: =D53+F53+H53+J53 -> 514.42482
A54: =Gen!A19 -> 44295 | C54: 300 | D54: =C54*217/300 -> 217 | E54: 295 | F54: =E54*92/305 -> 88.983607 | G54: 236 | H54: =G54*146/383 -> 89.963446 | I54: 279 | J54: =I54*213/308 -> 192.94481 | K54: =D54+F54+H54+J54 -> 588.89186
A55: =Gen!A20 -> 44296 | C55: 300 | D55: =C55*217/300 -> 217 | E55: 290 | F55: =E55*92/305 -> 87.47541 | G55: 295 | H55: =G55*146/383 -> 112.45431 | I55: 290 | J55: =I55*213/308 -> 200.55195 | K55: =D55+F55+H55+J55 -> 617.48167
A56: =Gen!A21 -> 44297 | C56: 298 | D56: =C56*217/300 -> 215.55333 | E56: 274 | F56: =E56*92/305 -> 82.64918 | G56: 217 | H56: =G56*146/383 -> 82.720627 | I56: 291 | J56: =I56*213/308 -> 201.24351 | K56: =D56+F56+H56+J56 -> 582.16665
A57: =Gen!A22 -> 44298 | C57: 280 | D57: =C57*217/300 -> 202.53333 | E57: 245 | F57: =E57*92/305 -> 73.901639 | G57: 185 | H57: =G57*146/383 -> 70.522193 | I57: 289 | J57: =I57*213/308 -> 199.86039 | K57: =D57+F57+H57+J57 -> 546.81756
... A75: =Gen!A40 -> 44316 | C75: 196 | D75: =C75*217/300 -> 141.77333 | E75: 160 | F75: =E75*92/305 -> 48.262295 | G75: 105 | H75: =G75*146/383 -> 40.02611 | I75: 271 | J75: =I75*213/308 -> 187.41234 | K75: =D75+F75+H75+J75 -> 417.47408
A76: =Gen!A41 -> 0 | D76: =C76*217/300 -> 0 | F76: =E76*92/305 -> 0 | H76: =G76*146/383 -> 0 | J76: =I76*213/308 -> 0 | K76: =D76+F76+H76+J76 -> 0
A77: =Gen!A42 -> 0 | D77: =C77*217/300 -> 0 | F77: =E77*92/305 -> 0 | H77: =G77*146/383 -> 0 | J77: =I77*213/308 -> 0 | K77: =D77+F77+H77+J77 -> 0
A78: =Gen!A43 -> BF

Sheet Water_Graph 
A1: Date | B1: Usage | C1: Occ %
A2: =Gen!A11 -> 44287 | B2: =SUM('[1]Water-Meter'!R10) -> #REF! | C2: =SUM([1]Gen!B11) -> 0.623
A3: =Gen!A12 -> 44288 | B3: =SUM('[1]Water-Meter'!R11) -> #REF! | C3: =SUM([1]Gen!B12) -> 0.779
A4: =Gen!A13 -> 44289 | B4: =SUM('[1]Water-Meter'!R12) -> #REF! | C4: =SUM([1]Gen!B13) -> 0.532
A5: =Gen!A14 -> 44290 | B5: =SUM('[1]Water-Meter'!R13) -> #REF! | C5: =SUM([1]Gen!B14) -> 0.61
A6: =Gen!A15 -> 44291 | B6: =SUM('[1]Water-Meter'!R14) -> #REF! | C6: =SUM([1]Gen!B15) -> 0.688
A7: =Gen!A16 -> 44292 | B7: =SUM('[1]Water-Meter'!R15) -> #REF! | C7: =SUM([1]Gen!B16) -> 0.532
A8: =Gen!A17 -> 44293 | B8: =SUM('[1]Water-Meter'!R16) -> #REF! | C8: =SUM([1]Gen!B17) -> 0.753
A9: =Gen!A18 -> 44294 | B9: =SUM('[1]Water-Meter'!R17) -> #REF! | C9: =SUM([1]Gen!B18) -> 0.156
A10: =Gen!A19 -> 44295 | B10: =SUM('[1]Water-Meter'!R18) -> #REF! | C10: =SUM([1]Gen!B19) -> 0.442
A11: =Gen!A20 -> 44296 | B11: =SUM('[1]Water-Meter'!R19) -> #REF! | C11: =SUM([1]Gen!B20) -> 0.325
A12: =Gen!A21 -> 44297 | B12: =SUM('[1]Water-Meter'!R20) -> #REF! | C12: =SUM([1]Gen!B21) -> 0.455
A13: =Gen!A22 -> 44298 | B13: =SUM('[1]Water-Meter'!R21) -> #REF! | C13: =SUM([1]Gen!B22) -> 0.416
... A32: =Gen!A41 -> 0 | B32: =SUM('[1]Water-Meter'!R40) -> #REF! | C32: =SUM([1]Gen!B41) -> #REF!

Sheet Sheet1
A2: Generator and Diseal Summry Report | Q2: 2209.85 | R2: Diesel Cost | S2: Rate$ | T2: 1584
M3: % of Gas balance in Tank | P3: % of Dieasel balance in Tank | Q3: HLP Cost (TSH) | V3: Total Cost (TSH) | W3: Consumption Guest Occ% | AA3: Budget Cost Per Room occ
A4: Date | B4: Gen Set Hours Working | C4: Occ% | D4: Total OCC Room | E4: Guest Room Occ | F4: Total Kwh Generated | G4: Diseal consumed by Gen (Ltrs) | H4: Diseal consumed by Veichel (Ltrs) | I4: Total diseal consumed (Ltrs) | J4: Balance stock of Diseal (Ltrs) | K4: Water consumed | L4: Gas consumed (KG) | M4: 3 | N4: 2 | O4: 1 | Q4: Electricity | R4: Cost per Room Total OOC Usd | S4: Cost per Room Guest OOC Usd | T4: Water | U4: Gas
A5: =Gen!A11 -> 44287 | B5: 0 | C5: =Gen!B11 -> 0.156 | D5: =SUM(77*C5) -> 12.012 | F5: =Gen!U11 -> 0.41777953 | G5: =Gen!T11 -> 3175 | H5: =[1]Gen!#REF! -> #REF! | I5: =SUM(G5:H5) -> #REF! | J5: =[1]Gen!AT11 -> 47806.65 | K5: ='Water-Meter'!E6 -> 89 | L5: ='Lpg (2)'!G10 -> 84.48 | M5: =#REF! -> #REF! | N5: =#REF! -> #REF! | O5: =#REF! -> #REF! | P5: =J5/52000 -> 0.91935865 | Q5: =I5*Q2 -> #REF! | R5: =SUM(Q5/D5)/X5 -> #REF! | S5: =SUM(Q5/E5)/X5 -> #REF! | T5: =(K5*102)/X5 -> 5.7310606 | U5: =SUM(L5*1963)/X5 -> 104.69333 | V5: =SUM(Q5+T5+U5) -> #REF! | W5: =SUM(V5/E5)/T2 -> #REF! | X5: =SUM(T2) -> 1584 | Y5: 106 | Z5: =SUM(Y5-S5) -> #REF! | AA5: 106
A6: =Gen!A12 -> 44288 | B6: 0 | C6: =Gen!B12 -> 0.169 | D6: =SUM(77*C6) -> 13.013 | F6: =Gen!U12 -> 0.41067775 | G6: =Gen!T12 -> 3187 | H6: =[1]Gen!#REF! -> #REF! | I6: =SUM(G6:H6) -> #REF! | J6: =[1]Gen!AT12 -> 45423.89 | K6: ='Water-Meter'!E7 -> 117 | L6: ='Lpg (2)'!G11 -> 86.548 | M6: =#REF! -> #REF! | N6: =#REF! -> #REF! | O6: =#REF! -> #REF! | P6: =J6/52000 -> 0.87353635 | Q6: =I6*Q2 -> #REF! | R6: =SUM(Q6/D6)/X6 -> #REF! | S6: =SUM(Q6/E6)/X6 -> #REF! | T6: =(K6*102)/X6 -> 7.5340909 | U6: =SUM(L6*1963)/X6 -> 107.25614 | V6: =SUM(Q6+T6+U6) -> #REF! | W6: =SUM(V6/E6)/T2 -> #REF! | X6: =SUM(X5) -> 1584 | Y6: 106 | Z6: =SUM(Y6-S6) -> #REF!
A7: =Gen!A13 -> 44289 | B7: 0 | C7: =Gen!B13 -> 0.23 | D7: =SUM(77*C7) -> 17.71 | F7: =Gen!U13 -> 0.4022758 | G7: =Gen!T13 -> 3546 | H7: =[1]Gen!#REF! -> #REF! | I7: =SUM(G7:H7) -> #REF! | J7: =[1]Gen!AT13 -> 42919.59 | K7: ='Water-Meter'!E8 -> 167 | L7: ='Lpg (2)'!G12 -> 88.968 | M7: =#REF! -> #REF! | N7: =#REF! -> #REF! | O7: =#REF! -> #REF! | P7: =J7/52000 -> 0.82537673 | Q7: =I7*Q2 -> #REF! | R7: =SUM(Q7/D7)/X7 -> #REF! | S7: =SUM(Q7/E7)/X7 -> #REF! | T7: =(K7*102)/X7 -> 10.753788 | U7: =SUM(L7*1963)/X7 -> 110.25517 | V7: =SUM(Q7+T7+U7) -> #REF! | W7: =SUM(V7/E7)/T2 -> #REF! | X7: =SUM(X6) -> 1584 | Y7: 106 | Z7: =SUM(Y7-S7) -> #REF!
A8: =Gen!A14 -> 44290 | B8: 0 | C8: =Gen!B14 -> 0.247 | D8: =SUM(77*C8) -> 19.019 | F8: =Gen!U14 -> 0.40958834 | G8: =Gen!T14 -> 3328 | H8: =[1]Gen!AJ9 -> #REF! | I8: =SUM(G8:H8) -> #REF! | J8: =[1]Gen!AT14 -> 40258.94 | K8: ='Water-Meter'!E9 -> 70 | L8: ='Lpg (2)'!G13 -> 86.372 | M8: =#REF! -> #REF! | N8: =#REF! -> #REF! | O8: =#REF! -> #REF! | P8: =J8/52000 -> 0.77421038 | Q8: =I8*Q2 -> #REF! | R8: =SUM(Q8/D8)/X8 -> #REF! | S8: =SUM(Q8/E8)/X8 -> #REF! | T8: =(K8*102)/X8 -> 4.5075758 | U8: =SUM(L8*1963)/X8 -> 107.03803 | V8: =SUM(Q8+T8+U8) -> #REF! | W8: =SUM(V8/E8)/T2 -> #REF! | X8: =SUM(X7) -> 1584 | Y8: 106 | Z8: =SUM(Y8-S8) -> #REF!
A9: =Gen!A15 -> 44291 | B9: 0 | C9: =Gen!B15 -> 0.13 | D9: =SUM(77*C9) -> 10.01 | F9: =Gen!U15 -> 0.40968615 | G9: =Gen!T15 -> 3250 | H9: =[1]Gen!AJ10 -> 0 | I9: =SUM(G9:H9) -> 3250 | J9: =[1]Gen!AT15 -> 37525.21 | K9: ='Water-Meter'!E10 -> 59 | L9: ='Lpg (2)'!G14 -> 88.528 | M9: =#REF! -> #REF! | N9: =#REF! -> #REF! | O9: =#REF! -> #REF! | P9: =J9/52000 -> 0.72163865 | Q9: =I9*Q2 -> 7182012.5 | R9: =SUM(Q9/D9)/X9 -> 452.95692 | S9: =SUM(Q9/E9)/X9 -> #DIV/0! | T9: =(K9*102)/X9 -> 3.7992424 | U9: =SUM(L9*1963)/X9 -> 109.70989 | V9: =SUM(Q9+T9+U9) -> 7182126 | W9: =SUM(V9/E9)/T2 -> #DIV/0! | X9: =SUM(X8) -> 1584 | Y9: 106 | Z9: =SUM(Y9-S9) -> #DIV/0!
A10: =Gen!A16 -> 44292 | B10: 0 | C10: =Gen!B16 -> 0.091 | D10: =SUM(77*C10) -> 7.007 | F10: =Gen!U16 -> 0.41273616 | G10: =Gen!T16 -> 3070 | H10: =[1]Gen!#REF! -> #REF! | I10: =SUM(G10:H10) -> #REF! | J10: =[1]Gen!AT16 -> 35107.69 | K10: ='Water-Meter'!E11 -> 210 | L10: ='Lpg (2)'!G15 -> 82.896 | M10: =#REF! -> #REF! | N10: =#REF! -> #REF! | O10: =#REF! -> #REF! | P10: =J10/52000 -> 0.67514788 | Q10: =I10*Q2 -> #REF! | R10: =SUM(Q10/D10)/X10 -> #REF! | S10: =SUM(Q10/E10)/X10 -> #REF! | T10: =(K10*102)/X10 -> 13.522727 | U10: =SUM(L10*1963)/X10 -> 102.73033 | V10: =SUM(Q10+T10+U10) -> #REF! | W10: =SUM(V10/E10)/T2 -> #REF! | X10: =SUM(X9) -> 1584 | Y10: 106 | Z10: =SUM(Y10-S10) -> #REF!
A11: =Gen!A17 -> 44293 | B11: 0 | C11: =Gen!B17 -> 0.065 | D11: =SUM(77*C11) -> 5.005 | F11: =Gen!U17 -> 0.40155219 | G11: =Gen!T17 -> 3363 | H11: =[1]Gen!AJ25 -> 80.56 | I11: =SUM(G11:H11) -> 3443.56 | J11: =[1]Gen!AT17 -> 47513.14 | K11: ='Water-Meter'!E12 -> 60 | L11: ='Lpg (2)'!G16 -> 80.212 | M11: =#REF! -> #REF! | N11: =#REF! -> #REF! | O11: =#REF! -> #REF! | P11: =J11/52000 -> 0.91371423 | Q11: =I11*Q2 -> 7609751.1 | R11: =SUM(Q11/D11)/X11 -> 959.86729 | S11: =SUM(Q11/E11)/X11 -> #DIV/0! | T11: =(K11*102)/X11 -> 3.8636364 | U11: =SUM(L11*1963)/X11 -> 99.404139 | V11: =SUM(Q11+T11+U11) -> 7609854.3 | W11: =SUM(V11/E11)/T2 -> #DIV/0! | X11: =SUM(X10) -> 1584 | Y11: 106 | Z11: =SUM(Y11-S11) -> #DIV/0!
A12: =Gen!A18 -> 44294 | B12: 0 | C12: =Gen!B18 -> 0.091 | D12: =SUM(77*C12) -> 7.007 | F12: =Gen!U18 -> 0.40188175 | G12: =Gen!T18 -> 3146 | H12: =[1]Gen!#REF! -> #REF! | I12: =SUM(G12:H12) -> #REF! | J12: =[1]Gen!AT18 -> 45161.89 | K12: ='Water-Meter'!E13 -> 75 | L12: ='Lpg (2)'!G17 -> 83.996 | M12: =#REF! -> #REF! | N12: =#REF! -> #REF! | O12: =#REF! -> #REF! | P12: =J12/52000 -> 0.86849788 | Q12: =I12*Q2 -> #REF! | R12: =SUM(Q12/D12)/X12 -> #REF! | S12: =SUM(Q12/E12)/X12 -> #REF! | T12: =(K12*102)/X12 -> 4.8295455 | U12: =SUM(L12*1963)/X12 -> 104.09353 | V12: =SUM(Q12+T12+U12) -> #REF! | W12: =SUM(V12/E12)/T2 -> #REF! | X12: =SUM(X11) -> 1584 | Y12: 106 | Z12: =SUM(Y12-S12) -> #REF!
A13: =Gen!A19 -> 44295 | B13: 0 | C13: =Gen!B19 -> 0.065 | D13: =SUM(77*C13) -> 5.005 | F13: =Gen!U19 -> 0.3941732 | G13: =Gen!T19 -> 3314 | H13: =[1]Gen!#REF! -> #REF! | I13: =SUM(G13:H13) -> #REF! | J13: =[1]Gen!AT19 -> 42825.48 | K13: ='Water-Meter'!E14 -> 47 | L13: ='Lpg (2)'!G18 -> 44 | M13: =#REF! -> #REF! | N13: =#REF! -> #REF! | O13: =#REF! -> #REF! | P13: =J13/52000 -> 0.82356692 | Q13: =I13*Q2 -> #REF! | R13: =SUM(Q13/D13)/X13 -> #REF! | S13: =SUM(Q13/E13)/X13 -> #REF! | T13: =(K13*102)/X13 -> 3.0265152 | U13: =SUM(L13*1963)/X13 -> 54.527778 | V13: =SUM(Q13+T13+U13) -> #REF! | W13: =SUM(V13/E13)/T2 -> #REF! | X13: =SUM(X12) -> 1584 | Y13: 106 | Z13: =SUM(Y13-S13) -> #REF!
A14: =Gen!A20 -> 44296 | B14: 0 | C14: =Gen!B20 -> 0.052 | D14: =SUM(77*C14) -> 4.004 | F14: =Gen!U20 -> 0.39324811 | G14: =Gen!T20 -> 3168 | H14: =[1]Gen!#REF! -> #REF! | I14: =SUM(G14:H14) -> #REF! | J14: =[1]Gen!AT20 -> 40110.38 | K14: ='Water-Meter'!E15 -> 46 | L14: ='Lpg (2)'!G19 -> 88 | M14: =#REF! -> #REF! | N14: =#REF! -> #REF! | O14: =#REF! -> #REF! | P14: =J14/52000 -> 0.77135346 | Q14: =I14*Q2 -> #REF! | R14: =SUM(Q14/D14)/X14 -> #REF! | S14: =SUM(Q14/E14)/X14 -> #REF! | T14: =(K14*102)/X14 -> 2.9621212 | U14: =SUM(L14*1963)/X14 -> 109.05556 | V14: =SUM(Q14+T14+U14) -> #REF! | W14: =SUM(V14/E14)/T2 -> #REF! | X14: =SUM(X13) -> 1584 | Y14: 106 | Z14: =SUM(Y14-S14) -> #REF!
A15: =Gen!A21 -> 44297 | B15: 0 | C15: =Gen!B21 -> 0.104 | D15: =SUM(77*C15) -> 8.008 | F15: =Gen!U21 -> 0.3966574 | G15: =Gen!T21 -> 3237 | H15: =[1]Gen!#REF! -> #REF! | I15: =SUM(G15:H15) -> #REF! | J15: =[1]Gen!AT21 -> 37540.57 | K15: ='Water-Meter'!E16 -> 50 | L15: ='Lpg (2)'!G20 -> 57.244 | M15: =#REF! -> #REF! | N15: =#REF! -> #REF! | O15: =#REF! -> #REF! | P15: =J15/52000 -> 0.72193404 | Q15: =I15*Q2 -> #REF! | R15: =SUM(Q15/D15)/X15 -> #REF! | S15: =SUM(Q15/E15)/X15 -> #REF! | T15: =(K15*102)/X15 -> 3.219697 | U15: =SUM(L15*1963)/X15 -> 70.940639 | V15: =SUM(Q15+T15+U15) -> #REF! | W15: =SUM(V15/E15)/T2 -> #REF! | X15: =SUM(X14) -> 1584 | Y15: 106 | Z15: =SUM(Y15-S15) -> #REF!
A16: =Gen!A22 -> 44298 | B16: 0 | C16: =Gen!B22 -> 0.104 | D16: =SUM(77*C16) -> 8.008 | F16: =Gen!U22 -> 0.35691343 | G16: =Gen!T22 -> 3269 | H16: =[1]Gen!#REF! -> #REF! | I16: =SUM(G16:H16) -> #REF! | J16: =[1]Gen!AT22 -> 34967.29 | K16: ='Water-Meter'!E17 -> 61 | L16: ='Lpg (2)'!G21 -> 64.328 | M16: =#REF! -> #REF! | N16: =#REF! -> #REF! | O16: =#REF! -> #REF! | P16: =J16/52000 -> 0.67244788 | Q16: =I16*Q2 -> #REF! | R16: =SUM(Q16/D16)/X16 -> #REF! | S16: =SUM(Q16/E16)/X16 -> #REF! | T16: =(K16*102)/X16 -> 3.9280303 | U16: =SUM(L16*1963)/X16 -> 79.719611 | V16: =SUM(Q16+T16+U16) -> #REF! | W16: =SUM(V16/E16)/T2 -> #REF! | X16: =SUM(X15) -> 1584 | Y16: 106 | Z16: =SUM(Y16-S16) -> #REF!
A17: =Gen!A23 -> 44299 | B17: 0 | C17: =Gen!B23 -> 0.013 | D17: =SUM(77*C17) -> 1.001 | F17: =Gen!U23 -> 0.40665666 | G17: =Gen!T23 -> 2665 | H17: =[1]Gen!#REF! -> #REF! | I17: =SUM(G17:H17) -> #REF! | J17: =[1]Gen!AT23 -> 32228.76 | K17: ='Water-Meter'!E18 -> 181 | L17: ='Lpg (2)'!G22 -> 63.228 | M17: =#REF! -> #REF! | N17: =#REF! -> #REF! | O17: =#REF! -> #REF! | P17: =J17/52000 -> 0.61978385 | Q17: =I17*Q2 -> #REF! | R17: =SUM(Q17/D17)/X17 -> #REF! | S17: =SUM(Q17/E17)/X17 -> #REF! | T17: =(K17*102)/X17 -> 11.655303 | U17: =SUM(L17*1963)/X17 -> 78.356417 | V17: =SUM(Q17+T17+U17) -> #REF! | W17: =SUM(V17/E17)/T2 -> #REF! | X17: =SUM(X16) -> 1584 | Y17: 106 | Z17: =SUM(Y17-S17) -> #REF!
A18: =Gen!A24 -> 44300 | B18: 0 | C18: =Gen!B24 -> 0 | D18: =SUM(77*C18) -> 0 | F18: =Gen!U24 -> 0.40256905 | G18: =Gen!T24 -> 2643 | H18: =[1]Gen!AJ27 -> 597.9 | I18: =SUM(G18:H18) -> 3240.9 | J18: =[1]Gen!AT24 -> 29915.45 | K18: ='Water-Meter'!E19 -> 46 | L18: ='Lpg (2)'!G23 -> 59.708 | M18: =#REF! -> #REF! | N18: =#REF! -> #REF! | O18: =#REF! -> #REF! | P18: =J18/52000 -> 0.57529712 | Q18: =I18*Q2 -> 7161902.9 | R18: =SUM(Q18/D18)/X18 -> #DIV/0! | S18: =SUM(Q18/E18)/X18 -> #DIV/0! | T18: =(K18*102)/X18 -> 2.9621212 | U18: =SUM(L18*1963)/X18 -> 73.994194 | V18: =SUM(Q18+T18+U18) -> 7161979.8 | W18: =SUM(V18/E18)/T2 -> #DIV/0! | X18: =SUM(X17) -> 1584 | Y18: 106 | Z18: =SUM(Y18-S18) -> #DIV/0!
A19: =Gen!A25 -> 44301 | B19: 0 | C19: =Gen!B25 -> 0 | D19: =SUM(77*C19) -> 0 | F19: =Gen!U25 -> 0.40148205 | G19: =Gen!T25 -> 2618 | H19: =[1]Gen!AJ28 -> 227.73 | I19: =SUM(G19:H19) -> 2845.73 | J19: =[1]Gen!AT25 -> 42248.24 | K19: ='Water-Meter'!E20 -> 47 | L19: ='Lpg (2)'!G24 -> 59.092 | M19: =#REF! -> #REF! | N19: =#REF! -> #REF! | O19: =#REF! -> #REF! | P19: =J19/52000 -> 0.81246615 | Q19: =I19*Q2 -> 6288636.4 | R19: =SUM(Q19/D19)/X19 -> #DIV/0! | S19: =SUM(Q19/E19)/X19 -> #DIV/0! | T19: =(K19*102)/X19 -> 3.0265152 | U19: =SUM(L19*1963)/X19 -> 73.230806 | V19: =SUM(Q19+T19+U19) -> 6288712.7 | W19: =SUM(V19/E19)/T2 -> #DIV/0! | X19: =SUM(X18) -> 1584 | Y19: 106 | Z19: =SUM(Y19-S19) -> #DIV/0!
A20: =Gen!A26 -> 44302 | B20: 0 | C20: =Gen!B26 -> 0 | D20: =SUM(77*C20) -> 0 | F20: =Gen!U26 -> 0.40802435 | G20: =Gen!T26 -> 2546 | H20: =[1]Gen!AJ29 -> 88.29 | I20: =SUM(G20:H20) -> 2634.29 | J20: =[1]Gen!AT26 -> 39497.37 | K20: ='Water-Meter'!E21 -> 40 | L20: ='Lpg (2)'!G25 -> 44 | M20: =#REF! -> #REF! | N20: =#REF! -> #REF! | O20: =#REF! -> #REF! | P20: =J20/52000 -> 0.75956481 | Q20: =I20*Q2 -> 5821385.8 | R20: =SUM(Q20/D20)/X20 -> #DIV/0! | S20: =SUM(Q20/E20)/X20 -> #DIV/0! | T20: =(K20*102)/X20 -> 2.5757576 | U20: =SUM(L20*1963)/X20 -> 54.527778 | V20: =SUM(Q20+T20+U20) -> 5821442.9 | W20: =SUM(V20/E20)/T2 -> #DIV/0! | X20: =SUM(X19) -> 1584 | Y20: 106 | Z20: =SUM(Y20-S20) -> #DIV/0!
A21: =Gen!A27 -> 44303 | B21: 0 | C21: =Gen!B27 -> 0.013 | D21: =SUM(77*C21) -> 1.001 | F21: =Gen!U27 -> 0.4093467 | G21: =Gen!T27 -> 2694 | H21: =[1]Gen!AJ30 -> 783.92 | I21: =SUM(G21:H21) -> 3477.92 | J21: =[1]Gen!AT27 -> 36688.35 | K21: ='Water-Meter'!E22 -> 52 | L21: ='Lpg (2)'!G26 -> 56.848 | M21: =#REF! -> #REF! | N21: =#REF! -> #REF! | O21: =#REF! -> #REF! | P21: =J21/52000 -> 0.70554519 | Q21: =I21*Q2 -> 7685681.5 | R21: =SUM(Q21/D21)/X21 -> 4847.2244 | S21: =SUM(Q21/E21)/X21 -> #DIV/0! | T21: =(K21*102)/X21 -> 3.3484848 | U21: =SUM(L21*1963)/X21 -> 70.449889 | V21: =SUM(Q21+T21+U21) -> 7685755.3 | W21: =SUM(V21/E21)/T2 -> #DIV/0! | X21: =SUM(X20) -> 1584 | Y21: 106 | Z21: =SUM(Y21-S21) -> #DIV/0!
A22: =Gen!A28 -> 44304 | B22: 0 | C22: =Gen!B28 -> 0.039 | D22: =SUM(77*C22) -> 3.003 | F22: =Gen!U28 -> 0.41046143 | G22: =Gen!T28 -> 2839 | H22: =[1]Gen!#REF! -> #REF! | I22: =SUM(G22:H22) -> #REF! | J22: =[1]Gen!AT28 -> 33769.34 | K22: ='Water-Meter'!E23 -> 53 | L22: ='Lpg (2)'!G27 -> 61.952 | M22: =#REF! -> #REF! | N22: =#REF! -> #REF! | O22: =#REF! -> #REF! | P22: =J22/52000 -> 0.64941038 | Q22: =I22*Q2 -> #REF! | R22: =SUM(Q22/D22)/X22 -> #REF! | S22: =SUM(Q22/E22)/X22 -> #REF! | T22: =(K22*102)/X22 -> 3.4128788 | U22: =SUM(L22*1963)/X22 -> 76.775111 | V22: =SUM(Q22+T22+U22) -> #REF! | W22: =SUM(V22/E22)/T2 -> #REF! | X22: =SUM(X21) -> 1584 | Y22: 106 | Z22: =SUM(Y22-S22) -> #REF!
A23: =Gen!A29 -> 44305 | B23: 0 | C23: =Gen!B29 -> 0.065 | D23: =SUM(77*C23) -> 5.005 | F23: =Gen!U29 -> 0.42041712 | G23: =Gen!T29 -> 2733 | H23: =[1]Gen!#REF! -> #REF! | I23: =SUM(G23:H23) -> #REF! | J23: =[1]Gen!AT29 -> 31336.77 | K23: ='Water-Meter'!E24 -> 58 | L23: ='Lpg (2)'!G28 -> 67.804 | M23: =#REF! -> #REF! | N23: =#REF! -> #REF! | O23: =#REF! -> #REF! | P23: =J23/52000 -> 0.60263019 | Q23: =I23*Q2 -> #REF! | R23: =SUM(Q23/D23)/X23 -> #REF! | S23: =SUM(Q23/E23)/X23 -> #REF! | T23: =(K23*102)/X23 -> 3.7348485 | U23: =SUM(L23*1963)/X23 -> 84.027306 | V23: =SUM(Q23+T23+U23) -> #REF! | W23: =SUM(V23/E23)/T2 -> #REF! | X23: =SUM(X22) -> 1584 | Y23: 106 | Z23: =SUM(Y23-S23) -> #REF!
A24: =Gen!A30 -> 44306 | B24: 0 | C24: =Gen!B30 -> 0.052 | D24: =SUM(77*C24) -> 4.004 | F24: =Gen!U30 -> 0.41581933 | G24: =Gen!T30 -> 2856 | H24: =[1]Gen!#REF! -> #REF! | I24: =SUM(G24:H24) -> #REF! | J24: =[1]Gen!AT30 -> 29403.3 | K24: ='Water-Meter'!E25 -> 66 | L24: ='Lpg (2)'!G29 -> 65.956 | M24: =#REF! -> #REF! | N24: =#REF! -> #REF! | O24: =#REF! -> #REF! | P24: =J24/52000 -> 0.56544808 | Q24: =I24*Q2 -> #REF! | R24: =SUM(Q24/D24)/X24 -> #REF! | S24: =SUM(Q24/E24)/X24 -> #REF! | T24: =(K24*102)/X24 -> 4.25 | U24: =SUM(L24*1963)/X24 -> 81.737139 | V24: =SUM(Q24+T24+U24) -> #REF! | W24: =SUM(V24/E24)/T2 -> #REF! | X24: =SUM(X23) -> 1584 | Y24: 106 | Z24: =SUM(Y24-S24) -> #REF!
A25: =Gen!A31 -> 44307 | B25: 0 | C25: =Gen!B31 -> 0.026 | D25: =SUM(77*C25) -> 2.002 | F25: =Gen!U31 -> 0.41387407 | G25: =Gen!T31 -> 2700 | H25: =[1]Gen!AJ31 -> 172.05 | I25: =SUM(G25:H25) -> 2872.05 | J25: =[1]Gen!AT31 -> 41422.37 | K25: ='Water-Meter'!E26 -> 47 | L25: ='Lpg (2)'!G30 -> 65.56 | M25: =#REF! -> #REF! | N25: =#REF! -> #REF! | O25: =#REF! -> #REF! | P25: =J25/52000 -> 0.79658404 | Q25: =I25*Q2 -> 6346799.7 | R25: =SUM(Q25/D25)/X25 -> 2001.4076 | S25: =SUM(Q25/E25)/X25 -> #DIV/0! | T25: =(K25*102)/X25 -> 3.0265152 | U25: =SUM(L25*1963)/X25 -> 81.246389 | V25: =SUM(Q25+T25+U25) -> 6346884 | W25: =SUM(V25/E25)/T2 -> #DIV/0! | X25: =SUM(X24) -> 1584 | Y25: 106 | Z25: =SUM(Y25-S25) -> #DIV/0!
A26: =Gen!A32 -> 44308 | B26: 0 | C26: =Gen!B32 -> 0 | D26: =SUM(77*C26) -> 0 | F26: =Gen!U32 -> 0.41092943 | G26: =Gen!T32 -> 2593 | H26: =[1]Gen!AJ32 -> 18.63 | I26: =SUM(G26:H26) -> 2611.63 | J26: =[1]Gen!AT32 -> 38988.16 | K26: ='Water-Meter'!E27 -> 50 | L26: ='Lpg (2)'!G31 -> 58.212 | M26: =#REF! -> #REF! | N26: =#REF! -> #REF! | O26: =#REF! -> #REF! | P26: =J26/52000 -> 0.74977231 | Q26: =I26*Q2 -> 5771310.6 | R26: =SUM(Q26/D26)/X26 -> #DIV/0! | S26: =SUM(Q26/E26)/X26 -> #DIV/0! | T26: =(K26*102)/X26 -> 3.219697 | U26: =SUM(L26*1963)/X26 -> 72.14025 | V26: =SUM(Q26+T26+U26) -> 5771385.9 | W26: =SUM(V26/E26)/T2 -> #DIV/0! | X26: =SUM(X25) -> 1584 | Y26: 106 | Z26: =SUM(Y26-S26) -> #DIV/0!
A27: =Gen!A33 -> 44309 | B27: 0 | C27: =Gen!B33 -> 0.013 | D27: =SUM(77*C27) -> 1.001 | F27: =Gen!U33 -> 0.40950696 | G27: =Gen!T33 -> 2657 | H27: =[1]Gen!AJ33 -> 311.34 | I27: =SUM(G27:H27) -> 2968.34 | J27: =[1]Gen!AT33 -> 36682.67 | K27: ='Water-Meter'!E28 -> 47 | L27: ='Lpg (2)'!G32 -> 41.14 | M27: =#REF! -> #REF! | N27: =#REF! -> #REF! | O27: =#REF! -> #REF! | P27: =J27/52000 -> 0.70543596 | Q27: =I27*Q2 -> 6559586.1 | R27: =SUM(Q27/D27)/X27 -> 4137.0159 | S27: =SUM(Q27/E27)/X27 -> #DIV/0! | T27: =(K27*102)/X27 -> 3.0265152 | U27: =SUM(L27*1963)/X27 -> 50.983472 | V27: =SUM(Q27+T27+U27) -> 6559640.2 | W27: =SUM(V27/E27)/T2 -> #DIV/0! | X27: =SUM(X26) -> 1584 | Y27: 106 | Z27: =SUM(Y27-S27) -> #DIV/0!
A28: =Gen!A34 -> 44310 | B28: 0 | C28: =Gen!B34 -> 0.026 | D28: =SUM(77*C28) -> 2.002 | F28: =Gen!U34 -> 0.39966527 | G28: =Gen!T34 -> 2629 | H28: =[1]Gen!AJ34 -> 380.7 | I28: =SUM(G28:H28) -> 3009.7 | J28: =[1]Gen!AT34 -> 44223.03 | K28: ='Water-Meter'!E29 -> 56 | L28: ='Lpg (2)'!G33 -> 62.788 | M28: =#REF! -> #REF! | N28: =#REF! -> #REF! | O28: =#REF! -> #REF! | P28: =J28/52000 -> 0.85044288 | Q28: =I28*Q2 -> 6650985.5 | R28: =SUM(Q28/D28)/X28 -> 2097.3299 | S28: =SUM(Q28/E28)/X28 -> #DIV/0! | T28: =(K28*102)/X28 -> 3.6060606 | U28: =SUM(L28*1963)/X28 -> 77.811139 | V28: =SUM(Q28+T28+U28) -> 6651067 | W28: =SUM(V28/E28)/T2 -> #DIV/0! | X28: =SUM(X27) -> 1584 | Y28: 106 | Z28: =SUM(Y28-S28) -> #DIV/0!
A29: =Gen!A35 -> 44311 | B29: 0 | C29: =Gen!B35 -> 0.052 | D29: =SUM(77*C29) -> 4.004 | F29: =Gen!U35 -> 0.39691349 | G29: =Gen!T35 -> 2890 | H29: =[1]Gen!AJ35 -> 273.37 | I29: =SUM(G29:H29) -> 3163.37 | J29: =[1]Gen!AT35 -> 41629.06 | K29: ='Water-Meter'!E30 -> 46 | L29: ='Lpg (2)'!G34 -> 66.132 | M29: =#REF! -> #REF! | N29: =#REF! -> #REF! | O29: =#REF! -> #REF! | P29: =J29/52000 -> 0.80055885 | Q29: =I29*Q2 -> 6990573.2 | R29: =SUM(Q29/D29)/X29 -> 1102.208 | S29: =SUM(Q29/E29)/X29 -> #DIV/0! | T29: =(K29*102)/X29 -> 2.9621212 | U29: =SUM(L29*1963)/X29 -> 81.95525 | V29: =SUM(Q29+T29+U29) -> 6990658.1 | W29: =SUM(V29/E29)/T2 -> #DIV/0! | X29: =SUM(X28) -> 1584 | Y29: 106 | Z29: =SUM(Y29-S29) -> #DIV/0!
A30: =Gen!A36 -> 44312 | B30: 0 | C30: =Gen!B36 -> 0.052 | D30: =SUM(77*C30) -> 4.004 | F30: =Gen!U36 -> 0.41366407 | G30: =Gen!T36 -> 2691 | H30: =[1]Gen!AJ36 -> 396.56 | I30: =SUM(G30:H30) -> 3087.56 | J30: =[1]Gen!AT36 -> 39251.17 | K30: ='Water-Meter'!E31 -> 53 | L30: ='Lpg (2)'!G35 -> 66.352 | M30: =#REF! -> #REF! | N30: =#REF! -> #REF! | O30: =#REF! -> #REF! | P30: =J30/52000 -> 0.75483019 | Q30: =I30*Q2 -> 6823044.5 | R30: =SUM(Q30/D30)/X30 -> 1075.7936 | S30: =SUM(Q30/E30)/X30 -> #DIV/0! | T30: =(K30*102)/X30 -> 3.4128788 | U30: =SUM(L30*1963)/X30 -> 82.227889 | V30: =SUM(Q30+T30+U30) -> 6823130.1 | W30: =SUM(V30/E30)/T2 -> #DIV/0! | X30: =SUM(X29) -> 1584 | Y30: 106 | Z30: =SUM(Y30-S30) -> #DIV/0!
A31: =Gen!A37 -> 44313 | B31: 0 | C31: =Gen!B37 -> 0.036 | D31: =SUM(77*C31) -> 2.772 | F31: =Gen!U37 -> 0.40857666 | G31: =Gen!T37 -> 2733 | H31: =[1]Gen!AJ37 -> 280.63 | I31: =SUM(G31:H31) -> 3013.63 | J31: =[1]Gen!AT37 -> 36384.37 | K31: ='Water-Meter'!E32 -> 43 | L31: ='Lpg (2)'!G36 -> 68.508 | M31: =#REF! -> #REF! | N31: =#REF! -> #REF! | O31: =#REF! -> #REF! | P31: =J31/52000 -> 0.69969942 | Q31: =I31*Q2 -> 6659670.3 | R31: =SUM(Q31/D31)/X31 -> 1516.7162 | S31: =SUM(Q31/E31)/X31 -> #DIV/0! | T31: =(K31*102)/X31 -> 2.7689394 | U31: =SUM(L31*1963)/X31 -> 84.89975 | V31: =SUM(Q31+T31+U31) -> 6659757.9 | W31: =SUM(V31/E31)/T2 -> #DIV/0! | X31: =SUM(X30) -> 1584 | Y31: 106 | Z31: =SUM(Y31-S31) -> #DIV/0!
A32: =Gen!A38 -> 44314 | B32: 0 | C32: =Gen!B38 -> 0.039 | D32: =SUM(77*C32) -> 3.003 | F32: =Gen!U38 -> 0.4296 | G32: =Gen!T38 -> 2725 | H32: =[1]Gen!AJ38 -> 0 | I32: =SUM(G32:H32) -> 2725 | J32: =[1]Gen!AT38 -> 33780 | K32: ='Water-Meter'!E33 -> 61 | L32: ='Lpg (2)'!G37 -> 66.484 | M32: =#REF! -> #REF! | N32: =#REF! -> #REF! | O32: =#REF! -> #REF! | P32: =J32/52000 -> 0.64961538 | Q32: =I32*Q2 -> 6021841.2 | R32: =SUM(Q32/D32)/X32 -> 1265.9565 | S32: =SUM(Q32/E32)/X32 -> #DIV/0! | T32: =(K32*102)/X32 -> 3.9280303 | U32: =SUM(L32*1963)/X32 -> 82.391472 | V32: =SUM(Q32+T32+U32) -> 6021927.6 | W32: =SUM(V32/E32)/T2 -> #DIV/0! | X32: =SUM(X31) -> 1584 | Y32: 106 | Z32: =SUM(Y32-S32) -> #DIV/0!
A33: =Gen!A39 -> 44315 | B33: 0 | C33: =Gen!B39 -> 0.026 | D33: =SUM(77*C33) -> 2.002 | F33: =Gen!U39 -> 0.39306079 | G33: =Gen!T39 -> 2813 | H33: =[1]Gen!AJ39 -> 0 | I33: =SUM(G33:H33) -> 2813 | J33: =[1]Gen!AT39 -> 33780 | K33: ='Water-Meter'!E34 -> 53 | L33: ='Lpg (2)'!G38 -> 62.348 | M33: =#REF! -> #REF! | N33: =#REF! -> #REF! | O33: =#REF! -> #REF! | P33: =J33/52000 -> 0.64961538 | Q33: =I33*Q2 -> 6216308 | R33: =SUM(Q33/D33)/X33 -> 1960.2582 | S33: =SUM(Q33/E33)/X33 -> #DIV/0! | T33: =(K33*102)/X33 -> 3.4128788 | U33: =SUM(L33*1963)/X33 -> 77.265861 | V33: =SUM(Q33+T33+U33) -> 6216388.7 | W33: =SUM(V33/E33)/T2 -> #DIV/0! | X33: =SUM(X32) -> 1584 | Y33: 106 | Z33: =SUM(Y33-S33) -> #DIV/0!
A34: =Gen!A40 -> 44316 | B34: 0 | C34: =Gen!B40 -> 0.01 | D34: =SUM(77*C34) -> 0.77 | F34: =Gen!U40 -> 0.40999268 | G34: =Gen!T40 -> 2731 | H34: =[1]Gen!AJ40 -> 0 | I34: =SUM(G34:H34) -> 2731 | J34: =[1]Gen!AT40 -> 33780 | K34: ='Water-Meter'!E35 -> 58 | L34: ='Lpg (2)'!G39 -> 62.656 | M34: =#REF! -> #REF! | N34: =#REF! -> #REF! | O34: =#REF! -> #REF! | P34: =J34/52000 -> 0.64961538 | Q34: =I34*Q2 -> 6035100.3 | R34: =SUM(Q34/D34)/X34 -> 4948.1014 | S34: =SUM(Q34/E34)/X34 -> #DIV/0! | T34: =(K34*102)/X34 -> 3.7348485 | U34: =SUM(L34*1963)/X34 -> 77.647556 | V34: =SUM(Q34+T34+U34) -> 6035181.7 | W34: =SUM(V34/E34)/T2 -> #DIV/0! | X34: =SUM(X33) -> 1584 | Y34: 106 | Z34: =SUM(Y34-S34) -> #DIV/0!
