Workbook

Sheet Total
A1: Site Name | B1: Day | C1: Month | D1: Year | E1: Total Electricity Kwh | F1: Electricity Tariff ($/Kwh) | G1: Total Fuel Oil (Liters) | H1: Fuel Oil $/Liter | I1: LPG (Kg) | J1: LPG $/Kg | K1: Water Utility Supply (m3) m3 | L1: Water Utility Supply (m3) $/m3 | M1: Irrigation Water (m3) m3 | N1: Irrigation water $/m3 | O1: Room Nights
A2: Beirut | B2: 1 | C2: 5 | D2: 2021 | E2: =ELEC!N3 -> 8346 | F2: =SUM('EDl log'!T4) -> 0.20265499 | G2: =-tanks!AW6 -> 195 | H2: =SUM(tanks!AV6) -> 0.92 | I2: =('B5'!AU5)*0.51 -> 0 | J2: ='B5'!AX5/0.51 -> 1.5686275 | K2: =WATER!I6 -> 7 | L2: =SUM(WATER!J6) -> 34.562212 | M2: =WATER!Q6 -> 0 | N2: 0.6 | O2: =ELEC!B3 -> 0
A3: Beirut | B3: =B2+1 -> 2 | C3: 5 | D3: 2021 | E3: =ELEC!N4 -> 6548 | F3: =SUM('EDl log'!T5) -> 0.15946937 | G3: =-tanks!AW7 -> 153 | H3: =SUM(tanks!AV7) -> 0.92 | I3: =('B5'!AU6)*0.51 -> 0 | J3: ='B5'!AX6/0.51 -> 1.5686275 | K3: =WATER!I7 -> 0 | L3: =SUM(WATER!J7) -> 0 | M3: =WATER!Q7 -> 0 | N3: 0.6 | O3: =ELEC!B4 -> 0
A4: Beirut | B4: =B3+1 -> 3 | C4: 5 | D4: 2021 | E4: =ELEC!N5 -> 7179 | F4: =SUM('EDl log'!T6) -> 0.16489325 | G4: =-tanks!AW8 -> 141 | H4: =SUM(tanks!AV8) -> 0.92 | I4: =('B5'!AU7)*0.51 -> 0 | J4: ='B5'!AX7/0.51 -> 1.5686275 | K4: =WATER!I8 -> 289 | L4: =SUM(WATER!J8) -> 0.837147 | M4: =WATER!Q8 -> 0 | N4: 0.6 | O4: =ELEC!B5 -> 0
A5: Beirut | B5: =B4+1 -> 4 | C5: 5 | D5: 2021 | E5: =ELEC!N6 -> 8383 | F5: =SUM('EDl log'!T7) -> 0.23069229 | G5: =-tanks!AW9 -> 95 | H5: =SUM(tanks!AV9) -> 0.92 | I5: =('B5'!AU8)*0.51 -> 0 | J5: ='B5'!AX8/0.51 -> 1.5686275 | K5: =WATER!I9 -> 0 | L5: =SUM(WATER!J9) -> 0 | M5: =WATER!Q9 -> 0 | N5: 0.6 | O5: =ELEC!B6 -> 0
A6: Beirut | B6: =B5+1 -> 5 | C6: 5 | D6: 2021 | E6: =ELEC!N7 -> 4768 | F6: =SUM('EDl log'!T8) -> 0.43179438 | G6: =-tanks!AW10 -> 164 | H6: =SUM(tanks!AV10) -> 0.92 | I6: =('B5'!AU9)*0.51 -> 0 | J6: ='B5'!AX9/0.51 -> 1.5686275 | K6: =WATER!I10 -> 295 | L6: =SUM(WATER!J10) -> 0.82012028 | M6: =WATER!Q10 -> 0 | N6: 0.6 | O6: =ELEC!B7 -> 0
A7: Beirut | B7: =B6+1 -> 6 | C7: 5 | D7: 2021 | E7: =ELEC!N8 -> 3912 | F7: =SUM('EDl log'!T9) -> 0.33343126 | G7: =-tanks!AW11 -> 155 | H7: =SUM(tanks!AV11) -> 0.92 | I7: =('B5'!AU10)*0.51 -> 0 | J7: ='B5'!AX10/0.51 -> 1.5686275 | K7: =WATER!I11 -> 0 | L7: =SUM(WATER!J11) -> 0 | M7: =WATER!Q11 -> 0 | N7: 0.6 | O7: =ELEC!B8 -> 0
A8: Beirut | B8: =B7+1 -> 7 | C8: 5 | D8: 2021 | E8: =ELEC!N9 -> 8995.4 | F8: =SUM('EDl log'!T10) -> 0.24911547 | G8: =-tanks!AW12 -> 166 | H8: =SUM(tanks!AV12) -> 0.92 | I8: =('B5'!AU11)*0.51 -> 0 | J8: ='B5'!AX11/0.51 -> 1.5686275 | K8: =WATER!I12 -> 293 | L8: =SUM(WATER!J12) -> 0.82571837 | M8: =WATER!Q12 -> 0 | N8: 0.6 | O8: =ELEC!B9 -> 0
A9: Beirut | B9: =B8+1 -> 8 | C9: 5 | D9: 2021 | E9: =ELEC!N10 -> 8249.8 | F9: =SUM('EDl log'!T11) -> 0.26949467 | G9: =-tanks!AW13 -> 156 | H9: =SUM(tanks!AV13) -> 0.92 | I9: =('B5'!AU12)*0.51 -> 0 | J9: ='B5'!AX12/0.51 -> 1.5686275 | K9: =WATER!I13 -> 0 | L9: =SUM(WATER!J13) -> 0 | M9: =WATER!Q13 -> 0 | N9: 0.6 | O9: =ELEC!B10 -> 0
A10: Beirut | B10: =B9+1 -> 9 | C10: 5 | D10: 2021 | E10: =ELEC!N11 -> 9025.8 | F10: =SUM('EDl log'!T12) -> 0.22805083 | G10: =-tanks!AW14 -> 112 | H10: =SUM(tanks!AV14) -> 0.92 | I10: =('B5'!AU13)*0.51 -> 0 | J10: ='B5'!AX13/0.51 -> 1.5686275 | K10: =WATER!I14 -> 0 | L10: =SUM(WATER!J14) -> 0 | M10: =WATER!Q14 -> 0 | N10: 0.6 | O10: =ELEC!B11 -> 0
A11: Beirut | B11: =B10+1 -> 10 | C11: 5 | D11: 2021 | E11: =ELEC!N12 -> 9481 | F11: =SUM('EDl log'!T13) -> 0.26187809 | G11: =-tanks!AW15 -> 82 | H11: =SUM(tanks!AV15) -> 0.92 | I11: =('B5'!AU14)*0.51 -> 0 | J11: ='B5'!AX14/0.51 -> 1.5686275 | K11: =WATER!I15 -> 0 | L11: =SUM(WATER!J15) -> 0 | M11: =WATER!Q15 -> 0 | N11: 0.6 | O11: =ELEC!B12 -> 0
A12: Beirut | B12: =B11+1 -> 11 | C12: 5 | D12: 2021 | E12: =ELEC!N13 -> 9028 | F12: =SUM('EDl log'!T14) -> -0.061126052 | G12: =-tanks!AW16 -> 137 | H12: =SUM(tanks!AV16) -> 0.94 | I12: =('B5'!AU15)*0.51 -> 0 | J12: ='B5'!AX15/0.51 -> 1.5686275 | K12: =WATER!I16 -> 0 | L12: =SUM(WATER!J16) -> 0 | M12: =WATER!Q16 -> 0 | N12: 0.6 | O12: =ELEC!B13 -> 0
A13: Beirut | B13: =B12+1 -> 12 | C13: 5 | D13: 2021 | E13: =ELEC!N14 -> 9411 | F13: =SUM('EDl log'!T15) -> 0.30014205 | G13: =-tanks!AW17 -> 154 | H13: =SUM(tanks!AV17) -> 0.94 | I13: =('B5'!AU16)*0.51 -> 0 | J13: ='B5'!AX16/0.51 -> 1.5686275 | K13: =WATER!I17 -> 0 | L13: =SUM(WATER!J17) -> 0 | M13: =WATER!Q17 -> 0 | N13: 0.6 | O13: =ELEC!B14 -> 0
A14: Beirut | B14: =B13+1 -> 13 | C14: 5 | D14: 2021 | E14: =ELEC!N15 -> 9646 | F14: =SUM('EDl log'!T16) -> 0.24391848 | G14: =-tanks!AW18 -> 115 | H14: =SUM(tanks!AV18) -> 0.94 | I14: =('B5'!AU17)*0.51 -> 0 | J14: ='B5'!AX17/0.51 -> 1.5686275 | K14: =WATER!I18 -> 341 | L14: =SUM(WATER!J18) -> 0.70948822 | M14: =WATER!Q18 -> 0 | N14: 0.6 | O14: =ELEC!B15 -> 0
... A32: Beirut | B32: =B31+1 -> 31 | C32: 5 | D32: 2022 | E32: =ELEC!N33 -> 0 | F32: =SUM('EDl log'!T34) -> 0 | G32: =-tanks!AW36 -> 0 | H32: =SUM(tanks!AV36) -> 1.003 | I32: =('B5'!AU35)*0.51 -> 0 | J32: ='B5'!AX35/0.51 -> 1.5686275 | K32: =WATER!I36 -> 0 | L32: =SUM(WATER!J36) -> 0 | M32: =WATER!Q36 -> 0 | N32: 1.6 | O32: =ELEC!B33 -> 0

Sheet Submetering
A1: Site Name | B1: Day | C1: Month | D1: Year | E1: ATS1 Kwh | F1: ATS2 Kwh | G1: ATS3 Kwh | H1: ATS4 Kwh | I1: ATS5 Kwh | J1: Guest (m3) | K1: Kitchen & Laundry (m3) | L1: Room Nights
A2: Beirut | B2: 1 | C2: 5 | D2: 2021 | E2: =ELEC!M3 -> 2194 | F2: =ELEC!K3 -> 1280 | G2: =ELEC!I3 -> 882 | H2: =ELEC!E3 -> 3356 | I2: =ELEC!G3 -> 634 | J2: =WATER!Y6 -> 0 | K2: =WATER!AJ6 -> 0 | L2: =ELEC!B3 -> 0
A3: Beirut | B3: =B2+1 -> 2 | C3: 5 | D3: 2021 | E3: =ELEC!M4 -> 1698 | F3: =ELEC!K4 -> 912 | G3: =ELEC!I4 -> 692 | H3: =ELEC!E4 -> 2632 | I3: =ELEC!G4 -> 614 | J3: =WATER!Y7 -> 0 | K3: =WATER!AJ7 -> 0 | L3: =ELEC!B4 -> 0
A4: Beirut | B4: =B3+1 -> 3 | C4: 5 | D4: 2021 | E4: =ELEC!M5 -> 1276 | F4: =ELEC!K5 -> 920 | G4: =ELEC!I5 -> 804 | H4: =ELEC!E5 -> 3588 | I4: =ELEC!G5 -> 591 | J4: =WATER!Y8 -> 82 | K4: =WATER!AJ8 -> 36 | L4: =ELEC!B5 -> 0
A5: Beirut | B5: =B4+1 -> 4 | C5: 5 | D5: 2021 | E5: =ELEC!M6 -> 1652 | F5: =ELEC!K6 -> 2336 | G5: =ELEC!I6 -> 788 | H5: =ELEC!E6 -> 2984 | I5: =ELEC!G6 -> 623 | J5: =WATER!Y9 -> 1 | K5: =WATER!AJ9 -> 0 | L5: =ELEC!B6 -> 0
A6: Beirut | B6: =B5+1 -> 5 | C6: 5 | D6: 2021 | E6: =ELEC!M7 -> 1880 | F6: =ELEC!K7 -> 1312 | G6: =ELEC!I7 -> 912 | H6: =ELEC!E7 -> 0 | I6: =ELEC!G7 -> 664 | J6: =WATER!Y10 -> 105 | K6: =WATER!AJ10 -> 0 | L6: =ELEC!B7 -> 0
A7: Beirut | B7: =B6+1 -> 6 | C7: 5 | D7: 2021 | E7: =ELEC!M8 -> 1498 | F7: =ELEC!K8 -> 924 | G7: =ELEC!I8 -> 792 | H7: =ELEC!AO8 -> 5767 | I7: =ELEC!G8 -> 698 | J7: =WATER!Y11 -> 0 | K7: =WATER!AJ11 -> 0 | L7: =ELEC!B8 -> 0
A8: Beirut | B8: =B7+1 -> 7 | C8: 5 | D8: 2021 | E8: =ELEC!M9 -> 1848 | F8: =ELEC!K9 -> 1228 | G8: =ELEC!I9 -> 968 | H8: =ELEC!AO9 -> 4201 | I8: =ELEC!G9 -> 750.4 | J8: =WATER!Y12 -> 145 | K8: =WATER!AJ12 -> 0 | L8: =ELEC!B9 -> 0
A9: Beirut | B9: =B8+1 -> 8 | C9: 5 | D9: 2021 | E9: =ELEC!M10 -> 1638 | F9: =ELEC!K10 -> 1186 | G9: =ELEC!I10 -> 792 | H9: =ELEC!AO10 -> 3953 | I9: =ELEC!G10 -> 680.8 | J9: =WATER!Y13 -> 0 | K9: =WATER!AJ13 -> 32 | L9: =ELEC!B10 -> 0
A10: Beirut | B10: =B9+1 -> 9 | C10: 5 | D10: 2021 | E10: =ELEC!M11 -> 1780 | F10: =ELEC!K11 -> 1272 | G10: =ELEC!I11 -> 796 | H10: =ELEC!AO11 -> 4500 | I10: =ELEC!G11 -> 677.8 | J10: =WATER!Y14 -> 26 | K10: =WATER!AJ14 -> 11 | L10: =ELEC!B11 -> 0
A11: Beirut | B11: =B10+1 -> 10 | C11: 5 | D11: 2021 | E11: =ELEC!M12 -> 1812 | F11: =ELEC!K12 -> 3382 | G11: =ELEC!I12 -> 836 | H11: =ELEC!AO12 -> 2791 | I11: =ELEC!G12 -> 660 | J11: =WATER!Y15 -> 0 | K11: =WATER!AJ15 -> 0 | L11: =ELEC!B12 -> 0
A12: Beirut | B12: =B11+1 -> 11 | C12: 5 | D12: 2021 | E12: =ELEC!M13 -> 1774 | F12: =ELEC!K13 -> 2956 | G12: =ELEC!I13 -> 906 | H12: =ELEC!AO13 -> 2692 | I12: =ELEC!G13 -> 700 | J12: =WATER!Y16 -> 0 | K12: =WATER!AJ16 -> 0 | L12: =ELEC!B13 -> 0
A13: Beirut | B13: =B12+1 -> 12 | C13: 5 | D13: 2021 | E13: =ELEC!M14 -> 1894 | F13: =ELEC!K14 -> 3444 | G13: =ELEC!I14 -> 910 | H13: =ELEC!AO14 -> 2489 | I13: =ELEC!G14 -> 674 | J13: =WATER!Y17 -> 0 | K13: =WATER!AJ17 -> 0 | L13: =ELEC!B14 -> 0
A14: Beirut | B14: =B13+1 -> 13 | C14: 5 | D14: 2021 | E14: =ELEC!M15 -> 1736 | F14: =ELEC!K15 -> 4104 | G14: =ELEC!I15 -> 788 | H14: =ELEC!AO15 -> 2415 | I14: =ELEC!G15 -> 603 | J14: =WATER!Y18 -> 0 | K14: =WATER!AJ18 -> 0 | L14: =ELEC!B15 -> 0
A15: Beirut | B15: =B14+1 -> 14 | C15: 5 | D15: 2021 | E15: =ELEC!M16 -> 1296 | F15: =ELEC!K16 -> 3042 | G15: =ELEC!I16 -> 748 | H15: =ELEC!AO16 -> 3136 | I15: =ELEC!G16 -> 646 | J15: =WATER!Y19 -> 0 | K15: =WATER!AJ19 -> 0 | L15: =ELEC!B16 -> 0
A16: Beirut | B16: =B15+1 -> 15 | C16: 5 | D16: 2021 | E16: =ELEC!M17 -> 1584 | F16: =ELEC!K17 -> 2474 | G16: =ELEC!I17 -> 836 | H16: =ELEC!AO17 -> 2032 | I16: =ELEC!G17 -> 661 | J16: =WATER!Y20 -> 0 | K16: =WATER!AJ20 -> 0 | L16: =ELEC!B17 -> 0
A17: Beirut | B17: =B16+1 -> 16 | C17: 5 | D17: 2021 | E17: =ELEC!M18 -> 2340 | F17: =ELEC!K18 -> 5432 | G17: =ELEC!I18 -> 1032 | H17: =ELEC!AO18 -> 3443 | I17: =ELEC!G18 -> 592 | J17: =WATER!Y21 -> 0 | K17: =WATER!AJ21 -> 0 | L17: =ELEC!B18 -> 0
A18: Beirut | B18: =B17+1 -> 17 | C18: 5 | D18: 2021 | E18: =ELEC!M19 -> 2048 | F18: =ELEC!K19 -> 2824 | G18: =ELEC!I19 -> 836 | H18: =ELEC!AO19 -> 3701 | I18: =ELEC!G19 -> 680 | J18: =WATER!Y22 -> 0 | K18: =WATER!AJ22 -> 0 | L18: =ELEC!B19 -> 0
... A32: Beirut | B32: =B31+1 -> 31 | C32: 5 | D32: 2021 | E32: =ELEC!M33 -> 0 | F32: =ELEC!K33 -> 0 | G32: =ELEC!I33 -> 0 | H32: =ELEC!AO33 -> 0 | I32: =ELEC!G33 -> 0 | J32: =WATER!Y36 -> 0 | K32: =WATER!AJ36 -> 0 | L32: =ELEC!B33 -> 0
D46: .

Sheet ELEC
A1: OOC | B1: Room OCC | D1: MDB3 | E1: MDB3/day | F1: EMDB2 | G1: EMDB2/day | H1: EMDB1 | I1: EMDB1/day | J1: MDB2 | K1: mdb2/day | L1: MDB1 | M1: MDB1/Day | N1: Total KWH | O1: KWH/Rooc | P1: Gen MHW | Q1: Gen/Day KWH | R1: EDL KWH | S1: CH1 RH | T1: RH | U1: C1h1 power | V1: CH1 Con KWH | W1: CH2 RH | X1: RH | Y1: Ch2 power | Z1: CH2 Con KWH | AA1: CH3 RH | AB1: RH | AC1: Ch3 power | AD1: CH3 Con KWH | AE1: RH total | AF1: KWH total | AG1: AVG chiller KW/Hr
A2: ='General information '!F5 -> 0 | B2: =SUM(230*A2) -> 0 | C2: 44316 | D2: 32819750 | E2: 3108 | F2: 4009734 | G2: 304 | H2: 17856136 | I2: 765 | J2: 29011666 | K2: 1972 | L2: 24175590 | M2: 1724 | N2: 7873 | O2: 0 | P2: 16972.836 | Q2: 4977 | R2: 2896 | S2: 10175 | T2: 0 | U2: 429166 | V2: 0 | W2: 32312 | X2: 5 | Y2: 721364 | Z2: 825 | AA2: 35884 | AB2: 3 | AC2: 949998 | AD2: 560 | AE2: 8 | AF2: 1385 | AG2: 173.125 | AI2: -999706
A3: ='General information '!F6 -> 0 | B3: =SUM(230*A3) -> 0 | C3: 44317 | D3: 32823106 | E3: =D3-D2 -> 3356 | F3: 4010368 | G3: =F3-F2 -> 634 | H3: 17857018 | I3: =H3-H2 -> 882 | J3: 29012946 | K3: =J3-J2 -> 1280 | L3: 24177784 | M3: =L3-L2 -> 2194 | N3: =M3+K3+I3+G3+E3 -> 8346 | O3: =IF(B3>0,N3/B3,0) -> 0 | P3: 16976.763 | Q3: =(P3-P2)*1000 -> 3927 | R3: =+N3-Q3 -> 4419 | S3: =S2 -> 10175 | T3: =S3-S2 -> 0 | U3: 429166 | V3: =U3-U2 -> 0 | W3: 32312 | X3: =W3-W2 -> 0 | Y3: =Y2 -> 721364 | Z3: =Y3-Y2 -> 0 | AA3: 35889 | AB3: =AA3-AA2 -> 5 | AC3: 951030 | AD3: =AC3-AC2 -> 1032 | AE3: =AB3+X3+T3 -> 5 | AF3: =V3+Z3+AD3 -> 1032 | AG3: =IF(AE3>0,AF3/AE3,0) -> 206.4
A4: ='General information '!F7 -> 0 | B4: =SUM(230*A4) -> 0 | C4: 44318 | D4: 32825738 | E4: =D4-D3 -> 2632 | F4: 4010982 | G4: =F4-F3 -> 614 | H4: 17857710 | I4: =H4-H3 -> 692 | J4: 29013858 | K4: =J4-J3 -> 912 | L4: 24179482 | M4: =L4-L3 -> 1698 | N4: =M4+K4+I4+G4+E4 -> 6548 | O4: =IF(B4>0,N4/B4,0) -> 0 | P4: 16978.759 | Q4: =(P4-P3)*1000 -> 1996 | R4: =N4-Q4 -> 4552 | S4: =S3 -> 10175 | T4: =S4-S3 -> 0 | U4: =U3 -> 429166 | V4: =U4-U3 -> 0 | W4: =W3 -> 32312 | X4: =W4-W3 -> 0 | Y4: =Y3 -> 721364 | Z4: =Y4-Y3 -> 0 | AA4: 35891 | AB4: =AA4-AA3 -> 2 | AC4: 951609 | AD4: =AC4-AC3 -> 579 | AE4: =AB4+X4+T4 -> 2 | AF4: =V4+Z4+AD4 -> 579 | AG4: =IF(AE4>0,AF4/AE4,0) -> 289.5 | AL4: ATS 4 till power meter is for MDB 3 is replaced
A5: ='General information '!F8 -> 0 | B5: =SUM(230*A5) -> 0 | C5: 44319 | D5: 32829326 | E5: =D5-D4 -> 3588 | F5: 4011573 | G5: =F5-F4 -> 591 | H5: 17858514 | I5: =H5-H4 -> 804 | J5: 29014778 | K5: =J5-J4 -> 920 | L5: 24180758 | M5: =L5-L4 -> 1276 | N5: =M5+K5+I5+G5+E5 -> 7179 | O5: =IF(B5>0,N5/B5,0) -> 0 | P5: 16981.779 | Q5: =(P5-P4)*1000 -> 3020 | R5: =N5-Q5 -> 4159 | S5: =S4 -> 10175 | T5: =S5-S4 -> 0 | U5: =U4 -> 429166 | V5: =U5-U4 -> 0 | W5: =W4 -> 32312 | X5: =W5-W4 -> 0 | Y5: =Y4 -> 721364 | Z5: =Y5-Y4 -> 0 | AA5: 35896 | AB5: =AA5-AA4 -> 5 | AC5: 952602 | AD5: =AC5-AC4 -> 993 | AE5: =AB5+X5+T5 -> 5 | AF5: =V5+Z5+AD5 -> 993 | AG5: =IF(AE5>0,AF5/AE5,0) -> 198.6 | AI5: =R5-'EDl log'!B3 -> -1004651 | AL5: Emergency | AM5: Normal | AN5: Total | AO5: Deference
A6: ='General information '!F9 -> 0 | B6: =SUM(230*A6) -> 0 | C6: 44320 | D6: 32832310 | E6: =D6-D5 -> 2984 | F6: 4012196 | G6: =F6-F5 -> 623 | H6: 17859302 | I6: =H6-H5 -> 788 | J6: 29017114 | K6: =J6-J5 -> 2336 | L6: 24182410 | M6: =L6-L5 -> 1652 | N6: =M6+K6+I6+G6+E6 -> 8383 | O6: =IF(B6>0,N6/B6,0) -> 0 | P6: 16985.99 | Q6: =(P6-P5)*1000 -> 4211 | R6: =N6-Q6 -> 4172 | S6: =S5 -> 10175 | T6: =S6-S5 -> 0 | U6: =U5 -> 429166 | V6: =U6-U5 -> 0 | W6: 32317 | X6: =W6-W5 -> 5 | Y6: 722633 | Z6: =Y6-Y5 -> 1269 | AA6: 35896 | AB6: =AA6-AA5 -> 0 | AC6: =AC5 -> 952602 | AD6: =AC6-AC5 -> 0 | AE6: =AB6+X6+T6 -> 5 | AF6: =V6+Z6+AD6 -> 1269 | AG6: =IF(AE6>0,AF6/AE6,0) -> 253.8 | AI6: =R6-'EDl log'!B4 -> -1007025 | AK6: 44320 | AL6: 270643 | AM6: 409413 | AN6: =AM6+AL6 -> 680056
A7: ='General information '!F10 -> 0 | B7: =SUM(230*A7) -> 0 | C7: 44321 | D7: 32832310 | E7: =D7-D6 -> 0 | F7: 4012860 | G7: =F7-F6 -> 664 | H7: 17860214 | I7: =H7-H6 -> 912 | J7: 29018426 | K7: =J7-J6 -> 1312 | L7: 24184290 | M7: =L7-L6 -> 1880 | N7: =M7+K7+I7+G7+E7 -> 4768 | O7: =IF(B7>0,N7/B7,0) -> 0 | P7: 16991.6 | Q7: =(P7-P6)*1000 -> 5610 | R7: =N7-Q7 -> -842 | S7: =S6 -> 10175 | T7: =S7-S6 -> 0 | U7: =U6 -> 429166 | V7: =U7-U6 -> 0 | W7: 32317 | X7: =W7-W6 -> 0 | Y7: 722652 | Z7: =Y7-Y6 -> 19 | AA7: 35905 | AB7: =AA7-AA6 -> 9 | AC7: 954371 | AD7: =AC7-AC6 -> 1769 | AE7: =AB7+X7+T7 -> 9 | AF7: =V7+Z7+AD7 -> 1788 | AG7: =IF(AE7>0,AF7/AE7,0) -> 198.66667 | AI7: =R7-'EDl log'!B5 -> -1014456 | AK7: 44321 | AL7: 270643 | AM7: 409413 | AN7: =AM7+AL7 -> 680056 | AO7: =AN7-AN6 -> 0
A8: ='General information '!F11 -> 0 | B8: =SUM(230*A8) -> 0 | C8: 44322 | D8: 32832310 | E8: =D8-D7 -> 0 | F8: 4013558 | G8: =F8-F7 -> 698 | H8: 17861006 | I8: =H8-H7 -> 792 | J8: 29019350 | K8: =J8-J7 -> 924 | L8: 24185788 | M8: =L8-L7 -> 1498 | N8: =M8+K8+I8+G8+E8 -> 3912 | O8: =IF(B8>0,N8/B8,0) -> 0 | P8: 16995.082 | Q8: =(P8-P7)*1000 -> 3482 | R8: =N8-Q8 -> 430 | S8: 10175 | T8: =S8-S7 -> 0 | U8: =U7 -> 429166 | V8: =U8-U7 -> 0 | W8: =W7 -> 32317 | X8: =W8-W7 -> 0 | Y8: =Y7 -> 722652 | Z8: =Y8-Y7 -> 0 | AA8: 35909 | AB8: =AA8-AA7 -> 4 | AC8: 955297 | AD8: =AC8-AC7 -> 926 | AE8: =AB8+X8+T8 -> 4 | AF8: =V8+Z8+AD8 -> 926 | AG8: =IF(AE8>0,AF8/AE8,0) -> 231.5 | AI8: =R8-'EDl log'!B6 -> -1015450 | AK8: 44322 | AL8: 274499 | AM8: 411324 | AN8: =AM8+AL8 -> 685823 | AO8: =AN8-AN7 -> 5767
A9: ='General information '!F12 -> 0 | B9: =SUM(230*A9) -> 0 | C9: 44323 | D9: =D8+AO9 -> 32836511 | E9: =D9-D8 -> 4201 | F9: 4014308.4 | G9: =F9-F8 -> 750.4 | H9: 17861974 | I9: =H9-H8 -> 968 | J9: 29020578 | K9: =J9-J8 -> 1228 | L9: 24187636 | M9: =L9-L8 -> 1848 | N9: =M9+K9+I9+G9+E9 -> 8995.4 | O9: =IF(B9>0,N9/B9,0) -> 0 | P9: 17000.937 | Q9: =(P9-P8)*1000 -> 5855 | R9: =N9-Q9 -> 3140.4 | S9: =S8 -> 10175 | T9: =S9-S8 -> 0 | U9: =U8 -> 429166 | V9: =U9-U8 -> 0 | W9: =W8 -> 32317 | X9: =W9-W8 -> 0 | Y9: =Y8 -> 722652 | Z9: =Y9-Y8 -> 0 | AA9: 35917 | AB9: =AA9-AA8 -> 8 | AC9: 956869 | AD9: =AC9-AC8 -> 1572 | AE9: =AB9+X9+T9 -> 8 | AF9: =V9+Z9+AD9 -> 1572 | AG9: =IF(AE9>0,AF9/AE9,0) -> 196.5 | AI9: =R9-'EDl log'!B7 -> -1014626.6 | AK9: 44323 | AL9: 277740 | AM9: 412284 | AN9: =AM9+AL9 -> 690024 | AO9: =AN9-AN8 -> 4201
A10: ='General information '!F13 -> 0 | B10: =SUM(230*A10) -> 0 | C10: 44324 | D10: =D9+AO10 -> 32840464 | E10: =D10-D9 -> 3953 | F10: 4014989.2 | G10: =F10-F9 -> 680.8 | H10: 17862766 | I10: =H10-H9 -> 792 | J10: 29021764 | K10: =J10-J9 -> 1186 | L10: 24189274 | M10: =L10-L9 -> 1638 | N10: =M10+K10+I10+G10+E10 -> 8249.8 | O10: =IF(B10>0,N10/B10,0) -> 0 | P10: 17006.446 | Q10: =(P10-P9)*1000 -> 5509 | R10: =N10-Q10 -> 2740.8 | S10: =S9 -> 10175 | T10: =S10-S9 -> 0 | U10: =U9 -> 429166 | V10: =U10-U9 -> 0 | W10: =W9 -> 32317 | X10: =W10-W9 -> 0 | Y10: =Y9 -> 722652 | Z10: =Y10-Y9 -> 0 | AA10: 35924 | AB10: =AA10-AA9 -> 7 | AC10: 958420 | AD10: =AC10-AC9 -> 1551 | AE10: =AB10+X10+T10 -> 7 | AF10: =V10+Z10+AD10 -> 1551 | AG10: =IF(AE10>0,AF10/AE10,0) -> 221.57143 | AI10: =R10-'EDl log'!B8 -> -1017112.2 | AK10: 44324 | AL10: 280877 | AM10: 413100 | AN10: =AM10+AL10 -> 693977 | AO10: =AN10-AN9 -> 3953
A11: ='General information '!F14 -> 0 | B11: =SUM(230*A11) -> 0 | C11: 44325 | D11: =D10+AO11 -> 32844964 | E11: =D11-D10 -> 4500 | F11: 4015667 | G11: =F11-F10 -> 677.8 | H11: 17863562 | I11: =H11-H10 -> 796 | J11: 29023036 | K11: =J11-J10 -> 1272 | L11: 24191054 | M11: =L11-L10 -> 1780 | N11: =M11+K11+I11+G11+E11 -> 9025.8 | O11: =IF(B11>0,N11/B11,0) -> 0 | P11: 17012.749 | Q11: =(P11-P10)*1000 -> 6303 | R11: =N11-Q11 -> 2722.8 | S11: =S10 -> 10175 | T11: =S11-S10 -> 0 | U11: =U10 -> 429166 | V11: =U11-U10 -> 0 | W11: =W10 -> 32317 | X11: =W11-W10 -> 0 | Y11: =Y10 -> 722652 | Z11: =Y11-Y10 -> 0 | AA11: 35932 | AB11: =AA11-AA10 -> 8 | AC11: 960238 | AD11: =AC11-AC10 -> 1818 | AE11: =AB11+X11+T11 -> 8 | AF11: =V11+Z11+AD11 -> 1818 | AG11: =IF(AE11>0,AF11/AE11,0) -> 227.25 | AI11: =R11-'EDl log'!B9 -> -1019084.2 | AK11: 44325 | AL11: 284469 | AM11: 414008 | AN11: =AM11+AL11 -> 698477 | AO11: =AN11-AN10 -> 4500
A12: ='General information '!F15 -> 0 | B12: =SUM(230*A12) -> 0 | C12: 44326 | D12: =D11+AO12 -> 32847755 | E12: =D12-D11 -> 2791 | F12: 4016327 | G12: =F12-F11 -> 660 | H12: 17864398 | I12: =H12-H11 -> 836 | J12: 29026418 | K12: =J12-J11 -> 3382 | L12: 24192866 | M12: =L12-L11 -> 1812 | N12: =M12+K12+I12+G12+E12 -> 9481 | O12: =IF(B12>0,N12/B12,0) -> 0 | P12: 17019.087 | Q12: =(P12-P11)*1000 -> 6338 | R12: =N12-Q12 -> 3143 | S12: =S11 -> 10175 | T12: =S12-S11 -> 0 | U12: =U11 -> 429166 | V12: =U12-U11 -> 0 | W12: 32325 | X12: =W12-W11 -> 8 | Y12: 724713 | Z12: =Y12-Y11 -> 2061 | AA12: =AA11 -> 35932 | AB12: =AA12-AA11 -> 0 | AC12: =AC11 -> 960238 | AD12: =AC12-AC11 -> 0 | AE12: =AB12+X12+T12 -> 8 | AF12: =V12+Z12+AD12 -> 2061 | AG12: =IF(AE12>0,AF12/AE12,0) -> 257.625 | AI12: =R12-'EDl log'!B10 -> -1020410 | AK12: 44326 | AL12: 286090 | AM12: 415178 | AN12: =AM12+AL12 -> 701268 | AO12: =AN12-AN11 -> 2791
A13: ='General information '!F16 -> 0 | B13: =SUM(230*A13) -> 0 | C13: 44327 | D13: =D12+AO13 -> 32850447 | E13: =D13-D12 -> 2692 | F13: 4017027 | G13: =F13-F12 -> 700 | H13: 17865304 | I13: =H13-H12 -> 906 | J13: 29029374 | K13: =J13-J12 -> 2956 | L13: 24194640 | M13: =L13-L12 -> 1774 | N13: =M13+K13+I13+G13+E13 -> 9028 | O13: =IF(B13>0,N13/B13,0) -> 0 | P13: 17024.831 | Q13: =(P13-P12)*1000 -> 5744 | R13: =N13-Q13 -> 3284 | S13: =S12 -> 10175 | T13: =S13-S12 -> 0 | U13: =U12 -> 429166 | V13: =U13-U12 -> 0 | W13: 32332 | X13: =W13-W12 -> 7 | Y13: 726135 | Z13: =Y13-Y12 -> 1422 | AA13: =AA12 -> 35932 | AB13: =AA13-AA12 -> 0 | AC13: =AC12 -> 960238 | AD13: =AC13-AC12 -> 0 | AE13: =AB13+X13+T13 -> 7 | AF13: =V13+Z13+AD13 -> 1422 | AG13: =IF(AE13>0,AF13/AE13,0) -> 203.14286 | AI13: =R13-'EDl log'!B11 -> -1021853 | AK13: 44327 | AL13: 287725 | AM13: 416235 | AN13: =AM13+AL13 -> 703960 | AO13: =AN13-AN12 -> 2692
A14: ='General information '!F17 -> 0 | B14: =SUM(230*A14) -> 0 | C14: 44328 | D14: =D13+AO14 -> 32852936 | E14: =D14-D13 -> 2489 | F14: 4017701 | G14: =F14-F13 -> 674 | H14: 17866214 | I14: =H14-H13 -> 910 | J14: 29032818 | K14: =J14-J13 -> 3444 | L14: 24196534 | M14: =L14-L13 -> 1894 | N14: =M14+K14+I14+G14+E14 -> 9411 | O14: =IF(B14>0,N14/B14,0) -> 0 | P14: 17032.1 | Q14: =(P14-P13)*1000 -> 7269 | R14: =N14-Q14 -> 2142 | S14: =S13 -> 10175 | T14: =S14-S13 -> 0 | U14: =U13 -> 429166 | V14: =U14-U13 -> 0 | W14: 32341 | X14: =W14-W13 -> 9 | Y14: 728306 | Z14: =Y14-Y13 -> 2171 | AA14: =AA13 -> 35932 | AB14: =AA14-AA13 -> 0 | AC14: =AC13 -> 960238 | AD14: =AC14-AC13 -> 0 | AE14: =AB14+X14+T14 -> 9 | AF14: =V14+Z14+AD14 -> 2171 | AG14: =IF(AE14>0,AF14/AE14,0) -> 241.22222 | AI14: =R14-'EDl log'!B12 -> -1024547 | AK14: 44328 | AL14: 289550 | AM14: 416899 | AN14: =AM14+AL14 -> 706449 | AO14: =AN14-AN13 -> 2489
A15: ='General information '!F18 -> 0 | B15: =SUM(230*A15) -> 0 | C15: 44329 | D15: =D14+AO15 -> 32855351 | E15: =D15-D14 -> 2415 | F15: 4018304 | G15: =F15-F14 -> 603 | H15: 17867002 | I15: =H15-H14 -> 788 | J15: 29036922 | K15: =J15-J14 -> 4104 | L15: 24198270 | M15: =L15-L14 -> 1736 | N15: =M15+K15+I15+G15+E15 -> 9646 | O15: =IF(B15>0,N15/B15,0) -> 0 | P15: 17038.805 | Q15: =(P15-P14)*1000 -> 6705 | R15: =N15-Q15 -> 2941 | S15: =S14 -> 10175 | T15: =S15-S14 -> 0 | U15: =U14 -> 429166 | V15: =U15-U14 -> 0 | W15: 32349 | X15: =W15-W14 -> 8 | Y15: 730287 | Z15: =Y15-Y14 -> 1981 | AA15: =AA14 -> 35932 | AB15: =AA15-AA14 -> 0 | AC15: =AC14 -> 960238 | AD15: =AC15-AC14 -> 0 | AE15: =AB15+X15+T15 -> 8 | AF15: =V15+Z15+AD15 -> 1981 | AG15: =IF(AE15>0,AF15/AE15,0) -> 247.625 | AI15: =R15-'EDl log'!B13 -> -1025522 | AK15: 44329 | AL15: 291124 | AM15: 417740 | AN15: =AM15+AL15 -> 708864 | AO15: =AN15-AN14 -> 2415
A16: ='General information '!F19 -> 0 | B16: =SUM(230*A16) -> 0 | C16: 44330 | D16: =D15+AO16 -> 32858487 | E16: =D16-D15 -> 3136 | F16: 4018950 | G16: =F16-F15 -> 646 | H16: 17867750 | I16: =H16-H15 -> 748 | J16: 29039964 | K16: =J16-J15 -> 3042 | L16: 24199566 | M16: =L16-L15 -> 1296 | N16: =M16+K16+I16+G16+E16 -> 8868 | O16: =IF(B16>0,N16/B16,0) -> 0 | P16: 17044.19 | Q16: =(P16-P15)*1000 -> 5385 | R16: =N16-Q16 -> 3483 | S16: =S15 -> 10175 | T16: =S16-S15 -> 0 | U16: =U15 -> 429166 | V16: =U16-U15 -> 0 | W16: 32354 | X16: =W16-W15 -> 5 | Y16: 731328 | Z16: =Y16-Y15 -> 1041 | AA16: 35935 | AB16: =AA16-AA15 -> 3 | AC16: 960881 | AD16: =AC16-AC15 -> 643 | AE16: =AB16+X16+T16 -> 8 | AF16: =V16+Z16+AD16 -> 1684 | AG16: =IF(AE16>0,AF16/AE16,0) -> 210.5 | AI16: =R16-'EDl log'!B14 -> -1026783 | AK16: 44330 | AL16: 292977 | AM16: 419023 | AN16: =AM16+AL16 -> 712000 | AO16: =AN16-AN15 -> 3136
A17: ='General information '!F20 -> 0 | B17: =SUM(230*A17) -> 0 | C17: 44331 | D17: =D16+AO17 -> 32860519 | E17: =D17-D16 -> 2032 | F17: 4019611 | G17: =F17-F16 -> 661 | H17: 17868586 | I17: =H17-H16 -> 836 | J17: 29042438 | K17: =J17-J16 -> 2474 | L17: 24201150 | M17: =L17-L16 -> 1584 | N17: =M17+K17+I17+G17+E17 -> 7587 | O17: =IF(B17>0,N17/B17,0) -> 0 | P17: 17050.586 | Q17: =(P17-P16)*1000 -> 6396 | R17: =N17-Q17 -> 1191 | S17: =S16 -> 10175 | T17: =S17-S16 -> 0 | U17: =U16 -> 429166 | V17: =U17-U16 -> 0 | W17: 32359 | X17: =W17-W16 -> 5 | Y17: 732497 | Z17: =Y17-Y16 -> 1169 | AA17: =AA16 -> 35935 | AB17: =AA17-AA16 -> 0 | AC17: =AC16 -> 960881 | AD17: =AC17-AC16 -> 0 | AE17: =AB17+X17+T17 -> 5 | AF17: =V17+Z17+AD17 -> 1169 | AG17: =IF(AE17>0,AF17/AE17,0) -> 233.8 | AI17: =R17-'EDl log'!B15 -> -1030324 | AK17: 44331 | AL17: 294108 | AM17: 419924 | AN17: =AM17+AL17 -> 714032 | AO17: =AN17-AN16 -> 2032
A18: ='General information '!F21 -> 0 | B18: =SUM(230*A18) -> 0 | C18: 44332 | D18: =D17+AO18 -> 32863962 | E18: =D18-D17 -> 3443 | F18: 4020203 | G18: =F18-F17 -> 592 | H18: 17869618 | I18: =H18-H17 -> 1032 | J18: 29047870 | K18: =J18-J17 -> 5432 | L18: 24203490 | M18: =L18-L17 -> 2340 | N18: =M18+K18+I18+G18+E18 -> 12839 | O18: =IF(B18>0,N18/B18,0) -> 0 | P18: 17055.611 | Q18: =(P18-P17)*1000 -> 5025 | R18: =N18-Q18 -> 7814 | S18: =S17 -> 10175 | T18: =S18-S17 -> 0 | U18: =U17 -> 429166 | V18: =U18-U17 -> 0 | W18: 32370 | X18: =W18-W17 -> 11 | Y18: 735160 | Z18: =Y18-Y17 -> 2663 | AA18: =AA17 -> 35935 | AB18: =AA18-AA17 -> 0 | AC18: =AC17 -> 960881 | AD18: =AC18-AC17 -> 0 | AE18: =AB18+X18+T18 -> 11 | AF18: =V18+Z18+AD18 -> 2663 | AG18: =IF(AE18>0,AF18/AE18,0) -> 242.09091 | AI18: =R18-'EDl log'!B16 -> -1025368 | AK18: 44332 | AL18: 296883 | AM18: 420592 | AN18: =AM18+AL18 -> 717475 | AO18: =AN18-AN17 -> 3443
A19: ='General information '!F22 -> 0 | B19: =SUM(230*A19) -> 0 | C19: 44333 | D19: =D18+AO19 -> 32867663 | E19: =D19-D18 -> 3701 | F19: 4020883 | G19: =F19-F18 -> 680 | H19: 17870454 | I19: =H19-H18 -> 836 | J19: 29050694 | K19: =J19-J18 -> 2824 | L19: 24205538 | M19: =L19-L18 -> 2048 | N19: =M19+K19+I19+G19+E19 -> 10089 | O19: =IF(B19>0,N19/B19,0) -> 0 | P19: 17065.003 | Q19: =(P19-P18)*1000 -> 9392 | R19: =N19-Q19 -> 697 | S19: =S18 -> 10175 | T19: =S19-S18 -> 0 | U19: =U18 -> 429166 | V19: =U19-U18 -> 0 | W19: 32376 | X19: =W19-W18 -> 6 | Y19: 736671 | Z19: =Y19-Y18 -> 1511 | AA19: 35939 | AB19: =AA19-AA18 -> 4 | AC19: 961645 | AD19: =AC19-AC18 -> 764 | AE19: =AB19+X19+T19 -> 10 | AF19: =V19+Z19+AD19 -> 2275 | AG19: =IF(AE19>0,AF19/AE19,0) -> 227.5 | AI19: =R19-'EDl log'!B17 -> -1034412 | AK19: 44333 | AL19: 299259 | AM19: 421917 | AN19: =AM19+AL19 -> 721176 | AO19: =AN19-AN18 -> 3701
A20: ='General information '!F23 -> 0 | B20: =SUM(230*A20) -> 0 | C20: 44334 | D20: =D19+AO20 -> 32870113 | E20: =D20-D19 -> 2450 | F20: 4021684 | G20: =F20-F19 -> 801 | H20: 17872138 | I20: =H20-H19 -> 1684 | J20: 29054174 | K20: =J20-J19 -> 3480 | L20: 24207420 | M20: =L20-L19 -> 1882 | N20: =M20+K20+I20+G20+E20 -> 10297 | O20: =IF(B20>0,N20/B20,0) -> 0 | P20: 17073.79 | Q20: =(P20-P19)*1000 -> 8787 | R20: =N20-Q20 -> 1510 | S20: =S19 -> 10175 | T20: =S20-S19 -> 0 | U20: =U19 -> 429166 | V20: =U20-U19 -> 0 | W20: 32387 | X20: =W20-W19 -> 11 | Y20: 738782 | Z20: =Y20-Y19 -> 2111 | AA20: =AA19 -> 35939 | AB20: =AA20-AA19 -> 0 | AC20: =AC19 -> 961645 | AD20: =AC20-AC19 -> 0 | AE20: =AB20+X20+T20 -> 11 | AF20: =V20+Z20+AD20 -> 2111 | AG20: =IF(AE20>0,AF20/AE20,0) -> 191.90909 | AI20: =R20-'EDl log'!B18 -> -1035295 | AK20: 44334 | AL20: 301110 | AM20: 422516 | AN20: =AM20+AL20 -> 723626 | AO20: =AN20-AN19 -> 2450
A21: ='General information '!F24 -> 0 | B21: =SUM(230*A21) -> 0 | C21: 44335 | D21: =D20+AO21 -> 32874062 | E21: =D21-D20 -> 3949 | F21: 4022730 | G21: =F21-F20 -> 1046 | H21: 17873314 | I21: =H21-H20 -> 1176 | J21: 29060818 | K21: =J21-J20 -> 6644 | L21: 24209944 | M21: =L21-L20 -> 2524 | N21: =M21+K21+I21+G21+E21 -> 15339 | O21: =IF(B21>0,N21/B21,0) -> 0 | P21: 17086.036 | Q21: =(P21-P20)*1000 -> 12246 | R21: =N21-Q21 -> 3093 | S21: =S20 -> 10175 | T21: =S21-S20 -> 0 | U21: =U20 -> 429166 | V21: =U21-U20 -> 0 | W21: 32397 | X21: =W21-W20 -> 10 | Y21: 740914 | Z21: =Y21-Y20 -> 2132 | AA21: =AA20 -> 35939 | AB21: =AA21-AA20 -> 0 | AC21: =AC20 -> 961645 | AD21: =AC21-AC20 -> 0 | AE21: =AB21+X21+T21 -> 10 | AF21: =V21+Z21+AD21 -> 2132 | AG21: =IF(AE21>0,AF21/AE21,0) -> 213.2 | AI21: =R21-'EDl log'!B19 -> -1034409 | AK21: 44335 | AL21: 304137 | AM21: 423438 | AN21: =AM21+AL21 -> 727575 | AO21: =AN21-AN20 -> 3949
A22: ='General information '!F25 -> 0 | B22: =SUM(230*A22) -> 0 | C22: 44336 | D22: =D21+AO22 -> 32876480 | E22: =D22-D21 -> 2418 | F22: 4023203 | G22: =F22-F21 -> 473 | H22: 17873896 | I22: =H22-H21 -> 582 | J22: 29064740 | K22: =J22-J21 -> 3922 | L22: 24211446 | M22: =L22-L21 -> 1502 | N22: =M22+K22+I22+G22+E22 -> 8897 | O22: =IF(B22>0,N22/B22,0) -> 0 | P22: 17093.373 | Q22: =(P22-P21)*1000 -> 7337 | R22: =N22-Q22 -> 1560 | S22: =S21 -> 10175 | T22: =S22-S21 -> 0 | U22: =U21 -> 429166 | V22: =U22-U21 -> 0 | W22: 32412 | X22: =W22-W21 -> 15 | Y22: 743939 | Z22: =Y22-Y21 -> 3025 | AA22: =AA21 -> 35939 | AB22: =AA22-AA21 -> 0 | AC22: =AC21 -> 961645 | AD22: =AC22-AC21 -> 0 | AE22: =AB22+X22+T22 -> 15 | AF22: =V22+Z22+AD22 -> 3025 | AG22: =IF(AE22>0,AF22/AE22,0) -> 201.66667 | AI22: =R22-'EDl log'!B20 -> -1038207 | AK22: 44336 | AL22: 305964 | AM22: 424029 | AN22: =AM22+AL22 -> 729993 | AO22: =AN22-AN21 -> 2418
A23: ='General information '!F26 -> 0 | B23: =SUM(230*A23) -> 0 | C23: 44337 | D23: =D22+AO23 -> 32879267 | E23: =D23-D22 -> 2787 | F23: 4023775 | G23: =F23-F22 -> 572 | H23: 17874670 | I23: =H23-H22 -> 774 | J23: 29068850 | K23: =J23-J22 -> 4110 | L23: 24213438 | M23: =L23-L22 -> 1992 | N23: =M23+K23+I23+G23+E23 -> 10235 | O23: =IF(B23>0,N23/B23,0) -> 0 | P23: 17101.325 | Q23: =(P23-P22)*1000 -> 7952 | R23: =N23-Q23 -> 2283 | S23: =S22 -> 10175 | T23: =S23-S22 -> 0 | U23: =U22 -> 429166 | V23: =U23-U22 -> 0 | W23: 32421 | X23: =W23-W22 -> 9 | Y23: 745900 | Z23: =Y23-Y22 -> 1961 | AA23: =AA22 -> 35939 | AB23: =AA23-AA22 -> 0 | AC23: =AC22 -> 961645 | AD23: =AC23-AC22 -> 0 | AE23: =AB23+X23+T23 -> 9 | AF23: =V23+Z23+AD23 -> 1961 | AG23: =IF(AE23>0,AF23/AE23,0) -> 217.88889 | AI23: =R23-'EDl log'!B21 -> -1039226 | AK23: 44337 | AL23: 308024 | AM23: 424756 | AN23: =AM23+AL23 -> 732780 | AO23: =AN23-AN22 -> 2787
A24: ='General information '!F27 -> 0 | B24: =SUM(230*A24) -> 0 | C24: 44338 | D24: =D23+AO24 -> 32882510 | E24: =D24-D23 -> 3243 | F24: 4024483 | G24: =F24-F23 -> 708 | H24: 17875516 | I24: =H24-H23 -> 846 | J24: 29074058 | K24: =J24-J23 -> 5208 | L24: 24215624 | M24: =L24-L23 -> 2186 | N24: =M24+K24+I24+G24+E24 -> 12191 | O24: =IF(B24>0,N24/B24,0) -> 0 | P24: 17111.872 | Q24: =(P24-P23)*1000 -> 10547 | R24: =N24-Q24 -> 1644 | S24: =S23 -> 10175 | T24: =S24-S23 -> 0 | U24: =U23 -> 429166 | V24: =U24-U23 -> 0 | W24: 32435 | X24: =W24-W23 -> 14 | Y24: 748409 | Z24: =Y24-Y23 -> 2509 | AA24: =AA23 -> 35939 | AB24: =AA24-AA23 -> 0 | AC24: =AC23 -> 961645 | AD24: =AC24-AC23 -> 0 | AE24: =AB24+X24+T24 -> 14 | AF24: =V24+Z24+AD24 -> 2509 | AG24: =IF(AE24>0,AF24/AE24,0) -> 179.21429 | AI24: =R24-'EDl log'!B22 -> -1041693 | AK24: 44338 | AL24: 310775 | AM24: 425248 | AN24: =AM24+AL24 -> 736023 | AO24: =AN24-AN23 -> 3243
A25: ='General information '!F28 -> 0 | B25: =SUM(230*A25) -> 0 | C25: 44339 | D25: =D24+AO25 -> 32884816 | E25: =D25-D24 -> 2306 | F25: 4025201 | G25: =F25-F24 -> 718 | H25: 17876278 | I25: =H25-H24 -> 762 | J25: 29077142 | K25: =J25-J24 -> 3084 | L25: 24217322 | M25: =L25-L24 -> 1698 | N25: =M25+K25+I25+G25+E25 -> 8568 | O25: =IF(B25>0,N25/B25,0) -> 0 | P25: 17117.407 | Q25: =(P25-P24)*1000 -> 5535 | R25: =N25-Q25 -> 3033 | S25: =S24 -> 10175 | T25: =S25-S24 -> 0 | U25: =U24 -> 429166 | V25: =U25-U24 -> 0 | W25: 32442 | X25: =W25-W24 -> 7 | Y25: 749823 | Z25: =Y25-Y24 -> 1414 | AA25: =AA24 -> 35939 | AB25: =AA25-AA24 -> 0 | AC25: =AC24 -> 961645 | AD25: =AC25-AC24 -> 0 | AE25: =AB25+X25+T25 -> 7 | AF25: =V25+Z25+AD25 -> 1414 | AG25: =IF(AE25>0,AF25/AE25,0) -> 202 | AI25: =R25-'EDl log'!B23 -> -1041224 | AK25: 44339 | AL25: 312222 | AM25: 426107 | AN25: =AM25+AL25 -> 738329 | AO25: =AN25-AN24 -> 2306
A26: ='General information '!F29 -> 0 | B26: =SUM(230*A26) -> 0 | C26: 44340 | D26: =D25+AO26 -> 32888344 | E26: =D26-D25 -> 3528 | F26: 4025963 | G26: =F26-F25 -> 762 | H26: 17877230 | I26: =H26-H25 -> 952 | J26: 29083398 | K26: =J26-J25 -> 6256 | L26: 24219552 | M26: =L26-L25 -> 2230 | N26: =M26+K26+I26+G26+E26 -> 13728 | O26: =IF(B26>0,N26/B26,0) -> 0 | P26: 17129.861 | Q26: =(P26-P25)*1000 -> 12454 | R26: =N26-Q26 -> 1274 | S26: =S25 -> 10175 | T26: =S26-S25 -> 0 | U26: =U25 -> 429166 | V26: =U26-U25 -> 0 | W26: 32458 | X26: =W26-W25 -> 16 | Y26: 752966 | Z26: =Y26-Y25 -> 3143 | AA26: =AA25 -> 35939 | AB26: =AA26-AA25 -> 0 | AC26: =AC25 -> 961645 | AD26: =AC26-AC25 -> 0 | AE26: =AB26+X26+T26 -> 16 | AF26: =V26+Z26+AD26 -> 3143 | AG26: =IF(AE26>0,AF26/AE26,0) -> 196.4375 | AI26: =R26-'EDl log'!B24 -> -1044290 | AK26: 44340 | AL26: 315305 | AM26: 426552 | AN26: =AM26+AL26 -> 741857 | AO26: =AN26-AN25 -> 3528
A27: ='General information '!F30 -> 0 | B27: =SUM(230*A27) -> 0 | C27: 44341 | D27: =D26+AO27 -> 32890826 | E27: =D27-D26 -> 2482 | F27: 4026726 | G27: =F27-F26 -> 763 | H27: 17878106 | I27: =H27-H26 -> 876 | J27: 29086978 | K27: =J27-J26 -> 3580 | L27: 24221654 | M27: =L27-L26 -> 2102 | N27: =M27+K27+I27+G27+E27 -> 9803 | O27: =IF(B27>0,N27/B27,0) -> 0 | P27: 17136.036 | Q27: =(P27-P26)*1000 -> 6175 | R27: =N27-Q27 -> 3628 | S27: =S26 -> 10175 | T27: =S27-S26 -> 0 | U27: =U26 -> 429166 | V27: =U27-U26 -> 0 | W27: 32465 | X27: =W27-W26 -> 7 | Y27: 754541 | Z27: =Y27-Y26 -> 1575 | AA27: =AA26 -> 35939 | AB27: =AA27-AA26 -> 0 | AC27: =AC26 -> 961645 | AD27: =AC27-AC26 -> 0 | AE27: =AB27+X27+T27 -> 7 | AF27: =V27+Z27+AD27 -> 1575 | AG27: =IF(AE27>0,AF27/AE27,0) -> 225 | AI27: =R27-'EDl log'!B25 -> -1042904 | AK27: 44341 | AL27: 316769 | AM27: 427570 | AN27: =AM27+AL27 -> 744339 | AO27: =AN27-AN26 -> 2482
A28: ='General information '!F31 -> 0 | B28: =SUM(230*A28) -> 0 | C28: 44342 | D28: =D27+AO28 -> 32894263 | E28: =D28-D27 -> 3437 | F28: 4027454 | G28: =F28-F27 -> 728 | H28: 17879062 | I28: =H28-H27 -> 956 | J28: 29093586 | K28: =J28-J27 -> 6608 | L28: 24224102 | M28: =L28-L27 -> 2448 | N28: =M28+K28+I28+G28+E28 -> 14177 | O28: =IF(B28>0,N28/B28,0) -> 0 | P28: 17149.122 | Q28: =(P28-P27)*1000 -> 13086 | R28: =N28-Q28 -> 1091 | S28: =S27 -> 10175 | T28: =S28-S27 -> 0 | U28: =U27 -> 429166 | V28: =U28-U27 -> 0 | W28: 32481 | X28: =W28-W27 -> 16 | Y28: 757511 | Z28: =Y28-Y27 -> 2970 | AA28: 35939 | AB28: =AA28-AA27 -> 0 | AC28: 961645 | AD28: =AC28-AC27 -> 0 | AE28: =AB28+X28+T28 -> 16 | AF28: =V28+Z28+AD28 -> 2970 | AG28: =IF(AE28>0,AF28/AE28,0) -> 185.625 | AI28: =R28-'EDl log'!B26 -> -1047128 | AK28: 44342 | AL28: 319879 | AM28: 427897 | AN28: =AM28+AL28 -> 747776 | AO28: =AN28-AN27 -> 3437
A29: ='General information '!F32 -> 0 | B29: =SUM(230*A29) -> 0 | C29: 44343 | D29: =D28+AO29 -> 32897198 | E29: =D29-D28 -> 2935 | F29: 4028246 | G29: =F29-F28 -> 792 | H29: 17879970 | I29: =H29-H28 -> 908 | J29: 29098618 | K29: =J29-J28 -> 5032 | L29: 24226262 | M29: =L29-L28 -> 2160 | N29: =M29+K29+I29+G29+E29 -> 11827 | O29: =IF(B29>0,N29/B29,0) -> 0 | P29: 17158.558 | Q29: =(P29-P28)*1000 -> 9436 | R29: =N29-Q29 -> 2391 | S29: =S28 -> 10175 | T29: =S29-S28 -> 0 | U29: =U28 -> 429166 | V29: =U29-U28 -> 0 | W29: 32492 | X29: =W29-W28 -> 11 | Y29: 760371 | Z29: =Y29-Y28 -> 2860 | AA29: =AA28 -> 35939 | AB29: =AA29-AA28 -> 0 | AC29: =AC28 -> 961645 | AD29: =AC29-AC28 -> 0 | AE29: =AB29+X29+T29 -> 11 | AF29: =V29+Z29+AD29 -> 2860 | AG29: =IF(AE29>0,AF29/AE29,0) -> 260 | AI29: =R29-'EDl log'!B27 -> -1046612 | AK29: 44343 | AL29: 322078 | AM29: 428633 | AN29: =AM29+AL29 -> 750711 | AO29: =AN29-AN28 -> 2935
A30: ='General information '!F33 -> 0 | B30: =SUM(230*A30) -> 0 | C30: 44344 | D30: =D29+AO30 -> 32897198 | E30: =D30-D29 -> 0 | F30: =F29 -> 4028246 | G30: =F30-F29 -> 0 | H30: =H29 -> 17879970 | I30: =H30-H29 -> 0 | J30: =J29 -> 29098618 | K30: =J30-J29 -> 0 | L30: =L29 -> 24226262 | M30: =L30-L29 -> 0 | N30: =M30+K30+I30+G30+E30 -> 0 | O30: =IF(B30>0,N30/B30,0) -> 0 | P30: =P29 -> 17158.558 | Q30: =(P30-P29)*1000 -> 0 | R30: =N30-Q30 -> 0 | S30: =S29 -> 10175 | T30: =S30-S29 -> 0 | U30: =U29 -> 429166 | V30: =U30-U29 -> 0 | W30: =W29 -> 32492 | X30: =W30-W29 -> 0 | Y30: =Y29 -> 760371 | Z30: =Y30-Y29 -> 0 | AA30: =AA29 -> 35939 | AB30: =AA30-AA29 -> 0 | AC30: =AC29 -> 961645 | AD30: =AC30-AC29 -> 0 | AE30: =AB30+X30+T30 -> 0 | AF30: =V30+Z30+AD30 -> 0 | AG30: =IF(AE30>0,AF30/AE30,0) -> 0 | AI30: =R30-'EDl log'!B28 -> -1050985 | AK30: 44344 | AL30: =AL29 -> 322078 | AM30: =AM29 -> 428633 | AN30: =AM30+AL30 -> 750711 | AO30: =AN30-AN29 -> 0
A31: ='General information '!F34 -> 0 | B31: =SUM(230*A31) -> 0 | C31: 44345 | D31: =D30+AO31 -> 32897198 | E31: =D31-D30 -> 0 | F31: =F30 -> 4028246 | G31: =F31-F30 -> 0 | H31: =H30 -> 17879970 | I31: =H31-H30 -> 0 | J31: =J30 -> 29098618 | K31: =J31-J30 -> 0 | L31: =L30 -> 24226262 | M31: =L31-L30 -> 0 | N31: =M31+K31+I31+G31+E31 -> 0 | O31: =IF(B31>0,N31/B31,0) -> 0 | P31: =P30 -> 17158.558 | Q31: =(P31-P30)*1000 -> 0 | R31: =N31-Q31 -> 0 | S31: =S30 -> 10175 | T31: =S31-S30 -> 0 | U31: =U30 -> 429166 | V31: =U31-U30 -> 0 | W31: =W30 -> 32492 | X31: =W31-W30 -> 0 | Y31: =Y30 -> 760371 | Z31: =Y31-Y30 -> 0 | AA31: =AA30 -> 35939 | AB31: =AA31-AA30 -> 0 | AC31: =AC30 -> 961645 | AD31: =AC31-AC30 -> 0 | AE31: =AB31+X31+T31 -> 0 | AF31: =V31+Z31+AD31 -> 0 | AG31: =IF(AE31>0,AF31/AE31,0) -> 0 | AI31: =R31-'EDl log'!B29 -> -1051724 | AK31: 44345 | AL31: =AL30 -> 322078 | AM31: =AM30 -> 428633 | AN31: =AM31+AL31 -> 750711 | AO31: =AN31-AN30 -> 0
A32: ='General information '!F35 -> 0 | B32: =SUM(230*A32) -> 0 | C32: 44346 | D32: =D31+AO32 -> 32897198 | E32: =D32-D31 -> 0 | F32: =F31 -> 4028246 | G32: =F32-F31 -> 0 | H32: =H31 -> 17879970 | I32: =H32-H31 -> 0 | J32: =J31 -> 29098618 | K32: =J32-J31 -> 0 | L32: =L31 -> 24226262 | M32: =L32-L31 -> 0 | N32: =M32+K32+I32+G32+E32 -> 0 | O32: =IF(B32>0,N32/B32,0) -> 0 | P32: =P31 -> 17158.558 | Q32: =(P32-P31)*1000 -> 0 | R32: =N32-Q32 -> 0 | S32: =S31 -> 10175 | T32: =S32-S31 -> 0 | U32: =U31 -> 429166 | V32: =U32-U31 -> 0 | W32: =W31 -> 32492 | X32: =W32-W31 -> 0 | Y32: =Y31 -> 760371 | Z32: =Y32-Y31 -> 0 | AA32: =AA31 -> 35939 | AB32: =AA32-AA31 -> 0 | AC32: =AC31 -> 961645 | AD32: =AC32-AC31 -> 0 | AE32: =AB32+X32+T32 -> 0 | AF32: =V32+Z32+AD32 -> 0 | AG32: =IF(AE32>0,AF32/AE32,0) -> 0 | AI32: =R32-'EDl log'!B30 -> -1053131 | AK32: 44346 | AL32: =AL31 -> 322078 | AM32: =AM31 -> 428633 | AN32: =AM32+AL32 -> 750711 | AO32: =AN32-AN31 -> 0
A33: ='General information '!F36 -> 0 | B33: =SUM(230*A33) -> 0 | C33: 44347 | D33: =D32+AO33 -> 32897198 | E33: =D33-D32 -> 0 | F33: =F32 -> 4028246 | G33: =F33-F32 -> 0 | H33: =H32 -> 17879970 | I33: =H33-H32 -> 0 | J33: =J32 -> 29098618 | K33: =J33-J32 -> 0 | L33: =L32 -> 24226262 | M33: =L33-L32 -> 0 | N33: =M33+K33+I33+G33+E33 -> 0 | O33: =IF(B33>0,N33/B33,0) -> 0 | P33: =P32 -> 17158.558 | Q33: =(P33-P32)*1000 -> 0 | R33: =N33-Q33 -> 0 | S33: =S32 -> 10175 | T33: =S33-S32 -> 0 | U33: =U32 -> 429166 | V33: =U33-U32 -> 0 | W33: =W32 -> 32492 | X33: =W33-W32 -> 0 | Y33: =Y32 -> 760371 | Z33: =Y33-Y32 -> 0 | AA33: =AA32 -> 35939 | AB33: =AA33-AA32 -> 0 | AC33: =AC32 -> 961645 | AD33: =AC33-AC32 -> 0 | AE33: =AB33+X33+T33 -> 0 | AF33: =V33+Z33+AD33 -> 0 | AG33: =IF(AE33>0,AF33/AE33,0) -> 0 | AI33: =R33-'EDl log'!B31 -> -1053131 | AK33: 44347 | AL33: =AL32 -> 322078 | AM33: =AM32 -> 428633 | AN33: =AM33+AL33 -> 750711 | AO33: =AN33-AN32 -> 0

Sheet B5
F1: Boiler A | J1: =J36 -> 71.615385 | K1: Boiler B | P1: Boiler C | V1: Boiler | X1: SteamA | AC1: SteamB | AH1: Steam | AI1: Boiler & steam | AL1: Total Boiler Runing H | AM1: Total Steam Runing H | AN1: GAS1 % | AO1: GAS1/L | AP1: GAS2% | AQ1: Gas2/L | AR1: GAS3% | AS1: GAS3/L | AU1: Gas Cons | AV1: Delivery | AW1: Cost/L
B2: Level Tank Gen | C2: Level tank Boiler | D2: Daily Cons Bo. | E2: Boiler litter | F2: Boiler A | G2: Run Hr a | H2: Boiler A fuel | I2: Daily consumption | J2: AVG | K2: index Run H | L2: Run Hrb | M2: Boiler B Fuel | O2: Daily consumption | P2: Boiler C | S2: Run C | U2: Total RH | V2: Total Fuel | X2: SteamA | Y2: Run SA | Z2: Steam A Conter | AA2: Liters | AC2: SteamB | AD2: Run SteamB | AE2: Steam B Conter | AF2: SB Litters | AG2: Avg | AH2: Total Fuel | AI2: Total Fuel
S3: 0
A4: =ELEC!C2 -> 44316 | B4: 239 | C4: 245 | D4: 6 | E4: 50.28 | F4: 1825 | G4: 1 | H4: 12185 | I4: 98 | J4: 98 | K4: 2315 | L4: 0 | M4: 170600 | N4: 0 | O4: 1869 | P4: 2079 | Q4: 174883 | R4: 71 | S4: 1 | T4: 0 | U4: 2 | V4: 169 | X4: 2467 | Y4: 0 | Z4: 138841 | AA4: 0 | AB4: 0 | AC4: 1936 | AD4: 0 | AE4: 365520.8 | AF4: 0 | AG4: 0 | AH4: 0 | AI4: 169 | AJ4: 169 | AK4: 0 | AL4: 2 | AM4: 0 | AN4: 67 | AO4: 2010 | AP4: 55 | AQ4: 1650 | AR4: 61 | AS4: 1830 | AT4: 5490 | AU4: 0 | AX4: =[1]B5!AX35 -> 0.8
A5: =ELEC!C3 -> 44317 | B5: 234 | C5: 240 | D5: =C4-C5 -> 5 | E5: =D5*8.38 -> 41.9 | F5: 1825 | G5: =F5-F4 -> 0 | H5: 12220 | I5: =SUM(H5-H4) -> 35 | J5: 1 | K5: 2315 | L5: =K5-K4 -> 0 | M5: 170650 | N5: =M5-M4 -> 50 | O5: =O4 -> 1869 | P5: 2080 | Q5: 174993 | R5: =Q5-Q4 -> 110 | S5: =SUM(P5-P4) -> 1 | T5: =SUM(S5*$T$2) -> 0 | U5: =SUM(G5+L5+S5) -> 1 | V5: =R5+N5+I5:I5 -> 195 | W5: =SUM(V5/U5) -> 195 | X5: =X4 -> 2467 | Y5: =X5-X4 -> 0 | Z5: =Z4 -> 138841 | AA5: =Z5-Z4 -> 0 | AB5: =SUM(Y5*$AB$2) -> 0 | AC5: =AC4 -> 1936 | AD5: =AC5-AC4 -> 0 | AE5: =AE4 -> 365520.8 | AF5: =AE5-AE4 -> 0 | AG5: =IF(AD5>0,AF5/AD5,0) -> 0 | AH5: =AF5+AA5 -> 0 | AI5: =SUM(AH5+V5) -> 195 | AJ5: =-tanks!AW6 -> 195 | AK5: =SUM(AJ5-AI5) -> 0 | AL5: =S5+L5+G5 -> 1 | AM5: =Y5+AD5 -> 0 | AN5: =AN4 -> 67 | AO5: =(AN5/100)*3000 -> 2010 | AP5: =AP4 -> 55 | AQ5: =(AP5/100)*3000 -> 1650 | AR5: =AR4 -> 61 | AS5: =(AR5/100)*3000 -> 1830 | AT5: =SUM(AO5+AQ5+AS5) -> 5490 | AU5: =AT4-AT5+AV5 -> 0 | AX5: =IF(AV5>0,AW5,AX4) -> 0.8
A6: =ELEC!C4 -> 44318 | B6: 231 | C6: 238 | D6: =C5-C6 -> 2 | E6: =D6*8.38 -> 16.76 | F6: =F5 -> 1825 | G6: =F6-F5 -> 0 | H6: =H5 -> 12220 | I6: =SUM(H6-H5) -> 0 | J6: =IF(G6>0,I6/G6,0) -> 0 | K6: 2316 | L6: =K6-K5 -> 1 | M6: 170693 | N6: =M6-M5 -> 43 | O6: =O5 -> 1869 | P6: 2081 | Q6: 175103 | R6: =Q6-Q5 -> 110 | S6: =SUM(P6-P5) -> 1 | T6: =SUM(S6*$T$2) -> 0 | U6: =SUM(G6+L6+S6) -> 2 | V6: =R6+N6+I6:I6 -> 153 | W6: =SUM(V6/U6) -> 76.5 | X6: =X5 -> 2467 | Y6: =X6-X5 -> 0 | Z6: =Z5 -> 138841 | AA6: =Z6-Z5 -> 0 | AB6: =SUM(Y6*$AB$2) -> 0 | AC6: =AC5 -> 1936 | AD6: =AC6-AC5 -> 0 | AE6: =AE5 -> 365520.8 | AF6: =AE6-AE5 -> 0 | AG6: =IF(AD6>0,AF6/AD6,0) -> 0 | AH6: =AF6+AA6 -> 0 | AI6: =SUM(AH6+V6) -> 153 | AJ6: =-tanks!AW7 -> 153 | AK6: =SUM(AJ6-AI6) -> 0 | AL6: =S6+L6+G6 -> 2 | AM6: =Y6+AD6 -> 0 | AN6: =AN5 -> 67 | AO6: =(AN6/100)*3000 -> 2010 | AP6: =AP5 -> 55 | AQ6: =(AP6/100)*3000 -> 1650 | AR6: =AR5 -> 61 | AS6: =(AR6/100)*3000 -> 1830 | AT6: =SUM(AO6+AQ6+AS6) -> 5490 | AU6: =AT5-AT6+AV6 -> 0 | AX6: =IF(AV6>0,AW6,AX5) -> 0.8
A7: =ELEC!C5 -> 44319 | B7: 228 | C7: 234 | D7: =C6-C7 -> 4 | E7: =D7*8.38 -> 33.52 | F7: 1827 | G7: =F7-F6 -> 2 | H7: 12328 | I7: =SUM(H7-H6) -> 108 | J7: =IF(G7>0,I7/G7,0) -> 54 | K7: =K6 -> 2316 | L7: =K7-K6 -> 0 | M7: =M6 -> 170693 | N7: =M7-M6 -> 0 | O7: =O6 -> 1869 | P7: 2082 | Q7: 175136 | R7: =Q7-Q6 -> 33 | S7: =SUM(P7-P6) -> 1 | T7: =SUM(S7*$T$2) -> 0 | U7: =SUM(G7+L7+S7) -> 3 | V7: =R7+N7+I7:I7 -> 141 | W7: =SUM(V7/U7) -> 47 | X7: =X6 -> 2467 | Y7: =X7-X6 -> 0 | Z7: =Z6 -> 138841 | AA7: =Z7-Z6 -> 0 | AB7: =SUM(Y7*$AB$2) -> 0 | AC7: =AC6 -> 1936 | AD7: =AC7-AC6 -> 0 | AE7: =AE6 -> 365520.8 | AF7: =AE7-AE6 -> 0 | AG7: =IF(AD7>0,AF7/AD7,0) -> 0 | AH7: =AF7+AA7 -> 0 | AI7: =SUM(AH7+V7) -> 141 | AJ7: =-tanks!AW8 -> 141 | AK7: =SUM(AJ7-AI7) -> 0 | AL7: =S7+L7+G7 -> 3 | AM7: =Y7+AD7 -> 0 | AN7: =AN6 -> 67 | AO7: =(AN7/100)*3000 -> 2010 | AP7: =AP6 -> 55 | AQ7: =(AP7/100)*3000 -> 1650 | AR7: =AR6 -> 61 | AS7: =(AR7/100)*3000 -> 1830 | AT7: =SUM(AO7+AQ7+AS7) -> 5490 | AU7: =AT6-AT7+AV7 -> 0 | AX7: =IF(AV7>0,AW7,AX6) -> 0.8
A8: =ELEC!C6 -> 44320 | B8: 222 | C8: 229 | D8: =C7-C8 -> 5 | E8: =D8*8.38 -> 41.9 | F8: =F7 -> 1827 | G8: =F8-F7 -> 0 | H8: =H7 -> 12328 | I8: =SUM(H8-H7) -> 0 | J8: =IF(G8>0,I8/G8,0) -> 0 | K8: 2317 | L8: =K8-K7 -> 1 | M8: 170788 | N8: =M8-M7 -> 95 | O8: =O7 -> 1869 | P8: =P7 -> 2082 | Q8: =Q7 -> 175136 | R8: =Q8-Q7 -> 0 | S8: =SUM(P8-P7) -> 0 | T8: =SUM(S8*$T$2) -> 0 | U8: =SUM(G8+L8+S8) -> 1 | V8: =R8+N8+I8:I8 -> 95 | W8: =SUM(V8/U8) -> 95 | X8: =X7 -> 2467 | Y8: =X8-X7 -> 0 | Z8: =Z7 -> 138841 | AA8: =Z8-Z7 -> 0 | AB8: =SUM(Y8*$AB$2) -> 0 | AC8: =AC7 -> 1936 | AD8: =AC8-AC7 -> 0 | AE8: =AE7 -> 365520.8 | AF8: =AE8-AE7 -> 0 | AG8: =IF(AD8>0,AF8/AD8,0) -> 0 | AH8: =AF8+AA8 -> 0 | AI8: =SUM(AH8+V8) -> 95 | AJ8: =-tanks!AW9 -> 95 | AK8: =SUM(AJ8-AI8) -> 0 | AL8: =S8+L8+G8 -> 1 | AM8: =Y8+AD8 -> 0 | AN8: =AN7 -> 67 | AO8: =(AN8/100)*3000 -> 2010 | AP8: =AP7 -> 55 | AQ8: =(AP8/100)*3000 -> 1650 | AR8: =AR7 -> 61 | AS8: =(AR8/100)*3000 -> 1830 | AT8: =SUM(AO8+AQ8+AS8) -> 5490 | AU8: =AT7-AT8+AV8 -> 0 | AX8: =IF(AV8>0,AW8,AX7) -> 0.8
A9: =ELEC!C7 -> 44321 | B9: 216 | C9: 222 | D9: =C8-C9 -> 7 | E9: =D9*8.38 -> 58.66 | F9: =F8 -> 1827 | G9: =F9-F8 -> 0 | H9: =H8 -> 12328 | I9: =SUM(H9-H8) -> 0 | J9: =IF(G9>0,I9/G9,0) -> 0 | K9: 2318 | L9: =K9-K8 -> 1 | M9: 170851 | N9: =M9-M8 -> 63 | O9: =O8 -> 1869 | P9: 2083 | Q9: 175237 | R9: =Q9-Q8 -> 101 | S9: =SUM(P9-P8) -> 1 | T9: =SUM(S9*$T$2) -> 0 | U9: =SUM(G9+L9+S9) -> 2 | V9: =R9+N9+I9:I9 -> 164 | W9: =SUM(V9/U9) -> 82 | X9: =X8 -> 2467 | Y9: =X9-X8 -> 0 | Z9: =Z8 -> 138841 | AA9: =Z9-Z8 -> 0 | AB9: =SUM(Y9*$AB$2) -> 0 | AC9: =AC8 -> 1936 | AD9: =AC9-AC8 -> 0 | AE9: =AE8 -> 365520.8 | AF9: =AE9-AE8 -> 0 | AG9: =IF(AD9>0,AF9/AD9,0) -> 0 | AH9: =AF9+AA9 -> 0 | AI9: =SUM(AH9+V9) -> 164 | AJ9: =-tanks!AW10 -> 164 | AK9: =SUM(AJ9-AI9) -> 0 | AL9: =S9+L9+G9 -> 2 | AM9: =Y9+AD9 -> 0 | AN9: =AN8 -> 67 | AO9: =(AN9/100)*3000 -> 2010 | AP9: =AP8 -> 55 | AQ9: =(AP9/100)*3000 -> 1650 | AR9: =AR8 -> 61 | AS9: =(AR9/100)*3000 -> 1830 | AT9: =SUM(AO9+AQ9+AS9) -> 5490 | AU9: =AT8-AT9+AV9 -> 0 | AX9: =IF(AV9>0,AW9,AX8) -> 0.8
A10: =ELEC!C8 -> 44322 | B10: 212 | C10: 219 | D10: =C9-C10 -> 3 | E10: =D10*8.38 -> 25.14 | F10: 1828 | G10: =F10-F9 -> 1 | H10: 12442 | I10: =SUM(H10-H9) -> 114 | J10: =IF(G10>0,I10/G10,0) -> 114 | K10: =K9 -> 2318 | L10: =K10-K9 -> 0 | M10: =M9 -> 170851 | N10: =M10-M9 -> 0 | O10: =O9 -> 1869 | P10: 2084 | Q10: 175278 | R10: =Q10-Q9 -> 41 | S10: =SUM(P10-P9) -> 1 | T10: =SUM(S10*$T$2) -> 0 | U10: =SUM(G10+L10+S10) -> 2 | V10: =R10+N10+I10:I10 -> 155 | W10: =SUM(V10/U10) -> 77.5 | X10: =X9 -> 2467 | Y10: =X10-X9 -> 0 | Z10: =Z9 -> 138841 | AA10: =Z10-Z9 -> 0 | AB10: =SUM(Y10*$AB$2) -> 0 | AC10: =AC9 -> 1936 | AD10: =AC10-AC9 -> 0 | AE10: =AE9 -> 365520.8 | AF10: =AE10-AE9 -> 0 | AG10: =IF(AD10>0,AF10/AD10,0) -> 0 | AH10: =AF10+AA10 -> 0 | AI10: =SUM(AH10+V10) -> 155 | AJ10: =-tanks!AW11 -> 155 | AK10: =SUM(AJ10-AI10) -> 0 | AL10: =S10+L10+G10 -> 2 | AM10: =Y10+AD10 -> 0 | AN10: =AN9 -> 67 | AO10: =(AN10/100)*3000 -> 2010 | AP10: =AP9 -> 55 | AQ10: =(AP10/100)*3000 -> 1650 | AR10: =AR9 -> 61 | AS10: =(AR10/100)*3000 -> 1830 | AT10: =SUM(AO10+AQ10+AS10) -> 5490 | AU10: =AT9-AT10+AV10 -> 0 | AX10: =IF(AV10>0,AW10,AX9) -> 0.8
A11: =ELEC!C9 -> 44323 | B11: 205 | C11: 212 | D11: =C10-C11 -> 7 | E11: =D11*8.38 -> 58.66 | F11: 1829 | G11: =F11-F10 -> 1 | H11: 12491 | I11: =SUM(H11-H10) -> 49 | J11: =IF(G11>0,I11/G11,0) -> 49 | K11: 2319 | L11: =K11-K10 -> 1 | M11: 170968 | N11: =M11-M10 -> 117 | O11: =O10 -> 1869 | P11: =P10 -> 2084 | Q11: =Q10 -> 175278 | R11: =Q11-Q10 -> 0 | S11: =SUM(P11-P10) -> 0 | T11: =SUM(S11*$T$2) -> 0 | U11: =SUM(G11+L11+S11) -> 2 | V11: =R11+N11+I11:I11 -> 166 | W11: =SUM(V11/U11) -> 83 | X11: =X10 -> 2467 | Y11: =X11-X10 -> 0 | Z11: =Z10 -> 138841 | AA11: =Z11-Z10 -> 0 | AB11: =SUM(Y11*$AB$2) -> 0 | AC11: =AC10 -> 1936 | AD11: =AC11-AC10 -> 0 | AE11: =AE10 -> 365520.8 | AF11: =AE11-AE10 -> 0 | AG11: =IF(AD11>0,AF11/AD11,0) -> 0 | AH11: =AF11+AA11 -> 0 | AI11: =SUM(AH11+V11) -> 166 | AJ11: =-tanks!AW12 -> 166 | AK11: =SUM(AJ11-AI11) -> 0 | AL11: =S11+L11+G11 -> 2 | AM11: =Y11+AD11 -> 0 | AN11: =AN10 -> 67 | AO11: =(AN11/100)*3000 -> 2010 | AP11: =AP10 -> 55 | AQ11: =(AP11/100)*3000 -> 1650 | AR11: =AR10 -> 61 | AS11: =(AR11/100)*3000 -> 1830 | AT11: =SUM(AO11+AQ11+AS11) -> 5490 | AU11: =AT10-AT11+AV11 -> 0 | AX11: =IF(AV11>0,AW11,AX10) -> 0.8
A12: =ELEC!C10 -> 44324 | B12: 198 | C12: 205 | D12: =C11-C12 -> 7 | E12: =D12*8.38 -> 58.66 | F12: =F11 -> 1829 | G12: =F12-F11 -> 0 | H12: =H11 -> 12491 | I12: =SUM(H12-H11) -> 0 | J12: =IF(G12>0,I12/G12,0) -> 0 | K12: 2320 | L12: =K12-K11 -> 1 | M12: 171004 | N12: =M12-M11 -> 36 | O12: =O11 -> 1869 | P12: 2085 | Q12: 175398 | R12: =Q12-Q11 -> 120 | S12: =SUM(P12-P11) -> 1 | T12: =SUM(S12*$T$2) -> 0 | U12: =SUM(G12+L12+S12) -> 2 | V12: =R12+N12+I12:I12 -> 156 | W12: =SUM(V12/U12) -> 78 | X12: =X11 -> 2467 | Y12: =X12-X11 -> 0 | Z12: =Z11 -> 138841 | AA12: =Z12-Z11 -> 0 | AB12: =SUM(Y12*$AB$2) -> 0 | AC12: =AC11 -> 1936 | AD12: =AC12-AC11 -> 0 | AE12: =AE11 -> 365520.8 | AF12: =AE12-AE11 -> 0 | AG12: =IF(AD12>0,AF12/AD12,0) -> 0 | AH12: =AF12+AA12 -> 0 | AI12: =SUM(AH12+V12) -> 156 | AJ12: =-tanks!AW13 -> 156 | AK12: =SUM(AJ12-AI12) -> 0 | AL12: =S12+L12+G12 -> 2 | AM12: =Y12+AD12 -> 0 | AN12: =AN11 -> 67 | AO12: =(AN12/100)*3000 -> 2010 | AP12: =AP11 -> 55 | AQ12: =(AP12/100)*3000 -> 1650 | AR12: =AR11 -> 61 | AS12: =(AR12/100)*3000 -> 1830 | AT12: =SUM(AO12+AQ12+AS12) -> 5490 | AU12: =AT11-AT12+AV12 -> 0 | AX12: =IF(AV12>0,AW12,AX11) -> 0.8
A13: =ELEC!C11 -> 44325 | B13: 192 | C13: 198 | D13: =C12-C13 -> 7 | E13: =D13*8.38 -> 58.66 | F13: 1830 | G13: =F13-F12 -> 1 | H13: 12563 | I13: =SUM(H13-H12) -> 72 | J13: =IF(G13>0,I13/G13,0) -> 72 | K13: =K12 -> 2320 | L13: =K13-K12 -> 0 | M13: =M12 -> 171004 | N13: =M13-M12 -> 0 | O13: =O12 -> 1869 | P13: 2086 | Q13: 175438 | R13: =Q13-Q12 -> 40 | S13: =SUM(P13-P12) -> 1 | T13: =SUM(S13*$T$2) -> 0 | U13: =SUM(G13+L13+S13) -> 2 | V13: =R13+N13+I13:I13 -> 112 | W13: =SUM(V13/U13) -> 56 | X13: =X12 -> 2467 | Y13: =X13-X12 -> 0 | Z13: =Z12 -> 138841 | AA13: =Z13-Z12 -> 0 | AB13: =SUM(Y13*$AB$2) -> 0 | AC13: =AC12 -> 1936 | AD13: =AC13-AC12 -> 0 | AE13: =AE12 -> 365520.8 | AF13: =AE13-AE12 -> 0 | AG13: =IF(AD13>0,AF13/AD13,0) -> 0 | AH13: =AF13+AA13 -> 0 | AI13: =SUM(AH13+V13) -> 112 | AJ13: =-tanks!AW14 -> 112 | AK13: =SUM(AJ13-AI13) -> 0 | AL13: =S13+L13+G13 -> 2 | AM13: =Y13+AD13 -> 0 | AN13: =AN12 -> 67 | AO13: =(AN13/100)*3000 -> 2010 | AP13: =AP12 -> 55 | AQ13: =(AP13/100)*3000 -> 1650 | AR13: =AR12 -> 61 | AS13: =(AR13/100)*3000 -> 1830 | AT13: =SUM(AO13+AQ13+AS13) -> 5490 | AU13: =AT12-AT13+AV13 -> 0 | AX13: =IF(AV13>0,AW13,AX12) -> 0.8
A14: =ELEC!C12 -> 44326 | B14: 184 | C14: 192 | D14: =C13-C14 -> 6 | E14: =D14*8.38 -> 50.28 | F14: =F13 -> 1830 | G14: =F14-F13 -> 0 | H14: =H13 -> 12563 | I14: =SUM(H14-H13) -> 0 | J14: =IF(G14>0,I14/G14,0) -> 0 | K14: 2321 | L14: =K14-K13 -> 1 | M14: 171086 | N14: =M14-M13 -> 82 | O14: =O13 -> 1869 | P14: =P13 -> 2086 | Q14: =Q13 -> 175438 | R14: =Q14-Q13 -> 0 | S14: =SUM(P14-P13) -> 0 | T14: =SUM(S14*$T$2) -> 0 | U14: =SUM(G14+L14+S14) -> 1 | V14: =R14+N14+I14:I14 -> 82 | W14: =SUM(V14/U14) -> 82 | X14: =X13 -> 2467 | Y14: =X14-X13 -> 0 | Z14: =Z13 -> 138841 | AA14: =Z14-Z13 -> 0 | AB14: =SUM(Y14*$AB$2) -> 0 | AC14: =AC13 -> 1936 | AD14: =AC14-AC13 -> 0 | AE14: =AE13 -> 365520.8 | AF14: =AE14-AE13 -> 0 | AG14: =IF(AD14>0,AF14/AD14,0) -> 0 | AH14: =AF14+AA14 -> 0 | AI14: =SUM(AH14+V14) -> 82 | AJ14: =-tanks!AW15 -> 82 | AK14: =SUM(AJ14-AI14) -> 0 | AL14: =S14+L14+G14 -> 1 | AM14: =Y14+AD14 -> 0 | AN14: =AN13 -> 67 | AO14: =(AN14/100)*3000 -> 2010 | AP14: =AP13 -> 55 | AQ14: =(AP14/100)*3000 -> 1650 | AR14: =AR13 -> 61 | AS14: =(AR14/100)*3000 -> 1830 | AT14: =SUM(AO14+AQ14+AS14) -> 5490 | AU14: =AT13-AT14+AV14 -> 0 | AX14: =IF(AV14>0,AW14,AX13) -> 0.8
A15: =ELEC!C13 -> 44327 | B15: 234 | C15: 241 | D15: =C14-C15 -> -49 | E15: =D15*8.38 -> -410.62 | F15: 1831 | G15: =F15-F14 -> 1 | H15: 12644 | I15: =SUM(H15-H14) -> 81 | J15: =IF(G15>0,I15/G15,0) -> 81 | K15: =K14 -> 2321 | L15: =K15-K14 -> 0 | M15: =M14 -> 171086 | N15: =M15-M14 -> 0 | O15: =O14 -> 1869 | P15: =P14 -> 2086 | Q15: =Q14 -> 175438 | R15: =Q15-Q14 -> 0 | S15: =SUM(P15-P14) -> 0 | T15: =SUM(S15*$T$2) -> 0 | U15: =SUM(G15+L15+S15) -> 1 | V15: =R15+N15+I15:I15 -> 81 | W15: =SUM(V15/U15) -> 81 | X15: =X14 -> 2467 | Y15: =X15-X14 -> 0 | Z15: 138897 | AA15: =Z15-Z14 -> 56 | AB15: =SUM(Y15*$AB$2) -> 0 | AC15: =AC14 -> 1936 | AD15: =AC15-AC14 -> 0 | AE15: =AE14 -> 365520.8 | AF15: =AE15-AE14 -> 0 | AG15: =IF(AD15>0,AF15/AD15,0) -> 0 | AH15: =AF15+AA15 -> 56 | AI15: =SUM(AH15+V15) -> 137 | AJ15: =-tanks!AW16 -> 137 | AK15: =SUM(AJ15-AI15) -> 0 | AL15: =S15+L15+G15 -> 1 | AM15: =Y15+AD15 -> 0 | AN15: =AN14 -> 67 | AO15: =(AN15/100)*3000 -> 2010 | AP15: =AP14 -> 55 | AQ15: =(AP15/100)*3000 -> 1650 | AR15: =AR14 -> 61 | AS15: =(AR15/100)*3000 -> 1830 | AT15: =SUM(AO15+AQ15+AS15) -> 5490 | AU15: =AT14-AT15+AV15 -> 0 | AX15: =IF(AV15>0,AW15,AX14) -> 0.8
A16: =ELEC!C14 -> 44328 | B16: 225 | C16: 232 | D16: =C15-C16 -> 9 | E16: =D16*8.38 -> 75.42 | F16: 1832 | G16: =F16-F15 -> 1 | H16: 12721 | I16: =SUM(H16-H15) -> 77 | J16: =IF(G16>0,I16/G16,0) -> 77 | K16: =K15 -> 2321 | L16: =K16-K15 -> 0 | M16: =M15 -> 171086 | N16: =M16-M15 -> 0 | O16: =O15 -> 1869 | P16: 2087 | Q16: 175515 | R16: =Q16-Q15 -> 77 | S16: =SUM(P16-P15) -> 1 | T16: =SUM(S16*$T$2) -> 0 | U16: =SUM(G16+L16+S16) -> 2 | V16: =R16+N16+I16:I16 -> 154 | W16: =SUM(V16/U16) -> 77 | X16: =X15 -> 2467 | Y16: =X16-X15 -> 0 | Z16: =Z15 -> 138897 | AA16: =Z16-Z15 -> 0 | AB16: =SUM(Y16*$AB$2) -> 0 | AC16: =AC15 -> 1936 | AD16: =AC16-AC15 -> 0 | AE16: =AE15 -> 365520.8 | AF16: =AE16-AE15 -> 0 | AG16: =IF(AD16>0,AF16/AD16,0) -> 0 | AH16: =AF16+AA16 -> 0 | AI16: =SUM(AH16+V16) -> 154 | AJ16: =-tanks!AW17 -> 154 | AK16: =SUM(AJ16-AI16) -> 0 | AL16: =S16+L16+G16 -> 2 | AM16: =Y16+AD16 -> 0 | AN16: =AN15 -> 67 | AO16: =(AN16/100)*3000 -> 2010 | AP16: =AP15 -> 55 | AQ16: =(AP16/100)*3000 -> 1650 | AR16: =AR15 -> 61 | AS16: =(AR16/100)*3000 -> 1830 | AT16: =SUM(AO16+AQ16+AS16) -> 5490 | AU16: =AT15-AT16+AV16 -> 0 | AX16: =IF(AV16>0,AW16,AX15) -> 0.8
A17: =ELEC!C15 -> 44329 | B17: 218 | C17: 224 | D17: =C16-C17 -> 8 | E17: =D17*8.38 -> 67.04 | F17: =F16 -> 1832 | G17: =F17-F16 -> 0 | H17: =H16 -> 12721 | I17: =SUM(H17-H16) -> 0 | J17: =IF(G17>0,I17/G17,0) -> 0 | K17: 2322 | L17: =K17-K16 -> 1 | M17: 171201 | N17: =M17-M16 -> 115 | O17: =O16 -> 1869 | P17: =P16 -> 2087 | Q17: =Q16 -> 175515 | R17: =Q17-Q16 -> 0 | S17: =SUM(P17-P16) -> 0 | T17: =SUM(S17*$T$2) -> 0 | U17: =SUM(G17+L17+S17) -> 1 | V17: =R17+N17+I17:I17 -> 115 | X17: =X16 -> 2467 | Y17: =X17-X16 -> 0 | Z17: =Z16 -> 138897 | AA17: =Z17-Z16 -> 0 | AB17: =SUM(Y17*$AB$2) -> 0 | AC17: =AC16 -> 1936 | AD17: =AC17-AC16 -> 0 | AE17: =AE16 -> 365520.8 | AF17: =AE17-AE16 -> 0 | AG17: =IF(AD17>0,AF17/AD17,0) -> 0 | AH17: =AF17+AA17 -> 0 | AI17: =SUM(AH17+V17) -> 115 | AJ17: =-tanks!AW18 -> 115 | AK17: =SUM(AJ17-AI17) -> 0 | AL17: =S17+L17+G17 -> 1 | AM17: =Y17+AD17 -> 0 | AN17: =AN16 -> 67 | AO17: =(AN17/100)*3000 -> 2010 | AP17: =AP16 -> 55 | AQ17: =(AP17/100)*3000 -> 1650 | AR17: =AR16 -> 61 | AS17: =(AR17/100)*3000 -> 1830 | AT17: =SUM(AO17+AQ17+AS17) -> 5490 | AU17: =AT16-AT17+AV17 -> 0 | AX17: =IF(AV17>0,AW17,AX16) -> 0.8
A18: =ELEC!C16 -> 44330 | B18: 212 | C18: 218 | D18: =C17-C18 -> 6 | E18: =D18*8.38 -> 50.28 | F18: =F17 -> 1832 | G18: =F18-F17 -> 0 | H18: =H17 -> 12721 | I18: =SUM(H18-H17) -> 0 | J18: =IF(G18>0,I18/G18,0) -> 0 | K18: =K17 -> 2322 | L18: =K18-K17 -> 0 | M18: =M17 -> 171201 | N18: =M18-M17 -> 0 | O18: 1869 | P18: 2088 | Q18: 175604 | R18: =Q18-Q17 -> 89 | S18: =SUM(P18-P17) -> 1 | T18: =SUM(S18*$T$2) -> 0 | U18: =SUM(G18+L18+S18) -> 1 | V18: =R18+N18+I18:I18 -> 89 | X18: =X17 -> 2467 | Y18: =X18-X17 -> 0 | Z18: =Z17 -> 138897 | AA18: =Z18-Z17 -> 0 | AB18: =SUM(Y18*$AB$2) -> 0 | AC18: =AC17 -> 1936 | AD18: =AC18-AC17 -> 0 | AE18: =AE17 -> 365520.8 | AF18: =AE18-AE17 -> 0 | AG18: =IF(AD18>0,AF18/AD18,0) -> 0 | AH18: =AF18+AA18 -> 0 | AI18: =SUM(AH18+V18) -> 89 | AJ18: =-tanks!AW19 -> 89 | AK18: =SUM(AJ18-AI18) -> 0 | AL18: =S18+L18+G18 -> 1 | AM18: =Y18+AD18 -> 0 | AN18: =AN17 -> 67 | AO18: =(AN18/100)*3000 -> 2010 | AP18: =AP17 -> 55 | AQ18: =(AP18/100)*3000 -> 1650 | AR18: =AR17 -> 61 | AS18: =(AR18/100)*3000 -> 1830 | AT18: =SUM(AO18+AQ18+AS18) -> 5490 | AU18: =AT17-AT18+AV18 -> 0 | AX18: =IF(AV18>0,AW18,AX17) -> 0.8
A19: =ELEC!C17 -> 44331 | B19: 206 | C19: 213 | D19: =C18-C19 -> 5 | E19: =D19*8.38 -> 41.9 | F19: 1833 | G19: =F19-F18 -> 1 | H19: 12810 | I19: =SUM(H19-H18) -> 89 | J19: =IF(G19>0,I19/G19,0) -> 89 | K19: =K18 -> 2322 | L19: =K19-K18 -> 0 | M19: =M18 -> 171201 | N19: =M19-M18 -> 0 | O19: =O18 -> 1869 | P19: 2089 | Q19: 175654 | R19: =Q19-Q18 -> 50 | S19: =SUM(P19-P18) -> 1 | T19: =SUM(S19*$T$2) -> 0 | U19: =SUM(G19+L19+S19) -> 2 | V19: =R19+N19+I19:I19 -> 139 | X19: =X18 -> 2467 | Y19: =X19-X18 -> 0 | Z19: =Z18 -> 138897 | AA19: =Z19-Z18 -> 0 | AB19: =SUM(Y19*$AB$2) -> 0 | AC19: =AC18 -> 1936 | AD19: =AC19-AC18 -> 0 | AE19: =AE18 -> 365520.8 | AF19: =AE19-AE18 -> 0 | AG19: =IF(AD19>0,AF19/AD19,0) -> 0 | AH19: =AF19+AA19 -> 0 | AI19: =SUM(AH19+V19) -> 139 | AJ19: =-tanks!AW20 -> 139 | AK19: =SUM(AJ19-AI19) -> 0 | AL19: =S19+L19+G19 -> 2 | AM19: =Y19+AD19 -> 0 | AN19: =AN18 -> 67 | AO19: =(AN19/100)*3000 -> 2010 | AP19: =AP18 -> 55 | AQ19: =(AP19/100)*3000 -> 1650 | AR19: =AR18 -> 61 | AS19: =(AR19/100)*3000 -> 1830 | AT19: =SUM(AO19+AQ19+AS19) -> 5490 | AU19: =AT18-AT19+AV19 -> 0 | AX19: =IF(AV19>0,AW19,AX18) -> 0.8
A20: =ELEC!C18 -> 44332 | B20: 195 | C20: 201 | D20: =C19-C20 -> 12 | E20: =D20*8.38 -> 100.56 | F20: =F19 -> 1833 | G20: =F20-F19 -> 0 | H20: 12841 | I20: =SUM(H20-H19) -> 31 | J20: =IF(G20>0,I20/G20,0) -> 0 | K20: 2323 | L20: =K20-K19 -> 1 | M20: 171285 | N20: =M20-M19 -> 84 | O20: =O19 -> 1869 | P20: =P19 -> 2089 | Q20: =Q19 -> 175654 | R20: =Q20-Q19 -> 0 | S20: =SUM(P20-P19) -> 0 | T20: =SUM(S20*$T$2) -> 0 | U20: =SUM(G20+L20+S20) -> 1 | V20: =R20+N20+I20:I20 -> 115 | X20: =X19 -> 2467 | Y20: =X20-X19 -> 0 | Z20: =Z19 -> 138897 | AA20: =Z20-Z19 -> 0 | AB20: =SUM(Y20*$AB$2) -> 0 | AC20: =AC19 -> 1936 | AD20: =AC20-AC19 -> 0 | AE20: =AE19 -> 365520.8 | AF20: =AE20-AE19 -> 0 | AG20: =IF(AD20>0,AF20/AD20,0) -> 0 | AH20: =AF20+AA20 -> 0 | AI20: =SUM(AH20+V20) -> 115 | AJ20: =-tanks!AW21 -> 115 | AK20: =SUM(AJ20-AI20) -> 0 | AL20: =S20+L20+G20 -> 1 | AM20: =Y20+AD20 -> 0 | AN20: =AN19 -> 67 | AO20: =(AN20/100)*3000 -> 2010 | AP20: =AP19 -> 55 | AQ20: =(AP20/100)*3000 -> 1650 | AR20: =AR19 -> 61 | AS20: =(AR20/100)*3000 -> 1830 | AT20: =SUM(AO20+AQ20+AS20) -> 5490 | AU20: =AT19-AT20+AV20 -> 0 | AX20: =IF(AV20>0,AW20,AX19) -> 0.8
A21: =ELEC!C19 -> 44333 | B21: 188 | C21: 194 | D21: =C20-C21 -> 7 | E21: =D21*8.38 -> 58.66 | F21: =F20 -> 1833 | G21: =F21-F20 -> 0 | H21: =H20 -> 12841 | I21: =SUM(H21-H20) -> 0 | J21: =IF(G21>0,I21/G21,0) -> 0 | K21: 2324 | L21: =K21-K20 -> 1 | M21: 171322 | N21: =M21-M20 -> 37 | O21: =O20 -> 1869 | P21: =P20 -> 2089 | Q21: 175710 | R21: =Q21-Q20 -> 56 | S21: =SUM(P21-P20) -> 0 | T21: =SUM(S21*$T$2) -> 0 | U21: =SUM(G21+L21+S21) -> 1 | V21: =R21+N21+I21:I21 -> 93 | X21: =X20 -> 2467 | Y21: =X21-X20 -> 0 | Z21: =Z20 -> 138897 | AA21: =Z21-Z20 -> 0 | AB21: =SUM(Y21*$AB$2) -> 0 | AC21: =AC20 -> 1936 | AD21: =AC21-AC20 -> 0 | AE21: =AE20 -> 365520.8 | AF21: =AE21-AE20 -> 0 | AG21: =IF(AD21>0,AF21/AD21,0) -> 0 | AH21: =AF21+AA21 -> 0 | AI21: =SUM(AH21+V21) -> 93 | AJ21: =-tanks!AW22 -> 93 | AK21: =SUM(AJ21-AI21) -> 0 | AL21: =S21+L21+G21 -> 1 | AM21: =Y21+AD21 -> 0 | AN21: =AN20 -> 67 | AO21: =(AN21/100)*3000 -> 2010 | AP21: =AP20 -> 55 | AQ21: =(AP21/100)*3000 -> 1650 | AR21: =AR20 -> 61 | AS21: =(AR21/100)*3000 -> 1830 | AT21: =SUM(AO21+AQ21+AS21) -> 5490 | AU21: =AT20-AT21+AV21 -> 0 | AX21: =IF(AV21>0,AW21,AX20) -> 0.8
A22: =ELEC!C20 -> 44334 | B22: 179 | C22: 186 | D22: =C21-C22 -> 8 | E22: =D22*8.38 -> 67.04 | F22: 1835 | G22: =F22-F21 -> 2 | H22: 12933 | I22: =SUM(H22-H21) -> 92 | J22: =IF(G22>0,I22/G22,0) -> 46 | K22: =K21 -> 2324 | L22: =K22-K21 -> 0 | M22: =M21 -> 171322 | N22: =M22-M21 -> 0 | O22: =O21 -> 1869 | P22: 2090 | Q22: 175754 | R22: =Q22-Q21 -> 44 | S22: =SUM(P22-P21) -> 1 | T22: =SUM(S22*$T$2) -> 0 | U22: =SUM(G22+L22+S22) -> 3 | V22: =R22+N22+I22:I22 -> 136 | X22: =X21 -> 2467 | Y22: =X22-X21 -> 0 | Z22: =Z21 -> 138897 | AA22: =Z22-Z21 -> 0 | AB22: =SUM(Y22*$AB$2) -> 0 | AC22: =AC21 -> 1936 | AD22: =AC22-AC21 -> 0 | AE22: =AE21 -> 365520.8 | AF22: =AE22-AE21 -> 0 | AG22: =IF(AD22>0,AF22/AD22,0) -> 0 | AH22: =AF22+AA22 -> 0 | AI22: =SUM(AH22+V22) -> 136 | AJ22: =-tanks!AW23 -> 136 | AK22: =SUM(AJ22-AI22) -> 0 | AL22: =S22+L22+G22 -> 3 | AM22: =Y22+AD22 -> 0 | AN22: =AN21 -> 67 | AO22: =(AN22/100)*3000 -> 2010 | AP22: =AP21 -> 55 | AQ22: =(AP22/100)*3000 -> 1650 | AR22: =AR21 -> 61 | AS22: =(AR22/100)*3000 -> 1830 | AT22: =SUM(AO22+AQ22+AS22) -> 5490 | AU22: =AT21-AT22+AV22 -> 0 | AX22: =IF(AV22>0,AW22,AX21) -> 0.8
A23: =ELEC!C21 -> 44335 | B23: 170 | C23: 178 | D23: =C22-C23 -> 8 | E23: =D23*8.38 -> 67.04 | F23: =F22 -> 1835 | G23: =F23-F22 -> 0 | H23: =H22 -> 12933 | I23: =SUM(H23-H22) -> 0 | J23: =IF(G23>0,I23/G23,0) -> 0 | K23: 2325 | L23: =K23-K22 -> 1 | M23: 171417 | N23: =M23-M22 -> 95 | O23: =O22 -> 1869 | P23: =P22 -> 2090 | Q23: =Q22 -> 175754 | R23: =Q23-Q22 -> 0 | S23: =SUM(P23-P22) -> 0 | T23: =SUM(S23*$T$2) -> 0 | U23: =SUM(G23+L23+S23) -> 1 | V23: =R23+N23+I23:I23 -> 95 | X23: =X22 -> 2467 | Y23: =X23-X22 -> 0 | Z23: =Z22 -> 138897 | AA23: =Z23-Z22 -> 0 | AB23: =SUM(Y23*$AB$2) -> 0 | AC23: =AC22 -> 1936 | AD23: =AC23-AC22 -> 0 | AE23: =AE22 -> 365520.8 | AF23: =AE23-AE22 -> 0 | AG23: =IF(AD23>0,AF23/AD23,0) -> 0 | AH23: =AF23+AA23 -> 0 | AI23: =SUM(AH23+V23) -> 95 | AJ23: =-tanks!AW24 -> 95 | AK23: =SUM(AJ23-AI23) -> 0 | AL23: =S23+L23+G23 -> 1 | AM23: =Y23+AD23 -> 0 | AN23: =AN22 -> 67 | AO23: =(AN23/100)*3000 -> 2010 | AP23: =AP22 -> 55 | AQ23: =(AP23/100)*3000 -> 1650 | AR23: =AR22 -> 61 | AS23: =(AR23/100)*3000 -> 1830 | AT23: =SUM(AO23+AQ23+AS23) -> 5490 | AU23: =AT22-AT23+AV23 -> 0 | AX23: =IF(AV23>0,AW23,AX22) -> 0.8
A24: =ELEC!C22 -> 44336 | B24: 203 | C24: 210 | D24: =C23-C24 -> -32 | E24: =D24*8.38 -> -268.16 | F24: =F23 -> 1835 | G24: =F24-F23 -> 0 | H24: =H23 -> 12933 | I24: =SUM(H24-H23) -> 0 | J24: =IF(G24>0,I24/G24,0) -> 0 | K24: =K23 -> 2325 | L24: =K24-K23 -> 0 | M24: =M23 -> 171417 | N24: =M24-M23 -> 0 | O24: =O23 -> 1869 | P24: 2091 | Q24: 175817 | R24: =Q24-Q23 -> 63 | S24: =SUM(P24-P23) -> 1 | T24: =SUM(S24*$T$2) -> 0 | U24: =SUM(G24+L24+S24) -> 1 | V24: =R24+N24+I24:I24 -> 63 | X24: =X23 -> 2467 | Y24: =X24-X23 -> 0 | Z24: =Z23 -> 138897 | AA24: =Z24-Z23 -> 0 | AB24: =SUM(Y24*$AB$2) -> 0 | AC24: =AC23 -> 1936 | AD24: =AC24-AC23 -> 0 | AE24: =AE23 -> 365520.8 | AF24: =AE24-AE23 -> 0 | AG24: =IF(AD24>0,AF24/AD24,0) -> 0 | AH24: =AF24+AA24 -> 0 | AI24: =SUM(AH24+V24) -> 63 | AJ24: =-tanks!AW25 -> 63 | AK24: =SUM(AJ24-AI24) -> 0 | AL24: =S24+L24+G24 -> 1 | AM24: =Y24+AD24 -> 0 | AN24: =AN23 -> 67 | AO24: =(AN24/100)*3000 -> 2010 | AP24: =AP23 -> 55 | AQ24: =(AP24/100)*3000 -> 1650 | AR24: =AR23 -> 61 | AS24: =(AR24/100)*3000 -> 1830 | AT24: =SUM(AO24+AQ24+AS24) -> 5490 | AU24: =AT23-AT24+AV24 -> 0 | AX24: =IF(AV24>0,AW24,AX23) -> 0.8
A25: =ELEC!C23 -> 44337 | B25: 194 | C25: 201 | D25: =C24-C25 -> 9 | E25: =D25*8.38 -> 75.42 | F25: 1836 | G25: =F25-F24 -> 1 | H25: 13065 | I25: =SUM(H25-H24) -> 132 | J25: =IF(G25>0,I25/G25,0) -> 132 | K25: =K24 -> 2325 | L25: =K25-K24 -> 0 | M25: 171439 | N25: =M25-M24 -> 22 | O25: =O24 -> 1869 | P25: =P24 -> 2091 | Q25: 175849 | R25: =Q25-Q24 -> 32 | S25: =SUM(P25-P24) -> 0 | T25: =SUM(S25*$T$2) -> 0 | U25: =SUM(G25+L25+S25) -> 1 | V25: =R25+N25+I25:I25 -> 186 | X25: 2468 | Y25: =X25-X24 -> 1 | Z25: 138920 | AA25: =Z25-Z24 -> 23 | AB25: =SUM(Y25*$AB$2) -> 0 | AC25: =AC24 -> 1936 | AD25: =AC25-AC24 -> 0 | AE25: =AE24 -> 365520.8 | AF25: =AE25-AE24 -> 0 | AG25: =IF(AD25>0,AF25/AD25,0) -> 0 | AH25: =AF25+AA25 -> 23 | AI25: =SUM(AH25+V25) -> 209 | AJ25: =-tanks!AW26 -> 209 | AK25: =SUM(AJ25-AI25) -> 0 | AL25: =S25+L25+G25 -> 1 | AM25: =Y25+AD25 -> 1 | AN25: =AN24 -> 67 | AO25: =(AN25/100)*3000 -> 2010 | AP25: =AP24 -> 55 | AQ25: =(AP25/100)*3000 -> 1650 | AR25: =AR24 -> 61 | AS25: =(AR25/100)*3000 -> 1830 | AT25: =SUM(AO25+AQ25+AS25) -> 5490 | AU25: =AT24-AT25+AV25 -> 0 | AX25: =IF(AV25>0,AW25,AX24) -> 0.8
A26: =ELEC!C24 -> 44338 | B26: 182 | C26: 189 | D26: =C25-C26 -> 12 | E26: =D26*8.38 -> 100.56 | F26: 1837 | G26: =F26-F25 -> 1 | H26: 13110 | I26: =SUM(H26-H25) -> 45 | J26: =IF(G26>0,I26/G26,0) -> 45 | K26: 2326 | L26: =K26-K25 -> 1 | M26: 171523 | N26: =M26-M25 -> 84 | O26: =O25 -> 1869 | P26: =P25 -> 2091 | Q26: =Q25 -> 175849 | R26: =Q26-Q25 -> 0 | S26: =SUM(P26-P25) -> 0 | T26: =SUM(S26*$T$2) -> 0 | U26: =SUM(G26+L26+S26) -> 2 | V26: =R26+N26+I26:I26 -> 129 | X26: 2468 | Y26: =X26-X25 -> 0 | Z26: 138920 | AA26: =Z26-Z25 -> 0 | AB26: =SUM(Y26*$AB$2) -> 0 | AC26: =AC25 -> 1936 | AD26: =AC26-AC25 -> 0 | AE26: =AE25 -> 365520.8 | AF26: =AE26-AE25 -> 0 | AG26: =IF(AD26>0,AF26/AD26,0) -> 0 | AH26: =AF26+AA26 -> 0 | AI26: =SUM(AH26+V26) -> 129 | AJ26: =-tanks!AW27 -> 129 | AK26: =SUM(AJ26-AI26) -> 0 | AL26: =S26+L26+G26 -> 2 | AM26: =Y26+AD26 -> 0 | AN26: =AN25 -> 67 | AO26: =(AN26/100)*3000 -> 2010 | AP26: =AP25 -> 55 | AQ26: =(AP26/100)*3000 -> 1650 | AR26: =AR25 -> 61 | AS26: =(AR26/100)*3000 -> 1830 | AT26: =SUM(AO26+AQ26+AS26) -> 5490 | AU26: =AT25-AT26+AV26 -> 0 | AX26: =IF(AV26>0,AW26,AX25) -> 0.8
A27: =ELEC!C25 -> 44339 | B27: 176 | C27: 182.5 | D27: =C26-C27 -> 6.5 | E27: =D27*8.38 -> 54.47 | F27: =F26 -> 1837 | G27: =F27-F26 -> 0 | H27: =H26 -> 13110 | I27: =SUM(H27-H26) -> 0 | J27: =IF(G27>0,I27/G27,0) -> 0 | K27: =K26 -> 2326 | L27: =K27-K26 -> 0 | M27: =M26 -> 171523 | N27: =M27-M26 -> 0 | O27: =O26 -> 1869 | P27: 2092 | Q27: 175918 | R27: =Q27-Q26 -> 69 | S27: =SUM(P27-P26) -> 1 | T27: =SUM(S27*$T$2) -> 0 | U27: =SUM(G27+L27+S27) -> 1 | V27: =R27+N27+I27:I27 -> 69 | X27: =X26 -> 2468 | Y27: =X27-X26 -> 0 | Z27: =Z26 -> 138920 | AA27: =Z27-Z26 -> 0 | AB27: =SUM(Y27*$AB$2) -> 0 | AC27: =AC26 -> 1936 | AD27: =AC27-AC26 -> 0 | AE27: =AE26 -> 365520.8 | AF27: =AE27-AE26 -> 0 | AG27: =IF(AD27>0,AF27/AD27,0) -> 0 | AH27: =AF27+AA27 -> 0 | AI27: =SUM(AH27+V27) -> 69 | AJ27: =-tanks!AW28 -> 69 | AK27: =SUM(AJ27-AI27) -> 0 | AL27: =S27+L27+G27 -> 1 | AM27: =Y27+AD27 -> 0 | AN27: =AN26 -> 67 | AO27: =(AN27/100)*3000 -> 2010 | AP27: =AP26 -> 55 | AQ27: =(AP27/100)*3000 -> 1650 | AR27: =AR26 -> 61 | AS27: =(AR27/100)*3000 -> 1830 | AT27: =SUM(AO27+AQ27+AS27) -> 5490 | AU27: =AT26-AT27+AV27 -> 0 | AX27: =IF(AV27>0,AW27,AX26) -> 0.8
A28: =ELEC!C26 -> 44340 | B28: 208 | C28: 215 | D28: =C27-C28 -> -32.5 | E28: =D28*8.38 -> -272.35 | F28: 1838 | G28: =F28-F27 -> 1 | H28: 13198 | I28: =SUM(H28-H27) -> 88 | J28: =IF(G28>0,I28/G28,0) -> 88 | K28: =K27 -> 2326 | L28: =K28-K27 -> 0 | M28: =M27 -> 171523 | N28: =M28-M27 -> 0 | O28: =O27 -> 1869 | P28: =P27 -> 2092 | Q28: =Q27 -> 175918 | R28: =Q28-Q27 -> 0 | S28: =SUM(P28-P27) -> 0 | T28: =SUM(S28*$T$2) -> 0 | U28: =SUM(G28+L28+S28) -> 1 | V28: =R28+N28+I28:I28 -> 88 | X28: 2469 | Y28: =X28-X27 -> 1 | Z28: 138993 | AA28: =Z28-Z27 -> 73 | AB28: =SUM(Y28*$AB$2) -> 0 | AC28: 1936 | AD28: =AC28-AC27 -> 0 | AE28: 365571 | AF28: =AE28-AE27 -> 50.2 | AG28: =IF(AD28>0,AF28/AD28,0) -> 0 | AH28: =AF28+AA28 -> 123.2 | AI28: =SUM(AH28+V28) -> 211.2 | AJ28: =-tanks!AW29 -> 211.2 | AK28: =SUM(AJ28-AI28) -> 0 | AL28: =S28+L28+G28 -> 1 | AM28: =Y28+AD28 -> 1 | AN28: =AN27 -> 67 | AO28: =(AN28/100)*3000 -> 2010 | AP28: =AP27 -> 55 | AQ28: =(AP28/100)*3000 -> 1650 | AR28: =AR27 -> 61 | AS28: =(AR28/100)*3000 -> 1830 | AT28: =SUM(AO28+AQ28+AS28) -> 5490 | AU28: =AT27-AT28+AV28 -> 0 | AX28: =IF(AV28>0,AW28,AX27) -> 0.8
A29: =ELEC!C27 -> 44341 | B29: 201 | C29: 208 | D29: =C28-C29 -> 7 | E29: =D29*8.38 -> 58.66 | F29: =F28 -> 1838 | G29: =F29-F28 -> 0 | H29: =H28 -> 13198 | I29: =SUM(H29-H28) -> 0 | J29: =IF(G29>0,I29/G29,0) -> 0 | K29: 2327 | L29: =K29-K28 -> 1 | M29: 171613 | N29: =M29-M28 -> 90 | O29: =O28 -> 1869 | P29: =P28 -> 2092 | Q29: =Q28 -> 175918 | R29: =Q29-Q28 -> 0 | S29: =SUM(P29-P28) -> 0 | T29: =SUM(S29*$T$2) -> 0 | U29: =SUM(G29+L29+S29) -> 1 | V29: =R29+N29+I29:I29 -> 90 | X29: =X28 -> 2469 | Y29: =X29-X28 -> 0 | Z29: =Z28 -> 138993 | AA29: =Z29-Z28 -> 0 | AB29: =SUM(Y29*$AB$2) -> 0 | AC29: =AC28 -> 1936 | AD29: =AC29-AC28 -> 0 | AE29: =AE28 -> 365571 | AF29: =AE29-AE28 -> 0 | AG29: =IF(AD29>0,AF29/AD29,0) -> 0 | AH29: =AF29+AA29 -> 0 | AI29: =SUM(AH29+V29) -> 90 | AJ29: =-tanks!AW30 -> 90 | AK29: =SUM(AJ29-AI29) -> 0 | AL29: =S29+L29+G29 -> 1 | AM29: =Y29+AD29 -> 0 | AN29: =AN28 -> 67 | AO29: =(AN29/100)*3000 -> 2010 | AP29: =AP28 -> 55 | AQ29: =(AP29/100)*3000 -> 1650 | AR29: =AR28 -> 61 | AS29: =(AR29/100)*3000 -> 1830 | AT29: =SUM(AO29+AQ29+AS29) -> 5490 | AU29: =AT28-AT29+AV29 -> 0 | AX29: =IF(AV29>0,AW29,AX28) -> 0.8
A30: =ELEC!C28 -> 44342 | B30: 187 | C30: 194 | D30: =C29-C30 -> 14 | E30: =D30*8.38 -> 117.32 | F30: =F29 -> 1838 | G30: =F30-F29 -> 0 | H30: =H29 -> 13198 | I30: =SUM(H30-H29) -> 0 | J30: =IF(G30>0,I30/G30,0) -> 0 | K30: =K29 -> 2327 | L30: =K30-K29 -> 0 | M30: =M29 -> 171613 | N30: =M30-M29 -> 0 | O30: =O29 -> 1869 | P30: 2093 | Q30: 176032 | R30: =Q30-Q29 -> 114 | S30: =SUM(P30-P29) -> 1 | T30: =SUM(S30*$T$2) -> 0 | U30: =SUM(G30+L30+S30) -> 1 | V30: =R30+N30+I30:I30 -> 114 | X30: =X29 -> 2469 | Y30: =X30-X29 -> 0 | Z30: =Z29 -> 138993 | AA30: =Z30-Z29 -> 0 | AB30: =SUM(Y30*$AB$2) -> 0 | AC30: =AC29 -> 1936 | AD30: =AC30-AC29 -> 0 | AE30: =AE29 -> 365571 | AF30: =AE30-AE29 -> 0 | AG30: =IF(AD30>0,AF30/AD30,0) -> 0 | AH30: =AF30+AA30 -> 0 | AI30: =SUM(AH30+V30) -> 114 | AJ30: =-tanks!AW31 -> 114 | AK30: =SUM(AJ30-AI30) -> 0 | AL30: =S30+L30+G30 -> 1 | AM30: =Y30+AD30 -> 0 | AN30: =AN29 -> 67 | AO30: =(AN30/100)*3000 -> 2010 | AP30: =AP29 -> 55 | AQ30: =(AP30/100)*3000 -> 1650 | AR30: =AR29 -> 61 | AS30: =(AR30/100)*3000 -> 1830 | AT30: =SUM(AO30+AQ30+AS30) -> 5490 | AU30: =AT29-AT30+AV30 -> 0 | AX30: =IF(AV30>0,AW30,AX29) -> 0.8
A31: =ELEC!C29 -> 44343 | B31: 177 | C31: 184 | D31: =C30-C31 -> 10 | E31: =D31*8.38 -> 83.8 | F31: 1839 | G31: =F31-F30 -> 1 | H31: 13281 | I31: =SUM(H31-H30) -> 83 | J31: =IF(G31>0,I31/G31,0) -> 83 | K31: =K30 -> 2327 | L31: =K31-K30 -> 0 | M31: =M30 -> 171613 | N31: =M31-M30 -> 0 | O31: =O30 -> 1869 | P31: 2094 | Q31: 176055 | R31: =Q31-Q30 -> 23 | S31: =SUM(P31-P30) -> 1 | T31: =SUM(S31*$T$2) -> 0 | U31: =SUM(G31+L31+S31) -> 2 | V31: =R31+N31+I31:I31 -> 106 | X31: =X30 -> 2469 | Y31: =X31-X30 -> 0 | Z31: =Z30 -> 138993 | AA31: =Z31-Z30 -> 0 | AB31: =SUM(Y31*$AB$2) -> 0 | AC31: =AC30 -> 1936 | AD31: =AC31-AC30 -> 0 | AE31: =AE30 -> 365571 | AF31: =AE31-AE30 -> 0 | AG31: =IF(AD31>0,AF31/AD31,0) -> 0 | AH31: =AF31+AA31 -> 0 | AI31: =SUM(AH31+V31) -> 106 | AJ31: =-tanks!AW32 -> 106 | AK31: =SUM(AJ31-AI31) -> 0 | AL31: =S31+L31+G31 -> 2 | AM31: =Y31+AD31 -> 0 | AN31: =AN30 -> 67 | AO31: =(AN31/100)*3000 -> 2010 | AP31: =AP30 -> 55 | AQ31: =(AP31/100)*3000 -> 1650 | AR31: =AR30 -> 61 | AS31: =(AR31/100)*3000 -> 1830 | AT31: =SUM(AO31+AQ31+AS31) -> 5490 | AU31: =AT30-AT31+AV31 -> 0 | AX31: =IF(AV31>0,AW31,AX30) -> 0.8
A32: =ELEC!C30 -> 44344 | B32: =B31 -> 177 | C32: =C31 -> 184 | D32: =C31-C32 -> 0 | E32: =D32*8.38 -> 0 | F32: =F31 -> 1839 | G32: =F32-F31 -> 0 | H32: =H31 -> 13281 | I32: =SUM(H32-H31) -> 0 | J32: =IF(G32>0,I32/G32,0) -> 0 | K32: =K31 -> 2327 | L32: =K32-K31 -> 0 | M32: =M31 -> 171613 | N32: =M32-M31 -> 0 | O32: =O31 -> 1869 | P32: =P31 -> 2094 | Q32: =Q31 -> 176055 | R32: =Q32-Q31 -> 0 | S32: =SUM(P32-P31) -> 0 | T32: =SUM(S32*$T$2) -> 0 | U32: =SUM(G32+L32+S32) -> 0 | V32: =R32+N32+I32:I32 -> 0 | X32: =X31 -> 2469 | Y32: =X32-X31 -> 0 | Z32: =Z31 -> 138993 | AA32: =Z32-Z31 -> 0 | AB32: =SUM(Y32*$AB$2) -> 0 | AC32: =AC31 -> 1936 | AD32: =AC32-AC31 -> 0 | AE32: =AE31 -> 365571 | AF32: =AE32-AE31 -> 0 | AG32: =IF(AD32>0,AF32/AD32,0) -> 0 | AH32: =AF32+AA32 -> 0 | AI32: =SUM(AH32+V32) -> 0 | AJ32: =-tanks!AW33 -> 0 | AK32: =SUM(AJ32-AI32) -> 0 | AL32: =S32+L32+G32 -> 0 | AM32: =Y32+AD32 -> 0 | AN32: =AN31 -> 67 | AO32: =(AN32/100)*3000 -> 2010 | AP32: =AP31 -> 55 | AQ32: =(AP32/100)*3000 -> 1650 | AR32: =AR31 -> 61 | AS32: =(AR32/100)*3000 -> 1830 | AT32: =SUM(AO32+AQ32+AS32) -> 5490 | AU32: =AT31-AT32+AV32 -> 0 | AX32: =IF(AV32>0,AW32,AX31) -> 0.8
A33: =ELEC!C31 -> 44345 | B33: =B32 -> 177 | C33: =C32 -> 184 | D33: =C32-C33 -> 0 | E33: =D33*8.38 -> 0 | F33: =F32 -> 1839 | G33: =F33-F32 -> 0 | H33: =H32 -> 13281 | I33: =SUM(H33-H32) -> 0 | J33: =IF(G33>0,I33/G33,0) -> 0 | K33: =K32 -> 2327 | L33: =K33-K32 -> 0 | M33: =M32 -> 171613 | N33: =M33-M32 -> 0 | O33: =O32 -> 1869 | P33: =P32 -> 2094 | Q33: =Q32 -> 176055 | R33: =Q33-Q32 -> 0 | S33: =SUM(P33-P32) -> 0 | T33: =SUM(S33*$T$2) -> 0 | U33: =SUM(G33+L33+S33) -> 0 | V33: =R33+N33+I33:I33 -> 0 | X33: =X32 -> 2469 | Y33: =X33-X32 -> 0 | Z33: =Z32 -> 138993 | AA33: =Z33-Z32 -> 0 | AB33: =SUM(Y33*$AB$2) -> 0 | AC33: =AC32 -> 1936 | AD33: =AC33-AC32 -> 0 | AE33: =AE32 -> 365571 | AF33: =AE33-AE32 -> 0 | AG33: =IF(AD33>0,AF33/AD33,0) -> 0 | AH33: =AF33+AA33 -> 0 | AI33: =SUM(AH33+V33) -> 0 | AJ33: =-tanks!AW34 -> 0 | AK33: =SUM(AJ33-AI33) -> 0 | AL33: =S33+L33+G33 -> 0 | AM33: =Y33+AD33 -> 0 | AN33: =AN32 -> 67 | AO33: =(AN33/100)*3000 -> 2010 | AP33: =AP32 -> 55 | AQ33: =(AP33/100)*3000 -> 1650 | AR33: =AR32 -> 61 | AS33: =(AR33/100)*3000 -> 1830 | AT33: =SUM(AO33+AQ33+AS33) -> 5490 | AU33: =AT32-AT33+AV33 -> 0 | AX33: =IF(AV33>0,AW33,AX32) -> 0.8
A34: =ELEC!C32 -> 44346 | B34: =B33 -> 177 | C34: =C33 -> 184 | D34: =C33-C34 -> 0 | E34: =D34*8.38 -> 0 | F34: =F33 -> 1839 | G34: =F34-F33 -> 0 | H34: =H33 -> 13281 | I34: =SUM(H34-H33) -> 0 | J34: =IF(G34>0,I34/G34,0) -> 0 | K34: =K33 -> 2327 | L34: =K34-K33 -> 0 | M34: =M33 -> 171613 | N34: =M34-M33 -> 0 | O34: =O33 -> 1869 | P34: =P33 -> 2094 | Q34: =Q33 -> 176055 | R34: =Q34-Q33 -> 0 | S34: =SUM(P34-P33) -> 0 | T34: =SUM(S34*$T$2) -> 0 | U34: =SUM(G34+L34+S34) -> 0 | V34: =R34+N34+I34:I34 -> 0 | X34: =X33 -> 2469 | Y34: =X34-X33 -> 0 | Z34: =Z33 -> 138993 | AA34: =Z34-Z33 -> 0 | AB34: =SUM(Y34*$AB$2) -> 0 | AC34: =AC33 -> 1936 | AD34: =AC34-AC33 -> 0 | AE34: =AE33 -> 365571 | AF34: =AE34-AE33 -> 0 | AG34: =IF(AD34>0,AF34/AD34,0) -> 0 | AH34: =AF34+AA34 -> 0 | AI34: =SUM(AH34+V34) -> 0 | AJ34: =-tanks!AW35 -> 0 | AK34: =SUM(AJ34-AI34) -> 0 | AL34: =S34+L34+G34 -> 0 | AM34: =Y34+AD34 -> 0 | AN34: =AN33 -> 67 | AO34: =(AN34/100)*3000 -> 2010 | AP34: =AP33 -> 55 | AQ34: =(AP34/100)*3000 -> 1650 | AR34: =AR33 -> 61 | AS34: =(AR34/100)*3000 -> 1830 | AT34: =SUM(AO34+AQ34+AS34) -> 5490 | AU34: =AT33-AT34+AV34 -> 0 | AX34: =IF(AV34>0,AW34,AX33) -> 0.8
A35: =ELEC!C33 -> 44347 | B35: =B34 -> 177 | C35: =C34 -> 184 | D35: =C34-C35 -> 0 | E35: =D35*8.38 -> 0 | F35: =F34 -> 1839 | G35: =F35-F34 -> 0 | H35: =H34 -> 13281 | I35: =SUM(H35-H34) -> 0 | J35: =IF(G35>0,I35/G35,0) -> 0 | K35: =K34 -> 2327 | L35: =K35-K34 -> 0 | M35: =M34 -> 171613 | N35: =M35-M34 -> 0 | O35: =O34 -> 1869 | P35: =P34 -> 2094 | Q35: =Q34 -> 176055 | R35: =Q35-Q34 -> 0 | S35: =SUM(P35-P34) -> 0 | T35: =SUM(S35*$T$2) -> 0 | U35: =SUM(G35+L35+S35) -> 0 | V35: =R35+N35+I35:I35 -> 0 | X35: =X34 -> 2469 | Y35: =X35-X34 -> 0 | Z35: =Z34 -> 138993 | AA35: =Z35-Z34 -> 0 | AB35: =SUM(Y35*$AB$2) -> 0 | AC35: =AC34 -> 1936 | AD35: =AC35-AC34 -> 0 | AE35: =AE34 -> 365571 | AF35: =AE35-AE34 -> 0 | AG35: =IF(AD35>0,AF35/AD35,0) -> 0 | AH35: =AF35+AA35 -> 0 | AI35: =SUM(AH35+V35) -> 0 | AJ35: =-tanks!AW37 -> 0 | AK35: =SUM(AJ35-AI35) -> 0 | AL35: =S35+L35+G35 -> 0 | AM35: =Y35+AD35 -> 0 | AN35: =AN34 -> 67 | AO35: =(AN35/100)*3000 -> 2010 | AP35: =AP34 -> 55 | AQ35: =(AP35/100)*3000 -> 1650 | AR35: =AR34 -> 61 | AS35: =(AR35/100)*3000 -> 1830 | AT35: =SUM(AO35+AQ35+AS35) -> 5490 | AU35: =AT34-AT35+AV35 -> 0 | AX35: =IF(AV35>0,AW35,AX34) -> 0.8
J36: =SUM(J5:J32)/(COUNT(J5:J32)-COUNTIF(J5:J32,0)) -> 71.615385 | V36: =SUM(V5:V32) -> 3281 | AE36: . | AH36: =SUM(AH5:AH32) -> 202.2 | AL36: =SUM(AL5:AL32) -> 41 | AM36: =SUM(AM5:AM32) -> 2 | AR36: Nb Delivery | AS36: =COUNT(AW5:AW32) -> 0 | AU36: =SUM(AU5:AU32) -> 0 | AV36: =SUM(AV5:AV32) -> 0 | AW36: =SUM(AW5:AW32)/AS36 -> #DIV/0!
AH37: =AF37+AA37 -> 0 | AI37: =SUM(AI5:AI32) -> 3483.2
AH38: =AF38+AA38 -> 0 | AU38: =AU36*0.51 -> 0 | AV38: =AV36/0.51 -> 0 | AW38: =SUM(AW5:AW32)/AS36 -> #DIV/0!
AV39: =AV36*0.51 -> 0

Sheet WATER
D1: =SUM(G21:G33) -> 8057178 | AR1: Entrance | AT1: Tank 1 | AV1: Tank 2
AR2: Level | AW2: Quantity CM3 | AZ2: Var
A3: Date | B3: Truck | C3: Truck M3/day | D3: N0. Trucks | F3: REQ. # of trucks | G3: City | H3: City/day | I3: Total water delivery | K3: SW | L3: Cosum SW/day | M3: RO Guest/ Liter | O3: RO K&L/ Liter | Q3: TOTAL RO Production | R3: RO 1 RH | S3: RO 2 RH | T3: RO water counter | U3: RO Cons m3 | V3: Steam Boiler | W3: Steam Boiler/day | X3: Softener Guest | Y3: Guest Sotf/day | Z3: Softener K&L | AA3: K&L Soft/Day | AB3: Fire Tank Level | AC3: Fire Tank Counter | AE3: Laundry Hot Water Counter | AF3: Hot Water Cons/day | AG3: Laundry Cold Water Counter | AH3: Cold Water Cons/day | AI3: Laundry Water Total Cons | AJ3: K&L Sotf/day | AK3: Guest / day | AL3: K&L /day | AM3: Avg Outside Temp | AN3: Banquet Activity | AR3: Date | AT3: MainI | AV3: Kitchen and Laundry | AX3: Guest | AY3: Main Tank | AZ3: Kitchen and Laundry | BA3: Guest | BB3: Kitchen and Laundry | BC3: Main | BD3: Guest | BE3: Total VAR | BF3: Hotel Consumption
E4: 1.66 | AN4: Ball R | AO4: Meeting | AP4: outlet | AT4: 180 | AV4: 220 | AX4: 580 | AY4: =SUM(AT4) -> 180 | AZ4: =SUM(AV4) -> 220 | BA4: =SUM(AX4) -> 580
A5: 44346 | B5: 109443 | C5: 0 | D5: 0 | E5: 250 | G5: 618491 | H5: 0 | I5: 0 | J5: 0 | K5: 6751 | L5: 0 | M5: 457.44 | N5: 0 | O5: 529.52 | P5: 0 | Q5: 0 | T5: 5171 | U5: 0 | V5: 470 | W5: 0 | X5: 151413 | Y5: 0 | Z5: 98768 | AA5: 0 | AB5: 261 | AC5: 731 | AD5: 0 | AE5: 229.78 | AF5: 0 | AG5: 2205.62 | AH5: 0 | AI5: 0 | AJ5: 0 | AK5: 0 | AL5: 0 | AM5: 23 | AN5: 0 | AP5: 0 | AR5: 44346 | AS5: 0.9 | AT5: 80 | AU5: 1.1 | AV5: 150 | AW5: 2.9 | AX5: 141 | AY5: 72 | AZ5: 165 | BA5: 408.9 | BB5: -9 | BC5: -2.2 | BD5: -11.6 | BE5: -22.8 | BF5: 22.8 | BG5: -22.8
A6: =ELEC!C3 -> 44317 | B6: =B5 -> 109443 | C6: =B6-B5 -> 0 | D6: =C6/27 -> 0 | E6: =SUM((C6*$E$4)+(7500/'EDl log'!$A$37)) -> 241.93548 | G6: 618498 | H6: =G6-G5 -> 7 | I6: =C6+H6 -> 7 | J6: =IF(I6>0,E6/I6,0) -> 34.562212 | K6: ='Swimming Pool quality check '!H6 -> 6751 | L6: 0 | M6: =M5 -> 457.44 | N6: =SUM(M6-M5) -> 0 | O6: =O5 -> 529.52 | P6: =SUM(O6-O5) -> 0 | Q6: =P6+N6 -> 0 | T6: =T5 -> 5171 | U6: =SUM(T6-T5) -> 0 | V6: =V5 -> 470 | W6: =+V6-V5 -> 0 | X6: 151413 | Y6: =SUM(X6-X5) -> 0 | Z6: =Z5 -> 98768 | AA6: =Z6-Z5 -> 0 | AB6: =AB5 -> 261 | AC6: =AC5 -> 731 | AD6: 0 | AE6: =AE5 -> 229.78 | AF6: =AE6-AE5 -> 0 | AG6: =AG5 -> 2205.62 | AH6: =AG6-AG5 -> 0 | AI6: =AF6+AH6 -> 0 | AJ6: =+Z6-Z5 -> 0 | AK6: =SUM(Y6-L6) -> 0 | AL6: =SUM(AJ6-W6) -> 0 | AM6: ='General information '!D6 -> 23.5 | AN6: ='General information '!H6 -> 0 | AP6: ='General information '!J6 -> 0 | AR6: =A6 -> 44317 | AS6: =AS5 -> 0.9 | AT6: 81 | AU6: =AU5 -> 1.1 | AV6: 148 | AW6: 2.9 | AX6: 139 | AY6: =AS6*AT6 -> 72.9 | AZ6: =AU6*AV6 -> 162.8 | BA6: =AW6*AX6 -> 403.1 | BB6: =AY6-AY5 -> 0.9 | BC6: =AZ6-AZ5 -> -2.2 | BD6: =BA6-BA5 -> -5.8 | BE6: =SUM(BB6:BD6) -> -7.1 | BF6: =SUM(I6-BE6) -> 14.1 | BG6: =SUM(I6-BF6) -> -7.1
A7: =ELEC!C4 -> 44318 | B7: =B6 -> 109443 | C7: =B7-B6 -> 0 | D7: =C7/27 -> 0 | E7: =SUM((C7*$E$4)+(7500/'EDl log'!$A$37)) -> 241.93548 | G7: =G6 -> 618498 | H7: =G7-G6 -> 0 | I7: =C7+H7 -> 0 | J7: =IF(I7>0,E7/I7,0) -> 0 | K7: ='Swimming Pool quality check '!H7 -> 6754 | L7: =K7-K6 -> 3 | M7: =M6 -> 457.44 | N7: =SUM(M7-M6) -> 0 | O7: =O6 -> 529.52 | P7: =SUM(O7-O6) -> 0 | Q7: =P7+N7 -> 0 | T7: =T6 -> 5171 | U7: =SUM(T7-T6) -> 0 | V7: =V6 -> 470 | W7: =+V7-V6 -> 0 | X7: =X6 -> 151413 | Y7: =SUM(X7-X6) -> 0 | Z7: =Z6 -> 98768 | AA7: =Z7-Z6 -> 0 | AB7: =AB6 -> 261 | AC7: =AC6 -> 731 | AD7: =AC7-AC6 -> 0 | AE7: =AE6 -> 229.78 | AF7: =AE7-AE6 -> 0 | AG7: =AG6 -> 2205.62 | AH7: =AG7-AG6 -> 0 | AI7: =AF7+AH7 -> 0 | AJ7: =+Z7-Z6 -> 0 | AK7: =SUM(Y7-L7) -> -3 | AL7: =SUM(AJ7-W7) -> 0 | AM7: ='General information '!D7 -> 23 | AN7: ='General information '!H7 -> 0 | AP7: ='General information '!J7 -> 0 | AR7: =A7 -> 44318 | AS7: =AS6 -> 0.9 | AT7: 82 | AU7: =AU6 -> 1.1 | AV7: 146 | AW7: 2.9 | AX7: 138 | AY7: =AS7*AT7 -> 73.8 | AZ7: =AU7*AV7 -> 160.6 | BA7: =AW7*AX7 -> 400.2 | BB7: =AY7-AY6 -> 0.9 | BC7: =AZ7-AZ6 -> -2.2 | BD7: =BA7-BA6 -> -2.9 | BE7: =SUM(BB7:BD7) -> -4.2 | BF7: =SUM(I7-BE7) -> 4.2 | BG7: =SUM(I7-BF7) -> -4.2
A8: =ELEC!C5 -> 44319 | B8: =B7 -> 109443 | C8: =B8-B7 -> 0 | D8: =C8/27 -> 0 | E8: =SUM((C8*$E$4)+(7500/'EDl log'!$A$37)) -> 241.93548 | G8: 618787 | H8: =G8-G7 -> 289 | I8: =C8+H8 -> 289 | J8: =IF(I8>0,E8/I8,0) -> 0.837147 | K8: ='Swimming Pool quality check '!H8 -> 6754 | L8: =K8-K7 -> 0 | M8: =M7 -> 457.44 | N8: =SUM(M8-M7) -> 0 | O8: =O7 -> 529.52 | P8: =SUM(O8-O7) -> 0 | Q8: =P8+N8 -> 0 | T8: =T7 -> 5171 | U8: =SUM(T8-T7) -> 0 | V8: =V7 -> 470 | W8: =+V8-V7 -> 0 | X8: 151495 | Y8: =SUM(X8-X7) -> 82 | Z8: 98804 | AA8: =Z8-Z7 -> 36 | AB8: =AB7 -> 261 | AC8: =AC7 -> 731 | AD8: =AC8-AC7 -> 0 | AE8: =AE7 -> 229.78 | AF8: =AE8-AE7 -> 0 | AG8: =AG7 -> 2205.62 | AH8: =AG8-AG7 -> 0 | AI8: =AF8+AH8 -> 0 | AJ8: =+Z8-Z7 -> 36 | AK8: =SUM(Y8-L8) -> 82 | AL8: =SUM(AJ8-W8) -> 36 | AM8: ='General information '!D8 -> 24 | AN8: ='General information '!H8 -> 0 | AP8: ='General information '!J8 -> 0 | AR8: =A8 -> 44319 | AS8: =AS7 -> 0.9 | AT8: 99 | AU8: 1.1 | AV8: 170 | AW8: 2.9 | AX8: 158 | AY8: =AS8*AT8 -> 89.1 | AZ8: =AU8*AV8 -> 187 | BA8: =AW8*AX8 -> 458.2 | BB8: =AY8-AY7 -> 15.3 | BC8: =AZ8-AZ7 -> 26.4 | BD8: =BA8-BA7 -> 58 | BE8: =SUM(BB8:BD8) -> 99.7 | BF8: =SUM(I8-BE8) -> 189.3 | BG8: =SUM(I8-BF8) -> 99.7
A9: =ELEC!C6 -> 44320 | B9: =B8 -> 109443 | C9: =B9-B8 -> 0 | D9: =C9/27 -> 0 | E9: =SUM((C9*$E$4)+(7500/'EDl log'!$A$37)) -> 241.93548 | G9: =G8 -> 618787 | H9: =G9-G8 -> 0 | I9: =C9+H9 -> 0 | J9: =IF(I9>0,E9/I9,0) -> 0 | K9: ='Swimming Pool quality check '!H9 -> 6754 | L9: =K9-K8 -> 0 | M9: =M8 -> 457.44 | N9: =SUM(M9-M8) -> 0 | O9: =O8 -> 529.52 | P9: =SUM(O9-O8) -> 0 | Q9: =P9+N9 -> 0 | T9: =T8 -> 5171 | U9: =SUM(T9-T8) -> 0 | V9: 471 | W9: =+V9-V8 -> 1 | X9: 151496 | Y9: =SUM(X9-X8) -> 1 | Z9: 98804 | AA9: =Z9-Z8 -> 0 | AB9: =AB8 -> 261 | AC9: =AC8 -> 731 | AD9: =AC9-AC8 -> 0 | AE9: =AE8 -> 229.78 | AF9: =AE9-AE8 -> 0 | AG9: =AG8 -> 2205.62 | AH9: =AG9-AG8 -> 0 | AI9: =AF9+AH9 -> 0 | AJ9: =+Z9-Z8 -> 0 | AK9: =SUM(Y9-L9) -> 1 | AL9: =SUM(AJ9-W9) -> -1 | AM9: ='General information '!D9 -> 22.5 | AN9: ='General information '!H9 -> 0 | AP9: ='General information '!J9 -> 0 | AR9: =A9 -> 44320 | AS9: =AS8 -> 0.9 | AT9: 82 | AU9: =AU8 -> 1.1 | AV9: 169 | AW9: 2.9 | AX9: 154 | AY9: =AS9*AT9 -> 73.8 | AZ9: =AU9*AV9 -> 185.9 | BA9: =AW9*AX9 -> 446.6 | BB9: =AY9-AY8 -> -15.3 | BC9: =AZ9-AZ8 -> -1.1 | BD9: =BA9-BA8 -> -11.6 | BE9: =SUM(BB9:BD9) -> -28 | BF9: =SUM(I9-BE9) -> 28 | BG9: =SUM(I9-BF9) -> -28
A10: =ELEC!C7 -> 44321 | B10: =B9 -> 109443 | C10: =B10-B9 -> 0 | D10: =C10/27 -> 0 | E10: =SUM((C10*$E$4)+(7500/'EDl log'!$A$37)) -> 241.93548 | G10: 619082 | H10: =G10-G9 -> 295 | I10: =C10+H10 -> 295 | J10: =IF(I10>0,E10/I10,0) -> 0.82012028 | K10: ='Swimming Pool quality check '!H10 -> 6754 | L10: =K10-K9 -> 0 | M10: =M9 -> 457.44 | N10: =SUM(M10-M9) -> 0 | O10: =O9 -> 529.52 | P10: =SUM(O10-O9) -> 0 | Q10: =P10+N10 -> 0 | T10: =T9 -> 5171 | U10: =SUM(T10-T9) -> 0 | V10: =V9 -> 471 | W10: =+V10-V9 -> 0 | X10: 151601 | Y10: =SUM(X10-X9) -> 105 | Z10: =Z9 -> 98804 | AA10: =Z10-Z9 -> 0 | AB10: =AB9 -> 261 | AC10: =AC9 -> 731 | AD10: =AC10-AC9 -> 0 | AE10: =AE9 -> 229.78 | AF10: =AE10-AE9 -> 0 | AG10: =AG9 -> 2205.62 | AH10: =AG10-AG9 -> 0 | AI10: =AF10+AH10 -> 0 | AJ10: =+Z10-Z9 -> 0 | AK10: =SUM(Y10-L10) -> 105 | AL10: =SUM(AJ10-W10) -> 0 | AM10: ='General information '!D10 -> 23 | AN10: ='General information '!H10 -> 0 | AP10: ='General information '!J10 -> 0 | AR10: =A10 -> 44321 | AS10: =AS9 -> 0.9 | AT10: 104 | AU10: =AU9 -> 1.1 | AV10: 167 | AW10: 2.9 | AX10: 177 | AY10: =AS10*AT10 -> 93.6 | AZ10: =AU10*AV10 -> 183.7 | BA10: =AW10*AX10 -> 513.3 | BB10: =AY10-AY9 -> 19.8 | BC10: =AZ10-AZ9 -> -2.2 | BD10: =BA10-BA9 -> 66.7 | BE10: =SUM(BB10:BD10) -> 84.3 | BF10: =SUM(I10-BE10) -> 210.7 | BG10: =SUM(I10-BF10) -> 84.3
A11: =ELEC!C8 -> 44322 | B11: =B10 -> 109443 | C11: =B11-B10 -> 0 | D11: =C11/27 -> 0 | E11: =SUM((C11*$E$4)+(7500/'EDl log'!$A$37)) -> 241.93548 | G11: =G10 -> 619082 | H11: =G11-G10 -> 0 | I11: =C11+H11 -> 0 | J11: =IF(I11>0,E11/I11,0) -> 0 | K11: ='Swimming Pool quality check '!H11 -> 6760 | L11: =K11-K10 -> 6 | M11: =M10 -> 457.44 | N11: =SUM(M11-M10) -> 0 | O11: =O10 -> 529.52 | P11: =SUM(O11-O10) -> 0 | Q11: =SUM(P11+N11) -> 0 | T11: =T10 -> 5171 | U11: =SUM(T11-T10) -> 0 | V11: =V10 -> 471 | W11: =+V11-V10 -> 0 | X11: =X10 -> 151601 | Y11: =SUM(X11-X10) -> 0 | Z11: =Z10 -> 98804 | AA11: =Z11-Z10 -> 0 | AB11: =AB10 -> 261 | AC11: =AC10 -> 731 | AD11: =AC11-AC10 -> 0 | AE11: =AE10 -> 229.78 | AF11: =AE11-AE10 -> 0 | AG11: =AG10 -> 2205.62 | AH11: =AG11-AG10 -> 0 | AI11: =AF11+AH11 -> 0 | AJ11: =+Z11-Z10 -> 0 | AK11: =SUM(Y11-L11) -> -6 | AL11: =SUM(AJ11-W11) -> 0 | AM11: ='General information '!D11 -> 22 | AN11: ='General information '!H11 -> 0 | AP11: ='General information '!J11 -> 0 | AR11: =A11 -> 44322 | AS11: =AS10 -> 0.9 | AT11: =AT10 -> 104 | AU11: =AU10 -> 1.1 | AV11: 165 | AW11: 2.9 | AX11: 176 | AY11: =AS11*AT11 -> 93.6 | AZ11: =AU11*AV11 -> 181.5 | BA11: =AW11*AX11 -> 510.4 | BB11: =AY11-AY10 -> 0 | BC11: =AZ11-AZ10 -> -2.2 | BD11: =BA11-BA10 -> -2.9 | BE11: =SUM(BB11:BD11) -> -5.1 | BF11: =SUM(I11-BE11) -> 5.1 | BG11: =SUM(I11-BF11) -> -5.1
A12: =ELEC!C9 -> 44323 | B12: =B11 -> 109443 | C12: =B12-B11 -> 0 | D12: =C12/27 -> 0 | E12: =SUM((C12*$E$4)+(7500/'EDl log'!$A$37)) -> 241.93548 | G12: 619375 | H12: =G12-G11 -> 293 | I12: =C12+H12 -> 293 | J12: =IF(I12>0,E12/I12,0) -> 0.82571837 | K12: ='Swimming Pool quality check '!H12 -> 6760 | L12: =K12-K11 -> 0 | M12: =M11 -> 457.44 | N12: =SUM(M12-M11) -> 0 | O12: =O11 -> 529.52 | P12: =SUM(O12-O11) -> 0 | Q12: =SUM(P12+N12) -> 0 | T12: =T11 -> 5171 | U12: =SUM(T12-T11) -> 0 | V12: =V11 -> 471 | W12: =+V12-V11 -> 0 | X12: 151746 | Y12: =SUM(X12-X11) -> 145 | Z12: =Z11 -> 98804 | AA12: =Z12-Z11 -> 0 | AB12: =AB11 -> 261 | AC12: =AC11 -> 731 | AD12: =AC12-AC11 -> 0 | AE12: =AE11 -> 229.78 | AF12: =AE12-AE11 -> 0 | AG12: =AG11 -> 2205.62 | AH12: =AG12-AG11 -> 0 | AI12: =AF12+AH12 -> 0 | AJ12: =+Z12-Z11 -> 0 | AK12: =SUM(Y12-L12) -> 145 | AL12: =SUM(AJ12-W12) -> 0 | AM12: ='General information '!D12 -> 23 | AN12: ='General information '!H12 -> 0 | AP12: ='General information '!J12 -> 0 | AR12: =A12 -> 44323 | AS12: =AS11 -> 0.9 | AT12: 86 | AU12: =AU11 -> 1.1 | AV12: 163 | AW12: 2.9 | AX12: 201 | AY12: =AS12*AT12 -> 77.4 | AZ12: =AU12*AV12 -> 179.3 | BA12: =AW12*AX12 -> 582.9 | BB12: =AY12-AY11 -> -16.2 | BC12: =AZ12-AZ11 -> -2.2 | BD12: =BA12-BA11 -> 72.5 | BE12: =SUM(BB12:BD12) -> 54.1 | BF12: =SUM(I12-BE12) -> 238.9 | BG12: =SUM(I12-BF12) -> 54.1
A13: =ELEC!C10 -> 44324 | B13: =B12 -> 109443 | C13: =B13-B12 -> 0 | D13: =C13/27 -> 0 | E13: =SUM((C13*$E$4)+(7500/'EDl log'!$A$37)) -> 241.93548 | G13: =G12 -> 619375 | H13: =G13-G12 -> 0 | I13: =C13+H13 -> 0 | J13: =IF(I13>0,E13/I13,0) -> 0 | K13: ='Swimming Pool quality check '!H13 -> 6760 | L13: =K13-K12 -> 0 | M13: =M12 -> 457.44 | N13: =SUM(M13-M12) -> 0 | O13: =O12 -> 529.52 | P13: =SUM(O13-O12) -> 0 | Q13: =SUM(P13+N13) -> 0 | T13: =T12 -> 5171 | U13: =SUM(T13-T12) -> 0 | V13: =V12 -> 471 | W13: =+V13-V12 -> 0 | X13: =X12 -> 151746 | Y13: =SUM(X13-X12) -> 0 | Z13: 98836 | AA13: =Z13-Z12 -> 32 | AB13: =AB12 -> 261 | AC13: =AC12 -> 731 | AD13: =AC13-AC12 -> 0 | AE13: =AE12 -> 229.78 | AF13: =AE13-AE12 -> 0 | AG13: =AG12 -> 2205.62 | AH13: =AG13-AG12 -> 0 | AI13: =AF13+AH13 -> 0 | AJ13: =+Z13-Z12 -> 32 | AK13: =SUM(Y13-L13) -> 0 | AL13: =SUM(AJ13-W13) -> 32 | AM13: ='General information '!D13 -> 24.5 | AN13: ='General information '!J13 -> 0 | AP13: ='General information '!J13 -> 0 | AR13: =A13 -> 44324 | AS13: =AS12 -> 0.9 | AT13: 58 | AU13: =AU12 -> 1.1 | AV13: 182 | AW13: 2.9 | AX13: 190 | AY13: =AS13*AT13 -> 52.2 | AZ13: =AU13*AV13 -> 200.2 | BA13: =AW13*AX13 -> 551 | BB13: =AY13-AY12 -> -25.2 | BC13: =AZ13-AZ12 -> 20.9 | BD13: =BA13-BA12 -> -31.9 | BE13: =SUM(BB13:BD13) -> -36.2 | BF13: =SUM(I13-BE13) -> 36.2 | BG13: =SUM(I13-BF13) -> -36.2
A14: =ELEC!C11 -> 44325 | B14: =B13 -> 109443 | C14: =B14-B13 -> 0 | D14: =C14/27 -> 0 | E14: =SUM((C14*$E$4)+(7500/'EDl log'!$A$37)) -> 241.93548 | G14: =G13 -> 619375 | H14: =G14-G13 -> 0 | I14: =C14+H14 -> 0 | J14: =IF(I14>0,E14/I14,0) -> 0 | K14: ='Swimming Pool quality check '!H14 -> 6762 | L14: =K14-K13 -> 2 | M14: =M13 -> 457.44 | N14: =SUM(M14-M13) -> 0 | O14: =O13 -> 529.52 | P14: =SUM(O14-O13) -> 0 | Q14: =SUM(P14+N14) -> 0 | T14: =T13 -> 5171 | U14: =SUM(T14-T13) -> 0 | V14: =V13 -> 471 | W14: =+V14-V13 -> 0 | X14: 151772 | Y14: =SUM(X14-X13) -> 26 | Z14: 98847 | AA14: =Z14-Z13 -> 11 | AB14: =AB13 -> 261 | AC14: =AC13 -> 731 | AD14: =AC14-AC13 -> 0 | AE14: =AE13 -> 229.78 | AF14: =AE14-AE13 -> 0 | AG14: =AG13 -> 2205.62 | AH14: =AG14-AG13 -> 0 | AI14: =AF14+AH14 -> 0 | AJ14: =+Z14-Z13 -> 11 | AK14: =SUM(Y14-L14) -> 24 | AL14: =SUM(AJ14-W14) -> 11 | AM14: ='General information '!D14 -> 24.5 | AN14: ='General information '!H14 -> 0 | AP14: ='General information '!J14 -> 0 | AR14: =A14 -> 44325 | AS14: =AS13 -> 0.9 | AT14: 164 | AU14: =AU13 -> 1.1 | AV14: 189 | AW14: 2.9 | AX14: 187 | AY14: =AS14*AT14 -> 147.6 | AZ14: =AU14*AV14 -> 207.9 | BA14: =AW14*AX14 -> 542.3 | BB14: =AY14-AY13 -> 95.4 | BC14: =AZ14-AZ13 -> 7.7 | BD14: =BA14-BA13 -> -8.7 | BE14: =SUM(BB14:BD14) -> 94.4 | BF14: =SUM(I14-BE14) -> -94.4 | BG14: =SUM(I14-BF14) -> 94.4
A15: =ELEC!C12 -> 44326 | B15: =B14 -> 109443 | C15: =B15-B14 -> 0 | D15: =C15/27 -> 0 | E15: =SUM((C15*$E$4)+(7500/'EDl log'!$A$37)) -> 241.93548 | G15: =G14 -> 619375 | H15: =G15-G14 -> 0 | I15: =C15+H15 -> 0 | J15: =IF(I15>0,E15/I15,0) -> 0 | K15: ='Swimming Pool quality check '!H15 -> 6762 | L15: =K15-K14 -> 0 | M15: =M14 -> 457.44 | N15: =SUM(M15-M14) -> 0 | O15: =O14 -> 529.52 | P15: =SUM(O15-O14) -> 0 | Q15: =SUM(P15+N15) -> 0 | T15: =T14 -> 5171 | U15: =SUM(T15-T14) -> 0 | V15: =V14 -> 471 | W15: =+V15-V14 -> 0 | X15: =X14 -> 151772 | Y15: =SUM(X15-X14) -> 0 | Z15: =Z14 -> 98847 | AA15: =Z15-Z14 -> 0 | AB15: =AB14 -> 261 | AC15: =AC14 -> 731 | AD15: =AC15-AC14 -> 0 | AE15: =AE14 -> 229.78 | AF15: =AE15-AE14 -> 0 | AG15: =AG14 -> 2205.62 | AH15: =AG15-AG14 -> 0 | AI15: =AF15+AH15 -> 0 | AJ15: =+Z15-Z14 -> 0 | AK15: =SUM(Y15-L15) -> 0 | AL15: =SUM(AJ15-W15) -> 0 | AM15: ='General information '!D15 -> 22 | AN15: ='General information '!H15 -> 0 | AP15: ='General information '!J15 -> 0 | AR15: =A15 -> 44326 | AS15: =AS14 -> 0.9 | AT15: 169 | AU15: =AU14 -> 1.1 | AV15: 188 | AW15: 2.9 | AX15: 181 | AY15: =AS15*AT15 -> 152.1 | AZ15: =AU15*AV15 -> 206.8 | BA15: =AW15*AX15 -> 524.9 | BB15: =AY15-AY14 -> 4.5 | BC15: =AZ15-AZ14 -> -1.1 | BD15: =BA15-BA14 -> -17.4 | BE15: =SUM(BB15:BD15) -> -14 | BF15: =SUM(I15-BE15) -> 14 | BG15: =SUM(I15-BF15) -> -14
A16: =ELEC!C13 -> 44327 | B16: =B15 -> 109443 | C16: =B16-B15 -> 0 | D16: =C16/27 -> 0 | E16: =SUM((C16*$E$4)+(7500/'EDl log'!$A$37)) -> 241.93548 | G16: =G15 -> 619375 | H16: =G16-G15 -> 0 | I16: =C16+H16 -> 0 | J16: =IF(I16>0,E16/I16,0) -> 0 | K16: ='Swimming Pool quality check '!H16 -> 6762 | L16: =K16-K15 -> 0 | M16: =M15 -> 457.44 | N16: =SUM(M16-M15) -> 0 | O16: =O15 -> 529.52 | P16: =SUM(O16-O15) -> 0 | Q16: =SUM(P16+N16) -> 0 | T16: =T15 -> 5171 | U16: =SUM(T16-T15) -> 0 | V16: =V15 -> 471 | W16: =+V16-V15 -> 0 | X16: =X15 -> 151772 | Y16: =SUM(X16-X15) -> 0 | Z16: =Z15 -> 98847 | AA16: =Z16-Z15 -> 0 | AB16: =AB15 -> 261 | AC16: =AC15 -> 731 | AD16: =AC16-AC15 -> 0 | AE16: =AE15 -> 229.78 | AF16: =AE16-AE15 -> 0 | AG16: =AG15 -> 2205.62 | AH16: =AG16-AG15 -> 0 | AI16: =AF16+AH16 -> 0 | AJ16: =+Z16-Z15 -> 0 | AK16: =SUM(Y16-L16) -> 0 | AL16: =SUM(AJ16-W16) -> 0 | AM16: ='General information '!D16 -> 21 | AN16: ='General information '!H16 -> 0 | AP16: ='General information '!J16 -> 0 | AR16: =A16 -> 44327 | AS16: =AS15 -> 0.9 | AT16: 133 | AU16: =AU15 -> 1.1 | AV16: 185 | AW16: 2.9 | AX16: 177 | AY16: =AS16*AT16 -> 119.7 | AZ16: =AU16*AV16 -> 203.5 | BA16: =AW16*AX16 -> 513.3 | BB16: =AY16-AY15 -> -32.4 | BC16: =AZ16-AZ15 -> -3.3 | BD16: =BA16-BA15 -> -11.6 | BE16: =SUM(BB16:BD16) -> -47.3 | BF16: =SUM(I16-BE16) -> 47.3 | BG16: =SUM(I16-BF16) -> -47.3
A17: =ELEC!C14 -> 44328 | B17: =B16 -> 109443 | C17: =B17-B16 -> 0 | D17: =C17/27 -> 0 | E17: =SUM((C17*$E$4)+(7500/'EDl log'!$A$37)) -> 241.93548 | G17: =G16 -> 619375 | H17: =G17-G16 -> 0 | I17: =C17+H17 -> 0 | J17: =IF(I17>0,E17/I17,0) -> 0 | K17: ='Swimming Pool quality check '!H17 -> 6762 | L17: =K17-K16 -> 0 | M17: =M16 -> 457.44 | N17: =SUM(M17-M16) -> 0 | O17: =O16 -> 529.52 | P17: =SUM(O17-O16) -> 0 | Q17: =SUM(P17+N17) -> 0 | T17: =T16 -> 5171 | U17: =SUM(T17-T16) -> 0 | V17: =V16 -> 471 | W17: =+V17-V16 -> 0 | X17: =X16 -> 151772 | Y17: =SUM(X17-X16) -> 0 | Z17: =Z16 -> 98847 | AA17: =Z17-Z16 -> 0 | AB17: =AB16 -> 261 | AC17: =AC16 -> 731 | AD17: =AC17-AC16 -> 0 | AE17: =AE16 -> 229.78 | AF17: =AE17-AE16 -> 0 | AG17: =AG16 -> 2205.62 | AH17: =AG17-AG16 -> 0 | AI17: =AF17+AH17 -> 0 | AJ17: =+Z17-Z16 -> 0 | AK17: =SUM(Y17-L17) -> 0 | AL17: =SUM(AJ17-W17) -> 0 | AM17: ='General information '!D17 -> 22 | AN17: ='General information '!H17 -> 0 | AP17: ='General information '!J17 -> 0 | AR17: =A17 -> 44328 | AS17: =AS16 -> 0.9 | AT17: =AT16 -> 133 | AU17: =AU16 -> 1.1 | AV17: 184 | AW17: 2.9 | AX17: 172 | AY17: =AS17*AT17 -> 119.7 | AZ17: =AU17*AV17 -> 202.4 | BA17: =AW17*AX17 -> 498.8 | BB17: =AY17-AY16 -> 0 | BC17: =AZ17-AZ16 -> -1.1 | BD17: =BA17-BA16 -> -14.5 | BE17: =SUM(BB17:BD17) -> -15.6 | BF17: =SUM(I17-BE17) -> 15.6 | BG17: =SUM(I17-BF17) -> -15.6
A18: =ELEC!C15 -> 44329 | B18: =B17 -> 109443 | C18: =B18-B17 -> 0 | D18: =C18/27 -> 0 | E18: =SUM((C18*$E$4)+(7500/'EDl log'!$A$37)) -> 241.93548 | G18: 619716 | H18: =G18-G17 -> 341 | I18: =C18+H18 -> 341 | J18: =IF(I18>0,E18/I18,0) -> 0.70948822 | K18: ='Swimming Pool quality check '!H18 -> 6762 | L18: =K18-K17 -> 0 | M18: =M17 -> 457.44 | N18: =SUM(M18-M17) -> 0 | O18: =O17 -> 529.52 | P18: =SUM(O18-O17) -> 0 | Q18: =SUM(P18+N18) -> 0 | T18: =T17 -> 5171 | U18: =SUM(T18-T17) -> 0 | V18: =V17 -> 471 | W18: =+V18-V17 -> 0 | X18: =X17 -> 151772 | Y18: =SUM(X18-X17) -> 0 | Z18: =Z17 -> 98847 | AA18: =Z18-Z17 -> 0 | AB18: =AB17 -> 261 | AC18: =AC17 -> 731 | AD18: =AC18-AC17 -> 0 | AE18: =AE17 -> 229.78 | AF18: =AE18-AE17 -> 0 | AG18: =AG17 -> 2205.62 | AH18: =AG18-AG17 -> 0 | AI18: =AF18+AH18 -> 0 | AJ18: =+Z18-Z17 -> 0 | AK18: =SUM(Y18-L18) -> 0 | AL18: =SUM(AJ18-W18) -> 0 | AM18: ='General information '!D18 -> 21 | AN18: ='General information '!H18 -> 0 | AP18: ='General information '!J18 -> 0 | AR18: =A18 -> 44329 | AS18: =AS17 -> 0.9 | AT18: =AT17 -> 133 | AU18: =AU17 -> 1.1 | AV18: 184 | AW18: 2.9 | AX18: 161 | AY18: =AS18*AT18 -> 119.7 | AZ18: =AU18*AV18 -> 202.4 | BA18: =AW18*AX18 -> 466.9 | BB18: =AY18-AY17 -> 0 | BC18: =AZ18-AZ17 -> 0 | BD18: =BA18-BA17 -> -31.9 | BE18: =SUM(BB18:BD18) -> -31.9 | BF18: =SUM(I18-BE18) -> 372.9 | BG18: =SUM(I18-BF18) -> -31.9
A19: =ELEC!C16 -> 44330 | B19: =B18 -> 109443 | C19: =B19-B18 -> 0 | D19: =C19/27 -> 0 | E19: =SUM((C19*$E$4)+(7500/'EDl log'!$A$37)) -> 241.93548 | G19: =G18 -> 619716 | H19: =G19-G18 -> 0 | I19: =C19+H19 -> 0 | J19: =IF(I19>0,E19/I19,0) -> 0 | K19: ='Swimming Pool quality check '!H19 -> 6762 | L19: =K19-K18 -> 0 | M19: =M18 -> 457.44 | N19: =SUM(M19-M18) -> 0 | O19: =O18 -> 529.52 | P19: =SUM(O19-O18) -> 0 | Q19: =SUM(P19+N19) -> 0 | T19: =T18 -> 5171 | U19: =SUM(T19-T18) -> 0 | V19: =V18 -> 471 | W19: =+V19-V18 -> 0 | X19: =X18 -> 151772 | Y19: =SUM(X19-X18) -> 0 | Z19: =Z18 -> 98847 | AA19: =Z19-Z18 -> 0 | AB19: =AB18 -> 261 | AC19: =AC18 -> 731 | AD19: =AC19-AC18 -> 0 | AE19: =AE18 -> 229.78 | AF19: =AE19-AE18 -> 0 | AG19: =AG18 -> 2205.62 | AH19: =AG19-AG18 -> 0 | AI19: =AF19+AH19 -> 0 | AJ19: =+Z19-Z18 -> 0 | AK19: =SUM(Y19-L19) -> 0 | AL19: =SUM(AJ19-W19) -> 0 | AM19: ='General information '!D19 -> 22.5 | AN19: ='General information '!H19 -> 0 | AP19: ='General information '!J19 -> 0 | AR19: =A19 -> 44330 | AS19: =AS18 -> 0.9 | AT19: =AT18 -> 133 | AU19: =AU18 -> 1.1 | AV19: 183 | AW19: 2.9 | AX19: =AX18 -> 161 | AY19: =AS19*AT19 -> 119.7 | AZ19: =AU19*AV19 -> 201.3 | BA19: =AW19*AX19 -> 466.9 | BB19: =AY19-AY18 -> 0 | BC19: =AZ19-AZ18 -> -1.1 | BD19: =BA19-BA18 -> 0 | BE19: =SUM(BB19:BD19) -> -1.1 | BF19: =SUM(I19-BE19) -> 1.1 | BG19: =SUM(I19-BF19) -> -1.1
A20: =ELEC!C17 -> 44331 | B20: =B19 -> 109443 | C20: =B20-B19 -> 0 | D20: =C20/27 -> 0 | E20: =SUM((C20*$E$4)+(7500/'EDl log'!$A$37)) -> 241.93548 | G20: =G19 -> 619716 | H20: =G20-G19 -> 0 | I20: =C20+H20 -> 0 | J20: =IF(I20>0,E20/I20,0) -> 0 | K20: ='Swimming Pool quality check '!H20 -> 6762 | L20: =K20-K19 -> 0 | M20: =M19 -> 457.44 | N20: =SUM(M20-M19) -> 0 | O20: =O19 -> 529.52 | P20: =SUM(O20-O19) -> 0 | Q20: =SUM(P20+N20) -> 0 | T20: =T19 -> 5171 | U20: =SUM(T20-T19) -> 0 | V20: =V19 -> 471 | W20: =+V20-V19 -> 0 | X20: =X19 -> 151772 | Y20: =SUM(X20-X19) -> 0 | Z20: =Z19 -> 98847 | AA20: =Z20-Z19 -> 0 | AB20: =AB19 -> 261 | AC20: =AC19 -> 731 | AD20: =AC20-AC19 -> 0 | AE20: =AE19 -> 229.78 | AF20: =AE20-AE19 -> 0 | AG20: =AG19 -> 2205.62 | AH20: =AG20-AG19 -> 0 | AI20: =AF20+AH20 -> 0 | AJ20: =+Z20-Z19 -> 0 | AK20: =SUM(Y20-L20) -> 0 | AL20: =SUM(AJ20-W20) -> 0 | AM20: ='General information '!D20 -> 23.5 | AN20: ='General information '!H20 -> 0 | AP20: ='General information '!J20 -> 0 | AR20: =A20 -> 44331 | AS20: =AS19 -> 0.9 | AT20: 133 | AU20: =AU19 -> 1.1 | AV20: 182 | AW20: 2.9 | AX20: 153 | AY20: =AS20*AT20 -> 119.7 | AZ20: =AU20*AV20 -> 200.2 | BA20: =AW20*AX20 -> 443.7 | BB20: =AY20-AY19 -> 0 | BC20: =AZ20-AZ19 -> -1.1 | BD20: =BA20-BA19 -> -23.2 | BE20: =SUM(BB20:BD20) -> -24.3 | BF20: =SUM(I20-BE20) -> 24.3 | BG20: =SUM(I20-BF20) -> -24.3
A21: =ELEC!C18 -> 44332 | B21: =B20 -> 109443 | C21: =B21-B20 -> 0 | D21: =C21/27 -> 0 | E21: =SUM((C21*$E$4)+(7500/'EDl log'!$A$37)) -> 241.93548 | G21: =G20 -> 619716 | H21: =G21-G20 -> 0 | I21: =C21+H21 -> 0 | J21: =IF(I21>0,E21/I21,0) -> 0 | K21: ='Swimming Pool quality check '!H21 -> 6766 | L21: =K21-K20 -> 4 | M21: =M20 -> 457.44 | N21: =SUM(M21-M20) -> 0 | O21: =O20 -> 529.52 | P21: =SUM(O21-O20) -> 0 | Q21: =SUM(P21+N21) -> 0 | T21: =T20 -> 5171 | U21: =SUM(T21-T20) -> 0 | V21: =V20 -> 471 | W21: =+V21-V20 -> 0 | X21: =X20 -> 151772 | Y21: =SUM(X21-X20) -> 0 | Z21: =Z20 -> 98847 | AA21: =Z21-Z20 -> 0 | AB21: =AB20 -> 261 | AC21: =AC20 -> 731 | AD21: =AC21-AC20 -> 0 | AE21: =AE20 -> 229.78 | AF21: =AE21-AE20 -> 0 | AG21: =AG20 -> 2205.62 | AH21: =AG21-AG20 -> 0 | AI21: =AF21+AH21 -> 0 | AJ21: =+Z21-Z20 -> 0 | AK21: =SUM(Y21-L21) -> -4 | AL21: =SUM(AJ21-W21) -> 0 | AM21: ='General information '!D21 -> 21.5 | AN21: ='General information '!H21 -> 0 | AP21: ='General information '!J21 -> 0 | AR21: =A21 -> 44332 | AS21: =AS20 -> 0.9 | AT21: =AT20 -> 133 | AU21: =AU20 -> 1.1 | AV21: 181 | AW21: 2.9 | AX21: 144 | AY21: =AS21*AT21 -> 119.7 | AZ21: =AU21*AV21 -> 199.1 | BA21: =AW21*AX21 -> 417.6 | BB21: =AY21-AY20 -> 0 | BC21: =AZ21-AZ20 -> -1.1 | BD21: =BA21-BA20 -> -26.1 | BE21: =SUM(BB21:BD21) -> -27.2 | BF21: =SUM(I21-BE21) -> 27.2 | BG21: =SUM(I21-BF21) -> -27.2
A22: =ELEC!C19 -> 44333 | B22: =B21 -> 109443 | C22: =B22-B21 -> 0 | D22: =C22/27 -> 0 | E22: =SUM((C22*$E$4)+(7500/'EDl log'!$A$37)) -> 241.93548 | G22: =G21 -> 619716 | H22: =G22-G21 -> 0 | I22: =C22+H22 -> 0 | J22: =IF(I22>0,E22/I22,0) -> 0 | K22: ='Swimming Pool quality check '!H22 -> 6766 | L22: =K22-K21 -> 0 | M22: =M21 -> 457.44 | N22: =SUM(M22-M21) -> 0 | O22: =O21 -> 529.52 | P22: =SUM(O22-O21) -> 0 | Q22: =SUM(P22+N22) -> 0 | T22: =T21 -> 5171 | U22: =SUM(T22-T21) -> 0 | V22: =V21 -> 471 | W22: =+V22-V21 -> 0 | X22: =X21 -> 151772 | Y22: =SUM(X22-X21) -> 0 | Z22: =Z21 -> 98847 | AA22: =Z22-Z21 -> 0 | AB22: =AB21 -> 261 | AC22: =AC21 -> 731 | AD22: =AC22-AC21 -> 0 | AE22: =AE21 -> 229.78 | AF22: =AE22-AE21 -> 0 | AG22: =AG21 -> 2205.62 | AH22: =AG22-AG21 -> 0 | AI22: =AF22+AH22 -> 0 | AJ22: =+Z22-Z21 -> 0 | AK22: =SUM(Y22-L22) -> 0 | AL22: =SUM(AJ22-W22) -> 0 | AM22: ='General information '!D22 -> 22.5 | AN22: ='General information '!H22 -> 0 | AP22: ='General information '!J22 -> 0 | AR22: =A22 -> 44333 | AS22: =AS21 -> 0.9 | AT22: =AT21 -> 133 | AU22: =AU21 -> 1.1 | AV22: 181 | AW22: 2.9 | AX22: 136 | AY22: =AS22*AT22 -> 119.7 | AZ22: =AU22*AV22 -> 199.1 | BA22: =AW22*AX22 -> 394.4 | BB22: =AY22-AY21 -> 0 | BC22: =AZ22-AZ21 -> 0 | BD22: =BA22-BA21 -> -23.2 | BE22: =SUM(BB22:BD22) -> -23.2 | BF22: =SUM(I22-BE22) -> 23.2 | BG22: =SUM(I22-BF22) -> -23.2
A23: =ELEC!C20 -> 44334 | B23: =B22 -> 109443 | C23: =B23-B22 -> 0 | D23: =C23/27 -> 0 | E23: =SUM((C23*$E$4)+(7500/'EDl log'!$A$37)) -> 241.93548 | G23: =G22 -> 619716 | H23: =G23-G22 -> 0 | I23: =C23+H23 -> 0 | J23: =IF(I23>0,E23/I23,0) -> 0 | K23: ='Swimming Pool quality check '!H23 -> 6768 | L23: =K23-K22 -> 2 | M23: =M22 -> 457.44 | N23: =SUM(M23-M22) -> 0 | O23: =O22 -> 529.52 | P23: =SUM(O23-O22) -> 0 | Q23: =SUM(P23+N23) -> 0 | T23: =T22 -> 5171 | U23: =SUM(T23-T22) -> 0 | V23: =V22 -> 471 | W23: =+V23-V22 -> 0 | X23: =X22 -> 151772 | Y23: =SUM(X23-X22) -> 0 | Z23: =Z22 -> 98847 | AA23: =Z23-Z22 -> 0 | AB23: =AB22 -> 261 | AC23: =AC22 -> 731 | AD23: =AC23-AC22 -> 0 | AE23: =AE22 -> 229.78 | AF23: =AE23-AE22 -> 0 | AG23: =AG22 -> 2205.62 | AH23: =AG23-AG22 -> 0 | AI23: =AF23+AH23 -> 0 | AJ23: =+Z23-Z22 -> 0 | AK23: =SUM(Y23-L23) -> -2 | AL23: =SUM(AJ23-W23) -> 0 | AM23: ='General information '!D23 -> 23 | AN23: ='General information '!H23 -> 0 | AP23: ='General information '!J23 -> 0 | AR23: =A23 -> 44334 | AS23: =AS22 -> 0.9 | AT23: 130 | AU23: =AU22 -> 1.1 | AV23: 180 | AW23: 2.9 | AX23: 126 | AY23: =AS23*AT23 -> 117 | AZ23: =AU23*AV23 -> 198 | BA23: =AW23*AX23 -> 365.4 | BB23: =AY23-AY22 -> -2.7 | BC23: =AZ23-AZ22 -> -1.1 | BD23: =BA23-BA22 -> -29 | BE23: =SUM(BB23:BD23) -> -32.8 | BF23: =SUM(I23-BE23) -> 32.8 | BG23: =SUM(I23-BF23) -> -32.8
A24: =ELEC!C21 -> 44335 | B24: =B23 -> 109443 | C24: =B24-B23 -> 0 | D24: =C24/27 -> 0 | E24: =SUM((C24*$E$4)+(7500/'EDl log'!$A$37)) -> 241.93548 | G24: =G23 -> 619716 | H24: =G24-G23 -> 0 | I24: =C24+H24 -> 0 | J24: =IF(I24>0,E24/I24,0) -> 0 | K24: ='Swimming Pool quality check '!H24 -> 6769 | L24: =K24-K23 -> 1 | M24: =M23 -> 457.44 | N24: =SUM(M24-M23) -> 0 | O24: =O23 -> 529.52 | P24: =SUM(O24-O23) -> 0 | Q24: =SUM(P24+N24) -> 0 | T24: =T23 -> 5171 | U24: =SUM(T24-T23) -> 0 | V24: 472 | W24: =+V24-V23 -> 1 | X24: 151832 | Y24: =SUM(X24-X23) -> 60 | Z24: =Z23 -> 98847 | AA24: =Z24-Z23 -> 0 | AB24: =AB23 -> 261 | AC24: =AC23 -> 731 | AD24: =AC24-AC23 -> 0 | AE24: =AE23 -> 229.78 | AF24: =AE24-AE23 -> 0 | AG24: =AG23 -> 2205.62 | AH24: =AG24-AG23 -> 0 | AI24: =AF24+AH24 -> 0 | AJ24: =+Z24-Z23 -> 0 | AK24: =SUM(Y24-L24) -> 59 | AL24: =SUM(AJ24-W24) -> -1 | AM24: ='General information '!D24 -> 23 | AN24: ='[2]General information '!H24 -> 0 | AP24: ='[2]General information '!J24 -> 0 | AR24: =A24 -> 44335 | AS24: =AS23 -> 0.9 | AT24: 64 | AU24: =AU23 -> 1.1 | AV24: 180 | AW24: 2.9 | AX24: 117 | AY24: =AS24*AT24 -> 57.6 | AZ24: =AU24*AV24 -> 198 | BA24: =AW24*AX24 -> 339.3 | BB24: =AY24-AY23 -> -59.4 | BC24: =AZ24-AZ23 -> 0 | BD24: =BA24-BA23 -> -26.1 | BE24: =SUM(BB24:BD24) -> -85.5 | BF24: =SUM(I24-BE24) -> 85.5 | BG24: =SUM(I24-BF24) -> -85.5
A25: =ELEC!C22 -> 44336 | B25: =B24 -> 109443 | C25: =B25-B24 -> 0 | D25: =C25/27 -> 0 | E25: =SUM((C25*$E$4)+(7500/'EDl log'!$A$37)) -> 241.93548 | G25: =G24 -> 619716 | H25: =G25-G24 -> 0 | I25: =C25+H25 -> 0 | J25: =IF(I25>0,E25/I25,0) -> 0 | K25: ='Swimming Pool quality check '!H25 -> 6769 | L25: =K25-K24 -> 0 | M25: =M24 -> 457.44 | N25: =SUM(M25-M24) -> 0 | O25: =O24 -> 529.52 | P25: =SUM(O25-O24) -> 0 | Q25: =SUM(P25+N25) -> 0 | T25: =T24 -> 5171 | U25: =SUM(T25-T24) -> 0 | V25: =V24 -> 472 | W25: =+V25-V24 -> 0 | X25: =X24 -> 151832 | Y25: =SUM(X25-X24) -> 0 | Z25: =Z24 -> 98847 | AA25: =Z25-Z24 -> 0 | AB25: =AB24 -> 261 | AC25: =AC24 -> 731 | AD25: =AC25-AC24 -> 0 | AE25: =AE24 -> 229.78 | AF25: =AE25-AE24 -> 0 | AG25: =AG24 -> 2205.62 | AH25: =AG25-AG24 -> 0 | AI25: =AF25+AH25 -> 0 | AJ25: =+Z25-Z24 -> 0 | AK25: =SUM(Y25-L25) -> 0 | AL25: =SUM(AJ25-W25) -> 0 | AM25: ='General information '!D25 -> 23.5 | AN25: ='General information '!H25 -> 0 | AP25: ='General information '!J25 -> 0 | AR25: =A25 -> 44336 | AS25: =AS24 -> 0.9 | AT25: =AT24 -> 64 | AU25: =AU24 -> 1.1 | AV25: 179 | AW25: 2.9 | AX25: 111 | AY25: =AS25*AT25 -> 57.6 | AZ25: =AU25*AV25 -> 196.9 | BA25: =AW25*AX25 -> 321.9 | BB25: =AY25-AY24 -> 0 | BC25: =AZ25-AZ24 -> -1.1 | BD25: =BA25-BA24 -> -17.4 | BE25: =SUM(BB25:BD25) -> -18.5 | BF25: =SUM(I25-BE25) -> 18.5 | BG25: =SUM(I25-BF25) -> -18.5
A26: =ELEC!C23 -> 44337 | B26: =B25 -> 109443 | C26: =B26-B25 -> 0 | D26: =C26/27 -> 0 | E26: =SUM((C26*$E$4)+(7500/'EDl log'!$A$37)) -> 241.93548 | G26: =G25 -> 619716 | H26: =G26-G25 -> 0 | I26: =C26+H26 -> 0 | J26: =IF(I26>0,E26/I26,0) -> 0 | K26: ='Swimming Pool quality check '!H26 -> 6769 | L26: =K26-K25 -> 0 | M26: =M25 -> 457.44 | N26: =SUM(M26-M25) -> 0 | O26: =O25 -> 529.52 | P26: =SUM(O26-O25) -> 0 | Q26: =SUM(P26+N26) -> 0 | T26: =T25 -> 5171 | U26: =SUM(T26-T25) -> 0 | V26: =V25 -> 472 | W26: =+V26-V25 -> 0 | X26: =X25 -> 151832 | Y26: =SUM(X26-X25) -> 0 | Z26: =Z25 -> 98847 | AA26: =Z26-Z25 -> 0 | AB26: =AB25 -> 261 | AC26: =AC25 -> 731 | AD26: =AC26-AC25 -> 0 | AE26: =AE25 -> 229.78 | AF26: =AE26-AE25 -> 0 | AG26: =AG25 -> 2205.62 | AH26: =AG26-AG25 -> 0 | AI26: =AF26+AH26 -> 0 | AJ26: =+Z26-Z25 -> 0 | AK26: =SUM(Y26-L26) -> 0 | AL26: =SUM(AJ26-W26) -> 0 | AM26: ='General information '!D26 -> 24.5 | AN26: ='General information '!H26 -> 0 | AP26: ='General information '!J26 -> 0 | AR26: =A26 -> 44337 | AS26: =AS25 -> 0.9 | AT26: =AT25 -> 64 | AU26: =AU25 -> 1.1 | AV26: 178 | AW26: 2.9 | AX26: 108 | AY26: 108 | AZ26: =AU26*AV26 -> 195.8 | BA26: =AW26*AX26 -> 313.2 | BB26: =AY26-AY25 -> 50.4 | BC26: =AZ26-AZ25 -> -1.1 | BD26: =BA26-BA25 -> -8.7 | BE26: =SUM(BB26:BD26) -> 40.6 | BF26: =SUM(I26-BE26) -> -40.6 | BG26: =SUM(I26-BF26) -> 40.6
A27: =ELEC!C24 -> 44338 | B27: =B26 -> 109443 | C27: =B27-B26 -> 0 | D27: =C27/27 -> 0 | E27: =SUM((C27*$E$4)+(7500/'EDl log'!$A$37)) -> 241.93548 | G27: =G26 -> 619716 | H27: =G27-G26 -> 0 | I27: =C27+H27 -> 0 | J27: =IF(I27>0,E27/I27,0) -> 0 | K27: ='Swimming Pool quality check '!H27 -> 6770 | L27: =K27-K26 -> 1 | M27: =M26 -> 457.44 | N27: =SUM(M27-M26) -> 0 | O27: =O26 -> 529.52 | P27: =SUM(O27-O26) -> 0 | Q27: =SUM(P27+N27) -> 0 | T27: =T26 -> 5171 | U27: =SUM(T27-T26) -> 0 | V27: =V26 -> 472 | W27: =+V27-V26 -> 0 | X27: =X26 -> 151832 | Y27: =SUM(X27-X26) -> 0 | Z27: =Z26 -> 98847 | AA27: =Z27-Z26 -> 0 | AB27: =AB26 -> 261 | AC27: =AC26 -> 731 | AD27: =AC27-AC26 -> 0 | AE27: =AE26 -> 229.78 | AF27: =AE27-AE26 -> 0 | AG27: =AG26 -> 2205.62 | AH27: =AG27-AG26 -> 0 | AI27: =AF27+AH27 -> 0 | AJ27: =+Z27-Z26 -> 0 | AK27: =SUM(Y27-L27) -> -1 | AL27: =SUM(AJ27-W27) -> 0 | AM27: ='General information '!D27 -> 24.5 | AN27: ='General information '!H27 -> 0 | AP27: ='General information '!J27 -> 0 | AR27: =A27 -> 44338 | AS27: =AS26 -> 0.9 | AT27: 120 | AU27: =AU26 -> 1.1 | AV27: 177 | AW27: 2.9 | AX27: 105 | AY27: =AS27*AT27 -> 108 | AZ27: =AU27*AV27 -> 194.7 | BA27: =AW27*AX27 -> 304.5 | BB27: =AY27-AY26 -> 0 | BC27: =AZ27-AZ26 -> -1.1 | BD27: =BA27-BA26 -> -8.7 | BE27: =SUM(BB27:BD27) -> -9.8 | BF27: =SUM(I27-BE27) -> 9.8 | BG27: =SUM(I27-BF27) -> -9.8
A28: =ELEC!C25 -> 44339 | B28: =B27 -> 109443 | C28: =B28-B27 -> 0 | D28: =C28/27 -> 0 | E28: =SUM((C28*$E$4)+(7500/'EDl log'!$A$37)) -> 241.93548 | G28: =G27 -> 619716 | H28: =G28-G27 -> 0 | I28: =C28+H28 -> 0 | J28: =IF(I28>0,E28/I28,0) -> 0 | K28: ='Swimming Pool quality check '!H28 -> 6770 | L28: =K28-K27 -> 0 | M28: =M27 -> 457.44 | N28: =SUM(M28-M27) -> 0 | O28: =O27 -> 529.52 | P28: =SUM(O28-O27) -> 0 | Q28: =SUM(P28+N28) -> 0 | T28: =T27 -> 5171 | U28: =SUM(T28-T27) -> 0 | V28: =V27 -> 472 | W28: =+V28-V27 -> 0 | X28: =X27 -> 151832 | Y28: =SUM(X28-X27) -> 0 | Z28: =Z27 -> 98847 | AA28: =Z28-Z27 -> 0 | AB28: =AB27 -> 261 | AC28: =AC27 -> 731 | AD28: =AC28-AC27 -> 0 | AE28: =AE27 -> 229.78 | AF28: =AE28-AE27 -> 0 | AG28: =AG27 -> 2205.62 | AH28: =AG28-AG27 -> 0 | AI28: =AF28+AH28 -> 0 | AJ28: =+Z28-Z27 -> 0 | AK28: =SUM(Y28-L28) -> 0 | AL28: =SUM(AJ28-W28) -> 0 | AM28: ='General information '!D28 -> 23.5 | AN28: ='General information '!H28 -> 0 | AP28: ='General information '!J28 -> 0 | AR28: =A28 -> 44339 | AS28: =AS27 -> 0.9 | AT28: 120 | AU28: =AU27 -> 1.1 | AV28: 176 | AW28: 2.9 | AX28: 102 | AY28: =AS28*AT28 -> 108 | AZ28: =AU28*AV28 -> 193.6 | BA28: =AW28*AX28 -> 295.8 | BB28: =AY28-AY27 -> 0 | BC28: =AZ28-AZ27 -> -1.1 | BD28: =BA28-BA27 -> -8.7 | BE28: =SUM(BB28:BD28) -> -9.8 | BF28: =SUM(I28-BE28) -> 9.8 | BG28: =SUM(I28-BF28) -> -9.8
A29: =ELEC!C26 -> 44340 | B29: =B28 -> 109443 | C29: =B29-B28 -> 0 | D29: =C29/27 -> 0 | E29: =SUM((C29*$E$4)+(7500/'EDl log'!$A$37)) -> 241.93548 | G29: =G28 -> 619716 | H29: =G29-G28 -> 0 | I29: =C29+H29 -> 0 | J29: =IF(I29>0,E29/I29,0) -> 0 | K29: ='Swimming Pool quality check '!H29 -> 6770 | L29: =K29-K28 -> 0 | M29: =M28 -> 457.44 | N29: =SUM(M29-M28) -> 0 | O29: =O28 -> 529.52 | P29: =SUM(O29-O28) -> 0 | Q29: =SUM(P29+N29) -> 0 | T29: =T28 -> 5171 | U29: =SUM(T29-T28) -> 0 | V29: =V28 -> 472 | W29: =+V29-V28 -> 0 | X29: =X28 -> 151832 | Y29: =SUM(X29-X28) -> 0 | Z29: =Z28 -> 98847 | AA29: =Z29-Z28 -> 0 | AB29: =AB28 -> 261 | AC29: =AC28 -> 731 | AD29: =AC29-AC28 -> 0 | AE29: =AE28 -> 229.78 | AF29: =AE29-AE28 -> 0 | AG29: =AG28 -> 2205.62 | AH29: =AG29-AG28 -> 0 | AI29: =AF29+AH29 -> 0 | AJ29: =+Z29-Z28 -> 0 | AK29: =SUM(Y29-L29) -> 0 | AL29: =SUM(AJ29-W29) -> 0 | AM29: ='General information '!D29 -> 24.5 | AN29: ='General information '!H29 -> 0 | AP29: ='General information '!J29 -> 0 | AR29: =A29 -> 44340 | AS29: =AS28 -> 0.9 | AT29: =AT28 -> 120 | AU29: =AU28 -> 1.1 | AV29: 175 | AW29: 2.9 | AX29: 115 | AY29: =AS29*AT29 -> 108 | AZ29: =AU29*AV29 -> 192.5 | BA29: =AW29*AX29 -> 333.5 | BB29: =AY29-AY28 -> 0 | BC29: =AZ29-AZ28 -> -1.1 | BD29: =BA29-BA28 -> 37.7 | BE29: =SUM(BB29:BD29) -> 36.6 | BF29: =SUM(I29-BE29) -> -36.6 | BG29: =SUM(I29-BF29) -> 36.6
A30: =ELEC!C27 -> 44341 | B30: =B29 -> 109443 | C30: =B30-B29 -> 0 | D30: =C30/27 -> 0 | E30: =SUM((C30*$E$4)+(7500/'EDl log'!$A$37)) -> 241.93548 | G30: =G29 -> 619716 | H30: =G30-G29 -> 0 | I30: =C30+H30 -> 0 | J30: =IF(I30>0,E30/I30,0) -> 0 | K30: ='Swimming Pool quality check '!H30 -> 6770 | L30: =K30-K29 -> 0 | M30: =M29 -> 457.44 | N30: =SUM(M30-M29) -> 0 | O30: =O29 -> 529.52 | P30: =SUM(O30-O29) -> 0 | Q30: =SUM(P30+N30) -> 0 | T30: =T29 -> 5171 | U30: =SUM(T30-T29) -> 0 | V30: =V29 -> 472 | W30: =+V30-V29 -> 0 | X30: =X29 -> 151832 | Y30: =SUM(X30-X29) -> 0 | Z30: =Z29 -> 98847 | AA30: =Z30-Z29 -> 0 | AB30: =AB29 -> 261 | AC30: =AC29 -> 731 | AD30: =AC30-AC29 -> 0 | AE30: =AE29 -> 229.78 | AF30: =AE30-AE29 -> 0 | AG30: =AG29 -> 2205.62 | AH30: =AG30-AG29 -> 0 | AI30: =AF30+AH30 -> 0 | AJ30: =+Z30-Z29 -> 0 | AK30: =SUM(Y30-L30) -> 0 | AL30: =SUM(AJ30-W30) -> 0 | AM30: ='General information '!D30 -> 24.5 | AN30: ='General information '!H30 -> 0 | AP30: ='General information '!J30 -> 0 | AR30: =A30 -> 44341 | AS30: =AS29 -> 0.9 | AT30: 84 | AU30: =AU29 -> 1.1 | AV30: 172 | AW30: 2.9 | AX30: 111 | AY30: =AS30*AT30 -> 75.6 | AZ30: =AU30*AV30 -> 189.2 | BA30: =AW30*AX30 -> 321.9 | BB30: =AY30-AY29 -> -32.4 | BC30: =AZ30-AZ29 -> -3.3 | BD30: =BA30-BA29 -> -11.6 | BE30: =SUM(BB30:BD30) -> -47.3 | BF30: =SUM(I30-BE30) -> 47.3 | BG30: =SUM(I30-BF30) -> -47.3
A31: =ELEC!C28 -> 44342 | B31: =B30 -> 109443 | C31: =B31-B30 -> 0 | D31: =C31/27 -> 0 | E31: =SUM((C31*$E$4)+(7500/'EDl log'!$A$37)) -> 241.93548 | G31: =G30 -> 619716 | H31: =G31-G30 -> 0 | I31: =C31+H31 -> 0 | J31: =IF(I31>0,E31/I31,0) -> 0 | K31: ='Swimming Pool quality check '!H31 -> 6773 | L31: =K31-K30 -> 3 | M31: =M30 -> 457.44 | N31: =SUM(M31-M30) -> 0 | O31: =O30 -> 529.52 | P31: =SUM(O31-O30) -> 0 | Q31: =SUM(P31+N31) -> 0 | T31: =T30 -> 5171 | U31: =SUM(T31-T30) -> 0 | V31: 474 | W31: =+V31-V30 -> 2 | X31: 151834 | Y31: =SUM(X31-X30) -> 2 | Z31: =Z30 -> 98847 | AA31: =Z31-Z30 -> 0 | AB31: =AB30 -> 261 | AC31: =AC30 -> 731 | AD31: =AC31-AC30 -> 0 | AE31: 229.81 | AF31: =AE31-AE30 -> 0.03 | AG31: 2205.98 | AH31: =AG31-AG30 -> 0.36 | AI31: =AF31+AH31 -> 0.39 | AJ31: =+Z31-Z30 -> 0 | AK31: =SUM(Y31-L31) -> -1 | AL31: =SUM(AJ31-W31) -> -2 | AM31: ='General information '!D31 -> 24.5 | AN31: ='General information '!H31 -> 0 | AP31: ='General information '!J31 -> 0 | AR31: =A31 -> 44342 | AS31: =AS30 -> 0.9 | AT31: 65 | AU31: =AU30 -> 1.1 | AV31: 169 | AW31: 2.9 | AX31: 105 | AY31: =AS31*AT31 -> 58.5 | AZ31: =AU31*AV31 -> 185.9 | BA31: =AW31*AX31 -> 304.5 | BB31: =AY31-AY30 -> -17.1 | BC31: =AZ31-AZ30 -> -3.3 | BD31: =BA31-BA30 -> -17.4 | BE31: =SUM(BB31:BD31) -> -37.8 | BF31: =SUM(I31-BE31) -> 37.8 | BG31: =SUM(I31-BF31) -> -37.8
A32: =ELEC!C29 -> 44343 | B32: =B31 -> 109443 | C32: =B32-B31 -> 0 | D32: =C32/27 -> 0 | E32: =SUM((C32*$E$4)+(7500/'EDl log'!$A$37)) -> 241.93548 | G32: 620151 | H32: =G32-G31 -> 435 | I32: =C32+H32 -> 435 | J32: =IF(I32>0,E32/I32,0) -> 0.55617353 | K32: ='Swimming Pool quality check '!H32 -> 6773 | L32: =K32-K31 -> 0 | M32: =M31 -> 457.44 | N32: =SUM(M32-M31) -> 0 | O32: =O31 -> 529.52 | P32: =SUM(O32-O31) -> 0 | Q32: =SUM(P32+N32) -> 0 | T32: =T31 -> 5171 | U32: =SUM(T32-T31) -> 0 | V32: =V31 -> 474 | W32: =+V32-V31 -> 0 | X32: 151905 | Y32: =SUM(X32-X31) -> 71 | Z32: =Z31 -> 98847 | AA32: =Z32-Z31 -> 0 | AB32: =AB31 -> 261 | AC32: =AC31 -> 731 | AD32: =AC32-AC31 -> 0 | AE32: =AE31 -> 229.81 | AF32: =AE32-AE31 -> 0 | AG32: =AG31 -> 2205.98 | AH32: =AG32-AG31 -> 0 | AI32: =AF32+AH32 -> 0 | AJ32: =+Z32-Z31 -> 0 | AK32: =SUM(Y32-L32) -> 71 | AL32: =SUM(AJ32-W32) -> 0 | AM32: ='General information '!D32 -> 23.5 | AN32: ='General information '!H32 -> 0 | AP32: ='General information '!J32 -> 0 | AR32: =A32 -> 44343 | AS32: =AS31 -> 0.9 | AT32: 120 | AU32: =AU31 -> 1.1 | AV32: 168 | AW32: 2.9 | AX32: 117 | AY32: =AS32*AT32 -> 108 | AZ32: =AU32*AV32 -> 184.8 | BA32: =AW32*AX32 -> 339.3 | BB32: =AY32-AY31 -> 49.5 | BC32: =AZ32-AZ31 -> -1.1 | BD32: =BA32-BA31 -> 34.8 | BE32: =SUM(BB32:BD32) -> 83.2 | BF32: =SUM(I32-BE32) -> 351.8 | BG32: =SUM(I32-BF32) -> 83.2
A33: =ELEC!C30 -> 44344 | B33: =B32 -> 109443 | C33: =B33-B32 -> 0 | D33: =C33/27 -> 0 | E33: =SUM((C33*$E$4)+(7500/'EDl log'!$A$37)) -> 241.93548 | G33: =G32 -> 620151 | H33: =G33-G32 -> 0 | I33: =C33+H33 -> 0 | J33: =IF(I33>0,E33/I33,0) -> 0 | K33: ='Swimming Pool quality check '!H33 -> 6773 | L33: =K33-K32 -> 0 | M33: =M32 -> 457.44 | N33: =SUM(M33-M32) -> 0 | O33: =O32 -> 529.52 | P33: =SUM(O33-O32) -> 0 | Q33: =SUM(P33+N33) -> 0 | T33: =T32 -> 5171 | U33: =SUM(T33-T32) -> 0 | V33: =V32 -> 474 | W33: =+V33-V32 -> 0 | X33: =X32 -> 151905 | Y33: =SUM(X33-X32) -> 0 | Z33: =Z32 -> 98847 | AA33: =Z33-Z32 -> 0 | AB33: =AB32 -> 261 | AC33: =AC32 -> 731 | AD33: =AC33-AC32 -> 0 | AE33: =AE32 -> 229.81 | AF33: =AE33-AE32 -> 0 | AG33: =AG32 -> 2205.98 | AH33: =AG33-AG32 -> 0 | AI33: =AF33+AH33 -> 0 | AJ33: =+Z33-Z32 -> 0 | AK33: =SUM(Y33-L33) -> 0 | AL33: =SUM(AJ33-W33) -> 0 | AM33: ='General information '!D33 -> 0 | AN33: ='General information '!H33 -> 0 | AP33: ='General information '!J33 -> 0 | AR33: =A33 -> 44344 | AS33: =AS32 -> 0.9 | AT33: =AT32 -> 120 | AU33: =AU32 -> 1.1 | AV33: =AV32 -> 168 | AW33: 2.9 | AX33: =AX32 -> 117 | AY33: =AS33*AT33 -> 108 | AZ33: =AU33*AV33 -> 184.8 | BA33: =AW33*AX33 -> 339.3 | BB33: =AY33-AY32 -> 0 | BC33: =AZ33-AZ32 -> 0 | BD33: =BA33-BA32 -> 0 | BE33: =SUM(BB33:BD33) -> 0 | BF33: =SUM(I33-BE33) -> 0 | BG33: =SUM(I33-BF33) -> 0
A34: =ELEC!C31 -> 44345 | B34: =B33 -> 109443 | C34: =B34-B33 -> 0 | D34: =C34/27 -> 0 | E34: =SUM((C34*$E$4)+(7500/'EDl log'!$A$37)) -> 241.93548 | G34: =G33 -> 620151 | H34: =G34-G33 -> 0 | I34: =C34+H34 -> 0 | J34: =IF(I34>0,E34/I34,0) -> 0 | K34: ='Swimming Pool quality check '!H34 -> 6773 | L34: =K34-K33 -> 0 | M34: =M33 -> 457.44 | N34: =SUM(M34-M33) -> 0 | O34: =O33 -> 529.52 | P34: =SUM(O34-O33) -> 0 | Q34: =SUM(P34+N34) -> 0 | T34: =T33 -> 5171 | U34: =SUM(T34-T33) -> 0 | V34: =V33 -> 474 | W34: =+V34-V33 -> 0 | X34: =X33 -> 151905 | Y34: =SUM(X34-X33) -> 0 | Z34: =Z33 -> 98847 | AA34: =Z34-Z33 -> 0 | AB34: =AB33 -> 261 | AC34: =AC33 -> 731 | AD34: =AC34-AC33 -> 0 | AE34: =AE33 -> 229.81 | AF34: =AE34-AE33 -> 0 | AG34: =AG33 -> 2205.98 | AH34: =AG34-AG33 -> 0 | AI34: =AF34+AH34 -> 0 | AJ34: =+Z34-Z33 -> 0 | AK34: =SUM(Y34-L34) -> 0 | AL34: =SUM(AJ34-W34) -> 0 | AM34: ='General information '!D34 -> 0 | AN34: ='General information '!H34 -> 0 | AP34: ='General information '!J34 -> 0 | AR34: =A34 -> 44345 | AS34: =AS33 -> 0.9 | AT34: =AT33 -> 120 | AU34: =AU33 -> 1.1 | AV34: =AV33 -> 168 | AW34: 2.9 | AX34: =AX33 -> 117 | AY34: =AS34*AT34 -> 108 | AZ34: =AU34*AV34 -> 184.8 | BA34: =AW34*AX34 -> 339.3 | BB34: =AY34-AY33 -> 0 | BC34: =AZ34-AZ33 -> 0 | BD34: =BA34-BA33 -> 0 | BE34: =SUM(BB34:BD34) -> 0 | BF34: =SUM(I34-BE34) -> 0 | BG34: =SUM(I34-BF34) -> 0
A35: =ELEC!C32 -> 44346 | B35: =B34 -> 109443 | C35: =B35-B34 -> 0 | D35: =C35/27 -> 0 | E35: =SUM((C35*$E$4)+(7500/'EDl log'!$A$37)) -> 241.93548 | G35: =G34 -> 620151 | H35: =G35-G34 -> 0 | I35: =C35+H35 -> 0 | J35: =IF(I35>0,E35/I35,0) -> 0 | K35: ='Swimming Pool quality check '!H35 -> 6773 | L35: =K35-K34 -> 0 | M35: =M34 -> 457.44 | N35: =SUM(M35-M34) -> 0 | O35: =O34 -> 529.52 | P35: =SUM(O35-O34) -> 0 | Q35: =SUM(P35+N35) -> 0 | T35: =T34 -> 5171 | U35: =SUM(T35-T34) -> 0 | V35: =V34 -> 474 | W35: =+V35-V34 -> 0 | X35: =X34 -> 151905 | Y35: =SUM(X35-X34) -> 0 | Z35: =Z34 -> 98847 | AA35: =Z35-Z34 -> 0 | AB35: =AB34 -> 261 | AC35: =AC34 -> 731 | AD35: =AC35-AC34 -> 0 | AE35: =AE34 -> 229.81 | AF35: =AE35-AE34 -> 0 | AG35: =AG34 -> 2205.98 | AH35: =AG35-AG34 -> 0 | AI35: =AF35+AH35 -> 0 | AJ35: =+Z35-Z34 -> 0 | AK35: =SUM(Y35-L35) -> 0 | AL35: =SUM(AJ35-W35) -> 0 | AM35: ='General information '!D35 -> 0 | AN35: ='General information '!H35 -> 0 | AP35: ='General information '!J35 -> 0 | AR35: =A35 -> 44346 | AS35: =AS34 -> 0.9 | AT35: =AT34 -> 120 | AU35: =AU34 -> 1.1 | AV35: =AV34 -> 168 | AW35: 2.9 | AX35: =AX34 -> 117 | AY35: =AS35*AT35 -> 108 | AZ35: =AU35*AV35 -> 184.8 | BA35: =AW35*AX35 -> 339.3 | BB35: =AY35-AY34 -> 0 | BC35: =AZ35-AZ34 -> 0 | BD35: =BA35-BA34 -> 0 | BE35: =SUM(BB35:BD35) -> 0 | BF35: =SUM(I35-BE35) -> 0 | BG35: =SUM(I35-BF35) -> 0
A36: =ELEC!C33 -> 44347 | B36: =B35 -> 109443 | C36: =B36-B35 -> 0 | D36: =C36/27 -> 0 | E36: =SUM((C36*$E$4)+(7500/'EDl log'!$A$37)) -> 241.93548 | G36: =G35 -> 620151 | H36: =G36-G35 -> 0 | I36: =C36+H36 -> 0 | J36: =IF(I36>0,E36/I36,0) -> 0 | K36: ='Swimming Pool quality check '!H36 -> 6773 | L36: =K36-K35 -> 0 | M36: =M35 -> 457.44 | N36: =SUM(M36-M35) -> 0 | O36: =O35 -> 529.52 | P36: =SUM(O36-O35) -> 0 | Q36: =SUM(P36+N36) -> 0 | T36: =T35 -> 5171 | U36: =SUM(T36-T35) -> 0 | V36: =V35 -> 474 | W36: =+V36-V35 -> 0 | X36: =X35 -> 151905 | Y36: =SUM(X36-X35) -> 0 | Z36: =Z35 -> 98847 | AA36: =Z36-Z35 -> 0 | AB36: =AB35 -> 261 | AC36: =AC35 -> 731 | AD36: =AC36-AC35 -> 0 | AE36: =AE35 -> 229.81 | AF36: =AE36-AE35 -> 0 | AG36: =AG35 -> 2205.98 | AH36: =AG36-AG35 -> 0 | AI36: =AF36+AH36 -> 0 | AJ36: =+Z36-Z35 -> 0 | AK36: =SUM(Y36-L36) -> 0 | AL36: =SUM(AJ36-W36) -> 0 | AM36: ='General information '!D37 -> 0 | AN36: ='General information '!H37 -> 0 | AP36: ='General information '!J37 -> 0
C37: =SUM(C6:C33) -> 0 | D37: =SUM(D6:D33) -> 0 | F37: =SUM(F6:F33) -> 0 | H37: =SUM(H6:H33) -> 1660 | I37: =SUM(I6:I33) -> 1660 | L37: =SUM(L7:L33) -> 22 | Q37: =SUM(Q5:Q33) -> 0 | U37: =SUM(U6:U33) -> 0 | Y37: =SUM(Y6,Y33,Y31,Y29,Y27,Y25,Y23,Y21,Y19,Y17,Y15,Y13,Y11,Y9,Y7,Y34,Y35,Y36) -> 3 | AJ37: =SUM(AJ6:AJ33) -> 79 | AK37: =SUM(Y37-L37) -> -19 | AL37: =SUM(AL6:AL33) -> 75
C38: =+C37*1.66 -> 0 | E38: =SUM(E6:E33) -> 6774.1935 | F38: =SUM(F6:F33) -> 0 | H38: 7500 | I38: =SUM('General information '!G37/WATER!I37) -> 0 | O38: =SUM(Q37+I37) -> 1660 | Z38: =SUM(Y37:AJ37) -> 82 | AK38: =SUM(Y38-L38) -> 0
B39: =9*27 -> 243 | D39: =SUM(D6:D33) -> 0 | F39: =SUM(F6:F33) -> 0 | G39: =SUM(I37) -> 1660 | H39: =SUM(H38+C38) -> 7500 | K39: =SUM(H39/G39) -> 4.5180723 | AJ39: =SUM(C38-AK38) -> 0 | AM39: =SUM(AJ39/AO38) -> #DIV/0!

Sheet GEN
B1: GEN1 | C1: RUN HR | D1: Fuel Counter Index | E1: Cons /day | F1: Diesel L/H | H1: next service | I1: ALARM | J1: GEN2 | K1: RUN HR | L1: Fuel Counter Index | M1: Cons /day | N1: Diesel L/H | P1: next service | Q1: ALARM | R1: GEN3 | S1: RUN HR | T1: Fuel Counter Index | U1: Cons /day | V1: Diesel L/H | X1: next service | Y1: ALARM | Z1: RH total | AA1: Gen Con /day | AB1: Total Deisel Cons/day | AC1: H /L | AD1: TOAL KW GEN | AI1: fuel Consuption | AK1: AVG KW/h
A2: =ELEC!C2 -> 44316 | B2: 9893 | C2: 8 | D2: 386061 | E2: 1483.7 | F2: 185.4625 | H2: 9934 | I2: ok | J2: 10698 | K2: 0 | L2: 357691 | M2: 0 | N2: 0 | P2: 10873 | Q2: ok | R2: 12150 | S2: 0 | T2: 438163 | U2: 0 | V2: 250 | X2: 12192 | Y2: ok | Z2: 8 | AA2: 1483.7 | AB2: 435.4625 | AC2: 185.4625 | AD2: 0 | AE2: 0 | AF2: 0 | AG2: 0 | AH2: 185.4625 | AI2: 0 | AJ2: 0.25738397 | AK2: 0
A3: =ELEC!C3 -> 44317 | B3: 9899 | C3: =B3-B2 -> 6 | D3: 387090 | E3: =SUM(D3-D2) -> 1029 | F3: =IF(C3>0,E3/C3,0) -> 171.5 | G3: =[3]GEN!G32 -> 0 | H3: =H2 -> 9934 | I3: =IF(B3-H3<=0,"ok","oil change") -> ok | J3: =J2 -> 10698 | K3: =J3-J2 -> 0 | L3: =L2 -> 357691 | M3: =SUM(L3-L2) -> 0 | N3: =IF(K3>0,M3/K3,0) -> 0 | O3: =[3]GEN!O32 -> 0 | P3: =P2 -> 10873 | Q3: =IF(J3-P3<=0,"ok","oil change") -> ok | R3: =R2 -> 12150 | S3: =R3-R2 -> 0 | T3: =T2 -> 438163 | U3: =V3*S3 -> 0 | V3: 250 | W3: =[3]GEN!W32 -> 0 | X3: =X2 -> 12192 | Y3: =IF(R3-X3<=0,"ok","oil change") -> ok | Z3: =C3+K3+S3 -> 6 | AA3: =U3+M3+E3 -> 1029 | AB3: =V3+N3+F3 -> 421.5 | AC3: =IF(Z3>0,AA3/Z3,0) -> 171.5 | AD3: =ELEC!Q3 -> 3927 | AE3: =SUM(AD3/Z3) -> 654.5 | AF3: =SUM(AE3/1600) -> 0.4090625 | AG3: =SUM(360*AF3) -> 147.2625 | AH3: =SUM(AC3-AG3) -> 24.2375 | AI3: =AD3*AJ3 -> 1010.7468 | AJ3: =305/1185 -> 0.25738397 | AK3: =AI3/Z3 -> 168.45781
A4: =ELEC!C4 -> 44318 | B4: 9902 | C4: =B4-B3 -> 3 | D4: 387585 | E4: =SUM(D4-D3) -> 495 | F4: =IF(C4>0,E4/C4,0) -> 165 | H4: 9934 | I4: =IF(B4-H4<=0,"ok","oil change") -> ok | J4: =J3 -> 10698 | K4: =J4-J3 -> 0 | L4: =L3 -> 357691 | M4: =SUM(L4-L3) -> 0 | N4: =IF(K4>0,M4/K4,0) -> 0 | P4: =P3 -> 10873 | Q4: =IF(J4-P4<=0,"ok","oil change") -> ok | R4: =R3 -> 12150 | S4: =R4-R3 -> 0 | T4: =T3 -> 438163 | U4: =V4*S4 -> 0 | V4: 250 | X4: 12192 | Y4: =IF(R4-X4<=0,"ok","oil change") -> ok | Z4: =C4+K4+S4 -> 3 | AA4: =U4+M4+E4 -> 495 | AB4: =V4+N4+F4 -> 415 | AC4: =IF(Z4>0,AA4/Z4,0) -> 165 | AD4: =ELEC!Q4 -> 1996 | AE4: =SUM(AD4/Z4) -> 665.33333 | AF4: =SUM(AE4/1600) -> 0.41583333 | AG4: =SUM(360*AF4) -> 149.7 | AH4: =SUM(AC4-AG4) -> 15.3 | AI4: =AD4*AJ4 -> 513.7384 | AJ4: =305/1185 -> 0.25738397 | AK4: =AI4/Z4 -> 171.24613
A5: =ELEC!C5 -> 44319 | B5: 9906 | C5: =B5-B4 -> 4 | D5: 388259 | E5: =SUM(D5-D4) -> 674 | F5: =IF(C5>0,E5/C5,0) -> 168.5 | H5: =H4 -> 9934 | I5: =IF(B5-H5<=0,"ok","oil change") -> ok | J5: =J4 -> 10698 | K5: =J5-J4 -> 0 | L5: =L4 -> 357691 | M5: =SUM(L5-L4) -> 0 | N5: =IF(K5>0,M5/K5,0) -> 0 | P5: =P4 -> 10873 | Q5: =IF(J5-P5<=0,"ok","oil change") -> ok | R5: =R4 -> 12150 | S5: =R5-R4 -> 0 | T5: =T4 -> 438163 | U5: =V5*S5 -> 0 | V5: 250 | X5: =X4 -> 12192 | Y5: =IF(R5-X5<=0,"ok","oil change") -> ok | Z5: =C5+K5+S5 -> 4 | AA5: =U5+M5+E5 -> 674 | AB5: =V5+N5+F5 -> 418.5 | AC5: =IF(Z5>0,AA5/Z5,0) -> 168.5 | AD5: =ELEC!Q5 -> 3020 | AE5: =SUM(AD5/Z5) -> 755 | AF5: =SUM(AE5/1600) -> 0.471875 | AG5: =SUM(320*AF5) -> 151 | AH5: =SUM(AC5-AG5) -> 17.5 | AI5: =AD5*AJ5 -> 777.29958 | AJ5: =305/1185 -> 0.25738397 | AK5: =AI5/Z5 -> 194.32489
A6: =ELEC!C6 -> 44320 | B6: 9914 | C6: =B6-B5 -> 8 | D6: 389826 | E6: =SUM(D6-D5) -> 1567 | F6: =IF(C6>0,E6/C6,0) -> 195.875 | H6: =H5 -> 9934 | I6: =IF(B6-H6<=0,"ok","oil change") -> ok | J6: =J5 -> 10698 | K6: =J6-J5 -> 0 | L6: =L5 -> 357691 | M6: =SUM(L6-L5) -> 0 | N6: =IF(K6>0,M6/K6,0) -> 0 | P6: =P5 -> 10873 | Q6: =IF(J6-P6<=0,"ok","oil change") -> ok | R6: =R5 -> 12150 | S6: =R6-R5 -> 0 | T6: =T5 -> 438163 | U6: =V6*S6 -> 0 | V6: 250 | X6: =X5 -> 12192 | Y6: =IF(R6-X6<=0,"ok","oil change") -> ok | Z6: =C6+K6+S6 -> 8 | AA6: =U6+M6+E6 -> 1567 | AB6: =V6+N6+F6 -> 445.875 | AC6: =IF(Z6>0,AA6/Z6,0) -> 195.875 | AD6: =ELEC!Q6 -> 4211 | AE6: =SUM(AD6/Z6) -> 526.375 | AF6: =SUM(AE6/1600) -> 0.32898438 | AG6: =SUM(320*AF6) -> 105.275 | AH6: =SUM(AC6-AG6) -> 90.6 | AI6: =AD6*AJ6 -> 1083.8439 | AJ6: =305/1185 -> 0.25738397 | AK6: =AI6/Z6 -> 135.48049
A7: =ELEC!C7 -> 44321 | B7: 9923 | C7: =B7-B6 -> 9 | D7: 391322.9 | E7: =SUM(D7-D6) -> 1496.9 | F7: =IF(C7>0,E7/C7,0) -> 166.32222 | H7: =H6 -> 9934 | I7: =IF(B7-H7<=0,"ok","oil change") -> ok | J7: =J6 -> 10698 | K7: =J7-J6 -> 0 | L7: =L6 -> 357691 | M7: =SUM(L7-L6) -> 0 | N7: =IF(K7>0,M7/K7,0) -> 0 | P7: =P6 -> 10873 | Q7: =IF(J7-P7<=0,"ok","oil change") -> ok | R7: 12150 | S7: =R7-R6 -> 0 | T7: =T6 -> 438163 | U7: =V7*S7 -> 0 | V7: 250 | X7: =X6 -> 12192 | Y7: =IF(R7-X7<=0,"ok","oil change") -> ok | Z7: =C7+K7+S7 -> 9 | AA7: =U7+M7+E7 -> 1496.9 | AB7: =V7+N7+F7 -> 416.32222 | AC7: =IF(Z7>0,AA7/Z7,0) -> 166.32222 | AD7: =ELEC!Q7 -> 5610 | AE7: =SUM(AD7/Z7) -> 623.33333 | AF7: =SUM(AE7/1600) -> 0.38958333 | AH7: =SUM(AC7-AG7) -> #VALUE! | AI7: =AD7*AJ7 -> 1443.9241 | AJ7: =305/1185 -> 0.25738397 | AK7: =AI7/Z7 -> 160.43601
A8: =ELEC!C8 -> 44322 | B8: 9929 | C8: =B8-B7 -> 6 | D8: 392266.5 | E8: =SUM(D8-D7) -> 943.6 | F8: =IF(C8>0,E8/C8,0) -> 157.26667 | H8: =H7 -> 9934 | I8: =IF(B8-H8<=0,"ok","oil change") -> ok | J8: =J7 -> 10698 | K8: =J8-J7 -> 0 | L8: =L7 -> 357691 | M8: =SUM(L8-L7) -> 0 | N8: =IF(K8>0,M8/K8,0) -> 0 | P8: =P7 -> 10873 | Q8: =IF(J8-P8<=0,"ok","oil change") -> ok | R8: =R7 -> 12150 | S8: =R8-R7 -> 0 | T8: =T7 -> 438163 | U8: =V8*S8 -> 0 | V8: 250 | X8: =X7 -> 12192 | Y8: =IF(R8-X8<=0,"ok","oil change") -> ok | Z8: =C8+K8+S8 -> 6 | AA8: =U8+M8+E8 -> 943.6 | AB8: =V8+N8+F8 -> 407.26667 | AC8: =IF(Z8>0,AA8/Z8,0) -> 157.26667 | AD8: =ELEC!Q8 -> 3482 | AE8: =SUM(AD8/Z8) -> 580.33333 | AF8: =SUM(AE8/1600) -> 0.36270833 | AG8: =SUM(320*AF8) -> 116.06667 | AH8: =SUM(AC8-AG8) -> 41.2 | AI8: =AD8*AJ8 -> 896.21097 | AJ8: =305/1185 -> 0.25738397 | AK8: =AI8/Z8 -> 149.3685
A9: =ELEC!C9 -> 44323 | B9: 9937.5 | C9: =B9-B8 -> 8.5 | D9: 394000.4 | E9: =SUM(D9-D8) -> 1733.9 | F9: =IF(C9>0,E9/C9,0) -> 203.98824 | H9: =H8 -> 9934 | I9: =IF(B9-H9<=0,"ok","oil change") -> oil change | J9: =J8 -> 10698 | K9: =J9-J8 -> 0 | L9: =L8 -> 357691 | M9: =SUM(L9-L8) -> 0 | N9: =IF(K9>0,M9/K9,0) -> 0 | P9: =P8 -> 10873 | Q9: =IF(J9-P9<=0,"ok","oil change") -> ok | R9: =R8 -> 12150 | S9: =R9-R8 -> 0 | T9: =T8 -> 438163 | U9: =V9*S9 -> 0 | V9: 250 | X9: =X8 -> 12192 | Y9: =IF(R9-X9<=0,"ok","oil change") -> ok | Z9: =C9+K9+S9 -> 8.5 | AA9: =U9+M9+E9 -> 1733.9 | AB9: =V9+N9+F9 -> 453.98824 | AC9: =IF(Z9>0,AA9/Z9,0) -> 203.98824 | AD9: =ELEC!Q9 -> 5855 | AE9: =SUM(AD9/Z9) -> 688.82353 | AF9: =SUM(AE9/1600) -> 0.43051471 | AG9: =SUM(320*AF9) -> 137.76471 | AH9: =SUM(AC9-AG9) -> 66.223529 | AI9: =AD9*AJ9 -> 1506.9831 | AJ9: 0.25738397 | AK9: =IF(Z9>0,AI9/Z9,0) -> 177.29213
A10: =ELEC!C10 -> 44324 | B10: 9946.1 | C10: =B10-B9 -> 8.6 | D10: 394894 | E10: =SUM(D10-D9) -> 893.6 | F10: =IF(C10>0,E10/C10,0) -> 103.90698 | H10: =H9 -> 9934 | I10: =IF(B10-H10<=0,"ok","oil change") -> oil change | J10: =J9 -> 10698 | K10: =J10-J9 -> 0 | L10: =L9 -> 357691 | M10: =SUM(L10-L9) -> 0 | N10: =IF(K10>0,M10/K10,0) -> 0 | P10: =P9 -> 10873 | Q10: =IF(J10-P10<=0,"ok","oil change") -> ok | R10: =R9 -> 12150 | S10: =R10-R9 -> 0 | T10: =T9 -> 438163 | U10: =V10*S10 -> 0 | V10: 250 | X10: =X9 -> 12192 | Y10: =IF(R10-X10<=0,"ok","oil change") -> ok | Z10: =C10+K10+S10 -> 8.6 | AA10: =U10+M10+E10 -> 893.6 | AB10: =V10+N10+F10 -> 353.90698 | AC10: =IF(Z10>0,AA10/Z10,0) -> 103.90698 | AD10: =ELEC!Q10 -> 5509 | AE10: =SUM(AD10/Z10) -> 640.5814 | AF10: =SUM(AE10/1600) -> 0.40036337 | AG10: =SUM(320*AF10) -> 128.11628 | AH10: =SUM(AC10-AG10) -> -24.209302 | AI10: =AD10*AJ10 -> 1417.9283 | AJ10: =305/1185 -> 0.25738397 | AK10: =IF(Z10>0,AI10/Z10,0) -> 164.87538
A11: =ELEC!C11 -> 44325 | B11: 9955 | C11: =B11-B10 -> 8.9 | D11: 396250 | E11: =SUM(D11-D10) -> 1356 | F11: =IF(C11>0,E11/C11,0) -> 152.35955 | H11: =H10 -> 9934 | I11: =IF(B11-H11<=0,"ok","oil change") -> oil change | J11: =J10 -> 10698 | K11: =J11-J10 -> 0 | L11: =L10 -> 357691 | M11: =SUM(L11-L10) -> 0 | N11: =IF(K11>0,M11/K11,0) -> 0 | P11: =P10 -> 10873 | Q11: =IF(J11-P11<=0,"ok","oil change") -> ok | R11: =R10 -> 12150 | S11: =R11-R10 -> 0 | T11: =T10 -> 438163 | U11: =V11*S11 -> 0 | V11: 250 | X11: =X10 -> 12192 | Y11: =IF(R11-X11<=0,"ok","oil change") -> ok | Z11: =C11+K11+S11 -> 8.9 | AA11: =U11+M11+E11 -> 1356 | AB11: =V11+N11+F11 -> 402.35955 | AC11: =IF(Z11>0,AA11/Z11,0) -> 152.35955 | AD11: =ELEC!Q11 -> 6303 | AE11: =SUM(AD11/Z11) -> 708.20225 | AF11: =SUM(AE11/1600) -> 0.4426264 | AG11: =SUM(320*AF11) -> 141.64045 | AH11: =SUM(AC11-AG11) -> 10.719101 | AI11: =AD11*AJ11 -> 1622.2911 | AJ11: =305/1185 -> 0.25738397 | AK11: =IF(Z11>0,AI11/Z11,0) -> 182.2799
A12: =ELEC!C12 -> 44326 | B12: 9955 | C12: =B12-B11 -> 0 | D12: 396268 | E12: =SUM(D12-D11) -> 18 | F12: =IF(C12>0,E12/C12,0) -> 0 | H12: =H11 -> 9934 | I12: =IF(B12-H12<=0,"ok","oil change") -> oil change | J12: =J11 -> 10698 | K12: =J12-J11 -> 0 | L12: =L11 -> 357691 | M12: =SUM(L12-L11) -> 0 | N12: =IF(K12>0,M12/K12,0) -> 0 | P12: =P11 -> 10873 | Q12: =IF(J12-P12<=0,"ok","oil change") -> ok | R12: 12159 | S12: =R12-R11 -> 9 | T12: 440413 | U12: =V12*S12 -> 2250 | V12: 250 | X12: =X11 -> 12192 | Y12: =IF(R12-X12<=0,"ok","oil change") -> ok | Z12: =C12+K12+S12 -> 9 | AA12: =U12+M12+E12 -> 2268 | AB12: =V12+N12+F12 -> 250 | AC12: =IF(Z12>0,AA12/Z12,0) -> 252 | AD12: =ELEC!Q12 -> 6338 | AE12: =SUM(AD12/Z12) -> 704.22222 | AF12: =SUM(AE12/1600) -> 0.44013889 | AG12: =SUM(320*AF12) -> 140.84444 | AH12: =SUM(AC12-AG12) -> 111.15556 | AI12: =AD12*AJ12 -> 1631.2996 | AJ12: =305/1185 -> 0.25738397 | AK12: =IF(Z12>0,AI12/Z12,0) -> 181.25551
A13: =ELEC!C13 -> 44327 | B13: =B12 -> 9955 | C13: =B13-B12 -> 0 | D13: 396271 | E13: =SUM(D13-D12) -> 3 | F13: =IF(C13>0,E13/C13,0) -> 0 | H13: =H12 -> 9934 | I13: =IF(B13-H13<=0,"ok","oil change") -> oil change | J13: =J12 -> 10698 | K13: =J13-J12 -> 0 | L13: =L12 -> 357691 | M13: =SUM(L13-L12) -> 0 | N13: =IF(K13>0,M13/K13,0) -> 0 | P13: =P12 -> 10873 | Q13: =IF(J13-P13<=0,"ok","oil change") -> ok | R13: 12169 | S13: =R13-R12 -> 10 | T13: =T12 -> 440413 | U13: =V13*S13 -> 2500 | V13: 250 | X13: =X12 -> 12192 | Y13: =IF(R13-X13<=0,"ok","oil change") -> ok | Z13: =C13+K13+S13 -> 10 | AA13: =U13+M13+E13 -> 2503 | AB13: =V13+N13+F13 -> 250 | AC13: =IF(Z13>0,AA13/Z13,0) -> 250.3 | AD13: =ELEC!Q13 -> 5744 | AE13: =SUM(AD13/Z13) -> 574.4 | AF13: =SUM(AE13/1600) -> 0.359 | AG13: =SUM(320*AF13) -> 114.88 | AH13: =SUM(AC13-AG13) -> 135.42 | AI13: =AD13*AJ13 -> 1478.4135 | AJ13: =305/1185 -> 0.25738397 | AK13: =IF(Z13>0,AI13/Z13,0) -> 147.84135
A14: =ELEC!C14 -> 44328 | B14: 9964 | C14: =B14-B13 -> 9 | D14: 397879 | E14: =SUM(D14-D13) -> 1608 | F14: =IF(C14>0,E14/C14,0) -> 178.66667 | H14: =H13 -> 9934 | I14: =IF(B14-H14<=0,"ok","oil change") -> oil change | J14: =J13 -> 10698 | K14: =J14-J13 -> 0 | L14: =L13 -> 357691 | M14: =SUM(L14-L13) -> 0 | N14: =IF(K14>0,M14/K14,0) -> 0 | P14: =P13 -> 10873 | Q14: =IF(J14-P14<=0,"ok","oil change") -> ok | R14: 12172 | S14: =R14-R13 -> 3 | T14: 3669836 | U14: =V14*S14 -> 750 | V14: 250 | X14: =X13 -> 12192 | Y14: =IF(R14-X14<=0,"ok","oil change") -> ok | Z14: =C14+K14+S14 -> 12 | AA14: =U14+M14+E14 -> 2358 | AB14: =V14+N14+F14 -> 428.66667 | AC14: =IF(Z14>0,AA14/Z14,0) -> 196.5 | AD14: =ELEC!Q14 -> 7269 | AE14: =SUM(AD14/Z14) -> 605.75 | AF14: =SUM(AE14/1600) -> 0.37859375 | AG14: =SUM(320*AF14) -> 121.15 | AH14: =SUM(AC14-AG14) -> 75.35 | AI14: =AD14*AJ14 -> 1870.9241 | AJ14: =305/1185 -> 0.25738397 | AK14: =IF(Z14>0,AI14/Z14,0) -> 155.91034
A15: =ELEC!C15 -> 44329 | B15: 9973 | C15: =B15-B14 -> 9 | D15: 398972 | E15: =SUM(D15-D14) -> 1093 | F15: =IF(C15>0,E15/C15,0) -> 121.44444 | H15: =H14 -> 9934 | I15: =IF(B15-H15<=0,"ok","oil change") -> oil change | J15: =J14 -> 10698 | K15: =J15-J14 -> 0 | L15: =L14 -> 357691 | M15: =SUM(L15-L14) -> 0 | N15: =IF(K15>0,M15/K15,0) -> 0 | P15: =P14 -> 10873 | Q15: =IF(J15-P15<=0,"ok","oil change") -> ok | R15: 12172 | S15: =R15-R14 -> 0 | T15: =T14 -> 3669836 | U15: =V15*S15 -> 0 | V15: 250 | X15: =X14 -> 12192 | Y15: =IF(R15-X15<=0,"ok","oil change") -> ok | Z15: =C15+K15+S15 -> 9 | AA15: =U15+M15+E15 -> 1093 | AB15: =V15+N15+F15 -> 371.44444 | AC15: =IF(Z15>0,AA15/Z15,0) -> 121.44444 | AD15: =ELEC!Q15 -> 6705 | AE15: =SUM(AD15/Z15) -> 745 | AF15: =SUM(AE15/1600) -> 0.465625 | AG15: =SUM(320*AF15) -> 149 | AH15: =SUM(AC15-AG15) -> -27.555556 | AI15: =AD15*AJ15 -> 1725.7595 | AJ15: =305/1185 -> 0.25738397 | AK15: =IF(Z15>0,AI15/Z15,0) -> 191.75105
A16: =ELEC!C16 -> 44330 | B16: 9983 | C16: =B16-B15 -> 10 | D16: 400946 | E16: =SUM(D16-D15) -> 1974 | F16: =IF(C16>0,E16/C16,0) -> 197.4 | H16: =H15 -> 9934 | I16: =IF(B16-H16<=0,"ok","oil change") -> oil change | J16: =J15 -> 10698 | K16: =J16-J15 -> 0 | L16: =L15 -> 357691 | M16: =SUM(L16-L15) -> 0 | N16: =IF(K16>0,M16/K16,0) -> 0 | P16: =P15 -> 10873 | Q16: =IF(J16-P16<=0,"ok","oil change") -> ok | R16: 12172 | S16: =R16-R15 -> 0 | T16: =T15 -> 3669836 | U16: =V16*S16 -> 0 | V16: 250 | X16: =X15 -> 12192 | Y16: =IF(R16-X16<=0,"ok","oil change") -> ok | Z16: =C16+K16+S16 -> 10 | AA16: =U16+M16+E16 -> 1974 | AB16: =V16+N16+F16 -> 447.4 | AC16: =IF(Z16>0,AA16/Z16,0) -> 197.4 | AD16: =ELEC!Q16 -> 5385 | AE16: =SUM(AD16/Z16) -> 538.5 | AF16: =SUM(AE16/1600) -> 0.3365625 | AG16: =SUM(320*AF16) -> 107.7 | AH16: =SUM(AC16-AG16) -> 89.7 | AI16: =AD16*AJ16 -> 1386.0127 | AJ16: =305/1185 -> 0.25738397 | AK16: =IF(Z16>0,AI16/Z16,0) -> 138.60127
A17: =ELEC!C17 -> 44331 | B17: 9990 | C17: =B17-B16 -> 7 | D17: 402914 | E17: =SUM(D17-D16) -> 1968 | F17: =IF(C17>0,E17/C17,0) -> 281.14286 | H17: =H16 -> 9934 | I17: =IF(B17-H17<=0,"ok","oil change") -> oil change | J17: =J16 -> 10698 | K17: =J17-J16 -> 0 | L17: =L16 -> 357691 | M17: =SUM(L17-L16) -> 0 | N17: =IF(K17>0,M17/K17,0) -> 0 | P17: =P16 -> 10873 | Q17: =IF(J17-P17<=0,"ok","oil change") -> ok | R17: =R16 -> 12172 | S17: =R17-R16 -> 0 | T17: =T16 -> 3669836 | U17: =V17*S17 -> 0 | V17: 250 | X17: =X16 -> 12192 | Y17: =IF(R17-X17<=0,"ok","oil change") -> ok | Z17: =C17+K17+S17 -> 7 | AA17: =U17+M17+E17 -> 1968 | AB17: =V17+N17+F17 -> 531.14286 | AC17: =IF(Z17>0,AA17/Z17,0) -> 281.14286 | AD17: =ELEC!Q17 -> 6396 | AE17: =SUM(AD17/Z17) -> 913.71429 | AF17: =SUM(AE17/1600) -> 0.57107143 | AG17: =SUM(320*AF17) -> 182.74286 | AH17: =SUM(AC17-AG17) -> 98.4 | AI17: =AD17*AJ17 -> 1646.2278 | AJ17: =305/1185 -> 0.25738397 | AK17: =IF(Z17>0,AI17/Z17,0) -> 235.17541
A18: =ELEC!C18 -> 44332 | B18: 10006 | C18: =B18-B17 -> 16 | D18: 404363.8 | E18: =SUM(D18-D17) -> 1449.8 | F18: =IF(C18>0,E18/C18,0) -> 90.6125 | H18: 10105 | I18: =IF(B18-H18<=0,"ok","oil change") -> ok | J18: =J17 -> 10698 | K18: =J18-J17 -> 0 | L18: =L17 -> 357691 | M18: =SUM(L18-L17) -> 0 | N18: =IF(K18>0,M18/K18,0) -> 0 | P18: =P17 -> 10873 | Q18: =IF(J18-P14<=0,"ok","oil change") -> ok | R18: =R17 -> 12172 | S18: =R18-R17 -> 0 | T18: =T17 -> 3669836 | U18: =V18*S18 -> 0 | V18: 250 | X18: =X17 -> 12192 | Y18: =IF(R18-X18<=0,"ok","oil change") -> ok | Z18: =C18+K18+S18 -> 16 | AA18: =U18+M18+E18 -> 1449.8 | AB18: =V18+N18+F18 -> 340.6125 | AC18: =IF(Z18>0,AA18/Z18,0) -> 90.6125 | AD18: =ELEC!Q18 -> 5025 | AE18: =SUM(AD18/Z18) -> 314.0625 | AF18: =SUM(AE18/1600) -> 0.19628906 | AG18: =SUM(320*AF18) -> 62.8125 | AH18: =SUM(AC18-AG18) -> 27.8 | AI18: =AD18*AJ18 -> 1293.3544 | AJ18: =305/1185 -> 0.25738397 | AK18: =IF(Z18>0,AI18/Z18,0) -> 80.834652
A19: =ELEC!C19 -> 44333 | B19: 10015 | C19: =B19-B18 -> 9 | D19: 405397 | E19: =SUM(D19-D18) -> 1033.2 | F19: =IF(C19>0,E19/C19,0) -> 114.8 | H19: =H18 -> 10105 | I19: =IF(B19-H19<=0,"ok","oil change") -> ok | J19: =J18 -> 10698 | K19: =J19-J18 -> 0 | L19: =L18 -> 357691 | M19: =SUM(L19-L18) -> 0 | N19: =IF(K19>0,M19/K19,0) -> 0 | P19: =P18 -> 10873 | Q19: =IF(J19-P19<=0,"ok","oil change") -> ok | R19: =R18 -> 12172 | S19: =R19-R18 -> 0 | T19: =T18 -> 3669836 | U19: =V19*S19 -> 0 | V19: 250 | X19: =X18 -> 12192 | Y19: =IF(R19-X19<=0,"ok","oil change") -> ok | Z19: =C19+K19+S19 -> 9 | AA19: =U19+M19+E19 -> 1033.2 | AB19: =V19+N19+F19 -> 364.8 | AC19: =IF(Z19>0,AA19/Z19,0) -> 114.8 | AD19: =ELEC!Q19 -> 9392 | AE19: =SUM(AD19/Z19) -> 1043.5556 | AF19: =SUM(AE19/1600) -> 0.65222222 | AG19: =SUM(320*AF19) -> 208.71111 | AH19: =SUM(AC19-AG19) -> -93.911111 | AI19: =AD19*AJ19 -> 2417.3502 | AJ19: =305/1185 -> 0.25738397 | AK19: =IF(Z19>0,AI19/Z19,0) -> 268.59447
A20: =ELEC!C20 -> 44334 | B20: 10026 | C20: =B20-B19 -> 11 | D20: 406672 | E20: =SUM(D20-D19) -> 1275 | F20: =IF(C20>0,E20/C20,0) -> 115.90909 | H20: =H19 -> 10105 | I20: =IF(B20-H20<=0,"ok","oil change") -> ok | J20: =J19 -> 10698 | K20: =J20-J19 -> 0 | L20: =L19 -> 357691 | M20: =SUM(L20-L19) -> 0 | N20: =IF(K20>0,M20/K20,0) -> 0 | P20: =P19 -> 10873 | Q20: =IF(J20-P20<=0,"ok","oil change") -> ok | R20: =R19 -> 12172 | S20: =R20-R19 -> 0 | T20: =T19 -> 3669836 | U20: =V20*S20 -> 0 | V20: 250 | X20: =X19 -> 12192 | Y20: =IF(R20-X20<=0,"ok","oil change") -> ok | Z20: =C20+K20+S20 -> 11 | AA20: =U20+M20+E20 -> 1275 | AB20: =V20+N20+F20 -> 365.90909 | AC20: =IF(Z20>0,AA20/Z20,0) -> 115.90909 | AD20: =ELEC!Q20 -> 8787 | AE20: =SUM(AD20/Z20) -> 798.81818 | AF20: =SUM(AE20/1600) -> 0.49926136 | AG20: =SUM(320*AF20) -> 159.76364 | AH20: =SUM(AC20-AG20) -> -43.854545 | AI20: =AD20*AJ20 -> 2261.6329 | AJ20: =305/1185 -> 0.25738397 | AK20: =IF(Z20>0,AI20/Z20,0) -> 205.60299
A21: =ELEC!C21 -> 44335 | B21: 10042 | C21: =B21-B20 -> 16 | D21: 408288 | E21: =SUM(D21-D20) -> 1616 | F21: =IF(C21>0,E21/C21,0) -> 101 | H21: =H20 -> 10105 | I21: =IF(B21-H21<=0,"ok","oil change") -> ok | J21: =J20 -> 10698 | K21: =J21-J20 -> 0 | L21: =L20 -> 357691 | M21: =SUM(L21-L20) -> 0 | N21: =IF(K21>0,M21/K21,0) -> 0 | P21: =P20 -> 10873 | Q21: =IF(J21-P21<=0,"ok","oil change") -> ok | R21: =R20 -> 12172 | S21: =R21-R20 -> 0 | T21: =T20 -> 3669836 | U21: =V21*S21 -> 0 | V21: 250 | X21: =X20 -> 12192 | Y21: =Y20 -> ok | Z21: =C21+K21+S21 -> 16 | AA21: =U21+M21+E21 -> 1616 | AB21: =V21+N21+F21 -> 351 | AC21: =IF(Z21>0,AA21/Z21,0) -> 101 | AD21: =ELEC!Q21 -> 12246 | AE21: =SUM(AD21/Z21) -> 765.375 | AF21: =SUM(AE21/1600) -> 0.47835937 | AG21: =SUM(320*AF21) -> 153.075 | AH21: =SUM(AC21-AG21) -> -52.075 | AI21: =AD21*AJ21 -> 3151.9241 | AJ21: =305/1185 -> 0.25738397 | AK21: =IF(Z21>0,AI21/Z21,0) -> 196.99525
A22: =ELEC!C22 -> 44336 | B22: 10052 | C22: =B22-B21 -> 10 | D22: 409524 | E22: =150*C22 -> 1500 | F22: =IF(C22>0,E22/C22,0) -> 150 | H22: =H21 -> 10105 | I22: =IF(B22-H22<=0,"ok","oil change") -> ok | J22: =J21 -> 10698 | K22: =J22-J21 -> 0 | L22: =L21 -> 357691 | M22: =SUM(L22-L21) -> 0 | N22: =IF(K22>0,M22/K22,0) -> 0 | P22: =P21 -> 10873 | Q22: =IF(J22-P22<=0,"ok","oil change") -> ok | R22: 12172 | S22: =R22-R21 -> 0 | T22: =T21 -> 3669836 | U22: =V22*S22 -> 0 | V22: 250 | X22: =X21 -> 12192 | Y22: =IF(R22-X22<=0,"ok","oil change") -> ok | Z22: =C22+K22+S22 -> 10 | AA22: =U22+M22+E22 -> 1500 | AB22: =V22+N22+F22 -> 400 | AC22: =IF(Z22>0,AA22/Z22,0) -> 150 | AD22: =ELEC!Q22 -> 7337 | AE22: =SUM(AD22/Z22) -> 733.7 | AF22: =SUM(AE22/1600) -> 0.4585625 | AG22: =SUM(320*AF22) -> 146.74 | AH22: =SUM(AC22-AG22) -> 3.26 | AI22: =AD22*AJ22 -> 1888.4262 | AJ22: =305/1185 -> 0.25738397 | AK22: =IF(Z22>0,AI22/Z22,0) -> 188.84262
A23: =ELEC!C23 -> 44337 | B23: 10054 | C23: =B23-B22 -> 2 | D23: 409912 | E23: =150*C23 -> 300 | F23: =IF(C23>0,E23/C23,0) -> 150 | H23: =H22 -> 10105 | I23: =IF(B23-H23<=0,"ok","oil change") -> ok | J23: =J22 -> 10698 | K23: =J23-J22 -> 0 | L23: =L22 -> 357691 | M23: =SUM(L23-L22) -> 0 | N23: =IF(K23>0,M23/K23,0) -> 0 | P23: =P22 -> 10873 | Q23: =IF(J23-P23<=0,"ok","oil change") -> ok | R23: 12182 | S23: =R23-R22 -> 10 | T23: 369837 | U23: =V23*S23 -> 2500 | V23: 250 | X23: =X22 -> 12192 | Y23: =IF(R23-X23<=0,"ok","oil change") -> ok | Z23: =C23+K23+S23 -> 12 | AA23: =U23+M23+E23 -> 2800 | AB23: =V23+N23+F23 -> 400 | AC23: =IF(Z23>0,AA23/Z23,0) -> 233.33333 | AD23: =ELEC!Q23 -> 7952 | AE23: =SUM(AD23/Z23) -> 662.66667 | AF23: =SUM(AE23/1600) -> 0.41416667 | AG23: =SUM(320*AF23) -> 132.53333 | AH23: =SUM(AC23-AG23) -> 100.8 | AI23: =AD23*AJ23 -> 2046.7173 | AJ23: =305/1185 -> 0.25738397 | AK23: =IF(Z23>0,AI23/Z23,0) -> 170.55977
A24: =ELEC!C24 -> 44338 | B24: 10054 | C24: =B24-B23 -> 0 | D24: =D23 -> 409912 | E24: =SUM(D24-D23) -> 0 | F24: =IF(C24>0,E24/C24,0) -> 0 | H24: =H23 -> 10105 | I24: =IF(B24-H24<=0,"ok","oil change") -> ok | J24: =J23 -> 10698 | K24: =J24-J23 -> 0 | L24: =L23 -> 357691 | M24: =SUM(L24-L23) -> 0 | N24: =IF(K24>0,M24/K24,0) -> 0 | P24: =P23 -> 10873 | Q24: =IF(J24-P24<=0,"ok","oil change") -> ok | R24: 12198 | S24: =R24-R23 -> 16 | T24: 373837 | U24: =V24*S24 -> 4000 | V24: 250 | X24: =X23 -> 12192 | Y24: =IF(R24-X24<=0,"ok","oil change") -> oil change | Z24: =C24+K24+S24 -> 16 | AA24: =U24+M24+E24 -> 4000 | AB24: =V24+N24+F24 -> 250 | AC24: =IF(Z24>0,AA24/Z24,0) -> 250 | AD24: =ELEC!Q24 -> 10547 | AE24: =SUM(AD24/Z24) -> 659.1875 | AF24: =SUM(AE24/1600) -> 0.41199219 | AG24: =SUM(320*AF24) -> 131.8375 | AH24: =SUM(AC24-AG24) -> 118.1625 | AI24: =AD24*AJ24 -> 2714.6287 | AJ24: =305/1185 -> 0.25738397 | AK24: =IF(Z24>0,AI24/Z24,0) -> 169.66429
A25: =ELEC!C25 -> 44339 | B25: =B24 -> 10054 | C25: =B25-B24 -> 0 | D25: =D24 -> 409912 | E25: =SUM(D25-D24) -> 0 | F25: =IF(C25>0,E25/C25,0) -> 0 | H25: =H24 -> 10105 | I25: =IF(B25-H25<=0,"ok","oil change") -> ok | J25: =J24 -> 10698 | K25: =J25-J24 -> 0 | L25: =L24 -> 357691 | M25: =SUM(L25-L24) -> 0 | N25: =IF(K25>0,M25/K25,0) -> 0 | P25: =P24 -> 10873 | Q25: =IF(J25-P25<=0,"ok","oil change") -> ok | R25: 12206 | S25: =R25-R24 -> 8 | T25: 375837 | U25: =V25*S25 -> 2000 | V25: 250 | X25: =X24 -> 12192 | Y25: =IF(R25-X25<=0,"ok","oil change") -> oil change | Z25: =C25+K25+S25 -> 8 | AA25: =U25+M25+E25 -> 2000 | AB25: =V25+N25+F25 -> 250 | AC25: =IF(Z25>0,AA25/Z25,0) -> 250 | AD25: =ELEC!Q25 -> 5535 | AE25: =SUM(AD25/Z25) -> 691.875 | AF25: =SUM(AE25/1600) -> 0.43242187 | AG25: =SUM(320*AF25) -> 138.375 | AH25: =SUM(AC25-AG25) -> 111.625 | AI25: =AD25*AJ25 -> 1424.6203 | AJ25: =305/1185 -> 0.25738397 | AK25: =IF(Z25>0,AI25/Z25,0) -> 178.07753
A26: =ELEC!C26 -> 44340 | B26: =B25 -> 10054 | C26: =B26-B25 -> 0 | D26: =D25 -> 409912 | E26: =SUM(D26-D25) -> 0 | F26: =IF(C26>0,E26/C26,0) -> 0 | H26: =H25 -> 10105 | I26: =IF(B26-H26<=0,"ok","oil change") -> ok | J26: =J25 -> 10698 | K26: =J26-J25 -> 0 | L26: =L25 -> 357691 | M26: =SUM(L26-L25) -> 0 | N26: =IF(K26>0,M26/K26,0) -> 0 | P26: =P25 -> 10873 | Q26: =IF(J26-P26<=0,"ok","oil change") -> ok | R26: 12223 | S26: =R26-R25 -> 17 | T26: 380087 | U26: =V26*S26 -> 4250 | V26: 250 | X26: =X25 -> 12192 | Y26: =IF(R26-X26<=0,"ok","oil change") -> oil change | Z26: =C26+K26+S26 -> 17 | AA26: =U26+M26+E26 -> 4250 | AB26: =V26+N26+F26 -> 250 | AC26: =IF(Z26>0,AA26/Z26,0) -> 250 | AD26: =ELEC!Q26 -> 12454 | AE26: =SUM(AD26/Z26) -> 732.58824 | AF26: =SUM(AE26/1600) -> 0.45786765 | AG26: =SUM(320*AF26) -> 146.51765 | AH26: =SUM(AC26-AG26) -> 103.48235 | AI26: =AD26*AJ26 -> 3205.4599 | AJ26: =305/1185 -> 0.25738397 | AK26: =IF(Z26>0,AI26/Z26,0) -> 188.55647
A27: =ELEC!C27 -> 44341 | B27: 10054 | C27: =B27-B26 -> 0 | D27: =D26 -> 409912 | E27: =SUM(D27-D26) -> 0 | F27: =IF(C27>0,E27/C27,0) -> 0 | H27: =H26 -> 10105 | I27: =IF(B27-H27<=0,"ok","oil change") -> ok | J27: =J26 -> 10698 | K27: =J27-J26 -> 0 | L27: =L26 -> 357691 | M27: =SUM(L27-L26) -> 0 | N27: =IF(K27>0,M27/K27,0) -> 0 | P27: =P26 -> 10873 | Q27: =IF(J27-P27<=0,"ok","oil change") -> ok | R27: 12232 | S27: =R27-R26 -> 9 | T27: =T26 -> 380087 | U27: =V27*S27 -> 2250 | V27: 250 | X27: 12342 | Y27: =IF(R27-X27<=0,"ok","oil change") -> ok | Z27: =C27+K27+S27 -> 9 | AA27: =U27+M27+E27 -> 2250 | AB27: =V27+N27+F27 -> 250 | AC27: =IF(Z27>0,AA27/Z27,0) -> 250 | AD27: =ELEC!Q27 -> 6175 | AE27: =SUM(AD27/Z27) -> 686.11111 | AF27: =SUM(AE27/1600) -> 0.42881944 | AG27: =SUM(320*AF27) -> 137.22222 | AH27: =SUM(AC27-AG27) -> 112.77778 | AI27: =AD27*AJ27 -> 1589.346 | AJ27: =305/1185 -> 0.25738397 | AK27: =IF(Z27>0,AI27/Z27,0) -> 176.594
A28: =ELEC!C28 -> 44342 | B28: 10064 | C28: =B28-B27 -> 10 | D28: 411327 | E28: =SUM(D28-D27) -> 1415 | F28: =IF(C28>0,E28/C28,0) -> 141.5 | H28: =H27 -> 10105 | I28: =IF(B28-H28<=0,"ok","oil change") -> ok | J28: =J27 -> 10698 | K28: =J28-J27 -> 0 | L28: =L27 -> 357691 | M28: =SUM(L28-L27) -> 0 | N28: =IF(K28>0,M28/K28,0) -> 0 | P28: =P27 -> 10873 | Q28: =IF(J28-P28<=0,"ok","oil change") -> ok | R28: 12240 | S28: =R28-R27 -> 8 | T28: 382087 | U28: =V28*S28 -> 2000 | V28: 250 | X28: =X27 -> 12342 | Y28: =IF(R28-X28<=0,"ok","oil change") -> ok | Z28: =C28+K28+S28 -> 18 | AA28: =U28+M28+E28 -> 3415 | AB28: =V28+N28+F28 -> 391.5 | AC28: =IF(Z28>0,AA28/Z28,0) -> 189.72222 | AD28: =ELEC!Q28 -> 13086 | AE28: =SUM(AD28/Z28) -> 727 | AF28: =SUM(AE28/1600) -> 0.454375 | AG28: =SUM(320*AF28) -> 145.4 | AH28: =SUM(AC28-AG28) -> 44.322222 | AI28: =AD28*AJ28 -> 3368.1266 | AJ28: =305/1185 -> 0.25738397 | AK28: =IF(Z28>0,AI28/Z28,0) -> 187.11814
A29: =ELEC!C29 -> 44343 | B29: 10077 | C29: =B29-B28 -> 13 | D29: 412973 | E29: =SUM(D29-D28) -> 1646 | F29: =IF(C29>0,E29/C29,0) -> 126.61538 | H29: =H28 -> 10105 | I29: =IF(B29-H29<=0,"ok","oil change") -> ok | J29: =J28 -> 10698 | K29: =J29-J28 -> 0 | L29: =L28 -> 357691 | M29: =SUM(L29-L28) -> 0 | N29: =IF(K29>0,M29/K29,0) -> 0 | P29: =P28 -> 10873 | Q29: =IF(J29-P29<=0,"ok","oil change") -> ok | R29: =R28 -> 12240 | S29: =R29-R28 -> 0 | T29: =T28 -> 382087 | U29: =V29*S29 -> 0 | V29: 250 | X29: =X28 -> 12342 | Y29: =IF(R29-X29<=0,"ok","oil change") -> ok | Z29: =C29+K29+S29 -> 13 | AA29: =U29+M29+E29 -> 1646 | AB29: =V29+N29+F29 -> 376.61538 | AC29: =IF(Z29>0,AA29/Z29,0) -> 126.61538 | AD29: =ELEC!Q29 -> 9436 | AE29: =SUM(AD29/Z29) -> 725.84615 | AF29: =SUM(AE29/1600) -> 0.45365385 | AG29: =SUM(320*AF29) -> 145.16923 | AH29: =SUM(AC29-AG29) -> -18.553846 | AI29: =AD29*AJ29 -> 2428.6751 | AJ29: =305/1185 -> 0.25738397 | AK29: =IF(Z29>0,AI29/Z29,0) -> 186.82116
A30: =ELEC!C30 -> 44344 | B30: =B29 -> 10077 | C30: =B30-B29 -> 0 | D30: =D29 -> 412973 | E30: =SUM(D30-D29) -> 0 | F30: =IF(C30>0,E30/C30,0) -> 0 | H30: =H29 -> 10105 | I30: =IF(B30-H30<=0,"ok","oil change") -> ok | J30: =J29 -> 10698 | K30: =J30-J29 -> 0 | L30: =L29 -> 357691 | M30: =SUM(L30-L29) -> 0 | N30: =IF(K30>0,M30/K30,0) -> 0 | P30: =P29 -> 10873 | Q30: =IF(J30-P30<=0,"ok","oil change") -> ok | R30: =R29 -> 12240 | S30: =R30-R29 -> 0 | T30: =T29 -> 382087 | U30: =V30*S30 -> 0 | V30: 250 | X30: =X29 -> 12342 | Y30: =IF(R30-X30<=0,"ok","oil change") -> ok | Z30: =C30+K30+S30 -> 0 | AA30: =U30+M30+E30 -> 0 | AB30: =V30+N30+F30 -> 250 | AC30: =IF(Z30>0,AA30/Z30,0) -> 0 | AD30: =ELEC!Q30 -> 0 | AE30: =SUM(AD30/Z30) -> #DIV/0! | AF30: =SUM(AE30/1600) -> #DIV/0! | AG30: =SUM(320*AF30) -> #DIV/0! | AH30: =SUM(AC30-AG30) -> #DIV/0! | AI30: =AD30*AJ30 -> 0 | AJ30: =305/1185 -> 0.25738397 | AK30: =IF(Z30>0,AI30/Z30,0) -> 0
A31: =ELEC!C31 -> 44345 | B31: =B30 -> 10077 | C31: =B31-B30 -> 0 | D31: =D30 -> 412973 | E31: =SUM(D31-D30) -> 0 | F31: =IF(C31>0,E31/C31,0) -> 0 | H31: =H30 -> 10105 | I31: =IF(B31-H31<=0,"ok","oil change") -> ok | J31: =J30 -> 10698 | K31: =J31-J30 -> 0 | L31: =L30 -> 357691 | M31: =SUM(L31-L30) -> 0 | N31: =IF(K31>0,M31/K31,0) -> 0 | P31: =P30 -> 10873 | Q31: =IF(J31-P31<=0,"ok","oil change") -> ok | R31: =R30 -> 12240 | S31: =R31-R30 -> 0 | T31: =T30 -> 382087 | U31: =V31*S31 -> 0 | V31: 250 | X31: =X30 -> 12342 | Y31: =IF(R31-X31<=0,"ok","oil change") -> ok | Z31: =C31+K31+S31 -> 0 | AA31: =U31+M31+E31 -> 0 | AB31: =V31+N31+F31 -> 250 | AC31: =IF(Z31>0,AA31/Z31,0) -> 0 | AD31: =ELEC!Q31 -> 0 | AE31: =SUM(AD31/Z31) -> #DIV/0! | AF31: =SUM(AE31/1600) -> #DIV/0! | AG31: =SUM(320*AF31) -> #DIV/0! | AH31: =SUM(AC31-AG31) -> #DIV/0! | AI31: =AD31*AJ31 -> 0 | AJ31: =305/1185 -> 0.25738397 | AK31: =IF(Z31>0,AI31/Z31,0) -> 0
A32: =ELEC!C32 -> 44346 | B32: =B31 -> 10077 | C32: =B32-B31 -> 0 | D32: =D31 -> 412973 | E32: =SUM(D32-D31) -> 0 | F32: =IF(C32>0,E32/C32,0) -> 0 | H32: =H31 -> 10105 | I32: =IF(B32-H32<=0,"ok","oil change") -> ok | J32: =J31 -> 10698 | K32: =J32-J31 -> 0 | L32: =L31 -> 357691 | M32: =SUM(L32-L31) -> 0 | N32: =IF(K32>0,M32/K32,0) -> 0 | P32: =P31 -> 10873 | Q32: =IF(J32-P32<=0,"ok","oil change") -> ok | R32: =R31 -> 12240 | S32: =R32-R31 -> 0 | T32: =T31 -> 382087 | U32: =V32*S32 -> 0 | V32: 250 | X32: =X31 -> 12342 | Y32: =IF(R32-X32<=0,"ok","oil change") -> ok | Z32: =C32+K32+S32 -> 0 | AA32: =U32+M32+E32 -> 0 | AB32: =V32+N32+F32 -> 250 | AC32: =IF(Z32>0,AA32/Z32,0) -> 0 | AD32: =ELEC!Q32 -> 0 | AE32: =SUM(AD32/Z32) -> #DIV/0! | AF32: =SUM(AE32/1600) -> #DIV/0! | AG32: =SUM(320*AF32) -> #DIV/0! | AH32: =SUM(AC32-AG32) -> #DIV/0! | AI32: =AD32*AJ32 -> 0 | AJ32: =305/1185 -> 0.25738397 | AK32: =IF(Z32>0,AI32/Z32,0) -> 0
A33: =ELEC!C33 -> 44347 | B33: =B32 -> 10077 | C33: =B33-B32 -> 0 | D33: =D32 -> 412973 | E33: =SUM(D33-D32) -> 0 | F33: =IF(C33>0,E33/C33,0) -> 0 | H33: =H32 -> 10105 | I33: =IF(B33-H33<=0,"ok","oil change") -> ok | J33: =J32 -> 10698 | K33: =J33-J32 -> 0 | L33: =L32 -> 357691 | M33: =SUM(L33-L32) -> 0 | N33: =IF(K33>0,M33/K33,0) -> 0 | P33: =P32 -> 10873 | Q33: =IF(J33-P33<=0,"ok","oil change") -> ok | R33: =R32 -> 12240 | S33: =R33-R32 -> 0 | T33: =T32 -> 382087 | U33: =V33*S33 -> 0 | V33: 250 | X33: =X32 -> 12342 | Y33: =IF(R33-X33<=0,"ok","oil change") -> ok | Z33: =C33+K33+S33 -> 0 | AA33: =U33+M33+E33 -> 0 | AB33: =V33+N33+F33 -> 250 | AC33: =IF(Z33>0,AA33/Z33,0) -> 0 | AD33: =ELEC!Q33 -> 0 | AE33: =SUM(AD33/Z33) -> #DIV/0! | AF33: =SUM(AE33/1600) -> #DIV/0! | AG33: =SUM(320*AF33) -> #DIV/0! | AH33: =SUM(AC33-AG33) -> #DIV/0! | AI33: =AD33*AJ33 -> 0 | AJ33: =305/1185 -> 0.25738397 | AK33: =IF(Z33>0,AI33/Z33,0) -> 0
P34: =+O34/3 -> 0 | U34: =SUM(C35:S35) -> 274 | X34: 341 | Z34: =SUM(Z3:Z33) -> 274
C35: =SUM(C3:C33) -> 184 | K35: =SUM(K3:K33) -> 0 | S35: =SUM(S3:S33) -> 90

Sheet tanks
B2: Tank 1 | D2: Tank 2 | F2: Tank 3 | H2: Tank 4 | J2: Tank 5 | L2: Tank 6 | N2: Tank 7 | P2: Tank 8 | R2: Tank 9 | T2: Tank 10 | V2: Tank 11 | Z2: Tank 1 | AB2: Tank 2 | AD2: Tank 3 | AF2: Tank 4 | AH2: Tank 5 | AJ2: Tank 6 | AL2: Tank 7
B3: 6670 | D3: =SUM(B3) -> 6670 | F3: =SUM(D3) -> 6670 | H3: =SUM(F3) -> 6670 | J3: =SUM(H3) -> 6670 | L3: =SUM(J3) -> 6670 | N3: =SUM(L3) -> 6670 | P3: =SUM(N3) -> 6670 | R3: =SUM(P3) -> 6670 | T3: =SUM(R3) -> 6670 | V3: =SUM(T3) -> 6670 | W3: =SUM(B3:V3) -> 73370 | Z3: 2800 | AB3: 2800 | AD3: 2800 | AF3: 2800 | AH3: 2800 | AJ3: 2800 | AL3: 2800 | AM3: =SUM(Z3:AL3) -> 19600 | AO3: =SUM(AM3+W3) -> 92970 | AR3: Total sotck | AS3: Diesel Cons Per day | AT3: Diesel Delivery | BE3: Genset Co | BF3: Steam | BG3: Boil | BH3: Outdoor temperature
B4: =B3/310 -> 21.516129 | D4: =SUM(B4) -> 21.516129 | F4: =SUM(D4) -> 21.516129 | H4: =SUM(F4) -> 21.516129 | J4: =SUM(H4) -> 21.516129 | L4: =SUM(J4) -> 21.516129 | N4: =SUM(L4) -> 21.516129 | P4: =SUM(N4) -> 21.516129 | R4: =SUM(P4) -> 21.516129 | T4: =SUM(R4) -> 21.516129 | V4: =SUM(T4) -> 21.516129 | Z4: =Z3/280 -> 10 | AA4: =AA3/280 -> 0 | AB4: =AB3/280 -> 10 | AC4: =AC3/280 -> 0 | AD4: =AD3/280 -> 10 | AE4: =AE3/280 -> 0 | AF4: =AF3/280 -> 10 | AG4: =AG3/280 -> 0 | ... AL4: =AL3/280 -> 10 | AT4: Delivery | AU4: Cost /L | AW4: Boiler+Steam | AX4: Generator | AZ4: Occupancy | BA4: AVE TEPM | BB4: AVE Humidity
A5: =ELEC!C2 -> 44316 | B5: 239 | C5: 5142.3548 | D5: 239 | E5: 5142.3548 | F5: 239 | G5: 5142.3548 | H5: 239 | I5: 5142.3548 | J5: 239 | K5: 5142.3548 | L5: 239 | M5: 5142.3548 | N5: 239 | O5: 5142.3548 | P5: 239 | Q5: 5142.3548 | R5: 239 | S5: 5142.3548 | T5: 239 | U5: 5142.3548 | V5: 239 | W5: 5142.3548 | X5: 0.77096774 | Y5: 56565.903 | Z5: 245 | AA5: 2450 | AB5: 245 | AC5: 2450 | AD5: 245 | AE5: 2450 | AF5: 245 | AG5: 2450 | AH5: 245 | AI5: 2450 | AJ5: 245 | AK5: 2450 | AL5: 245 | AM5: 2450 | AN5: 0.875 | AO5: 17150 | AQ5: 0.79289989 | AR5: 73715.903 | AS5: 0 | AV5: =[4]tanks!AV35 -> 0.92 | AW5: =[4]tanks!AW35 -> -169 | AX5: =[4]tanks!AX35 -> -1434.3871 | AY5: =[4]tanks!AY35 -> -1603.3871 | AZ5: =[4]tanks!AZ35 -> 0 | BA5: =[4]tanks!BA35 -> 23 | BB5: =[4]tanks!BB35 -> 0.56 | BC5: =[5]tanks!BC36 -> 0 | BD5: =[5]tanks!BD36 -> 19222 | BE5: =[5]tanks!BE36 -> #REF! | BF5: =[5]tanks!BF36 -> 0 | BG5: =[5]tanks!BG36 -> #REF! | BH5: =[6]tanks!BH36 -> 0
A6: =ELEC!C3 -> 44317 | B6: ='B5'!B5 -> 234 | C6: =B6*$B$4 -> 5034.7742 | D6: =SUM(B6) -> 234 | E6: =D6*$B$4 -> 5034.7742 | F6: =SUM(D6) -> 234 | G6: =F6*$B$4 -> 5034.7742 | H6: =SUM(F6) -> 234 | I6: =H6*$B$4 -> 5034.7742 | J6: =SUM(H6) -> 234 | K6: =J6*$B$4 -> 5034.7742 | L6: =SUM(J6) -> 234 | M6: =L6*$B$4 -> 5034.7742 | N6: =SUM(L6) -> 234 | O6: =N6*$B$4 -> 5034.7742 | P6: =SUM(N6) -> 234 | Q6: =P6*$B$4 -> 5034.7742 | R6: =SUM(P6) -> 234 | S6: =R6*$B$4 -> 5034.7742 | T6: =SUM(R6) -> 234 | U6: =T6*$B$4 -> 5034.7742 | V6: =SUM(T6) -> 234 | W6: =V6*$B$4 -> 5034.7742 | X6: =SUM(Y6/73370) -> 0.75483871 | Y6: =SUM(C6+E6+G6+I6+K6+M6+O6+Q6+S6+U6+W6) -> 55382.516 | Z6: ='B5'!C5 -> 240 | AA6: =SUM(Z6*$Z$4) -> 2400 | AB6: =SUM(Z6) -> 240 | AC6: =SUM(AB6*$Z$4) -> 2400 | AD6: =SUM(AB6) -> 240 | AE6: =SUM(AD6*$Z$4) -> 2400 | AF6: =SUM(AD6) -> 240 | AG6: =SUM(AF6*$Z$4) -> 2400 | AH6: =SUM(AF6) -> 240 | AI6: =SUM(AH6*$Z$4) -> 2400 | AJ6: =SUM(AH6) -> 240 | AK6: =SUM(AJ6*$Z$4) -> 2400 | AL6: =SUM(AJ6) -> 240 | AM6: =SUM(AL6*$Z$4) -> 2400 | AN6: =SUM(AO6/19600) -> 0.85714286 | AO6: =SUM(AA6+AC6+AE6+AG6+AI6+AK6+AM6) -> 16800 | AQ6: =SUM(AR6/92970) -> 0.77640654 | AR6: =Y6+AO6 -> 72182.516 | AS6: =SUM(AR6-AR5-AT6) -> -1533.3871 | AV6: =IF(AT6>0,AU6,AV5) -> 0.92 | AW6: =-SUM('B5'!AI5) -> -195 | AX6: =-SUM(AW6-AS6) -> -1338.3871 | AY6: =SUM(AX6+AW6) -> -1533.3871 | AZ6: =ELEC!A3 -> 0 | BA6: ='General information '!D6 -> 23.5 | BB6: =SUM('General information '!E6) -> 0.65 | BC6: =IF(AR3>=AR6,0,1) -> 0 | BD6: 19222 | BE6: =(305/1185)*ELEC!Q4 -> 513.7384 | BG6: =#REF!-BE6 -> #REF! | BH6: 21 | BI6: 12 | BJ6: =AX6/BI6 -> -111.53226 | BK6: =GEN!AF3 -> 0.4090625
A7: =ELEC!C4 -> 44318 | B7: ='B5'!B6 -> 231 | C7: =B7*$B$4 -> 4970.2258 | D7: =SUM(B7) -> 231 | E7: =D7*$B$4 -> 4970.2258 | F7: =SUM(D7) -> 231 | G7: =F7*$B$4 -> 4970.2258 | H7: =SUM(F7) -> 231 | I7: =H7*$B$4 -> 4970.2258 | J7: =SUM(H7) -> 231 | K7: =J7*$B$4 -> 4970.2258 | L7: =SUM(J7) -> 231 | M7: =L7*$B$4 -> 4970.2258 | N7: =SUM(L7) -> 231 | O7: =N7*$B$4 -> 4970.2258 | P7: =SUM(N7) -> 231 | Q7: =P7*$B$4 -> 4970.2258 | R7: =SUM(P7) -> 231 | S7: =R7*$B$4 -> 4970.2258 | T7: =SUM(R7) -> 231 | U7: =T7*$B$4 -> 4970.2258 | V7: =SUM(T7) -> 231 | W7: =V7*$B$4 -> 4970.2258 | X7: =SUM(Y7/73370) -> 0.74516129 | Y7: =SUM(C7+E7+G7+I7+K7+M7+O7+Q7+S7+U7+W7) -> 54672.484 | Z7: ='B5'!C6 -> 238 | AA7: =SUM(Z7*$Z$4) -> 2380 | AB7: =SUM(Z7) -> 238 | AC7: =SUM(AB7*$Z$4) -> 2380 | AD7: =SUM(AB7) -> 238 | AE7: =SUM(AD7*$Z$4) -> 2380 | AF7: =SUM(AD7) -> 238 | AG7: =SUM(AF7*$Z$4) -> 2380 | AH7: =SUM(AF7) -> 238 | AI7: =SUM(AH7*$Z$4) -> 2380 | AJ7: =SUM(AH7) -> 238 | AK7: =SUM(AJ7*$Z$4) -> 2380 | AL7: =SUM(AJ7) -> 238 | AM7: =SUM(AL7*$Z$4) -> 2380 | AN7: =SUM(AO7/19600) -> 0.85 | AO7: =SUM(AA7+AC7+AE7+AG7+AI7+AK7+AM7) -> 16660 | AQ7: =SUM(AR7/92970) -> 0.76726346 | AR7: =Y7+AO7 -> 71332.484 | AS7: =SUM(AR7-AR6-AT7) -> -850.03226 | AV7: =IF(AT7>0,AU7,AV6) -> 0.92 | AW7: =-SUM('B5'!AI6) -> -153 | AX7: =-SUM(AW7-AS7) -> -697.03226 | AY7: =SUM(AX7+AW7) -> -850.03226 | AZ7: =ELEC!A4 -> 0 | BA7: ='General information '!D7 -> 23 | BB7: =SUM('General information '!E7) -> 0.67 | BC7: 0 | BD7: 19222 | BE7: =(305/1185)*ELEC!Q5 -> 777.29958 | BG7: =#REF!-BE7 -> #REF! | BH7: 19 | BI7: 15 | BJ7: =AX7/BI7 -> -46.468817 | BK7: =GEN!AF4 -> 0.41583333
A8: =ELEC!C5 -> 44319 | B8: ='B5'!B7 -> 228 | C8: =B8*$B$4 -> 4905.6774 | D8: =SUM(B8) -> 228 | E8: =D8*$B$4 -> 4905.6774 | F8: =SUM(D8) -> 228 | G8: =F8*$B$4 -> 4905.6774 | H8: =SUM(F8) -> 228 | I8: =H8*$B$4 -> 4905.6774 | J8: =SUM(H8) -> 228 | K8: =J8*$B$4 -> 4905.6774 | L8: =SUM(J8) -> 228 | M8: =L8*$B$4 -> 4905.6774 | N8: =SUM(L8) -> 228 | O8: =N8*$B$4 -> 4905.6774 | P8: =SUM(N8) -> 228 | Q8: =P8*$B$4 -> 4905.6774 | R8: =SUM(P8) -> 228 | S8: =R8*$B$4 -> 4905.6774 | T8: =SUM(R8) -> 228 | U8: =T8*$B$4 -> 4905.6774 | V8: =SUM(T8) -> 228 | W8: =V8*$B$4 -> 4905.6774 | X8: =SUM(Y8/73370) -> 0.73548387 | Y8: =SUM(C8+E8+G8+I8+K8+M8+O8+Q8+S8+U8+W8) -> 53962.452 | Z8: ='B5'!C7 -> 234 | AA8: =SUM(Z8*$Z$4) -> 2340 | AB8: =SUM(Z8) -> 234 | AC8: =SUM(AB8*$Z$4) -> 2340 | AD8: =SUM(AB8) -> 234 | AE8: =SUM(AD8*$Z$4) -> 2340 | AF8: =SUM(AD8) -> 234 | AG8: =SUM(AF8*$Z$4) -> 2340 | AH8: =SUM(AF8) -> 234 | AI8: =SUM(AH8*$Z$4) -> 2340 | AJ8: =SUM(AH8) -> 234 | AK8: =SUM(AJ8*$Z$4) -> 2340 | AL8: =SUM(AJ8) -> 234 | AM8: =SUM(AL8*$Z$4) -> 2340 | AN8: =SUM(AO8/19600) -> 0.83571429 | AO8: =SUM(AA8+AC8+AE8+AG8+AI8+AK8+AM8) -> 16380 | AQ8: =SUM(AR8/92970) -> 0.75661452 | AR8: =Y8+AO8 -> 70342.452 | AS8: =SUM(AR8-AR7-AT8) -> -990.03226 | AV8: =IF(AT8>0,AU8,AV7) -> 0.92 | AW8: =-SUM('B5'!AI7) -> -141 | AX8: =-SUM(AW8-AS8) -> -849.03226 | AY8: =SUM(AX8+AW8) -> -990.03226 | AZ8: =ELEC!A5 -> 0 | BA8: ='General information '!D8 -> 24 | BB8: =SUM('General information '!E8) -> 0.65 | BC8: =IF(AR7>=AR8,0,1) -> 0 | BD8: 19222 | BE8: =(305/1185)*ELEC!Q6 -> 1083.8439 | BG8: =#REF!-BE8 -> #REF! | BH8: 16 | BI8: 9 | BJ8: =AX8/BI8 -> -94.336918 | BK8: =GEN!AF5 -> 0.471875
A9: =ELEC!C6 -> 44320 | B9: ='B5'!B8 -> 222 | C9: =B9*$B$4 -> 4776.5806 | D9: =SUM(B9) -> 222 | E9: =D9*$B$4 -> 4776.5806 | F9: =SUM(D9) -> 222 | G9: =F9*$B$4 -> 4776.5806 | H9: =SUM(F9) -> 222 | I9: =H9*$B$4 -> 4776.5806 | J9: =SUM(H9) -> 222 | K9: =J9*$B$4 -> 4776.5806 | L9: =SUM(J9) -> 222 | M9: =L9*$B$4 -> 4776.5806 | N9: =SUM(L9) -> 222 | O9: =N9*$B$4 -> 4776.5806 | P9: =SUM(N9) -> 222 | Q9: =P9*$B$4 -> 4776.5806 | R9: =SUM(P9) -> 222 | S9: =R9*$B$4 -> 4776.5806 | T9: =SUM(R9) -> 222 | U9: =T9*$B$4 -> 4776.5806 | V9: =SUM(T9) -> 222 | W9: =V9*$B$4 -> 4776.5806 | X9: =SUM(Y9/73370) -> 0.71612903 | Y9: =SUM(C9+E9+G9+I9+K9+M9+O9+Q9+S9+U9+W9) -> 52542.387 | Z9: ='B5'!C8 -> 229 | AA9: =SUM(Z9*$Z$4) -> 2290 | AB9: =SUM(Z9) -> 229 | AC9: =SUM(AB9*$Z$4) -> 2290 | AD9: =SUM(AB9) -> 229 | AE9: =SUM(AD9*$Z$4) -> 2290 | AF9: =SUM(AD9) -> 229 | AG9: =SUM(AF9*$Z$4) -> 2290 | AH9: =SUM(AF9) -> 229 | AI9: =SUM(AH9*$Z$4) -> 2290 | AJ9: =SUM(AH9) -> 229 | AK9: =SUM(AJ9*$Z$4) -> 2290 | AL9: =SUM(AJ9) -> 229 | AM9: =SUM(AL9*$Z$4) -> 2290 | AN9: =SUM(AO9/19600) -> 0.81785714 | AO9: =SUM(AA9+AC9+AE9+AG9+AI9+AK9+AM9) -> 16030 | AQ9: =SUM(AR9/92970) -> 0.73757542 | AR9: =Y9+AO9 -> 68572.387 | AS9: =SUM(AR9-AR8-AT9) -> -1770.0645 | AV9: =IF(AT9>0,AU9,AV8) -> 0.92 | AW9: =-SUM('B5'!AI8) -> -95 | AX9: =-SUM(AW9-AS9) -> -1675.0645 | AY9: =SUM(AX9+AW9) -> -1770.0645 | AZ9: =ELEC!A6 -> 0 | BA9: ='General information '!D9 -> 22.5 | BB9: =SUM('General information '!E9) -> 0.44 | BC9: =IF(AR8>=AR9,0,1) -> 0 | BD9: 19222 | BE9: =(305/1185)*ELEC!Q7 -> 1443.9241 | BG9: =#REF!-BE9 -> #REF! | BH9: 18 | BI9: 6 | BJ9: =AX9/BI9 -> -279.17742 | BK9: =GEN!AF6 -> 0.32898438
A10: =ELEC!C7 -> 44321 | B10: ='B5'!B9 -> 216 | C10: =B10*$B$4 -> 4647.4839 | D10: =SUM(B10) -> 216 | E10: =D10*$B$4 -> 4647.4839 | F10: =SUM(D10) -> 216 | G10: =F10*$B$4 -> 4647.4839 | H10: =SUM(F10) -> 216 | I10: =H10*$B$4 -> 4647.4839 | J10: =SUM(H10) -> 216 | K10: =J10*$B$4 -> 4647.4839 | L10: =SUM(J10) -> 216 | M10: =L10*$B$4 -> 4647.4839 | N10: =SUM(L10) -> 216 | O10: =N10*$B$4 -> 4647.4839 | P10: =SUM(N10) -> 216 | Q10: =P10*$B$4 -> 4647.4839 | R10: =SUM(P10) -> 216 | S10: =R10*$B$4 -> 4647.4839 | T10: =SUM(R10) -> 216 | U10: =T10*$B$4 -> 4647.4839 | V10: =SUM(T10) -> 216 | W10: =V10*$B$4 -> 4647.4839 | X10: =SUM(Y10/73370) -> 0.69677419 | Y10: =SUM(C10+E10+G10+I10+K10+M10+O10+Q10+S10+U10+W10) -> 51122.323 | Z10: ='B5'!C9 -> 222 | AA10: =SUM(Z10*$Z$4) -> 2220 | AB10: =SUM(Z10) -> 222 | AC10: =SUM(AB10*$Z$4) -> 2220 | AD10: =SUM(AB10) -> 222 | AE10: =SUM(AD10*$Z$4) -> 2220 | AF10: =SUM(AD10) -> 222 | AG10: =SUM(AF10*$Z$4) -> 2220 | AH10: =SUM(AF10) -> 222 | AI10: =SUM(AH10*$Z$4) -> 2220 | AJ10: =SUM(AH10) -> 222 | AK10: =SUM(AJ10*$Z$4) -> 2220 | AL10: =SUM(AJ10) -> 222 | AM10: =SUM(AL10*$Z$4) -> 2220 | AN10: =SUM(AO10/19600) -> 0.79285714 | AO10: =SUM(AA10+AC10+AE10+AG10+AI10+AK10+AM10) -> 15540 | AQ10: =SUM(AR10/92970) -> 0.71703047 | AR10: =Y10+AO10 -> 66662.323 | AS10: =SUM(AR10-AR9-AT10) -> -1910.0645 | AV10: =IF(AT10>0,AU10,AV9) -> 0.92 | AW10: =-SUM('B5'!AI9) -> -164 | AX10: =-SUM(AW10-AS10) -> -1746.0645 | AY10: =SUM(AX10+AW10) -> -1910.0645 | AZ10: =ELEC!A7 -> 0 | BA10: ='General information '!D10 -> 23 | BB10: =SUM('General information '!E10) -> 0.53 | BC10: =IF(AR9>=AR10,0,1) -> 0 | BD10: 19222 | BE10: =(305/1185)*ELEC!Q8 -> 896.21097 | BG10: =#REF!-BE10 -> #REF! | BH10: 16 | BI10: 7 | BJ10: =AX10/BI10 -> -249.43779 | BK10: =GEN!AF7 -> 0.38958333
A11: =ELEC!C8 -> 44322 | B11: ='B5'!B10 -> 212 | C11: =B11*$B$4 -> 4561.4194 | D11: =SUM(B11) -> 212 | E11: =D11*$B$4 -> 4561.4194 | F11: =SUM(D11) -> 212 | G11: =F11*$B$4 -> 4561.4194 | H11: =SUM(F11) -> 212 | I11: =H11*$B$4 -> 4561.4194 | J11: =SUM(H11) -> 212 | K11: =J11*$B$4 -> 4561.4194 | L11: =SUM(J11) -> 212 | M11: =L11*$B$4 -> 4561.4194 | N11: =SUM(L11) -> 212 | O11: =N11*$B$4 -> 4561.4194 | P11: =SUM(N11) -> 212 | Q11: =P11*$B$4 -> 4561.4194 | R11: =SUM(P11) -> 212 | S11: =R11*$B$4 -> 4561.4194 | T11: =SUM(R11) -> 212 | U11: =T11*$B$4 -> 4561.4194 | V11: =SUM(T11) -> 212 | W11: =V11*$B$4 -> 4561.4194 | X11: =SUM(Y11/73370) -> 0.68387097 | Y11: =SUM(C11+E11+G11+I11+K11+M11+O11+Q11+S11+U11+W11) -> 50175.613 | Z11: ='B5'!C10 -> 219 | AA11: =SUM(Z11*$Z$4) -> 2190 | AB11: =SUM(Z11) -> 219 | AC11: =SUM(AB11*$Z$4) -> 2190 | AD11: =SUM(AB11) -> 219 | AE11: =SUM(AD11*$Z$4) -> 2190 | AF11: =SUM(AD11) -> 219 | AG11: =SUM(AF11*$Z$4) -> 2190 | AH11: =SUM(AF11) -> 219 | AI11: =SUM(AH11*$Z$4) -> 2190 | AJ11: =SUM(AH11) -> 219 | AK11: =SUM(AJ11*$Z$4) -> 2190 | AL11: =SUM(AJ11) -> 219 | AM11: =SUM(AL11*$Z$4) -> 2190 | AN11: =SUM(AO11/19600) -> 0.78214286 | AO11: =SUM(AA11+AC11+AE11+AG11+AI11+AK11+AM11) -> 15330 | AQ11: =SUM(AR11/92970) -> 0.70458872 | AR11: =Y11+AO11 -> 65505.613 | AS11: =SUM(AR11-AR10-AT11) -> -1156.7097 | AV11: =IF(AT11>0,AU11,AV10) -> 0.92 | AW11: =-SUM('B5'!AI10) -> -155 | AX11: =-SUM(AW11-AS11) -> -1001.7097 | AY11: =SUM(AX11+AW11) -> -1156.7097 | AZ11: =ELEC!A8 -> 0 | BA11: ='General information '!D11 -> 22 | BB11: =SUM('General information '!E11) -> 0.64 | BC11: =IF(AR10>=AR11,0,1) -> 0 | BD11: 19222 | BE11: =(305/1185)*ELEC!Q9 -> 1506.9831 | BG11: =#REF!-BE11 -> #REF! | BH11: 16.5 | BI11: 9.3 | BJ11: =AX11/BI11 -> -107.71072 | BK11: =GEN!AF8 -> 0.36270833
A12: =ELEC!C9 -> 44323 | B12: ='B5'!B11 -> 205 | C12: =B12*$B$4 -> 4410.8065 | D12: =SUM(B12) -> 205 | E12: =D12*$B$4 -> 4410.8065 | F12: =SUM(D12) -> 205 | G12: =F12*$B$4 -> 4410.8065 | H12: =SUM(F12) -> 205 | I12: =H12*$B$4 -> 4410.8065 | J12: =SUM(H12) -> 205 | K12: =J12*$B$4 -> 4410.8065 | L12: =SUM(J12) -> 205 | M12: =L12*$B$4 -> 4410.8065 | N12: =SUM(L12) -> 205 | O12: =N12*$B$4 -> 4410.8065 | P12: =SUM(N12) -> 205 | Q12: =P12*$B$4 -> 4410.8065 | R12: =SUM(P12) -> 205 | S12: =R12*$B$4 -> 4410.8065 | T12: =SUM(R12) -> 205 | U12: =T12*$B$4 -> 4410.8065 | V12: =SUM(T12) -> 205 | W12: =V12*$B$4 -> 4410.8065 | X12: =SUM(Y12/73370) -> 0.66129032 | Y12: =SUM(C12+E12+G12+I12+K12+M12+O12+Q12+S12+U12+W12) -> 48518.871 | Z12: ='B5'!C11 -> 212 | AA12: =SUM(Z12*$Z$4) -> 2120 | AB12: =SUM(Z12) -> 212 | AC12: =SUM(AB12*$Z$4) -> 2120 | AD12: =SUM(AB12) -> 212 | AE12: =SUM(AD12*$Z$4) -> 2120 | AF12: =SUM(AD12) -> 212 | AG12: =SUM(AF12*$Z$4) -> 2120 | AH12: =SUM(AF12) -> 212 | AI12: =SUM(AH12*$Z$4) -> 2120 | AJ12: =SUM(AH12) -> 212 | AK12: =SUM(AJ12*$Z$4) -> 2120 | AL12: =SUM(AJ12) -> 212 | AM12: =SUM(AL12*$Z$4) -> 2120 | AN12: =SUM(AO12/19600) -> 0.75714286 | AO12: =SUM(AA12+AC12+AE12+AG12+AI12+AK12+AM12) -> 14840 | AQ12: =SUM(AR12/92970) -> 0.68149802 | AR12: =Y12+AO12 -> 63358.871 | AS12: =SUM(AR12-AR11-AT12) -> -2146.7419 | AV12: =IF(AT12>0,AU12,AV11) -> 0.92 | AW12: =-SUM('B5'!AI11) -> -166 | AX12: =-SUM(AW12-AS12) -> -1980.7419 | AY12: =SUM(AX12+AW12) -> -2146.7419 | AZ12: =ELEC!A9 -> 0 | BA12: ='General information '!D12 -> 23 | BB12: =SUM('General information '!E12) -> 0.65 | BC12: =IF(AR11>=AR12,0,1) -> 0 | BD12: 19222 | BE12: =(305/1185)*ELEC!Q10 -> 1417.9283 | BG12: =#REF!-BE12 -> #REF! | BH12: 15.5 | BI12: 3.7 | BJ12: =AX12/BI12 -> -535.33566 | BK12: =GEN!AF9 -> 0.43051471
A13: =ELEC!C10 -> 44324 | B13: ='B5'!B12 -> 198 | C13: =B13*$B$4 -> 4260.1935 | D13: =SUM(B13) -> 198 | E13: =D13*$B$4 -> 4260.1935 | F13: =SUM(D13) -> 198 | G13: =F13*$B$4 -> 4260.1935 | H13: =SUM(F13) -> 198 | I13: =H13*$B$4 -> 4260.1935 | J13: =SUM(H13) -> 198 | K13: =J13*$B$4 -> 4260.1935 | L13: =SUM(J13) -> 198 | M13: =L13*$B$4 -> 4260.1935 | N13: =SUM(L13) -> 198 | O13: =N13*$B$4 -> 4260.1935 | P13: =SUM(N13) -> 198 | Q13: =P13*$B$4 -> 4260.1935 | R13: =SUM(P13) -> 198 | S13: =R13*$B$4 -> 4260.1935 | T13: =SUM(R13) -> 198 | U13: =T13*$B$4 -> 4260.1935 | V13: =SUM(T13) -> 198 | W13: =V13*$B$4 -> 4260.1935 | X13: =SUM(Y13/73370) -> 0.63870968 | Y13: =SUM(C13+E13+G13+I13+K13+M13+O13+Q13+S13+U13+W13) -> 46862.129 | Z13: ='B5'!C12 -> 205 | AA13: =SUM(Z13*$Z$4) -> 2050 | AB13: =SUM(Z13) -> 205 | AC13: =SUM(AB13*$Z$4) -> 2050 | AD13: =SUM(AB13) -> 205 | AE13: =SUM(AD13*$Z$4) -> 2050 | AF13: =SUM(AD13) -> 205 | AG13: =SUM(AF13*$Z$4) -> 2050 | AH13: =SUM(AF13) -> 205 | AI13: =SUM(AH13*$Z$4) -> 2050 | AJ13: =SUM(AH13) -> 205 | AK13: =SUM(AJ13*$Z$4) -> 2050 | AL13: =SUM(AJ13) -> 205 | AM13: =SUM(AL13*$Z$4) -> 2050 | AN13: =SUM(AO13/19600) -> 0.73214286 | AO13: =SUM(AA13+AC13+AE13+AG13+AI13+AK13+AM13) -> 14350 | AQ13: =SUM(AR13/92970) -> 0.65840733 | AR13: =Y13+AO13 -> 61212.129 | AS13: =SUM(AR13-AR12-AT13) -> -2146.7419 | AV13: =IF(AT13>0,AU13,AV12) -> 0.92 | AW13: =-SUM('B5'!AI12) -> -156 | AX13: =-SUM(AW13-AS13) -> -1990.7419 | AY13: =SUM(AX13+AW13) -> -2146.7419 | AZ13: =ELEC!A10 -> 0 | BA13: ='General information '!D13 -> 24.5 | BB13: =SUM('General information '!E13) -> 0.52 | BC13: =IF(AR12>=AR13,0,1) -> 0 | BD13: 19222 | BE13: =(305/1185)*ELEC!Q11 -> 1622.2911 | BG13: =#REF!-BE13 -> #REF! | BI13: 5 | BJ13: =AX13/BI13 -> -398.14839 | BK13: =GEN!AF10 -> 0.40036337
A14: =ELEC!C11 -> 44325 | B14: ='B5'!B13 -> 192 | C14: =B14*$B$4 -> 4131.0968 | D14: =SUM(B14) -> 192 | E14: =D14*$B$4 -> 4131.0968 | F14: =SUM(D14) -> 192 | G14: =F14*$B$4 -> 4131.0968 | H14: =SUM(F14) -> 192 | I14: =H14*$B$4 -> 4131.0968 | J14: =SUM(H14) -> 192 | K14: =J14*$B$4 -> 4131.0968 | L14: =SUM(J14) -> 192 | M14: =L14*$B$4 -> 4131.0968 | N14: =SUM(L14) -> 192 | O14: =N14*$B$4 -> 4131.0968 | P14: =SUM(N14) -> 192 | Q14: =P14*$B$4 -> 4131.0968 | R14: =SUM(P14) -> 192 | S14: =R14*$B$4 -> 4131.0968 | T14: =SUM(R14) -> 192 | U14: =T14*$B$4 -> 4131.0968 | V14: =SUM(T14) -> 192 | W14: =V14*$B$4 -> 4131.0968 | X14: =SUM(Y14/73370) -> 0.61935484 | Y14: =SUM(C14+E14+G14+I14+K14+M14+O14+Q14+S14+U14+W14) -> 45442.065 | Z14: ='B5'!C13 -> 198 | AA14: =SUM(Z14*$Z$4) -> 1980 | AB14: =SUM(Z14) -> 198 | AC14: =SUM(AB14*$Z$4) -> 1980 | AD14: =SUM(AB14) -> 198 | AE14: =SUM(AD14*$Z$4) -> 1980 | AF14: =SUM(AD14) -> 198 | AG14: =SUM(AF14*$Z$4) -> 1980 | AH14: =SUM(AF14) -> 198 | AI14: =SUM(AH14*$Z$4) -> 1980 | AJ14: =SUM(AH14) -> 198 | AK14: =SUM(AJ14*$Z$4) -> 1980 | AL14: =SUM(AJ14) -> 198 | AM14: =SUM(AL14*$Z$4) -> 1980 | AN14: =SUM(AO14/19600) -> 0.70714286 | AO14: =SUM(AA14+AC14+AE14+AG14+AI14+AK14+AM14) -> 13860 | AQ14: =SUM(AR14/92970) -> 0.63786237 | AR14: =Y14+AO14 -> 59302.065 | AS14: =SUM(AR14-AR13-AT14) -> -1910.0645 | AV14: =IF(AT14>0,AU14,AV13) -> 0.92 | AW14: =-SUM('B5'!AI13) -> -112 | AX14: =-SUM(AW14-AS14) -> -1798.0645 | AY14: =SUM(AX14+AW14) -> -1910.0645 | AZ14: =ELEC!A11 -> 0 | BA14: ='General information '!D14 -> 24.5 | BB14: =SUM('General information '!E14) -> 0.55 | BC14: =IF(AR13>=AR14,0,1) -> 0 | BD14: 19222 | BE14: =(305/1185)*ELEC!Q12 -> 1631.2996 | BG14: =#REF!-BE14 -> #REF! | BI14: 3 | BJ14: =AX14/BI14 -> -599.35484 | BK14: =GEN!AF11 -> 0.4426264
A15: =ELEC!C12 -> 44326 | B15: ='B5'!B14 -> 184 | C15: =B15*$B$4 -> 3958.9677 | D15: =SUM(B15) -> 184 | E15: =D15*$B$4 -> 3958.9677 | F15: =SUM(D15) -> 184 | G15: =F15*$B$4 -> 3958.9677 | H15: =SUM(F15) -> 184 | I15: =H15*$B$4 -> 3958.9677 | J15: =SUM(H15) -> 184 | K15: =J15*$B$4 -> 3958.9677 | L15: =SUM(J15) -> 184 | M15: =L15*$B$4 -> 3958.9677 | N15: =SUM(L15) -> 184 | O15: =N15*$B$4 -> 3958.9677 | P15: =SUM(N15) -> 184 | Q15: =P15*$B$4 -> 3958.9677 | R15: =SUM(P15) -> 184 | S15: =R15*$B$4 -> 3958.9677 | T15: =SUM(R15) -> 184 | U15: =T15*$B$4 -> 3958.9677 | V15: =SUM(T15) -> 184 | W15: =V15*$B$4 -> 3958.9677 | X15: =SUM(Y15/73370) -> 0.59354839 | Y15: =SUM(C15+E15+G15+I15+K15+M15+O15+Q15+S15+U15+W15) -> 43548.645 | Z15: ='B5'!C14 -> 192 | AA15: =SUM(Z15*$Z$4) -> 1920 | AB15: =SUM(Z15) -> 192 | AC15: =SUM(AB15*$Z$4) -> 1920 | AD15: =SUM(AB15) -> 192 | AE15: =SUM(AD15*$Z$4) -> 1920 | AF15: =SUM(AD15) -> 192 | AG15: =SUM(AF15*$Z$4) -> 1920 | AH15: =SUM(AF15) -> 192 | AI15: =SUM(AH15*$Z$4) -> 1920 | AJ15: =SUM(AH15) -> 192 | AK15: =SUM(AJ15*$Z$4) -> 1920 | AL15: =SUM(AJ15) -> 192 | AM15: =SUM(AL15*$Z$4) -> 1920 | AN15: =SUM(AO15/19600) -> 0.68571429 | AO15: =SUM(AA15+AC15+AE15+AG15+AI15+AK15+AM15) -> 13440 | AQ15: =SUM(AR15/92970) -> 0.61297887 | AR15: =Y15+AO15 -> 56988.645 | AS15: =SUM(AR15-AR14-AT15) -> -2313.4194 | AV15: =IF(AT15>0,AU15,AV14) -> 0.92 | AW15: =-SUM('B5'!AI14) -> -82 | AX15: =-SUM(AW15-AS15) -> -2231.4194 | AY15: =SUM(AX15+AW15) -> -2313.4194 | AZ15: =ELEC!A12 -> 0 | BA15: ='General information '!D15 -> 22 | BB15: =SUM('General information '!E15) -> 0.53 | BC15: =IF(AR14>=AR15,0,1) -> 0 | BD15: 19222 | BE15: =(305/1185)*ELEC!Q13 -> 1478.4135 | BG15: =#REF!-BE15 -> #REF! | BI15: 4 | BJ15: =AX15/BI15 -> -557.85484 | BK15: =GEN!AF12 -> 0.44013889
A16: =ELEC!C13 -> 44327 | B16: ='B5'!B15 -> 234 | C16: =B16*$B$4 -> 5034.7742 | D16: =SUM(B16) -> 234 | E16: =D16*$B$4 -> 5034.7742 | F16: =SUM(D16) -> 234 | G16: =F16*$B$4 -> 5034.7742 | H16: =SUM(F16) -> 234 | I16: =H16*$B$4 -> 5034.7742 | J16: =SUM(H16) -> 234 | K16: =J16*$B$4 -> 5034.7742 | L16: =SUM(J16) -> 234 | M16: =L16*$B$4 -> 5034.7742 | N16: =SUM(L16) -> 234 | O16: =N16*$B$4 -> 5034.7742 | P16: =SUM(N16) -> 234 | Q16: =P16*$B$4 -> 5034.7742 | R16: =SUM(P16) -> 234 | S16: =R16*$B$4 -> 5034.7742 | T16: =SUM(R16) -> 234 | U16: =T16*$B$4 -> 5034.7742 | V16: =SUM(T16) -> 234 | W16: =V16*$B$4 -> 5034.7742 | X16: =SUM(Y16/73370) -> 0.75483871 | Y16: =SUM(C16+E16+G16+I16+K16+M16+O16+Q16+S16+U16+W16) -> 55382.516 | Z16: ='B5'!C15 -> 241 | AA16: =SUM(Z16*$Z$4) -> 2410 | AB16: =SUM(Z16) -> 241 | AC16: =SUM(AB16*$Z$4) -> 2410 | AD16: =SUM(AB16) -> 241 | AE16: =SUM(AD16*$Z$4) -> 2410 | AF16: =SUM(AD16) -> 241 | AG16: =SUM(AF16*$Z$4) -> 2410 | AH16: =SUM(AF16) -> 241 | AI16: =SUM(AH16*$Z$4) -> 2410 | AJ16: =SUM(AH16) -> 241 | AK16: =SUM(AJ16*$Z$4) -> 2410 | AL16: =SUM(AJ16) -> 241 | AM16: =SUM(AL16*$Z$4) -> 2410 | AN16: =SUM(AO16/19600) -> 0.86071429 | AO16: =SUM(AA16+AC16+AE16+AG16+AI16+AK16+AM16) -> 16870 | AQ16: =SUM(AR16/92970) -> 0.77715947 | AR16: =Y16+AO16 -> 72252.516 | AS16: =SUM(AR16-AR15-AT16) -> 718.87097 | AT16: 14545 | AU16: 0.94 | AV16: =IF(AT16>0,AU16,AV15) -> 0.94 | AW16: =-SUM('B5'!AI15) -> -137 | AX16: =-SUM(AW16-AS16) -> 855.87097 | AY16: =SUM(AX16+AW16) -> 718.87097 | AZ16: =ELEC!A13 -> 0 | BA16: ='General information '!D16 -> 21 | BB16: =SUM('General information '!E16) -> 0.74 | BC16: =IF(AR15>=AR16,0,1) -> 1 | BD16: 19222 | BE16: =(305/1185)*ELEC!Q14 -> 1870.9241 | BG16: =#REF!-BE16 -> #REF! | BI16: 3 | BJ16: =AX16/BI16 -> 285.29032 | BK16: =GEN!AF13 -> 0.359
A17: =ELEC!C14 -> 44328 | B17: ='B5'!B16 -> 225 | C17: =B17*$B$4 -> 4841.129 | D17: =SUM(B17) -> 225 | E17: =D17*$B$4 -> 4841.129 | F17: =SUM(D17) -> 225 | G17: =F17*$B$4 -> 4841.129 | H17: =SUM(F17) -> 225 | I17: =H17*$B$4 -> 4841.129 | J17: =SUM(H17) -> 225 | K17: =J17*$B$4 -> 4841.129 | L17: =SUM(J17) -> 225 | M17: =L17*$B$4 -> 4841.129 | N17: =SUM(L17) -> 225 | O17: =N17*$B$4 -> 4841.129 | P17: =SUM(N17) -> 225 | Q17: =P17*$B$4 -> 4841.129 | R17: =SUM(P17) -> 225 | S17: =R17*$B$4 -> 4841.129 | T17: =SUM(R17) -> 225 | U17: =T17*$B$4 -> 4841.129 | V17: =SUM(T17) -> 225 | W17: =V17*$B$4 -> 4841.129 | X17: =SUM(Y17/73370) -> 0.72580645 | Y17: =SUM(C17+E17+G17+I17+K17+M17+O17+Q17+S17+U17+W17) -> 53252.419 | Z17: ='B5'!C16 -> 232 | AA17: =SUM(Z17*$Z$4) -> 2320 | AB17: =SUM(Z17) -> 232 | AC17: =SUM(AB17*$Z$4) -> 2320 | AD17: =SUM(AB17) -> 232 | AE17: =SUM(AD17*$Z$4) -> 2320 | AF17: =SUM(AD17) -> 232 | AG17: =SUM(AF17*$Z$4) -> 2320 | AH17: =SUM(AF17) -> 232 | AI17: =SUM(AH17*$Z$4) -> 2320 | AJ17: =SUM(AH17) -> 232 | AK17: =SUM(AJ17*$Z$4) -> 2320 | AL17: =SUM(AJ17) -> 232 | AM17: =SUM(AL17*$Z$4) -> 2320 | AN17: =SUM(AO17/19600) -> 0.82857143 | AO17: =SUM(AA17+AC17+AE17+AG17+AI17+AK17+AM17) -> 16240 | AQ17: =SUM(AR17/92970) -> 0.74747144 | AR17: =Y17+AO17 -> 69492.419 | AS17: =SUM(AR17-AR16-AT17) -> -2760.0968 | AV17: =IF(AT17>0,AU17,AV16) -> 0.94 | AW17: =-SUM('B5'!AI16) -> -154 | AX17: =-SUM(AW17-AS17) -> -2606.0968 | AY17: =SUM(AX17+AW17) -> -2760.0968 | AZ17: =ELEC!A14 -> 0 | BA17: ='General information '!D17 -> 22 | BB17: =SUM('General information '!E17) -> 0.68 | BC17: =IF(AR16>=AR17,0,1) -> 0 | BD17: 19222 | BE17: =(305/1185)*ELEC!Q15 -> 1725.7595 | BG17: =#REF!-BE17 -> #REF!
A18: =ELEC!C15 -> 44329 | B18: ='B5'!B17 -> 218 | C18: =B18*$B$4 -> 4690.5161 | D18: =SUM(B18) -> 218 | E18: =D18*$B$4 -> 4690.5161 | F18: =SUM(D18) -> 218 | G18: =F18*$B$4 -> 4690.5161 | H18: =SUM(F18) -> 218 | I18: =H18*$B$4 -> 4690.5161 | J18: =SUM(H18) -> 218 | K18: =J18*$B$4 -> 4690.5161 | L18: =SUM(J18) -> 218 | M18: =L18*$B$4 -> 4690.5161 | N18: =SUM(L18) -> 218 | O18: =N18*$B$4 -> 4690.5161 | P18: =SUM(N18) -> 218 | Q18: =P18*$B$4 -> 4690.5161 | R18: =SUM(P18) -> 218 | S18: =R18*$B$4 -> 4690.5161 | T18: =SUM(R18) -> 218 | U18: =T18*$B$4 -> 4690.5161 | V18: =SUM(T18) -> 218 | W18: =V18*$B$4 -> 4690.5161 | X18: =SUM(Y18/73370) -> 0.70322581 | Y18: =SUM(C18+E18+G18+I18+K18+M18+O18+Q18+S18+U18+W18) -> 51595.677 | Z18: ='B5'!C17 -> 224 | AA18: =SUM(Z18*$Z$4) -> 2240 | AB18: =SUM(Z18) -> 224 | AC18: =SUM(AB18*$Z$4) -> 2240 | AD18: =SUM(AB18) -> 224 | AE18: =SUM(AD18*$Z$4) -> 2240 | AF18: =SUM(AD18) -> 224 | AG18: =SUM(AF18*$Z$4) -> 2240 | AH18: =SUM(AF18) -> 224 | AI18: =SUM(AH18*$Z$4) -> 2240 | AJ18: =SUM(AH18) -> 224 | AK18: =SUM(AJ18*$Z$4) -> 2240 | AL18: =SUM(AJ18) -> 224 | AM18: =SUM(AL18*$Z$4) -> 2240 | AN18: =SUM(AO18/19600) -> 0.8 | AO18: =SUM(AA18+AC18+AE18+AG18+AI18+AK18+AM18) -> 15680 | AQ18: =SUM(AR18/92970) -> 0.72362781 | AR18: =Y18+AO18 -> 67275.677 | AS18: =SUM(AR18-AR17-AT18) -> -2216.7419 | AV18: =IF(AT18>0,AU18,AV17) -> 0.94 | AW18: =-SUM('B5'!AI17) -> -115 | AX18: =-SUM(AW18-AS18) -> -2101.7419 | AY18: =SUM(AX18+AW18) -> -2216.7419 | AZ18: =ELEC!A15 -> 0 | BA18: ='General information '!D18 -> 21 | BB18: =SUM('General information '!E18) -> 0.74 | BC18: =IF(AR17>=AR18,0,1) -> 0 | BD18: 19222 | BE18: =(305/1185)*ELEC!Q16 -> 1386.0127 | BG18: =#REF!-BE18 -> #REF!
A19: =ELEC!C16 -> 44330 | B19: ='B5'!B18 -> 212 | C19: =B19*$B$4 -> 4561.4194 | D19: =SUM(B19) -> 212 | E19: =D19*$B$4 -> 4561.4194 | F19: =SUM(D19) -> 212 | G19: =F19*$B$4 -> 4561.4194 | H19: =SUM(F19) -> 212 | I19: =H19*$B$4 -> 4561.4194 | J19: =SUM(H19) -> 212 | K19: =J19*$B$4 -> 4561.4194 | L19: =SUM(J19) -> 212 | M19: =L19*$B$4 -> 4561.4194 | N19: =SUM(L19) -> 212 | O19: =N19*$B$4 -> 4561.4194 | P19: =SUM(N19) -> 212 | Q19: =P19*$B$4 -> 4561.4194 | R19: =SUM(P19) -> 212 | S19: =R19*$B$4 -> 4561.4194 | T19: =SUM(R19) -> 212 | U19: =T19*$B$4 -> 4561.4194 | V19: =SUM(T19) -> 212 | W19: =V19*$B$4 -> 4561.4194 | X19: =SUM(Y19/73370) -> 0.68387097 | Y19: =SUM(C19+E19+G19+I19+K19+M19+O19+Q19+S19+U19+W19) -> 50175.613 | Z19: ='B5'!C18 -> 218 | AA19: =SUM(Z19*$Z$4) -> 2180 | AB19: =SUM(Z19) -> 218 | AC19: =SUM(AB19*$Z$4) -> 2180 | AD19: =SUM(AB19) -> 218 | AE19: =SUM(AD19*$Z$4) -> 2180 | AF19: =SUM(AD19) -> 218 | AG19: =SUM(AF19*$Z$4) -> 2180 | AH19: =SUM(AF19) -> 218 | AI19: =SUM(AH19*$Z$4) -> 2180 | AJ19: =SUM(AH19) -> 218 | AK19: =SUM(AJ19*$Z$4) -> 2180 | AL19: =SUM(AJ19) -> 218 | AM19: =SUM(AL19*$Z$4) -> 2180 | AN19: =SUM(AO19/19600) -> 0.77857143 | AO19: =SUM(AA19+AC19+AE19+AG19+AI19+AK19+AM19) -> 15260 | AQ19: =SUM(AR19/92970) -> 0.70383578 | AR19: =Y19+AO19 -> 65435.613 | AS19: =SUM(AR19-AR18-AT19) -> -1840.0645 | AV19: =IF(AT19>0,AU19,AV18) -> 0.94 | AW19: =-SUM('B5'!AI18) -> -89 | AX19: =-SUM(AW19-AS19) -> -1751.0645 | AY19: =SUM(AX19+AW19) -> -1840.0645 | AZ19: =ELEC!A16 -> 0 | BA19: ='General information '!D19 -> 22.5 | BB19: =SUM('General information '!E19) -> 0.67 | BC19: =IF(AR18>=AR19,0,1) -> 0 | BD19: 19222 | BE19: =(305/1185)*ELEC!Q17 -> 1646.2278 | BG19: =#REF!-BE19 -> #REF!
A20: =ELEC!C17 -> 44331 | B20: ='B5'!B19 -> 206 | C20: =B20*$B$4 -> 4432.3226 | D20: =SUM(B20) -> 206 | E20: =D20*$B$4 -> 4432.3226 | F20: =SUM(D20) -> 206 | G20: =F20*$B$4 -> 4432.3226 | H20: =SUM(F20) -> 206 | I20: =H20*$B$4 -> 4432.3226 | J20: =SUM(H20) -> 206 | K20: =J20*$B$4 -> 4432.3226 | L20: =SUM(J20) -> 206 | M20: =L20*$B$4 -> 4432.3226 | N20: =SUM(L20) -> 206 | O20: =N20*$B$4 -> 4432.3226 | P20: =SUM(N20) -> 206 | Q20: =P20*$B$4 -> 4432.3226 | R20: =SUM(P20) -> 206 | S20: =R20*$B$4 -> 4432.3226 | T20: =SUM(R20) -> 206 | U20: =T20*$B$4 -> 4432.3226 | V20: =SUM(T20) -> 206 | W20: =V20*$B$4 -> 4432.3226 | X20: =SUM(Y20/73370) -> 0.66451613 | Y20: =SUM(C20+E20+G20+I20+K20+M20+O20+Q20+S20+U20+W20) -> 48755.548 | Z20: ='B5'!C19 -> 213 | AA20: =SUM(Z20*$Z$4) -> 2130 | AB20: =SUM(Z20) -> 213 | AC20: =SUM(AB20*$Z$4) -> 2130 | AD20: =SUM(AB20) -> 213 | AE20: =SUM(AD20*$Z$4) -> 2130 | AF20: =SUM(AD20) -> 213 | AG20: =SUM(AF20*$Z$4) -> 2130 | AH20: =SUM(AF20) -> 213 | AI20: =SUM(AH20*$Z$4) -> 2130 | AJ20: =SUM(AH20) -> 213 | AK20: =SUM(AJ20*$Z$4) -> 2130 | AL20: =SUM(AJ20) -> 213 | AM20: =SUM(AL20*$Z$4) -> 2130 | AN20: =SUM(AO20/19600) -> 0.76071429 | AO20: =SUM(AA20+AC20+AE20+AG20+AI20+AK20+AM20) -> 14910 | AQ20: =SUM(AR20/92970) -> 0.68479669 | AR20: =Y20+AO20 -> 63665.548 | AS20: =SUM(AR20-AR19-AT20) -> -1770.0645 | AV20: =IF(AT20>0,AU20,AV19) -> 0.94 | AW20: =-SUM('B5'!AI19) -> -139 | AX20: =-SUM(AW20-AS20) -> -1631.0645 | AY20: =SUM(AX20+AW20) -> -1770.0645 | AZ20: =ELEC!A17 -> 0 | BA20: ='General information '!D20 -> 23.5 | BB20: =SUM('General information '!E20) -> 0.65 | BC20: =IF(AR19>=AR20,0,1) -> 0 | BD20: 19222 | BE20: =(305/1185)*ELEC!Q18 -> 1293.3544 | BG20: =#REF!-BE20 -> #REF!
A21: =ELEC!C18 -> 44332 | B21: ='B5'!B20 -> 195 | C21: =B21*$B$4 -> 4195.6452 | D21: =SUM(B21) -> 195 | E21: =D21*$B$4 -> 4195.6452 | F21: =SUM(D21) -> 195 | G21: =F21*$B$4 -> 4195.6452 | H21: =SUM(F21) -> 195 | I21: =H21*$B$4 -> 4195.6452 | J21: =SUM(H21) -> 195 | K21: =J21*$B$4 -> 4195.6452 | L21: =SUM(J21) -> 195 | M21: =L21*$B$4 -> 4195.6452 | N21: =SUM(L21) -> 195 | O21: =N21*$B$4 -> 4195.6452 | P21: =SUM(N21) -> 195 | Q21: =P21*$B$4 -> 4195.6452 | R21: =SUM(P21) -> 195 | S21: =R21*$B$4 -> 4195.6452 | T21: =SUM(R21) -> 195 | U21: =T21*$B$4 -> 4195.6452 | V21: =SUM(T21) -> 195 | W21: =V21*$B$4 -> 4195.6452 | X21: =SUM(Y21/73370) -> 0.62903226 | Y21: =SUM(C21+E21+G21+I21+K21+M21+O21+Q21+S21+U21+W21) -> 46152.097 | Z21: ='B5'!C20 -> 201 | AA21: =SUM(Z21*$Z$4) -> 2010 | AB21: =SUM(Z21) -> 201 | AC21: =SUM(AB21*$Z$4) -> 2010 | AD21: =SUM(AB21) -> 201 | AE21: =SUM(AD21*$Z$4) -> 2010 | AF21: =SUM(AD21) -> 201 | AG21: =SUM(AF21*$Z$4) -> 2010 | AH21: =SUM(AF21) -> 201 | AI21: =SUM(AH21*$Z$4) -> 2010 | AJ21: =SUM(AH21) -> 201 | AK21: =SUM(AJ21*$Z$4) -> 2010 | AL21: =SUM(AJ21) -> 201 | AM21: =SUM(AL21*$Z$4) -> 2010 | AN21: =SUM(AO21/19600) -> 0.71785714 | AO21: =SUM(AA21+AC21+AE21+AG21+AI21+AK21+AM21) -> 14070 | AQ21: =SUM(AR21/92970) -> 0.64775838 | AR21: =Y21+AO21 -> 60222.097 | AS21: =SUM(AR21-AR20-AT21) -> -3443.4516 | AV21: =IF(AT21>0,AU21,AV20) -> 0.94 | AW21: =-SUM('B5'!AI20) -> -115 | AX21: =-SUM(AW21-AS21) -> -3328.4516 | AY21: =SUM(AX21+AW21) -> -3443.4516 | AZ21: =ELEC!A18 -> 0 | BA21: ='General information '!D21 -> 21.5 | BB21: =SUM('General information '!E21) -> 0.75 | BC21: =IF(AR20>=AR21,0,1) -> 0 | BD21: 19222 | BE21: =(305/1185)*ELEC!Q19 -> 2417.3502 | BG21: =#REF!-BE21 -> #REF!
A22: =ELEC!C19 -> 44333 | B22: ='B5'!B21 -> 188 | C22: =B22*$B$4 -> 4045.0323 | D22: =SUM(B22) -> 188 | E22: =D22*$B$4 -> 4045.0323 | F22: =SUM(D22) -> 188 | G22: =F22*$B$4 -> 4045.0323 | H22: =SUM(F22) -> 188 | I22: =H22*$B$4 -> 4045.0323 | J22: =SUM(H22) -> 188 | K22: =J22*$B$4 -> 4045.0323 | L22: =SUM(J22) -> 188 | M22: =L22*$B$4 -> 4045.0323 | N22: =SUM(L22) -> 188 | O22: =N22*$B$4 -> 4045.0323 | P22: =SUM(N22) -> 188 | Q22: =P22*$B$4 -> 4045.0323 | R22: =SUM(P22) -> 188 | S22: =R22*$B$4 -> 4045.0323 | T22: =SUM(R22) -> 188 | U22: =T22*$B$4 -> 4045.0323 | V22: =SUM(T22) -> 188 | W22: =V22*$B$4 -> 4045.0323 | X22: =SUM(Y22/73370) -> 0.60645161 | Y22: =SUM(C22+E22+G22+I22+K22+M22+O22+Q22+S22+U22+W22) -> 44495.355 | Z22: ='B5'!C21 -> 194 | AA22: =SUM(Z22*$Z$4) -> 1940 | AB22: =SUM(Z22) -> 194 | AC22: =SUM(AB22*$Z$4) -> 1940 | AD22: =SUM(AB22) -> 194 | AE22: =SUM(AD22*$Z$4) -> 1940 | AF22: =SUM(AD22) -> 194 | AG22: =SUM(AF22*$Z$4) -> 1940 | AH22: =SUM(AF22) -> 194 | AI22: =SUM(AH22*$Z$4) -> 1940 | AJ22: =SUM(AH22) -> 194 | AK22: =SUM(AJ22*$Z$4) -> 1940 | AL22: =SUM(AJ22) -> 194 | AM22: =SUM(AL22*$Z$4) -> 1940 | AN22: =SUM(AO22/19600) -> 0.69285714 | AO22: =SUM(AA22+AC22+AE22+AG22+AI22+AK22+AM22) -> 13580 | AQ22: =SUM(AR22/92970) -> 0.62466769 | AR22: =Y22+AO22 -> 58075.355 | AS22: =SUM(AR22-AR21-AT22) -> -2146.7419 | AV22: =IF(AT22>0,AU22,AV21) -> 0.94 | AW22: =-SUM('B5'!AI21) -> -93 | AX22: =-SUM(AW22-AS22) -> -2053.7419 | AY22: =SUM(AX22+AW22) -> -2146.7419 | AZ22: =ELEC!A19 -> 0 | BA22: ='General information '!D22 -> 22.5 | BB22: =SUM('General information '!E22) -> 0.7 | BC22: =IF(AR21>=AR22,0,1) -> 0 | BD22: 19222 | BE22: =(305/1185)*ELEC!Q20 -> 2261.6329 | BG22: =#REF!-BE22 -> #REF!
A23: =ELEC!C20 -> 44334 | B23: ='B5'!B22 -> 179 | C23: =B23*$B$4 -> 3851.3871 | D23: =SUM(B23) -> 179 | E23: =D23*$B$4 -> 3851.3871 | F23: =SUM(D23) -> 179 | G23: =F23*$B$4 -> 3851.3871 | H23: =SUM(F23) -> 179 | I23: =H23*$B$4 -> 3851.3871 | J23: =SUM(H23) -> 179 | K23: =J23*$B$4 -> 3851.3871 | L23: =SUM(J23) -> 179 | M23: =L23*$B$4 -> 3851.3871 | N23: =SUM(L23) -> 179 | O23: =N23*$B$4 -> 3851.3871 | P23: =SUM(N23) -> 179 | Q23: =P23*$B$4 -> 3851.3871 | R23: =SUM(P23) -> 179 | S23: =R23*$B$4 -> 3851.3871 | T23: =SUM(R23) -> 179 | U23: =T23*$B$4 -> 3851.3871 | V23: =SUM(T23) -> 179 | W23: =V23*$B$4 -> 3851.3871 | X23: =SUM(Y23/73370) -> 0.57741935 | Y23: =SUM(C23+E23+G23+I23+K23+M23+O23+Q23+S23+U23+W23) -> 42365.258 | Z23: ='B5'!C22 -> 186 | AA23: =SUM(Z23*$Z$4) -> 1860 | AB23: =SUM(Z23) -> 186 | AC23: =SUM(AB23*$Z$4) -> 1860 | AD23: =SUM(AB23) -> 186 | AE23: =SUM(AD23*$Z$4) -> 1860 | AF23: =SUM(AD23) -> 186 | AG23: =SUM(AF23*$Z$4) -> 1860 | AH23: =SUM(AF23) -> 186 | AI23: =SUM(AH23*$Z$4) -> 1860 | AJ23: =SUM(AH23) -> 186 | AK23: =SUM(AJ23*$Z$4) -> 1860 | AL23: =SUM(AJ23) -> 186 | AM23: =SUM(AL23*$Z$4) -> 1860 | AN23: =SUM(AO23/19600) -> 0.66428571 | AO23: =SUM(AA23+AC23+AE23+AG23+AI23+AK23+AM23) -> 13020 | AQ23: =SUM(AR23/92970) -> 0.59573258 | AR23: =Y23+AO23 -> 55385.258 | AS23: =SUM(AR23-AR22-AT23) -> -2690.0968 | AV23: =IF(AT23>0,AU23,AV22) -> 0.94 | AW23: =-SUM('B5'!AI22) -> -136 | AX23: =-SUM(AW23-AS23) -> -2554.0968 | AY23: =SUM(AX23+AW23) -> -2690.0968 | AZ23: =ELEC!A20 -> 0 | BA23: ='General information '!D23 -> 23 | BB23: =SUM('General information '!E23) -> 0.34 | BC23: =IF(AR22>=AR23,0,1) -> 0 | BD23: 19222 | BE23: =(305/1185)*ELEC!Q21 -> 3151.9241 | BG23: =#REF!-BE23 -> #REF!
A24: =ELEC!C21 -> 44335 | B24: ='B5'!B23 -> 170 | C24: =B24*$B$4 -> 3657.7419 | D24: =SUM(B24) -> 170 | E24: =D24*$B$4 -> 3657.7419 | F24: =SUM(D24) -> 170 | G24: =F24*$B$4 -> 3657.7419 | H24: =SUM(F24) -> 170 | I24: =H24*$B$4 -> 3657.7419 | J24: =SUM(H24) -> 170 | K24: =J24*$B$4 -> 3657.7419 | L24: =SUM(J24) -> 170 | M24: =L24*$B$4 -> 3657.7419 | N24: =SUM(L24) -> 170 | O24: =N24*$B$4 -> 3657.7419 | P24: =SUM(N24) -> 170 | Q24: =P24*$B$4 -> 3657.7419 | R24: =SUM(P24) -> 170 | S24: =R24*$B$4 -> 3657.7419 | T24: =SUM(R24) -> 170 | U24: =T24*$B$4 -> 3657.7419 | V24: =SUM(T24) -> 170 | W24: =V24*$B$4 -> 3657.7419 | X24: =SUM(Y24/73370) -> 0.5483871 | Y24: =SUM(C24+E24+G24+I24+K24+M24+O24+Q24+S24+U24+W24) -> 40235.161 | Z24: ='B5'!C23 -> 178 | AA24: =SUM(Z24*$Z$4) -> 1780 | AB24: =SUM(Z24) -> 178 | AC24: =SUM(AB24*$Z$4) -> 1780 | AD24: =SUM(AB24) -> 178 | AE24: =SUM(AD24*$Z$4) -> 1780 | AF24: =SUM(AD24) -> 178 | AG24: =SUM(AF24*$Z$4) -> 1780 | AH24: =SUM(AF24) -> 178 | AI24: =SUM(AH24*$Z$4) -> 1780 | AJ24: =SUM(AH24) -> 178 | AK24: =SUM(AJ24*$Z$4) -> 1780 | AL24: =SUM(AJ24) -> 178 | AM24: =SUM(AL24*$Z$4) -> 1780 | AN24: =SUM(AO24/19600) -> 0.63571429 | AO24: =SUM(AA24+AC24+AE24+AG24+AI24+AK24+AM24) -> 12460 | AQ24: =SUM(AR24/92970) -> 0.56679748 | AR24: =Y24+AO24 -> 52695.161 | AS24: =SUM(AR24-AR23-AT24) -> -2690.0968 | AV24: =IF(AT24>0,AU24,AV23) -> 0.94 | AW24: =-SUM('B5'!AI23) -> -95 | AX24: =-SUM(AW24-AS24) -> -2595.0968 | AY24: =SUM(AX24+AW24) -> -2690.0968 | AZ24: =ELEC!A21 -> 0 | BA24: ='General information '!D24 -> 23 | BB24: =SUM('General information '!E24) -> 0.73 | BC24: =IF(AR23>=AR24,0,1) -> 0 | BD24: 19222 | BE24: =(305/1185)*ELEC!Q22 -> 1888.4262 | BG24: =#REF!-BE24 -> #REF!
A25: =ELEC!C22 -> 44336 | B25: ='B5'!B24 -> 203 | C25: =B25*$B$4 -> 4367.7742 | D25: =SUM(B25) -> 203 | E25: =D25*$B$4 -> 4367.7742 | F25: =SUM(D25) -> 203 | G25: =F25*$B$4 -> 4367.7742 | H25: =SUM(F25) -> 203 | I25: =H25*$B$4 -> 4367.7742 | J25: =SUM(H25) -> 203 | K25: =J25*$B$4 -> 4367.7742 | L25: =SUM(J25) -> 203 | M25: =L25*$B$4 -> 4367.7742 | N25: =SUM(L25) -> 203 | O25: =N25*$B$4 -> 4367.7742 | P25: =SUM(N25) -> 203 | Q25: =P25*$B$4 -> 4367.7742 | R25: =SUM(P25) -> 203 | S25: =R25*$B$4 -> 4367.7742 | T25: =SUM(R25) -> 203 | U25: =T25*$B$4 -> 4367.7742 | V25: =SUM(T25) -> 203 | W25: =V25*$B$4 -> 4367.7742 | X25: =SUM(Y25/73370) -> 0.65483871 | Y25: =SUM(C25+E25+G25+I25+K25+M25+O25+Q25+S25+U25+W25) -> 48045.516 | Z25: ='B5'!C24 -> 210 | AA25: =SUM(Z25*$Z$4) -> 2100 | AB25: =SUM(Z25) -> 210 | AC25: =SUM(AB25*$Z$4) -> 2100 | AD25: =SUM(AB25) -> 210 | AE25: =SUM(AD25*$Z$4) -> 2100 | AF25: =SUM(AD25) -> 210 | AG25: =SUM(AF25*$Z$4) -> 2100 | AH25: =SUM(AF25) -> 210 | AI25: =SUM(AH25*$Z$4) -> 2100 | AJ25: =SUM(AH25) -> 210 | AK25: =SUM(AJ25*$Z$4) -> 2100 | AL25: =SUM(AJ25) -> 210 | AM25: =SUM(AL25*$Z$4) -> 2100 | AN25: =SUM(AO25/19600) -> 0.75 | AO25: =SUM(AA25+AC25+AE25+AG25+AI25+AK25+AM25) -> 14700 | AQ25: =SUM(AR25/92970) -> 0.67490068 | AR25: =Y25+AO25 -> 62745.516 | AS25: =SUM(AR25-AR24-AT25) -> -1618.4452 | AT25: 11668.8 | AU25: 1.003 | AV25: =IF(AT25>0,AU25,AV24) -> 1.003 | AW25: =-SUM('B5'!AI24) -> -63 | AX25: =-SUM(AW25-AS25) -> -1555.4452 | AY25: =SUM(AX25+AW25) -> -1618.4452 | AZ25: =ELEC!A22 -> 0 | BA25: ='General information '!D25 -> 23.5 | BB25: =SUM('General information '!E25) -> 0.77 | BC25: =IF(AR24>=AR25,0,1) -> 1 | BD25: 19222 | BE25: =(305/1185)*ELEC!Q23 -> 2046.7173 | BG25: =#REF!-BE25 -> #REF!
A26: =ELEC!C23 -> 44337 | B26: ='B5'!B25 -> 194 | C26: =B26*$B$4 -> 4174.129 | D26: =SUM(B26) -> 194 | E26: =D26*$B$4 -> 4174.129 | F26: =SUM(D26) -> 194 | G26: =F26*$B$4 -> 4174.129 | H26: =SUM(F26) -> 194 | I26: =H26*$B$4 -> 4174.129 | J26: =SUM(H26) -> 194 | K26: =J26*$B$4 -> 4174.129 | L26: =SUM(J26) -> 194 | M26: =L26*$B$4 -> 4174.129 | N26: =SUM(L26) -> 194 | O26: =N26*$B$4 -> 4174.129 | P26: =SUM(N26) -> 194 | Q26: =P26*$B$4 -> 4174.129 | R26: =SUM(P26) -> 194 | S26: =R26*$B$4 -> 4174.129 | T26: =SUM(R26) -> 194 | U26: =T26*$B$4 -> 4174.129 | V26: =SUM(T26) -> 194 | W26: =V26*$B$4 -> 4174.129 | X26: =SUM(Y26/73370) -> 0.62580645 | Y26: =SUM(C26+E26+G26+I26+K26+M26+O26+Q26+S26+U26+W26) -> 45915.419 | Z26: ='B5'!C25 -> 201 | AA26: =SUM(Z26*$Z$4) -> 2010 | AB26: =SUM(Z26) -> 201 | AC26: =SUM(AB26*$Z$4) -> 2010 | AD26: =SUM(AB26) -> 201 | AE26: =SUM(AD26*$Z$4) -> 2010 | AF26: =SUM(AD26) -> 201 | AG26: =SUM(AF26*$Z$4) -> 2010 | AH26: =SUM(AF26) -> 201 | AI26: =SUM(AH26*$Z$4) -> 2010 | AJ26: =SUM(AH26) -> 201 | AK26: =SUM(AJ26*$Z$4) -> 2010 | AL26: =SUM(AJ26) -> 201 | AM26: =SUM(AL26*$Z$4) -> 2010 | AN26: =SUM(AO26/19600) -> 0.71785714 | AO26: =SUM(AA26+AC26+AE26+AG26+AI26+AK26+AM26) -> 14070 | AQ26: =SUM(AR26/92970) -> 0.64521264 | AR26: =Y26+AO26 -> 59985.419 | AS26: =SUM(AR26-AR25-AT26) -> -2760.0968 | AV26: =IF(AT26>0,AU26,AV25) -> 1.003 | AW26: =-SUM('B5'!AI25) -> -209 | AX26: =-SUM(AW26-AS26) -> -2551.0968 | AY26: =SUM(AX26+AW26) -> -2760.0968 | AZ26: =ELEC!A23 -> 0 | BA26: ='General information '!D26 -> 24.5 | BB26: =SUM('General information '!E26) -> 0.47 | BC26: =IF(AR25>=AR26,0,1) -> 0 | BD26: 19222 | BE26: =(305/1185)*ELEC!Q24 -> 2714.6287 | BG26: =#REF!-BE26 -> #REF!
A27: =ELEC!C24 -> 44338 | B27: ='B5'!B26 -> 182 | C27: =B27*$B$4 -> 3915.9355 | D27: =SUM(B27) -> 182 | E27: =D27*$B$4 -> 3915.9355 | F27: =SUM(D27) -> 182 | G27: =F27*$B$4 -> 3915.9355 | H27: =SUM(F27) -> 182 | I27: =H27*$B$4 -> 3915.9355 | J27: =SUM(H27) -> 182 | K27: =J27*$B$4 -> 3915.9355 | L27: =SUM(J27) -> 182 | M27: =L27*$B$4 -> 3915.9355 | N27: =SUM(L27) -> 182 | O27: =N27*$B$4 -> 3915.9355 | P27: =SUM(N27) -> 182 | Q27: =P27*$B$4 -> 3915.9355 | R27: =SUM(P27) -> 182 | S27: =R27*$B$4 -> 3915.9355 | T27: =SUM(R27) -> 182 | U27: =T27*$B$4 -> 3915.9355 | V27: =SUM(T27) -> 182 | W27: =V27*$B$4 -> 3915.9355 | X27: =SUM(Y27/73370) -> 0.58709677 | Y27: =SUM(C27+E27+G27+I27+K27+M27+O27+Q27+S27+U27+W27) -> 43075.29 | Z27: ='B5'!C26 -> 189 | AA27: =SUM(Z27*$Z$4) -> 1890 | AB27: =SUM(Z27) -> 189 | AC27: =SUM(AB27*$Z$4) -> 1890 | AD27: =SUM(AB27) -> 189 | AE27: =SUM(AD27*$Z$4) -> 1890 | AF27: =SUM(AD27) -> 189 | AG27: =SUM(AF27*$Z$4) -> 1890 | AH27: =SUM(AF27) -> 189 | AI27: =SUM(AH27*$Z$4) -> 1890 | AJ27: =SUM(AH27) -> 189 | AK27: =SUM(AJ27*$Z$4) -> 1890 | AL27: =SUM(AJ27) -> 189 | AM27: =SUM(AL27*$Z$4) -> 1890 | AN27: =SUM(AO27/19600) -> 0.675 | AO27: =SUM(AA27+AC27+AE27+AG27+AI27+AK27+AM27) -> 13230 | AQ27: =SUM(AR27/92970) -> 0.60562859 | AR27: =Y27+AO27 -> 56305.29 | AS27: =SUM(AR27-AR26-AT27) -> -3680.129 | AV27: =IF(AT27>0,AU27,AV26) -> 1.003 | AW27: =-SUM('B5'!AI26) -> -129 | AX27: =-SUM(AW27-AS27) -> -3551.129 | AY27: =SUM(AX27+AW27) -> -3680.129 | AZ27: =ELEC!A24 -> 0 | BA27: ='General information '!D27 -> 24.5 | BB27: =SUM('General information '!E27) -> 0.5 | BC27: =IF(AR26>=AR27,0,1) -> 0 | BD27: 19222 | BE27: =(305/1185)*ELEC!Q25 -> 1424.6203 | BG27: =#REF!-BE27 -> #REF!
A28: =ELEC!C25 -> 44339 | B28: ='B5'!B27 -> 176 | C28: =B28*$B$4 -> 3786.8387 | D28: =SUM(B28) -> 176 | E28: =D28*$B$4 -> 3786.8387 | F28: =SUM(D28) -> 176 | G28: =F28*$B$4 -> 3786.8387 | H28: =SUM(F28) -> 176 | I28: =H28*$B$4 -> 3786.8387 | J28: =SUM(H28) -> 176 | K28: =J28*$B$4 -> 3786.8387 | L28: =SUM(J28) -> 176 | M28: =L28*$B$4 -> 3786.8387 | N28: =SUM(L28) -> 176 | O28: =N28*$B$4 -> 3786.8387 | P28: =SUM(N28) -> 176 | Q28: =P28*$B$4 -> 3786.8387 | R28: =SUM(P28) -> 176 | S28: =R28*$B$4 -> 3786.8387 | T28: =SUM(R28) -> 176 | U28: =T28*$B$4 -> 3786.8387 | V28: =SUM(T28) -> 176 | W28: =V28*$B$4 -> 3786.8387 | X28: =SUM(Y28/73370) -> 0.56774194 | Y28: =SUM(C28+E28+G28+I28+K28+M28+O28+Q28+S28+U28+W28) -> 41655.226 | Z28: ='B5'!C27 -> 182.5 | AA28: =SUM(Z28*$Z$4) -> 1825 | AB28: =SUM(Z28) -> 182.5 | AC28: =SUM(AB28*$Z$4) -> 1825 | AD28: =SUM(AB28) -> 182.5 | AE28: =SUM(AD28*$Z$4) -> 1825 | AF28: =SUM(AD28) -> 182.5 | AG28: =SUM(AF28*$Z$4) -> 1825 | AH28: =SUM(AF28) -> 182.5 | AI28: =SUM(AH28*$Z$4) -> 1825 | AJ28: =SUM(AH28) -> 182.5 | AK28: =SUM(AJ28*$Z$4) -> 1825 | AL28: =SUM(AJ28) -> 182.5 | AM28: =SUM(AL28*$Z$4) -> 1825 | AN28: =SUM(AO28/19600) -> 0.65178571 | AO28: =SUM(AA28+AC28+AE28+AG28+AI28+AK28+AM28) -> 12775 | AQ28: =SUM(AR28/92970) -> 0.5854601 | AR28: =Y28+AO28 -> 54430.226 | AS28: =SUM(AR28-AR27-AT28) -> -1875.0645 | AV28: =IF(AT28>0,AU28,AV27) -> 1.003 | AW28: =-SUM('B5'!AI27) -> -69 | AX28: =-SUM(AW28-AS28) -> -1806.0645 | AY28: =SUM(AX28+AW28) -> -1875.0645 | AZ28: =ELEC!A25 -> 0 | BA28: ='General information '!D28 -> 23.5 | BB28: =SUM('General information '!E28) -> 0.55 | BC28: =IF(AR27>=AR28,0,1) -> 0 | BD28: 19222 | BE28: =(305/1185)*ELEC!Q26 -> 3205.4599 | BG28: =#REF!-BE28 -> #REF!
A29: =ELEC!C26 -> 44340 | B29: ='B5'!B28 -> 208 | C29: =B29*$B$4 -> 4475.3548 | D29: =SUM(B29) -> 208 | E29: =D29*$B$4 -> 4475.3548 | F29: =SUM(D29) -> 208 | G29: =F29*$B$4 -> 4475.3548 | H29: =SUM(F29) -> 208 | I29: =H29*$B$4 -> 4475.3548 | J29: =SUM(H29) -> 208 | K29: =J29*$B$4 -> 4475.3548 | L29: =SUM(J29) -> 208 | M29: =L29*$B$4 -> 4475.3548 | N29: =SUM(L29) -> 208 | O29: =N29*$B$4 -> 4475.3548 | P29: =SUM(N29) -> 208 | Q29: =P29*$B$4 -> 4475.3548 | R29: =SUM(P29) -> 208 | S29: =R29*$B$4 -> 4475.3548 | T29: =SUM(R29) -> 208 | U29: =T29*$B$4 -> 4475.3548 | V29: =SUM(T29) -> 208 | W29: =V29*$B$4 -> 4475.3548 | X29: =SUM(Y29/73370) -> 0.67096774 | Y29: =SUM(C29+E29+G29+I29+K29+M29+O29+Q29+S29+U29+W29) -> 49228.903 | Z29: ='B5'!C28 -> 215 | AA29: =SUM(Z29*$Z$4) -> 2150 | AB29: =SUM(Z29) -> 215 | AC29: =SUM(AB29*$Z$4) -> 2150 | AD29: =SUM(AB29) -> 215 | AE29: =SUM(AD29*$Z$4) -> 2150 | AF29: =SUM(AD29) -> 215 | AG29: =SUM(AF29*$Z$4) -> 2150 | AH29: =SUM(AF29) -> 215 | AI29: =SUM(AH29*$Z$4) -> 2150 | AJ29: =SUM(AH29) -> 215 | AK29: =SUM(AJ29*$Z$4) -> 2150 | AL29: =SUM(AJ29) -> 215 | AM29: =SUM(AL29*$Z$4) -> 2150 | AN29: =SUM(AO29/19600) -> 0.76785714 | AO29: =SUM(AA29+AC29+AE29+AG29+AI29+AK29+AM29) -> 15050 | AQ29: =SUM(AR29/92970) -> 0.69139403 | AR29: =Y29+AO29 -> 64278.903 | AS29: =SUM(AR29-AR28-AT29) -> -2211.3226 | AT29: 12060 | AU29: 1.003 | AV29: =IF(AT29>0,AU29,AV28) -> 1.003 | AW29: =-SUM('B5'!AI28) -> -211.2 | AX29: =-SUM(AW29-AS29) -> -2000.1226 | AY29: =SUM(AX29+AW29) -> -2211.3226 | AZ29: =ELEC!A26 -> 0 | BA29: ='General information '!D29 -> 24.5 | BB29: =SUM('General information '!E29) -> 0.55 | BC29: =IF(AR28>=AR29,0,1) -> 1 | BD29: 19222 | BE29: =(305/1185)*ELEC!Q27 -> 1589.346 | BG29: =#REF!-BE29 -> #REF!
A30: =ELEC!C27 -> 44341 | B30: ='B5'!B29 -> 201 | C30: =B30*$B$4 -> 4324.7419 | D30: =SUM(B30) -> 201 | E30: =D30*$B$4 -> 4324.7419 | F30: =SUM(D30) -> 201 | G30: =F30*$B$4 -> 4324.7419 | H30: =SUM(F30) -> 201 | I30: =H30*$B$4 -> 4324.7419 | J30: =SUM(H30) -> 201 | K30: =J30*$B$4 -> 4324.7419 | L30: =SUM(J30) -> 201 | M30: =L30*$B$4 -> 4324.7419 | N30: =SUM(L30) -> 201 | O30: =N30*$B$4 -> 4324.7419 | P30: =SUM(N30) -> 201 | Q30: =P30*$B$4 -> 4324.7419 | R30: =SUM(P30) -> 201 | S30: =R30*$B$4 -> 4324.7419 | T30: =SUM(R30) -> 201 | U30: =T30*$B$4 -> 4324.7419 | V30: =SUM(T30) -> 201 | W30: =V30*$B$4 -> 4324.7419 | X30: =SUM(Y30/73370) -> 0.6483871 | Y30: =SUM(C30+E30+G30+I30+K30+M30+O30+Q30+S30+U30+W30) -> 47572.161 | Z30: ='B5'!C29 -> 208 | AA30: =SUM(Z30*$Z$4) -> 2080 | AB30: =SUM(Z30) -> 208 | AC30: =SUM(AB30*$Z$4) -> 2080 | AD30: =SUM(AB30) -> 208 | AE30: =SUM(AD30*$Z$4) -> 2080 | AF30: =SUM(AD30) -> 208 | AG30: =SUM(AF30*$Z$4) -> 2080 | AH30: =SUM(AF30) -> 208 | AI30: =SUM(AH30*$Z$4) -> 2080 | AJ30: =SUM(AH30) -> 208 | AK30: =SUM(AJ30*$Z$4) -> 2080 | AL30: =SUM(AJ30) -> 208 | AM30: =SUM(AL30*$Z$4) -> 2080 | AN30: =SUM(AO30/19600) -> 0.74285714 | AO30: =SUM(AA30+AC30+AE30+AG30+AI30+AK30+AM30) -> 14560 | AQ30: =SUM(AR30/92970) -> 0.66830334 | AR30: =Y30+AO30 -> 62132.161 | AS30: =SUM(AR30-AR29-AT30) -> -2146.7419 | AV30: =IF(AT30>0,AU30,AV29) -> 1.003 | AW30: =-SUM('B5'!AI29) -> -90 | AX30: =-SUM(AW30-AS30) -> -2056.7419 | AY30: =SUM(AX30+AW30) -> -2146.7419 | AZ30: =ELEC!A27 -> 0 | BA30: ='General information '!D30 -> 24.5 | BB30: =SUM('General information '!E30) -> 0.66 | BC30: =IF(AR29>=AR30,0,1) -> 0 | BD30: 19222 | BE30: =(305/1185)*ELEC!Q28 -> 3368.1266 | BG30: =#REF!-BE30 -> #REF!
A31: =ELEC!C28 -> 44342 | B31: ='B5'!B30 -> 187 | C31: =B31*$B$4 -> 4023.5161 | D31: =SUM(B31) -> 187 | E31: =D31*$B$4 -> 4023.5161 | F31: =SUM(D31) -> 187 | G31: =F31*$B$4 -> 4023.5161 | H31: =SUM(F31) -> 187 | I31: =H31*$B$4 -> 4023.5161 | J31: =SUM(H31) -> 187 | K31: =J31*$B$4 -> 4023.5161 | L31: =SUM(J31) -> 187 | M31: =L31*$B$4 -> 4023.5161 | N31: =SUM(L31) -> 187 | O31: =N31*$B$4 -> 4023.5161 | P31: =SUM(N31) -> 187 | Q31: =P31*$B$4 -> 4023.5161 | R31: =SUM(P31) -> 187 | S31: =R31*$B$4 -> 4023.5161 | T31: =SUM(R31) -> 187 | U31: =T31*$B$4 -> 4023.5161 | V31: =SUM(T31) -> 187 | W31: =V31*$B$4 -> 4023.5161 | X31: =SUM(Y31/73370) -> 0.60322581 | Y31: =SUM(C31+E31+G31+I31+K31+M31+O31+Q31+S31+U31+W31) -> 44258.677 | Z31: ='B5'!C30 -> 194 | AA31: =SUM(Z31*$Z$4) -> 1940 | AB31: =SUM(Z31) -> 194 | AC31: =SUM(AB31*$Z$4) -> 1940 | AD31: =SUM(AB31) -> 194 | AE31: =SUM(AD31*$Z$4) -> 1940 | AF31: =SUM(AD31) -> 194 | AG31: =SUM(AF31*$Z$4) -> 1940 | AH31: =SUM(AF31) -> 194 | AI31: =SUM(AH31*$Z$4) -> 1940 | AJ31: =SUM(AH31) -> 194 | AK31: =SUM(AJ31*$Z$4) -> 1940 | AL31: =SUM(AJ31) -> 194 | AM31: =SUM(AL31*$Z$4) -> 1940 | AN31: =SUM(AO31/19600) -> 0.69285714 | AO31: =SUM(AA31+AC31+AE31+AG31+AI31+AK31+AM31) -> 13580 | AQ31: =SUM(AR31/92970) -> 0.62212195 | AR31: =Y31+AO31 -> 57838.677 | AS31: =SUM(AR31-AR30-AT31) -> -4293.4839 | AV31: =IF(AT31>0,AU31,AV30) -> 1.003 | AW31: =-SUM('B5'!AI30) -> -114 | AX31: =-SUM(AW31-AS31) -> -4179.4839 | AY31: =SUM(AX31+AW31) -> -4293.4839 | AZ31: =ELEC!A28 -> 0 | BA31: ='General information '!D31 -> 24.5 | BB31: =SUM('General information '!E31) -> 0.65 | BC31: =IF(AR30>=AR31,0,1) -> 0 | BD31: 19222 | BE31: =(305/1185)*ELEC!Q29 -> 2428.6751 | BG31: =#REF!-BE31 -> #REF!
A32: =ELEC!C29 -> 44343 | B32: ='B5'!B31 -> 177 | C32: =B32*$B$4 -> 3808.3548 | D32: =SUM(B32) -> 177 | E32: =D32*$B$4 -> 3808.3548 | F32: =SUM(D32) -> 177 | G32: =F32*$B$4 -> 3808.3548 | H32: =SUM(F32) -> 177 | I32: =H32*$B$4 -> 3808.3548 | J32: =SUM(H32) -> 177 | K32: =J32*$B$4 -> 3808.3548 | L32: =SUM(J32) -> 177 | M32: =L32*$B$4 -> 3808.3548 | N32: =SUM(L32) -> 177 | O32: =N32*$B$4 -> 3808.3548 | P32: =SUM(N32) -> 177 | Q32: =P32*$B$4 -> 3808.3548 | R32: =SUM(P32) -> 177 | S32: =R32*$B$4 -> 3808.3548 | T32: =SUM(R32) -> 177 | U32: =T32*$B$4 -> 3808.3548 | V32: =SUM(T32) -> 177 | W32: =V32*$B$4 -> 3808.3548 | X32: =SUM(Y32/73370) -> 0.57096774 | Y32: =SUM(C32+E32+G32+I32+K32+M32+O32+Q32+S32+U32+W32) -> 41891.903 | Z32: ='B5'!C31 -> 184 | AA32: =SUM(Z32*$Z$4) -> 1840 | AB32: =SUM(Z32) -> 184 | AC32: =SUM(AB32*$Z$4) -> 1840 | AD32: =SUM(AB32) -> 184 | AE32: =SUM(AD32*$Z$4) -> 1840 | AF32: =SUM(AD32) -> 184 | AG32: =SUM(AF32*$Z$4) -> 1840 | AH32: =SUM(AF32) -> 184 | AI32: =SUM(AH32*$Z$4) -> 1840 | AJ32: =SUM(AH32) -> 184 | AK32: =SUM(AJ32*$Z$4) -> 1840 | AL32: =SUM(AJ32) -> 184 | AM32: =SUM(AL32*$Z$4) -> 1840 | AN32: =SUM(AO32/19600) -> 0.65714286 | AO32: =SUM(AA32+AC32+AE32+AG32+AI32+AK32+AM32) -> 12880 | AQ32: =SUM(AR32/92970) -> 0.58913524 | AR32: =Y32+AO32 -> 54771.903 | AS32: =SUM(AR32-AR31-AT32) -> -3066.7742 | AV32: =IF(AT32>0,AU32,AV31) -> 1.003 | AW32: =-SUM('B5'!AI31) -> -106 | AX32: =-SUM(AW32-AS32) -> -2960.7742 | AY32: =SUM(AX32+AW32) -> -3066.7742 | AZ32: =ELEC!A29 -> 0 | BA32: ='General information '!D32 -> 23.5 | BB32: =SUM('General information '!E32) -> 0.6 | BC32: =IF(AR31>=AR32,0,1) -> 0 | BD32: 19222 | BE32: =(305/1185)*ELEC!Q30 -> 0 | BG32: =#REF!-BE32 -> #REF!
