Workbook

Sheet Total
A1: Site Name | B1: Day | C1: Month | D1: Year | E1: Total Electricity Kwh | F1: Electricity Tariff ($/Kwh) | G1: Total Fuel Oil (Liters) | H1: Fuel Oil $/Liter | I1: LPG (Kg) | J1: LPG $/Kg | K1: Water Utility Supply (m3) m3 | L1: Water Utility Supply (m3) $/m3 | M1: Irrigation Water (m3) m3 | N1: Irrigation water $/m3 | O1: Room Nights
A2: Beirut | B2: 1 | C2: 6 | D2: 2021 | E2: =ELEC!N4 -> 9940 | F2: =SUM('EDl log'!T4) -> #DIV/0! | G2: =-tanks!AW6 -> 0 | H2: =SUM(tanks!AV6) -> 1.003 | I2: =('B5'!AU5)*0.51 -> 0 | J2: ='B5'!AX5/0.51 -> 1.5686275 | K2: =WATER!I6 -> 0 | L2: =SUM(WATER!J6) -> 0 | M2: =WATER!Q6 -> 0 | N2: 0.6 | O2: =ELEC!B4 -> 0
A3: Beirut | B3: =B2+1 -> 2 | C3: 6 | D3: 2021 | E3: =ELEC!N5 -> 0 | F3: =SUM('EDl log'!T5) -> 0 | G3: =-tanks!AW7 -> 0 | H3: =SUM(tanks!AV7) -> 1.003 | I3: =('B5'!AU6)*0.51 -> 0 | J3: ='B5'!AX6/0.51 -> 1.5686275 | K3: =WATER!I7 -> 0 | L3: =SUM(WATER!J7) -> 0 | M3: =WATER!Q7 -> 0 | N3: 0.6 | O3: =ELEC!B5 -> 0
A4: Beirut | B4: =B3+1 -> 3 | C4: 6 | D4: 2021 | E4: =ELEC!N6 -> 0 | F4: =SUM('EDl log'!T6) -> 0 | G4: =-tanks!AW8 -> 0 | H4: =SUM(tanks!AV8) -> 1.003 | I4: =('B5'!AU7)*0.51 -> 0 | J4: ='B5'!AX7/0.51 -> 1.5686275 | K4: =WATER!I8 -> 0 | L4: =SUM(WATER!J8) -> 0 | M4: =WATER!Q8 -> 0 | N4: 0.6 | O4: =ELEC!B6 -> 0
A5: Beirut | B5: =B4+1 -> 4 | C5: 6 | D5: 2021 | E5: =ELEC!N7 -> 0 | F5: =SUM('EDl log'!T7) -> 0 | G5: =-tanks!AW9 -> 0 | H5: =SUM(tanks!AV9) -> 1.003 | I5: =('B5'!AU8)*0.51 -> 0 | J5: ='B5'!AX8/0.51 -> 1.5686275 | K5: =WATER!I9 -> 0 | L5: =SUM(WATER!J9) -> 0 | M5: =WATER!Q9 -> 0 | N5: 0.6 | O5: =ELEC!B7 -> 0
A6: Beirut | B6: =B5+1 -> 5 | C6: 6 | D6: 2021 | E6: =ELEC!N8 -> 0 | F6: =SUM('EDl log'!T8) -> 0 | G6: =-tanks!AW10 -> 0 | H6: =SUM(tanks!AV10) -> 1.003 | I6: =('B5'!AU9)*0.51 -> 0 | J6: ='B5'!AX9/0.51 -> 1.5686275 | K6: =WATER!I10 -> 0 | L6: =SUM(WATER!J10) -> 0 | M6: =WATER!Q10 -> 0 | N6: 0.6 | O6: =ELEC!B8 -> 0
A7: Beirut | B7: =B6+1 -> 6 | C7: 6 | D7: 2021 | E7: =ELEC!N9 -> 0 | F7: =SUM('EDl log'!T9) -> 0 | G7: =-tanks!AW11 -> 0 | H7: =SUM(tanks!AV11) -> 1.003 | I7: =('B5'!AU10)*0.51 -> 0 | J7: ='B5'!AX10/0.51 -> 1.5686275 | K7: =WATER!I11 -> 0 | L7: =SUM(WATER!J11) -> 0 | M7: =WATER!Q11 -> 0 | N7: 0.6 | O7: =ELEC!B9 -> 0
A8: Beirut | B8: =B7+1 -> 7 | C8: 6 | D8: 2021 | E8: =ELEC!N10 -> 0 | F8: =SUM('EDl log'!T10) -> 0 | G8: =-tanks!AW12 -> 0 | H8: =SUM(tanks!AV12) -> 1.003 | I8: =('B5'!AU11)*0.51 -> 0 | J8: ='B5'!AX11/0.51 -> 1.5686275 | K8: =WATER!I12 -> 0 | L8: =SUM(WATER!J12) -> 0 | M8: =WATER!Q12 -> 0 | N8: 0.6 | O8: =ELEC!B10 -> 0
A9: Beirut | B9: =B8+1 -> 8 | C9: 6 | D9: 2021 | E9: =ELEC!N11 -> 0 | F9: =SUM('EDl log'!T11) -> 0 | G9: =-tanks!AW13 -> 0 | H9: =SUM(tanks!AV13) -> 1.003 | I9: =('B5'!AU12)*0.51 -> 0 | J9: ='B5'!AX12/0.51 -> 1.5686275 | K9: =WATER!I13 -> 0 | L9: =SUM(WATER!J13) -> 0 | M9: =WATER!Q13 -> 0 | N9: 0.6 | O9: =ELEC!B11 -> 0
A10: Beirut | B10: =B9+1 -> 9 | C10: 6 | D10: 2021 | E10: =ELEC!N12 -> 0 | F10: =SUM('EDl log'!T12) -> 0 | G10: =-tanks!AW14 -> 0 | H10: =SUM(tanks!AV14) -> 1.003 | I10: =('B5'!AU13)*0.51 -> 0 | J10: ='B5'!AX13/0.51 -> 1.5686275 | K10: =WATER!I14 -> 0 | L10: =SUM(WATER!J14) -> 0 | M10: =WATER!Q14 -> 0 | N10: 0.6 | O10: =ELEC!B12 -> 0
A11: Beirut | B11: =B10+1 -> 10 | C11: 6 | D11: 2021 | E11: =ELEC!N13 -> 0 | F11: =SUM('EDl log'!T13) -> 0 | G11: =-tanks!AW15 -> 0 | H11: =SUM(tanks!AV15) -> 1.003 | I11: =('B5'!AU14)*0.51 -> 0 | J11: ='B5'!AX14/0.51 -> 1.5686275 | K11: =WATER!I15 -> 0 | L11: =SUM(WATER!J15) -> 0 | M11: =WATER!Q15 -> 0 | N11: 0.6 | O11: =ELEC!B13 -> 0
A12: Beirut | B12: =B11+1 -> 11 | C12: 6 | D12: 2021 | E12: =ELEC!N14 -> 0 | F12: =SUM('EDl log'!T14) -> 0 | G12: =-tanks!AW16 -> 0 | H12: =SUM(tanks!AV16) -> 1.003 | I12: =('B5'!AU15)*0.51 -> 0 | J12: ='B5'!AX15/0.51 -> 1.5686275 | K12: =WATER!I16 -> 0 | L12: =SUM(WATER!J16) -> 0 | M12: =WATER!Q16 -> 0 | N12: 0.6 | O12: =ELEC!B14 -> 0
A13: Beirut | B13: =B12+1 -> 12 | C13: 6 | D13: 2021 | E13: =ELEC!N15 -> 0 | F13: =SUM('EDl log'!T15) -> 0 | G13: =-tanks!AW17 -> 0 | H13: =SUM(tanks!AV17) -> 1.003 | I13: =('B5'!AU16)*0.51 -> 0 | J13: ='B5'!AX16/0.51 -> 1.5686275 | K13: =WATER!I17 -> 0 | L13: =SUM(WATER!J17) -> 0 | M13: =WATER!Q17 -> 0 | N13: 0.6 | O13: =ELEC!B15 -> 0
A14: Beirut | B14: =B13+1 -> 13 | C14: 6 | D14: 2021 | E14: =ELEC!N16 -> 0 | F14: =SUM('EDl log'!T16) -> 0 | G14: =-tanks!AW18 -> 0 | H14: =SUM(tanks!AV18) -> 1.003 | I14: =('B5'!AU17)*0.51 -> 0 | J14: ='B5'!AX17/0.51 -> 1.5686275 | K14: =WATER!I18 -> 0 | L14: =SUM(WATER!J18) -> 0 | M14: =WATER!Q18 -> 0 | N14: 0.6 | O14: =ELEC!B16 -> 0
... A31: Beirut | B31: =B30+1 -> 30 | C31: 6 | D31: 2021 | E31: =ELEC!N33 -> 0 | F31: =SUM('EDl log'!T33) -> 0 | G31: =-tanks!AW35 -> 0 | H31: =SUM(tanks!AV35) -> 1.003 | I31: =('B5'!AU34)*0.51 -> 0 | J31: ='B5'!AX34/0.51 -> 1.5686275 | K31: =WATER!I35 -> 0 | L31: =SUM(WATER!J35) -> 0 | M31: =WATER!Q35 -> 0 | N31: 0.6 | O31: =ELEC!B33 -> 0

Sheet Submetering
A1: Site Name | B1: Day | C1: Month | D1: Year | E1: ATS1 Kwh | F1: ATS2 Kwh | G1: ATS3 Kwh | H1: ATS4 Kwh | I1: ATS5 Kwh | J1: Guest (m3) | K1: Kitchen & Laundry (m3) | L1: Room Nights
A2: Beirut | B2: 1 | C2: 6 | D2: 2021 | E2: =ELEC!M4 -> 1550 | F2: =ELEC!K4 -> 4758 | G2: =ELEC!I4 -> 742 | H2: =ELEC!E4 -> 2415 | I2: =ELEC!G4 -> 475 | J2: =WATER!Y6 -> 0 | K2: =WATER!AJ6 -> 0 | L2: =ELEC!B4 -> 0
A3: Beirut | B3: =B2+1 -> 2 | C3: 6 | D3: 2021 | E3: =ELEC!M5 -> 0 | F3: =ELEC!K5 -> 0 | G3: =ELEC!I5 -> 0 | H3: =ELEC!E5 -> 0 | I3: =ELEC!G5 -> 0 | J3: =WATER!Y7 -> 0 | K3: =WATER!AJ7 -> 0 | L3: =ELEC!B5 -> 0
A4: Beirut | B4: =B3+1 -> 3 | C4: 6 | D4: 2021 | E4: =ELEC!M6 -> 0 | F4: =ELEC!K6 -> 0 | G4: =ELEC!I6 -> 0 | H4: =ELEC!E6 -> 0 | I4: =ELEC!G6 -> 0 | J4: =WATER!Y8 -> 0 | K4: =WATER!AJ8 -> 0 | L4: =ELEC!B6 -> 0
A5: Beirut | B5: =B4+1 -> 4 | C5: 6 | D5: 2021 | E5: =ELEC!M7 -> 0 | F5: =ELEC!K7 -> 0 | G5: =ELEC!I7 -> 0 | H5: =ELEC!E7 -> 0 | I5: =ELEC!G7 -> 0 | J5: =WATER!Y9 -> 0 | K5: =WATER!AJ9 -> 0 | L5: =ELEC!B7 -> 0
A6: Beirut | B6: =B5+1 -> 5 | C6: 6 | D6: 2021 | E6: =ELEC!M8 -> 0 | F6: =ELEC!K8 -> 0 | G6: =ELEC!I8 -> 0 | H6: =ELEC!E8 -> 0 | I6: =ELEC!G8 -> 0 | J6: =WATER!Y10 -> 0 | K6: =WATER!AJ10 -> 0 | L6: =ELEC!B8 -> 0
A7: Beirut | B7: =B6+1 -> 6 | C7: 6 | D7: 2021 | E7: =ELEC!M9 -> 0 | F7: =ELEC!K9 -> 0 | G7: =ELEC!I9 -> 0 | H7: =ELEC!AO9 -> 0 | I7: =ELEC!G9 -> 0 | J7: =WATER!Y11 -> 0 | K7: =WATER!AJ11 -> 0 | L7: =ELEC!B9 -> 0
A8: Beirut | B8: =B7+1 -> 7 | C8: 6 | D8: 2021 | E8: =ELEC!M10 -> 0 | F8: =ELEC!K10 -> 0 | G8: =ELEC!I10 -> 0 | H8: =ELEC!AO10 -> 0 | I8: =ELEC!G10 -> 0 | J8: =WATER!Y12 -> 0 | K8: =WATER!AJ12 -> 0 | L8: =ELEC!B10 -> 0
A9: Beirut | B9: =B8+1 -> 8 | C9: 6 | D9: 2021 | E9: =ELEC!M11 -> 0 | F9: =ELEC!K11 -> 0 | G9: =ELEC!I11 -> 0 | H9: =ELEC!AO11 -> 0 | I9: =ELEC!G11 -> 0 | J9: =WATER!Y13 -> 0 | K9: =WATER!AJ13 -> 0 | L9: =ELEC!B11 -> 0
A10: Beirut | B10: =B9+1 -> 9 | C10: 6 | D10: 2021 | E10: =ELEC!M12 -> 0 | F10: =ELEC!K12 -> 0 | G10: =ELEC!I12 -> 0 | H10: =ELEC!AO12 -> 0 | I10: =ELEC!G12 -> 0 | J10: =WATER!Y14 -> 0 | K10: =WATER!AJ14 -> 0 | L10: =ELEC!B12 -> 0
A11: Beirut | B11: =B10+1 -> 10 | C11: 6 | D11: 2021 | E11: =ELEC!M13 -> 0 | F11: =ELEC!K13 -> 0 | G11: =ELEC!I13 -> 0 | H11: =ELEC!AO13 -> 0 | I11: =ELEC!G13 -> 0 | J11: =WATER!Y15 -> 0 | K11: =WATER!AJ15 -> 0 | L11: =ELEC!B13 -> 0
A12: Beirut | B12: =B11+1 -> 11 | C12: 6 | D12: 2021 | E12: =ELEC!M14 -> 0 | F12: =ELEC!K14 -> 0 | G12: =ELEC!I14 -> 0 | H12: =ELEC!AO14 -> 0 | I12: =ELEC!G14 -> 0 | J12: =WATER!Y16 -> 0 | K12: =WATER!AJ16 -> 0 | L12: =ELEC!B14 -> 0
A13: Beirut | B13: =B12+1 -> 12 | C13: 6 | D13: 2021 | E13: =ELEC!M15 -> 0 | F13: =ELEC!K15 -> 0 | G13: =ELEC!I15 -> 0 | H13: =ELEC!AO15 -> 0 | I13: =ELEC!G15 -> 0 | J13: =WATER!Y17 -> 0 | K13: =WATER!AJ17 -> 0 | L13: =ELEC!B15 -> 0
A14: Beirut | B14: =B13+1 -> 13 | C14: 6 | D14: 2021 | E14: =ELEC!M16 -> 0 | F14: =ELEC!K16 -> 0 | G14: =ELEC!I16 -> 0 | H14: =ELEC!AO16 -> 0 | I14: =ELEC!G16 -> 0 | J14: =WATER!Y18 -> 0 | K14: =WATER!AJ18 -> 0 | L14: =ELEC!B16 -> 0
A15: Beirut | B15: =B14+1 -> 14 | C15: 6 | D15: 2021 | E15: =ELEC!M17 -> 0 | F15: =ELEC!K17 -> 0 | G15: =ELEC!I17 -> 0 | H15: =ELEC!AO17 -> 0 | I15: =ELEC!G17 -> 0 | J15: =WATER!Y19 -> 0 | K15: =WATER!AJ19 -> 0 | L15: =ELEC!B17 -> 0
A16: Beirut | B16: =B15+1 -> 15 | C16: 6 | D16: 2021 | E16: =ELEC!M18 -> 0 | F16: =ELEC!K18 -> 0 | G16: =ELEC!I18 -> 0 | H16: =ELEC!AO18 -> 0 | I16: =ELEC!G18 -> 0 | J16: =WATER!Y20 -> 0 | K16: =WATER!AJ20 -> 0 | L16: =ELEC!B18 -> 0
A17: Beirut | B17: =B16+1 -> 16 | C17: 6 | D17: 2021 | E17: =ELEC!M19 -> 0 | F17: =ELEC!K19 -> 0 | G17: =ELEC!I19 -> 0 | H17: =ELEC!AO19 -> 0 | I17: =ELEC!G19 -> 0 | J17: =WATER!Y21 -> 0 | K17: =WATER!AJ21 -> 0 | L17: =ELEC!B19 -> 0
A18: Beirut | B18: =B17+1 -> 17 | C18: 6 | D18: 2021 | E18: =ELEC!M20 -> 0 | F18: =ELEC!K20 -> 0 | G18: =ELEC!I20 -> 0 | H18: =ELEC!AO20 -> 0 | I18: =ELEC!G20 -> 0 | J18: =WATER!Y22 -> 0 | K18: =WATER!AJ22 -> 0 | L18: =ELEC!B20 -> 0
... A31: Beirut | B31: =B30+1 -> 30 | C31: 6 | D31: 2021 | E31: =ELEC!M33 -> 0 | F31: =ELEC!K33 -> 0 | G31: =ELEC!I33 -> 0 | H31: =ELEC!AO33 -> 0 | I31: =ELEC!G33 -> 0 | J31: =WATER!Y35 -> 0 | K31: =WATER!AJ35 -> 0 | L31: =ELEC!B33 -> 0
D45: .

Sheet ELEC
AK1: ATS 4 till power meter is for MDB 3 is replaced
A2: OOC | B2: Room OCC | D2: MDB3 | E2: MDB3/day | F2: EMDB2 | G2: EMDB2/day | H2: EMDB1 | I2: EMDB1/day | J2: MDB2 | K2: mdb2/day | L2: MDB1 | M2: MDB1/Day | N2: Total KWH | O2: KWH/Rooc | P2: Gen MHW | Q2: Gen/Day KWH | R2: EDL KWH | S2: CH1 RH | T2: RH | U2: C1h1 power | V2: CH1 Con KWH | W2: CH2 RH | X2: RH | Y2: Ch2 power | Z2: CH2 Con KWH | AA2: CH3 RH | AB2: RH | AC2: Ch3 power | AD2: CH3 Con KWH | AE2: RH total | AF2: KWH total | AG2: AVG chiller KW/Hr | AK2: Emergency | AL2: Normal | AM2: Total | AN2: Difference
A3: =[1]ELEC!$A$33 -> 0 | B3: =[1]ELEC!$B$33 -> 0 | C3: 44347 | D3: =[2]ELEC!D33 -> 32911138 | E3: =[2]ELEC!E33 -> 4709 | F3: =[2]ELEC!F33 -> 4031450 | G3: =[2]ELEC!G33 -> 1057 | H3: =[2]ELEC!H33 -> 17884320 | I3: =[2]ELEC!I33 -> 1442 | J3: =[2]ELEC!J33 -> 29123928 | K3: =[2]ELEC!K33 -> 9050 | ... AG3: =[2]ELEC!AG33 -> 236.41667 | AI3: -999706 | AK3: 44347 | AL3: =[3]ELEC!AL33 -> 333631 | AM3: =[3]ELEC!AM33 -> 431020 | AN3: =[3]ELEC!AN33 -> 764651 | AO3: =[3]ELEC!AO33 -> 4709
A4: ='General information '!F6 -> 0 | B4: =SUM(230*A4) -> 0 | C4: 44348 | D4: =D3 -> 32911138 | E4: =AO4 -> 2415 | F4: 4031925 | G4: =F4-F3 -> 475 | H4: 17885062 | I4: =H4-H3 -> 742 | J4: 29128686 | K4: =J4-J3 -> 4758 | L4: 24237542 | M4: =L4-L3 -> 1550 | N4: =M4+K4+I4+G4+E4 -> 9940 | O4: =IF(B4>0,N4/B4,0) -> 0 | P4: 17216.967 | Q4: =(P4-P3)*1000 -> 9515 | R4: =+N4-Q4 -> 425 | S4: =S3 -> 10175 | T4: =S4-S3 -> 0 | U4: =U3 -> 429166 | V4: =U4-U3 -> 0 | W4: 32562 | X4: =W4-W3 -> 20 | Y4: 775030 | Z4: =Y4-Y3 -> 4098 | AA4: =AA3 -> 35939 | AB4: =AA4-AA3 -> 0 | AC4: =AC3 -> 961645 | AD4: =AC4-AC3 -> 0 | AE4: =AB4+X4+T4 -> 20 | AF4: =V4+Z4+AD4 -> 4098 | AG4: =IF(AE4>0,AF4/AE4,0) -> 204.9 | AI4: =R4-'EDl log'!B4 -> -1057750 | AK4: 44348 | AL4: 335894 | AM4: 431172 | AN4: =AM4+AL4 -> 767066 | AO4: =AN4-AN3 -> 2415
A5: ='General information '!F7 -> 0 | B5: =SUM(230*A5) -> 0 | C5: 44349 | D5: =D4 -> 32911138 | E5: =AO5 -> 0 | F5: =F4 -> 4031925 | G5: =F5-F4 -> 0 | H5: =H4 -> 17885062 | I5: =H5-H4 -> 0 | J5: =J4 -> 29128686 | K5: =J5-J4 -> 0 | L5: =L4 -> 24237542 | M5: =L5-L4 -> 0 | N5: =M5+K5+I5+G5+E5 -> 0 | O5: =IF(B5>0,N5/B5,0) -> 0 | P5: =P4 -> 17216.967 | Q5: =(P5-P4)*1000 -> 0 | R5: =N5-Q5 -> 0 | S5: =S4 -> 10175 | T5: =S5-S4 -> 0 | U5: =U4 -> 429166 | V5: =U5-U4 -> 0 | W5: =W4 -> 32562 | X5: =W5-W4 -> 0 | Y5: =Y4 -> 775030 | Z5: =Y5-Y4 -> 0 | AA5: =AA4 -> 35939 | AB5: =AA5-AA4 -> 0 | AC5: =AC4 -> 961645 | AD5: =AC5-AC4 -> 0 | AE5: =AB5+X5+T5 -> 0 | AF5: =V5+Z5+AD5 -> 0 | AG5: =IF(AE5>0,AF5/AE5,0) -> 0 | AI5: =R5-'EDl log'!B5 -> -1058175 | AK5: 44349 | AL5: =AL4 -> 335894 | AM5: =AM4 -> 431172 | AN5: =AM5+AL5 -> 767066 | AO5: =AN5-AN4 -> 0
A6: ='General information '!F8 -> 0 | B6: =SUM(230*A6) -> 0 | C6: 44350 | D6: =D5 -> 32911138 | E6: =AO6 -> 0 | F6: =F5 -> 4031925 | G6: =F6-F5 -> 0 | H6: =H5 -> 17885062 | I6: =H6-H5 -> 0 | J6: =J5 -> 29128686 | K6: =J6-J5 -> 0 | L6: =L5 -> 24237542 | M6: =L6-L5 -> 0 | N6: =M6+K6+I6+G6+E6 -> 0 | O6: =IF(B6>0,N6/B6,0) -> 0 | P6: =P5 -> 17216.967 | Q6: =(P6-P5)*1000 -> 0 | R6: =N6-Q6 -> 0 | S6: =S5 -> 10175 | T6: =S6-S5 -> 0 | U6: =U5 -> 429166 | V6: =U6-U5 -> 0 | W6: =W5 -> 32562 | X6: =W6-W5 -> 0 | Y6: =Y5 -> 775030 | Z6: =Y6-Y5 -> 0 | AA6: =AA5 -> 35939 | AB6: =AA6-AA5 -> 0 | AC6: =AC5 -> 961645 | AD6: =AC6-AC5 -> 0 | AE6: =AB6+X6+T6 -> 0 | AF6: =V6+Z6+AD6 -> 0 | AG6: =IF(AE6>0,AF6/AE6,0) -> 0 | AI6: =R6-'EDl log'!B6 -> -1058175 | AK6: 44350 | AL6: =AL5 -> 335894 | AM6: =AM5 -> 431172 | AN6: =AM6+AL6 -> 767066 | AO6: =AN6-AN5 -> 0
A7: ='General information '!F9 -> 0 | B7: =SUM(230*A7) -> 0 | C7: 44351 | D7: =D6 -> 32911138 | E7: =AO7 -> 0 | F7: =F6 -> 4031925 | G7: =F7-F6 -> 0 | H7: =H6 -> 17885062 | I7: =H7-H6 -> 0 | J7: =J6 -> 29128686 | K7: =J7-J6 -> 0 | L7: =L6 -> 24237542 | M7: =L7-L6 -> 0 | N7: =M7+K7+I7+G7+E7 -> 0 | O7: =IF(B7>0,N7/B7,0) -> 0 | P7: =P6 -> 17216.967 | Q7: =(P7-P6)*1000 -> 0 | R7: =N7-Q7 -> 0 | S7: =S6 -> 10175 | T7: =S7-S6 -> 0 | U7: =U6 -> 429166 | V7: =U7-U6 -> 0 | W7: =W6 -> 32562 | X7: =W7-W6 -> 0 | Y7: =Y6 -> 775030 | Z7: =Y7-Y6 -> 0 | AA7: =AA6 -> 35939 | AB7: =AA7-AA6 -> 0 | AC7: =AC6 -> 961645 | AD7: =AC7-AC6 -> 0 | AE7: =AB7+X7+T7 -> 0 | AF7: =V7+Z7+AD7 -> 0 | AG7: =IF(AE7>0,AF7/AE7,0) -> 0 | AI7: =R7-'EDl log'!B7 -> -1058175 | AK7: 44351 | AL7: =AL6 -> 335894 | AM7: =AM6 -> 431172 | AN7: =AM7+AL7 -> 767066 | AO7: =AN7-AN6 -> 0
A8: ='General information '!F10 -> 0 | B8: =SUM(230*A8) -> 0 | C8: 44352 | D8: =D7 -> 32911138 | E8: =AO8 -> 0 | F8: =F7 -> 4031925 | G8: =F8-F7 -> 0 | H8: =H7 -> 17885062 | I8: =H8-H7 -> 0 | J8: =J7 -> 29128686 | K8: =J8-J7 -> 0 | L8: =L7 -> 24237542 | M8: =L8-L7 -> 0 | N8: =M8+K8+I8+G8+E8 -> 0 | O8: =IF(B8>0,N8/B8,0) -> 0 | P8: =P7 -> 17216.967 | Q8: =(P8-P7)*1000 -> 0 | R8: =N8-Q8 -> 0 | S8: =S7 -> 10175 | T8: =S8-S7 -> 0 | U8: =U7 -> 429166 | V8: =U8-U7 -> 0 | W8: =W7 -> 32562 | X8: =W8-W7 -> 0 | Y8: =Y7 -> 775030 | Z8: =Y8-Y7 -> 0 | AA8: =AA7 -> 35939 | AB8: =AA8-AA7 -> 0 | AC8: =AC7 -> 961645 | AD8: =AC8-AC7 -> 0 | AE8: =AB8+X8+T8 -> 0 | AF8: =V8+Z8+AD8 -> 0 | AG8: =IF(AE8>0,AF8/AE8,0) -> 0 | AI8: =R8-'EDl log'!B8 -> -1058175 | AK8: 44352 | AL8: =AL7 -> 335894 | AM8: =AM7 -> 431172 | AN8: =AM8+AL8 -> 767066 | AO8: =AN8-AN7 -> 0
A9: ='General information '!F11 -> 0 | B9: =SUM(230*A9) -> 0 | C9: 44353 | D9: =D8 -> 32911138 | E9: =AO9 -> 0 | F9: =F8 -> 4031925 | G9: =F9-F8 -> 0 | H9: =H8 -> 17885062 | I9: =H9-H8 -> 0 | J9: =J8 -> 29128686 | K9: =J9-J8 -> 0 | L9: =L8 -> 24237542 | M9: =L9-L8 -> 0 | N9: =M9+K9+I9+G9+E9 -> 0 | O9: =IF(B9>0,N9/B9,0) -> 0 | P9: =P8 -> 17216.967 | Q9: =(P9-P8)*1000 -> 0 | R9: =N9-Q9 -> 0 | S9: =S8 -> 10175 | T9: =S9-S8 -> 0 | U9: =U8 -> 429166 | V9: =U9-U8 -> 0 | W9: =W8 -> 32562 | X9: =W9-W8 -> 0 | Y9: =Y8 -> 775030 | Z9: =Y9-Y8 -> 0 | AA9: =AA8 -> 35939 | AB9: =AA9-AA8 -> 0 | AC9: =AC8 -> 961645 | AD9: =AC9-AC8 -> 0 | AE9: =AB9+X9+T9 -> 0 | AF9: =V9+Z9+AD9 -> 0 | AG9: =IF(AE9>0,AF9/AE9,0) -> 0 | AI9: =R9-'EDl log'!B9 -> -1058175 | AK9: 44353 | AL9: =AL8 -> 335894 | AM9: =AM8 -> 431172 | AN9: =AM9+AL9 -> 767066 | AO9: =AN9-AN8 -> 0
A10: ='General information '!F12 -> 0 | B10: =SUM(230*A10) -> 0 | C10: 44354 | D10: =D9 -> 32911138 | E10: =AO10 -> 0 | F10: =F9 -> 4031925 | G10: =F10-F9 -> 0 | H10: =H9 -> 17885062 | I10: =H10-H9 -> 0 | J10: =J9 -> 29128686 | K10: =J10-J9 -> 0 | L10: =L9 -> 24237542 | M10: =L10-L9 -> 0 | N10: =M10+K10+I10+G10+E10 -> 0 | O10: =IF(B10>0,N10/B10,0) -> 0 | P10: =P9 -> 17216.967 | Q10: =(P10-P9)*1000 -> 0 | R10: =N10-Q10 -> 0 | S10: =S9 -> 10175 | T10: =S10-S9 -> 0 | U10: =U9 -> 429166 | V10: =U10-U9 -> 0 | W10: =W9 -> 32562 | X10: =W10-W9 -> 0 | Y10: =Y9 -> 775030 | Z10: =Y10-Y9 -> 0 | AA10: =AA9 -> 35939 | AB10: =AA10-AA9 -> 0 | AC10: =AC9 -> 961645 | AD10: =AC10-AC9 -> 0 | AE10: =AB10+X10+T10 -> 0 | AF10: =V10+Z10+AD10 -> 0 | AG10: =IF(AE10>0,AF10/AE10,0) -> 0 | AI10: =R10-'EDl log'!B10 -> -1058175 | AK10: 44354 | AL10: =AL9 -> 335894 | AM10: =AM9 -> 431172 | AN10: =AM10+AL10 -> 767066 | AO10: =AN10-AN9 -> 0
A11: ='General information '!F13 -> 0 | B11: =SUM(230*A11) -> 0 | C11: 44355 | D11: =D10 -> 32911138 | E11: =AO11 -> 0 | F11: =F10 -> 4031925 | G11: =F11-F10 -> 0 | H11: =H10 -> 17885062 | I11: =H11-H10 -> 0 | J11: =J10 -> 29128686 | K11: =J11-J10 -> 0 | L11: =L10 -> 24237542 | M11: =L11-L10 -> 0 | N11: =M11+K11+I11+G11+E11 -> 0 | O11: =IF(B11>0,N11/B11,0) -> 0 | P11: =P10 -> 17216.967 | Q11: =(P11-P10)*1000 -> 0 | R11: =N11-Q11 -> 0 | S11: =S10 -> 10175 | T11: =S11-S10 -> 0 | U11: =U10 -> 429166 | V11: =U11-U10 -> 0 | W11: =W10 -> 32562 | X11: =W11-W10 -> 0 | Y11: =Y10 -> 775030 | Z11: =Y11-Y10 -> 0 | AA11: =AA10 -> 35939 | AB11: =AA11-AA10 -> 0 | AC11: =AC10 -> 961645 | AD11: =AC11-AC10 -> 0 | AE11: =AB11+X11+T11 -> 0 | AF11: =V11+Z11+AD11 -> 0 | AG11: =IF(AE11>0,AF11/AE11,0) -> 0 | AI11: =R11-'EDl log'!B11 -> -1058175 | AK11: 44355 | AL11: =AL10 -> 335894 | AM11: =AM10 -> 431172 | AN11: =AM11+AL11 -> 767066 | AO11: =AN11-AN10 -> 0
A12: ='General information '!F14 -> 0 | B12: =SUM(230*A12) -> 0 | C12: 44356 | D12: =D11 -> 32911138 | E12: =AO12 -> 0 | F12: =F11 -> 4031925 | G12: =F12-F11 -> 0 | H12: =H11 -> 17885062 | I12: =H12-H11 -> 0 | J12: =J11 -> 29128686 | K12: =J12-J11 -> 0 | L12: =L11 -> 24237542 | M12: =L12-L11 -> 0 | N12: =M12+K12+I12+G12+E12 -> 0 | O12: =IF(B12>0,N12/B12,0) -> 0 | P12: =P11 -> 17216.967 | Q12: =(P12-P11)*1000 -> 0 | R12: =N12-Q12 -> 0 | S12: =S11 -> 10175 | T12: =S12-S11 -> 0 | U12: =U11 -> 429166 | V12: =U12-U11 -> 0 | W12: =W11 -> 32562 | X12: =W12-W11 -> 0 | Y12: =Y11 -> 775030 | Z12: =Y12-Y11 -> 0 | AA12: =AA11 -> 35939 | AB12: =AA12-AA11 -> 0 | AC12: =AC11 -> 961645 | AD12: =AC12-AC11 -> 0 | AE12: =AB12+X12+T12 -> 0 | AF12: =V12+Z12+AD12 -> 0 | AG12: =IF(AE12>0,AF12/AE12,0) -> 0 | AI12: =R12-'EDl log'!B12 -> -1058175 | AK12: 44356 | AL12: =AL11 -> 335894 | AM12: =AM11 -> 431172 | AN12: =AM12+AL12 -> 767066 | AO12: =AN12-AN11 -> 0
A13: ='General information '!F15 -> 0 | B13: =SUM(230*A13) -> 0 | C13: 44357 | D13: =D12 -> 32911138 | E13: =AO13 -> 0 | F13: =F12 -> 4031925 | G13: =F13-F12 -> 0 | H13: =H12 -> 17885062 | I13: =H13-H12 -> 0 | J13: =J12 -> 29128686 | K13: =J13-J12 -> 0 | L13: =L12 -> 24237542 | M13: =L13-L12 -> 0 | N13: =M13+K13+I13+G13+E13 -> 0 | O13: =IF(B13>0,N13/B13,0) -> 0 | P13: =P12 -> 17216.967 | Q13: =(P13-P12)*1000 -> 0 | R13: =N13-Q13 -> 0 | S13: =S12 -> 10175 | T13: =S13-S12 -> 0 | U13: =U12 -> 429166 | V13: =U13-U12 -> 0 | W13: =W12 -> 32562 | X13: =W13-W12 -> 0 | Y13: =Y12 -> 775030 | Z13: =Y13-Y12 -> 0 | AA13: =AA12 -> 35939 | AB13: =AA13-AA12 -> 0 | AC13: =AC12 -> 961645 | AD13: =AC13-AC12 -> 0 | AE13: =AB13+X13+T13 -> 0 | AF13: =V13+Z13+AD13 -> 0 | AG13: =IF(AE13>0,AF13/AE13,0) -> 0 | AI13: =R13-'EDl log'!B13 -> -1058175 | AK13: 44357 | AL13: =AL12 -> 335894 | AM13: =AM12 -> 431172 | AN13: =AM13+AL13 -> 767066 | AO13: =AN13-AN12 -> 0
A14: ='General information '!F16 -> 0 | B14: =SUM(230*A14) -> 0 | C14: 44358 | D14: =D13 -> 32911138 | E14: =AO14 -> 0 | F14: =F13 -> 4031925 | G14: =F14-F13 -> 0 | H14: =H13 -> 17885062 | I14: =H14-H13 -> 0 | J14: =J13 -> 29128686 | K14: =J14-J13 -> 0 | L14: =L13 -> 24237542 | M14: =L14-L13 -> 0 | N14: =M14+K14+I14+G14+E14 -> 0 | O14: =IF(B14>0,N14/B14,0) -> 0 | P14: =P13 -> 17216.967 | Q14: =(P14-P13)*1000 -> 0 | R14: =N14-Q14 -> 0 | S14: =S13 -> 10175 | T14: =S14-S13 -> 0 | U14: =U13 -> 429166 | V14: =U14-U13 -> 0 | W14: =W13 -> 32562 | X14: =W14-W13 -> 0 | Y14: =Y13 -> 775030 | Z14: =Y14-Y13 -> 0 | AA14: =AA13 -> 35939 | AB14: =AA14-AA13 -> 0 | AC14: =AC13 -> 961645 | AD14: =AC14-AC13 -> 0 | AE14: =AB14+X14+T14 -> 0 | AF14: =V14+Z14+AD14 -> 0 | AG14: =IF(AE14>0,AF14/AE14,0) -> 0 | AI14: =R14-'EDl log'!B14 -> -1058175 | AK14: 44358 | AL14: =AL13 -> 335894 | AM14: =AM13 -> 431172 | AN14: =AM14+AL14 -> 767066 | AO14: =AN14-AN13 -> 0
A15: ='General information '!F17 -> 0 | B15: =SUM(230*A15) -> 0 | C15: 44359 | D15: =D14 -> 32911138 | E15: =AO15 -> 0 | F15: =F14 -> 4031925 | G15: =F15-F14 -> 0 | H15: =H14 -> 17885062 | I15: =H15-H14 -> 0 | J15: =J14 -> 29128686 | K15: =J15-J14 -> 0 | L15: =L14 -> 24237542 | M15: =L15-L14 -> 0 | N15: =M15+K15+I15+G15+E15 -> 0 | O15: =IF(B15>0,N15/B15,0) -> 0 | P15: =P14 -> 17216.967 | Q15: =(P15-P14)*1000 -> 0 | R15: =N15-Q15 -> 0 | S15: =S14 -> 10175 | T15: =S15-S14 -> 0 | U15: =U14 -> 429166 | V15: =U15-U14 -> 0 | W15: =W14 -> 32562 | X15: =W15-W14 -> 0 | Y15: =Y14 -> 775030 | Z15: =Y15-Y14 -> 0 | AA15: =AA14 -> 35939 | AB15: =AA15-AA14 -> 0 | AC15: =AC14 -> 961645 | AD15: =AC15-AC14 -> 0 | AE15: =AB15+X15+T15 -> 0 | AF15: =V15+Z15+AD15 -> 0 | AG15: =IF(AE15>0,AF15/AE15,0) -> 0 | AI15: =R15-'EDl log'!B15 -> -1058175 | AK15: 44359 | AL15: =AL14 -> 335894 | AM15: =AM14 -> 431172 | AN15: =AM15+AL15 -> 767066 | AO15: =AN15-AN14 -> 0
A16: ='General information '!F18 -> 0 | B16: =SUM(230*A16) -> 0 | C16: 44360 | D16: =D15 -> 32911138 | E16: =AO16 -> 0 | F16: =F15 -> 4031925 | G16: =F16-F15 -> 0 | H16: =H15 -> 17885062 | I16: =H16-H15 -> 0 | J16: =J15 -> 29128686 | K16: =J16-J15 -> 0 | L16: =L15 -> 24237542 | M16: =L16-L15 -> 0 | N16: =M16+K16+I16+G16+E16 -> 0 | O16: =IF(B16>0,N16/B16,0) -> 0 | P16: =P15 -> 17216.967 | Q16: =(P16-P15)*1000 -> 0 | R16: =N16-Q16 -> 0 | S16: =S15 -> 10175 | T16: =S16-S15 -> 0 | U16: =U15 -> 429166 | V16: =U16-U15 -> 0 | W16: =W15 -> 32562 | X16: =W16-W15 -> 0 | Y16: =Y15 -> 775030 | Z16: =Y16-Y15 -> 0 | AA16: =AA15 -> 35939 | AB16: =AA16-AA15 -> 0 | AC16: =AC15 -> 961645 | AD16: =AC16-AC15 -> 0 | AE16: =AB16+X16+T16 -> 0 | AF16: =V16+Z16+AD16 -> 0 | AG16: =IF(AE16>0,AF16/AE16,0) -> 0 | AI16: =R16-'EDl log'!B16 -> -1058175 | AK16: 44360 | AL16: =AL15 -> 335894 | AM16: =AM15 -> 431172 | AN16: =AM16+AL16 -> 767066 | AO16: =AN16-AN15 -> 0
... A33: ='General information '!F35 -> 0 | B33: =SUM(230*A33) -> 0 | C33: 44377 | D33: =D32 -> 32911138 | E33: =AO33 -> 0 | F33: =F32 -> 4031925 | G33: =F33-F32 -> 0 | H33: =H32 -> 17885062 | I33: =H33-H32 -> 0 | J33: =J32 -> 29128686 | K33: =J33-J32 -> 0 | L33: =L32 -> 24237542 | M33: =L33-L32 -> 0 | N33: =M33+K33+I33+G33+E33 -> 0 | O33: =IF(B33>0,N33/B33,0) -> 0 | P33: =P32 -> 17216.967 | Q33: =(P33-P32)*1000 -> 0 | R33: =N33-Q33 -> 0 | S33: =S32 -> 10175 | T33: =S33-S32 -> 0 | U33: =U32 -> 429166 | V33: =U33-U32 -> 0 | W33: =W32 -> 32562 | X33: =W33-W32 -> 0 | Y33: =Y32 -> 775030 | Z33: =Y33-Y32 -> 0 | AA33: =AA32 -> 35939 | AB33: =AA33-AA32 -> 0 | AC33: =AC32 -> 961645 | AD33: =AC33-AC32 -> 0 | AE33: =AB33+X33+T33 -> 0 | AF33: =V33+Z33+AD33 -> 0 | AG33: =IF(AE33>0,AF33/AE33,0) -> 0 | AI33: =R33-'EDl log'!B33 -> -1058175 | AK33: 44377 | AL33: =AL32 -> 335894 | AM33: =AM32 -> 431172 | AN33: =AM33+AL33 -> 767066 | AO33: =AN33-AN32 -> 0

Sheet B5
F1: Boiler A | J1: =J35 -> 1 | K1: Boiler B | P1: Boiler C | V1: Boiler | X1: SteamA | AC1: SteamB | AH1: Steam | AI1: Boiler & steam | AL1: Total Boiler Runing H | AM1: Total Steam Runing H | AN1: GAS1 % | AO1: GAS1/L | AP1: GAS2% | AQ1: Gas2/L | AR1: GAS3% | AS1: GAS3/L | AU1: Gas Cons | AV1: Delivery | AW1: Cost/L
B2: Level Tank Gen | C2: Level tank Boiler | D2: Daily Cons Bo. | E2: Boiler litter | F2: Boiler A | G2: Run Hr a | H2: Boiler A fuel | I2: Daily consumption | J2: AVG | K2: index Run H | L2: Run Hrb | M2: Boiler B Fuel | O2: Daily consumption | P2: Boiler C | S2: Run C | U2: Total RH | V2: Total Fuel | X2: SteamA | Y2: Run SA | Z2: Steam A Conter | AA2: Liters | AC2: SteamB | AD2: Run SteamB | AE2: Steam B Conter | AF2: SB Litters | AG2: Avg | AH2: Total Fuel | AI2: Total Fuel
S3: 0
A4: =ELEC!C3 -> 44347 | B4: =[2]B5!B35 -> 207 | C4: =[2]B5!C35 -> 214 | D4: =[2]B5!D35 -> -27 | E4: =[2]B5!E35 -> -226.26 | F4: =[2]B5!F35 -> 1841 | G4: =[2]B5!G35 -> 1 | H4: =[2]B5!H35 -> 13408 | I4: =[2]B5!I35 -> 96 | ... AX4: =[2]B5!AX35 -> 0.8
A5: =ELEC!C4 -> 44348 | B5: 191 | C5: 204 | D5: =C4-C5 -> 10 | E5: =D5*8.38 -> 83.8 | F5: =F4 -> 1841 | G5: =F5-F4 -> 0 | H5: =H4 -> 13408 | I5: =SUM(H5-H4) -> 0 | J5: 1 | K5: =K4 -> 2331 | L5: =K5-K4 -> 0 | M5: =M4 -> 171898 | N5: =M5-M4 -> 0 | O5: =O4 -> 1869 | P5: =P4 -> 2096 | Q5: =Q4 -> 176206 | R5: =Q5-Q4 -> 0 | S5: =SUM(P5-P4) -> 0 | T5: =SUM(S5*$T$2) -> 0 | U5: =SUM(G5+L5+S5) -> 0 | V5: =R5+N5+I5:I5 -> 0 | W5: =SUM(V5/U5) -> #DIV/0! | X5: =X4 -> 2469 | Y5: =X5-X4 -> 0 | Z5: =Z4 -> 138993 | AA5: =Z5-Z4 -> 0 | AB5: =SUM(Y5*$AB$2) -> 0 | AC5: =AC4 -> 1937 | AD5: =AC5-AC4 -> 0 | AE5: =AE4 -> 365590 | AF5: =AE5-AE4 -> 0 | AG5: =IF(AD5>0,AF5/AD5,0) -> 0 | AH5: =AF5+AA5 -> 0 | AI5: =SUM(AH5+V5) -> 0 | AJ5: =-tanks!AW6 -> 0 | AK5: =SUM(AJ5-AI5) -> 0 | AL5: =S5+L5+G5 -> 0 | AM5: =Y5+AD5 -> 0 | AN5: =AN4 -> 67 | AO5: =(AN5/100)*3000 -> 2010 | AP5: =AP4 -> 55 | AQ5: =(AP5/100)*3000 -> 1650 | AR5: =AR4 -> 61 | AS5: =(AR5/100)*3000 -> 1830 | AT5: =SUM(AO5+AQ5+AS5) -> 5490 | AU5: =AT4-AT5+AV5 -> 0 | AX5: =IF(AV5>0,AW5,AX4) -> 0.8
A6: =ELEC!C5 -> 44349 | B6: =B5 -> 191 | C6: =C5 -> 204 | D6: =C5-C6 -> 0 | E6: =D6*8.38 -> 0 | F6: =F5 -> 1841 | G6: =F6-F5 -> 0 | H6: =H5 -> 13408 | I6: =SUM(H6-H5) -> 0 | J6: =IF(G6>0,I6/G6,0) -> 0 | K6: =K5 -> 2331 | L6: =K6-K5 -> 0 | M6: =M5 -> 171898 | N6: =M6-M5 -> 0 | O6: =O5 -> 1869 | P6: =P5 -> 2096 | Q6: =Q5 -> 176206 | R6: =Q6-Q5 -> 0 | S6: =SUM(P6-P5) -> 0 | T6: =SUM(S6*$T$2) -> 0 | U6: =SUM(G6+L6+S6) -> 0 | V6: =R6+N6+I6:I6 -> 0 | W6: =SUM(V6/U6) -> #DIV/0! | X6: =X5 -> 2469 | Y6: =X6-X5 -> 0 | Z6: =Z5 -> 138993 | AA6: =Z6-Z5 -> 0 | AB6: =SUM(Y6*$AB$2) -> 0 | AC6: =AC5 -> 1937 | AD6: =AC6-AC5 -> 0 | AE6: =AE5 -> 365590 | AF6: =AE6-AE5 -> 0 | AG6: =IF(AD6>0,AF6/AD6,0) -> 0 | AH6: =AF6+AA6 -> 0 | AI6: =SUM(AH6+V6) -> 0 | AJ6: =-tanks!AW7 -> 0 | AK6: =SUM(AJ6-AI6) -> 0 | AL6: =S6+L6+G6 -> 0 | AM6: =Y6+AD6 -> 0 | AN6: =AN5 -> 67 | AO6: =(AN6/100)*3000 -> 2010 | AP6: =AP5 -> 55 | AQ6: =(AP6/100)*3000 -> 1650 | AR6: =AR5 -> 61 | AS6: =(AR6/100)*3000 -> 1830 | AT6: =SUM(AO6+AQ6+AS6) -> 5490 | AU6: =AT5-AT6+AV6 -> 0 | AX6: =IF(AV6>0,AW6,AX5) -> 0.8
A7: =ELEC!C6 -> 44350 | B7: =B6 -> 191 | C7: =C6 -> 204 | D7: =C6-C7 -> 0 | E7: =D7*8.38 -> 0 | F7: =F6 -> 1841 | G7: =F7-F6 -> 0 | H7: =H6 -> 13408 | I7: =SUM(H7-H6) -> 0 | J7: =IF(G7>0,I7/G7,0) -> 0 | K7: =K6 -> 2331 | L7: =K7-K6 -> 0 | M7: =M6 -> 171898 | N7: =M7-M6 -> 0 | O7: =O6 -> 1869 | P7: =P6 -> 2096 | Q7: =Q6 -> 176206 | R7: =Q7-Q6 -> 0 | S7: =SUM(P7-P6) -> 0 | T7: =SUM(S7*$T$2) -> 0 | U7: =SUM(G7+L7+S7) -> 0 | V7: =R7+N7+I7:I7 -> 0 | W7: =SUM(V7/U7) -> #DIV/0! | X7: =X6 -> 2469 | Y7: =X7-X6 -> 0 | Z7: =Z6 -> 138993 | AA7: =Z7-Z6 -> 0 | AB7: =SUM(Y7*$AB$2) -> 0 | AC7: =AC6 -> 1937 | AD7: =AC7-AC6 -> 0 | AE7: =AE6 -> 365590 | AF7: =AE7-AE6 -> 0 | AG7: =IF(AD7>0,AF7/AD7,0) -> 0 | AH7: =AF7+AA7 -> 0 | AI7: =SUM(AH7+V7) -> 0 | AJ7: =-tanks!AW8 -> 0 | AK7: =SUM(AJ7-AI7) -> 0 | AL7: =S7+L7+G7 -> 0 | AM7: =Y7+AD7 -> 0 | AN7: =AN6 -> 67 | AO7: =(AN7/100)*3000 -> 2010 | AP7: =AP6 -> 55 | AQ7: =(AP7/100)*3000 -> 1650 | AR7: =AR6 -> 61 | AS7: =(AR7/100)*3000 -> 1830 | AT7: =SUM(AO7+AQ7+AS7) -> 5490 | AU7: =AT6-AT7+AV7 -> 0 | AX7: =IF(AV7>0,AW7,AX6) -> 0.8
A8: =ELEC!C7 -> 44351 | B8: =B7 -> 191 | C8: =C7 -> 204 | D8: =C7-C8 -> 0 | E8: =D8*8.38 -> 0 | F8: =F7 -> 1841 | G8: =F8-F7 -> 0 | H8: =H7 -> 13408 | I8: =SUM(H8-H7) -> 0 | J8: =IF(G8>0,I8/G8,0) -> 0 | K8: =K7 -> 2331 | L8: =K8-K7 -> 0 | M8: =M7 -> 171898 | N8: =M8-M7 -> 0 | O8: =O7 -> 1869 | P8: =P7 -> 2096 | Q8: =Q7 -> 176206 | R8: =Q8-Q7 -> 0 | S8: =SUM(P8-P7) -> 0 | T8: =SUM(S8*$T$2) -> 0 | U8: =SUM(G8+L8+S8) -> 0 | V8: =R8+N8+I8:I8 -> 0 | W8: =SUM(V8/U8) -> #DIV/0! | X8: =X7 -> 2469 | Y8: =X8-X7 -> 0 | Z8: =Z7 -> 138993 | AA8: =Z8-Z7 -> 0 | AB8: =SUM(Y8*$AB$2) -> 0 | AC8: =AC7 -> 1937 | AD8: =AC8-AC7 -> 0 | AE8: =AE7 -> 365590 | AF8: =AE8-AE7 -> 0 | AG8: =IF(AD8>0,AF8/AD8,0) -> 0 | AH8: =AF8+AA8 -> 0 | AI8: =SUM(AH8+V8) -> 0 | AJ8: =-tanks!AW9 -> 0 | AK8: =SUM(AJ8-AI8) -> 0 | AL8: =S8+L8+G8 -> 0 | AM8: =Y8+AD8 -> 0 | AN8: =AN7 -> 67 | AO8: =(AN8/100)*3000 -> 2010 | AP8: =AP7 -> 55 | AQ8: =(AP8/100)*3000 -> 1650 | AR8: =AR7 -> 61 | AS8: =(AR8/100)*3000 -> 1830 | AT8: =SUM(AO8+AQ8+AS8) -> 5490 | AU8: =AT7-AT8+AV8 -> 0 | AX8: =IF(AV8>0,AW8,AX7) -> 0.8
A9: =ELEC!C8 -> 44352 | B9: =B8 -> 191 | C9: =C8 -> 204 | D9: =C8-C9 -> 0 | E9: =D9*8.38 -> 0 | F9: =F8 -> 1841 | G9: =F9-F8 -> 0 | H9: =H8 -> 13408 | I9: =SUM(H9-H8) -> 0 | J9: =IF(G9>0,I9/G9,0) -> 0 | K9: =K8 -> 2331 | L9: =K9-K8 -> 0 | M9: =M8 -> 171898 | N9: =M9-M8 -> 0 | O9: =O8 -> 1869 | P9: =P8 -> 2096 | Q9: =Q8 -> 176206 | R9: =Q9-Q8 -> 0 | S9: =SUM(P9-P8) -> 0 | T9: =SUM(S9*$T$2) -> 0 | U9: =SUM(G9+L9+S9) -> 0 | V9: =R9+N9+I9:I9 -> 0 | W9: =SUM(V9/U9) -> #DIV/0! | X9: =X8 -> 2469 | Y9: =X9-X8 -> 0 | Z9: =Z8 -> 138993 | AA9: =Z9-Z8 -> 0 | AB9: =SUM(Y9*$AB$2) -> 0 | AC9: =AC8 -> 1937 | AD9: =AC9-AC8 -> 0 | AE9: =AE8 -> 365590 | AF9: =AE9-AE8 -> 0 | AG9: =IF(AD9>0,AF9/AD9,0) -> 0 | AH9: =AF9+AA9 -> 0 | AI9: =SUM(AH9+V9) -> 0 | AJ9: =-tanks!AW10 -> 0 | AK9: =SUM(AJ9-AI9) -> 0 | AL9: =S9+L9+G9 -> 0 | AM9: =Y9+AD9 -> 0 | AN9: =AN8 -> 67 | AO9: =(AN9/100)*3000 -> 2010 | AP9: =AP8 -> 55 | AQ9: =(AP9/100)*3000 -> 1650 | AR9: =AR8 -> 61 | AS9: =(AR9/100)*3000 -> 1830 | AT9: =SUM(AO9+AQ9+AS9) -> 5490 | AU9: =AT8-AT9+AV9 -> 0 | AX9: =IF(AV9>0,AW9,AX8) -> 0.8
A10: =ELEC!C9 -> 44353 | B10: =B9 -> 191 | C10: =C9 -> 204 | D10: =C9-C10 -> 0 | E10: =D10*8.38 -> 0 | F10: =F9 -> 1841 | G10: =F10-F9 -> 0 | H10: =H9 -> 13408 | I10: =SUM(H10-H9) -> 0 | J10: =IF(G10>0,I10/G10,0) -> 0 | K10: =K9 -> 2331 | L10: =K10-K9 -> 0 | M10: =M9 -> 171898 | N10: =M10-M9 -> 0 | O10: =O9 -> 1869 | P10: =P9 -> 2096 | Q10: =Q9 -> 176206 | R10: =Q10-Q9 -> 0 | S10: =SUM(P10-P9) -> 0 | T10: =SUM(S10*$T$2) -> 0 | U10: =SUM(G10+L10+S10) -> 0 | V10: =R10+N10+I10:I10 -> 0 | W10: =SUM(V10/U10) -> #DIV/0! | X10: =X9 -> 2469 | Y10: =X10-X9 -> 0 | Z10: =Z9 -> 138993 | AA10: =Z10-Z9 -> 0 | AB10: =SUM(Y10*$AB$2) -> 0 | AC10: =AC9 -> 1937 | AD10: =AC10-AC9 -> 0 | AE10: =AE9 -> 365590 | AF10: =AE10-AE9 -> 0 | AG10: =IF(AD10>0,AF10/AD10,0) -> 0 | AH10: =AF10+AA10 -> 0 | AI10: =SUM(AH10+V10) -> 0 | AJ10: =-tanks!AW11 -> 0 | AK10: =SUM(AJ10-AI10) -> 0 | AL10: =S10+L10+G10 -> 0 | AM10: =Y10+AD10 -> 0 | AN10: =AN9 -> 67 | AO10: =(AN10/100)*3000 -> 2010 | AP10: =AP9 -> 55 | AQ10: =(AP10/100)*3000 -> 1650 | AR10: =AR9 -> 61 | AS10: =(AR10/100)*3000 -> 1830 | AT10: =SUM(AO10+AQ10+AS10) -> 5490 | AU10: =AT9-AT10+AV10 -> 0 | AX10: =IF(AV10>0,AW10,AX9) -> 0.8
A11: =ELEC!C10 -> 44354 | B11: =B10 -> 191 | C11: =C10 -> 204 | D11: =C10-C11 -> 0 | E11: =D11*8.38 -> 0 | F11: =F10 -> 1841 | G11: =F11-F10 -> 0 | H11: =H10 -> 13408 | I11: =SUM(H11-H10) -> 0 | J11: =IF(G11>0,I11/G11,0) -> 0 | K11: =K10 -> 2331 | L11: =K11-K10 -> 0 | M11: =M10 -> 171898 | N11: =M11-M10 -> 0 | O11: =O10 -> 1869 | P11: =P10 -> 2096 | Q11: =Q10 -> 176206 | R11: =Q11-Q10 -> 0 | S11: =SUM(P11-P10) -> 0 | T11: =SUM(S11*$T$2) -> 0 | U11: =SUM(G11+L11+S11) -> 0 | V11: =R11+N11+I11:I11 -> 0 | W11: =SUM(V11/U11) -> #DIV/0! | X11: =X10 -> 2469 | Y11: =X11-X10 -> 0 | Z11: =Z10 -> 138993 | AA11: =Z11-Z10 -> 0 | AB11: =SUM(Y11*$AB$2) -> 0 | AC11: =AC10 -> 1937 | AD11: =AC11-AC10 -> 0 | AE11: =AE10 -> 365590 | AF11: =AE11-AE10 -> 0 | AG11: =IF(AD11>0,AF11/AD11,0) -> 0 | AH11: =AF11+AA11 -> 0 | AI11: =SUM(AH11+V11) -> 0 | AJ11: =-tanks!AW12 -> 0 | AK11: =SUM(AJ11-AI11) -> 0 | AL11: =S11+L11+G11 -> 0 | AM11: =Y11+AD11 -> 0 | AN11: =AN10 -> 67 | AO11: =(AN11/100)*3000 -> 2010 | AP11: =AP10 -> 55 | AQ11: =(AP11/100)*3000 -> 1650 | AR11: =AR10 -> 61 | AS11: =(AR11/100)*3000 -> 1830 | AT11: =SUM(AO11+AQ11+AS11) -> 5490 | AU11: =AT10-AT11+AV11 -> 0 | AX11: =IF(AV11>0,AW11,AX10) -> 0.8
A12: =ELEC!C11 -> 44355 | B12: =B11 -> 191 | C12: =C11 -> 204 | D12: =C11-C12 -> 0 | E12: =D12*8.38 -> 0 | F12: =F11 -> 1841 | G12: =F12-F11 -> 0 | H12: =H11 -> 13408 | I12: =SUM(H12-H11) -> 0 | J12: =IF(G12>0,I12/G12,0) -> 0 | K12: =K11 -> 2331 | L12: =K12-K11 -> 0 | M12: =M11 -> 171898 | N12: =M12-M11 -> 0 | O12: =O11 -> 1869 | P12: =P11 -> 2096 | Q12: =Q11 -> 176206 | R12: =Q12-Q11 -> 0 | S12: =SUM(P12-P11) -> 0 | T12: =SUM(S12*$T$2) -> 0 | U12: =SUM(G12+L12+S12) -> 0 | V12: =R12+N12+I12:I12 -> 0 | W12: =SUM(V12/U12) -> #DIV/0! | X12: =X11 -> 2469 | Y12: =X12-X11 -> 0 | Z12: =Z11 -> 138993 | AA12: =Z12-Z11 -> 0 | AB12: =SUM(Y12*$AB$2) -> 0 | AC12: =AC11 -> 1937 | AD12: =AC12-AC11 -> 0 | AE12: =AE11 -> 365590 | AF12: =AE12-AE11 -> 0 | AG12: =IF(AD12>0,AF12/AD12,0) -> 0 | AH12: =AF12+AA12 -> 0 | AI12: =SUM(AH12+V12) -> 0 | AJ12: =-tanks!AW13 -> 0 | AK12: =SUM(AJ12-AI12) -> 0 | AL12: =S12+L12+G12 -> 0 | AM12: =Y12+AD12 -> 0 | AN12: =AN11 -> 67 | AO12: =(AN12/100)*3000 -> 2010 | AP12: =AP11 -> 55 | AQ12: =(AP12/100)*3000 -> 1650 | AR12: =AR11 -> 61 | AS12: =(AR12/100)*3000 -> 1830 | AT12: =SUM(AO12+AQ12+AS12) -> 5490 | AU12: =AT11-AT12+AV12 -> 0 | AX12: =IF(AV12>0,AW12,AX11) -> 0.8
A13: =ELEC!C12 -> 44356 | B13: =B12 -> 191 | C13: =C12 -> 204 | D13: =C12-C13 -> 0 | E13: =D13*8.38 -> 0 | F13: =F12 -> 1841 | G13: =F13-F12 -> 0 | H13: =H12 -> 13408 | I13: =SUM(H13-H12) -> 0 | J13: =IF(G13>0,I13/G13,0) -> 0 | K13: =K12 -> 2331 | L13: =K13-K12 -> 0 | M13: =M12 -> 171898 | N13: =M13-M12 -> 0 | O13: =O12 -> 1869 | P13: =P12 -> 2096 | Q13: =Q12 -> 176206 | R13: =Q13-Q12 -> 0 | S13: =SUM(P13-P12) -> 0 | T13: =SUM(S13*$T$2) -> 0 | U13: =SUM(G13+L13+S13) -> 0 | V13: =R13+N13+I13:I13 -> 0 | W13: =SUM(V13/U13) -> #DIV/0! | X13: =X12 -> 2469 | Y13: =X13-X12 -> 0 | Z13: =Z12 -> 138993 | AA13: =Z13-Z12 -> 0 | AB13: =SUM(Y13*$AB$2) -> 0 | AC13: =AC12 -> 1937 | AD13: =AC13-AC12 -> 0 | AE13: =AE12 -> 365590 | AF13: =AE13-AE12 -> 0 | AG13: =IF(AD13>0,AF13/AD13,0) -> 0 | AH13: =AF13+AA13 -> 0 | AI13: =SUM(AH13+V13) -> 0 | AJ13: =-tanks!AW14 -> 0 | AK13: =SUM(AJ13-AI13) -> 0 | AL13: =S13+L13+G13 -> 0 | AM13: =Y13+AD13 -> 0 | AN13: =AN12 -> 67 | AO13: =(AN13/100)*3000 -> 2010 | AP13: =AP12 -> 55 | AQ13: =(AP13/100)*3000 -> 1650 | AR13: =AR12 -> 61 | AS13: =(AR13/100)*3000 -> 1830 | AT13: =SUM(AO13+AQ13+AS13) -> 5490 | AU13: =AT12-AT13+AV13 -> 0 | AX13: =IF(AV13>0,AW13,AX12) -> 0.8
A14: =ELEC!C13 -> 44357 | B14: =B13 -> 191 | C14: =C13 -> 204 | D14: =C13-C14 -> 0 | E14: =D14*8.38 -> 0 | F14: =F13 -> 1841 | G14: =F14-F13 -> 0 | H14: =H13 -> 13408 | I14: =SUM(H14-H13) -> 0 | J14: =IF(G14>0,I14/G14,0) -> 0 | K14: =K13 -> 2331 | L14: =K14-K13 -> 0 | M14: =M13 -> 171898 | N14: =M14-M13 -> 0 | O14: =O13 -> 1869 | P14: =P13 -> 2096 | Q14: =Q13 -> 176206 | R14: =Q14-Q13 -> 0 | S14: =SUM(P14-P13) -> 0 | T14: =SUM(S14*$T$2) -> 0 | U14: =SUM(G14+L14+S14) -> 0 | V14: =R14+N14+I14:I14 -> 0 | W14: =SUM(V14/U14) -> #DIV/0! | X14: =X13 -> 2469 | Y14: =X14-X13 -> 0 | Z14: =Z13 -> 138993 | AA14: =Z14-Z13 -> 0 | AB14: =SUM(Y14*$AB$2) -> 0 | AC14: =AC13 -> 1937 | AD14: =AC14-AC13 -> 0 | AE14: =AE13 -> 365590 | AF14: =AE14-AE13 -> 0 | AG14: =IF(AD14>0,AF14/AD14,0) -> 0 | AH14: =AF14+AA14 -> 0 | AI14: =SUM(AH14+V14) -> 0 | AJ14: =-tanks!AW15 -> 0 | AK14: =SUM(AJ14-AI14) -> 0 | AL14: =S14+L14+G14 -> 0 | AM14: =Y14+AD14 -> 0 | AN14: =AN13 -> 67 | AO14: =(AN14/100)*3000 -> 2010 | AP14: =AP13 -> 55 | AQ14: =(AP14/100)*3000 -> 1650 | AR14: =AR13 -> 61 | AS14: =(AR14/100)*3000 -> 1830 | AT14: =SUM(AO14+AQ14+AS14) -> 5490 | AU14: =AT13-AT14+AV14 -> 0 | AX14: =IF(AV14>0,AW14,AX13) -> 0.8
A15: =ELEC!C14 -> 44358 | B15: =B14 -> 191 | C15: =C14 -> 204 | D15: =C14-C15 -> 0 | E15: =D15*8.38 -> 0 | F15: =F14 -> 1841 | G15: =F15-F14 -> 0 | H15: =H14 -> 13408 | I15: =SUM(H15-H14) -> 0 | J15: =IF(G15>0,I15/G15,0) -> 0 | K15: =K14 -> 2331 | L15: =K15-K14 -> 0 | M15: =M14 -> 171898 | N15: =M15-M14 -> 0 | O15: =O14 -> 1869 | P15: =P14 -> 2096 | Q15: =Q14 -> 176206 | R15: =Q15-Q14 -> 0 | S15: =SUM(P15-P14) -> 0 | T15: =SUM(S15*$T$2) -> 0 | U15: =SUM(G15+L15+S15) -> 0 | V15: =R15+N15+I15:I15 -> 0 | W15: =SUM(V15/U15) -> #DIV/0! | X15: =X14 -> 2469 | Y15: =X15-X14 -> 0 | Z15: =Z14 -> 138993 | AA15: =Z15-Z14 -> 0 | AB15: =SUM(Y15*$AB$2) -> 0 | AC15: =AC14 -> 1937 | AD15: =AC15-AC14 -> 0 | AE15: =AE14 -> 365590 | AF15: =AE15-AE14 -> 0 | AG15: =IF(AD15>0,AF15/AD15,0) -> 0 | AH15: =AF15+AA15 -> 0 | AI15: =SUM(AH15+V15) -> 0 | AJ15: =-tanks!AW16 -> 0 | AK15: =SUM(AJ15-AI15) -> 0 | AL15: =S15+L15+G15 -> 0 | AM15: =Y15+AD15 -> 0 | AN15: =AN14 -> 67 | AO15: =(AN15/100)*3000 -> 2010 | AP15: =AP14 -> 55 | AQ15: =(AP15/100)*3000 -> 1650 | AR15: =AR14 -> 61 | AS15: =(AR15/100)*3000 -> 1830 | AT15: =SUM(AO15+AQ15+AS15) -> 5490 | AU15: =AT14-AT15+AV15 -> 0 | AX15: =IF(AV15>0,AW15,AX14) -> 0.8
A16: =ELEC!C15 -> 44359 | B16: =B15 -> 191 | C16: =C15 -> 204 | D16: =C15-C16 -> 0 | E16: =D16*8.38 -> 0 | F16: =F15 -> 1841 | G16: =F16-F15 -> 0 | H16: =H15 -> 13408 | I16: =SUM(H16-H15) -> 0 | J16: =IF(G16>0,I16/G16,0) -> 0 | K16: =K15 -> 2331 | L16: =K16-K15 -> 0 | M16: =M15 -> 171898 | N16: =M16-M15 -> 0 | O16: =O15 -> 1869 | P16: =P15 -> 2096 | Q16: =Q15 -> 176206 | R16: =Q16-Q15 -> 0 | S16: =SUM(P16-P15) -> 0 | T16: =SUM(S16*$T$2) -> 0 | U16: =SUM(G16+L16+S16) -> 0 | V16: =R16+N16+I16:I16 -> 0 | W16: =SUM(V16/U16) -> #DIV/0! | X16: =X15 -> 2469 | Y16: =X16-X15 -> 0 | Z16: =Z15 -> 138993 | AA16: =Z16-Z15 -> 0 | AB16: =SUM(Y16*$AB$2) -> 0 | AC16: =AC15 -> 1937 | AD16: =AC16-AC15 -> 0 | AE16: =AE15 -> 365590 | AF16: =AE16-AE15 -> 0 | AG16: =IF(AD16>0,AF16/AD16,0) -> 0 | AH16: =AF16+AA16 -> 0 | AI16: =SUM(AH16+V16) -> 0 | AJ16: =-tanks!AW17 -> 0 | AK16: =SUM(AJ16-AI16) -> 0 | AL16: =S16+L16+G16 -> 0 | AM16: =Y16+AD16 -> 0 | AN16: =AN15 -> 67 | AO16: =(AN16/100)*3000 -> 2010 | AP16: =AP15 -> 55 | AQ16: =(AP16/100)*3000 -> 1650 | AR16: =AR15 -> 61 | AS16: =(AR16/100)*3000 -> 1830 | AT16: =SUM(AO16+AQ16+AS16) -> 5490 | AU16: =AT15-AT16+AV16 -> 0 | AX16: =IF(AV16>0,AW16,AX15) -> 0.8
A17: =ELEC!C16 -> 44360 | B17: =B16 -> 191 | C17: =C16 -> 204 | D17: =C16-C17 -> 0 | E17: =D17*8.38 -> 0 | F17: =F16 -> 1841 | G17: =F17-F16 -> 0 | H17: =H16 -> 13408 | I17: =SUM(H17-H16) -> 0 | J17: =IF(G17>0,I17/G17,0) -> 0 | K17: =K16 -> 2331 | L17: =K17-K16 -> 0 | M17: =M16 -> 171898 | N17: =M17-M16 -> 0 | O17: =O16 -> 1869 | P17: =P16 -> 2096 | Q17: =Q16 -> 176206 | R17: =Q17-Q16 -> 0 | S17: =SUM(P17-P16) -> 0 | T17: =SUM(S17*$T$2) -> 0 | U17: =SUM(G17+L17+S17) -> 0 | V17: =R17+N17+I17:I17 -> 0 | X17: =X16 -> 2469 | Y17: =X17-X16 -> 0 | Z17: =Z16 -> 138993 | AA17: =Z17-Z16 -> 0 | AB17: =SUM(Y17*$AB$2) -> 0 | AC17: =AC16 -> 1937 | AD17: =AC17-AC16 -> 0 | AE17: =AE16 -> 365590 | AF17: =AE17-AE16 -> 0 | AG17: =IF(AD17>0,AF17/AD17,0) -> 0 | AH17: =AF17+AA17 -> 0 | AI17: =SUM(AH17+V17) -> 0 | AJ17: =-tanks!AW18 -> 0 | AK17: =SUM(AJ17-AI17) -> 0 | AL17: =S17+L17+G17 -> 0 | AM17: =Y17+AD17 -> 0 | AN17: =AN16 -> 67 | AO17: =(AN17/100)*3000 -> 2010 | AP17: =AP16 -> 55 | AQ17: =(AP17/100)*3000 -> 1650 | AR17: =AR16 -> 61 | AS17: =(AR17/100)*3000 -> 1830 | AT17: =SUM(AO17+AQ17+AS17) -> 5490 | AU17: =AT16-AT17+AV17 -> 0 | AX17: =IF(AV17>0,AW17,AX16) -> 0.8
A18: =ELEC!C17 -> 44361 | B18: =B17 -> 191 | C18: =C17 -> 204 | D18: =C17-C18 -> 0 | E18: =D18*8.38 -> 0 | F18: =F17 -> 1841 | G18: =F18-F17 -> 0 | H18: =H17 -> 13408 | I18: =SUM(H18-H17) -> 0 | J18: =IF(G18>0,I18/G18,0) -> 0 | K18: =K17 -> 2331 | L18: =K18-K17 -> 0 | M18: =M17 -> 171898 | N18: =M18-M17 -> 0 | O18: 1869 | P18: =P17 -> 2096 | Q18: =Q17 -> 176206 | R18: =Q18-Q17 -> 0 | S18: =SUM(P18-P17) -> 0 | T18: =SUM(S18*$T$2) -> 0 | U18: =SUM(G18+L18+S18) -> 0 | V18: =R18+N18+I18:I18 -> 0 | X18: =X17 -> 2469 | Y18: =X18-X17 -> 0 | Z18: =Z17 -> 138993 | AA18: =Z18-Z17 -> 0 | AB18: =SUM(Y18*$AB$2) -> 0 | AC18: =AC17 -> 1937 | AD18: =AC18-AC17 -> 0 | AE18: =AE17 -> 365590 | AF18: =AE18-AE17 -> 0 | AG18: =IF(AD18>0,AF18/AD18,0) -> 0 | AH18: =AF18+AA18 -> 0 | AI18: =SUM(AH18+V18) -> 0 | AJ18: =-tanks!AW19 -> 0 | AK18: =SUM(AJ18-AI18) -> 0 | AL18: =S18+L18+G18 -> 0 | AM18: =Y18+AD18 -> 0 | AN18: =AN17 -> 67 | AO18: =(AN18/100)*3000 -> 2010 | AP18: =AP17 -> 55 | AQ18: =(AP18/100)*3000 -> 1650 | AR18: =AR17 -> 61 | AS18: =(AR18/100)*3000 -> 1830 | AT18: =SUM(AO18+AQ18+AS18) -> 5490 | AU18: =AT17-AT18+AV18 -> 0 | AX18: =IF(AV18>0,AW18,AX17) -> 0.8
A19: =ELEC!C18 -> 44362 | B19: =B18 -> 191 | C19: =C18 -> 204 | D19: =C18-C19 -> 0 | E19: =D19*8.38 -> 0 | F19: =F18 -> 1841 | G19: =F19-F18 -> 0 | H19: =H18 -> 13408 | I19: =SUM(H19-H18) -> 0 | J19: =IF(G19>0,I19/G19,0) -> 0 | K19: =K18 -> 2331 | L19: =K19-K18 -> 0 | M19: =M18 -> 171898 | N19: =M19-M18 -> 0 | O19: =O18 -> 1869 | P19: =P18 -> 2096 | Q19: =Q18 -> 176206 | R19: =Q19-Q18 -> 0 | S19: =SUM(P19-P18) -> 0 | T19: =SUM(S19*$T$2) -> 0 | U19: =SUM(G19+L19+S19) -> 0 | V19: =R19+N19+I19:I19 -> 0 | X19: =X18 -> 2469 | Y19: =X19-X18 -> 0 | Z19: =Z18 -> 138993 | AA19: =Z19-Z18 -> 0 | AB19: =SUM(Y19*$AB$2) -> 0 | AC19: =AC18 -> 1937 | AD19: =AC19-AC18 -> 0 | AE19: =AE18 -> 365590 | AF19: =AE19-AE18 -> 0 | AG19: =IF(AD19>0,AF19/AD19,0) -> 0 | AH19: =AF19+AA19 -> 0 | AI19: =SUM(AH19+V19) -> 0 | AJ19: =-tanks!AW20 -> 0 | AK19: =SUM(AJ19-AI19) -> 0 | AL19: =S19+L19+G19 -> 0 | AM19: =Y19+AD19 -> 0 | AN19: =AN18 -> 67 | AO19: =(AN19/100)*3000 -> 2010 | AP19: =AP18 -> 55 | AQ19: =(AP19/100)*3000 -> 1650 | AR19: =AR18 -> 61 | AS19: =(AR19/100)*3000 -> 1830 | AT19: =SUM(AO19+AQ19+AS19) -> 5490 | AU19: =AT18-AT19+AV19 -> 0 | AX19: =IF(AV19>0,AW19,AX18) -> 0.8
A20: =ELEC!C19 -> 44363 | B20: =B19 -> 191 | C20: =C19 -> 204 | D20: =C19-C20 -> 0 | E20: =D20*8.38 -> 0 | F20: =F19 -> 1841 | G20: =F20-F19 -> 0 | H20: =H19 -> 13408 | I20: =SUM(H20-H19) -> 0 | J20: =IF(G20>0,I20/G20,0) -> 0 | K20: =K19 -> 2331 | L20: =K20-K19 -> 0 | M20: =M19 -> 171898 | N20: =M20-M19 -> 0 | O20: =O19 -> 1869 | P20: =P19 -> 2096 | Q20: =Q19 -> 176206 | R20: =Q20-Q19 -> 0 | S20: =SUM(P20-P19) -> 0 | T20: =SUM(S20*$T$2) -> 0 | U20: =SUM(G20+L20+S20) -> 0 | V20: =R20+N20+I20:I20 -> 0 | X20: =X19 -> 2469 | Y20: =X20-X19 -> 0 | Z20: =Z19 -> 138993 | AA20: =Z20-Z19 -> 0 | AB20: =SUM(Y20*$AB$2) -> 0 | AC20: =AC19 -> 1937 | AD20: =AC20-AC19 -> 0 | AE20: =AE19 -> 365590 | AF20: =AE20-AE19 -> 0 | AG20: =IF(AD20>0,AF20/AD20,0) -> 0 | AH20: =AF20+AA20 -> 0 | AI20: =SUM(AH20+V20) -> 0 | AJ20: =-tanks!AW21 -> 0 | AK20: =SUM(AJ20-AI20) -> 0 | AL20: =S20+L20+G20 -> 0 | AM20: =Y20+AD20 -> 0 | AN20: =AN19 -> 67 | AO20: =(AN20/100)*3000 -> 2010 | AP20: =AP19 -> 55 | AQ20: =(AP20/100)*3000 -> 1650 | AR20: =AR19 -> 61 | AS20: =(AR20/100)*3000 -> 1830 | AT20: =SUM(AO20+AQ20+AS20) -> 5490 | AU20: =AT19-AT20+AV20 -> 0 | AX20: =IF(AV20>0,AW20,AX19) -> 0.8
A21: =ELEC!C20 -> 44364 | B21: =B20 -> 191 | C21: =C20 -> 204 | D21: =C20-C21 -> 0 | E21: =D21*8.38 -> 0 | F21: =F20 -> 1841 | G21: =F21-F20 -> 0 | H21: =H20 -> 13408 | I21: =SUM(H21-H20) -> 0 | J21: =IF(G21>0,I21/G21,0) -> 0 | K21: =K20 -> 2331 | L21: =K21-K20 -> 0 | M21: =M20 -> 171898 | N21: =M21-M20 -> 0 | O21: =O20 -> 1869 | P21: =P20 -> 2096 | Q21: =Q20 -> 176206 | R21: =Q21-Q20 -> 0 | S21: =SUM(P21-P20) -> 0 | T21: =SUM(S21*$T$2) -> 0 | U21: =SUM(G21+L21+S21) -> 0 | V21: =R21+N21+I21:I21 -> 0 | X21: =X20 -> 2469 | Y21: =X21-X20 -> 0 | Z21: =Z20 -> 138993 | AA21: =Z21-Z20 -> 0 | AB21: =SUM(Y21*$AB$2) -> 0 | AC21: =AC20 -> 1937 | AD21: =AC21-AC20 -> 0 | AE21: =AE20 -> 365590 | AF21: =AE21-AE20 -> 0 | AG21: =IF(AD21>0,AF21/AD21,0) -> 0 | AH21: =AF21+AA21 -> 0 | AI21: =SUM(AH21+V21) -> 0 | AJ21: =-tanks!AW22 -> 0 | AK21: =SUM(AJ21-AI21) -> 0 | AL21: =S21+L21+G21 -> 0 | AM21: =Y21+AD21 -> 0 | AN21: =AN20 -> 67 | AO21: =(AN21/100)*3000 -> 2010 | AP21: =AP20 -> 55 | AQ21: =(AP21/100)*3000 -> 1650 | AR21: =AR20 -> 61 | AS21: =(AR21/100)*3000 -> 1830 | AT21: =SUM(AO21+AQ21+AS21) -> 5490 | AU21: =AT20-AT21+AV21 -> 0 | AX21: =IF(AV21>0,AW21,AX20) -> 0.8
A22: =ELEC!C21 -> 44365 | B22: =B21 -> 191 | C22: =C21 -> 204 | D22: =C21-C22 -> 0 | E22: =D22*8.38 -> 0 | F22: =F21 -> 1841 | G22: =F22-F21 -> 0 | H22: =H21 -> 13408 | I22: =SUM(H22-H21) -> 0 | J22: =IF(G22>0,I22/G22,0) -> 0 | K22: =K21 -> 2331 | L22: =K22-K21 -> 0 | M22: =M21 -> 171898 | N22: =M22-M21 -> 0 | O22: =O21 -> 1869 | P22: =P21 -> 2096 | Q22: =Q21 -> 176206 | R22: =Q22-Q21 -> 0 | S22: =SUM(P22-P21) -> 0 | T22: =SUM(S22*$T$2) -> 0 | U22: =SUM(G22+L22+S22) -> 0 | V22: =R22+N22+I22:I22 -> 0 | X22: =X21 -> 2469 | Y22: =X22-X21 -> 0 | Z22: =Z21 -> 138993 | AA22: =Z22-Z21 -> 0 | AB22: =SUM(Y22*$AB$2) -> 0 | AC22: =AC21 -> 1937 | AD22: =AC22-AC21 -> 0 | AE22: =AE21 -> 365590 | AF22: =AE22-AE21 -> 0 | AG22: =IF(AD22>0,AF22/AD22,0) -> 0 | AH22: =AF22+AA22 -> 0 | AI22: =SUM(AH22+V22) -> 0 | AJ22: =-tanks!AW23 -> 0 | AK22: =SUM(AJ22-AI22) -> 0 | AL22: =S22+L22+G22 -> 0 | AM22: =Y22+AD22 -> 0 | AN22: =AN21 -> 67 | AO22: =(AN22/100)*3000 -> 2010 | AP22: =AP21 -> 55 | AQ22: =(AP22/100)*3000 -> 1650 | AR22: =AR21 -> 61 | AS22: =(AR22/100)*3000 -> 1830 | AT22: =SUM(AO22+AQ22+AS22) -> 5490 | AU22: =AT21-AT22+AV22 -> 0 | AX22: =IF(AV22>0,AW22,AX21) -> 0.8
A23: =ELEC!C22 -> 44366 | B23: =B22 -> 191 | C23: =C22 -> 204 | D23: =C22-C23 -> 0 | E23: =D23*8.38 -> 0 | F23: =F22 -> 1841 | G23: =F23-F22 -> 0 | H23: =H22 -> 13408 | I23: =SUM(H23-H22) -> 0 | J23: =IF(G23>0,I23/G23,0) -> 0 | K23: =K22 -> 2331 | L23: =K23-K22 -> 0 | M23: =M22 -> 171898 | N23: =M23-M22 -> 0 | O23: =O22 -> 1869 | P23: =P22 -> 2096 | Q23: =Q22 -> 176206 | R23: =Q23-Q22 -> 0 | S23: =SUM(P23-P22) -> 0 | T23: =SUM(S23*$T$2) -> 0 | U23: =SUM(G23+L23+S23) -> 0 | V23: =R23+N23+I23:I23 -> 0 | X23: =X22 -> 2469 | Y23: =X23-X22 -> 0 | Z23: =Z22 -> 138993 | AA23: =Z23-Z22 -> 0 | AB23: =SUM(Y23*$AB$2) -> 0 | AC23: =AC22 -> 1937 | AD23: =AC23-AC22 -> 0 | AE23: =AE22 -> 365590 | AF23: =AE23-AE22 -> 0 | AG23: =IF(AD23>0,AF23/AD23,0) -> 0 | AH23: =AF23+AA23 -> 0 | AI23: =SUM(AH23+V23) -> 0 | AJ23: =-tanks!AW24 -> 0 | AK23: =SUM(AJ23-AI23) -> 0 | AL23: =S23+L23+G23 -> 0 | AM23: =Y23+AD23 -> 0 | AN23: =AN22 -> 67 | AO23: =(AN23/100)*3000 -> 2010 | AP23: =AP22 -> 55 | AQ23: =(AP23/100)*3000 -> 1650 | AR23: =AR22 -> 61 | AS23: =(AR23/100)*3000 -> 1830 | AT23: =SUM(AO23+AQ23+AS23) -> 5490 | AU23: =AT22-AT23+AV23 -> 0 | AX23: =IF(AV23>0,AW23,AX22) -> 0.8
A24: =ELEC!C23 -> 44367 | B24: =B23 -> 191 | C24: =C23 -> 204 | D24: =C23-C24 -> 0 | E24: =D24*8.38 -> 0 | F24: =F23 -> 1841 | G24: =F24-F23 -> 0 | H24: =H23 -> 13408 | I24: =SUM(H24-H23) -> 0 | J24: =IF(G24>0,I24/G24,0) -> 0 | K24: =K23 -> 2331 | L24: =K24-K23 -> 0 | M24: =M23 -> 171898 | N24: =M24-M23 -> 0 | O24: =O23 -> 1869 | P24: =P23 -> 2096 | Q24: =Q23 -> 176206 | R24: =Q24-Q23 -> 0 | S24: =SUM(P24-P23) -> 0 | T24: =SUM(S24*$T$2) -> 0 | U24: =SUM(G24+L24+S24) -> 0 | V24: =R24+N24+I24:I24 -> 0 | X24: =X23 -> 2469 | Y24: =X24-X23 -> 0 | Z24: =Z23 -> 138993 | AA24: =Z24-Z23 -> 0 | AB24: =SUM(Y24*$AB$2) -> 0 | AC24: =AC23 -> 1937 | AD24: =AC24-AC23 -> 0 | AE24: =AE23 -> 365590 | AF24: =AE24-AE23 -> 0 | AG24: =IF(AD24>0,AF24/AD24,0) -> 0 | AH24: =AF24+AA24 -> 0 | AI24: =SUM(AH24+V24) -> 0 | AJ24: =-tanks!AW25 -> 0 | AK24: =SUM(AJ24-AI24) -> 0 | AL24: =S24+L24+G24 -> 0 | AM24: =Y24+AD24 -> 0 | AN24: =AN23 -> 67 | AO24: =(AN24/100)*3000 -> 2010 | AP24: =AP23 -> 55 | AQ24: =(AP24/100)*3000 -> 1650 | AR24: =AR23 -> 61 | AS24: =(AR24/100)*3000 -> 1830 | AT24: =SUM(AO24+AQ24+AS24) -> 5490 | AU24: =AT23-AT24+AV24 -> 0 | AX24: =IF(AV24>0,AW24,AX23) -> 0.8
A25: =ELEC!C24 -> 44368 | B25: =B24 -> 191 | C25: =C24 -> 204 | D25: =C24-C25 -> 0 | E25: =D25*8.38 -> 0 | F25: =F24 -> 1841 | G25: =F25-F24 -> 0 | H25: =H24 -> 13408 | I25: =SUM(H25-H24) -> 0 | J25: =IF(G25>0,I25/G25,0) -> 0 | K25: =K24 -> 2331 | L25: =K25-K24 -> 0 | M25: =M24 -> 171898 | N25: =M25-M24 -> 0 | O25: =O24 -> 1869 | P25: =P24 -> 2096 | Q25: =Q24 -> 176206 | R25: =Q25-Q24 -> 0 | S25: =SUM(P25-P24) -> 0 | T25: =SUM(S25*$T$2) -> 0 | U25: =SUM(G25+L25+S25) -> 0 | V25: =R25+N25+I25:I25 -> 0 | X25: =X24 -> 2469 | Y25: =X25-X24 -> 0 | Z25: =Z24 -> 138993 | AA25: =Z25-Z24 -> 0 | AB25: =SUM(Y25*$AB$2) -> 0 | AC25: =AC24 -> 1937 | AD25: =AC25-AC24 -> 0 | AE25: =AE24 -> 365590 | AF25: =AE25-AE24 -> 0 | AG25: =IF(AD25>0,AF25/AD25,0) -> 0 | AH25: =AF25+AA25 -> 0 | AI25: =SUM(AH25+V25) -> 0 | AJ25: =-tanks!AW26 -> 0 | AK25: =SUM(AJ25-AI25) -> 0 | AL25: =S25+L25+G25 -> 0 | AM25: =Y25+AD25 -> 0 | AN25: =AN24 -> 67 | AO25: =(AN25/100)*3000 -> 2010 | AP25: =AP24 -> 55 | AQ25: =(AP25/100)*3000 -> 1650 | AR25: =AR24 -> 61 | AS25: =(AR25/100)*3000 -> 1830 | AT25: =SUM(AO25+AQ25+AS25) -> 5490 | AU25: =AT24-AT25+AV25 -> 0 | AX25: =IF(AV25>0,AW25,AX24) -> 0.8
A26: =ELEC!C25 -> 44369 | B26: =B25 -> 191 | C26: =C25 -> 204 | D26: =C25-C26 -> 0 | E26: =D26*8.38 -> 0 | F26: =F25 -> 1841 | G26: =F26-F25 -> 0 | H26: =H25 -> 13408 | I26: =SUM(H26-H25) -> 0 | J26: =IF(G26>0,I26/G26,0) -> 0 | K26: =K25 -> 2331 | L26: =K26-K25 -> 0 | M26: =M25 -> 171898 | N26: =M26-M25 -> 0 | O26: =O25 -> 1869 | P26: =P25 -> 2096 | Q26: =Q25 -> 176206 | R26: =Q26-Q25 -> 0 | S26: =SUM(P26-P25) -> 0 | T26: =SUM(S26*$T$2) -> 0 | U26: =SUM(G26+L26+S26) -> 0 | V26: =R26+N26+I26:I26 -> 0 | X26: =X25 -> 2469 | Y26: =X26-X25 -> 0 | Z26: =Z25 -> 138993 | AA26: =Z26-Z25 -> 0 | AB26: =SUM(Y26*$AB$2) -> 0 | AC26: =AC25 -> 1937 | AD26: =AC26-AC25 -> 0 | AE26: =AE25 -> 365590 | AF26: =AE26-AE25 -> 0 | AG26: =IF(AD26>0,AF26/AD26,0) -> 0 | AH26: =AF26+AA26 -> 0 | AI26: =SUM(AH26+V26) -> 0 | AJ26: =-tanks!AW27 -> 0 | AK26: =SUM(AJ26-AI26) -> 0 | AL26: =S26+L26+G26 -> 0 | AM26: =Y26+AD26 -> 0 | AN26: =AN25 -> 67 | AO26: =(AN26/100)*3000 -> 2010 | AP26: =AP25 -> 55 | AQ26: =(AP26/100)*3000 -> 1650 | AR26: =AR25 -> 61 | AS26: =(AR26/100)*3000 -> 1830 | AT26: =SUM(AO26+AQ26+AS26) -> 5490 | AU26: =AT25-AT26+AV26 -> 0 | AX26: =IF(AV26>0,AW26,AX25) -> 0.8
A27: =ELEC!C26 -> 44370 | B27: =B26 -> 191 | C27: =C26 -> 204 | D27: =C26-C27 -> 0 | E27: =D27*8.38 -> 0 | F27: =F26 -> 1841 | G27: =F27-F26 -> 0 | H27: =H26 -> 13408 | I27: =SUM(H27-H26) -> 0 | J27: =IF(G27>0,I27/G27,0) -> 0 | K27: =K26 -> 2331 | L27: =K27-K26 -> 0 | M27: =M26 -> 171898 | N27: =M27-M26 -> 0 | O27: =O26 -> 1869 | P27: =P26 -> 2096 | Q27: =Q26 -> 176206 | R27: =Q27-Q26 -> 0 | S27: =SUM(P27-P26) -> 0 | T27: =SUM(S27*$T$2) -> 0 | U27: =SUM(G27+L27+S27) -> 0 | V27: =R27+N27+I27:I27 -> 0 | X27: =X26 -> 2469 | Y27: =X27-X26 -> 0 | Z27: =Z26 -> 138993 | AA27: =Z27-Z26 -> 0 | AB27: =SUM(Y27*$AB$2) -> 0 | AC27: =AC26 -> 1937 | AD27: =AC27-AC26 -> 0 | AE27: =AE26 -> 365590 | AF27: =AE27-AE26 -> 0 | AG27: =IF(AD27>0,AF27/AD27,0) -> 0 | AH27: =AF27+AA27 -> 0 | AI27: =SUM(AH27+V27) -> 0 | AJ27: =-tanks!AW28 -> 0 | AK27: =SUM(AJ27-AI27) -> 0 | AL27: =S27+L27+G27 -> 0 | AM27: =Y27+AD27 -> 0 | AN27: =AN26 -> 67 | AO27: =(AN27/100)*3000 -> 2010 | AP27: =AP26 -> 55 | AQ27: =(AP27/100)*3000 -> 1650 | AR27: =AR26 -> 61 | AS27: =(AR27/100)*3000 -> 1830 | AT27: =SUM(AO27+AQ27+AS27) -> 5490 | AU27: =AT26-AT27+AV27 -> 0 | AX27: =IF(AV27>0,AW27,AX26) -> 0.8
A28: =ELEC!C27 -> 44371 | B28: =B27 -> 191 | C28: =C27 -> 204 | D28: =C27-C28 -> 0 | E28: =D28*8.38 -> 0 | F28: =F27 -> 1841 | G28: =F28-F27 -> 0 | H28: =H27 -> 13408 | I28: =SUM(H28-H27) -> 0 | J28: =IF(G28>0,I28/G28,0) -> 0 | K28: =K27 -> 2331 | L28: =K28-K27 -> 0 | M28: =M27 -> 171898 | N28: =M28-M27 -> 0 | O28: =O27 -> 1869 | P28: =P27 -> 2096 | Q28: =Q27 -> 176206 | R28: =Q28-Q27 -> 0 | S28: =SUM(P28-P27) -> 0 | T28: =SUM(S28*$T$2) -> 0 | U28: =SUM(G28+L28+S28) -> 0 | V28: =R28+N28+I28:I28 -> 0 | X28: =X27 -> 2469 | Y28: =X28-X27 -> 0 | Z28: =Z27 -> 138993 | AA28: =Z28-Z27 -> 0 | AB28: =SUM(Y28*$AB$2) -> 0 | AC28: =AC27 -> 1937 | AD28: =AC28-AC27 -> 0 | AE28: =AE27 -> 365590 | AF28: =AE28-AE27 -> 0 | AG28: =IF(AD28>0,AF28/AD28,0) -> 0 | AH28: =AF28+AA28 -> 0 | AI28: =SUM(AH28+V28) -> 0 | AJ28: =-tanks!AW29 -> 0 | AK28: =SUM(AJ28-AI28) -> 0 | AL28: =S28+L28+G28 -> 0 | AM28: =Y28+AD28 -> 0 | AN28: =AN27 -> 67 | AO28: =(AN28/100)*3000 -> 2010 | AP28: =AP27 -> 55 | AQ28: =(AP28/100)*3000 -> 1650 | AR28: =AR27 -> 61 | AS28: =(AR28/100)*3000 -> 1830 | AT28: =SUM(AO28+AQ28+AS28) -> 5490 | AU28: =AT27-AT28+AV28 -> 0 | AX28: =IF(AV28>0,AW28,AX27) -> 0.8
A29: =ELEC!C28 -> 44372 | B29: =B28 -> 191 | C29: =C28 -> 204 | D29: =C28-C29 -> 0 | E29: =D29*8.38 -> 0 | F29: =F28 -> 1841 | G29: =F29-F28 -> 0 | H29: =H28 -> 13408 | I29: =SUM(H29-H28) -> 0 | J29: =IF(G29>0,I29/G29,0) -> 0 | K29: =K28 -> 2331 | L29: =K29-K28 -> 0 | M29: =M28 -> 171898 | N29: =M29-M28 -> 0 | O29: =O28 -> 1869 | P29: =P28 -> 2096 | Q29: =Q28 -> 176206 | R29: =Q29-Q28 -> 0 | S29: =SUM(P29-P28) -> 0 | T29: =SUM(S29*$T$2) -> 0 | U29: =SUM(G29+L29+S29) -> 0 | V29: =R29+N29+I29:I29 -> 0 | X29: =X28 -> 2469 | Y29: =X29-X28 -> 0 | Z29: =Z28 -> 138993 | AA29: =Z29-Z28 -> 0 | AB29: =SUM(Y29*$AB$2) -> 0 | AC29: =AC28 -> 1937 | AD29: =AC29-AC28 -> 0 | AE29: =AE28 -> 365590 | AF29: =AE29-AE28 -> 0 | AG29: =IF(AD29>0,AF29/AD29,0) -> 0 | AH29: =AF29+AA29 -> 0 | AI29: =SUM(AH29+V29) -> 0 | AJ29: =-tanks!AW30 -> 0 | AK29: =SUM(AJ29-AI29) -> 0 | AL29: =S29+L29+G29 -> 0 | AM29: =Y29+AD29 -> 0 | AN29: =AN28 -> 67 | AO29: =(AN29/100)*3000 -> 2010 | AP29: =AP28 -> 55 | AQ29: =(AP29/100)*3000 -> 1650 | AR29: =AR28 -> 61 | AS29: =(AR29/100)*3000 -> 1830 | AT29: =SUM(AO29+AQ29+AS29) -> 5490 | AU29: =AT28-AT29+AV29 -> 0 | AX29: =IF(AV29>0,AW29,AX28) -> 0.8
A30: =ELEC!C29 -> 44373 | B30: =B29 -> 191 | C30: =C29 -> 204 | D30: =C29-C30 -> 0 | E30: =D30*8.38 -> 0 | F30: =F29 -> 1841 | G30: =F30-F29 -> 0 | H30: =H29 -> 13408 | I30: =SUM(H30-H29) -> 0 | J30: =IF(G30>0,I30/G30,0) -> 0 | K30: =K29 -> 2331 | L30: =K30-K29 -> 0 | M30: =M29 -> 171898 | N30: =M30-M29 -> 0 | O30: =O29 -> 1869 | P30: =P29 -> 2096 | Q30: =Q29 -> 176206 | R30: =Q30-Q29 -> 0 | S30: =SUM(P30-P29) -> 0 | T30: =SUM(S30*$T$2) -> 0 | U30: =SUM(G30+L30+S30) -> 0 | V30: =R30+N30+I30:I30 -> 0 | X30: =X29 -> 2469 | Y30: =X30-X29 -> 0 | Z30: =Z29 -> 138993 | AA30: =Z30-Z29 -> 0 | AB30: =SUM(Y30*$AB$2) -> 0 | AC30: =AC29 -> 1937 | AD30: =AC30-AC29 -> 0 | AE30: =AE29 -> 365590 | AF30: =AE30-AE29 -> 0 | AG30: =IF(AD30>0,AF30/AD30,0) -> 0 | AH30: =AF30+AA30 -> 0 | AI30: =SUM(AH30+V30) -> 0 | AJ30: =-tanks!AW31 -> 0 | AK30: =SUM(AJ30-AI30) -> 0 | AL30: =S30+L30+G30 -> 0 | AM30: =Y30+AD30 -> 0 | AN30: =AN29 -> 67 | AO30: =(AN30/100)*3000 -> 2010 | AP30: =AP29 -> 55 | AQ30: =(AP30/100)*3000 -> 1650 | AR30: =AR29 -> 61 | AS30: =(AR30/100)*3000 -> 1830 | AT30: =SUM(AO30+AQ30+AS30) -> 5490 | AU30: =AT29-AT30+AV30 -> 0 | AX30: =IF(AV30>0,AW30,AX29) -> 0.8
... A34: =ELEC!C33 -> 44377 | B34: =B33 -> 191 | C34: =C33 -> 204 | D34: =C33-C34 -> 0 | E34: =D34*8.38 -> 0 | F34: =F33 -> 1841 | G34: =F34-F33 -> 0 | H34: =H33 -> 13408 | I34: =SUM(H34-H33) -> 0 | J34: =IF(G34>0,I34/G34,0) -> 0 | K34: =K33 -> 2331 | L34: =K34-K33 -> 0 | M34: =M33 -> 171898 | N34: =M34-M33 -> 0 | O34: =O33 -> 1869 | P34: =P33 -> 2096 | Q34: =Q33 -> 176206 | R34: =Q34-Q33 -> 0 | S34: =SUM(P34-P33) -> 0 | T34: =SUM(S34*$T$2) -> 0 | U34: =SUM(G34+L34+S34) -> 0 | V34: =R34+N34+I34:I34 -> 0 | X34: =X33 -> 2469 | Y34: =X34-X33 -> 0 | Z34: =Z33 -> 138993 | AA34: =Z34-Z33 -> 0 | AB34: =SUM(Y34*$AB$2) -> 0 | AC34: =AC33 -> 1937 | AD34: =AC34-AC33 -> 0 | AE34: =AE33 -> 365590 | AF34: =AE34-AE33 -> 0 | AG34: =IF(AD34>0,AF34/AD34,0) -> 0 | AH34: =AF34+AA34 -> 0 | AI34: =SUM(AH34+V34) -> 0 | AJ34: =-tanks!AW35 -> 0 | AK34: =SUM(AJ34-AI34) -> 0 | AL34: =S34+L34+G34 -> 0 | AM34: =Y34+AD34 -> 0 | AN34: =AN33 -> 67 | AO34: =(AN34/100)*3000 -> 2010 | AP34: =AP33 -> 55 | AQ34: =(AP34/100)*3000 -> 1650 | AR34: =AR33 -> 61 | AS34: =(AR34/100)*3000 -> 1830 | AT34: =SUM(AO34+AQ34+AS34) -> 5490 | AU34: =AT33-AT34+AV34 -> 0 | AX34: =IF(AV34>0,AW34,AX33) -> 0.8
J35: =SUM(J5:J32)/(COUNT(J5:J32)-COUNTIF(J5:J32,0)) -> 1 | V35: =SUM(V5:V34) -> 0 | AE35: . | AH35: =SUM(AH5:AH34) -> 0 | AL35: =SUM(AL5:AL34) -> 0 | AM35: =SUM(AM5:AM34) -> 0 | AR35: Nb Delivery | AS35: =COUNT(AW5:AW32) -> 0 | AU35: =SUM(AU5:AU32) -> 0 | AV35: =SUM(AV5:AV32) -> 0 | AW35: =SUM(AW5:AW32)/AS35 -> #DIV/0!
AH36: =AF36+AA36 -> 0 | AI36: =SUM(AI5:AI34) -> 0
AH37: =AF37+AA37 -> 0 | AU37: =AU35*0.51 -> 0 | AV37: =AV35/0.51 -> 0 | AW37: =SUM(AW5:AW32)/AS35 -> #DIV/0!
AV38: =AV35*0.51 -> 0

Sheet WATER
D1: =SUM(G21:G33) -> 8065473 | AR1: Entrance | AT1: Tank 1 | AV1: Tank 2
AR2: Level | AW2: Quantity CM3 | AZ2: Var
A3: Date | B3: Truck | C3: Truck M3/day | D3: N0. Trucks | F3: REQ. # of trucks | G3: City | H3: City/day | I3: Total water delivery | K3: SW | L3: Cosum SW/day | M3: RO Guest/ Liter | O3: RO K&L/ Liter | Q3: TOTAL RO Production | R3: RO 1 RH | S3: RO 2 RH | T3: RO water counter | U3: RO Cons m3 | V3: Steam Boiler | W3: Steam Boiler/day | X3: Softener Guest | Y3: Guest Sotf/day | Z3: Softener K&L | AA3: K&L Soft/Day | AB3: Fire Tank Level | AC3: Fire Tank Counter | AE3: Laundry Hot Water Counter | AF3: Hot Water Cons/day | AG3: Laundry Cold Water Counter | AH3: Cold Water Cons/day | AI3: Laundry Water Total Cons | AJ3: K&L Sotf/day | AK3: Guest / day | AL3: K&L /day | AM3: Avg Outside Temp | AN3: Banquet Activity | AR3: Date | AT3: MainI | AV3: Kitchen and Laundry | AX3: Guest | AY3: Main Tank | AZ3: Kitchen and Laundry | BA3: Guest | BB3: Kitchen and Laundry | BC3: Main | BD3: Guest | BE3: Total VAR | BF3: Hotel Consumption
E4: 1.66 | AN4: Ball R | AO4: Meeting | AP4: outlet | AT4: 180 | AV4: 220 | AX4: 580 | AY4: =SUM(AT4) -> 180 | AZ4: =SUM(AV4) -> 220 | BA4: =SUM(AX4) -> 580
A5: 44347 | B5: =[2]WATER!B36 -> 109443 | C5: =[2]WATER!C36 -> 0 | D5: =[2]WATER!D36 -> 0 | E5: =[2]WATER!E36 -> 241.93548 | F5: =[2]WATER!F36 -> 0 | G5: =[2]WATER!G36 -> 620421 | H5: =[2]WATER!H36 -> 148 | I5: =[2]WATER!I36 -> 148 | ... AP5: =[2]WATER!AP36 -> 0 | AR5: =[2]WATER!$AR$36 -> 44347 | AS5: =[2]WATER!AS36 -> 0.9 | AT5: =[2]WATER!AT36 -> 156 | AU5: =[2]WATER!AU36 -> 1.1 | AV5: =[2]WATER!AV36 -> 162 | AW5: =[2]WATER!AW36 -> 2.9 | AX5: =[2]WATER!AX36 -> 106 | AY5: =[2]WATER!AY36 -> 140.4 | AZ5: =[2]WATER!AZ36 -> 178.2 | ... BG5: =[2]WATER!BG36 -> 0
A6: =ELEC!C4 -> 44348 | B6: =B5 -> 109443 | C6: =B6-B5 -> 0 | D6: =C6/27 -> 0 | E6: =SUM((C6*$E$4)+(7500/'EDl log'!$A$37)) -> 250 | G6: =G5 -> 620421 | H6: =G6-G5 -> 0 | I6: =C6+H6 -> 0 | J6: =IF(I6>0,E6/I6,0) -> 0 | K6: ='Swimming Pool quality check '!H6 -> 6775 | L6: 0 | M6: =M5 -> 457.44 | N6: =SUM(M6-M5) -> 0 | O6: =O5 -> 529.52 | P6: =SUM(O6-O5) -> 0 | Q6: =P6+N6 -> 0 | T6: 5172 | U6: =SUM(T6-T5) -> 1 | V6: =V5 -> 474 | W6: =+V6-V5 -> 0 | X6: =X5 -> 152036 | Y6: =SUM(X6-X5) -> 0 | Z6: =Z5 -> 98847 | AA6: =Z6-Z5 -> 0 | AB6: =AB5 -> 261 | AC6: =AC5 -> 731 | AD6: 0 | AE6: =AE5 -> 229.81 | AF6: =AE6-AE5 -> 0 | AG6: =AG5 -> 2205.98 | AH6: =AG6-AG5 -> 0 | AI6: =AF6+AH6 -> 0 | AJ6: =+Z6-Z5 -> 0 | AK6: =SUM(Y6-L6) -> 0 | AL6: =SUM(AJ6-W6) -> 0 | AM6: ='General information '!D6 -> 24 | AN6: ='General information '!H6 -> 0 | AP6: ='General information '!J6 -> 0 | AR6: =A6 -> 44348 | AS6: =AS5 -> 0.9 | AT6: 90 | AU6: =AU5 -> 1.1 | AV6: 159 | AW6: 2.9 | AX6: 97 | AY6: =AS6*AT6 -> 81 | AZ6: =AU6*AV6 -> 174.9 | BA6: =AW6*AX6 -> 281.3 | BB6: =AY6-AY5 -> -59.4 | BC6: =AZ6-AZ5 -> -3.3 | BD6: =BA6-BA5 -> -26.1 | BE6: =SUM(BB6:BD6) -> -88.8 | BF6: =SUM(I6-BE6) -> 88.8 | BG6: =SUM(I6-BF6) -> -88.8
A7: =ELEC!C5 -> 44349 | B7: =B6 -> 109443 | C7: =B7-B6 -> 0 | D7: =C7/27 -> 0 | E7: =SUM((C7*$E$4)+(7500/'EDl log'!$A$37)) -> 250 | G7: =G6 -> 620421 | H7: =G7-G6 -> 0 | I7: =C7+H7 -> 0 | J7: =IF(I7>0,E7/I7,0) -> 0 | K7: ='Swimming Pool quality check '!H7 -> 6775 | L7: =K7-K6 -> 0 | M7: =M6 -> 457.44 | N7: =SUM(M7-M6) -> 0 | O7: =O6 -> 529.52 | P7: =SUM(O7-O6) -> 0 | Q7: =P7+N7 -> 0 | T7: =T6 -> 5172 | U7: =SUM(T7-T6) -> 0 | V7: =V6 -> 474 | W7: =+V7-V6 -> 0 | X7: =X6 -> 152036 | Y7: =SUM(X7-X6) -> 0 | Z7: =Z6 -> 98847 | AA7: =Z7-Z6 -> 0 | AB7: =AB6 -> 261 | AC7: =AC6 -> 731 | AD7: =AC7-AC6 -> 0 | AE7: =AE6 -> 229.81 | AF7: =AE7-AE6 -> 0 | AG7: =AG6 -> 2205.98 | AH7: =AG7-AG6 -> 0 | AI7: =AF7+AH7 -> 0 | AJ7: =+Z7-Z6 -> 0 | AK7: =SUM(Y7-L7) -> 0 | AL7: =SUM(AJ7-W7) -> 0 | AM7: ='General information '!D7 -> 0 | AN7: ='General information '!H7 -> 0 | AP7: ='General information '!J7 -> 0 | AR7: =A7 -> 44349 | AS7: =AS6 -> 0.9 | AT7: =AT6 -> 90 | AU7: =AU6 -> 1.1 | AV7: =AV6 -> 159 | AW7: 2.9 | AX7: =AX6 -> 97 | AY7: =AS7*AT7 -> 81 | AZ7: =AU7*AV7 -> 174.9 | BA7: =AW7*AX7 -> 281.3 | BB7: =AY7-AY6 -> 0 | BC7: =AZ7-AZ6 -> 0 | BD7: =BA7-BA6 -> 0 | BE7: =SUM(BB7:BD7) -> 0 | BF7: =SUM(I7-BE7) -> 0 | BG7: =SUM(I7-BF7) -> 0
A8: =ELEC!C6 -> 44350 | B8: =B7 -> 109443 | C8: =B8-B7 -> 0 | D8: =C8/27 -> 0 | E8: =SUM((C8*$E$4)+(7500/'EDl log'!$A$37)) -> 250 | G8: =G7 -> 620421 | H8: =G8-G7 -> 0 | I8: =C8+H8 -> 0 | J8: =IF(I8>0,E8/I8,0) -> 0 | K8: ='Swimming Pool quality check '!H8 -> 6775 | L8: =K8-K7 -> 0 | M8: =M7 -> 457.44 | N8: =SUM(M8-M7) -> 0 | O8: =O7 -> 529.52 | P8: =SUM(O8-O7) -> 0 | Q8: =P8+N8 -> 0 | T8: =T7 -> 5172 | U8: =SUM(T8-T7) -> 0 | V8: =V7 -> 474 | W8: =+V8-V7 -> 0 | X8: =X7 -> 152036 | Y8: =SUM(X8-X7) -> 0 | Z8: =Z7 -> 98847 | AA8: =Z8-Z7 -> 0 | AB8: =AB7 -> 261 | AC8: =AC7 -> 731 | AD8: =AC8-AC7 -> 0 | AE8: =AE7 -> 229.81 | AF8: =AE8-AE7 -> 0 | AG8: =AG7 -> 2205.98 | AH8: =AG8-AG7 -> 0 | AI8: =AF8+AH8 -> 0 | AJ8: =+Z8-Z7 -> 0 | AK8: =SUM(Y8-L8) -> 0 | AL8: =SUM(AJ8-W8) -> 0 | AM8: ='General information '!D8 -> 0 | AN8: ='General information '!H8 -> 0 | AP8: ='General information '!J8 -> 0 | AR8: =A8 -> 44350 | AS8: =AS7 -> 0.9 | AT8: =AT7 -> 90 | AU8: 1.1 | AV8: =AV7 -> 159 | AW8: 2.9 | AX8: =AX7 -> 97 | AY8: =AS8*AT8 -> 81 | AZ8: =AU8*AV8 -> 174.9 | BA8: =AW8*AX8 -> 281.3 | BB8: =AY8-AY7 -> 0 | BC8: =AZ8-AZ7 -> 0 | BD8: =BA8-BA7 -> 0 | BE8: =SUM(BB8:BD8) -> 0 | BF8: =SUM(I8-BE8) -> 0 | BG8: =SUM(I8-BF8) -> 0
A9: =ELEC!C7 -> 44351 | B9: =B8 -> 109443 | C9: =B9-B8 -> 0 | D9: =C9/27 -> 0 | E9: =SUM((C9*$E$4)+(7500/'EDl log'!$A$37)) -> 250 | G9: =G8 -> 620421 | H9: =G9-G8 -> 0 | I9: =C9+H9 -> 0 | J9: =IF(I9>0,E9/I9,0) -> 0 | K9: ='Swimming Pool quality check '!H9 -> 6775 | L9: =K9-K8 -> 0 | M9: =M8 -> 457.44 | N9: =SUM(M9-M8) -> 0 | O9: =O8 -> 529.52 | P9: =SUM(O9-O8) -> 0 | Q9: =P9+N9 -> 0 | T9: =T8 -> 5172 | U9: =SUM(T9-T8) -> 0 | V9: =V8 -> 474 | W9: =+V9-V8 -> 0 | X9: =X8 -> 152036 | Y9: =SUM(X9-X8) -> 0 | Z9: =Z8 -> 98847 | AA9: =Z9-Z8 -> 0 | AB9: =AB8 -> 261 | AC9: =AC8 -> 731 | AD9: =AC9-AC8 -> 0 | AE9: =AE8 -> 229.81 | AF9: =AE9-AE8 -> 0 | AG9: =AG8 -> 2205.98 | AH9: =AG9-AG8 -> 0 | AI9: =AF9+AH9 -> 0 | AJ9: =+Z9-Z8 -> 0 | AK9: =SUM(Y9-L9) -> 0 | AL9: =SUM(AJ9-W9) -> 0 | AM9: ='General information '!D9 -> 0 | AN9: ='General information '!H9 -> 0 | AP9: ='General information '!J9 -> 0 | AR9: =A9 -> 44351 | AS9: =AS8 -> 0.9 | AT9: =AT8 -> 90 | AU9: =AU8 -> 1.1 | AV9: =AV8 -> 159 | AW9: 2.9 | AX9: =AX8 -> 97 | AY9: =AS9*AT9 -> 81 | AZ9: =AU9*AV9 -> 174.9 | BA9: =AW9*AX9 -> 281.3 | BB9: =AY9-AY8 -> 0 | BC9: =AZ9-AZ8 -> 0 | BD9: =BA9-BA8 -> 0 | BE9: =SUM(BB9:BD9) -> 0 | BF9: =SUM(I9-BE9) -> 0 | BG9: =SUM(I9-BF9) -> 0
A10: =ELEC!C8 -> 44352 | B10: =B9 -> 109443 | C10: =B10-B9 -> 0 | D10: =C10/27 -> 0 | E10: =SUM((C10*$E$4)+(7500/'EDl log'!$A$37)) -> 250 | G10: =G9 -> 620421 | H10: =G10-G9 -> 0 | I10: =C10+H10 -> 0 | J10: =IF(I10>0,E10/I10,0) -> 0 | K10: ='Swimming Pool quality check '!H10 -> 6775 | L10: =K10-K9 -> 0 | M10: =M9 -> 457.44 | N10: =SUM(M10-M9) -> 0 | O10: =O9 -> 529.52 | P10: =SUM(O10-O9) -> 0 | Q10: =P10+N10 -> 0 | T10: =T9 -> 5172 | U10: =SUM(T10-T9) -> 0 | V10: =V9 -> 474 | W10: =+V10-V9 -> 0 | X10: =X9 -> 152036 | Y10: =SUM(X10-X9) -> 0 | Z10: =Z9 -> 98847 | AA10: =Z10-Z9 -> 0 | AB10: =AB9 -> 261 | AC10: =AC9 -> 731 | AD10: =AC10-AC9 -> 0 | AE10: =AE9 -> 229.81 | AF10: =AE10-AE9 -> 0 | AG10: =AG9 -> 2205.98 | AH10: =AG10-AG9 -> 0 | AI10: =AF10+AH10 -> 0 | AJ10: =+Z10-Z9 -> 0 | AK10: =SUM(Y10-L10) -> 0 | AL10: =SUM(AJ10-W10) -> 0 | AM10: ='General information '!D10 -> 0 | AN10: ='General information '!H10 -> 0 | AP10: ='General information '!J10 -> 0 | AR10: =A10 -> 44352 | AS10: =AS9 -> 0.9 | AT10: =AT9 -> 90 | AU10: =AU9 -> 1.1 | AV10: =AV9 -> 159 | AW10: 2.9 | AX10: =AX9 -> 97 | AY10: =AS10*AT10 -> 81 | AZ10: =AU10*AV10 -> 174.9 | BA10: =AW10*AX10 -> 281.3 | BB10: =AY10-AY9 -> 0 | BC10: =AZ10-AZ9 -> 0 | BD10: =BA10-BA9 -> 0 | BE10: =SUM(BB10:BD10) -> 0 | BF10: =SUM(I10-BE10) -> 0 | BG10: =SUM(I10-BF10) -> 0
A11: =ELEC!C9 -> 44353 | B11: =B10 -> 109443 | C11: =B11-B10 -> 0 | D11: =C11/27 -> 0 | E11: =SUM((C11*$E$4)+(7500/'EDl log'!$A$37)) -> 250 | G11: =G10 -> 620421 | H11: =G11-G10 -> 0 | I11: =C11+H11 -> 0 | J11: =IF(I11>0,E11/I11,0) -> 0 | K11: ='Swimming Pool quality check '!H11 -> 6775 | L11: =K11-K10 -> 0 | M11: =M10 -> 457.44 | N11: =SUM(M11-M10) -> 0 | O11: =O10 -> 529.52 | P11: =SUM(O11-O10) -> 0 | Q11: =SUM(P11+N11) -> 0 | T11: =T10 -> 5172 | U11: =SUM(T11-T10) -> 0 | V11: =V10 -> 474 | W11: =+V11-V10 -> 0 | X11: =X10 -> 152036 | Y11: =SUM(X11-X10) -> 0 | Z11: =Z10 -> 98847 | AA11: =Z11-Z10 -> 0 | AB11: =AB10 -> 261 | AC11: =AC10 -> 731 | AD11: =AC11-AC10 -> 0 | AE11: =AE10 -> 229.81 | AF11: =AE11-AE10 -> 0 | AG11: =AG10 -> 2205.98 | AH11: =AG11-AG10 -> 0 | AI11: =AF11+AH11 -> 0 | AJ11: =+Z11-Z10 -> 0 | AK11: =SUM(Y11-L11) -> 0 | AL11: =SUM(AJ11-W11) -> 0 | AM11: ='General information '!D11 -> 0 | AN11: ='General information '!H11 -> 0 | AP11: ='General information '!J11 -> 0 | AR11: =A11 -> 44353 | AS11: =AS10 -> 0.9 | AT11: =AT10 -> 90 | AU11: =AU10 -> 1.1 | AV11: =AV10 -> 159 | AW11: 2.9 | AX11: =AX10 -> 97 | AY11: =AS11*AT11 -> 81 | AZ11: =AU11*AV11 -> 174.9 | BA11: =AW11*AX11 -> 281.3 | BB11: =AY11-AY10 -> 0 | BC11: =AZ11-AZ10 -> 0 | BD11: =BA11-BA10 -> 0 | BE11: =SUM(BB11:BD11) -> 0 | BF11: =SUM(I11-BE11) -> 0 | BG11: =SUM(I11-BF11) -> 0
A12: =ELEC!C10 -> 44354 | B12: =B11 -> 109443 | C12: =B12-B11 -> 0 | D12: =C12/27 -> 0 | E12: =SUM((C12*$E$4)+(7500/'EDl log'!$A$37)) -> 250 | G12: =G11 -> 620421 | H12: =G12-G11 -> 0 | I12: =C12+H12 -> 0 | J12: =IF(I12>0,E12/I12,0) -> 0 | K12: ='Swimming Pool quality check '!H12 -> 6775 | L12: =K12-K11 -> 0 | M12: =M11 -> 457.44 | N12: =SUM(M12-M11) -> 0 | O12: =O11 -> 529.52 | P12: =SUM(O12-O11) -> 0 | Q12: =SUM(P12+N12) -> 0 | T12: =T11 -> 5172 | U12: =SUM(T12-T11) -> 0 | V12: =V11 -> 474 | W12: =+V12-V11 -> 0 | X12: =X11 -> 152036 | Y12: =SUM(X12-X11) -> 0 | Z12: =Z11 -> 98847 | AA12: =Z12-Z11 -> 0 | AB12: =AB11 -> 261 | AC12: =AC11 -> 731 | AD12: =AC12-AC11 -> 0 | AE12: =AE11 -> 229.81 | AF12: =AE12-AE11 -> 0 | AG12: =AG11 -> 2205.98 | AH12: =AG12-AG11 -> 0 | AI12: =AF12+AH12 -> 0 | AJ12: =+Z12-Z11 -> 0 | AK12: =SUM(Y12-L12) -> 0 | AL12: =SUM(AJ12-W12) -> 0 | AM12: ='General information '!D12 -> 0 | AN12: ='General information '!H12 -> 0 | AP12: ='General information '!J12 -> 0 | AR12: =A12 -> 44354 | AS12: =AS11 -> 0.9 | AT12: =AT11 -> 90 | AU12: =AU11 -> 1.1 | AV12: =AV11 -> 159 | AW12: 2.9 | AX12: =AX11 -> 97 | AY12: =AS12*AT12 -> 81 | AZ12: =AU12*AV12 -> 174.9 | BA12: =AW12*AX12 -> 281.3 | BB12: =AY12-AY11 -> 0 | BC12: =AZ12-AZ11 -> 0 | BD12: =BA12-BA11 -> 0 | BE12: =SUM(BB12:BD12) -> 0 | BF12: =SUM(I12-BE12) -> 0 | BG12: =SUM(I12-BF12) -> 0
A13: =ELEC!C11 -> 44355 | B13: =B12 -> 109443 | C13: =B13-B12 -> 0 | D13: =C13/27 -> 0 | E13: =SUM((C13*$E$4)+(7500/'EDl log'!$A$37)) -> 250 | G13: =G12 -> 620421 | H13: =G13-G12 -> 0 | I13: =C13+H13 -> 0 | J13: =IF(I13>0,E13/I13,0) -> 0 | K13: ='Swimming Pool quality check '!H13 -> 6775 | L13: =K13-K12 -> 0 | M13: =M12 -> 457.44 | N13: =SUM(M13-M12) -> 0 | O13: =O12 -> 529.52 | P13: =SUM(O13-O12) -> 0 | Q13: =SUM(P13+N13) -> 0 | T13: =T12 -> 5172 | U13: =SUM(T13-T12) -> 0 | V13: =V12 -> 474 | W13: =+V13-V12 -> 0 | X13: =X12 -> 152036 | Y13: =SUM(X13-X12) -> 0 | Z13: =Z12 -> 98847 | AA13: =Z13-Z12 -> 0 | AB13: =AB12 -> 261 | AC13: =AC12 -> 731 | AD13: =AC13-AC12 -> 0 | AE13: =AE12 -> 229.81 | AF13: =AE13-AE12 -> 0 | AG13: =AG12 -> 2205.98 | AH13: =AG13-AG12 -> 0 | AI13: =AF13+AH13 -> 0 | AJ13: =+Z13-Z12 -> 0 | AK13: =SUM(Y13-L13) -> 0 | AL13: =SUM(AJ13-W13) -> 0 | AM13: ='General information '!D13 -> 0 | AN13: ='General information '!J13 -> 0 | AP13: ='General information '!J13 -> 0 | AR13: =A13 -> 44355 | AS13: =AS12 -> 0.9 | AT13: =AT12 -> 90 | AU13: =AU12 -> 1.1 | AV13: =AV12 -> 159 | AW13: 2.9 | AX13: =AX12 -> 97 | AY13: =AS13*AT13 -> 81 | AZ13: =AU13*AV13 -> 174.9 | BA13: =AW13*AX13 -> 281.3 | BB13: =AY13-AY12 -> 0 | BC13: =AZ13-AZ12 -> 0 | BD13: =BA13-BA12 -> 0 | BE13: =SUM(BB13:BD13) -> 0 | BF13: =SUM(I13-BE13) -> 0 | BG13: =SUM(I13-BF13) -> 0
A14: =ELEC!C12 -> 44356 | B14: =B13 -> 109443 | C14: =B14-B13 -> 0 | D14: =C14/27 -> 0 | E14: =SUM((C14*$E$4)+(7500/'EDl log'!$A$37)) -> 250 | G14: =G13 -> 620421 | H14: =G14-G13 -> 0 | I14: =C14+H14 -> 0 | J14: =IF(I14>0,E14/I14,0) -> 0 | K14: ='Swimming Pool quality check '!H14 -> 6775 | L14: =K14-K13 -> 0 | M14: =M13 -> 457.44 | N14: =SUM(M14-M13) -> 0 | O14: =O13 -> 529.52 | P14: =SUM(O14-O13) -> 0 | Q14: =SUM(P14+N14) -> 0 | T14: =T13 -> 5172 | U14: =SUM(T14-T13) -> 0 | V14: =V13 -> 474 | W14: =+V14-V13 -> 0 | X14: =X13 -> 152036 | Y14: =SUM(X14-X13) -> 0 | Z14: =Z13 -> 98847 | AA14: =Z14-Z13 -> 0 | AB14: =AB13 -> 261 | AC14: =AC13 -> 731 | AD14: =AC14-AC13 -> 0 | AE14: =AE13 -> 229.81 | AF14: =AE14-AE13 -> 0 | AG14: =AG13 -> 2205.98 | AH14: =AG14-AG13 -> 0 | AI14: =AF14+AH14 -> 0 | AJ14: =+Z14-Z13 -> 0 | AK14: =SUM(Y14-L14) -> 0 | AL14: =SUM(AJ14-W14) -> 0 | AM14: ='General information '!D14 -> 0 | AN14: ='General information '!H14 -> 0 | AP14: ='General information '!J14 -> 0 | AR14: =A14 -> 44356 | AS14: =AS13 -> 0.9 | AT14: =AT13 -> 90 | AU14: =AU13 -> 1.1 | AV14: =AV13 -> 159 | AW14: 2.9 | AX14: =AX13 -> 97 | AY14: =AS14*AT14 -> 81 | AZ14: =AU14*AV14 -> 174.9 | BA14: =AW14*AX14 -> 281.3 | BB14: =AY14-AY13 -> 0 | BC14: =AZ14-AZ13 -> 0 | BD14: =BA14-BA13 -> 0 | BE14: =SUM(BB14:BD14) -> 0 | BF14: =SUM(I14-BE14) -> 0 | BG14: =SUM(I14-BF14) -> 0
A15: =ELEC!C13 -> 44357 | B15: =B14 -> 109443 | C15: =B15-B14 -> 0 | D15: =C15/27 -> 0 | E15: =SUM((C15*$E$4)+(7500/'EDl log'!$A$37)) -> 250 | G15: =G14 -> 620421 | H15: =G15-G14 -> 0 | I15: =C15+H15 -> 0 | J15: =IF(I15>0,E15/I15,0) -> 0 | K15: ='Swimming Pool quality check '!H15 -> 6775 | L15: =K15-K14 -> 0 | M15: =M14 -> 457.44 | N15: =SUM(M15-M14) -> 0 | O15: =O14 -> 529.52 | P15: =SUM(O15-O14) -> 0 | Q15: =SUM(P15+N15) -> 0 | T15: =T14 -> 5172 | U15: =SUM(T15-T14) -> 0 | V15: =V14 -> 474 | W15: =+V15-V14 -> 0 | X15: =X14 -> 152036 | Y15: =SUM(X15-X14) -> 0 | Z15: =Z14 -> 98847 | AA15: =Z15-Z14 -> 0 | AB15: =AB14 -> 261 | AC15: =AC14 -> 731 | AD15: =AC15-AC14 -> 0 | AE15: =AE14 -> 229.81 | AF15: =AE15-AE14 -> 0 | AG15: =AG14 -> 2205.98 | AH15: =AG15-AG14 -> 0 | AI15: =AF15+AH15 -> 0 | AJ15: =+Z15-Z14 -> 0 | AK15: =SUM(Y15-L15) -> 0 | AL15: =SUM(AJ15-W15) -> 0 | AM15: ='General information '!D15 -> 0 | AN15: ='General information '!H15 -> 0 | AP15: ='General information '!J15 -> 0 | AR15: =A15 -> 44357 | AS15: =AS14 -> 0.9 | AT15: =AT14 -> 90 | AU15: =AU14 -> 1.1 | AV15: =AV14 -> 159 | AW15: 2.9 | AX15: =AX14 -> 97 | AY15: =AS15*AT15 -> 81 | AZ15: =AU15*AV15 -> 174.9 | BA15: =AW15*AX15 -> 281.3 | BB15: =AY15-AY14 -> 0 | BC15: =AZ15-AZ14 -> 0 | BD15: =BA15-BA14 -> 0 | BE15: =SUM(BB15:BD15) -> 0 | BF15: =SUM(I15-BE15) -> 0 | BG15: =SUM(I15-BF15) -> 0
A16: =ELEC!C14 -> 44358 | B16: =B15 -> 109443 | C16: =B16-B15 -> 0 | D16: =C16/27 -> 0 | E16: =SUM((C16*$E$4)+(7500/'EDl log'!$A$37)) -> 250 | G16: =G15 -> 620421 | H16: =G16-G15 -> 0 | I16: =C16+H16 -> 0 | J16: =IF(I16>0,E16/I16,0) -> 0 | K16: ='Swimming Pool quality check '!H16 -> 6775 | L16: =K16-K15 -> 0 | M16: =M15 -> 457.44 | N16: =SUM(M16-M15) -> 0 | O16: =O15 -> 529.52 | P16: =SUM(O16-O15) -> 0 | Q16: =SUM(P16+N16) -> 0 | T16: =T15 -> 5172 | U16: =SUM(T16-T15) -> 0 | V16: =V15 -> 474 | W16: =+V16-V15 -> 0 | X16: =X15 -> 152036 | Y16: =SUM(X16-X15) -> 0 | Z16: =Z15 -> 98847 | AA16: =Z16-Z15 -> 0 | AB16: =AB15 -> 261 | AC16: =AC15 -> 731 | AD16: =AC16-AC15 -> 0 | AE16: =AE15 -> 229.81 | AF16: =AE16-AE15 -> 0 | AG16: =AG15 -> 2205.98 | AH16: =AG16-AG15 -> 0 | AI16: =AF16+AH16 -> 0 | AJ16: =+Z16-Z15 -> 0 | AK16: =SUM(Y16-L16) -> 0 | AL16: =SUM(AJ16-W16) -> 0 | AM16: ='General information '!D16 -> 0 | AN16: ='General information '!H16 -> 0 | AP16: ='General information '!J16 -> 0 | AR16: =A16 -> 44358 | AS16: =AS15 -> 0.9 | AT16: =AT15 -> 90 | AU16: =AU15 -> 1.1 | AV16: =AV15 -> 159 | AW16: 2.9 | AX16: =AX15 -> 97 | AY16: =AS16*AT16 -> 81 | AZ16: =AU16*AV16 -> 174.9 | BA16: =AW16*AX16 -> 281.3 | BB16: =AY16-AY15 -> 0 | BC16: =AZ16-AZ15 -> 0 | BD16: =BA16-BA15 -> 0 | BE16: =SUM(BB16:BD16) -> 0 | BF16: =SUM(I16-BE16) -> 0 | BG16: =SUM(I16-BF16) -> 0
A17: =ELEC!C15 -> 44359 | B17: =B16 -> 109443 | C17: =B17-B16 -> 0 | D17: =C17/27 -> 0 | E17: =SUM((C17*$E$4)+(7500/'EDl log'!$A$37)) -> 250 | G17: =G16 -> 620421 | H17: =G17-G16 -> 0 | I17: =C17+H17 -> 0 | J17: =IF(I17>0,E17/I17,0) -> 0 | K17: ='Swimming Pool quality check '!H17 -> 6775 | L17: =K17-K16 -> 0 | M17: =M16 -> 457.44 | N17: =SUM(M17-M16) -> 0 | O17: =O16 -> 529.52 | P17: =SUM(O17-O16) -> 0 | Q17: =SUM(P17+N17) -> 0 | T17: =T16 -> 5172 | U17: =SUM(T17-T16) -> 0 | V17: =V16 -> 474 | W17: =+V17-V16 -> 0 | X17: =X16 -> 152036 | Y17: =SUM(X17-X16) -> 0 | Z17: =Z16 -> 98847 | AA17: =Z17-Z16 -> 0 | AB17: =AB16 -> 261 | AC17: =AC16 -> 731 | AD17: =AC17-AC16 -> 0 | AE17: =AE16 -> 229.81 | AF17: =AE17-AE16 -> 0 | AG17: =AG16 -> 2205.98 | AH17: =AG17-AG16 -> 0 | AI17: =AF17+AH17 -> 0 | AJ17: =+Z17-Z16 -> 0 | AK17: =SUM(Y17-L17) -> 0 | AL17: =SUM(AJ17-W17) -> 0 | AM17: ='General information '!D17 -> 0 | AN17: ='General information '!H17 -> 0 | AP17: ='General information '!J17 -> 0 | AR17: =A17 -> 44359 | AS17: =AS16 -> 0.9 | AT17: =AT16 -> 90 | AU17: =AU16 -> 1.1 | AV17: =AV16 -> 159 | AW17: 2.9 | AX17: =AX16 -> 97 | AY17: =AS17*AT17 -> 81 | AZ17: =AU17*AV17 -> 174.9 | BA17: =AW17*AX17 -> 281.3 | BB17: =AY17-AY16 -> 0 | BC17: =AZ17-AZ16 -> 0 | BD17: =BA17-BA16 -> 0 | BE17: =SUM(BB17:BD17) -> 0 | BF17: =SUM(I17-BE17) -> 0 | BG17: =SUM(I17-BF17) -> 0
A18: =ELEC!C16 -> 44360 | B18: =B17 -> 109443 | C18: =B18-B17 -> 0 | D18: =C18/27 -> 0 | E18: =SUM((C18*$E$4)+(7500/'EDl log'!$A$37)) -> 250 | G18: =G17 -> 620421 | H18: =G18-G17 -> 0 | I18: =C18+H18 -> 0 | J18: =IF(I18>0,E18/I18,0) -> 0 | K18: ='Swimming Pool quality check '!H18 -> 6775 | L18: =K18-K17 -> 0 | M18: =M17 -> 457.44 | N18: =SUM(M18-M17) -> 0 | O18: =O17 -> 529.52 | P18: =SUM(O18-O17) -> 0 | Q18: =SUM(P18+N18) -> 0 | T18: =T17 -> 5172 | U18: =SUM(T18-T17) -> 0 | V18: =V17 -> 474 | W18: =+V18-V17 -> 0 | X18: =X17 -> 152036 | Y18: =SUM(X18-X17) -> 0 | Z18: =Z17 -> 98847 | AA18: =Z18-Z17 -> 0 | AB18: =AB17 -> 261 | AC18: =AC17 -> 731 | AD18: =AC18-AC17 -> 0 | AE18: =AE17 -> 229.81 | AF18: =AE18-AE17 -> 0 | AG18: =AG17 -> 2205.98 | AH18: =AG18-AG17 -> 0 | AI18: =AF18+AH18 -> 0 | AJ18: =+Z18-Z17 -> 0 | AK18: =SUM(Y18-L18) -> 0 | AL18: =SUM(AJ18-W18) -> 0 | AM18: ='General information '!D18 -> 0 | AN18: ='General information '!H18 -> 0 | AP18: ='General information '!J18 -> 0 | AR18: =A18 -> 44360 | AS18: =AS17 -> 0.9 | AT18: =AT17 -> 90 | AU18: =AU17 -> 1.1 | AV18: =AV17 -> 159 | AW18: 2.9 | AX18: =AX17 -> 97 | AY18: =AS18*AT18 -> 81 | AZ18: =AU18*AV18 -> 174.9 | BA18: =AW18*AX18 -> 281.3 | BB18: =AY18-AY17 -> 0 | BC18: =AZ18-AZ17 -> 0 | BD18: =BA18-BA17 -> 0 | BE18: =SUM(BB18:BD18) -> 0 | BF18: =SUM(I18-BE18) -> 0 | BG18: =SUM(I18-BF18) -> 0
A19: =ELEC!C17 -> 44361 | B19: =B18 -> 109443 | C19: =B19-B18 -> 0 | D19: =C19/27 -> 0 | E19: =SUM((C19*$E$4)+(7500/'EDl log'!$A$37)) -> 250 | G19: =G18 -> 620421 | H19: =G19-G18 -> 0 | I19: =C19+H19 -> 0 | J19: =IF(I19>0,E19/I19,0) -> 0 | K19: ='Swimming Pool quality check '!H19 -> 6775 | L19: =K19-K18 -> 0 | M19: =M18 -> 457.44 | N19: =SUM(M19-M18) -> 0 | O19: =O18 -> 529.52 | P19: =SUM(O19-O18) -> 0 | Q19: =SUM(P19+N19) -> 0 | T19: =T18 -> 5172 | U19: =SUM(T19-T18) -> 0 | V19: =V18 -> 474 | W19: =+V19-V18 -> 0 | X19: =X18 -> 152036 | Y19: =SUM(X19-X18) -> 0 | Z19: =Z18 -> 98847 | AA19: =Z19-Z18 -> 0 | AB19: =AB18 -> 261 | AC19: =AC18 -> 731 | AD19: =AC19-AC18 -> 0 | AE19: =AE18 -> 229.81 | AF19: =AE19-AE18 -> 0 | AG19: =AG18 -> 2205.98 | AH19: =AG19-AG18 -> 0 | AI19: =AF19+AH19 -> 0 | AJ19: =+Z19-Z18 -> 0 | AK19: =SUM(Y19-L19) -> 0 | AL19: =SUM(AJ19-W19) -> 0 | AM19: ='General information '!D19 -> 0 | AN19: ='General information '!H19 -> 0 | AP19: ='General information '!J19 -> 0 | AR19: =A19 -> 44361 | AS19: =AS18 -> 0.9 | AT19: =AT18 -> 90 | AU19: =AU18 -> 1.1 | AV19: =AV18 -> 159 | AW19: 2.9 | AX19: =AX18 -> 97 | AY19: =AS19*AT19 -> 81 | AZ19: =AU19*AV19 -> 174.9 | BA19: =AW19*AX19 -> 281.3 | BB19: =AY19-AY18 -> 0 | BC19: =AZ19-AZ18 -> 0 | BD19: =BA19-BA18 -> 0 | BE19: =SUM(BB19:BD19) -> 0 | BF19: =SUM(I19-BE19) -> 0 | BG19: =SUM(I19-BF19) -> 0
A20: =ELEC!C18 -> 44362 | B20: =B19 -> 109443 | C20: =B20-B19 -> 0 | D20: =C20/27 -> 0 | E20: =SUM((C20*$E$4)+(7500/'EDl log'!$A$37)) -> 250 | G20: =G19 -> 620421 | H20: =G20-G19 -> 0 | I20: =C20+H20 -> 0 | J20: =IF(I20>0,E20/I20,0) -> 0 | K20: ='Swimming Pool quality check '!H20 -> 6775 | L20: =K20-K19 -> 0 | M20: =M19 -> 457.44 | N20: =SUM(M20-M19) -> 0 | O20: =O19 -> 529.52 | P20: =SUM(O20-O19) -> 0 | Q20: =SUM(P20+N20) -> 0 | T20: =T19 -> 5172 | U20: =SUM(T20-T19) -> 0 | V20: =V19 -> 474 | W20: =+V20-V19 -> 0 | X20: =X19 -> 152036 | Y20: =SUM(X20-X19) -> 0 | Z20: =Z19 -> 98847 | AA20: =Z20-Z19 -> 0 | AB20: =AB19 -> 261 | AC20: =AC19 -> 731 | AD20: =AC20-AC19 -> 0 | AE20: =AE19 -> 229.81 | AF20: =AE20-AE19 -> 0 | AG20: =AG19 -> 2205.98 | AH20: =AG20-AG19 -> 0 | AI20: =AF20+AH20 -> 0 | AJ20: =+Z20-Z19 -> 0 | AK20: =SUM(Y20-L20) -> 0 | AL20: =SUM(AJ20-W20) -> 0 | AM20: ='General information '!D20 -> 0 | AN20: ='General information '!H20 -> 0 | AP20: ='General information '!J20 -> 0 | AR20: =A20 -> 44362 | AS20: =AS19 -> 0.9 | AT20: =AT19 -> 90 | AU20: =AU19 -> 1.1 | AV20: =AV19 -> 159 | AW20: 2.9 | AX20: =AX19 -> 97 | AY20: =AS20*AT20 -> 81 | AZ20: =AU20*AV20 -> 174.9 | BA20: =AW20*AX20 -> 281.3 | BB20: =AY20-AY19 -> 0 | BC20: =AZ20-AZ19 -> 0 | BD20: =BA20-BA19 -> 0 | BE20: =SUM(BB20:BD20) -> 0 | BF20: =SUM(I20-BE20) -> 0 | BG20: =SUM(I20-BF20) -> 0
A21: =ELEC!C19 -> 44363 | B21: =B20 -> 109443 | C21: =B21-B20 -> 0 | D21: =C21/27 -> 0 | E21: =SUM((C21*$E$4)+(7500/'EDl log'!$A$37)) -> 250 | G21: =G20 -> 620421 | H21: =G21-G20 -> 0 | I21: =C21+H21 -> 0 | J21: =IF(I21>0,E21/I21,0) -> 0 | K21: ='Swimming Pool quality check '!H21 -> 6775 | L21: =K21-K20 -> 0 | M21: =M20 -> 457.44 | N21: =SUM(M21-M20) -> 0 | O21: =O20 -> 529.52 | P21: =SUM(O21-O20) -> 0 | Q21: =SUM(P21+N21) -> 0 | T21: =T20 -> 5172 | U21: =SUM(T21-T20) -> 0 | V21: =V20 -> 474 | W21: =+V21-V20 -> 0 | X21: =X20 -> 152036 | Y21: =SUM(X21-X20) -> 0 | Z21: =Z20 -> 98847 | AA21: =Z21-Z20 -> 0 | AB21: =AB20 -> 261 | AC21: =AC20 -> 731 | AD21: =AC21-AC20 -> 0 | AE21: =AE20 -> 229.81 | AF21: =AE21-AE20 -> 0 | AG21: =AG20 -> 2205.98 | AH21: =AG21-AG20 -> 0 | AI21: =AF21+AH21 -> 0 | AJ21: =+Z21-Z20 -> 0 | AK21: =SUM(Y21-L21) -> 0 | AL21: =SUM(AJ21-W21) -> 0 | AM21: ='General information '!D21 -> 0 | AN21: ='General information '!H21 -> 0 | AP21: ='General information '!J21 -> 0 | AR21: =A21 -> 44363 | AS21: =AS20 -> 0.9 | AT21: =AT20 -> 90 | AU21: =AU20 -> 1.1 | AV21: =AV20 -> 159 | AW21: 2.9 | AX21: =AX20 -> 97 | AY21: =AS21*AT21 -> 81 | AZ21: =AU21*AV21 -> 174.9 | BA21: =AW21*AX21 -> 281.3 | BB21: =AY21-AY20 -> 0 | BC21: =AZ21-AZ20 -> 0 | BD21: =BA21-BA20 -> 0 | BE21: =SUM(BB21:BD21) -> 0 | BF21: =SUM(I21-BE21) -> 0 | BG21: =SUM(I21-BF21) -> 0
A22: =ELEC!C20 -> 44364 | B22: =B21 -> 109443 | C22: =B22-B21 -> 0 | D22: =C22/27 -> 0 | E22: =SUM((C22*$E$4)+(7500/'EDl log'!$A$37)) -> 250 | G22: =G21 -> 620421 | H22: =G22-G21 -> 0 | I22: =C22+H22 -> 0 | J22: =IF(I22>0,E22/I22,0) -> 0 | K22: ='Swimming Pool quality check '!H22 -> 6775 | L22: =K22-K21 -> 0 | M22: =M21 -> 457.44 | N22: =SUM(M22-M21) -> 0 | O22: =O21 -> 529.52 | P22: =SUM(O22-O21) -> 0 | Q22: =SUM(P22+N22) -> 0 | T22: =T21 -> 5172 | U22: =SUM(T22-T21) -> 0 | V22: =V21 -> 474 | W22: =+V22-V21 -> 0 | X22: =X21 -> 152036 | Y22: =SUM(X22-X21) -> 0 | Z22: =Z21 -> 98847 | AA22: =Z22-Z21 -> 0 | AB22: =AB21 -> 261 | AC22: =AC21 -> 731 | AD22: =AC22-AC21 -> 0 | AE22: =AE21 -> 229.81 | AF22: =AE22-AE21 -> 0 | AG22: =AG21 -> 2205.98 | AH22: =AG22-AG21 -> 0 | AI22: =AF22+AH22 -> 0 | AJ22: =+Z22-Z21 -> 0 | AK22: =SUM(Y22-L22) -> 0 | AL22: =SUM(AJ22-W22) -> 0 | AM22: ='General information '!D22 -> 0 | AN22: ='General information '!H22 -> 0 | AP22: ='General information '!J22 -> 0 | AR22: =A22 -> 44364 | AS22: =AS21 -> 0.9 | AT22: =AT21 -> 90 | AU22: =AU21 -> 1.1 | AV22: =AV21 -> 159 | AW22: 2.9 | AX22: =AX21 -> 97 | AY22: =AS22*AT22 -> 81 | AZ22: =AU22*AV22 -> 174.9 | BA22: =AW22*AX22 -> 281.3 | BB22: =AY22-AY21 -> 0 | BC22: =AZ22-AZ21 -> 0 | BD22: =BA22-BA21 -> 0 | BE22: =SUM(BB22:BD22) -> 0 | BF22: =SUM(I22-BE22) -> 0 | BG22: =SUM(I22-BF22) -> 0
A23: =ELEC!C21 -> 44365 | B23: =B22 -> 109443 | C23: =B23-B22 -> 0 | D23: =C23/27 -> 0 | E23: =SUM((C23*$E$4)+(7500/'EDl log'!$A$37)) -> 250 | G23: =G22 -> 620421 | H23: =G23-G22 -> 0 | I23: =C23+H23 -> 0 | J23: =IF(I23>0,E23/I23,0) -> 0 | K23: ='Swimming Pool quality check '!H23 -> 6775 | L23: =K23-K22 -> 0 | M23: =M22 -> 457.44 | N23: =SUM(M23-M22) -> 0 | O23: =O22 -> 529.52 | P23: =SUM(O23-O22) -> 0 | Q23: =SUM(P23+N23) -> 0 | T23: =T22 -> 5172 | U23: =SUM(T23-T22) -> 0 | V23: =V22 -> 474 | W23: =+V23-V22 -> 0 | X23: =X22 -> 152036 | Y23: =SUM(X23-X22) -> 0 | Z23: =Z22 -> 98847 | AA23: =Z23-Z22 -> 0 | AB23: =AB22 -> 261 | AC23: =AC22 -> 731 | AD23: =AC23-AC22 -> 0 | AE23: =AE22 -> 229.81 | AF23: =AE23-AE22 -> 0 | AG23: =AG22 -> 2205.98 | AH23: =AG23-AG22 -> 0 | AI23: =AF23+AH23 -> 0 | AJ23: =+Z23-Z22 -> 0 | AK23: =SUM(Y23-L23) -> 0 | AL23: =SUM(AJ23-W23) -> 0 | AM23: ='General information '!D23 -> 0 | AN23: ='General information '!H23 -> 0 | AP23: ='General information '!J23 -> 0 | AR23: =A23 -> 44365 | AS23: =AS22 -> 0.9 | AT23: =AT22 -> 90 | AU23: =AU22 -> 1.1 | AV23: =AV22 -> 159 | AW23: 2.9 | AX23: =AX22 -> 97 | AY23: =AS23*AT23 -> 81 | AZ23: =AU23*AV23 -> 174.9 | BA23: =AW23*AX23 -> 281.3 | BB23: =AY23-AY22 -> 0 | BC23: =AZ23-AZ22 -> 0 | BD23: =BA23-BA22 -> 0 | BE23: =SUM(BB23:BD23) -> 0 | BF23: =SUM(I23-BE23) -> 0 | BG23: =SUM(I23-BF23) -> 0
A24: =ELEC!C22 -> 44366 | B24: =B23 -> 109443 | C24: =B24-B23 -> 0 | D24: =C24/27 -> 0 | E24: =SUM((C24*$E$4)+(7500/'EDl log'!$A$37)) -> 250 | G24: =G23 -> 620421 | H24: =G24-G23 -> 0 | I24: =C24+H24 -> 0 | J24: =IF(I24>0,E24/I24,0) -> 0 | K24: ='Swimming Pool quality check '!H24 -> 6775 | L24: =K24-K23 -> 0 | M24: =M23 -> 457.44 | N24: =SUM(M24-M23) -> 0 | O24: =O23 -> 529.52 | P24: =SUM(O24-O23) -> 0 | Q24: =SUM(P24+N24) -> 0 | T24: =T23 -> 5172 | U24: =SUM(T24-T23) -> 0 | V24: =V23 -> 474 | W24: =+V24-V23 -> 0 | X24: =X23 -> 152036 | Y24: =SUM(X24-X23) -> 0 | Z24: =Z23 -> 98847 | AA24: =Z24-Z23 -> 0 | AB24: =AB23 -> 261 | AC24: =AC23 -> 731 | AD24: =AC24-AC23 -> 0 | AE24: =AE23 -> 229.81 | AF24: =AE24-AE23 -> 0 | AG24: =AG23 -> 2205.98 | AH24: =AG24-AG23 -> 0 | AI24: =AF24+AH24 -> 0 | AJ24: =+Z24-Z23 -> 0 | AK24: =SUM(Y24-L24) -> 0 | AL24: =SUM(AJ24-W24) -> 0 | AM24: ='General information '!D24 -> 0 | AN24: ='[4]General information '!H24 -> 0 | AP24: ='[4]General information '!J24 -> 0 | AR24: =A24 -> 44366 | AS24: =AS23 -> 0.9 | AT24: =AT23 -> 90 | AU24: =AU23 -> 1.1 | AV24: =AV23 -> 159 | AW24: 2.9 | AX24: =AX23 -> 97 | AY24: =AS24*AT24 -> 81 | AZ24: =AU24*AV24 -> 174.9 | BA24: =AW24*AX24 -> 281.3 | BB24: =AY24-AY23 -> 0 | BC24: =AZ24-AZ23 -> 0 | BD24: =BA24-BA23 -> 0 | BE24: =SUM(BB24:BD24) -> 0 | BF24: =SUM(I24-BE24) -> 0 | BG24: =SUM(I24-BF24) -> 0
A25: =ELEC!C23 -> 44367 | B25: =B24 -> 109443 | C25: =B25-B24 -> 0 | D25: =C25/27 -> 0 | E25: =SUM((C25*$E$4)+(7500/'EDl log'!$A$37)) -> 250 | G25: =G24 -> 620421 | H25: =G25-G24 -> 0 | I25: =C25+H25 -> 0 | J25: =IF(I25>0,E25/I25,0) -> 0 | K25: ='Swimming Pool quality check '!H25 -> 6775 | L25: =K25-K24 -> 0 | M25: =M24 -> 457.44 | N25: =SUM(M25-M24) -> 0 | O25: =O24 -> 529.52 | P25: =SUM(O25-O24) -> 0 | Q25: =SUM(P25+N25) -> 0 | T25: =T24 -> 5172 | U25: =SUM(T25-T24) -> 0 | V25: =V24 -> 474 | W25: =+V25-V24 -> 0 | X25: =X24 -> 152036 | Y25: =SUM(X25-X24) -> 0 | Z25: =Z24 -> 98847 | AA25: =Z25-Z24 -> 0 | AB25: =AB24 -> 261 | AC25: =AC24 -> 731 | AD25: =AC25-AC24 -> 0 | AE25: =AE24 -> 229.81 | AF25: =AE25-AE24 -> 0 | AG25: =AG24 -> 2205.98 | AH25: =AG25-AG24 -> 0 | AI25: =AF25+AH25 -> 0 | AJ25: =+Z25-Z24 -> 0 | AK25: =SUM(Y25-L25) -> 0 | AL25: =SUM(AJ25-W25) -> 0 | AM25: ='General information '!D25 -> 0 | AN25: ='General information '!H25 -> 0 | AP25: ='General information '!J25 -> 0 | AR25: =A25 -> 44367 | AS25: =AS24 -> 0.9 | AT25: =AT24 -> 90 | AU25: =AU24 -> 1.1 | AV25: =AV24 -> 159 | AW25: 2.9 | AX25: =AX24 -> 97 | AY25: =AS25*AT25 -> 81 | AZ25: =AU25*AV25 -> 174.9 | BA25: =AW25*AX25 -> 281.3 | BB25: =AY25-AY24 -> 0 | BC25: =AZ25-AZ24 -> 0 | BD25: =BA25-BA24 -> 0 | BE25: =SUM(BB25:BD25) -> 0 | BF25: =SUM(I25-BE25) -> 0 | BG25: =SUM(I25-BF25) -> 0
A26: =ELEC!C24 -> 44368 | B26: =B25 -> 109443 | C26: =B26-B25 -> 0 | D26: =C26/27 -> 0 | E26: =SUM((C26*$E$4)+(7500/'EDl log'!$A$37)) -> 250 | G26: =G25 -> 620421 | H26: =G26-G25 -> 0 | I26: =C26+H26 -> 0 | J26: =IF(I26>0,E26/I26,0) -> 0 | K26: ='Swimming Pool quality check '!H26 -> 6775 | L26: =K26-K25 -> 0 | M26: =M25 -> 457.44 | N26: =SUM(M26-M25) -> 0 | O26: =O25 -> 529.52 | P26: =SUM(O26-O25) -> 0 | Q26: =SUM(P26+N26) -> 0 | T26: =T25 -> 5172 | U26: =SUM(T26-T25) -> 0 | V26: =V25 -> 474 | W26: =+V26-V25 -> 0 | X26: =X25 -> 152036 | Y26: =SUM(X26-X25) -> 0 | Z26: =Z25 -> 98847 | AA26: =Z26-Z25 -> 0 | AB26: =AB25 -> 261 | AC26: =AC25 -> 731 | AD26: =AC26-AC25 -> 0 | AE26: =AE25 -> 229.81 | AF26: =AE26-AE25 -> 0 | AG26: =AG25 -> 2205.98 | AH26: =AG26-AG25 -> 0 | AI26: =AF26+AH26 -> 0 | AJ26: =+Z26-Z25 -> 0 | AK26: =SUM(Y26-L26) -> 0 | AL26: =SUM(AJ26-W26) -> 0 | AM26: ='General information '!D26 -> 0 | AN26: ='General information '!H26 -> 0 | AP26: ='General information '!J26 -> 0 | AR26: =A26 -> 44368 | AS26: =AS25 -> 0.9 | AT26: =AT25 -> 90 | AU26: =AU25 -> 1.1 | AV26: =AV25 -> 159 | AW26: 2.9 | AX26: =AX25 -> 97 | AY26: =AS26*AT26 -> 81 | AZ26: =AU26*AV26 -> 174.9 | BA26: =AW26*AX26 -> 281.3 | BB26: =AY26-AY25 -> 0 | BC26: =AZ26-AZ25 -> 0 | BD26: =BA26-BA25 -> 0 | BE26: =SUM(BB26:BD26) -> 0 | BF26: =SUM(I26-BE26) -> 0 | BG26: =SUM(I26-BF26) -> 0
A27: =ELEC!C25 -> 44369 | B27: =B26 -> 109443 | C27: =B27-B26 -> 0 | D27: =C27/27 -> 0 | E27: =SUM((C27*$E$4)+(7500/'EDl log'!$A$37)) -> 250 | G27: =G26 -> 620421 | H27: =G27-G26 -> 0 | I27: =C27+H27 -> 0 | J27: =IF(I27>0,E27/I27,0) -> 0 | K27: ='Swimming Pool quality check '!H27 -> 6775 | L27: =K27-K26 -> 0 | M27: =M26 -> 457.44 | N27: =SUM(M27-M26) -> 0 | O27: =O26 -> 529.52 | P27: =SUM(O27-O26) -> 0 | Q27: =SUM(P27+N27) -> 0 | T27: =T26 -> 5172 | U27: =SUM(T27-T26) -> 0 | V27: =V26 -> 474 | W27: =+V27-V26 -> 0 | X27: =X26 -> 152036 | Y27: =SUM(X27-X26) -> 0 | Z27: =Z26 -> 98847 | AA27: =Z27-Z26 -> 0 | AB27: =AB26 -> 261 | AC27: =AC26 -> 731 | AD27: =AC27-AC26 -> 0 | AE27: =AE26 -> 229.81 | AF27: =AE27-AE26 -> 0 | AG27: =AG26 -> 2205.98 | AH27: =AG27-AG26 -> 0 | AI27: =AF27+AH27 -> 0 | AJ27: =+Z27-Z26 -> 0 | AK27: =SUM(Y27-L27) -> 0 | AL27: =SUM(AJ27-W27) -> 0 | AM27: ='General information '!D27 -> 0 | AN27: ='General information '!H27 -> 0 | AP27: ='General information '!J27 -> 0 | AR27: =A27 -> 44369 | AS27: =AS26 -> 0.9 | AT27: =AT26 -> 90 | AU27: =AU26 -> 1.1 | AV27: =AV26 -> 159 | AW27: 2.9 | AX27: =AX26 -> 97 | AY27: =AS27*AT27 -> 81 | AZ27: =AU27*AV27 -> 174.9 | BA27: =AW27*AX27 -> 281.3 | BB27: =AY27-AY26 -> 0 | BC27: =AZ27-AZ26 -> 0 | BD27: =BA27-BA26 -> 0 | BE27: =SUM(BB27:BD27) -> 0 | BF27: =SUM(I27-BE27) -> 0 | BG27: =SUM(I27-BF27) -> 0
A28: =ELEC!C26 -> 44370 | B28: =B27 -> 109443 | C28: =B28-B27 -> 0 | D28: =C28/27 -> 0 | E28: =SUM((C28*$E$4)+(7500/'EDl log'!$A$37)) -> 250 | G28: =G27 -> 620421 | H28: =G28-G27 -> 0 | I28: =C28+H28 -> 0 | J28: =IF(I28>0,E28/I28,0) -> 0 | K28: ='Swimming Pool quality check '!H28 -> 6775 | L28: =K28-K27 -> 0 | M28: =M27 -> 457.44 | N28: =SUM(M28-M27) -> 0 | O28: =O27 -> 529.52 | P28: =SUM(O28-O27) -> 0 | Q28: =SUM(P28+N28) -> 0 | T28: =T27 -> 5172 | U28: =SUM(T28-T27) -> 0 | V28: =V27 -> 474 | W28: =+V28-V27 -> 0 | X28: =X27 -> 152036 | Y28: =SUM(X28-X27) -> 0 | Z28: =Z27 -> 98847 | AA28: =Z28-Z27 -> 0 | AB28: =AB27 -> 261 | AC28: =AC27 -> 731 | AD28: =AC28-AC27 -> 0 | AE28: =AE27 -> 229.81 | AF28: =AE28-AE27 -> 0 | AG28: =AG27 -> 2205.98 | AH28: =AG28-AG27 -> 0 | AI28: =AF28+AH28 -> 0 | AJ28: =+Z28-Z27 -> 0 | AK28: =SUM(Y28-L28) -> 0 | AL28: =SUM(AJ28-W28) -> 0 | AM28: ='General information '!D28 -> 0 | AN28: ='General information '!H28 -> 0 | AP28: ='General information '!J28 -> 0 | AR28: =A28 -> 44370 | AS28: =AS27 -> 0.9 | AT28: =AT27 -> 90 | AU28: =AU27 -> 1.1 | AV28: =AV27 -> 159 | AW28: 2.9 | AX28: =AX27 -> 97 | AY28: =AS28*AT28 -> 81 | AZ28: =AU28*AV28 -> 174.9 | BA28: =AW28*AX28 -> 281.3 | BB28: =AY28-AY27 -> 0 | BC28: =AZ28-AZ27 -> 0 | BD28: =BA28-BA27 -> 0 | BE28: =SUM(BB28:BD28) -> 0 | BF28: =SUM(I28-BE28) -> 0 | BG28: =SUM(I28-BF28) -> 0
A29: =ELEC!C27 -> 44371 | B29: =B28 -> 109443 | C29: =B29-B28 -> 0 | D29: =C29/27 -> 0 | E29: =SUM((C29*$E$4)+(7500/'EDl log'!$A$37)) -> 250 | G29: =G28 -> 620421 | H29: =G29-G28 -> 0 | I29: =C29+H29 -> 0 | J29: =IF(I29>0,E29/I29,0) -> 0 | K29: ='Swimming Pool quality check '!H29 -> 6775 | L29: =K29-K28 -> 0 | M29: =M28 -> 457.44 | N29: =SUM(M29-M28) -> 0 | O29: =O28 -> 529.52 | P29: =SUM(O29-O28) -> 0 | Q29: =SUM(P29+N29) -> 0 | T29: =T28 -> 5172 | U29: =SUM(T29-T28) -> 0 | V29: =V28 -> 474 | W29: =+V29-V28 -> 0 | X29: =X28 -> 152036 | Y29: =SUM(X29-X28) -> 0 | Z29: =Z28 -> 98847 | AA29: =Z29-Z28 -> 0 | AB29: =AB28 -> 261 | AC29: =AC28 -> 731 | AD29: =AC29-AC28 -> 0 | AE29: =AE28 -> 229.81 | AF29: =AE29-AE28 -> 0 | AG29: =AG28 -> 2205.98 | AH29: =AG29-AG28 -> 0 | AI29: =AF29+AH29 -> 0 | AJ29: =+Z29-Z28 -> 0 | AK29: =SUM(Y29-L29) -> 0 | AL29: =SUM(AJ29-W29) -> 0 | AM29: ='General information '!D29 -> 0 | AN29: ='General information '!H29 -> 0 | AP29: ='General information '!J29 -> 0 | AR29: =A29 -> 44371 | AS29: =AS28 -> 0.9 | AT29: =AT28 -> 90 | AU29: =AU28 -> 1.1 | AV29: =AV28 -> 159 | AW29: 2.9 | AX29: =AX28 -> 97 | AY29: =AS29*AT29 -> 81 | AZ29: =AU29*AV29 -> 174.9 | BA29: =AW29*AX29 -> 281.3 | BB29: =AY29-AY28 -> 0 | BC29: =AZ29-AZ28 -> 0 | BD29: =BA29-BA28 -> 0 | BE29: =SUM(BB29:BD29) -> 0 | BF29: =SUM(I29-BE29) -> 0 | BG29: =SUM(I29-BF29) -> 0
A30: =ELEC!C28 -> 44372 | B30: =B29 -> 109443 | C30: =B30-B29 -> 0 | D30: =C30/27 -> 0 | E30: =SUM((C30*$E$4)+(7500/'EDl log'!$A$37)) -> 250 | G30: =G29 -> 620421 | H30: =G30-G29 -> 0 | I30: =C30+H30 -> 0 | J30: =IF(I30>0,E30/I30,0) -> 0 | K30: ='Swimming Pool quality check '!H30 -> 6775 | L30: =K30-K29 -> 0 | M30: =M29 -> 457.44 | N30: =SUM(M30-M29) -> 0 | O30: =O29 -> 529.52 | P30: =SUM(O30-O29) -> 0 | Q30: =SUM(P30+N30) -> 0 | T30: =T29 -> 5172 | U30: =SUM(T30-T29) -> 0 | V30: =V29 -> 474 | W30: =+V30-V29 -> 0 | X30: =X29 -> 152036 | Y30: =SUM(X30-X29) -> 0 | Z30: =Z29 -> 98847 | AA30: =Z30-Z29 -> 0 | AB30: =AB29 -> 261 | AC30: =AC29 -> 731 | AD30: =AC30-AC29 -> 0 | AE30: =AE29 -> 229.81 | AF30: =AE30-AE29 -> 0 | AG30: =AG29 -> 2205.98 | AH30: =AG30-AG29 -> 0 | AI30: =AF30+AH30 -> 0 | AJ30: =+Z30-Z29 -> 0 | AK30: =SUM(Y30-L30) -> 0 | AL30: =SUM(AJ30-W30) -> 0 | AM30: ='General information '!D30 -> 0 | AN30: ='General information '!H30 -> 0 | AP30: ='General information '!J30 -> 0 | AR30: =A30 -> 44372 | AS30: =AS29 -> 0.9 | AT30: =AT29 -> 90 | AU30: =AU29 -> 1.1 | AV30: =AV29 -> 159 | AW30: 2.9 | AX30: =AX29 -> 97 | AY30: =AS30*AT30 -> 81 | AZ30: =AU30*AV30 -> 174.9 | BA30: =AW30*AX30 -> 281.3 | BB30: =AY30-AY29 -> 0 | BC30: =AZ30-AZ29 -> 0 | BD30: =BA30-BA29 -> 0 | BE30: =SUM(BB30:BD30) -> 0 | BF30: =SUM(I30-BE30) -> 0 | BG30: =SUM(I30-BF30) -> 0
A31: =ELEC!C29 -> 44373 | B31: =B30 -> 109443 | C31: =B31-B30 -> 0 | D31: =C31/27 -> 0 | E31: =SUM((C31*$E$4)+(7500/'EDl log'!$A$37)) -> 250 | G31: =G30 -> 620421 | H31: =G31-G30 -> 0 | I31: =C31+H31 -> 0 | J31: =IF(I31>0,E31/I31,0) -> 0 | K31: ='Swimming Pool quality check '!H31 -> 6775 | L31: =K31-K30 -> 0 | M31: =M30 -> 457.44 | N31: =SUM(M31-M30) -> 0 | O31: =O30 -> 529.52 | P31: =SUM(O31-O30) -> 0 | Q31: =SUM(P31+N31) -> 0 | T31: =T30 -> 5172 | U31: =SUM(T31-T30) -> 0 | V31: =V30 -> 474 | W31: =+V31-V30 -> 0 | X31: =X30 -> 152036 | Y31: =SUM(X31-X30) -> 0 | Z31: =Z30 -> 98847 | AA31: =Z31-Z30 -> 0 | AB31: =AB30 -> 261 | AC31: =AC30 -> 731 | AD31: =AC31-AC30 -> 0 | AE31: =AE30 -> 229.81 | AF31: =AE31-AE30 -> 0 | AG31: =AG30 -> 2205.98 | AH31: =AG31-AG30 -> 0 | AI31: =AF31+AH31 -> 0 | AJ31: =+Z31-Z30 -> 0 | AK31: =SUM(Y31-L31) -> 0 | AL31: =SUM(AJ31-W31) -> 0 | AM31: ='General information '!D31 -> 0 | AN31: ='General information '!H31 -> 0 | AP31: ='General information '!J31 -> 0 | AR31: =A31 -> 44373 | AS31: =AS30 -> 0.9 | AT31: =AT30 -> 90 | AU31: =AU30 -> 1.1 | AV31: =AV30 -> 159 | AW31: 2.9 | AX31: =AX30 -> 97 | AY31: =AS31*AT31 -> 81 | AZ31: =AU31*AV31 -> 174.9 | BA31: =AW31*AX31 -> 281.3 | BB31: =AY31-AY30 -> 0 | BC31: =AZ31-AZ30 -> 0 | BD31: =BA31-BA30 -> 0 | BE31: =SUM(BB31:BD31) -> 0 | BF31: =SUM(I31-BE31) -> 0 | BG31: =SUM(I31-BF31) -> 0
A32: =ELEC!C30 -> 44374 | B32: =B31 -> 109443 | C32: =B32-B31 -> 0 | D32: =C32/27 -> 0 | E32: =SUM((C32*$E$4)+(7500/'EDl log'!$A$37)) -> 250 | G32: =G31 -> 620421 | H32: =G32-G31 -> 0 | I32: =C32+H32 -> 0 | J32: =IF(I32>0,E32/I32,0) -> 0 | K32: ='Swimming Pool quality check '!H32 -> 6775 | L32: =K32-K31 -> 0 | M32: =M31 -> 457.44 | N32: =SUM(M32-M31) -> 0 | O32: =O31 -> 529.52 | P32: =SUM(O32-O31) -> 0 | Q32: =SUM(P32+N32) -> 0 | T32: =T31 -> 5172 | U32: =SUM(T32-T31) -> 0 | V32: =V31 -> 474 | W32: =+V32-V31 -> 0 | X32: =X31 -> 152036 | Y32: =SUM(X32-X31) -> 0 | Z32: =Z31 -> 98847 | AA32: =Z32-Z31 -> 0 | AB32: =AB31 -> 261 | AC32: =AC31 -> 731 | AD32: =AC32-AC31 -> 0 | AE32: =AE31 -> 229.81 | AF32: =AE32-AE31 -> 0 | AG32: =AG31 -> 2205.98 | AH32: =AG32-AG31 -> 0 | AI32: =AF32+AH32 -> 0 | AJ32: =+Z32-Z31 -> 0 | AK32: =SUM(Y32-L32) -> 0 | AL32: =SUM(AJ32-W32) -> 0 | AM32: ='General information '!D32 -> 0 | AN32: ='General information '!H32 -> 0 | AP32: ='General information '!J32 -> 0 | AR32: =A32 -> 44374 | AS32: =AS31 -> 0.9 | AT32: =AT31 -> 90 | AU32: =AU31 -> 1.1 | AV32: =AV31 -> 159 | AW32: 2.9 | AX32: =AX31 -> 97 | AY32: =AS32*AT32 -> 81 | AZ32: =AU32*AV32 -> 174.9 | BA32: =AW32*AX32 -> 281.3 | BB32: =AY32-AY31 -> 0 | BC32: =AZ32-AZ31 -> 0 | BD32: =BA32-BA31 -> 0 | BE32: =SUM(BB32:BD32) -> 0 | BF32: =SUM(I32-BE32) -> 0 | BG32: =SUM(I32-BF32) -> 0
A33: =ELEC!C31 -> 44375 | B33: =B32 -> 109443 | C33: =B33-B32 -> 0 | D33: =C33/27 -> 0 | E33: =SUM((C33*$E$4)+(7500/'EDl log'!$A$37)) -> 250 | G33: =G32 -> 620421 | H33: =G33-G32 -> 0 | I33: =C33+H33 -> 0 | J33: =IF(I33>0,E33/I33,0) -> 0 | K33: ='Swimming Pool quality check '!H33 -> 6775 | L33: =K33-K32 -> 0 | M33: =M32 -> 457.44 | N33: =SUM(M33-M32) -> 0 | O33: =O32 -> 529.52 | P33: =SUM(O33-O32) -> 0 | Q33: =SUM(P33+N33) -> 0 | T33: =T32 -> 5172 | U33: =SUM(T33-T32) -> 0 | V33: =V32 -> 474 | W33: =+V33-V32 -> 0 | X33: =X32 -> 152036 | Y33: =SUM(X33-X32) -> 0 | Z33: =Z32 -> 98847 | AA33: =Z33-Z32 -> 0 | AB33: =AB32 -> 261 | AC33: =AC32 -> 731 | AD33: =AC33-AC32 -> 0 | AE33: =AE32 -> 229.81 | AF33: =AE33-AE32 -> 0 | AG33: =AG32 -> 2205.98 | AH33: =AG33-AG32 -> 0 | AI33: =AF33+AH33 -> 0 | AJ33: =+Z33-Z32 -> 0 | AK33: =SUM(Y33-L33) -> 0 | AL33: =SUM(AJ33-W33) -> 0 | AM33: ='General information '!D33 -> 0 | AN33: ='General information '!H33 -> 0 | AP33: ='General information '!J33 -> 0 | AR33: =A33 -> 44375 | AS33: =AS32 -> 0.9 | AT33: =AT32 -> 90 | AU33: =AU32 -> 1.1 | AV33: =AV32 -> 159 | AW33: 2.9 | AX33: =AX32 -> 97 | AY33: =AS33*AT33 -> 81 | AZ33: =AU33*AV33 -> 174.9 | BA33: =AW33*AX33 -> 281.3 | BB33: =AY33-AY32 -> 0 | BC33: =AZ33-AZ32 -> 0 | BD33: =BA33-BA32 -> 0 | BE33: =SUM(BB33:BD33) -> 0 | BF33: =SUM(I33-BE33) -> 0 | BG33: =SUM(I33-BF33) -> 0
A34: =ELEC!C32 -> 44376 | B34: =B33 -> 109443 | C34: =B34-B33 -> 0 | D34: =C34/27 -> 0 | E34: =SUM((C34*$E$4)+(7500/'EDl log'!$A$37)) -> 250 | G34: =G33 -> 620421 | H34: =G34-G33 -> 0 | I34: =C34+H34 -> 0 | J34: =IF(I34>0,E34/I34,0) -> 0 | K34: ='Swimming Pool quality check '!H34 -> 6775 | L34: =K34-K33 -> 0 | M34: =M33 -> 457.44 | N34: =SUM(M34-M33) -> 0 | O34: =O33 -> 529.52 | P34: =SUM(O34-O33) -> 0 | Q34: =SUM(P34+N34) -> 0 | T34: =T33 -> 5172 | U34: =SUM(T34-T33) -> 0 | V34: =V33 -> 474 | W34: =+V34-V33 -> 0 | X34: =X33 -> 152036 | Y34: =SUM(X34-X33) -> 0 | Z34: =Z33 -> 98847 | AA34: =Z34-Z33 -> 0 | AB34: =AB33 -> 261 | AC34: =AC33 -> 731 | AD34: =AC34-AC33 -> 0 | AE34: =AE33 -> 229.81 | AF34: =AE34-AE33 -> 0 | AG34: =AG33 -> 2205.98 | AH34: =AG34-AG33 -> 0 | AI34: =AF34+AH34 -> 0 | AJ34: =+Z34-Z33 -> 0 | AK34: =SUM(Y34-L34) -> 0 | AL34: =SUM(AJ34-W34) -> 0 | AM34: ='General information '!D34 -> 0 | AN34: ='General information '!H34 -> 0 | AP34: ='General information '!J34 -> 0 | AR34: =A34 -> 44376 | AS34: =AS33 -> 0.9 | AT34: =AT33 -> 90 | AU34: =AU33 -> 1.1 | AV34: =AV33 -> 159 | AW34: 2.9 | AX34: =AX33 -> 97 | AY34: =AS34*AT34 -> 81 | AZ34: =AU34*AV34 -> 174.9 | BA34: =AW34*AX34 -> 281.3 | BB34: =AY34-AY33 -> 0 | BC34: =AZ34-AZ33 -> 0 | BD34: =BA34-BA33 -> 0 | BE34: =SUM(BB34:BD34) -> 0 | BF34: =SUM(I34-BE34) -> 0 | BG34: =SUM(I34-BF34) -> 0
A35: =ELEC!C33 -> 44377 | B35: =B34 -> 109443 | C35: =B35-B34 -> 0 | D35: =C35/27 -> 0 | E35: =SUM((C35*$E$4)+(7500/'EDl log'!$A$37)) -> 250 | G35: =G34 -> 620421 | H35: =G35-G34 -> 0 | I35: =C35+H35 -> 0 | J35: =IF(I35>0,E35/I35,0) -> 0 | K35: ='Swimming Pool quality check '!H35 -> 6775 | L35: =K35-K34 -> 0 | M35: =M34 -> 457.44 | N35: =SUM(M35-M34) -> 0 | O35: =O34 -> 529.52 | P35: =SUM(O35-O34) -> 0 | Q35: =SUM(P35+N35) -> 0 | T35: =T34 -> 5172 | U35: =SUM(T35-T34) -> 0 | V35: =V34 -> 474 | W35: =+V35-V34 -> 0 | X35: =X34 -> 152036 | Y35: =SUM(X35-X34) -> 0 | Z35: =Z34 -> 98847 | AA35: =Z35-Z34 -> 0 | AB35: =AB34 -> 261 | AC35: =AC34 -> 731 | AD35: =AC35-AC34 -> 0 | AE35: =AE34 -> 229.81 | AF35: =AE35-AE34 -> 0 | AG35: =AG34 -> 2205.98 | AH35: =AG35-AG34 -> 0 | AI35: =AF35+AH35 -> 0 | AJ35: =+Z35-Z34 -> 0 | AK35: =SUM(Y35-L35) -> 0 | AL35: =SUM(AJ35-W35) -> 0 | AM35: ='General information '!D35 -> 0 | AN35: ='General information '!H35 -> 0 | AP35: ='General information '!J35 -> 0 | AR35: =A35 -> 44377 | AS35: =AS34 -> 0.9 | AT35: =AT34 -> 90 | AU35: =AU34 -> 1.1 | AV35: =AV34 -> 159 | AW35: 2.9 | AX35: =AX34 -> 97 | AY35: =AS35*AT35 -> 81 | AZ35: =AU35*AV35 -> 174.9 | BA35: =AW35*AX35 -> 281.3 | BB35: =AY35-AY34 -> 0 | BC35: =AZ35-AZ34 -> 0 | BD35: =BA35-BA34 -> 0 | BE35: =SUM(BB35:BD35) -> 0 | BF35: =SUM(I35-BE35) -> 0 | BG35: =SUM(I35-BF35) -> 0
C36: =SUM(C6:C35) -> 0 | D36: =SUM(D6:D35) -> 0 | F36: =SUM(F6:F35) -> 0 | H36: =SUM(H6:H35) -> 0 | I36: =SUM(I6:I35) -> 0 | L36: =SUM(L7:L35) -> 0 | Q36: =SUM(Q5:Q35) -> 0 | U36: =SUM(U6:U35) -> 1 | Y36: =SUM(Y6,Y33,Y31,Y29,Y27,Y25,Y23,Y21,Y19,Y17,Y15,Y13,Y11,Y9,Y7,Y34,Y35,#REF!) -> #REF! | AJ36: =SUM(AJ6:AJ35) -> 0 | AK36: =SUM(Y36-L36) -> #REF! | AL36: =SUM(AL6:AL35) -> 0
C37: =+C36*1.66 -> 0 | E37: =SUM(E6:E33) -> 7000 | F37: =SUM(F6:F35) -> 0 | H37: 7500 | I37: =SUM('General information '!G37/WATER!I36) -> #DIV/0! | O37: =SUM(Q36+I36) -> 0 | Z37: =SUM(Y36:AJ36) -> #REF! | AK37: =SUM(Y37-L37) -> 0
B38: =9*27 -> 243 | D38: =SUM(D6:D35) -> 0 | F38: =SUM(F6:F35) -> 0 | G38: =SUM(I36) -> 0 | H38: =SUM(H37+C37) -> 7500 | K38: =SUM(H38/G38) -> #DIV/0! | AJ38: =SUM(C37-AK37) -> 0 | AM38: =SUM(AJ38/AO37) -> #DIV/0!

Sheet GEN
B1: GEN1 | C1: RUN HR | D1: Fuel Counter Index | E1: Cons /day | F1: Diesel L/H | H1: next service | I1: ALARM | J1: GEN2 | K1: RUN HR | L1: Fuel Counter Index | M1: Cons /day | N1: Diesel L/H | P1: next service | Q1: ALARM | R1: GEN3 | S1: RUN HR | T1: Fuel Counter Index | U1: Cons /day | V1: Diesel L/H | X1: next service | Y1: ALARM | Z1: RH total | AA1: Gen Con /day | AB1: Total Deisel Cons/day | AC1: H /L | AD1: TOAL KW GEN | AI1: fuel Consuption | AK1: AVG KW/h
A2: =ELEC!C3 -> 44347 | B2: =[2]GEN!B33 -> 10123 | C2: =[2]GEN!C33 -> 4 | D2: =[2]GEN!D33 -> 417630 | E2: =[2]GEN!E33 -> 367 | F2: =[2]GEN!F33 -> 91.75 | G2: =[2]GEN!G33 -> 0 | H2: =[2]GEN!H33 -> 10105 | I2: =[2]GEN!I33 -> oil change | ... AK2: =[2]GEN!AK33 -> 192.18749
A3: =ELEC!C4 -> 44348 | B3: 10129 | C3: =B3-B2 -> 6 | D3: 418031 | E3: =SUM(D3-D2) -> 401 | F3: =IF(C3>0,E3/C3,0) -> 66.833333 | G3: =[5]GEN!G32 -> 0 | H3: =H2 -> 10105 | I3: =IF(B3-H3<=0,"ok","oil change") -> oil change | J3: =J2 -> 10698 | K3: =J3-J2 -> 0 | L3: =L2 -> 357691 | M3: =SUM(L3-L2) -> 0 | N3: =IF(K3>0,M3/K3,0) -> 0 | O3: =[5]GEN!O32 -> 0 | P3: =P2 -> 10873 | Q3: =IF(J3-P3<=0,"ok","oil change") -> ok | R3: 12265 | S3: =R3-R2 -> 6 | T3: 369839 | U3: =V3*S3 -> 1500 | V3: 250 | W3: =[5]GEN!W32 -> 0 | X3: =X2 -> 12342 | Y3: =IF(R3-X3<=0,"ok","oil change") -> ok | Z3: =C3+K3+S3 -> 12 | AA3: =U3+M3+E3 -> 1901 | AB3: =V3+N3+F3 -> 316.83333 | AC3: =IF(Z3>0,AA3/Z3,0) -> 158.41667 | AD3: =ELEC!Q4 -> 9515 | AE3: =SUM(AD3/Z3) -> 792.91667 | AF3: =SUM(AE3/1600) -> 0.49557292 | AG3: =SUM(360*AF3) -> 178.40625 | AH3: =SUM(AC3-AG3) -> -19.989583 | AI3: =AD3*AJ3 -> 2449.0084 | AJ3: =305/1185 -> 0.25738397 | AK3: =AI3/Z3 -> 204.08404
A4: =ELEC!C5 -> 44349 | B4: =B3 -> 10129 | C4: =B4-B3 -> 0 | D4: =D3 -> 418031 | E4: =SUM(D4-D3) -> 0 | F4: =IF(C4>0,E4/C4,0) -> 0 | H4: =H3 -> 10105 | I4: =IF(B4-H4<=0,"ok","oil change") -> oil change | J4: =J3 -> 10698 | K4: =J4-J3 -> 0 | L4: =L3 -> 357691 | M4: =SUM(L4-L3) -> 0 | N4: =IF(K4>0,M4/K4,0) -> 0 | P4: =P3 -> 10873 | Q4: =IF(J4-P4<=0,"ok","oil change") -> ok | R4: =R3 -> 12265 | S4: =R4-R3 -> 0 | T4: =T3 -> 369839 | U4: =V4*S4 -> 0 | V4: 250 | X4: =X3 -> 12342 | Y4: =IF(R4-X4<=0,"ok","oil change") -> ok | Z4: =C4+K4+S4 -> 0 | AA4: =U4+M4+E4 -> 0 | AB4: =V4+N4+F4 -> 250 | AC4: =IF(Z4>0,AA4/Z4,0) -> 0 | AD4: =ELEC!Q5 -> 0 | AE4: =SUM(AD4/Z4) -> #DIV/0! | AF4: =SUM(AE4/1600) -> #DIV/0! | AG4: =SUM(360*AF4) -> #DIV/0! | AH4: =SUM(AC4-AG4) -> #DIV/0! | AI4: =AD4*AJ4 -> 0 | AJ4: =305/1185 -> 0.25738397 | AK4: =AI4/Z4 -> #DIV/0!
A5: =ELEC!C6 -> 44350 | B5: =B4 -> 10129 | C5: =B5-B4 -> 0 | D5: =D4 -> 418031 | E5: =SUM(D5-D4) -> 0 | F5: =IF(C5>0,E5/C5,0) -> 0 | H5: =H4 -> 10105 | I5: =IF(B5-H5<=0,"ok","oil change") -> oil change | J5: =J4 -> 10698 | K5: =J5-J4 -> 0 | L5: =L4 -> 357691 | M5: =SUM(L5-L4) -> 0 | N5: =IF(K5>0,M5/K5,0) -> 0 | P5: =P4 -> 10873 | Q5: =IF(J5-P5<=0,"ok","oil change") -> ok | R5: =R4 -> 12265 | S5: =R5-R4 -> 0 | T5: =T4 -> 369839 | U5: =V5*S5 -> 0 | V5: 250 | X5: =X4 -> 12342 | Y5: =IF(R5-X5<=0,"ok","oil change") -> ok | Z5: =C5+K5+S5 -> 0 | AA5: =U5+M5+E5 -> 0 | AB5: =V5+N5+F5 -> 250 | AC5: =IF(Z5>0,AA5/Z5,0) -> 0 | AD5: =ELEC!Q6 -> 0 | AE5: =SUM(AD5/Z5) -> #DIV/0! | AF5: =SUM(AE5/1600) -> #DIV/0! | AG5: =SUM(320*AF5) -> #DIV/0! | AH5: =SUM(AC5-AG5) -> #DIV/0! | AI5: =AD5*AJ5 -> 0 | AJ5: =305/1185 -> 0.25738397 | AK5: =AI5/Z5 -> #DIV/0!
A6: =ELEC!C7 -> 44351 | B6: =B5 -> 10129 | C6: =B6-B5 -> 0 | D6: =D5 -> 418031 | E6: =SUM(D6-D5) -> 0 | F6: =IF(C6>0,E6/C6,0) -> 0 | H6: =H5 -> 10105 | I6: =IF(B6-H6<=0,"ok","oil change") -> oil change | J6: =J5 -> 10698 | K6: =J6-J5 -> 0 | L6: =L5 -> 357691 | M6: =SUM(L6-L5) -> 0 | N6: =IF(K6>0,M6/K6,0) -> 0 | P6: =P5 -> 10873 | Q6: =IF(J6-P6<=0,"ok","oil change") -> ok | R6: =R5 -> 12265 | S6: =R6-R5 -> 0 | T6: =T5 -> 369839 | U6: =V6*S6 -> 0 | V6: 250 | X6: =X5 -> 12342 | Y6: =IF(R6-X6<=0,"ok","oil change") -> ok | Z6: =C6+K6+S6 -> 0 | AA6: =U6+M6+E6 -> 0 | AB6: =V6+N6+F6 -> 250 | AC6: =IF(Z6>0,AA6/Z6,0) -> 0 | AD6: =ELEC!Q7 -> 0 | AE6: =SUM(AD6/Z6) -> #DIV/0! | AF6: =SUM(AE6/1600) -> #DIV/0! | AG6: =SUM(320*AF6) -> #DIV/0! | AH6: =SUM(AC6-AG6) -> #DIV/0! | AI6: =AD6*AJ6 -> 0 | AJ6: =305/1185 -> 0.25738397 | AK6: =AI6/Z6 -> #DIV/0!
A7: =ELEC!C8 -> 44352 | B7: =B6 -> 10129 | C7: =B7-B6 -> 0 | D7: =D6 -> 418031 | E7: =SUM(D7-D6) -> 0 | F7: =IF(C7>0,E7/C7,0) -> 0 | H7: =H6 -> 10105 | I7: =IF(B7-H7<=0,"ok","oil change") -> oil change | J7: =J6 -> 10698 | K7: =J7-J6 -> 0 | L7: =L6 -> 357691 | M7: =SUM(L7-L6) -> 0 | N7: =IF(K7>0,M7/K7,0) -> 0 | P7: =P6 -> 10873 | Q7: =IF(J7-P7<=0,"ok","oil change") -> ok | R7: =R6 -> 12265 | S7: =R7-R6 -> 0 | T7: =T6 -> 369839 | U7: =V7*S7 -> 0 | V7: 250 | X7: =X6 -> 12342 | Y7: =IF(R7-X7<=0,"ok","oil change") -> ok | Z7: =C7+K7+S7 -> 0 | AA7: =U7+M7+E7 -> 0 | AB7: =V7+N7+F7 -> 250 | AC7: =IF(Z7>0,AA7/Z7,0) -> 0 | AD7: =ELEC!Q8 -> 0 | AE7: =SUM(AD7/Z7) -> #DIV/0! | AF7: =SUM(AE7/1600) -> #DIV/0! | AG7: =SUM(AF7/1600) -> #DIV/0! | AH7: =SUM(AC7-AG7) -> #DIV/0! | AI7: =AD7*AJ7 -> 0 | AJ7: =305/1185 -> 0.25738397 | AK7: =AI7/Z7 -> #DIV/0!
A8: =ELEC!C9 -> 44353 | B8: =B7 -> 10129 | C8: =B8-B7 -> 0 | D8: =D7 -> 418031 | E8: =SUM(D8-D7) -> 0 | F8: =IF(C8>0,E8/C8,0) -> 0 | H8: =H7 -> 10105 | I8: =IF(B8-H8<=0,"ok","oil change") -> oil change | J8: =J7 -> 10698 | K8: =J8-J7 -> 0 | L8: =L7 -> 357691 | M8: =SUM(L8-L7) -> 0 | N8: =IF(K8>0,M8/K8,0) -> 0 | P8: =P7 -> 10873 | Q8: =IF(J8-P8<=0,"ok","oil change") -> ok | R8: =R7 -> 12265 | S8: =R8-R7 -> 0 | T8: =T7 -> 369839 | U8: =V8*S8 -> 0 | V8: 250 | X8: =X7 -> 12342 | Y8: =IF(R8-X8<=0,"ok","oil change") -> ok | Z8: =C8+K8+S8 -> 0 | AA8: =U8+M8+E8 -> 0 | AB8: =V8+N8+F8 -> 250 | AC8: =IF(Z8>0,AA8/Z8,0) -> 0 | AD8: =ELEC!Q9 -> 0 | AE8: =SUM(AD8/Z8) -> #DIV/0! | AF8: =SUM(AE8/1600) -> #DIV/0! | AG8: =SUM(320*AF8) -> #DIV/0! | AH8: =SUM(AC8-AG8) -> #DIV/0! | AI8: =AD8*AJ8 -> 0 | AJ8: =305/1185 -> 0.25738397 | AK8: =AI8/Z8 -> #DIV/0!
A9: =ELEC!C10 -> 44354 | B9: =B8 -> 10129 | C9: =B9-B8 -> 0 | D9: =D8 -> 418031 | E9: =SUM(D9-D8) -> 0 | F9: =IF(C9>0,E9/C9,0) -> 0 | H9: =H8 -> 10105 | I9: =IF(B9-H9<=0,"ok","oil change") -> oil change | J9: =J8 -> 10698 | K9: =J9-J8 -> 0 | L9: =L8 -> 357691 | M9: =SUM(L9-L8) -> 0 | N9: =IF(K9>0,M9/K9,0) -> 0 | P9: =P8 -> 10873 | Q9: =IF(J9-P9<=0,"ok","oil change") -> ok | R9: =R8 -> 12265 | S9: =R9-R8 -> 0 | T9: =T8 -> 369839 | U9: =V9*S9 -> 0 | V9: 250 | X9: =X8 -> 12342 | Y9: =IF(R9-X9<=0,"ok","oil change") -> ok | Z9: =C9+K9+S9 -> 0 | AA9: =U9+M9+E9 -> 0 | AB9: =V9+N9+F9 -> 250 | AC9: =IF(Z9>0,AA9/Z9,0) -> 0 | AD9: =ELEC!Q10 -> 0 | AE9: =SUM(AD9/Z9) -> #DIV/0! | AF9: =SUM(AE9/1600) -> #DIV/0! | AG9: =SUM(320*AF9) -> #DIV/0! | AH9: =SUM(AC9-AG9) -> #DIV/0! | AI9: =AD9*AJ9 -> 0 | AJ9: =305/1185 -> 0.25738397 | AK9: =AI9/Z9 -> #DIV/0!
A10: =ELEC!C11 -> 44355 | B10: =B9 -> 10129 | C10: =B10-B9 -> 0 | D10: =D9 -> 418031 | E10: =SUM(D10-D9) -> 0 | F10: =IF(C10>0,E10/C10,0) -> 0 | H10: =H9 -> 10105 | I10: =IF(B10-H10<=0,"ok","oil change") -> oil change | J10: =J9 -> 10698 | K10: =J10-J9 -> 0 | L10: =L9 -> 357691 | M10: =SUM(L10-L9) -> 0 | N10: =IF(K10>0,M10/K10,0) -> 0 | P10: =P9 -> 10873 | Q10: =IF(J10-P10<=0,"ok","oil change") -> ok | R10: =R9 -> 12265 | S10: =R10-R9 -> 0 | T10: =T9 -> 369839 | U10: =V10*S10 -> 0 | V10: 250 | X10: =X9 -> 12342 | Y10: =IF(R10-X10<=0,"ok","oil change") -> ok | Z10: =C10+K10+S10 -> 0 | AA10: =U10+M10+E10 -> 0 | AB10: =V10+N10+F10 -> 250 | AC10: =IF(Z10>0,AA10/Z10,0) -> 0 | AD10: =ELEC!Q11 -> 0 | AE10: =SUM(AD10/Z10) -> #DIV/0! | AF10: =SUM(AE10/1600) -> #DIV/0! | AG10: =SUM(320*AF10) -> #DIV/0! | AH10: =SUM(AC10-AG10) -> #DIV/0! | AI10: =AD10*AJ10 -> 0 | AJ10: =305/1185 -> 0.25738397 | AK10: =AI10/Z10 -> #DIV/0!
A11: =ELEC!C12 -> 44356 | B11: =B10 -> 10129 | C11: =B11-B10 -> 0 | D11: =D10 -> 418031 | E11: =SUM(D11-D10) -> 0 | F11: =IF(C11>0,E11/C11,0) -> 0 | H11: =H10 -> 10105 | I11: =IF(B11-H11<=0,"ok","oil change") -> oil change | J11: =J10 -> 10698 | K11: =J11-J10 -> 0 | L11: =L10 -> 357691 | M11: =SUM(L11-L10) -> 0 | N11: =IF(K11>0,M11/K11,0) -> 0 | P11: =P10 -> 10873 | Q11: =IF(J11-P11<=0,"ok","oil change") -> ok | R11: =R10 -> 12265 | S11: =R11-R10 -> 0 | T11: =T10 -> 369839 | U11: =V11*S11 -> 0 | V11: 250 | X11: =X10 -> 12342 | Y11: =IF(R11-X11<=0,"ok","oil change") -> ok | Z11: =C11+K11+S11 -> 0 | AA11: =U11+M11+E11 -> 0 | AB11: =V11+N11+F11 -> 250 | AC11: =IF(Z11>0,AA11/Z11,0) -> 0 | AD11: =ELEC!Q12 -> 0 | AE11: =SUM(AD11/Z11) -> #DIV/0! | AF11: =SUM(AE11/1600) -> #DIV/0! | AG11: =SUM(320*AF11) -> #DIV/0! | AH11: =SUM(AC11-AG11) -> #DIV/0! | AI11: =AD11*AJ11 -> 0 | AJ11: =305/1185 -> 0.25738397 | AK11: =AI11/Z11 -> #DIV/0!
A12: =ELEC!C13 -> 44357 | B12: =B11 -> 10129 | C12: =B12-B11 -> 0 | D12: =D11 -> 418031 | E12: =SUM(D12-D11) -> 0 | F12: =IF(C12>0,E12/C12,0) -> 0 | H12: =H11 -> 10105 | I12: =IF(B12-H12<=0,"ok","oil change") -> oil change | J12: =J11 -> 10698 | K12: =J12-J11 -> 0 | L12: =L11 -> 357691 | M12: =SUM(L12-L11) -> 0 | N12: =IF(K12>0,M12/K12,0) -> 0 | P12: =P11 -> 10873 | Q12: =IF(J12-P12<=0,"ok","oil change") -> ok | R12: =R11 -> 12265 | S12: =R12-R11 -> 0 | T12: =T11 -> 369839 | U12: =V12*S12 -> 0 | V12: 250 | X12: =X11 -> 12342 | Y12: =IF(R12-X12<=0,"ok","oil change") -> ok | Z12: =C12+K12+S12 -> 0 | AA12: =U12+M12+E12 -> 0 | AB12: =V12+N12+F12 -> 250 | AC12: =IF(Z12>0,AA12/Z12,0) -> 0 | AD12: =ELEC!Q13 -> 0 | AE12: =SUM(AD12/Z12) -> #DIV/0! | AF12: =SUM(AE12/1600) -> #DIV/0! | AG12: =SUM(320*AF12) -> #DIV/0! | AH12: =SUM(AC12-AG12) -> #DIV/0! | AI12: =AD12*AJ12 -> 0 | AJ12: =305/1185 -> 0.25738397 | AK12: =AI12/Z12 -> #DIV/0!
A13: =ELEC!C14 -> 44358 | B13: =B12 -> 10129 | C13: =B13-B12 -> 0 | D13: =D12 -> 418031 | E13: =SUM(D13-D12) -> 0 | F13: =IF(C13>0,E13/C13,0) -> 0 | H13: =H12 -> 10105 | I13: =IF(B13-H13<=0,"ok","oil change") -> oil change | J13: =J12 -> 10698 | K13: =J13-J12 -> 0 | L13: =L12 -> 357691 | M13: =SUM(L13-L12) -> 0 | N13: =IF(K13>0,M13/K13,0) -> 0 | P13: =P12 -> 10873 | Q13: =IF(J13-P13<=0,"ok","oil change") -> ok | R13: =R12 -> 12265 | S13: =R13-R12 -> 0 | T13: =T12 -> 369839 | U13: =V13*S13 -> 0 | V13: 250 | X13: =X12 -> 12342 | Y13: =IF(R13-X13<=0,"ok","oil change") -> ok | Z13: =C13+K13+S13 -> 0 | AA13: =U13+M13+E13 -> 0 | AB13: =V13+N13+F13 -> 250 | AC13: =IF(Z13>0,AA13/Z13,0) -> 0 | AD13: =ELEC!Q14 -> 0 | AE13: =SUM(AD13/Z13) -> #DIV/0! | AF13: =SUM(AE13/1600) -> #DIV/0! | AG13: =SUM(320*AF13) -> #DIV/0! | AH13: =SUM(AC13-AG13) -> #DIV/0! | AI13: =AD13*AJ13 -> 0 | AJ13: =305/1185 -> 0.25738397 | AK13: =AI13/Z13 -> #DIV/0!
A14: =ELEC!C15 -> 44359 | B14: =B13 -> 10129 | C14: =B14-B13 -> 0 | D14: =D13 -> 418031 | E14: =SUM(D14-D13) -> 0 | F14: =IF(C14>0,E14/C14,0) -> 0 | H14: =H13 -> 10105 | I14: =IF(B14-H14<=0,"ok","oil change") -> oil change | J14: =J13 -> 10698 | K14: =J14-J13 -> 0 | L14: =L13 -> 357691 | M14: =SUM(L14-L13) -> 0 | N14: =IF(K14>0,M14/K14,0) -> 0 | P14: =P13 -> 10873 | Q14: =IF(J14-P14<=0,"ok","oil change") -> ok | R14: =R13 -> 12265 | S14: =R14-R13 -> 0 | T14: =T13 -> 369839 | U14: =V14*S14 -> 0 | V14: 250 | X14: =X13 -> 12342 | Y14: =IF(R14-X14<=0,"ok","oil change") -> ok | Z14: =C14+K14+S14 -> 0 | AA14: =U14+M14+E14 -> 0 | AB14: =V14+N14+F14 -> 250 | AC14: =IF(Z14>0,AA14/Z14,0) -> 0 | AD14: =ELEC!Q15 -> 0 | AE14: =SUM(AD14/Z14) -> #DIV/0! | AF14: =SUM(AE14/1600) -> #DIV/0! | AG14: =SUM(320*AF14) -> #DIV/0! | AH14: =SUM(AC14-AG14) -> #DIV/0! | AI14: =AD14*AJ14 -> 0 | AJ14: =305/1185 -> 0.25738397 | AK14: =AI14/Z14 -> #DIV/0!
A15: =ELEC!C16 -> 44360 | B15: =B14 -> 10129 | C15: =B15-B14 -> 0 | D15: =D14 -> 418031 | E15: =SUM(D15-D14) -> 0 | F15: =IF(C15>0,E15/C15,0) -> 0 | H15: =H14 -> 10105 | I15: =IF(B15-H15<=0,"ok","oil change") -> oil change | J15: =J14 -> 10698 | K15: =J15-J14 -> 0 | L15: =L14 -> 357691 | M15: =SUM(L15-L14) -> 0 | N15: =IF(K15>0,M15/K15,0) -> 0 | P15: =P14 -> 10873 | Q15: =IF(J15-P15<=0,"ok","oil change") -> ok | R15: =R14 -> 12265 | S15: =R15-R14 -> 0 | T15: =T14 -> 369839 | U15: =V15*S15 -> 0 | V15: 250 | X15: =X14 -> 12342 | Y15: =IF(R15-X15<=0,"ok","oil change") -> ok | Z15: =C15+K15+S15 -> 0 | AA15: =U15+M15+E15 -> 0 | AB15: =V15+N15+F15 -> 250 | AC15: =IF(Z15>0,AA15/Z15,0) -> 0 | AD15: =ELEC!Q16 -> 0 | AE15: =SUM(AD15/Z15) -> #DIV/0! | AF15: =SUM(AE15/1600) -> #DIV/0! | AG15: =SUM(320*AF15) -> #DIV/0! | AH15: =SUM(AC15-AG15) -> #DIV/0! | AI15: =AD15*AJ15 -> 0 | AJ15: =305/1185 -> 0.25738397 | AK15: =AI15/Z15 -> #DIV/0!
A16: =ELEC!C17 -> 44361 | B16: =B15 -> 10129 | C16: =B16-B15 -> 0 | D16: =D15 -> 418031 | E16: =SUM(D16-D15) -> 0 | F16: =IF(C16>0,E16/C16,0) -> 0 | H16: =H15 -> 10105 | I16: =IF(B16-H16<=0,"ok","oil change") -> oil change | J16: =J15 -> 10698 | K16: =J16-J15 -> 0 | L16: =L15 -> 357691 | M16: =SUM(L16-L15) -> 0 | N16: =IF(K16>0,M16/K16,0) -> 0 | P16: =P15 -> 10873 | Q16: =IF(J16-P16<=0,"ok","oil change") -> ok | R16: =R15 -> 12265 | S16: =R16-R15 -> 0 | T16: =T15 -> 369839 | U16: =V16*S16 -> 0 | V16: 250 | X16: =X15 -> 12342 | Y16: =IF(R16-X16<=0,"ok","oil change") -> ok | Z16: =C16+K16+S16 -> 0 | AA16: =U16+M16+E16 -> 0 | AB16: =V16+N16+F16 -> 250 | AC16: =IF(Z16>0,AA16/Z16,0) -> 0 | AD16: =ELEC!Q17 -> 0 | AE16: =SUM(AD16/Z16) -> #DIV/0! | AF16: =SUM(AE16/1600) -> #DIV/0! | AG16: =SUM(320*AF16) -> #DIV/0! | AH16: =SUM(AC16-AG16) -> #DIV/0! | AI16: =AD16*AJ16 -> 0 | AJ16: =305/1185 -> 0.25738397 | AK16: =AI16/Z16 -> #DIV/0!
A17: =ELEC!C18 -> 44362 | B17: =B16 -> 10129 | C17: =B17-B16 -> 0 | D17: =D16 -> 418031 | E17: =SUM(D17-D16) -> 0 | F17: =IF(C17>0,E17/C17,0) -> 0 | H17: =H16 -> 10105 | I17: =IF(B17-H17<=0,"ok","oil change") -> oil change | J17: =J16 -> 10698 | K17: =J17-J16 -> 0 | L17: =L16 -> 357691 | M17: =SUM(L17-L16) -> 0 | N17: =IF(K17>0,M17/K17,0) -> 0 | P17: =P16 -> 10873 | Q17: =IF(J17-P17<=0,"ok","oil change") -> ok | R17: =R16 -> 12265 | S17: =R17-R16 -> 0 | T17: =T16 -> 369839 | U17: =V17*S17 -> 0 | V17: 250 | X17: =X16 -> 12342 | Y17: =IF(R17-X17<=0,"ok","oil change") -> ok | Z17: =C17+K17+S17 -> 0 | AA17: =U17+M17+E17 -> 0 | AB17: =V17+N17+F17 -> 250 | AC17: =IF(Z17>0,AA17/Z17,0) -> 0 | AD17: =ELEC!Q18 -> 0 | AE17: =SUM(AD17/Z17) -> #DIV/0! | AF17: =SUM(AE17/1600) -> #DIV/0! | AG17: =SUM(320*AF17) -> #DIV/0! | AH17: =SUM(AC17-AG17) -> #DIV/0! | AI17: =AD17*AJ17 -> 0 | AJ17: =305/1185 -> 0.25738397 | AK17: =AI17/Z17 -> #DIV/0!
A18: =ELEC!C19 -> 44363 | B18: =B17 -> 10129 | C18: =B18-B17 -> 0 | D18: =D17 -> 418031 | E18: =SUM(D18-D17) -> 0 | F18: =IF(C18>0,E18/C18,0) -> 0 | H18: =H17 -> 10105 | I18: =IF(B18-H18<=0,"ok","oil change") -> oil change | J18: =J17 -> 10698 | K18: =J18-J17 -> 0 | L18: =L17 -> 357691 | M18: =SUM(L18-L17) -> 0 | N18: =IF(K18>0,M18/K18,0) -> 0 | P18: =P17 -> 10873 | Q18: =IF(J18-P14<=0,"ok","oil change") -> ok | R18: =R17 -> 12265 | S18: =R18-R17 -> 0 | T18: =T17 -> 369839 | U18: =V18*S18 -> 0 | V18: 250 | X18: =X17 -> 12342 | Y18: =IF(R18-X18<=0,"ok","oil change") -> ok | Z18: =C18+K18+S18 -> 0 | AA18: =U18+M18+E18 -> 0 | AB18: =V18+N18+F18 -> 250 | AC18: =IF(Z18>0,AA18/Z18,0) -> 0 | AD18: =ELEC!Q19 -> 0 | AE18: =SUM(AD18/Z18) -> #DIV/0! | AF18: =SUM(AE18/1600) -> #DIV/0! | AG18: =SUM(320*AF18) -> #DIV/0! | AH18: =SUM(AC18-AG18) -> #DIV/0! | AI18: =AD18*AJ18 -> 0 | AJ18: =305/1185 -> 0.25738397 | AK18: =AI18/Z18 -> #DIV/0!
A19: =ELEC!C20 -> 44364 | B19: =B18 -> 10129 | C19: =B19-B18 -> 0 | D19: =D18 -> 418031 | E19: =SUM(D19-D18) -> 0 | F19: =IF(C19>0,E19/C19,0) -> 0 | H19: =H18 -> 10105 | I19: =IF(B19-H19<=0,"ok","oil change") -> oil change | J19: =J18 -> 10698 | K19: =J19-J18 -> 0 | L19: =L18 -> 357691 | M19: =SUM(L19-L18) -> 0 | N19: =IF(K19>0,M19/K19,0) -> 0 | P19: =P18 -> 10873 | Q19: =IF(J19-P19<=0,"ok","oil change") -> ok | R19: =R18 -> 12265 | S19: =R19-R18 -> 0 | T19: =T18 -> 369839 | U19: =V19*S19 -> 0 | V19: 250 | X19: =X18 -> 12342 | Y19: =IF(R19-X19<=0,"ok","oil change") -> ok | Z19: =C19+K19+S19 -> 0 | AA19: =U19+M19+E19 -> 0 | AB19: =V19+N19+F19 -> 250 | AC19: =IF(Z19>0,AA19/Z19,0) -> 0 | AD19: =ELEC!Q20 -> 0 | AE19: =SUM(AD19/Z19) -> #DIV/0! | AF19: =SUM(AE19/1600) -> #DIV/0! | AG19: =SUM(320*AF19) -> #DIV/0! | AH19: =SUM(AC19-AG19) -> #DIV/0! | AI19: =AD19*AJ19 -> 0 | AJ19: =305/1185 -> 0.25738397 | AK19: =AI19/Z19 -> #DIV/0!
A20: =ELEC!C21 -> 44365 | B20: =B19 -> 10129 | C20: =B20-B19 -> 0 | D20: =D19 -> 418031 | E20: =SUM(D20-D19) -> 0 | F20: =IF(C20>0,E20/C20,0) -> 0 | H20: =H19 -> 10105 | I20: =IF(B20-H20<=0,"ok","oil change") -> oil change | J20: =J19 -> 10698 | K20: =J20-J19 -> 0 | L20: =L19 -> 357691 | M20: =SUM(L20-L19) -> 0 | N20: =IF(K20>0,M20/K20,0) -> 0 | P20: =P19 -> 10873 | Q20: =IF(J20-P20<=0,"ok","oil change") -> ok | R20: =R19 -> 12265 | S20: =R20-R19 -> 0 | T20: =T19 -> 369839 | U20: =V20*S20 -> 0 | V20: 250 | X20: =X19 -> 12342 | Y20: =IF(R20-X20<=0,"ok","oil change") -> ok | Z20: =C20+K20+S20 -> 0 | AA20: =U20+M20+E20 -> 0 | AB20: =V20+N20+F20 -> 250 | AC20: =IF(Z20>0,AA20/Z20,0) -> 0 | AD20: =ELEC!Q21 -> 0 | AE20: =SUM(AD20/Z20) -> #DIV/0! | AF20: =SUM(AE20/1600) -> #DIV/0! | AG20: =SUM(320*AF20) -> #DIV/0! | AH20: =SUM(AC20-AG20) -> #DIV/0! | AI20: =AD20*AJ20 -> 0 | AJ20: =305/1185 -> 0.25738397 | AK20: =AI20/Z20 -> #DIV/0!
A21: =ELEC!C22 -> 44366 | B21: =B20 -> 10129 | C21: =B21-B20 -> 0 | D21: =D20 -> 418031 | E21: =SUM(D21-D20) -> 0 | F21: =IF(C21>0,E21/C21,0) -> 0 | H21: =H20 -> 10105 | I21: =IF(B21-H21<=0,"ok","oil change") -> oil change | J21: =J20 -> 10698 | K21: =J21-J20 -> 0 | L21: =L20 -> 357691 | M21: =SUM(L21-L20) -> 0 | N21: =IF(K21>0,M21/K21,0) -> 0 | P21: =P20 -> 10873 | Q21: =IF(J21-P21<=0,"ok","oil change") -> ok | R21: =R20 -> 12265 | S21: =R21-R20 -> 0 | T21: =T20 -> 369839 | U21: =V21*S21 -> 0 | V21: 250 | X21: =X20 -> 12342 | Y21: =Y20 -> ok | Z21: =C21+K21+S21 -> 0 | AA21: =U21+M21+E21 -> 0 | AB21: =V21+N21+F21 -> 250 | AC21: =IF(Z21>0,AA21/Z21,0) -> 0 | AD21: =ELEC!Q22 -> 0 | AE21: =SUM(AD21/Z21) -> #DIV/0! | AF21: =SUM(AE21/1600) -> #DIV/0! | AG21: =SUM(320*AF21) -> #DIV/0! | AH21: =SUM(AC21-AG21) -> #DIV/0! | AI21: =AD21*AJ21 -> 0 | AJ21: =305/1185 -> 0.25738397 | AK21: =AI21/Z21 -> #DIV/0!
A22: =ELEC!C23 -> 44367 | B22: =B21 -> 10129 | C22: =B22-B21 -> 0 | D22: =D21 -> 418031 | E22: =150*C22 -> 0 | F22: =IF(C22>0,E22/C22,0) -> 0 | H22: =H21 -> 10105 | I22: =IF(B22-H22<=0,"ok","oil change") -> oil change | J22: =J21 -> 10698 | K22: =J22-J21 -> 0 | L22: =L21 -> 357691 | M22: =SUM(L22-L21) -> 0 | N22: =IF(K22>0,M22/K22,0) -> 0 | P22: =P21 -> 10873 | Q22: =IF(J22-P22<=0,"ok","oil change") -> ok | R22: =R21 -> 12265 | S22: =R22-R21 -> 0 | T22: =T21 -> 369839 | U22: =V22*S22 -> 0 | V22: 250 | X22: =X21 -> 12342 | Y22: =IF(R22-X22<=0,"ok","oil change") -> ok | Z22: =C22+K22+S22 -> 0 | AA22: =U22+M22+E22 -> 0 | AB22: =V22+N22+F22 -> 250 | AC22: =IF(Z22>0,AA22/Z22,0) -> 0 | AD22: =ELEC!Q23 -> 0 | AE22: =SUM(AD22/Z22) -> #DIV/0! | AF22: =SUM(AE22/1600) -> #DIV/0! | AG22: =SUM(320*AF22) -> #DIV/0! | AH22: =SUM(AC22-AG22) -> #DIV/0! | AI22: =AD22*AJ22 -> 0 | AJ22: =305/1185 -> 0.25738397 | AK22: =AI22/Z22 -> #DIV/0!
A23: =ELEC!C24 -> 44368 | B23: =B22 -> 10129 | C23: =B23-B22 -> 0 | D23: =D22 -> 418031 | E23: =150*C23 -> 0 | F23: =IF(C23>0,E23/C23,0) -> 0 | H23: =H22 -> 10105 | I23: =IF(B23-H23<=0,"ok","oil change") -> oil change | J23: =J22 -> 10698 | K23: =J23-J22 -> 0 | L23: =L22 -> 357691 | M23: =SUM(L23-L22) -> 0 | N23: =IF(K23>0,M23/K23,0) -> 0 | P23: =P22 -> 10873 | Q23: =IF(J23-P23<=0,"ok","oil change") -> ok | R23: =R22 -> 12265 | S23: =R23-R22 -> 0 | T23: =T22 -> 369839 | U23: =V23*S23 -> 0 | V23: 250 | X23: =X22 -> 12342 | Y23: =IF(R23-X23<=0,"ok","oil change") -> ok | Z23: =C23+K23+S23 -> 0 | AA23: =U23+M23+E23 -> 0 | AB23: =V23+N23+F23 -> 250 | AC23: =IF(Z23>0,AA23/Z23,0) -> 0 | AD23: =ELEC!Q24 -> 0 | AE23: =SUM(AD23/Z23) -> #DIV/0! | AF23: =SUM(AE23/1600) -> #DIV/0! | AG23: =SUM(320*AF23) -> #DIV/0! | AH23: =SUM(AC23-AG23) -> #DIV/0! | AI23: =AD23*AJ23 -> 0 | AJ23: =305/1185 -> 0.25738397 | AK23: =AI23/Z23 -> #DIV/0!
A24: =ELEC!C25 -> 44369 | B24: =B23 -> 10129 | C24: =B24-B23 -> 0 | D24: =D23 -> 418031 | E24: =SUM(D24-D23) -> 0 | F24: =IF(C24>0,E24/C24,0) -> 0 | H24: =H23 -> 10105 | I24: =IF(B24-H24<=0,"ok","oil change") -> oil change | J24: =J23 -> 10698 | K24: =J24-J23 -> 0 | L24: =L23 -> 357691 | M24: =SUM(L24-L23) -> 0 | N24: =IF(K24>0,M24/K24,0) -> 0 | P24: =P23 -> 10873 | Q24: =IF(J24-P24<=0,"ok","oil change") -> ok | R24: =R23 -> 12265 | S24: =R24-R23 -> 0 | T24: =T23 -> 369839 | U24: =V24*S24 -> 0 | V24: 250 | X24: =X23 -> 12342 | Y24: =IF(R24-X24<=0,"ok","oil change") -> ok | Z24: =C24+K24+S24 -> 0 | AA24: =U24+M24+E24 -> 0 | AB24: =V24+N24+F24 -> 250 | AC24: =IF(Z24>0,AA24/Z24,0) -> 0 | AD24: =ELEC!Q25 -> 0 | AE24: =SUM(AD24/Z24) -> #DIV/0! | AF24: =SUM(AE24/1600) -> #DIV/0! | AG24: =SUM(320*AF24) -> #DIV/0! | AH24: =SUM(AC24-AG24) -> #DIV/0! | AI24: =AD24*AJ24 -> 0 | AJ24: =305/1185 -> 0.25738397 | AK24: =AI24/Z24 -> #DIV/0!
A25: =ELEC!C26 -> 44370 | B25: =B24 -> 10129 | C25: =B25-B24 -> 0 | D25: =D24 -> 418031 | E25: =SUM(D25-D24) -> 0 | F25: =IF(C25>0,E25/C25,0) -> 0 | H25: =H24 -> 10105 | I25: =IF(B25-H25<=0,"ok","oil change") -> oil change | J25: =J24 -> 10698 | K25: =J25-J24 -> 0 | L25: =L24 -> 357691 | M25: =SUM(L25-L24) -> 0 | N25: =IF(K25>0,M25/K25,0) -> 0 | P25: =P24 -> 10873 | Q25: =IF(J25-P25<=0,"ok","oil change") -> ok | R25: =R24 -> 12265 | S25: =R25-R24 -> 0 | T25: =T24 -> 369839 | U25: =V25*S25 -> 0 | V25: 250 | X25: =X24 -> 12342 | Y25: =IF(R25-X25<=0,"ok","oil change") -> ok | Z25: =C25+K25+S25 -> 0 | AA25: =U25+M25+E25 -> 0 | AB25: =V25+N25+F25 -> 250 | AC25: =IF(Z25>0,AA25/Z25,0) -> 0 | AD25: =ELEC!Q26 -> 0 | AE25: =SUM(AD25/Z25) -> #DIV/0! | AF25: =SUM(AE25/1600) -> #DIV/0! | AG25: =SUM(320*AF25) -> #DIV/0! | AH25: =SUM(AC25-AG25) -> #DIV/0! | AI25: =AD25*AJ25 -> 0 | AJ25: =305/1185 -> 0.25738397 | AK25: =AI25/Z25 -> #DIV/0!
A26: =ELEC!C27 -> 44371 | B26: =B25 -> 10129 | C26: =B26-B25 -> 0 | D26: =D25 -> 418031 | E26: =SUM(D26-D25) -> 0 | F26: =IF(C26>0,E26/C26,0) -> 0 | H26: =H25 -> 10105 | I26: =IF(B26-H26<=0,"ok","oil change") -> oil change | J26: =J25 -> 10698 | K26: =J26-J25 -> 0 | L26: =L25 -> 357691 | M26: =SUM(L26-L25) -> 0 | N26: =IF(K26>0,M26/K26,0) -> 0 | P26: =P25 -> 10873 | Q26: =IF(J26-P26<=0,"ok","oil change") -> ok | R26: =R25 -> 12265 | S26: =R26-R25 -> 0 | T26: =T25 -> 369839 | U26: =V26*S26 -> 0 | V26: 250 | X26: =X25 -> 12342 | Y26: =IF(R26-X26<=0,"ok","oil change") -> ok | Z26: =C26+K26+S26 -> 0 | AA26: =U26+M26+E26 -> 0 | AB26: =V26+N26+F26 -> 250 | AC26: =IF(Z26>0,AA26/Z26,0) -> 0 | AD26: =ELEC!Q27 -> 0 | AE26: =SUM(AD26/Z26) -> #DIV/0! | AF26: =SUM(AE26/1600) -> #DIV/0! | AG26: =SUM(320*AF26) -> #DIV/0! | AH26: =SUM(AC26-AG26) -> #DIV/0! | AI26: =AD26*AJ26 -> 0 | AJ26: =305/1185 -> 0.25738397 | AK26: =AI26/Z26 -> #DIV/0!
A27: =ELEC!C28 -> 44372 | B27: =B26 -> 10129 | C27: =B27-B26 -> 0 | D27: =D26 -> 418031 | E27: =SUM(D27-D26) -> 0 | F27: =IF(C27>0,E27/C27,0) -> 0 | H27: =H26 -> 10105 | I27: =IF(B27-H27<=0,"ok","oil change") -> oil change | J27: =J26 -> 10698 | K27: =J27-J26 -> 0 | L27: =L26 -> 357691 | M27: =SUM(L27-L26) -> 0 | N27: =IF(K27>0,M27/K27,0) -> 0 | P27: =P26 -> 10873 | Q27: =IF(J27-P27<=0,"ok","oil change") -> ok | R27: =R26 -> 12265 | S27: =R27-R26 -> 0 | T27: =T26 -> 369839 | U27: =V27*S27 -> 0 | V27: 250 | X27: =X26 -> 12342 | Y27: =IF(R27-X27<=0,"ok","oil change") -> ok | Z27: =C27+K27+S27 -> 0 | AA27: =U27+M27+E27 -> 0 | AB27: =V27+N27+F27 -> 250 | AC27: =IF(Z27>0,AA27/Z27,0) -> 0 | AD27: =ELEC!Q28 -> 0 | AE27: =SUM(AD27/Z27) -> #DIV/0! | AF27: =SUM(AE27/1600) -> #DIV/0! | AG27: =SUM(320*AF27) -> #DIV/0! | AH27: =SUM(AC27-AG27) -> #DIV/0! | AI27: =AD27*AJ27 -> 0 | AJ27: =305/1185 -> 0.25738397 | AK27: =AI27/Z27 -> #DIV/0!
A28: =ELEC!C29 -> 44373 | B28: =B27 -> 10129 | C28: =B28-B27 -> 0 | D28: =D27 -> 418031 | E28: =SUM(D28-D27) -> 0 | F28: =IF(C28>0,E28/C28,0) -> 0 | H28: =H27 -> 10105 | I28: =IF(B28-H28<=0,"ok","oil change") -> oil change | J28: =J27 -> 10698 | K28: =J28-J27 -> 0 | L28: =L27 -> 357691 | M28: =SUM(L28-L27) -> 0 | N28: =IF(K28>0,M28/K28,0) -> 0 | P28: =P27 -> 10873 | Q28: =IF(J28-P28<=0,"ok","oil change") -> ok | R28: =R27 -> 12265 | S28: =R28-R27 -> 0 | T28: =T27 -> 369839 | U28: =V28*S28 -> 0 | V28: 250 | X28: =X27 -> 12342 | Y28: =IF(R28-X28<=0,"ok","oil change") -> ok | Z28: =C28+K28+S28 -> 0 | AA28: =U28+M28+E28 -> 0 | AB28: =V28+N28+F28 -> 250 | AC28: =IF(Z28>0,AA28/Z28,0) -> 0 | AD28: =ELEC!Q29 -> 0 | AE28: =SUM(AD28/Z28) -> #DIV/0! | AF28: =SUM(AE28/1600) -> #DIV/0! | AG28: =SUM(320*AF28) -> #DIV/0! | AH28: =SUM(AC28-AG28) -> #DIV/0! | AI28: =AD28*AJ28 -> 0 | AJ28: =305/1185 -> 0.25738397 | AK28: =AI28/Z28 -> #DIV/0!
A29: =ELEC!C30 -> 44374 | B29: =B28 -> 10129 | C29: =B29-B28 -> 0 | D29: =D28 -> 418031 | E29: =SUM(D29-D28) -> 0 | F29: =IF(C29>0,E29/C29,0) -> 0 | H29: =H28 -> 10105 | I29: =IF(B29-H29<=0,"ok","oil change") -> oil change | J29: =J28 -> 10698 | K29: =J29-J28 -> 0 | L29: =L28 -> 357691 | M29: =SUM(L29-L28) -> 0 | N29: =IF(K29>0,M29/K29,0) -> 0 | P29: =P28 -> 10873 | Q29: =IF(J29-P29<=0,"ok","oil change") -> ok | R29: =R28 -> 12265 | S29: =R29-R28 -> 0 | T29: =T28 -> 369839 | U29: =V29*S29 -> 0 | V29: 250 | X29: =X28 -> 12342 | Y29: =IF(R29-X29<=0,"ok","oil change") -> ok | Z29: =C29+K29+S29 -> 0 | AA29: =U29+M29+E29 -> 0 | AB29: =V29+N29+F29 -> 250 | AC29: =IF(Z29>0,AA29/Z29,0) -> 0 | AD29: =ELEC!Q30 -> 0 | AE29: =SUM(AD29/Z29) -> #DIV/0! | AF29: =SUM(AE29/1600) -> #DIV/0! | AG29: =SUM(320*AF29) -> #DIV/0! | AH29: =SUM(AC29-AG29) -> #DIV/0! | AI29: =AD29*AJ29 -> 0 | AJ29: =305/1185 -> 0.25738397 | AK29: =AI29/Z29 -> #DIV/0!
A30: =ELEC!C31 -> 44375 | B30: =B29 -> 10129 | C30: =B30-B29 -> 0 | D30: =D29 -> 418031 | E30: =SUM(D30-D29) -> 0 | F30: =IF(C30>0,E30/C30,0) -> 0 | H30: =H29 -> 10105 | I30: =IF(B30-H30<=0,"ok","oil change") -> oil change | J30: =J29 -> 10698 | K30: =J30-J29 -> 0 | L30: =L29 -> 357691 | M30: =SUM(L30-L29) -> 0 | N30: =IF(K30>0,M30/K30,0) -> 0 | P30: =P29 -> 10873 | Q30: =IF(J30-P30<=0,"ok","oil change") -> ok | R30: =R29 -> 12265 | S30: =R30-R29 -> 0 | T30: =T29 -> 369839 | U30: =V30*S30 -> 0 | V30: 250 | X30: =X29 -> 12342 | Y30: =IF(R30-X30<=0,"ok","oil change") -> ok | Z30: =C30+K30+S30 -> 0 | AA30: =U30+M30+E30 -> 0 | AB30: =V30+N30+F30 -> 250 | AC30: =IF(Z30>0,AA30/Z30,0) -> 0 | AD30: =ELEC!Q31 -> 0 | AE30: =SUM(AD30/Z30) -> #DIV/0! | AF30: =SUM(AE30/1600) -> #DIV/0! | AG30: =SUM(320*AF30) -> #DIV/0! | AH30: =SUM(AC30-AG30) -> #DIV/0! | AI30: =AD30*AJ30 -> 0 | AJ30: =305/1185 -> 0.25738397 | AK30: =AI30/Z30 -> #DIV/0!
A31: =ELEC!C32 -> 44376 | B31: =B30 -> 10129 | C31: =B31-B30 -> 0 | D31: =D30 -> 418031 | E31: =SUM(D31-D30) -> 0 | F31: =IF(C31>0,E31/C31,0) -> 0 | H31: =H30 -> 10105 | I31: =IF(B31-H31<=0,"ok","oil change") -> oil change | J31: =J30 -> 10698 | K31: =J31-J30 -> 0 | L31: =L30 -> 357691 | M31: =SUM(L31-L30) -> 0 | N31: =IF(K31>0,M31/K31,0) -> 0 | P31: =P30 -> 10873 | Q31: =IF(J31-P31<=0,"ok","oil change") -> ok | R31: =R30 -> 12265 | S31: =R31-R30 -> 0 | T31: =T30 -> 369839 | U31: =V31*S31 -> 0 | V31: 250 | X31: =X30 -> 12342 | Y31: =IF(R31-X31<=0,"ok","oil change") -> ok | Z31: =C31+K31+S31 -> 0 | AA31: =U31+M31+E31 -> 0 | AB31: =V31+N31+F31 -> 250 | AC31: =IF(Z31>0,AA31/Z31,0) -> 0 | AD31: =ELEC!Q32 -> 0 | AE31: =SUM(AD31/Z31) -> #DIV/0! | AF31: =SUM(AE31/1600) -> #DIV/0! | AG31: =SUM(320*AF31) -> #DIV/0! | AH31: =SUM(AC31-AG31) -> #DIV/0! | AI31: =AD31*AJ31 -> 0 | AJ31: =305/1185 -> 0.25738397 | AK31: =AI31/Z31 -> #DIV/0!
A32: =ELEC!C33 -> 44377 | B32: =B31 -> 10129 | C32: =B32-B31 -> 0 | D32: =D31 -> 418031 | E32: =SUM(D32-D31) -> 0 | F32: =IF(C32>0,E32/C32,0) -> 0 | H32: =H31 -> 10105 | I32: =IF(B32-H32<=0,"ok","oil change") -> oil change | J32: =J31 -> 10698 | K32: =J32-J31 -> 0 | L32: =L31 -> 357691 | M32: =SUM(L32-L31) -> 0 | N32: =IF(K32>0,M32/K32,0) -> 0 | P32: =P31 -> 10873 | Q32: =IF(J32-P32<=0,"ok","oil change") -> ok | R32: =R31 -> 12265 | S32: =R32-R31 -> 0 | T32: =T31 -> 369839 | U32: =V32*S32 -> 0 | V32: 250 | X32: =X31 -> 12342 | Y32: =IF(R32-X32<=0,"ok","oil change") -> ok | Z32: =C32+K32+S32 -> 0 | AA32: =U32+M32+E32 -> 0 | AB32: =V32+N32+F32 -> 250 | AC32: =IF(Z32>0,AA32/Z32,0) -> 0 | AD32: =ELEC!Q33 -> 0 | AE32: =SUM(AD32/Z32) -> #DIV/0! | AF32: =SUM(AE32/1600) -> #DIV/0! | AG32: =SUM(320*AF32) -> #DIV/0! | AH32: =SUM(AC32-AG32) -> #DIV/0! | AI32: =AD32*AJ32 -> 0 | AJ32: =305/1185 -> 0.25738397 | AK32: =AI32/Z32 -> #DIV/0!
P33: =+O33/3 -> 0 | U33: =SUM(C34:S34) -> 12 | X33: 341 | Z33: =SUM(Z3:Z32) -> 12
C34: =SUM(C3:C32) -> 6 | K34: =SUM(K3:K32) -> 0 | S34: =SUM(S3:S32) -> 6

Sheet tanks
B2: Tank 1 | D2: Tank 2 | F2: Tank 3 | H2: Tank 4 | J2: Tank 5 | L2: Tank 6 | N2: Tank 7 | P2: Tank 8 | R2: Tank 9 | T2: Tank 10 | V2: Tank 11 | Z2: Tank 1 | AB2: Tank 2 | AD2: Tank 3 | AF2: Tank 4 | AH2: Tank 5 | AJ2: Tank 6 | AL2: Tank 7
B3: 6670 | D3: =SUM(B3) -> 6670 | F3: =SUM(D3) -> 6670 | H3: =SUM(F3) -> 6670 | J3: =SUM(H3) -> 6670 | L3: =SUM(J3) -> 6670 | N3: =SUM(L3) -> 6670 | P3: =SUM(N3) -> 6670 | R3: =SUM(P3) -> 6670 | T3: =SUM(R3) -> 6670 | V3: =SUM(T3) -> 6670 | W3: =SUM(B3:V3) -> 73370 | Z3: 2800 | AB3: 2800 | AD3: 2800 | AF3: 2800 | AH3: 2800 | AJ3: 2800 | AL3: 2800 | AM3: =SUM(Z3:AL3) -> 19600 | AO3: =SUM(AM3+W3) -> 92970 | AR3: Total sotck | AS3: Diesel Cons Per day | AT3: Diesel Delivery | BE3: Genset Co | BF3: Steam | BG3: Boil | BH3: Outdoor temperature
B4: =B3/310 -> 21.516129 | D4: =SUM(B4) -> 21.516129 | F4: =SUM(D4) -> 21.516129 | H4: =SUM(F4) -> 21.516129 | J4: =SUM(H4) -> 21.516129 | L4: =SUM(J4) -> 21.516129 | N4: =SUM(L4) -> 21.516129 | P4: =SUM(N4) -> 21.516129 | R4: =SUM(P4) -> 21.516129 | T4: =SUM(R4) -> 21.516129 | V4: =SUM(T4) -> 21.516129 | Z4: =Z3/280 -> 10 | AA4: =AA3/280 -> 0 | AB4: =AB3/280 -> 10 | AC4: =AC3/280 -> 0 | AD4: =AD3/280 -> 10 | AE4: =AE3/280 -> 0 | AF4: =AF3/280 -> 10 | AG4: =AG3/280 -> 0 | ... AL4: =AL3/280 -> 10 | AT4: Delivery | AU4: Cost /L | AW4: Boiler+Steam | AX4: Generator | AZ4: Occupancy | BA4: AVE TEPM | BB4: AVE Humidity
A5: =ELEC!C3 -> 44347 | B5: =[2]tanks!B36 -> 207 | C5: =[2]tanks!C36 -> 4453.8387 | D5: =[2]tanks!D36 -> 207 | E5: =[2]tanks!E36 -> 4453.8387 | F5: =[2]tanks!F36 -> 207 | G5: =[2]tanks!G36 -> 4453.8387 | H5: =[2]tanks!H36 -> 207 | I5: =[2]tanks!I36 -> 4453.8387 | ... AO5: =[2]tanks!AO36 -> 14980 | AQ5: =[2]tanks!AQ36 -> 0.68809536 | AR5: =[2]tanks!AR36 -> 63972.226 | AS5: =[2]tanks!AS36 -> -4016.3871 | AT5: =[2]tanks!AT36 -> 12060 | AU5: =[2]tanks!AU36 -> 1.003 | AV5: =[2]tanks!AV36 -> 1.003 | AW5: =[2]tanks!AW36 -> -306 | AX5: =[2]tanks!AX36 -> -3710.3871 | ... BH5: =[2]tanks!BH36 -> 0
A6: =ELEC!C4 -> 44348 | B6: =B5 -> 207 | C6: =B6*$B$4 -> 4453.8387 | D6: =SUM(B6) -> 207 | E6: =D6*$B$4 -> 4453.8387 | F6: =SUM(D6) -> 207 | G6: =F6*$B$4 -> 4453.8387 | H6: =SUM(F6) -> 207 | I6: =H6*$B$4 -> 4453.8387 | J6: =SUM(H6) -> 207 | K6: =J6*$B$4 -> 4453.8387 | L6: =SUM(J6) -> 207 | M6: =L6*$B$4 -> 4453.8387 | N6: =SUM(L6) -> 207 | O6: =N6*$B$4 -> 4453.8387 | P6: =SUM(N6) -> 207 | Q6: =P6*$B$4 -> 4453.8387 | R6: =SUM(P6) -> 207 | S6: =R6*$B$4 -> 4453.8387 | T6: =SUM(R6) -> 207 | U6: =T6*$B$4 -> 4453.8387 | V6: =SUM(T6) -> 207 | W6: =V6*$B$4 -> 4453.8387 | X6: =SUM(Y6/73370) -> 0.66774194 | Y6: =SUM(C6+E6+G6+I6+K6+M6+O6+Q6+S6+U6+W6) -> 48992.226 | Z6: ='B5'!C5 -> 204 | AA6: =SUM(Z6*$Z$4) -> 2040 | AB6: =SUM(Z6) -> 204 | AC6: =SUM(AB6*$Z$4) -> 2040 | AD6: =SUM(AB6) -> 204 | AE6: =SUM(AD6*$Z$4) -> 2040 | AF6: =SUM(AD6) -> 204 | AG6: =SUM(AF6*$Z$4) -> 2040 | AH6: =SUM(AF6) -> 204 | AI6: =SUM(AH6*$Z$4) -> 2040 | AJ6: =SUM(AH6) -> 204 | AK6: =SUM(AJ6*$Z$4) -> 2040 | AL6: =SUM(AJ6) -> 204 | AM6: =SUM(AL6*$Z$4) -> 2040 | AN6: =SUM(AO6/19600) -> 0.72857143 | AO6: =SUM(AA6+AC6+AE6+AG6+AI6+AK6+AM6) -> 14280 | AQ6: =SUM(AR6/92970) -> 0.68056605 | AR6: =Y6+AO6 -> 63272.226 | AS6: =SUM(AR6-AR5-AT6) -> -700 | AV6: =IF(AT6>0,AU6,AV5) -> 1.003 | AW6: =-SUM('B5'!AI5) -> 0 | AX6: =-SUM(AW6-AS6) -> -700 | AY6: =SUM(AX6+AW6) -> -700 | AZ6: =ELEC!A4 -> 0 | BA6: ='General information '!D6 -> 24 | BB6: =SUM('General information '!E6) -> 0.46 | BC6: =IF(AR3>=AR6,0,1) -> 0 | BD6: 19222 | BE6: =(305/1185)*ELEC!Q5 -> 0 | BG6: =#REF!-BE6 -> #REF! | BH6: 21 | BI6: 12 | BJ6: =AX6/BI6 -> -58.333333 | BK6: =GEN!AF3 -> 0.49557292
A7: =ELEC!C5 -> 44349 | B7: ='B5'!B6 -> 191 | C7: =B7*$B$4 -> 4109.5806 | D7: =SUM(B7) -> 191 | E7: =D7*$B$4 -> 4109.5806 | F7: =SUM(D7) -> 191 | G7: =F7*$B$4 -> 4109.5806 | H7: =SUM(F7) -> 191 | I7: =H7*$B$4 -> 4109.5806 | J7: =SUM(H7) -> 191 | K7: =J7*$B$4 -> 4109.5806 | L7: =SUM(J7) -> 191 | M7: =L7*$B$4 -> 4109.5806 | N7: =SUM(L7) -> 191 | O7: =N7*$B$4 -> 4109.5806 | P7: =SUM(N7) -> 191 | Q7: =P7*$B$4 -> 4109.5806 | R7: =SUM(P7) -> 191 | S7: =R7*$B$4 -> 4109.5806 | T7: =SUM(R7) -> 191 | U7: =T7*$B$4 -> 4109.5806 | V7: =SUM(T7) -> 191 | W7: =V7*$B$4 -> 4109.5806 | X7: =SUM(Y7/73370) -> 0.61612903 | Y7: =SUM(C7+E7+G7+I7+K7+M7+O7+Q7+S7+U7+W7) -> 45205.387 | Z7: ='B5'!C6 -> 204 | AA7: =SUM(Z7*$Z$4) -> 2040 | AB7: =SUM(Z7) -> 204 | AC7: =SUM(AB7*$Z$4) -> 2040 | AD7: =SUM(AB7) -> 204 | AE7: =SUM(AD7*$Z$4) -> 2040 | AF7: =SUM(AD7) -> 204 | AG7: =SUM(AF7*$Z$4) -> 2040 | AH7: =SUM(AF7) -> 204 | AI7: =SUM(AH7*$Z$4) -> 2040 | AJ7: =SUM(AH7) -> 204 | AK7: =SUM(AJ7*$Z$4) -> 2040 | AL7: =SUM(AJ7) -> 204 | AM7: =SUM(AL7*$Z$4) -> 2040 | AN7: =SUM(AO7/19600) -> 0.72857143 | AO7: =SUM(AA7+AC7+AE7+AG7+AI7+AK7+AM7) -> 14280 | AQ7: =SUM(AR7/92970) -> 0.63983422 | AR7: =Y7+AO7 -> 59485.387 | AS7: =SUM(AR7-AR6-AT7) -> -3786.8387 | AV7: =IF(AT7>0,AU7,AV6) -> 1.003 | AW7: =-SUM('B5'!AI6) -> 0 | AX7: =-SUM(AW7-AS7) -> -3786.8387 | AY7: =SUM(AX7+AW7) -> -3786.8387 | AZ7: =ELEC!A5 -> 0 | BA7: ='General information '!D7 -> 0 | BB7: =SUM('General information '!E7) -> 0 | BC7: 0 | BD7: 19222 | BE7: =(305/1185)*ELEC!Q6 -> 0 | BG7: =#REF!-BE7 -> #REF! | BH7: 19 | BI7: 15 | BJ7: =AX7/BI7 -> -252.45591 | BK7: =GEN!AF4 -> #DIV/0!
A8: =ELEC!C6 -> 44350 | B8: ='B5'!B7 -> 191 | C8: =B8*$B$4 -> 4109.5806 | D8: =SUM(B8) -> 191 | E8: =D8*$B$4 -> 4109.5806 | F8: =SUM(D8) -> 191 | G8: =F8*$B$4 -> 4109.5806 | H8: =SUM(F8) -> 191 | I8: =H8*$B$4 -> 4109.5806 | J8: =SUM(H8) -> 191 | K8: =J8*$B$4 -> 4109.5806 | L8: =SUM(J8) -> 191 | M8: =L8*$B$4 -> 4109.5806 | N8: =SUM(L8) -> 191 | O8: =N8*$B$4 -> 4109.5806 | P8: =SUM(N8) -> 191 | Q8: =P8*$B$4 -> 4109.5806 | R8: =SUM(P8) -> 191 | S8: =R8*$B$4 -> 4109.5806 | T8: =SUM(R8) -> 191 | U8: =T8*$B$4 -> 4109.5806 | V8: =SUM(T8) -> 191 | W8: =V8*$B$4 -> 4109.5806 | X8: =SUM(Y8/73370) -> 0.61612903 | Y8: =SUM(C8+E8+G8+I8+K8+M8+O8+Q8+S8+U8+W8) -> 45205.387 | Z8: ='B5'!C7 -> 204 | AA8: =SUM(Z8*$Z$4) -> 2040 | AB8: =SUM(Z8) -> 204 | AC8: =SUM(AB8*$Z$4) -> 2040 | AD8: =SUM(AB8) -> 204 | AE8: =SUM(AD8*$Z$4) -> 2040 | AF8: =SUM(AD8) -> 204 | AG8: =SUM(AF8*$Z$4) -> 2040 | AH8: =SUM(AF8) -> 204 | AI8: =SUM(AH8*$Z$4) -> 2040 | AJ8: =SUM(AH8) -> 204 | AK8: =SUM(AJ8*$Z$4) -> 2040 | AL8: =SUM(AJ8) -> 204 | AM8: =SUM(AL8*$Z$4) -> 2040 | AN8: =SUM(AO8/19600) -> 0.72857143 | AO8: =SUM(AA8+AC8+AE8+AG8+AI8+AK8+AM8) -> 14280 | AQ8: =SUM(AR8/92970) -> 0.63983422 | AR8: =Y8+AO8 -> 59485.387 | AS8: =SUM(AR8-AR7-AT8) -> 0 | AV8: =IF(AT8>0,AU8,AV7) -> 1.003 | AW8: =-SUM('B5'!AI7) -> 0 | AX8: =-SUM(AW8-AS8) -> 0 | AY8: =SUM(AX8+AW8) -> 0 | AZ8: =ELEC!A6 -> 0 | BA8: ='General information '!D8 -> 0 | BB8: =SUM('General information '!E8) -> 0 | BC8: =IF(AR7>=AR8,0,1) -> 0 | BD8: 19222 | BE8: =(305/1185)*ELEC!Q7 -> 0 | BG8: =#REF!-BE8 -> #REF! | BH8: 16 | BI8: 9 | BJ8: =AX8/BI8 -> 0 | BK8: =GEN!AF5 -> #DIV/0!
A9: =ELEC!C7 -> 44351 | B9: ='B5'!B8 -> 191 | C9: =B9*$B$4 -> 4109.5806 | D9: =SUM(B9) -> 191 | E9: =D9*$B$4 -> 4109.5806 | F9: =SUM(D9) -> 191 | G9: =F9*$B$4 -> 4109.5806 | H9: =SUM(F9) -> 191 | I9: =H9*$B$4 -> 4109.5806 | J9: =SUM(H9) -> 191 | K9: =J9*$B$4 -> 4109.5806 | L9: =SUM(J9) -> 191 | M9: =L9*$B$4 -> 4109.5806 | N9: =SUM(L9) -> 191 | O9: =N9*$B$4 -> 4109.5806 | P9: =SUM(N9) -> 191 | Q9: =P9*$B$4 -> 4109.5806 | R9: =SUM(P9) -> 191 | S9: =R9*$B$4 -> 4109.5806 | T9: =SUM(R9) -> 191 | U9: =T9*$B$4 -> 4109.5806 | V9: =SUM(T9) -> 191 | W9: =V9*$B$4 -> 4109.5806 | X9: =SUM(Y9/73370) -> 0.61612903 | Y9: =SUM(C9+E9+G9+I9+K9+M9+O9+Q9+S9+U9+W9) -> 45205.387 | Z9: ='B5'!C8 -> 204 | AA9: =SUM(Z9*$Z$4) -> 2040 | AB9: =SUM(Z9) -> 204 | AC9: =SUM(AB9*$Z$4) -> 2040 | AD9: =SUM(AB9) -> 204 | AE9: =SUM(AD9*$Z$4) -> 2040 | AF9: =SUM(AD9) -> 204 | AG9: =SUM(AF9*$Z$4) -> 2040 | AH9: =SUM(AF9) -> 204 | AI9: =SUM(AH9*$Z$4) -> 2040 | AJ9: =SUM(AH9) -> 204 | AK9: =SUM(AJ9*$Z$4) -> 2040 | AL9: =SUM(AJ9) -> 204 | AM9: =SUM(AL9*$Z$4) -> 2040 | AN9: =SUM(AO9/19600) -> 0.72857143 | AO9: =SUM(AA9+AC9+AE9+AG9+AI9+AK9+AM9) -> 14280 | AQ9: =SUM(AR9/92970) -> 0.63983422 | AR9: =Y9+AO9 -> 59485.387 | AS9: =SUM(AR9-AR8-AT9) -> 0 | AV9: =IF(AT9>0,AU9,AV8) -> 1.003 | AW9: =-SUM('B5'!AI8) -> 0 | AX9: =-SUM(AW9-AS9) -> 0 | AY9: =SUM(AX9+AW9) -> 0 | AZ9: =ELEC!A7 -> 0 | BA9: ='General information '!D9 -> 0 | BB9: =SUM('General information '!E9) -> 0 | BC9: =IF(AR8>=AR9,0,1) -> 0 | BD9: 19222 | BE9: =(305/1185)*ELEC!Q8 -> 0 | BG9: =#REF!-BE9 -> #REF! | BH9: 18 | BI9: 6 | BJ9: =AX9/BI9 -> 0 | BK9: =GEN!AF6 -> #DIV/0!
A10: =ELEC!C8 -> 44352 | B10: ='B5'!B9 -> 191 | C10: =B10*$B$4 -> 4109.5806 | D10: =SUM(B10) -> 191 | E10: =D10*$B$4 -> 4109.5806 | F10: =SUM(D10) -> 191 | G10: =F10*$B$4 -> 4109.5806 | H10: =SUM(F10) -> 191 | I10: =H10*$B$4 -> 4109.5806 | J10: =SUM(H10) -> 191 | K10: =J10*$B$4 -> 4109.5806 | L10: =SUM(J10) -> 191 | M10: =L10*$B$4 -> 4109.5806 | N10: =SUM(L10) -> 191 | O10: =N10*$B$4 -> 4109.5806 | P10: =SUM(N10) -> 191 | Q10: =P10*$B$4 -> 4109.5806 | R10: =SUM(P10) -> 191 | S10: =R10*$B$4 -> 4109.5806 | T10: =SUM(R10) -> 191 | U10: =T10*$B$4 -> 4109.5806 | V10: =SUM(T10) -> 191 | W10: =V10*$B$4 -> 4109.5806 | X10: =SUM(Y10/73370) -> 0.61612903 | Y10: =SUM(C10+E10+G10+I10+K10+M10+O10+Q10+S10+U10+W10) -> 45205.387 | Z10: ='B5'!C9 -> 204 | AA10: =SUM(Z10*$Z$4) -> 2040 | AB10: =SUM(Z10) -> 204 | AC10: =SUM(AB10*$Z$4) -> 2040 | AD10: =SUM(AB10) -> 204 | AE10: =SUM(AD10*$Z$4) -> 2040 | AF10: =SUM(AD10) -> 204 | AG10: =SUM(AF10*$Z$4) -> 2040 | AH10: =SUM(AF10) -> 204 | AI10: =SUM(AH10*$Z$4) -> 2040 | AJ10: =SUM(AH10) -> 204 | AK10: =SUM(AJ10*$Z$4) -> 2040 | AL10: =SUM(AJ10) -> 204 | AM10: =SUM(AL10*$Z$4) -> 2040 | AN10: =SUM(AO10/19600) -> 0.72857143 | AO10: =SUM(AA10+AC10+AE10+AG10+AI10+AK10+AM10) -> 14280 | AQ10: =SUM(AR10/92970) -> 0.63983422 | AR10: =Y10+AO10 -> 59485.387 | AS10: =SUM(AR10-AR9-AT10) -> 0 | AV10: =IF(AT10>0,AU10,AV9) -> 1.003 | AW10: =-SUM('B5'!AI9) -> 0 | AX10: =-SUM(AW10-AS10) -> 0 | AY10: =SUM(AX10+AW10) -> 0 | AZ10: =ELEC!A8 -> 0 | BA10: ='General information '!D10 -> 0 | BB10: =SUM('General information '!E10) -> 0 | BC10: =IF(AR9>=AR10,0,1) -> 0 | BD10: 19222 | BE10: =(305/1185)*ELEC!Q9 -> 0 | BG10: =#REF!-BE10 -> #REF! | BH10: 16 | BI10: 7 | BJ10: =AX10/BI10 -> 0 | BK10: =GEN!AF7 -> #DIV/0!
A11: =ELEC!C9 -> 44353 | B11: ='B5'!B10 -> 191 | C11: =B11*$B$4 -> 4109.5806 | D11: =SUM(B11) -> 191 | E11: =D11*$B$4 -> 4109.5806 | F11: =SUM(D11) -> 191 | G11: =F11*$B$4 -> 4109.5806 | H11: =SUM(F11) -> 191 | I11: =H11*$B$4 -> 4109.5806 | J11: =SUM(H11) -> 191 | K11: =J11*$B$4 -> 4109.5806 | L11: =SUM(J11) -> 191 | M11: =L11*$B$4 -> 4109.5806 | N11: =SUM(L11) -> 191 | O11: =N11*$B$4 -> 4109.5806 | P11: =SUM(N11) -> 191 | Q11: =P11*$B$4 -> 4109.5806 | R11: =SUM(P11) -> 191 | S11: =R11*$B$4 -> 4109.5806 | T11: =SUM(R11) -> 191 | U11: =T11*$B$4 -> 4109.5806 | V11: =SUM(T11) -> 191 | W11: =V11*$B$4 -> 4109.5806 | X11: =SUM(Y11/73370) -> 0.61612903 | Y11: =SUM(C11+E11+G11+I11+K11+M11+O11+Q11+S11+U11+W11) -> 45205.387 | Z11: ='B5'!C10 -> 204 | AA11: =SUM(Z11*$Z$4) -> 2040 | AB11: =SUM(Z11) -> 204 | AC11: =SUM(AB11*$Z$4) -> 2040 | AD11: =SUM(AB11) -> 204 | AE11: =SUM(AD11*$Z$4) -> 2040 | AF11: =SUM(AD11) -> 204 | AG11: =SUM(AF11*$Z$4) -> 2040 | AH11: =SUM(AF11) -> 204 | AI11: =SUM(AH11*$Z$4) -> 2040 | AJ11: =SUM(AH11) -> 204 | AK11: =SUM(AJ11*$Z$4) -> 2040 | AL11: =SUM(AJ11) -> 204 | AM11: =SUM(AL11*$Z$4) -> 2040 | AN11: =SUM(AO11/19600) -> 0.72857143 | AO11: =SUM(AA11+AC11+AE11+AG11+AI11+AK11+AM11) -> 14280 | AQ11: =SUM(AR11/92970) -> 0.63983422 | AR11: =Y11+AO11 -> 59485.387 | AS11: =SUM(AR11-AR10-AT11) -> 0 | AV11: =IF(AT11>0,AU11,AV10) -> 1.003 | AW11: =-SUM('B5'!AI10) -> 0 | AX11: =-SUM(AW11-AS11) -> 0 | AY11: =SUM(AX11+AW11) -> 0 | AZ11: =ELEC!A9 -> 0 | BA11: ='General information '!D11 -> 0 | BB11: =SUM('General information '!E11) -> 0 | BC11: =IF(AR10>=AR11,0,1) -> 0 | BD11: 19222 | BE11: =(305/1185)*ELEC!Q10 -> 0 | BG11: =#REF!-BE11 -> #REF! | BH11: 16.5 | BI11: 9.3 | BJ11: =AX11/BI11 -> 0 | BK11: =GEN!AF8 -> #DIV/0!
A12: =ELEC!C10 -> 44354 | B12: ='B5'!B11 -> 191 | C12: =B12*$B$4 -> 4109.5806 | D12: =SUM(B12) -> 191 | E12: =D12*$B$4 -> 4109.5806 | F12: =SUM(D12) -> 191 | G12: =F12*$B$4 -> 4109.5806 | H12: =SUM(F12) -> 191 | I12: =H12*$B$4 -> 4109.5806 | J12: =SUM(H12) -> 191 | K12: =J12*$B$4 -> 4109.5806 | L12: =SUM(J12) -> 191 | M12: =L12*$B$4 -> 4109.5806 | N12: =SUM(L12) -> 191 | O12: =N12*$B$4 -> 4109.5806 | P12: =SUM(N12) -> 191 | Q12: =P12*$B$4 -> 4109.5806 | R12: =SUM(P12) -> 191 | S12: =R12*$B$4 -> 4109.5806 | T12: =SUM(R12) -> 191 | U12: =T12*$B$4 -> 4109.5806 | V12: =SUM(T12) -> 191 | W12: =V12*$B$4 -> 4109.5806 | X12: =SUM(Y12/73370) -> 0.61612903 | Y12: =SUM(C12+E12+G12+I12+K12+M12+O12+Q12+S12+U12+W12) -> 45205.387 | Z12: ='B5'!C11 -> 204 | AA12: =SUM(Z12*$Z$4) -> 2040 | AB12: =SUM(Z12) -> 204 | AC12: =SUM(AB12*$Z$4) -> 2040 | AD12: =SUM(AB12) -> 204 | AE12: =SUM(AD12*$Z$4) -> 2040 | AF12: =SUM(AD12) -> 204 | AG12: =SUM(AF12*$Z$4) -> 2040 | AH12: =SUM(AF12) -> 204 | AI12: =SUM(AH12*$Z$4) -> 2040 | AJ12: =SUM(AH12) -> 204 | AK12: =SUM(AJ12*$Z$4) -> 2040 | AL12: =SUM(AJ12) -> 204 | AM12: =SUM(AL12*$Z$4) -> 2040 | AN12: =SUM(AO12/19600) -> 0.72857143 | AO12: =SUM(AA12+AC12+AE12+AG12+AI12+AK12+AM12) -> 14280 | AQ12: =SUM(AR12/92970) -> 0.63983422 | AR12: =Y12+AO12 -> 59485.387 | AS12: =SUM(AR12-AR11-AT12) -> 0 | AV12: =IF(AT12>0,AU12,AV11) -> 1.003 | AW12: =-SUM('B5'!AI11) -> 0 | AX12: =-SUM(AW12-AS12) -> 0 | AY12: =SUM(AX12+AW12) -> 0 | AZ12: =ELEC!A10 -> 0 | BA12: ='General information '!D12 -> 0 | BB12: =SUM('General information '!E12) -> 0 | BC12: =IF(AR11>=AR12,0,1) -> 0 | BD12: 19222 | BE12: =(305/1185)*ELEC!Q11 -> 0 | BG12: =#REF!-BE12 -> #REF! | BH12: 15.5 | BI12: 3.7 | BJ12: =AX12/BI12 -> 0 | BK12: =GEN!AF9 -> #DIV/0!
A13: =ELEC!C11 -> 44355 | B13: ='B5'!B12 -> 191 | C13: =B13*$B$4 -> 4109.5806 | D13: =SUM(B13) -> 191 | E13: =D13*$B$4 -> 4109.5806 | F13: =SUM(D13) -> 191 | G13: =F13*$B$4 -> 4109.5806 | H13: =SUM(F13) -> 191 | I13: =H13*$B$4 -> 4109.5806 | J13: =SUM(H13) -> 191 | K13: =J13*$B$4 -> 4109.5806 | L13: =SUM(J13) -> 191 | M13: =L13*$B$4 -> 4109.5806 | N13: =SUM(L13) -> 191 | O13: =N13*$B$4 -> 4109.5806 | P13: =SUM(N13) -> 191 | Q13: =P13*$B$4 -> 4109.5806 | R13: =SUM(P13) -> 191 | S13: =R13*$B$4 -> 4109.5806 | T13: =SUM(R13) -> 191 | U13: =T13*$B$4 -> 4109.5806 | V13: =SUM(T13) -> 191 | W13: =V13*$B$4 -> 4109.5806 | X13: =SUM(Y13/73370) -> 0.61612903 | Y13: =SUM(C13+E13+G13+I13+K13+M13+O13+Q13+S13+U13+W13) -> 45205.387 | Z13: ='B5'!C12 -> 204 | AA13: =SUM(Z13*$Z$4) -> 2040 | AB13: =SUM(Z13) -> 204 | AC13: =SUM(AB13*$Z$4) -> 2040 | AD13: =SUM(AB13) -> 204 | AE13: =SUM(AD13*$Z$4) -> 2040 | AF13: =SUM(AD13) -> 204 | AG13: =SUM(AF13*$Z$4) -> 2040 | AH13: =SUM(AF13) -> 204 | AI13: =SUM(AH13*$Z$4) -> 2040 | AJ13: =SUM(AH13) -> 204 | AK13: =SUM(AJ13*$Z$4) -> 2040 | AL13: =SUM(AJ13) -> 204 | AM13: =SUM(AL13*$Z$4) -> 2040 | AN13: =SUM(AO13/19600) -> 0.72857143 | AO13: =SUM(AA13+AC13+AE13+AG13+AI13+AK13+AM13) -> 14280 | AQ13: =SUM(AR13/92970) -> 0.63983422 | AR13: =Y13+AO13 -> 59485.387 | AS13: =SUM(AR13-AR12-AT13) -> 0 | AV13: =IF(AT13>0,AU13,AV12) -> 1.003 | AW13: =-SUM('B5'!AI12) -> 0 | AX13: =-SUM(AW13-AS13) -> 0 | AY13: =SUM(AX13+AW13) -> 0 | AZ13: =ELEC!A11 -> 0 | BA13: ='General information '!D13 -> 0 | BB13: =SUM('General information '!E13) -> 0 | BC13: =IF(AR12>=AR13,0,1) -> 0 | BD13: 19222 | BE13: =(305/1185)*ELEC!Q12 -> 0 | BG13: =#REF!-BE13 -> #REF! | BI13: 5 | BJ13: =AX13/BI13 -> 0 | BK13: =GEN!AF10 -> #DIV/0!
A14: =ELEC!C12 -> 44356 | B14: ='B5'!B13 -> 191 | C14: =B14*$B$4 -> 4109.5806 | D14: =SUM(B14) -> 191 | E14: =D14*$B$4 -> 4109.5806 | F14: =SUM(D14) -> 191 | G14: =F14*$B$4 -> 4109.5806 | H14: =SUM(F14) -> 191 | I14: =H14*$B$4 -> 4109.5806 | J14: =SUM(H14) -> 191 | K14: =J14*$B$4 -> 4109.5806 | L14: =SUM(J14) -> 191 | M14: =L14*$B$4 -> 4109.5806 | N14: =SUM(L14) -> 191 | O14: =N14*$B$4 -> 4109.5806 | P14: =SUM(N14) -> 191 | Q14: =P14*$B$4 -> 4109.5806 | R14: =SUM(P14) -> 191 | S14: =R14*$B$4 -> 4109.5806 | T14: =SUM(R14) -> 191 | U14: =T14*$B$4 -> 4109.5806 | V14: =SUM(T14) -> 191 | W14: =V14*$B$4 -> 4109.5806 | X14: =SUM(Y14/73370) -> 0.61612903 | Y14: =SUM(C14+E14+G14+I14+K14+M14+O14+Q14+S14+U14+W14) -> 45205.387 | Z14: ='B5'!C13 -> 204 | AA14: =SUM(Z14*$Z$4) -> 2040 | AB14: =SUM(Z14) -> 204 | AC14: =SUM(AB14*$Z$4) -> 2040 | AD14: =SUM(AB14) -> 204 | AE14: =SUM(AD14*$Z$4) -> 2040 | AF14: =SUM(AD14) -> 204 | AG14: =SUM(AF14*$Z$4) -> 2040 | AH14: =SUM(AF14) -> 204 | AI14: =SUM(AH14*$Z$4) -> 2040 | AJ14: =SUM(AH14) -> 204 | AK14: =SUM(AJ14*$Z$4) -> 2040 | AL14: =SUM(AJ14) -> 204 | AM14: =SUM(AL14*$Z$4) -> 2040 | AN14: =SUM(AO14/19600) -> 0.72857143 | AO14: =SUM(AA14+AC14+AE14+AG14+AI14+AK14+AM14) -> 14280 | AQ14: =SUM(AR14/92970) -> 0.63983422 | AR14: =Y14+AO14 -> 59485.387 | AS14: =SUM(AR14-AR13-AT14) -> 0 | AV14: =IF(AT14>0,AU14,AV13) -> 1.003 | AW14: =-SUM('B5'!AI13) -> 0 | AX14: =-SUM(AW14-AS14) -> 0 | AY14: =SUM(AX14+AW14) -> 0 | AZ14: =ELEC!A12 -> 0 | BA14: ='General information '!D14 -> 0 | BB14: =SUM('General information '!E14) -> 0 | BC14: =IF(AR13>=AR14,0,1) -> 0 | BD14: 19222 | BE14: =(305/1185)*ELEC!Q13 -> 0 | BG14: =#REF!-BE14 -> #REF! | BI14: 3 | BJ14: =AX14/BI14 -> 0 | BK14: =GEN!AF11 -> #DIV/0!
A15: =ELEC!C13 -> 44357 | B15: ='B5'!B14 -> 191 | C15: =B15*$B$4 -> 4109.5806 | D15: =SUM(B15) -> 191 | E15: =D15*$B$4 -> 4109.5806 | F15: =SUM(D15) -> 191 | G15: =F15*$B$4 -> 4109.5806 | H15: =SUM(F15) -> 191 | I15: =H15*$B$4 -> 4109.5806 | J15: =SUM(H15) -> 191 | K15: =J15*$B$4 -> 4109.5806 | L15: =SUM(J15) -> 191 | M15: =L15*$B$4 -> 4109.5806 | N15: =SUM(L15) -> 191 | O15: =N15*$B$4 -> 4109.5806 | P15: =SUM(N15) -> 191 | Q15: =P15*$B$4 -> 4109.5806 | R15: =SUM(P15) -> 191 | S15: =R15*$B$4 -> 4109.5806 | T15: =SUM(R15) -> 191 | U15: =T15*$B$4 -> 4109.5806 | V15: =SUM(T15) -> 191 | W15: =V15*$B$4 -> 4109.5806 | X15: =SUM(Y15/73370) -> 0.61612903 | Y15: =SUM(C15+E15+G15+I15+K15+M15+O15+Q15+S15+U15+W15) -> 45205.387 | Z15: ='B5'!C14 -> 204 | AA15: =SUM(Z15*$Z$4) -> 2040 | AB15: =SUM(Z15) -> 204 | AC15: =SUM(AB15*$Z$4) -> 2040 | AD15: =SUM(AB15) -> 204 | AE15: =SUM(AD15*$Z$4) -> 2040 | AF15: =SUM(AD15) -> 204 | AG15: =SUM(AF15*$Z$4) -> 2040 | AH15: =SUM(AF15) -> 204 | AI15: =SUM(AH15*$Z$4) -> 2040 | AJ15: =SUM(AH15) -> 204 | AK15: =SUM(AJ15*$Z$4) -> 2040 | AL15: =SUM(AJ15) -> 204 | AM15: =SUM(AL15*$Z$4) -> 2040 | AN15: =SUM(AO15/19600) -> 0.72857143 | AO15: =SUM(AA15+AC15+AE15+AG15+AI15+AK15+AM15) -> 14280 | AQ15: =SUM(AR15/92970) -> 0.63983422 | AR15: =Y15+AO15 -> 59485.387 | AS15: =SUM(AR15-AR14-AT15) -> 0 | AV15: =IF(AT15>0,AU15,AV14) -> 1.003 | AW15: =-SUM('B5'!AI14) -> 0 | AX15: =-SUM(AW15-AS15) -> 0 | AY15: =SUM(AX15+AW15) -> 0 | AZ15: =ELEC!A13 -> 0 | BA15: ='General information '!D15 -> 0 | BB15: =SUM('General information '!E15) -> 0 | BC15: =IF(AR14>=AR15,0,1) -> 0 | BD15: 19222 | BE15: =(305/1185)*ELEC!Q14 -> 0 | BG15: =#REF!-BE15 -> #REF! | BI15: 4 | BJ15: =AX15/BI15 -> 0 | BK15: =GEN!AF12 -> #DIV/0!
A16: =ELEC!C14 -> 44358 | B16: ='B5'!B15 -> 191 | C16: =B16*$B$4 -> 4109.5806 | D16: =SUM(B16) -> 191 | E16: =D16*$B$4 -> 4109.5806 | F16: =SUM(D16) -> 191 | G16: =F16*$B$4 -> 4109.5806 | H16: =SUM(F16) -> 191 | I16: =H16*$B$4 -> 4109.5806 | J16: =SUM(H16) -> 191 | K16: =J16*$B$4 -> 4109.5806 | L16: =SUM(J16) -> 191 | M16: =L16*$B$4 -> 4109.5806 | N16: =SUM(L16) -> 191 | O16: =N16*$B$4 -> 4109.5806 | P16: =SUM(N16) -> 191 | Q16: =P16*$B$4 -> 4109.5806 | R16: =SUM(P16) -> 191 | S16: =R16*$B$4 -> 4109.5806 | T16: =SUM(R16) -> 191 | U16: =T16*$B$4 -> 4109.5806 | V16: =SUM(T16) -> 191 | W16: =V16*$B$4 -> 4109.5806 | X16: =SUM(Y16/73370) -> 0.61612903 | Y16: =SUM(C16+E16+G16+I16+K16+M16+O16+Q16+S16+U16+W16) -> 45205.387 | Z16: ='B5'!C15 -> 204 | AA16: =SUM(Z16*$Z$4) -> 2040 | AB16: =SUM(Z16) -> 204 | AC16: =SUM(AB16*$Z$4) -> 2040 | AD16: =SUM(AB16) -> 204 | AE16: =SUM(AD16*$Z$4) -> 2040 | AF16: =SUM(AD16) -> 204 | AG16: =SUM(AF16*$Z$4) -> 2040 | AH16: =SUM(AF16) -> 204 | AI16: =SUM(AH16*$Z$4) -> 2040 | AJ16: =SUM(AH16) -> 204 | AK16: =SUM(AJ16*$Z$4) -> 2040 | AL16: =SUM(AJ16) -> 204 | AM16: =SUM(AL16*$Z$4) -> 2040 | AN16: =SUM(AO16/19600) -> 0.72857143 | AO16: =SUM(AA16+AC16+AE16+AG16+AI16+AK16+AM16) -> 14280 | AQ16: =SUM(AR16/92970) -> 0.63983422 | AR16: =Y16+AO16 -> 59485.387 | AS16: =SUM(AR16-AR15-AT16) -> 0 | AV16: =IF(AT16>0,AU16,AV15) -> 1.003 | AW16: =-SUM('B5'!AI15) -> 0 | AX16: =-SUM(AW16-AS16) -> 0 | AY16: =SUM(AX16+AW16) -> 0 | AZ16: =ELEC!A14 -> 0 | BA16: ='General information '!D16 -> 0 | BB16: =SUM('General information '!E16) -> 0 | BC16: =IF(AR15>=AR16,0,1) -> 0 | BD16: 19222 | BE16: =(305/1185)*ELEC!Q15 -> 0 | BG16: =#REF!-BE16 -> #REF! | BI16: 3 | BJ16: =AX16/BI16 -> 0 | BK16: =GEN!AF13 -> #DIV/0!
A17: =ELEC!C15 -> 44359 | B17: ='B5'!B16 -> 191 | C17: =B17*$B$4 -> 4109.5806 | D17: =SUM(B17) -> 191 | E17: =D17*$B$4 -> 4109.5806 | F17: =SUM(D17) -> 191 | G17: =F17*$B$4 -> 4109.5806 | H17: =SUM(F17) -> 191 | I17: =H17*$B$4 -> 4109.5806 | J17: =SUM(H17) -> 191 | K17: =J17*$B$4 -> 4109.5806 | L17: =SUM(J17) -> 191 | M17: =L17*$B$4 -> 4109.5806 | N17: =SUM(L17) -> 191 | O17: =N17*$B$4 -> 4109.5806 | P17: =SUM(N17) -> 191 | Q17: =P17*$B$4 -> 4109.5806 | R17: =SUM(P17) -> 191 | S17: =R17*$B$4 -> 4109.5806 | T17: =SUM(R17) -> 191 | U17: =T17*$B$4 -> 4109.5806 | V17: =SUM(T17) -> 191 | W17: =V17*$B$4 -> 4109.5806 | X17: =SUM(Y17/73370) -> 0.61612903 | Y17: =SUM(C17+E17+G17+I17+K17+M17+O17+Q17+S17+U17+W17) -> 45205.387 | Z17: ='B5'!C16 -> 204 | AA17: =SUM(Z17*$Z$4) -> 2040 | AB17: =SUM(Z17) -> 204 | AC17: =SUM(AB17*$Z$4) -> 2040 | AD17: =SUM(AB17) -> 204 | AE17: =SUM(AD17*$Z$4) -> 2040 | AF17: =SUM(AD17) -> 204 | AG17: =SUM(AF17*$Z$4) -> 2040 | AH17: =SUM(AF17) -> 204 | AI17: =SUM(AH17*$Z$4) -> 2040 | AJ17: =SUM(AH17) -> 204 | AK17: =SUM(AJ17*$Z$4) -> 2040 | AL17: =SUM(AJ17) -> 204 | AM17: =SUM(AL17*$Z$4) -> 2040 | AN17: =SUM(AO17/19600) -> 0.72857143 | AO17: =SUM(AA17+AC17+AE17+AG17+AI17+AK17+AM17) -> 14280 | AQ17: =SUM(AR17/92970) -> 0.63983422 | AR17: =Y17+AO17 -> 59485.387 | AS17: =SUM(AR17-AR16-AT17) -> 0 | AV17: =IF(AT17>0,AU17,AV16) -> 1.003 | AW17: =-SUM('B5'!AI16) -> 0 | AX17: =-SUM(AW17-AS17) -> 0 | AY17: =SUM(AX17+AW17) -> 0 | AZ17: =ELEC!A15 -> 0 | BA17: ='General information '!D17 -> 0 | BB17: =SUM('General information '!E17) -> 0 | BC17: =IF(AR16>=AR17,0,1) -> 0 | BD17: 19222 | BE17: =(305/1185)*ELEC!Q16 -> 0 | BG17: =#REF!-BE17 -> #REF!
A18: =ELEC!C16 -> 44360 | B18: ='B5'!B17 -> 191 | C18: =B18*$B$4 -> 4109.5806 | D18: =SUM(B18) -> 191 | E18: =D18*$B$4 -> 4109.5806 | F18: =SUM(D18) -> 191 | G18: =F18*$B$4 -> 4109.5806 | H18: =SUM(F18) -> 191 | I18: =H18*$B$4 -> 4109.5806 | J18: =SUM(H18) -> 191 | K18: =J18*$B$4 -> 4109.5806 | L18: =SUM(J18) -> 191 | M18: =L18*$B$4 -> 4109.5806 | N18: =SUM(L18) -> 191 | O18: =N18*$B$4 -> 4109.5806 | P18: =SUM(N18) -> 191 | Q18: =P18*$B$4 -> 4109.5806 | R18: =SUM(P18) -> 191 | S18: =R18*$B$4 -> 4109.5806 | T18: =SUM(R18) -> 191 | U18: =T18*$B$4 -> 4109.5806 | V18: =SUM(T18) -> 191 | W18: =V18*$B$4 -> 4109.5806 | X18: =SUM(Y18/73370) -> 0.61612903 | Y18: =SUM(C18+E18+G18+I18+K18+M18+O18+Q18+S18+U18+W18) -> 45205.387 | Z18: ='B5'!C17 -> 204 | AA18: =SUM(Z18*$Z$4) -> 2040 | AB18: =SUM(Z18) -> 204 | AC18: =SUM(AB18*$Z$4) -> 2040 | AD18: =SUM(AB18) -> 204 | AE18: =SUM(AD18*$Z$4) -> 2040 | AF18: =SUM(AD18) -> 204 | AG18: =SUM(AF18*$Z$4) -> 2040 | AH18: =SUM(AF18) -> 204 | AI18: =SUM(AH18*$Z$4) -> 2040 | AJ18: =SUM(AH18) -> 204 | AK18: =SUM(AJ18*$Z$4) -> 2040 | AL18: =SUM(AJ18) -> 204 | AM18: =SUM(AL18*$Z$4) -> 2040 | AN18: =SUM(AO18/19600) -> 0.72857143 | AO18: =SUM(AA18+AC18+AE18+AG18+AI18+AK18+AM18) -> 14280 | AQ18: =SUM(AR18/92970) -> 0.63983422 | AR18: =Y18+AO18 -> 59485.387 | AS18: =SUM(AR18-AR17-AT18) -> 0 | AV18: =IF(AT18>0,AU18,AV17) -> 1.003 | AW18: =-SUM('B5'!AI17) -> 0 | AX18: =-SUM(AW18-AS18) -> 0 | AY18: =SUM(AX18+AW18) -> 0 | AZ18: =ELEC!A16 -> 0 | BA18: ='General information '!D18 -> 0 | BB18: =SUM('General information '!E18) -> 0 | BC18: =IF(AR17>=AR18,0,1) -> 0 | BD18: 19222 | BE18: =(305/1185)*ELEC!Q17 -> 0 | BG18: =#REF!-BE18 -> #REF!
A19: =ELEC!C17 -> 44361 | B19: ='B5'!B18 -> 191 | C19: =B19*$B$4 -> 4109.5806 | D19: =SUM(B19) -> 191 | E19: =D19*$B$4 -> 4109.5806 | F19: =SUM(D19) -> 191 | G19: =F19*$B$4 -> 4109.5806 | H19: =SUM(F19) -> 191 | I19: =H19*$B$4 -> 4109.5806 | J19: =SUM(H19) -> 191 | K19: =J19*$B$4 -> 4109.5806 | L19: =SUM(J19) -> 191 | M19: =L19*$B$4 -> 4109.5806 | N19: =SUM(L19) -> 191 | O19: =N19*$B$4 -> 4109.5806 | P19: =SUM(N19) -> 191 | Q19: =P19*$B$4 -> 4109.5806 | R19: =SUM(P19) -> 191 | S19: =R19*$B$4 -> 4109.5806 | T19: =SUM(R19) -> 191 | U19: =T19*$B$4 -> 4109.5806 | V19: =SUM(T19) -> 191 | W19: =V19*$B$4 -> 4109.5806 | X19: =SUM(Y19/73370) -> 0.61612903 | Y19: =SUM(C19+E19+G19+I19+K19+M19+O19+Q19+S19+U19+W19) -> 45205.387 | Z19: ='B5'!C18 -> 204 | AA19: =SUM(Z19*$Z$4) -> 2040 | AB19: =SUM(Z19) -> 204 | AC19: =SUM(AB19*$Z$4) -> 2040 | AD19: =SUM(AB19) -> 204 | AE19: =SUM(AD19*$Z$4) -> 2040 | AF19: =SUM(AD19) -> 204 | AG19: =SUM(AF19*$Z$4) -> 2040 | AH19: =SUM(AF19) -> 204 | AI19: =SUM(AH19*$Z$4) -> 2040 | AJ19: =SUM(AH19) -> 204 | AK19: =SUM(AJ19*$Z$4) -> 2040 | AL19: =SUM(AJ19) -> 204 | AM19: =SUM(AL19*$Z$4) -> 2040 | AN19: =SUM(AO19/19600) -> 0.72857143 | AO19: =SUM(AA19+AC19+AE19+AG19+AI19+AK19+AM19) -> 14280 | AQ19: =SUM(AR19/92970) -> 0.63983422 | AR19: =Y19+AO19 -> 59485.387 | AS19: =SUM(AR19-AR18-AT19) -> 0 | AV19: =IF(AT19>0,AU19,AV18) -> 1.003 | AW19: =-SUM('B5'!AI18) -> 0 | AX19: =-SUM(AW19-AS19) -> 0 | AY19: =SUM(AX19+AW19) -> 0 | AZ19: =ELEC!A17 -> 0 | BA19: ='General information '!D19 -> 0 | BB19: =SUM('General information '!E19) -> 0 | BC19: =IF(AR18>=AR19,0,1) -> 0 | BD19: 19222 | BE19: =(305/1185)*ELEC!Q18 -> 0 | BG19: =#REF!-BE19 -> #REF!
A20: =ELEC!C18 -> 44362 | B20: ='B5'!B19 -> 191 | C20: =B20*$B$4 -> 4109.5806 | D20: =SUM(B20) -> 191 | E20: =D20*$B$4 -> 4109.5806 | F20: =SUM(D20) -> 191 | G20: =F20*$B$4 -> 4109.5806 | H20: =SUM(F20) -> 191 | I20: =H20*$B$4 -> 4109.5806 | J20: =SUM(H20) -> 191 | K20: =J20*$B$4 -> 4109.5806 | L20: =SUM(J20) -> 191 | M20: =L20*$B$4 -> 4109.5806 | N20: =SUM(L20) -> 191 | O20: =N20*$B$4 -> 4109.5806 | P20: =SUM(N20) -> 191 | Q20: =P20*$B$4 -> 4109.5806 | R20: =SUM(P20) -> 191 | S20: =R20*$B$4 -> 4109.5806 | T20: =SUM(R20) -> 191 | U20: =T20*$B$4 -> 4109.5806 | V20: =SUM(T20) -> 191 | W20: =V20*$B$4 -> 4109.5806 | X20: =SUM(Y20/73370) -> 0.61612903 | Y20: =SUM(C20+E20+G20+I20+K20+M20+O20+Q20+S20+U20+W20) -> 45205.387 | Z20: ='B5'!C19 -> 204 | AA20: =SUM(Z20*$Z$4) -> 2040 | AB20: =SUM(Z20) -> 204 | AC20: =SUM(AB20*$Z$4) -> 2040 | AD20: =SUM(AB20) -> 204 | AE20: =SUM(AD20*$Z$4) -> 2040 | AF20: =SUM(AD20) -> 204 | AG20: =SUM(AF20*$Z$4) -> 2040 | AH20: =SUM(AF20) -> 204 | AI20: =SUM(AH20*$Z$4) -> 2040 | AJ20: =SUM(AH20) -> 204 | AK20: =SUM(AJ20*$Z$4) -> 2040 | AL20: =SUM(AJ20) -> 204 | AM20: =SUM(AL20*$Z$4) -> 2040 | AN20: =SUM(AO20/19600) -> 0.72857143 | AO20: =SUM(AA20+AC20+AE20+AG20+AI20+AK20+AM20) -> 14280 | AQ20: =SUM(AR20/92970) -> 0.63983422 | AR20: =Y20+AO20 -> 59485.387 | AS20: =SUM(AR20-AR19-AT20) -> 0 | AV20: =IF(AT20>0,AU20,AV19) -> 1.003 | AW20: =-SUM('B5'!AI19) -> 0 | AX20: =-SUM(AW20-AS20) -> 0 | AY20: =SUM(AX20+AW20) -> 0 | AZ20: =ELEC!A18 -> 0 | BA20: ='General information '!D20 -> 0 | BB20: =SUM('General information '!E20) -> 0 | BC20: =IF(AR19>=AR20,0,1) -> 0 | BD20: 19222 | BE20: =(305/1185)*ELEC!Q19 -> 0 | BG20: =#REF!-BE20 -> #REF!
A21: =ELEC!C19 -> 44363 | B21: ='B5'!B20 -> 191 | C21: =B21*$B$4 -> 4109.5806 | D21: =SUM(B21) -> 191 | E21: =D21*$B$4 -> 4109.5806 | F21: =SUM(D21) -> 191 | G21: =F21*$B$4 -> 4109.5806 | H21: =SUM(F21) -> 191 | I21: =H21*$B$4 -> 4109.5806 | J21: =SUM(H21) -> 191 | K21: =J21*$B$4 -> 4109.5806 | L21: =SUM(J21) -> 191 | M21: =L21*$B$4 -> 4109.5806 | N21: =SUM(L21) -> 191 | O21: =N21*$B$4 -> 4109.5806 | P21: =SUM(N21) -> 191 | Q21: =P21*$B$4 -> 4109.5806 | R21: =SUM(P21) -> 191 | S21: =R21*$B$4 -> 4109.5806 | T21: =SUM(R21) -> 191 | U21: =T21*$B$4 -> 4109.5806 | V21: =SUM(T21) -> 191 | W21: =V21*$B$4 -> 4109.5806 | X21: =SUM(Y21/73370) -> 0.61612903 | Y21: =SUM(C21+E21+G21+I21+K21+M21+O21+Q21+S21+U21+W21) -> 45205.387 | Z21: ='B5'!C20 -> 204 | AA21: =SUM(Z21*$Z$4) -> 2040 | AB21: =SUM(Z21) -> 204 | AC21: =SUM(AB21*$Z$4) -> 2040 | AD21: =SUM(AB21) -> 204 | AE21: =SUM(AD21*$Z$4) -> 2040 | AF21: =SUM(AD21) -> 204 | AG21: =SUM(AF21*$Z$4) -> 2040 | AH21: =SUM(AF21) -> 204 | AI21: =SUM(AH21*$Z$4) -> 2040 | AJ21: =SUM(AH21) -> 204 | AK21: =SUM(AJ21*$Z$4) -> 2040 | AL21: =SUM(AJ21) -> 204 | AM21: =SUM(AL21*$Z$4) -> 2040 | AN21: =SUM(AO21/19600) -> 0.72857143 | AO21: =SUM(AA21+AC21+AE21+AG21+AI21+AK21+AM21) -> 14280 | AQ21: =SUM(AR21/92970) -> 0.63983422 | AR21: =Y21+AO21 -> 59485.387 | AS21: =SUM(AR21-AR20-AT21) -> 0 | AV21: =IF(AT21>0,AU21,AV20) -> 1.003 | AW21: =-SUM('B5'!AI20) -> 0 | AX21: =-SUM(AW21-AS21) -> 0 | AY21: =SUM(AX21+AW21) -> 0 | AZ21: =ELEC!A19 -> 0 | BA21: ='General information '!D21 -> 0 | BB21: =SUM('General information '!E21) -> 0 | BC21: =IF(AR20>=AR21,0,1) -> 0 | BD21: 19222 | BE21: =(305/1185)*ELEC!Q20 -> 0 | BG21: =#REF!-BE21 -> #REF!
A22: =ELEC!C20 -> 44364 | B22: ='B5'!B21 -> 191 | C22: =B22*$B$4 -> 4109.5806 | D22: =SUM(B22) -> 191 | E22: =D22*$B$4 -> 4109.5806 | F22: =SUM(D22) -> 191 | G22: =F22*$B$4 -> 4109.5806 | H22: =SUM(F22) -> 191 | I22: =H22*$B$4 -> 4109.5806 | J22: =SUM(H22) -> 191 | K22: =J22*$B$4 -> 4109.5806 | L22: =SUM(J22) -> 191 | M22: =L22*$B$4 -> 4109.5806 | N22: =SUM(L22) -> 191 | O22: =N22*$B$4 -> 4109.5806 | P22: =SUM(N22) -> 191 | Q22: =P22*$B$4 -> 4109.5806 | R22: =SUM(P22) -> 191 | S22: =R22*$B$4 -> 4109.5806 | T22: =SUM(R22) -> 191 | U22: =T22*$B$4 -> 4109.5806 | V22: =SUM(T22) -> 191 | W22: =V22*$B$4 -> 4109.5806 | X22: =SUM(Y22/73370) -> 0.61612903 | Y22: =SUM(C22+E22+G22+I22+K22+M22+O22+Q22+S22+U22+W22) -> 45205.387 | Z22: ='B5'!C21 -> 204 | AA22: =SUM(Z22*$Z$4) -> 2040 | AB22: =SUM(Z22) -> 204 | AC22: =SUM(AB22*$Z$4) -> 2040 | AD22: =SUM(AB22) -> 204 | AE22: =SUM(AD22*$Z$4) -> 2040 | AF22: =SUM(AD22) -> 204 | AG22: =SUM(AF22*$Z$4) -> 2040 | AH22: =SUM(AF22) -> 204 | AI22: =SUM(AH22*$Z$4) -> 2040 | AJ22: =SUM(AH22) -> 204 | AK22: =SUM(AJ22*$Z$4) -> 2040 | AL22: =SUM(AJ22) -> 204 | AM22: =SUM(AL22*$Z$4) -> 2040 | AN22: =SUM(AO22/19600) -> 0.72857143 | AO22: =SUM(AA22+AC22+AE22+AG22+AI22+AK22+AM22) -> 14280 | AQ22: =SUM(AR22/92970) -> 0.63983422 | AR22: =Y22+AO22 -> 59485.387 | AS22: =SUM(AR22-AR21-AT22) -> 0 | AV22: =IF(AT22>0,AU22,AV21) -> 1.003 | AW22: =-SUM('B5'!AI21) -> 0 | AX22: =-SUM(AW22-AS22) -> 0 | AY22: =SUM(AX22+AW22) -> 0 | AZ22: =ELEC!A20 -> 0 | BA22: ='General information '!D22 -> 0 | BB22: =SUM('General information '!E22) -> 0 | BC22: =IF(AR21>=AR22,0,1) -> 0 | BD22: 19222 | BE22: =(305/1185)*ELEC!Q21 -> 0 | BG22: =#REF!-BE22 -> #REF!
A23: =ELEC!C21 -> 44365 | B23: ='B5'!B22 -> 191 | C23: =B23*$B$4 -> 4109.5806 | D23: =SUM(B23) -> 191 | E23: =D23*$B$4 -> 4109.5806 | F23: =SUM(D23) -> 191 | G23: =F23*$B$4 -> 4109.5806 | H23: =SUM(F23) -> 191 | I23: =H23*$B$4 -> 4109.5806 | J23: =SUM(H23) -> 191 | K23: =J23*$B$4 -> 4109.5806 | L23: =SUM(J23) -> 191 | M23: =L23*$B$4 -> 4109.5806 | N23: =SUM(L23) -> 191 | O23: =N23*$B$4 -> 4109.5806 | P23: =SUM(N23) -> 191 | Q23: =P23*$B$4 -> 4109.5806 | R23: =SUM(P23) -> 191 | S23: =R23*$B$4 -> 4109.5806 | T23: =SUM(R23) -> 191 | U23: =T23*$B$4 -> 4109.5806 | V23: =SUM(T23) -> 191 | W23: =V23*$B$4 -> 4109.5806 | X23: =SUM(Y23/73370) -> 0.61612903 | Y23: =SUM(C23+E23+G23+I23+K23+M23+O23+Q23+S23+U23+W23) -> 45205.387 | Z23: ='B5'!C22 -> 204 | AA23: =SUM(Z23*$Z$4) -> 2040 | AB23: =SUM(Z23) -> 204 | AC23: =SUM(AB23*$Z$4) -> 2040 | AD23: =SUM(AB23) -> 204 | AE23: =SUM(AD23*$Z$4) -> 2040 | AF23: =SUM(AD23) -> 204 | AG23: =SUM(AF23*$Z$4) -> 2040 | AH23: =SUM(AF23) -> 204 | AI23: =SUM(AH23*$Z$4) -> 2040 | AJ23: =SUM(AH23) -> 204 | AK23: =SUM(AJ23*$Z$4) -> 2040 | AL23: =SUM(AJ23) -> 204 | AM23: =SUM(AL23*$Z$4) -> 2040 | AN23: =SUM(AO23/19600) -> 0.72857143 | AO23: =SUM(AA23+AC23+AE23+AG23+AI23+AK23+AM23) -> 14280 | AQ23: =SUM(AR23/92970) -> 0.63983422 | AR23: =Y23+AO23 -> 59485.387 | AS23: =SUM(AR23-AR22-AT23) -> 0 | AV23: =IF(AT23>0,AU23,AV22) -> 1.003 | AW23: =-SUM('B5'!AI22) -> 0 | AX23: =-SUM(AW23-AS23) -> 0 | AY23: =SUM(AX23+AW23) -> 0 | AZ23: =ELEC!A21 -> 0 | BA23: ='General information '!D23 -> 0 | BB23: =SUM('General information '!E23) -> 0 | BC23: =IF(AR22>=AR23,0,1) -> 0 | BD23: 19222 | BE23: =(305/1185)*ELEC!Q22 -> 0 | BG23: =#REF!-BE23 -> #REF!
A24: =ELEC!C22 -> 44366 | B24: ='B5'!B23 -> 191 | C24: =B24*$B$4 -> 4109.5806 | D24: =SUM(B24) -> 191 | E24: =D24*$B$4 -> 4109.5806 | F24: =SUM(D24) -> 191 | G24: =F24*$B$4 -> 4109.5806 | H24: =SUM(F24) -> 191 | I24: =H24*$B$4 -> 4109.5806 | J24: =SUM(H24) -> 191 | K24: =J24*$B$4 -> 4109.5806 | L24: =SUM(J24) -> 191 | M24: =L24*$B$4 -> 4109.5806 | N24: =SUM(L24) -> 191 | O24: =N24*$B$4 -> 4109.5806 | P24: =SUM(N24) -> 191 | Q24: =P24*$B$4 -> 4109.5806 | R24: =SUM(P24) -> 191 | S24: =R24*$B$4 -> 4109.5806 | T24: =SUM(R24) -> 191 | U24: =T24*$B$4 -> 4109.5806 | V24: =SUM(T24) -> 191 | W24: =V24*$B$4 -> 4109.5806 | X24: =SUM(Y24/73370) -> 0.61612903 | Y24: =SUM(C24+E24+G24+I24+K24+M24+O24+Q24+S24+U24+W24) -> 45205.387 | Z24: ='B5'!C23 -> 204 | AA24: =SUM(Z24*$Z$4) -> 2040 | AB24: =SUM(Z24) -> 204 | AC24: =SUM(AB24*$Z$4) -> 2040 | AD24: =SUM(AB24) -> 204 | AE24: =SUM(AD24*$Z$4) -> 2040 | AF24: =SUM(AD24) -> 204 | AG24: =SUM(AF24*$Z$4) -> 2040 | AH24: =SUM(AF24) -> 204 | AI24: =SUM(AH24*$Z$4) -> 2040 | AJ24: =SUM(AH24) -> 204 | AK24: =SUM(AJ24*$Z$4) -> 2040 | AL24: =SUM(AJ24) -> 204 | AM24: =SUM(AL24*$Z$4) -> 2040 | AN24: =SUM(AO24/19600) -> 0.72857143 | AO24: =SUM(AA24+AC24+AE24+AG24+AI24+AK24+AM24) -> 14280 | AQ24: =SUM(AR24/92970) -> 0.63983422 | AR24: =Y24+AO24 -> 59485.387 | AS24: =SUM(AR24-AR23-AT24) -> 0 | AV24: =IF(AT24>0,AU24,AV23) -> 1.003 | AW24: =-SUM('B5'!AI23) -> 0 | AX24: =-SUM(AW24-AS24) -> 0 | AY24: =SUM(AX24+AW24) -> 0 | AZ24: =ELEC!A22 -> 0 | BA24: ='General information '!D24 -> 0 | BB24: =SUM('General information '!E24) -> 0 | BC24: =IF(AR23>=AR24,0,1) -> 0 | BD24: 19222 | BE24: =(305/1185)*ELEC!Q23 -> 0 | BG24: =#REF!-BE24 -> #REF!
A25: =ELEC!C23 -> 44367 | B25: ='B5'!B24 -> 191 | C25: =B25*$B$4 -> 4109.5806 | D25: =SUM(B25) -> 191 | E25: =D25*$B$4 -> 4109.5806 | F25: =SUM(D25) -> 191 | G25: =F25*$B$4 -> 4109.5806 | H25: =SUM(F25) -> 191 | I25: =H25*$B$4 -> 4109.5806 | J25: =SUM(H25) -> 191 | K25: =J25*$B$4 -> 4109.5806 | L25: =SUM(J25) -> 191 | M25: =L25*$B$4 -> 4109.5806 | N25: =SUM(L25) -> 191 | O25: =N25*$B$4 -> 4109.5806 | P25: =SUM(N25) -> 191 | Q25: =P25*$B$4 -> 4109.5806 | R25: =SUM(P25) -> 191 | S25: =R25*$B$4 -> 4109.5806 | T25: =SUM(R25) -> 191 | U25: =T25*$B$4 -> 4109.5806 | V25: =SUM(T25) -> 191 | W25: =V25*$B$4 -> 4109.5806 | X25: =SUM(Y25/73370) -> 0.61612903 | Y25: =SUM(C25+E25+G25+I25+K25+M25+O25+Q25+S25+U25+W25) -> 45205.387 | Z25: ='B5'!C24 -> 204 | AA25: =SUM(Z25*$Z$4) -> 2040 | AB25: =SUM(Z25) -> 204 | AC25: =SUM(AB25*$Z$4) -> 2040 | AD25: =SUM(AB25) -> 204 | AE25: =SUM(AD25*$Z$4) -> 2040 | AF25: =SUM(AD25) -> 204 | AG25: =SUM(AF25*$Z$4) -> 2040 | AH25: =SUM(AF25) -> 204 | AI25: =SUM(AH25*$Z$4) -> 2040 | AJ25: =SUM(AH25) -> 204 | AK25: =SUM(AJ25*$Z$4) -> 2040 | AL25: =SUM(AJ25) -> 204 | AM25: =SUM(AL25*$Z$4) -> 2040 | AN25: =SUM(AO25/19600) -> 0.72857143 | AO25: =SUM(AA25+AC25+AE25+AG25+AI25+AK25+AM25) -> 14280 | AQ25: =SUM(AR25/92970) -> 0.63983422 | AR25: =Y25+AO25 -> 59485.387 | AS25: =SUM(AR25-AR24-AT25) -> 0 | AV25: =IF(AT25>0,AU25,AV24) -> 1.003 | AW25: =-SUM('B5'!AI24) -> 0 | AX25: =-SUM(AW25-AS25) -> 0 | AY25: =SUM(AX25+AW25) -> 0 | AZ25: =ELEC!A23 -> 0 | BA25: ='General information '!D25 -> 0 | BB25: =SUM('General information '!E25) -> 0 | BC25: =IF(AR24>=AR25,0,1) -> 0 | BD25: 19222 | BE25: =(305/1185)*ELEC!Q24 -> 0 | BG25: =#REF!-BE25 -> #REF!
A26: =ELEC!C24 -> 44368 | B26: ='B5'!B25 -> 191 | C26: =B26*$B$4 -> 4109.5806 | D26: =SUM(B26) -> 191 | E26: =D26*$B$4 -> 4109.5806 | F26: =SUM(D26) -> 191 | G26: =F26*$B$4 -> 4109.5806 | H26: =SUM(F26) -> 191 | I26: =H26*$B$4 -> 4109.5806 | J26: =SUM(H26) -> 191 | K26: =J26*$B$4 -> 4109.5806 | L26: =SUM(J26) -> 191 | M26: =L26*$B$4 -> 4109.5806 | N26: =SUM(L26) -> 191 | O26: =N26*$B$4 -> 4109.5806 | P26: =SUM(N26) -> 191 | Q26: =P26*$B$4 -> 4109.5806 | R26: =SUM(P26) -> 191 | S26: =R26*$B$4 -> 4109.5806 | T26: =SUM(R26) -> 191 | U26: =T26*$B$4 -> 4109.5806 | V26: =SUM(T26) -> 191 | W26: =V26*$B$4 -> 4109.5806 | X26: =SUM(Y26/73370) -> 0.61612903 | Y26: =SUM(C26+E26+G26+I26+K26+M26+O26+Q26+S26+U26+W26) -> 45205.387 | Z26: ='B5'!C25 -> 204 | AA26: =SUM(Z26*$Z$4) -> 2040 | AB26: =SUM(Z26) -> 204 | AC26: =SUM(AB26*$Z$4) -> 2040 | AD26: =SUM(AB26) -> 204 | AE26: =SUM(AD26*$Z$4) -> 2040 | AF26: =SUM(AD26) -> 204 | AG26: =SUM(AF26*$Z$4) -> 2040 | AH26: =SUM(AF26) -> 204 | AI26: =SUM(AH26*$Z$4) -> 2040 | AJ26: =SUM(AH26) -> 204 | AK26: =SUM(AJ26*$Z$4) -> 2040 | AL26: =SUM(AJ26) -> 204 | AM26: =SUM(AL26*$Z$4) -> 2040 | AN26: =SUM(AO26/19600) -> 0.72857143 | AO26: =SUM(AA26+AC26+AE26+AG26+AI26+AK26+AM26) -> 14280 | AQ26: =SUM(AR26/92970) -> 0.63983422 | AR26: =Y26+AO26 -> 59485.387 | AS26: =SUM(AR26-AR25-AT26) -> 0 | AV26: =IF(AT26>0,AU26,AV25) -> 1.003 | AW26: =-SUM('B5'!AI25) -> 0 | AX26: =-SUM(AW26-AS26) -> 0 | AY26: =SUM(AX26+AW26) -> 0 | AZ26: =ELEC!A24 -> 0 | BA26: ='General information '!D26 -> 0 | BB26: =SUM('General information '!E26) -> 0 | BC26: =IF(AR25>=AR26,0,1) -> 0 | BD26: 19222 | BE26: =(305/1185)*ELEC!Q25 -> 0 | BG26: =#REF!-BE26 -> #REF!
A27: =ELEC!C25 -> 44369 | B27: ='B5'!B26 -> 191 | C27: =B27*$B$4 -> 4109.5806 | D27: =SUM(B27) -> 191 | E27: =D27*$B$4 -> 4109.5806 | F27: =SUM(D27) -> 191 | G27: =F27*$B$4 -> 4109.5806 | H27: =SUM(F27) -> 191 | I27: =H27*$B$4 -> 4109.5806 | J27: =SUM(H27) -> 191 | K27: =J27*$B$4 -> 4109.5806 | L27: =SUM(J27) -> 191 | M27: =L27*$B$4 -> 4109.5806 | N27: =SUM(L27) -> 191 | O27: =N27*$B$4 -> 4109.5806 | P27: =SUM(N27) -> 191 | Q27: =P27*$B$4 -> 4109.5806 | R27: =SUM(P27) -> 191 | S27: =R27*$B$4 -> 4109.5806 | T27: =SUM(R27) -> 191 | U27: =T27*$B$4 -> 4109.5806 | V27: =SUM(T27) -> 191 | W27: =V27*$B$4 -> 4109.5806 | X27: =SUM(Y27/73370) -> 0.61612903 | Y27: =SUM(C27+E27+G27+I27+K27+M27+O27+Q27+S27+U27+W27) -> 45205.387 | Z27: ='B5'!C26 -> 204 | AA27: =SUM(Z27*$Z$4) -> 2040 | AB27: =SUM(Z27) -> 204 | AC27: =SUM(AB27*$Z$4) -> 2040 | AD27: =SUM(AB27) -> 204 | AE27: =SUM(AD27*$Z$4) -> 2040 | AF27: =SUM(AD27) -> 204 | AG27: =SUM(AF27*$Z$4) -> 2040 | AH27: =SUM(AF27) -> 204 | AI27: =SUM(AH27*$Z$4) -> 2040 | AJ27: =SUM(AH27) -> 204 | AK27: =SUM(AJ27*$Z$4) -> 2040 | AL27: =SUM(AJ27) -> 204 | AM27: =SUM(AL27*$Z$4) -> 2040 | AN27: =SUM(AO27/19600) -> 0.72857143 | AO27: =SUM(AA27+AC27+AE27+AG27+AI27+AK27+AM27) -> 14280 | AQ27: =SUM(AR27/92970) -> 0.63983422 | AR27: =Y27+AO27 -> 59485.387 | AS27: =SUM(AR27-AR26-AT27) -> 0 | AV27: =IF(AT27>0,AU27,AV26) -> 1.003 | AW27: =-SUM('B5'!AI26) -> 0 | AX27: =-SUM(AW27-AS27) -> 0 | AY27: =SUM(AX27+AW27) -> 0 | AZ27: =ELEC!A25 -> 0 | BA27: ='General information '!D27 -> 0 | BB27: =SUM('General information '!E27) -> 0 | BC27: =IF(AR26>=AR27,0,1) -> 0 | BD27: 19222 | BE27: =(305/1185)*ELEC!Q26 -> 0 | BG27: =#REF!-BE27 -> #REF!
A28: =ELEC!C26 -> 44370 | B28: ='B5'!B27 -> 191 | C28: =B28*$B$4 -> 4109.5806 | D28: =SUM(B28) -> 191 | E28: =D28*$B$4 -> 4109.5806 | F28: =SUM(D28) -> 191 | G28: =F28*$B$4 -> 4109.5806 | H28: =SUM(F28) -> 191 | I28: =H28*$B$4 -> 4109.5806 | J28: =SUM(H28) -> 191 | K28: =J28*$B$4 -> 4109.5806 | L28: =SUM(J28) -> 191 | M28: =L28*$B$4 -> 4109.5806 | N28: =SUM(L28) -> 191 | O28: =N28*$B$4 -> 4109.5806 | P28: =SUM(N28) -> 191 | Q28: =P28*$B$4 -> 4109.5806 | R28: =SUM(P28) -> 191 | S28: =R28*$B$4 -> 4109.5806 | T28: =SUM(R28) -> 191 | U28: =T28*$B$4 -> 4109.5806 | V28: =SUM(T28) -> 191 | W28: =V28*$B$4 -> 4109.5806 | X28: =SUM(Y28/73370) -> 0.61612903 | Y28: =SUM(C28+E28+G28+I28+K28+M28+O28+Q28+S28+U28+W28) -> 45205.387 | Z28: ='B5'!C27 -> 204 | AA28: =SUM(Z28*$Z$4) -> 2040 | AB28: =SUM(Z28) -> 204 | AC28: =SUM(AB28*$Z$4) -> 2040 | AD28: =SUM(AB28) -> 204 | AE28: =SUM(AD28*$Z$4) -> 2040 | AF28: =SUM(AD28) -> 204 | AG28: =SUM(AF28*$Z$4) -> 2040 | AH28: =SUM(AF28) -> 204 | AI28: =SUM(AH28*$Z$4) -> 2040 | AJ28: =SUM(AH28) -> 204 | AK28: =SUM(AJ28*$Z$4) -> 2040 | AL28: =SUM(AJ28) -> 204 | AM28: =SUM(AL28*$Z$4) -> 2040 | AN28: =SUM(AO28/19600) -> 0.72857143 | AO28: =SUM(AA28+AC28+AE28+AG28+AI28+AK28+AM28) -> 14280 | AQ28: =SUM(AR28/92970) -> 0.63983422 | AR28: =Y28+AO28 -> 59485.387 | AS28: =SUM(AR28-AR27-AT28) -> 0 | AV28: =IF(AT28>0,AU28,AV27) -> 1.003 | AW28: =-SUM('B5'!AI27) -> 0 | AX28: =-SUM(AW28-AS28) -> 0 | AY28: =SUM(AX28+AW28) -> 0 | AZ28: =ELEC!A26 -> 0 | BA28: ='General information '!D28 -> 0 | BB28: =SUM('General information '!E28) -> 0 | BC28: =IF(AR27>=AR28,0,1) -> 0 | BD28: 19222 | BE28: =(305/1185)*ELEC!Q27 -> 0 | BG28: =#REF!-BE28 -> #REF!
... A32: =ELEC!C30 -> 44374 | B32: ='B5'!B31 -> 191 | C32: =B32*$B$4 -> 4109.5806 | D32: =SUM(B32) -> 191 | E32: =D32*$B$4 -> 4109.5806 | F32: =SUM(D32) -> 191 | G32: =F32*$B$4 -> 4109.5806 | H32: =SUM(F32) -> 191 | I32: =H32*$B$4 -> 4109.5806 | J32: =SUM(H32) -> 191 | K32: =J32*$B$4 -> 4109.5806 | L32: =SUM(J32) -> 191 | M32: =L32*$B$4 -> 4109.5806 | N32: =SUM(L32) -> 191 | O32: =N32*$B$4 -> 4109.5806 | P32: =SUM(N32) -> 191 | Q32: =P32*$B$4 -> 4109.5806 | R32: =SUM(P32) -> 191 | S32: =R32*$B$4 -> 4109.5806 | T32: =SUM(R32) -> 191 | U32: =T32*$B$4 -> 4109.5806 | V32: =SUM(T32) -> 191 | W32: =V32*$B$4 -> 4109.5806 | X32: =SUM(Y32/73370) -> 0.61612903 | Y32: =SUM(C32+E32+G32+I32+K32+M32+O32+Q32+S32+U32+W32) -> 45205.387 | Z32: ='B5'!C31 -> 204 | AA32: =SUM(Z32*$Z$4) -> 2040 | AB32: =SUM(Z32) -> 204 | AC32: =SUM(AB32*$Z$4) -> 2040 | AD32: =SUM(AB32) -> 204 | AE32: =SUM(AD32*$Z$4) -> 2040 | AF32: =SUM(AD32) -> 204 | AG32: =SUM(AF32*$Z$4) -> 2040 | AH32: =SUM(AF32) -> 204 | AI32: =SUM(AH32*$Z$4) -> 2040 | AJ32: =SUM(AH32) -> 204 | AK32: =SUM(AJ32*$Z$4) -> 2040 | AL32: =SUM(AJ32) -> 204 | AM32: =SUM(AL32*$Z$4) -> 2040 | AN32: =SUM(AO32/19600) -> 0.72857143 | AO32: =SUM(AA32+AC32+AE32+AG32+AI32+AK32+AM32) -> 14280 | AQ32: =SUM(AR32/92970) -> 0.63983422 | AR32: =Y32+AO32 -> 59485.387 | AS32: =SUM(AR32-AR31-AT32) -> 0 | AV32: =IF(AT32>0,AU32,AV31) -> 1.003 | AW32: =-SUM('B5'!AI31) -> 0 | AX32: =-SUM(AW32-AS32) -> 0 | AY32: =SUM(AX32+AW32) -> 0 | AZ32: =ELEC!A30 -> 0 | BA32: ='General information '!D32 -> 0 | BB32: =SUM('General information '!E32) -> 0 | BC32: =IF(AR31>=AR32,0,1) -> 0 | BD32: 19222 | BE32: =(305/1185)*ELEC!Q31 -> 0 | BG32: =#REF!-BE32 -> #REF!
A33: =ELEC!C31 -> 44375 | B33: ='B5'!B32 -> 191 | C33: =B33*$B$4 -> 4109.5806 | D33: =SUM(B33) -> 191 | E33: =D33*$B$4 -> 4109.5806 | F33: =SUM(D33) -> 191 | G33: =F33*$B$4 -> 4109.5806 | H33: =SUM(F33) -> 191 | I33: =H33*$B$4 -> 4109.5806 | J33: =SUM(H33) -> 191 | K33: =J33*$B$4 -> 4109.5806 | L33: =SUM(J33) -> 191 | M33: =L33*$B$4 -> 4109.5806 | N33: =SUM(L33) -> 191 | O33: =N33*$B$4 -> 4109.5806 | P33: =SUM(N33) -> 191 | Q33: =P33*$B$4 -> 4109.5806 | R33: =SUM(P33) -> 191 | S33: =R33*$B$4 -> 4109.5806 | T33: =SUM(R33) -> 191 | U33: =T33*$B$4 -> 4109.5806 | V33: =SUM(T33) -> 191 | W33: =V33*$B$4 -> 4109.5806 | X33: =SUM(Y33/73370) -> 0.61612903 | Y33: =SUM(C33+E33+G33+I33+K33+M33+O33+Q33+S33+U33+W33) -> 45205.387 | Z33: ='B5'!C32 -> 204 | AA33: =SUM(Z33*$Z$4) -> 2040 | AB33: =SUM(Z33) -> 204 | AC33: =SUM(AB33*$Z$4) -> 2040 | AD33: =SUM(AB33) -> 204 | AE33: =SUM(AD33*$Z$4) -> 2040 | AF33: =SUM(AD33) -> 204 | AG33: =SUM(AF33*$Z$4) -> 2040 | AH33: =SUM(AF33) -> 204 | AI33: =SUM(AH33*$Z$4) -> 2040 | AJ33: =SUM(AH33) -> 204 | AK33: =SUM(AJ33*$Z$4) -> 2040 | AL33: =SUM(AJ33) -> 204 | AM33: =SUM(AL33*$Z$4) -> 2040 | AN33: =SUM(AO33/19600) -> 0.72857143 | AO33: =SUM(AA33+AC33+AE33+AG33+AI33+AK33+AM33) -> 14280 | AQ33: =SUM(AR33/92970) -> 0.63983422 | AR33: =Y33+AO33 -> 59485.387 | AS33: =SUM(AR33-AR32-AT33) -> 0 | AV33: =IF(AT33>0,AU33,AV32) -> 1.003 | AW33: =-SUM('B5'!AI32) -> 0 | AX33: =-SUM(AW33-AS33) -> 0 | AY33: =SUM(AX33+AW33) -> 0 | AZ33: =ELEC!A31 -> 0 | BA33: ='General information '!D33 -> 0 | BB33: =SUM('General information '!E33) -> 0 | BC33: =IF(AR32>=AR33,0,1) -> 0 | BD33: 19222 | BE33: =(305/1185)*ELEC!#REF! -> #REF! | BG33: =#REF!-BE33 -> #REF!
A34: =ELEC!C32 -> 44376 | B34: ='B5'!B33 -> 191 | C34: =B34*$B$4 -> 4109.5806 | D34: =SUM(B34) -> 191 | E34: =D34*$B$4 -> 4109.5806 | F34: =SUM(D34) -> 191 | G34: =F34*$B$4 -> 4109.5806 | H34: =SUM(F34) -> 191 | I34: =H34*$B$4 -> 4109.5806 | J34: =SUM(H34) -> 191 | K34: =J34*$B$4 -> 4109.5806 | L34: =SUM(J34) -> 191 | M34: =L34*$B$4 -> 4109.5806 | N34: =SUM(L34) -> 191 | O34: =N34*$B$4 -> 4109.5806 | P34: =SUM(N34) -> 191 | Q34: =P34*$B$4 -> 4109.5806 | R34: =SUM(P34) -> 191 | S34: =R34*$B$4 -> 4109.5806 | T34: =SUM(R34) -> 191 | U34: =T34*$B$4 -> 4109.5806 | V34: =SUM(T34) -> 191 | W34: =V34*$B$4 -> 4109.5806 | X34: =SUM(Y34/73370) -> 0.61612903 | Y34: =SUM(C34+E34+G34+I34+K34+M34+O34+Q34+S34+U34+W34) -> 45205.387 | Z34: ='B5'!C33 -> 204 | AA34: =SUM(Z34*$Z$4) -> 2040 | AB34: =SUM(Z34) -> 204 | AC34: =SUM(AB34*$Z$4) -> 2040 | AD34: =SUM(AB34) -> 204 | AE34: =SUM(AD34*$Z$4) -> 2040 | AF34: =SUM(AD34) -> 204 | AG34: =SUM(AF34*$Z$4) -> 2040 | AH34: =SUM(AF34) -> 204 | AI34: =SUM(AH34*$Z$4) -> 2040 | AJ34: =SUM(AH34) -> 204 | AK34: =SUM(AJ34*$Z$4) -> 2040 | AL34: =SUM(AJ34) -> 204 | AM34: =SUM(AL34*$Z$4) -> 2040 | AN34: =SUM(AO34/19600) -> 0.72857143 | AO34: =SUM(AA34+AC34+AE34+AG34+AI34+AK34+AM34) -> 14280 | AQ34: =SUM(AR34/92970) -> 0.63983422 | AR34: =Y34+AO34 -> 59485.387 | AS34: =SUM(AR34-AR33-AT34) -> 0 | AV34: =IF(AT34>0,AU34,AV33) -> 1.003 | AW34: =-SUM('B5'!AI33) -> 0 | AX34: =-SUM(AW34-AS34) -> 0 | AY34: =SUM(AX34+AW34) -> 0 | AZ34: =ELEC!A32 -> 0 | BA34: ='General information '!D34 -> 0 | BB34: =SUM('General information '!E34) -> 0
A35: =ELEC!C33 -> 44377 | B35: ='B5'!B34 -> 191 | C35: =B35*$B$4 -> 4109.5806 | D35: =SUM(B35) -> 191 | E35: =D35*$B$4 -> 4109.5806 | F35: =SUM(D35) -> 191 | G35: =F35*$B$4 -> 4109.5806 | H35: =SUM(F35) -> 191 | I35: =H35*$B$4 -> 4109.5806 | J35: =SUM(H35) -> 191 | K35: =J35*$B$4 -> 4109.5806 | L35: =SUM(J35) -> 191 | M35: =L35*$B$4 -> 4109.5806 | N35: =SUM(L35) -> 191 | O35: =N35*$B$4 -> 4109.5806 | P35: =SUM(N35) -> 191 | Q35: =P35*$B$4 -> 4109.5806 | R35: =SUM(P35) -> 191 | S35: =R35*$B$4 -> 4109.5806 | T35: =SUM(R35) -> 191 | U35: =T35*$B$4 -> 4109.5806 | V35: =SUM(T35) -> 191 | W35: =V35*$B$4 -> 4109.5806 | X35: =SUM(Y35/73370) -> 0.61612903 | Y35: =SUM(C35+E35+G35+I35+K35+M35+O35+Q35+S35+U35+W35) -> 45205.387 | Z35: ='B5'!C34 -> 204 | AA35: =SUM(Z35*$Z$4) -> 2040 | AB35: =SUM(Z35) -> 204 | AC35: =SUM(AB35*$Z$4) -> 2040 | AD35: =SUM(AB35) -> 204 | AE35: =SUM(AD35*$Z$4) -> 2040 | AF35: =SUM(AD35) -> 204 | AG35: =SUM(AF35*$Z$4) -> 2040 | AH35: =SUM(AF35) -> 204 | AI35: =SUM(AH35*$Z$4) -> 2040 | AJ35: =SUM(AH35) -> 204 | AK35: =SUM(AJ35*$Z$4) -> 2040 | AL35: =SUM(AJ35) -> 204 | AM35: =SUM(AL35*$Z$4) -> 2040 | AN35: =SUM(AO35/19600) -> 0.72857143 | AO35: =SUM(AA35+AC35+AE35+AG35+AI35+AK35+AM35) -> 14280 | AQ35: =SUM(AR35/92970) -> 0.63983422 | AR35: =Y35+AO35 -> 59485.387 | AS35: =SUM(AR35-AR34-AT35) -> 0 | AV35: =IF(AT35>0,AU35,AV34) -> 1.003 | AW35: =-SUM('B5'!AI34) -> 0 | AX35: =-SUM(AW35-AS35) -> 0 | AY35: =SUM(AX35+AW35) -> 0 | AZ35: =ELEC!A33 -> 0 | BA35: ='General information '!D35 -> 0 | BB35: =SUM('General information '!E35) -> 0
AR36: NB delivery | AS36: =COUNT(AT6:AT35) -> 0 | AT36: =SUM(AT6:AT35) -> 0 | AU36: =SUM(AU6:AU35)/AS36 -> #DIV/0! | AX36: =SUM(AX6:AX35) -> -4486.8387 | AY36: =SUM(AY6:AY35) -> -4486.8387
AT37: =+AT36*AU36 -> #DIV/0!
AS39: =SUM(AS6:AS35)/'EDl log'!A35 -> -4486.8387
AX40: 43309
AX41: =AX36/AX40 -> -0.10360061

Sheet EDl log
A1: Date | B1: EDL | C1: Conso EDL KW | F1: Peak | G1: 320 | H1: Day | I1: 112 | J1: Night | K1: 80
L2: P | M2: D | N2: N | O2: fee | P2: T EDL | Q2: Gen | R2: Elc C
A3: =ELEC!C3 -> 44347 | B3: ='[2]EDl log'!B34 -> 1057796 | C3: ='[2]EDl log'!C34 -> 1319 | D3: ='[2]EDl log'!D34 -> 1320 | E3: ='[2]EDl log'!E34 -> 1057797 | F3: ='[2]EDl log'!F34 -> 156087 | G3: ='[2]EDl log'!G34 -> 176 | H3: ='[2]EDl log'!H34 -> 515542 | I3: ='[2]EDl log'!I34 -> 551 | ... T3: ='[2]EDl log'!T34 -> 0.20289124 | Z3: VAT | AA3: 0.1
A4: =ELEC!C4 -> 44348 | B4: 1058175 | C4: =SUM(B4-B3) -> 379 | D4: =SUM(G4+I4+K4) -> 379 | E4: =B3+D4 -> 1058175 | F4: 156087 | G4: =F4-F3 -> 0 | H4: 515845 | I4: =H4-H3 -> 303 | J4: 386243 | K4: =J4-J3 -> 76 | L4: =SUM(G4*$Y$28)/1507.5 -> 0 | M4: =SUM(I4*$Y$27)/1507.5 -> 22.511443 | N4: =SUM(K4*$Y$26)/1507.5 -> 4.0331675 | O4: =($AC$29/$A$37)/1507.5 -> 159.96314 | P4: =SUM(L4:O4) -> 186.50775 | Q4: =SUM(-tanks!AX6*tanks!$AU$36) -> #DIV/0! | R4: =SUM(P4:Q4) -> #DIV/0! | S4: =SUM(ELEC!N4) -> 9940 | T4: =IF(S4>0,R4/S4,0) -> #DIV/0! | V4: ='[6]EDl log'!V21 -> EDL | W4: 44317 | Z4: Subscription
A5: =ELEC!C5 -> 44349 | B5: =B4 -> 1058175 | C5: =SUM(B5-B4) -> 0 | D5: =SUM(G5+I5+K5) -> 0 | E5: =B4+D5 -> 1058175 | F5: =F4 -> 156087 | G5: =F5-F4 -> 0 | H5: =H4 -> 515845 | I5: =H5-H4 -> 0 | J5: =J4 -> 386243 | K5: =J5-J4 -> 0 | L5: =SUM(G5*$Y$28)/1507.5 -> 0 | M5: =SUM(I5*$Y$27)/1507.5 -> 0 | N5: =SUM(K5*$Y$26)/1507.5 -> 0 | O5: =($AC$29/$A$37)/1507.5 -> 159.96314 | P5: =SUM(L5:O5) -> 159.96314 | Q5: =SUM(-tanks!AX7*tanks!$AU$36) -> #DIV/0! | R5: =SUM(P5:Q5) -> #DIV/0! | S5: =SUM(ELEC!N5) -> 0 | T5: =IF(S5>0,R5/S5,0) -> 0 | Z5: KVA | AA5: ='[7]EDl log'!AA22 -> 5000
A6: =ELEC!C6 -> 44350 | B6: =B5 -> 1058175 | C6: =SUM(B6-B5) -> 0 | D6: =SUM(G6+I6+K6) -> 0 | E6: =B5+D6 -> 1058175 | F6: =F5 -> 156087 | G6: =F6-F5 -> 0 | H6: =H5 -> 515845 | I6: =H6-H5 -> 0 | J6: =J5 -> 386243 | K6: =J6-J5 -> 0 | L6: =SUM(G6*$Y$28)/1507.5 -> 0 | M6: =SUM(I6*$Y$27)/1507.5 -> 0 | N6: =SUM(K6*$Y$26)/1507.5 -> 0 | O6: =($AC$29/$A$37)/1507.5 -> 159.96314 | P6: =SUM(L6:O6) -> 159.96314 | Q6: =SUM(-tanks!AX8*tanks!$AU$36) -> #DIV/0! | R6: =SUM(P6:Q6) -> #DIV/0! | S6: =SUM(ELEC!N6) -> 0 | T6: =IF(S6>0,R6/S6,0) -> 0
A7: =ELEC!C7 -> 44351 | B7: =B6 -> 1058175 | C7: =SUM(B7-B6) -> 0 | D7: =SUM(G7+I7+K7) -> 0 | E7: =B6+D7 -> 1058175 | F7: =F6 -> 156087 | G7: =F7-F6 -> 0 | H7: =H6 -> 515845 | I7: =H7-H6 -> 0 | J7: =J6 -> 386243 | K7: =J7-J6 -> 0 | L7: =SUM(G7*$Y$28)/1507.5 -> 0 | M7: =SUM(I7*$Y$27)/1507.5 -> 0 | N7: =SUM(K7*$Y$26)/1507.5 -> 0 | O7: =($AC$29/$A$37)/1507.5 -> 159.96314 | P7: =SUM(L7:O7) -> 159.96314 | Q7: =SUM(-tanks!AX9*tanks!$AU$36) -> #DIV/0! | R7: =SUM(P7:Q7) -> #DIV/0! | S7: =SUM(ELEC!N7) -> 0 | T7: =IF(S7>0,R7/S7,0) -> 0 | V7: Electricity consumption | X7: Price LL
A8: =ELEC!C8 -> 44352 | B8: =B7 -> 1058175 | C8: =SUM(B8-B7) -> 0 | D8: =SUM(G8+I8+K8) -> 0 | E8: =B7+D8 -> 1058175 | F8: =F7 -> 156087 | G8: =F8-F7 -> 0 | H8: =H7 -> 515845 | I8: =H8-H7 -> 0 | J8: =J7 -> 386243 | K8: =J8-J7 -> 0 | L8: =SUM(G8*$Y$28)/1507.5 -> 0 | M8: =SUM(I8*$Y$27)/1507.5 -> 0 | N8: =SUM(K8*$Y$26)/1507.5 -> 0 | O8: =($AC$29/$A$37)/1507.5 -> 159.96314 | P8: =SUM(L8:O8) -> 159.96314 | Q8: =SUM(-tanks!AX10*tanks!$AU$36) -> #DIV/0! | R8: =SUM(P8:Q8) -> #DIV/0! | S8: =SUM(ELEC!N8) -> 0 | T8: =IF(S8>0,R8/S8,0) -> 0 | V8: Index in | W8: Index Out | Y8: Kwh Cost | Z8: K | AA8: Kwh | AB8: ='[8]EDl log'!AB25 -> Total cost LL | AC8: Fees
A9: =ELEC!C9 -> 44353 | B9: =B8 -> 1058175 | C9: =SUM(B9-B8) -> 0 | D9: =SUM(G9+I9+K9) -> 0 | E9: =B8+D9 -> 1058175 | F9: =F8 -> 156087 | G9: =F9-F8 -> 0 | H9: =H8 -> 515845 | I9: =H9-H8 -> 0 | J9: =J8 -> 386243 | K9: =J9-J8 -> 0 | L9: =SUM(G9*$Y$28)/1507.5 -> 0 | M9: =SUM(I9*$Y$27)/1507.5 -> 0 | N9: =SUM(K9*$Y$26)/1507.5 -> 0 | O9: =($AC$29/$A$37)/1507.5 -> 159.96314 | P9: =SUM(L9:O9) -> 159.96314 | Q9: =SUM(-tanks!AX11*tanks!$AU$36) -> #DIV/0! | R9: =SUM(P9:Q9) -> #DIV/0! | S9: =SUM(ELEC!N9) -> 0 | T9: =IF(S9>0,R9/S9,0) -> 0 | V9: ='[2]EDl log'!V26 -> 365756 | W9: ='[2]EDl log'!W26 -> 386167 | X9: Night | Y9: ='[2]EDl log'!Y26 -> 80 | Z9: 1 | AA9: ='[2]EDl log'!AA26 -> 20411 | AB9: ='[2]EDl log'!AB26 -> 1632880 | AC9: ='[2]EDl log'!AC26 -> 1033333 | AD9: ='[2]EDl log'!AD26 -> 0.41575933
A10: =ELEC!C10 -> 44354 | B10: =B9 -> 1058175 | C10: =SUM(B10-B9) -> 0 | D10: =SUM(G10+I10+K10) -> 0 | E10: =B9+D10 -> 1058175 | F10: =F9 -> 156087 | G10: =F10-F9 -> 0 | H10: =H9 -> 515845 | I10: =H10-H9 -> 0 | J10: =J9 -> 386243 | K10: =J10-J9 -> 0 | L10: =SUM(G10*$Y$28)/1507.5 -> 0 | M10: =SUM(I10*$Y$27)/1507.5 -> 0 | N10: =SUM(K10*$Y$26)/1507.5 -> 0 | O10: =($AC$29/$A$37)/1507.5 -> 159.96314 | P10: =SUM(L10:O10) -> 159.96314 | Q10: =SUM(-tanks!AX12*tanks!$AU$36) -> #DIV/0! | R10: =SUM(P10:Q10) -> #DIV/0! | S10: =SUM(ELEC!N10) -> 0 | T10: =IF(S10>0,R10/S10,0) -> 0 | V10: ='[2]EDl log'!V27 -> 492400 | W10: ='[2]EDl log'!W27 -> 515542 | X10: day | Y10: ='[2]EDl log'!Y27 -> 112 | Z10: 1 | AA10: ='[2]EDl log'!AA27 -> 23142 | AB10: ='[2]EDl log'!AB27 -> 2591904 | AC10: ='[2]EDl log'!AC27 -> 6200000 | AD10: ='[2]EDl log'!AD27 -> 0.47393375
A11: =ELEC!C11 -> 44355 | B11: =B10 -> 1058175 | C11: =SUM(B11-B10) -> 0 | D11: =SUM(G11+I11+K11) -> 0 | E11: =B10+D11 -> 1058175 | F11: =F10 -> 156087 | G11: =F11-F10 -> 0 | H11: =H10 -> 515845 | I11: =H11-H10 -> 0 | J11: =J10 -> 386243 | K11: =J11-J10 -> 0 | L11: =SUM(G11*$Y$28)/1507.5 -> 0 | M11: =SUM(I11*$Y$27)/1507.5 -> 0 | N11: =SUM(K11*$Y$26)/1507.5 -> 0 | O11: =($AC$29/$A$37)/1507.5 -> 159.96314 | P11: =SUM(L11:O11) -> 159.96314 | Q11: =SUM(-tanks!AX13*tanks!$AU$36) -> #DIV/0! | R11: =SUM(P11:Q11) -> #DIV/0! | S11: =SUM(ELEC!N11) -> 0 | T11: =IF(S11>0,R11/S11,0) -> 0 | V11: ='[2]EDl log'!V28 -> 150653 | W11: ='[2]EDl log'!W28 -> 156087 | X11: Peak | Y11: ='[2]EDl log'!Y28 -> 320 | Z11: 1 | AA11: ='[2]EDl log'!AA28 -> 5434 | AB11: ='[2]EDl log'!AB28 -> 1738880 | AC11: ='[2]EDl log'!AC28 -> 1000 | AD11: ='[2]EDl log'!AD28 -> 0.11030692 | AE11: ='[2]EDl log'!AE28 -> 86944 | AF11: ='[2]EDl log'!AF28 -> 385037.71
A12: =ELEC!C12 -> 44356 | B12: =B11 -> 1058175 | C12: =SUM(B12-B11) -> 0 | D12: =SUM(G12+I12+K12) -> 0 | E12: =B11+D12 -> 1058175 | F12: =F11 -> 156087 | G12: =F12-F11 -> 0 | H12: =H11 -> 515845 | I12: =H12-H11 -> 0 | J12: =J11 -> 386243 | K12: =J12-J11 -> 0 | L12: =SUM(G12*$Y$28)/1507.5 -> 0 | M12: =SUM(I12*$Y$27)/1507.5 -> 0 | N12: =SUM(K12*$Y$26)/1507.5 -> 0 | O12: =($AC$29/$A$37)/1507.5 -> 159.96314 | P12: =SUM(L12:O12) -> 159.96314 | Q12: =SUM(-tanks!AX14*tanks!$AU$36) -> #DIV/0! | R12: =SUM(P12:Q12) -> #DIV/0! | S12: =SUM(ELEC!N12) -> 0 | T12: =IF(S12>0,R12/S12,0) -> 0 | AA12: ='[2]EDl log'!AA29 -> 48987 | AB12: ='[2]EDl log'!AB29 -> 0 | AC12: ='[2]EDl log'!AC29 -> 7234333
A13: =ELEC!C13 -> 44357 | B13: =B12 -> 1058175 | C13: =SUM(B13-B12) -> 0 | D13: =SUM(G13+I13+K13) -> 0 | E13: =B12+D13 -> 1058175 | F13: =F12 -> 156087 | G13: =F13-F12 -> 0 | H13: =H12 -> 515845 | I13: =H13-H12 -> 0 | J13: =J12 -> 386243 | K13: =J13-J12 -> 0 | L13: =SUM(G13*$Y$28)/1507.5 -> 0 | M13: =SUM(I13*$Y$27)/1507.5 -> 0 | N13: =SUM(K13*$Y$26)/1507.5 -> 0 | O13: =($AC$29/$A$37)/1507.5 -> 159.96314 | P13: =SUM(L13:O13) -> 159.96314 | Q13: =SUM(-tanks!AX15*tanks!$AU$36) -> #DIV/0! | R13: =SUM(P13:Q13) -> #DIV/0! | S13: =SUM(ELEC!N13) -> 0 | T13: =IF(S13>0,R13/S13,0) -> 0 | V13: ='[7]EDl log'!V30 -> Occ % | W13: ='[9]EDl log'!W30 -> 0 | Y13: ='[10]EDl log'!Y30 -> Per G | AB13: ='[2]EDl log'!AB30 -> 5963664 | AC13: ='[2]EDl log'!AC30 -> 0
A14: =ELEC!C14 -> 44358 | B14: =B13 -> 1058175 | C14: =SUM(B14-B13) -> 0 | D14: =SUM(G14+I14+K14) -> 0 | E14: =B13+D14 -> 1058175 | F14: =F13 -> 156087 | G14: =F14-F13 -> 0 | H14: =H13 -> 515845 | I14: =H14-H13 -> 0 | J14: =J13 -> 386243 | K14: =J14-J13 -> 0 | L14: =SUM(G14*$Y$28)/1507.5 -> 0 | M14: =SUM(I14*$Y$27)/1507.5 -> 0 | N14: =SUM(K14*$Y$26)/1507.5 -> 0 | O14: =($AC$29/$A$37)/1507.5 -> 159.96314 | P14: =SUM(L14:O14) -> 159.96314 | Q14: =SUM(-tanks!AX16*tanks!$AU$36) -> #DIV/0! | R14: =SUM(P14:Q14) -> #DIV/0! | S14: =SUM(ELEC!N14) -> 0 | T14: =IF(S14>0,R14/S14,0) -> 0 | V14: ='[7]EDl log'!V31 -> Gen RH | W14: ='[2]EDl log'!$W$33 -> 339 | X14: ='[2]EDl log'!$X$33 -> 10.935484 | Y14: ='[2]EDl log'!$Y$33 -> 10.935484 | AB14: ='[2]EDl log'!AB31 -> 0 | AC14: ='[2]EDl log'!AC31 -> 0
A15: =ELEC!C15 -> 44359 | B15: =B14 -> 1058175 | C15: =SUM(B15-B14) -> 0 | D15: =SUM(G15+I15+K15) -> 0 | E15: =B14+D15 -> 1058175 | F15: =F14 -> 156087 | G15: =F15-F14 -> 0 | H15: =H14 -> 515845 | I15: =H15-H14 -> 0 | J15: =J14 -> 386243 | K15: =J15-J14 -> 0 | L15: =SUM(G15*$Y$28)/1507.5 -> 0 | M15: =SUM(I15*$Y$27)/1507.5 -> 0 | N15: =SUM(K15*$Y$26)/1507.5 -> 0 | O15: =($AC$29/$A$37)/1507.5 -> 159.96314 | P15: =SUM(L15:O15) -> 159.96314 | Q15: =SUM(-tanks!AX17*tanks!$AU$36) -> #DIV/0! | R15: =SUM(P15:Q15) -> #DIV/0! | S15: =SUM(ELEC!N15) -> 0 | T15: =IF(S15>0,R15/S15,0) -> 0 | V15: ='[7]EDl log'!V32 -> H Deg | W15: ='[11]Degree Days 2020'!$N$43 -> -30.3 | AB15: ='[2]EDl log'!AB32 -> 0 | AC15: ='[2]EDl log'!AC32 -> 0
A16: =ELEC!C16 -> 44360 | B16: =B15 -> 1058175 | C16: =SUM(B16-B15) -> 0 | D16: =SUM(G16+I16+K16) -> 0 | E16: =B15+D16 -> 1058175 | F16: =F15 -> 156087 | G16: =F16-F15 -> 0 | H16: =H15 -> 515845 | I16: =H16-H15 -> 0 | J16: =J15 -> 386243 | K16: =J16-J15 -> 0 | L16: =SUM(G16*$Y$28)/1507.5 -> 0 | M16: =SUM(I16*$Y$27)/1507.5 -> 0 | N16: =SUM(K16*$Y$26)/1507.5 -> 0 | O16: =($AC$29/$A$37)/1507.5 -> 159.96314 | P16: =SUM(L16:O16) -> 159.96314 | Q16: =SUM(-tanks!AX18*tanks!$AU$36) -> #DIV/0! | R16: =SUM(P16:Q16) -> #DIV/0! | S16: =SUM(ELEC!N16) -> 0 | T16: =IF(S16>0,R16/S16,0) -> 0 | V16: ='[7]EDl log'!V33 -> C Deg | W16: ='[11]Degree Days 2020'!$O$43 -> 45.4 | AB16: ='[2]EDl log'!AB33 -> 13197997 | AC16: ='[2]EDl log'!AC33 -> 7234333
A17: =ELEC!C17 -> 44361 | B17: =B16 -> 1058175 | C17: =SUM(B17-B16) -> 0 | D17: =SUM(G17+I17+K17) -> 0 | E17: =B16+D17 -> 1058175 | F17: =F16 -> 156087 | G17: =F17-F16 -> 0 | H17: =H16 -> 515845 | I17: =H17-H16 -> 0 | J17: =J16 -> 386243 | K17: =J17-J16 -> 0 | L17: =SUM(G17*$Y$28)/1507.5 -> 0 | M17: =SUM(I17*$Y$27)/1507.5 -> 0 | N17: =SUM(K17*$Y$26)/1507.5 -> 0 | O17: =($AC$29/$A$37)/1507.5 -> 159.96314 | P17: =SUM(L17:O17) -> 159.96314 | Q17: =SUM(-tanks!AX19*tanks!$AU$36) -> #DIV/0! | R17: =SUM(P17:Q17) -> #DIV/0! | S17: =SUM(ELEC!N17) -> 0 | T17: =IF(S17>0,R17/S17,0) -> 0 | Z17: Vat | AA17: ='[12]EDl log'!AA34 -> 0.11 | AB17: ='[2]EDl log'!AB34 -> 0 | AC17: ='[13]EDl log'!AC34 -> 0
A18: =ELEC!C18 -> 44362 | B18: =B17 -> 1058175 | C18: =SUM(B18-B17) -> 0 | D18: =SUM(G18+I18+K18) -> 0 | E18: =B17+D18 -> 1058175 | F18: =F17 -> 156087 | G18: =F18-F17 -> 0 | H18: =H17 -> 515845 | I18: =H18-H17 -> 0 | J18: =J17 -> 386243 | K18: =J18-J17 -> 0 | L18: =SUM(G18*$Y$28)/1507.5 -> 0 | M18: =SUM(I18*$Y$27)/1507.5 -> 0 | N18: =SUM(K18*$Y$26)/1507.5 -> 0 | O18: =($AC$29/$A$37)/1507.5 -> 159.96314 | P18: =SUM(L18:O18) -> 159.96314 | Q18: =SUM(-tanks!AX20*tanks!$AU$36) -> #DIV/0! | R18: =SUM(P18:Q18) -> #DIV/0! | S18: =SUM(ELEC!N18) -> 0 | T18: =IF(S18>0,R18/S18,0) -> 0 | AB18: ='[2]EDl log'!AB35 -> 0 | AC18: ='[13]EDl log'!AC35 -> 0
A19: =ELEC!C19 -> 44363 | B19: =B18 -> 1058175 | C19: =SUM(B19-B18) -> 0 | D19: =SUM(G19+I19+K19) -> 0 | E19: =B18+D19 -> 1058175 | F19: =F18 -> 156087 | G19: =F19-F18 -> 0 | H19: =H18 -> 515845 | I19: =H19-H18 -> 0 | J19: =J18 -> 386243 | K19: =J19-J18 -> 0 | L19: =SUM(G19*$Y$28)/1507.5 -> 0 | M19: =SUM(I19*$Y$27)/1507.5 -> 0 | N19: =SUM(K19*$Y$26)/1507.5 -> 0 | O19: =($AC$29/$A$37)/1507.5 -> 159.96314 | P19: =SUM(L19:O19) -> 159.96314 | Q19: =SUM(-tanks!AX21*tanks!$AU$36) -> #DIV/0! | R19: =SUM(P19:Q19) -> #DIV/0! | S19: =SUM(ELEC!N19) -> 0 | T19: =IF(S19>0,R19/S19,0) -> 0 | AB19: ='[2]EDl log'!AB36 -> 8754.8902 | AC19: ='[13]EDl log'!AC36 -> 0
A20: =ELEC!C20 -> 44364 | B20: =B19 -> 1058175 | C20: =SUM(B20-B19) -> 0 | D20: =SUM(G20+I20+K20) -> 0 | E20: =B19+D20 -> 1058175 | F20: =F19 -> 156087 | G20: =F20-F19 -> 0 | H20: =H19 -> 515845 | I20: =H20-H19 -> 0 | J20: =J19 -> 386243 | K20: =J20-J19 -> 0 | L20: =SUM(G20*$Y$28)/1507.5 -> 0 | M20: =SUM(I20*$Y$27)/1507.5 -> 0 | N20: =SUM(K20*$Y$26)/1507.5 -> 0 | O20: =($AC$29/$A$37)/1507.5 -> 159.96314 | P20: =SUM(L20:O20) -> 159.96314 | Q20: =SUM(-tanks!AX22*tanks!$AU$36) -> #DIV/0! | R20: =SUM(P20:Q20) -> #DIV/0! | S20: =SUM(ELEC!N20) -> 0 | T20: =IF(S20>0,R20/S20,0) -> 0 | V20: Before new counter
A21: =ELEC!C21 -> 44365 | B21: =B20 -> 1058175 | C21: =SUM(B21-B20) -> 0 | D21: =SUM(G21+I21+K21) -> 0 | E21: =B20+D21 -> 1058175 | F21: =F20 -> 156087 | G21: =F21-F20 -> 0 | H21: =H20 -> 515845 | I21: =H21-H20 -> 0 | J21: =J20 -> 386243 | K21: =J21-J20 -> 0 | L21: =SUM(G21*$Y$28)/1507.5 -> 0 | M21: =SUM(I21*$Y$27)/1507.5 -> 0 | N21: =SUM(K21*$Y$26)/1507.5 -> 0 | O21: =($AC$29/$A$37)/1507.5 -> 159.96314 | P21: =SUM(L21:O21) -> 159.96314 | Q21: =SUM(-tanks!AX23*tanks!$AU$36) -> #DIV/0! | R21: =SUM(P21:Q21) -> #DIV/0! | S21: =SUM(ELEC!N21) -> 0 | T21: =IF(S21>0,R21/S21,0) -> 0 | V21: EDL | W21: 44348 | Z21: Subscription
A22: =ELEC!C22 -> 44366 | B22: =B21 -> 1058175 | C22: =SUM(B22-B21) -> 0 | D22: =SUM(G22+I22+K22) -> 0 | E22: =B21+D22 -> 1058175 | F22: =F21 -> 156087 | G22: =F22-F21 -> 0 | H22: =H21 -> 515845 | I22: =H22-H21 -> 0 | J22: =J21 -> 386243 | K22: =J22-J21 -> 0 | L22: =SUM(G22*$Y$28)/1507.5 -> 0 | M22: =SUM(I22*$Y$27)/1507.5 -> 0 | N22: =SUM(K22*$Y$26)/1507.5 -> 0 | O22: =($AC$29/$A$37)/1507.5 -> 159.96314 | P22: =SUM(L22:O22) -> 159.96314 | Q22: =SUM(-tanks!AX24*tanks!$AU$36) -> #DIV/0! | R22: =SUM(P22:Q22) -> #DIV/0! | S22: =SUM(ELEC!N22) -> 0 | T22: =IF(S22>0,R22/S22,0) -> 0 | Z22: KVA | AA22: 5000
A23: =ELEC!C23 -> 44367 | B23: =B22 -> 1058175 | C23: =SUM(B23-B22) -> 0 | D23: =SUM(G23+I23+K23) -> 0 | E23: =B22+D23 -> 1058175 | F23: =F22 -> 156087 | G23: =F23-F22 -> 0 | H23: =H22 -> 515845 | I23: =H23-H22 -> 0 | J23: =J22 -> 386243 | K23: =J23-J22 -> 0 | L23: =SUM(G23*$Y$28)/1507.5 -> 0 | M23: =SUM(I23*$Y$27)/1507.5 -> 0 | N23: =SUM(K23*$Y$26)/1507.5 -> 0 | O23: =($AC$29/$A$37)/1507.5 -> 159.96314 | P23: =SUM(L23:O23) -> 159.96314 | Q23: =SUM(-tanks!AX25*tanks!$AU$36) -> #DIV/0! | R23: =SUM(P23:Q23) -> #DIV/0! | S23: =SUM(ELEC!N23) -> 0 | T23: =IF(S23>0,R23/S23,0) -> 0
A24: =ELEC!C24 -> 44368 | B24: =B23 -> 1058175 | C24: =SUM(B24-B23) -> 0 | D24: =SUM(G24+I24+K24) -> 0 | E24: =B23+D24 -> 1058175 | F24: =F23 -> 156087 | G24: =F24-F23 -> 0 | H24: =H23 -> 515845 | I24: =H24-H23 -> 0 | J24: =J23 -> 386243 | K24: =J24-J23 -> 0 | L24: =SUM(G24*$Y$28)/1507.5 -> 0 | M24: =SUM(I24*$Y$27)/1507.5 -> 0 | N24: =SUM(K24*$Y$26)/1507.5 -> 0 | O24: =($AC$29/$A$37)/1507.5 -> 159.96314 | P24: =SUM(L24:O24) -> 159.96314 | Q24: =SUM(-tanks!AX26*tanks!$AU$36) -> #DIV/0! | R24: =SUM(P24:Q24) -> #DIV/0! | S24: =SUM(ELEC!N24) -> 0 | T24: =IF(S24>0,R24/S24,0) -> 0 | V24: Electricity consumption | X24: Price LL
A25: =ELEC!C25 -> 44369 | B25: =B24 -> 1058175 | C25: =SUM(B25-B24) -> 0 | D25: =SUM(G25+I25+K25) -> 0 | E25: =B24+D25 -> 1058175 | F25: =F24 -> 156087 | G25: =F25-F24 -> 0 | H25: =H24 -> 515845 | I25: =H25-H24 -> 0 | J25: =J24 -> 386243 | K25: =J25-J24 -> 0 | L25: =SUM(G25*$Y$28)/1507.5 -> 0 | M25: =SUM(I25*$Y$27)/1507.5 -> 0 | N25: =SUM(K25*$Y$26)/1507.5 -> 0 | O25: =($AC$29/$A$37)/1507.5 -> 159.96314 | P25: =SUM(L25:O25) -> 159.96314 | Q25: =SUM(-tanks!AX27*tanks!$AU$36) -> #DIV/0! | R25: =SUM(P25:Q25) -> #DIV/0! | S25: =SUM(ELEC!N25) -> 0 | T25: =IF(S25>0,R25/S25,0) -> 0 | V25: Index in | W25: Index Out | Y25: Kwh Cost | Z25: K | AA25: Kwh | AB25: Total cost LL | AC25: Fees
A26: =ELEC!C26 -> 44370 | B26: =B25 -> 1058175 | C26: =SUM(B26-B25) -> 0 | D26: =SUM(G26+I26+K26) -> 0 | E26: =B25+D26 -> 1058175 | F26: =F25 -> 156087 | G26: =F26-F25 -> 0 | H26: =H25 -> 515845 | I26: =H26-H25 -> 0 | J26: =J25 -> 386243 | K26: =J26-J25 -> 0 | L26: =SUM(G26*$Y$28)/1507.5 -> 0 | M26: =SUM(I26*$Y$27)/1507.5 -> 0 | N26: =SUM(K26*$Y$26)/1507.5 -> 0 | O26: =($AC$29/$A$37)/1507.5 -> 159.96314 | P26: =SUM(L26:O26) -> 159.96314 | Q26: =SUM(-tanks!AX28*tanks!$AU$36) -> #DIV/0! | R26: =SUM(P26:Q26) -> #DIV/0! | S26: =SUM(ELEC!N26) -> 0 | T26: =IF(S26>0,R26/S26,0) -> 0 | V26: =W9 -> 386167 | W26: =J33 -> 386243 | X26: Night | Y26: 80 | Z26: 1 | AA26: =(W26-V26)*Z26 -> 76 | AB26: =AA26*Y26 -> 6080 | AC26: =AC9 -> 1033333 | AD26: =SUM(K36) -> 0.2005277
A27: =ELEC!C27 -> 44371 | B27: =B26 -> 1058175 | C27: =SUM(B27-B26) -> 0 | D27: =SUM(G27+I27+K27) -> 0 | E27: =B26+D27 -> 1058175 | F27: =F26 -> 156087 | G27: =F27-F26 -> 0 | H27: =H26 -> 515845 | I27: =H27-H26 -> 0 | J27: =J26 -> 386243 | K27: =J27-J26 -> 0 | L27: =SUM(G27*$Y$28)/1507.5 -> 0 | M27: =SUM(I27*$Y$27)/1507.5 -> 0 | N27: =SUM(K27*$Y$26)/1507.5 -> 0 | O27: =($AC$29/$A$37)/1507.5 -> 159.96314 | P27: =SUM(L27:O27) -> 159.96314 | Q27: =SUM(-tanks!AX29*tanks!$AU$36) -> #DIV/0! | R27: =SUM(P27:Q27) -> #DIV/0! | S27: =SUM(ELEC!N27) -> 0 | T27: =IF(S27>0,R27/S27,0) -> 0 | V27: =W10 -> 515542 | W27: =H33 -> 515845 | X27: day | Y27: 112 | Z27: 1 | AA27: =(W27-V27)*Z27 -> 303 | AB27: =SUM(AA27*Y27) -> 33936 | AC27: =AC10 -> 6200000 | AD27: =SUM(I36) -> 0.7994723
A28: =ELEC!C28 -> 44372 | B28: =B27 -> 1058175 | C28: =SUM(B28-B27) -> 0 | D28: =SUM(G28+I28+K28) -> 0 | E28: =B27+D28 -> 1058175 | F28: =F27 -> 156087 | G28: =F28-F27 -> 0 | H28: =H27 -> 515845 | I28: =H28-H27 -> 0 | J28: =J27 -> 386243 | K28: =J28-J27 -> 0 | L28: =SUM(G28*$Y$28)/1507.5 -> 0 | M28: =SUM(I28*$Y$27)/1507.5 -> 0 | N28: =SUM(K28*$Y$26)/1507.5 -> 0 | O28: =($AC$29/$A$37)/1507.5 -> 159.96314 | P28: =SUM(L28:O28) -> 159.96314 | Q28: =SUM(-tanks!AX30*tanks!$AU$36) -> #DIV/0! | R28: =SUM(P28:Q28) -> #DIV/0! | S28: =SUM(ELEC!N28) -> 0 | T28: =IF(S28>0,R28/S28,0) -> 0 | V28: =W11 -> 156087 | W28: =F33 -> 156087 | X28: Peak | Y28: 320 | Z28: 1 | AA28: =(W28-V28)*Z28 -> 0 | AB28: =SUM(AA28*Y28) -> 0 | AC28: =AC11 -> 1000 | AD28: =SUM(G36) -> 0 | AE28: =SUM(AB28*5%) -> 0 | AF28: =SUM(AE28/7)*31 -> 0
A29: =ELEC!C29 -> 44373 | B29: =B28 -> 1058175 | C29: =SUM(B29-B28) -> 0 | D29: =SUM(G29+I29+K29) -> 0 | E29: =B28+D29 -> 1058175 | F29: =F28 -> 156087 | G29: =F29-F28 -> 0 | H29: =H28 -> 515845 | I29: =H29-H28 -> 0 | J29: =J28 -> 386243 | K29: =J29-J28 -> 0 | L29: =SUM(G29*$Y$28)/1507.5 -> 0 | M29: =SUM(I29*$Y$27)/1507.5 -> 0 | N29: =SUM(K29*$Y$26)/1507.5 -> 0 | O29: =($AC$29/$A$37)/1507.5 -> 159.96314 | P29: =SUM(L29:O29) -> 159.96314 | Q29: =SUM(-tanks!AX31*tanks!$AU$36) -> #DIV/0! | R29: =SUM(P29:Q29) -> #DIV/0! | S29: =SUM(ELEC!N29) -> 0 | T29: =IF(S29>0,R29/S29,0) -> 0 | AA29: =SUM(AA26:AA28) -> 379 | AC29: =SUM(AC26:AC28) -> 7234333
A30: =ELEC!C30 -> 44374 | B30: =B29 -> 1058175 | C30: =SUM(B30-B29) -> 0 | D30: =SUM(G30+I30+K30) -> 0 | E30: =B29+D30 -> 1058175 | F30: =F29 -> 156087 | G30: =F30-F29 -> 0 | H30: =H29 -> 515845 | I30: =H30-H29 -> 0 | J30: =J29 -> 386243 | K30: =J30-J29 -> 0 | L30: =SUM(G30*$Y$28)/1507.5 -> 0 | M30: =SUM(I30*$Y$27)/1507.5 -> 0 | N30: =SUM(K30*$Y$26)/1507.5 -> 0 | O30: =($AC$29/$A$37)/1507.5 -> 159.96314 | P30: =SUM(L30:O30) -> 159.96314 | Q30: =SUM(-tanks!AX32*tanks!$AU$36) -> #DIV/0! | R30: =SUM(P30:Q30) -> #DIV/0! | S30: =SUM(ELEC!N30) -> 0 | T30: =IF(S30>0,R30/S30,0) -> 0 | V30: Occ % | W30: ='General information '!F37 -> 0 | Y30: Per G | AB30: =SUM(AB26:AB29) -> 40016
A31: =ELEC!C31 -> 44375 | B31: =B30 -> 1058175 | C31: =SUM(B31-B30) -> 0 | D31: =SUM(G31+I31+K31) -> 0 | E31: =B30+D31 -> 1058175 | F31: =F30 -> 156087 | G31: =F31-F30 -> 0 | H31: =H30 -> 515845 | I31: =H31-H30 -> 0 | J31: =J30 -> 386243 | K31: =J31-J30 -> 0 | L31: =SUM(G31*$Y$28)/1507.5 -> 0 | M31: =SUM(I31*$Y$27)/1507.5 -> 0 | N31: =SUM(K31*$Y$26)/1507.5 -> 0 | O31: =($AC$29/$A$37)/1507.5 -> 159.96314 | P31: =SUM(L31:O31) -> 159.96314 | Q31: =SUM(-tanks!AX33*tanks!$AU$36) -> #DIV/0! | R31: =SUM(P31:Q31) -> #DIV/0! | S31: =SUM(ELEC!N31) -> 0 | T31: =IF(S31>0,R31/S31,0) -> 0
A32: =ELEC!C32 -> 44376 | B32: =B31 -> 1058175 | C32: =SUM(B32-B31) -> 0 | D32: =SUM(G32+I32+K32) -> 0 | E32: =B31+D32 -> 1058175 | F32: =F31 -> 156087 | G32: =F32-F31 -> 0 | H32: =H31 -> 515845 | I32: =H32-H31 -> 0 | J32: =J31 -> 386243 | K32: =J32-J31 -> 0 | L32: =SUM(G32*$Y$28)/1507.5 -> 0 | M32: =SUM(I32*$Y$27)/1507.5 -> 0 | N32: =SUM(K32*$Y$26)/1507.5 -> 0 | O32: =($AC$29/$A$37)/1507.5 -> 159.96314 | P32: =SUM(L32:O32) -> 159.96314 | Q32: =SUM(-tanks!AX34*tanks!$AU$36) -> #DIV/0! | R32: =SUM(P32:Q32) -> #DIV/0! | S32: =SUM(ELEC!N32) -> 0 | T32: =IF(S32>0,R32/S32,0) -> 0
A33: =ELEC!C33 -> 44377 | B33: =B32 -> 1058175 | C33: =SUM(B33-B32) -> 0 | D33: =SUM(G33+I33+K33) -> 0 | E33: =B32+D33 -> 1058175 | F33: =F32 -> 156087 | G33: =F33-F32 -> 0 | H33: =H32 -> 515845 | I33: =H33-H32 -> 0 | J33: =J32 -> 386243 | K33: =J33-J32 -> 0 | L33: =SUM(G33*$Y$28)/1507.5 -> 0 | M33: =SUM(I33*$Y$27)/1507.5 -> 0 | N33: =SUM(K33*$Y$26)/1507.5 -> 0 | O33: =($AC$29/$A$37)/1507.5 -> 159.96314 | P33: =SUM(L33:O33) -> 159.96314 | Q33: =SUM(-tanks!AX35*tanks!$AU$36) -> #DIV/0! | R33: =SUM(P33:Q33) -> #DIV/0! | S33: =SUM(ELEC!N33) -> 0 | T33: =IF(S33>0,R33/S33,0) -> 0 | V33: Gen RH | W33: ='Utility Cost '!B18 -> 12 | X33: =SUM(W33/A35) -> 12 | Y33: =SUM(X33/1) -> 12 | AB33: =SUM(AB30+AC33) -> 7274349 | AC33: =SUM(AC29) -> 7234333
V34: Gen RH | AB34: =SUM(AB31+AC34) -> 0 | AC34: =SUM(AC30) -> 0
A35: =A37-COUNTIF(C4:C33,0) -> 1 | C35: =SUM(C4:C33)/A35 -> 379 | G35: =SUM(G4:G33)/A35 -> 0 | I35: =SUM(I4:I33)/A35 -> 303 | K35: =SUM(K4:K33)/A35 -> 76 | L35: =SUM(L33*1507.5) -> 0 | M35: =SUM(M33*1507.5) -> 0 | N35: =SUM(N33*1507.5) -> 0 | O35: =SUM(O33*1507.5) -> 241144.43 | AD35: =AC33/1507 -> 4800.4864
C36: =SUM(G36:K36) -> 1 | G36: =IF(C35>0,G35/C35,0) -> 0 | I36: =SUM(I35/C35) -> 0.7994723 | K36: =SUM(K35/C35) -> 0.2005277 | AA36: $ | AB36: =SUM(AB33/1507.5) -> 4825.4388
A37: 30
AB38: =SUM(AB36) -> 4825.4388

Sheet graphic

Sheet General information 
A1: GENERAL & HOTEL'S INFORMATION SHEET
B4: Max Temp | C4: MIN TEMP | D4: AVE TEMP | E4: AVE Humidity | F4: AVE OCC | G4: # of OCC Rooms | H4: Ball room | I4: Meeting rooms | J4: Outlets | K4: Total covers | L4: # of permenant Emp | M4: # of casuals | N4: Total # of EMP | O4: # of EMP/OCC Room
A5: =ELEC!C3 -> 44347 | B5: 25 | C5: 21 | D5: =(C5+B5)/2 -> 23 | E5: 0.56 | F5: 0 | G5: =F5*230 -> 0 | H5: 0 | I5: 0 | J5: 0 | K5: =+J5+H5+I5 -> 0
A6: =ELEC!C4 -> 44348 | B6: 27 | C6: 21 | D6: =(C6+B6)/2 -> 24 | E6: 0.46 | F6: 0 | G6: =F6*230 -> 0 | H6: 0 | I6: 0 | J6: 0 | K6: =+J6+H6 -> 0
A7: =ELEC!C5 -> 44349 | D7: =(C7+B7)/2 -> 0 | F7: 0 | G7: =F7*230 -> 0 | H7: 0 | I7: 0 | J7: 0 | K7: =+J7+H7 -> 0
A8: =ELEC!C6 -> 44350 | D8: =(C8+B8)/2 -> 0 | F8: 0 | G8: =F8*230 -> 0 | H8: 0 | I8: 0 | J8: 0 | K8: =+J8+H8 -> 0
A9: =ELEC!C7 -> 44351 | D9: =(C9+B9)/2 -> 0 | F9: 0 | G9: =F9*230 -> 0 | H9: 0 | I9: 0 | J9: 0 | K9: =+J9+H9 -> 0
A10: =ELEC!C8 -> 44352 | D10: =(C10+B10)/2 -> 0 | F10: 0 | G10: =F10*230 -> 0 | H10: 0 | I10: 0 | J10: 0 | K10: =+J10+H10 -> 0
A11: =ELEC!C9 -> 44353 | D11: =(C11+B11)/2 -> 0 | F11: 0 | G11: =F11*230 -> 0 | H11: 0 | I11: 0 | J11: 0 | K11: =+J11+H11 -> 0
A12: =ELEC!C10 -> 44354 | D12: =(C12+B12)/2 -> 0 | F12: 0 | G12: =F12*230 -> 0 | H12: 0 | I12: 0 | J12: 0 | K12: =+J12+H12 -> 0
A13: =ELEC!C11 -> 44355 | D13: =(C13+B13)/2 -> 0 | F13: 0 | G13: =F13*230 -> 0 | H13: 0 | I13: 0 | J13: 0 | K13: =+J13+H13 -> 0
A14: =ELEC!C12 -> 44356 | D14: =(C14+B14)/2 -> 0 | F14: 0 | G14: =F14*230 -> 0 | H14: 0 | I14: 0 | J14: 0 | K14: =+J14+H14 -> 0
A15: =ELEC!C13 -> 44357 | D15: =(C15+B15)/2 -> 0 | F15: 0 | G15: =F15*230 -> 0 | H15: 0 | I15: 0 | J15: 0 | K15: =+J15+H15 -> 0
A16: =ELEC!C14 -> 44358 | D16: =(C16+B16)/2 -> 0 | F16: 0 | G16: =F16*230 -> 0 | H16: 0 | I16: 0 | J16: 0 | K16: =+J16+H16 -> 0
A17: =ELEC!C15 -> 44359 | D17: =(C17+B17)/2 -> 0 | F17: 0 | G17: =F17*230 -> 0 | H17: 0 | I17: 0 | J17: 0 | K17: =+J17+H17 -> 0
A18: =ELEC!C16 -> 44360 | D18: =(C18+B18)/2 -> 0 | F18: 0 | G18: =F18*230 -> 0 | H18: 0 | I18: 0 | J18: 0 | K18: =+J18+H18 -> 0
... A26: =ELEC!C24 -> 44368 | D26: =(C26+B26)/2 -> 0 | F26: 0 | G26: =F26*230 -> 0 | H26: 0 | I26: 0 | J26: 0 | K26: =+J26+H26 -> 0
A27: =ELEC!C25 -> 44369 | D27: =(C27+B27)/2 -> 0 | F27: 0 | G27: =F27*230 -> 0 | H27: 0 | I27: 0 | J27: 0 | K27: =+J27+H27+I27 -> 0
A28: =ELEC!C26 -> 44370 | D28: =(C28+B28)/2 -> 0 | F28: 0 | G28: =F28*230 -> 0 | H28: 0 | I28: 0 | J28: 0 | K28: =+J28+H28+I28 -> 0
A29: =ELEC!C27 -> 44371 | D29: =(C29+B29)/2 -> 0 | F29: 0 | G29: =F29*230 -> 0 | H29: 0 | I29: 0 | J29: 0 | K29: =+J29+H29+I29 -> 0
A30: =ELEC!C28 -> 44372 | D30: =(C30+B30)/2 -> 0 | F30: 0 | G30: =F30*230 -> 0 | H30: 0 | I30: 0 | J30: 0 | K30: =+J30+H30+I30 -> 0
A31: =ELEC!C29 -> 44373 | D31: =(C31+B31)/2 -> 0 | F31: 0 | G31: =F31*230 -> 0 | H31: 0 | I31: 0 | J31: 0 | K31: =+J31+H31+I31 -> 0
A32: =ELEC!C30 -> 44374 | D32: =(C32+B32)/2 -> 0 | F32: 0 | G32: =F32*230 -> 0 | H32: 0 | I32: 0 | J32: 0 | K32: =+J32+H32+I32 -> 0
A33: =ELEC!C31 -> 44375 | D33: =(C33+B33)/2 -> 0 | F33: 0 | G33: =F33*230 -> 0 | H33: 0 | I33: 0 | J33: 0 | K33: =+J33+H33+I33 -> 0
A34: =ELEC!C32 -> 44376 | D34: =(C34+B34)/2 -> 0 | F34: 0 | G34: =F34*230 -> 0 | H34: 0 | I34: 0 | J34: 0 | K34: =+J34+H34+I34 -> 0
A35: =ELEC!C33 -> 44377 | D35: =(C35+B35)/2 -> 0 | F35: 0 | G35: =F35*230 -> 0 | H35: 0 | I35: 0 | J35: 0 | K35: =+J35+H35+I35 -> 0
