Workbook

Sheet Total
A1: Site Name | B1: Day | C1: Month | D1: Year | E1: Total Electricity Kwh | F1: Electricity Tariff ($/Kwh) | G1: Total Fuel Oil (Liters) | H1: Fuel Oil $/Liter | I1: LPG (Kg) | J1: LPG $/Kg | K1: Water Utility Supply (m3) m3 | L1: Water Utility Supply (m3) $/m3 | M1: Irrigation Water (m3) m3 | N1: Irrigation water $/m3 | O1: Room Nights
A2: Beirut | B2: 1 | C2: 6 | D2: 2021 | E2: =ELEC!N4 -> 10480.6 | F2: =SUM('EDl log'!T4) -> 0.44676948 | G2: =-tanks!AW6 -> 107 | H2: =SUM(tanks!AV6) -> 1.003 | I2: =('B5'!AU5)*0.51 -> 0 | J2: ='B5'!AX5/0.51 -> 1.5686275 | K2: =WATER!I6 -> 0 | L2: =SUM(WATER!J6) -> 0 | M2: =WATER!Q6 -> 0 | N2: 0.6 | O2: =ELEC!B4 -> 0
A3: Beirut | B3: =B2+1 -> 2 | C3: 6 | D3: 2021 | E3: =ELEC!N5 -> 12363.8 | F3: =SUM('EDl log'!T5) -> 0.19803241 | G3: =-tanks!AW7 -> 128 | H3: =SUM(tanks!AV7) -> 1.003 | I3: =('B5'!AU6)*0.51 -> 0 | J3: ='B5'!AX6/0.51 -> 1.5686275 | K3: =WATER!I7 -> 109 | L3: =SUM(WATER!J7) -> 2.293578 | M3: =WATER!Q7 -> 0 | N3: 0.6 | O3: =ELEC!B5 -> 0
A4: Beirut | B4: =B3+1 -> 3 | C4: 6 | D4: 2021 | E4: =ELEC!N6 -> 15101 | F4: =SUM('EDl log'!T6) -> 0.1465717 | G4: =-tanks!AW8 -> 125 | H4: =SUM(tanks!AV8) -> 1.003 | I4: =('B5'!AU7)*0.51 -> 0 | J4: ='B5'!AX7/0.51 -> 1.5686275 | K4: =WATER!I8 -> 0 | L4: =SUM(WATER!J8) -> 0 | M4: =WATER!Q8 -> 0 | N4: 0.6 | O4: =ELEC!B6 -> 0
A5: Beirut | B5: =B4+1 -> 4 | C5: 6 | D5: 2021 | E5: =ELEC!N7 -> 16108.6 | F5: =SUM('EDl log'!T7) -> 0.19955771 | G5: =-tanks!AW9 -> 91 | H5: =SUM(tanks!AV9) -> 1.003 | I5: =('B5'!AU8)*0.51 -> 0 | J5: ='B5'!AX8/0.51 -> 1.5686275 | K5: =WATER!I9 -> 0 | L5: =SUM(WATER!J9) -> 0 | M5: =WATER!Q9 -> 0 | N5: 0.6 | O5: =ELEC!B7 -> 0
A6: Beirut | B6: =B5+1 -> 5 | C6: 6 | D6: 2021 | E6: =ELEC!N8 -> 12066 | F6: =SUM('EDl log'!T8) -> 0.44758356 | G6: =-tanks!AW10 -> 242 | H6: =SUM(tanks!AV10) -> 1.003 | I6: =('B5'!AU9)*0.51 -> 0 | J6: ='B5'!AX9/0.51 -> 1.5686275 | K6: =WATER!I10 -> 0 | L6: =SUM(WATER!J10) -> 0 | M6: =WATER!Q10 -> 0 | N6: 0.6 | O6: =ELEC!B8 -> 0
A7: Beirut | B7: =B6+1 -> 6 | C7: 6 | D7: 2021 | E7: =ELEC!N9 -> 11919 | F7: =SUM('EDl log'!T9) -> 0.35022596 | G7: =-tanks!AW11 -> 192 | H7: =SUM(tanks!AV11) -> 1.003 | I7: =('B5'!AU10)*0.51 -> 0 | J7: ='B5'!AX10/0.51 -> 1.5686275 | K7: =WATER!I11 -> 0 | L7: =SUM(WATER!J11) -> 0 | M7: =WATER!Q11 -> 0 | N7: 0.6 | O7: =ELEC!B9 -> 0
A8: Beirut | B8: =B7+1 -> 7 | C8: 6 | D8: 2021 | E8: =ELEC!N10 -> 15761 | F8: =SUM('EDl log'!T10) -> 0.16054063 | G8: =-tanks!AW12 -> 54 | H8: =SUM(tanks!AV12) -> 1.003 | I8: =('B5'!AU11)*0.51 -> 0 | J8: ='B5'!AX11/0.51 -> 1.5686275 | K8: =WATER!I12 -> 0 | L8: =SUM(WATER!J12) -> 0 | M8: =WATER!Q12 -> 0 | N8: 0.6 | O8: =ELEC!B10 -> 0
A9: Beirut | B9: =B8+1 -> 8 | C9: 6 | D9: 2021 | E9: =ELEC!N11 -> 11896 | F9: =SUM('EDl log'!T11) -> 0.31853204 | G9: =-tanks!AW13 -> 158 | H9: =SUM(tanks!AV13) -> 1.003 | I9: =('B5'!AU12)*0.51 -> 0 | J9: ='B5'!AX12/0.51 -> 1.5686275 | K9: =WATER!I13 -> 0 | L9: =SUM(WATER!J13) -> 0 | M9: =WATER!Q13 -> 0 | N9: 0.6 | O9: =ELEC!B11 -> 0
A10: Beirut | B10: =B9+1 -> 9 | C10: 6 | D10: 2021 | E10: =ELEC!N12 -> 13733 | F10: =SUM('EDl log'!T12) -> 0.36711189 | G10: =-tanks!AW14 -> 110 | H10: =SUM(tanks!AV14) -> 1.003 | I10: =('B5'!AU13)*0.51 -> 0 | J10: ='B5'!AX13/0.51 -> 1.5686275 | K10: =WATER!I14 -> 0 | L10: =SUM(WATER!J14) -> 0 | M10: =WATER!Q14 -> 0 | N10: 0.6 | O10: =ELEC!B12 -> 0
A11: Beirut | B11: =B10+1 -> 10 | C11: 6 | D11: 2021 | E11: =ELEC!N13 -> 14893 | F11: =SUM('EDl log'!T13) -> 0.1097534 | G11: =-tanks!AW15 -> 115 | H11: =SUM(tanks!AV15) -> 1.05 | I11: =('B5'!AU14)*0.51 -> 0 | J11: ='B5'!AX14/0.51 -> 1.5686275 | K11: =WATER!I15 -> 0 | L11: =SUM(WATER!J15) -> 0 | M11: =WATER!Q15 -> 0 | N11: 0.6 | O11: =ELEC!B13 -> 0
A12: Beirut | B12: =B11+1 -> 11 | C12: 6 | D12: 2021 | E12: =ELEC!N14 -> 14674 | F12: =SUM('EDl log'!T14) -> 0.35841243 | G12: =-tanks!AW16 -> 135 | H12: =SUM(tanks!AV16) -> 1.05 | I12: =('B5'!AU15)*0.51 -> 0 | J12: ='B5'!AX15/0.51 -> 1.5686275 | K12: =WATER!I16 -> 0 | L12: =SUM(WATER!J16) -> 0 | M12: =WATER!Q16 -> 0 | N12: 0.6 | O12: =ELEC!B14 -> 0
A13: Beirut | B13: =B12+1 -> 12 | C13: 6 | D13: 2021 | E13: =ELEC!N15 -> 12497 | F13: =SUM('EDl log'!T15) -> 0.25953867 | G13: =-tanks!AW17 -> 200 | H13: =SUM(tanks!AV17) -> 1.05 | I13: =('B5'!AU16)*0.51 -> 0 | J13: ='B5'!AX16/0.51 -> 1.5686275 | K13: =WATER!I17 -> 0 | L13: =SUM(WATER!J17) -> 0 | M13: =WATER!Q17 -> 0 | N13: 0.6 | O13: =ELEC!B15 -> 0
A14: Beirut | B14: =B13+1 -> 13 | C14: 6 | D14: 2021 | E14: =ELEC!N16 -> 12554 | F14: =SUM('EDl log'!T16) -> 0.38243213 | G14: =-tanks!AW18 -> 48 | H14: =SUM(tanks!AV18) -> 1.05 | I14: =('B5'!AU17)*0.51 -> 0 | J14: ='B5'!AX17/0.51 -> 1.5686275 | K14: =WATER!I18 -> 0 | L14: =SUM(WATER!J18) -> 0 | M14: =WATER!Q18 -> 0 | N14: 0.6 | O14: =ELEC!B16 -> 0
... A31: Beirut | B31: =B30+1 -> 30 | C31: 6 | D31: 2021 | E31: =ELEC!N33 -> 0 | F31: =SUM('EDl log'!T33) -> 0 | G31: =-tanks!AW35 -> 0 | H31: =SUM(tanks!AV35) -> 1.05 | I31: =('B5'!AU34)*0.51 -> 0 | J31: ='B5'!AX34/0.51 -> 1.5686275 | K31: =WATER!I35 -> 0 | L31: =SUM(WATER!J35) -> 0 | M31: =WATER!Q35 -> 0 | N31: 0.6 | O31: =ELEC!B33 -> 0

Sheet Submetering
A1: Site Name | B1: Day | C1: Month | D1: Year | E1: ATS1 Kwh | F1: ATS2 Kwh | G1: ATS3 Kwh | H1: ATS4 Kwh | I1: ATS5 Kwh | J1: Guest (m3) | K1: Kitchen & Laundry (m3) | L1: Room Nights
A2: Beirut | B2: 1 | C2: 6 | D2: 2021 | E2: =ELEC!M4 -> 1550 | F2: =ELEC!K4 -> 4758 | G2: =ELEC!I4 -> 742 | H2: =ELEC!E4 -> 2955 | I2: =ELEC!G4 -> 475.6 | J2: =WATER!Y6 -> 0 | K2: =WATER!AJ6 -> 0 | L2: =ELEC!B4 -> 0
A3: Beirut | B3: =B2+1 -> 2 | C3: 6 | D3: 2021 | E3: =ELEC!M5 -> 2160 | F3: =ELEC!K5 -> 5676 | G3: =ELEC!I5 -> 1106 | H3: =ELEC!E5 -> 2595 | I3: =ELEC!G5 -> 826.8 | J3: =WATER!Y7 -> 0 | K3: =WATER!AJ7 -> 0 | L3: =ELEC!B5 -> 0
A4: Beirut | B4: =B3+1 -> 3 | C4: 6 | D4: 2021 | E4: =ELEC!M6 -> 2288 | F4: =ELEC!K6 -> 7130 | G4: =ELEC!I6 -> 1112 | H4: =ELEC!E6 -> 3813 | I4: =ELEC!G6 -> 758 | J4: =WATER!Y8 -> 0 | K4: =WATER!AJ8 -> 0 | L4: =ELEC!B6 -> 0
A5: Beirut | B5: =B4+1 -> 4 | C5: 6 | D5: 2021 | E5: =ELEC!M7 -> 2664 | F5: =ELEC!K7 -> 7574 | G5: =ELEC!I7 -> 1174 | H5: =ELEC!E7 -> 3811 | I5: =ELEC!G7 -> 885.6 | J5: =WATER!Y9 -> 0 | K5: =WATER!AJ9 -> 0 | L5: =ELEC!B7 -> 0
A6: Beirut | B6: =B5+1 -> 5 | C6: 6 | D6: 2021 | E6: =ELEC!M8 -> 2118 | F6: =ELEC!K8 -> 5928 | G6: =ELEC!I8 -> 836 | H6: =ELEC!E8 -> 2604 | I6: =ELEC!G8 -> 580 | J6: =WATER!Y10 -> 0 | K6: =WATER!AJ10 -> 0 | L6: =ELEC!B8 -> 0
A7: Beirut | B7: =B6+1 -> 6 | C7: 6 | D7: 2021 | E7: =ELEC!M9 -> 2196 | F7: =ELEC!K9 -> 5372 | G7: =ELEC!I9 -> 790 | H7: =ELEC!E9 -> 2885 | I7: =ELEC!G9 -> 676 | J7: =WATER!Y11 -> 0 | K7: =WATER!AJ11 -> 0 | L7: =ELEC!B9 -> 0
A8: Beirut | B8: =B7+1 -> 7 | C8: 6 | D8: 2021 | E8: =ELEC!M10 -> 2410 | F8: =ELEC!K10 -> 7914 | G8: =ELEC!I10 -> 946 | H8: =ELEC!E10 -> 3742 | I8: =ELEC!G10 -> 749 | J8: =WATER!Y12 -> 0 | K8: =WATER!AJ12 -> 0 | L8: =ELEC!B10 -> 0
A9: Beirut | B9: =B8+1 -> 8 | C9: 6 | D9: 2021 | E9: =ELEC!M11 -> 2102 | F9: =ELEC!K11 -> 5162 | G9: =ELEC!I11 -> 880 | H9: =ELEC!E11 -> 3014 | I9: =ELEC!G11 -> 738 | J9: =WATER!Y13 -> 0 | K9: =WATER!AJ13 -> 0 | L9: =ELEC!B11 -> 0
A10: Beirut | B10: =B9+1 -> 9 | C10: 6 | D10: 2021 | E10: =ELEC!M12 -> 2354 | F10: =ELEC!K12 -> 6288 | G10: =ELEC!I12 -> 1038 | H10: =ELEC!E12 -> 3346 | I10: =ELEC!G12 -> 707 | J10: =WATER!Y14 -> 0 | K10: =WATER!AJ14 -> 0 | L10: =ELEC!B12 -> 0
A11: Beirut | B11: =B10+1 -> 10 | C11: 6 | D11: 2021 | E11: =ELEC!M13 -> 2492 | F11: =ELEC!K13 -> 4428 | G11: =ELEC!I13 -> 1016 | H11: =ELEC!E13 -> 6244 | I11: =ELEC!G13 -> 713 | J11: =WATER!Y15 -> 0 | K11: =WATER!AJ15 -> 0 | L11: =ELEC!B13 -> 0
A12: Beirut | B12: =B11+1 -> 11 | C12: 6 | D12: 2021 | E12: =ELEC!M14 -> 2600 | F12: =ELEC!K14 -> 2772 | G12: =ELEC!I14 -> 966 | H12: =ELEC!E14 -> 7647 | I12: =ELEC!G14 -> 689 | J12: =WATER!Y16 -> 0 | K12: =WATER!AJ16 -> 0 | L12: =ELEC!B14 -> 0
A13: Beirut | B13: =B12+1 -> 12 | C13: 6 | D13: 2021 | E13: =ELEC!M15 -> 2178 | F13: =ELEC!K15 -> 2518 | G13: =ELEC!I15 -> 940 | H13: =ELEC!E15 -> 6192 | I13: =ELEC!G15 -> 669 | J13: =WATER!Y17 -> 0 | K13: =WATER!AJ17 -> 0 | L13: =ELEC!B15 -> 0
A14: Beirut | B14: =B13+1 -> 13 | C14: 6 | D14: 2021 | E14: =ELEC!M16 -> 2500 | F14: =ELEC!K16 -> 2238 | G14: =ELEC!I16 -> 1014 | H14: =ELEC!E16 -> 6129 | I14: =ELEC!G16 -> 673 | J14: =WATER!Y18 -> 0 | K14: =WATER!AJ18 -> 0 | L14: =ELEC!B16 -> 0
... A31: Beirut | B31: =B30+1 -> 30 | C31: 6 | D31: 2021 | E31: =ELEC!M33 -> 0 | F31: =ELEC!K33 -> 0 | G31: =ELEC!I33 -> 0 | H31: =ELEC!E33 -> 0 | I31: =ELEC!G33 -> 0 | J31: =WATER!Y35 -> 0 | K31: =WATER!AJ35 -> 0 | L31: =ELEC!B33 -> 0
D45: .

Sheet ELEC
AK1: ATS 4 till power meter is for MDB 3 is replaced
A2: OOC | B2: Room OCC | D2: MDB3 | E2: MDB3/day | F2: EMDB2 | G2: EMDB2/day | H2: EMDB1 | I2: EMDB1/day | J2: MDB2 | K2: mdb2/day | L2: MDB1 | M2: MDB1/Day | N2: Total KWH | O2: KWH/Rooc | P2: Gen MHW | Q2: Gen/Day KWH | R2: EDL KWH | S2: CH1 RH | T2: RH | U2: C1h1 power | V2: CH1 Con KWH | W2: CH2 RH | X2: RH | Y2: Ch2 power | Z2: CH2 Con KWH | AA2: CH3 RH | AB2: RH | AC2: Ch3 power | AD2: CH3 Con KWH | AE2: RH total | AF2: KWH total | AG2: AVG chiller KW/Hr | AK2: Emergency | AL2: Normal | AM2: Total | AN2: Difference
A3: =[1]ELEC!$A$33 -> 0 | B3: =[1]ELEC!$B$33 -> 0 | C3: 44347 | D3: =[2]ELEC!D33 -> 32911138 | E3: =[2]ELEC!E33 -> 4709 | F3: =[2]ELEC!F33 -> 4031450 | G3: =[2]ELEC!G33 -> 1057 | H3: =[2]ELEC!H33 -> 17884320 | I3: =[2]ELEC!I33 -> 1442 | J3: =[2]ELEC!J33 -> 29123928 | K3: =[2]ELEC!K33 -> 9050 | ... AG3: =[2]ELEC!AG33 -> 236.41667 | AI3: =[2]ELEC!AI33 -> -1051635 | AJ3: 44347 | AK3: 333631 | AL3: 431020 | AM3: =AK3+AL3 -> 764651 | AN3: 4709
A4: ='General information '!F6 -> 0 | B4: =SUM(230*A4) -> 0 | C4: 44348 | D4: =D3 -> 32911138 | E4: =AN4 -> 2955 | F4: 4031925.6 | G4: =F4-F3 -> 475.6 | H4: 17885062 | I4: =H4-H3 -> 742 | J4: 29128686 | K4: =J4-J3 -> 4758 | L4: 24237542 | M4: =L4-L3 -> 1550 | N4: =M4+K4+I4+G4+E4 -> 10480.6 | O4: =IF(B4>0,N4/B4,0) -> 0 | P4: 17216.967 | Q4: =(P4-P3)*1000 -> 9515 | R4: =+N4-Q4 -> 965.6 | S4: =S3 -> 10175 | T4: =S4-S3 -> 0 | U4: =U3 -> 429166 | V4: =U4-U3 -> 0 | W4: 32562 | X4: =W4-W3 -> 20 | Y4: 775030 | Z4: =Y4-Y3 -> 4098 | AA4: =AA3 -> 35939 | AB4: =AA4-AA3 -> 0 | AC4: =AC3 -> 961645 | AD4: =AC4-AC3 -> 0 | AE4: =AB4+X4+T4 -> 20 | AF4: =V4+Z4+AD4 -> 4098 | AG4: =IF(AE4>0,AF4/AE4,0) -> 204.9 | AI4: =R4-'EDl log'!B4 -> -1057209.4 | AJ4: 44348 | AK4: 335894 | AL4: 431712 | AM4: =AK4+AL4 -> 767606 | AN4: =AM4-AM3 -> 2955
A5: ='General information '!F7 -> 0 | B5: =SUM(230*A5) -> 0 | C5: 44349 | D5: =D4 -> 32911138 | E5: =AN5 -> 2595 | F5: 4032752.4 | G5: =F5-F4 -> 826.8 | H5: 17886168 | I5: =H5-H4 -> 1106 | J5: 29134362 | K5: =J5-J4 -> 5676 | L5: 24239702 | M5: =L5-L4 -> 2160 | N5: =M5+K5+I5+G5+E5 -> 12363.8 | O5: =IF(B5>0,N5/B5,0) -> 0 | P5: 17227.848 | Q5: =(P5-P4)*1000 -> 10881 | R5: =N5-Q5 -> 1482.8 | S5: =S4 -> 10175 | T5: =S5-S4 -> 0 | U5: =U4 -> 429166 | V5: =U5-U4 -> 0 | W5: 32576 | X5: =W5-W4 -> 14 | Y5: 777894 | Z5: =Y5-Y4 -> 2864 | AA5: =AA4 -> 35939 | AB5: =AA5-AA4 -> 0 | AC5: =AC4 -> 961645 | AD5: =AC5-AC4 -> 0 | AE5: =AB5+X5+T5 -> 14 | AF5: =V5+Z5+AD5 -> 2864 | AG5: =IF(AE5>0,AF5/AE5,0) -> 204.57143 | AI5: =R5-'EDl log'!B5 -> -1057880.2 | AJ5: 44349 | AK5: 338482 | AL5: 431719 | AM5: =AK5+AL5 -> 770201 | AN5: =AM5-AM4 -> 2595
A6: ='General information '!F8 -> 0 | B6: =SUM(230*A6) -> 0 | C6: 44350 | D6: =D5 -> 32911138 | E6: =AN6 -> 3813 | F6: 4033510.4 | G6: =F6-F5 -> 758 | H6: 17887280 | I6: =H6-H5 -> 1112 | J6: 29141492 | K6: =J6-J5 -> 7130 | L6: 24241990 | M6: =L6-L5 -> 2288 | N6: =M6+K6+I6+G6+E6 -> 15101 | O6: =IF(B6>0,N6/B6,0) -> 0 | P6: 17242.466 | Q6: =(P6-P5)*1000 -> 14618 | R6: =N6-Q6 -> 483 | S6: =S5 -> 10175 | T6: =S6-S5 -> 0 | U6: =U5 -> 429166 | V6: =U6-U5 -> 0 | W6: 32593 | X6: =W6-W5 -> 17 | Y6: 781232 | Z6: =Y6-Y5 -> 3338 | AA6: =AA5 -> 35939 | AB6: =AA6-AA5 -> 0 | AC6: =AC5 -> 961645 | AD6: =AC6-AC5 -> 0 | AE6: =AB6+X6+T6 -> 17 | AF6: =V6+Z6+AD6 -> 3338 | AG6: =IF(AE6>0,AF6/AE6,0) -> 196.35294 | AI6: =R6-'EDl log'!B6 -> -1059322 | AJ6: 44350 | AK6: 342095 | AL6: 431919 | AM6: =AK6+AL6 -> 774014 | AN6: =AM6-AM5 -> 3813
A7: ='General information '!F9 -> 0 | B7: =SUM(230*A7) -> 0 | C7: 44351 | D7: =D6 -> 32911138 | E7: =AN7 -> 3811 | F7: 4034396 | G7: =F7-F6 -> 885.6 | H7: 17888454 | I7: =H7-H6 -> 1174 | J7: 29149066 | K7: =J7-J6 -> 7574 | L7: 24244654 | M7: =L7-L6 -> 2664 | N7: =M7+K7+I7+G7+E7 -> 16108.6 | O7: =IF(B7>0,N7/B7,0) -> 0 | P7: 17256.524 | Q7: =(P7-P6)*1000 -> 14058 | R7: =N7-Q7 -> 2050.6 | S7: =S6 -> 10175 | T7: =S7-S6 -> 0 | U7: =U6 -> 429166 | V7: =U7-U6 -> 0 | W7: 32605 | X7: =W7-W6 -> 12 | Y7: 783620 | Z7: =Y7-Y6 -> 2388 | AA7: =AA6 -> 35939 | AB7: =AA7-AA6 -> 0 | AC7: =AC6 -> 961645 | AD7: =AC7-AC6 -> 0 | AE7: =AB7+X7+T7 -> 12 | AF7: =V7+Z7+AD7 -> 2388 | AG7: =IF(AE7>0,AF7/AE7,0) -> 199 | AI7: =R7-'EDl log'!B7 -> -1057754.4 | AJ7: 44351 | AK7: 345431 | AL7: 432394 | AM7: =AK7+AL7 -> 777825 | AN7: =AM7-AM6 -> 3811
A8: ='General information '!F10 -> 0 | B8: =SUM(230*A8) -> 0 | C8: 44352 | D8: =D7 -> 32911138 | E8: =AN8 -> 2604 | F8: 4034976 | G8: =F8-F7 -> 580 | H8: 17889290 | I8: =H8-H7 -> 836 | J8: 29154994 | K8: =J8-J7 -> 5928 | L8: 24246772 | M8: =L8-L7 -> 2118 | N8: =M8+K8+I8+G8+E8 -> 12066 | O8: =IF(B8>0,N8/B8,0) -> 0 | P8: 17268.334 | Q8: =(P8-P7)*1000 -> 11810 | R8: =N8-Q8 -> 256 | S8: =S7 -> 10175 | T8: =S8-S7 -> 0 | U8: =U7 -> 429166 | V8: =U8-U7 -> 0 | W8: 32623 | X8: =W8-W7 -> 18 | Y8: 787323 | Z8: =Y8-Y7 -> 3703 | AA8: =AA7 -> 35939 | AB8: =AA8-AA7 -> 0 | AC8: =AC7 -> 961645 | AD8: =AC8-AC7 -> 0 | AE8: =AB8+X8+T8 -> 18 | AF8: =V8+Z8+AD8 -> 3703 | AG8: =IF(AE8>0,AF8/AE8,0) -> 205.72222 | AI8: =R8-'EDl log'!B8 -> -1061198 | AJ8: 44352 | AK8: 348088 | AL8: 432341 | AM8: =AK8+AL8 -> 780429 | AN8: =AM8-AM7 -> 2604
A9: ='General information '!F11 -> 0 | B9: =SUM(230*A9) -> 0 | C9: 44353 | D9: =D8 -> 32911138 | E9: =AN9 -> 2885 | F9: 4035652 | G9: =F9-F8 -> 676 | H9: 17890080 | I9: =H9-H8 -> 790 | J9: 29160366 | K9: =J9-J8 -> 5372 | L9: 24248968 | M9: =L9-L8 -> 2196 | N9: =M9+K9+I9+G9+E9 -> 11919 | O9: =IF(B9>0,N9/B9,0) -> 0 | P9: 17279.31 | Q9: =(P9-P8)*1000 -> 10976 | R9: =N9-Q9 -> 943 | S9: =S8 -> 10175 | T9: =S9-S8 -> 0 | U9: =U8 -> 429166 | V9: =U9-U8 -> 0 | W9: 32636 | X9: =W9-W8 -> 13 | Y9: 789812 | Z9: =Y9-Y8 -> 2489 | AA9: =AA8 -> 35939 | AB9: =AA9-AA8 -> 0 | AC9: =AC8 -> 961645 | AD9: =AC9-AC8 -> 0 | AE9: =AB9+X9+T9 -> 13 | AF9: =V9+Z9+AD9 -> 2489 | AG9: =IF(AE9>0,AF9/AE9,0) -> 191.46154 | AI9: =R9-'EDl log'!B9 -> -1061021 | AJ9: 44353 | AK9: 350597 | AL9: 432717 | AM9: =AK9+AL9 -> 783314 | AN9: =AM9-AM8 -> 2885
A10: ='General information '!F12 -> 0 | B10: =SUM(230*A10) -> 0 | C10: 44354 | D10: =D9 -> 32911138 | E10: =AN10 -> 3742 | F10: 4036401 | G10: =F10-F9 -> 749 | H10: 17891026 | I10: =H10-H9 -> 946 | J10: 29168280 | K10: =J10-J9 -> 7914 | L10: 24251378 | M10: =L10-L9 -> 2410 | N10: =M10+K10+I10+G10+E10 -> 15761 | O10: =IF(B10>0,N10/B10,0) -> 0 | P10: 17294.434 | Q10: =(P10-P9)*1000 -> 15124 | R10: =N10-Q10 -> 637 | S10: =S9 -> 10175 | T10: =S10-S9 -> 0 | U10: =U9 -> 429166 | V10: =U10-U9 -> 0 | W10: 32655 | X10: =W10-W9 -> 19 | Y10: 794074 | Z10: =Y10-Y9 -> 4262 | AA10: =AA9 -> 35939 | AB10: =AA10-AA9 -> 0 | AC10: =AC9 -> 961645 | AD10: =AC10-AC9 -> 0 | AE10: =AB10+X10+T10 -> 19 | AF10: =V10+Z10+AD10 -> 4262 | AG10: =IF(AE10>0,AF10/AE10,0) -> 224.31579 | AI10: =R10-'EDl log'!B10 -> -1061805 | AJ10: 44354 | AK10: 354127 | AL10: 432929 | AM10: =AK10+AL10 -> 787056 | AN10: =AM10-AM9 -> 3742
A11: ='General information '!F13 -> 0 | B11: =SUM(230*A11) -> 0 | C11: 44355 | D11: =D10 -> 32911138 | E11: =AN11 -> 3014 | F11: 4037139 | G11: =F11-F10 -> 738 | H11: 17891906 | I11: =H11-H10 -> 880 | J11: 29173442 | K11: =J11-J10 -> 5162 | L11: 24253480 | M11: =L11-L10 -> 2102 | N11: =M11+K11+I11+G11+E11 -> 11896 | O11: =IF(B11>0,N11/B11,0) -> 0 | P11: 17304.765 | Q11: =(P11-P10)*1000 -> 10331 | R11: =N11-Q11 -> 1565 | S11: =S10 -> 10175 | T11: =S11-S10 -> 0 | U11: =U10 -> 429166 | V11: =U11-U10 -> 0 | W11: 32669 | X11: =W11-W10 -> 14 | Y11: 796836 | Z11: =Y11-Y10 -> 2762 | AA11: =AA10 -> 35939 | AB11: =AA11-AA10 -> 0 | AC11: =AC10 -> 961645 | AD11: =AC11-AC10 -> 0 | AE11: =AB11+X11+T11 -> 14 | AF11: =V11+Z11+AD11 -> 2762 | AG11: =IF(AE11>0,AF11/AE11,0) -> 197.28571 | AI11: =R11-'EDl log'!B11 -> -1061837 | AJ11: 44355 | AK11: 356725 | AL11: 433345 | AM11: =AK11+AL11 -> 790070 | AN11: =AM11-AM10 -> 3014
A12: ='General information '!F14 -> 0 | B12: =SUM(230*A12) -> 0 | C12: 44356 | D12: =D11 -> 32911138 | E12: =AN12 -> 3346 | F12: 4037846 | G12: =F12-F11 -> 707 | H12: 17892944 | I12: =H12-H11 -> 1038 | J12: 29179730 | K12: =J12-J11 -> 6288 | L12: 24255834 | M12: =L12-L11 -> 2354 | N12: =M12+K12+I12+G12+E12 -> 13733 | O12: =IF(B12>0,N12/B12,0) -> 0 | P12: 17318.005 | Q12: =(P12-P11)*1000 -> 13240 | R12: =N12-Q12 -> 493 | S12: =S11 -> 10175 | T12: =S12-S11 -> 0 | U12: =U11 -> 429166 | V12: =U12-U11 -> 0 | W12: 32684 | X12: =W12-W11 -> 15 | Y12: 800305 | Z12: =Y12-Y11 -> 3469 | AA12: =AA11 -> 35939 | AB12: =AA12-AA11 -> 0 | AC12: =AC11 -> 961645 | AD12: =AC12-AC11 -> 0 | AE12: =AB12+X12+T12 -> 15 | AF12: =V12+Z12+AD12 -> 3469 | AG12: =IF(AE12>0,AF12/AE12,0) -> 231.26667 | AI12: =R12-'EDl log'!B12 -> -1063311 | AJ12: 44356 | AK12: 359901 | AL12: 433515 | AM12: =AK12+AL12 -> 793416 | AN12: =AM12-AM11 -> 3346
A13: ='General information '!F15 -> 0 | B13: =SUM(230*A13) -> 0 | C13: 44357 | D13: =D12 -> 32911138 | E13: =AN13 -> 6244 | F13: 4038559 | G13: =F13-F12 -> 713 | H13: 17893960 | I13: =H13-H12 -> 1016 | J13: 29184158 | K13: =J13-J12 -> 4428 | L13: 24258326 | M13: =L13-L12 -> 2492 | N13: =M13+K13+I13+G13+E13 -> 14893 | O13: =IF(B13>0,N13/B13,0) -> 0 | P13: 17331.902 | Q13: =(P13-P12)*1000 -> 13897 | R13: =N13-Q13 -> 996 | S13: =S12 -> 10175 | T13: =S13-S12 -> 0 | U13: =U12 -> 429166 | V13: =U13-U12 -> 0 | W13: 32691 | X13: =W13-W12 -> 7 | Y13: 801841 | Z13: =Y13-Y12 -> 1536 | AA13: 35950 | AB13: =AA13-AA12 -> 11 | AC13: 964432 | AD13: =AC13-AC12 -> 2787 | AE13: =AB13+X13+T13 -> 18 | AF13: =V13+Z13+AD13 -> 4323 | AG13: =IF(AE13>0,AF13/AE13,0) -> 240.16667 | AI13: =R13-'EDl log'!B13 -> -1063501 | AJ13: 44357 | AK13: 365855 | AL13: 433805 | AM13: =AK13+AL13 -> 799660 | AN13: =AM13-AM12 -> 6244
A14: ='General information '!F16 -> 0 | B14: =SUM(230*A14) -> 0 | C14: 44358 | D14: =D13 -> 32911138 | E14: =AN14 -> 7647 | F14: 4039248 | G14: =F14-F13 -> 689 | H14: 17894926 | I14: =H14-H13 -> 966 | J14: 29186930 | K14: =J14-J13 -> 2772 | L14: 24260926 | M14: =L14-L13 -> 2600 | N14: =M14+K14+I14+G14+E14 -> 14674 | O14: =IF(B14>0,N14/B14,0) -> 0 | P14: 17345.992 | Q14: =(P14-P13)*1000 -> 14090 | R14: =N14-Q14 -> 584 | S14: =S13 -> 10175 | T14: =S14-S13 -> 0 | U14: =U13 -> 429166 | V14: =U14-U13 -> 0 | W14: =W13 -> 32691 | X14: =W14-W13 -> 0 | Y14: =Y13 -> 801841 | Z14: =Y14-Y13 -> 0 | AA14: 35967 | AB14: =AA14-AA13 -> 17 | AC14: 968167 | AD14: =AC14-AC13 -> 3735 | AE14: =AB14+X14+T14 -> 17 | AF14: =V14+Z14+AD14 -> 3735 | AG14: =IF(AE14>0,AF14/AE14,0) -> 219.70588 | AI14: =R14-'EDl log'!B14 -> -1064389 | AJ14: 44358 | AK14: 373315 | AL14: 433992 | AM14: =AK14+AL14 -> 807307 | AN14: =AM14-AM13 -> 7647
A15: ='General information '!F17 -> 0 | B15: =SUM(230*A15) -> 0 | C15: 44359 | D15: =D14 -> 32911138 | E15: =AN15 -> 6192 | F15: 4039917 | G15: =F15-F14 -> 669 | H15: 17895866 | I15: =H15-H14 -> 940 | J15: 29189448 | K15: =J15-J14 -> 2518 | L15: 24263104 | M15: =L15-L14 -> 2178 | N15: =M15+K15+I15+G15+E15 -> 12497 | O15: =IF(B15>0,N15/B15,0) -> 0 | P15: 17357.442 | Q15: =(P15-P14)*1000 -> 11450 | R15: =N15-Q15 -> 1047 | S15: =S14 -> 10175 | T15: =S15-S14 -> 0 | U15: =U14 -> 429166 | V15: =U15-U14 -> 0 | W15: =W14 -> 32691 | X15: =W15-W14 -> 0 | Y15: =Y14 -> 801841 | Z15: =Y15-Y14 -> 0 | AA15: 35982 | AB15: =AA15-AA14 -> 15 | AC15: 971276 | AD15: =AC15-AC14 -> 3109 | AE15: =AB15+X15+T15 -> 15 | AF15: =V15+Z15+AD15 -> 3109 | AG15: =IF(AE15>0,AF15/AE15,0) -> 207.26667 | AI15: =R15-'EDl log'!B15 -> -1064651 | AJ15: 44359 | AK15: 379256 | AL15: 434243 | AM15: =AK15+AL15 -> 813499 | AN15: =AM15-AM14 -> 6192
A16: ='General information '!F18 -> 0 | B16: =SUM(230*A16) -> 0 | C16: 44360 | D16: =D15 -> 32911138 | E16: =AN16 -> 6129 | F16: 4040590 | G16: =F16-F15 -> 673 | H16: 17896880 | I16: =H16-H15 -> 1014 | J16: 29191686 | K16: =J16-J15 -> 2238 | L16: 24265604 | M16: =L16-L15 -> 2500 | N16: =M16+K16+I16+G16+E16 -> 12554 | O16: =IF(B16>0,N16/B16,0) -> 0 | P16: 17370.71 | Q16: =(P16-P15)*1000 -> 13268 | R16: =N16-Q16 -> -714 | S16: =S15 -> 10175 | T16: =S16-S15 -> 0 | U16: =U15 -> 429166 | V16: =U16-U15 -> 0 | W16: 32691 | X16: =W16-W15 -> 0 | Y16: =Y15 -> 801841 | Z16: =Y16-Y15 -> 0 | AA16: 35999 | AB16: =AA16-AA15 -> 17 | AC16: 974628 | AD16: =AC16-AC15 -> 3352 | AE16: =AB16+X16+T16 -> 17 | AF16: =V16+Z16+AD16 -> 3352 | AG16: =IF(AE16>0,AF16/AE16,0) -> 197.17647 | AI16: =R16-'EDl log'!B16 -> -1066998 | AJ16: 44360 | AK16: 385143 | AL16: 434485 | AM16: =AK16+AL16 -> 819628 | AN16: =AM16-AM15 -> 6129
A17: ='General information '!F19 -> 0 | B17: =SUM(230*A17) -> 0 | C17: 44361 | D17: =D16 -> 32911138 | E17: =AN17 -> 5834 | F17: 4041248 | G17: =F17-F16 -> 658 | H17: 17897710 | I17: =H17-H16 -> 830 | J17: 29193802 | K17: =J17-J16 -> 2116 | L17: 24267546 | M17: =L17-L16 -> 1942 | N17: =M17+K17+I17+G17+E17 -> 11380 | O17: =IF(B17>0,N17/B17,0) -> 0 | P17: 17379.304 | Q17: =(P17-P16)*1000 -> 8594 | R17: =N17-Q17 -> 2786 | S17: =S16 -> 10175 | T17: =S17-S16 -> 0 | U17: =U16 -> 429166 | V17: =U17-U16 -> 0 | W17: 32691 | X17: =W17-W16 -> 0 | Y17: =Y16 -> 801841 | Z17: =Y17-Y16 -> 0 | AA17: 36014 | AB17: =AA17-AA16 -> 15 | AC17: 977695 | AD17: =AC17-AC16 -> 3067 | AE17: =AB17+X17+T17 -> 15 | AF17: =V17+Z17+AD17 -> 3067 | AG17: =IF(AE17>0,AF17/AE17,0) -> 204.46667 | AI17: =R17-'EDl log'!B17 -> -1064217 | AJ17: 44361 | AK17: 390620 | AL17: 434842 | AM17: =AK17+AL17 -> 825462 | AN17: =AM17-AM16 -> 5834
A18: ='General information '!F20 -> 0 | B18: =SUM(230*A18) -> 0 | C18: 44362 | D18: =D17 -> 32911138 | E18: =AN18 -> 4340 | F18: 4041954 | G18: =F18-F17 -> 706 | H18: 17898706 | I18: =H18-H17 -> 996 | J18: 29198626 | K18: =J18-J17 -> 4824 | L18: 24269870 | M18: =L18-L17 -> 2324 | N18: =M18+K18+I18+G18+E18 -> 13190 | O18: =IF(B18>0,N18/B18,0) -> 0 | P18: 17391.748 | Q18: =(P18-P17)*1000 -> 12444 | R18: =N18-Q18 -> 746 | S18: =S17 -> 10175 | T18: =S18-S17 -> 0 | U18: =U17 -> 429166 | V18: =U18-U17 -> 0 | W18: 32702 | X18: =W18-W17 -> 11 | Y18: 804179 | Z18: =Y18-Y17 -> 2338 | AA18: 36020 | AB18: =AA18-AA17 -> 6 | AC18: 978935 | AD18: =AC18-AC17 -> 1240 | AE18: =AB18+X18+T18 -> 17 | AF18: =V18+Z18+AD18 -> 3578 | AG18: =IF(AE18>0,AF18/AE18,0) -> 210.47059 | AI18: =R18-'EDl log'!B18 -> -1066782 | AJ18: 44362 | AK18: 394712 | AL18: 435090 | AM18: =AK18+AL18 -> 829802 | AN18: =AM18-AM17 -> 4340
A19: ='General information '!F21 -> 0 | B19: =SUM(230*A19) -> 0 | C19: 44363 | D19: =D18 -> 32911138 | E19: =AN19 -> 4710 | F19: 4042661 | G19: =F19-F18 -> 707 | H19: 17899744 | I19: =H19-H18 -> 1038 | J19: 29202094 | K19: =J19-J18 -> 3468 | L19: 24272214 | M19: =L19-L18 -> 2344 | N19: =M19+K19+I19+G19+E19 -> 12267 | O19: =IF(B19>0,N19/B19,0) -> 0 | P19: 17405.023 | Q19: =(P19-P18)*1000 -> 13275 | R19: =N19-Q19 -> -1008 | S19: =S18 -> 10175 | T19: =S19-S18 -> 0 | U19: =U18 -> 429166 | V19: =U19-U18 -> 0 | W19: 32709 | X19: =W19-W18 -> 7 | Y19: 805616 | Z19: =Y19-Y18 -> 1437 | AA19: 36028 | AB19: =AA19-AA18 -> 8 | AC19: 980604 | AD19: =AC19-AC18 -> 1669 | AE19: =AB19+X19+T19 -> 15 | AF19: =V19+Z19+AD19 -> 3106 | AG19: =IF(AE19>0,AF19/AE19,0) -> 207.06667 | AI19: =R19-'EDl log'!B19 -> -1069350 | AJ19: 44363 | AK19: 399112 | AL19: 435400 | AM19: =AK19+AL19 -> 834512 | AN19: =AM19-AM18 -> 4710
A20: ='General information '!F22 -> 0 | B20: =SUM(230*A20) -> 0 | C20: 44364 | D20: =D19 -> 32911138 | E20: =AN20 -> 6488 | F20: 4043434 | G20: =F20-F19 -> 773 | H20: 17900838 | I20: =H20-H19 -> 1094 | J20: 29204422 | K20: =J20-J19 -> 2328 | L20: 24274486 | M20: =L20-L19 -> 2272 | N20: =M20+K20+I20+G20+E20 -> 12955 | O20: =IF(B20>0,N20/B20,0) -> 0 | P20: 17415.1 | Q20: =(P20-P19)*1000 -> 10077 | R20: =N20-Q20 -> 2878 | S20: =S19 -> 10175 | T20: =S20-S19 -> 0 | U20: =U19 -> 429166 | V20: =U20-U19 -> 0 | W20: 32709 | X20: =W20-W19 -> 0 | Y20: =Y19 -> 805616 | Z20: =Y20-Y19 -> 0 | AA20: 36044 | AB20: =AA20-AA19 -> 16 | AC20: 983863 | AD20: =AC20-AC19 -> 3259 | AE20: =AB20+X20+T20 -> 16 | AF20: =V20+Z20+AD20 -> 3259 | AG20: =IF(AE20>0,AF20/AE20,0) -> 203.6875 | AI20: =R20-'EDl log'!B20 -> -1065945 | AJ20: 44364 | AK20: 405216 | AL20: 435784 | AM20: =AK20+AL20 -> 841000 | AN20: =AM20-AM19 -> 6488
A21: ='General information '!F23 -> 0 | B21: =SUM(230*A21) -> 0 | C21: 44365 | D21: =D20 -> 32911138 | E21: =AN21 -> 0 | F21: =F20 -> 4043434 | G21: =F21-F20 -> 0 | H21: =H20 -> 17900838 | I21: =H21-H20 -> 0 | J21: =J20 -> 29204422 | K21: =J21-J20 -> 0 | L21: =L20 -> 24274486 | M21: =L21-L20 -> 0 | N21: =M21+K21+I21+G21+E21 -> 0 | O21: =IF(B21>0,N21/B21,0) -> 0 | P21: =P20 -> 17415.1 | Q21: =(P21-P20)*1000 -> 0 | R21: =N21-Q21 -> 0 | S21: =S20 -> 10175 | T21: =S21-S20 -> 0 | U21: =U20 -> 429166 | V21: =U21-U20 -> 0 | W21: =W20 -> 32709 | X21: =W21-W20 -> 0 | Y21: =Y20 -> 805616 | Z21: =Y21-Y20 -> 0 | AA21: =AA20 -> 36044 | AB21: =AA21-AA20 -> 0 | AC21: =AC20 -> 983863 | AD21: =AC21-AC20 -> 0 | AE21: =AB21+X21+T21 -> 0 | AF21: =V21+Z21+AD21 -> 0 | AG21: =IF(AE21>0,AF21/AE21,0) -> 0 | AI21: =R21-'EDl log'!B21 -> -1068823 | AJ21: 44365 | AK21: =AK20 -> 405216 | AL21: =AL20 -> 435784 | AM21: =AK21+AL21 -> 841000 | AN21: =AM21-AM20 -> 0
A22: ='General information '!F24 -> 0 | B22: =SUM(230*A22) -> 0 | C22: 44366 | D22: =D21 -> 32911138 | E22: =AN22 -> 0 | F22: =F21 -> 4043434 | G22: =F22-F21 -> 0 | H22: =H21 -> 17900838 | I22: =H22-H21 -> 0 | J22: =J21 -> 29204422 | K22: =J22-J21 -> 0 | L22: =L21 -> 24274486 | M22: =L22-L21 -> 0 | N22: =M22+K22+I22+G22+E22 -> 0 | O22: =IF(B22>0,N22/B22,0) -> 0 | P22: =P21 -> 17415.1 | Q22: =(P22-P21)*1000 -> 0 | R22: =N22-Q22 -> 0 | S22: =S21 -> 10175 | T22: =S22-S21 -> 0 | U22: =U21 -> 429166 | V22: =U22-U21 -> 0 | W22: =W21 -> 32709 | X22: =W22-W21 -> 0 | Y22: =Y21 -> 805616 | Z22: =Y22-Y21 -> 0 | AA22: =AA21 -> 36044 | AB22: =AA22-AA21 -> 0 | AC22: =AC21 -> 983863 | AD22: =AC22-AC21 -> 0 | AE22: =AB22+X22+T22 -> 0 | AF22: =V22+Z22+AD22 -> 0 | AG22: =IF(AE22>0,AF22/AE22,0) -> 0 | AI22: =R22-'EDl log'!B22 -> -1068823 | AJ22: 44366 | AK22: =AK21 -> 405216 | AL22: =AL21 -> 435784 | AM22: =AK22+AL22 -> 841000 | AN22: =AM22-AM21 -> 0
A23: ='General information '!F25 -> 0 | B23: =SUM(230*A23) -> 0 | C23: 44367 | D23: =D22 -> 32911138 | E23: =AN23 -> 0 | F23: =F22 -> 4043434 | G23: =F23-F22 -> 0 | H23: =H22 -> 17900838 | I23: =H23-H22 -> 0 | J23: =J22 -> 29204422 | K23: =J23-J22 -> 0 | L23: =L22 -> 24274486 | M23: =L23-L22 -> 0 | N23: =M23+K23+I23+G23+E23 -> 0 | O23: =IF(B23>0,N23/B23,0) -> 0 | P23: =P22 -> 17415.1 | Q23: =(P23-P22)*1000 -> 0 | R23: =N23-Q23 -> 0 | S23: =S22 -> 10175 | T23: =S23-S22 -> 0 | U23: =U22 -> 429166 | V23: =U23-U22 -> 0 | W23: =W22 -> 32709 | X23: =W23-W22 -> 0 | Y23: =Y22 -> 805616 | Z23: =Y23-Y22 -> 0 | AA23: =AA22 -> 36044 | AB23: =AA23-AA22 -> 0 | AC23: =AC22 -> 983863 | AD23: =AC23-AC22 -> 0 | AE23: =AB23+X23+T23 -> 0 | AF23: =V23+Z23+AD23 -> 0 | AG23: =IF(AE23>0,AF23/AE23,0) -> 0 | AI23: =R23-'EDl log'!B23 -> -1068823 | AJ23: 44367 | AK23: =AK22 -> 405216 | AL23: =AL22 -> 435784 | AM23: =AK23+AL23 -> 841000 | AN23: =AM23-AM22 -> 0
A24: ='General information '!F26 -> 0 | B24: =SUM(230*A24) -> 0 | C24: 44368 | D24: =D23 -> 32911138 | E24: =AN24 -> 0 | F24: =F23 -> 4043434 | G24: =F24-F23 -> 0 | H24: =H23 -> 17900838 | I24: =H24-H23 -> 0 | J24: =J23 -> 29204422 | K24: =J24-J23 -> 0 | L24: =L23 -> 24274486 | M24: =L24-L23 -> 0 | N24: =M24+K24+I24+G24+E24 -> 0 | O24: =IF(B24>0,N24/B24,0) -> 0 | P24: =P23 -> 17415.1 | Q24: =(P24-P23)*1000 -> 0 | R24: =N24-Q24 -> 0 | S24: =S23 -> 10175 | T24: =S24-S23 -> 0 | U24: =U23 -> 429166 | V24: =U24-U23 -> 0 | W24: =W23 -> 32709 | X24: =W24-W23 -> 0 | Y24: =Y23 -> 805616 | Z24: =Y24-Y23 -> 0 | AA24: =AA23 -> 36044 | AB24: =AA24-AA23 -> 0 | AC24: =AC23 -> 983863 | AD24: =AC24-AC23 -> 0 | AE24: =AB24+X24+T24 -> 0 | AF24: =V24+Z24+AD24 -> 0 | AG24: =IF(AE24>0,AF24/AE24,0) -> 0 | AI24: =R24-'EDl log'!B24 -> -1068823 | AJ24: 44368 | AK24: =AK23 -> 405216 | AL24: =AL23 -> 435784 | AM24: =AK24+AL24 -> 841000 | AN24: =AM24-AM23 -> 0
A25: ='General information '!F27 -> 0 | B25: =SUM(230*A25) -> 0 | C25: 44369 | D25: =D24 -> 32911138 | E25: =AN25 -> 0 | F25: =F24 -> 4043434 | G25: =F25-F24 -> 0 | H25: =H24 -> 17900838 | I25: =H25-H24 -> 0 | J25: =J24 -> 29204422 | K25: =J25-J24 -> 0 | L25: =L24 -> 24274486 | M25: =L25-L24 -> 0 | N25: =M25+K25+I25+G25+E25 -> 0 | O25: =IF(B25>0,N25/B25,0) -> 0 | P25: =P24 -> 17415.1 | Q25: =(P25-P24)*1000 -> 0 | R25: =N25-Q25 -> 0 | S25: =S24 -> 10175 | T25: =S25-S24 -> 0 | U25: =U24 -> 429166 | V25: =U25-U24 -> 0 | W25: =W24 -> 32709 | X25: =W25-W24 -> 0 | Y25: =Y24 -> 805616 | Z25: =Y25-Y24 -> 0 | AA25: =AA24 -> 36044 | AB25: =AA25-AA24 -> 0 | AC25: =AC24 -> 983863 | AD25: =AC25-AC24 -> 0 | AE25: =AB25+X25+T25 -> 0 | AF25: =V25+Z25+AD25 -> 0 | AG25: =IF(AE25>0,AF25/AE25,0) -> 0 | AI25: =R25-'EDl log'!B25 -> -1068823 | AJ25: 44369 | AK25: =AK24 -> 405216 | AL25: =AL24 -> 435784 | AM25: =AK25+AL25 -> 841000 | AN25: =AM25-AM24 -> 0
A26: ='General information '!F28 -> 0 | B26: =SUM(230*A26) -> 0 | C26: 44370 | D26: =D25 -> 32911138 | E26: =AN26 -> 0 | F26: =F25 -> 4043434 | G26: =F26-F25 -> 0 | H26: =H25 -> 17900838 | I26: =H26-H25 -> 0 | J26: =J25 -> 29204422 | K26: =J26-J25 -> 0 | L26: =L25 -> 24274486 | M26: =L26-L25 -> 0 | N26: =M26+K26+I26+G26+E26 -> 0 | O26: =IF(B26>0,N26/B26,0) -> 0 | P26: =P25 -> 17415.1 | Q26: =(P26-P25)*1000 -> 0 | R26: =N26-Q26 -> 0 | S26: =S25 -> 10175 | T26: =S26-S25 -> 0 | U26: =U25 -> 429166 | V26: =U26-U25 -> 0 | W26: =W25 -> 32709 | X26: =W26-W25 -> 0 | Y26: =Y25 -> 805616 | Z26: =Y26-Y25 -> 0 | AA26: =AA25 -> 36044 | AB26: =AA26-AA25 -> 0 | AC26: =AC25 -> 983863 | AD26: =AC26-AC25 -> 0 | AE26: =AB26+X26+T26 -> 0 | AF26: =V26+Z26+AD26 -> 0 | AG26: =IF(AE26>0,AF26/AE26,0) -> 0 | AI26: =R26-'EDl log'!B26 -> -1068823 | AJ26: 44370 | AK26: =AK25 -> 405216 | AL26: =AL25 -> 435784 | AM26: =AK26+AL26 -> 841000 | AN26: =AM26-AM25 -> 0
A27: ='General information '!F29 -> 0 | B27: =SUM(230*A27) -> 0 | C27: 44371 | D27: =D26 -> 32911138 | E27: =AN27 -> 0 | F27: =F26 -> 4043434 | G27: =F27-F26 -> 0 | H27: =H26 -> 17900838 | I27: =H27-H26 -> 0 | J27: =J26 -> 29204422 | K27: =J27-J26 -> 0 | L27: =L26 -> 24274486 | M27: =L27-L26 -> 0 | N27: =M27+K27+I27+G27+E27 -> 0 | O27: =IF(B27>0,N27/B27,0) -> 0 | P27: =P26 -> 17415.1 | Q27: =(P27-P26)*1000 -> 0 | R27: =N27-Q27 -> 0 | S27: =S26 -> 10175 | T27: =S27-S26 -> 0 | U27: =U26 -> 429166 | V27: =U27-U26 -> 0 | W27: =W26 -> 32709 | X27: =W27-W26 -> 0 | Y27: =Y26 -> 805616 | Z27: =Y27-Y26 -> 0 | AA27: =AA26 -> 36044 | AB27: =AA27-AA26 -> 0 | AC27: =AC26 -> 983863 | AD27: =AC27-AC26 -> 0 | AE27: =AB27+X27+T27 -> 0 | AF27: =V27+Z27+AD27 -> 0 | AG27: =IF(AE27>0,AF27/AE27,0) -> 0 | AI27: =R27-'EDl log'!B27 -> -1068823 | AJ27: 44371 | AK27: =AK26 -> 405216 | AL27: =AL26 -> 435784 | AM27: =AK27+AL27 -> 841000 | AN27: =AM27-AM26 -> 0
A28: ='General information '!F30 -> 0 | B28: =SUM(230*A28) -> 0 | C28: 44372 | D28: =D27 -> 32911138 | E28: =AN28 -> 0 | F28: =F27 -> 4043434 | G28: =F28-F27 -> 0 | H28: =H27 -> 17900838 | I28: =H28-H27 -> 0 | J28: =J27 -> 29204422 | K28: =J28-J27 -> 0 | L28: =L27 -> 24274486 | M28: =L28-L27 -> 0 | N28: =M28+K28+I28+G28+E28 -> 0 | O28: =IF(B28>0,N28/B28,0) -> 0 | P28: =P27 -> 17415.1 | Q28: =(P28-P27)*1000 -> 0 | R28: =N28-Q28 -> 0 | S28: =S27 -> 10175 | T28: =S28-S27 -> 0 | U28: =U27 -> 429166 | V28: =U28-U27 -> 0 | W28: =W27 -> 32709 | X28: =W28-W27 -> 0 | Y28: =Y27 -> 805616 | Z28: =Y28-Y27 -> 0 | AA28: =AA27 -> 36044 | AB28: =AA28-AA27 -> 0 | AC28: =AC27 -> 983863 | AD28: =AC28-AC27 -> 0 | AE28: =AB28+X28+T28 -> 0 | AF28: =V28+Z28+AD28 -> 0 | AG28: =IF(AE28>0,AF28/AE28,0) -> 0 | AI28: =R28-'EDl log'!B28 -> -1068823 | AJ28: 44372 | AK28: =AK27 -> 405216 | AL28: =AL27 -> 435784 | AM28: =AK28+AL28 -> 841000 | AN28: =AM28-AM27 -> 0
A29: ='General information '!F31 -> 0 | B29: =SUM(230*A29) -> 0 | C29: 44373 | D29: =D28 -> 32911138 | E29: =AN29 -> 0 | F29: =F28 -> 4043434 | G29: =F29-F28 -> 0 | H29: =H28 -> 17900838 | I29: =H29-H28 -> 0 | J29: =J28 -> 29204422 | K29: =J29-J28 -> 0 | L29: =L28 -> 24274486 | M29: =L29-L28 -> 0 | N29: =M29+K29+I29+G29+E29 -> 0 | O29: =IF(B29>0,N29/B29,0) -> 0 | P29: =P28 -> 17415.1 | Q29: =(P29-P28)*1000 -> 0 | R29: =N29-Q29 -> 0 | S29: =S28 -> 10175 | T29: =S29-S28 -> 0 | U29: =U28 -> 429166 | V29: =U29-U28 -> 0 | W29: =W28 -> 32709 | X29: =W29-W28 -> 0 | Y29: =Y28 -> 805616 | Z29: =Y29-Y28 -> 0 | AA29: =AA28 -> 36044 | AB29: =AA29-AA28 -> 0 | AC29: =AC28 -> 983863 | AD29: =AC29-AC28 -> 0 | AE29: =AB29+X29+T29 -> 0 | AF29: =V29+Z29+AD29 -> 0 | AG29: =IF(AE29>0,AF29/AE29,0) -> 0 | AI29: =R29-'EDl log'!B29 -> -1068823 | AJ29: 44373 | AK29: =AK28 -> 405216 | AL29: =AL28 -> 435784 | AM29: =AK29+AL29 -> 841000 | AN29: =AM29-AM28 -> 0
A30: ='General information '!F32 -> 0 | B30: =SUM(230*A30) -> 0 | C30: 44374 | D30: =D29 -> 32911138 | E30: =AN30 -> 0 | F30: =F29 -> 4043434 | G30: =F30-F29 -> 0 | H30: =H29 -> 17900838 | I30: =H30-H29 -> 0 | J30: =J29 -> 29204422 | K30: =J30-J29 -> 0 | L30: =L29 -> 24274486 | M30: =L30-L29 -> 0 | N30: =M30+K30+I30+G30+E30 -> 0 | O30: =IF(B30>0,N30/B30,0) -> 0 | P30: =P29 -> 17415.1 | Q30: =(P30-P29)*1000 -> 0 | R30: =N30-Q30 -> 0 | S30: =S29 -> 10175 | T30: =S30-S29 -> 0 | U30: =U29 -> 429166 | V30: =U30-U29 -> 0 | W30: =W29 -> 32709 | X30: =W30-W29 -> 0 | Y30: =Y29 -> 805616 | Z30: =Y30-Y29 -> 0 | AA30: =AA29 -> 36044 | AB30: =AA30-AA29 -> 0 | AC30: =AC29 -> 983863 | AD30: =AC30-AC29 -> 0 | AE30: =AB30+X30+T30 -> 0 | AF30: =V30+Z30+AD30 -> 0 | AG30: =IF(AE30>0,AF30/AE30,0) -> 0 | AI30: =R30-'EDl log'!B30 -> -1068823 | AJ30: 44374 | AK30: =AK29 -> 405216 | AL30: =AL29 -> 435784 | AM30: =AK30+AL30 -> 841000 | AN30: =AM30-AM29 -> 0
A31: ='General information '!F33 -> 0 | B31: =SUM(230*A31) -> 0 | C31: 44375 | D31: =D30 -> 32911138 | E31: =AN31 -> 0 | F31: =F30 -> 4043434 | G31: =F31-F30 -> 0 | H31: =H30 -> 17900838 | I31: =H31-H30 -> 0 | J31: =J30 -> 29204422 | K31: =J31-J30 -> 0 | L31: =L30 -> 24274486 | M31: =L31-L30 -> 0 | N31: =M31+K31+I31+G31+E31 -> 0 | O31: =IF(B31>0,N31/B31,0) -> 0 | P31: =P30 -> 17415.1 | Q31: =(P31-P30)*1000 -> 0 | R31: =N31-Q31 -> 0 | S31: =S30 -> 10175 | T31: =S31-S30 -> 0 | U31: =U30 -> 429166 | V31: =U31-U30 -> 0 | W31: =W30 -> 32709 | X31: =W31-W30 -> 0 | Y31: =Y30 -> 805616 | Z31: =Y31-Y30 -> 0 | AA31: =AA30 -> 36044 | AB31: =AA31-AA30 -> 0 | AC31: =AC30 -> 983863 | AD31: =AC31-AC30 -> 0 | AE31: =AB31+X31+T31 -> 0 | AF31: =V31+Z31+AD31 -> 0 | AG31: =IF(AE31>0,AF31/AE31,0) -> 0 | AI31: =R31-'EDl log'!B31 -> -1068823 | AJ31: 44375 | AK31: =AK30 -> 405216 | AL31: =AL30 -> 435784 | AM31: =AK31+AL31 -> 841000 | AN31: =AM31-AM30 -> 0
A32: ='General information '!F34 -> 0 | B32: =SUM(230*A32) -> 0 | C32: 44376 | D32: =D31 -> 32911138 | E32: =AN32 -> 0 | F32: =F31 -> 4043434 | G32: =F32-F31 -> 0 | H32: =H31 -> 17900838 | I32: =H32-H31 -> 0 | J32: =J31 -> 29204422 | K32: =J32-J31 -> 0 | L32: =L31 -> 24274486 | M32: =L32-L31 -> 0 | N32: =M32+K32+I32+G32+E32 -> 0 | O32: =IF(B32>0,N32/B32,0) -> 0 | P32: =P31 -> 17415.1 | Q32: =(P32-P31)*1000 -> 0 | R32: =N32-Q32 -> 0 | S32: =S31 -> 10175 | T32: =S32-S31 -> 0 | U32: =U31 -> 429166 | V32: =U32-U31 -> 0 | W32: =W31 -> 32709 | X32: =W32-W31 -> 0 | Y32: =Y31 -> 805616 | Z32: =Y32-Y31 -> 0 | AA32: =AA31 -> 36044 | AB32: =AA32-AA31 -> 0 | AC32: =AC31 -> 983863 | AD32: =AC32-AC31 -> 0 | AE32: =AB32+X32+T32 -> 0 | AF32: =V32+Z32+AD32 -> 0 | AG32: =IF(AE32>0,AF32/AE32,0) -> 0 | AI32: =R32-'EDl log'!B32 -> -1068823 | AJ32: 44376 | AK32: =AK31 -> 405216 | AL32: =AL31 -> 435784 | AM32: =AK32+AL32 -> 841000 | AN32: =AM32-AM31 -> 0
A33: ='General information '!F35 -> 0 | B33: =SUM(230*A33) -> 0 | C33: 44377 | D33: =D32 -> 32911138 | E33: =AN33 -> 0 | F33: =F32 -> 4043434 | G33: =F33-F32 -> 0 | H33: =H32 -> 17900838 | I33: =H33-H32 -> 0 | J33: =J32 -> 29204422 | K33: =J33-J32 -> 0 | L33: =L32 -> 24274486 | M33: =L33-L32 -> 0 | N33: =M33+K33+I33+G33+E33 -> 0 | O33: =IF(B33>0,N33/B33,0) -> 0 | P33: =P32 -> 17415.1 | Q33: =(P33-P32)*1000 -> 0 | R33: =N33-Q33 -> 0 | S33: =S32 -> 10175 | T33: =S33-S32 -> 0 | U33: =U32 -> 429166 | V33: =U33-U32 -> 0 | W33: =W32 -> 32709 | X33: =W33-W32 -> 0 | Y33: =Y32 -> 805616 | Z33: =Y33-Y32 -> 0 | AA33: =AA32 -> 36044 | AB33: =AA33-AA32 -> 0 | AC33: =AC32 -> 983863 | AD33: =AC33-AC32 -> 0 | AE33: =AB33+X33+T33 -> 0 | AF33: =V33+Z33+AD33 -> 0 | AG33: =IF(AE33>0,AF33/AE33,0) -> 0 | AI33: =R33-'EDl log'!B33 -> -1068823 | AJ33: 44377 | AK33: =AK32 -> 405216 | AL33: =AL32 -> 435784 | AM33: =AK33+AL33 -> 841000 | AN33: =AM33-AM32 -> 0

Sheet B5
F1: Boiler A | J1: =J35 -> 63.722222 | K1: Boiler B | P1: Boiler C | V1: Boiler | X1: SteamA | AC1: SteamB | AH1: Steam | AI1: Boiler & steam | AL1: Total Boiler Runing H | AM1: Total Steam Runing H | AN1: GAS1 % | AO1: GAS1/L | AP1: GAS2% | AQ1: Gas2/L | AR1: GAS3% | AS1: GAS3/L | AU1: Gas Cons | AV1: Delivery | AW1: Cost/L
B2: Level Tank Gen | C2: Level tank Boiler | D2: Daily Cons Bo. | E2: Boiler litter | F2: Boiler A | G2: Run Hr a | H2: Boiler A fuel | I2: Daily consumption | J2: AVG | K2: index Run H | L2: Run Hrb | M2: Boiler B Fuel | O2: Daily consumption | P2: Boiler C | S2: Run C | U2: Total RH | V2: Total Fuel | X2: SteamA | Y2: Run SA | Z2: Steam A Conter | AA2: Liters | AC2: SteamB | AD2: Run SteamB | AE2: Steam B Conter | AF2: SB Litters | AG2: Avg | AH2: Total Fuel | AI2: Total Fuel
S3: 0
A4: =ELEC!C3 -> 44347 | B4: =[3]B5!B35 -> 207 | C4: =[3]B5!C35 -> 214 | D4: =[3]B5!D35 -> -27 | E4: =[3]B5!E35 -> -226.26 | F4: =[3]B5!F35 -> 1841 | G4: =[3]B5!G35 -> 1 | H4: =[3]B5!H35 -> 13408 | I4: =[3]B5!I35 -> 96 | ... AX4: =[3]B5!AX35 -> 0.8
A5: =ELEC!C4 -> 44348 | B5: 191 | C5: 204 | D5: =C4-C5 -> 10 | E5: =D5*8.38 -> 83.8 | F5: =F4 -> 1841 | G5: =F5-F4 -> 0 | H5: 13425 | I5: =SUM(H5-H4) -> 17 | J5: 1 | K5: =K4 -> 2331 | L5: =K5-K4 -> 0 | M5: =M4 -> 171898 | N5: =M5-M4 -> 0 | O5: =O4 -> 1869 | P5: =P4 -> 2096 | Q5: 176252 | R5: =Q5-Q4 -> 46 | S5: =SUM(P5-P4) -> 0 | T5: =SUM(S5*$T$2) -> 0 | U5: =SUM(G5+L5+S5) -> 0 | V5: =R5+N5+I5:I5 -> 63 | W5: =SUM(V5/U5) -> #DIV/0! | X5: 2469 | Y5: =X5-X4 -> 0 | Z5: 138993 | AA5: =Z5-Z4 -> 0 | AB5: =SUM(Y5*$AB$2) -> 0 | AC5: =AC4 -> 1937 | AD5: =AC5-AC4 -> 0 | AE5: 365634 | AF5: =AE5-AE4 -> 44 | AG5: =IF(AD5>0,AF5/AD5,0) -> 0 | AH5: =AF5+AA5 -> 44 | AI5: =SUM(AH5+V5) -> 107 | AJ5: =-tanks!AW6 -> 107 | AK5: =SUM(AJ5-AI5) -> 0 | AL5: =S5+L5+G5 -> 0 | AM5: =Y5+AD5 -> 0 | AN5: =AN4 -> 67 | AO5: =(AN5/100)*3000 -> 2010 | AP5: =AP4 -> 55 | AQ5: =(AP5/100)*3000 -> 1650 | AR5: =AR4 -> 61 | AS5: =(AR5/100)*3000 -> 1830 | AT5: =SUM(AO5+AQ5+AS5) -> 5490 | AU5: =AT4-AT5+AV5 -> 0 | AX5: =IF(AV5>0,AW5,AX4) -> 0.8
A6: =ELEC!C5 -> 44349 | B6: 185 | C6: 192 | D6: =C5-C6 -> 12 | E6: =D6*8.38 -> 100.56 | F6: 1842 | G6: =F6-F5 -> 1 | H6: 13519 | I6: =SUM(H6-H5) -> 94 | J6: =IF(G6>0,I6/G6,0) -> 94 | K6: =K5 -> 2331 | L6: =K6-K5 -> 0 | M6: =M5 -> 171898 | N6: =M6-M5 -> 0 | O6: =O5 -> 1869 | P6: 2097 | Q6: 176286 | R6: =Q6-Q5 -> 34 | S6: =SUM(P6-P5) -> 1 | T6: =SUM(S6*$T$2) -> 0 | U6: =SUM(G6+L6+S6) -> 2 | V6: =R6+N6+I6:I6 -> 128 | W6: =SUM(V6/U6) -> 64 | X6: =X5 -> 2469 | Y6: =X6-X5 -> 0 | Z6: =Z5 -> 138993 | AA6: =Z6-Z5 -> 0 | AB6: =SUM(Y6*$AB$2) -> 0 | AC6: =AC5 -> 1937 | AD6: =AC6-AC5 -> 0 | AE6: =AE5 -> 365634 | AF6: =AE6-AE5 -> 0 | AG6: =IF(AD6>0,AF6/AD6,0) -> 0 | AH6: =AF6+AA6 -> 0 | AI6: =SUM(AH6+V6) -> 128 | AJ6: =-tanks!AW7 -> 128 | AK6: =SUM(AJ6-AI6) -> 0 | AL6: =S6+L6+G6 -> 2 | AM6: =Y6+AD6 -> 0 | AN6: =AN5 -> 67 | AO6: =(AN6/100)*3000 -> 2010 | AP6: =AP5 -> 55 | AQ6: =(AP6/100)*3000 -> 1650 | AR6: =AR5 -> 61 | AS6: =(AR6/100)*3000 -> 1830 | AT6: =SUM(AO6+AQ6+AS6) -> 5490 | AU6: =AT5-AT6+AV6 -> 0 | AX6: =IF(AV6>0,AW6,AX5) -> 0.8
A7: =ELEC!C6 -> 44350 | B7: 228 | C7: 235 | D7: =C6-C7 -> -43 | E7: =D7*8.38 -> -360.34 | F7: 1843 | G7: =F7-F6 -> 1 | H7: 13578 | I7: =SUM(H7-H6) -> 59 | J7: =IF(G7>0,I7/G7,0) -> 59 | K7: 2332 | L7: =K7-K6 -> 1 | M7: 171964 | N7: =M7-M6 -> 66 | O7: =O6 -> 1869 | P7: =P6 -> 2097 | Q7: =Q6 -> 176286 | R7: =Q7-Q6 -> 0 | S7: =SUM(P7-P6) -> 0 | T7: =SUM(S7*$T$2) -> 0 | U7: =SUM(G7+L7+S7) -> 2 | V7: =R7+N7+I7:I7 -> 125 | W7: =SUM(V7/U7) -> 62.5 | X7: =X6 -> 2469 | Y7: =X7-X6 -> 0 | Z7: =Z6 -> 138993 | AA7: =Z7-Z6 -> 0 | AB7: =SUM(Y7*$AB$2) -> 0 | AC7: =AC6 -> 1937 | AD7: =AC7-AC6 -> 0 | AE7: =AE6 -> 365634 | AF7: =AE7-AE6 -> 0 | AG7: =IF(AD7>0,AF7/AD7,0) -> 0 | AH7: =AF7+AA7 -> 0 | AI7: =SUM(AH7+V7) -> 125 | AJ7: =-tanks!AW8 -> 125 | AK7: =SUM(AJ7-AI7) -> 0 | AL7: =S7+L7+G7 -> 2 | AM7: =Y7+AD7 -> 0 | AN7: =AN6 -> 67 | AO7: =(AN7/100)*3000 -> 2010 | AP7: =AP6 -> 55 | AQ7: =(AP7/100)*3000 -> 1650 | AR7: =AR6 -> 61 | AS7: =(AR7/100)*3000 -> 1830 | AT7: =SUM(AO7+AQ7+AS7) -> 5490 | AU7: =AT6-AT7+AV7 -> 0 | AX7: =IF(AV7>0,AW7,AX6) -> 0.8
A8: =ELEC!C7 -> 44351 | B8: 218 | C8: 225 | D8: =C7-C8 -> 10 | E8: =D8*8.38 -> 83.8 | F8: =F7 -> 1843 | G8: =F8-F7 -> 0 | H8: =H7 -> 13578 | I8: =SUM(H8-H7) -> 0 | J8: =IF(G8>0,I8/G8,0) -> 0 | K8: 2332 | L8: =K8-K7 -> 0 | M8: 171994 | N8: =M8-M7 -> 30 | O8: =O7 -> 1869 | P8: 2098 | Q8: 176347 | R8: =Q8-Q7 -> 61 | S8: =SUM(P8-P7) -> 1 | T8: =SUM(S8*$T$2) -> 0 | U8: =SUM(G8+L8+S8) -> 1 | V8: =R8+N8+I8:I8 -> 91 | W8: =SUM(V8/U8) -> 91 | X8: =X7 -> 2469 | Y8: =X8-X7 -> 0 | Z8: =Z7 -> 138993 | AA8: =Z8-Z7 -> 0 | AB8: =SUM(Y8*$AB$2) -> 0 | AC8: =AC7 -> 1937 | AD8: =AC8-AC7 -> 0 | AE8: =AE7 -> 365634 | AF8: =AE8-AE7 -> 0 | AG8: =IF(AD8>0,AF8/AD8,0) -> 0 | AH8: =AF8+AA8 -> 0 | AI8: =SUM(AH8+V8) -> 91 | AJ8: =-tanks!AW9 -> 91 | AK8: =SUM(AJ8-AI8) -> 0 | AL8: =S8+L8+G8 -> 1 | AM8: =Y8+AD8 -> 0 | AN8: =AN7 -> 67 | AO8: =(AN8/100)*3000 -> 2010 | AP8: =AP7 -> 55 | AQ8: =(AP8/100)*3000 -> 1650 | AR8: =AR7 -> 61 | AS8: =(AR8/100)*3000 -> 1830 | AT8: =SUM(AO8+AQ8+AS8) -> 5490 | AU8: =AT7-AT8+AV8 -> 0 | AX8: =IF(AV8>0,AW8,AX7) -> 0.8
A9: =ELEC!C8 -> 44352 | B9: 201 | C9: 208 | D9: =C8-C9 -> 17 | E9: =D9*8.38 -> 142.46 | F9: 1844 | G9: =F9-F8 -> 1 | H9: 13635 | I9: =SUM(H9-H8) -> 57 | J9: =IF(G9>0,I9/G9,0) -> 57 | K9: =K8 -> 2332 | L9: =K9-K8 -> 0 | M9: =M8 -> 171994 | N9: =M9-M8 -> 0 | O9: =O8 -> 1869 | P9: 2099 | Q9: 176465 | R9: =Q9-Q8 -> 118 | S9: =SUM(P9-P8) -> 1 | T9: =SUM(S9*$T$2) -> 0 | U9: =SUM(G9+L9+S9) -> 2 | V9: =R9+N9+I9:I9 -> 175 | W9: =SUM(V9/U9) -> 87.5 | X9: =X8 -> 2469 | Y9: =X9-X8 -> 0 | Z9: =Z8 -> 138993 | AA9: =Z9-Z8 -> 0 | AB9: =SUM(Y9*$AB$2) -> 0 | AC9: 1938 | AD9: =AC9-AC8 -> 1 | AE9: 365701 | AF9: =AE9-AE8 -> 67 | AG9: =IF(AD9>0,AF9/AD9,0) -> 67 | AH9: =AF9+AA9 -> 67 | AI9: =SUM(AH9+V9) -> 242 | AJ9: =-tanks!AW10 -> 242 | AK9: =SUM(AJ9-AI9) -> 0 | AL9: =S9+L9+G9 -> 2 | AM9: =Y9+AD9 -> 1 | AN9: =AN8 -> 67 | AO9: =(AN9/100)*3000 -> 2010 | AP9: =AP8 -> 55 | AQ9: =(AP9/100)*3000 -> 1650 | AR9: =AR8 -> 61 | AS9: =(AR9/100)*3000 -> 1830 | AT9: =SUM(AO9+AQ9+AS9) -> 5490 | AU9: =AT8-AT9+AV9 -> 0 | AX9: =IF(AV9>0,AW9,AX8) -> 0.8
A10: =ELEC!C9 -> 44353 | B10: 188 | C10: 194 | D10: =C9-C10 -> 14 | E10: =D10*8.38 -> 117.32 | F10: =F9 -> 1844 | G10: =F10-F9 -> 0 | H10: 13664 | I10: =SUM(H10-H9) -> 29 | J10: =IF(G10>0,I10/G10,0) -> 0 | K10: 2333 | L10: =K10-K9 -> 1 | M10: 172051 | N10: =M10-M9 -> 57 | O10: =O9 -> 1869 | P10: =P9 -> 2099 | Q10: 176481 | R10: =Q10-Q9 -> 16 | S10: =SUM(P10-P9) -> 0 | T10: =SUM(S10*$T$2) -> 0 | U10: =SUM(G10+L10+S10) -> 1 | V10: =R10+N10+I10:I10 -> 102 | W10: =SUM(V10/U10) -> 102 | X10: 2470 | Y10: =X10-X9 -> 1 | Z10: 139083 | AA10: =Z10-Z9 -> 90 | AB10: =SUM(Y10*$AB$2) -> 0 | AC10: =AC9 -> 1938 | AD10: =AC10-AC9 -> 0 | AE10: =AE9 -> 365701 | AF10: =AE10-AE9 -> 0 | AG10: =IF(AD10>0,AF10/AD10,0) -> 0 | AH10: =AF10+AA10 -> 90 | AI10: =SUM(AH10+V10) -> 192 | AJ10: =-tanks!AW11 -> 192 | AK10: =SUM(AJ10-AI10) -> 0 | AL10: =S10+L10+G10 -> 1 | AM10: =Y10+AD10 -> 1 | AN10: =AN9 -> 67 | AO10: =(AN10/100)*3000 -> 2010 | AP10: =AP9 -> 55 | AQ10: =(AP10/100)*3000 -> 1650 | AR10: =AR9 -> 61 | AS10: =(AR10/100)*3000 -> 1830 | AT10: =SUM(AO10+AQ10+AS10) -> 5490 | AU10: =AT9-AT10+AV10 -> 0 | AX10: =IF(AV10>0,AW10,AX9) -> 0.8
A11: =ELEC!C10 -> 44354 | B11: 228 | C11: 234 | D11: =C10-C11 -> -40 | E11: =D11*8.38 -> -335.2 | F11: =F10 -> 1844 | G11: =F11-F10 -> 0 | H11: =H10 -> 13664 | I11: =SUM(H11-H10) -> 0 | J11: =IF(G11>0,I11/G11,0) -> 0 | K11: =K10 -> 2333 | L11: =K11-K10 -> 0 | M11: =M10 -> 172051 | N11: =M11-M10 -> 0 | O11: =O10 -> 1869 | P11: 2100 | Q11: 176535 | R11: =Q11-Q10 -> 54 | S11: =SUM(P11-P10) -> 1 | T11: =SUM(S11*$T$2) -> 0 | U11: =SUM(G11+L11+S11) -> 1 | V11: =R11+N11+I11:I11 -> 54 | W11: =SUM(V11/U11) -> 54 | X11: =X10 -> 2470 | Y11: =X11-X10 -> 0 | Z11: =Z10 -> 139083 | AA11: =Z11-Z10 -> 0 | AB11: =SUM(Y11*$AB$2) -> 0 | AC11: =AC10 -> 1938 | AD11: =AC11-AC10 -> 0 | AE11: =AE10 -> 365701 | AF11: =AE11-AE10 -> 0 | AG11: =IF(AD11>0,AF11/AD11,0) -> 0 | AH11: =AF11+AA11 -> 0 | AI11: =SUM(AH11+V11) -> 54 | AJ11: =-tanks!AW12 -> 54 | AK11: =SUM(AJ11-AI11) -> 0 | AL11: =S11+L11+G11 -> 1 | AM11: =Y11+AD11 -> 0 | AN11: =AN10 -> 67 | AO11: =(AN11/100)*3000 -> 2010 | AP11: =AP10 -> 55 | AQ11: =(AP11/100)*3000 -> 1650 | AR11: =AR10 -> 61 | AS11: =(AR11/100)*3000 -> 1830 | AT11: =SUM(AO11+AQ11+AS11) -> 5490 | AU11: =AT10-AT11+AV11 -> 0 | AX11: =IF(AV11>0,AW11,AX10) -> 0.8
A12: =ELEC!C11 -> 44355 | B12: 216 | C12: 223 | D12: =C11-C12 -> 11 | E12: =D12*8.38 -> 92.18 | F12: 1845 | G12: =F12-F11 -> 1 | H12: 13720 | I12: =SUM(H12-H11) -> 56 | J12: =IF(G12>0,I12/G12,0) -> 56 | K12: =K11 -> 2333 | L12: =K12-K11 -> 0 | M12: =M11 -> 172051 | N12: =M12-M11 -> 0 | O12: =O11 -> 1869 | P12: 2101 | Q12: 176637 | R12: =Q12-Q11 -> 102 | S12: =SUM(P12-P11) -> 1 | T12: =SUM(S12*$T$2) -> 0 | U12: =SUM(G12+L12+S12) -> 2 | V12: =R12+N12+I12:I12 -> 158 | W12: =SUM(V12/U12) -> 79 | X12: =X11 -> 2470 | Y12: =X12-X11 -> 0 | Z12: =Z11 -> 139083 | AA12: =Z12-Z11 -> 0 | AB12: =SUM(Y12*$AB$2) -> 0 | AC12: =AC11 -> 1938 | AD12: =AC12-AC11 -> 0 | AE12: =AE11 -> 365701 | AF12: =AE12-AE11 -> 0 | AG12: =IF(AD12>0,AF12/AD12,0) -> 0 | AH12: =AF12+AA12 -> 0 | AI12: =SUM(AH12+V12) -> 158 | AJ12: =-tanks!AW13 -> 158 | AK12: =SUM(AJ12-AI12) -> 0 | AL12: =S12+L12+G12 -> 2 | AM12: =Y12+AD12 -> 0 | AN12: =AN11 -> 67 | AO12: =(AN12/100)*3000 -> 2010 | AP12: =AP11 -> 55 | AQ12: =(AP12/100)*3000 -> 1650 | AR12: =AR11 -> 61 | AS12: =(AR12/100)*3000 -> 1830 | AT12: =SUM(AO12+AQ12+AS12) -> 5490 | AU12: =AT11-AT12+AV12 -> 0 | AX12: =IF(AV12>0,AW12,AX11) -> 0.8
A13: =ELEC!C12 -> 44356 | B13: 200 | C13: 208 | D13: =C12-C13 -> 15 | E13: =D13*8.38 -> 125.7 | F13: =F12 -> 1845 | G13: =F13-F12 -> 0 | H13: =H12 -> 13720 | I13: =SUM(H13-H12) -> 0 | J13: =IF(G13>0,I13/G13,0) -> 0 | K13: 2334 | L13: =K13-K12 -> 1 | M13: 172161 | N13: =M13-M12 -> 110 | O13: =O12 -> 1869 | P13: =P12 -> 2101 | Q13: =Q12 -> 176637 | R13: =Q13-Q12 -> 0 | S13: =SUM(P13-P12) -> 0 | T13: =SUM(S13*$T$2) -> 0 | U13: =SUM(G13+L13+S13) -> 1 | V13: =R13+N13+I13:I13 -> 110 | W13: =SUM(V13/U13) -> 110 | X13: =X12 -> 2470 | Y13: =X13-X12 -> 0 | Z13: =Z12 -> 139083 | AA13: =Z13-Z12 -> 0 | AB13: =SUM(Y13*$AB$2) -> 0 | AC13: =AC12 -> 1938 | AD13: =AC13-AC12 -> 0 | AE13: =AE12 -> 365701 | AF13: =AE13-AE12 -> 0 | AG13: =IF(AD13>0,AF13/AD13,0) -> 0 | AH13: =AF13+AA13 -> 0 | AI13: =SUM(AH13+V13) -> 110 | AJ13: =-tanks!AW14 -> 110 | AK13: =SUM(AJ13-AI13) -> 0 | AL13: =S13+L13+G13 -> 1 | AM13: =Y13+AD13 -> 0 | AN13: =AN12 -> 67 | AO13: =(AN13/100)*3000 -> 2010 | AP13: =AP12 -> 55 | AQ13: =(AP13/100)*3000 -> 1650 | AR13: =AR12 -> 61 | AS13: =(AR13/100)*3000 -> 1830 | AT13: =SUM(AO13+AQ13+AS13) -> 5490 | AU13: =AT12-AT13+AV13 -> 0 | AX13: =IF(AV13>0,AW13,AX12) -> 0.8
A14: =ELEC!C13 -> 44357 | B14: 246 | C14: 251 | D14: =C13-C14 -> -43 | E14: =D14*8.38 -> -360.34 | F14: =F13 -> 1845 | G14: =F14-F13 -> 0 | H14: =H13 -> 13720 | I14: =SUM(H14-H13) -> 0 | J14: =IF(G14>0,I14/G14,0) -> 0 | K14: 2335 | L14: =K14-K13 -> 1 | M14: 172230 | N14: =M14-M13 -> 69 | O14: =O13 -> 1869 | P14: 2102 | Q14: 176683 | R14: =Q14-Q13 -> 46 | S14: =SUM(P14-P13) -> 1 | T14: =SUM(S14*$T$2) -> 0 | U14: =SUM(G14+L14+S14) -> 2 | V14: =R14+N14+I14:I14 -> 115 | W14: =SUM(V14/U14) -> 57.5 | X14: =X13 -> 2470 | Y14: =X14-X13 -> 0 | Z14: =Z13 -> 139083 | AA14: =Z14-Z13 -> 0 | AB14: =SUM(Y14*$AB$2) -> 0 | AC14: =AC13 -> 1938 | AD14: =AC14-AC13 -> 0 | AE14: =AE13 -> 365701 | AF14: =AE14-AE13 -> 0 | AG14: =IF(AD14>0,AF14/AD14,0) -> 0 | AH14: =AF14+AA14 -> 0 | AI14: =SUM(AH14+V14) -> 115 | AJ14: =-tanks!AW15 -> 115 | AK14: =SUM(AJ14-AI14) -> 0 | AL14: =S14+L14+G14 -> 2 | AM14: =Y14+AD14 -> 0 | AN14: =AN13 -> 67 | AO14: =(AN14/100)*3000 -> 2010 | AP14: =AP13 -> 55 | AQ14: =(AP14/100)*3000 -> 1650 | AR14: =AR13 -> 61 | AS14: =(AR14/100)*3000 -> 1830 | AT14: =SUM(AO14+AQ14+AS14) -> 5490 | AU14: =AT13-AT14+AV14 -> 0 | AX14: =IF(AV14>0,AW14,AX13) -> 0.8
A15: =ELEC!C14 -> 44358 | B15: 229 | C15: 236 | D15: =C14-C15 -> 15 | E15: =D15*8.38 -> 125.7 | F15: 1846 | G15: =F15-F14 -> 1 | H15: 13830 | I15: =SUM(H15-H14) -> 110 | J15: =IF(G15>0,I15/G15,0) -> 110 | K15: =K14 -> 2335 | L15: =K15-K14 -> 0 | M15: =M14 -> 172230 | N15: =M15-M14 -> 0 | O15: =O14 -> 1869 | P15: =P14 -> 2102 | Q15: 176708 | R15: =Q15-Q14 -> 25 | S15: =SUM(P15-P14) -> 0 | T15: =SUM(S15*$T$2) -> 0 | U15: =SUM(G15+L15+S15) -> 1 | V15: =R15+N15+I15:I15 -> 135 | W15: =SUM(V15/U15) -> 135 | X15: =X14 -> 2470 | Y15: =X15-X14 -> 0 | Z15: =Z14 -> 139083 | AA15: =Z15-Z14 -> 0 | AB15: =SUM(Y15*$AB$2) -> 0 | AC15: =AC14 -> 1938 | AD15: =AC15-AC14 -> 0 | AE15: =AE14 -> 365701 | AF15: =AE15-AE14 -> 0 | AG15: =IF(AD15>0,AF15/AD15,0) -> 0 | AH15: =AF15+AA15 -> 0 | AI15: =SUM(AH15+V15) -> 135 | AJ15: =-tanks!AW16 -> 135 | AK15: =SUM(AJ15-AI15) -> 0 | AL15: =S15+L15+G15 -> 1 | AM15: =Y15+AD15 -> 0 | AN15: =AN14 -> 67 | AO15: =(AN15/100)*3000 -> 2010 | AP15: =AP14 -> 55 | AQ15: =(AP15/100)*3000 -> 1650 | AR15: =AR14 -> 61 | AS15: =(AR15/100)*3000 -> 1830 | AT15: =SUM(AO15+AQ15+AS15) -> 5490 | AU15: =AT14-AT15+AV15 -> 0 | AX15: =IF(AV15>0,AW15,AX14) -> 0.8
A16: =ELEC!C15 -> 44359 | B16: 219 | C16: 225 | D16: =C15-C16 -> 11 | E16: =D16*8.38 -> 92.18 | F16: 1847 | G16: =F16-F15 -> 1 | H16: 13919 | I16: =SUM(H16-H15) -> 89 | J16: =IF(G16>0,I16/G16,0) -> 89 | K16: 2336 | L16: =K16-K15 -> 1 | M16: 172287 | N16: =M16-M15 -> 57 | O16: =O15 -> 1869 | P16: =P15 -> 2102 | Q16: =Q15 -> 176708 | R16: =Q16-Q15 -> 0 | S16: =SUM(P16-P15) -> 0 | T16: =SUM(S16*$T$2) -> 0 | U16: =SUM(G16+L16+S16) -> 2 | V16: =R16+N16+I16:I16 -> 146 | W16: =SUM(V16/U16) -> 73 | X16: =X15 -> 2470 | Y16: =X16-X15 -> 0 | Z16: =Z15 -> 139083 | AA16: =Z16-Z15 -> 0 | AB16: =SUM(Y16*$AB$2) -> 0 | AC16: =AC15 -> 1938 | AD16: =AC16-AC15 -> 0 | AE16: 365755 | AF16: =AE16-AE15 -> 54 | AG16: =IF(AD16>0,AF16/AD16,0) -> 0 | AH16: =AF16+AA16 -> 54 | AI16: =SUM(AH16+V16) -> 200 | AJ16: =-tanks!AW17 -> 200 | AK16: =SUM(AJ16-AI16) -> 0 | AL16: =S16+L16+G16 -> 2 | AM16: =Y16+AD16 -> 0 | AN16: =AN15 -> 67 | AO16: =(AN16/100)*3000 -> 2010 | AP16: =AP15 -> 55 | AQ16: =(AP16/100)*3000 -> 1650 | AR16: =AR15 -> 61 | AS16: =(AR16/100)*3000 -> 1830 | AT16: =SUM(AO16+AQ16+AS16) -> 5490 | AU16: =AT15-AT16+AV16 -> 0 | AX16: =IF(AV16>0,AW16,AX15) -> 0.8
A17: =ELEC!C16 -> 44360 | B17: 204 | C17: 211 | D17: =C16-C17 -> 14 | E17: =D17*8.38 -> 117.32 | F17: =F16 -> 1847 | G17: =F17-F16 -> 0 | H17: =H16 -> 13919 | I17: =SUM(H17-H16) -> 0 | J17: =IF(G17>0,I17/G17,0) -> 0 | K17: =K16 -> 2336 | L17: =K17-K16 -> 0 | M17: =M16 -> 172287 | N17: =M17-M16 -> 0 | O17: =O16 -> 1869 | P17: 2103 | Q17: 176756 | R17: =Q17-Q16 -> 48 | S17: =SUM(P17-P16) -> 1 | T17: =SUM(S17*$T$2) -> 0 | U17: =SUM(G17+L17+S17) -> 1 | V17: =R17+N17+I17:I17 -> 48 | X17: =X16 -> 2470 | Y17: =X17-X16 -> 0 | Z17: =Z16 -> 139083 | AA17: =Z17-Z16 -> 0 | AB17: =SUM(Y17*$AB$2) -> 0 | AC17: =AC16 -> 1938 | AD17: =AC17-AC16 -> 0 | AE17: =AE16 -> 365755 | AF17: =AE17-AE16 -> 0 | AG17: =IF(AD17>0,AF17/AD17,0) -> 0 | AH17: =AF17+AA17 -> 0 | AI17: =SUM(AH17+V17) -> 48 | AJ17: =-tanks!AW18 -> 48 | AK17: =SUM(AJ17-AI17) -> 0 | AL17: =S17+L17+G17 -> 1 | AM17: =Y17+AD17 -> 0 | AN17: =AN16 -> 67 | AO17: =(AN17/100)*3000 -> 2010 | AP17: =AP16 -> 55 | AQ17: =(AP17/100)*3000 -> 1650 | AR17: =AR16 -> 61 | AS17: =(AR17/100)*3000 -> 1830 | AT17: =SUM(AO17+AQ17+AS17) -> 5490 | AU17: =AT16-AT17+AV17 -> 0 | AX17: =IF(AV17>0,AW17,AX16) -> 0.8
A18: =ELEC!C17 -> 44361 | B18: 193 | C18: 199 | D18: =C17-C18 -> 12 | E18: =D18*8.38 -> 100.56 | F18: 1848 | G18: =F18-F17 -> 1 | H18: 13976 | I18: =SUM(H18-H17) -> 57 | J18: =IF(G18>0,I18/G18,0) -> 57 | K18: =K17 -> 2336 | L18: =K18-K17 -> 0 | M18: =M17 -> 172287 | N18: =M18-M17 -> 0 | O18: 1869 | P18: =P17 -> 2103 | Q18: =Q17 -> 176756 | R18: =Q18-Q17 -> 0 | S18: =SUM(P18-P17) -> 0 | T18: =SUM(S18*$T$2) -> 0 | U18: =SUM(G18+L18+S18) -> 1 | V18: =R18+N18+I18:I18 -> 57 | X18: =X17 -> 2470 | Y18: =X18-X17 -> 0 | Z18: =Z17 -> 139083 | AA18: =Z18-Z17 -> 0 | AB18: =SUM(Y18*$AB$2) -> 0 | AC18: =AC17 -> 1938 | AD18: =AC18-AC17 -> 0 | AE18: =AE17 -> 365755 | AF18: =AE18-AE17 -> 0 | AG18: =IF(AD18>0,AF18/AD18,0) -> 0 | AH18: =AF18+AA18 -> 0 | AI18: =SUM(AH18+V18) -> 57 | AJ18: =-tanks!AW19 -> 57 | AK18: =SUM(AJ18-AI18) -> 0 | AL18: =S18+L18+G18 -> 1 | AM18: =Y18+AD18 -> 0 | AN18: =AN17 -> 67 | AO18: =(AN18/100)*3000 -> 2010 | AP18: =AP17 -> 55 | AQ18: =(AP18/100)*3000 -> 1650 | AR18: =AR17 -> 61 | AS18: =(AR18/100)*3000 -> 1830 | AT18: =SUM(AO18+AQ18+AS18) -> 5490 | AU18: =AT17-AT18+AV18 -> 0 | AX18: =IF(AV18>0,AW18,AX17) -> 0.8
A19: =ELEC!C18 -> 44362 | B19: 225 | C19: 231 | D19: =C18-C19 -> -32 | E19: =D19*8.38 -> -268.16 | F19: 1850 | G19: =F19-F18 -> 2 | H19: 14077 | I19: =SUM(H19-H18) -> 101 | J19: =IF(G19>0,I19/G19,0) -> 50.5 | K19: 2337 | L19: =K19-K18 -> 1 | M19: 172370 | N19: =M19-M18 -> 83 | O19: =O18 -> 1869 | P19: =P18 -> 2103 | Q19: =Q18 -> 176756 | R19: =Q19-Q18 -> 0 | S19: =SUM(P19-P18) -> 0 | T19: =SUM(S19*$T$2) -> 0 | U19: =SUM(G19+L19+S19) -> 3 | V19: =R19+N19+I19:I19 -> 184 | X19: =X18 -> 2470 | Y19: =X19-X18 -> 0 | Z19: =Z18 -> 139083 | AA19: =Z19-Z18 -> 0 | AB19: =SUM(Y19*$AB$2) -> 0 | AC19: =AC18 -> 1938 | AD19: =AC19-AC18 -> 0 | AE19: =AE18 -> 365755 | AF19: =AE19-AE18 -> 0 | AG19: =IF(AD19>0,AF19/AD19,0) -> 0 | AH19: =AF19+AA19 -> 0 | AI19: =SUM(AH19+V19) -> 184 | AJ19: =-tanks!AW20 -> 184 | AK19: =SUM(AJ19-AI19) -> 0 | AL19: =S19+L19+G19 -> 3 | AM19: =Y19+AD19 -> 0 | AN19: =AN18 -> 67 | AO19: =(AN19/100)*3000 -> 2010 | AP19: =AP18 -> 55 | AQ19: =(AP19/100)*3000 -> 1650 | AR19: =AR18 -> 61 | AS19: =(AR19/100)*3000 -> 1830 | AT19: =SUM(AO19+AQ19+AS19) -> 5490 | AU19: =AT18-AT19+AV19 -> 0 | AX19: =IF(AV19>0,AW19,AX18) -> 0.8
A20: =ELEC!C19 -> 44363 | B20: 213 | C20: 219 | D20: =C19-C20 -> 12 | E20: =D20*8.38 -> 100.56 | F20: =F19 -> 1850 | G20: =F20-F19 -> 0 | H20: =H19 -> 14077 | I20: =SUM(H20-H19) -> 0 | J20: =IF(G20>0,I20/G20,0) -> 0 | K20: =K19 -> 2337 | L20: =K20-K19 -> 0 | M20: =M19 -> 172370 | N20: =M20-M19 -> 0 | O20: =O19 -> 1869 | P20: 2104 | Q20: 176838 | R20: =Q20-Q19 -> 82 | S20: =SUM(P20-P19) -> 1 | T20: =SUM(S20*$T$2) -> 0 | U20: =SUM(G20+L20+S20) -> 1 | V20: =R20+N20+I20:I20 -> 82 | X20: =X19 -> 2470 | Y20: =X20-X19 -> 0 | Z20: =Z19 -> 139083 | AA20: =Z20-Z19 -> 0 | AB20: =SUM(Y20*$AB$2) -> 0 | AC20: =AC19 -> 1938 | AD20: =AC20-AC19 -> 0 | AE20: =AE19 -> 365755 | AF20: =AE20-AE19 -> 0 | AG20: =IF(AD20>0,AF20/AD20,0) -> 0 | AH20: =AF20+AA20 -> 0 | AI20: =SUM(AH20+V20) -> 82 | AJ20: =-tanks!AW21 -> 82 | AK20: =SUM(AJ20-AI20) -> 0 | AL20: =S20+L20+G20 -> 1 | AM20: =Y20+AD20 -> 0 | AN20: =AN19 -> 67 | AO20: =(AN20/100)*3000 -> 2010 | AP20: =AP19 -> 55 | AQ20: =(AP20/100)*3000 -> 1650 | AR20: =AR19 -> 61 | AS20: =(AR20/100)*3000 -> 1830 | AT20: =SUM(AO20+AQ20+AS20) -> 5490 | AU20: =AT19-AT20+AV20 -> 0 | AX20: =IF(AV20>0,AW20,AX19) -> 0.8
A21: =ELEC!C20 -> 44364 | B21: 199 | C21: 206 | D21: =C20-C21 -> 13 | E21: =D21*8.38 -> 108.94 | F21: =F20 -> 1850 | G21: =F21-F20 -> 0 | H21: 14125 | I21: =SUM(H21-H20) -> 48 | J21: =IF(G21>0,I21/G21,0) -> 0 | K21: =K20 -> 2337 | L21: =K21-K20 -> 0 | M21: =M20 -> 172370 | N21: =M21-M20 -> 0 | O21: =O20 -> 1869 | P21: 2105 | Q21: 176929 | R21: =Q21-Q20 -> 91 | S21: =SUM(P21-P20) -> 1 | T21: =SUM(S21*$T$2) -> 0 | U21: =SUM(G21+L21+S21) -> 1 | V21: =R21+N21+I21:I21 -> 139 | X21: =X20 -> 2470 | Y21: =X21-X20 -> 0 | Z21: =Z20 -> 139083 | AA21: =Z21-Z20 -> 0 | AB21: =SUM(Y21*$AB$2) -> 0 | AC21: =AC20 -> 1938 | AD21: =AC21-AC20 -> 0 | AE21: =AE20 -> 365755 | AF21: =AE21-AE20 -> 0 | AG21: =IF(AD21>0,AF21/AD21,0) -> 0 | AH21: =AF21+AA21 -> 0 | AI21: =SUM(AH21+V21) -> 139 | AJ21: =-tanks!AW22 -> 139 | AK21: =SUM(AJ21-AI21) -> 0 | AL21: =S21+L21+G21 -> 1 | AM21: =Y21+AD21 -> 0 | AN21: =AN20 -> 67 | AO21: =(AN21/100)*3000 -> 2010 | AP21: =AP20 -> 55 | AQ21: =(AP21/100)*3000 -> 1650 | AR21: =AR20 -> 61 | AS21: =(AR21/100)*3000 -> 1830 | AT21: =SUM(AO21+AQ21+AS21) -> 5490 | AU21: =AT20-AT21+AV21 -> 0 | AX21: =IF(AV21>0,AW21,AX20) -> 0.8
A22: =ELEC!C21 -> 44365 | B22: =B21 -> 199 | C22: =C21 -> 206 | D22: =C21-C22 -> 0 | E22: =D22*8.38 -> 0 | F22: =F21 -> 1850 | G22: =F22-F21 -> 0 | H22: =H21 -> 14125 | I22: =SUM(H22-H21) -> 0 | J22: =IF(G22>0,I22/G22,0) -> 0 | K22: =K21 -> 2337 | L22: =K22-K21 -> 0 | M22: =M21 -> 172370 | N22: =M22-M21 -> 0 | O22: =O21 -> 1869 | P22: =P21 -> 2105 | Q22: =Q21 -> 176929 | R22: =Q22-Q21 -> 0 | S22: =SUM(P22-P21) -> 0 | T22: =SUM(S22*$T$2) -> 0 | U22: =SUM(G22+L22+S22) -> 0 | V22: =R22+N22+I22:I22 -> 0 | X22: =X21 -> 2470 | Y22: =X22-X21 -> 0 | Z22: =Z21 -> 139083 | AA22: =Z22-Z21 -> 0 | AB22: =SUM(Y22*$AB$2) -> 0 | AC22: =AC21 -> 1938 | AD22: =AC22-AC21 -> 0 | AE22: =AE21 -> 365755 | AF22: =AE22-AE21 -> 0 | AG22: =IF(AD22>0,AF22/AD22,0) -> 0 | AH22: =AF22+AA22 -> 0 | AI22: =SUM(AH22+V22) -> 0 | AJ22: =-tanks!AW23 -> 0 | AK22: =SUM(AJ22-AI22) -> 0 | AL22: =S22+L22+G22 -> 0 | AM22: =Y22+AD22 -> 0 | AN22: =AN21 -> 67 | AO22: =(AN22/100)*3000 -> 2010 | AP22: =AP21 -> 55 | AQ22: =(AP22/100)*3000 -> 1650 | AR22: =AR21 -> 61 | AS22: =(AR22/100)*3000 -> 1830 | AT22: =SUM(AO22+AQ22+AS22) -> 5490 | AU22: =AT21-AT22+AV22 -> 0 | AX22: =IF(AV22>0,AW22,AX21) -> 0.8
A23: =ELEC!C22 -> 44366 | B23: =B22 -> 199 | C23: =C22 -> 206 | D23: =C22-C23 -> 0 | E23: =D23*8.38 -> 0 | F23: =F22 -> 1850 | G23: =F23-F22 -> 0 | H23: =H22 -> 14125 | I23: =SUM(H23-H22) -> 0 | J23: =IF(G23>0,I23/G23,0) -> 0 | K23: =K22 -> 2337 | L23: =K23-K22 -> 0 | M23: =M22 -> 172370 | N23: =M23-M22 -> 0 | O23: =O22 -> 1869 | P23: =P22 -> 2105 | Q23: =Q22 -> 176929 | R23: =Q23-Q22 -> 0 | S23: =SUM(P23-P22) -> 0 | T23: =SUM(S23*$T$2) -> 0 | U23: =SUM(G23+L23+S23) -> 0 | V23: =R23+N23+I23:I23 -> 0 | X23: =X22 -> 2470 | Y23: =X23-X22 -> 0 | Z23: =Z22 -> 139083 | AA23: =Z23-Z22 -> 0 | AB23: =SUM(Y23*$AB$2) -> 0 | AC23: =AC22 -> 1938 | AD23: =AC23-AC22 -> 0 | AE23: =AE22 -> 365755 | AF23: =AE23-AE22 -> 0 | AG23: =IF(AD23>0,AF23/AD23,0) -> 0 | AH23: =AF23+AA23 -> 0 | AI23: =SUM(AH23+V23) -> 0 | AJ23: =-tanks!AW24 -> 0 | AK23: =SUM(AJ23-AI23) -> 0 | AL23: =S23+L23+G23 -> 0 | AM23: =Y23+AD23 -> 0 | AN23: =AN22 -> 67 | AO23: =(AN23/100)*3000 -> 2010 | AP23: =AP22 -> 55 | AQ23: =(AP23/100)*3000 -> 1650 | AR23: =AR22 -> 61 | AS23: =(AR23/100)*3000 -> 1830 | AT23: =SUM(AO23+AQ23+AS23) -> 5490 | AU23: =AT22-AT23+AV23 -> 0 | AX23: =IF(AV23>0,AW23,AX22) -> 0.8
A24: =ELEC!C23 -> 44367 | B24: =B23 -> 199 | C24: =C23 -> 206 | D24: =C23-C24 -> 0 | E24: =D24*8.38 -> 0 | F24: =F23 -> 1850 | G24: =F24-F23 -> 0 | H24: =H23 -> 14125 | I24: =SUM(H24-H23) -> 0 | J24: =IF(G24>0,I24/G24,0) -> 0 | K24: =K23 -> 2337 | L24: =K24-K23 -> 0 | M24: =M23 -> 172370 | N24: =M24-M23 -> 0 | O24: =O23 -> 1869 | P24: =P23 -> 2105 | Q24: =Q23 -> 176929 | R24: =Q24-Q23 -> 0 | S24: =SUM(P24-P23) -> 0 | T24: =SUM(S24*$T$2) -> 0 | U24: =SUM(G24+L24+S24) -> 0 | V24: =R24+N24+I24:I24 -> 0 | X24: =X23 -> 2470 | Y24: =X24-X23 -> 0 | Z24: =Z23 -> 139083 | AA24: =Z24-Z23 -> 0 | AB24: =SUM(Y24*$AB$2) -> 0 | AC24: =AC23 -> 1938 | AD24: =AC24-AC23 -> 0 | AE24: =AE23 -> 365755 | AF24: =AE24-AE23 -> 0 | AG24: =IF(AD24>0,AF24/AD24,0) -> 0 | AH24: =AF24+AA24 -> 0 | AI24: =SUM(AH24+V24) -> 0 | AJ24: =-tanks!AW25 -> 0 | AK24: =SUM(AJ24-AI24) -> 0 | AL24: =S24+L24+G24 -> 0 | AM24: =Y24+AD24 -> 0 | AN24: =AN23 -> 67 | AO24: =(AN24/100)*3000 -> 2010 | AP24: =AP23 -> 55 | AQ24: =(AP24/100)*3000 -> 1650 | AR24: =AR23 -> 61 | AS24: =(AR24/100)*3000 -> 1830 | AT24: =SUM(AO24+AQ24+AS24) -> 5490 | AU24: =AT23-AT24+AV24 -> 0 | AX24: =IF(AV24>0,AW24,AX23) -> 0.8
A25: =ELEC!C24 -> 44368 | B25: =B24 -> 199 | C25: =C24 -> 206 | D25: =C24-C25 -> 0 | E25: =D25*8.38 -> 0 | F25: =F24 -> 1850 | G25: =F25-F24 -> 0 | H25: =H24 -> 14125 | I25: =SUM(H25-H24) -> 0 | J25: =IF(G25>0,I25/G25,0) -> 0 | K25: =K24 -> 2337 | L25: =K25-K24 -> 0 | M25: =M24 -> 172370 | N25: =M25-M24 -> 0 | O25: =O24 -> 1869 | P25: =P24 -> 2105 | Q25: =Q24 -> 176929 | R25: =Q25-Q24 -> 0 | S25: =SUM(P25-P24) -> 0 | T25: =SUM(S25*$T$2) -> 0 | U25: =SUM(G25+L25+S25) -> 0 | V25: =R25+N25+I25:I25 -> 0 | X25: =X24 -> 2470 | Y25: =X25-X24 -> 0 | Z25: =Z24 -> 139083 | AA25: =Z25-Z24 -> 0 | AB25: =SUM(Y25*$AB$2) -> 0 | AC25: =AC24 -> 1938 | AD25: =AC25-AC24 -> 0 | AE25: =AE24 -> 365755 | AF25: =AE25-AE24 -> 0 | AG25: =IF(AD25>0,AF25/AD25,0) -> 0 | AH25: =AF25+AA25 -> 0 | AI25: =SUM(AH25+V25) -> 0 | AJ25: =-tanks!AW26 -> 0 | AK25: =SUM(AJ25-AI25) -> 0 | AL25: =S25+L25+G25 -> 0 | AM25: =Y25+AD25 -> 0 | AN25: =AN24 -> 67 | AO25: =(AN25/100)*3000 -> 2010 | AP25: =AP24 -> 55 | AQ25: =(AP25/100)*3000 -> 1650 | AR25: =AR24 -> 61 | AS25: =(AR25/100)*3000 -> 1830 | AT25: =SUM(AO25+AQ25+AS25) -> 5490 | AU25: =AT24-AT25+AV25 -> 0 | AX25: =IF(AV25>0,AW25,AX24) -> 0.8
A26: =ELEC!C25 -> 44369 | B26: =B25 -> 199 | C26: =C25 -> 206 | D26: =C25-C26 -> 0 | E26: =D26*8.38 -> 0 | F26: =F25 -> 1850 | G26: =F26-F25 -> 0 | H26: =H25 -> 14125 | I26: =SUM(H26-H25) -> 0 | J26: =IF(G26>0,I26/G26,0) -> 0 | K26: =K25 -> 2337 | L26: =K26-K25 -> 0 | M26: =M25 -> 172370 | N26: =M26-M25 -> 0 | O26: =O25 -> 1869 | P26: =P25 -> 2105 | Q26: =Q25 -> 176929 | R26: =Q26-Q25 -> 0 | S26: =SUM(P26-P25) -> 0 | T26: =SUM(S26*$T$2) -> 0 | U26: =SUM(G26+L26+S26) -> 0 | V26: =R26+N26+I26:I26 -> 0 | X26: =X25 -> 2470 | Y26: =X26-X25 -> 0 | Z26: =Z25 -> 139083 | AA26: =Z26-Z25 -> 0 | AB26: =SUM(Y26*$AB$2) -> 0 | AC26: =AC25 -> 1938 | AD26: =AC26-AC25 -> 0 | AE26: =AE25 -> 365755 | AF26: =AE26-AE25 -> 0 | AG26: =IF(AD26>0,AF26/AD26,0) -> 0 | AH26: =AF26+AA26 -> 0 | AI26: =SUM(AH26+V26) -> 0 | AJ26: =-tanks!AW27 -> 0 | AK26: =SUM(AJ26-AI26) -> 0 | AL26: =S26+L26+G26 -> 0 | AM26: =Y26+AD26 -> 0 | AN26: =AN25 -> 67 | AO26: =(AN26/100)*3000 -> 2010 | AP26: =AP25 -> 55 | AQ26: =(AP26/100)*3000 -> 1650 | AR26: =AR25 -> 61 | AS26: =(AR26/100)*3000 -> 1830 | AT26: =SUM(AO26+AQ26+AS26) -> 5490 | AU26: =AT25-AT26+AV26 -> 0 | AX26: =IF(AV26>0,AW26,AX25) -> 0.8
A27: =ELEC!C26 -> 44370 | B27: =B26 -> 199 | C27: =C26 -> 206 | D27: =C26-C27 -> 0 | E27: =D27*8.38 -> 0 | F27: =F26 -> 1850 | G27: =F27-F26 -> 0 | H27: =H26 -> 14125 | I27: =SUM(H27-H26) -> 0 | J27: =IF(G27>0,I27/G27,0) -> 0 | K27: =K26 -> 2337 | L27: =K27-K26 -> 0 | M27: =M26 -> 172370 | N27: =M27-M26 -> 0 | O27: =O26 -> 1869 | P27: =P26 -> 2105 | Q27: =Q26 -> 176929 | R27: =Q27-Q26 -> 0 | S27: =SUM(P27-P26) -> 0 | T27: =SUM(S27*$T$2) -> 0 | U27: =SUM(G27+L27+S27) -> 0 | V27: =R27+N27+I27:I27 -> 0 | X27: =X26 -> 2470 | Y27: =X27-X26 -> 0 | Z27: =Z26 -> 139083 | AA27: =Z27-Z26 -> 0 | AB27: =SUM(Y27*$AB$2) -> 0 | AC27: =AC26 -> 1938 | AD27: =AC27-AC26 -> 0 | AE27: =AE26 -> 365755 | AF27: =AE27-AE26 -> 0 | AG27: =IF(AD27>0,AF27/AD27,0) -> 0 | AH27: =AF27+AA27 -> 0 | AI27: =SUM(AH27+V27) -> 0 | AJ27: =-tanks!AW28 -> 0 | AK27: =SUM(AJ27-AI27) -> 0 | AL27: =S27+L27+G27 -> 0 | AM27: =Y27+AD27 -> 0 | AN27: =AN26 -> 67 | AO27: =(AN27/100)*3000 -> 2010 | AP27: =AP26 -> 55 | AQ27: =(AP27/100)*3000 -> 1650 | AR27: =AR26 -> 61 | AS27: =(AR27/100)*3000 -> 1830 | AT27: =SUM(AO27+AQ27+AS27) -> 5490 | AU27: =AT26-AT27+AV27 -> 0 | AX27: =IF(AV27>0,AW27,AX26) -> 0.8
A28: =ELEC!C27 -> 44371 | B28: =B27 -> 199 | C28: =C27 -> 206 | D28: =C27-C28 -> 0 | E28: =D28*8.38 -> 0 | F28: =F27 -> 1850 | G28: =F28-F27 -> 0 | H28: =H27 -> 14125 | I28: =SUM(H28-H27) -> 0 | J28: =IF(G28>0,I28/G28,0) -> 0 | K28: =K27 -> 2337 | L28: =K28-K27 -> 0 | M28: =M27 -> 172370 | N28: =M28-M27 -> 0 | O28: =O27 -> 1869 | P28: =P27 -> 2105 | Q28: =Q27 -> 176929 | R28: =Q28-Q27 -> 0 | S28: =SUM(P28-P27) -> 0 | T28: =SUM(S28*$T$2) -> 0 | U28: =SUM(G28+L28+S28) -> 0 | V28: =R28+N28+I28:I28 -> 0 | X28: =X27 -> 2470 | Y28: =X28-X27 -> 0 | Z28: =Z27 -> 139083 | AA28: =Z28-Z27 -> 0 | AB28: =SUM(Y28*$AB$2) -> 0 | AC28: =AC27 -> 1938 | AD28: =AC28-AC27 -> 0 | AE28: =AE27 -> 365755 | AF28: =AE28-AE27 -> 0 | AG28: =IF(AD28>0,AF28/AD28,0) -> 0 | AH28: =AF28+AA28 -> 0 | AI28: =SUM(AH28+V28) -> 0 | AJ28: =-tanks!AW29 -> 0 | AK28: =SUM(AJ28-AI28) -> 0 | AL28: =S28+L28+G28 -> 0 | AM28: =Y28+AD28 -> 0 | AN28: =AN27 -> 67 | AO28: =(AN28/100)*3000 -> 2010 | AP28: =AP27 -> 55 | AQ28: =(AP28/100)*3000 -> 1650 | AR28: =AR27 -> 61 | AS28: =(AR28/100)*3000 -> 1830 | AT28: =SUM(AO28+AQ28+AS28) -> 5490 | AU28: =AT27-AT28+AV28 -> 0 | AX28: =IF(AV28>0,AW28,AX27) -> 0.8
A29: =ELEC!C28 -> 44372 | B29: =B28 -> 199 | C29: =C28 -> 206 | D29: =C28-C29 -> 0 | E29: =D29*8.38 -> 0 | F29: =F28 -> 1850 | G29: =F29-F28 -> 0 | H29: =H28 -> 14125 | I29: =SUM(H29-H28) -> 0 | J29: =IF(G29>0,I29/G29,0) -> 0 | K29: =K28 -> 2337 | L29: =K29-K28 -> 0 | M29: =M28 -> 172370 | N29: =M29-M28 -> 0 | O29: =O28 -> 1869 | P29: =P28 -> 2105 | Q29: =Q28 -> 176929 | R29: =Q29-Q28 -> 0 | S29: =SUM(P29-P28) -> 0 | T29: =SUM(S29*$T$2) -> 0 | U29: =SUM(G29+L29+S29) -> 0 | V29: =R29+N29+I29:I29 -> 0 | X29: =X28 -> 2470 | Y29: =X29-X28 -> 0 | Z29: =Z28 -> 139083 | AA29: =Z29-Z28 -> 0 | AB29: =SUM(Y29*$AB$2) -> 0 | AC29: =AC28 -> 1938 | AD29: =AC29-AC28 -> 0 | AE29: =AE28 -> 365755 | AF29: =AE29-AE28 -> 0 | AG29: =IF(AD29>0,AF29/AD29,0) -> 0 | AH29: =AF29+AA29 -> 0 | AI29: =SUM(AH29+V29) -> 0 | AJ29: =-tanks!AW30 -> 0 | AK29: =SUM(AJ29-AI29) -> 0 | AL29: =S29+L29+G29 -> 0 | AM29: =Y29+AD29 -> 0 | AN29: =AN28 -> 67 | AO29: =(AN29/100)*3000 -> 2010 | AP29: =AP28 -> 55 | AQ29: =(AP29/100)*3000 -> 1650 | AR29: =AR28 -> 61 | AS29: =(AR29/100)*3000 -> 1830 | AT29: =SUM(AO29+AQ29+AS29) -> 5490 | AU29: =AT28-AT29+AV29 -> 0 | AX29: =IF(AV29>0,AW29,AX28) -> 0.8
A30: =ELEC!C29 -> 44373 | B30: =B29 -> 199 | C30: =C29 -> 206 | D30: =C29-C30 -> 0 | E30: =D30*8.38 -> 0 | F30: =F29 -> 1850 | G30: =F30-F29 -> 0 | H30: =H29 -> 14125 | I30: =SUM(H30-H29) -> 0 | J30: =IF(G30>0,I30/G30,0) -> 0 | K30: =K29 -> 2337 | L30: =K30-K29 -> 0 | M30: =M29 -> 172370 | N30: =M30-M29 -> 0 | O30: =O29 -> 1869 | P30: =P29 -> 2105 | Q30: =Q29 -> 176929 | R30: =Q30-Q29 -> 0 | S30: =SUM(P30-P29) -> 0 | T30: =SUM(S30*$T$2) -> 0 | U30: =SUM(G30+L30+S30) -> 0 | V30: =R30+N30+I30:I30 -> 0 | X30: =X29 -> 2470 | Y30: =X30-X29 -> 0 | Z30: =Z29 -> 139083 | AA30: =Z30-Z29 -> 0 | AB30: =SUM(Y30*$AB$2) -> 0 | AC30: =AC29 -> 1938 | AD30: =AC30-AC29 -> 0 | AE30: =AE29 -> 365755 | AF30: =AE30-AE29 -> 0 | AG30: =IF(AD30>0,AF30/AD30,0) -> 0 | AH30: =AF30+AA30 -> 0 | AI30: =SUM(AH30+V30) -> 0 | AJ30: =-tanks!AW31 -> 0 | AK30: =SUM(AJ30-AI30) -> 0 | AL30: =S30+L30+G30 -> 0 | AM30: =Y30+AD30 -> 0 | AN30: =AN29 -> 67 | AO30: =(AN30/100)*3000 -> 2010 | AP30: =AP29 -> 55 | AQ30: =(AP30/100)*3000 -> 1650 | AR30: =AR29 -> 61 | AS30: =(AR30/100)*3000 -> 1830 | AT30: =SUM(AO30+AQ30+AS30) -> 5490 | AU30: =AT29-AT30+AV30 -> 0 | AX30: =IF(AV30>0,AW30,AX29) -> 0.8
A31: =ELEC!C30 -> 44374 | B31: =B30 -> 199 | C31: =C30 -> 206 | D31: =C30-C31 -> 0 | E31: =D31*8.38 -> 0 | F31: =F30 -> 1850 | G31: =F31-F30 -> 0 | H31: =H30 -> 14125 | I31: =SUM(H31-H30) -> 0 | J31: =IF(G31>0,I31/G31,0) -> 0 | K31: =K30 -> 2337 | L31: =K31-K30 -> 0 | M31: =M30 -> 172370 | N31: =M31-M30 -> 0 | O31: =O30 -> 1869 | P31: =P30 -> 2105 | Q31: =Q30 -> 176929 | R31: =Q31-Q30 -> 0 | S31: =SUM(P31-P30) -> 0 | T31: =SUM(S31*$T$2) -> 0 | U31: =SUM(G31+L31+S31) -> 0 | V31: =R31+N31+I31:I31 -> 0 | X31: =X30 -> 2470 | Y31: =X31-X30 -> 0 | Z31: =Z30 -> 139083 | AA31: =Z31-Z30 -> 0 | AB31: =SUM(Y31*$AB$2) -> 0 | AC31: =AC30 -> 1938 | AD31: =AC31-AC30 -> 0 | AE31: =AE30 -> 365755 | AF31: =AE31-AE30 -> 0 | AG31: =IF(AD31>0,AF31/AD31,0) -> 0 | AH31: =AF31+AA31 -> 0 | AI31: =SUM(AH31+V31) -> 0 | AJ31: =-tanks!AW32 -> 0 | AK31: =SUM(AJ31-AI31) -> 0 | AL31: =S31+L31+G31 -> 0 | AM31: =Y31+AD31 -> 0 | AN31: =AN30 -> 67 | AO31: =(AN31/100)*3000 -> 2010 | AP31: =AP30 -> 55 | AQ31: =(AP31/100)*3000 -> 1650 | AR31: =AR30 -> 61 | AS31: =(AR31/100)*3000 -> 1830 | AT31: =SUM(AO31+AQ31+AS31) -> 5490 | AU31: =AT30-AT31+AV31 -> 0 | AX31: =IF(AV31>0,AW31,AX30) -> 0.8
A32: =ELEC!C31 -> 44375 | B32: =B31 -> 199 | C32: =C31 -> 206 | D32: =C31-C32 -> 0 | E32: =D32*8.38 -> 0 | F32: =F31 -> 1850 | G32: =F32-F31 -> 0 | H32: =H31 -> 14125 | I32: =SUM(H32-H31) -> 0 | J32: =IF(G32>0,I32/G32,0) -> 0 | K32: =K31 -> 2337 | L32: =K32-K31 -> 0 | M32: =M31 -> 172370 | N32: =M32-M31 -> 0 | O32: =O31 -> 1869 | P32: =P31 -> 2105 | Q32: =Q31 -> 176929 | R32: =Q32-Q31 -> 0 | S32: =SUM(P32-P31) -> 0 | T32: =SUM(S32*$T$2) -> 0 | U32: =SUM(G32+L32+S32) -> 0 | V32: =R32+N32+I32:I32 -> 0 | X32: =X31 -> 2470 | Y32: =X32-X31 -> 0 | Z32: =Z31 -> 139083 | AA32: =Z32-Z31 -> 0 | AB32: =SUM(Y32*$AB$2) -> 0 | AC32: =AC31 -> 1938 | AD32: =AC32-AC31 -> 0 | AE32: =AE31 -> 365755 | AF32: =AE32-AE31 -> 0 | AG32: =IF(AD32>0,AF32/AD32,0) -> 0 | AH32: =AF32+AA32 -> 0 | AI32: =SUM(AH32+V32) -> 0 | AJ32: =-tanks!AW33 -> 0 | AK32: =SUM(AJ32-AI32) -> 0 | AL32: =S32+L32+G32 -> 0 | AM32: =Y32+AD32 -> 0 | AN32: =AN31 -> 67 | AO32: =(AN32/100)*3000 -> 2010 | AP32: =AP31 -> 55 | AQ32: =(AP32/100)*3000 -> 1650 | AR32: =AR31 -> 61 | AS32: =(AR32/100)*3000 -> 1830 | AT32: =SUM(AO32+AQ32+AS32) -> 5490 | AU32: =AT31-AT32+AV32 -> 0 | AX32: =IF(AV32>0,AW32,AX31) -> 0.8
A33: =ELEC!C32 -> 44376 | B33: =B32 -> 199 | C33: =C32 -> 206 | D33: =C32-C33 -> 0 | E33: =D33*8.38 -> 0 | F33: =F32 -> 1850 | G33: =F33-F32 -> 0 | H33: =H32 -> 14125 | I33: =SUM(H33-H32) -> 0 | J33: =IF(G33>0,I33/G33,0) -> 0 | K33: =K32 -> 2337 | L33: =K33-K32 -> 0 | M33: =M32 -> 172370 | N33: =M33-M32 -> 0 | O33: =O32 -> 1869 | P33: =P32 -> 2105 | Q33: =Q32 -> 176929 | R33: =Q33-Q32 -> 0 | S33: =SUM(P33-P32) -> 0 | T33: =SUM(S33*$T$2) -> 0 | U33: =SUM(G33+L33+S33) -> 0 | V33: =R33+N33+I33:I33 -> 0 | X33: =X32 -> 2470 | Y33: =X33-X32 -> 0 | Z33: =Z32 -> 139083 | AA33: =Z33-Z32 -> 0 | AB33: =SUM(Y33*$AB$2) -> 0 | AC33: =AC32 -> 1938 | AD33: =AC33-AC32 -> 0 | AE33: =AE32 -> 365755 | AF33: =AE33-AE32 -> 0 | AG33: =IF(AD33>0,AF33/AD33,0) -> 0 | AH33: =AF33+AA33 -> 0 | AI33: =SUM(AH33+V33) -> 0 | AJ33: =-tanks!AW34 -> 0 | AK33: =SUM(AJ33-AI33) -> 0 | AL33: =S33+L33+G33 -> 0 | AM33: =Y33+AD33 -> 0 | AN33: =AN32 -> 67 | AO33: =(AN33/100)*3000 -> 2010 | AP33: =AP32 -> 55 | AQ33: =(AP33/100)*3000 -> 1650 | AR33: =AR32 -> 61 | AS33: =(AR33/100)*3000 -> 1830 | AT33: =SUM(AO33+AQ33+AS33) -> 5490 | AU33: =AT32-AT33+AV33 -> 0 | AX33: =IF(AV33>0,AW33,AX32) -> 0.8
A34: =ELEC!C33 -> 44377 | B34: =B33 -> 199 | C34: =C33 -> 206 | D34: =C33-C34 -> 0 | E34: =D34*8.38 -> 0 | F34: =F33 -> 1850 | G34: =F34-F33 -> 0 | H34: =H33 -> 14125 | I34: =SUM(H34-H33) -> 0 | J34: =IF(G34>0,I34/G34,0) -> 0 | K34: =K33 -> 2337 | L34: =K34-K33 -> 0 | M34: =M33 -> 172370 | N34: =M34-M33 -> 0 | O34: =O33 -> 1869 | P34: =P33 -> 2105 | Q34: =Q33 -> 176929 | R34: =Q34-Q33 -> 0 | S34: =SUM(P34-P33) -> 0 | T34: =SUM(S34*$T$2) -> 0 | U34: =SUM(G34+L34+S34) -> 0 | V34: =R34+N34+I34:I34 -> 0 | X34: =X33 -> 2470 | Y34: =X34-X33 -> 0 | Z34: =Z33 -> 139083 | AA34: =Z34-Z33 -> 0 | AB34: =SUM(Y34*$AB$2) -> 0 | AC34: =AC33 -> 1938 | AD34: =AC34-AC33 -> 0 | AE34: =AE33 -> 365755 | AF34: =AE34-AE33 -> 0 | AG34: =IF(AD34>0,AF34/AD34,0) -> 0 | AH34: =AF34+AA34 -> 0 | AI34: =SUM(AH34+V34) -> 0 | AJ34: =-tanks!AW35 -> 0 | AK34: =SUM(AJ34-AI34) -> 0 | AL34: =S34+L34+G34 -> 0 | AM34: =Y34+AD34 -> 0 | AN34: =AN33 -> 67 | AO34: =(AN34/100)*3000 -> 2010 | AP34: =AP33 -> 55 | AQ34: =(AP34/100)*3000 -> 1650 | AR34: =AR33 -> 61 | AS34: =(AR34/100)*3000 -> 1830 | AT34: =SUM(AO34+AQ34+AS34) -> 5490 | AU34: =AT33-AT34+AV34 -> 0 | AX34: =IF(AV34>0,AW34,AX33) -> 0.8
J35: =SUM(J5:J32)/(COUNT(J5:J32)-COUNTIF(J5:J32,0)) -> 63.722222 | V35: =SUM(V5:V34) -> 1912 | AE35: . | AH35: =SUM(AH5:AH34) -> 255 | AL35: =SUM(AL5:AL34) -> 24 | AM35: =SUM(AM5:AM34) -> 2 | AR35: Nb Delivery | AS35: =COUNT(AW5:AW32) -> 0 | AU35: =SUM(AU5:AU32) -> 0 | AV35: =SUM(AV5:AV32) -> 0 | AW35: =SUM(AW5:AW32)/AS35 -> #DIV/0!
AH36: =AF36+AA36 -> 0 | AI36: =SUM(AI5:AI34) -> 2167
AH37: =AF37+AA37 -> 0 | AU37: =AU35*0.51 -> 0 | AV37: =AV35/0.51 -> 0 | AW37: =SUM(AW5:AW32)/AS35 -> #DIV/0!
AV38: =AV35*0.51 -> 0

Sheet WATER
D1: =SUM(G21:G33) -> 8069750 | AR1: Entrance | AT1: Tank 1 | AV1: Tank 2
AR2: Level | AW2: Quantity CM3 | AZ2: Var
A3: Date | B3: Truck | C3: Truck M3/day | D3: N0. Trucks | F3: REQ. # of trucks | G3: City | H3: City/day | I3: Total water delivery | K3: SW | L3: Cosum SW/day | M3: RO Guest/ Liter | O3: RO K&L/ Liter | Q3: TOTAL RO Production | R3: RO 1 RH | S3: RO 2 RH | T3: RO water counter | U3: RO Cons m3 | V3: Steam Boiler | W3: Steam Boiler/day | X3: Softener Guest | Y3: Guest Sotf/day | Z3: Softener K&L | AA3: K&L Soft/Day | AB3: Fire Tank Level | AC3: Fire Tank Counter | AE3: Laundry Hot Water Counter | AF3: Hot Water Cons/day | AG3: Laundry Cold Water Counter | AH3: Cold Water Cons/day | AI3: Laundry Water Total Cons | AJ3: K&L Sotf/day | AK3: Guest / day | AL3: K&L /day | AM3: Avg Outside Temp | AN3: Banquet Activity | AR3: Date | AT3: MainI | AV3: Kitchen and Laundry | AX3: Guest | AY3: Main Tank | AZ3: Kitchen and Laundry | BA3: Guest | BB3: Kitchen and Laundry | BC3: Main | BD3: Guest | BE3: Total VAR | BF3: Hotel Consumption
E4: 1.66 | AN4: Ball R | AO4: Meeting | AP4: outlet | AT4: 180 | AV4: 220 | AX4: 580 | AY4: =SUM(AT4) -> 180 | AZ4: =SUM(AV4) -> 220 | BA4: =SUM(AX4) -> 580
A5: 44347 | B5: =[3]WATER!B36 -> 109443 | C5: =[3]WATER!C36 -> 0 | D5: =[3]WATER!D36 -> 0 | E5: =[3]WATER!E36 -> 241.93548 | F5: =[3]WATER!F36 -> 0 | G5: =[3]WATER!G36 -> 620421 | H5: =[3]WATER!H36 -> 148 | I5: =[3]WATER!I36 -> 148 | ... AP5: =[3]WATER!AP36 -> 0 | AR5: =[3]WATER!$AR$36 -> 44347 | AS5: =[3]WATER!AS36 -> 0.9 | AT5: =[3]WATER!AT36 -> 156 | AU5: =[3]WATER!AU36 -> 1.1 | AV5: =[3]WATER!AV36 -> 162 | AW5: =[3]WATER!AW36 -> 2.9 | AX5: =[3]WATER!AX36 -> 106 | AY5: =[3]WATER!AY36 -> 140.4 | AZ5: =[3]WATER!AZ36 -> 178.2 | ... BG5: =[3]WATER!BG36 -> 0
A6: =ELEC!C4 -> 44348 | B6: =B5 -> 109443 | C6: =B6-B5 -> 0 | D6: =C6/27 -> 0 | E6: =SUM((C6*$E$4)+(7500/'EDl log'!$A$37)) -> 250 | G6: =G5 -> 620421 | H6: =G6-G5 -> 0 | I6: =C6+H6 -> 0 | J6: =IF(I6>0,E6/I6,0) -> 0 | K6: ='Swimming Pool quality check '!H6 -> 6775 | L6: 0 | M6: =M5 -> 457.44 | N6: =SUM(M6-M5) -> 0 | O6: =O5 -> 529.52 | P6: =SUM(O6-O5) -> 0 | Q6: =P6+N6 -> 0 | T6: 5172 | U6: =SUM(T6-T5) -> 1 | V6: =V5 -> 474 | W6: =+V6-V5 -> 0 | X6: =X5 -> 152036 | Y6: =SUM(X6-X5) -> 0 | Z6: =Z5 -> 98847 | AA6: =Z6-Z5 -> 0 | AB6: =AB5 -> 261 | AC6: =AC5 -> 731 | AD6: 0 | AE6: =AE5 -> 229.81 | AF6: =AE6-AE5 -> 0 | AG6: =AG5 -> 2205.98 | AH6: =AG6-AG5 -> 0 | AI6: =AF6+AH6 -> 0 | AJ6: =+Z6-Z5 -> 0 | AK6: =SUM(Y6-L6) -> 0 | AL6: =SUM(AJ6-W6) -> 0 | AM6: ='General information '!D6 -> 24 | AN6: ='General information '!H6 -> 0 | AP6: ='General information '!J6 -> 0 | AR6: =A6 -> 44348 | AS6: =AS5 -> 0.9 | AT6: 90 | AU6: =AU5 -> 1.1 | AV6: 159 | AW6: 2.9 | AX6: 97 | AY6: =AS6*AT6 -> 81 | AZ6: =AU6*AV6 -> 174.9 | BA6: =AW6*AX6 -> 281.3 | BB6: =AY6-AY5 -> -59.4 | BC6: =AZ6-AZ5 -> -3.3 | BD6: =BA6-BA5 -> -26.1 | BE6: =SUM(BB6:BD6) -> -88.8 | BF6: =SUM(I6-BE6) -> 88.8 | BG6: =SUM(I6-BF6) -> -88.8
A7: =ELEC!C5 -> 44349 | B7: =B6 -> 109443 | C7: =B7-B6 -> 0 | D7: =C7/27 -> 0 | E7: =SUM((C7*$E$4)+(7500/'EDl log'!$A$37)) -> 250 | G7: 620530 | H7: =G7-G6 -> 109 | I7: =C7+H7 -> 109 | J7: =IF(I7>0,E7/I7,0) -> 2.293578 | K7: ='Swimming Pool quality check '!H7 -> 6775 | L7: =K7-K6 -> 0 | M7: =M6 -> 457.44 | N7: =SUM(M7-M6) -> 0 | O7: =O6 -> 529.52 | P7: =SUM(O7-O6) -> 0 | Q7: =P7+N7 -> 0 | T7: =T6 -> 5172 | U7: =SUM(T7-T6) -> 0 | V7: =V6 -> 474 | W7: =+V7-V6 -> 0 | X7: =X6 -> 152036 | Y7: =SUM(X7-X6) -> 0 | Z7: =Z6 -> 98847 | AA7: =Z7-Z6 -> 0 | AB7: =AB6 -> 261 | AC7: =AC6 -> 731 | AD7: =AC7-AC6 -> 0 | AE7: =AE6 -> 229.81 | AF7: =AE7-AE6 -> 0 | AG7: =AG6 -> 2205.98 | AH7: =AG7-AG6 -> 0 | AI7: =AF7+AH7 -> 0 | AJ7: =+Z7-Z6 -> 0 | AK7: =SUM(Y7-L7) -> 0 | AL7: =SUM(AJ7-W7) -> 0 | AM7: ='General information '!D7 -> 24 | AN7: ='General information '!H7 -> 0 | AP7: ='General information '!J7 -> 0 | AR7: =A7 -> 44349 | AS7: =AS6 -> 0.9 | AT7: 152 | AU7: =AU6 -> 1.1 | AV7: 156 | AW7: 2.9 | AX7: 88 | AY7: =AS7*AT7 -> 136.8 | AZ7: =AU7*AV7 -> 171.6 | BA7: =AW7*AX7 -> 255.2 | BB7: =AY7-AY6 -> 55.8 | BC7: =AZ7-AZ6 -> -3.3 | BD7: =BA7-BA6 -> -26.1 | BE7: =SUM(BB7:BD7) -> 26.4 | BF7: =SUM(I7-BE7) -> 82.6 | BG7: =SUM(I7-BF7) -> 26.4
A8: =ELEC!C6 -> 44350 | B8: =B7 -> 109443 | C8: =B8-B7 -> 0 | D8: =C8/27 -> 0 | E8: =SUM((C8*$E$4)+(7500/'EDl log'!$A$37)) -> 250 | G8: =G7 -> 620530 | H8: =G8-G7 -> 0 | I8: =C8+H8 -> 0 | J8: =IF(I8>0,E8/I8,0) -> 0 | K8: ='Swimming Pool quality check '!H8 -> 6775 | L8: =K8-K7 -> 0 | M8: =M7 -> 457.44 | N8: =SUM(M8-M7) -> 0 | O8: =O7 -> 529.52 | P8: =SUM(O8-O7) -> 0 | Q8: =P8+N8 -> 0 | T8: =T7 -> 5172 | U8: =SUM(T8-T7) -> 0 | V8: =V7 -> 474 | W8: =+V8-V7 -> 0 | X8: =X7 -> 152036 | Y8: =SUM(X8-X7) -> 0 | Z8: =Z7 -> 98847 | AA8: =Z8-Z7 -> 0 | AB8: =AB7 -> 261 | AC8: =AC7 -> 731 | AD8: =AC8-AC7 -> 0 | AE8: =AE7 -> 229.81 | AF8: =AE8-AE7 -> 0 | AG8: =AG7 -> 2205.98 | AH8: =AG8-AG7 -> 0 | AI8: =AF8+AH8 -> 0 | AJ8: =+Z8-Z7 -> 0 | AK8: =SUM(Y8-L8) -> 0 | AL8: =SUM(AJ8-W8) -> 0 | AM8: ='General information '!D8 -> 24.5 | AN8: ='General information '!H8 -> 0 | AP8: ='General information '!J8 -> 0 | AR8: =A8 -> 44350 | AS8: =AS7 -> 0.9 | AT8: =AT7 -> 152 | AU8: 1.1 | AV8: 151 | AW8: 2.9 | AX8: 78 | AY8: =AS8*AT8 -> 136.8 | AZ8: =AU8*AV8 -> 166.1 | BA8: =AW8*AX8 -> 226.2 | BB8: =AY8-AY7 -> 0 | BC8: =AZ8-AZ7 -> -5.5 | BD8: =BA8-BA7 -> -29 | BE8: =SUM(BB8:BD8) -> -34.5 | BF8: =SUM(I8-BE8) -> 34.5 | BG8: =SUM(I8-BF8) -> -34.5
A9: =ELEC!C7 -> 44351 | B9: =B8 -> 109443 | C9: =B9-B8 -> 0 | D9: =C9/27 -> 0 | E9: =SUM((C9*$E$4)+(7500/'EDl log'!$A$37)) -> 250 | G9: =G8 -> 620530 | H9: =G9-G8 -> 0 | I9: =C9+H9 -> 0 | J9: =IF(I9>0,E9/I9,0) -> 0 | K9: ='Swimming Pool quality check '!H9 -> 6775 | L9: =K9-K8 -> 0 | M9: =M8 -> 457.44 | N9: =SUM(M9-M8) -> 0 | O9: =O8 -> 529.52 | P9: =SUM(O9-O8) -> 0 | Q9: =P9+N9 -> 0 | T9: =T8 -> 5172 | U9: =SUM(T9-T8) -> 0 | V9: =V8 -> 474 | W9: =+V9-V8 -> 0 | X9: =X8 -> 152036 | Y9: =SUM(X9-X8) -> 0 | Z9: =Z8 -> 98847 | AA9: =Z9-Z8 -> 0 | AB9: =AB8 -> 261 | AC9: =AC8 -> 731 | AD9: =AC9-AC8 -> 0 | AE9: =AE8 -> 229.81 | AF9: =AE9-AE8 -> 0 | AG9: =AG8 -> 2205.98 | AH9: =AG9-AG8 -> 0 | AI9: =AF9+AH9 -> 0 | AJ9: =+Z9-Z8 -> 0 | AK9: =SUM(Y9-L9) -> 0 | AL9: =SUM(AJ9-W9) -> 0 | AM9: ='General information '!D9 -> 25 | AN9: ='General information '!H9 -> 0 | AP9: ='General information '!J9 -> 0 | AR9: =A9 -> 44351 | AS9: =AS8 -> 0.9 | AT9: =AT8 -> 152 | AU9: =AU8 -> 1.1 | AV9: 148 | AW9: 2.9 | AX9: 71 | AY9: =AS9*AT9 -> 136.8 | AZ9: =AU9*AV9 -> 162.8 | BA9: =AW9*AX9 -> 205.9 | BB9: =AY9-AY8 -> 0 | BC9: =AZ9-AZ8 -> -3.3 | BD9: =BA9-BA8 -> -20.3 | BE9: =SUM(BB9:BD9) -> -23.6 | BF9: =SUM(I9-BE9) -> 23.6 | BG9: =SUM(I9-BF9) -> -23.6
A10: =ELEC!C8 -> 44352 | B10: =B9 -> 109443 | C10: =B10-B9 -> 0 | D10: =C10/27 -> 0 | E10: =SUM((C10*$E$4)+(7500/'EDl log'!$A$37)) -> 250 | G10: =G9 -> 620530 | H10: =G10-G9 -> 0 | I10: =C10+H10 -> 0 | J10: =IF(I10>0,E10/I10,0) -> 0 | K10: ='Swimming Pool quality check '!H10 -> 6775 | L10: =K10-K9 -> 0 | M10: =M9 -> 457.44 | N10: =SUM(M10-M9) -> 0 | O10: =O9 -> 529.52 | P10: =SUM(O10-O9) -> 0 | Q10: =P10+N10 -> 0 | T10: =T9 -> 5172 | U10: =SUM(T10-T9) -> 0 | V10: =V9 -> 474 | W10: =+V10-V9 -> 0 | X10: =X9 -> 152036 | Y10: =SUM(X10-X9) -> 0 | Z10: =Z9 -> 98847 | AA10: =Z10-Z9 -> 0 | AB10: =AB9 -> 261 | AC10: =AC9 -> 731 | AD10: =AC10-AC9 -> 0 | AE10: =AE9 -> 229.81 | AF10: =AE10-AE9 -> 0 | AG10: =AG9 -> 2205.98 | AH10: =AG10-AG9 -> 0 | AI10: =AF10+AH10 -> 0 | AJ10: =+Z10-Z9 -> 0 | AK10: =SUM(Y10-L10) -> 0 | AL10: =SUM(AJ10-W10) -> 0 | AM10: ='General information '!D10 -> 23 | AN10: ='General information '!H10 -> 0 | AP10: ='General information '!J10 -> 0 | AR10: =A10 -> 44352 | AS10: =AS9 -> 0.9 | AT10: =AT9 -> 152 | AU10: =AU9 -> 1.1 | AV10: 146 | AW10: 2.9 | AX10: 62 | AY10: =AS10*AT10 -> 136.8 | AZ10: =AU10*AV10 -> 160.6 | BA10: =AW10*AX10 -> 179.8 | BB10: =AY10-AY9 -> 0 | BC10: =AZ10-AZ9 -> -2.2 | BD10: =BA10-BA9 -> -26.1 | BE10: =SUM(BB10:BD10) -> -28.3 | BF10: =SUM(I10-BE10) -> 28.3 | BG10: =SUM(I10-BF10) -> -28.3
A11: =ELEC!C9 -> 44353 | B11: =B10 -> 109443 | C11: =B11-B10 -> 0 | D11: =C11/27 -> 0 | E11: =SUM((C11*$E$4)+(7500/'EDl log'!$A$37)) -> 250 | G11: =G10 -> 620530 | H11: =G11-G10 -> 0 | I11: =C11+H11 -> 0 | J11: =IF(I11>0,E11/I11,0) -> 0 | K11: ='Swimming Pool quality check '!H11 -> 6776 | L11: =K11-K10 -> 1 | M11: =M10 -> 457.44 | N11: =SUM(M11-M10) -> 0 | O11: =O10 -> 529.52 | P11: =SUM(O11-O10) -> 0 | Q11: =SUM(P11+N11) -> 0 | T11: =T10 -> 5172 | U11: =SUM(T11-T10) -> 0 | V11: =V10 -> 474 | W11: =+V11-V10 -> 0 | X11: =X10 -> 152036 | Y11: =SUM(X11-X10) -> 0 | Z11: =Z10 -> 98847 | AA11: =Z11-Z10 -> 0 | AB11: =AB10 -> 261 | AC11: =AC10 -> 731 | AD11: =AC11-AC10 -> 0 | AE11: 229.86 | AF11: =AE11-AE10 -> 0.05 | AG11: 2206.58 | AH11: =AG11-AG10 -> 0.6 | AI11: =AF11+AH11 -> 0.65 | AJ11: =+Z11-Z10 -> 0 | AK11: =SUM(Y11-L11) -> -1 | AL11: =SUM(AJ11-W11) -> 0 | AM11: ='General information '!D11 -> 24 | AN11: ='General information '!H11 -> 0 | AP11: ='General information '!J11 -> 0 | AR11: =A11 -> 44353 | AS11: =AS10 -> 0.9 | AT11: 152 | AU11: =AU10 -> 1.1 | AV11: 143 | AW11: 2.9 | AX11: 53 | AY11: =AS11*AT11 -> 136.8 | AZ11: =AU11*AV11 -> 157.3 | BA11: =AW11*AX11 -> 153.7 | BB11: =AY11-AY10 -> 0 | BC11: =AZ11-AZ10 -> -3.3 | BD11: =BA11-BA10 -> -26.1 | BE11: =SUM(BB11:BD11) -> -29.4 | BF11: =SUM(I11-BE11) -> 29.4 | BG11: =SUM(I11-BF11) -> -29.4
A12: =ELEC!C10 -> 44354 | B12: =B11 -> 109443 | C12: =B12-B11 -> 0 | D12: =C12/27 -> 0 | E12: =SUM((C12*$E$4)+(7500/'EDl log'!$A$37)) -> 250 | G12: =G11 -> 620530 | H12: =G12-G11 -> 0 | I12: =C12+H12 -> 0 | J12: =IF(I12>0,E12/I12,0) -> 0 | K12: ='Swimming Pool quality check '!H12 -> 6776 | L12: =K12-K11 -> 0 | M12: =M11 -> 457.44 | N12: =SUM(M12-M11) -> 0 | O12: =O11 -> 529.52 | P12: =SUM(O12-O11) -> 0 | Q12: =SUM(P12+N12) -> 0 | T12: =T11 -> 5172 | U12: =SUM(T12-T11) -> 0 | V12: =V11 -> 474 | W12: =+V12-V11 -> 0 | X12: =X11 -> 152036 | Y12: =SUM(X12-X11) -> 0 | Z12: =Z11 -> 98847 | AA12: =Z12-Z11 -> 0 | AB12: =AB11 -> 261 | AC12: =AC11 -> 731 | AD12: =AC12-AC11 -> 0 | AE12: =AE11 -> 229.86 | AF12: =AE12-AE11 -> 0 | AG12: =AG11 -> 2206.58 | AH12: =AG12-AG11 -> 0 | AI12: =AF12+AH12 -> 0 | AJ12: =+Z12-Z11 -> 0 | AK12: =SUM(Y12-L12) -> 0 | AL12: =SUM(AJ12-W12) -> 0 | AM12: ='General information '!D12 -> 25 | AN12: ='General information '!H12 -> 0 | AP12: ='General information '!J12 -> 0 | AR12: =A12 -> 44354 | AS12: =AS11 -> 0.9 | AT12: =AT11 -> 152 | AU12: =AU11 -> 1.1 | AV12: 134 | AW12: 2.9 | AX12: 41 | AY12: =AS12*AT12 -> 136.8 | AZ12: =AU12*AV12 -> 147.4 | BA12: =AW12*AX12 -> 118.9 | BB12: =AY12-AY11 -> 0 | BC12: =AZ12-AZ11 -> -9.9 | BD12: =BA12-BA11 -> -34.8 | BE12: =SUM(BB12:BD12) -> -44.7 | BF12: =SUM(I12-BE12) -> 44.7 | BG12: =SUM(I12-BF12) -> -44.7
A13: =ELEC!C11 -> 44355 | B13: =B12 -> 109443 | C13: =B13-B12 -> 0 | D13: =C13/27 -> 0 | E13: =SUM((C13*$E$4)+(7500/'EDl log'!$A$37)) -> 250 | G13: =G12 -> 620530 | H13: =G13-G12 -> 0 | I13: =C13+H13 -> 0 | J13: =IF(I13>0,E13/I13,0) -> 0 | K13: ='Swimming Pool quality check '!H13 -> 6781 | L13: =K13-K12 -> 5 | M13: =M12 -> 457.44 | N13: =SUM(M13-M12) -> 0 | O13: =O12 -> 529.52 | P13: =SUM(O13-O12) -> 0 | Q13: =SUM(P13+N13) -> 0 | T13: =T12 -> 5172 | U13: =SUM(T13-T12) -> 0 | V13: =V12 -> 474 | W13: =+V13-V12 -> 0 | X13: =X12 -> 152036 | Y13: =SUM(X13-X12) -> 0 | Z13: =Z12 -> 98847 | AA13: =Z13-Z12 -> 0 | AB13: =AB12 -> 261 | AC13: =AC12 -> 731 | AD13: =AC13-AC12 -> 0 | AE13: =AE12 -> 229.86 | AF13: =AE13-AE12 -> 0 | AG13: =AG12 -> 2206.58 | AH13: =AG13-AG12 -> 0 | AI13: =AF13+AH13 -> 0 | AJ13: =+Z13-Z12 -> 0 | AK13: =SUM(Y13-L13) -> -5 | AL13: =SUM(AJ13-W13) -> 0 | AM13: ='General information '!D13 -> 25 | AN13: ='General information '!J13 -> 0 | AP13: ='General information '!J13 -> 0 | AR13: =A13 -> 44355 | AS13: =AS12 -> 0.9 | AT13: =AT12 -> 152 | AU13: =AU12 -> 1.1 | AV13: =AV12 -> 134 | AW13: 2.9 | AX13: =AX12 -> 41 | AY13: =AS13*AT13 -> 136.8 | AZ13: =AU13*AV13 -> 147.4 | BA13: =AW13*AX13 -> 118.9 | BB13: =AY13-AY12 -> 0 | BC13: =AZ13-AZ12 -> 0 | BD13: =BA13-BA12 -> 0 | BE13: =SUM(BB13:BD13) -> 0 | BF13: =SUM(I13-BE13) -> 0 | BG13: =SUM(I13-BF13) -> 0
A14: =ELEC!C12 -> 44356 | B14: =B13 -> 109443 | C14: =B14-B13 -> 0 | D14: =C14/27 -> 0 | E14: =SUM((C14*$E$4)+(7500/'EDl log'!$A$37)) -> 250 | G14: =G13 -> 620530 | H14: =G14-G13 -> 0 | I14: =C14+H14 -> 0 | J14: =IF(I14>0,E14/I14,0) -> 0 | K14: ='Swimming Pool quality check '!H14 -> 6781 | L14: =K14-K13 -> 0 | M14: =M13 -> 457.44 | N14: =SUM(M14-M13) -> 0 | O14: =O13 -> 529.52 | P14: =SUM(O14-O13) -> 0 | Q14: =SUM(P14+N14) -> 0 | T14: =T13 -> 5172 | U14: =SUM(T14-T13) -> 0 | V14: =V13 -> 474 | W14: =+V14-V13 -> 0 | X14: =X13 -> 152036 | Y14: =SUM(X14-X13) -> 0 | Z14: =Z13 -> 98847 | AA14: =Z14-Z13 -> 0 | AB14: =AB13 -> 261 | AC14: =AC13 -> 731 | AD14: =AC14-AC13 -> 0 | AE14: =AE13 -> 229.86 | AF14: =AE14-AE13 -> 0 | AG14: =AG13 -> 2206.58 | AH14: =AG14-AG13 -> 0 | AI14: =AF14+AH14 -> 0 | AJ14: =+Z14-Z13 -> 0 | AK14: =SUM(Y14-L14) -> 0 | AL14: =SUM(AJ14-W14) -> 0 | AM14: ='General information '!D14 -> 24.5 | AN14: ='General information '!H14 -> 0 | AP14: ='General information '!J14 -> 0 | AR14: =A14 -> 44356 | AS14: =AS13 -> 0.9 | AT14: =AT13 -> 152 | AU14: =AU13 -> 1.1 | AV14: 130 | AW14: 2.9 | AX14: 57 | AY14: =AS14*AT14 -> 136.8 | AZ14: =AU14*AV14 -> 143 | BA14: =AW14*AX14 -> 165.3 | BB14: =AY14-AY13 -> 0 | BC14: =AZ14-AZ13 -> -4.4 | BD14: =BA14-BA13 -> 46.4 | BE14: =SUM(BB14:BD14) -> 42 | BF14: =SUM(I14-BE14) -> -42 | BG14: =SUM(I14-BF14) -> 42
A15: =ELEC!C13 -> 44357 | B15: =B14 -> 109443 | C15: =B15-B14 -> 0 | D15: =C15/27 -> 0 | E15: =SUM((C15*$E$4)+(7500/'EDl log'!$A$37)) -> 250 | G15: =G14 -> 620530 | H15: =G15-G14 -> 0 | I15: =C15+H15 -> 0 | J15: =IF(I15>0,E15/I15,0) -> 0 | K15: ='Swimming Pool quality check '!H15 -> 6782 | L15: =K15-K14 -> 1 | M15: =M14 -> 457.44 | N15: =SUM(M15-M14) -> 0 | O15: =O14 -> 529.52 | P15: =SUM(O15-O14) -> 0 | Q15: =SUM(P15+N15) -> 0 | T15: =T14 -> 5172 | U15: =SUM(T15-T14) -> 0 | V15: =V14 -> 474 | W15: =+V15-V14 -> 0 | X15: =X14 -> 152036 | Y15: =SUM(X15-X14) -> 0 | Z15: =Z14 -> 98847 | AA15: =Z15-Z14 -> 0 | AB15: =AB14 -> 261 | AC15: =AC14 -> 731 | AD15: =AC15-AC14 -> 0 | AE15: =AE14 -> 229.86 | AF15: =AE15-AE14 -> 0 | AG15: =AG14 -> 2206.58 | AH15: =AG15-AG14 -> 0 | AI15: =AF15+AH15 -> 0 | AJ15: =+Z15-Z14 -> 0 | AK15: =SUM(Y15-L15) -> -1 | AL15: =SUM(AJ15-W15) -> 0 | AM15: ='General information '!D15 -> 25 | AN15: ='General information '!H15 -> 0 | AP15: ='General information '!J15 -> 0 | AR15: =A15 -> 44357 | AS15: =AS14 -> 0.9 | AT15: =AT14 -> 152 | AU15: =AU14 -> 1.1 | AV15: 126 | AW15: 2.9 | AX15: 68 | AY15: =AS15*AT15 -> 136.8 | AZ15: =AU15*AV15 -> 138.6 | BA15: =AW15*AX15 -> 197.2 | BB15: =AY15-AY14 -> 0 | BC15: =AZ15-AZ14 -> -4.4 | BD15: =BA15-BA14 -> 31.9 | BE15: =SUM(BB15:BD15) -> 27.5 | BF15: =SUM(I15-BE15) -> -27.5 | BG15: =SUM(I15-BF15) -> 27.5
A16: =ELEC!C14 -> 44358 | B16: =B15 -> 109443 | C16: =B16-B15 -> 0 | D16: =C16/27 -> 0 | E16: =SUM((C16*$E$4)+(7500/'EDl log'!$A$37)) -> 250 | G16: =G15 -> 620530 | H16: =G16-G15 -> 0 | I16: =C16+H16 -> 0 | J16: =IF(I16>0,E16/I16,0) -> 0 | K16: ='Swimming Pool quality check '!H16 -> 6782 | L16: =K16-K15 -> 0 | M16: =M15 -> 457.44 | N16: =SUM(M16-M15) -> 0 | O16: =O15 -> 529.52 | P16: =SUM(O16-O15) -> 0 | Q16: =SUM(P16+N16) -> 0 | T16: =T15 -> 5172 | U16: =SUM(T16-T15) -> 0 | V16: =V15 -> 474 | W16: =+V16-V15 -> 0 | X16: =X15 -> 152036 | Y16: =SUM(X16-X15) -> 0 | Z16: =Z15 -> 98847 | AA16: =Z16-Z15 -> 0 | AB16: =AB15 -> 261 | AC16: =AC15 -> 731 | AD16: =AC16-AC15 -> 0 | AE16: =AE15 -> 229.86 | AF16: =AE16-AE15 -> 0 | AG16: =AG15 -> 2206.58 | AH16: =AG16-AG15 -> 0 | AI16: =AF16+AH16 -> 0 | AJ16: =+Z16-Z15 -> 0 | AK16: =SUM(Y16-L16) -> 0 | AL16: =SUM(AJ16-W16) -> 0 | AM16: ='General information '!D16 -> 26 | AN16: ='General information '!H16 -> 0 | AP16: ='General information '!J16 -> 0 | AR16: =A16 -> 44358 | AS16: =AS15 -> 0.9 | AT16: =AT15 -> 152 | AU16: =AU15 -> 1.1 | AV16: 124 | AW16: 2.9 | AX16: 66 | AY16: =AS16*AT16 -> 136.8 | AZ16: =AU16*AV16 -> 136.4 | BA16: =AW16*AX16 -> 191.4 | BB16: =AY16-AY15 -> 0 | BC16: =AZ16-AZ15 -> -2.2 | BD16: =BA16-BA15 -> -5.8 | BE16: =SUM(BB16:BD16) -> -8 | BF16: =SUM(I16-BE16) -> 8 | BG16: =SUM(I16-BF16) -> -8
A17: =ELEC!C15 -> 44359 | B17: =B16 -> 109443 | C17: =B17-B16 -> 0 | D17: =C17/27 -> 0 | E17: =SUM((C17*$E$4)+(7500/'EDl log'!$A$37)) -> 250 | G17: =G16 -> 620530 | H17: =G17-G16 -> 0 | I17: =C17+H17 -> 0 | J17: =IF(I17>0,E17/I17,0) -> 0 | K17: ='Swimming Pool quality check '!H17 -> 6782 | L17: =K17-K16 -> 0 | M17: =M16 -> 457.44 | N17: =SUM(M17-M16) -> 0 | O17: =O16 -> 529.52 | P17: =SUM(O17-O16) -> 0 | Q17: =SUM(P17+N17) -> 0 | T17: =T16 -> 5172 | U17: =SUM(T17-T16) -> 0 | V17: =V16 -> 474 | W17: =+V17-V16 -> 0 | X17: =X16 -> 152036 | Y17: =SUM(X17-X16) -> 0 | Z17: =Z16 -> 98847 | AA17: =Z17-Z16 -> 0 | AB17: =AB16 -> 261 | AC17: =AC16 -> 731 | AD17: =AC17-AC16 -> 0 | AE17: =AE16 -> 229.86 | AF17: =AE17-AE16 -> 0 | AG17: =AG16 -> 2206.58 | AH17: =AG17-AG16 -> 0 | AI17: =AF17+AH17 -> 0 | AJ17: =+Z17-Z16 -> 0 | AK17: =SUM(Y17-L17) -> 0 | AL17: =SUM(AJ17-W17) -> 0 | AM17: ='General information '!D17 -> 24.5 | AN17: ='General information '!H17 -> 0 | AP17: ='General information '!J17 -> 0 | AR17: =A17 -> 44359 | AS17: =AS16 -> 0.9 | AT17: =AT16 -> 152 | AU17: =AU16 -> 1.1 | AV17: 121 | AW17: 2.9 | AX17: 52 | AY17: =AS17*AT17 -> 136.8 | AZ17: =AU17*AV17 -> 133.1 | BA17: =AW17*AX17 -> 150.8 | BB17: =AY17-AY16 -> 0 | BC17: =AZ17-AZ16 -> -3.3 | BD17: =BA17-BA16 -> -40.6 | BE17: =SUM(BB17:BD17) -> -43.9 | BF17: =SUM(I17-BE17) -> 43.9 | BG17: =SUM(I17-BF17) -> -43.9
A18: =ELEC!C16 -> 44360 | B18: =B17 -> 109443 | C18: =B18-B17 -> 0 | D18: =C18/27 -> 0 | E18: =SUM((C18*$E$4)+(7500/'EDl log'!$A$37)) -> 250 | G18: =G17 -> 620530 | H18: =G18-G17 -> 0 | I18: =C18+H18 -> 0 | J18: =IF(I18>0,E18/I18,0) -> 0 | K18: ='Swimming Pool quality check '!H18 -> 6782 | L18: =K18-K17 -> 0 | M18: =M17 -> 457.44 | N18: =SUM(M18-M17) -> 0 | O18: =O17 -> 529.52 | P18: =SUM(O18-O17) -> 0 | Q18: =SUM(P18+N18) -> 0 | T18: =T17 -> 5172 | U18: =SUM(T18-T17) -> 0 | V18: =V17 -> 474 | W18: =+V18-V17 -> 0 | X18: =X17 -> 152036 | Y18: =SUM(X18-X17) -> 0 | Z18: =Z17 -> 98847 | AA18: =Z18-Z17 -> 0 | AB18: =AB17 -> 261 | AC18: =AC17 -> 731 | AD18: =AC18-AC17 -> 0 | AE18: =AE17 -> 229.86 | AF18: =AE18-AE17 -> 0 | AG18: =AG17 -> 2206.58 | AH18: =AG18-AG17 -> 0 | AI18: =AF18+AH18 -> 0 | AJ18: =+Z18-Z17 -> 0 | AK18: =SUM(Y18-L18) -> 0 | AL18: =SUM(AJ18-W18) -> 0 | AM18: ='General information '!D18 -> 23.5 | AN18: ='General information '!H18 -> 0 | AP18: ='General information '!J18 -> 0 | AR18: =A18 -> 44360 | AS18: =AS17 -> 0.9 | AT18: =AT17 -> 152 | AU18: =AU17 -> 1.1 | AV18: =AV17 -> 121 | AW18: 2.9 | AX18: =AX17 -> 52 | AY18: =AS18*AT18 -> 136.8 | AZ18: =AU18*AV18 -> 133.1 | BA18: =AW18*AX18 -> 150.8 | BB18: =AY18-AY17 -> 0 | BC18: =AZ18-AZ17 -> 0 | BD18: =BA18-BA17 -> 0 | BE18: =SUM(BB18:BD18) -> 0 | BF18: =SUM(I18-BE18) -> 0 | BG18: =SUM(I18-BF18) -> 0
A19: =ELEC!C17 -> 44361 | B19: =B18 -> 109443 | C19: =B19-B18 -> 0 | D19: =C19/27 -> 0 | E19: =SUM((C19*$E$4)+(7500/'EDl log'!$A$37)) -> 250 | G19: =G18 -> 620530 | H19: =G19-G18 -> 0 | I19: =C19+H19 -> 0 | J19: =IF(I19>0,E19/I19,0) -> 0 | K19: ='Swimming Pool quality check '!H19 -> 6783 | L19: =K19-K18 -> 1 | M19: =M18 -> 457.44 | N19: =SUM(M19-M18) -> 0 | O19: =O18 -> 529.52 | P19: =SUM(O19-O18) -> 0 | Q19: =SUM(P19+N19) -> 0 | T19: =T18 -> 5172 | U19: =SUM(T19-T18) -> 0 | V19: =V18 -> 474 | W19: =+V19-V18 -> 0 | X19: =X18 -> 152036 | Y19: =SUM(X19-X18) -> 0 | Z19: =Z18 -> 98847 | AA19: =Z19-Z18 -> 0 | AB19: =AB18 -> 261 | AC19: =AC18 -> 731 | AD19: =AC19-AC18 -> 0 | AE19: =AE18 -> 229.86 | AF19: =AE19-AE18 -> 0 | AG19: =AG18 -> 2206.58 | AH19: =AG19-AG18 -> 0 | AI19: =AF19+AH19 -> 0 | AJ19: =+Z19-Z18 -> 0 | AK19: =SUM(Y19-L19) -> -1 | AL19: =SUM(AJ19-W19) -> 0 | AM19: ='General information '!D19 -> 23 | AN19: ='General information '!H19 -> 0 | AP19: ='General information '!J19 -> 0 | AR19: =A19 -> 44361 | AS19: =AS18 -> 0.9 | AT19: 152 | AU19: =AU18 -> 1.1 | AV19: 114 | AW19: 2.9 | AX19: 29 | AY19: =AS19*AT19 -> 136.8 | AZ19: =AU19*AV19 -> 125.4 | BA19: =AW19*AX19 -> 84.1 | BB19: =AY19-AY18 -> 0 | BC19: =AZ19-AZ18 -> -7.7 | BD19: =BA19-BA18 -> -66.7 | BE19: =SUM(BB19:BD19) -> -74.4 | BF19: =SUM(I19-BE19) -> 74.4 | BG19: =SUM(I19-BF19) -> -74.4
A20: =ELEC!C18 -> 44362 | B20: =B19 -> 109443 | C20: =B20-B19 -> 0 | D20: =C20/27 -> 0 | E20: =SUM((C20*$E$4)+(7500/'EDl log'!$A$37)) -> 250 | G20: =G19 -> 620530 | H20: =G20-G19 -> 0 | I20: =C20+H20 -> 0 | J20: =IF(I20>0,E20/I20,0) -> 0 | K20: ='Swimming Pool quality check '!H20 -> 6783 | L20: =K20-K19 -> 0 | M20: =M19 -> 457.44 | N20: =SUM(M20-M19) -> 0 | O20: =O19 -> 529.52 | P20: =SUM(O20-O19) -> 0 | Q20: =SUM(P20+N20) -> 0 | T20: =T19 -> 5172 | U20: =SUM(T20-T19) -> 0 | V20: =V19 -> 474 | W20: =+V20-V19 -> 0 | X20: 152149 | Y20: =SUM(X20-X19) -> 113 | Z20: =Z19 -> 98847 | AA20: =Z20-Z19 -> 0 | AB20: =AB19 -> 261 | AC20: =AC19 -> 731 | AD20: =AC20-AC19 -> 0 | AE20: =AE19 -> 229.86 | AF20: =AE20-AE19 -> 0 | AG20: =AG19 -> 2206.58 | AH20: =AG20-AG19 -> 0 | AI20: =AF20+AH20 -> 0 | AJ20: =+Z20-Z19 -> 0 | AK20: =SUM(Y20-L20) -> 113 | AL20: =SUM(AJ20-W20) -> 0 | AM20: ='General information '!D20 -> 24.5 | AN20: ='General information '!H20 -> 0 | AP20: ='General information '!J20 -> 0 | AR20: =A20 -> 44362 | AS20: =AS19 -> 0.9 | AT20: 24 | AU20: =AU19 -> 1.1 | AV20: 109 | AW20: 2.9 | AX20: 72 | AY20: =AS20*AT20 -> 21.6 | AZ20: =AU20*AV20 -> 119.9 | BA20: =AW20*AX20 -> 208.8 | BB20: =AY20-AY19 -> -115.2 | BC20: =AZ20-AZ19 -> -5.5 | BD20: =BA20-BA19 -> 124.7 | BE20: =SUM(BB20:BD20) -> 4 | BF20: =SUM(I20-BE20) -> -4 | BG20: =SUM(I20-BF20) -> 4
A21: =ELEC!C19 -> 44363 | B21: =B20 -> 109443 | C21: =B21-B20 -> 0 | D21: =C21/27 -> 0 | E21: =SUM((C21*$E$4)+(7500/'EDl log'!$A$37)) -> 250 | G21: 620750 | H21: =G21-G20 -> 220 | I21: =C21+H21 -> 220 | J21: =IF(I21>0,E21/I21,0) -> 1.1363636 | K21: ='Swimming Pool quality check '!H21 -> 6784 | L21: =K21-K20 -> 1 | M21: =M20 -> 457.44 | N21: =SUM(M21-M20) -> 0 | O21: =O20 -> 529.52 | P21: =SUM(O21-O20) -> 0 | Q21: =SUM(P21+N21) -> 0 | T21: =T20 -> 5172 | U21: =SUM(T21-T20) -> 0 | V21: =V20 -> 474 | W21: =+V21-V20 -> 0 | X21: =X20 -> 152149 | Y21: =SUM(X21-X20) -> 0 | Z21: =Z20 -> 98847 | AA21: =Z21-Z20 -> 0 | AB21: =AB20 -> 261 | AC21: =AC20 -> 731 | AD21: =AC21-AC20 -> 0 | AE21: =AE20 -> 229.86 | AF21: =AE21-AE20 -> 0 | AG21: =AG20 -> 2206.58 | AH21: =AG21-AG20 -> 0 | AI21: =AF21+AH21 -> 0 | AJ21: =+Z21-Z20 -> 0 | AK21: =SUM(Y21-L21) -> -1 | AL21: =SUM(AJ21-W21) -> 0 | AM21: ='General information '!D21 -> 25 | AN21: ='General information '!H21 -> 0 | AP21: ='General information '!J21 -> 0 | AR21: =A21 -> 44363 | AS21: =AS20 -> 0.9 | AT21: 154 | AU21: =AU20 -> 1.1 | AV21: 103 | AW21: 2.9 | AX21: 55 | AY21: =AS21*AT21 -> 138.6 | AZ21: =AU21*AV21 -> 113.3 | BA21: =AW21*AX21 -> 159.5 | BB21: =AY21-AY20 -> 117 | BC21: =AZ21-AZ20 -> -6.6 | BD21: =BA21-BA20 -> -49.3 | BE21: =SUM(BB21:BD21) -> 61.1 | BF21: =SUM(I21-BE21) -> 158.9 | BG21: =SUM(I21-BF21) -> 61.1
A22: =ELEC!C20 -> 44364 | B22: =B21 -> 109443 | C22: =B22-B21 -> 0 | D22: =C22/27 -> 0 | E22: =SUM((C22*$E$4)+(7500/'EDl log'!$A$37)) -> 250 | G22: =G21 -> 620750 | H22: =G22-G21 -> 0 | I22: =C22+H22 -> 0 | J22: =IF(I22>0,E22/I22,0) -> 0 | K22: ='Swimming Pool quality check '!H22 -> 6785 | L22: =K22-K21 -> 1 | M22: =M21 -> 457.44 | N22: =SUM(M22-M21) -> 0 | O22: =O21 -> 529.52 | P22: =SUM(O22-O21) -> 0 | Q22: =SUM(P22+N22) -> 0 | T22: =T21 -> 5172 | U22: =SUM(T22-T21) -> 0 | V22: =V21 -> 474 | W22: =+V22-V21 -> 0 | X22: 152207 | Y22: =SUM(X22-X21) -> 58 | Z22: =Z21 -> 98847 | AA22: =Z22-Z21 -> 0 | AB22: =AB21 -> 261 | AC22: =AC21 -> 731 | AD22: =AC22-AC21 -> 0 | AE22: =AE21 -> 229.86 | AF22: =AE22-AE21 -> 0 | AG22: 2206.6 | AH22: =AG22-AG21 -> 0.02 | AI22: =AF22+AH22 -> 0.02 | AJ22: =+Z22-Z21 -> 0 | AK22: =SUM(Y22-L22) -> 57 | AL22: =SUM(AJ22-W22) -> 0 | AM22: ='General information '!D22 -> 24.5 | AN22: ='General information '!H22 -> 0 | AP22: ='General information '!J22 -> 0 | AR22: =A22 -> 44364 | AS22: =AS21 -> 0.9 | AT22: 100 | AU22: =AU21 -> 1.1 | AV22: 100 | AW22: 2.9 | AX22: 57 | AY22: =AS22*AT22 -> 90 | AZ22: =AU22*AV22 -> 110 | BA22: =AW22*AX22 -> 165.3 | BB22: =AY22-AY21 -> -48.6 | BC22: =AZ22-AZ21 -> -3.3 | BD22: =BA22-BA21 -> 5.8 | BE22: =SUM(BB22:BD22) -> -46.1 | BF22: =SUM(I22-BE22) -> 46.1 | BG22: =SUM(I22-BF22) -> -46.1
A23: =ELEC!C21 -> 44365 | B23: =B22 -> 109443 | C23: =B23-B22 -> 0 | D23: =C23/27 -> 0 | E23: =SUM((C23*$E$4)+(7500/'EDl log'!$A$37)) -> 250 | G23: =G22 -> 620750 | H23: =G23-G22 -> 0 | I23: =C23+H23 -> 0 | J23: =IF(I23>0,E23/I23,0) -> 0 | K23: ='Swimming Pool quality check '!H23 -> 6785 | L23: =K23-K22 -> 0 | M23: =M22 -> 457.44 | N23: =SUM(M23-M22) -> 0 | O23: =O22 -> 529.52 | P23: =SUM(O23-O22) -> 0 | Q23: =SUM(P23+N23) -> 0 | T23: =T22 -> 5172 | U23: =SUM(T23-T22) -> 0 | V23: =V22 -> 474 | W23: =+V23-V22 -> 0 | X23: =X22 -> 152207 | Y23: =SUM(X23-X22) -> 0 | Z23: =Z22 -> 98847 | AA23: =Z23-Z22 -> 0 | AB23: =AB22 -> 261 | AC23: =AC22 -> 731 | AD23: =AC23-AC22 -> 0 | AE23: =AE22 -> 229.86 | AF23: =AE23-AE22 -> 0 | AG23: =AG22 -> 2206.6 | AH23: =AG23-AG22 -> 0 | AI23: =AF23+AH23 -> 0 | AJ23: =+Z23-Z22 -> 0 | AK23: =SUM(Y23-L23) -> 0 | AL23: =SUM(AJ23-W23) -> 0 | AM23: ='General information '!D23 -> 0 | AN23: ='General information '!H23 -> 0 | AP23: ='General information '!J23 -> 0 | AR23: =A23 -> 44365 | AS23: =AS22 -> 0.9 | AT23: =AT22 -> 100 | AU23: =AU22 -> 1.1 | AV23: =AV22 -> 100 | AW23: 2.9 | AX23: =AX22 -> 57 | AY23: =AS23*AT23 -> 90 | AZ23: =AU23*AV23 -> 110 | BA23: =AW23*AX23 -> 165.3 | BB23: =AY23-AY22 -> 0 | BC23: =AZ23-AZ22 -> 0 | BD23: =BA23-BA22 -> 0 | BE23: =SUM(BB23:BD23) -> 0 | BF23: =SUM(I23-BE23) -> 0 | BG23: =SUM(I23-BF23) -> 0
A24: =ELEC!C22 -> 44366 | B24: =B23 -> 109443 | C24: =B24-B23 -> 0 | D24: =C24/27 -> 0 | E24: =SUM((C24*$E$4)+(7500/'EDl log'!$A$37)) -> 250 | G24: =G23 -> 620750 | H24: =G24-G23 -> 0 | I24: =C24+H24 -> 0 | J24: =IF(I24>0,E24/I24,0) -> 0 | K24: ='Swimming Pool quality check '!H24 -> 6785 | L24: =K24-K23 -> 0 | M24: =M23 -> 457.44 | N24: =SUM(M24-M23) -> 0 | O24: =O23 -> 529.52 | P24: =SUM(O24-O23) -> 0 | Q24: =SUM(P24+N24) -> 0 | T24: =T23 -> 5172 | U24: =SUM(T24-T23) -> 0 | V24: =V23 -> 474 | W24: =+V24-V23 -> 0 | X24: =X23 -> 152207 | Y24: =SUM(X24-X23) -> 0 | Z24: =Z23 -> 98847 | AA24: =Z24-Z23 -> 0 | AB24: =AB23 -> 261 | AC24: =AC23 -> 731 | AD24: =AC24-AC23 -> 0 | AE24: =AE23 -> 229.86 | AF24: =AE24-AE23 -> 0 | AG24: =AG23 -> 2206.6 | AH24: =AG24-AG23 -> 0 | AI24: =AF24+AH24 -> 0 | AJ24: =+Z24-Z23 -> 0 | AK24: =SUM(Y24-L24) -> 0 | AL24: =SUM(AJ24-W24) -> 0 | AM24: ='General information '!D24 -> 0 | AN24: ='[4]General information '!H24 -> 0 | AP24: ='[4]General information '!J24 -> 0 | AR24: =A24 -> 44366 | AS24: =AS23 -> 0.9 | AT24: =AT23 -> 100 | AU24: =AU23 -> 1.1 | AV24: =AV23 -> 100 | AW24: 2.9 | AX24: =AX23 -> 57 | AY24: =AS24*AT24 -> 90 | AZ24: =AU24*AV24 -> 110 | BA24: =AW24*AX24 -> 165.3 | BB24: =AY24-AY23 -> 0 | BC24: =AZ24-AZ23 -> 0 | BD24: =BA24-BA23 -> 0 | BE24: =SUM(BB24:BD24) -> 0 | BF24: =SUM(I24-BE24) -> 0 | BG24: =SUM(I24-BF24) -> 0
A25: =ELEC!C23 -> 44367 | B25: =B24 -> 109443 | C25: =B25-B24 -> 0 | D25: =C25/27 -> 0 | E25: =SUM((C25*$E$4)+(7500/'EDl log'!$A$37)) -> 250 | G25: =G24 -> 620750 | H25: =G25-G24 -> 0 | I25: =C25+H25 -> 0 | J25: =IF(I25>0,E25/I25,0) -> 0 | K25: ='Swimming Pool quality check '!H25 -> 6785 | L25: =K25-K24 -> 0 | M25: =M24 -> 457.44 | N25: =SUM(M25-M24) -> 0 | O25: =O24 -> 529.52 | P25: =SUM(O25-O24) -> 0 | Q25: =SUM(P25+N25) -> 0 | T25: =T24 -> 5172 | U25: =SUM(T25-T24) -> 0 | V25: =V24 -> 474 | W25: =+V25-V24 -> 0 | X25: =X24 -> 152207 | Y25: =SUM(X25-X24) -> 0 | Z25: =Z24 -> 98847 | AA25: =Z25-Z24 -> 0 | AB25: =AB24 -> 261 | AC25: =AC24 -> 731 | AD25: =AC25-AC24 -> 0 | AE25: =AE24 -> 229.86 | AF25: =AE25-AE24 -> 0 | AG25: =AG24 -> 2206.6 | AH25: =AG25-AG24 -> 0 | AI25: =AF25+AH25 -> 0 | AJ25: =+Z25-Z24 -> 0 | AK25: =SUM(Y25-L25) -> 0 | AL25: =SUM(AJ25-W25) -> 0 | AM25: ='General information '!D25 -> 0 | AN25: ='General information '!H25 -> 0 | AP25: ='General information '!J25 -> 0 | AR25: =A25 -> 44367 | AS25: =AS24 -> 0.9 | AT25: =AT24 -> 100 | AU25: =AU24 -> 1.1 | AV25: =AV24 -> 100 | AW25: 2.9 | AX25: =AX24 -> 57 | AY25: =AS25*AT25 -> 90 | AZ25: =AU25*AV25 -> 110 | BA25: =AW25*AX25 -> 165.3 | BB25: =AY25-AY24 -> 0 | BC25: =AZ25-AZ24 -> 0 | BD25: =BA25-BA24 -> 0 | BE25: =SUM(BB25:BD25) -> 0 | BF25: =SUM(I25-BE25) -> 0 | BG25: =SUM(I25-BF25) -> 0
A26: =ELEC!C24 -> 44368 | B26: =B25 -> 109443 | C26: =B26-B25 -> 0 | D26: =C26/27 -> 0 | E26: =SUM((C26*$E$4)+(7500/'EDl log'!$A$37)) -> 250 | G26: =G25 -> 620750 | H26: =G26-G25 -> 0 | I26: =C26+H26 -> 0 | J26: =IF(I26>0,E26/I26,0) -> 0 | K26: ='Swimming Pool quality check '!H26 -> 6785 | L26: =K26-K25 -> 0 | M26: =M25 -> 457.44 | N26: =SUM(M26-M25) -> 0 | O26: =O25 -> 529.52 | P26: =SUM(O26-O25) -> 0 | Q26: =SUM(P26+N26) -> 0 | T26: =T25 -> 5172 | U26: =SUM(T26-T25) -> 0 | V26: =V25 -> 474 | W26: =+V26-V25 -> 0 | X26: =X25 -> 152207 | Y26: =SUM(X26-X25) -> 0 | Z26: =Z25 -> 98847 | AA26: =Z26-Z25 -> 0 | AB26: =AB25 -> 261 | AC26: =AC25 -> 731 | AD26: =AC26-AC25 -> 0 | AE26: =AE25 -> 229.86 | AF26: =AE26-AE25 -> 0 | AG26: =AG25 -> 2206.6 | AH26: =AG26-AG25 -> 0 | AI26: =AF26+AH26 -> 0 | AJ26: =+Z26-Z25 -> 0 | AK26: =SUM(Y26-L26) -> 0 | AL26: =SUM(AJ26-W26) -> 0 | AM26: ='General information '!D26 -> 0 | AN26: ='General information '!H26 -> 0 | AP26: ='General information '!J26 -> 0 | AR26: =A26 -> 44368 | AS26: =AS25 -> 0.9 | AT26: =AT25 -> 100 | AU26: =AU25 -> 1.1 | AV26: =AV25 -> 100 | AW26: 2.9 | AX26: =AX25 -> 57 | AY26: =AS26*AT26 -> 90 | AZ26: =AU26*AV26 -> 110 | BA26: =AW26*AX26 -> 165.3 | BB26: =AY26-AY25 -> 0 | BC26: =AZ26-AZ25 -> 0 | BD26: =BA26-BA25 -> 0 | BE26: =SUM(BB26:BD26) -> 0 | BF26: =SUM(I26-BE26) -> 0 | BG26: =SUM(I26-BF26) -> 0
A27: =ELEC!C25 -> 44369 | B27: =B26 -> 109443 | C27: =B27-B26 -> 0 | D27: =C27/27 -> 0 | E27: =SUM((C27*$E$4)+(7500/'EDl log'!$A$37)) -> 250 | G27: =G26 -> 620750 | H27: =G27-G26 -> 0 | I27: =C27+H27 -> 0 | J27: =IF(I27>0,E27/I27,0) -> 0 | K27: ='Swimming Pool quality check '!H27 -> 6785 | L27: =K27-K26 -> 0 | M27: =M26 -> 457.44 | N27: =SUM(M27-M26) -> 0 | O27: =O26 -> 529.52 | P27: =SUM(O27-O26) -> 0 | Q27: =SUM(P27+N27) -> 0 | T27: =T26 -> 5172 | U27: =SUM(T27-T26) -> 0 | V27: =V26 -> 474 | W27: =+V27-V26 -> 0 | X27: =X26 -> 152207 | Y27: =SUM(X27-X26) -> 0 | Z27: =Z26 -> 98847 | AA27: =Z27-Z26 -> 0 | AB27: =AB26 -> 261 | AC27: =AC26 -> 731 | AD27: =AC27-AC26 -> 0 | AE27: =AE26 -> 229.86 | AF27: =AE27-AE26 -> 0 | AG27: =AG26 -> 2206.6 | AH27: =AG27-AG26 -> 0 | AI27: =AF27+AH27 -> 0 | AJ27: =+Z27-Z26 -> 0 | AK27: =SUM(Y27-L27) -> 0 | AL27: =SUM(AJ27-W27) -> 0 | AM27: ='General information '!D27 -> 0 | AN27: ='General information '!H27 -> 0 | AP27: ='General information '!J27 -> 0 | AR27: =A27 -> 44369 | AS27: =AS26 -> 0.9 | AT27: =AT26 -> 100 | AU27: =AU26 -> 1.1 | AV27: =AV26 -> 100 | AW27: 2.9 | AX27: =AX26 -> 57 | AY27: =AS27*AT27 -> 90 | AZ27: =AU27*AV27 -> 110 | BA27: =AW27*AX27 -> 165.3 | BB27: =AY27-AY26 -> 0 | BC27: =AZ27-AZ26 -> 0 | BD27: =BA27-BA26 -> 0 | BE27: =SUM(BB27:BD27) -> 0 | BF27: =SUM(I27-BE27) -> 0 | BG27: =SUM(I27-BF27) -> 0
A28: =ELEC!C26 -> 44370 | B28: =B27 -> 109443 | C28: =B28-B27 -> 0 | D28: =C28/27 -> 0 | E28: =SUM((C28*$E$4)+(7500/'EDl log'!$A$37)) -> 250 | G28: =G27 -> 620750 | H28: =G28-G27 -> 0 | I28: =C28+H28 -> 0 | J28: =IF(I28>0,E28/I28,0) -> 0 | K28: ='Swimming Pool quality check '!H28 -> 6785 | L28: =K28-K27 -> 0 | M28: =M27 -> 457.44 | N28: =SUM(M28-M27) -> 0 | O28: =O27 -> 529.52 | P28: =SUM(O28-O27) -> 0 | Q28: =SUM(P28+N28) -> 0 | T28: =T27 -> 5172 | U28: =SUM(T28-T27) -> 0 | V28: =V27 -> 474 | W28: =+V28-V27 -> 0 | X28: =X27 -> 152207 | Y28: =SUM(X28-X27) -> 0 | Z28: =Z27 -> 98847 | AA28: =Z28-Z27 -> 0 | AB28: =AB27 -> 261 | AC28: =AC27 -> 731 | AD28: =AC28-AC27 -> 0 | AE28: =AE27 -> 229.86 | AF28: =AE28-AE27 -> 0 | AG28: =AG27 -> 2206.6 | AH28: =AG28-AG27 -> 0 | AI28: =AF28+AH28 -> 0 | AJ28: =+Z28-Z27 -> 0 | AK28: =SUM(Y28-L28) -> 0 | AL28: =SUM(AJ28-W28) -> 0 | AM28: ='General information '!D28 -> 0 | AN28: ='General information '!H28 -> 0 | AP28: ='General information '!J28 -> 0 | AR28: =A28 -> 44370 | AS28: =AS27 -> 0.9 | AT28: =AT27 -> 100 | AU28: =AU27 -> 1.1 | AV28: =AV27 -> 100 | AW28: 2.9 | AX28: =AX27 -> 57 | AY28: =AS28*AT28 -> 90 | AZ28: =AU28*AV28 -> 110 | BA28: =AW28*AX28 -> 165.3 | BB28: =AY28-AY27 -> 0 | BC28: =AZ28-AZ27 -> 0 | BD28: =BA28-BA27 -> 0 | BE28: =SUM(BB28:BD28) -> 0 | BF28: =SUM(I28-BE28) -> 0 | BG28: =SUM(I28-BF28) -> 0
A29: =ELEC!C27 -> 44371 | B29: =B28 -> 109443 | C29: =B29-B28 -> 0 | D29: =C29/27 -> 0 | E29: =SUM((C29*$E$4)+(7500/'EDl log'!$A$37)) -> 250 | G29: =G28 -> 620750 | H29: =G29-G28 -> 0 | I29: =C29+H29 -> 0 | J29: =IF(I29>0,E29/I29,0) -> 0 | K29: ='Swimming Pool quality check '!H29 -> 6785 | L29: =K29-K28 -> 0 | M29: =M28 -> 457.44 | N29: =SUM(M29-M28) -> 0 | O29: =O28 -> 529.52 | P29: =SUM(O29-O28) -> 0 | Q29: =SUM(P29+N29) -> 0 | T29: =T28 -> 5172 | U29: =SUM(T29-T28) -> 0 | V29: =V28 -> 474 | W29: =+V29-V28 -> 0 | X29: =X28 -> 152207 | Y29: =SUM(X29-X28) -> 0 | Z29: =Z28 -> 98847 | AA29: =Z29-Z28 -> 0 | AB29: =AB28 -> 261 | AC29: =AC28 -> 731 | AD29: =AC29-AC28 -> 0 | AE29: =AE28 -> 229.86 | AF29: =AE29-AE28 -> 0 | AG29: =AG28 -> 2206.6 | AH29: =AG29-AG28 -> 0 | AI29: =AF29+AH29 -> 0 | AJ29: =+Z29-Z28 -> 0 | AK29: =SUM(Y29-L29) -> 0 | AL29: =SUM(AJ29-W29) -> 0 | AM29: ='General information '!D29 -> 0 | AN29: ='General information '!H29 -> 0 | AP29: ='General information '!J29 -> 0 | AR29: =A29 -> 44371 | AS29: =AS28 -> 0.9 | AT29: =AT28 -> 100 | AU29: =AU28 -> 1.1 | AV29: =AV28 -> 100 | AW29: 2.9 | AX29: =AX28 -> 57 | AY29: =AS29*AT29 -> 90 | AZ29: =AU29*AV29 -> 110 | BA29: =AW29*AX29 -> 165.3 | BB29: =AY29-AY28 -> 0 | BC29: =AZ29-AZ28 -> 0 | BD29: =BA29-BA28 -> 0 | BE29: =SUM(BB29:BD29) -> 0 | BF29: =SUM(I29-BE29) -> 0 | BG29: =SUM(I29-BF29) -> 0
A30: =ELEC!C28 -> 44372 | B30: =B29 -> 109443 | C30: =B30-B29 -> 0 | D30: =C30/27 -> 0 | E30: =SUM((C30*$E$4)+(7500/'EDl log'!$A$37)) -> 250 | G30: =G29 -> 620750 | H30: =G30-G29 -> 0 | I30: =C30+H30 -> 0 | J30: =IF(I30>0,E30/I30,0) -> 0 | K30: ='Swimming Pool quality check '!H30 -> 6785 | L30: =K30-K29 -> 0 | M30: =M29 -> 457.44 | N30: =SUM(M30-M29) -> 0 | O30: =O29 -> 529.52 | P30: =SUM(O30-O29) -> 0 | Q30: =SUM(P30+N30) -> 0 | T30: =T29 -> 5172 | U30: =SUM(T30-T29) -> 0 | V30: =V29 -> 474 | W30: =+V30-V29 -> 0 | X30: =X29 -> 152207 | Y30: =SUM(X30-X29) -> 0 | Z30: =Z29 -> 98847 | AA30: =Z30-Z29 -> 0 | AB30: =AB29 -> 261 | AC30: =AC29 -> 731 | AD30: =AC30-AC29 -> 0 | AE30: =AE29 -> 229.86 | AF30: =AE30-AE29 -> 0 | AG30: =AG29 -> 2206.6 | AH30: =AG30-AG29 -> 0 | AI30: =AF30+AH30 -> 0 | AJ30: =+Z30-Z29 -> 0 | AK30: =SUM(Y30-L30) -> 0 | AL30: =SUM(AJ30-W30) -> 0 | AM30: ='General information '!D30 -> 0 | AN30: ='General information '!H30 -> 0 | AP30: ='General information '!J30 -> 0 | AR30: =A30 -> 44372 | AS30: =AS29 -> 0.9 | AT30: =AT29 -> 100 | AU30: =AU29 -> 1.1 | AV30: =AV29 -> 100 | AW30: 2.9 | AX30: =AX29 -> 57 | AY30: =AS30*AT30 -> 90 | AZ30: =AU30*AV30 -> 110 | BA30: =AW30*AX30 -> 165.3 | BB30: =AY30-AY29 -> 0 | BC30: =AZ30-AZ29 -> 0 | BD30: =BA30-BA29 -> 0 | BE30: =SUM(BB30:BD30) -> 0 | BF30: =SUM(I30-BE30) -> 0 | BG30: =SUM(I30-BF30) -> 0
A31: =ELEC!C29 -> 44373 | B31: =B30 -> 109443 | C31: =B31-B30 -> 0 | D31: =C31/27 -> 0 | E31: =SUM((C31*$E$4)+(7500/'EDl log'!$A$37)) -> 250 | G31: =G30 -> 620750 | H31: =G31-G30 -> 0 | I31: =C31+H31 -> 0 | J31: =IF(I31>0,E31/I31,0) -> 0 | K31: ='Swimming Pool quality check '!H31 -> 6785 | L31: =K31-K30 -> 0 | M31: =M30 -> 457.44 | N31: =SUM(M31-M30) -> 0 | O31: =O30 -> 529.52 | P31: =SUM(O31-O30) -> 0 | Q31: =SUM(P31+N31) -> 0 | T31: =T30 -> 5172 | U31: =SUM(T31-T30) -> 0 | V31: =V30 -> 474 | W31: =+V31-V30 -> 0 | X31: =X30 -> 152207 | Y31: =SUM(X31-X30) -> 0 | Z31: =Z30 -> 98847 | AA31: =Z31-Z30 -> 0 | AB31: =AB30 -> 261 | AC31: =AC30 -> 731 | AD31: =AC31-AC30 -> 0 | AE31: =AE30 -> 229.86 | AF31: =AE31-AE30 -> 0 | AG31: =AG30 -> 2206.6 | AH31: =AG31-AG30 -> 0 | AI31: =AF31+AH31 -> 0 | AJ31: =+Z31-Z30 -> 0 | AK31: =SUM(Y31-L31) -> 0 | AL31: =SUM(AJ31-W31) -> 0 | AM31: ='General information '!D31 -> 0 | AN31: ='General information '!H31 -> 0 | AP31: ='General information '!J31 -> 0 | AR31: =A31 -> 44373 | AS31: =AS30 -> 0.9 | AT31: =AT30 -> 100 | AU31: =AU30 -> 1.1 | AV31: =AV30 -> 100 | AW31: 2.9 | AX31: =AX30 -> 57 | AY31: =AS31*AT31 -> 90 | AZ31: =AU31*AV31 -> 110 | BA31: =AW31*AX31 -> 165.3 | BB31: =AY31-AY30 -> 0 | BC31: =AZ31-AZ30 -> 0 | BD31: =BA31-BA30 -> 0 | BE31: =SUM(BB31:BD31) -> 0 | BF31: =SUM(I31-BE31) -> 0 | BG31: =SUM(I31-BF31) -> 0
A32: =ELEC!C30 -> 44374 | B32: =B31 -> 109443 | C32: =B32-B31 -> 0 | D32: =C32/27 -> 0 | E32: =SUM((C32*$E$4)+(7500/'EDl log'!$A$37)) -> 250 | G32: =G31 -> 620750 | H32: =G32-G31 -> 0 | I32: =C32+H32 -> 0 | J32: =IF(I32>0,E32/I32,0) -> 0 | K32: ='Swimming Pool quality check '!H32 -> 6785 | L32: =K32-K31 -> 0 | M32: =M31 -> 457.44 | N32: =SUM(M32-M31) -> 0 | O32: =O31 -> 529.52 | P32: =SUM(O32-O31) -> 0 | Q32: =SUM(P32+N32) -> 0 | T32: =T31 -> 5172 | U32: =SUM(T32-T31) -> 0 | V32: =V31 -> 474 | W32: =+V32-V31 -> 0 | X32: =X31 -> 152207 | Y32: =SUM(X32-X31) -> 0 | Z32: =Z31 -> 98847 | AA32: =Z32-Z31 -> 0 | AB32: =AB31 -> 261 | AC32: =AC31 -> 731 | AD32: =AC32-AC31 -> 0 | AE32: =AE31 -> 229.86 | AF32: =AE32-AE31 -> 0 | AG32: =AG31 -> 2206.6 | AH32: =AG32-AG31 -> 0 | AI32: =AF32+AH32 -> 0 | AJ32: =+Z32-Z31 -> 0 | AK32: =SUM(Y32-L32) -> 0 | AL32: =SUM(AJ32-W32) -> 0 | AM32: ='General information '!D32 -> 0 | AN32: ='General information '!H32 -> 0 | AP32: ='General information '!J32 -> 0 | AR32: =A32 -> 44374 | AS32: =AS31 -> 0.9 | AT32: =AT31 -> 100 | AU32: =AU31 -> 1.1 | AV32: =AV31 -> 100 | AW32: 2.9 | AX32: =AX31 -> 57 | AY32: =AS32*AT32 -> 90 | AZ32: =AU32*AV32 -> 110 | BA32: =AW32*AX32 -> 165.3 | BB32: =AY32-AY31 -> 0 | BC32: =AZ32-AZ31 -> 0 | BD32: =BA32-BA31 -> 0 | BE32: =SUM(BB32:BD32) -> 0 | BF32: =SUM(I32-BE32) -> 0 | BG32: =SUM(I32-BF32) -> 0
A33: =ELEC!C31 -> 44375 | B33: =B32 -> 109443 | C33: =B33-B32 -> 0 | D33: =C33/27 -> 0 | E33: =SUM((C33*$E$4)+(7500/'EDl log'!$A$37)) -> 250 | G33: =G32 -> 620750 | H33: =G33-G32 -> 0 | I33: =C33+H33 -> 0 | J33: =IF(I33>0,E33/I33,0) -> 0 | K33: ='Swimming Pool quality check '!H33 -> 6785 | L33: =K33-K32 -> 0 | M33: =M32 -> 457.44 | N33: =SUM(M33-M32) -> 0 | O33: =O32 -> 529.52 | P33: =SUM(O33-O32) -> 0 | Q33: =SUM(P33+N33) -> 0 | T33: =T32 -> 5172 | U33: =SUM(T33-T32) -> 0 | V33: =V32 -> 474 | W33: =+V33-V32 -> 0 | X33: =X32 -> 152207 | Y33: =SUM(X33-X32) -> 0 | Z33: =Z32 -> 98847 | AA33: =Z33-Z32 -> 0 | AB33: =AB32 -> 261 | AC33: =AC32 -> 731 | AD33: =AC33-AC32 -> 0 | AE33: =AE32 -> 229.86 | AF33: =AE33-AE32 -> 0 | AG33: =AG32 -> 2206.6 | AH33: =AG33-AG32 -> 0 | AI33: =AF33+AH33 -> 0 | AJ33: =+Z33-Z32 -> 0 | AK33: =SUM(Y33-L33) -> 0 | AL33: =SUM(AJ33-W33) -> 0 | AM33: ='General information '!D33 -> 0 | AN33: ='General information '!H33 -> 0 | AP33: ='General information '!J33 -> 0 | AR33: =A33 -> 44375 | AS33: =AS32 -> 0.9 | AT33: =AT32 -> 100 | AU33: =AU32 -> 1.1 | AV33: =AV32 -> 100 | AW33: 2.9 | AX33: =AX32 -> 57 | AY33: =AS33*AT33 -> 90 | AZ33: =AU33*AV33 -> 110 | BA33: =AW33*AX33 -> 165.3 | BB33: =AY33-AY32 -> 0 | BC33: =AZ33-AZ32 -> 0 | BD33: =BA33-BA32 -> 0 | BE33: =SUM(BB33:BD33) -> 0 | BF33: =SUM(I33-BE33) -> 0 | BG33: =SUM(I33-BF33) -> 0
A34: =ELEC!C32 -> 44376 | B34: =B33 -> 109443 | C34: =B34-B33 -> 0 | D34: =C34/27 -> 0 | E34: =SUM((C34*$E$4)+(7500/'EDl log'!$A$37)) -> 250 | G34: =G33 -> 620750 | H34: =G34-G33 -> 0 | I34: =C34+H34 -> 0 | J34: =IF(I34>0,E34/I34,0) -> 0 | K34: ='Swimming Pool quality check '!H34 -> 6785 | L34: =K34-K33 -> 0 | M34: =M33 -> 457.44 | N34: =SUM(M34-M33) -> 0 | O34: =O33 -> 529.52 | P34: =SUM(O34-O33) -> 0 | Q34: =SUM(P34+N34) -> 0 | T34: =T33 -> 5172 | U34: =SUM(T34-T33) -> 0 | V34: =V33 -> 474 | W34: =+V34-V33 -> 0 | X34: =X33 -> 152207 | Y34: =SUM(X34-X33) -> 0 | Z34: =Z33 -> 98847 | AA34: =Z34-Z33 -> 0 | AB34: =AB33 -> 261 | AC34: =AC33 -> 731 | AD34: =AC34-AC33 -> 0 | AE34: =AE33 -> 229.86 | AF34: =AE34-AE33 -> 0 | AG34: =AG33 -> 2206.6 | AH34: =AG34-AG33 -> 0 | AI34: =AF34+AH34 -> 0 | AJ34: =+Z34-Z33 -> 0 | AK34: =SUM(Y34-L34) -> 0 | AL34: =SUM(AJ34-W34) -> 0 | AM34: ='General information '!D34 -> 0 | AN34: ='General information '!H34 -> 0 | AP34: ='General information '!J34 -> 0 | AR34: =A34 -> 44376 | AS34: =AS33 -> 0.9 | AT34: =AT33 -> 100 | AU34: =AU33 -> 1.1 | AV34: =AV33 -> 100 | AW34: 2.9 | AX34: =AX33 -> 57 | AY34: =AS34*AT34 -> 90 | AZ34: =AU34*AV34 -> 110 | BA34: =AW34*AX34 -> 165.3 | BB34: =AY34-AY33 -> 0 | BC34: =AZ34-AZ33 -> 0 | BD34: =BA34-BA33 -> 0 | BE34: =SUM(BB34:BD34) -> 0 | BF34: =SUM(I34-BE34) -> 0 | BG34: =SUM(I34-BF34) -> 0
A35: =ELEC!C33 -> 44377 | B35: =B34 -> 109443 | C35: =B35-B34 -> 0 | D35: =C35/27 -> 0 | E35: =SUM((C35*$E$4)+(7500/'EDl log'!$A$37)) -> 250 | G35: =G34 -> 620750 | H35: =G35-G34 -> 0 | I35: =C35+H35 -> 0 | J35: =IF(I35>0,E35/I35,0) -> 0 | K35: ='Swimming Pool quality check '!H35 -> 6785 | L35: =K35-K34 -> 0 | M35: =M34 -> 457.44 | N35: =SUM(M35-M34) -> 0 | O35: =O34 -> 529.52 | P35: =SUM(O35-O34) -> 0 | Q35: =SUM(P35+N35) -> 0 | T35: =T34 -> 5172 | U35: =SUM(T35-T34) -> 0 | V35: =V34 -> 474 | W35: =+V35-V34 -> 0 | X35: =X34 -> 152207 | Y35: =SUM(X35-X34) -> 0 | Z35: =Z34 -> 98847 | AA35: =Z35-Z34 -> 0 | AB35: =AB34 -> 261 | AC35: =AC34 -> 731 | AD35: =AC35-AC34 -> 0 | AE35: =AE34 -> 229.86 | AF35: =AE35-AE34 -> 0 | AG35: =AG34 -> 2206.6 | AH35: =AG35-AG34 -> 0 | AI35: =AF35+AH35 -> 0 | AJ35: =+Z35-Z34 -> 0 | AK35: =SUM(Y35-L35) -> 0 | AL35: =SUM(AJ35-W35) -> 0 | AM35: ='General information '!D35 -> 0 | AN35: ='General information '!H35 -> 0 | AP35: ='General information '!J35 -> 0 | AR35: =A35 -> 44377 | AS35: =AS34 -> 0.9 | AT35: =AT34 -> 100 | AU35: =AU34 -> 1.1 | AV35: =AV34 -> 100 | AW35: 2.9 | AX35: =AX34 -> 57 | AY35: =AS35*AT35 -> 90 | AZ35: =AU35*AV35 -> 110 | BA35: =AW35*AX35 -> 165.3 | BB35: =AY35-AY34 -> 0 | BC35: =AZ35-AZ34 -> 0 | BD35: =BA35-BA34 -> 0 | BE35: =SUM(BB35:BD35) -> 0 | BF35: =SUM(I35-BE35) -> 0 | BG35: =SUM(I35-BF35) -> 0
C36: =SUM(C6:C35) -> 0 | D36: =SUM(D6:D35) -> 0 | F36: =SUM(F6:F35) -> 0 | H36: =SUM(H6:H35) -> 329 | I36: =SUM(I6:I35) -> 329 | L36: =SUM(L7:L35) -> 10 | Q36: =SUM(Q5:Q35) -> 0 | U36: =SUM(U6:U35) -> 1 | Y36: =SUM(Y6,Y33,Y31,Y29,Y27,Y25,Y23,Y21,Y19,Y17,Y15,Y13,Y11,Y9,Y7,Y34,Y35,#REF!) -> #REF! | AJ36: =SUM(AJ6:AJ35) -> 0 | AK36: =SUM(Y36-L36) -> #REF! | AL36: =SUM(AL6:AL35) -> 0
C37: =+C36*1.66 -> 0 | E37: =SUM(E6:E33) -> 7000 | F37: =SUM(F6:F35) -> 0 | H37: 7500 | I37: =SUM('General information '!G37/WATER!I36) -> 0 | O37: =SUM(Q36+I36) -> 329 | Z37: =SUM(Y36:AJ36) -> #REF! | AK37: =SUM(Y37-L37) -> 0
B38: =9*27 -> 243 | D38: =SUM(D6:D35) -> 0 | F38: =SUM(F6:F35) -> 0 | G38: =SUM(I36) -> 329 | H38: =SUM(H37+C37) -> 7500 | K38: =SUM(H38/G38) -> 22.796353 | AJ38: =SUM(C37-AK37) -> 0 | AM38: =SUM(AJ38/AO37) -> #DIV/0!

Sheet GEN
B1: GEN1 | C1: RUN HR | D1: Fuel Counter Index | E1: Cons /day | F1: Diesel L/H | H1: next service | I1: ALARM | J1: GEN2 | K1: RUN HR | L1: Fuel Counter Index | M1: Cons /day | N1: Diesel L/H | P1: next service | Q1: ALARM | R1: GEN3 | S1: RUN HR | T1: Fuel Counter Index | U1: Cons /day | V1: Diesel L/H | X1: next service | Y1: ALARM | Z1: RH total | AA1: Gen Con /day | AB1: Total Deisel Cons/day | AC1: H /L | AD1: TOAL KW GEN | AI1: fuel Consuption | AK1: AVG KW/h
A2: =ELEC!C3 -> 44347 | B2: =[3]GEN!B33 -> 10123 | C2: =[3]GEN!C33 -> 4 | D2: =[3]GEN!D33 -> 417630 | E2: =[3]GEN!E33 -> 367 | F2: =[3]GEN!F33 -> 91.75 | G2: =[3]GEN!G33 -> 0 | H2: =[3]GEN!H33 -> 10105 | I2: =[3]GEN!I33 -> oil change | ... AK2: =[3]GEN!AK33 -> 192.18749
A3: =ELEC!C4 -> 44348 | B3: 10129 | C3: =B3-B2 -> 6 | D3: 418031 | E3: =SUM(D3-D2) -> 401 | F3: =IF(C3>0,E3/C3,0) -> 66.833333 | G3: =[5]GEN!G32 -> 0 | H3: =H2 -> 10105 | I3: =IF(B3-H3<=0,"ok","oil change") -> oil change | J3: =J2 -> 10698 | K3: =J3-J2 -> 0 | L3: =L2 -> 357691 | M3: =SUM(L3-L2) -> 0 | N3: =IF(K3>0,M3/K3,0) -> 0 | O3: =[5]GEN!O32 -> 0 | P3: =P2 -> 10873 | Q3: =IF(J3-P3<=0,"ok","oil change") -> ok | R3: 12265 | S3: =R3-R2 -> 6 | T3: 369839 | U3: =V3*S3 -> 1500 | V3: 250 | W3: =[5]GEN!W32 -> 0 | X3: =X2 -> 12390 | Y3: =IF(R3-X3<=0,"ok","oil change") -> ok | Z3: =C3+K3+S3 -> 12 | AA3: =U3+M3+E3 -> 1901 | AB3: =V3+N3+F3 -> 316.83333 | AC3: =IF(Z3>0,AA3/Z3,0) -> 158.41667 | AD3: =ELEC!Q4 -> 9515 | AE3: =SUM(AD3/Z3) -> 792.91667 | AF3: =SUM(AE3/1600) -> 0.49557292 | AG3: =SUM(360*AF3) -> 178.40625 | AH3: =SUM(AC3-AG3) -> -19.989583 | AI3: =AD3*AJ3 -> 2449.0084 | AJ3: =305/1185 -> 0.25738397 | AK3: =AI3/Z3 -> 204.08404
A4: =ELEC!C5 -> 44349 | B4: 10136 | C4: =B4-B3 -> 7 | D4: 419094 | E4: =SUM(D4-D3) -> 1063 | F4: =IF(C4>0,E4/C4,0) -> 151.85714 | H4: =H3 -> 10105 | I4: =IF(B4-H4<=0,"ok","oil change") -> oil change | J4: =J3 -> 10698 | K4: =J4-J3 -> 0 | L4: =L3 -> 357691 | M4: =SUM(L4-L3) -> 0 | N4: =IF(K4>0,M4/K4,0) -> 0 | P4: =P3 -> 10873 | Q4: =IF(J4-P4<=0,"ok","oil change") -> ok | R4: 12271 | S4: =R4-R3 -> 6 | T4: 369840 | U4: =V4*S4 -> 1500 | V4: 250 | X4: =X3 -> 12390 | Y4: =IF(R4-X4<=0,"ok","oil change") -> ok | Z4: =C4+K4+S4 -> 13 | AA4: =U4+M4+E4 -> 2563 | AB4: =V4+N4+F4 -> 401.85714 | AC4: =IF(Z4>0,AA4/Z4,0) -> 197.15385 | AD4: =ELEC!Q5 -> 10881 | AE4: =SUM(AD4/Z4) -> 837 | AF4: =SUM(AE4/1600) -> 0.523125 | AG4: =SUM(360*AF4) -> 188.325 | AH4: =SUM(AC4-AG4) -> 8.8288462 | AI4: =AD4*AJ4 -> 2800.5949 | AJ4: =305/1185 -> 0.25738397 | AK4: =AI4/Z4 -> 215.43038
A5: =ELEC!C6 -> 44350 | B5: 10149 | C5: =B5-B4 -> 13 | D5: 420302.9 | E5: =SUM(D5-D4) -> 1208.9 | F5: =IF(C5>0,E5/C5,0) -> 92.992308 | H5: =H4 -> 10105 | I5: =IF(B5-H5<=0,"ok","oil change") -> oil change | J5: =J4 -> 10698 | K5: =J5-J4 -> 0 | L5: =L4 -> 357691 | M5: =SUM(L5-L4) -> 0 | N5: =IF(K5>0,M5/K5,0) -> 0 | P5: =P4 -> 10873 | Q5: =IF(J5-P5<=0,"ok","oil change") -> ok | R5: 12278 | S5: =R5-R4 -> 7 | T5: 371590 | U5: =V5*S5 -> 1750 | V5: 250 | X5: =X4 -> 12390 | Y5: =IF(R5-X5<=0,"ok","oil change") -> ok | Z5: =C5+K5+S5 -> 20 | AA5: =U5+M5+E5 -> 2958.9 | AB5: =V5+N5+F5 -> 342.99231 | AC5: =IF(Z5>0,AA5/Z5,0) -> 147.945 | AD5: =ELEC!Q6 -> 14618 | AE5: =SUM(AD5/Z5) -> 730.9 | AF5: =SUM(AE5/1600) -> 0.4568125 | AG5: =SUM(320*AF5) -> 146.18 | AH5: =SUM(AC5-AG5) -> 1.765 | AI5: =AD5*AJ5 -> 3762.4388 | AJ5: =305/1185 -> 0.25738397 | AK5: =AI5/Z5 -> 188.12194
A6: =ELEC!C7 -> 44351 | B6: 10157 | C6: =B6-B5 -> 8 | D6: 421121 | E6: =SUM(D6-D5) -> 818.1 | F6: =IF(C6>0,E6/C6,0) -> 102.2625 | H6: =H5 -> 10105 | I6: =IF(B6-H6<=0,"ok","oil change") -> oil change | J6: =J5 -> 10698 | K6: =J6-J5 -> 0 | L6: =L5 -> 357691 | M6: =SUM(L6-L5) -> 0 | N6: =IF(K6>0,M6/K6,0) -> 0 | P6: =P5 -> 10873 | Q6: =IF(J6-P6<=0,"ok","oil change") -> ok | R6: 12290 | S6: =R6-R5 -> 12 | T6: 374590 | U6: =V6*S6 -> 3000 | V6: 250 | X6: =X5 -> 12390 | Y6: =IF(R6-X6<=0,"ok","oil change") -> ok | Z6: =C6+K6+S6 -> 20 | AA6: =U6+M6+E6 -> 3818.1 | AB6: =V6+N6+F6 -> 352.2625 | AC6: =IF(Z6>0,AA6/Z6,0) -> 190.905 | AD6: =ELEC!Q7 -> 14058 | AE6: =SUM(AD6/Z6) -> 702.9 | AF6: =SUM(AE6/1600) -> 0.4393125 | AG6: =SUM(320*AF6) -> 140.58 | AH6: =SUM(AC6-AG6) -> 50.325 | AI6: =AD6*AJ6 -> 3618.3038 | AJ6: =305/1185 -> 0.25738397 | AK6: =AI6/Z6 -> 180.91519
A7: =ELEC!C8 -> 44352 | B7: 10167 | C7: =B7-B6 -> 10 | D7: 422593 | E7: =SUM(D7-D6) -> 1472 | F7: =IF(C7>0,E7/C7,0) -> 147.2 | H7: 10310 | I7: =IF(B7-H7<=0,"ok","oil change") -> ok | J7: =J6 -> 10698 | K7: =J7-J6 -> 0 | L7: =L6 -> 357691 | M7: =SUM(L7-L6) -> 0 | N7: =IF(K7>0,M7/K7,0) -> 0 | P7: =P6 -> 10873 | Q7: =IF(J7-P7<=0,"ok","oil change") -> ok | R7: 12296 | S7: =R7-R6 -> 6 | T7: =T6 -> 374590 | U7: =V7*S7 -> 1500 | V7: 250 | X7: =X6 -> 12390 | Y7: =IF(R7-X7<=0,"ok","oil change") -> ok | Z7: =C7+K7+S7 -> 16 | AA7: =U7+M7+E7 -> 2972 | AB7: =V7+N7+F7 -> 397.2 | AC7: =IF(Z7>0,AA7/Z7,0) -> 185.75 | AD7: =ELEC!Q8 -> 11810 | AE7: =SUM(AD7/Z7) -> 738.125 | AF7: =SUM(AE7/1600) -> 0.46132812 | AG7: =SUM(AF7/1600) -> 0.00028833008 | AH7: =SUM(AC7-AG7) -> 185.74971 | AI7: =AD7*AJ7 -> 3039.7046 | AJ7: =305/1185 -> 0.25738397 | AK7: =AI7/Z7 -> 189.98154
A8: =ELEC!C9 -> 44353 | B8: 10176 | C8: =B8-B7 -> 9 | D8: 423923 | E8: =SUM(D8-D7) -> 1330 | F8: =IF(C8>0,E8/C8,0) -> 147.77778 | H8: =H7 -> 10310 | I8: =IF(B8-H8<=0,"ok","oil change") -> ok | J8: =J7 -> 10698 | K8: =J8-J7 -> 0 | L8: =L7 -> 357691 | M8: =SUM(L8-L7) -> 0 | N8: =IF(K8>0,M8/K8,0) -> 0 | P8: =P7 -> 10873 | Q8: =IF(J8-P8<=0,"ok","oil change") -> ok | R8: 12306 | S8: =R8-R7 -> 10 | T8: 377090 | U8: =V8*S8 -> 2500 | V8: 250 | X8: =X7 -> 12390 | Y8: =IF(R8-X8<=0,"ok","oil change") -> ok | Z8: =C8+K8+S8 -> 19 | AA8: =U8+M8+E8 -> 3830 | AB8: =V8+N8+F8 -> 397.77778 | AC8: =IF(Z8>0,AA8/Z8,0) -> 201.57895 | AD8: =ELEC!Q9 -> 10976 | AE8: =SUM(AD8/Z8) -> 577.68421 | AF8: =SUM(AE8/1600) -> 0.36105263 | AG8: =SUM(320*AF8) -> 115.53684 | AH8: =SUM(AC8-AG8) -> 86.042105 | AI8: =AD8*AJ8 -> 2825.0464 | AJ8: =305/1185 -> 0.25738397 | AK8: =AI8/Z8 -> 148.68665
A9: =ELEC!C10 -> 44354 | B9: 10182 | C9: =B9-B8 -> 6 | D9: 424675 | E9: =SUM(D9-D8) -> 752 | F9: =IF(C9>0,E9/C9,0) -> 125.33333 | H9: =H8 -> 10310 | I9: =IF(B9-H9<=0,"ok","oil change") -> ok | J9: =J8 -> 10698 | K9: =J9-J8 -> 0 | L9: =L8 -> 357691 | M9: =SUM(L9-L8) -> 0 | N9: =IF(K9>0,M9/K9,0) -> 0 | P9: =P8 -> 10873 | Q9: =IF(J9-P9<=0,"ok","oil change") -> ok | R9: 12320 | S9: =R9-R8 -> 14 | T9: 380590 | U9: =V9*S9 -> 3500 | V9: 250 | X9: =X8 -> 12390 | Y9: =IF(R9-X9<=0,"ok","oil change") -> ok | Z9: =C9+K9+S9 -> 20 | AA9: =U9+M9+E9 -> 4252 | AB9: =V9+N9+F9 -> 375.33333 | AC9: =IF(Z9>0,AA9/Z9,0) -> 212.6 | AD9: =ELEC!Q10 -> 15124 | AE9: =SUM(AD9/Z9) -> 756.2 | AF9: =SUM(AE9/1600) -> 0.472625 | AG9: =SUM(320*AF9) -> 151.24 | AH9: =SUM(AC9-AG9) -> 61.36 | AI9: =AD9*AJ9 -> 3892.6751 | AJ9: =305/1185 -> 0.25738397 | AK9: =AI9/Z9 -> 194.63376
A10: =ELEC!C11 -> 44355 | B10: =B9 -> 10182 | C10: =B10-B9 -> 0 | D10: =D9 -> 424675 | E10: =SUM(D10-D9) -> 0 | F10: =IF(C10>0,E10/C10,0) -> 0 | H10: =H9 -> 10310 | I10: =IF(B10-H10<=0,"ok","oil change") -> ok | J10: =J9 -> 10698 | K10: =J10-J9 -> 0 | L10: =L9 -> 357691 | M10: =SUM(L10-L9) -> 0 | N10: =IF(K10>0,M10/K10,0) -> 0 | P10: =P9 -> 10873 | Q10: =IF(J10-P10<=0,"ok","oil change") -> ok | R10: 12335 | S10: =R10-R9 -> 15 | T10: =T9 -> 380590 | U10: =V10*S10 -> 3750 | V10: 250 | X10: =X9 -> 12390 | Y10: =IF(R10-X10<=0,"ok","oil change") -> ok | Z10: =C10+K10+S10 -> 15 | AA10: =U10+M10+E10 -> 3750 | AB10: =V10+N10+F10 -> 250 | AC10: =IF(Z10>0,AA10/Z10,0) -> 250 | AD10: =ELEC!Q11 -> 10331 | AE10: =SUM(AD10/Z10) -> 688.73333 | AF10: =SUM(AE10/1600) -> 0.43045833 | AG10: =SUM(320*AF10) -> 137.74667 | AH10: =SUM(AC10-AG10) -> 112.25333 | AI10: =AD10*AJ10 -> 2659.0338 | AJ10: =305/1185 -> 0.25738397 | AK10: =AI10/Z10 -> 177.26892
A11: =ELEC!C12 -> 44356 | B11: 10189 | C11: =B11-B10 -> 7 | D11: 425366.8 | E11: =SUM(D11-D10) -> 691.8 | F11: =IF(C11>0,E11/C11,0) -> 98.828571 | H11: =H10 -> 10310 | I11: =IF(B11-H11<=0,"ok","oil change") -> ok | J11: =J10 -> 10698 | K11: =J11-J10 -> 0 | L11: =L10 -> 357691 | M11: =SUM(L11-L10) -> 0 | N11: =IF(K11>0,M11/K11,0) -> 0 | P11: =P10 -> 10873 | Q11: =IF(J11-P11<=0,"ok","oil change") -> ok | R11: 12349 | S11: =R11-R10 -> 14 | T11: 384090 | U11: =V11*S11 -> 3500 | V11: 250 | X11: =X10 -> 12390 | Y11: =IF(R11-X11<=0,"ok","oil change") -> ok | Z11: =C11+K11+S11 -> 21 | AA11: =U11+M11+E11 -> 4191.8 | AB11: =V11+N11+F11 -> 348.82857 | AC11: =IF(Z11>0,AA11/Z11,0) -> 199.60952 | AD11: =ELEC!Q12 -> 13240 | AE11: =SUM(AD11/Z11) -> 630.47619 | AF11: =SUM(AE11/1600) -> 0.39404762 | AG11: =SUM(320*AF11) -> 126.09524 | AH11: =SUM(AC11-AG11) -> 73.514286 | AI11: =AD11*AJ11 -> 3407.7637 | AJ11: =305/1185 -> 0.25738397 | AK11: =AI11/Z11 -> 162.27446
A12: =ELEC!C13 -> 44357 | B12: 10204 | C12: =B12-B11 -> 15 | D12: 426571 | E12: =SUM(D12-D11) -> 1204.2 | F12: =IF(C12>0,E12/C12,0) -> 80.28 | H12: =H11 -> 10310 | I12: =IF(B12-H12<=0,"ok","oil change") -> ok | J12: =J11 -> 10698 | K12: =J12-J11 -> 0 | L12: =L11 -> 357691 | M12: =SUM(L12-L11) -> 0 | N12: =IF(K12>0,M12/K12,0) -> 0 | P12: =P11 -> 10873 | Q12: =IF(J12-P12<=0,"ok","oil change") -> ok | R12: 12352 | S12: =R12-R11 -> 3 | T12: 384840 | U12: =V12*S12 -> 750 | V12: 250 | X12: =X11 -> 12390 | Y12: =IF(R12-X12<=0,"ok","oil change") -> ok | Z12: =C12+K12+S12 -> 18 | AA12: =U12+M12+E12 -> 1954.2 | AB12: =V12+N12+F12 -> 330.28 | AC12: =IF(Z12>0,AA12/Z12,0) -> 108.56667 | AD12: =ELEC!Q13 -> 13897 | AE12: =SUM(AD12/Z12) -> 772.05556 | AF12: =SUM(AE12/1600) -> 0.48253472 | AG12: =SUM(320*AF12) -> 154.41111 | AH12: =SUM(AC12-AG12) -> -45.844444 | AI12: =AD12*AJ12 -> 3576.865 | AJ12: =305/1185 -> 0.25738397 | AK12: =AI12/Z12 -> 198.71472
A13: =ELEC!C14 -> 44358 | B13: 10214 | C13: =B13-B12 -> 10 | D13: 428008 | E13: =SUM(D13-D12) -> 1437 | F13: =IF(C13>0,E13/C13,0) -> 143.7 | H13: =H12 -> 10310 | I13: =IF(B13-H13<=0,"ok","oil change") -> ok | J13: =J12 -> 10698 | K13: =J13-J12 -> 0 | L13: =L12 -> 357691 | M13: =SUM(L13-L12) -> 0 | N13: =IF(K13>0,M13/K13,0) -> 0 | P13: =P12 -> 10873 | Q13: =IF(J13-P13<=0,"ok","oil change") -> ok | R13: 12362 | S13: =R13-R12 -> 10 | T13: 369841 | U13: =V13*S13 -> 2500 | V13: 250 | X13: =X12 -> 12390 | Y13: =IF(R13-X13<=0,"ok","oil change") -> ok | Z13: =C13+K13+S13 -> 20 | AA13: =U13+M13+E13 -> 3937 | AB13: =V13+N13+F13 -> 393.7 | AC13: =IF(Z13>0,AA13/Z13,0) -> 196.85 | AD13: =ELEC!Q14 -> 14090 | AE13: =SUM(AD13/Z13) -> 704.5 | AF13: =SUM(AE13/1600) -> 0.4403125 | AG13: =SUM(320*AF13) -> 140.9 | AH13: =SUM(AC13-AG13) -> 55.95 | AI13: =AD13*AJ13 -> 3626.5401 | AJ13: =305/1185 -> 0.25738397 | AK13: =AI13/Z13 -> 181.327
A14: =ELEC!C15 -> 44359 | B14: 10221 | C14: =B14-B13 -> 7 | D14: 429020 | E14: =SUM(D14-D13) -> 1012 | F14: =IF(C14>0,E14/C14,0) -> 144.57143 | H14: =H13 -> 10310 | I14: =IF(B14-H14<=0,"ok","oil change") -> ok | J14: =J13 -> 10698 | K14: =J14-J13 -> 0 | L14: =L13 -> 357691 | M14: =SUM(L14-L13) -> 0 | N14: =IF(K14>0,M14/K14,0) -> 0 | P14: =P13 -> 10873 | Q14: =IF(J14-P14<=0,"ok","oil change") -> ok | R14: 12377 | S14: =R14-R13 -> 15 | T14: 373591 | U14: =V14*S14 -> 3750 | V14: 250 | X14: =X13 -> 12390 | Y14: =IF(R14-X14<=0,"ok","oil change") -> ok | Z14: =C14+K14+S14 -> 22 | AA14: =U14+M14+E14 -> 4762 | AB14: =V14+N14+F14 -> 394.57143 | AC14: =IF(Z14>0,AA14/Z14,0) -> 216.45455 | AD14: =ELEC!Q15 -> 11450 | AE14: =SUM(AD14/Z14) -> 520.45455 | AF14: =SUM(AE14/1600) -> 0.32528409 | AG14: =SUM(320*AF14) -> 104.09091 | AH14: =SUM(AC14-AG14) -> 112.36364 | AI14: =AD14*AJ14 -> 2947.0464 | AJ14: =305/1185 -> 0.25738397 | AK14: =AI14/Z14 -> 133.95666
A15: =ELEC!C16 -> 44360 | B15: 10237 | C15: =B15-B14 -> 16 | D15: 432006 | E15: =SUM(D15-D14) -> 2986 | F15: =IF(C15>0,E15/C15,0) -> 186.625 | H15: =H14 -> 10310 | I15: =IF(B15-H15<=0,"ok","oil change") -> ok | J15: =J14 -> 10698 | K15: =J15-J14 -> 0 | L15: =L14 -> 357691 | M15: =SUM(L15-L14) -> 0 | N15: =IF(K15>0,M15/K15,0) -> 0 | P15: =P14 -> 10873 | Q15: =IF(J15-P15<=0,"ok","oil change") -> ok | R15: 12378 | S15: =R15-R14 -> 1 | T15: 369842 | U15: =V15*S15 -> 250 | V15: 250 | X15: =X14 -> 12390 | Y15: =IF(R15-X15<=0,"ok","oil change") -> ok | Z15: =C15+K15+S15 -> 17 | AA15: =U15+M15+E15 -> 3236 | AB15: =V15+N15+F15 -> 436.625 | AC15: =IF(Z15>0,AA15/Z15,0) -> 190.35294 | AD15: =ELEC!Q16 -> 13268 | AE15: =SUM(AD15/Z15) -> 780.47059 | AF15: =SUM(AE15/1600) -> 0.48779412 | AG15: =SUM(320*AF15) -> 156.09412 | AH15: =SUM(AC15-AG15) -> 34.258824 | AI15: =AD15*AJ15 -> 3414.9705 | AJ15: =305/1185 -> 0.25738397 | AK15: =AI15/Z15 -> 200.88062
A16: =ELEC!C17 -> 44361 | B16: 10237 | C16: =B16-B15 -> 0 | D16: =D15 -> 432006 | E16: =SUM(D16-D15) -> 0 | F16: =IF(C16>0,E16/C16,0) -> 0 | H16: =H15 -> 10310 | I16: =IF(B16-H16<=0,"ok","oil change") -> ok | J16: =J15 -> 10698 | K16: =J16-J15 -> 0 | L16: =L15 -> 357691 | M16: =SUM(L16-L15) -> 0 | N16: =IF(K16>0,M16/K16,0) -> 0 | P16: =P15 -> 10873 | Q16: =IF(J16-P16<=0,"ok","oil change") -> ok | R16: 12392 | S16: =R16-R15 -> 14 | T16: 373342 | U16: =V16*S16 -> 3500 | V16: 250 | X16: =X15 -> 12390 | Y16: =IF(R16-X16<=0,"ok","oil change") -> oil change | Z16: =C16+K16+S16 -> 14 | AA16: =U16+M16+E16 -> 3500 | AB16: =V16+N16+F16 -> 250 | AC16: =IF(Z16>0,AA16/Z16,0) -> 250 | AD16: =ELEC!Q17 -> 8594 | AE16: =SUM(AD16/Z16) -> 613.85714 | AF16: =SUM(AE16/1600) -> 0.38366071 | AG16: =SUM(320*AF16) -> 122.77143 | AH16: =SUM(AC16-AG16) -> 127.22857 | AI16: =AD16*AJ16 -> 2211.9578 | AJ16: =305/1185 -> 0.25738397 | AK16: =AI16/Z16 -> 157.99699
A17: =ELEC!C18 -> 44362 | B17: 10243 | C17: =B17-B16 -> 6 | D17: 433281 | E17: =SUM(D17-D16) -> 1275 | F17: =IF(C17>0,E17/C17,0) -> 212.5 | H17: =H16 -> 10310 | I17: =IF(B17-H17<=0,"ok","oil change") -> ok | J17: =J16 -> 10698 | K17: =J17-J16 -> 0 | L17: =L16 -> 357691 | M17: =SUM(L17-L16) -> 0 | N17: =IF(K17>0,M17/K17,0) -> 0 | P17: =P16 -> 10873 | Q17: =IF(J17-P17<=0,"ok","oil change") -> ok | R17: 12405 | S17: =R17-R16 -> 13 | T17: 369842 | U17: =V17*S17 -> 3250 | V17: 250 | X17: =X16 -> 12390 | Y17: =IF(R17-X17<=0,"ok","oil change") -> oil change | Z17: =C17+K17+S17 -> 19 | AA17: =U17+M17+E17 -> 4525 | AB17: =V17+N17+F17 -> 462.5 | AC17: =IF(Z17>0,AA17/Z17,0) -> 238.15789 | AD17: =ELEC!Q18 -> 12444 | AE17: =SUM(AD17/Z17) -> 654.94737 | AF17: =SUM(AE17/1600) -> 0.40934211 | AG17: =SUM(320*AF17) -> 130.98947 | AH17: =SUM(AC17-AG17) -> 107.16842 | AI17: =AD17*AJ17 -> 3202.8861 | AJ17: =305/1185 -> 0.25738397 | AK17: =AI17/Z17 -> 168.57295
A18: =ELEC!C19 -> 44363 | B18: 10256 | C18: =B18-B17 -> 13 | D18: 435767 | E18: =SUM(D18-D17) -> 2486 | F18: =IF(C18>0,E18/C18,0) -> 191.23077 | H18: =H17 -> 10310 | I18: =IF(B18-H18<=0,"ok","oil change") -> ok | J18: =J17 -> 10698 | K18: =J18-J17 -> 0 | L18: =L17 -> 357691 | M18: =SUM(L18-L17) -> 0 | N18: =IF(K18>0,M18/K18,0) -> 0 | P18: =P17 -> 10873 | Q18: =IF(J18-P14<=0,"ok","oil change") -> ok | R18: 12409 | S18: =R18-R17 -> 4 | T18: 370842 | U18: =V18*S18 -> 1000 | V18: 250 | X18: 12540 | Y18: =IF(R18-X18<=0,"ok","oil change") -> ok | Z18: =C18+K18+S18 -> 17 | AA18: =U18+M18+E18 -> 3486 | AB18: =V18+N18+F18 -> 441.23077 | AC18: =IF(Z18>0,AA18/Z18,0) -> 205.05882 | AD18: =ELEC!Q19 -> 13275 | AE18: =SUM(AD18/Z18) -> 780.88235 | AF18: =SUM(AE18/1600) -> 0.48805147 | AG18: =SUM(320*AF18) -> 156.17647 | AH18: =SUM(AC18-AG18) -> 48.882353 | AI18: =AD18*AJ18 -> 3416.7722 | AJ18: =305/1185 -> 0.25738397 | AK18: =AI18/Z18 -> 200.9866
A19: =ELEC!C20 -> 44364 | B19: 10269 | C19: =B19-B18 -> 13 | D19: 438387 | E19: =SUM(D19-D18) -> 2620 | F19: =IF(C19>0,E19/C19,0) -> 201.53846 | H19: =H18 -> 10310 | I19: =IF(B19-H19<=0,"ok","oil change") -> ok | J19: =J18 -> 10698 | K19: =J19-J18 -> 0 | L19: =L18 -> 357691 | M19: =SUM(L19-L18) -> 0 | N19: =IF(K19>0,M19/K19,0) -> 0 | P19: =P18 -> 10873 | Q19: =IF(J19-P19<=0,"ok","oil change") -> ok | R19: 12417 | S19: =R19-R18 -> 8 | T19: 372842 | U19: =V19*S19 -> 2000 | V19: 250 | X19: =X18 -> 12540 | Y19: =IF(R19-X19<=0,"ok","oil change") -> ok | Z19: =C19+K19+S19 -> 21 | AA19: =U19+M19+E19 -> 4620 | AB19: =V19+N19+F19 -> 451.53846 | AC19: =IF(Z19>0,AA19/Z19,0) -> 220 | AD19: =ELEC!Q20 -> 10077 | AE19: =SUM(AD19/Z19) -> 479.85714 | AF19: =SUM(AE19/1600) -> 0.29991071 | AG19: =SUM(320*AF19) -> 95.971429 | AH19: =SUM(AC19-AG19) -> 124.02857 | AI19: =AD19*AJ19 -> 2593.6582 | AJ19: =305/1185 -> 0.25738397 | AK19: =AI19/Z19 -> 123.50753
A20: =ELEC!C21 -> 44365 | B20: =B19 -> 10269 | C20: =B20-B19 -> 0 | D20: =D19 -> 438387 | E20: =SUM(D20-D19) -> 0 | F20: =IF(C20>0,E20/C20,0) -> 0 | H20: =H19 -> 10310 | I20: =IF(B20-H20<=0,"ok","oil change") -> ok | J20: =J19 -> 10698 | K20: =J20-J19 -> 0 | L20: =L19 -> 357691 | M20: =SUM(L20-L19) -> 0 | N20: =IF(K20>0,M20/K20,0) -> 0 | P20: =P19 -> 10873 | Q20: =IF(J20-P20<=0,"ok","oil change") -> ok | R20: =R19 -> 12417 | S20: =R20-R19 -> 0 | T20: =T19 -> 372842 | U20: =V20*S20 -> 0 | V20: 250 | X20: =X19 -> 12540 | Y20: =IF(R20-X20<=0,"ok","oil change") -> ok | Z20: =C20+K20+S20 -> 0 | AA20: =U20+M20+E20 -> 0 | AB20: =V20+N20+F20 -> 250 | AC20: =IF(Z20>0,AA20/Z20,0) -> 0 | AD20: =ELEC!Q21 -> 0 | AE20: =SUM(AD20/Z20) -> #DIV/0! | AF20: =SUM(AE20/1600) -> #DIV/0! | AG20: =SUM(320*AF20) -> #DIV/0! | AH20: =SUM(AC20-AG20) -> #DIV/0! | AI20: =AD20*AJ20 -> 0 | AJ20: =305/1185 -> 0.25738397 | AK20: =AI20/Z20 -> #DIV/0!
A21: =ELEC!C22 -> 44366 | B21: =B20 -> 10269 | C21: =B21-B20 -> 0 | D21: =D20 -> 438387 | E21: =SUM(D21-D20) -> 0 | F21: =IF(C21>0,E21/C21,0) -> 0 | H21: =H20 -> 10310 | I21: =IF(B21-H21<=0,"ok","oil change") -> ok | J21: =J20 -> 10698 | K21: =J21-J20 -> 0 | L21: =L20 -> 357691 | M21: =SUM(L21-L20) -> 0 | N21: =IF(K21>0,M21/K21,0) -> 0 | P21: =P20 -> 10873 | Q21: =IF(J21-P21<=0,"ok","oil change") -> ok | R21: =R20 -> 12417 | S21: =R21-R20 -> 0 | T21: =T20 -> 372842 | U21: =V21*S21 -> 0 | V21: 250 | X21: =X20 -> 12540 | Y21: =Y20 -> ok | Z21: =C21+K21+S21 -> 0 | AA21: =U21+M21+E21 -> 0 | AB21: =V21+N21+F21 -> 250 | AC21: =IF(Z21>0,AA21/Z21,0) -> 0 | AD21: =ELEC!Q22 -> 0 | AE21: =SUM(AD21/Z21) -> #DIV/0! | AF21: =SUM(AE21/1600) -> #DIV/0! | AG21: =SUM(320*AF21) -> #DIV/0! | AH21: =SUM(AC21-AG21) -> #DIV/0! | AI21: =AD21*AJ21 -> 0 | AJ21: =305/1185 -> 0.25738397 | AK21: =AI21/Z21 -> #DIV/0!
A22: =ELEC!C23 -> 44367 | B22: =B21 -> 10269 | C22: =B22-B21 -> 0 | D22: =D21 -> 438387 | E22: =150*C22 -> 0 | F22: =IF(C22>0,E22/C22,0) -> 0 | H22: =H21 -> 10310 | I22: =IF(B22-H22<=0,"ok","oil change") -> ok | J22: =J21 -> 10698 | K22: =J22-J21 -> 0 | L22: =L21 -> 357691 | M22: =SUM(L22-L21) -> 0 | N22: =IF(K22>0,M22/K22,0) -> 0 | P22: =P21 -> 10873 | Q22: =IF(J22-P22<=0,"ok","oil change") -> ok | R22: =R21 -> 12417 | S22: =R22-R21 -> 0 | T22: =T21 -> 372842 | U22: =V22*S22 -> 0 | V22: 250 | X22: =X21 -> 12540 | Y22: =IF(R22-X22<=0,"ok","oil change") -> ok | Z22: =C22+K22+S22 -> 0 | AA22: =U22+M22+E22 -> 0 | AB22: =V22+N22+F22 -> 250 | AC22: =IF(Z22>0,AA22/Z22,0) -> 0 | AD22: =ELEC!Q23 -> 0 | AE22: =SUM(AD22/Z22) -> #DIV/0! | AF22: =SUM(AE22/1600) -> #DIV/0! | AG22: =SUM(320*AF22) -> #DIV/0! | AH22: =SUM(AC22-AG22) -> #DIV/0! | AI22: =AD22*AJ22 -> 0 | AJ22: =305/1185 -> 0.25738397 | AK22: =AI22/Z22 -> #DIV/0!
A23: =ELEC!C24 -> 44368 | B23: =B22 -> 10269 | C23: =B23-B22 -> 0 | D23: =D22 -> 438387 | E23: =150*C23 -> 0 | F23: =IF(C23>0,E23/C23,0) -> 0 | H23: =H22 -> 10310 | I23: =IF(B23-H23<=0,"ok","oil change") -> ok | J23: =J22 -> 10698 | K23: =J23-J22 -> 0 | L23: =L22 -> 357691 | M23: =SUM(L23-L22) -> 0 | N23: =IF(K23>0,M23/K23,0) -> 0 | P23: =P22 -> 10873 | Q23: =IF(J23-P23<=0,"ok","oil change") -> ok | R23: =R22 -> 12417 | S23: =R23-R22 -> 0 | T23: =T22 -> 372842 | U23: =V23*S23 -> 0 | V23: 250 | X23: =X22 -> 12540 | Y23: =IF(R23-X23<=0,"ok","oil change") -> ok | Z23: =C23+K23+S23 -> 0 | AA23: =U23+M23+E23 -> 0 | AB23: =V23+N23+F23 -> 250 | AC23: =IF(Z23>0,AA23/Z23,0) -> 0 | AD23: =ELEC!Q24 -> 0 | AE23: =SUM(AD23/Z23) -> #DIV/0! | AF23: =SUM(AE23/1600) -> #DIV/0! | AG23: =SUM(320*AF23) -> #DIV/0! | AH23: =SUM(AC23-AG23) -> #DIV/0! | AI23: =AD23*AJ23 -> 0 | AJ23: =305/1185 -> 0.25738397 | AK23: =AI23/Z23 -> #DIV/0!
A24: =ELEC!C25 -> 44369 | B24: =B23 -> 10269 | C24: =B24-B23 -> 0 | D24: =D23 -> 438387 | E24: =SUM(D24-D23) -> 0 | F24: =IF(C24>0,E24/C24,0) -> 0 | H24: =H23 -> 10310 | I24: =IF(B24-H24<=0,"ok","oil change") -> ok | J24: =J23 -> 10698 | K24: =J24-J23 -> 0 | L24: =L23 -> 357691 | M24: =SUM(L24-L23) -> 0 | N24: =IF(K24>0,M24/K24,0) -> 0 | P24: =P23 -> 10873 | Q24: =IF(J24-P24<=0,"ok","oil change") -> ok | R24: =R23 -> 12417 | S24: =R24-R23 -> 0 | T24: =T23 -> 372842 | U24: =V24*S24 -> 0 | V24: 250 | X24: =X23 -> 12540 | Y24: =IF(R24-X24<=0,"ok","oil change") -> ok | Z24: =C24+K24+S24 -> 0 | AA24: =U24+M24+E24 -> 0 | AB24: =V24+N24+F24 -> 250 | AC24: =IF(Z24>0,AA24/Z24,0) -> 0 | AD24: =ELEC!Q25 -> 0 | AE24: =SUM(AD24/Z24) -> #DIV/0! | AF24: =SUM(AE24/1600) -> #DIV/0! | AG24: =SUM(320*AF24) -> #DIV/0! | AH24: =SUM(AC24-AG24) -> #DIV/0! | AI24: =AD24*AJ24 -> 0 | AJ24: =305/1185 -> 0.25738397 | AK24: =AI24/Z24 -> #DIV/0!
A25: =ELEC!C26 -> 44370 | B25: =B24 -> 10269 | C25: =B25-B24 -> 0 | D25: =D24 -> 438387 | E25: =SUM(D25-D24) -> 0 | F25: =IF(C25>0,E25/C25,0) -> 0 | H25: =H24 -> 10310 | I25: =IF(B25-H25<=0,"ok","oil change") -> ok | J25: =J24 -> 10698 | K25: =J25-J24 -> 0 | L25: =L24 -> 357691 | M25: =SUM(L25-L24) -> 0 | N25: =IF(K25>0,M25/K25,0) -> 0 | P25: =P24 -> 10873 | Q25: =IF(J25-P25<=0,"ok","oil change") -> ok | R25: =R24 -> 12417 | S25: =R25-R24 -> 0 | T25: =T24 -> 372842 | U25: =V25*S25 -> 0 | V25: 250 | X25: =X24 -> 12540 | Y25: =IF(R25-X25<=0,"ok","oil change") -> ok | Z25: =C25+K25+S25 -> 0 | AA25: =U25+M25+E25 -> 0 | AB25: =V25+N25+F25 -> 250 | AC25: =IF(Z25>0,AA25/Z25,0) -> 0 | AD25: =ELEC!Q26 -> 0 | AE25: =SUM(AD25/Z25) -> #DIV/0! | AF25: =SUM(AE25/1600) -> #DIV/0! | AG25: =SUM(320*AF25) -> #DIV/0! | AH25: =SUM(AC25-AG25) -> #DIV/0! | AI25: =AD25*AJ25 -> 0 | AJ25: =305/1185 -> 0.25738397 | AK25: =AI25/Z25 -> #DIV/0!
A26: =ELEC!C27 -> 44371 | B26: =B25 -> 10269 | C26: =B26-B25 -> 0 | D26: =D25 -> 438387 | E26: =SUM(D26-D25) -> 0 | F26: =IF(C26>0,E26/C26,0) -> 0 | H26: =H25 -> 10310 | I26: =IF(B26-H26<=0,"ok","oil change") -> ok | J26: =J25 -> 10698 | K26: =J26-J25 -> 0 | L26: =L25 -> 357691 | M26: =SUM(L26-L25) -> 0 | N26: =IF(K26>0,M26/K26,0) -> 0 | P26: =P25 -> 10873 | Q26: =IF(J26-P26<=0,"ok","oil change") -> ok | R26: =R25 -> 12417 | S26: =R26-R25 -> 0 | T26: =T25 -> 372842 | U26: =V26*S26 -> 0 | V26: 250 | X26: =X25 -> 12540 | Y26: =IF(R26-X26<=0,"ok","oil change") -> ok | Z26: =C26+K26+S26 -> 0 | AA26: =U26+M26+E26 -> 0 | AB26: =V26+N26+F26 -> 250 | AC26: =IF(Z26>0,AA26/Z26,0) -> 0 | AD26: =ELEC!Q27 -> 0 | AE26: =SUM(AD26/Z26) -> #DIV/0! | AF26: =SUM(AE26/1600) -> #DIV/0! | AG26: =SUM(320*AF26) -> #DIV/0! | AH26: =SUM(AC26-AG26) -> #DIV/0! | AI26: =AD26*AJ26 -> 0 | AJ26: =305/1185 -> 0.25738397 | AK26: =AI26/Z26 -> #DIV/0!
A27: =ELEC!C28 -> 44372 | B27: =B26 -> 10269 | C27: =B27-B26 -> 0 | D27: =D26 -> 438387 | E27: =SUM(D27-D26) -> 0 | F27: =IF(C27>0,E27/C27,0) -> 0 | H27: =H26 -> 10310 | I27: =IF(B27-H27<=0,"ok","oil change") -> ok | J27: =J26 -> 10698 | K27: =J27-J26 -> 0 | L27: =L26 -> 357691 | M27: =SUM(L27-L26) -> 0 | N27: =IF(K27>0,M27/K27,0) -> 0 | P27: =P26 -> 10873 | Q27: =IF(J27-P27<=0,"ok","oil change") -> ok | R27: =R26 -> 12417 | S27: =R27-R26 -> 0 | T27: =T26 -> 372842 | U27: =V27*S27 -> 0 | V27: 250 | X27: =X26 -> 12540 | Y27: =IF(R27-X27<=0,"ok","oil change") -> ok | Z27: =C27+K27+S27 -> 0 | AA27: =U27+M27+E27 -> 0 | AB27: =V27+N27+F27 -> 250 | AC27: =IF(Z27>0,AA27/Z27,0) -> 0 | AD27: =ELEC!Q28 -> 0 | AE27: =SUM(AD27/Z27) -> #DIV/0! | AF27: =SUM(AE27/1600) -> #DIV/0! | AG27: =SUM(320*AF27) -> #DIV/0! | AH27: =SUM(AC27-AG27) -> #DIV/0! | AI27: =AD27*AJ27 -> 0 | AJ27: =305/1185 -> 0.25738397 | AK27: =AI27/Z27 -> #DIV/0!
A28: =ELEC!C29 -> 44373 | B28: =B27 -> 10269 | C28: =B28-B27 -> 0 | D28: =D27 -> 438387 | E28: =SUM(D28-D27) -> 0 | F28: =IF(C28>0,E28/C28,0) -> 0 | H28: =H27 -> 10310 | I28: =IF(B28-H28<=0,"ok","oil change") -> ok | J28: =J27 -> 10698 | K28: =J28-J27 -> 0 | L28: =L27 -> 357691 | M28: =SUM(L28-L27) -> 0 | N28: =IF(K28>0,M28/K28,0) -> 0 | P28: =P27 -> 10873 | Q28: =IF(J28-P28<=0,"ok","oil change") -> ok | R28: =R27 -> 12417 | S28: =R28-R27 -> 0 | T28: =T27 -> 372842 | U28: =V28*S28 -> 0 | V28: 250 | X28: =X27 -> 12540 | Y28: =IF(R28-X28<=0,"ok","oil change") -> ok | Z28: =C28+K28+S28 -> 0 | AA28: =U28+M28+E28 -> 0 | AB28: =V28+N28+F28 -> 250 | AC28: =IF(Z28>0,AA28/Z28,0) -> 0 | AD28: =ELEC!Q29 -> 0 | AE28: =SUM(AD28/Z28) -> #DIV/0! | AF28: =SUM(AE28/1600) -> #DIV/0! | AG28: =SUM(320*AF28) -> #DIV/0! | AH28: =SUM(AC28-AG28) -> #DIV/0! | AI28: =AD28*AJ28 -> 0 | AJ28: =305/1185 -> 0.25738397 | AK28: =AI28/Z28 -> #DIV/0!
A29: =ELEC!C30 -> 44374 | B29: =B28 -> 10269 | C29: =B29-B28 -> 0 | D29: =D28 -> 438387 | E29: =SUM(D29-D28) -> 0 | F29: =IF(C29>0,E29/C29,0) -> 0 | H29: =H28 -> 10310 | I29: =IF(B29-H29<=0,"ok","oil change") -> ok | J29: =J28 -> 10698 | K29: =J29-J28 -> 0 | L29: =L28 -> 357691 | M29: =SUM(L29-L28) -> 0 | N29: =IF(K29>0,M29/K29,0) -> 0 | P29: =P28 -> 10873 | Q29: =IF(J29-P29<=0,"ok","oil change") -> ok | R29: =R28 -> 12417 | S29: =R29-R28 -> 0 | T29: =T28 -> 372842 | U29: =V29*S29 -> 0 | V29: 250 | X29: =X28 -> 12540 | Y29: =IF(R29-X29<=0,"ok","oil change") -> ok | Z29: =C29+K29+S29 -> 0 | AA29: =U29+M29+E29 -> 0 | AB29: =V29+N29+F29 -> 250 | AC29: =IF(Z29>0,AA29/Z29,0) -> 0 | AD29: =ELEC!Q30 -> 0 | AE29: =SUM(AD29/Z29) -> #DIV/0! | AF29: =SUM(AE29/1600) -> #DIV/0! | AG29: =SUM(320*AF29) -> #DIV/0! | AH29: =SUM(AC29-AG29) -> #DIV/0! | AI29: =AD29*AJ29 -> 0 | AJ29: =305/1185 -> 0.25738397 | AK29: =AI29/Z29 -> #DIV/0!
A30: =ELEC!C31 -> 44375 | B30: =B29 -> 10269 | C30: =B30-B29 -> 0 | D30: =D29 -> 438387 | E30: =SUM(D30-D29) -> 0 | F30: =IF(C30>0,E30/C30,0) -> 0 | H30: =H29 -> 10310 | I30: =IF(B30-H30<=0,"ok","oil change") -> ok | J30: =J29 -> 10698 | K30: =J30-J29 -> 0 | L30: =L29 -> 357691 | M30: =SUM(L30-L29) -> 0 | N30: =IF(K30>0,M30/K30,0) -> 0 | P30: =P29 -> 10873 | Q30: =IF(J30-P30<=0,"ok","oil change") -> ok | R30: =R29 -> 12417 | S30: =R30-R29 -> 0 | T30: =T29 -> 372842 | U30: =V30*S30 -> 0 | V30: 250 | X30: =X29 -> 12540 | Y30: =IF(R30-X30<=0,"ok","oil change") -> ok | Z30: =C30+K30+S30 -> 0 | AA30: =U30+M30+E30 -> 0 | AB30: =V30+N30+F30 -> 250 | AC30: =IF(Z30>0,AA30/Z30,0) -> 0 | AD30: =ELEC!Q31 -> 0 | AE30: =SUM(AD30/Z30) -> #DIV/0! | AF30: =SUM(AE30/1600) -> #DIV/0! | AG30: =SUM(320*AF30) -> #DIV/0! | AH30: =SUM(AC30-AG30) -> #DIV/0! | AI30: =AD30*AJ30 -> 0 | AJ30: =305/1185 -> 0.25738397 | AK30: =AI30/Z30 -> #DIV/0!
A31: =ELEC!C32 -> 44376 | B31: =B30 -> 10269 | C31: =B31-B30 -> 0 | D31: =D30 -> 438387 | E31: =SUM(D31-D30) -> 0 | F31: =IF(C31>0,E31/C31,0) -> 0 | H31: =H30 -> 10310 | I31: =IF(B31-H31<=0,"ok","oil change") -> ok | J31: =J30 -> 10698 | K31: =J31-J30 -> 0 | L31: =L30 -> 357691 | M31: =SUM(L31-L30) -> 0 | N31: =IF(K31>0,M31/K31,0) -> 0 | P31: =P30 -> 10873 | Q31: =IF(J31-P31<=0,"ok","oil change") -> ok | R31: =R30 -> 12417 | S31: =R31-R30 -> 0 | T31: =T30 -> 372842 | U31: =V31*S31 -> 0 | V31: 250 | X31: =X30 -> 12540 | Y31: =IF(R31-X31<=0,"ok","oil change") -> ok | Z31: =C31+K31+S31 -> 0 | AA31: =U31+M31+E31 -> 0 | AB31: =V31+N31+F31 -> 250 | AC31: =IF(Z31>0,AA31/Z31,0) -> 0 | AD31: =ELEC!Q32 -> 0 | AE31: =SUM(AD31/Z31) -> #DIV/0! | AF31: =SUM(AE31/1600) -> #DIV/0! | AG31: =SUM(320*AF31) -> #DIV/0! | AH31: =SUM(AC31-AG31) -> #DIV/0! | AI31: =AD31*AJ31 -> 0 | AJ31: =305/1185 -> 0.25738397 | AK31: =AI31/Z31 -> #DIV/0!
A32: =ELEC!C33 -> 44377 | B32: =B31 -> 10269 | C32: =B32-B31 -> 0 | D32: =D31 -> 438387 | E32: =SUM(D32-D31) -> 0 | F32: =IF(C32>0,E32/C32,0) -> 0 | H32: =H31 -> 10310 | I32: =IF(B32-H32<=0,"ok","oil change") -> ok | J32: =J31 -> 10698 | K32: =J32-J31 -> 0 | L32: =L31 -> 357691 | M32: =SUM(L32-L31) -> 0 | N32: =IF(K32>0,M32/K32,0) -> 0 | P32: =P31 -> 10873 | Q32: =IF(J32-P32<=0,"ok","oil change") -> ok | R32: =R31 -> 12417 | S32: =R32-R31 -> 0 | T32: =T31 -> 372842 | U32: =V32*S32 -> 0 | V32: 250 | X32: =X31 -> 12540 | Y32: =IF(R32-X32<=0,"ok","oil change") -> ok | Z32: =C32+K32+S32 -> 0 | AA32: =U32+M32+E32 -> 0 | AB32: =V32+N32+F32 -> 250 | AC32: =IF(Z32>0,AA32/Z32,0) -> 0 | AD32: =ELEC!Q33 -> 0 | AE32: =SUM(AD32/Z32) -> #DIV/0! | AF32: =SUM(AE32/1600) -> #DIV/0! | AG32: =SUM(320*AF32) -> #DIV/0! | AH32: =SUM(AC32-AG32) -> #DIV/0! | AI32: =AD32*AJ32 -> 0 | AJ32: =305/1185 -> 0.25738397 | AK32: =AI32/Z32 -> #DIV/0!
P33: =+O33/3 -> 0 | U33: =SUM(C34:S34) -> 304 | X33: 341 | Z33: =SUM(Z3:Z32) -> 304
C34: =SUM(C3:C32) -> 146 | K34: =SUM(K3:K32) -> 0 | S34: =SUM(S3:S32) -> 158

Sheet tanks
B2: Tank 1 | D2: Tank 2 | F2: Tank 3 | H2: Tank 4 | J2: Tank 5 | L2: Tank 6 | N2: Tank 7 | P2: Tank 8 | R2: Tank 9 | T2: Tank 10 | V2: Tank 11 | Z2: Tank 1 | AB2: Tank 2 | AD2: Tank 3 | AF2: Tank 4 | AH2: Tank 5 | AJ2: Tank 6 | AL2: Tank 7
B3: 6670 | D3: =SUM(B3) -> 6670 | F3: =SUM(D3) -> 6670 | H3: =SUM(F3) -> 6670 | J3: =SUM(H3) -> 6670 | L3: =SUM(J3) -> 6670 | N3: =SUM(L3) -> 6670 | P3: =SUM(N3) -> 6670 | R3: =SUM(P3) -> 6670 | T3: =SUM(R3) -> 6670 | V3: =SUM(T3) -> 6670 | W3: =SUM(B3:V3) -> 73370 | Z3: 2800 | AB3: 2800 | AD3: 2800 | AF3: 2800 | AH3: 2800 | AJ3: 2800 | AL3: 2800 | AM3: =SUM(Z3:AL3) -> 19600 | AO3: =SUM(AM3+W3) -> 92970 | AR3: Total sotck | AS3: Diesel Cons Per day | AT3: Diesel Delivery | BE3: Genset Co | BF3: Steam | BG3: Boil | BH3: Outdoor temperature
B4: =B3/310 -> 21.516129 | D4: =SUM(B4) -> 21.516129 | F4: =SUM(D4) -> 21.516129 | H4: =SUM(F4) -> 21.516129 | J4: =SUM(H4) -> 21.516129 | L4: =SUM(J4) -> 21.516129 | N4: =SUM(L4) -> 21.516129 | P4: =SUM(N4) -> 21.516129 | R4: =SUM(P4) -> 21.516129 | T4: =SUM(R4) -> 21.516129 | V4: =SUM(T4) -> 21.516129 | Z4: =Z3/280 -> 10 | AA4: =AA3/280 -> 0 | AB4: =AB3/280 -> 10 | AC4: =AC3/280 -> 0 | AD4: =AD3/280 -> 10 | AE4: =AE3/280 -> 0 | AF4: =AF3/280 -> 10 | AG4: =AG3/280 -> 0 | ... AL4: =AL3/280 -> 10 | AT4: Delivery | AU4: Cost /L | AW4: Boiler+Steam | AX4: Generator | AZ4: Occupancy | BA4: AVE TEPM | BB4: AVE Humidity
A5: =ELEC!C3 -> 44347 | B5: =[3]tanks!B36 -> 207 | C5: =[3]tanks!C36 -> 4453.8387 | D5: =[3]tanks!D36 -> 207 | E5: =[3]tanks!E36 -> 4453.8387 | F5: =[3]tanks!F36 -> 207 | G5: =[3]tanks!G36 -> 4453.8387 | H5: =[3]tanks!H36 -> 207 | I5: =[3]tanks!I36 -> 4453.8387 | ... AO5: =[3]tanks!AO36 -> 14980 | AQ5: =[3]tanks!AQ36 -> 0.68809536 | AR5: =[3]tanks!AR36 -> 63972.226 | AS5: =[3]tanks!AS36 -> -4016.3871 | AT5: =[3]tanks!AT36 -> 12060 | AU5: =[3]tanks!AU36 -> 1.003 | AV5: =[3]tanks!AV36 -> 1.003 | AW5: =[3]tanks!AW36 -> -306 | AX5: =[3]tanks!AX36 -> -3710.3871 | ... BH5: =[3]tanks!BH36 -> 0
A6: =ELEC!C4 -> 44348 | B6: ='B5'!B5 -> 191 | C6: =B6*$B$4 -> 4109.5806 | D6: =SUM(B6) -> 191 | E6: =D6*$B$4 -> 4109.5806 | F6: =SUM(D6) -> 191 | G6: =F6*$B$4 -> 4109.5806 | H6: =SUM(F6) -> 191 | I6: =H6*$B$4 -> 4109.5806 | J6: =SUM(H6) -> 191 | K6: =J6*$B$4 -> 4109.5806 | L6: =SUM(J6) -> 191 | M6: =L6*$B$4 -> 4109.5806 | N6: =SUM(L6) -> 191 | O6: =N6*$B$4 -> 4109.5806 | P6: =SUM(N6) -> 191 | Q6: =P6*$B$4 -> 4109.5806 | R6: =SUM(P6) -> 191 | S6: =R6*$B$4 -> 4109.5806 | T6: =SUM(R6) -> 191 | U6: =T6*$B$4 -> 4109.5806 | V6: =SUM(T6) -> 191 | W6: =V6*$B$4 -> 4109.5806 | X6: =SUM(Y6/73370) -> 0.61612903 | Y6: =SUM(C6+E6+G6+I6+K6+M6+O6+Q6+S6+U6+W6) -> 45205.387 | Z6: ='B5'!C5 -> 204 | AA6: =SUM(Z6*$Z$4) -> 2040 | AB6: =SUM(Z6) -> 204 | AC6: =SUM(AB6*$Z$4) -> 2040 | AD6: =SUM(AB6) -> 204 | AE6: =SUM(AD6*$Z$4) -> 2040 | AF6: =SUM(AD6) -> 204 | AG6: =SUM(AF6*$Z$4) -> 2040 | AH6: =SUM(AF6) -> 204 | AI6: =SUM(AH6*$Z$4) -> 2040 | AJ6: =SUM(AH6) -> 204 | AK6: =SUM(AJ6*$Z$4) -> 2040 | AL6: =SUM(AJ6) -> 204 | AM6: =SUM(AL6*$Z$4) -> 2040 | AN6: =SUM(AO6/19600) -> 0.72857143 | AO6: =SUM(AA6+AC6+AE6+AG6+AI6+AK6+AM6) -> 14280 | AQ6: =SUM(AR6/92970) -> 0.63983422 | AR6: =Y6+AO6 -> 59485.387 | AS6: =SUM(AR6-AR5-AT6) -> -4486.8387 | AV6: =IF(AT6>0,AU6,AV5) -> 1.003 | AW6: =-SUM('B5'!AI5) -> -107 | AX6: =-SUM(AW6-AS6) -> -4379.8387 | AY6: =SUM(AX6+AW6) -> -4486.8387 | AZ6: =ELEC!A4 -> 0 | BA6: ='General information '!D6 -> 24 | BB6: =SUM('General information '!E6) -> 0.46 | BC6: =IF(AR3>=AR6,0,1) -> 0 | BD6: 19222 | BE6: =(305/1185)*ELEC!Q5 -> 2800.5949 | BG6: =#REF!-BE6 -> #REF! | BH6: 21 | BI6: 12 | BJ6: =AX6/BI6 -> -364.98656 | BK6: =GEN!AF3 -> 0.49557292
A7: =ELEC!C5 -> 44349 | B7: ='B5'!B6 -> 185 | C7: =B7*$B$4 -> 3980.4839 | D7: =SUM(B7) -> 185 | E7: =D7*$B$4 -> 3980.4839 | F7: =SUM(D7) -> 185 | G7: =F7*$B$4 -> 3980.4839 | H7: =SUM(F7) -> 185 | I7: =H7*$B$4 -> 3980.4839 | J7: =SUM(H7) -> 185 | K7: =J7*$B$4 -> 3980.4839 | L7: =SUM(J7) -> 185 | M7: =L7*$B$4 -> 3980.4839 | N7: =SUM(L7) -> 185 | O7: =N7*$B$4 -> 3980.4839 | P7: =SUM(N7) -> 185 | Q7: =P7*$B$4 -> 3980.4839 | R7: =SUM(P7) -> 185 | S7: =R7*$B$4 -> 3980.4839 | T7: =SUM(R7) -> 185 | U7: =T7*$B$4 -> 3980.4839 | V7: =SUM(T7) -> 185 | W7: =V7*$B$4 -> 3980.4839 | X7: =SUM(Y7/73370) -> 0.59677419 | Y7: =SUM(C7+E7+G7+I7+K7+M7+O7+Q7+S7+U7+W7) -> 43785.323 | Z7: ='B5'!C6 -> 192 | AA7: =SUM(Z7*$Z$4) -> 1920 | AB7: =SUM(Z7) -> 192 | AC7: =SUM(AB7*$Z$4) -> 1920 | AD7: =SUM(AB7) -> 192 | AE7: =SUM(AD7*$Z$4) -> 1920 | AF7: =SUM(AD7) -> 192 | AG7: =SUM(AF7*$Z$4) -> 1920 | AH7: =SUM(AF7) -> 192 | AI7: =SUM(AH7*$Z$4) -> 1920 | AJ7: =SUM(AH7) -> 192 | AK7: =SUM(AJ7*$Z$4) -> 1920 | AL7: =SUM(AJ7) -> 192 | AM7: =SUM(AL7*$Z$4) -> 1920 | AN7: =SUM(AO7/19600) -> 0.68571429 | AO7: =SUM(AA7+AC7+AE7+AG7+AI7+AK7+AM7) -> 13440 | AQ7: =SUM(AR7/92970) -> 0.61552461 | AR7: =Y7+AO7 -> 57225.323 | AS7: =SUM(AR7-AR6-AT7) -> -2260.0645 | AV7: =IF(AT7>0,AU7,AV6) -> 1.003 | AW7: =-SUM('B5'!AI6) -> -128 | AX7: =-SUM(AW7-AS7) -> -2132.0645 | AY7: =SUM(AX7+AW7) -> -2260.0645 | AZ7: =ELEC!A5 -> 0 | BA7: ='General information '!D7 -> 24 | BB7: =SUM('General information '!E7) -> 0.62 | BC7: 0 | BD7: 19222 | BE7: =(305/1185)*ELEC!Q6 -> 3762.4388 | BG7: =#REF!-BE7 -> #REF! | BH7: 19 | BI7: 15 | BJ7: =AX7/BI7 -> -142.13763 | BK7: =GEN!AF4 -> 0.523125
A8: =ELEC!C6 -> 44350 | B8: ='B5'!B7 -> 228 | C8: =B8*$B$4 -> 4905.6774 | D8: =SUM(B8) -> 228 | E8: =D8*$B$4 -> 4905.6774 | F8: =SUM(D8) -> 228 | G8: =F8*$B$4 -> 4905.6774 | H8: =SUM(F8) -> 228 | I8: =H8*$B$4 -> 4905.6774 | J8: =SUM(H8) -> 228 | K8: =J8*$B$4 -> 4905.6774 | L8: =SUM(J8) -> 228 | M8: =L8*$B$4 -> 4905.6774 | N8: =SUM(L8) -> 228 | O8: =N8*$B$4 -> 4905.6774 | P8: =SUM(N8) -> 228 | Q8: =P8*$B$4 -> 4905.6774 | R8: =SUM(P8) -> 228 | S8: =R8*$B$4 -> 4905.6774 | T8: =SUM(R8) -> 228 | U8: =T8*$B$4 -> 4905.6774 | V8: =SUM(T8) -> 228 | W8: =V8*$B$4 -> 4905.6774 | X8: =SUM(Y8/73370) -> 0.73548387 | Y8: =SUM(C8+E8+G8+I8+K8+M8+O8+Q8+S8+U8+W8) -> 53962.452 | Z8: ='B5'!C7 -> 235 | AA8: =SUM(Z8*$Z$4) -> 2350 | AB8: =SUM(Z8) -> 235 | AC8: =SUM(AB8*$Z$4) -> 2350 | AD8: =SUM(AB8) -> 235 | AE8: =SUM(AD8*$Z$4) -> 2350 | AF8: =SUM(AD8) -> 235 | AG8: =SUM(AF8*$Z$4) -> 2350 | AH8: =SUM(AF8) -> 235 | AI8: =SUM(AH8*$Z$4) -> 2350 | AJ8: =SUM(AH8) -> 235 | AK8: =SUM(AJ8*$Z$4) -> 2350 | AL8: =SUM(AJ8) -> 235 | AM8: =SUM(AL8*$Z$4) -> 2350 | AN8: =SUM(AO8/19600) -> 0.83928571 | AO8: =SUM(AA8+AC8+AE8+AG8+AI8+AK8+AM8) -> 16450 | AQ8: =SUM(AR8/92970) -> 0.75736745 | AR8: =Y8+AO8 -> 70412.452 | AS8: =SUM(AR8-AR7-AT8) -> -2097.871 | AT8: 15285 | AU8: 1.003 | AV8: =IF(AT8>0,AU8,AV7) -> 1.003 | AW8: =-SUM('B5'!AI7) -> -125 | AX8: =-SUM(AW8-AS8) -> -1972.871 | AY8: =SUM(AX8+AW8) -> -2097.871 | AZ8: =ELEC!A6 -> 0 | BA8: ='General information '!D8 -> 24.5 | BB8: =SUM('General information '!E8) -> 0.65 | BC8: =IF(AR7>=AR8,0,1) -> 1 | BD8: 19222 | BE8: =(305/1185)*ELEC!Q7 -> 3618.3038 | BG8: =#REF!-BE8 -> #REF! | BH8: 16 | BI8: 9 | BJ8: =AX8/BI8 -> -219.20789 | BK8: =GEN!AF5 -> 0.4568125
A9: =ELEC!C7 -> 44351 | B9: ='B5'!B8 -> 218 | C9: =B9*$B$4 -> 4690.5161 | D9: =SUM(B9) -> 218 | E9: =D9*$B$4 -> 4690.5161 | F9: =SUM(D9) -> 218 | G9: =F9*$B$4 -> 4690.5161 | H9: =SUM(F9) -> 218 | I9: =H9*$B$4 -> 4690.5161 | J9: =SUM(H9) -> 218 | K9: =J9*$B$4 -> 4690.5161 | L9: =SUM(J9) -> 218 | M9: =L9*$B$4 -> 4690.5161 | N9: =SUM(L9) -> 218 | O9: =N9*$B$4 -> 4690.5161 | P9: =SUM(N9) -> 218 | Q9: =P9*$B$4 -> 4690.5161 | R9: =SUM(P9) -> 218 | S9: =R9*$B$4 -> 4690.5161 | T9: =SUM(R9) -> 218 | U9: =T9*$B$4 -> 4690.5161 | V9: =SUM(T9) -> 218 | W9: =V9*$B$4 -> 4690.5161 | X9: =SUM(Y9/73370) -> 0.70322581 | Y9: =SUM(C9+E9+G9+I9+K9+M9+O9+Q9+S9+U9+W9) -> 51595.677 | Z9: ='B5'!C8 -> 225 | AA9: =SUM(Z9*$Z$4) -> 2250 | AB9: =SUM(Z9) -> 225 | AC9: =SUM(AB9*$Z$4) -> 2250 | AD9: =SUM(AB9) -> 225 | AE9: =SUM(AD9*$Z$4) -> 2250 | AF9: =SUM(AD9) -> 225 | AG9: =SUM(AF9*$Z$4) -> 2250 | AH9: =SUM(AF9) -> 225 | AI9: =SUM(AH9*$Z$4) -> 2250 | AJ9: =SUM(AH9) -> 225 | AK9: =SUM(AJ9*$Z$4) -> 2250 | AL9: =SUM(AJ9) -> 225 | AM9: =SUM(AL9*$Z$4) -> 2250 | AN9: =SUM(AO9/19600) -> 0.80357143 | AO9: =SUM(AA9+AC9+AE9+AG9+AI9+AK9+AM9) -> 15750 | AQ9: =SUM(AR9/92970) -> 0.72438074 | AR9: =Y9+AO9 -> 67345.677 | AS9: =SUM(AR9-AR8-AT9) -> -3066.7742 | AV9: =IF(AT9>0,AU9,AV8) -> 1.003 | AW9: =-SUM('B5'!AI8) -> -91 | AX9: =-SUM(AW9-AS9) -> -2975.7742 | AY9: =SUM(AX9+AW9) -> -3066.7742 | AZ9: =ELEC!A7 -> 0 | BA9: ='General information '!D9 -> 25 | BB9: =SUM('General information '!E9) -> 0.65 | BC9: =IF(AR8>=AR9,0,1) -> 0 | BD9: 19222 | BE9: =(305/1185)*ELEC!Q8 -> 3039.7046 | BG9: =#REF!-BE9 -> #REF! | BH9: 18 | BI9: 6 | BJ9: =AX9/BI9 -> -495.96237 | BK9: =GEN!AF6 -> 0.4393125
A10: =ELEC!C8 -> 44352 | B10: ='B5'!B9 -> 201 | C10: =B10*$B$4 -> 4324.7419 | D10: =SUM(B10) -> 201 | E10: =D10*$B$4 -> 4324.7419 | F10: =SUM(D10) -> 201 | G10: =F10*$B$4 -> 4324.7419 | H10: =SUM(F10) -> 201 | I10: =H10*$B$4 -> 4324.7419 | J10: =SUM(H10) -> 201 | K10: =J10*$B$4 -> 4324.7419 | L10: =SUM(J10) -> 201 | M10: =L10*$B$4 -> 4324.7419 | N10: =SUM(L10) -> 201 | O10: =N10*$B$4 -> 4324.7419 | P10: =SUM(N10) -> 201 | Q10: =P10*$B$4 -> 4324.7419 | R10: =SUM(P10) -> 201 | S10: =R10*$B$4 -> 4324.7419 | T10: =SUM(R10) -> 201 | U10: =T10*$B$4 -> 4324.7419 | V10: =SUM(T10) -> 201 | W10: =V10*$B$4 -> 4324.7419 | X10: =SUM(Y10/73370) -> 0.6483871 | Y10: =SUM(C10+E10+G10+I10+K10+M10+O10+Q10+S10+U10+W10) -> 47572.161 | Z10: ='B5'!C9 -> 208 | AA10: =SUM(Z10*$Z$4) -> 2080 | AB10: =SUM(Z10) -> 208 | AC10: =SUM(AB10*$Z$4) -> 2080 | AD10: =SUM(AB10) -> 208 | AE10: =SUM(AD10*$Z$4) -> 2080 | AF10: =SUM(AD10) -> 208 | AG10: =SUM(AF10*$Z$4) -> 2080 | AH10: =SUM(AF10) -> 208 | AI10: =SUM(AH10*$Z$4) -> 2080 | AJ10: =SUM(AH10) -> 208 | AK10: =SUM(AJ10*$Z$4) -> 2080 | AL10: =SUM(AJ10) -> 208 | AM10: =SUM(AL10*$Z$4) -> 2080 | AN10: =SUM(AO10/19600) -> 0.74285714 | AO10: =SUM(AA10+AC10+AE10+AG10+AI10+AK10+AM10) -> 14560 | AQ10: =SUM(AR10/92970) -> 0.66830334 | AR10: =Y10+AO10 -> 62132.161 | AS10: =SUM(AR10-AR9-AT10) -> -5213.5161 | AV10: =IF(AT10>0,AU10,AV9) -> 1.003 | AW10: =-SUM('B5'!AI9) -> -242 | AX10: =-SUM(AW10-AS10) -> -4971.5161 | AY10: =SUM(AX10+AW10) -> -5213.5161 | AZ10: =ELEC!A8 -> 0 | BA10: ='General information '!D10 -> 23 | BB10: =SUM('General information '!E10) -> 0.66 | BC10: =IF(AR9>=AR10,0,1) -> 0 | BD10: 19222 | BE10: =(305/1185)*ELEC!Q9 -> 2825.0464 | BG10: =#REF!-BE10 -> #REF! | BH10: 16 | BI10: 7 | BJ10: =AX10/BI10 -> -710.21659 | BK10: =GEN!AF7 -> 0.46132812
A11: =ELEC!C9 -> 44353 | B11: ='B5'!B10 -> 188 | C11: =B11*$B$4 -> 4045.0323 | D11: =SUM(B11) -> 188 | E11: =D11*$B$4 -> 4045.0323 | F11: =SUM(D11) -> 188 | G11: =F11*$B$4 -> 4045.0323 | H11: =SUM(F11) -> 188 | I11: =H11*$B$4 -> 4045.0323 | J11: =SUM(H11) -> 188 | K11: =J11*$B$4 -> 4045.0323 | L11: =SUM(J11) -> 188 | M11: =L11*$B$4 -> 4045.0323 | N11: =SUM(L11) -> 188 | O11: =N11*$B$4 -> 4045.0323 | P11: =SUM(N11) -> 188 | Q11: =P11*$B$4 -> 4045.0323 | R11: =SUM(P11) -> 188 | S11: =R11*$B$4 -> 4045.0323 | T11: =SUM(R11) -> 188 | U11: =T11*$B$4 -> 4045.0323 | V11: =SUM(T11) -> 188 | W11: =V11*$B$4 -> 4045.0323 | X11: =SUM(Y11/73370) -> 0.60645161 | Y11: =SUM(C11+E11+G11+I11+K11+M11+O11+Q11+S11+U11+W11) -> 44495.355 | Z11: ='B5'!C10 -> 194 | AA11: =SUM(Z11*$Z$4) -> 1940 | AB11: =SUM(Z11) -> 194 | AC11: =SUM(AB11*$Z$4) -> 1940 | AD11: =SUM(AB11) -> 194 | AE11: =SUM(AD11*$Z$4) -> 1940 | AF11: =SUM(AD11) -> 194 | AG11: =SUM(AF11*$Z$4) -> 1940 | AH11: =SUM(AF11) -> 194 | AI11: =SUM(AH11*$Z$4) -> 1940 | AJ11: =SUM(AH11) -> 194 | AK11: =SUM(AJ11*$Z$4) -> 1940 | AL11: =SUM(AJ11) -> 194 | AM11: =SUM(AL11*$Z$4) -> 1940 | AN11: =SUM(AO11/19600) -> 0.69285714 | AO11: =SUM(AA11+AC11+AE11+AG11+AI11+AK11+AM11) -> 13580 | AQ11: =SUM(AR11/92970) -> 0.62466769 | AR11: =Y11+AO11 -> 58075.355 | AS11: =SUM(AR11-AR10-AT11) -> -4056.8065 | AV11: =IF(AT11>0,AU11,AV10) -> 1.003 | AW11: =-SUM('B5'!AI10) -> -192 | AX11: =-SUM(AW11-AS11) -> -3864.8065 | AY11: =SUM(AX11+AW11) -> -4056.8065 | AZ11: =ELEC!A9 -> 0 | BA11: ='General information '!D11 -> 24 | BB11: =SUM('General information '!E11) -> 0.65 | BC11: =IF(AR10>=AR11,0,1) -> 0 | BD11: 19222 | BE11: =(305/1185)*ELEC!Q10 -> 3892.6751 | BG11: =#REF!-BE11 -> #REF! | BH11: 16.5 | BI11: 9.3 | BJ11: =AX11/BI11 -> -415.57059 | BK11: =GEN!AF8 -> 0.36105263
A12: =ELEC!C10 -> 44354 | B12: ='B5'!B11 -> 228 | C12: =B12*$B$4 -> 4905.6774 | D12: =SUM(B12) -> 228 | E12: =D12*$B$4 -> 4905.6774 | F12: =SUM(D12) -> 228 | G12: =F12*$B$4 -> 4905.6774 | H12: =SUM(F12) -> 228 | I12: =H12*$B$4 -> 4905.6774 | J12: =SUM(H12) -> 228 | K12: =J12*$B$4 -> 4905.6774 | L12: =SUM(J12) -> 228 | M12: =L12*$B$4 -> 4905.6774 | N12: =SUM(L12) -> 228 | O12: =N12*$B$4 -> 4905.6774 | P12: =SUM(N12) -> 228 | Q12: =P12*$B$4 -> 4905.6774 | R12: =SUM(P12) -> 228 | S12: =R12*$B$4 -> 4905.6774 | T12: =SUM(R12) -> 228 | U12: =T12*$B$4 -> 4905.6774 | V12: =SUM(T12) -> 228 | W12: =V12*$B$4 -> 4905.6774 | X12: =SUM(Y12/73370) -> 0.73548387 | Y12: =SUM(C12+E12+G12+I12+K12+M12+O12+Q12+S12+U12+W12) -> 53962.452 | Z12: ='B5'!C11 -> 234 | AA12: =SUM(Z12*$Z$4) -> 2340 | AB12: =SUM(Z12) -> 234 | AC12: =SUM(AB12*$Z$4) -> 2340 | AD12: =SUM(AB12) -> 234 | AE12: =SUM(AD12*$Z$4) -> 2340 | AF12: =SUM(AD12) -> 234 | AG12: =SUM(AF12*$Z$4) -> 2340 | AH12: =SUM(AF12) -> 234 | AI12: =SUM(AH12*$Z$4) -> 2340 | AJ12: =SUM(AH12) -> 234 | AK12: =SUM(AJ12*$Z$4) -> 2340 | AL12: =SUM(AJ12) -> 234 | AM12: =SUM(AL12*$Z$4) -> 2340 | AN12: =SUM(AO12/19600) -> 0.83571429 | AO12: =SUM(AA12+AC12+AE12+AG12+AI12+AK12+AM12) -> 16380 | AQ12: =SUM(AR12/92970) -> 0.75661452 | AR12: =Y12+AO12 -> 70342.452 | AS12: =SUM(AR12-AR11-AT12) -> -2332.9032 | AT12: 14600 | AU12: 1.003 | AV12: =IF(AT12>0,AU12,AV11) -> 1.003 | AW12: =-SUM('B5'!AI11) -> -54 | AX12: =-SUM(AW12-AS12) -> -2278.9032 | AY12: =SUM(AX12+AW12) -> -2332.9032 | AZ12: =ELEC!A10 -> 0 | BA12: ='General information '!D12 -> 25 | BB12: =SUM('General information '!E12) -> 0.57 | BC12: =IF(AR11>=AR12,0,1) -> 1 | BD12: 19222 | BE12: =(305/1185)*ELEC!Q11 -> 2659.0338 | BG12: =#REF!-BE12 -> #REF! | BH12: 15.5 | BI12: 3.7 | BJ12: =AX12/BI12 -> -615.91979 | BK12: =GEN!AF9 -> 0.472625
A13: =ELEC!C11 -> 44355 | B13: ='B5'!B12 -> 216 | C13: =B13*$B$4 -> 4647.4839 | D13: =SUM(B13) -> 216 | E13: =D13*$B$4 -> 4647.4839 | F13: =SUM(D13) -> 216 | G13: =F13*$B$4 -> 4647.4839 | H13: =SUM(F13) -> 216 | I13: =H13*$B$4 -> 4647.4839 | J13: =SUM(H13) -> 216 | K13: =J13*$B$4 -> 4647.4839 | L13: =SUM(J13) -> 216 | M13: =L13*$B$4 -> 4647.4839 | N13: =SUM(L13) -> 216 | O13: =N13*$B$4 -> 4647.4839 | P13: =SUM(N13) -> 216 | Q13: =P13*$B$4 -> 4647.4839 | R13: =SUM(P13) -> 216 | S13: =R13*$B$4 -> 4647.4839 | T13: =SUM(R13) -> 216 | U13: =T13*$B$4 -> 4647.4839 | V13: =SUM(T13) -> 216 | W13: =V13*$B$4 -> 4647.4839 | X13: =SUM(Y13/73370) -> 0.69677419 | Y13: =SUM(C13+E13+G13+I13+K13+M13+O13+Q13+S13+U13+W13) -> 51122.323 | Z13: ='B5'!C12 -> 223 | AA13: =SUM(Z13*$Z$4) -> 2230 | AB13: =SUM(Z13) -> 223 | AC13: =SUM(AB13*$Z$4) -> 2230 | AD13: =SUM(AB13) -> 223 | AE13: =SUM(AD13*$Z$4) -> 2230 | AF13: =SUM(AD13) -> 223 | AG13: =SUM(AF13*$Z$4) -> 2230 | AH13: =SUM(AF13) -> 223 | AI13: =SUM(AH13*$Z$4) -> 2230 | AJ13: =SUM(AH13) -> 223 | AK13: =SUM(AJ13*$Z$4) -> 2230 | AL13: =SUM(AJ13) -> 223 | AM13: =SUM(AL13*$Z$4) -> 2230 | AN13: =SUM(AO13/19600) -> 0.79642857 | AO13: =SUM(AA13+AC13+AE13+AG13+AI13+AK13+AM13) -> 15610 | AQ13: =SUM(AR13/92970) -> 0.7177834 | AR13: =Y13+AO13 -> 66732.323 | AS13: =SUM(AR13-AR12-AT13) -> -3610.129 | AV13: =IF(AT13>0,AU13,AV12) -> 1.003 | AW13: =-SUM('B5'!AI12) -> -158 | AX13: =-SUM(AW13-AS13) -> -3452.129 | AY13: =SUM(AX13+AW13) -> -3610.129 | AZ13: =ELEC!A11 -> 0 | BA13: ='General information '!D13 -> 25 | BB13: =SUM('General information '!E13) -> 0.52 | BC13: =IF(AR12>=AR13,0,1) -> 0 | BD13: 19222 | BE13: =(305/1185)*ELEC!Q12 -> 3407.7637 | BG13: =#REF!-BE13 -> #REF! | BI13: 5 | BJ13: =AX13/BI13 -> -690.42581 | BK13: =GEN!AF10 -> 0.43045833
A14: =ELEC!C12 -> 44356 | B14: ='B5'!B13 -> 200 | C14: =B14*$B$4 -> 4303.2258 | D14: =SUM(B14) -> 200 | E14: =D14*$B$4 -> 4303.2258 | F14: =SUM(D14) -> 200 | G14: =F14*$B$4 -> 4303.2258 | H14: =SUM(F14) -> 200 | I14: =H14*$B$4 -> 4303.2258 | J14: =SUM(H14) -> 200 | K14: =J14*$B$4 -> 4303.2258 | L14: =SUM(J14) -> 200 | M14: =L14*$B$4 -> 4303.2258 | N14: =SUM(L14) -> 200 | O14: =N14*$B$4 -> 4303.2258 | P14: =SUM(N14) -> 200 | Q14: =P14*$B$4 -> 4303.2258 | R14: =SUM(P14) -> 200 | S14: =R14*$B$4 -> 4303.2258 | T14: =SUM(R14) -> 200 | U14: =T14*$B$4 -> 4303.2258 | V14: =SUM(T14) -> 200 | W14: =V14*$B$4 -> 4303.2258 | X14: =SUM(Y14/73370) -> 0.64516129 | Y14: =SUM(C14+E14+G14+I14+K14+M14+O14+Q14+S14+U14+W14) -> 47335.484 | Z14: ='B5'!C13 -> 208 | AA14: =SUM(Z14*$Z$4) -> 2080 | AB14: =SUM(Z14) -> 208 | AC14: =SUM(AB14*$Z$4) -> 2080 | AD14: =SUM(AB14) -> 208 | AE14: =SUM(AD14*$Z$4) -> 2080 | AF14: =SUM(AD14) -> 208 | AG14: =SUM(AF14*$Z$4) -> 2080 | AH14: =SUM(AF14) -> 208 | AI14: =SUM(AH14*$Z$4) -> 2080 | AJ14: =SUM(AH14) -> 208 | AK14: =SUM(AJ14*$Z$4) -> 2080 | AL14: =SUM(AJ14) -> 208 | AM14: =SUM(AL14*$Z$4) -> 2080 | AN14: =SUM(AO14/19600) -> 0.74285714 | AO14: =SUM(AA14+AC14+AE14+AG14+AI14+AK14+AM14) -> 14560 | AQ14: =SUM(AR14/92970) -> 0.6657576 | AR14: =Y14+AO14 -> 61895.484 | AS14: =SUM(AR14-AR13-AT14) -> -4836.8387 | AV14: =IF(AT14>0,AU14,AV13) -> 1.003 | AW14: =-SUM('B5'!AI13) -> -110 | AX14: =-SUM(AW14-AS14) -> -4726.8387 | AY14: =SUM(AX14+AW14) -> -4836.8387 | AZ14: =ELEC!A12 -> 0 | BA14: ='General information '!D14 -> 24.5 | BB14: =SUM('General information '!E14) -> 0.55 | BC14: =IF(AR13>=AR14,0,1) -> 0 | BD14: 19222 | BE14: =(305/1185)*ELEC!Q13 -> 3576.865 | BG14: =#REF!-BE14 -> #REF! | BI14: 3 | BJ14: =AX14/BI14 -> -1575.6129 | BK14: =GEN!AF11 -> 0.39404762
A15: =ELEC!C13 -> 44357 | B15: ='B5'!B14 -> 246 | C15: =B15*$B$4 -> 5292.9677 | D15: =SUM(B15) -> 246 | E15: =D15*$B$4 -> 5292.9677 | F15: =SUM(D15) -> 246 | G15: =F15*$B$4 -> 5292.9677 | H15: =SUM(F15) -> 246 | I15: =H15*$B$4 -> 5292.9677 | J15: =SUM(H15) -> 246 | K15: =J15*$B$4 -> 5292.9677 | L15: =SUM(J15) -> 246 | M15: =L15*$B$4 -> 5292.9677 | N15: =SUM(L15) -> 246 | O15: =N15*$B$4 -> 5292.9677 | P15: =SUM(N15) -> 246 | Q15: =P15*$B$4 -> 5292.9677 | R15: =SUM(P15) -> 246 | S15: =R15*$B$4 -> 5292.9677 | T15: =SUM(R15) -> 246 | U15: =T15*$B$4 -> 5292.9677 | V15: =SUM(T15) -> 246 | W15: =V15*$B$4 -> 5292.9677 | X15: =SUM(Y15/73370) -> 0.79354839 | Y15: =SUM(C15+E15+G15+I15+K15+M15+O15+Q15+S15+U15+W15) -> 58222.645 | Z15: ='B5'!C14 -> 251 | AA15: =SUM(Z15*$Z$4) -> 2510 | AB15: =SUM(Z15) -> 251 | AC15: =SUM(AB15*$Z$4) -> 2510 | AD15: =SUM(AB15) -> 251 | AE15: =SUM(AD15*$Z$4) -> 2510 | AF15: =SUM(AD15) -> 251 | AG15: =SUM(AF15*$Z$4) -> 2510 | AH15: =SUM(AF15) -> 251 | AI15: =SUM(AH15*$Z$4) -> 2510 | AJ15: =SUM(AH15) -> 251 | AK15: =SUM(AJ15*$Z$4) -> 2510 | AL15: =SUM(AJ15) -> 251 | AM15: =SUM(AL15*$Z$4) -> 2510 | AN15: =SUM(AO15/19600) -> 0.89642857 | AO15: =SUM(AA15+AC15+AE15+AG15+AI15+AK15+AM15) -> 17570 | AQ15: =SUM(AR15/92970) -> 0.81523766 | AR15: =Y15+AO15 -> 75792.645 | AS15: =SUM(AR15-AR14-AT15) -> -1492.8387 | AT15: 15390 | AU15: 1.05 | AV15: =IF(AT15>0,AU15,AV14) -> 1.05 | AW15: =-SUM('B5'!AI14) -> -115 | AX15: =-SUM(AW15-AS15) -> -1377.8387 | AY15: =SUM(AX15+AW15) -> -1492.8387 | AZ15: =ELEC!A13 -> 0 | BA15: ='General information '!D15 -> 25 | BB15: =SUM('General information '!E15) -> 0.65 | BC15: =IF(AR14>=AR15,0,1) -> 1 | BD15: 19222 | BE15: =(305/1185)*ELEC!Q14 -> 3626.5401 | BG15: =#REF!-BE15 -> #REF! | BI15: 4 | BJ15: =AX15/BI15 -> -344.45968 | BK15: =GEN!AF12 -> 0.48253472
A16: =ELEC!C14 -> 44358 | B16: ='B5'!B15 -> 229 | C16: =B16*$B$4 -> 4927.1935 | D16: =SUM(B16) -> 229 | E16: =D16*$B$4 -> 4927.1935 | F16: =SUM(D16) -> 229 | G16: =F16*$B$4 -> 4927.1935 | H16: =SUM(F16) -> 229 | I16: =H16*$B$4 -> 4927.1935 | J16: =SUM(H16) -> 229 | K16: =J16*$B$4 -> 4927.1935 | L16: =SUM(J16) -> 229 | M16: =L16*$B$4 -> 4927.1935 | N16: =SUM(L16) -> 229 | O16: =N16*$B$4 -> 4927.1935 | P16: =SUM(N16) -> 229 | Q16: =P16*$B$4 -> 4927.1935 | R16: =SUM(P16) -> 229 | S16: =R16*$B$4 -> 4927.1935 | T16: =SUM(R16) -> 229 | U16: =T16*$B$4 -> 4927.1935 | V16: =SUM(T16) -> 229 | W16: =V16*$B$4 -> 4927.1935 | X16: =SUM(Y16/73370) -> 0.73870968 | Y16: =SUM(C16+E16+G16+I16+K16+M16+O16+Q16+S16+U16+W16) -> 54199.129 | Z16: ='B5'!C15 -> 236 | AA16: =SUM(Z16*$Z$4) -> 2360 | AB16: =SUM(Z16) -> 236 | AC16: =SUM(AB16*$Z$4) -> 2360 | AD16: =SUM(AB16) -> 236 | AE16: =SUM(AD16*$Z$4) -> 2360 | AF16: =SUM(AD16) -> 236 | AG16: =SUM(AF16*$Z$4) -> 2360 | AH16: =SUM(AF16) -> 236 | AI16: =SUM(AH16*$Z$4) -> 2360 | AJ16: =SUM(AH16) -> 236 | AK16: =SUM(AJ16*$Z$4) -> 2360 | AL16: =SUM(AJ16) -> 236 | AM16: =SUM(AL16*$Z$4) -> 2360 | AN16: =SUM(AO16/19600) -> 0.84285714 | AO16: =SUM(AA16+AC16+AE16+AG16+AI16+AK16+AM16) -> 16520 | AQ16: =SUM(AR16/92970) -> 0.76066612 | AR16: =Y16+AO16 -> 70719.129 | AS16: =SUM(AR16-AR15-AT16) -> -5073.5161 | AV16: =IF(AT16>0,AU16,AV15) -> 1.05 | AW16: =-SUM('B5'!AI15) -> -135 | AX16: =-SUM(AW16-AS16) -> -4938.5161 | AY16: =SUM(AX16+AW16) -> -5073.5161 | AZ16: =ELEC!A14 -> 0 | BA16: ='General information '!D16 -> 26 | BB16: =SUM('General information '!E16) -> 0.49 | BC16: =IF(AR15>=AR16,0,1) -> 0 | BD16: 19222 | BE16: =(305/1185)*ELEC!Q15 -> 2947.0464 | BG16: =#REF!-BE16 -> #REF! | BI16: 3 | BJ16: =AX16/BI16 -> -1646.172 | BK16: =GEN!AF13 -> 0.4403125
A17: =ELEC!C15 -> 44359 | B17: ='B5'!B16 -> 219 | C17: =B17*$B$4 -> 4712.0323 | D17: =SUM(B17) -> 219 | E17: =D17*$B$4 -> 4712.0323 | F17: =SUM(D17) -> 219 | G17: =F17*$B$4 -> 4712.0323 | H17: =SUM(F17) -> 219 | I17: =H17*$B$4 -> 4712.0323 | J17: =SUM(H17) -> 219 | K17: =J17*$B$4 -> 4712.0323 | L17: =SUM(J17) -> 219 | M17: =L17*$B$4 -> 4712.0323 | N17: =SUM(L17) -> 219 | O17: =N17*$B$4 -> 4712.0323 | P17: =SUM(N17) -> 219 | Q17: =P17*$B$4 -> 4712.0323 | R17: =SUM(P17) -> 219 | S17: =R17*$B$4 -> 4712.0323 | T17: =SUM(R17) -> 219 | U17: =T17*$B$4 -> 4712.0323 | V17: =SUM(T17) -> 219 | W17: =V17*$B$4 -> 4712.0323 | X17: =SUM(Y17/73370) -> 0.70645161 | Y17: =SUM(C17+E17+G17+I17+K17+M17+O17+Q17+S17+U17+W17) -> 51832.355 | Z17: ='B5'!C16 -> 225 | AA17: =SUM(Z17*$Z$4) -> 2250 | AB17: =SUM(Z17) -> 225 | AC17: =SUM(AB17*$Z$4) -> 2250 | AD17: =SUM(AB17) -> 225 | AE17: =SUM(AD17*$Z$4) -> 2250 | AF17: =SUM(AD17) -> 225 | AG17: =SUM(AF17*$Z$4) -> 2250 | AH17: =SUM(AF17) -> 225 | AI17: =SUM(AH17*$Z$4) -> 2250 | AJ17: =SUM(AH17) -> 225 | AK17: =SUM(AJ17*$Z$4) -> 2250 | AL17: =SUM(AJ17) -> 225 | AM17: =SUM(AL17*$Z$4) -> 2250 | AN17: =SUM(AO17/19600) -> 0.80357143 | AO17: =SUM(AA17+AC17+AE17+AG17+AI17+AK17+AM17) -> 15750 | AQ17: =SUM(AR17/92970) -> 0.72692648 | AR17: =Y17+AO17 -> 67582.355 | AS17: =SUM(AR17-AR16-AT17) -> -3136.7742 | AV17: =IF(AT17>0,AU17,AV16) -> 1.05 | AW17: =-SUM('B5'!AI16) -> -200 | AX17: =-SUM(AW17-AS17) -> -2936.7742 | AY17: =SUM(AX17+AW17) -> -3136.7742 | AZ17: =ELEC!A15 -> 0 | BA17: ='General information '!D17 -> 24.5 | BB17: =SUM('General information '!E17) -> 0.67 | BC17: =IF(AR16>=AR17,0,1) -> 0 | BD17: 19222 | BE17: =(305/1185)*ELEC!Q16 -> 3414.9705 | BG17: =#REF!-BE17 -> #REF!
A18: =ELEC!C16 -> 44360 | B18: ='B5'!B17 -> 204 | C18: =B18*$B$4 -> 4389.2903 | D18: =SUM(B18) -> 204 | E18: =D18*$B$4 -> 4389.2903 | F18: =SUM(D18) -> 204 | G18: =F18*$B$4 -> 4389.2903 | H18: =SUM(F18) -> 204 | I18: =H18*$B$4 -> 4389.2903 | J18: =SUM(H18) -> 204 | K18: =J18*$B$4 -> 4389.2903 | L18: =SUM(J18) -> 204 | M18: =L18*$B$4 -> 4389.2903 | N18: =SUM(L18) -> 204 | O18: =N18*$B$4 -> 4389.2903 | P18: =SUM(N18) -> 204 | Q18: =P18*$B$4 -> 4389.2903 | R18: =SUM(P18) -> 204 | S18: =R18*$B$4 -> 4389.2903 | T18: =SUM(R18) -> 204 | U18: =T18*$B$4 -> 4389.2903 | V18: =SUM(T18) -> 204 | W18: =V18*$B$4 -> 4389.2903 | X18: =SUM(Y18/73370) -> 0.65806452 | Y18: =SUM(C18+E18+G18+I18+K18+M18+O18+Q18+S18+U18+W18) -> 48282.194 | Z18: ='B5'!C17 -> 211 | AA18: =SUM(Z18*$Z$4) -> 2110 | AB18: =SUM(Z18) -> 211 | AC18: =SUM(AB18*$Z$4) -> 2110 | AD18: =SUM(AB18) -> 211 | AE18: =SUM(AD18*$Z$4) -> 2110 | AF18: =SUM(AD18) -> 211 | AG18: =SUM(AF18*$Z$4) -> 2110 | AH18: =SUM(AF18) -> 211 | AI18: =SUM(AH18*$Z$4) -> 2110 | AJ18: =SUM(AH18) -> 211 | AK18: =SUM(AJ18*$Z$4) -> 2110 | AL18: =SUM(AJ18) -> 211 | AM18: =SUM(AL18*$Z$4) -> 2110 | AN18: =SUM(AO18/19600) -> 0.75357143 | AO18: =SUM(AA18+AC18+AE18+AG18+AI18+AK18+AM18) -> 14770 | AQ18: =SUM(AR18/92970) -> 0.67819935 | AR18: =Y18+AO18 -> 63052.194 | AS18: =SUM(AR18-AR17-AT18) -> -4530.1613 | AV18: =IF(AT18>0,AU18,AV17) -> 1.05 | AW18: =-SUM('B5'!AI17) -> -48 | AX18: =-SUM(AW18-AS18) -> -4482.1613 | AY18: =SUM(AX18+AW18) -> -4530.1613 | AZ18: =ELEC!A16 -> 0 | BA18: ='General information '!D18 -> 23.5 | BB18: =SUM('General information '!E18) -> 0.7 | BC18: =IF(AR17>=AR18,0,1) -> 0 | BD18: 19222 | BE18: =(305/1185)*ELEC!Q17 -> 2211.9578 | BG18: =#REF!-BE18 -> #REF!
A19: =ELEC!C17 -> 44361 | B19: ='B5'!B18 -> 193 | C19: =B19*$B$4 -> 4152.6129 | D19: =SUM(B19) -> 193 | E19: =D19*$B$4 -> 4152.6129 | F19: =SUM(D19) -> 193 | G19: =F19*$B$4 -> 4152.6129 | H19: =SUM(F19) -> 193 | I19: =H19*$B$4 -> 4152.6129 | J19: =SUM(H19) -> 193 | K19: =J19*$B$4 -> 4152.6129 | L19: =SUM(J19) -> 193 | M19: =L19*$B$4 -> 4152.6129 | N19: =SUM(L19) -> 193 | O19: =N19*$B$4 -> 4152.6129 | P19: =SUM(N19) -> 193 | Q19: =P19*$B$4 -> 4152.6129 | R19: =SUM(P19) -> 193 | S19: =R19*$B$4 -> 4152.6129 | T19: =SUM(R19) -> 193 | U19: =T19*$B$4 -> 4152.6129 | V19: =SUM(T19) -> 193 | W19: =V19*$B$4 -> 4152.6129 | X19: =SUM(Y19/73370) -> 0.62258065 | Y19: =SUM(C19+E19+G19+I19+K19+M19+O19+Q19+S19+U19+W19) -> 45678.742 | Z19: ='B5'!C18 -> 199 | AA19: =SUM(Z19*$Z$4) -> 1990 | AB19: =SUM(Z19) -> 199 | AC19: =SUM(AB19*$Z$4) -> 1990 | AD19: =SUM(AB19) -> 199 | AE19: =SUM(AD19*$Z$4) -> 1990 | AF19: =SUM(AD19) -> 199 | AG19: =SUM(AF19*$Z$4) -> 1990 | AH19: =SUM(AF19) -> 199 | AI19: =SUM(AH19*$Z$4) -> 1990 | AJ19: =SUM(AH19) -> 199 | AK19: =SUM(AJ19*$Z$4) -> 1990 | AL19: =SUM(AJ19) -> 199 | AM19: =SUM(AL19*$Z$4) -> 1990 | AN19: =SUM(AO19/19600) -> 0.71071429 | AO19: =SUM(AA19+AC19+AE19+AG19+AI19+AK19+AM19) -> 13930 | AQ19: =SUM(AR19/92970) -> 0.64116104 | AR19: =Y19+AO19 -> 59608.742 | AS19: =SUM(AR19-AR18-AT19) -> -3443.4516 | AV19: =IF(AT19>0,AU19,AV18) -> 1.05 | AW19: =-SUM('B5'!AI18) -> -57 | AX19: =-SUM(AW19-AS19) -> -3386.4516 | AY19: =SUM(AX19+AW19) -> -3443.4516 | AZ19: =ELEC!A17 -> 0 | BA19: ='General information '!D19 -> 23 | BB19: =SUM('General information '!E19) -> 0.64 | BC19: =IF(AR18>=AR19,0,1) -> 0 | BD19: 19222 | BE19: =(305/1185)*ELEC!Q18 -> 3202.8861 | BG19: =#REF!-BE19 -> #REF!
A20: =ELEC!C18 -> 44362 | B20: ='B5'!B19 -> 225 | C20: =B20*$B$4 -> 4841.129 | D20: =SUM(B20) -> 225 | E20: =D20*$B$4 -> 4841.129 | F20: =SUM(D20) -> 225 | G20: =F20*$B$4 -> 4841.129 | H20: =SUM(F20) -> 225 | I20: =H20*$B$4 -> 4841.129 | J20: =SUM(H20) -> 225 | K20: =J20*$B$4 -> 4841.129 | L20: =SUM(J20) -> 225 | M20: =L20*$B$4 -> 4841.129 | N20: =SUM(L20) -> 225 | O20: =N20*$B$4 -> 4841.129 | P20: =SUM(N20) -> 225 | Q20: =P20*$B$4 -> 4841.129 | R20: =SUM(P20) -> 225 | S20: =R20*$B$4 -> 4841.129 | T20: =SUM(R20) -> 225 | U20: =T20*$B$4 -> 4841.129 | V20: =SUM(T20) -> 225 | W20: =V20*$B$4 -> 4841.129 | X20: =SUM(Y20/73370) -> 0.72580645 | Y20: =SUM(C20+E20+G20+I20+K20+M20+O20+Q20+S20+U20+W20) -> 53252.419 | Z20: ='B5'!C19 -> 231 | AA20: =SUM(Z20*$Z$4) -> 2310 | AB20: =SUM(Z20) -> 231 | AC20: =SUM(AB20*$Z$4) -> 2310 | AD20: =SUM(AB20) -> 231 | AE20: =SUM(AD20*$Z$4) -> 2310 | AF20: =SUM(AD20) -> 231 | AG20: =SUM(AF20*$Z$4) -> 2310 | AH20: =SUM(AF20) -> 231 | AI20: =SUM(AH20*$Z$4) -> 2310 | AJ20: =SUM(AH20) -> 231 | AK20: =SUM(AJ20*$Z$4) -> 2310 | AL20: =SUM(AJ20) -> 231 | AM20: =SUM(AL20*$Z$4) -> 2310 | AN20: =SUM(AO20/19600) -> 0.825 | AO20: =SUM(AA20+AC20+AE20+AG20+AI20+AK20+AM20) -> 16170 | AQ20: =SUM(AR20/92970) -> 0.7467185 | AR20: =Y20+AO20 -> 69422.419 | AS20: =SUM(AR20-AR19-AT20) -> -2246.3226 | AT20: 12060 | AU20: 1.05 | AV20: =IF(AT20>0,AU20,AV19) -> 1.05 | AW20: =-SUM('B5'!AI19) -> -184 | AX20: =-SUM(AW20-AS20) -> -2062.3226 | AY20: =SUM(AX20+AW20) -> -2246.3226 | AZ20: =ELEC!A18 -> 0 | BA20: ='General information '!D20 -> 24.5 | BB20: =SUM('General information '!E20) -> 0.61 | BC20: =IF(AR19>=AR20,0,1) -> 1 | BD20: 19222 | BE20: =(305/1185)*ELEC!Q19 -> 3416.7722 | BG20: =#REF!-BE20 -> #REF!
A21: =ELEC!C19 -> 44363 | B21: ='B5'!B20 -> 213 | C21: =B21*$B$4 -> 4582.9355 | D21: =SUM(B21) -> 213 | E21: =D21*$B$4 -> 4582.9355 | F21: =SUM(D21) -> 213 | G21: =F21*$B$4 -> 4582.9355 | H21: =SUM(F21) -> 213 | I21: =H21*$B$4 -> 4582.9355 | J21: =SUM(H21) -> 213 | K21: =J21*$B$4 -> 4582.9355 | L21: =SUM(J21) -> 213 | M21: =L21*$B$4 -> 4582.9355 | N21: =SUM(L21) -> 213 | O21: =N21*$B$4 -> 4582.9355 | P21: =SUM(N21) -> 213 | Q21: =P21*$B$4 -> 4582.9355 | R21: =SUM(P21) -> 213 | S21: =R21*$B$4 -> 4582.9355 | T21: =SUM(R21) -> 213 | U21: =T21*$B$4 -> 4582.9355 | V21: =SUM(T21) -> 213 | W21: =V21*$B$4 -> 4582.9355 | X21: =SUM(Y21/73370) -> 0.68709677 | Y21: =SUM(C21+E21+G21+I21+K21+M21+O21+Q21+S21+U21+W21) -> 50412.29 | Z21: ='B5'!C20 -> 219 | AA21: =SUM(Z21*$Z$4) -> 2190 | AB21: =SUM(Z21) -> 219 | AC21: =SUM(AB21*$Z$4) -> 2190 | AD21: =SUM(AB21) -> 219 | AE21: =SUM(AD21*$Z$4) -> 2190 | AF21: =SUM(AD21) -> 219 | AG21: =SUM(AF21*$Z$4) -> 2190 | AH21: =SUM(AF21) -> 219 | AI21: =SUM(AH21*$Z$4) -> 2190 | AJ21: =SUM(AH21) -> 219 | AK21: =SUM(AJ21*$Z$4) -> 2190 | AL21: =SUM(AJ21) -> 219 | AM21: =SUM(AL21*$Z$4) -> 2190 | AN21: =SUM(AO21/19600) -> 0.78214286 | AO21: =SUM(AA21+AC21+AE21+AG21+AI21+AK21+AM21) -> 15330 | AQ21: =SUM(AR21/92970) -> 0.70713446 | AR21: =Y21+AO21 -> 65742.29 | AS21: =SUM(AR21-AR20-AT21) -> -3680.129 | AV21: =IF(AT21>0,AU21,AV20) -> 1.05 | AW21: =-SUM('B5'!AI20) -> -82 | AX21: =-SUM(AW21-AS21) -> -3598.129 | AY21: =SUM(AX21+AW21) -> -3680.129 | AZ21: =ELEC!A19 -> 0 | BA21: ='General information '!D21 -> 25 | BB21: =SUM('General information '!E21) -> 0.67 | BC21: =IF(AR20>=AR21,0,1) -> 0 | BD21: 19222 | BE21: =(305/1185)*ELEC!Q20 -> 2593.6582 | BG21: =#REF!-BE21 -> #REF!
A22: =ELEC!C20 -> 44364 | B22: ='B5'!B21 -> 199 | C22: =B22*$B$4 -> 4281.7097 | D22: =SUM(B22) -> 199 | E22: =D22*$B$4 -> 4281.7097 | F22: =SUM(D22) -> 199 | G22: =F22*$B$4 -> 4281.7097 | H22: =SUM(F22) -> 199 | I22: =H22*$B$4 -> 4281.7097 | J22: =SUM(H22) -> 199 | K22: =J22*$B$4 -> 4281.7097 | L22: =SUM(J22) -> 199 | M22: =L22*$B$4 -> 4281.7097 | N22: =SUM(L22) -> 199 | O22: =N22*$B$4 -> 4281.7097 | P22: =SUM(N22) -> 199 | Q22: =P22*$B$4 -> 4281.7097 | R22: =SUM(P22) -> 199 | S22: =R22*$B$4 -> 4281.7097 | T22: =SUM(R22) -> 199 | U22: =T22*$B$4 -> 4281.7097 | V22: =SUM(T22) -> 199 | W22: =V22*$B$4 -> 4281.7097 | X22: =SUM(Y22/73370) -> 0.64193548 | Y22: =SUM(C22+E22+G22+I22+K22+M22+O22+Q22+S22+U22+W22) -> 47098.806 | Z22: ='B5'!C21 -> 206 | AA22: =SUM(Z22*$Z$4) -> 2060 | AB22: =SUM(Z22) -> 206 | AC22: =SUM(AB22*$Z$4) -> 2060 | AD22: =SUM(AB22) -> 206 | AE22: =SUM(AD22*$Z$4) -> 2060 | AF22: =SUM(AD22) -> 206 | AG22: =SUM(AF22*$Z$4) -> 2060 | AH22: =SUM(AF22) -> 206 | AI22: =SUM(AH22*$Z$4) -> 2060 | AJ22: =SUM(AH22) -> 206 | AK22: =SUM(AJ22*$Z$4) -> 2060 | AL22: =SUM(AJ22) -> 206 | AM22: =SUM(AL22*$Z$4) -> 2060 | AN22: =SUM(AO22/19600) -> 0.73571429 | AO22: =SUM(AA22+AC22+AE22+AG22+AI22+AK22+AM22) -> 14420 | AQ22: =SUM(AR22/92970) -> 0.661706 | AR22: =Y22+AO22 -> 61518.806 | AS22: =SUM(AR22-AR21-AT22) -> -4223.4839 | AV22: =IF(AT22>0,AU22,AV21) -> 1.05 | AW22: =-SUM('B5'!AI21) -> -139 | AX22: =-SUM(AW22-AS22) -> -4084.4839 | AY22: =SUM(AX22+AW22) -> -4223.4839 | AZ22: =ELEC!A20 -> 0 | BA22: ='General information '!D22 -> 24.5 | BB22: =SUM('General information '!E22) -> 0.65 | BC22: =IF(AR21>=AR22,0,1) -> 0 | BD22: 19222 | BE22: =(305/1185)*ELEC!Q21 -> 0 | BG22: =#REF!-BE22 -> #REF!
A23: =ELEC!C21 -> 44365 | B23: ='B5'!B22 -> 199 | C23: =B23*$B$4 -> 4281.7097 | D23: =SUM(B23) -> 199 | E23: =D23*$B$4 -> 4281.7097 | F23: =SUM(D23) -> 199 | G23: =F23*$B$4 -> 4281.7097 | H23: =SUM(F23) -> 199 | I23: =H23*$B$4 -> 4281.7097 | J23: =SUM(H23) -> 199 | K23: =J23*$B$4 -> 4281.7097 | L23: =SUM(J23) -> 199 | M23: =L23*$B$4 -> 4281.7097 | N23: =SUM(L23) -> 199 | O23: =N23*$B$4 -> 4281.7097 | P23: =SUM(N23) -> 199 | Q23: =P23*$B$4 -> 4281.7097 | R23: =SUM(P23) -> 199 | S23: =R23*$B$4 -> 4281.7097 | T23: =SUM(R23) -> 199 | U23: =T23*$B$4 -> 4281.7097 | V23: =SUM(T23) -> 199 | W23: =V23*$B$4 -> 4281.7097 | X23: =SUM(Y23/73370) -> 0.64193548 | Y23: =SUM(C23+E23+G23+I23+K23+M23+O23+Q23+S23+U23+W23) -> 47098.806 | Z23: ='B5'!C22 -> 206 | AA23: =SUM(Z23*$Z$4) -> 2060 | AB23: =SUM(Z23) -> 206 | AC23: =SUM(AB23*$Z$4) -> 2060 | AD23: =SUM(AB23) -> 206 | AE23: =SUM(AD23*$Z$4) -> 2060 | AF23: =SUM(AD23) -> 206 | AG23: =SUM(AF23*$Z$4) -> 2060 | AH23: =SUM(AF23) -> 206 | AI23: =SUM(AH23*$Z$4) -> 2060 | AJ23: =SUM(AH23) -> 206 | AK23: =SUM(AJ23*$Z$4) -> 2060 | AL23: =SUM(AJ23) -> 206 | AM23: =SUM(AL23*$Z$4) -> 2060 | AN23: =SUM(AO23/19600) -> 0.73571429 | AO23: =SUM(AA23+AC23+AE23+AG23+AI23+AK23+AM23) -> 14420 | AQ23: =SUM(AR23/92970) -> 0.661706 | AR23: =Y23+AO23 -> 61518.806 | AS23: =SUM(AR23-AR22-AT23) -> 0 | AV23: =IF(AT23>0,AU23,AV22) -> 1.05 | AW23: =-SUM('B5'!AI22) -> 0 | AX23: =-SUM(AW23-AS23) -> 0 | AY23: =SUM(AX23+AW23) -> 0 | AZ23: =ELEC!A21 -> 0 | BA23: ='General information '!D23 -> 0 | BB23: =SUM('General information '!E23) -> 0 | BC23: =IF(AR22>=AR23,0,1) -> 0 | BD23: 19222 | BE23: =(305/1185)*ELEC!Q22 -> 0 | BG23: =#REF!-BE23 -> #REF!
A24: =ELEC!C22 -> 44366 | B24: ='B5'!B23 -> 199 | C24: =B24*$B$4 -> 4281.7097 | D24: =SUM(B24) -> 199 | E24: =D24*$B$4 -> 4281.7097 | F24: =SUM(D24) -> 199 | G24: =F24*$B$4 -> 4281.7097 | H24: =SUM(F24) -> 199 | I24: =H24*$B$4 -> 4281.7097 | J24: =SUM(H24) -> 199 | K24: =J24*$B$4 -> 4281.7097 | L24: =SUM(J24) -> 199 | M24: =L24*$B$4 -> 4281.7097 | N24: =SUM(L24) -> 199 | O24: =N24*$B$4 -> 4281.7097 | P24: =SUM(N24) -> 199 | Q24: =P24*$B$4 -> 4281.7097 | R24: =SUM(P24) -> 199 | S24: =R24*$B$4 -> 4281.7097 | T24: =SUM(R24) -> 199 | U24: =T24*$B$4 -> 4281.7097 | V24: =SUM(T24) -> 199 | W24: =V24*$B$4 -> 4281.7097 | X24: =SUM(Y24/73370) -> 0.64193548 | Y24: =SUM(C24+E24+G24+I24+K24+M24+O24+Q24+S24+U24+W24) -> 47098.806 | Z24: ='B5'!C23 -> 206 | AA24: =SUM(Z24*$Z$4) -> 2060 | AB24: =SUM(Z24) -> 206 | AC24: =SUM(AB24*$Z$4) -> 2060 | AD24: =SUM(AB24) -> 206 | AE24: =SUM(AD24*$Z$4) -> 2060 | AF24: =SUM(AD24) -> 206 | AG24: =SUM(AF24*$Z$4) -> 2060 | AH24: =SUM(AF24) -> 206 | AI24: =SUM(AH24*$Z$4) -> 2060 | AJ24: =SUM(AH24) -> 206 | AK24: =SUM(AJ24*$Z$4) -> 2060 | AL24: =SUM(AJ24) -> 206 | AM24: =SUM(AL24*$Z$4) -> 2060 | AN24: =SUM(AO24/19600) -> 0.73571429 | AO24: =SUM(AA24+AC24+AE24+AG24+AI24+AK24+AM24) -> 14420 | AQ24: =SUM(AR24/92970) -> 0.661706 | AR24: =Y24+AO24 -> 61518.806 | AS24: =SUM(AR24-AR23-AT24) -> 0 | AV24: =IF(AT24>0,AU24,AV23) -> 1.05 | AW24: =-SUM('B5'!AI23) -> 0 | AX24: =-SUM(AW24-AS24) -> 0 | AY24: =SUM(AX24+AW24) -> 0 | AZ24: =ELEC!A22 -> 0 | BA24: ='General information '!D24 -> 0 | BB24: =SUM('General information '!E24) -> 0 | BC24: =IF(AR23>=AR24,0,1) -> 0 | BD24: 19222 | BE24: =(305/1185)*ELEC!Q23 -> 0 | BG24: =#REF!-BE24 -> #REF!
A25: =ELEC!C23 -> 44367 | B25: ='B5'!B24 -> 199 | C25: =B25*$B$4 -> 4281.7097 | D25: =SUM(B25) -> 199 | E25: =D25*$B$4 -> 4281.7097 | F25: =SUM(D25) -> 199 | G25: =F25*$B$4 -> 4281.7097 | H25: =SUM(F25) -> 199 | I25: =H25*$B$4 -> 4281.7097 | J25: =SUM(H25) -> 199 | K25: =J25*$B$4 -> 4281.7097 | L25: =SUM(J25) -> 199 | M25: =L25*$B$4 -> 4281.7097 | N25: =SUM(L25) -> 199 | O25: =N25*$B$4 -> 4281.7097 | P25: =SUM(N25) -> 199 | Q25: =P25*$B$4 -> 4281.7097 | R25: =SUM(P25) -> 199 | S25: =R25*$B$4 -> 4281.7097 | T25: =SUM(R25) -> 199 | U25: =T25*$B$4 -> 4281.7097 | V25: =SUM(T25) -> 199 | W25: =V25*$B$4 -> 4281.7097 | X25: =SUM(Y25/73370) -> 0.64193548 | Y25: =SUM(C25+E25+G25+I25+K25+M25+O25+Q25+S25+U25+W25) -> 47098.806 | Z25: ='B5'!C24 -> 206 | AA25: =SUM(Z25*$Z$4) -> 2060 | AB25: =SUM(Z25) -> 206 | AC25: =SUM(AB25*$Z$4) -> 2060 | AD25: =SUM(AB25) -> 206 | AE25: =SUM(AD25*$Z$4) -> 2060 | AF25: =SUM(AD25) -> 206 | AG25: =SUM(AF25*$Z$4) -> 2060 | AH25: =SUM(AF25) -> 206 | AI25: =SUM(AH25*$Z$4) -> 2060 | AJ25: =SUM(AH25) -> 206 | AK25: =SUM(AJ25*$Z$4) -> 2060 | AL25: =SUM(AJ25) -> 206 | AM25: =SUM(AL25*$Z$4) -> 2060 | AN25: =SUM(AO25/19600) -> 0.73571429 | AO25: =SUM(AA25+AC25+AE25+AG25+AI25+AK25+AM25) -> 14420 | AQ25: =SUM(AR25/92970) -> 0.661706 | AR25: =Y25+AO25 -> 61518.806 | AS25: =SUM(AR25-AR24-AT25) -> 0 | AV25: =IF(AT25>0,AU25,AV24) -> 1.05 | AW25: =-SUM('B5'!AI24) -> 0 | AX25: =-SUM(AW25-AS25) -> 0 | AY25: =SUM(AX25+AW25) -> 0 | AZ25: =ELEC!A23 -> 0 | BA25: ='General information '!D25 -> 0 | BB25: =SUM('General information '!E25) -> 0 | BC25: =IF(AR24>=AR25,0,1) -> 0 | BD25: 19222 | BE25: =(305/1185)*ELEC!Q24 -> 0 | BG25: =#REF!-BE25 -> #REF!
A26: =ELEC!C24 -> 44368 | B26: ='B5'!B25 -> 199 | C26: =B26*$B$4 -> 4281.7097 | D26: =SUM(B26) -> 199 | E26: =D26*$B$4 -> 4281.7097 | F26: =SUM(D26) -> 199 | G26: =F26*$B$4 -> 4281.7097 | H26: =SUM(F26) -> 199 | I26: =H26*$B$4 -> 4281.7097 | J26: =SUM(H26) -> 199 | K26: =J26*$B$4 -> 4281.7097 | L26: =SUM(J26) -> 199 | M26: =L26*$B$4 -> 4281.7097 | N26: =SUM(L26) -> 199 | O26: =N26*$B$4 -> 4281.7097 | P26: =SUM(N26) -> 199 | Q26: =P26*$B$4 -> 4281.7097 | R26: =SUM(P26) -> 199 | S26: =R26*$B$4 -> 4281.7097 | T26: =SUM(R26) -> 199 | U26: =T26*$B$4 -> 4281.7097 | V26: =SUM(T26) -> 199 | W26: =V26*$B$4 -> 4281.7097 | X26: =SUM(Y26/73370) -> 0.64193548 | Y26: =SUM(C26+E26+G26+I26+K26+M26+O26+Q26+S26+U26+W26) -> 47098.806 | Z26: ='B5'!C25 -> 206 | AA26: =SUM(Z26*$Z$4) -> 2060 | AB26: =SUM(Z26) -> 206 | AC26: =SUM(AB26*$Z$4) -> 2060 | AD26: =SUM(AB26) -> 206 | AE26: =SUM(AD26*$Z$4) -> 2060 | AF26: =SUM(AD26) -> 206 | AG26: =SUM(AF26*$Z$4) -> 2060 | AH26: =SUM(AF26) -> 206 | AI26: =SUM(AH26*$Z$4) -> 2060 | AJ26: =SUM(AH26) -> 206 | AK26: =SUM(AJ26*$Z$4) -> 2060 | AL26: =SUM(AJ26) -> 206 | AM26: =SUM(AL26*$Z$4) -> 2060 | AN26: =SUM(AO26/19600) -> 0.73571429 | AO26: =SUM(AA26+AC26+AE26+AG26+AI26+AK26+AM26) -> 14420 | AQ26: =SUM(AR26/92970) -> 0.661706 | AR26: =Y26+AO26 -> 61518.806 | AS26: =SUM(AR26-AR25-AT26) -> 0 | AV26: =IF(AT26>0,AU26,AV25) -> 1.05 | AW26: =-SUM('B5'!AI25) -> 0 | AX26: =-SUM(AW26-AS26) -> 0 | AY26: =SUM(AX26+AW26) -> 0 | AZ26: =ELEC!A24 -> 0 | BA26: ='General information '!D26 -> 0 | BB26: =SUM('General information '!E26) -> 0 | BC26: =IF(AR25>=AR26,0,1) -> 0 | BD26: 19222 | BE26: =(305/1185)*ELEC!Q25 -> 0 | BG26: =#REF!-BE26 -> #REF!
A27: =ELEC!C25 -> 44369 | B27: ='B5'!B26 -> 199 | C27: =B27*$B$4 -> 4281.7097 | D27: =SUM(B27) -> 199 | E27: =D27*$B$4 -> 4281.7097 | F27: =SUM(D27) -> 199 | G27: =F27*$B$4 -> 4281.7097 | H27: =SUM(F27) -> 199 | I27: =H27*$B$4 -> 4281.7097 | J27: =SUM(H27) -> 199 | K27: =J27*$B$4 -> 4281.7097 | L27: =SUM(J27) -> 199 | M27: =L27*$B$4 -> 4281.7097 | N27: =SUM(L27) -> 199 | O27: =N27*$B$4 -> 4281.7097 | P27: =SUM(N27) -> 199 | Q27: =P27*$B$4 -> 4281.7097 | R27: =SUM(P27) -> 199 | S27: =R27*$B$4 -> 4281.7097 | T27: =SUM(R27) -> 199 | U27: =T27*$B$4 -> 4281.7097 | V27: =SUM(T27) -> 199 | W27: =V27*$B$4 -> 4281.7097 | X27: =SUM(Y27/73370) -> 0.64193548 | Y27: =SUM(C27+E27+G27+I27+K27+M27+O27+Q27+S27+U27+W27) -> 47098.806 | Z27: ='B5'!C26 -> 206 | AA27: =SUM(Z27*$Z$4) -> 2060 | AB27: =SUM(Z27) -> 206 | AC27: =SUM(AB27*$Z$4) -> 2060 | AD27: =SUM(AB27) -> 206 | AE27: =SUM(AD27*$Z$4) -> 2060 | AF27: =SUM(AD27) -> 206 | AG27: =SUM(AF27*$Z$4) -> 2060 | AH27: =SUM(AF27) -> 206 | AI27: =SUM(AH27*$Z$4) -> 2060 | AJ27: =SUM(AH27) -> 206 | AK27: =SUM(AJ27*$Z$4) -> 2060 | AL27: =SUM(AJ27) -> 206 | AM27: =SUM(AL27*$Z$4) -> 2060 | AN27: =SUM(AO27/19600) -> 0.73571429 | AO27: =SUM(AA27+AC27+AE27+AG27+AI27+AK27+AM27) -> 14420 | AQ27: =SUM(AR27/92970) -> 0.661706 | AR27: =Y27+AO27 -> 61518.806 | AS27: =SUM(AR27-AR26-AT27) -> 0 | AV27: =IF(AT27>0,AU27,AV26) -> 1.05 | AW27: =-SUM('B5'!AI26) -> 0 | AX27: =-SUM(AW27-AS27) -> 0 | AY27: =SUM(AX27+AW27) -> 0 | AZ27: =ELEC!A25 -> 0 | BA27: ='General information '!D27 -> 0 | BB27: =SUM('General information '!E27) -> 0 | BC27: =IF(AR26>=AR27,0,1) -> 0 | BD27: 19222 | BE27: =(305/1185)*ELEC!Q26 -> 0 | BG27: =#REF!-BE27 -> #REF!
A28: =ELEC!C26 -> 44370 | B28: ='B5'!B27 -> 199 | C28: =B28*$B$4 -> 4281.7097 | D28: =SUM(B28) -> 199 | E28: =D28*$B$4 -> 4281.7097 | F28: =SUM(D28) -> 199 | G28: =F28*$B$4 -> 4281.7097 | H28: =SUM(F28) -> 199 | I28: =H28*$B$4 -> 4281.7097 | J28: =SUM(H28) -> 199 | K28: =J28*$B$4 -> 4281.7097 | L28: =SUM(J28) -> 199 | M28: =L28*$B$4 -> 4281.7097 | N28: =SUM(L28) -> 199 | O28: =N28*$B$4 -> 4281.7097 | P28: =SUM(N28) -> 199 | Q28: =P28*$B$4 -> 4281.7097 | R28: =SUM(P28) -> 199 | S28: =R28*$B$4 -> 4281.7097 | T28: =SUM(R28) -> 199 | U28: =T28*$B$4 -> 4281.7097 | V28: =SUM(T28) -> 199 | W28: =V28*$B$4 -> 4281.7097 | X28: =SUM(Y28/73370) -> 0.64193548 | Y28: =SUM(C28+E28+G28+I28+K28+M28+O28+Q28+S28+U28+W28) -> 47098.806 | Z28: ='B5'!C27 -> 206 | AA28: =SUM(Z28*$Z$4) -> 2060 | AB28: =SUM(Z28) -> 206 | AC28: =SUM(AB28*$Z$4) -> 2060 | AD28: =SUM(AB28) -> 206 | AE28: =SUM(AD28*$Z$4) -> 2060 | AF28: =SUM(AD28) -> 206 | AG28: =SUM(AF28*$Z$4) -> 2060 | AH28: =SUM(AF28) -> 206 | AI28: =SUM(AH28*$Z$4) -> 2060 | AJ28: =SUM(AH28) -> 206 | AK28: =SUM(AJ28*$Z$4) -> 2060 | AL28: =SUM(AJ28) -> 206 | AM28: =SUM(AL28*$Z$4) -> 2060 | AN28: =SUM(AO28/19600) -> 0.73571429 | AO28: =SUM(AA28+AC28+AE28+AG28+AI28+AK28+AM28) -> 14420 | AQ28: =SUM(AR28/92970) -> 0.661706 | AR28: =Y28+AO28 -> 61518.806 | AS28: =SUM(AR28-AR27-AT28) -> 0 | AV28: =IF(AT28>0,AU28,AV27) -> 1.05 | AW28: =-SUM('B5'!AI27) -> 0 | AX28: =-SUM(AW28-AS28) -> 0 | AY28: =SUM(AX28+AW28) -> 0 | AZ28: =ELEC!A26 -> 0 | BA28: ='General information '!D28 -> 0 | BB28: =SUM('General information '!E28) -> 0 | BC28: =IF(AR27>=AR28,0,1) -> 0 | BD28: 19222 | BE28: =(305/1185)*ELEC!Q27 -> 0 | BG28: =#REF!-BE28 -> #REF!
A29: =ELEC!C27 -> 44371 | B29: ='B5'!B28 -> 199 | C29: =B29*$B$4 -> 4281.7097 | D29: =SUM(B29) -> 199 | E29: =D29*$B$4 -> 4281.7097 | F29: =SUM(D29) -> 199 | G29: =F29*$B$4 -> 4281.7097 | H29: =SUM(F29) -> 199 | I29: =H29*$B$4 -> 4281.7097 | J29: =SUM(H29) -> 199 | K29: =J29*$B$4 -> 4281.7097 | L29: =SUM(J29) -> 199 | M29: =L29*$B$4 -> 4281.7097 | N29: =SUM(L29) -> 199 | O29: =N29*$B$4 -> 4281.7097 | P29: =SUM(N29) -> 199 | Q29: =P29*$B$4 -> 4281.7097 | R29: =SUM(P29) -> 199 | S29: =R29*$B$4 -> 4281.7097 | T29: =SUM(R29) -> 199 | U29: =T29*$B$4 -> 4281.7097 | V29: =SUM(T29) -> 199 | W29: =V29*$B$4 -> 4281.7097 | X29: =SUM(Y29/73370) -> 0.64193548 | Y29: =SUM(C29+E29+G29+I29+K29+M29+O29+Q29+S29+U29+W29) -> 47098.806 | Z29: ='B5'!C28 -> 206 | AA29: =SUM(Z29*$Z$4) -> 2060 | AB29: =SUM(Z29) -> 206 | AC29: =SUM(AB29*$Z$4) -> 2060 | AD29: =SUM(AB29) -> 206 | AE29: =SUM(AD29*$Z$4) -> 2060 | AF29: =SUM(AD29) -> 206 | AG29: =SUM(AF29*$Z$4) -> 2060 | AH29: =SUM(AF29) -> 206 | AI29: =SUM(AH29*$Z$4) -> 2060 | AJ29: =SUM(AH29) -> 206 | AK29: =SUM(AJ29*$Z$4) -> 2060 | AL29: =SUM(AJ29) -> 206 | AM29: =SUM(AL29*$Z$4) -> 2060 | AN29: =SUM(AO29/19600) -> 0.73571429 | AO29: =SUM(AA29+AC29+AE29+AG29+AI29+AK29+AM29) -> 14420 | AQ29: =SUM(AR29/92970) -> 0.661706 | AR29: =Y29+AO29 -> 61518.806 | AS29: =SUM(AR29-AR28-AT29) -> 0 | AV29: =IF(AT29>0,AU29,AV28) -> 1.05 | AW29: =-SUM('B5'!AI28) -> 0 | AX29: =-SUM(AW29-AS29) -> 0 | AY29: =SUM(AX29+AW29) -> 0 | AZ29: =ELEC!A27 -> 0 | BA29: ='General information '!D29 -> 0 | BB29: =SUM('General information '!E29) -> 0 | BC29: =IF(AR28>=AR29,0,1) -> 0 | BD29: 19222 | BE29: =(305/1185)*ELEC!Q28 -> 0 | BG29: =#REF!-BE29 -> #REF!
A30: =ELEC!C28 -> 44372 | B30: ='B5'!B29 -> 199 | C30: =B30*$B$4 -> 4281.7097 | D30: =SUM(B30) -> 199 | E30: =D30*$B$4 -> 4281.7097 | F30: =SUM(D30) -> 199 | G30: =F30*$B$4 -> 4281.7097 | H30: =SUM(F30) -> 199 | I30: =H30*$B$4 -> 4281.7097 | J30: =SUM(H30) -> 199 | K30: =J30*$B$4 -> 4281.7097 | L30: =SUM(J30) -> 199 | M30: =L30*$B$4 -> 4281.7097 | N30: =SUM(L30) -> 199 | O30: =N30*$B$4 -> 4281.7097 | P30: =SUM(N30) -> 199 | Q30: =P30*$B$4 -> 4281.7097 | R30: =SUM(P30) -> 199 | S30: =R30*$B$4 -> 4281.7097 | T30: =SUM(R30) -> 199 | U30: =T30*$B$4 -> 4281.7097 | V30: =SUM(T30) -> 199 | W30: =V30*$B$4 -> 4281.7097 | X30: =SUM(Y30/73370) -> 0.64193548 | Y30: =SUM(C30+E30+G30+I30+K30+M30+O30+Q30+S30+U30+W30) -> 47098.806 | Z30: ='B5'!C29 -> 206 | AA30: =SUM(Z30*$Z$4) -> 2060 | AB30: =SUM(Z30) -> 206 | AC30: =SUM(AB30*$Z$4) -> 2060 | AD30: =SUM(AB30) -> 206 | AE30: =SUM(AD30*$Z$4) -> 2060 | AF30: =SUM(AD30) -> 206 | AG30: =SUM(AF30*$Z$4) -> 2060 | AH30: =SUM(AF30) -> 206 | AI30: =SUM(AH30*$Z$4) -> 2060 | AJ30: =SUM(AH30) -> 206 | AK30: =SUM(AJ30*$Z$4) -> 2060 | AL30: =SUM(AJ30) -> 206 | AM30: =SUM(AL30*$Z$4) -> 2060 | AN30: =SUM(AO30/19600) -> 0.73571429 | AO30: =SUM(AA30+AC30+AE30+AG30+AI30+AK30+AM30) -> 14420 | AQ30: =SUM(AR30/92970) -> 0.661706 | AR30: =Y30+AO30 -> 61518.806 | AS30: =SUM(AR30-AR29-AT30) -> 0 | AV30: =IF(AT30>0,AU30,AV29) -> 1.05 | AW30: =-SUM('B5'!AI29) -> 0 | AX30: =-SUM(AW30-AS30) -> 0 | AY30: =SUM(AX30+AW30) -> 0 | AZ30: =ELEC!A28 -> 0 | BA30: ='General information '!D30 -> 0 | BB30: =SUM('General information '!E30) -> 0 | BC30: =IF(AR29>=AR30,0,1) -> 0 | BD30: 19222 | BE30: =(305/1185)*ELEC!Q29 -> 0 | BG30: =#REF!-BE30 -> #REF!
A31: =ELEC!C29 -> 44373 | B31: ='B5'!B30 -> 199 | C31: =B31*$B$4 -> 4281.7097 | D31: =SUM(B31) -> 199 | E31: =D31*$B$4 -> 4281.7097 | F31: =SUM(D31) -> 199 | G31: =F31*$B$4 -> 4281.7097 | H31: =SUM(F31) -> 199 | I31: =H31*$B$4 -> 4281.7097 | J31: =SUM(H31) -> 199 | K31: =J31*$B$4 -> 4281.7097 | L31: =SUM(J31) -> 199 | M31: =L31*$B$4 -> 4281.7097 | N31: =SUM(L31) -> 199 | O31: =N31*$B$4 -> 4281.7097 | P31: =SUM(N31) -> 199 | Q31: =P31*$B$4 -> 4281.7097 | R31: =SUM(P31) -> 199 | S31: =R31*$B$4 -> 4281.7097 | T31: =SUM(R31) -> 199 | U31: =T31*$B$4 -> 4281.7097 | V31: =SUM(T31) -> 199 | W31: =V31*$B$4 -> 4281.7097 | X31: =SUM(Y31/73370) -> 0.64193548 | Y31: =SUM(C31+E31+G31+I31+K31+M31+O31+Q31+S31+U31+W31) -> 47098.806 | Z31: ='B5'!C30 -> 206 | AA31: =SUM(Z31*$Z$4) -> 2060 | AB31: =SUM(Z31) -> 206 | AC31: =SUM(AB31*$Z$4) -> 2060 | AD31: =SUM(AB31) -> 206 | AE31: =SUM(AD31*$Z$4) -> 2060 | AF31: =SUM(AD31) -> 206 | AG31: =SUM(AF31*$Z$4) -> 2060 | AH31: =SUM(AF31) -> 206 | AI31: =SUM(AH31*$Z$4) -> 2060 | AJ31: =SUM(AH31) -> 206 | AK31: =SUM(AJ31*$Z$4) -> 2060 | AL31: =SUM(AJ31) -> 206 | AM31: =SUM(AL31*$Z$4) -> 2060 | AN31: =SUM(AO31/19600) -> 0.73571429 | AO31: =SUM(AA31+AC31+AE31+AG31+AI31+AK31+AM31) -> 14420 | AQ31: =SUM(AR31/92970) -> 0.661706 | AR31: =Y31+AO31 -> 61518.806 | AS31: =SUM(AR31-AR30-AT31) -> 0 | AV31: =IF(AT31>0,AU31,AV30) -> 1.05 | AW31: =-SUM('B5'!AI30) -> 0 | AX31: =-SUM(AW31-AS31) -> 0 | AY31: =SUM(AX31+AW31) -> 0 | AZ31: =ELEC!A29 -> 0 | BA31: ='General information '!D31 -> 0 | BB31: =SUM('General information '!E31) -> 0 | BC31: =IF(AR30>=AR31,0,1) -> 0 | BD31: 19222 | BE31: =(305/1185)*ELEC!Q30 -> 0 | BG31: =#REF!-BE31 -> #REF!
A32: =ELEC!C30 -> 44374 | B32: ='B5'!B31 -> 199 | C32: =B32*$B$4 -> 4281.7097 | D32: =SUM(B32) -> 199 | E32: =D32*$B$4 -> 4281.7097 | F32: =SUM(D32) -> 199 | G32: =F32*$B$4 -> 4281.7097 | H32: =SUM(F32) -> 199 | I32: =H32*$B$4 -> 4281.7097 | J32: =SUM(H32) -> 199 | K32: =J32*$B$4 -> 4281.7097 | L32: =SUM(J32) -> 199 | M32: =L32*$B$4 -> 4281.7097 | N32: =SUM(L32) -> 199 | O32: =N32*$B$4 -> 4281.7097 | P32: =SUM(N32) -> 199 | Q32: =P32*$B$4 -> 4281.7097 | R32: =SUM(P32) -> 199 | S32: =R32*$B$4 -> 4281.7097 | T32: =SUM(R32) -> 199 | U32: =T32*$B$4 -> 4281.7097 | V32: =SUM(T32) -> 199 | W32: =V32*$B$4 -> 4281.7097 | X32: =SUM(Y32/73370) -> 0.64193548 | Y32: =SUM(C32+E32+G32+I32+K32+M32+O32+Q32+S32+U32+W32) -> 47098.806 | Z32: ='B5'!C31 -> 206 | AA32: =SUM(Z32*$Z$4) -> 2060 | AB32: =SUM(Z32) -> 206 | AC32: =SUM(AB32*$Z$4) -> 2060 | AD32: =SUM(AB32) -> 206 | AE32: =SUM(AD32*$Z$4) -> 2060 | AF32: =SUM(AD32) -> 206 | AG32: =SUM(AF32*$Z$4) -> 2060 | AH32: =SUM(AF32) -> 206 | AI32: =SUM(AH32*$Z$4) -> 2060 | AJ32: =SUM(AH32) -> 206 | AK32: =SUM(AJ32*$Z$4) -> 2060 | AL32: =SUM(AJ32) -> 206 | AM32: =SUM(AL32*$Z$4) -> 2060 | AN32: =SUM(AO32/19600) -> 0.73571429 | AO32: =SUM(AA32+AC32+AE32+AG32+AI32+AK32+AM32) -> 14420 | AQ32: =SUM(AR32/92970) -> 0.661706 | AR32: =Y32+AO32 -> 61518.806 | AS32: =SUM(AR32-AR31-AT32) -> 0 | AV32: =IF(AT32>0,AU32,AV31) -> 1.05 | AW32: =-SUM('B5'!AI31) -> 0 | AX32: =-SUM(AW32-AS32) -> 0 | AY32: =SUM(AX32+AW32) -> 0 | AZ32: =ELEC!A30 -> 0 | BA32: ='General information '!D32 -> 0 | BB32: =SUM('General information '!E32) -> 0 | BC32: =IF(AR31>=AR32,0,1) -> 0 | BD32: 19222 | BE32: =(305/1185)*ELEC!Q31 -> 0 | BG32: =#REF!-BE32 -> #REF!
A33: =ELEC!C31 -> 44375 | B33: ='B5'!B32 -> 199 | C33: =B33*$B$4 -> 4281.7097 | D33: =SUM(B33) -> 199 | E33: =D33*$B$4 -> 4281.7097 | F33: =SUM(D33) -> 199 | G33: =F33*$B$4 -> 4281.7097 | H33: =SUM(F33) -> 199 | I33: =H33*$B$4 -> 4281.7097 | J33: =SUM(H33) -> 199 | K33: =J33*$B$4 -> 4281.7097 | L33: =SUM(J33) -> 199 | M33: =L33*$B$4 -> 4281.7097 | N33: =SUM(L33) -> 199 | O33: =N33*$B$4 -> 4281.7097 | P33: =SUM(N33) -> 199 | Q33: =P33*$B$4 -> 4281.7097 | R33: =SUM(P33) -> 199 | S33: =R33*$B$4 -> 4281.7097 | T33: =SUM(R33) -> 199 | U33: =T33*$B$4 -> 4281.7097 | V33: =SUM(T33) -> 199 | W33: =V33*$B$4 -> 4281.7097 | X33: =SUM(Y33/73370) -> 0.64193548 | Y33: =SUM(C33+E33+G33+I33+K33+M33+O33+Q33+S33+U33+W33) -> 47098.806 | Z33: ='B5'!C32 -> 206 | AA33: =SUM(Z33*$Z$4) -> 2060 | AB33: =SUM(Z33) -> 206 | AC33: =SUM(AB33*$Z$4) -> 2060 | AD33: =SUM(AB33) -> 206 | AE33: =SUM(AD33*$Z$4) -> 2060 | AF33: =SUM(AD33) -> 206 | AG33: =SUM(AF33*$Z$4) -> 2060 | AH33: =SUM(AF33) -> 206 | AI33: =SUM(AH33*$Z$4) -> 2060 | AJ33: =SUM(AH33) -> 206 | AK33: =SUM(AJ33*$Z$4) -> 2060 | AL33: =SUM(AJ33) -> 206 | AM33: =SUM(AL33*$Z$4) -> 2060 | AN33: =SUM(AO33/19600) -> 0.73571429 | AO33: =SUM(AA33+AC33+AE33+AG33+AI33+AK33+AM33) -> 14420 | AQ33: =SUM(AR33/92970) -> 0.661706 | AR33: =Y33+AO33 -> 61518.806 | AS33: =SUM(AR33-AR32-AT33) -> 0 | AV33: =IF(AT33>0,AU33,AV32) -> 1.05 | AW33: =-SUM('B5'!AI32) -> 0 | AX33: =-SUM(AW33-AS33) -> 0 | AY33: =SUM(AX33+AW33) -> 0 | AZ33: =ELEC!A31 -> 0 | BA33: ='General information '!D33 -> 0 | BB33: =SUM('General information '!E33) -> 0 | BC33: =IF(AR32>=AR33,0,1) -> 0 | BD33: 19222 | BE33: =(305/1185)*ELEC!#REF! -> #REF! | BG33: =#REF!-BE33 -> #REF!
A34: =ELEC!C32 -> 44376 | B34: ='B5'!B33 -> 199 | C34: =B34*$B$4 -> 4281.7097 | D34: =SUM(B34) -> 199 | E34: =D34*$B$4 -> 4281.7097 | F34: =SUM(D34) -> 199 | G34: =F34*$B$4 -> 4281.7097 | H34: =SUM(F34) -> 199 | I34: =H34*$B$4 -> 4281.7097 | J34: =SUM(H34) -> 199 | K34: =J34*$B$4 -> 4281.7097 | L34: =SUM(J34) -> 199 | M34: =L34*$B$4 -> 4281.7097 | N34: =SUM(L34) -> 199 | O34: =N34*$B$4 -> 4281.7097 | P34: =SUM(N34) -> 199 | Q34: =P34*$B$4 -> 4281.7097 | R34: =SUM(P34) -> 199 | S34: =R34*$B$4 -> 4281.7097 | T34: =SUM(R34) -> 199 | U34: =T34*$B$4 -> 4281.7097 | V34: =SUM(T34) -> 199 | W34: =V34*$B$4 -> 4281.7097 | X34: =SUM(Y34/73370) -> 0.64193548 | Y34: =SUM(C34+E34+G34+I34+K34+M34+O34+Q34+S34+U34+W34) -> 47098.806 | Z34: ='B5'!C33 -> 206 | AA34: =SUM(Z34*$Z$4) -> 2060 | AB34: =SUM(Z34) -> 206 | AC34: =SUM(AB34*$Z$4) -> 2060 | AD34: =SUM(AB34) -> 206 | AE34: =SUM(AD34*$Z$4) -> 2060 | AF34: =SUM(AD34) -> 206 | AG34: =SUM(AF34*$Z$4) -> 2060 | AH34: =SUM(AF34) -> 206 | AI34: =SUM(AH34*$Z$4) -> 2060 | AJ34: =SUM(AH34) -> 206 | AK34: =SUM(AJ34*$Z$4) -> 2060 | AL34: =SUM(AJ34) -> 206 | AM34: =SUM(AL34*$Z$4) -> 2060 | AN34: =SUM(AO34/19600) -> 0.73571429 | AO34: =SUM(AA34+AC34+AE34+AG34+AI34+AK34+AM34) -> 14420 | AQ34: =SUM(AR34/92970) -> 0.661706 | AR34: =Y34+AO34 -> 61518.806 | AS34: =SUM(AR34-AR33-AT34) -> 0 | AV34: =IF(AT34>0,AU34,AV33) -> 1.05 | AW34: =-SUM('B5'!AI33) -> 0 | AX34: =-SUM(AW34-AS34) -> 0 | AY34: =SUM(AX34+AW34) -> 0 | AZ34: =ELEC!A32 -> 0 | BA34: ='General information '!D34 -> 0 | BB34: =SUM('General information '!E34) -> 0
A35: =ELEC!C33 -> 44377 | B35: ='B5'!B34 -> 199 | C35: =B35*$B$4 -> 4281.7097 | D35: =SUM(B35) -> 199 | E35: =D35*$B$4 -> 4281.7097 | F35: =SUM(D35) -> 199 | G35: =F35*$B$4 -> 4281.7097 | H35: =SUM(F35) -> 199 | I35: =H35*$B$4 -> 4281.7097 | J35: =SUM(H35) -> 199 | K35: =J35*$B$4 -> 4281.7097 | L35: =SUM(J35) -> 199 | M35: =L35*$B$4 -> 4281.7097 | N35: =SUM(L35) -> 199 | O35: =N35*$B$4 -> 4281.7097 | P35: =SUM(N35) -> 199 | Q35: =P35*$B$4 -> 4281.7097 | R35: =SUM(P35) -> 199 | S35: =R35*$B$4 -> 4281.7097 | T35: =SUM(R35) -> 199 | U35: =T35*$B$4 -> 4281.7097 | V35: =SUM(T35) -> 199 | W35: =V35*$B$4 -> 4281.7097 | X35: =SUM(Y35/73370) -> 0.64193548 | Y35: =SUM(C35+E35+G35+I35+K35+M35+O35+Q35+S35+U35+W35) -> 47098.806 | Z35: ='B5'!C34 -> 206 | AA35: =SUM(Z35*$Z$4) -> 2060 | AB35: =SUM(Z35) -> 206 | AC35: =SUM(AB35*$Z$4) -> 2060 | AD35: =SUM(AB35) -> 206 | AE35: =SUM(AD35*$Z$4) -> 2060 | AF35: =SUM(AD35) -> 206 | AG35: =SUM(AF35*$Z$4) -> 2060 | AH35: =SUM(AF35) -> 206 | AI35: =SUM(AH35*$Z$4) -> 2060 | AJ35: =SUM(AH35) -> 206 | AK35: =SUM(AJ35*$Z$4) -> 2060 | AL35: =SUM(AJ35) -> 206 | AM35: =SUM(AL35*$Z$4) -> 2060 | AN35: =SUM(AO35/19600) -> 0.73571429 | AO35: =SUM(AA35+AC35+AE35+AG35+AI35+AK35+AM35) -> 14420 | AQ35: =SUM(AR35/92970) -> 0.661706 | AR35: =Y35+AO35 -> 61518.806 | AS35: =SUM(AR35-AR34-AT35) -> 0 | AV35: =IF(AT35>0,AU35,AV34) -> 1.05 | AW35: =-SUM('B5'!AI34) -> 0 | AX35: =-SUM(AW35-AS35) -> 0 | AY35: =SUM(AX35+AW35) -> 0 | AZ35: =ELEC!A33 -> 0 | BA35: ='General information '!D35 -> 0 | BB35: =SUM('General information '!E35) -> 0
AR36: NB delivery | AS36: =COUNT(AT6:AT35) -> 4 | AT36: =SUM(AT6:AT35) -> 57335 | AU36: =SUM(AU6:AU35)/AS36 -> 1.0265 | AX36: =SUM(AX6:AX35) -> -57621.419 | AY36: =SUM(AY6:AY35) -> -59788.419
AT37: =+AT36*AU36 -> 58854.377
AS39: =SUM(AS6:AS35)/'EDl log'!A35 -> -3736.7762
AX40: 43309
AX41: =AX36/AX40 -> -1.3304722

Sheet EDl log
A1: Date | B1: EDL | C1: Conso EDL KW | F1: Peak | G1: 320 | H1: Day | I1: 112 | J1: Night | K1: 80
L2: P | M2: D | N2: N | O2: fee | P2: T EDL | Q2: Gen | R2: Elc C
A3: =ELEC!C3 -> 44347 | B3: ='[3]EDl log'!B34 -> 1057796 | C3: ='[3]EDl log'!C34 -> 1319 | D3: ='[3]EDl log'!D34 -> 1320 | E3: ='[3]EDl log'!E34 -> 1057797 | F3: ='[3]EDl log'!F34 -> 156087 | G3: ='[3]EDl log'!G34 -> 176 | H3: ='[3]EDl log'!H34 -> 515542 | I3: ='[3]EDl log'!I34 -> 551 | ... T3: ='[3]EDl log'!T34 -> 0.20289124 | Z3: VAT | AA3: 0.1
A4: =ELEC!C4 -> 44348 | B4: 1058175 | C4: =SUM(B4-B3) -> 379 | D4: =SUM(G4+I4+K4) -> 379 | E4: =B3+D4 -> 1058175 | F4: 156087 | G4: =F4-F3 -> 0 | H4: 515845 | I4: =H4-H3 -> 303 | J4: 386243 | K4: =J4-J3 -> 76 | L4: =SUM(G4*$Y$28)/1507.5 -> 0 | M4: =SUM(I4*$Y$27)/1507.5 -> 22.511443 | N4: =SUM(K4*$Y$26)/1507.5 -> 4.0331675 | O4: =($AC$29/$A$37)/1507.5 -> 159.96314 | P4: =SUM(L4:O4) -> 186.50775 | Q4: =SUM(-tanks!AX6*tanks!$AU$36) -> 4495.9044 | R4: =SUM(P4:Q4) -> 4682.4122 | S4: =SUM(ELEC!N4) -> 10480.6 | T4: =IF(S4>0,R4/S4,0) -> 0.44676948 | V4: ='[6]EDl log'!V21 -> EDL | W4: 44317 | Z4: Subscription
A5: =ELEC!C5 -> 44349 | B5: 1059363 | C5: =SUM(B5-B4) -> 1188 | D5: =SUM(G5+I5+K5) -> 1186 | E5: =B4+D5 -> 1059361 | F5: 156260 | G5: =F5-F4 -> 173 | H5: 516289 | I5: =H5-H4 -> 444 | J5: 386812 | K5: =J5-J4 -> 569 | L5: =SUM(G5*$Y$28)/1507.5 -> 36.723051 | M5: =SUM(I5*$Y$27)/1507.5 -> 32.987065 | N5: =SUM(K5*$Y$26)/1507.5 -> 30.195688 | O5: =($AC$29/$A$37)/1507.5 -> 159.96314 | P5: =SUM(L5:O5) -> 259.86894 | Q5: =SUM(-tanks!AX7*tanks!$AU$36) -> 2188.5642 | R5: =SUM(P5:Q5) -> 2448.4332 | S5: =SUM(ELEC!N5) -> 12363.8 | T5: =IF(S5>0,R5/S5,0) -> 0.19803241 | Z5: KVA | AA5: ='[7]EDl log'!AA22 -> 5000
