Workbook

Sheet Total
A1: Site Name | B1: Day | C1: Month | D1: Year | E1: Total Electricity Kwh | F1: Electricity Tariff ($/Kwh) | G1: LPG (Kg) | H1: LPG $/Kg | I1: Water Utility Supply (m3) m3 | J1: Water Utility Supply (m3) $/m3 | K1: Room Nights | L1: Utilities day cost dh
A2: Serengeti | B2: 1 | C2: 7 | D2: 2021 | E2: ='UTILITY REPORT 1'!F3 -> 4264 | F2: =('UTILITY REPORT 1'!E3*'UTILITY REPORT 1'!D3)/'UTILITY REPORT 1'!F3 -> 0.42204034 | G2: =IF('Utility summery'!M6<0,"0",'Utility summery'!M6) -> 130.68 | H2: 0 | I2: =IF('UTILITY REPORT 1'!G3<0,"0",'UTILITY REPORT 1'!G3) -> 109 | J2: 2.165 | K2: ='UTILITY REPORT 1'!C3 -> 23 | L2: =E2*F2+G2*H2+#REF!*#REF!+I2*J2 -> #REF!
A3: Serengeti | B3: =B2+1 -> 2 | C3: 7 | D3: 2021 | E3: ='UTILITY REPORT 1'!F4 -> 4274 | F3: =('UTILITY REPORT 1'!E4*'UTILITY REPORT 1'!D4)/'UTILITY REPORT 1'!F4 -> 0.39586336 | G3: =IF('Utility summery'!M7<0,"0",'Utility summery'!M7) -> 124.52 | H3: 0 | I3: =IF('UTILITY REPORT 1'!G4<0,"0",'UTILITY REPORT 1'!G4) -> 101 | J3: 2.165 | K3: ='UTILITY REPORT 1'!C4 -> 27 | L3: =E3*F3+G3*H3+#REF!*#REF!+I3*J3 -> #REF!
A4: Serengeti | B4: =B3+1 -> 3 | C4: 7 | D4: 2021 | E4: ='UTILITY REPORT 1'!F5 -> 4467 | F4: =('UTILITY REPORT 1'!E5*'UTILITY REPORT 1'!D5)/'UTILITY REPORT 1'!F5 -> 0.40530557 | G4: =IF('Utility summery'!M8<0,"0",'Utility summery'!M8) -> 44 | H4: 0 | I4: =IF('UTILITY REPORT 1'!G5<0,"0",'UTILITY REPORT 1'!G5) -> 94 | J4: 2.165 | K4: ='UTILITY REPORT 1'!C5 -> 20 | L4: =E4*F4+G4*H4+#REF!*#REF!+I4*J4 -> #REF!
A5: Serengeti | B5: =B4+1 -> 4 | C5: 7 | D5: 2021 | E5: ='UTILITY REPORT 1'!F6 -> 4106 | F5: =('UTILITY REPORT 1'!E6*'UTILITY REPORT 1'!D6)/'UTILITY REPORT 1'!F6 -> 0.40242085 | G5: =IF('Utility summery'!M9<0,"0",'Utility summery'!M9) -> 89.364 | H5: 0 | I5: =IF('UTILITY REPORT 1'!G6<0,"0",'UTILITY REPORT 1'!G6) -> 98 | J5: 2.165 | K5: ='UTILITY REPORT 1'!C6 -> 14 | L5: =E5*F5+G5*H5+#REF!*#REF!+I5*J5 -> #REF!
A6: Serengeti | B6: =B5+1 -> 5 | C6: 7 | D6: 2021 | E6: ='UTILITY REPORT 1'!F7 -> 4026 | F6: =('UTILITY REPORT 1'!E7*'UTILITY REPORT 1'!D7)/'UTILITY REPORT 1'!F7 -> 0.40842524 | G6: =IF('Utility summery'!M10<0,"0",'Utility summery'!M10) -> 112.42 | H6: 0 | I6: =IF('UTILITY REPORT 1'!G7<0,"0",'UTILITY REPORT 1'!G7) -> 135 | J6: 2.165 | K6: ='UTILITY REPORT 1'!C7 -> 11 | L6: =E6*F6+G6*H6+#REF!*#REF!+I6*J6 -> #REF!
A7: Serengeti | B7: =B6+1 -> 6 | C7: 7 | D7: 2021 | E7: ='UTILITY REPORT 1'!F8 -> 4145 | F7: =('UTILITY REPORT 1'!E8*'UTILITY REPORT 1'!D8)/'UTILITY REPORT 1'!F8 -> 0.40270929 | G7: =IF('Utility summery'!M11<0,"0",'Utility summery'!M11) -> 116.776 | H7: 0 | I7: =IF('UTILITY REPORT 1'!G8<0,"0",'UTILITY REPORT 1'!G8) -> 124 | J7: 2.165 | K7: ='UTILITY REPORT 1'!C8 -> 14 | L7: =E7*F7+G7*H7+#REF!*#REF!+I7*J7 -> #REF!
A8: Serengeti | B8: =B7+1 -> 7 | C8: 7 | D8: 2021 | E8: ='UTILITY REPORT 1'!F9 -> 4675 | F8: =('UTILITY REPORT 1'!E9*'UTILITY REPORT 1'!D9)/'UTILITY REPORT 1'!F9 -> 0.40618396 | G8: =IF('Utility summery'!M12<0,"0",'Utility summery'!M12) -> 108.328 | H8: 0 | I8: =IF('UTILITY REPORT 1'!G9<0,"0",'UTILITY REPORT 1'!G9) -> 114 | J8: 2.165 | K8: ='UTILITY REPORT 1'!C9 -> 29 | L8: =E8*F8+G8*H8+#REF!*#REF!+I8*J8 -> #REF!
A9: Serengeti | B9: =B8+1 -> 8 | C9: 7 | D9: 2021 | E9: ='UTILITY REPORT 1'!F10 -> 4550 | F9: =('UTILITY REPORT 1'!E10*'UTILITY REPORT 1'!D10)/'UTILITY REPORT 1'!F10 -> 0.41006374 | G9: =IF('Utility summery'!M13<0,"0",'Utility summery'!M13) -> 112.376 | H9: 0 | I9: =IF('UTILITY REPORT 1'!G10<0,"0",'UTILITY REPORT 1'!G10) -> 94 | J9: 2.165 | K9: ='UTILITY REPORT 1'!C10 -> 35 | L9: =E9*F9+G9*H9+#REF!*#REF!+I9*J9 -> #REF!
A10: Serengeti | B10: =B9+1 -> 9 | C10: 7 | D10: 2021 | E10: ='UTILITY REPORT 1'!F11 -> 4263 | F10: =('UTILITY REPORT 1'!E11*'UTILITY REPORT 1'!D11)/'UTILITY REPORT 1'!F11 -> 0.4239315 | G10: =IF('Utility summery'!M14<0,"0",'Utility summery'!M14) -> 103.4 | H10: 0 | I10: =IF('UTILITY REPORT 1'!G11<0,"0",'UTILITY REPORT 1'!G11) -> 108 | J10: 2.165 | K10: ='UTILITY REPORT 1'!C11 -> 39 | L10: =E10*F10+G10*H10+#REF!*#REF!+I10*J10 -> #REF!
A11: Serengeti | B11: =B10+1 -> 10 | C11: 7 | D11: 2021 | E11: ='UTILITY REPORT 1'!F12 -> 4506 | F11: =('UTILITY REPORT 1'!E12*'UTILITY REPORT 1'!D12)/'UTILITY REPORT 1'!F12 -> 0.41897026 | G11: =IF('Utility summery'!M15<0,"0",'Utility summery'!M15) -> 117.304 | H11: 0 | I11: =IF('UTILITY REPORT 1'!G12<0,"0",'UTILITY REPORT 1'!G12) -> 116 | J11: 2.165 | K11: ='UTILITY REPORT 1'!C12 -> 32 | L11: =E11*F11+G11*H11+#REF!*#REF!+I11*J11 -> #REF!
A12: Serengeti | B12: =B11+1 -> 11 | C12: 7 | D12: 2021 | E12: ='UTILITY REPORT 1'!F13 -> 4459 | F12: =('UTILITY REPORT 1'!E13*'UTILITY REPORT 1'!D13)/'UTILITY REPORT 1'!F13 -> 0.41547432 | G12: =IF('Utility summery'!M16<0,"0",'Utility summery'!M16) -> 115.676 | H12: 0 | I12: =IF('UTILITY REPORT 1'!G13<0,"0",'UTILITY REPORT 1'!G13) -> 116 | J12: 2.165 | K12: ='UTILITY REPORT 1'!C13 -> 31 | L12: =E12*F12+G12*H12+#REF!*#REF!+I12*J12 -> #REF!
A13: Serengeti | B13: =B12+1 -> 12 | C13: 7 | D13: 2021 | E13: ='UTILITY REPORT 1'!F14 -> 4438 | F13: =('UTILITY REPORT 1'!E14*'UTILITY REPORT 1'!D14)/'UTILITY REPORT 1'!F14 -> 0.37453132 | G13: =IF('Utility summery'!M17<0,"0",'Utility summery'!M17) -> 126.984 | H13: 0 | I13: =IF('UTILITY REPORT 1'!G14<0,"0",'UTILITY REPORT 1'!G14) -> 109 | J13: 2.165 | K13: ='UTILITY REPORT 1'!C14 -> 32 | L13: =E13*F13+G13*H13+#REF!*#REF!+I13*J13 -> #REF!
A14: Serengeti | B14: =B13+1 -> 13 | C14: 7 | D14: 2021 | E14: ='UTILITY REPORT 1'!F15 -> 4300 | F14: =('UTILITY REPORT 1'!E15*'UTILITY REPORT 1'!D15)/'UTILITY REPORT 1'!F15 -> 0.42904884 | G14: =IF('Utility summery'!M18<0,"0",'Utility summery'!M18) -> 117.876 | H14: 0 | I14: =IF('UTILITY REPORT 1'!G15<0,"0",'UTILITY REPORT 1'!G15) -> 105 | J14: 2.165 | K14: ='UTILITY REPORT 1'!C15 -> 19 | L14: =E14*F14+G14*H14+#REF!*#REF!+I14*J14 -> #REF!
... A30: Serengeti | B30: =B29+1 -> 29 | C30: 7 | D30: 2021 | E30: ='UTILITY REPORT 1'!F31 -> 3985 | F30: =('UTILITY REPORT 1'!E31*'UTILITY REPORT 1'!D31)/'UTILITY REPORT 1'!F31 -> 0.49988959 | G30: =IF('Utility summery'!M34<0,"0",'Utility summery'!M34) -> 175.648 | H30: 0 | I30: =IF('UTILITY REPORT 1'!G31<0,"0",'UTILITY REPORT 1'!G31) -> 111 | J30: 2.165 | K30: ='UTILITY REPORT 1'!C31 -> 0 | L30: =E30*F30+G30*H30+#REF!*#REF!+I30*J30 -> #REF!
A31: Serengeti | B31: 30 | C31: 7 | D31: 2021 | E31: ='UTILITY REPORT 1'!F32 -> 4484 | F31: =('UTILITY REPORT 1'!E32*'UTILITY REPORT 1'!D32)/'UTILITY REPORT 1'!F32 -> 0.40646075 | G31: =IF('Utility summery'!M35<0,"0",'Utility summery'!M35) -> 171.292 | H31: 0 | I31: =IF('UTILITY REPORT 1'!G32<0,"0",'UTILITY REPORT 1'!G32) -> 105 | J31: 2.165 | K31: ='UTILITY REPORT 1'!C32 -> 0 | L31: =E31*F31+G31*H31+#REF!*#REF!+I31*J31 -> #REF!
A32: Serengeti | B32: 31 | C32: 7 | D32: 2021 | E32: ='UTILITY REPORT 1'!F33 -> 4015 | F32: =('UTILITY REPORT 1'!E33*'UTILITY REPORT 1'!D33)/'UTILITY REPORT 1'!F33 -> 0.41843587 | G32: =IF('Utility summery'!M36<0,"0",'Utility summery'!M36) -> 111.232 | H32: 0 | I32: =IF('UTILITY REPORT 1'!G33<0,"0",'UTILITY REPORT 1'!G33) -> 99 | J32: 2.165 | K32: ='UTILITY REPORT 1'!C33 -> 0

Sheet Submetering
A1: Site Name | B1: Day | C1: Month | D1: Year | E1: Transport Consumption (LT) | F1: Generators Consumption (LT) | G1: Total Electricity Kwh | H1: Kitchen (KWh) | I1: Laundry (KWh) | J1: STP (M3) | K1: RO prodution (M3) | L1: Amani Restaurant (M3) | M1: Kitchen (M3) | N1: Laundry (M3) | O1: Laundry (M3) | P1: Total water Consumption (M3) | Q1: Borehole #1 (M3) | R1: Borehole #2 (M3) | S1: Borehole #3 (M3) | T1: Borehole #4 (M3) | U1: Borehole #5 (M3) | V1: Borehole #6 (M3) | W1: Total Bore holes production (M3) | X1: Room Nights
A2: Serengeti | B2: 1 | C2: 7 | D2: 2021 | E2: ='UTILITY REPORT 1'!I3 -> 0 | F2: ='UTILITY REPORT 1'!E3 -> 1799.58 | G2: ='UTILITY REPORT 1'!F3 -> 4264 | H2: =IF('Kit report'!F4<0,"0",'Kit report'!F4) -> 1128180 | I2: =IF('Kit report'!X4<0,"0",'Kit report'!X4) -> 1647280 | J2: =IF('Utility summery'!H6<0,"0",'Utility summery'!H6) -> 33 | K2: =IF('UTILITY REPORT 1'!H3<0,"0",'UTILITY REPORT 1'!H3) -> 80 | L2: ='Water-Meter'!K6 -> 2 | M2: ='Water-Meter'!H6 -> 0 | N2: ='Water-Meter'!Q6 -> 3 | O2: =K2*E2+H2*I2+#REF!*#REF!+J2*L2 -> #REF! | P2: ='Water-Meter'!E6 -> 109 | Q2: =IF('Water-Meter'!U6<0,"0",'Water-Meter'!U6) -> 48 | R2: =IF('Water-Meter'!X6<0,"0",'Water-Meter'!X6) -> 0 | S2: =IF('Water-Meter'!AA6<0,"0",'Water-Meter'!AA6) -> 35 | T2: =IF('Water-Meter'!AD6<0,"0",'Water-Meter'!AD6) -> 16 | U2: =IF('Water-Meter'!AG6<0,"0",'Water-Meter'!AG6) -> 0 | V2: =IF('Water-Meter'!AJ6<0,"0",'Water-Meter'!AJ6) -> 32 | W2: ='Water-Meter'!AN6 -> 131 | X2: =Total!K2 -> 23
A3: Serengeti | B3: =B2+1 -> 2 | C3: 7 | D3: 2021 | E3: ='UTILITY REPORT 1'!I4 -> 324.81 | F3: ='UTILITY REPORT 1'!E4 -> 1691.92 | G3: ='UTILITY REPORT 1'!F4 -> 4274 | H3: =IF('Kit report'!F5<0,"0",'Kit report'!F5) -> 324 | I3: =IF('Kit report'!X5<0,"0",'Kit report'!X5) -> 560 | J3: =IF('Utility summery'!H7<0,"0",'Utility summery'!H7) -> 35 | K3: =IF('UTILITY REPORT 1'!H4<0,"0",'UTILITY REPORT 1'!H4) -> 60 | L3: ='Water-Meter'!K7 -> 2 | M3: ='Water-Meter'!H7 -> 0 | N3: ='Water-Meter'!Q7 -> 7 | O3: =K3*E3+H3*I3+#REF!*#REF!+J3*L3 -> #REF! | P3: ='Water-Meter'!E7 -> 101 | Q3: =IF('Water-Meter'!U7<0,"0",'Water-Meter'!U7) -> 79 | R3: =IF('Water-Meter'!X7<0,"0",'Water-Meter'!X7) -> 0 | S3: =IF('Water-Meter'!AA7<0,"0",'Water-Meter'!AA7) -> 33 | T3: =IF('Water-Meter'!AD7<0,"0",'Water-Meter'!AD7) -> 15 | U3: =IF('Water-Meter'!AG7<0,"0",'Water-Meter'!AG7) -> 0 | V3: =IF('Water-Meter'!AJ7<0,"0",'Water-Meter'!AJ7) -> 29 | W3: ='Water-Meter'!AN7 -> 156 | X3: =Total!K3 -> 27
A4: Serengeti | B4: =B3+1 -> 3 | C4: 7 | D4: 2021 | E4: ='UTILITY REPORT 1'!I5 -> 0 | F4: ='UTILITY REPORT 1'!E5 -> 1810.5 | G4: ='UTILITY REPORT 1'!F5 -> 4467 | H4: =IF('Kit report'!F6<0,"0",'Kit report'!F6) -> 360 | I4: =IF('Kit report'!X6<0,"0",'Kit report'!X6) -> 540 | J4: =IF('Utility summery'!H8<0,"0",'Utility summery'!H8) -> 10 | K4: =IF('UTILITY REPORT 1'!H5<0,"0",'UTILITY REPORT 1'!H5) -> 55 | L4: ='Water-Meter'!K8 -> 3 | M4: ='Water-Meter'!H8 -> 0 | N4: ='Water-Meter'!Q8 -> 8 | O4: =K4*E4+H4*I4+#REF!*#REF!+J4*L4 -> #REF! | P4: ='Water-Meter'!E8 -> 94 | Q4: =IF('Water-Meter'!U8<0,"0",'Water-Meter'!U8) -> 89 | R4: =IF('Water-Meter'!X8<0,"0",'Water-Meter'!X8) -> 0 | S4: =IF('Water-Meter'!AA8<0,"0",'Water-Meter'!AA8) -> 37 | T4: =IF('Water-Meter'!AD8<0,"0",'Water-Meter'!AD8) -> 17 | U4: =IF('Water-Meter'!AG8<0,"0",'Water-Meter'!AG8) -> 0 | V4: =IF('Water-Meter'!AJ8<0,"0",'Water-Meter'!AJ8) -> 32 | W4: ='Water-Meter'!AN8 -> 175 | X4: =Total!K4 -> 20
A5: Serengeti | B5: =B4+1 -> 4 | C5: 7 | D5: 2021 | E5: ='UTILITY REPORT 1'!I6 -> 233.22 | F5: ='UTILITY REPORT 1'!E6 -> 1652.34 | G5: ='UTILITY REPORT 1'!F6 -> 4106 | H5: =IF('Kit report'!F7<0,"0",'Kit report'!F7) -> 324 | I5: =IF('Kit report'!X7<0,"0",'Kit report'!X7) -> 660 | J5: =IF('Utility summery'!H9<0,"0",'Utility summery'!H9) -> 58 | K5: =IF('UTILITY REPORT 1'!H6<0,"0",'UTILITY REPORT 1'!H6) -> 48 | L5: ='Water-Meter'!K9 -> 2 | M5: ='Water-Meter'!H9 -> 0 | N5: ='Water-Meter'!Q9 -> 10 | O5: =K5*E5+H5*I5+#REF!*#REF!+J5*L5 -> #REF! | P5: ='Water-Meter'!E9 -> 98 | Q5: =IF('Water-Meter'!U9<0,"0",'Water-Meter'!U9) -> 80 | R5: =IF('Water-Meter'!X9<0,"0",'Water-Meter'!X9) -> 0 | S5: =IF('Water-Meter'!AA9<0,"0",'Water-Meter'!AA9) -> 33 | T5: =IF('Water-Meter'!AD9<0,"0",'Water-Meter'!AD9) -> 15 | U5: =IF('Water-Meter'!AG9<0,"0",'Water-Meter'!AG9) -> 0 | V5: =IF('Water-Meter'!AJ9<0,"0",'Water-Meter'!AJ9) -> 30 | W5: ='Water-Meter'!AN9 -> 158 | X5: =Total!K5 -> 14
A6: Serengeti | B6: =B5+1 -> 5 | C6: 7 | D6: 2021 | E6: ='UTILITY REPORT 1'!I7 -> 148.61 | F6: ='UTILITY REPORT 1'!E7 -> 1644.32 | G6: ='UTILITY REPORT 1'!F7 -> 4026 | H6: =IF('Kit report'!F8<0,"0",'Kit report'!F8) -> 264 | I6: =IF('Kit report'!X8<0,"0",'Kit report'!X8) -> 660 | J6: =IF('Utility summery'!H10<0,"0",'Utility summery'!H10) -> 44 | K6: =IF('UTILITY REPORT 1'!H7<0,"0",'UTILITY REPORT 1'!H7) -> 50 | L6: ='Water-Meter'!K10 -> 1 | M6: ='Water-Meter'!H10 -> 0 | N6: ='Water-Meter'!Q10 -> 7 | O6: =K6*E6+H6*I6+#REF!*#REF!+J6*L6 -> #REF! | P6: ='Water-Meter'!E10 -> 135 | Q6: =IF('Water-Meter'!U10<0,"0",'Water-Meter'!U10) -> 49 | R6: =IF('Water-Meter'!X10<0,"0",'Water-Meter'!X10) -> 0 | S6: =IF('Water-Meter'!AA10<0,"0",'Water-Meter'!AA10) -> 34 | T6: =IF('Water-Meter'!AD10<0,"0",'Water-Meter'!AD10) -> 17 | U6: =IF('Water-Meter'!AG10<0,"0",'Water-Meter'!AG10) -> 0 | V6: =IF('Water-Meter'!AJ10<0,"0",'Water-Meter'!AJ10) -> 31 | W6: ='Water-Meter'!AN10 -> 131 | X6: =Total!K6 -> 11
A7: Serengeti | B7: =B6+1 -> 6 | C7: 7 | D7: 2021 | E7: ='UTILITY REPORT 1'!I8 -> 199.93 | F7: ='UTILITY REPORT 1'!E8 -> 1669.23 | G7: ='UTILITY REPORT 1'!F8 -> 4145 | H7: =IF('Kit report'!F9<0,"0",'Kit report'!F9) -> 276 | I7: =IF('Kit report'!X9<0,"0",'Kit report'!X9) -> 600 | J7: =IF('Utility summery'!H11<0,"0",'Utility summery'!H11) -> 52 | K7: =IF('UTILITY REPORT 1'!H8<0,"0",'UTILITY REPORT 1'!H8) -> 113 | L7: ='Water-Meter'!K11 -> 2 | M7: ='Water-Meter'!H11 -> 0 | N7: ='Water-Meter'!Q11 -> 10 | O7: =K7*E7+H7*I7+#REF!*#REF!+J7*L7 -> #REF! | P7: ='Water-Meter'!E11 -> 124 | Q7: =IF('Water-Meter'!U11<0,"0",'Water-Meter'!U11) -> 0 | R7: =IF('Water-Meter'!X11<0,"0",'Water-Meter'!X11) -> 0 | S7: =IF('Water-Meter'!AA11<0,"0",'Water-Meter'!AA11) -> 35 | T7: =IF('Water-Meter'!AD11<0,"0",'Water-Meter'!AD11) -> 16 | U7: =IF('Water-Meter'!AG11<0,"0",'Water-Meter'!AG11) -> 0 | V7: =IF('Water-Meter'!AJ11<0,"0",'Water-Meter'!AJ11) -> 31 | W7: ='Water-Meter'!AN11 -> 82 | X7: =Total!K7 -> 14
A8: Serengeti | B8: =B7+1 -> 7 | C8: 7 | D8: 2021 | E8: ='UTILITY REPORT 1'!I9 -> 168.95 | F8: ='UTILITY REPORT 1'!E9 -> 1898.91 | G8: ='UTILITY REPORT 1'!F9 -> 4675 | H8: =IF('Kit report'!F10<0,"0",'Kit report'!F10) -> 264 | I8: =IF('Kit report'!X10<0,"0",'Kit report'!X10) -> 800 | J8: =IF('Utility summery'!H12<0,"0",'Utility summery'!H12) -> 52 | K8: =IF('UTILITY REPORT 1'!H9<0,"0",'UTILITY REPORT 1'!H9) -> 121 | L8: ='Water-Meter'!K12 -> 2 | M8: ='Water-Meter'!H12 -> 0 | N8: ='Water-Meter'!Q12 -> 11 | O8: =K8*E8+H8*I8+#REF!*#REF!+J8*L8 -> #REF! | P8: ='Water-Meter'!E12 -> 114 | Q8: =IF('Water-Meter'!U12<0,"0",'Water-Meter'!U12) -> 86 | R8: =IF('Water-Meter'!X12<0,"0",'Water-Meter'!X12) -> 0 | S8: =IF('Water-Meter'!AA12<0,"0",'Water-Meter'!AA12) -> 33 | T8: =IF('Water-Meter'!AD12<0,"0",'Water-Meter'!AD12) -> 16 | U8: =IF('Water-Meter'!AG12<0,"0",'Water-Meter'!AG12) -> 0 | V8: =IF('Water-Meter'!AJ12<0,"0",'Water-Meter'!AJ12) -> 32 | W8: ='Water-Meter'!AN12 -> 167 | X8: =Total!K8 -> 29
A9: Serengeti | B9: =B8+1 -> 8 | C9: 7 | D9: 2021 | E9: ='UTILITY REPORT 1'!I10 -> 47 | F9: ='UTILITY REPORT 1'!E10 -> 1865.79 | G9: ='UTILITY REPORT 1'!F10 -> 4550 | H9: =IF('Kit report'!F11<0,"0",'Kit report'!F11) -> 252 | I9: =IF('Kit report'!X11<0,"0",'Kit report'!X11) -> 760 | J9: =IF('Utility summery'!H13<0,"0",'Utility summery'!H13) -> 57 | K9: =IF('UTILITY REPORT 1'!H10<0,"0",'UTILITY REPORT 1'!H10) -> 201 | L9: ='Water-Meter'!K13 -> 1 | M9: ='Water-Meter'!H13 -> 0 | N9: ='Water-Meter'!Q13 -> 9 | O9: =K9*E9+H9*I9+#REF!*#REF!+J9*L9 -> #REF! | P9: ='Water-Meter'!E13 -> 94 | Q9: =IF('Water-Meter'!U13<0,"0",'Water-Meter'!U13) -> 82 | R9: =IF('Water-Meter'!X13<0,"0",'Water-Meter'!X13) -> 0 | S9: =IF('Water-Meter'!AA13<0,"0",'Water-Meter'!AA13) -> 33 | T9: =IF('Water-Meter'!AD13<0,"0",'Water-Meter'!AD13) -> 16 | U9: =IF('Water-Meter'!AG13<0,"0",'Water-Meter'!AG13) -> 0 | V9: =IF('Water-Meter'!AJ13<0,"0",'Water-Meter'!AJ13) -> 33 | W9: ='Water-Meter'!AN13 -> 164 | X9: =Total!K9 -> 35
A10: Serengeti | B10: =B9+1 -> 9 | C10: 7 | D10: 2021 | E10: ='UTILITY REPORT 1'!I11 -> 456 | F10: ='UTILITY REPORT 1'!E11 -> 1807.22 | G10: ='UTILITY REPORT 1'!F11 -> 4263 | H10: =IF('Kit report'!F12<0,"0",'Kit report'!F12) -> 288 | I10: =IF('Kit report'!X12<0,"0",'Kit report'!X12) -> 880 | J10: =IF('Utility summery'!H14<0,"0",'Utility summery'!H14) -> 59 | K10: =IF('UTILITY REPORT 1'!H11<0,"0",'UTILITY REPORT 1'!H11) -> 1 | L10: ='Water-Meter'!K14 -> 2 | M10: ='Water-Meter'!H14 -> 0 | N10: ='Water-Meter'!Q14 -> 10 | O10: =K10*E10+H10*I10+#REF!*#REF!+J10*L10 -> #REF! | P10: ='Water-Meter'!E14 -> 108 | Q10: =IF('Water-Meter'!U14<0,"0",'Water-Meter'!U14) -> 83 | R10: =IF('Water-Meter'!X14<0,"0",'Water-Meter'!X14) -> 0 | S10: =IF('Water-Meter'!AA14<0,"0",'Water-Meter'!AA14) -> 34 | T10: =IF('Water-Meter'!AD14<0,"0",'Water-Meter'!AD14) -> 17 | U10: =IF('Water-Meter'!AG14<0,"0",'Water-Meter'!AG14) -> 0 | V10: =IF('Water-Meter'!AJ14<0,"0",'Water-Meter'!AJ14) -> 33 | W10: ='Water-Meter'!AN14 -> 167 | X10: =Total!K10 -> 39
A11: Serengeti | B11: =B10+1 -> 10 | C11: 7 | D11: 2021 | E11: ='UTILITY REPORT 1'!I12 -> 644.97 | F11: ='UTILITY REPORT 1'!E12 -> 1887.88 | G11: ='UTILITY REPORT 1'!F12 -> 4506 | H11: =IF('Kit report'!F13<0,"0",'Kit report'!F13) -> 240 | I11: =IF('Kit report'!X13<0,"0",'Kit report'!X13) -> 820 | J11: =IF('Utility summery'!H15<0,"0",'Utility summery'!H15) -> 56 | K11: =IF('UTILITY REPORT 1'!H12<0,"0",'UTILITY REPORT 1'!H12) -> 70 | L11: ='Water-Meter'!K15 -> 2 | M11: ='Water-Meter'!H15 -> 0 | N11: ='Water-Meter'!Q15 -> 11 | O11: =K11*E11+H11*I11+#REF!*#REF!+J11*L11 -> #REF! | P11: ='Water-Meter'!E15 -> 116 | Q11: =IF('Water-Meter'!U15<0,"0",'Water-Meter'!U15) -> 81 | R11: =IF('Water-Meter'!X15<0,"0",'Water-Meter'!X15) -> 0 | S11: =IF('Water-Meter'!AA15<0,"0",'Water-Meter'!AA15) -> 40 | T11: =IF('Water-Meter'!AD15<0,"0",'Water-Meter'!AD15) -> 16 | U11: =IF('Water-Meter'!AG15<0,"0",'Water-Meter'!AG15) -> 0 | V11: =IF('Water-Meter'!AJ15<0,"0",'Water-Meter'!AJ15) -> 35 | W11: ='Water-Meter'!AN15 -> 172 | X11: =Total!K11 -> 32
A12: Serengeti | B12: =B11+1 -> 11 | C12: 7 | D12: 2021 | E12: ='UTILITY REPORT 1'!I13 -> 608.62 | F12: ='UTILITY REPORT 1'!E13 -> 1852.6 | G12: ='UTILITY REPORT 1'!F13 -> 4459 | H12: =IF('Kit report'!F14<0,"0",'Kit report'!F14) -> 276 | I12: =IF('Kit report'!X14<0,"0",'Kit report'!X14) -> 900 | J12: =IF('Utility summery'!H16<0,"0",'Utility summery'!H16) -> 0 | K12: =IF('UTILITY REPORT 1'!H13<0,"0",'UTILITY REPORT 1'!H13) -> 41 | L12: ='Water-Meter'!K16 -> 6 | M12: ='Water-Meter'!H16 -> 0 | N12: ='Water-Meter'!Q16 -> 11 | O12: =K12*E12+H12*I12+#REF!*#REF!+J12*L12 -> #REF! | P12: ='Water-Meter'!E16 -> 116 | Q12: =IF('Water-Meter'!U16<0,"0",'Water-Meter'!U16) -> 82 | R12: =IF('Water-Meter'!X16<0,"0",'Water-Meter'!X16) -> 0 | S12: =IF('Water-Meter'!AA16<0,"0",'Water-Meter'!AA16) -> 34 | T12: =IF('Water-Meter'!AD16<0,"0",'Water-Meter'!AD16) -> 14 | U12: =IF('Water-Meter'!AG16<0,"0",'Water-Meter'!AG16) -> 0 | V12: =IF('Water-Meter'!AJ16<0,"0",'Water-Meter'!AJ16) -> 24 | W12: ='Water-Meter'!AN16 -> 154 | X12: =Total!K12 -> 31
A13: Serengeti | B13: =B12+1 -> 12 | C13: 7 | D13: 2021 | E13: ='UTILITY REPORT 1'!I14 -> 677.99 | F13: ='UTILITY REPORT 1'!E14 -> 1662.17 | G13: ='UTILITY REPORT 1'!F14 -> 4438 | H13: =IF('Kit report'!F15<0,"0",'Kit report'!F15) -> 264 | I13: =IF('Kit report'!X15<0,"0",'Kit report'!X15) -> 1020 | J13: =IF('Utility summery'!H17<0,"0",'Utility summery'!H17) -> 1 | K13: =IF('UTILITY REPORT 1'!H14<0,"0",'UTILITY REPORT 1'!H14) -> 40 | L13: ='Water-Meter'!K17 -> 2 | M13: ='Water-Meter'!H17 -> 0 | N13: ='Water-Meter'!Q17 -> 10 | O13: =K13*E13+H13*I13+#REF!*#REF!+J13*L13 -> #REF! | P13: ='Water-Meter'!E17 -> 109 | Q13: =IF('Water-Meter'!U17<0,"0",'Water-Meter'!U17) -> 86 | R13: =IF('Water-Meter'!X17<0,"0",'Water-Meter'!X17) -> 0 | S13: =IF('Water-Meter'!AA17<0,"0",'Water-Meter'!AA17) -> 37 | T13: =IF('Water-Meter'!AD17<0,"0",'Water-Meter'!AD17) -> 15 | U13: =IF('Water-Meter'!AG17<0,"0",'Water-Meter'!AG17) -> 0 | V13: =IF('Water-Meter'!AJ17<0,"0",'Water-Meter'!AJ17) -> 33 | W13: ='Water-Meter'!AN17 -> 171 | X13: =Total!K13 -> 32
A14: Serengeti | B14: =B13+1 -> 13 | C14: 7 | D14: 2021 | E14: ='UTILITY REPORT 1'!I15 -> 204.13 | F14: ='UTILITY REPORT 1'!E15 -> 1844.91 | G14: ='UTILITY REPORT 1'!F15 -> 4300 | H14: =IF('Kit report'!F16<0,"0",'Kit report'!F16) -> 276 | I14: =IF('Kit report'!X16<0,"0",'Kit report'!X16) -> 960 | J14: =IF('Utility summery'!H18<0,"0",'Utility summery'!H18) -> 60 | K14: =IF('UTILITY REPORT 1'!H15<0,"0",'UTILITY REPORT 1'!H15) -> 37 | L14: ='Water-Meter'!K18 -> 2 | M14: ='Water-Meter'!H18 -> 0 | N14: ='Water-Meter'!Q18 -> 12 | O14: =K14*E14+H14*I14+#REF!*#REF!+J14*L14 -> #REF! | P14: ='Water-Meter'!E18 -> 105 | Q14: =IF('Water-Meter'!U18<0,"0",'Water-Meter'!U18) -> 83 | R14: =IF('Water-Meter'!X18<0,"0",'Water-Meter'!X18) -> 0 | S14: =IF('Water-Meter'!AA18<0,"0",'Water-Meter'!AA18) -> 36 | T14: =IF('Water-Meter'!AD18<0,"0",'Water-Meter'!AD18) -> 15 | U14: =IF('Water-Meter'!AG18<0,"0",'Water-Meter'!AG18) -> 0 | V14: =IF('Water-Meter'!AJ18<0,"0",'Water-Meter'!AJ18) -> 31 | W14: ='Water-Meter'!AN18 -> 165 | X14: =Total!K14 -> 19
... A25: Serengeti | B25: =B24+1 -> 24 | C25: 7 | D25: 2021 | E25: ='UTILITY REPORT 1'!I26 -> 442.98 | F25: ='UTILITY REPORT 1'!E26 -> 2014.73 | G25: ='UTILITY REPORT 1'!F26 -> 4879 | H25: =IF('Kit report'!F27<0,"0",'Kit report'!F27) -> 348 | I25: =IF('Kit report'!X27<0,"0",'Kit report'!X27) -> 740 | J25: =IF('Utility summery'!H29<0,"0",'Utility summery'!H29) -> 67 | K25: =IF('UTILITY REPORT 1'!H26<0,"0",'UTILITY REPORT 1'!H26) -> 0 | L25: ='Water-Meter'!K29 -> 2 | M25: ='Water-Meter'!H29 -> 0 | N25: ='Water-Meter'!Q29 -> 11 | O25: =K25*E25+H25*I25+#REF!*#REF!+J25*L25 -> #REF! | P25: ='Water-Meter'!E29 -> 106 | Q25: =IF('Water-Meter'!U29<0,"0",'Water-Meter'!U29) -> 79 | R25: =IF('Water-Meter'!X29<0,"0",'Water-Meter'!X29) -> 0 | S25: =IF('Water-Meter'!AA29<0,"0",'Water-Meter'!AA29) -> 33 | T25: =IF('Water-Meter'!AD29<0,"0",'Water-Meter'!AD29) -> 17 | U25: =IF('Water-Meter'!AG29<0,"0",'Water-Meter'!AG29) -> 0 | V25: =IF('Water-Meter'!AJ29<0,"0",'Water-Meter'!AJ29) -> 29 | W25: ='Water-Meter'!AN29 -> 158 | X25: =Total!K25 -> 0
A26: Serengeti | B26: =B25+1 -> 25 | C26: 7 | D26: 2021 | E26: ='UTILITY REPORT 1'!I27 -> 259.79 | F26: ='UTILITY REPORT 1'!E27 -> 1869.09 | G26: ='UTILITY REPORT 1'!F27 -> 4599 | H26: =IF('Kit report'!F28<0,"0",'Kit report'!F28) -> 360 | I26: =IF('Kit report'!X28<0,"0",'Kit report'!X28) -> 800 | J26: =IF('Utility summery'!H30<0,"0",'Utility summery'!H30) -> 64 | K26: =IF('UTILITY REPORT 1'!H27<0,"0",'UTILITY REPORT 1'!H27) -> 81 | L26: ='Water-Meter'!K30 -> 2 | M26: ='Water-Meter'!H30 -> 0 | N26: ='Water-Meter'!Q30 -> 10 | O26: =K26*E26+H26*I26+#REF!*#REF!+J26*L26 -> #REF! | P26: ='Water-Meter'!E30 -> 106 | Q26: =IF('Water-Meter'!U30<0,"0",'Water-Meter'!U30) -> 82 | R26: =IF('Water-Meter'!X30<0,"0",'Water-Meter'!X30) -> 0 | S26: =IF('Water-Meter'!AA31<0,"0",'Water-Meter'!AA31) -> 35 | T26: =IF('Water-Meter'!AD30<0,"0",'Water-Meter'!AD30) -> 19 | U26: =IF('Water-Meter'!AG30<0,"0",'Water-Meter'!AG30) -> 0 | V26: =IF('Water-Meter'!AJ30<0,"0",'Water-Meter'!AJ30) -> 33 | W26: ='Water-Meter'!AN30 -> 169 | X26: =Total!K26 -> 0
A27: Serengeti | B27: =B26+1 -> 26 | C27: 7 | D27: 2021 | E27: ='UTILITY REPORT 1'!I28 -> 70.92 | F27: ='UTILITY REPORT 1'!E28 -> 1888.8 | G27: ='UTILITY REPORT 1'!F28 -> 4415 | H27: =IF('Kit report'!F29<0,"0",'Kit report'!F29) -> 276 | I27: =IF('Kit report'!X29<0,"0",'Kit report'!X29) -> 860 | J27: =IF('Utility summery'!H31<0,"0",'Utility summery'!H31) -> 58 | K27: =IF('UTILITY REPORT 1'!H28<0,"0",'UTILITY REPORT 1'!H28) -> 25 | L27: ='Water-Meter'!K31 -> 3 | M27: ='Water-Meter'!H31 -> 0 | N27: ='Water-Meter'!Q31 -> 10 | O27: =K27*E27+H27*I27+#REF!*#REF!+J27*L27 -> #REF! | P27: ='Water-Meter'!E31 -> 96 | Q27: =IF('Water-Meter'!U31<0,"0",'Water-Meter'!U31) -> 81 | R27: =IF('Water-Meter'!X31<0,"0",'Water-Meter'!X31) -> 0 | S27: =IF('Water-Meter'!#REF!<0,"0",'Water-Meter'!#REF!) -> #REF! | T27: =IF('Water-Meter'!AD31<0,"0",'Water-Meter'!AD31) -> 17 | U27: =IF('Water-Meter'!AG31<0,"0",'Water-Meter'!AG31) -> 0 | V27: =IF('Water-Meter'!AJ31<0,"0",'Water-Meter'!AJ31) -> 31 | W27: ='Water-Meter'!AN31 -> 164 | X27: =Total!K27 -> 0
A28: Serengeti | B28: =B27+1 -> 27 | C28: 7 | D28: 2021 | E28: ='UTILITY REPORT 1'!I29 -> 491.89 | F28: ='UTILITY REPORT 1'!E29 -> 1921.29 | G28: ='UTILITY REPORT 1'!F29 -> 4607 | H28: =IF('Kit report'!F30<0,"0",'Kit report'!F30) -> 300 | I28: =IF('Kit report'!X30<0,"0",'Kit report'!X30) -> 700 | J28: =IF('Utility summery'!H32<0,"0",'Utility summery'!H32) -> 47 | K28: =IF('UTILITY REPORT 1'!H29<0,"0",'UTILITY REPORT 1'!H29) -> 93 | L28: ='Water-Meter'!K32 -> 2 | M28: ='Water-Meter'!H32 -> 0 | N28: ='Water-Meter'!Q32 -> 8 | O28: =K28*E28+H28*I28+#REF!*#REF!+J28*L28 -> #REF! | P28: ='Water-Meter'!E32 -> 103 | Q28: =IF('Water-Meter'!U32<0,"0",'Water-Meter'!U32) -> 80 | R28: =IF('Water-Meter'!X32<0,"0",'Water-Meter'!X32) -> 0 | S28: =IF('Water-Meter'!AA32<0,"0",'Water-Meter'!AA32) -> 35 | T28: =IF('Water-Meter'!AD32<0,"0",'Water-Meter'!AD32) -> 17 | U28: =IF('Water-Meter'!AG32<0,"0",'Water-Meter'!AG32) -> 0 | V28: =IF('Water-Meter'!AJ32<0,"0",'Water-Meter'!AJ32) -> 31 | W28: ='Water-Meter'!AN32 -> 163 | X28: =Total!K28 -> 0
A29: Serengeti | B29: =B28+1 -> 28 | C29: 7 | D29: 2021 | E29: ='UTILITY REPORT 1'!I30 -> 147.47 | F29: ='UTILITY REPORT 1'!E30 -> 1696.62 | G29: ='UTILITY REPORT 1'!F30 -> 4642 | H29: =IF('Kit report'!F31<0,"0",'Kit report'!F31) -> 324 | I29: =IF('Kit report'!X31<0,"0",'Kit report'!X31) -> 680 | J29: =IF('Utility summery'!H33<0,"0",'Utility summery'!H33) -> 53 | K29: =IF('UTILITY REPORT 1'!H30<0,"0",'UTILITY REPORT 1'!H30) -> 161 | L29: ='Water-Meter'!K33 -> 3 | M29: ='Water-Meter'!H33 -> 0 | N29: ='Water-Meter'!Q33 -> 9 | O29: =K29*E29+H29*I29+#REF!*#REF!+J29*L29 -> #REF! | P29: ='Water-Meter'!E33 -> 115 | Q29: =IF('Water-Meter'!U33<0,"0",'Water-Meter'!U33) -> 13 | R29: =IF('Water-Meter'!X33<0,"0",'Water-Meter'!X33) -> 0 | S29: =IF('Water-Meter'!AA33<0,"0",'Water-Meter'!AA33) -> 34 | T29: =IF('Water-Meter'!AD33<0,"0",'Water-Meter'!AD33) -> 17 | U29: =IF('Water-Meter'!AG33<0,"0",'Water-Meter'!AG33) -> 0 | V29: =IF('Water-Meter'!AJ33<0,"0",'Water-Meter'!AJ33) -> 32 | W29: ='Water-Meter'!AN33 -> 96 | X29: =Total!K29 -> 0
A30: Serengeti | B30: =B29+1 -> 29 | C30: 7 | D30: 2021 | E30: ='UTILITY REPORT 1'!I31 -> 246.95 | F30: ='UTILITY REPORT 1'!E31 -> 1992.06 | G30: ='UTILITY REPORT 1'!F31 -> 3985 | H30: =IF('Kit report'!F32<0,"0",'Kit report'!F32) -> 336 | I30: =IF('Kit report'!X32<0,"0",'Kit report'!X32) -> 600 | J30: =IF('Utility summery'!H34<0,"0",'Utility summery'!H34) -> 51 | K30: =IF('UTILITY REPORT 1'!H31<0,"0",'UTILITY REPORT 1'!H31) -> 109 | L30: ='Water-Meter'!K34 -> 2 | M30: ='Water-Meter'!H34 -> 0 | N30: ='Water-Meter'!Q34 -> 10 | O30: =K30*E30+H30*I30+#REF!*#REF!+J30*L30 -> #REF! | P30: ='Water-Meter'!E34 -> 111 | Q30: =IF('Water-Meter'!U34<0,"0",'Water-Meter'!U34) -> 72 | R30: =IF('Water-Meter'!X34<0,"0",'Water-Meter'!X34) -> 0 | S30: =IF('Water-Meter'!AA34<0,"0",'Water-Meter'!AA34) -> 34 | T30: =IF('Water-Meter'!AD34<0,"0",'Water-Meter'!AD34) -> 16 | U30: =IF('Water-Meter'!AG34<0,"0",'Water-Meter'!AG34) -> 0 | V30: =IF('Water-Meter'!AJ34<0,"0",'Water-Meter'!AJ34) -> 31 | W30: ='Water-Meter'!AN34 -> 153 | X30: =Total!K30 -> 0
A31: Serengeti | B31: 30 | C31: 7 | D31: 2021 | E31: ='UTILITY REPORT 1'!I32 -> 369 | F31: ='UTILITY REPORT 1'!E32 -> 1822.57 | G31: ='UTILITY REPORT 1'!F32 -> 4484 | H31: =IF('Kit report'!F33<0,"0",'Kit report'!F33) -> 300 | I31: =IF('Kit report'!X33<0,"0",'Kit report'!X33) -> 660 | J31: =IF('Utility summery'!H35<0,"0",'Utility summery'!H35) -> 47 | K31: =IF('UTILITY REPORT 1'!H32<0,"0",'UTILITY REPORT 1'!H32) -> 64 | L31: ='Water-Meter'!K35 -> 3 | M31: ='Water-Meter'!H35 -> 0 | N31: ='Water-Meter'!Q35 -> 10 | O31: =K31*E31+H31*I31+#REF!*#REF!+J31*L31 -> #REF! | P31: ='Water-Meter'!E35 -> 105 | Q31: =IF('Water-Meter'!U35<0,"0",'Water-Meter'!U35) -> 81 | R31: =IF('Water-Meter'!X35<0,"0",'Water-Meter'!X35) -> 0 | S31: =IF('Water-Meter'!AA35<0,"0",'Water-Meter'!AA35) -> 35 | T31: =IF('Water-Meter'!AD35<0,"0",'Water-Meter'!AD35) -> 20 | U31: =IF('Water-Meter'!AG35<0,"0",'Water-Meter'!AG35) -> 0 | V31: =IF('Water-Meter'!AJ35<0,"0",'Water-Meter'!AJ35) -> 31 | W31: ='Water-Meter'!AN35 -> 167 | X31: =Total!K31 -> 0
A32: Serengeti | B32: 31 | C32: 7 | D32: 2021 | E32: ='UTILITY REPORT 1'!I33 -> 376.24 | F32: ='UTILITY REPORT 1'!E33 -> 1680.02 | G32: ='UTILITY REPORT 1'!F33 -> 4015 | H32: =IF('Kit report'!F34<0,"0",'Kit report'!F34) -> 336 | I32: =IF('Kit report'!X34<0,"0",'Kit report'!X34) -> 760 | J32: =IF('Utility summery'!H36<0,"0",'Utility summery'!H36) -> 50 | K32: =IF('UTILITY REPORT 1'!H33<0,"0",'UTILITY REPORT 1'!H33) -> 65 | L32: ='Water-Meter'!K36 -> 2 | M32: ='Water-Meter'!H36 -> 0 | N32: ='Water-Meter'!Q36 -> 11 | P32: ='Water-Meter'!E36 -> 99 | Q32: =IF('Water-Meter'!U36<0,"0",'Water-Meter'!U36) -> 80 | R32: =IF('Water-Meter'!X36<0,"0",'Water-Meter'!X36) -> 0 | S32: =IF('Water-Meter'!AA36<0,"0",'Water-Meter'!AA36) -> 33 | T32: =IF('Water-Meter'!AD36<0,"0",'Water-Meter'!AD36) -> 16 | U32: =IF('Water-Meter'!AG36<0,"0",'Water-Meter'!AG36) -> 0 | V32: =IF('Water-Meter'!AJ36<0,"0",'Water-Meter'!AJ36) -> 20 | W32: ='Water-Meter'!AN36 -> 149 | X32: =Total!K32 -> 0

Sheet UTILITY REPORT 1
A1: UTILITY REPORT
A2: Date | B2: % | C2: Guest Rooms Occupied | D2: Diesel cost Per Liter ($) | E2: Diesel consumption (LT) | F2: Power production (KW) | G2: Water consumption (M3) | H2: RO prodution (M3) | I2: Transport Consupmtion (LT)
A3: =Gen!A11 -> 44378 | B3: =Gen!B11 -> 0.3 | C3: ='Summery Report'!E5 -> 23 | D3: 1 | E3: =Gen!S11 -> 1799.58 | F3: =Gen!T11 -> 4264 | G3: ='Water-Meter'!E6 -> 109 | H3: ='Utility report '!AC6 -> 80 | I3: =Gen!AJ11 -> 0
A4: =Gen!A12 -> 44379 | B4: =Gen!B12 -> 0.35 | C4: ='Summery Report'!E6 -> 27 | D4: 1 | E4: =Gen!S12 -> 1691.92 | F4: =Gen!T12 -> 4274 | G4: ='Water-Meter'!E7 -> 101 | H4: ='Utility report '!AC7 -> 60 | I4: =Gen!AJ12 -> 324.81
A5: =Gen!A13 -> 44380 | B5: =Gen!B13 -> 0.2609 | C5: ='Summery Report'!E7 -> 20 | D5: 1 | E5: =Gen!S13 -> 1810.5 | F5: =Gen!T13 -> 4467 | G5: ='Water-Meter'!E8 -> 94 | H5: ='Utility report '!AC8 -> 55 | I5: =Gen!AJ13 -> 0
A6: =Gen!A14 -> 44381 | B6: =Gen!B14 -> 0.18 | C6: ='Summery Report'!E8 -> 14 | D6: 1 | E6: =Gen!S14 -> 1652.34 | F6: =Gen!T14 -> 4106 | G6: ='Water-Meter'!E9 -> 98 | H6: ='Utility report '!AC9 -> 48 | I6: =Gen!AJ14 -> 233.22
A7: =Gen!A15 -> 44382 | B7: =Gen!B15 -> 0.14 | C7: ='Summery Report'!E9 -> 11 | D7: 1 | E7: =Gen!S15 -> 1644.32 | F7: =Gen!T15 -> 4026 | G7: ='Water-Meter'!E10 -> 135 | H7: ='Utility report '!AC10 -> 50 | I7: =Gen!AJ15 -> 148.61
A8: =Gen!A16 -> 44383 | B8: =Gen!B16 -> 0.169 | C8: ='Summery Report'!E10 -> 14 | D8: 1 | E8: =Gen!S16 -> 1669.23 | F8: =Gen!T16 -> 4145 | G8: ='Water-Meter'!E11 -> 124 | H8: ='Utility report '!AC11 -> 113 | I8: =Gen!AJ16 -> 199.93
A9: =Gen!A17 -> 44384 | B9: =Gen!B17 -> 0.364 | C9: ='Summery Report'!E11 -> 29 | D9: 1 | E9: =Gen!S17 -> 1898.91 | F9: =Gen!T17 -> 4675 | G9: ='Water-Meter'!E12 -> 114 | H9: ='Utility report '!AC12 -> 121 | I9: =Gen!AJ17 -> 168.95
A10: =Gen!A18 -> 44385 | B10: =Gen!B18 -> 0.455 | C10: ='Summery Report'!E12 -> 35 | D10: 1 | E10: =Gen!S18 -> 1865.79 | F10: =Gen!T18 -> 4550 | G10: ='Water-Meter'!E13 -> 94 | H10: ='Utility report '!AC13 -> 201 | I10: =Gen!AJ18 -> 47
A11: =Gen!A19 -> 44386 | B11: =Gen!B19 -> 0.468 | C11: ='Summery Report'!E13 -> 39 | D11: 1 | E11: =Gen!S19 -> 1807.22 | F11: =Gen!T19 -> 4263 | G11: ='Water-Meter'!E14 -> 108 | H11: ='Utility report '!AC14 -> 1 | I11: =Gen!AJ19 -> 456
A12: =Gen!A20 -> 44387 | B12: =Gen!B20 -> 0.39 | C12: ='Summery Report'!E14 -> 32 | D12: 1 | E12: =Gen!S20 -> 1887.88 | F12: =Gen!T20 -> 4506 | G12: ='Water-Meter'!E15 -> 116 | H12: ='Utility report '!AC15 -> 70 | I12: =Gen!AJ20 -> 644.97
A13: =Gen!A21 -> 44388 | B13: =Gen!B21 -> 0.403 | C13: ='Summery Report'!E15 -> 31 | D13: 1 | E13: =Gen!S21 -> 1852.6 | F13: =Gen!T21 -> 4459 | G13: ='Water-Meter'!E16 -> 116 | H13: ='Utility report '!AC16 -> 41 | I13: =Gen!AJ21 -> 608.62
A14: =Gen!A22 -> 44389 | B14: =Gen!B22 -> 0.39 | C14: ='Summery Report'!E16 -> 32 | D14: 1 | E14: =Gen!S22 -> 1662.17 | F14: =Gen!T22 -> 4438 | G14: ='Water-Meter'!E17 -> 109 | H14: ='Utility report '!AC17 -> 40 | I14: =Gen!AJ22 -> 677.99
... A33: =Gen!A41 -> 44408 | B33: =Gen!B41 -> 0.15 | C33: ='Summery Report'!E35 -> 0 | D33: 1 | E33: =Gen!S41 -> 1680.02 | F33: =Gen!T41 -> 4015 | G33: ='Water-Meter'!E36 -> 99 | H33: ='Utility report '!AC36 -> 65 | I33: =Gen!AJ41 -> 376.24
B34: =Gen!B42 -> 0 | C34: ='Summery Report'!E36 -> 0 | D34: 2 | E34: =Gen!S42 -> 0 | F34: =Gen!T42 -> 0 | G34: ='Water-Meter'!E37 -> 0 | H34: ='Utility report '!AC37 -> -7713 | I34: =Gen!AK42 -> 0

Sheet Utility summery
A4: Date | B4: Room Occupied | C4: Electricity Units Generated KW | D4: Diseal | G4: Water | J4: Gas | N4: Cost of utilites
D5: Generator | E5: Transport | F5: Total | G5: RO | H5: STP | I5: Total Consumption | J5: 2 ton | K5: 1 Ton | L5: 1 Ton | M5: Total consumption | N5: Electricity /1.4$/liter | O5: Diseal for Transport | P5: Gas /2.38$/Kg | Q5: Total HLP Cost | R5: Electricity Cost/Room $ | S5: cost/Room $
A6: =Gen!A11 -> 44378 | B6: ='Summery Report'!E5 -> 23 | C6: =Gen!U11 -> 0.42204034 | D6: =Gen!S11 -> 1799.58 | E6: =Gen!AJ11 -> 0 | F6: =Gen!AS11 -> 0 | G6: ='Utility report '!AC6 -> 80 | H6: ='Utility report '!AE6 -> 33 | I6: ='Water-Meter'!E6 -> 109 | J6: ='Lpg (2)'!B10 -> 85 | K6: ='Lpg (2)'!C10 -> 37 | L6: ='Lpg (2)'!D10 -> 85 | M6: ='Lpg (2)'!G10 -> 130.68 | N6: =D6*1.4 -> 2519.412 | O6: =E6*1.4 -> 0 | P6: =('Lpg (2)'!G10)*2.38 -> 311.0184 | Q6: #REF! | R6: =N6/B6 -> 109.53965 | S6: =Q6/B6 -> #REF!
A7: =Gen!A12 -> 44379 | B7: ='Summery Report'!E6 -> 27 | C7: =Gen!U12 -> 0.39586336 | D7: =Gen!S12 -> 1691.92 | E7: =Gen!AJ12 -> 324.81 | F7: =Gen!AS12 -> 0 | G7: ='Utility report '!AC7 -> 60 | H7: ='Utility report '!AE7 -> 35 | I7: ='Water-Meter'!E7 -> 101 | J7: ='Lpg (2)'!B11 -> 85 | K7: ='Lpg (2)'!C11 -> 35 | L7: ='Lpg (2)'!D11 -> 85 | M7: ='Lpg (2)'!G11 -> 124.52 | N7: =D7*1.4 -> 2368.688 | O7: =E7*1.4 -> 454.734 | P7: =('Lpg (2)'!G11)*2.38 -> 296.3576 | Q7: #REF! | R7: =N7/B7 -> 87.729185 | S7: =Q7/B7 -> #REF!
A8: =Gen!A13 -> 44380 | B8: ='Summery Report'!E7 -> 20 | C8: =Gen!U13 -> 0.40530557 | D8: =Gen!S13 -> 1810.5 | E8: =Gen!AJ13 -> 0 | F8: =Gen!AS13 -> 0 | G8: ='Utility report '!AC8 -> 55 | H8: ='Utility report '!AE8 -> 10 | I8: ='Water-Meter'!E8 -> 94 | J8: ='Lpg (2)'!B12 -> 85 | K8: ='Lpg (2)'!C12 -> 30 | L8: ='Lpg (2)'!D12 -> 85 | M8: ='Lpg (2)'!G12 -> 44 | N8: =D8*1.4 -> 2534.7 | O8: =E8*1.4 -> 0 | P8: =('Lpg (2)'!G12)*2.38 -> 104.72 | Q8: #REF! | R8: =N8/B8 -> 126.735 | S8: =Q8/B8 -> #REF!
A9: =Gen!A14 -> 44381 | B9: ='Summery Report'!E8 -> 14 | C9: =Gen!U14 -> 0.40242085 | D9: =Gen!S14 -> 1652.34 | E9: =Gen!AJ14 -> 233.22 | F9: =Gen!AS14 -> 0 | G9: ='Utility report '!AC9 -> 48 | H9: ='Utility report '!AE9 -> 58 | I9: ='Water-Meter'!E9 -> 98 | J9: ='Lpg (2)'!B13 -> 85 | K9: ='Lpg (2)'!C13 -> 20 | L9: ='Lpg (2)'!D13 -> 85 | M9: ='Lpg (2)'!G13 -> 89.364 | N9: =D9*1.4 -> 2313.276 | O9: =E9*1.4 -> 326.508 | P9: =('Lpg (2)'!G13)*2.38 -> 212.68632 | Q9: #REF! | R9: =N9/B9 -> 165.234 | S9: =Q9/B9 -> #REF!
A10: =Gen!A15 -> 44382 | B10: ='Summery Report'!E9 -> 11 | C10: =Gen!U15 -> 0.40842524 | D10: =Gen!S15 -> 1644.32 | E10: =Gen!AJ15 -> 148.61 | F10: =Gen!AS15 -> 0 | G10: ='Utility report '!AC10 -> 50 | H10: ='Utility report '!AE10 -> 44 | I10: ='Water-Meter'!E10 -> 135 | J10: ='Lpg (2)'!B14 -> 85 | K10: ='Lpg (2)'!C14 -> 15 | L10: ='Lpg (2)'!D14 -> 85 | M10: ='Lpg (2)'!G14 -> 112.42 | N10: =D10*1.4 -> 2302.048 | O10: =E10*1.4 -> 208.054 | P10: =('Lpg (2)'!G14)*2.38 -> 267.5596 | Q10: #REF! | R10: =N10/B10 -> 209.27709 | S10: =Q10/B10 -> #REF!
A11: =Gen!A16 -> 44383 | B11: ='Summery Report'!E10 -> 14 | C11: =Gen!U16 -> 0.40270929 | D11: =Gen!S16 -> 1669.23 | E11: =Gen!AJ16 -> 199.93 | F11: =Gen!AS16 -> 0 | G11: ='Utility report '!AC11 -> 113 | H11: ='Utility report '!AE11 -> 52 | I11: ='Water-Meter'!E11 -> 124 | J11: ='Lpg (2)'!B15 -> 85 | K11: ='Lpg (2)'!C15 -> 10 | L11: ='Lpg (2)'!D15 -> 85 | M11: ='Lpg (2)'!G15 -> 116.776 | N11: =D11*1.4 -> 2336.922 | O11: =E11*1.4 -> 279.902 | P11: =('Lpg (2)'!G15)*2.38 -> 277.92688 | Q11: #REF! | R11: =N11/B11 -> 166.923 | S11: =Q11/B11 -> #REF!
A12: =Gen!A17 -> 44384 | B12: ='Summery Report'!E11 -> 29 | C12: =Gen!U17 -> 0.40618396 | D12: =Gen!S17 -> 1898.91 | E12: =Gen!AJ17 -> 168.95 | F12: =Gen!AS17 -> 0 | G12: ='Utility report '!AC12 -> 121 | H12: ='Utility report '!AE12 -> 52 | I12: ='Water-Meter'!E12 -> 114 | J12: ='Lpg (2)'!B16 -> 85 | K12: ='Lpg (2)'!C16 -> 4 | L12: ='Lpg (2)'!D16 -> 85 | M12: ='Lpg (2)'!G16 -> 108.328 | N12: =D12*1.4 -> 2658.474 | O12: =E12*1.4 -> 236.53 | P12: =('Lpg (2)'!G16)*2.38 -> 257.82064 | Q12: #REF! | R12: =N12/B12 -> 91.671517 | S12: =Q12/B12 -> #REF!
A13: =Gen!A18 -> 44385 | B13: ='Summery Report'!E12 -> 35 | C13: =Gen!U18 -> 0.41006374 | D13: =Gen!S18 -> 1865.79 | E13: =Gen!AJ18 -> 47 | F13: =Gen!AS18 -> 0 | G13: ='Utility report '!AC13 -> 201 | H13: ='Utility report '!AE13 -> 57 | I13: ='Water-Meter'!E13 -> 94 | J13: ='Lpg (2)'!B17 -> 85 | K13: ='Lpg (2)'!C17 -> 3 | L13: ='Lpg (2)'!D17 -> 85 | M13: ='Lpg (2)'!G17 -> 112.376 | N13: =D13*1.4 -> 2612.106 | O13: =E13*1.4 -> 65.8 | P13: =('Lpg (2)'!G17)*2.38 -> 267.45488 | Q13: #REF! | R13: =N13/B13 -> 74.6316 | S13: =Q13/B13 -> #REF!
A14: =Gen!A19 -> 44386 | B14: ='Summery Report'!E13 -> 39 | C14: =Gen!U19 -> 0.4239315 | D14: =Gen!S19 -> 1807.22 | E14: =Gen!AJ19 -> 456 | F14: =Gen!AS19 -> 0 | G14: ='Utility report '!AC14 -> 1 | H14: ='Utility report '!AE14 -> 59 | I14: ='Water-Meter'!E14 -> 108 | J14: ='Lpg (2)'!B18 -> 85 | K14: ='Lpg (2)'!C18 -> 2 | L14: ='Lpg (2)'!D18 -> 85 | M14: ='Lpg (2)'!G18 -> 103.4 | N14: =D14*1.4 -> 2530.108 | O14: =E14*1.4 -> 638.4 | P14: =('Lpg (2)'!G18)*2.38 -> 246.092 | Q14: #REF! | R14: =N14/B14 -> 64.874564 | S14: =Q14/B14 -> #REF!
A15: =Gen!A20 -> 44387 | B15: ='Summery Report'!E14 -> 32 | C15: =Gen!U20 -> 0.41897026 | D15: =Gen!S20 -> 1887.88 | E15: =Gen!AJ20 -> 644.97 | F15: =Gen!AS20 -> 0 | G15: ='Utility report '!AC15 -> 70 | H15: ='Utility report '!AE15 -> 56 | I15: ='Water-Meter'!E15 -> 116 | J15: ='Lpg (2)'!B19 -> 85 | K15: ='Lpg (2)'!C19 -> 1 | L15: ='Lpg (2)'!D19 -> 85 | M15: ='Lpg (2)'!G19 -> 117.304 | N15: =D15*1.4 -> 2643.032 | O15: =E15*1.4 -> 902.958 | P15: =('Lpg (2)'!G19)*2.38 -> 279.18352 | Q15: #REF! | R15: =N15/B15 -> 82.59475 | S15: =Q15/B15 -> #REF!
A16: =Gen!A21 -> 44388 | B16: ='Summery Report'!E15 -> 31 | C16: =Gen!U21 -> 0.41547432 | D16: =Gen!S21 -> 1852.6 | E16: =Gen!AJ21 -> 608.62 | F16: =Gen!AS21 -> 0 | G16: ='Utility report '!AC16 -> 41 | H16: ='Utility report '!AE16 -> 0 | I16: ='Water-Meter'!E16 -> 116 | J16: ='Lpg (2)'!B20 -> 85 | K16: ='Lpg (2)'!C20 -> 0 | L16: ='Lpg (2)'!D20 -> 85 | M16: ='Lpg (2)'!G20 -> 115.676 | N16: =D16*1.4 -> 2593.64 | O16: =E16*1.4 -> 852.068 | P16: =('Lpg (2)'!G20)*2.38 -> 275.30888 | Q16: #REF! | R16: =N16/B16 -> 83.665806 | S16: =Q16/B16 -> #REF!
A17: =Gen!A22 -> 44389 | B17: ='Summery Report'!E16 -> 32 | C17: =Gen!U22 -> 0.37453132 | D17: =Gen!S22 -> 1662.17 | E17: =Gen!AJ22 -> 677.99 | F17: =Gen!AS22 -> 0 | G17: ='Utility report '!AC17 -> 40 | H17: ='Utility report '!AE17 -> 1 | I17: ='Water-Meter'!E17 -> 109 | J17: ='Lpg (2)'!B21 -> 85 | K17: ='Lpg (2)'!C22 -> 0 | L17: ='Lpg (2)'!D21 -> 80 | M17: ='Lpg (2)'!G21 -> 126.984 | N17: =D17*1.4 -> 2327.038 | O17: =E17*1.4 -> 949.186 | P17: =('Lpg (2)'!G21)*2.38 -> 302.22192 | Q17: #REF! | R17: =N17/B17 -> 72.719938 | S17: =Q17/B17 -> #REF!
A18: =Gen!A23 -> 44390 | B18: ='Summery Report'!E17 -> 19 | C18: =Gen!U23 -> 0.42904884 | D18: =Gen!S23 -> 1844.91 | E18: =Gen!AJ23 -> 204.13 | F18: =Gen!AS23 -> 0 | G18: ='Utility report '!AC18 -> 37 | H18: ='Utility report '!AE18 -> 60 | I18: ='Water-Meter'!E18 -> 105 | J18: ='Lpg (2)'!B22 -> 85 | K18: ='Lpg (2)'!C23 -> 0 | L18: ='Lpg (2)'!D22 -> 76 | M18: ='Lpg (2)'!G22 -> 117.876 | N18: =D18*1.4 -> 2582.874 | O18: =E18*1.4 -> 285.782 | P18: =('Lpg (2)'!G22)*2.38 -> 280.54488 | Q18: #REF! | R18: =N18/B18 -> 135.94074 | S18: =Q18/B18 -> #REF!
A19: =Gen!A24 -> 44391 | B19: ='Summery Report'!E18 -> 14 | C19: =Gen!U24 -> 0.42290364 | D19: =Gen!S24 -> 1650.17 | E19: =Gen!AJ24 -> 1434.84 | F19: =Gen!AS24 -> 0 | G19: ='Utility report '!AC19 -> 38 | H19: ='Utility report '!AE19 -> 58 | I19: ='Water-Meter'!E19 -> 105 | J19: ='Lpg (2)'!B23 -> 85 | K19: ='Lpg (2)'!C24 -> 0 | L19: ='Lpg (2)'!D23 -> 70 | M19: ='Lpg (2)'!G23 -> 127.776 | N19: =D19*1.4 -> 2310.238 | O19: =E19*1.4 -> 2008.776 | P19: =('Lpg (2)'!G23)*2.38 -> 304.10688 | Q19: #REF! | R19: =N19/B19 -> 165.017 | S19: =Q19/B19 -> #REF!
A20: =Gen!A25 -> 44392 | B20: ='Summery Report'!E19 -> 16 | C20: =Gen!U25 -> 0.4287138 | D20: =Gen!S25 -> 1643.26 | E20: =Gen!AJ25 -> 155.98 | F20: =Gen!AS25 -> 0 | G20: ='Utility report '!AC20 -> 36 | H20: ='Utility report '!AE20 -> 53 | I20: ='Water-Meter'!E20 -> 83 | J20: ='Lpg (2)'!B24 -> 85 | K20: ='Lpg (2)'!C25 -> 0 | L20: ='Lpg (2)'!D24 -> 65 | M20: ='Lpg (2)'!G24 -> 124.74 | N20: =D20*1.4 -> 2300.564 | O20: =E20*1.4 -> 218.372 | P20: =('Lpg (2)'!G24)*2.38 -> 296.8812 | Q20: #REF! | R20: =N20/B20 -> 143.78525 | S20: =Q20/B20 -> #REF!
A21: =Gen!A26 -> 44393 | B21: ='Summery Report'!E20 -> 0 | C21: =Gen!U26 -> 0.42469118 | D21: =Gen!S26 -> 1732.74 | E21: =Gen!AJ26 -> 85.68 | F21: =Gen!AS26 -> 0 | G21: ='Utility report '!AC21 -> 21 | H21: ='Utility report '!AE21 -> 58 | I21: ='Water-Meter'!E21 -> 103 | J21: ='Lpg (2)'!B25 -> 85 | K21: ='Lpg (2)'!C25 -> 0 | L21: ='Lpg (2)'!D25 -> 45 | M21: ='Lpg (2)'!G25 -> 119.064 | N21: =D21*1.4 -> 2425.836 | O21: =E21*1.4 -> 119.952 | P21: =('Lpg (2)'!G25)*2.38 -> 283.37232 | Q21: #REF! | R21: =N21/B21 -> #DIV/0! | S21: =Q21/B21 -> #REF!
A22: =Gen!A27 -> 44394 | B22: ='Summery Report'!E21 -> 0 | C22: =Gen!U27 -> 0.43173021 | D22: =Gen!S27 -> 1766.64 | E22: =Gen!AJ27 -> 496.38 | F22: =Gen!AS27 -> 0 | G22: ='Utility report '!AC22 -> 35 | H22: ='Utility report '!AE22 -> 58 | I22: ='Water-Meter'!E22 -> 107 | J22: ='Lpg (2)'!B26 -> 85 | K22: ='Lpg (2)'!C26 -> 0 | L22: ='Lpg (2)'!D26 -> 38 | M22: ='Lpg (2)'!G26 -> 114.444 | N22: =D22*1.4 -> 2473.296 | O22: =E22*1.4 -> 694.932 | P22: =('Lpg (2)'!G26)*2.38 -> 272.37672 | Q22: #REF! | R22: =N22/B22 -> #DIV/0! | S22: =Q22/B22 -> #REF!
A23: =Gen!A28 -> 44395 | B23: ='Summery Report'!E22 -> 0 | C23: =Gen!U28 -> 0.40179326 | D23: =Gen!S28 -> 1787.98 | E23: =Gen!AJ28 -> 374.23 | F23: =Gen!AS28 -> 0 | G23: ='Utility report '!AC23 -> 42 | H23: ='Utility report '!AE23 -> 22 | I23: ='Water-Meter'!E23 -> 128 | J23: ='Lpg (2)'!B27 -> 85 | K23: ='Lpg (2)'!C27 -> 0 | L23: ='Lpg (2)'!D27 -> 30 | M23: ='Lpg (2)'!G27 -> 104.324 | N23: =D23*1.4 -> 2503.172 | O23: =E23*1.4 -> 523.922 | P23: =('Lpg (2)'!G27)*2.38 -> 248.29112 | Q23: #REF! | R23: =N23/B23 -> #DIV/0! | S23: =Q23/B23 -> #REF!
A24: =Gen!A29 -> 44396 | B24: ='Summery Report'!E23 -> 0 | C24: =Gen!U29 -> 0.39119145 | D24: =Gen!S29 -> 1812.39 | E24: =Gen!AJ29 -> 224 | F24: =Gen!AS29 -> 0 | G24: ='Utility report '!AC24 -> 101 | H24: ='Utility report '!AE24 -> 47 | I24: ='Water-Meter'!E24 -> 115 | J24: ='Lpg (2)'!B28 -> 85 | K24: ='Lpg (2)'!C28 -> 0 | L24: ='Lpg (2)'!D28 -> 27 | M24: ='Lpg (2)'!G28 -> 113.652 | N24: =D24*1.4 -> 2537.346 | O24: =E24*1.4 -> 313.6 | P24: =('Lpg (2)'!G28)*2.38 -> 270.49176 | Q24: #REF! | R24: =N24/B24 -> #DIV/0! | S24: =Q24/B24 -> #REF!
A25: =Gen!A30 -> 44397 | B25: ='Summery Report'!E24 -> 0 | C25: =Gen!U30 -> 0.4251673 | D25: =Gen!S30 -> 2007.64 | E25: =Gen!AJ30 -> 49.26 | F25: =Gen!AS30 -> 0 | G25: ='Utility report '!AC25 -> 155 | H25: ='Utility report '!AE25 -> 25 | I25: ='Water-Meter'!E25 -> 113 | J25: ='Lpg (2)'!B29 -> 85 | K25: ='Lpg (2)'!C29 -> 0 | L25: ='Lpg (2)'!D29 -> 20 | M25: ='Lpg (2)'!G29 -> 111.892 | N25: =D25*1.4 -> 2810.696 | O25: =E25*1.4 -> 68.964 | P25: =('Lpg (2)'!G29)*2.38 -> 266.30296 | Q25: #REF! | R25: =N25/B25 -> #DIV/0! | S25: =Q25/B25 -> #REF!
A26: =Gen!A31 -> 44398 | B26: ='Summery Report'!E25 -> 0 | C26: =Gen!U31 -> 0.40577886 | D26: =Gen!S31 -> 1992.78 | E26: =Gen!AJ31 -> 556.39 | F26: =Gen!AS31 -> 0 | G26: ='Utility report '!AC26 -> 0 | H26: ='Utility report '!AE26 -> 43 | I26: ='Water-Meter'!E26 -> 133 | J26: ='Lpg (2)'!B30 -> 85 | K26: ='Lpg (2)'!C30 -> 0 | L26: ='Lpg (2)'!D30 -> 15 | M26: ='Lpg (2)'!G30 -> 336.116 | N26: =D26*1.4 -> 2789.892 | O26: =E26*1.4 -> 778.946 | P26: =('Lpg (2)'!G30)*2.38 -> 799.95608 | Q26: #REF! | R26: =N26/B26 -> #DIV/0! | S26: =Q26/B26 -> #REF!
A27: =Gen!A32 -> 44399 | B27: ='Summery Report'!E26 -> 0 | C27: =Gen!U32 -> 0.4272656 | D27: =Gen!S32 -> 2232.89 | E27: =Gen!AJ32 -> 494.65 | F27: =Gen!AS32 -> 0 | G27: ='Utility report '!AC27 -> 167 | H27: ='Utility report '!AE27 -> 57 | I27: ='Water-Meter'!E27 -> 113 | J27: ='Lpg (2)'!B31 -> 85 | K27: ='Lpg (2)'!C31 -> 0 | L27: ='Lpg (2)'!D31 -> 9 | M27: ='Lpg (2)'!G31 -> -106.612 | N27: =D27*1.4 -> 3126.046 | O27: =E27*1.4 -> 692.51 | P27: =('Lpg (2)'!G31)*2.38 -> -253.73656 | Q27: #REF! | R27: =N27/B27 -> #DIV/0! | S27: =Q27/B27 -> #REF!
A28: =Gen!A33 -> 44400 | B28: ='Summery Report'!E27 -> 0 | C28: =Gen!U33 -> 0.44202748 | D28: =Gen!S33 -> 2090.79 | E28: =Gen!AJ33 -> 228.3 | F28: =Gen!AS33 -> 0 | G28: ='Utility report '!AC28 -> 163 | H28: ='Utility report '!AE28 -> 23 | I28: ='Water-Meter'!E28 -> 108 | J28: ='Lpg (2)'!B32 -> 85 | K28: ='Lpg (2)'!C32 -> 0 | L28: ='Lpg (2)'!D32 -> 5 | M28: ='Lpg (2)'!G32 -> 98.296 | N28: =D28*1.4 -> 2927.106 | O28: =E28*1.4 -> 319.62 | P28: =('Lpg (2)'!G32)*2.38 -> 233.94448 | Q28: #REF! | R28: =N28/B28 -> #DIV/0! | S28: =Q28/B28 -> #REF!
A29: =Gen!A34 -> 44401 | B29: ='Summery Report'!E28 -> 0 | C29: =Gen!U34 -> 0.41293913 | D29: =Gen!S34 -> 2014.73 | E29: =Gen!AJ34 -> 442.98 | F29: =Gen!AS34 -> 0 | G29: ='Utility report '!AC29 -> 0 | H29: ='Utility report '!AE29 -> 67 | I29: ='Water-Meter'!E29 -> 106 | J29: ='Lpg (2)'!B33 -> 85 | K29: ='Lpg (2)'!C33 -> 0 | L29: ='Lpg (2)'!D33 -> 2 | M29: ='Lpg (2)'!G33 -> 98.868 | N29: =D29*1.4 -> 2820.622 | O29: =E29*1.4 -> 620.172 | P29: =('Lpg (2)'!G33)*2.38 -> 235.30584 | Q29: #REF! | R29: =N29/B29 -> #DIV/0! | S29: =Q29/B29 -> #REF!
A30: =Gen!A35 -> 44402 | B30: ='Summery Report'!E29 -> 0 | C30: =Gen!U35 -> 0.40641226 | D30: =Gen!S35 -> 1869.09 | E30: =Gen!AJ35 -> 259.79 | F30: =Gen!AS35 -> 0 | G30: ='Utility report '!AC30 -> 81 | H30: ='Utility report '!AE30 -> 64 | I30: ='Water-Meter'!E30 -> 106 | J30: ='Lpg (2)'!B34 -> 85 | K30: ='Lpg (2)'!C34 -> 0 | L30: ='Lpg (2)'!D34 -> 1 | M30: ='Lpg (2)'!G34 -> 106.392 | N30: =D30*1.4 -> 2616.726 | O30: =E30*1.4 -> 363.706 | P30: =('Lpg (2)'!G34)*2.38 -> 253.21296 | Q30: #REF! | R30: =N30/B30 -> #DIV/0! | S30: =Q30/B30 -> #REF!
A31: =Gen!A36 -> 44403 | B31: ='Summery Report'!E30 -> 0 | C31: =Gen!U36 -> 0.42781427 | D31: =Gen!S36 -> 1888.8 | E31: =Gen!AJ36 -> 70.92 | F31: =Gen!AS36 -> 0 | G31: ='Utility report '!AC31 -> 25 | H31: ='Utility report '!AE31 -> 58 | I31: ='Water-Meter'!E31 -> 96 | J31: ='Lpg (2)'!B35 -> 85 | K31: ='Lpg (2)'!C35 -> 0 | L31: ='Lpg (2)'!D35 -> 1 | M31: ='Lpg (2)'!G35 -> 93.324 | N31: =D31*1.4 -> 2644.32 | O31: =E31*1.4 -> 99.288 | P31: =('Lpg (2)'!G35)*2.38 -> 222.11112 | Q31: #REF! | R31: =N31/B31 -> #DIV/0! | S31: =Q31/B31 -> #REF!
A32: =Gen!A37 -> 44404 | B32: ='Summery Report'!E31 -> 0 | C32: =Gen!U37 -> 0.41703712 | D32: =Gen!S37 -> 1921.29 | E32: =Gen!AJ37 -> 491.89 | F32: =Gen!AS37 -> 0 | G32: ='Utility report '!AC32 -> 93 | H32: ='Utility report '!AE32 -> 47 | I32: ='Water-Meter'!E32 -> 103 | J32: ='Lpg (2)'!B36 -> 85 | K32: ='Lpg (2)'!C36 -> 0 | L32: ='Lpg (2)'!D36 -> 0 | M32: ='Lpg (2)'!G36 -> 74.228 | N32: =D32*1.4 -> 2689.806 | O32: =E32*1.4 -> 688.646 | P32: =('Lpg (2)'!G36)*2.38 -> 176.66264 | Q32: #REF! | R32: =N32/B32 -> #DIV/0! | S32: =Q32/B32 -> #REF!
... A36: =Gen!A41 -> 44408 | B36: ='Summery Report'!E35 -> 0 | C36: =Gen!U41 -> 0.41843587 | D36: =Gen!S41 -> 1680.02 | E36: =Gen!AJ41 -> 376.24 | F36: =Gen!AS41 -> 0 | G36: ='Utility report '!AC36 -> 65 | H36: ='Utility report '!AE36 -> 50 | I36: ='Water-Meter'!E36 -> 99 | J36: ='Lpg (2)'!B40 -> 76 | K36: ='Lpg (2)'!C40 -> 0 | L36: ='Lpg (2)'!D40 -> 0 | M36: ='Lpg (2)'!G40 -> 111.232 | N36: =D36*1.4 -> 2352.028 | O36: =E36*1.4 -> 526.736 | P36: =('Lpg (2)'!G40)*2.38 -> 264.73216 | Q36: #REF! | R36: =N36/B36 -> #DIV/0! | S36: =Q36/B36 -> #REF!
B37: ='Summery Report'!E36 -> 0 | C37: =Gen!U42 -> 0 | D37: =Gen!S42 -> 0 | E37: =Gen!AJ42 -> 0 | F37: =Gen!AS42 -> 0 | I37: ='Water-Meter'!E37 -> 0 | J37: ='Lpg (2)'!B41 -> 0 | K37: ='Lpg (2)'!C41 -> 0 | L37: ='Lpg (2)'!D41 -> 0 | Q37: #REF! | R37: =N37/B37 -> #DIV/0! | S37: =Q37/B37 -> #REF!
A39: Total | B39: =SUM(B7:B37) -> 333 | C39: =AVERAGE(C6:C36) -> 0.41518431 | D39: =SUM(D7:D35) -> 53210.23 | E39: =SUM(E7:E36) -> 10219.18 | F39: =SUM(F7:F35) -> 0 | G39: =SUM(G7:G36) -> 2193 | H39: =SUM(H7:H36) -> 1365 | I39: =SUM(I7:I36) -> 3263 | J39: =SUM(J7:J36) -> 2535 | K39: =SUM(K7:K36) -> 120 | L39: =SUM(L7:L36) -> 1334 | M39: =SUM(M7:M36) -> 3342.9 | N39: =SUM(N7:N36) -> 76846.35 | O39: =SUM(O7:O36) -> 14306.852 | P39: =SUM(P7:P35) -> 7691.3698 | Q39: =SUM(Q7:Q35) -> #REF! | R39: =SUM(R7:R35) -> #DIV/0! | S39: =SUM(S7:S35) -> #REF!

Sheet Utility report 
A1: =A6 -> 44378
A2: Date | B2: Total occupancy | H2: Diesel balance LTS | I2: Diesel Deliveries | J2: Gen.Diesel consumption LTS | L2: Total Diesel consumption LTS | M2: Water Meter reading | N2: Water consumption m³ | O2: R.O WATER PRODUCTION LTRS + TIME | AA2: Total RO production | AB2: RO Meter reading | AD2: 0 | AE2: STP | AF2: GAS TANK A | AG2: GAS TANK B | AH2: GAS TANK C | AI2: Total Gas Tanks | AJ2: Kg /day | AK2: TOTAL GAS cons.
A3: Rate Tsh /$ | B3: 1640 | C3: Diesel cost / lits | D3: 2175 | F3: =SUM(D3/B3) -> 1.3262195 | H3: =Gen!C11 -> 29939.14 | K3: Transport consumption | M3: Balance | O3: PLANT NO 1 | S3: PLANT NO 2 | W3: PLANT NO 3 | AA3: /day | AB3: Balance | AD3: 0 | AE3: Production | AF3: Capacity | AG3: Capacity | AH3: Capacity | AI3: Kg | AJ3: /day | AK3: /day
B4: Rooms OCC | C4: % | D4: Guest Rooms Occ | F4: Electricity Production Cost /Room Occ by guest | G4: All Cost /Room Occ by guest | O4: Flow M3 | P4: Reading Hours Meter | Q4: Hrs | R4: total production M3 | S4: Flow M3 | T4: Reading Hours Meter | U4: Hrs | V4: total production M3 | W4: Flow M3 | X4: READING HOURS METER | Y4: Hrs | Z4: total production M3 | AA4: M3 | AC4: M3 | AE4: M3 | AF4: 2000 | AG4: 1000 | AH4: 1000 | AI4: #VALUE! | AJ4: Kg | AK4: M3
P5: 19038 | T5: 18452 | X5: 28673 | AB5: 5440 | AD5: 218871 | AF5: 0.85 | AG5: 0.85 | AH5: 0.85
A6: =Gen!A11 -> 44378 | B6: ='Summery Report'!E5 -> 23 | C6: =Gen!B11 -> 0.3 | D6: ='Summery Report'!E5 -> 23 | E6: =SUM(F3) -> 1.3262195 | F6: =SUM(J6*E6)/D6 -> 245.86957 | G6: =SUM(L6*E6)/D6 -> 245.86957 | H6: =Gen!C11 -> 29939.14 | I6: =Gen!E11 -> 0 | J6: =Gen!T11 -> 4264 | K6: =Gen!AK11 -> 0 | L6: =SUM(J6:K6) -> 4264 | M6: ='Water-Meter'!K46 -> 486.19483 | N6: ='Water-Meter'!E6 -> 109 | P6: 19038 | Q6: =SUM(P6-P5) -> 0 | R6: =SUM(Q6*O6) -> 0 | S6: 7.2 | T6: 18471 | U6: =T6-T5 -> 19 | V6: - | W6: 1.6 | X6: 28673 | Y6: =X6-X5 -> 0 | Z6: =Y6-Y5 -> 0 | AA6: =Z6-Z5 -> 0 | AB6: 5520 | AC6: =AB6-AB5 -> 80 | AD6: 218904 | AE6: =AD6-AD5 -> 33 | AF6: ='Lpg (2)'!B10*2000/85 -> 2000 | AG6: ='Lpg (2)'!C10*1000/85 -> 435.29412 | AH6: ='Lpg (2)'!D10*1000/85 -> 1000 | AI6: =SUM(AF6*2000)+(AG6*1000)+(AH6*1000) -> 5435294.1 | AJ6: =SUM(AI5-AI6) -> -5435294.1
A7: =Gen!A12 -> 44379 | B7: ='Summery Report'!E6 -> 27 | C7: =Gen!B12 -> 0.35 | D7: ='Summery Report'!E6 -> 27 | E7: =SUM(E6) -> 1.3262195 | F7: =SUM(J7*E7)/D7 -> 209.93564 | G7: =SUM(L7*E7)/D7 -> 209.93564 | H7: =Gen!C12 -> 28139.56 | I7: =Gen!E12 -> 0 | J7: =Gen!T12 -> 4274 | K7: =Gen!AK12 -> 0 | L7: =SUM(J7:K7) -> 4274 | M7: ='Water-Meter'!K47 -> 486.2234 | N7: ='Water-Meter'!E7 -> 101 | P7: 19038 | Q7: =SUM(P7-P6) -> 0 | R7: =SUM(Q7*O7) -> 0 | S7: 7.2 | T7: 18494 | U7: =T7-T6 -> 23 | V7: =SUM(U7*S7) -> 165.6 | W7: 1.6 | X7: 28673 | Y7: =X7-X6 -> 0 | Z7: =SUM(Y7*W7) -> 0 | AA7: =SUM(Z7*X9) -> 0 | AB7: 5580 | AC7: =AB7-AB6 -> 60 | AD7: 218939 | AE7: =AD7-AD6 -> 35 | AF7: ='Lpg (2)'!B11*2000/85 -> 2000 | AG7: ='Lpg (2)'!C11*1000/85 -> 411.76471 | AH7: ='Lpg (2)'!D11*1000/85 -> 1000 | AI7: =SUM(AF6*2000)+(AG7*1000)+(AH7*1000) -> 5411764.7 | AJ7: =SUM(AI6-AI7) -> 23529.412
A8: =Gen!A13 -> 44380 | B8: ='Summery Report'!E7 -> 20 | C8: =Gen!B13 -> 0.2609 | D8: ='Summery Report'!E7 -> 20 | E8: =SUM(E7) -> 1.3262195 | F8: =SUM(J8*E8)/D8 -> 296.21113 | G8: =SUM(L8*E8)/D8 -> 296.21113 | H8: =Gen!C13 -> 44122.83 | I8: =Gen!E13 -> 18000 | J8: =Gen!T13 -> 4467 | K8: =Gen!AK13 -> 0 | L8: =SUM(J8:K8) -> 4467 | M8: ='Water-Meter'!K48 -> 535.73281 | N8: ='Water-Meter'!E8 -> 94 | P8: 19038 | Q8: =SUM(P8-P7) -> 0 | R8: =SUM(Q8*O8) -> 0 | S8: 7.1 | T8: 18500 | U8: =T8-T7 -> 6 | V8: =SUM(U8*S8) -> 42.6 | W8: 1.6 | X8: 28673 | Y8: =X8-X7 -> 0 | Z8: =SUM(Y8*W8) -> 0 | AA8: =SUM(Z8*X10) -> 0 | AB8: 5635 | AC8: =AB8-AB7 -> 55 | AD8: 218949 | AE8: =AD8-AD7 -> 10 | AF8: ='Lpg (2)'!B12*2000/85 -> 2000 | AG8: ='Lpg (2)'!C12*1000/85 -> 352.94118 | AH8: ='Lpg (2)'!D12*1000/85 -> 1000 | AI8: =SUM(AF7*2000)+(AG8*1000)+(AH8*1000) -> 5352941.2 | AJ8: =SUM(AI7-AI8) -> 58823.529
A9: =Gen!A14 -> 44381 | B9: ='Summery Report'!E8 -> 14 | C9: =Gen!B14 -> 0.18 | D9: ='Summery Report'!E8 -> 14 | E9: =SUM(E8) -> 1.3262195 | F9: =SUM(J9*E9)/D9 -> 388.96124 | G9: =SUM(L9*E9)/D9 -> 388.96124 | H9: =Gen!C14 -> 42312.33 | I9: =Gen!E14 -> 0 | J9: =Gen!T14 -> 4106 | K9: =Gen!AK14 -> 0 | L9: =SUM(J9:K9) -> 4106 | M9: ='Water-Meter'!K49 -> 571.29614 | N9: ='Water-Meter'!E9 -> 98 | P9: 19038 | Q9: =SUM(P9-P8) -> 0 | R9: =SUM(Q9*O9) -> 0 | S9: 6.9 | T9: 18501 | U9: =T9-T8 -> 1 | V9: =SUM(U9*S10) -> 6.9 | W9: 1.6 | X9: 28673 | Y9: =X9-X8 -> 0 | Z9: =SUM(Y9*W11) -> 0 | AA9: =SUM(Z9*X11) -> 0 | AB9: 5683 | AC9: =AB9-AB8 -> 48 | AD9: 219007 | AE9: =AD9-AD8 -> 58 | AF9: ='Lpg (2)'!B13*2000/85 -> 2000 | AG9: ='Lpg (2)'!C13*1000/85 -> 235.29412 | AH9: ='Lpg (2)'!D13*1000/85 -> 1000 | AI9: =SUM(AF8*2000)+(AG9*1000)+(AH9*1000) -> 5235294.1 | AJ9: =SUM(AI8-AI9) -> 117647.06
A10: =Gen!A15 -> 44382 | B10: ='Summery Report'!E9 -> 11 | C10: =Gen!B15 -> 0.14 | D10: ='Summery Report'!E9 -> 11 | E10: =SUM(E9) -> 1.3262195 | F10: =SUM(J10*E10)/D10 -> 485.39634 | G10: =SUM(L10*E10)/D10 -> 485.39634 | H10: =Gen!C15 -> 40426.77 | I10: =Gen!E15 -> 0 | J10: =Gen!T15 -> 4026 | K10: =Gen!AK15 -> 0 | L10: =SUM(J10:K10) -> 4026 | M10: ='Water-Meter'!K50 -> 565.93234 | N10: ='Water-Meter'!E10 -> 135 | P10: 19038 | Q10: =SUM(P10-P9) -> 0 | R10: =SUM(Q10*O10) -> 0 | S10: 6.9 | T10: 18502 | U10: =T10-T9 -> 1 | V10: =SUM(U10*S11) -> 6.9 | W10: 1.6 | X10: 28695 | Y10: =X10-X9 -> 22 | Z10: =SUM(Y10*W10) -> 35.2 | AA10: =SUM(Z10*X12) -> 1010908.8 | AB10: 5733 | AC10: =AB10-AB9 -> 50 | AD10: 219051 | AE10: =AD10-AD9 -> 44 | AF10: ='Lpg (2)'!B14*2000/85 -> 2000 | AG10: ='Lpg (2)'!C14*1000/85 -> 176.47059 | AH10: ='Lpg (2)'!D14*1000/85 -> 1000 | AI10: =SUM(AF9*2000)+(AG10*1000)+(AH10*1000) -> 5176470.6 | AJ10: =SUM(AI9-AI10) -> 58823.529
A11: =Gen!A16 -> 44383 | B11: ='Summery Report'!E10 -> 14 | C11: =Gen!B16 -> 0.169 | D11: ='Summery Report'!E10 -> 14 | E11: =SUM(E10) -> 1.3262195 | F11: =SUM(J11*E11)/D11 -> 392.65571 | G11: =SUM(L11*E11)/D11 -> 392.65571 | H11: =Gen!C16 -> 38633.84 | I11: =Gen!E16 -> 0 | J11: =Gen!T16 -> 4145 | K11: =Gen!AK16 -> 0 | L11: =SUM(J11:K11) -> 4145 | M11: ='Water-Meter'!K51 -> 459.57978 | N11: ='Water-Meter'!E11 -> 124 | P11: 19038 | Q11: =SUM(P11-P10) -> 0 | R11: =SUM(Q11*O11) -> 0 | S11: 6.9 | T11: 18504 | U11: =T11-T10 -> 2 | V11: =SUM(U11*S12) -> 14.2 | W11: 1.6 | X11: 28695 | Y11: =X11-X10 -> 0 | Z11: =SUM(Y11*W11) -> 0 | AA11: =SUM(Z11*X13) -> 0 | AB11: 5846 | AC11: =AB11-AB10 -> 113 | AD11: 219103 | AE11: =AD11-AD10 -> 52 | AF11: ='Lpg (2)'!B15*2000/85 -> 2000 | AG11: ='Lpg (2)'!C15*1000/85 -> 117.64706 | AH11: ='Lpg (2)'!D15*1000/85 -> 1000 | AI11: =SUM(AF10*2000)+(AG11*1000)+(AH11*1000) -> 5117647.1 | AJ11: =SUM(AI10-AI11) -> 58823.529
A12: =Gen!A17 -> 44384 | B12: ='Summery Report'!E11 -> 29 | C12: =Gen!B17 -> 0.364 | D12: ='Summery Report'!E11 -> 29 | E12: =SUM(E11) -> 1.3262195 | F12: =SUM(J12*E12)/D12 -> 213.79573 | G12: =SUM(L12*E12)/D12 -> 213.79573 | H12: =Gen!C17 -> 36764.68 | I12: =Gen!E17 -> 0 | J12: =Gen!T17 -> 4675 | K12: =Gen!AK17 -> 0 | L12: =SUM(J12:K12) -> 4675 | M12: ='Water-Meter'!K52 -> 384.44269 | N12: ='Water-Meter'!E12 -> 114 | P12: 19038 | Q12: =SUM(P12-P11) -> 0 | R12: =SUM(Q12*O12) -> 0 | S12: 7.1 | T12: 18516 | U12: =T12-T11 -> 12 | V12: =SUM(U12*S12) -> 85.2 | W12: 1.6 | X12: 28719 | Y12: =X12-X11 -> 24 | Z12: =SUM(Y12*W12) -> 38.4 | AA12: =SUM(Z12*X14) -> 1103769.6 | AB12: 5967 | AC12: =AB12-AB11 -> 121 | AD12: 219155 | AE12: =AD12-AD11 -> 52 | AF12: ='Lpg (2)'!B16*2000/85 -> 2000 | AG12: ='Lpg (2)'!C16*1000/85 -> 47.058824 | AH12: ='Lpg (2)'!D16*1000/85 -> 1000 | AI12: =SUM(AF11*2000)+(AG12*1000)+(AH12*1000) -> 5047058.8 | AJ12: =SUM(AI11-AI12) -> 70588.235
A13: =Gen!A18 -> 44385 | B13: ='Summery Report'!E12 -> 35 | C13: =Gen!B18 -> 0.455 | D13: ='Summery Report'!E12 -> 35 | E13: =SUM(E12) -> 1.3262195 | F13: =SUM(J13*E13)/D13 -> 172.40854 | G13: =SUM(L13*E13)/D13 -> 172.40854 | H13: =Gen!C18 -> 34696.82 | I13: =Gen!E18 -> 0 | J13: =Gen!T18 -> 4550 | K13: =Gen!AK18 -> 0 | L13: =SUM(J13:K13) -> 4550 | M13: ='Water-Meter'!K53 -> 353.8128 | N13: ='Water-Meter'!E13 -> 94 | P13: 19038 | Q13: =SUM(P13-P12) -> 0 | R13: =SUM(Q13*O13) -> 0 | S13: 7.2 | T13: 18539 | U13: =T13-T12 -> 23 | V13: =SUM(U13*S13) -> 165.6 | W13: 1.7 | X13: 28743 | Y13: =X13-X12 -> 24 | Z13: =SUM(Y13*W13) -> 40.8 | AA13: =SUM(Z13*X15) -> 1172755.2 | AB13: 6168 | AC13: =AB13-AB12 -> 201 | AD13: 219212 | AE13: =AD13-AD12 -> 57 | AF13: ='Lpg (2)'!B17*2000/85 -> 2000 | AG13: ='Lpg (2)'!C17*1000/85 -> 35.294118 | AH13: ='Lpg (2)'!D17*1000/85 -> 1000 | AI13: =SUM(AF12*2000)+(AG13*1000)+(AH13*1000) -> 5035294.1 | AJ13: =SUM(AI12-AI13) -> 11764.706
A14: =Gen!A19 -> 44386 | B14: ='Summery Report'!E13 -> 39 | C14: =Gen!B19 -> 0.468 | D14: ='Summery Report'!E13 -> 39 | E14: =SUM(E13) -> 1.3262195 | F14: =SUM(J14*E14)/D14 -> 144.96599 | G14: =SUM(L14*E14)/D14 -> 144.96599 | H14: =Gen!C19 -> 32784.03 | I14: =Gen!E19 -> 0 | J14: =Gen!T19 -> 4263 | K14: =Gen!AK19 -> 0 | L14: =SUM(J14:K14) -> 4263 | M14: ='Water-Meter'!K54 -> 427.30401 | N14: ='Water-Meter'!E14 -> 108 | P14: 19038 | Q14: =SUM(P14-P13) -> 0 | R14: =SUM(Q14*O14) -> 0 | S14: 7.1 | T14: 18540 | U14: =T14-T13 -> 1 | V14: =SUM(U14*S14) -> 7.1 | W14: 1.6 | X14: 28744 | Y14: =X14-X13 -> 1 | Z14: =SUM(Y14*W14) -> 1.6 | AA14: =SUM(Z14*X16) -> 46051.2 | AB14: 6169 | AC14: =AB14-AB13 -> 1 | AD14: 219271 | AE14: =AD14-AD13 -> 59 | AF14: ='Lpg (2)'!B18*2000/85 -> 2000 | AG14: ='Lpg (2)'!C18*1000/85 -> 23.529412 | AH14: ='Lpg (2)'!D18*1000/85 -> 1000 | AI14: =SUM(AF13*2000)+(AG14*1000)+(AH14*1000) -> 5023529.4 | AJ14: =SUM(AI13-AI14) -> 11764.706
A15: =Gen!A20 -> 44387 | B15: ='Summery Report'!E14 -> 32 | C15: =Gen!B20 -> 0.39 | D15: ='Summery Report'!E14 -> 32 | E15: =SUM(E14) -> 1.3262195 | F15: =SUM(J15*E15)/D15 -> 186.74829 | G15: =SUM(L15*E15)/D15 -> 186.74829 | H15: =Gen!C20 -> 30520.81 | I15: =Gen!E20 -> 0 | J15: =Gen!T20 -> 4506 | K15: =Gen!AK20 -> 0 | L15: =SUM(J15:K15) -> 4506 | M15: ='Water-Meter'!K55 -> 433.33688 | N15: ='Water-Meter'!E15 -> 116 | P15: 19038 | Q15: =SUM(P15-P14) -> 0 | R15: =SUM(Q15*O15) -> 0 | S15: 7.1 | T15: 18548 | U15: =T15-T14 -> 8 | V15: =SUM(U15*S15) -> 56.8 | X15: 28744 | Y15: =X15-X14 -> 0 | Z15: =SUM(Y15*W15) -> 0 | AA15: =SUM(Z15*X17) -> 0 | AB15: 6239 | AC15: =AB15-AB14 -> 70 | AD15: 219327 | AE15: =AD15-AD14 -> 56 | AF15: ='Lpg (2)'!B19*2000/85 -> 2000 | AG15: ='Lpg (2)'!C19*1000/85 -> 11.764706 | AH15: ='Lpg (2)'!D19*1000/85 -> 1000 | AI15: =SUM(AF15*2000)+(AG15*1000)+(AH15*1000) -> 5011764.7 | AJ15: =SUM(AI14-AI15) -> 11764.706
A16: =Gen!A21 -> 44388 | B16: ='Summery Report'!E15 -> 31 | C16: =Gen!B21 -> 0.403 | D16: ='Summery Report'!E15 -> 31 | E16: =SUM(E15) -> 1.3262195 | F16: =SUM(J16*E16)/D16 -> 190.7617 | G16: =SUM(L16*E16)/D16 -> 190.7617 | H16: =Gen!C21 -> 45987.96 | I16: =Gen!E21 -> 0 | J16: =Gen!T21 -> 4459 | K16: =Gen!AK21 -> 0 | L16: =SUM(J16:K16) -> 4459 | M16: ='Water-Meter'!K56 -> 513.3163 | N16: ='Water-Meter'!E16 -> 116 | P16: 19038 | Q16: =SUM(P16-P15) -> 0 | R16: =SUM(Q16*O16) -> 0 | S16: 7.1 | T16: 18548 | U16: =T16-T15 -> 0 | V16: =SUM(U16*S16) -> 0 | W16: 1.7 | X16: 28782 | Y16: =X16-X15 -> 38 | Z16: =SUM(Y16*W16) -> 64.6 | AA16: =SUM(Z16*X18) -> 1862353.4 | AB16: 6280 | AC16: =AB16-AB15 -> 41 | AD16: 219327 | AE16: =AD16-AD15 -> 0 | AF16: ='Lpg (2)'!B20*2000/85 -> 2000 | AG16: ='Lpg (2)'!C20*1000/85 -> 0 | AH16: ='Lpg (2)'!D20*1000/85 -> 1000 | AI16: =SUM(AF16*2000)+(AG16*1000)+(AH16*1000) -> 5000000 | AJ16: =SUM(AI15-AI16) -> 11764.706
A17: =Gen!A22 -> 44389 | B17: ='Summery Report'!E16 -> 32 | C17: =Gen!B22 -> 0.39 | D17: ='Summery Report'!E16 -> 32 | E17: =SUM(E16) -> 1.3262195 | F17: =SUM(J17*E17)/D17 -> 183.93007 | G17: =SUM(L17*E17)/D17 -> 183.93007 | H17: =Gen!C22 -> 43526.74 | I17: =Gen!E22 -> 0 | J17: =Gen!T22 -> 4438 | K17: =Gen!AK22 -> 0 | L17: =SUM(J17:K17) -> 4438 | M17: ='Water-Meter'!K57 -> 541.0714 | N17: ='Water-Meter'!E17 -> 109 | P17: 19038 | Q17: =SUM(P18-P16) -> 0 | R17: =SUM(Q17*O17) -> 0 | S17: 7.1 | T17: 18548 | U17: =T17-T16 -> 0 | V17: =SUM(U17*S17) -> 0 | W17: 1.7 | X17: 28806 | Y17: =X17-X16 -> 24 | Z17: =SUM(Y17*W17) -> 40.8 | AA17: =SUM(Z17*X19) -> 1177202.4 | AB17: 6320 | AC17: =AB17-AB16 -> 40 | AD17: 219328 | AE17: =AD17-AD16 -> 1 | AF17: ='Lpg (2)'!B21*2000/85 -> 2000 | AG17: ='Lpg (2)'!C21*1000/85 -> 0 | AH17: ='Lpg (2)'!D21*1000/85 -> 941.17647 | AI17: =SUM(AF17*2000)+(AG17*1000)+(AH17*1000) -> 4941176.5 | AJ17: =SUM(AI16-AI17) -> 58823.529
A18: =Gen!A23 -> 44390 | B18: ='Summery Report'!E17 -> 19 | C18: =Gen!B23 -> 0.221 | D18: ='Summery Report'!E17 -> 19 | E18: =SUM(E17) -> 1.3262195 | F18: =SUM(J18*E18)/D18 -> 300.14442 | G18: =SUM(L18*E18)/D18 -> 300.14442 | H18: =Gen!C23 -> 41186.58 | I18: =Gen!E23 -> 0 | J18: =Gen!T23 -> 4300 | K18: =Gen!AK23 -> 0 | L18: =SUM(J18:K18) -> 4300 | M18: ='Water-Meter'!K58 -> 585.69948 | N18: ='Water-Meter'!E18 -> 105 | P18: 19038 | R18: =SUM(Q18*O18) -> 0 | S18: 7.1 | T18: 18548 | U18: =T18-T17 -> 0 | V18: =SUM(U18*S18) -> 0 | W18: 1.7 | X18: 28829 | Y18: =X18-X17 -> 23 | Z18: =SUM(Y18*W18) -> 39.1 | AA18: =SUM(Z18*X20) -> 1129090.7 | AB18: 6357 | AC18: =AB18-AB17 -> 37 | AD18: 219388 | AE18: =AD18-AD17 -> 60 | AF18: ='Lpg (2)'!B22*2000/85 -> 2000 | AG18: ='Lpg (2)'!C22*1000/85 -> 0 | AH18: ='Lpg (2)'!D22*1000/85 -> 894.11765 | AI18: =SUM(AF18*2000)+(AG18*1000)+(AH18*1000) -> 4894117.6 | AJ18: =SUM(AI17-AI18) -> 47058.824
A19: =Gen!A24 -> 44391 | B19: ='Summery Report'!E18 -> 14 | C19: =Gen!B24 -> 0.195 | D19: ='Summery Report'!E18 -> 14 | E19: =SUM(E18) -> 1.3262195 | F19: =SUM(J19*E19)/D19 -> 369.63632 | G19: =SUM(L19*E19)/D19 -> 369.63632 | H19: =Gen!C24 -> 39137.54 | I19: =Gen!E24 -> 18000 | J19: =Gen!T24 -> 3902 | K19: =Gen!AK24 -> 0 | L19: =SUM(J19:K19) -> 3902 | M19: ='Water-Meter'!K59 -> 599.92981 | N19: ='Water-Meter'!E19 -> 105 | P19: 19038 | R19: =SUM(Q19*O19) -> 0 | S19: 7.1 | T19: 18548 | U19: =T19-T18 -> 0 | V19: =SUM(U19*S19) -> 0 | W19: 1.7 | X19: 28853 | Y19: =X19-X18 -> 24 | Z19: =SUM(Y19*W19) -> 40.8 | AA19: =SUM(Z19*X21) -> 1178752.8 | AB19: 6395 | AC19: =AB19-AB18 -> 38 | AD19: 219446 | AE19: =AD19-AD18 -> 58 | AF19: ='Lpg (2)'!B23*2000/85 -> 2000 | AG19: ='Lpg (2)'!C23*1000/85 -> 0 | AH19: ='Lpg (2)'!D23*1000/85 -> 823.52941 | AI19: =SUM(AF19*2000)+(AG19*1000)+(AH19*1000) -> 4823529.4 | AJ19: =SUM(AI18-AI19) -> 70588.235
A20: =Gen!A25 -> 44392 | B20: ='Summery Report'!E19 -> 16 | C20: =Gen!B25 -> 0.208 | D20: ='Summery Report'!E19 -> 16 | E20: =SUM(E19) -> 1.3262195 | F20: =SUM(J20*E20)/D20 -> 317.71246 | G20: =SUM(L20*E20)/D20 -> 317.71246 | H20: =Gen!C25 -> 36052.53 | I20: =Gen!E25 -> 0 | J20: =Gen!T25 -> 3833 | K20: =Gen!AK25 -> 0 | L20: =SUM(J20:K20) -> 3833 | M20: ='Water-Meter'!K60 -> 535.35338 | N20: ='Water-Meter'!E20 -> 83 | P20: 19038 | Q20: =SUM(P20-P19) -> 0 | R20: =SUM(Q20*O20) -> 0 | S20: 7.1 | T20: 18548 | U20: =T20-T19 -> 0 | V20: =SUM(U20*S20) -> 0 | W20: 1.5 | X20: 28877 | Y20: =X20-X19 -> 24 | Z20: =SUM(Y20*W20) -> 36 | AA20: =SUM(Z20*X22) -> 1040076 | AB20: 6431 | AC20: =AB20-AB19 -> 36 | AD20: 219499 | AE20: =AD20-AD19 -> 53 | AF20: ='Lpg (2)'!B24*2000/85 -> 2000 | AG20: ='Lpg (2)'!C24*1000/85 -> 0 | AH20: ='Lpg (2)'!D24*1000/85 -> 764.70588 | AI20: =SUM(AF20*2000)+(AG20*1000)+(AH20*1000) -> 4764705.9 | AJ20: =SUM(AI19-AI20) -> 58823.529
A21: =Gen!A26 -> 44393 | B21: ='Summery Report'!E20 -> 0 | C21: =Gen!B26 -> 0.27 | D21: ='Summery Report'!E20 -> 0 | E21: =SUM(E20) -> 1.3262195 | F21: =SUM(J21*E21)/D21 -> #DIV/0! | G21: =SUM(L21*E21)/D21 -> #DIV/0! | H21: =Gen!C26 -> 34253.29 | I21: =Gen!E26 -> 0 | J21: =Gen!T26 -> 4080 | K21: =Gen!AK26 -> 0 | L21: =SUM(J21:K21) -> 4080 | M21: ='Water-Meter'!K61 -> 517.67916 | N21: ='Water-Meter'!E21 -> 103 | P21: 19038 | Q21: =SUM(P21-P20) -> 0 | R21: =SUM(Q21*O21) -> 0 | S21: 7.1 | T21: 18548 | U21: =T21-T20 -> 0 | V21: =SUM(U21*S21) -> 0 | W21: 1.5 | X21: 28891 | Y21: =X21-X20 -> 14 | Z21: =SUM(Y21*W21) -> 21 | AA21: =SUM(Z21*X23) -> 606711 | AB21: 6452 | AC21: =AB21-AB20 -> 21 | AD21: 219557 | AE21: =AD21-AD20 -> 58 | AF21: ='Lpg (2)'!B25*2000/85 -> 2000 | AG21: ='Lpg (2)'!C25*1000/85 -> 0 | AH21: ='Lpg (2)'!D25*1000/85 -> 529.41176 | AI21: =SUM(AF21*2000)+(AG21*1000)+(AH21*1000) -> 4529411.8 | AJ21: =SUM(AI20-AI21) -> 235294.12
A22: =Gen!A27 -> 44394 | B22: ='Summery Report'!E21 -> 0 | C22: =Gen!B27 -> 0.26 | D22: ='Summery Report'!E21 -> 0 | E22: =SUM(E21) -> 1.3262195 | F22: =SUM(J22*E22)/D22 -> #DIV/0! | G22: =SUM(L22*E22)/D22 -> #DIV/0! | H22: =Gen!C27 -> 32434.87 | I22: =Gen!E27 -> 0 | J22: =Gen!T27 -> 4092 | K22: =Gen!AK27 -> 0 | L22: =SUM(J22:K22) -> 4092 | M22: ='Water-Meter'!K62 -> 561.96719 | N22: ='Water-Meter'!E22 -> 107 | P22: 19038 | Q22: =SUM(P22-P21) -> 0 | R22: =SUM(Q22*O22) -> 0 | S22: 7.1 | T22: 18548 | U22: =T22-T21 -> 0 | V22: =SUM(U22*S22) -> 0 | W22: 1.5 | X22: 28891 | Y22: =X22-X21 -> 0 | Z22: =SUM(Y22*W22) -> 0 | AA22: =SUM(Z22*X24) -> 0 | AB22: 6487 | AC22: =AB22-AB21 -> 35 | AD22: 219615 | AE22: =AD22-AD21 -> 58 | AF22: ='Lpg (2)'!B26*2000/85 -> 2000 | AG22: ='Lpg (2)'!C26*1000/85 -> 0 | AH22: ='Lpg (2)'!D26*1000/85 -> 447.05882 | AI22: =SUM(AF22*2000)+(AG22*1000)+(AH22*1000) -> 4447058.8 | AJ22: =SUM(AI21-AI22) -> 82352.941
A23: =Gen!A28 -> 44395 | B23: ='Summery Report'!E22 -> 0 | C23: =Gen!B28 -> 0.35 | D23: ='Summery Report'!E22 -> 0 | E23: =SUM(E22) -> 1.3262195 | F23: =SUM(J23*E23)/D23 -> #DIV/0! | G23: =SUM(L23*E23)/D23 -> #DIV/0! | H23: =Gen!C28 -> 30171.85 | I23: =Gen!E28 -> 0 | J23: =Gen!T28 -> 4450 | K23: =Gen!AK28 -> 0 | L23: =SUM(J23:K23) -> 4450 | M23: ='Water-Meter'!K63 -> 598.40501 | N23: ='Water-Meter'!E23 -> 128 | P23: 19038 | Q23: =SUM(P23-P22) -> 0 | R23: =SUM(Q23*O23) -> 0 | S23: 7.1 | T23: 18556 | U23: =T23-T22 -> 8 | V23: =SUM(U23*S23) -> 56.8 | W23: 1.5 | X23: 28891 | Y23: =X23-X22 -> 0 | Z23: =SUM(Y23*W23) -> 0 | AA23: =SUM(Z23*X25) -> 0 | AB23: 6529 | AC23: =AB23-AB22 -> 42 | AD23: 219637 | AE23: =AD23-AD22 -> 22 | AF23: ='Lpg (2)'!B27*2000/85 -> 2000 | AG23: ='Lpg (2)'!C27*1000/85 -> 0 | AH23: ='Lpg (2)'!D27*1000/85 -> 352.94118 | AI23: =SUM(AF23*2000)+(AG23*1000)+(AH23*1000) -> 4352941.2 | AJ23: =SUM(AI22-AI23) -> 94117.647
A24: =Gen!A29 -> 44396 | B24: ='Summery Report'!E23 -> 0 | C24: =Gen!B29 -> 0.39 | D24: ='Summery Report'!E23 -> 0 | E24: =SUM(E23) -> 1.3262195 | F24: =SUM(J24*E24)/D24 -> #DIV/0! | G24: =SUM(L24*E24)/D24 -> #DIV/0! | H24: =Gen!C29 -> 28009.64 | I24: =Gen!E29 -> 0 | J24: =Gen!T29 -> 4633 | K24: =Gen!AK29 -> 0 | L24: =SUM(J24:K24) -> 4633 | M24: ='Water-Meter'!K64 -> 490.51432 | N24: ='Water-Meter'!E24 -> 115 | P24: 19038 | Q24: =SUM(P24-P23) -> 0 | R24: =SUM(Q24*O24) -> 0 | S24: 7.1 | T24: 18571 | U24: =T24-T23 -> 15 | V24: =SUM(U24*S24) -> 106.5 | W24: 1.5 | X24: 28891 | Y24: =X24-X23 -> 0 | Z24: =SUM(Y24*W24) -> 0 | AA24: =SUM(Z24*X26) -> 0 | AB24: 6630 | AC24: =AB24-AB23 -> 101 | AD24: 219684 | AE24: =AD24-AD23 -> 47 | AF24: ='Lpg (2)'!B28*2000/85 -> 2000 | AG24: ='Lpg (2)'!C28*1000/85 -> 0 | AH24: ='Lpg (2)'!D28*1000/85 -> 317.64706 | AI24: =SUM(AF24*2000)+(AG24*1000)+(AH24*1000) -> 4317647.1 | AJ24: =SUM(AI23-AI24) -> 35294.118
A25: =Gen!A30 -> 44397 | B25: ='Summery Report'!E24 -> 0 | C25: =Gen!B30 -> 0.39 | D25: ='Summery Report'!E24 -> 0 | E25: =SUM(E24) -> 1.3262195 | F25: =SUM(J25*E25)/D25 -> #DIV/0! | G25: =SUM(L25*E25)/D25 -> #DIV/0! | H25: =Gen!C30 -> 25973.25 | I25: =Gen!E30 -> 0 | J25: =Gen!T30 -> 4722 | K25: =Gen!AK30 -> 0 | L25: =SUM(J25:K25) -> 4722 | M25: ='Water-Meter'!K65 -> 494.66639 | N25: ='Water-Meter'!E25 -> 113 | P25: 19038 | Q25: =SUM(P25-P24) -> 0 | R25: =SUM(Q25*O25) -> 0 | S25: 6.7 | T25: 18592 | U25: =T25-T24 -> 21 | V25: =SUM(U25*S25) -> 140.7 | W25: 1.5 | X25: 28891 | Y25: =X25-X24 -> 0 | Z25: =SUM(Y25*W25) -> 0 | AA25: =SUM(Z25*X27) -> 0 | AB25: 6785 | AC25: =AB25-AB24 -> 155 | AD25: 219709 | AE25: =AD25-AD24 -> 25 | AF25: ='Lpg (2)'!B29*2000/85 -> 2000 | AG25: ='Lpg (2)'!C29*1000/85 -> 0 | AH25: ='Lpg (2)'!D29*1000/85 -> 235.29412 | AI25: =SUM(AF25*2000)+(AG25*1000)+(AH25*1000) -> 4235294.1 | AJ25: =SUM(AI24-AI25) -> 82352.941
A26: =Gen!A31 -> 44398 | B26: ='Summery Report'!E25 -> 0 | C26: =Gen!B31 -> 0.55 | D26: ='Summery Report'!E25 -> 0 | E26: =SUM(E25) -> 1.3262195 | F26: =SUM(J26*E26)/D26 -> #DIV/0! | G26: =SUM(L26*E26)/D26 -> #DIV/0! | H26: =Gen!C31 -> 23916.35 | I26: =Gen!E31 -> 0 | J26: =Gen!T31 -> 4911 | K26: =Gen!AK31 -> 0 | L26: =SUM(J26:K26) -> 4911 | M26: ='Water-Meter'!K66 -> 493.1609 | N26: ='Water-Meter'!E26 -> 133 | P26: 19038 | Q26: =SUM(P26-P25) -> 0 | R26: =SUM(Q26*O26) -> 0 | S26: 6.7 | T26: 18592 | U26: =T26-T25 -> 0 | V26: =SUM(U26*S26) -> 0 | W26: 1.5 | X26: 28891 | Y26: =X26-X25 -> 0 | Z26: =SUM(Y26*W27) -> 0 | AA26: =SUM(Z26*X28) -> 0 | AB26: 6785 | AC26: =AB26-AB25 -> 0 | AD26: 219752 | AE26: =AD26-AD25 -> 43 | AF26: ='Lpg (2)'!B30*2000/85 -> 2000 | AG26: ='Lpg (2)'!C30*1000/85 -> 0 | AH26: ='Lpg (2)'!D30*1000/85 -> 176.47059 | AI26: =SUM(AF26*2000)+(AG26*1000)+(AH26*1000) -> 4176470.6 | AJ26: =SUM(AI25-AI26) -> 58823.529
A27: =Gen!A32 -> 44399 | B27: ='Summery Report'!E26 -> 0 | C27: =Gen!B32 -> 0.545 | D27: ='Summery Report'!E26 -> 0 | E27: =SUM(E26) -> 1.3262195 | F27: =SUM(J27*E27)/D27 -> #DIV/0! | G27: =SUM(L27*E27)/D27 -> #DIV/0! | H27: =Gen!C32 -> 21367.18 | I27: =Gen!E32 -> 0 | J27: =Gen!T32 -> 5226 | K27: =Gen!AK32 -> 0 | L27: =SUM(J27:K27) -> 5226 | M27: ='Water-Meter'!K67 -> 451.95098 | N27: ='Water-Meter'!E27 -> 113 | P27: 19038 | Q27: =SUM(P27-P26) -> 0 | R27: =SUM(Q27*O27) -> 0 | S27: 7.1 | T27: 18616 | U27: =T27-T26 -> 24 | V27: =SUM(U27*S27) -> 170.4 | W27: 1.5 | X27: 28891 | Y27: =X27-X26 -> 0 | Z27: =SUM(Y27*#REF!) -> #REF! | AA27: =SUM(Z27*X29) -> #REF! | AB27: 6952 | AC27: =AB27-AB26 -> 167 | AD27: 219809 | AE27: =AD27-AD26 -> 57 | AF27: ='Lpg (2)'!B31*2000/85 -> 2000 | AG27: ='Lpg (2)'!C31*1000/85 -> 0 | AH27: ='Lpg (2)'!D31*1000/85 -> 105.88235 | AI27: =SUM(AF27*2000)+(AG27*1000)+(AH27*1000) -> 4105882.4 | AJ27: =SUM(AI26-AI27) -> 70588.235
A28: =Gen!A33 -> 44400 | B28: ='Summery Report'!E27 -> 0 | C28: =Gen!B33 -> 0.455 | D28: ='Summery Report'!E27 -> 0 | E28: =SUM(E27) -> 1.3262195 | F28: =SUM(J28*E28)/D28 -> #DIV/0! | G28: =SUM(L28*E28)/D28 -> #DIV/0! | H28: =Gen!C33 -> 18639.64 | I28: =Gen!E33 -> 0 | J28: =Gen!T33 -> 4730 | K28: =Gen!AK33 -> 0 | L28: =SUM(J28:K28) -> 4730 | M28: ='Water-Meter'!K68 -> 419.79785 | N28: ='Water-Meter'!E28 -> 108 | P28: 19038 | Q28: =SUM(P28-P27) -> 0 | R28: =SUM(Q28*O28) -> 0 | S28: 7.1 | T28: 18639 | U28: =T28-T27 -> 23 | V28: =SUM(U28*S28) -> 163.3 | W28: 1.5 | X28: 28891 | Y28: =X28-X27 -> 0 | Z28: =SUM(Y28*W28) -> 0 | AA28: =SUM(Z28*X30) -> 0 | AB28: 7115 | AC28: =SUM(AB28-AB27) -> 163 | AD28: 219832 | AE28: =AD28-AD27 -> 23 | AF28: ='Lpg (2)'!B32*2000/85 -> 2000 | AG28: ='Lpg (2)'!C32*1000/85 -> 0 | AH28: ='Lpg (2)'!D32*1000/85 -> 58.823529 | AI28: =SUM(AF28*2000)+(AG28*1000)+(AH28*1000) -> 4058823.5 | AJ28: =SUM(AI27-AI28) -> 47058.824
A29: =Gen!A34 -> 44401 | B29: ='Summery Report'!E28 -> 0 | C29: =Gen!B34 -> 0.247 | D29: ='Summery Report'!E28 -> 0 | E29: =SUM(E28) -> 1.3262195 | F29: =SUM(J29*E29)/D29 -> #DIV/0! | G29: =SUM(L29*E29)/D29 -> #DIV/0! | H29: =Gen!C34 -> 16320.55 | I29: =Gen!E34 -> 15000 | J29: =Gen!T34 -> 4879 | K29: =Gen!AK34 -> 0 | L29: =SUM(J29:K29) -> 4879 | M29: ='Water-Meter'!K69 -> 397.53681 | N29: ='Water-Meter'!E29 -> 106 | P29: 19038 | Q29: =SUM(P29-P28) -> 0 | R29: =SUM(Q29*O29) -> 0 | S29: 7.1 | T29: 18639 | U29: =T29-T28 -> 0 | V29: =SUM(U29*S29) -> 0 | W29: 1.5 | X29: 28891 | Y29: =X29-X28 -> 0 | Z29: =SUM(Y29*W29) -> 0 | AA29: =SUM(Z29*X31) -> 0 | AB29: 7115 | AC29: =SUM(AB29-AB28) -> 0 | AD29: 219899 | AE29: =AD29-AD28 -> 67 | AF29: ='Lpg (2)'!B33*2000/85 -> 2000 | AG29: ='Lpg (2)'!C33*1000/85 -> 0 | AH29: ='Lpg (2)'!D33*1000/85 -> 23.529412 | AI29: =SUM(AF29*2000)+(AG29*1000)+(AH29*1000) -> 4023529.4 | AJ29: =SUM(AI28-AI29) -> 35294.118
A30: =Gen!A35 -> 44402 | B30: ='Summery Report'!E29 -> 0 | C30: =Gen!B35 -> 0.208 | D30: ='Summery Report'!E29 -> 0 | E30: =SUM(E29) -> 1.3262195 | F30: =SUM(J30*E30)/D30 -> #DIV/0! | G30: =SUM(L30*E30)/D30 -> #DIV/0! | H30: =Gen!C35 -> 28862.84 | I30: =Gen!E35 -> 0 | J30: =Gen!T35 -> 4599 | K30: =Gen!AK35 -> 0 | L30: =SUM(J30:K30) -> 4599 | M30: ='Water-Meter'!K70 -> 426.45072 | N30: ='Water-Meter'!E30 -> 106 | P30: 19038 | Q30: =SUM(P30-P29) -> 0 | R30: =SUM(Q30*O30) -> 0 | S30: 7.1 | T30: 18647 | U30: =T30-T29 -> 8 | V30: =SUM(U30*S30) -> 56.8 | W30: 1.5 | X30: 28891 | Y30: =X30-X29 -> 0 | Z30: =SUM(Y30*W30) -> 0 | AA30: =SUM(Z30*X32) -> 0 | AB30: 7196 | AC30: =SUM(AB30-AB29) -> 81 | AD30: 219963 | AE30: =AD30-AD29 -> 64 | AF30: ='Lpg (2)'!B34*2000/85 -> 2000 | AG30: ='Lpg (2)'!C34*1000/85 -> 0 | AH30: ='Lpg (2)'!D34*1000/85 -> 11.764706 | AI30: =SUM(AF30*2000)+(AG30*1000)+(AH30*1000) -> 4011764.7 | AJ30: =SUM(AI29-AI30) -> 11764.706
A31: =Gen!A36 -> 44403 | B31: ='Summery Report'!E30 -> 0 | C31: =Gen!B36 -> 0.156 | D31: ='Summery Report'!E30 -> 0 | E31: =SUM(E30) -> 1.3262195 | F31: =SUM(J31*E31)/D31 -> #DIV/0! | G31: =SUM(L31*E31)/D31 -> #DIV/0! | H31: =Gen!C36 -> 26733.96 | I31: =Gen!E36 -> 0 | J31: =Gen!T36 -> 4415 | K31: =Gen!AK36 -> 0 | L31: =SUM(J31:K31) -> 4415 | M31: ='Water-Meter'!K71 -> 473.64849 | N31: ='Water-Meter'!E31 -> 96 | P31: 19038 | Q31: =SUM(P31-P30) -> 0 | R31: =SUM(Q31*O31) -> 0 | S31: 7.1 | T31: 18651 | U31: =T31-T30 -> 4 | V31: =SUM(U31*S31) -> 28.4 | W31: 1.5 | X31: 28891 | Y31: =X31-X30 -> 0 | Z31: =SUM(Y31*W31) -> 0 | AA31: =SUM(Z31*X33) -> 0 | AB31: 7221 | AC31: =SUM(AB31-AB30) -> 25 | AD31: 220021 | AE31: =AD31-AD30 -> 58 | AF31: ='Lpg (2)'!B35*2000/85 -> 2000 | AG31: ='Lpg (2)'!C35*1000/85 -> 0 | AH31: ='Lpg (2)'!D35*1000/85 -> 11.764706 | AI31: =SUM(AF31*2000)+(AG31*1000)+(AH31*1000) -> 4011764.7 | AJ31: =SUM(AI30-AI31) -> 0
A32: =Gen!A37 -> 44404 | B32: ='Summery Report'!E31 -> 0 | C32: =Gen!B37 -> 0.299 | D32: ='Summery Report'!E31 -> 0 | E32: =SUM(E31) -> 1.3262195 | F32: =SUM(J32*E32)/D32 -> #DIV/0! | G32: =SUM(L32*E32)/D32 -> #DIV/0! | H32: =Gen!C37 -> 24774.24 | I32: =Gen!E37 -> 18000 | J32: =Gen!T37 -> 4607 | K32: =Gen!AK37 -> 0 | L32: =SUM(J32:K32) -> 4607 | M32: ='Water-Meter'!K72 -> 541.97526 | N32: ='Water-Meter'!E32 -> 103 | P32: 19038 | Q32: =SUM(P32-P31) -> 0 | R32: =SUM(Q32*O32) -> 0 | S32: 7.1 | T32: 18651 | U32: =T32-T31 -> 0 | V32: =SUM(U32*S32) -> 0 | W32: 1.5 | X32: 28891 | Y32: =X32-X31 -> 0 | Z32: =SUM(Y32*W32) -> 0 | AA32: =SUM(Z32*X34) -> 0 | AB32: 7314 | AC32: =SUM(AB32-AB31) -> 93 | AD32: 220068 | AE32: =AD32-AD31 -> 47 | AF32: ='Lpg (2)'!B36*2000/85 -> 2000 | AG32: ='Lpg (2)'!C36*1000/85 -> 0 | AH32: ='Lpg (2)'!D36*1000/85 -> 0 | AI32: =SUM(AF32*2000)+(AG32*1000)+(AH32*1000) -> 4000000 | AJ32: =SUM(AI31-AI32) -> 11764.706
A33: =Gen!A38 -> 44405 | B33: ='Summery Report'!E32 -> 0 | C33: =Gen!B38 -> 0.468 | D33: ='Summery Report'!E32 -> 0 | E33: =SUM(E32) -> 1.3262195 | F33: =SUM(J33*E33)/D33 -> #DIV/0! | G33: =SUM(L33*E33)/D33 -> #DIV/0! | H33: =Gen!C38 -> 37361.06 | I33: =Gen!E38 -> 0 | J33: =Gen!T38 -> 4642 | K33: =Gen!AK38 -> 0 | L33: =SUM(J33:K33) -> 4642 | M33: ='Water-Meter'!K73 -> 570.54013 | N33: ='Water-Meter'!E33 -> 115 | P33: 19038 | Q33: =SUM(P33-P32) -> 0 | R33: =SUM(Q33*O33) -> 0 | S33: 7.1 | T33: 18661 | U33: =T33-T32 -> 10 | V33: =SUM(U33*S33) -> 71 | W33: 1.5 | X33: 28891 | Y33: =X33-X32 -> 0 | Z33: =SUM(Y33*W33) -> 0 | AA33: =SUM(Z33*X35) -> 0 | AB33: 7475 | AC33: =SUM(AB33-AB32) -> 161 | AD33: 220121 | AE33: =AD33-AD32 -> 53 | AF33: ='Lpg (2)'!B37*2000/85 -> 2000 | AG33: ='Lpg (2)'!C37*1000/85 -> 0 | AH33: ='Lpg (2)'!D37*1000/85 -> 0 | AI33: =SUM(AF33*2000)+(AG33*1000)+(AH33*1000) -> 4000000 | AJ33: =SUM(AI32-AI33) -> 0
A34: =Gen!A39 -> 44406 | B34: ='Summery Report'!E33 -> 0 | C34: =Gen!B39 -> 0.51 | D34: ='Summery Report'!E33 -> 0 | E34: =SUM(E33) -> 1.3262195 | F34: =SUM(J34*E34)/D34 -> #DIV/0! | G34: =SUM(L34*E34)/D34 -> #DIV/0! | H34: =Gen!C39 -> 35516.97 | I34: =Gen!E39 -> 0 | J34: =Gen!T39 -> 3985 | K34: =Gen!AK39 -> 0 | L34: =SUM(J34:K34) -> 3985 | M34: ='Water-Meter'!K74 -> 431.57864 | N34: ='Water-Meter'!E34 -> 111 | P34: 19038 | Q34: =SUM(P34-P33) -> 0 | R34: =SUM(Q34*O34) -> 0 | S34: 7.1 | T34: 18680 | U34: =T34-T33 -> 19 | V34: =SUM(U34*S34) -> 134.9 | W34: 1.5 | X34: 28891 | Y34: =X34-X33 -> 0 | Z34: =SUM(Y34*W34) -> 0 | AA34: =SUM(Z34*X36) -> 0 | AB34: 7584 | AC34: =SUM(AB34-AB33) -> 109 | AD34: 220172 | AE34: =AD34-AD33 -> 51 | AF34: ='Lpg (2)'!B38*2000/85 -> 1976.4706 | AG34: ='Lpg (2)'!C38*1000/85 -> 0 | AH34: ='Lpg (2)'!D38*1000/85 -> 0 | AI34: =SUM(AF34*2000)+(AG34*1000)+(AH34*1000) -> 3952941.2 | AJ34: =SUM(AI33-AI34) -> 47058.824
A35: =Gen!A40 -> 44407 | B35: ='Summery Report'!E34 -> 0 | C35: =Gen!B40 -> 0.38 | D35: ='Summery Report'!E34 -> 0 | E35: =SUM(E34) -> 1.3262195 | F35: =SUM(J35*E35)/D35 -> #DIV/0! | G35: =SUM(L35*E35)/D35 -> #DIV/0! | H35: =Gen!C40 -> 33277.96 | I35: =Gen!E40 -> 0 | J35: =Gen!T40 -> 4484 | K35: =Gen!AK40 -> 0 | L35: =SUM(J35:K35) -> 4484 | M35: ='Water-Meter'!K75 -> 452.74411 | N35: ='Water-Meter'!E35 -> 105 | P35: 19038 | Q35: =SUM(P35-P34) -> 0 | R35: =SUM(Q35*O35) -> 0 | S35: 7.1 | T35: 18680 | U35: =T35-T34 -> 0 | V35: =SUM(U35*S35) -> 0 | W35: 1.5 | X35: 28891 | Y35: =X35-X34 -> 0 | Z35: =SUM(Y35*W35) -> 0 | AA35: =SUM(Z35*X37) -> 0 | AB35: 7648 | AC35: =SUM(AB35-AB34) -> 64 | AD35: 220219 | AE35: =AD35-AD34 -> 47 | AF35: ='Lpg (2)'!B39*2000/85 -> 1882.3529 | AG35: ='Lpg (2)'!C39*1000/85 -> 0 | AH35: ='Lpg (2)'!D39*1000/85 -> 0 | AI35: =SUM(AF35*2000)+(AG35*1000)+(AH35*1000) -> 3764705.9 | AJ35: =SUM(AI34-AI35) -> 188235.29
A36: =Gen!A41 -> 44408 | B36: ='Summery Report'!E35 -> 0 | C36: =Gen!B41 -> 0.15 | D36: ='Summery Report'!E35 -> 0 | E36: =SUM(E35) -> 1.3262195 | F36: =SUM(J36*E36)/D36 -> #DIV/0! | G36: =SUM(L36*E36)/D36 -> #DIV/0! | H36: =Gen!C41 -> 31086.39 | I36: =Gen!E41 -> 0 | J36: =Gen!T41 -> 4015 | K36: =Gen!AK41 -> 0 | L36: =SUM(J36:K36) -> 4015 | M36: ='Water-Meter'!K76 -> 528.06942 | N36: ='Water-Meter'!E36 -> 99 | P36: 19038 | Q36: =SUM(P36-P35) -> 0 | R36: =SUM(Q36*O36) -> 0 | S36: 7.1 | T36: 18688 | U36: =T36-T35 -> 8 | V36: =SUM(U36*S36) -> 56.8 | W36: 1.5 | X36: 28891 | Y36: =X36-X35 -> 0 | Z36: =SUM(Y36*W36) -> 0 | AA36: =SUM(Z36*X38) -> 0 | AB36: 7713 | AC36: =SUM(AB36-AB35) -> 65 | AD36: 220269 | AE36: =AD36-AD35 -> 50 | AF36: ='Lpg (2)'!B40*2000/85 -> 1788.2353 | AG36: ='Lpg (2)'!C40*1000/85 -> 0 | AH36: ='Lpg (2)'!D40*1000/85 -> 0 | AI36: =SUM(AF36*1000)+(AG36*1000)+(AH36*2000) -> 1788235.3 | AJ36: =SUM(AI35-AI36) -> 1976470.6
A37: =Gen!A42 -> 0 | B37: 0 | J37: =SUM(J6:J36) -> 136678 | L37: =SUM(J37:K37) -> 136678 | M37: ='Water-Meter'!K77 -> 0 | N37: ='Water-Meter'!E37 -> 0 | Q37: =SUM(P37-P36) -> -19038 | R37: =SUM(Q37*O37) -> 0 | U37: =T37-T36 -> -18688 | V37: =SUM(U37*S37) -> 0 | Y37: =X37-X36 -> -28891 | Z37: =SUM(Y37*W37) -> 0 | AA37: =SUM(Z37*X39) -> 0 | AC37: =SUM(AB37-AB36) -> -7713 | AE37: =AD37-AD36 -> -220269 | AF37: ='Lpg (2)'!B41*2000/85 -> 0 | AG37: ='Lpg (2)'!C41*1000/85 -> 0 | AH37: ='Lpg (2)'!D41*1000/85 -> 0 | AJ37: =SUM(AI36-AI37) -> 1788235.3

Sheet Kit report
B1: KITCHEN THREE PHASE KWH METER READING | H1: KITCHEN WATER METER READING | M1: AMANI Restaurant WATER METER READING | T1: LAUNDRY THREE PHASE KWH METER READING | Y1: LAUNDRY WATER METER READING
A2: Occ % | B2: DATE | C2: READING TIME | D2: METER READING OPEN | E2: METER READING ClOSE | F2: UNIT USED Kwh | H2: DATE | I2: READING TIME | J2: METER READING OPEN Cbm | K2: METER READING ClOSE Cbm | L2: UNIT USED Cbm | M2: DATE | N2: READING TIME | O2: METER READING OPEN Cbm | P2: METER READING ClOSE Cbm | Q2: UNIT USED Cbm | R2: Cost Per day Elct+Water $ | S2: % as per the total Lodge consumption | T2: DATE | U2: READING TIME | V2: METER READING OPEN (Kwh) | W2: METER READING ClOSE (Kwh) | X2: UNIT USED Kwh | Y2: DATE | Z2: READING TIME | AA2: METER READING OPEN Cbm | AB2: METER READING ClOSE Cbm | AC2: UNIT USED Cbm
A3: =Gen!A11 -> 44378 | B3: Close Last Month | F3: X120 | H3: Close Last Month | J3: ='Water-Meter'!G5 -> 0 | K3: ='Water-Meter'!G5 -> 0 | M3: Close Last Month | P3: ='Water-Meter'!J5 -> 8522 | T3: Close Last Month | X3: =(W3-V3)*200 -> 0 | Y3: Close Last Month
A4: =Gen!B11 -> 0.3 | B4: =Gen!A11 -> 44378 | D4: =E3 -> 0 | E4: 9401.5 | F4: =SUM(E4-D4)*120 -> 1128180 | H4: =B4 -> 44378 | J4: ='Water-Meter'!G6 -> 0 | K4: ='Water-Meter'!G6 -> 0 | L4: =SUM(K4-J4) -> 0 | M4: =H4 -> 44378 | P4: ='Water-Meter'!J6 -> 8524 | Q4: =N4-O3 -> 0 | R4: =SUM(Q4/1615) -> 0 | S4: =Gen!T11 -> 4264 | T4: =M4 -> 44378 | V4: =W3 -> 0 | W4: 8236.4 | X4: =(W4-V4)*200 -> 1647280 | Y4: =T4 -> 44378 | AB4: ='Water-Meter'!P6 -> 21544 | AC4: =AA4-AB3 -> 0
A5: =Gen!B12 -> 0.35 | B5: =Gen!A12 -> 44379 | D5: =E4 -> 9401.5 | E5: 9404.2 | F5: =SUM(E5-D5)*120 -> 324 | H5: =B5 -> 44379 | J5: ='Water-Meter'!G7 -> 0 | K5: ='Water-Meter'!G7 -> 0 | L5: =SUM(K5-J5) -> 0 | M5: =H5 -> 44379 | P5: ='Water-Meter'!J7 -> 8526 | Q5: =N5-O4 -> 0 | R5: =SUM(Q5/1615) -> 0 | S5: =Gen!T12 -> 4274 | T5: =M5 -> 44379 | V5: =W4 -> 8236.4 | W5: 8239.2 | X5: =(W5-V5)*200 -> 560 | Y5: =T5 -> 44379 | AB5: ='Water-Meter'!P7 -> 21551 | AC5: =AA5-AB4 -> -21544
A6: =Gen!B13 -> 0.2609 | B6: =Gen!A13 -> 44380 | D6: =E5 -> 9404.2 | E6: 9407.2 | F6: =SUM(E6-D6)*120 -> 360 | H6: =B6 -> 44380 | J6: ='Water-Meter'!G8 -> 0 | K6: ='Water-Meter'!G8 -> 0 | L6: =SUM(K6-J6) -> 0 | M6: =H6 -> 44380 | P6: ='Water-Meter'!J8 -> 8529 | Q6: =N6-O5 -> 0 | R6: =SUM(Q6/1615) -> 0 | S6: =Gen!T13 -> 4467 | T6: =M6 -> 44380 | V6: =W5 -> 8239.2 | W6: 8241.9 | X6: =(W6-V6)*200 -> 540 | Y6: =T6 -> 44380 | AB6: ='Water-Meter'!P8 -> 21559 | AC6: =AA6-AB5 -> -21551
A7: =Gen!B14 -> 0.18 | B7: =Gen!A14 -> 44381 | D7: =E6 -> 9407.2 | E7: 9409.9 | F7: =SUM(E7-D7)*120 -> 324 | H7: =B7 -> 44381 | J7: ='Water-Meter'!G9 -> 0 | K7: ='Water-Meter'!G9 -> 0 | L7: =SUM(K7-J7) -> 0 | M7: =H7 -> 44381 | P7: ='Water-Meter'!J9 -> 8531 | Q7: =N7-O6 -> 0 | R7: =SUM(Q7/1615) -> 0 | S7: =Gen!T14 -> 4106 | T7: =M7 -> 44381 | V7: =W6 -> 8241.9 | W7: 8245.2 | X7: =(W7-V7)*200 -> 660 | Y7: =T7 -> 44381 | AB7: ='Water-Meter'!P9 -> 21569 | AC7: =AA7-AB6 -> -21559
A8: =Gen!B15 -> 0.14 | B8: =Gen!A15 -> 44382 | D8: =E7 -> 9409.9 | E8: 9412.1 | F8: =SUM(E8-D8)*120 -> 264 | H8: =B8 -> 44382 | J8: ='Water-Meter'!G10 -> 0 | K8: ='Water-Meter'!G10 -> 0 | L8: =SUM(K8-J8) -> 0 | M8: =H8 -> 44382 | P8: ='Water-Meter'!J10 -> 8532 | Q8: =N8-O7 -> 0 | R8: =SUM(Q8/1615) -> 0 | S8: =Gen!T15 -> 4026 | T8: =M8 -> 44382 | V8: =W7 -> 8245.2 | W8: 8248.5 | X8: =(W8-V8)*200 -> 660 | Y8: =T8 -> 44382 | AB8: ='Water-Meter'!P10 -> 21576 | AC8: =AA8-AB7 -> -21569
A9: =Gen!B16 -> 0.169 | B9: =Gen!A16 -> 44383 | D9: =E8 -> 9412.1 | E9: 9414.4 | F9: =SUM(E9-D9)*120 -> 276 | H9: =B9 -> 44383 | J9: ='Water-Meter'!G11 -> 0 | K9: ='Water-Meter'!G11 -> 0 | L9: =SUM(K9-J9) -> 0 | M9: =H9 -> 44383 | P9: ='Water-Meter'!J11 -> 8534 | Q9: =N9-O8 -> 0 | R9: =SUM(Q9/1615) -> 0 | S9: =Gen!T16 -> 4145 | T9: =M9 -> 44383 | V9: =W8 -> 8248.5 | W9: 8251.5 | X9: =(W9-V9)*200 -> 600 | Y9: =T9 -> 44383 | AB9: ='Water-Meter'!P11 -> 21586 | AC9: =AA9-AB8 -> -21576
A10: =Gen!B17 -> 0.364 | B10: =Gen!A17 -> 44384 | D10: =E9 -> 9414.4 | E10: 9416.6 | F10: =SUM(E10-D10)*120 -> 264 | H10: =B10 -> 44384 | J10: ='Water-Meter'!G12 -> 0 | K10: ='Water-Meter'!G12 -> 0 | L10: =SUM(K10-J10) -> 0 | M10: =H10 -> 44384 | P10: ='Water-Meter'!J12 -> 8536 | Q10: =N10-O9 -> 0 | R10: =SUM(Q10/1615) -> 0 | S10: =Gen!T17 -> 4675 | T10: =M10 -> 44384 | V10: =W9 -> 8251.5 | W10: 8255.5 | X10: =(W10-V10)*200 -> 800 | Y10: =T10 -> 44384 | AB10: ='Water-Meter'!P12 -> 21597 | AC10: =AA10-AB9 -> -21586
A11: =Gen!B18 -> 0.455 | B11: =Gen!A18 -> 44385 | D11: =E10 -> 9416.6 | E11: 9418.7 | F11: =SUM(E11-D11)*120 -> 252 | H11: =B11 -> 44385 | J11: ='Water-Meter'!G13 -> 0 | K11: ='Water-Meter'!G13 -> 0 | L11: =SUM(K11-J11) -> 0 | M11: =H11 -> 44385 | P11: ='Water-Meter'!J13 -> 8537 | Q11: =N11-O10 -> 0 | R11: =SUM(Q11/1615) -> 0 | S11: =Gen!T18 -> 4550 | T11: =M11 -> 44385 | V11: =W10 -> 8255.5 | W11: 8259.3 | X11: =(W11-V11)*200 -> 760 | Y11: =T11 -> 44385 | AB11: ='Water-Meter'!P13 -> 21606 | AC11: =AA11-AB10 -> -21597
A12: =Gen!B19 -> 0.468 | B12: =Gen!A19 -> 44386 | D12: =E11 -> 9418.7 | E12: 9421.1 | F12: =SUM(E12-D12)*120 -> 288 | H12: =B12 -> 44386 | J12: ='Water-Meter'!G14 -> 0 | K12: ='Water-Meter'!G14 -> 0 | L12: =SUM(K12-J12) -> 0 | M12: =H12 -> 44386 | P12: ='Water-Meter'!J14 -> 8539 | Q12: =N12-O11 -> 0 | R12: =SUM(Q12/1615) -> 0 | S12: =Gen!T19 -> 4263 | T12: =M12 -> 44386 | V12: =W11 -> 8259.3 | W12: 8263.7 | X12: =(W12-V12)*200 -> 880 | Y12: =T12 -> 44386 | AB12: ='Water-Meter'!P14 -> 21616 | AC12: =AA12-AB11 -> -21606
A13: =Gen!B20 -> 0.39 | B13: =Gen!A20 -> 44387 | D13: =E12 -> 9421.1 | E13: 9423.1 | F13: =SUM(E13-D13)*120 -> 240 | H13: =B13 -> 44387 | J13: ='Water-Meter'!G15 -> 0 | K13: ='Water-Meter'!G15 -> 0 | L13: =SUM(K13-J13) -> 0 | M13: =H13 -> 44387 | P13: ='Water-Meter'!J15 -> 8541 | Q13: =N13-O12 -> 0 | R13: =SUM(Q13/1615) -> 0 | S13: =Gen!T20 -> 4506 | T13: =M13 -> 44387 | V13: =W12 -> 8263.7 | W13: 8267.8 | X13: =(W13-V13)*200 -> 820 | Y13: =T13 -> 44387 | AB13: ='Water-Meter'!P15 -> 21627 | AC13: =AA13-AB12 -> -21616
A14: =Gen!B21 -> 0.403 | B14: =Gen!A21 -> 44388 | D14: =E13 -> 9423.1 | E14: 9425.4 | F14: =SUM(E14-D14)*120 -> 276 | H14: =B14 -> 44388 | J14: ='Water-Meter'!G15 -> 0 | K14: ='Water-Meter'!G15 -> 0 | L14: =SUM(K14-J14) -> 0 | M14: =H14 -> 44388 | P14: ='Water-Meter'!J16 -> 8547 | Q14: 8095 | R14: =SUM(Q14/1615) -> 5.0123839 | S14: =Gen!T21 -> 4459 | T14: =M14 -> 44388 | V14: =W13 -> 8267.8 | W14: 8272.3 | X14: =(W14-V14)*200 -> 900 | Y14: =T14 -> 44388 | AB14: ='Water-Meter'!P16 -> 21638 | AC14: 20490
A15: =Gen!B22 -> 0.39 | B15: =Gen!A22 -> 44389 | D15: =E14 -> 9425.4 | E15: 9427.6 | F15: =SUM(E15-D15)*120 -> 264 | H15: =B15 -> 44389 | J15: ='Water-Meter'!G17 -> 0 | K15: ='Water-Meter'!G17 -> 0 | L15: =SUM(K15-J15) -> 0 | M15: =H15 -> 44389 | P15: ='Water-Meter'!J17 -> 8549 | Q15: =N15-O14 -> 0 | R15: =SUM(Q15/1615) -> 0 | S15: =Gen!T22 -> 4438 | T15: =M15 -> 44389 | V15: =W14 -> 8272.3 | W15: 8277.4 | X15: =(W15-V15)*200 -> 1020 | Y15: =T15 -> 44389 | AB15: ='Water-Meter'!P17 -> 21648 | AC15: =AA15-AB14 -> -21638
A16: =Gen!B23 -> 0.221 | B16: =Gen!A23 -> 44390 | D16: =E15 -> 9427.6 | E16: 9429.9 | F16: =SUM(E16-D16)*120 -> 276 | H16: =B16 -> 44390 | J16: ='Water-Meter'!G18 -> 0 | K16: ='Water-Meter'!G18 -> 0 | L16: =SUM(K16-J16) -> 0 | M16: =H16 -> 44390 | P16: ='Water-Meter'!J18 -> 8551 | Q16: =N16-O15 -> 0 | R16: =SUM(Q16/1615) -> 0 | S16: =Gen!T23 -> 4300 | T16: =M16 -> 44390 | V16: =W15 -> 8277.4 | W16: 8282.2 | X16: =(W16-V16)*200 -> 960 | Y16: =T16 -> 44390 | AB16: ='Water-Meter'!P18 -> 21660 | AC16: =AA16-AB15 -> -21648
A17: =Gen!B24 -> 0.195 | B17: =Gen!A24 -> 44391 | D17: =E16 -> 9429.9 | E17: 9432.3 | F17: =SUM(E17-D17)*120 -> 288 | H17: =B17 -> 44391 | J17: ='Water-Meter'!G19 -> 0 | K17: ='Water-Meter'!G19 -> 0 | L17: =SUM(K17-J17) -> 0 | M17: =H17 -> 44391 | P17: ='Water-Meter'!J19 -> 8553 | Q17: =N17-O16 -> 0 | R17: =SUM(Q17/1615) -> 0 | S17: =Gen!T24 -> 3902 | T17: =M17 -> 44391 | V17: =W16 -> 8282.2 | W17: 8285.1 | X17: =(W17-V17)*200 -> 580 | Y17: =T17 -> 44391 | AB17: ='Water-Meter'!P19 -> 21670 | AC17: =AA17-AB16 -> -21660
A18: =Gen!B25 -> 0.208 | B18: =Gen!A25 -> 44392 | D18: =E17 -> 9432.3 | E18: 9434.7 | F18: =SUM(E18-D18)*120 -> 288 | H18: =B18 -> 44392 | J18: ='Water-Meter'!G20 -> 0 | K18: ='Water-Meter'!G20 -> 0 | L18: =SUM(K18-J18) -> 0 | M18: =H18 -> 44392 | O18: ='Water-Meter'!J20 -> 8555 | P18: ='Water-Meter'!J20 -> 8555 | Q18: =N18-O17 -> 0 | R18: =SUM(Q18/1615) -> 0 | S18: =Gen!T25 -> 3833 | T18: =M18 -> 44392 | V18: =W17 -> 8285.1 | W18: 8288.9 | X18: =(W18-V18)*200 -> 760 | Y18: =T18 -> 44392 | AB18: ='Water-Meter'!P20 -> 21678 | AC18: =AA18-AB17 -> -21670
A19: =Gen!B26 -> 0.27 | B19: =Gen!A26 -> 44393 | D19: =E18 -> 9434.7 | E19: 9436.9 | F19: =SUM(E19-D19)*120 -> 264 | H19: =B19 -> 44393 | J19: ='Water-Meter'!G21 -> 0 | K19: ='Water-Meter'!G21 -> 0 | L19: =SUM(K19-J19) -> 0 | M19: =H19 -> 44393 | O19: ='Water-Meter'!J21 -> 8560 | P19: ='Water-Meter'!J21 -> 8560 | Q19: =N19-O18 -> -8555 | R19: =SUM(Q19/1615) -> -5.2972136 | S19: =Gen!T26 -> 4080 | T19: =M19 -> 44393 | V19: =W18 -> 8288.9 | W19: 8292.3 | X19: =(W19-V19)*200 -> 680 | Y19: =T19 -> 44393 | AB19: ='Water-Meter'!P21 -> 21688 | AC19: =AA19-AB18 -> -21678
A20: =Gen!B27 -> 0.26 | B20: =Gen!A27 -> 44394 | D20: =E19 -> 9436.9 | E20: 9439.4 | F20: =SUM(E20-D20)*120 -> 300 | H20: =B20 -> 44394 | J20: ='Water-Meter'!G22 -> 0 | K20: ='Water-Meter'!G22 -> 0 | L20: =SUM(K20-J20) -> 0 | M20: =H20 -> 44394 | O20: ='Water-Meter'!J22 -> 8564 | P20: ='Water-Meter'!J22 -> 8564 | Q20: =N20-O19 -> -8560 | R20: =SUM(Q20/1615) -> -5.3003096 | S20: =Gen!T27 -> 4092 | T20: =M20 -> 44394 | V20: =W19 -> 8292.3 | W20: 8296.2 | X20: =(W20-V20)*200 -> 780 | Y20: =T20 -> 44394 | AB20: ='Water-Meter'!P22 -> 21698 | AC20: =AA20-AB19 -> -21688
A21: =Gen!B28 -> 0.35 | B21: =Gen!A28 -> 44395 | D21: =E20 -> 9439.4 | E21: 9441.9 | F21: =SUM(E21-D21)*120 -> 300 | H21: =B21 -> 44395 | J21: ='Water-Meter'!G23 -> 0 | K21: ='Water-Meter'!G23 -> 0 | L21: =SUM(K21-J21) -> 0 | M21: =H21 -> 44395 | O21: ='Water-Meter'!J23 -> 8567 | P21: ='Water-Meter'!J23 -> 8567 | Q21: =N21-O20 -> -8564 | R21: =SUM(Q21/1615) -> -5.3027864 | S21: =Gen!T28 -> 4450 | T21: =M21 -> 44395 | V21: =W20 -> 8296.2 | W21: 8300.2 | X21: =(W21-V21)*200 -> 800 | Y21: =T21 -> 44395 | AB21: ='Water-Meter'!P23 -> 21706 | AC21: =AA21-AB20 -> -21698
A22: =Gen!B29 -> 0.39 | B22: =Gen!A29 -> 44396 | D22: =E21 -> 9441.9 | E22: 9444.3 | F22: =SUM(E22-D22)*120 -> 288 | H22: =B22 -> 44396 | J22: ='Water-Meter'!G24 -> 0 | K22: ='Water-Meter'!G24 -> 0 | L22: =SUM(K22-J22) -> 0 | M22: =H22 -> 44396 | O22: ='Water-Meter'!J24 -> 8568 | P22: ='Water-Meter'!J24 -> 8568 | Q22: =N22-O21 -> -8567 | R22: =SUM(Q22/1615) -> -5.304644 | S22: =Gen!T29 -> 4633 | T22: =M22 -> 44396 | V22: =W21 -> 8300.2 | W22: 8304.1 | X22: =(W22-V22)*200 -> 780 | Y22: =T22 -> 44396 | AB22: ='Water-Meter'!P24 -> 21718 | AC22: =AA22-AB21 -> -21706
A23: =Gen!B30 -> 0.39 | B23: =Gen!A30 -> 44397 | D23: =E22 -> 9444.3 | E23: 9447.1 | F23: =SUM(E23-D23)*120 -> 336 | H23: =B23 -> 44397 | J23: ='Water-Meter'!G25 -> 0 | K23: ='Water-Meter'!G26 -> 0 | L23: =SUM(K23-J23) -> 0 | M23: =H23 -> 44397 | O23: ='Water-Meter'!J25 -> 8569 | P23: ='Water-Meter'!J25 -> 8569 | Q23: =N23-O22 -> -8568 | R23: =SUM(Q23/1615) -> -5.3052632 | S23: =Gen!T30 -> 4722 | T23: =M23 -> 44397 | V23: =W22 -> 8304.1 | W23: 8307.6 | X23: =(W23-V23)*200 -> 700 | Y23: =T23 -> 44397 | AB23: ='Water-Meter'!P25 -> 21726 | AC23: =AA23-AB22 -> -21718
A24: =Gen!B31 -> 0.55 | B24: =Gen!A31 -> 44398 | D24: =SUM(E23) -> 9447.1 | E24: 9449.6 | F24: =SUM(E24-D24)*120 -> 300 | H24: =B24 -> 44398 | J24: ='Water-Meter'!G26 -> 0 | K24: ='Water-Meter'!G27 -> 0 | L24: =SUM(K24-J24) -> 0 | M24: =H24 -> 44398 | O24: ='Water-Meter'!J26 -> 8571 | P24: ='Water-Meter'!J26 -> 8571 | Q24: =N24-O23 -> -8569 | R24: =SUM(Q24/1615) -> -5.3058824 | S24: =Gen!T31 -> 4911 | T24: =M24 -> 44398 | V24: =W23 -> 8307.6 | W24: 8311.5 | X24: =(W24-V24)*200 -> 780 | Y24: =T24 -> 44398 | AB24: ='Water-Meter'!P26 -> 21732 | AC24: =AA24-AB23 -> -21726
A25: =Gen!B32 -> 0.545 | B25: =Gen!A32 -> 44399 | D25: =SUM(E24) -> 9449.6 | E25: 9452.3 | F25: =SUM(E25-D25)*120 -> 324 | H25: =B25 -> 44399 | J25: ='Water-Meter'!G27 -> 0 | K25: ='Water-Meter'!G28 -> 0 | L25: =SUM(K25-J25) -> 0 | M25: =H25 -> 44399 | O25: ='Water-Meter'!J27 -> 8572 | P25: ='Water-Meter'!J27 -> 8572 | Q25: =N25-O24 -> -8571 | R25: =SUM(Q25/1615) -> -5.3071207 | S25: =Gen!T32 -> 5226 | T25: =M25 -> 44399 | V25: =W24 -> 8311.5 | W25: 8315.4 | X25: =(W25-V25)*200 -> 780 | Y25: =T25 -> 44399 | AB25: ='Water-Meter'!P27 -> 21741 | AC25: =AA25-AB24 -> -21732
A26: =Gen!B33 -> 0.455 | B26: =Gen!A33 -> 44400 | D26: =SUM(E25) -> 9452.3 | E26: 9455.2 | F26: =SUM(E26-D26)*120 -> 348 | H26: =B26 -> 44400 | J26: ='Water-Meter'!G28 -> 0 | K26: ='Water-Meter'!G29 -> 0 | L26: =SUM(K26-J26) -> 0 | M26: =H26 -> 44400 | O26: ='Water-Meter'!J28 -> 8573 | P26: ='Water-Meter'!J28 -> 8573 | Q26: =N26-O25 -> -8572 | R26: =SUM(Q26/1615) -> -5.3077399 | S26: =Gen!T33 -> 4730 | T26: =M26 -> 44400 | V26: =W25 -> 8315.4 | W26: 8319.7 | X26: =(W26-V26)*200 -> 860 | Y26: =T26 -> 44400 | AB26: ='Water-Meter'!P28 -> 21749 | AC26: =AA26-AB25 -> -21741
A27: =Gen!B34 -> 0.247 | B27: =Gen!A34 -> 44401 | D27: =SUM(E26) -> 9455.2 | E27: 9458.1 | F27: =SUM(E27-D27)*120 -> 348 | H27: =B27 -> 44401 | J27: ='Water-Meter'!G29 -> 0 | K27: ='Water-Meter'!G30 -> 0 | L27: =SUM(K27-J27) -> 0 | M27: =H27 -> 44401 | O27: ='Water-Meter'!J29 -> 8575 | P27: ='Water-Meter'!J29 -> 8575 | Q27: =N27-O26 -> -8573 | R27: =SUM(Q27/1615) -> -5.3083591 | S27: =Gen!T34 -> 4879 | T27: =M27 -> 44401 | V27: =W26 -> 8319.7 | W27: 8323.4 | X27: =(W27-V27)*200 -> 740 | Y27: =T27 -> 44401 | AB27: ='Water-Meter'!P29 -> 21760 | AC27: =AA27-AB26 -> -21749
A28: =Gen!B35 -> 0.208 | B28: =Gen!A35 -> 44402 | D28: =SUM(E27) -> 9458.1 | E28: 9461.1 | F28: =SUM(E28-D28)*120 -> 360 | H28: =B28 -> 44402 | J28: ='Water-Meter'!G30 -> 0 | K28: ='Water-Meter'!G31 -> 0 | L28: =SUM(K28-J28) -> 0 | M28: =H28 -> 44402 | O28: ='Water-Meter'!J30 -> 8577 | P28: ='Water-Meter'!J30 -> 8577 | Q28: =N28-O27 -> -8575 | R28: =SUM(Q28/1615) -> -5.3095975 | S28: =Gen!T35 -> 4599 | T28: =M28 -> 44402 | V28: =W27 -> 8323.4 | W28: 8327.4 | X28: =(W28-V28)*200 -> 800 | Y28: =T28 -> 44402 | AB28: ='Water-Meter'!P30 -> 21770 | AC28: =AA28-AB27 -> -21760
A29: =Gen!B36 -> 0.156 | B29: =Gen!A36 -> 44403 | D29: =SUM(E28) -> 9461.1 | E29: 9463.4 | F29: =SUM(E29-D29)*120 -> 276 | H29: =B29 -> 44403 | J29: ='Water-Meter'!G31 -> 0 | K29: ='Water-Meter'!G32 -> 0 | L29: =SUM(K29-J29) -> 0 | M29: =H29 -> 44403 | O29: ='Water-Meter'!J31 -> 8580 | P29: ='Water-Meter'!J31 -> 8580 | Q29: =N29-O28 -> -8577 | R29: =SUM(Q29/1615) -> -5.3108359 | S29: =Gen!T36 -> 4415 | T29: =M29 -> 44403 | V29: =W28 -> 8327.4 | W29: 8331.7 | X29: =(W29-V29)*200 -> 860 | Y29: =T29 -> 44403 | AB29: ='Water-Meter'!P31 -> 21780 | AC29: =AA29-AB28 -> -21770
A30: =Gen!B37 -> 0.299 | B30: =Gen!A37 -> 44404 | D30: =SUM(E29) -> 9463.4 | E30: 9465.9 | F30: =SUM(E30-D30)*120 -> 300 | H30: =B30 -> 44404 | J30: ='Water-Meter'!G32 -> 0 | K30: ='Water-Meter'!G33 -> 0 | L30: =SUM(K30-J30) -> 0 | M30: =H30 -> 44404 | O30: ='Water-Meter'!J32 -> 8582 | P30: ='Water-Meter'!J32 -> 8582 | Q30: =N30-O29 -> -8580 | R30: =SUM(Q30/1615) -> -5.3126935 | S30: =Gen!T37 -> 4607 | T30: =M30 -> 44404 | V30: =W29 -> 8331.7 | W30: 8335.2 | X30: =(W30-V30)*200 -> 700 | Y30: =T30 -> 44404 | AB30: ='Water-Meter'!P32 -> 21788 | AC30: =AA30-AB29 -> -21780
A31: =Gen!B38 -> 0.468 | B31: =Gen!A38 -> 44405 | D31: =SUM(E30) -> 9465.9 | E31: 9468.6 | F31: =SUM(E31-D31)*120 -> 324 | H31: =B31 -> 44405 | J31: ='Water-Meter'!G33 -> 0 | K31: ='Water-Meter'!G34 -> 0 | L31: =SUM(K31-J31) -> 0 | M31: =H31 -> 44405 | O31: ='Water-Meter'!J33 -> 8585 | P31: ='Water-Meter'!J33 -> 8585 | Q31: =N31-O30 -> -8582 | R31: =SUM(Q31/1615) -> -5.3139319 | S31: =Gen!T38 -> 4642 | T31: =M31 -> 44405 | V31: =W30 -> 8335.2 | W31: 8338.6 | X31: =(W31-V31)*200 -> 680 | Y31: =T31 -> 44405 | AB31: ='Water-Meter'!P33 -> 21797 | AC31: =AA31-AB30 -> -21788
A32: =Gen!B39 -> 0.51 | B32: =Gen!A39 -> 44406 | D32: =SUM(E31) -> 9468.6 | E32: 9471.4 | F32: =SUM(E32-D32)*120 -> 336 | H32: =B32 -> 44406 | J32: ='Water-Meter'!G34 -> 0 | K32: ='Water-Meter'!G34 -> 0 | L32: =SUM(K32-J32) -> 0 | M32: =H32 -> 44406 | O32: ='Water-Meter'!J34 -> 8587 | P32: ='Water-Meter'!J34 -> 8587 | Q32: =N32-O31 -> -8585 | R32: =SUM(Q32/1615) -> -5.3157895 | S32: =Gen!T39 -> 3985 | T32: =M32 -> 44406 | V32: =W31 -> 8338.6 | W32: 8341.6 | X32: =(W32-V32)*200 -> 600 | Y32: =T32 -> 44406 | AB32: ='Water-Meter'!P34 -> 21807 | AC32: =AA32-AB31 -> -21797
A33: =Gen!B40 -> 0.38 | B33: =Gen!A40 -> 44407 | D33: =SUM(E32) -> 9471.4 | E33: 9473.9 | F33: =SUM(E33-D33)*120 -> 300 | H33: =B33 -> 44407 | J33: ='Water-Meter'!G35 -> 0 | K33: ='Water-Meter'!G35 -> 0 | L33: =SUM(K33-J33) -> 0 | M33: =H33 -> 44407 | O33: ='Water-Meter'!J35 -> 8590 | P33: ='Water-Meter'!J35 -> 8590 | Q33: =N33-O32 -> -8587 | R33: =SUM(Q33/1615) -> -5.3170279 | S33: =Gen!T40 -> 4484 | T33: =M33 -> 44407 | V33: =W32 -> 8341.6 | W33: 8344.9 | X33: =(W33-V33)*200 -> 660 | Y33: =T33 -> 44407 | AB33: ='Water-Meter'!P35 -> 21817 | AC33: =AA33-AB32 -> -21807
A34: =Gen!B41 -> 0.15 | B34: =Gen!A41 -> 44408 | D34: =SUM(E33) -> 9473.9 | E34: 9476.7 | F34: =SUM(E34-D34)*120 -> 336 | H34: =B34 -> 44408 | J34: ='Water-Meter'!G36 -> 0 | K34: ='Water-Meter'!G36 -> 0 | L34: =SUM(K34-J34) -> 0 | M34: =H34 -> 44408 | O34: ='Water-Meter'!J36 -> 8592 | P34: ='Water-Meter'!J36 -> 8592 | Q34: =N34-O33 -> -8590 | R34: =SUM(Q34/1615) -> -5.3188854 | S34: =Gen!T41 -> 4015 | T34: =M34 -> 44408 | V34: =SUM(W33) -> 8344.9 | W34: 8348.7 | X34: =(W34-V34)*200 -> 760 | Y34: =T34 -> 44408 | AB34: ='Water-Meter'!P36 -> 21828 | AC34: =AA34-AB33 -> -21817
A35: #REF! | B35: #REF! | D35: =SUM(E34) -> 9476.7 | E35: 9479.2 | F35: =SUM(E35-D35)*120 -> 300 | H35: =B35 -> #REF! | J35: =SUM(K34) -> 0 | K35: ='Water-Meter'!G37 -> 0 | L35: =SUM(L5:L34) -> 0 | M35: =H35 -> #REF! | P35: ='Water-Meter'!J37 -> 0 | Q35: =N35-O34 -> -8592 | R35: =SUM(Q35/1615) -> -5.3201238 | S35: =Gen!T42 -> 0 | T35: =M35 -> #REF! | V35: =SUM(W34) -> 8348.7 | W35: 8352.8 | X35: =(W35-V35)*200 -> 820 | Y35: =T35 -> #REF! | AB35: ='Water-Meter'!P37 -> 0 | AC35: =AA35-AB34 -> -21828
X36: =SUM(X4:X6) -> 1648380

Sheet Energy Graph
A1: Date | B1: Usage KW | C1: Occ % | D1: Total Occ | E1: Guest Occ
A2: =Gen!A11 -> 44378 | B2: ='Summery Report'!F5 -> 4264 | C2: ='Summery Report'!C5 -> 0.3 | D2: ='Summery Report'!D5 -> 23 | E2: ='Summery Report'!E5 -> 23
A3: =Gen!A12 -> 44379 | B3: ='Summery Report'!F6 -> 4274 | C3: ='Summery Report'!C6 -> 0.35 | D3: ='Summery Report'!D6 -> 27 | E3: ='Summery Report'!E6 -> 27
A4: =Gen!A13 -> 44380 | B4: ='Summery Report'!F7 -> 4467 | C4: ='Summery Report'!C7 -> 0.2609 | D4: ='Summery Report'!D7 -> 20 | E4: ='Summery Report'!E7 -> 20
A5: =Gen!A14 -> 44381 | B5: ='Summery Report'!F8 -> 4106 | C5: ='Summery Report'!C8 -> 0.18 | D5: ='Summery Report'!D8 -> 14 | E5: ='Summery Report'!E8 -> 14
A6: =Gen!A15 -> 44382 | B6: ='Summery Report'!F9 -> 4026 | C6: ='Summery Report'!C9 -> 0.14 | D6: ='Summery Report'!D9 -> 11 | E6: ='Summery Report'!E9 -> 11
A7: =Gen!A16 -> 44383 | B7: ='Summery Report'!F10 -> 4145 | C7: ='Summery Report'!C10 -> 0.169 | D7: ='Summery Report'!D10 -> 14 | E7: ='Summery Report'!E10 -> 14
A8: =Gen!A17 -> 44384 | B8: ='Summery Report'!F11 -> 4675 | C8: ='Summery Report'!C11 -> 0.364 | D8: ='Summery Report'!D11 -> 29 | E8: ='Summery Report'!E11 -> 29
A9: =Gen!A18 -> 44385 | B9: ='Summery Report'!F12 -> 4550 | C9: ='Summery Report'!C12 -> 0.455 | D9: ='Summery Report'!D12 -> 35 | E9: ='Summery Report'!E12 -> 35
A10: =Gen!A19 -> 44386 | B10: ='Summery Report'!F13 -> 4263 | C10: ='Summery Report'!C13 -> 0.468 | D10: ='Summery Report'!D13 -> 39 | E10: ='Summery Report'!E13 -> 39
A11: =Gen!A20 -> 44387 | B11: ='Summery Report'!F14 -> 4506 | C11: ='Summery Report'!C14 -> 0.39 | D11: ='Summery Report'!D14 -> 32 | E11: ='Summery Report'!E14 -> 32
A12: =Gen!A21 -> 44388 | B12: ='Summery Report'!F15 -> 4459 | C12: ='Summery Report'!C15 -> 0.403 | D12: ='Summery Report'!D15 -> 31 | E12: ='Summery Report'!E15 -> 31
A13: =Gen!A22 -> 44389 | B13: ='Summery Report'!F16 -> 4438 | C13: ='Summery Report'!C16 -> 0.39 | D13: ='Summery Report'!D16 -> 32 | E13: ='Summery Report'!E16 -> 32
... A31: =Gen!A40 -> 44407 | B31: ='Summery Report'!F34 -> 4484 | C31: ='Summery Report'!C34 -> 0.38 | D31: ='Summery Report'!D34 -> 0 | E31: ='Summery Report'!E34 -> 0
A32: =Gen!A41 -> 44408 | B32: ='Summery Report'!F35 -> 4015 | C32: ='Summery Report'!C35 -> 0.15 | D32: ='Summery Report'!D35 -> 0 | E32: ='Summery Report'!E35 -> 0 | F32: 0.175
A33: =Gen!A42 -> 0 | B33: 0

Sheet Summery Report
A1: =A5 -> 44378
A4: Date | B4: Gen Set Hours Working | C4: Occ% | D4: Total OCC Room | E4: Guest Room Occ | F4: Total Kwh Generated | G4: Diesel consumed by Gen (Ltrs) | H4: Diesel consumed by Vehicle (Ltrs) | I4: Total diesel consumed (Ltrs) | J4: Balance stock of Diesel (Ltrs) | K4: Water consumed | L4: Gas consumed (KG)
A5: =Gen!A11 -> 44378 | B5: ='Daily report Gen'!Z6 -> 34 | C5: =Gen!B11 -> 0.3 | D5: =E5 -> 23 | E5: 23 | F5: =Gen!T11 -> 4264 | G5: =Gen!S11 -> 1799.58 | H5: =Gen!AJ11 -> 0 | I5: =SUM(G5:H5) -> 1799.58 | J5: =Gen!C11 -> 29939.14 | K5: ='Water-Meter'!E6 -> 109 | L5: ='Lpg (2)'!G10 -> 130.68 | M5: =SUM(#REF!-#REF!) -> #REF!
A6: =Gen!A12 -> 44379 | B6: ='Daily report Gen'!Z7 -> 35 | C6: =Gen!B12 -> 0.35 | D6: =E6 -> 27 | E6: 27 | F6: =Gen!T12 -> 4274 | G6: =Gen!S12 -> 1691.92 | H6: =Gen!AJ12 -> 324.81 | I6: =SUM(G6:H6) -> 2016.73 | J6: =Gen!C12 -> 28139.56 | K6: ='Water-Meter'!E7 -> 101 | L6: ='Lpg (2)'!G11 -> 124.52 | M6: =SUM(#REF!-#REF!) -> #REF!
A7: =Gen!A13 -> 44380 | B7: ='Daily report Gen'!Z8 -> 40 | C7: =Gen!B13 -> 0.2609 | D7: =E7 -> 20 | E7: 20 | F7: =Gen!T13 -> 4467 | G7: =Gen!S13 -> 1810.5 | H7: =Gen!AJ13 -> 0 | I7: =SUM(G7:H7) -> 1810.5 | J7: =Gen!C13 -> 44122.83 | K7: ='Water-Meter'!E8 -> 94 | L7: ='Lpg (2)'!G12 -> 44 | M7: =SUM(#REF!-#REF!) -> #REF!
A8: =Gen!A14 -> 44381 | B8: ='Daily report Gen'!Z9 -> 36 | C8: =Gen!B14 -> 0.18 | D8: =E8 -> 14 | E8: 14 | F8: =Gen!T14 -> 4106 | G8: =Gen!S14 -> 1652.34 | H8: =Gen!AJ14 -> 233.22 | I8: =SUM(G8:H8) -> 1885.56 | J8: =Gen!C14 -> 42312.33 | K8: ='Water-Meter'!E9 -> 98 | L8: ='Lpg (2)'!G13 -> 89.364 | M8: =SUM(#REF!-#REF!) -> #REF!
A9: =Gen!A15 -> 44382 | B9: ='Daily report Gen'!Z10 -> 34 | C9: =Gen!B15 -> 0.14 | D9: =E9 -> 11 | E9: 11 | F9: =Gen!T15 -> 4026 | G9: =Gen!S15 -> 1644.32 | H9: =Gen!AJ15 -> 148.61 | I9: =SUM(G9:H9) -> 1792.93 | J9: =Gen!C15 -> 40426.77 | K9: ='Water-Meter'!E10 -> 135 | L9: ='Lpg (2)'!G14 -> 112.42 | M9: =SUM(#REF!-#REF!) -> #REF!
A10: =Gen!A16 -> 44383 | B10: ='Daily report Gen'!Z11 -> 35 | C10: =Gen!B16 -> 0.169 | D10: =E10 -> 14 | E10: 14 | F10: =Gen!T16 -> 4145 | G10: =Gen!S16 -> 1669.23 | H10: =Gen!AJ16 -> 199.93 | I10: =SUM(G10:H10) -> 1869.16 | J10: =Gen!C16 -> 38633.84 | K10: ='Water-Meter'!E11 -> 124 | L10: ='Lpg (2)'!G15 -> 116.776 | M10: =SUM(#REF!-#REF!) -> #REF!
A11: =Gen!A17 -> 44384 | B11: ='Daily report Gen'!Z12 -> 41 | C11: =Gen!B17 -> 0.364 | D11: =E11 -> 29 | E11: 29 | F11: =Gen!T17 -> 4675 | G11: =Gen!S17 -> 1898.91 | H11: =Gen!AJ17 -> 168.95 | I11: =SUM(G11:H11) -> 2067.86 | J11: =Gen!C17 -> 36764.68 | K11: ='Water-Meter'!E12 -> 114 | L11: ='Lpg (2)'!G16 -> 108.328 | M11: =SUM(#REF!-#REF!) -> #REF!
A12: =Gen!A18 -> 44385 | B12: ='Daily report Gen'!Z13 -> 37 | C12: =Gen!B18 -> 0.455 | D12: =E12 -> 35 | E12: 35 | F12: =Gen!T18 -> 4550 | G12: =Gen!S18 -> 1865.79 | H12: =Gen!AJ18 -> 47 | I12: =SUM(G12:H12) -> 1912.79 | J12: =Gen!C18 -> 34696.82 | K12: ='Water-Meter'!E13 -> 94 | L12: ='Lpg (2)'!G17 -> 112.376 | M12: =SUM(#REF!-#REF!) -> #REF!
A13: =Gen!A19 -> 44386 | B13: ='Daily report Gen'!Z14 -> 29 | C13: =Gen!B19 -> 0.468 | D13: =E13 -> 39 | E13: 39 | F13: =Gen!T19 -> 4263 | G13: =Gen!S19 -> 1807.22 | H13: =Gen!AJ19 -> 456 | I13: =SUM(G13:H13) -> 2263.22 | J13: =Gen!C19 -> 32784.03 | K13: ='Water-Meter'!E14 -> 108 | L13: ='Lpg (2)'!G18 -> 103.4 | M13: =SUM(#REF!-#REF!) -> #REF!
A14: =Gen!A20 -> 44387 | B14: ='Daily report Gen'!Z15 -> 43 | C14: =Gen!B20 -> 0.39 | D14: =E14 -> 32 | E14: 32 | F14: =Gen!T20 -> 4506 | G14: =Gen!S20 -> 1887.88 | H14: =Gen!AJ20 -> 644.97 | I14: =SUM(G14:H14) -> 2532.85 | J14: =Gen!C20 -> 30520.81 | K14: ='Water-Meter'!E15 -> 116 | L14: ='Lpg (2)'!G19 -> 117.304 | M14: =SUM(#REF!-#REF!) -> #REF!
A15: =Gen!A21 -> 44388 | B15: ='Daily report Gen'!Z16 -> 43 | C15: =Gen!B21 -> 0.403 | D15: =E15 -> 31 | E15: 31 | F15: =Gen!T21 -> 4459 | G15: =Gen!S21 -> 1852.6 | H15: =Gen!AJ21 -> 608.62 | I15: =SUM(G15:H15) -> 2461.22 | J15: =Gen!C21 -> 45987.96 | K15: ='Water-Meter'!E16 -> 116 | L15: ='Lpg (2)'!G20 -> 115.676 | M15: =SUM(#REF!-#REF!) -> #REF!
A16: =Gen!A22 -> 44389 | B16: ='Daily report Gen'!Z17 -> 42 | C16: =Gen!B22 -> 0.39 | D16: =E16 -> 32 | E16: 32 | F16: =Gen!T22 -> 4438 | G16: =Gen!S22 -> 1662.17 | H16: =Gen!AJ22 -> 677.99 | I16: =SUM(G16:H16) -> 2340.16 | J16: =Gen!C22 -> 43526.74 | K16: ='Water-Meter'!E17 -> 109 | L16: ='Lpg (2)'!G21 -> 126.984 | M16: =SUM(#REF!-#REF!) -> #REF!
... A19: =Gen!A25 -> 44392 | B19: ='Daily report Gen'!Z20 -> 39 | C19: =Gen!B25 -> 0.208 | D19: =E19 -> 16 | E19: 16 | F19: =Gen!T25 -> 3833 | G19: =Gen!S25 -> 1643.26 | H19: =Gen!AJ25 -> 155.98 | I19: =SUM(G19:H19) -> 1799.24 | J19: =Gen!C25 -> 36052.53 | K19: ='Water-Meter'!E20 -> 83 | L19: ='Lpg (2)'!G24 -> 124.74 | M19: =SUM(#REF!-#REF!) -> #REF!
A20: =Gen!A26 -> 44393 | B20: ='Daily report Gen'!Z21 -> 41 | C20: =Gen!B26 -> 0.27 | D20: =E20 -> 0 | F20: =Gen!T26 -> 4080 | G20: =Gen!S26 -> 1732.74 | H20: =Gen!AJ26 -> 85.68 | I20: =SUM(G20:H20) -> 1818.42 | J20: =Gen!C26 -> 34253.29 | K20: ='Water-Meter'!E21 -> 103 | L20: ='Lpg (2)'!G25 -> 119.064 | M20: =SUM(#REF!-#REF!) -> #REF!
A21: =Gen!A27 -> 44394 | B21: ='Daily report Gen'!Z22 -> 41 | C21: =Gen!B27 -> 0.26 | D21: =E21 -> 0 | F21: =Gen!T27 -> 4092 | G21: =Gen!S27 -> 1766.64 | H21: =Gen!AJ27 -> 496.38 | I21: =SUM(G21:H21) -> 2263.02 | J21: =Gen!C27 -> 32434.87 | K21: ='Water-Meter'!E22 -> 107 | L21: ='Lpg (2)'!G26 -> 114.444 | M21: =SUM(#REF!-#REF!) -> #REF!
A22: =Gen!A28 -> 44395 | B22: ='Daily report Gen'!Z23 -> 41 | C22: =Gen!B28 -> 0.35 | D22: =E22 -> 0 | F22: =Gen!T28 -> 4450 | G22: =Gen!S28 -> 1787.98 | H22: =Gen!AJ28 -> 374.23 | I22: =SUM(G22:H22) -> 2162.21 | J22: =Gen!C28 -> 30171.85 | K22: ='Water-Meter'!E23 -> 128 | L22: ='Lpg (2)'!G27 -> 104.324 | M22: =SUM(#REF!-#REF!) -> #REF!
A23: =Gen!A29 -> 44396 | B23: ='Daily report Gen'!Z24 -> 41 | C23: =Gen!B29 -> 0.39 | D23: =E23 -> 0 | F23: =Gen!T29 -> 4633 | G23: =Gen!S29 -> 1812.39 | H23: =Gen!AJ29 -> 224 | I23: =SUM(G23:H23) -> 2036.39 | J23: =Gen!C29 -> 28009.64 | K23: ='Water-Meter'!E24 -> 115 | L23: ='Lpg (2)'!G28 -> 113.652 | M23: =SUM(#REF!-#REF!) -> #REF!
A24: =Gen!A30 -> 44397 | B24: ='Daily report Gen'!Z25 -> 41 | C24: =Gen!B30 -> 0.39 | D24: =E24 -> 0 | F24: =Gen!T30 -> 4722 | G24: =Gen!S30 -> 2007.64 | H24: =Gen!AJ30 -> 49.26 | I24: =SUM(G24:H24) -> 2056.9 | J24: =Gen!C30 -> 25973.25 | K24: ='Water-Meter'!E25 -> 113 | L24: ='Lpg (2)'!G29 -> 111.892 | M24: =SUM(#REF!-#REF!) -> #REF!
A25: =Gen!A31 -> 44398 | B25: ='Daily report Gen'!Z26 -> 39 | C25: =Gen!B31 -> 0.55 | D25: =E25 -> 0 | F25: =Gen!T31 -> 4911 | G25: =Gen!S31 -> 1992.78 | H25: =Gen!AJ31 -> 556.39 | I25: =SUM(G25:H25) -> 2549.17 | J25: =Gen!C31 -> 23916.35 | K25: ='Water-Meter'!E26 -> 133 | L25: ='Lpg (2)'!G30 -> 336.116 | M25: =SUM(#REF!-#REF!) -> #REF!
A26: =Gen!A32 -> 44399 | B26: ='Daily report Gen'!Z27 -> 50 | C26: =Gen!B32 -> 0.545 | D26: =E26 -> 0 | F26: =Gen!T32 -> 5226 | G26: =Gen!S32 -> 2232.89 | H26: =Gen!AJ32 -> 494.65 | I26: =SUM(G26:H26) -> 2727.54 | J26: =Gen!C32 -> 21367.18 | K26: ='Water-Meter'!E27 -> 113 | L26: ='Lpg (2)'!G31 -> -106.612 | M26: =SUM(#REF!-#REF!) -> #REF!
A27: =Gen!A33 -> 44400 | B27: ='Daily report Gen'!Z28 -> 41 | C27: =Gen!B33 -> 0.455 | D27: =E27 -> 0 | F27: =Gen!T33 -> 4730 | G27: =Gen!S33 -> 2090.79 | H27: =Gen!AJ33 -> 228.3 | I27: =SUM(G27:H27) -> 2319.09 | J27: =Gen!C33 -> 18639.64 | K27: ='Water-Meter'!E28 -> 108 | L27: ='Lpg (2)'!G32 -> 98.296 | M27: =SUM(#REF!-#REF!) -> #REF!
A28: =Gen!A34 -> 44401 | B28: ='Daily report Gen'!Z29 -> 43 | C28: =Gen!B34 -> 0.247 | D28: =E28 -> 0 | F28: =Gen!T34 -> 4879 | G28: =Gen!S34 -> 2014.73 | H28: =Gen!AJ34 -> 442.98 | I28: =SUM(G28:H28) -> 2457.71 | J28: =Gen!C34 -> 16320.55 | K28: ='Water-Meter'!E29 -> 106 | L28: ='Lpg (2)'!G33 -> 98.868 | M28: =SUM(#REF!-#REF!) -> #REF!
A29: =Gen!A35 -> 44402 | B29: ='Daily report Gen'!Z30 -> 41 | C29: =Gen!B35 -> 0.208 | D29: =E29 -> 0 | F29: =Gen!T35 -> 4599 | G29: =Gen!S35 -> 1869.09 | H29: =Gen!AJ35 -> 259.79 | I29: =SUM(G29:H29) -> 2128.88 | J29: =Gen!C35 -> 28862.84 | K29: ='Water-Meter'!E30 -> 106 | L29: ='Lpg (2)'!G34 -> 106.392 | M29: =SUM(#REF!-#REF!) -> #REF!
A30: =Gen!A36 -> 44403 | B30: ='Daily report Gen'!Z31 -> 42 | C30: =Gen!B36 -> 0.156 | D30: =E30 -> 0 | F30: =Gen!T36 -> 4415 | G30: =Gen!S36 -> 1888.8 | H30: =Gen!AJ36 -> 70.92 | I30: =SUM(G30:H30) -> 1959.72 | J30: =Gen!C36 -> 26733.96 | K30: ='Water-Meter'!E31 -> 96 | L30: ='Lpg (2)'!G35 -> 93.324 | M30: =SUM(#REF!-#REF!) -> #REF!
A31: =Gen!A37 -> 44404 | B31: ='Daily report Gen'!Z32 -> 40 | C31: =Gen!B37 -> 0.299 | D31: =E31 -> 0 | F31: =Gen!T37 -> 4607 | G31: =Gen!S37 -> 1921.29 | H31: =Gen!AJ37 -> 491.89 | I31: =SUM(G31:H31) -> 2413.18 | J31: =Gen!C37 -> 24774.24 | K31: ='Water-Meter'!E32 -> 103 | L31: ='Lpg (2)'!G36 -> 74.228 | M31: =SUM(#REF!-#REF!) -> #REF!
... A35: =Gen!A41 -> 44408 | B35: ='Daily report Gen'!Z36 -> 40 | C35: =Gen!B41 -> 0.15 | D35: =E35 -> 0 | F35: =Gen!T41 -> 4015 | G35: =Gen!S41 -> 1680.02 | H35: =Gen!AJ41 -> 376.24 | I35: =SUM(G35:H35) -> 2056.26 | J35: =Gen!C41 -> 31086.39 | K35: ='Water-Meter'!E36 -> 99 | L35: ='Lpg (2)'!G40 -> 111.232 | M35: =SUM(#REF!-#REF!) -> #REF!
A36: =Gen!A42 -> 0 | B36: ='Daily report Gen'!Z37 -> -162399 | C36: =Gen!B42 -> 0 | D36: =E36 -> 0 | F36: =Gen!T42 -> 0 | G36: =Gen!S42 -> 0 | H36: =Gen!AJ42 -> 0 | I36: =SUM(G36:H36) -> 0 | J36: =Gen!C42 -> 29030.13 | K36: ='Water-Meter'!E37 -> 0 | L36: ='Lpg (2)'!G41 -> -344473.58

Sheet Daily report Gen
A1: =A6 -> 44378
K3: GENERATOR NO.1 | N3: GENERATOR NO.2 | Q3: GENERATOR NO.4 | T3: GENERATOR NO.5 | W3: GENERATOR NO.6
A4: DATE | B4: OCC% | C4: D-TANK A | D4: D-TANK B | E4: DELIVERY DATE | F4: DELIVERY | G4: ISSUED-VEHICLE | H4: OTHERS | I4: M-R LV PANEL 1. KW-HR | J4: M-R LV PANEL 2. KW-HR | K4: OPEN HRS READING | L4: CLOSE HRS READING | M4: RUNNING HRS | N4: OPEN HRS READING | O4: CLOSE HRS READING | P4: RUNNING HRS | Q4: OPEN HRS READING | R4: CLOSE HRS READING | S4: RUNNING HRS | T4: OPEN HRS READING | U4: CLOSE HRS READING | V4: RUNNING HRS | W4: OPEN HRS READING | X4: CLOSE HRS READING | Y4: RUNNING HRS | Z4: TOTAL RUNNING HRS | AA4: MAX KW | AB4: MIN-KW | AC4: TOTAL DIESEL CONS.
L5: 36628 | O5: 31504 | R5: 36782 | U5: 33996 | X5: 22248 | AA5: 365 | AB5: 135
A6: =Gen!A11 -> 44378 | B6: =Gen!B11 -> 0.3 | C6: 16439.27 | D6: 13501.87 | I6: 32326.4 | J6: 21546.1 | K6: =L5 -> 36628 | L6: 36643 | M6: =L6-K6 -> 15 | N6: =O5 -> 31504 | O6: 31504 | P6: =O6-N6 -> 0 | Q6: =R5 -> 36782 | R6: 36786 | S6: =R6-Q6 -> 4 | T6: =U5 -> 33996 | U6: 34001 | V6: =U6-T6 -> 5 | W6: =X5 -> 22248 | X6: 22258 | Y6: =X6-W6 -> 10 | Z6: =Y6+V6+S6+P6+M6 -> 34 | AA6: 370 | AB6: 150 | AC6: =Gen!AR11 -> 1799.58
A7: =Gen!A12 -> 44379 | B7: =Gen!B12 -> 0.35 | C7: 16439.27 | D7: 11699.29 | G7: 324.81 | I7: 32333.5 | J7: 21550.8 | K7: =L6 -> 36643 | L7: 36653 | M7: =L7-K7 -> 10 | N7: =O6 -> 31504 | O7: 31504 | P7: =O7-N7 -> 0 | Q7: =R6 -> 36786 | R7: 36786 | S7: =R7-Q7 -> 0 | T7: =U6 -> 34001 | U7: 34016 | V7: =U7-T7 -> 15 | W7: =X6 -> 22258 | X7: 22268 | Y7: =X7-W7 -> 10 | Z7: =Y7+V7+S7+P7+M7 -> 35 | AA7: 385 | AB7: 165 | AC7: =Gen!AR12 -> 2016.73
A8: =Gen!A13 -> 44380 | B8: =Gen!B13 -> 0.2609 | C8: 20200.27 | D8: 23921.83 | I8: 32340.8 | J8: 21555.8 | K8: =L7 -> 36653 | L8: 36668 | M8: =L8-K8 -> 15 | N8: =O7 -> 31504 | O8: 31505 | P8: =O8-N8 -> 1 | Q8: =R7 -> 36786 | R8: 36786 | S8: =R8-Q8 -> 0 | T8: =U7 -> 34016 | U8: 34030 | V8: =U8-T8 -> 14 | W8: =X7 -> 22268 | X8: 22278 | Y8: =X8-W8 -> 10 | Z8: =Y8+V8+S8+P8+M8 -> 40 | AA8: 365 | AB8: 140 | AC8: =Gen!AR13 -> 1810.5
A9: =Gen!A14 -> 44381 | B9: =Gen!B14 -> 0.18 | C9: 20200.27 | D9: 22111.06 | G9: 233.22 | I9: 32348.4 | J9: 21560.6 | K9: =L8 -> 36668 | L9: 36674 | M9: =L9-K9 -> 6 | N9: =O8 -> 31505 | O9: 31505 | P9: =O9-N9 -> 0 | Q9: =R8 -> 36786 | R9: 36796 | S9: =R9-Q9 -> 10 | T9: =U8 -> 34030 | U9: 34041 | V9: =U9-T9 -> 11 | W9: =X8 -> 22278 | X9: 22287 | Y9: =X9-W9 -> 9 | Z9: =Y9+V9+S9+P9+M9 -> 36 | AA9: 380 | AB9: 170 | AC9: =Gen!AR14 -> 1885.56
A10: =Gen!A15 -> 44382 | B10: =Gen!B15 -> 0.14 | C10: 20200.27 | D10: 20225.5 | G10: 148.61 | I10: 32355.4 | J10: 21564.9 | K10: =L9 -> 36674 | L10: 36674 | M10: =L10-K10 -> 0 | N10: =O9 -> 31505 | O10: 31514 | P10: =O10-N10 -> 9 | Q10: =R9 -> 36796 | R10: 36811 | S10: =R10-Q10 -> 15 | T10: =U9 -> 34041 | U10: 34051 | V10: =U10-T10 -> 10 | W10: =X9 -> 22287 | X10: 22287 | Y10: =X10-W10 -> 0 | Z10: =Y10+V10+S10+P10+M10 -> 34 | AA10: 360 | AB10: 150 | AC10: =Gen!AR15 -> 1792.93
A11: =Gen!A16 -> 44383 | B11: =Gen!B16 -> 0.169 | C11: 20200.27 | D11: 18432.57 | G11: 199.93 | I11: 32362.4 | J11: 21569.2 | K11: =L10 -> 36674 | L11: 36689 | M11: =L11-K11 -> 15 | N11: =O10 -> 31514 | O11: 31514 | P11: =O11-N11 -> 0 | Q11: =R10 -> 36811 | R11: 36811 | S11: =R11-Q11 -> 0 | T11: =U10 -> 34051 | U11: 34060 | V11: =U11-T11 -> 9 | W11: =X10 -> 22287 | X11: 22298 | Y11: =X11-W11 -> 11 | Z11: =Y11+V11+S11+P11+M11 -> 35 | AA11: 370 | AB11: 160 | AC11: =Gen!AR16 -> 1869.16
A12: =Gen!A17 -> 44384 | B12: =Gen!B17 -> 0.364 | C12: 20200.27 | D12: 16664.14 | G12: 168.95 | I12: 32369.7 | J12: 21573.5 | K12: =L11 -> 36689 | L12: 36699 | M12: =L12-K12 -> 10 | N12: =O11 -> 31514 | O12: 31516 | P12: =O12-N12 -> 2 | Q12: =R11 -> 36811 | R12: 36817 | S12: =R12-Q12 -> 6 | T12: =U11 -> 34060 | U12: 34069 | V12: =U12-T12 -> 9 | W12: =X11 -> 22298 | X12: 22312 | Y12: =X12-W12 -> 14 | Z12: =Y12+V12+S12+P12+M12 -> 41 | AA12: 382 | AB12: 168 | AC12: =Gen!AR17 -> 2067.86
A13: =Gen!A18 -> 44385 | B13: =Gen!B18 -> 0.455 | C13: 20200.27 | D13: 14596.28 | G13: 47 | I13: 32377.3 | J13: 21578.7 | K13: =L12 -> 36699 | L13: 36715 | M13: =L13-K13 -> 16 | N13: =O12 -> 31516 | O13: 31527 | P13: =O13-N13 -> 11 | Q13: =R12 -> 36817 | R13: 36817 | S13: =R13-Q13 -> 0 | T13: =U12 -> 34069 | U13: 34069 | V13: =U13-T13 -> 0 | W13: =X12 -> 22312 | X13: 22322 | Y13: =X13-W13 -> 10 | Z13: =Y13+V13+S13+P13+M13 -> 37 | AA13: 370 | AB13: 180 | AC13: =Gen!AR18 -> 1912.79
A14: =Gen!A19 -> 44386 | B14: =Gen!B19 -> 0.468 | C14: 20200.27 | D14: 12683.49 | I14: 32385.8 | J14: 21583.4 | K14: =L13 -> 36715 | L14: 36723 | M14: =L14-K14 -> 8 | N14: =O14 -> 31539 | O14: 31539 | P14: =O14-N14 -> 0 | Q14: =R13 -> 36817 | R14: 36821 | S14: =R14-Q14 -> 4 | T14: =U13 -> 34069 | U14: 34074 | V14: =U14-T14 -> 5 | W14: =X13 -> 22322 | X14: 22334 | Y14: =X14-W14 -> 12 | Z14: =Y14+V14+S14+P14+M14 -> 29 | AA14: 380 | AB14: 200 | AC14: =Gen!AR19 -> 2263.22
A15: =Gen!A20 -> 44387 | B15: =Gen!B20 -> 0.39 | C15: 20200.27 | D15: 10419.27 | G15: 644.97 | I15: 32393.7 | J15: 21587.9 | K15: =L14 -> 36723 | L15: 36732 | M15: =L15-K15 -> 9 | N15: =O15 -> 31554 | O15: 31554 | P15: =O16-N15 -> 17 | Q15: =R14 -> 36821 | R15: 36821 | S15: =R15-Q15 -> 0 | T15: =U14 -> 34074 | U15: 34075 | V15: =U15-T15 -> 1 | W15: =X14 -> 22334 | X15: 22350 | Y15: =X15-W15 -> 16 | Z15: =Y15+V15+S15+P15+M15 -> 43 | AA15: 385 | AB15: 210 | AC15: =Gen!AR20 -> 2532.85
A16: =Gen!A21 -> 44388 | B16: =Gen!B21 -> 0.403 | C16: 23886.34 | D16: 22200.34 | G16: 608.62 | I16: 32401.7 | J16: 21592.8 | K16: =L15 -> 36732 | L16: 36732 | M16: =L16-K16 -> 0 | N16: =O15 -> 31554 | O16: 31571 | P16: =O16-N16 -> 17 | Q16: =R15 -> 36821 | R16: 36822 | S16: =R16-Q16 -> 1 | T16: =U14 -> 34074 | U16: 34091 | V16: =U16-T16 -> 17 | W16: =X15 -> 22350 | X16: 22358 | Y16: =X16-W16 -> 8 | Z16: =Y16+V16+S16+P16+M16 -> 43 | AA16: 380 | AB16: 200 | AC16: =Gen!AR21 -> 2461.22
A17: =Gen!A22 -> 44389 | B17: =Gen!B22 -> 0.39 | C17: 23886.34 | D17: 19739.13 | G17: 677.99 | I17: 32409.8 | J17: 21597.7 | K17: =L16 -> 36732 | L17: 36749 | M17: =L17-K17 -> 17 | N17: =O16 -> 31571 | O17: 31571 | P17: =O17-N17 -> 0 | Q17: =R16 -> 36822 | R17: 36822 | S17: =R17-Q17 -> 0 | T17: =U16 -> 34091 | U17: 34107 | V17: =U17-T17 -> 16 | W17: =X16 -> 22358 | X17: 22367 | Y17: =X17-W17 -> 9 | Z17: =Y17+V17+S17+P17+M17 -> 42 | AA17: 365 | AB17: 190 | AC17: =Gen!AR22 -> 2340.16
A18: =Gen!A23 -> 44390 | B18: =Gen!B23 -> 0.221 | C18: 23886.34 | D18: 17398.97 | I18: 32417.6 | J18: 21602.6 | K18: =L17 -> 36749 | L18: 36765 | M18: =L18-K18 -> 16 | N18: =O17 -> 31571 | O18: 31571 | P18: =O18-N18 -> 0 | Q18: =R17 -> 36822 | R18: 36822 | S18: =R18-Q18 -> 0 | T18: =U17 -> 34107 | U18: 34120 | V18: =U18-T18 -> 13 | W18: =X17 -> 22367 | X18: 22377 | Y18: =X18-W18 -> 10 | Z18: =Y18+V18+S18+P18+M18 -> 39 | AA18: 370 | AB18: 260 | AC18: =Gen!AR23 -> 2049.04
A19: =Gen!A24 -> 44391 | B19: =Gen!B24 -> 0.195 | C19: 21837.3 | D19: 17398.97 | I19: 34424.5 | J19: 21607.1 | K19: =L18 -> 36765 | L19: 36781 | M19: =L19-K19 -> 16 | N19: =O18 -> 31571 | O19: 31586 | P19: =O19-N19 -> 15 | Q19: =R18 -> 36822 | R19: 36822 | S19: =R19-Q19 -> 0 | T19: =U18 -> 34120 | U19: 34129 | V19: =U19-T19 -> 9 | W19: =X18 -> 22377 | X19: 22378 | Y19: =X19-W19 -> 1 | Z19: =Y19+V19+S19+P19+M19 -> 41 | AA19: 375 | AB19: 265 | AC19: =Gen!AR24 -> 3085.01
A20: =Gen!A25 -> 44392 | B20: =Gen!B25 -> 0.208 | C20: 19752.29 | D20: 17398.97 | I20: 32431.9 | J20: 21611.3 | K20: =L19 -> 36781 | L20: 36791 | M20: =L20-K20 -> 10 | N20: =O19 -> 31586 | O20: 31601 | P20: =O20-N20 -> 15 | Q20: =R19 -> 36822 | R20: 36822 | S20: =R20-Q20 -> 0 | T20: =U19 -> 34129 | U20: 34129 | V20: =U20-T20 -> 0 | W20: =X19 -> 22378 | X20: 22392 | Y20: =X20-W20 -> 14 | Z20: =Y20+V20+S20+P20+M20 -> 39 | AA20: 370 | AB20: 255 | AC20: =Gen!AR25 -> 1799.24
A21: =Gen!A26 -> 44393 | B21: =Gen!B26 -> 0.27 | C21: 16953.05 | D21: 17398.97 | I21: 32438.9 | J21: 21615.2 | K21: =L20 -> 36791 | L21: 36791 | M21: =L21-K21 -> 0 | N21: =O20 -> 31601 | O21: 31617 | P21: =O21-N21 -> 16 | Q21: =R20 -> 36822 | R21: 36822 | S21: =R21-Q21 -> 0 | T21: =U20 -> 34129 | U21: 34138 | V21: =U21-T21 -> 9 | W21: =X20 -> 22392 | X21: 22408 | Y21: =X21-W21 -> 16 | Z21: =Y21+V21+S21+P21+M21 -> 41 | AA21: 365 | AB21: 260 | AC21: =Gen!AR26 -> 1818.42
A22: =Gen!A27 -> 44394 | B22: =Gen!B27 -> 0.26 | C22: 1513405 | D22: 17398.97 | I22: 32446.4 | J22: 21619.5 | K22: =L21 -> 36791 | L22: 36807 | M22: =L22-K22 -> 16 | N22: =O21 -> 31617 | O22: 31617 | P22: =O22-N22 -> 0 | Q22: =R21 -> 36822 | R22: 36822 | S22: =R22-Q22 -> 0 | T22: =U21 -> 34138 | U22: 34147 | V22: =U22-T22 -> 9 | W22: =X21 -> 22408 | X22: 22424 | Y22: =X22-W22 -> 16 | Z22: =Y22+V22+S22+P22+M22 -> 41 | AA22: 370 | AB22: 265 | AC22: =Gen!AR27 -> 2263.02
A23: =Gen!A28 -> 44395 | B23: =Gen!B28 -> 0.35 | C23: 12871.61 | D23: 17398.97 | I23: 32453.7 | J23: 21624.1 | K23: =L22 -> 36807 | L23: 36820 | M23: =L23-K23 -> 13 | N23: =O22 -> 31617 | O23: 31629 | P23: =O23-N23 -> 12 | Q23: =R22 -> 36822 | R23: 36822 | S23: =R23-Q23 -> 0 | T23: =U22 -> 34147 | U23: 34147 | V23: =U23-T23 -> 0 | W23: =X22 -> 22424 | X23: 22440 | Y23: =X23-W23 -> 16 | Z23: =Y23+V23+S23+P23+M23 -> 41 | AA23: 370 | AB23: 265 | AC23: =Gen!AR28 -> 2162.21
A24: =Gen!A29 -> 44396 | B24: =Gen!B29 -> 0.39 | C24: 17398.97 | D24: 17398.97 | I24: 32461.3 | J24: 21629.1 | K24: =L23 -> 36820 | L24: 36820 | M24: =L24-K24 -> 0 | N24: =O23 -> 31629 | O24: 31646 | P24: =O24-N24 -> 17 | Q24: =R23 -> 36822 | R24: 36822 | S24: =R24-Q24 -> 0 | T24: =U23 -> 34147 | U24: 34164 | V24: =U24-T24 -> 17 | W24: =X23 -> 22440 | X24: 22447 | Y24: =X24-W24 -> 7 | Z24: =Y24+V24+S24+P24+M24 -> 41 | AA24: 365 | AB24: 240 | AC24: =Gen!AR29 -> 2036.39
A25: =Gen!A30 -> 44397 | B25: =Gen!B30 -> 0.39 | C25: 8673.01 | D25: 8673.01 | I25: 32469.1 | J25: 21634.5 | K25: =L24 -> 36820 | L25: 36836 | M25: =L25-K25 -> 16 | N25: =O24 -> 31646 | O25: 31646 | P25: =O25-N25 -> 0 | Q25: =R24 -> 36822 | R25: 36822 | S25: =R25-Q25 -> 0 | T25: =U24 -> 34164 | U25: 34180 | V25: =U25-T25 -> 16 | W25: =X24 -> 22447 | X25: 22456 | Y25: =X25-W25 -> 9 | Z25: =Y25+V25+S25+P25+M25 -> 41 | AA25: 370 | AB25: 270 | AC25: =Gen!AR30 -> 2056.9
A26: =Gen!A31 -> 44398 | B26: =Gen!B31 -> 0.55 | C26: 6616.11 | D26: 6616.11 | I26: 32476.8 | J26: 21640.1 | K26: =L25 -> 36836 | L26: 36851 | M26: =L26-K26 -> 15 | N26: =O25 -> 31646 | O26: 31646 | P26: =O26-N26 -> 0 | Q26: =R25 -> 36822 | R26: 36822 | S26: =R26-Q26 -> 0 | T26: =U25 -> 34180 | U26: 34191 | V26: =U26-T26 -> 11 | W26: =X25 -> 22456 | X26: 22469 | Y26: =X26-W26 -> 13 | Z26: =Y26+V26+S26+P26+M26 -> 39 | AA26: 380 | AB26: 275 | AC26: =Gen!AR31 -> 2549.17
A27: =Gen!A32 -> 44399 | B27: =Gen!B32 -> 0.545 | C27: 4066.22 | D27: 4066.22 | I27: 32485.1 | J27: 21646.4 | K27: =L26 -> 36851 | L27: 36876 | M27: =L27-K27 -> 25 | N27: =O26 -> 31646 | O27: 31646 | P27: =O27-N27 -> 0 | Q27: =R26 -> 36822 | R27: 36822 | S27: =R27-Q27 -> 0 | T27: =U26 -> 34191 | U27: 34200 | V27: =U27-T27 -> 9 | W27: =X26 -> 22469 | X27: 22485 | Y27: =X27-W27 -> 16 | Z27: =Y27+V27+S27+P27+M27 -> 50 | AA27: 380 | AB27: 270 | AC27: =Gen!AR32 -> 2727.54
A28: =Gen!A33 -> 44400 | B28: =Gen!B33 -> 0.455 | C28: 1339.4 | D28: 979.69 | I28: 32493.4 | J28: 21652.8 | K28: =L27 -> 36876 | L28: 36876 | M28: =L28-K28 -> 0 | N28: =O27 -> 31646 | O28: 31664 | P28: =O28-N28 -> 18 | Q28: =R27 -> 36822 | R28: 36822 | S28: =R28-Q28 -> 0 | T28: =U27 -> 34200 | U28: 34215 | V28: =U28-T28 -> 15 | W28: =X27 -> 22485 | X28: 22493 | Y28: =X28-W28 -> 8 | Z28: =Y28+V28+S28+P28+M28 -> 41 | AA28: 370 | AB28: 265 | AC28: =Gen!AR33 -> 2319.09
A29: =Gen!A34 -> 44401 | B29: =Gen!B34 -> 0.247 | C29: 16419.28 | D29: 979.69 | I29: 32501.3 | J29: 21658.6 | K29: =L28 -> 36876 | L29: 36894 | M29: =L29-K29 -> 18 | N29: =O28 -> 31664 | O29: 31664 | P29: =O29-N29 -> 0 | Q29: =R28 -> 36822 | R29: 36822 | S29: =R29-Q29 -> 0 | T29: =U28 -> 34215 | U29: 34232 | V29: =U29-T29 -> 17 | W29: =X28 -> 22493 | X29: 22501 | Y29: =X29-W29 -> 8 | Z29: =Y29+V29+S29+P29+M29 -> 43 | AA29: 375 | AB29: 270 | AC29: =Gen!AR34 -> 2457.71
... A32: =Gen!A37 -> 44404 | B32: =Gen!B37 -> 0.299 | C32: 23892.28 | D32: 979.69 | I32: 32524.3 | J32: 21674.9 | K32: =L31 -> 36927 | L32: 36927 | M32: =L32-K32 -> 0 | N32: =O31 -> 31681 | O32: 31697 | P32: =O32-N32 -> 16 | Q32: =R31 -> 36822 | R32: 36822 | S32: =R32-Q32 -> 0 | T32: =U31 -> 34248 | U32: 34256 | V32: =U32-T32 -> 8 | W32: =X31 -> 22518 | X32: 22534 | Y32: =X32-W32 -> 16 | Z32: =Y32+V32+S32+P32+M32 -> 40 | AA32: 380 | AB32: 270 | AC32: =Gen!AR37 -> 2413.18
A33: =Gen!A38 -> 44405 | B33: =Gen!B38 -> 0.468 | C33: 21479.1 | D33: 979.69 | G33: 147.47 | I33: 32531.5 | J33: 21680.7 | K33: =L32 -> 36927 | L33: 36944 | M33: =L33-K33 -> 17 | N33: =O32 -> 31697 | O33: 31697 | P33: =O33-N33 -> 0 | Q33: =R32 -> 36822 | R33: 36822 | S33: =R33-Q33 -> 0 | T33: =U32 -> 34256 | U33: 34264 | V33: =U33-T33 -> 8 | W33: =X32 -> 22534 | X33: 22550 | Y33: =X33-W33 -> 16 | Z33: =Y33+V33+S33+P33+M33 -> 41 | AA33: 370 | AB33: 210 | AC33: =Gen!AR38 -> 1844.09
A34: =Gen!A39 -> 44406 | B34: =Gen!B39 -> 0.51 | C34: 21479.1 | D34: 14135.6 | G34: 246.95 | I34: 32539.1 | J34: 21686.3 | K34: =L33 -> 36944 | L34: 36949 | M34: =L34-K34 -> 5 | N34: =O33 -> 31697 | O34: 31708 | P34: =O34-N34 -> 11 | Q34: =R34 -> 36822 | R34: 36822 | S34: =R34-Q34 -> 0 | T34: =U33 -> 34264 | U34: 34272 | V34: =U34-T34 -> 8 | W34: =X33 -> 22550 | X34: 22566 | Y34: =X34-W34 -> 16 | Z34: =Y34+V34+S34+P34+M34 -> 40 | AA34: 390 | AB34: 220 | AC34: =Gen!AR39 -> 2239.01
A35: =Gen!A40 -> 44407 | B35: =Gen!B40 -> 0.38 | C35: 19240.09 | D35: 14135.6 | G35: 369 | I35: 32546.3 | J35: 21692.1 | K35: =L34 -> 36949 | L35: 36966 | M35: =L35-K35 -> 17 | N35: =O34 -> 31708 | O35: 31708 | P35: =O35-N35 -> 0 | Q35: =R35 -> 36822 | R35: 36822 | S35: =R35-Q35 -> 0 | T35: =U34 -> 34272 | U35: 34281 | V35: =U35-T35 -> 9 | W35: =X34 -> 22566 | X35: 22582 | Y35: =X35-W35 -> 16 | Z35: =Y35+V35+S35+P35+M35 -> 42 | AA35: 380 | AB35: 210 | AC35: =Gen!AR40 -> 2191.57
A36: =Gen!A41 -> 44408 | B36: =Gen!B41 -> 0.15 | C36: 17048.52 | D36: 14135.6 | G36: 376.24 | I36: 32553.7 | J36: 21697.4 | K36: =L35 -> 36966 | L36: 36979 | M36: =L36-K36 -> 13 | N36: =O35 -> 31708 | O36: 31711 | P36: =O36-N36 -> 3 | Q36: =R35 -> 36822 | R36: 36822 | S36: =R36-Q36 -> 0 | T36: =U35 -> 34281 | U36: 34290 | V36: =U36-T36 -> 9 | W36: =X35 -> 22582 | X36: 22597 | Y36: =X36-W36 -> 15 | Z36: =Y36+V36+S36+P36+M36 -> 40 | AA36: 375 | AB36: 195 | AC36: =Gen!AR41 -> 2056.26
A37: =Gen!A42 -> 0 | B37: =Gen!B42 -> 0 | C37: 14992.26 | D37: 14135.6 | I37: 32560.6 | J37: 21702.6 | K37: =L36 -> 36979 | M37: =L37-K37 -> -36979 | N37: =O36 -> 31711 | P37: =O37-N37 -> -31711 | Q37: =R36 -> 36822 | S37: =R37-Q37 -> -36822 | T37: =U36 -> 34290 | V37: =U37-T37 -> -34290 | W37: =X36 -> 22597 | Y37: =X37-W37 -> -22597 | Z37: =Y37+V37+S37+P37+M37 -> -162399 | AC37: =Gen!AR42 -> 0

Sheet Gen
D2: =A11 -> 44378
F6: BILILA LODGE INVESTMENT LIMITED | V6: 1 | W6: 2 | X6: 3 | Y6: 4 | Z6: 5 | AA6: 6 | AB6: 7 | AC6: 8 | AD6: 9 | AE6: 10 | AF6: 11
F7: Diesel Consumed by 500KVA Generator | M7: 500KVA Generator KWh | V7: Safari-STAFF | W7: Safari-STAFF | X7: Lc/swg/gust | Y7: Eng pikcup | Z7: VIP Safari Car | AA7: GX Guest | AB7: GX Guest | AC7: T/Hillux/pur | AD7: TATA | AE7: MAN | AF7: F/Truck | AG7: Incenerator | AH7: A&K | AI7: OTHER | AJ7: TOTAL CO
A8: Date | B8: Occupancy % | C8: OPENING | D8: Received | E8: Schedule delivery | F8: Company | G8: 1 | H8: 2 | I8: 3 | J8: 4 | K8: 5 | L8: 6 | M8: 1 | N8: 2 | O8: 3 | P8: 4 | Q8: 5 | R8: 6 | S8: Total Diseal Consumed | T8: Total Kwh generated | U8: Average Diesel/Kwh | V8: T 128 AXJ | W8: T 134 AXJ | X8: T 499 AXG | Y8: T 217 CHV | Z8: T 214 CHV | AA8: T 139 AXE | AB8: T 242 AXN | AC8: T 476 AWZ | AD8: T 226 AUQ | AE8: T 308 CLD | AF8: T 852 AWU | AG8: Machine ENG | AH8: Vehicle | AI8: Vehicle | AR8: Total Diseal Consumed Gen & Vehicle | AS8: Total cost /Day (TSH) | AT8: BALANCE
C9: =[2]Gen!$C$43 -> 29939.14 | S9: =SUM(F9:L9) -> 0 | AR9: =SUM(AJ9+S9) -> 0 | AT9: 38784.7
S10: =SUM(F10:L10) -> 0 | T10: =SUM(M10:R10) -> 0 | AJ10: =SUM(V10:AI10) -> 0 | AR10: =SUM(AJ10+S10) -> 0
A11: 44378 | B11: 0.3 | C11: =SUM(C9+D11) -> 29939.14 | G11: 816.6 | J11: 239.84 | K11: 200.76 | L11: 542.38 | M11: 2015 | P11: 377 | Q11: 487 | R11: 1385 | S11: =SUM(F11:L11) -> 1799.58 | T11: =SUM(M11:R11) -> 4264 | U11: =S11/T11 -> 0.42204034 | AJ11: =SUM(V11:AI11) -> 0 | AR11: =SUM(AJ11+S11) -> 1799.58 | AS11: =AR11*AU11 -> 0 | AT11: =C11 -> 29939.14
A12: 44379 | B12: 0.35 | C12: =SUM(C11-AR11+D12) -> 28139.56 | G12: 388.86 | K12: 781.3 | L12: 521.76 | M12: 1002 | Q12: 1935 | R12: 1337 | S12: =SUM(F12:L12) -> 1691.92 | T12: =SUM(M12:R12) -> 4274 | U12: =S12/T12 -> 0.39586336 | V12: 108.94 | Z12: 88.83 | AH12: 87.04 | AI12: 40 | AJ12: =SUM(V12:AI12) -> 324.81 | AR12: =SUM(AJ12+S12) -> 2016.73 | AS12: =AR12*AU12 -> 0 | AT12: =C12 -> 28139.56
A13: 44380 | B13: 0.2609 | C13: =SUM(C12-AR12+D13) -> 44122.83 | D13: 18000 | E13: 18000 | F13: RAHA | G13: 649.14 | K13: 606.64 | L13: 554.72 | M13: 1649 | Q13: 1389 | R13: 1429 | S13: =SUM(F13:L13) -> 1810.5 | T13: =SUM(M13:R13) -> 4467 | U13: =S13/T13 -> 0.40530557 | AJ13: =SUM(V13:AI13) -> 0 | AR13: =SUM(AJ13+S13) -> 1810.5 | AS13: =AR13*AU13 -> 0 | AT13: =C13 -> 44122.83
A14: 44381 | B14: 0.18 | C14: =SUM(C13-AR13+D14) -> 42312.33 | G14: 335.4 | J14: 545.32 | K14: 324.84 | L14: 446.78 | M14: 497 | P14: 1335 | Q14: 944 | R14: 1330 | S14: =SUM(F14:L14) -> 1652.34 | T14: =SUM(M14:R14) -> 4106 | U14: =S14/T14 -> 0.40242085 | Z14: 36.1 | AA14: 57.52 | AI14: 139.6 | AJ14: =SUM(V14:AI14) -> 233.22 | AR14: =SUM(AJ14+S14) -> 1885.56 | AS14: =AR14*AU14 -> 0 | AT14: =C14 -> 42312.33
A15: 44382 | B15: 0.14 | C15: =SUM(C14-AR14+D15) -> 40426.77 | H15: 362.94 | J15: 791.43 | K15: 489.95 | N15: 798 | P15: 1932 | Q15: 1296 | S15: =SUM(F15:L15) -> 1644.32 | T15: =SUM(M15:R15) -> 4026 | U15: =S15/T15 -> 0.40842524 | AE15: 15.61 | AH15: 133 | AJ15: =SUM(V15:AI15) -> 148.61 | AR15: =SUM(AJ15+S15) -> 1792.93 | AS15: =AR15*AU15 -> 0 | AT15: =C15 -> 40426.77
A16: 44383 | B16: 0.169 | C16: =SUM(C15-AR15+D16) -> 38633.84 | G16: 754.35 | K16: 475.77 | L16: 439.11 | M16: 1871 | Q16: 1230 | R16: 1044 | S16: =SUM(F16:L16) -> 1669.23 | T16: =SUM(M16:R16) -> 4145 | U16: =S16/T16 -> 0.40270929 | V16: 15.89 | W16: 26.82 | Z16: 84.64 | AI16: 72.58 | AJ16: =SUM(V16:AI16) -> 199.93 | AR16: =SUM(AJ16+S16) -> 1869.16 | AS16: =AR16*AU16 -> 0 | AT16: =C16 -> 38633.84
A17: 44384 | B17: 0.364 | C17: =SUM(C16-AR16+D17) -> 36764.68 | G17: 407.2 | H17: 170.79 | J17: 232.8 | K17: 454.88 | L17: 633.24 | M17: 1089 | N17: 239 | P17: 535 | Q17: 1214 | R17: 1598 | S17: =SUM(F17:L17) -> 1898.91 | T17: =SUM(M17:R17) -> 4675 | U17: =S17/T17 -> 0.40618396 | W17: 73.95 | AI17: 95 | AJ17: =SUM(V17:AI17) -> 168.95 | AR17: =SUM(AJ17+S17) -> 2067.86 | AS17: =AR17*AU17 -> 0 | AT17: =C17 -> 36764.68
A18: 44385 | B18: 0.455 | C18: =SUM(C17-AR17+D18) -> 34696.82 | G18: 786.04 | H18: 548.84 | L18: 530.91 | M18: 1946 | N18: 1332 | R18: 1272 | S18: =SUM(F18:L18) -> 1865.79 | T18: =SUM(M18:R18) -> 4550 | U18: =S18/T18 -> 0.41006374 | AI18: 47 | AJ18: =SUM(V18:AI18) -> 47 | AR18: =SUM(AJ18+S18) -> 1912.79 | AS18: =AR18*AU18 -> 0 | AT18: =C18 -> 34696.82
A19: 44386 | B19: 0.468 | C19: =SUM(C18-AR18+D19) -> 32784.03 | G19: 408.97 | H19: 462.84 | J19: 198.72 | K19: 224.12 | L19: 512.57 | M19: 954 | N19: 1201 | P19: 462 | Q19: 430 | R19: 1216 | S19: =SUM(F19:L19) -> 1807.22 | T19: =SUM(M19:R19) -> 4263 | U19: =S19/T19 -> 0.4239315 | AH19: 456 | AJ19: =SUM(V19:AI19) -> 456 | AR19: =SUM(AJ19+S19) -> 2263.22 | AS19: =AR19*AU19 -> 0 | AT19: =C19 -> 32784.03
A20: 44387 | B20: 0.39 | C20: =SUM(C19-AR19+D20) -> 30520.81 | G20: 482.3 | H20: 700.31 | L20: 705.27 | M20: 1250 | N20: 1617 | R20: 1639 | S20: =SUM(F20:L20) -> 1887.88 | T20: =SUM(M20:R20) -> 4506 | U20: =S20/T20 -> 0.41897026 | V20: 53.69 | W20: 48.64 | AF20: 149.64 | AI20: 393 | AJ20: =SUM(V20:AI20) -> 644.97 | AR20: =SUM(AJ20+S20) -> 2532.85 | AS20: =AR20*AU20 -> 0 | AT20: =C20 -> 30520.81
A21: 44388 | B21: 0.403 | C21: =SUM(C20-AR20+D21) -> 45987.96 | D21: 18000 | H21: 749.94 | K21: 704.16 | L21: 398.5 | N21: 1772 | Q21: 1686 | R21: 1001 | S21: =SUM(F21:L21) -> 1852.6 | T21: =SUM(M21:R21) -> 4459 | U21: =S21/T21 -> 0.41547432 | Y21: 76.48 | AA21: 64.22 | AC21: 45.92 | AH21: 261 | AI21: 161 | AJ21: =SUM(V21:AI21) -> 608.62 | AR21: =SUM(AJ21+S21) -> 2461.22 | AS21: =AR21*AU21 -> 0 | AT21: =C21 -> 45987.96
A22: 44389 | B22: 0.39 | C22: =SUM(C21-AR21+D22) -> 43526.74 | G22: 736.75 | K22: 492.54 | L22: 432.88 | M22: 1787 | Q22: 1567 | R22: 1084 | S22: =SUM(F22:L22) -> 1662.17 | T22: =SUM(M22:R22) -> 4438 | U22: =S22/T22 -> 0.37453132 | AG22: 220.99 | AH22: 345 | AI22: 112 | AJ22: =SUM(V22:AI22) -> 677.99 | AR22: =SUM(AJ22+S22) -> 2340.16 | AS22: =AR22*AU22 -> 0 | AT22: =C22 -> 43526.74
A23: 44390 | B23: 0.221 | C23: =SUM(C22-AR22+D23) -> 41186.58 | G23: 509.86 | K23: 661.38 | L23: 673.67 | M23: 1787 | Q23: 1267 | R23: 1246 | S23: =SUM(F23:L23) -> 1844.91 | T23: =SUM(M23:R23) -> 4300 | U23: =S23/T23 -> 0.42904884 | W23: 44.11 | AA23: 27.02 | AH23: 133 | AJ23: =SUM(V23:AI23) -> 204.13 | AR23: =SUM(AJ23+S23) -> 2049.04 | AS23: =AR23*AU23 -> 0 | AT23: =C23 -> 41186.58
A24: 44391 | B24: 0.195 | C24: =SUM(C23-AR23+D24) -> 39137.54 | E24: 18000 | F24: RAHA | G24: 653.44 | H24: 597.33 | K24: 399.4 | M24: 1481 | N24: 1415 | Q24: 1006 | S24: =SUM(F24:L24) -> 1650.17 | T24: =SUM(M24:R24) -> 3902 | U24: =S24/T24 -> 0.42290364 | AA24: 56.84 | AG24: 1000 | AH24: 201 | AI24: 177 | AJ24: =SUM(V24:AI24) -> 1434.84 | AR24: =SUM(AJ24+S24) -> 3085.01 | AS24: =AR24*AU24 -> 0 | AT24: =C24 -> 39137.54
A25: 44392 | B25: 0.208 | C25: =SUM(C24-AR24+D25) -> 36052.53 | G25: 470.18 | H25: 586.49 | L25: 586.59 | M25: 1145 | N25: 1366 | Q25: 1322 | S25: =SUM(F25:L25) -> 1643.26 | T25: =SUM(M25:R25) -> 3833 | U25: =S25/T25 -> 0.4287138 | AA25: 17.98 | AH25: 138 | AJ25: =SUM(V25:AI25) -> 155.98 | AR25: =SUM(AJ25+S25) -> 1799.24 | AS25: =AR25*AU25 -> 0 | AT25: =C25 -> 36052.53
A26: 44393 | B26: 0.27 | C26: =SUM(C25-AR25+D26) -> 34253.29 | H26: 650.18 | K26: 432.57 | L26: 649.99 | N26: 1534 | Q26: 1052 | R26: 1494 | S26: =SUM(F26:L26) -> 1732.74 | T26: =SUM(M26:R26) -> 4080 | U26: =S26/T26 -> 0.42469118 | W26: 85.68 | AJ26: =SUM(V26:AI26) -> 85.68 | AR26: =SUM(AJ26+S26) -> 1818.42 | AS26: =AR26*AU26 -> 0 | AT26: =C26 -> 34253.29
A27: 44394 | B27: 0.26 | C27: =SUM(C26-AR26+D27) -> 32434.87 | G27: 708.73 | K27: 420.6 | L27: 637.31 | M27: 1568 | Q27: 1043 | R27: 1481 | S27: =SUM(F27:L27) -> 1766.64 | T27: =SUM(M27:R27) -> 4092 | U27: =S27/T27 -> 0.43173021 | V27: 55.38 | AI27: 441 | AJ27: =SUM(V27:AI27) -> 496.38 | AR27: =SUM(AJ27+S27) -> 2263.02 | AS27: =AR27*AU27 -> 0 | AT27: =C27 -> 32434.87
A28: 44395 | B28: 0.35 | C28: =SUM(C27-AR27+D28) -> 30171.85 | G28: 638.42 | H28: 447.01 | L28: 702.55 | M28: 1618 | N28: 1177 | R28: 1655 | S28: =SUM(F28:L28) -> 1787.98 | T28: =SUM(M28:R28) -> 4450 | U28: =S28/T28 -> 0.40179326 | AB28: 28.07 | AE28: 251.16 | AH28: 95 | AJ28: =SUM(V28:AI28) -> 374.23 | AR28: =SUM(AJ28+S28) -> 2162.21 | AS28: =AR28*AU28 -> 0 | AT28: =C28 -> 30171.85
A29: 44396 | B29: 0.39 | C29: =SUM(C28-AR28+D29) -> 28009.64 | H29: 722.84 | K29: 715.97 | L29: 373.58 | N29: 1875 | Q29: 1788 | R29: 970 | S29: =SUM(F29:L29) -> 1812.39 | T29: =SUM(M29:R29) -> 4633 | U29: =S29/T29 -> 0.39119145 | AH29: 99 | AI29: 125 | AJ29: =SUM(V29:AI29) -> 224 | AR29: =SUM(AJ29+S29) -> 2036.39 | AS29: =AR29*AU29 -> 0 | AT29: =C29 -> 28009.64
A30: 44397 | B30: 0.39 | C30: =SUM(C29-AR29+D30) -> 25973.25 | G30: 728.6 | K30: 792.32 | L30: 486.72 | M30: 1817 | Q30: 1646 | R30: 1259 | S30: =SUM(F30:L30) -> 2007.64 | T30: =SUM(M30:R30) -> 4722 | U30: =S30/T30 -> 0.4251673 | AC30: 49.26 | AJ30: =SUM(V30:AI30) -> 49.26 | AR30: =SUM(AJ30+S30) -> 2056.9 | AS30: =AR30*AU30 -> 0 | AT30: =C30 -> 25973.25
A31: 44398 | B31: 0.55 | C31: =SUM(C30-AR30+D31) -> 23916.35 | G31: 831.04 | K31: 611.04 | L31: 550.7 | M31: 1817 | Q31: 1519 | R31: 1575 | S31: =SUM(F31:L31) -> 1992.78 | T31: =SUM(M31:R31) -> 4911 | U31: =S31/T31 -> 0.40577886 | V31: 128.39 | W31: 33 | AH31: 205 | AI31: 190 | AJ31: =SUM(V31:AI31) -> 556.39 | AR31: =SUM(AJ31+S31) -> 2549.17 | AS31: =AR31*AU31 -> 0 | AT31: =C31 -> 23916.35
A32: 44399 | B32: 0.545 | C32: =SUM(C31-AR31+D32) -> 21367.18 | G32: 1044.18 | K32: 277.8 | L32: 910.91 | M32: 2672 | Q32: 640 | R32: 1914 | S32: =SUM(F32:L32) -> 2232.89 | T32: =SUM(M32:R32) -> 5226 | U32: =S32/T32 -> 0.4272656 | W32: 49.65 | AA32: 33.04 | AD32: 206.96 | AI32: 205 | AJ32: =SUM(V32:AI32) -> 494.65 | AR32: =SUM(AJ32+S32) -> 2727.54 | AS32: =AR32*AU32 -> 0 | AT32: =C32 -> 21367.18
A33: 44400 | B33: 0.455 | C33: =SUM(C32-AR32+D33) -> 18639.64 | H33: 868.66 | K33: 721.5 | L33: 500.63 | N33: 1793 | Q33: 1709 | R33: 1228 | S33: =SUM(F33:L33) -> 2090.79 | T33: =SUM(M33:R33) -> 4730 | U33: =S33/T33 -> 0.44202748 | AE33: 228.3 | AJ33: =SUM(V33:AI33) -> 228.3 | AR33: =SUM(AJ33+S33) -> 2319.09 | AS33: =AR33*AU33 -> 0 | AT33: =C33 -> 18639.64
A34: 44401 | B34: 0.247 | C34: =SUM(C33-AR33+D34) -> 16320.55 | E34: 15000 | F34: RAHA | G34: 845.13 | K34: 724.39 | L34: 445.21 | M34: 1925 | Q34: 1792 | R34: 1162 | S34: =SUM(F34:L34) -> 2014.73 | T34: =SUM(M34:R34) -> 4879 | U34: =S34/T34 -> 0.41293913 | V34: 55.53 | W34: 29.45 | AH34: 227 | AI34: 131 | AJ34: =SUM(V34:AI34) -> 442.98 | AR34: =SUM(AJ34+S34) -> 2457.71 | AS34: =AR34*AU34 -> 0 | AT34: =C34 -> 16320.55
A35: 44402 | B35: 0.208 | C35: =SUM(C34-AR34+D35) -> 28862.84 | D35: 15000 | G35: 692.84 | H35: 706.76 | K35: 469.49 | M35: 1785 | N35: 1718 | Q35: 1096 | S35: =SUM(F35:L35) -> 1869.09 | T35: =SUM(M35:R35) -> 4599 | U35: =S35/T35 -> 0.40641226 | W35: 26.79 | AH35: 142 | AI35: 91 | AJ35: =SUM(V35:AI35) -> 259.79 | AR35: =SUM(AJ35+S35) -> 2128.88 | AS35: =AR35*AU35 -> 0 | AT35: =C35 -> 28862.84
A36: 44403 | B36: 0.156 | C36: =SUM(C35-AR35+D36) -> 26733.96 | G36: 831.64 | K36: 400.73 | L36: 656.43 | M36: 1710 | Q36: 1038 | R36: 1667 | S36: =SUM(F36:L36) -> 1888.8 | T36: =SUM(M36:R36) -> 4415 | U36: =S36/T36 -> 0.42781427 | AA36: 12.76 | AB36: 58.16 | AJ36: =SUM(V36:AI36) -> 70.92 | AR36: =SUM(AJ36+S36) -> 1959.72 | AS36: =AR36*AU36 -> 0 | AT36: =C36 -> 26733.96
A37: 44404 | B37: 0.299 | C37: =SUM(C36-AR36+D37) -> 24774.24 | E37: 18000 | F37: RAHA | H37: 698.88 | K37: 448.66 | L37: 773.75 | N37: 1728 | Q37: 1139 | R37: 1740 | S37: =SUM(F37:L37) -> 1921.29 | T37: =SUM(M37:R37) -> 4607 | U37: =S37/T37 -> 0.41703712 | V37: 62.69 | W37: 16.19 | Y37: 71.61 | AA37: 54.4 | AH37: 247 | AI37: 40 | AJ37: =SUM(V37:AI37) -> 491.89 | AR37: =SUM(AJ37+S37) -> 2413.18 | AS37: =AR37*AU37 -> 0 | AT37: =C37 -> 24774.24
A38: 44405 | B38: 0.468 | C38: =SUM(C37-AR37+D38) -> 37361.06 | D38: 15000 | G38: 682.69 | K38: 490.45 | L38: 523.48 | M38: 1715 | Q38: 1267 | R38: 1660 | S38: =SUM(F38:L38) -> 1696.62 | T38: =SUM(M38:R38) -> 4642 | U38: =S38/T38 -> 0.36549332 | W38: 72.92 | X38: 74.55 | AJ38: =SUM(V38:AI38) -> 147.47 | AR38: =SUM(AJ38+S38) -> 1844.09 | AS38: =AR38*AU38 -> 0 | AT38: =C38 -> 37361.06
A39: 44406 | B39: 0.51 | C39: =SUM(C38-AR38+D39) -> 35516.97 | G39: 721.85 | K39: 476.87 | L39: 793.34 | M39: 1104 | Q39: 1209 | R39: 1672 | S39: =SUM(F39:L39) -> 1992.06 | T39: =SUM(M39:R39) -> 3985 | U39: =S39/T39 -> 0.49988959 | X39: 10.33 | Z39: 69.62 | AH39: 97 | AI39: 70 | AJ39: =SUM(V39:AI39) -> 246.95 | AR39: =SUM(AJ39+S39) -> 2239.01 | AS39: =AR39*AU39 -> 0 | AT39: =C39 -> 35516.97
A40: 44407 | B40: 0.38 | C40: =SUM(C39-AR39+D40) -> 33277.96 | G40: 698.52 | K40: 420.79 | L40: 703.26 | M40: 1753 | Q40: 1068 | R40: 1663 | S40: =SUM(F40:L40) -> 1822.57 | T40: =SUM(M40:R40) -> 4484 | U40: =S40/T40 -> 0.40646075 | AH40: 369 | AJ40: =SUM(V40:AI40) -> 369 | AR40: =SUM(AJ40+S40) -> 2191.57 | AS40: =AR40*AU40 -> 0 | AT40: =C40 -> 33277.96
A41: 44408 | B41: 0.15 | C41: =SUM(C40-AR40+D41) -> 31086.39 | G41: 572.96 | K41: 497.34 | L41: 609.72 | M41: 1248 | Q41: 1268 | R41: 1499 | S41: =SUM(F41:L41) -> 1680.02 | T41: =SUM(M41:R41) -> 4015 | U41: =S41/T41 -> 0.41843587 | X41: 27.24 | AH41: 349 | AJ41: =SUM(V41:AI41) -> 376.24 | AR41: =SUM(AJ41+S41) -> 2056.26 | AS41: =AR41*AU41 -> 0 | AT41: =C41 -> 31086.39
C42: =SUM(C41-AR41+D42) -> 29030.13 | S42: =SUM(F42:L42) -> 0 | T42: =SUM(M42:R42) -> 0 | AJ42: =SUM(V42:AI42) -> 0 | AR42: =SUM(AJ42+S42) -> 0 | AS42: =AR42*AU42 -> 0 | AT42: =C42 -> 29030.13
A43: BF | B43: =AVERAGE(B11:B42) -> 0.3265129 | C43: =SUM(C42-AR42+D43) -> 29030.13 | S43: =SUM(F43:L43) -> 0 | T43: =SUM(M43:R43) -> 0 | AJ43: =SUM(V43:AI43) -> 0 | AR43: =SUM(AJ43+S43) -> 0 | AS43: =AR43*AU43 -> 0 | AT43: =C43 -> 29030.13
S44: =SUM(F44:L44) -> 0 | T44: =SUM(M44:R44) -> 0 | AJ44: =SUM(V44:AI44) -> 0 | AR44: =SUM(AJ44+S44) -> 0 | AS44: =AR44*AU44 -> 0
D45: =SUM(D11:D44) -> 66000 | E45: =SUM(E11:E42) -> 69000 | F45: =SUM(F11:F44) -> 0 | G45: =SUM(G11:G44) -> 16395.69 | H45: =SUM(H11:H44) -> 8273.81 | I45: =SUM(I11:I44) -> 0 | J45: =SUM(J11:J44) -> 2008.11 | K45: =SUM(K11:K44) -> 13716.26 | L45: =SUM(L11:L44) -> 16295.96 | M45: =SUM(M11:M44) -> 39205 | ... O45: =SUM(O11:O44) -> 0 | P45: =SUM(P11:P43) -> 4641 | Q45: =SUM(Q11:Q44) -> 35047 | R45: =SUM(R11:R44) -> 38220 | S45: =SUM(G45:L45) -> 56689.83 | T45: =SUM(M45:R45) -> 136678 | U45: =SUM(U11:U42) -> 12.870714 | V45: =SUM(V9:V44) -> 480.51 | W45: =SUM(W9:W44) -> 507.2 | X45: =SUM(X9:X44) -> 112.12 | Y45: =SUM(Y9:Y44) -> 148.09 | Z45: =SUM(Z9:Z44) -> 279.19 | AA45: =SUM(AA9:AA44) -> 323.78 | AB45: =SUM(AB9:AB44) -> 86.23 | AC45: =SUM(AC10:AC44) -> 95.18 | AD45: =SUM(AD10:AD44) -> 206.96 | AE45: =SUM(AE9:AE44) -> 495.07 | AF45: =SUM(AF9:AF44) -> 149.64 | AG45: =SUM(AG9:AG44) -> 1220.99 | AH45: =SUM(AH9:AH43) -> 3584.04 | AI45: =SUM(AI9:AI39) -> 2530.18 | AJ45: =SUM(AJ9:AJ44) -> 10219.18 | AR45: =SUM(AJ45+S45) -> 66909.01 | AS45: =SUM(AS11:AS44) -> 0
A46: Nb Day
S47: =AVERAGE(S11:S41) -> 1828.7042 | T47: =S45*2315 -> 1.3123696e+08 | U47: TZS | AR47: =AR45*2143 -> 1.4338601e+08 | AS47: TZS
A48: Av. Occ | T48: =T47/2289 -> 57333.751 | U48: USD | AR48: =AR47/2289 -> 62641.332 | AS48: USD
B50: A & K VEHICLES | H50: MAULY VEHICLES | N50: GREEN LAND VEHICLES | T50: OTHERS VEHICLES
B51: Date | C51: Vehicles | D51: Liters | E51: Driver name | F51: Authority manager | H51: Date | I51: Vehicles | J51: Liters | K51: Driver name | L51: Authority manager | N51: Date | O51: Vehicles | P51: Liters | Q51: Driver name | R51: Authorized Manager | T51: Date | U51: Vehicles | V51: Liters | W51: Driver name | X51: Athorized Manager | Y51: Reasons
B52: 44234 | C52: T178DKT | D52: 60 | E52: Elihakim | F52: Noel | N52: 44293 | O52: T165DKR | P52: 66 | Q52: Chande | R52: Noel | T52: 44379 | U52: STLB734 | V52: 40 | W52: Kwera | X52: Kwella/Vedastus
B53: 44234 | C53: T882DKQ | D53: 27 | E53: Donard | F53: Noel | N53: 44293 | O53: T394DLP | P53: 73 | Q53: David | R53: Noel | T53: 44476 | U53: UTO124 | V53: 20 | W53: Mwegeta | X53: Vedastus/Shamim
B54: 44323 | C54: T106CWQ | D54: 133 | E54: Andason | F54: Noel | N54: 44354 | O54: T635CAV | P54: 72.58 | Q54: Jilius | R54: Noel | T54: 27/7/2021 | U54: PT1862 | V54: 40 | W54: Kwera | X54: Vedastus/Kwella
B55: 9/72021 | C55: T132CWQ | D55: 136 | E55: Nuru | F55: Noel | N55: 44384 | O55: T165DKR | P55: 95 | Q55: Chande | R55: Noel
B56: 44447 | C56: T111CWQ | D56: 132 | E56: Dominic | F56: Noel | N56: 44415 | O56: T594DLP | P56: 47 | Q56: David | R56: Noel
B57: 44447 | C57: T880DKQ | D57: 122 | E57: Priscus | F57: Noel | N57: 44476 | O57: T728CXC | P57: 138 | Q57: Jackson | R57: Noel
B58: 44447 | C58: T840DDW | D58: 66 | E58: Herman | F58: Noel | N58: 44476 | O58: T559DLW | P58: 155 | Q58: Elifraha | R58: Noel
B59: 44508 | C59: T364AHF | D59: 56 | E59: Gurisha | F59: Noel | N59: 44476 | O59: T165DKR | P59: 80 | Q59: Chande | R59: Noel
B60: 44508 | C60: T391DQR | D60: 111 | E60: Kessy | F60: Noel | N60: 44507 | O60: T594DLP | P60: 90 | Q60: David | R60: Noel
B61: 44508 | C61: T106CWQ | D61: 94 | E61: Elihakim | F61: Noel | N61: 44507 | O61: T635CAV | P61: 71 | Q61: JULIUS | R61: Noel
B62: 44538 | C62: T882DKQ | D62: 136 | E62: Godlisen | F62: NOel | N62: 44537 | O62: T755CJQ | P62: 112 | Q62: KARUME | R62: Noel
B63: 44538 | C63: T880DKQ | D63: 144 | E63: Priscus | F63: Noel | N63: 14/7/2021 | O63: 165DKR | P63: 103 | Q63: CHANDE | R63: Noel
B64: 44538 | C64: T106CWQ | D64: 65 | E64: Elihakim | F64: Noel | N64: 14/7/2021 | O64: T594DLP | P64: 74 | Q64: DAVID | R64: Huruma
B65: 13/7/2021 | C65: T882DKQ | D65: 13 | E65: Godlisen | F65: Noel | N65: 17/7/2021 | O65: T755CJQ | P65: 99 | Q65: KARUME | R65: Huruma
B66: 13/7/2021 | C66: T111CWQ | D66: 120 | E66: Dominic | F66: Noel | N66: 17/7/2021 | O66: T594DLP | P66: 92 | Q66: DAVID | R66: Huruma
B67: 14/7/2021 | C67: T364AHF | D67: 42 | E67: Hassan | F67: Noel | N67: 17/7/2021 | O67: T559DLW | P67: 126 | Q67: Elifraha | R67: Huruma
B68: 14/7/2021 | C68: T132CWQ | D68: 159 | E68: Nuru | F68: Noel | N68: 17/7/2021 | O68: T635CAV | P68: 80 | Q68: JULIUS | R68: Huruma
B69: 14/7/2021 | C69: T840DDW | D69: 138 | E69: Herman | F69: Huruma | N69: 17/7/2021 | O69: T165DKR | P69: 44 | Q69: Chande | R69: Huruma
B70: 18/7/2021 | C70: T880DKQ | D70: 95 | E70: Priscus | F70: Huruma | N70: 19/7/2021 | O70: T165DKR | P70: 125 | Q70: Chande | R70: Huruma
B71: 19/72021 | C71: T111CWQ | D71: 99 | E71: Dominic | F71: Huruma | N71: 21/7/2021 | O71: T594DLP | P71: 86 | Q71: David | R71: Huruma
B72: 21/7/2021 | C72: T391DQR | D72: 141 | E72: JOSEPH | F72: Huruma | N72: 21/72021 | O72: T755CJQ | P72: 104 | Q72: KARUME | R72: Huruma
B73: 21/7/2021 | C73: T880DKQ | D73: 64 | E73: Priscus | F73: Huruma | N73: 22/72021 | O73: T635CAV | P73: 72 | Q73: JULIUS | R73: Huruma
B74: 24/7/2021 | C74: T111CWQ | D74: 119 | E74: Dominic | F74: Huruma | N74: 22/7/2021 | O74: T559DLW | P74: 133 | Q74: Elifraha | R74: Huruma
B75: 24/7/2021 | C75: T132CWQ | D75: 108 | E75: Nuru | F75: Huruma | N75: 24/7/2021 | O75: T594DLP | P75: 31 | Q75: David | R75: Huruma
B76: 25/7/2021 | C76: T880DKQ | D76: 142 | E76: Priscus | F76: Huruma | N76: 24/7/2021 | O76: T728CXC | P76: 100 | Q76: Jackson | R76: Huruma
F77: Huruma | R77: Huruma
B78: 27/7/2021 | C78: T391DQR | D78: 135 | E78: JOSEPH | F78: Huruma | N78: 25/7/2021 | O78: T635CAV | P78: 91 | Q78: Jilius | R78: Huruma
B79: 27/7/2021 | C79: T882DKQ | D79: 112 | E79: Herman | F79: Huruma | N79: 29/7/2021 | O79: T755CJQ | P79: 70 | Q79: Karume | R79: Huruma
B80: 29/7/2021 | C80: T132CWQ | D80: 97 | E80: Nuru | F80: Huruma
B81: 30/7/2021 | C81: T106CWQ | D81: 46 | E81: Priscus | F81: Huruma
B82: 30/7/2021 | C82: T840DDW | D82: 103 | E82: Herman | F82: Huruma
B83: 30/7/2021 | C83: T880DKQ | D83: 117 | E83: Priscus | F83: Huruma
B84: 30/7/2021 | C84: T111CWQ | D84: 60 | E84: Dominic | F84: Huruma
B85: 30/7/2021 | C85: T364AHF | D85: 43 | E85: Dominic | F85: Huruma
B86: 31/7/2021 | C86: T191DQR | D86: 90 | E86: JOSEPH | F86: Huruma
B87: 31/7/2021 | C87: T882DKQ | D87: 62 | E87: Herman | F87: Huruma
B88: 31/7/2021 | C88: T132CWQ | D88: 31 | E88: Walfgan | F88: Huruma
B89: 31/7/2021 | C89: T364AHF | D89: 11 | E89: Emanuel | F89: Huruma
B90: 31/7/2021 | C90: T106CWQ | D90: 12 | E90: Lucas | F90: Huruma
B91: 31/7/2021 | C91: T675ANT | D91: 143 | E91: Fadhili | F91: Huruma

Sheet Lpg (2)
C3: Four Sasons Safari Lodge Serengeti
G6: VALUE | H6: Cost
A7: DATE | B7: A | C7: B | D7: C | F7: Meter Reading | G7: Total | H7: Occu | I7: No.of | J7: Kg
B8: 2Ton% | C8: 1Ton (%) | D8: 1Ton% | F8: consumption | G8: Consumption Kg | H8: % | I8: pax | J8: per pax
B9: 85 | C9: 41 | D9: 85 | E9: 77500 | F9: 77500
A10: =Gen!A11 -> 44378 | B10: 85 | C10: 37 | D10: 85 | E10: 77529.7 | F10: 77529.7 | G10: =(F10-F9)*4.4 -> 130.68 | H10: =Gen!B11 -> 0.3 | I10: =SUM(F10/H10) -> 258432.33 | J10: =SUM(G10/I10) -> 0.00050566428
A11: =Gen!A12 -> 44379 | B11: 85 | C11: 35 | D11: 85 | E11: 77529.7 | F11: 77558 | G11: =(F11-F10)*4.4 -> 124.52 | H11: =Gen!B12 -> 0.35 | I11: =SUM(F11/H11) -> 221594.29 | J11: =SUM(G11/I11) -> 0.00056192785
A12: =Gen!A13 -> 44380 | B12: 85 | C12: 30 | D12: 85 | F12: 77568 | G12: =(F12-F11)*4.4 -> 44 | H12: =Gen!B13 -> 0.2609 | I12: =SUM(F12/H12) -> 297309.31 | J12: =SUM(G12/I12) -> 0.00014799402
A13: =Gen!A14 -> 44381 | B13: 85 | C13: 20 | D13: 85 | F13: 77588.31 | G13: =(F13-F12)*4.4 -> 89.364 | H13: =Gen!B14 -> 0.18 | I13: =SUM(F13/H13) -> 431046.17 | J13: =SUM(G13/I13) -> 0.00020731886
A14: =Gen!A15 -> 44382 | B14: 85 | C14: 15 | D14: 85 | F14: 77613.86 | G14: =(F14-F13)*4.4 -> 112.42 | H14: =Gen!B15 -> 0.14 | I14: =SUM(F14/H14) -> 554384.71 | J14: =SUM(G14/I14) -> 0.00020278337
A15: =Gen!A16 -> 44383 | B15: 85 | C15: 10 | D15: 85 | F15: 77640.4 | G15: =(F15-F14)*4.4 -> 116.776 | H15: =Gen!B16 -> 0.169 | I15: =SUM(F15/H15) -> 459410.65 | J15: =SUM(G15/I15) -> 0.00025418653
A16: =Gen!A17 -> 44384 | B16: 85 | C16: 4 | D16: 85 | F16: 77665.02 | G16: =(F16-F15)*4.4 -> 108.328 | H16: =Gen!B17 -> 0.364 | I16: =SUM(F16/H16) -> 213365.44 | J16: =SUM(G16/I16) -> 0.00050771109
A17: =Gen!A18 -> 44385 | B17: 85 | C17: 3 | D17: 85 | F17: 77690.56 | G17: =(F17-F16)*4.4 -> 112.376 | H17: =Gen!B18 -> 0.455 | I17: =SUM(F17/H17) -> 170748.48 | J17: =SUM(G17/I17) -> 0.00065813762
A18: =Gen!A19 -> 44386 | B18: 85 | C18: 2 | D18: 85 | F18: 77714.06 | G18: =(F18-F17)*4.4 -> 103.4 | H18: =Gen!B19 -> 0.468 | I18: =SUM(F18/H18) -> 166055.68 | J18: =SUM(G18/I18) -> 0.00062268269
A19: =Gen!A20 -> 44387 | B19: 85 | C19: 1 | D19: 85 | F19: 77740.72 | G19: =(F19-F18)*4.4 -> 117.304 | H19: =Gen!B20 -> 0.39 | I19: =SUM(F19/H19) -> 199335.18 | J19: =SUM(G19/I19) -> 0.00058847616
A20: =Gen!A21 -> 44388 | B20: 85 | C20: 0 | D20: 85 | F20: 77767.01 | G20: =(F20-F19)*4.4 -> 115.676 | H20: =Gen!B21 -> 0.403 | I20: =SUM(F20/H20) -> 192970.25 | J20: =SUM(G20/I20) -> 0.00059944992
A21: =Gen!A22 -> 44389 | B21: 85 | C21: 0 | D21: 80 | F21: 77795.87 | G21: =(F21-F20)*4.4 -> 126.984 | H21: =Gen!B22 -> 0.39 | I21: =SUM(F21/H21) -> 199476.59 | J21: =SUM(G21/I21) -> 0.00063658598
A22: =Gen!A23 -> 44390 | B22: 85 | C22: 0 | D22: 76 | F22: 77822.66 | G22: =(F22-F21)*4.4 -> 117.876 | H22: =Gen!B23 -> 0.221 | I22: =SUM(F22/H22) -> 352138.73 | J22: =SUM(G22/I22) -> 0.00033474307
A23: =Gen!A24 -> 44391 | B23: 85 | C23: 0 | D23: 70 | F23: 77851.7 | G23: =(F23-F22)*4.4 -> 127.776 | H23: =Gen!B24 -> 0.195 | I23: =SUM(F23/H23) -> 399239.49 | J23: =SUM(G23/I23) -> 0.0003200485
... A40: =Gen!A41 -> 44408 | B40: 76 | C40: 0 | D40: 0 | F40: 78289.45 | G40: =(F40-F39)*4.4 -> 111.232 | H40: =Gen!B41 -> 0.15 | I40: =SUM(F40/H40) -> 521929.67 | J40: =SUM(G40/I40) -> 0.00021311684
G41: =(F41-F40)*4.4 -> -344473.58 | H41: =Gen!B42 -> 0 | I41: =SUM(F41/H41) -> #DIV/0!
C42: TOTAL USAGE | E42: =SUM(E10:E40) -> 155059.4 | F42: =SUM(F10:F41) -> 2414957.3 | G42: =SUM(G10:G40) -> 3473.58 | H42: =Gen!B43 -> 0.3265129 | I42: =SUM(F42/H42) -> 7396207.9
B56: GAS TANK A | D56: GAS TANK B | G56: GAS TANK C

Sheet LPG_Graph
A1: Date | B1: Usage KG | C1: Occ %
A2: =Gen!A11 -> 44378 | B2: ='Lpg (2)'!G10 -> 130.68 | C2: =Gen!B11 -> 0.3
A3: =Gen!A12 -> 44379 | B3: ='Lpg (2)'!G11 -> 124.52 | C3: =Gen!B12 -> 0.35
A4: =Gen!A13 -> 44380 | B4: ='Lpg (2)'!G12 -> 44 | C4: =Gen!B13 -> 0.2609
A5: =Gen!A14 -> 44381 | B5: ='Lpg (2)'!G13 -> 89.364 | C5: =Gen!B14 -> 0.18
A6: =Gen!A15 -> 44382 | B6: ='Lpg (2)'!G14 -> 112.42 | C6: =Gen!B15 -> 0.14
A7: =Gen!A16 -> 44383 | B7: ='Lpg (2)'!G15 -> 116.776 | C7: =Gen!B16 -> 0.169
A8: =Gen!A17 -> 44384 | B8: ='Lpg (2)'!G16 -> 108.328 | C8: =Gen!B17 -> 0.364
A9: =Gen!A18 -> 44385 | B9: ='Lpg (2)'!G17 -> 112.376 | C9: =Gen!B18 -> 0.455
A10: =Gen!A19 -> 44386 | B10: ='Lpg (2)'!G18 -> 103.4 | C10: =Gen!B19 -> 0.468
A11: =Gen!A20 -> 44387 | B11: ='Lpg (2)'!G19 -> 117.304 | C11: =Gen!B20 -> 0.39
A12: =Gen!A21 -> 44388 | B12: ='Lpg (2)'!G20 -> 115.676 | C12: =Gen!B21 -> 0.403
A13: =Gen!A22 -> 44389 | B13: ='Lpg (2)'!G21 -> 126.984 | C13: =Gen!B22 -> 0.39
... A32: =Gen!A41 -> 44408 | B32: ='Lpg (2)'!G40 -> 111.232 | C32: =Gen!B41 -> 0.15

Sheet Water-Meter
A1: Four Seasons Safari Lodge Serengeti - Water Report
C2: Main Meter | F2: KITCHEN | I2: Amani café | L2: Main SW POOL | O2: Laundry | S2: BORE HOLE NO.1 METER READING | V2: BORE HOLE NO.2 METER READING | Y2: BORE HOLE NO.3 METER READING | AB2: BORE HOLE NO.4 METER READING | AE2: BORE HOLE NO.5 METER READING | AH2: BORE HOLE NO.6 METER READING | AK2: RAIN WATER - METER READING | AN2: TOTAL WATER PRODUCTION
A3: DATE | C3: Open Bal | D3: Final | E3: consumption | F3: Open Bal | G3: Final | H3: consumption | I3: Open Bal | J3: Final | K3: consumption | L3: Open Bal | M3: Final | N3: consumption | O3: Open Bal | P3: Final | Q3: consumption | R3: Total consumption
S4: OPEN | T4: FINAL | U4: PROD. | V4: OPEN | W4: FINAL | X4: PROD. | Y4: OPEN | Z4: FINAL | AA4: PROD. | AB4: OPEN | AC4: FINAL | AD4: M3 | AE4: OPEN | AF4: FINAL | AG4: M3 | AH4: OPEN | AI4: FINAL | AJ4: M3 | AK4: OPEN | AL4: FINAL | AM4: M3
C5: =D4 -> 0 | D5: 259247 | E5: =IF((D5-D4)<0,"0",(D5-D4)) -> 259247 | F5: =G4 -> 0 | H5: 0 | I5: =J4 -> 0 | J5: 8522 | K5: =J5-J4 -> 8522 | L5: =M4 -> 0 | N5: 0 | O5: =P4 -> 0 | P5: 21541 | Q5: =IF((P5-P4)<0,"0",(P5-P4)) -> 21541 | T5: 71758 | V5: =W4 -> FINAL | W5: 73031 | X5: 0 | Y5: =Z4 -> FINAL | Z5: 91012 | AA5: 0 | AB5: =AC4 -> FINAL | AC5: 20259 | AE5: =AF4 -> FINAL | AF5: 8305 | AG5: 0 | AH5: =AI4 -> FINAL | AI5: 33029 | AK5: =AL4 -> FINAL
A6: =Gen!A11 -> 44378 | C6: =D5 -> 259247 | D6: 259356 | E6: =IF((D6-D5)<0,"0",(D6-D5)) -> 109 | F6: =G5 -> 0 | H6: =IF((G6-G5)<0,"0",(G6-G5)) -> 0 | I6: =J5 -> 8522 | J6: 8524 | K6: =J6-J5 -> 2 | L6: =M5 -> 0 | N6: =IF((M6-M5)<0,"0",(M6-M5)) -> 0 | O6: =P5 -> 21541 | P6: 21544 | Q6: =IF((P6-P5)<0,"0",(P6-P5)) -> 3 | R6: =Q6+N6+K6+H6 -> 5 | S6: =T5 -> 71758 | T6: 71806 | U6: =IF((T6-T5)<0,"0",(T6-T5)) -> 48 | V6: =W5 -> 73031 | W6: 73031 | X6: =IF((W6-W5)<0,"0",(W6-W5)) -> 0 | Y6: =Z5 -> 91012 | Z6: 91047 | AA6: =IF((Z6-Z5)<0,"0",(Z6-Z5)) -> 35 | AB6: =AC5 -> 20259 | AC6: 20275 | AD6: =IF((AC6-AC5)<0,"0",(AC6-AC5)) -> 16 | AE6: =AF5 -> 8305 | AF6: 8305 | AG6: =IF((AF6-AF5)<0,"0",(AF6-AF5)) -> 0 | AH6: =AI5 -> 33029 | AI6: 33061 | AJ6: =IF((AI6-AI5)<0,"0",(AI6-AI5)) -> 32 | AK6: =AL5 -> 0 | AM6: =IF((AL6-AL5)<0,"0",(AL6-AL5)) -> 0 | AN6: =U6+X6+AA6+AD6+AG6+AJ6+AM6 -> 131
A7: =Gen!A12 -> 44379 | C7: =D6 -> 259356 | D7: 259457 | E7: =IF((D7-D6)<0,"0",(D7-D6)) -> 101 | F7: =G6 -> 0 | H7: =IF((G7-G6)<0,"0",(G7-G6)) -> 0 | I7: =J6 -> 8524 | J7: 8526 | K7: =J7-J6 -> 2 | L7: =M6 -> 0 | N7: =IF((M7-M6)<0,"0",(M7-M6)) -> 0 | O7: =P6 -> 21544 | P7: 21551 | Q7: =IF((P7-P6)<0,"0",(P7-P6)) -> 7 | S7: =T6 -> 71806 | T7: 71885 | U7: =IF((T7-T6)<0,"0",(T7-T6)) -> 79 | V7: =W6 -> 73031 | W7: 73031 | X7: =IF((W7-W6)<0,"0",(W7-W6)) -> 0 | Y7: =Z6 -> 91047 | Z7: 91080 | AA7: =IF((Z7-Z6)<0,"0",(Z7-Z6)) -> 33 | AB7: =AC6 -> 20275 | AC7: 20290 | AD7: =IF((AC7-AC6)<0,"0",(AC7-AC6)) -> 15 | AE7: =AF6 -> 8305 | AF7: 8305 | AG7: =IF((AF7-AF6)<0,"0",(AF7-AF6)) -> 0 | AH7: =AI6 -> 33061 | AI7: 33090 | AJ7: =IF((AI7-AI6)<0,"0",(AI7-AI6)) -> 29 | AK7: =AL6 -> 0 | AM7: =IF((AL7-AL6)<0,"0",(AL7-AL6)) -> 0 | AN7: =U7+X7+AA7+AD7+AG7+AJ7+AM7 -> 156
A8: =Gen!A13 -> 44380 | C8: =D7 -> 259457 | D8: 259551 | E8: =IF((D8-D7)<0,"0",(D8-D7)) -> 94 | F8: =G7 -> 0 | H8: =IF((G8-G7)<0,"0",(G8-G7)) -> 0 | I8: =J7 -> 8526 | J8: 8529 | K8: =J8-J7 -> 3 | L8: =M7 -> 0 | N8: =IF((M8-M7)<0,"0",(M8-M7)) -> 0 | O8: =P7 -> 21551 | P8: 21559 | Q8: =IF((P8-P7)<0,"0",(P8-P7)) -> 8 | S8: =T7 -> 71885 | T8: 71974 | U8: =IF((T8-T7)<0,"0",(T8-T7)) -> 89 | V8: =W7 -> 73031 | W8: 73031 | X8: =IF((W8-W7)<0,"0",(W8-W7)) -> 0 | Y8: =Z7 -> 91080 | Z8: 91117 | AA8: =IF((Z8-Z7)<0,"0",(Z8-Z7)) -> 37 | AB8: =AC7 -> 20290 | AC8: 20307 | AD8: =IF((AC8-AC7)<0,"0",(AC8-AC7)) -> 17 | AE8: =AF7 -> 8305 | AF8: 8305 | AG8: =IF((AF8-AF7)<0,"0",(AF8-AF7)) -> 0 | AH8: =AI7 -> 33090 | AI8: 33122 | AJ8: =IF((AI8-AI7)<0,"0",(AI8-AI7)) -> 32 | AK8: =AL7 -> 0 | AM8: =IF((AL8-AL7)<0,"0",(AL8-AL7)) -> 0 | AN8: =U8+X8+AA8+AD8+AG8+AJ8+AM8 -> 175
A9: =Gen!A14 -> 44381 | C9: =D8 -> 259551 | D9: 259649 | E9: =IF((D9-D8)<0,"0",(D9-D8)) -> 98 | F9: =G8 -> 0 | H9: =IF((G9-G8)<0,"0",(G9-G8)) -> 0 | I9: =J8 -> 8529 | J9: 8531 | K9: =J9-J8 -> 2 | L9: =M8 -> 0 | N9: =IF((M9-M8)<0,"0",(M9-M8)) -> 0 | O9: =P8 -> 21559 | P9: 21569 | Q9: =IF((P9-P8)<0,"0",(P9-P8)) -> 10 | S9: =T8 -> 71974 | T9: 72054 | U9: =IF((T9-T8)<0,"0",(T9-T8)) -> 80 | V9: =W8 -> 73031 | W9: 73031 | X9: =IF((W9-W8)<0,"0",(W9-W8)) -> 0 | Y9: =Z8 -> 91117 | Z9: 91150 | AA9: =IF((Z9-Z8)<0,"0",(Z9-Z8)) -> 33 | AB9: =AC8 -> 20307 | AC9: 20322 | AD9: =IF((AC9-AC8)<0,"0",(AC9-AC8)) -> 15 | AE9: =AF8 -> 8305 | AF9: 8305 | AG9: =IF((AF9-AF8)<0,"0",(AF9-AF8)) -> 0 | AH9: =AI9 -> 33152 | AI9: 33152 | AJ9: =IF((AI9-AI8)<0,"0",(AI9-AI8)) -> 30 | AK9: =AL8 -> 0 | AM9: =IF((AL9-AL8)<0,"0",(AL9-AL8)) -> 0 | AN9: =U9+X9+AA9+AD9+AG9+AJ9+AM9 -> 158
A10: =Gen!A15 -> 44382 | C10: =D9 -> 259649 | D10: 259784 | E10: =IF((D10-D9)<0,"0",(D10-D9)) -> 135 | F10: =G9 -> 0 | H10: =IF((G10-G9)<0,"0",(G10-G9)) -> 0 | I10: =J9 -> 8531 | J10: 8532 | K10: =J10-J9 -> 1 | L10: =M9 -> 0 | N10: =IF((M10-M9)<0,"0",(M10-M9)) -> 0 | O10: =P9 -> 21569 | P10: 21576 | Q10: =IF((P10-P9)<0,"0",(P10-P9)) -> 7 | S10: =T9 -> 72054 | T10: 72103 | U10: =IF((T10-T9)<0,"0",(T10-T9)) -> 49 | V10: =W9 -> 73031 | W10: 73031 | X10: =IF((W10-W9)<0,"0",(W10-W9)) -> 0 | Y10: =Z9 -> 91150 | Z10: 91184 | AA10: =IF((Z10-Z9)<0,"0",(Z10-Z9)) -> 34 | AB10: =AC9 -> 20322 | AC10: 20339 | AD10: =IF((AC10-AC9)<0,"0",(AC10-AC9)) -> 17 | AE10: =AF9 -> 8305 | AF10: 8305 | AG10: =IF((AF10-AF9)<0,"0",(AF10-AF9)) -> 0 | AH10: =AI9 -> 33152 | AI10: 33183 | AJ10: =IF((AI10-AI9)<0,"0",(AI10-AI9)) -> 31 | AK10: =AL9 -> 0 | AM10: =IF((AL10-AL9)<0,"0",(AL10-AL9)) -> 0 | AN10: =U10+X10+AA10+AD10+AG10+AJ10+AM10 -> 131
A11: =Gen!A16 -> 44383 | C11: =D10 -> 259784 | D11: 259908 | E11: =IF((D11-D10)<0,"0",(D11-D10)) -> 124 | F11: =G10 -> 0 | H11: =IF((G11-G10)<0,"0",(G11-G10)) -> 0 | I11: =J10 -> 8532 | J11: 8534 | K11: =J11-J10 -> 2 | L11: =M10 -> 0 | N11: =IF((M11-M10)<0,"0",(M11-M10)) -> 0 | O11: =P10 -> 21576 | P11: 21586 | Q11: =IF((P11-P10)<0,"0",(P11-P10)) -> 10 | S11: =T10 -> 72103 | T11: 72103 | U11: =IF((T11-T10)<0,"0",(T11-T10)) -> 0 | V11: =W10 -> 73031 | W11: 73031 | X11: =IF((W12-W10)<0,"0",(W12-W10)) -> 0 | Y11: =Z10 -> 91184 | Z11: 91219 | AA11: =IF((Z11-Z10)<0,"0",(Z11-Z10)) -> 35 | AB11: =AC10 -> 20339 | AC11: 20355 | AD11: =IF((AC11-AC10)<0,"0",(AC11-AC10)) -> 16 | AE11: =AF11 -> 8305 | AF11: 8305 | AG11: =IF((AF11-AF10)<0,"0",(AF11-AF10)) -> 0 | AH11: =AI10 -> 33183 | AI11: 33214 | AJ11: =IF((AI11-AI10)<0,"0",(AI11-AI10)) -> 31 | AK11: =AL10 -> 0 | AM11: =IF((AL11-AL10)<0,"0",(AL11-AL10)) -> 0 | AN11: =U11+X11+AA11+AD11+AG11+AJ11+AM11 -> 82
A12: =Gen!A17 -> 44384 | C12: =D11 -> 259908 | D12: 260022 | E12: =IF((D12-D11)<0,"0",(D12-D11)) -> 114 | F12: =G11 -> 0 | H12: =IF((G12-G11)<0,"0",(G12-G11)) -> 0 | I12: =J11 -> 8534 | J12: 8536 | K12: =J12-J11 -> 2 | L12: =M11 -> 0 | N12: =IF((M12-M11)<0,"0",(M12-M11)) -> 0 | O12: =P11 -> 21586 | P12: 21597 | Q12: =IF((P12-P11)<0,"0",(P12-P11)) -> 11 | S12: =T11 -> 72103 | T12: 72189 | U12: =IF((T12-T11)<0,"0",(T12-T11)) -> 86 | V12: =W12 -> 73031 | W12: 73031 | X12: =IF((W13-W11)<0,"0",(W13-W11)) -> 0 | Y12: =Z11 -> 91219 | Z12: 91252 | AA12: =IF((Z12-Z11)<0,"0",(Z12-Z11)) -> 33 | AB12: =AC11 -> 20355 | AC12: 20371 | AD12: =IF((AC12-AC11)<0,"0",(AC12-AC11)) -> 16 | AE12: =AF12 -> 8305 | AF12: 8305 | AG12: =IF((AF12-AF11)<0,"0",(AF12-AF11)) -> 0 | AH12: =AI11 -> 33214 | AI12: 33246 | AJ12: =IF((AI12-AI11)<0,"0",(AI12-AI11)) -> 32 | AK12: =AL11 -> 0 | AM12: =IF((AL12-AL11)<0,"0",(AL12-AL11)) -> 0 | AN12: =U12+X12+AA12+AD12+AG12+AJ12+AM12 -> 167
A13: =Gen!A18 -> 44385 | C13: =D12 -> 260022 | D13: 260116 | E13: =IF((D13-D12)<0,"0",(D13-D12)) -> 94 | F13: =G12 -> 0 | H13: =IF((G13-G12)<0,"0",(G13-G12)) -> 0 | I13: =J12 -> 8536 | J13: 8537 | K13: =J13-J12 -> 1 | L13: =M12 -> 0 | N13: =IF((M13-M12)<0,"0",(M13-M12)) -> 0 | O13: =P12 -> 21597 | P13: 21606 | Q13: =IF((P13-P12)<0,"0",(P13-P12)) -> 9 | S13: =T12 -> 72189 | T13: 72271 | U13: =IF((T13-T12)<0,"0",(T13-T12)) -> 82 | V13: =W13 -> 73031 | W13: 73031 | X13: =IF((W14-W12)<0,"0",(W14-W12)) -> 0 | Y13: =Z12 -> 91252 | Z13: 91285 | AA13: =IF((Z13-Z12)<0,"0",(Z13-Z12)) -> 33 | AB13: =AC12 -> 20371 | AC13: 20387 | AD13: =IF((AC13-AC12)<0,"0",(AC13-AC12)) -> 16 | AE13: =AF13 -> 8305 | AF13: 8305 | AG13: =IF((AF13-AF12)<0,"0",(AF13-AF12)) -> 0 | AH13: =AI12 -> 33246 | AI13: 33279 | AJ13: =IF((AI13-AI12)<0,"0",(AI13-AI12)) -> 33 | AK13: =AL12 -> 0 | AM13: =IF((AL13-AL12)<0,"0",(AL13-AL12)) -> 0 | AN13: =U13+X13+AA13+AD13+AG13+AJ13+AM13 -> 164
A14: =Gen!A19 -> 44386 | C14: =D13 -> 260116 | D14: 260224 | E14: =IF((D14-D13)<0,"0",(D14-D13)) -> 108 | F14: =G13 -> 0 | H14: =IF((G14-G13)<0,"0",(G14-G13)) -> 0 | I14: =J13 -> 8537 | J14: 8539 | K14: =IF((J14-J13)<0,"0",(J14-J13)) -> 2 | L14: =M13 -> 0 | N14: =IF((M14-M13)<0,"0",(M14-M13)) -> 0 | O14: =P13 -> 21606 | P14: 21616 | Q14: =IF((P14-P13)<0,"0",(P14-P13)) -> 10 | S14: =T13 -> 72271 | T14: 72354 | U14: =IF((T14-T13)<0,"0",(T14-T13)) -> 83 | V14: =W14 -> 73031 | W14: 73031 | X14: =IF((W15-W13)<0,"0",(W15-W13)) -> 0 | Y14: =Z13 -> 91285 | Z14: 91319 | AA14: =IF((Z14-Z13)<0,"0",(Z14-Z13)) -> 34 | AB14: =AC13 -> 20387 | AC14: 20404 | AD14: =IF((AC14-AC13)<0,"0",(AC14-AC13)) -> 17 | AE14: =AF14 -> 8305 | AF14: 8305 | AG14: =IF((AF14-AF13)<0,"0",(AF14-AF13)) -> 0 | AH14: =AI13 -> 33279 | AI14: 33312 | AJ14: =IF((AI14-AI13)<0,"0",(AI14-AI13)) -> 33 | AK14: =AL13 -> 0 | AM14: =IF((AL14-AL13)<0,"0",(AL14-AL13)) -> 0 | AN14: =U14+X14+AA14+AD14+AG14+AJ14+AM14 -> 167
A15: =Gen!A20 -> 44387 | C15: =D14 -> 260224 | D15: 260340 | E15: =IF((D15-D14)<0,"0",(D15-D14)) -> 116 | F15: =G14 -> 0 | H15: =IF((G15-G14)<0,"0",(G15-G14)) -> 0 | I15: =J14 -> 8539 | J15: 8541 | K15: =IF((J15-J14)<0,"0",(J15-J14)) -> 2 | L15: =M14 -> 0 | N15: =IF((M15-M14)<0,"0",(M15-M14)) -> 0 | O15: =P14 -> 21616 | P15: 21627 | Q15: =IF((P15-P14)<0,"0",(P15-P14)) -> 11 | S15: =T14 -> 72354 | T15: 72435 | U15: =IF((T15-T14)<0,"0",(T15-T14)) -> 81 | V15: =W14 -> 73031 | W15: 73031 | X15: =IF((W15-W14)<0,"0",(W15-W14)) -> 0 | Y15: =Z14 -> 91319 | Z15: 91359 | AA15: =IF((Z15-Z14)<0,"0",(Z15-Z14)) -> 40 | AB15: =AC14 -> 20404 | AC15: 20420 | AD15: =IF((AC15-AC14)<0,"0",(AC15-AC14)) -> 16 | AE15: =AF15 -> 8305 | AF15: 8305 | AG15: =IF((AF15-AF14)<0,"0",(AF15-AF14)) -> 0 | AH15: =AI14 -> 33312 | AI15: 33347 | AJ15: =IF((AI15-AI14)<0,"0",(AI15-AI14)) -> 35 | AK15: =AL14 -> 0 | AM15: =IF((AL15-AL14)<0,"0",(AL15-AL14)) -> 0 | AN15: =U15+X15+AA15+AD15+AG15+AJ15+AM15 -> 172
A16: =Gen!A21 -> 44388 | C16: =D15 -> 260340 | D16: 260456 | E16: =IF((D16-D15)<0,"0",(D16-D15)) -> 116 | F16: =G15 -> 0 | H16: =IF((G16-G15)<0,"0",(G16-G15)) -> 0 | I16: =J15 -> 8541 | J16: 8547 | K16: =IF((J16-J15)<0,"0",(J16-J15)) -> 6 | L16: =M15 -> 0 | N16: =IF((M16-M15)<0,"0",(M16-M15)) -> 0 | O16: =P15 -> 21627 | P16: 21638 | Q16: =IF((P16-P15)<0,"0",(P16-P15)) -> 11 | S16: =T15 -> 72435 | T16: 72517 | U16: =IF((T16-T15)<0,"0",(T16-T15)) -> 82 | V16: =W15 -> 73031 | W16: 73031 | X16: =IF((W16-W15)<0,"0",(W16-W15)) -> 0 | Y16: =Z15 -> 91359 | Z16: 91393 | AA16: =IF((Z16-Z15)<0,"0",(Z16-Z15)) -> 34 | AB16: =AC15 -> 20420 | AC16: 20434 | AD16: =IF((AC16-AC15)<0,"0",(AC16-AC15)) -> 14 | AE16: =AF16 -> 8305 | AF16: 8305 | AG16: =IF((AF16-AF15)<0,"0",(AF16-AF15)) -> 0 | AH16: =AI15 -> 33347 | AI16: 33371 | AJ16: =IF((AI16-AI15)<0,"0",(AI16-AI15)) -> 24 | AK16: =AL15 -> 0 | AM16: =IF((AL16-AL15)<0,"0",(AL16-AL15)) -> 0 | AN16: =U16+X16+AA16+AD16+AG16+AJ16+AM16 -> 154
A17: =Gen!A22 -> 44389 | C17: =D16 -> 260456 | D17: 260565 | E17: =IF((D17-D16)<0,"0",(D17-D16)) -> 109 | F17: =G16 -> 0 | H17: =IF((G17-G16)<0,"0",(G17-G16)) -> 0 | I17: =J16 -> 8547 | J17: 8549 | K17: =IF((J17-J16)<0,"0",(J17-J16)) -> 2 | L17: =M16 -> 0 | N17: =IF((M17-M16)<0,"0",(M17-M16)) -> 0 | O17: =P16 -> 21638 | P17: 21648 | Q17: =IF((P17-P16)<0,"0",(P17-P16)) -> 10 | S17: =T16 -> 72517 | T17: 72603 | U17: =IF((T17-T16)<0,"0",(T17-T16)) -> 86 | V17: =W16 -> 73031 | W17: 73031 | X17: =IF((W17-W16)<0,"0",(W17-W16)) -> 0 | Y17: =Z16 -> 91393 | Z17: 91430 | AA17: =IF((Z17-Z16)<0,"0",(Z17-Z16)) -> 37 | AB17: =AC16 -> 20434 | AC17: 20449 | AD17: =IF((AC17-AC16)<0,"0",(AC17-AC16)) -> 15 | AE17: =AF17 -> 8305 | AF17: 8305 | AG17: =IF((AF17-AF16)<0,"0",(AF17-AF16)) -> 0 | AH17: =AI16 -> 33371 | AI17: 33404 | AJ17: =IF((AI17-AI16)<0,"0",(AI17-AI16)) -> 33 | AK17: =AL16 -> 0 | AM17: =IF((AL17-AL16)<0,"0",(AL17-AL16)) -> 0 | AN17: =U17+X17+AA17+AD17+AG17+AJ17+AM17 -> 171
A18: =Gen!A23 -> 44390 | C18: =D17 -> 260565 | D18: 260670 | E18: =IF((D18-D17)<0,"0",(D18-D17)) -> 105 | F18: =G17 -> 0 | H18: =IF((G18-G17)<0,"0",(G18-G17)) -> 0 | J18: 8551 | K18: =IF((J18-J17)<0,"0",(J18-J17)) -> 2 | L18: =M17 -> 0 | N18: =IF((M18-M17)<0,"0",(M18-M17)) -> 0 | O18: =P17 -> 21648 | P18: 21660 | Q18: =IF((P18-P17)<0,"0",(P18-P17)) -> 12 | S18: =T17 -> 72603 | T18: 72686 | U18: =IF((T18-T17)<0,"0",(T18-T17)) -> 83 | V18: =W17 -> 73031 | W18: 73031 | X18: =IF((W18-W17)<0,"0",(W18-W17)) -> 0 | Y18: =Z17 -> 91430 | Z18: 91466 | AA18: =IF((Z18-Z17)<0,"0",(Z18-Z17)) -> 36 | AB18: =AC17 -> 20449 | AC18: 20464 | AD18: =IF((AC18-AC17)<0,"0",(AC18-AC17)) -> 15 | AE18: =AF18 -> 8305 | AF18: 8305 | AG18: =IF((AF18-AF17)<0,"0",(AF18-AF17)) -> 0 | AH18: =AI17 -> 33404 | AI18: 33435 | AJ18: =IF((AI18-AI17)<0,"0",(AI18-AI17)) -> 31 | AK18: =AL17 -> 0 | AM18: =IF((AL18-AL17)<0,"0",(AL18-AL17)) -> 0 | AN18: =U18+X18+AA18+AD18+AG18+AJ18+AM18 -> 165
A19: =Gen!A24 -> 44391 | C19: =D18 -> 260670 | D19: 260775 | E19: =IF((D19-D18)<0,"0",(D19-D18)) -> 105 | F19: =G18 -> 0 | H19: =IF((G19-G18)<0,"0",(G19-G18)) -> 0 | I19: =J18 -> 8551 | J19: 8553 | K19: =IF((J19-J18)<0,"0",(J19-J18)) -> 2 | L19: =M18 -> 0 | N19: =IF((M19-M18)<0,"0",(M19-M18)) -> 0 | O19: =P18 -> 21660 | P19: 21670 | Q19: =IF((P19-P18)<0,"0",(P19-P18)) -> 10 | S19: =T18 -> 72686 | T19: 72688 | U19: =IF((T19-T18)<0,"0",(T19-T18)) -> 2 | V19: =W18 -> 73031 | W19: 73031 | X19: =IF((W19-W18)<0,"0",(W19-W18)) -> 0 | Y19: =Z18 -> 91466 | Z19: 91502 | AA19: =IF((Z19-Z18)<0,"0",(Z19-Z18)) -> 36 | AB19: =AC18 -> 20464 | AC19: 20479 | AD19: =IF((AC19-AC18)<0,"0",(AC19-AC18)) -> 15 | AE19: =AF19 -> 8305 | AF19: 8305 | AG19: =IF((AF19-AF18)<0,"0",(AF19-AF18)) -> 0 | AH19: =AI18 -> 33435 | AI19: 33466 | AJ19: =IF((AI19-AI18)<0,"0",(AI19-AI18)) -> 31 | AK19: =AL18 -> 0 | AM19: =IF((AL19-AL18)<0,"0",(AL19-AL18)) -> 0 | AN19: =U19+X19+AA19+AD19+AG19+AJ19+AM19 -> 84
A20: =Gen!A25 -> 44392 | C20: =D19 -> 260775 | D20: 260858 | E20: =IF((D20-D19)<0,"0",(D20-D19)) -> 83 | F20: =G19 -> 0 | H20: =IF((G20-G19)<0,"0",(G20-G19)) -> 0 | I20: =J19 -> 8553 | J20: 8555 | K20: =IF((J20-J19)<0,"0",(J20-J19)) -> 2 | L20: =M19 -> 0 | N20: =IF((M20-M19)<0,"0",(M20-M19)) -> 0 | O20: =P19 -> 21670 | P20: 21678 | Q20: =IF((P20-P19)<0,"0",(P20-P19)) -> 8 | S20: =T20 -> 72688 | T20: 72688 | U20: =IF((T20-T19)<0,"0",(T20-T19)) -> 0 | V20: =W19 -> 73031 | W20: 73031 | X20: =IF((W20-W19)<0,"0",(W20-W19)) -> 0 | Y20: =Z19 -> 91502 | Z20: 91539 | AA20: =IF((Z20-Z19)<0,"0",(Z20-Z19)) -> 37 | AB20: =AC19 -> 20479 | AC20: 20494 | AD20: =IF((AC20-AC19)<0,"0",(AC20-AC19)) -> 15 | AE20: =AF20 -> 8305 | AF20: 8305 | AG20: =IF((AF20-AF19)<0,"0",(AF20-AF19)) -> 0 | AH20: =AI19 -> 33466 | AI20: 33496 | AJ20: =IF((AI20-AI19)<0,"0",(AI20-AI19)) -> 30 | AK20: =AL19 -> 0 | AM20: =IF((AL20-AL19)<0,"0",(AL20-AL19)) -> 0 | AN20: =U20+X20+AA20+AD20+AG20+AJ20+AM20 -> 82
A21: =Gen!A26 -> 44393 | C21: =D20 -> 260858 | D21: 260961 | E21: =IF((D21-D20)<0,"0",(D21-D20)) -> 103 | F21: =G20 -> 0 | H21: =IF((G21-G20)<0,"0",(G21-G20)) -> 0 | I21: =J20 -> 8555 | J21: 8560 | K21: =IF((J21-J20)<0,"0",(J21-J20)) -> 5 | L21: =M20 -> 0 | N21: =IF((M21-M20)<0,"0",(M21-M20)) -> 0 | O21: =P20 -> 21678 | P21: 21688 | Q21: =IF((P21-P20)<0,"0",(P21-P20)) -> 10 | S21: =T21 -> 72747 | T21: 72747 | U21: =IF((T21-T20)<0,"0",(T21-T20)) -> 59 | V21: =W20 -> 73031 | W21: 73031 | X21: =IF((W21-W20)<0,"0",(W21-W20)) -> 0 | Y21: =Z20 -> 91539 | Z21: 91576 | AA21: =IF((Z21-Z20)<0,"0",(Z21-Z20)) -> 37 | AB21: =AC20 -> 20494 | AC21: 20511 | AD21: =IF((AC21-AC20)<0,"0",(AC21-AC20)) -> 17 | AE21: =AF20 -> 8305 | AF21: 8305 | AG21: =IF((AF21-AF20)<0,"0",(AF21-AF20)) -> 0 | AH21: =AI20 -> 33496 | AI21: 33538 | AJ21: =IF((AI21-AI20)<0,"0",(AI21-AI20)) -> 42 | AK21: =AL20 -> 0 | AM21: =IF((AL21-AL20)<0,"0",(AL21-AL20)) -> 0 | AN21: =U21+X21+AA21+AD21+AG21+AJ21+AM21 -> 155
A22: =Gen!A27 -> 44394 | C22: =D21 -> 260961 | D22: 261068 | E22: =IF((D22-D21)<0,"0",(D22-D21)) -> 107 | F22: =G21 -> 0 | H22: =IF((G22-G21)<0,"0",(G22-G21)) -> 0 | I22: =J21 -> 8560 | J22: 8564 | K22: =IF((J22-J21)<0,"0",(J22-J21)) -> 4 | L22: =M21 -> 0 | N22: =IF((M22-M21)<0,"0",(M22-M21)) -> 0 | O22: =P21 -> 21688 | P22: 21698 | Q22: =IF((P22-P21)<0,"0",(P22-P21)) -> 10 | S22: =T22 -> 72829 | T22: 72829 | U22: =IF((T22-T21)<0,"0",(T22-T21)) -> 82 | V22: =W21 -> 73031 | W22: 73031 | X22: =IF((W22-W21)<0,"0",(W22-W21)) -> 0 | Y22: =Z21 -> 91576 | Z22: 91614 | AA22: =IF((Z22-Z21)<0,"0",(Z22-Z21)) -> 38 | AB22: =AC21 -> 20511 | AC22: 20528 | AD22: =IF((AC22-AC21)<0,"0",(AC22-AC21)) -> 17 | AE22: =AF21 -> 8305 | AF22: 8305 | AG22: =IF((AF22-AF21)<0,"0",(AF22-AF21)) -> 0 | AH22: =AI21 -> 33538 | AI22: 33560 | AJ22: =IF((AI22-AI21)<0,"0",(AI22-AI21)) -> 22 | AK22: =AL21 -> 0 | AM22: =IF((AL22-AL21)<0,"0",(AL22-AL21)) -> 0 | AN22: =U22+X22+AA22+AD22+AG22+AJ22+AM22 -> 159
A23: =Gen!A28 -> 44395 | C23: =D22 -> 261068 | D23: 261196 | E23: =IF((D23-D22)<0,"0",(D23-D22)) -> 128 | F23: =G22 -> 0 | H23: =IF((G23-G22)<0,"0",(G23-G22)) -> 0 | I23: =J22 -> 8564 | J23: 8567 | K23: =IF((J23-J22)<0,"0",(J23-J22)) -> 3 | L23: =M22 -> 0 | N23: =IF((M23-M22)<0,"0",(M23-M22)) -> 0 | O23: =P22 -> 21698 | P23: 21706 | Q23: =IF((P23-P22)<0,"0",(P23-P22)) -> 8 | S23: =T22 -> 72829 | T23: 72829 | U23: =IF((T23-T22)<0,"0",(T23-T22)) -> 0 | V23: =W22 -> 73031 | W23: 73031 | X23: =IF((W23-W22)<0,"0",(W23-W22)) -> 0 | Y23: =Z22 -> 91614 | Z23: 91651 | AA23: =IF((Z23-Z22)<0,"0",(Z23-Z22)) -> 37 | AB23: =AC22 -> 20528 | AC23: 20545 | AD23: =IF((AC23-AC22)<0,"0",(AC23-AC22)) -> 17 | AE23: =AF22 -> 8305 | AF23: 8305 | AG23: =IF((AF23-AF22)<0,"0",(AF23-AF22)) -> 0 | AH23: =AI22 -> 33560 | AI23: 33591 | AJ23: =IF((AI23-AI22)<0,"0",(AI23-AI22)) -> 31 | AK23: =AL22 -> 0 | AM23: =IF((AL23-AL22)<0,"0",(AL23-AL22)) -> 0 | AN23: =U23+X23+AA23+AD23+AG23+AJ23+AM23 -> 85
A24: =Gen!A29 -> 44396 | C24: =D23 -> 261196 | D24: 261311 | E24: =IF((D24-D23)<0,"0",(D24-D23)) -> 115 | F24: =G23 -> 0 | H24: =IF((G24-G23)<0,"0",(G24-G23)) -> 0 | I24: =J23 -> 8567 | J24: 8568 | K24: =IF((J24-J23)<0,"0",(J24-J23)) -> 1 | L24: =M23 -> 0 | N24: =IF((M24-M23)<0,"0",(M24-M23)) -> 0 | O24: =P23 -> 21706 | P24: 21718 | Q24: =IF((P24-P23)<0,"0",(P24-P23)) -> 12 | S24: =T23 -> 72829 | T24: 72830 | U24: =IF((T24-T23)<0,"0",(T24-T23)) -> 1 | V24: =W23 -> 73031 | W24: 73031 | X24: =IF((W24-W22)<0,"0",(W24-W22)) -> 0 | Y24: =Z23 -> 91651 | Z24: 91689 | AA24: =IF((Z24-Z23)<0,"0",(Z24-Z23)) -> 38 | AB24: =AC23 -> 20545 | AC24: 20563 | AD24: =IF((AC24-AC23)<0,"0",(AC24-AC23)) -> 18 | AE24: =AF23 -> 8305 | AF24: 8305 | AG24: =IF((AF24-AF23)<0,"0",(AF24-AF23)) -> 0 | AH24: =AI23 -> 33591 | AI24: 33622 | AJ24: =IF((AI24-AI23)<0,"0",(AI24-AI23)) -> 31 | AK24: =AL23 -> 0 | AM24: =IF((AL24-AL23)<0,"0",(AL24-AL23)) -> 0 | AN24: =U24+X24+AA24+AD24+AG24+AJ24+AM24 -> 88
A25: =Gen!A30 -> 44397 | C25: =D24 -> 261311 | D25: 261424 | E25: =IF((D25-D24)<0,"0",(D25-D24)) -> 113 | F25: =G24 -> 0 | H25: =IF((G26-G24)<0,"0",(G26-G24)) -> 0 | I25: =J24 -> 8568 | J25: 8569 | K25: =IF((J25-J24)<0,"0",(J25-J24)) -> 1 | L25: =M24 -> 0 | N25: =IF((M25-M24)<0,"0",(M25-M24)) -> 0 | O25: =P24 -> 21718 | P25: 21726 | Q25: =IF((P25-P24)<0,"0",(P25-P24)) -> 8 | S25: =T24 -> 72830 | T25: 72914 | U25: =IF((T25-T24)<0,"0",(T25-T24)) -> 84 | V25: =W24 -> 73031 | W25: 73031 | X25: =IF((W25-W23)<0,"0",(W25-W23)) -> 0 | Y25: =Z24 -> 91689 | Z25: 91725 | AA25: =IF((Z25-Z24)<0,"0",(Z25-Z24)) -> 36 | AB25: =AC24 -> 20563 | AC25: 20580 | AD25: =IF((AC25-AC24)<0,"0",(AC25-AC24)) -> 17 | AE25: =AF24 -> 8305 | AF25: 8305 | AG25: =IF((AF25-AF24)<0,"0",(AF25-AF24)) -> 0 | AH25: =AI24 -> 33622 | AI25: 33653 | AJ25: =IF((AI25-AI24)<0,"0",(AI25-AI24)) -> 31 | AK25: =AL24 -> 0 | AM25: =IF((AL25-AL24)<0,"0",(AL25-AL24)) -> 0 | AN25: =U25+X25+AA25+AD25+AG25+AJ25+AM25 -> 168
A26: =Gen!A31 -> 44398 | C26: =D25 -> 261424 | D26: 261557 | E26: =IF((D26-D25)<0,"0",(D26-D25)) -> 133 | F26: =G26 -> 0 | H26: =IF((G27-G25)<0,"0",(G27-G25)) -> 0 | I26: =J25 -> 8569 | J26: 8571 | K26: =IF((J26-J25)<0,"0",(J26-J25)) -> 2 | L26: =M25 -> 0 | N26: =IF((M26-M25)<0,"0",(M26-M25)) -> 0 | O26: =P25 -> 21726 | P26: 21732 | Q26: =IF((P26-P25)<0,"0",(P26-P25)) -> 6 | S26: =T25 -> 72914 | T26: 72997 | U26: =IF((T26-T25)<0,"0",(T26-T25)) -> 83 | V26: =W25 -> 73031 | W26: 73031 | X26: =IF((W26-W25)<0,"0",(W26-W25)) -> 0 | Y26: =Z25 -> 91725 | Z26: 91761 | AA26: =IF((Z26-Z25)<0,"0",(Z26-Z25)) -> 36 | AB26: =AC25 -> 20580 | AC26: 20598 | AD26: =IF((AC26-AC25)<0,"0",(AC26-AC25)) -> 18 | AE26: =AF25 -> 8305 | AF26: 8305 | AG26: =IF((AF26-AF25)<0,"0",(AF26-AF25)) -> 0 | AH26: =AI25 -> 33653 | AI26: 33685 | AJ26: =IF((AI26-AI25)<0,"0",(AI26-AI25)) -> 32 | AK26: =AL25 -> 0 | AM26: =IF((AL26-AL25)<0,"0",(AL26-AL25)) -> 0 | AN26: =U26+X26+AA26+AD26+AG26+AJ26+AM26 -> 169
A27: =Gen!A32 -> 44399 | C27: =D26 -> 261557 | D27: 261670 | E27: =IF((D27-D26)<0,"0",(D27-D26)) -> 113 | F27: =G27 -> 0 | H27: =IF((G28-G26)<0,"0",(G28-G26)) -> 0 | I27: =J26 -> 8571 | J27: 8572 | K27: =IF((J27-J26)<0,"0",(J27-J26)) -> 1 | L27: =M26 -> 0 | N27: =IF((M27-M26)<0,"0",(M27-M26)) -> 0 | O27: =P26 -> 21732 | P27: 21741 | Q27: =IF((P27-P26)<0,"0",(P27-P26)) -> 9 | S27: =T26 -> 72997 | T27: 73042 | U27: =IF((T27-T26)<0,"0",(T27-T26)) -> 45 | V27: =W26 -> 73031 | W27: 73031 | X27: =IF((W27-W26)<0,"0",(W27-W26)) -> 0 | Y27: =Z26 -> 91761 | Z27: 91796 | AA27: =IF((Z27-Z26)<0,"0",(Z27-Z26)) -> 35 | AB27: =AC26 -> 20598 | AC27: 20626 | AD27: =IF((AC27-AC26)<0,"0",(AC27-AC26)) -> 28 | AE27: =AF26 -> 8305 | AF27: 8305 | AG27: =IF((AF27-AF26)<0,"0",(AF27-AF26)) -> 0 | AH27: =AI26 -> 33685 | AI27: 33716 | AJ27: =IF((AI27-AI26)<0,"0",(AI27-AI26)) -> 31 | AK27: =AL26 -> 0 | AM27: =IF((AL27-AL26)<0,"0",(AL27-AL26)) -> 0 | AN27: =U27+X27+AA27+AD27+AG27+AJ27+AM27 -> 139
A28: =Gen!A33 -> 44400 | C28: =D27 -> 261670 | D28: 261778 | E28: =IF((D28-D27)<0,"0",(D28-D27)) -> 108 | F28: =G28 -> 0 | H28: =IF((G28-G27)<0,"0",(G28-G27)) -> 0 | I28: =J27 -> 8572 | J28: 8573 | K28: =IF((J28-J27)<0,"0",(J28-J27)) -> 1 | L28: =M27 -> 0 | N28: =IF((M28-M27)<0,"0",(M28-M27)) -> 0 | O28: =P27 -> 21741 | P28: 21749 | Q28: =IF((P28-P27)<0,"0",(P28-P27)) -> 8 | S28: =T27 -> 73042 | T28: 73119 | U28: =IF((T28-T27)<0,"0",(T28-T27)) -> 77 | V28: =W27 -> 73031 | W28: 73031 | X28: =IF((W28-W27)<0,"0",(W28-W27)) -> 0 | Y28: =Z27 -> 91796 | Z28: 91831 | AA28: =IF((Z28-Z27)<0,"0",(Z28-Z27)) -> 35 | AB28: =AC27 -> 20626 | AC28: 20647 | AD28: =IF((AC28-AC27)<0,"0",(AC28-AC27)) -> 21 | AE28: =AF27 -> 8305 | AF28: 8305 | AG28: =IF((AF28-AF27)<0,"0",(AF28-AF27)) -> 0 | AH28: =AI27 -> 33716 | AI28: 33748 | AJ28: =IF((AI28-AI27)<0,"0",(AI28-AI27)) -> 32 | AK28: =AL27 -> 0 | AM28: =IF((AL28-AL27)<0,"0",(AL28-AL27)) -> 0 | AN28: =U28+X28+AA28+AD28+AG28+AJ28+AM28 -> 165
A29: =Gen!A34 -> 44401 | C29: =D28 -> 261778 | D29: 261884 | E29: =IF((D29-D28)<0,"0",(D29-D28)) -> 106 | F29: =G29 -> 0 | H29: =IF((G29-G28)<0,"0",(G29-G28)) -> 0 | I29: =J28 -> 8573 | J29: 8575 | K29: =IF((J29-J28)<0,"0",(J29-J28)) -> 2 | L29: =M28 -> 0 | N29: =IF((M29-M28)<0,"0",(M29-M28)) -> 0 | O29: =P28 -> 21749 | P29: 21760 | Q29: =IF((P29-P28)<0,"0",(P29-P28)) -> 11 | S29: =T28 -> 73119 | T29: 73198 | U29: =IF((T29-T28)<0,"0",(T29-T28)) -> 79 | V29: =W28 -> 73031 | W29: 73031 | X29: =IF((W29-W28)<0,"0",(W29-W28)) -> 0 | Y29: =Z28 -> 91831 | Z29: 91864 | AA29: =IF((Z29-Z28)<0,"0",(Z29-Z28)) -> 33 | AB29: =AC28 -> 20647 | AC29: 20664 | AD29: =IF((AC29-AC28)<0,"0",(AC29-AC28)) -> 17 | AE29: =AF28 -> 8305 | AF29: 8305 | AG29: =IF((AF29-AF28)<0,"0",(AF29-AF28)) -> 0 | AH29: =AI28 -> 33748 | AI29: 33777 | AJ29: =IF((AI29-AI28)<0,"0",(AI29-AI28)) -> 29 | AK29: =AL28 -> 0 | AM29: =IF((AL29-AL28)<0,"0",(AL29-AL28)) -> 0 | AN29: =U29+X29+AA29+AD29+AG29+AJ29+AM29 -> 158
A30: =Gen!A35 -> 44402 | C30: =D29 -> 261884 | D30: 261990 | E30: =IF((D30-D29)<0,"0",(D30-D29)) -> 106 | F30: =G30 -> 0 | H30: =IF((G30-G29)<0,"0",(G30-G29)) -> 0 | I30: =J29 -> 8575 | J30: 8577 | K30: =IF((J30-J29)<0,"0",(J30-J29)) -> 2 | L30: =M29 -> 0 | N30: =IF((M30-M29)<0,"0",(M30-M29)) -> 0 | O30: =P29 -> 21760 | P30: 21770 | Q30: =IF((P30-P29)<0,"0",(P30-P29)) -> 10 | S30: =T29 -> 73198 | T30: 73280 | U30: =IF((T30-T29)<0,"0",(T30-T29)) -> 82 | V30: =W29 -> 73031 | W30: 73031 | X30: =IF((W30-W29)<0,"0",(W30-W29)) -> 0 | Y30: =Z29 -> 91864 | Z30: 91900 | AA30: =IF((Z30-Z29)<0,"0",(Z30-Z29)) -> 36 | AB30: =AC29 -> 20664 | AC30: 20683 | AD30: =IF((AC30-AC29)<0,"0",(AC30-AC29)) -> 19 | AE30: =AF29 -> 8305 | AF30: 8305 | AG30: =IF((AF30-AF29)<0,"0",(AF30-AF29)) -> 0 | AH30: =AI29 -> 33777 | AI30: 33810 | AJ30: =IF((AI30-AI29)<0,"0",(AI30-AI29)) -> 33 | AK30: =AL29 -> 0 | AM30: =IF((AL30-AL29)<0,"0",(AL30-AL29)) -> 0 | AN30: =U30+X30+AA31+AD30+AG30+AJ30+AM30 -> 169
A31: =Gen!A36 -> 44403 | C31: =D30 -> 261990 | D31: 262086 | E31: =IF((D31-D30)<0,"0",(D31-D30)) -> 96 | F31: =G31 -> 0 | H31: =IF((G31-G30)<0,"0",(G31-G30)) -> 0 | I31: =J30 -> 8577 | J31: 8580 | K31: =IF((J31-J30)<0,"0",(J31-J30)) -> 3 | L31: =M30 -> 0 | N31: =IF((M31-M30)<0,"0",(M31-M30)) -> 0 | O31: =P30 -> 21770 | P31: 21780 | Q31: =IF((P31-P30)<0,"0",(P31-P30)) -> 10 | S31: =T30 -> 73280 | T31: 73361 | U31: =IF((T31-T30)<0,"0",(T31-T30)) -> 81 | V31: =W30 -> 73031 | W31: 73031 | X31: =IF((W31-W30)<0,"0",(W31-W30)) -> 0 | Y31: =Z30 -> 91900 | Z31: 91935 | AA31: =IF((Z31-Z30)<0,"0",(Z31-Z30)) -> 35 | AB31: =AC30 -> 20683 | AC31: 20700 | AD31: =IF((AC31-AC30)<0,"0",(AC31-AC30)) -> 17 | AE31: =AF30 -> 8305 | AF31: 8305 | AG31: =IF((AF31-AF30)<0,"0",(AF31-AF30)) -> 0 | AH31: =AI30 -> 33810 | AI31: 33841 | AJ31: =IF((AI31-AI30)<0,"0",(AI31-AI30)) -> 31 | AK31: =AL30 -> 0 | AM31: =IF((AL31-AL30)<0,"0",(AL31-AL30)) -> 0 | AN31: =U31+X31+AA31+AD31+AG31+AJ31+AM31 -> 164
A32: =Gen!A37 -> 44404 | B32: 10/27//2009 | C32: =D31 -> 262086 | D32: 262189 | E32: =IF((D32-D31)<0,"0",(D32-D31)) -> 103 | F32: =G31 -> 0 | H32: =IF((G32-G31)<0,"0",(G32-G31)) -> 0 | I32: =J31 -> 8580 | J32: 8582 | K32: =IF((J32-J31)<0,"0",(J32-J31)) -> 2 | L32: =M31 -> 0 | N32: =IF((M32-M31)<0,"0",(M32-M31)) -> 0 | O32: =P31 -> 21780 | P32: 21788 | Q32: =IF((P32-P31)<0,"0",(P32-P31)) -> 8 | S32: =T31 -> 73361 | T32: 73441 | U32: =IF((T32-T31)<0,"0",(T32-T31)) -> 80 | V32: =W31 -> 73031 | W32: 73031 | X32: =IF((W32-W31)<0,"0",(W32-W31)) -> 0 | Y32: =Z31 -> 91935 | Z32: 91970 | AA32: =IF((Z32-Z31)<0,"0",(Z32-Z31)) -> 35 | AB32: =AC31 -> 20700 | AC32: 20717 | AD32: =IF((AC32-AC31)<0,"0",(AC32-AC31)) -> 17 | AE32: =AF31 -> 8305 | AF32: 8305 | AG32: =IF((AF32-AF31)<0,"0",(AF32-AF31)) -> 0 | AH32: =AI31 -> 33841 | AI32: 33872 | AJ32: =IF((AI32-AI31)<0,"0",(AI32-AI31)) -> 31 | AK32: =AL31 -> 0 | AM32: =IF((AL32-AL31)<0,"0",(AL32-AL31)) -> 0 | AN32: =U32+X32+AA32+AD32+AG32+AJ32+AM32 -> 163
A33: =Gen!A38 -> 44405 | C33: =D32 -> 262189 | D33: 262304 | E33: =IF((D33-D32)<0,"0",(D33-D32)) -> 115 | F33: =G32 -> 0 | H33: =IF((G33-G32)<0,"0",(G33-G32)) -> 0 | I33: =J32 -> 8582 | J33: 8585 | K33: =IF((J33-J32)<0,"0",(J33-J32)) -> 3 | L33: =M32 -> 0 | N33: =IF((M33-M32)<0,"0",(M33-M32)) -> 0 | O33: =P32 -> 21788 | P33: 21797 | Q33: =IF((P33-P32)<0,"0",(P33-P32)) -> 9 | S33: =T32 -> 73441 | T33: 73454 | U33: =IF((T33-T32)<0,"0",(T33-T32)) -> 13 | V33: =W32 -> 73031 | W33: 73031 | X33: =IF((W33-W32)<0,"0",(W33-W32)) -> 0 | Y33: =Z32 -> 91970 | Z33: 92004 | AA33: =IF((Z33-Z32)<0,"0",(Z33-Z32)) -> 34 | AB33: =AC32 -> 20717 | AC33: 20734 | AD33: =IF((AC33-AC32)<0,"0",(AC33-AC32)) -> 17 | AE33: =AF32 -> 8305 | AF33: 8305 | AG33: =IF((AF33-AF32)<0,"0",(AF33-AF32)) -> 0 | AH33: =AI32 -> 33872 | AI33: 33904 | AJ33: =IF((AI33-AI32)<0,"0",(AI33-AI32)) -> 32 | AK33: =AL32 -> 0 | AM33: =IF((AL33-AL32)<0,"0",(AL33-AL32)) -> 0 | AN33: =U33+X33+AA33+AD33+AG33+AJ33+AM33 -> 96
A34: =Gen!A39 -> 44406 | C34: =D33 -> 262304 | D34: 262415 | E34: =IF((D34-D33)<0,"0",(D34-D33)) -> 111 | F34: =G33 -> 0 | H34: =IF((G34-G33)<0,"0",(G34-G33)) -> 0 | I34: =J33 -> 8585 | J34: 8587 | K34: =IF((J34-J33)<0,"0",(J34-J33)) -> 2 | L34: =M33 -> 0 | N34: =IF((M34-M33)<0,"0",(M34-M33)) -> 0 | O34: =P33 -> 21797 | P34: 21807 | Q34: =IF((P34-P33)<0,"0",(P34-P33)) -> 10 | S34: =T33 -> 73454 | T34: 73526 | U34: =IF((T34-T33)<0,"0",(T34-T33)) -> 72 | V34: =W33 -> 73031 | W34: 73031 | X34: =IF((W34-W33)<0,"0",(W34-W33)) -> 0 | Y34: =Z33 -> 92004 | Z34: 92038 | AA34: =IF((Z34-Z33)<0,"0",(Z34-Z33)) -> 34 | AB34: =AC33 -> 20734 | AC34: 20750 | AD34: =IF((AC34-AC33)<0,"0",(AC34-AC33)) -> 16 | AE34: =AF33 -> 8305 | AF34: 8305 | AG34: =IF((AF34-AF33)<0,"0",(AF34-AF33)) -> 0 | AH34: =AI33 -> 33904 | AI34: 33935 | AJ34: =IF((AI34-AI33)<0,"0",(AI34-AI33)) -> 31 | AK34: =AL33 -> 0 | AM34: =IF((AL34-AL33)<0,"0",(AL34-AL33)) -> 0 | AN34: =U34+X34+AA34+AD34+AG34+AJ34+AM34 -> 153
A35: =Gen!A40 -> 44407 | C35: =D34 -> 262415 | D35: 262520 | E35: =IF((D35-D34)<0,"0",(D35-D34)) -> 105 | F35: =G34 -> 0 | H35: =IF((G35-G34)<0,"0",(G35-G34)) -> 0 | I35: =J34 -> 8587 | J35: 8590 | K35: =IF((J35-J34)<0,"0",(J35-J34)) -> 3 | L35: =M34 -> 0 | N35: =IF((M35-M34)<0,"0",(M35-M34)) -> 0 | O35: =P34 -> 21807 | P35: 21817 | Q35: =IF((P35-P34)<0,"0",(P35-P34)) -> 10 | S35: =T34 -> 73526 | T35: 73607 | U35: =IF((T35-T34)<0,"0",(T35-T34)) -> 81 | V35: =W34 -> 73031 | W35: 73031 | X35: =IF((W36-W34)<0,"0",(W36-W34)) -> 0 | Y35: =Z34 -> 92038 | Z35: 92073 | AA35: =IF((Z35-Z34)<0,"0",(Z35-Z34)) -> 35 | AB35: =AC34 -> 20750 | AC35: 20770 | AD35: =IF((AC35-AC34)<0,"0",(AC35-AC34)) -> 20 | AE35: =AF34 -> 8305 | AF35: 8305 | AG35: =IF((AF35-AF34)<0,"0",(AF35-AF34)) -> 0 | AH35: =AI34 -> 33935 | AI35: 33966 | AJ35: =IF((AI35-AI34)<0,"0",(AI35-AI34)) -> 31 | AK35: =AL34 -> 0 | AM35: =IF((AL35-AL34)<0,"0",(AL35-AL34)) -> 0 | AN35: =U35+X35+AA35+AD35+AG35+AJ35+AM35 -> 167
A36: =Gen!A41 -> 44408 | C36: =D35 -> 262520 | D36: 262619 | E36: =IF((D36-D35)<0,"0",(D36-D35)) -> 99 | F36: =G35 -> 0 | H36: =IF((G36-G35)<0,"0",(G36-G35)) -> 0 | I36: =J35 -> 8590 | J36: 8592 | K36: =IF((J36-J35)<0,"0",(J36-J35)) -> 2 | L36: =M35 -> 0 | N36: =IF((M36-M35)<0,"0",(M36-M35)) -> 0 | O36: =P35 -> 21817 | P36: 21828 | Q36: =IF((P36-P35)<0,"0",(P36-P35)) -> 11 | S36: =T35 -> 73607 | T36: 73687 | U36: =IF((T36-T35)<0,"0",(T36-T35)) -> 80 | V36: =W36 -> 73031 | W36: 73031 | X36: =IF((W37-W35)<0,"0",(W37-W35)) -> 0 | Y36: =Z35 -> 92073 | Z36: 92106 | AA36: =IF((Z36-Z35)<0,"0",(Z36-Z35)) -> 33 | AB36: =AC35 -> 20770 | AC36: 20786 | AD36: =IF((AC36-AC35)<0,"0",(AC36-AC35)) -> 16 | AE36: =AF35 -> 8305 | AF36: 8305 | AG36: =IF((AF36-AF35)<0,"0",(AF36-AF35)) -> 0 | AH36: =AI35 -> 33966 | AI36: 33986 | AJ36: =IF((AI36-AI35)<0,"0",(AI36-AI35)) -> 20 | AK36: =AL35 -> 0 | AM36: =IF((AL36-AL35)<0,"0",(AL36-AL35)) -> 0 | AN36: =U36+X36+AA36+AD36+AG36+AJ36+AM36 -> 149
C37: =D36 -> 262619 | E37: =IF((D37-D36)<0,"0",(D37-D36)) -> 0 | F37: =G36 -> 0 | H37: =IF((G37-G36)<0,"0",(G37-G36)) -> 0 | I37: =J36 -> 8592 | K37: =IF((J37-J36)<0,"0",(J37-J36)) -> 0 | L37: =M36 -> 0 | N37: =IF((M37-M36)<0,"0",(M37-M36)) -> 0 | O37: =P36 -> 21828 | Q37: =IF((P37-P36)<0,"0",(P37-P36)) -> 0 | AA37: =IF((Z37-Z36)<0,"0",(Z37-Z36)) -> 0 | AB37: =AC36 -> 20786 | AD37: =IF((AC37-AC36)<0,"0",(AC37-AC36)) -> 0 | AE37: =AF36 -> 8305
C38: TOTAL USAGE | E38: =SUM(E6:E36) -> 3372 | F38: KL | H38: =SUM(H6:H37) -> 0 | K38: =SUM(K6:K37) -> 70 | N38: =M38-M37 -> 0 | Q38: =P38-O38 -> 0 | R38: =E38 -> 3372 | U38: =SUM(U6:U37) -> 1929 | X38: =SUM(X13:X37) -> 0 | AA38: =SUM(AA6:AA37) -> 1094 | AD38: =SUM(AD6:AD37) -> 527 | AG38: =SUM(AG6:AG37) -> 0 | AJ38: =SUM(AJ6:AJ37) -> 957 | AM38: =SUM(AM6:AM37) -> 0 | AN38: =U38+X38+AA38+AD38+AG38+AJ38+AM38 -> 4507
C42: WATER TANK LEVEL
C43: RAW WATER TANK NO.1 | E43: RAW WATER TANK NO.2 | G43: TREATED WATER TANK | I43: TREATED -HILL TANK | K43: TOTAL WATER AVAILABLE
C44: CAPACITY 217 m³ | E44: CAPACITY 92 m³ | G44: CAPACITY 146 m³ | I44: CAPACITY 213 m³
C45: cm | D45: m³ | E45: cm | F45: m³ | H45: m³ | J45: m³ | K45: m³
A46: =Gen!A11 -> 44378 | C46: 205 | D46: =C46*217/300 -> 148.28333 | E46: 175 | F46: =E46*92/305 -> 52.786885 | G46: 240 | H46: =G46*146/383 -> 91.488251 | I46: 280 | J46: =I46*213/308 -> 193.63636 | K46: =D46+F46+H46+J46 -> 486.19483
A47: =Gen!A12 -> 44379 | C47: 230 | D47: =C47*217/300 -> 166.36667 | E47: 110 | F47: =E47*92/305 -> 33.180328 | G47: 235 | H47: =G47*146/383 -> 89.582245 | I47: 285 | J47: =I47*213/308 -> 197.09416 | K47: =D47+F47+H47+J47 -> 486.2234
A48: =Gen!A13 -> 44380 | C48: 250 | D48: =C48*217/300 -> 180.83333 | E48: 225 | F48: =E48*92/305 -> 67.868852 | G48: 245 | H48: =G48*146/383 -> 93.394256 | I48: 280 | J48: =I48*213/308 -> 193.63636 | K48: =D48+F48+H48+J48 -> 535.73281
A49: =Gen!A14 -> 44381 | C49: 300 | D49: =C49*217/300 -> 217 | E49: 300 | F49: =E49*92/305 -> 90.491803 | G49: 175 | H49: =G49*146/383 -> 66.710183 | I49: 285 | J49: =I49*213/308 -> 197.09416 | K49: =D49+F49+H49+J49 -> 571.29614
A50: =Gen!A15 -> 44382 | C50: 300 | D50: =C50*217/300 -> 217 | E50: 300 | F50: =E50*92/305 -> 90.491803 | G50: 170 | H50: =G50*146/383 -> 64.804178 | I50: 280 | J50: =I50*213/308 -> 193.63636 | K50: =D50+F50+H50+J50 -> 565.93234
A51: =Gen!A16 -> 44383 | C51: 250 | D51: =C51*217/300 -> 180.83333 | E51: 215 | F51: =E51*92/305 -> 64.852459 | G51: 35 | H51: =G51*146/383 -> 13.342037 | I51: 290 | J51: =I51*213/308 -> 200.55195 | K51: =D51+F51+H51+J51 -> 459.57978
A52: =Gen!A17 -> 44384 | C52: 160 | D52: =C52*217/300 -> 115.73333 | E52: 130 | F52: =E52*92/305 -> 39.213115 | G52: 85 | H52: =G52*146/383 -> 32.402089 | I52: 285 | J52: =I52*213/308 -> 197.09416 | K52: =D52+F52+H52+J52 -> 384.44269
A53: =Gen!A18 -> 44385 | C53: 55 | D53: =C53*217/300 -> 39.783333 | E53: 20 | F53: =E53*92/305 -> 6.0327869 | G53: 300 | H53: =G53*146/383 -> 114.36031 | I53: 280 | J53: =I53*213/308 -> 193.63636 | K53: =D53+F53+H53+J53 -> 353.8128
A54: =Gen!A19 -> 44386 | C54: 200 | D54: =C54*217/300 -> 144.66667 | E54: 175 | F54: =E54*92/305 -> 52.786885 | G54: 95 | H54: =G54*146/383 -> 36.214099 | I54: 280 | J54: =I54*213/308 -> 193.63636 | K54: =D54+F54+H54+J54 -> 427.30401
A55: =Gen!A20 -> 44387 | C55: 185 | D55: =C55*217/300 -> 133.81667 | E55: 150 | F55: =E55*92/305 -> 45.245902 | G55: 150 | H55: =G55*146/383 -> 57.180157 | I55: 285 | J55: =I55*213/308 -> 197.09416 | K55: =D55+F55+H55+J55 -> 433.33688
A56: =Gen!A21 -> 44388 | C56: 285 | D56: =C56*217/300 -> 206.15 | E56: 250 | F56: =E56*92/305 -> 75.409836 | G56: 100 | H56: =G56*146/383 -> 38.120104 | I56: 280 | J56: =I56*213/308 -> 193.63636 | K56: =D56+F56+H56+J56 -> 513.3163
A57: =Gen!A22 -> 44389 | C57: 270 | D57: =C57*217/300 -> 195.3 | E57: 235 | F57: =E57*92/305 -> 70.885246 | G57: 195 | H57: =G57*146/383 -> 74.334204 | I57: 290 | J57: =I57*213/308 -> 200.55195 | K57: =D57+F57+H57+J57 -> 541.0714
... A76: =Gen!A41 -> 44408 | C76: 235 | D76: =C76*217/300 -> 169.98333 | E76: 200 | F76: =E76*92/305 -> 60.327869 | G76: 255 | H76: =G76*146/383 -> 97.206266 | I76: 290 | J76: =I76*213/308 -> 200.55195 | K76: =D76+F76+H76+J76 -> 528.06942
A77: =Gen!A42 -> 0 | D77: =C77*217/300 -> 0 | F77: =E77*92/305 -> 0 | H77: =G77*146/383 -> 0 | J77: =I77*213/308 -> 0 | K77: =D77+F77+H77+J77 -> 0
A78: =Gen!A43 -> BF

Sheet Water_Graph 
A1: Date | B1: Usage | C1: Occ %
A2: =Gen!A11 -> 44378 | B2: #REF! | C2: 0.623
A3: =Gen!A12 -> 44379 | B3: #REF! | C3: 0.779
A4: =Gen!A13 -> 44380 | B4: #REF! | C4: 0.532
A5: =Gen!A14 -> 44381 | B5: #REF! | C5: 0.61
A6: =Gen!A15 -> 44382 | B6: #REF! | C6: 0.688
A7: =Gen!A16 -> 44383 | B7: #REF! | C7: 0.532
A8: =Gen!A17 -> 44384 | B8: #REF! | C8: 0.753
A9: =Gen!A18 -> 44385 | B9: #REF! | C9: 0.156
A10: =Gen!A19 -> 44386 | B10: #REF! | C10: 0.442
A11: =Gen!A20 -> 44387 | B11: #REF! | C11: 0.325
A12: =Gen!A21 -> 44388 | B12: #REF! | C12: 0.455
A13: =Gen!A22 -> 44389 | B13: #REF! | C13: 0.416
... A29: =Gen!A38 -> 44405 | B29: #REF! | C29: 0.273
A30: =Gen!A39 -> 44406 | B30: -212333 | C30: #REF!
A31: =Gen!A40 -> 44407 | B31: #REF! | C31: #REF!
A32: =Gen!A41 -> 44408 | B32: #REF! | C32: #REF!

Sheet Sheet1
A2: Generator and Diseal Summry Report | Q2: 2209.85 | R2: Diesel Cost | S2: Rate$ | T2: 1584
M3: % of Gas balance in Tank | P3: % of Dieasel balance in Tank | Q3: HLP Cost (TSH) | V3: Total Cost (TSH) | W3: Consumption Guest Occ% | AA3: Budget Cost Per Room occ
A4: Date | B4: Gen Set Hours Working | C4: Occ% | D4: Total OCC Room | E4: Guest Room Occ | F4: Total Kwh Generated | G4: Diseal consumed by Gen (Ltrs) | H4: Diseal consumed by Veichel (Ltrs) | I4: Total diseal consumed (Ltrs) | J4: Balance stock of Diseal (Ltrs) | K4: Water consumed | L4: Gas consumed (KG) | M4: 3 | N4: 2 | O4: 1 | Q4: Electricity | R4: Cost per Room Total OOC Usd | S4: Cost per Room Guest OOC Usd | T4: Water | U4: Gas
A5: =Gen!A11 -> 44378 | B5: 0 | C5: =Gen!B11 -> 0.3 | D5: =SUM(77*C5) -> 23.1 | F5: =Gen!U11 -> 0.42204034 | G5: =Gen!T11 -> 4264 | H5: #REF! | I5: =SUM(G5:H5) -> #REF! | J5: 47806.65 | K5: ='Water-Meter'!E6 -> 109 | L5: ='Lpg (2)'!G10 -> 130.68 | M5: =#REF! -> #REF! | N5: =#REF! -> #REF! | O5: =#REF! -> #REF! | P5: =J5/52000 -> 0.91935865 | Q5: =I5*Q2 -> #REF! | R5: =SUM(Q5/D5)/X5 -> #REF! | S5: =SUM(Q5/E5)/X5 -> #REF! | T5: =(K5*102)/X5 -> 7.0189394 | U5: =SUM(L5*1963)/X5 -> 161.9475 | V5: =SUM(Q5+T5+U5) -> #REF! | W5: =SUM(V5/E5)/T2 -> #REF! | X5: =SUM(T2) -> 1584 | Y5: 106 | Z5: =SUM(Y5-S5) -> #REF! | AA5: 106
A6: =Gen!A12 -> 44379 | B6: 0 | C6: =Gen!B12 -> 0.35 | D6: =SUM(77*C6) -> 26.95 | F6: =Gen!U12 -> 0.39586336 | G6: =Gen!T12 -> 4274 | H6: #REF! | I6: =SUM(G6:H6) -> #REF! | J6: 45423.89 | K6: ='Water-Meter'!E7 -> 101 | L6: ='Lpg (2)'!G11 -> 124.52 | M6: =#REF! -> #REF! | N6: =#REF! -> #REF! | O6: =#REF! -> #REF! | P6: =J6/52000 -> 0.87353635 | Q6: =I6*Q2 -> #REF! | R6: =SUM(Q6/D6)/X6 -> #REF! | S6: =SUM(Q6/E6)/X6 -> #REF! | T6: =(K6*102)/X6 -> 6.5037879 | U6: =SUM(L6*1963)/X6 -> 154.31361 | V6: =SUM(Q6+T6+U6) -> #REF! | W6: =SUM(V6/E6)/T2 -> #REF! | X6: =SUM(X5) -> 1584 | Y6: 106 | Z6: =SUM(Y6-S6) -> #REF!
A7: =Gen!A13 -> 44380 | B7: 0 | C7: =Gen!B13 -> 0.2609 | D7: =SUM(77*C7) -> 20.0893 | F7: =Gen!U13 -> 0.40530557 | G7: =Gen!T13 -> 4467 | H7: #REF! | I7: =SUM(G7:H7) -> #REF! | J7: 42919.59 | K7: ='Water-Meter'!E8 -> 94 | L7: ='Lpg (2)'!G12 -> 44 | M7: =#REF! -> #REF! | N7: =#REF! -> #REF! | O7: =#REF! -> #REF! | P7: =J7/52000 -> 0.82537673 | Q7: =I7*Q2 -> #REF! | R7: =SUM(Q7/D7)/X7 -> #REF! | S7: =SUM(Q7/E7)/X7 -> #REF! | T7: =(K7*102)/X7 -> 6.0530303 | U7: =SUM(L7*1963)/X7 -> 54.527778 | V7: =SUM(Q7+T7+U7) -> #REF! | W7: =SUM(V7/E7)/T2 -> #REF! | X7: =SUM(X6) -> 1584 | Y7: 106 | Z7: =SUM(Y7-S7) -> #REF!
A8: =Gen!A14 -> 44381 | B8: 0 | C8: =Gen!B14 -> 0.18 | D8: =SUM(77*C8) -> 13.86 | F8: =Gen!U14 -> 0.40242085 | G8: =Gen!T14 -> 4106 | H8: #REF! | I8: =SUM(G8:H8) -> #REF! | J8: 40258.94 | K8: ='Water-Meter'!E9 -> 98 | L8: ='Lpg (2)'!G13 -> 89.364 | M8: =#REF! -> #REF! | N8: =#REF! -> #REF! | O8: =#REF! -> #REF! | P8: =J8/52000 -> 0.77421038 | Q8: =I8*Q2 -> #REF! | R8: =SUM(Q8/D8)/X8 -> #REF! | S8: =SUM(Q8/E8)/X8 -> #REF! | T8: =(K8*102)/X8 -> 6.3106061 | U8: =SUM(L8*1963)/X8 -> 110.74592 | V8: =SUM(Q8+T8+U8) -> #REF! | W8: =SUM(V8/E8)/T2 -> #REF! | X8: =SUM(X7) -> 1584 | Y8: 106 | Z8: =SUM(Y8-S8) -> #REF!
A9: =Gen!A15 -> 44382 | B9: 0 | C9: =Gen!B15 -> 0.14 | D9: =SUM(77*C9) -> 10.78 | F9: =Gen!U15 -> 0.40842524 | G9: =Gen!T15 -> 4026 | H9: 0 | I9: =SUM(G9:H9) -> 4026 | J9: 37525.21 | K9: ='Water-Meter'!E10 -> 135 | L9: ='Lpg (2)'!G14 -> 112.42 | M9: =#REF! -> #REF! | N9: =#REF! -> #REF! | O9: =#REF! -> #REF! | P9: =J9/52000 -> 0.72163865 | Q9: =I9*Q2 -> 8896856.1 | R9: =SUM(Q9/D9)/X9 -> 521.02988 | S9: =SUM(Q9/E9)/X9 -> #DIV/0! | T9: =(K9*102)/X9 -> 8.6931818 | U9: =SUM(L9*1963)/X9 -> 139.31847 | V9: =SUM(Q9+T9+U9) -> 8897004.1 | W9: =SUM(V9/E9)/T2 -> #DIV/0! | X9: =SUM(X8) -> 1584 | Y9: 106 | Z9: =SUM(Y9-S9) -> #DIV/0!
A10: =Gen!A16 -> 44383 | B10: 0 | C10: =Gen!B16 -> 0.169 | D10: =SUM(77*C10) -> 13.013 | F10: =Gen!U16 -> 0.40270929 | G10: =Gen!T16 -> 4145 | H10: #REF! | I10: =SUM(G10:H10) -> #REF! | J10: 35107.69 | K10: ='Water-Meter'!E11 -> 124 | L10: ='Lpg (2)'!G15 -> 116.776 | M10: =#REF! -> #REF! | N10: =#REF! -> #REF! | O10: =#REF! -> #REF! | P10: =J10/52000 -> 0.67514788 | Q10: =I10*Q2 -> #REF! | R10: =SUM(Q10/D10)/X10 -> #REF! | S10: =SUM(Q10/E10)/X10 -> #REF! | T10: =(K10*102)/X10 -> 7.9848485 | U10: =SUM(L10*1963)/X10 -> 144.71672 | V10: =SUM(Q10+T10+U10) -> #REF! | W10: =SUM(V10/E10)/T2 -> #REF! | X10: =SUM(X9) -> 1584 | Y10: 106 | Z10: =SUM(Y10-S10) -> #REF!
A11: =Gen!A17 -> 44384 | B11: 0 | C11: =Gen!B17 -> 0.364 | D11: =SUM(77*C11) -> 28.028 | F11: =Gen!U17 -> 0.40618396 | G11: =Gen!T17 -> 4675 | H11: 80.56 | I11: =SUM(G11:H11) -> 4755.56 | J11: 47513.14 | K11: ='Water-Meter'!E12 -> 114 | L11: ='Lpg (2)'!G16 -> 108.328 | M11: =#REF! -> #REF! | N11: =#REF! -> #REF! | O11: =#REF! -> #REF! | P11: =J11/52000 -> 0.91371423 | Q11: =I11*Q2 -> 10509074 | R11: =SUM(Q11/D11)/X11 -> 236.71031 | S11: =SUM(Q11/E11)/X11 -> #DIV/0! | T11: =(K11*102)/X11 -> 7.3409091 | U11: =SUM(L11*1963)/X11 -> 134.24739 | V11: =SUM(Q11+T11+U11) -> 10509216 | W11: =SUM(V11/E11)/T2 -> #DIV/0! | X11: =SUM(X10) -> 1584 | Y11: 106 | Z11: =SUM(Y11-S11) -> #DIV/0!
A12: =Gen!A18 -> 44385 | B12: 0 | C12: =Gen!B18 -> 0.455 | D12: =SUM(77*C12) -> 35.035 | F12: =Gen!U18 -> 0.41006374 | G12: =Gen!T18 -> 4550 | H12: #REF! | I12: =SUM(G12:H12) -> #REF! | J12: 45161.89 | K12: ='Water-Meter'!E13 -> 94 | L12: ='Lpg (2)'!G17 -> 112.376 | M12: =#REF! -> #REF! | N12: =#REF! -> #REF! | O12: =#REF! -> #REF! | P12: =J12/52000 -> 0.86849788 | Q12: =I12*Q2 -> #REF! | R12: =SUM(Q12/D12)/X12 -> #REF! | S12: =SUM(Q12/E12)/X12 -> #REF! | T12: =(K12*102)/X12 -> 6.0530303 | U12: =SUM(L12*1963)/X12 -> 139.26394 | V12: =SUM(Q12+T12+U12) -> #REF! | W12: =SUM(V12/E12)/T2 -> #REF! | X12: =SUM(X11) -> 1584 | Y12: 106 | Z12: =SUM(Y12-S12) -> #REF!
A13: =Gen!A19 -> 44386 | B13: 0 | C13: =Gen!B19 -> 0.468 | D13: =SUM(77*C13) -> 36.036 | F13: =Gen!U19 -> 0.4239315 | G13: =Gen!T19 -> 4263 | H13: #REF! | I13: =SUM(G13:H13) -> #REF! | J13: 42825.48 | K13: ='Water-Meter'!E14 -> 108 | L13: ='Lpg (2)'!G18 -> 103.4 | M13: =#REF! -> #REF! | N13: =#REF! -> #REF! | O13: =#REF! -> #REF! | P13: =J13/52000 -> 0.82356692 | Q13: =I13*Q2 -> #REF! | R13: =SUM(Q13/D13)/X13 -> #REF! | S13: =SUM(Q13/E13)/X13 -> #REF! | T13: =(K13*102)/X13 -> 6.9545455 | U13: =SUM(L13*1963)/X13 -> 128.14028 | V13: =SUM(Q13+T13+U13) -> #REF! | W13: =SUM(V13/E13)/T2 -> #REF! | X13: =SUM(X12) -> 1584 | Y13: 106 | Z13: =SUM(Y13-S13) -> #REF!
A14: =Gen!A20 -> 44387 | B14: 0 | C14: =Gen!B20 -> 0.39 | D14: =SUM(77*C14) -> 30.03 | F14: =Gen!U20 -> 0.41897026 | G14: =Gen!T20 -> 4506 | H14: #REF! | I14: =SUM(G14:H14) -> #REF! | J14: 40110.38 | K14: ='Water-Meter'!E15 -> 116 | L14: ='Lpg (2)'!G19 -> 117.304 | M14: =#REF! -> #REF! | N14: =#REF! -> #REF! | O14: =#REF! -> #REF! | P14: =J14/52000 -> 0.77135346 | Q14: =I14*Q2 -> #REF! | R14: =SUM(Q14/D14)/X14 -> #REF! | S14: =SUM(Q14/E14)/X14 -> #REF! | T14: =(K14*102)/X14 -> 7.469697 | U14: =SUM(L14*1963)/X14 -> 145.37106 | V14: =SUM(Q14+T14+U14) -> #REF! | W14: =SUM(V14/E14)/T2 -> #REF! | X14: =SUM(X13) -> 1584 | Y14: 106 | Z14: =SUM(Y14-S14) -> #REF!
A15: =Gen!A21 -> 44388 | B15: 0 | C15: =Gen!B21 -> 0.403 | D15: =SUM(77*C15) -> 31.031 | F15: =Gen!U21 -> 0.41547432 | G15: =Gen!T21 -> 4459 | H15: #REF! | I15: =SUM(G15:H15) -> #REF! | J15: 37540.57 | K15: ='Water-Meter'!E16 -> 116 | L15: ='Lpg (2)'!G20 -> 115.676 | M15: =#REF! -> #REF! | N15: =#REF! -> #REF! | O15: =#REF! -> #REF! | P15: =J15/52000 -> 0.72193404 | Q15: =I15*Q2 -> #REF! | R15: =SUM(Q15/D15)/X15 -> #REF! | S15: =SUM(Q15/E15)/X15 -> #REF! | T15: =(K15*102)/X15 -> 7.469697 | U15: =SUM(L15*1963)/X15 -> 143.35353 | V15: =SUM(Q15+T15+U15) -> #REF! | W15: =SUM(V15/E15)/T2 -> #REF! | X15: =SUM(X14) -> 1584 | Y15: 106 | Z15: =SUM(Y15-S15) -> #REF!
A16: =Gen!A22 -> 44389 | B16: 0 | C16: =Gen!B22 -> 0.39 | D16: =SUM(77*C16) -> 30.03 | F16: =Gen!U22 -> 0.37453132 | G16: =Gen!T22 -> 4438 | H16: #REF! | I16: =SUM(G16:H16) -> #REF! | J16: 34967.29 | K16: ='Water-Meter'!E17 -> 109 | L16: ='Lpg (2)'!G21 -> 126.984 | M16: =#REF! -> #REF! | N16: =#REF! -> #REF! | O16: =#REF! -> #REF! | P16: =J16/52000 -> 0.67244788 | Q16: =I16*Q2 -> #REF! | R16: =SUM(Q16/D16)/X16 -> #REF! | S16: =SUM(Q16/E16)/X16 -> #REF! | T16: =(K16*102)/X16 -> 7.0189394 | U16: =SUM(L16*1963)/X16 -> 157.36717 | V16: =SUM(Q16+T16+U16) -> #REF! | W16: =SUM(V16/E16)/T2 -> #REF! | X16: =SUM(X15) -> 1584 | Y16: 106 | Z16: =SUM(Y16-S16) -> #REF!
A17: =Gen!A23 -> 44390 | B17: 0 | C17: =Gen!B23 -> 0.221 | D17: =SUM(77*C17) -> 17.017 | F17: =Gen!U23 -> 0.42904884 | G17: =Gen!T23 -> 4300 | H17: #REF! | I17: =SUM(G17:H17) -> #REF! | J17: 32228.76 | K17: ='Water-Meter'!E18 -> 105 | L17: ='Lpg (2)'!G22 -> 117.876 | M17: =#REF! -> #REF! | N17: =#REF! -> #REF! | O17: =#REF! -> #REF! | P17: =J17/52000 -> 0.61978385 | Q17: =I17*Q2 -> #REF! | R17: =SUM(Q17/D17)/X17 -> #REF! | S17: =SUM(Q17/E17)/X17 -> #REF! | T17: =(K17*102)/X17 -> 6.7613636 | U17: =SUM(L17*1963)/X17 -> 146.07992 | V17: =SUM(Q17+T17+U17) -> #REF! | W17: =SUM(V17/E17)/T2 -> #REF! | X17: =SUM(X16) -> 1584 | Y17: 106 | Z17: =SUM(Y17-S17) -> #REF!
A18: =Gen!A24 -> 44391 | B18: 0 | C18: =Gen!B24 -> 0.195 | D18: =SUM(77*C18) -> 15.015 | F18: =Gen!U24 -> 0.42290364 | G18: =Gen!T24 -> 3902 | H18: 597.9 | I18: =SUM(G18:H18) -> 4499.9 | J18: 29915.45 | K18: ='Water-Meter'!E19 -> 105 | L18: ='Lpg (2)'!G23 -> 127.776 | M18: =#REF! -> #REF! | N18: =#REF! -> #REF! | O18: =#REF! -> #REF! | P18: =J18/52000 -> 0.57529712 | Q18: =I18*Q2 -> 9944104 | R18: =SUM(Q18/D18)/X18 -> 418.10479 | S18: =SUM(Q18/E18)/X18 -> #DIV/0! | T18: =(K18*102)/X18 -> 6.7613636 | U18: =SUM(L18*1963)/X18 -> 158.34867 | V18: =SUM(Q18+T18+U18) -> 9944269.1 | W18: =SUM(V18/E18)/T2 -> #DIV/0! | X18: =SUM(X17) -> 1584 | Y18: 106 | Z18: =SUM(Y18-S18) -> #DIV/0!
A19: =Gen!A25 -> 44392 | B19: 0 | C19: =Gen!B25 -> 0.208 | D19: =SUM(77*C19) -> 16.016 | F19: =Gen!U25 -> 0.4287138 | G19: =Gen!T25 -> 3833 | H19: 227.73 | I19: =SUM(G19:H19) -> 4060.73 | J19: 42248.24 | K19: ='Water-Meter'!E20 -> 83 | L19: ='Lpg (2)'!G24 -> 124.74 | M19: =#REF! -> #REF! | N19: =#REF! -> #REF! | O19: =#REF! -> #REF! | P19: =J19/52000 -> 0.81246615 | Q19: =I19*Q2 -> 8973604.2 | R19: =SUM(Q19/D19)/X19 -> 353.71842 | S19: =SUM(Q19/E19)/X19 -> #DIV/0! | T19: =(K19*102)/X19 -> 5.344697 | U19: =SUM(L19*1963)/X19 -> 154.58625 | V19: =SUM(Q19+T19+U19) -> 8973764.1 | W19: =SUM(V19/E19)/T2 -> #DIV/0! | X19: =SUM(X18) -> 1584 | Y19: 106 | Z19: =SUM(Y19-S19) -> #DIV/0!
A20: =Gen!A26 -> 44393 | B20: 0 | C20: =Gen!B26 -> 0.27 | D20: =SUM(77*C20) -> 20.79 | F20: =Gen!U26 -> 0.42469118 | G20: =Gen!T26 -> 4080 | H20: 88.29 | I20: =SUM(G20:H20) -> 4168.29 | J20: 39497.37 | K20: ='Water-Meter'!E21 -> 103 | L20: ='Lpg (2)'!G25 -> 119.064 | M20: =#REF! -> #REF! | N20: =#REF! -> #REF! | O20: =#REF! -> #REF! | P20: =J20/52000 -> 0.75956481 | Q20: =I20*Q2 -> 9211295.7 | R20: =SUM(Q20/D20)/X20 -> 279.71197 | S20: =SUM(Q20/E20)/X20 -> #DIV/0! | T20: =(K20*102)/X20 -> 6.6325758 | U20: =SUM(L20*1963)/X20 -> 147.55217 | V20: =SUM(Q20+T20+U20) -> 9211449.8 | W20: =SUM(V20/E20)/T2 -> #DIV/0! | X20: =SUM(X19) -> 1584 | Y20: 106 | Z20: =SUM(Y20-S20) -> #DIV/0!
A21: =Gen!A27 -> 44394 | B21: 0 | C21: =Gen!B27 -> 0.26 | D21: =SUM(77*C21) -> 20.02 | F21: =Gen!U27 -> 0.43173021 | G21: =Gen!T27 -> 4092 | H21: 783.92 | I21: =SUM(G21:H21) -> 4875.92 | J21: 36688.35 | K21: ='Water-Meter'!E22 -> 107 | L21: ='Lpg (2)'!G26 -> 114.444 | M21: =#REF! -> #REF! | N21: =#REF! -> #REF! | O21: =#REF! -> #REF! | P21: =J21/52000 -> 0.70554519 | Q21: =I21*Q2 -> 10775052 | R21: =SUM(Q21/D21)/X21 -> 339.7818 | S21: =SUM(Q21/E21)/X21 -> #DIV/0! | T21: =(K21*102)/X21 -> 6.8901515 | U21: =SUM(L21*1963)/X21 -> 141.82675 | V21: =SUM(Q21+T21+U21) -> 10775201 | W21: =SUM(V21/E21)/T2 -> #DIV/0! | X21: =SUM(X20) -> 1584 | Y21: 106 | Z21: =SUM(Y21-S21) -> #DIV/0!
A22: =Gen!A28 -> 44395 | B22: 0 | C22: =Gen!B28 -> 0.35 | D22: =SUM(77*C22) -> 26.95 | F22: =Gen!U28 -> 0.40179326 | G22: =Gen!T28 -> 4450 | H22: #REF! | I22: =SUM(G22:H22) -> #REF! | J22: 33769.34 | K22: ='Water-Meter'!E23 -> 128 | L22: ='Lpg (2)'!G27 -> 104.324 | M22: =#REF! -> #REF! | N22: =#REF! -> #REF! | O22: =#REF! -> #REF! | P22: =J22/52000 -> 0.64941038 | Q22: =I22*Q2 -> #REF! | R22: =SUM(Q22/D22)/X22 -> #REF! | S22: =SUM(Q22/E22)/X22 -> #REF! | T22: =(K22*102)/X22 -> 8.2424242 | U22: =SUM(L22*1963)/X22 -> 129.28536 | V22: =SUM(Q22+T22+U22) -> #REF! | W22: =SUM(V22/E22)/T2 -> #REF! | X22: =SUM(X21) -> 1584 | Y22: 106 | Z22: =SUM(Y22-S22) -> #REF!
A23: =Gen!A29 -> 44396 | B23: 0 | C23: =Gen!B29 -> 0.39 | D23: =SUM(77*C23) -> 30.03 | F23: =Gen!U29 -> 0.39119145 | G23: =Gen!T29 -> 4633 | H23: #REF! | I23: =SUM(G23:H23) -> #REF! | J23: 31336.77 | K23: ='Water-Meter'!E24 -> 115 | L23: ='Lpg (2)'!G28 -> 113.652 | M23: =#REF! -> #REF! | N23: =#REF! -> #REF! | O23: =#REF! -> #REF! | P23: =J23/52000 -> 0.60263019 | Q23: =I23*Q2 -> #REF! | R23: =SUM(Q23/D23)/X23 -> #REF! | S23: =SUM(Q23/E23)/X23 -> #REF! | T23: =(K23*102)/X23 -> 7.405303 | U23: =SUM(L23*1963)/X23 -> 140.84525 | V23: =SUM(Q23+T23+U23) -> #REF! | W23: =SUM(V23/E23)/T2 -> #REF! | X23: =SUM(X22) -> 1584 | Y23: 106 | Z23: =SUM(Y23-S23) -> #REF!
