Workbook

Sheet Total
A1: Site Name | B1: Day | C1: Month | D1: Year | E1: Total Electricity Kwh | F1: Electricity Tariff ($/Kwh) | G1: Total Fuel Oil (Liters) | H1: Fuel Oil $/Liter | I1: LPG (Kg) | J1: LPG $/Kg | K1: Water Utility Supply (m3) m3 | L1: Water Utility Supply (m3) $/m3 | M1: Irrigation Water (m3) m3 | N1: Irrigation water $/m3 | O1: Room Nights
A2: Beirut | B2: 1 | C2: 10 | D2: 2021 | E2: =ELEC!N4 -> 0 | F2: =SUM('EDl log'!T4) -> 0 | G2: =-tanks!AW6 -> 0 | H2: =SUM(tanks!AV6) -> 0.615 | I2: =('B5'!AU5)*0.51 -> 0 | J2: ='B5'!AX5/0.51 -> 1.5686275 | K2: =WATER!I6 -> 0 | L2: =SUM(WATER!J6) -> 0 | M2: =WATER!Q6 -> 0 | N2: 0.6 | O2: =ELEC!B4 -> 0
A3: Beirut | B3: =B2+1 -> 2 | C3: 10 | D3: 2021 | E3: =ELEC!N5 -> 0 | F3: =SUM('EDl log'!T5) -> 0 | G3: =-tanks!AW7 -> 0 | H3: =SUM(tanks!AV7) -> 0.615 | I3: =('B5'!AU6)*0.51 -> 0 | J3: ='B5'!AX6/0.51 -> 1.5686275 | K3: =WATER!I7 -> 0 | L3: =SUM(WATER!J7) -> 0 | M3: =WATER!Q7 -> 0 | N3: 0.6 | O3: =ELEC!B5 -> 0
A4: Beirut | B4: =B3+1 -> 3 | C4: 10 | D4: 2021 | E4: =ELEC!N6 -> 6878 | F4: =SUM('EDl log'!T6) -> -0.28637463 | G4: =-tanks!AW8 -> 81 | H4: =SUM(tanks!AV8) -> 0.615 | I4: =('B5'!AU7)*0.51 -> 0 | J4: ='B5'!AX7/0.51 -> 1.5686275 | K4: =WATER!I8 -> 0 | L4: =SUM(WATER!J8) -> 0 | M4: =WATER!Q8 -> 0 | N4: 0.6 | O4: =ELEC!B6 -> 0
A5: Beirut | B5: =B4+1 -> 4 | C5: 10 | D5: 2021 | E5: =ELEC!N7 -> 0 | F5: =SUM('EDl log'!T7) -> 0 | G5: =-tanks!AW9 -> 0 | H5: =SUM(tanks!AV9) -> 0.615 | I5: =('B5'!AU8)*0.51 -> 0 | J5: ='B5'!AX8/0.51 -> 1.5686275 | K5: =WATER!I9 -> 0 | L5: =SUM(WATER!J9) -> 0 | M5: =WATER!Q9 -> 0 | N5: 0.6 | O5: =ELEC!B7 -> 0
A6: Beirut | B6: =B5+1 -> 5 | C6: 10 | D6: 2021 | E6: =ELEC!N8 -> 0 | F6: =SUM('EDl log'!T8) -> 0 | G6: =-tanks!AW10 -> 0 | H6: =SUM(tanks!AV10) -> 0.615 | I6: =('B5'!AU9)*0.51 -> 0 | J6: ='B5'!AX9/0.51 -> 1.5686275 | K6: =WATER!I10 -> 0 | L6: =SUM(WATER!J10) -> 0 | M6: =WATER!Q10 -> 0 | N6: 0.6 | O6: =ELEC!B8 -> 0
A7: Beirut | B7: =B6+1 -> 6 | C7: 10 | D7: 2021 | E7: =ELEC!N9 -> 0 | F7: =SUM('EDl log'!T9) -> 0 | G7: =-tanks!AW11 -> 0 | H7: =SUM(tanks!AV11) -> 0.615 | I7: =('B5'!AU10)*0.51 -> 0 | J7: ='B5'!AX10/0.51 -> 1.5686275 | K7: =WATER!I11 -> 0 | L7: =SUM(WATER!J11) -> 0 | M7: =WATER!Q11 -> 0 | N7: 0.6 | O7: =ELEC!B9 -> 0
A8: Beirut | B8: =B7+1 -> 7 | C8: 10 | D8: 2021 | E8: =ELEC!N10 -> 0 | F8: =SUM('EDl log'!T10) -> 0 | G8: =-tanks!AW12 -> 0 | H8: =SUM(tanks!AV12) -> 0.615 | I8: =('B5'!AU11)*0.51 -> 0 | J8: ='B5'!AX11/0.51 -> 1.5686275 | K8: =WATER!I12 -> 0 | L8: =SUM(WATER!J12) -> 0 | M8: =WATER!Q12 -> 0 | N8: 0.6 | O8: =ELEC!B10 -> 0
A9: Beirut | B9: =B8+1 -> 8 | C9: 10 | D9: 2021 | E9: =ELEC!N11 -> 0 | F9: =SUM('EDl log'!T11) -> 0 | G9: =-tanks!AW13 -> 0 | H9: =SUM(tanks!AV13) -> 0.615 | I9: =('B5'!AU12)*0.51 -> 0 | J9: ='B5'!AX12/0.51 -> 1.5686275 | K9: =WATER!I13 -> 0 | L9: =SUM(WATER!J13) -> 0 | M9: =WATER!Q13 -> 0 | N9: 0.6 | O9: =ELEC!B11 -> 0
A10: Beirut | B10: =B9+1 -> 9 | C10: 10 | D10: 2021 | E10: =ELEC!N12 -> 0 | F10: =SUM('EDl log'!T12) -> 0 | G10: =-tanks!AW14 -> 0 | H10: =SUM(tanks!AV14) -> 0.615 | I10: =('B5'!AU13)*0.51 -> 0 | J10: ='B5'!AX13/0.51 -> 1.5686275 | K10: =WATER!I14 -> 0 | L10: =SUM(WATER!J14) -> 0 | M10: =WATER!Q14 -> 0 | N10: 0.6 | O10: =ELEC!B12 -> 0
A11: Beirut | B11: =B10+1 -> 10 | C11: 10 | D11: 2021 | E11: =ELEC!N13 -> 0 | F11: =SUM('EDl log'!T13) -> 0 | G11: =-tanks!AW15 -> 0 | H11: =SUM(tanks!AV15) -> 0.615 | I11: =('B5'!AU14)*0.51 -> 0 | J11: ='B5'!AX14/0.51 -> 1.5686275 | K11: =WATER!I15 -> 0 | L11: =SUM(WATER!J15) -> 0 | M11: =WATER!Q15 -> 0 | N11: 0.6 | O11: =ELEC!B13 -> 0
A12: Beirut | B12: =B11+1 -> 11 | C12: 10 | D12: 2021 | E12: =ELEC!N14 -> 0 | F12: =SUM('EDl log'!T14) -> 0 | G12: =-tanks!AW16 -> 0 | H12: =SUM(tanks!AV16) -> 0.615 | I12: =('B5'!AU15)*0.51 -> 0 | J12: ='B5'!AX15/0.51 -> 1.5686275 | K12: =WATER!I16 -> 0 | L12: =SUM(WATER!J16) -> 0 | M12: =WATER!Q16 -> 0 | N12: 0.6 | O12: =ELEC!B14 -> 0
A13: Beirut | B13: =B12+1 -> 12 | C13: 10 | D13: 2021 | E13: =ELEC!N15 -> 0 | F13: =SUM('EDl log'!T15) -> 0 | G13: =-tanks!AW17 -> 0 | H13: =SUM(tanks!AV17) -> 0.615 | I13: =('B5'!AU16)*0.51 -> 0 | J13: ='B5'!AX16/0.51 -> 1.5686275 | K13: =WATER!I17 -> 0 | L13: =SUM(WATER!J17) -> 0 | M13: =WATER!Q17 -> 0 | N13: 0.6 | O13: =ELEC!B15 -> 0
A14: Beirut | B14: =B13+1 -> 13 | C14: 10 | D14: 2021 | E14: =ELEC!N16 -> 0 | F14: =SUM('EDl log'!T16) -> 0 | G14: =-tanks!AW18 -> 0 | H14: =SUM(tanks!AV18) -> 0.615 | I14: =('B5'!AU17)*0.51 -> 0 | J14: ='B5'!AX17/0.51 -> 1.5686275 | K14: =WATER!I18 -> 0 | L14: =SUM(WATER!J18) -> 0 | M14: =WATER!Q18 -> 0 | N14: 0.6 | O14: =ELEC!B16 -> 0
... A32: Beirut | B32: =B31+1 -> 31 | C32: 10 | D32: 2021 | E32: =ELEC!N34 -> 0 | F32: =SUM('EDl log'!T34) -> 0 | G32: =-tanks!AW36 -> 0 | H32: =SUM(tanks!AV36) -> 0.615 | I32: =('B5'!AU35)*0.51 -> 0 | J32: ='B5'!AX35/0.51 -> 1.5686275 | K32: =WATER!I36 -> 0 | L32: =SUM(WATER!J36) -> 0 | M32: =WATER!Q36 -> 0 | N32: 0.6 | O32: =ELEC!B34 -> 0

Sheet Submetering
A1: Site Name | B1: Day | C1: Month | D1: Year | E1: ATS1 Kwh | F1: ATS2 Kwh | G1: ATS3 Kwh | H1: ATS4 Kwh | I1: ATS5 Kwh | J1: Guest (m3) | K1: Kitchen & Laundry (m3) | L1: Room Nights
A2: Beirut | B2: 1 | C2: 10 | D2: 2021 | E2: =ELEC!M4 -> 0 | F2: =ELEC!K4 -> 0 | G2: =ELEC!I4 -> 0 | H2: =ELEC!E4 -> 0 | I2: =ELEC!G4 -> 0 | J2: =WATER!Y6 -> 0 | K2: =WATER!AJ6 -> 0 | L2: =ELEC!B4 -> 0
A3: Beirut | B3: =B2+1 -> 2 | C3: 10 | D3: 2021 | E3: =ELEC!M5 -> 0 | F3: =ELEC!K5 -> 0 | G3: =ELEC!I5 -> 0 | H3: =ELEC!E5 -> 0 | I3: =ELEC!G5 -> 0 | J3: =WATER!Y7 -> 0 | K3: =WATER!AJ7 -> 0 | L3: =ELEC!B5 -> 0
A4: Beirut | B4: =B3+1 -> 3 | C4: 10 | D4: 2021 | E4: =ELEC!M6 -> 1076 | F4: =ELEC!K6 -> 2878 | G4: =ELEC!I6 -> 546 | H4: =ELEC!E6 -> 2378 | I4: =ELEC!G6 -> 0 | J4: =WATER!Y8 -> 0 | K4: =WATER!AJ8 -> 0 | L4: =ELEC!B6 -> 0
A5: Beirut | B5: =B4+1 -> 4 | C5: 10 | D5: 2021 | E5: =ELEC!M7 -> 0 | F5: =ELEC!K7 -> 0 | G5: =ELEC!I7 -> 0 | H5: =ELEC!E7 -> 0 | I5: =ELEC!G7 -> 0 | J5: =WATER!Y9 -> 0 | K5: =WATER!AJ9 -> 0 | L5: =ELEC!B7 -> 0
A6: Beirut | B6: =B5+1 -> 5 | C6: 10 | D6: 2021 | E6: =ELEC!M8 -> 0 | F6: =ELEC!K8 -> 0 | G6: =ELEC!I8 -> 0 | H6: =ELEC!E8 -> 0 | I6: =ELEC!G8 -> 0 | J6: =WATER!Y10 -> 0 | K6: =WATER!AJ10 -> 0 | L6: =ELEC!B8 -> 0
A7: Beirut | B7: =B6+1 -> 6 | C7: 10 | D7: 2021 | E7: =ELEC!M9 -> 0 | F7: =ELEC!K9 -> 0 | G7: =ELEC!I9 -> 0 | H7: =ELEC!E9 -> 0 | I7: =ELEC!G9 -> 0 | J7: =WATER!Y11 -> 0 | K7: =WATER!AJ11 -> 0 | L7: =ELEC!B9 -> 0
A8: Beirut | B8: =B7+1 -> 7 | C8: 10 | D8: 2021 | E8: =ELEC!M10 -> 0 | F8: =ELEC!K10 -> 0 | G8: =ELEC!I10 -> 0 | H8: =ELEC!E10 -> 0 | I8: =ELEC!G10 -> 0 | J8: =WATER!Y12 -> 0 | K8: =WATER!AJ12 -> 0 | L8: =ELEC!B10 -> 0
A9: Beirut | B9: =B8+1 -> 8 | C9: 10 | D9: 2021 | E9: =ELEC!M11 -> 0 | F9: =ELEC!K11 -> 0 | G9: =ELEC!I11 -> 0 | H9: =ELEC!E11 -> 0 | I9: =ELEC!G11 -> 0 | J9: =WATER!Y13 -> 0 | K9: =WATER!AJ13 -> 0 | L9: =ELEC!B11 -> 0
A10: Beirut | B10: =B9+1 -> 9 | C10: 10 | D10: 2021 | E10: =ELEC!M12 -> 0 | F10: =ELEC!K12 -> 0 | G10: =ELEC!I12 -> 0 | H10: =ELEC!E12 -> 0 | I10: =ELEC!G12 -> 0 | J10: =WATER!Y14 -> 0 | K10: =WATER!AJ14 -> 0 | L10: =ELEC!B12 -> 0
A11: Beirut | B11: =B10+1 -> 10 | C11: 10 | D11: 2021 | E11: =ELEC!M13 -> 0 | F11: =ELEC!K13 -> 0 | G11: =ELEC!I13 -> 0 | H11: =ELEC!E13 -> 0 | I11: =ELEC!G13 -> 0 | J11: =WATER!Y15 -> 0 | K11: =WATER!AJ15 -> 0 | L11: =ELEC!B13 -> 0
A12: Beirut | B12: =B11+1 -> 11 | C12: 10 | D12: 2021 | E12: =ELEC!M14 -> 0 | F12: =ELEC!K14 -> 0 | G12: =ELEC!I14 -> 0 | H12: =ELEC!E14 -> 0 | I12: =ELEC!G14 -> 0 | J12: =WATER!Y16 -> 0 | K12: =WATER!AJ16 -> 0 | L12: =ELEC!B14 -> 0
A13: Beirut | B13: =B12+1 -> 12 | C13: 10 | D13: 2021 | E13: =ELEC!M15 -> 0 | F13: =ELEC!K15 -> 0 | G13: =ELEC!I15 -> 0 | H13: =ELEC!E15 -> 0 | I13: =ELEC!G15 -> 0 | J13: =WATER!Y17 -> 0 | K13: =WATER!AJ17 -> 0 | L13: =ELEC!B15 -> 0
A14: Beirut | B14: =B13+1 -> 13 | C14: 10 | D14: 2021 | E14: =ELEC!M16 -> 0 | F14: =ELEC!K16 -> 0 | G14: =ELEC!I16 -> 0 | H14: =ELEC!E16 -> 0 | I14: =ELEC!G16 -> 0 | J14: =WATER!Y18 -> 0 | K14: =WATER!AJ18 -> 0 | L14: =ELEC!B16 -> 0
... A31: Beirut | B31: =B30+1 -> 30 | C31: 10 | D31: 2021 | E31: =ELEC!M33 -> 0 | F31: =ELEC!K33 -> 0 | G31: =ELEC!I33 -> 0 | H31: =ELEC!E33 -> 0 | I31: =ELEC!G33 -> 0 | J31: =WATER!Y35 -> 0 | K31: =WATER!AJ35 -> 0 | L31: =ELEC!B33 -> 0
A32: Beirut | B32: 31 | C32: 10 | D32: 2021 | E32: =ELEC!M34 -> 0 | F32: =ELEC!K34 -> 0 | G32: =ELEC!I34 -> 0 | H32: =ELEC!E34 -> 0 | I32: =ELEC!G34 -> 0 | J32: =WATER!Y36 -> 0 | K32: =WATER!AJ36 -> 0 | L32: =ELEC!B34 -> 0
D45: .

Sheet ELEC
AK1: ATS 4 till power meter is for MDB 3 is replaced
A2: OOC | B2: Room OCC | D2: MDB3 | E2: MDB3/day | F2: EMDB2 | G2: EMDB2/day | H2: EMDB1 | I2: EMDB1/day | J2: MDB2 | K2: mdb2/day | L2: MDB1 | M2: MDB1/Day | N2: Total KWH | O2: KWH/Rooc | P2: Gen MHW | Q2: Gen/Day KWH | R2: EDL KWH | S2: CH1 RH | T2: RH | U2: C1h1 power | V2: CH1 Con KWH | W2: CH2 RH | X2: RH | Y2: Ch2 power | Z2: CH2 Con KWH | AA2: CH3 RH | AB2: RH | AC2: Ch3 power | AD2: CH3 Con KWH | AE2: RH total | AF2: KWH total | AG2: AVG chiller KW/Hr | AK2: Emergency | AL2: Normal | AM2: Total | AN2: Difference
A3: =[1]ELEC!$A$34 -> 0 | B3: =[1]ELEC!$B$34 -> 0 | C3: =[2]ELEC!$C$33 -> 44469 | D3: =[2]ELEC!$D$33 -> 32911138 | E3: =[2]ELEC!E33 -> 1729 | F3: =[2]ELEC!F33 -> 4091226 | G3: =[2]ELEC!G33 -> 169.6 | H3: =[2]ELEC!H33 -> 17967768 | I3: =[2]ELEC!I33 -> 524 | J3: =[2]ELEC!J33 -> 29530270 | K3: =[2]ELEC!K33 -> 2988 | L3: =[2]ELEC!L33 -> 24431942 | ... AG3: =[2]ELEC!AG33 -> 237.375 | AI3: =[2]ELEC!AI33 -> -1095679.4 | AJ3: =[2]ELEC!$AJ$33 -> 44469 | AK3: =[2]ELEC!AK33 -> 1272761 | AL3: =[2]ELEC!AL33 -> 1431 | AM3: =[2]ELEC!AM33 -> 1274192 | AN3: =[2]ELEC!AN33 -> 1729
A4: ='General information '!F5 -> 0 | B4: =SUM(230*A4) -> 0 | C4: 44470 | D4: =D3 -> 32911138 | E4: =AN4 -> 0 | F4: =F3 -> 4091226 | G4: =F4-F3 -> 0 | H4: =H3 -> 17967768 | I4: =H4-H3 -> 0 | J4: =J3 -> 29530270 | K4: =J4-J3 -> 0 | L4: =L3 -> 24431942 | M4: =L4-L3 -> 0 | N4: =M4+K4+I4+G4+E4 -> 0 | O4: =IF(B4>0,N4/B4,0) -> 0 | P4: =P3 -> 18411.684 | Q4: =(P4-P3)*1000 -> 0 | R4: =+N4-Q4 -> 0 | S4: =S3 -> 10175 | T4: =S4-S3 -> 0 | U4: =U3 -> 429166 | V4: =U4-U3 -> 0 | W4: =W3 -> 33304 | X4: =W4-W3 -> 0 | Y4: =Y3 -> 953159 | Z4: =Y4-Y3 -> 0 | AA4: =AA3 -> 36762 | AB4: =AA4-AA3 -> 0 | AC4: =AC3 -> 1162232 | AD4: =AC4-AC3 -> 0 | AE4: =AB4+X4+T4 -> 0 | AF4: =V4+Z4+AD4 -> 0 | AG4: =IF(AE4>0,AF4/AE4,0) -> 0 | AI4: =R4-'EDl log'!B4 -> -1095809 | AJ4: 44470 | AK4: =AK3 -> 1272761 | AL4: =AL3 -> 1431 | AM4: =AK4+AL4 -> 1274192 | AN4: =AM4-AM3 -> 0
A5: ='General information '!F6 -> 0 | B5: =SUM(230*A5) -> 0 | C5: 44471 | D5: =D4 -> 32911138 | E5: =AN5 -> 0 | F5: =F4 -> 4091226 | G5: =F5-F4 -> 0 | H5: =H4 -> 17967768 | I5: =H5-H4 -> 0 | J5: =J4 -> 29530270 | K5: =J5-J4 -> 0 | L5: =L4 -> 24431942 | M5: =L5-L4 -> 0 | N5: =M5+K5+I5+G5+E5 -> 0 | O5: =IF(B5>0,N5/B5,0) -> 0 | P5: =P4 -> 18411.684 | Q5: =(P5-P4)*1000 -> 0 | R5: =N5-Q5 -> 0 | S5: =S4 -> 10175 | T5: =S5-S4 -> 0 | U5: =U4 -> 429166 | V5: =U5-U4 -> 0 | W5: =W4 -> 33304 | X5: =W5-W4 -> 0 | Y5: =Y4 -> 953159 | Z5: =Y5-Y4 -> 0 | AA5: =AA4 -> 36762 | AB5: =AA5-AA4 -> 0 | AC5: =AC4 -> 1162232 | AD5: =AC5-AC4 -> 0 | AE5: =AB5+X5+T5 -> 0 | AF5: =V5+Z5+AD5 -> 0 | AG5: =IF(AE5>0,AF5/AE5,0) -> 0 | AI5: =R5-'EDl log'!B5 -> -1095809 | AJ5: 44471 | AK5: =AK4 -> 1272761 | AL5: =AL4 -> 1431 | AM5: =AK5+AL5 -> 1274192 | AN5: =AM5-AM4 -> 0
A6: ='General information '!F7 -> 0 | B6: =SUM(230*A6) -> 0 | C6: 44472 | D6: =D5 -> 32911138 | E6: =AN6 -> 2378 | F6: 4091226 | G6: =F6-F5 -> 0 | H6: 17968314 | I6: =H6-H5 -> 546 | J6: 29533148 | K6: =J6-J5 -> 2878 | L6: 24433018 | M6: =L6-L5 -> 1076 | N6: =M6+K6+I6+G6+E6 -> 6878 | O6: =IF(B6>0,N6/B6,0) -> 0 | P6: 18418.3 | Q6: =(P6-P5)*1000 -> 6616 | R6: =N6-Q6 -> 262 | S6: =S5 -> 10175 | T6: =S6-S5 -> 0 | U6: =U5 -> 429166 | V6: =U6-U5 -> 0 | W6: 33311 | X6: =W6-W5 -> 7 | Y6: 954830 | Z6: =Y6-Y5 -> 1671 | AA6: 36763 | AB6: =AA6-AA5 -> 1 | AC6: 1162613 | AD6: =AC6-AC5 -> 381 | AE6: =AB6+X6+T6 -> 8 | AF6: =V6+Z6+AD6 -> 2052 | AG6: =IF(AE6>0,AF6/AE6,0) -> 256.5 | AI6: =R6-'EDl log'!B6 -> -1095547 | AJ6: 44472 | AK6: 1274972 | AL6: 1598 | AM6: =AK6+AL6 -> 1276570 | AN6: =AM6-AM5 -> 2378
A7: ='General information '!F8 -> 0 | B7: =SUM(230*A7) -> 0 | C7: 44473 | D7: =D6 -> 32911138 | E7: =AN7 -> 0 | F7: =F6 -> 4091226 | G7: =F7-F6 -> 0 | H7: =H6 -> 17968314 | I7: =H7-H6 -> 0 | J7: =J6 -> 29533148 | K7: =J7-J6 -> 0 | L7: =L6 -> 24433018 | M7: =L7-L6 -> 0 | N7: =M7+K7+I7+G7+E7 -> 0 | O7: =IF(B7>0,N7/B7,0) -> 0 | P7: =P6 -> 18418.3 | Q7: =(P7-P6)*1000 -> 0 | R7: =N7-Q7 -> 0 | S7: =S6 -> 10175 | T7: =S7-S6 -> 0 | U7: =U6 -> 429166 | V7: =U7-U6 -> 0 | W7: =W6 -> 33311 | X7: =W7-W6 -> 0 | Y7: =Y6 -> 954830 | Z7: =Y7-Y6 -> 0 | AA7: =AA6 -> 36763 | AB7: =AA7-AA6 -> 0 | AC7: =AC6 -> 1162613 | AD7: =AC7-AC6 -> 0 | AE7: =AB7+X7+T7 -> 0 | AF7: =V7+Z7+AD7 -> 0 | AG7: =IF(AE7>0,AF7/AE7,0) -> 0 | AI7: =R7-'EDl log'!B7 -> -1095809 | AJ7: 44473 | AK7: =AK6 -> 1274972 | AL7: =AL6 -> 1598 | AM7: =AK7+AL7 -> 1276570 | AN7: =AM7-AM6 -> 0
A8: ='General information '!F9 -> 0 | B8: =SUM(230*A8) -> 0 | C8: 44474 | D8: =D7 -> 32911138 | E8: =AN8 -> 0 | F8: =F7 -> 4091226 | G8: =F8-F7 -> 0 | H8: =H7 -> 17968314 | I8: =H8-H7 -> 0 | J8: =J7 -> 29533148 | K8: =J8-J7 -> 0 | L8: =L7 -> 24433018 | M8: =L8-L7 -> 0 | N8: =M8+K8+I8+G8+E8 -> 0 | O8: =IF(B8>0,N8/B8,0) -> 0 | P8: =P7 -> 18418.3 | Q8: =(P8-P7)*1000 -> 0 | R8: =N8-Q8 -> 0 | S8: =S7 -> 10175 | T8: =S8-S7 -> 0 | U8: =U7 -> 429166 | V8: =U8-U7 -> 0 | W8: =W7 -> 33311 | X8: =W8-W7 -> 0 | Y8: =Y7 -> 954830 | Z8: =Y8-Y7 -> 0 | AA8: =AA7 -> 36763 | AB8: =AA8-AA7 -> 0 | AC8: =AC7 -> 1162613 | AD8: =AC8-AC7 -> 0 | AE8: =AB8+X8+T8 -> 0 | AF8: =V8+Z8+AD8 -> 0 | AG8: =IF(AE8>0,AF8/AE8,0) -> 0 | AI8: =R8-'EDl log'!B8 -> -1095809 | AJ8: 44474 | AK8: =AK7 -> 1274972 | AL8: =AL7 -> 1598 | AM8: =AK8+AL8 -> 1276570 | AN8: =AM8-AM7 -> 0
A9: ='General information '!F10 -> 0 | B9: =SUM(230*A9) -> 0 | C9: 44475 | D9: =D8 -> 32911138 | E9: =AN9 -> 0 | F9: =F8 -> 4091226 | G9: =F9-F8 -> 0 | H9: =H8 -> 17968314 | I9: =H9-H8 -> 0 | J9: =J8 -> 29533148 | K9: =J9-J8 -> 0 | L9: =L8 -> 24433018 | M9: =L9-L8 -> 0 | N9: =M9+K9+I9+G9+E9 -> 0 | O9: =IF(B9>0,N9/B9,0) -> 0 | P9: =P8 -> 18418.3 | Q9: =(P9-P8)*1000 -> 0 | R9: =N9-Q9 -> 0 | S9: =S8 -> 10175 | T9: =S9-S8 -> 0 | U9: =U8 -> 429166 | V9: =U9-U8 -> 0 | W9: =W8 -> 33311 | X9: =W9-W8 -> 0 | Y9: =Y8 -> 954830 | Z9: =Y9-Y8 -> 0 | AA9: =AA8 -> 36763 | AB9: =AA9-AA8 -> 0 | AC9: =AC8 -> 1162613 | AD9: =AC9-AC8 -> 0 | AE9: =AB9+X9+T9 -> 0 | AF9: =V9+Z9+AD9 -> 0 | AG9: =IF(AE9>0,AF9/AE9,0) -> 0 | AI9: =R9-'EDl log'!B9 -> -1095809 | AJ9: 44475 | AK9: =AK8 -> 1274972 | AL9: =AL8 -> 1598 | AM9: =AK9+AL9 -> 1276570 | AN9: =AM9-AM8 -> 0
A10: ='General information '!F11 -> 0 | B10: =SUM(230*A10) -> 0 | C10: 44476 | D10: =D9 -> 32911138 | E10: =AN10 -> 0 | F10: =F9 -> 4091226 | G10: =F10-F9 -> 0 | H10: =H9 -> 17968314 | I10: =H10-H9 -> 0 | J10: =J9 -> 29533148 | K10: =J10-J9 -> 0 | L10: =L9 -> 24433018 | M10: =L10-L9 -> 0 | N10: =M10+K10+I10+G10+E10 -> 0 | O10: =IF(B10>0,N10/B10,0) -> 0 | P10: =P9 -> 18418.3 | Q10: =(P10-P9)*1000 -> 0 | R10: =N10-Q10 -> 0 | S10: =S9 -> 10175 | T10: =S10-S9 -> 0 | U10: =U9 -> 429166 | V10: =U10-U9 -> 0 | W10: =W9 -> 33311 | X10: =W10-W9 -> 0 | Y10: =Y9 -> 954830 | Z10: =Y10-Y9 -> 0 | AA10: =AA9 -> 36763 | AB10: =AA10-AA9 -> 0 | AC10: =AC9 -> 1162613 | AD10: =AC10-AC9 -> 0 | AE10: =AB10+X10+T10 -> 0 | AF10: =V10+Z10+AD10 -> 0 | AG10: =IF(AE10>0,AF10/AE10,0) -> 0 | AI10: =R10-'EDl log'!B10 -> -1095809 | AJ10: 44476 | AK10: =AK9 -> 1274972 | AL10: =AL9 -> 1598 | AM10: =AK10+AL10 -> 1276570 | AN10: =AM10-AM9 -> 0
A11: ='General information '!F12 -> 0 | B11: =SUM(230*A11) -> 0 | C11: 44477 | D11: =D10 -> 32911138 | E11: =AN11 -> 0 | F11: =F10 -> 4091226 | G11: =F11-F10 -> 0 | H11: =H10 -> 17968314 | I11: =H11-H10 -> 0 | J11: =J10 -> 29533148 | K11: =J11-J10 -> 0 | L11: =L10 -> 24433018 | M11: =L11-L10 -> 0 | N11: =M11+K11+I11+G11+E11 -> 0 | O11: =IF(B11>0,N11/B11,0) -> 0 | P11: =P10 -> 18418.3 | Q11: =(P11-P10)*1000 -> 0 | R11: =N11-Q11 -> 0 | S11: =S10 -> 10175 | T11: =S11-S10 -> 0 | U11: =U10 -> 429166 | V11: =U11-U10 -> 0 | W11: =W10 -> 33311 | X11: =W11-W10 -> 0 | Y11: =Y10 -> 954830 | Z11: =Y11-Y10 -> 0 | AA11: =AA10 -> 36763 | AB11: =AA11-AA10 -> 0 | AC11: =AC10 -> 1162613 | AD11: =AC11-AC10 -> 0 | AE11: =AB11+X11+T11 -> 0 | AF11: =V11+Z11+AD11 -> 0 | AG11: =IF(AE11>0,AF11/AE11,0) -> 0 | AI11: =R11-'EDl log'!B11 -> -1095809 | AJ11: 44477 | AK11: =AK10 -> 1274972 | AL11: =AL10 -> 1598 | AM11: =AK11+AL11 -> 1276570 | AN11: =AM11-AM10 -> 0
A12: ='General information '!F13 -> 0 | B12: =SUM(230*A12) -> 0 | C12: 44478 | D12: =D11 -> 32911138 | E12: =AN12 -> 0 | F12: =F11 -> 4091226 | G12: =F12-F11 -> 0 | H12: =H11 -> 17968314 | I12: =H12-H11 -> 0 | J12: =J11 -> 29533148 | K12: =J12-J11 -> 0 | L12: =L11 -> 24433018 | M12: =L12-L11 -> 0 | N12: =M12+K12+I12+G12+E12 -> 0 | O12: =IF(B12>0,N12/B12,0) -> 0 | P12: =P11 -> 18418.3 | Q12: =(P12-P11)*1000 -> 0 | R12: =N12-Q12 -> 0 | S12: =S11 -> 10175 | T12: =S12-S11 -> 0 | U12: =U11 -> 429166 | V12: =U12-U11 -> 0 | W12: =W11 -> 33311 | X12: =W12-W11 -> 0 | Y12: =Y11 -> 954830 | Z12: =Y12-Y11 -> 0 | AA12: =AA11 -> 36763 | AB12: =AA12-AA11 -> 0 | AC12: =AC11 -> 1162613 | AD12: =AC12-AC11 -> 0 | AE12: =AB12+X12+T12 -> 0 | AF12: =V12+Z12+AD12 -> 0 | AG12: =IF(AE12>0,AF12/AE12,0) -> 0 | AI12: =R12-'EDl log'!B12 -> -1095809 | AJ12: 44478 | AK12: =AK11 -> 1274972 | AL12: =AL11 -> 1598 | AM12: =AK12+AL12 -> 1276570 | AN12: =AM12-AM11 -> 0
A13: ='General information '!F14 -> 0 | B13: =SUM(230*A13) -> 0 | C13: 44479 | D13: =D12 -> 32911138 | E13: =AN13 -> 0 | F13: =F12 -> 4091226 | G13: =F13-F12 -> 0 | H13: =H12 -> 17968314 | I13: =H13-H12 -> 0 | J13: =J12 -> 29533148 | K13: =J13-J12 -> 0 | L13: =L12 -> 24433018 | M13: =L13-L12 -> 0 | N13: =M13+K13+I13+G13+E13 -> 0 | O13: =IF(B13>0,N13/B13,0) -> 0 | P13: =P12 -> 18418.3 | Q13: =(P13-P12)*1000 -> 0 | R13: =N13-Q13 -> 0 | S13: =S12 -> 10175 | T13: =S13-S12 -> 0 | U13: =U12 -> 429166 | V13: =U13-U12 -> 0 | W13: =W12 -> 33311 | X13: =W13-W12 -> 0 | Y13: =Y12 -> 954830 | Z13: =Y13-Y12 -> 0 | AA13: =AA12 -> 36763 | AB13: =AA13-AA12 -> 0 | AC13: =AC12 -> 1162613 | AD13: =AC13-AC12 -> 0 | AE13: =AB13+X13+T13 -> 0 | AF13: =V13+Z13+AD13 -> 0 | AG13: =IF(AE13>0,AF13/AE13,0) -> 0 | AI13: =R13-'EDl log'!B13 -> -1095809 | AJ13: 44479 | AK13: =AK12 -> 1274972 | AL13: =AL12 -> 1598 | AM13: =AK13+AL13 -> 1276570 | AN13: =AM13-AM12 -> 0
A14: ='General information '!F15 -> 0 | B14: =SUM(230*A14) -> 0 | C14: 44480 | D14: =D13 -> 32911138 | E14: =AN14 -> 0 | F14: =F13 -> 4091226 | G14: =F14-F13 -> 0 | H14: =H13 -> 17968314 | I14: =H14-H13 -> 0 | J14: =J13 -> 29533148 | K14: =J14-J13 -> 0 | L14: =L13 -> 24433018 | M14: =L14-L13 -> 0 | N14: =M14+K14+I14+G14+E14 -> 0 | O14: =IF(B14>0,N14/B14,0) -> 0 | P14: =P13 -> 18418.3 | Q14: =(P14-P13)*1000 -> 0 | R14: =N14-Q14 -> 0 | S14: =S13 -> 10175 | T14: =S14-S13 -> 0 | U14: =U13 -> 429166 | V14: =U14-U13 -> 0 | W14: =W13 -> 33311 | X14: =W14-W13 -> 0 | Y14: =Y13 -> 954830 | Z14: =Y14-Y13 -> 0 | AA14: =AA13 -> 36763 | AB14: =AA14-AA13 -> 0 | AC14: =AC13 -> 1162613 | AD14: =AC14-AC13 -> 0 | AE14: =AB14+X14+T14 -> 0 | AF14: =V14+Z14+AD14 -> 0 | AG14: =IF(AE14>0,AF14/AE14,0) -> 0 | AI14: =R14-'EDl log'!B14 -> -1095809 | AJ14: 44480 | AK14: =AK13 -> 1274972 | AL14: =AL13 -> 1598 | AM14: =AK14+AL14 -> 1276570 | AN14: =AM14-AM13 -> 0
A15: ='General information '!F16 -> 0 | B15: =SUM(230*A15) -> 0 | C15: 44481 | D15: =D14 -> 32911138 | E15: =AN15 -> 0 | F15: =F14 -> 4091226 | G15: =F15-F14 -> 0 | H15: =H14 -> 17968314 | I15: =H15-H14 -> 0 | J15: =J14 -> 29533148 | K15: =J15-J14 -> 0 | L15: =L14 -> 24433018 | M15: =L15-L14 -> 0 | N15: =M15+K15+I15+G15+E15 -> 0 | O15: =IF(B15>0,N15/B15,0) -> 0 | P15: =P14 -> 18418.3 | Q15: =(P15-P14)*1000 -> 0 | R15: =N15-Q15 -> 0 | S15: =S14 -> 10175 | T15: =S15-S14 -> 0 | U15: =U14 -> 429166 | V15: =U15-U14 -> 0 | W15: =W14 -> 33311 | X15: =W15-W14 -> 0 | Y15: =Y14 -> 954830 | Z15: =Y15-Y14 -> 0 | AA15: =AA14 -> 36763 | AB15: =AA15-AA14 -> 0 | AC15: =AC14 -> 1162613 | AD15: =AC15-AC14 -> 0 | AE15: =AB15+X15+T15 -> 0 | AF15: =V15+Z15+AD15 -> 0 | AG15: =IF(AE15>0,AF15/AE15,0) -> 0 | AI15: =R15-'EDl log'!B15 -> -1095809 | AJ15: 44481 | AK15: =AK14 -> 1274972 | AL15: =AL14 -> 1598 | AM15: =AK15+AL15 -> 1276570 | AN15: =AM15-AM14 -> 0
A16: ='General information '!F17 -> 0 | B16: =SUM(230*A16) -> 0 | C16: 44482 | D16: =D15 -> 32911138 | E16: =AN16 -> 0 | F16: =F15 -> 4091226 | G16: =F16-F15 -> 0 | H16: =H15 -> 17968314 | I16: =H16-H15 -> 0 | J16: =J15 -> 29533148 | K16: =J16-J15 -> 0 | L16: =L15 -> 24433018 | M16: =L16-L15 -> 0 | N16: =M16+K16+I16+G16+E16 -> 0 | O16: =IF(B16>0,N16/B16,0) -> 0 | P16: =P15 -> 18418.3 | Q16: =(P16-P15)*1000 -> 0 | R16: =N16-Q16 -> 0 | S16: =S15 -> 10175 | T16: =S16-S15 -> 0 | U16: =U15 -> 429166 | V16: =U16-U15 -> 0 | W16: =W15 -> 33311 | X16: =W16-W15 -> 0 | Y16: =Y15 -> 954830 | Z16: =Y16-Y15 -> 0 | AA16: =AA15 -> 36763 | AB16: =AA16-AA15 -> 0 | AC16: =AC15 -> 1162613 | AD16: =AC16-AC15 -> 0 | AE16: =AB16+X16+T16 -> 0 | AF16: =V16+Z16+AD16 -> 0 | AG16: =IF(AE16>0,AF16/AE16,0) -> 0 | AI16: =R16-'EDl log'!B16 -> -1095809 | AJ16: 44482 | AK16: =AK15 -> 1274972 | AL16: =AL15 -> 1598 | AM16: =AK16+AL16 -> 1276570 | AN16: =AM16-AM15 -> 0
A17: ='General information '!F18 -> 0 | B17: =SUM(230*A17) -> 0 | C17: 44483 | D17: =D16 -> 32911138 | E17: =AN17 -> 0 | F17: =F16 -> 4091226 | G17: =F17-F16 -> 0 | H17: =H16 -> 17968314 | I17: =H17-H16 -> 0 | J17: =J16 -> 29533148 | K17: =J17-J16 -> 0 | L17: =L16 -> 24433018 | M17: =L17-L16 -> 0 | N17: =M17+K17+I17+G17+E17 -> 0 | O17: =IF(B17>0,N17/B17,0) -> 0 | P17: =P16 -> 18418.3 | Q17: =(P17-P16)*1000 -> 0 | R17: =N17-Q17 -> 0 | S17: =S16 -> 10175 | T17: =S17-S16 -> 0 | U17: =U16 -> 429166 | V17: =U17-U16 -> 0 | W17: =W16 -> 33311 | X17: =W17-W16 -> 0 | Y17: =Y16 -> 954830 | Z17: =Y17-Y16 -> 0 | AA17: =AA16 -> 36763 | AB17: =AA17-AA16 -> 0 | AC17: =AC16 -> 1162613 | AD17: =AC17-AC16 -> 0 | AE17: =AB17+X17+T17 -> 0 | AF17: =V17+Z17+AD17 -> 0 | AG17: =IF(AE17>0,AF17/AE17,0) -> 0 | AI17: =R17-'EDl log'!B17 -> -1095809 | AJ17: 44483 | AK17: =AK16 -> 1274972 | AL17: =AL16 -> 1598 | AM17: =AK17+AL17 -> 1276570 | AN17: =AM17-AM16 -> 0
A18: ='General information '!F19 -> 0 | B18: =SUM(230*A18) -> 0 | C18: 44484 | D18: =D17 -> 32911138 | E18: =AN18 -> 0 | F18: =F17 -> 4091226 | G18: =F18-F17 -> 0 | H18: =H17 -> 17968314 | I18: =H18-H17 -> 0 | J18: =J17 -> 29533148 | K18: =J18-J17 -> 0 | L18: =L17 -> 24433018 | M18: =L18-L17 -> 0 | N18: =M18+K18+I18+G18+E18 -> 0 | O18: =IF(B18>0,N18/B18,0) -> 0 | P18: =P17 -> 18418.3 | Q18: =(P18-P17)*1000 -> 0 | R18: =N18-Q18 -> 0 | S18: =S17 -> 10175 | T18: =S18-S17 -> 0 | U18: =U17 -> 429166 | V18: =U18-U17 -> 0 | W18: =W17 -> 33311 | X18: =W18-W17 -> 0 | Y18: =Y17 -> 954830 | Z18: =Y18-Y17 -> 0 | AA18: =AA17 -> 36763 | AB18: =AA18-AA17 -> 0 | AC18: =AC17 -> 1162613 | AD18: =AC18-AC17 -> 0 | AE18: =AB18+X18+T18 -> 0 | AF18: =V18+Z18+AD18 -> 0 | AG18: =IF(AE18>0,AF18/AE18,0) -> 0 | AI18: =R18-'EDl log'!B18 -> -1095809 | AJ18: 44484 | AK18: =AK17 -> 1274972 | AL18: =AL17 -> 1598 | AM18: =AK18+AL18 -> 1276570 | AN18: =AM18-AM17 -> 0 | AO18: =G18+I18+K18+M18 -> 0 | AP18: =Q18+'EDl log'!C18 -> 0
A19: ='General information '!F20 -> 0 | B19: =SUM(230*A19) -> 0 | C19: 44485 | D19: =D18 -> 32911138 | E19: =AN19 -> 0 | F19: =F18 -> 4091226 | G19: =F19-F18 -> 0 | H19: =H18 -> 17968314 | I19: =H19-H18 -> 0 | J19: =J18 -> 29533148 | K19: =J19-J18 -> 0 | L19: =L18 -> 24433018 | M19: =L19-L18 -> 0 | N19: =M19+K19+I19+G19+E19 -> 0 | O19: =IF(B19>0,N19/B19,0) -> 0 | P19: =P18 -> 18418.3 | Q19: =(P19-P18)*1000 -> 0 | R19: =N19-Q19 -> 0 | S19: =S18 -> 10175 | T19: =S19-S18 -> 0 | U19: =U18 -> 429166 | V19: =U19-U18 -> 0 | W19: =W18 -> 33311 | X19: =W19-W18 -> 0 | Y19: =Y18 -> 954830 | Z19: =Y19-Y18 -> 0 | AA19: =AA18 -> 36763 | AB19: =AA19-AA18 -> 0 | AC19: =AC18 -> 1162613 | AD19: =AC19-AC18 -> 0 | AE19: =AB19+X19+T19 -> 0 | AF19: =V19+Z19+AD19 -> 0 | AG19: =IF(AE19>0,AF19/AE19,0) -> 0 | AI19: =R19-'EDl log'!B19 -> -1095809 | AJ19: 44485 | AK19: =AK18 -> 1274972 | AL19: =AL18 -> 1598 | AM19: =AK19+AL19 -> 1276570 | AN19: =AM19-AM18 -> 0 | AO19: =G19+I19+K19+M19 -> 0 | AP19: =Q19+'EDl log'!C19 -> 0
A20: ='General information '!F21 -> 0 | B20: =SUM(230*A20) -> 0 | C20: 44486 | D20: =D19 -> 32911138 | E20: =AN20 -> 0 | F20: =F19 -> 4091226 | G20: =F20-F19 -> 0 | H20: =H19 -> 17968314 | I20: =H20-H19 -> 0 | J20: =J19 -> 29533148 | K20: =J20-J19 -> 0 | L20: =L19 -> 24433018 | M20: =L20-L19 -> 0 | N20: =M20+K20+I20+G20+E20 -> 0 | O20: =IF(B20>0,N20/B20,0) -> 0 | P20: =P19 -> 18418.3 | Q20: =(P20-P19)*1000 -> 0 | R20: =N20-Q20 -> 0 | S20: =S19 -> 10175 | T20: =S20-S19 -> 0 | U20: =U19 -> 429166 | V20: =U20-U19 -> 0 | W20: =W19 -> 33311 | X20: =W20-W19 -> 0 | Y20: =Y19 -> 954830 | Z20: =Y20-Y19 -> 0 | AA20: =AA19 -> 36763 | AB20: =AA20-AA19 -> 0 | AC20: =AC19 -> 1162613 | AD20: =AC20-AC19 -> 0 | AE20: =AB20+X20+T20 -> 0 | AF20: =V20+Z20+AD20 -> 0 | AG20: =IF(AE20>0,AF20/AE20,0) -> 0 | AI20: =R20-'EDl log'!B20 -> -1095809 | AJ20: 44486 | AK20: =AK19 -> 1274972 | AL20: =AL19 -> 1598 | AM20: =AK20+AL20 -> 1276570 | AN20: =AM20-AM19 -> 0 | AO20: =G20+I20+K20+M20 -> 0 | AP20: =Q20+'EDl log'!C20 -> 0
A21: ='General information '!F22 -> 0 | B21: =SUM(230*A21) -> 0 | C21: 44487 | D21: =D20 -> 32911138 | E21: =AN21 -> 0 | F21: =F20 -> 4091226 | G21: =F21-F20 -> 0 | H21: =H20 -> 17968314 | I21: =H21-H20 -> 0 | J21: =J20 -> 29533148 | K21: =J21-J20 -> 0 | L21: =L20 -> 24433018 | M21: =L21-L20 -> 0 | N21: =M21+K21+I21+G21+E21 -> 0 | O21: =IF(B21>0,N21/B21,0) -> 0 | P21: =P20 -> 18418.3 | Q21: =(P21-P20)*1000 -> 0 | R21: =N21-Q21 -> 0 | S21: =S20 -> 10175 | T21: =S21-S20 -> 0 | U21: =U20 -> 429166 | V21: =U21-U20 -> 0 | W21: =W20 -> 33311 | X21: =W21-W20 -> 0 | Y21: =Y20 -> 954830 | Z21: =Y21-Y20 -> 0 | AA21: =AA20 -> 36763 | AB21: =AA21-AA20 -> 0 | AC21: =AC20 -> 1162613 | AD21: =AC21-AC20 -> 0 | AE21: =AB21+X21+T21 -> 0 | AF21: =V21+Z21+AD21 -> 0 | AG21: =IF(AE21>0,AF21/AE21,0) -> 0 | AI21: =R21-'EDl log'!B21 -> -1095809 | AJ21: 44487 | AK21: =AK20 -> 1274972 | AL21: =AL20 -> 1598 | AM21: =AK21+AL21 -> 1276570 | AN21: =AM21-AM20 -> 0 | AO21: =G21+I21+K21+M21 -> 0 | AP21: =Q21+'EDl log'!C21 -> 0
A22: ='General information '!F23 -> 0 | B22: =SUM(230*A22) -> 0 | C22: 44488 | D22: =D21 -> 32911138 | E22: =AN22 -> 0 | F22: =F21 -> 4091226 | G22: =F22-F21 -> 0 | H22: =H21 -> 17968314 | I22: =H22-H21 -> 0 | J22: =J21 -> 29533148 | K22: =J22-J21 -> 0 | L22: =L21 -> 24433018 | M22: =L22-L21 -> 0 | N22: =M22+K22+I22+G22+E22 -> 0 | O22: =IF(B22>0,N22/B22,0) -> 0 | P22: =P21 -> 18418.3 | Q22: =(P22-P21)*1000 -> 0 | R22: =N22-Q22 -> 0 | S22: =S21 -> 10175 | T22: =S22-S21 -> 0 | U22: =U21 -> 429166 | V22: =U22-U21 -> 0 | W22: =W21 -> 33311 | X22: =W22-W21 -> 0 | Y22: =Y21 -> 954830 | Z22: =Y22-Y21 -> 0 | AA22: =AA21 -> 36763 | AB22: =AA22-AA21 -> 0 | AC22: =AC21 -> 1162613 | AD22: =AC22-AC21 -> 0 | AE22: =AB22+X22+T22 -> 0 | AF22: =V22+Z22+AD22 -> 0 | AG22: =IF(AE22>0,AF22/AE22,0) -> 0 | AI22: =R22-'EDl log'!B22 -> -1095809 | AJ22: 44488 | AK22: =AK21 -> 1274972 | AL22: =AL21 -> 1598 | AM22: =AK22+AL22 -> 1276570 | AN22: =AM22-AM21 -> 0 | AO22: =G22+I22+K22+M22 -> 0 | AP22: =Q22+'EDl log'!C22 -> 0
A23: ='General information '!F24 -> 0 | B23: =SUM(230*A23) -> 0 | C23: 44489 | D23: =D22 -> 32911138 | E23: =AN23 -> 0 | F23: =F22 -> 4091226 | G23: =F23-F22 -> 0 | H23: =H22 -> 17968314 | I23: =H23-H22 -> 0 | J23: =J22 -> 29533148 | K23: =J23-J22 -> 0 | L23: =L22 -> 24433018 | M23: =L23-L22 -> 0 | N23: =M23+K23+I23+G23+E23 -> 0 | O23: =IF(B23>0,N23/B23,0) -> 0 | P23: =P22 -> 18418.3 | Q23: =(P23-P22)*1000 -> 0 | R23: =AP23-Q23 -> 0 | S23: =S22 -> 10175 | T23: =S23-S22 -> 0 | U23: =U22 -> 429166 | V23: =U23-U22 -> 0 | W23: =W22 -> 33311 | X23: =W23-W22 -> 0 | Y23: =Y22 -> 954830 | Z23: =Y23-Y22 -> 0 | AA23: =AA22 -> 36763 | AB23: =AA23-AA22 -> 0 | AC23: =AC22 -> 1162613 | AD23: =AC23-AC22 -> 0 | AE23: =AB23+X23+T23 -> 0 | AF23: =V23+Z23+AD23 -> 0 | AG23: =IF(AE23>0,AF23/AE23,0) -> 0 | AI23: =R23-'EDl log'!B23 -> -1095809 | AJ23: 44489 | AK23: =AK22 -> 1274972 | AL23: =AL22 -> 1598 | AM23: =AK23+AL23 -> 1276570 | AN23: =AM23-AM22 -> 0 | AO23: =G23+I23+K23+M23 -> 0 | AP23: =Q23+'EDl log'!C23 -> 0
A24: ='General information '!F25 -> 0 | B24: =SUM(230*A24) -> 0 | C24: 44490 | D24: =D23 -> 32911138 | E24: =AN24 -> 0 | F24: =F23 -> 4091226 | G24: =F24-F23 -> 0 | H24: =H23 -> 17968314 | I24: =H24-H23 -> 0 | J24: =J23 -> 29533148 | K24: =J24-J23 -> 0 | L24: =L23 -> 24433018 | M24: =L24-L23 -> 0 | N24: =M24+K24+I24+G24+E24 -> 0 | O24: =IF(B24>0,N24/B24,0) -> 0 | P24: =P23 -> 18418.3 | Q24: =(P24-P23)*1000 -> 0 | R24: =N24-Q24 -> 0 | S24: =S23 -> 10175 | T24: =S24-S23 -> 0 | U24: =U23 -> 429166 | V24: =U24-U23 -> 0 | W24: =W23 -> 33311 | X24: =W24-W23 -> 0 | Y24: =Y23 -> 954830 | Z24: =Y24-Y23 -> 0 | AA24: =AA23 -> 36763 | AB24: =AA24-AA23 -> 0 | AC24: =AC23 -> 1162613 | AD24: =AC24-AC23 -> 0 | AE24: =AB24+X24+T24 -> 0 | AF24: =V24+Z24+AD24 -> 0 | AG24: =IF(AE24>0,AF24/AE24,0) -> 0 | AI24: =R24-'EDl log'!B24 -> -1095809 | AJ24: 44490 | AK24: =AK23 -> 1274972 | AL24: =AL23 -> 1598 | AM24: =AK24+AL24 -> 1276570 | AN24: =AM24-AM23 -> 0 | AO24: =G24+I24+K24+M24 -> 0 | AP24: =Q24+'EDl log'!C24 -> 0
A25: ='General information '!F26 -> 0 | B25: =SUM(230*A25) -> 0 | C25: 44491 | D25: =D24 -> 32911138 | E25: =AN25 -> 0 | F25: =F24 -> 4091226 | G25: =F25-F24 -> 0 | H25: =H24 -> 17968314 | I25: =H25-H24 -> 0 | J25: =J24 -> 29533148 | K25: =J25-J24 -> 0 | L25: =L24 -> 24433018 | M25: =L25-L24 -> 0 | N25: =M25+K25+I25+G25+E25 -> 0 | O25: =IF(B25>0,N25/B25,0) -> 0 | P25: =P24 -> 18418.3 | Q25: =(P25-P24)*1000 -> 0 | R25: =N25-Q25 -> 0 | S25: =S24 -> 10175 | T25: =S25-S24 -> 0 | U25: =U24 -> 429166 | V25: =U25-U24 -> 0 | W25: =W24 -> 33311 | X25: =W25-W24 -> 0 | Y25: =Y24 -> 954830 | Z25: =Y25-Y24 -> 0 | AA25: =AA24 -> 36763 | AB25: =AA25-AA24 -> 0 | AC25: =AC24 -> 1162613 | AD25: =AC25-AC24 -> 0 | AE25: =AB25+X25+T25 -> 0 | AF25: =V25+Z25+AD25 -> 0 | AG25: =IF(AE25>0,AF25/AE25,0) -> 0 | AI25: =R25-'EDl log'!B25 -> -1095809 | AJ25: 44491 | AK25: =AK24 -> 1274972 | AL25: =AL24 -> 1598 | AM25: =AK25+AL25 -> 1276570 | AN25: =AM25-AM24 -> 0 | AO25: =G25+I25+K25+M25 -> 0 | AP25: =Q25+'EDl log'!C25 -> 0
A26: ='General information '!F27 -> 0 | B26: =SUM(230*A26) -> 0 | C26: 44492 | D26: =D25 -> 32911138 | E26: =AN26 -> 0 | F26: =F25 -> 4091226 | G26: =F26-F25 -> 0 | H26: =H25 -> 17968314 | I26: =H26-H25 -> 0 | J26: =J25 -> 29533148 | K26: =J26-J25 -> 0 | L26: =L25 -> 24433018 | M26: =L26-L25 -> 0 | N26: =M26+K26+I26+G26+E26 -> 0 | O26: =IF(B26>0,N26/B26,0) -> 0 | P26: =P25 -> 18418.3 | Q26: =(P26-P25)*1000 -> 0 | R26: =N26-Q26 -> 0 | S26: =S25 -> 10175 | T26: =S26-S25 -> 0 | U26: =U25 -> 429166 | V26: =U26-U25 -> 0 | W26: =W25 -> 33311 | X26: =W26-W25 -> 0 | Y26: =Y25 -> 954830 | Z26: =Y26-Y25 -> 0 | AA26: =AA25 -> 36763 | AB26: =AA26-AA25 -> 0 | AC26: =AC25 -> 1162613 | AD26: =AC26-AC25 -> 0 | AE26: =AB26+X26+T26 -> 0 | AF26: =V26+Z26+AD26 -> 0 | AG26: =IF(AE26>0,AF26/AE26,0) -> 0 | AI26: =R26-'EDl log'!B26 -> -1095809 | AJ26: 44492 | AK26: =AK25 -> 1274972 | AL26: =AL25 -> 1598 | AM26: =AK26+AL26 -> 1276570 | AN26: =AM26-AM25 -> 0 | AO26: =G26+I26+K26+M26 -> 0 | AP26: =Q26+'EDl log'!C26 -> 0
A27: ='General information '!F28 -> 0 | B27: =SUM(230*A27) -> 0 | C27: 44493 | D27: =D26 -> 32911138 | E27: =AN27 -> 0 | F27: =F26 -> 4091226 | G27: =F27-F26 -> 0 | H27: =H26 -> 17968314 | I27: =H27-H26 -> 0 | J27: =J26 -> 29533148 | K27: =J27-J26 -> 0 | L27: =L26 -> 24433018 | M27: =L27-L26 -> 0 | N27: =M27+K27+I27+G27+E27 -> 0 | O27: =IF(B27>0,N27/B27,0) -> 0 | P27: =P26 -> 18418.3 | Q27: =(P27-P26)*1000 -> 0 | R27: =N27-Q27 -> 0 | S27: =S26 -> 10175 | T27: =S27-S26 -> 0 | U27: =U26 -> 429166 | V27: =U27-U26 -> 0 | W27: =W26 -> 33311 | X27: =W27-W26 -> 0 | Y27: =Y26 -> 954830 | Z27: =Y27-Y26 -> 0 | AA27: =AA26 -> 36763 | AB27: =AA27-AA26 -> 0 | AC27: =AC26 -> 1162613 | AD27: =AC27-AC26 -> 0 | AE27: =AB27+X27+T27 -> 0 | AF27: =V27+Z27+AD27 -> 0 | AG27: =IF(AE27>0,AF27/AE27,0) -> 0 | AI27: =R27-'EDl log'!B27 -> -1095809 | AJ27: 44493 | AK27: =AK26 -> 1274972 | AL27: =AL26 -> 1598 | AM27: =AK27+AL27 -> 1276570 | AN27: =AM27-AM26 -> 0 | AO27: =G27+I27+K27+M27 -> 0 | AP27: =Q27+'EDl log'!C27 -> 0
A28: ='General information '!F29 -> 0 | B28: =SUM(230*A28) -> 0 | C28: 44494 | D28: =D27 -> 32911138 | E28: =AN28 -> 0 | F28: =F27 -> 4091226 | G28: =F28-F27 -> 0 | H28: =H27 -> 17968314 | I28: =H28-H27 -> 0 | J28: =J27 -> 29533148 | K28: =J28-J27 -> 0 | L28: =L27 -> 24433018 | M28: =L28-L27 -> 0 | N28: =M28+K28+I28+G28+E28 -> 0 | O28: =IF(B28>0,N28/B28,0) -> 0 | P28: =P27 -> 18418.3 | Q28: =(P28-P27)*1000 -> 0 | R28: =N28-Q28 -> 0 | S28: =S27 -> 10175 | T28: =S28-S27 -> 0 | U28: =U27 -> 429166 | V28: =U28-U27 -> 0 | W28: =W27 -> 33311 | X28: =W28-W27 -> 0 | Y28: =Y27 -> 954830 | Z28: =Y28-Y27 -> 0 | AA28: =AA27 -> 36763 | AB28: =AA28-AA27 -> 0 | AC28: =AC27 -> 1162613 | AD28: =AC28-AC27 -> 0 | AE28: =AB28+X28+T28 -> 0 | AF28: =V28+Z28+AD28 -> 0 | AG28: =IF(AE28>0,AF28/AE28,0) -> 0 | AI28: =R28-'EDl log'!B28 -> -1095809 | AJ28: 44494 | AK28: =AK27 -> 1274972 | AL28: =AL27 -> 1598 | AM28: =AK28+AL28 -> 1276570 | AN28: =AM28-AM27 -> 0 | AO28: =G28+I28+K28+M28 -> 0 | AP28: =Q28+'EDl log'!C28 -> 0
A29: ='General information '!F30 -> 0 | B29: =SUM(230*A29) -> 0 | C29: 44495 | D29: =D28 -> 32911138 | E29: =AN29 -> 0 | F29: =F28 -> 4091226 | G29: =F29-F28 -> 0 | H29: =H28 -> 17968314 | I29: =H29-H28 -> 0 | J29: =J28 -> 29533148 | K29: =J29-J28 -> 0 | L29: =L28 -> 24433018 | M29: =L29-L28 -> 0 | N29: =M29+K29+I29+G29+E29 -> 0 | O29: =IF(B29>0,N29/B29,0) -> 0 | P29: =P28 -> 18418.3 | Q29: =(P29-P28)*1000 -> 0 | R29: =N29-Q29 -> 0 | S29: =S28 -> 10175 | T29: =S29-S28 -> 0 | U29: =U28 -> 429166 | V29: =U29-U28 -> 0 | W29: =W28 -> 33311 | X29: =W29-W28 -> 0 | Y29: =Y28 -> 954830 | Z29: =Y29-Y28 -> 0 | AA29: =AA28 -> 36763 | AB29: =AA29-AA28 -> 0 | AC29: =AC28 -> 1162613 | AD29: =AC29-AC28 -> 0 | AE29: =AB29+X29+T29 -> 0 | AF29: =V29+Z29+AD29 -> 0 | AG29: =IF(AE29>0,AF29/AE29,0) -> 0 | AI29: =R29-'EDl log'!B29 -> -1095809 | AJ29: 44495 | AK29: =AK28 -> 1274972 | AL29: =AL28 -> 1598 | AM29: =AK29+AL29 -> 1276570 | AN29: =AM29-AM28 -> 0 | AO29: =G29+I29+K29+M29 -> 0 | AP29: =Q29+'EDl log'!C29 -> 0
A30: ='General information '!F31 -> 0 | B30: =SUM(230*A30) -> 0 | C30: 44496 | D30: =D29 -> 32911138 | E30: =AN30 -> 0 | F30: =F29 -> 4091226 | G30: =F30-F29 -> 0 | H30: =H29 -> 17968314 | I30: =H30-H29 -> 0 | J30: =J29 -> 29533148 | K30: =J30-J29 -> 0 | L30: =L29 -> 24433018 | M30: =L30-L29 -> 0 | N30: =M30+K30+I30+G30+E30 -> 0 | O30: =IF(B30>0,N30/B30,0) -> 0 | P30: =P29 -> 18418.3 | Q30: =(P30-P29)*1000 -> 0 | R30: =N30-Q30 -> 0 | S30: =S29 -> 10175 | T30: =S30-S29 -> 0 | U30: =U29 -> 429166 | V30: =U30-U29 -> 0 | W30: =W29 -> 33311 | X30: =W30-W29 -> 0 | Y30: =Y29 -> 954830 | Z30: =Y30-Y29 -> 0 | AA30: =AA29 -> 36763 | AB30: =AA30-AA29 -> 0 | AC30: =AC29 -> 1162613 | AD30: =AC30-AC29 -> 0 | AE30: =AB30+X30+T30 -> 0 | AF30: =V30+Z30+AD30 -> 0 | AG30: =IF(AE30>0,AF30/AE30,0) -> 0 | AI30: =R30-'EDl log'!B30 -> -1095809 | AJ30: 44496 | AK30: =AK29 -> 1274972 | AL30: =AL29 -> 1598 | AM30: =AK30+AL30 -> 1276570 | AN30: =AM30-AM29 -> 0 | AO30: =G30+I30+K30+M30 -> 0 | AP30: =Q30+'EDl log'!C30 -> 0
A31: ='General information '!F32 -> 0 | B31: =SUM(230*A31) -> 0 | C31: 44497 | D31: =D30 -> 32911138 | E31: =AN31 -> 0 | F31: =F30 -> 4091226 | G31: =F31-F30 -> 0 | H31: =H30 -> 17968314 | I31: =H31-H30 -> 0 | J31: =J30 -> 29533148 | K31: =J31-J30 -> 0 | L31: =L30 -> 24433018 | M31: =L31-L30 -> 0 | N31: =M31+K31+I31+G31+E31 -> 0 | O31: =IF(B31>0,N31/B31,0) -> 0 | P31: =P30 -> 18418.3 | Q31: =(P31-P30)*1000 -> 0 | R31: =N31-Q31 -> 0 | S31: =S30 -> 10175 | T31: =S31-S30 -> 0 | U31: =U30 -> 429166 | V31: =U31-U30 -> 0 | W31: =W30 -> 33311 | X31: =W31-W30 -> 0 | Y31: =Y30 -> 954830 | Z31: =Y31-Y30 -> 0 | AA31: =AA30 -> 36763 | AB31: =AA31-AA30 -> 0 | AC31: =AC30 -> 1162613 | AD31: =AC31-AC30 -> 0 | AE31: =AB31+X31+T31 -> 0 | AF31: =V31+Z31+AD31 -> 0 | AG31: =IF(AE31>0,AF31/AE31,0) -> 0 | AI31: =R31-'EDl log'!B31 -> -1095809 | AJ31: 44497 | AK31: =AK30 -> 1274972 | AL31: =AL30 -> 1598 | AM31: =AK31+AL31 -> 1276570 | AN31: =AM31-AM30 -> 0 | AO31: =G31+I31+K31+M31 -> 0 | AP31: =Q31+'EDl log'!C31 -> 0
A32: ='General information '!F33 -> 0 | B32: =SUM(230*A32) -> 0 | C32: 44498 | D32: =D31 -> 32911138 | E32: =AN32 -> 0 | F32: =F31 -> 4091226 | G32: =F32-F31 -> 0 | H32: =H31 -> 17968314 | I32: =H32-H31 -> 0 | J32: =J31 -> 29533148 | K32: =J32-J31 -> 0 | L32: =L31 -> 24433018 | M32: =L32-L31 -> 0 | N32: =M32+K32+I32+G32+E32 -> 0 | O32: =IF(B32>0,N32/B32,0) -> 0 | P32: =P31 -> 18418.3 | Q32: =(P32-P31)*1000 -> 0 | R32: =N32-Q32 -> 0 | S32: =S31 -> 10175 | T32: =S32-S31 -> 0 | U32: =U31 -> 429166 | V32: =U32-U31 -> 0 | W32: =W31 -> 33311 | X32: =W32-W31 -> 0 | Y32: =Y31 -> 954830 | Z32: =Y32-Y31 -> 0 | AA32: =AA31 -> 36763 | AB32: =AA32-AA31 -> 0 | AC32: =AC31 -> 1162613 | AD32: =AC32-AC31 -> 0 | AE32: =AB32+X32+T32 -> 0 | AF32: =V32+Z32+AD32 -> 0 | AG32: =IF(AE32>0,AF32/AE32,0) -> 0 | AI32: =R32-'EDl log'!B32 -> -1095809 | AJ32: 44498 | AK32: =AK31 -> 1274972 | AL32: =AL31 -> 1598 | AM32: =AK32+AL32 -> 1276570 | AN32: =AM32-AM31 -> 0 | AO32: =G32+I32+K32+M32 -> 0 | AP32: =Q32+'EDl log'!C32 -> 0
A33: ='General information '!F34 -> 0 | B33: =SUM(230*A33) -> 0 | C33: 44499 | D33: =D32 -> 32911138 | E33: =AN33 -> 0 | F33: =F32 -> 4091226 | G33: =F33-F32 -> 0 | H33: =H32 -> 17968314 | I33: =H33-H32 -> 0 | J33: =J32 -> 29533148 | K33: =J33-J32 -> 0 | L33: =L32 -> 24433018 | M33: =L33-L32 -> 0 | N33: =M33+K33+I33+G33+E33 -> 0 | O33: =IF(B33>0,N33/B33,0) -> 0 | P33: =P32 -> 18418.3 | Q33: =(P33-P32)*1000 -> 0 | R33: =N33-Q33 -> 0 | S33: =S32 -> 10175 | T33: =S33-S32 -> 0 | U33: =U32 -> 429166 | V33: =U33-U32 -> 0 | W33: =W32 -> 33311 | X33: =W33-W32 -> 0 | Y33: =Y32 -> 954830 | Z33: =Y33-Y32 -> 0 | AA33: =AA32 -> 36763 | AB33: =AA33-AA32 -> 0 | AC33: =AC32 -> 1162613 | AD33: =AC33-AC32 -> 0 | AE33: =AB33+X33+T33 -> 0 | AF33: =V33+Z33+AD33 -> 0 | AG33: =IF(AE33>0,AF33/AE33,0) -> 0 | AI33: =R33-'EDl log'!B33 -> -1095809 | AJ33: 44499 | AK33: =AK32 -> 1274972 | AL33: =AL32 -> 1598 | AM33: =AK33+AL33 -> 1276570 | AN33: =AM33-AM32 -> 0 | AO33: =G33+I33+K33+M33 -> 0 | AP33: =Q33+'EDl log'!C33 -> 0
A34: ='General information '!F35 -> 0 | B34: =SUM(230*A34) -> 0 | C34: 44500 | D34: =D33 -> 32911138 | E34: =AN34 -> 0 | F34: =F33 -> 4091226 | G34: =F34-F33 -> 0 | H34: =H33 -> 17968314 | I34: =H34-H33 -> 0 | J34: =J33 -> 29533148 | K34: =J34-J33 -> 0 | L34: =L33 -> 24433018 | M34: =L34-L33 -> 0 | N34: =M34+K34+I34+G34+E34 -> 0 | O34: =IF(B34>0,N34/B34,0) -> 0 | P34: =P33 -> 18418.3 | Q34: =(P34-P33)*1000 -> 0 | R34: =N34-Q34 -> 0 | S34: =S33 -> 10175 | T34: =S34-S33 -> 0 | U34: =U33 -> 429166 | V34: =U34-U33 -> 0 | W34: =W33 -> 33311 | X34: =W34-W33 -> 0 | Y34: =Y33 -> 954830 | Z34: =Y34-Y33 -> 0 | AA34: =AA33 -> 36763 | AB34: =AA34-AA33 -> 0 | AC34: =AC33 -> 1162613 | AD34: =AC34-AC33 -> 0 | AE34: =AB34+X34+T34 -> 0 | AF34: =V34+Z34+AD34 -> 0 | AG34: =IF(AE34>0,AF34/AE34,0) -> 0 | AI34: =R34-'EDl log'!B34 -> -1095809 | AJ34: 44500 | AK34: =AK33 -> 1274972 | AL34: =AL33 -> 1598 | AM34: =AK34+AL34 -> 1276570 | AN34: =AM34-AM33 -> 0 | AO34: =G34+I34+K34+M34 -> 0 | AP34: =Q34+'EDl log'!C34 -> 0

Sheet B5
F1: Boiler A | J1: =J36 -> 41 | K1: Boiler B | P1: Boiler C | V1: Boiler | X1: SteamA | AC1: SteamB | AH1: Steam | AI1: Boiler & steam | AL1: Total Boiler Runing H | AM1: Total Steam Runing H | AN1: GAS1 % | AO1: GAS1/L | AP1: GAS2% | AQ1: Gas2/L | AR1: GAS3% | AS1: GAS3/L | AU1: Gas Cons | AV1: Delivery | AW1: Cost/L
B2: Level Tank Gen | C2: Level tank Boiler | D2: Daily Cons Bo. | E2: Boiler litter | F2: Boiler A | G2: Run Hr a | H2: Boiler A fuel | I2: Daily consumption | J2: AVG | K2: index Run H | L2: Run Hrb | M2: Boiler B Fuel | O2: Daily consumption | P2: Boiler C | S2: Run C | U2: Total RH | V2: Total Fuel | X2: SteamA | Y2: Run SA | Z2: Steam A Conter | AA2: Liters | AC2: SteamB | AD2: Run SteamB | AE2: Steam B Conter | AF2: SB Litters | AG2: Avg | AH2: Total Fuel | AI2: Total Fuel
S3: 0
A4: =ELEC!C3 -> 44469 | B4: =[2]B5!B34 -> 146 | C4: =[2]B5!C34 -> 153 | D4: =[2]B5!D34 -> 7 | E4: =[2]B5!E34 -> 58.66 | F4: =[2]B5!F34 -> 1890 | G4: =[2]B5!G34 -> 1 | H4: =[2]B5!H34 -> 17095 | I4: =[2]B5!I34 -> 57 | ... AX4: =[2]B5!AX34 -> 0.8
A5: =ELEC!C4 -> 44470 | B5: =B4 -> 146 | C5: =C4 -> 153 | D5: =C4-C5 -> 0 | E5: =D5*8.38 -> 0 | F5: =F4 -> 1890 | G5: =F5-F4 -> 0 | H5: =H4 -> 17095 | I5: =SUM(H5-H4) -> 0 | J5: 1 | K5: =K4 -> 2356 | L5: =K5-K4 -> 0 | M5: =M4 -> 173915 | N5: =M5-M4 -> 0 | O5: =O4 -> 1869 | P5: =P4 -> 2129 | Q5: =Q4 -> 178720 | R5: =Q5-Q4 -> 0 | S5: =SUM(P5-P4) -> 0 | T5: =SUM(S5*$T$2) -> 0 | U5: =SUM(G5+L5+S5) -> 0 | V5: =R5+N5+I5:I5 -> 0 | W5: =SUM(V5/U5) -> #DIV/0! | X5: =X4 -> 2470 | Y5: =X5-X4 -> 0 | Z5: =Z4 -> 139138.1 | AA5: =Z5-Z4 -> 0 | AB5: =SUM(Y5*$AB$2) -> 0 | AC5: =AC4 -> 1942 | AD5: =AC5-AC4 -> 0 | AE5: =AE4 -> 366072 | AF5: =AE5-AE4 -> 0 | AG5: =IF(AD5>0,AF5/AD5,0) -> 0 | AH5: =AF5+AA5 -> 0 | AI5: =SUM(AH5+V5) -> 0 | AJ5: =-tanks!AW6 -> 0 | AK5: =SUM(AJ5-AI5) -> 0 | AL5: =S5+L5+G5 -> 0 | AM5: =Y5+AD5 -> 0 | AN5: =AN4 -> 65 | AO5: =(AN5/100)*3000 -> 1950 | AP5: =AP4 -> 55 | AQ5: =(AP5/100)*3000 -> 1650 | AR5: =AR4 -> 61 | AS5: =(AR5/100)*3000 -> 1830 | AT5: =SUM(AO5+AQ5+AS5) -> 5430 | AU5: =AT4-AT5+AV5 -> 0 | AX5: =IF(AV5>0,AW5,AX4) -> 0.8
A6: =ELEC!C5 -> 44471 | B6: =B5 -> 146 | C6: =C5 -> 153 | D6: =C5-C6 -> 0 | E6: =D6*8.38 -> 0 | F6: =F5 -> 1890 | G6: =F6-F5 -> 0 | H6: =H5 -> 17095 | I6: =SUM(H6-H5) -> 0 | J6: =IF(G6>0,I6/G6,0) -> 0 | K6: =K5 -> 2356 | L6: =K6-K5 -> 0 | M6: =M5 -> 173915 | N6: =M6-M5 -> 0 | O6: =O5 -> 1869 | P6: =P5 -> 2129 | Q6: =Q5 -> 178720 | R6: =Q6-Q5 -> 0 | S6: =SUM(P6-P5) -> 0 | T6: =SUM(S6*$T$2) -> 0 | U6: =SUM(G6+L6+S6) -> 0 | V6: =R6+N6+I6:I6 -> 0 | W6: =SUM(V6/U6) -> #DIV/0! | X6: =X5 -> 2470 | Y6: =X6-X5 -> 0 | Z6: =Z5 -> 139138.1 | AA6: =Z6-Z5 -> 0 | AB6: =SUM(Y6*$AB$2) -> 0 | AC6: =AC5 -> 1942 | AD6: =AC6-AC5 -> 0 | AE6: =AE5 -> 366072 | AF6: =AE6-AE5 -> 0 | AG6: =IF(AD6>0,AF6/AD6,0) -> 0 | AH6: =AF6+AA6 -> 0 | AI6: =SUM(AH6+V6) -> 0 | AJ6: =-tanks!AW7 -> 0 | AK6: =SUM(AJ6-AI6) -> 0 | AL6: =S6+L6+G6 -> 0 | AM6: =Y6+AD6 -> 0 | AN6: =AN5 -> 65 | AO6: =(AN6/100)*3000 -> 1950 | AP6: =AP5 -> 55 | AQ6: =(AP6/100)*3000 -> 1650 | AR6: =AR5 -> 61 | AS6: =(AR6/100)*3000 -> 1830 | AT6: =SUM(AO6+AQ6+AS6) -> 5430 | AU6: =AT5-AT6+AV6 -> 0 | AX6: =IF(AV6>0,AW6,AX5) -> 0.8
A7: =ELEC!C6 -> 44472 | B7: 157 | C7: 164 | D7: =C6-C7 -> -11 | E7: =D7*8.38 -> -92.18 | F7: 1891 | G7: =F7-F6 -> 1 | H7: 17176 | I7: =SUM(H7-H6) -> 81 | J7: =IF(G7>0,I7/G7,0) -> 81 | K7: =K6 -> 2356 | L7: =K7-K6 -> 0 | M7: =M6 -> 173915 | N7: =M7-M6 -> 0 | O7: =O6 -> 1869 | P7: =P6 -> 2129 | Q7: =Q6 -> 178720 | R7: =Q7-Q6 -> 0 | S7: =SUM(P7-P6) -> 0 | T7: =SUM(S7*$T$2) -> 0 | U7: =SUM(G7+L7+S7) -> 1 | V7: =R7+N7+I7:I7 -> 81 | W7: =SUM(V7/U7) -> 81 | X7: =X6 -> 2470 | Y7: =X7-X6 -> 0 | Z7: =Z6 -> 139138.1 | AA7: =Z7-Z6 -> 0 | AB7: =SUM(Y7*$AB$2) -> 0 | AC7: =AC6 -> 1942 | AD7: =AC7-AC6 -> 0 | AE7: =AE6 -> 366072 | AF7: =AE7-AE6 -> 0 | AG7: =IF(AD7>0,AF7/AD7,0) -> 0 | AH7: =AF7+AA7 -> 0 | AI7: =SUM(AH7+V7) -> 81 | AJ7: =-tanks!AW8 -> 81 | AK7: =SUM(AJ7-AI7) -> 0 | AL7: =S7+L7+G7 -> 1 | AM7: =Y7+AD7 -> 0 | AN7: =AN6 -> 65 | AO7: =(AN7/100)*3000 -> 1950 | AP7: =AP6 -> 55 | AQ7: =(AP7/100)*3000 -> 1650 | AR7: =AR6 -> 61 | AS7: =(AR7/100)*3000 -> 1830 | AT7: =SUM(AO7+AQ7+AS7) -> 5430 | AU7: =AT6-AT7+AV7 -> 0 | AX7: =IF(AV7>0,AW7,AX6) -> 0.8
A8: =ELEC!C7 -> 44473 | B8: =B7 -> 157 | C8: =C7 -> 164 | D8: =C7-C8 -> 0 | E8: =D8*8.38 -> 0 | F8: =F7 -> 1891 | G8: =F8-F7 -> 0 | H8: =H7 -> 17176 | I8: =SUM(H8-H7) -> 0 | J8: =IF(G8>0,I8/G8,0) -> 0 | K8: =K7 -> 2356 | L8: =K8-K7 -> 0 | M8: =M7 -> 173915 | N8: =M8-M7 -> 0 | O8: =O7 -> 1869 | P8: =P7 -> 2129 | Q8: =Q7 -> 178720 | R8: =Q8-Q7 -> 0 | S8: =SUM(P8-P7) -> 0 | T8: =SUM(S8*$T$2) -> 0 | U8: =SUM(G8+L8+S8) -> 0 | V8: =R8+N8+I8:I8 -> 0 | W8: =SUM(V8/U8) -> #DIV/0! | X8: =X7 -> 2470 | Y8: =X8-X7 -> 0 | Z8: =Z7 -> 139138.1 | AA8: =Z8-Z7 -> 0 | AB8: =SUM(Y8*$AB$2) -> 0 | AC8: =AC7 -> 1942 | AD8: =AC8-AC7 -> 0 | AE8: =AE7 -> 366072 | AF8: =AE8-AE7 -> 0 | AG8: =IF(AD8>0,AF8/AD8,0) -> 0 | AH8: =AF8+AA8 -> 0 | AI8: =SUM(AH8+V8) -> 0 | AJ8: =-tanks!AW9 -> 0 | AK8: =SUM(AJ8-AI8) -> 0 | AL8: =S8+L8+G8 -> 0 | AM8: =Y8+AD8 -> 0 | AN8: =AN7 -> 65 | AO8: =(AN8/100)*3000 -> 1950 | AP8: =AP7 -> 55 | AQ8: =(AP8/100)*3000 -> 1650 | AR8: =AR7 -> 61 | AS8: =(AR8/100)*3000 -> 1830 | AT8: =SUM(AO8+AQ8+AS8) -> 5430 | AU8: =AT7-AT8+AV8 -> 0 | AX8: =IF(AV8>0,AW8,AX7) -> 0.8
A9: =ELEC!C8 -> 44474 | B9: =B8 -> 157 | C9: =C8 -> 164 | D9: =C8-C9 -> 0 | E9: =D9*8.38 -> 0 | F9: =F8 -> 1891 | G9: =F9-F8 -> 0 | H9: =H8 -> 17176 | I9: =SUM(H9-H8) -> 0 | J9: =IF(G9>0,I9/G9,0) -> 0 | K9: =K8 -> 2356 | L9: =K9-K8 -> 0 | M9: =M8 -> 173915 | N9: =M9-M8 -> 0 | O9: =O8 -> 1869 | P9: =P8 -> 2129 | Q9: =Q8 -> 178720 | R9: =Q9-Q8 -> 0 | S9: =SUM(P9-P8) -> 0 | T9: =SUM(S9*$T$2) -> 0 | U9: =SUM(G9+L9+S9) -> 0 | V9: =R9+N9+I9:I9 -> 0 | W9: =SUM(V9/U9) -> #DIV/0! | X9: =X8 -> 2470 | Y9: =X9-X8 -> 0 | Z9: =Z8 -> 139138.1 | AA9: =Z9-Z8 -> 0 | AB9: =SUM(Y9*$AB$2) -> 0 | AC9: =AC8 -> 1942 | AD9: =AC9-AC8 -> 0 | AE9: =AE8 -> 366072 | AF9: =AE9-AE8 -> 0 | AG9: =IF(AD9>0,AF9/AD9,0) -> 0 | AH9: =AF9+AA9 -> 0 | AI9: =SUM(AH9+V9) -> 0 | AJ9: =-tanks!AW10 -> 0 | AK9: =SUM(AJ9-AI9) -> 0 | AL9: =S9+L9+G9 -> 0 | AM9: =Y9+AD9 -> 0 | AN9: =AN8 -> 65 | AO9: =(AN9/100)*3000 -> 1950 | AP9: =AP8 -> 55 | AQ9: =(AP9/100)*3000 -> 1650 | AR9: =AR8 -> 61 | AS9: =(AR9/100)*3000 -> 1830 | AT9: =SUM(AO9+AQ9+AS9) -> 5430 | AU9: =AT8-AT9+AV9 -> 0 | AX9: =IF(AV9>0,AW9,AX8) -> 0.8
A10: =ELEC!C9 -> 44475 | B10: =B9 -> 157 | C10: =C9 -> 164 | D10: =C9-C10 -> 0 | E10: =D10*8.38 -> 0 | F10: =F9 -> 1891 | G10: =F10-F9 -> 0 | H10: =H9 -> 17176 | I10: =SUM(H10-H9) -> 0 | J10: =IF(G10>0,I10/G10,0) -> 0 | K10: =K9 -> 2356 | L10: =K10-K9 -> 0 | M10: =M9 -> 173915 | N10: =M10-M9 -> 0 | O10: =O9 -> 1869 | P10: =P9 -> 2129 | Q10: =Q9 -> 178720 | R10: =Q10-Q9 -> 0 | S10: =SUM(P10-P9) -> 0 | T10: =SUM(S10*$T$2) -> 0 | U10: =SUM(G10+L10+S10) -> 0 | V10: =R10+N10+I10:I10 -> 0 | W10: =SUM(V10/U10) -> #DIV/0! | X10: =X9 -> 2470 | Y10: =X10-X9 -> 0 | Z10: =Z9 -> 139138.1 | AA10: =Z10-Z9 -> 0 | AB10: =SUM(Y10*$AB$2) -> 0 | AC10: =AC9 -> 1942 | AD10: =AC10-AC9 -> 0 | AE10: =AE9 -> 366072 | AF10: =AE10-AE9 -> 0 | AG10: =IF(AD10>0,AF10/AD10,0) -> 0 | AH10: =AF10+AA10 -> 0 | AI10: =SUM(AH10+V10) -> 0 | AJ10: =-tanks!AW11 -> 0 | AK10: =SUM(AJ10-AI10) -> 0 | AL10: =S10+L10+G10 -> 0 | AM10: =Y10+AD10 -> 0 | AN10: =AN9 -> 65 | AO10: =(AN10/100)*3000 -> 1950 | AP10: =AP9 -> 55 | AQ10: =(AP10/100)*3000 -> 1650 | AR10: =AR9 -> 61 | AS10: =(AR10/100)*3000 -> 1830 | AT10: =SUM(AO10+AQ10+AS10) -> 5430 | AU10: =AT9-AT10+AV10 -> 0 | AX10: =IF(AV10>0,AW10,AX9) -> 0.8
A11: =ELEC!C10 -> 44476 | B11: =B10 -> 157 | C11: =C10 -> 164 | D11: =C10-C11 -> 0 | E11: =D11*8.38 -> 0 | F11: =F10 -> 1891 | G11: =F11-F10 -> 0 | H11: =H10 -> 17176 | I11: =SUM(H11-H10) -> 0 | J11: =IF(G11>0,I11/G11,0) -> 0 | K11: =K10 -> 2356 | L11: =K11-K10 -> 0 | M11: =M10 -> 173915 | N11: =M11-M10 -> 0 | O11: =O10 -> 1869 | P11: =P10 -> 2129 | Q11: =Q10 -> 178720 | R11: =Q11-Q10 -> 0 | S11: =SUM(P11-P10) -> 0 | T11: =SUM(S11*$T$2) -> 0 | U11: =SUM(G11+L11+S11) -> 0 | V11: =R11+N11+I11:I11 -> 0 | W11: =SUM(V11/U11) -> #DIV/0! | X11: =X10 -> 2470 | Y11: =X11-X10 -> 0 | Z11: =Z10 -> 139138.1 | AA11: =Z11-Z10 -> 0 | AB11: =SUM(Y11*$AB$2) -> 0 | AC11: =AC10 -> 1942 | AD11: =AC11-AC10 -> 0 | AE11: =AE10 -> 366072 | AF11: =AE11-AE10 -> 0 | AG11: =IF(AD11>0,AF11/AD11,0) -> 0 | AH11: =AF11+AA11 -> 0 | AI11: =SUM(AH11+V11) -> 0 | AJ11: =-tanks!AW12 -> 0 | AK11: =SUM(AJ11-AI11) -> 0 | AL11: =S11+L11+G11 -> 0 | AM11: =Y11+AD11 -> 0 | AN11: =AN10 -> 65 | AO11: =(AN11/100)*3000 -> 1950 | AP11: =AP10 -> 55 | AQ11: =(AP11/100)*3000 -> 1650 | AR11: =AR10 -> 61 | AS11: =(AR11/100)*3000 -> 1830 | AT11: =SUM(AO11+AQ11+AS11) -> 5430 | AU11: =AT10-AT11+AV11 -> 0 | AX11: =IF(AV11>0,AW11,AX10) -> 0.8
A12: =ELEC!C11 -> 44477 | B12: =B11 -> 157 | C12: =C11 -> 164 | D12: =C11-C12 -> 0 | E12: =D12*8.38 -> 0 | F12: =F11 -> 1891 | G12: =F12-F11 -> 0 | H12: =H11 -> 17176 | I12: =SUM(H12-H11) -> 0 | J12: =IF(G12>0,I12/G12,0) -> 0 | K12: =K11 -> 2356 | L12: =K12-K11 -> 0 | M12: =M11 -> 173915 | N12: =M12-M11 -> 0 | O12: =O11 -> 1869 | P12: =P11 -> 2129 | Q12: =Q11 -> 178720 | R12: =Q12-Q11 -> 0 | S12: =SUM(P12-P11) -> 0 | T12: =SUM(S12*$T$2) -> 0 | U12: =SUM(G12+L12+S12) -> 0 | V12: =R12+N12+I12:I12 -> 0 | W12: =SUM(V12/U12) -> #DIV/0! | X12: =X11 -> 2470 | Y12: =X12-X11 -> 0 | Z12: =Z11 -> 139138.1 | AA12: =Z12-Z11 -> 0 | AB12: =SUM(Y12*$AB$2) -> 0 | AC12: =AC11 -> 1942 | AD12: =AC12-AC11 -> 0 | AE12: =AE11 -> 366072 | AF12: =AE12-AE11 -> 0 | AG12: =IF(AD12>0,AF12/AD12,0) -> 0 | AH12: =AF12+AA12 -> 0 | AI12: =SUM(AH12+V12) -> 0 | AJ12: =-tanks!AW13 -> 0 | AK12: =SUM(AJ12-AI12) -> 0 | AL12: =S12+L12+G12 -> 0 | AM12: =Y12+AD12 -> 0 | AN12: =AN11 -> 65 | AO12: =(AN12/100)*3000 -> 1950 | AP12: =AP11 -> 55 | AQ12: =(AP12/100)*3000 -> 1650 | AR12: =AR11 -> 61 | AS12: =(AR12/100)*3000 -> 1830 | AT12: =SUM(AO12+AQ12+AS12) -> 5430 | AU12: =AT11-AT12+AV12 -> 0 | AX12: =IF(AV12>0,AW12,AX11) -> 0.8
A13: =ELEC!C12 -> 44478 | B13: =B12 -> 157 | C13: =C12 -> 164 | D13: =C12-C13 -> 0 | E13: =D13*8.38 -> 0 | F13: =F12 -> 1891 | G13: =F13-F12 -> 0 | H13: =H12 -> 17176 | I13: =SUM(H13-H12) -> 0 | J13: =IF(G13>0,I13/G13,0) -> 0 | K13: =K12 -> 2356 | L13: =K13-K12 -> 0 | M13: =M12 -> 173915 | N13: =M13-M12 -> 0 | O13: =O12 -> 1869 | P13: =P12 -> 2129 | Q13: =Q12 -> 178720 | R13: =Q13-Q12 -> 0 | S13: =SUM(P13-P12) -> 0 | T13: =SUM(S13*$T$2) -> 0 | U13: =SUM(G13+L13+S13) -> 0 | V13: =R13+N13+I13:I13 -> 0 | W13: =SUM(V13/U13) -> #DIV/0! | X13: =X12 -> 2470 | Y13: =X13-X12 -> 0 | Z13: =Z12 -> 139138.1 | AA13: =Z13-Z12 -> 0 | AB13: =SUM(Y13*$AB$2) -> 0 | AC13: =AC12 -> 1942 | AD13: =AC13-AC12 -> 0 | AE13: =AE12 -> 366072 | AF13: =AE13-AE12 -> 0 | AG13: =IF(AD13>0,AF13/AD13,0) -> 0 | AH13: =AF13+AA13 -> 0 | AI13: =SUM(AH13+V13) -> 0 | AJ13: =-tanks!AW14 -> 0 | AK13: =SUM(AJ13-AI13) -> 0 | AL13: =S13+L13+G13 -> 0 | AM13: =Y13+AD13 -> 0 | AN13: =AN12 -> 65 | AO13: =(AN13/100)*3000 -> 1950 | AP13: =AP12 -> 55 | AQ13: =(AP13/100)*3000 -> 1650 | AR13: =AR12 -> 61 | AS13: =(AR13/100)*3000 -> 1830 | AT13: =SUM(AO13+AQ13+AS13) -> 5430 | AU13: =AT12-AT13+AV13 -> 0 | AX13: =IF(AV13>0,AW13,AX12) -> 0.8
A14: =ELEC!C13 -> 44479 | B14: =B13 -> 157 | C14: =C13 -> 164 | D14: =C13-C14 -> 0 | E14: =D14*8.38 -> 0 | F14: =F13 -> 1891 | G14: =F14-F13 -> 0 | H14: =H13 -> 17176 | I14: =SUM(H14-H13) -> 0 | J14: =IF(G14>0,I14/G14,0) -> 0 | K14: =K13 -> 2356 | L14: =K14-K13 -> 0 | M14: =M13 -> 173915 | N14: =M14-M13 -> 0 | O14: =O13 -> 1869 | P14: =P13 -> 2129 | Q14: =Q13 -> 178720 | R14: =Q14-Q13 -> 0 | S14: =SUM(P14-P13) -> 0 | T14: =SUM(S14*$T$2) -> 0 | U14: =SUM(G14+L14+S14) -> 0 | V14: =R14+N14+I14:I14 -> 0 | W14: =SUM(V14/U14) -> #DIV/0! | X14: =X13 -> 2470 | Y14: =X14-X13 -> 0 | Z14: =Z13 -> 139138.1 | AA14: =Z14-Z13 -> 0 | AB14: =SUM(Y14*$AB$2) -> 0 | AC14: =AC13 -> 1942 | AD14: =AC14-AC13 -> 0 | AE14: =AE13 -> 366072 | AF14: =AE14-AE13 -> 0 | AG14: =IF(AD14>0,AF14/AD14,0) -> 0 | AH14: =AF14+AA14 -> 0 | AI14: =SUM(AH14+V14) -> 0 | AJ14: =-tanks!AW15 -> 0 | AK14: =SUM(AJ14-AI14) -> 0 | AL14: =S14+L14+G14 -> 0 | AM14: =Y14+AD14 -> 0 | AN14: =AN13 -> 65 | AO14: =(AN14/100)*3000 -> 1950 | AP14: =AP13 -> 55 | AQ14: =(AP14/100)*3000 -> 1650 | AR14: =AR13 -> 61 | AS14: =(AR14/100)*3000 -> 1830 | AT14: =SUM(AO14+AQ14+AS14) -> 5430 | AU14: =AT13-AT14+AV14 -> 0 | AX14: =IF(AV14>0,AW14,AX13) -> 0.8
A15: =ELEC!C14 -> 44480 | B15: =B14 -> 157 | C15: =C14 -> 164 | D15: =C14-C15 -> 0 | E15: =D15*8.38 -> 0 | F15: =F14 -> 1891 | G15: =F15-F14 -> 0 | H15: =H14 -> 17176 | I15: =SUM(H15-H14) -> 0 | J15: =IF(G15>0,I15/G15,0) -> 0 | K15: =K14 -> 2356 | L15: =K15-K14 -> 0 | M15: =M14 -> 173915 | N15: =M15-M14 -> 0 | O15: =O14 -> 1869 | P15: =P14 -> 2129 | Q15: =Q14 -> 178720 | R15: =Q15-Q14 -> 0 | S15: =SUM(P15-P14) -> 0 | T15: =SUM(S15*$T$2) -> 0 | U15: =SUM(G15+L15+S15) -> 0 | V15: =R15+N15+I15:I15 -> 0 | W15: =SUM(V15/U15) -> #DIV/0! | X15: =X14 -> 2470 | Y15: =X15-X14 -> 0 | Z15: =Z14 -> 139138.1 | AA15: =Z15-Z14 -> 0 | AB15: =SUM(Y15*$AB$2) -> 0 | AC15: =AC14 -> 1942 | AD15: =AC15-AC14 -> 0 | AE15: =AE14 -> 366072 | AF15: =AE15-AE14 -> 0 | AG15: =IF(AD15>0,AF15/AD15,0) -> 0 | AH15: =AF15+AA15 -> 0 | AI15: =SUM(AH15+V15) -> 0 | AJ15: =-tanks!AW16 -> 0 | AK15: =SUM(AJ15-AI15) -> 0 | AL15: =S15+L15+G15 -> 0 | AM15: =Y15+AD15 -> 0 | AN15: =AN14 -> 65 | AO15: =(AN15/100)*3000 -> 1950 | AP15: =AP14 -> 55 | AQ15: =(AP15/100)*3000 -> 1650 | AR15: =AR14 -> 61 | AS15: =(AR15/100)*3000 -> 1830 | AT15: =SUM(AO15+AQ15+AS15) -> 5430 | AU15: =AT14-AT15+AV15 -> 0 | AX15: =IF(AV15>0,AW15,AX14) -> 0.8
A16: =ELEC!C15 -> 44481 | B16: =B15 -> 157 | C16: =C15 -> 164 | D16: =C15-C16 -> 0 | E16: =D16*8.38 -> 0 | F16: =F15 -> 1891 | G16: =F16-F15 -> 0 | H16: =H15 -> 17176 | I16: =SUM(H16-H15) -> 0 | J16: =IF(G16>0,I16/G16,0) -> 0 | K16: =K15 -> 2356 | L16: =K16-K15 -> 0 | M16: =M15 -> 173915 | N16: =M16-M15 -> 0 | O16: =O15 -> 1869 | P16: =P15 -> 2129 | Q16: =Q15 -> 178720 | R16: =Q16-Q15 -> 0 | S16: =SUM(P16-P15) -> 0 | T16: =SUM(S16*$T$2) -> 0 | U16: =SUM(G16+L16+S16) -> 0 | V16: =R16+N16+I16:I16 -> 0 | W16: =SUM(V16/U16) -> #DIV/0! | X16: =X15 -> 2470 | Y16: =X16-X15 -> 0 | Z16: =Z15 -> 139138.1 | AA16: =Z16-Z15 -> 0 | AB16: =SUM(Y16*$AB$2) -> 0 | AC16: =AC15 -> 1942 | AD16: =AC16-AC15 -> 0 | AE16: =AE15 -> 366072 | AF16: =AE16-AE15 -> 0 | AG16: =IF(AD16>0,AF16/AD16,0) -> 0 | AH16: =AF16+AA16 -> 0 | AI16: =SUM(AH16+V16) -> 0 | AJ16: =-tanks!AW17 -> 0 | AK16: =SUM(AJ16-AI16) -> 0 | AL16: =S16+L16+G16 -> 0 | AM16: =Y16+AD16 -> 0 | AN16: =AN15 -> 65 | AO16: =(AN16/100)*3000 -> 1950 | AP16: =AP15 -> 55 | AQ16: =(AP16/100)*3000 -> 1650 | AR16: =AR15 -> 61 | AS16: =(AR16/100)*3000 -> 1830 | AT16: =SUM(AO16+AQ16+AS16) -> 5430 | AU16: =AT15-AT16+AV16 -> 0 | AX16: =IF(AV16>0,AW16,AX15) -> 0.8
A17: =ELEC!C16 -> 44482 | B17: =B16 -> 157 | C17: =C16 -> 164 | D17: =C16-C17 -> 0 | E17: =D17*8.38 -> 0 | F17: =F16 -> 1891 | G17: =F17-F16 -> 0 | H17: =H16 -> 17176 | I17: =SUM(H17-H16) -> 0 | J17: =IF(G17>0,I17/G17,0) -> 0 | K17: =K16 -> 2356 | L17: =K17-K16 -> 0 | M17: =M16 -> 173915 | N17: =M17-M16 -> 0 | O17: =O16 -> 1869 | P17: =P16 -> 2129 | Q17: =Q16 -> 178720 | R17: =Q17-Q16 -> 0 | S17: =SUM(P17-P16) -> 0 | T17: =SUM(S17*$T$2) -> 0 | U17: =SUM(G17+L17+S17) -> 0 | V17: =R17+N17+I17:I17 -> 0 | X17: =X16 -> 2470 | Y17: =X17-X16 -> 0 | Z17: =Z16 -> 139138.1 | AA17: =Z17-Z16 -> 0 | AB17: =SUM(Y17*$AB$2) -> 0 | AC17: =AC16 -> 1942 | AD17: =AC17-AC16 -> 0 | AE17: =AE16 -> 366072 | AF17: =AE17-AE16 -> 0 | AG17: =IF(AD17>0,AF17/AD17,0) -> 0 | AH17: =AF17+AA17 -> 0 | AI17: =SUM(AH17+V17) -> 0 | AJ17: =-tanks!AW18 -> 0 | AK17: =SUM(AJ17-AI17) -> 0 | AL17: =S17+L17+G17 -> 0 | AM17: =Y17+AD17 -> 0 | AN17: =AN16 -> 65 | AO17: =(AN17/100)*3000 -> 1950 | AP17: =AP16 -> 55 | AQ17: =(AP17/100)*3000 -> 1650 | AR17: =AR16 -> 61 | AS17: =(AR17/100)*3000 -> 1830 | AT17: =SUM(AO17+AQ17+AS17) -> 5430 | AU17: =AT16-AT17+AV17 -> 0 | AX17: =IF(AV17>0,AW17,AX16) -> 0.8
A18: =ELEC!C17 -> 44483 | B18: =B17 -> 157 | C18: =C17 -> 164 | D18: =C17-C18 -> 0 | E18: =D18*8.38 -> 0 | F18: =F17 -> 1891 | G18: =F18-F17 -> 0 | H18: =H17 -> 17176 | I18: =SUM(H18-H17) -> 0 | J18: =IF(G18>0,I18/G18,0) -> 0 | K18: =K17 -> 2356 | L18: =K18-K17 -> 0 | M18: =M17 -> 173915 | N18: =M18-M17 -> 0 | O18: 1869 | P18: =P17 -> 2129 | Q18: =Q17 -> 178720 | R18: =Q18-Q17 -> 0 | S18: =SUM(P18-P17) -> 0 | T18: =SUM(S18*$T$2) -> 0 | U18: =SUM(G18+L18+S18) -> 0 | V18: =R18+N18+I18:I18 -> 0 | X18: =X17 -> 2470 | Y18: =X18-X17 -> 0 | Z18: =Z17 -> 139138.1 | AA18: =Z18-Z17 -> 0 | AB18: =SUM(Y18*$AB$2) -> 0 | AC18: =AC17 -> 1942 | AD18: =AC18-AC17 -> 0 | AE18: =AE17 -> 366072 | AF18: =AE18-AE17 -> 0 | AG18: =IF(AD18>0,AF18/AD18,0) -> 0 | AH18: =AF18+AA18 -> 0 | AI18: =SUM(AH18+V18) -> 0 | AJ18: =-tanks!AW19 -> 0 | AK18: =SUM(AJ18-AI18) -> 0 | AL18: =S18+L18+G18 -> 0 | AM18: =Y18+AD18 -> 0 | AN18: =AN17 -> 65 | AO18: =(AN18/100)*3000 -> 1950 | AP18: =AP17 -> 55 | AQ18: =(AP18/100)*3000 -> 1650 | AR18: =AR17 -> 61 | AS18: =(AR18/100)*3000 -> 1830 | AT18: =SUM(AO18+AQ18+AS18) -> 5430 | AU18: =AT17-AT18+AV18 -> 0 | AX18: =IF(AV18>0,AW18,AX17) -> 0.8
A19: =ELEC!C18 -> 44484 | B19: =B18 -> 157 | C19: =C18 -> 164 | D19: =C18-C19 -> 0 | E19: =D19*8.38 -> 0 | F19: =F18 -> 1891 | G19: =F19-F18 -> 0 | H19: =H18 -> 17176 | I19: =SUM(H19-H18) -> 0 | J19: =IF(G19>0,I19/G19,0) -> 0 | K19: =K18 -> 2356 | L19: =K19-K18 -> 0 | M19: =M18 -> 173915 | N19: =M19-M18 -> 0 | O19: =O18 -> 1869 | P19: =P18 -> 2129 | Q19: =Q18 -> 178720 | R19: =Q19-Q18 -> 0 | S19: =SUM(P19-P18) -> 0 | T19: =SUM(S19*$T$2) -> 0 | U19: =SUM(G19+L19+S19) -> 0 | V19: =R19+N19+I19:I19 -> 0 | X19: =X18 -> 2470 | Y19: =X19-X18 -> 0 | Z19: =Z18 -> 139138.1 | AA19: =Z19-Z18 -> 0 | AB19: =SUM(Y19*$AB$2) -> 0 | AC19: =AC18 -> 1942 | AD19: =AC19-AC18 -> 0 | AE19: =AE18 -> 366072 | AF19: =AE19-AE18 -> 0 | AG19: =IF(AD19>0,AF19/AD19,0) -> 0 | AH19: =AF19+AA19 -> 0 | AI19: =SUM(AH19+V19) -> 0 | AJ19: =-tanks!AW20 -> 0 | AK19: =SUM(AJ19-AI19) -> 0 | AL19: =S19+L19+G19 -> 0 | AM19: =Y19+AD19 -> 0 | AN19: =AN18 -> 65 | AO19: =(AN19/100)*3000 -> 1950 | AP19: =AP18 -> 55 | AQ19: =(AP19/100)*3000 -> 1650 | AR19: =AR18 -> 61 | AS19: =(AR19/100)*3000 -> 1830 | AT19: =SUM(AO19+AQ19+AS19) -> 5430 | AU19: =AT18-AT19+AV19 -> 0 | AX19: =IF(AV19>0,AW19,AX18) -> 0.8
A20: =ELEC!C19 -> 44485 | B20: =B19 -> 157 | C20: =C19 -> 164 | D20: =C19-C20 -> 0 | E20: =D20*8.38 -> 0 | F20: =F19 -> 1891 | G20: =F20-F19 -> 0 | H20: =H19 -> 17176 | I20: =SUM(H20-H19) -> 0 | J20: =IF(G20>0,I20/G20,0) -> 0 | K20: =K19 -> 2356 | L20: =K20-K19 -> 0 | M20: =M19 -> 173915 | N20: =M20-M19 -> 0 | O20: =O19 -> 1869 | P20: =P19 -> 2129 | Q20: =Q19 -> 178720 | R20: =Q20-Q19 -> 0 | S20: =SUM(P20-P19) -> 0 | T20: =SUM(S20*$T$2) -> 0 | U20: =SUM(G20+L20+S20) -> 0 | V20: =R20+N20+I20:I20 -> 0 | X20: =X19 -> 2470 | Y20: =X20-X19 -> 0 | Z20: =Z19 -> 139138.1 | AA20: =Z20-Z19 -> 0 | AB20: =SUM(Y20*$AB$2) -> 0 | AC20: =AC19 -> 1942 | AD20: =AC20-AC19 -> 0 | AE20: =AE19 -> 366072 | AF20: =AE20-AE19 -> 0 | AG20: =IF(AD20>0,AF20/AD20,0) -> 0 | AH20: =AF20+AA20 -> 0 | AI20: =SUM(AH20+V20) -> 0 | AJ20: =-tanks!AW21 -> 0 | AK20: =SUM(AJ20-AI20) -> 0 | AL20: =S20+L20+G20 -> 0 | AM20: =Y20+AD20 -> 0 | AN20: =AN19 -> 65 | AO20: =(AN20/100)*3000 -> 1950 | AP20: =AP19 -> 55 | AQ20: =(AP20/100)*3000 -> 1650 | AR20: =AR19 -> 61 | AS20: =(AR20/100)*3000 -> 1830 | AT20: =SUM(AO20+AQ20+AS20) -> 5430 | AU20: =AT19-AT20+AV20 -> 0 | AX20: =IF(AV20>0,AW20,AX19) -> 0.8
A21: =ELEC!C20 -> 44486 | B21: =B20 -> 157 | C21: =C20 -> 164 | D21: =C20-C21 -> 0 | E21: =D21*8.38 -> 0 | F21: =F20 -> 1891 | G21: =F21-F20 -> 0 | H21: =H20 -> 17176 | I21: =SUM(H21-H20) -> 0 | J21: =IF(G21>0,I21/G21,0) -> 0 | K21: =K20 -> 2356 | L21: =K21-K20 -> 0 | M21: =M20 -> 173915 | N21: =M21-M20 -> 0 | O21: =O20 -> 1869 | P21: =P20 -> 2129 | Q21: =Q20 -> 178720 | R21: =Q21-Q20 -> 0 | S21: =SUM(P21-P20) -> 0 | T21: =SUM(S21*$T$2) -> 0 | U21: =SUM(G21+L21+S21) -> 0 | V21: =R21+N21+I21:I21 -> 0 | X21: =X20 -> 2470 | Y21: =X21-X20 -> 0 | Z21: =Z20 -> 139138.1 | AA21: =Z21-Z20 -> 0 | AB21: =SUM(Y21*$AB$2) -> 0 | AC21: =AC20 -> 1942 | AD21: =AC21-AC20 -> 0 | AE21: =AE20 -> 366072 | AF21: =AE21-AE20 -> 0 | AG21: =IF(AD21>0,AF21/AD21,0) -> 0 | AH21: =AF21+AA21 -> 0 | AI21: =SUM(AH21+V21) -> 0 | AJ21: =-tanks!AW22 -> 0 | AK21: =SUM(AJ21-AI21) -> 0 | AL21: =S21+L21+G21 -> 0 | AM21: =Y21+AD21 -> 0 | AN21: =AN20 -> 65 | AO21: =(AN21/100)*3000 -> 1950 | AP21: =AP20 -> 55 | AQ21: =(AP21/100)*3000 -> 1650 | AR21: =AR20 -> 61 | AS21: =(AR21/100)*3000 -> 1830 | AT21: =SUM(AO21+AQ21+AS21) -> 5430 | AU21: =AT20-AT21+AV21 -> 0 | AX21: =IF(AV21>0,AW21,AX20) -> 0.8
A22: =ELEC!C21 -> 44487 | B22: =B21 -> 157 | C22: =C21 -> 164 | D22: =C21-C22 -> 0 | E22: =D22*8.38 -> 0 | F22: =F21 -> 1891 | G22: =F22-F21 -> 0 | H22: =H21 -> 17176 | I22: =SUM(H22-H21) -> 0 | J22: =IF(G22>0,I22/G22,0) -> 0 | K22: =K21 -> 2356 | L22: =K22-K21 -> 0 | M22: =M21 -> 173915 | N22: =M22-M21 -> 0 | O22: =O21 -> 1869 | P22: =P21 -> 2129 | Q22: =Q21 -> 178720 | R22: =Q22-Q21 -> 0 | S22: =SUM(P22-P21) -> 0 | T22: =SUM(S22*$T$2) -> 0 | U22: =SUM(G22+L22+S22) -> 0 | V22: =R22+N22+I22:I22 -> 0 | X22: =X21 -> 2470 | Y22: =X22-X21 -> 0 | Z22: =Z21 -> 139138.1 | AA22: =Z22-Z21 -> 0 | AB22: =SUM(Y22*$AB$2) -> 0 | AC22: =AC21 -> 1942 | AD22: =AC22-AC21 -> 0 | AE22: =AE21 -> 366072 | AF22: =AE22-AE21 -> 0 | AG22: =IF(AD22>0,AF22/AD22,0) -> 0 | AH22: =AF22+AA22 -> 0 | AI22: =SUM(AH22+V22) -> 0 | AJ22: =-tanks!AW23 -> 0 | AK22: =SUM(AJ22-AI22) -> 0 | AL22: =S22+L22+G22 -> 0 | AM22: =Y22+AD22 -> 0 | AN22: =AN21 -> 65 | AO22: =(AN22/100)*3000 -> 1950 | AP22: =AP21 -> 55 | AQ22: =(AP22/100)*3000 -> 1650 | AR22: =AR21 -> 61 | AS22: =(AR22/100)*3000 -> 1830 | AT22: =SUM(AO22+AQ22+AS22) -> 5430 | AU22: =AT21-AT22+AV22 -> 0 | AX22: =IF(AV22>0,AW22,AX21) -> 0.8
A23: =ELEC!C22 -> 44488 | B23: =B22 -> 157 | C23: =C22 -> 164 | D23: =C22-C23 -> 0 | E23: =D23*8.38 -> 0 | F23: =F22 -> 1891 | G23: =F23-F22 -> 0 | H23: =H22 -> 17176 | I23: =SUM(H23-H22) -> 0 | J23: =IF(G23>0,I23/G23,0) -> 0 | K23: =K22 -> 2356 | L23: =K23-K22 -> 0 | M23: =M22 -> 173915 | N23: =M23-M22 -> 0 | O23: =O22 -> 1869 | P23: =P22 -> 2129 | Q23: =Q22 -> 178720 | R23: =Q23-Q22 -> 0 | S23: =SUM(P23-P22) -> 0 | T23: =SUM(S23*$T$2) -> 0 | U23: =SUM(G23+L23+S23) -> 0 | V23: =R23+N23+I23:I23 -> 0 | X23: =X22 -> 2470 | Y23: =X23-X22 -> 0 | Z23: =Z22 -> 139138.1 | AA23: =Z23-Z22 -> 0 | AB23: =SUM(Y23*$AB$2) -> 0 | AC23: =AC22 -> 1942 | AD23: =AC23-AC22 -> 0 | AE23: =AE22 -> 366072 | AF23: =AE23-AE22 -> 0 | AG23: =IF(AD23>0,AF23/AD23,0) -> 0 | AH23: =AF23+AA23 -> 0 | AI23: =SUM(AH23+V23) -> 0 | AJ23: =-tanks!AW24 -> 0 | AK23: =SUM(AJ23-AI23) -> 0 | AL23: =S23+L23+G23 -> 0 | AM23: =Y23+AD23 -> 0 | AN23: =AN22 -> 65 | AO23: =(AN23/100)*3000 -> 1950 | AP23: =AP22 -> 55 | AQ23: =(AP23/100)*3000 -> 1650 | AR23: =AR22 -> 61 | AS23: =(AR23/100)*3000 -> 1830 | AT23: =SUM(AO23+AQ23+AS23) -> 5430 | AU23: =AT22-AT23+AV23 -> 0 | AX23: =IF(AV23>0,AW23,AX22) -> 0.8
A24: =ELEC!C23 -> 44489 | B24: =B23 -> 157 | C24: =C23 -> 164 | D24: =C23-C24 -> 0 | E24: =D24*8.38 -> 0 | F24: =F23 -> 1891 | G24: =F24-F23 -> 0 | H24: =H23 -> 17176 | I24: =SUM(H24-H23) -> 0 | J24: =IF(G24>0,I24/G24,0) -> 0 | K24: =K23 -> 2356 | L24: =K24-K23 -> 0 | M24: =M23 -> 173915 | N24: =M24-M23 -> 0 | O24: =O23 -> 1869 | P24: =P23 -> 2129 | Q24: =Q23 -> 178720 | R24: =Q24-Q23 -> 0 | S24: =SUM(P24-P23) -> 0 | T24: =SUM(S24*$T$2) -> 0 | U24: =SUM(G24+L24+S24) -> 0 | V24: =R24+N24+I24:I24 -> 0 | X24: =X23 -> 2470 | Y24: =X24-X23 -> 0 | Z24: =Z23 -> 139138.1 | AA24: =Z24-Z23 -> 0 | AB24: =SUM(Y24*$AB$2) -> 0 | AC24: =AC23 -> 1942 | AD24: =AC24-AC23 -> 0 | AE24: =AE23 -> 366072 | AF24: =AE24-AE23 -> 0 | AG24: =IF(AD24>0,AF24/AD24,0) -> 0 | AH24: =AF24+AA24 -> 0 | AI24: =SUM(AH24+V24) -> 0 | AJ24: =-tanks!AW25 -> 0 | AK24: =SUM(AJ24-AI24) -> 0 | AL24: =S24+L24+G24 -> 0 | AM24: =Y24+AD24 -> 0 | AN24: =AN23 -> 65 | AO24: =(AN24/100)*3000 -> 1950 | AP24: =AP23 -> 55 | AQ24: =(AP24/100)*3000 -> 1650 | AR24: =AR23 -> 61 | AS24: =(AR24/100)*3000 -> 1830 | AT24: =SUM(AO24+AQ24+AS24) -> 5430 | AU24: =AT23-AT24+AV24 -> 0 | AX24: =IF(AV24>0,AW24,AX23) -> 0.8
A25: =ELEC!C24 -> 44490 | B25: =B24 -> 157 | C25: =C24 -> 164 | D25: =C24-C25 -> 0 | E25: =D25*8.38 -> 0 | F25: =F24 -> 1891 | G25: =F25-F24 -> 0 | H25: =H24 -> 17176 | I25: =SUM(H25-H24) -> 0 | J25: =IF(G25>0,I25/G25,0) -> 0 | K25: =K24 -> 2356 | L25: =K25-K24 -> 0 | M25: =M24 -> 173915 | N25: =M25-M24 -> 0 | O25: =O24 -> 1869 | P25: =P24 -> 2129 | Q25: =Q24 -> 178720 | R25: =Q25-Q24 -> 0 | S25: =SUM(P25-P24) -> 0 | T25: =SUM(S25*$T$2) -> 0 | U25: =SUM(G25+L25+S25) -> 0 | V25: =R25+N25+I25:I25 -> 0 | X25: =X24 -> 2470 | Y25: =X25-X24 -> 0 | Z25: =Z24 -> 139138.1 | AA25: =Z25-Z24 -> 0 | AB25: =SUM(Y25*$AB$2) -> 0 | AC25: =AC24 -> 1942 | AD25: =AC25-AC24 -> 0 | AE25: =AE24 -> 366072 | AF25: =AE25-AE24 -> 0 | AG25: =IF(AD25>0,AF25/AD25,0) -> 0 | AH25: =AF25+AA25 -> 0 | AI25: =SUM(AH25+V25) -> 0 | AJ25: =-tanks!AW26 -> 0 | AK25: =SUM(AJ25-AI25) -> 0 | AL25: =S25+L25+G25 -> 0 | AM25: =Y25+AD25 -> 0 | AN25: =AN24 -> 65 | AO25: =(AN25/100)*3000 -> 1950 | AP25: =AP24 -> 55 | AQ25: =(AP25/100)*3000 -> 1650 | AR25: =AR24 -> 61 | AS25: =(AR25/100)*3000 -> 1830 | AT25: =SUM(AO25+AQ25+AS25) -> 5430 | AU25: =AT24-AT25+AV25 -> 0 | AX25: =IF(AV25>0,AW25,AX24) -> 0.8
A26: =ELEC!C25 -> 44491 | B26: =B25 -> 157 | C26: =C25 -> 164 | D26: =C25-C26 -> 0 | E26: =D26*8.38 -> 0 | F26: =F25 -> 1891 | G26: =F26-F25 -> 0 | H26: =H25 -> 17176 | I26: =SUM(H26-H25) -> 0 | J26: =IF(G26>0,I26/G26,0) -> 0 | K26: =K25 -> 2356 | L26: =K26-K25 -> 0 | M26: =M25 -> 173915 | N26: =M26-M25 -> 0 | O26: =O25 -> 1869 | P26: =P25 -> 2129 | Q26: =Q25 -> 178720 | R26: =Q26-Q25 -> 0 | S26: =SUM(P26-P25) -> 0 | T26: =SUM(S26*$T$2) -> 0 | U26: =SUM(G26+L26+S26) -> 0 | V26: =R26+N26+I26:I26 -> 0 | X26: =X25 -> 2470 | Y26: =X26-X25 -> 0 | Z26: 139138.1 | AA26: =Z26-Z25 -> 0 | AB26: =SUM(Y26*$AB$2) -> 0 | AC26: =AC25 -> 1942 | AD26: =AC26-AC25 -> 0 | AE26: =AE25 -> 366072 | AF26: =AE26-AE25 -> 0 | AG26: =IF(AD26>0,AF26/AD26,0) -> 0 | AH26: =AF26+AA26 -> 0 | AI26: =SUM(AH26+V26) -> 0 | AJ26: =-tanks!AW27 -> 0 | AK26: =SUM(AJ26-AI26) -> 0 | AL26: =S26+L26+G26 -> 0 | AM26: =Y26+AD26 -> 0 | AN26: =AN25 -> 65 | AO26: =(AN26/100)*3000 -> 1950 | AP26: =AP25 -> 55 | AQ26: =(AP26/100)*3000 -> 1650 | AR26: =AR25 -> 61 | AS26: =(AR26/100)*3000 -> 1830 | AT26: =SUM(AO26+AQ26+AS26) -> 5430 | AU26: =AT25-AT26+AV26 -> 0 | AX26: =IF(AV26>0,AW26,AX25) -> 0.8
A27: =ELEC!C26 -> 44492 | B27: =B26 -> 157 | C27: =C26 -> 164 | D27: =C26-C27 -> 0 | E27: =D27*8.38 -> 0 | F27: =F26 -> 1891 | G27: =F27-F26 -> 0 | H27: =H26 -> 17176 | I27: =SUM(H27-H26) -> 0 | J27: =IF(G27>0,I27/G27,0) -> 0 | K27: =K26 -> 2356 | L27: =K27-K26 -> 0 | M27: =M26 -> 173915 | N27: =M27-M26 -> 0 | O27: =O26 -> 1869 | P27: =P26 -> 2129 | Q27: =Q26 -> 178720 | R27: =Q27-Q26 -> 0 | S27: =SUM(P27-P26) -> 0 | T27: =SUM(S27*$T$2) -> 0 | U27: =SUM(G27+L27+S27) -> 0 | V27: =R27+N27+I27:I27 -> 0 | X27: =X26 -> 2470 | Y27: =X27-X26 -> 0 | Z27: =Z26 -> 139138.1 | AA27: =Z27-Z26 -> 0 | AB27: =SUM(Y27*$AB$2) -> 0 | AC27: =AC26 -> 1942 | AD27: =AC27-AC26 -> 0 | AE27: =AE26 -> 366072 | AF27: =AE27-AE26 -> 0 | AG27: =IF(AD27>0,AF27/AD27,0) -> 0 | AH27: =AF27+AA27 -> 0 | AI27: =SUM(AH27+V27) -> 0 | AJ27: =-tanks!AW28 -> 0 | AK27: =SUM(AJ27-AI27) -> 0 | AL27: =S27+L27+G27 -> 0 | AM27: =Y27+AD27 -> 0 | AN27: =AN26 -> 65 | AO27: =(AN27/100)*3000 -> 1950 | AP27: =AP26 -> 55 | AQ27: =(AP27/100)*3000 -> 1650 | AR27: =AR26 -> 61 | AS27: =(AR27/100)*3000 -> 1830 | AT27: =SUM(AO27+AQ27+AS27) -> 5430 | AU27: =AT26-AT27+AV27 -> 0 | AX27: =IF(AV27>0,AW27,AX26) -> 0.8
A28: =ELEC!C27 -> 44493 | B28: =B27 -> 157 | C28: =C27 -> 164 | D28: =C27-C28 -> 0 | E28: =D28*8.38 -> 0 | F28: =F27 -> 1891 | G28: =F28-F27 -> 0 | H28: =H27 -> 17176 | I28: =SUM(H28-H27) -> 0 | J28: =IF(G28>0,I28/G28,0) -> 0 | K28: =K27 -> 2356 | L28: =K28-K27 -> 0 | M28: =M27 -> 173915 | N28: =M28-M27 -> 0 | O28: =O27 -> 1869 | P28: =P27 -> 2129 | Q28: =Q27 -> 178720 | R28: =Q28-Q27 -> 0 | S28: =SUM(P28-P27) -> 0 | T28: =SUM(S28*$T$2) -> 0 | U28: =SUM(G28+L28+S28) -> 0 | V28: =R28+N28+I28:I28 -> 0 | X28: =X27 -> 2470 | Y28: =X28-X27 -> 0 | Z28: =Z27 -> 139138.1 | AA28: =Z28-Z27 -> 0 | AB28: =SUM(Y28*$AB$2) -> 0 | AC28: =AC27 -> 1942 | AD28: =AC28-AC27 -> 0 | AE28: =AE27 -> 366072 | AF28: =AE28-AE27 -> 0 | AG28: =IF(AD28>0,AF28/AD28,0) -> 0 | AH28: =AF28+AA28 -> 0 | AI28: =SUM(AH28+V28) -> 0 | AJ28: =-tanks!AW29 -> 0 | AK28: =SUM(AJ28-AI28) -> 0 | AL28: =S28+L28+G28 -> 0 | AM28: =Y28+AD28 -> 0 | AN28: =AN27 -> 65 | AO28: =(AN28/100)*3000 -> 1950 | AP28: =AP27 -> 55 | AQ28: =(AP28/100)*3000 -> 1650 | AR28: =AR27 -> 61 | AS28: =(AR28/100)*3000 -> 1830 | AT28: =SUM(AO28+AQ28+AS28) -> 5430 | AU28: =AT27-AT28+AV28 -> 0 | AX28: =IF(AV28>0,AW28,AX27) -> 0.8
A29: =ELEC!C28 -> 44494 | B29: =B28 -> 157 | C29: =C28 -> 164 | D29: =C28-C29 -> 0 | E29: =D29*8.38 -> 0 | F29: =F28 -> 1891 | G29: =F29-F28 -> 0 | H29: =H28 -> 17176 | I29: =SUM(H29-H28) -> 0 | J29: =IF(G29>0,I29/G29,0) -> 0 | K29: =K28 -> 2356 | L29: =K29-K28 -> 0 | M29: =M28 -> 173915 | N29: =M29-M28 -> 0 | O29: =O28 -> 1869 | P29: =P28 -> 2129 | Q29: =Q28 -> 178720 | R29: =Q29-Q28 -> 0 | S29: =SUM(P29-P28) -> 0 | T29: =SUM(S29*$T$2) -> 0 | U29: =SUM(G29+L29+S29) -> 0 | V29: =R29+N29+I29:I29 -> 0 | X29: =X28 -> 2470 | Y29: =X29-X28 -> 0 | Z29: =Z28 -> 139138.1 | AA29: =Z29-Z28 -> 0 | AB29: =SUM(Y29*$AB$2) -> 0 | AC29: =AC28 -> 1942 | AD29: =AC29-AC28 -> 0 | AE29: =AE28 -> 366072 | AF29: =AE29-AE28 -> 0 | AG29: =IF(AD29>0,AF29/AD29,0) -> 0 | AH29: =AF29+AA29 -> 0 | AI29: =SUM(AH29+V29) -> 0 | AJ29: =-tanks!AW30 -> 0 | AK29: =SUM(AJ29-AI29) -> 0 | AL29: =S29+L29+G29 -> 0 | AM29: =Y29+AD29 -> 0 | AN29: =AN28 -> 65 | AO29: =(AN29/100)*3000 -> 1950 | AP29: =AP28 -> 55 | AQ29: =(AP29/100)*3000 -> 1650 | AR29: =AR28 -> 61 | AS29: =(AR29/100)*3000 -> 1830 | AT29: =SUM(AO29+AQ29+AS29) -> 5430 | AU29: =AT28-AT29+AV29 -> 0 | AX29: =IF(AV29>0,AW29,AX28) -> 0.8
A30: =ELEC!C29 -> 44495 | B30: =B29 -> 157 | C30: =C29 -> 164 | D30: =C29-C30 -> 0 | E30: =D30*8.38 -> 0 | F30: =F29 -> 1891 | G30: =F30-F29 -> 0 | H30: =H29 -> 17176 | I30: =SUM(H30-H29) -> 0 | J30: =IF(G30>0,I30/G30,0) -> 0 | K30: =K29 -> 2356 | L30: =K30-K29 -> 0 | M30: =M29 -> 173915 | N30: =M30-M29 -> 0 | O30: =O29 -> 1869 | P30: =P29 -> 2129 | Q30: =Q29 -> 178720 | R30: =Q30-Q29 -> 0 | S30: =SUM(P30-P29) -> 0 | T30: =SUM(S30*$T$2) -> 0 | U30: =SUM(G30+L30+S30) -> 0 | V30: =R30+N30+I30:I30 -> 0 | X30: =X29 -> 2470 | Y30: =X30-X29 -> 0 | Z30: =Z29 -> 139138.1 | AA30: =Z30-Z29 -> 0 | AB30: =SUM(Y30*$AB$2) -> 0 | AC30: =AC29 -> 1942 | AD30: =AC30-AC29 -> 0 | AE30: =AE29 -> 366072 | AF30: =AE30-AE29 -> 0 | AG30: =IF(AD30>0,AF30/AD30,0) -> 0 | AH30: =AF30+AA30 -> 0 | AI30: =SUM(AH30+V30) -> 0 | AJ30: =-tanks!AW31 -> 0 | AK30: =SUM(AJ30-AI30) -> 0 | AL30: =S30+L30+G30 -> 0 | AM30: =Y30+AD30 -> 0 | AN30: =AN29 -> 65 | AO30: =(AN30/100)*3000 -> 1950 | AP30: =AP29 -> 55 | AQ30: =(AP30/100)*3000 -> 1650 | AR30: =AR29 -> 61 | AS30: =(AR30/100)*3000 -> 1830 | AT30: =SUM(AO30+AQ30+AS30) -> 5430 | AU30: =AT29-AT30+AV30 -> 0 | AX30: =IF(AV30>0,AW30,AX29) -> 0.8
A31: =ELEC!C30 -> 44496 | B31: =B30 -> 157 | C31: =C30 -> 164 | D31: =C30-C31 -> 0 | E31: =D31*8.38 -> 0 | F31: =F30 -> 1891 | G31: =F31-F30 -> 0 | H31: =H30 -> 17176 | I31: =SUM(H31-H30) -> 0 | J31: =IF(G31>0,I31/G31,0) -> 0 | K31: =K30 -> 2356 | L31: =K31-K30 -> 0 | M31: =M30 -> 173915 | N31: =M31-M30 -> 0 | O31: =O30 -> 1869 | P31: =P30 -> 2129 | Q31: =Q30 -> 178720 | R31: =Q31-Q30 -> 0 | S31: =SUM(P31-P30) -> 0 | T31: =SUM(S31*$T$2) -> 0 | U31: =SUM(G31+L31+S31) -> 0 | V31: =R31+N31+I31:I31 -> 0 | X31: =X30 -> 2470 | Y31: =X31-X30 -> 0 | Z31: =Z30 -> 139138.1 | AA31: =Z31-Z30 -> 0 | AB31: =SUM(Y31*$AB$2) -> 0 | AC31: =AC30 -> 1942 | AD31: =AC31-AC30 -> 0 | AE31: =AE30 -> 366072 | AF31: =AE31-AE30 -> 0 | AG31: =IF(AD31>0,AF31/AD31,0) -> 0 | AH31: =AF31+AA31 -> 0 | AI31: =SUM(AH31+V31) -> 0 | AJ31: =-tanks!AW32 -> 0 | AK31: =SUM(AJ31-AI31) -> 0 | AL31: =S31+L31+G31 -> 0 | AM31: =Y31+AD31 -> 0 | AN31: =AN30 -> 65 | AO31: =(AN31/100)*3000 -> 1950 | AP31: =AP30 -> 55 | AQ31: =(AP31/100)*3000 -> 1650 | AR31: =AR30 -> 61 | AS31: =(AR31/100)*3000 -> 1830 | AT31: =SUM(AO31+AQ31+AS31) -> 5430 | AU31: =AT30-AT31+AV31 -> 0 | AX31: =IF(AV31>0,AW31,AX30) -> 0.8
A32: =ELEC!C31 -> 44497 | B32: =B31 -> 157 | C32: =C31 -> 164 | D32: =C31-C32 -> 0 | E32: =D32*8.38 -> 0 | F32: =F31 -> 1891 | G32: =F32-F31 -> 0 | H32: =H31 -> 17176 | I32: =SUM(H32-H31) -> 0 | J32: =IF(G32>0,I32/G32,0) -> 0 | K32: =K31 -> 2356 | L32: =K32-K31 -> 0 | M32: =M31 -> 173915 | N32: =M32-M31 -> 0 | O32: =O31 -> 1869 | P32: =P31 -> 2129 | Q32: =Q31 -> 178720 | R32: =Q32-Q31 -> 0 | S32: =SUM(P32-P31) -> 0 | T32: =SUM(S32*$T$2) -> 0 | U32: =SUM(G32+L32+S32) -> 0 | V32: =R32+N32+I32:I32 -> 0 | X32: =X31 -> 2470 | Y32: =X32-X31 -> 0 | Z32: =Z31 -> 139138.1 | AA32: =Z32-Z31 -> 0 | AB32: =SUM(Y32*$AB$2) -> 0 | AC32: =AC31 -> 1942 | AD32: =AC32-AC31 -> 0 | AE32: =AE31 -> 366072 | AF32: =AE32-AE31 -> 0 | AG32: =IF(AD32>0,AF32/AD32,0) -> 0 | AH32: =AF32+AA32 -> 0 | AI32: =SUM(AH32+V32) -> 0 | AJ32: =-tanks!AW33 -> 0 | AK32: =SUM(AJ32-AI32) -> 0 | AL32: =S32+L32+G32 -> 0 | AM32: =Y32+AD32 -> 0 | AN32: =AN31 -> 65 | AO32: =(AN32/100)*3000 -> 1950 | AP32: =AP31 -> 55 | AQ32: =(AP32/100)*3000 -> 1650 | AR32: =AR31 -> 61 | AS32: =(AR32/100)*3000 -> 1830 | AT32: =SUM(AO32+AQ32+AS32) -> 5430 | AU32: =AT31-AT32+AV32 -> 0 | AX32: =IF(AV32>0,AW32,AX31) -> 0.8
A33: =ELEC!C32 -> 44498 | B33: =B32 -> 157 | C33: =C32 -> 164 | D33: =C32-C33 -> 0 | E33: =D33*8.38 -> 0 | F33: =F32 -> 1891 | G33: =F33-F32 -> 0 | H33: =H32 -> 17176 | I33: =SUM(H33-H32) -> 0 | J33: =IF(G33>0,I33/G33,0) -> 0 | K33: =K32 -> 2356 | L33: =K33-K32 -> 0 | M33: =M32 -> 173915 | N33: =M33-M32 -> 0 | O33: =O32 -> 1869 | P33: =P32 -> 2129 | Q33: =Q32 -> 178720 | R33: =Q33-Q32 -> 0 | S33: =SUM(P33-P32) -> 0 | T33: =SUM(S33*$T$2) -> 0 | U33: =SUM(G33+L33+S33) -> 0 | V33: =R33+N33+I33:I33 -> 0 | X33: =X32 -> 2470 | Y33: =X33-X32 -> 0 | Z33: =Z32 -> 139138.1 | AA33: =Z33-Z32 -> 0 | AB33: =SUM(Y33*$AB$2) -> 0 | AC33: =AC32 -> 1942 | AD33: =AC33-AC32 -> 0 | AE33: =AE32 -> 366072 | AF33: =AE33-AE32 -> 0 | AG33: =IF(AD33>0,AF33/AD33,0) -> 0 | AH33: =AF33+AA33 -> 0 | AI33: =SUM(AH33+V33) -> 0 | AJ33: =-tanks!AW34 -> 0 | AK33: =SUM(AJ33-AI33) -> 0 | AL33: =S33+L33+G33 -> 0 | AM33: =Y33+AD33 -> 0 | AN33: =AN32 -> 65 | AO33: =(AN33/100)*3000 -> 1950 | AP33: =AP32 -> 55 | AQ33: =(AP33/100)*3000 -> 1650 | AR33: =AR32 -> 61 | AS33: =(AR33/100)*3000 -> 1830 | AT33: =SUM(AO33+AQ33+AS33) -> 5430 | AU33: =AT32-AT33+AV33 -> 0 | AX33: =IF(AV33>0,AW33,AX32) -> 0.8
A34: =ELEC!C33 -> 44499 | B34: =B33 -> 157 | C34: =C33 -> 164 | D34: =C33-C34 -> 0 | E34: =D34*8.38 -> 0 | F34: =F33 -> 1891 | G34: =F34-F33 -> 0 | H34: =H33 -> 17176 | I34: =SUM(H34-H33) -> 0 | J34: =IF(G34>0,I34/G34,0) -> 0 | K34: =K33 -> 2356 | L34: =K34-K33 -> 0 | M34: =M33 -> 173915 | N34: =M34-M33 -> 0 | O34: =O33 -> 1869 | P34: =P33 -> 2129 | Q34: =Q33 -> 178720 | R34: =Q34-Q33 -> 0 | S34: =SUM(P34-P33) -> 0 | T34: =SUM(S34*$T$2) -> 0 | U34: =SUM(G34+L34+S34) -> 0 | V34: =R34+N34+I34:I34 -> 0 | X34: =X33 -> 2470 | Y34: =X34-X33 -> 0 | Z34: =Z33 -> 139138.1 | AA34: =Z34-Z33 -> 0 | AB34: =SUM(Y34*$AB$2) -> 0 | AC34: =AC33 -> 1942 | AD34: =AC34-AC33 -> 0 | AE34: =AE33 -> 366072 | AF34: =AE34-AE33 -> 0 | AG34: =IF(AD34>0,AF34/AD34,0) -> 0 | AH34: =AF34+AA34 -> 0 | AI34: =SUM(AH34+V34) -> 0 | AJ34: =-tanks!AW35 -> 0 | AK34: =SUM(AJ34-AI34) -> 0 | AL34: =S34+L34+G34 -> 0 | AM34: =Y34+AD34 -> 0 | AN34: =AN33 -> 65 | AO34: =(AN34/100)*3000 -> 1950 | AP34: =AP33 -> 55 | AQ34: =(AP34/100)*3000 -> 1650 | AR34: =AR33 -> 61 | AS34: =(AR34/100)*3000 -> 1830 | AT34: =SUM(AO34+AQ34+AS34) -> 5430 | AU34: =AT33-AT34+AV34 -> 0 | AX34: =IF(AV34>0,AW34,AX33) -> 0.8
A35: =ELEC!C34 -> 44500 | B35: =B34 -> 157 | C35: =C34 -> 164 | D35: =C34-C35 -> 0 | E35: =D35*8.38 -> 0 | F35: =F34 -> 1891 | G35: =F35-F34 -> 0 | H35: =H34 -> 17176 | I35: =SUM(H35-H34) -> 0 | J35: =IF(G35>0,I35/G35,0) -> 0 | K35: =K34 -> 2356 | L35: =K35-K34 -> 0 | M35: =M34 -> 173915 | N35: =M35-M34 -> 0 | O35: =O34 -> 1869 | P35: =P34 -> 2129 | Q35: =Q34 -> 178720 | R35: =Q35-Q34 -> 0 | S35: =SUM(P35-P34) -> 0 | T35: =SUM(S35*$T$2) -> 0 | U35: =SUM(G35+L35+S35) -> 0 | V35: =R35+N35+I35:I35 -> 0 | X35: =X34 -> 2470 | Y35: =X35-X34 -> 0 | Z35: =Z34 -> 139138.1 | AA35: =Z35-Z34 -> 0 | AB35: =SUM(Y35*$AB$2) -> 0 | AC35: =AC34 -> 1942 | AD35: =AC35-AC34 -> 0 | AE35: =AE34 -> 366072 | AF35: =AE35-AE34 -> 0 | AG35: =IF(AD35>0,AF35/AD35,0) -> 0 | AH35: =AF35+AA35 -> 0 | AI35: =SUM(AH35+V35) -> 0 | AJ35: =-tanks!AW36 -> 0 | AK35: =SUM(AJ35-AI35) -> 0 | AL35: =S35+L35+G35 -> 0 | AM35: =Y35+AD35 -> 0 | AN35: =AN34 -> 65 | AO35: =(AN35/100)*3000 -> 1950 | AP35: =AP34 -> 55 | AQ35: =(AP35/100)*3000 -> 1650 | AR35: =AR34 -> 61 | AS35: =(AR35/100)*3000 -> 1830 | AT35: =SUM(AO35+AQ35+AS35) -> 5430 | AU35: =AT34-AT35+AV35 -> 0 | AX35: =IF(AV35>0,AW35,AX34) -> 0.8
J36: =SUM(J5:J32)/(COUNT(J5:J32)-COUNTIF(J5:J32,0)) -> 41 | V36: =SUM(V5:W35) -> #DIV/0! | AE36: . | AH36: =SUM(AH5:AH35) -> 0 | AL36: =SUM(AL5:AL35) -> 1 | AM36: =SUM(AM5:AM35) -> 0 | AR36: Nb Delivery | AS36: =COUNT(AW5:AW35) -> 0 | AU36: =SUM(AU5:AU35) -> 0 | AV36: =SUM(AV5:AV35) -> 0 | AW36: =SUM(AW5:AW35)/AS36 -> #DIV/0!
AH37: =AF37+AA37 -> 0 | AI37: =SUM(AI5:AI35) -> 81
AH38: =AF38+AA38 -> 0 | AU38: =AU36*0.51 -> 0 | AV38: =AV36/0.51 -> 0 | AW38: =SUM(AW5:AW32)/AS36 -> #DIV/0!
AV39: =AV36*0.51 -> 0

Sheet WATER
D1: =SUM(G21:G33) -> 8121399 | AR1: Entrance | AT1: Tank 1 | AV1: Tank 2
AR2: Level | AW2: Quantity CM3 | AZ2: Var
A3: Date | B3: Truck | C3: Truck M3/day | D3: N0. Trucks | F3: REQ. # of trucks | G3: City | H3: City/day | I3: Total water delivery | K3: SW | L3: Cosum SW/day | M3: RO Guest/ Liter | O3: RO K&L/ Liter | Q3: TOTAL RO Production | R3: RO 1 RH | S3: RO 2 RH | T3: RO water counter | U3: RO Cons m3 | V3: Steam Boiler | W3: Steam Boiler/day | X3: Softener Guest | Y3: Guest Sotf/day | Z3: Softener K&L | AA3: K&L Soft/Day | AB3: Fire Tank Level | AC3: Fire Tank Counter | AE3: Laundry Hot Water Counter | AF3: Hot Water Cons/day | AG3: Laundry Cold Water Counter | AH3: Cold Water Cons/day | AI3: Laundry Water Total Cons | AJ3: K&L Sotf/day | AK3: Guest / day | AL3: K&L /day | AM3: Avg Outside Temp | AN3: Banquet Activity | AR3: Date | AT3: MainI | AV3: Kitchen and Laundry | AX3: Guest | AY3: Main Tank | AZ3: Kitchen and Laundry | BA3: Guest | BB3: Kitchen and Laundry | BC3: Main | BD3: Guest | BE3: Total VAR | BF3: Hotel Consumption
E4: 1.66 | AN4: Ball R | AO4: Meeting | AP4: outlet | AT4: 180 | AV4: 220 | AX4: 580 | AY4: =SUM(AT4) -> 180 | AZ4: =SUM(AV4) -> 220 | BA4: =SUM(AX4) -> 580
A5: =[2]WATER!$A$35 -> 44469 | B5: =[2]WATER!B35 -> 109443 | C5: =[2]WATER!C35 -> 0 | D5: =[2]WATER!D35 -> 0 | E5: =[2]WATER!E35 -> 250 | F5: =[2]WATER!F35 -> 0 | G5: =[2]WATER!G35 -> 624723 | H5: =[2]WATER!H35 -> 0 | I5: =[2]WATER!I35 -> 0 | ... AP5: =[2]WATER!AP35 -> 0 | AR5: =[2]WATER!$AR$35 -> 44469 | AS5: =[2]WATER!AS35 -> 0.9 | AT5: =[2]WATER!AT35 -> 107 | AU5: =[2]WATER!AU35 -> 1.1 | AV5: =[2]WATER!AV35 -> 155 | AW5: =[2]WATER!AW35 -> 2.9 | AX5: =[2]WATER!AX35 -> 131 | AY5: =[2]WATER!AY35 -> 96.3 | AZ5: =[2]WATER!AZ35 -> 170.5 | ... BG5: =[2]WATER!BG35 -> -19
A6: =ELEC!C4 -> 44470 | B6: =B5 -> 109443 | C6: =B6-B5 -> 0 | D6: =C6/27 -> 0 | E6: =SUM((C6*$E$4)+(7500/'EDl log'!$A$37)) -> 241.93548 | G6: =G5 -> 624723 | H6: =G6-G5 -> 0 | I6: =C6+H6 -> 0 | J6: =IF(I6>0,E6/I6,0) -> 0 | K6: ='Swimming Pool quality check '!H6 -> 6884 | L6: 0 | M6: =M5 -> 457.44 | N6: =SUM(M6-M5) -> 0 | O6: =O5 -> 529.52 | P6: =SUM(O6-O5) -> 0 | Q6: =P6+N6 -> 0 | T6: 5176 | U6: =SUM(T6-T5) -> -4 | V6: =V5 -> 477 | W6: =+V6-V5 -> 0 | X6: =X5 -> 153815 | Y6: =SUM(X6-X5) -> 0 | Z6: 99258 | AA6: =Z6-Z5 -> 0 | AB6: =AB5 -> 238 | AC6: =AC5 -> 779 | AD6: 0 | AE6: =AE5 -> 238.2 | AF6: =AE6-AE5 -> 0 | AG6: 2215.8 | AH6: =AG6-AG5 -> 0 | AI6: =AF6+AH6 -> 0 | AJ6: =+Z6-Z5 -> 0 | AK6: =SUM(Y6-L6) -> 0 | AL6: =SUM(AJ6-W6) -> 0 | AM6: ='General information '!D5 -> 0 | AN6: ='General information '!H5 -> 0 | AP6: ='General information '!J5 -> 0 | AR6: =A6 -> 44470 | AS6: =AS5 -> 0.9 | AT6: =AT5 -> 107 | AU6: =AU5 -> 1.1 | AV6: =AV5 -> 155 | AW6: 2.9 | AX6: =AX5 -> 131 | AY6: =AY5 -> 96.3 | AZ6: =AU6*AV6 -> 170.5 | BA6: =AW6*AX6 -> 379.9 | BB6: =AY6-AY5 -> 0 | BC6: =AZ6-AZ5 -> 0 | BD6: =BA6-BA5 -> 0 | BE6: =SUM(BB6:BD6) -> 0 | BF6: =SUM(I6-BE6) -> 0 | BG6: =SUM(I6-BF6) -> 0
A7: =ELEC!C5 -> 44471 | B7: =B6 -> 109443 | C7: =B7-B6 -> 0 | D7: =C7/27 -> 0 | E7: =SUM((C7*$E$4)+(7500/'EDl log'!$A$37)) -> 241.93548 | G7: =G6 -> 624723 | H7: =G7-G6 -> 0 | I7: =C7+H7 -> 0 | J7: =IF(I7>0,E7/I7,0) -> 0 | K7: ='Swimming Pool quality check '!H7 -> 6884 | L7: =K7-K6 -> 0 | M7: =M6 -> 457.44 | N7: =SUM(M7-M6) -> 0 | O7: =O6 -> 529.52 | P7: =SUM(O7-O6) -> 0 | Q7: =P7+N7 -> 0 | T7: =T6 -> 5176 | U7: =SUM(T7-T6) -> 0 | V7: =V6 -> 477 | W7: =+V7-V6 -> 0 | X7: =X6 -> 153815 | Y7: =SUM(X7-X6) -> 0 | Z7: =Z6 -> 99258 | AA7: =Z7-Z6 -> 0 | AB7: =AB6 -> 238 | AC7: =AC6 -> 779 | AD7: =AC7-AC6 -> 0 | AE7: =AE6 -> 238.2 | AF7: =AE7-AE6 -> 0 | AG7: =AG6 -> 2215.8 | AH7: =AG7-AG6 -> 0 | AI7: =AF7+AH7 -> 0 | AJ7: =+Z7-Z6 -> 0 | AK7: =SUM(Y7-L7) -> 0 | AL7: =SUM(AJ7-W7) -> 0 | AM7: ='General information '!D6 -> 0 | AN7: ='General information '!H6 -> 0 | AP7: ='General information '!J6 -> 0 | AR7: =A7 -> 44471 | AS7: =AS6 -> 0.9 | AT7: =AT6 -> 107 | AU7: =AU6 -> 1.1 | AV7: =AV6 -> 155 | AW7: 2.9 | AX7: =AX6 -> 131 | AY7: =AS7*AT7 -> 96.3 | AZ7: =AU7*AV7 -> 170.5 | BA7: =AW7*AX7 -> 379.9 | BB7: =AY7-AY6 -> 0 | BC7: =AZ7-AZ6 -> 0 | BD7: =BA7-BA6 -> 0 | BE7: =SUM(BB7:BD7) -> 0 | BF7: =SUM(I7-BE7) -> 0 | BG7: =SUM(I7-BF7) -> 0
A8: =ELEC!C6 -> 44472 | B8: =B7 -> 109443 | C8: =B8-B7 -> 0 | D8: =C8/27 -> 0 | E8: =SUM((C8*$E$4)+(7500/'EDl log'!$A$37)) -> 241.93548 | G8: =G7 -> 624723 | H8: =G8-G7 -> 0 | I8: =C8+H8 -> 0 | J8: =IF(I8>0,E8/I8,0) -> 0 | K8: ='Swimming Pool quality check '!H8 -> 6886 | L8: =K8-K7 -> 2 | M8: =M7 -> 457.44 | N8: =SUM(M8-M7) -> 0 | O8: =O7 -> 529.52 | P8: =SUM(O8-O7) -> 0 | Q8: =P8+N8 -> 0 | T8: =T7 -> 5176 | U8: =SUM(T8-T7) -> 0 | V8: =V7 -> 477 | W8: =+V8-V7 -> 0 | X8: =X7 -> 153815 | Y8: =SUM(X8-X7) -> 0 | Z8: =Z7 -> 99258 | AA8: =Z8-Z7 -> 0 | AB8: 244 | AC8: =AC7 -> 779 | AD8: =AC8-AC7 -> 0 | AE8: 239.06 | AF8: =AE8-AE7 -> 0.86 | AG8: 2217.7 | AH8: =AG8-AG7 -> 1.9 | AI8: =AF8+AH8 -> 2.76 | AJ8: =+Z8-Z7 -> 0 | AK8: =SUM(Y8-L8) -> -2 | AL8: =SUM(AJ8-W8) -> 0 | AM8: ='General information '!D7 -> 26 | AN8: ='General information '!H7 -> 0 | AP8: ='General information '!J7 -> 0 | AR8: =A8 -> 44472 | AS8: =AS7 -> 0.9 | AT8: 120 | AU8: 1.1 | AV8: 154 | AW8: 2.9 | AX8: 125 | AY8: =AS8*AT8 -> 108 | AZ8: =AU8*AV8 -> 169.4 | BA8: =AW8*AX8 -> 362.5 | BB8: =AY8-AY7 -> 11.7 | BC8: =AZ8-AZ7 -> -1.1 | BD8: =BA8-BA7 -> -17.4 | BE8: =SUM(BB8:BD8) -> -6.8 | BF8: =SUM(I8-BE8) -> 6.8 | BG8: =SUM(I8-BF8) -> -6.8
A9: =ELEC!C7 -> 44473 | B9: =B8 -> 109443 | C9: =B9-B8 -> 0 | D9: =C9/27 -> 0 | E9: =SUM((C9*$E$4)+(7500/'EDl log'!$A$37)) -> 241.93548 | G9: =G8 -> 624723 | H9: =G9-G8 -> 0 | I9: =C9+H9 -> 0 | J9: =IF(I9>0,E9/I9,0) -> 0 | K9: ='Swimming Pool quality check '!H9 -> 6886 | L9: =K9-K8 -> 0 | M9: =M8 -> 457.44 | N9: =SUM(M9-M8) -> 0 | O9: =O8 -> 529.52 | P9: =SUM(O9-O8) -> 0 | Q9: =P9+N9 -> 0 | T9: =T8 -> 5176 | U9: =SUM(T9-T8) -> 0 | V9: =V8 -> 477 | W9: =+V9-V8 -> 0 | X9: =X8 -> 153815 | Y9: =SUM(X9-X8) -> 0 | Z9: =Z8 -> 99258 | AA9: =Z9-Z8 -> 0 | AB9: =AB8 -> 244 | AC9: =AC8 -> 779 | AD9: =AC9-AC8 -> 0 | AE9: =AE8 -> 239.06 | AF9: =AE9-AE8 -> 0 | AG9: =AG8 -> 2217.7 | AH9: =AG9-AG8 -> 0 | AI9: =AF9+AH9 -> 0 | AJ9: =+Z9-Z8 -> 0 | AK9: =SUM(Y9-L9) -> 0 | AL9: =SUM(AJ9-W9) -> 0 | AM9: ='General information '!D8 -> 0 | AN9: ='General information '!H8 -> 0 | AP9: ='General information '!J8 -> 0 | AR9: =A9 -> 44473 | AS9: =AS8 -> 0.9 | AT9: =AT8 -> 120 | AU9: =AU8 -> 1.1 | AV9: =AV8 -> 154 | AW9: 2.9 | AX9: =AX8 -> 125 | AY9: =AS9*AT9 -> 108 | AZ9: =AU9*AV9 -> 169.4 | BA9: =AW9*AX9 -> 362.5 | BB9: =AY9-AY8 -> 0 | BC9: =AZ9-AZ8 -> 0 | BD9: =BA9-BA8 -> 0 | BE9: =SUM(BB9:BD9) -> 0 | BF9: =SUM(I9-BE9) -> 0 | BG9: =SUM(I9-BF9) -> 0
A10: =ELEC!C8 -> 44474 | B10: =B9 -> 109443 | C10: =B10-B9 -> 0 | D10: =C10/27 -> 0 | E10: =SUM((C10*$E$4)+(7500/'EDl log'!$A$37)) -> 241.93548 | G10: =G9 -> 624723 | H10: =G10-G9 -> 0 | I10: =C10+H10 -> 0 | J10: =IF(I10>0,E10/I10,0) -> 0 | K10: ='Swimming Pool quality check '!H10 -> 6886 | L10: =K10-K9 -> 0 | M10: =M9 -> 457.44 | N10: =SUM(M10-M9) -> 0 | O10: =O9 -> 529.52 | P10: =SUM(O10-O9) -> 0 | Q10: =P10+N10 -> 0 | T10: =T9 -> 5176 | U10: =SUM(T10-T9) -> 0 | V10: =V9 -> 477 | W10: =+V10-V9 -> 0 | X10: =X9 -> 153815 | Y10: =SUM(X10-X9) -> 0 | Z10: =Z9 -> 99258 | AA10: =Z10-Z9 -> 0 | AB10: =AB9 -> 244 | AC10: =AC9 -> 779 | AD10: =AC10-AC9 -> 0 | AE10: =AE9 -> 239.06 | AF10: =AE10-AE9 -> 0 | AG10: =AG9 -> 2217.7 | AH10: =AG10-AG9 -> 0 | AI10: =AF10+AH10 -> 0 | AJ10: =+Z10-Z9 -> 0 | AK10: =SUM(Y10-L10) -> 0 | AL10: =SUM(AJ10-W10) -> 0 | AM10: ='General information '!D9 -> 0 | AN10: ='General information '!H9 -> 0 | AP10: ='General information '!J9 -> 0 | AR10: =A10 -> 44474 | AS10: =AS9 -> 0.9 | AT10: =AT9 -> 120 | AU10: =AU9 -> 1.1 | AV10: =AV9 -> 154 | AW10: 2.9 | AX10: =AX9 -> 125 | AY10: =AS10*AT10 -> 108 | AZ10: =AU10*AV10 -> 169.4 | BA10: =AW10*AX10 -> 362.5 | BB10: =AY10-AY9 -> 0 | BC10: =AZ10-AZ9 -> 0 | BD10: =BA10-BA9 -> 0 | BE10: =SUM(BB10:BD10) -> 0 | BF10: =SUM(I10-BE10) -> 0 | BG10: =SUM(I10-BF10) -> 0
A11: =ELEC!C9 -> 44475 | B11: =B10 -> 109443 | C11: =B11-B10 -> 0 | D11: =C11/27 -> 0 | E11: =SUM((C11*$E$4)+(7500/'EDl log'!$A$37)) -> 241.93548 | G11: =G10 -> 624723 | H11: =G11-G10 -> 0 | I11: =C11+H11 -> 0 | J11: =IF(I11>0,E11/I11,0) -> 0 | K11: ='Swimming Pool quality check '!H11 -> 6886 | L11: =K11-K10 -> 0 | M11: =M10 -> 457.44 | N11: =SUM(M11-M10) -> 0 | O11: =O10 -> 529.52 | P11: =SUM(O11-O10) -> 0 | Q11: =SUM(P11+N11) -> 0 | T11: =T10 -> 5176 | U11: =SUM(T11-T10) -> 0 | V11: =V10 -> 477 | W11: =+V11-V10 -> 0 | X11: =X10 -> 153815 | Y11: =SUM(X11-X10) -> 0 | Z11: =Z10 -> 99258 | AA11: =Z11-Z10 -> 0 | AB11: =AB10 -> 244 | AC11: =AC10 -> 779 | AD11: =AC11-AC10 -> 0 | AE11: =AE10 -> 239.06 | AF11: =AE11-AE10 -> 0 | AG11: =AG10 -> 2217.7 | AH11: =AG11-AG10 -> 0 | AI11: =AF11+AH11 -> 0 | AJ11: =+Z11-Z10 -> 0 | AK11: =SUM(Y11-L11) -> 0 | AL11: =SUM(AJ11-W11) -> 0 | AM11: ='General information '!D10 -> 0 | AN11: ='General information '!H10 -> 0 | AP11: ='General information '!J10 -> 0 | AR11: =A11 -> 44475 | AS11: =AS10 -> 0.9 | AT11: =AT10 -> 120 | AU11: =AU10 -> 1.1 | AV11: =AV10 -> 154 | AW11: 2.9 | AX11: =AX10 -> 125 | AY11: =AS11*AT11 -> 108 | AZ11: =AU11*AV11 -> 169.4 | BA11: =AW11*AX11 -> 362.5 | BB11: =AY11-AY10 -> 0 | BC11: =AZ11-AZ10 -> 0 | BD11: =BA11-BA10 -> 0 | BE11: =SUM(BB11:BD11) -> 0 | BF11: =SUM(I11-BE11) -> 0 | BG11: =SUM(I11-BF11) -> 0
A12: =ELEC!C10 -> 44476 | B12: =B11 -> 109443 | C12: =B12-B11 -> 0 | D12: =C12/27 -> 0 | E12: =SUM((C12*$E$4)+(7500/'EDl log'!$A$37)) -> 241.93548 | G12: =G11 -> 624723 | H12: =G12-G11 -> 0 | I12: =C12+H12 -> 0 | J12: =IF(I12>0,E12/I12,0) -> 0 | K12: ='Swimming Pool quality check '!H12 -> 6886 | L12: =K12-K11 -> 0 | M12: =M11 -> 457.44 | N12: =SUM(M12-M11) -> 0 | O12: =O11 -> 529.52 | P12: =SUM(O12-O11) -> 0 | Q12: =SUM(P12+N12) -> 0 | T12: =T11 -> 5176 | U12: =SUM(T12-T11) -> 0 | V12: =V11 -> 477 | W12: =+V12-V11 -> 0 | X12: =X11 -> 153815 | Y12: =SUM(X12-X11) -> 0 | Z12: =Z11 -> 99258 | AA12: =Z12-Z11 -> 0 | AB12: =AB11 -> 244 | AC12: =AC11 -> 779 | AD12: =AC12-AC11 -> 0 | AE12: =AE11 -> 239.06 | AF12: =AE12-AE11 -> 0 | AG12: =AG11 -> 2217.7 | AH12: =AG12-AG11 -> 0 | AI12: =AF12+AH12 -> 0 | AJ12: =+Z12-Z11 -> 0 | AK12: =SUM(Y12-L12) -> 0 | AL12: =SUM(AJ12-W12) -> 0 | AM12: ='General information '!D11 -> 0 | AN12: ='General information '!H11 -> 0 | AP12: ='General information '!J11 -> 0 | AR12: =A12 -> 44476 | AS12: =AS11 -> 0.9 | AT12: =AT11 -> 120 | AU12: =AU11 -> 1.1 | AV12: =AV11 -> 154 | AW12: 2.9 | AX12: =AX11 -> 125 | AY12: =AS12*AT12 -> 108 | AZ12: =AU12*AV12 -> 169.4 | BA12: =AW12*AX12 -> 362.5 | BB12: =AY12-AY11 -> 0 | BC12: =AZ12-AZ11 -> 0 | BD12: =BA12-BA11 -> 0 | BE12: =SUM(BB12:BD12) -> 0 | BF12: =SUM(I12-BE12) -> 0 | BG12: =SUM(I12-BF12) -> 0
A13: =ELEC!C11 -> 44477 | B13: =B12 -> 109443 | C13: =B13-B12 -> 0 | D13: =C13/27 -> 0 | E13: =SUM((C13*$E$4)+(7500/'EDl log'!$A$37)) -> 241.93548 | G13: =G12 -> 624723 | H13: =G13-G12 -> 0 | I13: =C13+H13 -> 0 | J13: =IF(I13>0,E13/I13,0) -> 0 | K13: ='Swimming Pool quality check '!H13 -> 6886 | L13: =K13-K12 -> 0 | M13: =M12 -> 457.44 | N13: =SUM(M13-M12) -> 0 | O13: =O12 -> 529.52 | P13: =SUM(O13-O12) -> 0 | Q13: =SUM(P13+N13) -> 0 | T13: =T12 -> 5176 | U13: =SUM(T13-T12) -> 0 | V13: =V12 -> 477 | W13: =+V13-V12 -> 0 | X13: =X12 -> 153815 | Y13: =SUM(X13-X12) -> 0 | Z13: =Z12 -> 99258 | AA13: =Z13-Z12 -> 0 | AB13: =AB12 -> 244 | AC13: =AC12 -> 779 | AD13: =AC13-AC12 -> 0 | AE13: =AE12 -> 239.06 | AF13: =AE13-AE12 -> 0 | AG13: =AG12 -> 2217.7 | AH13: =AG13-AG12 -> 0 | AI13: =AF13+AH13 -> 0 | AJ13: =+Z13-Z12 -> 0 | AK13: =SUM(Y13-L13) -> 0 | AL13: =SUM(AJ13-W13) -> 0 | AM13: ='General information '!D12 -> 0 | AN13: ='General information '!J12 -> 0 | AP13: ='General information '!J12 -> 0 | AR13: =A13 -> 44477 | AS13: =AS12 -> 0.9 | AT13: =AT12 -> 120 | AU13: =AU12 -> 1.1 | AV13: =AV12 -> 154 | AW13: 2.9 | AX13: =AX12 -> 125 | AY13: =AS13*AT13 -> 108 | AZ13: =AU13*AV13 -> 169.4 | BA13: =AW13*AX13 -> 362.5 | BB13: =AY13-AY12 -> 0 | BC13: =AZ13-AZ12 -> 0 | BD13: =BA13-BA12 -> 0 | BE13: =SUM(BB13:BD13) -> 0 | BF13: =SUM(I13-BE13) -> 0 | BG13: =SUM(I13-BF13) -> 0
A14: =ELEC!C12 -> 44478 | B14: =B13 -> 109443 | C14: =B14-B13 -> 0 | D14: =C14/27 -> 0 | E14: =SUM((C14*$E$4)+(7500/'EDl log'!$A$37)) -> 241.93548 | G14: =G13 -> 624723 | H14: =G14-G13 -> 0 | I14: =C14+H14 -> 0 | J14: =IF(I14>0,E14/I14,0) -> 0 | K14: ='Swimming Pool quality check '!H14 -> 6886 | L14: =K14-K13 -> 0 | M14: =M13 -> 457.44 | N14: =SUM(M14-M13) -> 0 | O14: =O13 -> 529.52 | P14: =SUM(O14-O13) -> 0 | Q14: =SUM(P14+N14) -> 0 | T14: =T13 -> 5176 | U14: =SUM(T14-T13) -> 0 | V14: =V13 -> 477 | W14: =+V14-V13 -> 0 | X14: =X13 -> 153815 | Y14: =SUM(X14-X13) -> 0 | Z14: =Z13 -> 99258 | AA14: =Z14-Z13 -> 0 | AB14: =AB13 -> 244 | AC14: =AC13 -> 779 | AD14: =AC14-AC13 -> 0 | AE14: =AE13 -> 239.06 | AF14: =AE14-AE13 -> 0 | AG14: =AG13 -> 2217.7 | AH14: =AG14-AG13 -> 0 | AI14: =AF14+AH14 -> 0 | AJ14: =+Z14-Z13 -> 0 | AK14: =SUM(Y14-L14) -> 0 | AL14: =SUM(AJ14-W14) -> 0 | AM14: ='General information '!D13 -> 0 | AN14: ='General information '!H13 -> 0 | AP14: ='General information '!J13 -> 0 | AR14: =A14 -> 44478 | AS14: =AS13 -> 0.9 | AT14: =AT13 -> 120 | AU14: =AU13 -> 1.1 | AV14: =AV13 -> 154 | AW14: 2.9 | AX14: =AX13 -> 125 | AY14: =AS14*AT14 -> 108 | AZ14: =AU14*AV14 -> 169.4 | BA14: =AW14*AX14 -> 362.5 | BB14: =AY14-AY13 -> 0 | BC14: =AZ14-AZ13 -> 0 | BD14: =BA14-BA13 -> 0 | BE14: =SUM(BB14:BD14) -> 0 | BF14: =SUM(I14-BE14) -> 0 | BG14: =SUM(I14-BF14) -> 0
A15: =ELEC!C13 -> 44479 | B15: =B14 -> 109443 | C15: =B15-B14 -> 0 | D15: =C15/27 -> 0 | E15: =SUM((C15*$E$4)+(7500/'EDl log'!$A$37)) -> 241.93548 | G15: =G14 -> 624723 | H15: =G15-G14 -> 0 | I15: =C15+H15 -> 0 | J15: =IF(I15>0,E15/I15,0) -> 0 | K15: ='Swimming Pool quality check '!H15 -> 6886 | L15: =K15-K14 -> 0 | M15: =M14 -> 457.44 | N15: =SUM(M15-M14) -> 0 | O15: =O14 -> 529.52 | P15: =SUM(O15-O14) -> 0 | Q15: =SUM(P15+N15) -> 0 | T15: =T14 -> 5176 | U15: =SUM(T15-T14) -> 0 | V15: =V14 -> 477 | W15: =+V15-V14 -> 0 | X15: =X14 -> 153815 | Y15: =SUM(X15-X14) -> 0 | Z15: =Z14 -> 99258 | AA15: =Z15-Z14 -> 0 | AB15: =AB14 -> 244 | AC15: =AC14 -> 779 | AD15: =AC15-AC14 -> 0 | AE15: =AE14 -> 239.06 | AF15: =AE15-AE14 -> 0 | AG15: =AG14 -> 2217.7 | AH15: =AG15-AG14 -> 0 | AI15: =AF15+AH15 -> 0 | AJ15: =+Z15-Z14 -> 0 | AK15: =SUM(Y15-L15) -> 0 | AL15: =SUM(AJ15-W15) -> 0 | AM15: ='General information '!D14 -> 0 | AN15: ='General information '!H14 -> 0 | AP15: ='General information '!J14 -> 0 | AR15: =A15 -> 44479 | AS15: =AS14 -> 0.9 | AT15: =AT14 -> 120 | AU15: =AU14 -> 1.1 | AV15: =AV14 -> 154 | AW15: 2.9 | AX15: =AX14 -> 125 | AY15: =AS15*AT15 -> 108 | AZ15: =AU15*AV15 -> 169.4 | BA15: =AW15*AX15 -> 362.5 | BB15: =AY15-AY14 -> 0 | BC15: =AZ15-AZ14 -> 0 | BD15: =BA15-BA14 -> 0 | BE15: =SUM(BB15:BD15) -> 0 | BF15: =SUM(I15-BE15) -> 0 | BG15: =SUM(I15-BF15) -> 0
A16: =ELEC!C14 -> 44480 | B16: =B15 -> 109443 | C16: =B16-B15 -> 0 | D16: =C16/27 -> 0 | E16: =SUM((C16*$E$4)+(7500/'EDl log'!$A$37)) -> 241.93548 | G16: =G15 -> 624723 | H16: =G16-G15 -> 0 | I16: =C16+H16 -> 0 | J16: =IF(I16>0,E16/I16,0) -> 0 | K16: ='Swimming Pool quality check '!H16 -> 6886 | L16: =K16-K15 -> 0 | M16: =M15 -> 457.44 | N16: =SUM(M16-M15) -> 0 | O16: =O15 -> 529.52 | P16: =SUM(O16-O15) -> 0 | Q16: =SUM(P16+N16) -> 0 | T16: =T15 -> 5176 | U16: =SUM(T16-T15) -> 0 | V16: =V15 -> 477 | W16: =+V16-V15 -> 0 | X16: =X15 -> 153815 | Y16: =SUM(X16-X15) -> 0 | Z16: =Z15 -> 99258 | AA16: =Z16-Z15 -> 0 | AB16: =AB15 -> 244 | AC16: =AC15 -> 779 | AD16: =AC16-AC15 -> 0 | AE16: =AE15 -> 239.06 | AF16: =AE16-AE15 -> 0 | AG16: =AG15 -> 2217.7 | AH16: =AG16-AG15 -> 0 | AI16: =AF16+AH16 -> 0 | AJ16: =+Z16-Z15 -> 0 | AK16: =SUM(Y16-L16) -> 0 | AL16: =SUM(AJ16-W16) -> 0 | AM16: ='General information '!D15 -> 0 | AN16: ='General information '!H15 -> 0 | AP16: ='General information '!J15 -> 0 | AR16: =A16 -> 44480 | AS16: =AS15 -> 0.9 | AT16: =AT15 -> 120 | AU16: =AU15 -> 1.1 | AV16: =AV15 -> 154 | AW16: 2.9 | AX16: =AX15 -> 125 | AY16: =AS16*AT16 -> 108 | AZ16: =AU16*AV16 -> 169.4 | BA16: =AW16*AX16 -> 362.5 | BB16: =AY16-AY15 -> 0 | BC16: =AZ16-AZ15 -> 0 | BD16: =BA16-BA15 -> 0 | BE16: =SUM(BB16:BD16) -> 0 | BF16: =SUM(I16-BE16) -> 0 | BG16: =SUM(I16-BF16) -> 0
A17: =ELEC!C15 -> 44481 | B17: =B16 -> 109443 | C17: =B17-B16 -> 0 | D17: =C17/27 -> 0 | E17: =SUM((C17*$E$4)+(7500/'EDl log'!$A$37)) -> 241.93548 | G17: =G16 -> 624723 | H17: =G17-G16 -> 0 | I17: =C17+H17 -> 0 | J17: =IF(I17>0,E17/I17,0) -> 0 | K17: ='Swimming Pool quality check '!H17 -> 6886 | L17: =K17-K16 -> 0 | M17: =M16 -> 457.44 | N17: =SUM(M17-M16) -> 0 | O17: =O16 -> 529.52 | P17: =SUM(O17-O16) -> 0 | Q17: =SUM(P17+N17) -> 0 | T17: =T16 -> 5176 | U17: =SUM(T17-T16) -> 0 | V17: =V16 -> 477 | W17: =+V17-V16 -> 0 | X17: =X16 -> 153815 | Y17: =SUM(X17-X16) -> 0 | Z17: =Z16 -> 99258 | AA17: =Z17-Z16 -> 0 | AB17: =AB16 -> 244 | AC17: =AC16 -> 779 | AD17: =AC17-AC16 -> 0 | AE17: =AE16 -> 239.06 | AF17: =AE17-AE16 -> 0 | AG17: =AG16 -> 2217.7 | AH17: =AG17-AG16 -> 0 | AI17: =AF17+AH17 -> 0 | AJ17: =+Z17-Z16 -> 0 | AK17: =SUM(Y17-L17) -> 0 | AL17: =SUM(AJ17-W17) -> 0 | AM17: ='General information '!D16 -> 0 | AN17: ='General information '!H16 -> 0 | AP17: ='General information '!J16 -> 0 | AR17: =A17 -> 44481 | AS17: =AS16 -> 0.9 | AT17: =AT16 -> 120 | AU17: =AU16 -> 1.1 | AV17: =AV16 -> 154 | AW17: 2.9 | AX17: =AX16 -> 125 | AY17: =AS17*AT17 -> 108 | AZ17: =AU17*AV17 -> 169.4 | BA17: =AW17*AX17 -> 362.5 | BB17: =AY17-AY16 -> 0 | BC17: =AZ17-AZ16 -> 0 | BD17: =BA17-BA16 -> 0 | BE17: =SUM(BB17:BD17) -> 0 | BF17: =SUM(I17-BE17) -> 0 | BG17: =SUM(I17-BF17) -> 0
A18: =ELEC!C16 -> 44482 | B18: =B17 -> 109443 | C18: =B18-B17 -> 0 | D18: =C18/27 -> 0 | E18: =SUM((C18*$E$4)+(7500/'EDl log'!$A$37)) -> 241.93548 | G18: =G17 -> 624723 | H18: =G18-G17 -> 0 | I18: =C18+H18 -> 0 | J18: =IF(I18>0,E18/I18,0) -> 0 | K18: ='Swimming Pool quality check '!H18 -> 6886 | L18: =K18-K17 -> 0 | M18: =M17 -> 457.44 | N18: =SUM(M18-M17) -> 0 | O18: =O17 -> 529.52 | P18: =SUM(O18-O17) -> 0 | Q18: =SUM(P18+N18) -> 0 | T18: =T17 -> 5176 | U18: =SUM(T18-T17) -> 0 | V18: =V17 -> 477 | W18: =+V18-V17 -> 0 | X18: =X17 -> 153815 | Y18: =SUM(X18-X17) -> 0 | Z18: =Z17 -> 99258 | AA18: =Z18-Z17 -> 0 | AB18: =AB17 -> 244 | AC18: =AC17 -> 779 | AD18: =AC18-AC17 -> 0 | AE18: =AE17 -> 239.06 | AF18: =AE18-AE17 -> 0 | AG18: =AG17 -> 2217.7 | AH18: =AG18-AG17 -> 0 | AI18: =AF18+AH18 -> 0 | AJ18: =+Z18-Z17 -> 0 | AK18: =SUM(Y18-L18) -> 0 | AL18: =SUM(AJ18-W18) -> 0 | AM18: ='General information '!D17 -> 0 | AN18: ='General information '!H17 -> 0 | AP18: ='General information '!J17 -> 0 | AR18: =A18 -> 44482 | AS18: =AS17 -> 0.9 | AT18: =AT17 -> 120 | AU18: =AU17 -> 1.1 | AV18: =AV17 -> 154 | AW18: 2.9 | AX18: =AX17 -> 125 | AY18: =AS18*AT18 -> 108 | AZ18: =AU18*AV18 -> 169.4 | BA18: =AW18*AX18 -> 362.5 | BB18: =AY18-AY17 -> 0 | BC18: =AZ18-AZ17 -> 0 | BD18: =BA18-BA17 -> 0 | BE18: =SUM(BB18:BD18) -> 0 | BF18: =SUM(I18-BE18) -> 0 | BG18: =SUM(I18-BF18) -> 0
A19: =ELEC!C17 -> 44483 | B19: =B18 -> 109443 | C19: =B19-B18 -> 0 | D19: =C19/27 -> 0 | E19: =SUM((C19*$E$4)+(7500/'EDl log'!$A$37)) -> 241.93548 | G19: =G18 -> 624723 | H19: =G19-G18 -> 0 | I19: =C19+H19 -> 0 | J19: =IF(I19>0,E19/I19,0) -> 0 | K19: ='Swimming Pool quality check '!H19 -> 6886 | L19: =K19-K18 -> 0 | M19: =M18 -> 457.44 | N19: =SUM(M19-M18) -> 0 | O19: =O18 -> 529.52 | P19: =SUM(O19-O18) -> 0 | Q19: =SUM(P19+N19) -> 0 | T19: =T18 -> 5176 | U19: =SUM(T19-T18) -> 0 | V19: =V18 -> 477 | W19: =+V19-V18 -> 0 | X19: =X18 -> 153815 | Y19: =SUM(X19-X18) -> 0 | Z19: =Z18 -> 99258 | AA19: =Z19-Z18 -> 0 | AB19: =AB18 -> 244 | AC19: =AC18 -> 779 | AD19: =AC19-AC18 -> 0 | AE19: =AE18 -> 239.06 | AF19: =AE19-AE18 -> 0 | AG19: =AG18 -> 2217.7 | AH19: =AG19-AG18 -> 0 | AI19: =AF19+AH19 -> 0 | AJ19: =+Z19-Z18 -> 0 | AK19: =SUM(Y19-L19) -> 0 | AL19: =SUM(AJ19-W19) -> 0 | AM19: ='General information '!D18 -> 0 | AN19: ='General information '!H18 -> 0 | AP19: ='General information '!J18 -> 0 | AR19: =A19 -> 44483 | AS19: =AS18 -> 0.9 | AT19: =AT18 -> 120 | AU19: =AU18 -> 1.1 | AV19: =AV18 -> 154 | AW19: 2.9 | AX19: =AX18 -> 125 | AY19: =AS19*AT19 -> 108 | AZ19: =AU19*AV19 -> 169.4 | BA19: =AW19*AX19 -> 362.5 | BB19: =AY19-AY18 -> 0 | BC19: =AZ19-AZ18 -> 0 | BD19: =BA19-BA18 -> 0 | BE19: =SUM(BB19:BD19) -> 0 | BF19: =SUM(I19-BE19) -> 0 | BG19: =SUM(I19-BF19) -> 0
A20: =ELEC!C18 -> 44484 | B20: =B19 -> 109443 | C20: =B20-B19 -> 0 | D20: =C20/27 -> 0 | E20: =SUM((C20*$E$4)+(7500/'EDl log'!$A$37)) -> 241.93548 | G20: =G19 -> 624723 | H20: =G20-G19 -> 0 | I20: =C20+H20 -> 0 | J20: =IF(I20>0,E20/I20,0) -> 0 | K20: ='Swimming Pool quality check '!H20 -> 6886 | L20: =K20-K19 -> 0 | M20: =M19 -> 457.44 | N20: =SUM(M20-M19) -> 0 | O20: =O19 -> 529.52 | P20: =SUM(O20-O19) -> 0 | Q20: =SUM(P20+N20) -> 0 | T20: =T19 -> 5176 | U20: =SUM(T20-T19) -> 0 | V20: =V19 -> 477 | W20: =+V20-V19 -> 0 | X20: =X19 -> 153815 | Y20: =SUM(X20-X19) -> 0 | Z20: =Z19 -> 99258 | AA20: =Z20-Z19 -> 0 | AB20: =AB19 -> 244 | AC20: =AC19 -> 779 | AD20: =AC20-AC19 -> 0 | AE20: =AE19 -> 239.06 | AF20: =AE20-AE19 -> 0 | AG20: =AG19 -> 2217.7 | AH20: =AG20-AG19 -> 0 | AI20: =AF20+AH20 -> 0 | AJ20: =+Z20-Z19 -> 0 | AK20: =SUM(Y20-L20) -> 0 | AL20: =SUM(AJ20-W20) -> 0 | AM20: ='General information '!D19 -> 0 | AN20: ='General information '!H19 -> 0 | AP20: ='General information '!J19 -> 0 | AR20: =A20 -> 44484 | AS20: =AS19 -> 0.9 | AT20: =AT19 -> 120 | AU20: =AU19 -> 1.1 | AV20: =AV19 -> 154 | AW20: 2.9 | AX20: =AX19 -> 125 | AY20: =AS20*AT20 -> 108 | AZ20: =AU20*AV20 -> 169.4 | BA20: =AW20*AX20 -> 362.5 | BB20: =AY20-AY19 -> 0 | BC20: =AZ20-AZ19 -> 0 | BD20: =BA20-BA19 -> 0 | BE20: =SUM(BB20:BD20) -> 0 | BF20: =SUM(I20-BE20) -> 0 | BG20: =SUM(I20-BF20) -> 0
A21: =ELEC!C19 -> 44485 | B21: =B20 -> 109443 | C21: =B21-B20 -> 0 | D21: =C21/27 -> 0 | E21: =SUM((C21*$E$4)+(7500/'EDl log'!$A$37)) -> 241.93548 | G21: =G20 -> 624723 | H21: =G21-G20 -> 0 | I21: =C21+H21 -> 0 | J21: =IF(I21>0,E21/I21,0) -> 0 | K21: ='Swimming Pool quality check '!H21 -> 6886 | L21: =K21-K20 -> 0 | M21: =M20 -> 457.44 | N21: =SUM(M21-M20) -> 0 | O21: =O20 -> 529.52 | P21: =SUM(O21-O20) -> 0 | Q21: =SUM(P21+N21) -> 0 | T21: =T20 -> 5176 | U21: =SUM(T21-T20) -> 0 | V21: =V20 -> 477 | W21: =+V21-V20 -> 0 | X21: =X20 -> 153815 | Y21: =SUM(X21-X20) -> 0 | Z21: =Z20 -> 99258 | AA21: =Z21-Z20 -> 0 | AB21: =AB20 -> 244 | AC21: =AC20 -> 779 | AD21: =AC21-AC20 -> 0 | AE21: 238.2 | AF21: =AE21-AE20 -> -0.86 | AG21: 2215.8 | AH21: =AG21-AG20 -> -1.9 | AI21: =AF21+AH21 -> -2.76 | AJ21: =+Z21-Z20 -> 0 | AK21: =SUM(Y21-L21) -> 0 | AL21: =SUM(AJ21-W21) -> 0 | AM21: ='General information '!D20 -> 0 | AN21: ='General information '!H20 -> 0 | AP21: ='General information '!J20 -> 0 | AR21: =A21 -> 44485 | AS21: =AS20 -> 0.9 | AT21: =AT20 -> 120 | AU21: =AU20 -> 1.1 | AV21: =AV20 -> 154 | AW21: 2.9 | AX21: =AX20 -> 125 | AY21: =AS21*AT21 -> 108 | AZ21: =AU21*AV21 -> 169.4 | BA21: =AW21*AX21 -> 362.5 | BB21: =AY21-AY20 -> 0 | BC21: =AZ21-AZ20 -> 0 | BD21: =BA21-BA20 -> 0 | BE21: =SUM(BB21:BD21) -> 0 | BF21: =SUM(I21-BE21) -> 0 | BG21: =SUM(I21-BF21) -> 0
A22: =ELEC!C20 -> 44486 | B22: =B21 -> 109443 | C22: =B22-B21 -> 0 | D22: =C22/27 -> 0 | E22: =SUM((C22*$E$4)+(7500/'EDl log'!$A$37)) -> 241.93548 | G22: =G21 -> 624723 | H22: =G22-G21 -> 0 | I22: =C22+H22 -> 0 | J22: =IF(I22>0,E22/I22,0) -> 0 | K22: ='Swimming Pool quality check '!H22 -> 6886 | L22: =K22-K21 -> 0 | M22: =M21 -> 457.44 | N22: =SUM(M22-M21) -> 0 | O22: =O21 -> 529.52 | P22: =SUM(O22-O21) -> 0 | Q22: =SUM(P22+N22) -> 0 | T22: =T21 -> 5176 | U22: =SUM(T22-T21) -> 0 | V22: =V21 -> 477 | W22: =+V22-V21 -> 0 | X22: =X21 -> 153815 | Y22: =SUM(X22-X21) -> 0 | Z22: =Z21 -> 99258 | AA22: =Z22-Z21 -> 0 | AB22: =AB21 -> 244 | AC22: =AC21 -> 779 | AD22: =AC22-AC21 -> 0 | AE22: =AE21 -> 238.2 | AF22: =AE22-AE21 -> 0 | AG22: =AG21 -> 2215.8 | AH22: =AG22-AG21 -> 0 | AI22: =AF22+AH22 -> 0 | AJ22: =+Z22-Z21 -> 0 | AK22: =SUM(Y22-L22) -> 0 | AL22: =SUM(AJ22-W22) -> 0 | AM22: ='General information '!D21 -> 0 | AN22: ='General information '!H21 -> 0 | AP22: ='General information '!J21 -> 0 | AR22: =A22 -> 44486 | AS22: =AS21 -> 0.9 | AT22: =AT21 -> 120 | AU22: =AU21 -> 1.1 | AV22: =AV21 -> 154 | AW22: 2.9 | AX22: =AX21 -> 125 | AY22: =AS22*AT22 -> 108 | AZ22: =AU22*AV22 -> 169.4 | BA22: =AW22*AX22 -> 362.5 | BB22: =AY22-AY21 -> 0 | BC22: =AZ22-AZ21 -> 0 | BD22: =BA22-BA21 -> 0 | BE22: =SUM(BB22:BD22) -> 0 | BF22: =SUM(I22-BE22) -> 0 | BG22: =SUM(I22-BF22) -> 0
A23: =ELEC!C21 -> 44487 | B23: =B22 -> 109443 | C23: =B23-B22 -> 0 | D23: =C23/27 -> 0 | E23: =SUM((C23*$E$4)+(7500/'EDl log'!$A$37)) -> 241.93548 | G23: =G22 -> 624723 | H23: =G23-G22 -> 0 | I23: =C23+H23 -> 0 | J23: =IF(I23>0,E23/I23,0) -> 0 | K23: ='Swimming Pool quality check '!H23 -> 6886 | L23: =K23-K22 -> 0 | M23: =M22 -> 457.44 | N23: =SUM(M23-M22) -> 0 | O23: =O22 -> 529.52 | P23: =SUM(O23-O22) -> 0 | Q23: =SUM(P23+N23) -> 0 | T23: =T22 -> 5176 | U23: =SUM(T23-T22) -> 0 | V23: =V22 -> 477 | W23: =+V23-V22 -> 0 | X23: =X22 -> 153815 | Y23: =SUM(X23-X22) -> 0 | Z23: =Z22 -> 99258 | AA23: =Z23-Z22 -> 0 | AB23: =AB22 -> 244 | AC23: =AC22 -> 779 | AD23: =AC23-AC22 -> 0 | AE23: =AE22 -> 238.2 | AF23: =AE23-AE22 -> 0 | AG23: =AG22 -> 2215.8 | AH23: =AG23-AG22 -> 0 | AI23: =AF23+AH23 -> 0 | AJ23: =+Z23-Z22 -> 0 | AK23: =SUM(Y23-L23) -> 0 | AL23: =SUM(AJ23-W23) -> 0 | AM23: ='General information '!D22 -> 0 | AN23: ='General information '!H22 -> 0 | AP23: ='General information '!J22 -> 0 | AR23: =A23 -> 44487 | AS23: =AS22 -> 0.9 | AT23: =AT22 -> 120 | AU23: =AU22 -> 1.1 | AV23: =AV22 -> 154 | AW23: 2.9 | AX23: =AX22 -> 125 | AY23: =AS23*AT23 -> 108 | AZ23: =AU23*AV23 -> 169.4 | BA23: =AW23*AX23 -> 362.5 | BB23: =AY23-AY22 -> 0 | BC23: =AZ23-AZ22 -> 0 | BD23: =BA23-BA22 -> 0 | BE23: =SUM(BB23:BD23) -> 0 | BF23: =SUM(I23-BE23) -> 0 | BG23: =SUM(I23-BF23) -> 0
A24: =ELEC!C22 -> 44488 | B24: =B23 -> 109443 | C24: =B24-B23 -> 0 | D24: =C24/27 -> 0 | E24: =SUM((C24*$E$4)+(7500/'EDl log'!$A$37)) -> 241.93548 | G24: =G23 -> 624723 | H24: =G24-G23 -> 0 | I24: =C24+H24 -> 0 | J24: =IF(I24>0,E24/I24,0) -> 0 | K24: ='Swimming Pool quality check '!H24 -> 6886 | L24: =K24-K23 -> 0 | M24: =M23 -> 457.44 | N24: =SUM(M24-M23) -> 0 | O24: =O23 -> 529.52 | P24: =SUM(O24-O23) -> 0 | Q24: =SUM(P24+N24) -> 0 | T24: =T23 -> 5176 | U24: =SUM(T24-T23) -> 0 | V24: =V23 -> 477 | W24: =+V24-V23 -> 0 | X24: =X23 -> 153815 | Y24: =SUM(X24-X23) -> 0 | Z24: =Z23 -> 99258 | AA24: =Z24-Z23 -> 0 | AB24: =AB23 -> 244 | AC24: =AC23 -> 779 | AD24: =AC24-AC23 -> 0 | AE24: =AE23 -> 238.2 | AF24: =AE24-AE23 -> 0 | AG24: =AG23 -> 2215.8 | AH24: =AG24-AG23 -> 0 | AI24: =AF24+AH24 -> 0 | AJ24: =+Z24-Z23 -> 0 | AK24: =SUM(Y24-L24) -> 0 | AL24: =SUM(AJ24-W24) -> 0 | AM24: ='General information '!D23 -> 0 | AN24: ='[3]General information '!H24 -> 0 | AP24: ='[3]General information '!J24 -> 0 | AR24: =A24 -> 44488 | AS24: =AS23 -> 0.9 | AT24: =AT23 -> 120 | AU24: =AU23 -> 1.1 | AV24: =AV23 -> 154 | AW24: 2.9 | AX24: =AX23 -> 125 | AY24: =AS24*AT24 -> 108 | AZ24: =AU24*AV24 -> 169.4 | BA24: =AW24*AX24 -> 362.5 | BB24: =AY24-AY23 -> 0 | BC24: =AZ24-AZ23 -> 0 | BD24: =BA24-BA23 -> 0 | BE24: =SUM(BB24:BD24) -> 0 | BF24: =SUM(I24-BE24) -> 0 | BG24: =SUM(I24-BF24) -> 0
A25: =ELEC!C23 -> 44489 | B25: =B24 -> 109443 | C25: =B25-B24 -> 0 | D25: =C25/27 -> 0 | E25: =SUM((C25*$E$4)+(7500/'EDl log'!$A$37)) -> 241.93548 | G25: =G24 -> 624723 | H25: =G25-G24 -> 0 | I25: =C25+H25 -> 0 | J25: =IF(I25>0,E25/I25,0) -> 0 | K25: ='Swimming Pool quality check '!H25 -> 6886 | L25: =K25-K24 -> 0 | M25: =M24 -> 457.44 | N25: =SUM(M25-M24) -> 0 | O25: =O24 -> 529.52 | P25: =SUM(O25-O24) -> 0 | Q25: =SUM(P25+N25) -> 0 | T25: =T24 -> 5176 | U25: =SUM(T25-T24) -> 0 | V25: =V24 -> 477 | W25: =+V25-V24 -> 0 | X25: =X24 -> 153815 | Y25: =SUM(X25-X24) -> 0 | Z25: =Z24 -> 99258 | AA25: =Z25-Z24 -> 0 | AB25: =AB24 -> 244 | AC25: =AC24 -> 779 | AD25: =AC25-AC24 -> 0 | AE25: =AE24 -> 238.2 | AF25: =AE25-AE24 -> 0 | AG25: =AG24 -> 2215.8 | AH25: =AG25-AG24 -> 0 | AI25: =AF25+AH25 -> 0 | AJ25: =+Z25-Z24 -> 0 | AK25: =SUM(Y25-L25) -> 0 | AL25: =SUM(AJ25-W25) -> 0 | AM25: ='General information '!D24 -> 0 | AN25: ='General information '!H24 -> 0 | AP25: ='General information '!J24 -> 0 | AR25: =A25 -> 44489 | AS25: =AS24 -> 0.9 | AT25: =AT24 -> 120 | AU25: =AU24 -> 1.1 | AV25: =AV24 -> 154 | AW25: 2.9 | AX25: =AX24 -> 125 | AY25: =AS25*AT25 -> 108 | AZ25: =AU25*AV25 -> 169.4 | BA25: =AW25*AX25 -> 362.5 | BB25: =AY25-AY24 -> 0 | BC25: =AZ25-AZ24 -> 0 | BD25: =BA25-BA24 -> 0 | BE25: =SUM(BB25:BD25) -> 0 | BF25: =SUM(I25-BE25) -> 0 | BG25: =SUM(I25-BF25) -> 0
A26: =ELEC!C24 -> 44490 | B26: =B25 -> 109443 | C26: =B26-B25 -> 0 | D26: =C26/27 -> 0 | E26: =SUM((C26*$E$4)+(7500/'EDl log'!$A$37)) -> 241.93548 | G26: =G25 -> 624723 | H26: =G26-G25 -> 0 | I26: =C26+H26 -> 0 | J26: =IF(I26>0,E26/I26,0) -> 0 | K26: ='Swimming Pool quality check '!H26 -> 6886 | L26: =K26-K25 -> 0 | M26: =M25 -> 457.44 | N26: =SUM(M26-M25) -> 0 | O26: =O25 -> 529.52 | P26: =SUM(O26-O25) -> 0 | Q26: =SUM(P26+N26) -> 0 | T26: =T25 -> 5176 | U26: =SUM(T26-T25) -> 0 | V26: =V25 -> 477 | W26: =+V26-V25 -> 0 | X26: =X25 -> 153815 | Y26: =SUM(X26-X25) -> 0 | Z26: =Z25 -> 99258 | AA26: =Z26-Z25 -> 0 | AB26: =AB25 -> 244 | AC26: =AC25 -> 779 | AD26: =AC26-AC25 -> 0 | AE26: =AE25 -> 238.2 | AF26: =AE26-AE25 -> 0 | AG26: =AG25 -> 2215.8 | AH26: =AG26-AG25 -> 0 | AI26: =AF26+AH26 -> 0 | AJ26: =+Z26-Z25 -> 0 | AK26: =SUM(Y26-L26) -> 0 | AL26: =SUM(AJ26-W26) -> 0 | AM26: ='General information '!D25 -> 0 | AN26: ='General information '!H25 -> 0 | AP26: ='General information '!J25 -> 0 | AR26: =A26 -> 44490 | AS26: =AS25 -> 0.9 | AT26: =AT25 -> 120 | AU26: =AU25 -> 1.1 | AV26: =AV25 -> 154 | AW26: 2.9 | AX26: =AX25 -> 125 | AY26: =AS26*AT26 -> 108 | AZ26: =AU26*AV26 -> 169.4 | BA26: =AW26*AX26 -> 362.5 | BB26: =AY26-AY25 -> 0 | BC26: =AZ26-AZ25 -> 0 | BD26: =BA26-BA25 -> 0 | BE26: =SUM(BB26:BD26) -> 0 | BF26: =SUM(I26-BE26) -> 0 | BG26: =SUM(I26-BF26) -> 0
A27: =ELEC!C25 -> 44491 | B27: =B26 -> 109443 | C27: =B27-B26 -> 0 | D27: =C27/27 -> 0 | E27: =SUM((C27*$E$4)+(7500/'EDl log'!$A$37)) -> 241.93548 | G27: =G26 -> 624723 | H27: =G27-G26 -> 0 | I27: =C27+H27 -> 0 | J27: =IF(I27>0,E27/I27,0) -> 0 | K27: ='Swimming Pool quality check '!H27 -> 6886 | L27: =K27-K26 -> 0 | M27: =M26 -> 457.44 | N27: =SUM(M27-M26) -> 0 | O27: =O26 -> 529.52 | P27: =SUM(O27-O26) -> 0 | Q27: =SUM(P27+N27) -> 0 | T27: =T26 -> 5176 | U27: =SUM(T27-T26) -> 0 | V27: =V26 -> 477 | W27: =+V27-V26 -> 0 | X27: =X26 -> 153815 | Y27: =SUM(X27-X26) -> 0 | Z27: =Z26 -> 99258 | AA27: =Z27-Z26 -> 0 | AB27: =AB26 -> 244 | AC27: =AC26 -> 779 | AD27: =AC27-AC26 -> 0 | AE27: =AE26 -> 238.2 | AF27: =AE27-AE26 -> 0 | AG27: =AG26 -> 2215.8 | AH27: =AG27-AG26 -> 0 | AI27: =AF27+AH27 -> 0 | AJ27: =+Z27-Z26 -> 0 | AK27: =SUM(Y27-L27) -> 0 | AL27: =SUM(AJ27-W27) -> 0 | AM27: ='General information '!D26 -> 0 | AN27: ='General information '!H26 -> 0 | AP27: ='General information '!J26 -> 0 | AR27: =A27 -> 44491 | AS27: =AS26 -> 0.9 | AT27: =AT26 -> 120 | AU27: =AU26 -> 1.1 | AV27: =AV26 -> 154 | AW27: 2.9 | AX27: =AX26 -> 125 | AY27: =AS27*AT27 -> 108 | AZ27: =AU27*AV27 -> 169.4 | BA27: =AW27*AX27 -> 362.5 | BB27: =AY27-AY26 -> 0 | BC27: =AZ27-AZ26 -> 0 | BD27: =BA27-BA26 -> 0 | BE27: =SUM(BB27:BD27) -> 0 | BF27: =SUM(I27-BE27) -> 0 | BG27: =SUM(I27-BF27) -> 0
A28: =ELEC!C26 -> 44492 | B28: =B27 -> 109443 | C28: =B28-B27 -> 0 | D28: =C28/27 -> 0 | E28: =SUM((C28*$E$4)+(7500/'EDl log'!$A$37)) -> 241.93548 | G28: =G27 -> 624723 | H28: =G28-G27 -> 0 | I28: =C28+H28 -> 0 | J28: =IF(I28>0,E28/I28,0) -> 0 | K28: ='Swimming Pool quality check '!H28 -> 6886 | L28: =K28-K27 -> 0 | M28: =M27 -> 457.44 | N28: =SUM(M28-M27) -> 0 | O28: =O27 -> 529.52 | P28: =SUM(O28-O27) -> 0 | Q28: =SUM(P28+N28) -> 0 | T28: =T27 -> 5176 | U28: =SUM(T28-T27) -> 0 | V28: =V27 -> 477 | W28: =+V28-V27 -> 0 | X28: =X27 -> 153815 | Y28: =SUM(X28-X27) -> 0 | Z28: =Z27 -> 99258 | AA28: =Z28-Z27 -> 0 | AB28: =AB27 -> 244 | AC28: =AC27 -> 779 | AD28: =AC28-AC27 -> 0 | AE28: =AE27 -> 238.2 | AF28: =AE28-AE27 -> 0 | AG28: =AG27 -> 2215.8 | AH28: =AG28-AG27 -> 0 | AI28: =AF28+AH28 -> 0 | AJ28: =+Z28-Z27 -> 0 | AK28: =SUM(Y28-L28) -> 0 | AL28: =SUM(AJ28-W28) -> 0 | AM28: ='General information '!D27 -> 0 | AN28: ='General information '!H27 -> 0 | AP28: ='General information '!J27 -> 0 | AR28: =A28 -> 44492 | AS28: =AS27 -> 0.9 | AT28: =AT27 -> 120 | AU28: =AU27 -> 1.1 | AV28: =AV27 -> 154 | AW28: 2.9 | AX28: =AX27 -> 125 | AY28: =AS28*AT28 -> 108 | AZ28: =AU28*AV28 -> 169.4 | BA28: =AW28*AX28 -> 362.5 | BB28: =AY28-AY27 -> 0 | BC28: =AZ28-AZ27 -> 0 | BD28: =BA28-BA27 -> 0 | BE28: =SUM(BB28:BD28) -> 0 | BF28: =SUM(I28-BE28) -> 0 | BG28: =SUM(I28-BF28) -> 0
A29: =ELEC!C27 -> 44493 | B29: =B28 -> 109443 | C29: =B29-B28 -> 0 | D29: =C29/27 -> 0 | E29: =SUM((C29*$E$4)+(7500/'EDl log'!$A$37)) -> 241.93548 | G29: =G28 -> 624723 | H29: =G29-G28 -> 0 | I29: =C29+H29 -> 0 | J29: =IF(I29>0,E29/I29,0) -> 0 | K29: ='Swimming Pool quality check '!H29 -> 6886 | L29: =K29-K28 -> 0 | M29: =M28 -> 457.44 | N29: =SUM(M29-M28) -> 0 | O29: =O28 -> 529.52 | P29: =SUM(O29-O28) -> 0 | Q29: =SUM(P29+N29) -> 0 | T29: =T28 -> 5176 | U29: =SUM(T29-T28) -> 0 | V29: =V28 -> 477 | W29: =+V29-V28 -> 0 | X29: =X28 -> 153815 | Y29: =SUM(X29-X28) -> 0 | Z29: =Z28 -> 99258 | AA29: =Z29-Z28 -> 0 | AB29: =AB28 -> 244 | AC29: =AC28 -> 779 | AD29: =AC29-AC28 -> 0 | AE29: =AE28 -> 238.2 | AF29: =AE29-AE28 -> 0 | AG29: =AG28 -> 2215.8 | AH29: =AG29-AG28 -> 0 | AI29: =AF29+AH29 -> 0 | AJ29: =+Z29-Z28 -> 0 | AK29: =SUM(Y29-L29) -> 0 | AL29: =SUM(AJ29-W29) -> 0 | AM29: ='General information '!D28 -> 0 | AN29: ='General information '!H28 -> 0 | AP29: ='General information '!J28 -> 0 | AR29: =A29 -> 44493 | AS29: =AS28 -> 0.9 | AT29: =AT28 -> 120 | AU29: =AU28 -> 1.1 | AV29: =AV28 -> 154 | AW29: 2.9 | AX29: =AX28 -> 125 | AY29: =AS29*AT29 -> 108 | AZ29: =AU29*AV29 -> 169.4 | BA29: =AW29*AX29 -> 362.5 | BB29: =AY29-AY28 -> 0 | BC29: =AZ29-AZ28 -> 0 | BD29: =BA29-BA28 -> 0 | BE29: =SUM(BB29:BD29) -> 0 | BF29: =SUM(I29-BE29) -> 0 | BG29: =SUM(I29-BF29) -> 0
A30: =ELEC!C28 -> 44494 | B30: =B29 -> 109443 | C30: =B30-B29 -> 0 | D30: =C30/27 -> 0 | E30: =SUM((C30*$E$4)+(7500/'EDl log'!$A$37)) -> 241.93548 | G30: =G29 -> 624723 | H30: =G30-G29 -> 0 | I30: =C30+H30 -> 0 | J30: =IF(I30>0,E30/I30,0) -> 0 | K30: ='Swimming Pool quality check '!H30 -> 6886 | L30: =K30-K29 -> 0 | M30: =M29 -> 457.44 | N30: =SUM(M30-M29) -> 0 | O30: =O29 -> 529.52 | P30: =SUM(O30-O29) -> 0 | Q30: =SUM(P30+N30) -> 0 | T30: =T29 -> 5176 | U30: =SUM(T30-T29) -> 0 | V30: =V29 -> 477 | W30: =+V30-V29 -> 0 | X30: =X29 -> 153815 | Y30: =SUM(X30-X29) -> 0 | Z30: =Z29 -> 99258 | AA30: =Z30-Z29 -> 0 | AB30: =AB29 -> 244 | AC30: =AC29 -> 779 | AD30: =AC30-AC29 -> 0 | AE30: =AE29 -> 238.2 | AF30: =AE30-AE29 -> 0 | AG30: =AG29 -> 2215.8 | AH30: =AG30-AG29 -> 0 | AI30: =AF30+AH30 -> 0 | AJ30: =+Z30-Z29 -> 0 | AK30: =SUM(Y30-L30) -> 0 | AL30: =SUM(AJ30-W30) -> 0 | AM30: ='General information '!D29 -> 0 | AN30: ='General information '!H29 -> 0 | AP30: ='General information '!J29 -> 0 | AR30: =A30 -> 44494 | AS30: =AS29 -> 0.9 | AT30: =AT29 -> 120 | AU30: =AU29 -> 1.1 | AV30: =AV29 -> 154 | AW30: 2.9 | AX30: =AX29 -> 125 | AY30: =AS30*AT30 -> 108 | AZ30: =AU30*AV30 -> 169.4 | BA30: =AW30*AX30 -> 362.5 | BB30: =AY30-AY29 -> 0 | BC30: =AZ30-AZ29 -> 0 | BD30: =BA30-BA29 -> 0 | BE30: =SUM(BB30:BD30) -> 0 | BF30: =SUM(I30-BE30) -> 0 | BG30: =SUM(I30-BF30) -> 0
A31: =ELEC!C29 -> 44495 | B31: =B30 -> 109443 | C31: =B31-B30 -> 0 | D31: =C31/27 -> 0 | E31: =SUM((C31*$E$4)+(7500/'EDl log'!$A$37)) -> 241.93548 | G31: =G30 -> 624723 | H31: =G31-G30 -> 0 | I31: =C31+H31 -> 0 | J31: =IF(I31>0,E31/I31,0) -> 0 | K31: ='Swimming Pool quality check '!H31 -> 6886 | L31: =K31-K30 -> 0 | M31: =M30 -> 457.44 | N31: =SUM(M31-M30) -> 0 | O31: =O30 -> 529.52 | P31: =SUM(O31-O30) -> 0 | Q31: =SUM(P31+N31) -> 0 | T31: =T30 -> 5176 | U31: =SUM(T31-T30) -> 0 | V31: =V30 -> 477 | W31: =+V31-V30 -> 0 | X31: =X30 -> 153815 | Y31: =SUM(X31-X30) -> 0 | Z31: =Z30 -> 99258 | AA31: =Z31-Z30 -> 0 | AB31: =AB30 -> 244 | AC31: =AC30 -> 779 | AD31: =AC31-AC30 -> 0 | AE31: =AE30 -> 238.2 | AF31: =AE31-AE30 -> 0 | AG31: =AG30 -> 2215.8 | AH31: =AG31-AG30 -> 0 | AI31: =AF31+AH31 -> 0 | AJ31: =+Z31-Z30 -> 0 | AK31: =SUM(Y31-L31) -> 0 | AL31: =SUM(AJ31-W31) -> 0 | AM31: ='General information '!D30 -> 0 | AN31: ='General information '!H30 -> 0 | AP31: ='General information '!J30 -> 0 | AR31: =A31 -> 44495 | AS31: =AS30 -> 0.9 | AT31: =AT30 -> 120 | AU31: =AU30 -> 1.1 | AV31: =AV30 -> 154 | AW31: 2.9 | AX31: =AX30 -> 125 | AY31: =AS31*AT31 -> 108 | AZ31: =AU31*AV31 -> 169.4 | BA31: =AW31*AX31 -> 362.5 | BB31: =AY31-AY30 -> 0 | BC31: =AZ31-AZ30 -> 0 | BD31: =BA31-BA30 -> 0 | BE31: =SUM(BB31:BD31) -> 0 | BF31: =SUM(I31-BE31) -> 0 | BG31: =SUM(I31-BF31) -> 0
A32: =ELEC!C30 -> 44496 | B32: =B31 -> 109443 | C32: =B32-B31 -> 0 | D32: =C32/27 -> 0 | E32: =SUM((C32*$E$4)+(7500/'EDl log'!$A$37)) -> 241.93548 | G32: =G31 -> 624723 | H32: =G32-G31 -> 0 | I32: =C32+H32 -> 0 | J32: =IF(I32>0,E32/I32,0) -> 0 | K32: ='Swimming Pool quality check '!H32 -> 6886 | L32: =K32-K31 -> 0 | M32: =M31 -> 457.44 | N32: =SUM(M32-M31) -> 0 | O32: =O31 -> 529.52 | P32: =SUM(O32-O31) -> 0 | Q32: =SUM(P32+N32) -> 0 | T32: =T31 -> 5176 | U32: =SUM(T32-T31) -> 0 | V32: =V31 -> 477 | W32: =+V32-V31 -> 0 | X32: =X31 -> 153815 | Y32: =SUM(X32-X31) -> 0 | Z32: =Z31 -> 99258 | AA32: =Z32-Z31 -> 0 | AB32: =AB31 -> 244 | AC32: =AC31 -> 779 | AD32: =AC32-AC31 -> 0 | AE32: =AE31 -> 238.2 | AF32: =AE32-AE31 -> 0 | AG32: =AG31 -> 2215.8 | AH32: =AG32-AG31 -> 0 | AI32: =AF32+AH32 -> 0 | AJ32: =+Z32-Z31 -> 0 | AK32: =SUM(Y32-L32) -> 0 | AL32: =SUM(AJ32-W32) -> 0 | AM32: ='General information '!D31 -> 0 | AN32: ='General information '!H31 -> 0 | AP32: ='General information '!J31 -> 0 | AR32: =A32 -> 44496 | AS32: =AS31 -> 0.9 | AT32: =AT31 -> 120 | AU32: =AU31 -> 1.1 | AV32: =AV31 -> 154 | AW32: 2.9 | AX32: =AX31 -> 125 | AY32: =AS32*AT32 -> 108 | AZ32: =AU32*AV32 -> 169.4 | BA32: =AW32*AX32 -> 362.5 | BB32: =AY32-AY31 -> 0 | BC32: =AZ32-AZ31 -> 0 | BD32: =BA32-BA31 -> 0 | BE32: =SUM(BB32:BD32) -> 0 | BF32: =SUM(I32-BE32) -> 0 | BG32: =SUM(I32-BF32) -> 0
A33: =ELEC!C31 -> 44497 | B33: =B32 -> 109443 | C33: =B33-B32 -> 0 | D33: =C33/27 -> 0 | E33: =SUM((C33*$E$4)+(7500/'EDl log'!$A$37)) -> 241.93548 | G33: =G32 -> 624723 | H33: =G33-G32 -> 0 | I33: =C33+H33 -> 0 | J33: =IF(I33>0,E33/I33,0) -> 0 | K33: ='Swimming Pool quality check '!H33 -> 6886 | L33: =K33-K32 -> 0 | M33: =M32 -> 457.44 | N33: =SUM(M33-M32) -> 0 | O33: =O32 -> 529.52 | P33: =SUM(O33-O32) -> 0 | Q33: =SUM(P33+N33) -> 0 | T33: =T32 -> 5176 | U33: =SUM(T33-T32) -> 0 | V33: =V32 -> 477 | W33: =+V33-V32 -> 0 | X33: =X32 -> 153815 | Y33: =SUM(X33-X32) -> 0 | Z33: =Z32 -> 99258 | AA33: =Z33-Z32 -> 0 | AB33: =AB32 -> 244 | AC33: =AC32 -> 779 | AD33: =AC33-AC32 -> 0 | AE33: =AE32 -> 238.2 | AF33: =AE33-AE32 -> 0 | AG33: =AG32 -> 2215.8 | AH33: =AG33-AG32 -> 0 | AI33: =AF33+AH33 -> 0 | AJ33: =+Z33-Z32 -> 0 | AK33: =SUM(Y33-L33) -> 0 | AL33: =SUM(AJ33-W33) -> 0 | AM33: ='General information '!D32 -> 0 | AN33: ='General information '!H32 -> 0 | AP33: ='General information '!J32 -> 0 | AR33: =A33 -> 44497 | AS33: =AS32 -> 0.9 | AT33: =AT32 -> 120 | AU33: =AU32 -> 1.1 | AV33: =AV32 -> 154 | AW33: 2.9 | AX33: =AX32 -> 125 | AY33: =AS33*AT33 -> 108 | AZ33: =AU33*AV33 -> 169.4 | BA33: =AW33*AX33 -> 362.5 | BB33: =AY33-AY32 -> 0 | BC33: =AZ33-AZ32 -> 0 | BD33: =BA33-BA32 -> 0 | BE33: =SUM(BB33:BD33) -> 0 | BF33: =SUM(I33-BE33) -> 0 | BG33: =SUM(I33-BF33) -> 0
A34: =ELEC!C32 -> 44498 | B34: =B33 -> 109443 | C34: =B34-B33 -> 0 | D34: =C34/27 -> 0 | E34: =SUM((C34*$E$4)+(7500/'EDl log'!$A$37)) -> 241.93548 | G34: =G33 -> 624723 | H34: =G34-G33 -> 0 | I34: =C34+H34 -> 0 | J34: =IF(I34>0,E34/I34,0) -> 0 | K34: ='Swimming Pool quality check '!H34 -> 6886 | L34: =K34-K33 -> 0 | M34: =M33 -> 457.44 | N34: =SUM(M34-M33) -> 0 | O34: =O33 -> 529.52 | P34: =SUM(O34-O33) -> 0 | Q34: =SUM(P34+N34) -> 0 | T34: =T33 -> 5176 | U34: =SUM(T34-T33) -> 0 | V34: =V33 -> 477 | W34: =+V34-V33 -> 0 | X34: =X33 -> 153815 | Y34: =SUM(X34-X33) -> 0 | Z34: =Z33 -> 99258 | AA34: =Z34-Z33 -> 0 | AB34: =AB33 -> 244 | AC34: =AC33 -> 779 | AD34: =AC34-AC33 -> 0 | AE34: =AE33 -> 238.2 | AF34: =AE34-AE33 -> 0 | AG34: =AG33 -> 2215.8 | AH34: =AG34-AG33 -> 0 | AI34: =AF34+AH34 -> 0 | AJ34: =+Z34-Z33 -> 0 | AK34: =SUM(Y34-L34) -> 0 | AL34: =SUM(AJ34-W34) -> 0 | AM34: ='General information '!D33 -> 0 | AN34: ='General information '!H33 -> 0 | AP34: ='General information '!J33 -> 0 | AR34: =A34 -> 44498 | AS34: =AS33 -> 0.9 | AT34: =AT33 -> 120 | AU34: =AU33 -> 1.1 | AV34: =AV33 -> 154 | AW34: 2.9 | AX34: =AX33 -> 125 | AY34: =AS34*AT34 -> 108 | AZ34: =AU34*AV34 -> 169.4 | BA34: =AW34*AX34 -> 362.5 | BB34: =AY34-AY33 -> 0 | BC34: =AZ34-AZ33 -> 0 | BD34: =BA34-BA33 -> 0 | BE34: =SUM(BB34:BD34) -> 0 | BF34: =SUM(I34-BE34) -> 0 | BG34: =SUM(I34-BF34) -> 0
A35: =ELEC!C33 -> 44499 | B35: =B34 -> 109443 | C35: =B35-B34 -> 0 | D35: =C35/27 -> 0 | E35: =SUM((C35*$E$4)+(7500/'EDl log'!$A$37)) -> 241.93548 | G35: =G34 -> 624723 | H35: =G35-G34 -> 0 | I35: =C35+H35 -> 0 | J35: =IF(I35>0,E35/I35,0) -> 0 | K35: ='Swimming Pool quality check '!H35 -> 6886 | L35: =K35-K34 -> 0 | M35: =M34 -> 457.44 | N35: =SUM(M35-M34) -> 0 | O35: =O34 -> 529.52 | P35: =SUM(O35-O34) -> 0 | Q35: =SUM(P35+N35) -> 0 | T35: =T34 -> 5176 | U35: =SUM(T35-T34) -> 0 | V35: =V34 -> 477 | W35: =+V35-V34 -> 0 | X35: =X34 -> 153815 | Y35: =SUM(X35-X34) -> 0 | Z35: =Z34 -> 99258 | AA35: =Z35-Z34 -> 0 | AB35: =AB34 -> 244 | AC35: =AC34 -> 779 | AD35: =AC35-AC34 -> 0 | AE35: =AE34 -> 238.2 | AF35: =AE35-AE34 -> 0 | AG35: =AG34 -> 2215.8 | AH35: =AG35-AG34 -> 0 | AI35: =AF35+AH35 -> 0 | AJ35: =+Z35-Z34 -> 0 | AK35: =SUM(Y35-L35) -> 0 | AL35: =SUM(AJ35-W35) -> 0 | AM35: ='General information '!D34 -> 0 | AN35: ='General information '!H34 -> 0 | AP35: ='General information '!J34 -> 0 | AR35: =A35 -> 44499 | AS35: =AS34 -> 0.9 | AT35: =AT34 -> 120 | AU35: =AU34 -> 1.1 | AV35: =AV34 -> 154 | AW35: 2.9 | AX35: =AX34 -> 125 | AY35: =AS35*AT35 -> 108 | AZ35: =AU35*AV35 -> 169.4 | BA35: =AW35*AX35 -> 362.5 | BB35: =AY35-AY34 -> 0 | BC35: =AZ35-AZ34 -> 0 | BD35: =BA35-BA34 -> 0 | BE35: =SUM(BB35:BD35) -> 0 | BF35: =SUM(I35-BE35) -> 0 | BG35: =SUM(I35-BF35) -> 0
A36: =ELEC!C34 -> 44500 | B36: =B35 -> 109443 | C36: =B36-B35 -> 0 | D36: =C36/27 -> 0 | E36: =SUM((C36*$E$4)+(7500/'EDl log'!$A$37)) -> 241.93548 | G36: =G35 -> 624723 | H36: =G36-G35 -> 0 | I36: =C36+H36 -> 0 | J36: =IF(I36>0,E36/I36,0) -> 0 | K36: ='Swimming Pool quality check '!H36 -> 6886 | L36: =K36-K35 -> 0 | M36: =M35 -> 457.44 | N36: =SUM(M36-M35) -> 0 | O36: =O35 -> 529.52 | P36: =SUM(O36-O35) -> 0 | Q36: =SUM(P36+N36) -> 0 | T36: =T35 -> 5176 | U36: =SUM(T36-T35) -> 0 | V36: =V35 -> 477 | W36: =+V36-V35 -> 0 | X36: =X35 -> 153815 | Y36: =SUM(X36-X35) -> 0 | Z36: =Z35 -> 99258 | AA36: =Z36-Z35 -> 0 | AB36: =AB35 -> 244 | AC36: =AC35 -> 779 | AD36: =AC36-AC35 -> 0 | AE36: =AE35 -> 238.2 | AF36: =AE36-AE35 -> 0 | AG36: =AG35 -> 2215.8 | AH36: =AG36-AG35 -> 0 | AI36: =AF36+AH36 -> 0 | AJ36: =+Z36-Z35 -> 0 | AK36: =SUM(Y36-L36) -> 0 | AL36: =SUM(AJ36-W36) -> 0 | AM36: ='General information '!D35 -> 0 | AN36: ='General information '!H35 -> 0 | AP36: ='General information '!J35 -> 0 | AR36: =A36 -> 44500 | AS36: =AS35 -> 0.9 | AT36: =AT35 -> 120 | AU36: =AU35 -> 1.1 | AV36: =AV35 -> 154 | AW36: 2.9 | AX36: =AX35 -> 125 | AY36: =AS36*AT36 -> 108 | AZ36: =AU36*AV36 -> 169.4 | BA36: =AW36*AX36 -> 362.5 | BB36: =AY36-AY35 -> 0 | BC36: =AZ36-AZ35 -> 0 | BD36: =BA36-BA35 -> 0 | BE36: =SUM(BB36:BD36) -> 0 | BF36: =SUM(I36-BE36) -> 0 | BG36: =SUM(I36-BF36) -> 0
C37: =SUM(C6:C36) -> 0 | D37: =SUM(D6:D36) -> 0 | F37: =SUM(F6:F36) -> 0 | H37: =SUM(H6:H36) -> 0 | I37: =SUM(I6:I36) -> 0 | L37: =SUM(L7:L36) -> 2 | Q37: =SUM(Q6:Q36) -> 0 | U37: =SUM(U6:U36) -> -4 | Y37: =SUM(Y6,Y33,Y31,Y29,Y27,Y25,Y23,Y21,Y19,Y17,Y15,Y13,Y11,Y9,Y7,Y34,Y35,Y36) -> 0 | AJ37: =SUM(AJ6:AJ36) -> 0 | AK37: =SUM(Y37-L37) -> -2 | AL37: =SUM(AL6:AL36) -> 0
C38: =+C37*1.66 -> 0 | E38: =SUM(E6:E33) -> 6774.1935 | F38: =SUM(F6:F35) -> 0 | H38: 7500 | I38: =SUM('General information '!G36/WATER!I37) -> #DIV/0! | O38: =SUM(Q37+I37) -> 0 | Z38: =SUM(Y37:AJ37) -> 0 | AK38: =SUM(Y38-L38) -> 0
B39: =9*31 -> 279 | D39: =SUM(D6:D35) -> 0 | F39: =SUM(F6:F36) -> 0 | G39: =SUM(I37) -> 0 | H39: =SUM(H38+C38) -> 7500 | K39: =SUM(H39/G39) -> #DIV/0! | AJ39: =SUM(C38-AK38) -> 0 | AM39: =SUM(AJ39/AO38) -> #DIV/0!

Sheet GEN
B1: GEN1 | C1: RUN HR | D1: Fuel Counter Index | E1: Cons /day | F1: Diesel L/H | H1: next service | I1: ALARM | J1: GEN2 | K1: RUN HR | L1: Fuel Counter Index | M1: Cons /day | N1: Diesel L/H | P1: next service | Q1: ALARM | R1: GEN3 | S1: RUN HR | T1: Fuel Counter Index | U1: Cons /day | V1: Diesel L/H | X1: next service | Y1: ALARM | Z1: RH total | AA1: Gen Con /day | AB1: Total Deisel Cons/day | AC1: H /L | AD1: TOAL KW GEN | AI1: fuel Consuption | AK1: AVG KW/h
A2: =[2]GEN!A32 -> 44469 | B2: =[2]GEN!B32 -> 10965 | C2: =[2]GEN!C32 -> 8 | D2: =[2]GEN!D32 -> 522014.3 | E2: =[2]GEN!E32 -> 982.3 | F2: =[2]GEN!F32 -> 122.7875 | G2: =[2]GEN!G32 -> 0 | H2: =[2]GEN!H32 -> 11055 | ... AK2: =[2]GEN!AK32 -> 163.00127
A3: =ELEC!C4 -> 44470 | B3: =B2 -> 10965 | C3: =B3-B2 -> 0 | D3: =D2 -> 522014.3 | E3: =SUM(D3-D2) -> 0 | F3: =IF(C3>0,E3/C3,0) -> 0 | G3: =[4]GEN!G32 -> 0 | H3: =H2 -> 11055 | I3: =IF(B3-H3<=0,"ok","oil change") -> ok | J3: =J2 -> 10698 | K3: =J3-J2 -> 0 | L3: =L2 -> 357691 | M3: =SUM(L3-L2) -> 0 | N3: =IF(K3>0,M3/K3,0) -> 0 | O3: =[4]GEN!O32 -> 0 | P3: =P2 -> 10873 | Q3: =IF(J3-P3<=0,"ok","oil change") -> ok | R3: =R2 -> 13131 | S3: =R3-R2 -> 0 | T3: =T2 -> 222244 | U3: =V3*S3 -> 0 | V3: 250 | W3: =[4]GEN!W32 -> 0 | X3: 13068 | Y3: =IF(R3-X3<=0,"ok","oil change") -> oil change | Z3: =C3+K3+S3 -> 0 | AA3: =U3+M3+E3 -> 0 | AB3: =V3+N3+F3 -> 250 | AC3: =IF(Z3>0,AA3/Z3,0) -> 0 | AD3: =ELEC!Q4 -> 0 | AE3: =SUM(AD3/Z3) -> #DIV/0! | AF3: =SUM(AE3/1600) -> #DIV/0! | AG3: =SUM(360*AF3) -> #DIV/0! | AH3: =SUM(AC3-AG3) -> #DIV/0! | AI3: =AD3*AJ3 -> 0 | AJ3: =305/1185 -> 0.25738397 | AK3: =AI3/Z3 -> #DIV/0!
A4: =ELEC!C5 -> 44471 | B4: =B3 -> 10965 | C4: =B4-B3 -> 0 | D4: =D3 -> 522014.3 | E4: =SUM(D4-D3) -> 0 | F4: =IF(C4>0,E4/C4,0) -> 0 | H4: =H3 -> 11055 | I4: =IF(B4-H4<=0,"ok","oil change") -> ok | J4: =J3 -> 10698 | K4: =J4-J3 -> 0 | L4: =L3 -> 357691 | M4: =SUM(L4-L3) -> 0 | N4: =IF(K4>0,M4/K4,0) -> 0 | P4: =P3 -> 10873 | Q4: =IF(J4-P4<=0,"ok","oil change") -> ok | R4: =R3 -> 13131 | S4: =R4-R3 -> 0 | T4: =T3+U4 -> 222244 | U4: =V4*S4 -> 0 | V4: 250 | X4: =X3 -> 13068 | Y4: =IF(R4-X4<=0,"ok","oil change") -> oil change | Z4: =C4+K4+S4 -> 0 | AA4: =U4+M4+E4 -> 0 | AB4: =V4+N4+F4 -> 250 | AC4: =IF(Z4>0,AA4/Z4,0) -> 0 | AD4: =ELEC!Q5 -> 0 | AE4: =SUM(AD4/Z4) -> #DIV/0! | AF4: =SUM(AE4/1600) -> #DIV/0! | AG4: =SUM(360*AF4) -> #DIV/0! | AH4: =SUM(AC4-AG4) -> #DIV/0! | AI4: =AD4*AJ4 -> 0 | AJ4: =305/1185 -> 0.25738397 | AK4: =AI4/Z4 -> #DIV/0!
A5: =ELEC!C6 -> 44472 | B5: 10971 | C5: =B5-B4 -> 6 | D5: 522800 | E5: =SUM(D5-D4) -> 785.7 | F5: =IF(C5>0,E5/C5,0) -> 130.95 | H5: =H4 -> 11055 | I5: =IF(B5-H5<=0,"ok","oil change") -> ok | J5: =J4 -> 10698 | K5: =J5-J4 -> 0 | L5: =L4 -> 357691 | M5: =SUM(L5-L4) -> 0 | N5: =IF(K5>0,M5/K5,0) -> 0 | P5: =P4 -> 10873 | Q5: =IF(J5-P5<=0,"ok","oil change") -> ok | R5: 13134 | S5: =R5-R4 -> 3 | T5: =T4+U5 -> 222994 | U5: =V5*S5 -> 750 | V5: 250 | X5: =X4 -> 13068 | Y5: =IF(R5-X5<=0,"ok","oil change") -> oil change | Z5: =C5+K5+S5 -> 9 | AA5: =U5+M5+E5 -> 1535.7 | AB5: =V5+N5+F5 -> 380.95 | AC5: =IF(Z5>0,AA5/Z5,0) -> 170.63333 | AD5: =ELEC!Q6 -> 6616 | AE5: =SUM(AD5/Z5) -> 735.11111 | AF5: =SUM(AE5/1600) -> 0.45944444 | AG5: =SUM(320*AF5) -> 147.02222 | AH5: =SUM(AC5-AG5) -> 23.611111 | AI5: =AD5*AJ5 -> 1702.8523 | AJ5: =305/1185 -> 0.25738397 | AK5: =AI5/Z5 -> 189.20581
A6: =ELEC!C7 -> 44473 | B6: =B5 -> 10971 | C6: =B6-B5 -> 0 | D6: =D5 -> 522800 | E6: =SUM(D6-D5) -> 0 | F6: =IF(C6>0,E6/C6,0) -> 0 | H6: =H5 -> 11055 | I6: =IF(B6-H6<=0,"ok","oil change") -> ok | J6: =J5 -> 10698 | K6: =J6-J5 -> 0 | L6: =L5 -> 357691 | M6: =SUM(L6-L5) -> 0 | N6: =IF(K6>0,M6/K6,0) -> 0 | P6: =P5 -> 10873 | Q6: =IF(J6-P6<=0,"ok","oil change") -> ok | R6: =R5 -> 13134 | S6: =R6-R5 -> 0 | T6: =T5+U6 -> 222994 | U6: =V6*S6 -> 0 | V6: 250 | X6: =X5 -> 13068 | Y6: =IF(R6-X6<=0,"ok","oil change") -> oil change | Z6: =C6+K6+S6 -> 0 | AA6: =U6+M6+E6 -> 0 | AB6: =V6+N6+F6 -> 250 | AC6: =IF(Z6>0,AA6/Z6,0) -> 0 | AD6: =ELEC!Q7 -> 0 | AE6: =SUM(AD6/Z6) -> #DIV/0! | AF6: =SUM(AE6/1600) -> #DIV/0! | AG6: =SUM(320*AF6) -> #DIV/0! | AH6: =SUM(AC6-AG6) -> #DIV/0! | AI6: =AD6*AJ6 -> 0 | AJ6: =305/1185 -> 0.25738397 | AK6: =AI6/Z6 -> #DIV/0!
A7: =ELEC!C8 -> 44474 | B7: =B6 -> 10971 | C7: =B7-B6 -> 0 | D7: =D6 -> 522800 | E7: =SUM(D7-D6) -> 0 | F7: =IF(C7>0,E7/C7,0) -> 0 | H7: =H6 -> 11055 | I7: =IF(B7-H7<=0,"ok","oil change") -> ok | J7: =J6 -> 10698 | K7: =J7-J6 -> 0 | L7: =L6 -> 357691 | M7: =SUM(L7-L6) -> 0 | N7: =IF(K7>0,M7/K7,0) -> 0 | P7: =P6 -> 10873 | Q7: =IF(J7-P7<=0,"ok","oil change") -> ok | R7: =R6 -> 13134 | S7: =R7-R6 -> 0 | T7: =T6+U7 -> 222994 | U7: =V7*S7 -> 0 | V7: 250 | X7: =X6 -> 13068 | Y7: =IF(R7-X7<=0,"ok","oil change") -> oil change | Z7: =C7+K7+S7 -> 0 | AA7: =U7+M7+E7 -> 0 | AB7: =V7+N7+F7 -> 250 | AC7: =IF(Z7>0,AA7/Z7,0) -> 0 | AD7: =ELEC!Q8 -> 0 | AE7: =SUM(AD7/Z7) -> #DIV/0! | AF7: =SUM(AE7/1600) -> #DIV/0! | AG7: =SUM(AF7/1600) -> #DIV/0! | AH7: =SUM(AC7-AG7) -> #DIV/0! | AI7: =AD7*AJ7 -> 0 | AJ7: =305/1185 -> 0.25738397 | AK7: =AI7/Z7 -> #DIV/0!
A8: =ELEC!C9 -> 44475 | B8: =B7 -> 10971 | C8: =B8-B7 -> 0 | D8: =D7 -> 522800 | E8: =SUM(D8-D7) -> 0 | F8: =IF(C8>0,E8/C8,0) -> 0 | H8: =H7 -> 11055 | I8: =IF(B8-H8<=0,"ok","oil change") -> ok | J8: =J7 -> 10698 | K8: =J8-J7 -> 0 | L8: =L7 -> 357691 | M8: =SUM(L8-L7) -> 0 | N8: =IF(K8>0,M8/K8,0) -> 0 | P8: =P7 -> 10873 | Q8: =IF(J8-P8<=0,"ok","oil change") -> ok | R8: =R7 -> 13134 | S8: =R8-R7 -> 0 | T8: =T7+U8 -> 222994 | U8: =V8*S8 -> 0 | V8: 250 | X8: =X7 -> 13068 | Y8: =IF(R8-X8<=0,"ok","oil change") -> oil change | Z8: =C8+K8+S8 -> 0 | AA8: =U8+M8+E8 -> 0 | AB8: =V8+N8+F8 -> 250 | AC8: =IF(Z8>0,AA8/Z8,0) -> 0 | AD8: =ELEC!Q9 -> 0 | AE8: =SUM(AD8/Z8) -> #DIV/0! | AF8: =SUM(AE8/1600) -> #DIV/0! | AG8: =SUM(320*AF8) -> #DIV/0! | AH8: =SUM(AC8-AG8) -> #DIV/0! | AI8: =AD8*AJ8 -> 0 | AJ8: =305/1185 -> 0.25738397 | AK8: =AI8/Z8 -> #DIV/0!
A9: =ELEC!C10 -> 44476 | B9: =B8 -> 10971 | C9: =B9-B8 -> 0 | D9: =D8 -> 522800 | E9: =SUM(D9-D8) -> 0 | F9: =IF(C9>0,E9/C9,0) -> 0 | H9: =H8 -> 11055 | I9: =IF(B9-H9<=0,"ok","oil change") -> ok | J9: =J8 -> 10698 | K9: =J9-J8 -> 0 | L9: =L8 -> 357691 | M9: =SUM(L9-L8) -> 0 | N9: =IF(K9>0,M9/K9,0) -> 0 | P9: =P8 -> 10873 | Q9: =IF(J9-P9<=0,"ok","oil change") -> ok | R9: =R8 -> 13134 | S9: =R9-R8 -> 0 | T9: =T8+U9 -> 222994 | U9: =V9*S9 -> 0 | V9: 250 | X9: =X8 -> 13068 | Y9: =IF(R9-X9<=0,"ok","oil change") -> oil change | Z9: =C9+K9+S9 -> 0 | AA9: =U9+M9+E9 -> 0 | AB9: =V9+N9+F9 -> 250 | AC9: =IF(Z9>0,AA9/Z9,0) -> 0 | AD9: =ELEC!Q10 -> 0 | AE9: =SUM(AD9/Z9) -> #DIV/0! | AF9: =SUM(AE9/1600) -> #DIV/0! | AG9: =SUM(320*AF9) -> #DIV/0! | AH9: =SUM(AC9-AG9) -> #DIV/0! | AI9: =AD9*AJ9 -> 0 | AJ9: =305/1185 -> 0.25738397 | AK9: =AI9/Z9 -> #DIV/0!
A10: =ELEC!C11 -> 44477 | B10: =B9 -> 10971 | C10: =B10-B9 -> 0 | D10: =D9 -> 522800 | E10: =SUM(D10-D9) -> 0 | F10: =IF(C10>0,E10/C10,0) -> 0 | H10: =H9 -> 11055 | I10: =IF(B10-H10<=0,"ok","oil change") -> ok | J10: =J9 -> 10698 | K10: =J10-J9 -> 0 | L10: =L9 -> 357691 | M10: =SUM(L10-L9) -> 0 | N10: =IF(K10>0,M10/K10,0) -> 0 | P10: =P9 -> 10873 | Q10: =IF(J10-P10<=0,"ok","oil change") -> ok | R10: =R9 -> 13134 | S10: =R10-R9 -> 0 | T10: =T9+U10 -> 222994 | U10: =V10*S10 -> 0 | V10: 250 | X10: =X9 -> 13068 | Y10: =IF(R10-X10<=0,"ok","oil change") -> oil change | Z10: =C10+K10+S10 -> 0 | AA10: =U10+M10+E10 -> 0 | AB10: =V10+N10+F10 -> 250 | AC10: =IF(Z10>0,AA10/Z10,0) -> 0 | AD10: =ELEC!Q11 -> 0 | AE10: =SUM(AD10/Z10) -> #DIV/0! | AF10: =SUM(AE10/1600) -> #DIV/0! | AG10: =SUM(320*AF10) -> #DIV/0! | AH10: =SUM(AC10-AG10) -> #DIV/0! | AI10: =AD10*AJ10 -> 0 | AJ10: =305/1185 -> 0.25738397 | AK10: =AI10/Z10 -> #DIV/0!
A11: =ELEC!C12 -> 44478 | B11: =B10 -> 10971 | C11: =B11-B10 -> 0 | D11: =D10 -> 522800 | E11: =SUM(D11-D10) -> 0 | F11: =IF(C11>0,E11/C11,0) -> 0 | H11: =H10 -> 11055 | I11: =IF(B11-H11<=0,"ok","oil change") -> ok | J11: =J10 -> 10698 | K11: =J11-J10 -> 0 | L11: =L10 -> 357691 | M11: =SUM(L11-L10) -> 0 | N11: =IF(K11>0,M11/K11,0) -> 0 | P11: =P10 -> 10873 | Q11: =IF(J11-P11<=0,"ok","oil change") -> ok | R11: =R10 -> 13134 | S11: =R11-R10 -> 0 | T11: =T10+U11 -> 222994 | U11: =V11*S11 -> 0 | V11: 250 | X11: =X10 -> 13068 | Y11: =IF(R11-X11<=0,"ok","oil change") -> oil change | Z11: =C11+K11+S11 -> 0 | AA11: =U11+M11+E11 -> 0 | AB11: =V11+N11+F11 -> 250 | AC11: =IF(Z11>0,AA11/Z11,0) -> 0 | AD11: =ELEC!Q12 -> 0 | AE11: =SUM(AD11/Z11) -> #DIV/0! | AF11: =SUM(AE11/1600) -> #DIV/0! | AG11: =SUM(320*AF11) -> #DIV/0! | AH11: =SUM(AC11-AG11) -> #DIV/0! | AI11: =AD11*AJ11 -> 0 | AJ11: =305/1185 -> 0.25738397 | AK11: =AI11/Z11 -> #DIV/0!
A12: =ELEC!C13 -> 44479 | B12: =B11 -> 10971 | C12: =B12-B11 -> 0 | D12: =D11 -> 522800 | E12: =SUM(D12-D11) -> 0 | F12: =IF(C12>0,E12/C12,0) -> 0 | H12: =H11 -> 11055 | I12: =IF(B12-H12<=0,"ok","oil change") -> ok | J12: =J11 -> 10698 | K12: =J12-J11 -> 0 | L12: =L11 -> 357691 | M12: =SUM(L12-L11) -> 0 | N12: =IF(K12>0,M12/K12,0) -> 0 | P12: =P11 -> 10873 | Q12: =IF(J12-P12<=0,"ok","oil change") -> ok | R12: =R11 -> 13134 | S12: =R12-R11 -> 0 | T12: =T11+U12 -> 222994 | U12: =V12*S12 -> 0 | V12: 250 | X12: =X11 -> 13068 | Y12: =IF(R12-X12<=0,"ok","oil change") -> oil change | Z12: =C12+K12+S12 -> 0 | AA12: =U12+M12+E12 -> 0 | AB12: =V12+N12+F12 -> 250 | AC12: =IF(Z12>0,AA12/Z12,0) -> 0 | AD12: =ELEC!Q13 -> 0 | AE12: =SUM(AD12/Z12) -> #DIV/0! | AF12: =SUM(AE12/1600) -> #DIV/0! | AG12: =SUM(320*AF12) -> #DIV/0! | AH12: =SUM(AC12-AG12) -> #DIV/0! | AI12: =AD12*AJ12 -> 0 | AJ12: =305/1185 -> 0.25738397 | AK12: =AI12/Z12 -> #DIV/0!
A13: =ELEC!C14 -> 44480 | B13: =B12 -> 10971 | C13: =B13-B12 -> 0 | D13: =D12 -> 522800 | E13: =SUM(D13-D12) -> 0 | F13: =IF(C13>0,E13/C13,0) -> 0 | H13: =H12 -> 11055 | I13: =IF(B13-H13<=0,"ok","oil change") -> ok | J13: =J12 -> 10698 | K13: =J13-J12 -> 0 | L13: =L12 -> 357691 | M13: =SUM(L13-L12) -> 0 | N13: =IF(K13>0,M13/K13,0) -> 0 | P13: =P12 -> 10873 | Q13: =IF(J13-P13<=0,"ok","oil change") -> ok | R13: =R12 -> 13134 | S13: =R13-R12 -> 0 | T13: =T12+U13 -> 222994 | U13: =V13*S13 -> 0 | V13: 250 | X13: =X12 -> 13068 | Y13: =IF(R13-X13<=0,"ok","oil change") -> oil change | Z13: =C13+K13+S13 -> 0 | AA13: =U13+M13+E13 -> 0 | AB13: =V13+N13+F13 -> 250 | AC13: =IF(Z13>0,AA13/Z13,0) -> 0 | AD13: =ELEC!Q14 -> 0 | AE13: =SUM(AD13/Z13) -> #DIV/0! | AF13: =SUM(AE13/1600) -> #DIV/0! | AG13: =SUM(320*AF13) -> #DIV/0! | AH13: =SUM(AC13-AG13) -> #DIV/0! | AI13: =AD13*AJ13 -> 0 | AJ13: =305/1185 -> 0.25738397 | AK13: =AI13/Z13 -> #DIV/0!
A14: =ELEC!C15 -> 44481 | B14: =B13 -> 10971 | C14: =B14-B13 -> 0 | D14: =D13 -> 522800 | E14: =SUM(D14-D13) -> 0 | F14: =IF(C14>0,E14/C14,0) -> 0 | H14: 11055 | I14: =IF(B14-H14<=0,"ok","oil change") -> ok | J14: =J13 -> 10698 | K14: =J14-J13 -> 0 | L14: =L13 -> 357691 | M14: =SUM(L14-L13) -> 0 | N14: =IF(K14>0,M14/K14,0) -> 0 | P14: =P13 -> 10873 | Q14: =IF(J14-P14<=0,"ok","oil change") -> ok | R14: =R13 -> 13134 | S14: =R14-R13 -> 0 | T14: =T13+U14 -> 222994 | U14: =V14*S14 -> 0 | V14: 250 | X14: =X13 -> 13068 | Y14: =IF(R14-X14<=0,"ok","oil change") -> oil change | Z14: =C14+K14+S14 -> 0 | AA14: =U14+M14+E14 -> 0 | AB14: =V14+N14+F14 -> 250 | AC14: =IF(Z14>0,AA14/Z14,0) -> 0 | AD14: =ELEC!Q15 -> 0 | AE14: =SUM(AD14/Z14) -> #DIV/0! | AF14: =SUM(AE14/1600) -> #DIV/0! | AG14: =SUM(320*AF14) -> #DIV/0! | AH14: =SUM(AC14-AG14) -> #DIV/0! | AI14: =AD14*AJ14 -> 0 | AJ14: =305/1185 -> 0.25738397 | AK14: =AI14/Z14 -> #DIV/0!
A15: =ELEC!C16 -> 44482 | B15: =B14 -> 10971 | C15: =B15-B14 -> 0 | D15: =D14 -> 522800 | E15: =SUM(D15-D14) -> 0 | F15: =IF(C15>0,E15/C15,0) -> 0 | H15: 11055 | I15: =IF(B15-H15<=0,"ok","oil change") -> ok | J15: =J14 -> 10698 | K15: =J15-J14 -> 0 | L15: =L14 -> 357691 | M15: =SUM(L15-L14) -> 0 | N15: =IF(K15>0,M15/K15,0) -> 0 | P15: =P14 -> 10873 | Q15: =IF(J15-P15<=0,"ok","oil change") -> ok | R15: =R14 -> 13134 | S15: =R15-R14 -> 0 | T15: =T14+U15 -> 222994 | U15: =V15*S15 -> 0 | V15: 250 | X15: =X14 -> 13068 | Y15: =IF(R15-X15<=0,"ok","oil change") -> oil change | Z15: =C15+K15+S15 -> 0 | AA15: =U15+M15+E15 -> 0 | AB15: =V15+N15+F15 -> 250 | AC15: =IF(Z15>0,AA15/Z15,0) -> 0 | AD15: =ELEC!Q16 -> 0 | AE15: =SUM(AD15/Z15) -> #DIV/0! | AF15: =SUM(AE15/1600) -> #DIV/0! | AG15: =SUM(320*AF15) -> #DIV/0! | AH15: =SUM(AC15-AG15) -> #DIV/0! | AI15: =AD15*AJ15 -> 0 | AJ15: =305/1185 -> 0.25738397 | AK15: =AI15/Z15 -> #DIV/0!
A16: =ELEC!C17 -> 44483 | B16: =B15 -> 10971 | C16: =B16-B15 -> 0 | D16: =D15 -> 522800 | E16: =SUM(D16-D15) -> 0 | F16: =IF(C16>0,E16/C16,0) -> 0 | H16: 11055 | I16: =IF(B16-H16<=0,"ok","oil change") -> ok | J16: =J15 -> 10698 | K16: =J16-J15 -> 0 | L16: =L15 -> 357691 | M16: =SUM(L16-L15) -> 0 | N16: =IF(K16>0,M16/K16,0) -> 0 | P16: =P15 -> 10873 | Q16: =IF(J16-P16<=0,"ok","oil change") -> ok | R16: =R15 -> 13134 | S16: =R16-R15 -> 0 | T16: =T15+U16 -> 222994 | U16: =V16*S16 -> 0 | V16: 250 | X16: =X15 -> 13068 | Y16: =IF(R16-X16<=0,"ok","oil change") -> oil change | Z16: =C16+K16+S16 -> 0 | AA16: =U16+M16+E16 -> 0 | AB16: =V16+N16+F16 -> 250 | AC16: =IF(Z16>0,AA16/Z16,0) -> 0 | AD16: =ELEC!Q17 -> 0 | AE16: =SUM(AD16/Z16) -> #DIV/0! | AF16: =SUM(AE16/1600) -> #DIV/0! | AG16: =SUM(320*AF16) -> #DIV/0! | AH16: =SUM(AC16-AG16) -> #DIV/0! | AI16: =AD16*AJ16 -> 0 | AJ16: =305/1185 -> 0.25738397 | AK16: =AI16/Z16 -> #DIV/0!
A17: =ELEC!C18 -> 44484 | B17: =B16 -> 10971 | C17: =B17-B16 -> 0 | D17: =D16 -> 522800 | E17: =SUM(D17-D16) -> 0 | F17: =IF(C17>0,E17/C17,0) -> 0 | H17: =H16 -> 11055 | I17: =IF(B17-H17<=0,"ok","oil change") -> ok | J17: =J16 -> 10698 | K17: =J17-J16 -> 0 | L17: =L16 -> 357691 | M17: =SUM(L17-L16) -> 0 | N17: =IF(K17>0,M17/K17,0) -> 0 | P17: =P16 -> 10873 | Q17: =IF(J17-P17<=0,"ok","oil change") -> ok | R17: =R16 -> 13134 | S17: =R17-R16 -> 0 | T17: =T16+U17 -> 222994 | U17: =V17*S17 -> 0 | V17: 250 | X17: =X16 -> 13068 | Y17: =IF(R17-X17<=0,"ok","oil change") -> oil change | Z17: =C17+K17+S17 -> 0 | AA17: =U17+M17+E17 -> 0 | AB17: =V17+N17+F17 -> 250 | AC17: =IF(Z17>0,AA17/Z17,0) -> 0 | AD17: =ELEC!Q18 -> 0 | AE17: =SUM(AD17/Z17) -> #DIV/0! | AF17: =SUM(AE17/1600) -> #DIV/0! | AG17: =SUM(320*AF17) -> #DIV/0! | AH17: =SUM(AC17-AG17) -> #DIV/0! | AI17: =AD17*AJ17 -> 0 | AJ17: =305/1185 -> 0.25738397 | AK17: =AI17/Z17 -> #DIV/0!
A18: =ELEC!C19 -> 44485 | B18: =B17 -> 10971 | C18: =B18-B17 -> 0 | D18: =D17 -> 522800 | E18: =SUM(D18-D17) -> 0 | F18: =IF(C18>0,E18/C18,0) -> 0 | H18: =H17 -> 11055 | I18: =IF(B18-H18<=0,"ok","oil change") -> ok | J18: =J17 -> 10698 | K18: =J18-J17 -> 0 | L18: =L17 -> 357691 | M18: =SUM(L18-L17) -> 0 | N18: =IF(K18>0,M18/K18,0) -> 0 | P18: =P17 -> 10873 | Q18: =IF(J18-P14<=0,"ok","oil change") -> ok | R18: =R17 -> 13134 | S18: =R18-R17 -> 0 | T18: =T17+U18 -> 222994 | U18: =V18*S18 -> 0 | V18: 250 | X18: =X17 -> 13068 | Y18: =IF(R18-X18<=0,"ok","oil change") -> oil change | Z18: =C18+K18+S18 -> 0 | AA18: =U18+M18+E18 -> 0 | AB18: =V18+N18+F18 -> 250 | AC18: =IF(Z18>0,AA18/Z18,0) -> 0 | AD18: =ELEC!Q19 -> 0 | AE18: =SUM(AD18/Z18) -> #DIV/0! | AF18: =SUM(AE18/1600) -> #DIV/0! | AG18: =SUM(320*AF18) -> #DIV/0! | AH18: =SUM(AC18-AG18) -> #DIV/0! | AI18: =AD18*AJ18 -> 0 | AJ18: =305/1185 -> 0.25738397 | AK18: =AI18/Z18 -> #DIV/0!
A19: =ELEC!C20 -> 44486 | B19: =B18 -> 10971 | C19: =B19-B18 -> 0 | D19: =D18 -> 522800 | E19: =SUM(D19-D18) -> 0 | F19: =IF(C19>0,E19/C19,0) -> 0 | H19: =H18 -> 11055 | I19: =IF(B19-H19<=0,"ok","oil change") -> ok | J19: =J18 -> 10698 | K19: =J19-J18 -> 0 | L19: =L18 -> 357691 | M19: =SUM(L19-L18) -> 0 | N19: =IF(K19>0,M19/K19,0) -> 0 | P19: =P18 -> 10873 | Q19: =IF(J19-P19<=0,"ok","oil change") -> ok | R19: =R18 -> 13134 | S19: =R19-R18 -> 0 | T19: =T18+U19 -> 222994 | U19: =V19*S19 -> 0 | V19: 250 | X19: =X18 -> 13068 | Y19: =IF(R19-X19<=0,"ok","oil change") -> oil change | Z19: =C19+K19+S19 -> 0 | AA19: =U19+M19+E19 -> 0 | AB19: =V19+N19+F19 -> 250 | AC19: =IF(Z19>0,AA19/Z19,0) -> 0 | AD19: =ELEC!Q20 -> 0 | AE19: =SUM(AD19/Z19) -> #DIV/0! | AF19: =SUM(AE19/1600) -> #DIV/0! | AG19: =SUM(320*AF19) -> #DIV/0! | AH19: =SUM(AC19-AG19) -> #DIV/0! | AI19: =AD19*AJ19 -> 0 | AJ19: =305/1185 -> 0.25738397 | AK19: =AI19/Z19 -> #DIV/0!
A20: =ELEC!C21 -> 44487 | B20: =B19 -> 10971 | C20: =B20-B19 -> 0 | D20: =D19 -> 522800 | E20: =SUM(D20-D19) -> 0 | F20: =IF(C20>0,E20/C20,0) -> 0 | H20: =H19 -> 11055 | I20: =IF(B20-H20<=0,"ok","oil change") -> ok | J20: =J19 -> 10698 | K20: =J20-J19 -> 0 | L20: =L19 -> 357691 | M20: =SUM(L20-L19) -> 0 | N20: =IF(K20>0,M20/K20,0) -> 0 | P20: =P19 -> 10873 | Q20: =IF(J20-P20<=0,"ok","oil change") -> ok | R20: =R19 -> 13134 | S20: =R20-R19 -> 0 | T20: =T19+U20 -> 222994 | U20: =V20*S20 -> 0 | V20: 250 | X20: =X19 -> 13068 | Y20: =IF(R20-X20<=0,"ok","oil change") -> oil change | Z20: =C20+K20+S20 -> 0 | AA20: =U20+M20+E20 -> 0 | AB20: =V20+N20+F20 -> 250 | AC20: =IF(Z20>0,AA20/Z20,0) -> 0 | AD20: =ELEC!Q21 -> 0 | AE20: =SUM(AD20/Z20) -> #DIV/0! | AF20: =SUM(AE20/1600) -> #DIV/0! | AG20: =SUM(320*AF20) -> #DIV/0! | AH20: =SUM(AC20-AG20) -> #DIV/0! | AI20: =AD20*AJ20 -> 0 | AJ20: =305/1185 -> 0.25738397 | AK20: =AI20/Z20 -> #DIV/0!
A21: =ELEC!C22 -> 44488 | B21: =B20 -> 10971 | C21: =B21-B20 -> 0 | D21: =D20 -> 522800 | E21: =SUM(D21-D20) -> 0 | F21: =IF(C21>0,E21/C21,0) -> 0 | H21: =H20 -> 11055 | I21: =IF(B21-H21<=0,"ok","oil change") -> ok | J21: =J20 -> 10698 | K21: =J21-J20 -> 0 | L21: =L20 -> 357691 | M21: =SUM(L21-L20) -> 0 | N21: =IF(K21>0,M21/K21,0) -> 0 | P21: =P20 -> 10873 | Q21: =IF(J21-P21<=0,"ok","oil change") -> ok | R21: =R20 -> 13134 | S21: =R21-R20 -> 0 | T21: =T20+U21 -> 222994 | U21: =V21*S21 -> 0 | V21: 250 | X21: =X20 -> 13068 | Y21: =Y20 -> oil change | Z21: =C21+K21+S21 -> 0 | AA21: =U21+M21+E21 -> 0 | AB21: =V21+N21+F21 -> 250 | AC21: =IF(Z21>0,AA21/Z21,0) -> 0 | AD21: =ELEC!Q22 -> 0 | AE21: =SUM(AD21/Z21) -> #DIV/0! | AF21: =SUM(AE21/1600) -> #DIV/0! | AG21: =SUM(320*AF21) -> #DIV/0! | AH21: =SUM(AC21-AG21) -> #DIV/0! | AI21: =AD21*AJ21 -> 0 | AJ21: =305/1185 -> 0.25738397 | AK21: =AI21/Z21 -> #DIV/0!
A22: =ELEC!C23 -> 44489 | B22: =B21 -> 10971 | C22: =B22-B21 -> 0 | D22: =D21 -> 522800 | E22: =150*C22 -> 0 | F22: =IF(C22>0,E22/C22,0) -> 0 | H22: =H21 -> 11055 | I22: =IF(B22-H22<=0,"ok","oil change") -> ok | J22: =J21 -> 10698 | K22: =J22-J21 -> 0 | L22: =L21 -> 357691 | M22: =SUM(L22-L21) -> 0 | N22: =IF(K22>0,M22/K22,0) -> 0 | P22: =P21 -> 10873 | Q22: =IF(J22-P22<=0,"ok","oil change") -> ok | R22: =R21 -> 13134 | S22: =R22-R21 -> 0 | T22: =T21+U22 -> 222994 | U22: =V22*S22 -> 0 | V22: 250 | X22: 13229 | Y22: =IF(R22-X22<=0,"ok","oil change") -> ok | Z22: =C22+K22+S22 -> 0 | AA22: =U22+M22+E22 -> 0 | AB22: =V22+N22+F22 -> 250 | AC22: =IF(Z22>0,AA22/Z22,0) -> 0 | AD22: =ELEC!Q23 -> 0 | AE22: =SUM(AD22/Z22) -> #DIV/0! | AF22: =SUM(AE22/1600) -> #DIV/0! | AG22: =SUM(320*AF22) -> #DIV/0! | AH22: =SUM(AC22-AG22) -> #DIV/0! | AI22: =AD22*AJ22 -> 0 | AJ22: =305/1185 -> 0.25738397 | AK22: =AI22/Z22 -> #DIV/0!
A23: =ELEC!C24 -> 44490 | B23: =B22 -> 10971 | C23: =B23-B22 -> 0 | D23: =D22 -> 522800 | E23: =150*C23 -> 0 | F23: =IF(C23>0,E23/C23,0) -> 0 | H23: =H22 -> 11055 | I23: =IF(B23-H23<=0,"ok","oil change") -> ok | J23: =J22 -> 10698 | K23: =J23-J22 -> 0 | L23: =L22 -> 357691 | M23: =SUM(L23-L22) -> 0 | N23: =IF(K23>0,M23/K23,0) -> 0 | P23: =P22 -> 10873 | Q23: =IF(J23-P23<=0,"ok","oil change") -> ok | R23: =R22 -> 13134 | S23: =R23-R22 -> 0 | T23: =T22+U23 -> 222994 | U23: =V23*S23 -> 0 | V23: 250 | X23: 13229 | Y23: =IF(R23-X23<=0,"ok","oil change") -> ok | Z23: =C23+K23+S23 -> 0 | AA23: =U23+M23+E23 -> 0 | AB23: =V23+N23+F23 -> 250 | AC23: =IF(Z23>0,AA23/Z23,0) -> 0 | AD23: =ELEC!Q24 -> 0 | AE23: =SUM(AD23/Z23) -> #DIV/0! | AF23: =SUM(AE23/1600) -> #DIV/0! | AG23: =SUM(320*AF23) -> #DIV/0! | AH23: =SUM(AC23-AG23) -> #DIV/0! | AI23: =AD23*AJ23 -> 0 | AJ23: =305/1185 -> 0.25738397 | AK23: =AI23/Z23 -> #DIV/0!
A24: =ELEC!C25 -> 44491 | B24: =B23 -> 10971 | C24: =B24-B23 -> 0 | D24: =D23 -> 522800 | E24: =SUM(D24-D23) -> 0 | F24: =IF(C24>0,E24/C24,0) -> 0 | H24: =H23 -> 11055 | I24: =IF(B24-H24<=0,"ok","oil change") -> ok | J24: =J23 -> 10698 | K24: =J24-J23 -> 0 | L24: =L23 -> 357691 | M24: =SUM(L24-L23) -> 0 | N24: =IF(K24>0,M24/K24,0) -> 0 | P24: =P23 -> 10873 | Q24: =IF(J24-P24<=0,"ok","oil change") -> ok | R24: =R23 -> 13134 | S24: =R24-R23 -> 0 | T24: =T23+U24 -> 222994 | U24: =V24*S24 -> 0 | V24: 250 | X24: =X23 -> 13229 | Y24: =IF(R24-X24<=0,"ok","oil change") -> ok | Z24: =C24+K24+S24 -> 0 | AA24: =U24+M24+E24 -> 0 | AB24: =V24+N24+F24 -> 250 | AC24: =IF(Z24>0,AA24/Z24,0) -> 0 | AD24: =ELEC!Q25 -> 0 | AE24: =SUM(AD24/Z24) -> #DIV/0! | AF24: =SUM(AE24/1600) -> #DIV/0! | AG24: =SUM(320*AF24) -> #DIV/0! | AH24: =SUM(AC24-AG24) -> #DIV/0! | AI24: =AD24*AJ24 -> 0 | AJ24: =305/1185 -> 0.25738397 | AK24: =AI24/Z24 -> #DIV/0!
A25: =ELEC!C26 -> 44492 | B25: =B24 -> 10971 | C25: =B25-B24 -> 0 | D25: =D24 -> 522800 | E25: =SUM(D25-D24) -> 0 | F25: =IF(C25>0,E25/C25,0) -> 0 | H25: =H24 -> 11055 | I25: =IF(B25-H25<=0,"ok","oil change") -> ok | J25: =J24 -> 10698 | K25: =J25-J24 -> 0 | L25: =L24 -> 357691 | M25: =SUM(L25-L24) -> 0 | N25: =IF(K25>0,M25/K25,0) -> 0 | P25: =P24 -> 10873 | Q25: =IF(J25-P25<=0,"ok","oil change") -> ok | R25: =R24 -> 13134 | S25: =R25-R24 -> 0 | T25: =T24+U25 -> 222994 | U25: =V25*S25 -> 0 | V25: 250 | X25: =X24 -> 13229 | Y25: =IF(R25-X25<=0,"ok","oil change") -> ok | Z25: =C25+K25+S25 -> 0 | AA25: =U25+M25+E25 -> 0 | AB25: =V25+N25+F25 -> 250 | AC25: =IF(Z25>0,AA25/Z25,0) -> 0 | AD25: =ELEC!Q26 -> 0 | AE25: =SUM(AD25/Z25) -> #DIV/0! | AF25: =SUM(AE25/1600) -> #DIV/0! | AG25: =SUM(320*AF25) -> #DIV/0! | AH25: =SUM(AC25-AG25) -> #DIV/0! | AI25: =AD25*AJ25 -> 0 | AJ25: =305/1185 -> 0.25738397 | AK25: =AI25/Z25 -> #DIV/0!
A26: =ELEC!C27 -> 44493 | B26: =B25 -> 10971 | C26: =B26-B25 -> 0 | D26: =D25 -> 522800 | E26: =SUM(D26-D25) -> 0 | F26: =IF(C26>0,E26/C26,0) -> 0 | H26: =H25 -> 11055 | I26: =IF(B26-H26<=0,"ok","oil change") -> ok | J26: =J25 -> 10698 | K26: =J26-J25 -> 0 | L26: =L25 -> 357691 | M26: =SUM(L26-L25) -> 0 | N26: =IF(K26>0,M26/K26,0) -> 0 | P26: =P25 -> 10873 | Q26: =IF(J26-P26<=0,"ok","oil change") -> ok | R26: =R25 -> 13134 | S26: =R26-R25 -> 0 | T26: =T25+U26 -> 222994 | U26: =V26*S26 -> 0 | V26: 250 | X26: =X25 -> 13229 | Y26: =IF(R26-X26<=0,"ok","oil change") -> ok | Z26: =C26+K26+S26 -> 0 | AA26: =U26+M26+E26 -> 0 | AB26: =V26+N26+F26 -> 250 | AC26: =IF(Z26>0,AA26/Z26,0) -> 0 | AD26: =ELEC!Q27 -> 0 | AE26: =SUM(AD26/Z26) -> #DIV/0! | AF26: =SUM(AE26/1600) -> #DIV/0! | AG26: =SUM(320*AF26) -> #DIV/0! | AH26: =SUM(AC26-AG26) -> #DIV/0! | AI26: =AD26*AJ26 -> 0 | AJ26: =305/1185 -> 0.25738397 | AK26: =AI26/Z26 -> #DIV/0!
A27: =ELEC!C28 -> 44494 | B27: =B26 -> 10971 | C27: =B27-B26 -> 0 | D27: =D26 -> 522800 | E27: =SUM(D27-D26) -> 0 | F27: =IF(C27>0,E27/C27,0) -> 0 | H27: =H26 -> 11055 | I27: =IF(B27-H27<=0,"ok","oil change") -> ok | J27: =J26 -> 10698 | K27: =J27-J26 -> 0 | L27: =L26 -> 357691 | M27: =SUM(L27-L26) -> 0 | N27: =IF(K27>0,M27/K27,0) -> 0 | P27: =P26 -> 10873 | Q27: =IF(J27-P27<=0,"ok","oil change") -> ok | R27: =R26 -> 13134 | S27: =R27-R26 -> 0 | T27: =T26+U27 -> 222994 | U27: =V27*S27 -> 0 | V27: 250 | X27: =X26 -> 13229 | Y27: =IF(R27-X27<=0,"ok","oil change") -> ok | Z27: =C27+K27+S27 -> 0 | AA27: =U27+M27+E27 -> 0 | AB27: =V27+N27+F27 -> 250 | AC27: =IF(Z27>0,AA27/Z27,0) -> 0 | AD27: =ELEC!Q28 -> 0 | AE27: =SUM(AD27/Z27) -> #DIV/0! | AF27: =SUM(AE27/1600) -> #DIV/0! | AG27: =SUM(320*AF27) -> #DIV/0! | AH27: =SUM(AC27-AG27) -> #DIV/0! | AI27: =AD27*AJ27 -> 0 | AJ27: =305/1185 -> 0.25738397 | AK27: =AI27/Z27 -> #DIV/0!
A28: =ELEC!C29 -> 44495 | B28: =B27 -> 10971 | C28: =B28-B27 -> 0 | D28: =D27 -> 522800 | E28: =SUM(D28-D27) -> 0 | F28: =IF(C28>0,E28/C28,0) -> 0 | H28: =H27 -> 11055 | I28: =IF(B28-H28<=0,"ok","oil change") -> ok | J28: =J27 -> 10698 | K28: =J28-J27 -> 0 | L28: =L27 -> 357691 | M28: =SUM(L28-L27) -> 0 | N28: =IF(K28>0,M28/K28,0) -> 0 | P28: =P27 -> 10873 | Q28: =IF(J28-P28<=0,"ok","oil change") -> ok | R28: =R27 -> 13134 | S28: =R28-R27 -> 0 | T28: =T27+U28 -> 222994 | U28: =V28*S28 -> 0 | V28: 250 | X28: =X27 -> 13229 | Y28: =IF(R28-X28<=0,"ok","oil change") -> ok | Z28: =C28+K28+S28 -> 0 | AA28: =U28+M28+E28 -> 0 | AB28: =V28+N28+F28 -> 250 | AC28: =IF(Z28>0,AA28/Z28,0) -> 0 | AD28: =ELEC!Q29 -> 0 | AE28: =SUM(AD28/Z28) -> #DIV/0! | AF28: =SUM(AE28/1600) -> #DIV/0! | AG28: =SUM(320*AF28) -> #DIV/0! | AH28: =SUM(AC28-AG28) -> #DIV/0! | AI28: =AD28*AJ28 -> 0 | AJ28: =305/1185 -> 0.25738397 | AK28: =AI28/Z28 -> #DIV/0!
A29: =ELEC!C30 -> 44496 | B29: =B28 -> 10971 | C29: =B29-B28 -> 0 | D29: =D28 -> 522800 | E29: =SUM(D29-D28) -> 0 | F29: =IF(C29>0,E29/C29,0) -> 0 | H29: =H28 -> 11055 | I29: =IF(B29-H29<=0,"ok","oil change") -> ok | J29: =J28 -> 10698 | K29: =J29-J28 -> 0 | L29: =L28 -> 357691 | M29: =SUM(L29-L28) -> 0 | N29: =IF(K29>0,M29/K29,0) -> 0 | P29: =P28 -> 10873 | Q29: =IF(J29-P29<=0,"ok","oil change") -> ok | R29: =R28 -> 13134 | S29: =R29-R28 -> 0 | T29: =T28+U29 -> 222994 | U29: =V29*S29 -> 0 | V29: 250 | X29: =X28 -> 13229 | Y29: =IF(R29-X29<=0,"ok","oil change") -> ok | Z29: =C29+K29+S29 -> 0 | AA29: =U29+M29+E29 -> 0 | AB29: =V29+N29+F29 -> 250 | AC29: =IF(Z29>0,AA29/Z29,0) -> 0 | AD29: =ELEC!Q30 -> 0 | AE29: =SUM(AD29/Z29) -> #DIV/0! | AF29: =SUM(AE29/1600) -> #DIV/0! | AG29: =SUM(320*AF29) -> #DIV/0! | AH29: =SUM(AC29-AG29) -> #DIV/0! | AI29: =AD29*AJ29 -> 0 | AJ29: =305/1185 -> 0.25738397 | AK29: =AI29/Z29 -> #DIV/0!
A30: =ELEC!C31 -> 44497 | B30: =B29 -> 10971 | C30: =B30-B29 -> 0 | D30: =D29 -> 522800 | E30: =SUM(D30-D29) -> 0 | F30: =IF(C30>0,E30/C30,0) -> 0 | H30: =H29 -> 11055 | I30: =IF(B30-H30<=0,"ok","oil change") -> ok | J30: =J29 -> 10698 | K30: =J30-J29 -> 0 | L30: =L29 -> 357691 | M30: =SUM(L30-L29) -> 0 | N30: =IF(K30>0,M30/K30,0) -> 0 | P30: =P29 -> 10873 | Q30: =IF(J30-P30<=0,"ok","oil change") -> ok | R30: =R29 -> 13134 | S30: =R30-R29 -> 0 | T30: =T29+U30 -> 222994 | U30: =V30*S30 -> 0 | V30: 250 | X30: =X29 -> 13229 | Y30: =IF(R30-X30<=0,"ok","oil change") -> ok | Z30: =C30+K30+S30 -> 0 | AA30: =U30+M30+E30 -> 0 | AB30: =V30+N30+F30 -> 250 | AC30: =IF(Z30>0,AA30/Z30,0) -> 0 | AD30: =ELEC!Q31 -> 0 | AE30: =SUM(AD30/Z30) -> #DIV/0! | AF30: =SUM(AE30/1600) -> #DIV/0! | AG30: =SUM(320*AF30) -> #DIV/0! | AH30: =SUM(AC30-AG30) -> #DIV/0! | AI30: =AD30*AJ30 -> 0 | AJ30: =305/1185 -> 0.25738397 | AK30: =AI30/Z30 -> #DIV/0!
A31: =ELEC!C32 -> 44498 | B31: =B30 -> 10971 | C31: =B31-B30 -> 0 | D31: =D30 -> 522800 | E31: =SUM(D31-D30) -> 0 | F31: =IF(C31>0,E31/C31,0) -> 0 | H31: =H30 -> 11055 | I31: =IF(B31-H31<=0,"ok","oil change") -> ok | J31: =J30 -> 10698 | K31: =J31-J30 -> 0 | L31: =L30 -> 357691 | M31: =SUM(L31-L30) -> 0 | N31: =IF(K31>0,M31/K31,0) -> 0 | P31: =P30 -> 10873 | Q31: =IF(J31-P31<=0,"ok","oil change") -> ok | R31: =R30 -> 13134 | S31: =R31-R30 -> 0 | T31: =T30+U31 -> 222994 | U31: =V31*S31 -> 0 | V31: 250 | X31: =X30 -> 13229 | Y31: =IF(R31-X31<=0,"ok","oil change") -> ok | Z31: =C31+K31+S31 -> 0 | AA31: =U31+M31+E31 -> 0 | AB31: =V31+N31+F31 -> 250 | AC31: =IF(Z31>0,AA31/Z31,0) -> 0 | AD31: =ELEC!Q32 -> 0 | AE31: =SUM(AD31/Z31) -> #DIV/0! | AF31: =SUM(AE31/1600) -> #DIV/0! | AG31: =SUM(320*AF31) -> #DIV/0! | AH31: =SUM(AC31-AG31) -> #DIV/0! | AI31: =AD31*AJ31 -> 0 | AJ31: =305/1185 -> 0.25738397 | AK31: =AI31/Z31 -> #DIV/0!
A32: =ELEC!C33 -> 44499 | B32: =B31 -> 10971 | C32: =B32-B31 -> 0 | D32: =D31 -> 522800 | E32: =SUM(D32-D31) -> 0 | F32: =IF(C32>0,E32/C32,0) -> 0 | H32: =H31 -> 11055 | I32: =IF(B32-H32<=0,"ok","oil change") -> ok | J32: =J31 -> 10698 | K32: =J32-J31 -> 0 | L32: =L31 -> 357691 | M32: =SUM(L32-L31) -> 0 | N32: =IF(K32>0,M32/K32,0) -> 0 | P32: =P31 -> 10873 | Q32: =IF(J32-P32<=0,"ok","oil change") -> ok | R32: =R31 -> 13134 | S32: =R32-R31 -> 0 | T32: =T31+U32 -> 222994 | U32: =V32*S32 -> 0 | V32: 250 | X32: =X31 -> 13229 | Y32: =IF(R32-X32<=0,"ok","oil change") -> ok | Z32: =C32+K32+S32 -> 0 | AA32: =U32+M32+E32 -> 0 | AB32: =V32+N32+F32 -> 250 | AC32: =IF(Z32>0,AA32/Z32,0) -> 0 | AD32: =ELEC!Q33 -> 0 | AE32: =SUM(AD32/Z32) -> #DIV/0! | AF32: =SUM(AE32/1600) -> #DIV/0! | AG32: =SUM(320*AF32) -> #DIV/0! | AH32: =SUM(AC32-AG32) -> #DIV/0! | AI32: =AD32*AJ32 -> 0 | AJ32: =305/1185 -> 0.25738397 | AK32: =AI32/Z32 -> #DIV/0!
A33: =ELEC!C34 -> 44500 | B33: =B32 -> 10971 | C33: =B33-B32 -> 0 | D33: =D32 -> 522800 | E33: =SUM(D33-D32) -> 0 | F33: =IF(C33>0,E33/C33,0) -> 0 | H33: =H32 -> 11055 | I33: =IF(B33-H33<=0,"ok","oil change") -> ok | J33: =J32 -> 10698 | K33: =J33-J32 -> 0 | L33: =L32 -> 357691 | M33: =SUM(L33-L32) -> 0 | N33: =IF(K33>0,M33/K33,0) -> 0 | P33: =P32 -> 10873 | Q33: =IF(J33-P33<=0,"ok","oil change") -> ok | R33: =R32 -> 13134 | S33: =R33-R32 -> 0 | T33: =T32+U33 -> 222994 | U33: =V33*S33 -> 0 | V33: 251 | X33: =X32 -> 13229 | Y33: =IF(R33-X33<=0,"ok","oil change") -> ok | Z33: =C33+K33+S33 -> 0 | AA33: =U33+M33+E33 -> 0 | AB33: =V33+N33+F33 -> 251 | AC33: =IF(Z33>0,AA33/Z33,0) -> 0 | AD33: =ELEC!Q34 -> 0 | AE33: =SUM(AD33/Z33) -> #DIV/0! | AF33: =SUM(AE33/1600) -> #DIV/0! | AG33: =SUM(320*AF33) -> #DIV/0! | AH33: =SUM(AC33-AG33) -> #DIV/0! | AI33: =AD33*AJ33 -> 0 | AJ33: =305/1185 -> 0.25738397 | AK33: =AI33/Z33 -> #DIV/0!
P34: =+O34/3 -> 0 | U34: =SUM(C35:S35) -> 9 | X34: 341 | Z34: =SUM(Z3:Z33) -> 9
C35: =SUM(C3:C33) -> 6 | K35: =SUM(K3:K33) -> 0 | S35: =SUM(S3:S33) -> 3

Sheet tanks
B2: Tank 1 | D2: Tank 2 | F2: Tank 3 | H2: Tank 4 | J2: Tank 5 | L2: Tank 6 | N2: Tank 7 | P2: Tank 8 | R2: Tank 9 | T2: Tank 10 | V2: Tank 11 | Z2: Tank 1 | AB2: Tank 2 | AD2: Tank 3 | AF2: Tank 4 | AH2: Tank 5 | AJ2: Tank 6 | AL2: Tank 7
B3: 6670 | D3: =SUM(B3) -> 6670 | F3: =SUM(D3) -> 6670 | H3: =SUM(F3) -> 6670 | J3: =SUM(H3) -> 6670 | L3: =SUM(J3) -> 6670 | N3: =SUM(L3) -> 6670 | P3: =SUM(N3) -> 6670 | R3: =SUM(P3) -> 6670 | T3: =SUM(R3) -> 6670 | V3: =SUM(T3) -> 6670 | W3: =SUM(B3:V3) -> 73370 | Z3: 2800 | AB3: 2800 | AD3: 2800 | AF3: 2800 | AH3: 2800 | AJ3: 2800 | AL3: 2800 | AM3: =SUM(Z3:AL3) -> 19600 | AO3: =SUM(AM3+W3) -> 92970 | AR3: Total sotck | AS3: Diesel Cons Per day | AT3: Diesel Delivery | BE3: Genset Co | BF3: Steam | BG3: Boil | BH3: Outdoor temperature
B4: =B3/310 -> 21.516129 | D4: =SUM(B4) -> 21.516129 | F4: =SUM(D4) -> 21.516129 | H4: =SUM(F4) -> 21.516129 | J4: =SUM(H4) -> 21.516129 | L4: =SUM(J4) -> 21.516129 | N4: =SUM(L4) -> 21.516129 | P4: =SUM(N4) -> 21.516129 | R4: =SUM(P4) -> 21.516129 | T4: =SUM(R4) -> 21.516129 | V4: =SUM(T4) -> 21.516129 | Z4: =Z3/280 -> 10 | AA4: =AA3/280 -> 0 | AB4: =AB3/280 -> 10 | AC4: =AC3/280 -> 0 | AD4: =AD3/280 -> 10 | AE4: =AE3/280 -> 0 | AF4: =AF3/280 -> 10 | AG4: =AG3/280 -> 0 | ... AL4: =AL3/280 -> 10 | AT4: Delivery | AU4: Cost /L | AW4: Boiler+Steam | AX4: Generator | AZ4: Occupancy | BA4: AVE TEPM | BB4: AVE Humidity
A5: =[2]tanks!$A$35 -> 44469 | B5: =[2]tanks!B35 -> 146 | C5: =[2]tanks!C35 -> 3141.3548 | D5: =[2]tanks!D35 -> 146 | E5: =[2]tanks!E35 -> 3141.3548 | F5: =[2]tanks!F35 -> 146 | G5: =[2]tanks!G35 -> 3141.3548 | H5: =[2]tanks!H35 -> 146 | I5: =[2]tanks!I35 -> 3141.3548 | ... AD5: =[2]tanks!AD35 -> 153 | AE5: =[2]tanks!$AE$35 -> 1530 | AF5: =[2]tanks!AF35 -> 153 | AG5: =[2]tanks!AG35 -> 1530 | AH5: =[2]tanks!AH35 -> 153 | AI5: =[2]tanks!AI35 -> 1530 | AJ5: =[2]tanks!AJ35 -> 153 | AK5: =[2]tanks!AK35 -> 1530 | AL5: =[2]tanks!AL35 -> 153 | AM5: =[2]tanks!AM35 -> 1530 | ... AO5: =[2]tanks!AO35 -> 10710 | AQ5: =[2]tanks!$AQ$35 -> 0.48687645 | AR5: =[2]tanks!AR35 -> 45264.903 | AS5: =[2]tanks!AS35 -> -2383.4194 | AT5: =[2]tanks!AT35 -> 0 | AU5: =[2]tanks!AU35 -> 0 | AV5: =[2]tanks!AV35 -> 0.605 | AW5: =[2]tanks!AW35 -> -57 | AX5: =[2]tanks!AX35 -> -2326.4194 | AY5: =[2]tanks!AY35 -> -2383.4194 | ... BG5: =[2]tanks!BG35 -> 0 | BH5: =[5]tanks!BH36 -> 0
A6: =ELEC!C4 -> 44470 | B6: ='B5'!B5 -> 146 | C6: =B6*$B$4 -> 3141.3548 | D6: =SUM(B6) -> 146 | E6: =D6*$B$4 -> 3141.3548 | F6: =SUM(D6) -> 146 | G6: =F6*$B$4 -> 3141.3548 | H6: =SUM(F6) -> 146 | I6: =H6*$B$4 -> 3141.3548 | J6: =SUM(H6) -> 146 | K6: =J6*$B$4 -> 3141.3548 | L6: =SUM(J6) -> 146 | M6: =L6*$B$4 -> 3141.3548 | N6: =SUM(L6) -> 146 | O6: =N6*$B$4 -> 3141.3548 | P6: =SUM(N6) -> 146 | Q6: =P6*$B$4 -> 3141.3548 | R6: =SUM(P6) -> 146 | S6: =R6*$B$4 -> 3141.3548 | T6: =SUM(R6) -> 146 | U6: =T6*$B$4 -> 3141.3548 | V6: =SUM(T6) -> 146 | W6: =V6*$B$4 -> 3141.3548 | X6: =SUM(Y6/73370) -> 0.47096774 | Y6: =SUM(C6+E6+G6+I6+K6+M6+O6+Q6+S6+U6+W6) -> 34554.903 | Z6: ='B5'!C5 -> 153 | AA6: =SUM(Z6*$Z$4) -> 1530 | AB6: =SUM(Z6) -> 153 | AC6: =SUM(AB6*$Z$4) -> 1530 | AD6: =SUM(AB6) -> 153 | AE6: =SUM(AD6*$Z$4) -> 1530 | AF6: =SUM(AD6) -> 153 | AG6: =SUM(AF6*$Z$4) -> 1530 | AH6: =SUM(AF6) -> 153 | AI6: =SUM(AH6*$Z$4) -> 1530 | AJ6: =SUM(AH6) -> 153 | AK6: =SUM(AJ6*$Z$4) -> 1530 | AL6: =SUM(AJ6) -> 153 | AM6: =SUM(AL6*$Z$4) -> 1530 | AN6: =SUM(AO6/19600) -> 0.54642857 | AO6: =SUM(AA6+AC6+AE6+AG6+AI6+AK6+AM6) -> 10710 | AQ6: =SUM(AR6/92970) -> 0.48687645 | AR6: =Y6+AO6 -> 45264.903 | AS6: =SUM(AR6-AR5-AT6) -> -5000 | AT6: 5000 | AU6: 0.615 | AV6: =IF(AT6>0,AU6,AV5) -> 0.615 | AW6: =-SUM('B5'!AI5) -> 0 | AX6: =-SUM(AW6-AS6) -> -5000 | AY6: =SUM(AX6+AW6) -> -5000 | AZ6: =ELEC!A4 -> 0 | BA6: ='General information '!D5 -> 0 | BB6: =SUM('General information '!E5) -> 0 | BC6: =IF(AR3>=AR6,0,1) -> 0 | BD6: 19222 | BE6: =(305/1185)*ELEC!Q5 -> 0 | BG6: =#REF!-BE6 -> #REF! | BH6: 21 | BI6: 12 | BJ6: =AX6/BI6 -> -416.66667 | BK6: =GEN!AF3 -> #DIV/0!
A7: =ELEC!C5 -> 44471 | B7: ='B5'!B6 -> 146 | C7: =B7*$B$4 -> 3141.3548 | D7: =SUM(B7) -> 146 | E7: =D7*$B$4 -> 3141.3548 | F7: =SUM(D7) -> 146 | G7: =F7*$B$4 -> 3141.3548 | H7: =SUM(F7) -> 146 | I7: =H7*$B$4 -> 3141.3548 | J7: =SUM(H7) -> 146 | K7: =J7*$B$4 -> 3141.3548 | L7: =SUM(J7) -> 146 | M7: =L7*$B$4 -> 3141.3548 | N7: =SUM(L7) -> 146 | O7: =N7*$B$4 -> 3141.3548 | P7: =SUM(N7) -> 146 | Q7: =P7*$B$4 -> 3141.3548 | R7: =SUM(P7) -> 146 | S7: =R7*$B$4 -> 3141.3548 | T7: =SUM(R7) -> 146 | U7: =T7*$B$4 -> 3141.3548 | V7: =SUM(T7) -> 146 | W7: =V7*$B$4 -> 3141.3548 | X7: =SUM(Y7/73370) -> 0.47096774 | Y7: =SUM(C7+E7+G7+I7+K7+M7+O7+Q7+S7+U7+W7) -> 34554.903 | Z7: ='B5'!C6 -> 153 | AA7: =SUM(Z7*$Z$4) -> 1530 | AB7: =SUM(Z7) -> 153 | AC7: =SUM(AB7*$Z$4) -> 1530 | AD7: =SUM(AB7) -> 153 | AE7: =SUM(AD7*$Z$4) -> 1530 | AF7: =SUM(AD7) -> 153 | AG7: =SUM(AF7*$Z$4) -> 1530 | AH7: =SUM(AF7) -> 153 | AI7: =SUM(AH7*$Z$4) -> 1530 | AJ7: =SUM(AH7) -> 153 | AK7: =SUM(AJ7*$Z$4) -> 1530 | AL7: =SUM(AJ7) -> 153 | AM7: =SUM(AL7*$Z$4) -> 1530 | AN7: =SUM(AO7/19600) -> 0.54642857 | AO7: =SUM(AA7+AC7+AE7+AG7+AI7+AK7+AM7) -> 10710 | AQ7: =SUM(AR7/92970) -> 0.48687645 | AR7: =Y7+AO7 -> 45264.903 | AS7: =SUM(AR7-AR6-AT7) -> 0 | AV7: =IF(AT7>0,AU7,AV6) -> 0.615 | AW7: =-SUM('B5'!AI6) -> 0 | AX7: =-SUM(AW7-AS7) -> 0 | AY7: =SUM(AX7+AW7) -> 0 | AZ7: =ELEC!A5 -> 0 | BA7: ='General information '!D6 -> 0 | BB7: =SUM('General information '!E6) -> 0 | BC7: 0 | BD7: 19222 | BE7: =(305/1185)*ELEC!Q6 -> 1702.8523 | BG7: =#REF!-BE7 -> #REF! | BH7: 19 | BI7: 15 | BJ7: =AX7/BI7 -> 0 | BK7: =GEN!AF4 -> #DIV/0!
A8: =ELEC!C6 -> 44472 | B8: ='B5'!B7 -> 157 | C8: =B8*$B$4 -> 3378.0323 | D8: =SUM(B8) -> 157 | E8: =D8*$B$4 -> 3378.0323 | F8: =SUM(D8) -> 157 | G8: =F8*$B$4 -> 3378.0323 | H8: =SUM(F8) -> 157 | I8: =H8*$B$4 -> 3378.0323 | J8: =SUM(H8) -> 157 | K8: =J8*$B$4 -> 3378.0323 | L8: =SUM(J8) -> 157 | M8: =L8*$B$4 -> 3378.0323 | N8: =SUM(L8) -> 157 | O8: =N8*$B$4 -> 3378.0323 | P8: =SUM(N8) -> 157 | Q8: =P8*$B$4 -> 3378.0323 | R8: =SUM(P8) -> 157 | S8: =R8*$B$4 -> 3378.0323 | T8: =SUM(R8) -> 157 | U8: =T8*$B$4 -> 3378.0323 | V8: =SUM(T8) -> 157 | W8: =V8*$B$4 -> 3378.0323 | X8: =SUM(Y8/73370) -> 0.50645161 | Y8: =SUM(C8+E8+G8+I8+K8+M8+O8+Q8+S8+U8+W8) -> 37158.355 | Z8: ='B5'!C7 -> 164 | AA8: =SUM(Z8*$Z$4) -> 1640 | AB8: =SUM(Z8) -> 164 | AC8: =SUM(AB8*$Z$4) -> 1640 | AD8: =SUM(AB8) -> 164 | AE8: =SUM(AD8*$Z$4) -> 1640 | AF8: =SUM(AD8) -> 164 | AG8: =SUM(AF8*$Z$4) -> 1640 | AH8: =SUM(AF8) -> 164 | AI8: =SUM(AH8*$Z$4) -> 1640 | AJ8: =SUM(AH8) -> 164 | AK8: =SUM(AJ8*$Z$4) -> 1640 | AL8: =SUM(AJ8) -> 164 | AM8: =SUM(AL8*$Z$4) -> 1640 | AN8: =SUM(AO8/19600) -> 0.58571429 | AO8: =SUM(AA8+AC8+AE8+AG8+AI8+AK8+AM8) -> 11480 | AQ8: =SUM(AR8/92970) -> 0.52316182 | AR8: =Y8+AO8 -> 48638.355 | AS8: =SUM(AR8-AR7-AT8) -> 3373.4516 | AV8: =IF(AT8>0,AU8,AV7) -> 0.615 | AW8: =-SUM('B5'!AI7) -> -81 | AX8: =-SUM(AW8-AS8) -> 3454.4516 | AY8: =SUM(AX8+AW8) -> 3373.4516 | AZ8: =ELEC!A6 -> 0 | BA8: ='General information '!D7 -> 26 | BB8: =SUM('General information '!E7) -> 0.63 | BC8: =IF(AR7>=AR8,0,1) -> 1 | BD8: 19222 | BE8: =(305/1185)*ELEC!Q7 -> 0 | BG8: =#REF!-BE8 -> #REF! | BH8: 16 | BI8: 9 | BJ8: =AX8/BI8 -> 383.82796 | BK8: =GEN!AF5 -> 0.45944444
A9: =ELEC!C7 -> 44473 | B9: ='B5'!B8 -> 157 | C9: =B9*$B$4 -> 3378.0323 | D9: =SUM(B9) -> 157 | E9: =D9*$B$4 -> 3378.0323 | F9: =SUM(D9) -> 157 | G9: =F9*$B$4 -> 3378.0323 | H9: =SUM(F9) -> 157 | I9: =H9*$B$4 -> 3378.0323 | J9: =SUM(H9) -> 157 | K9: =J9*$B$4 -> 3378.0323 | L9: =SUM(J9) -> 157 | M9: =L9*$B$4 -> 3378.0323 | N9: =SUM(L9) -> 157 | O9: =N9*$B$4 -> 3378.0323 | P9: =SUM(N9) -> 157 | Q9: =P9*$B$4 -> 3378.0323 | R9: =SUM(P9) -> 157 | S9: =R9*$B$4 -> 3378.0323 | T9: =SUM(R9) -> 157 | U9: =T9*$B$4 -> 3378.0323 | V9: =SUM(T9) -> 157 | W9: =V9*$B$4 -> 3378.0323 | X9: =SUM(Y9/73370) -> 0.50645161 | Y9: =SUM(C9+E9+G9+I9+K9+M9+O9+Q9+S9+U9+W9) -> 37158.355 | Z9: ='B5'!C8 -> 164 | AA9: =SUM(Z9*$Z$4) -> 1640 | AB9: =SUM(Z9) -> 164 | AC9: =SUM(AB9*$Z$4) -> 1640 | AD9: =SUM(AB9) -> 164 | AE9: =SUM(AD9*$Z$4) -> 1640 | AF9: =SUM(AD9) -> 164 | AG9: =SUM(AF9*$Z$4) -> 1640 | AH9: =SUM(AF9) -> 164 | AI9: =SUM(AH9*$Z$4) -> 1640 | AJ9: =SUM(AH9) -> 164 | AK9: =SUM(AJ9*$Z$4) -> 1640 | AL9: =SUM(AJ9) -> 164 | AM9: =SUM(AL9*$Z$4) -> 1640 | AN9: =SUM(AO9/19600) -> 0.58571429 | AO9: =SUM(AA9+AC9+AE9+AG9+AI9+AK9+AM9) -> 11480 | AQ9: =SUM(AR9/92970) -> 0.52316182 | AR9: =Y9+AO9 -> 48638.355 | AS9: =SUM(AR9-AR8-AT9) -> 0 | AV9: =IF(AT9>0,AU9,AV8) -> 0.615 | AW9: =-SUM('B5'!AI8) -> 0 | AX9: =-SUM(AW9-AS9) -> 0 | AY9: =SUM(AX9+AW9) -> 0 | AZ9: =ELEC!A7 -> 0 | BA9: ='General information '!D8 -> 0 | BB9: =SUM('General information '!E8) -> 0 | BC9: =IF(AR8>=AR9,0,1) -> 0 | BD9: 19222 | BE9: =(305/1185)*ELEC!Q8 -> 0 | BG9: =#REF!-BE9 -> #REF! | BH9: 18 | BI9: 6 | BJ9: =AX9/BI9 -> 0 | BK9: =GEN!AF6 -> #DIV/0!
A10: =ELEC!C8 -> 44474 | B10: ='B5'!B9 -> 157 | C10: =B10*$B$4 -> 3378.0323 | D10: =SUM(B10) -> 157 | E10: =D10*$B$4 -> 3378.0323 | F10: =SUM(D10) -> 157 | G10: =F10*$B$4 -> 3378.0323 | H10: =SUM(F10) -> 157 | I10: =H10*$B$4 -> 3378.0323 | J10: =SUM(H10) -> 157 | K10: =J10*$B$4 -> 3378.0323 | L10: =SUM(J10) -> 157 | M10: =L10*$B$4 -> 3378.0323 | N10: =SUM(L10) -> 157 | O10: =N10*$B$4 -> 3378.0323 | P10: =SUM(N10) -> 157 | Q10: =P10*$B$4 -> 3378.0323 | R10: =SUM(P10) -> 157 | S10: =R10*$B$4 -> 3378.0323 | T10: =SUM(R10) -> 157 | U10: =T10*$B$4 -> 3378.0323 | V10: =SUM(T10) -> 157 | W10: =V10*$B$4 -> 3378.0323 | X10: =SUM(Y10/73370) -> 0.50645161 | Y10: =SUM(C10+E10+G10+I10+K10+M10+O10+Q10+S10+U10+W10) -> 37158.355 | Z10: ='B5'!C9 -> 164 | AA10: =SUM(Z10*$Z$4) -> 1640 | AB10: =SUM(Z10) -> 164 | AC10: =SUM(AB10*$Z$4) -> 1640 | AD10: =SUM(AB10) -> 164 | AE10: =SUM(AD10*$Z$4) -> 1640 | AF10: =SUM(AD10) -> 164 | AG10: =SUM(AF10*$Z$4) -> 1640 | AH10: =SUM(AF10) -> 164 | AI10: =SUM(AH10*$Z$4) -> 1640 | AJ10: =SUM(AH10) -> 164 | AK10: =SUM(AJ10*$Z$4) -> 1640 | AL10: =SUM(AJ10) -> 164 | AM10: =SUM(AL10*$Z$4) -> 1640 | AN10: =SUM(AO10/19600) -> 0.58571429 | AO10: =SUM(AA10+AC10+AE10+AG10+AI10+AK10+AM10) -> 11480 | AQ10: =SUM(AR10/92970) -> 0.52316182 | AR10: =Y10+AO10 -> 48638.355 | AS10: =SUM(AR10-AR9-AT10) -> 0 | AV10: =IF(AT10>0,AU10,AV9) -> 0.615 | AW10: =-SUM('B5'!AI9) -> 0 | AX10: =-SUM(AW10-AS10) -> 0 | AY10: =SUM(AX10+AW10) -> 0 | AZ10: =ELEC!A8 -> 0 | BA10: ='General information '!D9 -> 0 | BB10: =SUM('General information '!E9) -> 0 | BC10: =IF(AR9>=AR10,0,1) -> 0 | BD10: 19222 | BE10: =(305/1185)*ELEC!Q9 -> 0 | BG10: =#REF!-BE10 -> #REF! | BH10: 16 | BI10: 7 | BJ10: =AX10/BI10 -> 0 | BK10: =GEN!AF7 -> #DIV/0!
A11: =ELEC!C9 -> 44475 | B11: ='B5'!B10 -> 157 | C11: =B11*$B$4 -> 3378.0323 | D11: =SUM(B11) -> 157 | E11: =D11*$B$4 -> 3378.0323 | F11: =SUM(D11) -> 157 | G11: =F11*$B$4 -> 3378.0323 | H11: =SUM(F11) -> 157 | I11: =H11*$B$4 -> 3378.0323 | J11: =SUM(H11) -> 157 | K11: =J11*$B$4 -> 3378.0323 | L11: =SUM(J11) -> 157 | M11: =L11*$B$4 -> 3378.0323 | N11: =SUM(L11) -> 157 | O11: =N11*$B$4 -> 3378.0323 | P11: =SUM(N11) -> 157 | Q11: =P11*$B$4 -> 3378.0323 | R11: =SUM(P11) -> 157 | S11: =R11*$B$4 -> 3378.0323 | T11: =SUM(R11) -> 157 | U11: =T11*$B$4 -> 3378.0323 | V11: =SUM(T11) -> 157 | W11: =V11*$B$4 -> 3378.0323 | X11: =SUM(Y11/73370) -> 0.50645161 | Y11: =SUM(C11+E11+G11+I11+K11+M11+O11+Q11+S11+U11+W11) -> 37158.355 | Z11: ='B5'!C10 -> 164 | AA11: =SUM(Z11*$Z$4) -> 1640 | AB11: =SUM(Z11) -> 164 | AC11: =SUM(AB11*$Z$4) -> 1640 | AD11: =SUM(AB11) -> 164 | AE11: =SUM(AD11*$Z$4) -> 1640 | AF11: =SUM(AD11) -> 164 | AG11: =SUM(AF11*$Z$4) -> 1640 | AH11: =SUM(AF11) -> 164 | AI11: =SUM(AH11*$Z$4) -> 1640 | AJ11: =SUM(AH11) -> 164 | AK11: =SUM(AJ11*$Z$4) -> 1640 | AL11: =SUM(AJ11) -> 164 | AM11: =SUM(AL11*$Z$4) -> 1640 | AN11: =SUM(AO11/19600) -> 0.58571429 | AO11: =SUM(AA11+AC11+AE11+AG11+AI11+AK11+AM11) -> 11480 | AQ11: =SUM(AR11/92970) -> 0.52316182 | AR11: =Y11+AO11 -> 48638.355 | AS11: =SUM(AR11-AR10-AT11) -> 0 | AV11: =IF(AT11>0,AU11,AV10) -> 0.615 | AW11: =-SUM('B5'!AI10) -> 0 | AX11: =-SUM(AW11-AS11) -> 0 | AY11: =SUM(AX11+AW11) -> 0 | AZ11: =ELEC!A9 -> 0 | BA11: ='General information '!D10 -> 0 | BB11: =SUM('General information '!E10) -> 0 | BC11: =IF(AR10>=AR11,0,1) -> 0 | BD11: 19222 | BE11: =(305/1185)*ELEC!Q10 -> 0 | BG11: =#REF!-BE11 -> #REF! | BH11: 16.5 | BI11: 9.3 | BJ11: =AX11/BI11 -> 0 | BK11: =GEN!AF8 -> #DIV/0!
A12: =ELEC!C10 -> 44476 | B12: ='B5'!B11 -> 157 | C12: =B12*$B$4 -> 3378.0323 | D12: =SUM(B12) -> 157 | E12: =D12*$B$4 -> 3378.0323 | F12: =SUM(D12) -> 157 | G12: =F12*$B$4 -> 3378.0323 | H12: =SUM(F12) -> 157 | I12: =H12*$B$4 -> 3378.0323 | J12: =SUM(H12) -> 157 | K12: =J12*$B$4 -> 3378.0323 | L12: =SUM(J12) -> 157 | M12: =L12*$B$4 -> 3378.0323 | N12: =SUM(L12) -> 157 | O12: =N12*$B$4 -> 3378.0323 | P12: =SUM(N12) -> 157 | Q12: =P12*$B$4 -> 3378.0323 | R12: =SUM(P12) -> 157 | S12: =R12*$B$4 -> 3378.0323 | T12: =SUM(R12) -> 157 | U12: =T12*$B$4 -> 3378.0323 | V12: =SUM(T12) -> 157 | W12: =V12*$B$4 -> 3378.0323 | X12: =SUM(Y12/73370) -> 0.50645161 | Y12: =SUM(C12+E12+G12+I12+K12+M12+O12+Q12+S12+U12+W12) -> 37158.355 | Z12: ='B5'!C11 -> 164 | AA12: =SUM(Z12*$Z$4) -> 1640 | AB12: =SUM(Z12) -> 164 | AC12: =SUM(AB12*$Z$4) -> 1640 | AD12: =SUM(AB12) -> 164 | AE12: =SUM(AD12*$Z$4) -> 1640 | AF12: =SUM(AD12) -> 164 | AG12: =SUM(AF12*$Z$4) -> 1640 | AH12: =SUM(AF12) -> 164 | AI12: =SUM(AH12*$Z$4) -> 1640 | AJ12: =SUM(AH12) -> 164 | AK12: =SUM(AJ12*$Z$4) -> 1640 | AL12: =SUM(AJ12) -> 164 | AM12: =SUM(AL12*$Z$4) -> 1640 | AN12: =SUM(AO12/19600) -> 0.58571429 | AO12: =SUM(AA12+AC12+AE12+AG12+AI12+AK12+AM12) -> 11480 | AQ12: =SUM(AR12/92970) -> 0.52316182 | AR12: =Y12+AO12 -> 48638.355 | AS12: =SUM(AR12-AR11-AT12) -> 0 | AV12: =IF(AT12>0,AU12,AV11) -> 0.615 | AW12: =-SUM('B5'!AI11) -> 0 | AX12: =-SUM(AW12-AS12) -> 0 | AY12: =SUM(AX12+AW12) -> 0 | AZ12: =ELEC!A10 -> 0 | BA12: ='General information '!D11 -> 0 | BB12: =SUM('General information '!E11) -> 0 | BC12: =IF(AR11>=AR12,0,1) -> 0 | BD12: 19222 | BE12: =(305/1185)*ELEC!Q11 -> 0 | BG12: =#REF!-BE12 -> #REF! | BH12: 15.5 | BI12: 3.7 | BJ12: =AX12/BI12 -> 0 | BK12: =GEN!AF9 -> #DIV/0!
A13: =ELEC!C11 -> 44477 | B13: ='B5'!B12 -> 157 | C13: =B13*$B$4 -> 3378.0323 | D13: =SUM(B13) -> 157 | E13: =D13*$B$4 -> 3378.0323 | F13: =SUM(D13) -> 157 | G13: =F13*$B$4 -> 3378.0323 | H13: =SUM(F13) -> 157 | I13: =H13*$B$4 -> 3378.0323 | J13: =SUM(H13) -> 157 | K13: =J13*$B$4 -> 3378.0323 | L13: =SUM(J13) -> 157 | M13: =L13*$B$4 -> 3378.0323 | N13: =SUM(L13) -> 157 | O13: =N13*$B$4 -> 3378.0323 | P13: =SUM(N13) -> 157 | Q13: =P13*$B$4 -> 3378.0323 | R13: =SUM(P13) -> 157 | S13: =R13*$B$4 -> 3378.0323 | T13: =SUM(R13) -> 157 | U13: =T13*$B$4 -> 3378.0323 | V13: =SUM(T13) -> 157 | W13: =V13*$B$4 -> 3378.0323 | X13: =SUM(Y13/73370) -> 0.50645161 | Y13: =SUM(C13+E13+G13+I13+K13+M13+O13+Q13+S13+U13+W13) -> 37158.355 | Z13: ='B5'!C12 -> 164 | AA13: =SUM(Z13*$Z$4) -> 1640 | AB13: =SUM(Z13) -> 164 | AC13: =SUM(AB13*$Z$4) -> 1640 | AD13: =SUM(AB13) -> 164 | AE13: =SUM(AD13*$Z$4) -> 1640 | AF13: =SUM(AD13) -> 164 | AG13: =SUM(AF13*$Z$4) -> 1640 | AH13: =SUM(AF13) -> 164 | AI13: =SUM(AH13*$Z$4) -> 1640 | AJ13: =SUM(AH13) -> 164 | AK13: =SUM(AJ13*$Z$4) -> 1640 | AL13: =SUM(AJ13) -> 164 | AM13: =SUM(AL13*$Z$4) -> 1640 | AN13: =SUM(AO13/19600) -> 0.58571429 | AO13: =SUM(AA13+AC13+AE13+AG13+AI13+AK13+AM13) -> 11480 | AQ13: =SUM(AR13/92970) -> 0.52316182 | AR13: =Y13+AO13 -> 48638.355 | AS13: =SUM(AR13-AR12-AT13) -> 0 | AV13: =IF(AT13>0,AU13,AV12) -> 0.615 | AW13: =-SUM('B5'!AI12) -> 0 | AX13: =-SUM(AW13-AS13) -> 0 | AY13: =SUM(AX13+AW13) -> 0 | AZ13: =ELEC!A11 -> 0 | BA13: ='General information '!D12 -> 0 | BB13: =SUM('General information '!E12) -> 0 | BC13: =IF(AR12>=AR13,0,1) -> 0 | BD13: 19222 | BE13: =(305/1185)*ELEC!Q12 -> 0 | BG13: =#REF!-BE13 -> #REF! | BI13: 5 | BJ13: =AX13/BI13 -> 0 | BK13: =GEN!AF10 -> #DIV/0!
A14: =ELEC!C12 -> 44478 | B14: ='B5'!B13 -> 157 | C14: =B14*$B$4 -> 3378.0323 | D14: =SUM(B14) -> 157 | E14: =D14*$B$4 -> 3378.0323 | F14: =SUM(D14) -> 157 | G14: =F14*$B$4 -> 3378.0323 | H14: =SUM(F14) -> 157 | I14: =H14*$B$4 -> 3378.0323 | J14: =SUM(H14) -> 157 | K14: =J14*$B$4 -> 3378.0323 | L14: =SUM(J14) -> 157 | M14: =L14*$B$4 -> 3378.0323 | N14: =SUM(L14) -> 157 | O14: =N14*$B$4 -> 3378.0323 | P14: =SUM(N14) -> 157 | Q14: =P14*$B$4 -> 3378.0323 | R14: =SUM(P14) -> 157 | S14: =R14*$B$4 -> 3378.0323 | T14: =SUM(R14) -> 157 | U14: =T14*$B$4 -> 3378.0323 | V14: =SUM(T14) -> 157 | W14: =V14*$B$4 -> 3378.0323 | X14: =SUM(Y14/73370) -> 0.50645161 | Y14: =SUM(C14+E14+G14+I14+K14+M14+O14+Q14+S14+U14+W14) -> 37158.355 | Z14: ='B5'!C13 -> 164 | AA14: =SUM(Z14*$Z$4) -> 1640 | AB14: =SUM(Z14) -> 164 | AC14: =SUM(AB14*$Z$4) -> 1640 | AD14: =SUM(AB14) -> 164 | AE14: =SUM(AD14*$Z$4) -> 1640 | AF14: =SUM(AD14) -> 164 | AG14: =SUM(AF14*$Z$4) -> 1640 | AH14: =SUM(AF14) -> 164 | AI14: =SUM(AH14*$Z$4) -> 1640 | AJ14: =SUM(AH14) -> 164 | AK14: =SUM(AJ14*$Z$4) -> 1640 | AL14: =SUM(AJ14) -> 164 | AM14: =SUM(AL14*$Z$4) -> 1640 | AN14: =SUM(AO14/19600) -> 0.58571429 | AO14: =SUM(AA14+AC14+AE14+AG14+AI14+AK14+AM14) -> 11480 | AQ14: =SUM(AR14/92970) -> 0.52316182 | AR14: =Y14+AO14 -> 48638.355 | AS14: =SUM(AR14-AR13-AT14) -> 0 | AV14: =IF(AT14>0,AU14,AV13) -> 0.615 | AW14: =-SUM('B5'!AI13) -> 0 | AX14: =-SUM(AW14-AS14) -> 0 | AY14: =SUM(AX14+AW14) -> 0 | AZ14: =ELEC!A12 -> 0 | BA14: ='General information '!D13 -> 0 | BB14: =SUM('General information '!E13) -> 0 | BC14: =IF(AR13>=AR14,0,1) -> 0 | BD14: 19222 | BE14: =(305/1185)*ELEC!Q13 -> 0 | BG14: =#REF!-BE14 -> #REF! | BI14: 3 | BJ14: =AX14/BI14 -> 0 | BK14: =GEN!AF11 -> #DIV/0!
A15: =ELEC!C13 -> 44479 | B15: ='B5'!B14 -> 157 | C15: =B15*$B$4 -> 3378.0323 | D15: =SUM(B15) -> 157 | E15: =D15*$B$4 -> 3378.0323 | F15: =SUM(D15) -> 157 | G15: =F15*$B$4 -> 3378.0323 | H15: =SUM(F15) -> 157 | I15: =H15*$B$4 -> 3378.0323 | J15: =SUM(H15) -> 157 | K15: =J15*$B$4 -> 3378.0323 | L15: =SUM(J15) -> 157 | M15: =L15*$B$4 -> 3378.0323 | N15: =SUM(L15) -> 157 | O15: =N15*$B$4 -> 3378.0323 | P15: =SUM(N15) -> 157 | Q15: =P15*$B$4 -> 3378.0323 | R15: =SUM(P15) -> 157 | S15: =R15*$B$4 -> 3378.0323 | T15: =SUM(R15) -> 157 | U15: =T15*$B$4 -> 3378.0323 | V15: =SUM(T15) -> 157 | W15: =V15*$B$4 -> 3378.0323 | X15: =SUM(Y15/73370) -> 0.50645161 | Y15: =SUM(C15+E15+G15+I15+K15+M15+O15+Q15+S15+U15+W15) -> 37158.355 | Z15: ='B5'!C14 -> 164 | AA15: =SUM(Z15*$Z$4) -> 1640 | AB15: =SUM(Z15) -> 164 | AC15: =SUM(AB15*$Z$4) -> 1640 | AD15: =SUM(AB15) -> 164 | AE15: =SUM(AD15*$Z$4) -> 1640 | AF15: =SUM(AD15) -> 164 | AG15: =SUM(AF15*$Z$4) -> 1640 | AH15: =SUM(AF15) -> 164 | AI15: =SUM(AH15*$Z$4) -> 1640 | AJ15: =SUM(AH15) -> 164 | AK15: =SUM(AJ15*$Z$4) -> 1640 | AL15: =SUM(AJ15) -> 164 | AM15: =SUM(AL15*$Z$4) -> 1640 | AN15: =SUM(AO15/19600) -> 0.58571429 | AO15: =SUM(AA15+AC15+AE15+AG15+AI15+AK15+AM15) -> 11480 | AQ15: =SUM(AR15/92970) -> 0.52316182 | AR15: =Y15+AO15 -> 48638.355 | AS15: =SUM(AR15-AR14-AT15) -> 0 | AV15: =IF(AT15>0,AU15,AV14) -> 0.615 | AW15: =-SUM('B5'!AI14) -> 0 | AX15: =-SUM(AW15-AS15) -> 0 | AY15: =SUM(AX15+AW15) -> 0 | AZ15: =ELEC!A13 -> 0 | BA15: ='General information '!D14 -> 0 | BB15: =SUM('General information '!E14) -> 0 | BC15: =IF(AR14>=AR15,0,1) -> 0 | BD15: 19222 | BE15: =(305/1185)*ELEC!Q14 -> 0 | BG15: =#REF!-BE15 -> #REF! | BI15: 4 | BJ15: =AX15/BI15 -> 0 | BK15: =GEN!AF12 -> #DIV/0!
A16: =ELEC!C14 -> 44480 | B16: ='B5'!B15 -> 157 | C16: =B16*$B$4 -> 3378.0323 | D16: =SUM(B16) -> 157 | E16: =D16*$B$4 -> 3378.0323 | F16: =SUM(D16) -> 157 | G16: =F16*$B$4 -> 3378.0323 | H16: =SUM(F16) -> 157 | I16: =H16*$B$4 -> 3378.0323 | J16: =SUM(H16) -> 157 | K16: =J16*$B$4 -> 3378.0323 | L16: =SUM(J16) -> 157 | M16: =L16*$B$4 -> 3378.0323 | N16: =SUM(L16) -> 157 | O16: =N16*$B$4 -> 3378.0323 | P16: =SUM(N16) -> 157 | Q16: =P16*$B$4 -> 3378.0323 | R16: =SUM(P16) -> 157 | S16: =R16*$B$4 -> 3378.0323 | T16: =SUM(R16) -> 157 | U16: =T16*$B$4 -> 3378.0323 | V16: =SUM(T16) -> 157 | W16: =V16*$B$4 -> 3378.0323 | X16: =SUM(Y16/73370) -> 0.50645161 | Y16: =SUM(C16+E16+G16+I16+K16+M16+O16+Q16+S16+U16+W16) -> 37158.355 | Z16: ='B5'!C15 -> 164 | AA16: =SUM(Z16*$Z$4) -> 1640 | AB16: =SUM(Z16) -> 164 | AC16: =SUM(AB16*$Z$4) -> 1640 | AD16: =SUM(AB16) -> 164 | AE16: =SUM(AD16*$Z$4) -> 1640 | AF16: =SUM(AD16) -> 164 | AG16: =SUM(AF16*$Z$4) -> 1640 | AH16: =SUM(AF16) -> 164 | AI16: =SUM(AH16*$Z$4) -> 1640 | AJ16: =SUM(AH16) -> 164 | AK16: =SUM(AJ16*$Z$4) -> 1640 | AL16: =SUM(AJ16) -> 164 | AM16: =SUM(AL16*$Z$4) -> 1640 | AN16: =SUM(AO16/19600) -> 0.58571429 | AO16: =SUM(AA16+AC16+AE16+AG16+AI16+AK16+AM16) -> 11480 | AQ16: =SUM(AR16/92970) -> 0.52316182 | AR16: =Y16+AO16 -> 48638.355 | AS16: =SUM(AR16-AR15-AT16) -> 0 | AV16: =IF(AT16>0,AU16,AV15) -> 0.615 | AW16: =-SUM('B5'!AI15) -> 0 | AX16: =-SUM(AW16-AS16) -> 0 | AY16: =SUM(AX16+AW16) -> 0 | AZ16: =ELEC!A14 -> 0 | BA16: ='General information '!D15 -> 0 | BB16: =SUM('General information '!E15) -> 0 | BC16: =IF(AR15>=AR16,0,1) -> 0 | BD16: 19222 | BE16: =(305/1185)*ELEC!Q15 -> 0 | BG16: =#REF!-BE16 -> #REF! | BI16: 3 | BJ16: =AX16/BI16 -> 0 | BK16: =GEN!AF13 -> #DIV/0!
A17: =ELEC!C15 -> 44481 | B17: ='B5'!B16 -> 157 | C17: =B17*$B$4 -> 3378.0323 | D17: =SUM(B17) -> 157 | E17: =D17*$B$4 -> 3378.0323 | F17: =SUM(D17) -> 157 | G17: =F17*$B$4 -> 3378.0323 | H17: =SUM(F17) -> 157 | I17: =H17*$B$4 -> 3378.0323 | J17: =SUM(H17) -> 157 | K17: =J17*$B$4 -> 3378.0323 | L17: =SUM(J17) -> 157 | M17: =L17*$B$4 -> 3378.0323 | N17: =SUM(L17) -> 157 | O17: =N17*$B$4 -> 3378.0323 | P17: =SUM(N17) -> 157 | Q17: =P17*$B$4 -> 3378.0323 | R17: =SUM(P17) -> 157 | S17: =R17*$B$4 -> 3378.0323 | T17: =SUM(R17) -> 157 | U17: =T17*$B$4 -> 3378.0323 | V17: =SUM(T17) -> 157 | W17: =V17*$B$4 -> 3378.0323 | X17: =SUM(Y17/73370) -> 0.50645161 | Y17: =SUM(C17+E17+G17+I17+K17+M17+O17+Q17+S17+U17+W17) -> 37158.355 | Z17: ='B5'!C16 -> 164 | AA17: =SUM(Z17*$Z$4) -> 1640 | AB17: =SUM(Z17) -> 164 | AC17: =SUM(AB17*$Z$4) -> 1640 | AD17: =SUM(AB17) -> 164 | AE17: =SUM(AD17*$Z$4) -> 1640 | AF17: =SUM(AD17) -> 164 | AG17: =SUM(AF17*$Z$4) -> 1640 | AH17: =SUM(AF17) -> 164 | AI17: =SUM(AH17*$Z$4) -> 1640 | AJ17: =SUM(AH17) -> 164 | AK17: =SUM(AJ17*$Z$4) -> 1640 | AL17: =SUM(AJ17) -> 164 | AM17: =SUM(AL17*$Z$4) -> 1640 | AN17: =SUM(AO17/19600) -> 0.58571429 | AO17: =SUM(AA17+AC17+AE17+AG17+AI17+AK17+AM17) -> 11480 | AQ17: =SUM(AR17/92970) -> 0.52316182 | AR17: =Y17+AO17 -> 48638.355 | AS17: =SUM(AR17-AR16-AT17) -> 0 | AV17: =IF(AT17>0,AU17,AV16) -> 0.615 | AW17: =-SUM('B5'!AI16) -> 0 | AX17: =-SUM(AW17-AS17) -> 0 | AY17: =SUM(AX17+AW17) -> 0 | AZ17: =ELEC!A15 -> 0 | BA17: ='General information '!D16 -> 0 | BB17: =SUM('General information '!E16) -> 0 | BC17: =IF(AR16>=AR17,0,1) -> 0 | BD17: 19222 | BE17: =(305/1185)*ELEC!Q16 -> 0 | BG17: =#REF!-BE17 -> #REF!
A18: =ELEC!C16 -> 44482 | B18: ='B5'!B17 -> 157 | C18: =B18*$B$4 -> 3378.0323 | D18: =SUM(B18) -> 157 | E18: =D18*$B$4 -> 3378.0323 | F18: =SUM(D18) -> 157 | G18: =F18*$B$4 -> 3378.0323 | H18: =SUM(F18) -> 157 | I18: =H18*$B$4 -> 3378.0323 | J18: =SUM(H18) -> 157 | K18: =J18*$B$4 -> 3378.0323 | L18: =SUM(J18) -> 157 | M18: =L18*$B$4 -> 3378.0323 | N18: =SUM(L18) -> 157 | O18: =N18*$B$4 -> 3378.0323 | P18: =SUM(N18) -> 157 | Q18: =P18*$B$4 -> 3378.0323 | R18: =SUM(P18) -> 157 | S18: =R18*$B$4 -> 3378.0323 | T18: =SUM(R18) -> 157 | U18: =T18*$B$4 -> 3378.0323 | V18: =SUM(T18) -> 157 | W18: =V18*$B$4 -> 3378.0323 | X18: =SUM(Y18/73370) -> 0.50645161 | Y18: =SUM(C18+E18+G18+I18+K18+M18+O18+Q18+S18+U18+W18) -> 37158.355 | Z18: ='B5'!C17 -> 164 | AA18: =SUM(Z18*$Z$4) -> 1640 | AB18: =SUM(Z18) -> 164 | AC18: =SUM(AB18*$Z$4) -> 1640 | AD18: =SUM(AB18) -> 164 | AE18: =SUM(AD18*$Z$4) -> 1640 | AF18: =SUM(AD18) -> 164 | AG18: =SUM(AF18*$Z$4) -> 1640 | AH18: =SUM(AF18) -> 164 | AI18: =SUM(AH18*$Z$4) -> 1640 | AJ18: =SUM(AH18) -> 164 | AK18: =SUM(AJ18*$Z$4) -> 1640 | AL18: =SUM(AJ18) -> 164 | AM18: =SUM(AL18*$Z$4) -> 1640 | AN18: =SUM(AO18/19600) -> 0.58571429 | AO18: =SUM(AA18+AC18+AE18+AG18+AI18+AK18+AM18) -> 11480 | AQ18: =SUM(AR18/92970) -> 0.52316182 | AR18: =Y18+AO18 -> 48638.355 | AS18: =SUM(AR18-AR17-AT18) -> 0 | AV18: =IF(AT18>0,AU18,AV17) -> 0.615 | AW18: =-SUM('B5'!AI17) -> 0 | AX18: =-SUM(AW18-AS18) -> 0 | AY18: =SUM(AX18+AW18) -> 0 | AZ18: =ELEC!A16 -> 0 | BA18: ='General information '!D17 -> 0 | BB18: =SUM('General information '!E17) -> 0 | BC18: =IF(AR17>=AR18,0,1) -> 0 | BD18: 19222 | BE18: =(305/1185)*ELEC!Q17 -> 0 | BG18: =#REF!-BE18 -> #REF!
A19: =ELEC!C17 -> 44483 | B19: ='B5'!B18 -> 157 | C19: =B19*$B$4 -> 3378.0323 | D19: =SUM(B19) -> 157 | E19: =D19*$B$4 -> 3378.0323 | F19: =SUM(D19) -> 157 | G19: =F19*$B$4 -> 3378.0323 | H19: =SUM(F19) -> 157 | I19: =H19*$B$4 -> 3378.0323 | J19: =SUM(H19) -> 157 | K19: =J19*$B$4 -> 3378.0323 | L19: =SUM(J19) -> 157 | M19: =L19*$B$4 -> 3378.0323 | N19: =SUM(L19) -> 157 | O19: =N19*$B$4 -> 3378.0323 | P19: =SUM(N19) -> 157 | Q19: =P19*$B$4 -> 3378.0323 | R19: =SUM(P19) -> 157 | S19: =R19*$B$4 -> 3378.0323 | T19: =SUM(R19) -> 157 | U19: =T19*$B$4 -> 3378.0323 | V19: =SUM(T19) -> 157 | W19: =V19*$B$4 -> 3378.0323 | X19: =SUM(Y19/73370) -> 0.50645161 | Y19: =SUM(C19+E19+G19+I19+K19+M19+O19+Q19+S19+U19+W19) -> 37158.355 | Z19: ='B5'!C18 -> 164 | AA19: =SUM(Z19*$Z$4) -> 1640 | AB19: =SUM(Z19) -> 164 | AC19: =SUM(AB19*$Z$4) -> 1640 | AD19: =SUM(AB19) -> 164 | AE19: =SUM(AD19*$Z$4) -> 1640 | AF19: =SUM(AD19) -> 164 | AG19: =SUM(AF19*$Z$4) -> 1640 | AH19: =SUM(AF19) -> 164 | AI19: =SUM(AH19*$Z$4) -> 1640 | AJ19: =SUM(AH19) -> 164 | AK19: =SUM(AJ19*$Z$4) -> 1640 | AL19: =SUM(AJ19) -> 164 | AM19: =SUM(AL19*$Z$4) -> 1640 | AN19: =SUM(AO19/19600) -> 0.58571429 | AO19: =SUM(AA19+AC19+AE19+AG19+AI19+AK19+AM19) -> 11480 | AQ19: =SUM(AR19/92970) -> 0.52316182 | AR19: =Y19+AO19 -> 48638.355 | AS19: =SUM(AR19-AR18-AT19) -> 0 | AV19: =IF(AT19>0,AU19,AV18) -> 0.615 | AW19: =-SUM('B5'!AI18) -> 0 | AX19: =-SUM(AW19-AS19) -> 0 | AY19: =SUM(AX19+AW19) -> 0 | AZ19: =ELEC!A17 -> 0 | BA19: ='General information '!D18 -> 0 | BB19: =SUM('General information '!E18) -> 0 | BC19: =IF(AR18>=AR19,0,1) -> 0 | BD19: 19222 | BE19: =(305/1185)*ELEC!Q18 -> 0 | BG19: =#REF!-BE19 -> #REF!
A20: =ELEC!C18 -> 44484 | B20: ='B5'!B19 -> 157 | C20: =B20*$B$4 -> 3378.0323 | D20: =SUM(B20) -> 157 | E20: =D20*$B$4 -> 3378.0323 | F20: =SUM(D20) -> 157 | G20: =F20*$B$4 -> 3378.0323 | H20: =SUM(F20) -> 157 | I20: =H20*$B$4 -> 3378.0323 | J20: =SUM(H20) -> 157 | K20: =J20*$B$4 -> 3378.0323 | L20: =SUM(J20) -> 157 | M20: =L20*$B$4 -> 3378.0323 | N20: =SUM(L20) -> 157 | O20: =N20*$B$4 -> 3378.0323 | P20: =SUM(N20) -> 157 | Q20: =P20*$B$4 -> 3378.0323 | R20: =SUM(P20) -> 157 | S20: =R20*$B$4 -> 3378.0323 | T20: =SUM(R20) -> 157 | U20: =T20*$B$4 -> 3378.0323 | V20: =SUM(T20) -> 157 | W20: =V20*$B$4 -> 3378.0323 | X20: =SUM(Y20/73370) -> 0.50645161 | Y20: =SUM(C20+E20+G20+I20+K20+M20+O20+Q20+S20+U20+W20) -> 37158.355 | Z20: ='B5'!C19 -> 164 | AA20: =SUM(Z20*$Z$4) -> 1640 | AB20: =SUM(Z20) -> 164 | AC20: =SUM(AB20*$Z$4) -> 1640 | AD20: =SUM(AB20) -> 164 | AE20: =SUM(AD20*$Z$4) -> 1640 | AF20: =SUM(AD20) -> 164 | AG20: =SUM(AF20*$Z$4) -> 1640 | AH20: =SUM(AF20) -> 164 | AI20: =SUM(AH20*$Z$4) -> 1640 | AJ20: =SUM(AH20) -> 164 | AK20: =SUM(AJ20*$Z$4) -> 1640 | AL20: =SUM(AJ20) -> 164 | AM20: =SUM(AL20*$Z$4) -> 1640 | AN20: =SUM(AO20/19600) -> 0.58571429 | AO20: =SUM(AA20+AC20+AE20+AG20+AI20+AK20+AM20) -> 11480 | AQ20: =SUM(AR20/92970) -> 0.52316182 | AR20: =Y20+AO20 -> 48638.355 | AS20: =SUM(AR20-AR19-AT20) -> 0 | AV20: =IF(AT20>0,AU20,AV19) -> 0.615 | AW20: =-SUM('B5'!AI19) -> 0 | AX20: =-SUM(AW20-AS20) -> 0 | AY20: =SUM(AX20+AW20) -> 0 | AZ20: =ELEC!A18 -> 0 | BA20: ='General information '!D19 -> 0 | BB20: =SUM('General information '!E19) -> 0 | BC20: =IF(AR19>=AR20,0,1) -> 0 | BD20: 19222 | BE20: =(305/1185)*ELEC!Q19 -> 0 | BG20: =#REF!-BE20 -> #REF!
A21: =ELEC!C19 -> 44485 | B21: ='B5'!B20 -> 157 | C21: =B21*$B$4 -> 3378.0323 | D21: =SUM(B21) -> 157 | E21: =D21*$B$4 -> 3378.0323 | F21: =SUM(D21) -> 157 | G21: =F21*$B$4 -> 3378.0323 | H21: =SUM(F21) -> 157 | I21: =H21*$B$4 -> 3378.0323 | J21: =SUM(H21) -> 157 | K21: =J21*$B$4 -> 3378.0323 | L21: =SUM(J21) -> 157 | M21: =L21*$B$4 -> 3378.0323 | N21: =SUM(L21) -> 157 | O21: =N21*$B$4 -> 3378.0323 | P21: =SUM(N21) -> 157 | Q21: =P21*$B$4 -> 3378.0323 | R21: =SUM(P21) -> 157 | S21: =R21*$B$4 -> 3378.0323 | T21: =SUM(R21) -> 157 | U21: =T21*$B$4 -> 3378.0323 | V21: =SUM(T21) -> 157 | W21: =V21*$B$4 -> 3378.0323 | X21: =SUM(Y21/73370) -> 0.50645161 | Y21: =SUM(C21+E21+G21+I21+K21+M21+O21+Q21+S21+U21+W21) -> 37158.355 | Z21: ='B5'!C20 -> 164 | AA21: =SUM(Z21*$Z$4) -> 1640 | AB21: =SUM(Z21) -> 164 | AC21: =SUM(AB21*$Z$4) -> 1640 | AD21: =SUM(AB21) -> 164 | AE21: =SUM(AD21*$Z$4) -> 1640 | AF21: =SUM(AD21) -> 164 | AG21: =SUM(AF21*$Z$4) -> 1640 | AH21: =SUM(AF21) -> 164 | AI21: =SUM(AH21*$Z$4) -> 1640 | AJ21: =SUM(AH21) -> 164 | AK21: =SUM(AJ21*$Z$4) -> 1640 | AL21: =SUM(AJ21) -> 164 | AM21: =SUM(AL21*$Z$4) -> 1640 | AN21: =SUM(AO21/19600) -> 0.58571429 | AO21: =SUM(AA21+AC21+AE21+AG21+AI21+AK21+AM21) -> 11480 | AQ21: =SUM(AR21/92970) -> 0.52316182 | AR21: =Y21+AO21 -> 48638.355 | AS21: =SUM(AR21-AR20-AT21) -> 0 | AV21: =IF(AT21>0,AU21,AV20) -> 0.615 | AW21: =-SUM('B5'!AI20) -> 0 | AX21: =-SUM(AW21-AS21) -> 0 | AY21: =SUM(AX21+AW21) -> 0 | AZ21: =ELEC!A19 -> 0 | BA21: ='General information '!D20 -> 0 | BB21: =SUM('General information '!E20) -> 0 | BC21: =IF(AR20>=AR21,0,1) -> 0 | BD21: 19222 | BE21: =(305/1185)*ELEC!Q20 -> 0 | BG21: =#REF!-BE21 -> #REF!
A22: =ELEC!C20 -> 44486 | B22: ='B5'!B21 -> 157 | C22: =B22*$B$4 -> 3378.0323 | D22: =SUM(B22) -> 157 | E22: =D22*$B$4 -> 3378.0323 | F22: =SUM(D22) -> 157 | G22: =F22*$B$4 -> 3378.0323 | H22: =SUM(F22) -> 157 | I22: =H22*$B$4 -> 3378.0323 | J22: =SUM(H22) -> 157 | K22: =J22*$B$4 -> 3378.0323 | L22: =SUM(J22) -> 157 | M22: =L22*$B$4 -> 3378.0323 | N22: =SUM(L22) -> 157 | O22: =N22*$B$4 -> 3378.0323 | P22: =SUM(N22) -> 157 | Q22: =P22*$B$4 -> 3378.0323 | R22: =SUM(P22) -> 157 | S22: =R22*$B$4 -> 3378.0323 | T22: =SUM(R22) -> 157 | U22: =T22*$B$4 -> 3378.0323 | V22: =SUM(T22) -> 157 | W22: =V22*$B$4 -> 3378.0323 | X22: =SUM(Y22/73370) -> 0.50645161 | Y22: =SUM(C22+E22+G22+I22+K22+M22+O22+Q22+S22+U22+W22) -> 37158.355 | Z22: ='B5'!C21 -> 164 | AA22: =SUM(Z22*$Z$4) -> 1640 | AB22: =SUM(Z22) -> 164 | AC22: =SUM(AB22*$Z$4) -> 1640 | AD22: =SUM(AB22) -> 164 | AE22: =SUM(AD22*$Z$4) -> 1640 | AF22: =SUM(AD22) -> 164 | AG22: =SUM(AF22*$Z$4) -> 1640 | AH22: =SUM(AF22) -> 164 | AI22: =SUM(AH22*$Z$4) -> 1640 | AJ22: =SUM(AH22) -> 164 | AK22: =SUM(AJ22*$Z$4) -> 1640 | AL22: =SUM(AJ22) -> 164 | AM22: =SUM(AL22*$Z$4) -> 1640 | AN22: =SUM(AO22/19600) -> 0.58571429 | AO22: =SUM(AA22+AC22+AE22+AG22+AI22+AK22+AM22) -> 11480 | AQ22: =SUM(AR22/92970) -> 0.52316182 | AR22: =Y22+AO22 -> 48638.355 | AS22: =SUM(AR22-AR21-AT22) -> 0 | AV22: =IF(AT22>0,AU22,AV21) -> 0.615 | AW22: =-SUM('B5'!AI21) -> 0 | AX22: =-SUM(AW22-AS22) -> 0 | AY22: =SUM(AX22+AW22) -> 0 | AZ22: =ELEC!A20 -> 0 | BA22: ='General information '!D21 -> 0 | BB22: =SUM('General information '!E21) -> 0 | BC22: =IF(AR21>=AR22,0,1) -> 0 | BD22: 19222 | BE22: =(305/1185)*ELEC!Q21 -> 0 | BG22: =#REF!-BE22 -> #REF!
A23: =ELEC!C21 -> 44487 | B23: ='B5'!B22 -> 157 | C23: =B23*$B$4 -> 3378.0323 | D23: =SUM(B23) -> 157 | E23: =D23*$B$4 -> 3378.0323 | F23: =SUM(D23) -> 157 | G23: =F23*$B$4 -> 3378.0323 | H23: =SUM(F23) -> 157 | I23: =H23*$B$4 -> 3378.0323 | J23: =SUM(H23) -> 157 | K23: =J23*$B$4 -> 3378.0323 | L23: =SUM(J23) -> 157 | M23: =L23*$B$4 -> 3378.0323 | N23: =SUM(L23) -> 157 | O23: =N23*$B$4 -> 3378.0323 | P23: =SUM(N23) -> 157 | Q23: =P23*$B$4 -> 3378.0323 | R23: =SUM(P23) -> 157 | S23: =R23*$B$4 -> 3378.0323 | T23: =SUM(R23) -> 157 | U23: =T23*$B$4 -> 3378.0323 | V23: =SUM(T23) -> 157 | W23: =V23*$B$4 -> 3378.0323 | X23: =SUM(Y23/73370) -> 0.50645161 | Y23: =SUM(C23+E23+G23+I23+K23+M23+O23+Q23+S23+U23+W23) -> 37158.355 | Z23: ='B5'!C22 -> 164 | AA23: =SUM(Z23*$Z$4) -> 1640 | AB23: =SUM(Z23) -> 164 | AC23: =SUM(AB23*$Z$4) -> 1640 | AD23: =SUM(AB23) -> 164 | AE23: =SUM(AD23*$Z$4) -> 1640 | AF23: =SUM(AD23) -> 164 | AG23: =SUM(AF23*$Z$4) -> 1640 | AH23: =SUM(AF23) -> 164 | AI23: =SUM(AH23*$Z$4) -> 1640 | AJ23: =SUM(AH23) -> 164 | AK23: =SUM(AJ23*$Z$4) -> 1640 | AL23: =SUM(AJ23) -> 164 | AM23: =SUM(AL23*$Z$4) -> 1640 | AN23: =SUM(AO23/19600) -> 0.58571429 | AO23: =SUM(AA23+AC23+AE23+AG23+AI23+AK23+AM23) -> 11480 | AQ23: =SUM(AR23/92970) -> 0.52316182 | AR23: =Y23+AO23 -> 48638.355 | AS23: =SUM(AR23-AR22-AT23) -> 0 | AV23: =IF(AT23>0,AU23,AV22) -> 0.615 | AW23: =-SUM('B5'!AI22) -> 0 | AX23: =-SUM(AW23-AS23) -> 0 | AY23: =SUM(AX23+AW23) -> 0 | AZ23: =ELEC!A21 -> 0 | BA23: ='General information '!D22 -> 0 | BB23: =SUM('General information '!E22) -> 0 | BC23: =IF(AR22>=AR23,0,1) -> 0 | BD23: 19222 | BE23: =(305/1185)*ELEC!Q22 -> 0 | BG23: =#REF!-BE23 -> #REF!
A24: =ELEC!C22 -> 44488 | B24: ='B5'!B23 -> 157 | C24: =B24*$B$4 -> 3378.0323 | D24: =SUM(B24) -> 157 | E24: =D24*$B$4 -> 3378.0323 | F24: =SUM(D24) -> 157 | G24: =F24*$B$4 -> 3378.0323 | H24: =SUM(F24) -> 157 | I24: =H24*$B$4 -> 3378.0323 | J24: =SUM(H24) -> 157 | K24: =J24*$B$4 -> 3378.0323 | L24: =SUM(J24) -> 157 | M24: =L24*$B$4 -> 3378.0323 | N24: =SUM(L24) -> 157 | O24: =N24*$B$4 -> 3378.0323 | P24: =SUM(N24) -> 157 | Q24: =P24*$B$4 -> 3378.0323 | R24: =SUM(P24) -> 157 | S24: =R24*$B$4 -> 3378.0323 | T24: =SUM(R24) -> 157 | U24: =T24*$B$4 -> 3378.0323 | V24: =SUM(T24) -> 157 | W24: =V24*$B$4 -> 3378.0323 | X24: =SUM(Y24/73370) -> 0.50645161 | Y24: =SUM(C24+E24+G24+I24+K24+M24+O24+Q24+S24+U24+W24) -> 37158.355 | Z24: ='B5'!C23 -> 164 | AA24: =SUM(Z24*$Z$4) -> 1640 | AB24: =SUM(Z24) -> 164 | AC24: =SUM(AB24*$Z$4) -> 1640 | AD24: =SUM(AB24) -> 164 | AE24: =SUM(AD24*$Z$4) -> 1640 | AF24: =SUM(AD24) -> 164 | AG24: =SUM(AF24*$Z$4) -> 1640 | AH24: =SUM(AF24) -> 164 | AI24: =SUM(AH24*$Z$4) -> 1640 | AJ24: =SUM(AH24) -> 164 | AK24: =SUM(AJ24*$Z$4) -> 1640 | AL24: =SUM(AJ24) -> 164 | AM24: =SUM(AL24*$Z$4) -> 1640 | AN24: =SUM(AO24/19600) -> 0.58571429 | AO24: =SUM(AA24+AC24+AE24+AG24+AI24+AK24+AM24) -> 11480 | AQ24: =SUM(AR24/92970) -> 0.52316182 | AR24: =Y24+AO24 -> 48638.355 | AS24: =SUM(AR24-AR23-AT24) -> 0 | AV24: =IF(AT24>0,AU24,AV23) -> 0.615 | AW24: =-SUM('B5'!AI23) -> 0 | AX24: =-SUM(AW24-AS24) -> 0 | AY24: =SUM(AX24+AW24) -> 0 | AZ24: =ELEC!A22 -> 0 | BA24: ='General information '!D23 -> 0 | BB24: =SUM('General information '!E23) -> 0 | BC24: =IF(AR23>=AR24,0,1) -> 0 | BD24: 19222 | BE24: =(305/1185)*ELEC!Q23 -> 0 | BG24: =#REF!-BE24 -> #REF!
A25: =ELEC!C23 -> 44489 | B25: ='B5'!B24 -> 157 | C25: =B25*$B$4 -> 3378.0323 | D25: =SUM(B25) -> 157 | E25: =D25*$B$4 -> 3378.0323 | F25: =SUM(D25) -> 157 | G25: =F25*$B$4 -> 3378.0323 | H25: =SUM(F25) -> 157 | I25: =H25*$B$4 -> 3378.0323 | J25: =SUM(H25) -> 157 | K25: =J25*$B$4 -> 3378.0323 | L25: =SUM(J25) -> 157 | M25: =L25*$B$4 -> 3378.0323 | N25: =SUM(L25) -> 157 | O25: =N25*$B$4 -> 3378.0323 | P25: =SUM(N25) -> 157 | Q25: =P25*$B$4 -> 3378.0323 | R25: =SUM(P25) -> 157 | S25: =R25*$B$4 -> 3378.0323 | T25: =SUM(R25) -> 157 | U25: =T25*$B$4 -> 3378.0323 | V25: =SUM(T25) -> 157 | W25: =V25*$B$4 -> 3378.0323 | X25: =SUM(Y25/73370) -> 0.50645161 | Y25: =SUM(C25+E25+G25+I25+K25+M25+O25+Q25+S25+U25+W25) -> 37158.355 | Z25: ='B5'!C24 -> 164 | AA25: =SUM(Z25*$Z$4) -> 1640 | AB25: =SUM(Z25) -> 164 | AC25: =SUM(AB25*$Z$4) -> 1640 | AD25: =SUM(AB25) -> 164 | AE25: =SUM(AD25*$Z$4) -> 1640 | AF25: =SUM(AD25) -> 164 | AG25: =SUM(AF25*$Z$4) -> 1640 | AH25: =SUM(AF25) -> 164 | AI25: =SUM(AH25*$Z$4) -> 1640 | AJ25: =SUM(AH25) -> 164 | AK25: =SUM(AJ25*$Z$4) -> 1640 | AL25: =SUM(AJ25) -> 164 | AM25: =SUM(AL25*$Z$4) -> 1640 | AN25: =SUM(AO25/19600) -> 0.58571429 | AO25: =SUM(AA25+AC25+AE25+AG25+AI25+AK25+AM25) -> 11480 | AQ25: =SUM(AR25/92970) -> 0.52316182 | AR25: =Y25+AO25 -> 48638.355 | AS25: =SUM(AR25-AR24-AT25) -> 0 | AV25: =IF(AT25>0,AU25,AV24) -> 0.615 | AW25: =-SUM('B5'!AI24) -> 0 | AX25: =-SUM(AW25-AS25) -> 0 | AY25: =SUM(AX25+AW25) -> 0 | AZ25: =ELEC!A23 -> 0 | BA25: ='General information '!D24 -> 0 | BB25: =SUM('General information '!E24) -> 0 | BC25: =IF(AR24>=AR25,0,1) -> 0 | BD25: 19222 | BE25: =(305/1185)*ELEC!Q24 -> 0 | BG25: =#REF!-BE25 -> #REF!
A26: =ELEC!C24 -> 44490 | B26: ='B5'!B25 -> 157 | C26: =B26*$B$4 -> 3378.0323 | D26: =SUM(B26) -> 157 | E26: =D26*$B$4 -> 3378.0323 | F26: =SUM(D26) -> 157 | G26: =F26*$B$4 -> 3378.0323 | H26: =SUM(F26) -> 157 | I26: =H26*$B$4 -> 3378.0323 | J26: =SUM(H26) -> 157 | K26: =J26*$B$4 -> 3378.0323 | L26: =SUM(J26) -> 157 | M26: =L26*$B$4 -> 3378.0323 | N26: =SUM(L26) -> 157 | O26: =N26*$B$4 -> 3378.0323 | P26: =SUM(N26) -> 157 | Q26: =P26*$B$4 -> 3378.0323 | R26: =SUM(P26) -> 157 | S26: =R26*$B$4 -> 3378.0323 | T26: =SUM(R26) -> 157 | U26: =T26*$B$4 -> 3378.0323 | V26: =SUM(T26) -> 157 | W26: =V26*$B$4 -> 3378.0323 | X26: =SUM(Y26/73370) -> 0.50645161 | Y26: =SUM(C26+E26+G26+I26+K26+M26+O26+Q26+S26+U26+W26) -> 37158.355 | Z26: ='B5'!C25 -> 164 | AA26: =SUM(Z26*$Z$4) -> 1640 | AB26: =SUM(Z26) -> 164 | AC26: =SUM(AB26*$Z$4) -> 1640 | AD26: =SUM(AB26) -> 164 | AE26: =SUM(AD26*$Z$4) -> 1640 | AF26: =SUM(AD26) -> 164 | AG26: =SUM(AF26*$Z$4) -> 1640 | AH26: =SUM(AF26) -> 164 | AI26: =SUM(AH26*$Z$4) -> 1640 | AJ26: =SUM(AH26) -> 164 | AK26: =SUM(AJ26*$Z$4) -> 1640 | AL26: =SUM(AJ26) -> 164 | AM26: =SUM(AL26*$Z$4) -> 1640 | AN26: =SUM(AO26/19600) -> 0.58571429 | AO26: =SUM(AA26+AC26+AE26+AG26+AI26+AK26+AM26) -> 11480 | AQ26: =SUM(AR26/92970) -> 0.52316182 | AR26: =Y26+AO26 -> 48638.355 | AS26: =SUM(AR26-AR25-AT26) -> 0 | AV26: =IF(AT26>0,AU26,AV25) -> 0.615 | AW26: =-SUM('B5'!AI25) -> 0 | AX26: =-SUM(AW26-AS26) -> 0 | AY26: =SUM(AX26+AW26) -> 0 | AZ26: =ELEC!A24 -> 0 | BA26: ='General information '!D25 -> 0 | BB26: =SUM('General information '!E25) -> 0 | BC26: =IF(AR25>=AR26,0,1) -> 0 | BD26: 19222 | BE26: =(305/1185)*ELEC!Q25 -> 0 | BG26: =#REF!-BE26 -> #REF!
A27: =ELEC!C25 -> 44491 | B27: ='B5'!B26 -> 157 | C27: =B27*$B$4 -> 3378.0323 | D27: =SUM(B27) -> 157 | E27: =D27*$B$4 -> 3378.0323 | F27: =SUM(D27) -> 157 | G27: =F27*$B$4 -> 3378.0323 | H27: =SUM(F27) -> 157 | I27: =H27*$B$4 -> 3378.0323 | J27: =SUM(H27) -> 157 | K27: =J27*$B$4 -> 3378.0323 | L27: =SUM(J27) -> 157 | M27: =L27*$B$4 -> 3378.0323 | N27: =SUM(L27) -> 157 | O27: =N27*$B$4 -> 3378.0323 | P27: =SUM(N27) -> 157 | Q27: =P27*$B$4 -> 3378.0323 | R27: =SUM(P27) -> 157 | S27: =R27*$B$4 -> 3378.0323 | T27: =SUM(R27) -> 157 | U27: =T27*$B$4 -> 3378.0323 | V27: =SUM(T27) -> 157 | W27: =V27*$B$4 -> 3378.0323 | X27: =SUM(Y27/73370) -> 0.50645161 | Y27: =SUM(C27+E27+G27+I27+K27+M27+O27+Q27+S27+U27+W27) -> 37158.355 | Z27: ='B5'!C26 -> 164 | AA27: =SUM(Z27*$Z$4) -> 1640 | AB27: =SUM(Z27) -> 164 | AC27: =SUM(AB27*$Z$4) -> 1640 | AD27: =SUM(AB27) -> 164 | AE27: =SUM(AD27*$Z$4) -> 1640 | AF27: =SUM(AD27) -> 164 | AG27: =SUM(AF27*$Z$4) -> 1640 | AH27: =SUM(AF27) -> 164 | AI27: =SUM(AH27*$Z$4) -> 1640 | AJ27: =SUM(AH27) -> 164 | AK27: =SUM(AJ27*$Z$4) -> 1640 | AL27: =SUM(AJ27) -> 164 | AM27: =SUM(AL27*$Z$4) -> 1640 | AN27: =SUM(AO27/19600) -> 0.58571429 | AO27: =SUM(AA27+AC27+AE27+AG27+AI27+AK27+AM27) -> 11480 | AQ27: =SUM(AR27/92970) -> 0.52316182 | AR27: =Y27+AO27 -> 48638.355 | AS27: =SUM(AR27-AR26-AT27) -> 0 | AV27: =IF(AT27>0,AU27,AV26) -> 0.615 | AW27: =-SUM('B5'!AI26) -> 0 | AX27: =-SUM(AW27-AS27) -> 0 | AY27: =SUM(AX27+AW27) -> 0 | AZ27: =ELEC!A25 -> 0 | BA27: ='General information '!D26 -> 0 | BB27: =SUM('General information '!E26) -> 0 | BC27: =IF(AR26>=AR27,0,1) -> 0 | BD27: 19222 | BE27: =(305/1185)*ELEC!Q26 -> 0 | BG27: =#REF!-BE27 -> #REF!
A28: =ELEC!C26 -> 44492 | B28: ='B5'!B27 -> 157 | C28: =B28*$B$4 -> 3378.0323 | D28: =SUM(B28) -> 157 | E28: =D28*$B$4 -> 3378.0323 | F28: =SUM(D28) -> 157 | G28: =F28*$B$4 -> 3378.0323 | H28: =SUM(F28) -> 157 | I28: =H28*$B$4 -> 3378.0323 | J28: =SUM(H28) -> 157 | K28: =J28*$B$4 -> 3378.0323 | L28: =SUM(J28) -> 157 | M28: =L28*$B$4 -> 3378.0323 | N28: =SUM(L28) -> 157 | O28: =N28*$B$4 -> 3378.0323 | P28: =SUM(N28) -> 157 | Q28: =P28*$B$4 -> 3378.0323 | R28: =SUM(P28) -> 157 | S28: =R28*$B$4 -> 3378.0323 | T28: =SUM(R28) -> 157 | U28: =T28*$B$4 -> 3378.0323 | V28: =SUM(T28) -> 157 | W28: =V28*$B$4 -> 3378.0323 | X28: =SUM(Y28/73370) -> 0.50645161 | Y28: =SUM(C28+E28+G28+I28+K28+M28+O28+Q28+S28+U28+W28) -> 37158.355 | Z28: ='B5'!C27 -> 164 | AA28: =SUM(Z28*$Z$4) -> 1640 | AB28: =SUM(Z28) -> 164 | AC28: =SUM(AB28*$Z$4) -> 1640 | AD28: =SUM(AB28) -> 164 | AE28: =SUM(AD28*$Z$4) -> 1640 | AF28: =SUM(AD28) -> 164 | AG28: =SUM(AF28*$Z$4) -> 1640 | AH28: =SUM(AF28) -> 164 | AI28: =SUM(AH28*$Z$4) -> 1640 | AJ28: =SUM(AH28) -> 164 | AK28: =SUM(AJ28*$Z$4) -> 1640 | AL28: =SUM(AJ28) -> 164 | AM28: =SUM(AL28*$Z$4) -> 1640 | AN28: =SUM(AO28/19600) -> 0.58571429 | AO28: =SUM(AA28+AC28+AE28+AG28+AI28+AK28+AM28) -> 11480 | AQ28: =SUM(AR28/92970) -> 0.52316182 | AR28: =Y28+AO28 -> 48638.355 | AS28: =SUM(AR28-AR27-AT28) -> 0 | AV28: =IF(AT28>0,AU28,AV27) -> 0.615 | AW28: =-SUM('B5'!AI27) -> 0 | AX28: =-SUM(AW28-AS28) -> 0 | AY28: =SUM(AX28+AW28) -> 0 | AZ28: =ELEC!A26 -> 0 | BA28: ='General information '!D27 -> 0 | BB28: =SUM('General information '!E27) -> 0 | BC28: =IF(AR27>=AR28,0,1) -> 0 | BD28: 19222 | BE28: =(305/1185)*ELEC!Q27 -> 0 | BG28: =#REF!-BE28 -> #REF!
... A32: =ELEC!C30 -> 44496 | B32: ='B5'!B31 -> 157 | C32: =B32*$B$4 -> 3378.0323 | D32: =SUM(B32) -> 157 | E32: =D32*$B$4 -> 3378.0323 | F32: =SUM(D32) -> 157 | G32: =F32*$B$4 -> 3378.0323 | H32: =SUM(F32) -> 157 | I32: =H32*$B$4 -> 3378.0323 | J32: =SUM(H32) -> 157 | K32: =J32*$B$4 -> 3378.0323 | L32: =SUM(J32) -> 157 | M32: =L32*$B$4 -> 3378.0323 | N32: =SUM(L32) -> 157 | O32: =N32*$B$4 -> 3378.0323 | P32: =SUM(N32) -> 157 | Q32: =P32*$B$4 -> 3378.0323 | R32: =SUM(P32) -> 157 | S32: =R32*$B$4 -> 3378.0323 | T32: =SUM(R32) -> 157 | U32: =T32*$B$4 -> 3378.0323 | V32: =SUM(T32) -> 157 | W32: =V32*$B$4 -> 3378.0323 | X32: =SUM(Y32/73370) -> 0.50645161 | Y32: =SUM(C32+E32+G32+I32+K32+M32+O32+Q32+S32+U32+W32) -> 37158.355 | Z32: ='B5'!C31 -> 164 | AA32: =SUM(Z32*$Z$4) -> 1640 | AB32: =SUM(Z32) -> 164 | AC32: =SUM(AB32*$Z$4) -> 1640 | AD32: =SUM(AB32) -> 164 | AE32: =SUM(AD32*$Z$4) -> 1640 | AF32: =SUM(AD32) -> 164 | AG32: =SUM(AF32*$Z$4) -> 1640 | AH32: =SUM(AF32) -> 164 | AI32: =SUM(AH32*$Z$4) -> 1640 | AJ32: =SUM(AH32) -> 164 | AK32: =SUM(AJ32*$Z$4) -> 1640 | AL32: =SUM(AJ32) -> 164 | AM32: =SUM(AL32*$Z$4) -> 1640 | AN32: =SUM(AO32/19600) -> 0.58571429 | AO32: =SUM(AA32+AC32+AE32+AG32+AI32+AK32+AM32) -> 11480 | AQ32: =SUM(AR32/92970) -> 0.52316182 | AR32: =Y32+AO32 -> 48638.355 | AS32: =SUM(AR32-AR31-AT32) -> 0 | AV32: =IF(AT32>0,AU32,AV31) -> 0.615 | AW32: =-SUM('B5'!AI31) -> 0 | AX32: =-SUM(AW32-AS32) -> 0 | AY32: =SUM(AX32+AW32) -> 0 | AZ32: =ELEC!A30 -> 0 | BA32: ='General information '!D31 -> 0 | BB32: =SUM('General information '!E31) -> 0 | BC32: =IF(AR31>=AR32,0,1) -> 0 | BD32: 19222 | BE32: =(305/1185)*ELEC!Q31 -> 0 | BG32: =#REF!-BE32 -> #REF!
A33: =ELEC!C31 -> 44497 | B33: ='B5'!B32 -> 157 | C33: =B33*$B$4 -> 3378.0323 | D33: =SUM(B33) -> 157 | E33: =D33*$B$4 -> 3378.0323 | F33: =SUM(D33) -> 157 | G33: =F33*$B$4 -> 3378.0323 | H33: =SUM(F33) -> 157 | I33: =H33*$B$4 -> 3378.0323 | J33: =SUM(H33) -> 157 | K33: =J33*$B$4 -> 3378.0323 | L33: =SUM(J33) -> 157 | M33: =L33*$B$4 -> 3378.0323 | N33: =SUM(L33) -> 157 | O33: =N33*$B$4 -> 3378.0323 | P33: =SUM(N33) -> 157 | Q33: =P33*$B$4 -> 3378.0323 | R33: =SUM(P33) -> 157 | S33: =R33*$B$4 -> 3378.0323 | T33: =SUM(R33) -> 157 | U33: =T33*$B$4 -> 3378.0323 | V33: =SUM(T33) -> 157 | W33: =V33*$B$4 -> 3378.0323 | X33: =SUM(Y33/73370) -> 0.50645161 | Y33: =SUM(C33+E33+G33+I33+K33+M33+O33+Q33+S33+U33+W33) -> 37158.355 | Z33: ='B5'!C32 -> 164 | AA33: =SUM(Z33*$Z$4) -> 1640 | AB33: =SUM(Z33) -> 164 | AC33: =SUM(AB33*$Z$4) -> 1640 | AD33: =SUM(AB33) -> 164 | AE33: =SUM(AD33*$Z$4) -> 1640 | AF33: =SUM(AD33) -> 164 | AG33: =SUM(AF33*$Z$4) -> 1640 | AH33: =SUM(AF33) -> 164 | AI33: =SUM(AH33*$Z$4) -> 1640 | AJ33: =SUM(AH33) -> 164 | AK33: =SUM(AJ33*$Z$4) -> 1640 | AL33: =SUM(AJ33) -> 164 | AM33: =SUM(AL33*$Z$4) -> 1640 | AN33: =SUM(AO33/19600) -> 0.58571429 | AO33: =SUM(AA33+AC33+AE33+AG33+AI33+AK33+AM33) -> 11480 | AQ33: =SUM(AR33/92970) -> 0.52316182 | AR33: =Y33+AO33 -> 48638.355 | AS33: =SUM(AR33-AR32-AT33) -> 0 | AV33: =IF(AT33>0,AU33,AV32) -> 0.615 | AW33: =-SUM('B5'!AI32) -> 0 | AX33: =-SUM(AW33-AS33) -> 0 | AY33: =SUM(AX33+AW33) -> 0 | AZ33: =ELEC!A31 -> 0 | BA33: ='General information '!D32 -> 0 | BB33: =SUM('General information '!E32) -> 0 | BC33: =IF(AR32>=AR33,0,1) -> 0 | BD33: 19222 | BE33: =(305/1185)*ELEC!#REF! -> #REF! | BG33: =#REF!-BE33 -> #REF!
A34: =ELEC!C32 -> 44498 | B34: ='B5'!B33 -> 157 | C34: =B34*$B$4 -> 3378.0323 | D34: =SUM(B34) -> 157 | E34: =D34*$B$4 -> 3378.0323 | F34: =SUM(D34) -> 157 | G34: =F34*$B$4 -> 3378.0323 | H34: =SUM(F34) -> 157 | I34: =H34*$B$4 -> 3378.0323 | J34: =SUM(H34) -> 157 | K34: =J34*$B$4 -> 3378.0323 | L34: =SUM(J34) -> 157 | M34: =L34*$B$4 -> 3378.0323 | N34: =SUM(L34) -> 157 | O34: =N34*$B$4 -> 3378.0323 | P34: =SUM(N34) -> 157 | Q34: =P34*$B$4 -> 3378.0323 | R34: =SUM(P34) -> 157 | S34: =R34*$B$4 -> 3378.0323 | T34: =SUM(R34) -> 157 | U34: =T34*$B$4 -> 3378.0323 | V34: =SUM(T34) -> 157 | W34: =V34*$B$4 -> 3378.0323 | X34: =SUM(Y34/73370) -> 0.50645161 | Y34: =SUM(C34+E34+G34+I34+K34+M34+O34+Q34+S34+U34+W34) -> 37158.355 | Z34: ='B5'!C33 -> 164 | AA34: =SUM(Z34*$Z$4) -> 1640 | AB34: =SUM(Z34) -> 164 | AC34: =SUM(AB34*$Z$4) -> 1640 | AD34: =SUM(AB34) -> 164 | AE34: =SUM(AD34*$Z$4) -> 1640 | AF34: =SUM(AD34) -> 164 | AG34: =SUM(AF34*$Z$4) -> 1640 | AH34: =SUM(AF34) -> 164 | AI34: =SUM(AH34*$Z$4) -> 1640 | AJ34: =SUM(AH34) -> 164 | AK34: =SUM(AJ34*$Z$4) -> 1640 | AL34: =SUM(AJ34) -> 164 | AM34: =SUM(AL34*$Z$4) -> 1640 | AN34: =SUM(AO34/19600) -> 0.58571429 | AO34: =SUM(AA34+AC34+AE34+AG34+AI34+AK34+AM34) -> 11480 | AQ34: =SUM(AR34/92970) -> 0.52316182 | AR34: =Y34+AO34 -> 48638.355 | AS34: =SUM(AR34-AR33-AT34) -> 0 | AV34: =IF(AT34>0,AU34,AV33) -> 0.615 | AW34: =-SUM('B5'!AI33) -> 0 | AX34: =-SUM(AW34-AS34) -> 0 | AY34: =SUM(AX34+AW34) -> 0 | AZ34: =ELEC!A32 -> 0 | BA34: ='General information '!D33 -> 0 | BB34: =SUM('General information '!E33) -> 0
A35: =ELEC!C33 -> 44499 | B35: ='B5'!B34 -> 157 | C35: =B35*$B$4 -> 3378.0323 | D35: =SUM(B35) -> 157 | E35: =D35*$B$4 -> 3378.0323 | F35: =SUM(D35) -> 157 | G35: =F35*$B$4 -> 3378.0323 | H35: =SUM(F35) -> 157 | I35: =H35*$B$4 -> 3378.0323 | J35: =SUM(H35) -> 157 | K35: =J35*$B$4 -> 3378.0323 | L35: =SUM(J35) -> 157 | M35: =L35*$B$4 -> 3378.0323 | N35: =SUM(L35) -> 157 | O35: =N35*$B$4 -> 3378.0323 | P35: =SUM(N35) -> 157 | Q35: =P35*$B$4 -> 3378.0323 | R35: =SUM(P35) -> 157 | S35: =R35*$B$4 -> 3378.0323 | T35: =SUM(R35) -> 157 | U35: =T35*$B$4 -> 3378.0323 | V35: =SUM(T35) -> 157 | W35: =V35*$B$4 -> 3378.0323 | X35: =SUM(Y35/73370) -> 0.50645161 | Y35: =SUM(C35+E35+G35+I35+K35+M35+O35+Q35+S35+U35+W35) -> 37158.355 | Z35: ='B5'!C34 -> 164 | AA35: =SUM(Z35*$Z$4) -> 1640 | AB35: =SUM(Z35) -> 164 | AC35: =SUM(AB35*$Z$4) -> 1640 | AD35: =SUM(AB35) -> 164 | AE35: =SUM(AD35*$Z$4) -> 1640 | AF35: =SUM(AD35) -> 164 | AG35: =SUM(AF35*$Z$4) -> 1640 | AH35: =SUM(AF35) -> 164 | AI35: =SUM(AH35*$Z$4) -> 1640 | AJ35: =SUM(AH35) -> 164 | AK35: =SUM(AJ35*$Z$4) -> 1640 | AL35: =SUM(AJ35) -> 164 | AM35: =SUM(AL35*$Z$4) -> 1640 | AN35: =SUM(AO35/19600) -> 0.58571429 | AO35: =SUM(AA35+AC35+AE35+AG35+AI35+AK35+AM35) -> 11480 | AQ35: =SUM(AR35/92970) -> 0.52316182 | AR35: =Y35+AO35 -> 48638.355 | AS35: =SUM(AR35-AR34-AT35) -> 0 | AV35: =IF(AT35>0,AU35,AV34) -> 0.615 | AW35: =-SUM('B5'!AI34) -> 0 | AX35: =-SUM(AW35-AS35) -> 0 | AY35: =SUM(AX35+AW35) -> 0 | AZ35: =ELEC!A33 -> 0 | BA35: ='General information '!D34 -> 0 | BB35: =SUM('General information '!E34) -> 0
