Workbook

Sheet Total
A1: Site Name | B1: Day | C1: Month | D1: Year | E1: Total Electricity Kwh | F1: Electricity Tariff ($/Kwh) | G1: Total Fuel Oil (Liter) | H1: Fuel Oil $/Liter | I1: LPG (Kg) | J1: LPG $/Kg | K1: Water Utility Supply (m3) m3 | L1: Water Utility Supply (m3) $/m3 | M1: Irrigation Water (m3) m3 | N1: Irrigation water $/m3 | O1: Room Nights
A2: Beirut | B2: 1 | C2: 12 | D2: 2021 | E2: =ELEC!N4 -> 6332 | F2: =SUM('EDl log'!T4) -> 0.24813551 | G2: =-tanks!AW6 -> 0 | H2: =SUM(tanks!AV6) -> 0.71 | I2: =('B5'!AU5)*0.51 -> 0 | J2: ='B5'!AX5/0.51 -> 1.5686275 | K2: =WATER!I6 -> 0 | L2: =SUM(WATER!J6) -> 0 | M2: =WATER!Q6 -> 0 | N2: 0.6 | O2: =ELEC!B4 -> 0
A3: Beirut | B3: =B2+1 -> 2 | C3: 12 | D3: 2021 | E3: =ELEC!N5 -> 5540 | F3: =SUM('EDl log'!T5) -> 0.2390325 | G3: =-tanks!AW7 -> 0 | H3: =SUM(tanks!AV7) -> 0.71 | I3: =('B5'!AU6)*0.51 -> 0 | J3: ='B5'!AX6/0.51 -> 1.5686275 | K3: =WATER!I7 -> 160 | L3: =SUM(WATER!J7) -> 1.5120968 | M3: =WATER!Q7 -> 0 | N3: 0.6 | O3: =ELEC!B5 -> 0
A4: Beirut | B4: =B3+1 -> 3 | C4: 12 | D4: 2021 | E4: =ELEC!N6 -> 0 | F4: =SUM('EDl log'!T6) -> 0 | G4: =-tanks!AW8 -> 0 | H4: =SUM(tanks!AV8) -> 0.71 | I4: =('B5'!AU7)*0.51 -> 0 | J4: ='B5'!AX7/0.51 -> 1.5686275 | K4: =WATER!I8 -> 0 | L4: =SUM(WATER!J8) -> 0 | M4: =WATER!Q8 -> 0 | N4: 0.6 | O4: =ELEC!B6 -> 0
A5: Beirut | B5: =B4+1 -> 4 | C5: 12 | D5: 2021 | E5: =ELEC!N7 -> 0 | F5: =SUM('EDl log'!T7) -> 0 | G5: =-tanks!AW9 -> 0 | H5: =SUM(tanks!AV9) -> 0.71 | I5: =('B5'!AU8)*0.51 -> 0 | J5: ='B5'!AX8/0.51 -> 1.5686275 | K5: =WATER!I9 -> 0 | L5: =SUM(WATER!J9) -> 0 | M5: =WATER!Q9 -> 0 | N5: 0.6 | O5: =ELEC!B7 -> 0
A6: Beirut | B6: =B5+1 -> 5 | C6: 12 | D6: 2021 | E6: =ELEC!N8 -> 6729 | F6: =SUM('EDl log'!T8) -> 0.035135947 | G6: =-tanks!AW10 -> 193 | H6: =SUM(tanks!AV10) -> 0.634 | I6: =('B5'!AU9)*0.51 -> 0 | J6: ='B5'!AX9/0.51 -> 1.5686275 | K6: =WATER!I10 -> 0 | L6: =SUM(WATER!J10) -> 0 | M6: =WATER!Q10 -> 0 | N6: 0.6 | O6: =ELEC!B8 -> 0
A7: Beirut | B7: =B6+1 -> 6 | C7: 12 | D7: 2021 | E7: =ELEC!N9 -> 4979 | F7: =SUM('EDl log'!T9) -> 0.25551462 | G7: =-tanks!AW11 -> 110 | H7: =SUM(tanks!AV11) -> 0.634 | I7: =('B5'!AU10)*0.51 -> 0 | J7: ='B5'!AX10/0.51 -> 1.5686275 | K7: =WATER!I11 -> 0 | L7: =SUM(WATER!J11) -> 0 | M7: =WATER!Q11 -> 0 | N7: 0.6 | O7: =ELEC!B9 -> 0
A8: Beirut | B8: =B7+1 -> 7 | C8: 12 | D8: 2021 | E8: =ELEC!N10 -> 5333 | F8: =SUM('EDl log'!T10) -> 0.33870024 | G8: =-tanks!AW12 -> 119 | H8: =SUM(tanks!AV12) -> 0.634 | I8: =('B5'!AU11)*0.51 -> 0 | J8: ='B5'!AX11/0.51 -> 1.5686275 | K8: =WATER!I12 -> 0 | L8: =SUM(WATER!J12) -> 0 | M8: =WATER!Q12 -> 0 | N8: 0.6 | O8: =ELEC!B10 -> 0
A9: Beirut | B9: =B8+1 -> 8 | C9: 12 | D9: 2021 | E9: =ELEC!N11 -> 5724 | F9: =SUM('EDl log'!T11) -> 0.24599689 | G9: =-tanks!AW13 -> 0 | H9: =SUM(tanks!AV13) -> 0.634 | I9: =('B5'!AU12)*0.51 -> 0 | J9: ='B5'!AX12/0.51 -> 1.5686275 | K9: =WATER!I13 -> 0 | L9: =SUM(WATER!J13) -> 0 | M9: =WATER!Q13 -> 0 | N9: 0.6 | O9: =ELEC!B11 -> 0
A10: Beirut | B10: =B9+1 -> 9 | C10: 12 | D10: 2021 | E10: =ELEC!N12 -> 4995 | F10: =SUM('EDl log'!T12) -> 0.29572966 | G10: =-tanks!AW14 -> 0 | H10: =SUM(tanks!AV14) -> 0.634 | I10: =('B5'!AU13)*0.51 -> 0 | J10: ='B5'!AX13/0.51 -> 1.5686275 | K10: =WATER!I14 -> 170 | L10: =SUM(WATER!J14) -> 1.4231499 | M10: =WATER!Q14 -> 0 | N10: 0.6 | O10: =ELEC!B12 -> 0
A11: Beirut | B11: =B10+1 -> 10 | C11: 12 | D11: 2021 | E11: =ELEC!N13 -> 0 | F11: =SUM('EDl log'!T13) -> 0 | G11: =-tanks!AW15 -> 0 | H11: =SUM(tanks!AV15) -> 0.634 | I11: =('B5'!AU14)*0.51 -> 0 | J11: ='B5'!AX14/0.51 -> 1.5686275 | K11: =WATER!I15 -> 0 | L11: =SUM(WATER!J15) -> 0 | M11: =WATER!Q15 -> 0 | N11: 0.6 | O11: =ELEC!B13 -> 0
A12: Beirut | B12: =B11+1 -> 11 | C12: 12 | D12: 2021 | E12: =ELEC!N14 -> 0 | F12: =SUM('EDl log'!T14) -> 0 | G12: =-tanks!AW16 -> 0 | H12: =SUM(tanks!AV16) -> 0.634 | I12: =('B5'!AU15)*0.51 -> 0 | J12: ='B5'!AX15/0.51 -> 1.5686275 | K12: =WATER!I16 -> 0 | L12: =SUM(WATER!J16) -> 0 | M12: =WATER!Q16 -> 0 | N12: 0.6 | O12: =ELEC!B14 -> 0
A13: Beirut | B13: =B12+1 -> 12 | C13: 12 | D13: 2021 | E13: =ELEC!N15 -> 6833 | F13: =SUM('EDl log'!T15) -> 0.15574876 | G13: =-tanks!AW17 -> 118 | H13: =SUM(tanks!AV17) -> 0.634 | I13: =('B5'!AU16)*0.51 -> 0 | J13: ='B5'!AX16/0.51 -> 1.5686275 | K13: =WATER!I17 -> 2 | L13: =SUM(WATER!J17) -> 120.96774 | M13: =WATER!Q17 -> 0 | N13: 0.6 | O13: =ELEC!B15 -> 0
A14: Beirut | B14: =B13+1 -> 13 | C14: 12 | D14: 2021 | E14: =ELEC!N16 -> 5512.2 | F14: =SUM('EDl log'!T16) -> 0.23998005 | G14: =-tanks!AW18 -> 169 | H14: =SUM(tanks!AV18) -> 0.634 | I14: =('B5'!AU17)*0.51 -> 0 | J14: ='B5'!AX17/0.51 -> 1.5686275 | K14: =WATER!I18 -> 0 | L14: =SUM(WATER!J18) -> 0 | M14: =WATER!Q18 -> 0 | N14: 0.6 | O14: =ELEC!B16 -> 0
... A32: Beirut | B32: =B31+1 -> 31 | C32: 12 | D32: 2021 | E32: =ELEC!N34 -> 0 | F32: =SUM('EDl log'!T34) -> 0 | G32: =-tanks!AW36 -> 0 | H32: =SUM(tanks!AV36) -> 0.604 | I32: =('B5'!AU35)*0.51 -> 0 | J32: ='B5'!AX35/0.51 -> 1.5686275 | K32: =WATER!I36 -> 0 | L32: =SUM(WATER!J36) -> 0 | M32: =WATER!Q36 -> 0 | N32: 0.6 | O32: =ELEC!B34 -> 0

Sheet Submetering
A1: Site Name | B1: Day | C1: Month | D1: Year | E1: ATS1 Kwh | F1: ATS2 Kwh | G1: ATS3 Kwh | H1: ATS4 Kwh | I1: ATS5 Kwh | J1: Guest (m3) | K1: Kitchen & Laundry (m3) | L1: Room Nights
A2: Beirut | B2: 1 | C2: 12 | D2: 2021 | E2: =ELEC!M4 -> 1200 | F2: =ELEC!K4 -> 2064 | G2: =ELEC!I4 -> 576 | H2: =ELEC!E4 -> 2190 | I2: =ELEC!G4 -> 302 | J2: =WATER!Y6 -> 0 | K2: =WATER!AJ6 -> 0 | L2: =ELEC!B4 -> 0
A3: Beirut | B3: =B2+1 -> 2 | C3: 12 | D3: 2021 | E3: =ELEC!M5 -> 1092 | F3: =ELEC!K5 -> 1712 | G3: =ELEC!I5 -> 536 | H3: =ELEC!E5 -> 1922 | I3: =ELEC!G5 -> 278 | J3: =WATER!Y7 -> 0 | K3: =WATER!AJ7 -> 0 | L3: =ELEC!B5 -> 0
A4: Beirut | B4: =B3+1 -> 3 | C4: 12 | D4: 2021 | E4: =ELEC!M6 -> 0 | F4: =ELEC!K6 -> 0 | G4: =ELEC!I6 -> 0 | H4: =ELEC!E6 -> 0 | I4: =ELEC!G6 -> 0 | J4: =WATER!Y8 -> 0 | K4: =WATER!AJ8 -> 0 | L4: =ELEC!B6 -> 0
A5: Beirut | B5: =B4+1 -> 4 | C5: 12 | D5: 2021 | E5: =ELEC!M7 -> 0 | F5: =ELEC!K7 -> 0 | G5: =ELEC!I7 -> 0 | H5: =ELEC!E7 -> 0 | I5: =ELEC!G7 -> 0 | J5: =WATER!Y9 -> 0 | K5: =WATER!AJ9 -> 0 | L5: =ELEC!B7 -> 0
A6: Beirut | B6: =B5+1 -> 5 | C6: 12 | D6: 2021 | E6: =ELEC!M8 -> 1268 | F6: =ELEC!K8 -> 2160 | G6: =ELEC!I8 -> 620 | H6: =ELEC!E8 -> 2372 | I6: =ELEC!G8 -> 309 | J6: =WATER!Y10 -> 0 | K6: =WATER!AJ10 -> 0 | L6: =ELEC!B8 -> 0
A7: Beirut | B7: =B6+1 -> 6 | C7: 12 | D7: 2021 | E7: =ELEC!M9 -> 960 | F7: =ELEC!K9 -> 1500 | G7: =ELEC!I9 -> 452 | H7: =ELEC!E9 -> 1810 | I7: =ELEC!G9 -> 257 | J7: =WATER!Y11 -> 0 | K7: =WATER!AJ11 -> 0 | L7: =ELEC!B9 -> 0
A8: Beirut | B8: =B7+1 -> 7 | C8: 12 | D8: 2021 | E8: =ELEC!M10 -> 1022 | F8: =ELEC!K10 -> 1574 | G8: =ELEC!I10 -> 484 | H8: =ELEC!E10 -> 1991 | I8: =ELEC!G10 -> 262 | J8: =WATER!Y12 -> 0 | K8: =WATER!AJ12 -> 0 | L8: =ELEC!B10 -> 0
A9: Beirut | B9: =B8+1 -> 8 | C9: 12 | D9: 2021 | E9: =ELEC!M11 -> 970 | F9: =ELEC!K11 -> 1650 | G9: =ELEC!I11 -> 558 | H9: =ELEC!E11 -> 2244 | I9: =ELEC!G11 -> 302 | J9: =WATER!Y13 -> 0 | K9: =WATER!AJ13 -> 0 | L9: =ELEC!B11 -> 0
A10: Beirut | B10: =B9+1 -> 9 | C10: 12 | D10: 2021 | E10: =ELEC!M12 -> 916 | F10: =ELEC!K12 -> 1332 | G10: =ELEC!I12 -> 486 | H10: =ELEC!E12 -> 2009 | I10: =ELEC!G12 -> 252 | J10: =WATER!Y14 -> 146 | K10: =WATER!AJ14 -> 0 | L10: =ELEC!B12 -> 0
A11: Beirut | B11: =B10+1 -> 10 | C11: 12 | D11: 2021 | E11: =ELEC!M13 -> 0 | F11: =ELEC!K13 -> 0 | G11: =ELEC!I13 -> 0 | H11: =ELEC!E13 -> 0 | I11: =ELEC!G13 -> 0 | J11: =WATER!Y15 -> 0 | K11: =WATER!AJ15 -> 0 | L11: =ELEC!B13 -> 0
A12: Beirut | B12: =B11+1 -> 11 | C12: 12 | D12: 2021 | E12: =ELEC!M14 -> 0 | F12: =ELEC!K14 -> 0 | G12: =ELEC!I14 -> 0 | H12: =ELEC!E14 -> 0 | I12: =ELEC!G14 -> 0 | J12: =WATER!Y16 -> 0 | K12: =WATER!AJ16 -> 0 | L12: =ELEC!B14 -> 0
A13: Beirut | B13: =B12+1 -> 12 | C13: 12 | D13: 2021 | E13: =ELEC!M15 -> 1248 | F13: =ELEC!K15 -> 2454 | G13: =ELEC!I15 -> 596 | H13: =ELEC!E15 -> 2210 | I13: =ELEC!G15 -> 325 | J13: =WATER!Y17 -> 0 | K13: =WATER!AJ17 -> 0 | L13: =ELEC!B15 -> 0
A14: Beirut | B14: =B13+1 -> 13 | C14: 12 | D14: 2021 | E14: =ELEC!M16 -> 1040 | F14: =ELEC!K16 -> 1578 | G14: =ELEC!I16 -> 508 | H14: =ELEC!E16 -> 2104 | I14: =ELEC!G16 -> 282.2 | J14: =WATER!Y18 -> 0 | K14: =WATER!AJ18 -> 0 | L14: =ELEC!B16 -> 0
... A31: Beirut | B31: =B30+1 -> 30 | C31: 12 | D31: 2021 | E31: =ELEC!M33 -> 0 | F31: =ELEC!K33 -> 0 | G31: =ELEC!I33 -> 0 | H31: =ELEC!E33 -> 0 | I31: =ELEC!G33 -> 0 | J31: =WATER!Y35 -> 0 | K31: =WATER!AJ35 -> 0 | L31: =ELEC!B33 -> 0
A32: Beirut | B32: 31 | C32: 12 | D32: 2021 | E32: =ELEC!M34 -> 0 | F32: =ELEC!K34 -> 0 | G32: =ELEC!I34 -> 0 | H32: =ELEC!E34 -> 0 | I32: =ELEC!G34 -> 0 | J32: =WATER!Y36 -> 0 | K32: =WATER!AJ36 -> 0 | L32: =ELEC!B34 -> 0
D45: .

Sheet ELEC
A2: OOC | B2: Room OCC | D2: MDB3 | E2: MDB3/day | F2: EMDB2 | G2: EMDB2/day | H2: EMDB1 | I2: EMDB1/day | J2: MDB2 | K2: mdb2/day | L2: MDB1 | M2: MDB1/Day | N2: Total KWH | O2: KWH/Rooc | P2: Gen MHW | Q2: Gen/Day KWH | R2: EDL KWH | S2: CH1 RH | T2: RH | U2: C1h1 power | V2: CH1 Con KWH | W2: CH2 RH | X2: RH | Y2: Ch2 power | Z2: CH2 Con KWH | AA2: CH3 RH | AB2: RH | AC2: Ch3 power | AD2: CH3 Con KWH | AE2: RH total | AF2: KWH total | AG2: AVG chiller KW/Hr
A3: =[1]ELEC!$A$34 -> 0 | B3: =[1]ELEC!$B$34 -> 0 | C3: =[2]ELEC!$C$33 -> 44530 | D3: =[2]ELEC!D33 -> 69398 | E3: =[2]ELEC!E33 -> 2255 | F3: =[2]ELEC!F33 -> 4103940 | G3: =[2]ELEC!G33 -> 322 | H3: =[2]ELEC!H33 -> 17989982 | I3: =[2]ELEC!I33 -> 582 | J3: =[2]ELEC!J33 -> 29621430 | K3: =[2]ELEC!K33 -> 2298 | ... AG3: =[2]ELEC!AG33 -> 286.33333
A4: ='General information '!F5 -> 0 | B4: =SUM(230*A4) -> 0 | C4: 44531 | D4: 71588 | E4: =D4-D3 -> 2190 | F4: 4104242 | G4: =F4-F3 -> 302 | H4: 17990558 | I4: =H4-H3 -> 576 | J4: 29623494 | K4: =J4-J3 -> 2064 | L4: 24475190 | M4: =L4-L3 -> 1200 | N4: =M4+K4+I4+G4+E4 -> 6332 | O4: =IF(B4>0,N4/B4,0) -> 0 | P4: 18665.984 | Q4: =(P4-P3)*1000 -> 6199 | R4: =+N4-Q4 -> 133 | S4: =S3 -> 10175 | T4: =S4-S3 -> 0 | U4: =U3 -> 429166 | V4: =U4-U3 -> 0 | W4: 33460 | X4: =W4-W3 -> 3 | Y4: 991168 | Z4: =Y4-Y3 -> 661 | AA4: =AA3 -> 36796 | AB4: =AA4-AA3 -> 0 | AC4: =AC3 -> 1170505 | AD4: =AC4-AC3 -> 0 | AE4: =AB4+X4+T4 -> 3 | AF4: =V4+Z4+AD4 -> 661 | AG4: =IF(AE4>0,AF4/AE4,0) -> 220.33333
A5: ='General information '!F6 -> 0 | B5: =SUM(230*A5) -> 0 | C5: 44532 | D5: 73510 | E5: =D5-D4 -> 1922 | F5: 4104520 | G5: =F5-F4 -> 278 | H5: 17991094 | I5: =H5-H4 -> 536 | J5: 29625206 | K5: =J5-J4 -> 1712 | L5: 24476282 | M5: =L5-L4 -> 1092 | N5: =M5+K5+I5+G5+E5 -> 5540 | O5: =IF(B5>0,N5/B5,0) -> 0 | P5: 18671.347 | Q5: =(P5-P4)*1000 -> 5363 | R5: =N5-Q5 -> 177 | S5: =S4 -> 10175 | T5: =S5-S4 -> 0 | U5: =U4 -> 429166 | V5: =U5-U4 -> 0 | W5: 33463 | X5: =W5-W4 -> 3 | Y5: 991838 | Z5: =Y5-Y4 -> 670 | AA5: 36796 | AB5: =AA5-AA4 -> 0 | AC5: =AC4 -> 1170505 | AD5: =AC5-AC4 -> 0 | AE5: =AB5+X5+T5 -> 3 | AF5: =V5+Z5+AD5 -> 670 | AG5: =IF(AE5>0,AF5/AE5,0) -> 223.33333
A6: ='General information '!F7 -> 0 | B6: =SUM(230*A6) -> 0 | C6: 44533 | D6: =D5 -> 73510 | E6: =D6-D5 -> 0 | F6: =F5 -> 4104520 | G6: =F6-F5 -> 0 | H6: =H5 -> 17991094 | I6: =H6-H5 -> 0 | J6: =J5 -> 29625206 | K6: =J6-J5 -> 0 | L6: =L5 -> 24476282 | M6: =L6-L5 -> 0 | N6: =M6+K6+I6+G6+E6 -> 0 | O6: =IF(B6>0,N6/B6,0) -> 0 | P6: =P5 -> 18671.347 | Q6: =(P6-P5)*1000 -> 0 | R6: =N6-Q6 -> 0 | S6: =S5 -> 10175 | T6: =S6-S5 -> 0 | U6: =U5 -> 429166 | V6: =U6-U5 -> 0 | W6: =W5 -> 33463 | X6: =W6-W5 -> 0 | Y6: =Y5 -> 991838 | Z6: =Y6-Y5 -> 0 | AA6: =AA5 -> 36796 | AB6: =AA6-AA5 -> 0 | AC6: =AC5 -> 1170505 | AD6: =AC6-AC5 -> 0 | AE6: =AB6+X6+T6 -> 0 | AF6: =V6+Z6+AD6 -> 0 | AG6: =IF(AE6>0,AF6/AE6,0) -> 0
A7: ='General information '!F8 -> 0 | B7: =SUM(230*A7) -> 0 | C7: 44534 | D7: =D6 -> 73510 | E7: =D7-D6 -> 0 | F7: =F6 -> 4104520 | G7: =F7-F6 -> 0 | H7: =H6 -> 17991094 | I7: =H7-H6 -> 0 | J7: =J6 -> 29625206 | K7: =J7-J6 -> 0 | L7: =L6 -> 24476282 | M7: =L7-L6 -> 0 | N7: =M7+K7+I7+G7+E7 -> 0 | O7: =IF(B7>0,N7/B7,0) -> 0 | P7: =P6 -> 18671.347 | Q7: =(P7-P6)*1000 -> 0 | R7: =N7-Q7 -> 0 | S7: =S6 -> 10175 | T7: =S7-S6 -> 0 | U7: =U6 -> 429166 | V7: =U7-U6 -> 0 | W7: =W6 -> 33463 | X7: =W7-W6 -> 0 | Y7: =Y6 -> 991838 | Z7: =Y7-Y6 -> 0 | AA7: =AA6 -> 36796 | AB7: =AA7-AA6 -> 0 | AC7: =AC6 -> 1170505 | AD7: =AC7-AC6 -> 0 | AE7: =AB7+X7+T7 -> 0 | AF7: =V7+Z7+AD7 -> 0 | AG7: =IF(AE7>0,AF7/AE7,0) -> 0
A8: ='General information '!F9 -> 0 | B8: =SUM(230*A8) -> 0 | C8: 44535 | D8: 75882 | E8: =D8-D7 -> 2372 | F8: 4104829 | G8: =F8-F7 -> 309 | H8: 17991714 | I8: =H8-H7 -> 620 | J8: 29627366 | K8: =J8-J7 -> 2160 | L8: 24477550 | M8: =L8-L7 -> 1268 | N8: =M8+K8+I8+G8+E8 -> 6729 | O8: =IF(B8>0,N8/B8,0) -> 0 | P8: 18677.892 | Q8: =(P8-P7)*1000 -> 6545 | R8: =N8-Q8 -> 184 | S8: =S7 -> 10175 | T8: =S8-S7 -> 0 | U8: =U7 -> 429166 | V8: =U8-U7 -> 0 | W8: 33464 | X8: =W8-W7 -> 1 | Y8: 992217 | Z8: =Y8-Y7 -> 379 | AA8: =AA7 -> 36796 | AB8: =AA8-AA7 -> 0 | AC8: =AC7 -> 1170505 | AD8: =AC8-AC7 -> 0 | AE8: =AB8+X8+T8 -> 1 | AF8: =V8+Z8+AD8 -> 379 | AG8: =IF(AE8>0,AF8/AE8,0) -> 379
A9: ='General information '!F10 -> 0 | B9: =SUM(230*A9) -> 0 | C9: 44536 | D9: 77692 | E9: =D9-D8 -> 1810 | F9: 4105086 | G9: =F9-F8 -> 257 | H9: 17992166 | I9: =H9-H8 -> 452 | J9: 29628866 | K9: =J9-J8 -> 1500 | L9: 24478510 | M9: =L9-L8 -> 960 | N9: =M9+K9+I9+G9+E9 -> 4979 | O9: =IF(B9>0,N9/B9,0) -> 0 | P9: 18682.821 | Q9: =(P9-P8)*1000 -> 4929 | R9: =N9-Q9 -> 50 | S9: =S8 -> 10175 | T9: =S9-S8 -> 0 | U9: =U8 -> 429166 | V9: =U9-U8 -> 0 | W9: 33466 | X9: =W9-W8 -> 2 | Y9: 992709 | Z9: =Y9-Y8 -> 492 | AA9: =AA8 -> 36796 | AB9: =AA9-AA8 -> 0 | AC9: =AC8 -> 1170505 | AD9: =AC9-AC8 -> 0 | AE9: =AB9+X9+T9 -> 2 | AF9: =V9+Z9+AD9 -> 492 | AG9: =IF(AE9>0,AF9/AE9,0) -> 246
A10: ='General information '!F11 -> 0 | B10: =SUM(230*A10) -> 0 | C10: 44537 | D10: 79683 | E10: =D10-D9 -> 1991 | F10: 4105348 | G10: =F10-F9 -> 262 | H10: 17992650 | I10: =H10-H9 -> 484 | J10: 29630440 | K10: =J10-J9 -> 1574 | L10: 24479532 | M10: =L10-L9 -> 1022 | N10: =M10+K10+I10+G10+E10 -> 5333 | O10: =IF(B10>0,N10/B10,0) -> 0 | P10: 18688.065 | Q10: =(P10-P9)*1000 -> 5244 | R10: =N10-Q10 -> 89 | S10: =S9 -> 10175 | T10: =S10-S9 -> 0 | U10: =U9 -> 429166 | V10: =U10-U9 -> 0 | W10: 33468 | X10: =W10-W9 -> 2 | Y10: 993093 | Z10: =Y10-Y9 -> 384 | AA10: 36796 | AB10: =AA10-AA9 -> 0 | AC10: =AC9 -> 1170505 | AD10: =AC10-AC9 -> 0 | AE10: =AB10+X10+T10 -> 2 | AF10: =V10+Z10+AD10 -> 384 | AG10: =IF(AE10>0,AF10/AE10,0) -> 192
A11: ='General information '!F12 -> 0 | B11: =SUM(230*A11) -> 0 | C11: 44538 | D11: 81927 | E11: =D11-D10 -> 2244 | F11: 4105650 | G11: =F11-F10 -> 302 | H11: 17993208 | I11: =H11-H10 -> 558 | J11: 29632090 | K11: =J11-J10 -> 1650 | L11: 24480502 | M11: =L11-L10 -> 970 | N11: =M11+K11+I11+G11+E11 -> 5724 | O11: =IF(B11>0,N11/B11,0) -> 0 | P11: 18694.028 | Q11: =(P11-P10)*1000 -> 5963 | R11: =N11-Q11 -> -239 | S11: =S10 -> 10175 | T11: =S11-S10 -> 0 | U11: =U10 -> 429166 | V11: =U11-U10 -> 0 | W11: 33469 | X11: =W11-W10 -> 1 | Y11: 993264 | Z11: =Y11-Y10 -> 171 | AA11: =AA10 -> 36796 | AB11: =AA11-AA10 -> 0 | AC11: =AC10 -> 1170505 | AD11: =AC11-AC10 -> 0 | AE11: =AB11+X11+T11 -> 1 | AF11: =V11+Z11+AD11 -> 171 | AG11: =IF(AE11>0,AF11/AE11,0) -> 171
A12: ='General information '!F13 -> 0 | B12: =SUM(230*A12) -> 0 | C12: 44539 | D12: 83936 | E12: =D12-D11 -> 2009 | F12: 4105902 | G12: =F12-F11 -> 252 | H12: 17993694 | I12: =H12-H11 -> 486 | J12: 29633422 | K12: =J12-J11 -> 1332 | L12: 24481418 | M12: =L12-L11 -> 916 | N12: =M12+K12+I12+G12+E12 -> 4995 | O12: =IF(B12>0,N12/B12,0) -> 0 | P12: 18698.864 | Q12: =(P12-P11)*1000 -> 4836 | R12: =N12-Q12 -> 159 | S12: =S11 -> 10175 | T12: =S12-S11 -> 0 | U12: =U11 -> 429166 | V12: =U12-U11 -> 0 | W12: 33470 | X12: =W12-W11 -> 1 | Y12: 993482 | Z12: =Y12-Y11 -> 218 | AA12: =AA11 -> 36796 | AB12: =AA12-AA11 -> 0 | AC12: =AC11 -> 1170505 | AD12: =AC12-AC11 -> 0 | AE12: =AB12+X12+T12 -> 1 | AF12: =V12+Z12+AD12 -> 218 | AG12: =IF(AE12>0,AF12/AE12,0) -> 218
A13: ='General information '!F14 -> 0 | B13: =SUM(230*A13) -> 0 | C13: 44540 | D13: =D12 -> 83936 | E13: =D13-D12 -> 0 | F13: =F12 -> 4105902 | G13: =F13-F12 -> 0 | H13: =H12 -> 17993694 | I13: =H13-H12 -> 0 | J13: =J12 -> 29633422 | K13: =J13-J12 -> 0 | L13: =L12 -> 24481418 | M13: =L13-L12 -> 0 | N13: =M13+K13+I13+G13+E13 -> 0 | O13: =IF(B13>0,N13/B13,0) -> 0 | P13: =P12 -> 18698.864 | Q13: =(P13-P12)*1000 -> 0 | R13: =N13-Q13 -> 0 | S13: =S12 -> 10175 | T13: =S13-S12 -> 0 | U13: =U12 -> 429166 | V13: =U13-U12 -> 0 | W13: =W12 -> 33470 | X13: =W13-W12 -> 0 | Y13: =Y12 -> 993482 | Z13: =Y13-Y12 -> 0 | AA13: =AA12 -> 36796 | AB13: =AA13-AA12 -> 0 | AC13: =AC12 -> 1170505 | AD13: =AC13-AC12 -> 0 | AE13: =AB13+X13+T13 -> 0 | AF13: =V13+Z13+AD13 -> 0 | AG13: =IF(AE13>0,AF13/AE13,0) -> 0
A14: ='General information '!F15 -> 0 | B14: =SUM(230*A14) -> 0 | C14: 44541 | D14: =D13 -> 83936 | E14: =D14-D13 -> 0 | F14: =F13 -> 4105902 | G14: =F14-F13 -> 0 | H14: =H13 -> 17993694 | I14: =H14-H13 -> 0 | J14: =J13 -> 29633422 | K14: =J14-J13 -> 0 | L14: =L13 -> 24481418 | M14: =L14-L13 -> 0 | N14: =M14+K14+I14+G14+E14 -> 0 | O14: =IF(B14>0,N14/B14,0) -> 0 | P14: =P13 -> 18698.864 | Q14: =(P14-P13)*1000 -> 0 | R14: =N14-Q14 -> 0 | S14: =S13 -> 10175 | T14: =S14-S13 -> 0 | U14: =U13 -> 429166 | V14: =U14-U13 -> 0 | W14: =W13 -> 33470 | X14: =W14-W13 -> 0 | Y14: =Y13 -> 993482 | Z14: =Y14-Y13 -> 0 | AA14: =AA13 -> 36796 | AB14: =AA14-AA13 -> 0 | AC14: =AC13 -> 1170505 | AD14: =AC14-AC13 -> 0 | AE14: =AB14+X14+T14 -> 0 | AF14: =V14+Z14+AD14 -> 0 | AG14: =IF(AE14>0,AF14/AE14,0) -> 0
A15: ='General information '!F16 -> 0 | B15: =SUM(230*A15) -> 0 | C15: 44542 | D15: 86146 | E15: =D15-D14 -> 2210 | F15: 4106227 | G15: =F15-F14 -> 325 | H15: 17994290 | I15: =H15-H14 -> 596 | J15: 29635876 | K15: =J15-J14 -> 2454 | L15: 24482666 | M15: =L15-L14 -> 1248 | N15: =M15+K15+I15+G15+E15 -> 6833 | O15: =IF(B15>0,N15/B15,0) -> 0 | P15: 18705.586 | Q15: =(P15-P14)*1000 -> 6722 | R15: =N15-Q15 -> 111 | S15: =S14 -> 10175 | T15: =S15-S14 -> 0 | U15: =U14 -> 429166 | V15: =U15-U14 -> 0 | W15: 33472 | X15: =W15-W14 -> 2 | Y15: 993956 | Z15: =Y15-Y14 -> 474 | AA15: =AA14 -> 36796 | AB15: =AA15-AA14 -> 0 | AC15: =AC14 -> 1170505 | AD15: =AC15-AC14 -> 0 | AE15: =AB15+X15+T15 -> 2 | AF15: =V15+Z15+AD15 -> 474 | AG15: =IF(AE15>0,AF15/AE15,0) -> 237
A16: ='General information '!F17 -> 0 | B16: =SUM(230*A16) -> 0 | C16: 44543 | D16: 88250 | E16: =D16-D15 -> 2104 | F16: 4106509.2 | G16: =F16-F15 -> 282.2 | H16: 17994798 | I16: =H16-H15 -> 508 | J16: 29637454 | K16: =J16-J15 -> 1578 | L16: 24483706 | M16: =L16-L15 -> 1040 | N16: =M16+K16+I16+G16+E16 -> 5512.2 | O16: =IF(B16>0,N16/B16,0) -> 0 | P16: 18710.711 | Q16: =(P16-P15)*1000 -> 5125 | R16: =N16-Q16 -> 387.2 | S16: =S15 -> 10175 | T16: =S16-S15 -> 0 | U16: =U15 -> 429166 | V16: =U16-U15 -> 0 | W16: 33474 | X16: =W16-W15 -> 2 | Y16: 994549 | Z16: =Y16-Y15 -> 593 | AA16: =AA15 -> 36796 | AB16: =AA16-AA15 -> 0 | AC16: =AC15 -> 1170505 | AD16: =AC16-AC15 -> 0 | AE16: =AB16+X16+T16 -> 2 | AF16: =V16+Z16+AD16 -> 593 | AG16: =IF(AE16>0,AF16/AE16,0) -> 296.5
A17: ='General information '!F18 -> 0 | B17: =SUM(230*A17) -> 0 | C17: 44544 | D17: 90130 | E17: =D17-D16 -> 1880 | F17: 4106779 | G17: =F17-F16 -> 269.8 | H17: 17995322 | I17: =H17-H16 -> 524 | J17: 29639054 | K17: =J17-J16 -> 1600 | L17: 24484746 | M17: =L17-L16 -> 1040 | N17: =M17+K17+I17+G17+E17 -> 5313.8 | O17: =IF(B17>0,N17/B17,0) -> 0 | P17: 18715.857 | Q17: =(P17-P16)*1000 -> 5146 | R17: =N17-Q17 -> 167.8 | S17: =S16 -> 10175 | T17: =S17-S16 -> 0 | U17: =U16 -> 429166 | V17: =U17-U16 -> 0 | W17: 33475 | X17: =W17-W16 -> 1 | Y17: 994802 | Z17: =Y17-Y16 -> 253 | AA17: =AA16 -> 36796 | AB17: =AA17-AA16 -> 0 | AC17: =AC16 -> 1170505 | AD17: =AC17-AC16 -> 0 | AE17: =AB17+X17+T17 -> 1 | AF17: =V17+Z17+AD17 -> 253 | AG17: =IF(AE17>0,AF17/AE17,0) -> 253
A18: ='General information '!F19 -> 0 | B18: =SUM(230*A18) -> 0 | C18: 44545 | D18: 92274 | E18: =D18-D17 -> 2144 | F18: 4107038 | G18: =F18-F17 -> 259 | H18: 17995838 | I18: =H18-H17 -> 516 | J18: 29640750 | K18: =J18-J17 -> 1696 | L18: 24485774 | M18: =L18-L17 -> 1028 | N18: =M18+K18+I18+G18+E18 -> 5643 | O18: =IF(B18>0,N18/B18,0) -> 0 | P18: 18721.031 | Q18: =(P18-P17)*1000 -> 5174 | R18: =N18-Q18 -> 469 | S18: =S17 -> 10175 | T18: =S18-S17 -> 0 | U18: =U17 -> 429166 | V18: =U18-U17 -> 0 | W18: 33476 | X18: =W18-W17 -> 1 | Y18: 995165 | Z18: =Y18-Y17 -> 363 | AA18: =AA17 -> 36796 | AB18: =AA18-AA17 -> 0 | AC18: =AC17 -> 1170505 | AD18: =AC18-AC17 -> 0 | AE18: =AB18+X18+T18 -> 1 | AF18: =V18+Z18+AD18 -> 363 | AG18: =IF(AE18>0,AF18/AE18,0) -> 363
A19: ='General information '!F20 -> 0 | B19: =SUM(230*A19) -> 0 | C19: 44546 | D19: 95274 | E19: =D19-D18 -> 3000 | F19: 4107541 | G19: =F19-F18 -> 503 | H19: 17996778 | I19: =H19-H18 -> 940 | J19: 29643616 | K19: =J19-J18 -> 2866 | L19: 24488010 | M19: =L19-L18 -> 2236 | N19: =M19+K19+I19+G19+E19 -> 9545 | O19: =IF(B19>0,N19/B19,0) -> 0 | P19: 18730.953 | Q19: =(P19-P18)*1000 -> 9922 | R19: =N19-Q19 -> -377 | S19: =S18 -> 10175 | T19: =S19-S18 -> 0 | U19: =U18 -> 429166 | V19: =U19-U18 -> 0 | W19: =W18 -> 33476 | X19: =W19-W18 -> 0 | Y19: =Y18 -> 995165 | Z19: =Y19-Y18 -> 0 | AA19: =AA18 -> 36796 | AB19: =AA19-AA18 -> 0 | AC19: =AC18 -> 1170505 | AD19: =AC19-AC18 -> 0 | AE19: =AB19+X19+T19 -> 0 | AF19: =V19+Z19+AD19 -> 0 | AG19: =IF(AE19>0,AF19/AE19,0) -> 0
A20: ='General information '!F21 -> 0 | B20: =SUM(230*A20) -> 0 | C20: 44547 | D20: =D19 -> 95274 | E20: =D20-D19 -> 0 | F20: =F19 -> 4107541 | G20: =F20-F19 -> 0 | H20: =H19 -> 17996778 | I20: =H20-H19 -> 0 | J20: =J19 -> 29643616 | K20: =J20-J19 -> 0 | L20: =L19 -> 24488010 | M20: =L20-L19 -> 0 | N20: =M20+K20+I20+G20+E20 -> 0 | O20: =IF(B20>0,N20/B20,0) -> 0 | P20: =P19 -> 18730.953 | Q20: =(P20-P19)*1000 -> 0 | R20: =N20-Q20 -> 0 | S20: =S19 -> 10175 | T20: =S20-S19 -> 0 | U20: =U19 -> 429166 | V20: =U20-U19 -> 0 | W20: =W19 -> 33476 | X20: =W20-W19 -> 0 | Y20: =Y19 -> 995165 | Z20: =Y20-Y19 -> 0 | AA20: =AA19 -> 36796 | AB20: =AA20-AA19 -> 0 | AC20: =AC19 -> 1170505 | AD20: =AC20-AC19 -> 0 | AE20: =AB20+X20+T20 -> 0 | AF20: =V20+Z20+AD20 -> 0 | AG20: =IF(AE20>0,AF20/AE20,0) -> 0
A21: ='General information '!F22 -> 0 | B21: =SUM(230*A21) -> 0 | C21: 44548 | D21: =D20 -> 95274 | E21: =D21-D20 -> 0 | F21: =F20 -> 4107541 | G21: =F21-F20 -> 0 | H21: =H20 -> 17996778 | I21: =H21-H20 -> 0 | J21: =J20 -> 29643616 | K21: =J21-J20 -> 0 | L21: =L20 -> 24488010 | M21: =L21-L20 -> 0 | N21: =M21+K21+I21+G21+E21 -> 0 | O21: =IF(B21>0,N21/B21,0) -> 0 | P21: =P20 -> 18730.953 | Q21: =(P21-P20)*1000 -> 0 | R21: =N21-Q21 -> 0 | S21: =S20 -> 10175 | T21: =S21-S20 -> 0 | U21: =U20 -> 429166 | V21: =U21-U20 -> 0 | W21: =W20 -> 33476 | X21: =W21-W20 -> 0 | Y21: =Y20 -> 995165 | Z21: =Y21-Y20 -> 0 | AA21: 36796 | AB21: =AA21-AA20 -> 0 | AC21: =AC20 -> 1170505 | AD21: =AC21-AC20 -> 0 | AE21: =AB21+X21+T21 -> 0 | AF21: =V21+Z21+AD21 -> 0 | AG21: =IF(AE21>0,AF21/AE21,0) -> 0
A22: ='General information '!F23 -> 0 | B22: =SUM(230*A22) -> 0 | C22: 44549 | D22: 98285 | E22: =D22-D21 -> 3011 | F22: 4107808 | G22: =F22-F21 -> 267 | H22: 17997282 | I22: =H22-H21 -> 504 | J22: 29645126 | K22: =J22-J21 -> 1510 | L22: 24489106 | M22: =L22-L21 -> 1096 | N22: =M22+K22+I22+G22+E22 -> 6388 | O22: =IF(B22>0,N22/B22,0) -> 0 | P22: 18736.311 | Q22: =(P22-P21)*1000 -> 5358 | R22: =N22-Q22 -> 1030 | S22: =S21 -> 10175 | T22: =S22-S21 -> 0 | U22: =U21 -> 429166 | V22: =U22-U21 -> 0 | W22: 33478 | X22: =W22-W21 -> 2 | Y22: 995560 | Z22: =Y22-Y21 -> 395 | AA22: =AA21 -> 36796 | AB22: =AA22-AA21 -> 0 | AC22: =AC21 -> 1170505 | AD22: =AC22-AC21 -> 0 | AE22: =AB22+X22+T22 -> 2 | AF22: =V22+Z22+AD22 -> 395 | AG22: =IF(AE22>0,AF22/AE22,0) -> 197.5
A23: ='General information '!F24 -> 0 | B23: =SUM(230*A23) -> 0 | C23: 44550 | D23: 100066 | E23: =D23-D22 -> 1781 | F23: 4108095 | G23: =F23-F22 -> 287 | H23: 17997818 | I23: =H23-H22 -> 536 | J23: 29646818 | K23: =J23-J22 -> 1692 | L23: 24490354 | M23: =L23-L22 -> 1248 | N23: =M23+K23+I23+G23+E23 -> 5544 | O23: =IF(B23>0,N23/B23,0) -> 0 | P23: 18742.013 | Q23: =(P23-P22)*1000 -> 5702 | R23: =N23-Q23 -> -158 | S23: =S22 -> 10175 | T23: =S23-S22 -> 0 | U23: =U22 -> 429166 | V23: =U23-U22 -> 0 | W23: =W22 -> 33478 | X23: =W23-W22 -> 0 | Y23: =Y22 -> 995560 | Z23: =Y23-Y22 -> 0 | AA23: =AA22 -> 36796 | AB23: =AA23-AA22 -> 0 | AC23: =AC22 -> 1170505 | AD23: =AC23-AC22 -> 0 | AE23: =AB23+X23+T23 -> 0 | AF23: =V23+Z23+AD23 -> 0 | AG23: =IF(AE23>0,AF23/AE23,0) -> 0
A24: ='General information '!F25 -> 0 | B24: =SUM(230*A24) -> 0 | C24: 44551 | D24: 100367 | E24: =D24-D23 -> 301 | F24: 4108377 | G24: =F24-F23 -> 282 | H24: 17998366 | I24: =H24-H23 -> 548 | J24: 29648566 | K24: =J24-J23 -> 1748 | L24: 24491666 | M24: =L24-L23 -> 1312 | N24: =M24+K24+I24+G24+E24 -> 4191 | O24: =IF(B24>0,N24/B24,0) -> 0 | P24: 18748.414 | Q24: =(P24-P23)*1000 -> 6401 | R24: =N24-Q24 -> -2210 | S24: =S23 -> 10175 | T24: =S24-S23 -> 0 | U24: =U23 -> 429166 | V24: =U24-U23 -> 0 | W24: =W23 -> 33478 | X24: =W24-W23 -> 0 | Y24: =Y23 -> 995560 | Z24: =Y24-Y23 -> 0 | AA24: =AA23 -> 36796 | AB24: =AA24-AA23 -> 0 | AC24: =AC23 -> 1170505 | AD24: =AC24-AC23 -> 0 | AE24: =AB24+X24+T24 -> 0 | AF24: =V24+Z24+AD24 -> 0 | AG24: =IF(AE24>0,AF24/AE24,0) -> 0
A25: ='General information '!F26 -> 0 | B25: =SUM(230*A25) -> 0 | C25: 44552 | D25: 105139 | E25: =D25-D24 -> 4772 | F25: 4108670 | G25: =F25-F24 -> 293 | H25: 17998936 | I25: =H25-H24 -> 570 | J25: 29650262 | K25: =J25-J24 -> 1696 | L25: 24492868 | M25: =L25-L24 -> 1202 | N25: =M25+K25+I25+G25+E25 -> 8533 | O25: =IF(B25>0,N25/B25,0) -> 0 | P25: 18754.1 | Q25: =(P25-P24)*1000 -> 5686 | R25: =N25-Q25 -> 2847 | S25: =S24 -> 10175 | T25: =S25-S24 -> 0 | U25: =U24 -> 429166 | V25: =U25-U24 -> 0 | W25: =W24 -> 33478 | X25: =W25-W24 -> 0 | Y25: =Y24 -> 995560 | Z25: =Y25-Y24 -> 0 | AA25: =AA24 -> 36796 | AB25: =AA25-AA24 -> 0 | AC25: =AC24 -> 1170505 | AD25: =AC25-AC24 -> 0 | AE25: =AB25+X25+T25 -> 0 | AF25: =V25+Z25+AD25 -> 0 | AG25: =IF(AE25>0,AF25/AE25,0) -> 0
A26: ='General information '!F27 -> 0 | B26: =SUM(230*A26) -> 0 | C26: 44553 | D26: 107288 | E26: =D26-D25 -> 2149 | F26: 4108906 | G26: =F26-F25 -> 236 | H26: 17999348 | I26: =H26-H25 -> 412 | J26: 29651508 | K26: =J26-J25 -> 1246 | L26: 24493836 | M26: =L26-L25 -> 968 | N26: =M26+K26+I26+G26+E26 -> 5011 | O26: =IF(B26>0,N26/B26,0) -> 0 | P26: 18758.488 | Q26: =(P26-P25)*1000 -> 4388 | R26: =N26-Q26 -> 623 | S26: =S25 -> 10175 | T26: =S26-S25 -> 0 | U26: =U25 -> 429166 | V26: =U26-U25 -> 0 | W26: =W25 -> 33478 | X26: =W26-W25 -> 0 | Y26: =Y25 -> 995560 | Z26: =Y26-Y25 -> 0 | AA26: =AA25 -> 36796 | AB26: =AA26-AA25 -> 0 | AC26: =AC25 -> 1170505 | AD26: =AC26-AC25 -> 0 | AE26: =AB26+X26+T26 -> 0 | AF26: =V26+Z26+AD26 -> 0 | AG26: =IF(AE26>0,AF26/AE26,0) -> 0
A27: ='General information '!F28 -> 0 | B27: =SUM(230*A27) -> 0 | C27: 44554 | D27: =D26 -> 107288 | E27: =D27-D26 -> 0 | F27: =F26 -> 4108906 | G27: =F27-F26 -> 0 | H27: =H26 -> 17999348 | I27: =H27-H26 -> 0 | J27: =J26 -> 29651508 | K27: =J27-J26 -> 0 | L27: =L26 -> 24493836 | M27: =L27-L26 -> 0 | N27: =M27+K27+I27+G27+E27 -> 0 | O27: =IF(B27>0,N27/B27,0) -> 0 | P27: =P26 -> 18758.488 | Q27: =(P27-P26)*1000 -> 0 | R27: =N27-Q27 -> 0 | S27: =S26 -> 10175 | T27: =S27-S26 -> 0 | U27: =U26 -> 429166 | V27: =U27-U26 -> 0 | W27: =W26 -> 33478 | X27: =W27-W26 -> 0 | Y27: =Y26 -> 995560 | Z27: =Y27-Y26 -> 0 | AA27: =AA26 -> 36796 | AB27: =AA27-AA26 -> 0 | AC27: =AC26 -> 1170505 | AD27: =AC27-AC26 -> 0 | AE27: =AB27+X27+T27 -> 0 | AF27: =V27+Z27+AD27 -> 0 | AG27: =IF(AE27>0,AF27/AE27,0) -> 0
A28: ='General information '!F29 -> 0 | B28: =SUM(230*A28) -> 0 | C28: 44555 | D28: =D27 -> 107288 | E28: =D28-D27 -> 0 | F28: =F27 -> 4108906 | G28: =F28-F27 -> 0 | H28: =H27 -> 17999348 | I28: =H28-H27 -> 0 | J28: =J27 -> 29651508 | K28: =J28-J27 -> 0 | L28: =L27 -> 24493836 | M28: =L28-L27 -> 0 | N28: =M28+K28+I28+G28+E28 -> 0 | O28: =IF(B28>0,N28/B28,0) -> 0 | P28: =P27 -> 18758.488 | Q28: =(P28-P27)*1000 -> 0 | R28: =N28-Q28 -> 0 | S28: =S27 -> 10175 | T28: =S28-S27 -> 0 | U28: =U27 -> 429166 | V28: =U28-U27 -> 0 | W28: =W27 -> 33478 | X28: =W28-W27 -> 0 | Y28: =Y27 -> 995560 | Z28: =Y28-Y27 -> 0 | AA28: =AA27 -> 36796 | AB28: =AA28-AA27 -> 0 | AC28: =AC27 -> 1170505 | AD28: =AC28-AC27 -> 0 | AE28: =AB28+X28+T28 -> 0 | AF28: =V28+Z28+AD28 -> 0 | AG28: =IF(AE28>0,AF28/AE28,0) -> 0
A29: ='General information '!F30 -> 0 | B29: =SUM(230*A29) -> 0 | C29: 44556 | D29: =D28 -> 107288 | E29: =D29-D28 -> 0 | F29: =F28 -> 4108906 | G29: =F29-F28 -> 0 | H29: =H28 -> 17999348 | I29: =H29-H28 -> 0 | J29: =J28 -> 29651508 | K29: =J29-J28 -> 0 | L29: =L28 -> 24493836 | M29: =L29-L28 -> 0 | N29: =M29+K29+I29+G29+E29 -> 0 | O29: =IF(B29>0,N29/B29,0) -> 0 | P29: =P28 -> 18758.488 | Q29: =(P29-P28)*1000 -> 0 | R29: =N29-Q29 -> 0 | S29: =S28 -> 10175 | T29: =S29-S28 -> 0 | U29: =U28 -> 429166 | V29: =U29-U28 -> 0 | W29: =W28 -> 33478 | X29: =W29-W28 -> 0 | Y29: =Y28 -> 995560 | Z29: =Y29-Y28 -> 0 | AA29: =AA28 -> 36796 | AB29: =AA29-AA28 -> 0 | AC29: =AC28 -> 1170505 | AD29: =AC29-AC28 -> 0 | AE29: =AB29+X29+T29 -> 0 | AF29: =V29+Z29+AD29 -> 0 | AG29: =IF(AE29>0,AF29/AE29,0) -> 0
A30: ='General information '!F31 -> 0 | B30: =SUM(230*A30) -> 0 | C30: 44557 | D30: 109560 | E30: =D30-D29 -> 2272 | F30: 4109137 | G30: =F30-F29 -> 231 | H30: 17999886 | I30: =H30-H29 -> 538 | J30: 29652908 | K30: =J30-J29 -> 1400 | L30: 24494672 | M30: =L30-L29 -> 836 | N30: =M30+K30+I30+G30+E30 -> 5277 | O30: =IF(B30>0,N30/B30,0) -> 0 | P30: 18763.629 | Q30: =(P30-P29)*1000 -> 5141 | R30: =N30-Q30 -> 136 | S30: =S29 -> 10175 | T30: =S30-S29 -> 0 | U30: =U29 -> 429166 | V30: =U30-U29 -> 0 | W30: 33479 | X30: =W30-W29 -> 1 | Y30: 995654 | Z30: =Y30-Y29 -> 94 | AA30: =AA29 -> 36796 | AB30: =AA30-AA29 -> 0 | AC30: =AC29 -> 1170505 | AD30: =AC30-AC29 -> 0 | AE30: =AB30+X30+T30 -> 1 | AF30: =V30+Z30+AD30 -> 94 | AG30: =IF(AE30>0,AF30/AE30,0) -> 94
A31: ='General information '!F32 -> 0 | B31: =SUM(230*A31) -> 0 | C31: 44558 | D31: 111170 | E31: =D31-D30 -> 1610 | F31: 4109381 | G31: =F31-F30 -> 244 | H31: 18000402 | I31: =H31-H30 -> 516 | J31: 29654238 | K31: =J31-J30 -> 1330 | L31: 24495762 | M31: =L31-L30 -> 1090 | N31: =M31+K31+I31+G31+E31 -> 4790 | O31: =IF(B31>0,N31/B31,0) -> 0 | P31: 18768.924 | Q31: =(P31-P30)*1000 -> 5295 | R31: =N31-Q31 -> -505 | S31: =S30 -> 10175 | T31: =S31-S30 -> 0 | U31: =U30 -> 429166 | V31: =U31-U30 -> 0 | W31: =W30 -> 33479 | X31: =W31-W30 -> 0 | Y31: =Y30 -> 995654 | Z31: =Y31-Y30 -> 0 | AA31: =AA30 -> 36796 | AB31: =AA31-AA30 -> 0 | AC31: =AC30 -> 1170505 | AD31: =AC31-AC30 -> 0 | AE31: =AB31+X31+T31 -> 0 | AF31: =V31+Z31+AD31 -> 0 | AG31: =IF(AE31>0,AF31/AE31,0) -> 0
A32: ='General information '!F33 -> 0 | B32: =SUM(230*A32) -> 0 | C32: 44559 | D32: 113520 | E32: =D32-D31 -> 2350 | F32: 4109588 | G32: =F32-F31 -> 207 | H32: 18000802 | I32: =H32-H31 -> 400 | J32: 29655023 | K32: =J32-J31 -> 785 | L32: 24497123 | M32: =L32-L31 -> 1361 | N32: =M32+K32+I32+G32+E32 -> 5103 | O32: =IF(B32>0,N32/B32,0) -> 0 | P32: 18774.755 | Q32: =(P32-P31)*1000 -> 5831 | R32: =N32-Q32 -> -728 | S32: =S31 -> 10175 | T32: =S32-S31 -> 0 | U32: =U31 -> 429166 | V32: =U32-U31 -> 0 | W32: =W31 -> 33479 | X32: =W32-W31 -> 0 | Y32: =Y31 -> 995654 | Z32: =Y32-Y31 -> 0 | AA32: =AA31 -> 36796 | AB32: =AA32-AA31 -> 0 | AC32: =AC31 -> 1170505 | AD32: =AC32-AC31 -> 0 | AE32: =AB32+X32+T32 -> 0 | AF32: =V32+Z32+AD32 -> 0 | AG32: =IF(AE32>0,AF32/AE32,0) -> 0
A33: ='General information '!F34 -> 0 | B33: =SUM(230*A33) -> 0 | C33: 44560 | D33: =D32 -> 113520 | E33: =D33-D32 -> 0 | F33: =F32 -> 4109588 | G33: =F33-F32 -> 0 | H33: =H32 -> 18000802 | I33: =H33-H32 -> 0 | J33: =J32 -> 29655023 | K33: =J33-J32 -> 0 | L33: =L32 -> 24497123 | M33: =L33-L32 -> 0 | N33: =M33+K33+I33+G33+E33 -> 0 | O33: =IF(B33>0,N33/B33,0) -> 0 | P33: =P32 -> 18774.755 | Q33: =(P33-P32)*1000 -> 0 | R33: =N33-Q33 -> 0 | S33: =S32 -> 10175 | T33: =S33-S32 -> 0 | U33: =U32 -> 429166 | V33: =U33-U32 -> 0 | W33: =W32 -> 33479 | X33: =W33-W32 -> 0 | Y33: =Y32 -> 995654 | Z33: =Y33-Y32 -> 0 | AA33: =AA32 -> 36796 | AB33: =AA33-AA32 -> 0 | AC33: =AC32 -> 1170505 | AD33: =AC33-AC32 -> 0 | AE33: =AB33+X33+T33 -> 0 | AF33: =V33+Z33+AD33 -> 0 | AG33: =IF(AE33>0,AF33/AE33,0) -> 0
A34: ='General information '!F35 -> 0 | B34: =SUM(230*A34) -> 0 | C34: 44561 | D34: =D33 -> 113520 | E34: =D34-D33 -> 0 | F34: =F33 -> 4109588 | G34: =F34-F33 -> 0 | H34: =H33 -> 18000802 | I34: =H34-H33 -> 0 | J34: =J33 -> 29655023 | K34: =J34-J33 -> 0 | L34: =L33 -> 24497123 | M34: =L34-L33 -> 0 | N34: =M34+K34+I34+G34+E34 -> 0 | O34: =IF(B34>0,N34/B34,0) -> 0 | P34: =P33 -> 18774.755 | Q34: =(P34-P33)*1000 -> 0 | R34: =N34-Q34 -> 0 | S34: =S33 -> 10175 | T34: =S34-S33 -> 0 | U34: =U33 -> 429166 | V34: =U34-U33 -> 0 | W34: =W33 -> 33479 | X34: =W34-W33 -> 0 | Y34: =Y33 -> 995654 | Z34: =Y34-Y33 -> 0 | AA34: =AA33 -> 36796 | AB34: =AA34-AA33 -> 0 | AC34: =AC33 -> 1170505 | AD34: =AC34-AC33 -> 0 | AE34: =AB34+X34+T34 -> 0 | AF34: =V34+Z34+AD34 -> 0 | AG34: =IF(AE34>0,AF34/AE34,0) -> 0

Sheet B5
F1: Boiler A | J1: =J36 -> 73.401961 | K1: Boiler B | P1: Boiler C | V1: Boiler | X1: SteamA | AC1: SteamB | AH1: Steam | AI1: Boiler & steam | AL1: Total Boiler Runing H | AM1: Total Steam Runing H | AN1: GAS1 % | AO1: GAS1/L | AP1: GAS2% | AQ1: Gas2/L | AR1: GAS3% | AS1: GAS3/L | AU1: Gas Cons | AV1: Delivery | AW1: Cost/L
B2: Level Tank Gen | C2: Level tank Boiler | D2: Daily Cons Bo. | E2: Boiler litter | F2: Boiler A | G2: Run Hr a | H2: Boiler A fuel | I2: Daily consumption | J2: AVG | K2: index Run H | L2: Run Hrb | M2: Boiler B Fuel | O2: Daily consumption | P2: Boiler C | S2: Run C | U2: Total RH | V2: Total Fuel | X2: SteamA | Y2: Run SA | Z2: Steam A Conter | AA2: Liters | AC2: SteamB | AD2: Run SteamB | AE2: Steam B Conter | AF2: SB Litters | AG2: Avg | AH2: Total Fuel | AI2: Total Fuel
S3: 0
A4: =ELEC!C3 -> 44530 | B4: =[2]B5!B34 -> 218 | C4: =[2]B5!C34 -> 224 | D4: =[2]B5!D34 -> 8 | E4: =[2]B5!E34 -> 67.04 | F4: =[2]B5!F34 -> 1921 | G4: =[2]B5!G34 -> 0 | H4: =[2]B5!H34 -> 19436 | I4: =[2]B5!I34 -> 0 | ... AX4: =[2]B5!AX34 -> 0.8
A5: =ELEC!C4 -> 44531 | B5: 210 | C5: 218 | D5: =C4-C5 -> 6 | E5: =D5*8.38 -> 50.28 | F5: 1924 | G5: =F5-F4 -> 3 | H5: 19613 | I5: =SUM(H5-H4) -> 177 | J5: 1 | K5: =K4 -> 2367 | L5: =K5-K4 -> 0 | M5: =M4 -> 174784 | N5: =M5-M4 -> 0 | O5: =O4 -> 1869 | P5: =P4 -> 2137 | Q5: =Q4 -> 179335 | R5: =Q5-Q4 -> 0 | S5: =SUM(P5-P4) -> 0 | T5: =SUM(S5*$T$2) -> 0 | U5: =SUM(G5+L5+S5) -> 3 | V5: 0 | W5: =SUM(V5/U5) -> 0 | X5: =X4 -> 2480 | Y5: =X5-X4 -> 0 | Z5: =Z4 -> 139172.2 | AA5: =Z5-Z4 -> 0 | AB5: =SUM(Y5*$AB$2) -> 0 | AC5: =AC4 -> 1943 | AD5: =AC5-AC4 -> 0 | AE5: =AE4 -> 366210 | AF5: =AE5-AE4 -> 0 | AG5: =IF(AD5>0,AF5/AD5,0) -> 0 | AH5: =AF5+AA5 -> 0 | AI5: =SUM(AH5+V5) -> 0 | AJ5: =-tanks!AW6 -> 0 | AK5: =SUM(AJ5-AI5) -> 0 | AL5: =S5+L5+G5 -> 3 | AM5: =Y5+AD5 -> 0 | AN5: =AN4 -> 65 | AO5: =(AN5/100)*3000 -> 1950 | AP5: =AP4 -> 55 | AQ5: =(AP5/100)*3000 -> 1650 | AR5: =AR4 -> 61 | AS5: =(AR5/100)*3000 -> 1830 | AT5: =SUM(AO5+AQ5+AS5) -> 5430 | AU5: =AT4-AT5+AV5 -> 0 | AX5: =IF(AV5>0,AW5,AX4) -> 0.8
A6: =ELEC!C5 -> 44532 | B6: 204 | C6: 211 | D6: =C5-C6 -> 7 | E6: =D6*8.38 -> 58.66 | F6: =F5 -> 1924 | G6: =F6-F5 -> 0 | H6: =H5 -> 19613 | I6: =SUM(H6-H5) -> 0 | J6: =IF(G6>0,I6/G6,0) -> 0 | K6: =K5 -> 2367 | L6: =K6-K5 -> 0 | M6: =M5 -> 174784 | N6: =M6-M5 -> 0 | O6: =O5 -> 1869 | P6: =P5 -> 2137 | Q6: =Q5 -> 179335 | R6: =Q6-Q5 -> 0 | S6: =SUM(P6-P5) -> 0 | T6: =SUM(S6*$T$2) -> 0 | U6: =SUM(G6+L6+S6) -> 0 | V6: =R6+N6+I6:I6 -> 0 | W6: =SUM(V6/U6) -> #DIV/0! | X6: =X5 -> 2480 | Y6: =X6-X5 -> 0 | Z6: =Z5 -> 139172.2 | AA6: =Z6-Z5 -> 0 | AB6: =SUM(Y6*$AB$2) -> 0 | AC6: =AC5 -> 1943 | AD6: =AC6-AC5 -> 0 | AE6: =AE5 -> 366210 | AF6: =AE6-AE5 -> 0 | AG6: =IF(AD6>0,AF6/AD6,0) -> 0 | AH6: =AF6+AA6 -> 0 | AI6: =SUM(AH6+V6) -> 0 | AJ6: =-tanks!AW7 -> 0 | AK6: =SUM(AJ6-AI6) -> 0 | AL6: =S6+L6+G6 -> 0 | AM6: =Y6+AD6 -> 0 | AN6: =AN5 -> 65 | AO6: =(AN6/100)*3000 -> 1950 | AP6: =AP5 -> 55 | AQ6: =(AP6/100)*3000 -> 1650 | AR6: =AR5 -> 61 | AS6: =(AR6/100)*3000 -> 1830 | AT6: =SUM(AO6+AQ6+AS6) -> 5430 | AU6: =AT5-AT6+AV6 -> 0 | AX6: =IF(AV6>0,AW6,AX5) -> 0.8
A7: =ELEC!C6 -> 44533 | B7: =B6 -> 204 | C7: =C6 -> 211 | D7: =C6-C7 -> 0 | E7: =D7*8.38 -> 0 | F7: =F6 -> 1924 | G7: =F7-F6 -> 0 | H7: =H6 -> 19613 | I7: =SUM(H7-H6) -> 0 | J7: =IF(G7>0,I7/G7,0) -> 0 | K7: =K6 -> 2367 | L7: =K7-K6 -> 0 | M7: =M6 -> 174784 | N7: =M7-M6 -> 0 | O7: =O6 -> 1869 | P7: =P6 -> 2137 | Q7: =Q6 -> 179335 | R7: =Q7-Q6 -> 0 | S7: =SUM(P7-P6) -> 0 | T7: =SUM(S7*$T$2) -> 0 | U7: =SUM(G7+L7+S7) -> 0 | V7: =R7+N7+I7:I7 -> 0 | W7: =SUM(V7/U7) -> #DIV/0! | X7: =X6 -> 2480 | Y7: =X7-X6 -> 0 | Z7: =Z6 -> 139172.2 | AA7: =Z7-Z6 -> 0 | AB7: =SUM(Y7*$AB$2) -> 0 | AC7: =AC6 -> 1943 | AD7: =AC7-AC6 -> 0 | AE7: =AE6 -> 366210 | AF7: =AE7-AE6 -> 0 | AG7: =IF(AD7>0,AF7/AD7,0) -> 0 | AH7: =AF7+AA7 -> 0 | AI7: =SUM(AH7+V7) -> 0 | AJ7: =-tanks!AW8 -> 0 | AK7: =SUM(AJ7-AI7) -> 0 | AL7: =S7+L7+G7 -> 0 | AM7: =Y7+AD7 -> 0 | AN7: =AN6 -> 65 | AO7: =(AN7/100)*3000 -> 1950 | AP7: =AP6 -> 55 | AQ7: =(AP7/100)*3000 -> 1650 | AR7: =AR6 -> 61 | AS7: =(AR7/100)*3000 -> 1830 | AT7: =SUM(AO7+AQ7+AS7) -> 5430 | AU7: =AT6-AT7+AV7 -> 0 | AX7: =IF(AV7>0,AW7,AX6) -> 0.8
A8: =ELEC!C7 -> 44534 | B8: =B7 -> 204 | C8: =C7 -> 211 | D8: =C7-C8 -> 0 | E8: =D8*8.38 -> 0 | F8: =F7 -> 1924 | G8: =F8-F7 -> 0 | H8: =H7 -> 19613 | I8: =SUM(H8-H7) -> 0 | J8: =IF(G8>0,I8/G8,0) -> 0 | K8: =K7 -> 2367 | L8: =K8-K7 -> 0 | M8: =M7 -> 174784 | N8: =M8-M7 -> 0 | O8: =O7 -> 1869 | P8: =P7 -> 2137 | Q8: =Q7 -> 179335 | R8: =Q8-Q7 -> 0 | S8: =SUM(P8-P7) -> 0 | T8: =SUM(S8*$T$2) -> 0 | U8: =SUM(G8+L8+S8) -> 0 | V8: 0 | W8: =SUM(V8/U8) -> #DIV/0! | X8: =X7 -> 2480 | Y8: =X8-X7 -> 0 | Z8: =Z7 -> 139172.2 | AA8: =Z8-Z7 -> 0 | AB8: =SUM(Y8*$AB$2) -> 0 | AC8: =AC7 -> 1943 | AD8: =AC8-AC7 -> 0 | AE8: =AE7 -> 366210 | AF8: =AE8-AE7 -> 0 | AG8: =IF(AD8>0,AF8/AD8,0) -> 0 | AH8: =AF8+AA8 -> 0 | AI8: =SUM(AH8+V8) -> 0 | AJ8: =-tanks!AW9 -> 0 | AK8: =SUM(AJ8-AI8) -> 0 | AL8: =S8+L8+G8 -> 0 | AM8: =Y8+AD8 -> 0 | AN8: =AN7 -> 65 | AO8: =(AN8/100)*3000 -> 1950 | AP8: =AP7 -> 55 | AQ8: =(AP8/100)*3000 -> 1650 | AR8: =AR7 -> 61 | AS8: =(AR8/100)*3000 -> 1830 | AT8: =SUM(AO8+AQ8+AS8) -> 5430 | AU8: =AT7-AT8+AV8 -> 0 | AX8: =IF(AV8>0,AW8,AX7) -> 0.8
A9: =ELEC!C8 -> 44535 | B9: 236 | C9: 241 | D9: =C8-C9 -> -30 | E9: =D9*8.38 -> -251.4 | F9: 1926 | G9: =F9-F8 -> 2 | H9: 19806 | I9: =SUM(H9-H8) -> 193 | J9: =IF(G9>0,I9/G9,0) -> 96.5 | K9: =K8 -> 2367 | L9: =K9-K8 -> 0 | M9: =M8 -> 174784 | N9: =M9-M8 -> 0 | O9: =O8 -> 1869 | P9: =P8 -> 2137 | Q9: =Q8 -> 179335 | R9: =Q9-Q8 -> 0 | S9: =SUM(P9-P8) -> 0 | T9: =SUM(S9*$T$2) -> 0 | U9: =SUM(G9+L9+S9) -> 2 | V9: =R9+N9+I9:I9 -> 193 | W9: =SUM(V9/U9) -> 96.5 | X9: =X8 -> 2480 | Y9: =X9-X8 -> 0 | Z9: =Z8 -> 139172.2 | AA9: =Z9-Z8 -> 0 | AB9: =SUM(Y9*$AB$2) -> 0 | AC9: =AC8 -> 1943 | AD9: =AC9-AC8 -> 0 | AE9: =AE8 -> 366210 | AF9: =AE9-AE8 -> 0 | AG9: =IF(AD9>0,AF9/AD9,0) -> 0 | AH9: =AF9+AA9 -> 0 | AI9: =SUM(AH9+V9) -> 193 | AJ9: =-tanks!AW10 -> 193 | AK9: =SUM(AJ9-AI9) -> 0 | AL9: =S9+L9+G9 -> 2 | AM9: =Y9+AD9 -> 0 | AN9: =AN8 -> 65 | AO9: =(AN9/100)*3000 -> 1950 | AP9: =AP8 -> 55 | AQ9: =(AP9/100)*3000 -> 1650 | AR9: =AR8 -> 61 | AS9: =(AR9/100)*3000 -> 1830 | AT9: =SUM(AO9+AQ9+AS9) -> 5430 | AU9: =AT8-AT9+AV9 -> 0 | AX9: =IF(AV9>0,AW9,AX8) -> 0.8
A10: =ELEC!C9 -> 44536 | B10: 229 | C10: 239 | D10: =C9-C10 -> 2 | E10: =D10*8.38 -> 16.76 | F10: 1928 | G10: =F10-F9 -> 2 | H10: 19916 | I10: =SUM(H10-H9) -> 110 | J10: =IF(G10>0,I10/G10,0) -> 55 | K10: =K9 -> 2367 | L10: =K10-K9 -> 0 | M10: =M9 -> 174784 | N10: =M10-M9 -> 0 | O10: =O9 -> 1869 | P10: =P9 -> 2137 | Q10: =Q9 -> 179335 | R10: =Q10-Q9 -> 0 | S10: =SUM(P10-P9) -> 0 | T10: =SUM(S10*$T$2) -> 0 | U10: =SUM(G10+L10+S10) -> 2 | V10: =R10+N10+I10:I10 -> 110 | W10: =SUM(V10/U10) -> 55 | X10: =X9 -> 2480 | Y10: =X10-X9 -> 0 | Z10: =Z9 -> 139172.2 | AA10: =Z10-Z9 -> 0 | AB10: =SUM(Y10*$AB$2) -> 0 | AC10: =AC9 -> 1943 | AD10: =AC10-AC9 -> 0 | AE10: =AE9 -> 366210 | AF10: =AE10-AE9 -> 0 | AG10: =IF(AD10>0,AF10/AD10,0) -> 0 | AH10: =AF10+AA10 -> 0 | AI10: =SUM(AH10+V10) -> 110 | AJ10: =-tanks!AW11 -> 110 | AK10: =SUM(AJ10-AI10) -> 0 | AL10: =S10+L10+G10 -> 2 | AM10: =Y10+AD10 -> 0 | AN10: =AN9 -> 65 | AO10: =(AN10/100)*3000 -> 1950 | AP10: =AP9 -> 55 | AQ10: =(AP10/100)*3000 -> 1650 | AR10: =AR9 -> 61 | AS10: =(AR10/100)*3000 -> 1830 | AT10: =SUM(AO10+AQ10+AS10) -> 5430 | AU10: =AT9-AT10+AV10 -> 0 | AX10: =IF(AV10>0,AW10,AX9) -> 0.8
A11: =ELEC!C10 -> 44537 | B11: 221 | C11: 226 | D11: =C10-C11 -> 13 | E11: =D11*8.38 -> 108.94 | F11: 1929 | G11: =F11-F10 -> 1 | H11: 20035 | I11: =SUM(H11-H10) -> 119 | J11: =IF(G11>0,I11/G11,0) -> 119 | K11: =K10 -> 2367 | L11: =K11-K10 -> 0 | M11: =M10 -> 174784 | N11: =M11-M10 -> 0 | O11: =O10 -> 1869 | P11: =P10 -> 2137 | Q11: =Q10 -> 179335 | R11: =Q11-Q10 -> 0 | S11: =SUM(P11-P10) -> 0 | T11: =SUM(S11*$T$2) -> 0 | U11: =SUM(G11+L11+S11) -> 1 | V11: =R11+N11+I11:I11 -> 119 | W11: =SUM(V11/U11) -> 119 | X11: =X10 -> 2480 | Y11: =X11-X10 -> 0 | Z11: =Z10 -> 139172.2 | AA11: =Z11-Z10 -> 0 | AB11: =SUM(Y11*$AB$2) -> 0 | AC11: =AC10 -> 1943 | AD11: =AC11-AC10 -> 0 | AE11: =AE10 -> 366210 | AF11: =AE11-AE10 -> 0 | AG11: =IF(AD11>0,AF11/AD11,0) -> 0 | AH11: =AF11+AA11 -> 0 | AI11: =SUM(AH11+V11) -> 119 | AJ11: =-tanks!AW12 -> 119 | AK11: =SUM(AJ11-AI11) -> 0 | AL11: =S11+L11+G11 -> 1 | AM11: =Y11+AD11 -> 0 | AN11: =AN10 -> 65 | AO11: =(AN11/100)*3000 -> 1950 | AP11: =AP10 -> 55 | AQ11: =(AP11/100)*3000 -> 1650 | AR11: =AR10 -> 61 | AS11: =(AR11/100)*3000 -> 1830 | AT11: =SUM(AO11+AQ11+AS11) -> 5430 | AU11: =AT10-AT11+AV11 -> 0 | AX11: =IF(AV11>0,AW11,AX10) -> 0.8
A12: =ELEC!C11 -> 44538 | B12: 214 | C12: 221 | D12: =C11-C12 -> 5 | E12: =D12*8.38 -> 41.9 | F12: 1930 | G12: =F12-F11 -> 1 | H12: 20124 | I12: =SUM(H12-H11) -> 89 | J12: =IF(G12>0,I12/G12,0) -> 89 | K12: =K11 -> 2367 | L12: =K12-K11 -> 0 | M12: =M11 -> 174784 | N12: =M12-M11 -> 0 | O12: =O11 -> 1869 | P12: =P11 -> 2137 | Q12: =Q11 -> 179335 | R12: =Q12-Q11 -> 0 | S12: =SUM(P12-P11) -> 0 | T12: =SUM(S12*$T$2) -> 0 | U12: =SUM(G12+L12+S12) -> 1 | V12: 0 | W12: =SUM(V12/U12) -> 0 | X12: =X11 -> 2480 | Y12: =X12-X11 -> 0 | Z12: =Z11 -> 139172.2 | AA12: =Z12-Z11 -> 0 | AB12: =SUM(Y12*$AB$2) -> 0 | AC12: =AC11 -> 1943 | AD12: =AC12-AC11 -> 0 | AE12: =AE11 -> 366210 | AF12: =AE12-AE11 -> 0 | AG12: =IF(AD12>0,AF12/AD12,0) -> 0 | AH12: =AF12+AA12 -> 0 | AI12: =SUM(AH12+V12) -> 0 | AJ12: =-tanks!AW13 -> 0 | AK12: =SUM(AJ12-AI12) -> 0 | AL12: =S12+L12+G12 -> 1 | AM12: =Y12+AD12 -> 0 | AN12: =AN11 -> 65 | AO12: =(AN12/100)*3000 -> 1950 | AP12: =AP11 -> 55 | AQ12: =(AP12/100)*3000 -> 1650 | AR12: =AR11 -> 61 | AS12: =(AR12/100)*3000 -> 1830 | AT12: =SUM(AO12+AQ12+AS12) -> 5430 | AU12: =AT11-AT12+AV12 -> 0 | AX12: =IF(AV12>0,AW12,AX11) -> 0.8
A13: =ELEC!C12 -> 44539 | B13: 207 | C13: 214 | D13: =C12-C13 -> 7 | E13: =D13*8.38 -> 58.66 | F13: 1931 | G13: =F13-F12 -> 1 | H13: 20194 | I13: =SUM(H13-H12) -> 70 | J13: =IF(G13>0,I13/G13,0) -> 70 | K13: =K12 -> 2367 | L13: =K13-K12 -> 0 | M13: =M12 -> 174784 | N13: =M13-M12 -> 0 | O13: =O12 -> 1869 | P13: =P12 -> 2137 | Q13: =Q12 -> 179335 | R13: =Q13-Q12 -> 0 | S13: =SUM(P13-P12) -> 0 | T13: =SUM(S13*$T$2) -> 0 | U13: =SUM(G13+L13+S13) -> 1 | V13: 0 | W13: =SUM(V13/U13) -> 0 | X13: =X12 -> 2480 | Y13: =X13-X12 -> 0 | Z13: =Z12 -> 139172.2 | AA13: =Z13-Z12 -> 0 | AB13: =SUM(Y13*$AB$2) -> 0 | AC13: =AC12 -> 1943 | AD13: =AC13-AC12 -> 0 | AE13: =AE12 -> 366210 | AF13: =AE13-AE12 -> 0 | AG13: =IF(AD13>0,AF13/AD13,0) -> 0 | AH13: =AF13+AA13 -> 0 | AI13: =SUM(AH13+V13) -> 0 | AJ13: =-tanks!AW14 -> 0 | AK13: =SUM(AJ13-AI13) -> 0 | AL13: =S13+L13+G13 -> 1 | AM13: =Y13+AD13 -> 0 | AN13: =AN12 -> 65 | AO13: =(AN13/100)*3000 -> 1950 | AP13: =AP12 -> 55 | AQ13: =(AP13/100)*3000 -> 1650 | AR13: =AR12 -> 61 | AS13: =(AR13/100)*3000 -> 1830 | AT13: =SUM(AO13+AQ13+AS13) -> 5430 | AU13: =AT12-AT13+AV13 -> 0 | AX13: =IF(AV13>0,AW13,AX12) -> 0.8
A14: =ELEC!C13 -> 44540 | B14: =B13 -> 207 | C14: =C13 -> 214 | D14: =C13-C14 -> 0 | E14: =D14*8.38 -> 0 | F14: =F13 -> 1931 | G14: =F14-F13 -> 0 | H14: =H13 -> 20194 | I14: =SUM(H14-H13) -> 0 | J14: =IF(G14>0,I14/G14,0) -> 0 | K14: =K13 -> 2367 | L14: =K14-K13 -> 0 | M14: =M13 -> 174784 | N14: =M14-M13 -> 0 | O14: =O13 -> 1869 | P14: =P13 -> 2137 | Q14: =Q13 -> 179335 | R14: =Q14-Q13 -> 0 | S14: =SUM(P14-P13) -> 0 | T14: =SUM(S14*$T$2) -> 0 | U14: =SUM(G14+L14+S14) -> 0 | V14: =R14+N14+I14:I14 -> 0 | W14: =SUM(V14/U14) -> #DIV/0! | X14: =X13 -> 2480 | Y14: =X14-X13 -> 0 | Z14: =Z13 -> 139172.2 | AA14: =Z14-Z13 -> 0 | AB14: =SUM(Y14*$AB$2) -> 0 | AC14: =AC13 -> 1943 | AD14: =AC14-AC13 -> 0 | AE14: =AE13 -> 366210 | AF14: =AE14-AE13 -> 0 | AG14: =IF(AD14>0,AF14/AD14,0) -> 0 | AH14: =AF14+AA14 -> 0 | AI14: =SUM(AH14+V14) -> 0 | AJ14: =-tanks!AW15 -> 0 | AK14: =SUM(AJ14-AI14) -> 0 | AL14: =S14+L14+G14 -> 0 | AM14: =Y14+AD14 -> 0 | AN14: =AN13 -> 65 | AO14: =(AN14/100)*3000 -> 1950 | AP14: =AP13 -> 55 | AQ14: =(AP14/100)*3000 -> 1650 | AR14: =AR13 -> 61 | AS14: =(AR14/100)*3000 -> 1830 | AT14: =SUM(AO14+AQ14+AS14) -> 5430 | AU14: =AT13-AT14+AV14 -> 0 | AX14: =IF(AV14>0,AW14,AX13) -> 0.8
A15: =ELEC!C14 -> 44541 | B15: =B14 -> 207 | C15: =C14 -> 214 | D15: =C14-C15 -> 0 | E15: =D15*8.38 -> 0 | F15: =F14 -> 1931 | G15: =F15-F14 -> 0 | H15: =H14 -> 20194 | I15: =SUM(H15-H14) -> 0 | J15: =IF(G15>0,I15/G15,0) -> 0 | K15: =K14 -> 2367 | L15: =K15-K14 -> 0 | M15: =M14 -> 174784 | N15: =M15-M14 -> 0 | O15: =O14 -> 1869 | P15: =P14 -> 2137 | Q15: =Q14 -> 179335 | R15: =Q15-Q14 -> 0 | S15: =SUM(P15-P14) -> 0 | T15: =SUM(S15*$T$2) -> 0 | U15: =SUM(G15+L15+S15) -> 0 | V15: =R15+N15+I15:I15 -> 0 | W15: =SUM(V15/U15) -> #DIV/0! | X15: =X14 -> 2480 | Y15: =X15-X14 -> 0 | Z15: =Z14 -> 139172.2 | AA15: =Z15-Z14 -> 0 | AB15: =SUM(Y15*$AB$2) -> 0 | AC15: =AC14 -> 1943 | AD15: =AC15-AC14 -> 0 | AE15: =AE14 -> 366210 | AF15: =AE15-AE14 -> 0 | AG15: =IF(AD15>0,AF15/AD15,0) -> 0 | AH15: =AF15+AA15 -> 0 | AI15: =SUM(AH15+V15) -> 0 | AJ15: =-tanks!AW16 -> 0 | AK15: =SUM(AJ15-AI15) -> 0 | AL15: =S15+L15+G15 -> 0 | AM15: =Y15+AD15 -> 0 | AN15: =AN14 -> 65 | AO15: =(AN15/100)*3000 -> 1950 | AP15: =AP14 -> 55 | AQ15: =(AP15/100)*3000 -> 1650 | AR15: =AR14 -> 61 | AS15: =(AR15/100)*3000 -> 1830 | AT15: =SUM(AO15+AQ15+AS15) -> 5430 | AU15: =AT14-AT15+AV15 -> 0 | AX15: =IF(AV15>0,AW15,AX14) -> 0.8
A16: =ELEC!C15 -> 44542 | B16: 202 | C16: 208 | D16: =C15-C16 -> 6 | E16: =D16*8.38 -> 50.28 | F16: 1933 | G16: =F16-F15 -> 2 | H16: 20312 | I16: =SUM(H16-H15) -> 118 | J16: =IF(G16>0,I16/G16,0) -> 59 | K16: =K15 -> 2367 | L16: =K16-K15 -> 0 | M16: =M15 -> 174784 | N16: =M16-M15 -> 0 | O16: =O15 -> 1869 | P16: =P15 -> 2137 | Q16: =Q15 -> 179335 | R16: =Q16-Q15 -> 0 | S16: =SUM(P16-P15) -> 0 | T16: =SUM(S16*$T$2) -> 0 | U16: =SUM(G16+L16+S16) -> 2 | V16: =R16+N16+I16:I16 -> 118 | W16: =SUM(V16/U16) -> 59 | X16: =X15 -> 2480 | Y16: =X16-X15 -> 0 | Z16: =Z15 -> 139172.2 | AA16: =Z16-Z15 -> 0 | AB16: =SUM(Y16*$AB$2) -> 0 | AC16: =AC15 -> 1943 | AD16: =AC16-AC15 -> 0 | AE16: =AE15 -> 366210 | AF16: =AE16-AE15 -> 0 | AG16: =IF(AD16>0,AF16/AD16,0) -> 0 | AH16: =AF16+AA16 -> 0 | AI16: =SUM(AH16+V16) -> 118 | AJ16: =-tanks!AW17 -> 118 | AK16: =SUM(AJ16-AI16) -> 0 | AL16: =S16+L16+G16 -> 2 | AM16: =Y16+AD16 -> 0 | AN16: =AN15 -> 65 | AO16: =(AN16/100)*3000 -> 1950 | AP16: =AP15 -> 55 | AQ16: =(AP16/100)*3000 -> 1650 | AR16: =AR15 -> 61 | AS16: =(AR16/100)*3000 -> 1830 | AT16: =SUM(AO16+AQ16+AS16) -> 5430 | AU16: =AT15-AT16+AV16 -> 0 | AX16: =IF(AV16>0,AW16,AX15) -> 0.8
A17: =ELEC!C16 -> 44543 | B17: 195 | C17: 202 | D17: =C16-C17 -> 6 | E17: =D17*8.38 -> 50.28 | F17: 1934 | G17: =F17-F16 -> 1 | H17: 20372 | I17: =SUM(H17-H16) -> 60 | J17: =IF(G17>0,I17/G17,0) -> 60 | K17: 2368 | L17: =K17-K16 -> 1 | M17: 174856 | N17: =M17-M16 -> 72 | O17: =O16 -> 1869 | P17: 2138 | Q17: 179372 | R17: =Q17-Q16 -> 37 | S17: =SUM(P17-P16) -> 1 | T17: =SUM(S17*$T$2) -> 0 | U17: =SUM(G17+L17+S17) -> 3 | V17: =R17+N17+I17:I17 -> 169 | X17: =X16 -> 2480 | Y17: =X17-X16 -> 0 | Z17: =Z16 -> 139172.2 | AA17: =Z17-Z16 -> 0 | AB17: =SUM(Y17*$AB$2) -> 0 | AC17: =AC16 -> 1943 | AD17: =AC17-AC16 -> 0 | AE17: =AE16 -> 366210 | AF17: =AE17-AE16 -> 0 | AG17: =IF(AD17>0,AF17/AD17,0) -> 0 | AH17: =AF17+AA17 -> 0 | AI17: =SUM(AH17+V17) -> 169 | AJ17: =-tanks!AW18 -> 169 | AK17: =SUM(AJ17-AI17) -> 0 | AL17: =S17+L17+G17 -> 3 | AM17: =Y17+AD17 -> 0 | AN17: =AN16 -> 65 | AO17: =(AN17/100)*3000 -> 1950 | AP17: =AP16 -> 55 | AQ17: =(AP17/100)*3000 -> 1650 | AR17: =AR16 -> 61 | AS17: =(AR17/100)*3000 -> 1830 | AT17: =SUM(AO17+AQ17+AS17) -> 5430 | AU17: =AT16-AT17+AV17 -> 0 | AX17: =IF(AV17>0,AW17,AX16) -> 0.8
A18: =ELEC!C17 -> 44544 | B18: 226 | C18: 233 | D18: =C17-C18 -> -31 | E18: =D18*8.38 -> -259.78 | F18: 1935 | G18: =F18-F17 -> 1 | H18: 20451 | I18: =SUM(H18-H17) -> 79 | J18: =IF(G18>0,I18/G18,0) -> 79 | K18: =K17 -> 2368 | L18: =K18-K17 -> 0 | M18: =M17 -> 174856 | N18: =M18-M17 -> 0 | O18: 1869 | P18: =P17 -> 2138 | Q18: 179410 | R18: =Q18-Q17 -> 38 | S18: =SUM(P18-P17) -> 0 | T18: =SUM(S18*$T$2) -> 0 | U18: =SUM(G18+L18+S18) -> 1 | V18: =R18+N18+I18:I18 -> 117 | X18: =X17 -> 2480 | Y18: =X18-X17 -> 0 | Z18: =Z17 -> 139172.2 | AA18: =Z18-Z17 -> 0 | AB18: =SUM(Y18*$AB$2) -> 0 | AC18: =AC17 -> 1943 | AD18: =AC18-AC17 -> 0 | AE18: =AE17 -> 366210 | AF18: =AE18-AE17 -> 0 | AG18: =IF(AD18>0,AF18/AD18,0) -> 0 | AH18: =AF18+AA18 -> 0 | AI18: =SUM(AH18+V18) -> 117 | AJ18: =-tanks!AW19 -> 117 | AK18: =SUM(AJ18-AI18) -> 0 | AL18: =S18+L18+G18 -> 1 | AM18: =Y18+AD18 -> 0 | AN18: =AN17 -> 65 | AO18: =(AN18/100)*3000 -> 1950 | AP18: =AP17 -> 55 | AQ18: =(AP18/100)*3000 -> 1650 | AR18: =AR17 -> 61 | AS18: =(AR18/100)*3000 -> 1830 | AT18: =SUM(AO18+AQ18+AS18) -> 5430 | AU18: =AT17-AT18+AV18 -> 0 | AX18: =IF(AV18>0,AW18,AX17) -> 0.8
A19: =ELEC!C18 -> 44545 | B19: 219 | C19: 227 | D19: =C18-C19 -> 6 | E19: =D19*8.38 -> 50.28 | F19: 1936 | G19: =F19-F18 -> 1 | H19: 20563 | I19: =SUM(H19-H18) -> 112 | J19: =IF(G19>0,I19/G19,0) -> 112 | K19: =K18 -> 2368 | L19: =K19-K18 -> 0 | M19: =M18 -> 174856 | N19: =M19-M18 -> 0 | O19: =O18 -> 1869 | P19: =P18 -> 2138 | Q19: 179410 | R19: =Q19-Q18 -> 0 | S19: =SUM(P19-P18) -> 0 | T19: =SUM(S19*$T$2) -> 0 | U19: =SUM(G19+L19+S19) -> 1 | V19: =R19+N19+I19:I19 -> 112 | X19: =X18 -> 2480 | Y19: =X19-X18 -> 0 | Z19: =Z18 -> 139172.2 | AA19: =Z19-Z18 -> 0 | AB19: =SUM(Y19*$AB$2) -> 0 | AC19: =AC18 -> 1943 | AD19: =AC19-AC18 -> 0 | AE19: =AE18 -> 366210 | AF19: =AE19-AE18 -> 0 | AG19: =IF(AD19>0,AF19/AD19,0) -> 0 | AH19: =AF19+AA19 -> 0 | AI19: =SUM(AH19+V19) -> 112 | AJ19: =-tanks!AW20 -> 112 | AK19: =SUM(AJ19-AI19) -> 0 | AL19: =S19+L19+G19 -> 1 | AM19: =Y19+AD19 -> 0 | AN19: =AN18 -> 65 | AO19: =(AN19/100)*3000 -> 1950 | AP19: =AP18 -> 55 | AQ19: =(AP19/100)*3000 -> 1650 | AR19: =AR18 -> 61 | AS19: =(AR19/100)*3000 -> 1830 | AT19: =SUM(AO19+AQ19+AS19) -> 5430 | AU19: =AT18-AT19+AV19 -> 0 | AX19: =IF(AV19>0,AW19,AX18) -> 0.8
A20: =ELEC!C19 -> 44546 | B20: 211 | C20: 218 | D20: =C19-C20 -> 9 | E20: =D20*8.38 -> 75.42 | F20: =F19 -> 1936 | G20: =F20-F19 -> 0 | H20: =H19 -> 20563 | I20: =SUM(H20-H19) -> 0 | J20: =IF(G20>0,I20/G20,0) -> 0 | K20: =K19 -> 2368 | L20: =K20-K19 -> 0 | M20: =M19 -> 174856 | N20: =M20-M19 -> 0 | O20: =O19 -> 1869 | P20: =P19 -> 2138 | Q20: =Q19 -> 179410 | R20: =Q20-Q19 -> 0 | S20: =SUM(P20-P19) -> 0 | T20: =SUM(S20*$T$2) -> 0 | U20: =SUM(G20+L20+S20) -> 0 | V20: =R20+N20+I20:I20 -> 0 | X20: =X19 -> 2480 | Y20: =X20-X19 -> 0 | Z20: =Z19 -> 139172.2 | AA20: =Z20-Z19 -> 0 | AB20: =SUM(Y20*$AB$2) -> 0 | AC20: =AC19 -> 1943 | AD20: =AC20-AC19 -> 0 | AE20: =AE19 -> 366210 | AF20: =AE20-AE19 -> 0 | AG20: =IF(AD20>0,AF20/AD20,0) -> 0 | AH20: =AF20+AA20 -> 0 | AI20: =SUM(AH20+V20) -> 0 | AJ20: =-tanks!AW21 -> 0 | AK20: =SUM(AJ20-AI20) -> 0 | AL20: =S20+L20+G20 -> 0 | AM20: =Y20+AD20 -> 0 | AN20: =AN19 -> 65 | AO20: =(AN20/100)*3000 -> 1950 | AP20: =AP19 -> 55 | AQ20: =(AP20/100)*3000 -> 1650 | AR20: =AR19 -> 61 | AS20: =(AR20/100)*3000 -> 1830 | AT20: =SUM(AO20+AQ20+AS20) -> 5430 | AU20: =AT19-AT20+AV20 -> 0 | AX20: =IF(AV20>0,AW20,AX19) -> 0.8
A21: =ELEC!C20 -> 44547 | B21: =B20 -> 211 | C21: =C20 -> 218 | D21: =C20-C21 -> 0 | E21: =D21*8.38 -> 0 | F21: =F20 -> 1936 | G21: =F21-F20 -> 0 | H21: =H20 -> 20563 | I21: =SUM(H21-H20) -> 0 | J21: =IF(G21>0,I21/G21,0) -> 0 | K21: =K20 -> 2368 | L21: =K21-K20 -> 0 | M21: =M20 -> 174856 | N21: =M21-M20 -> 0 | O21: =O20 -> 1869 | P21: =P20 -> 2138 | Q21: =Q20 -> 179410 | R21: =Q21-Q20 -> 0 | S21: =SUM(P21-P20) -> 0 | T21: =SUM(S21*$T$2) -> 0 | U21: =SUM(G21+L21+S21) -> 0 | V21: =R21+N21+I21:I21 -> 0 | X21: =X20 -> 2480 | Y21: =X21-X20 -> 0 | Z21: =Z20 -> 139172.2 | AA21: =Z21-Z20 -> 0 | AB21: =SUM(Y21*$AB$2) -> 0 | AC21: =AC20 -> 1943 | AD21: =AC21-AC20 -> 0 | AE21: =AE20 -> 366210 | AF21: =AE21-AE20 -> 0 | AG21: =IF(AD21>0,AF21/AD21,0) -> 0 | AH21: =AF21+AA21 -> 0 | AI21: =SUM(AH21+V21) -> 0 | AJ21: =-tanks!AW22 -> 0 | AK21: =SUM(AJ21-AI21) -> 0 | AL21: =S21+L21+G21 -> 0 | AM21: =Y21+AD21 -> 0 | AN21: =AN20 -> 65 | AO21: =(AN21/100)*3000 -> 1950 | AP21: =AP20 -> 55 | AQ21: =(AP21/100)*3000 -> 1650 | AR21: =AR20 -> 61 | AS21: =(AR21/100)*3000 -> 1830 | AT21: =SUM(AO21+AQ21+AS21) -> 5430 | AU21: =AT20-AT21+AV21 -> 0 | AX21: =IF(AV21>0,AW21,AX20) -> 0.8
A22: =ELEC!C21 -> 44548 | B22: =B21 -> 211 | C22: =C21 -> 218 | D22: =C21-C22 -> 0 | E22: =D22*8.38 -> 0 | F22: =F21 -> 1936 | G22: =F22-F21 -> 0 | H22: =H21 -> 20563 | I22: =SUM(H22-H21) -> 0 | J22: =IF(G22>0,I22/G22,0) -> 0 | K22: =K21 -> 2368 | L22: =K22-K21 -> 0 | M22: =M21 -> 174856 | N22: =M22-M21 -> 0 | O22: =O21 -> 1869 | P22: =P21 -> 2138 | Q22: =Q21 -> 179410 | R22: =Q22-Q21 -> 0 | S22: =SUM(P22-P21) -> 0 | T22: =SUM(S22*$T$2) -> 0 | U22: =SUM(G22+L22+S22) -> 0 | V22: =R22+N22+I22:I22 -> 0 | X22: =X21 -> 2480 | Y22: =X22-X21 -> 0 | Z22: =Z21 -> 139172.2 | AA22: =Z22-Z21 -> 0 | AB22: =SUM(Y22*$AB$2) -> 0 | AC22: =AC21 -> 1943 | AD22: =AC22-AC21 -> 0 | AE22: =AE21 -> 366210 | AF22: =AE22-AE21 -> 0 | AG22: =IF(AD22>0,AF22/AD22,0) -> 0 | AH22: =AF22+AA22 -> 0 | AI22: =SUM(AH22+V22) -> 0 | AJ22: =-tanks!AW23 -> 0 | AK22: =SUM(AJ22-AI22) -> 0 | AL22: =S22+L22+G22 -> 0 | AM22: =Y22+AD22 -> 0 | AN22: =AN21 -> 65 | AO22: =(AN22/100)*3000 -> 1950 | AP22: =AP21 -> 55 | AQ22: =(AP22/100)*3000 -> 1650 | AR22: =AR21 -> 61 | AS22: =(AR22/100)*3000 -> 1830 | AT22: =SUM(AO22+AQ22+AS22) -> 5430 | AU22: =AT21-AT22+AV22 -> 0 | AX22: =IF(AV22>0,AW22,AX21) -> 0.8
A23: =ELEC!C22 -> 44549 | B23: 200 | C23: 208 | D23: =C22-C23 -> 10 | E23: =D23*8.38 -> 83.8 | F23: 1938 | G23: =F23-F22 -> 2 | H23: 20666 | I23: =SUM(H23-H22) -> 103 | J23: =IF(G23>0,I23/G23,0) -> 51.5 | K23: 2370 | L23: =K23-K22 -> 2 | M23: 175038 | N23: =M23-M22 -> 182 | O23: =O22 -> 1869 | P23: =P22 -> 2138 | Q23: =Q22 -> 179410 | R23: =Q23-Q22 -> 0 | S23: =SUM(P23-P22) -> 0 | T23: =SUM(S23*$T$2) -> 0 | U23: =SUM(G23+L23+S23) -> 4 | V23: =R23+N23+I23:I23 -> 285 | X23: =X22 -> 2480 | Y23: =X23-X22 -> 0 | Z23: =Z22 -> 139172.2 | AA23: =Z23-Z22 -> 0 | AB23: =SUM(Y23*$AB$2) -> 0 | AC23: =AC22 -> 1943 | AD23: =AC23-AC22 -> 0 | AE23: =AE22 -> 366210 | AF23: =AE23-AE22 -> 0 | AG23: =IF(AD23>0,AF23/AD23,0) -> 0 | AH23: =AF23+AA23 -> 0 | AI23: =SUM(AH23+V23) -> 285 | AJ23: =-tanks!AW24 -> 285 | AK23: =SUM(AJ23-AI23) -> 0 | AL23: =S23+L23+G23 -> 4 | AM23: =Y23+AD23 -> 0 | AN23: =AN22 -> 65 | AO23: =(AN23/100)*3000 -> 1950 | AP23: =AP22 -> 55 | AQ23: =(AP23/100)*3000 -> 1650 | AR23: =AR22 -> 61 | AS23: =(AR23/100)*3000 -> 1830 | AT23: =SUM(AO23+AQ23+AS23) -> 5430 | AU23: =AT22-AT23+AV23 -> 0 | AX23: =IF(AV23>0,AW23,AX22) -> 0.8
A24: =ELEC!C23 -> 44550 | B24: 194 | C24: 200 | D24: =C23-C24 -> 8 | E24: =D24*8.38 -> 67.04 | F24: 1940 | G24: =F24-F23 -> 2 | H24: 20865 | I24: =SUM(H24-H23) -> 199 | J24: =IF(G24>0,I24/G24,0) -> 99.5 | K24: =K23 -> 2370 | L24: =K24-K23 -> 0 | M24: =M23 -> 175038 | N24: =M24-M23 -> 0 | O24: =O23 -> 1869 | P24: =P23 -> 2138 | Q24: =Q23 -> 179410 | R24: =Q24-Q23 -> 0 | S24: =SUM(P24-P23) -> 0 | T24: =SUM(S24*$T$2) -> 0 | U24: =SUM(G24+L24+S24) -> 2 | V24: =R24+N24+I24:I24 -> 199 | X24: =X23 -> 2480 | Y24: =X24-X23 -> 0 | Z24: =Z23 -> 139172.2 | AA24: =Z24-Z23 -> 0 | AB24: =SUM(Y24*$AB$2) -> 0 | AC24: =AC23 -> 1943 | AD24: =AC24-AC23 -> 0 | AE24: =AE23 -> 366210 | AF24: =AE24-AE23 -> 0 | AG24: =IF(AD24>0,AF24/AD24,0) -> 0 | AH24: =AF24+AA24 -> 0 | AI24: =SUM(AH24+V24) -> 199 | AJ24: =-tanks!AW25 -> 199 | AK24: =SUM(AJ24-AI24) -> 0 | AL24: =S24+L24+G24 -> 2 | AM24: =Y24+AD24 -> 0 | AN24: =AN23 -> 65 | AO24: =(AN24/100)*3000 -> 1950 | AP24: =AP23 -> 55 | AQ24: =(AP24/100)*3000 -> 1650 | AR24: =AR23 -> 61 | AS24: =(AR24/100)*3000 -> 1830 | AT24: =SUM(AO24+AQ24+AS24) -> 5430 | AU24: =AT23-AT24+AV24 -> 0 | AX24: =IF(AV24>0,AW24,AX23) -> 0.8
A25: =ELEC!C24 -> 44551 | B25: 224 | C25: 230 | D25: =C24-C25 -> -30 | E25: =D25*8.38 -> -251.4 | F25: 1941 | G25: =F25-F24 -> 1 | H25: 20894 | I25: =SUM(H25-H24) -> 29 | J25: =IF(G25>0,I25/G25,0) -> 29 | K25: 2371 | L25: =K25-K24 -> 1 | M25: 175129 | N25: =M25-M24 -> 91 | O25: =O24 -> 1869 | P25: =P24 -> 2138 | Q25: =Q24 -> 179410 | R25: =Q25-Q24 -> 0 | S25: =SUM(P25-P24) -> 0 | T25: =SUM(S25*$T$2) -> 0 | U25: =SUM(G25+L25+S25) -> 2 | V25: =R25+N25+I25:I25 -> 120 | X25: =X24 -> 2480 | Y25: =X25-X24 -> 0 | Z25: =Z24 -> 139172.2 | AA25: =Z25-Z24 -> 0 | AB25: =SUM(Y25*$AB$2) -> 0 | AC25: =AC24 -> 1943 | AD25: =AC25-AC24 -> 0 | AE25: =AE24 -> 366210 | AF25: =AE25-AE24 -> 0 | AG25: =IF(AD25>0,AF25/AD25,0) -> 0 | AH25: =AF25+AA25 -> 0 | AI25: =SUM(AH25+V25) -> 120 | AJ25: =-tanks!AW26 -> 120 | AK25: =SUM(AJ25-AI25) -> 0 | AL25: =S25+L25+G25 -> 2 | AM25: =Y25+AD25 -> 0 | AN25: =AN24 -> 65 | AO25: =(AN25/100)*3000 -> 1950 | AP25: =AP24 -> 55 | AQ25: =(AP25/100)*3000 -> 1650 | AR25: =AR24 -> 61 | AS25: =(AR25/100)*3000 -> 1830 | AT25: =SUM(AO25+AQ25+AS25) -> 5430 | AU25: =AT24-AT25+AV25 -> 0 | AX25: =IF(AV25>0,AW25,AX24) -> 0.8
A26: =ELEC!C25 -> 44552 | B26: 235 | C26: 242 | D26: =C25-C26 -> -12 | E26: =D26*8.38 -> -100.56 | F26: 1945 | G26: =F26-F25 -> 4 | H26: 21192 | I26: =SUM(H26-H25) -> 298 | J26: =IF(G26>0,I26/G26,0) -> 74.5 | K26: =K25 -> 2371 | L26: =K26-K25 -> 0 | M26: =M25 -> 175129 | N26: =M26-M25 -> 0 | O26: =O25 -> 1869 | P26: =P25 -> 2138 | Q26: =Q25 -> 179410 | R26: =Q26-Q25 -> 0 | S26: =SUM(P26-P25) -> 0 | T26: =SUM(S26*$T$2) -> 0 | U26: =SUM(G26+L26+S26) -> 4 | V26: =R26+N26+I26:I26 -> 298 | X26: =X25 -> 2480 | Y26: =X26-X25 -> 0 | Z26: =Z25 -> 139172.2 | AA26: =Z26-Z25 -> 0 | AB26: =SUM(Y26*$AB$2) -> 0 | AC26: =AC25 -> 1943 | AD26: =AC26-AC25 -> 0 | AE26: =AE25 -> 366210 | AF26: =AE26-AE25 -> 0 | AG26: =IF(AD26>0,AF26/AD26,0) -> 0 | AH26: =AF26+AA26 -> 0 | AI26: =SUM(AH26+V26) -> 298 | AJ26: =-tanks!AW27 -> 298 | AK26: =SUM(AJ26-AI26) -> 0 | AL26: =S26+L26+G26 -> 4 | AM26: =Y26+AD26 -> 0 | AN26: =AN25 -> 65 | AO26: =(AN26/100)*3000 -> 1950 | AP26: =AP25 -> 55 | AQ26: =(AP26/100)*3000 -> 1650 | AR26: =AR25 -> 61 | AS26: =(AR26/100)*3000 -> 1830 | AT26: =SUM(AO26+AQ26+AS26) -> 5430 | AU26: =AT25-AT26+AV26 -> 0 | AX26: =IF(AV26>0,AW26,AX25) -> 0.8
A27: =ELEC!C26 -> 44553 | B27: 229 | C27: 236 | D27: =C26-C27 -> 6 | E27: =D27*8.38 -> 50.28 | F27: 1947 | G27: =F27-F26 -> 2 | H27: 21408 | I27: =SUM(H27-H26) -> 216 | J27: =IF(G27>0,I27/G27,0) -> 108 | K27: =K26 -> 2371 | L27: =K27-K26 -> 0 | M27: 175131 | N27: =M27-M26 -> 2 | O27: =O26 -> 1869 | P27: =P26 -> 2138 | Q27: =Q26 -> 179410 | R27: =Q27-Q26 -> 0 | S27: =SUM(P27-P26) -> 0 | T27: =SUM(S27*$T$2) -> 0 | U27: =SUM(G27+L27+S27) -> 2 | V27: =R27+N27+I27:I27 -> 218 | X27: =X26 -> 2480 | Y27: =X27-X26 -> 0 | Z27: =Z26 -> 139172.2 | AA27: =Z27-Z26 -> 0 | AB27: =SUM(Y27*$AB$2) -> 0 | AC27: =AC26 -> 1943 | AD27: =AC27-AC26 -> 0 | AE27: =AE26 -> 366210 | AF27: =AE27-AE26 -> 0 | AG27: =IF(AD27>0,AF27/AD27,0) -> 0 | AH27: =AF27+AA27 -> 0 | AI27: =SUM(AH27+V27) -> 218 | AJ27: =-tanks!AW28 -> 218 | AK27: =SUM(AJ27-AI27) -> 0 | AL27: =S27+L27+G27 -> 2 | AM27: =Y27+AD27 -> 0 | AN27: =AN26 -> 65 | AO27: =(AN27/100)*3000 -> 1950 | AP27: =AP26 -> 55 | AQ27: =(AP27/100)*3000 -> 1650 | AR27: =AR26 -> 61 | AS27: =(AR27/100)*3000 -> 1830 | AT27: =SUM(AO27+AQ27+AS27) -> 5430 | AU27: =AT26-AT27+AV27 -> 0 | AX27: =IF(AV27>0,AW27,AX26) -> 0.8
A28: =ELEC!C27 -> 44554 | B28: =B27 -> 229 | C28: =C27 -> 236 | D28: =C27-C28 -> 0 | E28: =D28*8.38 -> 0 | F28: =F27 -> 1947 | G28: =F28-F27 -> 0 | H28: =H27 -> 21408 | I28: =SUM(H28-H27) -> 0 | J28: =IF(G28>0,I28/G28,0) -> 0 | K28: =K27 -> 2371 | L28: =K28-K27 -> 0 | M28: =M27 -> 175131 | N28: =M28-M27 -> 0 | O28: =O27 -> 1869 | P28: =P27 -> 2138 | Q28: =Q27 -> 179410 | R28: =Q28-Q27 -> 0 | S28: =SUM(P28-P27) -> 0 | T28: =SUM(S28*$T$2) -> 0 | U28: =SUM(G28+L28+S28) -> 0 | V28: =R28+N28+I28:I28 -> 0 | X28: =X27 -> 2480 | Y28: =X28-X27 -> 0 | Z28: =Z27 -> 139172.2 | AA28: =Z28-Z27 -> 0 | AB28: =SUM(Y28*$AB$2) -> 0 | AC28: =AC27 -> 1943 | AD28: =AC28-AC27 -> 0 | AE28: =AE27 -> 366210 | AF28: =AE28-AE27 -> 0 | AG28: =IF(AD28>0,AF28/AD28,0) -> 0 | AH28: =AF28+AA28 -> 0 | AI28: =SUM(AH28+V28) -> 0 | AJ28: =-tanks!AW29 -> 0 | AK28: =SUM(AJ28-AI28) -> 0 | AL28: =S28+L28+G28 -> 0 | AM28: =Y28+AD28 -> 0 | AN28: =AN27 -> 65 | AO28: =(AN28/100)*3000 -> 1950 | AP28: =AP27 -> 55 | AQ28: =(AP28/100)*3000 -> 1650 | AR28: =AR27 -> 61 | AS28: =(AR28/100)*3000 -> 1830 | AT28: =SUM(AO28+AQ28+AS28) -> 5430 | AU28: =AT27-AT28+AV28 -> 0 | AX28: =IF(AV28>0,AW28,AX27) -> 0.8
A29: =ELEC!C28 -> 44555 | B29: =B28 -> 229 | C29: =C28 -> 236 | D29: =C28-C29 -> 0 | E29: =D29*8.38 -> 0 | F29: =F28 -> 1947 | G29: =F29-F28 -> 0 | H29: =H28 -> 21408 | I29: =SUM(H29-H28) -> 0 | J29: =IF(G29>0,I29/G29,0) -> 0 | K29: =K28 -> 2371 | L29: =K29-K28 -> 0 | M29: =M28 -> 175131 | N29: =M29-M28 -> 0 | O29: =O28 -> 1869 | P29: =P28 -> 2138 | Q29: =Q28 -> 179410 | R29: =Q29-Q28 -> 0 | S29: =SUM(P29-P28) -> 0 | T29: =SUM(S29*$T$2) -> 0 | U29: =SUM(G29+L29+S29) -> 0 | V29: =R29+N29+I29:I29 -> 0 | X29: =X28 -> 2480 | Y29: =X29-X28 -> 0 | Z29: =Z28 -> 139172.2 | AA29: =Z29-Z28 -> 0 | AB29: =SUM(Y29*$AB$2) -> 0 | AC29: =AC28 -> 1943 | AD29: =AC29-AC28 -> 0 | AE29: =AE28 -> 366210 | AF29: =AE29-AE28 -> 0 | AG29: =IF(AD29>0,AF29/AD29,0) -> 0 | AH29: =AF29+AA29 -> 0 | AI29: =SUM(AH29+V29) -> 0 | AJ29: =-tanks!AW30 -> 0 | AK29: =SUM(AJ29-AI29) -> 0 | AL29: =S29+L29+G29 -> 0 | AM29: =Y29+AD29 -> 0 | AN29: =AN28 -> 65 | AO29: =(AN29/100)*3000 -> 1950 | AP29: =AP28 -> 55 | AQ29: =(AP29/100)*3000 -> 1650 | AR29: =AR28 -> 61 | AS29: =(AR29/100)*3000 -> 1830 | AT29: =SUM(AO29+AQ29+AS29) -> 5430 | AU29: =AT28-AT29+AV29 -> 0 | AX29: =IF(AV29>0,AW29,AX28) -> 0.8
A30: =ELEC!C29 -> 44556 | B30: =B29 -> 229 | C30: =C29 -> 236 | D30: =C29-C30 -> 0 | E30: =D30*8.38 -> 0 | F30: =F29 -> 1947 | G30: =F30-F29 -> 0 | H30: =H29 -> 21408 | I30: =SUM(H30-H29) -> 0 | J30: =IF(G30>0,I30/G30,0) -> 0 | K30: =K29 -> 2371 | L30: =K30-K29 -> 0 | M30: =M29 -> 175131 | N30: =M30-M29 -> 0 | O30: =O29 -> 1869 | P30: =P29 -> 2138 | Q30: =Q29 -> 179410 | R30: =Q30-Q29 -> 0 | S30: =SUM(P30-P29) -> 0 | T30: =SUM(S30*$T$2) -> 0 | U30: =SUM(G30+L30+S30) -> 0 | V30: =R30+N30+I30:I30 -> 0 | X30: =X29 -> 2480 | Y30: =X30-X29 -> 0 | Z30: =Z29 -> 139172.2 | AA30: =Z30-Z29 -> 0 | AB30: =SUM(Y30*$AB$2) -> 0 | AC30: =AC29 -> 1943 | AD30: =AC30-AC29 -> 0 | AE30: =AE29 -> 366210 | AF30: =AE30-AE29 -> 0 | AG30: =IF(AD30>0,AF30/AD30,0) -> 0 | AH30: =AF30+AA30 -> 0 | AI30: =SUM(AH30+V30) -> 0 | AJ30: =-tanks!AW31 -> 0 | AK30: =SUM(AJ30-AI30) -> 0 | AL30: =S30+L30+G30 -> 0 | AM30: =Y30+AD30 -> 0 | AN30: =AN29 -> 65 | AO30: =(AN30/100)*3000 -> 1950 | AP30: =AP29 -> 55 | AQ30: =(AP30/100)*3000 -> 1650 | AR30: =AR29 -> 61 | AS30: =(AR30/100)*3000 -> 1830 | AT30: =SUM(AO30+AQ30+AS30) -> 5430 | AU30: =AT29-AT30+AV30 -> 0 | AX30: =IF(AV30>0,AW30,AX29) -> 0.8
A31: =ELEC!C30 -> 44557 | B31: 223 | C31: 230 | D31: =C30-C31 -> 6 | E31: =D31*8.38 -> 50.28 | F31: 1950 | G31: =F31-F30 -> 3 | H31: 21607 | I31: =SUM(H31-H30) -> 199 | J31: =IF(G31>0,I31/G31,0) -> 66.333333 | K31: =K30 -> 2371 | L31: =K31-K30 -> 0 | M31: =M30 -> 175131 | N31: =M31-M30 -> 0 | O31: =O30 -> 1869 | P31: =P30 -> 2138 | Q31: =Q30 -> 179410 | R31: =Q31-Q30 -> 0 | S31: =SUM(P31-P30) -> 0 | T31: =SUM(S31*$T$2) -> 0 | U31: =SUM(G31+L31+S31) -> 3 | V31: =R31+N31+I31:I31 -> 199 | X31: =X30 -> 2480 | Y31: =X31-X30 -> 0 | Z31: =Z30 -> 139172.2 | AA31: =Z31-Z30 -> 0 | AB31: =SUM(Y31*$AB$2) -> 0 | AC31: =AC30 -> 1943 | AD31: =AC31-AC30 -> 0 | AE31: =AE30 -> 366210 | AF31: =AE31-AE30 -> 0 | AG31: =IF(AD31>0,AF31/AD31,0) -> 0 | AH31: =AF31+AA31 -> 0 | AI31: =SUM(AH31+V31) -> 199 | AJ31: =-tanks!AW32 -> 199 | AK31: =SUM(AJ31-AI31) -> 0 | AL31: =S31+L31+G31 -> 3 | AM31: =Y31+AD31 -> 0 | AN31: =AN30 -> 65 | AO31: =(AN31/100)*3000 -> 1950 | AP31: =AP30 -> 55 | AQ31: =(AP31/100)*3000 -> 1650 | AR31: =AR30 -> 61 | AS31: =(AR31/100)*3000 -> 1830 | AT31: =SUM(AO31+AQ31+AS31) -> 5430 | AU31: =AT30-AT31+AV31 -> 0 | AX31: =IF(AV31>0,AW31,AX30) -> 0.8
A32: =ELEC!C31 -> 44558 | B32: 216 | C32: 223 | D32: =C31-C32 -> 7 | E32: =D32*8.38 -> 58.66 | F32: 1954 | G32: =F32-F31 -> 4 | H32: 21921 | I32: =SUM(H32-H31) -> 314 | J32: =IF(G32>0,I32/G32,0) -> 78.5 | K32: =K31 -> 2371 | L32: =K32-K31 -> 0 | M32: =M31 -> 175131 | N32: =M32-M31 -> 0 | O32: =O31 -> 1869 | P32: =P31 -> 2138 | Q32: =Q31 -> 179410 | R32: =Q32-Q31 -> 0 | S32: =SUM(P32-P31) -> 0 | T32: =SUM(S32*$T$2) -> 0 | U32: =SUM(G32+L32+S32) -> 4 | V32: =R32+N32+I32:I32 -> 314 | X32: =X31 -> 2480 | Y32: =X32-X31 -> 0 | Z32: =Z31 -> 139172.2 | AA32: =Z32-Z31 -> 0 | AB32: =SUM(Y32*$AB$2) -> 0 | AC32: =AC31 -> 1943 | AD32: =AC32-AC31 -> 0 | AE32: =AE31 -> 366210 | AF32: =AE32-AE31 -> 0 | AG32: =IF(AD32>0,AF32/AD32,0) -> 0 | AH32: =AF32+AA32 -> 0 | AI32: =SUM(AH32+V32) -> 314 | AJ32: =-tanks!AW33 -> 314 | AK32: =SUM(AJ32-AI32) -> 0 | AL32: =S32+L32+G32 -> 4 | AM32: =Y32+AD32 -> 0 | AN32: =AN31 -> 65 | AO32: =(AN32/100)*3000 -> 1950 | AP32: =AP31 -> 55 | AQ32: =(AP32/100)*3000 -> 1650 | AR32: =AR31 -> 61 | AS32: =(AR32/100)*3000 -> 1830 | AT32: =SUM(AO32+AQ32+AS32) -> 5430 | AU32: =AT31-AT32+AV32 -> 0 | AX32: =IF(AV32>0,AW32,AX31) -> 0.8
A33: =ELEC!C32 -> 44559 | B33: 209 | C33: 217 | D33: =C32-C33 -> 6 | E33: =D33*8.38 -> 50.28 | F33: =F32 -> 1954 | G33: =F33-F32 -> 0 | H33: =H32 -> 21921 | I33: =SUM(H33-H32) -> 0 | J33: =IF(G33>0,I33/G33,0) -> 0 | K33: =K32 -> 2371 | L33: =K33-K32 -> 0 | M33: =M32 -> 175131 | N33: =M33-M32 -> 0 | O33: =O32 -> 1869 | P33: =P32 -> 2138 | Q33: =Q32 -> 179410 | R33: =Q33-Q32 -> 0 | S33: =SUM(P33-P32) -> 0 | T33: =SUM(S33*$T$2) -> 0 | U33: =SUM(G33+L33+S33) -> 0 | V33: =R33+N33+I33:I33 -> 0 | X33: =X32 -> 2480 | Y33: =X33-X32 -> 0 | Z33: =Z32 -> 139172.2 | AA33: =Z33-Z32 -> 0 | AB33: =SUM(Y33*$AB$2) -> 0 | AC33: =AC32 -> 1943 | AD33: =AC33-AC32 -> 0 | AE33: =AE32 -> 366210 | AF33: =AE33-AE32 -> 0 | AG33: =IF(AD33>0,AF33/AD33,0) -> 0 | AH33: =AF33+AA33 -> 0 | AI33: =SUM(AH33+V33) -> 0 | AJ33: =-tanks!AW34 -> 0 | AK33: =SUM(AJ33-AI33) -> 0 | AL33: =S33+L33+G33 -> 0 | AM33: =Y33+AD33 -> 0 | AN33: =AN32 -> 65 | AO33: =(AN33/100)*3000 -> 1950 | AP33: =AP32 -> 55 | AQ33: =(AP33/100)*3000 -> 1650 | AR33: =AR32 -> 61 | AS33: =(AR33/100)*3000 -> 1830 | AT33: =SUM(AO33+AQ33+AS33) -> 5430 | AU33: =AT32-AT33+AV33 -> 0 | AX33: =IF(AV33>0,AW33,AX32) -> 0.8
A34: =ELEC!C33 -> 44560 | B34: =B33 -> 209 | C34: =C33 -> 217 | D34: =C33-C34 -> 0 | E34: =D34*8.38 -> 0 | F34: =F33 -> 1954 | G34: =F34-F33 -> 0 | H34: =H33 -> 21921 | I34: =SUM(H34-H33) -> 0 | J34: =IF(G34>0,I34/G34,0) -> 0 | K34: =K33 -> 2371 | L34: =K34-K33 -> 0 | M34: =M33 -> 175131 | N34: =M34-M33 -> 0 | O34: =O33 -> 1869 | P34: =P33 -> 2138 | Q34: =Q33 -> 179410 | R34: =Q34-Q33 -> 0 | S34: =SUM(P34-P33) -> 0 | T34: =SUM(S34*$T$2) -> 0 | U34: =SUM(G34+L34+S34) -> 0 | V34: =R34+N34+I34:I34 -> 0 | X34: =X33 -> 2480 | Y34: =X34-X33 -> 0 | Z34: =Z33 -> 139172.2 | AA34: =Z34-Z33 -> 0 | AB34: =SUM(Y34*$AB$2) -> 0 | AC34: =AC33 -> 1943 | AD34: =AC34-AC33 -> 0 | AE34: =AE33 -> 366210 | AF34: =AE34-AE33 -> 0 | AG34: =IF(AD34>0,AF34/AD34,0) -> 0 | AH34: =AF34+AA34 -> 0 | AI34: =SUM(AH34+V34) -> 0 | AJ34: =-tanks!AW35 -> 0 | AK34: =SUM(AJ34-AI34) -> 0 | AL34: =S34+L34+G34 -> 0 | AM34: =Y34+AD34 -> 0 | AN34: =AN33 -> 65 | AO34: =(AN34/100)*3000 -> 1950 | AP34: =AP33 -> 55 | AQ34: =(AP34/100)*3000 -> 1650 | AR34: =AR33 -> 61 | AS34: =(AR34/100)*3000 -> 1830 | AT34: =SUM(AO34+AQ34+AS34) -> 5430 | AU34: =AT33-AT34+AV34 -> 0 | AX34: =IF(AV34>0,AW34,AX33) -> 0.8
A35: =ELEC!C34 -> 44561 | B35: =B34 -> 209 | C35: =C34 -> 217 | D35: =C34-C35 -> 0 | E35: =D35*8.38 -> 0 | F35: =F34 -> 1954 | G35: =F35-F34 -> 0 | H35: =H34 -> 21921 | I35: =SUM(H35-H34) -> 0 | J35: =IF(G35>0,I35/G35,0) -> 0 | K35: =K34 -> 2371 | L35: =K35-K34 -> 0 | M35: =M34 -> 175131 | N35: =M35-M34 -> 0 | O35: =O34 -> 1869 | P35: =P34 -> 2138 | Q35: =Q34 -> 179410 | R35: =Q35-Q34 -> 0 | S35: =SUM(P35-P34) -> 0 | T35: =SUM(S35*$T$2) -> 0 | U35: =SUM(G35+L35+S35) -> 0 | V35: =R35+N35+I35:I35 -> 0 | X35: =X34 -> 2480 | Y35: =X35-X34 -> 0 | Z35: =Z34 -> 139172.2 | AA35: =Z35-Z34 -> 0 | AB35: =SUM(Y35*$AB$2) -> 0 | AC35: =AC34 -> 1943 | AD35: =AC35-AC34 -> 0 | AE35: =AE34 -> 366210 | AF35: =AE35-AE34 -> 0 | AG35: =IF(AD35>0,AF35/AD35,0) -> 0 | AH35: =AF35+AA35 -> 0 | AI35: =SUM(AH35+V35) -> 0 | AJ35: =-tanks!AW36 -> 0 | AK35: =SUM(AJ35-AI35) -> 0 | AL35: =S35+L35+G35 -> 0 | AM35: =Y35+AD35 -> 0 | AN35: =AN34 -> 65 | AO35: =(AN35/100)*3000 -> 1950 | AP35: =AP34 -> 55 | AQ35: =(AP35/100)*3000 -> 1650 | AR35: =AR34 -> 61 | AS35: =(AR35/100)*3000 -> 1830 | AT35: =SUM(AO35+AQ35+AS35) -> 5430 | AU35: =AT34-AT35+AV35 -> 0 | AX35: =IF(AV35>0,AW35,AX34) -> 0.8
J36: =SUM(J5:J32)/(COUNT(J5:J32)-COUNTIF(J5:J32,0)) -> 73.401961 | U36: =SUM(U5:U35) -> 38 | V36: =SUM(V5:V35) -> 2571 | AE36: . | AH36: =SUM(AH5:AH35) -> 0 | AL36: =SUM(AL5:AL35) -> 38 | AM36: =SUM(AM5:AM35) -> 0 | AR36: Nb Delivery | AS36: =COUNT(AW5:AW35) -> 0 | AU36: =SUM(AU5:AU35) -> 0 | AV36: =SUM(AV5:AV35) -> 0 | AW36: =SUM(AW5:AW35)/AS36 -> #DIV/0!
V37: =V36/U36 -> 67.657895 | AH37: =AF37+AA37 -> 0 | AI37: =SUM(AI5:AI35) -> 2571
AH38: =AF38+AA38 -> 0 | AU38: =AU36*0.51 -> 0 | AV38: =AV36/0.51 -> 0 | AW38: =SUM(AW5:AW32)/AS36 -> #DIV/0!
AV39: =AV36*0.51 -> 0

Sheet WATER
D1: =SUM(G21:G33) -> 8142030 | AR1: Entrance | AT1: Tank 1 | AV1: Tank 2
AR2: Level | AW2: Quantity CM3 | AZ2: Var
A3: Date | B3: Truck | C3: Truck M3/day | D3: N0. Trucks | F3: REQ. # of trucks | G3: City | H3: City/day | I3: Total water delivery | K3: SW | L3: Cosum SW/day | M3: RO Guest/ Liter | O3: RO K&L/ Liter | Q3: TOTAL RO Production | R3: RO 1 RH | S3: RO 2 RH | T3: RO water counter | U3: RO Cons m3 | V3: Steam Boiler | W3: Steam Boiler/day | X3: Softener Guest | Y3: Guest Sotf/day | Z3: Softener K&L | AA3: K&L Soft/Day | AB3: Fire Tank Level | AC3: Fire Tank Counter | AE3: Laundry Hot Water Counter | AF3: Hot Water Cons/day | AG3: Laundry Cold Water Counter | AH3: Cold Water Cons/day | AI3: Laundry Water Total Cons | AJ3: K&L Sotf/day | AK3: Guest / day | AL3: K&L /day | AM3: Avg Outside Temp | AN3: Banquet Activity | AR3: Date | AT3: MainI | AV3: Kitchen and Laundry | AX3: Guest | AY3: Main Tank | AZ3: Kitchen and Laundry | BA3: Guest | BB3: Kitchen and Laundry | BC3: Main | BD3: Guest | BE3: Total VAR | BF3: Hotel Consumption
E4: 1.66 | AN4: Ball R | AO4: Meeting | AP4: outlet | AT4: 180 | AV4: 220 | AX4: 580 | AY4: =SUM(AT4) -> 180 | AZ4: =SUM(AV4) -> 220 | BA4: =SUM(AX4) -> 580
A5: =[2]WATER!$A$35 -> 44530 | B5: =[2]WATER!B36 -> 109443 | C5: =[2]WATER!C36 -> 0 | D5: =[2]WATER!D36 -> 0 | E5: =[2]WATER!E36 -> 250 | F5: =[2]WATER!F36 -> 0 | G5: =[2]WATER!G36 -> 625978 | H5: =[2]WATER!H36 -> 0 | I5: =[2]WATER!I36 -> 0 | ... W5: =[2]WATER!W36 -> 0 | X5: 154335 | Y5: =[2]WATER!Y36 -> 0 | Z5: =[2]WATER!Z36 -> 99258 | AA5: =[2]WATER!AA36 -> 0 | AB5: =[2]WATER!AB36 -> 248 | AC5: =[2]WATER!AC36 -> 789 | AD5: =[2]WATER!AD36 -> 0 | AE5: =[2]WATER!AE36 -> 239.1 | AF5: =[2]WATER!AF36 -> 0 | ... AP5: =[2]WATER!AP36 -> 0 | AR5: =[2]WATER!$AR$35 -> 44530 | AS5: =[2]WATER!AS36 -> 0.9 | AT5: =[2]WATER!AT36 -> 94 | AU5: =[2]WATER!AU36 -> 1.1 | AV5: =[2]WATER!AV36 -> 139 | AW5: =[2]WATER!AW36 -> 2.9 | AX5: =[2]WATER!AX36 -> 101 | AY5: =[2]WATER!AY36 -> 84.6 | AZ5: =[2]WATER!AZ36 -> 152.9 | ... BG5: =[2]WATER!BG36 -> 0
A6: =ELEC!C4 -> 44531 | B6: =B5 -> 109443 | C6: =B6-B5 -> 0 | D6: =C6/27 -> 0 | E6: =SUM((C6*$E$4)+(7500/'EDl log'!$A$37)) -> 241.93548 | G6: =G5 -> 625978 | H6: =G6-G5 -> 0 | I6: =C6+H6 -> 0 | J6: =IF(I6>0,E6/I6,0) -> 0 | K6: ='Swimming Pool quality check '!H6 -> 6954 | L6: 0 | M6: =M5 -> 457.44 | N6: =SUM(M6-M5) -> 0 | O6: =O5 -> 529.52 | P6: =SUM(O6-O5) -> 0 | Q6: =P6+N6 -> 0 | T6: =T5 -> 5180 | U6: =SUM(T6-T5) -> 0 | V6: =V5 -> 477 | W6: =+V6-V5 -> 0 | X6: =X5 -> 154335 | Y6: =SUM(X6-X5) -> 0 | Z6: =Z5 -> 99258 | AA6: =Z6-Z5 -> 0 | AB6: =AB5 -> 248 | AC6: =AC5 -> 789 | AD6: 0 | AE6: =AE5 -> 239.1 | AF6: =AE6-AE5 -> 0 | AG6: =AG5 -> 2217.83 | AH6: =AG6-AG5 -> 0 | AI6: =AF6+AH6 -> 0 | AJ6: =+Z6-Z5 -> 0 | AK6: =SUM(Y6-L6) -> 0 | AL6: =SUM(AJ6-W6) -> 0 | AM6: ='General information '!D5 -> 18.5 | AN6: ='General information '!H5 -> 0 | AP6: ='General information '!J5 -> 0 | AR6: =A6 -> 44531 | AS6: =AS5 -> 0.9 | AT6: =AT5 -> 94 | AU6: =AU5 -> 1.1 | AV6: 137 | AW6: 2.9 | AX6: 100 | AY6: =AS6*AT6 -> 84.6 | AZ6: =AU6*AV6 -> 150.7 | BA6: =AW6*AX6 -> 290 | BB6: =AY6-AY5 -> 0 | BC6: =AZ6-AZ5 -> -2.2 | BD6: =BA6-BA5 -> -2.9 | BE6: =SUM(BB6:BD6) -> -5.1 | BF6: =SUM(I6-BE6) -> 5.1 | BG6: =SUM(I6-BF6) -> -5.1
A7: =ELEC!C5 -> 44532 | B7: =B6 -> 109443 | C7: =B7-B6 -> 0 | D7: =C7/27 -> 0 | E7: =SUM((C7*$E$4)+(7500/'EDl log'!$A$37)) -> 241.93548 | G7: 626138 | H7: =G7-G6 -> 160 | I7: =C7+H7 -> 160 | J7: =IF(I7>0,E7/I7,0) -> 1.5120968 | K7: ='Swimming Pool quality check '!H7 -> 6954 | L7: =K7-K6 -> 0 | M7: =M6 -> 457.44 | N7: =SUM(M7-M6) -> 0 | O7: =O6 -> 529.52 | P7: =SUM(O7-O6) -> 0 | Q7: =P7+N7 -> 0 | T7: =T6 -> 5180 | U7: =SUM(T7-T6) -> 0 | V7: =V6 -> 477 | W7: =+V7-V6 -> 0 | X7: =X6 -> 154335 | Y7: =SUM(X7-X6) -> 0 | Z7: =Z6 -> 99258 | AA7: =Z7-Z6 -> 0 | AB7: =AB6 -> 248 | AC7: =AC6 -> 789 | AD7: =AC7-AC6 -> 0 | AE7: =AE6 -> 239.1 | AF7: =AE7-AE6 -> 0 | AG7: =AG6 -> 2217.83 | AH7: =AG7-AG6 -> 0 | AI7: =AF7+AH7 -> 0 | AJ7: =+Z7-Z6 -> 0 | AK7: =SUM(Y7-L7) -> 0 | AL7: =SUM(AJ7-W7) -> 0 | AM7: ='General information '!D6 -> 18 | AN7: ='General information '!H6 -> 0 | AP7: ='General information '!J6 -> 0 | AR7: =A7 -> 44532 | AS7: =AS6 -> 0.9 | AT7: 186 | AU7: =AU6 -> 1.1 | AV7: 135 | AW7: 2.9 | AX7: 98 | AY7: =AS7*AT7 -> 167.4 | AZ7: =AU7*AV7 -> 148.5 | BA7: =AW7*AX7 -> 284.2 | BB7: =AY7-AY6 -> 82.8 | BC7: =AZ7-AZ6 -> -2.2 | BD7: =BA7-BA6 -> -5.8 | BE7: =SUM(BB7:BD7) -> 74.8 | BF7: =SUM(I7-BE7) -> 85.2 | BG7: =SUM(I7-BF7) -> 74.8
A8: =ELEC!C6 -> 44533 | B8: =B7 -> 109443 | C8: =B8-B7 -> 0 | D8: =C8/27 -> 0 | E8: =SUM((C8*$E$4)+(7500/'EDl log'!$A$37)) -> 241.93548 | G8: =G7 -> 626138 | H8: =G8-G7 -> 0 | I8: =C8+H8 -> 0 | J8: =IF(I8>0,E8/I8,0) -> 0 | K8: ='Swimming Pool quality check '!H8 -> 6954 | L8: =K8-K7 -> 0 | M8: =M7 -> 457.44 | N8: =SUM(M8-M7) -> 0 | O8: =O7 -> 529.52 | P8: =SUM(O8-O7) -> 0 | Q8: =P8+N8 -> 0 | T8: =T7 -> 5180 | U8: =SUM(T8-T7) -> 0 | V8: =V7 -> 477 | W8: =+V8-V7 -> 0 | X8: =X7 -> 154335 | Y8: =SUM(X8-X7) -> 0 | Z8: =Z7 -> 99258 | AA8: =Z8-Z7 -> 0 | AB8: =AB7 -> 248 | AC8: =AC7 -> 789 | AD8: =AC8-AC7 -> 0 | AE8: =AE7 -> 239.1 | AF8: =AE8-AE7 -> 0 | AG8: =AG7 -> 2217.83 | AH8: =AG8-AG7 -> 0 | AI8: =AF8+AH8 -> 0 | AJ8: =+Z8-Z7 -> 0 | AK8: =SUM(Y8-L8) -> 0 | AL8: =SUM(AJ8-W8) -> 0 | AM8: ='General information '!D7 -> 0 | AN8: ='General information '!H7 -> 0 | AP8: ='General information '!J7 -> 0 | AR8: =A8 -> 44533 | AS8: =AS7 -> 0.9 | AT8: =AT7 -> 186 | AU8: 1.1 | AV8: =AV7 -> 135 | AW8: 2.9 | AX8: =AX7 -> 98 | AY8: =AS8*AT8 -> 167.4 | AZ8: =AU8*AV8 -> 148.5 | BA8: =AW8*AX8 -> 284.2 | BB8: =AY8-AY7 -> 0 | BC8: =AZ8-AZ7 -> 0 | BD8: =BA8-BA7 -> 0 | BE8: =SUM(BB8:BD8) -> 0 | BF8: =SUM(I8-BE8) -> 0 | BG8: =SUM(I8-BF8) -> 0
A9: =ELEC!C7 -> 44534 | B9: =B8 -> 109443 | C9: =B9-B8 -> 0 | D9: =C9/27 -> 0 | E9: =SUM((C9*$E$4)+(7500/'EDl log'!$A$37)) -> 241.93548 | G9: =G8 -> 626138 | H9: =G9-G8 -> 0 | I9: =C9+H9 -> 0 | J9: =IF(I9>0,E9/I9,0) -> 0 | K9: ='Swimming Pool quality check '!H9 -> 6954 | L9: =K9-K8 -> 0 | M9: =M8 -> 457.44 | N9: =SUM(M9-M8) -> 0 | O9: =O8 -> 529.52 | P9: =SUM(O9-O8) -> 0 | Q9: =P9+N9 -> 0 | T9: =T8 -> 5180 | U9: =SUM(T9-T8) -> 0 | V9: =V8 -> 477 | W9: =+V9-V8 -> 0 | X9: =X8 -> 154335 | Y9: =SUM(X9-X8) -> 0 | Z9: =Z8 -> 99258 | AA9: =Z9-Z8 -> 0 | AB9: =AB8 -> 248 | AC9: =AC8 -> 789 | AD9: =AC9-AC8 -> 0 | AE9: =AE8 -> 239.1 | AF9: =AE9-AE8 -> 0 | AG9: =AG8 -> 2217.83 | AH9: =AG9-AG8 -> 0 | AI9: =AF9+AH9 -> 0 | AJ9: =+Z9-Z8 -> 0 | AK9: =SUM(Y9-L9) -> 0 | AL9: =SUM(AJ9-W9) -> 0 | AM9: ='General information '!D8 -> 0 | AN9: ='General information '!H8 -> 0 | AP9: ='General information '!J8 -> 0 | AR9: =A9 -> 44534 | AS9: =AS8 -> 0.9 | AT9: =AT8 -> 186 | AU9: =AU8 -> 1.1 | AV9: =AV8 -> 135 | AW9: 2.9 | AX9: =AX8 -> 98 | AY9: =AS9*AT9 -> 167.4 | AZ9: =AU9*AV9 -> 148.5 | BA9: =AW9*AX9 -> 284.2 | BB9: =AY9-AY8 -> 0 | BC9: =AZ9-AZ8 -> 0 | BD9: =BA9-BA8 -> 0 | BE9: =SUM(BB9:BD9) -> 0 | BF9: =SUM(I9-BE9) -> 0 | BG9: =SUM(I9-BF9) -> 0
A10: =ELEC!C8 -> 44535 | B10: =B9 -> 109443 | C10: =B10-B9 -> 0 | D10: =C10/27 -> 0 | E10: =SUM((C10*$E$4)+(7500/'EDl log'!$A$37)) -> 241.93548 | G10: =G9 -> 626138 | H10: =G10-G9 -> 0 | I10: =C10+H10 -> 0 | J10: =IF(I10>0,E10/I10,0) -> 0 | K10: ='Swimming Pool quality check '!H10 -> 6960 | L10: =K10-K9 -> 6 | M10: =M9 -> 457.44 | N10: =SUM(M10-M9) -> 0 | O10: =O9 -> 529.52 | P10: =SUM(O10-O9) -> 0 | Q10: =P10+N10 -> 0 | T10: =T9 -> 5180 | U10: =SUM(T10-T9) -> 0 | V10: =V9 -> 477 | W10: =+V10-V9 -> 0 | X10: =X9 -> 154335 | Y10: =SUM(X10-X9) -> 0 | Z10: =Z9 -> 99258 | AA10: =Z10-Z9 -> 0 | AB10: =AB9 -> 248 | AC10: =AC9 -> 789 | AD10: =AC10-AC9 -> 0 | AE10: =AE9 -> 239.1 | AF10: =AE10-AE9 -> 0 | AG10: =AG9 -> 2217.83 | AH10: =AG10-AG9 -> 0 | AI10: =AF10+AH10 -> 0 | AJ10: =+Z10-Z9 -> 0 | AK10: =SUM(Y10-L10) -> -6 | AL10: =SUM(AJ10-W10) -> 0 | AM10: ='General information '!D9 -> 20 | AN10: ='General information '!H9 -> 0 | AP10: ='General information '!J9 -> 0 | AR10: =A10 -> 44535 | AS10: =AS9 -> 0.9 | AT10: =AT9 -> 186 | AU10: =AU9 -> 1.1 | AV10: =AV9 -> 135 | AW10: 2.9 | AX10: 97 | AY10: =AS10*AT10 -> 167.4 | AZ10: =AU10*AV10 -> 148.5 | BA10: =AW10*AX10 -> 281.3 | BB10: =AY10-AY9 -> 0 | BC10: =AZ10-AZ9 -> 0 | BD10: =BA10-BA9 -> -2.9 | BE10: =SUM(BB10:BD10) -> -2.9 | BF10: =SUM(I10-BE10) -> 2.9 | BG10: =SUM(I10-BF10) -> -2.9
A11: =ELEC!C9 -> 44536 | B11: =B10 -> 109443 | C11: =B11-B10 -> 0 | D11: =C11/27 -> 0 | E11: =SUM((C11*$E$4)+(7500/'EDl log'!$A$37)) -> 241.93548 | G11: =G10 -> 626138 | H11: =G11-G10 -> 0 | I11: =C11+H11 -> 0 | J11: =IF(I11>0,E11/I11,0) -> 0 | K11: ='Swimming Pool quality check '!H11 -> 6960 | L11: =K11-K10 -> 0 | M11: =M10 -> 457.44 | N11: =SUM(M11-M10) -> 0 | O11: =O10 -> 529.52 | P11: =SUM(O11-O10) -> 0 | Q11: =SUM(P11+N11) -> 0 | T11: =T10 -> 5180 | U11: =SUM(T11-T10) -> 0 | V11: =V10 -> 477 | W11: =+V11-V10 -> 0 | X11: =X10 -> 154335 | Y11: =SUM(X11-X10) -> 0 | Z11: =Z10 -> 99258 | AA11: =Z11-Z10 -> 0 | AB11: =AB10 -> 248 | AC11: =AC10 -> 789 | AD11: =AC11-AC10 -> 0 | AE11: =AE10 -> 239.1 | AF11: =AE11-AE10 -> 0 | AG11: =AG10 -> 2217.83 | AH11: =AG11-AG10 -> 0 | AI11: =AF11+AH11 -> 0 | AJ11: =+Z11-Z10 -> 0 | AK11: =SUM(Y11-L11) -> 0 | AL11: =SUM(AJ11-W11) -> 0 | AM11: ='General information '!D10 -> 19 | AN11: ='General information '!H10 -> 0 | AP11: ='General information '!J10 -> 0 | AR11: =A11 -> 44536 | AS11: =AS10 -> 0.9 | AT11: =AT10 -> 186 | AU11: =AU10 -> 1.1 | AV11: =AV10 -> 135 | AW11: 2.9 | AX11: 96 | AY11: =AS11*AT11 -> 167.4 | AZ11: =AU11*AV11 -> 148.5 | BA11: =AW11*AX11 -> 278.4 | BB11: =AY11-AY10 -> 0 | BC11: =AZ11-AZ10 -> 0 | BD11: =BA11-BA10 -> -2.9 | BE11: =SUM(BB11:BD11) -> -2.9 | BF11: =SUM(I11-BE11) -> 2.9 | BG11: =SUM(I11-BF11) -> -2.9
A12: =ELEC!C10 -> 44537 | B12: =B11 -> 109443 | C12: =B12-B11 -> 0 | D12: =C12/27 -> 0 | E12: =SUM((C12*$E$4)+(7500/'EDl log'!$A$37)) -> 241.93548 | G12: =G11 -> 626138 | H12: =G12-G11 -> 0 | I12: =C12+H12 -> 0 | J12: =IF(I12>0,E12/I12,0) -> 0 | K12: ='Swimming Pool quality check '!H12 -> 6960 | L12: =K12-K11 -> 0 | M12: =M11 -> 457.44 | N12: =SUM(M12-M11) -> 0 | O12: =O11 -> 529.52 | P12: =SUM(O12-O11) -> 0 | Q12: =SUM(P12+N12) -> 0 | T12: =T11 -> 5180 | U12: =SUM(T12-T11) -> 0 | V12: =V11 -> 477 | W12: =+V12-V11 -> 0 | X12: =X11 -> 154335 | Y12: =SUM(X12-X11) -> 0 | Z12: =Z11 -> 99258 | AA12: =Z12-Z11 -> 0 | AB12: =AB11 -> 248 | AC12: =AC11 -> 789 | AD12: =AC12-AC11 -> 0 | AE12: =AE11 -> 239.1 | AF12: =AE12-AE11 -> 0 | AG12: =AG11 -> 2217.83 | AH12: =AG12-AG11 -> 0 | AI12: =AF12+AH12 -> 0 | AJ12: =+Z12-Z11 -> 0 | AK12: =SUM(Y12-L12) -> 0 | AL12: =SUM(AJ12-W12) -> 0 | AM12: ='General information '!D11 -> 19.5 | AN12: ='General information '!H11 -> 0 | AP12: ='General information '!J11 -> 0 | AR12: =A12 -> 44537 | AS12: =AS11 -> 0.9 | AT12: 184 | AU12: =AU11 -> 1.1 | AV12: 134 | AW12: 2.9 | AX12: 94 | AY12: =AS12*AT12 -> 165.6 | AZ12: =AU12*AV12 -> 147.4 | BA12: =AW12*AX12 -> 272.6 | BB12: =AY12-AY11 -> -1.8 | BC12: =AZ12-AZ11 -> -1.1 | BD12: =BA12-BA11 -> -5.8 | BE12: =SUM(BB12:BD12) -> -8.7 | BF12: =SUM(I12-BE12) -> 8.7 | BG12: =SUM(I12-BF12) -> -8.7
A13: =ELEC!C11 -> 44538 | B13: =B12 -> 109443 | C13: =B13-B12 -> 0 | D13: =C13/27 -> 0 | E13: =SUM((C13*$E$4)+(7500/'EDl log'!$A$37)) -> 241.93548 | G13: =G12 -> 626138 | H13: =G13-G12 -> 0 | I13: =C13+H13 -> 0 | J13: =IF(I13>0,E13/I13,0) -> 0 | K13: ='Swimming Pool quality check '!H13 -> 6960 | L13: =K13-K12 -> 0 | M13: =M12 -> 457.44 | N13: =SUM(M13-M12) -> 0 | O13: =O12 -> 529.52 | P13: =SUM(O13-O12) -> 0 | Q13: =SUM(P13+N13) -> 0 | T13: =T12 -> 5180 | U13: =SUM(T13-T12) -> 0 | V13: =V12 -> 477 | W13: =+V13-V12 -> 0 | X13: =X12 -> 154335 | Y13: =SUM(X13-X12) -> 0 | Z13: =Z12 -> 99258 | AA13: =Z13-Z12 -> 0 | AB13: =AB12 -> 248 | AC13: =AC12 -> 789 | AD13: =AC13-AC12 -> 0 | AE13: =AE12 -> 239.1 | AF13: =AE13-AE12 -> 0 | AG13: =AG12 -> 2217.83 | AH13: =AG13-AG12 -> 0 | AI13: =AF13+AH13 -> 0 | AJ13: =+Z13-Z12 -> 0 | AK13: =SUM(Y13-L13) -> 0 | AL13: =SUM(AJ13-W13) -> 0 | AM13: ='General information '!D12 -> 16.5 | AN13: ='General information '!J12 -> 0 | AP13: ='General information '!J12 -> 0 | AR13: =A13 -> 44538 | AS13: =AS12 -> 0.9 | AT13: =AT12 -> 184 | AU13: =AU12 -> 1.1 | AV13: =AV12 -> 134 | AW13: 2.9 | AX13: 84 | AY13: =AS13*AT13 -> 165.6 | AZ13: =AU13*AV13 -> 147.4 | BA13: =AW13*AX13 -> 243.6 | BB13: =AY13-AY12 -> 0 | BC13: =AZ13-AZ12 -> 0 | BD13: =BA13-BA12 -> -29 | BE13: =SUM(BB13:BD13) -> -29 | BF13: =SUM(I13-BE13) -> 29 | BG13: =SUM(I13-BF13) -> -29
A14: =ELEC!C12 -> 44539 | B14: =B13 -> 109443 | C14: =B14-B13 -> 0 | D14: =C14/27 -> 0 | E14: =SUM((C14*$E$4)+(7500/'EDl log'!$A$37)) -> 241.93548 | G14: 626308 | H14: =G14-G13 -> 170 | I14: =C14+H14 -> 170 | J14: =IF(I14>0,E14/I14,0) -> 1.4231499 | K14: ='Swimming Pool quality check '!H14 -> 6966 | L14: =K14-K13 -> 6 | M14: =M13 -> 457.44 | N14: =SUM(M14-M13) -> 0 | O14: =O13 -> 529.52 | P14: =SUM(O14-O13) -> 0 | Q14: =SUM(P14+N14) -> 0 | T14: =T13 -> 5180 | U14: =SUM(T14-T13) -> 0 | V14: =V13 -> 477 | W14: =+V14-V13 -> 0 | X14: 154481 | Y14: =SUM(X14-X13) -> 146 | Z14: =Z13 -> 99258 | AA14: =Z14-Z13 -> 0 | AB14: =AB13 -> 248 | AC14: =AC13 -> 789 | AD14: =AC14-AC13 -> 0 | AE14: =AE13 -> 239.1 | AF14: =AE14-AE13 -> 0 | AG14: =AG13 -> 2217.83 | AH14: =AG14-AG13 -> 0 | AI14: =AF14+AH14 -> 0 | AJ14: =+Z14-Z13 -> 0 | AK14: =SUM(Y14-L14) -> 140 | AL14: =SUM(AJ14-W14) -> 0 | AM14: ='General information '!D13 -> 17 | AN14: ='General information '!H13 -> 0 | AP14: ='General information '!J13 -> 0 | AR14: =A14 -> 44539 | AS14: =AS13 -> 0.9 | AT14: 114 | AU14: =AU13 -> 1.1 | AV14: 132 | AW14: 2.9 | AX14: 124 | AY14: =AS14*AT14 -> 102.6 | AZ14: =AU14*AV14 -> 145.2 | BA14: =AW14*AX14 -> 359.6 | BB14: =AY14-AY13 -> -63 | BC14: =AZ14-AZ13 -> -2.2 | BD14: =BA14-BA13 -> 116 | BE14: =SUM(BB14:BD14) -> 50.8 | BF14: =SUM(I14-BE14) -> 119.2 | BG14: =SUM(I14-BF14) -> 50.8
A15: =ELEC!C13 -> 44540 | B15: =B14 -> 109443 | C15: =B15-B14 -> 0 | D15: =C15/27 -> 0 | E15: =SUM((C15*$E$4)+(7500/'EDl log'!$A$37)) -> 241.93548 | G15: =G14 -> 626308 | H15: =G15-G14 -> 0 | I15: =C15+H15 -> 0 | J15: =IF(I15>0,E15/I15,0) -> 0 | K15: ='Swimming Pool quality check '!H15 -> 6966 | L15: =K15-K14 -> 0 | M15: =M14 -> 457.44 | N15: =SUM(M15-M14) -> 0 | O15: =O14 -> 529.52 | P15: =SUM(O15-O14) -> 0 | Q15: =SUM(P15+N15) -> 0 | T15: =T14 -> 5180 | U15: =SUM(T15-T14) -> 0 | V15: =V14 -> 477 | W15: =+V15-V14 -> 0 | X15: =X14 -> 154481 | Y15: =SUM(X15-X14) -> 0 | Z15: =Z14 -> 99258 | AA15: =Z15-Z14 -> 0 | AB15: =AB14 -> 248 | AC15: =AC14 -> 789 | AD15: =AC15-AC14 -> 0 | AE15: =AE14 -> 239.1 | AF15: =AE15-AE14 -> 0 | AG15: =AG14 -> 2217.83 | AH15: =AG15-AG14 -> 0 | AI15: =AF15+AH15 -> 0 | AJ15: =+Z15-Z14 -> 0 | AK15: =SUM(Y15-L15) -> 0 | AL15: =SUM(AJ15-W15) -> 0 | AM15: ='General information '!D14 -> 0 | AN15: ='General information '!H14 -> 0 | AP15: ='General information '!J14 -> 0 | AR15: =A15 -> 44540 | AS15: =AS14 -> 0.9 | AT15: =AT14 -> 114 | AU15: =AU14 -> 1.1 | AV15: =AV14 -> 132 | AW15: 2.9 | AX15: =AX14 -> 124 | AY15: =AS15*AT15 -> 102.6 | AZ15: =AU15*AV15 -> 145.2 | BA15: =AW15*AX15 -> 359.6 | BB15: =AY15-AY14 -> 0 | BC15: =AZ15-AZ14 -> 0 | BD15: =BA15-BA14 -> 0 | BE15: =SUM(BB15:BD15) -> 0 | BF15: =SUM(I15-BE15) -> 0 | BG15: =SUM(I15-BF15) -> 0
A16: =ELEC!C14 -> 44541 | B16: =B15 -> 109443 | C16: =B16-B15 -> 0 | D16: =C16/27 -> 0 | E16: =SUM((C16*$E$4)+(7500/'EDl log'!$A$37)) -> 241.93548 | G16: =G15 -> 626308 | H16: =G16-G15 -> 0 | I16: =C16+H16 -> 0 | J16: =IF(I16>0,E16/I16,0) -> 0 | K16: ='Swimming Pool quality check '!H16 -> 6966 | L16: =K16-K15 -> 0 | M16: =M15 -> 457.44 | N16: =SUM(M16-M15) -> 0 | O16: =O15 -> 529.52 | P16: =SUM(O16-O15) -> 0 | Q16: =SUM(P16+N16) -> 0 | T16: =T15 -> 5180 | U16: =SUM(T16-T15) -> 0 | V16: =V15 -> 477 | W16: =+V16-V15 -> 0 | X16: =X15 -> 154481 | Y16: =SUM(X16-X15) -> 0 | Z16: =Z15 -> 99258 | AA16: =Z16-Z15 -> 0 | AB16: =AB15 -> 248 | AC16: =AC15 -> 789 | AD16: =AC16-AC15 -> 0 | AE16: =AE15 -> 239.1 | AF16: =AE16-AE15 -> 0 | AG16: =AG15 -> 2217.83 | AH16: =AG16-AG15 -> 0 | AI16: =AF16+AH16 -> 0 | AJ16: =+Z16-Z15 -> 0 | AK16: =SUM(Y16-L16) -> 0 | AL16: =SUM(AJ16-W16) -> 0 | AM16: ='General information '!D15 -> 0 | AN16: ='General information '!H15 -> 0 | AP16: ='General information '!J15 -> 0 | AR16: =A16 -> 44541 | AS16: =AS15 -> 0.9 | AT16: =AT15 -> 114 | AU16: =AU15 -> 1.1 | AV16: =AV15 -> 132 | AW16: 2.9 | AX16: =AX15 -> 124 | AY16: =AS16*AT16 -> 102.6 | AZ16: =AU16*AV16 -> 145.2 | BA16: =AW16*AX16 -> 359.6 | BB16: =AY16-AY15 -> 0 | BC16: =AZ16-AZ15 -> 0 | BD16: =BA16-BA15 -> 0 | BE16: =SUM(BB16:BD16) -> 0 | BF16: =SUM(I16-BE16) -> 0 | BG16: =SUM(I16-BF16) -> 0
A17: =ELEC!C15 -> 44542 | B17: =B16 -> 109443 | C17: =B17-B16 -> 0 | D17: =C17/27 -> 0 | E17: =SUM((C17*$E$4)+(7500/'EDl log'!$A$37)) -> 241.93548 | G17: 626310 | H17: =G17-G16 -> 2 | I17: =C17+H17 -> 2 | J17: =IF(I17>0,E17/I17,0) -> 120.96774 | K17: ='Swimming Pool quality check '!H17 -> 6967 | L17: =K17-K16 -> 1 | M17: =M16 -> 457.44 | N17: =SUM(M17-M16) -> 0 | O17: =O16 -> 529.52 | P17: =SUM(O17-O16) -> 0 | Q17: =SUM(P17+N17) -> 0 | T17: =T16 -> 5180 | U17: =SUM(T17-T16) -> 0 | V17: =V16 -> 477 | W17: =+V17-V16 -> 0 | X17: =X16 -> 154481 | Y17: =SUM(X17-X16) -> 0 | Z17: =Z16 -> 99258 | AA17: =Z17-Z16 -> 0 | AB17: =AB16 -> 248 | AC17: =AC16 -> 789 | AD17: =AC17-AC16 -> 0 | AE17: =AE16 -> 239.1 | AF17: =AE17-AE16 -> 0 | AG17: =AG16 -> 2217.83 | AH17: =AG17-AG16 -> 0 | AI17: =AF17+AH17 -> 0 | AJ17: =+Z17-Z16 -> 0 | AK17: =SUM(Y17-L17) -> -1 | AL17: =SUM(AJ17-W17) -> 0 | AM17: ='General information '!D16 -> 18.5 | AN17: ='General information '!H16 -> 0 | AP17: ='General information '!J16 -> 0 | AR17: =A17 -> 44542 | AS17: =AS16 -> 0.9 | AT17: 117 | AU17: =AU16 -> 1.1 | AV17: 131 | AW17: 2.9 | AX17: 122 | AY17: =AS17*AT17 -> 105.3 | AZ17: =AU17*AV17 -> 144.1 | BA17: =AW17*AX17 -> 353.8 | BB17: =AY17-AY16 -> 2.7 | BC17: =AZ17-AZ16 -> -1.1 | BD17: =BA17-BA16 -> -5.8 | BE17: =SUM(BB17:BD17) -> -4.2 | BF17: =SUM(I17-BE17) -> 6.2 | BG17: =SUM(I17-BF17) -> -4.2
A18: =ELEC!C16 -> 44543 | B18: =B17 -> 109443 | C18: =B18-B17 -> 0 | D18: =C18/27 -> 0 | E18: =SUM((C18*$E$4)+(7500/'EDl log'!$A$37)) -> 241.93548 | G18: =G17 -> 626310 | H18: =G18-G17 -> 0 | I18: =C18+H18 -> 0 | J18: =IF(I18>0,E18/I18,0) -> 0 | K18: ='Swimming Pool quality check '!H18 -> 6967 | L18: =K18-K17 -> 0 | M18: =M17 -> 457.44 | N18: =SUM(M18-M17) -> 0 | O18: =O17 -> 529.52 | P18: =SUM(O18-O17) -> 0 | Q18: =SUM(P18+N18) -> 0 | T18: =T17 -> 5180 | U18: =SUM(T18-T17) -> 0 | V18: =V17 -> 477 | W18: =+V18-V17 -> 0 | X18: =X17 -> 154481 | Y18: =SUM(X18-X17) -> 0 | Z18: =Z17 -> 99258 | AA18: =Z18-Z17 -> 0 | AB18: =AB17 -> 248 | AC18: =AC17 -> 789 | AD18: =AC18-AC17 -> 0 | AE18: =AE17 -> 239.1 | AF18: =AE18-AE17 -> 0 | AG18: =AG17 -> 2217.83 | AH18: =AG18-AG17 -> 0 | AI18: =AF18+AH18 -> 0 | AJ18: =+Z18-Z17 -> 0 | AK18: =SUM(Y18-L18) -> 0 | AL18: =SUM(AJ18-W18) -> 0 | AM18: ='General information '!D17 -> 20 | AN18: ='General information '!H17 -> 0 | AP18: ='General information '!J17 -> 0 | AR18: =A18 -> 44543 | AS18: =AS17 -> 0.9 | AT18: =AT17 -> 117 | AU18: =AU17 -> 1.1 | AV18: 130 | AW18: 2.9 | AX18: 120 | AY18: =AS18*AT18 -> 105.3 | AZ18: =AU18*AV18 -> 143 | BA18: =AW18*AX18 -> 348 | BB18: =AY18-AY17 -> 0 | BC18: =AZ18-AZ17 -> -1.1 | BD18: =BA18-BA17 -> -5.8 | BE18: =SUM(BB18:BD18) -> -6.9 | BF18: =SUM(I18-BE18) -> 6.9 | BG18: =SUM(I18-BF18) -> -6.9
A19: =ELEC!C17 -> 44544 | B19: =B18 -> 109443 | C19: =B19-B18 -> 0 | D19: =C19/27 -> 0 | E19: =SUM((C19*$E$4)+(7500/'EDl log'!$A$37)) -> 241.93548 | G19: =G18 -> 626310 | H19: =G19-G18 -> 0 | I19: =C19+H19 -> 0 | J19: =IF(I19>0,E19/I19,0) -> 0 | K19: ='Swimming Pool quality check '!H19 -> 6968 | L19: =K19-K18 -> 1 | M19: =M18 -> 457.44 | N19: =SUM(M19-M18) -> 0 | O19: =O18 -> 529.52 | P19: =SUM(O19-O18) -> 0 | Q19: =SUM(P19+N19) -> 0 | T19: =T18 -> 5180 | U19: =SUM(T19-T18) -> 0 | V19: =V18 -> 477 | W19: =+V19-V18 -> 0 | X19: =X18 -> 154481 | Y19: =SUM(X19-X18) -> 0 | Z19: =Z18 -> 99258 | AA19: =Z19-Z18 -> 0 | AB19: =AB18 -> 248 | AC19: =AC18 -> 789 | AD19: =AC19-AC18 -> 0 | AE19: =AE18 -> 239.1 | AF19: =AE19-AE18 -> 0 | AG19: =AG18 -> 2217.83 | AH19: =AG19-AG18 -> 0 | AI19: =AF19+AH19 -> 0 | AJ19: =+Z19-Z18 -> 0 | AK19: =SUM(Y19-L19) -> -1 | AL19: =SUM(AJ19-W19) -> 0 | AM19: ='General information '!D18 -> 19 | AN19: ='General information '!H18 -> 0 | AP19: ='General information '!J18 -> 0 | AR19: =A19 -> 44544 | AS19: =AS18 -> 0.9 | AT19: 181 | AU19: =AU18 -> 1.1 | AV19: 129 | AW19: 2.9 | AX19: 119 | AY19: =AS19*AT19 -> 162.9 | AZ19: =AU19*AV19 -> 141.9 | BA19: =AW19*AX19 -> 345.1 | BB19: =AY19-AY18 -> 57.6 | BC19: =AZ19-AZ18 -> -1.1 | BD19: =BA19-BA18 -> -2.9 | BE19: =SUM(BB19:BD19) -> 53.6 | BF19: =SUM(I19-BE19) -> -53.6 | BG19: =SUM(I19-BF19) -> 53.6
A20: =ELEC!C18 -> 44545 | B20: =B19 -> 109443 | C20: =B20-B19 -> 0 | D20: =C20/27 -> 0 | E20: =SUM((C20*$E$4)+(7500/'EDl log'!$A$37)) -> 241.93548 | G20: =G19 -> 626310 | H20: =G20-G19 -> 0 | I20: =C20+H20 -> 0 | J20: =IF(I20>0,E20/I20,0) -> 0 | K20: ='Swimming Pool quality check '!H20 -> 6969 | L20: =K20-K19 -> 1 | M20: =M19 -> 457.44 | N20: =SUM(M20-M19) -> 0 | O20: =O19 -> 529.52 | P20: =SUM(O20-O19) -> 0 | Q20: =SUM(P20+N20) -> 0 | T20: =T19 -> 5180 | U20: =SUM(T20-T19) -> 0 | V20: =V19 -> 477 | W20: =+V20-V19 -> 0 | X20: =X19 -> 154481 | Y20: =SUM(X20-X19) -> 0 | Z20: =Z19 -> 99258 | AA20: =Z20-Z19 -> 0 | AB20: =AB19 -> 248 | AC20: =AC19 -> 789 | AD20: =AC20-AC19 -> 0 | AE20: =AE19 -> 239.1 | AF20: =AE20-AE19 -> 0 | AG20: =AG19 -> 2217.83 | AH20: =AG20-AG19 -> 0 | AI20: =AF20+AH20 -> 0 | AJ20: =+Z20-Z19 -> 0 | AK20: =SUM(Y20-L20) -> -1 | AL20: =SUM(AJ20-W20) -> 0 | AM20: ='General information '!D19 -> 18 | AN20: ='General information '!H19 -> 0 | AP20: ='General information '!J19 -> 0 | AR20: =A20 -> 44545 | AS20: =AS19 -> 0.9 | AT20: =AT19 -> 181 | AU20: =AU19 -> 1.1 | AV20: 127 | AW20: 2.9 | AX20: 118 | AY20: =AS20*AT20 -> 162.9 | AZ20: =AU20*AV20 -> 139.7 | BA20: =AW20*AX20 -> 342.2 | BB20: =AY20-AY19 -> 0 | BC20: =AZ20-AZ19 -> -2.2 | BD20: =BA20-BA19 -> -2.9 | BE20: =SUM(BB20:BD20) -> -5.1 | BF20: =SUM(I20-BE20) -> 5.1 | BG20: =SUM(I20-BF20) -> -5.1
A21: =ELEC!C19 -> 44546 | B21: =B20 -> 109443 | C21: =B21-B20 -> 0 | D21: =C21/27 -> 0 | E21: =SUM((C21*$E$4)+(7500/'EDl log'!$A$37)) -> 241.93548 | G21: =G20 -> 626310 | H21: =G21-G20 -> 0 | I21: =C21+H21 -> 0 | J21: =IF(I21>0,E21/I21,0) -> 0 | K21: ='Swimming Pool quality check '!H21 -> 6969 | L21: =K21-K20 -> 0 | M21: =M20 -> 457.44 | N21: =SUM(M21-M20) -> 0 | O21: =O20 -> 529.52 | P21: =SUM(O21-O20) -> 0 | Q21: =SUM(P21+N21) -> 0 | T21: =T20 -> 5180 | U21: =SUM(T21-T20) -> 0 | V21: =V20 -> 477 | W21: =+V21-V20 -> 0 | X21: =X20 -> 154481 | Y21: =SUM(X21-X20) -> 0 | Z21: =Z20 -> 99258 | AA21: =Z21-Z20 -> 0 | AB21: =AB20 -> 248 | AC21: =AC20 -> 789 | AD21: =AC21-AC20 -> 0 | AE21: =AE20 -> 239.1 | AF21: =AE21-AE20 -> 0 | AG21: =AG20 -> 2217.83 | AH21: =AG21-AG20 -> 0 | AI21: =AF21+AH21 -> 0 | AJ21: =+Z21-Z20 -> 0 | AK21: =SUM(Y21-L21) -> 0 | AL21: =SUM(AJ21-W21) -> 0 | AM21: ='General information '!D20 -> 15.5 | AN21: ='General information '!H20 -> 0 | AP21: ='General information '!J20 -> 0 | AR21: =A21 -> 44546 | AS21: =AS20 -> 0.9 | AT21: =AT20 -> 181 | AU21: =AU20 -> 1.1 | AV21: =AV20 -> 127 | AW21: 2.9 | AX21: 119 | AY21: =AS21*AT21 -> 162.9 | AZ21: =AU21*AV21 -> 139.7 | BA21: =AW21*AX21 -> 345.1 | BB21: =AY21-AY20 -> 0 | BC21: =AZ21-AZ20 -> 0 | BD21: =BA21-BA20 -> 2.9 | BE21: =SUM(BB21:BD21) -> 2.9 | BF21: =SUM(I21-BE21) -> -2.9 | BG21: =SUM(I21-BF21) -> 2.9
A22: =ELEC!C20 -> 44547 | B22: =B21 -> 109443 | C22: =B22-B21 -> 0 | D22: =C22/27 -> 0 | E22: =SUM((C22*$E$4)+(7500/'EDl log'!$A$37)) -> 241.93548 | G22: =G21 -> 626310 | H22: =G22-G21 -> 0 | I22: =C22+H22 -> 0 | J22: =IF(I22>0,E22/I22,0) -> 0 | K22: ='Swimming Pool quality check '!H22 -> 6969 | L22: =K22-K21 -> 0 | M22: =M21 -> 457.44 | N22: =SUM(M22-M21) -> 0 | O22: =O21 -> 529.52 | P22: =SUM(O22-O21) -> 0 | Q22: =SUM(P22+N22) -> 0 | T22: =T21 -> 5180 | U22: =SUM(T22-T21) -> 0 | V22: =V21 -> 477 | W22: =+V22-V21 -> 0 | X22: =X21 -> 154481 | Y22: =SUM(X22-X21) -> 0 | Z22: =Z21 -> 99258 | AA22: =Z22-Z21 -> 0 | AB22: =AB21 -> 248 | AC22: =AC21 -> 789 | AD22: =AC22-AC21 -> 0 | AE22: =AE21 -> 239.1 | AF22: =AE22-AE21 -> 0 | AG22: =AG21 -> 2217.83 | AH22: =AG22-AG21 -> 0 | AI22: =AF22+AH22 -> 0 | AJ22: =+Z22-Z21 -> 0 | AK22: =SUM(Y22-L22) -> 0 | AL22: =SUM(AJ22-W22) -> 0 | AM22: ='General information '!D21 -> 0 | AN22: ='General information '!H21 -> 0 | AP22: ='General information '!J21 -> 0 | AR22: =A22 -> 44547 | AS22: =AS21 -> 0.9 | AT22: =AT21 -> 181 | AU22: =AU21 -> 1.1 | AV22: =AV21 -> 127 | AW22: 2.9 | AX22: =AX21 -> 119 | AY22: =AS22*AT22 -> 162.9 | AZ22: =AU22*AV22 -> 139.7 | BA22: =AW22*AX22 -> 345.1 | BB22: =AY22-AY21 -> 0 | BC22: =AZ22-AZ21 -> 0 | BD22: =BA22-BA21 -> 0 | BE22: =SUM(BB22:BD22) -> 0 | BF22: =SUM(I22-BE22) -> 0 | BG22: =SUM(I22-BF22) -> 0
A23: =ELEC!C21 -> 44548 | B23: =B22 -> 109443 | C23: =B23-B22 -> 0 | D23: =C23/27 -> 0 | E23: =SUM((C23*$E$4)+(7500/'EDl log'!$A$37)) -> 241.93548 | G23: =G22 -> 626310 | H23: =G23-G22 -> 0 | I23: =C23+H23 -> 0 | J23: =IF(I23>0,E23/I23,0) -> 0 | K23: ='Swimming Pool quality check '!H23 -> 6969 | L23: =K23-K22 -> 0 | M23: =M22 -> 457.44 | N23: =SUM(M23-M22) -> 0 | O23: =O22 -> 529.52 | P23: =SUM(O23-O22) -> 0 | Q23: =SUM(P23+N23) -> 0 | T23: =T22 -> 5180 | U23: =SUM(T23-T22) -> 0 | V23: =V22 -> 477 | W23: =+V23-V22 -> 0 | X23: =X22 -> 154481 | Y23: =SUM(X23-X22) -> 0 | Z23: =Z22 -> 99258 | AA23: =Z23-Z22 -> 0 | AB23: =AB22 -> 248 | AC23: =AC22 -> 789 | AD23: =AC23-AC22 -> 0 | AE23: =AE22 -> 239.1 | AF23: =AE23-AE22 -> 0 | AG23: =AG22 -> 2217.83 | AH23: =AG23-AG22 -> 0 | AI23: =AF23+AH23 -> 0 | AJ23: =+Z23-Z22 -> 0 | AK23: =SUM(Y23-L23) -> 0 | AL23: =SUM(AJ23-W23) -> 0 | AM23: ='General information '!D22 -> 0 | AN23: ='General information '!H22 -> 0 | AP23: ='General information '!J22 -> 0 | AR23: =A23 -> 44548 | AS23: =AS22 -> 0.9 | AT23: =AT22 -> 181 | AU23: =AU22 -> 1.1 | AV23: =AV22 -> 127 | AW23: 2.9 | AX23: =AX22 -> 119 | AY23: =AS23*AT23 -> 162.9 | AZ23: =AU23*AV23 -> 139.7 | BA23: =AW23*AX23 -> 345.1 | BB23: =AY23-AY22 -> 0 | BC23: =AZ23-AZ22 -> 0 | BD23: =BA23-BA22 -> 0 | BE23: =SUM(BB23:BD23) -> 0 | BF23: =SUM(I23-BE23) -> 0 | BG23: =SUM(I23-BF23) -> 0
A24: =ELEC!C22 -> 44549 | B24: =B23 -> 109443 | C24: =B24-B23 -> 0 | D24: =C24/27 -> 0 | E24: =SUM((C24*$E$4)+(7500/'EDl log'!$A$37)) -> 241.93548 | G24: =G23 -> 626310 | H24: =G24-G23 -> 0 | I24: =C24+H24 -> 0 | J24: =IF(I24>0,E24/I24,0) -> 0 | K24: ='Swimming Pool quality check '!H24 -> 6969 | L24: =K24-K23 -> 0 | M24: =M23 -> 457.44 | N24: =SUM(M24-M23) -> 0 | O24: =O23 -> 529.52 | P24: =SUM(O24-O23) -> 0 | Q24: =SUM(P24+N24) -> 0 | T24: =T23 -> 5180 | U24: =SUM(T24-T23) -> 0 | V24: =V23 -> 477 | W24: =+V24-V23 -> 0 | X24: =X23 -> 154481 | Y24: =SUM(X24-X23) -> 0 | Z24: =Z23 -> 99258 | AA24: =Z24-Z23 -> 0 | AB24: =AB23 -> 248 | AC24: =AC23 -> 789 | AD24: =AC24-AC23 -> 0 | AE24: =AE23 -> 239.1 | AF24: =AE24-AE23 -> 0 | AG24: =AG23 -> 2217.83 | AH24: =AG24-AG23 -> 0 | AI24: =AF24+AH24 -> 0 | AJ24: =+Z24-Z23 -> 0 | AK24: =SUM(Y24-L24) -> 0 | AL24: =SUM(AJ24-W24) -> 0 | AM24: ='General information '!D23 -> 16.5 | AN24: ='[3]General information '!H24 -> 0 | AP24: ='[3]General information '!J24 -> 0 | AR24: =A24 -> 44549 | AS24: =AS23 -> 0.9 | AT24: =AT23 -> 181 | AU24: =AU23 -> 1.1 | AV24: 126 | AW24: 2.9 | AX24: 110 | AY24: =AS24*AT24 -> 162.9 | AZ24: =AU24*AV24 -> 138.6 | BA24: =AW24*AX24 -> 319 | BB24: =AY24-AY23 -> 0 | BC24: =AZ24-AZ23 -> -1.1 | BD24: =BA24-BA23 -> -26.1 | BE24: =SUM(BB24:BD24) -> -27.2 | BF24: =SUM(I24-BE24) -> 27.2 | BG24: =SUM(I24-BF24) -> -27.2
A25: =ELEC!C23 -> 44550 | B25: =B24 -> 109443 | C25: =B25-B24 -> 0 | D25: =C25/27 -> 0 | E25: =SUM((C25*$E$4)+(7500/'EDl log'!$A$37)) -> 241.93548 | G25: =G24 -> 626310 | H25: =G25-G24 -> 0 | I25: =C25+H25 -> 0 | J25: =IF(I25>0,E25/I25,0) -> 0 | K25: ='Swimming Pool quality check '!H25 -> 6971 | L25: =K25-K24 -> 2 | M25: =M24 -> 457.44 | N25: =SUM(M25-M24) -> 0 | O25: =O24 -> 529.52 | P25: =SUM(O25-O24) -> 0 | Q25: =SUM(P25+N25) -> 0 | T25: =T24 -> 5180 | U25: =SUM(T25-T24) -> 0 | V25: =V24 -> 477 | W25: =+V25-V24 -> 0 | X25: =X24 -> 154481 | Y25: =SUM(X25-X24) -> 0 | Z25: =Z24 -> 99258 | AA25: =Z25-Z24 -> 0 | AB25: =AB24 -> 248 | AC25: =AC24 -> 789 | AD25: =AC25-AC24 -> 0 | AE25: =AE24 -> 239.1 | AF25: =AE25-AE24 -> 0 | AG25: =AG24 -> 2217.83 | AH25: =AG25-AG24 -> 0 | AI25: =AF25+AH25 -> 0 | AJ25: =+Z25-Z24 -> 0 | AK25: =SUM(Y25-L25) -> -2 | AL25: =SUM(AJ25-W25) -> 0 | AM25: ='General information '!D24 -> 13 | AN25: ='General information '!H24 -> 0 | AP25: ='General information '!J24 -> 0 | AR25: =A25 -> 44550 | AS25: =AS24 -> 0.9 | AT25: =AT24 -> 181 | AU25: =AU24 -> 1.1 | AV25: =AV24 -> 126 | AW25: 2.9 | AX25: 109 | AY25: =AS25*AT25 -> 162.9 | AZ25: =AU25*AV25 -> 138.6 | BA25: =AW25*AX25 -> 316.1 | BB25: =AY25-AY24 -> 0 | BC25: =AZ25-AZ24 -> 0 | BD25: =BA25-BA24 -> -2.9 | BE25: =SUM(BB25:BD25) -> -2.9 | BF25: =SUM(I25-BE25) -> 2.9 | BG25: =SUM(I25-BF25) -> -2.9
A26: =ELEC!C24 -> 44551 | B26: =B25 -> 109443 | C26: =B26-B25 -> 0 | D26: =C26/27 -> 0 | E26: =SUM((C26*$E$4)+(7500/'EDl log'!$A$37)) -> 241.93548 | G26: =G25 -> 626310 | H26: =G26-G25 -> 0 | I26: =C26+H26 -> 0 | J26: =IF(I26>0,E26/I26,0) -> 0 | K26: ='Swimming Pool quality check '!H26 -> 6971 | L26: =K26-K25 -> 0 | M26: =M25 -> 457.44 | N26: =SUM(M26-M25) -> 0 | O26: =O25 -> 529.52 | P26: =SUM(O26-O25) -> 0 | Q26: =SUM(P26+N26) -> 0 | T26: =T25 -> 5180 | U26: =SUM(T26-T25) -> 0 | V26: =V25 -> 477 | W26: =+V26-V25 -> 0 | X26: =X25 -> 154481 | Y26: =SUM(X26-X25) -> 0 | Z26: =Z25 -> 99258 | AA26: =Z26-Z25 -> 0 | AB26: =AB25 -> 248 | AC26: =AC25 -> 789 | AD26: =AC26-AC25 -> 0 | AE26: =AE25 -> 239.1 | AF26: =AE26-AE25 -> 0 | AG26: =AG25 -> 2217.83 | AH26: =AG26-AG25 -> 0 | AI26: =AF26+AH26 -> 0 | AJ26: =+Z26-Z25 -> 0 | AK26: =SUM(Y26-L26) -> 0 | AL26: =SUM(AJ26-W26) -> 0 | AM26: ='General information '!D25 -> 16 | AN26: ='General information '!H25 -> 0 | AP26: ='General information '!J25 -> 0 | AR26: =A26 -> 44551 | AS26: =AS25 -> 0.9 | AT26: 181 | AU26: =AU25 -> 1.1 | AV26: 126 | AW26: 2.9 | AX26: 107 | AY26: =AS26*AT26 -> 162.9 | AZ26: =AU26*AV26 -> 138.6 | BA26: =AW26*AX26 -> 310.3 | BB26: =AY26-AY25 -> 0 | BC26: =AZ26-AZ25 -> 0 | BD26: =BA26-BA25 -> -5.8 | BE26: =SUM(BB26:BD26) -> -5.8 | BF26: =SUM(I26-BE26) -> 5.8 | BG26: =SUM(I26-BF26) -> -5.8
A27: =ELEC!C25 -> 44552 | B27: =B26 -> 109443 | C27: =B27-B26 -> 0 | D27: =C27/27 -> 0 | E27: =SUM((C27*$E$4)+(7500/'EDl log'!$A$37)) -> 241.93548 | G27: =G26 -> 626310 | H27: =G27-G26 -> 0 | I27: =C27+H27 -> 0 | J27: =IF(I27>0,E27/I27,0) -> 0 | K27: ='Swimming Pool quality check '!H27 -> 6971 | L27: =K27-K26 -> 0 | M27: =M26 -> 457.44 | N27: =SUM(M27-M26) -> 0 | O27: =O26 -> 529.52 | P27: =SUM(O27-O26) -> 0 | Q27: =SUM(P27+N27) -> 0 | T27: 5180 | U27: =SUM(T27-T26) -> 0 | V27: =V26 -> 477 | W27: =+V27-V26 -> 0 | X27: =X26 -> 154481 | Y27: =SUM(X27-X26) -> 0 | Z27: =Z26 -> 99258 | AA27: =Z27-Z26 -> 0 | AB27: =AB26 -> 248 | AC27: =AC26 -> 789 | AD27: =AC27-AC26 -> 0 | AE27: =AE26 -> 239.1 | AF27: =AE27-AE26 -> 0 | AG27: =AG26 -> 2217.83 | AH27: =AG27-AG26 -> 0 | AI27: =AF27+AH27 -> 0 | AJ27: =+Z27-Z26 -> 0 | AK27: =SUM(Y27-L27) -> 0 | AL27: =SUM(AJ27-W27) -> 0 | AM27: ='General information '!D26 -> 14.5 | AN27: ='General information '!H26 -> 0 | AP27: ='General information '!J26 -> 0 | AR27: =A27 -> 44552 | AS27: =AS26 -> 0.9 | AT27: =AT26 -> 181 | AU27: =AU26 -> 1.1 | AV27: 125 | AW27: 2.9 | AX27: 105 | AY27: =AS27*AT27 -> 162.9 | AZ27: =AU27*AV27 -> 137.5 | BA27: =AW27*AX27 -> 304.5 | BB27: =AY27-AY26 -> 0 | BC27: =AZ27-AZ26 -> -1.1 | BD27: =BA27-BA26 -> -5.8 | BE27: =SUM(BB27:BD27) -> -6.9 | BF27: =SUM(I27-BE27) -> 6.9 | BG27: =SUM(I27-BF27) -> -6.9
A28: =ELEC!C26 -> 44553 | B28: =B27 -> 109443 | C28: =B28-B27 -> 0 | D28: =C28/27 -> 0 | E28: =SUM((C28*$E$4)+(7500/'EDl log'!$A$37)) -> 241.93548 | G28: =G27 -> 626310 | H28: =G28-G27 -> 0 | I28: =C28+H28 -> 0 | J28: =IF(I28>0,E28/I28,0) -> 0 | K28: ='Swimming Pool quality check '!H28 -> 6971 | L28: =K28-K27 -> 0 | M28: =M27 -> 457.44 | N28: =SUM(M28-M27) -> 0 | O28: =O27 -> 529.52 | P28: =SUM(O28-O27) -> 0 | Q28: =SUM(P28+N28) -> 0 | T28: =T27 -> 5180 | U28: =SUM(T28-T27) -> 0 | V28: =V27 -> 477 | W28: =+V28-V27 -> 0 | X28: =X27 -> 154481 | Y28: =SUM(X28-X27) -> 0 | Z28: =Z27 -> 99258 | AA28: =Z28-Z27 -> 0 | AB28: =AB27 -> 248 | AC28: =AC27 -> 789 | AD28: =AC28-AC27 -> 0 | AE28: =AE27 -> 239.1 | AF28: =AE28-AE27 -> 0 | AG28: =AG27 -> 2217.83 | AH28: =AG28-AG27 -> 0 | AI28: =AF28+AH28 -> 0 | AJ28: =+Z28-Z27 -> 0 | AK28: =SUM(Y28-L28) -> 0 | AL28: =SUM(AJ28-W28) -> 0 | AM28: ='General information '!D27 -> 13 | AN28: ='General information '!H27 -> 0 | AP28: ='General information '!J27 -> 0 | AR28: =A28 -> 44553 | AS28: =AS27 -> 0.9 | AT28: =AT27 -> 181 | AU28: =AU27 -> 1.1 | AV28: =AV27 -> 125 | AW28: 2.9 | AX28: 101 | AY28: =AS28*AT28 -> 162.9 | AZ28: =AU28*AV28 -> 137.5 | BA28: =AW28*AX28 -> 292.9 | BB28: =AY28-AY27 -> 0 | BC28: =AZ28-AZ27 -> 0 | BD28: =BA28-BA27 -> -11.6 | BE28: =SUM(BB28:BD28) -> -11.6 | BF28: =SUM(I28-BE28) -> 11.6 | BG28: =SUM(I28-BF28) -> -11.6
A29: =ELEC!C27 -> 44554 | B29: =B28 -> 109443 | C29: =B29-B28 -> 0 | D29: =C29/27 -> 0 | E29: =SUM((C29*$E$4)+(7500/'EDl log'!$A$37)) -> 241.93548 | G29: =G28 -> 626310 | H29: =G29-G28 -> 0 | I29: =C29+H29 -> 0 | J29: =IF(I29>0,E29/I29,0) -> 0 | K29: ='Swimming Pool quality check '!H29 -> 6971 | L29: =K29-K28 -> 0 | M29: =M28 -> 457.44 | N29: =SUM(M29-M28) -> 0 | O29: =O28 -> 529.52 | P29: =SUM(O29-O28) -> 0 | Q29: =SUM(P29+N29) -> 0 | T29: =T28 -> 5180 | U29: =SUM(T29-T28) -> 0 | V29: =V28 -> 477 | W29: =+V29-V28 -> 0 | X29: =X28 -> 154481 | Y29: =SUM(X29-X28) -> 0 | Z29: =Z28 -> 99258 | AA29: =Z29-Z28 -> 0 | AB29: =AB28 -> 248 | AC29: =AC28 -> 789 | AD29: =AC29-AC28 -> 0 | AE29: =AE28 -> 239.1 | AF29: =AE29-AE28 -> 0 | AG29: =AG28 -> 2217.83 | AH29: =AG29-AG28 -> 0 | AI29: =AF29+AH29 -> 0 | AJ29: =+Z29-Z28 -> 0 | AK29: =SUM(Y29-L29) -> 0 | AL29: =SUM(AJ29-W29) -> 0 | AM29: ='General information '!D28 -> 0 | AN29: ='General information '!H28 -> 0 | AP29: ='General information '!J28 -> 0 | AR29: =A29 -> 44554 | AS29: =AS28 -> 0.9 | AT29: =AT28 -> 181 | AU29: =AU28 -> 1.1 | AV29: =AV28 -> 125 | AW29: 2.9 | AX29: =AX28 -> 101 | AY29: =AS29*AT29 -> 162.9 | AZ29: =AU29*AV29 -> 137.5 | BA29: =AW29*AX29 -> 292.9 | BB29: =AY29-AY28 -> 0 | BC29: =AZ29-AZ28 -> 0 | BD29: =BA29-BA28 -> 0 | BE29: =SUM(BB29:BD29) -> 0 | BF29: =SUM(I29-BE29) -> 0 | BG29: =SUM(I29-BF29) -> 0
A30: =ELEC!C28 -> 44555 | B30: =B29 -> 109443 | C30: =B30-B29 -> 0 | D30: =C30/27 -> 0 | E30: =SUM((C30*$E$4)+(7500/'EDl log'!$A$37)) -> 241.93548 | G30: =G29 -> 626310 | H30: =G30-G29 -> 0 | I30: =C30+H30 -> 0 | J30: =IF(I30>0,E30/I30,0) -> 0 | K30: ='Swimming Pool quality check '!H30 -> 6971 | L30: =K30-K29 -> 0 | M30: =M29 -> 457.44 | N30: =SUM(M30-M29) -> 0 | O30: =O29 -> 529.52 | P30: =SUM(O30-O29) -> 0 | Q30: =SUM(P30+N30) -> 0 | T30: =T29 -> 5180 | U30: =SUM(T30-T29) -> 0 | V30: =V29 -> 477 | W30: =+V30-V29 -> 0 | X30: =X29 -> 154481 | Y30: =SUM(X30-X29) -> 0 | Z30: =Z29 -> 99258 | AA30: =Z30-Z29 -> 0 | AB30: =AB29 -> 248 | AC30: =AC29 -> 789 | AD30: =AC30-AC29 -> 0 | AE30: =AE29 -> 239.1 | AF30: =AE30-AE29 -> 0 | AG30: =AG29 -> 2217.83 | AH30: =AG30-AG29 -> 0 | AI30: =AF30+AH30 -> 0 | AJ30: =+Z30-Z29 -> 0 | AK30: =SUM(Y30-L30) -> 0 | AL30: =SUM(AJ30-W30) -> 0 | AM30: ='General information '!D29 -> 0 | AN30: ='General information '!H29 -> 0 | AP30: ='General information '!J29 -> 0 | AR30: =A30 -> 44555 | AS30: =AS29 -> 0.9 | AT30: =AT29 -> 181 | AU30: =AU29 -> 1.1 | AV30: =AV29 -> 125 | AW30: 2.9 | AX30: =AX29 -> 101 | AY30: =AS30*AT30 -> 162.9 | AZ30: =AU30*AV30 -> 137.5 | BA30: =AW30*AX30 -> 292.9 | BB30: =AY30-AY29 -> 0 | BC30: =AZ30-AZ29 -> 0 | BD30: =BA30-BA29 -> 0 | BE30: =SUM(BB30:BD30) -> 0 | BF30: =SUM(I30-BE30) -> 0 | BG30: =SUM(I30-BF30) -> 0
A31: =ELEC!C29 -> 44556 | B31: =B30 -> 109443 | C31: =B31-B30 -> 0 | D31: =C31/27 -> 0 | E31: =SUM((C31*$E$4)+(7500/'EDl log'!$A$37)) -> 241.93548 | G31: =G30 -> 626310 | H31: =G31-G30 -> 0 | I31: =C31+H31 -> 0 | J31: =IF(I31>0,E31/I31,0) -> 0 | K31: ='Swimming Pool quality check '!H31 -> 6971 | L31: =K31-K30 -> 0 | M31: =M30 -> 457.44 | N31: =SUM(M31-M30) -> 0 | O31: =O30 -> 529.52 | P31: =SUM(O31-O30) -> 0 | Q31: =SUM(P31+N31) -> 0 | T31: =T30 -> 5180 | U31: =SUM(T31-T30) -> 0 | V31: =V30 -> 477 | W31: =+V31-V30 -> 0 | X31: =X30 -> 154481 | Y31: =SUM(X31-X30) -> 0 | Z31: =Z30 -> 99258 | AA31: =Z31-Z30 -> 0 | AB31: =AB30 -> 248 | AC31: =AC30 -> 789 | AD31: =AC31-AC30 -> 0 | AE31: =AE30 -> 239.1 | AF31: =AE31-AE30 -> 0 | AG31: =AG30 -> 2217.83 | AH31: =AG31-AG30 -> 0 | AI31: =AF31+AH31 -> 0 | AJ31: =+Z31-Z30 -> 0 | AK31: =SUM(Y31-L31) -> 0 | AL31: =SUM(AJ31-W31) -> 0 | AM31: ='General information '!D30 -> 0 | AN31: ='General information '!H30 -> 0 | AP31: ='General information '!J30 -> 0 | AR31: =A31 -> 44556 | AS31: =AS30 -> 0.9 | AT31: =AT30 -> 181 | AU31: =AU30 -> 1.1 | AV31: =AV30 -> 125 | AW31: 2.9 | AX31: =AX30 -> 101 | AY31: =AS31*AT31 -> 162.9 | AZ31: =AU31*AV31 -> 137.5 | BA31: =AW31*AX31 -> 292.9 | BB31: =AY31-AY30 -> 0 | BC31: =AZ31-AZ30 -> 0 | BD31: =BA31-BA30 -> 0 | BE31: =SUM(BB31:BD31) -> 0 | BF31: =SUM(I31-BE31) -> 0 | BG31: =SUM(I31-BF31) -> 0
A32: =ELEC!C30 -> 44557 | B32: =B31 -> 109443 | C32: =B32-B31 -> 0 | D32: =C32/27 -> 0 | E32: =SUM((C32*$E$4)+(7500/'EDl log'!$A$37)) -> 241.93548 | G32: =G31 -> 626310 | H32: =G32-G31 -> 0 | I32: =C32+H32 -> 0 | J32: =IF(I32>0,E32/I32,0) -> 0 | K32: ='Swimming Pool quality check '!H32 -> 6975 | L32: =K32-K31 -> 4 | M32: =M31 -> 457.44 | N32: =SUM(M32-M31) -> 0 | O32: =O31 -> 529.52 | P32: =SUM(O32-O31) -> 0 | Q32: =SUM(P32+N32) -> 0 | T32: =T31 -> 5180 | U32: =SUM(T32-T31) -> 0 | V32: =V31 -> 477 | W32: =+V32-V31 -> 0 | X32: =X31 -> 154481 | Y32: =SUM(X32-X31) -> 0 | Z32: =Z31 -> 99258 | AA32: =Z32-Z31 -> 0 | AB32: =AB31 -> 248 | AC32: =AC31 -> 789 | AD32: =AC32-AC31 -> 0 | AE32: =AE31 -> 239.1 | AF32: =AE32-AE31 -> 0 | AG32: =AG31 -> 2217.83 | AH32: =AG32-AG31 -> 0 | AI32: =AF32+AH32 -> 0 | AJ32: =+Z32-Z31 -> 0 | AK32: =SUM(Y32-L32) -> -4 | AL32: =SUM(AJ32-W32) -> 0 | AM32: ='General information '!D31 -> 15.5 | AN32: ='General information '!H31 -> 0 | AP32: ='General information '!J31 -> 0 | AR32: =A32 -> 44557 | AS32: =AS31 -> 0.9 | AT32: =AT31 -> 181 | AU32: =AU31 -> 1.1 | AV32: =AV31 -> 125 | AW32: 2.9 | AX32: 94 | AY32: =AS32*AT32 -> 162.9 | AZ32: =AU32*AV32 -> 137.5 | BA32: =AW32*AX32 -> 272.6 | BB32: =AY32-AY31 -> 0 | BC32: =AZ32-AZ31 -> 0 | BD32: =BA32-BA31 -> -20.3 | BE32: =SUM(BB32:BD32) -> -20.3 | BF32: =SUM(I32-BE32) -> 20.3 | BG32: =SUM(I32-BF32) -> -20.3
A33: =ELEC!C31 -> 44558 | B33: =B32 -> 109443 | C33: =B33-B32 -> 0 | D33: =C33/27 -> 0 | E33: =SUM((C33*$E$4)+(7500/'EDl log'!$A$37)) -> 241.93548 | G33: =G32 -> 626310 | H33: =G33-G32 -> 0 | I33: =C33+H33 -> 0 | J33: =IF(I33>0,E33/I33,0) -> 0 | K33: ='Swimming Pool quality check '!H33 -> 6976 | L33: =K33-K32 -> 1 | M33: =M32 -> 457.44 | N33: =SUM(M33-M32) -> 0 | O33: =O32 -> 529.52 | P33: =SUM(O33-O32) -> 0 | Q33: =SUM(P33+N33) -> 0 | T33: =T32 -> 5180 | U33: =SUM(T33-T32) -> 0 | V33: =V32 -> 477 | W33: =+V33-V32 -> 0 | X33: =X32 -> 154481 | Y33: =SUM(X33-X32) -> 0 | Z33: =Z32 -> 99258 | AA33: =Z33-Z32 -> 0 | AB33: =AB32 -> 248 | AC33: =AC32 -> 789 | AD33: =AC33-AC32 -> 0 | AE33: =AE32 -> 239.1 | AF33: =AE33-AE32 -> 0 | AG33: =AG32 -> 2217.83 | AH33: =AG33-AG32 -> 0 | AI33: =AF33+AH33 -> 0 | AJ33: =+Z33-Z32 -> 0 | AK33: =SUM(Y33-L33) -> -1 | AL33: =SUM(AJ33-W33) -> 0 | AM33: ='General information '!D32 -> 16 | AN33: ='General information '!H32 -> 0 | AP33: ='General information '!J32 -> 0 | AR33: =A33 -> 44558 | AS33: =AS32 -> 0.9 | AT33: 173 | AU33: =AU32 -> 1.1 | AV33: 122 | AW33: 2.9 | AX33: 90 | AY33: =AS33*AT33 -> 155.7 | AZ33: =AU33*AV33 -> 134.2 | BA33: =AW33*AX33 -> 261 | BB33: =AY33-AY32 -> -7.2 | BC33: =AZ33-AZ32 -> -3.3 | BD33: =BA33-BA32 -> -11.6 | BE33: =SUM(BB33:BD33) -> -22.1 | BF33: =SUM(I33-BE33) -> 22.1 | BG33: =SUM(I33-BF33) -> -22.1
A34: =ELEC!C32 -> 44559 | B34: =B33 -> 109443 | C34: =B34-B33 -> 0 | D34: =C34/27 -> 0 | E34: =SUM((C34*$E$4)+(7500/'EDl log'!$A$37)) -> 241.93548 | G34: =G33 -> 626310 | H34: =G34-G33 -> 0 | I34: =C34+H34 -> 0 | J34: =IF(I34>0,E34/I34,0) -> 0 | K34: ='Swimming Pool quality check '!H34 -> 6976 | L34: =K34-K33 -> 0 | M34: =M33 -> 457.44 | N34: =SUM(M34-M33) -> 0 | O34: =O33 -> 529.52 | P34: =SUM(O34-O33) -> 0 | Q34: =SUM(P34+N34) -> 0 | T34: =T33 -> 5180 | U34: =SUM(T34-T33) -> 0 | V34: =V33 -> 477 | W34: =+V34-V33 -> 0 | X34: =X33 -> 154481 | Y34: =SUM(X34-X33) -> 0 | Z34: =Z33 -> 99258 | AA34: =Z34-Z33 -> 0 | AB34: =AB33 -> 248 | AC34: =AC33 -> 789 | AD34: =AC34-AC33 -> 0 | AE34: =AE33 -> 239.1 | AF34: =AE34-AE33 -> 0 | AG34: =AG33 -> 2217.83 | AH34: =AG34-AG33 -> 0 | AI34: =AF34+AH34 -> 0 | AJ34: =+Z34-Z33 -> 0 | AK34: =SUM(Y34-L34) -> 0 | AL34: =SUM(AJ34-W34) -> 0 | AM34: ='General information '!D33 -> 16.5 | AN34: ='General information '!H33 -> 0 | AP34: ='General information '!J33 -> 0 | AR34: =A34 -> 44559 | AS34: =AS33 -> 0.9 | AT34: =AT33 -> 173 | AU34: =AU33 -> 1.1 | AV34: =AV33 -> 122 | AW34: 2.9 | AX34: =AX33 -> 90 | AY34: =AS34*AT34 -> 155.7 | AZ34: =AU34*AV34 -> 134.2 | BA34: =AW34*AX34 -> 261 | BB34: =AY34-AY33 -> 0 | BC34: =AZ34-AZ33 -> 0 | BD34: =BA34-BA33 -> 0 | BE34: =SUM(BB34:BD34) -> 0 | BF34: =SUM(I34-BE34) -> 0 | BG34: =SUM(I34-BF34) -> 0
A35: =ELEC!C33 -> 44560 | B35: =B34 -> 109443 | C35: =B35-B34 -> 0 | D35: =C35/27 -> 0 | E35: =SUM((C35*$E$4)+(7500/'EDl log'!$A$37)) -> 241.93548 | G35: =G34 -> 626310 | H35: =G35-G34 -> 0 | I35: =C35+H35 -> 0 | J35: =IF(I35>0,E35/I35,0) -> 0 | K35: ='Swimming Pool quality check '!H35 -> 6976 | L35: =K35-K34 -> 0 | M35: =M34 -> 457.44 | N35: =SUM(M35-M34) -> 0 | O35: =O34 -> 529.52 | P35: =SUM(O35-O34) -> 0 | Q35: =SUM(P35+N35) -> 0 | T35: =T34 -> 5180 | U35: =SUM(T35-T34) -> 0 | V35: =V34 -> 477 | W35: =+V35-V34 -> 0 | X35: =X34 -> 154481 | Y35: =SUM(X35-X34) -> 0 | Z35: =Z34 -> 99258 | AA35: =Z35-Z34 -> 0 | AB35: =AB34 -> 248 | AC35: =AC34 -> 789 | AD35: =AC35-AC34 -> 0 | AE35: =AE34 -> 239.1 | AF35: =AE35-AE34 -> 0 | AG35: =AG34 -> 2217.83 | AH35: =AG35-AG34 -> 0 | AI35: =AF35+AH35 -> 0 | AJ35: =+Z35-Z34 -> 0 | AK35: =SUM(Y35-L35) -> 0 | AL35: =SUM(AJ35-W35) -> 0 | AM35: ='General information '!D34 -> 0 | AN35: ='General information '!H34 -> 0 | AP35: ='General information '!J34 -> 0 | AR35: =A35 -> 44560 | AS35: =AS34 -> 0.9 | AT35: =AT34 -> 173 | AU35: =AU34 -> 1.1 | AV35: =AV34 -> 122 | AW35: 2.9 | AX35: =AX34 -> 90 | AY35: =AS35*AT35 -> 155.7 | AZ35: =AU35*AV35 -> 134.2 | BA35: =AW35*AX35 -> 261 | BB35: =AY35-AY34 -> 0 | BC35: =AZ35-AZ34 -> 0 | BD35: =BA35-BA34 -> 0 | BE35: =SUM(BB35:BD35) -> 0 | BF35: =SUM(I35-BE35) -> 0 | BG35: =SUM(I35-BF35) -> 0
A36: =ELEC!C34 -> 44561 | B36: =B35 -> 109443 | C36: =B36-B35 -> 0 | D36: =C36/27 -> 0 | E36: =SUM((C36*$E$4)+(7500/'EDl log'!$A$37)) -> 241.93548 | G36: =G35 -> 626310 | H36: =G36-G35 -> 0 | I36: =C36+H36 -> 0 | J36: =IF(I36>0,E36/I36,0) -> 0 | K36: ='Swimming Pool quality check '!H36 -> 6976 | L36: =K36-K35 -> 0 | M36: =M35 -> 457.44 | N36: =SUM(M36-M35) -> 0 | O36: =O35 -> 529.52 | P36: =SUM(O36-O35) -> 0 | Q36: =SUM(P36+N36) -> 0 | T36: =T35 -> 5180 | U36: =SUM(T36-T35) -> 0 | V36: =V35 -> 477 | W36: =+V36-V35 -> 0 | X36: =X35 -> 154481 | Y36: =SUM(X36-X35) -> 0 | Z36: =Z35 -> 99258 | AA36: =Z36-Z35 -> 0 | AB36: =AB35 -> 248 | AC36: =AC35 -> 789 | AD36: =AC36-AC35 -> 0 | AE36: =AE35 -> 239.1 | AF36: =AE36-AE35 -> 0 | AG36: =AG35 -> 2217.83 | AH36: =AG36-AG35 -> 0 | AI36: =AF36+AH36 -> 0 | AJ36: =+Z36-Z35 -> 0 | AK36: =SUM(Y36-L36) -> 0 | AL36: =SUM(AJ36-W36) -> 0 | AM36: ='General information '!D35 -> 0 | AN36: ='General information '!H35 -> 0 | AP36: ='General information '!J35 -> 0 | AR36: =A36 -> 44561 | AS36: =AS35 -> 0.9 | AT36: =AT35 -> 173 | AU36: =AU35 -> 1.1 | AV36: =AV35 -> 122 | AW36: 2.9 | AX36: =AX35 -> 90 | AY36: =AS36*AT36 -> 155.7 | AZ36: =AU36*AV36 -> 134.2 | BA36: =AW36*AX36 -> 261 | BB36: =AY36-AY35 -> 0 | BC36: =AZ36-AZ35 -> 0 | BD36: =BA36-BA35 -> 0 | BE36: =SUM(BB36:BD36) -> 0 | BF36: =SUM(I36-BE36) -> 0 | BG36: =SUM(I36-BF36) -> 0
C37: =SUM(C6:C36) -> 0 | D37: =SUM(D6:D36) -> 0 | F37: =SUM(F6:F36) -> 0 | H37: =SUM(H6:H36) -> 332 | I37: =SUM(I6:I36) -> 332 | L37: =SUM(L7:L36) -> 22 | Q37: =SUM(Q6:Q36) -> 0 | U37: =SUM(U6:U36) -> 0 | Y37: =SUM(Y6,Y33,Y31,Y29,Y27,Y25,Y23,Y21,Y19,Y17,Y15,Y13,Y11,Y9,Y7,Y34,Y35,Y36) -> 0 | AJ37: =SUM(AJ6:AJ36) -> 0 | AK37: =SUM(Y37-L37) -> -22 | AL37: =SUM(AL6:AL36) -> 0
C38: =+C37*1.66 -> 0 | E38: =SUM(E6:E33) -> 6774.1935 | F38: =SUM(F6:F35) -> 0 | H38: 7500 | I38: =SUM('General information '!G36/WATER!I37) -> 0 | O38: =SUM(Q37+I37) -> 332 | Z38: =SUM(Y37:AJ37) -> 0 | AK38: =SUM(Y38-L38) -> 0
B39: =9*31 -> 279 | D39: =SUM(D6:D35) -> 0 | F39: =SUM(F6:F36) -> 0 | G39: =SUM(I37) -> 332 | H39: =SUM(H38+C38) -> 7500 | K39: =SUM(H39/G39) -> 22.590361 | AJ39: =SUM(C38-AK38) -> 0 | AM39: =SUM(AJ39/AO38) -> #DIV/0!

Sheet GEN
B1: GEN1 | C1: RUN HR | D1: Fuel Counter Index | E1: Cons /day | F1: Diesel L/H | H1: next service | I1: ALARM | J1: GEN2 | K1: RUN HR | L1: Fuel Counter Index | M1: Cons /day | N1: Diesel L/H | P1: next service | Q1: ALARM | R1: GEN3 | S1: RUN HR | T1: Fuel Counter Index | U1: Cons /day | V1: Diesel L/H | X1: next service | Y1: ALARM | Z1: RH total | AA1: Gen Con /day | AB1: Total Deisel Cons/day | AC1: H /L | AD1: TOAL KW GEN | AI1: fuel Consuption | AK1: AVG KW/h
A2: =[2]GEN!$A$32 -> 44530 | B2: =[2]GEN!B32 -> 11198 | C2: =[2]GEN!C32 -> 9 | D2: =[2]GEN!D32 -> 562516 | E2: =[2]GEN!E32 -> 2250 | F2: =[2]GEN!F32 -> 250 | G2: =[2]GEN!G32 -> 0 | H2: =[2]GEN!H32 -> 11218 | I2: =[2]GEN!I32 -> ok | ... AK2: =[2]GEN!AK32 -> 169.51308
A3: =ELEC!C4 -> 44531 | B3: 11202 | C3: =B3-B2 -> 4 | D3: =D2+C3*250 -> 563516 | E3: =SUM(D3-D2) -> 1000 | F3: =IF(C3>0,E3/C3,0) -> 250 | G3: =[4]GEN!G32 -> 0 | H3: =H2 -> 11218 | I3: =IF(B3-H3<=0,"ok","oil change") -> ok | J3: =J2 -> 10698 | K3: =J3-J2 -> 0 | L3: =L2 -> 357691 | M3: =SUM(L3-L2) -> 0 | N3: =IF(K3>0,M3/K3,0) -> 0 | O3: =[4]GEN!O32 -> 0 | P3: =P2 -> 10873 | Q3: =IF(J3-P3<=0,"ok","oil change") -> ok | R3: 13319 | S3: =R3-R2 -> 7 | T3: =T2+U3 -> 269246 | U3: =V3*S3 -> 1750 | V3: 250 | W3: =[4]GEN!W32 -> 0 | X3: =13279+150 -> 13429 | Y3: =IF(R3-X3<=0,"ok","oil change") -> ok | Z3: =C3+K3+S3 -> 11 | AA3: =U3+M3+E3 -> 2750 | AB3: =V3+N3+F3 -> 500 | AC3: =IF(Z3>0,AA3/Z3,0) -> 250 | AD3: =ELEC!Q4 -> 6199 | AE3: =SUM(AD3/Z3) -> 563.54545 | AF3: =SUM(AE3/1600) -> 0.35221591 | AG3: =SUM(360*AF3) -> 126.79773 | AH3: =SUM(AC3-AG3) -> 123.20227 | AI3: =AD3*AJ3 -> 1595.5232 | AJ3: =305/1185 -> 0.25738397 | AK3: =AI3/Z3 -> 145.04756 | AL3: =IF(Z3=0,0,1) -> 1
A4: =ELEC!C5 -> 44532 | B4: 11213 | C4: =B4-B3 -> 11 | D4: =D3+C4*250 -> 566266 | E4: =SUM(D4-D3) -> 2750 | F4: =IF(C4>0,E4/C4,0) -> 250 | H4: =H3 -> 11218 | I4: =IF(B4-H4<=0,"ok","oil change") -> ok | J4: =J3 -> 10698 | K4: =J4-J3 -> 0 | L4: =L3 -> 357691 | M4: =SUM(L4-L3) -> 0 | N4: =IF(K4>0,M4/K4,0) -> 0 | P4: =P3 -> 10873 | Q4: =IF(J4-P4<=0,"ok","oil change") -> ok | R4: 13320 | S4: =R4-R3 -> 1 | T4: =T3+U4 -> 269496 | U4: =V4*S4 -> 250 | V4: 250 | X4: =13279+150 -> 13429 | Y4: =IF(R4-X4<=0,"ok","oil change") -> ok | Z4: =C4+K4+S4 -> 12 | AA4: =U4+M4+E4 -> 3000 | AB4: =V4+N4+F4 -> 500 | AC4: =IF(Z4>0,AA4/Z4,0) -> 250 | AD4: =ELEC!Q5 -> 5363 | AE4: =SUM(AD4/Z4) -> 446.91667 | AF4: =SUM(AE4/1600) -> 0.27932292 | AG4: =SUM(360*AF4) -> 100.55625 | AH4: =SUM(AC4-AG4) -> 149.44375 | AI4: =AD4*AJ4 -> 1380.3502 | AJ4: =305/1185 -> 0.25738397 | AK4: =AI4/Z4 -> 115.02918 | AL4: =IF(Z4=0,0,1) -> 1
A5: =ELEC!C6 -> 44533 | B5: =B4 -> 11213 | C5: =B5-B4 -> 0 | D5: =D4+C5*250 -> 566266 | E5: =SUM(D5-D4) -> 0 | F5: =IF(C5>0,E5/C5,0) -> 0 | H5: =H4 -> 11218 | I5: =IF(B5-H5<=0,"ok","oil change") -> ok | J5: =J4 -> 10698 | K5: =J5-J4 -> 0 | L5: =L4 -> 357691 | M5: =SUM(L5-L4) -> 0 | N5: =IF(K5>0,M5/K5,0) -> 0 | P5: =P4 -> 10873 | Q5: =IF(J5-P5<=0,"ok","oil change") -> ok | R5: =R4 -> 13320 | S5: =R5-R4 -> 0 | T5: =T4+U5 -> 269496 | U5: =V5*S5 -> 0 | V5: 250 | X5: =13279+150 -> 13429 | Y5: =IF(R5-X5<=0,"ok","oil change") -> ok | Z5: =C5+K5+S5 -> 0 | AA5: =U5+M5+E5 -> 0 | AB5: =V5+N5+F5 -> 250 | AC5: =IF(Z5>0,AA5/Z5,0) -> 0 | AD5: =ELEC!Q6 -> 0 | AE5: =SUM(AD5/Z5) -> #DIV/0! | AF5: =SUM(AE5/1600) -> #DIV/0! | AG5: =SUM(320*AF5) -> #DIV/0! | AH5: =SUM(AC5-AG5) -> #DIV/0! | AI5: =AD5*AJ5 -> 0 | AJ5: =305/1185 -> 0.25738397 | AK5: =AI5/Z5 -> #DIV/0! | AL5: =IF(Z5=0,0,1) -> 0
A6: =ELEC!C7 -> 44534 | B6: =B5 -> 11213 | C6: =B6-B5 -> 0 | D6: =D5+C6*250 -> 566266 | E6: =SUM(D6-D5) -> 0 | F6: =IF(C6>0,E6/C6,0) -> 0 | H6: =H5 -> 11218 | I6: =IF(B6-H6<=0,"ok","oil change") -> ok | J6: =J5 -> 10698 | K6: =J6-J5 -> 0 | L6: =L5 -> 357691 | M6: =SUM(L6-L5) -> 0 | N6: =IF(K6>0,M6/K6,0) -> 0 | P6: =P5 -> 10873 | Q6: =IF(J6-P6<=0,"ok","oil change") -> ok | R6: =R5 -> 13320 | S6: =R6-R5 -> 0 | T6: =T5+U6 -> 269496 | U6: =V6*S6 -> 0 | V6: 250 | X6: =13279+150 -> 13429 | Y6: =IF(R6-X6<=0,"ok","oil change") -> ok | Z6: =C6+K6+S6 -> 0 | AA6: =U6+M6+E6 -> 0 | AB6: =V6+N6+F6 -> 250 | AC6: =IF(Z6>0,AA6/Z6,0) -> 0 | AD6: =ELEC!Q7 -> 0 | AE6: =SUM(AD6/Z6) -> #DIV/0! | AF6: =SUM(AE6/1600) -> #DIV/0! | AG6: =SUM(320*AF6) -> #DIV/0! | AH6: =SUM(AC6-AG6) -> #DIV/0! | AI6: =AD6*AJ6 -> 0 | AJ6: =305/1185 -> 0.25738397 | AK6: =AI6/Z6 -> #DIV/0! | AL6: =IF(Z6=0,0,1) -> 0
A7: =ELEC!C8 -> 44535 | B7: 11214 | C7: =B7-B6 -> 1 | D7: =D6+C7*250 -> 566516 | E7: =SUM(D7-D6) -> 250 | F7: =IF(C7>0,E7/C7,0) -> 250 | H7: =H6 -> 11218 | I7: =IF(B7-H7<=0,"ok","oil change") -> ok | J7: =J6 -> 10698 | K7: =J7-J6 -> 0 | L7: =L6 -> 357691 | M7: =SUM(L7-L6) -> 0 | N7: =IF(K7>0,M7/K7,0) -> 0 | P7: =P6 -> 10873 | Q7: =IF(J7-P7<=0,"ok","oil change") -> ok | R7: 13329 | S7: =R7-R6 -> 9 | T7: =T6+U7 -> 271746 | U7: =V7*S7 -> 2250 | V7: 250 | X7: =13279+150 -> 13429 | Y7: =IF(R7-X7<=0,"ok","oil change") -> ok | Z7: =C7+K7+S7 -> 10 | AA7: =U7+M7+E7 -> 2500 | AB7: =V7+N7+F7 -> 500 | AC7: =IF(Z7>0,AA7/Z7,0) -> 250 | AD7: =ELEC!Q8 -> 6545 | AE7: =SUM(AD7/Z7) -> 654.5 | AF7: =SUM(AE7/1600) -> 0.4090625 | AG7: =SUM(AF7/1600) -> 0.00025566406 | AH7: =SUM(AC7-AG7) -> 249.99974 | AI7: =AD7*AJ7 -> 1684.5781 | AJ7: =305/1185 -> 0.25738397 | AK7: =AI7/Z7 -> 168.45781 | AL7: =IF(Z7=0,0,1) -> 1
A8: =ELEC!C9 -> 44536 | B8: 11216 | C8: =B8-B7 -> 2 | D8: =D7+C8*250 -> 567016 | E8: =SUM(D8-D7) -> 500 | F8: =IF(C8>0,E8/C8,0) -> 250 | H8: =H7 -> 11218 | I8: =IF(B8-H8<=0,"ok","oil change") -> ok | J8: =J7 -> 10698 | K8: =J8-J7 -> 0 | L8: =L7 -> 357691 | M8: =SUM(L8-L7) -> 0 | N8: =IF(K8>0,M8/K8,0) -> 0 | P8: =P7 -> 10873 | Q8: =IF(J8-P8<=0,"ok","oil change") -> ok | R8: 13336 | S8: =R8-R7 -> 7 | T8: =T7+U8 -> 273496 | U8: =V8*S8 -> 1750 | V8: 250 | X8: =13279+150 -> 13429 | Y8: =IF(R8-X8<=0,"ok","oil change") -> ok | Z8: =C8+K8+S8 -> 9 | AA8: =U8+M8+E8 -> 2250 | AB8: =V8+N8+F8 -> 500 | AC8: =IF(Z8>0,AA8/Z8,0) -> 250 | AD8: =ELEC!Q9 -> 4929 | AE8: =SUM(AD8/Z8) -> 547.66667 | AF8: =SUM(AE8/1600) -> 0.34229167 | AG8: =SUM(AF8/1600) -> 0.00021393229 | AH8: =SUM(AC8-AG8) -> 249.99979 | AI8: =AD8*AJ8 -> 1268.6456 | AJ8: =305/1185 -> 0.25738397 | AK8: =AI8/Z8 -> 140.96062 | AL8: =IF(Z8=0,0,1) -> 1
A9: =ELEC!C10 -> 44537 | B9: 11224 | C9: =B9-B8 -> 8 | D9: =D8+C9*250 -> 569016 | E9: =SUM(D9-D8) -> 2000 | F9: =IF(C9>0,E9/C9,0) -> 250 | H9: =H8 -> 11218 | I9: =IF(B9-H9<=0,"ok","oil change") -> oil change | J9: =J8 -> 10698 | K9: =J9-J8 -> 0 | L9: =L8 -> 357691 | M9: =SUM(L9-L8) -> 0 | N9: =IF(K9>0,M9/K9,0) -> 0 | P9: =P8 -> 10873 | Q9: =IF(J9-P9<=0,"ok","oil change") -> ok | R9: 13338 | S9: =R9-R8 -> 2 | T9: =T8+U9 -> 273996 | U9: =V9*S9 -> 500 | V9: 250 | X9: =13279+150 -> 13429 | Y9: =IF(R9-X9<=0,"ok","oil change") -> ok | Z9: =C9+K9+S9 -> 10 | AA9: =U9+M9+E9 -> 2500 | AB9: =V9+N9+F9 -> 500 | AC9: =IF(Z9>0,AA9/Z9,0) -> 250 | AD9: =ELEC!Q10 -> 5244 | AE9: =SUM(AD9/Z9) -> 524.4 | AF9: =SUM(AE9/1600) -> 0.32775 | AG9: =SUM(AF9/1600) -> 0.00020484375 | AH9: =SUM(AC9-AG9) -> 249.9998 | AI9: =AD9*AJ9 -> 1349.7215 | AJ9: =305/1185 -> 0.25738397 | AK9: =AI9/Z9 -> 134.97215 | AL9: =IF(Z9=0,0,1) -> 1
A10: =ELEC!C11 -> 44538 | B10: 11224 | C10: =B10-B9 -> 0 | D10: =D9+C10*250 -> 569016 | E10: =SUM(D10-D9) -> 0 | F10: =IF(C10>0,E10/C10,0) -> 0 | H10: =H9 -> 11218 | I10: =IF(B10-H10<=0,"ok","oil change") -> oil change | J10: =J9 -> 10698 | K10: =J10-J9 -> 0 | L10: =L9 -> 357691 | M10: =SUM(L10-L9) -> 0 | N10: =IF(K10>0,M10/K10,0) -> 0 | P10: =P9 -> 10873 | Q10: =IF(J10-P10<=0,"ok","oil change") -> ok | R10: 13349 | S10: =R10-R9 -> 11 | T10: =T9+U10 -> 276746 | U10: =V10*S10 -> 2750 | V10: 250 | X10: =13279+150 -> 13429 | Y10: =IF(R10-X10<=0,"ok","oil change") -> ok | Z10: =C10+K10+S10 -> 11 | AA10: =U10+M10+E10 -> 2750 | AB10: =V10+N10+F10 -> 250 | AC10: =IF(Z10>0,AA10/Z10,0) -> 250 | AD10: =ELEC!Q11 -> 5963 | AE10: =SUM(AD10/Z10) -> 542.09091 | AF10: =SUM(AE10/1600) -> 0.33880682 | AG10: =SUM(AF10/1600) -> 0.00021175426 | AH10: =SUM(AC10-AG10) -> 249.99979 | AI10: =AD10*AJ10 -> 1534.7806 | AJ10: =305/1185 -> 0.25738397 | AK10: =AI10/Z10 -> 139.52551 | AL10: =IF(Z10=0,0,1) -> 1
A11: =ELEC!C12 -> 44539 | B11: 11225 | C11: =B11-B10 -> 1 | D11: =D10+C11*250 -> 569266 | E11: =SUM(D11-D10) -> 250 | F11: =IF(C11>0,E11/C11,0) -> 250 | H11: =H10 -> 11218 | I11: =IF(B11-H11<=0,"ok","oil change") -> oil change | J11: =J10 -> 10698 | K11: =J11-J10 -> 0 | L11: =L10 -> 357691 | M11: =SUM(L11-L10) -> 0 | N11: =IF(K11>0,M11/K11,0) -> 0 | P11: =P10 -> 10873 | Q11: =IF(J11-P11<=0,"ok","oil change") -> ok | R11: 13357 | S11: =R11-R10 -> 8 | T11: =T10+U11 -> 278746 | U11: =V11*S11 -> 2000 | V11: 250 | X11: =13279+150 -> 13429 | Y11: =IF(R11-X11<=0,"ok","oil change") -> ok | Z11: =C11+K11+S11 -> 9 | AA11: =U11+M11+E11 -> 2250 | AB11: =V11+N11+F11 -> 500 | AC11: =IF(Z11>0,AA11/Z11,0) -> 250 | AD11: =ELEC!Q12 -> 4836 | AE11: =SUM(AD11/Z11) -> 537.33333 | AF11: =SUM(AE11/1600) -> 0.33583333 | AG11: =SUM(AF11/1600) -> 0.00020989583 | AH11: =SUM(AC11-AG11) -> 249.99979 | AI11: =AD11*AJ11 -> 1244.7089 | AJ11: =305/1185 -> 0.25738397 | AK11: =AI11/Z11 -> 138.30098 | AL11: =IF(Z11=0,0,1) -> 1
A12: =ELEC!C13 -> 44540 | B12: =B11 -> 11225 | C12: =B12-B11 -> 0 | D12: =D11+C12*250 -> 569266 | E12: =SUM(D12-D11) -> 0 | F12: =IF(C12>0,E12/C12,0) -> 0 | H12: 11374 | I12: =IF(B12-H12<=0,"ok","oil change") -> ok | J12: =J11 -> 10698 | K12: =J12-J11 -> 0 | L12: =L11 -> 357691 | M12: =SUM(L12-L11) -> 0 | N12: =IF(K12>0,M12/K12,0) -> 0 | P12: =P11 -> 10873 | Q12: =IF(J12-P12<=0,"ok","oil change") -> ok | R12: =R11 -> 13357 | S12: =R12-R11 -> 0 | T12: =T11+U12 -> 278746 | U12: =V12*S12 -> 0 | V12: 250 | X12: =13279+150 -> 13429 | Y12: =IF(R12-X12<=0,"ok","oil change") -> ok | Z12: =C12+K12+S12 -> 0 | AA12: =U12+M12+E12 -> 0 | AB12: =V12+N12+F12 -> 250 | AC12: =IF(Z12>0,AA12/Z12,0) -> 0 | AD12: =ELEC!Q13 -> 0 | AE12: =SUM(AD12/Z12) -> #DIV/0! | AF12: =SUM(AE12/1600) -> #DIV/0! | AG12: =SUM(AF12/1600) -> #DIV/0! | AH12: =SUM(AC12-AG12) -> #DIV/0! | AI12: =AD12*AJ12 -> 0 | AJ12: =305/1185 -> 0.25738397 | AK12: =AI12/Z12 -> #DIV/0! | AL12: =IF(Z12=0,0,1) -> 0
A13: =ELEC!C14 -> 44541 | B13: =B12 -> 11225 | C13: =B13-B12 -> 0 | D13: =D12+C13*250 -> 569266 | E13: =SUM(D13-D12) -> 0 | F13: =IF(C13>0,E13/C13,0) -> 0 | H13: =H12 -> 11374 | I13: =IF(B13-H13<=0,"ok","oil change") -> ok | J13: =J12 -> 10698 | K13: =J13-J12 -> 0 | L13: =L12 -> 357691 | M13: =SUM(L13-L12) -> 0 | N13: =IF(K13>0,M13/K13,0) -> 0 | P13: =P12 -> 10873 | Q13: =IF(J13-P13<=0,"ok","oil change") -> ok | R13: =R12 -> 13357 | S13: =R13-R12 -> 0 | T13: =T12+U13 -> 278746 | U13: =V13*S13 -> 0 | V13: 250 | X13: =13279+150 -> 13429 | Y13: =IF(R13-X13<=0,"ok","oil change") -> ok | Z13: =C13+K13+S13 -> 0 | AA13: =U13+M13+E13 -> 0 | AB13: =V13+N13+F13 -> 250 | AC13: =IF(Z13>0,AA13/Z13,0) -> 0 | AD13: =ELEC!Q14 -> 0 | AE13: =SUM(AD13/Z13) -> #DIV/0! | AF13: =SUM(AE13/1600) -> #DIV/0! | AG13: =SUM(AF13/1600) -> #DIV/0! | AH13: =SUM(AC13-AG13) -> #DIV/0! | AI13: =AD13*AJ13 -> 0 | AJ13: =305/1185 -> 0.25738397 | AK13: =AI13/Z13 -> #DIV/0! | AL13: =IF(Z13=0,0,1) -> 0
A14: =ELEC!C15 -> 44542 | B14: 11234 | C14: =B14-B13 -> 9 | D14: =D13+C14*250 -> 571516 | E14: =SUM(D14-D13) -> 2250 | F14: =IF(C14>0,E14/C14,0) -> 250 | H14: =H13 -> 11374 | I14: =IF(B14-H14<=0,"ok","oil change") -> ok | J14: =J13 -> 10698 | K14: =J14-J13 -> 0 | L14: =L13 -> 357691 | M14: =SUM(L14-L13) -> 0 | N14: =IF(K14>0,M14/K14,0) -> 0 | P14: =P13 -> 10873 | Q14: =IF(J14-P14<=0,"ok","oil change") -> ok | R14: 13359 | S14: =R14-R13 -> 2 | T14: =T13+U14 -> 279246 | U14: =V14*S14 -> 500 | V14: 250 | X14: =13279+150 -> 13429 | Y14: =IF(R14-X14<=0,"ok","oil change") -> ok | Z14: =C14+K14+S14 -> 11 | AA14: =U14+M14+E14 -> 2750 | AB14: =V14+N14+F14 -> 500 | AC14: =IF(Z14>0,AA14/Z14,0) -> 250 | AD14: =ELEC!Q15 -> 6722 | AE14: =SUM(AD14/Z14) -> 611.09091 | AF14: =SUM(AE14/1600) -> 0.38193182 | AG14: =SUM(AF14/1600) -> 0.00023870739 | AH14: =SUM(AC14-AG14) -> 249.99976 | AI14: =AD14*AJ14 -> 1730.135 | AJ14: =305/1185 -> 0.25738397 | AK14: =AI14/Z14 -> 157.285 | AL14: =IF(Z14=0,0,1) -> 1
A15: =ELEC!C16 -> 44543 | B15: 11236 | C15: =B15-B14 -> 2 | D15: =D14+C15*250 -> 572016 | E15: =SUM(D15-D14) -> 500 | F15: =IF(C15>0,E15/C15,0) -> 250 | H15: =H14 -> 11374 | I15: =IF(B15-H15<=0,"ok","oil change") -> ok | J15: =J14 -> 10698 | K15: =J15-J14 -> 0 | L15: =L14 -> 357691 | M15: =SUM(L15-L14) -> 0 | N15: =IF(K15>0,M15/K15,0) -> 0 | P15: =P14 -> 10873 | Q15: =IF(J15-P15<=0,"ok","oil change") -> ok | R15: 13367 | S15: =R15-R14 -> 8 | T15: =T14+U15 -> 281246 | U15: =V15*S15 -> 2000 | V15: 250 | X15: =13279+150 -> 13429 | Y15: =IF(R15-X15<=0,"ok","oil change") -> ok | Z15: =C15+K15+S15 -> 10 | AA15: =U15+M15+E15 -> 2500 | AB15: =V15+N15+F15 -> 500 | AC15: =IF(Z15>0,AA15/Z15,0) -> 250 | AD15: =ELEC!Q16 -> 5125 | AE15: =SUM(AD15/Z15) -> 512.5 | AF15: =SUM(AE15/1600) -> 0.3203125 | AG15: =SUM(AF15/1600) -> 0.00020019531 | AH15: =SUM(AC15-AG15) -> 249.9998 | AI15: =AD15*AJ15 -> 1319.0928 | AJ15: =305/1185 -> 0.25738397 | AK15: =AI15/Z15 -> 131.90928 | AL15: =IF(Z15=0,0,1) -> 1
A16: =ELEC!C17 -> 44544 | B16: 11243 | C16: =B16-B15 -> 7 | D16: =D15+C16*250 -> 573766 | E16: =SUM(D16-D15) -> 1750 | F16: =IF(C16>0,E16/C16,0) -> 250 | H16: =H15 -> 11374 | I16: =IF(B16-H16<=0,"ok","oil change") -> ok | J16: =J15 -> 10698 | K16: =J16-J15 -> 0 | L16: =L15 -> 357691 | M16: =SUM(L16-L15) -> 0 | N16: =IF(K16>0,M16/K16,0) -> 0 | P16: =P15 -> 10873 | Q16: =IF(J16-P16<=0,"ok","oil change") -> ok | R16: 13369 | S16: =R16-R15 -> 2 | T16: =T15+U16 -> 281746 | U16: =V16*S16 -> 500 | V16: 250 | X16: =13279+150 -> 13429 | Y16: =IF(R16-X16<=0,"ok","oil change") -> ok | Z16: =C16+K16+S16 -> 9 | AA16: =U16+M16+E16 -> 2250 | AB16: =V16+N16+F16 -> 500 | AC16: =IF(Z16>0,AA16/Z16,0) -> 250 | AD16: =ELEC!Q17 -> 5146 | AE16: =SUM(AD16/Z16) -> 571.77778 | AF16: =SUM(AE16/1600) -> 0.35736111 | AG16: =SUM(AF16/1600) -> 0.00022335069 | AH16: =SUM(AC16-AG16) -> 249.99978 | AI16: =AD16*AJ16 -> 1324.4979 | AJ16: =305/1185 -> 0.25738397 | AK16: =AI16/Z16 -> 147.16643 | AL16: =IF(Z16=0,0,1) -> 1
A17: =ELEC!C18 -> 44545 | B17: 11245 | C17: =B17-B16 -> 2 | D17: =D16+C17*250 -> 574266 | E17: =SUM(D17-D16) -> 500 | F17: =IF(C17>0,E17/C17,0) -> 250 | H17: =H16 -> 11374 | I17: =IF(B17-H17<=0,"ok","oil change") -> ok | J17: =J16 -> 10698 | K17: =J17-J16 -> 0 | L17: =L16 -> 357691 | M17: =SUM(L17-L16) -> 0 | N17: =IF(K17>0,M17/K17,0) -> 0 | P17: =P16 -> 10873 | Q17: =IF(J17-P17<=0,"ok","oil change") -> ok | R17: 13377 | S17: =R17-R16 -> 8 | T17: =T16+U17 -> 283746 | U17: =V17*S17 -> 2000 | V17: 250 | X17: =13279+150 -> 13429 | Y17: =IF(R17-X17<=0,"ok","oil change") -> ok | Z17: =C17+K17+S17 -> 10 | AA17: =U17+M17+E17 -> 2500 | AB17: =V17+N17+F17 -> 500 | AC17: =IF(Z17>0,AA17/Z17,0) -> 250 | AD17: =ELEC!Q18 -> 5174 | AE17: =SUM(AD17/Z17) -> 517.4 | AF17: =SUM(AE17/1600) -> 0.323375 | AG17: =SUM(AF17/1600) -> 0.00020210937 | AH17: =SUM(AC17-AG17) -> 249.9998 | AI17: =AD17*AJ17 -> 1331.7046 | AJ17: =305/1185 -> 0.25738397 | AK17: =AI17/Z17 -> 133.17046 | AL17: =IF(Z17=0,0,1) -> 1
A18: =ELEC!C19 -> 44546 | B18: 11265 | C18: =B18-B17 -> 20 | D18: =D17+C18*250 -> 579266 | E18: =SUM(D18-D17) -> 5000 | F18: =IF(C18>0,E18/C18,0) -> 250 | H18: =H17 -> 11374 | I18: =IF(B18-H18<=0,"ok","oil change") -> ok | J18: =J17 -> 10698 | K18: =J18-J17 -> 0 | L18: =L17 -> 357691 | M18: =SUM(L18-L17) -> 0 | N18: =IF(K18>0,M18/K18,0) -> 0 | P18: =P17 -> 10873 | Q18: =IF(J18-P14<=0,"ok","oil change") -> ok | R18: =R17 -> 13377 | S18: =R18-R17 -> 0 | T18: =T17+U18 -> 283746 | U18: =V18*S18 -> 0 | V18: 250 | X18: =13279+150 -> 13429 | Y18: =IF(R18-X18<=0,"ok","oil change") -> ok | Z18: =C18+K18+S18 -> 20 | AA18: =U18+M18+E18 -> 5000 | AB18: =V18+N18+F18 -> 500 | AC18: =IF(Z18>0,AA18/Z18,0) -> 250 | AD18: =ELEC!Q19 -> 9922 | AE18: =SUM(AD18/Z18) -> 496.1 | AF18: =SUM(AE18/1600) -> 0.3100625 | AG18: =SUM(AF18/1600) -> 0.00019378906 | AH18: =SUM(AC18-AG18) -> 249.99981 | AI18: =AD18*AJ18 -> 2553.7637 | AJ18: =305/1185 -> 0.25738397 | AK18: =AI18/Z18 -> 127.68819 | AL18: =IF(Z18=0,0,1) -> 1
A19: =ELEC!C20 -> 44547 | B19: =B18 -> 11265 | C19: =B19-B18 -> 0 | D19: =D18+C19*250 -> 579266 | E19: =SUM(D19-D18) -> 0 | F19: =IF(C19>0,E19/C19,0) -> 0 | H19: =H18 -> 11374 | I19: =IF(B19-H19<=0,"ok","oil change") -> ok | J19: =J18 -> 10698 | K19: =J19-J18 -> 0 | L19: =L18 -> 357691 | M19: =SUM(L19-L18) -> 0 | N19: =IF(K19>0,M19/K19,0) -> 0 | P19: =P18 -> 10873 | Q19: =IF(J19-P19<=0,"ok","oil change") -> ok | R19: =R18 -> 13377 | S19: =R19-R18 -> 0 | T19: =T18+U19 -> 283746 | U19: =V19*S19 -> 0 | V19: 250 | X19: =13279+150 -> 13429 | Y19: =IF(R19-X19<=0,"ok","oil change") -> ok | Z19: =C19+K19+S19 -> 0 | AA19: =U19+M19+E19 -> 0 | AB19: =V19+N19+F19 -> 250 | AC19: =IF(Z19>0,AA19/Z19,0) -> 0 | AD19: =ELEC!Q20 -> 0 | AE19: =SUM(AD19/Z19) -> #DIV/0! | AF19: =SUM(AE19/1600) -> #DIV/0! | AG19: =SUM(AF19/1600) -> #DIV/0! | AH19: =SUM(AC19-AG19) -> #DIV/0! | AI19: =AD19*AJ19 -> 0 | AJ19: =305/1185 -> 0.25738397 | AK19: =AI19/Z19 -> #DIV/0! | AL19: =IF(Z19=0,0,1) -> 0
A20: =ELEC!C21 -> 44548 | B20: =B19 -> 11265 | C20: =B20-B19 -> 0 | D20: =D19+C20*250 -> 579266 | E20: =SUM(D20-D19) -> 0 | F20: =IF(C20>0,E20/C20,0) -> 0 | H20: =H19 -> 11374 | I20: =IF(B20-H20<=0,"ok","oil change") -> ok | J20: =J19 -> 10698 | K20: =J20-J19 -> 0 | L20: =L19 -> 357691 | M20: =SUM(L20-L19) -> 0 | N20: =IF(K20>0,M20/K20,0) -> 0 | P20: =P19 -> 10873 | Q20: =IF(J20-P20<=0,"ok","oil change") -> ok | R20: =R19 -> 13377 | S20: =R20-R19 -> 0 | T20: =T19+U20 -> 283746 | U20: =V20*S20 -> 0 | V20: 250 | X20: =13279+150 -> 13429 | Y20: =IF(R20-X20<=0,"ok","oil change") -> ok | Z20: =C20+K20+S20 -> 0 | AA20: =U20+M20+E20 -> 0 | AB20: =V20+N20+F20 -> 250 | AC20: =IF(Z20>0,AA20/Z20,0) -> 0 | AD20: =ELEC!Q21 -> 0 | AE20: =SUM(AD20/Z20) -> #DIV/0! | AF20: =SUM(AE20/1600) -> #DIV/0! | AG20: =SUM(AF20/1600) -> #DIV/0! | AH20: =SUM(AC20-AG20) -> #DIV/0! | AI20: =AD20*AJ20 -> 0 | AJ20: =305/1185 -> 0.25738397 | AK20: =AI20/Z20 -> #DIV/0! | AL20: =IF(Z20=0,0,1) -> 0
A21: =ELEC!C22 -> 44549 | B21: 11275 | C21: =B21-B20 -> 10 | D21: =D20+C21*250 -> 581766 | E21: =SUM(D21-D20) -> 2500 | F21: =IF(C21>0,E21/C21,0) -> 250 | H21: =H20 -> 11374 | I21: =IF(B21-H21<=0,"ok","oil change") -> ok | J21: =J20 -> 10698 | K21: =J21-J20 -> 0 | L21: =L20 -> 357691 | M21: =SUM(L21-L20) -> 0 | N21: =IF(K21>0,M21/K21,0) -> 0 | P21: =P20 -> 10873 | Q21: =IF(J21-P21<=0,"ok","oil change") -> ok | R21: 13379 | S21: =R21-R20 -> 2 | T21: =T20+U21 -> 284246 | U21: =V21*S21 -> 500 | V21: 250 | X21: =13279+150 -> 13429 | Y21: =Y20 -> ok | Z21: =C21+K21+S21 -> 12 | AA21: =U21+M21+E21 -> 3000 | AB21: =V21+N21+F21 -> 500 | AC21: =IF(Z21>0,AA21/Z21,0) -> 250 | AD21: =ELEC!Q22 -> 5358 | AE21: =SUM(AD21/Z21) -> 446.5 | AF21: =SUM(AE21/1600) -> 0.2790625 | AG21: =SUM(AF21/1600) -> 0.00017441406 | AH21: =SUM(AC21-AG21) -> 249.99983 | AI21: =AD21*AJ21 -> 1379.0633 | AJ21: =305/1185 -> 0.25738397 | AK21: =AI21/Z21 -> 114.92194 | AL21: =IF(Z21=0,0,1) -> 1
A22: =ELEC!C23 -> 44550 | B22: 11278 | C22: =B22-B21 -> 3 | D22: =D21+C22*250 -> 582516 | E22: =150*C22 -> 450 | F22: =IF(C22>0,E22/C22,0) -> 150 | H22: =H21 -> 11374 | I22: =IF(B22-H22<=0,"ok","oil change") -> ok | J22: =J21 -> 10698 | K22: =J22-J21 -> 0 | L22: =L21 -> 357691 | M22: =SUM(L22-L21) -> 0 | N22: =IF(K22>0,M22/K22,0) -> 0 | P22: =P21 -> 10873 | Q22: =IF(J22-P22<=0,"ok","oil change") -> ok | R22: 13387 | S22: =R22-R21 -> 8 | T22: =T21+U22 -> 286246 | U22: =V22*S22 -> 2000 | V22: 250 | X22: =13279+150 -> 13429 | Y22: =Y21 -> ok | Z22: =C22+K22+S22 -> 11 | AA22: =U22+M22+E22 -> 2450 | AB22: =V22+N22+F22 -> 400 | AC22: =IF(Z22>0,AA22/Z22,0) -> 222.72727 | AD22: =ELEC!Q23 -> 5702 | AE22: =SUM(AD22/Z22) -> 518.36364 | AF22: =SUM(AE22/1600) -> 0.32397727 | AG22: =SUM(AF22/1600) -> 0.0002024858 | AH22: =SUM(AC22-AG22) -> 222.72707 | AI22: =AD22*AJ22 -> 1467.6034 | AJ22: =305/1185 -> 0.25738397 | AK22: =AI22/Z22 -> 133.41849 | AL22: =IF(Z22=0,0,1) -> 1
A23: =ELEC!C24 -> 44551 | B23: 11290 | C23: =B23-B22 -> 12 | D23: =D22+C23*250 -> 585516 | E23: =150*C23 -> 1800 | F23: =IF(C23>0,E23/C23,0) -> 150 | H23: =H22 -> 11374 | I23: =IF(B23-H23<=0,"ok","oil change") -> ok | J23: =J22 -> 10698 | K23: =J23-J22 -> 0 | L23: =L22 -> 357691 | M23: =SUM(L23-L22) -> 0 | N23: =IF(K23>0,M23/K23,0) -> 0 | P23: =P22 -> 10873 | Q23: =IF(J23-P23<=0,"ok","oil change") -> ok | R23: =R22 -> 13387 | S23: =R23-R22 -> 0 | T23: =T22+U23 -> 286246 | U23: =V23*S23 -> 0 | V23: 250 | X23: =13279+150 -> 13429 | Y23: =Y22 -> ok | Z23: =C23+K23+S23 -> 12 | AA23: =U23+M23+E23 -> 1800 | AB23: =V23+N23+F23 -> 400 | AC23: =IF(Z23>0,AA23/Z23,0) -> 150 | AD23: =ELEC!Q24 -> 6401 | AE23: =SUM(AD23/Z23) -> 533.41667 | AF23: =SUM(AE23/1600) -> 0.33338542 | AG23: =SUM(AF23/1600) -> 0.00020836589 | AH23: =SUM(AC23-AG23) -> 149.99979 | AI23: =AD23*AJ23 -> 1647.5148 | AJ23: =305/1185 -> 0.25738397 | AK23: =AI23/Z23 -> 137.2929 | AL23: =IF(Z23=0,0,1) -> 1
A24: =ELEC!C25 -> 44552 | B24: 11293 | C24: =B24-B23 -> 3 | D24: =D23+C24*250 -> 586266 | E24: =SUM(D24-D23) -> 750 | F24: =IF(C24>0,E24/C24,0) -> 250 | H24: =H23 -> 11374 | I24: =IF(B24-H24<=0,"ok","oil change") -> ok | J24: =J23 -> 10698 | K24: =J24-J23 -> 0 | L24: =L23 -> 357691 | M24: =SUM(L24-L23) -> 0 | N24: =IF(K24>0,M24/K24,0) -> 0 | P24: =P23 -> 10873 | Q24: =IF(J24-P24<=0,"ok","oil change") -> ok | R24: 13396 | S24: =R24-R23 -> 9 | T24: =T23+U24 -> 288496 | U24: =V24*S24 -> 2250 | V24: 250 | X24: =13279+150 -> 13429 | Y24: =Y23 -> ok | Z24: =C24+K24+S24 -> 12 | AA24: =U24+M24+E24 -> 3000 | AB24: =V24+N24+F24 -> 500 | AC24: =IF(Z24>0,AA24/Z24,0) -> 250 | AD24: =ELEC!Q25 -> 5686 | AE24: =SUM(AD24/Z24) -> 473.83333 | AF24: =SUM(AE24/1600) -> 0.29614583 | AG24: =SUM(AF24/1600) -> 0.00018509115 | AH24: =SUM(AC24-AG24) -> 249.99981 | AI24: =AD24*AJ24 -> 1463.4852 | AJ24: =305/1185 -> 0.25738397 | AK24: =AI24/Z24 -> 121.9571 | AL24: =IF(Z24=0,0,1) -> 1
A25: =ELEC!C26 -> 44553 | B25: 11301 | C25: =B25-B24 -> 8 | D25: =D24+C25*250 -> 588266 | E25: =SUM(D25-D24) -> 2000 | F25: =IF(C25>0,E25/C25,0) -> 250 | H25: =H24 -> 11374 | I25: =IF(B25-H25<=0,"ok","oil change") -> ok | J25: =J24 -> 10698 | K25: =J25-J24 -> 0 | L25: =L24 -> 357691 | M25: =SUM(L25-L24) -> 0 | N25: =IF(K25>0,M25/K25,0) -> 0 | P25: =P24 -> 10873 | Q25: =IF(J25-P25<=0,"ok","oil change") -> ok | R25: 13397 | S25: =R25-R24 -> 1 | T25: =T24+U25 -> 288746 | U25: =V25*S25 -> 250 | V25: 250 | X25: =13279+150 -> 13429 | Y25: =Y24 -> ok | Z25: =C25+K25+S25 -> 9 | AA25: =U25+M25+E25 -> 2250 | AB25: =V25+N25+F25 -> 500 | AC25: =IF(Z25>0,AA25/Z25,0) -> 250 | AD25: =ELEC!Q26 -> 4388 | AE25: =SUM(AD25/Z25) -> 487.55556 | AF25: =SUM(AE25/1600) -> 0.30472222 | AG25: =SUM(AF25/1600) -> 0.00019045139 | AH25: =SUM(AC25-AG25) -> 249.99981 | AI25: =AD25*AJ25 -> 1129.4008 | AJ25: =305/1185 -> 0.25738397 | AK25: =AI25/Z25 -> 125.48898 | AL25: =IF(Z25=0,0,1) -> 1
A26: =ELEC!C27 -> 44554 | B26: =B25 -> 11301 | C26: =B26-B25 -> 0 | D26: =D25+C26*250 -> 588266 | E26: =SUM(D26-D25) -> 0 | F26: =IF(C26>0,E26/C26,0) -> 0 | H26: =H25 -> 11374 | I26: =IF(B26-H26<=0,"ok","oil change") -> ok | J26: =J25 -> 10698 | K26: =J26-J25 -> 0 | L26: =L25 -> 357691 | M26: =SUM(L26-L25) -> 0 | N26: =IF(K26>0,M26/K26,0) -> 0 | P26: =P25 -> 10873 | Q26: =IF(J26-P26<=0,"ok","oil change") -> ok | R26: =R25 -> 13397 | S26: =R26-R25 -> 0 | T26: =T25+U26 -> 288746 | U26: =V26*S26 -> 0 | V26: 250 | X26: =13279+150 -> 13429 | Y26: =Y25 -> ok | Z26: =C26+K26+S26 -> 0 | AA26: =U26+M26+E26 -> 0 | AB26: =V26+N26+F26 -> 250 | AC26: =IF(Z26>0,AA26/Z26,0) -> 0 | AD26: =ELEC!Q27 -> 0 | AE26: =SUM(AD26/Z26) -> #DIV/0! | AF26: =SUM(AE26/1600) -> #DIV/0! | AG26: =SUM(AF26/1600) -> #DIV/0! | AH26: =SUM(AC26-AG26) -> #DIV/0! | AI26: =AD26*AJ26 -> 0 | AJ26: =305/1185 -> 0.25738397 | AK26: =AI26/Z26 -> #DIV/0! | AL26: =IF(Z26=0,0,1) -> 0
A27: =ELEC!C28 -> 44555 | B27: =B26 -> 11301 | C27: =B27-B26 -> 0 | D27: =D26+C27*250 -> 588266 | E27: =SUM(D27-D26) -> 0 | F27: =IF(C27>0,E27/C27,0) -> 0 | H27: =H26 -> 11374 | I27: =IF(B27-H27<=0,"ok","oil change") -> ok | J27: =J26 -> 10698 | K27: =J27-J26 -> 0 | L27: =L26 -> 357691 | M27: =SUM(L27-L26) -> 0 | N27: =IF(K27>0,M27/K27,0) -> 0 | P27: =P26 -> 10873 | Q27: =IF(J27-P27<=0,"ok","oil change") -> ok | R27: =R26 -> 13397 | S27: =R27-R26 -> 0 | T27: =T26+U27 -> 288746 | U27: =V27*S27 -> 0 | V27: 250 | X27: =13279+150 -> 13429 | Y27: =Y26 -> ok | Z27: =C27+K27+S27 -> 0 | AA27: =U27+M27+E27 -> 0 | AB27: =V27+N27+F27 -> 250 | AC27: =IF(Z27>0,AA27/Z27,0) -> 0 | AD27: =ELEC!Q28 -> 0 | AE27: =SUM(AD27/Z27) -> #DIV/0! | AF27: =SUM(AE27/1600) -> #DIV/0! | AG27: =SUM(AF27/1600) -> #DIV/0! | AH27: =SUM(AC27-AG27) -> #DIV/0! | AI27: =AD27*AJ27 -> 0 | AJ27: =305/1185 -> 0.25738397 | AK27: =AI27/Z27 -> #DIV/0! | AL27: =IF(Z27=0,0,1) -> 0
A28: =ELEC!C29 -> 44556 | B28: =B27 -> 11301 | C28: =B28-B27 -> 0 | D28: =D27+C28*250 -> 588266 | E28: =SUM(D28-D27) -> 0 | F28: =IF(C28>0,E28/C28,0) -> 0 | H28: =H27 -> 11374 | I28: =IF(B28-H28<=0,"ok","oil change") -> ok | J28: =J27 -> 10698 | K28: =J28-J27 -> 0 | L28: =L27 -> 357691 | M28: =SUM(L28-L27) -> 0 | N28: =IF(K28>0,M28/K28,0) -> 0 | P28: =P27 -> 10873 | Q28: =IF(J28-P28<=0,"ok","oil change") -> ok | R28: =R27 -> 13397 | S28: =R28-R27 -> 0 | T28: =T27+U28 -> 288746 | U28: =V28*S28 -> 0 | V28: 250 | X28: =13279+150 -> 13429 | Y28: =Y27 -> ok | Z28: =C28+K28+S28 -> 0 | AA28: =U28+M28+E28 -> 0 | AB28: =V28+N28+F28 -> 250 | AC28: =IF(Z28>0,AA28/Z28,0) -> 0 | AD28: =ELEC!Q29 -> 0 | AE28: =SUM(AD28/Z28) -> #DIV/0! | AF28: =SUM(AE28/1600) -> #DIV/0! | AG28: =SUM(AF28/1600) -> #DIV/0! | AH28: =SUM(AC28-AG28) -> #DIV/0! | AI28: =AD28*AJ28 -> 0 | AJ28: =305/1185 -> 0.25738397 | AK28: =AI28/Z28 -> #DIV/0! | AL28: =IF(Z28=0,0,1) -> 0
A29: =ELEC!C30 -> 44557 | B29: 11303 | C29: =B29-B28 -> 2 | D29: =D28+C29*250 -> 588766 | E29: =SUM(D29-D28) -> 500 | F29: =IF(C29>0,E29/C29,0) -> 250 | H29: =H28 -> 11374 | I29: =IF(B29-H29<=0,"ok","oil change") -> ok | J29: =J28 -> 10698 | K29: =J29-J28 -> 0 | L29: =L28 -> 357691 | M29: =SUM(L29-L28) -> 0 | N29: =IF(K29>0,M29/K29,0) -> 0 | P29: =P28 -> 10873 | Q29: =IF(J29-P29<=0,"ok","oil change") -> ok | R29: 13405 | S29: =R29-R28 -> 8 | T29: =T28+U29 -> 290746 | U29: =V29*S29 -> 2000 | V29: 250 | X29: =13279+150 -> 13429 | Y29: =Y28 -> ok | Z29: =C29+K29+S29 -> 10 | AA29: =U29+M29+E29 -> 2500 | AB29: =V29+N29+F29 -> 500 | AC29: =IF(Z29>0,AA29/Z29,0) -> 250 | AD29: =ELEC!Q30 -> 5141 | AE29: =SUM(AD29/Z29) -> 514.1 | AF29: =SUM(AE29/1600) -> 0.3213125 | AG29: =SUM(AF29/1600) -> 0.00020082031 | AH29: =SUM(AC29-AG29) -> 249.9998 | AI29: =AD29*AJ29 -> 1323.211 | AJ29: =305/1185 -> 0.25738397 | AK29: =AI29/Z29 -> 132.3211 | AL29: =IF(Z29=0,0,1) -> 1
A30: =ELEC!C31 -> 44558 | B30: 11313 | C30: =B30-B29 -> 10 | D30: =D29+C30*250 -> 591266 | E30: =SUM(D30-D29) -> 2500 | F30: =IF(C30>0,E30/C30,0) -> 250 | H30: =H29 -> 11374 | I30: =IF(B30-H30<=0,"ok","oil change") -> ok | J30: =J29 -> 10698 | K30: =J30-J29 -> 0 | L30: =L29 -> 357691 | M30: =SUM(L30-L29) -> 0 | N30: =IF(K30>0,M30/K30,0) -> 0 | P30: =P29 -> 10873 | Q30: =IF(J30-P30<=0,"ok","oil change") -> ok | R30: =R29 -> 13405 | S30: =R30-R29 -> 0 | T30: =T29+U30 -> 290746 | U30: =V30*S30 -> 0 | V30: 250 | X30: =13279+150 -> 13429 | Y30: =Y29 -> ok | Z30: =C30+K30+S30 -> 10 | AA30: =U30+M30+E30 -> 2500 | AB30: =V30+N30+F30 -> 500 | AC30: =IF(Z30>0,AA30/Z30,0) -> 250 | AD30: =ELEC!Q31 -> 5295 | AE30: =SUM(AD30/Z30) -> 529.5 | AF30: =SUM(AE30/1600) -> 0.3309375 | AG30: =SUM(AF30/1600) -> 0.00020683594 | AH30: =SUM(AC30-AG30) -> 249.99979 | AI30: =AD30*AJ30 -> 1362.8481 | AJ30: =305/1185 -> 0.25738397 | AK30: =AI30/Z30 -> 136.28481 | AL30: =IF(Z30=0,0,1) -> 1
A31: =ELEC!C32 -> 44559 | B31: 11317 | C31: =B31-B30 -> 4 | D31: =D30+C31*250 -> 592266 | E31: =SUM(D31-D30) -> 1000 | F31: =IF(C31>0,E31/C31,0) -> 250 | H31: =H30 -> 11374 | I31: =IF(B31-H31<=0,"ok","oil change") -> ok | J31: =J30 -> 10698 | K31: =J31-J30 -> 0 | L31: =L30 -> 357691 | M31: =SUM(L31-L30) -> 0 | N31: =IF(K31>0,M31/K31,0) -> 0 | P31: =P30 -> 10873 | Q31: =IF(J31-P31<=0,"ok","oil change") -> ok | R31: 13411 | S31: =R31-R30 -> 6 | T31: =T30+U31 -> 292246 | U31: =V31*S31 -> 1500 | V31: 250 | X31: =13279+150 -> 13429 | Y31: =Y30 -> ok | Z31: =C31+K31+S31 -> 10 | AA31: =U31+M31+E31 -> 2500 | AB31: =V31+N31+F31 -> 500 | AC31: =IF(Z31>0,AA31/Z31,0) -> 250 | AD31: =ELEC!Q32 -> 5831 | AE31: =SUM(AD31/Z31) -> 583.1 | AF31: =SUM(AE31/1600) -> 0.3644375 | AG31: =SUM(AF31/1600) -> 0.00022777344 | AH31: =SUM(AC31-AG31) -> 249.99977 | AI31: =AD31*AJ31 -> 1500.8059 | AJ31: =305/1185 -> 0.25738397 | AK31: =AI31/Z31 -> 150.08059 | AL31: =IF(Z31=0,0,1) -> 1
A32: =ELEC!C33 -> 44560 | B32: =B31 -> 11317 | C32: =B32-B31 -> 0 | D32: =D31+C32*250 -> 592266 | E32: =SUM(D32-D31) -> 0 | F32: =IF(C32>0,E32/C32,0) -> 0 | H32: =H31 -> 11374 | I32: =IF(B32-H32<=0,"ok","oil change") -> ok | J32: =J31 -> 10698 | K32: =J32-J31 -> 0 | L32: =L31 -> 357691 | M32: =SUM(L32-L31) -> 0 | N32: =IF(K32>0,M32/K32,0) -> 0 | P32: =P31 -> 10873 | Q32: =IF(J32-P32<=0,"ok","oil change") -> ok | R32: =R31 -> 13411 | S32: =R32-R31 -> 0 | T32: =T31+U32 -> 292246 | U32: =V32*S32 -> 0 | V32: 250 | X32: =13279+150 -> 13429 | Y32: =Y31 -> ok | Z32: =C32+K32+S32 -> 0 | AA32: =U32+M32+E32 -> 0 | AB32: =V32+N32+F32 -> 250 | AC32: =IF(Z32>0,AA32/Z32,0) -> 0 | AD32: =ELEC!Q33 -> 0 | AE32: =SUM(AD32/Z32) -> #DIV/0! | AF32: =SUM(AE32/1600) -> #DIV/0! | AG32: =SUM(AF32/1600) -> #DIV/0! | AH32: =SUM(AC32-AG32) -> #DIV/0! | AI32: =AD32*AJ32 -> 0 | AJ32: =305/1185 -> 0.25738397 | AK32: =AI32/Z32 -> #DIV/0! | AL32: =IF(Z32=0,0,1) -> 0
A33: =ELEC!C34 -> 44561 | B33: =B32 -> 11317 | C33: =B33-B32 -> 0 | D33: =D32+C33*250 -> 592266 | E33: =SUM(D33-D32) -> 0 | F33: =IF(C33>0,E33/C33,0) -> 0 | H33: =H32 -> 11374 | I33: =IF(B33-H33<=0,"ok","oil change") -> ok | J33: =J32 -> 10698 | K33: =J33-J32 -> 0 | L33: =L32 -> 357691 | M33: =SUM(L33-L32) -> 0 | N33: =IF(K33>0,M33/K33,0) -> 0 | P33: =P32 -> 10873 | Q33: =IF(J33-P33<=0,"ok","oil change") -> ok | R33: =R32 -> 13411 | S33: =R33-R32 -> 0 | T33: =T32+U33 -> 292246 | U33: =V33*S33 -> 0 | V33: 251 | X33: =13279+150 -> 13429 | Y33: =Y32 -> ok | Z33: =C33+K33+S33 -> 0 | AA33: =U33+M33+E33 -> 0 | AB33: =V33+N33+F33 -> 251 | AC33: =IF(Z33>0,AA33/Z33,0) -> 0 | AD33: =ELEC!Q34 -> 0 | AE33: =SUM(AD33/Z33) -> #DIV/0! | AF33: =SUM(AE33/1600) -> #DIV/0! | AG33: =SUM(AF33/1600) -> #DIV/0! | AH33: =SUM(AC33-AG33) -> #DIV/0! | AI33: =AD33*AJ33 -> 0 | AJ33: =305/1185 -> 0.25738397 | AK33: =AI33/Z33 -> #DIV/0! | AL33: =IF(Z33=0,0,1) -> 0
P34: =+O34/3 -> 0 | U34: =SUM(C35:S35) -> 218 | X34: 341 | Z34: =SUM(Z3:Z33) -> 218 | AF34: =SUM(AE34/1600) -> 0 | AL34: =SUM(AL3:AL33) -> 20
C35: =SUM(C3:C33) -> 119 | K35: =SUM(K3:K33) -> 0 | S35: =SUM(S3:S33) -> 99

Sheet tanks
B2: Tank 1 | D2: Tank 2 | F2: Tank 3 | H2: Tank 4 | J2: Tank 5 | L2: Tank 6 | N2: Tank 7 | P2: Tank 8 | R2: Tank 9 | T2: Tank 10 | V2: Tank 11 | Z2: Tank 1 | AB2: Tank 2 | AD2: Tank 3 | AF2: Tank 4 | AH2: Tank 5 | AJ2: Tank 6 | AL2: Tank 7
B3: 6670 | D3: =SUM(B3) -> 6670 | F3: =SUM(D3) -> 6670 | H3: =SUM(F3) -> 6670 | J3: =SUM(H3) -> 6670 | L3: =SUM(J3) -> 6670 | N3: =SUM(L3) -> 6670 | P3: =SUM(N3) -> 6670 | R3: =SUM(P3) -> 6670 | T3: =SUM(R3) -> 6670 | V3: =SUM(T3) -> 6670 | W3: =SUM(B3:V3) -> 73370 | Z3: 2800 | AB3: 2800 | AD3: 2800 | AF3: 2800 | AH3: 2800 | AJ3: 2800 | AL3: 2800 | AM3: =SUM(Z3:AL3) -> 19600 | AO3: =SUM(AM3+W3) -> 92970 | AR3: Total sotck | AS3: Diesel Cons Per day | AT3: Diesel Delivery | BE3: Genset Co | BF3: Steam | BG3: Boil | BH3: Outdoor temperature
B4: =B3/310 -> 21.516129 | D4: =SUM(B4) -> 21.516129 | F4: =SUM(D4) -> 21.516129 | H4: =SUM(F4) -> 21.516129 | J4: =SUM(H4) -> 21.516129 | L4: =SUM(J4) -> 21.516129 | N4: =SUM(L4) -> 21.516129 | P4: =SUM(N4) -> 21.516129 | R4: =SUM(P4) -> 21.516129 | T4: =SUM(R4) -> 21.516129 | V4: =SUM(T4) -> 21.516129 | Z4: =Z3/280 -> 10 | AA4: =AA3/280 -> 0 | AB4: =AB3/280 -> 10 | AC4: =AC3/280 -> 0 | AD4: =AD3/280 -> 10 | AE4: =AE3/280 -> 0 | AF4: =AF3/280 -> 10 | AG4: =AG3/280 -> 0 | ... AL4: =AL3/280 -> 10 | AT4: Delivery | AU4: Cost /L | AW4: Boiler+Steam | AX4: Generator | AZ4: Occupancy | BA4: AVE TEPM | BB4: AVE Humidity
A5: =[2]tanks!$A$35 -> 44530 | B5: =[2]tanks!B36 -> 218 | C5: =[2]tanks!C36 -> 4690.5161 | D5: =[2]tanks!D36 -> 218 | E5: =[2]tanks!E36 -> 4690.5161 | F5: =[2]tanks!F36 -> 218 | G5: =[2]tanks!G36 -> 4690.5161 | H5: =[2]tanks!H36 -> 218 | I5: =[2]tanks!I36 -> 4690.5161 | ... AO5: =[2]tanks!AO36 -> 15680 | AQ5: =[2]tanks!$AQ$36 -> 0.72362781 | AR5: =[2]tanks!$AR$36 -> 67275.677 | AS5: =[2]tanks!$AS$36 -> 0 | AT5: =[5]tanks!$AT$36 -> 0 | AU5: =[5]tanks!$AU$36 -> 0 | AV5: =[2]tanks!$AV$35 -> 0.71 | AW5: =[2]tanks!AW36 -> 0 | AX5: =[2]tanks!AX36 -> 0 | AY5: =[2]tanks!AY36 -> 0 | AZ5: =[2]tanks!AZ36 -> 0 | BA5: =[2]tanks!BA36 -> 0 | BB5: =[2]tanks!BB36 -> 0 | BC5: =[2]tanks!BC36 -> 0 | BD5: =[2]tanks!BD36 -> 0 | ... BI5: =[2]tanks!BI36 -> 23
A6: =ELEC!C4 -> 44531 | B6: ='B5'!B5 -> 210 | C6: =B6*$B$4 -> 4518.3871 | D6: =SUM(B6) -> 210 | E6: =D6*$B$4 -> 4518.3871 | F6: =SUM(D6) -> 210 | G6: =F6*$B$4 -> 4518.3871 | H6: =SUM(F6) -> 210 | I6: =H6*$B$4 -> 4518.3871 | J6: =SUM(H6) -> 210 | K6: =J6*$B$4 -> 4518.3871 | L6: =SUM(J6) -> 210 | M6: =L6*$B$4 -> 4518.3871 | N6: =SUM(L6) -> 210 | O6: =N6*$B$4 -> 4518.3871 | P6: =SUM(N6) -> 210 | Q6: =P6*$B$4 -> 4518.3871 | R6: =SUM(P6) -> 210 | S6: =R6*$B$4 -> 4518.3871 | T6: =SUM(R6) -> 210 | U6: =T6*$B$4 -> 4518.3871 | V6: =SUM(T6) -> 210 | W6: =V6*$B$4 -> 4518.3871 | X6: =SUM(Y6/73370) -> 0.67741935 | Y6: =SUM(C6+E6+G6+I6+K6+M6+O6+Q6+S6+U6+W6) -> 49702.258 | Z6: ='B5'!C5 -> 218 | AA6: =SUM(Z6*$Z$4) -> 2180 | AB6: =SUM(Z6) -> 218 | AC6: =SUM(AB6*$Z$4) -> 2180 | AD6: =SUM(AB6) -> 218 | AE6: =SUM(AD6*$Z$4) -> 2180 | AF6: =SUM(AD6) -> 218 | AG6: =SUM(AF6*$Z$4) -> 2180 | AH6: =SUM(AF6) -> 218 | AI6: =SUM(AH6*$Z$4) -> 2180 | AJ6: =SUM(AH6) -> 218 | AK6: =SUM(AJ6*$Z$4) -> 2180 | AL6: =SUM(AJ6) -> 218 | AM6: =SUM(AL6*$Z$4) -> 2180 | AN6: =SUM(AO6/19600) -> 0.77857143 | AO6: =SUM(AA6+AC6+AE6+AG6+AI6+AK6+AM6) -> 15260 | AQ6: =SUM(AR6/92970) -> 0.69874431 | AR6: =Y6+AO6 -> 64962.258 | AS6: =SUM(AR6-AR5-AT6) -> -2313.4194 | AV6: =IF(AT6>0,AU6,AV5) -> 0.71 | AW6: =-SUM('B5'!AI5) -> 0 | AX6: =-SUM(AW6-AS6) -> -2313.4194 | AY6: =SUM(AX6+AW6) -> -2313.4194 | AZ6: =ELEC!A4 -> 0 | BA6: ='General information '!D5 -> 18.5 | BB6: =SUM('General information '!E5) -> 0.66 | BC6: =IF(AR3>=AR6,0,1) -> 0 | BD6: 19222 | BE6: =(305/1185)*ELEC!Q5 -> 1380.3502 | BG6: =#REF!-BE6 -> #REF! | BH6: 21 | BI6: 12 | BJ6: =AX6/BI6 -> -192.78495 | BK6: =GEN!AF3 -> 0.35221591
A7: =ELEC!C5 -> 44532 | B7: ='B5'!B6 -> 204 | C7: =B7*$B$4 -> 4389.2903 | D7: =SUM(B7) -> 204 | E7: =D7*$B$4 -> 4389.2903 | F7: =SUM(D7) -> 204 | G7: =F7*$B$4 -> 4389.2903 | H7: =SUM(F7) -> 204 | I7: =H7*$B$4 -> 4389.2903 | J7: =SUM(H7) -> 204 | K7: =J7*$B$4 -> 4389.2903 | L7: =SUM(J7) -> 204 | M7: =L7*$B$4 -> 4389.2903 | N7: =SUM(L7) -> 204 | O7: =N7*$B$4 -> 4389.2903 | P7: =SUM(N7) -> 204 | Q7: =P7*$B$4 -> 4389.2903 | R7: =SUM(P7) -> 204 | S7: =R7*$B$4 -> 4389.2903 | T7: =SUM(R7) -> 204 | U7: =T7*$B$4 -> 4389.2903 | V7: =SUM(T7) -> 204 | W7: =V7*$B$4 -> 4389.2903 | X7: =SUM(Y7/73370) -> 0.65806452 | Y7: =SUM(C7+E7+G7+I7+K7+M7+O7+Q7+S7+U7+W7) -> 48282.194 | Z7: ='B5'!C6 -> 211 | AA7: =SUM(Z7*$Z$4) -> 2110 | AB7: =SUM(Z7) -> 211 | AC7: =SUM(AB7*$Z$4) -> 2110 | AD7: =SUM(AB7) -> 211 | AE7: =SUM(AD7*$Z$4) -> 2110 | AF7: =SUM(AD7) -> 211 | AG7: =SUM(AF7*$Z$4) -> 2110 | AH7: =SUM(AF7) -> 211 | AI7: =SUM(AH7*$Z$4) -> 2110 | AJ7: =SUM(AH7) -> 211 | AK7: =SUM(AJ7*$Z$4) -> 2110 | AL7: =SUM(AJ7) -> 211 | AM7: =SUM(AL7*$Z$4) -> 2110 | AN7: =SUM(AO7/19600) -> 0.75357143 | AO7: =SUM(AA7+AC7+AE7+AG7+AI7+AK7+AM7) -> 14770 | AQ7: =SUM(AR7/92970) -> 0.67819935 | AR7: =Y7+AO7 -> 63052.194 | AS7: =SUM(AR7-AR6-AT7) -> -1910.0645 | AV7: =IF(AT7>0,AU7,AV6) -> 0.71 | AW7: =-SUM('B5'!AI6) -> 0 | AX7: =-SUM(AW7-AS7) -> -1910.0645 | AY7: =SUM(AX7+AW7) -> -1910.0645 | AZ7: =ELEC!A5 -> 0 | BA7: ='General information '!D6 -> 18 | BB7: =SUM('General information '!E6) -> 0.54 | BC7: 0 | BD7: 19222 | BE7: =(305/1185)*ELEC!Q6 -> 0 | BG7: =#REF!-BE7 -> #REF! | BH7: 19 | BI7: 15 | BJ7: =AX7/BI7 -> -127.33763 | BK7: =GEN!AF4 -> 0.27932292
A8: =ELEC!C6 -> 44533 | B8: ='B5'!B7 -> 204 | C8: =B8*$B$4 -> 4389.2903 | D8: =SUM(B8) -> 204 | E8: =D8*$B$4 -> 4389.2903 | F8: =SUM(D8) -> 204 | G8: =F8*$B$4 -> 4389.2903 | H8: =SUM(F8) -> 204 | I8: =H8*$B$4 -> 4389.2903 | J8: =SUM(H8) -> 204 | K8: =J8*$B$4 -> 4389.2903 | L8: =SUM(J8) -> 204 | M8: =L8*$B$4 -> 4389.2903 | N8: =SUM(L8) -> 204 | O8: =N8*$B$4 -> 4389.2903 | P8: =SUM(N8) -> 204 | Q8: =P8*$B$4 -> 4389.2903 | R8: =SUM(P8) -> 204 | S8: =R8*$B$4 -> 4389.2903 | T8: =SUM(R8) -> 204 | U8: =T8*$B$4 -> 4389.2903 | V8: =SUM(T8) -> 204 | W8: =V8*$B$4 -> 4389.2903 | X8: =SUM(Y8/73370) -> 0.65806452 | Y8: =SUM(C8+E8+G8+I8+K8+M8+O8+Q8+S8+U8+W8) -> 48282.194 | Z8: ='B5'!C7 -> 211 | AA8: =SUM(Z8*$Z$4) -> 2110 | AB8: =SUM(Z8) -> 211 | AC8: =SUM(AB8*$Z$4) -> 2110 | AD8: =SUM(AB8) -> 211 | AE8: =SUM(AD8*$Z$4) -> 2110 | AF8: =SUM(AD8) -> 211 | AG8: =SUM(AF8*$Z$4) -> 2110 | AH8: =SUM(AF8) -> 211 | AI8: =SUM(AH8*$Z$4) -> 2110 | AJ8: =SUM(AH8) -> 211 | AK8: =SUM(AJ8*$Z$4) -> 2110 | AL8: =SUM(AJ8) -> 211 | AM8: =SUM(AL8*$Z$4) -> 2110 | AN8: =SUM(AO8/19600) -> 0.75357143 | AO8: =SUM(AA8+AC8+AE8+AG8+AI8+AK8+AM8) -> 14770 | AQ8: =SUM(AR8/92970) -> 0.67819935 | AR8: =Y8+AO8 -> 63052.194 | AS8: =SUM(AR8-AR7-AT8) -> 0 | AV8: =IF(AT8>0,AU8,AV7) -> 0.71 | AW8: =-SUM('B5'!AI7) -> 0 | AX8: =-SUM(AW8-AS8) -> 0 | AY8: =SUM(AX8+AW8) -> 0 | AZ8: =ELEC!A6 -> 0 | BA8: ='General information '!D7 -> 0 | BB8: =SUM('General information '!E7) -> 0 | BC8: =IF(AR7>=AR8,0,1) -> 0 | BD8: 19222 | BE8: =(305/1185)*ELEC!Q7 -> 0 | BG8: =#REF!-BE8 -> #REF! | BH8: 16 | BI8: 9 | BJ8: =AX8/BI8 -> 0 | BK8: =GEN!AF5 -> #DIV/0!
A9: =ELEC!C7 -> 44534 | B9: ='B5'!B8 -> 204 | C9: =B9*$B$4 -> 4389.2903 | D9: =SUM(B9) -> 204 | E9: =D9*$B$4 -> 4389.2903 | F9: =SUM(D9) -> 204 | G9: =F9*$B$4 -> 4389.2903 | H9: =SUM(F9) -> 204 | I9: =H9*$B$4 -> 4389.2903 | J9: =SUM(H9) -> 204 | K9: =J9*$B$4 -> 4389.2903 | L9: =SUM(J9) -> 204 | M9: =L9*$B$4 -> 4389.2903 | N9: =SUM(L9) -> 204 | O9: =N9*$B$4 -> 4389.2903 | P9: =SUM(N9) -> 204 | Q9: =P9*$B$4 -> 4389.2903 | R9: =SUM(P9) -> 204 | S9: =R9*$B$4 -> 4389.2903 | T9: =SUM(R9) -> 204 | U9: =T9*$B$4 -> 4389.2903 | V9: =SUM(T9) -> 204 | W9: =V9*$B$4 -> 4389.2903 | X9: =SUM(Y9/73370) -> 0.65806452 | Y9: =SUM(C9+E9+G9+I9+K9+M9+O9+Q9+S9+U9+W9) -> 48282.194 | Z9: ='B5'!C8 -> 211 | AA9: =SUM(Z9*$Z$4) -> 2110 | AB9: =SUM(Z9) -> 211 | AC9: =SUM(AB9*$Z$4) -> 2110 | AD9: =SUM(AB9) -> 211 | AE9: =SUM(AD9*$Z$4) -> 2110 | AF9: =SUM(AD9) -> 211 | AG9: =SUM(AF9*$Z$4) -> 2110 | AH9: =SUM(AF9) -> 211 | AI9: =SUM(AH9*$Z$4) -> 2110 | AJ9: =SUM(AH9) -> 211 | AK9: =SUM(AJ9*$Z$4) -> 2110 | AL9: =SUM(AJ9) -> 211 | AM9: =SUM(AL9*$Z$4) -> 2110 | AN9: =SUM(AO9/19600) -> 0.75357143 | AO9: =SUM(AA9+AC9+AE9+AG9+AI9+AK9+AM9) -> 14770 | AQ9: =SUM(AR9/92970) -> 0.67819935 | AR9: =Y9+AO9 -> 63052.194 | AS9: =SUM(AR9-AR8-AT9) -> 0 | AV9: =IF(AT9>0,AU9,AV8) -> 0.71 | AW9: =-SUM('B5'!AI8) -> 0 | AX9: =-SUM(AW9-AS9) -> 0 | AY9: =SUM(AX9+AW9) -> 0 | AZ9: =ELEC!A7 -> 0 | BA9: ='General information '!D8 -> 0 | BB9: =SUM('General information '!E8) -> 0 | BC9: =IF(AR8>=AR9,0,1) -> 0 | BD9: 19222 | BE9: =(305/1185)*ELEC!Q8 -> 1684.5781 | BG9: =#REF!-BE9 -> #REF! | BH9: 18 | BI9: 6 | BJ9: =AX9/BI9 -> 0 | BK9: =GEN!AF6 -> #DIV/0!
A10: =ELEC!C8 -> 44535 | B10: ='B5'!B9 -> 236 | C10: =B10*$B$4 -> 5077.8065 | D10: =SUM(B10) -> 236 | E10: =D10*$B$4 -> 5077.8065 | F10: =SUM(D10) -> 236 | G10: =F10*$B$4 -> 5077.8065 | H10: =SUM(F10) -> 236 | I10: =H10*$B$4 -> 5077.8065 | J10: =SUM(H10) -> 236 | K10: =J10*$B$4 -> 5077.8065 | L10: =SUM(J10) -> 236 | M10: =L10*$B$4 -> 5077.8065 | N10: =SUM(L10) -> 236 | O10: =N10*$B$4 -> 5077.8065 | P10: =SUM(N10) -> 236 | Q10: =P10*$B$4 -> 5077.8065 | R10: =SUM(P10) -> 236 | S10: =R10*$B$4 -> 5077.8065 | T10: =SUM(R10) -> 236 | U10: =T10*$B$4 -> 5077.8065 | V10: =SUM(T10) -> 236 | W10: =V10*$B$4 -> 5077.8065 | X10: =SUM(Y10/73370) -> 0.76129032 | Y10: =SUM(C10+E10+G10+I10+K10+M10+O10+Q10+S10+U10+W10) -> 55855.871 | Z10: ='B5'!C9 -> 241 | AA10: =SUM(Z10*$Z$4) -> 2410 | AB10: =SUM(Z10) -> 241 | AC10: =SUM(AB10*$Z$4) -> 2410 | AD10: =SUM(AB10) -> 241 | AE10: =SUM(AD10*$Z$4) -> 2410 | AF10: =SUM(AD10) -> 241 | AG10: =SUM(AF10*$Z$4) -> 2410 | AH10: =SUM(AF10) -> 241 | AI10: =SUM(AH10*$Z$4) -> 2410 | AJ10: =SUM(AH10) -> 241 | AK10: =SUM(AJ10*$Z$4) -> 2410 | AL10: =SUM(AJ10) -> 241 | AM10: =SUM(AL10*$Z$4) -> 2410 | AN10: =SUM(AO10/19600) -> 0.86071429 | AO10: =SUM(AA10+AC10+AE10+AG10+AI10+AK10+AM10) -> 16870 | AQ10: =SUM(AR10/92970) -> 0.78225095 | AR10: =Y10+AO10 -> 72725.871 | AS10: =SUM(AR10-AR9-AT10) -> -326.32258 | AT10: 10000 | AU10: 0.634 | AV10: =IF(AT10>0,AU10,AV9) -> 0.634 | AW10: =-SUM('B5'!AI9) -> -193 | AX10: =-SUM(AW10-AS10) -> -133.32258 | AY10: =SUM(AX10+AW10) -> -326.32258 | AZ10: =ELEC!A8 -> 0 | BA10: ='General information '!D9 -> 20 | BB10: =SUM('General information '!E9) -> 0.54 | BC10: =IF(AR9>=AR10,0,1) -> 1 | BD10: 19222 | BE10: =(305/1185)*ELEC!Q9 -> 1268.6456 | BG10: =#REF!-BE10 -> #REF! | BH10: 16 | BI10: 7 | BJ10: =AX10/BI10 -> -19.046083 | BK10: =GEN!AF7 -> 0.4090625
A11: =ELEC!C9 -> 44536 | B11: ='B5'!B10 -> 229 | C11: =B11*$B$4 -> 4927.1935 | D11: =SUM(B11) -> 229 | E11: =D11*$B$4 -> 4927.1935 | F11: =SUM(D11) -> 229 | G11: =F11*$B$4 -> 4927.1935 | H11: =SUM(F11) -> 229 | I11: =H11*$B$4 -> 4927.1935 | J11: =SUM(H11) -> 229 | K11: =J11*$B$4 -> 4927.1935 | L11: =SUM(J11) -> 229 | M11: =L11*$B$4 -> 4927.1935 | N11: =SUM(L11) -> 229 | O11: =N11*$B$4 -> 4927.1935 | P11: =SUM(N11) -> 229 | Q11: =P11*$B$4 -> 4927.1935 | R11: =SUM(P11) -> 229 | S11: =R11*$B$4 -> 4927.1935 | T11: =SUM(R11) -> 229 | U11: =T11*$B$4 -> 4927.1935 | V11: =SUM(T11) -> 229 | W11: =V11*$B$4 -> 4927.1935 | X11: =SUM(Y11/73370) -> 0.73870968 | Y11: =SUM(C11+E11+G11+I11+K11+M11+O11+Q11+S11+U11+W11) -> 54199.129 | Z11: ='B5'!C10 -> 239 | AA11: =SUM(Z11*$Z$4) -> 2390 | AB11: =SUM(Z11) -> 239 | AC11: =SUM(AB11*$Z$4) -> 2390 | AD11: =SUM(AB11) -> 239 | AE11: =SUM(AD11*$Z$4) -> 2390 | AF11: =SUM(AD11) -> 239 | AG11: =SUM(AF11*$Z$4) -> 2390 | AH11: =SUM(AF11) -> 239 | AI11: =SUM(AH11*$Z$4) -> 2390 | AJ11: =SUM(AH11) -> 239 | AK11: =SUM(AJ11*$Z$4) -> 2390 | AL11: =SUM(AJ11) -> 239 | AM11: =SUM(AL11*$Z$4) -> 2390 | AN11: =SUM(AO11/19600) -> 0.85357143 | AO11: =SUM(AA11+AC11+AE11+AG11+AI11+AK11+AM11) -> 16730 | AQ11: =SUM(AR11/92970) -> 0.76292491 | AR11: =Y11+AO11 -> 70929.129 | AS11: =SUM(AR11-AR10-AT11) -> -1796.7419 | AV11: =IF(AT11>0,AU11,AV10) -> 0.634 | AW11: =-SUM('B5'!AI10) -> -110 | AX11: =-SUM(AW11-AS11) -> -1686.7419 | AY11: =SUM(AX11+AW11) -> -1796.7419 | AZ11: =ELEC!A9 -> 0 | BA11: ='General information '!D10 -> 19 | BB11: =SUM('General information '!E10) -> 0.59 | BC11: =IF(AR10>=AR11,0,1) -> 0 | BD11: 19222 | BE11: =(305/1185)*ELEC!Q10 -> 1349.7215 | BG11: =#REF!-BE11 -> #REF! | BH11: 16.5 | BI11: 9.3 | BJ11: =AX11/BI11 -> -181.3701 | BK11: =GEN!AF8 -> 0.34229167
A12: =ELEC!C10 -> 44537 | B12: ='B5'!B11 -> 221 | C12: =B12*$B$4 -> 4755.0645 | D12: =SUM(B12) -> 221 | E12: =D12*$B$4 -> 4755.0645 | F12: =SUM(D12) -> 221 | G12: =F12*$B$4 -> 4755.0645 | H12: =SUM(F12) -> 221 | I12: =H12*$B$4 -> 4755.0645 | J12: =SUM(H12) -> 221 | K12: =J12*$B$4 -> 4755.0645 | L12: =SUM(J12) -> 221 | M12: =L12*$B$4 -> 4755.0645 | N12: =SUM(L12) -> 221 | O12: =N12*$B$4 -> 4755.0645 | P12: =SUM(N12) -> 221 | Q12: =P12*$B$4 -> 4755.0645 | R12: =SUM(P12) -> 221 | S12: =R12*$B$4 -> 4755.0645 | T12: =SUM(R12) -> 221 | U12: =T12*$B$4 -> 4755.0645 | V12: =SUM(T12) -> 221 | W12: =V12*$B$4 -> 4755.0645 | X12: =SUM(Y12/73370) -> 0.71290323 | Y12: =SUM(C12+E12+G12+I12+K12+M12+O12+Q12+S12+U12+W12) -> 52305.71 | Z12: ='B5'!C11 -> 226 | AA12: =SUM(Z12*$Z$4) -> 2260 | AB12: =SUM(Z12) -> 226 | AC12: =SUM(AB12*$Z$4) -> 2260 | AD12: =SUM(AB12) -> 226 | AE12: =SUM(AD12*$Z$4) -> 2260 | AF12: =SUM(AD12) -> 226 | AG12: =SUM(AF12*$Z$4) -> 2260 | AH12: =SUM(AF12) -> 226 | AI12: =SUM(AH12*$Z$4) -> 2260 | AJ12: =SUM(AH12) -> 226 | AK12: =SUM(AJ12*$Z$4) -> 2260 | AL12: =SUM(AJ12) -> 226 | AM12: =SUM(AL12*$Z$4) -> 2260 | AN12: =SUM(AO12/19600) -> 0.80714286 | AO12: =SUM(AA12+AC12+AE12+AG12+AI12+AK12+AM12) -> 15820 | AQ12: =SUM(AR12/92970) -> 0.73277089 | AR12: =Y12+AO12 -> 68125.71 | AS12: =SUM(AR12-AR11-AT12) -> -2803.4194 | AV12: =IF(AT12>0,AU12,AV11) -> 0.634 | AW12: =-SUM('B5'!AI11) -> -119 | AX12: =-SUM(AW12-AS12) -> -2684.4194 | AY12: =SUM(AX12+AW12) -> -2803.4194 | AZ12: =ELEC!A10 -> 0 | BA12: ='General information '!D11 -> 19.5 | BB12: =SUM('General information '!E11) -> 0.44 | BC12: =IF(AR11>=AR12,0,1) -> 0 | BD12: 19222 | BE12: =(305/1185)*ELEC!Q11 -> 1534.7806 | BG12: =#REF!-BE12 -> #REF! | BH12: 15.5 | BI12: 3.7 | BJ12: =AX12/BI12 -> -725.51874 | BK12: =GEN!AF9 -> 0.32775
A13: =ELEC!C11 -> 44538 | B13: ='B5'!B12 -> 214 | C13: =B13*$B$4 -> 4604.4516 | D13: =SUM(B13) -> 214 | E13: =D13*$B$4 -> 4604.4516 | F13: =SUM(D13) -> 214 | G13: =F13*$B$4 -> 4604.4516 | H13: =SUM(F13) -> 214 | I13: =H13*$B$4 -> 4604.4516 | J13: =SUM(H13) -> 214 | K13: =J13*$B$4 -> 4604.4516 | L13: =SUM(J13) -> 214 | M13: =L13*$B$4 -> 4604.4516 | N13: =SUM(L13) -> 214 | O13: =N13*$B$4 -> 4604.4516 | P13: =SUM(N13) -> 214 | Q13: =P13*$B$4 -> 4604.4516 | R13: =SUM(P13) -> 214 | S13: =R13*$B$4 -> 4604.4516 | T13: =SUM(R13) -> 214 | U13: =T13*$B$4 -> 4604.4516 | V13: =SUM(T13) -> 214 | W13: =V13*$B$4 -> 4604.4516 | X13: =SUM(Y13/73370) -> 0.69032258 | Y13: =SUM(C13+E13+G13+I13+K13+M13+O13+Q13+S13+U13+W13) -> 50648.968 | Z13: ='B5'!C12 -> 221 | AA13: =SUM(Z13*$Z$4) -> 2210 | AB13: =SUM(Z13) -> 221 | AC13: =SUM(AB13*$Z$4) -> 2210 | AD13: =SUM(AB13) -> 221 | AE13: =SUM(AD13*$Z$4) -> 2210 | AF13: =SUM(AD13) -> 221 | AG13: =SUM(AF13*$Z$4) -> 2210 | AH13: =SUM(AF13) -> 221 | AI13: =SUM(AH13*$Z$4) -> 2210 | AJ13: =SUM(AH13) -> 221 | AK13: =SUM(AJ13*$Z$4) -> 2210 | AL13: =SUM(AJ13) -> 221 | AM13: =SUM(AL13*$Z$4) -> 2210 | AN13: =SUM(AO13/19600) -> 0.78928571 | AO13: =SUM(AA13+AC13+AE13+AG13+AI13+AK13+AM13) -> 15470 | AQ13: =SUM(AR13/92970) -> 0.71118606 | AR13: =Y13+AO13 -> 66118.968 | AS13: =SUM(AR13-AR12-AT13) -> -2006.7419 | AV13: =IF(AT13>0,AU13,AV12) -> 0.634 | AW13: =-SUM('B5'!AI12) -> 0 | AX13: =-SUM(AW13-AS13) -> -2006.7419 | AY13: =SUM(AX13+AW13) -> -2006.7419 | AZ13: =ELEC!A11 -> 0 | BA13: ='General information '!D12 -> 16.5 | BB13: =SUM('General information '!E12) -> 0.63 | BC13: =IF(AR12>=AR13,0,1) -> 0 | BD13: 19222 | BE13: =(305/1185)*ELEC!Q12 -> 1244.7089 | BG13: =#REF!-BE13 -> #REF! | BI13: 5 | BJ13: =AX13/BI13 -> -401.34839 | BK13: =GEN!AF10 -> 0.33880682
A14: =ELEC!C12 -> 44539 | B14: ='B5'!B13 -> 207 | C14: =B14*$B$4 -> 4453.8387 | D14: =SUM(B14) -> 207 | E14: =D14*$B$4 -> 4453.8387 | F14: =SUM(D14) -> 207 | G14: =F14*$B$4 -> 4453.8387 | H14: =SUM(F14) -> 207 | I14: =H14*$B$4 -> 4453.8387 | J14: =SUM(H14) -> 207 | K14: =J14*$B$4 -> 4453.8387 | L14: =SUM(J14) -> 207 | M14: =L14*$B$4 -> 4453.8387 | N14: =SUM(L14) -> 207 | O14: =N14*$B$4 -> 4453.8387 | P14: =SUM(N14) -> 207 | Q14: =P14*$B$4 -> 4453.8387 | R14: =SUM(P14) -> 207 | S14: =R14*$B$4 -> 4453.8387 | T14: =SUM(R14) -> 207 | U14: =T14*$B$4 -> 4453.8387 | V14: =SUM(T14) -> 207 | W14: =V14*$B$4 -> 4453.8387 | X14: =SUM(Y14/73370) -> 0.66774194 | Y14: =SUM(C14+E14+G14+I14+K14+M14+O14+Q14+S14+U14+W14) -> 48992.226 | Z14: ='B5'!C13 -> 214 | AA14: =SUM(Z14*$Z$4) -> 2140 | AB14: =SUM(Z14) -> 214 | AC14: =SUM(AB14*$Z$4) -> 2140 | AD14: =SUM(AB14) -> 214 | AE14: =SUM(AD14*$Z$4) -> 2140 | AF14: =SUM(AD14) -> 214 | AG14: =SUM(AF14*$Z$4) -> 2140 | AH14: =SUM(AF14) -> 214 | AI14: =SUM(AH14*$Z$4) -> 2140 | AJ14: =SUM(AH14) -> 214 | AK14: =SUM(AJ14*$Z$4) -> 2140 | AL14: =SUM(AJ14) -> 214 | AM14: =SUM(AL14*$Z$4) -> 2140 | AN14: =SUM(AO14/19600) -> 0.76428571 | AO14: =SUM(AA14+AC14+AE14+AG14+AI14+AK14+AM14) -> 14980 | AQ14: =SUM(AR14/92970) -> 0.68809536 | AR14: =Y14+AO14 -> 63972.226 | AS14: =SUM(AR14-AR13-AT14) -> -2146.7419 | AV14: =IF(AT14>0,AU14,AV13) -> 0.634 | AW14: =-SUM('B5'!AI13) -> 0 | AX14: =-SUM(AW14-AS14) -> -2146.7419 | AY14: =SUM(AX14+AW14) -> -2146.7419 | AZ14: =ELEC!A12 -> 0 | BA14: ='General information '!D13 -> 17 | BB14: =SUM('General information '!E13) -> 0.73 | BC14: =IF(AR13>=AR14,0,1) -> 0 | BD14: 19222 | BE14: =(305/1185)*ELEC!Q13 -> 0 | BG14: =#REF!-BE14 -> #REF! | BI14: 3 | BJ14: =AX14/BI14 -> -715.58065 | BK14: =GEN!AF11 -> 0.33583333
A15: =ELEC!C13 -> 44540 | B15: ='B5'!B14 -> 207 | C15: =B15*$B$4 -> 4453.8387 | D15: =SUM(B15) -> 207 | E15: =D15*$B$4 -> 4453.8387 | F15: =SUM(D15) -> 207 | G15: =F15*$B$4 -> 4453.8387 | H15: =SUM(F15) -> 207 | I15: =H15*$B$4 -> 4453.8387 | J15: =SUM(H15) -> 207 | K15: =J15*$B$4 -> 4453.8387 | L15: =SUM(J15) -> 207 | M15: =L15*$B$4 -> 4453.8387 | N15: =SUM(L15) -> 207 | O15: =N15*$B$4 -> 4453.8387 | P15: =SUM(N15) -> 207 | Q15: =P15*$B$4 -> 4453.8387 | R15: =SUM(P15) -> 207 | S15: =R15*$B$4 -> 4453.8387 | T15: =SUM(R15) -> 207 | U15: =T15*$B$4 -> 4453.8387 | V15: =SUM(T15) -> 207 | W15: =V15*$B$4 -> 4453.8387 | X15: =SUM(Y15/73370) -> 0.66774194 | Y15: =SUM(C15+E15+G15+I15+K15+M15+O15+Q15+S15+U15+W15) -> 48992.226 | Z15: ='B5'!C14 -> 214 | AA15: =SUM(Z15*$Z$4) -> 2140 | AB15: =SUM(Z15) -> 214 | AC15: =SUM(AB15*$Z$4) -> 2140 | AD15: =SUM(AB15) -> 214 | AE15: =SUM(AD15*$Z$4) -> 2140 | AF15: =SUM(AD15) -> 214 | AG15: =SUM(AF15*$Z$4) -> 2140 | AH15: =SUM(AF15) -> 214 | AI15: =SUM(AH15*$Z$4) -> 2140 | AJ15: =SUM(AH15) -> 214 | AK15: =SUM(AJ15*$Z$4) -> 2140 | AL15: =SUM(AJ15) -> 214 | AM15: =SUM(AL15*$Z$4) -> 2140 | AN15: =SUM(AO15/19600) -> 0.76428571 | AO15: =SUM(AA15+AC15+AE15+AG15+AI15+AK15+AM15) -> 14980 | AQ15: =SUM(AR15/92970) -> 0.68809536 | AR15: =Y15+AO15 -> 63972.226 | AS15: =SUM(AR15-AR14-AT15) -> 0 | AV15: =IF(AT15>0,AU15,AV14) -> 0.634 | AW15: =-SUM('B5'!AI14) -> 0 | AX15: =-SUM(AW15-AS15) -> 0 | AY15: =SUM(AX15+AW15) -> 0 | AZ15: =ELEC!A13 -> 0 | BA15: ='General information '!D14 -> 0 | BB15: =SUM('General information '!E14) -> 0 | BC15: =IF(AR14>=AR15,0,1) -> 0 | BD15: 19222 | BE15: =(305/1185)*ELEC!Q14 -> 0 | BG15: =#REF!-BE15 -> #REF! | BI15: 4 | BJ15: =AX15/BI15 -> 0 | BK15: =GEN!AF12 -> #DIV/0!
A16: =ELEC!C14 -> 44541 | B16: ='B5'!B15 -> 207 | C16: =B16*$B$4 -> 4453.8387 | D16: =SUM(B16) -> 207 | E16: =D16*$B$4 -> 4453.8387 | F16: =SUM(D16) -> 207 | G16: =F16*$B$4 -> 4453.8387 | H16: =SUM(F16) -> 207 | I16: =H16*$B$4 -> 4453.8387 | J16: =SUM(H16) -> 207 | K16: =J16*$B$4 -> 4453.8387 | L16: =SUM(J16) -> 207 | M16: =L16*$B$4 -> 4453.8387 | N16: =SUM(L16) -> 207 | O16: =N16*$B$4 -> 4453.8387 | P16: =SUM(N16) -> 207 | Q16: =P16*$B$4 -> 4453.8387 | R16: =SUM(P16) -> 207 | S16: =R16*$B$4 -> 4453.8387 | T16: =SUM(R16) -> 207 | U16: =T16*$B$4 -> 4453.8387 | V16: =SUM(T16) -> 207 | W16: =V16*$B$4 -> 4453.8387 | X16: =SUM(Y16/73370) -> 0.66774194 | Y16: =SUM(C16+E16+G16+I16+K16+M16+O16+Q16+S16+U16+W16) -> 48992.226 | Z16: ='B5'!C15 -> 214 | AA16: =SUM(Z16*$Z$4) -> 2140 | AB16: =SUM(Z16) -> 214 | AC16: =SUM(AB16*$Z$4) -> 2140 | AD16: =SUM(AB16) -> 214 | AE16: =SUM(AD16*$Z$4) -> 2140 | AF16: =SUM(AD16) -> 214 | AG16: =SUM(AF16*$Z$4) -> 2140 | AH16: =SUM(AF16) -> 214 | AI16: =SUM(AH16*$Z$4) -> 2140 | AJ16: =SUM(AH16) -> 214 | AK16: =SUM(AJ16*$Z$4) -> 2140 | AL16: =SUM(AJ16) -> 214 | AM16: =SUM(AL16*$Z$4) -> 2140 | AN16: =SUM(AO16/19600) -> 0.76428571 | AO16: =SUM(AA16+AC16+AE16+AG16+AI16+AK16+AM16) -> 14980 | AQ16: =SUM(AR16/92970) -> 0.68809536 | AR16: =Y16+AO16 -> 63972.226 | AS16: =SUM(AR16-AR15-AT16) -> 0 | AV16: =IF(AT16>0,AU16,AV15) -> 0.634 | AW16: =-SUM('B5'!AI15) -> 0 | AX16: =-SUM(AW16-AS16) -> 0 | AY16: =SUM(AX16+AW16) -> 0 | AZ16: =ELEC!A14 -> 0 | BA16: ='General information '!D15 -> 0 | BB16: =SUM('General information '!E15) -> 0 | BC16: =IF(AR15>=AR16,0,1) -> 0 | BD16: 19222 | BE16: =(305/1185)*ELEC!Q15 -> 1730.135 | BG16: =#REF!-BE16 -> #REF! | BI16: 3 | BJ16: =AX16/BI16 -> 0 | BK16: =GEN!AF13 -> #DIV/0!
A17: =ELEC!C15 -> 44542 | B17: ='B5'!B16 -> 202 | C17: =B17*$B$4 -> 4346.2581 | D17: =SUM(B17) -> 202 | E17: =D17*$B$4 -> 4346.2581 | F17: =SUM(D17) -> 202 | G17: =F17*$B$4 -> 4346.2581 | H17: =SUM(F17) -> 202 | I17: =H17*$B$4 -> 4346.2581 | J17: =SUM(H17) -> 202 | K17: =J17*$B$4 -> 4346.2581 | L17: =SUM(J17) -> 202 | M17: =L17*$B$4 -> 4346.2581 | N17: =SUM(L17) -> 202 | O17: =N17*$B$4 -> 4346.2581 | P17: =SUM(N17) -> 202 | Q17: =P17*$B$4 -> 4346.2581 | R17: =SUM(P17) -> 202 | S17: =R17*$B$4 -> 4346.2581 | T17: =SUM(R17) -> 202 | U17: =T17*$B$4 -> 4346.2581 | V17: =SUM(T17) -> 202 | W17: =V17*$B$4 -> 4346.2581 | X17: =SUM(Y17/73370) -> 0.6516129 | Y17: =SUM(C17+E17+G17+I17+K17+M17+O17+Q17+S17+U17+W17) -> 47808.839 | Z17: ='B5'!C16 -> 208 | AA17: =SUM(Z17*$Z$4) -> 2080 | AB17: =SUM(Z17) -> 208 | AC17: =SUM(AB17*$Z$4) -> 2080 | AD17: =SUM(AB17) -> 208 | AE17: =SUM(AD17*$Z$4) -> 2080 | AF17: =SUM(AD17) -> 208 | AG17: =SUM(AF17*$Z$4) -> 2080 | AH17: =SUM(AF17) -> 208 | AI17: =SUM(AH17*$Z$4) -> 2080 | AJ17: =SUM(AH17) -> 208 | AK17: =SUM(AJ17*$Z$4) -> 2080 | AL17: =SUM(AJ17) -> 208 | AM17: =SUM(AL17*$Z$4) -> 2080 | AN17: =SUM(AO17/19600) -> 0.74285714 | AO17: =SUM(AA17+AC17+AE17+AG17+AI17+AK17+AM17) -> 14560 | AQ17: =SUM(AR17/92970) -> 0.67084908 | AR17: =Y17+AO17 -> 62368.839 | AS17: =SUM(AR17-AR16-AT17) -> -1603.3871 | AV17: =IF(AT17>0,AU17,AV16) -> 0.634 | AW17: =-SUM('B5'!AI16) -> -118 | AX17: =-SUM(AW17-AS17) -> -1485.3871 | AY17: =SUM(AX17+AW17) -> -1603.3871 | AZ17: =ELEC!A15 -> 0 | BA17: ='General information '!D16 -> 18.5 | BB17: =SUM('General information '!E16) -> 0.54 | BC17: =IF(AR16>=AR17,0,1) -> 0 | BD17: 19222 | BE17: =(305/1185)*ELEC!Q16 -> 1319.0928 | BG17: =#REF!-BE17 -> #REF! | BI17: 4 | BJ17: =AX17/BI17 -> -371.34677 | BK17: =GEN!AF14 -> 0.38193182
A18: =ELEC!C16 -> 44543 | B18: ='B5'!B17 -> 195 | C18: =B18*$B$4 -> 4195.6452 | D18: =SUM(B18) -> 195 | E18: =D18*$B$4 -> 4195.6452 | F18: =SUM(D18) -> 195 | G18: =F18*$B$4 -> 4195.6452 | H18: =SUM(F18) -> 195 | I18: =H18*$B$4 -> 4195.6452 | J18: =SUM(H18) -> 195 | K18: =J18*$B$4 -> 4195.6452 | L18: =SUM(J18) -> 195 | M18: =L18*$B$4 -> 4195.6452 | N18: =SUM(L18) -> 195 | O18: =N18*$B$4 -> 4195.6452 | P18: =SUM(N18) -> 195 | Q18: =P18*$B$4 -> 4195.6452 | R18: =SUM(P18) -> 195 | S18: =R18*$B$4 -> 4195.6452 | T18: =SUM(R18) -> 195 | U18: =T18*$B$4 -> 4195.6452 | V18: =SUM(T18) -> 195 | W18: =V18*$B$4 -> 4195.6452 | X18: =SUM(Y18/73370) -> 0.62903226 | Y18: =SUM(C18+E18+G18+I18+K18+M18+O18+Q18+S18+U18+W18) -> 46152.097 | Z18: ='B5'!C17 -> 202 | AA18: =SUM(Z18*$Z$4) -> 2020 | AB18: =SUM(Z18) -> 202 | AC18: =SUM(AB18*$Z$4) -> 2020 | AD18: =SUM(AB18) -> 202 | AE18: =SUM(AD18*$Z$4) -> 2020 | AF18: =SUM(AD18) -> 202 | AG18: =SUM(AF18*$Z$4) -> 2020 | AH18: =SUM(AF18) -> 202 | AI18: =SUM(AH18*$Z$4) -> 2020 | AJ18: =SUM(AH18) -> 202 | AK18: =SUM(AJ18*$Z$4) -> 2020 | AL18: =SUM(AJ18) -> 202 | AM18: =SUM(AL18*$Z$4) -> 2020 | AN18: =SUM(AO18/19600) -> 0.72142857 | AO18: =SUM(AA18+AC18+AE18+AG18+AI18+AK18+AM18) -> 14140 | AQ18: =SUM(AR18/92970) -> 0.64851131 | AR18: =Y18+AO18 -> 60292.097 | AS18: =SUM(AR18-AR17-AT18) -> -2076.7419 | AV18: =IF(AT18>0,AU18,AV17) -> 0.634 | AW18: =-SUM('B5'!AI17) -> -169 | AX18: =-SUM(AW18-AS18) -> -1907.7419 | AY18: =SUM(AX18+AW18) -> -2076.7419 | AZ18: =ELEC!A16 -> 0 | BA18: ='General information '!D17 -> 20 | BB18: =SUM('General information '!E17) -> 0.54 | BC18: =IF(AR17>=AR18,0,1) -> 0 | BD18: 19222 | BE18: =(305/1185)*ELEC!Q17 -> 1324.4979 | BG18: =#REF!-BE18 -> #REF! | BI18: 5 | BJ18: =AX18/BI18 -> -381.54839 | BK18: =GEN!AF15 -> 0.3203125
A19: =ELEC!C17 -> 44544 | B19: ='B5'!B18 -> 226 | C19: =B19*$B$4 -> 4862.6452 | D19: =SUM(B19) -> 226 | E19: =D19*$B$4 -> 4862.6452 | F19: =SUM(D19) -> 226 | G19: =F19*$B$4 -> 4862.6452 | H19: =SUM(F19) -> 226 | I19: =H19*$B$4 -> 4862.6452 | J19: =SUM(H19) -> 226 | K19: =J19*$B$4 -> 4862.6452 | L19: =SUM(J19) -> 226 | M19: =L19*$B$4 -> 4862.6452 | N19: =SUM(L19) -> 226 | O19: =N19*$B$4 -> 4862.6452 | P19: =SUM(N19) -> 226 | Q19: =P19*$B$4 -> 4862.6452 | R19: =SUM(P19) -> 226 | S19: =R19*$B$4 -> 4862.6452 | T19: =SUM(R19) -> 226 | U19: =T19*$B$4 -> 4862.6452 | V19: =SUM(T19) -> 226 | W19: =V19*$B$4 -> 4862.6452 | X19: =SUM(Y19/73370) -> 0.72903226 | Y19: =SUM(C19+E19+G19+I19+K19+M19+O19+Q19+S19+U19+W19) -> 53489.097 | Z19: ='B5'!C18 -> 233 | AA19: =SUM(Z19*$Z$4) -> 2330 | AB19: =SUM(Z19) -> 233 | AC19: =SUM(AB19*$Z$4) -> 2330 | AD19: =SUM(AB19) -> 233 | AE19: =SUM(AD19*$Z$4) -> 2330 | AF19: =SUM(AD19) -> 233 | AG19: =SUM(AF19*$Z$4) -> 2330 | AH19: =SUM(AF19) -> 233 | AI19: =SUM(AH19*$Z$4) -> 2330 | AJ19: =SUM(AH19) -> 233 | AK19: =SUM(AJ19*$Z$4) -> 2330 | AL19: =SUM(AJ19) -> 233 | AM19: =SUM(AL19*$Z$4) -> 2330 | AN19: =SUM(AO19/19600) -> 0.83214286 | AO19: =SUM(AA19+AC19+AE19+AG19+AI19+AK19+AM19) -> 16310 | AQ19: =SUM(AR19/92970) -> 0.75077011 | AR19: =Y19+AO19 -> 69799.097 | AS19: =SUM(AR19-AR18-AT19) -> -493 | AT19: 10000 | AU19: 0.607 | AV19: =IF(AT19>0,AU19,AV18) -> 0.607 | AW19: =-SUM('B5'!AI18) -> -117 | AX19: =-SUM(AW19-AS19) -> -376 | AY19: =SUM(AX19+AW19) -> -493 | AZ19: =ELEC!A17 -> 0 | BA19: ='General information '!D18 -> 19 | BB19: =SUM('General information '!E18) -> 0.63 | BC19: =IF(AR18>=AR19,0,1) -> 1 | BD19: 19222 | BE19: =(305/1185)*ELEC!Q18 -> 1331.7046 | BG19: =#REF!-BE19 -> #REF! | BI19: 6 | BJ19: =AX19/BI19 -> -62.666667 | BK19: =GEN!AF16 -> 0.35736111
A20: =ELEC!C18 -> 44545 | B20: ='B5'!B19 -> 219 | C20: =B20*$B$4 -> 4712.0323 | D20: =SUM(B20) -> 219 | E20: =D20*$B$4 -> 4712.0323 | F20: =SUM(D20) -> 219 | G20: =F20*$B$4 -> 4712.0323 | H20: =SUM(F20) -> 219 | I20: =H20*$B$4 -> 4712.0323 | J20: =SUM(H20) -> 219 | K20: =J20*$B$4 -> 4712.0323 | L20: =SUM(J20) -> 219 | M20: =L20*$B$4 -> 4712.0323 | N20: =SUM(L20) -> 219 | O20: =N20*$B$4 -> 4712.0323 | P20: =SUM(N20) -> 219 | Q20: =P20*$B$4 -> 4712.0323 | R20: =SUM(P20) -> 219 | S20: =R20*$B$4 -> 4712.0323 | T20: =SUM(R20) -> 219 | U20: =T20*$B$4 -> 4712.0323 | V20: =SUM(T20) -> 219 | W20: =V20*$B$4 -> 4712.0323 | X20: =SUM(Y20/73370) -> 0.70645161 | Y20: =SUM(C20+E20+G20+I20+K20+M20+O20+Q20+S20+U20+W20) -> 51832.355 | Z20: ='B5'!C19 -> 227 | AA20: =SUM(Z20*$Z$4) -> 2270 | AB20: =SUM(Z20) -> 227 | AC20: =SUM(AB20*$Z$4) -> 2270 | AD20: =SUM(AB20) -> 227 | AE20: =SUM(AD20*$Z$4) -> 2270 | AF20: =SUM(AD20) -> 227 | AG20: =SUM(AF20*$Z$4) -> 2270 | AH20: =SUM(AF20) -> 227 | AI20: =SUM(AH20*$Z$4) -> 2270 | AJ20: =SUM(AH20) -> 227 | AK20: =SUM(AJ20*$Z$4) -> 2270 | AL20: =SUM(AJ20) -> 227 | AM20: =SUM(AL20*$Z$4) -> 2270 | AN20: =SUM(AO20/19600) -> 0.81071429 | AO20: =SUM(AA20+AC20+AE20+AG20+AI20+AK20+AM20) -> 15890 | AQ20: =SUM(AR20/92970) -> 0.72843234 | AR20: =Y20+AO20 -> 67722.355 | AS20: =SUM(AR20-AR19-AT20) -> -2076.7419 | AV20: =IF(AT20>0,AU20,AV19) -> 0.607 | AW20: =-SUM('B5'!AI19) -> -112 | AX20: =-SUM(AW20-AS20) -> -1964.7419 | AY20: =SUM(AX20+AW20) -> -2076.7419 | AZ20: =ELEC!A18 -> 0 | BA20: ='General information '!D19 -> 18 | BB20: =SUM('General information '!E19) -> 0.7 | BC20: =IF(AR19>=AR20,0,1) -> 0 | BD20: 19222 | BE20: =(305/1185)*ELEC!Q19 -> 2553.7637 | BG20: =#REF!-BE20 -> #REF! | BI20: 7 | BJ20: =AX20/BI20 -> -280.67742 | BK20: =GEN!AF17 -> 0.323375
A21: =ELEC!C19 -> 44546 | B21: ='B5'!B20 -> 211 | C21: =B21*$B$4 -> 4539.9032 | D21: =SUM(B21) -> 211 | E21: =D21*$B$4 -> 4539.9032 | F21: =SUM(D21) -> 211 | G21: =F21*$B$4 -> 4539.9032 | H21: =SUM(F21) -> 211 | I21: =H21*$B$4 -> 4539.9032 | J21: =SUM(H21) -> 211 | K21: =J21*$B$4 -> 4539.9032 | L21: =SUM(J21) -> 211 | M21: =L21*$B$4 -> 4539.9032 | N21: =SUM(L21) -> 211 | O21: =N21*$B$4 -> 4539.9032 | P21: =SUM(N21) -> 211 | Q21: =P21*$B$4 -> 4539.9032 | R21: =SUM(P21) -> 211 | S21: =R21*$B$4 -> 4539.9032 | T21: =SUM(R21) -> 211 | U21: =T21*$B$4 -> 4539.9032 | V21: =SUM(T21) -> 211 | W21: =V21*$B$4 -> 4539.9032 | X21: =SUM(Y21/73370) -> 0.68064516 | Y21: =SUM(C21+E21+G21+I21+K21+M21+O21+Q21+S21+U21+W21) -> 49938.935 | Z21: ='B5'!C20 -> 218 | AA21: =SUM(Z21*$Z$4) -> 2180 | AB21: =SUM(Z21) -> 218 | AC21: =SUM(AB21*$Z$4) -> 2180 | AD21: =SUM(AB21) -> 218 | AE21: =SUM(AD21*$Z$4) -> 2180 | AF21: =SUM(AD21) -> 218 | AG21: =SUM(AF21*$Z$4) -> 2180 | AH21: =SUM(AF21) -> 218 | AI21: =SUM(AH21*$Z$4) -> 2180 | AJ21: =SUM(AH21) -> 218 | AK21: =SUM(AJ21*$Z$4) -> 2180 | AL21: =SUM(AJ21) -> 218 | AM21: =SUM(AL21*$Z$4) -> 2180 | AN21: =SUM(AO21/19600) -> 0.77857143 | AO21: =SUM(AA21+AC21+AE21+AG21+AI21+AK21+AM21) -> 15260 | AQ21: =SUM(AR21/92970) -> 0.70129005 | AR21: =Y21+AO21 -> 65198.935 | AS21: =SUM(AR21-AR20-AT21) -> -2523.4194 | AV21: =IF(AT21>0,AU21,AV20) -> 0.607 | AW21: =-SUM('B5'!AI20) -> 0 | AX21: =-SUM(AW21-AS21) -> -2523.4194 | AY21: =SUM(AX21+AW21) -> -2523.4194 | AZ21: =ELEC!A19 -> 0 | BA21: ='General information '!D20 -> 15.5 | BB21: =SUM('General information '!E20) -> 0.72 | BC21: =IF(AR20>=AR21,0,1) -> 0 | BD21: 19222 | BE21: =(305/1185)*ELEC!Q20 -> 0 | BG21: =#REF!-BE21 -> #REF! | BI21: 8 | BJ21: =AX21/BI21 -> -315.42742 | BK21: =GEN!AF18 -> 0.3100625
A22: =ELEC!C20 -> 44547 | B22: ='B5'!B21 -> 211 | C22: =B22*$B$4 -> 4539.9032 | D22: =SUM(B22) -> 211 | E22: =D22*$B$4 -> 4539.9032 | F22: =SUM(D22) -> 211 | G22: =F22*$B$4 -> 4539.9032 | H22: =SUM(F22) -> 211 | I22: =H22*$B$4 -> 4539.9032 | J22: =SUM(H22) -> 211 | K22: =J22*$B$4 -> 4539.9032 | L22: =SUM(J22) -> 211 | M22: =L22*$B$4 -> 4539.9032 | N22: =SUM(L22) -> 211 | O22: =N22*$B$4 -> 4539.9032 | P22: =SUM(N22) -> 211 | Q22: =P22*$B$4 -> 4539.9032 | R22: =SUM(P22) -> 211 | S22: =R22*$B$4 -> 4539.9032 | T22: =SUM(R22) -> 211 | U22: =T22*$B$4 -> 4539.9032 | V22: =SUM(T22) -> 211 | W22: =V22*$B$4 -> 4539.9032 | X22: =SUM(Y22/73370) -> 0.68064516 | Y22: =SUM(C22+E22+G22+I22+K22+M22+O22+Q22+S22+U22+W22) -> 49938.935 | Z22: ='B5'!C21 -> 218 | AA22: =SUM(Z22*$Z$4) -> 2180 | AB22: =SUM(Z22) -> 218 | AC22: =SUM(AB22*$Z$4) -> 2180 | AD22: =SUM(AB22) -> 218 | AE22: =SUM(AD22*$Z$4) -> 2180 | AF22: =SUM(AD22) -> 218 | AG22: =SUM(AF22*$Z$4) -> 2180 | AH22: =SUM(AF22) -> 218 | AI22: =SUM(AH22*$Z$4) -> 2180 | AJ22: =SUM(AH22) -> 218 | AK22: =SUM(AJ22*$Z$4) -> 2180 | AL22: =SUM(AJ22) -> 218 | AM22: =SUM(AL22*$Z$4) -> 2180 | AN22: =SUM(AO22/19600) -> 0.77857143 | AO22: =SUM(AA22+AC22+AE22+AG22+AI22+AK22+AM22) -> 15260 | AQ22: =SUM(AR22/92970) -> 0.70129005 | AR22: =Y22+AO22 -> 65198.935 | AS22: =SUM(AR22-AR21-AT22) -> 0 | AV22: =IF(AT22>0,AU22,AV21) -> 0.607 | AW22: =-SUM('B5'!AI21) -> 0 | AX22: =-SUM(AW22-AS22) -> 0 | AY22: =SUM(AX22+AW22) -> 0 | AZ22: =ELEC!A20 -> 0 | BA22: ='General information '!D21 -> 0 | BB22: =SUM('General information '!E21) -> 0 | BC22: =IF(AR21>=AR22,0,1) -> 0 | BD22: 19222 | BE22: =(305/1185)*ELEC!Q21 -> 0 | BG22: =#REF!-BE22 -> #REF! | BI22: 9 | BJ22: =AX22/BI22 -> 0 | BK22: =GEN!AF19 -> #DIV/0!
A23: =ELEC!C21 -> 44548 | B23: ='B5'!B22 -> 211 | C23: =B23*$B$4 -> 4539.9032 | D23: =SUM(B23) -> 211 | E23: =D23*$B$4 -> 4539.9032 | F23: =SUM(D23) -> 211 | G23: =F23*$B$4 -> 4539.9032 | H23: =SUM(F23) -> 211 | I23: =H23*$B$4 -> 4539.9032 | J23: =SUM(H23) -> 211 | K23: =J23*$B$4 -> 4539.9032 | L23: =SUM(J23) -> 211 | M23: =L23*$B$4 -> 4539.9032 | N23: =SUM(L23) -> 211 | O23: =N23*$B$4 -> 4539.9032 | P23: =SUM(N23) -> 211 | Q23: =P23*$B$4 -> 4539.9032 | R23: =SUM(P23) -> 211 | S23: =R23*$B$4 -> 4539.9032 | T23: =SUM(R23) -> 211 | U23: =T23*$B$4 -> 4539.9032 | V23: =SUM(T23) -> 211 | W23: =V23*$B$4 -> 4539.9032 | X23: =SUM(Y23/73370) -> 0.68064516 | Y23: =SUM(C23+E23+G23+I23+K23+M23+O23+Q23+S23+U23+W23) -> 49938.935 | Z23: ='B5'!C22 -> 218 | AA23: =SUM(Z23*$Z$4) -> 2180 | AB23: =SUM(Z23) -> 218 | AC23: =SUM(AB23*$Z$4) -> 2180 | AD23: =SUM(AB23) -> 218 | AE23: =SUM(AD23*$Z$4) -> 2180 | AF23: =SUM(AD23) -> 218 | AG23: =SUM(AF23*$Z$4) -> 2180 | AH23: =SUM(AF23) -> 218 | AI23: =SUM(AH23*$Z$4) -> 2180 | AJ23: =SUM(AH23) -> 218 | AK23: =SUM(AJ23*$Z$4) -> 2180 | AL23: =SUM(AJ23) -> 218 | AM23: =SUM(AL23*$Z$4) -> 2180 | AN23: =SUM(AO23/19600) -> 0.77857143 | AO23: =SUM(AA23+AC23+AE23+AG23+AI23+AK23+AM23) -> 15260 | AQ23: =SUM(AR23/92970) -> 0.70129005 | AR23: =Y23+AO23 -> 65198.935 | AS23: =SUM(AR23-AR22-AT23) -> 0 | AV23: =IF(AT23>0,AU23,AV22) -> 0.607 | AW23: =-SUM('B5'!AI22) -> 0 | AX23: =-SUM(AW23-AS23) -> 0 | AY23: =SUM(AX23+AW23) -> 0 | AZ23: =ELEC!A21 -> 0 | BA23: ='General information '!D22 -> 0 | BB23: =SUM('General information '!E22) -> 0 | BC23: =IF(AR22>=AR23,0,1) -> 0 | BD23: 19222 | BE23: =(305/1185)*ELEC!Q22 -> 1379.0633 | BG23: =#REF!-BE23 -> #REF! | BI23: 10 | BJ23: =AX23/BI23 -> 0 | BK23: =GEN!AF20 -> #DIV/0!
A24: =ELEC!C22 -> 44549 | B24: ='B5'!B23 -> 200 | C24: =B24*$B$4 -> 4303.2258 | D24: =SUM(B24) -> 200 | E24: =D24*$B$4 -> 4303.2258 | F24: =SUM(D24) -> 200 | G24: =F24*$B$4 -> 4303.2258 | H24: =SUM(F24) -> 200 | I24: =H24*$B$4 -> 4303.2258 | J24: =SUM(H24) -> 200 | K24: =J24*$B$4 -> 4303.2258 | L24: =SUM(J24) -> 200 | M24: =L24*$B$4 -> 4303.2258 | N24: =SUM(L24) -> 200 | O24: =N24*$B$4 -> 4303.2258 | P24: =SUM(N24) -> 200 | Q24: =P24*$B$4 -> 4303.2258 | R24: =SUM(P24) -> 200 | S24: =R24*$B$4 -> 4303.2258 | T24: =SUM(R24) -> 200 | U24: =T24*$B$4 -> 4303.2258 | V24: =SUM(T24) -> 200 | W24: =V24*$B$4 -> 4303.2258 | X24: =SUM(Y24/73370) -> 0.64516129 | Y24: =SUM(C24+E24+G24+I24+K24+M24+O24+Q24+S24+U24+W24) -> 47335.484 | Z24: ='B5'!C23 -> 208 | AA24: =SUM(Z24*$Z$4) -> 2080 | AB24: =SUM(Z24) -> 208 | AC24: =SUM(AB24*$Z$4) -> 2080 | AD24: =SUM(AB24) -> 208 | AE24: =SUM(AD24*$Z$4) -> 2080 | AF24: =SUM(AD24) -> 208 | AG24: =SUM(AF24*$Z$4) -> 2080 | AH24: =SUM(AF24) -> 208 | AI24: =SUM(AH24*$Z$4) -> 2080 | AJ24: =SUM(AH24) -> 208 | AK24: =SUM(AJ24*$Z$4) -> 2080 | AL24: =SUM(AJ24) -> 208 | AM24: =SUM(AL24*$Z$4) -> 2080 | AN24: =SUM(AO24/19600) -> 0.74285714 | AO24: =SUM(AA24+AC24+AE24+AG24+AI24+AK24+AM24) -> 14560 | AQ24: =SUM(AR24/92970) -> 0.6657576 | AR24: =Y24+AO24 -> 61895.484 | AS24: =SUM(AR24-AR23-AT24) -> -3303.4516 | AV24: =IF(AT24>0,AU24,AV23) -> 0.607 | AW24: =-SUM('B5'!AI23) -> -285 | AX24: =-SUM(AW24-AS24) -> -3018.4516 | AY24: =SUM(AX24+AW24) -> -3303.4516 | AZ24: =ELEC!A22 -> 0 | BA24: ='General information '!D23 -> 16.5 | BB24: =SUM('General information '!E23) -> 0.5 | BC24: =IF(AR23>=AR24,0,1) -> 0 | BD24: 19222 | BE24: =(305/1185)*ELEC!Q23 -> 1467.6034 | BG24: =#REF!-BE24 -> #REF! | BI24: 11 | BJ24: =AX24/BI24 -> -274.40469 | BK24: =GEN!AF21 -> 0.2790625
A25: =ELEC!C23 -> 44550 | B25: ='B5'!B24 -> 194 | C25: =B25*$B$4 -> 4174.129 | D25: =SUM(B25) -> 194 | E25: =D25*$B$4 -> 4174.129 | F25: =SUM(D25) -> 194 | G25: =F25*$B$4 -> 4174.129 | H25: =SUM(F25) -> 194 | I25: =H25*$B$4 -> 4174.129 | J25: =SUM(H25) -> 194 | K25: =J25*$B$4 -> 4174.129 | L25: =SUM(J25) -> 194 | M25: =L25*$B$4 -> 4174.129 | N25: =SUM(L25) -> 194 | O25: =N25*$B$4 -> 4174.129 | P25: =SUM(N25) -> 194 | Q25: =P25*$B$4 -> 4174.129 | R25: =SUM(P25) -> 194 | S25: =R25*$B$4 -> 4174.129 | T25: =SUM(R25) -> 194 | U25: =T25*$B$4 -> 4174.129 | V25: =SUM(T25) -> 194 | W25: =V25*$B$4 -> 4174.129 | X25: =SUM(Y25/73370) -> 0.62580645 | Y25: =SUM(C25+E25+G25+I25+K25+M25+O25+Q25+S25+U25+W25) -> 45915.419 | Z25: ='B5'!C24 -> 200 | AA25: =SUM(Z25*$Z$4) -> 2000 | AB25: =SUM(Z25) -> 200 | AC25: =SUM(AB25*$Z$4) -> 2000 | AD25: =SUM(AB25) -> 200 | AE25: =SUM(AD25*$Z$4) -> 2000 | AF25: =SUM(AD25) -> 200 | AG25: =SUM(AF25*$Z$4) -> 2000 | AH25: =SUM(AF25) -> 200 | AI25: =SUM(AH25*$Z$4) -> 2000 | AJ25: =SUM(AH25) -> 200 | AK25: =SUM(AJ25*$Z$4) -> 2000 | AL25: =SUM(AJ25) -> 200 | AM25: =SUM(AL25*$Z$4) -> 2000 | AN25: =SUM(AO25/19600) -> 0.71428571 | AO25: =SUM(AA25+AC25+AE25+AG25+AI25+AK25+AM25) -> 14000 | AQ25: =SUM(AR25/92970) -> 0.64445971 | AR25: =Y25+AO25 -> 59915.419 | AS25: =SUM(AR25-AR24-AT25) -> -1980.0645 | AV25: =IF(AT25>0,AU25,AV24) -> 0.607 | AW25: =-SUM('B5'!AI24) -> -199 | AX25: =-SUM(AW25-AS25) -> -1781.0645 | AY25: =SUM(AX25+AW25) -> -1980.0645 | AZ25: =ELEC!A23 -> 0 | BA25: ='General information '!D24 -> 13 | BB25: =SUM('General information '!E24) -> 0.61 | BC25: =IF(AR24>=AR25,0,1) -> 0 | BD25: 19222 | BE25: =(305/1185)*ELEC!Q24 -> 1647.5148 | BG25: =#REF!-BE25 -> #REF! | BI25: 12 | BJ25: =AX25/BI25 -> -148.42204 | BK25: =GEN!AF22 -> 0.32397727
A26: =ELEC!C24 -> 44551 | B26: ='B5'!B25 -> 224 | C26: =B26*$B$4 -> 4819.6129 | D26: =SUM(B26) -> 224 | E26: =D26*$B$4 -> 4819.6129 | F26: =SUM(D26) -> 224 | G26: =F26*$B$4 -> 4819.6129 | H26: =SUM(F26) -> 224 | I26: =H26*$B$4 -> 4819.6129 | J26: =SUM(H26) -> 224 | K26: =J26*$B$4 -> 4819.6129 | L26: =SUM(J26) -> 224 | M26: =L26*$B$4 -> 4819.6129 | N26: =SUM(L26) -> 224 | O26: =N26*$B$4 -> 4819.6129 | P26: =SUM(N26) -> 224 | Q26: =P26*$B$4 -> 4819.6129 | R26: =SUM(P26) -> 224 | S26: =R26*$B$4 -> 4819.6129 | T26: =SUM(R26) -> 224 | U26: =T26*$B$4 -> 4819.6129 | V26: =SUM(T26) -> 224 | W26: =V26*$B$4 -> 4819.6129 | X26: =SUM(Y26/73370) -> 0.72258065 | Y26: =SUM(C26+E26+G26+I26+K26+M26+O26+Q26+S26+U26+W26) -> 53015.742 | Z26: ='B5'!C25 -> 230 | AA26: =SUM(Z26*$Z$4) -> 2300 | AB26: =SUM(Z26) -> 230 | AC26: =SUM(AB26*$Z$4) -> 2300 | AD26: =SUM(AB26) -> 230 | AE26: =SUM(AD26*$Z$4) -> 2300 | AF26: =SUM(AD26) -> 230 | AG26: =SUM(AF26*$Z$4) -> 2300 | AH26: =SUM(AF26) -> 230 | AI26: =SUM(AH26*$Z$4) -> 2300 | AJ26: =SUM(AH26) -> 230 | AK26: =SUM(AJ26*$Z$4) -> 2300 | AL26: =SUM(AJ26) -> 230 | AM26: =SUM(AL26*$Z$4) -> 2300 | AN26: =SUM(AO26/19600) -> 0.82142857 | AO26: =SUM(AA26+AC26+AE26+AG26+AI26+AK26+AM26) -> 16100 | AQ26: =SUM(AR26/92970) -> 0.74341983 | AR26: =Y26+AO26 -> 69115.742 | AS26: =SUM(AR26-AR25-AT26) -> -799.67742 | AT26: 10000 | AU26: 0.604 | AV26: =IF(AT26>0,AU26,AV25) -> 0.604 | AW26: =-SUM('B5'!AI25) -> -120 | AX26: =-SUM(AW26-AS26) -> -679.67742 | AY26: =SUM(AX26+AW26) -> -799.67742 | AZ26: =ELEC!A24 -> 0 | BA26: ='General information '!D25 -> 16 | BB26: =SUM('General information '!E25) -> 0.61 | BC26: =IF(AR25>=AR26,0,1) -> 1 | BD26: 19222 | BE26: =(305/1185)*ELEC!Q25 -> 1463.4852 | BG26: =#REF!-BE26 -> #REF! | BI26: 13 | BJ26: =AX26/BI26 -> -52.282878 | BK26: =GEN!AF23 -> 0.33338542
A27: =ELEC!C25 -> 44552 | B27: ='B5'!B26 -> 235 | C27: =B27*$B$4 -> 5056.2903 | D27: =SUM(B27) -> 235 | E27: =D27*$B$4 -> 5056.2903 | F27: =SUM(D27) -> 235 | G27: =F27*$B$4 -> 5056.2903 | H27: =SUM(F27) -> 235 | I27: =H27*$B$4 -> 5056.2903 | J27: =SUM(H27) -> 235 | K27: =J27*$B$4 -> 5056.2903 | L27: =SUM(J27) -> 235 | M27: =L27*$B$4 -> 5056.2903 | N27: =SUM(L27) -> 235 | O27: =N27*$B$4 -> 5056.2903 | P27: =SUM(N27) -> 235 | Q27: =P27*$B$4 -> 5056.2903 | R27: =SUM(P27) -> 235 | S27: =R27*$B$4 -> 5056.2903 | T27: =SUM(R27) -> 235 | U27: =T27*$B$4 -> 5056.2903 | V27: =SUM(T27) -> 235 | W27: =V27*$B$4 -> 5056.2903 | X27: =SUM(Y27/73370) -> 0.75806452 | Y27: =SUM(C27+E27+G27+I27+K27+M27+O27+Q27+S27+U27+W27) -> 55619.194 | Z27: ='B5'!C26 -> 242 | AA27: =SUM(Z27*$Z$4) -> 2420 | AB27: =SUM(Z27) -> 242 | AC27: =SUM(AB27*$Z$4) -> 2420 | AD27: =SUM(AB27) -> 242 | AE27: =SUM(AD27*$Z$4) -> 2420 | AF27: =SUM(AD27) -> 242 | AG27: =SUM(AF27*$Z$4) -> 2420 | AH27: =SUM(AF27) -> 242 | AI27: =SUM(AH27*$Z$4) -> 2420 | AJ27: =SUM(AH27) -> 242 | AK27: =SUM(AJ27*$Z$4) -> 2420 | AL27: =SUM(AJ27) -> 242 | AM27: =SUM(AL27*$Z$4) -> 2420 | AN27: =SUM(AO27/19600) -> 0.86428571 | AO27: =SUM(AA27+AC27+AE27+AG27+AI27+AK27+AM27) -> 16940 | AQ27: =SUM(AR27/92970) -> 0.78045814 | AR27: =Y27+AO27 -> 72559.194 | AS27: =SUM(AR27-AR26-AT27) -> -1556.5484 | AT27: 5000 | AU27: 0.604 | AV27: =IF(AT27>0,AU27,AV26) -> 0.604 | AW27: =-SUM('B5'!AI26) -> -298 | AX27: =-SUM(AW27-AS27) -> -1258.5484 | AY27: =SUM(AX27+AW27) -> -1556.5484 | AZ27: =ELEC!A25 -> 0 | BA27: ='General information '!D26 -> 14.5 | BB27: =SUM('General information '!E26) -> 0.69 | BC27: =IF(AR26>=AR27,0,1) -> 1 | BD27: 19222 | BE27: =(305/1185)*ELEC!Q26 -> 1129.4008 | BG27: =#REF!-BE27 -> #REF! | BI27: 14 | BJ27: =AX27/BI27 -> -89.896313 | BK27: =GEN!AF24 -> 0.29614583
A28: =ELEC!C26 -> 44553 | B28: ='B5'!B27 -> 229 | C28: =B28*$B$4 -> 4927.1935 | D28: =SUM(B28) -> 229 | E28: =D28*$B$4 -> 4927.1935 | F28: =SUM(D28) -> 229 | G28: =F28*$B$4 -> 4927.1935 | H28: =SUM(F28) -> 229 | I28: =H28*$B$4 -> 4927.1935 | J28: =SUM(H28) -> 229 | K28: =J28*$B$4 -> 4927.1935 | L28: =SUM(J28) -> 229 | M28: =L28*$B$4 -> 4927.1935 | N28: =SUM(L28) -> 229 | O28: =N28*$B$4 -> 4927.1935 | P28: =SUM(N28) -> 229 | Q28: =P28*$B$4 -> 4927.1935 | R28: =SUM(P28) -> 229 | S28: =R28*$B$4 -> 4927.1935 | T28: =SUM(R28) -> 229 | U28: =T28*$B$4 -> 4927.1935 | V28: =SUM(T28) -> 229 | W28: =V28*$B$4 -> 4927.1935 | X28: =SUM(Y28/73370) -> 0.73870968 | Y28: =SUM(C28+E28+G28+I28+K28+M28+O28+Q28+S28+U28+W28) -> 54199.129 | Z28: ='B5'!C27 -> 236 | AA28: =SUM(Z28*$Z$4) -> 2360 | AB28: =SUM(Z28) -> 236 | AC28: =SUM(AB28*$Z$4) -> 2360 | AD28: =SUM(AB28) -> 236 | AE28: =SUM(AD28*$Z$4) -> 2360 | AF28: =SUM(AD28) -> 236 | AG28: =SUM(AF28*$Z$4) -> 2360 | AH28: =SUM(AF28) -> 236 | AI28: =SUM(AH28*$Z$4) -> 2360 | AJ28: =SUM(AH28) -> 236 | AK28: =SUM(AJ28*$Z$4) -> 2360 | AL28: =SUM(AJ28) -> 236 | AM28: =SUM(AL28*$Z$4) -> 2360 | AN28: =SUM(AO28/19600) -> 0.84285714 | AO28: =SUM(AA28+AC28+AE28+AG28+AI28+AK28+AM28) -> 16520 | AQ28: =SUM(AR28/92970) -> 0.76066612 | AR28: =Y28+AO28 -> 70719.129 | AS28: =SUM(AR28-AR27-AT28) -> -1840.0645 | AV28: =IF(AT28>0,AU28,AV27) -> 0.604 | AW28: =-SUM('B5'!AI27) -> -218 | AX28: =-SUM(AW28-AS28) -> -1622.0645 | AY28: =SUM(AX28+AW28) -> -1840.0645 | AZ28: =ELEC!A26 -> 0 | BA28: ='General information '!D27 -> 13 | BB28: =SUM('General information '!E27) -> 0.77 | BC28: =IF(AR27>=AR28,0,1) -> 0 | BD28: 19222 | BE28: =(305/1185)*ELEC!Q27 -> 0 | BG28: =#REF!-BE28 -> #REF! | BI28: 15 | BJ28: =AX28/BI28 -> -108.13763 | BK28: =GEN!AF25 -> 0.30472222
A29: =ELEC!C27 -> 44554 | B29: ='B5'!B28 -> 229 | C29: =B29*$B$4 -> 4927.1935 | D29: =SUM(B29) -> 229 | E29: =D29*$B$4 -> 4927.1935 | F29: =SUM(D29) -> 229 | G29: =F29*$B$4 -> 4927.1935 | H29: =SUM(F29) -> 229 | I29: =H29*$B$4 -> 4927.1935 | J29: =SUM(H29) -> 229 | K29: =J29*$B$4 -> 4927.1935 | L29: =SUM(J29) -> 229 | M29: =L29*$B$4 -> 4927.1935 | N29: =SUM(L29) -> 229 | O29: =N29*$B$4 -> 4927.1935 | P29: =SUM(N29) -> 229 | Q29: =P29*$B$4 -> 4927.1935 | R29: =SUM(P29) -> 229 | S29: =R29*$B$4 -> 4927.1935 | T29: =SUM(R29) -> 229 | U29: =T29*$B$4 -> 4927.1935 | V29: =SUM(T29) -> 229 | W29: =V29*$B$4 -> 4927.1935 | X29: =SUM(Y29/73370) -> 0.73870968 | Y29: =SUM(C29+E29+G29+I29+K29+M29+O29+Q29+S29+U29+W29) -> 54199.129 | Z29: ='B5'!C28 -> 236 | AA29: =SUM(Z29*$Z$4) -> 2360 | AB29: =SUM(Z29) -> 236 | AC29: =SUM(AB29*$Z$4) -> 2360 | AD29: =SUM(AB29) -> 236 | AE29: =SUM(AD29*$Z$4) -> 2360 | AF29: =SUM(AD29) -> 236 | AG29: =SUM(AF29*$Z$4) -> 2360 | AH29: =SUM(AF29) -> 236 | AI29: =SUM(AH29*$Z$4) -> 2360 | AJ29: =SUM(AH29) -> 236 | AK29: =SUM(AJ29*$Z$4) -> 2360 | AL29: =SUM(AJ29) -> 236 | AM29: =SUM(AL29*$Z$4) -> 2360 | AN29: =SUM(AO29/19600) -> 0.84285714 | AO29: =SUM(AA29+AC29+AE29+AG29+AI29+AK29+AM29) -> 16520 | AQ29: =SUM(AR29/92970) -> 0.76066612 | AR29: =Y29+AO29 -> 70719.129 | AS29: =SUM(AR29-AR28-AT29) -> 0 | AV29: =IF(AT29>0,AU29,AV28) -> 0.604 | AW29: =-SUM('B5'!AI28) -> 0 | AX29: =-SUM(AW29-AS29) -> 0 | AY29: =SUM(AX29+AW29) -> 0 | AZ29: =ELEC!A27 -> 0 | BA29: ='General information '!D28 -> 0 | BB29: =SUM('General information '!E28) -> 0 | BC29: =IF(AR28>=AR29,0,1) -> 0 | BD29: 19222 | BE29: =(305/1185)*ELEC!Q28 -> 0 | BG29: =#REF!-BE29 -> #REF! | BI29: 16 | BJ29: =AX29/BI29 -> 0 | BK29: =GEN!AF26 -> #DIV/0!
A30: =ELEC!C28 -> 44555 | B30: ='B5'!B29 -> 229 | C30: =B30*$B$4 -> 4927.1935 | D30: =SUM(B30) -> 229 | E30: =D30*$B$4 -> 4927.1935 | F30: =SUM(D30) -> 229 | G30: =F30*$B$4 -> 4927.1935 | H30: =SUM(F30) -> 229 | I30: =H30*$B$4 -> 4927.1935 | J30: =SUM(H30) -> 229 | K30: =J30*$B$4 -> 4927.1935 | L30: =SUM(J30) -> 229 | M30: =L30*$B$4 -> 4927.1935 | N30: =SUM(L30) -> 229 | O30: =N30*$B$4 -> 4927.1935 | P30: =SUM(N30) -> 229 | Q30: =P30*$B$4 -> 4927.1935 | R30: =SUM(P30) -> 229 | S30: =R30*$B$4 -> 4927.1935 | T30: =SUM(R30) -> 229 | U30: =T30*$B$4 -> 4927.1935 | V30: =SUM(T30) -> 229 | W30: =V30*$B$4 -> 4927.1935 | X30: =SUM(Y30/73370) -> 0.73870968 | Y30: =SUM(C30+E30+G30+I30+K30+M30+O30+Q30+S30+U30+W30) -> 54199.129 | Z30: ='B5'!C29 -> 236 | AA30: =SUM(Z30*$Z$4) -> 2360 | AB30: =SUM(Z30) -> 236 | AC30: =SUM(AB30*$Z$4) -> 2360 | AD30: =SUM(AB30) -> 236 | AE30: =SUM(AD30*$Z$4) -> 2360 | AF30: =SUM(AD30) -> 236 | AG30: =SUM(AF30*$Z$4) -> 2360 | AH30: =SUM(AF30) -> 236 | AI30: =SUM(AH30*$Z$4) -> 2360 | AJ30: =SUM(AH30) -> 236 | AK30: =SUM(AJ30*$Z$4) -> 2360 | AL30: =SUM(AJ30) -> 236 | AM30: =SUM(AL30*$Z$4) -> 2360 | AN30: =SUM(AO30/19600) -> 0.84285714 | AO30: =SUM(AA30+AC30+AE30+AG30+AI30+AK30+AM30) -> 16520 | AQ30: =SUM(AR30/92970) -> 0.76066612 | AR30: =Y30+AO30 -> 70719.129 | AS30: =SUM(AR30-AR29-AT30) -> 0 | AV30: =IF(AT30>0,AU30,AV29) -> 0.604 | AW30: =-SUM('B5'!AI29) -> 0 | AX30: =-SUM(AW30-AS30) -> 0 | AY30: =SUM(AX30+AW30) -> 0 | AZ30: =ELEC!A28 -> 0 | BA30: ='General information '!D29 -> 0 | BB30: =SUM('General information '!E29) -> 0 | BC30: =IF(AR29>=AR30,0,1) -> 0 | BD30: 19222 | BE30: =(305/1185)*ELEC!Q29 -> 0 | BG30: =#REF!-BE30 -> #REF! | BI30: 17 | BJ30: =AX30/BI30 -> 0 | BK30: =GEN!AF27 -> #DIV/0!
A31: =ELEC!C29 -> 44556 | B31: ='B5'!B30 -> 229 | C31: =B31*$B$4 -> 4927.1935 | D31: =SUM(B31) -> 229 | E31: =D31*$B$4 -> 4927.1935 | F31: =SUM(D31) -> 229 | G31: =F31*$B$4 -> 4927.1935 | H31: =SUM(F31) -> 229 | I31: =H31*$B$4 -> 4927.1935 | J31: =SUM(H31) -> 229 | K31: =J31*$B$4 -> 4927.1935 | L31: =SUM(J31) -> 229 | M31: =L31*$B$4 -> 4927.1935 | N31: =SUM(L31) -> 229 | O31: =N31*$B$4 -> 4927.1935 | P31: =SUM(N31) -> 229 | Q31: =P31*$B$4 -> 4927.1935 | R31: =SUM(P31) -> 229 | S31: =R31*$B$4 -> 4927.1935 | T31: =SUM(R31) -> 229 | U31: =T31*$B$4 -> 4927.1935 | V31: =SUM(T31) -> 229 | W31: =V31*$B$4 -> 4927.1935 | X31: =SUM(Y31/73370) -> 0.73870968 | Y31: =SUM(C31+E31+G31+I31+K31+M31+O31+Q31+S31+U31+W31) -> 54199.129 | Z31: ='B5'!C30 -> 236 | AA31: =SUM(Z31*$Z$4) -> 2360 | AB31: =SUM(Z31) -> 236 | AC31: =SUM(AB31*$Z$4) -> 2360 | AD31: =SUM(AB31) -> 236 | AE31: =SUM(AD31*$Z$4) -> 2360 | AF31: =SUM(AD31) -> 236 | AG31: =SUM(AF31*$Z$4) -> 2360 | AH31: =SUM(AF31) -> 236 | AI31: =SUM(AH31*$Z$4) -> 2360 | AJ31: =SUM(AH31) -> 236 | AK31: =SUM(AJ31*$Z$4) -> 2360 | AL31: =SUM(AJ31) -> 236 | AM31: =SUM(AL31*$Z$4) -> 2360 | AN31: =SUM(AO31/19600) -> 0.84285714 | AO31: =SUM(AA31+AC31+AE31+AG31+AI31+AK31+AM31) -> 16520 | AQ31: =SUM(AR31/92970) -> 0.76066612 | AR31: =Y31+AO31 -> 70719.129 | AS31: =SUM(AR31-AR30-AT31) -> 0 | AV31: =IF(AT31>0,AU31,AV30) -> 0.604 | AW31: =-SUM('B5'!AI30) -> 0 | AX31: =-SUM(AW31-AS31) -> 0 | AY31: =SUM(AX31+AW31) -> 0 | AZ31: =ELEC!A29 -> 0 | BA31: ='General information '!D30 -> 0 | BB31: =SUM('General information '!E30) -> 0 | BC31: =IF(AR30>=AR31,0,1) -> 0 | BD31: 19222 | BE31: =(305/1185)*ELEC!Q30 -> 1323.211 | BG31: =#REF!-BE31 -> #REF! | BI31: 18 | BJ31: =AX31/BI31 -> 0 | BK31: =GEN!AF28 -> #DIV/0!
A32: =ELEC!C30 -> 44557 | B32: ='B5'!B31 -> 223 | C32: =B32*$B$4 -> 4798.0968 | D32: =SUM(B32) -> 223 | E32: =D32*$B$4 -> 4798.0968 | F32: =SUM(D32) -> 223 | G32: =F32*$B$4 -> 4798.0968 | H32: =SUM(F32) -> 223 | I32: =H32*$B$4 -> 4798.0968 | J32: =SUM(H32) -> 223 | K32: =J32*$B$4 -> 4798.0968 | L32: =SUM(J32) -> 223 | M32: =L32*$B$4 -> 4798.0968 | N32: =SUM(L32) -> 223 | O32: =N32*$B$4 -> 4798.0968 | P32: =SUM(N32) -> 223 | Q32: =P32*$B$4 -> 4798.0968 | R32: =SUM(P32) -> 223 | S32: =R32*$B$4 -> 4798.0968 | T32: =SUM(R32) -> 223 | U32: =T32*$B$4 -> 4798.0968 | V32: =SUM(T32) -> 223 | W32: =V32*$B$4 -> 4798.0968 | X32: =SUM(Y32/73370) -> 0.71935484 | Y32: =SUM(C32+E32+G32+I32+K32+M32+O32+Q32+S32+U32+W32) -> 52779.065 | Z32: ='B5'!C31 -> 230 | AA32: =SUM(Z32*$Z$4) -> 2300 | AB32: =SUM(Z32) -> 230 | AC32: =SUM(AB32*$Z$4) -> 2300 | AD32: =SUM(AB32) -> 230 | AE32: =SUM(AD32*$Z$4) -> 2300 | AF32: =SUM(AD32) -> 230 | AG32: =SUM(AF32*$Z$4) -> 2300 | AH32: =SUM(AF32) -> 230 | AI32: =SUM(AH32*$Z$4) -> 2300 | AJ32: =SUM(AH32) -> 230 | AK32: =SUM(AJ32*$Z$4) -> 2300 | AL32: =SUM(AJ32) -> 230 | AM32: =SUM(AL32*$Z$4) -> 2300 | AN32: =SUM(AO32/19600) -> 0.82142857 | AO32: =SUM(AA32+AC32+AE32+AG32+AI32+AK32+AM32) -> 16100 | AQ32: =SUM(AR32/92970) -> 0.74087409 | AR32: =Y32+AO32 -> 68879.065 | AS32: =SUM(AR32-AR31-AT32) -> -1840.0645 | AV32: =IF(AT32>0,AU32,AV31) -> 0.604 | AW32: =-SUM('B5'!AI31) -> -199 | AX32: =-SUM(AW32-AS32) -> -1641.0645 | AY32: =SUM(AX32+AW32) -> -1840.0645 | AZ32: =ELEC!A30 -> 0 | BA32: ='General information '!D31 -> 15.5 | BB32: =SUM('General information '!E31) -> 0.5 | BC32: =IF(AR31>=AR32,0,1) -> 0 | BD32: 19222 | BE32: =(305/1185)*ELEC!Q31 -> 1362.8481 | BG32: =#REF!-BE32 -> #REF! | BI32: 19 | BJ32: =AX32/BI32 -> -86.371817 | BK32: =GEN!AF29 -> 0.3213125
A33: =ELEC!C31 -> 44558 | B33: ='B5'!B32 -> 216 | C33: =B33*$B$4 -> 4647.4839 | D33: =SUM(B33) -> 216 | E33: =D33*$B$4 -> 4647.4839 | F33: =SUM(D33) -> 216 | G33: =F33*$B$4 -> 4647.4839 | H33: =SUM(F33) -> 216 | I33: =H33*$B$4 -> 4647.4839 | J33: =SUM(H33) -> 216 | K33: =J33*$B$4 -> 4647.4839 | L33: =SUM(J33) -> 216 | M33: =L33*$B$4 -> 4647.4839 | N33: =SUM(L33) -> 216 | O33: =N33*$B$4 -> 4647.4839 | P33: =SUM(N33) -> 216 | Q33: =P33*$B$4 -> 4647.4839 | R33: =SUM(P33) -> 216 | S33: =R33*$B$4 -> 4647.4839 | T33: =SUM(R33) -> 216 | U33: =T33*$B$4 -> 4647.4839 | V33: =SUM(T33) -> 216 | W33: =V33*$B$4 -> 4647.4839 | X33: =SUM(Y33/73370) -> 0.69677419 | Y33: =SUM(C33+E33+G33+I33+K33+M33+O33+Q33+S33+U33+W33) -> 51122.323 | Z33: ='B5'!C32 -> 223 | AA33: =SUM(Z33*$Z$4) -> 2230 | AB33: =SUM(Z33) -> 223 | AC33: =SUM(AB33*$Z$4) -> 2230 | AD33: =SUM(AB33) -> 223 | AE33: =SUM(AD33*$Z$4) -> 2230 | AF33: =SUM(AD33) -> 223 | AG33: =SUM(AF33*$Z$4) -> 2230 | AH33: =SUM(AF33) -> 223 | AI33: =SUM(AH33*$Z$4) -> 2230 | AJ33: =SUM(AH33) -> 223 | AK33: =SUM(AJ33*$Z$4) -> 2230 | AL33: =SUM(AJ33) -> 223 | AM33: =SUM(AL33*$Z$4) -> 2230 | AN33: =SUM(AO33/19600) -> 0.79642857 | AO33: =SUM(AA33+AC33+AE33+AG33+AI33+AK33+AM33) -> 15610 | AQ33: =SUM(AR33/92970) -> 0.7177834 | AR33: =Y33+AO33 -> 66732.323 | AS33: =SUM(AR33-AR32-AT33) -> -2146.7419 | AV33: =IF(AT33>0,AU33,AV32) -> 0.604 | AW33: =-SUM('B5'!AI32) -> -314 | AX33: =-SUM(AW33-AS33) -> -1832.7419 | AY33: =SUM(AX33+AW33) -> -2146.7419 | AZ33: =ELEC!A31 -> 0 | BA33: ='General information '!D32 -> 16 | BB33: =SUM('General information '!E32) -> 0.43 | BC33: =IF(AR32>=AR33,0,1) -> 0 | BD33: 19222 | BE33: =(305/1185)*ELEC!#REF! -> #REF! | BG33: =#REF!-BE33 -> #REF! | BI33: 20 | BJ33: =AX33/BI33 -> -91.637097 | BK33: =GEN!AF30 -> 0.3309375
A34: =ELEC!C32 -> 44559 | B34: ='B5'!B33 -> 209 | C34: =B34*$B$4 -> 4496.871 | D34: =SUM(B34) -> 209 | E34: =D34*$B$4 -> 4496.871 | F34: =SUM(D34) -> 209 | G34: =F34*$B$4 -> 4496.871 | H34: =SUM(F34) -> 209 | I34: =H34*$B$4 -> 4496.871 | J34: =SUM(H34) -> 209 | K34: =J34*$B$4 -> 4496.871 | L34: =SUM(J34) -> 209 | M34: =L34*$B$4 -> 4496.871 | N34: =SUM(L34) -> 209 | O34: =N34*$B$4 -> 4496.871 | P34: =SUM(N34) -> 209 | Q34: =P34*$B$4 -> 4496.871 | R34: =SUM(P34) -> 209 | S34: =R34*$B$4 -> 4496.871 | T34: =SUM(R34) -> 209 | U34: =T34*$B$4 -> 4496.871 | V34: =SUM(T34) -> 209 | W34: =V34*$B$4 -> 4496.871 | X34: =SUM(Y34/73370) -> 0.67419355 | Y34: =SUM(C34+E34+G34+I34+K34+M34+O34+Q34+S34+U34+W34) -> 49465.581 | Z34: ='B5'!C33 -> 217 | AA34: =SUM(Z34*$Z$4) -> 2170 | AB34: =SUM(Z34) -> 217 | AC34: =SUM(AB34*$Z$4) -> 2170 | AD34: =SUM(AB34) -> 217 | AE34: =SUM(AD34*$Z$4) -> 2170 | AF34: =SUM(AD34) -> 217 | AG34: =SUM(AF34*$Z$4) -> 2170 | AH34: =SUM(AF34) -> 217 | AI34: =SUM(AH34*$Z$4) -> 2170 | AJ34: =SUM(AH34) -> 217 | AK34: =SUM(AJ34*$Z$4) -> 2170 | AL34: =SUM(AJ34) -> 217 | AM34: =SUM(AL34*$Z$4) -> 2170 | AN34: =SUM(AO34/19600) -> 0.775 | AO34: =SUM(AA34+AC34+AE34+AG34+AI34+AK34+AM34) -> 15190 | AQ34: =SUM(AR34/92970) -> 0.69544563 | AR34: =Y34+AO34 -> 64655.581 | AS34: =SUM(AR34-AR33-AT34) -> -2076.7419 | AV34: =IF(AT34>0,AU34,AV33) -> 0.604 | AW34: =-SUM('B5'!AI33) -> 0 | AX34: =-SUM(AW34-AS34) -> -2076.7419 | AY34: =SUM(AX34+AW34) -> -2076.7419 | AZ34: =ELEC!A32 -> 0 | BA34: ='General information '!D33 -> 16.5 | BB34: =SUM('General information '!E33) -> 0.47 | BI34: 21 | BJ34: =AX34/BI34 -> -98.892473 | BK34: =GEN!AF31 -> 0.3644375
