Workbook

Sheet Submetering
A1: Site Name | B1: Day | C1: Month | D1: Year | E1: Transport Consumption (LT) | F1: Generators Consumption (LT) | G1: Total Electricity Kwh | H1: Kitchen (KWh) | I1: Laundry (KWh) | J1: STP (M3) | K1: RO prodution (M3) | L1: Amani Restaurant (M3) | M1: Kitchen (M3) | N1: Laundry (M3) | O1: Laundry (M3) | P1: Total water Consumption (M3) | Q1: Borehole #1 (M3) | R1: Borehole #2 (M3) | S1: Borehole #3 (M3) | T1: Borehole #4 (M3) | U1: Borehole #5 (M3) | V1: Borehole #6 (M3) | W1: Total Bore holes production (M3) | X1: Room Nights
A2: Serengeti | B2: 1 | C2: 12 | D2: 2021 | E2: ='UTILITY REPORT 1'!I3 -> 55.31 | F2: ='UTILITY REPORT 1'!E3 -> 1340.69 | G2: ='UTILITY REPORT 1'!F3 -> 3130 | H2: =IF('Kit report'!F4<0,"0",'Kit report'!F4) -> 240 | I2: =IF('Kit report'!X4<0,"0",'Kit report'!X4) -> 0 | J2: =IF('Utility summery'!H6<0,"0",'Utility summery'!H6) -> 73 | K2: =IF('UTILITY REPORT 1'!H3<0,"0",'UTILITY REPORT 1'!H3) -> 35 | L2: ='Water-Meter'!K6 -> 1 | M2: ='Water-Meter'!H6 -> 0 | N2: ='Water-Meter'!Q6 -> 7 | O2: =K2*E2+H2*I2+#REF!*#REF!+J2*L2 -> #REF! | P2: ='Water-Meter'!E6 -> 79 | Q2: =IF('Water-Meter'!U6<0,"0",'Water-Meter'!U6) -> 35 | R2: =IF('Water-Meter'!X6<0,"0",'Water-Meter'!X6) -> 0 | S2: =IF('Water-Meter'!AA6<0,"0",'Water-Meter'!AA6) -> 36 | T2: =IF('Water-Meter'!AD6<0,"0",'Water-Meter'!AD6) -> 26 | U2: =IF('Water-Meter'!AG6<0,"0",'Water-Meter'!AG6) -> 0 | V2: =IF('Water-Meter'!AJ6<0,"0",'Water-Meter'!AJ6) -> 35 | W2: ='Water-Meter'!AN6 -> 132 | X2: 6
A3: Serengeti | B3: =B2+1 -> 2 | C3: 12 | D3: 2021 | E3: ='UTILITY REPORT 1'!I4 -> 596.04 | F3: ='UTILITY REPORT 1'!E4 -> 1268.81 | G3: ='UTILITY REPORT 1'!F4 -> 3105 | H3: =IF('Kit report'!F5<0,"0",'Kit report'!F5) -> 240 | I3: =IF('Kit report'!X5<0,"0",'Kit report'!X5) -> 440 | J3: =IF('Utility summery'!H7<0,"0",'Utility summery'!H7) -> 69 | K3: =IF('UTILITY REPORT 1'!H4<0,"0",'UTILITY REPORT 1'!H4) -> 61 | L3: ='Water-Meter'!K7 -> 2 | M3: ='Water-Meter'!H7 -> 0 | N3: ='Water-Meter'!Q7 -> 5 | O3: =K3*E3+H3*I3+#REF!*#REF!+J3*L3 -> #REF! | P3: ='Water-Meter'!E7 -> 67 | Q3: =IF('Water-Meter'!U7<0,"0",'Water-Meter'!U7) -> 0 | R3: =IF('Water-Meter'!X7<0,"0",'Water-Meter'!X7) -> 0 | S3: =IF('Water-Meter'!AA7<0,"0",'Water-Meter'!AA7) -> 37 | T3: =IF('Water-Meter'!AD7<0,"0",'Water-Meter'!AD7) -> 1 | U3: =IF('Water-Meter'!AG7<0,"0",'Water-Meter'!AG7) -> 0 | V3: =IF('Water-Meter'!AJ7<0,"0",'Water-Meter'!AJ7) -> 36 | W3: ='Water-Meter'!AN7 -> 74 | X3: 5
A4: Serengeti | B4: =B3+1 -> 3 | C4: 12 | D4: 2021 | E4: ='UTILITY REPORT 1'!I5 -> 0 | F4: ='UTILITY REPORT 1'!E5 -> 1177.17 | G4: ='UTILITY REPORT 1'!F5 -> 2910 | H4: =IF('Kit report'!F6<0,"0",'Kit report'!F6) -> 252 | I4: =IF('Kit report'!X6<0,"0",'Kit report'!X6) -> 320 | J4: =IF('Utility summery'!H8<0,"0",'Utility summery'!H8) -> 70 | K4: =IF('UTILITY REPORT 1'!H5<0,"0",'UTILITY REPORT 1'!H5) -> 50 | L4: ='Water-Meter'!K8 -> 2 | M4: ='Water-Meter'!H8 -> 0 | N4: ='Water-Meter'!Q8 -> 3 | O4: =K4*E4+H4*I4+#REF!*#REF!+J4*L4 -> #REF! | P4: ='Water-Meter'!E8 -> 83 | Q4: =IF('Water-Meter'!U8<0,"0",'Water-Meter'!U8) -> 0 | R4: =IF('Water-Meter'!X8<0,"0",'Water-Meter'!X8) -> 0 | S4: =IF('Water-Meter'!AA8<0,"0",'Water-Meter'!AA8) -> 38 | T4: =IF('Water-Meter'!AD8<0,"0",'Water-Meter'!AD8) -> 10 | U4: =IF('Water-Meter'!AG8<0,"0",'Water-Meter'!AG8) -> 0 | V4: =IF('Water-Meter'!AJ8<0,"0",'Water-Meter'!AJ8) -> 36 | W4: ='Water-Meter'!AN8 -> 84 | X4: 3
A5: Serengeti | B5: =B4+1 -> 4 | C5: 12 | D5: 2021 | E5: ='UTILITY REPORT 1'!I6 -> 199.51 | F5: ='UTILITY REPORT 1'!E6 -> 1293.22 | G5: ='UTILITY REPORT 1'!F6 -> 3289 | H5: =IF('Kit report'!F7<0,"0",'Kit report'!F7) -> 276 | I5: =IF('Kit report'!X7<0,"0",'Kit report'!X7) -> 340 | J5: =IF('Utility summery'!H9<0,"0",'Utility summery'!H9) -> 63 | K5: =IF('UTILITY REPORT 1'!H6<0,"0",'UTILITY REPORT 1'!H6) -> 89 | L5: ='Water-Meter'!K9 -> 13 | M5: ='Water-Meter'!H9 -> 0 | N5: ='Water-Meter'!Q9 -> 5 | O5: =K5*E5+H5*I5+#REF!*#REF!+J5*L5 -> #REF! | P5: ='Water-Meter'!E9 -> 67 | Q5: =IF('Water-Meter'!U9<0,"0",'Water-Meter'!U9) -> 0 | R5: =IF('Water-Meter'!X9<0,"0",'Water-Meter'!X9) -> 0 | S5: =IF('Water-Meter'!AA9<0,"0",'Water-Meter'!AA9) -> 33 | T5: =IF('Water-Meter'!AD9<0,"0",'Water-Meter'!AD9) -> 15 | U5: =IF('Water-Meter'!AG9<0,"0",'Water-Meter'!AG9) -> 0 | V5: =IF('Water-Meter'!AJ9<0,"0",'Water-Meter'!AJ9) -> 33 | W5: ='Water-Meter'!AN9 -> 81 | X5: 8
A6: Serengeti | B6: =B5+1 -> 5 | C6: 12 | D6: 2021 | E6: ='UTILITY REPORT 1'!I7 -> 53.33 | F6: ='UTILITY REPORT 1'!E7 -> 1246.93 | G6: ='UTILITY REPORT 1'!F7 -> 3146 | H6: =IF('Kit report'!F8<0,"0",'Kit report'!F8) -> 216 | I6: =IF('Kit report'!X8<0,"0",'Kit report'!X8) -> 300 | J6: =IF('Utility summery'!H10<0,"0",'Utility summery'!H10) -> 47 | K6: =IF('UTILITY REPORT 1'!H7<0,"0",'UTILITY REPORT 1'!H7) -> 103 | L6: ='Water-Meter'!K10 -> 6 | M6: ='Water-Meter'!H10 -> 0 | N6: ='Water-Meter'!Q10 -> 4 | O6: =K6*E6+H6*I6+#REF!*#REF!+J6*L6 -> #REF! | P6: ='Water-Meter'!E10 -> 62 | Q6: =IF('Water-Meter'!U10<0,"0",'Water-Meter'!U10) -> 0 | R6: =IF('Water-Meter'!X10<0,"0",'Water-Meter'!X10) -> 0 | S6: =IF('Water-Meter'!AA10<0,"0",'Water-Meter'!AA10) -> 35 | T6: =IF('Water-Meter'!AD10<0,"0",'Water-Meter'!AD10) -> 14 | U6: =IF('Water-Meter'!AG10<0,"0",'Water-Meter'!AG10) -> 0 | V6: =IF('Water-Meter'!AJ10<0,"0",'Water-Meter'!AJ10) -> 35 | W6: ='Water-Meter'!AN10 -> 84 | X6: 6
A7: Serengeti | B7: =B6+1 -> 6 | C7: 12 | D7: 2021 | E7: ='UTILITY REPORT 1'!I8 -> 67.4 | F7: ='UTILITY REPORT 1'!E8 -> 1325.89 | G7: ='UTILITY REPORT 1'!F8 -> 3361 | H7: =IF('Kit report'!F9<0,"0",'Kit report'!F9) -> 228 | I7: =IF('Kit report'!X9<0,"0",'Kit report'!X9) -> 320 | J7: =IF('Utility summery'!H11<0,"0",'Utility summery'!H11) -> 53 | K7: =IF('UTILITY REPORT 1'!H8<0,"0",'UTILITY REPORT 1'!H8) -> 17 | L7: ='Water-Meter'!K11 -> 2 | M7: ='Water-Meter'!H11 -> 0 | N7: ='Water-Meter'!Q11 -> 5 | O7: =K7*E7+H7*I7+#REF!*#REF!+J7*L7 -> #REF! | P7: ='Water-Meter'!E11 -> 57 | Q7: =IF('Water-Meter'!U11<0,"0",'Water-Meter'!U11) -> 0 | R7: =IF('Water-Meter'!X11<0,"0",'Water-Meter'!X11) -> 0 | S7: =IF('Water-Meter'!AA11<0,"0",'Water-Meter'!AA11) -> 35 | T7: =IF('Water-Meter'!AD11<0,"0",'Water-Meter'!AD11) -> 2 | U7: =IF('Water-Meter'!AG11<0,"0",'Water-Meter'!AG11) -> 0 | V7: =IF('Water-Meter'!AJ11<0,"0",'Water-Meter'!AJ11) -> 35 | W7: ='Water-Meter'!AN11 -> 72 | X7: 9
A8: Serengeti | B8: =B7+1 -> 7 | C8: 12 | D8: 2021 | E8: ='UTILITY REPORT 1'!I9 -> 135.94 | F8: ='UTILITY REPORT 1'!E9 -> 1368.94 | G8: ='UTILITY REPORT 1'!F9 -> 3380 | H8: =IF('Kit report'!F10<0,"0",'Kit report'!F10) -> 228 | I8: =IF('Kit report'!X10<0,"0",'Kit report'!X10) -> 320 | J8: =IF('Utility summery'!H12<0,"0",'Utility summery'!H12) -> 50 | K8: =IF('UTILITY REPORT 1'!H9<0,"0",'UTILITY REPORT 1'!H9) -> 121 | L8: ='Water-Meter'!K12 -> 3 | M8: ='Water-Meter'!H12 -> 0 | N8: ='Water-Meter'!Q12 -> 7 | O8: =K8*E8+H8*I8+#REF!*#REF!+J8*L8 -> #REF! | P8: ='Water-Meter'!E12 -> 73 | Q8: =IF('Water-Meter'!U12<0,"0",'Water-Meter'!U12) -> 0 | R8: =IF('Water-Meter'!X12<0,"0",'Water-Meter'!X12) -> 0 | S8: =IF('Water-Meter'!AA12<0,"0",'Water-Meter'!AA12) -> 37 | T8: =IF('Water-Meter'!AD12<0,"0",'Water-Meter'!AD12) -> 0 | U8: =IF('Water-Meter'!AG12<0,"0",'Water-Meter'!AG12) -> 0 | V8: =IF('Water-Meter'!AJ12<0,"0",'Water-Meter'!AJ12) -> 35 | W8: ='Water-Meter'!AN12 -> 72 | X8: 9
A9: Serengeti | B9: =B8+1 -> 8 | C9: 12 | D9: 2021 | E9: ='UTILITY REPORT 1'!I10 -> 83.59 | F9: ='UTILITY REPORT 1'!E10 -> 1527.6 | G9: ='UTILITY REPORT 1'!F10 -> 3662 | H9: =IF('Kit report'!F11<0,"0",'Kit report'!F11) -> 240 | I9: =IF('Kit report'!X11<0,"0",'Kit report'!X11) -> 440 | J9: =IF('Utility summery'!H13<0,"0",'Utility summery'!H13) -> 63 | K9: =IF('UTILITY REPORT 1'!H10<0,"0",'UTILITY REPORT 1'!H10) -> 170 | L9: ='Water-Meter'!K13 -> 3 | M9: ='Water-Meter'!H13 -> 0 | N9: ='Water-Meter'!Q13 -> 6 | O9: =K9*E9+H9*I9+#REF!*#REF!+J9*L9 -> #REF! | P9: ='Water-Meter'!E13 -> 80 | Q9: =IF('Water-Meter'!U13<0,"0",'Water-Meter'!U13) -> 74 | R9: =IF('Water-Meter'!X13<0,"0",'Water-Meter'!X13) -> 0 | S9: =IF('Water-Meter'!AA13<0,"0",'Water-Meter'!AA13) -> 35 | T9: =IF('Water-Meter'!AD13<0,"0",'Water-Meter'!AD13) -> 0 | U9: =IF('Water-Meter'!AG13<0,"0",'Water-Meter'!AG13) -> 0 | V9: =IF('Water-Meter'!AJ13<0,"0",'Water-Meter'!AJ13) -> 35 | W9: ='Water-Meter'!AN13 -> 144 | X9: 12
A10: Serengeti | B10: =B9+1 -> 9 | C10: 12 | D10: 2021 | E10: ='UTILITY REPORT 1'!I11 -> 51.98 | F10: ='UTILITY REPORT 1'!E11 -> 1371.66 | G10: ='UTILITY REPORT 1'!F11 -> 3399 | H10: =IF('Kit report'!F12<0,"0",'Kit report'!F12) -> 240 | I10: =IF('Kit report'!X12<0,"0",'Kit report'!X12) -> 320 | J10: =IF('Utility summery'!H14<0,"0",'Utility summery'!H14) -> 55 | K10: =IF('UTILITY REPORT 1'!H11<0,"0",'UTILITY REPORT 1'!H11) -> 0 | L10: ='Water-Meter'!K14 -> 2 | M10: ='Water-Meter'!H14 -> 0 | N10: ='Water-Meter'!Q14 -> 3 | O10: =K10*E10+H10*I10+#REF!*#REF!+J10*L10 -> #REF! | P10: ='Water-Meter'!E14 -> 65 | Q10: =IF('Water-Meter'!U14<0,"0",'Water-Meter'!U14) -> 68 | R10: =IF('Water-Meter'!X14<0,"0",'Water-Meter'!X14) -> 0 | S10: =IF('Water-Meter'!AA14<0,"0",'Water-Meter'!AA14) -> 34 | T10: =IF('Water-Meter'!AD14<0,"0",'Water-Meter'!AD14) -> 0 | U10: =IF('Water-Meter'!AG14<0,"0",'Water-Meter'!AG14) -> 0 | V10: =IF('Water-Meter'!AJ14<0,"0",'Water-Meter'!AJ14) -> 33 | W10: ='Water-Meter'!AN14 -> 135 | X10: 10
A11: Serengeti | B11: =B10+1 -> 10 | C11: 12 | D11: 2021 | E11: ='UTILITY REPORT 1'!I12 -> 448.65 | F11: ='UTILITY REPORT 1'!E12 -> 1347.33 | G11: ='UTILITY REPORT 1'!F12 -> 3440 | H11: =IF('Kit report'!F13<0,"0",'Kit report'!F13) -> 252 | I11: =IF('Kit report'!X13<0,"0",'Kit report'!X13) -> 380 | J11: =IF('Utility summery'!H15<0,"0",'Utility summery'!H15) -> 54 | K11: =IF('UTILITY REPORT 1'!H12<0,"0",'UTILITY REPORT 1'!H12) -> 167 | L11: ='Water-Meter'!K15 -> 1 | M11: ='Water-Meter'!H15 -> 0 | N11: ='Water-Meter'!Q15 -> 6 | O11: =K11*E11+H11*I11+#REF!*#REF!+J11*L11 -> #REF! | P11: ='Water-Meter'!E15 -> 71 | Q11: =IF('Water-Meter'!U15<0,"0",'Water-Meter'!U15) -> 73 | R11: =IF('Water-Meter'!X15<0,"0",'Water-Meter'!X15) -> 0 | S11: =IF('Water-Meter'!AA15<0,"0",'Water-Meter'!AA15) -> 37 | T11: =IF('Water-Meter'!AD15<0,"0",'Water-Meter'!AD15) -> 0 | U11: =IF('Water-Meter'!AG15<0,"0",'Water-Meter'!AG15) -> 0 | V11: =IF('Water-Meter'!AJ15<0,"0",'Water-Meter'!AJ15) -> 36 | W11: ='Water-Meter'!AN15 -> 146 | X11: 12
A12: Serengeti | B12: =B11+1 -> 11 | C12: 12 | D12: 2021 | E12: ='UTILITY REPORT 1'!I13 -> 37.87 | F12: ='UTILITY REPORT 1'!E13 -> 1512.79 | G12: ='UTILITY REPORT 1'!F13 -> 3696 | H12: =IF('Kit report'!F14<0,"0",'Kit report'!F14) -> 228 | I12: =IF('Kit report'!X14<0,"0",'Kit report'!X14) -> 340 | J12: =IF('Utility summery'!H16<0,"0",'Utility summery'!H16) -> 60 | K12: =IF('UTILITY REPORT 1'!H13<0,"0",'UTILITY REPORT 1'!H13) -> 15 | L12: ='Water-Meter'!K16 -> 2 | M12: ='Water-Meter'!H16 -> 0 | N12: ='Water-Meter'!Q16 -> 4 | O12: =K12*E12+H12*I12+#REF!*#REF!+J12*L12 -> #REF! | P12: ='Water-Meter'!E16 -> 72 | Q12: =IF('Water-Meter'!U16<0,"0",'Water-Meter'!U16) -> 69 | R12: =IF('Water-Meter'!X16<0,"0",'Water-Meter'!X16) -> 0 | S12: =IF('Water-Meter'!AA16<0,"0",'Water-Meter'!AA16) -> 36 | T12: =IF('Water-Meter'!AD16<0,"0",'Water-Meter'!AD16) -> 0 | U12: =IF('Water-Meter'!AG16<0,"0",'Water-Meter'!AG16) -> 0 | V12: =IF('Water-Meter'!AJ16<0,"0",'Water-Meter'!AJ16) -> 35 | W12: ='Water-Meter'!AN16 -> 140 | X12: 12
A13: Serengeti | B13: =B12+1 -> 12 | C13: 12 | D13: 2021 | E13: ='UTILITY REPORT 1'!I14 -> 68.16 | F13: ='UTILITY REPORT 1'!E14 -> 1485.24 | G13: ='UTILITY REPORT 1'!F14 -> 3646 | H13: =IF('Kit report'!F15<0,"0",'Kit report'!F15) -> 264 | I13: =IF('Kit report'!X15<0,"0",'Kit report'!X15) -> 440 | J13: =IF('Utility summery'!H17<0,"0",'Utility summery'!H17) -> 62 | K13: =IF('UTILITY REPORT 1'!H14<0,"0",'UTILITY REPORT 1'!H14) -> 157 | L13: ='Water-Meter'!K17 -> 2 | M13: ='Water-Meter'!H17 -> 0 | N13: ='Water-Meter'!Q17 -> 5 | O13: =K13*E13+H13*I13+#REF!*#REF!+J13*L13 -> #REF! | P13: ='Water-Meter'!E17 -> 65 | Q13: =IF('Water-Meter'!U17<0,"0",'Water-Meter'!U17) -> 69 | R13: =IF('Water-Meter'!X17<0,"0",'Water-Meter'!X17) -> 0 | S13: =IF('Water-Meter'!AA17<0,"0",'Water-Meter'!AA17) -> 37 | T13: =IF('Water-Meter'!AD17<0,"0",'Water-Meter'!AD17) -> 0 | U13: =IF('Water-Meter'!AG17<0,"0",'Water-Meter'!AG17) -> 0 | V13: =IF('Water-Meter'!AJ17<0,"0",'Water-Meter'!AJ17) -> 35 | W13: ='Water-Meter'!AN17 -> 141 | X13: 12
A14: Serengeti | B14: =B13+1 -> 13 | C14: 12 | D14: 2021 | E14: ='UTILITY REPORT 1'!I15 -> 103.25 | F14: ='UTILITY REPORT 1'!E15 -> 1579.63 | G14: ='UTILITY REPORT 1'!F15 -> 3967 | H14: =IF('Kit report'!F16<0,"0",'Kit report'!F16) -> 276 | I14: =IF('Kit report'!X16<0,"0",'Kit report'!X16) -> 560 | J14: =IF('Utility summery'!H18<0,"0",'Utility summery'!H18) -> 66 | K14: =IF('UTILITY REPORT 1'!H15<0,"0",'UTILITY REPORT 1'!H15) -> 44 | L14: ='Water-Meter'!K18 -> 3 | M14: ='Water-Meter'!H18 -> 0 | N14: ='Water-Meter'!Q18 -> 7 | O14: =K14*E14+H14*I14+#REF!*#REF!+J14*L14 -> #REF! | P14: ='Water-Meter'!E18 -> 68 | Q14: =IF('Water-Meter'!U18<0,"0",'Water-Meter'!U18) -> 69 | R14: =IF('Water-Meter'!X18<0,"0",'Water-Meter'!X18) -> 0 | S14: =IF('Water-Meter'!AA18<0,"0",'Water-Meter'!AA18) -> 39 | T14: =IF('Water-Meter'!AD18<0,"0",'Water-Meter'!AD18) -> 0 | U14: =IF('Water-Meter'!AG18<0,"0",'Water-Meter'!AG18) -> 0 | V14: =IF('Water-Meter'!AJ18<0,"0",'Water-Meter'!AJ18) -> 38 | W14: ='Water-Meter'!AN18 -> 146 | X14: 15
... A30: Serengeti | B30: =B29+1 -> 29 | C30: 12 | D30: 2021 | E30: ='UTILITY REPORT 1'!I31 -> 236.12 | F30: ='UTILITY REPORT 1'!E31 -> 2039.95 | G30: ='UTILITY REPORT 1'!F31 -> 4892 | H30: =IF('Kit report'!F32<0,"0",'Kit report'!F32) -> 180 | I30: =IF('Kit report'!X32<0,"0",'Kit report'!X32) -> 840 | J30: =IF('Utility summery'!H34<0,"0",'Utility summery'!H34) -> 63 | K30: =IF('UTILITY REPORT 1'!H31<0,"0",'UTILITY REPORT 1'!H31) -> 101 | L30: ='Water-Meter'!K34 -> 5 | M30: ='Water-Meter'!H34 -> 0 | N30: ='Water-Meter'!Q34 -> 14 | O30: =K30*E30+H30*I30+#REF!*#REF!+J30*L30 -> #REF! | P30: ='Water-Meter'!E34 -> 111 | Q30: =IF('Water-Meter'!U34<0,"0",'Water-Meter'!U34) -> 48 | R30: =IF('Water-Meter'!X34<0,"0",'Water-Meter'!X34) -> 0 | S30: =IF('Water-Meter'!AA34<0,"0",'Water-Meter'!AA34) -> 44 | T30: =IF('Water-Meter'!AD34<0,"0",'Water-Meter'!AD34) -> 15 | U30: =IF('Water-Meter'!AG34<0,"0",'Water-Meter'!AG34) -> 0 | V30: =IF('Water-Meter'!AJ34<0,"0",'Water-Meter'!AJ34) -> 37 | W30: ='Water-Meter'!AN34 -> 144 | X30: 42
A31: Serengeti | B31: 30 | C31: 12 | D31: 2021 | E31: ='UTILITY REPORT 1'!I32 -> 34.26 | F31: ='UTILITY REPORT 1'!E32 -> 2039.77 | G31: ='UTILITY REPORT 1'!F32 -> 4766 | H31: =IF('Kit report'!F33<0,"0",'Kit report'!F33) -> 216 | I31: =IF('Kit report'!X33<0,"0",'Kit report'!X33) -> 900 | J31: =IF('Utility summery'!H35<0,"0",'Utility summery'!H35) -> 49 | K31: =IF('UTILITY REPORT 1'!H32<0,"0",'UTILITY REPORT 1'!H32) -> 149 | L31: ='Water-Meter'!K35 -> 3 | M31: ='Water-Meter'!H35 -> 0 | N31: ='Water-Meter'!Q35 -> 10 | O31: =K31*E31+H31*I31+#REF!*#REF!+J31*L31 -> #REF! | P31: ='Water-Meter'!E35 -> 102 | Q31: =IF('Water-Meter'!U35<0,"0",'Water-Meter'!U35) -> 25 | R31: =IF('Water-Meter'!X35<0,"0",'Water-Meter'!X35) -> 0 | S31: =IF('Water-Meter'!AA35<0,"0",'Water-Meter'!AA35) -> 43 | T31: =IF('Water-Meter'!AD35<0,"0",'Water-Meter'!AD35) -> 14 | U31: =IF('Water-Meter'!AG35<0,"0",'Water-Meter'!AG35) -> 0 | V31: =IF('Water-Meter'!AJ35<0,"0",'Water-Meter'!AJ35) -> 36 | W31: ='Water-Meter'!AN35 -> 118 | X31: 48
A32: Serengeti | B32: 31 | C32: 12 | D32: 2021 | E32: ='UTILITY REPORT 1'!I33 -> 882.87 | F32: ='UTILITY REPORT 1'!E33 -> 1894.18 | G32: ='UTILITY REPORT 1'!F33 -> 4562 | H32: =IF('Kit report'!F34<0,"0",'Kit report'!F34) -> 264 | I32: =IF('Kit report'!X34<0,"0",'Kit report'!X34) -> 800 | J32: =IF('Utility summery'!H36<0,"0",'Utility summery'!H36) -> 51 | K32: =IF('UTILITY REPORT 1'!H33<0,"0",'UTILITY REPORT 1'!H33) -> 156 | L32: ='Water-Meter'!K36 -> 3 | M32: ='Water-Meter'!H36 -> 0 | N32: ='Water-Meter'!Q36 -> 9 | P32: ='Water-Meter'!E36 -> 102 | Q32: =IF('Water-Meter'!U36<0,"0",'Water-Meter'!U36) -> 0 | R32: =IF('Water-Meter'!X36<0,"0",'Water-Meter'!X36) -> 0 | S32: =IF('Water-Meter'!AA36<0,"0",'Water-Meter'!AA36) -> 39 | T32: =IF('Water-Meter'!AD36<0,"0",'Water-Meter'!AD36) -> 11 | U32: =IF('Water-Meter'!AG36<0,"0",'Water-Meter'!AG36) -> 0 | V32: =IF('Water-Meter'!AJ36<0,"0",'Water-Meter'!AJ36) -> 33 | W32: ='Water-Meter'!AN36 -> 83 | X32: 48

Sheet Total
A1: Site Name | B1: Day | C1: Month | D1: Year | E1: Total Electricity Kwh | F1: Electricity Tariff ($/Kwh) | G1: LPG (Kg) | H1: LPG $/Kg | I1: Water Utility Supply (m3) m3 | J1: Water Utility Supply (m3) $/m3 | K1: Room Nights | L1: Utilities day cost dh
A2: Serengeti | B2: 1 | C2: 12 | D2: 2021 | E2: ='UTILITY REPORT 1'!F3 -> 3130 | F2: =('UTILITY REPORT 1'!E3*'UTILITY REPORT 1'!D3)/'UTILITY REPORT 1'!F3 -> 0.42833546 | G2: =IF('Utility summery'!M6<0,"0",'Utility summery'!M6) -> 101.244 | H2: 2.165 | I2: =IF('UTILITY REPORT 1'!G3<0,"0",'UTILITY REPORT 1'!G3) -> 79 | J2: 0 | K2: =Submetering!X2 -> 6 | L2: =E2*F2+G2*H2+#REF!*#REF!+I2*J2 -> #REF!
A3: Serengeti | B3: =B2+1 -> 2 | C3: 12 | D3: 2021 | E3: ='UTILITY REPORT 1'!F4 -> 3105 | F3: =('UTILITY REPORT 1'!E4*'UTILITY REPORT 1'!D4)/'UTILITY REPORT 1'!F4 -> 0.40863446 | G3: =IF('Utility summery'!M7<0,"0",'Utility summery'!M7) -> 70.312 | H3: 2.165 | I3: =IF('UTILITY REPORT 1'!G4<0,"0",'UTILITY REPORT 1'!G4) -> 67 | J3: 0 | K3: =Submetering!X3 -> 5 | L3: =E3*F3+G3*H3+#REF!*#REF!+I3*J3 -> #REF!
A4: Serengeti | B4: =B3+1 -> 3 | C4: 12 | D4: 2021 | E4: ='UTILITY REPORT 1'!F5 -> 2910 | F4: =('UTILITY REPORT 1'!E5*'UTILITY REPORT 1'!D5)/'UTILITY REPORT 1'!F5 -> 0.40452577 | G4: =IF('Utility summery'!M8<0,"0",'Utility summery'!M8) -> 59.576 | H4: 2.165 | I4: =IF('UTILITY REPORT 1'!G5<0,"0",'UTILITY REPORT 1'!G5) -> 83 | J4: 0 | K4: =Submetering!X4 -> 3 | L4: =E4*F4+G4*H4+#REF!*#REF!+I4*J4 -> #REF!
A5: Serengeti | B5: =B4+1 -> 4 | C5: 12 | D5: 2021 | E5: ='UTILITY REPORT 1'!F6 -> 3289 | F5: =('UTILITY REPORT 1'!E6*'UTILITY REPORT 1'!D6)/'UTILITY REPORT 1'!F6 -> 0.3931955 | G5: =IF('Utility summery'!M9<0,"0",'Utility summery'!M9) -> 61.512 | H5: 2.165 | I5: =IF('UTILITY REPORT 1'!G6<0,"0",'UTILITY REPORT 1'!G6) -> 67 | J5: 0 | K5: =Submetering!X5 -> 8 | L5: =E5*F5+G5*H5+#REF!*#REF!+I5*J5 -> #REF!
A6: Serengeti | B6: =B5+1 -> 5 | C6: 12 | D6: 2021 | E6: ='UTILITY REPORT 1'!F7 -> 3146 | F6: =('UTILITY REPORT 1'!E7*'UTILITY REPORT 1'!D7)/'UTILITY REPORT 1'!F7 -> 0.3963541 | G6: =IF('Utility summery'!M10<0,"0",'Utility summery'!M10) -> 87.34 | H6: 2.165 | I6: =IF('UTILITY REPORT 1'!G7<0,"0",'UTILITY REPORT 1'!G7) -> 62 | J6: 0 | K6: =Submetering!X6 -> 6 | L6: =E6*F6+G6*H6+#REF!*#REF!+I6*J6 -> #REF!
A7: Serengeti | B7: =B6+1 -> 6 | C7: 12 | D7: 2021 | E7: ='UTILITY REPORT 1'!F8 -> 3361 | F7: =('UTILITY REPORT 1'!E8*'UTILITY REPORT 1'!D8)/'UTILITY REPORT 1'!F8 -> 0.39449271 | G7: =IF('Utility summery'!M11<0,"0",'Utility summery'!M11) -> 107.492 | H7: 2.165 | I7: =IF('UTILITY REPORT 1'!G8<0,"0",'UTILITY REPORT 1'!G8) -> 57 | J7: 0 | K7: =Submetering!X7 -> 9 | L7: =E7*F7+G7*H7+#REF!*#REF!+I7*J7 -> #REF!
A8: Serengeti | B8: =B7+1 -> 7 | C8: 12 | D8: 2021 | E8: ='UTILITY REPORT 1'!F9 -> 3380 | F8: =('UTILITY REPORT 1'!E9*'UTILITY REPORT 1'!D9)/'UTILITY REPORT 1'!F9 -> 0.40501183 | G8: =IF('Utility summery'!M12<0,"0",'Utility summery'!M12) -> 90.684 | H8: 2.165 | I8: =IF('UTILITY REPORT 1'!G9<0,"0",'UTILITY REPORT 1'!G9) -> 73 | J8: 0 | K8: =Submetering!X8 -> 9 | L8: =E8*F8+G8*H8+#REF!*#REF!+I8*J8 -> #REF!
A9: Serengeti | B9: =B8+1 -> 8 | C9: 12 | D9: 2021 | E9: ='UTILITY REPORT 1'!F10 -> 3662 | F9: =('UTILITY REPORT 1'!E10*'UTILITY REPORT 1'!D10)/'UTILITY REPORT 1'!F10 -> 0.4171491 | G9: =IF('Utility summery'!M13<0,"0",'Utility summery'!M13) -> 99.88 | H9: 2.165 | I9: =IF('UTILITY REPORT 1'!G10<0,"0",'UTILITY REPORT 1'!G10) -> 80 | J9: 0 | K9: =Submetering!X9 -> 12 | L9: =E9*F9+G9*H9+#REF!*#REF!+I9*J9 -> #REF!
A10: Serengeti | B10: =B9+1 -> 9 | C10: 12 | D10: 2021 | E10: ='UTILITY REPORT 1'!F11 -> 3399 | F10: =('UTILITY REPORT 1'!E11*'UTILITY REPORT 1'!D11)/'UTILITY REPORT 1'!F11 -> 0.4035481 | G10: =IF('Utility summery'!M14<0,"0",'Utility summery'!M14) -> 108.988 | H10: 2.165 | I10: =IF('UTILITY REPORT 1'!G11<0,"0",'UTILITY REPORT 1'!G11) -> 65 | J10: 0 | K10: =Submetering!X10 -> 10 | L10: =E10*F10+G10*H10+#REF!*#REF!+I10*J10 -> #REF!
A11: Serengeti | B11: =B10+1 -> 10 | C11: 12 | D11: 2021 | E11: ='UTILITY REPORT 1'!F12 -> 3440 | F11: =('UTILITY REPORT 1'!E12*'UTILITY REPORT 1'!D12)/'UTILITY REPORT 1'!F12 -> 0.3916657 | G11: =IF('Utility summery'!M15<0,"0",'Utility summery'!M15) -> 110 | H11: 2.165 | I11: =IF('UTILITY REPORT 1'!G12<0,"0",'UTILITY REPORT 1'!G12) -> 71 | J11: 0 | K11: =Submetering!X11 -> 12 | L11: =E11*F11+G11*H11+#REF!*#REF!+I11*J11 -> #REF!
A12: Serengeti | B12: =B11+1 -> 11 | C12: 12 | D12: 2021 | E12: ='UTILITY REPORT 1'!F13 -> 3696 | F12: =('UTILITY REPORT 1'!E13*'UTILITY REPORT 1'!D13)/'UTILITY REPORT 1'!F13 -> 0.40930465 | G12: =IF('Utility summery'!M16<0,"0",'Utility summery'!M16) -> 105.38 | H12: 2.165 | I12: =IF('UTILITY REPORT 1'!G13<0,"0",'UTILITY REPORT 1'!G13) -> 72 | J12: 0 | K12: =Submetering!X12 -> 12 | L12: =E12*F12+G12*H12+#REF!*#REF!+I12*J12 -> #REF!
A13: Serengeti | B13: =B12+1 -> 12 | C13: 12 | D13: 2021 | E13: ='UTILITY REPORT 1'!F14 -> 3646 | F13: =('UTILITY REPORT 1'!E14*'UTILITY REPORT 1'!D14)/'UTILITY REPORT 1'!F14 -> 0.40736149 | G13: =IF('Utility summery'!M17<0,"0",'Utility summery'!M17) -> 106.656 | H13: 2.165 | I13: =IF('UTILITY REPORT 1'!G14<0,"0",'UTILITY REPORT 1'!G14) -> 65 | J13: 0 | K13: =Submetering!X13 -> 12 | L13: =E13*F13+G13*H13+#REF!*#REF!+I13*J13 -> #REF!
A14: Serengeti | B14: =B13+1 -> 13 | C14: 12 | D14: 2021 | E14: ='UTILITY REPORT 1'!F15 -> 3967 | F14: =('UTILITY REPORT 1'!E15*'UTILITY REPORT 1'!D15)/'UTILITY REPORT 1'!F15 -> 0.39819259 | G14: =IF('Utility summery'!M18<0,"0",'Utility summery'!M18) -> 108.02 | H14: 2.165 | I14: =IF('UTILITY REPORT 1'!G15<0,"0",'UTILITY REPORT 1'!G15) -> 68 | J14: 0 | K14: =Submetering!X14 -> 15 | L14: =E14*F14+G14*H14+#REF!*#REF!+I14*J14 -> #REF!
... A30: Serengeti | B30: =B29+1 -> 29 | C30: 12 | D30: 2021 | E30: ='UTILITY REPORT 1'!F31 -> 4892 | F30: =('UTILITY REPORT 1'!E31*'UTILITY REPORT 1'!D31)/'UTILITY REPORT 1'!F31 -> 0.41699714 | G30: =IF('Utility summery'!M34<0,"0",'Utility summery'!M34) -> 135.388 | H30: 2.165 | I30: =IF('UTILITY REPORT 1'!G31<0,"0",'UTILITY REPORT 1'!G31) -> 111 | J30: 0 | K30: =Submetering!X30 -> 42 | L30: =E30*F30+G30*H30+#REF!*#REF!+I30*J30 -> #REF!
A31: Serengeti | B31: 30 | C31: 12 | D31: 2021 | E31: ='UTILITY REPORT 1'!F32 -> 4766 | F31: =('UTILITY REPORT 1'!E32*'UTILITY REPORT 1'!D32)/'UTILITY REPORT 1'!F32 -> 0.42798363 | G31: =IF('Utility summery'!M35<0,"0",'Utility summery'!M35) -> 157.3 | H31: 2.165 | I31: =IF('UTILITY REPORT 1'!G32<0,"0",'UTILITY REPORT 1'!G32) -> 102 | J31: 0 | K31: =Submetering!X31 -> 48 | L31: =E31*F31+G31*H31+#REF!*#REF!+I31*J31 -> #REF!
A32: Serengeti | B32: 31 | C32: 12 | D32: 2021 | E32: ='UTILITY REPORT 1'!F33 -> 4562 | F32: =('UTILITY REPORT 1'!E33*'UTILITY REPORT 1'!D33)/'UTILITY REPORT 1'!F33 -> 0.41520824 | G32: =IF('Utility summery'!M36<0,"0",'Utility summery'!M36) -> 163.02 | H32: 2.165 | I32: =IF('UTILITY REPORT 1'!G33<0,"0",'UTILITY REPORT 1'!G33) -> 102 | J32: 0 | K32: =Submetering!X32 -> 48

Sheet Energy Graph
A1: Date | B1: Usage KW | C1: Occ % | D1: Total Occ | E1: Guest Occ
A2: =Gen!B11 -> 44531 | B2: ='Summery Report'!F5 -> 3130 | C2: ='Summery Report'!C5 -> 0.0519 | D2: =E2 -> 6 | E2: =Total!K2 -> 6
A3: =Gen!B12 -> 44532 | B3: ='Summery Report'!F6 -> 3105 | C3: ='Summery Report'!C6 -> 0.05 | D3: =E3 -> 5 | E3: =Total!K3 -> 5
A4: =Gen!B13 -> 44533 | B4: ='Summery Report'!F7 -> 2910 | C4: ='Summery Report'!C7 -> 0.05 | D4: =E4 -> 3 | E4: =Total!K4 -> 3
A5: =Gen!B14 -> 44534 | B5: ='Summery Report'!F8 -> 3289 | C5: ='Summery Report'!C8 -> 0.08 | D5: =E5 -> 8 | E5: =Total!K5 -> 8
A6: =Gen!B15 -> 44535 | B6: ='Summery Report'!F9 -> 3146 | C6: ='Summery Report'!C9 -> 0.05 | D6: =E6 -> 6 | E6: =Total!K6 -> 6
A7: =Gen!B16 -> 44536 | B7: ='Summery Report'!F10 -> 3361 | C7: ='Summery Report'!C10 -> 0.0779 | D7: =E7 -> 9 | E7: =Total!K7 -> 9
A8: =Gen!B17 -> 44537 | B8: ='Summery Report'!F11 -> 3380 | C8: ='Summery Report'!C11 -> 0.0779 | D8: =E8 -> 9 | E8: =Total!K8 -> 9
A9: =Gen!B18 -> 44538 | B9: ='Summery Report'!F12 -> 3662 | C9: ='Summery Report'!C12 -> 0.12 | D9: =E9 -> 12 | E9: =Total!K9 -> 12
A10: =Gen!B19 -> 44539 | B10: ='Summery Report'!F13 -> 3399 | C10: ='Summery Report'!C13 -> 0.09 | D10: =E10 -> 10 | E10: =Total!K10 -> 10
A11: =Gen!B20 -> 44540 | B11: ='Summery Report'!F14 -> 3440 | C11: ='Summery Report'!C14 -> 0.12 | D11: =E11 -> 12 | E11: =Total!K11 -> 12
A12: =Gen!B21 -> 44541 | B12: ='Summery Report'!F15 -> 3696 | C12: ='Summery Report'!C15 -> 0.12 | D12: =E12 -> 12 | E12: =Total!K12 -> 12
A13: =Gen!B22 -> 44542 | B13: ='Summery Report'!F16 -> 3646 | C13: ='Summery Report'!C16 -> 0.12 | D13: =E13 -> 12 | E13: =Total!K13 -> 12
... A31: =Gen!B40 -> 44560 | B31: ='Summery Report'!F34 -> 4766 | C31: ='Summery Report'!C34 -> 0.61 | D31: =E31 -> 48 | E31: =Total!K31 -> 48
A32: =Gen!B41 -> 44561 | B32: ='Summery Report'!F35 -> 4562 | C32: ='Summery Report'!C35 -> 0.61 | D32: =E32 -> 48 | E32: =Total!K32 -> 48 | F32: 0.175
A33: =Gen!B42 -> 0 | B33: 0

Sheet UTILITY REPORT 1
A1: UTILITY REPORT
A2: Date | B2: % | C2: Guest Rooms Occupied | D2: Diesel cost Per Liter ($) | E2: Diesel consumption (LT) | F2: Power production (KW) | G2: Water consumption (M3) | H2: RO prodution (M3) | I2: Transport Consupmtion (LT)
A3: =Gen!B11 -> 44531 | B3: 0.0519 | C3: 6 | D3: 1 | E3: =Gen!T11 -> 1340.69 | F3: =Gen!U11 -> 3130 | G3: ='Water-Meter'!E6 -> 79 | H3: ='Utility report '!AC6 -> 35 | I3: =Gen!AK11 -> 55.31
A4: =Gen!B12 -> 44532 | B4: 0.05 | C4: 5 | D4: 1 | E4: =Gen!T12 -> 1268.81 | F4: =Gen!U12 -> 3105 | G4: ='Water-Meter'!E7 -> 67 | H4: ='Utility report '!AC7 -> 61 | I4: =Gen!AK12 -> 596.04
A5: =Gen!B13 -> 44533 | B5: =Gen!C13 -> 0.05 | C5: 3 | D5: 1 | E5: =Gen!T13 -> 1177.17 | F5: =Gen!U13 -> 2910 | G5: ='Water-Meter'!E8 -> 83 | H5: ='Utility report '!AC8 -> 50 | I5: =Gen!AK13 -> 0
A6: =Gen!B14 -> 44534 | B6: 0.08 | C6: 8 | D6: 1 | E6: =Gen!T14 -> 1293.22 | F6: =Gen!U14 -> 3289 | G6: ='Water-Meter'!E9 -> 67 | H6: ='Utility report '!AC9 -> 89 | I6: =Gen!AK14 -> 199.51
A7: =Gen!B15 -> 44535 | B7: 0.05 | C7: 6 | D7: 1 | E7: =Gen!T15 -> 1246.93 | F7: =Gen!U15 -> 3146 | G7: ='Water-Meter'!E10 -> 62 | H7: ='Utility report '!AC10 -> 103 | I7: =Gen!AK15 -> 53.33
A8: =Gen!B16 -> 44536 | B8: 0.0779 | C8: 9 | D8: 1 | E8: =Gen!T16 -> 1325.89 | F8: =Gen!U16 -> 3361 | G8: ='Water-Meter'!E11 -> 57 | H8: ='Utility report '!AC11 -> 17 | I8: =Gen!AK16 -> 67.4
A9: =Gen!B17 -> 44537 | B9: 0.0779 | C9: 9 | D9: 1 | E9: =Gen!T17 -> 1368.94 | F9: =Gen!U17 -> 3380 | G9: ='Water-Meter'!E12 -> 73 | H9: ='Utility report '!AC12 -> 121 | I9: =Gen!AK17 -> 135.94
A10: =Gen!B18 -> 44538 | B10: 0.12 | C10: 12 | D10: 1 | E10: =Gen!T18 -> 1527.6 | F10: =Gen!U18 -> 3662 | G10: ='Water-Meter'!E13 -> 80 | H10: ='Utility report '!AC13 -> 170 | I10: =Gen!AK18 -> 83.59
A11: =Gen!B19 -> 44539 | B11: 0.09 | C11: 10 | D11: 1 | E11: =Gen!T19 -> 1371.66 | F11: =Gen!U19 -> 3399 | G11: ='Water-Meter'!E14 -> 65 | H11: ='Utility report '!AC14 -> 0 | I11: =Gen!AK19 -> 51.98
A12: =Gen!B20 -> 44540 | B12: 0.12 | C12: 12 | D12: 1 | E12: =Gen!T20 -> 1347.33 | F12: =Gen!U20 -> 3440 | G12: ='Water-Meter'!E15 -> 71 | H12: ='Utility report '!AC15 -> 167 | I12: =Gen!AK20 -> 448.65
A13: =Gen!B21 -> 44541 | B13: 0.12 | C13: 12 | D13: 1 | E13: =Gen!T21 -> 1512.79 | F13: =Gen!U21 -> 3696 | G13: ='Water-Meter'!E16 -> 72 | H13: ='Utility report '!AC16 -> 15 | I13: =Gen!AK21 -> 37.87
A14: =Gen!B22 -> 44542 | B14: 0.12 | C14: 12 | D14: 1 | E14: =Gen!T22 -> 1485.24 | F14: =Gen!U22 -> 3646 | G14: ='Water-Meter'!E17 -> 65 | H14: ='Utility report '!AC17 -> 157 | I14: =Gen!AK22 -> 68.16
A15: =Gen!B23 -> 44543 | B15: 0.16 | C15: 15 | D15: 1 | E15: =Gen!T23 -> 1579.63 | F15: =Gen!U23 -> 3967 | G15: ='Water-Meter'!E18 -> 68 | H15: ='Utility report '!AC18 -> 44 | I15: =Gen!AK23 -> 103.25
A16: =Gen!B24 -> 44544 | B16: 0.17 | C16: 16 | D16: 1 | E16: =Gen!T24 -> 1342.22 | F16: =Gen!U24 -> 3411 | G16: ='Water-Meter'!E19 -> 78 | H16: ='Utility report '!AC19 -> 167 | I16: =Gen!AK24 -> 194.5
A17: =Gen!B25 -> 44545 | B17: 0.18 | C17: 17 | D17: 1 | E17: =Gen!T25 -> 1601.91 | F17: =Gen!U25 -> 3878 | G17: ='Water-Meter'!E20 -> 72 | H17: ='Utility report '!AC20 -> 104 | I17: =Gen!AK25 -> 0
... A33: =Gen!B41 -> 44561 | B33: 0.61 | C33: 48 | D33: 1 | E33: =Gen!T41 -> 1894.18 | F33: =Gen!U41 -> 4562 | G33: ='Water-Meter'!E36 -> 102 | H33: ='Utility report '!AC36 -> 156 | I33: =Gen!AK41 -> 882.87
B34: =Gen!C42 -> 0 | C34: ='Summery Report'!E36 -> 0 | D34: 2 | E34: =Gen!T42 -> 0 | F34: =Gen!U42 -> 0 | G34: ='Water-Meter'!E37 -> 120 | H34: ='Utility report '!AC37 -> -21907 | I34: =Gen!AL42 -> 0

Sheet Kit report
B1: KITCHEN THREE PHASE KWH METER READING | H1: KITCHEN WATER METER READING | M1: AMANI Restaurant WATER METER READING | T1: LAUNDRY THREE PHASE KWH METER READING | Y1: LAUNDRY WATER METER READING
A2: Occ % | B2: DATE | C2: READING TIME | D2: METER READING OPEN | E2: METER READING ClOSE | F2: UNIT USED Kwh | H2: DATE | I2: READING TIME | J2: METER READING OPEN Cbm | K2: METER READING ClOSE Cbm | L2: UNIT USED Cbm | M2: DATE | N2: READING TIME | O2: METER READING OPEN Cbm | P2: METER READING ClOSE Cbm | Q2: UNIT USED Cbm | R2: Cost Per day Elct+Water $ | S2: % as per the total Lodge consumption | T2: DATE | U2: READING TIME | V2: METER READING OPEN (Kwh) | W2: METER READING ClOSE (Kwh) | X2: UNIT USED Kwh | Y2: DATE | Z2: READING TIME | AA2: METER READING OPEN Cbm | AB2: METER READING ClOSE Cbm | AC2: UNIT USED Cbm
A3: =Gen!B11 -> 44531 | B3: Close Last Month | E3: 9756.7 | F3: X120 | H3: Close Last Month | J3: ='Water-Meter'!G5 -> 0 | K3: ='Water-Meter'!G5 -> 0 | M3: Close Last Month | P3: ='Water-Meter'!J5 -> 8871 | T3: Close Last Month | W3: 8710.3 | X3: =(W3-V3)*200 -> 1742060 | Y3: Close Last Month | AB3: ='Water-Meter'!P5 -> 22709
A4: =Gen!C11 -> 0.0519 | B4: =Gen!B11 -> 44531 | D4: =E3 -> 9756.7 | E4: 9756.7 | F4: =SUM(E5-D4)*120 -> 240 | H4: =B4 -> 44531 | J4: ='Water-Meter'!G6 -> 0 | K4: ='Water-Meter'!G6 -> 0 | L4: =SUM(K4-J4) -> 0 | M4: =H4 -> 44531 | P4: ='Water-Meter'!J6 -> 8872 | Q4: =N4-O3 -> 0 | R4: =SUM(Q4/1615) -> 0 | S4: =Gen!U11 -> 3130 | T4: =M4 -> 44531 | V4: =W3 -> 8710.3 | W4: 8710.3 | X4: =(W4-V4)*200 -> 0 | Y4: =T4 -> 44531 | AA4: =AB3 -> 22709 | AB4: ='Water-Meter'!P6 -> 22716 | AC4: =AB4-AA4 -> 7
A5: =Gen!C12 -> 0.05 | B5: =Gen!B12 -> 44532 | D5: =E5 -> 9758.7 | E5: 9758.7 | F5: =SUM(E6-D5)*120 -> 240 | H5: =B5 -> 44532 | J5: ='Water-Meter'!G7 -> 0 | K5: ='Water-Meter'!G7 -> 0 | L5: =SUM(K5-J5) -> 0 | M5: =H5 -> 44532 | P5: ='Water-Meter'!J7 -> 8874 | Q5: =N5-O4 -> 0 | R5: =SUM(Q5/1615) -> 0 | S5: =Gen!U12 -> 3105 | T5: =M5 -> 44532 | V5: =W4 -> 8710.3 | W5: 8712.5 | X5: =(W5-V5)*200 -> 440 | Y5: =T5 -> 44532 | AA5: =AB4 -> 22716 | AB5: ='Water-Meter'!P7 -> 22721 | AC5: =AB5-AA5 -> 5
A6: =Gen!C13 -> 0.05 | B6: =Gen!B13 -> 44533 | D6: =E6 -> 9760.7 | E6: 9760.7 | F6: =SUM(E7-D6)*120 -> 252 | H6: =B6 -> 44533 | J6: ='Water-Meter'!G8 -> 0 | K6: ='Water-Meter'!G8 -> 0 | L6: =SUM(K6-J6) -> 0 | M6: =H6 -> 44533 | P6: ='Water-Meter'!J8 -> 8876 | Q6: =N6-O5 -> 0 | R6: =SUM(Q6/1615) -> 0 | S6: =Gen!U13 -> 2910 | T6: =M6 -> 44533 | V6: =W5 -> 8712.5 | W6: 8714.1 | X6: =(W6-V6)*200 -> 320 | Y6: =T6 -> 44533 | AA6: =AB5 -> 22721 | AB6: ='Water-Meter'!P8 -> 22724 | AC6: =AB6-AA6 -> 3
A7: =Gen!C14 -> 0.08 | B7: =Gen!B14 -> 44534 | D7: =E7 -> 9762.8 | E7: 9762.8 | F7: =SUM(E8-D7)*120 -> 276 | H7: =B7 -> 44534 | J7: ='Water-Meter'!G9 -> 0 | K7: ='Water-Meter'!G9 -> 0 | L7: =SUM(K7-J7) -> 0 | M7: =H7 -> 44534 | P7: ='Water-Meter'!J9 -> 8889 | Q7: =N7-O6 -> 0 | R7: =SUM(Q7/1615) -> 0 | S7: =Gen!U14 -> 3289 | T7: =M7 -> 44534 | V7: =W6 -> 8714.1 | W7: 8715.8 | X7: =(W7-V7)*200 -> 340 | Y7: =T7 -> 44534 | AA7: =AB6 -> 22724 | AB7: ='Water-Meter'!P9 -> 22729 | AC7: =AB7-AA7 -> 5
A8: =Gen!C15 -> 0.05 | B8: =Gen!B15 -> 44535 | D8: =E8 -> 9765.1 | E8: 9765.1 | F8: =SUM(E9-D8)*120 -> 216 | H8: =B8 -> 44535 | J8: ='Water-Meter'!G10 -> 0 | K8: ='Water-Meter'!G10 -> 0 | L8: =SUM(K8-J8) -> 0 | M8: =H8 -> 44535 | P8: ='Water-Meter'!J10 -> 8895 | Q8: =N8-O7 -> 0 | R8: =SUM(Q8/1615) -> 0 | S8: =Gen!U15 -> 3146 | T8: =M8 -> 44535 | V8: =W7 -> 8715.8 | W8: 8717.3 | X8: =(W8-V8)*200 -> 300 | Y8: =T8 -> 44535 | AA8: =AB7 -> 22729 | AB8: ='Water-Meter'!P10 -> 22733 | AC8: =AB8-AA8 -> 4
A9: =Gen!C16 -> 0.0779 | B9: =Gen!B16 -> 44536 | D9: =E9 -> 9766.9 | E9: 9766.9 | F9: =SUM(E10-D9)*120 -> 228 | H9: =B9 -> 44536 | J9: ='Water-Meter'!G11 -> 0 | K9: ='Water-Meter'!G11 -> 0 | L9: =SUM(K9-J9) -> 0 | M9: =H9 -> 44536 | P9: ='Water-Meter'!J11 -> 8897 | Q9: =N9-O8 -> 0 | R9: =SUM(Q9/1615) -> 0 | S9: =Gen!U16 -> 3361 | T9: =M9 -> 44536 | V9: =W8 -> 8717.3 | W9: 8718.9 | X9: =(W9-V9)*200 -> 320 | Y9: =T9 -> 44536 | AA9: =AB8 -> 22733 | AB9: ='Water-Meter'!P11 -> 22738 | AC9: =AB9-AA9 -> 5
A10: =Gen!C17 -> 0.0779 | B10: =Gen!B17 -> 44537 | D10: =E10 -> 9768.8 | E10: 9768.8 | F10: =SUM(E11-D10)*120 -> 228 | H10: =B10 -> 44537 | J10: ='Water-Meter'!G12 -> 0 | K10: ='Water-Meter'!G12 -> 0 | L10: =SUM(K10-J10) -> 0 | M10: =H10 -> 44537 | P10: ='Water-Meter'!J12 -> 8900 | R10: =SUM(Q10/1615) -> 0 | S10: =Gen!U17 -> 3380 | T10: =M10 -> 44537 | V10: =W9 -> 8718.9 | W10: 8720.5 | X10: =(W10-V10)*200 -> 320 | Y10: =T10 -> 44537 | AA10: =AB9 -> 22738 | AB10: ='Water-Meter'!P12 -> 22745 | AC10: =AB10-AA10 -> 7
A11: =Gen!C18 -> 0.12 | B11: =Gen!B18 -> 44538 | D11: =E11 -> 9770.7 | E11: 9770.7 | F11: =SUM(E12-D11)*120 -> 240 | H11: =B11 -> 44538 | J11: ='Water-Meter'!G13 -> 0 | K11: ='Water-Meter'!G13 -> 0 | L11: =SUM(K11-J11) -> 0 | M11: =H11 -> 44538 | P11: ='Water-Meter'!J13 -> 8903 | Q11: =N11-O10 -> 0 | R11: =SUM(Q11/1615) -> 0 | S11: =Gen!U18 -> 3662 | T11: =M11 -> 44538 | V11: =W10 -> 8720.5 | W11: 8722.7 | X11: =(W11-V11)*200 -> 440 | Y11: =T11 -> 44538 | AA11: =AB10 -> 22745 | AB11: ='Water-Meter'!P13 -> 22751 | AC11: =AB11-AA11 -> 6
A12: =Gen!C19 -> 0.09 | B12: =Gen!B19 -> 44539 | D12: =E12 -> 9772.7 | E12: 9772.7 | F12: =SUM(E13-D12)*120 -> 240 | H12: =B12 -> 44539 | J12: ='Water-Meter'!G14 -> 0 | K12: ='Water-Meter'!G14 -> 0 | L12: =SUM(K12-J12) -> 0 | M12: =H12 -> 44539 | P12: ='Water-Meter'!J14 -> 8905 | Q12: =N12-O11 -> 0 | R12: =SUM(Q12/1615) -> 0 | S12: =Gen!U19 -> 3399 | T12: =M12 -> 44539 | V12: =W11 -> 8722.7 | W12: 8724.3 | X12: =(W12-V12)*200 -> 320 | Y12: =T12 -> 44539 | AA12: =AB11 -> 22751 | AB12: ='Water-Meter'!P14 -> 22754 | AC12: =AB12-AA12 -> 3
A13: =Gen!C20 -> 0.12 | B13: =Gen!B20 -> 44540 | D13: =E13 -> 9774.7 | E13: 9774.7 | F13: =SUM(E14-D13)*120 -> 252 | H13: =B13 -> 44540 | J13: ='Water-Meter'!G15 -> 0 | K13: ='Water-Meter'!G15 -> 0 | L13: =SUM(K13-J13) -> 0 | M13: =H13 -> 44540 | P13: ='Water-Meter'!J15 -> 8906 | Q13: =N13-O12 -> 0 | R13: =SUM(Q13/1615) -> 0 | S13: =Gen!U20 -> 3440 | T13: =M13 -> 44540 | V13: =W12 -> 8724.3 | W13: 8726.2 | X13: =(W13-V13)*200 -> 380 | Y13: =T13 -> 44540 | AA13: =AB12 -> 22754 | AB13: ='Water-Meter'!P15 -> 22760 | AC13: =AB13-AA13 -> 6
A14: =Gen!C21 -> 0.12 | B14: =Gen!B21 -> 44541 | D14: =E14 -> 9776.8 | E14: 9776.8 | F14: =SUM(E15-D14)*120 -> 228 | H14: =B14 -> 44541 | J14: ='Water-Meter'!G15 -> 0 | K14: ='Water-Meter'!G15 -> 0 | L14: =SUM(K14-J14) -> 0 | M14: =H14 -> 44541 | P14: ='Water-Meter'!J16 -> 8908 | Q14: =N14-O13 -> 0 | R14: =SUM(Q14/1615) -> 0 | S14: =Gen!U21 -> 3696 | T14: =M14 -> 44541 | V14: =W13 -> 8726.2 | W14: 8727.9 | X14: =(W14-V14)*200 -> 340 | Y14: =T14 -> 44541 | AA14: =AB13 -> 22760 | AB14: ='Water-Meter'!P16 -> 22764 | AC14: =AB14-AA14 -> 4
A15: =Gen!C22 -> 0.12 | B15: =Gen!B22 -> 44542 | D15: =E15 -> 9778.7 | E15: 9778.7 | F15: =SUM(E16-D15)*120 -> 264 | H15: =B15 -> 44542 | J15: ='Water-Meter'!G17 -> 0 | K15: ='Water-Meter'!G17 -> 0 | L15: =SUM(K15-J15) -> 0 | M15: =H15 -> 44542 | P15: ='Water-Meter'!J17 -> 8910 | Q15: =N15-O14 -> 0 | R15: =SUM(Q15/1615) -> 0 | S15: =Gen!U22 -> 3646 | T15: =M15 -> 44542 | V15: =W14 -> 8727.9 | W15: 8730.1 | X15: =(W15-V15)*200 -> 440 | Y15: =T15 -> 44542 | AA15: =AB14 -> 22764 | AB15: ='Water-Meter'!P17 -> 22769 | AC15: =AB15-AA15 -> 5
A16: =Gen!C23 -> 0.16 | B16: =Gen!B23 -> 44543 | D16: =E16 -> 9780.9 | E16: 9780.9 | F16: =SUM(E17-D16)*120 -> 276 | H16: =B16 -> 44543 | J16: ='Water-Meter'!G18 -> 0 | K16: ='Water-Meter'!G18 -> 0 | L16: =SUM(K16-J16) -> 0 | M16: =H16 -> 44543 | P16: ='Water-Meter'!J18 -> 8913 | Q16: =N16-O15 -> 0 | R16: =SUM(Q16/1615) -> 0 | S16: =Gen!U23 -> 3967 | T16: =M16 -> 44543 | V16: =W15 -> 8730.1 | W16: 8732.9 | X16: =(W16-V16)*200 -> 560 | Y16: =T16 -> 44543 | AA16: =AB15 -> 22769 | AB16: ='Water-Meter'!P18 -> 22776 | AC16: =AB16-AA16 -> 7
A17: =Gen!C24 -> 0.17 | B17: =Gen!B24 -> 44544 | D17: =E17 -> 9783.2 | E17: 9783.2 | F17: =SUM(E18-D17)*120 -> 252 | H17: =B17 -> 44544 | J17: ='Water-Meter'!G19 -> 0 | K17: ='Water-Meter'!G19 -> 0 | L17: =SUM(K17-J17) -> 0 | M17: =H17 -> 44544 | P17: ='Water-Meter'!J19 -> 8916 | Q17: =N17-O16 -> 0 | R17: =SUM(Q17/1615) -> 0 | S17: =Gen!U24 -> 3411 | T17: =M17 -> 44544 | V17: =W16 -> 8732.9 | W17: 8735.1 | X17: =(W17-V17)*200 -> 440 | Y17: =T17 -> 44544 | AA17: =AB16 -> 22776 | AB17: ='Water-Meter'!P19 -> 22784 | AC17: =AB17-AA17 -> 8
A18: =Gen!C25 -> 0.18 | B18: =Gen!B25 -> 44545 | D18: =E18 -> 9785.3 | E18: 9785.3 | F18: =SUM(E19-D18)*120 -> 240 | H18: =B18 -> 44545 | J18: ='Water-Meter'!G20 -> 0 | K18: ='Water-Meter'!G20 -> 0 | L18: =SUM(K18-J18) -> 0 | M18: =H18 -> 44545 | P18: ='Water-Meter'!J20 -> 8918 | Q18: =N18-O17 -> 0 | R18: =SUM(Q18/1615) -> 0 | S18: =Gen!U25 -> 3878 | T18: =M18 -> 44545 | V18: =W17 -> 8735.1 | W18: 8736.9 | X18: =(W18-V18)*200 -> 360 | Y18: =T18 -> 44545 | AA18: =AB17 -> 22784 | AB18: ='Water-Meter'!P20 -> 22789 | AC18: =AB18-AA18 -> 5
A19: =Gen!C26 -> 0.16 | B19: =Gen!B26 -> 44546 | D19: =E19 -> 9787.3 | E19: 9787.3 | F19: =SUM(E20-D19)*120 -> 264 | H19: =B19 -> 44546 | J19: ='Water-Meter'!G21 -> 0 | K19: ='Water-Meter'!G21 -> 0 | L19: =SUM(K19-J19) -> 0 | M19: =H19 -> 44546 | P19: ='Water-Meter'!J21 -> 8920 | Q19: =N19-O18 -> 0 | R19: =SUM(Q19/1615) -> 0 | S19: =Gen!U26 -> 3906 | T19: =M19 -> 44546 | V19: =W18 -> 8736.9 | W19: 8739.5 | X19: =(W19-V19)*200 -> 520 | Y19: =T19 -> 44546 | AA19: =AB18 -> 22789 | AB19: ='Water-Meter'!P21 -> 22794 | AC19: =AB19-AA19 -> 5
A20: =Gen!C27 -> 0.16 | B20: =Gen!B27 -> 44547 | D20: =E20 -> 9789.5 | E20: 9789.5 | F20: =SUM(E21-D20)*120 -> 264 | H20: =B20 -> 44547 | J20: ='Water-Meter'!G22 -> 0 | K20: ='Water-Meter'!G22 -> 0 | L20: =SUM(K20-J20) -> 0 | M20: =H20 -> 44547 | P20: ='Water-Meter'!J22 -> 8922 | Q20: =N20-O19 -> 0 | R20: =SUM(Q20/1615) -> 0 | S20: =Gen!U27 -> 3764 | T20: =M20 -> 44547 | V20: =W19 -> 8739.5 | W20: 8741.7 | X20: =(W20-V20)*200 -> 440 | Y20: =T20 -> 44547 | AA20: =AB19 -> 22794 | AB20: ='Water-Meter'!P22 -> 22798 | AC20: =AB20-AA20 -> 4
A21: =Gen!C28 -> 0.13 | B21: =Gen!B28 -> 44548 | D21: =E21 -> 9791.7 | E21: 9791.7 | F21: =SUM(E22-D21)*120 -> 264 | H21: =B21 -> 44548 | J21: ='Water-Meter'!G23 -> 0 | K21: ='Water-Meter'!G23 -> 0 | L21: =SUM(K21-J21) -> 0 | M21: =H21 -> 44548 | P21: ='Water-Meter'!J23 -> 8925 | Q21: =N21-O20 -> 0 | R21: =SUM(Q21/1615) -> 0 | S21: =Gen!U28 -> 3882 | T21: =M21 -> 44548 | V21: =W20 -> 8741.7 | W21: 8744 | X21: =(W21-V21)*200 -> 460 | Y21: =T21 -> 44548 | AA21: =AB20 -> 22798 | AB21: ='Water-Meter'!P23 -> 22806 | AC21: =AB21-AA21 -> 8
A22: =Gen!C29 -> 0.12 | B22: =Gen!B29 -> 44549 | D22: =E22 -> 9793.9 | E22: 9793.9 | F22: =SUM(E23-D22)*120 -> 216 | H22: =B22 -> 44549 | K22: ='Water-Meter'!G24 -> 0 | L22: =SUM(K22-J22) -> 0 | M22: =H22 -> 44549 | P22: ='Water-Meter'!J24 -> 8928 | Q22: =N22-O21 -> 0 | R22: =SUM(Q22/1615) -> 0 | S22: =Gen!U29 -> 3745 | T22: =M22 -> 44549 | V22: =W21 -> 8744 | W22: 8746.7 | X22: =(W22-V22)*200 -> 540 | Y22: =T22 -> 44549 | AA22: =AB21 -> 22806 | AB22: ='Water-Meter'!P24 -> 22812 | AC22: =AB22-AA22 -> 6
A23: =Gen!C30 -> 0.06 | B23: =Gen!B30 -> 44550 | D23: =E23 -> 9795.7 | E23: 9795.7 | F23: =SUM(E24-D23)*120 -> 228 | H23: =B23 -> 44550 | J23: ='Water-Meter'!G25 -> 0 | K23: ='Water-Meter'!G26 -> 0 | L23: =SUM(K23-J23) -> 0 | M23: =H23 -> 44550 | P23: ='Water-Meter'!J25 -> 8930 | Q23: =N23-O22 -> 0 | R23: =SUM(Q23/1615) -> 0 | S23: =Gen!U30 -> 3257 | T23: =M23 -> 44550 | V23: =W22 -> 8746.7 | W23: 8749.7 | X23: =(W23-V23)*200 -> 600 | Y23: =T23 -> 44550 | AA23: =AB22 -> 22812 | AB23: ='Water-Meter'!P25 -> 22817 | AC23: =AB23-AA23 -> 5
A24: =Gen!C31 -> 0.1 | B24: =Gen!B31 -> 44551 | D24: =E24 -> 9797.6 | E24: 9797.6 | F24: =SUM(E25-D24)*120 -> 252 | H24: =B24 -> 44551 | J24: ='Water-Meter'!G26 -> 0 | K24: ='Water-Meter'!G27 -> 0 | L24: =SUM(K24-J24) -> 0 | M24: =H24 -> 44551 | P24: ='Water-Meter'!J26 -> 8932 | Q24: =N24-O23 -> 0 | R24: =SUM(Q24/1615) -> 0 | S24: =Gen!U31 -> 4495 | T24: =M24 -> 44551 | V24: =W23 -> 8749.7 | W24: 8752.7 | X24: =(W24-V24)*200 -> 600 | Y24: =T24 -> 44551 | AA24: =AB23 -> 22817 | AB24: ='Water-Meter'!P26 -> 22822 | AC24: =AB24-AA24 -> 5
A25: =Gen!C32 -> 0.17 | B25: =Gen!B32 -> 44552 | D25: =E25 -> 9799.7 | E25: 9799.7 | F25: =SUM(E26-D25)*120 -> 264 | H25: =B25 -> 44552 | J25: ='Water-Meter'!G27 -> 0 | K25: ='Water-Meter'!G28 -> 0 | L25: =SUM(K25-J25) -> 0 | M25: =H25 -> 44552 | P25: ='Water-Meter'!J27 -> 8936 | Q25: =N25-O24 -> 0 | R25: =SUM(Q25/1615) -> 0 | S25: =Gen!U32 -> 3996 | T25: =M25 -> 44552 | V25: =W24 -> 8752.7 | W25: 8755.6 | X25: =(W25-V25)*200 -> 580 | Y25: =T25 -> 44552 | AA25: =AB24 -> 22822 | AB25: ='Water-Meter'!P27 -> 22829 | AC25: =AB25-AA25 -> 7
A26: =Gen!C33 -> 0.17 | B26: =Gen!B33 -> 44553 | D26: =E26 -> 9801.9 | E26: 9801.9 | F26: =SUM(E27-D26)*120 -> 240 | H26: =B26 -> 44553 | J26: ='Water-Meter'!G28 -> 0 | K26: ='Water-Meter'!G29 -> 0 | L26: =SUM(K26-J26) -> 0 | M26: =H26 -> 44553 | P26: ='Water-Meter'!J28 -> 8938 | Q26: =N26-O25 -> 0 | R26: =SUM(Q26/1615) -> 0 | S26: =Gen!U33 -> 4192 | T26: =M26 -> 44553 | V26: =W25 -> 8755.6 | W26: 8758.7 | X26: =(W26-V26)*200 -> 620 | Y26: =T26 -> 44553 | AA26: =AB25 -> 22829 | AB26: ='Water-Meter'!P28 -> 22839 | AC26: =AB26-AA26 -> 10
A27: =Gen!C34 -> 0.47 | B27: =Gen!B34 -> 44554 | D27: =E27 -> 9803.9 | E27: 9803.9 | F27: =SUM(E28-D27)*120 -> 276 | H27: =B27 -> 44554 | J27: ='Water-Meter'!G29 -> 0 | K27: ='Water-Meter'!G30 -> 0 | L27: =SUM(K27-J27) -> 0 | M27: =H27 -> 44554 | P27: ='Water-Meter'!J29 -> 8941 | Q27: =N27-O26 -> 0 | R27: =SUM(Q27/1615) -> 0 | S27: =Gen!U34 -> 4947 | T27: =M27 -> 44554 | V27: =W26 -> 8758.7 | W27: 8762.7 | X27: =(W27-V27)*200 -> 800 | Y27: =T27 -> 44554 | AA27: =AB26 -> 22839 | AB27: ='Water-Meter'!P29 -> 22848 | AC27: =AB27-AA27 -> 9
A28: =Gen!C35 -> 0.58 | B28: =Gen!B35 -> 44555 | D28: =E28 -> 9806.2 | E28: 9806.2 | F28: =SUM(E29-D28)*120 -> 300 | H28: =B28 -> 44555 | J28: ='Water-Meter'!G30 -> 0 | K28: ='Water-Meter'!G31 -> 0 | L28: =SUM(K28-J28) -> 0 | M28: =H28 -> 44555 | P28: ='Water-Meter'!J30 -> 8944 | Q28: =N28-O27 -> 0 | R28: =SUM(Q28/1615) -> 0 | S28: =Gen!U35 -> 4917 | T28: =M28 -> 44555 | V28: =W27 -> 8762.7 | W28: 8765.6 | X28: =(W28-V28)*200 -> 580 | Y28: =T28 -> 44555 | AA28: =AB27 -> 22848 | AB28: ='Water-Meter'!P30 -> 22861 | AC28: =AB28-AA28 -> 13
A29: =Gen!C36 -> 0.43 | B29: =Gen!B36 -> 44556 | D29: =E29 -> 9808.7 | E29: 9808.7 | F29: =SUM(E30-D29)*120 -> 264 | H29: =B29 -> 44556 | J29: ='Water-Meter'!G31 -> 0 | K29: ='Water-Meter'!G32 -> 0 | L29: =SUM(K29-J29) -> 0 | M29: =H29 -> 44556 | P29: ='Water-Meter'!J31 -> 8947 | Q29: =N29-O28 -> 0 | R29: =SUM(Q29/1615) -> 0 | S29: =Gen!U36 -> 4944 | T29: =M29 -> 44556 | V29: =W28 -> 8765.6 | W29: 8769.5 | X29: =(W29-V29)*200 -> 780 | Y29: =T29 -> 44556 | AA29: =AB28 -> 22861 | AB29: ='Water-Meter'!P31 -> 22873 | AC29: =AB29-AA29 -> 12
A30: =Gen!C37 -> 0.39 | B30: =Gen!B37 -> 44557 | D30: =E30 -> 9810.9 | E30: 9810.9 | F30: =SUM(E31-D30)*120 -> 276 | H30: =B30 -> 44557 | J30: ='Water-Meter'!G32 -> 0 | K30: ='Water-Meter'!G33 -> 0 | L30: =SUM(K30-J30) -> 0 | M30: =H30 -> 44557 | P30: ='Water-Meter'!J32 -> 8951 | Q30: =N30-O29 -> 0 | R30: =SUM(Q30/1615) -> 0 | S30: =Gen!U37 -> 5000 | T30: =M30 -> 44557 | V30: =W29 -> 8769.5 | W30: 8774.3 | X30: =(W30-V30)*200 -> 960 | Y30: =T30 -> 44557 | AA30: =AB29 -> 22873 | AB30: ='Water-Meter'!P32 -> 22886 | AC30: =AB30-AA30 -> 13
A31: =Gen!C38 -> 0.43 | B31: =Gen!B38 -> 44558 | D31: =E31 -> 9813.2 | E31: 9813.2 | F31: =SUM(E32-D31)*120 -> 204 | H31: =B31 -> 44558 | J31: ='Water-Meter'!G33 -> 0 | K31: ='Water-Meter'!G34 -> 0 | L31: =SUM(K31-J31) -> 0 | M31: =H31 -> 44558 | P31: ='Water-Meter'!J33 -> 8954 | Q31: =N31-O30 -> 0 | R31: =SUM(Q31/1615) -> 0 | S31: =Gen!U38 -> 4676 | T31: =M31 -> 44558 | V31: =W30 -> 8774.3 | W31: 8778.5 | X31: =(W31-V31)*200 -> 840 | Y31: =T31 -> 44558 | AA31: =AB30 -> 22886 | AB31: ='Water-Meter'!P33 -> 22895 | AC31: =AB31-AA31 -> 9
A32: =Gen!C39 -> 0.53 | B32: =Gen!B39 -> 44559 | D32: =E32 -> 9814.9 | E32: 9814.9 | F32: =SUM(E33-D32)*120 -> 180 | H32: =B32 -> 44559 | J32: ='Water-Meter'!G34 -> 0 | K32: ='Water-Meter'!G34 -> 0 | L32: =SUM(K32-J32) -> 0 | M32: =H32 -> 44559 | P32: ='Water-Meter'!J34 -> 8959 | Q32: =N32-O31 -> 0 | R32: =SUM(Q32/1615) -> 0 | S32: =Gen!U39 -> 4892 | T32: =M32 -> 44559 | V32: =W31 -> 8778.5 | W32: 8782.7 | X32: =(W32-V32)*200 -> 840 | Y32: =T32 -> 44559 | AA32: =AB31 -> 22895 | AB32: ='Water-Meter'!P34 -> 22909 | AC32: =AB32-AA32 -> 14
A33: =Gen!C40 -> 0.61 | B33: =Gen!B40 -> 44560 | D33: =E33 -> 9816.4 | E33: 9816.4 | F33: =SUM(E34-D33)*120 -> 216 | H33: =B33 -> 44560 | J33: ='Water-Meter'!G35 -> 0 | K33: ='Water-Meter'!G35 -> 0 | L33: =SUM(K33-J33) -> 0 | M33: =H33 -> 44560 | P33: ='Water-Meter'!J35 -> 8962 | Q33: =N33-O32 -> 0 | R33: =SUM(Q33/1615) -> 0 | S33: =Gen!U40 -> 4766 | T33: =M33 -> 44560 | V33: =W32 -> 8782.7 | W33: 8787.2 | X33: =(W33-V33)*200 -> 900 | Y33: =T33 -> 44560 | AA33: =AB32 -> 22909 | AB33: ='Water-Meter'!P35 -> 22919 | AC33: =AB33-AA33 -> 10
A34: =Gen!C41 -> 0.61 | B34: =Gen!B41 -> 44561 | D34: =E34 -> 9818.2 | E34: 9818.2 | F34: =SUM(E35-D34)*120 -> 264 | H34: =E30 -> 9810.9 | J34: ='Water-Meter'!G36 -> 0 | K34: ='Water-Meter'!G36 -> 0 | L34: =SUM(K34-J34) -> 0 | M34: =H34 -> 9810.9 | P34: ='Water-Meter'!J36 -> 8965 | Q34: =N34-O33 -> 0 | R34: =SUM(Q34/1615) -> 0 | S34: =Gen!U41 -> 4562 | T34: =M34 -> 9810.9 | V34: =SUM(W33) -> 8787.2 | W34: 8791.2 | X34: =(W34-V34)*200 -> 800 | Y34: =T34 -> 9810.9 | AA34: =AB33 -> 22919 | AB34: ='Water-Meter'!P36 -> 22928 | AC34: =AA34-AB33 -> 0
A35: #REF! | B35: #REF! | D35: =E35 -> 9820.4 | E35: 9820.4 | F35: =SUM(E36-D35)*120 -> -1178448 | H35: =B35 -> #REF! | J35: =SUM(K34) -> 0 | K35: ='Water-Meter'!G37 -> 0 | L35: =SUM(L5:L34) -> 0 | M35: =H35 -> #REF! | P35: ='Water-Meter'!J37 -> 0 | Q35: =N35-O34 -> 0 | R35: =SUM(Q35/1615) -> 0 | S35: =Gen!U42 -> 0 | T35: =M35 -> #REF! | V35: =SUM(W34) -> 8791.2 | W35: 8794.9 | X35: =(W35-V35)*200 -> 740 | Y35: =T35 -> #REF! | AB35: ='Water-Meter'!P37 -> 0 | AC35: =AA35-AB34 -> -22928
F36: =SUM(E37-D36)*120 -> 0 | X36: =SUM(X4:X6) -> 760

Sheet Utility report 
A1: =A6 -> 44531
A2: Date | B2: Total occupancy | H2: Diesel balance LTS | I2: Diesel Deliveries | J2: Gen.Diesel consumption LTS | L2: Total Diesel consumption LTS | M2: Water Meter reading | N2: Water consumption m³ | O2: R.O WATER PRODUCTION LTRS + TIME | AA2: Total RO production | AB2: RO Meter reading | AD2: 0 | AE2: STP | AF2: GAS TANK A | AG2: GAS TANK B | AH2: GAS TANK C | AI2: Total Gas Tanks | AJ2: Kg /day | AK2: TOTAL GAS cons.
A3: Rate Tsh /$ | B3: 1640 | C3: Diesel cost / lits | D3: 2175 | F3: =SUM(D3/B3) -> 1.3262195 | H3: =Gen!D11 -> 43219.56 | K3: Transport consumption | M3: Balance | O3: PLANT NO 1 | S3: PLANT NO 2 | W3: PLANT NO 3 | AA3: /day | AB3: Balance | AD3: 0 | AE3: Production | AF3: Capacity | AG3: Capacity | AH3: Capacity | AI3: Kg | AJ3: /day | AK3: /day
B4: Rooms OCC | C4: % | D4: Guest Rooms Occ | F4: Electricity Production Cost /Room Occ by guest | G4: All Cost /Room Occ by guest | O4: Flow M3 | P4: Reading Hours Meter | Q4: Hrs | R4: total production M3 | S4: Flow M3 | T4: Reading Hours Meter | U4: Hrs | V4: total production M3 | W4: Flow M3 | X4: READING HOURS METER | Y4: Hrs | Z4: total production M3 | AA4: M3 | AC4: M3 | AE4: M3 | AF4: 2000 | AG4: 1000 | AH4: 1000 | AI4: #VALUE! | AJ4: Kg | AK4: M3
P5: 19136 | T5: 20105 | X5: 29498 | AB5: 19032 | AD5: 226990 | AF5: 0.85 | AG5: 0.85 | AH5: 0.85
A6: =Gen!B11 -> 44531 | B6: ='Summery Report'!E5 -> 6 | C6: =Gen!C11 -> 0.0519 | D6: ='Summery Report'!E5 -> 6 | E6: =SUM(F3) -> 1.3262195 | F6: =SUM(J6*E6)/D6 -> 691.84451 | G6: =SUM(L6*E6)/D6 -> 691.84451 | H6: =Gen!D11 -> 43219.56 | I6: =Gen!F11 -> 0 | J6: =Gen!U11 -> 3130 | K6: =Gen!AL11 -> 0 | L6: =SUM(J6:K6) -> 3130 | M6: ='Water-Meter'!K46 -> 579.88445 | N6: ='Water-Meter'!E6 -> 79 | P6: 19136 | Q6: =SUM(P6-P5) -> 0 | R6: =SUM(Q6*O6) -> 0 | S6: 7 | T6: 20110 | U6: =T6-T5 -> 5 | V6: =SUM(U6*S7) -> 35 | X6: 29498 | Y6: =X6-X5 -> 0 | Z6: =Y6-Y5 -> 0 | AA6: =Z6-Z5 -> 0 | AB6: 19067 | AC6: =AB6-AB5 -> 35 | AD6: 227063 | AE6: =AD6-AD5 -> 73 | AF6: ='Lpg (2)'!B10*2000/85 -> 2000 | AG6: ='Lpg (2)'!C10*1000/85 -> 988.23529 | AH6: ='Lpg (2)'!D10*1000/85 -> 0 | AI6: =SUM(AF6*2000)+(AG6*1000)+(AH6*1000) -> 4988235.3 | AJ6: =SUM(AI5-AI6) -> -4988235.3
A7: =Gen!B12 -> 44532 | B7: ='Summery Report'!E6 -> 5 | C7: =Gen!C12 -> 0.05 | D7: ='Summery Report'!E6 -> 5 | E7: =SUM(E6) -> 1.3262195 | F7: =SUM(J7*E7)/D7 -> 823.58232 | G7: =SUM(L7*E7)/D7 -> 823.58232 | H7: =Gen!D12 -> 41823.56 | I7: =Gen!F12 -> 0 | J7: =Gen!U12 -> 3105 | K7: =Gen!AL12 -> 0 | L7: =SUM(J7:K7) -> 3105 | M7: ='Water-Meter'!K47 -> 574.08186 | N7: ='Water-Meter'!E7 -> 67 | P7: 19136 | Q7: =SUM(P7-P6) -> 0 | R7: =SUM(Q7*O7) -> 0 | S7: 7 | T7: 20119 | U7: =T7-T6 -> 9 | V7: =SUM(U7*S8) -> 63 | X7: 29498 | Y7: =X7-X6 -> 0 | Z7: =SUM(Y7*W7) -> 0 | AA7: =SUM(Z7*X9) -> 0 | AB7: 19128 | AC7: =AB7-AB6 -> 61 | AD7: 227132 | AE7: =AD7-AD6 -> 69 | AF7: ='Lpg (2)'!B11*2000/85 -> 2000 | AG7: ='Lpg (2)'!C11*1000/85 -> 941.17647 | AH7: ='Lpg (2)'!D11*1000/85 -> 0 | AI7: =SUM(AF6*2000)+(AG7*1000)+(AH7*1000) -> 4941176.5 | AJ7: =SUM(AI6-AI7) -> 47058.824
A8: =Gen!B13 -> 44533 | B8: ='Summery Report'!E7 -> 3 | C8: =Gen!C13 -> 0.05 | D8: ='Summery Report'!E7 -> 3 | E8: =SUM(E7) -> 1.3262195 | F8: =SUM(J8*E8)/D8 -> 1286.4329 | G8: =SUM(L8*E8)/D8 -> 1286.4329 | H8: =Gen!D13 -> 39958.71 | I8: =Gen!F13 -> 0 | J8: =Gen!U13 -> 2910 | K8: =Gen!AL13 -> 0 | L8: =SUM(J8:K8) -> 2910 | M8: ='Water-Meter'!K48 -> 554.48732 | N8: ='Water-Meter'!E8 -> 83 | P8: 19136 | Q8: =SUM(P8-P7) -> 0 | R8: =SUM(Q8*O8) -> 0 | S8: 7 | T8: 20126 | U8: =T8-T7 -> 7 | V8: =SUM(U8*S9) -> 49 | X8: 29498 | Y8: =X8-X7 -> 0 | Z8: =SUM(Y8*W8) -> 0 | AA8: =SUM(Z8*X10) -> 0 | AB8: 19178 | AC8: =AB8-AB7 -> 50 | AD8: 227202 | AE8: =AD8-AD7 -> 70 | AF8: ='Lpg (2)'!B12*2000/85 -> 2000 | AG8: ='Lpg (2)'!C12*1000/85 -> 870.58824 | AH8: ='Lpg (2)'!D12*1000/85 -> 0 | AI8: =SUM(AF7*2000)+(AG8*1000)+(AH8*1000) -> 4870588.2 | AJ8: =SUM(AI7-AI8) -> 70588.235
A9: =Gen!B14 -> 44534 | B9: ='Summery Report'!E8 -> 8 | C9: =Gen!C14 -> 0.08 | D9: ='Summery Report'!E8 -> 8 | E9: =SUM(E8) -> 1.3262195 | F9: =SUM(J9*E9)/D9 -> 545.242 | G9: =SUM(L9*E9)/D9 -> 545.242 | H9: =Gen!D14 -> 38781.54 | I9: =Gen!F14 -> 0 | J9: =Gen!U14 -> 3289 | K9: =Gen!AL14 -> 0 | L9: =SUM(J9:K9) -> 3289 | M9: ='Water-Meter'!K49 -> 534.16708 | N9: ='Water-Meter'!E9 -> 67 | P9: 19136 | Q9: =SUM(P9-P7) -> 0 | R9: =SUM(Q9*O9) -> 0 | S9: 7 | T9: 20138 | U9: =T9-T8 -> 12 | V9: =SUM(U9*S10) -> 84 | X9: 29498 | Y9: =X9-X8 -> 0 | Z9: =SUM(Y9*W11) -> 0 | AA9: =SUM(Z9*X11) -> 0 | AB9: 19267 | AC9: =AB9-AB8 -> 89 | AD9: 227265 | AE9: =AD9-AD8 -> 63 | AF9: ='Lpg (2)'!B13*2000/85 -> 2000 | AG9: ='Lpg (2)'!C13*1000/85 -> 764.70588 | AH9: ='Lpg (2)'!D13*1000/85 -> 0 | AI9: =SUM(AF8*2000)+(AG9*1000)+(AH9*1000) -> 4764705.9 | AJ9: =SUM(AI8-AI9) -> 105882.35
A10: =Gen!B15 -> 44535 | B10: ='Summery Report'!E9 -> 6 | C10: =Gen!C15 -> 0.05 | D10: ='Summery Report'!E9 -> 6 | E10: =SUM(E9) -> 1.3262195 | F10: =SUM(J10*E10)/D10 -> 695.3811 | G10: =SUM(L10*E10)/D10 -> 695.3811 | H10: =Gen!D15 -> 37288.81 | I10: =Gen!F15 -> 0 | J10: =Gen!U15 -> 3146 | K10: =Gen!AL15 -> 0 | L10: =SUM(J10:K10) -> 3146 | M10: ='Water-Meter'!K50 -> 517.28554 | N10: ='Water-Meter'!E10 -> 62 | P10: 19136 | Q10: =SUM(P10-P9) -> 0 | R10: =SUM(Q10*O10) -> 0 | S10: 7 | T10: 20154 | U10: =T10-T9 -> 16 | V10: =SUM(U10*S11) -> 112 | X10: 29498 | Y10: =X10-X9 -> 0 | Z10: =SUM(Y10*W10) -> 0 | AA10: =SUM(Z10*X12) -> 0 | AB10: 19370 | AC10: =AB10-AB9 -> 103 | AD10: 227312 | AE10: =AD10-AD9 -> 47 | AF10: ='Lpg (2)'!B14*2000/85 -> 2000 | AG10: ='Lpg (2)'!C14*1000/85 -> 647.05882 | AH10: ='Lpg (2)'!D14*1000/85 -> 0 | AI10: =SUM(AF9*2000)+(AG10*1000)+(AH10*1000) -> 4647058.8 | AJ10: =SUM(AI9-AI10) -> 117647.06
A11: =Gen!B16 -> 44536 | B11: ='Summery Report'!E10 -> 9 | C11: =Gen!C16 -> 0.0779 | D11: ='Summery Report'!E10 -> 9 | E11: =SUM(E10) -> 1.3262195 | F11: =SUM(J11*E11)/D11 -> 495.26931 | G11: =SUM(L11*E11)/D11 -> 495.26931 | H11: =Gen!D16 -> 35988.55 | I11: =Gen!F16 -> 0 | J11: =Gen!U16 -> 3361 | K11: =Gen!AL16 -> 0 | L11: =SUM(J11:K11) -> 3361 | M11: ='Water-Meter'!K51 -> 521.78639 | N11: ='Water-Meter'!E11 -> 57 | P11: 19136 | Q11: =SUM(P11-P10) -> 0 | R11: =SUM(Q11*O11) -> 0 | S11: 7 | T11: 20158 | U11: =T11-T10 -> 4 | V11: =SUM(U11*S12) -> 27.2 | X11: 29498 | Y11: =X11-X10 -> 0 | Z11: =SUM(Y11*W11) -> 0 | AA11: =SUM(Z11*X13) -> 0 | AB11: 19387 | AC11: =AB11-AB10 -> 17 | AD11: 227365 | AE11: =AD11-AD10 -> 53 | AF11: ='Lpg (2)'!B15*2000/85 -> 2000 | AG11: ='Lpg (2)'!C15*1000/85 -> 588.23529 | AH11: ='Lpg (2)'!D15*1000/85 -> 0 | AI11: =SUM(AF10*2000)+(AG11*1000)+(AH11*1000) -> 4588235.3 | AJ11: =SUM(AI10-AI11) -> 58823.529
A12: =Gen!B17 -> 44537 | B12: ='Summery Report'!E11 -> 9 | C12: =Gen!C17 -> 0.0779 | D12: ='Summery Report'!E11 -> 9 | E12: =SUM(E11) -> 1.3262195 | F12: =SUM(J12*E12)/D12 -> 498.06911 | G12: =SUM(L12*E12)/D12 -> 498.06911 | H12: =Gen!D17 -> 34595.26 | I12: =Gen!F17 -> 18000 | J12: =Gen!U17 -> 3380 | K12: =Gen!AL17 -> 0 | L12: =SUM(J12:K12) -> 3380 | M12: ='Water-Meter'!K52 -> 440.4761 | N12: ='Water-Meter'!E12 -> 73 | P12: 19136 | Q12: =SUM(P12-P11) -> 0 | R12: =SUM(Q12*O12) -> 0 | S12: 6.8 | T12: 20174 | U12: =T12-T11 -> 16 | V12: =SUM(U12*S12) -> 108.8 | X12: 29498 | Y12: =X12-X11 -> 0 | Z12: =SUM(Y12*W12) -> 0 | AA12: =SUM(Z12*X14) -> 0 | AB12: 19508 | AC12: =AB12-AB11 -> 121 | AD12: 227415 | AE12: =AD12-AD11 -> 50 | AF12: ='Lpg (2)'!B16*2000/85 -> 2000 | AG12: ='Lpg (2)'!C16*1000/85 -> 529.41176 | AH12: ='Lpg (2)'!D16*1000/85 -> 0 | AI12: =SUM(AF11*2000)+(AG12*1000)+(AH12*1000) -> 4529411.8 | AJ12: =SUM(AI11-AI12) -> 58823.529
A13: =Gen!B18 -> 44538 | B13: ='Summery Report'!E12 -> 12 | C13: =Gen!C18 -> 0.12 | D13: ='Summery Report'!E12 -> 12 | E13: =SUM(E12) -> 1.3262195 | F13: =SUM(J13*E13)/D13 -> 404.71799 | G13: =SUM(L13*E13)/D13 -> 404.71799 | H13: =Gen!D18 -> 33090.38 | I13: =Gen!F18 -> 0 | J13: =Gen!U18 -> 3662 | K13: =Gen!AL18 -> 0 | L13: =SUM(J13:K13) -> 3662 | M13: ='Water-Meter'!K53 -> 541.76567 | N13: ='Water-Meter'!E13 -> 80 | P13: 19136 | Q13: =SUM(P13-P12) -> 0 | R13: =SUM(Q13*O13) -> 0 | S13: 7 | T13: 20198 | U13: =T13-T12 -> 24 | V13: =SUM(U13*S13) -> 168 | X13: 29498 | Y13: =X13-X12 -> 0 | Z13: =SUM(Y13*W13) -> 0 | AA13: =SUM(Z13*X15) -> 0 | AB13: 19678 | AC13: =AB13-AB12 -> 170 | AD13: 227478 | AE13: =AD13-AD12 -> 63 | AF13: ='Lpg (2)'!B17*2000/85 -> 2000 | AG13: ='Lpg (2)'!C17*1000/85 -> 470.58824 | AH13: ='Lpg (2)'!D17*1000/85 -> 0 | AI13: =SUM(AF12*2000)+(AG13*1000)+(AH13*1000) -> 4470588.2 | AJ13: =SUM(AI12-AI13) -> 58823.529
A14: =Gen!B19 -> 44539 | B14: ='Summery Report'!E13 -> 10 | C14: =Gen!C19 -> 0.09 | D14: ='Summery Report'!E13 -> 10 | E14: =SUM(E13) -> 1.3262195 | F14: =SUM(J14*E14)/D14 -> 450.78201 | G14: =SUM(L14*E14)/D14 -> 450.78201 | H14: =Gen!D19 -> 31479.19 | I14: =Gen!F19 -> 0 | J14: =Gen!U19 -> 3399 | K14: =Gen!AL19 -> 0 | L14: =SUM(J14:K14) -> 3399 | M14: ='Water-Meter'!K54 -> 488.20218 | N14: ='Water-Meter'!E14 -> 65 | P14: 19136 | Q14: =SUM(P14-P13) -> 0 | R14: =SUM(Q14*O14) -> 0 | S14: 6.8 | T14: 20198 | U14: =T14-T13 -> 0 | V14: =SUM(U14*S14) -> 0 | X14: 29498 | Y14: =X14-X13 -> 0 | Z14: =SUM(Y14*W14) -> 0 | AA14: =SUM(Z14*X16) -> 0 | AB14: 19678 | AC14: =AB14-AB13 -> 0 | AD14: 227533 | AE14: =AD14-AD13 -> 55 | AF14: ='Lpg (2)'!B18*2000/85 -> 2000 | AG14: ='Lpg (2)'!C18*1000/85 -> 411.76471 | AH14: ='Lpg (2)'!D18*1000/85 -> 0 | AI14: =SUM(AF13*2000)+(AG14*1000)+(AH14*1000) -> 4411764.7 | AJ14: =SUM(AI13-AI14) -> 58823.529
A15: =Gen!B20 -> 44540 | B15: ='Summery Report'!E14 -> 12 | C15: =Gen!C20 -> 0.12 | D15: ='Summery Report'!E14 -> 12 | E15: =SUM(E14) -> 1.3262195 | F15: =SUM(J15*E15)/D15 -> 380.18293 | G15: =SUM(L15*E15)/D15 -> 380.18293 | H15: =Gen!D20 -> 30055.55 | I15: =Gen!F20 -> 0 | J15: =Gen!U20 -> 3440 | K15: =Gen!AL20 -> 0 | L15: =SUM(J15:K15) -> 3440 | M15: ='Water-Meter'!K55 -> 489.96748 | N15: ='Water-Meter'!E15 -> 71 | P15: 19136 | Q15: =SUM(P15-P14) -> 0 | R15: =SUM(Q15*O15) -> 0 | T15: 20222 | U15: =T15-T14 -> 24 | V15: =SUM(U15*S15) -> 0 | X15: 29498 | Y15: =X15-X14 -> 0 | Z15: =SUM(Y15*W15) -> 0 | AA15: =SUM(Z15*X17) -> 0 | AB15: 19845 | AC15: =AB15-AB14 -> 167 | AD15: 227587 | AE15: =AD15-AD14 -> 54 | AF15: ='Lpg (2)'!B19*2000/85 -> 2000 | AG15: ='Lpg (2)'!C19*1000/85 -> 352.94118 | AH15: ='Lpg (2)'!D19*1000/85 -> 0 | AI15: =SUM(AF15*2000)+(AG15*1000)+(AH15*1000) -> 4352941.2 | AJ15: =SUM(AI14-AI15) -> 58823.529
A16: =Gen!B21 -> 44541 | B16: ='Summery Report'!E15 -> 12 | C16: =Gen!C21 -> 0.12 | D16: ='Summery Report'!E15 -> 12 | E16: =SUM(E15) -> 1.3262195 | F16: =SUM(J16*E16)/D16 -> 408.47561 | G16: =SUM(L16*E16)/D16 -> 408.47561 | H16: =Gen!D21 -> 28259.57 | I16: =Gen!F21 -> 0 | J16: =Gen!U21 -> 3696 | K16: =Gen!AL21 -> 0 | L16: =SUM(J16:K16) -> 3696 | M16: ='Water-Meter'!K56 -> 530.64049 | N16: ='Water-Meter'!E16 -> 72 | P16: 19136 | Q16: =SUM(P16-P15) -> 0 | R16: =SUM(Q16*O16) -> 0 | S16: 6.8 | T16: 20224 | U16: =T16-T15 -> 2 | V16: =SUM(U16*S16) -> 13.6 | X16: 29498 | Y16: =X16-X15 -> 0 | Z16: =SUM(Y16*W16) -> 0 | AA16: =SUM(Z16*X18) -> 0 | AB16: 19860 | AC16: =AB16-AB15 -> 15 | AD16: 227647 | AE16: =AD16-AD15 -> 60 | AF16: ='Lpg (2)'!B20*2000/85 -> 2000 | AG16: ='Lpg (2)'!C20*1000/85 -> 258.82353 | AH16: ='Lpg (2)'!D20*1000/85 -> 0 | AI16: =SUM(AF16*2000)+(AG16*1000)+(AH16*1000) -> 4258823.5 | AJ16: =SUM(AI15-AI16) -> 94117.647
A17: =Gen!B22 -> 44542 | B17: ='Summery Report'!E16 -> 12 | C17: =Gen!C22 -> 0.12 | D17: ='Summery Report'!E16 -> 12 | E17: =SUM(E16) -> 1.3262195 | F17: =SUM(J17*E17)/D17 -> 402.9497 | G17: =SUM(L17*E17)/D17 -> 402.9497 | H17: =Gen!D22 -> 26708.91 | I17: =Gen!F22 -> 0 | J17: =Gen!U22 -> 3646 | K17: =Gen!AL22 -> 0 | L17: =SUM(J17:K17) -> 3646 | M17: ='Water-Meter'!K57 -> 548.84013 | N17: ='Water-Meter'!E17 -> 65 | P17: 19136 | Q17: =SUM(P17-P16) -> 0 | R17: =SUM(Q17*O17) -> 0 | S17: 6.8 | T17: 20247 | U17: =T17-T16 -> 23 | V17: =SUM(U17*S17) -> 156.4 | X17: 29498 | Y17: =X17-X16 -> 0 | Z17: =SUM(Y17*W17) -> 0 | AA17: =SUM(Z17*X19) -> 0 | AB17: 20017 | AC17: =AB17-AB16 -> 157 | AD17: 227709 | AE17: =AD17-AD16 -> 62 | AF17: ='Lpg (2)'!B21*2000/85 -> 2000 | AG17: ='Lpg (2)'!C21*1000/85 -> 176.47059 | AH17: ='Lpg (2)'!D21*1000/85 -> 0 | AI17: =SUM(AF17*2000)+(AG17*1000)+(AH17*1000) -> 4176470.6 | AJ17: =SUM(AI16-AI17) -> 82352.941
A18: =Gen!B23 -> 44543 | B18: ='Summery Report'!E17 -> 15 | C18: =Gen!C23 -> 0.16 | D18: ='Summery Report'!E17 -> 15 | E18: =SUM(E17) -> 1.3262195 | F18: =SUM(J18*E18)/D18 -> 350.74085 | G18: =SUM(L18*E18)/D18 -> 350.74085 | H18: =Gen!D23 -> 25155.51 | I18: =Gen!F23 -> 0 | J18: =Gen!U23 -> 3967 | K18: =Gen!AL23 -> 0 | L18: =SUM(J18:K18) -> 3967 | M18: ='Water-Meter'!K58 -> 604.45026 | N18: ='Water-Meter'!E18 -> 68 | P18: 19136 | Q18: =SUM(P18-P17) -> 0 | R18: =SUM(Q18*O18) -> 0 | S18: 6.8 | T18: 20254 | U18: =T18-T17 -> 7 | V18: =SUM(U18*S18) -> 47.6 | X18: 29498 | Y18: =X18-X17 -> 0 | Z18: =SUM(Y18*W18) -> 0 | AA18: =SUM(Z18*X20) -> 0 | AB18: 20061 | AC18: =AB18-AB17 -> 44 | AD18: 227775 | AE18: =AD18-AD17 -> 66 | AF18: ='Lpg (2)'!B22*2000/85 -> 2000 | AG18: ='Lpg (2)'!C22*1000/85 -> 117.64706 | AH18: ='Lpg (2)'!D22*1000/85 -> 0 | AI18: =SUM(AF18*2000)+(AG18*1000)+(AH18*1000) -> 4117647.1 | AJ18: =SUM(AI17-AI18) -> 58823.529
A19: =Gen!B24 -> 44544 | B19: ='Summery Report'!E18 -> 16 | C19: =Gen!C24 -> 0.17 | D19: ='Summery Report'!E18 -> 16 | E19: =SUM(E18) -> 1.3262195 | F19: =SUM(J19*E19)/D19 -> 282.73342 | G19: =SUM(L19*E19)/D19 -> 282.73342 | H19: =Gen!D24 -> 41472.63 | I19: =Gen!F24 -> 0 | J19: =Gen!U24 -> 3411 | K19: =Gen!AL24 -> 0 | L19: =SUM(J19:K19) -> 3411 | M19: ='Water-Meter'!K59 -> 544.56368 | N19: ='Water-Meter'!E19 -> 78 | P19: 19136 | R19: =SUM(Q19*O19) -> 0 | S19: 6.8 | T19: 20278 | U19: =T19-T18 -> 24 | V19: =SUM(U19*S19) -> 163.2 | X19: 29498 | Y19: =X19-X18 -> 0 | Z19: =SUM(Y19*W19) -> 0 | AA19: =SUM(Z19*X21) -> 0 | AB19: 20228 | AC19: =AB19-AB18 -> 167 | AD19: 227831 | AE19: =AD19-AD18 -> 56 | AF19: ='Lpg (2)'!B23*2000/85 -> 2000 | AG19: ='Lpg (2)'!C23*1000/85 -> 82.352941 | AH19: ='Lpg (2)'!D23*1000/85 -> 0 | AI19: =SUM(AF19*2000)+(AG19*1000)+(AH19*1000) -> 4082352.9 | AJ19: =SUM(AI18-AI19) -> 35294.118
A20: =Gen!B25 -> 44545 | B20: ='Summery Report'!E19 -> 17 | C20: =Gen!C25 -> 0.18 | D20: ='Summery Report'!E19 -> 17 | E20: =SUM(E19) -> 1.3262195 | F20: =SUM(J20*E20)/D20 -> 302.53407 | G20: =SUM(L20*E20)/D20 -> 302.53407 | H20: =Gen!D25 -> 39935.91 | I20: =Gen!F25 -> 0 | J20: =Gen!U25 -> 3878 | K20: =Gen!AL25 -> 0 | L20: =SUM(J20:K20) -> 3878 | M20: ='Water-Meter'!K60 -> 557.63933 | N20: ='Water-Meter'!E20 -> 72 | P20: 19136 | Q20: =SUM(P20-P18) -> 0 | R20: =SUM(Q20*O20) -> 0 | S20: 6.8 | T20: 20291 | U20: =T20-T19 -> 13 | V20: =SUM(U20*S20) -> 88.4 | X20: 29498 | Y20: =X20-X19 -> 0 | Z20: =SUM(Y20*W20) -> 0 | AA20: =SUM(Z20*X22) -> 0 | AB20: 20332 | AC20: =AB20-AB19 -> 104 | AD20: 227955 | AE20: =AD20-AD19 -> 124 | AF20: ='Lpg (2)'!B24*2000/85 -> 2000 | AG20: ='Lpg (2)'!C24*1000/85 -> 70.588235 | AH20: ='Lpg (2)'!D24*1000/85 -> 0 | AI20: =SUM(AF20*2000)+(AG20*1000)+(AH20*1000) -> 4070588.2 | AJ20: =SUM(AI19-AI20) -> 11764.706
A21: =Gen!B26 -> 44546 | B21: ='Summery Report'!E20 -> 15 | C21: =Gen!C26 -> 0.16 | D21: ='Summery Report'!E20 -> 15 | E21: =SUM(E20) -> 1.3262195 | F21: =SUM(J21*E21)/D21 -> 345.34756 | G21: =SUM(L21*E21)/D21 -> 345.34756 | H21: =Gen!D26 -> 38334 | I21: =Gen!F26 -> 0 | J21: =Gen!U26 -> 3906 | K21: =Gen!AL26 -> 0 | L21: =SUM(J21:K21) -> 3906 | M21: ='Water-Meter'!K61 -> 544.36195 | N21: ='Water-Meter'!E21 -> 73 | P21: 19136 | Q21: =SUM(P21-P20) -> 0 | R21: =SUM(Q21*O21) -> 0 | S21: 6.8 | T21: 20304 | U21: =T21-T20 -> 13 | V21: =SUM(U21*S21) -> 88.4 | X21: 29498 | Y21: =X21-X20 -> 0 | Z21: =SUM(Y21*W21) -> 0 | AA21: =SUM(Z21*X23) -> 0 | AB21: 20414 | AC21: =AB21-AB20 -> 82 | AD21: 228013 | AE21: =AD21-AD20 -> 58 | AF21: ='Lpg (2)'!B25*2000/85 -> 2000 | AG21: ='Lpg (2)'!C25*1000/85 -> 58.823529 | AH21: ='Lpg (2)'!D25*1000/85 -> 0 | AI21: =SUM(AF21*2000)+(AG21*1000)+(AH21*1000) -> 4058823.5 | AJ21: =SUM(AI20-AI21) -> 11764.706
A22: =Gen!B27 -> 44547 | B22: ='Summery Report'!E21 -> 15 | C22: =Gen!C27 -> 0.16 | D22: ='Summery Report'!E21 -> 15 | E22: =SUM(E21) -> 1.3262195 | F22: =SUM(J22*E22)/D22 -> 332.79268 | G22: =SUM(L22*E22)/D22 -> 332.79268 | H22: =Gen!D27 -> 51630.67 | I22: =Gen!F27 -> 15000 | J22: =Gen!U27 -> 3764 | K22: =Gen!AL27 -> 0 | L22: =SUM(J22:K22) -> 3764 | M22: ='Water-Meter'!K62 -> 532.40578 | N22: ='Water-Meter'!E22 -> 73 | P22: 19136 | Q22: =SUM(P22-P21) -> 0 | R22: =SUM(Q22*O22) -> 0 | S22: 6.8 | T22: 20309 | U22: =T22-T21 -> 5 | V22: =SUM(U22*S22) -> 34 | X22: 29498 | Y22: =X22-X21 -> 0 | Z22: =SUM(Y22*W22) -> 0 | AA22: =SUM(Z22*X24) -> 0 | AB22: 20421 | AC22: =AB22-AB21 -> 7 | AD22: 228067 | AE22: =AD22-AD21 -> 54 | AF22: ='Lpg (2)'!B26*2000/85 -> 2000 | AG22: ='Lpg (2)'!C26*1000/85 -> 47.058824 | AH22: ='Lpg (2)'!D26*1000/85 -> 0 | AI22: =SUM(AF22*2000)+(AG22*1000)+(AH22*1000) -> 4047058.8 | AJ22: =SUM(AI21-AI22) -> 11764.706
A23: =Gen!B28 -> 44548 | B23: ='Summery Report'!E22 -> 13 | C23: =Gen!C28 -> 0.13 | D23: ='Summery Report'!E22 -> 13 | E23: =SUM(E22) -> 1.3262195 | F23: =SUM(J23*E23)/D23 -> 396.02955 | G23: =SUM(L23*E23)/D23 -> 396.02955 | H23: =Gen!D28 -> 49995.77 | I23: =Gen!F28 -> 0 | J23: =Gen!U28 -> 3882 | K23: =Gen!AL28 -> 0 | L23: =SUM(J23:K23) -> 3882 | M23: ='Water-Meter'!K63 -> 508.56404 | N23: ='Water-Meter'!E23 -> 85 | P23: 19136 | Q23: =SUM(P23-P22) -> 0 | R23: =SUM(Q23*O23) -> 0 | S23: 6.8 | T23: 20328 | U23: =T23-T22 -> 19 | V23: =SUM(U23*S23) -> 129.2 | X23: 29498 | Y23: =X23-X22 -> 0 | Z23: =SUM(Y23*W23) -> 0 | AA23: =SUM(Z23*X25) -> 0 | AB23: 20573 | AC23: =AB23-AB22 -> 152 | AD23: 228130 | AE23: =AD23-AD22 -> 63 | AF23: ='Lpg (2)'!B27*2000/85 -> 2000 | AG23: ='Lpg (2)'!C27*1000/85 -> 35.294118 | AH23: ='Lpg (2)'!D27*1000/85 -> 0 | AI23: =SUM(AF23*2000)+(AG23*1000)+(AH23*1000) -> 4035294.1 | AJ23: =SUM(AI22-AI23) -> 11764.706
A24: =Gen!B29 -> 44549 | B24: ='Summery Report'!E23 -> 10 | C24: =Gen!C29 -> 0.12 | D24: ='Summery Report'!E23 -> 10 | E24: =SUM(E23) -> 1.3262195 | F24: =SUM(J24*E24)/D24 -> 496.66921 | G24: =SUM(L24*E24)/D24 -> 496.66921 | H24: =Gen!D29 -> 48117.15 | I24: =Gen!F29 -> 0 | J24: =Gen!U29 -> 3745 | K24: =Gen!AL29 -> 0 | L24: =SUM(J24:K24) -> 3745 | M24: ='Water-Meter'!K64 -> 474.7559 | N24: ='Water-Meter'!E24 -> 80 | P24: 19136 | Q24: =SUM(P24-P23) -> 0 | R24: =SUM(Q24*O24) -> 0 | S24: 6.8 | T24: 20351 | U24: =T24-T23 -> 23 | V24: =SUM(U24*S24) -> 156.4 | X24: 29498 | Y24: =X24-X23 -> 0 | Z24: =SUM(Y24*W24) -> 0 | AA24: =SUM(Z24*X26) -> 0 | AB24: 20741 | AC24: =AB24-AB23 -> 168 | AD24: 228192 | AE24: =AD24-AD23 -> 62 | AF24: ='Lpg (2)'!B28*2000/85 -> 2000 | AG24: ='Lpg (2)'!C28*1000/85 -> 23.529412 | AH24: ='Lpg (2)'!D28*1000/85 -> 0 | AI24: =SUM(AF24*2000)+(AG24*1000)+(AH24*1000) -> 4023529.4 | AJ24: =SUM(AI23-AI24) -> 11764.706
A25: =Gen!B30 -> 44550 | B25: ='Summery Report'!E24 -> 6 | C25: =Gen!C30 -> 0.06 | D25: ='Summery Report'!E24 -> 6 | E25: =SUM(E24) -> 1.3262195 | F25: =SUM(J25*E25)/D25 -> 719.91616 | G25: =SUM(L25*E25)/D25 -> 719.91616 | H25: =Gen!D30 -> 46497.59 | I25: =Gen!F30 -> 0 | J25: =Gen!U30 -> 3257 | K25: =Gen!AL30 -> 0 | L25: =SUM(J25:K25) -> 3257 | M25: ='Water-Meter'!K65 -> 460.05038 | N25: ='Water-Meter'!E25 -> 76 | P25: 19136 | Q25: =SUM(P25-P24) -> 0 | R25: =SUM(Q25*O25) -> 0 | S25: 6.8 | T25: 20351 | U25: =T25-T24 -> 0 | V25: =SUM(U25*S25) -> 0 | X25: 29498 | Y25: =X25-X24 -> 0 | Z25: =SUM(Y25*W25) -> 0 | AA25: =SUM(Z25*X27) -> 0 | AB25: 20741 | AC25: =AB25-AB24 -> 0 | AD25: 228250 | AE25: =AD25-AD24 -> 58 | AF25: ='Lpg (2)'!B29*2000/85 -> 2000 | AG25: ='Lpg (2)'!C29*1000/85 -> 11.764706 | AH25: ='Lpg (2)'!D29*1000/85 -> 0 | AI25: =SUM(AF25*2000)+(AG25*1000)+(AH25*1000) -> 4011764.7 | AJ25: =SUM(AI24-AI25) -> 11764.706
A26: =Gen!B31 -> 44551 | B26: ='Summery Report'!E25 -> 9 | C26: =Gen!C31 -> 0.1 | D26: ='Summery Report'!E25 -> 9 | E26: =SUM(E25) -> 1.3262195 | F26: =SUM(J26*E26)/D26 -> 662.37297 | G26: =SUM(L26*E26)/D26 -> 662.37297 | H26: =Gen!D31 -> 44968.52 | I26: =Gen!F31 -> 0 | J26: =Gen!U31 -> 4495 | K26: =Gen!AL31 -> 0 | L26: =SUM(J26:K26) -> 4495 | M26: ='Water-Meter'!K66 -> 502.70532 | N26: ='Water-Meter'!E26 -> 69 | P26: 19136 | Q26: =SUM(P26-P25) -> 0 | R26: =SUM(Q26*O26) -> 0 | S26: 6.8 | T26: 20364 | U26: =T26-T25 -> 13 | V26: =SUM(U26*S26) -> 88.4 | X26: 29498 | Y26: =X26-X25 -> 0 | Z26: =SUM(Y26*W26) -> 0 | AA26: =SUM(Z26*X28) -> 0 | AB26: 20827 | AC26: =AB26-AB25 -> 86 | AD26: 228307 | AE26: =AD26-AD25 -> 57 | AF26: ='Lpg (2)'!B30*2000/85 -> 1952.9412 | AG26: ='Lpg (2)'!C30*1000/85 -> 0 | AH26: ='Lpg (2)'!D30*1000/85 -> 0 | AI26: =SUM(AF26*2000)+(AG26*1000)+(AH26*1000) -> 3905882.4 | AJ26: =SUM(AI25-AI26) -> 105882.35
A27: =Gen!B32 -> 44552 | B27: ='Summery Report'!E26 -> 14 | C27: =Gen!C32 -> 0.17 | D27: ='Summery Report'!E26 -> 14 | E27: =SUM(E26) -> 1.3262195 | F27: =SUM(J27*E27)/D27 -> 378.54094 | G27: =SUM(L27*E27)/D27 -> 378.54094 | H27: =Gen!D32 -> 43036.55 | I27: =Gen!F32 -> 0 | J27: =Gen!U32 -> 3996 | K27: =Gen!AL32 -> 0 | L27: =SUM(J27:K27) -> 3996 | M27: ='Water-Meter'!K67 -> 539.2849 | N27: ='Water-Meter'!E27 -> 71 | P27: 19136 | Q27: =SUM(P27-P26) -> 0 | R27: =SUM(Q27*O27) -> 0 | S27: 6.8 | T27: 20379 | U27: =T27-T26 -> 15 | V27: =SUM(U27*S27) -> 102 | X27: 29498 | Y27: =X27-X26 -> 0 | Z27: =SUM(Y27*X27) -> 0 | AA27: =SUM(Z27*X29) -> 0 | AB27: 20927 | AC27: =AB27-AB26 -> 100 | AD27: 228367 | AE27: =AD27-AD26 -> 60 | AF27: ='Lpg (2)'!B31*2000/85 -> 1905.8824 | AG27: ='Lpg (2)'!C31*1000/85 -> 0 | AH27: ='Lpg (2)'!D31*1000/85 -> 0 | AI27: =SUM(AF27*2000)+(AG27*1000)+(AH27*1000) -> 3811764.7 | AJ27: =SUM(AI26-AI27) -> 94117.647
A28: =Gen!B33 -> 44553 | B28: ='Summery Report'!E27 -> 14 | C28: =Gen!C33 -> 0.17 | D28: ='Summery Report'!E27 -> 14 | E28: =SUM(E27) -> 1.3262195 | F28: =SUM(J28*E28)/D28 -> 397.10801 | G28: =SUM(L28*E28)/D28 -> 397.10801 | H28: =Gen!D33 -> 41053.29 | I28: =Gen!F33 -> 0 | J28: =Gen!U33 -> 4192 | K28: =Gen!AL33 -> 0 | L28: =SUM(J28:K28) -> 4192 | M28: ='Water-Meter'!K68 -> 533.59209 | N28: ='Water-Meter'!E28 -> 85 | P28: 19136 | Q28: =SUM(P28-P27) -> 0 | R28: =SUM(Q28*O28) -> 0 | S28: 6.8 | T28: 20394 | U28: =T28-T27 -> 15 | V28: =SUM(U28*S28) -> 102 | X28: 29498 | Y28: =X28-X27 -> 0 | Z28: =SUM(Y28*X28) -> 0 | AA28: =SUM(Z28*X30) -> 0 | AB28: 21022 | AC28: =SUM(AB28-AB27) -> 95 | AD28: 228426 | AE28: =AD28-AD27 -> 59 | AF28: ='Lpg (2)'!B32*2000/85 -> 1835.2941 | AG28: ='Lpg (2)'!C32*1000/85 -> 0 | AH28: ='Lpg (2)'!D32*1000/85 -> 0 | AI28: =SUM(AF28*2000)+(AG28*1000)+(AH28*1000) -> 3670588.2 | AJ28: =SUM(AI27-AI28) -> 141176.47
A29: =Gen!B34 -> 44554 | B29: ='Summery Report'!E28 -> 37 | C29: =Gen!C34 -> 0.47 | D29: ='Summery Report'!E28 -> 37 | E29: =SUM(E28) -> 1.3262195 | F29: =SUM(J29*E29)/D29 -> 177.31913 | G29: =SUM(L29*E29)/D29 -> 177.31913 | H29: =Gen!D34 -> 39249.8 | I29: =Gen!F34 -> 0 | J29: =Gen!U34 -> 4947 | K29: =Gen!AL34 -> 0 | L29: =SUM(J29:K29) -> 4947 | M29: ='Water-Meter'!K69 -> 502.87938 | N29: ='Water-Meter'!E29 -> 75 | P29: 19136 | Q29: =SUM(P29-P28) -> 0 | R29: =SUM(Q29*O29) -> 0 | S29: 6.7 | T29: 20414 | U29: =T29-T28 -> 20 | V29: =SUM(U29*S29) -> 134 | X29: 29498 | Y29: =X29-X28 -> 0 | Z29: =SUM(Y29*W29) -> 0 | AA29: =SUM(Z29*X31) -> 0 | AB29: 21156 | AC29: =SUM(AB29-AB28) -> 134 | AD29: 228484 | AE29: =AD29-AD28 -> 58 | AF29: ='Lpg (2)'!B33*2000/85 -> 1764.7059 | AG29: ='Lpg (2)'!C33*1000/85 -> 0 | AH29: ='Lpg (2)'!D33*1000/85 -> 0 | AI29: =SUM(AF29*2000)+(AG29*1000)+(AH29*1000) -> 3529411.8 | AJ29: =SUM(AI28-AI29) -> 141176.47
A30: =Gen!B35 -> 44555 | B30: ='Summery Report'!E29 -> 46 | C30: =Gen!C35 -> 0.58 | D30: ='Summery Report'!E29 -> 46 | E30: =SUM(E29) -> 1.3262195 | F30: =SUM(J30*E30)/D30 -> 141.76133 | G30: =SUM(L30*E30)/D30 -> 141.76133 | H30: =Gen!D35 -> 37137.14 | I30: =Gen!F35 -> 0 | J30: =Gen!U35 -> 4917 | K30: =Gen!AL35 -> 0 | L30: =SUM(J30:K30) -> 4917 | M30: ='Water-Meter'!K70 -> 476.8967 | N30: ='Water-Meter'!E30 -> 102 | P30: 19136 | Q30: =SUM(P30-P29) -> 0 | R30: =SUM(Q30*O30) -> 0 | S30: 6.7 | T30: 20427 | U30: =T30-T29 -> 13 | V30: =SUM(U30*S30) -> 87.1 | X30: 29498 | Y30: =X30-X29 -> 0 | Z30: =SUM(Y30*W30) -> 0 | AA30: =SUM(Z30*X32) -> 0 | AB30: 21241 | AC30: =SUM(AB30-AB29) -> 85 | AD30: 228541 | AE30: =AD30-AD29 -> 57 | AF30: ='Lpg (2)'!B34*2000/85 -> 1694.1176 | AG30: ='Lpg (2)'!C34*1000/85 -> 0 | AH30: ='Lpg (2)'!D34*1000/85 -> 0 | AI30: =SUM(AF30*2000)+(AG30*1000)+(AH30*1000) -> 3388235.3 | AJ30: =SUM(AI29-AI30) -> 141176.47
A31: =Gen!B36 -> 44556 | B31: ='Summery Report'!E30 -> 35 | C31: =Gen!C36 -> 0.43 | D31: ='Summery Report'!E30 -> 35 | E31: =SUM(E30) -> 1.3262195 | F31: =SUM(J31*E31)/D31 -> 187.33798 | G31: =SUM(L31*E31)/D31 -> 187.33798 | H31: =Gen!D36 -> 35096.45 | I31: =Gen!F36 -> 0 | J31: =Gen!U36 -> 4944 | K31: =Gen!AL36 -> 0 | L31: =SUM(J31:K31) -> 4944 | M31: ='Water-Meter'!K71 -> 508.95873 | N31: ='Water-Meter'!E31 -> 106 | P31: 19136 | Q31: =SUM(P31-P30) -> 0 | R31: =SUM(Q31*O31) -> 0 | S31: 6.7 | T31: 20434 | U31: =T31-T30 -> 7 | V31: =SUM(U31*S31) -> 46.9 | X31: 29498 | Y31: =X31-X30 -> 0 | Z31: =SUM(Y31*W32) -> 0 | AA31: =SUM(Z31*X33) -> 0 | AB31: 21289 | AC31: =SUM(AB31-AB30) -> 48 | AD31: 228591 | AE31: =AD31-AD30 -> 50 | AF31: ='Lpg (2)'!B35*2000/85 -> 1600 | AG31: ='Lpg (2)'!C35*1000/85 -> 0 | AH31: ='Lpg (2)'!D35*1000/85 -> 0 | AI31: =SUM(AF31*2000)+(AG31*1000)+(AH31*1000) -> 3200000 | AJ31: =SUM(AI30-AI31) -> 188235.29
A32: =Gen!B37 -> 44557 | B32: ='Summery Report'!E31 -> 31 | C32: =Gen!C37 -> 0.39 | D32: ='Summery Report'!E31 -> 31 | E32: =SUM(E31) -> 1.3262195 | F32: =SUM(J32*E32)/D32 -> 213.90637 | G32: =SUM(L32*E32)/D32 -> 213.90637 | H32: =Gen!D37 -> 32646.31 | I32: =Gen!F37 -> 0 | J32: =Gen!U37 -> 5000 | K32: =Gen!AL37 -> 0 | L32: =SUM(J32:K32) -> 5000 | M32: ='Water-Meter'!K72 -> 548.19649 | N32: ='Water-Meter'!E32 -> 102 | O32: 1.7 | P32: 19044 | Q32: =SUM(P32-P31) -> -92 | R32: =SUM(Q32*O32) -> -156.4 | S32: 6.8 | T32: 20454 | U32: =T32-T31 -> 20 | V32: =SUM(U32*S32) -> 136 | X32: 29498 | Y32: =X32-X31 -> 0 | Z32: =SUM(Y32*W32) -> 0 | AA32: =SUM(Z32*X34) -> 0 | AB32: 21424 | AC32: =SUM(AB32-AB31) -> 135 | AD32: 228654 | AE32: =AD32-AD31 -> 63 | AF32: ='Lpg (2)'!B36*2000/85 -> 1552.9412 | AG32: ='Lpg (2)'!C36*1000/85 -> 0 | AH32: ='Lpg (2)'!D36*1000/85 -> 0 | AI32: =SUM(AF32*2000)+(AG32*1000)+(AH32*1000) -> 3105882.4 | AJ32: =SUM(AI31-AI32) -> 94117.647
A33: =Gen!B38 -> 44558 | B33: ='Summery Report'!E32 -> 34 | C33: =Gen!C38 -> 0.43 | D33: ='Summery Report'!E32 -> 34 | E33: =SUM(E32) -> 1.3262195 | F33: =SUM(J33*E33)/D33 -> 182.39419 | G33: =SUM(L33*E33)/D33 -> 182.39419 | H33: =Gen!D38 -> 30567.86 | I33: =Gen!F38 -> 18000 | J33: =Gen!U38 -> 4676 | K33: =Gen!AL38 -> 0 | L33: =SUM(J33:K33) -> 4676 | M33: ='Water-Meter'!K73 -> 514.79618 | N33: ='Water-Meter'!E33 -> 109 | P33: 19044 | Q33: =SUM(P33-P32) -> 0 | R33: =SUM(Q33*O33) -> 0 | S33: 6.7 | T33: 20465 | U33: =T33-T32 -> 11 | V33: =SUM(U33*S33) -> 73.7 | X33: 29498 | Y33: =X33-X32 -> 0 | Z33: =SUM(Y33*W33) -> 0 | AA33: =SUM(Z33*X35) -> 0 | AB33: 21501 | AC33: =SUM(AB33-AB32) -> 77 | AD33: 228715 | AE33: =AD33-AD32 -> 61 | AF33: ='Lpg (2)'!B37*2000/85 -> 1505.8824 | AG33: ='Lpg (2)'!C37*1000/85 -> 0 | AH33: ='Lpg (2)'!D37*1000/85 -> 0 | AI33: =SUM(AF33*2000)+(AG33*1000)+(AH33*1000) -> 3011764.7 | AJ33: =SUM(AI32-AI33) -> 94117.647
A34: =Gen!B39 -> 44559 | B34: ='Summery Report'!E33 -> 42 | C34: =Gen!C39 -> 0.53 | D34: ='Summery Report'!E33 -> 42 | E34: =SUM(E33) -> 1.3262195 | F34: =SUM(J34*E34)/D34 -> 154.473 | G34: =SUM(L34*E34)/D34 -> 154.473 | H34: =Gen!D39 -> 46327.78 | I34: =Gen!F39 -> 0 | J34: =Gen!U39 -> 4892 | K34: =Gen!AL39 -> 0 | L34: =SUM(J34:K34) -> 4892 | M34: ='Water-Meter'!K74 -> 514.85393 | N34: ='Water-Meter'!E34 -> 111 | P34: 19044 | Q34: =SUM(P34-P33) -> 0 | R34: =SUM(Q34*O34) -> 0 | S34: 6.7 | T34: 20481 | U34: =T34-T33 -> 16 | V34: =SUM(U34*S34) -> 107.2 | X34: 29498 | Y34: =X34-X33 -> 0 | Z34: =SUM(Y34*W34) -> 0 | AA34: =SUM(Z34*X36) -> 0 | AB34: 21602 | AC34: =SUM(AB34-AB33) -> 101 | AD34: 228778 | AE34: =AD34-AD33 -> 63 | AF34: ='Lpg (2)'!B38*2000/85 -> 1411.7647 | AG34: ='Lpg (2)'!C38*1000/85 -> 0 | AH34: ='Lpg (2)'!D38*1000/85 -> 0 | AI34: =SUM(AF34*2000)+(AG34*1000)+(AH34*1000) -> 2823529.4 | AJ34: =SUM(AI33-AI34) -> 188235.29
A35: =Gen!B40 -> 44560 | B35: ='Summery Report'!E34 -> 48 | C35: =Gen!C40 -> 0.61 | D35: ='Summery Report'!E34 -> 48 | E35: =SUM(E34) -> 1.3262195 | F35: =SUM(J35*E35)/D35 -> 131.68255 | G35: =SUM(L35*E35)/D35 -> 131.68255 | H35: =Gen!D40 -> 44051.71 | I35: =Gen!F40 -> 0 | J35: =Gen!U40 -> 4766 | K35: =Gen!AL40 -> 0 | L35: =SUM(J35:K35) -> 4766 | M35: ='Water-Meter'!K75 -> 481.41025 | N35: ='Water-Meter'!E35 -> 102 | P35: 19044 | Q35: =SUM(P35-P34) -> 0 | R35: =SUM(Q35*O35) -> 0 | S35: 6.7 | T35: 20503 | U35: =T35-T34 -> 22 | V35: =SUM(U35*S35) -> 147.4 | X35: 29498 | Y35: =X35-X34 -> 0 | Z35: =SUM(Y35*W35) -> 0 | AA35: =SUM(Z35*X37) -> 0 | AB35: 21751 | AC35: =SUM(AB35-AB34) -> 149 | AD35: 228827 | AE35: =AD35-AD34 -> 49 | AF35: ='Lpg (2)'!B39*2000/85 -> 1317.6471 | AG35: ='Lpg (2)'!C39*1000/85 -> 0 | AH35: ='Lpg (2)'!D39*1000/85 -> 0 | AI35: =SUM(AF35*2000)+(AG35*1000)+(AH35*1000) -> 2635294.1 | AJ35: =SUM(AI34-AI35) -> 188235.29
A36: =Gen!B41 -> 44561 | B36: ='Summery Report'!E35 -> 48 | C36: =Gen!C41 -> 0.61 | D36: ='Summery Report'!E35 -> 48 | E36: =SUM(E35) -> 1.3262195 | F36: =SUM(J36*E36)/D36 -> 126.04611 | G36: =SUM(L36*E36)/D36 -> 126.04611 | H36: =Gen!D41 -> 41977.68 | I36: =Gen!F41 -> 0 | J36: =Gen!U41 -> 4562 | K36: =Gen!AL41 -> 0 | L36: =SUM(J36:K36) -> 4562 | M36: ='Water-Meter'!K76 -> 427.70997 | N36: ='Water-Meter'!E36 -> 102 | P36: 19044 | Q36: =SUM(P36-P35) -> 0 | R36: =SUM(Q36*O36) -> 0 | S36: 6.7 | T36: 20528 | U36: =T36-T35 -> 25 | V36: =SUM(U36*S36) -> 167.5 | X36: 29498 | Y36: =X36-X35 -> 0 | Z36: =SUM(Y36*W36) -> 0 | AA36: =SUM(Z36*X38) -> 0 | AB36: 21907 | AC36: =SUM(AB36-AB35) -> 156 | AD36: 228878 | AE36: =AD36-AD35 -> 51 | AF36: ='Lpg (2)'!B40*2000/85 -> 1247.0588 | AG36: ='Lpg (2)'!C40*1000/85 -> 0 | AH36: ='Lpg (2)'!D40*1000/85 -> 0 | AI36: =SUM(AF36*1000)+(AG36*1000)+(AH36*2000) -> 1247058.8 | AJ36: =SUM(AI35-AI36) -> 1388235.3
A37: =Gen!B42 -> 0 | B37: 0 | J37: =SUM(J6:J36) -> 121361 | L37: =SUM(J37:K37) -> 121361 | M37: ='Water-Meter'!K77 -> 452.068 | N37: ='Water-Meter'!E37 -> 120 | Q37: =SUM(P37-P36) -> -19044 | R37: =SUM(Q37*O37) -> 0 | U37: =T37-T36 -> -20528 | V37: =SUM(U37*S37) -> 0 | Y37: =X37-X36 -> -29498 | Z37: =SUM(Y37*W37) -> 0 | AA37: =SUM(Z37*X39) -> 0 | AC37: =SUM(AB37-AB36) -> -21907 | AE37: =AD37-AD36 -> -228878 | AF37: ='Lpg (2)'!#REF!*2000/85 -> #REF! | AG37: ='Lpg (2)'!#REF!*1000/85 -> #REF! | AH37: ='Lpg (2)'!#REF!*1000/85 -> #REF! | AJ37: =SUM(AI36-AI37) -> 1247058.8

Sheet Sheet3

Sheet Utility summery
A4: Date | B4: Room Occupied | C4: Electricity Units Generated KW | D4: Diseal | G4: Water | J4: Gas | N4: Cost of utilites
D5: Generator | E5: Transport | F5: Total | G5: RO | H5: STP | I5: Total Consumption | J5: 2 ton | K5: 1 Ton | L5: 1 Ton | M5: Total consumption | N5: Electricity /1.4$/liter | O5: Diseal for Transport | P5: Gas /2.38$/Kg | Q5: Total HLP Cost | R5: Electricity Cost/Room $ | S5: cost/Room $
A6: =Gen!B11 -> 44531 | B6: 6 | C6: =Gen!V11 -> 0.42833546 | D6: =Gen!T11 -> 1340.69 | E6: =Gen!AK11 -> 55.31 | F6: =Gen!AT11 -> 0 | G6: ='Utility report '!AC6 -> 35 | H6: ='Utility report '!AE6 -> 73 | I6: ='Water-Meter'!E6 -> 79 | J6: ='Lpg (2)'!B10 -> 85 | K6: ='Lpg (2)'!C10 -> 84 | L6: ='Lpg (2)'!D10 -> 0 | M6: ='Lpg (2)'!G10 -> 101.244 | N6: =D6*1.4 -> 1876.966 | O6: =E6*1.4 -> 77.434 | P6: =('Lpg (2)'!G10)*2.38 -> 240.96072 | Q6: =N6+O6+P6 -> 2195.3607 | R6: =N6/B6 -> 312.82767 | S6: =Q6/B6 -> 365.89345
A7: =Gen!B12 -> 44532 | B7: 5 | C7: =Gen!V12 -> 0.40863446 | D7: =Gen!T12 -> 1268.81 | E7: =Gen!AK12 -> 596.04 | F7: =Gen!AT12 -> 0 | G7: ='Utility report '!AC7 -> 61 | H7: ='Utility report '!AE7 -> 69 | I7: ='Water-Meter'!E7 -> 67 | J7: ='Lpg (2)'!B11 -> 85 | K7: ='Lpg (2)'!C11 -> 80 | L7: ='Lpg (2)'!D11 -> 0 | M7: ='Lpg (2)'!G11 -> 70.312 | N7: =D7*1.4 -> 1776.334 | O7: =E7*1.4 -> 834.456 | P7: =('Lpg (2)'!G11)*2.38 -> 167.34256 | Q7: =N7+O7+P7 -> 2778.1326 | R7: =N7/B7 -> 355.2668 | S7: =Q7/B7 -> 555.62651
A8: =Gen!B13 -> 44533 | B8: 3 | C8: =Gen!V13 -> 0.40452577 | D8: =Gen!T13 -> 1177.17 | E8: =Gen!AK13 -> 0 | F8: =Gen!AT13 -> 0 | G8: ='Utility report '!AC8 -> 50 | H8: ='Utility report '!AE8 -> 70 | I8: ='Water-Meter'!E8 -> 83 | J8: ='Lpg (2)'!B12 -> 85 | K8: ='Lpg (2)'!C12 -> 74 | L8: ='Lpg (2)'!D12 -> 0 | M8: ='Lpg (2)'!G12 -> 59.576 | N8: =D8*1.4 -> 1648.038 | O8: =E8*1.4 -> 0 | P8: =('Lpg (2)'!G12)*2.38 -> 141.79088 | Q8: =N8+O8+P8 -> 1789.8289 | R8: =N8/B8 -> 549.346 | S8: =Q8/B8 -> 596.60963
A9: =Gen!B14 -> 44534 | B9: 8 | C9: =Gen!V14 -> 0.3931955 | D9: =Gen!T14 -> 1293.22 | E9: =Gen!AK14 -> 199.51 | F9: =Gen!AT14 -> 0 | G9: ='Utility report '!AC9 -> 89 | H9: ='Utility report '!AE9 -> 63 | I9: ='Water-Meter'!E9 -> 67 | J9: ='Lpg (2)'!B13 -> 85 | K9: ='Lpg (2)'!C13 -> 65 | L9: ='Lpg (2)'!D13 -> 0 | M9: ='Lpg (2)'!G13 -> 61.512 | N9: =D9*1.4 -> 1810.508 | O9: =E9*1.4 -> 279.314 | P9: =('Lpg (2)'!G13)*2.38 -> 146.39856 | Q9: =N9+O9+P9 -> 2236.2206 | R9: =N9/B9 -> 226.3135 | S9: =Q9/B9 -> 279.52757
A10: =Gen!B15 -> 44535 | B10: 6 | C10: =Gen!V15 -> 0.3963541 | D10: =Gen!T15 -> 1246.93 | E10: =Gen!AK15 -> 53.33 | F10: =Gen!AT15 -> 0 | G10: ='Utility report '!AC10 -> 103 | H10: ='Utility report '!AE10 -> 47 | I10: ='Water-Meter'!E10 -> 62 | J10: ='Lpg (2)'!B14 -> 85 | K10: ='Lpg (2)'!C14 -> 55 | L10: ='Lpg (2)'!D14 -> 0 | M10: ='Lpg (2)'!G14 -> 87.34 | N10: =D10*1.4 -> 1745.702 | O10: =E10*1.4 -> 74.662 | P10: =('Lpg (2)'!G14)*2.38 -> 207.8692 | Q10: =N10+O10+P10 -> 2028.2332 | R10: =N10/B10 -> 290.95033 | S10: =Q10/B10 -> 338.03887
A11: =Gen!B16 -> 44536 | B11: 9 | C11: =Gen!V16 -> 0.39449271 | D11: =Gen!T16 -> 1325.89 | E11: 0 | F11: =Gen!AT16 -> 0 | G11: ='Utility report '!AC11 -> 17 | H11: ='Utility report '!AE11 -> 53 | I11: ='Water-Meter'!E11 -> 57 | J11: ='Lpg (2)'!B15 -> 85 | K11: ='Lpg (2)'!C15 -> 50 | L11: ='Lpg (2)'!D15 -> 0 | M11: ='Lpg (2)'!G15 -> 107.492 | N11: =D11*1.4 -> 1856.246 | O11: =E11*1.4 -> 0 | P11: =('Lpg (2)'!G15)*2.38 -> 255.83096 | Q11: =N11+O11+P11 -> 2112.077 | R11: =N11/B11 -> 206.24956 | S11: =Q11/B11 -> 234.67522
A12: =Gen!B17 -> 44537 | B12: 9 | C12: =Gen!V17 -> 0.40501183 | D12: =Gen!T17 -> 1368.94 | E12: =Gen!AK17 -> 135.94 | F12: =Gen!AT17 -> 0 | G12: ='Utility report '!AC12 -> 121 | H12: ='Utility report '!AE12 -> 50 | I12: ='Water-Meter'!E12 -> 73 | J12: ='Lpg (2)'!B16 -> 85 | K12: ='Lpg (2)'!C16 -> 45 | L12: ='Lpg (2)'!D16 -> 0 | M12: ='Lpg (2)'!G16 -> 90.684 | N12: =D12*1.4 -> 1916.516 | O12: =E12*1.4 -> 190.316 | P12: =('Lpg (2)'!G16)*2.38 -> 215.82792 | Q12: =N12+O12+P12 -> 2322.6599 | R12: =N12/B12 -> 212.94622 | S12: =Q12/B12 -> 258.07332
A13: =Gen!B18 -> 44538 | B13: 12 | C13: =Gen!V18 -> 0.4171491 | D13: =Gen!T18 -> 1527.6 | E13: =Gen!AK18 -> 83.59 | F13: =Gen!AT18 -> 0 | G13: ='Utility report '!AC13 -> 170 | H13: ='Utility report '!AE13 -> 63 | I13: ='Water-Meter'!E13 -> 80 | J13: ='Lpg (2)'!B17 -> 85 | K13: ='Lpg (2)'!C17 -> 40 | L13: ='Lpg (2)'!D17 -> 0 | M13: ='Lpg (2)'!G17 -> 99.88 | N13: =D13*1.4 -> 2138.64 | O13: =E13*1.4 -> 117.026 | P13: =('Lpg (2)'!G17)*2.38 -> 237.7144 | Q13: =N13+O13+P13 -> 2493.3804 | R13: =N13/B13 -> 178.22 | S13: =Q13/B13 -> 207.7817
A14: =Gen!B19 -> 44539 | B14: 10 | C14: =Gen!V19 -> 0.4035481 | D14: =Gen!T19 -> 1371.66 | E14: =Gen!AK19 -> 51.98 | F14: =Gen!AT19 -> 0 | G14: ='Utility report '!AC14 -> 0 | H14: ='Utility report '!AE14 -> 55 | I14: ='Water-Meter'!E14 -> 65 | J14: ='Lpg (2)'!B18 -> 85 | K14: ='Lpg (2)'!C18 -> 35 | L14: ='Lpg (2)'!D18 -> 0 | M14: ='Lpg (2)'!G18 -> 108.988 | N14: =D14*1.4 -> 1920.324 | O14: =E14*1.4 -> 72.772 | P14: =('Lpg (2)'!G18)*2.38 -> 259.39144 | Q14: =N14+O14+P14 -> 2252.4874 | R14: =N14/B14 -> 192.0324 | S14: =Q14/B14 -> 225.24874
A15: =Gen!B20 -> 44540 | B15: 12 | C15: =Gen!V20 -> 0.3916657 | D15: =Gen!T20 -> 1347.33 | E15: =Gen!AK20 -> 448.65 | F15: =Gen!AT20 -> 0 | G15: ='Utility report '!AC15 -> 167 | H15: ='Utility report '!AE15 -> 54 | I15: ='Water-Meter'!E15 -> 71 | J15: ='Lpg (2)'!B19 -> 85 | K15: ='Lpg (2)'!C19 -> 30 | L15: ='Lpg (2)'!D19 -> 0 | M15: ='Lpg (2)'!G19 -> 110 | N15: =D15*1.4 -> 1886.262 | O15: =E15*1.4 -> 628.11 | P15: =('Lpg (2)'!G19)*2.38 -> 261.8 | Q15: =N15+O15+P15 -> 2776.172 | R15: =N15/B15 -> 157.1885 | S15: =Q15/B15 -> 231.34767
A16: =Gen!B21 -> 44541 | B16: 12 | C16: =Gen!V21 -> 0.40930465 | D16: =Gen!T21 -> 1512.79 | E16: =Gen!AK21 -> 37.87 | F16: =Gen!AT9 -> 0 | G16: ='Utility report '!AC16 -> 15 | H16: ='Utility report '!AE16 -> 60 | I16: ='Water-Meter'!E16 -> 72 | J16: ='Lpg (2)'!B20 -> 85 | K16: ='Lpg (2)'!C20 -> 22 | L16: ='Lpg (2)'!D20 -> 0 | M16: ='Lpg (2)'!G20 -> 105.38 | N16: =D16*1.4 -> 2117.906 | O16: =E16*1.4 -> 53.018 | P16: =('Lpg (2)'!G20)*2.38 -> 250.8044 | Q16: =N16+O16+P16 -> 2421.7284 | R16: =N16/B16 -> 176.49217 | S16: =Q16/B16 -> 201.8107
A17: =Gen!B22 -> 44542 | B17: 12 | C17: =Gen!V22 -> 0.40736149 | D17: =Gen!T22 -> 1485.24 | E17: =Gen!AK22 -> 68.16 | F17: =Gen!AT22 -> 0 | G17: ='Utility report '!AC17 -> 157 | H17: ='Utility report '!AE17 -> 62 | I17: ='Water-Meter'!E17 -> 65 | J17: ='Lpg (2)'!B21 -> 85 | K17: ='Lpg (2)'!C22 -> 10 | L17: ='Lpg (2)'!D21 -> 0 | M17: ='Lpg (2)'!G21 -> 106.656 | N17: =D17*1.4 -> 2079.336 | O17: =E17*1.4 -> 95.424 | P17: =('Lpg (2)'!G21)*2.38 -> 253.84128 | Q17: =N17+O17+P17 -> 2428.6013 | R17: =N17/B17 -> 173.278 | S17: =Q17/B17 -> 202.38344
A18: =Gen!B23 -> 44543 | B18: 15 | C18: =Gen!V23 -> 0.39819259 | D18: =Gen!T23 -> 1579.63 | E18: =Gen!AK23 -> 103.25 | F18: =Gen!AT23 -> 0 | G18: ='Utility report '!AC18 -> 44 | H18: ='Utility report '!AE18 -> 66 | I18: ='Water-Meter'!E18 -> 68 | J18: ='Lpg (2)'!B22 -> 85 | K18: ='Lpg (2)'!C23 -> 7 | L18: ='Lpg (2)'!D22 -> 0 | M18: ='Lpg (2)'!G22 -> 108.02 | N18: =D18*1.4 -> 2211.482 | O18: =E18*1.4 -> 144.55 | P18: =('Lpg (2)'!G22)*2.38 -> 257.0876 | Q18: =N18+O18+P18 -> 2613.1196 | R18: =N18/B18 -> 147.43213 | S18: =Q18/B18 -> 174.20797
A19: =Gen!B24 -> 44544 | B19: 16 | C19: =Gen!V24 -> 0.39349751 | D19: =Gen!T24 -> 1342.22 | E19: =Gen!AK24 -> 194.5 | F19: =Gen!AT24 -> 0 | G19: ='Utility report '!AC19 -> 167 | H19: ='Utility report '!AE19 -> 56 | I19: ='Water-Meter'!E19 -> 78 | J19: ='Lpg (2)'!B23 -> 85 | K19: ='Lpg (2)'!C24 -> 6 | L19: ='Lpg (2)'!D23 -> 0 | M19: ='Lpg (2)'!G23 -> 103.664 | N19: =D19*1.4 -> 1879.108 | O19: =E19*1.4 -> 272.3 | P19: =('Lpg (2)'!G23)*2.38 -> 246.72032 | Q19: =N19+O19+P19 -> 2398.1283 | R19: =N19/B19 -> 117.44425 | S19: =Q19/B19 -> 149.88302
A20: =Gen!B25 -> 44545 | B20: 17 | C20: =Gen!V25 -> 0.41307633 | D20: =Gen!T25 -> 1601.91 | E20: =Gen!AK25 -> 0 | F20: =Gen!AT25 -> 0 | G20: ='Utility report '!AC20 -> 104 | H20: ='Utility report '!AE20 -> 124 | I20: ='Water-Meter'!E20 -> 72 | J20: ='Lpg (2)'!B24 -> 85 | K20: ='Lpg (2)'!C25 -> 5 | L20: ='Lpg (2)'!D24 -> 0 | M20: ='Lpg (2)'!G24 -> 98.428 | N20: =D20*1.4 -> 2242.674 | O20: =E20*1.4 -> 0 | P20: =('Lpg (2)'!G24)*2.38 -> 234.25864 | Q20: =N20+O20+P20 -> 2476.9326 | R20: =N20/B20 -> 131.922 | S20: =Q20/B20 -> 145.70192
A21: =Gen!B26 -> 44546 | B21: 15 | C21: =Gen!V26 -> 0.39082693 | D21: =Gen!T26 -> 1526.57 | E21: =Gen!AK26 -> 176.76 | F21: =Gen!AT26 -> 0 | G21: ='Utility report '!AC21 -> 82 | H21: ='Utility report '!AE21 -> 58 | I21: ='Water-Meter'!E21 -> 73 | J21: ='Lpg (2)'!B25 -> 85 | K21: ='Lpg (2)'!C25 -> 5 | L21: ='Lpg (2)'!D25 -> 0 | M21: ='Lpg (2)'!G25 -> 105.028 | N21: =D21*1.4 -> 2137.198 | O21: =E21*1.4 -> 247.464 | P21: =('Lpg (2)'!G25)*2.38 -> 249.96664 | Q21: =N21+O21+P21 -> 2634.6286 | R21: =N21/B21 -> 142.47987 | S21: =Q21/B21 -> 175.64191
A22: =Gen!B27 -> 44547 | B22: 15 | C22: =Gen!V27 -> 0.40365834 | D22: =Gen!T27 -> 1519.37 | E22: =Gen!AK27 -> 115.53 | F22: =Gen!AT27 -> 0 | G22: ='Utility report '!AC22 -> 7 | H22: ='Utility report '!AE22 -> 54 | I22: ='Water-Meter'!E22 -> 73 | J22: ='Lpg (2)'!B26 -> 85 | K22: ='Lpg (2)'!C26 -> 4 | L22: ='Lpg (2)'!D26 -> 0 | M22: ='Lpg (2)'!G26 -> 101.728 | N22: =D22*1.4 -> 2127.118 | O22: =E22*1.4 -> 161.742 | P22: =('Lpg (2)'!G26)*2.38 -> 242.11264 | Q22: =N22+O22+P22 -> 2530.9726 | R22: =N22/B22 -> 141.80787 | S22: =Q22/B22 -> 168.73151
A23: =Gen!B28 -> 44548 | B23: 13 | C23: =Gen!V28 -> 0.39454405 | D23: =Gen!T28 -> 1531.62 | E23: =Gen!AK28 -> 347 | F23: =Gen!AT28 -> 0 | G23: ='Utility report '!AC23 -> 152 | H23: ='Utility report '!AE23 -> 63 | I23: ='Water-Meter'!E23 -> 85 | J23: ='Lpg (2)'!B27 -> 85 | K23: ='Lpg (2)'!C27 -> 3 | L23: ='Lpg (2)'!D27 -> 0 | M23: ='Lpg (2)'!G27 -> 107.272 | N23: =D23*1.4 -> 2144.268 | O23: =E23*1.4 -> 485.8 | P23: =('Lpg (2)'!G27)*2.38 -> 255.30736 | Q23: =N23+O23+P23 -> 2885.3754 | R23: =N23/B23 -> 164.94369 | S23: =Q23/B23 -> 221.95195
A24: =Gen!B29 -> 44549 | B24: 10 | C24: =Gen!V29 -> 0.42474232 | D24: =Gen!T29 -> 1590.66 | E24: =Gen!AK29 -> 28.9 | F24: =Gen!AT29 -> 0 | G24: ='Utility report '!AC24 -> 168 | H24: ='Utility report '!AE24 -> 62 | I24: ='Water-Meter'!E24 -> 80 | J24: ='Lpg (2)'!B28 -> 85 | K24: ='Lpg (2)'!C28 -> 2 | L24: ='Lpg (2)'!D28 -> 0 | M24: ='Lpg (2)'!G28 -> 94.468 | N24: =D24*1.4 -> 2226.924 | O24: =E24*1.4 -> 40.46 | P24: =('Lpg (2)'!G28)*2.38 -> 224.83384 | Q24: =N24+O24+P24 -> 2492.2178 | R24: =N24/B24 -> 222.6924 | S24: =Q24/B24 -> 249.22178
A25: =Gen!B30 -> 44550 | B25: 6 | C25: =Gen!V30 -> 0.39317777 | D25: =Gen!T30 -> 1280.58 | E25: =Gen!AK30 -> 248.49 | F25: =Gen!AT30 -> 0 | G25: ='Utility report '!AC25 -> 0 | H25: ='Utility report '!AE25 -> 58 | I25: ='Water-Meter'!E25 -> 76 | J25: ='Lpg (2)'!B29 -> 85 | K25: ='Lpg (2)'!C29 -> 1 | L25: ='Lpg (2)'!D29 -> 0 | M25: ='Lpg (2)'!G29 -> 87.868 | N25: =D25*1.4 -> 1792.812 | O25: =E25*1.4 -> 347.886 | P25: =('Lpg (2)'!G29)*2.38 -> 209.12584 | Q25: =N25+O25+P25 -> 2349.8238 | R25: =N25/B25 -> 298.802 | S25: =Q25/B25 -> 391.63731
A26: =Gen!B31 -> 44551 | B26: 9 | C26: =Gen!V31 -> 0.4117842 | D26: =Gen!T31 -> 1850.97 | E26: =Gen!AK31 -> 81 | F26: =Gen!AT31 -> 0 | G26: ='Utility report '!AC26 -> 86 | H26: ='Utility report '!AE26 -> 57 | I26: ='Water-Meter'!E26 -> 69 | J26: ='Lpg (2)'!B30 -> 83 | K26: ='Lpg (2)'!C30 -> 0 | L26: ='Lpg (2)'!D30 -> 0 | M26: ='Lpg (2)'!G30 -> 113.432 | N26: =D26*1.4 -> 2591.358 | O26: =E26*1.4 -> 113.4 | P26: =('Lpg (2)'!G30)*2.38 -> 269.96816 | Q26: =N26+O26+P26 -> 2974.7262 | R26: =N26/B26 -> 287.92867 | S26: =Q26/B26 -> 330.52513
A27: =Gen!B32 -> 44552 | B27: 14 | C27: =Gen!V32 -> 0.42388138 | D27: =Gen!T32 -> 1693.83 | E27: =Gen!AK32 -> 289.43 | F27: =Gen!AT32 -> 0 | G27: ='Utility report '!AC27 -> 100 | H27: ='Utility report '!AE27 -> 60 | I27: ='Water-Meter'!E27 -> 71 | J27: ='Lpg (2)'!B31 -> 81 | K27: ='Lpg (2)'!C31 -> 0 | L27: ='Lpg (2)'!D31 -> 0 | M27: ='Lpg (2)'!G31 -> 114.444 | N27: =D27*1.4 -> 2371.362 | O27: =E27*1.4 -> 405.202 | P27: =('Lpg (2)'!G31)*2.38 -> 272.37672 | Q27: =N27+O27+P27 -> 3048.9407 | R27: =N27/B27 -> 169.383 | S27: =Q27/B27 -> 217.78148
A28: =Gen!B33 -> 44553 | B28: 14 | C28: =Gen!V33 -> 0.40096613 | D28: =Gen!T33 -> 1680.85 | E28: =Gen!AK33 -> 122.64 | F28: =Gen!AT33 -> 0 | G28: ='Utility report '!AC28 -> 95 | H28: ='Utility report '!AE28 -> 59 | I28: ='Water-Meter'!E28 -> 85 | J28: ='Lpg (2)'!B32 -> 78 | K28: ='Lpg (2)'!C32 -> 0 | L28: ='Lpg (2)'!D32 -> 0 | M28: ='Lpg (2)'!G32 -> 114.092 | N28: =D28*1.4 -> 2353.19 | O28: =E28*1.4 -> 171.696 | P28: =('Lpg (2)'!G32)*2.38 -> 271.53896 | Q28: =N28+O28+P28 -> 2796.425 | R28: =N28/B28 -> 168.085 | S28: =Q28/B28 -> 199.74464
A29: =Gen!B34 -> 44554 | B29: 37 | C29: =Gen!V34 -> 0.42705882 | D29: =Gen!T34 -> 2112.66 | E29: =Gen!AK34 -> 0 | F29: =Gen!AT34 -> 0 | G29: ='Utility report '!AC29 -> 134 | H29: ='Utility report '!AE29 -> 58 | I29: ='Water-Meter'!E29 -> 75 | J29: ='Lpg (2)'!B33 -> 75 | K29: ='Lpg (2)'!C33 -> 0 | L29: ='Lpg (2)'!D33 -> 0 | M29: ='Lpg (2)'!G33 -> 117.92 | N29: =D29*1.4 -> 2957.724 | O29: =E29*1.4 -> 0 | P29: =('Lpg (2)'!G33)*2.38 -> 280.6496 | Q29: =N29+O29+P29 -> 3238.3736 | R29: =N29/B29 -> 79.938486 | S29: =Q29/B29 -> 87.523611
A30: =Gen!B35 -> 44555 | B30: 46 | C30: =Gen!V35 -> 0.40786862 | D30: =Gen!T35 -> 2005.49 | E30: =Gen!AK35 -> 35.2 | F30: =Gen!AT35 -> 0 | G30: ='Utility report '!AC30 -> 85 | H30: ='Utility report '!AE30 -> 57 | I30: ='Water-Meter'!E30 -> 102 | J30: ='Lpg (2)'!B34 -> 72 | K30: ='Lpg (2)'!C34 -> 0 | L30: ='Lpg (2)'!D34 -> 0 | M30: ='Lpg (2)'!G34 -> 129.404 | N30: =D30*1.4 -> 2807.686 | O30: =E30*1.4 -> 49.28 | P30: =('Lpg (2)'!G34)*2.38 -> 307.98152 | Q30: =N30+O30+P30 -> 3164.9475 | R30: =N30/B30 -> 61.036652 | S30: =Q30/B30 -> 68.803207
A31: =Gen!B36 -> 44556 | B31: 35 | C31: =Gen!V36 -> 0.43874595 | D31: =Gen!T36 -> 2169.16 | E31: =Gen!AK36 -> 280.98 | F31: =Gen!AT36 -> 0 | G31: ='Utility report '!AC31 -> 48 | H31: ='Utility report '!AE31 -> 50 | I31: ='Water-Meter'!E31 -> 106 | J31: ='Lpg (2)'!B35 -> 68 | K31: ='Lpg (2)'!C35 -> 0 | L31: ='Lpg (2)'!D35 -> 0 | M31: ='Lpg (2)'!G35 -> 115.764 | N31: =D31*1.4 -> 3036.824 | O31: =E31*1.4 -> 393.372 | P31: =('Lpg (2)'!G35)*2.38 -> 275.51832 | Q31: =N31+O31+P31 -> 3705.7143 | R31: =N31/B31 -> 86.7664 | S31: =Q31/B31 -> 105.87755
A32: =Gen!B37 -> 44557 | B32: 31 | C32: =Gen!V37 -> 0.405758 | D32: =Gen!T37 -> 2028.79 | E32: =Gen!AK37 -> 49.66 | F32: =Gen!AT37 -> 0 | G32: ='Utility report '!AC32 -> 135 | H32: ='Utility report '!AE32 -> 63 | I32: ='Water-Meter'!E32 -> 102 | J32: ='Lpg (2)'!B36 -> 66 | K32: ='Lpg (2)'!C36 -> 0 | L32: ='Lpg (2)'!D36 -> 0 | M32: ='Lpg (2)'!G36 -> 127.336 | N32: =D32*1.4 -> 2840.306 | O32: =E32*1.4 -> 69.524 | P32: =('Lpg (2)'!G36)*2.38 -> 303.05968 | Q32: =N32+O32+P32 -> 3212.8897 | R32: =N32/B32 -> 91.622774 | S32: =Q32/B32 -> 103.6416
... A36: =Gen!B41 -> 44561 | B36: 48 | C36: =Gen!V41 -> 0.41520824 | D36: =Gen!T41 -> 1894.18 | E36: =Gen!AK41 -> 882.87 | F36: =Gen!AT41 -> 0 | G36: ='Utility report '!AC36 -> 156 | H36: ='Utility report '!AE36 -> 51 | I36: ='Water-Meter'!E36 -> 102 | J36: ='Lpg (2)'!B40 -> 53 | K36: ='Lpg (2)'!C40 -> 0 | L36: ='Lpg (2)'!D40 -> 0 | M36: ='Lpg (2)'!G40 -> 163.02 | N36: =D36*1.4 -> 2651.852 | O36: =E36*1.4 -> 1236.018 | P36: =('Lpg (2)'!G40)*2.38 -> 387.9876 | Q36: =N36+O36+P36 -> 4275.8576 | R36: =N36/B36 -> 55.246917 | S36: =Q36/B36 -> 89.080367
B37: ='Summery Report'!E36 -> 0 | C37: =Gen!V42 -> 0 | D37: =Gen!T42 -> 0 | E37: =Gen!AK42 -> 0 | F37: =Gen!AT42 -> 0 | G37: ='Utility report '!AC37 -> -21907 | H37: ='Utility report '!AE37 -> -228878 | I37: ='Water-Meter'!E37 -> 120 | J37: ='Lpg (2)'!#REF! -> #REF! | K37: ='Lpg (2)'!#REF! -> #REF! | L37: ='Lpg (2)'!#REF! -> #REF! | M37: ='Lpg (2)'!#REF! -> #REF! | Q37: =N37+O37+P37 -> 0 | R37: =N37/B37 -> #DIV/0! | S37: =Q37/B37 -> #DIV/0!
R38: =N38/B38 -> #DIV/0!
A39: Total | B39: =SUM(B7:B37) -> 563 | C39: =SUM(C7:C35) -> 11.84318 | D39: =SUM(D7:D35) -> 46573.2 | E39: =SUM(E7:E35) -> 4205.28 | F39: =SUM(F7:F35) -> 0 | G39: =SUM(G7:G35) -> 2684 | H39: =SUM(H7:H35) -> 1764 | I39: =SUM(I7:I35) -> 2299 | J39: =SUM(J7:J35) -> 2318 | ... S39: =SUM(S7:S35) -> 6374.9399

Sheet Sheet4

Sheet Gen
E2: =B11 -> 44531
G6: BILILA LODGE INVESTMENT LIMITED | W6: 1 | X6: 2 | Y6: 3 | Z6: 4 | AA6: 5 | AB6: 6 | AC6: 7 | AD6: 8 | AE6: 9 | AF6: 10 | AG6: 11
G7: Diesel Consumed by 500KVA Generator | N7: 500KVA Generator KWh | W7: Safari-STAFF | X7: Safari-STAFF | Y7: Lc/swg/gust | Z7: Eng pikcup | AA7: VIP Safari Car | AB7: GX Guest | AC7: GX Guest | AD7: T/Hillux/pur | AE7: TATA | AF7: MAN | AG7: F/Truck | AH7: Incenerator | AI7: A&K | AJ7: OTHER | AK7: TOTAL CO
B8: Date | C8: Occupancy % | D8: OPENING | E8: Received | F8: Schedule delivery | G8: Company | H8: 1 | I8: 2 | J8: 3 | K8: 4 | L8: 5 | M8: 6 | N8: 1 | O8: 2 | P8: 3 | Q8: 4 | R8: 5 | S8: 6 | T8: Total Diseal Consumed | U8: Total Kwh generated | V8: Average Diesel/Kwh | W8: T 128 AXJ | X8: T 134 AXJ | Y8: T 499 AXG | Z8: T 217 CHV | AA8: T 214 CHV | AB8: T 139 AXE | AC8: T 242 AXN | AD8: T 476 AWZ | AE8: T 226 AUQ | AF8: T 308 CLD | AG8: T 852 AWU | AH8: Machine ENG | AI8: Vehicle | AJ8: Vehicle | AS8: Total Diseal Consumed Gen & Vehicle | AT8: Total cost /Day (TSH) | AU8: BALANCE
D9: 43219.56 | T9: =SUM(G9:M9) -> 0 | AS9: =SUM(AK9+T9) -> 0 | AT9: =AS21*AV21 -> 0
T10: =SUM(G10:M10) -> 0 | U10: =SUM(N10:S10) -> 0 | AK10: =SUM(W10:AJ10) -> 0 | AS10: =SUM(AK10+T10) -> 0 | AT10: =AS10*AV10 -> 0
B11: 44531 | C11: 0.0519 | D11: =SUM(D9+E11) -> 43219.56 | H11: 711.06 | K11: 193.22 | L11: 436.41 | N11: 1709 | Q11: 380 | R11: 1041 | T11: =SUM(H11:M11) -> 1340.69 | U11: =SUM(N11:S11) -> 3130 | V11: =T11/U11 -> 0.42833546 | Y11: 19.9 | AB11: 35.41 | AK11: =SUM(W11:AJ11) -> 55.31 | AS11: =SUM(AK11+T11) -> 1396 | AT11: =AS11*AV11 -> 0 | AU11: =D11 -> 43219.56 | AX11: =AV11*T11 -> 0
B12: 44532 | C12: 0.05 | D12: =SUM(D11-AS11+E12) -> 41823.56 | K12: 245.53 | L12: 401.03 | M12: 622.25 | Q12: 555 | R12: 969 | S12: 1581 | T12: =SUM(H12:M12) -> 1268.81 | U12: =SUM(N12:S12) -> 3105 | V12: =T12/U12 -> 0.40863446 | Y12: 28.89 | Z12: 77.18 | AE12: 225.16 | AF12: 264.81 | AK12: =SUM(W12:AJ12) -> 596.04 | AS12: =SUM(AK12+T12) -> 1864.85 | AT12: =AS12*AV12 -> 0 | AU12: =D12 -> 41823.56 | AX12: =AV12*T12 -> 0
B13: 44533 | C13: 0.05 | D13: =SUM(D12-AS12+E13) -> 39958.71 | H13: 728.96 | L13: 448.21 | N13: 1834 | R13: 1076 | T13: =SUM(H13:M13) -> 1177.17 | U13: =SUM(N13:S13) -> 2910 | V13: =T13/U13 -> 0.40452577 | AK13: =SUM(W13:AJ13) -> 0 | AS13: =SUM(AK13+T13) -> 1177.17 | AT13: =AS13*AV13 -> 0 | AU13: =D13 -> 39958.71 | AX13: =AV13*T13 -> 0
B14: 44534 | C14: 0.08 | D14: =SUM(D13-AS13+E14) -> 38781.54 | L14: 471.12 | M14: 822.1 | R14: 1145 | S14: 2144 | T14: =SUM(H14:M14) -> 1293.22 | U14: =SUM(N14:S14) -> 3289 | V14: =T14/U14 -> 0.3931955 | W14: 81.57 | Y14: 23.7 | AA14: 94.24 | AK14: =SUM(W14:AJ14) -> 199.51 | AS14: =SUM(AK14+T14) -> 1492.73 | AT14: =AS14*AV14 -> 0 | AU14: =D14 -> 38781.54 | AX14: =AV14*T14 -> 0
B15: 44535 | C15: 0.05 | D15: =SUM(D14-AS14+E15) -> 37288.81 | H15: 854.96 | L15: 391.97 | N15: 2161 | R15: 985 | T15: =SUM(H15:M15) -> 1246.93 | U15: =SUM(N15:S15) -> 3146 | V15: =T15/U15 -> 0.3963541 | Y15: 29.5 | AA15: 23.83 | AK15: =SUM(W15:AJ15) -> 53.33 | AS15: =SUM(AK15+T15) -> 1300.26 | AT15: =AS15*AV15 -> 0 | AU15: =D15 -> 37288.81 | AX15: =AV15*T15 -> 0
B16: 44536 | C16: 0.0779 | D16: =SUM(D15-AS15+E16) -> 35988.55 | L16: 486.81 | M16: 839.08 | R16: 1191 | S16: 2170 | T16: =SUM(H16:M16) -> 1325.89 | U16: =SUM(N16:S16) -> 3361 | V16: =T16/U16 -> 0.39449271 | W16: 67.4 | AK16: =SUM(W16:AJ16) -> 67.4 | AS16: =SUM(AK16+T16) -> 1393.29 | AT16: =AS16*AV16 -> 0 | AU16: =D16 -> 35988.55 | AX16: =AV16*T16 -> 0
B17: 44537 | C17: 0.0779 | D17: =SUM(D16-AS16+E17) -> 34595.26 | F17: 18000 | G17: PUMA | H17: 906.64 | L17: 462.3 | N17: 2209 | R17: 1171 | T17: =SUM(H17:M17) -> 1368.94 | U17: =SUM(N17:S17) -> 3380 | V17: =T17/U17 -> 0.40501183 | Y17: 19.74 | AA17: 27.2 | AI17: 89 | AK17: =SUM(W17:AJ17) -> 135.94 | AS17: =SUM(AK17+T17) -> 1504.88 | AT17: =AS17*AV17 -> 0 | AU17: =D17 -> 34595.26 | AX17: =AV17*T17 -> 0
B18: 44538 | C18: 0.12 | D18: =SUM(D17-AS17+E18) -> 33090.38 | K18: 622.72 | M18: 904.88 | Q18: 1282 | S18: 2380 | T18: =SUM(H18:M18) -> 1527.6 | U18: =SUM(N18:S18) -> 3662 | V18: =T18/U18 -> 0.4171491 | Y18: 9.44 | AA18: 74.15 | AK18: =SUM(W18:AJ18) -> 83.59 | AS18: =SUM(AK18+T18) -> 1611.19 | AT18: =AS18*AV18 -> 0 | AU18: =D18 -> 33090.38 | AX18: =AV18*T18 -> 0
B19: 44539 | C19: 0.09 | D19: =SUM(D18-AS18+E19) -> 31479.19 | H19: 869.94 | K19: 501.72 | N19: 2189 | Q19: 1210 | T19: =SUM(H19:M19) -> 1371.66 | U19: =SUM(N19:S19) -> 3399 | V19: =T19/U19 -> 0.4035481 | Y19: 51.98 | AK19: =SUM(W19:AJ19) -> 51.98 | AS19: =SUM(AK19+T19) -> 1423.64 | AT19: =AS19*AV19 -> 0 | AU19: =D19 -> 31479.19 | AX19: =AV19*T19 -> 0
B20: 44540 | C20: 0.12 | D20: =SUM(D19-AS19+E20) -> 30055.55 | L20: 474.74 | M20: 872.59 | R20: 1182 | S20: 2258 | T20: =SUM(H20:M20) -> 1347.33 | U20: =SUM(N20:S20) -> 3440 | V20: =T20/U20 -> 0.3916657 | Y20: 23.35 | AA20: 39.3 | AI20: 279 | AJ20: 107 | AK20: =SUM(W20:AJ20) -> 448.65 | AS20: =SUM(AK20+T20) -> 1795.98 | AT20: =AS20*AV20 -> 0 | AU20: =D20 -> 30055.55 | AX20: =AV20*T20 -> 0
B21: 44541 | C21: 0.12 | D21: =SUM(D20-AS20+E21) -> 28259.57 | H21: 783.8 | K21: 728.99 | N21: 1945 | Q21: 1751 | T21: =SUM(H21:M21) -> 1512.79 | U21: =SUM(N21:S21) -> 3696 | V21: =T21/U21 -> 0.40930465 | AA21: 37.87 | AK21: =SUM(W21:AJ21) -> 37.87 | AS21: =SUM(AK21+T21) -> 1550.66 | AT21: =AS21*AV21 -> 0 | AU21: =D21 -> 28259.57 | AX21: =AV21*T21 -> 0
B22: 44542 | C22: 0.12 | D22: =SUM(D21-AS21+E22) -> 26708.91 | K22: 511.98 | M22: 973.26 | Q22: 1249 | S22: 2397 | T22: =SUM(H22:M22) -> 1485.24 | U22: =SUM(N22:S22) -> 3646 | V22: =T22/U22 -> 0.40736149 | AA22: 68.16 | AK22: =SUM(W22:AJ22) -> 68.16 | AS22: =SUM(AK22+T22) -> 1553.4 | AT22: =AS22*AV22 -> 0 | AU22: =D22 -> 26708.91 | AX22: =AV22*T22 -> 0
B23: 44543 | C23: 0.16 | D23: =SUM(D22-AS22+E23) -> 25155.51 | H23: 797.57 | K23: 522 | L23: 260.06 | N23: 2079 | Q23: 1317 | R23: 571 | T23: =SUM(H23:M23) -> 1579.63 | U23: =SUM(N23:S23) -> 3967 | V23: =T23/U23 -> 0.39819259 | Y23: 12.93 | AB23: 90.32 | AK23: =SUM(W23:AJ23) -> 103.25 | AS23: =SUM(AK23+T23) -> 1682.88 | AT23: =AS23*AV23 -> 0 | AU23: =D23 -> 25155.51 | AX23: =AV23*T23 -> 0
B24: 44544 | C24: 0.17 | D24: =SUM(D23-AS23+E24) -> 41472.63 | E24: 18000 | K24: 470.7 | M24: 871.52 | Q24: 1152 | S24: 2259 | T24: =SUM(H24:M24) -> 1342.22 | U24: =SUM(N24:S24) -> 3411 | V24: =T24/U24 -> 0.39349751 | AA24: 56.5 | AI24: 138 | AK24: =SUM(W24:AJ24) -> 194.5 | AS24: =SUM(AK24+T24) -> 1536.72 | AT24: =AS24*AV24 -> 0 | AU24: =D24 -> 41472.63 | AX24: =AV24*T24 -> 0
B25: 44545 | C25: 0.18 | D25: =SUM(D24-AS24+E25) -> 39935.91 | H25: 720.56 | K25: 479.27 | L25: 402.08 | N25: 1798 | Q25: 1185 | R25: 895 | T25: =SUM(H25:M25) -> 1601.91 | U25: =SUM(N25:S25) -> 3878 | V25: =T25/U25 -> 0.41307633 | AK25: =SUM(W25:AJ25) -> 0 | AS25: =SUM(AK25+T25) -> 1601.91 | AT25: =AS25*AV25 -> 0 | AU25: =D25 -> 39935.91 | AX25: =AV25*T25 -> 0
B26: 44546 | C26: 0.16 | D26: =SUM(D25-AS25+E26) -> 38334 | H26: 81 | K26: 477.78 | M26: 967.79 | N26: 117 | Q26: 1200 | S26: 2589 | T26: =SUM(H26:M26) -> 1526.57 | U26: =SUM(N26:S26) -> 3906 | V26: =T26/U26 -> 0.39082693 | X26: 114.28 | AD26: 62.48 | AK26: =SUM(W26:AJ26) -> 176.76 | AS26: =SUM(AK26+T26) -> 1703.33 | AT26: =AS26*AV26 -> 0 | AU26: =D26 -> 38334 | AX26: =AV26*T26 -> 0
B27: 44547 | C27: 0.16 | D27: =SUM(D26-AS26+E27) -> 51630.67 | E27: 15000 | F27: 15000 | G27: PUMA | H27: 1024.79 | L27: 494.58 | N27: 2549 | R27: 1215 | T27: =SUM(H27:M27) -> 1519.37 | U27: =SUM(N27:S27) -> 3764 | V27: =T27/U27 -> 0.40365834 | X27: 26 | Y27: 35.53 | AI27: 54 | AK27: =SUM(W27:AJ27) -> 115.53 | AS27: =SUM(AK27+T27) -> 1634.9 | AT27: =AS27*AV27 -> 0 | AU27: =D27 -> 51630.67 | AX27: =AV27*T27 -> 0
B28: 44548 | C28: 0.13 | D28: =SUM(D27-AS27+E28) -> 49995.77 | K28: 527.07 | M28: 1004.55 | Q28: 1313 | S28: 2569 | T28: =SUM(H28:M28) -> 1531.62 | U28: =SUM(N28:S28) -> 3882 | V28: =T28/U28 -> 0.39454405 | AI28: 226 | AJ28: 121 | AK28: =SUM(W28:AJ28) -> 347 | AS28: =SUM(AK28+T28) -> 1878.62 | AT28: =AS28*AV28 -> 0 | AU28: =D28 -> 49995.77 | AX28: =AV28*T28 -> 0
B29: 44549 | C29: 0.12 | D29: =SUM(D28-AS28+E29) -> 48117.15 | H29: 600.36 | K29: 742.28 | M29: 248.02 | N29: 1429 | Q29: 1797 | S29: 519 | T29: =SUM(H29:M29) -> 1590.66 | U29: =SUM(N29:S29) -> 3745 | V29: =T29/U29 -> 0.42474232 | AD29: 28.9 | AK29: =SUM(W29:AJ29) -> 28.9 | AS29: =SUM(AK29+T29) -> 1619.56 | AT29: =AS29*AV29 -> 0 | AU29: =D29 -> 48117.15 | AX29: =AV29*T29 -> 0
B30: 44550 | C30: 0.06 | D30: =SUM(D29-AS29+E30) -> 46497.59 | K30: 478.01 | M30: 802.57 | Q30: 1182 | S30: 2075 | T30: =SUM(H30:M30) -> 1280.58 | U30: =SUM(N30:S30) -> 3257 | V30: =T30/U30 -> 0.39317777 | Y30: 37.14 | AA30: 120.35 | AI30: 91 | AK30: =SUM(W30:AJ30) -> 248.49 | AS30: =SUM(AK30+T30) -> 1529.07 | AT30: =AS30*AV30 -> 0 | AU30: =D30 -> 46497.59 | AX30: =AV30*T30 -> 0
B31: 44551 | C31: 0.1 | D31: =SUM(D30-AS30+E31) -> 44968.52 | H31: 412.99 | K31: 465.43 | L31: 972.55 | N31: 954 | Q31: 1151 | R31: 2390 | T31: =SUM(H31:M31) -> 1850.97 | U31: =SUM(N31:S31) -> 4495 | V31: =T31/U31 -> 0.4117842 | AI31: 81 | AK31: =SUM(W31:AJ31) -> 81 | AS31: =SUM(AK31+T31) -> 1931.97 | AT31: =AS31*AV31 -> 0 | AU31: =D31 -> 44968.52 | AX31: =AV31*T31 -> 0
B32: 44552 | C32: 0.17 | D32: =SUM(D31-AS31+E32) -> 43036.55 | K32: 554.03 | L32: 527.81 | M32: 611.99 | Q32: 1252 | R32: 1268 | S32: 1476 | T32: =SUM(H32:M32) -> 1693.83 | U32: =SUM(N32:S32) -> 3996 | V32: =T32/U32 -> 0.42388138 | Y32: 35.35 | Z32: 46.66 | AA32: 97.42 | AI32: 110 | AK32: =SUM(W32:AJ32) -> 289.43 | AS32: =SUM(AK32+T32) -> 1983.26 | AT32: =AS32*AV32 -> 0 | AU32: =D32 -> 43036.55 | AX32: =AV32*T32 -> 0
B33: 44553 | C33: 0.17 | D33: =SUM(D32-AS32+E33) -> 41053.29 | H33: 730.5 | K33: 486.8 | L33: 463.55 | N33: 1800 | Q33: 1168 | R33: 1224 | T33: =SUM(H33:M33) -> 1680.85 | U33: =SUM(N33:S33) -> 4192 | V33: =T33/U33 -> 0.40096613 | Y33: 54.53 | AA33: 68.11 | AK33: =SUM(W33:AJ33) -> 122.64 | AS33: =SUM(AK33+T33) -> 1803.49 | AT33: =AS33*AV33 -> 0 | AU33: =D33 -> 41053.29 | AX33: =AV33*T33 -> 0
B34: 44554 | C34: 0.47 | D34: =SUM(D33-AS33+E34) -> 39249.8 | H34: 683.76 | L34: 652.39 | M34: 776.51 | N34: 1603 | R34: 1404 | S34: 1940 | T34: =SUM(H34:M34) -> 2112.66 | U34: =SUM(N34:S34) -> 4947 | V34: =T34/U34 -> 0.42705882 | AK34: =SUM(W34:AJ34) -> 0 | AS34: =SUM(AK34+T34) -> 2112.66 | AT34: =AS34*AV34 -> 0 | AU34: =D34 -> 39249.8 | AX34: =AV34*T34 -> 0
B35: 44555 | C35: 0.58 | D35: =SUM(D34-AS34+E35) -> 37137.14 | H35: 663.02 | K35: 688.71 | L35: 653.76 | N35: 1648 | Q35: 1628 | R35: 1641 | T35: =SUM(H35:M35) -> 2005.49 | U35: =SUM(N35:S35) -> 4917 | V35: =T35/U35 -> 0.40786862 | AA35: 35.2 | AK35: =SUM(W35:AJ35) -> 35.2 | AS35: =SUM(AK35+T35) -> 2040.69 | AT35: =AS35*AV35 -> 0 | AU35: =D35 -> 37137.14 | AX35: =AV35*T35 -> 0
B36: 44556 | C36: 0.43 | D36: =SUM(D35-AS35+E36) -> 35096.45 | K36: 909 | L36: 494.47 | M36: 765.69 | Q36: 1895 | R36: 1254 | S36: 1795 | T36: =SUM(H36:M36) -> 2169.16 | U36: =SUM(N36:S36) -> 4944 | V36: =T36/U36 -> 0.43874595 | W36: 80.44 | AA36: 71.54 | AI36: 129 | AK36: =SUM(W36:AJ36) -> 280.98 | AS36: =SUM(AK36+T36) -> 2450.14 | AT36: =AS36*AV36 -> 0 | AU36: =D36 -> 35096.45 | AX36: =AV36*T36 -> 0
B37: 44557 | C37: 0.39 | D37: =SUM(D36-AS36+E37) -> 32646.31 | H37: 734.5 | K37: 734.27 | L37: 560.02 | N37: 1732 | Q37: 1851 | R37: 1417 | T37: =SUM(H37:M37) -> 2028.79 | U37: =SUM(N37:S37) -> 5000 | V37: =T37/U37 -> 0.405758 | X37: 47.66 | AA37: 2 | AK37: =SUM(W37:AJ37) -> 49.66 | AS37: =SUM(AK37+T37) -> 2078.45 | AT37: =AS37*AV37 -> 0 | AU37: =D37 -> 32646.31 | AX37: =AV37*T37 -> 0
B38: 44558 | C38: 0.43 | D38: =SUM(D37-AS37+E38) -> 30567.86 | F38: 18000 | G38: RAHA | K38: 705.16 | L38: 473.93 | M38: 874.5 | Q38: 1500 | R38: 1197 | S38: 1979 | T38: =SUM(H38:M38) -> 2053.59 | U38: =SUM(N38:S38) -> 4676 | V38: =T38/U38 -> 0.43917665 | X38: 36.43 | Y38: 33.06 | AI38: 117 | AK38: =SUM(W38:AJ38) -> 186.49 | AS38: =SUM(AK38+T38) -> 2240.08 | AT38: =AS38*AV38 -> 0 | AU38: =D38 -> 30567.86 | AX38: =AV38*T38 -> 0
B39: 44559 | C39: 0.53 | D39: =SUM(D38-AS38+E39) -> 46327.78 | E39: 18000 | H39: 762.29 | L39: 552.72 | M39: 724.94 | N39: 1863 | R39: 1415 | S39: 1614 | T39: =SUM(H39:M39) -> 2039.95 | U39: =SUM(N39:S39) -> 4892 | V39: =T39/U39 -> 0.41699714 | Z39: 84.83 | AA39: 81.29 | AJ39: 70 | AK39: =SUM(W39:AJ39) -> 236.12 | AS39: =SUM(AK39+T39) -> 2276.07 | AT39: =AS39*AV39 -> 0 | AU39: =D39 -> 46327.78 | AX39: =AV39*T39 -> 0
B40: 44560 | C40: 0.61 | D40: =SUM(D39-AS39+E40) -> 44051.71 | H40: 805.54 | K40: 748.95 | L40: 485.28 | N40: 1816 | Q40: 1761 | R40: 1189 | T40: =SUM(H40:M40) -> 2039.77 | U40: =SUM(N40:S40) -> 4766 | V40: =T40/U40 -> 0.42798363 | Y40: 34.26 | AK40: =SUM(W40:AJ40) -> 34.26 | AS40: =SUM(AK40+T40) -> 2074.03 | AT40: =AS40*AV40 -> 0 | AU40: =D40 -> 44051.71 | AX40: =AV40*T40 -> 0
B41: 44561 | C41: 0.61 | D41: =SUM(D40-AS40+E41) -> 41977.68 | K41: 714.11 | L41: 553.88 | M41: 626.19 | Q41: 1681 | R41: 1403 | S41: 1478 | T41: =SUM(G41:M41) -> 1894.18 | U41: =SUM(N41:S41) -> 4562 | V41: =T41/U41 -> 0.41520824 | W41: 78.63 | X41: 54.24 | AI41: 750 | AK41: =SUM(W41:AJ41) -> 882.87 | AS41: =SUM(AK41+T41) -> 2777.05 | AT41: =AS41*AV41 -> 0 | AU41: =D41 -> 41977.68 | AX41: =SUM(AX11:AX40) -> 0
D42: =SUM(D41-AS41+E42) -> 39200.63 | T42: =SUM(G42:M42) -> 0 | U42: =SUM(N42:S42) -> 0 | AK42: =SUM(W42:AJ42) -> 0 | AS42: =SUM(AK42+T42) -> 0 | AT42: =AS42*AV42 -> 0 | AU42: =D42 -> 39200.63
B43: BF | D43: =SUM(D42-AS42+E43) -> 39200.63 | T43: =SUM(G43:M43) -> 0 | U43: =SUM(N43:S43) -> 0 | AK43: =SUM(W43:AJ43) -> 0 | AS43: =SUM(AK43+T43) -> 0 | AT43: =AS43*AV43 -> 0 | AU43: =D43 -> 39200.63
T44: =SUM(G44:M44) -> 0 | U44: =SUM(N44:S44) -> 0 | AK44: =SUM(W44:AJ44) -> 0 | AS44: =T44+AK44 -> 0 | AT44: =AS44*AV44 -> 0
E45: =SUM(E11:E44) -> 51000 | F45: =SUM(F11:F42) -> 51000 | G45: =SUM(G12:G44) -> 0 | H45: =SUM(H11:H44) -> 12872.24 | I45: =SUM(I11:I44) -> 0 | J45: =SUM(J11:J44) -> 0 | K45: =SUM(K11:K44) -> 12507.73 | L45: =SUM(L11:L44) -> 11119.67 | M45: =SUM(M11:M44) -> 13308.43 | N45: =SUM(N11:N44) -> 31435 | O45: =SUM(O11:O44) -> 0 | P45: =SUM(P11:P44) -> 0 | Q45: =SUM(Q11:Q43) -> 29460 | R45: =SUM(R11:R44) -> 27243 | S45: =SUM(S11:S44) -> 33223 | T45: =SUM(H45:M45) -> 49808.07 | U45: =SUM(N45:S45) -> 121361 | V45: =SUM(V11:V42) -> 12.686724 | W45: =SUM(W9:W44) -> 308.04 | X45: =SUM(X9:X44) -> 278.61 | Y45: =SUM(Y9:Y44) -> 449.3 | Z45: =SUM(Z9:Z44) -> 208.67 | AA45: =SUM(AA9:AA44) -> 897.16 | AB45: =SUM(AB9:AB44) -> 125.73 | AC45: =SUM(AC9:AC44) -> 0 | AD45: =SUM(AD10:AD44) -> 91.38 | AE45: =SUM(AE10:AE44) -> 225.16 | AF45: =SUM(AF9:AF44) -> 264.81 | AG45: =SUM(AG9:AG44) -> 0 | AH45: =SUM(AH9:AH44) -> 0 | AI45: =SUM(AI9:AI43) -> 2064 | AJ45: =SUM(AJ9:AJ39) -> 298 | AK45: =SUM(AK9:AK44) -> 5210.86 | AS45: =SUM(AS11:AS43) -> 55018.93 | AT45: =SUM(AT11:AT44) -> 0
B46: Nb Day | N46: =H45/N45 -> 0.40948751 | Q46: =K45/Q45 -> 0.42456653 | R46: =L45/R45 -> 0.40816613 | S46: =M45/S45 -> 0.40057882 | V46: =T45/U45 -> 0.41041249
C47: =AVERAGE(C11:C40) -> 0.20092333 | U47: =T45*2475 -> 1.2327497e+08 | V47: TZS | AS47: =AS45*2143 -> 1.1790557e+08 | AT47: TZS
B48: Av. Occ | U48: =U47/2289 -> 53855.384 | V48: USD | AS48: =AS47/2289 -> 51509.64 | AT48: USD
C50: A & K VEHICLES | I50: MAULY VEHICLES | O50: GREEN LAND VEHICLES | U50: OTHERS VEHICLES
C51: Date | D51: Vehicles | E51: Liters | F51: Driver name | G51: Authority manager | I51: Date | J51: Vehicles | K51: Liters | L51: Driver name | M51: Authority manager | O51: Date | P51: Vehicles | Q51: Liters | R51: Driver name | S51: Authorized Manager | U51: Date | V51: Vehicles | W51: Liters | X51: Driver name | Y51: Athorized Manager | Z51: Reasons
C52: 44389 | D52: T840DDW | E52: 89 | F52: Donald | G52: Huruma | O52: 44481 | P52: T726DCD | Q52: 107 | R52: Jafari | S52: Huruma
C53: 44481 | D53: T391DQR | E53: 147 | F53: Joseph | G53: Huruma | O53: 18/1282021 | P53: T827CuD | Q53: 70 | R53: Charles | S53: Huruma
C54: 44481 | D54: T106CWQ | E54: 132 | F54: Andason | G54: Huruma | O54: 18/12/2021 | P54: T662CZG | Q54: 51 | R54: Michael | S54: Huruma
C55: 14/12/2021 | D55: T840DDW | E55: 138 | F55: Donald | G55: Huruma | O55: 29/12/2021 | P55: T726DCD | Q55: 70 | R55: Jafari | S55: Huruma
C56: 17/12/2021 | D56: T882DKQ | E56: 54 | F56: Herman | G56: Huruma
C57: 18/12/2021 | D57: T106CWQ | E57: 96 | F57: Andason | G57: Huruma
C58: 18/12/2021 | D58: T111CWQ | E58: 130 | F58: Mushi | G58: Huruma
C59: 20/12/2021 | D59: T111CWQ | E59: 29 | F59: George | G59: Huruma
C60: 20/12/2021 | D60: T132CWQ | E60: 62 | F60: Jeremia | G60: Huruma
C61: 21/12/2021 | D61: T880DKQ | E61: 81 | F61: Priscus | G61: Huruma
C62: 22/12/2021 | D62: T391DQR | E62: 110 | F62: Joseph | G62: Huruma
C63: 26/12/2021 | D63: T880DKQ | E63: 129 | F63: Priscus | G63: Huruma
C64: 28/12/2021 | D64: T840DDW | E64: 117 | F64: Dickson | G64: Huruma
C65: 31/12/2021 | D65: T840DDW | E65: 86 | F65: Dickson | G65: Huruma
C66: 31/12/2021 | D66: T132CWQ | E66: 96 | F66: Herman | G66: Huruma
C67: 31/12/2021 | D67: T111CWQ | E67: 119 | F67: Richard | G67: huruma
... C73: 31/12/2021 | D73: T880DKQ | E73: 62 | F73: Priscus | G73: Huruma

Sheet Lpg (2)
C3: Four Sasons Safari Lodge Serengeti
G6: VALUE | H6: Cost
A7: DATE | B7: A | C7: B | D7: C | F7: Meter Reading | G7: Total | H7: Occu | I7: No.of | J7: Kg
B8: 2Ton% | C8: 1Ton (%) | D8: 1Ton% | F8: consumption | G8: Consumption Kg | H8: % | I8: pax | J8: per pax
F9: 81529.71
A10: =Gen!B11 -> 44531 | B10: 85 | C10: 84 | D10: 0 | F10: 81552.72 | G10: =(F10-F9)*4.4 -> 101.244 | H10: =Gen!C11 -> 0.0519 | I10: 10 | J10: =SUM(G10/I10) -> 10.1244
A11: =Gen!B12 -> 44532 | B11: 85 | C11: 80 | D11: 0 | F11: 81568.7 | G11: =(F11-F10)*4.4 -> 70.312 | H11: =Gen!C12 -> 0.05 | I11: 9 | J11: =SUM(G11/I11) -> 7.8124444
A12: =Gen!B13 -> 44533 | B12: 85 | C12: 74 | D12: 0 | F12: 81582.24 | G12: =(F12-F11)*4.4 -> 59.576 | H12: =Gen!C13 -> 0.05 | I12: 10 | J12: =SUM(G12/I12) -> 5.9576
A13: =Gen!B14 -> 44534 | B13: 85 | C13: 65 | D13: 0 | F13: 81596.22 | G13: =(F13-F12)*4.4 -> 61.512 | H13: =Gen!C14 -> 0.08 | I13: 16 | J13: =SUM(G13/I13) -> 3.8445
A14: =Gen!B15 -> 44535 | B14: 85 | C14: 55 | D14: 0 | F14: 81616.07 | G14: =(F14-F13)*4.4 -> 87.34 | H14: =Gen!C15 -> 0.05 | I14: 12 | J14: =SUM(G14/I14) -> 7.2783333
A15: =Gen!B16 -> 44536 | B15: 85 | C15: 50 | D15: 0 | F15: 81640.5 | G15: =(F15-F14)*4.4 -> 107.492 | H15: =Gen!C16 -> 0.0779 | I15: 17 | J15: =SUM(G15/I15) -> 6.3230588
A16: =Gen!B17 -> 44537 | B16: 85 | C16: 45 | D16: 0 | F16: 81661.11 | G16: =(F16-F15)*4.4 -> 90.684 | H16: =Gen!C17 -> 0.0779 | I16: 15 | J16: =SUM(G16/I16) -> 6.0456
A17: =Gen!B18 -> 44538 | B17: 85 | C17: 40 | D17: 0 | F17: 81683.81 | G17: =(F17-F16)*4.4 -> 99.88 | H17: =Gen!C18 -> 0.12 | I17: 23 | J17: =SUM(G17/I17) -> 4.3426087
A18: =Gen!B19 -> 44539 | B18: 85 | C18: 35 | D18: 0 | F18: 81708.58 | G18: =(F18-F17)*4.4 -> 108.988 | H18: =Gen!C19 -> 0.09 | I18: 19 | J18: =SUM(G18/I18) -> 5.7362105
A19: =Gen!B20 -> 44540 | B19: 85 | C19: 30 | D19: 0 | F19: 81733.58 | G19: =(F19-F18)*4.4 -> 110 | H19: =Gen!C20 -> 0.12 | I19: 20 | J19: =SUM(G19/I19) -> 5.5
A20: =Gen!B21 -> 44541 | B20: 85 | C20: 22 | D20: 0 | F20: 81757.53 | G20: =(F20-F19)*4.4 -> 105.38 | H20: =Gen!C21 -> 0.12 | I20: 22 | J20: =SUM(G20/I20) -> 4.79
A21: =Gen!B22 -> 44542 | B21: 85 | C21: 15 | D21: 0 | F21: 81781.77 | G21: =(F21-F20)*4.4 -> 106.656 | H21: =Gen!C22 -> 0.12 | I21: 23 | J21: =SUM(G21/I21) -> 4.6372174
... A40: =Gen!B41 -> 44561 | B40: 53 | C40: 0 | D40: 0 | F40: 82286.61 | G40: =(F40-F39)*4.4 -> 163.02 | H40: =Gen!C41 -> 0.61 | I40: 120 | J40: =SUM(G40/I40) -> 1.3585
C41: TOTAL USAGE | E41: =SUM(E10:E40) -> 0 | F41: =SUM(F10:F41) -> 2538412 | G41: =SUM(G10:G40) -> 3330.36 | H41: =Gen!C43 -> 0 | J41: =SUM(G41/I41) -> #DIV/0!

Sheet Summery Report
A1: =A5 -> 44531
A4: Date | B4: Gen Set Hours Working | C4: Occ% | D4: Total OCC Room | E4: Guest Room Occ | F4: Total Kwh Generated | G4: Diesel consumed by Gen (Ltrs) | H4: Diesel consumed by Vehicle (Ltrs) | I4: Total diesel consumed (Ltrs) | J4: Balance stock of Diesel (Ltrs) | K4: Water consumed | L4: Gas consumed (KG)
A5: =Gen!B11 -> 44531 | B5: ='Daily report Gen'!Z6 -> 30 | C5: =Gen!C11 -> 0.0519 | D5: =E5 -> 6 | E5: 6 | F5: =Gen!U11 -> 3130 | G5: =Gen!T11 -> 1340.69 | H5: =Gen!AK11 -> 55.31 | I5: =SUM(G5:H5) -> 1396 | J5: =Gen!D11 -> 43219.56 | K5: ='Water-Meter'!E6 -> 79 | L5: ='Lpg (2)'!G10 -> 101.244 | M5: =SUM(#REF!-#REF!) -> #REF!
A6: =Gen!B12 -> 44532 | B6: ='Daily report Gen'!Z7 -> 33 | C6: =Gen!C12 -> 0.05 | D6: =E6 -> 5 | E6: 5 | F6: =Gen!U12 -> 3105 | G6: =Gen!T12 -> 1268.81 | H6: =Gen!AK12 -> 596.04 | I6: =SUM(G6:H6) -> 1864.85 | J6: =Gen!D12 -> 41823.56 | K6: ='Water-Meter'!E7 -> 67 | L6: ='Lpg (2)'!G11 -> 70.312 | M6: =SUM(#REF!-#REF!) -> #REF!
A7: =Gen!B13 -> 44533 | B7: ='Daily report Gen'!Z8 -> 24 | C7: =Gen!C13 -> 0.05 | D7: =E7 -> 3 | E7: 3 | F7: =Gen!U13 -> 2910 | G7: =Gen!T13 -> 1177.17 | H7: =Gen!AK13 -> 0 | I7: =SUM(G7:H7) -> 1177.17 | J7: =Gen!D13 -> 39958.71 | K7: ='Water-Meter'!E8 -> 83 | L7: ='Lpg (2)'!G12 -> 59.576 | M7: =SUM(#REF!-#REF!) -> #REF!
A8: =Gen!B14 -> 44534 | B8: ='Daily report Gen'!Z9 -> 25 | C8: =Gen!C14 -> 0.08 | D8: =E8 -> 8 | E8: 8 | F8: =Gen!U14 -> 3289 | G8: =Gen!T14 -> 1293.22 | H8: =Gen!AK14 -> 199.51 | I8: =SUM(G8:H8) -> 1492.73 | J8: =Gen!D14 -> 38781.54 | K8: ='Water-Meter'!E9 -> 67 | L8: ='Lpg (2)'!G13 -> 61.512 | M8: =SUM(#REF!-#REF!) -> #REF!
A9: =Gen!B15 -> 44535 | B9: ='Daily report Gen'!Z10 -> 25 | C9: =Gen!C15 -> 0.05 | D9: =E9 -> 6 | E9: 6 | F9: =Gen!U15 -> 3146 | G9: =Gen!T15 -> 1246.93 | H9: =Gen!AK15 -> 53.33 | I9: =SUM(G9:H9) -> 1300.26 | J9: =Gen!D15 -> 37288.81 | K9: ='Water-Meter'!E10 -> 62 | L9: ='Lpg (2)'!G14 -> 87.34 | M9: =SUM(#REF!-#REF!) -> #REF!
A10: =Gen!B16 -> 44536 | B10: ='Daily report Gen'!Z11 -> 24 | C10: =Gen!C16 -> 0.0779 | D10: =E10 -> 9 | E10: 9 | F10: =Gen!U16 -> 3361 | G10: =Gen!T16 -> 1325.89 | H10: =Gen!AK16 -> 67.4 | I10: =SUM(G10:H10) -> 1393.29 | J10: =Gen!D16 -> 35988.55 | K10: ='Water-Meter'!E11 -> 57 | L10: ='Lpg (2)'!G15 -> 107.492 | M10: =SUM(#REF!-#REF!) -> #REF!
A11: =Gen!B17 -> 44537 | B11: ='Daily report Gen'!Z12 -> 24 | C11: =Gen!C17 -> 0.0779 | D11: =E11 -> 9 | E11: 9 | F11: =Gen!U17 -> 3380 | G11: =Gen!T17 -> 1368.94 | H11: =Gen!AK17 -> 135.94 | I11: =SUM(G11:H11) -> 1504.88 | J11: =Gen!D17 -> 34595.26 | K11: ='Water-Meter'!E12 -> 73 | L11: ='Lpg (2)'!G16 -> 90.684 | M11: =SUM(#REF!-#REF!) -> #REF!
A12: =Gen!B18 -> 44538 | B12: ='Daily report Gen'!Z13 -> 32 | C12: =Gen!C18 -> 0.12 | D12: =E12 -> 12 | E12: 12 | F12: =Gen!U18 -> 3662 | G12: =Gen!T18 -> 1527.6 | H12: =Gen!AK18 -> 83.59 | I12: =SUM(G12:H12) -> 1611.19 | J12: =Gen!D18 -> 33090.38 | K12: ='Water-Meter'!E13 -> 80 | L12: ='Lpg (2)'!G17 -> 99.88 | M12: =SUM(#REF!-#REF!) -> #REF!
A13: =Gen!B19 -> 44539 | B13: ='Daily report Gen'!Z14 -> 25 | C13: =Gen!C19 -> 0.09 | D13: =E13 -> 10 | E13: 10 | F13: =Gen!U19 -> 3399 | G13: =Gen!T19 -> 1371.66 | H13: =Gen!AK19 -> 51.98 | I13: =SUM(G13:H13) -> 1423.64 | J13: =Gen!D19 -> 31479.19 | K13: ='Water-Meter'!E14 -> 65 | L13: ='Lpg (2)'!G18 -> 108.988 | M13: =SUM(#REF!-#REF!) -> #REF!
A14: =Gen!B20 -> 44540 | B14: ='Daily report Gen'!Z15 -> 25 | C14: =Gen!C20 -> 0.12 | D14: =E14 -> 12 | E14: 12 | F14: =Gen!U20 -> 3440 | G14: =Gen!T20 -> 1347.33 | H14: =Gen!AK20 -> 448.65 | I14: =SUM(G14:H14) -> 1795.98 | J14: =Gen!D20 -> 30055.55 | K14: ='Water-Meter'!E15 -> 71 | L14: ='Lpg (2)'!G19 -> 110 | M14: =SUM(#REF!-#REF!) -> #REF!
A15: =Gen!B21 -> 44541 | B15: ='Daily report Gen'!Z16 -> 42 | C15: =Gen!C21 -> 0.12 | D15: =E15 -> 12 | E15: 12 | F15: =Gen!U21 -> 3696 | G15: =Gen!T21 -> 1512.79 | H15: =Gen!AK21 -> 37.87 | I15: =SUM(G15:H15) -> 1550.66 | J15: =Gen!D21 -> 28259.57 | K15: ='Water-Meter'!E16 -> 72 | L15: ='Lpg (2)'!G20 -> 105.38 | M15: =SUM(#REF!-#REF!) -> #REF!
A16: =Gen!B22 -> 44542 | B16: ='Daily report Gen'!Z17 -> 25 | C16: =Gen!C22 -> 0.12 | D16: =E16 -> 12 | E16: 12 | F16: =Gen!U22 -> 3646 | G16: =Gen!T22 -> 1485.24 | H16: =Gen!AK22 -> 68.16 | I16: =SUM(G16:H16) -> 1553.4 | J16: =Gen!D22 -> 26708.91 | K16: ='Water-Meter'!E17 -> 65 | L16: ='Lpg (2)'!G21 -> 106.656 | M16: =SUM(#REF!-#REF!) -> #REF!
... A35: =Gen!B41 -> 44561 | B35: ='Daily report Gen'!Z36 -> 42 | C35: =Gen!C41 -> 0.61 | D35: =E35 -> 48 | E35: 48 | F35: =Gen!U41 -> 4562 | G35: =Gen!T41 -> 1894.18 | H35: =Gen!AK41 -> 882.87 | I35: =SUM(G35:H35) -> 2777.05 | J35: =Gen!D41 -> 41977.68 | K35: ='Water-Meter'!E36 -> 102 | L35: ='Lpg (2)'!G40 -> 163.02 | M35: =SUM(#REF!-#REF!) -> #REF!
A36: =Gen!B42 -> 0 | B36: ='Daily report Gen'!Z37 -> -130496 | C36: =Gen!C42 -> 0 | D36: =E36 -> 0 | F36: =Gen!U42 -> 0 | G36: =Gen!T42 -> 0 | H36: =Gen!AK42 -> 0 | I36: =SUM(G36:H36) -> 0 | J36: =Gen!D42 -> 39200.63 | K36: ='Water-Meter'!E37 -> 120 | L36: ='Lpg (2)'!#REF! -> #REF!

Sheet Water-Meter
A1: Four Seasons Safari Lodge Serengeti - Water Report
C2: Main Meter | F2: KITCHEN | I2: Amani café | L2: Main SW POOL | O2: Laundry | S2: BORE HOLE NO.1 METER READING | V2: BORE HOLE NO.2 METER READING | Y2: BORE HOLE NO.3 METER READING | AB2: BORE HOLE NO.4 METER READING | AE2: BORE HOLE NO.5 METER READING | AH2: BORE HOLE NO.6 METER READING | AK2: RAIN WATER - METER READING | AN2: TOTAL WATER PRODUCTION
A3: DATE | C3: Open Bal | D3: Final | E3: consumption | F3: Open Bal | G3: Final | H3: consumption | I3: Open Bal | J3: Final | K3: consumption | L3: Open Bal | M3: Final | N3: consumption | O3: Open Bal | P3: Final | Q3: consumption | R3: Total consumption
S4: OPEN | T4: FINAL | U4: PROD. | V4: OPEN | W4: FINAL | X4: PROD. | Y4: OPEN | Z4: FINAL | AA4: PROD. | AB4: OPEN | AC4: FINAL | AD4: M3 | AE4: OPEN | AF4: FINAL | AG4: M3 | AH4: OPEN | AI4: FINAL | AJ4: M3 | AK4: OPEN | AL4: FINAL | AM4: M3
C5: =D4 -> 0 | D5: 274783 | F5: =G4 -> 0 | H5: 0 | I5: =J4 -> 0 | J5: 8871 | L5: =M4 -> 0 | N5: 0 | O5: =P4 -> 0 | P5: 22709 | T5: 79950 | V5: =W4 -> FINAL | X5: 0 | Y5: =Z4 -> FINAL | Z5: 96644 | AA5: 0 | AB5: =AC4 -> FINAL | AC5: 23145 | AE5: =AF4 -> FINAL | AG5: 0 | AH5: =AI4 -> FINAL | AI5: 37477 | AK5: =AL4 -> FINAL
A6: =Gen!B11 -> 44531 | C6: =D5 -> 274783 | D6: 274862 | E6: =IF((D6-D5)<0,"0",(D6-D5)) -> 79 | F6: =G5 -> 0 | H6: =IF((G6-G5)<0,"0",(G6-G5)) -> 0 | I6: =J5 -> 8871 | J6: 8872 | K6: =J6-J5 -> 1 | L6: =M5 -> 0 | N6: =IF((M6-M5)<0,"0",(M6-M5)) -> 0 | O6: =P5 -> 22709 | P6: 22716 | Q6: =IF((P6-P5)<0,"0",(P6-P5)) -> 7 | R6: =Q6+N6+K6+H6 -> 8 | S6: =T5 -> 79950 | T6: 79985 | U6: =IF((T6-T5)<0,"0",(T6-T5)) -> 35 | V6: =W5 -> 0 | X6: =IF((W6-W5)<0,"0",(W6-W5)) -> 0 | Y6: =Z5 -> 96644 | Z6: 96680 | AA6: =IF((Z6-Z5)<0,"0",(Z6-Z5)) -> 36 | AB6: =AC5 -> 23145 | AC6: 23171 | AD6: =IF((AC6-AC5)<0,"0",(AC6-AC5)) -> 26 | AE6: =AF5 -> 0 | AG6: =IF((AF6-AF5)<0,"0",(AF6-AF5)) -> 0 | AH6: =AI5 -> 37477 | AI6: 37512 | AJ6: =IF((AI6-AI5)<0,"0",(AI6-AI5)) -> 35 | AK6: =AL5 -> 0 | AM6: =IF((AL6-AL5)<0,"0",(AL6-AL5)) -> 0 | AN6: =U6+X6+AA6+AD6+AG6+AJ6+AM6 -> 132
A7: =Gen!B12 -> 44532 | C7: =D6 -> 274862 | D7: 274929 | E7: =IF((D7-D6)<0,"0",(D7-D6)) -> 67 | F7: =G6 -> 0 | H7: =IF((G7-G6)<0,"0",(G7-G6)) -> 0 | I7: =J6 -> 8872 | J7: 8874 | K7: =J7-J6 -> 2 | L7: =M6 -> 0 | N7: =IF((M7-M6)<0,"0",(M7-M6)) -> 0 | O7: =P6 -> 22716 | P7: 22721 | Q7: =IF((P7-P6)<0,"0",(P7-P6)) -> 5 | R7: =Q7+N7+K7+H7 -> 7 | S7: =T6 -> 79985 | T7: 79985 | U7: =IF((T7-T6)<0,"0",(T7-T6)) -> 0 | V7: =W6 -> 0 | X7: =IF((W7-W6)<0,"0",(W7-W6)) -> 0 | Y7: =Z6 -> 96680 | Z7: 96717 | AA7: =IF((Z7-Z6)<0,"0",(Z7-Z6)) -> 37 | AB7: =AC6 -> 23171 | AC7: 23172 | AD7: =IF((AC7-AC6)<0,"0",(AC7-AC6)) -> 1 | AE7: =AF6 -> 0 | AG7: =IF((AF7-AF6)<0,"0",(AF7-AF6)) -> 0 | AH7: =AI6 -> 37512 | AI7: 37548 | AJ7: =IF((AI7-AI6)<0,"0",(AI7-AI6)) -> 36 | AK7: =AL6 -> 0 | AM7: =IF((AL7-AL6)<0,"0",(AL7-AL6)) -> 0 | AN7: =U7+X7+AA7+AD7+AG7+AJ7+AM7 -> 74
A8: =Gen!B13 -> 44533 | C8: =D7 -> 274929 | D8: 275012 | E8: =IF((D8-D7)<0,"0",(D8-D7)) -> 83 | F8: =G7 -> 0 | H8: =IF((G8-G7)<0,"0",(G8-G7)) -> 0 | I8: =J7 -> 8874 | J8: 8876 | K8: =J8-J7 -> 2 | L8: =M7 -> 0 | N8: =IF((M8-M7)<0,"0",(M8-M7)) -> 0 | O8: =P7 -> 22721 | P8: 22724 | Q8: =IF((P8-P7)<0,"0",(P8-P7)) -> 3 | R8: =Q8+N8+K8+H8 -> 5 | S8: =T7 -> 79985 | T8: 79985 | U8: =IF((T8-T7)<0,"0",(T8-T7)) -> 0 | V8: =W7 -> 0 | X8: =IF((W8-W7)<0,"0",(W8-W7)) -> 0 | Y8: =Z7 -> 96717 | Z8: 96755 | AA8: =IF((Z8-Z7)<0,"0",(Z8-Z7)) -> 38 | AB8: =AC7 -> 23172 | AC8: 23182 | AD8: =IF((AC8-AC7)<0,"0",(AC8-AC7)) -> 10 | AE8: =AF7 -> 0 | AG8: =IF((AF8-AF7)<0,"0",(AF8-AF7)) -> 0 | AH8: =AI7 -> 37548 | AI8: 37584 | AJ8: =IF((AI8-AI7)<0,"0",(AI8-AI7)) -> 36 | AK8: =AL7 -> 0 | AM8: =IF((AL8-AL7)<0,"0",(AL8-AL7)) -> 0 | AN8: =U8+X8+AA8+AD8+AG8+AJ8+AM8 -> 84
A9: =Gen!B14 -> 44534 | C9: =D8 -> 275012 | D9: 275079 | E9: =IF((D9-D8)<0,"0",(D9-D8)) -> 67 | F9: =G8 -> 0 | H9: =IF((G9-G8)<0,"0",(G9-G8)) -> 0 | I9: =J8 -> 8876 | J9: 8889 | K9: =J9-J8 -> 13 | L9: =M8 -> 0 | N9: =IF((M9-M8)<0,"0",(M9-M8)) -> 0 | O9: =P8 -> 22724 | P9: 22729 | Q9: =IF((P9-P8)<0,"0",(P9-P8)) -> 5 | R9: =Q9+N9+K9+H9 -> 18 | S9: =T8 -> 79985 | T9: 79985 | U9: =IF((T9-T8)<0,"0",(T9-T8)) -> 0 | V9: =W8 -> 0 | X9: =IF((W9-W8)<0,"0",(W9-W8)) -> 0 | Y9: =Z8 -> 96755 | Z9: 96788 | AA9: =IF((Z9-Z8)<0,"0",(Z9-Z8)) -> 33 | AB9: =AC8 -> 23182 | AC9: 23197 | AD9: =IF((AC9-AC8)<0,"0",(AC9-AC8)) -> 15 | AE9: =AF8 -> 0 | AG9: =IF((AF9-AF8)<0,"0",(AF9-AF8)) -> 0 | AH9: =AI8 -> 37584 | AI9: 37617 | AJ9: =IF((AI9-AI8)<0,"0",(AI9-AI8)) -> 33 | AK9: =AL8 -> 0 | AM9: =IF((AL9-AL8)<0,"0",(AL9-AL8)) -> 0 | AN9: =U9+X9+AA9+AD9+AG9+AJ9+AM9 -> 81
A10: =Gen!B15 -> 44535 | C10: =D9 -> 275079 | D10: 275141 | E10: =IF((D10-D9)<0,"0",(D10-D9)) -> 62 | F10: =G9 -> 0 | H10: =IF((G10-G9)<0,"0",(G10-G9)) -> 0 | I10: =J9 -> 8889 | J10: 8895 | K10: =J10-J9 -> 6 | L10: =M9 -> 0 | N10: =IF((M10-M9)<0,"0",(M10-M9)) -> 0 | O10: =P9 -> 22729 | P10: 22733 | Q10: =IF((P10-P9)<0,"0",(P10-P9)) -> 4 | R10: =Q10+N10+K10+H10 -> 10 | S10: =T9 -> 79985 | T10: 79985 | U10: =IF((T10-T9)<0,"0",(T10-T9)) -> 0 | V10: =W9 -> 0 | X10: =IF((W10-W9)<0,"0",(W10-W9)) -> 0 | Y10: =Z9 -> 96788 | Z10: 96823 | AA10: =IF((Z10-Z9)<0,"0",(Z10-Z9)) -> 35 | AB10: =AC9 -> 23197 | AC10: 23211 | AD10: =IF((AC10-AC9)<0,"0",(AC10-AC9)) -> 14 | AE10: =AF9 -> 0 | AG10: =IF((AF10-AF9)<0,"0",(AF10-AF9)) -> 0 | AH10: =AI9 -> 37617 | AI10: 37652 | AJ10: =IF((AI10-AI9)<0,"0",(AI10-AI9)) -> 35 | AK10: =AL9 -> 0 | AM10: =IF((AL10-AL9)<0,"0",(AL10-AL9)) -> 0 | AN10: =U10+X10+AA10+AD10+AG10+AJ10+AM10 -> 84
A11: =Gen!B16 -> 44536 | C11: =D10 -> 275141 | D11: 275198 | E11: =IF((D11-D10)<0,"0",(D11-D10)) -> 57 | F11: =G10 -> 0 | H11: =IF((G11-G10)<0,"0",(G11-G10)) -> 0 | I11: =J10 -> 8895 | J11: 8897 | K11: =J11-J10 -> 2 | L11: =M10 -> 0 | N11: =IF((M11-M10)<0,"0",(M11-M10)) -> 0 | O11: =P10 -> 22733 | P11: 22738 | Q11: =IF((P11-P10)<0,"0",(P11-P10)) -> 5 | R11: =Q11+N11+K11+H11 -> 7 | S11: =T10 -> 79985 | T11: 79985 | U11: =IF((T11-T10)<0,"0",(T11-T10)) -> 0 | V11: =W10 -> 0 | X11: =IF((W12-W10)<0,"0",(W12-W10)) -> 0 | Y11: =Z10 -> 96823 | Z11: 96858 | AA11: =IF((Z11-Z10)<0,"0",(Z11-Z10)) -> 35 | AB11: =AC10 -> 23211 | AC11: 23213 | AD11: =IF((AC11-AC10)<0,"0",(AC11-AC10)) -> 2 | AE11: =AF11 -> 0 | AG11: =IF((AF11-AF10)<0,"0",(AF11-AF10)) -> 0 | AH11: =AI10 -> 37652 | AI11: 37687 | AJ11: =IF((AI11-AI10)<0,"0",(AI11-AI10)) -> 35 | AK11: =AL10 -> 0 | AM11: =IF((AL11-AL10)<0,"0",(AL11-AL10)) -> 0 | AN11: =U11+X11+AA11+AD11+AG11+AJ11+AM11 -> 72
A12: =Gen!B17 -> 44537 | C12: =D11 -> 275198 | D12: 275271 | E12: =IF((D12-D11)<0,"0",(D12-D11)) -> 73 | F12: =G11 -> 0 | H12: =IF((G12-G11)<0,"0",(G12-G11)) -> 0 | I12: =J11 -> 8897 | J12: 8900 | K12: =J12-J11 -> 3 | L12: =M11 -> 0 | N12: =IF((M12-M11)<0,"0",(M12-M11)) -> 0 | O12: =P11 -> 22738 | P12: 22745 | Q12: =IF((P12-P11)<0,"0",(P12-P11)) -> 7 | R12: =Q12+N12+K12+H12 -> 10 | S12: =T11 -> 79985 | T12: 79985 | U12: =IF((T12-T11)<0,"0",(T12-T11)) -> 0 | V12: =W12 -> 0 | X12: =IF((W13-W11)<0,"0",(W13-W11)) -> 0 | Y12: =Z11 -> 96858 | Z12: 96895 | AA12: =IF((Z12-Z11)<0,"0",(Z12-Z11)) -> 37 | AB12: =AC11 -> 23213 | AC12: 23213 | AD12: =IF((AC12-AC11)<0,"0",(AC12-AC11)) -> 0 | AE12: =AF12 -> 0 | AG12: =IF((AF12-AF11)<0,"0",(AF12-AF11)) -> 0 | AH12: =AI11 -> 37687 | AI12: 37722 | AJ12: =IF((AI12-AI11)<0,"0",(AI12-AI11)) -> 35 | AK12: =AL11 -> 0 | AM12: =IF((AL12-AL11)<0,"0",(AL12-AL11)) -> 0 | AN12: =U12+X12+AA12+AD12+AG12+AJ12+AM12 -> 72
A13: =Gen!B18 -> 44538 | C13: =D12 -> 275271 | D13: 275351 | E13: =IF((D13-D12)<0,"0",(D13-D12)) -> 80 | F13: =G12 -> 0 | H13: =IF((G13-G12)<0,"0",(G13-G12)) -> 0 | I13: =J12 -> 8900 | J13: 8903 | K13: =J13-J12 -> 3 | L13: =M12 -> 0 | N13: =IF((M13-M12)<0,"0",(M13-M12)) -> 0 | O13: =P12 -> 22745 | P13: 22751 | Q13: =IF((P13-P12)<0,"0",(P13-P12)) -> 6 | R13: =Q13+N13+K13+H13 -> 9 | S13: =T12 -> 79985 | T13: 80059 | U13: =IF((T13-T12)<0,"0",(T13-T12)) -> 74 | V13: =W13 -> 0 | X13: =IF((W14-W12)<0,"0",(W14-W12)) -> 0 | Y13: =Z12 -> 96895 | Z13: 96930 | AA13: =IF((Z13-Z12)<0,"0",(Z13-Z12)) -> 35 | AB13: =AC12 -> 23213 | AC13: 23213 | AD13: =IF((AC13-AC12)<0,"0",(AC13-AC12)) -> 0 | AE13: =AF13 -> 0 | AG13: =IF((AF13-AF12)<0,"0",(AF13-AF12)) -> 0 | AH13: =AI12 -> 37722 | AI13: 37757 | AJ13: =IF((AI13-AI12)<0,"0",(AI13-AI12)) -> 35 | AK13: =AL12 -> 0 | AM13: =IF((AL13-AL12)<0,"0",(AL13-AL12)) -> 0 | AN13: =U13+X13+AA13+AD13+AG13+AJ13+AM13 -> 144
A14: =Gen!B19 -> 44539 | C14: =D13 -> 275351 | D14: 275416 | E14: =IF((D14-D13)<0,"0",(D14-D13)) -> 65 | F14: =G13 -> 0 | H14: =IF((G14-G13)<0,"0",(G14-G13)) -> 0 | I14: =J13 -> 8903 | J14: 8905 | K14: =IF((J14-J13)<0,"0",(J14-J13)) -> 2 | L14: =M13 -> 0 | N14: =IF((M14-M13)<0,"0",(M14-M13)) -> 0 | O14: =P13 -> 22751 | P14: 22754 | Q14: =IF((P14-P13)<0,"0",(P14-P13)) -> 3 | R14: =Q14+N14+K14+H14 -> 5 | S14: =T13 -> 80059 | T14: 80127 | U14: =IF((T14-T13)<0,"0",(T14-T13)) -> 68 | V14: =W14 -> 0 | X14: =IF((W15-W13)<0,"0",(W15-W13)) -> 0 | Y14: =Z13 -> 96930 | Z14: 96964 | AA14: =IF((Z14-Z13)<0,"0",(Z14-Z13)) -> 34 | AB14: =AC13 -> 23213 | AC14: 23213 | AD14: =IF((AC14-AC13)<0,"0",(AC14-AC13)) -> 0 | AE14: =AF14 -> 0 | AG14: =IF((AF14-AF13)<0,"0",(AF14-AF13)) -> 0 | AH14: =AI13 -> 37757 | AI14: 37790 | AJ14: =IF((AI14-AI13)<0,"0",(AI14-AI13)) -> 33 | AK14: =AL13 -> 0 | AM14: =IF((AL14-AL13)<0,"0",(AL14-AL13)) -> 0 | AN14: =U14+X14+AA14+AD14+AG14+AJ14+AM14 -> 135
A15: =Gen!B20 -> 44540 | C15: =D14 -> 275416 | D15: 275487 | E15: =IF((D15-D14)<0,"0",(D15-D14)) -> 71 | F15: =G14 -> 0 | H15: =IF((G15-G14)<0,"0",(G15-G14)) -> 0 | I15: =J14 -> 8905 | J15: 8906 | K15: =IF((J15-J14)<0,"0",(J15-J14)) -> 1 | L15: =M14 -> 0 | N15: =IF((M15-M14)<0,"0",(M15-M14)) -> 0 | O15: =P14 -> 22754 | P15: 22760 | Q15: =IF((P15-P14)<0,"0",(P15-P14)) -> 6 | R15: =Q15+N15+K15+H15 -> 7 | S15: =T14 -> 80127 | T15: 80200 | U15: =IF((T15-T14)<0,"0",(T15-T14)) -> 73 | V15: =W14 -> 0 | X15: =IF((W15-W14)<0,"0",(W15-W14)) -> 0 | Y15: =Z14 -> 96964 | Z15: 97001 | AA15: =IF((Z15-Z14)<0,"0",(Z15-Z14)) -> 37 | AB15: =AC14 -> 23213 | AC15: 23213 | AD15: =IF((AC15-AC14)<0,"0",(AC15-AC14)) -> 0 | AE15: =AF15 -> 0 | AG15: =IF((AF15-AF14)<0,"0",(AF15-AF14)) -> 0 | AH15: =AI14 -> 37790 | AI15: 37826 | AJ15: =IF((AI15-AI14)<0,"0",(AI15-AI14)) -> 36 | AK15: =AL14 -> 0 | AM15: =IF((AL15-AL14)<0,"0",(AL15-AL14)) -> 0 | AN15: =U15+X15+AA15+AD15+AG15+AJ15+AM15 -> 146
A16: =Gen!B21 -> 44541 | C16: =D15 -> 275487 | D16: 275559 | E16: =IF((D16-D15)<0,"0",(D16-D15)) -> 72 | F16: =G15 -> 0 | H16: =IF((G16-G15)<0,"0",(G16-G15)) -> 0 | I16: =J15 -> 8906 | J16: 8908 | K16: =IF((J16-J15)<0,"0",(J16-J15)) -> 2 | L16: =M15 -> 0 | N16: =IF((M16-M15)<0,"0",(M16-M15)) -> 0 | O16: =P15 -> 22760 | P16: 22764 | Q16: =IF((P16-P15)<0,"0",(P16-P15)) -> 4 | R16: =Q16+N16+K16+H16 -> 6 | S16: =T15 -> 80200 | T16: 80269 | U16: =IF((T16-T15)<0,"0",(T16-T15)) -> 69 | V16: =W15 -> 0 | X16: =IF((W16-W15)<0,"0",(W16-W15)) -> 0 | Y16: =Z15 -> 97001 | Z16: 97037 | AA16: =IF((Z16-Z15)<0,"0",(Z16-Z15)) -> 36 | AB16: =AC15 -> 23213 | AC16: 23213 | AD16: =IF((AC16-AC15)<0,"0",(AC16-AC15)) -> 0 | AE16: =AF16 -> 0 | AG16: =IF((AF16-AF15)<0,"0",(AF16-AF15)) -> 0 | AH16: =AI15 -> 37826 | AI16: 37861 | AJ16: =IF((AI16-AI15)<0,"0",(AI16-AI15)) -> 35 | AK16: =AL15 -> 0 | AM16: =IF((AL16-AL15)<0,"0",(AL16-AL15)) -> 0 | AN16: =U16+X16+AA16+AD16+AG16+AJ16+AM16 -> 140
A17: =Gen!B22 -> 44542 | C17: =D16 -> 275559 | D17: 275624 | E17: =IF((D17-D16)<0,"0",(D17-D16)) -> 65 | F17: =G16 -> 0 | H17: =IF((G17-G16)<0,"0",(G17-G16)) -> 0 | I17: =J16 -> 8908 | J17: 8910 | K17: =IF((J17-J16)<0,"0",(J17-J16)) -> 2 | L17: =M16 -> 0 | N17: =IF((M17-M16)<0,"0",(M17-M16)) -> 0 | O17: =P16 -> 22764 | P17: 22769 | Q17: =IF((P17-P16)<0,"0",(P17-P16)) -> 5 | R17: =Q17+N17+K17+H17 -> 7 | S17: =T16 -> 80269 | T17: 80338 | U17: =IF((T17-T16)<0,"0",(T17-T16)) -> 69 | V17: =W16 -> 0 | X17: =IF((W17-W16)<0,"0",(W17-W16)) -> 0 | Y17: =Z16 -> 97037 | Z17: 97074 | AA17: =IF((Z17-Z16)<0,"0",(Z17-Z16)) -> 37 | AB17: =AC16 -> 23213 | AC17: 23213 | AD17: =IF((AC17-AC16)<0,"0",(AC17-AC16)) -> 0 | AE17: =AF17 -> 0 | AG17: =IF((AF17-AF16)<0,"0",(AF17-AF16)) -> 0 | AH17: =AI16 -> 37861 | AI17: 37896 | AJ17: =IF((AI17-AI16)<0,"0",(AI17-AI16)) -> 35 | AK17: =AL16 -> 0 | AM17: =IF((AL17-AL16)<0,"0",(AL17-AL16)) -> 0 | AN17: =U17+X17+AA17+AD17+AG17+AJ17+AM17 -> 141
A18: =Gen!B23 -> 44543 | C18: =D17 -> 275624 | D18: 275692 | E18: =IF((D18-D17)<0,"0",(D18-D17)) -> 68 | F18: =G17 -> 0 | H18: =IF((G18-G17)<0,"0",(G18-G17)) -> 0 | J18: 8913 | K18: =IF((J18-J17)<0,"0",(J18-J17)) -> 3 | L18: =M17 -> 0 | N18: =IF((M18-M17)<0,"0",(M18-M17)) -> 0 | O18: =P17 -> 22769 | P18: 22776 | Q18: =IF((P18-P17)<0,"0",(P18-P17)) -> 7 | R18: =Q18+N18+K18+H18 -> 10 | S18: =T17 -> 80338 | T18: 80407 | U18: =IF((T18-T17)<0,"0",(T18-T17)) -> 69 | V18: =W17 -> 0 | X18: =IF((W18-W17)<0,"0",(W18-W17)) -> 0 | Y18: =Z17 -> 97074 | Z18: 97113 | AA18: =IF((Z18-Z17)<0,"0",(Z18-Z17)) -> 39 | AB18: =AC17 -> 23213 | AC18: 23213 | AD18: =IF((AC18-AC17)<0,"0",(AC18-AC17)) -> 0 | AE18: =AF18 -> 0 | AG18: =IF((AF18-AF17)<0,"0",(AF18-AF17)) -> 0 | AH18: =AI17 -> 37896 | AI18: 37934 | AJ18: =IF((AI18-AI17)<0,"0",(AI18-AI17)) -> 38 | AK18: =AL17 -> 0 | AM18: =IF((AL18-AL17)<0,"0",(AL18-AL17)) -> 0 | AN18: =U18+X18+AA18+AD18+AG18+AJ18+AM18 -> 146
A19: =Gen!B24 -> 44544 | C19: =D18 -> 275692 | D19: 275770 | E19: =IF((D19-D18)<0,"0",(D19-D18)) -> 78 | F19: =G18 -> 0 | H19: =IF((G19-G18)<0,"0",(G19-G18)) -> 0 | I19: =J18 -> 8913 | J19: 8916 | K19: =IF((J19-J18)<0,"0",(J19-J18)) -> 3 | L19: =M18 -> 0 | N19: =IF((M19-M18)<0,"0",(M19-M18)) -> 0 | O19: =P18 -> 22776 | P19: 22784 | Q19: =IF((P19-P18)<0,"0",(P19-P18)) -> 8 | R19: =Q19+N19+K19+H19 -> 11 | S19: =T18 -> 80407 | T19: 80475 | U19: =IF((T19-T18)<0,"0",(T19-T18)) -> 68 | V19: =W18 -> 0 | X19: =IF((W19-W18)<0,"0",(W19-W18)) -> 0 | Y19: =Z18 -> 97113 | Z19: 97145 | AA19: =IF((Z19-Z18)<0,"0",(Z19-Z18)) -> 32 | AB19: =AC18 -> 23213 | AC19: 23233 | AD19: =IF((AC19-AC18)<0,"0",(AC19-AC18)) -> 20 | AE19: =AF19 -> 0 | AG19: =IF((AF19-AF18)<0,"0",(AF19-AF18)) -> 0 | AH19: =AI18 -> 37934 | AI19: 37969 | AJ19: =IF((AI19-AI18)<0,"0",(AI19-AI18)) -> 35 | AK19: =AL18 -> 0 | AM19: =IF((AL19-AL18)<0,"0",(AL19-AL18)) -> 0 | AN19: =U19+X19+AA19+AD19+AG19+AJ19+AM19 -> 155
A20: =Gen!B25 -> 44545 | C20: =D19 -> 275770 | D20: 275842 | E20: =IF((D20-D19)<0,"0",(D20-D19)) -> 72 | F20: =G19 -> 0 | H20: =IF((G20-G19)<0,"0",(G20-G19)) -> 0 | I20: =J19 -> 8916 | J20: 8918 | K20: =IF((J20-J19)<0,"0",(J20-J19)) -> 2 | L20: =M19 -> 0 | N20: =IF((M20-M19)<0,"0",(M20-M19)) -> 0 | O20: =P19 -> 22784 | P20: 22789 | Q20: =IF((P20-P19)<0,"0",(P20-P19)) -> 5 | R20: =Q20+N20+K20+H20 -> 7 | S20: =T19 -> 80475 | T20: 80475 | U20: =IF((T20-T19)<0,"0",(T20-T19)) -> 0 | V20: =W19 -> 0 | X20: =IF((W20-W19)<0,"0",(W20-W19)) -> 0 | Y20: =Z19 -> 97145 | Z20: 97190 | AA20: =IF((Z20-Z19)<0,"0",(Z20-Z19)) -> 45 | AB20: =AC19 -> 23233 | AC20: 23253 | AD20: =IF((AC20-AC19)<0,"0",(AC20-AC19)) -> 20 | AE20: =AF20 -> 0 | AG20: =IF((AF20-AF19)<0,"0",(AF20-AF19)) -> 0 | AH20: =AI19 -> 37969 | AI20: 38006 | AJ20: =IF((AI20-AI19)<0,"0",(AI20-AI19)) -> 37 | AK20: =AL19 -> 0 | AM20: =IF((AL20-AL19)<0,"0",(AL20-AL19)) -> 0 | AN20: =U20+X20+AA20+AD20+AG20+AJ20+AM20 -> 102
A21: =Gen!B26 -> 44546 | C21: =D20 -> 275842 | D21: 275915 | E21: =IF((D21-D20)<0,"0",(D21-D20)) -> 73 | F21: =G20 -> 0 | H21: =IF((G21-G20)<0,"0",(G21-G20)) -> 0 | I21: =J20 -> 8918 | J21: 8920 | K21: =IF((J21-J20)<0,"0",(J21-J20)) -> 2 | L21: =M20 -> 0 | N21: =IF((M21-M20)<0,"0",(M21-M20)) -> 0 | O21: =P20 -> 22789 | P21: 22794 | Q21: =IF((P21-P20)<0,"0",(P21-P20)) -> 5 | R21: =Q21+N21+K21+H21 -> 7 | S21: =T20 -> 80475 | T21: 80475 | U21: =IF((T21-T20)<0,"0",(T21-T20)) -> 0 | V21: =W20 -> 0 | X21: =IF((W21-W20)<0,"0",(W21-W20)) -> 0 | Y21: =Z20 -> 97190 | Z21: 97225 | AA21: =IF((Z21-Z20)<0,"0",(Z21-Z20)) -> 35 | AB21: =AC20 -> 23253 | AC21: 23270 | AD21: =IF((AC21-AC20)<0,"0",(AC21-AC20)) -> 17 | AE21: =AF20 -> 0 | AG21: =IF((AF21-AF20)<0,"0",(AF21-AF20)) -> 0 | AH21: =AI20 -> 38006 | AI21: 38045 | AJ21: =IF((AI21-AI20)<0,"0",(AI21-AI20)) -> 39 | AK21: =AL20 -> 0 | AM21: =IF((AL21-AL20)<0,"0",(AL21-AL20)) -> 0 | AN21: =U21+X21+AA21+AD21+AG21+AJ21+AM21 -> 91
A22: =Gen!B27 -> 44547 | C22: =D21 -> 275915 | D22: 275988 | E22: =IF((D22-D21)<0,"0",(D22-D21)) -> 73 | F22: =G21 -> 0 | H22: =IF((G22-G21)<0,"0",(G22-G21)) -> 0 | I22: =J21 -> 8920 | J22: 8922 | K22: =IF((J22-J21)<0,"0",(J22-J21)) -> 2 | L22: =M21 -> 0 | N22: =IF((M22-M21)<0,"0",(M22-M21)) -> 0 | O22: =P21 -> 22794 | P22: 22798 | Q22: =IF((P22-P21)<0,"0",(P22-P21)) -> 4 | R22: =Q22+N22+K22+H22 -> 6 | S22: =T21 -> 80475 | T22: 80475 | U22: =IF((T22-T21)<0,"0",(T22-T21)) -> 0 | V22: =W21 -> 0 | X22: =IF((W22-W21)<0,"0",(W22-W21)) -> 0 | Y22: =Z21 -> 97225 | Z22: 97265 | AA22: =IF((Z22-Z21)<0,"0",(Z22-Z21)) -> 40 | AB22: =AC21 -> 23270 | AC22: 23309 | AD22: =IF((AC22-AC21)<0,"0",(AC22-AC21)) -> 39 | AE22: =AF21 -> 0 | AG22: =IF((AF22-AF21)<0,"0",(AF22-AF21)) -> 0 | AH22: =AI21 -> 38045 | AI22: 38075 | AJ22: =IF((AI22-AI21)<0,"0",(AI22-AI21)) -> 30 | AK22: =AL21 -> 0 | AM22: =IF((AL22-AL21)<0,"0",(AL22-AL21)) -> 0 | AN22: =U22+X22+AA22+AD22+AG22+AJ22+AM22 -> 109
A23: =Gen!B28 -> 44548 | C23: =D22 -> 275988 | D23: 276073 | E23: =IF((D23-D22)<0,"0",(D23-D22)) -> 85 | F23: =G22 -> 0 | H23: =IF((G23-G22)<0,"0",(G23-G22)) -> 0 | I23: =J22 -> 8922 | J23: 8925 | K23: =IF((J23-J22)<0,"0",(J23-J22)) -> 3 | L23: =M22 -> 0 | N23: =IF((M23-M22)<0,"0",(M23-M22)) -> 0 | O23: =P22 -> 22798 | P23: 22806 | Q23: =IF((P23-P22)<0,"0",(P23-P22)) -> 8 | R23: =Q23+N23+K23+H23 -> 11 | S23: =T22 -> 80475 | T23: 80475 | U23: =IF((T23-T22)<0,"0",(T23-T22)) -> 0 | V23: =W22 -> 0 | X23: =IF((W23-W22)<0,"0",(W23-W22)) -> 0 | Y23: =Z22 -> 97265 | Z23: 97303 | AA23: =IF((Z23-Z22)<0,"0",(Z23-Z22)) -> 38 | AB23: =AC22 -> 23309 | AC23: 23347 | AD23: =IF((AC23-AC22)<0,"0",(AC23-AC22)) -> 38 | AE23: =AF22 -> 0 | AG23: =IF((AF23-AF22)<0,"0",(AF23-AF22)) -> 0 | AH23: =AI22 -> 38075 | AI23: 38108 | AJ23: =IF((AI23-AI22)<0,"0",(AI23-AI22)) -> 33 | AK23: =AL22 -> 0 | AM23: =IF((AL23-AL22)<0,"0",(AL23-AL22)) -> 0 | AN23: =U23+X23+AA23+AD23+AG23+AJ23+AM23 -> 109
A24: =Gen!B29 -> 44549 | C24: =D23 -> 276073 | D24: 276153 | E24: =IF((D24-D23)<0,"0",(D24-D23)) -> 80 | F24: =G23 -> 0 | H24: =IF((G24-G23)<0,"0",(G24-G23)) -> 0 | I24: =J23 -> 8925 | J24: 8928 | K24: =IF((J24-J23)<0,"0",(J24-J23)) -> 3 | L24: =M23 -> 0 | N24: =IF((M24-M23)<0,"0",(M24-M23)) -> 0 | O24: =P23 -> 22806 | P24: 22812 | Q24: =IF((P24-P23)<0,"0",(P24-P23)) -> 6 | R24: =Q24+N24+K24+H24 -> 9 | S24: =T23 -> 80475 | T24: 80475 | U24: =IF((T24-T23)<0,"0",(T24-T23)) -> 0 | V24: =W23 -> 0 | X24: =IF((W24-W23)<0,"0",(W24-W23)) -> 0 | Y24: =Z23 -> 97303 | Z24: 97344 | AA24: =IF((Z24-Z23)<0,"0",(Z24-Z23)) -> 41 | AB24: =AC23 -> 23347 | AC24: 23386 | AD24: =IF((AC24-AC23)<0,"0",(AC24-AC23)) -> 39 | AE24: =AF23 -> 0 | AG24: =IF((AF24-AF23)<0,"0",(AF24-AF23)) -> 0 | AH24: =AI23 -> 38108 | AI24: 38143 | AJ24: =IF((AI24-AI23)<0,"0",(AI24-AI23)) -> 35 | AK24: =AL23 -> 0 | AM24: =IF((AL24-AL23)<0,"0",(AL24-AL23)) -> 0 | AN24: =U24+X24+AA24+AD24+AG24+AJ24+AM24 -> 115
A25: =Gen!B30 -> 44550 | C25: =D24 -> 276153 | D25: 276229 | E25: =IF((D25-D24)<0,"0",(D25-D24)) -> 76 | F25: =G24 -> 0 | H25: =IF((G26-G24)<0,"0",(G26-G24)) -> 0 | I25: =J24 -> 8928 | J25: 8930 | K25: =IF((J25-J24)<0,"0",(J25-J24)) -> 2 | L25: =M24 -> 0 | N25: =IF((M25-M24)<0,"0",(M25-M24)) -> 0 | O25: =P24 -> 22812 | P25: 22817 | Q25: =IF((P25-P24)<0,"0",(P25-P24)) -> 5 | R25: =Q25+N25+K25+H25 -> 7 | S25: =T24 -> 80475 | T25: 80475 | U25: =IF((T25-T24)<0,"0",(T25-T24)) -> 0 | V25: =W24 -> 0 | X25: =IF((W25-W24)<0,"0",(W25-W24)) -> 0 | Y25: =Z24 -> 97344 | Z25: 97383 | AA25: =IF((Z25-Z24)<0,"0",(Z25-Z24)) -> 39 | AB25: =AC24 -> 23386 | AC25: 23411 | AD25: =IF((AC25-AC24)<0,"0",(AC25-AC24)) -> 25 | AE25: =AF24 -> 0 | AG25: =IF((AF25-AF24)<0,"0",(AF25-AF24)) -> 0 | AH25: =AI24 -> 38143 | AI25: 38181 | AJ25: =IF((AI25-AI24)<0,"0",(AI25-AI24)) -> 38 | AK25: =AL24 -> 0 | AM25: =IF((AL25-AL24)<0,"0",(AL25-AL24)) -> 0 | AN25: =U25+X25+AA25+AD25+AG25+AJ25+AM25 -> 102
A26: =Gen!B31 -> 44551 | C26: =D25 -> 276229 | D26: 276298 | E26: =IF((D26-D25)<0,"0",(D26-D25)) -> 69 | F26: =G26 -> 0 | H26: =IF((G27-G25)<0,"0",(G27-G25)) -> 0 | I26: =J25 -> 8930 | J26: 8932 | K26: =IF((J26-J25)<0,"0",(J26-J25)) -> 2 | L26: =M25 -> 0 | N26: =IF((M26-M25)<0,"0",(M26-M25)) -> 0 | O26: =P25 -> 22817 | P26: 22822 | Q26: =IF((P26-P25)<0,"0",(P26-P25)) -> 5 | R26: =Q26+N26+K26+H26 -> 7 | S26: =T25 -> 80475 | T26: 80547 | U26: =IF((T26-T25)<0,"0",(T26-T25)) -> 72 | V26: =W25 -> 0 | X26: =IF((W26-W25)<0,"0",(W26-W25)) -> 0 | Y26: =Z25 -> 97383 | Z26: 97421 | AA26: =IF((Z26-Z25)<0,"0",(Z26-Z25)) -> 38 | AB26: =AC25 -> 23411 | AC26: 23428 | AD26: =IF((AC26-AC25)<0,"0",(AC26-AC25)) -> 17 | AE26: =AF25 -> 0 | AG26: =IF((AF26-AF25)<0,"0",(AF26-AF25)) -> 0 | AH26: =AI25 -> 38181 | AI26: 38219 | AJ26: =IF((AI26-AI25)<0,"0",(AI26-AI25)) -> 38 | AK26: =AL25 -> 0 | AM26: =IF((AL26-AL25)<0,"0",(AL26-AL25)) -> 0 | AN26: =U26+X26+AA26+AD26+AG26+AJ26+AM26 -> 165
A27: =Gen!B32 -> 44552 | C27: =D26 -> 276298 | D27: 276369 | E27: =IF((D27-D26)<0,"0",(D27-D26)) -> 71 | F27: =G27 -> 0 | H27: =IF((G28-G26)<0,"0",(G28-G26)) -> 0 | I27: =J26 -> 8932 | J27: 8936 | K27: =IF((J27-J26)<0,"0",(J27-J26)) -> 4 | L27: =M26 -> 0 | N27: =IF((M27-M26)<0,"0",(M27-M26)) -> 0 | O27: =P26 -> 22822 | P27: 22829 | Q27: =IF((P27-P26)<0,"0",(P27-P26)) -> 7 | R27: =Q27+N27+K27+H27 -> 11 | S27: =T26 -> 80547 | T27: 80618 | U27: =IF((T27-T26)<0,"0",(T27-T26)) -> 71 | V27: =W26 -> 0 | X27: =IF((W27-W26)<0,"0",(W27-W26)) -> 0 | Y27: =Z26 -> 97421 | Z27: 97456 | AA27: =IF((Z27-Z26)<0,"0",(Z27-Z26)) -> 35 | AB27: =AC26 -> 23428 | AC27: 23444 | AD27: =IF((AC27-AC26)<0,"0",(AC27-AC26)) -> 16 | AE27: =AF26 -> 0 | AG27: =IF((AF27-AF26)<0,"0",(AF27-AF26)) -> 0 | AH27: =AI26 -> 38219 | AI27: 38251 | AJ27: =IF((AI27-AI26)<0,"0",(AI27-AI26)) -> 32 | AK27: =AL26 -> 0 | AM27: =IF((AL27-AL26)<0,"0",(AL27-AL26)) -> 0 | AN27: =U27+X27+AA27+AD27+AG27+AJ27+AM27 -> 154
A28: =Gen!B33 -> 44553 | C28: =D27 -> 276369 | D28: 276454 | E28: =IF((D28-D27)<0,"0",(D28-D27)) -> 85 | F28: =G28 -> 0 | H28: =IF((G28-G27)<0,"0",(G28-G27)) -> 0 | I28: =J27 -> 8936 | J28: 8938 | K28: =IF((J28-J27)<0,"0",(J28-J27)) -> 2 | L28: =M27 -> 0 | N28: =IF((M28-M27)<0,"0",(M28-M27)) -> 0 | O28: =P27 -> 22829 | P28: 22839 | Q28: =IF((P28-P27)<0,"0",(P28-P27)) -> 10 | R28: =Q28+N28+K28+H28 -> 12 | S28: =T27 -> 80618 | T28: 80641 | U28: =IF((T28-T27)<0,"0",(T28-T27)) -> 23 | V28: =W27 -> 0 | X28: =IF((W28-W27)<0,"0",(W28-W27)) -> 0 | Y28: =Z27 -> 97456 | Z28: 97497 | AA28: =IF((Z28-Z27)<0,"0",(Z28-Z27)) -> 41 | AB28: =AC27 -> 23444 | AC28: 23462 | AD28: =IF((AC28-AC27)<0,"0",(AC28-AC27)) -> 18 | AE28: =AF27 -> 0 | AG28: =IF((AF28-AF27)<0,"0",(AF28-AF27)) -> 0 | AH28: =AI27 -> 38251 | AI28: 38287 | AJ28: =IF((AI28-AI27)<0,"0",(AI28-AI27)) -> 36 | AK28: =AL27 -> 0 | AM28: =IF((AL28-AL27)<0,"0",(AL28-AL27)) -> 0 | AN28: =U28+X28+AA28+AD28+AG28+AJ28+AM28 -> 118
A29: =Gen!B34 -> 44554 | C29: =D28 -> 276454 | D29: 276529 | E29: =IF((D29-D28)<0,"0",(D29-D28)) -> 75 | F29: =G29 -> 0 | H29: =IF((G29-G28)<0,"0",(G29-G28)) -> 0 | I29: =J28 -> 8938 | J29: 8941 | K29: =IF((J29-J28)<0,"0",(J29-J28)) -> 3 | L29: =M28 -> 0 | N29: =IF((M29-M28)<0,"0",(M29-M28)) -> 0 | O29: =P28 -> 22839 | P29: 22848 | Q29: =IF((P29-P28)<0,"0",(P29-P28)) -> 9 | R29: =Q29+N29+K29+H29 -> 12 | S29: =T28 -> 80641 | T29: 80641 | U29: =IF((T29-T28)<0,"0",(T29-T28)) -> 0 | V29: =W28 -> 0 | X29: =IF((W29-W28)<0,"0",(W29-W28)) -> 0 | Y29: =Z28 -> 97497 | Z29: 97537 | AA29: =IF((Z29-Z28)<0,"0",(Z29-Z28)) -> 40 | AB29: =AC28 -> 23462 | AC29: 23478 | AD29: =IF((AC29-AC28)<0,"0",(AC29-AC28)) -> 16 | AE29: =AF28 -> 0 | AG29: =IF((AF29-AF28)<0,"0",(AF29-AF28)) -> 0 | AH29: =AI28 -> 38287 | AI29: 38323 | AJ29: =IF((AI29-AI28)<0,"0",(AI29-AI28)) -> 36 | AK29: =AL28 -> 0 | AM29: =IF((AL29-AL28)<0,"0",(AL29-AL28)) -> 0 | AN29: =U29+X29+AA29+AD29+AG29+AJ29+AM29 -> 92
A30: =Gen!B35 -> 44555 | C30: =D29 -> 276529 | D30: 276631 | E30: =IF((D30-D29)<0,"0",(D30-D29)) -> 102 | F30: =G30 -> 0 | H30: =IF((G30-G29)<0,"0",(G30-G29)) -> 0 | I30: =J29 -> 8941 | J30: 8944 | K30: =IF((J30-J29)<0,"0",(J30-J29)) -> 3 | L30: =M29 -> 0 | N30: =IF((M30-M29)<0,"0",(M30-M29)) -> 0 | O30: =P29 -> 22848 | P30: 22861 | Q30: =IF((P30-P29)<0,"0",(P30-P29)) -> 13 | R30: =Q30+N30+K30+H30 -> 16 | S30: =T29 -> 80641 | T30: 80677 | U30: =IF((T30-T29)<0,"0",(T30-T29)) -> 36 | V30: =W29 -> 0 | X30: =IF((W30-W29)<0,"0",(W30-W29)) -> 0 | Y30: =Z29 -> 97537 | Z30: 97579 | AA30: =IF((Z30-Z29)<0,"0",(Z30-Z29)) -> 42 | AB30: =AC29 -> 23478 | AC30: 23493 | AD30: =IF((AC30-AC29)<0,"0",(AC30-AC29)) -> 15 | AE30: =AF29 -> 0 | AG30: =IF((AF30-AF29)<0,"0",(AF30-AF29)) -> 0 | AH30: =AI29 -> 38323 | AI30: 38357 | AJ30: =IF((AI30-AI29)<0,"0",(AI30-AI29)) -> 34 | AK30: =AL29 -> 0 | AM30: =IF((AL30-AL29)<0,"0",(AL30-AL29)) -> 0 | AN30: =U30+X30+AA30+AD30+AG30+AJ30+AM30 -> 127
A31: =Gen!B36 -> 44556 | C31: =D30 -> 276631 | D31: 276737 | E31: =IF((D31-D30)<0,"0",(D31-D30)) -> 106 | F31: =G31 -> 0 | H31: =IF((G31-G30)<0,"0",(G31-G30)) -> 0 | I31: =J30 -> 8944 | J31: 8947 | K31: =IF((J31-J30)<0,"0",(J31-J30)) -> 3 | L31: =M30 -> 0 | N31: =IF((M31-M30)<0,"0",(M31-M30)) -> 0 | O31: =P30 -> 22861 | P31: 22873 | Q31: =IF((P31-P30)<0,"0",(P31-P30)) -> 12 | R31: =Q31+N31+K31+H31 -> 15 | S31: =T30 -> 80677 | T31: 80751 | U31: =IF((T31-T30)<0,"0",(T31-T30)) -> 74 | V31: =W30 -> 0 | X31: =IF((W31-W30)<0,"0",(W31-W30)) -> 0 | Y31: =Z30 -> 97579 | Z31: 97620 | AA31: =IF((Z31-Z30)<0,"0",(Z31-Z30)) -> 41 | AB31: =AC30 -> 23493 | AC31: 23507 | AD31: =IF((AC31-AC30)<0,"0",(AC31-AC30)) -> 14 | AE31: =AF30 -> 0 | AG31: =IF((AF31-AF30)<0,"0",(AF31-AF30)) -> 0 | AH31: =AI30 -> 38357 | AI31: 38392 | AJ31: =IF((AI31-AI30)<0,"0",(AI31-AI30)) -> 35 | AK31: =AL30 -> 0 | AM31: =IF((AL31-AL30)<0,"0",(AL31-AL30)) -> 0 | AN31: =U31+X31+AA31+AD31+AG31+AJ31+AM31 -> 164
A32: =Gen!B37 -> 44557 | B32: 10/27//2009 | C32: =D31 -> 276737 | D32: 276839 | E32: =IF((D32-D31)<0,"0",(D32-D31)) -> 102 | F32: =G31 -> 0 | H32: =IF((G32-G31)<0,"0",(G32-G31)) -> 0 | I32: =J31 -> 8947 | J32: 8951 | K32: =IF((J32-J31)<0,"0",(J32-J31)) -> 4 | L32: =M31 -> 0 | N32: =IF((M32-M31)<0,"0",(M32-M31)) -> 0 | O32: =P31 -> 22873 | P32: 22886 | Q32: =IF((P32-P31)<0,"0",(P32-P31)) -> 13 | R32: =Q32+N32+K32+H32 -> 17 | S32: =T31 -> 80751 | T32: 80821 | U32: =IF((T32-T31)<0,"0",(T32-T31)) -> 70 | V32: =W31 -> 0 | X32: =IF((W32-W31)<0,"0",(W32-W31)) -> 0 | Y32: =Z31 -> 97620 | Z32: 97663 | AA32: =IF((Z32-Z31)<0,"0",(Z32-Z31)) -> 43 | AB32: =AC31 -> 23507 | AC32: 23523 | AD32: =IF((AC32-AC31)<0,"0",(AC32-AC31)) -> 16 | AE32: =AF31 -> 0 | AG32: =IF((AF32-AF31)<0,"0",(AF32-AF31)) -> 0 | AH32: =AI31 -> 38392 | AI32: 38427 | AJ32: =IF((AI32-AI31)<0,"0",(AI32-AI31)) -> 35 | AK32: =AL31 -> 0 | AM32: =IF((AL32-AL31)<0,"0",(AL32-AL31)) -> 0 | AN32: =U32+X32+AA32+AD32+AG32+AJ32+AM32 -> 164
A33: =Gen!B38 -> 44558 | C33: =D32 -> 276839 | D33: 276948 | E33: =IF((D33-D32)<0,"0",(D33-D32)) -> 109 | F33: =G32 -> 0 | H33: =IF((G33-G32)<0,"0",(G33-G32)) -> 0 | I33: =J32 -> 8951 | J33: 8954 | K33: =IF((J33-J32)<0,"0",(J33-J32)) -> 3 | L33: =M32 -> 0 | N33: =IF((M33-M32)<0,"0",(M33-M32)) -> 0 | O33: =P32 -> 22886 | P33: 22895 | Q33: =IF((P33-P32)<0,"0",(P33-P32)) -> 9 | R33: =Q33+N33+K33+H33 -> 12 | S33: =T32 -> 80821 | T33: 80822 | U33: =IF((T33-T32)<0,"0",(T33-T32)) -> 1 | V33: =W32 -> 0 | X33: =IF((W33-W32)<0,"0",(W33-W32)) -> 0 | Y33: =Z32 -> 97663 | Z33: 97702 | AA33: =IF((Z33-Z32)<0,"0",(Z33-Z32)) -> 39 | AB33: =AC32 -> 23523 | AC33: 23537 | AD33: =IF((AC33-AC32)<0,"0",(AC33-AC32)) -> 14 | AE33: =AF32 -> 0 | AG33: =IF((AF33-AF32)<0,"0",(AF33-AF32)) -> 0 | AH33: =AI32 -> 38427 | AI33: 38463 | AJ33: =IF((AI33-AI32)<0,"0",(AI33-AI32)) -> 36 | AK33: =AL32 -> 0 | AM33: =IF((AL33-AL32)<0,"0",(AL33-AL32)) -> 0 | AN33: =U33+X33+AA33+AD33+AG33+AJ33+AM33 -> 90
A34: =Gen!B39 -> 44559 | C34: =D33 -> 276948 | D34: 277059 | E34: =IF((D34-D33)<0,"0",(D34-D33)) -> 111 | F34: =G33 -> 0 | H34: =IF((G34-G33)<0,"0",(G34-G33)) -> 0 | I34: =J33 -> 8954 | J34: 8959 | K34: =IF((J34-J33)<0,"0",(J34-J33)) -> 5 | L34: =M33 -> 0 | N34: =IF((M34-M33)<0,"0",(M34-M33)) -> 0 | O34: =P33 -> 22895 | P34: 22909 | Q34: =IF((P34-P33)<0,"0",(P34-P33)) -> 14 | R34: =Q34+N34+K34+H34 -> 19 | S34: =T33 -> 80822 | T34: 80870 | U34: =IF((T34-T33)<0,"0",(T34-T33)) -> 48 | V34: =W33 -> 0 | X34: =IF((W34-W33)<0,"0",(W34-W33)) -> 0 | Y34: =Z33 -> 97702 | Z34: 97746 | AA34: =IF((Z34-Z33)<0,"0",(Z34-Z33)) -> 44 | AB34: =AC33 -> 23537 | AC34: 23552 | AD34: =IF((AC34-AC33)<0,"0",(AC34-AC33)) -> 15 | AE34: =AF33 -> 0 | AG34: =IF((AF34-AF33)<0,"0",(AF34-AF33)) -> 0 | AH34: =AI33 -> 38463 | AI34: 38500 | AJ34: =IF((AI34-AI33)<0,"0",(AI34-AI33)) -> 37 | AK34: =AL33 -> 0 | AM34: =IF((AL34-AL33)<0,"0",(AL34-AL33)) -> 0 | AN34: =U34+X34+AA34+AD34+AG34+AJ34+AM34 -> 144
A35: =Gen!B40 -> 44560 | C35: =D34 -> 277059 | D35: 277161 | E35: =IF((D35-D34)<0,"0",(D35-D34)) -> 102 | F35: =G34 -> 0 | H35: =IF((G35-G34)<0,"0",(G35-G34)) -> 0 | I35: =J34 -> 8959 | J35: 8962 | K35: =IF((J35-J34)<0,"0",(J35-J34)) -> 3 | L35: =M34 -> 0 | N35: =IF((M35-M34)<0,"0",(M35-M34)) -> 0 | O35: =P34 -> 22909 | P35: 22919 | Q35: =IF((P35-P34)<0,"0",(P35-P34)) -> 10 | R35: =Q35+N35+K35+H35 -> 13 | S35: =T34 -> 80870 | T35: 80895 | U35: =IF((T35-T34)<0,"0",(T35-T34)) -> 25 | V35: =W34 -> 0 | X35: =IF((W36-W34)<0,"0",(W36-W34)) -> 0 | Y35: =Z34 -> 97746 | Z35: 97789 | AA35: =IF((Z35-Z34)<0,"0",(Z35-Z34)) -> 43 | AB35: =AC34 -> 23552 | AC35: 23566 | AD35: =IF((AC35-AC34)<0,"0",(AC35-AC34)) -> 14 | AE35: =AF34 -> 0 | AG35: =IF((AF35-AF34)<0,"0",(AF35-AF34)) -> 0 | AH35: =AI34 -> 38500 | AI35: 38536 | AJ35: =IF((AI35-AI34)<0,"0",(AI35-AI34)) -> 36 | AK35: =AL34 -> 0 | AM35: =IF((AL35-AL34)<0,"0",(AL35-AL34)) -> 0 | AN35: =U35+X35+AA35+AD35+AG35+AJ35+AM35 -> 118
A36: =Gen!B41 -> 44561 | C36: =D35 -> 277161 | D36: 277263 | E36: =IF((D36-D35)<0,"0",(D36-D35)) -> 102 | F36: =G35 -> 0 | H36: =IF((G36-G35)<0,"0",(G36-G35)) -> 0 | I36: =J35 -> 8962 | J36: 8965 | K36: =IF((J36-J35)<0,"0",(J36-J35)) -> 3 | L36: =M35 -> 0 | N36: =IF((M36-M35)<0,"0",(M36-M35)) -> 0 | O36: =P35 -> 22919 | P36: 22928 | Q36: =IF((P36-P35)<0,"0",(P36-P35)) -> 9 | R36: =Q36+N36+K36+H36 -> 12 | S36: =T35 -> 80895 | T36: 80895 | U36: =IF((T36-T35)<0,"0",(T36-T35)) -> 0 | V36: =W35 -> 0 | X36: =IF((W37-W35)<0,"0",(W37-W35)) -> 0 | Y36: =Z35 -> 97789 | Z36: 97828 | AA36: =IF((Z36-Z35)<0,"0",(Z36-Z35)) -> 39 | AB36: =AC35 -> 23566 | AC36: 23577 | AD36: =IF((AC36-AC35)<0,"0",(AC36-AC35)) -> 11 | AE36: =AF35 -> 0 | AG36: =IF((AF36-AF35)<0,"0",(AF36-AF35)) -> 0 | AH36: =AI35 -> 38536 | AI36: 38569 | AJ36: =IF((AI36-AI35)<0,"0",(AI36-AI35)) -> 33 | AK36: =AL35 -> 0 | AM36: =IF((AL36-AL35)<0,"0",(AL36-AL35)) -> 0 | AN36: =U36+X36+AA36+AD36+AG36+AJ36+AM36 -> 83
C37: =D36 -> 277263 | D37: 277383 | E37: =IF((D37-D36)<0,"0",(D37-D36)) -> 120 | F37: =G36 -> 0 | H37: =IF((G37-G36)<0,"0",(G37-G36)) -> 0 | I37: =J36 -> 8965 | K37: =IF((J37-J36)<0,"0",(J37-J36)) -> 0 | L37: =M36 -> 0 | N37: =IF((M37-M36)<0,"0",(M37-M36)) -> 0 | O37: =P36 -> 22928 | Q37: =IF((P37-P36)<0,"0",(P37-P36)) -> 0 | R37: =Q37+N37+K37+H37 -> 0 | S37: =T36 -> 80895 | T37: 80966 | U37: =IF((T37-T36)<0,"0",(T37-T36)) -> 71 | V37: =W36 -> 0 | Z37: 97863 | AA37: =IF((Z37-Z36)<0,"0",(Z37-Z36)) -> 35 | AB37: =AC36 -> 23577 | AC37: 23590 | AD37: =IF((AC37-AC36)<0,"0",(AC37-AC36)) -> 13 | AE37: =AF36 -> 0 | AI37: 38601 | AJ37: =IF((AI37-AI36)<0,"0",(AI37-AI36)) -> 32 | AK37: =AL36 -> 0 | AN37: =U37+X37+AA37+AD37+AG37+AJ37+AM37 -> 151
C38: TOTAL USAGE | E38: =SUM(E6:E36) -> 2480 | F38: KL | H38: =SUM(H6:H37) -> 0 | K38: =SUM(K6:K37) -> 94 | N38: =M38-M37 -> 0 | Q38: =P38-O38 -> 0 | R38: =Q38+N38+K38+H38 -> 94 | U38: =SUM(U6:U37) -> 1016 | X38: =SUM(X13:X37) -> 0 | AA38: =SUM(AA6:AA37) -> 1219 | AD38: =SUM(AD6:AD37) -> 445 | AG38: =SUM(AG6:AG37) -> 0 | AJ38: =SUM(AJ6:AJ37) -> 1124 | AM38: =SUM(AM6:AM37) -> 0 | AN38: =U38+X38+AA38+AD38+AG38+AJ38+AM38 -> 3804
C42: WATER TANK LEVEL
C43: RAW WATER TANK NO.1 | E43: RAW WATER TANK NO.2 | G43: TREATED WATER TANK | I43: TREATED -HILL TANK | K43: TOTAL WATER AVAILABLE
C44: CAPACITY 217 m³ | E44: CAPACITY 92 m³ | G44: CAPACITY 146 m³ | I44: CAPACITY 213 m³
C45: cm | D45: m³ | E45: cm | F45: m³ | H45: m³ | J45: m³ | K45: m³
A46: =Gen!B11 -> 44531 | C46: 300 | D46: =C46*217/300 -> 217 | E46: 290 | F46: =E46*92/305 -> 87.47541 | G46: 200 | H46: =G46*146/383 -> 76.240209 | I46: 288 | J46: =I46*213/308 -> 199.16883 | K46: =D46+F46+H46+J46 -> 579.88445
A47: =Gen!B12 -> 44532 | C47: 298 | D47: =C47*217/300 -> 215.55333 | E47: 275 | F47: =E47*92/305 -> 82.95082 | G47: 195 | H47: =G47*146/383 -> 74.334204 | I47: 291 | J47: =I47*213/308 -> 201.24351 | K47: =D47+F47+H47+J47 -> 574.08186
A48: =Gen!B13 -> 44533 | C48: 300 | D48: =C48*217/300 -> 217 | E48: 296 | F48: =E48*92/305 -> 89.285246 | G48: 125 | H48: =G48*146/383 -> 47.650131 | I48: 290 | J48: =I48*213/308 -> 200.55195 | K48: =D48+F48+H48+J48 -> 554.48732
A49: =Gen!B14 -> 44534 | C49: 280 | D49: =C49*217/300 -> 202.53333 | E49: 245 | F49: =E49*92/305 -> 73.901639 | G49: 150 | H49: =G49*146/383 -> 57.180157 | I49: 290 | J49: =I49*213/308 -> 200.55195 | K49: =D49+F49+H49+J49 -> 534.16708
A50: =Gen!B15 -> 44535 | C50: 215 | D50: =C50*217/300 -> 155.51667 | E50: 180 | F50: =E50*92/305 -> 54.295082 | G50: 295 | H50: =G50*146/383 -> 112.45431 | I50: 282 | J50: =I50*213/308 -> 195.01948 | K50: =D50+F50+H50+J50 -> 517.28554
A51: =Gen!B16 -> 44536 | C51: 250 | D51: =C51*217/300 -> 180.83333 | E51: 215 | F51: =E51*92/305 -> 64.852459 | G51: 200 | H51: =G51*146/383 -> 76.240209 | I51: 289 | J51: =I51*213/308 -> 199.86039 | K51: =D51+F51+H51+J51 -> 521.78639
A52: =Gen!B17 -> 44537 | C52: 195 | D52: =C52*217/300 -> 141.05 | E52: 155 | F52: =E52*92/305 -> 46.754098 | G52: 300 | H52: =G52*146/383 -> 114.36031 | I52: 200 | J52: =I52*213/308 -> 138.31169 | K52: =D52+F52+H52+J52 -> 440.4761
A53: =Gen!B18 -> 44538 | C53: 235 | D53: =C53*217/300 -> 169.98333 | E53: 200 | F53: =E53*92/305 -> 60.327869 | G53: 300 | H53: =G53*146/383 -> 114.36031 | I53: 285 | J53: =I53*213/308 -> 197.09416 | K53: =D53+F53+H53+J53 -> 541.76567
A54: =Gen!B19 -> 44539 | C54: 240 | D54: =C54*217/300 -> 173.6 | E54: 200 | F54: =E54*92/305 -> 60.327869 | G54: 150 | H54: =G54*146/383 -> 57.180157 | I54: 285 | J54: =I54*213/308 -> 197.09416 | K54: =D54+F54+H54+J54 -> 488.20218
A55: =Gen!B20 -> 44540 | C55: 190 | D55: =C55*217/300 -> 137.43333 | E55: 150 | F55: =E55*92/305 -> 45.245902 | G55: 280 | H55: =G55*146/383 -> 106.73629 | I55: 290 | J55: =I55*213/308 -> 200.55195 | K55: =D55+F55+H55+J55 -> 489.96748
A56: =Gen!B21 -> 44541 | C56: 300 | D56: =C56*217/300 -> 217 | E56: 260 | F56: =E56*92/305 -> 78.42623 | G56: 100 | H56: =G56*146/383 -> 38.120104 | I56: 285 | J56: =I56*213/308 -> 197.09416 | K56: =D56+F56+H56+J56 -> 530.64049
A57: =Gen!B22 -> 44542 | C57: 240 | D57: =C57*217/300 -> 173.6 | E57: 200 | F57: =E57*92/305 -> 60.327869 | G57: 300 | H57: =G57*146/383 -> 114.36031 | I57: 290 | J57: =I57*213/308 -> 200.55195 | K57: =D57+F57+H57+J57 -> 548.84013
... A77: =Gen!B42 -> 0 | C77: 150 | D77: =C77*217/300 -> 108.5 | E77: 95 | F77: =E77*92/305 -> 28.655738 | G77: 300 | H77: =G77*146/383 -> 114.36031 | I77: 290 | J77: =I77*213/308 -> 200.55195 | K77: =D77+F77+H77+J77 -> 452.068
A78: =Gen!B43 -> BF

Sheet LPG_Graph
A1: Date | B1: Usage KG | C1: Occ %
A2: =Gen!B11 -> 44531 | B2: ='Lpg (2)'!G10 -> 101.244 | C2: =Gen!C11 -> 0.0519
A3: =Gen!B12 -> 44532 | B3: ='Lpg (2)'!G11 -> 70.312 | C3: =Gen!C12 -> 0.05
A4: =Gen!B13 -> 44533 | B4: ='Lpg (2)'!G12 -> 59.576 | C4: =Gen!C13 -> 0.05
A5: =Gen!B14 -> 44534 | B5: ='Lpg (2)'!G13 -> 61.512 | C5: =Gen!C14 -> 0.08
A6: =Gen!B15 -> 44535 | B6: ='Lpg (2)'!G14 -> 87.34 | C6: =Gen!C15 -> 0.05
A7: =Gen!B16 -> 44536 | B7: ='Lpg (2)'!G15 -> 107.492 | C7: =Gen!C16 -> 0.0779
A8: =Gen!B17 -> 44537 | B8: ='Lpg (2)'!G16 -> 90.684 | C8: =Gen!C17 -> 0.0779
A9: =Gen!B18 -> 44538 | B9: ='Lpg (2)'!G17 -> 99.88 | C9: =Gen!C18 -> 0.12
A10: =Gen!B19 -> 44539 | B10: ='Lpg (2)'!G18 -> 108.988 | C10: =Gen!C19 -> 0.09
A11: =Gen!B20 -> 44540 | B11: ='Lpg (2)'!G19 -> 110 | C11: =Gen!C20 -> 0.12
A12: =Gen!B21 -> 44541 | B12: ='Lpg (2)'!G20 -> 105.38 | C12: =Gen!C21 -> 0.12
A13: =Gen!B22 -> 44542 | B13: ='Lpg (2)'!G21 -> 106.656 | C13: =Gen!C22 -> 0.12
... A32: =Gen!B41 -> 44561 | B32: ='Lpg (2)'!G40 -> 163.02 | C32: =Gen!C41 -> 0.61

Sheet Daily report Gen
A1: =A6 -> 44531
K3: GENERATOR NO.1 | N3: GENERATOR NO.2 | Q3: GENERATOR NO.4 | T3: GENERATOR NO.5 | W3: GENERATOR NO.6
A4: DATE | B4: OCC% | C4: D-TANK A | D4: D-TANK B | E4: DELIVERY DATE | F4: DELIVERY | G4: ISSUED-VEHICLE | H4: OTHERS | I4: M-R LV PANEL 1. KW-HR | J4: M-R LV PANEL 2. KW-HR | K4: OPEN HRS READING | L4: CLOSE HRS READING | M4: RUNNING HRS | N4: OPEN HRS READING | O4: CLOSE HRS READING | P4: RUNNING HRS | Q4: OPEN HRS READING | R4: CLOSE HRS READING | S4: RUNNING HRS | T4: OPEN HRS READING | U4: CLOSE HRS READING | V4: RUNNING HRS | W4: OPEN HRS READING | X4: CLOSE HRS READING | Y4: RUNNING HRS | Z4: TOTAL RUNNING HRS | AA4: MAX KW | AB4: MIN-KW | AC4: TOTAL DIESEL CONS.
L5: 38411 | O5: 32025 | R5: 37151 | U5: 35506 | X5: 23836
A6: =Gen!B11 -> 44531 | B6: =Gen!C11 -> 0.0519 | C6: 26400.87 | D6: 16818.69 | G6: 55.31 | I6: 33422.2 | J6: 22226.7 | K6: =L5 -> 38411 | L6: 38425 | M6: =L6-K6 -> 14 | N6: =O5 -> 32025 | O6: 32025 | P6: =O6-N6 -> 0 | Q6: =R5 -> 37151 | R6: 37157 | S6: =R6-Q6 -> 6 | T6: =U5 -> 35506 | U6: 35516 | V6: =U6-T6 -> 10 | W6: =X5 -> 23836 | X6: 23836 | Y6: =X6-W6 -> 0 | Z6: =Y6+V6+S6+P6+M6 -> 30 | AA6: 320 | AB6: 140 | AC6: =Gen!T11 -> 1340.69
A7: =Gen!B12 -> 44532 | B7: =Gen!C12 -> 0.05 | C7: 26400.87 | D7: 15422.69 | G7: 596.04 | I7: 33427.9 | J7: 22230.1 | K7: =L6 -> 38425 | L7: 38425 | M7: =L7-K7 -> 0 | N7: =O6 -> 32025 | O7: 32025 | P7: =O7-N7 -> 0 | Q7: =R6 -> 37157 | R7: 37165 | S7: =R7-Q7 -> 8 | T7: =U6 -> 35516 | U7: 35526 | V7: =U7-T7 -> 10 | W7: =X6 -> 23836 | X7: 23851 | Y7: =X7-W7 -> 15 | Z7: =Y7+V7+S7+P7+M7 -> 33 | AA7: 295 | AB7: 125 | AC7: =Gen!T12 -> 1268.81
A8: =Gen!B13 -> 44533 | B8: =Gen!C13 -> 0.05 | C8: 26400.87 | D8: 13557.84 | I8: 33433.3 | J8: 22233.2 | K8: =L7 -> 38425 | L8: 38439 | M8: =L8-K8 -> 14 | N8: =O7 -> 32025 | O8: 32025 | P8: =O8-N8 -> 0 | Q8: =R7 -> 37165 | R8: 37165 | S8: =R8-Q8 -> 0 | T8: =U7 -> 35526 | U8: 35536 | V8: =U8-T8 -> 10 | W8: =X7 -> 23851 | X8: 23851 | Y8: =X8-W8 -> 0 | Z8: =Y8+V8+S8+P8+M8 -> 24 | AA8: 290 | AB8: 125 | AC8: =Gen!T13 -> 1177.17
A9: =Gen!B14 -> 44534 | B9: =Gen!C14 -> 0.08 | C9: 26400.87 | D9: 12380.67 | G9: 199.51 | I9: 33438.9 | J9: 22236.6 | K9: =L8 -> 38439 | L9: 38440 | M9: =L9-K9 -> 1 | N9: =O8 -> 32025 | O9: 32025 | P9: =O9-N9 -> 0 | Q9: =R8 -> 37165 | R9: 37165 | S9: =R9-Q9 -> 0 | T9: =U8 -> 35536 | U9: 35546 | V9: =U9-T9 -> 10 | W9: =X8 -> 23851 | X9: 23865 | Y9: =X9-W9 -> 14 | Z9: =Y9+V9+S9+P9+M9 -> 25 | AA9: 278 | AB9: 116 | AC9: =Gen!T14 -> 1293.22
A10: =Gen!B15 -> 44535 | B10: =Gen!C15 -> 0.05 | C10: 26400.87 | D10: 10888.67 | G10: 53.33 | I10: 33444.7 | J10: 22240.2 | K10: =L9 -> 38440 | L10: 38455 | M10: =L10-K10 -> 15 | N10: =O9 -> 32025 | O10: 32025 | P10: =O10-N10 -> 0 | Q10: =R9 -> 37165 | R10: 37165 | S10: =R10-Q10 -> 0 | T10: =U9 -> 35546 | U10: 35556 | V10: =U10-T10 -> 10 | W10: =X9 -> 23865 | X10: 23865 | Y10: =X10-W10 -> 0 | Z10: =Y10+V10+S10+P10+M10 -> 25 | AA10: 280 | AB10: 115 | AC10: =Gen!T15 -> 1246.93
A11: =Gen!B16 -> 44536 | B11: =Gen!C16 -> 0.0779 | C11: 26400.87 | D11: 9586.68 | G11: 67.4 | I11: 33450.1 | J11: 22243.4 | K11: =L10 -> 38455 | L11: 38455 | M11: =L11-K11 -> 0 | N11: =O10 -> 32025 | O11: 32025 | P11: =O11-N11 -> 0 | Q11: =R10 -> 37165 | R11: 37165 | S11: =R11-Q11 -> 0 | T11: =U10 -> 35556 | U11: 35566 | V11: =U11-T11 -> 10 | W11: =X10 -> 23865 | X11: 23879 | Y11: =X11-W11 -> 14 | Z11: =Y11+V11+S11+P11+M11 -> 24 | AA11: 285 | AB11: 115 | AC11: =Gen!T16 -> 1325.89
A12: =Gen!B17 -> 44537 | B12: =Gen!C17 -> 0.0779 | C12: 26400.87 | D12: 8193.39 | G12: 135.94 | I12: 33456.1 | J12: 22246.8 | K12: =L11 -> 38455 | L12: 38470 | M12: =L12-K12 -> 15 | N12: =O11 -> 32025 | O12: 32025 | P12: =O12-N12 -> 0 | Q12: =R11 -> 37165 | R12: 37165 | S12: =R12-Q12 -> 0 | T12: =U11 -> 35566 | U12: 35575 | V12: =U12-T12 -> 9 | W12: =X11 -> 23879 | X12: 23879 | Y12: =X12-W12 -> 0 | Z12: =Y12+V12+S12+P12+M12 -> 24 | AA12: 290 | AB12: 120 | AC12: =Gen!T17 -> 1368.94
A13: =Gen!B18 -> 44538 | B13: =Gen!C18 -> 0.12 | C13: 26400.87 | D13: 6688.51 | G13: 83.59 | I13: 33462.2 | J13: 22250.7 | K13: =L12 -> 38470 | L13: 38470 | M13: =L13-K13 -> 0 | N13: =O12 -> 32025 | O13: 32025 | P13: =O13-O12 -> 0 | Q13: =R12 -> 37165 | R13: 37181 | S13: =R13-Q13 -> 16 | T13: =U12 -> 35575 | U13: 35575 | V13: =U13-T13 -> 0 | W13: =X12 -> 23879 | X13: 23895 | Y13: =X13-W13 -> 16 | Z13: =Y13+V13+S13+P13+M13 -> 32 | AA13: 295 | AB13: 120 | AC13: =Gen!T18 -> 1527.6
A14: =Gen!B19 -> 44539 | B14: =Gen!C19 -> 0.09 | C14: 26400.87 | D14: 5077.32 | G14: 51.98 | I14: 33468.3 | J14: 22254.3 | K14: =L13 -> 38470 | L14: 38484 | M14: =L14-K14 -> 14 | N14: =O14 -> 32025 | O14: 32025 | P14: =O14-O13 -> 0 | Q14: =R13 -> 37181 | R14: 37192 | S14: =R14-Q14 -> 11 | T14: =U13 -> 35575 | U14: 35575 | V14: =U14-T14 -> 0 | W14: =X13 -> 23895 | X14: 23895 | Y14: =X14-W14 -> 0 | Z14: =Y14+V14+S14+P14+M14 -> 25 | AA14: 285 | AB14: 120 | AC14: =Gen!T19 -> 1371.66
A15: =Gen!B20 -> 44540 | B15: =Gen!C20 -> 0.12 | C15: 26400.87 | D15: 3653.68 | G15: 448.65 | I15: 33474.2 | J15: 22258.1 | K15: =L14 -> 38484 | L15: 38484 | M15: =L15-K15 -> 0 | N15: =O15 -> 32025 | O15: 32025 | P15: =O15-O14 -> 0 | Q15: =R14 -> 37192 | R15: 37192 | S15: =R15-Q15 -> 0 | T15: =U14 -> 35575 | U15: 35586 | V15: =U15-T15 -> 11 | W15: =X14 -> 23895 | X15: 23909 | Y15: =X15-W15 -> 14 | Z15: =Y15+V15+S15+P15+M15 -> 25 | AA15: 280 | AB15: 115 | AC15: =Gen!T20 -> 1347.33
A16: =Gen!B21 -> 44541 | B16: =Gen!C21 -> 0.12 | C16: 26400.87 | D16: 1857.7 | G16: 37.87 | I16: 33480 | J16: 22261.8 | K16: =L15 -> 38484 | L16: 38499 | M16: =L16-K16 -> 15 | N16: =O15 -> 32025 | O16: 32025 | P16: =O16-O15 -> 0 | Q16: =R15 -> 37192 | R16: 37208 | S16: =R16-Q16 -> 16 | T16: =U14 -> 35575 | U16: 35586 | V16: =U16-T16 -> 11 | W16: =X15 -> 23909 | X16: 23909 | Y16: =X16-W16 -> 0 | Z16: =Y16+V16+S16+P16+M16 -> 42 | AA16: 285 | AB16: 120 | AC16: =Gen!T21 -> 1512.79
A17: =Gen!B22 -> 44542 | B17: =Gen!C22 -> 0.12 | C17: 24850.21 | D17: 1857.7 | G17: 68.16 | I17: 33486.2 | J17: 22266.1 | K17: =L16 -> 38499 | L17: 38499 | M17: =L17-K17 -> 0 | N17: =O16 -> 32025 | O17: 32025 | P17: =O17-O16 -> 0 | Q17: =R16 -> 37208 | R17: 37218 | S17: =R17-Q17 -> 10 | T17: =U16 -> 35586 | U17: 35586 | V17: =U17-T17 -> 0 | W17: =X16 -> 23909 | X17: 23924 | Y17: =X17-W17 -> 15 | Z17: =Y17+V17+S17+P17+M17 -> 25 | AA17: 350 | AB17: 140 | AC17: =Gen!T22 -> 1485.24
A18: =Gen!B23 -> 44543 | B18: =Gen!C23 -> 0.16 | C18: 23296.81 | D18: 1857.7 | G18: 103.25 | I18: 33492.7 | J18: 22270 | K18: =L17 -> 38499 | L18: 38513 | M18: =L18-K18 -> 14 | N18: =O17 -> 32025 | O18: 32025 | P18: =O18-O17 -> 0 | Q18: =R17 -> 37218 | R18: 37228 | S18: =R18-Q18 -> 10 | T18: =U17 -> 35586 | U18: 35592 | V18: =U18-T18 -> 6 | W18: =X17 -> 23924 | X18: 23924 | Y18: =X18-W18 -> 0 | Z18: =Y18+V18+S18+P18+M18 -> 30 | AA18: 370 | AB18: 145 | AC18: =Gen!T23 -> 1579.63
A19: =Gen!B24 -> 44544 | B19: =Gen!C24 -> 0.17 | C19: 22670.93 | D19: 18800.7 | G19: 194.5 | I19: 33499.8 | J19: 22274.1 | K19: =L18 -> 38513 | L19: 38513 | M19: =L19-K19 -> 0 | N19: =O18 -> 32025 | O19: 32025 | P19: =O19-O18 -> 0 | Q19: =R18 -> 37228 | R19: 37238 | S19: =R19-Q19 -> 10 | T19: =U18 -> 35592 | U19: 35592 | V19: =U19-T19 -> 0 | W19: =X18 -> 23924 | X19: 23939 | Y19: =X19-W19 -> 15 | Z19: =Y19+V19+S19+P19+M19 -> 25 | AA19: 350 | AB19: 140 | AC19: =Gen!T24 -> 1342.22
A20: =Gen!B25 -> 44545 | B20: =Gen!C25 -> 0.18 | C20: 21134.21 | D20: 18800.7 | I20: 33506.1 | J20: 22277.8 | K20: =L19 -> 38513 | L20: 38530 | M20: =L20-K20 -> 17 | N20: =O19 -> 32025 | O20: 32025 | P20: =O20-O19 -> 0 | Q20: =R19 -> 37238 | R20: 37248 | S20: =R20-Q20 -> 10 | T20: =U19 -> 35592 | U20: 35603 | V20: =U20-T20 -> 11 | W20: =X19 -> 23939 | X20: 23939 | Y20: =X20-W20 -> 0 | Z20: =Y20+V20+S20+P20+M20 -> 38 | AA20: 370 | AB20: 135 | AC20: =Gen!T25 -> 1601.91
A21: =Gen!B26 -> 44546 | B21: =Gen!C26 -> 0.16 | C21: 19532.3 | D21: 18800.7 | G21: 176.76 | I21: 33512.7 | J21: 22281.4 | K21: =L20 -> 38530 | L21: 38531 | M21: =L21-K21 -> 1 | N21: =O20 -> 32025 | O21: 32025 | P21: =O21-O20 -> 0 | Q21: =R20 -> 37248 | R21: 37258 | S21: =R21-Q21 -> 10 | T21: =U20 -> 35603 | U21: 35603 | V21: =U21-T21 -> 0 | W21: =X20 -> 23939 | X21: 23954 | Y21: =X21-W21 -> 15 | Z21: =Y21+V21+S21+P21+M21 -> 26 | AA21: 350 | AB21: 140 | AC21: =Gen!T26 -> 1526.57
A22: =Gen!B27 -> 44547 | B22: =Gen!C27 -> 0.16 | C22: 24800.7 | D22: 26828.97 | G22: 115.53 | I22: 33519.5 | J22: 22285.5 | K22: =L21 -> 38531 | L22: 38546 | M22: =L22-K22 -> 15 | N22: =O21 -> 32025 | O22: 32025 | P22: =O22-O21 -> 0 | Q22: =R21 -> 37258 | R22: 37258 | S22: =R22-Q22 -> 0 | T22: =U21 -> 35603 | U22: 35613 | V22: =U22-T22 -> 10 | W22: =X21 -> 23954 | X22: 23954 | Y22: =X22-W22 -> 0 | Z22: =Y22+V22+S22+P22+M22 -> 25 | AA22: 320 | AB22: 145 | AC22: =Gen!T27 -> 1519.37
A23: =Gen!B28 -> 44548 | B23: =Gen!C28 -> 0.13 | C23: 24800.7 | D23: 25194.07 | G23: 347 | I23: 33526.3 | J23: 22289.4 | K23: =L22 -> 38546 | L23: 38546 | M23: =L23-K23 -> 0 | N23: =O22 -> 32025 | O23: 32025 | P23: =O23-O22 -> 0 | Q23: =R22 -> 37258 | R23: 37268 | S23: =R23-Q23 -> 10 | T23: =U22 -> 35613 | U23: 35613 | V23: =U23-T23 -> 0 | W23: =X22 -> 23954 | X23: 23968 | Y23: =X23-W23 -> 14 | Z23: =Y23+V23+S23+P23+M23 -> 24 | AA23: 350 | AB23: 140 | AC23: =Gen!T28 -> 1531.62
A24: =Gen!B29 -> 44549 | B24: =Gen!C29 -> 0.12 | C24: 24800.7 | D24: 23315.45 | G24: 28.9 | I24: 33533.1 | J24: 22293.7 | K24: =L23 -> 38546 | L24: 38556 | M24: =L24-K24 -> 10 | N24: =O23 -> 32025 | O24: 32025 | P24: =O24-N24 -> 0 | Q24: =R23 -> 37268 | R24: 37284 | S24: =R24-Q24 -> 16 | T24: =U23 -> 35613 | U24: 35613 | V24: =U24-T24 -> 0 | W24: =X23 -> 23968 | X24: 23975 | Y24: =X24-W24 -> 7 | Z24: =Y24+V24+S24+P24+M24 -> 33 | AA24: 380 | AB24: 150 | AC24: =Gen!T29 -> 1590.66
A25: =Gen!B30 -> 44550 | B25: =Gen!C30 -> 0.06 | C25: 24800.7 | D25: 21695.89 | G25: 248.49 | I25: 33540.1 | J25: 22297.9 | K25: =L24 -> 38556 | L25: 38556 | M25: =L25-K25 -> 0 | N25: =O24 -> 32025 | O25: 32025 | P25: =O25-N25 -> 0 | Q25: =R24 -> 37284 | R25: 37294 | S25: =R25-Q25 -> 10 | T25: =U24 -> 35613 | U25: 35613 | V25: =U25-T25 -> 0 | W25: =X24 -> 23975 | X25: 23989 | Y25: =X25-W25 -> 14 | Z25: =Y25+V25+S25+P25+M25 -> 24 | AA25: 355 | AB25: 145 | AC25: =Gen!T30 -> 1280.58
A26: =Gen!B31 -> 44551 | B26: =Gen!C31 -> 0.1 | C26: 24800.7 | D26: 20166.82 | G26: 81 | I26: 33546.7 | J26: 22301.7 | K26: =L25 -> 38556 | L26: 38566 | M26: =L26-K26 -> 10 | N26: =O25 -> 32025 | O26: 32025 | P26: =O26-N26 -> 0 | Q26: =R25 -> 37294 | R26: 37304 | S26: =R26-Q26 -> 10 | T26: =U25 -> 35613 | U26: 35632 | V26: =U26-T26 -> 19 | W26: =X25 -> 23989 | X26: 23989 | Y26: =X26-W26 -> 0 | Z26: =Y26+V26+S26+P26+M26 -> 39 | AA26: 370 | AB26: 145 | AC26: =Gen!T31 -> 1850.97
A27: =Gen!B32 -> 44552 | B27: =Gen!C32 -> 0.17 | C27: 24800.7 | D27: 18231.85 | G27: 289.43 | I27: 33553.3 | J27: 22305.8 | K27: =L26 -> 38566 | L27: 38566 | M27: =L27-K27 -> 0 | N27: =O26 -> 32025 | O27: 32025 | P27: =O27-N27 -> 0 | Q27: =R26 -> 37304 | R27: 37316 | S27: =R27-Q27 -> 12 | T27: =U26 -> 35632 | U27: 35641 | V27: =U27-T27 -> 9 | W27: =X26 -> 23989 | X27: 24003 | Y27: =X27-W27 -> 14 | Z27: =Y27+V27+S27+P27+M27 -> 35 | AA27: 365 | AB27: 170 | AC27: =Gen!T32 -> 1693.83
A28: =Gen!B33 -> 44553 | B28: =Gen!C33 -> 0.17 | C28: 24800.7 | D28: 16248.59 | G28: 122.64 | I28: 33560.4 | J28: 22310.1 | K28: =L27 -> 38566 | L28: 38581 | M28: =L28-K28 -> 15 | N28: =O27 -> 32025 | O28: 32025 | P28: =O28-N28 -> 0 | Q28: =R27 -> 37316 | R28: 37327 | S28: =R28-Q28 -> 11 | T28: =U27 -> 35641 | U28: 35653 | V28: =U28-T28 -> 12 | W28: =X27 -> 24003 | X28: 24003 | Y28: =X28-W28 -> 0 | Z28: =Y28+V28+S28+P28+M28 -> 38 | AA28: 381 | AB28: 169 | AC28: =Gen!T33 -> 1680.85
A29: =Gen!B34 -> 44554 | B29: =Gen!C34 -> 0.47 | C29: 24800.7 | D29: 14445.1 | I29: 33564.1 | J29: 22314.9 | K29: =L28 -> 38581 | L29: 38594 | M29: =L29-K29 -> 13 | N29: =O28 -> 32025 | O29: 32025 | P29: =O29-N29 -> 0 | Q29: =R28 -> 37327 | R29: 37327 | S29: =R29-Q29 -> 0 | T29: =U28 -> 35653 | U29: 35664 | V29: =U29-T29 -> 11 | W29: =X28 -> 24003 | X29: 24017 | Y29: =X29-W29 -> 14 | Z29: =Y29+V29+S29+P29+M29 -> 38 | AA29: 412 | AB29: 175 | AC29: =Gen!T34 -> 2112.66
A30: =Gen!B35 -> 44555 | B30: =Gen!C35 -> 0.58 | C30: 24800.7 | D30: 12326.44 | G30: 35.2 | I30: 33575.6 | J30: 22320.8 | K30: =L29 -> 38594 | L30: 38610 | M30: =L30-K30 -> 16 | N30: =O29 -> 32025 | O30: 32025 | P30: =O30-N30 -> 0 | Q30: =R29 -> 37327 | R30: 37340 | S30: =R30-Q30 -> 13 | T30: =U29 -> 35664 | U30: 35676 | V30: =U30-T30 -> 12 | W30: =X29 -> 24017 | X30: 24017 | Y30: =X30-W30 -> 0 | Z30: =Y30+V30+S30+P30+M30 -> 41 | AA30: 420 | AB30: 160 | AC30: =Gen!T35 -> 2005.49
A31: =Gen!B36 -> 44556 | B31: =Gen!C36 -> 0.43 | C31: 24800.7 | D31: 10285.75 | G31: 280.98 | I31: 33584.7 | J31: 22326.6 | K31: =L30 -> 38610 | L31: 38610 | M31: =L31-K31 -> 0 | N31: =O30 -> 32025 | O31: 32025 | P31: =O31-N31 -> 0 | Q31: =R30 -> 37340 | R31: 37357 | S31: =R31-Q31 -> 17 | T31: =U30 -> 35676 | U31: 35685 | V31: =U31-T31 -> 9 | W31: =X30 -> 24017 | X31: 24033 | Y31: =X31-W31 -> 16 | Z31: =Y31+V31+S31+P31+M31 -> 42 | AA31: 460 | AB31: 170 | AC31: =Gen!T36 -> 2169.16
A32: =Gen!B37 -> 44557 | B32: =Gen!C37 -> 0.39 | C32: 24800.7 | D32: 7835.61 | G32: 49.66 | I32: 33593.7 | J32: 22332.3 | K32: =L31 -> 38610 | L32: 38625 | M32: =L32-K32 -> 15 | N32: =O31 -> 32025 | O32: 32025 | P32: =O32-N32 -> 0 | Q32: =R31 -> 37357 | R32: 37372 | S32: =R32-Q32 -> 15 | T32: =U31 -> 35685 | U32: 35695 | V32: =U32-T32 -> 10 | W32: =X31 -> 24033 | X32: 24033 | Y32: =X32-W32 -> 0 | Z32: =Y32+V32+S32+P32+M32 -> 40 | AA32: 450 | AB32: 165 | AC32: =Gen!T37 -> 2028.79
A33: =Gen!B38 -> 44558 | B33: =Gen!C38 -> 0.43 | C33: 24800.7 | D33: 5757.16 | G33: 186.49 | I33: 33602.2 | J33: 22337.9 | K33: =L32 -> 38625 | L33: 38625 | M33: =L33-K33 -> 0 | N33: =O32 -> 32025 | O33: 32025 | P33: =O33-N33 -> 0 | Q33: =R32 -> 37372 | R33: 37386 | S33: =R33-Q33 -> 14 | T33: =U32 -> 35695 | U33: 35704 | V33: =U33-T33 -> 9 | W33: =X32 -> 24033 | X33: 24049 | Y33: =X33-W33 -> 16 | Z33: =Y33+V33+S33+P33+M33 -> 39 | AA33: 460 | AB33: 170 | AC33: =Gen!T38 -> 2053.59
A34: =Gen!B39 -> 44559 | B34: =Gen!C39 -> 0.53 | C34: 24800.7 | D34: 3517.08 | G34: 236.12 | I34: 33610.1 | J34: 22343.7 | K34: =L33 -> 38625 | L34: 38642 | M34: =L34-K34 -> 17 | N34: =O33 -> 32025 | O34: 32025 | P34: =O34-N34 -> 0 | Q34: =R34 -> 37386 | R34: 37386 | S34: =R34-Q34 -> 0 | T34: =U33 -> 35704 | U34: 35713 | V34: =U34-T34 -> 9 | W34: =X33 -> 24049 | X34: 24063 | Y34: =X34-W34 -> 14 | Z34: =Y34+V34+S34+P34+M34 -> 40 | AA34: 465 | AB34: 165 | AC34: =Gen!T39 -> 2039.95
A35: =Gen!B40 -> 44560 | B35: =Gen!C40 -> 0.61 | C35: 24800.7 | D35: 19241.01 | G35: 34.26 | I35: 33618.2 | J35: 22349.3 | K35: =L34 -> 38642 | L35: 38658 | M35: =L35-K35 -> 16 | N35: =O34 -> 32025 | O35: 32025 | P35: =O35-N35 -> 0 | Q35: =R35 -> 37402 | R35: 37402 | S35: =R35-Q35 -> 0 | T35: =U34 -> 35713 | U35: 35722 | V35: =U35-T35 -> 9 | W35: =X34 -> 24063 | X35: 24063 | Y35: =X35-W35 -> 0 | Z35: =Y35+V35+S35+P35+M35 -> 25 | AA35: 471 | AB35: 180 | AC35: =Gen!T40 -> 2039.77
A36: =Gen!B41 -> 44561 | B36: =Gen!C41 -> 0.61 | C36: 24800.7 | D36: 17166.98 | F36: =Gen!E40 -> 0 | G36: 882.87 | I36: 33626.4 | J36: 22355.1 | K36: =L35 -> 38658 | L36: 38661 | M36: =L36-K36 -> 3 | N36: =O35 -> 32025 | O36: 32025 | P36: =O36-N36 -> 0 | Q36: =R35 -> 37402 | R36: 37416 | S36: =R36-Q36 -> 14 | T36: =U35 -> 35722 | U36: 35733 | V36: =U36-T36 -> 11 | W36: =X35 -> 24063 | X36: 24077 | Y36: =X36-W36 -> 14 | Z36: =Y36+V36+S36+P36+M36 -> 42 | AA36: 471 | AB36: 185
A37: =Gen!B42 -> 0 | B37: =Gen!C42 -> 0 | C37: 24800.7 | D37: 14399.93 | I37: 33634.2 | J37: 22360.8 | K37: =L36 -> 38661 | M37: =L37-K37 -> -38661 | N37: =O36 -> 32025 | P37: =O37-N37 -> -32025 | Q37: =R36 -> 37416 | T37: =U36 -> 35733 | V37: =U37-T37 -> -35733 | W37: =X36 -> 24077 | Y37: =X37-W37 -> -24077 | Z37: =Y37+V37+S37+P37+M37 -> -130496

Sheet Water_Graph 
A1: Date | B1: Usage | C1: Occ %
A2: =Gen!B11 -> 44531 | B2: #REF! | C2: =Gen!C11 -> 0.0519
A3: =Gen!B12 -> 44532 | B3: #REF! | C3: =Gen!C12 -> 0.05
A4: =Gen!B13 -> 44533 | B4: #REF! | C4: =Gen!C13 -> 0.05
A5: =Gen!B14 -> 44534 | B5: #REF! | C5: =Gen!C14 -> 0.08
A6: =Gen!B15 -> 44535 | B6: #REF! | C6: =Gen!C15 -> 0.05
A7: =Gen!B16 -> 44536 | B7: #REF! | C7: =Gen!C16 -> 0.0779
A8: =Gen!B17 -> 44537 | B8: #REF! | C8: =Gen!C17 -> 0.0779
A9: =Gen!B18 -> 44538 | B9: #REF! | C9: =Gen!C18 -> 0.12
A10: =Gen!B19 -> 44539 | B10: #REF! | C10: =Gen!C19 -> 0.09
A11: =Gen!B20 -> 44540 | B11: #REF! | C11: =Gen!C20 -> 0.12
A12: =Gen!B21 -> 44541 | B12: #REF! | C12: =Gen!C21 -> 0.12
A13: =Gen!B22 -> 44542 | B13: #REF! | C13: =Gen!C22 -> 0.12
... A29: =Gen!B38 -> 44558 | B29: #REF! | C29: =Gen!C38 -> 0.43
A30: =Gen!B39 -> 44559 | B30: -212333 | C30: =Gen!C39 -> 0.53
A31: =Gen!B40 -> 44560 | B31: #REF! | C31: =Gen!C40 -> 0.61
A32: =Gen!B41 -> 44561 | B32: #REF! | C32: =Gen!C41 -> 0.61

Sheet Sheet1
A2: Generator and Diseal Summry Report | Q2: 2209.85 | R2: Diesel Cost | S2: Rate$ | T2: 1584
M3: % of Gas balance in Tank | P3: % of Dieasel balance in Tank | Q3: HLP Cost (TSH) | V3: Total Cost (TSH) | W3: Consumption Guest Occ% | AA3: Budget Cost Per Room occ
A4: Date | B4: Gen Set Hours Working | C4: Occ% | D4: Total OCC Room | E4: Guest Room Occ | F4: Total Kwh Generated | G4: Diseal consumed by Gen (Ltrs) | H4: Diseal consumed by Veichel (Ltrs) | I4: Total diseal consumed (Ltrs) | J4: Balance stock of Diseal (Ltrs) | K4: Water consumed | L4: Gas consumed (KG) | M4: 3 | N4: 2 | O4: 1 | Q4: Electricity | R4: Cost per Room Total OOC Usd | S4: Cost per Room Guest OOC Usd | T4: Water | U4: Gas
A5: =Gen!B11 -> 44531 | B5: 0 | C5: =Gen!C11 -> 0.0519 | D5: =E5 -> 2 | E5: 2 | F5: =Gen!V11 -> 0.42833546 | G5: =Gen!U11 -> 3130 | H5: #REF! | I5: =SUM(G5:H5) -> #REF! | J5: 47806.65 | K5: ='Water-Meter'!E6 -> 79 | L5: ='Lpg (2)'!G10 -> 101.244 | M5: =#REF! -> #REF! | N5: =#REF! -> #REF! | O5: =#REF! -> #REF! | P5: =J5/52000 -> 0.91935865 | Q5: =I5*Q2 -> #REF! | R5: =SUM(Q5/D5)/X5 -> #REF! | S5: =SUM(Q5/E5)/X5 -> #REF! | T5: =(K5*102)/X5 -> 5.0871212 | U5: =SUM(L5*1963)/X5 -> 125.46842 | V5: =SUM(Q5+T5+U5) -> #REF! | W5: =SUM(V5/E5)/#REF! -> #REF! | X5: =SUM(T2) -> 1584 | Y5: 106 | Z5: =SUM(Y5-S5) -> #REF! | AA5: 106
A6: =Gen!B12 -> 44532 | B6: 0 | C6: =Gen!C12 -> 0.05 | D6: =E6 -> 1 | E6: 1 | F6: =Gen!V12 -> 0.40863446 | G6: =Gen!U12 -> 3105 | H6: #REF! | I6: =SUM(G6:H6) -> #REF! | J6: 45423.89 | K6: ='Water-Meter'!E7 -> 67 | L6: ='Lpg (2)'!G11 -> 70.312 | M6: =#REF! -> #REF! | N6: =#REF! -> #REF! | O6: =#REF! -> #REF! | P6: =J6/52000 -> 0.87353635 | Q6: =I6*Q2 -> #REF! | R6: =SUM(Q6/D6)/X6 -> #REF! | S6: =SUM(Q6/E6)/X6 -> #REF! | T6: =(K6*102)/X6 -> 4.3143939 | U6: =SUM(L6*1963)/X6 -> 87.135389 | V6: =SUM(Q6+T6+U6) -> #REF! | W6: =SUM(V6/E6)/#REF! -> #REF! | X6: =SUM(X5) -> 1584 | Y6: 106 | Z6: =SUM(Y6-S6) -> #REF!
A7: =Gen!B13 -> 44533 | B7: 0 | C7: =Gen!C13 -> 0.05 | D7: =E7 -> 3 | E7: 3 | F7: =Gen!V13 -> 0.40452577 | G7: =Gen!U13 -> 2910 | H7: #REF! | I7: =SUM(G7:H7) -> #REF! | J7: 42919.59 | K7: ='Water-Meter'!E8 -> 83 | L7: ='Lpg (2)'!G12 -> 59.576 | M7: =#REF! -> #REF! | N7: =#REF! -> #REF! | O7: =#REF! -> #REF! | P7: =J7/52000 -> 0.82537673 | Q7: =I7*Q2 -> #REF! | R7: =SUM(Q7/D7)/X7 -> #REF! | S7: =SUM(Q7/E7)/X7 -> #REF! | T7: =(K7*102)/X7 -> 5.344697 | U7: =SUM(L7*1963)/X7 -> 73.830611 | V7: =SUM(Q7+T7+U7) -> #REF! | W7: =SUM(V7/E7)/#REF! -> #REF! | X7: =SUM(X6) -> 1584 | Y7: 106 | Z7: =SUM(Y7-S7) -> #REF!
A8: =Gen!B14 -> 44534 | B8: 0 | C8: =Gen!C14 -> 0.08 | D8: =E8 -> 3 | E8: 3 | F8: =Gen!V14 -> 0.3931955 | G8: =Gen!U14 -> 3289 | H8: #REF! | I8: =SUM(G8:H8) -> #REF! | J8: 40258.94 | K8: ='Water-Meter'!E9 -> 67 | L8: ='Lpg (2)'!G13 -> 61.512 | M8: =#REF! -> #REF! | N8: =#REF! -> #REF! | O8: =#REF! -> #REF! | P8: =J8/52000 -> 0.77421038 | Q8: =I8*Q2 -> #REF! | R8: =SUM(Q8/D8)/X8 -> #REF! | S8: =SUM(Q8/E8)/X8 -> #REF! | T8: =(K8*102)/X8 -> 4.3143939 | U8: =SUM(L8*1963)/X8 -> 76.229833 | V8: =SUM(Q8+T8+U8) -> #REF! | W8: =SUM(V8/E8)/#REF! -> #REF! | X8: =SUM(X7) -> 1584 | Y8: 106 | Z8: =SUM(Y8-S8) -> #REF!
A9: =Gen!B15 -> 44535 | B9: 0 | C9: =Gen!C15 -> 0.05 | D9: =E9 -> 1 | E9: 1 | F9: =Gen!V15 -> 0.3963541 | G9: =Gen!U15 -> 3146 | H9: 0 | I9: =SUM(G9:H9) -> 3146 | J9: 37525.21 | K9: ='Water-Meter'!E10 -> 62 | L9: ='Lpg (2)'!G14 -> 87.34 | M9: =#REF! -> #REF! | N9: =#REF! -> #REF! | O9: =#REF! -> #REF! | P9: =J9/52000 -> 0.72163865 | Q9: =I9*Q2 -> 6952188.1 | R9: =SUM(Q9/D9)/X9 -> 4389.0076 | S9: =SUM(Q9/E9)/X9 -> 4389.0076 | T9: =(K9*102)/X9 -> 3.9924242 | U9: =SUM(L9*1963)/X9 -> 108.23764 | V9: =SUM(Q9+T9+U9) -> 6952300.3 | W9: =SUM(V9/E9)/#REF! -> #REF! | X9: =SUM(X8) -> 1584 | Y9: 106 | Z9: =SUM(Y9-S9) -> -4283.0076
A10: =Gen!B16 -> 44536 | B10: 0 | C10: =Gen!C16 -> 0.0779 | D10: =E10 -> 5 | E10: 5 | F10: =Gen!V16 -> 0.39449271 | G10: =Gen!U16 -> 3361 | H10: #REF! | I10: =SUM(G10:H10) -> #REF! | J10: 35107.69 | K10: ='Water-Meter'!E11 -> 57 | L10: ='Lpg (2)'!G15 -> 107.492 | M10: =#REF! -> #REF! | N10: =#REF! -> #REF! | O10: =#REF! -> #REF! | P10: =J10/52000 -> 0.67514788 | Q10: =I10*Q2 -> #REF! | R10: =SUM(Q10/D10)/X10 -> #REF! | S10: =SUM(Q10/E10)/X10 -> #REF! | T10: =(K10*102)/X10 -> 3.6704545 | U10: =SUM(L10*1963)/X10 -> 133.21136 | V10: =SUM(Q10+T10+U10) -> #REF! | W10: =SUM(V10/E10)/#REF! -> #REF! | X10: =SUM(X9) -> 1584 | Y10: 106 | Z10: =SUM(Y10-S10) -> #REF!
A11: =Gen!B17 -> 44537 | B11: 0 | C11: =Gen!C17 -> 0.0779 | D11: =E11 -> 2 | E11: 2 | F11: =Gen!V17 -> 0.40501183 | G11: =Gen!U17 -> 3380 | H11: 80.56 | I11: =SUM(G11:H11) -> 3460.56 | J11: 47513.14 | K11: ='Water-Meter'!E12 -> 73 | L11: ='Lpg (2)'!G16 -> 90.684 | M11: =#REF! -> #REF! | N11: =#REF! -> #REF! | O11: =#REF! -> #REF! | P11: =J11/52000 -> 0.91371423 | Q11: =I11*Q2 -> 7647318.5 | R11: =SUM(Q11/D11)/X11 -> 2413.9263 | S11: =SUM(Q11/E11)/X11 -> 2413.9263 | T11: =(K11*102)/X11 -> 4.7007576 | U11: =SUM(L11*1963)/X11 -> 112.38175 | V11: =SUM(Q11+T11+U11) -> 7647435.6 | W11: =SUM(V11/E11)/#REF! -> #REF! | X11: =SUM(X10) -> 1584 | Y11: 106 | Z11: =SUM(Y11-S11) -> -2307.9263
A12: =Gen!B18 -> 44538 | B12: 0 | C12: =Gen!C18 -> 0.12 | D12: =E12 -> 4 | E12: 4 | F12: =Gen!V18 -> 0.4171491 | G12: =Gen!U18 -> 3662 | H12: #REF! | I12: =SUM(G12:H12) -> #REF! | J12: 45161.89 | K12: ='Water-Meter'!E13 -> 80 | L12: ='Lpg (2)'!G17 -> 99.88 | M12: =#REF! -> #REF! | N12: =#REF! -> #REF! | O12: =#REF! -> #REF! | P12: =J12/52000 -> 0.86849788 | Q12: =I12*Q2 -> #REF! | R12: =SUM(Q12/D12)/X12 -> #REF! | S12: =SUM(Q12/E12)/X12 -> #REF! | T12: =(K12*102)/X12 -> 5.1515152 | U12: =SUM(L12*1963)/X12 -> 123.77806 | V12: =SUM(Q12+T12+U12) -> #REF! | W12: =SUM(V12/E12)/#REF! -> #REF! | X12: =SUM(X11) -> 1584 | Y12: 106 | Z12: =SUM(Y12-S12) -> #REF!
A13: =Gen!B19 -> 44539 | B13: 0 | C13: =Gen!C19 -> 0.09 | D13: =E13 -> 3 | E13: 3 | F13: =Gen!V19 -> 0.4035481 | G13: =Gen!U19 -> 3399 | H13: #REF! | I13: =SUM(G13:H13) -> #REF! | J13: 42825.48 | K13: ='Water-Meter'!E14 -> 65 | L13: ='Lpg (2)'!G18 -> 108.988 | M13: =#REF! -> #REF! | N13: =#REF! -> #REF! | O13: =#REF! -> #REF! | P13: =J13/52000 -> 0.82356692 | Q13: =I13*Q2 -> #REF! | R13: =SUM(Q13/D13)/X13 -> #REF! | S13: =SUM(Q13/E13)/X13 -> #REF! | T13: =(K13*102)/X13 -> 4.1856061 | U13: =SUM(L13*1963)/X13 -> 135.06531 | V13: =SUM(Q13+T13+U13) -> #REF! | W13: =SUM(V13/E13)/#REF! -> #REF! | X13: =SUM(X12) -> 1584 | Y13: 106 | Z13: =SUM(Y13-S13) -> #REF!
A14: =Gen!B20 -> 44540 | B14: 0 | C14: =Gen!C20 -> 0.12 | D14: =E14 -> 4 | E14: 4 | F14: =Gen!V20 -> 0.3916657 | G14: =Gen!U20 -> 3440 | H14: #REF! | I14: =SUM(G14:H14) -> #REF! | J14: 40110.38 | K14: ='Water-Meter'!E15 -> 71 | L14: ='Lpg (2)'!G19 -> 110 | M14: =#REF! -> #REF! | N14: =#REF! -> #REF! | O14: =#REF! -> #REF! | P14: =J14/52000 -> 0.77135346 | Q14: =I14*Q2 -> #REF! | R14: =SUM(Q14/D14)/X14 -> #REF! | S14: =SUM(Q14/E14)/X14 -> #REF! | T14: =(K14*102)/X14 -> 4.5719697 | U14: =SUM(L14*1963)/X14 -> 136.31944 | V14: =SUM(Q14+T14+U14) -> #REF! | W14: =SUM(V14/E14)/#REF! -> #REF! | X14: =SUM(X13) -> 1584 | Y14: 106 | Z14: =SUM(Y14-S14) -> #REF!
A15: =Gen!B21 -> 44541 | B15: 0 | C15: =Gen!C21 -> 0.12 | D15: =E15 -> 3 | E15: 3 | F15: =Gen!V21 -> 0.40930465 | G15: =Gen!U21 -> 3696 | H15: #REF! | I15: =SUM(G15:H15) -> #REF! | J15: 37540.57 | K15: ='Water-Meter'!E16 -> 72 | L15: ='Lpg (2)'!G20 -> 105.38 | M15: =#REF! -> #REF! | N15: =#REF! -> #REF! | O15: =#REF! -> #REF! | P15: =J15/52000 -> 0.72193404 | Q15: =I15*Q2 -> #REF! | R15: =SUM(Q15/D15)/X15 -> #REF! | S15: =SUM(Q15/E15)/X15 -> #REF! | T15: =(K15*102)/X15 -> 4.6363636 | U15: =SUM(L15*1963)/X15 -> 130.59403 | V15: =SUM(Q15+T15+U15) -> #REF! | W15: =SUM(V15/E15)/#REF! -> #REF! | X15: =SUM(X14) -> 1584 | Y15: 106 | Z15: =SUM(Y15-S15) -> #REF!
A16: =Gen!B22 -> 44542 | B16: 0 | C16: =Gen!C22 -> 0.12 | D16: =E16 -> 2 | E16: 2 | F16: =Gen!V22 -> 0.40736149 | G16: =Gen!U22 -> 3646 | H16: #REF! | I16: =SUM(G16:H16) -> #REF! | J16: 34967.29 | K16: ='Water-Meter'!E17 -> 65 | L16: ='Lpg (2)'!G21 -> 106.656 | M16: =#REF! -> #REF! | N16: =#REF! -> #REF! | O16: =#REF! -> #REF! | P16: =J16/52000 -> 0.67244788 | Q16: =I16*Q2 -> #REF! | R16: =SUM(Q16/D16)/X16 -> #REF! | S16: =SUM(Q16/E16)/X16 -> #REF! | T16: =(K16*102)/X16 -> 4.1856061 | U16: =SUM(L16*1963)/X16 -> 132.17533 | V16: =SUM(Q16+T16+U16) -> #REF! | W16: =SUM(V16/E16)/#REF! -> #REF! | X16: =SUM(X15) -> 1584 | Y16: 106 | Z16: =SUM(Y16-S16) -> #REF!
A17: =Gen!B23 -> 44543 | B17: 0 | C17: =Gen!C23 -> 0.16 | D17: =E17 -> 8 | E17: 8 | F17: =Gen!V23 -> 0.39819259 | G17: =Gen!U23 -> 3967 | H17: #REF! | I17: =SUM(G17:H17) -> #REF! | J17: 32228.76 | K17: ='Water-Meter'!E18 -> 68 | L17: ='Lpg (2)'!G22 -> 108.02 | M17: =#REF! -> #REF! | N17: =#REF! -> #REF! | O17: =#REF! -> #REF! | P17: =J17/52000 -> 0.61978385 | Q17: =I17*Q2 -> #REF! | R17: =SUM(Q17/D17)/X17 -> #REF! | S17: =SUM(Q17/E17)/X17 -> #REF! | T17: =(K17*102)/X17 -> 4.3787879 | U17: =SUM(L17*1963)/X17 -> 133.86569 | V17: =SUM(Q17+T17+U17) -> #REF! | W17: =SUM(V17/E17)/#REF! -> #REF! | X17: =SUM(X16) -> 1584 | Y17: 106 | Z17: =SUM(Y17-S17) -> #REF!
A18: =Gen!B24 -> 44544 | B18: 0 | C18: =Gen!C24 -> 0.17 | D18: =E18 -> 3 | E18: 3 | F18: =Gen!V24 -> 0.39349751 | G18: =Gen!U24 -> 3411 | H18: 597.9 | I18: =SUM(G18:H18) -> 4008.9 | J18: 29915.45 | K18: ='Water-Meter'!E19 -> 78 | L18: ='Lpg (2)'!G23 -> 103.664 | M18: =#REF! -> #REF! | N18: =#REF! -> #REF! | O18: =#REF! -> #REF! | P18: =J18/52000 -> 0.57529712 | Q18: =I18*Q2 -> 8859067.7 | R18: =SUM(Q18/D18)/X18 -> 1864.2819 | S18: =SUM(Q18/E18)/X18 -> 1864.2819 | T18: =(K18*102)/X18 -> 5.0227273 | U18: =SUM(L18*1963)/X18 -> 128.46744 | V18: =SUM(Q18+T18+U18) -> 8859201.2 | W18: =SUM(V18/E18)/#REF! -> #REF! | X18: =SUM(X17) -> 1584 | Y18: 106 | Z18: =SUM(Y18-S18) -> -1758.2819
A19: =Gen!B25 -> 44545 | B19: 0 | C19: =Gen!C25 -> 0.18 | D19: =E19 -> 4 | E19: 4 | F19: =Gen!V25 -> 0.41307633 | G19: =Gen!U25 -> 3878 | H19: 227.73 | I19: =SUM(G19:H19) -> 4105.73 | J19: 42248.24 | K19: ='Water-Meter'!E20 -> 72 | L19: ='Lpg (2)'!G24 -> 98.428 | M19: =#REF! -> #REF! | N19: =#REF! -> #REF! | O19: =#REF! -> #REF! | P19: =J19/52000 -> 0.81246615 | Q19: =I19*Q2 -> 9073047.4 | R19: =SUM(Q19/D19)/X19 -> 1431.9835 | S19: =SUM(Q19/E19)/X19 -> 1431.9835 | T19: =(K19*102)/X19 -> 4.6363636 | U19: =SUM(L19*1963)/X19 -> 121.97864 | V19: =SUM(Q19+T19+U19) -> 9073174.1 | W19: =SUM(V19/E19)/#REF! -> #REF! | X19: =SUM(X18) -> 1584 | Y19: 106 | Z19: =SUM(Y19-S19) -> -1325.9835
A20: =Gen!B26 -> 44546 | B20: 0 | C20: =Gen!C26 -> 0.16 | D20: =E20 -> 7 | E20: 7 | F20: =Gen!V26 -> 0.39082693 | G20: =Gen!U26 -> 3906 | H20: 88.29 | I20: =SUM(G20:H20) -> 3994.29 | J20: 39497.37 | K20: ='Water-Meter'!E21 -> 73 | L20: ='Lpg (2)'!G25 -> 105.028 | M20: =#REF! -> #REF! | N20: =#REF! -> #REF! | O20: =#REF! -> #REF! | P20: =J20/52000 -> 0.75956481 | Q20: =I20*Q2 -> 8826781.8 | R20: =SUM(Q20/D20)/X20 -> 796.06618 | S20: =SUM(Q20/E20)/X20 -> 796.06618 | T20: =(K20*102)/X20 -> 4.7007576 | U20: =SUM(L20*1963)/X20 -> 130.15781 | V20: =SUM(Q20+T20+U20) -> 8826916.6 | W20: =SUM(V20/E20)/#REF! -> #REF! | X20: =SUM(X19) -> 1584 | Y20: 106 | Z20: =SUM(Y20-S20) -> -690.06618
A21: =Gen!B27 -> 44547 | B21: 0 | C21: =Gen!C27 -> 0.16 | D21: =E21 -> 3 | E21: 3 | F21: =Gen!V27 -> 0.40365834 | G21: =Gen!U27 -> 3764 | H21: 783.92 | I21: =SUM(G21:H21) -> 4547.92 | J21: 36688.35 | K21: ='Water-Meter'!E22 -> 73 | L21: ='Lpg (2)'!G26 -> 101.728 | M21: =#REF! -> #REF! | N21: =#REF! -> #REF! | O21: =#REF! -> #REF! | P21: =J21/52000 -> 0.70554519 | Q21: =I21*Q2 -> 10050221 | R21: =SUM(Q21/D21)/X21 -> 2114.9455 | S21: =SUM(Q21/E21)/X21 -> 2114.9455 | T21: =(K21*102)/X21 -> 4.7007576 | U21: =SUM(L21*1963)/X21 -> 126.06822 | V21: =SUM(Q21+T21+U21) -> 10050352 | W21: =SUM(V21/E21)/#REF! -> #REF! | X21: =SUM(X20) -> 1584 | Y21: 106 | Z21: =SUM(Y21-S21) -> -2008.9455
A22: =Gen!B28 -> 44548 | B22: 0 | C22: =Gen!C28 -> 0.13 | D22: =E22 -> 1 | E22: 1 | F22: =Gen!V28 -> 0.39454405 | G22: =Gen!U28 -> 3882 | H22: #REF! | I22: =SUM(G22:H22) -> #REF! | J22: 33769.34 | K22: ='Water-Meter'!E23 -> 85 | L22: ='Lpg (2)'!G27 -> 107.272 | M22: =#REF! -> #REF! | N22: =#REF! -> #REF! | O22: =#REF! -> #REF! | P22: =J22/52000 -> 0.64941038 | Q22: =I22*Q2 -> #REF! | R22: =SUM(Q22/D22)/X22 -> #REF! | S22: =SUM(Q22/E22)/X22 -> #REF! | T22: =(K22*102)/X22 -> 5.4734848 | U22: =SUM(L22*1963)/X22 -> 132.93872 | V22: =SUM(Q22+T22+U22) -> #REF! | W22: =SUM(V22/E22)/#REF! -> #REF! | X22: =SUM(X21) -> 1584 | Y22: 106 | Z22: =SUM(Y22-S22) -> #REF!
A23: =Gen!B29 -> 44549 | B23: 0 | C23: =Gen!C29 -> 0.12 | D23: =E23 -> 0 | E23: 0 | F23: =Gen!V29 -> 0.42474232 | G23: =Gen!U29 -> 3745 | H23: #REF! | I23: =SUM(G23:H23) -> #REF! | J23: 31336.77 | K23: ='Water-Meter'!E24 -> 80 | L23: ='Lpg (2)'!G28 -> 94.468 | M23: =#REF! -> #REF! | N23: =#REF! -> #REF! | O23: =#REF! -> #REF! | P23: =J23/52000 -> 0.60263019 | Q23: =I23*Q2 -> #REF! | R23: =SUM(Q23/D23)/X23 -> #REF! | S23: =SUM(Q23/E23)/X23 -> #REF! | T23: =(K23*102)/X23 -> 5.1515152 | U23: =SUM(L23*1963)/X23 -> 117.07114 | V23: =SUM(Q23+T23+U23) -> #REF! | W23: =SUM(V23/E23)/#REF! -> #REF! | X23: =SUM(X22) -> 1584 | Y23: 106 | Z23: =SUM(Y23-S23) -> #REF!
A24: =Gen!B30 -> 44550 | B24: 0 | C24: =Gen!C30 -> 0.06 | D24: =E24 -> 3 | E24: 3 | F24: =Gen!V30 -> 0.39317777 | G24: =Gen!U30 -> 3257 | H24: #REF! | I24: =SUM(G24:H24) -> #REF! | J24: 29403.3 | K24: ='Water-Meter'!E25 -> 76 | L24: ='Lpg (2)'!G29 -> 87.868 | M24: =#REF! -> #REF! | N24: =#REF! -> #REF! | O24: =#REF! -> #REF! | P24: =J24/52000 -> 0.56544808 | Q24: =I24*Q2 -> #REF! | R24: =SUM(Q24/D24)/X24 -> #REF! | S24: =SUM(Q24/E24)/X24 -> #REF! | T24: =(K24*102)/X24 -> 4.8939394 | U24: =SUM(L24*1963)/X24 -> 108.89197 | V24: =SUM(Q24+T24+U24) -> #REF! | W24: =SUM(V24/E24)/#REF! -> #REF! | X24: =SUM(X23) -> 1584 | Y24: 106 | Z24: =SUM(Y24-S24) -> #REF!
A25: =Gen!B31 -> 44551 | B25: 0 | C25: =Gen!C31 -> 0.1 | D25: =E25 -> 5 | E25: 5 | F25: =Gen!V31 -> 0.4117842 | G25: =Gen!U31 -> 4495 | H25: =Gen!V31 -> 0.4117842 | I25: =Gen!W31 -> 0 | J25: 41422.37 | K25: ='Water-Meter'!E26 -> 69 | L25: ='Lpg (2)'!G30 -> 113.432 | M25: =#REF! -> #REF! | N25: =#REF! -> #REF! | O25: =#REF! -> #REF! | P25: =J25/52000 -> 0.79658404 | Q25: =I25*Q2 -> 0 | R25: =SUM(Q25/D25)/X25 -> 0 | S25: =SUM(Q25/E25)/X25 -> 0 | T25: =(K25*102)/X25 -> 4.4431818 | U25: =SUM(L25*1963)/X25 -> 140.57261 | V25: =SUM(Q25+T25+U25) -> 145.01579 | W25: =SUM(V25/E25)/T1 -> #DIV/0! | X25: =SUM(X24) -> 1584 | Y25: 106 | Z25: =SUM(Y25-S25) -> 106
A26: =Gen!B32 -> 44552 | B26: 0 | C26: =Gen!C32 -> 0.17 | D26: =E26 -> 6 | E26: 6 | F26: =Gen!V32 -> 0.42388138 | G26: =Gen!U32 -> 3996 | H26: 18.63 | I26: =SUM(G26:H26) -> 4014.63 | J26: 38988.16 | K26: ='Water-Meter'!E27 -> 71 | L26: ='Lpg (2)'!G31 -> 114.444 | M26: =#REF! -> #REF! | N26: =#REF! -> #REF! | O26: =#REF! -> #REF! | P26: =J26/52000 -> 0.74977231 | Q26: =I26*Q2 -> 8871730.1 | R26: =SUM(Q26/D26)/X26 -> 933.47329 | S26: =SUM(Q26/E26)/X26 -> 933.47329 | T26: =(K26*102)/X26 -> 4.5719697 | U26: =SUM(L26*1963)/X26 -> 141.82675 | V26: =SUM(Q26+T26+U26) -> 8871876.5 | W26: =SUM(V26/E26)/T2 -> 933.48869 | X26: =SUM(X25) -> 1584 | Y26: 106 | Z26: =SUM(Y26-S26) -> -827.47329
A27: =Gen!B33 -> 44553 | B27: 0 | C27: =Gen!C33 -> 0.17 | D27: =E27 -> 4 | E27: 4 | F27: =Gen!V33 -> 0.40096613 | G27: =Gen!U33 -> 4192 | H27: 311.34 | I27: =SUM(G27:H27) -> 4503.34 | J27: 36682.67 | K27: ='Water-Meter'!E28 -> 85 | L27: ='Lpg (2)'!G32 -> 114.092 | M27: =#REF! -> #REF! | N27: =#REF! -> #REF! | O27: =#REF! -> #REF! | P27: =J27/52000 -> 0.70543596 | Q27: =I27*Q2 -> 9951705.9 | R27: =SUM(Q27/D27)/X27 -> 1570.6607 | S27: =SUM(Q27/E27)/X27 -> 1570.6607 | T27: =(K27*102)/X27 -> 5.4734848 | U27: =SUM(L27*1963)/X27 -> 141.39053 | V27: =SUM(Q27+T27+U27) -> 9951852.8 | W27: =SUM(V27/E27)/T2 -> 1570.6838 | X27: =SUM(X26) -> 1584 | Y27: 106 | Z27: =SUM(Y27-S27) -> -1464.6607
A28: =Gen!B34 -> 44554 | B28: 0 | C28: =Gen!C34 -> 0.47 | D28: =E28 -> 25 | E28: 25 | F28: =Gen!V34 -> 0.42705882 | G28: =Gen!U34 -> 4947 | H28: 380.7 | I28: =SUM(G28:H28) -> 5327.7 | J28: 44223.03 | K28: ='Water-Meter'!E29 -> 75 | L28: ='Lpg (2)'!G33 -> 117.92 | M28: =#REF! -> #REF! | N28: =#REF! -> #REF! | O28: =#REF! -> #REF! | P28: =J28/52000 -> 0.85044288 | Q28: =I28*Q2 -> 11773418 | R28: =SUM(Q28/D28)/X28 -> 297.30853 | S28: =SUM(Q28/E28)/X28 -> 297.30853 | T28: =(K28*102)/X28 -> 4.8295455 | U28: =SUM(L28*1963)/X28 -> 146.13444 | V28: =SUM(Q28+T28+U28) -> 11773569 | W28: =SUM(V28/E28)/T2 -> 297.31234 | X28: =SUM(X27) -> 1584 | Y28: 106 | Z28: =SUM(Y28-S28) -> -191.30853
A29: =Gen!B35 -> 44555 | B29: 0 | C29: =Gen!C35 -> 0.58 | D29: =E29 -> 19 | E29: 19 | F29: =Gen!V35 -> 0.40786862 | G29: =Gen!U35 -> 4917 | H29: 273.37 | I29: =SUM(G29:H29) -> 5190.37 | J29: 41629.06 | K29: ='Water-Meter'!E30 -> 102 | L29: ='Lpg (2)'!G34 -> 129.404 | M29: =#REF! -> #REF! | N29: =#REF! -> #REF! | O29: =#REF! -> #REF! | P29: =J29/52000 -> 0.80055885 | Q29: =I29*Q2 -> 11469939 | R29: =SUM(Q29/D29)/X29 -> 381.11175 | S29: =SUM(Q29/E29)/X29 -> 381.11175 | T29: =(K29*102)/X29 -> 6.5681818 | U29: =SUM(L29*1963)/X29 -> 160.36619 | V29: =SUM(Q29+T29+U29) -> 11470106 | W29: =SUM(V29/E29)/T2 -> 381.11729 | X29: =SUM(X28) -> 1584 | Y29: 106 | Z29: =SUM(Y29-S29) -> -275.11175
A30: =Gen!B36 -> 44556 | B30: 0 | C30: =Gen!C36 -> 0.43 | D30: =E30 -> 3 | E30: 3 | F30: =Gen!V36 -> 0.43874595 | G30: =Gen!U36 -> 4944 | H30: 396.56 | I30: =SUM(G30:H30) -> 5340.56 | J30: 39251.17 | K30: ='Water-Meter'!E31 -> 106 | L30: ='Lpg (2)'!G35 -> 115.764 | M30: =#REF! -> #REF! | N30: =#REF! -> #REF! | O30: =#REF! -> #REF! | P30: =J30/52000 -> 0.75483019 | Q30: =I30*Q2 -> 11801837 | R30: =SUM(Q30/D30)/X30 -> 2483.5515 | S30: =SUM(Q30/E30)/X30 -> 2483.5515 | T30: =(K30*102)/X30 -> 6.8257576 | U30: =SUM(L30*1963)/X30 -> 143.46258 | V30: =SUM(Q30+T30+U30) -> 11801987 | W30: =SUM(V30/E30)/T2 -> 2483.5831 | X30: =SUM(X29) -> 1584 | Y30: 106 | Z30: =SUM(Y30-S30) -> -2377.5515
A31: =Gen!B37 -> 44557 | B31: 0 | C31: =Gen!C37 -> 0.39 | D31: =E31 -> 16 | E31: 16 | F31: =Gen!V37 -> 0.405758 | G31: =Gen!U37 -> 5000 | H31: 280.63 | I31: =SUM(G31:H31) -> 5280.63 | J31: 36384.37 | K31: ='Water-Meter'!E32 -> 102 | L31: ='Lpg (2)'!G36 -> 127.336 | M31: =#REF! -> #REF! | N31: =#REF! -> #REF! | O31: =#REF! -> #REF! | P31: =J31/52000 -> 0.69969942 | Q31: =I31*Q2 -> 11669400 | R31: =SUM(Q31/D31)/X31 -> 460.44035 | S31: =SUM(Q31/E31)/X31 -> 460.44035 | T31: =(K31*102)/X31 -> 6.5681818 | U31: =SUM(L31*1963)/X31 -> 157.80339 | V31: =SUM(Q31+T31+U31) -> 11669565 | W31: =SUM(V31/E31)/T2 -> 460.44683 | X31: =SUM(X30) -> 1584 | Y31: 106 | Z31: =SUM(Y31-S31) -> -354.44035
A32: =Gen!B38 -> 44558 | B32: 0 | C32: =Gen!C38 -> 0.43 | D32: =E32 -> 15 | E32: 15 | F32: =Gen!V38 -> 0.43917665 | G32: =Gen!U38 -> 4676 | H32: 0 | I32: =SUM(G32:H32) -> 4676 | J32: 33780 | K32: ='Water-Meter'!E33 -> 109 | L32: ='Lpg (2)'!G37 -> 126.72 | M32: =#REF! -> #REF! | N32: =#REF! -> #REF! | O32: =#REF! -> #REF! | P32: =J32/52000 -> 0.64961538 | Q32: =I32*Q2 -> 10333259 | R32: =SUM(Q32/D32)/X32 -> 434.90146 | S32: =SUM(Q32/E32)/X32 -> 434.90146 | T32: =(K32*102)/X32 -> 7.0189394 | U32: =SUM(L32*1963)/X32 -> 157.04 | V32: =SUM(Q32+T32+U32) -> 10333423 | W32: =SUM(V32/E32)/T2 -> 434.90836 | X32: =SUM(X31) -> 1584 | Y32: 106 | Z32: =SUM(Y32-S32) -> -328.90146
A33: =Gen!B39 -> 44559 | B33: 0 | C33: =Gen!C39 -> 0.53 | D33: =E33 -> 11 | E33: 11 | F33: =Gen!V39 -> 0.41699714 | G33: =Gen!U39 -> 4892 | H33: 0 | I33: =SUM(G33:H33) -> 4892 | J33: 33780 | K33: ='Water-Meter'!E34 -> 111 | L33: ='Lpg (2)'!G38 -> 135.388 | M33: =#REF! -> #REF! | N33: =#REF! -> #REF! | O33: =#REF! -> #REF! | P33: =J33/52000 -> 0.64961538 | Q33: =I33*Q2 -> 10810586 | R33: =SUM(Q33/D33)/X33 -> 620.44228 | S33: =SUM(Q33/E33)/X33 -> 620.44228 | T33: =(K33*102)/X33 -> 7.1477273 | U33: =SUM(L33*1963)/X33 -> 167.78197 | V33: =SUM(Q33+T33+U33) -> 10810761 | W33: =SUM(V33/E33)/T2 -> 620.45231 | X33: =SUM(X32) -> 1584 | Y33: 106 | Z33: =SUM(Y33-S33) -> -514.44228
A34: =Gen!B40 -> 44560 | B34: 0 | C34: =Gen!C40 -> 0.61 | D34: =E34 -> 13 | E34: 13 | F34: =Gen!V40 -> 0.42798363 | G34: =Gen!U40 -> 4766 | H34: 0 | I34: =SUM(G34:H34) -> 4766 | J34: 33780 | K34: ='Water-Meter'!E35 -> 102 | L34: ='Lpg (2)'!G39 -> 157.3 | M34: =#REF! -> #REF! | N34: =#REF! -> #REF! | O34: =#REF! -> #REF! | P34: =J34/52000 -> 0.64961538 | Q34: =I34*Q2 -> 10532145 | R34: =SUM(Q34/D34)/X34 -> 511.46781 | S34: =SUM(Q34/E34)/X34 -> 511.46781 | T34: =(K34*102)/X34 -> 6.5681818 | U34: =SUM(L34*1963)/X34 -> 194.93681 | V34: =SUM(Q34+T34+U34) -> 10532347 | W34: =SUM(V34/E34)/T2 -> 511.47759 | X34: =SUM(X33) -> 1584 | Y34: 106 | Z34: =SUM(Y34-S34) -> -405.46781
A35: =Gen!B41 -> 44561 | B35: 0 | C35: =Gen!C41 -> 0.61 | D35: =E35 -> 18 | E35: 18 | F35: =Gen!V41 -> 0.41520824 | G35: =Gen!U41 -> 4562 | H35: 0 | I35: =SUM(G35:H35) -> 4562 | J35: 33780 | K35: ='Water-Meter'!E36 -> 102 | L35: ='Lpg (2)'!G40 -> 163.02 | M35: =#REF! -> #REF! | N35: =#REF! -> #REF! | O35: =#REF! -> #REF! | P35: =J35/52000 -> 0.64961538 | Q35: =I35*Q2 -> 10081336 | R35: =SUM(Q35/D35)/X35 -> 353.5822 | S35: =SUM(Q35/E35)/X35 -> 353.5822 | T35: =(K35*102)/X35 -> 6.5681818 | U35: =SUM(L35*1963)/X35 -> 202.02542 | V35: =SUM(Q35+T35+U35) -> 10081544 | W35: =SUM(V35/E35)/T2 -> 353.58952 | X35: =SUM(X34) -> 1584 | Y35: 106 | Z35: =SUM(Y35-S35) -> -247.5822
D36: =E36 -> 0 | K36: ='Water-Meter'!E37 -> 120 | Q36: =I36*2057.79 -> 0 | V36: =SUM(Q36+T36+U36) -> 0
K37: ='Water-Meter'!E38 -> 2480 | S37: #REF!
B38: #REF! | M38: =0.5*2057.79 -> 1028.895
B39: #REF! | C39: =SUM(B39/250) -> #REF! | M39: =M38/1500 -> 0.68593 | O39: =(24*2.2)*2 -> 105.6 | P39: =O39*1029 -> 108662.4 | R39: Over budget | S39: =SUM(S37-Y35) -> #REF!
P40: =P39/K5 -> 1375.4734

Sheet VODACOM AND AIRTEL
A1: VODACOM AND AIRTEL KWH METER READING
B2: VODACOM TOWER | E2: AIRTEL TOWER
A3: DATE | B3: OPEN METER READING | C3: CLOSE METER READING | D3: UNIT CONSUMED | E3: OPEN METER READING | F3: CLOSE METER READING | G3: UNIT CONSUMED
A4: 43101 | B4: 46071 | C4: 48188 | D4: 2117 | E4: 216654 | F4: 218779 | G4: 2125
A5: 43132 | B5: =C4 -> 48188 | C5: 50066 | D5: =C5-B5 -> 1878 | E5: =F4 -> 218779 | F5: 220744 | G5: =F5-E5 -> 1965
A6: 43160 | B6: =C5 -> 50066 | C6: 51916 | D6: =C6-B6 -> 1850 | E6: =F5 -> 220744 | F6: 222873 | G6: =F6-E6 -> 2129
A7: 43191 | B7: =C6 -> 51916 | C7: 53641 | D7: =C7-B7 -> 1725 | E7: =F6 -> 222873 | F7: 224922 | G7: =F7-E7 -> 2049
A8: 43221 | B8: =C7 -> 53641 | C8: 55409 | D8: =C8-B8 -> 1768 | E8: =F7 -> 224922 | F8: 227063 | G8: =F8-E8 -> 2141
A9: 43252 | B9: =C8 -> 55409 | C9: 57396 | D9: =C9-B9 -> 1987 | E9: =F8 -> 227063 | F9: 229163 | G9: =F9-E9 -> 2100
A10: 43282 | B10: =C9 -> 57396 | C10: 59391 | D10: =C10-B10 -> 1995 | E10: =F9 -> 229163 | F10: 231359 | G10: =F10-E10 -> 2196
A11: 43313 | B11: =C10 -> 59391 | C11: 61427 | D11: =C11-B11 -> 2036 | E11: =F10 -> 231359 | F11: 233548 | G11: =F11-E11 -> 2189
A12: 43344 | B12: =C11 -> 61427 | C12: 63464 | D12: =C12-B12 -> 2037 | E12: =F11 -> 233548 | F12: 235653 | G12: =F12-E12 -> 2105
A13: 43374 | B13: =C12 -> 63464 | C13: 65577 | D13: =C13-B13 -> 2113 | E13: =F12 -> 235653 | F13: 237802 | G13: =F13-E13 -> 2149
A14: 43405 | B14: =C13 -> 65577 | C14: 67714 | D14: =C14-B14 -> 2137 | E14: =F13 -> 237802 | F14: 239883 | G14: =F14-E14 -> 2081
A15: 43435 | B15: =C14 -> 67714 | C15: 69886 | D15: =C15-B15 -> 2172 | E15: =F14 -> 239883 | F15: 242023 | G15: =F15-E15 -> 2140
A16: 43466 | B16: =C15 -> 69886 | C16: 72120 | D16: =C16-B16 -> 2234 | E16: =F15 -> 242023 | F16: 244252 | G16: =F16-E16 -> 2229
... A51: 44531 | B51: =C50 -> 143031 | C51: 145144 | D51: =C51-B51 -> 2113 | E51: =F50 -> 316380 | F51: 318576 | G51: =F51-E51 -> 2196
A52: 44562 | B52: =C51 -> 145144 | D52: =C52-B52 -> -145144 | E52: =F51 -> 318576 | G52: =F52-E52 -> -318576
A53: 44593 | B53: =C52 -> 0 | D53: =C53-B53 -> 0 | E53: =F52 -> 0 | G53: =F53-E53 -> 0
A54: 44621 | B54: =C53 -> 0 | D54: =C54-B54 -> 0 | E54: =F53 -> 0 | G54: =F54-E54 -> 0
A55: 44652 | B55: =C54 -> 0 | D55: =C55-B55 -> 0 | E55: =F54 -> 0 | G55: =F55-E55 -> 0
A56: 44682 | B56: =C55 -> 0 | D56: =C56-B56 -> 0 | E56: =F55 -> 0 | G56: =F56-E56 -> 0
A57: 44713 | B57: =C56 -> 0 | D57: =C57-B57 -> 0 | E57: =F56 -> 0 | G57: =F57-E57 -> 0
A58: 44743 | B58: =C57 -> 0 | D58: =C58-B58 -> 0 | E58: =F57 -> 0 | G58: =F58-E58 -> 0
A59: 44774 | B59: =C58 -> 0 | D59: =C59-B59 -> 0 | E59: =F58 -> 0 | G59: =F59-E59 -> 0
A60: 44805 | B60: =C59 -> 0 | D60: =C60-B60 -> 0 | E60: =F59 -> 0 | G60: =F60-E60 -> 0
A61: 44835 | B61: =C60 -> 0 | D61: =C61-B61 -> 0 | E61: =F60 -> 0 | G61: =F61-E61 -> 0
A62: 44866 | B62: =C61 -> 0 | D62: =C62-B62 -> 0 | E62: =F61 -> 0 | G62: =F62-E62 -> 0
A63: 44896 | B63: =C62 -> 0 | D63: =C63-B63 -> 0 | E63: =F62 -> 0 | G63: =F63-E63 -> 0
... A75: 44896 | B75: =C74 -> 0 | D75: =C75-B75 -> 0 | E75: =F74 -> 0 | G75: =F75-E75 -> 0
B89: VODACOM POWER METER READING | E89: AITEL POWER METER READING

Sheet FUEL METER READING
A1: FUEL METER 1 READNG | H1: FUEL METER 2 READING
A2: DATE | B2: OPEN METER READING | C2: CLOSE METER READING | D2: Diesel consumed | E2: HLP-GENSETS | F2: DIFFERENCE | G2: OPEN METER | H2: CLOSE METER | I2: DIESEL CONSUMED | J2: HLP-VEHICLES | K2: DIFFERENCE | L2: TOTAL DIESEL CONS.
A3: 43101 | B3: 6476953 | C3: 6542879 | D3: 65926 | E3: 65927.77 | F3: -1.77 | G3: =H2 -> CLOSE METER | H3: 59763 | I3: =H3-G3 -> #VALUE! | J3: 6874.87 | K3: =I3-J3 -> #VALUE! | L3: 72799
A4: 43132 | B4: 6542879 | C4: 6604433 | D4: 61554 | E4: 61553.03 | F4: 0.97 | G4: =H3 -> 59763 | H4: 66652 | I4: =H4-G4 -> 6889 | J4: 6890.89 | K4: =I4-J4 -> -1.89 | L4: 68443
A5: 43160 | B5: 6604433 | C5: 6660226 | D5: 55793 | E5: 55792.75 | F5: 0.25 | G5: =H4 -> 66652 | H5: 77607 | I5: =H5-G5 -> 10955 | J5: 10955.45 | K5: =I5-J5 -> -0.45 | L5: 66748
A6: 43191 | B6: 6660226 | C6: 6714539 | D6: 54313 | E6: 54312.28 | F6: 0.72 | G6: =H5 -> 77607 | H6: 82271 | I6: =H6-G6 -> 4664 | J6: 4665.22 | K6: =I6-J6 -> -1.22 | L6: 58977
A7: 43221 | B7: 6714539 | C7: 6774547 | D7: 60008 | E7: 60007.47 | F7: 0.53 | G7: =H6 -> 82271 | H7: 88664 | I7: =H7-G7 -> 6393 | J7: 6392.14 | K7: =I7-J7 -> 0.86 | L7: 66401
A8: 43252 | B8: 6774547 | C8: 6845214 | D8: 70667 | E8: 70666.29 | F8: 0.71 | G8: =H7 -> 88664 | H8: 99683 | I8: =H8-G8 -> 11019 | J8: 11020.51 | K8: =I8-J8 -> -1.51 | L8: 81686
A9: 43282 | B9: 6845214 | C9: 6921964 | D9: 76750 | E9: 76750.25 | F9: -0.25 | G9: =H8 -> 99683 | H9: 107936 | I9: =H9-G9 -> 8253 | J9: 8252.24 | K9: =I9-J9 -> 0.76 | L9: 85003
A10: 43313 | B10: 6921964 | C10: 7001142 | D10: 79178 | E10: 79179.56 | F10: -1.56 | G10: =H9 -> 107936 | H10: 116730 | I10: =H10-G10 -> 8794 | J10: 8793.12 | K10: =I10-J10 -> 0.88 | L10: 87972
A11: 43344 | B11: 7001142 | C11: 7074217 | D11: 73075 | E11: 73076.96 | F11: -1.96 | G11: =H10 -> 116730 | H11: 127346 | I11: =H11-G11 -> 10616 | J11: 10615.37 | K11: =I11-J11 -> 0.63 | L11: 83691
A12: 43374 | B12: 7074217 | C12: 7154506 | D12: 80289 | E12: 80287.84 | F12: 1.16 | G12: =H11 -> 127346 | H12: 134840 | I12: =H12-G12 -> 7494 | J12: 7493.99 | K12: =I12-J12 -> 0.01 | L12: 87783
A13: 43405 | B13: 7154506 | C13: 7225359 | D13: 70853 | E13: 70852.88 | F13: 0.12 | G13: =H12 -> 134840 | H13: 145302 | I13: =H13-G13 -> 10462 | J13: 10462.7 | K13: =I13-J13 -> -0.7 | L13: 81315
A14: 43435 | B14: 7225359 | C14: 7296581 | D14: 71222 | E14: 71221.22 | F14: 0.78 | G14: =H13 -> 145302 | H14: 154999 | I14: =H14-G14 -> 9697 | J14: 9696.8 | K14: =I14-J14 -> 0.2 | L14: 80919
