Workbook

Sheet Total
A1: Site Name | B1: Day | C1: Month | D1: Year | E1: Total Electricity Kwh | F1: Electricity Tariff ($/Kwh) | G1: LPG (Kg) | H1: LPG $/Kg | I1: Water Utility Supply (m3) m3 | J1: Water Utility Supply (m3) $/m3 | K1: Room Nights | L1: Utilities day cost dh
A2: Serengeti | B2: 1 | C2: 1 | D2: =Submetering!D2 -> 2022 | E2: ='UTILITY REPORT 1'!F3 -> 4734 | F2: =('UTILITY REPORT 1'!E3*'UTILITY REPORT 1'!D3)/'UTILITY REPORT 1'!F3 -> 0.41514575 | G2: =IF('Utility summery'!M6<0,"0",'Utility summery'!M6) -> 144.452 | H2: 2.165 | I2: =IF('UTILITY REPORT 1'!G3<0,"0",'UTILITY REPORT 1'!G3) -> 116 | J2: 0 | K2: 89 | L2: =E2*F2+G2*H2+#REF!*#REF!+I2*J2 -> #REF!
A3: Serengeti | B3: =B2+1 -> 2 | C3: 1 | D3: =Submetering!D3 -> 2022 | E3: ='UTILITY REPORT 1'!F4 -> 4563 | F3: =('UTILITY REPORT 1'!E4*'UTILITY REPORT 1'!D4)/'UTILITY REPORT 1'!F4 -> 0.42232742 | G3: =IF('Utility summery'!M7<0,"0",'Utility summery'!M7) -> 150.7 | H3: 2.165 | I3: =IF('UTILITY REPORT 1'!G4<0,"0",'UTILITY REPORT 1'!G4) -> 94 | J3: 0 | K3: 102 | L3: =E3*F3+G3*H3+#REF!*#REF!+I3*J3 -> #REF!
A4: Serengeti | B4: =B3+1 -> 3 | C4: 1 | D4: =Submetering!D4 -> 2022 | E4: ='UTILITY REPORT 1'!F5 -> 4574 | F4: =('UTILITY REPORT 1'!E5*'UTILITY REPORT 1'!D5)/'UTILITY REPORT 1'!F5 -> 0.40662877 | G4: =IF('Utility summery'!M8<0,"0",'Utility summery'!M8) -> 156.948 | H4: 2.165 | I4: =IF('UTILITY REPORT 1'!G5<0,"0",'UTILITY REPORT 1'!G5) -> 110 | J4: 0 | K4: 74 | L4: =E4*F4+G4*H4+#REF!*#REF!+I4*J4 -> #REF!
A5: Serengeti | B5: =B4+1 -> 4 | C5: 1 | D5: =Submetering!D5 -> 2022 | E5: ='UTILITY REPORT 1'!F6 -> 4346 | F5: =('UTILITY REPORT 1'!E6*'UTILITY REPORT 1'!D6)/'UTILITY REPORT 1'!F6 -> 0.43481362 | G5: =IF('Utility summery'!M9<0,"0",'Utility summery'!M9) -> 132.088 | H5: 2.165 | I5: =IF('UTILITY REPORT 1'!G6<0,"0",'UTILITY REPORT 1'!G6) -> 94 | J5: 0 | K5: 68 | L5: =E5*F5+G5*H5+#REF!*#REF!+I5*J5 -> #REF!
A6: Serengeti | B6: =B5+1 -> 5 | C6: 1 | D6: =Submetering!D6 -> 2022 | E6: ='UTILITY REPORT 1'!F7 -> 3969 | F6: =('UTILITY REPORT 1'!E7*'UTILITY REPORT 1'!D7)/'UTILITY REPORT 1'!F7 -> 0.43244898 | G6: =IF('Utility summery'!M10<0,"0",'Utility summery'!M10) -> 122.188 | H6: 2.165 | I6: =IF('UTILITY REPORT 1'!G7<0,"0",'UTILITY REPORT 1'!G7) -> 86 | J6: 0 | K6: 48 | L6: =E6*F6+G6*H6+#REF!*#REF!+I6*J6 -> #REF!
A7: Serengeti | B7: =B6+1 -> 6 | C7: 1 | D7: =Submetering!D7 -> 2022 | E7: ='UTILITY REPORT 1'!F8 -> 4325 | F7: =('UTILITY REPORT 1'!E8*'UTILITY REPORT 1'!D8)/'UTILITY REPORT 1'!F8 -> 0.42292486 | G7: =IF('Utility summery'!M11<0,"0",'Utility summery'!M11) -> 137.72 | H7: 2.165 | I7: =IF('UTILITY REPORT 1'!G8<0,"0",'UTILITY REPORT 1'!G8) -> 90 | J7: 0 | K7: 61 | L7: =E7*F7+G7*H7+#REF!*#REF!+I7*J7 -> #REF!
A8: Serengeti | B8: =B7+1 -> 7 | C8: 1 | D8: =Submetering!D8 -> 2022 | E8: ='UTILITY REPORT 1'!F9 -> 4444 | F8: =('UTILITY REPORT 1'!E9*'UTILITY REPORT 1'!D9)/'UTILITY REPORT 1'!F9 -> 0.41997075 | G8: =IF('Utility summery'!M12<0,"0",'Utility summery'!M12) -> 132.88 | H8: 2.165 | I8: =IF('UTILITY REPORT 1'!G9<0,"0",'UTILITY REPORT 1'!G9) -> 92 | J8: 0 | K8: 46 | L8: =E8*F8+G8*H8+#REF!*#REF!+I8*J8 -> #REF!
A9: Serengeti | B9: =B8+1 -> 8 | C9: 1 | D9: =Submetering!D9 -> 2022 | E9: ='UTILITY REPORT 1'!F10 -> 4291 | F9: =('UTILITY REPORT 1'!E10*'UTILITY REPORT 1'!D10)/'UTILITY REPORT 1'!F10 -> 0.41184805 | G9: =IF('Utility summery'!M13<0,"0",'Utility summery'!M13) -> 112.024 | H9: 2.165 | I9: =IF('UTILITY REPORT 1'!G10<0,"0",'UTILITY REPORT 1'!G10) -> 108 | J9: 0 | K9: 48 | L9: =E9*F9+G9*H9+#REF!*#REF!+I9*J9 -> #REF!
A10: Serengeti | B10: =B9+1 -> 9 | C10: 1 | D10: =Submetering!D10 -> 2022 | E10: ='UTILITY REPORT 1'!F11 -> 4336 | F10: =('UTILITY REPORT 1'!E11*'UTILITY REPORT 1'!D11)/'UTILITY REPORT 1'!F11 -> 0.42574954 | G10: =IF('Utility summery'!M14<0,"0",'Utility summery'!M14) -> 106.084 | H10: 2.165 | I10: =IF('UTILITY REPORT 1'!G11<0,"0",'UTILITY REPORT 1'!G11) -> 101 | J10: 0 | K10: 43 | L10: =E10*F10+G10*H10+#REF!*#REF!+I10*J10 -> #REF!
A11: Serengeti | B11: =B10+1 -> 10 | C11: 1 | D11: =Submetering!D11 -> 2022 | E11: ='UTILITY REPORT 1'!F12 -> 4279 | F11: =('UTILITY REPORT 1'!E12*'UTILITY REPORT 1'!D12)/'UTILITY REPORT 1'!F12 -> 0.41262678 | G11: =IF('Utility summery'!M15<0,"0",'Utility summery'!M15) -> 113.784 | H11: 2.165 | I11: =IF('UTILITY REPORT 1'!G12<0,"0",'UTILITY REPORT 1'!G12) -> 83 | J11: 0 | K11: 39 | L11: =E11*F11+G11*H11+#REF!*#REF!+I11*J11 -> #REF!
A12: Serengeti | B12: =B11+1 -> 11 | C12: 1 | D12: =Submetering!D12 -> 2022 | E12: ='UTILITY REPORT 1'!F13 -> 3862 | F12: =('UTILITY REPORT 1'!E13*'UTILITY REPORT 1'!D13)/'UTILITY REPORT 1'!F13 -> 0.42083894 | G12: =IF('Utility summery'!M16<0,"0",'Utility summery'!M16) -> 116.908 | H12: 2.165 | I12: =IF('UTILITY REPORT 1'!G13<0,"0",'UTILITY REPORT 1'!G13) -> 67 | J12: 0 | K12: 23 | L12: =E12*F12+G12*H12+#REF!*#REF!+I12*J12 -> #REF!
A13: Serengeti | B13: =B12+1 -> 12 | C13: 1 | D13: =Submetering!D13 -> 2022 | E13: ='UTILITY REPORT 1'!F14 -> 3803 | F13: =('UTILITY REPORT 1'!E14*'UTILITY REPORT 1'!D14)/'UTILITY REPORT 1'!F14 -> 0.42066001 | G13: =IF('Utility summery'!M17<0,"0",'Utility summery'!M17) -> 99.484 | H13: 2.165 | I13: =IF('UTILITY REPORT 1'!G14<0,"0",'UTILITY REPORT 1'!G14) -> 133 | J13: 0 | K13: 17 | L13: =E13*F13+G13*H13+#REF!*#REF!+I13*J13 -> #REF!
A14: Serengeti | B14: =B13+1 -> 13 | C14: 1 | D14: =Submetering!D14 -> 2022 | E14: ='UTILITY REPORT 1'!F15 -> 3648 | F14: =('UTILITY REPORT 1'!E15*'UTILITY REPORT 1'!D15)/'UTILITY REPORT 1'!F15 -> 0.41318257 | G14: =IF('Utility summery'!M18<0,"0",'Utility summery'!M18) -> 90.904 | H14: 2.165 | I14: =IF('UTILITY REPORT 1'!G15<0,"0",'UTILITY REPORT 1'!G15) -> 86 | J14: 0 | K14: 29 | L14: =E14*F14+G14*H14+#REF!*#REF!+I14*J14 -> #REF!
... A30: Serengeti | B30: =B29+1 -> 29 | C30: 1 | D30: =Submetering!D30 -> 2022 | E30: ='UTILITY REPORT 1'!F31 -> 3589 | F30: =('UTILITY REPORT 1'!E31*'UTILITY REPORT 1'!D31)/'UTILITY REPORT 1'!F31 -> 0.39403455 | G30: =IF('Utility summery'!M34<0,"0",'Utility summery'!M34) -> 112.816 | H30: 2.165 | I30: =IF('UTILITY REPORT 1'!G31<0,"0",'UTILITY REPORT 1'!G31) -> 80 | J30: 0 | K30: 20 | L30: =E30*F30+G30*H30+#REF!*#REF!+I30*J30 -> #REF!
A31: Serengeti | B31: 30 | C31: 1 | D31: =Submetering!D31 -> 2022 | E31: ='UTILITY REPORT 1'!F32 -> 3575 | F31: =('UTILITY REPORT 1'!E32*'UTILITY REPORT 1'!D32)/'UTILITY REPORT 1'!F32 -> 0.37674685 | G31: =IF('Utility summery'!M35<0,"0",'Utility summery'!M35) -> 103.796 | H31: 2.165 | I31: =IF('UTILITY REPORT 1'!G32<0,"0",'UTILITY REPORT 1'!G32) -> 110 | J31: 0 | K31: 18 | L31: =E31*F31+G31*H31+#REF!*#REF!+I31*J31 -> #REF!
A32: Serengeti | B32: 31 | C32: 1 | D32: =Submetering!D32 -> 2022 | E32: ='UTILITY REPORT 1'!F33 -> 3272 | F32: =('UTILITY REPORT 1'!E33*'UTILITY REPORT 1'!D33)/'UTILITY REPORT 1'!F33 -> 0.39228606 | G32: =IF('Utility summery'!M36<0,"0",'Utility summery'!M36) -> 0 | H32: 2.165 | I32: =IF('UTILITY REPORT 1'!G33<0,"0",'UTILITY REPORT 1'!G33) -> 104 | J32: 0 | K32: 12

Sheet Submetering
A1: Site Name | B1: Day | C1: Month | D1: Year | E1: Transport Consumption (LT) | F1: Generators Consumption (LT) | G1: Total Electricity Kwh | H1: Kitchen (KWh) | I1: Laundry (KWh) | J1: STP (M3) | K1: RO prodution (M3) | L1: Amani Restaurant (M3) | M1: Kitchen (M3) | N1: Laundry (M3) | O1: Laundry (M3) | P1: Total water Consumption (M3) | Q1: Borehole #1 (M3) | R1: Borehole #2 (M3) | S1: Borehole #3 (M3) | T1: Borehole #4 (M3) | U1: Borehole #5 (M3) | V1: Borehole #6 (M3) | W1: Total Bore holes production (M3) | X1: Room Nights
A2: Serengeti | B2: 1 | C2: 1 | D2: 2022 | E2: ='UTILITY REPORT 1'!I3 -> 320.11 | F2: ='UTILITY REPORT 1'!E3 -> 1965.3 | G2: ='UTILITY REPORT 1'!F3 -> 4734 | H2: =IF('Kit report'!F4<0,"0",'Kit report'!F4) -> 564 | I2: =IF('Kit report'!X4<0,"0",'Kit report'!X4) -> 940 | J2: =IF('Utility summery'!H6<0,"0",'Utility summery'!H6) -> 56 | K2: =IF('UTILITY REPORT 1'!H3<0,"0",'UTILITY REPORT 1'!H3) -> 102 | L2: ='Water-Meter'!K6 -> 3 | M2: ='Water-Meter'!H6 -> 0 | N2: ='Water-Meter'!Q6 -> 11 | O2: =K2*E2+H2*I2+#REF!*#REF!+J2*L2 -> #REF! | P2: ='Water-Meter'!E6 -> 116 | Q2: =IF('Water-Meter'!U6<0,"0",'Water-Meter'!U6) -> 69 | R2: =IF('Water-Meter'!X6<0,"0",'Water-Meter'!X6) -> 0 | S2: =IF('Water-Meter'!AA6<0,"0",'Water-Meter'!AA6) -> 36 | T2: =IF('Water-Meter'!AD6<0,"0",'Water-Meter'!AD6) -> 17 | U2: =IF('Water-Meter'!AG6<0,"0",'Water-Meter'!AG6) -> 0 | V2: =IF('Water-Meter'!AJ6<0,"0",'Water-Meter'!AJ6) -> 35 | W2: ='Water-Meter'!AN6 -> 157 | X2: =Total!K2 -> 89
A3: Serengeti | B3: =B2+1 -> 2 | C3: 1 | D3: 2022 | E3: ='UTILITY REPORT 1'!I4 -> 237.31 | F3: ='UTILITY REPORT 1'!E4 -> 1927.08 | G3: ='UTILITY REPORT 1'!F4 -> 4563 | H3: =IF('Kit report'!F5<0,"0",'Kit report'!F5) -> 204 | I3: =IF('Kit report'!X5<0,"0",'Kit report'!X5) -> 1040 | J3: =IF('Utility summery'!H7<0,"0",'Utility summery'!H7) -> 55 | K3: =IF('UTILITY REPORT 1'!H4<0,"0",'UTILITY REPORT 1'!H4) -> 64 | L3: ='Water-Meter'!K7 -> 3 | M3: ='Water-Meter'!H7 -> 0 | N3: ='Water-Meter'!Q7 -> 9 | O3: =K3*E3+H3*I3+#REF!*#REF!+J3*L3 -> #REF! | P3: ='Water-Meter'!E7 -> 94 | Q3: =IF('Water-Meter'!U7<0,"0",'Water-Meter'!U7) -> 70 | R3: =IF('Water-Meter'!X7<0,"0",'Water-Meter'!X7) -> 0 | S3: =IF('Water-Meter'!AA7<0,"0",'Water-Meter'!AA7) -> 36 | T3: =IF('Water-Meter'!AD7<0,"0",'Water-Meter'!AD7) -> 18 | U3: =IF('Water-Meter'!AG7<0,"0",'Water-Meter'!AG7) -> 0 | V3: =IF('Water-Meter'!AJ7<0,"0",'Water-Meter'!AJ7) -> 35 | W3: ='Water-Meter'!AN7 -> 159 | X3: =Total!K3 -> 102
A4: Serengeti | B4: =B3+1 -> 3 | C4: 1 | D4: 2022 | E4: ='UTILITY REPORT 1'!I5 -> 231 | F4: ='UTILITY REPORT 1'!E5 -> 1859.92 | G4: ='UTILITY REPORT 1'!F5 -> 4574 | H4: =IF('Kit report'!F6<0,"0",'Kit report'!F6) -> 276 | I4: =IF('Kit report'!X6<0,"0",'Kit report'!X6) -> 920 | J4: =IF('Utility summery'!H8<0,"0",'Utility summery'!H8) -> 56 | K4: =IF('UTILITY REPORT 1'!H5<0,"0",'UTILITY REPORT 1'!H5) -> 105 | L4: ='Water-Meter'!K8 -> 4 | M4: ='Water-Meter'!H8 -> 0 | N4: ='Water-Meter'!Q8 -> 12 | O4: =K4*E4+H4*I4+#REF!*#REF!+J4*L4 -> #REF! | P4: ='Water-Meter'!E8 -> 110 | Q4: =IF('Water-Meter'!U8<0,"0",'Water-Meter'!U8) -> 67 | R4: =IF('Water-Meter'!X8<0,"0",'Water-Meter'!X8) -> 0 | S4: =IF('Water-Meter'!AA8<0,"0",'Water-Meter'!AA8) -> 36 | T4: =IF('Water-Meter'!AD8<0,"0",'Water-Meter'!AD8) -> 18 | U4: =IF('Water-Meter'!AG8<0,"0",'Water-Meter'!AG8) -> 0 | V4: =IF('Water-Meter'!AJ8<0,"0",'Water-Meter'!AJ8) -> 36 | W4: ='Water-Meter'!AG17 -> 0 | X4: =Total!K4 -> 74
A5: Serengeti | B5: =B4+1 -> 4 | C5: 1 | D5: 2022 | E5: ='UTILITY REPORT 1'!I6 -> 247.48 | F5: ='UTILITY REPORT 1'!E6 -> 1889.7 | G5: ='UTILITY REPORT 1'!F6 -> 4346 | H5: =IF('Kit report'!F7<0,"0",'Kit report'!F7) -> 228 | I5: =IF('Kit report'!X7<0,"0",'Kit report'!X7) -> 740 | J5: =IF('Utility summery'!H9<0,"0",'Utility summery'!H9) -> 59 | K5: =IF('UTILITY REPORT 1'!H6<0,"0",'UTILITY REPORT 1'!H6) -> 147 | L5: ='Water-Meter'!K9 -> 3 | M5: ='Water-Meter'!H9 -> 0 | N5: ='Water-Meter'!Q9 -> 9 | O5: =K5*E5+H5*I5+#REF!*#REF!+J5*L5 -> #REF! | P5: ='Water-Meter'!E9 -> 94 | Q5: =IF('Water-Meter'!U9<0,"0",'Water-Meter'!U9) -> 69 | R5: =IF('Water-Meter'!X9<0,"0",'Water-Meter'!X9) -> 0 | S5: =IF('Water-Meter'!AA9<0,"0",'Water-Meter'!AA9) -> 38 | T5: =IF('Water-Meter'!AD9<0,"0",'Water-Meter'!AD9) -> 18 | U5: =IF('Water-Meter'!AG9<0,"0",'Water-Meter'!AG9) -> 0 | V5: =IF('Water-Meter'!AJ9<0,"0",'Water-Meter'!AJ9) -> 38 | W5: ='Water-Meter'!AN9 -> 163 | X5: =Total!K5 -> 68
A6: Serengeti | B6: =B5+1 -> 5 | C6: 1 | D6: 2022 | E6: ='UTILITY REPORT 1'!I7 -> 110 | F6: ='UTILITY REPORT 1'!E7 -> 1716.39 | G6: ='UTILITY REPORT 1'!F7 -> 3969 | H6: =IF('Kit report'!F8<0,"0",'Kit report'!F8) -> 204 | I6: =IF('Kit report'!X8<0,"0",'Kit report'!X8) -> 740 | J6: =IF('Utility summery'!H10<0,"0",'Utility summery'!H10) -> 49 | K6: =IF('UTILITY REPORT 1'!H7<0,"0",'UTILITY REPORT 1'!H7) -> 0 | L6: ='Water-Meter'!K10 -> 3 | M6: ='Water-Meter'!H10 -> 0 | N6: ='Water-Meter'!Q10 -> 9 | O6: =K6*E6+H6*I6+#REF!*#REF!+J6*L6 -> #REF! | P6: ='Water-Meter'!E10 -> 86 | Q6: =IF('Water-Meter'!U10<0,"0",'Water-Meter'!U10) -> 69 | R6: =IF('Water-Meter'!X10<0,"0",'Water-Meter'!X10) -> 0 | S6: =IF('Water-Meter'!AA10<0,"0",'Water-Meter'!AA10) -> 38 | T6: =IF('Water-Meter'!AD10<0,"0",'Water-Meter'!AD10) -> 16 | U6: =IF('Water-Meter'!AG10<0,"0",'Water-Meter'!AG10) -> 0 | V6: =IF('Water-Meter'!AJ10<0,"0",'Water-Meter'!AJ10) -> 33 | W6: ='Water-Meter'!AN10 -> 156 | X6: =Total!K6 -> 48
A7: Serengeti | B7: =B6+1 -> 6 | C7: 1 | D7: 2022 | E7: ='UTILITY REPORT 1'!I8 -> 299.04 | F7: ='UTILITY REPORT 1'!E8 -> 1829.15 | G7: ='UTILITY REPORT 1'!F8 -> 4325 | H7: =IF('Kit report'!F9<0,"0",'Kit report'!F9) -> 228 | I7: =IF('Kit report'!X9<0,"0",'Kit report'!X9) -> 660 | J7: =IF('Utility summery'!H11<0,"0",'Utility summery'!H11) -> 54 | K7: =IF('UTILITY REPORT 1'!H8<0,"0",'UTILITY REPORT 1'!H8) -> 148 | L7: ='Water-Meter'!K11 -> -1 | M7: ='Water-Meter'!H11 -> 0 | N7: ='Water-Meter'!Q11 -> 34 | O7: =K7*E7+H7*I7+#REF!*#REF!+J7*L7 -> #REF! | P7: ='Water-Meter'!E11 -> 90 | Q7: =IF('Water-Meter'!U11<0,"0",'Water-Meter'!U11) -> 67 | R7: =IF('Water-Meter'!X11<0,"0",'Water-Meter'!X11) -> 0 | S7: =IF('Water-Meter'!AA11<0,"0",'Water-Meter'!AA11) -> 32 | T7: =IF('Water-Meter'!AD11<0,"0",'Water-Meter'!AD11) -> 17 | U7: =IF('Water-Meter'!AG11<0,"0",'Water-Meter'!AG11) -> 0 | V7: =IF('Water-Meter'!AJ11<0,"0",'Water-Meter'!AJ11) -> 36 | W7: ='Water-Meter'!AN11 -> 152 | X7: =Total!K7 -> 61
A8: Serengeti | B8: =B7+1 -> 7 | C8: 1 | D8: 2022 | E8: ='UTILITY REPORT 1'!I9 -> 133 | F8: ='UTILITY REPORT 1'!E9 -> 1866.35 | G8: ='UTILITY REPORT 1'!F9 -> 4444 | H8: =IF('Kit report'!F10<0,"0",'Kit report'!F10) -> 216 | I8: =IF('Kit report'!X10<0,"0",'Kit report'!X10) -> 740 | J8: =IF('Utility summery'!H12<0,"0",'Utility summery'!H12) -> 0 | K8: =IF('UTILITY REPORT 1'!H9<0,"0",'UTILITY REPORT 1'!H9) -> 0 | L8: ='Water-Meter'!K12 -> 2 | M8: ='Water-Meter'!H12 -> 0 | N8: ='Water-Meter'!Q12 -> 8 | O8: =K8*E8+H8*I8+#REF!*#REF!+J8*L8 -> #REF! | P8: ='Water-Meter'!E12 -> 92 | Q8: =IF('Water-Meter'!U12<0,"0",'Water-Meter'!U12) -> 66 | R8: =IF('Water-Meter'!X12<0,"0",'Water-Meter'!X12) -> 0 | S8: =IF('Water-Meter'!AA12<0,"0",'Water-Meter'!AA12) -> 38 | T8: =IF('Water-Meter'!AD12<0,"0",'Water-Meter'!AD12) -> 16 | U8: =IF('Water-Meter'!AG12<0,"0",'Water-Meter'!AG12) -> 0 | V8: =IF('Water-Meter'!AJ12<0,"0",'Water-Meter'!AJ12) -> 37 | W8: ='Water-Meter'!AN12 -> 157 | X8: =Total!K8 -> 46
A9: Serengeti | B9: =B8+1 -> 8 | C9: 1 | D9: 2022 | E9: ='UTILITY REPORT 1'!I10 -> 162.47 | F9: ='UTILITY REPORT 1'!E10 -> 1767.24 | G9: ='UTILITY REPORT 1'!F10 -> 4291 | H9: =IF('Kit report'!F11<0,"0",'Kit report'!F11) -> 240 | I9: =IF('Kit report'!X11<0,"0",'Kit report'!X11) -> 700 | J9: =IF('Utility summery'!H13<0,"0",'Utility summery'!H13) -> 229265 | K9: =IF('UTILITY REPORT 1'!H10<0,"0",'UTILITY REPORT 1'!H10) -> 22575 | L9: ='Water-Meter'!K13 -> 2 | M9: ='Water-Meter'!H13 -> 0 | N9: ='Water-Meter'!Q13 -> 6 | O9: =K9*E9+H9*I9+#REF!*#REF!+J9*L9 -> #REF! | P9: ='Water-Meter'!E13 -> 108 | Q9: =IF('Water-Meter'!U13<0,"0",'Water-Meter'!U13) -> 72 | R9: =IF('Water-Meter'!X13<0,"0",'Water-Meter'!X13) -> 0 | S9: =IF('Water-Meter'!AA13<0,"0",'Water-Meter'!AA13) -> 35 | T9: =IF('Water-Meter'!AD13<0,"0",'Water-Meter'!AD13) -> 16 | U9: =IF('Water-Meter'!AG13<0,"0",'Water-Meter'!AG13) -> 0 | V9: =IF('Water-Meter'!AJ13<0,"0",'Water-Meter'!AJ13) -> 35 | W9: ='Water-Meter'!AN13 -> 158 | X9: =Total!K9 -> 48
A10: Serengeti | B10: =B9+1 -> 9 | C10: 1 | D10: 2022 | E10: ='UTILITY REPORT 1'!I11 -> 109.74 | F10: ='UTILITY REPORT 1'!E11 -> 1846.05 | G10: ='UTILITY REPORT 1'!F11 -> 4336 | H10: =IF('Kit report'!F12<0,"0",'Kit report'!F12) -> 252 | I10: =IF('Kit report'!X12<0,"0",'Kit report'!X12) -> 780 | J10: =IF('Utility summery'!H14<0,"0",'Utility summery'!H14) -> 56 | K10: =IF('UTILITY REPORT 1'!H11<0,"0",'UTILITY REPORT 1'!H11) -> 128 | L10: ='Water-Meter'!K14 -> 3 | M10: ='Water-Meter'!H14 -> 0 | N10: ='Water-Meter'!Q14 -> 4 | O10: =K10*E10+H10*I10+#REF!*#REF!+J10*L10 -> #REF! | P10: ='Water-Meter'!E14 -> 101 | Q10: =IF('Water-Meter'!U14<0,"0",'Water-Meter'!U14) -> 67 | R10: =IF('Water-Meter'!X14<0,"0",'Water-Meter'!X14) -> 0 | S10: =IF('Water-Meter'!AA14<0,"0",'Water-Meter'!AA14) -> 39 | T10: =IF('Water-Meter'!AD14<0,"0",'Water-Meter'!AD14) -> 13 | U10: =IF('Water-Meter'!AG14<0,"0",'Water-Meter'!AG14) -> 0 | V10: =IF('Water-Meter'!AJ14<0,"0",'Water-Meter'!AJ14) -> 35 | W10: ='Water-Meter'!AN14 -> 154 | X10: =Total!K10 -> 43
A11: Serengeti | B11: =B10+1 -> 10 | C11: 1 | D11: 2022 | E11: ='UTILITY REPORT 1'!I12 -> 79.83 | F11: ='UTILITY REPORT 1'!E12 -> 1765.63 | G11: ='UTILITY REPORT 1'!F12 -> 4279 | H11: =IF('Kit report'!F13<0,"0",'Kit report'!F13) -> 288 | I11: =IF('Kit report'!X13<0,"0",'Kit report'!X13) -> 640 | J11: =IF('Utility summery'!H15<0,"0",'Utility summery'!H15) -> 3 | K11: =IF('UTILITY REPORT 1'!H12<0,"0",'UTILITY REPORT 1'!H12) -> 77 | L11: ='Water-Meter'!K15 -> 2 | M11: ='Water-Meter'!H15 -> 0 | N11: ='Water-Meter'!Q15 -> 17 | O11: =K11*E11+H11*I11+#REF!*#REF!+J11*L11 -> #REF! | P11: ='Water-Meter'!E15 -> 83 | Q11: =IF('Water-Meter'!U15<0,"0",'Water-Meter'!U15) -> 0 | R11: =IF('Water-Meter'!X15<0,"0",'Water-Meter'!X15) -> 0 | S11: =IF('Water-Meter'!AA15<0,"0",'Water-Meter'!AA15) -> 38 | T11: =IF('Water-Meter'!AD15<0,"0",'Water-Meter'!AD15) -> 14 | U11: =IF('Water-Meter'!AG15<0,"0",'Water-Meter'!AG15) -> 0 | V11: =IF('Water-Meter'!AJ15<0,"0",'Water-Meter'!AJ15) -> 36 | W11: ='Water-Meter'!AN15 -> 88 | X11: =Total!K11 -> 39
A12: Serengeti | B12: =B11+1 -> 11 | C12: 1 | D12: 2022 | E12: ='UTILITY REPORT 1'!I13 -> 386.46 | F12: ='UTILITY REPORT 1'!E13 -> 1625.28 | G12: ='UTILITY REPORT 1'!F13 -> 3862 | H12: =IF('Kit report'!F14<0,"0",'Kit report'!F14) -> 288 | I12: =IF('Kit report'!X14<0,"0",'Kit report'!X14) -> 500 | J12: =IF('Utility summery'!H16<0,"0",'Utility summery'!H16) -> 3 | K12: =IF('UTILITY REPORT 1'!H13<0,"0",'UTILITY REPORT 1'!H13) -> 114 | L12: ='Water-Meter'!K16 -> 2 | M12: ='Water-Meter'!H16 -> 0 | N12: ='Water-Meter'!Q16 -> 8 | O12: =K12*E12+H12*I12+#REF!*#REF!+J12*L12 -> #REF! | P12: ='Water-Meter'!E16 -> 67 | Q12: =IF('Water-Meter'!U16<0,"0",'Water-Meter'!U16) -> 0 | R12: =IF('Water-Meter'!X16<0,"0",'Water-Meter'!X16) -> 0 | S12: =IF('Water-Meter'!AA16<0,"0",'Water-Meter'!AA16) -> 42 | T12: =IF('Water-Meter'!AD16<0,"0",'Water-Meter'!AD16) -> 11 | U12: =IF('Water-Meter'!AG16<0,"0",'Water-Meter'!AG16) -> 0 | V12: =IF('Water-Meter'!AJ16<0,"0",'Water-Meter'!AJ16) -> 34 | W12: ='Water-Meter'!AN16 -> 87 | X12: =Total!K12 -> 23
A13: Serengeti | B13: =B12+1 -> 12 | C13: 1 | D13: 2022 | E13: ='UTILITY REPORT 1'!I14 -> 0 | F13: ='UTILITY REPORT 1'!E14 -> 1599.77 | G13: ='UTILITY REPORT 1'!F14 -> 3803 | H13: =IF('Kit report'!F15<0,"0",'Kit report'!F15) -> 240 | I13: =IF('Kit report'!X15<0,"0",'Kit report'!X15) -> 540 | J13: =IF('Utility summery'!H17<0,"0",'Utility summery'!H17) -> 0 | K13: =IF('UTILITY REPORT 1'!H14<0,"0",'UTILITY REPORT 1'!H14) -> 112 | L13: ='Water-Meter'!K17 -> 3 | M13: ='Water-Meter'!H17 -> 0 | N13: ='Water-Meter'!Q17 -> 9 | O13: =K13*E13+H13*I13+#REF!*#REF!+J13*L13 -> #REF! | P13: ='Water-Meter'!E17 -> 133 | Q13: =IF('Water-Meter'!U17<0,"0",'Water-Meter'!U17) -> 0 | R13: =IF('Water-Meter'!X17<0,"0",'Water-Meter'!X17) -> 0 | S13: =IF('Water-Meter'!AA17<0,"0",'Water-Meter'!AA17) -> 38 | T13: =IF('Water-Meter'!AD17<0,"0",'Water-Meter'!AD17) -> 13 | U13: =IF('Water-Meter'!AG17<0,"0",'Water-Meter'!AG17) -> 0 | V13: =IF('Water-Meter'!AJ17<0,"0",'Water-Meter'!AJ17) -> 35 | W13: ='Water-Meter'!AN17 -> 86 | X13: =Total!K13 -> 17
A14: Serengeti | B14: =B13+1 -> 13 | C14: 1 | D14: 2022 | E14: ='UTILITY REPORT 1'!I15 -> 66.31 | F14: ='UTILITY REPORT 1'!E15 -> 1507.29 | G14: ='UTILITY REPORT 1'!F15 -> 3648 | H14: =IF('Kit report'!F16<0,"0",'Kit report'!F16) -> 288 | I14: =IF('Kit report'!X16<0,"0",'Kit report'!X16) -> 500 | J14: =IF('Utility summery'!H18<0,"0",'Utility summery'!H18) -> 0 | K14: =IF('UTILITY REPORT 1'!H15<0,"0",'UTILITY REPORT 1'!H15) -> 111 | L14: ='Water-Meter'!K18 -> 2 | M14: ='Water-Meter'!H18 -> 0 | N14: ='Water-Meter'!Q18 -> 6 | O14: =K14*E14+H14*I14+#REF!*#REF!+J14*L14 -> #REF! | P14: ='Water-Meter'!E18 -> 86 | Q14: =IF('Water-Meter'!U18<0,"0",'Water-Meter'!U18) -> 0 | R14: =IF('Water-Meter'!X18<0,"0",'Water-Meter'!X18) -> 0 | S14: =IF('Water-Meter'!AA18<0,"0",'Water-Meter'!AA18) -> 39 | T14: =IF('Water-Meter'!AD18<0,"0",'Water-Meter'!AD18) -> 14 | U14: =IF('Water-Meter'!AG18<0,"0",'Water-Meter'!AG18) -> 0 | V14: =IF('Water-Meter'!AJ18<0,"0",'Water-Meter'!AJ18) -> 33 | W14: ='Water-Meter'!AN18 -> 86 | X14: =Total!K14 -> 29
A15: Serengeti | B15: =B14+1 -> 14 | C15: 1 | D15: 2022 | E15: ='UTILITY REPORT 1'!I16 -> 288.08 | F15: ='UTILITY REPORT 1'!E16 -> 1511.92 | G15: ='UTILITY REPORT 1'!F16 -> 3795 | H15: =IF('Kit report'!F17<0,"0",'Kit report'!F17) -> 276 | I15: =IF('Kit report'!X17<0,"0",'Kit report'!X17) -> 500 | J15: =IF('Utility summery'!H19<0,"0",'Utility summery'!H19) -> 43 | K15: =IF('UTILITY REPORT 1'!H16<0,"0",'UTILITY REPORT 1'!H16) -> 92 | L15: ='Water-Meter'!K19 -> 2 | M15: ='Water-Meter'!H19 -> 0 | N15: ='Water-Meter'!Q19 -> 8 | O15: =K15*E15+H15*I15+#REF!*#REF!+J15*L15 -> #REF! | P15: ='Water-Meter'!E19 -> 92 | Q15: =IF('Water-Meter'!U19<0,"0",'Water-Meter'!U19) -> 0 | R15: =IF('Water-Meter'!X19<0,"0",'Water-Meter'!X19) -> 0 | S15: =IF('Water-Meter'!AA19<0,"0",'Water-Meter'!AA19) -> 40 | T15: =IF('Water-Meter'!AD19<0,"0",'Water-Meter'!AD19) -> 18 | U15: =IF('Water-Meter'!AG19<0,"0",'Water-Meter'!AG19) -> 0 | V15: =IF('Water-Meter'!AJ19<0,"0",'Water-Meter'!AJ19) -> 33 | W15: ='Water-Meter'!AN19 -> 91 | X15: =Total!K15 -> 37
A16: Serengeti | B16: =B15+1 -> 15 | C16: 1 | D16: 2022 | E16: ='UTILITY REPORT 1'!I17 -> 0 | F16: ='UTILITY REPORT 1'!E17 -> 1442 | G16: ='UTILITY REPORT 1'!F17 -> 3648 | H16: =IF('Kit report'!F18<0,"0",'Kit report'!F18) -> 276 | I16: =IF('Kit report'!X18<0,"0",'Kit report'!X18) -> 580 | J16: =IF('Utility summery'!H20<0,"0",'Utility summery'!H20) -> 26 | K16: =IF('UTILITY REPORT 1'!H17<0,"0",'UTILITY REPORT 1'!H17) -> 58 | L16: ='Water-Meter'!K20 -> 2 | M16: ='Water-Meter'!H20 -> 0 | N16: ='Water-Meter'!Q20 -> 10 | O16: =K16*E16+H16*I16+#REF!*#REF!+J16*L16 -> #REF! | P16: ='Water-Meter'!E20 -> 102 | Q16: =IF('Water-Meter'!U20<0,"0",'Water-Meter'!U20) -> 0 | R16: =IF('Water-Meter'!X20<0,"0",'Water-Meter'!X20) -> 0 | S16: =IF('Water-Meter'!AA20<0,"0",'Water-Meter'!AA20) -> 39 | T16: =IF('Water-Meter'!AD20<0,"0",'Water-Meter'!AD20) -> 27 | U16: =IF('Water-Meter'!AG20<0,"0",'Water-Meter'!AG20) -> 0 | V16: =IF('Water-Meter'!AJ20<0,"0",'Water-Meter'!AJ20) -> 0 | W16: ='Water-Meter'!AN20 -> 66 | X16: =Total!K16 -> 31
... A18: Serengeti | B18: =B17+1 -> 17 | C18: 1 | D18: 2022 | E18: ='UTILITY REPORT 1'!I19 -> 0 | F18: ='UTILITY REPORT 1'!E19 -> 1220.47 | G18: ='UTILITY REPORT 1'!F19 -> 2977 | H18: =IF('Kit report'!F20<0,"0",'Kit report'!F20) -> 204 | I18: =IF('Kit report'!X20<0,"0",'Kit report'!X20) -> 600 | J18: =IF('Utility summery'!H22<0,"0",'Utility summery'!H22) -> 36 | K18: =IF('UTILITY REPORT 1'!H19<0,"0",'UTILITY REPORT 1'!H19) -> 78 | L18: ='Water-Meter'!K22 -> 2 | M18: ='Water-Meter'!H22 -> 0 | N18: ='Water-Meter'!Q22 -> 7 | O18: =K18*E18+H18*I18+#REF!*#REF!+J18*L18 -> #REF! | P18: ='Water-Meter'!E22 -> 68 | Q18: =IF('Water-Meter'!U22<0,"0",'Water-Meter'!U22) -> 0 | R18: =IF('Water-Meter'!X22<0,"0",'Water-Meter'!X22) -> 0 | S18: =IF('Water-Meter'!AA22<0,"0",'Water-Meter'!AA22) -> 36 | T18: =IF('Water-Meter'!AD22<0,"0",'Water-Meter'!AD22) -> 25 | U18: =IF('Water-Meter'!AG22<0,"0",'Water-Meter'!AG22) -> 0 | V18: =IF('Water-Meter'!AJ22<0,"0",'Water-Meter'!AJ22) -> 0 | W18: ='Water-Meter'!AN22 -> 61 | X18: =Total!K18 -> 15
A19: Serengeti | B19: =B18+1 -> 18 | C19: 1 | D19: 2022 | E19: ='UTILITY REPORT 1'!I20 -> 221.01 | F19: ='UTILITY REPORT 1'!E20 -> 1382.64 | G19: ='UTILITY REPORT 1'!F20 -> 3443 | H19: =IF('Kit report'!F21<0,"0",'Kit report'!F21) -> 276 | I19: =IF('Kit report'!X21<0,"0",'Kit report'!X21) -> 540 | J19: =IF('Utility summery'!H23<0,"0",'Utility summery'!H23) -> 0 | K19: =IF('UTILITY REPORT 1'!H20<0,"0",'UTILITY REPORT 1'!H20) -> 0 | L19: ='Water-Meter'!K23 -> 2 | M19: ='Water-Meter'!H23 -> 0 | N19: ='Water-Meter'!Q23 -> 8 | O19: =K19*E19+H19*I19+#REF!*#REF!+J19*L19 -> #REF! | P19: ='Water-Meter'!E23 -> 62 | Q19: =IF('Water-Meter'!U23<0,"0",'Water-Meter'!U23) -> 0 | R19: =IF('Water-Meter'!X23<0,"0",'Water-Meter'!X23) -> 0 | S19: =IF('Water-Meter'!AA23<0,"0",'Water-Meter'!AA23) -> 37 | T19: =IF('Water-Meter'!AD23<0,"0",'Water-Meter'!AD23) -> 26 | U19: =IF('Water-Meter'!AG27<0,"0",'Water-Meter'!AG27) -> 0 | V19: =IF('Water-Meter'!AJ23<0,"0",'Water-Meter'!AJ23) -> 0 | W19: ='Water-Meter'!AN23 -> 63 | X19: =Total!K19 -> 25
A20: Serengeti | B20: =B19+1 -> 19 | C20: 1 | D20: 2022 | E20: ='UTILITY REPORT 1'!I21 -> 127.84 | F20: ='UTILITY REPORT 1'!E21 -> 1252.71 | G20: ='UTILITY REPORT 1'!F21 -> 3010 | H20: =IF('Kit report'!F22<0,"0",'Kit report'!F22) -> 192 | I20: =IF('Kit report'!X22<0,"0",'Kit report'!X22) -> 520 | J20: =IF('Utility summery'!H24<0,"0",'Utility summery'!H24) -> 1 | K20: =IF('UTILITY REPORT 1'!H21<0,"0",'UTILITY REPORT 1'!H21) -> 144 | L20: ='Water-Meter'!K24 -> 2 | M20: ='Water-Meter'!H24 -> 0 | N20: ='Water-Meter'!Q24 -> 6 | O20: =K20*E20+H20*I20+#REF!*#REF!+J20*L20 -> #REF! | P20: ='Water-Meter'!E24 -> 70 | Q20: =IF('Water-Meter'!U24<0,"0",'Water-Meter'!U24) -> 0 | R20: =IF('Water-Meter'!X24<0,"0",'Water-Meter'!X24) -> 0 | S20: =IF('Water-Meter'!AA24<0,"0",'Water-Meter'!AA24) -> 39 | T20: =IF('Water-Meter'!AD24<0,"0",'Water-Meter'!AD24) -> 13 | U20: =IF('Water-Meter'!AG24<0,"0",'Water-Meter'!AG24) -> 0 | V20: =IF('Water-Meter'!AJ24<0,"0",'Water-Meter'!AJ24) -> 0 | W20: ='Water-Meter'!AN24 -> 52 | X20: =Total!K20 -> 28
A21: Serengeti | B21: =B20+1 -> 20 | C21: 1 | D21: 2022 | E21: ='UTILITY REPORT 1'!I22 -> 238.02 | F21: ='UTILITY REPORT 1'!E22 -> 1370.45 | G21: ='UTILITY REPORT 1'!F22 -> 3323 | H21: =IF('Kit report'!F23<0,"0",'Kit report'!F23) -> 240 | I21: =IF('Kit report'!X23<0,"0",'Kit report'!X23) -> 500 | J21: =IF('Utility summery'!H25<0,"0",'Utility summery'!H25) -> 0 | K21: =IF('UTILITY REPORT 1'!H22<0,"0",'UTILITY REPORT 1'!H22) -> 45 | L21: ='Water-Meter'!K25 -> 2 | M21: ='Water-Meter'!H25 -> 0 | N21: ='Water-Meter'!Q25 -> 7 | O21: =K21*E21+H21*I21+#REF!*#REF!+J21*L21 -> #REF! | P21: ='Water-Meter'!E25 -> 88 | Q21: =IF('Water-Meter'!U25<0,"0",'Water-Meter'!U25) -> 80 | R21: =IF('Water-Meter'!X25<0,"0",'Water-Meter'!X25) -> 0 | S21: =IF('Water-Meter'!AA25<0,"0",'Water-Meter'!AA25) -> 39 | T21: =IF('Water-Meter'!AD25<0,"0",'Water-Meter'!AD25) -> 14 | U21: =IF('Water-Meter'!AG25<0,"0",'Water-Meter'!AG25) -> 0 | V21: =IF('Water-Meter'!AJ25<0,"0",'Water-Meter'!AJ25) -> 0 | W21: ='Water-Meter'!AN25 -> 133 | X21: =Total!K21 -> 29
A22: Serengeti | B22: =B21+1 -> 21 | C22: 1 | D22: 2022 | E22: ='UTILITY REPORT 1'!I23 -> 15 | F22: ='UTILITY REPORT 1'!E23 -> 1280.31 | G22: ='UTILITY REPORT 1'!F23 -> 3113 | H22: =IF('Kit report'!F24<0,"0",'Kit report'!F24) -> 228 | I22: =IF('Kit report'!X24<0,"0",'Kit report'!X24) -> 520 | J22: =IF('Utility summery'!H26<0,"0",'Utility summery'!H26) -> 30 | K22: =IF('UTILITY REPORT 1'!H23<0,"0",'UTILITY REPORT 1'!H23) -> 139 | L22: ='Water-Meter'!K26 -> 2 | M22: ='Water-Meter'!H26 -> 0 | N22: ='Water-Meter'!Q26 -> 8 | O22: =K22*E22+H22*I22+#REF!*#REF!+J22*L22 -> #REF! | P22: ='Water-Meter'!E26 -> 81 | Q22: =IF('Water-Meter'!U26<0,"0",'Water-Meter'!U26) -> 78 | R22: =IF('Water-Meter'!X26<0,"0",'Water-Meter'!X26) -> 0 | S22: =IF('Water-Meter'!AA26<0,"0",'Water-Meter'!AA26) -> 39 | T22: =IF('Water-Meter'!AD26<0,"0",'Water-Meter'!AD26) -> 13 | U22: =IF('Water-Meter'!AG26<0,"0",'Water-Meter'!AG26) -> 0 | V22: =IF('Water-Meter'!AJ26<0,"0",'Water-Meter'!AJ26) -> 8 | W22: ='Water-Meter'!AN26 -> 138 | X22: =Total!K22 -> 13
A23: Serengeti | B23: =B22+1 -> 22 | C23: 1 | D23: 2022 | E23: ='UTILITY REPORT 1'!I24 -> 264.82 | F23: ='UTILITY REPORT 1'!E24 -> 1286.26 | G23: ='UTILITY REPORT 1'!F24 -> 3124 | H23: =IF('Kit report'!F25<0,"0",'Kit report'!F25) -> 1183860 | I23: =IF('Kit report'!X25<0,"0",'Kit report'!X25) -> 460 | J23: =IF('Utility summery'!H27<0,"0",'Utility summery'!H27) -> 43 | K23: =IF('UTILITY REPORT 1'!H24<0,"0",'UTILITY REPORT 1'!H24) -> 100 | L23: ='Water-Meter'!K27 -> 2 | M23: ='Water-Meter'!H27 -> 0 | N23: ='Water-Meter'!Q27 -> 4 | O23: =K23*E23+H23*I23+#REF!*#REF!+J23*L23 -> #REF! | P23: ='Water-Meter'!E27 -> 71 | Q23: =IF('Water-Meter'!U27<0,"0",'Water-Meter'!U27) -> 80 | R23: =IF('Water-Meter'!X27<0,"0",'Water-Meter'!X27) -> 0 | S23: =IF('Water-Meter'!AA27<0,"0",'Water-Meter'!AA27) -> 37 | T23: =IF('Water-Meter'!AD27<0,"0",'Water-Meter'!AD27) -> 14 | U23: =IF('Water-Meter'!AG27<0,"0",'Water-Meter'!AG27) -> 0 | V23: =IF('Water-Meter'!AJ27<0,"0",'Water-Meter'!AJ27) -> 0 | W23: ='Water-Meter'!AN27 -> 131 | X23: =Total!K23 -> 11
A24: Serengeti | B24: =B23+1 -> 23 | C24: 1 | D24: 2022 | E24: ='UTILITY REPORT 1'!I25 -> 253.24 | F24: ='UTILITY REPORT 1'!E25 -> 1199.28 | G24: ='UTILITY REPORT 1'!F25 -> 2797 | H24: =IF('Kit report'!F26<0,"0",'Kit report'!F26) -> 204 | I24: =IF('Kit report'!X26<0,"0",'Kit report'!X26) -> 400 | J24: =IF('Utility summery'!H28<0,"0",'Utility summery'!H28) -> 93 | K24: =IF('UTILITY REPORT 1'!H25<0,"0",'UTILITY REPORT 1'!H25) -> 74 | L24: ='Water-Meter'!K28 -> 2 | M24: ='Water-Meter'!H28 -> 0 | N24: ='Water-Meter'!Q28 -> 3 | O24: =K24*E24+H24*I24+#REF!*#REF!+J24*L24 -> #REF! | P24: ='Water-Meter'!E28 -> 62 | Q24: =IF('Water-Meter'!U28<0,"0",'Water-Meter'!U28) -> 34 | R24: =IF('Water-Meter'!X28<0,"0",'Water-Meter'!X28) -> 0 | S24: =IF('Water-Meter'!AA28<0,"0",'Water-Meter'!AA28) -> 39 | T24: =IF('Water-Meter'!AD28<0,"0",'Water-Meter'!AD28) -> 18 | U24: =IF('Water-Meter'!AG28<0,"0",'Water-Meter'!AG28) -> 0 | V24: =IF('Water-Meter'!AJ28<0,"0",'Water-Meter'!AJ28) -> 0 | W24: ='Water-Meter'!AN28 -> 91 | X24: =Total!K24 -> 5
A25: Serengeti | B25: =B24+1 -> 24 | C25: 1 | D25: 2022 | E25: ='UTILITY REPORT 1'!I26 -> 237.04 | F25: ='UTILITY REPORT 1'!E26 -> 1340.81 | G25: ='UTILITY REPORT 1'!F26 -> 3295 | H25: =IF('Kit report'!F27<0,"0",'Kit report'!F27) -> 240 | I25: =IF('Kit report'!X27<0,"0",'Kit report'!X27) -> 480 | J25: =IF('Utility summery'!H29<0,"0",'Utility summery'!H29) -> 61 | K25: =IF('UTILITY REPORT 1'!H26<0,"0",'UTILITY REPORT 1'!H26) -> 17 | L25: ='Water-Meter'!K29 -> 3 | M25: ='Water-Meter'!H29 -> 0 | N25: ='Water-Meter'!Q29 -> 9 | O25: =K25*E25+H25*I25+#REF!*#REF!+J25*L25 -> #REF! | P25: ='Water-Meter'!E29 -> 75 | Q25: =IF('Water-Meter'!U29<0,"0",'Water-Meter'!U29) -> 0 | R25: =IF('Water-Meter'!X29<0,"0",'Water-Meter'!X29) -> 0 | S25: =IF('Water-Meter'!AA29<0,"0",'Water-Meter'!AA29) -> 39 | T25: =IF('Water-Meter'!AD29<0,"0",'Water-Meter'!AD29) -> 16 | U25: =IF('Water-Meter'!AG29<0,"0",'Water-Meter'!AG29) -> 0 | V25: =IF('Water-Meter'!AJ29<0,"0",'Water-Meter'!AJ29) -> 0 | W25: ='Water-Meter'!AN29 -> 55 | X25: =Total!K25 -> 15
A26: Serengeti | B26: =B25+1 -> 25 | C26: 1 | D26: 2022 | E26: ='UTILITY REPORT 1'!I27 -> 118.03 | F26: ='UTILITY REPORT 1'!E27 -> 1255.47 | G26: ='UTILITY REPORT 1'!F27 -> 3205 | H26: =IF('Kit report'!F28<0,"0",'Kit report'!F28) -> 264 | I26: =IF('Kit report'!X28<0,"0",'Kit report'!X28) -> 7000 | J26: =IF('Utility summery'!H30<0,"0",'Utility summery'!H30) -> 65 | K26: =IF('UTILITY REPORT 1'!H27<0,"0",'UTILITY REPORT 1'!H27) -> 133 | L26: ='Water-Meter'!K30 -> 2 | M26: ='Water-Meter'!H30 -> 0 | N26: ='Water-Meter'!Q30 -> 7 | O26: =K26*E26+H26*I26+#REF!*#REF!+J26*L26 -> #REF! | P26: ='Water-Meter'!E30 -> 160 | Q26: =IF('Water-Meter'!U30<0,"0",'Water-Meter'!U30) -> 0 | R26: =IF('Water-Meter'!X30<0,"0",'Water-Meter'!X30) -> 0 | S26: =IF('Water-Meter'!AA30<0,"0",'Water-Meter'!AA30) -> 36 | T26: =IF('Water-Meter'!AD30<0,"0",'Water-Meter'!AD30) -> 17 | U26: =IF('Water-Meter'!AG30<0,"0",'Water-Meter'!AG30) -> 0 | V26: =IF('Water-Meter'!AJ30<0,"0",'Water-Meter'!AJ30) -> 0 | W26: ='Water-Meter'!AN30 -> 53 | X26: =Total!K26 -> 23
A27: Serengeti | B27: =B26+1 -> 26 | C27: 1 | D27: 2022 | E27: ='UTILITY REPORT 1'!I28 -> 73.37 | F27: ='UTILITY REPORT 1'!E28 -> 1351.98 | G27: ='UTILITY REPORT 1'!F28 -> 3575 | H27: =IF('Kit report'!F29<0,"0",'Kit report'!F29) -> 264 | I27: =IF('Kit report'!X29<0,"0",'Kit report'!X29) -> 480 | J27: =IF('Utility summery'!H31<0,"0",'Utility summery'!H31) -> 67 | K27: =IF('UTILITY REPORT 1'!H28<0,"0",'UTILITY REPORT 1'!H28) -> 12 | L27: ='Water-Meter'!K31 -> 2 | M27: ='Water-Meter'!H31 -> 0 | N27: ='Water-Meter'!Q31 -> 5 | O27: =K27*E27+H27*I27+#REF!*#REF!+J27*L27 -> #REF! | P27: ='Water-Meter'!E31 -> 66 | Q27: =IF('Water-Meter'!U31<0,"0",'Water-Meter'!U31) -> 71 | R27: =IF('Water-Meter'!X31<0,"0",'Water-Meter'!X31) -> 0 | S27: =IF('Water-Meter'!AA31<0,"0",'Water-Meter'!AA31) -> 36 | T27: =IF('Water-Meter'!AD31<0,"0",'Water-Meter'!AD31) -> 16 | U27: =IF('Water-Meter'!AG31<0,"0",'Water-Meter'!AG31) -> 0 | V27: =IF('Water-Meter'!AJ31<0,"0",'Water-Meter'!AJ31) -> 0 | W27: ='Water-Meter'!AN31 -> 123 | X27: =Total!K27 -> 24
A28: Serengeti | B28: =B27+1 -> 27 | C28: 1 | D28: 2022 | E28: ='UTILITY REPORT 1'!I29 -> 353.88 | F28: ='UTILITY REPORT 1'!E29 -> 1411.45 | G28: ='UTILITY REPORT 1'!F29 -> 3610 | H28: =IF('Kit report'!F30<0,"0",'Kit report'!F30) -> 228 | I28: =IF('Kit report'!X30<0,"0",'Kit report'!X30) -> 520 | J28: =IF('Utility summery'!H32<0,"0",'Utility summery'!H32) -> 76 | K28: =IF('UTILITY REPORT 1'!H29<0,"0",'UTILITY REPORT 1'!H29) -> 184 | L28: ='Water-Meter'!K32 -> 2 | M28: ='Water-Meter'!H32 -> 0 | N28: ='Water-Meter'!Q32 -> 6 | O28: =K28*E28+H28*I28+#REF!*#REF!+J28*L28 -> #REF! | P28: ='Water-Meter'!E32 -> 75 | Q28: =IF('Water-Meter'!U32<0,"0",'Water-Meter'!U32) -> 69 | R28: =IF('Water-Meter'!X32<0,"0",'Water-Meter'!X32) -> 0 | S28: =IF('Water-Meter'!AA32<0,"0",'Water-Meter'!AA32) -> 42 | T28: =IF('Water-Meter'!AD32<0,"0",'Water-Meter'!AD32) -> 17 | U28: =IF('Water-Meter'!AG32<0,"0",'Water-Meter'!AG32) -> 0 | V28: =IF('Water-Meter'!AJ32<0,"0",'Water-Meter'!AJ32) -> 49 | W28: ='Water-Meter'!AN32 -> 177 | X28: =Total!K28 -> 22
A29: Serengeti | B29: =B28+1 -> 28 | C29: 1 | D29: 2022 | E29: ='UTILITY REPORT 1'!I30 -> 0 | F29: ='UTILITY REPORT 1'!E30 -> 1429.2 | G29: ='UTILITY REPORT 1'!F30 -> 3593 | H29: =IF('Kit report'!F31<0,"0",'Kit report'!F31) -> 264 | I29: =IF('Kit report'!X31<0,"0",'Kit report'!X31) -> 480 | J29: =IF('Utility summery'!H33<0,"0",'Utility summery'!H33) -> 61 | K29: =IF('UTILITY REPORT 1'!H30<0,"0",'UTILITY REPORT 1'!H30) -> 66 | L29: ='Water-Meter'!K33 -> 2 | M29: ='Water-Meter'!H33 -> 0 | N29: ='Water-Meter'!Q33 -> 5 | O29: =K29*E29+H29*I29+#REF!*#REF!+J29*L29 -> #REF! | P29: ='Water-Meter'!E33 -> 64 | Q29: =IF('Water-Meter'!U33<0,"0",'Water-Meter'!U33) -> 69 | R29: =IF('Water-Meter'!X33<0,"0",'Water-Meter'!X33) -> 0 | S29: =IF('Water-Meter'!AA33<0,"0",'Water-Meter'!AA33) -> 37 | T29: =IF('Water-Meter'!AD33<0,"0",'Water-Meter'!AD33) -> 15 | U29: =IF('Water-Meter'!AG33<0,"0",'Water-Meter'!AG33) -> 0 | V29: =IF('Water-Meter'!AJ33<0,"0",'Water-Meter'!AJ33) -> 38 | W29: ='Water-Meter'!AN33 -> 159 | X29: =Total!K29 -> 18
A30: Serengeti | B30: =B29+1 -> 29 | C30: 1 | D30: 2022 | E30: ='UTILITY REPORT 1'!I31 -> 48.59 | F30: ='UTILITY REPORT 1'!E31 -> 1414.19 | G30: ='UTILITY REPORT 1'!F31 -> 3589 | H30: =IF('Kit report'!F32<0,"0",'Kit report'!F32) -> 264 | I30: =IF('Kit report'!X32<0,"0",'Kit report'!X32) -> 560 | J30: =IF('Utility summery'!H34<0,"0",'Utility summery'!H34) -> 67 | K30: =IF('UTILITY REPORT 1'!H31<0,"0",'UTILITY REPORT 1'!H31) -> 135 | L30: ='Water-Meter'!K34 -> 6 | M30: ='Water-Meter'!H34 -> 0 | N30: ='Water-Meter'!Q34 -> 6 | O30: =K30*E30+H30*I30+#REF!*#REF!+J30*L30 -> #REF! | P30: ='Water-Meter'!E34 -> 80 | Q30: =IF('Water-Meter'!U34<0,"0",'Water-Meter'!U34) -> 68 | R30: =IF('Water-Meter'!X34<0,"0",'Water-Meter'!X34) -> 0 | S30: =IF('Water-Meter'!AA34<0,"0",'Water-Meter'!AA34) -> 36 | T30: =IF('Water-Meter'!AD34<0,"0",'Water-Meter'!AD34) -> 15 | U30: =IF('Water-Meter'!AG34<0,"0",'Water-Meter'!AG34) -> 0 | V30: =IF('Water-Meter'!AJ34<0,"0",'Water-Meter'!AJ34) -> 36 | W30: ='Water-Meter'!AN34 -> 155 | X30: =Total!K30 -> 20
A31: Serengeti | B31: 30 | C31: 1 | D31: 2022 | E31: ='UTILITY REPORT 1'!I32 -> 96 | F31: ='UTILITY REPORT 1'!E32 -> 1346.87 | G31: ='UTILITY REPORT 1'!F32 -> 3575 | H31: =IF('Kit report'!F33<0,"0",'Kit report'!F33) -> 216 | I31: =IF('Kit report'!X33<0,"0",'Kit report'!X33) -> 400 | J31: =IF('Utility summery'!H35<0,"0",'Utility summery'!H35) -> 68 | K31: =IF('UTILITY REPORT 1'!H32<0,"0",'UTILITY REPORT 1'!H32) -> 11 | L31: ='Water-Meter'!K35 -> 3 | M31: ='Water-Meter'!H35 -> 0 | N31: ='Water-Meter'!Q35 -> 8 | O31: =K31*E31+H31*I31+#REF!*#REF!+J31*L31 -> #REF! | P31: ='Water-Meter'!E35 -> 110 | Q31: =IF('Water-Meter'!U35<0,"0",'Water-Meter'!U35) -> 67 | R31: =IF('Water-Meter'!X35<0,"0",'Water-Meter'!X35) -> 0 | S31: =IF('Water-Meter'!AA35<0,"0",'Water-Meter'!AA35) -> 36 | T31: =IF('Water-Meter'!AD35<0,"0",'Water-Meter'!AD35) -> 14 | U31: =IF('Water-Meter'!AG35<0,"0",'Water-Meter'!AG35) -> 0 | V31: =IF('Water-Meter'!AJ35<0,"0",'Water-Meter'!AJ35) -> 36 | W31: ='Water-Meter'!AN35 -> 153 | X31: =Total!K31 -> 18
A32: Serengeti | B32: 31 | C32: 1 | D32: 2022 | E32: ='UTILITY REPORT 1'!I33 -> 511.7 | F32: ='UTILITY REPORT 1'!E33 -> 1283.56 | G32: ='UTILITY REPORT 1'!F33 -> 3272 | H32: =IF('Kit report'!F34<0,"0",'Kit report'!F34) -> 180 | I32: =IF('Kit report'!X34<0,"0",'Kit report'!X34) -> 460 | J32: =IF('Utility summery'!H36<0,"0",'Utility summery'!H36) -> 66 | K32: =IF('UTILITY REPORT 1'!H33<0,"0",'UTILITY REPORT 1'!H33) -> 135 | L32: ='Water-Meter'!K36 -> 3 | M32: ='Water-Meter'!H36 -> 0 | N32: ='Water-Meter'!Q36 -> 9 | P32: ='Water-Meter'!E36 -> 104 | Q32: =IF('Water-Meter'!U36<0,"0",'Water-Meter'!U36) -> 63 | R32: =IF('Water-Meter'!X36<0,"0",'Water-Meter'!X36) -> 0 | S32: =IF('Water-Meter'!AA36<0,"0",'Water-Meter'!AA36) -> 36 | T32: =IF('Water-Meter'!AD36<0,"0",'Water-Meter'!AD36) -> 15 | U32: =IF('Water-Meter'!AG36<0,"0",'Water-Meter'!AG36) -> 0 | V32: =IF('Water-Meter'!AJ36<0,"0",'Water-Meter'!AJ36) -> 37 | W32: ='Water-Meter'!AN36 -> 151 | X32: =Total!K32 -> 12

Sheet Energy Graph
A1: Date | B1: Usage KW | C1: Occ % | D1: Total Occ | E1: Guest Occ
A2: =Gen!B11 -> 44562 | B2: ='Summery Report'!F5 -> 4734 | C2: ='Summery Report'!C5 -> 0.4156 | D2: 34 | E2: =D2 -> 34
A3: =Gen!B12 -> 44563 | B3: ='Summery Report'!F6 -> 4563 | C3: ='Summery Report'!C6 -> 0.53 | D3: 42 | E3: =D3 -> 42
A4: =Gen!B13 -> 44564 | B4: ='Summery Report'!F7 -> 4574 | C4: ='Summery Report'!C7 -> 0.36 | D4: 29 | E4: =D4 -> 29
A5: =Gen!B14 -> 44565 | B5: ='Summery Report'!F8 -> 4346 | C5: ='Summery Report'!C8 -> 0.35 | D5: 28 | E5: =D5 -> 28
A6: =Gen!B15 -> 44566 | B6: ='Summery Report'!F9 -> 3969 | C6: ='Summery Report'!C9 -> 0.26 | D6: 21 | E6: =D6 -> 21
A7: =Gen!B16 -> 44567 | B7: ='Summery Report'!F10 -> 4325 | C7: ='Summery Report'!C10 -> 0.31 | D7: 25 | E7: =D7 -> 25
A8: =Gen!B17 -> 44568 | B8: ='Summery Report'!F11 -> 4444 | C8: ='Summery Report'!C11 -> 0.2468 | D8: 20 | E8: =D8 -> 20
A9: =Gen!B18 -> 44569 | B9: ='Summery Report'!F12 -> 4291 | C9: ='Summery Report'!C12 -> 0.23 | D9: 19 | E9: =D9 -> 19
A10: =Gen!B19 -> 44570 | B10: ='Summery Report'!F13 -> 4336 | C10: ='Summery Report'!C13 -> 0.2078 | D10: 17 | E10: =D10 -> 17
A11: =Gen!B20 -> 44571 | B11: ='Summery Report'!F14 -> 4279 | C11: ='Summery Report'!C14 -> 0.17 | D11: 16 | E11: =D11 -> 16
A12: =Gen!B21 -> 44572 | B12: ='Summery Report'!F15 -> 3862 | C12: ='Summery Report'!C15 -> 0.1 | D12: 11 | E12: =D12 -> 11
A13: =Gen!B22 -> 44573 | B13: ='Summery Report'!F16 -> 3803 | C13: ='Summery Report'!C16 -> 0.0649 | D13: 8 | E13: =D13 -> 8
... A32: =Gen!B41 -> 44592 | B32: ='Summery Report'!F35 -> 3272 | C32: ='Summery Report'!C35 -> 0.05 | D32: 5 | E32: =D32 -> 5
A33: =Gen!B42 -> 0 | B33: 0

Sheet UTILITY REPORT 1
A1: UTILITY REPORT
A2: Date | B2: % | C2: Guest Rooms Occupied | D2: Diesel cost Per Liter ($) | E2: Diesel consumption (LT) | F2: Power production (KW) | G2: Water consumption (M3) | H2: RO prodution (M3) | I2: Transport Consupmtion (LT)
A3: =Gen!B11 -> 44562 | B3: =Gen!C11 -> 0.4156 | C3: ='Energy Graph'!E2 -> 34 | D3: 1 | E3: =Gen!T11 -> 1965.3 | F3: =Gen!U11 -> 4734 | G3: ='Water-Meter'!E6 -> 116 | H3: ='Utility report '!AC6 -> 102 | I3: =Gen!AK11 -> 320.11
A4: =Gen!B12 -> 44563 | B4: =Gen!C12 -> 0.53 | C4: ='Energy Graph'!E3 -> 42 | D4: 1 | E4: =Gen!T12 -> 1927.08 | F4: =Gen!U12 -> 4563 | G4: ='Water-Meter'!E7 -> 94 | H4: ='Utility report '!AC7 -> 64 | I4: =Gen!AK12 -> 237.31
A5: =Gen!B13 -> 44564 | B5: =Gen!C13 -> 0.36 | C5: ='Energy Graph'!E4 -> 29 | D5: 1 | E5: =Gen!T13 -> 1859.92 | F5: =Gen!U13 -> 4574 | G5: ='Water-Meter'!E8 -> 110 | H5: ='Utility report '!AC8 -> 105 | I5: =Gen!AK13 -> 231
A6: =Gen!B14 -> 44565 | B6: =Gen!C14 -> 0.35 | C6: ='Energy Graph'!E5 -> 28 | D6: 1 | E6: =Gen!T14 -> 1889.7 | F6: =Gen!U14 -> 4346 | G6: ='Water-Meter'!E9 -> 94 | H6: ='Utility report '!AC9 -> 147 | I6: =Gen!AK14 -> 247.48
A7: =Gen!B15 -> 44566 | B7: =Gen!C15 -> 0.26 | C7: ='Energy Graph'!E6 -> 21 | D7: 1 | E7: =Gen!T15 -> 1716.39 | F7: =Gen!U15 -> 3969 | G7: ='Water-Meter'!E10 -> 86 | H7: ='Utility report '!AC10 -> 0 | I7: =Gen!AK15 -> 110
A8: =Gen!B16 -> 44567 | B8: =Gen!C16 -> 0.31 | C8: ='Energy Graph'!E7 -> 25 | D8: 1 | E8: =Gen!T16 -> 1829.15 | F8: =Gen!U16 -> 4325 | G8: ='Water-Meter'!E11 -> 90 | H8: ='Utility report '!AC11 -> 148 | I8: =Gen!AK16 -> 299.04
A9: =Gen!B17 -> 44568 | B9: =Gen!C17 -> 0.2468 | C9: ='Energy Graph'!E8 -> 20 | D9: 1 | E9: =Gen!T17 -> 1866.35 | F9: =Gen!U17 -> 4444 | G9: ='Water-Meter'!E12 -> 92 | H9: ='Utility report '!AC12 -> -22473 | I9: =Gen!AK17 -> 133
A10: =Gen!B18 -> 44569 | B10: =Gen!C18 -> 0.23 | C10: ='Energy Graph'!E9 -> 19 | D10: 1 | E10: =Gen!T18 -> 1767.24 | F10: =Gen!U18 -> 4291 | G10: ='Water-Meter'!E13 -> 108 | H10: ='Utility report '!AC13 -> 22575 | I10: =Gen!AK18 -> 162.47
A11: =Gen!B19 -> 44570 | B11: =Gen!C19 -> 0.2078 | C11: ='Energy Graph'!E10 -> 17 | D11: 1 | E11: =Gen!T19 -> 1846.05 | F11: =Gen!U19 -> 4336 | G11: ='Water-Meter'!E14 -> 101 | H11: ='Utility report '!AC14 -> 128 | I11: =Gen!AK19 -> 109.74
A12: =Gen!B20 -> 44571 | B12: =Gen!C20 -> 0.17 | C12: ='Energy Graph'!E11 -> 16 | D12: 1 | E12: =Gen!T20 -> 1765.63 | F12: =Gen!U20 -> 4279 | G12: ='Water-Meter'!E15 -> 83 | H12: ='Utility report '!AC15 -> 77 | I12: =Gen!AK20 -> 79.83
A13: =Gen!B21 -> 44572 | B13: =Gen!C21 -> 0.1 | C13: ='Energy Graph'!E12 -> 11 | D13: 1 | E13: =Gen!T21 -> 1625.28 | F13: =Gen!U21 -> 3862 | G13: ='Water-Meter'!E16 -> 67 | H13: ='Utility report '!AC16 -> 114 | I13: =Gen!AK21 -> 386.46
A14: =Gen!B22 -> 44573 | B14: =Gen!C22 -> 0.0649 | C14: ='Energy Graph'!E13 -> 8 | D14: 1 | E14: =Gen!T22 -> 1599.77 | F14: =Gen!U22 -> 3803 | G14: ='Water-Meter'!E17 -> 133 | H14: ='Utility report '!AC17 -> 112 | I14: =Gen!AK22 -> 0
... A33: =Gen!B41 -> 44592 | B33: =Gen!C41 -> 0.05 | C33: ='Energy Graph'!E32 -> 5 | D33: 1 | E33: =Gen!T41 -> 1283.56 | F33: =Gen!U41 -> 3272 | G33: ='Water-Meter'!E36 -> 104 | H33: ='Utility report '!AC36 -> 135 | I33: =Gen!AK41 -> 511.7
B34: =Gen!C42 -> 0 | C34: ='Energy Graph'!E33 -> 0

Sheet Utility report 
A1: =A6 -> 44562
A2: Date | B2: Total occupancy | H2: Diesel balance LTS | I2: Diesel Deliveries | J2: Gen.Diesel consumption LTS | L2: Total Diesel consumption LTS | M2: Water Meter reading | N2: Water consumption m³ | O2: R.O WATER PRODUCTION LTRS + TIME | AA2: Total RO production | AB2: RO Meter reading | AD2: 0 | AE2: STP | AF2: GAS TANK A | AG2: GAS TANK B | AH2: GAS TANK C | AI2: Total Gas Tanks | AJ2: Kg /day | AK2: TOTAL GAS cons.
A3: Rate Tsh /$ | B3: 1640 | C3: Diesel cost / lits | D3: 2175 | F3: =SUM(D3/B3) -> 1.3262195 | H3: =Gen!D11 -> 39200.63 | K3: Transport consumption | M3: Balance | O3: PLANT NO 1 | S3: PLANT NO 2 | W3: PLANT NO 3 | AA3: /day | AB3: Balance | AD3: 0 | AE3: Production | AF3: Capacity | AG3: Capacity | AH3: Capacity | AI3: Kg | AJ3: /day | AK3: /day
B4: Rooms OCC | C4: % | D4: Guest Rooms Occ | F4: Electricity Production Cost /Room Occ by guest | G4: All Cost /Room Occ by guest | O4: Flow M3 | P4: Reading Hours Meter | Q4: Hrs | R4: total production M3 | S4: Flow M3 | T4: Reading Hours Meter | U4: Hrs | V4: total production M3 | W4: Flow M3 | X4: READING HOURS METER | Y4: Hrs | Z4: total production M3 | AA4: M3 | AC4: M3 | AE4: M3 | AF4: 2000 | AG4: 1000 | AH4: 1000 | AI4: #VALUE! | AJ4: Kg | AK4: M3
T5: 20528 | AB5: 21907 | AD5: 228878 | AF5: 0.85 | AG5: 0.85 | AH5: 0.85
A6: =Gen!B11 -> 44562 | B6: ='UTILITY REPORT 1'!C3 -> 34 | D6: =B6 -> 34 | E6: =SUM(F3) -> 1.3262195 | F6: =SUM(J6*E6)/D6 -> 184.65656 | G6: =SUM(L6*E6)/D6 -> 184.65656 | H6: =Gen!D11 -> 39200.63 | I6: =Gen!F11 -> 0 | J6: =Gen!U11 -> 4734 | K6: =Gen!AL11 -> 0 | L6: =SUM(J6:K6) -> 4734 | M6: ='Water-Meter'!K46 -> 452.068 | N6: ='Water-Meter'!E6 -> 116 | P6: 19044 | Q6: =SUM(P6-P5) -> 19044 | R6: =SUM(Q6*O6) -> 0 | S6: 6.7 | T6: 20544 | U6: =T6-T5 -> 16 | V6: =SUM(U6*S7) -> 107.2 | X6: 29498 | Y6: =X6-X5 -> 29498 | Z6: =Y6-Y5 -> 29498 | AA6: =Z6-Z5 -> 29498 | AB6: 22009 | AC6: =AB6-AB5 -> 102 | AD6: 228934 | AE6: =AD6-AD5 -> 56 | AF6: ='Lpg (2)'!B10*2000/85 -> 1176.4706 | AG6: ='Lpg (2)'!C10*1000/85 -> 0 | AH6: ='Lpg (2)'!D10*1000/85 -> 0 | AI6: =SUM(AF6*2000)+(AG6*1000)+(AH6*1000) -> 2352941.2 | AJ6: =SUM(AI5-AI6) -> -2352941.2
A7: =Gen!B12 -> 44563 | B7: ='UTILITY REPORT 1'!C4 -> 42 | D7: =B7 -> 42 | E7: =SUM(E6) -> 1.3262195 | F7: =SUM(J7*E7)/D7 -> 144.08428 | G7: =SUM(L7*E7)/D7 -> 144.08428 | H7: =Gen!D12 -> 36915.22 | I7: =Gen!F12 -> 0 | J7: =Gen!U12 -> 4563 | K7: =Gen!AL12 -> 0 | L7: =SUM(J7:K7) -> 4563 | M7: ='Water-Meter'!K47 -> 449.21462 | N7: ='Water-Meter'!E7 -> 94 | P7: 19044 | Q7: =SUM(P7-P6) -> 0 | R7: =SUM(Q7*O7) -> 0 | S7: 6.7 | T7: 20544 | U7: =T7-T6 -> 0 | V7: =SUM(U7*S8) -> 0 | X7: 29498 | Y7: =X7-X6 -> 0 | Z7: =Y7-Y6 -> -29498 | AA7: =Z7-Z6 -> -58996 | AB7: 22073 | AC7: =AB7-AB6 -> 64 | AD7: 228989 | AE7: =AD7-AD6 -> 55 | AF7: ='Lpg (2)'!B11*2000/85 -> 1058.8235 | AG7: ='Lpg (2)'!C11*1000/85 -> 0 | AH7: ='Lpg (2)'!D11*1000/85 -> 0 | AI7: =SUM(AF6*2000)+(AG7*1000)+(AH7*1000) -> 2352941.2 | AJ7: =SUM(AI6-AI7) -> 0
A8: =Gen!B13 -> 44564 | B8: ='UTILITY REPORT 1'!C5 -> 29 | D8: =B8 -> 29 | E8: =SUM(E7) -> 1.3262195 | F8: =SUM(J8*E8)/D8 -> 209.17683 | G8: =SUM(L8*E8)/D8 -> 209.17683 | H8: =Gen!D13 -> 34750.83 | I8: =Gen!F13 -> 0 | J8: =Gen!U13 -> 4574 | K8: =Gen!AL13 -> 0 | L8: =SUM(J8:K8) -> 4574 | M8: ='Water-Meter'!K48 -> 474.25283 | N8: ='Water-Meter'!E8 -> 110 | P8: 19044 | Q8: =SUM(P8-P7) -> 0 | R8: =SUM(Q8*O8) -> 0 | S8: 6.7 | T8: 20554 | U8: =T8-T7 -> 10 | V8: =SUM(U8*S9) -> 68 | X8: 29498 | Y8: =X8-X7 -> 0 | Z8: =Y8-Y7 -> 0 | AA8: =Z8-Z7 -> 29498 | AB8: 22178 | AC8: =AB8-AB7 -> 105 | AD8: 229045 | AE8: =AD8-AD7 -> 56 | AF8: ='Lpg (2)'!B12*2000/85 -> 964.70588 | AG8: ='Lpg (2)'!C12*1000/85 -> 0 | AH8: ='Lpg (2)'!D12*1000/85 -> 0 | AI8: =SUM(AF7*2000)+(AG8*1000)+(AH8*1000) -> 2117647.1 | AJ8: =SUM(AI7-AI8) -> 235294.12
A9: =Gen!B14 -> 44565 | B9: ='UTILITY REPORT 1'!C6 -> 28 | D9: =B9 -> 28 | E9: =SUM(E8) -> 1.3262195 | F9: =SUM(J9*E9)/D9 -> 205.84821 | G9: =SUM(L9*E9)/D9 -> 205.84821 | H9: =Gen!D14 -> 32659.91 | I9: =Gen!F14 -> 0 | J9: =Gen!U14 -> 4346 | K9: =Gen!AL14 -> 0 | L9: =SUM(J9:K9) -> 4346 | M9: ='Water-Meter'!K49 -> 536.57201 | N9: ='Water-Meter'!E9 -> 94 | P9: 19044 | Q9: =SUM(P9-P7) -> 0 | R9: =SUM(Q9*O9) -> 0 | S9: 6.8 | T9: 20595 | U9: =T9-T8 -> 41 | V9: =SUM(U9*S10) -> 278.8 | X9: 29498 | Y9: =X9-X8 -> 0 | Z9: =Y9-Y8 -> 0 | AA9: =Z9-Z8 -> 0 | AB9: 22325 | AC9: =AB9-AB8 -> 147 | AD9: 229104 | AE9: =AD9-AD8 -> 59 | AF9: ='Lpg (2)'!B13*2000/85 -> 941.17647 | AG9: ='Lpg (2)'!C13*1000/85 -> 0 | AH9: ='Lpg (2)'!D13*1000/85 -> 0 | AI9: =SUM(AF8*2000)+(AG9*1000)+(AH9*1000) -> 1929411.8 | AJ9: =SUM(AI8-AI9) -> 188235.29
A10: =Gen!B15 -> 44566 | B10: ='UTILITY REPORT 1'!C7 -> 21 | D10: =B10 -> 21 | E10: =SUM(E9) -> 1.3262195 | F10: =SUM(J10*E10)/D10 -> 250.65549 | G10: =SUM(L10*E10)/D10 -> 250.65549 | H10: =Gen!D15 -> 30522.73 | I10: =Gen!F15 -> 0 | J10: =Gen!U15 -> 3969 | K10: =Gen!AL15 -> 0 | L10: =SUM(J10:K10) -> 3969 | M10: ='Water-Meter'!K50 -> 525.16541 | N10: ='Water-Meter'!E10 -> 86 | P10: 19044 | Q10: =SUM(P10-P9) -> 0 | R10: =SUM(Q10*O10) -> 0 | S10: 6.8 | T10: 20595 | U10: =T10-T9 -> 0 | V10: =SUM(U10*S11) -> 0 | X10: 29498 | Y10: =X10-X9 -> 0 | Z10: =SUM(Y10*W10) -> 0 | AA10: =Z10-Z9 -> 0 | AB10: 22325 | AC10: =AB10-AB9 -> 0 | AD10: 229153 | AE10: =AD10-AD9 -> 49 | AF10: ='Lpg (2)'!B14*2000/85 -> 894.11765 | AG10: ='Lpg (2)'!C14*1000/85 -> 0 | AH10: ='Lpg (2)'!D14*1000/85 -> 0 | AI10: =SUM(AF9*2000)+(AG10*1000)+(AH10*1000) -> 1882352.9 | AJ10: =SUM(AI9-AI10) -> 47058.824
A11: =Gen!B16 -> 44567 | B11: ='UTILITY REPORT 1'!C8 -> 25 | D11: =B11 -> 25 | E11: =SUM(E10) -> 1.3262195 | F11: =SUM(J11*E11)/D11 -> 229.43598 | G11: =SUM(L11*E11)/D11 -> 229.43598 | H11: =Gen!D16 -> 28696.34 | I11: =Gen!F16 -> 0 | J11: =Gen!U16 -> 4325 | K11: =Gen!AL16 -> 0 | L11: =SUM(J11:K11) -> 4325 | M11: ='Water-Meter'!K51 -> 534.09828 | N11: ='Water-Meter'!E11 -> 90 | P11: 19044 | Q11: =SUM(P11-P10) -> 0 | R11: =SUM(Q11*O11) -> 0 | S11: 6.8 | T11: 20618 | U11: =T11-T10 -> 23 | V11: =SUM(U11*S12) -> 156.4 | X11: 29498 | Y11: =X11-X10 -> 0 | Z11: =SUM(Y11*W11) -> 0 | AA11: =SUM(Z11*X13) -> 0 | AB11: 22473 | AC11: =AB11-AB10 -> 148 | AD11: 229207 | AE11: =AD11-AD10 -> 54 | AF11: ='Lpg (2)'!B15*2000/85 -> 1694.1176 | AG11: ='Lpg (2)'!C15*1000/85 -> 1000 | AH11: ='Lpg (2)'!D15*1000/85 -> 1000 | AI11: =SUM(AF10*2000)+(AG11*1000)+(AH11*1000) -> 3788235.3 | AJ11: =SUM(AI10-AI11) -> -1905882.4
A12: =Gen!B17 -> 44568 | B12: ='UTILITY REPORT 1'!C9 -> 20 | D12: =B12 -> 20 | E12: =SUM(E11) -> 1.3262195 | F12: =SUM(J12*E12)/D12 -> 294.68598 | G12: =SUM(L12*E12)/D12 -> 294.68598 | H12: =Gen!D17 -> 26568.15 | I12: =Gen!F17 -> 18000 | J12: =Gen!U17 -> 4444 | K12: =Gen!AL17 -> 0 | L12: =SUM(J12:K12) -> 4444 | M12: ='Water-Meter'!K52 -> 568.9489 | N12: ='Water-Meter'!E12 -> 92 | P12: 19044 | Q12: =SUM(P12-P11) -> 0 | R12: =SUM(Q12*O12) -> 0 | S12: 6.8 | T12: 20634 | U12: =T12-T11 -> 16 | V12: =SUM(U12*S12) -> 108.8 | X12: 29498 | Y12: =X12-X11 -> 0 | Z12: =SUM(Y12*W12) -> 0 | AA12: =SUM(Z12*X14) -> 0 | AC12: =AB12-AB11 -> -22473 | AE12: =AD12-AD11 -> -229207 | AF12: ='Lpg (2)'!B16*2000/85 -> 1647.0588 | AG12: ='Lpg (2)'!C16*1000/85 -> 1000 | AH12: ='Lpg (2)'!D16*1000/85 -> 1000 | AI12: =SUM(AF11*2000)+(AG12*1000)+(AH12*1000) -> 5388235.3 | AJ12: =SUM(AI11-AI12) -> -1600000
A13: =Gen!B18 -> 44569 | B13: ='UTILITY REPORT 1'!C10 -> 19 | D13: =B13 -> 19 | E13: =SUM(E12) -> 1.3262195 | F13: =SUM(J13*E13)/D13 -> 299.51621 | G13: =SUM(L13*E13)/D13 -> 299.51621 | H13: =Gen!D18 -> 24568.8 | I13: =Gen!F18 -> 0 | J13: =Gen!U18 -> 4291 | K13: =Gen!AL18 -> 0 | L13: =SUM(J13:K13) -> 4291 | M13: ='Water-Meter'!K53 -> 571.96529 | N13: ='Water-Meter'!E13 -> 108 | P13: 19044 | Q13: =SUM(P13-P12) -> 0 | R13: =SUM(Q13*O13) -> 0 | S13: 6.8 | T13: 20634 | U13: =T13-T12 -> 0 | V13: =SUM(U13*S13) -> 0 | X13: 29498 | Y13: =X13-X12 -> 0 | Z13: =SUM(Y13*W13) -> 0 | AA13: =SUM(Z13*X15) -> 0 | AB13: 22575 | AC13: =AB13-AB12 -> 22575 | AD13: 229265 | AE13: =AD13-AD12 -> 229265 | AF13: ='Lpg (2)'!B17*2000/85 -> 1647.0588 | AG13: ='Lpg (2)'!C17*1000/85 -> 1000 | AH13: ='Lpg (2)'!D17*1000/85 -> 1000 | AI13: =SUM(AF12*2000)+(AG13*1000)+(AH13*1000) -> 5294117.6 | AJ13: =SUM(AI12-AI13) -> 94117.647
A14: =Gen!B19 -> 44570 | B14: ='UTILITY REPORT 1'!C11 -> 17 | D14: =B14 -> 17 | E14: =SUM(E13) -> 1.3262195 | F14: =SUM(J14*E14)/D14 -> 338.26399 | G14: =SUM(L14*E14)/D14 -> 338.26399 | H14: =Gen!D19 -> 40639.09 | I14: =Gen!F19 -> 0 | J14: =Gen!U19 -> 4336 | K14: =Gen!AL19 -> 0 | L14: =SUM(J14:K14) -> 4336 | M14: ='Water-Meter'!K54 -> 575.97264 | N14: ='Water-Meter'!E14 -> 101 | P14: 19044 | Q14: =SUM(P14-P13) -> 0 | R14: =SUM(Q14*O14) -> 0 | S14: 6.8 | T14: 20655 | U14: =T14-T13 -> 21 | V14: =SUM(U14*S14) -> 142.8 | X14: 29498 | Y14: =X14-X13 -> 0 | Z14: =SUM(Y14*W14) -> 0 | AA14: =SUM(Z14*X16) -> 0 | AB14: 22703 | AC14: =AB14-AB13 -> 128 | AD14: 229321 | AE14: =AD14-AD13 -> 56 | AF14: ='Lpg (2)'!B18*2000/85 -> 1529.4118 | AG14: ='Lpg (2)'!C18*1000/85 -> 1000 | AH14: ='Lpg (2)'!D18*1000/85 -> 1000 | AI14: =SUM(AF13*2000)+(AG14*1000)+(AH14*1000) -> 5294117.6 | AJ14: =SUM(AI13-AI14) -> 0
A15: =Gen!B20 -> 44571 | B15: ='UTILITY REPORT 1'!C12 -> 16 | D15: =B15 -> 16 | E15: =SUM(E14) -> 1.3262195 | F15: =SUM(J15*E15)/D15 -> 354.68083 | G15: =SUM(L15*E15)/D15 -> 354.68083 | H15: =Gen!D20 -> 38683.3 | I15: =Gen!F20 -> 0 | J15: =Gen!U20 -> 4279 | K15: =Gen!AL20 -> 0 | L15: =SUM(J15:K15) -> 4279 | M15: ='Water-Meter'!K55 -> 615.62824 | N15: ='Water-Meter'!E15 -> 83 | P15: 19044 | Q15: =SUM(P15-P14) -> 0 | R15: =SUM(Q15*O15) -> 0 | S15: 6.8 | T15: 20667 | U15: =T15-T14 -> 12 | V15: =SUM(U15*S15) -> 81.6 | X15: 29498 | Y15: =X15-X14 -> 0 | Z15: =SUM(Y15*W15) -> 0 | AA15: =SUM(Z15*X17) -> 0 | AB15: 22780 | AC15: =AB15-AB14 -> 77 | AD15: 229324 | AE15: =AD15-AD14 -> 3 | AF15: ='Lpg (2)'!B19*2000/85 -> 1458.8235 | AG15: ='Lpg (2)'!C19*1000/85 -> 1000 | AH15: ='Lpg (2)'!D19*1000/85 -> 1000 | AI15: =SUM(AF15*2000)+(AG15*1000)+(AH15*1000) -> 4917647.1 | AJ15: =SUM(AI14-AI15) -> 376470.59
A16: =Gen!B21 -> 44572 | B16: ='UTILITY REPORT 1'!C13 -> 11 | D16: =B16 -> 11 | E16: =SUM(E15) -> 1.3262195 | F16: =SUM(J16*E16)/D16 -> 465.62361 | G16: =SUM(L16*E16)/D16 -> 465.62361 | H16: =Gen!D21 -> 36837.84 | I16: =Gen!F21 -> 0 | J16: =Gen!U21 -> 3862 | K16: =Gen!AL21 -> 0 | L16: =SUM(J16:K16) -> 3862 | M16: ='Water-Meter'!K56 -> 590.0892 | N16: ='Water-Meter'!E16 -> 67 | P16: 19044 | Q16: =SUM(P16-P15) -> 0 | R16: =SUM(Q16*O16) -> 0 | S16: 6.8 | T16: 20685 | U16: =T16-T15 -> 18 | V16: =SUM(U16*S16) -> 122.4 | X16: 29498 | Y16: =X16-X15 -> 0 | Z16: =SUM(Y16*W16) -> 0 | AA16: =SUM(Z16*X18) -> 0 | AB16: 22894 | AC16: =AB16-AB15 -> 114 | AD16: 229327 | AE16: =AD16-AD15 -> 3 | AF16: ='Lpg (2)'!B20*2000/85 -> 1411.7647 | AG16: ='Lpg (2)'!C20*1000/85 -> 682.35294 | AH16: ='Lpg (2)'!D20*1000/85 -> 1000 | AI16: =SUM(AF16*2000)+(AG16*1000)+(AH16*1000) -> 4505882.4 | AJ16: =SUM(AI15-AI16) -> 411764.71
A17: =Gen!B22 -> 44573 | B17: ='UTILITY REPORT 1'!C14 -> 8 | D17: =B17 -> 8 | E17: =SUM(E16) -> 1.3262195 | F17: =SUM(J17*E17)/D17 -> 630.4516 | G17: =SUM(L17*E17)/D17 -> 630.4516 | H17: =Gen!D22 -> 34826.1 | I17: =Gen!F22 -> 0 | J17: =Gen!U22 -> 3803 | K17: =Gen!AL22 -> 0 | L17: =SUM(J17:K17) -> 3803 | M17: ='Water-Meter'!K57 -> 581.09751 | N17: ='Water-Meter'!E17 -> 133 | P17: 19044 | Q17: =SUM(P17-P16) -> 0 | R17: =SUM(Q17*O17) -> 0 | S17: 6.8 | T17: 20702 | U17: =T17-T16 -> 17 | V17: =SUM(U17*S17) -> 115.6 | X17: 29498 | Y17: =X17-X16 -> 0 | Z17: =SUM(Y17*W17) -> 0 | AA17: =SUM(Z17*X19) -> 0 | AB17: 23006 | AC17: =AB17-AB16 -> 112 | AD17: 229327 | AE17: =AD17-AD16 -> 0 | AF17: ='Lpg (2)'!B21*2000/85 -> 1364.7059 | AG17: ='Lpg (2)'!C21*1000/85 -> 1000 | AH17: ='Lpg (2)'!D21*1000/85 -> 1000 | AI17: =SUM(AF17*2000)+(AG17*1000)+(AH17*1000) -> 4729411.8 | AJ17: =SUM(AI16-AI17) -> -223529.41
A18: =Gen!B23 -> 44574 | B18: ='UTILITY REPORT 1'!C15 -> 13 | D18: =B18 -> 13 | E18: =SUM(E17) -> 1.3262195 | F18: =SUM(J18*E18)/D18 -> 372.1576 | G18: =SUM(L18*E18)/D18 -> 372.1576 | H18: =Gen!D23 -> 33226.33 | I18: =Gen!F23 -> 0 | J18: =Gen!U23 -> 3648 | K18: =Gen!AL23 -> 0 | L18: =SUM(J18:K18) -> 3648 | M18: ='Water-Meter'!K58 -> 590.0892 | N18: ='Water-Meter'!E18 -> 86 | P18: 19044 | Q18: =SUM(P18-P17) -> 0 | R18: =SUM(Q18*O18) -> 0 | S18: 6.8 | T18: 20720 | U18: =T18-T17 -> 18 | V18: =SUM(U18*S18) -> 122.4 | X18: 29498 | Y18: =X18-X17 -> 0 | Z18: =SUM(Y18*W18) -> 0 | AA18: =SUM(Z18*X20) -> 0 | AB18: 23117 | AC18: =AB18-AB17 -> 111 | AD18: 229327 | AE18: =AD18-AD17 -> 0 | AF18: ='Lpg (2)'!B22*2000/85 -> 1294.1176 | AG18: ='Lpg (2)'!C22*1000/85 -> 1000 | AH18: ='Lpg (2)'!D22*1000/85 -> 1000 | AI18: =SUM(AF18*2000)+(AG18*1000)+(AH18*1000) -> 4588235.3 | AJ18: =SUM(AI17-AI18) -> 141176.47
A19: =Gen!B24 -> 44575 | B19: ='UTILITY REPORT 1'!C16 -> 17 | D19: =B19 -> 17 | E19: =SUM(E18) -> 1.3262195 | F19: =SUM(J19*E19)/D19 -> 296.059 | G19: =SUM(L19*E19)/D19 -> 296.059 | H19: =Gen!D24 -> 31652.73 | I19: =Gen!F24 -> 0 | J19: =Gen!U24 -> 3795 | K19: =Gen!AL24 -> 0 | L19: =SUM(J19:K19) -> 3795 | M19: ='Water-Meter'!K59 -> 594.5225 | N19: ='Water-Meter'!E19 -> 92 | P19: 19044 | Q19: =SUM(P19-P18) -> 0 | R19: =SUM(Q19*O19) -> 0 | S19: 6.8 | T19: 20734 | U19: =T19-T18 -> 14 | V19: =SUM(U19*S19) -> 95.2 | X19: 29498 | Y19: =X19-X18 -> 0 | Z19: =SUM(Y19*W19) -> 0 | AA19: =SUM(Z19*X21) -> 0 | AB19: 23209 | AC19: =AB19-AB18 -> 92 | AD19: 229370 | AE19: =AD19-AD18 -> 43 | AF19: ='Lpg (2)'!B23*2000/85 -> 1223.5294 | AG19: ='Lpg (2)'!C23*1000/85 -> 1000 | AH19: ='Lpg (2)'!D23*1000/85 -> 1000 | AI19: =SUM(AF19*2000)+(AG19*1000)+(AH19*1000) -> 4447058.8 | AJ19: =SUM(AI18-AI19) -> 141176.47
A20: =Gen!B25 -> 44576 | B20: ='UTILITY REPORT 1'!C17 -> 15 | D20: =B20 -> 15 | E20: =SUM(E19) -> 1.3262195 | F20: =SUM(J20*E20)/D20 -> 322.53659 | G20: =SUM(L20*E20)/D20 -> 322.53659 | H20: =Gen!D25 -> 29852.73 | I20: =Gen!F25 -> 0 | J20: =Gen!U25 -> 3648 | K20: =Gen!AL25 -> 0 | L20: =SUM(J20:K20) -> 3648 | M20: ='Water-Meter'!K60 -> 566.29314 | N20: ='Water-Meter'!E20 -> 102 | P20: 19044 | Q20: =SUM(P20-P18) -> 0 | R20: =SUM(Q20*O20) -> 0 | S20: 6.8 | T20: 20743 | U20: =T20-T19 -> 9 | V20: =SUM(U20*S20) -> 61.2 | X20: 29498 | Y20: =X20-X19 -> 0 | Z20: =SUM(Y20*W20) -> 0 | AA20: =SUM(Z20*X22) -> 0 | AB20: 23267 | AC20: =AB20-AB19 -> 58 | AD20: 229396 | AE20: =AD20-AD19 -> 26 | AF20: ='Lpg (2)'!B24*2000/85 -> 1176.4706 | AG20: ='Lpg (2)'!C24*1000/85 -> 1000 | AH20: ='Lpg (2)'!D24*1000/85 -> 1000 | AI20: =SUM(AF20*2000)+(AG20*1000)+(AH20*1000) -> 4352941.2 | AJ20: =SUM(AI19-AI20) -> 94117.647
A21: =Gen!B26 -> 44577 | B21: ='UTILITY REPORT 1'!C18 -> 17 | D21: =B21 -> 17 | E21: =SUM(E20) -> 1.3262195 | F21: =SUM(J21*E21)/D21 -> 264.69781 | G21: =SUM(L21*E21)/D21 -> 264.69781 | H21: =Gen!D26 -> 28410.73 | I21: =Gen!F26 -> 0 | J21: =Gen!U26 -> 3393 | K21: =Gen!AL26 -> 0 | L21: =SUM(J21:K21) -> 3393 | M21: ='Water-Meter'!K61 -> 550.85724 | N21: ='Water-Meter'!E21 -> 74 | P21: 19044 | Q21: =SUM(P21-P20) -> 0 | R21: =SUM(Q21*O21) -> 0 | S21: 6.8 | T21: 20758 | U21: =T21-T20 -> 15 | V21: =SUM(U21*S21) -> 102 | X21: 29498 | Y21: =X21-X20 -> 0 | Z21: =SUM(Y21*W21) -> 0 | AA21: =SUM(Z21*X23) -> 0 | AB21: 23358 | AC21: =AB21-AB20 -> 91 | AD21: 229459 | AE21: =AD21-AD20 -> 63 | AF21: ='Lpg (2)'!B25*2000/85 -> 1105.8824 | AG21: ='Lpg (2)'!C25*1000/85 -> 1000 | AH21: ='Lpg (2)'!D25*1000/85 -> 1000 | AI21: =SUM(AF21*2000)+(AG21*1000)+(AH21*1000) -> 4211764.7 | AJ21: =SUM(AI20-AI21) -> 141176.47
A22: =Gen!B27 -> 44578 | B22: ='UTILITY REPORT 1'!C19 -> 10 | D22: =B22 -> 10 | E22: =SUM(E21) -> 1.3262195 | F22: =SUM(J22*E22)/D22 -> 394.81555 | G22: =SUM(L22*E22)/D22 -> 394.81555 | H22: =Gen!D27 -> 26609.35 | I22: =Gen!F27 -> 18000 | J22: =Gen!U27 -> 2977 | K22: =Gen!AL27 -> 0 | L22: =SUM(J22:K22) -> 2977 | M22: ='Water-Meter'!K62 -> 575.40819 | N22: ='Water-Meter'!E22 -> 68 | P22: 19044 | Q22: =SUM(P22-P21) -> 0 | R22: =SUM(Q22*O22) -> 0 | S22: 6.8 | T22: 20771 | U22: =T22-T21 -> 13 | V22: =SUM(U22*S22) -> 88.4 | X22: 29498 | Y22: =X22-X21 -> 0 | Z22: =SUM(Y22*W22) -> 0 | AA22: =SUM(Z22*X24) -> 0 | AB22: 23436 | AC22: =AB22-AB21 -> 78 | AD22: 229495 | AE22: =AD22-AD21 -> 36 | AF22: ='Lpg (2)'!B26*2000/85 -> 1035.2941 | AG22: ='Lpg (2)'!C26*1000/85 -> 1000 | AH22: ='Lpg (2)'!D26*1000/85 -> 1000 | AI22: =SUM(AF22*2000)+(AG22*1000)+(AH22*1000) -> 4070588.2 | AJ22: =SUM(AI21-AI22) -> 141176.47
A23: =Gen!B28 -> 44579 | B23: ='UTILITY REPORT 1'!C20 -> 14 | D23: =B23 -> 14 | E23: =SUM(E22) -> 1.3262195 | F23: =SUM(J23*E23)/D23 -> 326.15527 | G23: =SUM(L23*E23)/D23 -> 326.15527 | H23: =Gen!D28 -> 25388.88 | I23: =Gen!F28 -> 0 | J23: =Gen!U28 -> 3443 | K23: =Gen!AL28 -> 0 | L23: =SUM(J23:K23) -> 3443 | M23: ='Water-Meter'!K63 -> 544.43275 | N23: ='Water-Meter'!E23 -> 62 | P23: 19044 | Q23: =SUM(P23-P22) -> 0 | R23: =SUM(Q23*O23) -> 0 | S23: 6.8 | T23: 20771 | U23: =T23-T22 -> 0 | V23: =SUM(U23*S23) -> 0 | X23: 29498 | Y23: =X23-X22 -> 0 | Z23: =SUM(Y23*W23) -> 0 | AA23: =SUM(Z23*X25) -> 0 | AB23: 23436 | AC23: =AB23-AB22 -> 0 | AD23: 229495 | AE23: =AD23-AD22 -> 0 | AF23: ='Lpg (2)'!B27*2000/85 -> 964.70588 | AG23: ='Lpg (2)'!C27*1000/85 -> 1000 | AH23: ='Lpg (2)'!D27*1000/85 -> 1000 | AI23: =SUM(AF23*2000)+(AG23*1000)+(AH23*1000) -> 3929411.8 | AJ23: =SUM(AI22-AI23) -> 141176.47
A24: =Gen!B29 -> 44580 | B24: ='UTILITY REPORT 1'!C21 -> 15 | D24: =B24 -> 15 | E24: =SUM(E23) -> 1.3262195 | F24: =SUM(J24*E24)/D24 -> 266.12805 | G24: =SUM(L24*E24)/D24 -> 266.12805 | H24: =Gen!D29 -> 23785.23 | I24: =Gen!F29 -> 0 | J24: =Gen!U29 -> 3010 | K24: =Gen!AL29 -> 0 | L24: =SUM(J24:K24) -> 3010 | M24: ='Water-Meter'!K64 -> 445.94505 | N24: ='Water-Meter'!E24 -> 70 | P24: 19044 | Q24: =SUM(P24-P23) -> 0 | R24: =SUM(Q24*O24) -> 0 | S24: 6.8 | T24: 20794 | U24: =T24-T23 -> 23 | V24: =SUM(U24*S24) -> 156.4 | X24: 29498 | Y24: =X24-X23 -> 0 | Z24: =SUM(Y24*W24) -> 0 | AA24: =SUM(Z24*X26) -> 0 | AB24: 23580 | AC24: =AB24-AB23 -> 144 | AD24: 229496 | AE24: =AD24-AD23 -> 1 | AF24: ='Lpg (2)'!B28*2000/85 -> 894.11765 | AG24: ='Lpg (2)'!C28*1000/85 -> 1000 | AH24: ='Lpg (2)'!D28*1000/85 -> 1000 | AI24: =SUM(AF24*2000)+(AG24*1000)+(AH24*1000) -> 3788235.3 | AJ24: =SUM(AI23-AI24) -> 141176.47
A25: =Gen!B30 -> 44581 | B25: ='UTILITY REPORT 1'!C22 -> 17 | D25: =B25 -> 17 | E25: =SUM(E24) -> 1.3262195 | F25: =SUM(J25*E25)/D25 -> 259.23691 | G25: =SUM(L25*E25)/D25 -> 259.23691 | H25: =Gen!D30 -> 22404.68 | I25: =Gen!F30 -> 0 | J25: =Gen!U30 -> 3323 | K25: =Gen!AL30 -> 0 | L25: =SUM(J25:K25) -> 3323 | M25: ='Water-Meter'!K65 -> 616.79833 | N25: ='Water-Meter'!E25 -> 88 | P25: 19044 | Q25: =SUM(P25-P24) -> 0 | R25: =SUM(Q25*O25) -> 0 | S25: 6.8 | T25: 20802 | U25: =T25-T24 -> 8 | V25: =SUM(U25*S25) -> 54.4 | X25: 29498 | Y25: =X25-X24 -> 0 | Z25: =SUM(Y25*W25) -> 0 | AA25: =SUM(Z25*X27) -> 0 | AB25: 23625 | AC25: =AB25-AB24 -> 45 | AD25: 229496 | AE25: =AD25-AD24 -> 0 | AF25: ='Lpg (2)'!B29*2000/85 -> 870.58824 | AG25: ='Lpg (2)'!C29*1000/85 -> 1000 | AH25: ='Lpg (2)'!D29*1000/85 -> 1000 | AI25: =SUM(AF25*2000)+(AG25*1000)+(AH25*1000) -> 3741176.5 | AJ25: =SUM(AI24-AI25) -> 47058.824
A26: =Gen!B31 -> 44582 | B26: ='UTILITY REPORT 1'!C23 -> 8 | D26: =B26 -> 8 | E26: =SUM(E25) -> 1.3262195 | F26: =SUM(J26*E26)/D26 -> 516.06517 | G26: =SUM(L26*E26)/D26 -> 516.06517 | H26: =Gen!D31 -> 20796.21 | I26: =Gen!F31 -> 0 | J26: =Gen!U31 -> 3113 | K26: =Gen!AL31 -> 0 | L26: =SUM(J26:K26) -> 3113 | M26: ='Water-Meter'!K66 -> 552.0154 | N26: ='Water-Meter'!E26 -> 81 | P26: 19044 | Q26: =SUM(P26-P25) -> 0 | R26: =SUM(Q26*O26) -> 0 | S26: 6.8 | T26: 20826 | U26: =T26-T25 -> 24 | V26: =SUM(U26*S26) -> 163.2 | X26: 29498 | Y26: =X26-X25 -> 0 | Z26: =SUM(Y26*W26) -> 0 | AA26: =SUM(Z26*X28) -> 0 | AB26: 23764 | AC26: =AB26-AB25 -> 139 | AD26: 229526 | AE26: =AD26-AD25 -> 30 | AF26: ='Lpg (2)'!B30*2000/85 -> 847.05882 | AG26: ='Lpg (2)'!C30*1000/85 -> 1000 | AH26: ='Lpg (2)'!D30*1000/85 -> 1000 | AI26: =SUM(AF26*2000)+(AG26*1000)+(AH26*1000) -> 3694117.6 | AJ26: =SUM(AI25-AI26) -> 47058.824
A27: =Gen!B32 -> 44583 | B27: ='UTILITY REPORT 1'!C24 -> 7 | D27: =B27 -> 7 | E27: =SUM(E26) -> 1.3262195 | F27: =SUM(J27*E27)/D27 -> 591.87282 | G27: =SUM(L27*E27)/D27 -> 591.87282 | H27: =Gen!D32 -> 19500.9 | I27: =Gen!F32 -> 0 | J27: =Gen!U32 -> 3124 | K27: =Gen!AL32 -> 0 | L27: =SUM(J27:K27) -> 3124 | M27: ='Water-Meter'!K67 -> 541.21611 | N27: ='Water-Meter'!E27 -> 71 | P27: 19044 | Q27: =SUM(P27-P26) -> 0 | R27: =SUM(Q27*O27) -> 0 | S27: 6.8 | T27: 20843 | U27: =T27-T26 -> 17 | V27: =SUM(U27*S27) -> 115.6 | X27: 29498 | Y27: ='Utility report '!X18 -> 29498 | Z27: =SUM(Y27*W27) -> 0 | AA27: =SUM(Z27*X29) -> 0 | AB27: 23864 | AC27: =AB27-AB26 -> 100 | AD27: 229569 | AE27: =AD27-AD26 -> 43 | AF27: ='Lpg (2)'!B31*2000/85 -> 800 | AG27: ='Lpg (2)'!C31*1000/85 -> 1000 | AH27: ='Lpg (2)'!D31*1000/85 -> 1000 | AI27: =SUM(AF27*2000)+(AG27*1000)+(AH27*1000) -> 3600000 | AJ27: =SUM(AI26-AI27) -> 94117.647
A28: =Gen!B33 -> 44584 | B28: ='UTILITY REPORT 1'!C25 -> 4 | D28: =B28 -> 4 | E28: =SUM(E27) -> 1.3262195 | F28: =SUM(J28*E28)/D28 -> 927.35899 | G28: =SUM(L28*E28)/D28 -> 927.35899 | H28: =Gen!D33 -> 35949.82 | I28: =Gen!F33 -> 0 | J28: =Gen!U33 -> 2797 | K28: =Gen!AL33 -> 0 | L28: =SUM(J28:K28) -> 2797 | M28: ='Water-Meter'!K68 -> 577.19832 | N28: ='Water-Meter'!E28 -> 62 | P28: 19044 | Q28: =SUM(P28-P27) -> 0 | R28: =SUM(Q28*O28) -> 0 | S28: 6.9 | T28: 20854 | U28: =T28-T27 -> 11 | V28: =SUM(U28*S28) -> 75.9 | X28: 29498 | Y28: =X28-X27 -> 0 | Z28: =SUM(Y28*W28) -> 0 | AA28: =SUM(Z28*X30) -> 0 | AB28: 23938 | AC28: =SUM(AB28-AB27) -> 74 | AD28: 229662 | AE28: =AD28-AD27 -> 93 | AF28: ='Lpg (2)'!B32*2000/85 -> 705.88235 | AG28: ='Lpg (2)'!C32*1000/85 -> 1000 | AH28: ='Lpg (2)'!D32*1000/85 -> 1000 | AI28: =SUM(AF28*2000)+(AG28*1000)+(AH28*1000) -> 3411764.7 | AJ28: =SUM(AI27-AI28) -> 188235.29
A29: =Gen!B34 -> 44585 | B29: ='UTILITY REPORT 1'!C26 -> 9 | D29: =B29 -> 9 | E29: =SUM(E28) -> 1.3262195 | F29: =SUM(J29*E29)/D29 -> 485.5437 | G29: =SUM(L29*E29)/D29 -> 485.5437 | H29: =Gen!D34 -> 34497.3 | I29: =Gen!F34 -> 0 | J29: =Gen!U34 -> 3295 | K29: =Gen!AL34 -> 0 | L29: =SUM(J29:K29) -> 3295 | M29: ='Water-Meter'!K69 -> 614.02387 | N29: ='Water-Meter'!E29 -> 75 | P29: 19044 | Q29: =SUM(P29-P28) -> 0 | R29: =SUM(Q29*O29) -> 0 | S29: 6.9 | T29: 20859 | U29: =T29-T28 -> 5 | V29: =SUM(U29*S29) -> 34.5 | X29: 29498 | Y29: =X29-X28 -> 0 | Z29: =SUM(Y29*W29) -> 0 | AA29: =SUM(Z29*X31) -> 0 | AB29: 23955 | AC29: =SUM(AB29-AB28) -> 17 | AD29: 229723 | AE29: =AD29-AD28 -> 61 | AF29: ='Lpg (2)'!B33*2000/85 -> 635.29412 | AG29: ='Lpg (2)'!C33*1000/85 -> 1000 | AH29: ='Lpg (2)'!D33*1000/85 -> 1000 | AI29: =SUM(AF29*2000)+(AG29*1000)+(AH29*1000) -> 3270588.2 | AJ29: =SUM(AI28-AI29) -> 141176.47
A30: =Gen!B35 -> 44586 | B30: ='UTILITY REPORT 1'!C27 -> 12 | D30: =B30 -> 12 | E30: =SUM(E29) -> 1.3262195 | F30: =SUM(J30*E30)/D30 -> 354.21113 | G30: =SUM(L30*E30)/D30 -> 354.21113 | H30: =Gen!D35 -> 32919.45 | I30: =Gen!F35 -> 0 | J30: =Gen!U35 -> 3205 | K30: =Gen!AL35 -> 0 | L30: =SUM(J30:K30) -> 3205 | M30: ='Water-Meter'!K70 -> 493.97483 | N30: ='Water-Meter'!E30 -> 160 | P30: 19044 | Q30: =SUM(P30-P29) -> 0 | R30: =SUM(Q30*O30) -> 0 | S30: 6.9 | T30: 20882 | U30: =T30-T29 -> 23 | V30: =SUM(U30*S30) -> 158.7 | X30: 29498 | Y30: =X30-X29 -> 0 | Z30: =SUM(Y30*W30) -> 0 | AA30: =SUM(Z30*X32) -> 0 | AB30: 24088 | AC30: =SUM(AB30-AB29) -> 133 | AD30: 229788 | AE30: =AD30-AD29 -> 65 | AF30: ='Lpg (2)'!B34*2000/85 -> 541.17647 | AG30: ='Lpg (2)'!C34*1000/85 -> 1000 | AH30: ='Lpg (2)'!D34*1000/85 -> 1000 | AI30: =SUM(AF30*2000)+(AG30*1000)+(AH30*1000) -> 3082352.9 | AJ30: =SUM(AI29-AI30) -> 188235.29
A31: =Gen!B36 -> 44587 | B31: ='UTILITY REPORT 1'!C28 -> 13 | D31: =B31 -> 13 | E31: =SUM(E30) -> 1.3262195 | F31: =SUM(J31*E31)/D31 -> 364.71037 | G31: =SUM(L31*E31)/D31 -> 364.71037 | H31: =Gen!D36 -> 31545.95 | I31: =Gen!F36 -> 15000 | J31: =Gen!U36 -> 3575 | K31: =Gen!AL36 -> 0 | L31: =SUM(J31:K31) -> 3575 | M31: ='Water-Meter'!K71 -> 407.6984 | N31: ='Water-Meter'!E31 -> 66 | P31: 19044 | Q31: =SUM(P31-P30) -> 0 | R31: =SUM(Q31*O31) -> 0 | S31: 6.7 | T31: 20902 | U31: =T31-T30 -> 20 | V31: =SUM(U31*S31) -> 134 | X31: 29498 | Y31: =X31-X30 -> 0 | Z31: =SUM(Y31*W31) -> 0 | AA31: =SUM(Z31*X33) -> 0 | AB31: 24100 | AC31: =SUM(AB31-AB30) -> 12 | AD31: 229855 | AE31: =AD31-AD30 -> 67 | AF31: ='Lpg (2)'!B35*2000/85 -> 470.58824 | AG31: ='Lpg (2)'!C35*1000/85 -> 1000 | AH31: ='Lpg (2)'!D35*1000/85 -> 1000 | AI31: =SUM(AF31*2000)+(AG31*1000)+(AH31*1000) -> 2941176.5 | AJ31: =SUM(AI30-AI31) -> 141176.47
A32: =Gen!B37 -> 44588 | B32: ='UTILITY REPORT 1'!C29 -> 11 | D32: =B32 -> 11 | E32: =SUM(E31) -> 1.3262195 | F32: =SUM(J32*E32)/D32 -> 435.24113 | G32: =SUM(L32*E32)/D32 -> 435.24113 | H32: =Gen!D37 -> 45120.6 | I32: =Gen!F37 -> 0 | J32: =Gen!U37 -> 3610 | K32: =Gen!AL37 -> 0 | L32: =SUM(J32:K32) -> 3610 | M32: ='Water-Meter'!K72 -> 444.55214 | N32: ='Water-Meter'!E32 -> 75 | P32: 19044 | Q32: =SUM(P32-P31) -> 0 | R32: =SUM(Q32*O32) -> 0 | S32: 6.7 | T32: 20917 | U32: =T32-T31 -> 15 | V32: =SUM(U32*S32) -> 100.5 | X32: 29498 | Y32: =X32-X31 -> 0 | Z32: =SUM(Y32*W32) -> 0 | AA32: =SUM(Z32*X34) -> 0 | AB32: 24284 | AC32: =SUM(AB32-AB31) -> 184 | AD32: 229931 | AE32: =AD32-AD31 -> 76 | AF32: ='Lpg (2)'!B36*2000/85 -> 447.05882 | AG32: ='Lpg (2)'!C36*1000/85 -> 1000 | AH32: ='Lpg (2)'!D36*1000/85 -> 1000 | AI32: =SUM(AF32*2000)+(AG32*1000)+(AH32*1000) -> 2894117.6 | AJ32: =SUM(AI31-AI32) -> 47058.824
A33: =Gen!B38 -> 44589 | B33: ='UTILITY REPORT 1'!C30 -> 8 | D33: =B33 -> 8 | E33: =SUM(E32) -> 1.3262195 | F33: =SUM(J33*E33)/D33 -> 595.63834 | G33: =SUM(L33*E33)/D33 -> 595.63834 | H33: =Gen!D38 -> 43355.27 | I33: =Gen!F38 -> 0 | J33: =Gen!U38 -> 3593 | K33: =Gen!AL38 -> 0 | L33: =SUM(J33:K33) -> 3593 | M33: ='Water-Meter'!K73 -> 474.54203 | N33: ='Water-Meter'!E33 -> 64 | P33: 19044 | Q33: =SUM(P33-P32) -> 0 | R33: =SUM(Q33*O33) -> 0 | S33: 6.7 | T33: 20928 | U33: =T33-T32 -> 11 | V33: =SUM(U33*S33) -> 73.7 | X33: 29498 | Y33: =X33-X32 -> 0 | Z33: =SUM(Y33*W33) -> 0 | AA33: =SUM(Z33*X35) -> 0 | AB33: 24350 | AC33: =SUM(AB33-AB32) -> 66 | AD33: 229992 | AE33: =AD33-AD32 -> 61 | AF33: ='Lpg (2)'!B37*2000/85 -> 400 | AG33: ='Lpg (2)'!C37*1000/85 -> 1000 | AH33: ='Lpg (2)'!D37*1000/85 -> 1000 | AI33: =SUM(AF33*2000)+(AG33*1000)+(AH33*1000) -> 2800000 | AJ33: =SUM(AI32-AI33) -> 94117.647
A34: =Gen!B39 -> 44590 | B34: ='UTILITY REPORT 1'!C31 -> 8 | D34: =B34 -> 8 | E34: =SUM(E33) -> 1.3262195 | F34: =SUM(J34*E34)/D34 -> 594.97523 | G34: =SUM(L34*E34)/D34 -> 594.97523 | H34: =Gen!D39 -> 41926.07 | I34: =Gen!F39 -> 0 | J34: =Gen!U39 -> 3589 | K34: =Gen!AL39 -> 0 | L34: =SUM(J34:K34) -> 3589 | M34: ='Water-Meter'!K74 -> 488.84997 | N34: ='Water-Meter'!E34 -> 80 | P34: 19044 | Q34: =SUM(P34-P33) -> 0 | R34: =SUM(Q34*O34) -> 0 | S34: 6.7 | T34: 20953 | U34: =T34-T33 -> 25 | V34: =SUM(U34*S34) -> 167.5 | X34: 29498 | Y34: =X34-X33 -> 0 | Z34: =SUM(Y34*W34) -> 0 | AA34: =SUM(Z34*X36) -> 0 | AB34: 24485 | AC34: =SUM(AB34-AB33) -> 135 | AD34: 230059 | AE34: =AD34-AD33 -> 67 | AF34: ='Lpg (2)'!B38*2000/85 -> 352.94118 | AG34: ='Lpg (2)'!C38*1000/85 -> 1000 | AH34: ='Lpg (2)'!D38*1000/85 -> 1000 | AI34: =SUM(AF34*2000)+(AG34*1000)+(AH34*1000) -> 2705882.4 | AJ34: =SUM(AI33-AI34) -> 94117.647
A35: =Gen!B40 -> 44591 | B35: ='UTILITY REPORT 1'!C32 -> 6 | D35: =B35 -> 6 | E35: =SUM(E34) -> 1.3262195 | F35: =SUM(J35*E35)/D35 -> 790.20579 | G35: =SUM(L35*E35)/D35 -> 790.20579 | H35: =Gen!D40 -> 40463.29 | I35: =Gen!F40 -> 0 | J35: =Gen!U40 -> 3575 | K35: =Gen!AL40 -> 0 | L35: =SUM(J35:K35) -> 3575 | M35: ='Water-Meter'!K75 -> 557.19794 | N35: ='Water-Meter'!E35 -> 110 | P35: 19044 | Q35: =SUM(P35-P34) -> 0 | R35: =SUM(Q35*O35) -> 0 | S35: 6.7 | T35: 20954 | U35: =T35-T34 -> 1 | V35: =SUM(U35*S35) -> 6.7 | X35: 29498 | Y35: =X35-X34 -> 0 | Z35: =SUM(Y35*W35) -> 0 | AA35: =SUM(Z35*X37) -> 0 | AB35: 24496 | AC35: =SUM(AB35-AB34) -> 11 | AD35: 230127 | AE35: =AD35-AD34 -> 68 | AF35: ='Lpg (2)'!B39*2000/85 -> 258.82353 | AG35: ='Lpg (2)'!C39*1000/85 -> 1000 | AH35: ='Lpg (2)'!D39*1000/85 -> 1000 | AI35: =SUM(AF35*2000)+(AG35*1000)+(AH35*1000) -> 2517647.1 | AJ35: =SUM(AI34-AI35) -> 188235.29
A36: =Gen!B41 -> 44592 | B36: ='UTILITY REPORT 1'!C33 -> 5 | D36: =B36 -> 5 | E36: =SUM(E35) -> 1.3262195 | F36: =SUM(J36*E36)/D36 -> 867.87805 | G36: =SUM(L36*E36)/D36 -> 867.87805 | H36: =Gen!D41 -> 39020.42 | I36: =Gen!F41 -> 0 | J36: =Gen!U41 -> 3272 | K36: =Gen!AL41 -> 0 | L36: =SUM(J36:K36) -> 3272 | M36: ='Water-Meter'!K76 -> 510.09745 | N36: ='Water-Meter'!E36 -> 104 | P36: 19044 | Q36: =SUM(P36-P35) -> 0 | R36: =SUM(Q36*O36) -> 0 | S36: 6.8 | T36: 20954 | U36: =T36-T35 -> 0 | V36: =SUM(U36*S36) -> 0 | X36: 29498 | Y36: =X36-X35 -> 0 | Z36: =SUM(Y36*W36) -> 0 | AA36: =SUM(Z36*X38) -> 0 | AB36: 24631 | AC36: =SUM(AB36-AB35) -> 135 | AD36: 230193 | AE36: =AD36-AD35 -> 66 | AF36: ='Lpg (2)'!B40*2000/85 -> 211.76471 | AG36: ='Lpg (2)'!C40*1000/85 -> 1000 | AH36: ='Lpg (2)'!D40*1000/85 -> 1000 | AI36: =SUM(AF36*1000)+(AG36*1000)+(AH36*2000) -> 3211764.7 | AJ36: =SUM(AI35-AI36) -> -694117.65
A37: =Gen!B42 -> 0 | B37: ='UTILITY REPORT 1'!C34 -> 0 | J37: =SUM(J6:J36) -> 115511 | L37: =SUM(J37:K37) -> 115511 | M37: ='Water-Meter'!K77 -> 0 | N37: ='Water-Meter'!E37 -> 0 | Q37: =SUM(P37-P36) -> -19044 | R37: =SUM(Q37*O37) -> 0 | U37: =T37-T36 -> -20954 | V37: =SUM(U37*S37) -> 0 | Y37: =X37-X36 -> -29498 | Z37: =SUM(Y37*W37) -> 0 | AA37: =SUM(Z37*X39) -> 0 | AB37: 24759 | AC37: =SUM(AB37-AB36) -> 128 | AD37: 230257 | AE37: =AD37-AD36 -> 64 | AF37: ='Lpg (2)'!B41*2000/85 -> 0 | AG37: ='Lpg (2)'!C41*1000/85 -> 0 | AH37: ='Lpg (2)'!D41*1000/85 -> 0 | AJ37: =SUM(AI36-AI37) -> 3211764.7

Sheet Kit report
B1: KITCHEN THREE PHASE KWH METER READING | H1: KITCHEN WATER METER READING | M1: AMANI Restaurant WATER METER READING | T1: LAUNDRY THREE PHASE KWH METER READING | Y1: LAUNDRY WATER METER READING
A2: Occ % | B2: DATE | C2: READING TIME | D2: METER READING OPEN | E2: METER READING ClOSE | F2: UNIT USED Kwh | H2: DATE | I2: READING TIME | J2: METER READING OPEN Cbm | K2: METER READING ClOSE Cbm | L2: UNIT USED Cbm | M2: DATE | N2: READING TIME | O2: METER READING OPEN Cbm | P2: METER READING ClOSE Cbm | Q2: UNIT USED Cbm | R2: Cost Per day Elct+Water $ | S2: % as per the total Lodge consumption | T2: DATE | U2: READING TIME | V2: METER READING OPEN (Kwh) | W2: METER READING ClOSE (Kwh) | X2: UNIT USED Kwh | Y2: DATE | Z2: READING TIME | AA2: METER READING OPEN Cbm | AB2: METER READING ClOSE Cbm | AC2: UNIT USED Cbm
A3: =Gen!B11 -> 44562 | B3: Close Last Month | E3: 9818.2 | F3: =SUM(E4-D3)*120 -> 1178448 | H3: Close Last Month | J3: ='Water-Meter'!G5 -> 0 | K3: ='Water-Meter'!G5 -> 0 | M3: Close Last Month | P3: ='Water-Meter'!J5 -> 8965 | T3: Close Last Month | W3: 8794.9 | X3: =(W3-V3)*200 -> 1758980 | Y3: Close Last Month | AB3: ='Water-Meter'!P5 -> 22928
A4: =Gen!C11 -> 0.4156 | B4: =Gen!B11 -> 44562 | D4: =E3 -> 9818.2 | E4: 9820.4 | F4: =SUM(E5-D4)*120 -> 564 | H4: =B4 -> 44562 | J4: ='Water-Meter'!G6 -> 0 | K4: ='Water-Meter'!G6 -> 0 | L4: =SUM(K4-J4) -> 0 | M4: =H4 -> 44562 | P4: ='Water-Meter'!J6 -> 8968 | Q4: =N4-O3 -> 0 | R4: =SUM(Q4/1615) -> 0 | S4: =Gen!U11 -> 4734 | T4: =M4 -> 44562 | V4: =W3 -> 8794.9 | W4: 8799.6 | X4: =(W4-V4)*200 -> 940 | Y4: =T4 -> 44562 | AA4: =AB3 -> 22928 | AB4: ='Water-Meter'!P6 -> 22939 | AC4: =AB4-AA4 -> 11
A5: =Gen!C12 -> 0.53 | B5: =Gen!B12 -> 44563 | D5: =E5 -> 9822.9 | E5: 9822.9 | F5: =SUM(E6-D5)*120 -> 204 | H5: =B5 -> 44563 | J5: ='Water-Meter'!G7 -> 0 | K5: ='Water-Meter'!G7 -> 0 | L5: =SUM(K5-J5) -> 0 | M5: =H5 -> 44563 | P5: ='Water-Meter'!J7 -> 8971 | Q5: =N5-O4 -> 0 | R5: =SUM(Q5/1615) -> 0 | S5: =Gen!U12 -> 4563 | T5: =M5 -> 44563 | V5: =W4 -> 8799.6 | W5: 8804.8 | X5: =(W5-V5)*200 -> 1040 | Y5: =T5 -> 44563 | AA5: =AB4 -> 22939 | AB5: ='Water-Meter'!P7 -> 22948 | AC5: =AB5-AA5 -> 9
A6: =Gen!C13 -> 0.36 | B6: =Gen!B13 -> 44564 | D6: =E6 -> 9824.6 | E6: 9824.6 | F6: =SUM(E7-D6)*120 -> 276 | H6: =B6 -> 44564 | J6: ='Water-Meter'!G8 -> 0 | K6: ='Water-Meter'!G8 -> 0 | L6: =SUM(K6-J6) -> 0 | M6: =H6 -> 44564 | P6: ='Water-Meter'!J8 -> 8975 | Q6: =N6-O5 -> 0 | R6: =SUM(Q6/1615) -> 0 | S6: =Gen!U13 -> 4574 | T6: =M6 -> 44564 | V6: =W5 -> 8804.8 | W6: 8809.4 | X6: =(W6-V6)*200 -> 920 | Y6: =T6 -> 44564 | AA6: =AB5 -> 22948 | AB6: ='Water-Meter'!P8 -> 22960 | AC6: =AB6-AA6 -> 12
A7: =Gen!C14 -> 0.35 | B7: =Gen!B14 -> 44565 | D7: =E7 -> 9826.9 | E7: 9826.9 | F7: =SUM(E8-D7)*120 -> 228 | H7: =B7 -> 44565 | J7: ='Water-Meter'!G9 -> 0 | K7: ='Water-Meter'!G9 -> 0 | L7: =SUM(K7-J7) -> 0 | M7: =H7 -> 44565 | P7: ='Water-Meter'!J9 -> 8978 | Q7: =N7-O6 -> 0 | R7: =SUM(Q7/1615) -> 0 | S7: =Gen!U14 -> 4346 | T7: =M7 -> 44565 | V7: =W6 -> 8809.4 | W7: 8813.1 | X7: =(W7-V7)*200 -> 740 | Y7: =T7 -> 44565 | AA7: =AB6 -> 22960 | AB7: ='Water-Meter'!P9 -> 22969 | AC7: =AB7-AA7 -> 9
A8: =Gen!C15 -> 0.26 | B8: =Gen!B15 -> 44566 | D8: =E8 -> 9828.8 | E8: 9828.8 | F8: =SUM(E9-D8)*120 -> 204 | H8: =B8 -> 44566 | J8: ='Water-Meter'!G10 -> 0 | K8: ='Water-Meter'!G10 -> 0 | L8: =SUM(K8-J8) -> 0 | M8: =H8 -> 44566 | P8: ='Water-Meter'!J10 -> 8981 | Q8: =N8-O7 -> 0 | R8: =SUM(Q8/1615) -> 0 | S8: =Gen!U15 -> 3969 | T8: =M8 -> 44566 | V8: =W7 -> 8813.1 | W8: 8816.8 | X8: =(W8-V8)*200 -> 740 | Y8: =T8 -> 44566 | AA8: =AB7 -> 22969 | AB8: ='Water-Meter'!P10 -> 22978 | AC8: =AB8-AA8 -> 9
A9: =Gen!C16 -> 0.31 | B9: =Gen!B16 -> 44567 | D9: =E9 -> 9830.5 | E9: 9830.5 | F9: =SUM(E10-D9)*120 -> 228 | H9: =B9 -> 44567 | J9: ='Water-Meter'!G11 -> 0 | K9: ='Water-Meter'!G11 -> 0 | L9: =SUM(K9-J9) -> 0 | M9: =H9 -> 44567 | P9: ='Water-Meter'!J11 -> 8980 | Q9: =N9-O8 -> 0 | R9: =SUM(Q9/1615) -> 0 | S9: =Gen!U16 -> 4325 | T9: =M9 -> 44567 | V9: =W8 -> 8816.8 | W9: 8820.1 | X9: =(W9-V9)*200 -> 660 | Y9: =T9 -> 44567 | AA9: =AB8 -> 22978 | AB9: ='Water-Meter'!P11 -> 23012 | AC9: =AB9-AA9 -> 34
A10: =Gen!C17 -> 0.2468 | B10: =Gen!B17 -> 44568 | D10: =E10 -> 9832.4 | E10: 9832.4 | F10: =SUM(E11-D10)*120 -> 216 | H10: =B10 -> 44568 | J10: ='Water-Meter'!G12 -> 0 | K10: ='Water-Meter'!G12 -> 0 | L10: =SUM(K10-J10) -> 0 | M10: =H10 -> 44568 | P10: ='Water-Meter'!J12 -> 8982 | Q10: =N10-O9 -> 0 | R10: =SUM(Q10/1615) -> 0 | S10: =Gen!U17 -> 4444 | T10: =M10 -> 44568 | V10: =W9 -> 8820.1 | W10: 8823.8 | X10: =(W10-V10)*200 -> 740 | Y10: =T10 -> 44568 | AA10: =AB9 -> 23012 | AB10: ='Water-Meter'!P12 -> 23020 | AC10: =AB10-AA10 -> 8
A11: =Gen!C18 -> 0.23 | B11: =Gen!B18 -> 44569 | D11: =E11 -> 9834.2 | E11: 9834.2 | F11: =SUM(E12-D11)*120 -> 240 | H11: =B11 -> 44569 | J11: ='Water-Meter'!G13 -> 0 | K11: ='Water-Meter'!G13 -> 0 | L11: =SUM(K11-J11) -> 0 | M11: =H11 -> 44569 | P11: ='Water-Meter'!J13 -> 8984 | Q11: =N11-O10 -> 0 | R11: =SUM(Q11/1615) -> 0 | S11: =Gen!U18 -> 4291 | T11: =M11 -> 44569 | V11: =W10 -> 8823.8 | W11: 8827.3 | X11: =(W11-V11)*200 -> 700 | Y11: =T11 -> 44569 | AA11: =AB10 -> 23020 | AB11: ='Water-Meter'!P13 -> 23026 | AC11: =AB11-AA11 -> 6
A12: =Gen!C19 -> 0.2078 | B12: =Gen!B19 -> 44570 | D12: =E12 -> 9836.2 | E12: 9836.2 | F12: =SUM(E13-D12)*120 -> 252 | H12: =B12 -> 44570 | J12: ='Water-Meter'!G14 -> 0 | K12: ='Water-Meter'!G14 -> 0 | L12: =SUM(K12-J12) -> 0 | M12: =H12 -> 44570 | P12: ='Water-Meter'!J14 -> 8987 | Q12: =N12-O11 -> 0 | R12: =SUM(Q12/1615) -> 0 | S12: =Gen!U19 -> 4336 | T12: =M12 -> 44570 | V12: =W11 -> 8827.3 | W12: 8831.2 | X12: =(W12-V12)*200 -> 780 | Y12: =T12 -> 44570 | AA12: =AB11 -> 23026 | AB12: ='Water-Meter'!P14 -> 23030 | AC12: =AB12-AA12 -> 4
A13: =Gen!C20 -> 0.17 | B13: =Gen!B20 -> 44571 | D13: =E13 -> 9838.3 | E13: 9838.3 | F13: =SUM(E14-D13)*120 -> 288 | H13: =B13 -> 44571 | J13: ='Water-Meter'!G15 -> 0 | K13: ='Water-Meter'!G15 -> 0 | L13: =SUM(K13-J13) -> 0 | M13: =H13 -> 44571 | P13: ='Water-Meter'!J15 -> 8989 | Q13: =N13-O12 -> 0 | R13: =SUM(Q13/1615) -> 0 | S13: =Gen!U20 -> 4279 | T13: =M13 -> 44571 | V13: =W12 -> 8831.2 | W13: 8834.4 | X13: =(W13-V13)*200 -> 640 | Y13: =T13 -> 44571 | AA13: =AB12 -> 23030 | AB13: ='Water-Meter'!P15 -> 23047 | AC13: =AB13-AA13 -> 17
A14: =Gen!C21 -> 0.1 | B14: =Gen!B21 -> 44572 | D14: =E14 -> 9840.7 | E14: 9840.7 | F14: =SUM(E15-D14)*120 -> 288 | H14: =B14 -> 44572 | J14: ='Water-Meter'!G15 -> 0 | K14: ='Water-Meter'!G15 -> 0 | L14: =SUM(K14-J14) -> 0 | M14: =H14 -> 44572 | P14: ='Water-Meter'!J16 -> 8991 | Q14: =N14-O13 -> 0 | R14: =SUM(Q14/1615) -> 0 | S14: =Gen!U21 -> 3862 | T14: =M14 -> 44572 | V14: =W13 -> 8834.4 | W14: 8836.9 | X14: =(W14-V14)*200 -> 500 | Y14: =T14 -> 44572 | AA14: =AB13 -> 23047 | AB14: ='Water-Meter'!P16 -> 23055 | AC14: =AB14-AA14 -> 8
A15: =Gen!C22 -> 0.0649 | B15: =Gen!B22 -> 44573 | D15: =E15 -> 9843.1 | E15: 9843.1 | F15: =SUM(E16-D15)*120 -> 240 | H15: =B15 -> 44573 | J15: ='Water-Meter'!G17 -> 0 | K15: ='Water-Meter'!G17 -> 0 | L15: =SUM(K15-J15) -> 0 | M15: =H15 -> 44573 | P15: ='Water-Meter'!J17 -> 8994 | Q15: =N15-O14 -> 0 | R15: =SUM(Q15/1615) -> 0 | S15: =Gen!U22 -> 3803 | T15: =M15 -> 44573 | V15: =W14 -> 8836.9 | W15: 8839.6 | X15: =(W15-V15)*200 -> 540 | Y15: =T15 -> 44573 | AA15: =AB14 -> 23055 | AB15: ='Water-Meter'!P17 -> 23064 | AC15: =AB15-AA15 -> 9
A16: =Gen!C23 -> 0.13 | B16: =Gen!B23 -> 44574 | D16: =E16 -> 9845.1 | E16: 9845.1 | F16: =SUM(E17-D16)*120 -> 288 | H16: =B16 -> 44574 | J16: ='Water-Meter'!G18 -> 0 | K16: ='Water-Meter'!G18 -> 0 | L16: =SUM(K16-J16) -> 0 | M16: =H16 -> 44574 | P16: ='Water-Meter'!J18 -> 8996 | Q16: =N16-O15 -> 0 | R16: =SUM(Q16/1615) -> 0 | S16: =Gen!U23 -> 3648 | T16: =M16 -> 44574 | V16: =W15 -> 8839.6 | W16: 8842.1 | X16: =(W16-V16)*200 -> 500 | Y16: =T16 -> 44574 | AA16: =AB15 -> 23064 | AB16: ='Water-Meter'!P18 -> 23070 | AC16: =AB16-AA16 -> 6
A17: =Gen!C24 -> 0.18 | B17: =Gen!B24 -> 44575 | D17: =E17 -> 9847.5 | E17: 9847.5 | F17: =SUM(E18-D17)*120 -> 276 | H17: =B17 -> 44575 | J17: ='Water-Meter'!G19 -> 0 | K17: ='Water-Meter'!G19 -> 0 | L17: =SUM(K17-J17) -> 0 | M17: =H17 -> 44575 | P17: ='Water-Meter'!J19 -> 8998 | Q17: =N17-O16 -> 0 | R17: =SUM(Q17/1615) -> 0 | S17: =Gen!U24 -> 3795 | T17: =M17 -> 44575 | V17: =W16 -> 8842.1 | W17: 8844.6 | X17: =(W17-V17)*200 -> 500 | Y17: =T17 -> 44575 | AA17: =AB16 -> 23070 | AB17: ='Water-Meter'!P19 -> 23078 | AC17: =AB17-AA17 -> 8
A18: =Gen!C25 -> 0.16 | B18: =Gen!B25 -> 44576 | D18: =E18 -> 9849.8 | E18: 9849.8 | F18: =SUM(E19-D18)*120 -> 276 | H18: =B18 -> 44576 | J18: ='Water-Meter'!G20 -> 0 | K18: ='Water-Meter'!G20 -> 0 | L18: =SUM(K18-J18) -> 0 | M18: =H18 -> 44576 | P18: ='Water-Meter'!J20 -> 9000 | Q18: =N18-O17 -> 0 | R18: =SUM(Q18/1615) -> 0 | S18: =Gen!U25 -> 3648 | T18: =M18 -> 44576 | V18: =W17 -> 8844.6 | W18: 8847.5 | X18: =(W18-V18)*200 -> 580 | Y18: =T18 -> 44576 | AA18: =AB17 -> 23078 | AB18: ='Water-Meter'!P20 -> 23088 | AC18: =AB18-AA18 -> 10
A19: =Gen!C26 -> 0.18 | B19: =Gen!B26 -> 44577 | D19: =E19 -> 9852.1 | E19: 9852.1 | F19: =SUM(E20-D19)*120 -> 252 | H19: =B19 -> 44577 | J19: ='Water-Meter'!G21 -> 0 | K19: ='Water-Meter'!G21 -> 0 | L19: =SUM(K19-J19) -> 0 | M19: =H19 -> 44577 | P19: ='Water-Meter'!J21 -> 9002 | Q19: =N19-O18 -> 0 | R19: =SUM(Q19/1615) -> 0 | S19: =Gen!U26 -> 3393 | T19: =M19 -> 44577 | V19: =W18 -> 8847.5 | W19: 8850.1 | X19: =(W19-V19)*200 -> 520 | Y19: =T19 -> 44577 | AA19: =AB18 -> 23088 | AB19: ='Water-Meter'!P21 -> 23096 | AC19: =AB19-AA19 -> 8
A20: =Gen!C27 -> 0.09 | B20: =Gen!B27 -> 44578 | D20: =E20 -> 9854.2 | E20: 9854.2 | F20: =SUM(E21-D20)*120 -> 204 | H20: =B20 -> 44578 | J20: ='Water-Meter'!G22 -> 0 | K20: ='Water-Meter'!G22 -> 0 | L20: =SUM(K20-J20) -> 0 | M20: =H20 -> 44578 | P20: ='Water-Meter'!J22 -> 9004 | Q20: =N20-O19 -> 0 | R20: =SUM(Q20/1615) -> 0 | S20: =Gen!U27 -> 2977 | T20: =M20 -> 44578 | V20: =W19 -> 8850.1 | W20: 8853.1 | X20: =(W20-V20)*200 -> 600 | Y20: =T20 -> 44578 | AA20: =AB19 -> 23096 | AB20: ='Water-Meter'!P22 -> 23103 | AC20: =AB20-AA20 -> 7
A21: =Gen!C28 -> 0.16 | B21: =Gen!B28 -> 44579 | D21: =E21 -> 9855.9 | E21: 9855.9 | F21: =SUM(E22-D21)*120 -> 276 | H21: =B21 -> 44579 | J21: ='Water-Meter'!G23 -> 0 | K21: ='Water-Meter'!G23 -> 0 | L21: =SUM(K21-J21) -> 0 | M21: =H21 -> 44579 | P21: ='Water-Meter'!J23 -> 9006 | Q21: =N21-O20 -> 0 | R21: =SUM(Q21/1615) -> 0 | S21: =Gen!U28 -> 3443 | T21: =M21 -> 44579 | V21: =W20 -> 8853.1 | W21: 8855.8 | X21: =(W21-V21)*200 -> 540 | Y21: =T21 -> 44579 | AA21: =AB20 -> 23103 | AB21: ='Water-Meter'!P23 -> 23111 | AC21: =AB21-AA21 -> 8
A22: =Gen!C29 -> 0.18 | B22: =Gen!B29 -> 44580 | D22: =E22 -> 9858.2 | E22: 9858.2 | F22: =SUM(E23-D22)*120 -> 192 | H22: =B22 -> 44580 | J22: ='Water-Meter'!G24 -> 0 | K22: ='Water-Meter'!G24 -> 0 | L22: =SUM(K22-J22) -> 0 | M22: =H22 -> 44580 | P22: ='Water-Meter'!J22 -> 9004 | Q22: =N22-O21 -> 0 | R22: =SUM(Q22/1615) -> 0 | S22: =Gen!U29 -> 3010 | T22: =M22 -> 44580 | V22: =W21 -> 8855.8 | W22: 8858.4 | X22: =(W22-V22)*200 -> 520 | Y22: =T22 -> 44580 | AA22: =AB21 -> 23111 | AB22: ='Water-Meter'!P24 -> 23117 | AC22: =AB22-AA22 -> 6
A23: =Gen!C30 -> 0.21 | B23: =Gen!B30 -> 44581 | D23: =E23 -> 9859.8 | E23: 9859.8 | F23: =SUM(E24-D23)*120 -> 240 | H23: =B23 -> 44581 | J23: ='Water-Meter'!G25 -> 0 | K23: ='Water-Meter'!G26 -> 0 | L23: =SUM(K23-J23) -> 0 | M23: =H23 -> 44581 | P23: ='Water-Meter'!J25 -> 9010 | Q23: =N23-O22 -> 0 | R23: =SUM(Q23/1615) -> 0 | S23: =Gen!U30 -> 3323 | T23: =M23 -> 44581 | V23: =W22 -> 8858.4 | W23: 8860.9 | X23: =(W23-V23)*200 -> 500 | Y23: =T23 -> 44581 | AA23: =AB22 -> 23117 | AB23: ='Water-Meter'!P25 -> 23124 | AC23: =AB23-AA23 -> 7
A24: =Gen!C31 -> 0.09 | B24: =Gen!B31 -> 44582 | D24: =E24 -> 9861.8 | E24: 9861.8 | F24: =SUM(E25-D24)*120 -> 228 | H24: =B24 -> 44582 | J24: ='Water-Meter'!G26 -> 0 | K24: ='Water-Meter'!G27 -> 0 | L24: =SUM(K24-J24) -> 0 | M24: =H24 -> 44582 | P24: ='Water-Meter'!J26 -> 9012 | Q24: =N24-O23 -> 0 | R24: =SUM(Q24/1615) -> 0 | S24: =Gen!U31 -> 3113 | T24: =M24 -> 44582 | V24: =W23 -> 8860.9 | W24: 8863.5 | X24: =(W24-V24)*200 -> 520 | Y24: =T24 -> 44582 | AA24: =AB23 -> 23124 | AB24: ='Water-Meter'!P26 -> 23132 | AC24: =AB24-AA24 -> 8
A25: =Gen!C32 -> 0.08 | B25: =Gen!B32 -> 44583 | E25: 9863.7 | F25: =SUM(E26-D25)*120 -> 1183860 | H25: =B25 -> 44583 | J25: ='Water-Meter'!G27 -> 0 | K25: ='Water-Meter'!G28 -> 0 | L25: =SUM(K25-J25) -> 0 | M25: =H25 -> 44583 | P25: ='Water-Meter'!J27 -> 9014 | Q25: =N25-O24 -> 0 | R25: =SUM(Q25/1615) -> 0 | S25: =Gen!U32 -> 3124 | T25: =M25 -> 44583 | V25: =W24 -> 8863.5 | W25: 8865.8 | X25: =(W25-V25)*200 -> 460 | Y25: =T25 -> 44583 | AA25: =AB24 -> 23132 | AB25: ='Water-Meter'!P27 -> 23136 | AC25: =AB25-AA25 -> 4
A26: =Gen!C33 -> 0.04 | B26: =Gen!B33 -> 44584 | D26: =E26 -> 9865.5 | E26: 9865.5 | F26: =SUM(E27-D26)*120 -> 204 | H26: =B26 -> 44584 | J26: ='Water-Meter'!G28 -> 0 | K26: ='Water-Meter'!G29 -> 0 | L26: =SUM(K26-J26) -> 0 | M26: =H26 -> 44584 | P26: ='Water-Meter'!J28 -> 9016 | Q26: =N26-O25 -> 0 | R26: =SUM(Q26/1615) -> 0 | S26: =Gen!U33 -> 2797 | T26: =M26 -> 44584 | V26: =W25 -> 8865.8 | W26: 8867.8 | X26: =(W26-V26)*200 -> 400 | Y26: =T26 -> 44584 | AA26: =AB25 -> 23136 | AB26: ='Water-Meter'!P28 -> 23139 | AC26: =AB26-AA26 -> 3
A27: =Gen!C34 -> 0.1 | B27: =Gen!B34 -> 44585 | D27: =E27 -> 9867.2 | E27: 9867.2 | F27: =SUM(E28-D27)*120 -> 240 | H27: =B27 -> 44585 | J27: ='Water-Meter'!G29 -> 0 | K27: ='Water-Meter'!G30 -> 0 | L27: =SUM(K27-J27) -> 0 | M27: =H27 -> 44585 | P27: ='Water-Meter'!J29 -> 9019 | Q27: =N27-O26 -> 0 | R27: =SUM(Q27/1615) -> 0 | S27: =Gen!U34 -> 3295 | T27: =M27 -> 44585 | V27: =W26 -> 8867.8 | W27: 8870.2 | X27: =(W27-V27)*200 -> 480 | Y27: =T27 -> 44585 | AA27: =AB26 -> 23139 | AB27: ='Water-Meter'!P29 -> 23148 | AC27: =AB27-AA27 -> 9
A28: =Gen!C35 -> 0.14 | B28: =Gen!B35 -> 44586 | D28: =E28 -> 9869.2 | E28: 9869.2 | F28: =SUM(E29-D28)*120 -> 264 | H28: =B28 -> 44586 | J28: ='Water-Meter'!G30 -> 0 | K28: ='Water-Meter'!G31 -> 0 | L28: =SUM(K28-J28) -> 0 | M28: =H28 -> 44586 | P28: ='Water-Meter'!J30 -> 9021 | Q28: =N28-O27 -> 0 | R28: =SUM(Q28/1615) -> 0 | S28: =Gen!U35 -> 3205 | T28: =M28 -> 44586 | V28: =W14 -> 8836.9 | W28: 8871.9 | X28: =(W28-V28)*200 -> 7000 | Y28: =T28 -> 44586 | AA28: =AB27 -> 23148 | AB28: ='Water-Meter'!P30 -> 23155 | AC28: =AB28-AA28 -> 7
A29: =Gen!C36 -> 0.16 | B29: =Gen!B36 -> 44587 | D29: =E29 -> 9871.4 | E29: 9871.4 | F29: =SUM(E30-D29)*120 -> 264 | H29: =B29 -> 44587 | J29: ='Water-Meter'!G31 -> 0 | K29: ='Water-Meter'!G32 -> 0 | L29: =SUM(K29-J29) -> 0 | M29: =H29 -> 44587 | P29: ='Water-Meter'!J31 -> 9023 | Q29: =N29-O28 -> 0 | R29: =SUM(Q29/1615) -> 0 | S29: =Gen!U36 -> 3575 | T29: =M29 -> 44587 | V29: =W28 -> 8871.9 | W29: 8874.3 | X29: =(W29-V29)*200 -> 480 | Y29: =T29 -> 44587 | AA29: =AB28 -> 23155 | AB29: ='Water-Meter'!P31 -> 23160 | AC29: =AB29-AA29 -> 5
A30: =Gen!C37 -> 0.13 | B30: =Gen!B37 -> 44588 | D30: =E30 -> 9873.6 | E30: 9873.6 | F30: =SUM(E31-D30)*120 -> 228 | H30: =B30 -> 44588 | J30: ='Water-Meter'!G32 -> 0 | K30: ='Water-Meter'!G33 -> 0 | L30: =SUM(K30-J30) -> 0 | M30: =H30 -> 44588 | P30: ='Water-Meter'!J32 -> 9025 | Q30: =N30-O29 -> 0 | R30: =SUM(Q30/1615) -> 0 | S30: =Gen!U37 -> 3610 | T30: =M30 -> 44588 | V30: =W29 -> 8874.3 | W30: 8876.9 | X30: =(W30-V30)*200 -> 520 | Y30: =T30 -> 44588 | AA30: =AB29 -> 23160 | AB30: ='Water-Meter'!P32 -> 23166 | AC30: =AB30-AA30 -> 6
A31: =Gen!C38 -> 0.09 | B31: =Gen!B38 -> 44589 | D31: =E31 -> 9875.5 | E31: 9875.5 | F31: =SUM(E32-D31)*120 -> 264 | H31: =B31 -> 44589 | J31: ='Water-Meter'!G33 -> 0 | K31: ='Water-Meter'!G34 -> 0 | L31: =SUM(K31-J31) -> 0 | M31: =H31 -> 44589 | P31: ='Water-Meter'!J33 -> 9027 | Q31: =N31-O30 -> 0 | R31: =SUM(Q31/1615) -> 0 | S31: =Gen!U38 -> 3593 | T31: =M31 -> 44589 | V31: =W30 -> 8876.9 | W31: 8879.3 | X31: =(W31-V31)*200 -> 480 | Y31: =T31 -> 44589 | AA31: =AB30 -> 23166 | AB31: ='Water-Meter'!P33 -> 23171 | AC31: =AB31-AA31 -> 5
A32: =Gen!C39 -> 0.09 | B32: =Gen!B39 -> 44590 | D32: =E32 -> 9877.7 | E32: 9877.7 | F32: =SUM(E33-D32)*120 -> 264 | H32: =B32 -> 44590 | J32: ='Water-Meter'!G34 -> 0 | K32: ='Water-Meter'!G34 -> 0 | L32: =SUM(K32-J32) -> 0 | M32: =H32 -> 44590 | P32: ='Water-Meter'!J34 -> 9033 | Q32: =N32-O31 -> 0 | R32: =SUM(Q32/1615) -> 0 | S32: =Gen!U39 -> 3589 | T32: =M32 -> 44590 | V32: =W31 -> 8879.3 | W32: 8882.1 | X32: =(W32-V32)*200 -> 560 | Y32: =T32 -> 44590 | AA32: =AB31 -> 23171 | AB32: ='Water-Meter'!P34 -> 23177 | AC32: =AB32-AA32 -> 6
A33: =Gen!C40 -> 0.06 | B33: =Gen!B40 -> 44591 | D33: =E33 -> 9879.9 | E33: 9879.9 | F33: =SUM(E34-D33)*120 -> 216 | H33: =B33 -> 44591 | J33: ='Water-Meter'!G35 -> 0 | K33: ='Water-Meter'!G35 -> 0 | L33: =SUM(K33-J33) -> 0 | M33: =H33 -> 44591 | P33: ='Water-Meter'!J35 -> 9036 | Q33: =N33-O32 -> 0 | R33: =SUM(Q33/1615) -> 0 | S33: =Gen!U40 -> 3575 | T33: =M33 -> 44591 | V33: =W32 -> 8882.1 | W33: 8884.1 | X33: =(W33-V33)*200 -> 400 | Y33: =T33 -> 44591 | AA33: =AB32 -> 23177 | AB33: ='Water-Meter'!P35 -> 23185 | AC33: =AB33-AA33 -> 8
A34: =Gen!C41 -> 0.05 | B34: =Gen!B41 -> 44592 | D34: =E34 -> 9881.7 | E34: 9881.7 | F34: =SUM(E35-D34)*120 -> 180 | H34: =E30 -> 9873.6 | J34: ='Water-Meter'!G36 -> 0 | K34: ='Water-Meter'!G36 -> 0 | L34: =SUM(K34-J34) -> 0 | M34: =H34 -> 9873.6 | P34: ='Water-Meter'!J36 -> 9039 | Q34: =N34-O33 -> 0 | R34: =SUM(Q34/1615) -> 0 | S34: =Gen!U41 -> 3272 | T34: =M34 -> 9873.6 | V34: =SUM(W33) -> 8884.1 | W34: 8886.4 | X34: =(W34-V34)*200 -> 460 | Y34: =T34 -> 9873.6 | AA34: =AB33 -> 23185 | AB34: ='Water-Meter'!P36 -> 23194 | AC34: =AA34-AB33 -> 0
A35: #REF! | B35: =Gen!B42 -> 0 | D35: =E35 -> 9883.2 | E35: 9883.2 | F35: =SUM(E36-D35)*120 -> -1185984 | H35: =E31 -> 9875.5 | J35: =SUM(K34) -> 0 | K35: ='Water-Meter'!G37 -> 0 | L35: =SUM(L5:L34) -> 0 | M35: =H35 -> 9875.5 | P35: ='Water-Meter'!J37 -> 0 | Q35: =N35-O34 -> 0 | R35: =SUM(Q35/1615) -> 0 | S35: =Gen!U42 -> 0 | T35: =M35 -> 9875.5 | V35: =SUM(W34) -> 8886.4 | X35: =(W35-V35)*200 -> -1777280 | Y35: =T35 -> 9875.5 | AB35: ='Water-Meter'!P37 -> 0 | AC35: =AA35-AB34 -> -23194

Sheet Utility summery
A4: Date | B4: Room Occupied | C4: Electricity Units Generated KW | D4: Diseal | G4: Water | J4: Gas | N4: Cost of utilites
D5: Generator | E5: Transport | F5: Total | G5: RO | H5: STP | I5: Total Consumption | J5: 2 ton | K5: 1 Ton | L5: 1 Ton | M5: Total consumption | N5: Electricity /1.4$/liter | O5: Diseal for Transport | P5: Gas /2.38$/Kg | Q5: Total HLP Cost | R5: Electricity Cost/Room $ | S5: cost/Room $
A6: =Gen!B11 -> 44562 | B6: ='Utility report '!B6 -> 34 | C6: =Gen!V11 -> 0.41514575 | D6: =Gen!T11 -> 1965.3 | E6: =Gen!AK11 -> 320.11 | F6: =Gen!AT11 -> 0 | G6: ='Utility report '!AC6 -> 102 | H6: ='Utility report '!AE6 -> 56 | I6: ='Water-Meter'!E6 -> 116 | J6: ='Lpg (2)'!B10 -> 50 | K6: ='Lpg (2)'!C10 -> 0 | L6: ='Lpg (2)'!D10 -> 0 | M6: ='Lpg (2)'!G10 -> 144.452 | N6: =D6*1.4 -> 2751.42 | O6: =E6*1.4 -> 448.154 | P6: =('Lpg (2)'!G10)*2.38 -> 343.79576 | Q6: =N6+O6+P6 -> 3543.3698 | R6: =N6/B6 -> 80.924118 | S6: =Q6/B6 -> 104.21676
A7: =Gen!B12 -> 44563 | B7: ='Utility report '!B7 -> 42 | C7: =Gen!V12 -> 0.42232742 | D7: =Gen!T12 -> 1927.08 | E7: =Gen!AK12 -> 237.31 | F7: =Gen!AT12 -> 0 | G7: ='Utility report '!AC7 -> 64 | H7: ='Utility report '!AE7 -> 55 | I7: ='Water-Meter'!E7 -> 94 | J7: ='Lpg (2)'!B11 -> 45 | K7: ='Lpg (2)'!C11 -> 0 | L7: ='Lpg (2)'!D11 -> 0 | M7: ='Lpg (2)'!G11 -> 150.7 | N7: =D7*1.4 -> 2697.912 | O7: =E7*1.4 -> 332.234 | P7: =('Lpg (2)'!G11)*2.38 -> 358.666 | Q7: =N7+O7+P7 -> 3388.812 | R7: =N7/B7 -> 64.236 | S7: =Q7/B7 -> 80.686
A8: =Gen!B13 -> 44564 | B8: ='Utility report '!B8 -> 29 | C8: =Gen!V13 -> 0.40662877 | D8: =Gen!T13 -> 1859.92 | E8: =Gen!AK13 -> 231 | F8: =Gen!AT13 -> 0 | G8: ='Utility report '!AC8 -> 105 | H8: ='Utility report '!AE8 -> 56 | I8: ='Water-Meter'!E8 -> 110 | J8: ='Lpg (2)'!B12 -> 41 | K8: ='Lpg (2)'!C12 -> 0 | L8: ='Lpg (2)'!D12 -> 0 | M8: ='Lpg (2)'!G12 -> 156.948 | N8: =D8*1.4 -> 2603.888 | O8: =E8*1.4 -> 323.4 | P8: =('Lpg (2)'!G12)*2.38 -> 373.53624 | Q8: =N8+O8+P8 -> 3300.8242 | R8: =N8/B8 -> 89.789241 | S8: =Q8/B8 -> 113.82153
A9: =Gen!B14 -> 44565 | B9: ='Utility report '!B9 -> 28 | C9: =Gen!V14 -> 0.43481362 | D9: =Gen!T14 -> 1889.7 | E9: =Gen!AK14 -> 247.48 | F9: =Gen!AT14 -> 0 | G9: ='Utility report '!AC9 -> 147 | H9: ='Utility report '!AE9 -> 59 | I9: ='Water-Meter'!E9 -> 94 | J9: ='Lpg (2)'!B13 -> 40 | K9: ='Lpg (2)'!C13 -> 0 | L9: ='Lpg (2)'!D13 -> 0 | M9: ='Lpg (2)'!G13 -> 132.088 | N9: =D9*1.4 -> 2645.58 | O9: =E9*1.4 -> 346.472 | P9: =('Lpg (2)'!G13)*2.38 -> 314.36944 | Q9: =N9+O9+P9 -> 3306.4214 | R9: =N9/B9 -> 94.485 | S9: =Q9/B9 -> 118.08648
A10: =Gen!B15 -> 44566 | B10: ='Utility report '!B10 -> 21 | C10: =Gen!V15 -> 0.43244898 | D10: =Gen!T15 -> 1716.39 | E10: =Gen!AK15 -> 110 | F10: =Gen!AT15 -> 0 | G10: ='Utility report '!AC10 -> 0 | H10: ='Utility report '!AE10 -> 49 | I10: ='Water-Meter'!E10 -> 86 | J10: ='Lpg (2)'!B14 -> 38 | K10: ='Lpg (2)'!C14 -> 0 | L10: ='Lpg (2)'!D14 -> 0 | M10: ='Lpg (2)'!G14 -> 122.188 | N10: =D10*1.4 -> 2402.946 | O10: =E10*1.4 -> 154 | P10: =('Lpg (2)'!G14)*2.38 -> 290.80744 | Q10: =N10+O10+P10 -> 2847.7534 | R10: =N10/B10 -> 114.426 | S10: =Q10/B10 -> 135.60731
A11: =Gen!B16 -> 44567 | B11: ='Utility report '!B11 -> 25 | C11: =Gen!V16 -> 0.42292486 | D11: =Gen!T16 -> 1829.15 | E11: 0 | F11: =Gen!AT16 -> 0 | G11: ='Utility report '!AC11 -> 148 | H11: ='Utility report '!AE11 -> 54 | I11: ='Water-Meter'!E11 -> 90 | J11: ='Lpg (2)'!B15 -> 72 | K11: ='Lpg (2)'!C15 -> 85 | L11: ='Lpg (2)'!D15 -> 85 | M11: ='Lpg (2)'!G15 -> 137.72 | N11: =D11*1.4 -> 2560.81 | O11: =E11*1.4 -> 0 | P11: =('Lpg (2)'!G15)*2.38 -> 327.7736 | Q11: =N11+O11+P11 -> 2888.5836 | R11: =N11/B11 -> 102.4324 | S11: =Q11/B11 -> 115.54334
A12: =Gen!B17 -> 44568 | B12: ='Utility report '!B12 -> 20 | C12: =Gen!V17 -> 0.41997075 | D12: =Gen!T17 -> 1866.35 | E12: =Gen!AK17 -> 133 | F12: =Gen!AT17 -> 0 | G12: ='Utility report '!AC12 -> -22473 | H12: ='Utility report '!AE12 -> -229207 | I12: ='Water-Meter'!E12 -> 92 | J12: ='Lpg (2)'!B16 -> 70 | K12: ='Lpg (2)'!C16 -> 85 | L12: ='Lpg (2)'!D16 -> 85 | M12: ='Lpg (2)'!G16 -> 132.88 | N12: =D12*1.4 -> 2612.89 | O12: =E12*1.4 -> 186.2 | P12: =('Lpg (2)'!G16)*2.38 -> 316.2544 | Q12: =N12+O12+P12 -> 3115.3444 | R12: =N12/B12 -> 130.6445 | S12: =Q12/B12 -> 155.76722
A13: =Gen!B18 -> 44569 | B13: ='Utility report '!B13 -> 19 | C13: =Gen!V18 -> 0.41184805 | D13: =Gen!T18 -> 1767.24 | E13: =Gen!AK18 -> 162.47 | F13: =Gen!AT18 -> 0 | G13: ='Utility report '!AC13 -> 22575 | H13: ='Utility report '!AE13 -> 229265 | I13: ='Water-Meter'!E13 -> 108 | J13: ='Lpg (2)'!B17 -> 70 | K13: ='Lpg (2)'!C17 -> 85 | L13: ='Lpg (2)'!D17 -> 85 | M13: ='Lpg (2)'!G17 -> 112.024 | N13: =D13*1.4 -> 2474.136 | O13: =E13*1.4 -> 227.458 | P13: =('Lpg (2)'!G17)*2.38 -> 266.61712 | Q13: =N13+O13+P13 -> 2968.2111 | R13: =N13/B13 -> 130.21768 | S13: =Q13/B13 -> 156.22164
A14: =Gen!B19 -> 44570 | B14: ='Utility report '!B14 -> 17 | C14: =Gen!V19 -> 0.42574954 | D14: =Gen!T19 -> 1846.05 | E14: =Gen!AK19 -> 109.74 | F14: =Gen!AT19 -> 0 | G14: ='Utility report '!AC14 -> 128 | H14: ='Utility report '!AE14 -> 56 | I14: ='Water-Meter'!E14 -> 101 | J14: ='Lpg (2)'!B18 -> 65 | K14: ='Lpg (2)'!C18 -> 85 | L14: ='Lpg (2)'!D18 -> 85 | M14: ='Lpg (2)'!G18 -> 106.084 | N14: =D14*1.4 -> 2584.47 | O14: =E14*1.4 -> 153.636 | P14: =('Lpg (2)'!G18)*2.38 -> 252.47992 | Q14: =N14+O14+P14 -> 2990.5859 | R14: =N14/B14 -> 152.02765 | S14: =Q14/B14 -> 175.91682
A15: =Gen!B20 -> 44571 | B15: ='Utility report '!B15 -> 16 | C15: =Gen!V20 -> 0.41262678 | D15: =Gen!T20 -> 1765.63 | E15: =Gen!AK20 -> 79.83 | F15: =Gen!AT20 -> 0 | G15: ='Utility report '!AC15 -> 77 | H15: ='Utility report '!AE15 -> 3 | I15: ='Water-Meter'!E15 -> 83 | J15: ='Lpg (2)'!B19 -> 62 | K15: ='Lpg (2)'!C19 -> 85 | L15: ='Lpg (2)'!D19 -> 85 | M15: ='Lpg (2)'!G19 -> 113.784 | N15: =D15*1.4 -> 2471.882 | O15: =E15*1.4 -> 111.762 | P15: =('Lpg (2)'!G19)*2.38 -> 270.80592 | Q15: =N15+O15+P15 -> 2854.4499 | R15: =N15/B15 -> 154.49263 | S15: =Q15/B15 -> 178.40312
A16: =Gen!B21 -> 44572 | B16: ='Utility report '!B16 -> 11 | C16: =Gen!V21 -> 0.42083894 | D16: =Gen!T21 -> 1625.28 | E16: =Gen!AK21 -> 386.46 | F16: =Gen!AT9 -> 0 | G16: ='Utility report '!AC16 -> 114 | H16: ='Utility report '!AE16 -> 3 | I16: ='Water-Meter'!E16 -> 67 | J16: ='Lpg (2)'!B20 -> 60 | K16: ='Lpg (2)'!C20 -> 58 | L16: ='Lpg (2)'!D20 -> 85 | M16: ='Lpg (2)'!G20 -> 116.908 | N16: =D16*1.4 -> 2275.392 | O16: =E16*1.4 -> 541.044 | P16: =('Lpg (2)'!G20)*2.38 -> 278.24104 | Q16: =N16+O16+P16 -> 3094.677 | R16: =N16/B16 -> 206.85382 | S16: =Q16/B16 -> 281.33428
A17: =Gen!B22 -> 44573 | B17: ='Utility report '!B17 -> 8 | C17: =Gen!V22 -> 0.42066001 | D17: =Gen!T22 -> 1599.77 | E17: =Gen!AK22 -> 0 | F17: =Gen!AT22 -> 0 | G17: ='Utility report '!AC17 -> 112 | H17: ='Utility report '!AE17 -> 0 | I17: ='Water-Meter'!E17 -> 133 | J17: ='Lpg (2)'!B21 -> 58 | K17: ='Lpg (2)'!C22 -> 85 | L17: ='Lpg (2)'!D21 -> 85 | M17: ='Lpg (2)'!G21 -> 99.484 | N17: =D17*1.4 -> 2239.678 | O17: =E17*1.4 -> 0 | P17: =('Lpg (2)'!G21)*2.38 -> 236.77192 | Q17: =N17+O17+P17 -> 2476.4499 | R17: =N17/B17 -> 279.95975 | S17: =Q17/B17 -> 309.55624
A18: =Gen!B23 -> 44574 | B18: ='Utility report '!B18 -> 13 | C18: =Gen!V23 -> 0.41318257 | D18: =Gen!T23 -> 1507.29 | E18: =Gen!AK23 -> 66.31 | F18: =Gen!AT23 -> 0 | G18: ='Utility report '!AC18 -> 111 | H18: ='Utility report '!AE18 -> 0 | I18: ='Water-Meter'!E18 -> 86 | J18: ='Lpg (2)'!B22 -> 55 | K18: ='Lpg (2)'!C23 -> 85 | L18: ='Lpg (2)'!D22 -> 85 | M18: ='Lpg (2)'!G22 -> 90.904 | N18: =D18*1.4 -> 2110.206 | O18: =E18*1.4 -> 92.834 | P18: =('Lpg (2)'!G22)*2.38 -> 216.35152 | Q18: =N18+O18+P18 -> 2419.3915 | R18: =N18/B18 -> 162.32354 | S18: =Q18/B18 -> 186.10704
A19: =Gen!B24 -> 44575 | B19: ='Utility report '!B19 -> 17 | C19: =Gen!V24 -> 0.39839789 | D19: =Gen!T24 -> 1511.92 | E19: =Gen!AK24 -> 288.08 | F19: =Gen!AT24 -> 0 | G19: ='Utility report '!AC19 -> 92 | H19: ='Utility report '!AE19 -> 43 | I19: ='Water-Meter'!E19 -> 92 | J19: ='Lpg (2)'!B23 -> 52 | K19: ='Lpg (2)'!C24 -> 85 | L19: ='Lpg (2)'!D23 -> 85 | M19: ='Lpg (2)'!G23 -> 73.568 | N19: =D19*1.4 -> 2116.688 | O19: =E19*1.4 -> 403.312 | P19: =('Lpg (2)'!G23)*2.38 -> 175.09184 | Q19: =N19+O19+P19 -> 2695.0918 | R19: =N19/B19 -> 124.51106 | S19: =Q19/B19 -> 158.53481
A20: =Gen!B25 -> 44576 | B20: ='Utility report '!B20 -> 15 | C20: =Gen!V25 -> 0.39528509 | D20: =Gen!T25 -> 1442 | E20: =Gen!AK25 -> 0 | F20: =Gen!AT25 -> 0 | G20: ='Utility report '!AC20 -> 58 | H20: ='Utility report '!AE20 -> 26 | I20: ='Water-Meter'!E20 -> 102 | J20: ='Lpg (2)'!B24 -> 50 | K20: ='Lpg (2)'!C25 -> 85 | L20: ='Lpg (2)'!D24 -> 85 | M20: ='Lpg (2)'!G24 -> 74.316 | N20: =D20*1.4 -> 2018.8 | O20: =E20*1.4 -> 0 | P20: =('Lpg (2)'!G24)*2.38 -> 176.87208 | Q20: =N20+O20+P20 -> 2195.6721 | R20: =N20/B20 -> 134.58667 | S20: =Q20/B20 -> 146.37814
A21: =Gen!B26 -> 44577 | B21: ='Utility report '!B21 -> 17 | C21: =Gen!V26 -> 0.39916888 | D21: =Gen!T26 -> 1354.38 | E21: =Gen!AK26 -> 447 | F21: =Gen!AT26 -> 0 | G21: ='Utility report '!AC21 -> 91 | H21: ='Utility report '!AE21 -> 63 | I21: ='Water-Meter'!E21 -> 74 | J21: ='Lpg (2)'!B25 -> 47 | K21: ='Lpg (2)'!C25 -> 85 | L21: ='Lpg (2)'!D25 -> 85 | M21: ='Lpg (2)'!G25 -> 109.604 | N21: =D21*1.4 -> 1896.132 | O21: =E21*1.4 -> 625.8 | P21: =('Lpg (2)'!G25)*2.38 -> 260.85752 | Q21: =N21+O21+P21 -> 2782.7895 | R21: =N21/B21 -> 111.53718 | S21: =Q21/B21 -> 163.6935
A22: =Gen!B27 -> 44578 | B22: ='Utility report '!B22 -> 10 | C22: =Gen!V27 -> 0.40996641 | D22: =Gen!T27 -> 1220.47 | E22: =Gen!AK27 -> 0 | F22: =Gen!AT27 -> 0 | G22: ='Utility report '!AC22 -> 78 | H22: ='Utility report '!AE22 -> 36 | I22: ='Water-Meter'!E22 -> 68 | J22: ='Lpg (2)'!B26 -> 44 | K22: ='Lpg (2)'!C26 -> 85 | L22: ='Lpg (2)'!D26 -> 85 | M22: ='Lpg (2)'!G26 -> 108.9 | N22: =D22*1.4 -> 1708.658 | O22: =E22*1.4 -> 0 | P22: =('Lpg (2)'!G26)*2.38 -> 259.182 | Q22: =N22+O22+P22 -> 1967.84 | R22: =N22/B22 -> 170.8658 | S22: =Q22/B22 -> 196.784
A23: =Gen!B28 -> 44579 | B23: ='Utility report '!B23 -> 14 | C23: =Gen!V28 -> 0.40158002 | D23: =Gen!T28 -> 1382.64 | E23: =Gen!AK28 -> 221.01 | F23: =Gen!AT28 -> 0 | G23: ='Utility report '!AC23 -> 0 | H23: ='Utility report '!AE23 -> 0 | I23: ='Water-Meter'!E23 -> 62 | J23: ='Lpg (2)'!B27 -> 41 | K23: ='Lpg (2)'!C27 -> 85 | L23: ='Lpg (2)'!D27 -> 85 | M23: ='Lpg (2)'!G27 -> 98.824 | N23: =D23*1.4 -> 1935.696 | O23: =E23*1.4 -> 309.414 | P23: =('Lpg (2)'!G27)*2.38 -> 235.20112 | Q23: =N23+O23+P23 -> 2480.3111 | R23: =N23/B23 -> 138.264 | S23: =Q23/B23 -> 177.16508
A24: =Gen!B29 -> 44580 | B24: ='Utility report '!B24 -> 15 | C24: =Gen!V29 -> 0.41618272 | D24: =Gen!T29 -> 1252.71 | E24: =Gen!AK29 -> 127.84 | F24: =Gen!AT29 -> 0 | G24: ='Utility report '!AC24 -> 144 | H24: ='Utility report '!AE24 -> 1 | I24: ='Water-Meter'!E24 -> 70 | J24: ='Lpg (2)'!B28 -> 38 | K24: ='Lpg (2)'!C28 -> 85 | L24: ='Lpg (2)'!D28 -> 85 | M24: ='Lpg (2)'!G28 -> 113.828 | N24: =D24*1.4 -> 1753.794 | O24: =E24*1.4 -> 178.976 | P24: =('Lpg (2)'!G28)*2.38 -> 270.91064 | Q24: =N24+O24+P24 -> 2203.6806 | R24: =N24/B24 -> 116.9196 | S24: =Q24/B24 -> 146.91204
A25: =Gen!B30 -> 44581 | B25: ='Utility report '!B25 -> 17 | C25: =Gen!V30 -> 0.41241348 | D25: =Gen!T30 -> 1370.45 | E25: =Gen!AK30 -> 238.02 | F25: =Gen!AT30 -> 0 | G25: ='Utility report '!AC25 -> 45 | H25: ='Utility report '!AE25 -> 0 | I25: ='Water-Meter'!E25 -> 88 | J25: ='Lpg (2)'!B29 -> 37 | K25: ='Lpg (2)'!C29 -> 85 | L25: ='Lpg (2)'!D29 -> 85 | M25: ='Lpg (2)'!G29 -> 115.148 | N25: =D25*1.4 -> 1918.63 | O25: =E25*1.4 -> 333.228 | P25: =('Lpg (2)'!G29)*2.38 -> 274.05224 | Q25: =N25+O25+P25 -> 2525.9102 | R25: =N25/B25 -> 112.86059 | S25: =Q25/B25 -> 148.58296
A26: =Gen!B31 -> 44582 | B26: ='Utility report '!B26 -> 8 | C26: =Gen!V31 -> 0.41127851 | D26: =Gen!T31 -> 1280.31 | E26: =Gen!AK31 -> 15 | F26: =Gen!AT31 -> 0 | G26: ='Utility report '!AC26 -> 139 | H26: ='Utility report '!AE26 -> 30 | I26: ='Water-Meter'!E26 -> 81 | J26: ='Lpg (2)'!B30 -> 36 | K26: ='Lpg (2)'!C30 -> 85 | L26: ='Lpg (2)'!D30 -> 85 | M26: ='Lpg (2)'!G30 -> 113.828 | N26: =D26*1.4 -> 1792.434 | O26: =E26*1.4 -> 21 | P26: =('Lpg (2)'!G30)*2.38 -> 270.91064 | Q26: =N26+O26+P26 -> 2084.3446 | R26: =N26/B26 -> 224.05425 | S26: =Q26/B26 -> 260.54308
A27: =Gen!B32 -> 44583 | B27: ='Utility report '!B27 -> 7 | C27: =Gen!V32 -> 0.41173496 | D27: =Gen!T32 -> 1286.26 | E27: =Gen!AK32 -> 264.82 | F27: =Gen!AT32 -> 0 | G27: ='Utility report '!AC27 -> 100 | H27: ='Utility report '!AE27 -> 43 | I27: ='Water-Meter'!E27 -> 71 | J27: ='Lpg (2)'!B31 -> 34 | K27: ='Lpg (2)'!C31 -> 85 | L27: ='Lpg (2)'!D31 -> 85 | M27: ='Lpg (2)'!G31 -> 96.712 | N27: =D27*1.4 -> 1800.764 | O27: =E27*1.4 -> 370.748 | P27: =('Lpg (2)'!G31)*2.38 -> 230.17456 | Q27: =N27+O27+P27 -> 2401.6866 | R27: =N27/B27 -> 257.252 | S27: =Q27/B27 -> 343.09808
A28: =Gen!B33 -> 44584 | B28: ='Utility report '!B28 -> 4 | C28: =Gen!V33 -> 0.42877369 | D28: =Gen!T33 -> 1199.28 | E28: =Gen!AK33 -> 253.24 | F28: =Gen!AT33 -> 0 | G28: ='Utility report '!AC28 -> 74 | H28: ='Utility report '!AE28 -> 93 | I28: ='Water-Meter'!E28 -> 62 | J28: ='Lpg (2)'!B32 -> 30 | K28: ='Lpg (2)'!C32 -> 85 | L28: ='Lpg (2)'!D32 -> 85 | M28: ='Lpg (2)'!G32 -> 93.236 | N28: =D28*1.4 -> 1678.992 | O28: =E28*1.4 -> 354.536 | P28: =('Lpg (2)'!G32)*2.38 -> 221.90168 | Q28: =N28+O28+P28 -> 2255.4297 | R28: =N28/B28 -> 419.748 | S28: =Q28/B28 -> 563.85742
A29: =Gen!B34 -> 44585 | B29: ='Utility report '!B29 -> 9 | C29: =Gen!V34 -> 0.40692261 | D29: =Gen!T34 -> 1340.81 | E29: =Gen!AK34 -> 237.04 | F29: =Gen!AT34 -> 0 | G29: ='Utility report '!AC29 -> 17 | H29: ='Utility report '!AE29 -> 61 | I29: ='Water-Meter'!E29 -> 75 | J29: ='Lpg (2)'!B33 -> 27 | K29: ='Lpg (2)'!C33 -> 85 | L29: ='Lpg (2)'!D33 -> 85 | M29: ='Lpg (2)'!G33 -> 103.312 | N29: =D29*1.4 -> 1877.134 | O29: =E29*1.4 -> 331.856 | P29: =('Lpg (2)'!G33)*2.38 -> 245.88256 | Q29: =N29+O29+P29 -> 2454.8726 | R29: =N29/B29 -> 208.57044 | S29: =Q29/B29 -> 272.76362
A30: =Gen!B35 -> 44586 | B30: ='Utility report '!B30 -> 12 | C30: =Gen!V35 -> 0.39172231 | D30: =Gen!T35 -> 1255.47 | E30: =Gen!AK35 -> 118.03 | F30: =Gen!AT35 -> 0 | G30: ='Utility report '!AC30 -> 133 | H30: ='Utility report '!AE30 -> 65 | I30: ='Water-Meter'!E30 -> 160 | J30: ='Lpg (2)'!B34 -> 23 | K30: ='Lpg (2)'!C34 -> 85 | L30: ='Lpg (2)'!D34 -> 85 | M30: ='Lpg (2)'!G34 -> 113.388 | N30: =D30*1.4 -> 1757.658 | O30: =E30*1.4 -> 165.242 | P30: =('Lpg (2)'!G34)*2.38 -> 269.86344 | Q30: =N30+O30+P30 -> 2192.7634 | R30: =N30/B30 -> 146.4715 | S30: =Q30/B30 -> 182.73029
A31: =Gen!B36 -> 44587 | B31: ='Utility report '!B31 -> 13 | C31: =Gen!V36 -> 0.37817622 | D31: =Gen!T36 -> 1351.98 | E31: =Gen!AK36 -> 73.37 | F31: =Gen!AT36 -> 0 | G31: ='Utility report '!AC31 -> 12 | H31: ='Utility report '!AE31 -> 67 | I31: ='Water-Meter'!E31 -> 66 | J31: ='Lpg (2)'!B35 -> 20 | K31: ='Lpg (2)'!C35 -> 85 | L31: ='Lpg (2)'!D35 -> 85 | M31: ='Lpg (2)'!G35 -> 121.352 | N31: =D31*1.4 -> 1892.772 | O31: =E31*1.4 -> 102.718 | P31: =('Lpg (2)'!G35)*2.38 -> 288.81776 | Q31: =N31+O31+P31 -> 2284.3078 | R31: =N31/B31 -> 145.59785 | S31: =Q31/B31 -> 175.71598
A32: =Gen!B37 -> 44588 | B32: ='Utility report '!B32 -> 11 | C32: =Gen!V37 -> 0.39098338 | D32: =Gen!T37 -> 1411.45 | E32: =Gen!AK37 -> 353.88 | F32: =Gen!AT37 -> 0 | G32: ='Utility report '!AC32 -> 184 | H32: ='Utility report '!AE32 -> 76 | I32: ='Water-Meter'!E32 -> 75 | J32: ='Lpg (2)'!B36 -> 19 | K32: ='Lpg (2)'!C36 -> 85 | L32: ='Lpg (2)'!D36 -> 85 | M32: ='Lpg (2)'!G36 -> 119.328 | N32: =D32*1.4 -> 1976.03 | O32: =E32*1.4 -> 495.432 | P32: =('Lpg (2)'!G36)*2.38 -> 284.00064 | Q32: =N32+O32+P32 -> 2755.4626 | R32: =N32/B32 -> 179.63909 | S32: =Q32/B32 -> 250.4966
... A36: =Gen!B41 -> 44592 | B36: ='Utility report '!B36 -> 5 | C36: =Gen!V41 -> 0.39228606 | D36: =Gen!T41 -> 1283.56 | E36: =Gen!AK41 -> 511.7 | F36: =Gen!AT41 -> 0 | G36: ='Utility report '!AC36 -> 135 | H36: ='Utility report '!AE36 -> 66 | I36: ='Water-Meter'!E36 -> 104 | J36: ='Lpg (2)'!B40 -> 9 | K36: ='Lpg (2)'!C40 -> 85 | L36: ='Lpg (2)'!D40 -> 85 | M36: ='Lpg (2)'!G40 -> -4278.824 | N36: =D36*1.4 -> 1796.984 | O36: =E36*1.4 -> 716.38 | P36: =('Lpg (2)'!G40)*2.38 -> -10183.601 | Q36: =N36+O36+P36 -> -7670.2371 | R36: =N36/B36 -> 359.3968 | S36: =Q36/B36 -> -1534.0474
B37: ='Summery Report'!E36 -> 0 | C37: =Gen!V42 -> #DIV/0! | D37: =Gen!T42 -> 0 | E37: =Gen!AK42 -> 0 | F37: =Gen!AT42 -> 0 | G37: ='Utility report '!AC37 -> 128 | H37: ='Utility report '!AE37 -> 64 | I37: ='Water-Meter'!E37 -> 0 | J37: ='Lpg (2)'!B41 -> 0 | K37: ='Lpg (2)'!C41 -> 0 | L37: ='Lpg (2)'!D41 -> 0 | M37: ='Lpg (2)'!G41 -> -361186.45 | Q37: =N37+O37+P37 -> 0 | R37: =N37/B37 -> #DIV/0! | S37: =Q37/B37 -> #DIV/0!
R38: =N38/B38 -> #DIV/0!
A39: Total | B39: =SUM(B7:B37) -> 445 | C39: =SUM(C7:C35) -> 11.865161 | D39: =SUM(D7:D35) -> 44050.24 | E39: =SUM(E7:E35) -> 4545.52 | F39: =SUM(F7:F35) -> 0 | G39: =SUM(G7:G35) -> 2487 | H39: =SUM(H7:H35) -> 1193 | I39: =SUM(I7:I35) -> 2544 | J39: =SUM(J7:J35) -> 1217 | ... S39: =SUM(S7:S35) -> 6146.3394

Sheet Gen
E2: =B11 -> 44562
G6: BILILA LODGE INVESTMENT LIMITED | W6: 1 | X6: 2 | Y6: 3 | Z6: 4 | AA6: 5 | AB6: 6 | AC6: 7 | AD6: 8 | AE6: 9 | AF6: 10 | AG6: 11
G7: Diesel Consumed by 500KVA Generator | N7: 500KVA Generator KWh | W7: Safari-STAFF | X7: Safari-STAFF | Y7: Lc/swg/gust | Z7: Eng pikcup | AA7: VIP Safari Car | AB7: GX Guest | AC7: GX Guest | AD7: T/Hillux/pur | AE7: TATA | AF7: MAN | AG7: F/Truck | AH7: Incenerator | AI7: A&K | AJ7: OTHER | AK7: TOTAL CO
B8: Date | C8: Occupancy % | D8: OPENING | E8: Received | F8: Schedule delivery | G8: Company | H8: 1 | I8: 2 | J8: 3 | K8: 4 | L8: 5 | M8: 6 | N8: 1 | O8: 2 | P8: 3 | Q8: 4 | R8: 5 | S8: 6 | T8: Total Diseal Consumed | U8: Total Kwh generated | V8: Average Diesel/Kwh | W8: T 128 AXJ | X8: T 134 AXJ | Y8: T 499 AXG | Z8: T 217 CHV | AA8: T 214 CHV | AB8: T 139 AXE | AC8: T 242 AXN | AD8: T 476 AWZ | AE8: T 226 AUQ | AF8: T 308 CLD | AG8: T 852 AWU | AH8: Machine ENG | AI8: Vehicle | AJ8: Vehicle | AS8: Total Diseal Consumed Gen & Vehicle | AT8: Total cost /Day (TSH) | AU8: BALANCE
D9: 39200.63 | AS9: =SUM(AK9+T9) -> 0 | AT9: =AS9*AV9 -> 0
AK10: =SUM(W10:AJ10) -> 0 | AS10: =SUM(AK10+T10) -> 0 | AT10: =AS10*AV10 -> 0
B11: 44562 | C11: 0.4156 | D11: =SUM(D9+E11) -> 39200.63 | H11: 775.54 | L11: 511.49 | M11: 678.27 | N11: 1720 | R11: 1319 | S11: 1695 | T11: =SUM(H11:M11) -> 1965.3 | U11: =SUM(N11:S11) -> 4734 | V11: =T11/U11 -> 0.41514575 | X11: 53.11 | AJ11: 267 | AK11: =SUM(W11:AJ11) -> 320.11 | AS11: =SUM(AK11+T11) -> 2285.41 | AT11: =AS11*AV11 -> 0 | AU11: =D11 -> 39200.63 | AX11: =AV11*T11 -> 0
B12: 44563 | C12: 0.53 | D12: =SUM(D11-AS11+E12) -> 36915.22 | H12: 729.69 | K12: 524.01 | M12: 673.38 | N12: 1664 | Q12: 1286 | S12: 1613 | T12: =SUM(H12:M12) -> 1927.08 | U12: =SUM(N12:S12) -> 4563 | V12: =T12/U12 -> 0.42232742 | X12: 24.03 | AA12: 24.28 | AJ12: 189 | AK12: =SUM(W12:AJ12) -> 237.31 | AS12: =SUM(AK12+T12) -> 2164.39 | AT12: =AS12*AV12 -> 0 | AU12: =D12 -> 36915.22 | AX12: =AV12*T12 -> 0
B13: 44564 | C13: 0.36 | D13: =SUM(D12-AS12+E13) -> 34750.83 | H13: 664.93 | K13: 541.77 | L13: 653.22 | N13: 1679 | Q13: 1307 | R13: 1588 | T13: =SUM(H13:M13) -> 1859.92 | U13: =SUM(N13:S13) -> 4574 | V13: =T13/U13 -> 0.40662877 | AI13: 149 | AJ13: 82 | AK13: =SUM(W13:AJ13) -> 231 | AS13: =SUM(AK13+T13) -> 2090.92 | AT13: =AS13*AV13 -> 0 | AU13: =D13 -> 34750.83 | AX13: =AV13*T13 -> 0
B14: 44565 | C14: 0.35 | D14: =SUM(D13-AS13+E14) -> 32659.91 | H14: 676.52 | L14: 548.16 | M14: 665.02 | N14: 1665 | R14: 1226 | S14: 1455 | T14: =SUM(H14:M14) -> 1889.7 | U14: =SUM(N14:S14) -> 4346 | V14: =T14/U14 -> 0.43481362 | AA14: 22.48 | AJ14: 225 | AK14: =SUM(W14:AJ14) -> 247.48 | AS14: =SUM(AK14+T14) -> 2137.18 | AT14: =AS14*AV14 -> 0 | AU14: =D14 -> 32659.91 | AX14: =AV14*T14 -> 0
B15: 44566 | C15: 0.26 | D15: =SUM(D14-AS14+E15) -> 30522.73 | H15: 717.82 | L15: 348.48 | M15: 650.09 | N15: 1620 | R15: 889 | S15: 1460 | T15: =SUM(H15:M15) -> 1716.39 | U15: =SUM(N15:S15) -> 3969 | V15: =T15/U15 -> 0.43244898 | AJ15: 110 | AK15: =SUM(W15:AJ15) -> 110 | AS15: =SUM(AK15+T15) -> 1826.39 | AT15: =AS15*AV15 -> 0 | AU15: =D15 -> 30522.73 | AX15: =AV15*T15 -> 0
B16: 44567 | C16: 0.31 | D16: =SUM(D15-AS15+E16) -> 28696.34 | H16: 533.32 | K16: 642.04 | M16: 653.79 | N16: 1341 | Q16: 1524 | S16: 1460 | T16: =SUM(H16:M16) -> 1829.15 | U16: =SUM(N16:S16) -> 4325 | V16: =T16/U16 -> 0.42292486 | Y16: 26.62 | AA16: 64.42 | AI16: 125 | AJ16: 83 | AK16: =SUM(W16:AJ16) -> 299.04 | AS16: =SUM(AK16+T16) -> 2128.19 | AT16: =AS16*AV16 -> 0 | AU16: =D16 -> 28696.34 | AX16: =AV16*T16 -> 0
B17: 44568 | C17: 0.2468 | D17: =SUM(D16-AS16+E17) -> 26568.15 | F17: 18000 | G17: PUMA | K17: 599.58 | L17: 403.81 | M17: 862.96 | Q17: 1400 | R17: 957 | S17: 2087 | T17: =SUM(H17:M17) -> 1866.35 | U17: =SUM(N17:S17) -> 4444 | V17: =T17/U17 -> 0.41997075 | AI17: 107 | AJ17: 26 | AK17: =SUM(W17:AJ17) -> 133 | AS17: =SUM(AK17+T17) -> 1999.35 | AT17: =AS17*AV17 -> 0 | AU17: =D17 -> 26568.15 | AX17: =AV17*T17 -> 0
B18: 44569 | C18: 0.23 | D18: =SUM(D17-AS17+E18) -> 24568.8 | H18: 666.2 | K18: 670.74 | L18: 430.3 | N18: 1591 | Q18: 1585 | R18: 1115 | T18: =SUM(H18:M18) -> 1767.24 | U18: =SUM(N18:S18) -> 4291 | V18: =T18/U18 -> 0.41184805 | Y18: 34.47 | AI18: 128 | AK18: =SUM(W18:AJ18) -> 162.47 | AS18: =SUM(AK18+T18) -> 1929.71 | AT18: =AS18*AV18 -> 0 | AU18: =D18 -> 24568.8 | AX18: =AV18*T18 -> 0
B19: 44570 | C19: 0.2078 | D19: =SUM(D18-AS18+E19) -> 40639.09 | E19: 18000 | H19: 659.54 | L19: 450 | M19: 736.51 | N19: 1587 | R19: 1074 | S19: 1675 | T19: =SUM(H19:M19) -> 1846.05 | U19: =SUM(N19:S19) -> 4336 | V19: =T19/U19 -> 0.42574954 | W19: 43.86 | X19: 58.67 | Y19: 7.21 | AK19: =SUM(W19:AJ19) -> 109.74 | AS19: =SUM(AK19+T19) -> 1955.79 | AT19: =AS19*AV19 -> 0 | AU19: =D19 -> 40639.09 | AX19: =AV19*T19 -> 0
B20: 44571 | C20: 0.17 | D20: =SUM(D19-AS19+E20) -> 38683.3 | K20: 703.65 | L20: 384.33 | M20: 677.65 | Q20: 1634 | R20: 1042 | S20: 1603 | T20: =SUM(H20:M20) -> 1765.63 | U20: =SUM(N20:S20) -> 4279 | V20: =T20/U20 -> 0.41262678 | Z20: 79.83 | AK20: =SUM(W20:AJ20) -> 79.83 | AS20: =SUM(AK20+T20) -> 1845.46 | AT20: =AS20*AV20 -> 0 | AU20: =D20 -> 38683.3 | AX20: =AV20*T20 -> 0
B21: 44572 | C21: 0.1 | D21: =SUM(D20-AS20+E21) -> 36837.84 | H21: 609.03 | K21: 615.9 | L21: 400.35 | N21: 1462 | Q21: 1449 | R21: 951 | T21: =SUM(H21:M21) -> 1625.28 | U21: =SUM(N21:S21) -> 3862 | V21: =T21/U21 -> 0.42083894 | W21: 33.66 | Y21: 49.8 | AI21: 303 | AK21: =SUM(W21:AJ21) -> 386.46 | AS21: =SUM(AK21+T21) -> 2011.74 | AT21: =AS21*AV21 -> 0 | AU21: =D21 -> 36837.84 | AX21: =AV21*T21 -> 0
B22: 44573 | C22: 0.0649 | D22: =SUM(D21-AS21+E22) -> 34826.1 | H22: 609.09 | L22: 380.6 | M22: 610.08 | N22: 1445 | R22: 981 | S22: 1377 | T22: =SUM(H22:M22) -> 1599.77 | U22: =SUM(N22:S22) -> 3803 | V22: =T22/U22 -> 0.42066001 | AK22: =SUM(W22:AJ22) -> 0 | AS22: =SUM(AK22+T22) -> 1599.77 | AT22: =AS22*AV22 -> 0 | AU22: =D22 -> 34826.1 | AX22: =AV22*T22 -> 0
B23: 44574 | C23: 0.13 | D23: =SUM(D22-AS22+E23) -> 33226.33 | K23: 977.03 | L23: 530.26 | R23: 2558 | S23: 1090 | T23: =SUM(H23:M23) -> 1507.29 | U23: =SUM(N23:S23) -> 3648 | V23: =T23/U23 -> 0.41318257 | Y23: 66.31 | AK23: =SUM(W23:AJ23) -> 66.31 | AS23: =SUM(AK23+T23) -> 1573.6 | AT23: =AS23*AV23 -> 0 | AU23: =D23 -> 33226.33 | AX23: =AV23*T23 -> 0
B24: 44575 | C24: 0.18 | D24: =SUM(D23-AS23+E24) -> 31652.73 | H24: 385.12 | K24: 135.22 | M24: 991.58 | N24: 969 | Q24: 227 | S24: 2599 | T24: =SUM(H24:M24) -> 1511.92 | U24: =SUM(N24:S24) -> 3795 | V24: =T24/U24 -> 0.39839789 | W24: 51.62 | AG24: 111.46 | AI24: 125 | AK24: =SUM(W24:AJ24) -> 288.08 | AS24: =SUM(AK24+T24) -> 1800 | AT24: =AS24*AV24 -> 0 | AU24: =D24 -> 31652.73 | AX24: =AV24*T24 -> 0
B25: 44576 | C25: 0.16 | D25: =SUM(D24-AS24+E25) -> 29852.73 | K25: 933.83 | L25: 508.17 | Q25: 2445 | R25: 1203 | T25: =SUM(H25:M25) -> 1442 | U25: =SUM(N25:S25) -> 3648 | V25: =T25/U25 -> 0.39528509 | AK25: =SUM(W25:AJ25) -> 0 | AS25: =SUM(AK25+T25) -> 1442 | AT25: =AS25*AV25 -> 0 | AU25: =D25 -> 29852.73 | AX25: =AV25*T25 -> 0
B26: 44577 | C26: 0.18 | D26: =SUM(D25-AS25+E26) -> 28410.73 | H26: 538.66 | M26: 815.72 | N26: 1292 | S26: 2101 | T26: =SUM(H26:M26) -> 1354.38 | U26: =SUM(N26:S26) -> 3393 | V26: =T26/U26 -> 0.39916888 | AI26: 327 | AJ26: 120 | AK26: =SUM(W26:AJ26) -> 447 | AS26: =SUM(AK26+T26) -> 1801.38 | AT26: =AS26*AV26 -> 0 | AU26: =D26 -> 28410.73 | AX26: =AV26*T26 -> 0
B27: 44578 | C27: 0.09 | D27: =SUM(D26-AS26+E27) -> 26609.35 | F27: 18000 | G27: PUMA | K27: 828.54 | L27: 391.93 | Q27: 2000 | R27: 977 | T27: =SUM(H27:M27) -> 1220.47 | U27: =SUM(N27:S27) -> 2977 | V27: =T27/U27 -> 0.40996641 | AK27: =SUM(W27:AJ27) -> 0 | AS27: =SUM(AK27+T27) -> 1220.47 | AT27: =AS27*AV27 -> 0 | AU27: =D27 -> 26609.35 | AX27: =AV27*T27 -> 0
B28: 44579 | C28: 0.16 | D28: =SUM(D27-AS27+E28) -> 25388.88 | H28: 439.26 | M28: 943.38 | N28: 1055 | S28: 2388 | T28: =SUM(H28:M28) -> 1382.64 | U28: =SUM(N28:S28) -> 3443 | V28: =T28/U28 -> 0.40158002 | W28: 43.17 | AB28: 111.94 | AF28: 65.9 | AK28: =SUM(W28:AJ28) -> 221.01 | AS28: =SUM(AK28+T28) -> 1603.65 | AT28: =AS28*AV28 -> 0 | AU28: =D28 -> 25388.88 | AX28: =AV28*T28 -> 0
B29: 44580 | C29: 0.18 | D29: =SUM(D28-AS28+E29) -> 23785.23 | K29: 825.01 | L29: 427.7 | Q29: 1979 | R29: 1031 | T29: =SUM(H29:M29) -> 1252.71 | U29: =SUM(N29:S29) -> 3010 | V29: =T29/U29 -> 0.41618272 | W29: 84.95 | AA29: 42.89 | AK29: =SUM(W29:AJ29) -> 127.84 | AS29: =SUM(AK29+T29) -> 1380.55 | AT29: =AS29*AV29 -> 0 | AU29: =D29 -> 23785.23 | AX29: =AV29*T29 -> 0
B30: 44581 | C30: 0.21 | D30: =SUM(D29-AS29+E30) -> 22404.68 | K30: 448.87 | M30: 921.58 | Q30: 1084 | S30: 2239 | T30: =SUM(H30:M30) -> 1370.45 | U30: =SUM(N30:S30) -> 3323 | V30: =T30/U30 -> 0.41241348 | W30: 77.02 | AI30: 161 | AK30: =SUM(W30:AJ30) -> 238.02 | AS30: =SUM(AK30+T30) -> 1608.47 | AT30: =AS30*AV30 -> 0 | AU30: =D30 -> 22404.68 | AX30: =AV30*T30 -> 0
B31: 44582 | C31: 0.09 | D31: =SUM(D30-AS30+E31) -> 20796.21 | K31: 407.7 | L31: 872.61 | Q31: 997 | R31: 2116 | T31: =SUM(H31:M31) -> 1280.31 | U31: =SUM(N31:S31) -> 3113 | V31: =T31/U31 -> 0.41127851 | AI31: 15 | AK31: =SUM(W31:AJ31) -> 15 | AS31: =SUM(AK31+T31) -> 1295.31 | AT31: =AS31*AV31 -> 0 | AU31: =D31 -> 20796.21 | AX31: =AV31*T31 -> 0
B32: 44583 | C32: 0.08 | D32: =SUM(D31-AS31+E32) -> 19500.9 | H32: 417.95 | K32: 366.95 | M32: 501.36 | N32: 1024 | Q32: 924 | S32: 1176 | T32: =SUM(H32:M32) -> 1286.26 | U32: =SUM(N32:S32) -> 3124 | V32: =T32/U32 -> 0.41173496 | AB32: 67 | AE32: 197.82 | AK32: =SUM(W32:AJ32) -> 264.82 | AS32: =SUM(AK32+T32) -> 1551.08 | AT32: =AS32*AV32 -> 0 | AU32: =D32 -> 19500.9 | AX32: =AV32*T32 -> 0
B33: 44584 | C33: 0.04 | D33: =SUM(D32-AS32+E33) -> 35949.82 | E33: 18000 | L33: 639.09 | M33: 560.19 | R33: 1169 | S33: 1628 | T33: =SUM(H33:M33) -> 1199.28 | U33: =SUM(N33:S33) -> 2797 | V33: =T33/U33 -> 0.42877369 | Z33: 71.24 | AI33: 182 | AK33: =SUM(W33:AJ33) -> 253.24 | AS33: =SUM(AK33+T33) -> 1452.52 | AT33: =AS33*AV33 -> 0 | AU33: =D33 -> 35949.82 | AX33: =AV33*T33 -> 0
B34: 44585 | C34: 0.1 | D34: =SUM(D33-AS33+E34) -> 34497.3 | H34: 418.24 | K34: 922.57 | N34: 1136 | Q34: 2159 | T34: =SUM(H34:M34) -> 1340.81 | U34: =SUM(N34:S34) -> 3295 | V34: =T34/U34 -> 0.40692261 | AA34: 118.04 | AI34: 119 | AK34: =SUM(W34:AJ34) -> 237.04 | AS34: =SUM(AK34+T34) -> 1577.85 | AT34: =AS34*AV34 -> 0 | AU34: =D34 -> 34497.3 | AX34: =AV34*T34 -> 0
B35: 44586 | C35: 0.14 | D35: =SUM(D34-AS34+E35) -> 32919.45 | K35: 405.54 | L35: 849.93 | Q35: 1001 | R35: 2204 | T35: =SUM(H35:M35) -> 1255.47 | U35: =SUM(N35:S35) -> 3205 | V35: =T35/U35 -> 0.39172231 | AA35: 29.03 | AB35: 89 | AK35: =SUM(W35:AJ35) -> 118.03 | AS35: =SUM(AK35+T35) -> 1373.5 | AT35: =AS35*AV35 -> 0 | AU35: =D35 -> 32919.45 | AX35: =AV35*T35 -> 0
B36: 44587 | C36: 0.16 | D36: =SUM(D35-AS35+E36) -> 31545.95 | F36: 15000 | G36: RAHA | K36: 423.83 | M36: 928.15 | Q36: 1064 | S36: 2511 | T36: =SUM(H36:M36) -> 1351.98 | U36: =SUM(N36:S36) -> 3575 | V36: =T36/U36 -> 0.37817622 | AA36: 73.37 | AK36: =SUM(W36:AJ36) -> 73.37 | AS36: =SUM(AK36+T36) -> 1425.35 | AT36: =AS36*AV36 -> 0 | AU36: =D36 -> 31545.95 | AX36: =AV36*T36 -> 0
B37: 44588 | C37: 0.13 | D37: =SUM(D36-AS36+E37) -> 45120.6 | E37: 15000 | H37: 964.39 | L37: 447.06 | N37: 2497 | R37: 1113 | T37: =SUM(H37:M37) -> 1411.45 | U37: =SUM(N37:S37) -> 3610 | V37: =T37/U37 -> 0.39098338 | AA37: 21.32 | AG37: 56.56 | AI37: 276 | AK37: =SUM(W37:AJ37) -> 353.88 | AS37: =SUM(AK37+T37) -> 1765.33 | AT37: =AS37*AV37 -> 0 | AU37: =D37 -> 45120.6 | AX37: =AV37*T37 -> 0
B38: 44589 | C38: 0.09 | D38: =SUM(D37-AS37+E38) -> 43355.27 | K38: 431.06 | M38: 998.14 | Q38: 1090 | S38: 2503 | T38: =SUM(H38:M38) -> 1429.2 | U38: =SUM(N38:S38) -> 3593 | V38: =T38/U38 -> 0.39777345 | AK38: =SUM(W38:AJ38) -> 0 | AS38: =SUM(AK38+T38) -> 1429.2 | AT38: =AS38*AV38 -> 0 | AU38: =D38 -> 43355.27 | AX38: =AV38*T38 -> 0
B39: 44590 | C39: 0.09 | D39: =SUM(D38-AS38+E39) -> 41926.07 | H39: 441.31 | L39: 972.88 | N39: 1104 | R39: 2485 | T39: =SUM(H39:M39) -> 1414.19 | U39: =SUM(N39:S39) -> 3589 | V39: =T39/U39 -> 0.39403455 | AA39: 26.59 | AJ39: 22 | AK39: =SUM(W39:AJ39) -> 48.59 | AS39: =SUM(AK39+T39) -> 1462.78 | AT39: =AS39*AV39 -> 0 | AU39: =D39 -> 41926.07 | AX39: =AV39*T39 -> 0
B40: 44591 | C40: 0.06 | D40: =SUM(D39-AS39+E40) -> 40463.29 | K40: 465.43 | M40: 881.44 | Q40: 1174 | S40: 2401 | T40: =SUM(H40:M40) -> 1346.87 | U40: =SUM(N40:S40) -> 3575 | V40: =T40/U40 -> 0.37674685 | AI40: 96 | AK40: =SUM(W40:AJ40) -> 96 | AS40: =SUM(AK40+T40) -> 1442.87 | AT40: =AS40*AV40 -> 0 | AU40: =D40 -> 40463.29 | AX40: =AV40*T40 -> 0
B41: 44592 | C41: 0.05 | D41: =SUM(D40-AS40+E41) -> 39020.42 | H41: 417.06 | L41: 866.5 | N41: 1041 | R41: 2231 | T41: =SUM(G41:M41) -> 1283.56 | U41: =SUM(N41:S41) -> 3272 | V41: =T41/U41 -> 0.39228606 | Y41: 35.12 | AE41: 43.58 | AI41: 433 | AK41: =SUM(W41:AJ41) -> 511.7 | AS41: =SUM(AK41+T41) -> 1795.26 | AT41: =AS41*AV41 -> 0 | AU41: =D41 -> 39020.42 | AX41: =SUM(AX11:AX40) -> 0
D42: =SUM(D41-AS41+E42) -> 37225.16 | T42: =SUM(G42:M42) -> 0 | U42: =SUM(N42:S42) -> 0 | V42: =T42/U42 -> #DIV/0! | AK42: =SUM(W42:AJ42) -> 0 | AS42: =SUM(AK42+T42) -> 0 | AT42: =AS42*AV42 -> 0 | AU42: =D42 -> 37225.16
B43: BF | D43: =SUM(D42-AS42+E43) -> 37225.16 | T43: =SUM(G43:M43) -> 0 | U43: =SUM(N43:S43) -> 0 | AK43: =SUM(W43:AJ43) -> 0 | AS43: =SUM(AK43+T43) -> 0 | AT43: =AS43*AV43 -> 0 | AU43: =D43 -> 37225.16
T44: =SUM(G44:M44) -> 0 | U44: =SUM(N44:S44) -> 0 | AK44: =SUM(W44:AJ44) -> 0 | AS44: =T44+AK44 -> 0 | AT44: =AS44*AV44 -> 0
E45: =SUM(E11:E44) -> 51000 | F45: =SUM(F11:F42) -> 51000 | G45: =SUM(G12:G44) -> 0 | H45: =SUM(H11:H44) -> 10663.67 | I45: =SUM(I11:I44) -> 0 | J45: =SUM(J11:J44) -> 0 | K45: =SUM(K11:K44) -> 11869.27 | L45: =SUM(L11:L44) -> 11016.87 | M45: =SUM(M11:M44) -> 13749.29 | N45: =SUM(N11:N44) -> 25892 | O45: =SUM(O11:O44) -> 0 | P45: =SUM(P11:P44) -> 0 | Q45: =SUM(Q11:Q43) -> 26329 | R45: =SUM(R11:R44) -> 28229 | S45: =SUM(S11:S44) -> 35061 | T45: =SUM(H45:M45) -> 47299.1 | U45: =SUM(N45:S45) -> 115511 | V45: =SUM(V11:V42) -> #DIV/0! | W45: =SUM(W9:W44) -> 334.28 | X45: =SUM(X9:X44) -> 135.81 | Y45: =SUM(Y9:Y44) -> 219.53 | Z45: =SUM(Z9:Z44) -> 151.07 | AA45: =SUM(AA9:AA44) -> 422.42 | AB45: =SUM(AB9:AB44) -> 267.94 | AC45: =SUM(AC9:AC44) -> 0 | AD45: =SUM(AD10:AD44) -> 0 | AE45: =SUM(AE10:AE44) -> 241.4 | AF45: =SUM(AF9:AF44) -> 65.9 | AG45: =SUM(AG9:AG44) -> 168.02 | AH45: =SUM(AH9:AH44) -> 0 | AI45: =SUM(AI9:AI43) -> 2546 | AJ45: =SUM(AJ9:AJ39) -> 1124 | AK45: =SUM(AK9:AK44) -> 5676.37 | AS45: =SUM(AS11:AS43) -> 52975.47 | AT45: =SUM(AT11:AT44) -> 0
B46: Nb Day | N46: =H45/N45 -> 0.41185192 | Q46: =K45/Q45 -> 0.45080596 | R46: =L45/R45 -> 0.39026781 | S46: =M45/S45 -> 0.39215339 | V46: =T45/U45 -> 0.40947702
C47: =AVERAGE(C11:C40) -> 0.18383667 | U47: =T45*2475 -> 1.1706527e+08 | V47: TZS | AS47: =AS45*2143 -> 1.1352643e+08 | AT47: TZS
B48: Av. Occ | U48: =U47/2289 -> 51142.539 | V48: USD | AS48: =AS47/2289 -> 49596.519 | AT48: USD
C50: A & K VEHICLES | I50: MAULY VEHICLES | O50: GREEN LAND VEHICLES | U50: OTHERS VEHICLES
C51: Date | D51: Vehicles | E51: Liters | F51: Driver name | G51: Authority manager | I51: Date | J51: Vehicles | K51: Liters | L51: Driver name | M51: Authority manager | O51: Date | P51: Vehicles | Q51: Liters | R51: Driver name | S51: Authorized Manager | U51: Date | V51: Vehicles | W51: Liters | X51: Driver name | Y51: Athorized Manager | Z51: Reasons
C52: 44621 | D52: T132CWQ | E52: 75 | F52: Hassan | G52: NOEL | O52: 44562 | P52: T559DLW | Q52: 115 | R52: Elifuraha | S52: NOEL | U52: 16/1/2022 | V52: T882DLC | W52: 120 | X52: BENSON | Y52: NOEL | Z52: PAID
C53: 44630 | D53: T106CWQ | E53: 74 | F53: Dominik | G53: NOEL | O53: 44562 | P53: T367DHU | Q53: 55 | R53: FREDY | S53: NOEL
C54: 44713 | D54: T840DDW | E54: 125 | F54: DICKSON | G54: HURUMA | O54: 44562 | P54: T726DCD | Q54: 97 | R54: Jafary | S54: NOEL
C55: 44743 | D55: T882DKQ | E55: 107 | F55: HErman | G55: HURUMA | O55: 44593 | P55: T755CJQ | Q55: 30 | R55: Karume | S55: NOEL
C56: 44774 | D56: T880DKQ | E56: 128 | F56: PRISCUS | G56: hURUMA
C57: 44866 | D57: T391DQR | E57: 150 | F57: JOSEPH | G57: HURUMA | O57: 44593 | P57: T827CUD | Q57: 109 | R57: Charles | S57: NOEL
C58: 44866 | D58: T111CWQ | E58: 153 | F58: RICHARD | G58: HURUMA | O58: 44621 | P58: T726DCD | Q58: 72 | R58: Jafary | S58: NOEL
C59: 14/01/2022 | D59: T88ODKQ | E59: 125 | F59: PRISCUS | G59: NOEL | O59: 44621 | P59: T755CJQ | Q59: 10 | R59: Karume | S59: NOEL
C60: 16/01/2022 | D60: T882DKQ | E60: 138 | F60: HErman | G60: NOEL | O60: 44652 | P60: T367DHU | Q60: 30 | R60: FREDY | S60: NOEL
C61: 16/01/2022 | D61: T106CWQ | E61: 114 | F61: KESSY | G61: NOEL | O61: 44652 | P61: T559DLW | Q61: 105 | R61: Elifuraha | S61: NOEL
C62: 16/01/2022 | D62: T391DQR | E62: 75 | F62: JOSEPH | G62: NOEL | O62: 44652 | P62: T254DCP | Q62: 90 | R62: RAFAEL | S62: HURUMA
C63: 20/01/2022 | D63: T840DDW | E63: 77 | F63: NURU | G63: NOEL | O63: 44682 | P63: T228CRW | Q63: 110 | R63: Shaban | S63: HURUMA
C64: 20/01/2022 | D64: T132CWQ | E64: 84 | F64: GODLUCK | G64: NOEL | O64: 44713 | P64: T728CXC | Q64: 40 | R64: PETER | S64: HURUMA
C65: 21/01/2022 | D65: T391DQR | E65: 15 | F65: FADHILI | G65: NOEL | O65: 44713 | P65: T662CZG | Q65: 43 | R65: MICHAEL | S65: HURUMA
C66: 23/01/2022 | D66: T106CWQ | E66: 51 | F66: KESSY | G66: NOEL | O66: 44743 | P66: T726DCD | Q66: 26 | R66: Jafary | S66: NOEL
C67: 23/01/2022 | D67: T111CWQ | E67: 131 | F67: HErman | G67: NOEL | O67: 29/01/2022 | P67: T662CZG | Q67: 22 | R67: MICHAEL | S67: NOEL
C68: 24/01/2022 | D68: T880DKQ | E68: 119 | F68: PRISCUS | G68: NOEL
C69: 27/01/2022 | D69: T882DKQ | E69: 145 | F69: Herman | G69: NOEL
C70: 27/01/2022 | D70: T840DDW | E70: 131 | F70: NURU | G70: NOEL
C71: 30/01/2022 | D71: T880DKQ | E71: 96 | F71: PRISCUS | G71: NOEL
C72: 31/01/2022 | D72: T840DDW | E72: 28 | F72: NURU | G72: NOEL
C73: 31/01/2022 | D73: T364AHF | E73: 25 | F73: HErman | G73: NOEL
C74: 31/01/2022 | D74: T111CWQ | E74: 101 | F74: KESSY | G74: NOEL
C75: 31/01/2022 | D75: T882DKQ | E75: 15 | F75: HErman | G75: NOEL
C76: 31/01/2022 | D76: T675ANT | E76: 118 | F76: HErman | G76: NOEL
C78: 31/01/2022 | D78: T391DQR | E78: 73 | F78: GODLUCK | G78: NOEL
C79: 31/01/2022 | D79: T132CWQ | E79: 73 | F79: GODLUCK | G79: NOEL

Sheet Lpg (2)
C3: Four Sasons Safari Lodge Serengeti
G6: VALUE | H6: Cost
A7: DATE | B7: A | C7: B | D7: C | F7: Meter Reading | G7: Total | H7: Occu | I7: No.of | J7: Kg
B8: 2Ton% | C8: 1Ton (%) | D8: 1Ton% | F8: consumption | G8: Consumption Kg | H8: % | I8: pax | J8: per pax
F9: 82286.61
A10: =Gen!B11 -> 44562 | B10: 50 | C10: 0 | D10: 0 | F10: 82319.44 | G10: =(F10-F9)*4.4 -> 144.452 | H10: =Gen!C11 -> 0.4156 | I10: =Submetering!X2 -> 89 | J10: =SUM(G10/I10) -> 1.6230562
A11: =Gen!B12 -> 44563 | B11: 45 | C11: 0 | D11: 0 | F11: 82353.69 | G11: =(F11-F10)*4.4 -> 150.7 | H11: =Gen!C12 -> 0.53 | I11: =Submetering!X3 -> 102 | J11: =SUM(G11/I11) -> 1.477451
A12: =Gen!B13 -> 44564 | B12: 41 | C12: 0 | D12: 0 | F12: 82389.36 | G12: =(F12-F11)*4.4 -> 156.948 | H12: =Gen!C13 -> 0.36 | I12: =Submetering!X4 -> 74 | J12: =SUM(G12/I12) -> 2.1209189
A13: =Gen!B14 -> 44565 | B13: 40 | C13: 0 | D13: 0 | F13: 82419.38 | G13: =(F13-F12)*4.4 -> 132.088 | H13: =Gen!C14 -> 0.35 | I13: =Submetering!X5 -> 68 | J13: =SUM(G13/I13) -> 1.9424706
A14: =Gen!B15 -> 44566 | B14: 38 | C14: 0 | D14: 0 | F14: 82447.15 | G14: =(F14-F13)*4.4 -> 122.188 | H14: =Gen!C15 -> 0.26 | I14: =Submetering!X6 -> 48 | J14: =SUM(G14/I14) -> 2.5455833
A15: =Gen!B16 -> 44567 | B15: 72 | C15: 85 | D15: 85 | F15: 82478.45 | G15: =(F15-F14)*4.4 -> 137.72 | H15: =Gen!C16 -> 0.31 | I15: =Submetering!X7 -> 61 | J15: =SUM(G15/I15) -> 2.2577049
A16: =Gen!B17 -> 44568 | B16: 70 | C16: 85 | D16: 85 | F16: 82508.65 | G16: =(F16-F15)*4.4 -> 132.88 | H16: =Gen!C17 -> 0.2468 | I16: =Submetering!X8 -> 46 | J16: =SUM(G16/I16) -> 2.8886957
A17: =Gen!B18 -> 44569 | B17: 70 | C17: 85 | D17: 85 | F17: 82534.11 | G17: =(F17-F16)*4.4 -> 112.024 | H17: =Gen!C18 -> 0.23 | I17: =Submetering!X9 -> 48 | J17: =SUM(G17/I17) -> 2.3338333
A18: =Gen!B19 -> 44570 | B18: 65 | C18: 85 | D18: 85 | F18: 82558.22 | G18: =(F18-F17)*4.4 -> 106.084 | H18: =Gen!C19 -> 0.2078 | I18: =Submetering!X10 -> 43 | J18: =SUM(G18/I18) -> 2.4670698
A19: =Gen!B20 -> 44571 | B19: 62 | C19: 85 | D19: 85 | F19: 82584.08 | G19: =(F19-F18)*4.4 -> 113.784 | H19: =Gen!C20 -> 0.17 | I19: =Submetering!X11 -> 39 | J19: =SUM(G19/I19) -> 2.9175385
A20: =Gen!B21 -> 44572 | B20: 60 | C20: 58 | D20: 85 | F20: 82610.65 | G20: =(F20-F19)*4.4 -> 116.908 | H20: =Gen!C21 -> 0.1 | I20: =Submetering!X12 -> 23 | J20: =SUM(G20/I20) -> 5.0829565
A21: =Gen!B22 -> 44573 | B21: 58 | C21: 85 | D21: 85 | F21: 82633.26 | G21: =(F21-F20)*4.4 -> 99.484 | H21: =Gen!C22 -> 0.0649 | I21: =Submetering!X13 -> 17 | J21: =SUM(G21/I21) -> 5.852
... A40: =Gen!B41 -> 44592 | B40: 9 | C40: 85 | D40: 85 | F40: 82087.83 | G40: =(F40-F39)*4.4 -> -4278.824 | H40: =Gen!C41 -> 0.05 | I40: =Submetering!X32 -> 12 | J40: =SUM(G40/I40) -> -356.56867
G41: =(F41-F40)*4.4 -> -361186.45 | H41: =Gen!C42 -> 0 | J41: =SUM(G41/I41) -> #DIV/0!
C42: TOTAL USAGE | E42: =SUM(E10:E40) -> 0 | F42: =SUM(F10:F41) -> 2563205.2 | G42: =SUM(G10:G40) -> -874.632 | H42: =Gen!C43 -> 0

Sheet Summery Report
A1: =A5 -> 44562
A4: Date | B4: Gen Set Hours Working | C4: Occ% | D4: Total OCC Room | E4: Guest Room Occ | F4: Total Kwh Generated | G4: Diesel consumed by Gen (Ltrs) | H4: Diesel consumed by Vehicle (Ltrs) | I4: Total diesel consumed (Ltrs) | J4: Balance stock of Diesel (Ltrs) | K4: Water consumed | L4: Gas consumed (KG)
A5: =Gen!B11 -> 44562 | B5: ='Daily report Gen'!Z6 -> 42 | C5: =Gen!C11 -> 0.4156 | D5: =E5 -> 34 | E5: ='Energy Graph'!E2 -> 34 | F5: =Gen!U11 -> 4734 | G5: =Gen!T11 -> 1965.3 | H5: =Gen!AK11 -> 320.11 | I5: =SUM(G5:H5) -> 2285.41 | J5: =Gen!D11 -> 39200.63 | K5: ='Water-Meter'!E6 -> 116 | L5: ='Lpg (2)'!G10 -> 144.452 | M5: =SUM(#REF!-#REF!) -> #REF!
A6: =Gen!B12 -> 44563 | B6: ='Daily report Gen'!Z7 -> 40 | C6: =Gen!C12 -> 0.53 | D6: =E6 -> 42 | E6: ='Energy Graph'!E3 -> 42 | F6: =Gen!U12 -> 4563 | G6: =Gen!T12 -> 1927.08 | H6: =Gen!AK12 -> 237.31 | I6: =SUM(G6:H6) -> 2164.39 | J6: =Gen!D12 -> 36915.22 | K6: ='Water-Meter'!E7 -> 94 | L6: ='Lpg (2)'!G11 -> 150.7 | M6: =SUM(#REF!-#REF!) -> #REF!
A7: =Gen!B13 -> 44564 | B7: ='Daily report Gen'!Z8 -> 40 | C7: =Gen!C13 -> 0.36 | D7: =E7 -> 29 | E7: ='Energy Graph'!E4 -> 29 | F7: =Gen!U13 -> 4574 | G7: =Gen!T13 -> 1859.92 | H7: =Gen!AK13 -> 231 | I7: =SUM(G7:H7) -> 2090.92 | J7: =Gen!D13 -> 34750.83 | K7: ='Water-Meter'!E8 -> 110 | L7: ='Lpg (2)'!G12 -> 156.948 | M7: =SUM(#REF!-#REF!) -> #REF!
A8: =Gen!B14 -> 44565 | B8: ='Daily report Gen'!Z9 -> 41 | C8: =Gen!C14 -> 0.35 | D8: =E8 -> 28 | E8: ='Energy Graph'!E5 -> 28 | F8: =Gen!U14 -> 4346 | G8: =Gen!T14 -> 1889.7 | H8: =Gen!AK14 -> 247.48 | I8: =SUM(G8:H8) -> 2137.18 | J8: =Gen!D14 -> 32659.91 | K8: ='Water-Meter'!E9 -> 94 | L8: ='Lpg (2)'!G13 -> 132.088 | M8: =SUM(#REF!-#REF!) -> #REF!
A9: =Gen!B15 -> 44566 | B9: ='Daily report Gen'!Z10 -> 41 | C9: =Gen!C15 -> 0.26 | D9: =E9 -> 21 | E9: ='Energy Graph'!E6 -> 21 | F9: =Gen!U15 -> 3969 | G9: =Gen!T15 -> 1716.39 | H9: =Gen!AK15 -> 110 | I9: =SUM(G9:H9) -> 1826.39 | J9: =Gen!D15 -> 30522.73 | K9: ='Water-Meter'!E10 -> 86 | L9: ='Lpg (2)'!G14 -> 122.188 | M9: =SUM(#REF!-#REF!) -> #REF!
A10: =Gen!B16 -> 44567 | B10: ='Daily report Gen'!Z11 -> 39 | C10: =Gen!C16 -> 0.31 | D10: =E10 -> 25 | E10: ='Energy Graph'!E7 -> 25 | F10: =Gen!U16 -> 4325 | G10: =Gen!T16 -> 1829.15 | H10: =Gen!AK16 -> 299.04 | I10: =SUM(G10:H10) -> 2128.19 | J10: =Gen!D16 -> 28696.34 | K10: ='Water-Meter'!E11 -> 90 | L10: ='Lpg (2)'!G15 -> 137.72 | M10: =SUM(#REF!-#REF!) -> #REF!
A11: =Gen!B17 -> 44568 | B11: ='Daily report Gen'!Z12 -> 38 | C11: =Gen!C17 -> 0.2468 | D11: =E11 -> 20 | E11: ='Energy Graph'!E8 -> 20 | F11: =Gen!U17 -> 4444 | G11: =Gen!T17 -> 1866.35 | H11: =Gen!AK17 -> 133 | I11: =SUM(G11:H11) -> 1999.35 | J11: =Gen!D17 -> 26568.15 | K11: ='Water-Meter'!E12 -> 92 | L11: ='Lpg (2)'!G16 -> 132.88 | M11: =SUM(#REF!-#REF!) -> #REF!
A12: =Gen!B18 -> 44569 | B12: ='Daily report Gen'!Z13 -> 40 | C12: =Gen!C18 -> 0.23 | D12: =E12 -> 19 | E12: ='Energy Graph'!E9 -> 19 | F12: =Gen!U18 -> 4291 | G12: =Gen!T18 -> 1767.24 | H12: =Gen!AK18 -> 162.47 | I12: =SUM(G12:H12) -> 1929.71 | J12: =Gen!D18 -> 24568.8 | K12: ='Water-Meter'!E13 -> 108 | L12: ='Lpg (2)'!G17 -> 112.024 | M12: =SUM(#REF!-#REF!) -> #REF!
A13: =Gen!B19 -> 44570 | B13: ='Daily report Gen'!Z14 -> 43 | C13: =Gen!C19 -> 0.2078 | D13: =E13 -> 17 | E13: ='Energy Graph'!E10 -> 17 | F13: =Gen!U19 -> 4336 | G13: =Gen!T19 -> 1846.05 | H13: =Gen!AK19 -> 109.74 | I13: =SUM(G13:H13) -> 1955.79 | J13: =Gen!D19 -> 40639.09 | K13: ='Water-Meter'!E14 -> 101 | L13: ='Lpg (2)'!G18 -> 106.084 | M13: =SUM(#REF!-#REF!) -> #REF!
A14: =Gen!B20 -> 44571 | B14: ='Daily report Gen'!Z15 -> 39 | C14: =Gen!C20 -> 0.17 | D14: =E14 -> 16 | E14: ='Energy Graph'!E11 -> 16 | F14: =Gen!U20 -> 4279 | G14: =Gen!T20 -> 1765.63 | H14: =Gen!AK20 -> 79.83 | I14: =SUM(G14:H14) -> 1845.46 | J14: =Gen!D20 -> 38683.3 | K14: ='Water-Meter'!E15 -> 83 | L14: ='Lpg (2)'!G19 -> 113.784 | M14: =SUM(#REF!-#REF!) -> #REF!
A15: =Gen!B21 -> 44572 | B15: ='Daily report Gen'!Z16 -> 49 | C15: =Gen!C21 -> 0.1 | D15: =E15 -> 11 | E15: ='Energy Graph'!E12 -> 11 | F15: =Gen!U21 -> 3862 | G15: =Gen!T21 -> 1625.28 | H15: =Gen!AK21 -> 386.46 | I15: =SUM(G15:H15) -> 2011.74 | J15: =Gen!D21 -> 36837.84 | K15: ='Water-Meter'!E16 -> 67 | L15: ='Lpg (2)'!G20 -> 116.908 | M15: =SUM(#REF!-#REF!) -> #REF!
A16: =Gen!B22 -> 44573 | B16: ='Daily report Gen'!Z17 -> 42 | C16: =Gen!C22 -> 0.0649 | D16: =E16 -> 8 | E16: ='Energy Graph'!E13 -> 8 | F16: =Gen!U22 -> 3803 | G16: =Gen!T22 -> 1599.77 | H16: =Gen!AK22 -> 0 | I16: =SUM(G16:H16) -> 1599.77 | J16: =Gen!D22 -> 34826.1 | K16: ='Water-Meter'!E17 -> 133 | L16: ='Lpg (2)'!G21 -> 99.484 | M16: =SUM(#REF!-#REF!) -> #REF!
... A35: =Gen!B41 -> 44592 | B35: ='Daily report Gen'!Z36 -> 24 | C35: =Gen!C41 -> 0.05 | D35: =E35 -> 5 | E35: ='Energy Graph'!E32 -> 5 | F35: =Gen!U41 -> 3272 | G35: =Gen!T41 -> 1283.56 | H35: =Gen!AK41 -> 511.7 | I35: =SUM(G35:H35) -> 1795.26 | J35: =Gen!D41 -> 39020.42 | K35: ='Water-Meter'!E36 -> 104 | L35: ='Lpg (2)'!G40 -> -4278.824 | M35: =SUM(#REF!-#REF!) -> #REF!
A36: =Gen!B42 -> 0 | B36: ='Daily report Gen'!Z37 -> -131224 | C36: =Gen!C42 -> 0 | D36: =E36 -> 0 | F36: =Gen!U42 -> 0 | G36: =Gen!T42 -> 0 | H36: =Gen!AK42 -> 0 | I36: =SUM(G36:H36) -> 0 | J36: =Gen!D42 -> 37225.16 | K36: ='Water-Meter'!E37 -> 0 | L36: ='Lpg (2)'!G41 -> -361186.45

Sheet Daily report Gen
A1: =A6 -> 44562
K3: GENERATOR NO.1 | N3: GENERATOR NO.2 | Q3: GENERATOR NO.4 | T3: GENERATOR NO.5 | W3: GENERATOR NO.6
A4: DATE | B4: OCC% | C4: D-TANK A | D4: D-TANK B | E4: DELIVERY DATE | F4: DELIVERY | G4: ISSUED-VEHICLE | H4: OTHERS | I4: M-R LV PANEL 1. KW-HR | J4: M-R LV PANEL 2. KW-HR | K4: OPEN HRS READING | L4: CLOSE HRS READING | M4: RUNNING HRS | N4: OPEN HRS READING | O4: CLOSE HRS READING | P4: RUNNING HRS | Q4: OPEN HRS READING | R4: CLOSE HRS READING | S4: RUNNING HRS | T4: OPEN HRS READING | U4: CLOSE HRS READING | V4: RUNNING HRS | W4: OPEN HRS READING | X4: CLOSE HRS READING | Y4: RUNNING HRS | Z4: TOTAL RUNNING HRS | AA4: MAX KW | AB4: MIN-KW | AC4: TOTAL DIESEL CONS.
L5: 38661 | O5: 32025 | R5: 37416 | U5: 35733 | X5: 24077
A6: =Gen!B11 -> 44562 | B6: =Gen!C11 -> 0.4156 | C6: 24800.7 | D6: 12114.52 | G6: 320.11 | I6: 33634.2 | J6: 22360.8 | K6: =L5 -> 38661 | L6: 38677 | M6: =L6-K6 -> 16 | N6: =O5 -> 32025 | O6: 32025 | P6: =O6-N6 -> 0 | Q6: =R5 -> 37416 | R6: 37417 | S6: =R6-Q6 -> 1 | T6: =U5 -> 35733 | U6: 35743 | V6: =U6-T6 -> 10 | W6: =X5 -> 24077 | X6: 24092 | Y6: =X6-W6 -> 15 | Z6: =Y6+V6+S6+P6+M6 -> 42 | AA6: 490 | AB6: 185 | AC6: =Gen!T11 -> 1965.3
A7: =Gen!B12 -> 44563 | B7: =Gen!C12 -> 0.53 | C7: 22636.31 | D7: 12114.52 | G7: 237.31 | I7: 33642.2 | J7: 22366.1 | K7: =L6 -> 38677 | L7: 38692 | M7: =L7-K7 -> 15 | N7: =O6 -> 32025 | O7: 32025 | P7: =O7-N7 -> 0 | Q7: =R6 -> 37417 | R7: 37427 | S7: =R7-Q7 -> 10 | T7: =U6 -> 35743 | U7: 35743 | V7: =U7-T7 -> 0 | W7: =X6 -> 24092 | X7: 24107 | Y7: =X7-W7 -> 15 | Z7: =Y7+V7+S7+P7+M7 -> 40 | AA7: 485 | AB7: 200 | AC7: =Gen!T12 -> 1927.08
A8: =Gen!B13 -> 44564 | B8: =Gen!C13 -> 0.36 | C8: 20545.39 | D8: 12114.52 | G8: 231 | I8: 33650.4 | J8: 22371.1 | K8: =L7 -> 38692 | L8: 38707 | M8: =L8-K8 -> 15 | N8: =O7 -> 32025 | O8: 32025 | P8: =O8-N8 -> 0 | Q8: =R7 -> 37427 | R8: 37437 | S8: =R8-Q8 -> 10 | T8: =U7 -> 35743 | U8: 35758 | V8: =U8-T8 -> 15 | W8: =X7 -> 24107 | X8: 24107 | Y8: =X8-W8 -> 0 | Z8: =Y8+V8+S8+P8+M8 -> 40 | AA8: 485 | AB8: 115 | AC8: =Gen!T13 -> 1859.92
A9: =Gen!B14 -> 44565 | B9: =Gen!C14 -> 0.35 | C9: 18408.21 | D9: 12114.52 | G9: 247.48 | I9: 33658.6 | J9: 22376.1 | K9: =L8 -> 38707 | L9: 38723 | M9: =L9-K9 -> 16 | N9: =O8 -> 32025 | O9: 32025 | P9: =O9-N9 -> 0 | Q9: =R8 -> 37437 | R9: 37437 | S9: =R9-Q9 -> 0 | T9: =U8 -> 35758 | U9: 35768 | V9: =U9-T9 -> 10 | W9: =X8 -> 24107 | X9: 24122 | Y9: =X9-W9 -> 15 | Z9: =Y9+V9+S9+P9+M9 -> 41 | AA9: 450 | AB9: 200 | AC9: =Gen!T14 -> 1889.7
A10: =Gen!B15 -> 44566 | B10: =Gen!C15 -> 0.26 | C10: 16581.82 | D10: 12114.52 | G10: 110 | I10: 33665.9 | J10: 22381.1 | K10: =L9 -> 38723 | L10: 38740 | M10: =L10-K10 -> 17 | N10: =O9 -> 32025 | O10: 32025 | P10: =O10-N10 -> 0 | Q10: =R9 -> 37437 | R10: 37437 | S10: =R10-Q10 -> 0 | T10: =U9 -> 35768 | U10: 35776 | V10: =U10-T10 -> 8 | W10: =X9 -> 24122 | X10: 24138 | Y10: =X10-W10 -> 16 | Z10: =Y10+V10+S10+P10+M10 -> 41 | AA10: 470 | AB10: 220 | AC10: =Gen!T15 -> 1716.39
A11: =Gen!B16 -> 44567 | B11: =Gen!C16 -> 0.31 | C11: 14455.63 | D11: 12114.52 | G11: 299.04 | I11: 33673.2 | J11: 22385.3 | K11: =L10 -> 38740 | L11: 38750 | M11: =L11-K11 -> 10 | N11: =O10 -> 32025 | O11: 32025 | P11: =O11-N11 -> 0 | Q11: =R10 -> 37437 | R11: 37451 | S11: =R11-Q11 -> 14 | T11: =U10 -> 35776 | U11: 35776 | V11: =U11-T11 -> 0 | W11: =X10 -> 24138 | X11: 24153 | Y11: =X11-W11 -> 15 | Z11: =Y11+V11+S11+P11+M11 -> 39 | AA11: 420 | AB11: 200 | AC11: =Gen!T16 -> 1829.15
A12: =Gen!B17 -> 44568 | B12: =Gen!C17 -> 0.2468 | C12: 12459.27 | D12: 12114.52 | G12: 133.01 | I12: 33681.1 | J12: 22390.2 | K12: =L11 -> 38750 | L12: 38750 | M12: =L12-K12 -> 0 | N12: =O11 -> 32025 | O12: 32025 | P12: =O12-N12 -> 0 | Q12: =R11 -> 37451 | R12: 37464 | S12: =R12-Q12 -> 13 | T12: =U11 -> 35776 | U12: 35784 | V12: =U12-T12 -> 8 | W12: =X11 -> 24153 | X12: 24170 | Y12: =X12-W12 -> 17 | Z12: =Y12+V12+S12+P12+M12 -> 38 | AA12: 480 | AB12: 250 | AC12: =Gen!T17 -> 1866.35
A13: =Gen!B18 -> 44569 | B13: =Gen!C18 -> 0.23 | C13: 10525.85 | D13: 12114.52 | G13: 162.47 | I13: 33688.9 | J13: 22394.8 | K13: =L12 -> 38750 | L13: 38766 | M13: =L13-K13 -> 16 | N13: =O12 -> 32025 | O13: 32025 | P13: =O13-O12 -> 0 | Q13: =R12 -> 37464 | R13: 37480 | S13: =R13-Q13 -> 16 | T13: =U12 -> 35784 | U13: 35792 | V13: =U13-T13 -> 8 | W13: =X12 -> 24170 | X13: 24170 | Y13: =X13-W13 -> 0 | Z13: =Y13+V13+S13+P13+M13 -> 40 | AA13: 440 | AB13: 260 | AC13: =Gen!T18 -> 1767.24
A14: =Gen!B19 -> 44570 | B14: =Gen!C19 -> 0.2078 | C14: 26570.06 | D14: 12114.52 | E14: 44805 | F14: 18000 | G14: 109.74 | I14: 33696.9 | J14: 22399.1 | K14: =L13 -> 38766 | L14: 38782 | M14: =L14-K14 -> 16 | N14: =O14 -> 32025 | O14: 32025 | P14: =O14-O13 -> 0 | Q14: =R13 -> 37480 | R14: 37482 | S14: =R14-Q14 -> 2 | T14: =U13 -> 35792 | U14: 35800 | V14: =U14-T14 -> 8 | W14: =X13 -> 24170 | X14: 24187 | Y14: =X14-W14 -> 17 | Z14: =Y14+V14+S14+P14+M14 -> 43 | AA14: 485 | AB14: 260 | AC14: =Gen!T19 -> 1846.05
A15: =Gen!B20 -> 44571 | B15: =Gen!C20 -> 0.17 | C15: 24724.6 | D15: 12114.52 | G15: 79.83 | I15: 33704.9 | J15: 22403.6 | K15: =L14 -> 38782 | L15: 38782 | M15: =L15-K15 -> 0 | N15: =O15 -> 32025 | O15: 32025 | P15: =O15-O14 -> 0 | Q15: =R14 -> 37482 | R15: 37497 | S15: =R15-Q15 -> 15 | T15: =U14 -> 35800 | U15: 35808 | V15: =U15-T15 -> 8 | W15: =X14 -> 24187 | X15: 24203 | Y15: =X15-W15 -> 16 | Z15: =Y15+V15+S15+P15+M15 -> 39 | AA15: 485 | AB15: 200 | AC15: =Gen!T20 -> 1765.63
A16: =Gen!B21 -> 44572 | B16: =Gen!C21 -> 0.1 | C16: 21113.09 | D16: 12114.52 | G16: 66.311 | I16: 33712.6 | J16: 22403.6 | K16: =L15 -> 38782 | L16: 38798 | M16: =L16-K16 -> 16 | N16: =O15 -> 32025 | O16: 32025 | P16: =O16-O15 -> 0 | Q16: =R15 -> 37497 | R16: 37514 | S16: =R16-Q16 -> 17 | T16: =U14 -> 35800 | U16: 35816 | V16: =U16-T16 -> 16 | W16: =X15 -> 24203 | X16: 24203 | Y16: =X16-W16 -> 0 | Z16: =Y16+V16+S16+P16+M16 -> 49 | AA16: 300 | AB16: 115 | AC16: =Gen!T21 -> 1625.28
A17: =Gen!B22 -> 44573 | B17: =Gen!C22 -> 0.0649 | C17: 19539.48 | D17: 12114.52 | G17: 288..08 | I17: 33719.3 | J17: 22411.7 | K17: =L16 -> 38798 | L17: 38815 | M17: =L17-K17 -> 17 | N17: =O16 -> 32025 | O17: 32025 | P17: =O17-O16 -> 0 | Q17: =R16 -> 37514 | R17: 37514 | S17: =R17-Q17 -> 0 | T17: =U16 -> 35816 | U17: 35824 | V17: =U17-T17 -> 8 | W17: =X16 -> 24203 | X17: 24220 | Y17: =X17-W17 -> 17 | Z17: =Y17+V17+S17+P17+M17 -> 42 | AA17: 360 | AB17: 250 | AC17: =Gen!T22 -> 1599.77
A18: =Gen!B23 -> 44574 | B18: =Gen!C23 -> 0.13 | C18: 17739.49 | D18: 12114.52 | I18: 33726.1 | J18: 22415.4 | K18: =L17 -> 38815 | L18: 38815 | M18: =L18-K18 -> 0 | N18: =O17 -> 32025 | O18: 32025 | P18: =O18-O17 -> 0 | Q18: =R17 -> 37514 | R18: 37529 | S18: =R18-Q18 -> 15 | T18: =U17 -> 35824 | U18: 35835 | V18: =U18-T18 -> 11 | W18: =X17 -> 24220 | X18: 24220 | Y18: =X18-W18 -> 0 | Z18: =Y18+V18+S18+P18+M18 -> 26 | AA18: 300 | AB18: 115 | AC18: =Gen!T23 -> 1507.29
A19: =Gen!B24 -> 44575 | B19: =Gen!C24 -> 0.18 | C19: 16296.49 | D19: 12114.52 | I19: 33733.5 | J19: 22419.1 | K19: =L18 -> 38815 | L19: 38823 | M19: =L19-K19 -> 8 | N19: =O18 -> 32025 | O19: 32025 | P19: =O19-O18 -> 0 | Q19: =R18 -> 37529 | R19: 37531 | S19: =R19-Q19 -> 2 | T19: =U18 -> 35835 | U19: 35835 | V19: =U19-T19 -> 0 | W19: =X18 -> 24220 | X19: 24236 | Y19: =X19-W19 -> 16 | Z19: =Y19+V19+S19+P19+M19 -> 26 | AA19: 300 | AB19: 115 | AC19: =Gen!T24 -> 1511.92
A20: =Gen!B25 -> 44576 | B20: =Gen!C25 -> 0.16 | C20: 14495.11 | D20: 12114.52 | I20: 33740.2 | J20: 22423.1 | K20: =L19 -> 38823 | L20: 38823 | M20: =L20-K20 -> 0 | N20: =O19 -> 32025 | O20: 32025 | P20: =O20-O19 -> 0 | Q20: =R19 -> 37531 | R20: 37546 | S20: =R20-Q20 -> 15 | T20: =U19 -> 35835 | U20: 35845 | V20: =U20-T20 -> 10 | W20: =X19 -> 24236 | X20: 24236 | Y20: =X20-W20 -> 0 | Z20: =Y20+V20+S20+P20+M20 -> 25 | AA20: 300 | AB20: 120 | AC20: =Gen!T25 -> 1442
A21: =Gen!B26 -> 44577 | B21: =Gen!C26 -> 0.18 | C21: 13274.64 | D21: 12114.52 | G21: 447 | I21: 33746.8 | J21: 22426.9 | K21: =L20 -> 38823 | L21: 38836 | M21: =L21-K21 -> 13 | N21: =O20 -> 32025 | O21: 32025 | P21: =O21-O20 -> 0 | Q21: =R20 -> 37546 | R21: 37546 | S21: =R21-Q21 -> 0 | T21: =U20 -> 35845 | U21: 35846 | V21: =U21-T21 -> 1 | W21: =X20 -> 24236 | X21: 24251 | Y21: =X21-W21 -> 15 | Z21: =Y21+V21+S21+P21+M21 -> 29 | AA21: 280 | AB21: 100 | AC21: =Gen!T26 -> 1354.38
A22: =Gen!B27 -> 44578 | B22: =Gen!C27 -> 0.09 | C22: 11670.99 | D22: 12114.52 | I22: 33752.7 | J22: 22430.5 | K22: =L21 -> 38836 | L22: 38836 | M22: =L22-K22 -> 0 | N22: =O21 -> 32025 | O22: 32025 | P22: =O22-O21 -> 0 | Q22: =R21 -> 37546 | R22: 37560 | S22: =R22-Q22 -> 14 | T22: =U21 -> 35846 | U22: 35855 | V22: =U22-T22 -> 9 | W22: =X21 -> 24251 | X22: 24251 | Y22: =X22-W22 -> 0 | Z22: =Y22+V22+S22+P22+M22 -> 23 | AA22: 285 | AB22: 115 | AC22: =Gen!T27 -> 1220.47
A23: =Gen!B28 -> 44579 | B23: =Gen!C28 -> 0.16 | C23: 10293.44 | D23: 12114.52 | G23: 221.1 | I23: 33764.7 | J23: 22433.5 | K23: =L22 -> 38836 | L23: 38846 | M23: =L23-K23 -> 10 | N23: =O22 -> 32025 | O23: 32025 | P23: =O23-O22 -> 0 | Q23: =R22 -> 37560 | R23: 37561 | S23: =R23-Q23 -> 1 | T23: =U22 -> 35855 | U23: 35855 | V23: =U23-T23 -> 0 | W23: =X22 -> 24251 | X23: 24266 | Y23: =X23-W23 -> 15 | Z23: =Y23+V23+S23+P23+M23 -> 26 | AA23: 290 | AB23: 200 | AC23: =Gen!T28 -> 1382.64
A24: =Gen!B29 -> 44580 | B24: =Gen!C29 -> 0.18 | C24: 8684.97 | D24: 12114.52 | G24: 127.84 | I24: 33770.3 | J24: 22436.7 | K24: =L23 -> 38846 | L24: 38846 | M24: =L24-K24 -> 0 | N24: =O23 -> 32025 | O24: 32025 | P24: =O24-N24 -> 0 | Q24: =R23 -> 37561 | R24: 37575 | S24: =R24-Q24 -> 14 | T24: =U23 -> 35855 | U24: 35866 | V24: =U24-T24 -> 11 | W24: =X23 -> 24266 | X24: 24266 | Y24: =X24-W24 -> 0 | Z24: =Y24+V24+S24+P24+M24 -> 25 | AA24: 300 | AB24: 250 | AC24: =Gen!T29 -> 1252.71
A25: =Gen!B30 -> 44581 | B25: =Gen!C30 -> 0.21 | C25: 5185.51 | D25: 12114.52 | G25: 238.02 | I25: 33776.4 | J25: 22443.3 | K25: =L24 -> 38846 | L25: 38846 | M25: =L25-K25 -> 0 | N25: =O24 -> 32025 | O25: 32025 | P25: =O25-N25 -> 0 | Q25: =R24 -> 37575 | R25: 37585 | S25: =R25-Q25 -> 10 | T25: =U24 -> 35866 | U25: 35866 | V25: =U25-T25 -> 0 | W25: =X24 -> 24266 | X25: 24281 | Y25: =X25-W25 -> 15 | Z25: =Y25+V25+S25+P25+M25 -> 25 | AA25: 250 | AB25: 90 | AC25: =Gen!T30 -> 1370.45
A26: =Gen!B31 -> 44582 | B26: =Gen!C31 -> 0.09 | C26: 5185.51 | D26: 14318.67 | G26: 15 | I26: 33782.2 | J26: 22446.4 | K26: =L25 -> 38846 | L26: 38846 | M26: =L26-K26 -> 0 | N26: =O25 -> 32025 | O26: 32025 | P26: =O26-N26 -> 0 | Q26: =R25 -> 37585 | R26: 37595 | S26: =R26-Q26 -> 10 | T26: =U25 -> 35866 | U26: 35881 | V26: =U26-T26 -> 15 | W26: =X25 -> 24281 | X26: 24281 | Y26: =X26-W26 -> 0 | Z26: =Y26+V26+S26+P26+M26 -> 25 | AA26: 230 | AB26: 100 | AC26: =Gen!T31 -> 1280.31
A27: =Gen!B32 -> 44583 | B27: =Gen!C32 -> 0.08 | C27: 5185.51 | D27: 29315.07 | G27: 264.82 | I27: 33787.8 | J27: 22449.7 | K27: =L26 -> 38846 | L27: 38857 | M27: =L27-K27 -> 11 | N27: =O26 -> 32025 | O27: 32025 | P27: =O27-N27 -> 0 | Q27: =R26 -> 37595 | R27: 37602 | S27: =R27-Q27 -> 7 | T27: =U26 -> 35881 | U27: 35881 | V27: =U27-T27 -> 0 | W27: =X26 -> 24281 | X27: 24289 | Y27: =X27-W27 -> 8 | Z27: =Y27+V27+S27+P27+M27 -> 26 | AA27: 250 | AB27: 115 | AC27: =Gen!T32 -> 1286.26
A28: =Gen!B33 -> 44584 | B28: =Gen!C33 -> 0.04 | C28: 5185.51 | D28: 30162.08 | E28: 23/1/2022 | F28: 18000 | G28: 253.24 | I28: 33793.1 | J28: 22452.6 | K28: =L27 -> 38857 | L28: 38857 | M28: =L28-K28 -> 0 | N28: =O27 -> 32025 | O28: 32025 | P28: =O28-N28 -> 0 | Q28: =R27 -> 37602 | R28: 37602 | S28: =R28-Q28 -> 0 | T28: =U27 -> 35881 | U28: 35889 | V28: =U28-T28 -> 8 | W28: =X27 -> 24289 | X28: 24305 | Y28: =X28-W28 -> 16 | Z28: =Y28+V28+S28+P28+M28 -> 24 | AA28: 300 | AB28: 200 | AC28: =Gen!T33 -> 1199.28
A29: =Gen!B34 -> 44585 | B29: =Gen!C34 -> 0.1 | C29: 21732.99 | D29: 12767.59 | G29: 237.04 | I29: 33798.8 | J29: 22456.1 | K29: =L28 -> 38857 | L29: 38868 | M29: =L29-K29 -> 11 | N29: =O28 -> 32025 | O29: 32025 | P29: =O29-N29 -> 0 | Q29: =R28 -> 37602 | R29: 37616 | S29: =R29-Q29 -> 14 | T29: =U28 -> 35889 | U29: 35890 | V29: =U29-T29 -> 1 | W29: =X28 -> 24305 | X29: 24305 | Y29: =X29-W29 -> 0 | Z29: =Y29+V29+S29+P29+M29 -> 26 | AA29: 260 | AB29: 120 | AC29: =Gen!T34 -> 1340.81
A30: =Gen!B35 -> 44586 | B30: =Gen!C35 -> 0.14 | C30: 20155.14 | D30: 12767.59 | G30: 118.03 | I30: 33804.5 | J30: 22459.4 | K30: =L29 -> 38868 | L30: 38868 | M30: =L30-K30 -> 0 | N30: =O29 -> 32025 | O30: 32025 | P30: =O30-N30 -> 0 | Q30: =R29 -> 37616 | R30: 37625 | S30: =R30-Q30 -> 9 | T30: =U29 -> 35890 | U30: 35905 | V30: =U30-T30 -> 15 | W30: =X29 -> 24305 | X30: 24305 | Y30: =X30-W30 -> 0 | Z30: =Y30+V30+S30+P30+M30 -> 24 | AA30: 280 | AB30: 150 | AC30: =Gen!T35 -> 1255.47
A31: =Gen!B36 -> 44587 | B31: =Gen!C36 -> 0.16 | C31: 18781.64 | D31: 12767.59 | G31: 73.37 | I31: 33810.8 | J31: 22463.2 | K31: =L30 -> 38868 | L31: 38868 | M31: =L31-K31 -> 0 | N31: =O30 -> 32025 | O31: 32025 | P31: =O31-N31 -> 0 | Q31: =R30 -> 37625 | R31: 37635 | S31: =R31-Q31 -> 10 | T31: =U30 -> 35905 | U31: 35905 | V31: =U31-T31 -> 0 | W31: =X30 -> 24305 | X31: 24321 | Y31: =X31-W31 -> 16 | Z31: =Y31+V31+S31+P31+M31 -> 26 | AA31: 260 | AB31: 200 | AC31: =Gen!T36 -> 1351.98
A32: =Gen!B37 -> 44588 | B32: =Gen!C37 -> 0.13 | C32: 17356.29 | D32: 12767.59 | E32: 27/1/2022 | F32: 15000 | G32: 353.88 | I32: 33817.1 | J32: 22466.9 | K32: =L31 -> 38868 | L32: 38883 | M32: =L32-K32 -> 15 | N32: =O31 -> 32025 | O32: 32025 | P32: =O32-N32 -> 0 | Q32: =R31 -> 37635 | R32: 37635 | S32: =R32-Q32 -> 0 | T32: =U31 -> 35905 | U32: 35914 | V32: =U32-T32 -> 9 | W32: =X31 -> 24321 | X32: 24321 | Y32: =X32-W32 -> 0 | Z32: =Y32+V32+S32+P32+M32 -> 24 | AA32: 230 | AB32: 100 | AC32: =Gen!T37 -> 1411.45
A33: =Gen!B38 -> 44589 | B33: =Gen!C38 -> 0.09 | C33: 32590.96 | D33: 12767.59 | I33: 33823.4 | J33: 22470.7 | K33: =L32 -> 38883 | L33: 38883 | M33: =L33-K33 -> 0 | N33: =O32 -> 32025 | O33: 32025 | P33: =O33-N33 -> 0 | Q33: =R32 -> 37635 | R33: 37644 | S33: =R33-Q33 -> 9 | T33: =U32 -> 35914 | U33: 35914 | V33: =U33-T33 -> 0 | W33: =X32 -> 24321 | X33: 24336 | Y33: =X33-W33 -> 15 | Z33: =Y33+V33+S33+P33+M33 -> 24 | AA33: 220 | AB33: 120 | AC33: =Gen!T38 -> 1429.2
A34: =Gen!B39 -> 44590 | B34: =Gen!C39 -> 0.09 | C34: 29161.76 | D34: 12767.59 | G34: 48.59 | I34: 33829.8 | J34: 22474.4 | K34: =L33 -> 38883 | L34: 38893 | M34: =L34-K34 -> 10 | N34: =O33 -> 32025 | O34: 32025 | P34: =O34-N34 -> 0 | Q34: =R34 -> 37644 | R34: 37644 | S34: =R34-Q34 -> 0 | T34: =U33 -> 35914 | U34: 35930 | V34: =U34-T34 -> 16 | W34: =X33 -> 24336 | X34: 24336 | Y34: =X34-W34 -> 0 | Z34: =Y34+V34+S34+P34+M34 -> 26 | AA34: 260 | AB34: 220 | AC34: =Gen!T39 -> 1414.19
A35: =Gen!B40 -> 44591 | B35: =Gen!C40 -> 0.06 | C35: 27698.98 | D35: 12767.59 | I35: 33835.8 | J35: 22478.3 | K35: =L34 -> 38893 | L35: 38893 | M35: =L35-K35 -> 0 | N35: =O34 -> 32025 | O35: 32025 | P35: =O35-N35 -> 0 | Q35: =R35 -> 37655 | R35: 37655 | S35: =R35-Q35 -> 0 | T35: =U34 -> 35930 | U35: 35930 | V35: =U35-T35 -> 0 | W35: =X34 -> 24336 | X35: 24352 | Y35: =X35-W35 -> 16 | Z35: =Y35+V35+S35+P35+M35 -> 16 | AA35: 280 | AB35: 200 | AC35: =Gen!T40 -> 1346.87
A36: =Gen!B41 -> 44592 | B36: =Gen!C41 -> 0.05 | C36: 26253.11 | D36: 12767.59 | F36: =Gen!E40 -> 0 | I36: 33841.6 | J36: 22481.6 | K36: =L35 -> 38893 | L36: 38903 | M36: =L36-K36 -> 10 | N36: =O35 -> 32025 | O36: 32025 | P36: =O36-N36 -> 0 | Q36: =R35 -> 37655 | R36: 37655 | S36: =R36-Q36 -> 0 | T36: =U35 -> 35930 | U36: 35944 | V36: =U36-T36 -> 14 | W36: =X35 -> 24352 | X36: 24352 | Y36: =X36-W36 -> 0 | Z36: =Y36+V36+S36+P36+M36 -> 24
A37: =Gen!B42 -> 0 | B37: =Gen!C42 -> 0 | C37: 24225.85 | D37: 12767.59 | K37: =L36 -> 38903 | M37: =L37-K37 -> -38903 | N37: =O36 -> 32025 | P37: =O37-N37 -> -32025 | Q37: =R36 -> 37655 | T37: =U36 -> 35944 | V37: =U37-T37 -> -35944 | W37: =X36 -> 24352 | Y37: =X37-W37 -> -24352 | Z37: =Y37+V37+S37+P37+M37 -> -131224

Sheet Water-Meter
A1: Four Seasons Safari Lodge Serengeti - Water Report
C2: Main Meter | F2: KITCHEN | I2: Amani café | L2: Main SW POOL | O2: Laundry | S2: BORE HOLE NO.1 METER READING | V2: BORE HOLE NO.2 METER READING | Y2: BORE HOLE NO.3 METER READING | AB2: BORE HOLE NO.4 METER READING | AE2: BORE HOLE NO.5 METER READING | AH2: BORE HOLE NO.6 METER READING | AK2: RAIN WATER - METER READING | AN2: TOTAL WATER PRODUCTION
A3: DATE | C3: Open Bal | D3: Final | E3: consumption | F3: Open Bal | G3: Final | H3: consumption | I3: Open Bal | J3: Final | K3: consumption | L3: Open Bal | M3: Final | N3: consumption | O3: Open Bal | P3: Final | Q3: consumption | R3: Total consumption
S4: OPEN | T4: FINAL | U4: PROD. | V4: OPEN | W4: FINAL | X4: PROD. | Y4: OPEN | Z4: FINAL | AA4: PROD. | AB4: OPEN | AC4: FINAL | AD4: M3 | AE4: OPEN | AF4: FINAL | AG4: M3 | AH4: OPEN | AI4: FINAL | AJ4: M3 | AK4: OPEN | AL4: FINAL | AM4: M3
C5: =D4 -> 0 | D5: 277383 | E5: =IF((D6-D5)<0,"0",(D6-D5)) -> 116 | F5: =G4 -> 0 | H5: 0 | I5: =J4 -> 0 | J5: 8965 | L5: =M4 -> 0 | N5: 0 | O5: =P4 -> 0 | P5: 22928 | T5: 80966 | V5: =W4 -> FINAL | X5: 0 | Y5: =Z4 -> FINAL | Z5: 97863 | AA5: 0 | AB5: =AC4 -> FINAL | AC5: 23590 | AE5: =AF4 -> FINAL | AG5: 0 | AH5: =AI4 -> FINAL | AI5: 38601 | AK5: =AL4 -> FINAL | AN5: =U5+X5+AA5+AD5+AG5+AJ5+AM5 -> 0
A6: =Gen!B11 -> 44562 | C6: =D5 -> 277383 | D6: 277499 | E6: =IF((D6-D5)<0,"0",(D6-D5)) -> 116 | F6: =G5 -> 0 | H6: =IF((G6-G5)<0,"0",(G6-G5)) -> 0 | I6: =J5 -> 8965 | J6: 8968 | K6: =J6-J5 -> 3 | L6: =M5 -> 0 | N6: =IF((M6-M5)<0,"0",(M6-M5)) -> 0 | O6: =P5 -> 22928 | P6: 22939 | Q6: =IF((P6-P5)<0,"0",(P6-P5)) -> 11 | R6: =Q6+N6+K6+H6 -> 14 | S6: =T5 -> 80966 | T6: 81035 | U6: =IF((T6-T5)<0,"0",(T6-T5)) -> 69 | V6: =W5 -> 0 | X6: =IF((W6-W5)<0,"0",(W6-W5)) -> 0 | Y6: =Z5 -> 97863 | Z6: 97899 | AA6: =IF((Z6-Z5)<0,"0",(Z6-Z5)) -> 36 | AB6: =AC5 -> 23590 | AC6: 23607 | AD6: =IF((AC6-AC5)<0,"0",(AC6-AC5)) -> 17 | AE6: =AF5 -> 0 | AG6: =IF((AF6-AF5)<0,"0",(AF6-AF5)) -> 0 | AH6: =AI5 -> 38601 | AI6: 38636 | AJ6: =IF((AI6-AI5)<0,"0",(AI6-AI5)) -> 35 | AK6: =AL5 -> 0 | AM6: =IF((AL6-AL5)<0,"0",(AL6-AL5)) -> 0 | AN6: =U6+X6+AA6+AD6+AG6+AJ6+AM6 -> 157
A7: =Gen!B12 -> 44563 | C7: =D6 -> 277499 | D7: 277593 | E7: =IF((D7-D6)<0,"0",(D7-D6)) -> 94 | F7: =G6 -> 0 | H7: =IF((G7-G6)<0,"0",(G7-G6)) -> 0 | I7: =J6 -> 8968 | J7: 8971 | K7: =J7-J6 -> 3 | L7: =M6 -> 0 | N7: =IF((M7-M6)<0,"0",(M7-M6)) -> 0 | O7: =P6 -> 22939 | P7: 22948 | Q7: =IF((P7-P6)<0,"0",(P7-P6)) -> 9 | R7: =Q7+N7+K7+H7 -> 12 | S7: =T6 -> 81035 | T7: 81105 | U7: =IF((T7-T6)<0,"0",(T7-T6)) -> 70 | V7: =W6 -> 0 | X7: =IF((W7-W6)<0,"0",(W7-W6)) -> 0 | Y7: =Z6 -> 97899 | Z7: 97935 | AA7: =IF((Z7-Z6)<0,"0",(Z7-Z6)) -> 36 | AB7: =AC6 -> 23607 | AC7: 23625 | AD7: =IF((AC7-AC6)<0,"0",(AC7-AC6)) -> 18 | AE7: =AF6 -> 0 | AG7: =IF((AF7-AF6)<0,"0",(AF7-AF6)) -> 0 | AH7: =AI6 -> 38636 | AI7: 38671 | AJ7: =IF((AI7-AI6)<0,"0",(AI7-AI6)) -> 35 | AK7: =AL6 -> 0 | AM7: =IF((AL7-AL6)<0,"0",(AL7-AL6)) -> 0 | AN7: =U7+X7+AA7+AD7+AG7+AJ7+AM7 -> 159
A8: =Gen!B13 -> 44564 | C8: =D7 -> 277593 | D8: 277703 | E8: =IF((D8-D7)<0,"0",(D8-D7)) -> 110 | F8: =G7 -> 0 | H8: =IF((G8-G7)<0,"0",(G8-G7)) -> 0 | I8: =J7 -> 8971 | J8: 8975 | K8: =J8-J7 -> 4 | L8: =M7 -> 0 | N8: =IF((M8-M7)<0,"0",(M8-M7)) -> 0 | O8: =P7 -> 22948 | P8: 22960 | Q8: =IF((P8-P7)<0,"0",(P8-P7)) -> 12 | R8: =Q8+N8+K8+H8 -> 16 | S8: =T7 -> 81105 | T8: 81172 | U8: =IF((T8-T7)<0,"0",(T8-T7)) -> 67 | V8: =W7 -> 0 | X8: =IF((W8-W7)<0,"0",(W8-W7)) -> 0 | Y8: =Z7 -> 97935 | Z8: 97971 | AA8: =IF((Z8-Z7)<0,"0",(Z8-Z7)) -> 36 | AB8: =AC7 -> 23625 | AC8: 23643 | AD8: =IF((AC8-AC7)<0,"0",(AC8-AC7)) -> 18 | AE8: =AF7 -> 0 | AG8: =IF((AF8-AF7)<0,"0",(AF8-AF7)) -> 0 | AH8: =AI7 -> 38671 | AI8: 38707 | AJ8: =IF((AI8-AI7)<0,"0",(AI8-AI7)) -> 36 | AK8: =AL7 -> 0 | AM8: =IF((AL8-AL7)<0,"0",(AL8-AL7)) -> 0 | AN8: =U8+X8+AA8+AD8+AG8+AJ8+AM8 -> 157
A9: =Gen!B14 -> 44565 | C9: =D8 -> 277703 | D9: 277797 | E9: =IF((D9-D8)<0,"0",(D9-D8)) -> 94 | F9: =G8 -> 0 | H9: =IF((G9-G8)<0,"0",(G9-G8)) -> 0 | I9: =J8 -> 8975 | J9: 8978 | K9: =J9-J8 -> 3 | L9: =M8 -> 0 | N9: =IF((M9-M8)<0,"0",(M9-M8)) -> 0 | O9: =P8 -> 22960 | P9: 22969 | Q9: =IF((P9-P8)<0,"0",(P9-P8)) -> 9 | R9: =Q9+N9+K9+H9 -> 12 | S9: =T8 -> 81172 | T9: 81241 | U9: =IF((T9-T8)<0,"0",(T9-T8)) -> 69 | V9: =W8 -> 0 | X9: =IF((W9-W8)<0,"0",(W9-W8)) -> 0 | Y9: =Z8 -> 97971 | Z9: 98009 | AA9: =IF((Z9-Z8)<0,"0",(Z9-Z8)) -> 38 | AB9: =AC8 -> 23643 | AC9: 23661 | AD9: =IF((AC9-AC8)<0,"0",(AC9-AC8)) -> 18 | AE9: =AF8 -> 0 | AG9: =IF((AF9-AF8)<0,"0",(AF9-AF8)) -> 0 | AH9: =AI8 -> 38707 | AI9: 38745 | AJ9: =IF((AI9-AI8)<0,"0",(AI9-AI8)) -> 38 | AK9: =AL8 -> 0 | AM9: =IF((AL9-AL8)<0,"0",(AL9-AL8)) -> 0 | AN9: =U9+X9+AA9+AD9+AG9+AJ9+AM9 -> 163
A10: =Gen!B15 -> 44566 | C10: =D9 -> 277797 | D10: 277883 | E10: =IF((D10-D9)<0,"0",(D10-D9)) -> 86 | F10: =G9 -> 0 | H10: =IF((G10-G9)<0,"0",(G10-G9)) -> 0 | I10: =J9 -> 8978 | J10: 8981 | K10: =J10-J9 -> 3 | L10: =M9 -> 0 | N10: =IF((M10-M9)<0,"0",(M10-M9)) -> 0 | O10: =P9 -> 22969 | P10: 22978 | Q10: =IF((P10-P9)<0,"0",(P10-P9)) -> 9 | R10: =Q10+N10+K10+H10 -> 12 | S10: =T9 -> 81241 | T10: 81310 | U10: =IF((T10-T9)<0,"0",(T10-T9)) -> 69 | V10: =W9 -> 0 | X10: =IF((W10-W9)<0,"0",(W10-W9)) -> 0 | Y10: =Z9 -> 98009 | Z10: 98047 | AA10: =IF((Z10-Z9)<0,"0",(Z10-Z9)) -> 38 | AB10: =AC9 -> 23661 | AC10: 23677 | AD10: =IF((AC10-AC9)<0,"0",(AC10-AC9)) -> 16 | AE10: =AF9 -> 0 | AG10: =IF((AF10-AF9)<0,"0",(AF10-AF9)) -> 0 | AH10: =AI9 -> 38745 | AI10: 38778 | AJ10: =IF((AI10-AI9)<0,"0",(AI10-AI9)) -> 33 | AK10: =AL9 -> 0 | AM10: =IF((AL10-AL9)<0,"0",(AL10-AL9)) -> 0 | AN10: =U10+X10+AA10+AD10+AG10+AJ10+AM10 -> 156
A11: =Gen!B16 -> 44567 | C11: =D10 -> 277883 | D11: 277973 | E11: =IF((D11-D10)<0,"0",(D11-D10)) -> 90 | F11: =G10 -> 0 | H11: =IF((G11-G10)<0,"0",(G11-G10)) -> 0 | I11: =J10 -> 8981 | J11: 8980 | K11: =J11-J10 -> -1 | L11: =M10 -> 0 | N11: =IF((M11-M10)<0,"0",(M11-M10)) -> 0 | O11: =P10 -> 22978 | P11: 23012 | Q11: =IF((P11-P10)<0,"0",(P11-P10)) -> 34 | R11: =Q11+N11+K11+H11 -> 33 | S11: =T10 -> 81310 | T11: 81377 | U11: =IF((T11-T10)<0,"0",(T11-T10)) -> 67 | V11: =W10 -> 0 | X11: =IF((W12-W10)<0,"0",(W12-W10)) -> 0 | Y11: =Z10 -> 98047 | Z11: 98079 | AA11: =IF((Z11-Z10)<0,"0",(Z11-Z10)) -> 32 | AB11: =AC10 -> 23677 | AC11: 23694 | AD11: =IF((AC11-AC10)<0,"0",(AC11-AC10)) -> 17 | AE11: =AF11 -> 0 | AG11: =IF((AF11-AF10)<0,"0",(AF11-AF10)) -> 0 | AH11: =AI10 -> 38778 | AI11: 38814 | AJ11: =IF((AI11-AI10)<0,"0",(AI11-AI10)) -> 36 | AK11: =AL10 -> 0 | AM11: =IF((AL11-AL10)<0,"0",(AL11-AL10)) -> 0 | AN11: =U11+X11+AA11+AD11+AG11+AJ11+AM11 -> 152
A12: =Gen!B17 -> 44568 | C12: =D11 -> 277973 | D12: 278065 | E12: =IF((D12-D11)<0,"0",(D12-D11)) -> 92 | F12: =G11 -> 0 | H12: =IF((G12-G11)<0,"0",(G12-G11)) -> 0 | I12: =J11 -> 8980 | J12: 8982 | K12: =J12-J11 -> 2 | L12: =M11 -> 0 | N12: =IF((M12-M11)<0,"0",(M12-M11)) -> 0 | O12: =P11 -> 23012 | P12: 23020 | Q12: =IF((P12-P11)<0,"0",(P12-P11)) -> 8 | R12: =Q12+N12+K12+H12 -> 10 | S12: =T11 -> 81377 | T12: 81443 | U12: =IF((T12-T11)<0,"0",(T12-T11)) -> 66 | V12: =W12 -> 0 | X12: =IF((W13-W11)<0,"0",(W13-W11)) -> 0 | Y12: =Z11 -> 98079 | Z12: 98117 | AA12: =IF((Z12-Z11)<0,"0",(Z12-Z11)) -> 38 | AB12: =AC11 -> 23694 | AC12: 23710 | AD12: =IF((AC12-AC11)<0,"0",(AC12-AC11)) -> 16 | AE12: =AF12 -> 0 | AG12: =IF((AF12-AF11)<0,"0",(AF12-AF11)) -> 0 | AH12: =AI11 -> 38814 | AI12: 38851 | AJ12: =IF((AI12-AI11)<0,"0",(AI12-AI11)) -> 37 | AK12: =AL11 -> 0 | AM12: =IF((AL12-AL11)<0,"0",(AL12-AL11)) -> 0 | AN12: =U12+X12+AA12+AD12+AG12+AJ12+AM12 -> 157
A13: =Gen!B18 -> 44569 | C13: =D12 -> 278065 | D13: 278173 | E13: =IF((D13-D12)<0,"0",(D13-D12)) -> 108 | F13: =G12 -> 0 | H13: =IF((G13-G12)<0,"0",(G13-G12)) -> 0 | I13: =J12 -> 8982 | J13: 8984 | K13: =J13-J12 -> 2 | L13: =M12 -> 0 | N13: =IF((M13-M12)<0,"0",(M13-M12)) -> 0 | O13: =P12 -> 23020 | P13: 23026 | Q13: =IF((P13-P12)<0,"0",(P13-P12)) -> 6 | R13: =Q13+N13+K13+H13 -> 8 | S13: =T12 -> 81443 | T13: 81515 | U13: =IF((T13-T12)<0,"0",(T13-T12)) -> 72 | V13: =W13 -> 0 | X13: =IF((W14-W12)<0,"0",(W14-W12)) -> 0 | Y13: =Z12 -> 98117 | Z13: 98152 | AA13: =IF((Z13-Z12)<0,"0",(Z13-Z12)) -> 35 | AB13: =AC12 -> 23710 | AC13: 23726 | AD13: =IF((AC13-AC12)<0,"0",(AC13-AC12)) -> 16 | AE13: =AF13 -> 0 | AG13: =IF((AF13-AF12)<0,"0",(AF13-AF12)) -> 0 | AH13: =AI12 -> 38851 | AI13: 38886 | AJ13: =IF((AI13-AI12)<0,"0",(AI13-AI12)) -> 35 | AK13: =AL12 -> 0 | AM13: =IF((AL13-AL12)<0,"0",(AL13-AL12)) -> 0 | AN13: =U13+X13+AA13+AD13+AG13+AJ13+AM13 -> 158
A14: =Gen!B19 -> 44570 | C14: =D13 -> 278173 | D14: 278274 | E14: =IF((D14-D13)<0,"0",(D14-D13)) -> 101 | F14: =G13 -> 0 | H14: =IF((G14-G13)<0,"0",(G14-G13)) -> 0 | I14: =J13 -> 8984 | J14: 8987 | K14: =IF((J14-J13)<0,"0",(J14-J13)) -> 3 | L14: =M13 -> 0 | N14: =IF((M14-M13)<0,"0",(M14-M13)) -> 0 | O14: =P13 -> 23026 | P14: 23030 | Q14: =IF((P14-P13)<0,"0",(P14-P13)) -> 4 | R14: =Q14+N14+K14+H14 -> 7 | S14: =T13 -> 81515 | T14: 81582 | U14: =IF((T14-T13)<0,"0",(T14-T13)) -> 67 | V14: =W14 -> 0 | X14: =IF((W15-W13)<0,"0",(W15-W13)) -> 0 | Y14: =Z13 -> 98152 | Z14: 98191 | AA14: =IF((Z14-Z13)<0,"0",(Z14-Z13)) -> 39 | AB14: =AC13 -> 23726 | AC14: 23739 | AD14: =IF((AC14-AC13)<0,"0",(AC14-AC13)) -> 13 | AE14: =AF14 -> 0 | AG14: =IF((AF14-AF13)<0,"0",(AF14-AF13)) -> 0 | AH14: =AI13 -> 38886 | AI14: 38921 | AJ14: =IF((AI14-AI13)<0,"0",(AI14-AI13)) -> 35 | AK14: =AL13 -> 0 | AM14: =IF((AL14-AL13)<0,"0",(AL14-AL13)) -> 0 | AN14: =U14+X14+AA14+AD14+AG14+AJ14+AM14 -> 154
A15: =Gen!B20 -> 44571 | C15: =D14 -> 278274 | D15: 278357 | E15: =IF((D15-D14)<0,"0",(D15-D14)) -> 83 | F15: =G14 -> 0 | H15: =IF((G15-G14)<0,"0",(G15-G14)) -> 0 | I15: =J14 -> 8987 | J15: 8989 | K15: =IF((J15-J14)<0,"0",(J15-J14)) -> 2 | L15: =M14 -> 0 | N15: =IF((M15-M14)<0,"0",(M15-M14)) -> 0 | O15: =P14 -> 23030 | P15: 23047 | Q15: =IF((P15-P14)<0,"0",(P15-P14)) -> 17 | R15: =Q15+N15+K15+H15 -> 19 | S15: =T14 -> 81582 | T15: 81582 | U15: =IF((T15-T14)<0,"0",(T15-T14)) -> 0 | V15: =W14 -> 0 | X15: =IF((W15-W14)<0,"0",(W15-W14)) -> 0 | Y15: =Z14 -> 98191 | Z15: 98229 | AA15: =IF((Z15-Z14)<0,"0",(Z15-Z14)) -> 38 | AB15: =AC14 -> 23739 | AC15: 23753 | AD15: =IF((AC15-AC14)<0,"0",(AC15-AC14)) -> 14 | AE15: =AF15 -> 0 | AG15: =IF((AF15-AF14)<0,"0",(AF15-AF14)) -> 0 | AH15: =AI14 -> 38921 | AI15: 38957 | AJ15: =IF((AI15-AI14)<0,"0",(AI15-AI14)) -> 36 | AK15: =AL14 -> 0 | AM15: =IF((AL15-AL14)<0,"0",(AL15-AL14)) -> 0 | AN15: =U15+X15+AA15+AD15+AG15+AJ15+AM15 -> 88
A16: =Gen!B21 -> 44572 | C16: =D15 -> 278357 | D16: 278424 | E16: =IF((D16-D15)<0,"0",(D16-D15)) -> 67 | F16: =G15 -> 0 | H16: =IF((G16-G15)<0,"0",(G16-G15)) -> 0 | I16: =J15 -> 8989 | J16: 8991 | K16: =IF((J16-J15)<0,"0",(J16-J15)) -> 2 | L16: =M15 -> 0 | N16: =IF((M16-M15)<0,"0",(M16-M15)) -> 0 | O16: =P15 -> 23047 | P16: 23055 | Q16: =IF((P16-P15)<0,"0",(P16-P15)) -> 8 | R16: =Q16+N16+K16+H16 -> 10 | S16: =T15 -> 81582 | T16: 81582 | U16: =IF((T16-T15)<0,"0",(T16-T15)) -> 0 | V16: =W15 -> 0 | X16: =IF((W16-W15)<0,"0",(W16-W15)) -> 0 | Y16: =Z15 -> 98229 | Z16: 98271 | AA16: =IF((Z16-Z15)<0,"0",(Z16-Z15)) -> 42 | AB16: =AC15 -> 23753 | AC16: 23764 | AD16: =IF((AC16-AC15)<0,"0",(AC16-AC15)) -> 11 | AE16: =AF16 -> 0 | AG16: =IF((AF16-AF15)<0,"0",(AF16-AF15)) -> 0 | AH16: =AI15 -> 38957 | AI16: 38991 | AJ16: =IF((AI16-AI15)<0,"0",(AI16-AI15)) -> 34 | AK16: =AL15 -> 0 | AM16: =IF((AL16-AL15)<0,"0",(AL16-AL15)) -> 0 | AN16: =U16+X16+AA16+AD16+AG16+AJ16+AM16 -> 87
A17: =Gen!B22 -> 44573 | C17: =D16 -> 278424 | D17: 278557 | E17: =IF((D17-D16)<0,"0",(D17-D16)) -> 133 | F17: =G16 -> 0 | H17: =IF((G17-G16)<0,"0",(G17-G16)) -> 0 | I17: =J16 -> 8991 | J17: 8994 | K17: =IF((J17-J16)<0,"0",(J17-J16)) -> 3 | L17: =M16 -> 0 | N17: =IF((M17-M16)<0,"0",(M17-M16)) -> 0 | O17: =P16 -> 23055 | P17: 23064 | Q17: =IF((P17-P16)<0,"0",(P17-P16)) -> 9 | R17: =Q17+N17+K17+H17 -> 12 | S17: =T16 -> 81582 | T17: 81582 | U17: =IF((T17-T16)<0,"0",(T17-T16)) -> 0 | V17: =W16 -> 0 | X17: =IF((W17-W16)<0,"0",(W17-W16)) -> 0 | Y17: =Z16 -> 98271 | Z17: 98309 | AA17: =IF((Z17-Z16)<0,"0",(Z17-Z16)) -> 38 | AB17: =AC16 -> 23764 | AC17: 23777 | AD17: =IF((AC17-AC16)<0,"0",(AC17-AC16)) -> 13 | AE17: =AF17 -> 0 | AG17: =IF((AF17-AF16)<0,"0",(AF17-AF16)) -> 0 | AH17: =AI16 -> 38991 | AI17: 39026 | AJ17: =IF((AI17-AI16)<0,"0",(AI17-AI16)) -> 35 | AK17: =AL16 -> 0 | AM17: =IF((AL17-AL16)<0,"0",(AL17-AL16)) -> 0 | AN17: =U17+X17+AA17+AD17+AG17+AJ17+AM17 -> 86
A18: =Gen!B23 -> 44574 | C18: =D17 -> 278557 | D18: 278643 | E18: =IF((D18-D17)<0,"0",(D18-D17)) -> 86 | F18: =G17 -> 0 | H18: =IF((G18-G17)<0,"0",(G18-G17)) -> 0 | J18: 8996 | K18: =IF((J18-J17)<0,"0",(J18-J17)) -> 2 | L18: =M17 -> 0 | N18: =IF((M18-M17)<0,"0",(M18-M17)) -> 0 | O18: =P17 -> 23064 | P18: 23070 | Q18: =IF((P18-P17)<0,"0",(P18-P17)) -> 6 | R18: =Q18+N18+K18+H18 -> 8 | S18: =T17 -> 81582 | T18: 81582 | U18: =IF((T18-T17)<0,"0",(T18-T17)) -> 0 | V18: =W17 -> 0 | X18: =IF((W18-W17)<0,"0",(W18-W17)) -> 0 | Y18: =Z17 -> 98309 | Z18: 98348 | AA18: =IF((Z18-Z17)<0,"0",(Z18-Z17)) -> 39 | AB18: =AC17 -> 23777 | AC18: 23791 | AD18: =IF((AC18-AC17)<0,"0",(AC18-AC17)) -> 14 | AE18: =AF18 -> 0 | AG18: =IF((AF18-AF17)<0,"0",(AF18-AF17)) -> 0 | AH18: =AI17 -> 39026 | AI18: 39059 | AJ18: =IF((AI18-AI17)<0,"0",(AI18-AI17)) -> 33 | AK18: =AL17 -> 0 | AM18: =IF((AL18-AL17)<0,"0",(AL18-AL17)) -> 0 | AN18: =U18+X18+AA18+AD18+AG18+AJ18+AM18 -> 86
A19: =Gen!B24 -> 44575 | C19: =D18 -> 278643 | D19: 278735 | E19: =IF((D19-D18)<0,"0",(D19-D18)) -> 92 | F19: =G18 -> 0 | H19: =IF((G19-G18)<0,"0",(G19-G18)) -> 0 | I19: =J18 -> 8996 | J19: 8998 | K19: =IF((J19-J18)<0,"0",(J19-J18)) -> 2 | L19: =M18 -> 0 | N19: =IF((M19-M18)<0,"0",(M19-M18)) -> 0 | O19: =P18 -> 23070 | P19: 23078 | Q19: =IF((P19-P18)<0,"0",(P19-P18)) -> 8 | R19: =Q19+N19+K19+H19 -> 10 | S19: =T18 -> 81582 | T19: 81582 | U19: =IF((T19-T18)<0,"0",(T19-T18)) -> 0 | V19: =W18 -> 0 | X19: =IF((W19-W18)<0,"0",(W19-W18)) -> 0 | Y19: =Z18 -> 98348 | Z19: 98388 | AA19: =IF((Z19-Z18)<0,"0",(Z19-Z18)) -> 40 | AB19: =AC18 -> 23791 | AC19: 23809 | AD19: =IF((AC19-AC18)<0,"0",(AC19-AC18)) -> 18 | AE19: =AF19 -> 0 | AG19: =IF((AF19-AF18)<0,"0",(AF19-AF18)) -> 0 | AH19: =AI18 -> 39059 | AI19: 39092 | AJ19: =IF((AI19-AI18)<0,"0",(AI19-AI18)) -> 33 | AK19: =AL18 -> 0 | AM19: =IF((AL19-AL18)<0,"0",(AL19-AL18)) -> 0 | AN19: =U19+X19+AA19+AD19+AG19+AJ19+AM19 -> 91
A20: =Gen!B25 -> 44576 | C20: =D19 -> 278735 | D20: 278837 | E20: =IF((D20-D19)<0,"0",(D20-D19)) -> 102 | F20: =G19 -> 0 | H20: =IF((G20-G19)<0,"0",(G20-G19)) -> 0 | I20: =J19 -> 8998 | J20: 9000 | K20: =IF((J20-J19)<0,"0",(J20-J19)) -> 2 | L20: =M19 -> 0 | N20: =IF((M20-M19)<0,"0",(M20-M19)) -> 0 | O20: =P19 -> 23078 | P20: 23088 | Q20: =IF((P20-P19)<0,"0",(P20-P19)) -> 10 | R20: =Q20+N20+K20+H20 -> 12 | S20: =T19 -> 81582 | T20: 81582 | U20: =IF((T20-T19)<0,"0",(T20-T19)) -> 0 | V20: =W19 -> 0 | X20: =IF((W20-W19)<0,"0",(W20-W19)) -> 0 | Y20: =Z19 -> 98388 | Z20: 98427 | AA20: =IF((Z20-Z19)<0,"0",(Z20-Z19)) -> 39 | AB20: =AC19 -> 23809 | AC20: 23836 | AD20: =IF((AC20-AC19)<0,"0",(AC20-AC19)) -> 27 | AE20: =AF20 -> 0 | AG20: =IF((AF20-AF19)<0,"0",(AF20-AF19)) -> 0 | AH20: =AI19 -> 39092 | AI20: 39092 | AJ20: =IF((AI20-AI19)<0,"0",(AI20-AI19)) -> 0 | AK20: =AL19 -> 0 | AM20: =IF((AL20-AL19)<0,"0",(AL20-AL19)) -> 0 | AN20: =U20+X20+AA20+AD20+AG20+AJ20+AM20 -> 66
A21: =Gen!B26 -> 44577 | C21: =D20 -> 278837 | D21: 278911 | E21: =IF((D21-D20)<0,"0",(D21-D20)) -> 74 | F21: =G20 -> 0 | H21: =IF((G21-G20)<0,"0",(G21-G20)) -> 0 | I21: =J20 -> 9000 | J21: 9002 | K21: =IF((J21-J20)<0,"0",(J21-J20)) -> 2 | L21: =M20 -> 0 | N21: =IF((M21-M20)<0,"0",(M21-M20)) -> 0 | O21: =P20 -> 23088 | P21: 23096 | Q21: =IF((P21-P20)<0,"0",(P21-P20)) -> 8 | R21: =Q21+N21+K21+H21 -> 10 | S21: =T22 -> 81582 | T21: 81582 | U21: =IF((T21-T20)<0,"0",(T21-T20)) -> 0 | V21: =W20 -> 0 | X21: =IF((W21-W20)<0,"0",(W21-W20)) -> 0 | Y21: =Z20 -> 98427 | Z21: 98463 | AA21: =IF((Z21-Z20)<0,"0",(Z21-Z20)) -> 36 | AB21: =AC20 -> 23836 | AC21: 23861 | AD21: =IF((AC21-AC20)<0,"0",(AC21-AC20)) -> 25 | AE21: =AF20 -> 0 | AG21: =IF((AF21-AF20)<0,"0",(AF21-AF20)) -> 0 | AH21: =AI20 -> 39092 | AI21: 39092 | AJ21: =IF((AI21-AI20)<0,"0",(AI21-AI20)) -> 0 | AK21: =AL20 -> 0 | AM21: =IF((AL21-AL20)<0,"0",(AL21-AL20)) -> 0 | AN21: =U21+X21+AA21+AD21+AG21+AJ21+AM21 -> 61
A22: =Gen!B27 -> 44578 | C22: =D21 -> 278911 | D22: 278979 | E22: =IF((D22-D21)<0,"0",(D22-D21)) -> 68 | F22: =G21 -> 0 | H22: =IF((G22-G21)<0,"0",(G22-G21)) -> 0 | I22: =J21 -> 9002 | J22: 9004 | K22: =IF((J22-J21)<0,"0",(J22-J21)) -> 2 | L22: =M21 -> 0 | N22: =IF((M22-M21)<0,"0",(M22-M21)) -> 0 | O22: =P21 -> 23096 | P22: 23103 | Q22: =IF((P22-P21)<0,"0",(P22-P21)) -> 7 | R22: =Q22+N22+K22+H22 -> 9 | S22: =T21 -> 81582 | T22: 81582 | U22: =IF((T22-T21)<0,"0",(T22-T21)) -> 0 | V22: =W21 -> 0 | X22: =IF((W22-W21)<0,"0",(W22-W21)) -> 0 | Y22: =Z21 -> 98463 | Z22: 98499 | AA22: =IF((Z22-Z21)<0,"0",(Z22-Z21)) -> 36 | AB22: =AC21 -> 23861 | AC22: 23886 | AD22: =IF((AC22-AC21)<0,"0",(AC22-AC21)) -> 25 | AE22: =AF21 -> 0 | AG22: =IF((AF22-AF21)<0,"0",(AF22-AF21)) -> 0 | AH22: =AI21 -> 39092 | AI22: 39092 | AJ22: =IF((AI22-AI21)<0,"0",(AI22-AI21)) -> 0 | AK22: =AL21 -> 0 | AM22: =IF((AL22-AL21)<0,"0",(AL22-AL21)) -> 0 | AN22: =U22+X22+AA22+AD22+AG22+AJ22+AM22 -> 61
A23: =Gen!B28 -> 44579 | C23: =D22 -> 278979 | D23: 279041 | E23: =IF((D23-D22)<0,"0",(D23-D22)) -> 62 | F23: =G22 -> 0 | H23: =IF((G23-G22)<0,"0",(G23-G22)) -> 0 | I23: =J22 -> 9004 | J23: 9006 | K23: =IF((J23-J22)<0,"0",(J23-J22)) -> 2 | L23: =M22 -> 0 | N23: =IF((M23-M22)<0,"0",(M23-M22)) -> 0 | O23: =P22 -> 23103 | P23: 23111 | Q23: =IF((P23-P22)<0,"0",(P23-P22)) -> 8 | R23: =Q23+N23+K23+H23 -> 10 | S23: =T22 -> 81582 | T23: 81582 | V23: =W22 -> 0 | X23: =IF((W23-W22)<0,"0",(W23-W22)) -> 0 | Y23: =Z22 -> 98499 | Z23: 98536 | AA23: =IF((Z23-Z22)<0,"0",(Z23-Z22)) -> 37 | AB23: =AC22 -> 23886 | AC23: 23912 | AD23: =IF((AC23-AC22)<0,"0",(AC23-AC22)) -> 26 | AE23: =AF22 -> 0 | AG23: =IF((AF23-AF22)<0,"0",(AF23-AF22)) -> 0 | AH23: =AI22 -> 39092 | AI23: 39092 | AJ23: =IF((AI23-AI22)<0,"0",(AI23-AI22)) -> 0 | AK23: =AL22 -> 0 | AM23: =IF((AL23-AL22)<0,"0",(AL23-AL22)) -> 0 | AN23: =U23+X23+AA23+AD23+AG23+AJ23+AM23 -> 63
A24: =Gen!B29 -> 44580 | C24: =D23 -> 279041 | D24: 279111 | E24: =IF((D24-D23)<0,"0",(D24-D23)) -> 70 | F24: =G23 -> 0 | H24: =IF((G24-G23)<0,"0",(G24-G23)) -> 0 | I24: =J23 -> 9006 | J24: 9008 | K24: =IF((J24-J23)<0,"0",(J24-J23)) -> 2 | L24: =M23 -> 0 | N24: =IF((M24-M23)<0,"0",(M24-M23)) -> 0 | O24: =P23 -> 23111 | P24: 23117 | Q24: =IF((P24-P23)<0,"0",(P24-P23)) -> 6 | R24: =Q24+N24+K24+H24 -> 8 | S24: =T23 -> 81582 | T24: 82210 | U24: =IF((T24-T25)<0,"0",(T24-T25)) -> 0 | V24: =W23 -> 0 | X24: =IF((W24-W23)<0,"0",(W24-W23)) -> 0 | Y24: =Z23 -> 98536 | Z24: 98575 | AA24: =IF((Z24-Z23)<0,"0",(Z24-Z23)) -> 39 | AB24: =AC23 -> 23912 | AC24: 23925 | AD24: =IF((AC24-AC23)<0,"0",(AC24-AC23)) -> 13 | AE24: =AF23 -> 0 | AG24: =IF((AF24-AF23)<0,"0",(AF24-AF23)) -> 0 | AH24: =AI23 -> 39092 | AI24: 39092 | AJ24: =IF((AI24-AI23)<0,"0",(AI24-AI23)) -> 0 | AK24: =AL23 -> 0 | AM24: =IF((AL24-AL23)<0,"0",(AL24-AL23)) -> 0 | AN24: =U24+X24+AA24+AD24+AG24+AJ24+AM24 -> 52
A25: =Gen!B30 -> 44581 | C25: =D24 -> 279111 | D25: 279199 | E25: =IF((D25-D24)<0,"0",(D25-D24)) -> 88 | F25: =G24 -> 0 | H25: =IF((G26-G24)<0,"0",(G26-G24)) -> 0 | I25: =J24 -> 9008 | J25: 9010 | K25: =IF((J25-J24)<0,"0",(J25-J24)) -> 2 | L25: =M24 -> 0 | N25: =IF((M25-M24)<0,"0",(M25-M24)) -> 0 | O25: =P24 -> 23117 | P25: 23124 | Q25: =IF((P25-P24)<0,"0",(P25-P24)) -> 7 | R25: =Q25+N25+K25+H25 -> 9 | S25: =T24 -> 82210 | T25: 82290 | U25: =IF((T25-T24)<0,"0",(T25-T24)) -> 80 | V25: =W24 -> 0 | X25: =IF((W25-W24)<0,"0",(W25-W24)) -> 0 | Y25: =Z24 -> 98575 | Z25: 98614 | AA25: =IF((Z25-Z24)<0,"0",(Z25-Z24)) -> 39 | AB25: =AC24 -> 23925 | AC25: 23939 | AD25: =IF((AC25-AC24)<0,"0",(AC25-AC24)) -> 14 | AE25: =AF24 -> 0 | AG25: =IF((AF25-AF24)<0,"0",(AF25-AF24)) -> 0 | AH25: =AI24 -> 39092 | AI25: 39092 | AJ25: =IF((AI25-AI24)<0,"0",(AI25-AI24)) -> 0 | AK25: =AL24 -> 0 | AM25: =IF((AL25-AL24)<0,"0",(AL25-AL24)) -> 0 | AN25: =U25+X25+AA25+AD25+AG25+AJ25+AM25 -> 133
A26: =Gen!B31 -> 44582 | C26: =D25 -> 279199 | D26: 279280 | E26: =IF((D26-D25)<0,"0",(D26-D25)) -> 81 | F26: =G26 -> 0 | H26: =IF((G27-G25)<0,"0",(G27-G25)) -> 0 | I26: =J25 -> 9010 | J26: 9012 | K26: =IF((J26-J25)<0,"0",(J26-J25)) -> 2 | L26: =M25 -> 0 | N26: =IF((M26-M25)<0,"0",(M26-M25)) -> 0 | O26: =P25 -> 23124 | P26: 23132 | Q26: =IF((P26-P25)<0,"0",(P26-P25)) -> 8 | R26: =Q26+N26+K26+H26 -> 10 | S26: =T25 -> 82290 | T26: 82368 | U26: =IF((T26-T25)<0,"0",(T26-T25)) -> 78 | V26: =W25 -> 0 | X26: =IF((W26-W25)<0,"0",(W26-W25)) -> 0 | Y26: =Z25 -> 98614 | Z26: 98653 | AA26: =IF((Z26-Z25)<0,"0",(Z26-Z25)) -> 39 | AB26: =AC25 -> 23939 | AC26: 23952 | AD26: =IF((AC26-AC25)<0,"0",(AC26-AC25)) -> 13 | AE26: =AF25 -> 0 | AG26: =IF((AF26-AF25)<0,"0",(AF26-AF25)) -> 0 | AH26: =AI25 -> 39092 | AI26: 39100 | AJ26: =IF((AI26-AI25)<0,"0",(AI26-AI25)) -> 8 | AK26: =AL25 -> 0 | AM26: =IF((AL26-AL25)<0,"0",(AL26-AL25)) -> 0 | AN26: =U26+X26+AA26+AD26+AG26+AJ26+AM26 -> 138
A27: =Gen!B32 -> 44583 | C27: =D26 -> 279280 | D27: 279351 | E27: =IF((D27-D26)<0,"0",(D27-D26)) -> 71 | F27: =G27 -> 0 | H27: =IF((G28-G26)<0,"0",(G28-G26)) -> 0 | I27: =J26 -> 9012 | J27: 9014 | K27: =IF((J27-J26)<0,"0",(J27-J26)) -> 2 | L27: =M26 -> 0 | N27: =IF((M27-M26)<0,"0",(M27-M26)) -> 0 | O27: =P26 -> 23132 | P27: 23136 | Q27: =IF((P27-P26)<0,"0",(P27-P26)) -> 4 | R27: =Q27+N27+K27+H27 -> 6 | S27: =T26 -> 82368 | T27: 82448 | U27: =IF((T27-T26)<0,"0",(T27-T26)) -> 80 | V27: =W26 -> 0 | X27: =IF((W27-W26)<0,"0",(W27-W26)) -> 0 | Y27: =Z26 -> 98653 | Z27: 98690 | AA27: =IF((Z27-Z26)<0,"0",(Z27-Z26)) -> 37 | AB27: =AC26 -> 23952 | AC27: 23966 | AD27: =IF((AC27-AC26)<0,"0",(AC27-AC26)) -> 14 | AE27: =AF26 -> 0 | AG27: =IF((AF27-AF26)<0,"0",(AF27-AF26)) -> 0 | AH27: =AI26 -> 39100 | AI27: 39100 | AJ27: =IF((AI27-AI26)<0,"0",(AI27-AI26)) -> 0 | AK27: =AL26 -> 0 | AM27: =IF((AL27-AL26)<0,"0",(AL27-AL26)) -> 0 | AN27: =U27+X27+AA27+AD27+AG27+AJ27+AM27 -> 131
A28: =Gen!B33 -> 44584 | C28: =D27 -> 279351 | D28: 279413 | E28: =IF((D28-D27)<0,"0",(D28-D27)) -> 62 | F28: =G28 -> 0 | H28: =IF((G28-G27)<0,"0",(G28-G27)) -> 0 | I28: =J27 -> 9014 | J28: 9016 | K28: =IF((J28-J27)<0,"0",(J28-J27)) -> 2 | L28: =M27 -> 0 | N28: =IF((M28-M27)<0,"0",(M28-M27)) -> 0 | O28: =P27 -> 23136 | P28: 23139 | Q28: =IF((P28-P27)<0,"0",(P28-P27)) -> 3 | R28: =Q28+N28+K28+H28 -> 5 | S28: =T27 -> 82448 | T28: 82482 | U28: =IF((T28-T27)<0,"0",(T28-T27)) -> 34 | V28: =W27 -> 0 | X28: =IF((W28-W27)<0,"0",(W28-W27)) -> 0 | Y28: =Z27 -> 98690 | Z28: 98729 | AA28: =IF((Z28-Z27)<0,"0",(Z28-Z27)) -> 39 | AB28: =AC27 -> 23966 | AC28: 23984 | AD28: =IF((AC28-AC27)<0,"0",(AC28-AC27)) -> 18 | AE28: =AF27 -> 0 | AG28: =IF((AF28-AF27)<0,"0",(AF28-AF27)) -> 0 | AH28: =AI27 -> 39100 | AI28: 39100 | AJ28: =IF((AI28-AI27)<0,"0",(AI28-AI27)) -> 0 | AK28: =AL27 -> 0 | AM28: =IF((AL28-AL27)<0,"0",(AL28-AL27)) -> 0 | AN28: =U28+X28+AA28+AD28+AG28+AJ28+AM28 -> 91
A29: =Gen!B34 -> 44585 | C29: =D28 -> 279413 | D29: 279488 | E29: =IF((D29-D28)<0,"0",(D29-D28)) -> 75 | F29: =G29 -> 0 | H29: =IF((G29-G28)<0,"0",(G29-G28)) -> 0 | I29: =J28 -> 9016 | J29: 9019 | K29: =IF((J29-J28)<0,"0",(J29-J28)) -> 3 | L29: =M28 -> 0 | N29: =IF((M29-M28)<0,"0",(M29-M28)) -> 0 | O29: =P28 -> 23139 | P29: 23148 | Q29: =IF((P29-P28)<0,"0",(P29-P28)) -> 9 | R29: =Q29+N29+K29+H29 -> 12 | S29: =T28 -> 82482 | T29: 82482 | U29: =IF((T29-T28)<0,"0",(T29-T28)) -> 0 | V29: =W28 -> 0 | X29: =IF((W29-W28)<0,"0",(W29-W28)) -> 0 | Y29: =Z28 -> 98729 | Z29: 98768 | AA29: =IF((Z29-Z28)<0,"0",(Z29-Z28)) -> 39 | AB29: =AC28 -> 23984 | AC29: 24000 | AD29: =IF((AC29-AC28)<0,"0",(AC29-AC28)) -> 16 | AE29: =AF28 -> 0 | AG29: =IF((AF29-AF28)<0,"0",(AF29-AF28)) -> 0 | AH29: =AI28 -> 39100 | AI29: 39100 | AJ29: =IF((AI29-AI28)<0,"0",(AI29-AI28)) -> 0 | AK29: =AL28 -> 0 | AM29: =IF((AL29-AL28)<0,"0",(AL29-AL28)) -> 0 | AN29: =U29+X29+AA29+AD29+AG29+AJ29+AM29 -> 55
A30: =Gen!B35 -> 44586 | C30: =D29 -> 279488 | D30: 279648 | E30: =IF((D30-D29)<0,"0",(D30-D29)) -> 160 | F30: =G30 -> 0 | H30: =IF((G30-G29)<0,"0",(G30-G29)) -> 0 | I30: =J29 -> 9019 | J30: 9021 | K30: =IF((J30-J29)<0,"0",(J30-J29)) -> 2 | L30: =M29 -> 0 | N30: =IF((M30-M29)<0,"0",(M30-M29)) -> 0 | O30: =P29 -> 23148 | P30: 23155 | Q30: =IF((P30-P29)<0,"0",(P30-P29)) -> 7 | R30: =Q30+N30+K30+H30 -> 9 | S30: =T29 -> 82482 | T30: 82482 | U30: =IF((T30-T29)<0,"0",(T30-T29)) -> 0 | V30: =W29 -> 0 | X30: =IF((W30-W29)<0,"0",(W30-W29)) -> 0 | Y30: =Z29 -> 98768 | Z30: 98804 | AA30: =IF((Z30-Z29)<0,"0",(Z30-Z29)) -> 36 | AB30: =AC29 -> 24000 | AC30: 24017 | AD30: =IF((AC30-AC29)<0,"0",(AC30-AC29)) -> 17 | AE30: =AF29 -> 0 | AG30: =IF((AF30-AF29)<0,"0",(AF30-AF29)) -> 0 | AH30: =AI29 -> 39100 | AI30: 39100 | AJ30: =IF((AI30-AI29)<0,"0",(AI30-AI29)) -> 0 | AK30: =AL29 -> 0 | AM30: =IF((AL30-AL29)<0,"0",(AL30-AL29)) -> 0 | AN30: =U30+X30+AA30+AD30+AG30+AJ30+AM30 -> 53
A31: =Gen!B36 -> 44587 | C31: =D30 -> 279648 | D31: 279714 | E31: =IF((D31-D30)<0,"0",(D31-D30)) -> 66 | F31: =G31 -> 0 | H31: =IF((G31-G30)<0,"0",(G31-G30)) -> 0 | I31: =J30 -> 9021 | J31: 9023 | K31: =IF((J31-J30)<0,"0",(J31-J30)) -> 2 | L31: =M30 -> 0 | N31: =IF((M31-M30)<0,"0",(M31-M30)) -> 0 | O31: =P30 -> 23155 | P31: 23160 | Q31: =IF((P31-P30)<0,"0",(P31-P30)) -> 5 | R31: =Q31+N31+K31+H31 -> 7 | S31: =T30 -> 82482 | T31: 82553 | U31: =IF((T31-T30)<0,"0",(T31-T30)) -> 71 | V31: =W30 -> 0 | X31: =IF((W31-W30)<0,"0",(W31-W30)) -> 0 | Y31: =Z30 -> 98804 | Z31: 98840 | AA31: =IF((Z31-Z30)<0,"0",(Z31-Z30)) -> 36 | AB31: =AC30 -> 24017 | AC31: 24033 | AD31: =IF((AC31-AC30)<0,"0",(AC31-AC30)) -> 16 | AE31: =AF30 -> 0 | AG31: =IF((AF31-AF30)<0,"0",(AF31-AF30)) -> 0 | AH31: =AI30 -> 39100 | AI31: 39100 | AJ31: =IF((AI31-AI30)<0,"0",(AI31-AI30)) -> 0 | AK31: =AL30 -> 0 | AM31: =IF((AL31-AL30)<0,"0",(AL31-AL30)) -> 0 | AN31: =U31+X31+AA31+AD31+AG31+AJ31+AM31 -> 123
A32: =Gen!B37 -> 44588 | B32: 10/27//2009 | C32: =D31 -> 279714 | D32: 279789 | E32: =IF((D32-D31)<0,"0",(D32-D31)) -> 75 | F32: =G31 -> 0 | H32: =IF((G32-G31)<0,"0",(G32-G31)) -> 0 | I32: =J31 -> 9023 | J32: 9025 | K32: =IF((J32-J31)<0,"0",(J32-J31)) -> 2 | L32: =M31 -> 0 | N32: =IF((M32-M31)<0,"0",(M32-M31)) -> 0 | O32: =P31 -> 23160 | P32: 23166 | Q32: =IF((P32-P31)<0,"0",(P32-P31)) -> 6 | R32: =Q32+N32+K32+H32 -> 8 | S32: =T31 -> 82553 | T32: 82622 | U32: =IF((T32-T31)<0,"0",(T32-T31)) -> 69 | V32: =W31 -> 0 | X32: =IF((W32-W31)<0,"0",(W32-W31)) -> 0 | Y32: =Z31 -> 98840 | Z32: 98882 | AA32: =IF((Z32-Z31)<0,"0",(Z32-Z31)) -> 42 | AB32: =AC31 -> 24033 | AC32: 24050 | AD32: =IF((AC32-AC31)<0,"0",(AC32-AC31)) -> 17 | AE32: =AF31 -> 0 | AG32: =IF((AF32-AF31)<0,"0",(AF32-AF31)) -> 0 | AH32: =AI31 -> 39100 | AI32: 39149 | AJ32: =IF((AI32-AI31)<0,"0",(AI32-AI31)) -> 49 | AK32: =AL31 -> 0 | AM32: =IF((AL32-AL31)<0,"0",(AL32-AL31)) -> 0 | AN32: =U32+X32+AA32+AD32+AG32+AJ32+AM32 -> 177
A33: =Gen!B38 -> 44589 | C33: =D32 -> 279789 | D33: 279853 | E33: =IF((D33-D32)<0,"0",(D33-D32)) -> 64 | F33: =G32 -> 0 | H33: =IF((G33-G32)<0,"0",(G33-G32)) -> 0 | I33: =J32 -> 9025 | J33: 9027 | K33: =IF((J33-J32)<0,"0",(J33-J32)) -> 2 | L33: =M32 -> 0 | N33: =IF((M33-M32)<0,"0",(M33-M32)) -> 0 | O33: =P32 -> 23166 | P33: 23171 | Q33: =IF((P33-P32)<0,"0",(P33-P32)) -> 5 | R33: =Q33+N33+K33+H33 -> 7 | S33: =T32 -> 82622 | T33: 82691 | U33: =IF((T33-T32)<0,"0",(T33-T32)) -> 69 | V33: =W32 -> 0 | X33: =IF((W33-W32)<0,"0",(W33-W32)) -> 0 | Y33: =Z32 -> 98882 | Z33: 98919 | AA33: =IF((Z33-Z32)<0,"0",(Z33-Z32)) -> 37 | AB33: =AC32 -> 24050 | AC33: 24065 | AD33: =IF((AC33-AC32)<0,"0",(AC33-AC32)) -> 15 | AE33: =AF32 -> 0 | AG33: =IF((AF33-AF32)<0,"0",(AF33-AF32)) -> 0 | AH33: =AI32 -> 39149 | AI33: 39187 | AJ33: =IF((AI33-AI32)<0,"0",(AI33-AI32)) -> 38 | AK33: =AL32 -> 0 | AM33: =IF((AL33-AL32)<0,"0",(AL33-AL32)) -> 0 | AN33: =U33+X33+AA33+AD33+AG33+AJ33+AM33 -> 159
A34: =Gen!B39 -> 44590 | C34: =D33 -> 279853 | D34: 279933 | E34: =IF((D34-D33)<0,"0",(D34-D33)) -> 80 | F34: =G33 -> 0 | H34: =IF((G34-G33)<0,"0",(G34-G33)) -> 0 | I34: =J33 -> 9027 | J34: 9033 | K34: =IF((J34-J33)<0,"0",(J34-J33)) -> 6 | L34: =M33 -> 0 | N34: =IF((M34-M33)<0,"0",(M34-M33)) -> 0 | O34: =P33 -> 23171 | P34: 23177 | Q34: =IF((P34-P33)<0,"0",(P34-P33)) -> 6 | R34: =Q34+N34+K34+H34 -> 12 | S34: =T33 -> 82691 | T34: 82759 | U34: =IF((T34-T33)<0,"0",(T34-T33)) -> 68 | V34: =W33 -> 0 | X34: =IF((W34-W33)<0,"0",(W34-W33)) -> 0 | Y34: =Z33 -> 98919 | Z34: 98955 | AA34: =IF((Z34-Z33)<0,"0",(Z34-Z33)) -> 36 | AB34: =AC33 -> 24065 | AC34: 24080 | AD34: =IF((AC34-AC33)<0,"0",(AC34-AC33)) -> 15 | AE34: =AF33 -> 0 | AG34: =IF((AF34-AF33)<0,"0",(AF34-AF33)) -> 0 | AH34: =AI33 -> 39187 | AI34: 39223 | AJ34: =IF((AI34-AI33)<0,"0",(AI34-AI33)) -> 36 | AK34: =AL33 -> 0 | AM34: =IF((AL34-AL33)<0,"0",(AL34-AL33)) -> 0 | AN34: =U34+X34+AA34+AD34+AG34+AJ34+AM34 -> 155
A35: =Gen!B40 -> 44591 | C35: =D34 -> 279933 | D35: 280043 | E35: =IF((D35-D34)<0,"0",(D35-D34)) -> 110 | F35: =G34 -> 0 | H35: =IF((G35-G34)<0,"0",(G35-G34)) -> 0 | I35: =J34 -> 9033 | J35: 9036 | K35: =IF((J35-J34)<0,"0",(J35-J34)) -> 3 | L35: =M34 -> 0 | N35: =IF((M35-M34)<0,"0",(M35-M34)) -> 0 | O35: =P34 -> 23177 | P35: 23185 | Q35: =IF((P35-P34)<0,"0",(P35-P34)) -> 8 | R35: =Q35+N35+K35+H35 -> 11 | S35: =T34 -> 82759 | T35: 82826 | U35: =IF((T35-T34)<0,"0",(T35-T34)) -> 67 | V35: =W34 -> 0 | X35: =IF((W36-W34)<0,"0",(W36-W34)) -> 0 | Y35: =Z34 -> 98955 | Z35: 98991 | AA35: =IF((Z35-Z34)<0,"0",(Z35-Z34)) -> 36 | AB35: =AC34 -> 24080 | AC35: 24094 | AD35: =IF((AC35-AC34)<0,"0",(AC35-AC34)) -> 14 | AE35: =AF34 -> 0 | AG35: =IF((AF35-AF34)<0,"0",(AF35-AF34)) -> 0 | AH35: =AI34 -> 39223 | AI35: 39259 | AJ35: =IF((AI35-AI34)<0,"0",(AI35-AI34)) -> 36 | AK35: =AL34 -> 0 | AM35: =IF((AL35-AL34)<0,"0",(AL35-AL34)) -> 0 | AN35: =U35+X35+AA35+AD35+AG35+AJ35+AM35 -> 153
A36: =Gen!B41 -> 44592 | C36: =D35 -> 280043 | D36: 280147 | E36: =IF((D36-D35)<0,"0",(D36-D35)) -> 104 | F36: =G35 -> 0 | H36: =IF((G36-G35)<0,"0",(G36-G35)) -> 0 | I36: =J35 -> 9036 | J36: 9039 | K36: =IF((J36-J35)<0,"0",(J36-J35)) -> 3 | L36: =M35 -> 0 | N36: =IF((M36-M35)<0,"0",(M36-M35)) -> 0 | O36: =P35 -> 23185 | P36: 23194 | Q36: =IF((P36-P35)<0,"0",(P36-P35)) -> 9 | R36: =Q36+N36+K36+H36 -> 12 | S36: =T35 -> 82826 | T36: 82889 | U36: =IF((T36-T35)<0,"0",(T36-T35)) -> 63 | V36: =W36 -> 0 | X36: =IF((W37-W35)<0,"0",(W37-W35)) -> 0 | Y36: =Z35 -> 98991 | Z36: 99027 | AA36: =IF((Z36-Z35)<0,"0",(Z36-Z35)) -> 36 | AB36: =AC35 -> 24094 | AC36: 24109 | AD36: =IF((AC36-AC35)<0,"0",(AC36-AC35)) -> 15 | AE36: =AF35 -> 0 | AG36: =IF((AF36-AF35)<0,"0",(AF36-AF35)) -> 0 | AH36: =AI35 -> 39259 | AI36: 39296 | AJ36: =IF((AI36-AI35)<0,"0",(AI36-AI35)) -> 37 | AK36: =AL35 -> 0 | AM36: =IF((AL36-AL35)<0,"0",(AL36-AL35)) -> 0 | AN36: =U36+X36+AA36+AD36+AG36+AJ36+AM36 -> 151
C37: =D36 -> 280147 | E37: =IF((D37-D36)<0,"0",(D37-D36)) -> 0 | F37: =G36 -> 0 | H37: =IF((G37-G36)<0,"0",(G37-G36)) -> 0 | I37: =J36 -> 9039 | K37: =IF((J37-J36)<0,"0",(J37-J36)) -> 0 | L37: =M36 -> 0 | N37: =IF((M37-M36)<0,"0",(M37-M36)) -> 0 | O37: =P36 -> 23194 | Q37: =IF((P37-P36)<0,"0",(P37-P36)) -> 0 | R37: =Q37+N37+K37+H37 -> 0 | AA37: =IF((Z37-Z36)<0,"0",(Z37-Z36)) -> 0 | AB37: =AC36 -> 24109 | AD37: =IF((AC37-AC36)<0,"0",(AC37-AC36)) -> 0 | AE37: =AF36 -> 0 | AN37: =U37+X37+AA37+AD37+AG37+AJ37+AM37 -> 0
C38: TOTAL USAGE | E38: =SUM(E6:E36) -> 2764 | F38: KL | H38: =SUM(H6:H37) -> 0 | K38: =SUM(K6:K37) -> 74 | N38: =M38-M37 -> 0 | Q38: =P38-O38 -> 0 | R38: =E38 -> 2764 | U38: =SUM(U6:U37) -> 1295 | X38: =SUM(X13:X37) -> 0 | AA38: =SUM(AA6:AA37) -> 1164 | AD38: =SUM(AD6:AD37) -> 519 | AG38: =SUM(AG6:AG37) -> 0 | AJ38: =SUM(AJ6:AJ37) -> 695 | AM38: =SUM(AM6:AM37) -> 0 | AN38: =U38+X38+AA38+AD38+AG38+AJ38+AM38 -> 3673
C42: WATER TANK LEVEL
C43: RAW WATER TANK NO.1 | E43: RAW WATER TANK NO.2 | G43: TREATED WATER TANK | I43: TREATED -HILL TANK | K43: TOTAL WATER AVAILABLE
C44: CAPACITY 217 m³ | E44: CAPACITY 92 m³ | G44: CAPACITY 146 m³ | I44: CAPACITY 213 m³
C45: cm | D45: m³ | E45: cm | F45: m³ | H45: m³ | J45: m³ | K45: m³
A46: =Gen!B11 -> 44562 | C46: 150 | D46: =C46*217/300 -> 108.5 | E46: 95 | F46: =E46*92/305 -> 28.655738 | G46: 300 | H46: =G46*146/383 -> 114.36031 | I46: 290 | J46: =I46*213/308 -> 200.55195 | K46: =D46+F46+H46+J46 -> 452.068
A47: =Gen!B12 -> 44563 | C47: 155 | D47: =C47*217/300 -> 112.11667 | E47: 100 | F47: =E47*92/305 -> 30.163934 | G47: 270 | H47: =G47*146/383 -> 102.92428 | I47: 295 | J47: =I47*213/308 -> 204.00974 | K47: =D47+F47+H47+J47 -> 449.21462
A48: =Gen!B13 -> 44564 | C48: 210 | D48: =C48*217/300 -> 151.9 | E48: 170 | F48: =E48*92/305 -> 51.278689 | G48: 185 | H48: =G48*146/383 -> 70.522193 | I48: 290 | J48: =I48*213/308 -> 200.55195 | K48: =D48+F48+H48+J48 -> 474.25283
A49: =Gen!B14 -> 44565 | C49: 250 | D49: =C49*217/300 -> 180.83333 | E49: 210 | F49: =E49*92/305 -> 63.344262 | G49: 250 | H49: =G49*146/383 -> 95.300261 | I49: 285 | J49: =I49*213/308 -> 197.09416 | K49: =D49+F49+H49+J49 -> 536.57201
A50: =Gen!B15 -> 44566 | C50: 215 | D50: =C50*217/300 -> 155.51667 | E50: 170 | F50: =E50*92/305 -> 51.278689 | G50: 300 | H50: =G50*146/383 -> 114.36031 | I50: 295 | J50: =I50*213/308 -> 204.00974 | K50: =D50+F50+H50+J50 -> 525.16541
A51: =Gen!B16 -> 44567 | C51: 300 | D51: =C51*217/300 -> 217 | E51: 260 | F51: =E51*92/305 -> 78.42623 | G51: 100 | H51: =G51*146/383 -> 38.120104 | I51: 290 | J51: =I51*213/308 -> 200.55195 | K51: =D51+F51+H51+J51 -> 534.09828
A52: =Gen!B17 -> 44568 | C52: 270 | D52: =C52*217/300 -> 195.3 | E52: 220 | F52: =E52*92/305 -> 66.360656 | G52: 280 | H52: =G52*146/383 -> 106.73629 | I52: 290 | J52: =I52*213/308 -> 200.55195 | K52: =D52+F52+H52+J52 -> 568.9489
A53: =Gen!B18 -> 44569 | C53: 270 | D53: =C53*217/300 -> 195.3 | E53: 230 | F53: =E53*92/305 -> 69.377049 | G53: 280 | H53: =G53*146/383 -> 106.73629 | I53: 290 | J53: =I53*213/308 -> 200.55195 | K53: =D53+F53+H53+J53 -> 571.96529
A54: =Gen!B19 -> 44570 | C54: 265 | D54: =C54*217/300 -> 191.68333 | E54: 230 | F54: =E54*92/305 -> 69.377049 | G54: 300 | H54: =G54*146/383 -> 114.36031 | I54: 290 | J54: =I54*213/308 -> 200.55195 | K54: =D54+F54+H54+J54 -> 575.97264
A55: =Gen!B20 -> 44571 | C55: 300 | D55: =C55*217/300 -> 217 | E55: 289 | F55: =E55*92/305 -> 87.17377 | G55: 300 | H55: =G55*146/383 -> 114.36031 | I55: 285 | J55: =I55*213/308 -> 197.09416 | K55: =D55+F55+H55+J55 -> 615.62824
A56: =Gen!B21 -> 44572 | C56: 280 | D56: =C56*217/300 -> 202.53333 | E56: 250 | F56: =E56*92/305 -> 75.409836 | G56: 300 | H56: =G56*146/383 -> 114.36031 | I56: 286 | J56: =I56*213/308 -> 197.78571 | K56: =D56+F56+H56+J56 -> 590.0892
A57: =Gen!B22 -> 44573 | C57: 270 | D57: =C57*217/300 -> 195.3 | E57: 235 | F57: =E57*92/305 -> 70.885246 | G57: 300 | H57: =G57*146/383 -> 114.36031 | I57: 290 | J57: =I57*213/308 -> 200.55195 | K57: =D57+F57+H57+J57 -> 581.09751
... A76: =Gen!B41 -> 44592 | C76: 280 | D76: =C76*217/300 -> 202.53333 | E76: 245 | F76: =E76*92/305 -> 73.901639 | G76: 105 | H76: =G76*146/383 -> 40.02611 | I76: 280 | J76: =I76*213/308 -> 193.63636 | K76: =D76+F76+H76+J76 -> 510.09745
A77: =Gen!B42 -> 0 | D77: =C77*217/300 -> 0 | F77: =E77*92/305 -> 0 | H77: =G77*146/383 -> 0 | J77: =I77*213/308 -> 0 | K77: =D77+F77+H77+J77 -> 0
A78: =Gen!B43 -> BF

Sheet LPG_Graph
A1: Date | B1: Usage KG | C1: Occ %
A2: =Gen!B11 -> 44562 | B2: ='Lpg (2)'!G10 -> 144.452 | C2: =Gen!C11 -> 0.4156
A3: =Gen!B12 -> 44563 | B3: ='Lpg (2)'!G11 -> 150.7 | C3: =Gen!C12 -> 0.53
A4: =Gen!B13 -> 44564 | B4: ='Lpg (2)'!G12 -> 156.948 | C4: =Gen!C13 -> 0.36
A5: =Gen!B14 -> 44565 | B5: ='Lpg (2)'!G13 -> 132.088 | C5: =Gen!C14 -> 0.35
A6: =Gen!B15 -> 44566 | B6: ='Lpg (2)'!G14 -> 122.188 | C6: =Gen!C15 -> 0.26
A7: =Gen!B16 -> 44567 | B7: ='Lpg (2)'!G15 -> 137.72 | C7: =Gen!C16 -> 0.31
A8: =Gen!B17 -> 44568 | B8: ='Lpg (2)'!G16 -> 132.88 | C8: =Gen!C17 -> 0.2468
A9: =Gen!B18 -> 44569 | B9: ='Lpg (2)'!G17 -> 112.024 | C9: =Gen!C18 -> 0.23
A10: =Gen!B19 -> 44570 | B10: ='Lpg (2)'!G18 -> 106.084 | C10: =Gen!C19 -> 0.2078
A11: =Gen!B20 -> 44571 | B11: ='Lpg (2)'!G19 -> 113.784 | C11: =Gen!C20 -> 0.17
A12: =Gen!B21 -> 44572 | B12: ='Lpg (2)'!G20 -> 116.908 | C12: =Gen!C21 -> 0.1
A13: =Gen!B22 -> 44573 | B13: ='Lpg (2)'!G21 -> 99.484 | C13: =Gen!C22 -> 0.0649
... A32: =Gen!B41 -> 44592 | B32: ='Lpg (2)'!G40 -> -4278.824 | C32: =Gen!C41 -> 0.05

Sheet Water_Graph 
A1: Date | B1: Usage | C1: Occ %
A2: =Gen!B11 -> 44562 | B2: #REF! | C2: =Gen!C11 -> 0.4156
A3: =Gen!B12 -> 44563 | B3: #REF! | C3: =Gen!C12 -> 0.53
A4: =Gen!B13 -> 44564 | B4: #REF! | C4: =Gen!C13 -> 0.36
A5: =Gen!B14 -> 44565 | B5: #REF! | C5: =Gen!C14 -> 0.35
A6: =Gen!B15 -> 44566 | B6: #REF! | C6: =Gen!C15 -> 0.26
A7: =Gen!B16 -> 44567 | B7: #REF! | C7: =Gen!C16 -> 0.31
A8: =Gen!B17 -> 44568 | B8: #REF! | C8: =Gen!C17 -> 0.2468
A9: =Gen!B18 -> 44569 | B9: #REF! | C9: =Gen!C18 -> 0.23
A10: =Gen!B19 -> 44570 | B10: #REF! | C10: =Gen!C19 -> 0.2078
A11: =Gen!B20 -> 44571 | B11: #REF! | C11: =Gen!C20 -> 0.17
A12: =Gen!B21 -> 44572 | B12: #REF! | C12: =Gen!C21 -> 0.1
A13: =Gen!B22 -> 44573 | B13: #REF! | C13: =Gen!C22 -> 0.0649
... A29: =Gen!B38 -> 44589 | B29: #REF! | C29: =Gen!C38 -> 0.09
A30: =Gen!B39 -> 44590 | B30: -212333 | C30: =Gen!C39 -> 0.09
A31: =Gen!B40 -> 44591 | B31: #REF! | C31: =Gen!C40 -> 0.06
A32: =Gen!B41 -> 44592 | B32: #REF! | C32: =Gen!C41 -> 0.05

Sheet Sheet1
A2: Generator and Diseal Summry Report | Q2: 2209.85 | R2: Diesel Cost | S2: Rate$ | T2: 1584
M3: % of Gas balance in Tank | P3: % of Dieasel balance in Tank | Q3: HLP Cost (TSH) | V3: Total Cost (TSH) | W3: Consumption Guest Occ% | AA3: Budget Cost Per Room occ
A4: Date | B4: Gen Set Hours Working | C4: Occ% | D4: Total OCC Room | E4: Guest Room Occ | F4: Total Kwh Generated | G4: Diseal consumed by Gen (Ltrs) | H4: Diseal consumed by Veichel (Ltrs) | I4: Total diseal consumed (Ltrs) | J4: Balance stock of Diseal (Ltrs) | K4: Water consumed | L4: Gas consumed (KG) | M4: 3 | N4: 2 | O4: 1 | Q4: Electricity | R4: Cost per Room Total OOC Usd | S4: Cost per Room Guest OOC Usd | T4: Water | U4: Gas
A5: =Gen!B11 -> 44562 | B5: 0 | C5: =Gen!C11 -> 0.4156 | D5: =E5 -> 34 | E5: ='Summery Report'!E5 -> 34 | F5: =Gen!V11 -> 0.41514575 | G5: =Gen!U11 -> 4734 | H5: #REF! | I5: =SUM(G5:H5) -> #REF! | J5: 47806.65 | K5: ='Water-Meter'!E6 -> 116 | L5: ='Lpg (2)'!G10 -> 144.452 | M5: =#REF! -> #REF! | N5: =#REF! -> #REF! | O5: =#REF! -> #REF! | P5: =J5/52000 -> 0.91935865 | Q5: =I5*Q2 -> #REF! | R5: =SUM(Q5/D5)/X5 -> #REF! | S5: =SUM(Q5/E5)/X5 -> #REF! | T5: =(K5*102)/X5 -> 7.469697 | U5: =SUM(L5*1963)/X5 -> 179.01469 | V5: =SUM(Q5+T5+U5) -> #REF! | W5: =SUM(V5/E5)/T2 -> #REF! | X5: =SUM(T2) -> 1584 | Y5: 106 | Z5: =SUM(Y5-S5) -> #REF! | AA5: 106
A6: =Gen!B12 -> 44563 | B6: 0 | C6: =Gen!C12 -> 0.53 | D6: =E6 -> 42 | E6: ='Summery Report'!E6 -> 42 | F6: =Gen!V12 -> 0.42232742 | G6: =Gen!U12 -> 4563 | H6: #REF! | I6: =SUM(G6:H6) -> #REF! | J6: 45423.89 | K6: ='Water-Meter'!E7 -> 94 | L6: ='Lpg (2)'!G11 -> 150.7 | M6: =#REF! -> #REF! | N6: =#REF! -> #REF! | O6: =#REF! -> #REF! | P6: =J6/52000 -> 0.87353635 | Q6: =I6*Q2 -> #REF! | R6: =SUM(Q6/D6)/X6 -> #REF! | S6: =SUM(Q6/E6)/X6 -> #REF! | T6: =(K6*102)/X6 -> 6.0530303 | U6: =SUM(L6*1963)/X6 -> 186.75764 | V6: =SUM(Q6+T6+U6) -> #REF! | W6: =SUM(V6/E6)/T2 -> #REF! | X6: =SUM(X5) -> 1584 | Y6: 106 | Z6: =SUM(Y6-S6) -> #REF!
A7: =Gen!B13 -> 44564 | B7: 0 | C7: =Gen!C13 -> 0.36 | D7: =E7 -> 29 | E7: ='Summery Report'!E7 -> 29 | F7: =Gen!V13 -> 0.40662877 | G7: =Gen!U13 -> 4574 | H7: #REF! | I7: =SUM(G7:H7) -> #REF! | J7: 42919.59 | K7: ='Water-Meter'!E8 -> 110 | L7: ='Lpg (2)'!G12 -> 156.948 | M7: =#REF! -> #REF! | N7: =#REF! -> #REF! | O7: =#REF! -> #REF! | P7: =J7/52000 -> 0.82537673 | Q7: =I7*Q2 -> #REF! | R7: =SUM(Q7/D7)/X7 -> #REF! | S7: =SUM(Q7/E7)/X7 -> #REF! | T7: =(K7*102)/X7 -> 7.0833333 | U7: =SUM(L7*1963)/X7 -> 194.50058 | V7: =SUM(Q7+T7+U7) -> #REF! | W7: =SUM(V7/E7)/T2 -> #REF! | X7: =SUM(X6) -> 1584 | Y7: 106 | Z7: =SUM(Y7-S7) -> #REF!
A8: =Gen!B14 -> 44565 | B8: 0 | C8: =Gen!C14 -> 0.35 | D8: =E8 -> 28 | E8: ='Summery Report'!E8 -> 28 | F8: =Gen!V14 -> 0.43481362 | G8: =Gen!U14 -> 4346 | H8: #REF! | I8: =SUM(G8:H8) -> #REF! | J8: 40258.94 | K8: ='Water-Meter'!E9 -> 94 | L8: ='Lpg (2)'!G13 -> 132.088 | M8: =#REF! -> #REF! | N8: =#REF! -> #REF! | O8: =#REF! -> #REF! | P8: =J8/52000 -> 0.77421038 | Q8: =I8*Q2 -> #REF! | R8: =SUM(Q8/D8)/X8 -> #REF! | S8: =SUM(Q8/E8)/X8 -> #REF! | T8: =(K8*102)/X8 -> 6.0530303 | U8: =SUM(L8*1963)/X8 -> 163.69239 | V8: =SUM(Q8+T8+U8) -> #REF! | W8: =SUM(V8/E8)/T2 -> #REF! | X8: =SUM(X7) -> 1584 | Y8: 106 | Z8: =SUM(Y8-S8) -> #REF!
A9: =Gen!B15 -> 44566 | B9: 0 | C9: =Gen!C15 -> 0.26 | D9: =E9 -> 21 | E9: ='Summery Report'!E9 -> 21 | F9: =Gen!V15 -> 0.43244898 | G9: =Gen!U15 -> 3969 | H9: 0 | I9: =SUM(G9:H9) -> 3969 | J9: 37525.21 | K9: ='Water-Meter'!E10 -> 86 | L9: ='Lpg (2)'!G14 -> 122.188 | M9: =#REF! -> #REF! | N9: =#REF! -> #REF! | O9: =#REF! -> #REF! | P9: =J9/52000 -> 0.72163865 | Q9: =I9*Q2 -> 8770894.7 | R9: =SUM(Q9/D9)/X9 -> 263.67528 | S9: =SUM(Q9/E9)/X9 -> 263.67528 | T9: =(K9*102)/X9 -> 5.5378788 | U9: =SUM(L9*1963)/X9 -> 151.42364 | V9: =SUM(Q9+T9+U9) -> 8771051.6 | W9: =SUM(V9/E9)/T2 -> 263.68 | X9: =SUM(X8) -> 1584 | Y9: 106 | Z9: =SUM(Y9-S9) -> -157.67528
A10: =Gen!B16 -> 44567 | B10: 0 | C10: =Gen!C16 -> 0.31 | D10: =E10 -> 25 | E10: ='Summery Report'!E10 -> 25 | F10: =Gen!V16 -> 0.42292486 | G10: =Gen!U16 -> 4325 | H10: #REF! | I10: =SUM(G10:H10) -> #REF! | J10: 35107.69 | K10: ='Water-Meter'!E11 -> 90 | L10: ='Lpg (2)'!G15 -> 137.72 | M10: =#REF! -> #REF! | N10: =#REF! -> #REF! | O10: =#REF! -> #REF! | P10: =J10/52000 -> 0.67514788 | Q10: =I10*Q2 -> #REF! | R10: =SUM(Q10/D10)/X10 -> #REF! | S10: =SUM(Q10/E10)/X10 -> #REF! | T10: =(K10*102)/X10 -> 5.7954545 | U10: =SUM(L10*1963)/X10 -> 170.67194 | V10: =SUM(Q10+T10+U10) -> #REF! | W10: =SUM(V10/E10)/T2 -> #REF! | X10: =SUM(X9) -> 1584 | Y10: 106 | Z10: =SUM(Y10-S10) -> #REF!
A11: =Gen!B17 -> 44568 | B11: 0 | C11: =Gen!C17 -> 0.2468 | D11: =E11 -> 20 | E11: ='Summery Report'!E11 -> 20 | F11: =Gen!V17 -> 0.41997075 | G11: =Gen!U17 -> 4444 | H11: 80.56 | I11: =SUM(G11:H11) -> 4524.56 | J11: 47513.14 | K11: ='Water-Meter'!E12 -> 92 | L11: ='Lpg (2)'!G16 -> 132.88 | M11: =#REF! -> #REF! | N11: =#REF! -> #REF! | O11: =#REF! -> #REF! | P11: =J11/52000 -> 0.91371423 | Q11: =I11*Q2 -> 9998598.9 | R11: =SUM(Q11/D11)/X11 -> 315.61234 | S11: =SUM(Q11/E11)/X11 -> 315.61234 | T11: =(K11*102)/X11 -> 5.9242424 | U11: =SUM(L11*1963)/X11 -> 164.67389 | V11: =SUM(Q11+T11+U11) -> 9998769.5 | W11: =SUM(V11/E11)/T2 -> 315.61772 | X11: =SUM(X10) -> 1584 | Y11: 106 | Z11: =SUM(Y11-S11) -> -209.61234
A12: =Gen!B18 -> 44569 | B12: 0 | C12: =Gen!C18 -> 0.23 | D12: =E12 -> 19 | E12: ='Summery Report'!E12 -> 19 | F12: =Gen!V18 -> 0.41184805 | G12: =Gen!U18 -> 4291 | H12: #REF! | I12: =SUM(G12:H12) -> #REF! | J12: 45161.89 | K12: ='Water-Meter'!E13 -> 108 | L12: ='Lpg (2)'!G17 -> 112.024 | M12: =#REF! -> #REF! | N12: =#REF! -> #REF! | O12: =#REF! -> #REF! | P12: =J12/52000 -> 0.86849788 | Q12: =I12*Q2 -> #REF! | R12: =SUM(Q12/D12)/X12 -> #REF! | S12: =SUM(Q12/E12)/X12 -> #REF! | T12: =(K12*102)/X12 -> 6.9545455 | U12: =SUM(L12*1963)/X12 -> 138.82772 | V12: =SUM(Q12+T12+U12) -> #REF! | W12: =SUM(V12/E12)/T2 -> #REF! | X12: =SUM(X11) -> 1584 | Y12: 106 | Z12: =SUM(Y12-S12) -> #REF!
A13: =Gen!B19 -> 44570 | B13: 0 | C13: =Gen!C19 -> 0.2078 | D13: =E13 -> 17 | E13: ='Summery Report'!E13 -> 17 | F13: =Gen!V19 -> 0.42574954 | G13: =Gen!U19 -> 4336 | H13: #REF! | I13: =SUM(G13:H13) -> #REF! | J13: 42825.48 | K13: ='Water-Meter'!E14 -> 101 | L13: ='Lpg (2)'!G18 -> 106.084 | M13: =#REF! -> #REF! | N13: =#REF! -> #REF! | O13: =#REF! -> #REF! | P13: =J13/52000 -> 0.82356692 | Q13: =I13*Q2 -> #REF! | R13: =SUM(Q13/D13)/X13 -> #REF! | S13: =SUM(Q13/E13)/X13 -> #REF! | T13: =(K13*102)/X13 -> 6.5037879 | U13: =SUM(L13*1963)/X13 -> 131.46647 | V13: =SUM(Q13+T13+U13) -> #REF! | W13: =SUM(V13/E13)/T2 -> #REF! | X13: =SUM(X12) -> 1584 | Y13: 106 | Z13: =SUM(Y13-S13) -> #REF!
A14: =Gen!B20 -> 44571 | B14: 0 | C14: =Gen!C20 -> 0.17 | D14: =E14 -> 16 | E14: ='Summery Report'!E14 -> 16 | F14: =Gen!V20 -> 0.41262678 | G14: =Gen!U20 -> 4279 | H14: #REF! | I14: =SUM(G14:H14) -> #REF! | J14: 40110.38 | K14: ='Water-Meter'!E15 -> 83 | L14: ='Lpg (2)'!G19 -> 113.784 | M14: =#REF! -> #REF! | N14: =#REF! -> #REF! | O14: =#REF! -> #REF! | P14: =J14/52000 -> 0.77135346 | Q14: =I14*Q2 -> #REF! | R14: =SUM(Q14/D14)/X14 -> #REF! | S14: =SUM(Q14/E14)/X14 -> #REF! | T14: =(K14*102)/X14 -> 5.344697 | U14: =SUM(L14*1963)/X14 -> 141.00883 | V14: =SUM(Q14+T14+U14) -> #REF! | W14: =SUM(V14/E14)/T2 -> #REF! | X14: =SUM(X13) -> 1584 | Y14: 106 | Z14: =SUM(Y14-S14) -> #REF!
A15: =Gen!B21 -> 44572 | B15: 0 | C15: =Gen!C21 -> 0.1 | D15: =E15 -> 11 | E15: ='Summery Report'!E15 -> 11 | F15: =Gen!V21 -> 0.42083894 | G15: =Gen!U21 -> 3862 | H15: #REF! | I15: =SUM(G15:H15) -> #REF! | J15: 37540.57 | K15: ='Water-Meter'!E16 -> 67 | L15: ='Lpg (2)'!G20 -> 116.908 | M15: =#REF! -> #REF! | N15: =#REF! -> #REF! | O15: =#REF! -> #REF! | P15: =J15/52000 -> 0.72193404 | Q15: =I15*Q2 -> #REF! | R15: =SUM(Q15/D15)/X15 -> #REF! | S15: =SUM(Q15/E15)/X15 -> #REF! | T15: =(K15*102)/X15 -> 4.3143939 | U15: =SUM(L15*1963)/X15 -> 144.88031 | V15: =SUM(Q15+T15+U15) -> #REF! | W15: =SUM(V15/E15)/T2 -> #REF! | X15: =SUM(X14) -> 1584 | Y15: 106 | Z15: =SUM(Y15-S15) -> #REF!
A16: =Gen!B22 -> 44573 | B16: 0 | C16: =Gen!C22 -> 0.0649 | D16: =E16 -> 8 | E16: ='Summery Report'!E16 -> 8 | F16: =Gen!V22 -> 0.42066001 | G16: =Gen!U22 -> 3803 | H16: #REF! | I16: =SUM(G16:H16) -> #REF! | J16: 34967.29 | K16: ='Water-Meter'!E17 -> 133 | L16: ='Lpg (2)'!G21 -> 99.484 | M16: =#REF! -> #REF! | N16: =#REF! -> #REF! | O16: =#REF! -> #REF! | P16: =J16/52000 -> 0.67244788 | Q16: =I16*Q2 -> #REF! | R16: =SUM(Q16/D16)/X16 -> #REF! | S16: =SUM(Q16/E16)/X16 -> #REF! | T16: =(K16*102)/X16 -> 8.5643939 | U16: =SUM(L16*1963)/X16 -> 123.28731 | V16: =SUM(Q16+T16+U16) -> #REF! | W16: =SUM(V16/E16)/T2 -> #REF! | X16: =SUM(X15) -> 1584 | Y16: 106 | Z16: =SUM(Y16-S16) -> #REF!
A17: =Gen!B23 -> 44574 | B17: 0 | C17: =Gen!C23 -> 0.13 | D17: =E17 -> 13 | E17: ='Summery Report'!E17 -> 13 | F17: =Gen!V23 -> 0.41318257 | G17: =Gen!U23 -> 3648 | H17: #REF! | I17: =SUM(G17:H17) -> #REF! | J17: 32228.76 | K17: ='Water-Meter'!E18 -> 86 | L17: ='Lpg (2)'!G22 -> 90.904 | M17: =#REF! -> #REF! | N17: =#REF! -> #REF! | O17: =#REF! -> #REF! | P17: =J17/52000 -> 0.61978385 | Q17: =I17*Q2 -> #REF! | R17: =SUM(Q17/D17)/X17 -> #REF! | S17: =SUM(Q17/E17)/X17 -> #REF! | T17: =(K17*102)/X17 -> 5.5378788 | U17: =SUM(L17*1963)/X17 -> 112.65439 | V17: =SUM(Q17+T17+U17) -> #REF! | W17: =SUM(V17/E17)/T2 -> #REF! | X17: =SUM(X16) -> 1584 | Y17: 106 | Z17: =SUM(Y17-S17) -> #REF!
A18: =Gen!B24 -> 44575 | B18: 0 | C18: =Gen!C24 -> 0.18 | D18: =E18 -> 17 | E18: ='Summery Report'!E18 -> 17 | F18: =Gen!V24 -> 0.39839789 | G18: =Gen!U24 -> 3795 | H18: 597.9 | I18: =SUM(G18:H18) -> 4392.9 | J18: 29915.45 | K18: ='Water-Meter'!E19 -> 92 | L18: ='Lpg (2)'!G23 -> 73.568 | M18: =#REF! -> #REF! | N18: =#REF! -> #REF! | O18: =#REF! -> #REF! | P18: =J18/52000 -> 0.57529712 | Q18: =I18*Q2 -> 9707650.1 | R18: =SUM(Q18/D18)/X18 -> 360.50394 | S18: =SUM(Q18/E18)/X18 -> 360.50394 | T18: =(K18*102)/X18 -> 5.9242424 | U18: =SUM(L18*1963)/X18 -> 91.170444 | V18: =SUM(Q18+T18+U18) -> 9707747.2 | W18: =SUM(V18/E18)/T2 -> 360.50754 | X18: =SUM(X17) -> 1584 | Y18: 106 | Z18: =SUM(Y18-S18) -> -254.50394
A19: =Gen!B25 -> 44576 | B19: 0 | C19: =Gen!C25 -> 0.16 | D19: =E19 -> 15 | E19: ='Summery Report'!E19 -> 15 | F19: =Gen!V25 -> 0.39528509 | G19: =Gen!U25 -> 3648 | H19: 227.73 | I19: =SUM(G19:H19) -> 3875.73 | J19: 42248.24 | K19: ='Water-Meter'!E20 -> 102 | L19: ='Lpg (2)'!G24 -> 74.316 | M19: =#REF! -> #REF! | N19: =#REF! -> #REF! | O19: =#REF! -> #REF! | P19: =J19/52000 -> 0.81246615 | Q19: =I19*Q2 -> 8564781.9 | R19: =SUM(Q19/D19)/X19 -> 360.47062 | S19: =SUM(Q19/E19)/X19 -> 360.47062 | T19: =(K19*102)/X19 -> 6.5681818 | U19: =SUM(L19*1963)/X19 -> 92.097417 | V19: =SUM(Q19+T19+U19) -> 8564880.6 | W19: =SUM(V19/E19)/T2 -> 360.47477 | X19: =SUM(X18) -> 1584 | Y19: 106 | Z19: =SUM(Y19-S19) -> -254.47062
A20: =Gen!B26 -> 44577 | B20: 0 | C20: =Gen!C26 -> 0.18 | D20: =E20 -> 17 | E20: ='Summery Report'!E20 -> 17 | F20: =Gen!V26 -> 0.39916888 | G20: =Gen!U26 -> 3393 | H20: 88.29 | I20: =SUM(G20:H20) -> 3481.29 | J20: 39497.37 | K20: ='Water-Meter'!E21 -> 74 | L20: ='Lpg (2)'!G25 -> 109.604 | M20: =#REF! -> #REF! | N20: =#REF! -> #REF! | O20: =#REF! -> #REF! | P20: =J20/52000 -> 0.75956481 | Q20: =I20*Q2 -> 7693128.7 | R20: =SUM(Q20/D20)/X20 -> 285.69254 | S20: =SUM(Q20/E20)/X20 -> 285.69254 | T20: =(K20*102)/X20 -> 4.7651515 | U20: =SUM(L20*1963)/X20 -> 135.82869 | V20: =SUM(Q20+T20+U20) -> 7693269.3 | W20: =SUM(V20/E20)/T2 -> 285.69776 | X20: =SUM(X19) -> 1584 | Y20: 106 | Z20: =SUM(Y20-S20) -> -179.69254
