Workbook

Sheet TOTAL
A1: Site Name | B1: Day | C1: Month | D1: Year | E1: Total Electricity Kwh | F1: Electricity Tariff ($/Kwh) | G1: LPG (Kg) | H1: LPG $/Kg | I1: Water Utility Supply (m3) m3 | J1: Water Utility Supply (m3) $/m3 | K1: Room Nights | L1: Total Guests | M1: Utilities day cost dh
A2: Casablanca | B2: 1 | C2: 3 | D2: 2022 | E2: =submetering!E2+submetering!F2+submetering!G2 -> 10871 | F2: 1.05 | G2: ='Consommation mensuel énergie'!V10 -> 0 | H2: 9.965 | I2: ='Consommation mensuel énergie'!F10 -> 104 | J2: 11.4 | K2: ='Consommation mensuel énergie'!D10 -> 0 | L2: ='Consommation mensuel énergie'!E10 -> 0 | M2: =E2*F2+G2*H2+#REF!*#REF!+I2*J2 -> #REF!
A3: Casablanca | B3: =B2+1 -> 2 | C3: 3 | D3: 2022 | E3: =submetering!E3+submetering!F3+submetering!G3 -> 0 | F3: 1.05 | G3: ='Consommation mensuel énergie'!V11 -> 0 | H3: 9.965 | I3: ='Consommation mensuel énergie'!F11 -> 0 | J3: 11.4 | K3: ='Consommation mensuel énergie'!D11 -> 0 | L3: ='Consommation mensuel énergie'!E11 -> 0 | M3: =E3*F3+G3*H3+#REF!*#REF!+I3*J3 -> #REF!
A4: Casablanca | B4: =B3+1 -> 3 | C4: 3 | D4: 2022 | E4: =submetering!E4+submetering!F4+submetering!G4 -> 0 | F4: 1.05 | G4: ='Consommation mensuel énergie'!V12 -> 0 | H4: 9.965 | I4: ='Consommation mensuel énergie'!F12 -> 0 | J4: 11.4 | K4: ='Consommation mensuel énergie'!D12 -> 0 | L4: ='Consommation mensuel énergie'!E12 -> 0 | M4: =E4*F4+G4*H4+#REF!*#REF!+I4*J4 -> #REF!
A5: Casablanca | B5: =B4+1 -> 4 | C5: 3 | D5: 2022 | E5: =submetering!E5+submetering!F5+submetering!G5 -> 0 | F5: 1.05 | G5: ='Consommation mensuel énergie'!V13 -> 0 | H5: 9.965 | I5: ='Consommation mensuel énergie'!F13 -> 0 | J5: 11.4 | K5: ='Consommation mensuel énergie'!D13 -> 0 | L5: ='Consommation mensuel énergie'!E13 -> 0 | M5: =E5*F5+G5*H5+#REF!*#REF!+I5*J5 -> #REF!
A6: Casablanca | B6: =B5+1 -> 5 | C6: 3 | D6: 2022 | E6: =submetering!E6+submetering!F6+submetering!G6 -> 0 | F6: 1.05 | G6: ='Consommation mensuel énergie'!V14 -> 0 | H6: 9.965 | I6: ='Consommation mensuel énergie'!F14 -> 0 | J6: 11.4 | K6: ='Consommation mensuel énergie'!D14 -> 0 | L6: ='Consommation mensuel énergie'!E14 -> 0 | M6: =E6*F6+G6*H6+#REF!*#REF!+I6*J6 -> #REF!
A7: Casablanca | B7: =B6+1 -> 6 | C7: 3 | D7: 2022 | E7: =submetering!E7+submetering!F7+submetering!G7 -> 0 | F7: 1.05 | G7: ='Consommation mensuel énergie'!V15 -> 0 | H7: 9.965 | I7: ='Consommation mensuel énergie'!F15 -> 0 | J7: 11.4 | K7: ='Consommation mensuel énergie'!D15 -> 0 | L7: ='Consommation mensuel énergie'!E15 -> 0 | M7: =E7*F7+G7*H7+#REF!*#REF!+I7*J7 -> #REF!
A8: Casablanca | B8: =B7+1 -> 7 | C8: 3 | D8: 2022 | E8: =submetering!E8+submetering!F8+submetering!G8 -> 0 | F8: 1.05 | G8: ='Consommation mensuel énergie'!V16 -> 0 | H8: 9.965 | I8: ='Consommation mensuel énergie'!F16 -> 0 | J8: 11.4 | K8: ='Consommation mensuel énergie'!D16 -> 0 | L8: ='Consommation mensuel énergie'!E16 -> 0 | M8: =E8*F8+G8*H8+#REF!*#REF!+I8*J8 -> #REF!
A9: Casablanca | B9: =B8+1 -> 8 | C9: 3 | D9: 2022 | E9: =submetering!E9+submetering!F9+submetering!G9 -> 0 | F9: 1.05 | G9: ='Consommation mensuel énergie'!V17 -> 0 | H9: 9.965 | I9: ='Consommation mensuel énergie'!F17 -> 0 | J9: 11.4 | K9: ='Consommation mensuel énergie'!D17 -> 0 | L9: ='Consommation mensuel énergie'!E17 -> 0 | M9: =E9*F9+G9*H9+#REF!*#REF!+I9*J9 -> #REF!
A10: Casablanca | B10: =B9+1 -> 9 | C10: 3 | D10: 2022 | E10: =submetering!E10+submetering!F10+submetering!G10 -> 0 | F10: 1.05 | G10: ='Consommation mensuel énergie'!V19 -> 0 | H10: 9.965 | I10: ='Consommation mensuel énergie'!F18 -> 0 | J10: 11.4 | K10: ='Consommation mensuel énergie'!D18 -> 0 | L10: ='Consommation mensuel énergie'!E18 -> 0 | M10: =E10*F10+G10*H10+#REF!*#REF!+I10*J10 -> #REF!
A11: Casablanca | B11: =B10+1 -> 10 | C11: 3 | D11: 2022 | E11: =submetering!E11+submetering!F11+submetering!G11 -> 0 | F11: 1.05 | G11: ='Consommation mensuel énergie'!V20 -> 0 | H11: 9.965 | I11: ='Consommation mensuel énergie'!F19 -> 0 | J11: 11.4 | K11: ='Consommation mensuel énergie'!D19 -> 0 | L11: ='Consommation mensuel énergie'!E19 -> 0 | M11: =E11*F11+G11*H11+#REF!*#REF!+I11*J11 -> #REF!
A12: Casablanca | B12: =B11+1 -> 11 | C12: 3 | D12: 2022 | E12: =submetering!E12+submetering!F12+submetering!G12 -> 0 | F12: 1.05 | G12: ='Consommation mensuel énergie'!V21 -> 0 | H12: 9.965 | I12: ='Consommation mensuel énergie'!F20 -> 0 | J12: 11.4 | K12: ='Consommation mensuel énergie'!D20 -> 0 | L12: ='Consommation mensuel énergie'!E20 -> 0 | M12: =E12*F12+G12*H12+#REF!*#REF!+I12*J12 -> #REF!
A13: Casablanca | B13: =B12+1 -> 12 | C13: 3 | D13: 2022 | E13: =submetering!E13+submetering!F13+submetering!G13 -> 0 | F13: 1.05 | G13: ='Consommation mensuel énergie'!V22 -> 0 | H13: 9.965 | I13: ='Consommation mensuel énergie'!F21 -> 0 | J13: 11.4 | K13: ='Consommation mensuel énergie'!D21 -> 0 | L13: ='Consommation mensuel énergie'!E21 -> 0 | M13: =E13*F13+G13*H13+#REF!*#REF!+I13*J13 -> #REF!
A14: Casablanca | B14: =B13+1 -> 13 | C14: 3 | D14: 2022 | E14: =submetering!E14+submetering!F14+submetering!G14 -> 0 | F14: 1.05 | G14: ='Consommation mensuel énergie'!V23 -> 0 | H14: 9.965 | I14: ='Consommation mensuel énergie'!F22 -> 0 | J14: 11.4 | K14: ='Consommation mensuel énergie'!D22 -> 0 | L14: ='Consommation mensuel énergie'!E22 -> 0 | M14: =E14*F14+G14*H14+#REF!*#REF!+I14*J14 -> #REF!
A15: Casablanca | B15: =B14+1 -> 14 | C15: 3 | D15: 2022 | E15: =submetering!E15+submetering!F15+submetering!G15 -> 0 | F15: 1.05 | G15: ='Consommation mensuel énergie'!V24 -> 0 | H15: 9.965 | I15: ='Consommation mensuel énergie'!F23 -> 0 | J15: 11.4 | K15: ='Consommation mensuel énergie'!D23 -> 0 | L15: ='Consommation mensuel énergie'!E23 -> 0 | M15: =E15*F15+G15*H15+#REF!*#REF!+I15*J15 -> #REF!
A16: Casablanca | B16: =B15+1 -> 15 | C16: 3 | D16: 2022 | E16: =submetering!E16+submetering!F16+submetering!G16 -> 0 | F16: 1.05 | G16: ='Consommation mensuel énergie'!V25 -> 0 | H16: 9.965 | I16: ='Consommation mensuel énergie'!F24 -> 0 | J16: 11.4 | K16: ='Consommation mensuel énergie'!D24 -> 0 | L16: ='Consommation mensuel énergie'!E24 -> 0 | M16: =E16*F16+G16*H16+#REF!*#REF!+I16*J16 -> #REF!
A17: Casablanca | B17: =B16+1 -> 16 | C17: 3 | D17: 2022 | E17: =submetering!E17+submetering!F17+submetering!G17 -> 0 | F17: 1.05 | G17: ='Consommation mensuel énergie'!V26 -> 0 | H17: 9.965 | I17: ='Consommation mensuel énergie'!F25 -> 0 | J17: 11.4 | K17: ='Consommation mensuel énergie'!D25 -> 0 | L17: ='Consommation mensuel énergie'!E25 -> 0 | M17: =E17*F17+G17*H17+#REF!*#REF!+I17*J17 -> #REF!
A18: Casablanca | B18: =B17+1 -> 17 | C18: 3 | D18: 2022 | E18: =submetering!E18+submetering!F18+submetering!G18 -> 0 | F18: 1.05 | G18: ='Consommation mensuel énergie'!V27 -> 0 | H18: 9.965 | I18: ='Consommation mensuel énergie'!F26 -> 0 | J18: 11.4 | K18: ='Consommation mensuel énergie'!D26 -> 0 | L18: ='Consommation mensuel énergie'!E26 -> 0 | M18: =E18*F18+G18*H18+#REF!*#REF!+I18*J18 -> #REF!
A19: Casablanca | B19: =B18+1 -> 18 | C19: 3 | D19: 2022 | E19: =submetering!E19+submetering!F19+submetering!G19 -> 0 | F19: 1.05 | G19: ='Consommation mensuel énergie'!V28 -> 0 | H19: 9.965 | I19: ='Consommation mensuel énergie'!F27 -> 0 | J19: 11.4 | K19: ='Consommation mensuel énergie'!D27 -> 0 | L19: ='Consommation mensuel énergie'!E27 -> 0 | M19: =E19*F19+G19*H19+#REF!*#REF!+I19*J19 -> #REF!
A20: Casablanca | B20: =B19+1 -> 19 | C20: 3 | D20: 2022 | E20: =submetering!E20+submetering!F20+submetering!G20 -> 0 | F20: 1.05 | G20: ='Consommation mensuel énergie'!V29 -> 0 | H20: 9.965 | I20: ='Consommation mensuel énergie'!F28 -> 0 | J20: 11.4 | K20: ='Consommation mensuel énergie'!D28 -> 0 | L20: ='Consommation mensuel énergie'!E28 -> 0 | M20: =E20*F20+G20*H20+#REF!*#REF!+I20*J20 -> #REF!
A21: Casablanca | B21: =B20+1 -> 20 | C21: 3 | D21: 2022 | E21: =submetering!E21+submetering!F21+submetering!G21 -> 0 | F21: 1.05 | G21: ='Consommation mensuel énergie'!V30 -> 0 | H21: 9.965 | I21: ='Consommation mensuel énergie'!F29 -> 0 | J21: 11.4 | K21: ='Consommation mensuel énergie'!D29 -> 0 | L21: ='Consommation mensuel énergie'!E29 -> 0 | M21: =E21*F21+G21*H21+#REF!*#REF!+I21*J21 -> #REF!
... A26: Casablanca | B26: =B25+1 -> 25 | C26: 3 | D26: 2022 | E26: =submetering!E26+submetering!F26+submetering!G26 -> 0 | F26: 1.05 | G26: ='Consommation mensuel énergie'!V35 -> 0 | H26: 9.965 | I26: ='Consommation mensuel énergie'!F34 -> 0 | J26: 11.4 | K26: ='Consommation mensuel énergie'!D34 -> 0 | L26: ='Consommation mensuel énergie'!E34 -> 0 | M26: =E26*F26+G26*H26+#REF!*#REF!+I26*J26 -> #REF!
A27: Casablanca | B27: =B26+1 -> 26 | C27: 3 | D27: 2022 | E27: =submetering!E27+submetering!F27+submetering!G27 -> 0 | F27: 1.05 | G27: ='Consommation mensuel énergie'!V36 -> 0 | H27: 9.965 | I27: ='Consommation mensuel énergie'!F35 -> 0 | J27: 11.4 | K27: ='Consommation mensuel énergie'!D35 -> 0 | L27: ='Consommation mensuel énergie'!E35 -> 0
A28: Casablanca | B28: =B27+1 -> 27 | C28: 3 | D28: 2022 | E28: =submetering!E28+submetering!F28+submetering!G28 -> 0 | F28: 1.05 | G28: ='Consommation mensuel énergie'!V37 -> 0 | H28: 9.965 | I28: ='Consommation mensuel énergie'!F36 -> 0 | J28: 11.4 | K28: ='Consommation mensuel énergie'!D36 -> 0 | L28: ='Consommation mensuel énergie'!E36 -> 0
A29: Casablanca | B29: =B28+1 -> 28 | C29: 3 | D29: 2022 | E29: =submetering!E29+submetering!F29+submetering!G29 -> 0 | F29: 1.05 | G29: ='Consommation mensuel énergie'!V38 -> 0 | H29: 9.965 | I29: ='Consommation mensuel énergie'!F37 -> 0 | J29: 11.4 | K29: ='Consommation mensuel énergie'!D37 -> 0 | L29: ='Consommation mensuel énergie'!E37 -> 0
A30: Casablanca | B30: =B29+1 -> 29 | C30: 3 | D30: 2022 | E30: =submetering!E30+submetering!F30+submetering!G30 -> 0 | F30: 1.05 | G30: ='Consommation mensuel énergie'!V39 -> 0 | H30: 9.965 | I30: ='Consommation mensuel énergie'!F38 -> 0 | J30: 11.4 | K30: ='Consommation mensuel énergie'!D38 -> 0 | L30: ='Consommation mensuel énergie'!E38 -> 0
A31: Casablanca | B31: =B30+1 -> 30 | C31: 3 | D31: 2022 | E31: =submetering!E31+submetering!F31+submetering!G31 -> 0 | F31: 1.05 | G31: ='Consommation mensuel énergie'!V40 -> 0 | H31: 9.965 | I31: ='Consommation mensuel énergie'!F38 -> 0 | J31: 11.4 | K31: ='Consommation mensuel énergie'!D38 -> 0 | L31: ='Consommation mensuel énergie'!E39 -> 0
A32: Casablanca | B32: =B31+1 -> 31 | C32: 3 | D32: 2022 | E32: =submetering!E32+submetering!F32+submetering!G32 -> 0 | F32: 1.05 | G32: ='Consommation mensuel énergie'!V41 -> 0 | H32: 9.965 | I32: ='Consommation mensuel énergie'!F40 -> 0 | J32: 11.4 | K32: ='Consommation mensuel énergie'!D40 -> 0 | L32: ='Consommation mensuel énergie'!E40 -> 0

Sheet submetering
A1: Site Name | B1: Day | C1: Month | D1: Year | E1: Creuse 81 - KWh | F1: Pleine 82-KWh | G1: Pointe 83 - KWh | H1: Room Nights | I1: Total Guests | J1: Utilities day cost dh
A2: Casablanca | B2: 1 | C2: 3 | D2: 2022 | E2: ='Consommation mensuel énergie'!L10 -> 3191 | F2: ='Consommation mensuel énergie'!M10 -> 5249 | G2: ='Consommation mensuel énergie'!N10 -> 2431 | H2: ='Consommation mensuel énergie'!D10 -> 0 | I2: ='Consommation mensuel énergie'!E10 -> 0 | J2: =E2*F2+G2*#REF!+#REF!*#REF!+#REF!*#REF! -> #REF!
A3: Casablanca | B3: =B2+1 -> 2 | C3: 3 | D3: 2022 | E3: ='Consommation mensuel énergie'!L11 -> 0 | F3: ='Consommation mensuel énergie'!M11 -> 0 | G3: ='Consommation mensuel énergie'!N14 -> 0 | H3: ='Consommation mensuel énergie'!D11 -> 0 | I3: ='Consommation mensuel énergie'!E11 -> 0 | J3: =E3*F3+G3*#REF!+#REF!*#REF!+#REF!*#REF! -> #REF!
A4: Casablanca | B4: =B3+1 -> 3 | C4: 3 | D4: 2022 | E4: ='Consommation mensuel énergie'!L12 -> 0 | F4: ='Consommation mensuel énergie'!M12 -> 0 | G4: ='Consommation mensuel énergie'!N12 -> 0 | H4: ='Consommation mensuel énergie'!D12 -> 0 | I4: ='Consommation mensuel énergie'!E12 -> 0 | J4: =E4*F4+G4*#REF!+#REF!*#REF!+#REF!*#REF! -> #REF!
A5: Casablanca | B5: =B4+1 -> 4 | C5: 3 | D5: 2022 | E5: ='Consommation mensuel énergie'!L13 -> 0 | F5: ='Consommation mensuel énergie'!M13 -> 0 | G5: ='Consommation mensuel énergie'!N13 -> 0 | H5: ='Consommation mensuel énergie'!D13 -> 0 | I5: ='Consommation mensuel énergie'!E13 -> 0 | J5: =E5*F5+G5*#REF!+#REF!*#REF!+#REF!*#REF! -> #REF!
A6: Casablanca | B6: =B5+1 -> 5 | C6: 3 | D6: 2022 | E6: ='Consommation mensuel énergie'!L14 -> 0 | F6: ='Consommation mensuel énergie'!M14 -> 0 | G6: ='Consommation mensuel énergie'!N14 -> 0 | H6: ='Consommation mensuel énergie'!D14 -> 0 | I6: ='Consommation mensuel énergie'!E14 -> 0 | J6: =E6*F6+G6*#REF!+#REF!*#REF!+#REF!*#REF! -> #REF!
A7: Casablanca | B7: =B6+1 -> 6 | C7: 3 | D7: 2022 | E7: ='Consommation mensuel énergie'!L15 -> 0 | F7: ='Consommation mensuel énergie'!M15 -> 0 | G7: ='Consommation mensuel énergie'!N15 -> 0 | H7: ='Consommation mensuel énergie'!D15 -> 0 | I7: ='Consommation mensuel énergie'!E15 -> 0 | J7: =E7*F7+G7*#REF!+#REF!*#REF!+#REF!*#REF! -> #REF!
A8: Casablanca | B8: =B7+1 -> 7 | C8: 3 | D8: 2022 | E8: ='Consommation mensuel énergie'!L16 -> 0 | F8: ='Consommation mensuel énergie'!M16 -> 0 | G8: ='Consommation mensuel énergie'!N16 -> 0 | H8: ='Consommation mensuel énergie'!D16 -> 0 | I8: ='Consommation mensuel énergie'!E16 -> 0 | J8: =E8*F8+G8*#REF!+#REF!*#REF!+#REF!*#REF! -> #REF!
A9: Casablanca | B9: =B8+1 -> 8 | C9: 3 | D9: 2022 | E9: ='Consommation mensuel énergie'!L17 -> 0 | F9: ='Consommation mensuel énergie'!M17 -> 0 | G9: ='Consommation mensuel énergie'!N17 -> 0 | H9: ='Consommation mensuel énergie'!D17 -> 0 | I9: ='Consommation mensuel énergie'!E17 -> 0 | J9: =E9*F9+G9*#REF!+#REF!*#REF!+#REF!*#REF! -> #REF!
A10: Casablanca | B10: =B9+1 -> 9 | C10: 3 | D10: 2022 | E10: ='Consommation mensuel énergie'!L18 -> 0 | F10: ='Consommation mensuel énergie'!M18 -> 0 | G10: ='Consommation mensuel énergie'!N18 -> 0 | H10: ='Consommation mensuel énergie'!D18 -> 0 | I10: ='Consommation mensuel énergie'!E18 -> 0 | J10: =E10*F10+G10*#REF!+#REF!*#REF!+#REF!*#REF! -> #REF!
A11: Casablanca | B11: =B10+1 -> 10 | C11: 3 | D11: 2022 | E11: ='Consommation mensuel énergie'!L19 -> 0 | F11: ='Consommation mensuel énergie'!M19 -> 0 | G11: ='Consommation mensuel énergie'!N19 -> 0 | H11: ='Consommation mensuel énergie'!D19 -> 0 | I11: ='Consommation mensuel énergie'!E19 -> 0 | J11: =E11*F11+G11*#REF!+#REF!*#REF!+#REF!*#REF! -> #REF!
A12: Casablanca | B12: =B11+1 -> 11 | C12: 3 | D12: 2022 | E12: ='Consommation mensuel énergie'!L20 -> 0 | F12: ='Consommation mensuel énergie'!M20 -> 0 | G12: ='Consommation mensuel énergie'!N20 -> 0 | H12: ='Consommation mensuel énergie'!D20 -> 0 | I12: ='Consommation mensuel énergie'!E20 -> 0 | J12: =E12*F12+G12*#REF!+#REF!*#REF!+#REF!*#REF! -> #REF!
A13: Casablanca | B13: =B12+1 -> 12 | C13: 3 | D13: 2022 | E13: ='Consommation mensuel énergie'!L21 -> 0 | F13: ='Consommation mensuel énergie'!M21 -> 0 | G13: ='Consommation mensuel énergie'!N21 -> 0 | H13: ='Consommation mensuel énergie'!D21 -> 0 | I13: ='Consommation mensuel énergie'!E21 -> 0 | J13: =E13*F13+G13*#REF!+#REF!*#REF!+#REF!*#REF! -> #REF!
A14: Casablanca | B14: =B13+1 -> 13 | C14: 3 | D14: 2022 | E14: ='Consommation mensuel énergie'!L22 -> 0 | F14: ='Consommation mensuel énergie'!M22 -> 0 | G14: ='Consommation mensuel énergie'!N22 -> 0 | H14: ='Consommation mensuel énergie'!D22 -> 0 | I14: ='Consommation mensuel énergie'!E22 -> 0 | J14: =E14*F14+G14*#REF!+#REF!*#REF!+#REF!*#REF! -> #REF!
A15: Casablanca | B15: =B14+1 -> 14 | C15: 3 | D15: 2022 | E15: ='Consommation mensuel énergie'!L23 -> 0 | F15: ='Consommation mensuel énergie'!M23 -> 0 | G15: ='Consommation mensuel énergie'!N23 -> 0 | H15: ='Consommation mensuel énergie'!D23 -> 0 | I15: ='Consommation mensuel énergie'!E23 -> 0 | J15: =E15*F15+G15*#REF!+#REF!*#REF!+#REF!*#REF! -> #REF!
... A26: Casablanca | B26: =B25+1 -> 25 | C26: 3 | D26: 2022 | E26: ='Consommation mensuel énergie'!L34 -> 0 | F26: ='Consommation mensuel énergie'!M34 -> 0 | G26: ='Consommation mensuel énergie'!N34 -> 0 | H26: ='Consommation mensuel énergie'!D34 -> 0 | I26: ='Consommation mensuel énergie'!E34 -> 0 | J26: =E26*F26+G26*#REF!+#REF!*#REF!+#REF!*#REF! -> #REF!
A27: Casablanca | B27: =B26+1 -> 26 | C27: 3 | D27: 2022 | E27: ='Consommation mensuel énergie'!L35 -> 0 | F27: ='Consommation mensuel énergie'!M35 -> 0 | G27: ='Consommation mensuel énergie'!N35 -> 0 | H27: ='Consommation mensuel énergie'!D35 -> 0 | I27: ='Consommation mensuel énergie'!E35 -> 0
A28: Casablanca | B28: =B27+1 -> 27 | C28: 3 | D28: 2022 | E28: ='Consommation mensuel énergie'!L36 -> 0 | F28: ='Consommation mensuel énergie'!M36 -> 0 | G28: ='Consommation mensuel énergie'!N36 -> 0 | H28: ='Consommation mensuel énergie'!D36 -> 0 | I28: ='Consommation mensuel énergie'!E36 -> 0
A29: Casablanca | B29: =B28+1 -> 28 | C29: 3 | D29: 2022 | E29: ='Consommation mensuel énergie'!L37 -> 0 | F29: ='Consommation mensuel énergie'!M37 -> 0 | G29: ='Consommation mensuel énergie'!N37 -> 0 | H29: ='Consommation mensuel énergie'!D37 -> 0 | I29: ='Consommation mensuel énergie'!E37 -> 0
A30: Casablanca | B30: =B29+1 -> 29 | C30: 3 | D30: 2022 | E30: ='Consommation mensuel énergie'!L38 -> 0 | F30: ='Consommation mensuel énergie'!M38 -> 0 | G30: ='Consommation mensuel énergie'!N38 -> 0 | H30: ='Consommation mensuel énergie'!D38 -> 0 | I30: ='Consommation mensuel énergie'!E38 -> 0
A31: Casablanca | B31: =B30+1 -> 30 | C31: 3 | D31: 2022 | E31: ='Consommation mensuel énergie'!L39 -> 0 | F31: ='Consommation mensuel énergie'!M39 -> 0 | G31: ='Consommation mensuel énergie'!N39 -> 0 | H31: ='Consommation mensuel énergie'!D39 -> 0 | I31: ='Consommation mensuel énergie'!E39 -> 0
A32: Casablanca | B32: =B31+1 -> 31 | C32: 3 | D32: 2022 | E32: ='Consommation mensuel énergie'!L40 -> 0 | F32: ='Consommation mensuel énergie'!M40 -> 0 | G32: ='Consommation mensuel énergie'!N40 -> 0 | H32: ='Consommation mensuel énergie'!D40 -> 0 | I32: ='Consommation mensuel énergie'!E40 -> 0

Sheet Consommation mensuel énergie
I2: Consommation mensuel Eau /électricité/Gaz
B8: Date | D8: ROOM Nights | E8: Guests | F8: Cons Eau/Hotel | H8: Consommation du jour en DH | K8: date / électr | L8: ELECTRICITE en KWH | O8: total | Q8: Consommation du jour en DH | S8: Cons Elec/Villa | U8: Cons Elec/RIAD | V8: GAZ en Kg | X8: Consommation du jour en DH
L9: creuse 81 | M9: pleine 82 | N9: pointe 83
B10: 44621 | F10: ='Suivi EAU-ELEC'!E9 -> 104 | H10: =F10*8.79 -> 914.16 | K10: 42278 | L10: ='Suivi EAU-ELEC'!G9 -> 3191 | M10: ='Suivi EAU-ELEC'!I9 -> 5249 | N10: ='Suivi EAU-ELEC'!K9 -> 2431 | O10: =L10+M10+N10 -> 10871 | Q10: =L10*0.6985+M10*0.9514+N10*1.3304 -> 10457.015 | X10: =V10*11.79 -> 0
B11: 44622 | H11: =F11*8.79 -> 0 | K11: 42279 | O11: =L11+M11+N11 -> 0 | Q11: =L11*0.6985+M11*0.9514+N14*1.3304 -> 0 | X11: =V11*11.79 -> 0
B12: 44623 | H12: =F12*8.79 -> 0 | K12: 42280 | O12: =L12+M12+N12 -> 0 | Q12: =L12*0.6985+M12*0.9514+N12*1.3304 -> 0 | X12: =V12*11.79 -> 0
B13: 44624 | H13: =F13*8.79 -> 0 | K13: 42281 | O13: =L13+M13+N13 -> 0 | Q13: =L13*0.6985+M13*0.9514+N13*1.3304 -> 0 | X13: =V13*11.79 -> 0
B14: 44625 | H14: =F14*8.79 -> 0 | K14: 42282 | O14: =L14+M14+N14 -> 0 | Q14: =L14*0.6985+M14*0.9514+N14*1.3304 -> 0 | X14: =V14*11.79 -> 0
B15: 44626 | H15: =F15*8.79 -> 0 | K15: 42283 | O15: =L15+M15+N15 -> 0 | Q15: =L15*0.6985+M15*0.9514+N15*1.3304 -> 0 | X15: =V15*11.79 -> 0
B16: 44627 | H16: =F16*8.79 -> 0 | K16: 42284 | O16: =L16+M16+N16 -> 0 | Q16: =L16*0.6985+M16*0.9514+N16*1.3304 -> 0 | X16: =V16*11.79 -> 0
B17: 44628 | H17: =F17*8.79 -> 0 | K17: 42285 | O17: =L17+M17+N17 -> 0 | Q17: =L17*0.6985+M17*0.9514+N17*1.3304 -> 0 | X17: =V17*11.79 -> 0
B18: 44629 | H18: =F18*8.79 -> 0 | K18: 42286 | O18: =L18+M18+N18 -> 0 | Q18: =L18*0.6985+M18*0.9514+N18*1.3304 -> 0 | X18: =V18*11.79 -> 0
B19: 44630 | H19: =F19*8.79 -> 0 | K19: 42287 | O19: =L19+M19+N19 -> 0 | Q19: =L19*0.6985+M19*0.9514+N19*1.3304 -> 0 | X19: =V19*11.79 -> 0
B20: 44631 | H20: =F20*8.79 -> 0 | K20: 42288 | O20: =L20+M20+N20 -> 0 | Q20: =L20*0.6985+M20*0.9514+N20*1.3304 -> 0 | X20: =V20*11.79 -> 0
B21: 44632 | H21: =F21*8.79 -> 0 | K21: 42289 | O21: =L21+M21+N21 -> 0 | Q21: =L21*0.6985+M21*0.9514+N21*1.3304 -> 0 | X21: =V21*11.79 -> 0
B22: 44633 | H22: =F22*8.79 -> 0 | K22: 42290 | O22: =L22+M22+N22 -> 0 | Q22: =L22*0.6985+M22*0.9514+N22*1.3304 -> 0 | X22: =V22*11.79 -> 0
B23: 44634 | H23: =F23*8.79 -> 0 | K23: 42291 | O23: =L23+M23+N23 -> 0 | Q23: =L23*0.6985+M23*0.9514+N23*1.3304 -> 0 | X23: =V23*11.79 -> 0
... B35: 44646 | H35: =F35*8.79 -> 0 | K35: 42303 | O35: =L35+M35+N35 -> 0 | Q35: =L35*0.6985+M35*0.9514+N35*1.3304 -> 0 | X35: =V35*11.79 -> 0
B36: 44647 | H36: =F36*8.79 -> 0 | O36: =L36+M36+N36 -> 0 | Q36: =L36*0.6985+M36*0.9514+N36*1.3304 -> 0
B37: 44648 | H37: =F37*8.79 -> 0 | O37: =L37+M37+N37 -> 0 | Q37: =L37*0.6985+M37*0.9514+N37*1.3304 -> 0
B38: 44649 | H38: =F38*8.79 -> 0 | K38: 42304 | O38: =L38+M38+N38 -> 0 | Q38: =L38*0.6985+M38*0.9514+N38*1.3304 -> 0 | X38: =V38*11.79 -> 0
B39: 44650 | H39: =F39*8.79 -> 0 | O39: =L39+M39+N39 -> 0 | Q39: =L39*0.6985+M39*0.9514+N39*1.3304 -> 0
B40: 44651 | H40: =F40*8.79 -> 0 | O40: =L40+M40+N40 -> 0 | Q40: =L40*0.6985+M40*0.9514+N40*1.3304 -> 0 | X40: =V40*11.79 -> 0
D41: =SUM(D10:D40) -> 0 | E41: =SUM(E10:E40) -> 0 | F41: =SUM(F10:F40) -> 104 | H41: =SUM(H10:H40) -> 914.16 | L41: =SUM(L10:L40) -> 3191 | M41: =SUM(M10:M40) -> 5249 | N41: =SUM(N10:N40) -> 2431 | O41: =SUM(O10:O40) -> 10871 | Q41: =SUM(Q10:Q40) -> 10457.015 | S41: =SUM(S10:S40) -> 0 | U41: =SUM(U10:U40) -> 0 | V41: =SUM(V10:V40) -> 0 | X41: =SUM(X10:X40) -> 0
A43: Désignation | H43: COUTS | I43: Consommations | L43: Consommations /DHs | N43: TOTAL Consommations /DHs
A44: ELECTRICITE / Kw/h | D44: creuse 81 | E44: creuse 81 | F44: creuse 81 | H44: 0.6985 | I44: =L41 -> 3191 | L44: =I44*H44 -> 2228.9135 | N44: =L44+L45+L46 -> 10457.015
D45: pleine 82 | E45: pleine 82 | F45: pleine 82 | H45: 0.9514 | I45: =M41 -> 5249 | L45: =I45*H45 -> 4993.8986
D46: pointe 83 | E46: pointe 83 | F46: pointe 83 | H46: 1.3304 | I46: =N41 -> 2431 | L46: =I46*H46 -> 3234.2024
N47: =N44*1.3 -> 13594.119
A48: EAU HOTEL M3 | H48: 8.79 | I48: =F41 -> 104 | L48: =I48*H48 -> 914.16 | N48: =L48 -> 914.16
A49: GAZ Kg | H49: 11.79 | I49: =V41 -> 0 | L49: =I49*H49 -> 0 | N49: =L49 -> 0

Sheet Suivi EAU-ELEC
E1: Suivi Compteur d'Eau- électricité Lydec- MARS 2022 | J1: Département Engineering 2022
A7: Date/électriqie | B7: Incendie | D7: Eau m3 | F7: Electricité Kw/h
B8: Compteur | C8: Consommation | D8: Compteur | E8: Consommation | F8: Compteur H.Creuse | G8: Consommation H.Creuse | H8: Compteur H.Pleine | I8: Consommation H.Pleine | J8: Compteur H.Pointe | K8: Consommation H.Pointe
A9: 44621 | B9: 2560 | C9: 0 | D9: 136510 | E9: 104 | F9: 11511320 | G9: 3191 | H9: 19513625 | I9: 5249 | J9: 8573535 | K9: 2431
A10: 44622
A11: 44623 | C11: =B11-B10 -> 0 | E11: =D11-D10 -> 0 | G11: =F11-F10 -> 0 | I11: =H11-H10 -> 0 | K11: =J11-J10 -> 0
A12: 44624 | C12: =B12-B11 -> 0 | E12: =D12-D11 -> 0 | G12: =F12-F11 -> 0 | I12: =H12-H11 -> 0 | K12: =J12-J11 -> 0
A13: 44625 | C13: =B13-B12 -> 0 | E13: =D13-D12 -> 0 | G13: =F13-F12 -> 0 | I13: =H13-H12 -> 0 | K13: =J13-J12 -> 0
A14: 44626 | C14: =B14-B13 -> 0 | E14: =D14-D13 -> 0 | G14: =F14-F13 -> 0 | I14: =H14-H13 -> 0 | K14: =J14-J13 -> 0
A15: 44627 | C15: =B15-B14 -> 0 | E15: =D15-D14 -> 0 | G15: =F15-F14 -> 0 | I15: =H15-H14 -> 0 | K15: =J15-J14 -> 0
A16: 44628 | C16: =B16-B15 -> 0 | E16: =D16-D15 -> 0 | G16: =F16-F15 -> 0 | I16: =H16-H15 -> 0 | K16: =J16-J15 -> 0
A17: 44629 | C17: =B17-B16 -> 0 | E17: =D17-D16 -> 0 | G17: =F17-F16 -> 0 | I17: =H17-H16 -> 0 | K17: =J17-J16 -> 0
A18: 44630 | C18: =B18-B17 -> 0 | E18: =D18-D17 -> 0 | G18: =F18-F17 -> 0 | I18: =H18-H17 -> 0 | K18: =J18-J17 -> 0
A19: 44631 | C19: =B19-B18 -> 0 | E19: =D19-D18 -> 0 | G19: =F19-F18 -> 0 | I19: =H19-H18 -> 0 | K19: =J19-J18 -> 0
A20: 44632 | C20: =B20-B19 -> 0 | E20: =D20-D19 -> 0 | G20: =F20-F19 -> 0 | I20: =H20-H19 -> 0 | K20: =J20-J19 -> 0
A21: 44633 | C21: =B21-B20 -> 0 | E21: =D21-D20 -> 0 | G21: =F21-F20 -> 0 | I21: =H21-H20 -> 0 | K21: =J21-J20 -> 0
A22: 44634 | C22: =B22-B21 -> 0 | E22: =D22-D21 -> 0 | G22: =F22-F21 -> 0 | I22: =H22-H21 -> 0 | K22: =J22-J21 -> 0
... A37: 44649 | C37: =B37-B36 -> 0 | E37: =D37-D36 -> 0 | G37: =F37-F36 -> 0 | I37: =H37-H36 -> 0 | K37: =J37-J36 -> 0
A38: 44650
A39: 44651
A40: 44652

Sheet Suvi Gaz
F1: suivi Gaz MARS 2022
Q2: 803 | T2: 519 | W2: 800 | Z2: 802
B3: Relvé C1 | C3: cons C1 | D3: Relvé C2 | E3: cons C2 | F3: Relvé C3 | G3: cons C3 | H3: Relvé C4 | I3: cons C4 | J3: ∑ des relevés | K3: moyen general % | L3: con.j | M3: ∑ de volume en L | N3: cons./jen L | O3: cons./jen Kg | P3: cons./jen DH | Q3: livraison C1 | R3: %Avant | S3: % Après | T3: livraison C2 | U3: %Avant | V3: % Après | W3: livraison C3 | X3: %Avant | Y3: % Après | Z3: livraison C4 | AA3: %Avant | AB3: % Après | AC3: total livraison litre | AD3: moyen general % Avant L | AE3: moyen general % Aaprés L
A4: 44621 | B4: 66 | C4: =IF(AC4>0,((B4-R4)+(S4-B5)),IF(B5=0, ,(B4-B5))) -> 0 | D4: 68 | E4: =IF(AC4>0,((D4-U4)+(V4-D5)),IF(D5=0, ,(D4-D5))) -> 0 | F4: 72 | G4: =IF(AC4>0,((F4-X4)+(Y4-F5)),IF(F5=0, ,(F4-F5))) -> 0 | H4: 73 | I4: =IF(AC4>0,((H4-AA4)+(AB4-H5)),IF(H5=0, ,(H4-H5))) -> 0 | J4: =B4+D4+F4+H4 -> 279 | K4: =J4/4 -> 69.75 | L4: =IF(AC4>0,((K4-AD4)+(AE4-K5)),IF(K5=0, ,(K4-K5))) -> 0 | M4: =6049*4 -> 24196 | N4: =L4*M4/100 -> 0 | O4: =N4*0.529 -> 0 | P4: =O4*11.79 -> 0 | AC4: =Q4+T4+W4+Z4 -> 0 | AD4: =(R4+U4+X4+AA4)/4 -> 0 | AE4: =(S4+V4+Y4+AB4)/4 -> 0
A5: 44622 | C5: =IF(AC5>0,((B5-R5)+(S5-B6)),IF(B6=0, ,(B5-B6))) -> 0 | E5: =IF(AC5>0,((D5-U5)+(V5-D6)),IF(D6=0, ,(D5-D6))) -> 0 | G5: =IF(AC5>0,((F5-X5)+(Y5-F6)),IF(F6=0, ,(F5-F6))) -> 0 | I5: =IF(AC5>0,((H5-AA5)+(AB5-H6)),IF(H6=0, ,(H5-H6))) -> 0 | J5: =B5+D5+F5+H5 -> 0 | K5: =J5/4 -> 0 | L5: =IF(AC5>0,((K5-AD5)+(AE5-K6)),IF(K6=0, ,(K5-K6))) -> 0 | M5: =6049*4 -> 24196 | N5: =L5*M5/100 -> 0 | O5: =N5*0.529 -> 0 | P5: =O5*11.79 -> 0 | AC5: =Q5+T5+W5+Z5 -> 0 | AD5: =(R5+U5+X5+AA5)/4 -> 0 | AE5: =(S5+V5+Y5+AB5)/4 -> 0
A6: 44623 | C6: =IF(AC6>0,((B6-R6)+(S6-B7)),IF(B7=0, ,(B6-B7))) -> 0 | E6: =IF(AC6>0,((D6-U6)+(V6-D7)),IF(D7=0, ,(D6-D7))) -> 0 | G6: =IF(AC6>0,((F6-X6)+(Y6-F7)),IF(F7=0, ,(F6-F7))) -> 0 | I6: =IF(AC6>0,((H6-AA6)+(AB6-H7)),IF(H7=0, ,(H6-H7))) -> 0 | J6: =B6+D6+F6+H6 -> 0 | K6: =J6/4 -> 0 | L6: =IF(AC6>0,((K6-AD6)+(AE6-K7)),IF(K7=0, ,(K6-K7))) -> 0 | M6: =6049*4 -> 24196 | N6: =L6*M6/100 -> 0 | O6: =N6*0.529 -> 0 | P6: =O6*11.79 -> 0 | AC6: =Q6+T6+W6+Z6 -> 0 | AD6: =(R6+U6+X6+AA6)/4 -> 0 | AE6: =(S6+V6+Y6+AB6)/4 -> 0
A7: 44624 | C7: =IF(AC7>0,((B7-R7)+(S7-B8)),IF(B8=0, ,(B7-B8))) -> 0 | E7: =IF(AC7>0,((D7-U7)+(V7-D8)),IF(D8=0, ,(D7-D8))) -> 0 | G7: =IF(AC7>0,((F7-X7)+(Y7-F8)),IF(F8=0, ,(F7-F8))) -> 0 | I7: =IF(AC7>0,((H7-AA7)+(AB7-H8)),IF(H8=0, ,(H7-H8))) -> 0 | J7: =B7+D7+F7+H7 -> 0 | K7: =J7/4 -> 0 | L7: =IF(AC7>0,((K7-AD7)+(AE7-K8)),IF(K8=0, ,(K7-K8))) -> 0 | M7: =6049*4 -> 24196 | N7: =L7*M7/100 -> 0 | O7: =N7*0.53 -> 0 | P7: =O7*11.79 -> 0 | AC7: =Q7+T7+W7+Z7 -> 0 | AD7: =(R7+U7+X7+AA7)/4 -> 0 | AE7: =(S7+V7+Y7+AB7)/4 -> 0
A8: 44625 | C8: =IF(AC8>0,((B8-R8)+(S8-B9)),IF(B9=0, ,(B8-B9))) -> 0 | E8: =IF(AC8>0,((D8-U8)+(V8-D9)),IF(D9=0, ,(D8-D9))) -> 0 | G8: =IF(AC8>0,((F8-X8)+(Y8-F9)),IF(F9=0, ,(F8-F9))) -> 0 | I8: =IF(AC8>0,((H8-AA8)+(AB8-H9)),IF(H9=0, ,(H8-H9))) -> 0 | J8: =B8+D8+F8+H8 -> 0 | K8: =J8/4 -> 0 | L8: =IF(AC8>0,((K8-AD8)+(AE8-K9)),IF(K9=0, ,(K8-K9))) -> 0 | M8: =6049*4 -> 24196 | N8: =L8*M8/100 -> 0 | O8: =N8*0.529 -> 0 | P8: =O8*11.79 -> 0 | AC8: =Q8+T8+W8+Z8 -> 0 | AD8: =(R8+U8+X8+AA8)/4 -> 0 | AE8: =(S8+V8+Y8+AB8)/4 -> 0
A9: 44626 | C9: =IF(AC9>0,((B9-R9)+(S9-B10)),IF(B10=0, ,(B9-B10))) -> 0 | E9: =IF(AC9>0,((D9-U9)+(V9-D10)),IF(D10=0, ,(D9-D10))) -> 0 | G9: =IF(AC9>0,((F9-X9)+(Y9-F10)),IF(F10=0, ,(F9-F10))) -> 0 | I9: =IF(AC9>0,((H9-AA9)+(AB9-H10)),IF(H10=0, ,(H9-H10))) -> 0 | J9: =B9+D9+F9+H9 -> 0 | K9: =J9/4 -> 0 | L9: =IF(AC9>0,((K9-AD9)+(AE9-K10)),IF(K10=0, ,(K9-K10))) -> 0 | M9: =6049*4 -> 24196 | N9: =L9*M9/100 -> 0 | O9: =N9*0.529 -> 0 | P9: =O9*11.79 -> 0 | AC9: =Q9+T9+W9+Z9 -> 0 | AD9: =(R9+U9+X9+AA9)/4 -> 0 | AE9: =(S9+V9+Y9+AB9)/4 -> 0
A10: 44627 | C10: =IF(AC10>0,((B10-R10)+(S10-B11)),IF(B11=0, ,(B10-B11))) -> 0 | E10: =IF(AC10>0,((D10-U10)+(V10-D11)),IF(D11=0, ,(D10-D11))) -> 0 | G10: =IF(AC10>0,((F10-X10)+(Y10-F11)),IF(F11=0, ,(F10-F11))) -> 0 | I10: =IF(AC10>0,((H10-AA10)+(AB10-H11)),IF(H11=0, ,(H10-H11))) -> 0 | J10: =B10+D10+F10+H10 -> 0 | K10: =J10/4 -> 0 | L10: =IF(AC10>0,((K10-AD10)+(AE10-K11)),IF(K11=0, ,(K10-K11))) -> 0 | M10: =6049*4 -> 24196 | N10: =L10*M10/100 -> 0 | O10: =N10*0.529 -> 0 | P10: =O10*11.79 -> 0 | AC10: =Q10+T10+W10+Z10 -> 0 | AD10: =(R10+U10+X10+AA10)/4 -> 0 | AE10: =(S10+V10+Y10+AB10)/4 -> 0
A11: 44628 | C11: =IF(AC11>0,((B11-R11)+(S11-B12)),IF(B12=0, ,(B11-B12))) -> 0 | E11: =IF(AC11>0,((D11-U11)+(V11-D12)),IF(D12=0, ,(D11-D12))) -> 0 | G11: =IF(AC11>0,((F11-X11)+(Y11-F12)),IF(F12=0, ,(F11-F12))) -> 0 | I11: =IF(AC11>0,((H11-AA11)+(AB11-H12)),IF(H12=0, ,(H11-H12))) -> 0 | J11: =B11+D11+F11+H11 -> 0 | K11: =J11/4 -> 0 | L11: =IF(AC11>0,((K11-AD11)+(AE11-K12)),IF(K12=0, ,(K11-K12))) -> 0 | M11: =6049*4 -> 24196 | N11: =L11*M11/100 -> 0 | O11: =N11*0.529 -> 0 | P11: =O11*11.79 -> 0 | AC11: =Q11+T11+W11+Z11 -> 0 | AD11: =(R11+U11+X11+AA11)/4 -> 0 | AE11: =(S11+V11+Y11+AB11)/4 -> 0
A12: 44629 | C12: =IF(AC12>0,((B12-R12)+(S12-B13)),IF(B13=0, ,(B12-B13))) -> 0 | E12: =IF(AC12>0,((D12-U12)+(V12-D13)),IF(D13=0, ,(D12-D13))) -> 0 | G12: =IF(AC12>0,((F12-X12)+(Y12-F13)),IF(F13=0, ,(F12-F13))) -> 0 | I12: =IF(AC12>0,((H12-AA12)+(AB12-H13)),IF(H13=0, ,(H12-H13))) -> 0 | J12: =B12+D12+F12+H12 -> 0 | K12: =J12/4 -> 0 | L12: =IF(AC12>0,((K12-AD12)+(AE12-K13)),IF(K13=0, ,(K12-K13))) -> 0 | M12: =6049*4 -> 24196 | N12: =L12*M12/100 -> 0 | O12: =N12*0.529 -> 0 | P12: =O12*11.79 -> 0 | AC12: =Q12+T12+W12+Z12 -> 0 | AD12: =(R12+U12+X12+AA12)/4 -> 0 | AE12: =(S12+V12+Y12+AB12)/4 -> 0
A13: 44630 | C13: =IF(AC13>0,((B13-R13)+(S13-B14)),IF(B14=0, ,(B13-B14))) -> 0 | E13: =IF(AC13>0,((D13-U13)+(V13-D14)),IF(D14=0, ,(D13-D14))) -> 0 | G13: =IF(AC13>0,((F13-X13)+(Y13-F14)),IF(F14=0, ,(F13-F14))) -> 0 | I13: =IF(AC13>0,((H13-AA13)+(AB13-H14)),IF(H14=0, ,(H13-H14))) -> 0 | J13: =B13+D13+F13+H13 -> 0 | K13: =J13/4 -> 0 | L13: =IF(AC13>0,((K13-AD13)+(AE13-K14)),IF(K14=0, ,(K13-K14))) -> 0 | M13: =6049*4 -> 24196 | N13: =L13*M13/100 -> 0 | O13: =N13*0.529 -> 0 | P13: =O13*11.79 -> 0 | AC13: =Q13+T13+W13+Z13 -> 0 | AD13: =(R13+U13+X13+AA13)/4 -> 0 | AE13: =(S13+V13+Y13+AB13)/4 -> 0
A14: 44631 | C14: =IF(AC14>0,((B14-R14)+(S14-B15)),IF(B15=0, ,(B14-B15))) -> 0 | E14: =IF(AC14>0,((D14-U14)+(V14-D15)),IF(D15=0, ,(D14-D15))) -> 0 | G14: =IF(AC14>0,((F14-X14)+(Y14-F15)),IF(F15=0, ,(F14-F15))) -> 0 | I14: =IF(AC14>0,((H14-AA14)+(AB14-H15)),IF(H15=0, ,(H14-H15))) -> 0 | J14: =B14+D14+F14+H14 -> 0 | K14: =J14/4 -> 0 | L14: =IF(AC14>0,((K14-AD14)+(AE14-K15)),IF(K15=0, ,(K14-K15))) -> 0 | M14: =6049*4 -> 24196 | N14: =L14*M14/100 -> 0 | O14: =N14*0.529 -> 0 | P14: =O14*11.79 -> 0 | AC14: =Q14+T14+W14+Z14 -> 0 | AD14: =(R14+U14+X14+AA14)/4 -> 0 | AE14: =(S14+V14+Y14+AB14)/4 -> 0
A15: 44632 | C15: =IF(AC15>0,((B15-R15)+(S15-B16)),IF(B16=0, ,(B15-B16))) -> 0 | E15: =IF(AC15>0,((D15-U15)+(V15-D16)),IF(D16=0, ,(D15-D16))) -> 0 | G15: =IF(AC15>0,((F15-X15)+(Y15-F16)),IF(F16=0, ,(F15-F16))) -> 0 | I15: =IF(AC15>0,((H15-AA15)+(AB15-H16)),IF(H16=0, ,(H15-H16))) -> 0 | J15: =B15+D15+F15+H15 -> 0 | K15: =J15/4 -> 0 | L15: =IF(AC15>0,((K15-AD15)+(AE15-K16)),IF(K16=0, ,(K15-K16))) -> 0 | M15: =6049*4 -> 24196 | N15: =L15*M15/100 -> 0 | O15: =N15*0.529 -> 0 | P15: =O15*11.79 -> 0 | AC15: =Q15+T15+W15+Z15 -> 0 | AD15: =(R15+U15+X15+AA15)/4 -> 0 | AE15: =(S15+V15+Y15+AB15)/4 -> 0
A16: 44633 | C16: =IF(AC16>0,((B16-R16)+(S16-B17)),IF(B17=0, ,(B16-B17))) -> 0 | E16: =IF(AC16>0,((D16-U16)+(V16-D17)),IF(D17=0, ,(D16-D17))) -> 0 | G16: =IF(AC16>0,((F16-X16)+(Y16-F17)),IF(F17=0, ,(F16-F17))) -> 0 | I16: =IF(AC16>0,((H16-AA16)+(AB16-H17)),IF(H17=0, ,(H16-H17))) -> 0 | J16: =B16+D16+F16+H16 -> 0 | K16: =J16/4 -> 0 | L16: =IF(AC16>0,((K16-AD16)+(AE16-K17)),IF(K17=0, ,(K16-K17))) -> 0 | M16: =6049*4 -> 24196 | N16: =L16*M16/100 -> 0 | O16: =N16*0.529 -> 0 | P16: =O16*11.79 -> 0 | AC16: =Q16+T16+W16+Z16 -> 0 | AD16: =(R16+U16+X16+AA16)/4 -> 0 | AE16: =(S16+V16+Y16+AB16)/4 -> 0
A17: 44634 | C17: =IF(AC17>0,((B17-R17)+(S17-B18)),IF(B18=0, ,(B17-B18))) -> 0 | E17: =IF(AC17>0,((D17-U17)+(V17-D18)),IF(D18=0, ,(D17-D18))) -> 0 | G17: =IF(AC17>0,((F17-X17)+(Y17-F18)),IF(F18=0, ,(F17-F18))) -> 0 | I17: =IF(AC17>0,((H17-AA17)+(AB17-H18)),IF(H18=0, ,(H17-H18))) -> 0 | J17: =B17+D17+F17+H17 -> 0 | K17: =J17/4 -> 0 | L17: =IF(AC17>0,((K17-AD17)+(AE17-K18)),IF(K18=0, ,(K17-K18))) -> 0 | M17: =6049*4 -> 24196 | N17: =L17*M17/100 -> 0 | O17: =N17*0.529 -> 0 | P17: =O17*11.79 -> 0 | AC17: =Q17+T17+W17+Z17 -> 0 | AD17: =(R17+U17+X17+AA17)/4 -> 0 | AE17: =(S17+V17+Y17+AB17)/4 -> 0
A18: 44635 | C18: =IF(AC18>0,((B18-R18)+(S18-B19)),IF(B19=0, ,(B18-B19))) -> 0 | E18: =IF(AC18>0,((D18-U18)+(V18-D19)),IF(D19=0, ,(D18-D19))) -> 0 | G18: =IF(AC18>0,((F18-X18)+(Y18-F19)),IF(F19=0, ,(F18-F19))) -> 0 | I18: =IF(AC18>0,((H18-AA18)+(AB18-H19)),IF(H19=0, ,(H18-H19))) -> 0 | J18: =B18+D18+F18+H18 -> 0 | K18: =J18/4 -> 0 | L18: =IF(AC18>0,((K18-AD18)+(AE18-K19)),IF(K19=0, ,(K18-K19))) -> 0 | M18: =6049*4 -> 24196 | N18: =L18*M18/100 -> 0 | O18: =N18*0.529 -> 0 | P18: =O18*11.79 -> 0 | AC18: =Q18+T18+W18+Z18 -> 0 | AD18: =(R18+U18+X18+AA18)/4 -> 0 | AE18: =(S18+V18+Y18+AB18)/4 -> 0
A19: 44636 | C19: =IF(AC19>0,((B19-R19)+(S19-B20)),IF(B20=0, ,(B19-B20))) -> 0 | E19: =IF(AC19>0,((D19-U19)+(V19-D20)),IF(D20=0, ,(D19-D20))) -> 0 | G19: =IF(AC19>0,((F19-X19)+(Y19-F20)),IF(F20=0, ,(F19-F20))) -> 0 | I19: =IF(AC19>0,((H19-AA19)+(AB19-H20)),IF(H20=0, ,(H19-H20))) -> 0 | J19: =B19+D19+F19+H19 -> 0 | K19: =J19/4 -> 0 | L19: =IF(AC19>0,((K19-AD19)+(AE19-K20)),IF(K20=0, ,(K19-K20))) -> 0 | M19: =6049*4 -> 24196 | N19: =L19*M19/100 -> 0 | O19: =N19*0.529 -> 0 | P19: =O19*11.79 -> 0 | AC19: =Q19+T19+W19+Z19 -> 0 | AD19: =(R19+U19+X19+AA19)/4 -> 0 | AE19: =(S19+V19+Y19+AB19)/4 -> 0
... A35: 44652 | C35: =IF(AC35>0,((B35-R35)+(S35-B36)),IF(B36=0, ,(B35-B36))) -> 0 | E35: =IF(AC35>0,((D35-U35)+(V35-D36)),IF(D36=0, ,(D35-D36))) -> 0 | G35: =IF(AC35>0,((F35-X35)+(Y35-F36)),IF(F36=0, ,(F35-F36))) -> 0 | I35: =IF(AC35>0,((H35-AA35)+(AB35-H36)),IF(H36=0, ,(H35-H36))) -> 0 | J35: =B35+D35+F35+H35 -> 0 | K35: =J35/4 -> 0 | L35: =IF(AC35>0,((K35-AD35)+(AE35-K36)),IF(K36=0, ,(K35-K36))) -> 0 | M35: =6049*4 -> 24196 | N35: =L35*M35/100 -> 0 | O35: =N35*0.529 -> 0 | P35: =O35*11.79 -> 0 | AC35: =Q35+T35+W35+Z35 -> 0 | AD35: =(R35+U35+X35+AA35)/4 -> 0 | AE35: =(S35+V35+Y35+AB35)/4 -> 0
C36: =IF(AC36>0,((B36-R36)+(S36-B37)),IF(B37=0, ,(B36-B37))) -> 0 | E36: =IF(AC36>0,((D36-U36)+(V36-D37)),IF(D37=0, ,(D36-D37))) -> 0 | G36: =IF(AC36>0,((F36-X36)+(Y36-F37)),IF(F37=0, ,(F36-F37))) -> 0 | I36: =IF(AC36>0,((H36-AA36)+(AB36-H37)),IF(H37=0, ,(H36-H37))) -> 0 | J36: =B36+D36+F36+H36 -> 0 | K36: =J36/4 -> 0 | L36: =IF(AC36>0,((K36-AD36)+(AE36-K37)),IF(K37=0, ,(K36-K37))) -> 0 | M36: =6049*4 -> 24196 | N36: =L36*M36/100 -> 0 | O36: =N36*0.529 -> 0 | P36: =O36*11.79 -> 0 | AC36: =Q36+T36+W36+Z36 -> 0 | AD36: =(R36+U36+X36+AA36)/4 -> 0 | AE36: =(S36+V36+Y36+AB36)/4 -> 0
C37: =IF(AC37>0,((B37-R37)+(S37-B38)),IF(B38=0, ,(B37-B38))) -> 0 | E37: =IF(AC37:AC60>0,((D37-U37)+(V37-D38)),IF(D38=0, ,(D37-D38))) -> 0 | G37: =IF(AC37>0,((F37-X37)+(Y37-F38)),IF(F38=0, ,(F37-F38))) -> 0 | I37: =IF(AC37>0,((H37-AA37)+(AB37-H38)),IF(H38=0, ,(H37-H38))) -> 0 | J37: =B37+D37+F37+H37 -> 0 | K37: =J37/4 -> 0 | L37: =IF(AC37>0,((K37-AD37)+(AE37-K38)),IF(K38=0, ,(K37-K38))) -> 0 | M37: =6049*4 -> 24196 | N37: =L37*M37/100 -> 0 | O37: =N37*0.529 -> 0 | P37: =O37*11.565 -> 0 | AC37: =Q37+T37+W37+Z37 -> 0 | AD37: =(R37+U37+X37+AA37)/4 -> 0 | AE37: =(S37+V37+Y37+AB37)/4 -> 0
C38: =IF(AC38>0,((B38-R38)+(S38-B39)),IF(B39=0, ,(B38-B39))) -> 0 | E38: =IF(AC38:AC61>0,((D38-U38)+(V38-D39)),IF(D39=0, ,(D38-D39))) -> 0 | G38: =IF(AC38>0,((F38-X38)+(Y38-F39)),IF(F39=0, ,(F38-F39))) -> 0 | I38: =IF(AC38>0,((H38-AA38)+(AB38-H39)),IF(H39=0, ,(H38-H39))) -> 0 | J38: =B38+D38+F38+H38 -> 0 | K38: =J38/4 -> 0 | L38: =IF(AC38>0,((K38-AD38)+(AE38-K39)),IF(K39=0, ,(K38-K39))) -> 0 | M38: =6049*4 -> 24196 | N38: =L38*M38/100 -> 0 | O38: =N38*0.53 -> 0 | P38: =O38*11.565 -> 0 | AC38: =Q38+T38+W38+Z38 -> 0 | AD38: =(R38+U38+X38+AA38)/4 -> 0 | AE38: =(S38+V38+Y38+AB38)/4 -> 0
C39: =IF(AC39>0,((B39-R39)+(S39-B40)),IF(B40=0, ,(B39-B40))) -> 0 | E39: =IF(AC39>0,((D39-U39)+(V39-D40)),IF(D40=0, ,(D39-D40))) -> 0 | G39: =IF(AC39>0,((F39-X39)+(Y39-F40)),IF(F40=0, ,(F39-F40))) -> 0 | I39: =IF(AC39>0,((H39-AA39)+(AB39-H40)),IF(H40=0, ,(H39-H40))) -> 0 | J39: =B39+D39+F39+H39 -> 0 | K39: =J39/4 -> 0 | L39: =IF(AC39>0,((K39-AD39)+(AE39-K40)),IF(K40=0, ,(K39-K40))) -> 0 | M39: =6049*4 -> 24196 | N39: =L39*M39/100 -> 0 | O39: =N39*0.53 -> 0 | P39: =O39*11.2513 -> 0 | AC39: =Q39+T39+W39+Z39 -> 0 | AD39: =(R39+U39+X39+AA39)/4 -> 0 | AE39: =(S39+V39+Y39+AB39)/4 -> 0
C40: =IF(AC40>0,((B40-R40)+(S40-B41)),IF(B41=0, ,(B40-B41))) -> 0 | E40: =IF(AC40>0,((D40-U40)+(V40-D41)),IF(D41=0, ,(D40-D41))) -> 0 | G40: =IF(AC40>0,((F40-X40)+(Y40-F41)),IF(F41=0, ,(F40-F41))) -> 0 | I40: =IF(AC40>0,((H40-AA40)+(AB40-H41)),IF(H41=0, ,(H40-H41))) -> 0 | J40: =B40+D40+F40+H40 -> 0 | K40: =J40/4 -> 0 | L40: =IF(AC40>0,((K40-AD40)+(AE40-K41)),IF(K41=0, ,(K40-K41))) -> 0 | M40: =6049*4 -> 24196 | N40: =L40*M40/100 -> 0 | O40: =N40*0.53 -> 0 | P40: =O40*9.965 -> 0 | AC40: =Q40+T40+W40+Z40 -> 0 | AD40: =(R40+U40+X40+AA40)/4 -> 0 | AE40: =(S40+V40+Y40+AB40)/4 -> 0
C41: =IF(AC41>0,((B41-R41)+(S41-B42)),IF(B42=0, ,(B41-B42))) -> 0 | E41: =IF(AC41>0,((D41-U41)+(V41-D42)),IF(D42=0, ,(D41-D42))) -> 0 | G41: =IF(AC41>0,((F41-X41)+(Y41-F42)),IF(F42=0, ,(F41-F42))) -> 0 | I41: =IF(AC41>0,((H41-AA41)+(AB41-H42)),IF(H42=0, ,(H41-H42))) -> 0 | J41: =B41+D41+F41+H41 -> 0 | K41: =J41/4 -> 0 | L41: =IF(AC41>0,((K41-AD41)+(AE41-K42)),IF(K42=0, ,(K41-K42))) -> 0 | M41: =6049*4 -> 24196 | N41: =L41*M41/100 -> 0 | O41: =N41*0.53 -> 0 | P41: =O41*9.965 -> 0 | AC41: =Q41+T41+W41+Z41 -> 0 | AD41: =(R41+U41+X41+AA41)/4 -> 0 | AE41: =(S41+V41+Y41+AB41)/4 -> 0
C42: =IF(AC42>0,((B42-R42)+(S42-B43)),IF(B43=0, ,(B42-B43))) -> 0 | E42: =IF(AC42>0,((D42-U42)+(V42-D43)),IF(D43=0, ,(D42-D43))) -> 0 | G42: =IF(AC42>0,((F42-X42)+(Y42-F43)),IF(F43=0, ,(F42-F43))) -> 0 | I42: =IF(AC42>0,((H42-AA42)+(AB42-H43)),IF(H43=0, ,(H42-H43))) -> 0 | J42: =B42+D42+F42+H42 -> 0 | K42: =J42/4 -> 0 | L42: =IF(AC42>0,((K42-AD42)+(AE42-K43)),IF(K43=0, ,(K42-K43))) -> 0 | M42: =6049*4 -> 24196 | N42: =L42*M42/100 -> 0 | O42: =N42*0.53 -> 0 | P42: =O42*9.965 -> 0 | AC42: =Q42+T42+W42+Z42 -> 0 | AD42: =(R42+U42+X42+AA42)/4 -> 0 | AE42: =(S42+V42+Y42+AB42)/4 -> 0
N43: =SUM(N4:N42) -> 0 | O43: =N43*0.529 -> 0 | P43: =O43*11.79 -> 0 | Q43: =SUM(Q4:Q42) -> 0 | T43: =SUM(T4:T42) -> 0 | W43: =SUM(W4:W42) -> 0 | Z43: =SUM(Z4:Z42) -> 0 | AC43: =Q43+T43+W43+Z43 -> 0
Q44: =Q43+T43+W43+Z43 -> 0 | AC44: =Q44+T44+W44+Z44 -> 0
K46: Litre | L46: Kg | M46: DH
H47: Consommation du mois | K47: =N43 -> 0 | L47: =O43 -> 0 | M47: =P43 -> 0
H48: Livraison du mois | K48: =AC44 -> 0 | L48: =K48*0.529 -> 0 | M48: =L48*11.79 -> 0

Sheet facture électricité
C1: Estimation de la consommation électrique Janvier 2022 | H1: Fiche technique
H3: DT fourseasons CBL
A7: N° de compteur | C7: Ancienne date de lecture | E7: Nouvelle date de lecture | F7: N de jours de consommation | G7: Heures pleines | H7: Heures creuses | I7: Heures de pointe
A8: 95670781 | C8: 44224 | E8: 44620 | F8: 30jours
A11: Type de comptage | C11: Puissance installée KVA | E11: Puissance souscrite KVA | G11: Puissance appelée KVA | I11: Dépassement de la puissance souscrite KVA
A12: 4T | C12: 3750 | E12: 1000 | G12: 815
A16: Eléments de relève | C16: Nouvel Index | D16: Ancien Index | E16: Consommation | F16: Energie révaluée | G16: Consommation Compteur démarquant | I16: Energie à facturer
A17: HEURES PLEINE | C17: 19508376 | D17: 19398677 | E17: =MIN(C17-D17) -> 109699 | F17: =+E17 -> 109699 | I17: =+E17 -> 109699
A18: HEURES CREUSES | C18: 11505965 | D18: 11424147 | E18: =MIN(C18-D18) -> 81818 | F18: =+E18 -> 81818 | I18: =+E18 -> 81818
A19: HEURES DE POINTE | C19: 8571104 | D19: 8517838 | E19: =AVERAGE(C19-D19) -> 53266 | F19: =+E19 -> 53266 | I19: =+E19 -> 53266
A20: TOTAL | E20: =SUM(E17:E19) -> 244783
A23: Détail de la facture | D23: Quantité | E23: Prix unitaire | F23: Montant HT | G23: TVA | I23: Montant TTC
G24: Taux % | H24: Montant
A25: ENERGIE ACTIVE H. PLEINES | D25: =+E17 -> 109699 | E25: 0.9514 | F25: =PRODUCT(D25*E25) -> 104367.63 | G25: 14 | H25: =PRODUCT(0.14,F25) -> 14611.468 | I25: =SUM(H25,F25) -> 118979.1
A26: ENERGIE ACTIVE H. CREUSES | D26: =+E18 -> 81818 | E26: 0.6985 | F26: =PRODUCT(D26*E26) -> 57149.873 | G26: 14 | H26: =PRODUCT(0.14,F26) -> 8000.9822 | I26: =SUM(H26,F26) -> 65150.855
A27: ENETGIE ACTIVE H. DE POINTE | D27: =+E19 -> 53266 | E27: 1.3304 | F27: =PRODUCT(D27*E27) -> 70865.086 | G27: 14 | H27: =PRODUCT(0.14,F27) -> 9921.1121 | I27: =SUM(H27,F27) -> 80786.198
A28: REDEVANCE DE PUISSANCE | D28: 1000 | E28: 43.88167 | F28: =PRODUCT(D28,E28) -> 43881.67 | G28: 14 | H28: =PRODUCT(0.14,F28) -> 6143.4338 | I28: =SUM(H28,F28) -> 50025.104
A29: DEPASSEMENT DE PUISSANCE | D29: 0 | E29: =E28*1.5 -> 65.822505 | F29: =PRODUCT(D29,E29) -> 0 | G29: 14 | H29: =PRODUCT(0.14,F29) -> 0 | I29: =SUM(H29,F29) -> 0
A30: ENTRETIEN COMPTAGE | F30: 841 | G30: 20 | H30: =PRODUCT(F30,0.2) -> 168.2 | I30: =SUM(H30,F30) -> 1009.2
A31: LOCATION COMPTAGE | F31: 1492 | G31: 7 | H31: =PRODUCT(F31,0.07) -> 104.44 | I31: =SUM(H31,F31) -> 1596.44
A32: Total | F32: =SUM(F25:F31) -> 278597.26 | I32: =SUM(I25:J31) -> 317546.89

Sheet Facture journalier D'élect
C1: Estimation de la consommation électrique Jan 2022 | H1: Fiche technique
H3: DT fourseasons CBL
A7: N° de compteur | C7: Ancienne date de lecture | E7: Nouvelle date de lecture | F7: N de jours de consommation | G7: Heures pleines | H7: Heures creuses | I7: Heures de pointe
A8: 95670781 | C8: 44297 | E8: 44327 | F8: 01jours
A11: Type de comptage | C11: Puissance installée KVA | E11: Puissance souscrite KVA | G11: Puissance appelée KVA | I11: Dépassement de la puissance souscrite KVA
A12: 4T | C12: 3750 | E12: 1000 | G12: 712
A16: Eléments de relève | C16: Nouvel Index | D16: Ancien Index | E16: Consommation | F16: Energie révaluée | G16: Consommation Compteur démarquant | I16: Energie à facturer
A17: HEURES PLEINE | C17: 19067297 | D17: 19060410 | E17: =MIN(C17-D17) -> 6887 | F17: =+E17 -> 6887 | I17: =+E17 -> 6887
A18: HEURES CREUSES | C18: 11187556 | D18: 11183757 | E18: =MIN(C18-D18) -> 3799 | F18: =+E18 -> 3799 | I18: =+E18 -> 3799
A19: HEURES DE POINTE | C19: 8363547 | D19: 8360474 | E19: =AVERAGE(C19-D19) -> 3073 | F19: =+E19 -> 3073 | I19: =+E19 -> 3073
A20: TOTAL | E20: =SUM(E17:E19) -> 13759
A23: Détail de la facture | D23: Quantité | E23: Prix unitaire | F23: Montant HT | G23: TVA | I23: Montant TTC
G24: Taux % | H24: Montant
A25: ENERGIE ACTIVE H. PLEINES | D25: =+E17 -> 6887 | E25: 0.9514 | F25: =PRODUCT(D25*E25) -> 6552.2918 | G25: 14 | H25: =PRODUCT(0.14,F25) -> 917.32085 | I25: =SUM(H25,F25) -> 7469.6127
A26: ENERGIE ACTIVE H. CREUSES | D26: =+E18 -> 3799 | E26: 0.6985 | F26: =PRODUCT(D26*E26) -> 2653.6015 | G26: 14 | H26: =PRODUCT(0.14,F26) -> 371.50421 | I26: =SUM(H26,F26) -> 3025.1057
A27: ENETGIE ACTIVE H. DE POINTE | D27: =+E19 -> 3073 | E27: 1.3304 | F27: =PRODUCT(D27*E27) -> 4088.3192 | G27: 14 | H27: =PRODUCT(0.14,F27) -> 572.36469 | I27: =SUM(H27,F27) -> 4660.6839
A28: REDEVANCE DE PUISSANCE | D28: 1000 | E28: 43.88167 | F28: =PRODUCT(D28,E28) -> 43881.67 | G28: 14 | H28: =PRODUCT(0.14,F28) -> 6143.4338 | I28: =SUM(H28,F28) -> 50025.104
A29: DEPASSEMENT DE PUISSANCE | D29: 0 | E29: 48.97249 | F29: =PRODUCT(D29,E29) -> 0 | G29: 14 | H29: =PRODUCT(0.14,F29) -> 0 | I29: =SUM(H29,F29) -> 0
A30: ENTRETIEN COMPTAGE | F30: 841 | G30: 20 | H30: =PRODUCT(F30,0.2) -> 168.2 | I30: =SUM(H30,F30) -> 1009.2
A31: LOCATION COMPTAGE | F31: 1492 | G31: 7 | H31: =PRODUCT(F31,0.07) -> 104.44 | I31: =SUM(H31,F31) -> 1596.44
A32: Total | F32: =SUM(F25:F31) -> 59508.882 | I32: =SUM(I25:J31) -> 67786.146

Sheet facture d'eau
B1: Estimation de la consommation d'Eau Sanitaire JAN 2022 | F1: Fiche technique
F3: DT fourseasons CBL
A7: N° de compteur | B7: Type de relevé | C7: Ancien index | D7: Ancienne date de lecture | E7: Nouvel index | F7: Nouvelle date de lecture | G7: Consommation M3 | H7: N de jours de consommation
B8: RELEVEE | C8: 134294.1 | D8: 44593 | E8: 136510 | F8: 44621 | G8: =E8-C8 -> 2215.9
B10: Quantité | D10: Prix unitaire HT | F10: Montant HT
A11: Redevances Fixes | F11: 23
A12: Consommation eau
A13: Tranche unique | B13: =G8 -> 2215.9 | D13: 8.79 | F13: =PRODUCT(D13,B13) -> 19477.761
A14: Assainissement
A16: Tranche 1 | B16: 0 | D16: 0 | F16: =PRODUCT(D16,B16) -> 0
A17: Tranche 2 | B17: 0 | D17: 0 | F17: =PRODUCT(D17,B17) -> 0
A18: Tranche 3 | B18: 0 | D18: 0 | F18: =PRODUCT(D18,B18) -> 0
A19: Tranche 4 | B19: =G8 -> 2215.9 | D19: 2.61 | F19: =PRODUCT(D19,B19) -> 5783.499
A20: Total HT | F20: =SUM(F11+F13+F16+F17+F18+F19) -> 25284.26
A21: TVA 7% | F21: =PRODUCT(F20,0.07) -> 1769.8982
A22: Timbres Fiscaux | F22: 208.26
A23: Total Taxes | F23: =SUM(F21:H22) -> 1978.1582
A24: Net à payer | F24: =SUM(F20,F23) -> 27262.418

Sheet Facture journalier d'eau
B1: Estimation de la consommation d'Eau Sanitaire JAN 2022 | F1: Fiche technique
F3: DT fourseasons CBL
A7: N° de compteur | B7: Type de relevé | C7: Ancien index | D7: Ancienne date de lecture | E7: Nouvel index | F7: Nouvelle date de lecture | G7: Consommation M3 | H7: N de jours de consommation
B8: RELEVEE | C8: 127985.9 | D8: 44504 | E8: 128105.7 | F8: 44505 | G8: =E8-C8 -> 119.8
B10: Quantité | D10: Prix unitaire HT | F10: Montant HT
A11: Redevances Fixes | F11: 23
A12: Consommation eau
A13: Tranche unique | B13: =G8 -> 119.8 | D13: 8.5 | F13: =PRODUCT(D13,B13) -> 1018.3
A14: Assainissement
A16: Tranche 1 | B16: 0 | D16: 0 | F16: =PRODUCT(D16,B16) -> 0
A17: Tranche 2 | B17: 0 | D17: 0 | F17: =PRODUCT(D17,B17) -> 0
A18: Tranche 3 | B18: 0 | D18: 0 | F18: =PRODUCT(D18,B18) -> 0
A19: Tranche 4 | B19: 0 | D19: 0 | F19: 0
A20: Tranche 5 | B20: =G8 -> 119.8 | D20: 2.54 | F20: =PRODUCT(D20,B20) -> 304.292
A21: Total HT | F21: =SUM(F11+F13+F16+F17+F18+F20) -> 1345.592
A22: TVA 7% | F22: =PRODUCT(F21,0.07) -> 94.19144
A23: Timbres Fiscaux | F23: 208.26
A24: Total Taxes | F24: =SUM(F22:H23) -> 302.45144
A25: Net à payer | F25: =SUM(F21,F24) -> 1648.0434

Sheet facture incendie
B1: Estimation de la consommation d'Eau incendie JAN 2022 | F1: Fiche technique
F3: DT fourseasons CBL
A7: N° de compteur | B7: Type de relevé | C7: Ancien index | D7: Ancienne date de lecture | E7: Nouvel index | F7: Nouvelle date de lecture | G7: Consommation M3 | H7: N de jours de consommation
B8: RELEVEE | C8: 2560 | D8: 44228 | E8: 2560 | F8: 44621 | G8: =E8-C8 -> 0
B10: Quantité | D10: Prix unitaire HT | F10: Montant HT
A11: Redevances Fixes | F11: 15
A12: Consommation eau
A13: Tranche unique 1 | B13: =G8 -> 0 | D13: 16.48 | F13: =PRODUCT(D13,B13) -> 0
A14: Tranche unique 2
A15: Tranche unique 3
A16: Tranche unique 4
A17: Tranche unique 5
A18: Assainissement
A20: Tranche 1 | B20: 0 | D20: 0 | F20: =PRODUCT(D20,B20) -> 0
A21: Tranche 2 | B21: 0 | D21: 0 | F21: =PRODUCT(D21,B21) -> 0
A22: Tranche 3 | B22: 0 | D22: 0 | F22: =PRODUCT(D22,B22) -> 0
A23: Tranche 4 | B23: =G8 -> 0 | D23: 0 | F23: =PRODUCT(D23,B23) -> 0
A24: Tranche 5 | B24: 0 | D24: 2.54 | F24: =B24*D24 -> 0
A25: Total HT | F25: =SUM(F11+F13+F20+F21+F22+F23) -> 15
A26: TVA 7% | F26: 63.63
A27: Timbres Fiscaux | F27: 2.43
A28: Total Taxes | F28: =SUM(F26:H27) -> 66.06
A29: Net à payer | F29: =SUM(F25,F28) -> 81.06

Sheet cons annuel électr
C5: électricité en KW
C7: Janvier | D7: Février | E7: Mars | F7: avril | G7: Mai | H7: juin | I7: Juillet | J7: aout | K7: Septembre | L7: Octobre | M7: Novembre | N7: Décembre
B8: Année 2015 | L8: 544520 | M8: 561765 | N8: 546771
B9: Année 2016 | C9: 564170 | D9: 532072 | E9: 405239 | F9: 469130 | G9: 543877 | H9: 605744 | I9: 722083 | J9: 802210 | K9: 762933 | L9: 670848 | M9: 626451 | N9: 557392
B10: Année 2017 | C10: 520977 | D10: 541271 | E10: 508392 | F10: 659200 | G10: 705703 | H10: 784214 | I10: 823726 | J10: 913736 | K10: 831734 | L10: 794243 | M10: 688127 | N10: 577067
B11: Année 2018 | C11: 586355 | D11: 563735 | E11: 512313 | F11: 573440 | G11: 535115 | H11: 570139 | I11: 669302 | J11: 704714 | K11: 682717 | L11: 581239 | M11: 438561 | N11: 400672
B12: Année 2019 | C12: 388363 | D12: 407737 | E12: 392102 | F12: 454554 | G12: 448580 | H12: 535391 | I12: 549301 | J12: 576078 | K12: 612675 | L12: 542640 | M12: 507495 | N12: 444826
B13: Année 2020 | C13: 417018 | D13: 434912 | E13: 278008 | F13: 90895 | G13: 70143 | H13: 76577 | I13: 238549 | J13: 371235 | K13: 295161 | L13: 318184 | M13: 297355 | N13: 260661
B14: Année 2021 | C14: 239911 | D14: 247692 | E14: 242350 | F14: 282564 | G14: 272836 | H14: 362809 | I14: 454598 | J14: 470109 | K14: 458455 | L14: 444199 | M14: 374528 | N14: 256419
B15: Année 2022 | C15: 206479 | D15: 244783
C16: électricité en DH HT
C18: Janvier | D18: Février | E18: Mars | F18: avril | G18: Mai | H18: juin | I18: Juillet | J18: aout | K18: Septembre | L18: Octobre | M18: Novembre | N18: Décembre
B19: Année 2015 | L19: 527344.76 | M19: 542887.95 | N19: 530789.1
B20: Année 2016 | C20: 577599.26 | D20: 549500.3 | E20: 437038.73 | F20: 498381.29 | G20: 567710.59 | H20: 626665.41 | I20: 732996.54 | J20: 807380.12 | K20: 765103.7 | L20: 674808.61 | M20: 636029.23 | N20: 575999.91
B21: Année 2017 | C21: 565777.06 | D21: 589465.87 | E21: 559348.97 | F21: 706566.83 | G21: 750048.77 | H21: 823657.04 | I21: 863911.21 | J21: 948371.74 | K21: 870086.49 | L21: 828237.33 | M21: 728226.36 | N21: 620794.43
B22: Année 2018 | C22: 629018.45 | D22: 609232.05 | E22: 564099.54 | F22: 625412.74 | G22: 591310.65 | H22: 627578.14 | I22: 723790.51 | J22: 756208.25 | K22: 734211.55 | L22: 634725.02 | M22: 492313.54 | N22: 430486.08
B23: Année 2019 | C23: 417767.5 | D23: 437511.45 | E23: 422948.91 | F23: 483026.43 | G23: 494466.66 | H23: 589026.66 | I23: 597445.77 | J23: 624719.21 | K23: 662255.27 | L23: 572138.69 | M23: 536725.71 | N23: 473017.45
B24: Année 2020 | C24: 445089.46 | D24: 464838.33 | E24: 310234.48 | F24: 132086.12 | G24: 81934.238 | H24: 88016.123 | I24: 290744.44 | J24: 372885.54 | K24: 328998.33 | L24: 350713.84 | M24: 329624.09 | N24: 294931.2
B25: Année 2021 | C25: 274561.56 | D25: 283692.47 | E25: 278888.13 | F25: 318224.92 | G25: 309500.68 | H25: 396582.06 | I25: 498105.11 | J25: 506423.32 | K25: 486424.27 | L25: 473503.95 | M25: 403992.35 | N25: 289205.49
B26: Année 2022 | C26: 240995.18 | D26: 278597.26

Sheet cons annuel EAU  
C5: L'eau en M3
C7: Janvier | D7: Février | E7: Mars | F7: avril | G7: Mai | H7: juin | I7: Juillet | J7: aout | K7: Septembre | L7: Octobre | M7: Novembre | N7: Décembre
B8: Année 2015 | M8: 3298 | N8: 3866
B9: Année 2016 | C9: 4094 | D9: 3691 | E9: 3917 | F9: 4785 | G9: 5213 | H9: 4103 | I9: 5622 | J9: 6568 | K9: 4813 | L9: 6088 | M9: 4819 | N9: 5252
B10: Année 2017 | C10: 5132 | D10: 4589 | E10: 6190 | F10: 6170 | G10: 5980 | H10: 6097.8 | I10: 7050 | J10: 8050 | K10: 6678 | L10: 6859 | M10: 5960 | N10: 5210.1
B11: Année 2018 | C11: 5598.9 | D11: 5297 | E11: 5857 | F11: 6284 | G11: 5500 | H11: 5583.8 | I11: 6266.9 | J11: 6178.3 | K11: 6144.5 | L11: 6117.5 | M11: 5023 | N11: 4767.8
B12: Année 2019 | C12: 5044.8 | D12: 5061 | E12: 5504 | F12: 5372.3 | G12: 4507.3 | H12: 5269.2 | I12: 5509.2 | J12: 5601 | K12: 5387 | L12: 6051 | M12: 5532 | N12: 5565.2
B13: Année 2020 | C13: 5763.4 | D13: 5632.4 | E13: 3058.7 | F13: 714.5 | G13: 439.8 | H13: 1383.4 | I13: 3491.8 | J13: 2618.7 | K13: 1829.7 | L13: 3000 | M13: 1896 | N13: 1780.6
B14: Année 2021 | C14: 2083.2 | D14: 2115.3 | E14: 2406.3 | F14: 2166.2 | G14: 2527.2 | H14: 2925.2 | I14: 3819.3 | J14: 3510.1 | K14: 3086.2 | L14: 3330.5 | M14: 2932.2 | N14: 2091.1
B15: Année 2022 | C15: 1595.1 | D15: 2215.9
C16: L'eau en DH HT
C18: Janvier | D18: Février | E18: Mars | F18: avril | G18: Mai | H18: juin | I18: Juillet | J18: aout | K18: Septembre | L18: Octobre | M18: Novembre | N18: Décembre
B19: Année 2015 | M19: 43165.84 | N19: 50595.28
B20: Année 2016 | C20: 53565.52 | D20: 48294.28 | E20: 51250.36 | F20: 62603.8 | G20: 68202.04 | H20: 53683.24 | I20: 73551.76 | J20: 85925.44 | K20: 57158.52 | L20: 67234.52 | M20: 53224.76 | N20: 58005.08
B21: Année 2017 | C21: 56680.28 | D21: 50685.56 | E21: 68360.6 | F21: 68139.8 | G21: 66042.2 | H21: 67342.712 | I21: 77855 | J21: 88895 | K21: 73748.12 | L21: 75746.36 | M21: 65821.4 | N21: 57542.504
B22: Année 2018 | C22: 61834.856 | D22: 58501.88 | E22: 64684.28 | F22: 69398.36 | G22: 60743 | H22: 61668.152 | I22: 69209.576 | J22: 68231.432 | K22: 67858.28 | L22: 67560.2 | M22: 55476.92 | N22: 52659.512
B23: Année 2019 | C23: 55717.592 | D23: 57718.4 | E23: 62768.6 | F23: 61267.22 | G23: 51406.22 | H23: 60091.88 | I23: 62827.88 | J23: 63874.4 | K23: 61434.8 | L23: 69004.4 | M23: 63087.8 | N23: 63466.28
B24: Année 2020 | C24: 65725.76 | D24: 64232.36 | E24: 34892.18 | F24: 8168.3 | G24: 5036.72 | H24: 15793.76 | I24: 39829.52 | J24: 29876.18 | K24: 20881.58 | L24: 34223 | M24: 21637.4 | N24: 20321.84
B25: Année 2021 | C25: 23771.48 | D25: 24137.42 | E25: 27454.82 | F25: 24717.68 | G25: 28833.08 | H25: 33370.28 | I25: 43563.02 | J25: 40038.14 | K25: 35205.68 | L25: 37990.7 | M25: 33450.08 | N25: 23861.54
B26: Année 2022 | C26: 18207.14 | D26: 25284.26

Sheet livraison annuel GAZ
C5: Gaz en KG
C7: Janvier | D7: Février | E7: Mars | F7: avril | G7: Mai | H7: juin | I7: Juillet | J7: aout | K7: Septembre | L7: Octobre | M7: Novembre | N7: Décembre
B8: Année 2015 | L8: 19365 | M8: 21235 | N8: 34053
B9: Année 2016 | C9: 23598 | D9: 28302 | E9: 23000 | F9: 28601 | G9: 24612 | H9: 16695 | I9: 10756 | J9: 14749 | K9: 18297 | L9: 20801 | M9: 22927 | N9: 38265
B10: Année 2017 | C10: 39843 | D10: 27644 | E10: 31207 | F10: 34231 | G10: 21149.42 | H10: 19502 | I10: 22293 | J10: 21244 | K10: 20201 | L10: 21000 | M10: 30135 | N10: 28841
B11: Année 2018 | C11: 33210.62 | D11: 27328.669 | E11: 22296.292 | F11: 18205.006 | G11: 16641.811 | H11: 17087.758 | I11: 13220.239 | J11: 15457.909 | K11: 10651.944 | L11: 13951.846 | M11: 24676.263 | N11: 21781.575
B12: Année 2019 | C12: 26669.535 | D12: 26601.294 | E12: 23114.126 | F12: 20873.811 | G12: 14596.168 | H12: 10659.35 | I12: 18584.299 | J12: 10559.898 | K12: 8546.524 | L12: 17517.306 | M12: 20452.198 | N12: 27341.365
B13: Année 2020 | C13: 30735.958 | D13: 21724.443 | E13: 11128.573 | F13: 4506.022 | G13: 0 | H13: 2998.372 | I13: 8663.559 | J13: 4731.905 | K13: 4832.415 | L13: 13092.221 | M13: 17284.017 | N13: 16432.856
B14: Année 2021 | C14: 16222.314 | D14: 13578.901 | E14: 18500.717 | F14: 11555.476 | G14: 10801.651 | H14: 13800.552 | I14: 9448.469 | J14: 8828.481 | K14: 11498.344 | L14: 11280.396 | M14: 20677.552 | N14: 12106.165
B15: Année 2022 | C15: 8859.163 | D15: 13938.621
C16: GAZ en DH HT
C18: Janvier | D18: Février | E18: Mars | F18: avril | G18: Mai | H18: juin | I18: Juillet | J18: aout | K18: Septembre | L18: Octobre | M18: Novembre | N18: Décembre
B19: Année 2015 | L19: 222503.85 | M19: 248385.8 | N19: 412790.47
B20: Année 2016 | C20: 281335.36 | D20: 329491.88 | E20: 263166 | F20: 334402.89 | G20: 287763.5 | H20: 200206.44 | I20: 128985.95 | J20: 174687.16 | K20: 221708.41 | L20: 257125.33 | M20: 290283.33 | N20: 491751.17
B21: Année 2017 | C21: 534222.91 | D21: 397841.39 | E21: 463317.85 | F21: 473982.96 | G21: 288617.67 | H21: 262138.08 | I21: 290959.32 | J21: 277268.19 | K21: 269109.64 | L21: 279753.6 | M21: 411233.26 | N21: 393575.46
B22: Année 2018 | C22: 433913.36 | D22: 365261.33 | E22: 291312.2 | F22: 213834.18 | G22: 197886.11 | H22: 143537.17 | I22: 111050.01 | J22: 129846.44 | K22: 97997.885 | L22: 117195.51 | M22: 207280.61 | N22: 182965.23
B23: Année 2019 | C23: 224024.09 | D23: 223450.87 | E23: 209182.84 | F23: 188907.99 | G23: 129176.09 | H23: 94335.247 | I23: 144957.53 | J23: 77405.108 | K23: 62646.876 | L23: 128403.6 | M23: 149916.66 | N23: 217831.39
B24: Année 2020 | C24: 244876.45 | D24: 193260.64 | E24: 87871.212 | F24: 35579.55 | G24: 0 | H24: 23675.145 | I24: 72782.559 | J24: 40462.52 | K24: 41321.981 | L24: 111951.58 | M24: 151252.43 | N24: 147090.49
B25: Année 2021 | C25: 175249.66 | D25: 133357.03 | E25: 160956.24 | F25: 100532.64 | G25: 93974.364 | H25: 120064.8 | I25: 79461.624 | J25: 84841.702 | K25: 114581 | L25: 126919.12 | M25: 216928.2 | N25: 127005.78
B26: Année 2022 | C26: 102456.22 | D26: 164336.34

Sheet Feuil1
