Workbook

Sheet Total
A1: Site Name | B1: Day | C1: Month | D1: Year | E1: Total Electricity Kwh | F1: Electricity Tariff ($/Kwh) | G1: Total Fuel Oil (Liter) | H1: Fuel Oil $/Liter | I1: LPG (Kg) | J1: LPG $/Kg | K1: Water Utility Supply (m3) m3 | L1: Water Utility Supply (m3) $/m3 | M1: Irrigation Water (m3) m3 | N1: Irrigation water $/m3 | O1: Room Nights
A2: Beirut | B2: 1 | C2: 5 | D2: 2022 | E2: =ELEC!N4 -> 0 | F2: =SUM('EDl log'!T4) -> 0 | G2: =-tanks!AW6 -> 0 | H2: =tanks!AV6 -> 1.05 | I2: =('B5'!AU5)*0.51 -> 0 | J2: ='B5'!AX5/0.51 -> 1.5686275 | K2: =WATER!I6 -> 0 | L2: =SUM(WATER!J6) -> 0 | M2: =WATER!Q6 -> 0 | N2: 0.6 | O2: =ELEC!B4 -> 0
A3: Beirut | B3: =B2+1 -> 2 | C3: 5 | D3: =D2 -> 2022 | E3: =ELEC!N5 -> 0 | F3: =SUM('EDl log'!T5) -> 0 | G3: =-tanks!AW7 -> 0 | H3: =tanks!AV7 -> 1.05 | I3: =('B5'!AU6)*0.51 -> 0 | J3: ='B5'!AX6/0.51 -> 1.5686275 | K3: =WATER!I7 -> 0 | L3: =SUM(WATER!J7) -> 0 | M3: =WATER!Q7 -> 0 | N3: 0.6 | O3: =ELEC!B5 -> 0
A4: Beirut | B4: =B3+1 -> 3 | C4: 5 | D4: =D3 -> 2022 | E4: =ELEC!N6 -> 6202 | F4: =SUM('EDl log'!T6) -> 0.44501661 | G4: =-tanks!AW8 -> 289 | H4: =tanks!AV8 -> 1.05 | I4: =('B5'!AU7)*0.51 -> 0 | J4: ='B5'!AX7/0.51 -> 1.5686275 | K4: =WATER!I8 -> 0 | L4: =SUM(WATER!J8) -> 0 | M4: =WATER!Q8 -> 0 | N4: 0.6 | O4: =ELEC!B6 -> 0
A5: Beirut | B5: =B4+1 -> 4 | C5: 5 | D5: =D4 -> 2022 | E5: =ELEC!N7 -> 4288 | F5: =SUM('EDl log'!T7) -> 0.43226632 | G5: =-tanks!AW9 -> 305 | H5: =tanks!AV9 -> 1.05 | I5: =('B5'!AU8)*0.51 -> 0 | J5: ='B5'!AX8/0.51 -> 1.5686275 | K5: =WATER!I9 -> 0 | L5: =SUM(WATER!J9) -> 0 | M5: =WATER!Q9 -> 0 | N5: 0.6 | O5: =ELEC!B7 -> 0
A6: Beirut | B6: =B5+1 -> 5 | C6: 5 | D6: =D5 -> 2022 | E6: =ELEC!N8 -> 3111 | F6: =SUM('EDl log'!T8) -> 0.35528706 | G6: =-tanks!AW10 -> 44 | H6: =tanks!AV10 -> 1.05 | I6: =('B5'!AU9)*0.51 -> 0 | J6: ='B5'!AX9/0.51 -> 1.5686275 | K6: =WATER!I10 -> 103 | L6: =SUM(WATER!J10) -> 2.3488882 | M6: =WATER!Q10 -> 0 | N6: 0.6 | O6: =ELEC!B8 -> 0
A7: Beirut | B7: =B6+1 -> 6 | C7: 5 | D7: =D6 -> 2022 | E7: =ELEC!N9 -> 0 | F7: =SUM('EDl log'!T9) -> 0 | G7: =-tanks!AW11 -> 0 | H7: =tanks!AV11 -> 1.05 | I7: =('B5'!AU10)*0.51 -> 0 | J7: ='B5'!AX10/0.51 -> 1.5686275 | K7: =WATER!I11 -> 0 | L7: =SUM(WATER!J11) -> 0 | M7: =WATER!Q11 -> 0 | N7: 0.6 | O7: =ELEC!B9 -> 0
A8: Beirut | B8: =B7+1 -> 7 | C8: 5 | D8: =D7 -> 2022 | E8: =ELEC!N10 -> 0 | F8: =SUM('EDl log'!T10) -> 0 | G8: =-tanks!AW12 -> 0 | H8: =tanks!AV12 -> 1.05 | I8: =('B5'!AU11)*0.51 -> 0 | J8: ='B5'!AX11/0.51 -> 1.5686275 | K8: =WATER!I12 -> 0 | L8: =SUM(WATER!J12) -> 0 | M8: =WATER!Q12 -> 0 | N8: 0.6 | O8: =ELEC!B10 -> 0
A9: Beirut | B9: =B8+1 -> 8 | C9: 5 | D9: =D8 -> 2022 | E9: =ELEC!N11 -> 3135 | F9: =SUM('EDl log'!T11) -> -0.15376004 | G9: =-tanks!AW13 -> 259 | H9: =tanks!AV13 -> 1.085 | I9: =('B5'!AU12)*0.51 -> 0 | J9: ='B5'!AX12/0.51 -> 1.5686275 | K9: =WATER!I13 -> 0 | L9: =SUM(WATER!J13) -> 0 | M9: =WATER!Q13 -> 0 | N9: 0.6 | O9: =ELEC!B11 -> 0
A10: Beirut | B10: =B9+1 -> 9 | C10: 5 | D10: =D9 -> 2022 | E10: =ELEC!N12 -> 3445 | F10: =SUM('EDl log'!T12) -> 0.40530902 | G10: =-tanks!AW14 -> 101 | H10: =tanks!AV14 -> 1.085 | I10: =('B5'!AU13)*0.51 -> 0 | J10: ='B5'!AX13/0.51 -> 1.5686275 | K10: =WATER!I14 -> 0 | L10: =SUM(WATER!J14) -> 0 | M10: =WATER!Q14 -> 0 | N10: 0.6 | O10: =ELEC!B12 -> 0
A11: Beirut | B11: =B10+1 -> 10 | C11: 5 | D11: =D10 -> 2022 | E11: =ELEC!N13 -> 3157 | F11: =SUM('EDl log'!T13) -> 0.35063058 | G11: =-tanks!AW15 -> 45 | H11: =tanks!AV15 -> 1.085 | I11: =('B5'!AU14)*0.51 -> 0 | J11: ='B5'!AX14/0.51 -> 1.5686275 | K11: =WATER!I15 -> 127 | L11: =SUM(WATER!J15) -> 1.9050038 | M11: =WATER!Q15 -> 0 | N11: 0.6 | O11: =ELEC!B13 -> 0
A12: Beirut | B12: =B11+1 -> 11 | C12: 5 | D12: =D11 -> 2022 | E12: =ELEC!N14 -> 3105 | F12: =SUM('EDl log'!T14) -> 0.41807998 | G12: =-tanks!AW16 -> 192 | H12: =tanks!AV16 -> 1.085 | I12: =('B5'!AU15)*0.51 -> 0 | J12: ='B5'!AX15/0.51 -> 1.5686275 | K12: =WATER!I16 -> 68 | L12: =SUM(WATER!J16) -> 3.5578748 | M12: =WATER!Q16 -> 0 | N12: 0.6 | O12: =ELEC!B14 -> 0
A13: Beirut | B13: =B12+1 -> 12 | C13: 5 | D13: =D12 -> 2022 | E13: =ELEC!N15 -> 2743 | F13: =SUM('EDl log'!T15) -> 0.4910921 | G13: =-tanks!AW17 -> 131 | H13: =tanks!AV17 -> 1.085 | I13: =('B5'!AU16)*0.51 -> 0 | J13: ='B5'!AX16/0.51 -> 1.5686275 | K13: =WATER!I17 -> 0 | L13: =SUM(WATER!J17) -> 0 | M13: =WATER!Q17 -> 0 | N13: 0.6 | O13: =ELEC!B15 -> 0
A14: Beirut | B14: =B13+1 -> 13 | C14: 5 | D14: =D13 -> 2022 | E14: =ELEC!N16 -> 0 | F14: =SUM('EDl log'!T16) -> 0 | G14: =-tanks!AW18 -> 0 | H14: =tanks!AV18 -> 1.085 | I14: =('B5'!AU17)*0.51 -> 0 | J14: ='B5'!AX17/0.51 -> 1.5686275 | K14: =WATER!I18 -> 0 | L14: =SUM(WATER!J18) -> 0 | M14: =WATER!Q18 -> 0 | N14: 0.6 | O14: =ELEC!B16 -> 0
... A32: Beirut | B32: =B31+1 -> 31 | C32: 5 | D32: =D31 -> 2022 | E32: =ELEC!N34 -> 0 | F32: =SUM('EDl log'!T34) -> 0 | G32: =-tanks!AW36 -> 0 | H32: =tanks!AV36 -> 1.085 | I32: =('B5'!AU35)*0.51 -> 0 | J32: ='B5'!AX35/0.51 -> 1.5686275 | K32: =WATER!I36 -> 0 | L32: =SUM(WATER!J36) -> 0 | M32: =WATER!Q36 -> 0 | N32: 0.6 | O32: =ELEC!B34 -> 0

Sheet Submetering
A1: Site Name | B1: Day | C1: Month | D1: Year | E1: ATS1 Kwh | F1: ATS2 Kwh | G1: ATS3 Kwh | H1: ATS4 Kwh | I1: ATS5 Kwh | J1: Guest (m3) | K1: Kitchen & Laundry (m3) | L1: Room Nights
A2: Beirut | B2: 1 | C2: 5 | D2: 2022 | E2: =ELEC!M4 -> 0 | F2: =ELEC!K4 -> 0 | G2: =ELEC!I4 -> 0 | H2: =ELEC!E4 -> 0 | I2: =ELEC!G4 -> 0 | J2: =WATER!Y6 -> 0 | K2: =WATER!AJ6 -> 0 | L2: =ELEC!B4 -> 0
A3: Beirut | B3: =B2+1 -> 2 | C3: 5 | D3: 2022 | E3: =ELEC!M5 -> 0 | F3: =ELEC!K5 -> 0 | G3: =ELEC!I5 -> 0 | H3: =ELEC!E5 -> 0 | I3: =ELEC!G5 -> 0 | J3: =WATER!Y7 -> 0 | K3: =WATER!AJ7 -> 0 | L3: =ELEC!B5 -> 0
A4: Beirut | B4: =B3+1 -> 3 | C4: 5 | D4: 2022 | E4: =ELEC!M6 -> 1162 | F4: =ELEC!K6 -> 2202 | G4: =ELEC!I6 -> 552 | H4: =ELEC!E6 -> 1900 | I4: =ELEC!G6 -> 386 | J4: =WATER!Y8 -> 0 | K4: =WATER!AJ8 -> 0 | L4: =ELEC!B6 -> 0
A5: Beirut | B5: =B4+1 -> 4 | C5: 5 | D5: 2022 | E5: =ELEC!M7 -> 980 | F5: =ELEC!K7 -> 1324 | G5: =ELEC!I7 -> 448 | H5: =ELEC!E7 -> 1240 | I5: =ELEC!G7 -> 296 | J5: =WATER!Y9 -> 0 | K5: =WATER!AJ9 -> 0 | L5: =ELEC!B7 -> 0
A6: Beirut | B6: =B5+1 -> 5 | C6: 5 | D6: 2022 | E6: =ELEC!M8 -> 880 | F6: =ELEC!K8 -> 742 | G6: =ELEC!I8 -> 428 | H6: =ELEC!E8 -> 780 | I6: =ELEC!G8 -> 281 | J6: =WATER!Y10 -> 0 | K6: =WATER!AJ10 -> 0 | L6: =ELEC!B8 -> 0
A7: Beirut | B7: =B6+1 -> 6 | C7: 5 | D7: 2022 | E7: =ELEC!M9 -> 0 | F7: =ELEC!K9 -> 0 | G7: =ELEC!I9 -> 0 | H7: =ELEC!E9 -> 0 | I7: =ELEC!G9 -> 0 | J7: =WATER!Y11 -> 0 | K7: =WATER!AJ11 -> 0 | L7: =ELEC!B9 -> 0
A8: Beirut | B8: =B7+1 -> 7 | C8: 5 | D8: 2022 | E8: =ELEC!M10 -> 0 | F8: =ELEC!K10 -> 0 | G8: =ELEC!I10 -> 0 | H8: =ELEC!E10 -> 0 | I8: =ELEC!G10 -> 0 | J8: =WATER!Y12 -> 0 | K8: =WATER!AJ12 -> 0 | L8: =ELEC!B10 -> 0
A9: Beirut | B9: =B8+1 -> 8 | C9: 5 | D9: 2022 | E9: =ELEC!M11 -> 780 | F9: =ELEC!K11 -> 624 | G9: =ELEC!I11 -> 364 | H9: =ELEC!E11 -> 1110 | I9: =ELEC!G11 -> 257 | J9: =WATER!Y13 -> 0 | K9: =WATER!AJ13 -> 0 | L9: =ELEC!B11 -> 0
A10: Beirut | B10: =B9+1 -> 9 | C10: 5 | D10: 2022 | E10: =ELEC!M12 -> 1016 | F10: =ELEC!K12 -> 712 | G10: =ELEC!I12 -> 530 | H10: =ELEC!E12 -> 840 | I10: =ELEC!G12 -> 347 | J10: =WATER!Y14 -> 89 | K10: =WATER!AJ14 -> 27 | L10: =ELEC!B12 -> 0
A11: Beirut | B11: =B10+1 -> 10 | C11: 5 | D11: 2022 | E11: =ELEC!M13 -> 976 | F11: =ELEC!K13 -> 620 | G11: =ELEC!I13 -> 486 | H11: =ELEC!E13 -> 770 | I11: =ELEC!G13 -> 305 | J11: =WATER!Y15 -> 0 | K11: =WATER!AJ15 -> 0 | L11: =ELEC!B13 -> 0
A12: Beirut | B12: =B11+1 -> 11 | C12: 5 | D12: 2022 | E12: =ELEC!M14 -> 908 | F12: =ELEC!K14 -> 638 | G12: =ELEC!I14 -> 488 | H12: =ELEC!E14 -> 770 | I12: =ELEC!G14 -> 301 | J12: =WATER!Y16 -> 0 | K12: =WATER!AJ16 -> 0 | L12: =ELEC!B14 -> 0
A13: Beirut | B13: =B12+1 -> 12 | C13: 5 | D13: 2022 | E13: =ELEC!M15 -> 766 | F13: =ELEC!K15 -> 564 | G13: =ELEC!I15 -> 436 | H13: =ELEC!E15 -> 690 | I13: =ELEC!G15 -> 287 | J13: =WATER!Y17 -> 0 | K13: =WATER!AJ17 -> 0 | L13: =ELEC!B15 -> 0
A14: Beirut | B14: =B13+1 -> 13 | C14: 5 | D14: 2022 | E14: =ELEC!M16 -> 0 | F14: =ELEC!K16 -> 0 | G14: =ELEC!I16 -> 0 | H14: =ELEC!E16 -> 0 | I14: =ELEC!G16 -> 0 | J14: =WATER!Y18 -> 0 | K14: =WATER!AJ18 -> 0 | L14: =ELEC!B16 -> 0
... A32: Beirut | B32: =B31+1 -> 31 | C32: 5 | D32: 2022 | E32: =ELEC!M34 -> 0 | F32: =ELEC!K34 -> 0 | G32: =ELEC!I34 -> 0 | H32: =ELEC!E34 -> 0 | I32: =ELEC!G34 -> 0 | J32: =WATER!Y36 -> 0 | K32: =WATER!AJ36 -> 0 | L32: =ELEC!B34 -> 0
D45: .

Sheet ELEC
A2: OOC | B2: Room OCC | D2: MDB3 | E2: MDB3/day | F2: EMDB2 | G2: EMDB2/day | H2: EMDB1 | I2: EMDB1/day | J2: MDB2 | K2: mdb2/day | L2: MDB1 | M2: MDB1/Day | N2: Total KWH | O2: KWH/Rooc | P2: Gen MHW | Q2: Gen/Day KWH | R2: EDL KWH | S2: CH1 RH | T2: RH | U2: C1h1 power | V2: CH1 Con KWH | W2: CH2 RH | X2: RH | Y2: Ch2 power | Z2: CH2 Con KWH | AA2: CH3 RH | AB2: RH | AC2: Ch3 power | AD2: CH3 Con KWH | AE2: RH total | AF2: KWH total | AG2: AVG chiller KW/Hr
A3: =[1]ELEC!$A$34 -> 0 | B3: =[1]ELEC!$B$34 -> 0 | C3: =[2]ELEC!$C$33 -> 44681 | D3: =[2]ELEC!D33 -> 286340 | E3: =[2]ELEC!E33 -> 0 | F3: =[2]ELEC!F33 -> 4130656 | G3: =[2]ELEC!G33 -> 0 | H3: =[2]ELEC!H33 -> 18038570 | I3: =[2]ELEC!I33 -> 0 | J3: =[2]ELEC!J33 -> 29783774 | K3: =[2]ELEC!K33 -> 0 | ... AG3: =[2]ELEC!AG33 -> 0
A4: ='General information '!F5 -> 0 | B4: =SUM(230*A4) -> 0 | C4: 44682 | D4: =D3 -> 286340 | E4: =D4-D3 -> 0 | F4: =F3 -> 4130656 | G4: =F4-F3 -> 0 | H4: =H3 -> 18038570 | I4: =H4-H3 -> 0 | J4: =J3 -> 29783774 | K4: =J4-J3 -> 0 | L4: =L3 -> 24577264 | M4: =L4-L3 -> 0 | N4: =M4+K4+I4+G4+E4 -> 0 | O4: =IF(B4>0,N4/B4,0) -> 0 | P4: =P3 -> 19199.525 | Q4: =(P4-P3)*1000 -> 0 | R4: =+N4-Q4 -> 0 | S4: =S3 -> 10175 | T4: =S4-S3 -> 0 | U4: =U3 -> 429166 | V4: =U4-U3 -> 0 | W4: =W3 -> 33484 | X4: =W4-W3 -> 0 | Y4: =Y3 -> 996900 | Z4: =Y4-Y3 -> 0 | AA4: =AA3 -> 36796 | AB4: =AA4-AA3 -> 0 | AC4: =AC3 -> 1170505 | AD4: =AC4-AC3 -> 0 | AE4: =AB4+X4+T4 -> 0 | AF4: =V4+Z4+AD4 -> 0 | AG4: =IF(AE4>0,AF4/AE4,0) -> 0
A5: ='General information '!F6 -> 0 | B5: =SUM(230*A5) -> 0 | C5: 44683 | D5: =D4 -> 286340 | E5: =D5-D4 -> 0 | F5: =F4 -> 4130656 | G5: =F5-F4 -> 0 | H5: =H4 -> 18038570 | I5: =H5-H4 -> 0 | J5: =J4 -> 29783774 | K5: =J5-J4 -> 0 | L5: =L4 -> 24577264 | M5: =L5-L4 -> 0 | N5: =M5+K5+I5+G5+E5 -> 0 | O5: =IF(B5>0,N5/B5,0) -> 0 | P5: =P4 -> 19199.525 | Q5: =(P5-P4)*1000 -> 0 | R5: =N5-Q5 -> 0 | S5: =S4 -> 10175 | T5: =S5-S4 -> 0 | U5: =U4 -> 429166 | V5: =U5-U4 -> 0 | W5: =W4 -> 33484 | X5: =W5-W4 -> 0 | Y5: =Y4 -> 996900 | Z5: =Y5-Y4 -> 0 | AA5: =AA4 -> 36796 | AB5: =AA5-AA4 -> 0 | AC5: =AC4 -> 1170505 | AD5: =AC5-AC4 -> 0 | AE5: =AB5+X5+T5 -> 0 | AF5: =V5+Z5+AD5 -> 0 | AG5: =IF(AE5>0,AF5/AE5,0) -> 0
A6: ='General information '!F7 -> 0 | B6: =SUM(230*A6) -> 0 | C6: 44684 | D6: 288240 | E6: =D6-D5 -> 1900 | F6: 4131042 | G6: =F6-F5 -> 386 | H6: 18039122 | I6: =H6-H5 -> 552 | J6: 29785976 | K6: =J6-J5 -> 2202 | L6: 24578426 | M6: =L6-L5 -> 1162 | N6: =M6+K6+I6+G6+E6 -> 6202 | O6: =IF(B6>0,N6/B6,0) -> 0 | P6: 19205.543 | Q6: =(P6-P5)*1000 -> 6018 | R6: =N6-Q6 -> 184 | S6: =S5 -> 10175 | T6: =S6-S5 -> 0 | U6: =U5 -> 429166 | V6: =U6-U5 -> 0 | W6: =W5 -> 33484 | X6: =W6-W5 -> 0 | Y6: =Y5 -> 996900 | Z6: =Y6-Y5 -> 0 | AA6: =AA5 -> 36796 | AB6: =AA6-AA5 -> 0 | AC6: =AC5 -> 1170505 | AD6: =AC6-AC5 -> 0 | AE6: =AB6+X6+T6 -> 0 | AF6: =V6+Z6+AD6 -> 0 | AG6: =IF(AE6>0,AF6/AE6,0) -> 0
A7: ='General information '!F8 -> 0 | B7: =SUM(230*A7) -> 0 | C7: 44685 | D7: 289480 | E7: =D7-D6 -> 1240 | F7: 4131338 | G7: =F7-F6 -> 296 | H7: 18039570 | I7: =H7-H6 -> 448 | J7: 29787300 | K7: =J7-J6 -> 1324 | L7: 24579406 | M7: =L7-L6 -> 980 | N7: =M7+K7+I7+G7+E7 -> 4288 | O7: =IF(B7>0,N7/B7,0) -> 0 | P7: 19209.517 | Q7: =(P7-P6)*1000 -> 3974 | R7: =N7-Q7 -> 314 | S7: =S6 -> 10175 | T7: =S7-S6 -> 0 | U7: =U6 -> 429166 | V7: =U7-U6 -> 0 | W7: =W6 -> 33484 | X7: =W7-W6 -> 0 | Y7: =Y6 -> 996900 | Z7: =Y7-Y6 -> 0 | AA7: 36796 | AB7: =AA7-AA6 -> 0 | AC7: 1170516 | AD7: =AC7-AC6 -> 11 | AE7: =AB7+X7+T7 -> 0 | AF7: =V7+Z7+AD7 -> 11 | AG7: =IF(AE7>0,AF7/AE7,0) -> 0
A8: ='General information '!F9 -> 0 | B8: =SUM(230*A8) -> 0 | C8: 44686 | D8: 290260 | E8: =D8-D7 -> 780 | F8: 4131619 | G8: =F8-F7 -> 281 | H8: 18039998 | I8: =H8-H7 -> 428 | J8: 29788042 | K8: =J8-J7 -> 742 | L8: 24580286 | M8: =L8-L7 -> 880 | N8: =M8+K8+I8+G8+E8 -> 3111 | O8: =IF(B8>0,N8/B8,0) -> 0 | P8: 19212.417 | Q8: =(P8-P7)*1000 -> 2900 | R8: =N8-Q8 -> 211 | S8: =S7 -> 10175 | T8: =S8-S7 -> 0 | U8: =U7 -> 429166 | V8: =U8-U7 -> 0 | W8: =W7 -> 33484 | X8: =W8-W7 -> 0 | Y8: =Y7 -> 996900 | Z8: =Y8-Y7 -> 0 | AA8: =AA7 -> 36796 | AB8: =AA8-AA7 -> 0 | AC8: =AC7 -> 1170516 | AD8: =AC8-AC7 -> 0 | AE8: =AB8+X8+T8 -> 0 | AF8: =V8+Z8+AD8 -> 0 | AG8: =IF(AE8>0,AF8/AE8,0) -> 0
A9: ='General information '!F10 -> 0 | B9: =SUM(230*A9) -> 0 | C9: 44687 | D9: =D8 -> 290260 | E9: =D9-D8 -> 0 | F9: =F8 -> 4131619 | G9: =F9-F8 -> 0 | H9: =H8 -> 18039998 | I9: =H9-H8 -> 0 | J9: =J8 -> 29788042 | K9: =J9-J8 -> 0 | L9: =L8 -> 24580286 | M9: =L9-L8 -> 0 | N9: =M9+K9+I9+G9+E9 -> 0 | O9: =IF(B9>0,N9/B9,0) -> 0 | P9: =P8 -> 19212.417 | Q9: =(P9-P8)*1000 -> 0 | R9: =N9-Q9 -> 0 | S9: =S8 -> 10175 | T9: =S9-S8 -> 0 | U9: =U8 -> 429166 | V9: =U9-U8 -> 0 | W9: =W8 -> 33484 | X9: =W9-W8 -> 0 | Y9: =Y8 -> 996900 | Z9: =Y9-Y8 -> 0 | AA9: =AA8 -> 36796 | AB9: =AA9-AA8 -> 0 | AC9: =AC8 -> 1170516 | AD9: =AC9-AC8 -> 0 | AE9: =AB9+X9+T9 -> 0 | AF9: =V9+Z9+AD9 -> 0 | AG9: =IF(AE9>0,AF9/AE9,0) -> 0
A10: ='General information '!F11 -> 0 | B10: =SUM(230*A10) -> 0 | C10: 44688 | D10: =D9 -> 290260 | E10: =D10-D9 -> 0 | F10: =F9 -> 4131619 | G10: =F10-F9 -> 0 | H10: =H9 -> 18039998 | I10: =H10-H9 -> 0 | J10: =J9 -> 29788042 | K10: =J10-J9 -> 0 | L10: =L9 -> 24580286 | M10: =L10-L9 -> 0 | N10: =M10+K10+I10+G10+E10 -> 0 | O10: =IF(B10>0,N10/B10,0) -> 0 | P10: =P9 -> 19212.417 | Q10: =(P10-P9)*1000 -> 0 | R10: =N10-Q10 -> 0 | S10: =S9 -> 10175 | T10: =S10-S9 -> 0 | U10: =U9 -> 429166 | V10: =U10-U9 -> 0 | W10: =W9 -> 33484 | X10: =W10-W9 -> 0 | Y10: =Y9 -> 996900 | Z10: =Y10-Y9 -> 0 | AA10: =AA9 -> 36796 | AB10: =AA10-AA9 -> 0 | AC10: =AC9 -> 1170516 | AD10: =AC10-AC9 -> 0 | AE10: =AB10+X10+T10 -> 0 | AF10: =V10+Z10+AD10 -> 0 | AG10: =IF(AE10>0,AF10/AE10,0) -> 0
A11: ='General information '!F12 -> 0 | B11: =SUM(230*A11) -> 0 | C11: 44689 | D11: 291370 | E11: =D11-D10 -> 1110 | F11: 4131876 | G11: =F11-F10 -> 257 | H11: 18040362 | I11: =H11-H10 -> 364 | J11: 29788666 | K11: =J11-J10 -> 624 | L11: 24581066 | M11: =L11-L10 -> 780 | N11: =M11+K11+I11+G11+E11 -> 3135 | O11: =IF(B11>0,N11/B11,0) -> 0 | P11: 19215.397 | Q11: =(P11-P10)*1000 -> 2980 | R11: =N11-Q11 -> 155 | S11: =S10 -> 10175 | T11: =S11-S10 -> 0 | U11: =U10 -> 429166 | V11: =U11-U10 -> 0 | W11: =W10 -> 33484 | X11: =W11-W10 -> 0 | Y11: =Y10 -> 996900 | Z11: =Y11-Y10 -> 0 | AA11: =AA10 -> 36796 | AB11: =AA11-AA10 -> 0 | AC11: =AC10 -> 1170516 | AD11: =AC11-AC10 -> 0 | AE11: =AB11+X11+T11 -> 0 | AF11: =V11+Z11+AD11 -> 0 | AG11: =IF(AE11>0,AF11/AE11,0) -> 0
A12: ='General information '!F13 -> 0 | B12: =SUM(230*A12) -> 0 | C12: 44690 | D12: 292210 | E12: =D12-D11 -> 840 | F12: 4132223 | G12: =F12-F11 -> 347 | H12: 18040892 | I12: =H12-H11 -> 530 | J12: 29789378 | K12: =J12-J11 -> 712 | L12: 24582082 | M12: =L12-L11 -> 1016 | N12: =M12+K12+I12+G12+E12 -> 3445 | O12: =IF(B12>0,N12/B12,0) -> 0 | P12: 19218.531 | Q12: =(P12-P11)*1000 -> 3134 | R12: =N12-Q12 -> 311 | S12: =S11 -> 10175 | T12: =S12-S11 -> 0 | U12: =U11 -> 429166 | V12: =U12-U11 -> 0 | W12: =W11 -> 33484 | X12: =W12-W11 -> 0 | Y12: =Y11 -> 996900 | Z12: =Y12-Y11 -> 0 | AA12: =AA11 -> 36796 | AB12: =AA12-AA11 -> 0 | AC12: =AC11 -> 1170516 | AD12: =AC12-AC11 -> 0 | AE12: =AB12+X12+T12 -> 0 | AF12: =V12+Z12+AD12 -> 0 | AG12: =IF(AE12>0,AF12/AE12,0) -> 0
A13: ='General information '!F14 -> 0 | B13: =SUM(230*A13) -> 0 | C13: 44691 | D13: 292980 | E13: =D13-D12 -> 770 | F13: 4132528 | G13: =F13-F12 -> 305 | H13: 18041378 | I13: =H13-H12 -> 486 | J13: 29789998 | K13: =J13-J12 -> 620 | L13: 24583058 | M13: =L13-L12 -> 976 | N13: =M13+K13+I13+G13+E13 -> 3157 | O13: =IF(B13>0,N13/B13,0) -> 0 | P13: 19221.399 | Q13: =(P13-P12)*1000 -> 2868 | R13: =N13-Q13 -> 289 | S13: =S12 -> 10175 | T13: =S13-S12 -> 0 | U13: =U12 -> 429166 | V13: =U13-U12 -> 0 | W13: =W12 -> 33484 | X13: =W13-W12 -> 0 | Y13: =Y12 -> 996900 | Z13: =Y13-Y12 -> 0 | AA13: =AA12 -> 36796 | AB13: =AA13-AA12 -> 0 | AC13: =AC12 -> 1170516 | AD13: =AC13-AC12 -> 0 | AE13: =AB13+X13+T13 -> 0 | AF13: =V13+Z13+AD13 -> 0 | AG13: =IF(AE13>0,AF13/AE13,0) -> 0
A14: ='General information '!F15 -> 0 | B14: =SUM(230*A14) -> 0 | C14: 44692 | D14: 293750 | E14: =D14-D13 -> 770 | F14: 4132829 | G14: =F14-F13 -> 301 | H14: 18041866 | I14: =H14-H13 -> 488 | J14: 29790636 | K14: =J14-J13 -> 638 | L14: 24583966 | M14: =L14-L13 -> 908 | N14: =M14+K14+I14+G14+E14 -> 3105 | O14: =IF(B14>0,N14/B14,0) -> 0 | P14: 19224.4 | Q14: =(P14-P13)*1000 -> 3001 | R14: =N14-Q14 -> 104 | S14: =S13 -> 10175 | T14: =S14-S13 -> 0 | U14: =U13 -> 429166 | V14: =U14-U13 -> 0 | W14: =W13 -> 33484 | X14: =W14-W13 -> 0 | Y14: =Y13 -> 996900 | Z14: =Y14-Y13 -> 0 | AA14: =AA13 -> 36796 | AB14: =AA14-AA13 -> 0 | AC14: =AC13 -> 1170516 | AD14: =AC14-AC13 -> 0 | AE14: =AB14+X14+T14 -> 0 | AF14: =V14+Z14+AD14 -> 0 | AG14: =IF(AE14>0,AF14/AE14,0) -> 0
A15: ='General information '!F16 -> 0 | B15: =SUM(230*A15) -> 0 | C15: 44693 | D15: 294440 | E15: =D15-D14 -> 690 | F15: 4133116 | G15: =F15-F14 -> 287 | H15: 18042302 | I15: =H15-H14 -> 436 | J15: 29791200 | K15: =J15-J14 -> 564 | L15: 24584732 | M15: =L15-L14 -> 766 | N15: =M15+K15+I15+G15+E15 -> 2743 | O15: =IF(B15>0,N15/B15,0) -> 0 | P15: 19227.006 | Q15: =(P15-P14)*1000 -> 2606 | R15: =N15-Q15 -> 137 | S15: =S14 -> 10175 | T15: =S15-S14 -> 0 | U15: =U14 -> 429166 | V15: =U15-U14 -> 0 | W15: =W14 -> 33484 | X15: =W15-W14 -> 0 | Y15: =Y14 -> 996900 | Z15: =Y15-Y14 -> 0 | AA15: =AA14 -> 36796 | AB15: =AA15-AA14 -> 0 | AC15: =AC14 -> 1170516 | AD15: =AC15-AC14 -> 0 | AE15: =AB15+X15+T15 -> 0 | AF15: =V15+Z15+AD15 -> 0 | AG15: =IF(AE15>0,AF15/AE15,0) -> 0
A16: ='General information '!F17 -> 0 | B16: =SUM(230*A16) -> 0 | C16: 44694 | D16: =D15 -> 294440 | E16: =D16-D15 -> 0 | F16: =F15 -> 4133116 | G16: =F16-F15 -> 0 | H16: =H15 -> 18042302 | I16: =H16-H15 -> 0 | J16: =J15 -> 29791200 | K16: =J16-J15 -> 0 | L16: =L15 -> 24584732 | M16: =L16-L15 -> 0 | N16: =M16+K16+I16+G16+E16 -> 0 | O16: =IF(B16>0,N16/B16,0) -> 0 | P16: =P15 -> 19227.006 | Q16: =(P16-P15)*1000 -> 0 | R16: =N16-Q16 -> 0 | S16: =S15 -> 10175 | T16: =S16-S15 -> 0 | U16: =U15 -> 429166 | V16: =U16-U15 -> 0 | W16: =W15 -> 33484 | X16: =W16-W15 -> 0 | Y16: =Y15 -> 996900 | Z16: =Y16-Y15 -> 0 | AA16: =AA15 -> 36796 | AB16: =AA16-AA15 -> 0 | AC16: =AC15 -> 1170516 | AD16: =AC16-AC15 -> 0 | AE16: =AB16+X16+T16 -> 0 | AF16: =V16+Z16+AD16 -> 0 | AG16: =IF(AE16>0,AF16/AE16,0) -> 0
A17: ='General information '!F18 -> 0 | B17: =SUM(230*A17) -> 0 | C17: 44695 | D17: =D16 -> 294440 | E17: =D17-D16 -> 0 | F17: =F16 -> 4133116 | G17: =F17-F16 -> 0 | H17: =H16 -> 18042302 | I17: =H17-H16 -> 0 | J17: =J16 -> 29791200 | K17: =J17-J16 -> 0 | L17: =L16 -> 24584732 | M17: =L17-L16 -> 0 | N17: =M17+K17+I17+G17+E17 -> 0 | O17: =IF(B17>0,N17/B17,0) -> 0 | P17: =P16 -> 19227.006 | Q17: =(P17-P16)*1000 -> 0 | R17: =N17-Q17 -> 0 | S17: =S16 -> 10175 | T17: =S17-S16 -> 0 | U17: =U16 -> 429166 | V17: =U17-U16 -> 0 | W17: =W16 -> 33484 | X17: =W17-W16 -> 0 | Y17: =Y16 -> 996900 | Z17: =Y17-Y16 -> 0 | AA17: =AA16 -> 36796 | AB17: =AA17-AA16 -> 0 | AC17: =AC16 -> 1170516 | AD17: =AC17-AC16 -> 0 | AE17: =AB17+X17+T17 -> 0 | AF17: =V17+Z17+AD17 -> 0 | AG17: =IF(AE17>0,AF17/AE17,0) -> 0
A18: ='General information '!F19 -> 0 | B18: =SUM(230*A18) -> 0 | C18: 44696 | D18: =D17 -> 294440 | E18: =D18-D17 -> 0 | F18: =F17 -> 4133116 | G18: =F18-F17 -> 0 | H18: =H17 -> 18042302 | I18: =H18-H17 -> 0 | J18: =J17 -> 29791200 | K18: =J18-J17 -> 0 | L18: =L17 -> 24584732 | M18: =L18-L17 -> 0 | N18: =M18+K18+I18+G18+E18 -> 0 | O18: =IF(B18>0,N18/B18,0) -> 0 | P18: =P17 -> 19227.006 | Q18: =(P18-P17)*1000 -> 0 | R18: =N18-Q18 -> 0 | S18: =S17 -> 10175 | T18: =S18-S17 -> 0 | U18: =U17 -> 429166 | V18: =U18-U17 -> 0 | W18: =W17 -> 33484 | X18: =W18-W17 -> 0 | Y18: =Y17 -> 996900 | Z18: =Y18-Y17 -> 0 | AA18: =AA17 -> 36796 | AB18: =AA18-AA17 -> 0 | AC18: =AC17 -> 1170516 | AD18: =AC18-AC17 -> 0 | AE18: =AB18+X18+T18 -> 0 | AF18: =V18+Z18+AD18 -> 0 | AG18: =IF(AE18>0,AF18/AE18,0) -> 0
A19: ='General information '!F20 -> 0 | B19: =SUM(230*A19) -> 0 | C19: 44697 | D19: =D18 -> 294440 | E19: =D19-D18 -> 0 | F19: =F18 -> 4133116 | G19: =F19-F18 -> 0 | H19: =H18 -> 18042302 | I19: =H19-H18 -> 0 | J19: =J18 -> 29791200 | K19: =J19-J18 -> 0 | L19: =L18 -> 24584732 | M19: =L19-L18 -> 0 | N19: =M19+K19+I19+G19+E19 -> 0 | O19: =IF(B19>0,N19/B19,0) -> 0 | P19: =P18 -> 19227.006 | Q19: =(P19-P18)*1000 -> 0 | R19: =N19-Q19 -> 0 | S19: =S18 -> 10175 | T19: =S19-S18 -> 0 | U19: =U18 -> 429166 | V19: =U19-U18 -> 0 | W19: =W18 -> 33484 | X19: =W19-W18 -> 0 | Y19: =Y18 -> 996900 | Z19: =Y19-Y18 -> 0 | AA19: =AA18 -> 36796 | AB19: =AA19-AA18 -> 0 | AC19: =AC18 -> 1170516 | AD19: =AC19-AC18 -> 0 | AE19: =AB19+X19+T19 -> 0 | AF19: =V19+Z19+AD19 -> 0 | AG19: =IF(AE19>0,AF19/AE19,0) -> 0
A20: ='General information '!F21 -> 0 | B20: =SUM(230*A20) -> 0 | C20: 44698 | D20: =D19 -> 294440 | E20: =D20-D19 -> 0 | F20: =F19 -> 4133116 | G20: =F20-F19 -> 0 | H20: =H19 -> 18042302 | I20: =H20-H19 -> 0 | J20: =J19 -> 29791200 | K20: =J20-J19 -> 0 | L20: =L19 -> 24584732 | M20: =L20-L19 -> 0 | N20: =M20+K20+I20+G20+E20 -> 0 | O20: =IF(B20>0,N20/B20,0) -> 0 | P20: =P19 -> 19227.006 | Q20: =(P20-P19)*1000 -> 0 | R20: =N20-Q20 -> 0 | S20: =S19 -> 10175 | T20: =S20-S19 -> 0 | U20: =U19 -> 429166 | V20: =U20-U19 -> 0 | W20: =W19 -> 33484 | X20: =W20-W19 -> 0 | Y20: =Y19 -> 996900 | Z20: =Y20-Y19 -> 0 | AA20: =AA19 -> 36796 | AB20: =AA20-AA19 -> 0 | AC20: =AC19 -> 1170516 | AD20: =AC20-AC19 -> 0 | AE20: =AB20+X20+T20 -> 0 | AF20: =V20+Z20+AD20 -> 0 | AG20: =IF(AE20>0,AF20/AE20,0) -> 0
A21: ='General information '!F22 -> 0 | B21: =SUM(230*A21) -> 0 | C21: 44699 | D21: =D20 -> 294440 | E21: =D21-D20 -> 0 | F21: =F20 -> 4133116 | G21: =F21-F20 -> 0 | H21: =H20 -> 18042302 | I21: =H21-H20 -> 0 | J21: =J20 -> 29791200 | K21: =J21-J20 -> 0 | L21: =L20 -> 24584732 | M21: =L21-L20 -> 0 | N21: =M21+K21+I21+G21+E21 -> 0 | O21: =IF(B21>0,N21/B21,0) -> 0 | P21: =P20 -> 19227.006 | Q21: =(P21-P20)*1000 -> 0 | R21: =N21-Q21 -> 0 | S21: =S20 -> 10175 | T21: =S21-S20 -> 0 | U21: =U20 -> 429166 | V21: =U21-U20 -> 0 | W21: =W20 -> 33484 | X21: =W21-W20 -> 0 | Y21: =Y20 -> 996900 | Z21: =Y21-Y20 -> 0 | AA21: =AA20 -> 36796 | AB21: =AA21-AA20 -> 0 | AC21: =AC20 -> 1170516 | AD21: =AC21-AC20 -> 0 | AE21: =AB21+X21+T21 -> 0 | AF21: =V21+Z21+AD21 -> 0 | AG21: =IF(AE21>0,AF21/AE21,0) -> 0
A22: ='General information '!F23 -> 0 | B22: =SUM(230*A22) -> 0 | C22: 44700 | D22: =D21 -> 294440 | E22: =D22-D21 -> 0 | F22: =F21 -> 4133116 | G22: =F22-F21 -> 0 | H22: =H21 -> 18042302 | I22: =H22-H21 -> 0 | J22: =J21 -> 29791200 | K22: =J22-J21 -> 0 | L22: =L21 -> 24584732 | M22: =L22-L21 -> 0 | N22: =M22+K22+I22+G22+E22 -> 0 | O22: =IF(B22>0,N22/B22,0) -> 0 | P22: =P21 -> 19227.006 | Q22: =(P22-P21)*1000 -> 0 | R22: =N22-Q22 -> 0 | S22: =S21 -> 10175 | T22: =S22-S21 -> 0 | U22: =U21 -> 429166 | V22: =U22-U21 -> 0 | W22: =W21 -> 33484 | X22: =W22-W21 -> 0 | Y22: =Y21 -> 996900 | Z22: =Y22-Y21 -> 0 | AA22: =AA21 -> 36796 | AB22: =AA22-AA21 -> 0 | AC22: =AC21 -> 1170516 | AD22: =AC22-AC21 -> 0 | AE22: =AB22+X22+T22 -> 0 | AF22: =V22+Z22+AD22 -> 0 | AG22: =IF(AE22>0,AF22/AE22,0) -> 0
A23: ='General information '!F24 -> 0 | B23: =SUM(230*A23) -> 0 | C23: 44701 | D23: =D22 -> 294440 | E23: =D23-D22 -> 0 | F23: =F22 -> 4133116 | G23: =F23-F22 -> 0 | H23: =H22 -> 18042302 | I23: =H23-H22 -> 0 | J23: =J22 -> 29791200 | K23: =J23-J22 -> 0 | L23: =L22 -> 24584732 | M23: =L23-L22 -> 0 | N23: =M23+K23+I23+G23+E23 -> 0 | O23: =IF(B23>0,N23/B23,0) -> 0 | P23: =P22 -> 19227.006 | Q23: =(P23-P22)*1000 -> 0 | R23: =N23-Q23 -> 0 | S23: =S22 -> 10175 | T23: =S23-S22 -> 0 | U23: =U22 -> 429166 | V23: =U23-U22 -> 0 | W23: =W22 -> 33484 | X23: =W23-W22 -> 0 | Y23: =Y22 -> 996900 | Z23: =Y23-Y22 -> 0 | AA23: =AA22 -> 36796 | AB23: =AA23-AA22 -> 0 | AC23: =AC22 -> 1170516 | AD23: =AC23-AC22 -> 0 | AE23: =AB23+X23+T23 -> 0 | AF23: =V23+Z23+AD23 -> 0 | AG23: =IF(AE23>0,AF23/AE23,0) -> 0
A24: ='General information '!F25 -> 0 | B24: =SUM(230*A24) -> 0 | C24: 44702 | D24: =D23 -> 294440 | E24: =D24-D23 -> 0 | F24: =F23 -> 4133116 | G24: =F24-F23 -> 0 | H24: =H23 -> 18042302 | I24: =H24-H23 -> 0 | J24: =J23 -> 29791200 | K24: =J24-J23 -> 0 | L24: =L23 -> 24584732 | M24: =L24-L23 -> 0 | N24: =M24+K24+I24+G24+E24 -> 0 | O24: =IF(B24>0,N24/B24,0) -> 0 | P24: =P23 -> 19227.006 | Q24: =(P24-P23)*1000 -> 0 | R24: =N24-Q24 -> 0 | S24: =S23 -> 10175 | T24: =S24-S23 -> 0 | U24: =U23 -> 429166 | V24: =U24-U23 -> 0 | W24: =W23 -> 33484 | X24: =W24-W23 -> 0 | Y24: =Y23 -> 996900 | Z24: =Y24-Y23 -> 0 | AA24: =AA23 -> 36796 | AB24: =AA24-AA23 -> 0 | AC24: =AC23 -> 1170516 | AD24: =AC24-AC23 -> 0 | AE24: =AB24+X24+T24 -> 0 | AF24: =V24+Z24+AD24 -> 0 | AG24: =IF(AE24>0,AF24/AE24,0) -> 0
A25: ='General information '!F26 -> 0 | B25: =SUM(230*A25) -> 0 | C25: 44703 | D25: =D24 -> 294440 | E25: =D25-D24 -> 0 | F25: =F24 -> 4133116 | G25: =F25-F24 -> 0 | H25: =H24 -> 18042302 | I25: =H25-H24 -> 0 | J25: =J24 -> 29791200 | K25: =J25-J24 -> 0 | L25: =L24 -> 24584732 | M25: =L25-L24 -> 0 | N25: =M25+K25+I25+G25+E25 -> 0 | O25: =IF(B25>0,N25/B25,0) -> 0 | P25: =P24 -> 19227.006 | Q25: =(P25-P24)*1000 -> 0 | R25: =N25-Q25 -> 0 | S25: =S24 -> 10175 | T25: =S25-S24 -> 0 | U25: =U24 -> 429166 | V25: =U25-U24 -> 0 | W25: =W24 -> 33484 | X25: =W25-W24 -> 0 | Y25: =Y24 -> 996900 | Z25: =Y25-Y24 -> 0 | AA25: =AA24 -> 36796 | AB25: =AA25-AA24 -> 0 | AC25: =AC24 -> 1170516 | AD25: =AC25-AC24 -> 0 | AE25: =AB25+X25+T25 -> 0 | AF25: =V25+Z25+AD25 -> 0 | AG25: =IF(AE25>0,AF25/AE25,0) -> 0
A26: ='General information '!F27 -> 0 | B26: =SUM(230*A26) -> 0 | C26: 44704 | D26: =D25 -> 294440 | E26: =D26-D25 -> 0 | F26: =F25 -> 4133116 | G26: =F26-F25 -> 0 | H26: =H25 -> 18042302 | I26: =H26-H25 -> 0 | J26: =J25 -> 29791200 | K26: =J26-J25 -> 0 | L26: =L25 -> 24584732 | M26: =L26-L25 -> 0 | N26: =M26+K26+I26+G26+E26 -> 0 | O26: =IF(B26>0,N26/B26,0) -> 0 | P26: =P25 -> 19227.006 | Q26: =(P26-P25)*1000 -> 0 | R26: =N26-Q26 -> 0 | S26: =S25 -> 10175 | T26: =S26-S25 -> 0 | U26: =U25 -> 429166 | V26: =U26-U25 -> 0 | W26: =W25 -> 33484 | X26: =W26-W25 -> 0 | Y26: =Y25 -> 996900 | Z26: =Y26-Y25 -> 0 | AA26: =AA25 -> 36796 | AB26: =AA26-AA25 -> 0 | AC26: =AC25 -> 1170516 | AD26: =AC26-AC25 -> 0 | AE26: =AB26+X26+T26 -> 0 | AF26: =V26+Z26+AD26 -> 0 | AG26: =IF(AE26>0,AF26/AE26,0) -> 0
A27: ='General information '!F28 -> 0 | B27: =SUM(230*A27) -> 0 | C27: 44705 | D27: =D26 -> 294440 | E27: =D27-D26 -> 0 | F27: =F26 -> 4133116 | G27: =F27-F26 -> 0 | H27: =H26 -> 18042302 | I27: =H27-H26 -> 0 | J27: =J26 -> 29791200 | K27: =J27-J26 -> 0 | L27: =L26 -> 24584732 | M27: =L27-L26 -> 0 | N27: =M27+K27+I27+G27+E27 -> 0 | O27: =IF(B27>0,N27/B27,0) -> 0 | P27: =P26 -> 19227.006 | Q27: =(P27-P26)*1000 -> 0 | R27: =N27-Q27 -> 0 | S27: =S26 -> 10175 | T27: =S27-S26 -> 0 | U27: =U26 -> 429166 | V27: =U27-U26 -> 0 | W27: =W26 -> 33484 | X27: =W27-W26 -> 0 | Y27: =Y26 -> 996900 | Z27: =Y27-Y26 -> 0 | AA27: =AA26 -> 36796 | AB27: =AA27-AA26 -> 0 | AC27: =AC26 -> 1170516 | AD27: =AC27-AC26 -> 0 | AE27: =AB27+X27+T27 -> 0 | AF27: =V27+Z27+AD27 -> 0 | AG27: =IF(AE27>0,AF27/AE27,0) -> 0
... A34: ='General information '!F35 -> 0 | B34: =SUM(230*A34) -> 0 | C34: 44712 | D34: =D33 -> 294440 | E34: =D34-D33 -> 0 | F34: =F33 -> 4133116 | G34: =F34-F33 -> 0 | H34: =H33 -> 18042302 | I34: =H34-H33 -> 0 | J34: =J33 -> 29791200 | K34: =J34-J33 -> 0 | L34: =L33 -> 24584732 | M34: =L34-L33 -> 0 | N34: =M34+K34+I34+G34+E34 -> 0 | O34: =IF(B34>0,N34/B34,0) -> 0 | P34: =P33 -> 19227.006 | Q34: =(P34-P33)*1000 -> 0 | R34: =N34-Q34 -> 0 | S34: =S33 -> 10175 | T34: =S34-S33 -> 0 | U34: =U33 -> 429166 | V34: =U34-U33 -> 0 | W34: =W33 -> 33484 | X34: =W34-W33 -> 0 | Y34: =Y33 -> 996900 | Z34: =Y34-Y33 -> 0 | AA34: =AA33 -> 36796 | AB34: =AA34-AA33 -> 0 | AC34: =AC33 -> 1170516 | AD34: =AC34-AC33 -> 0 | AE34: =AB34+X34+T34 -> 0 | AF34: =V34+Z34+AD34 -> 0 | AG34: =IF(AE34>0,AF34/AE34,0) -> 0

Sheet B5
F1: Boiler A | J1: =J36 -> 1 | K1: Boiler B | P1: Boiler C | V1: Boiler | X1: SteamA | AC1: SteamB | AH1: Steam | AI1: Boiler & steam | AL1: Total Boiler Runing H | AM1: Total Steam Runing H | AN1: GAS1 % | AO1: GAS1/L | AP1: GAS2% | AQ1: Gas2/L | AR1: GAS3% | AS1: GAS3/L | AU1: Gas Cons | AV1: Delivery | AW1: Cost/L
B2: Level Tank Gen | C2: Level tank Boiler | D2: Daily Cons Bo. | E2: Boiler litter | F2: Boiler A | G2: Run Hr a | H2: Boiler A fuel | I2: Daily consumption | J2: AVG | K2: index Run H | L2: Run Hrb | M2: Boiler B Fuel | O2: Daily consumption | P2: Boiler C | S2: Run C | U2: Total RH | V2: Total Fuel | X2: SteamA | Y2: Run SA | Z2: Steam A Conter | AA2: Liters | AC2: SteamB | AD2: Run SteamB | AE2: Steam B Conter | AF2: SB Litters | AG2: Avg | AH2: Total Fuel | AI2: Total Fuel
S3: 0
A4: =[2]B5!$A$34 -> 44681 | B4: =[2]B5!B34 -> 233 | C4: =[2]B5!C34 -> 239 | D4: =[2]B5!D34 -> 0 | E4: =[2]B5!E34 -> 0 | F4: =[2]B5!F34 -> 2242 | G4: =[2]B5!G34 -> 0 | H4: =[2]B5!H34 -> 43494 | I4: =[2]B5!I34 -> 0 | ... AX4: =[2]B5!AX34 -> 0.8
A5: =ELEC!C4 -> 44682 | B5: =B4 -> 233 | C5: =C4 -> 239 | D5: =C4-C5 -> 0 | E5: =D5*8.38 -> 0 | F5: =F4 -> 2242 | G5: =F5-F4 -> 0 | H5: =H4 -> 43494 | I5: =SUM(H5-H4) -> 0 | J5: 1 | K5: =K4 -> 2412 | L5: =K5-K4 -> 0 | M5: =M4 -> 178611 | N5: =M5-M4 -> 0 | O5: =O4 -> 1869 | P5: =P4 -> 2199 | Q5: =Q4 -> 183982 | R5: =Q5-Q4 -> 0 | S5: =SUM(P5-P4) -> 0 | T5: =SUM(S5*$T$2) -> 0 | U5: =SUM(G5+L5+S5) -> 0 | V5: =R5+N5+I5:I5 -> 0 | W5: =SUM(V5/U5) -> #DIV/0! | X5: =X4 -> 2477 | Y5: =X5-X4 -> 0 | Z5: =Z4 -> 139698 | AA5: =Z5-Z4 -> 0 | AB5: =SUM(Y5*$AB$2) -> 0 | AC5: =AC4 -> 1944 | AD5: =AC5-AC4 -> 0 | AE5: =AE4 -> 366312 | AF5: =AE5-AE4 -> 0 | AG5: =IF(AD5>0,AF5/AD5,0) -> 0 | AH5: =AF5+AA5 -> 0 | AI5: =SUM(AH5+V5) -> 0 | AJ5: =-tanks!AW6 -> 0 | AK5: =SUM(AJ5-AI5) -> 0 | AL5: =S5+L5+G5 -> 0 | AM5: =Y5+AD5 -> 0 | AN5: =AN4 -> 65 | AO5: =(AN5/100)*3000 -> 1950 | AP5: =AP4 -> 55 | AQ5: =(AP5/100)*3000 -> 1650 | AR5: =AR4 -> 61 | AS5: =(AR5/100)*3000 -> 1830 | AT5: =SUM(AO5+AQ5+AS5) -> 5430 | AU5: =AT4-AT5+AV5 -> 0 | AX5: =IF(AV5>0,AW5,AX4) -> 0.8
A6: =ELEC!C5 -> 44683 | B6: =B5 -> 233 | C6: =C5 -> 239 | D6: =C5-C6 -> 0 | E6: =D6*8.38 -> 0 | F6: =F5 -> 2242 | G6: =F6-F5 -> 0 | H6: =H5 -> 43494 | I6: =SUM(H6-H5) -> 0 | J6: =IF(G6>0,I6/G6,0) -> 0 | K6: =K5 -> 2412 | L6: =K6-K5 -> 0 | M6: =M5 -> 178611 | N6: =M6-M5 -> 0 | O6: =O5 -> 1869 | P6: =P5 -> 2199 | Q6: =Q5 -> 183982 | R6: =Q6-Q5 -> 0 | S6: =SUM(P6-P5) -> 0 | T6: =SUM(S6*$T$2) -> 0 | U6: =SUM(G6+L6+S6) -> 0 | V6: =R6+N6+I6:I6 -> 0 | W6: =SUM(V6/U6) -> #DIV/0! | X6: =X5 -> 2477 | Y6: =X6-X5 -> 0 | Z6: =Z5 -> 139698 | AA6: =Z6-Z5 -> 0 | AB6: =SUM(Y6*$AB$2) -> 0 | AC6: =AC5 -> 1944 | AD6: =AC6-AC5 -> 0 | AE6: =AE5 -> 366312 | AF6: =AE6-AE5 -> 0 | AG6: =IF(AD6>0,AF6/AD6,0) -> 0 | AH6: =AF6+AA6 -> 0 | AI6: =SUM(AH6+V6) -> 0 | AJ6: =-tanks!AW7 -> 0 | AK6: =SUM(AJ6-AI6) -> 0 | AL6: =S6+L6+G6 -> 0 | AM6: =Y6+AD6 -> 0 | AN6: =AN5 -> 65 | AO6: =(AN6/100)*3000 -> 1950 | AP6: =AP5 -> 55 | AQ6: =(AP6/100)*3000 -> 1650 | AR6: =AR5 -> 61 | AS6: =(AR6/100)*3000 -> 1830 | AT6: =SUM(AO6+AQ6+AS6) -> 5430 | AU6: =AT5-AT6+AV6 -> 0 | AX6: =IF(AV6>0,AW6,AX5) -> 0.8
A7: =ELEC!C6 -> 44684 | B7: 224 | C7: 231 | D7: =C6-C7 -> 8 | E7: =D7*8.38 -> 67.04 | F7: =F6 -> 2242 | G7: =F7-F6 -> 0 | H7: =H6 -> 43494 | I7: =SUM(H7-H6) -> 0 | J7: =IF(G7>0,I7/G7,0) -> 0 | K7: 2415 | L7: =K7-K6 -> 3 | M7: 178900 | N7: =M7-M6 -> 289 | O7: =O6 -> 1869 | P7: =P6 -> 2199 | Q7: =Q6 -> 183982 | R7: =Q7-Q6 -> 0 | S7: =SUM(P7-P6) -> 0 | T7: =SUM(S7*$T$2) -> 0 | U7: =SUM(G7+L7+S7) -> 3 | V7: =R7+N7+I7:I7 -> 289 | W7: =SUM(V7/U7) -> 96.333333 | X7: =X6 -> 2477 | Y7: =X7-X6 -> 0 | Z7: =Z6 -> 139698 | AA7: =Z7-Z6 -> 0 | AB7: =SUM(Y7*$AB$2) -> 0 | AC7: =AC6 -> 1944 | AD7: =AC7-AC6 -> 0 | AE7: =AE6 -> 366312 | AF7: =AE7-AE6 -> 0 | AG7: =IF(AD7>0,AF7/AD7,0) -> 0 | AH7: =AF7+AA7 -> 0 | AI7: =SUM(AH7+V7) -> 289 | AJ7: =-tanks!AW8 -> 289 | AK7: =SUM(AJ7-AI7) -> 0 | AL7: =S7+L7+G7 -> 3 | AM7: =Y7+AD7 -> 0 | AN7: =AN6 -> 65 | AO7: =(AN7/100)*3000 -> 1950 | AP7: =AP6 -> 55 | AQ7: =(AP7/100)*3000 -> 1650 | AR7: =AR6 -> 61 | AS7: =(AR7/100)*3000 -> 1830 | AT7: =SUM(AO7+AQ7+AS7) -> 5430 | AU7: =AT6-AT7+AV7 -> 0 | AX7: =IF(AV7>0,AW7,AX6) -> 0.8
A8: =ELEC!C7 -> 44685 | B8: 218 | C8: 225 | D8: =C7-C8 -> 6 | E8: =D8*8.38 -> 50.28 | F8: =F7 -> 2242 | G8: =F8-F7 -> 0 | H8: =H7 -> 43494 | I8: =SUM(H8-H7) -> 0 | J8: =IF(G8>0,I8/G8,0) -> 0 | K8: 2419 | L8: =K8-K7 -> 4 | M8: 179204 | N8: =M8-M7 -> 304 | O8: =O7 -> 1869 | P8: 2199 | Q8: 183983 | R8: =Q8-Q7 -> 1 | S8: =SUM(P8-P7) -> 0 | T8: =SUM(S8*$T$2) -> 0 | U8: =SUM(G8+L8+S8) -> 4 | V8: =R8+N8+I8:I8 -> 305 | W8: =SUM(V8/U8) -> 76.25 | X8: =X7 -> 2477 | Y8: =X8-X7 -> 0 | Z8: =Z7 -> 139698 | AA8: =Z8-Z7 -> 0 | AB8: =SUM(Y8*$AB$2) -> 0 | AC8: =AC7 -> 1944 | AD8: =AC8-AC7 -> 0 | AE8: =AE7 -> 366312 | AF8: =AE8-AE7 -> 0 | AG8: =IF(AD8>0,AF8/AD8,0) -> 0 | AH8: =AF8+AA8 -> 0 | AI8: =SUM(AH8+V8) -> 305 | AJ8: =-tanks!AW9 -> 305 | AK8: =SUM(AJ8-AI8) -> 0 | AL8: =S8+L8+G8 -> 4 | AM8: =Y8+AD8 -> 0 | AN8: =AN7 -> 65 | AO8: =(AN8/100)*3000 -> 1950 | AP8: =AP7 -> 55 | AQ8: =(AP8/100)*3000 -> 1650 | AR8: =AR7 -> 61 | AS8: =(AR8/100)*3000 -> 1830 | AT8: =SUM(AO8+AQ8+AS8) -> 5430 | AU8: =AT7-AT8+AV8 -> 0 | AX8: =IF(AV8>0,AW8,AX7) -> 0.8
A9: =ELEC!C8 -> 44686 | B9: 215 | C9: 222 | D9: =C8-C9 -> 3 | E9: =D9*8.38 -> 25.14 | F9: =F8 -> 2242 | G9: =F9-F8 -> 0 | H9: =H8 -> 43494 | I9: =SUM(H9-H8) -> 0 | J9: =IF(G9>0,I9/G9,0) -> 0 | K9: =K8 -> 2419 | L9: =K9-K8 -> 0 | M9: 179248 | N9: =M9-M8 -> 44 | O9: =O8 -> 1869 | P9: =P8 -> 2199 | Q9: =Q8 -> 183983 | R9: =Q9-Q8 -> 0 | S9: =SUM(P9-P8) -> 0 | T9: =SUM(S9*$T$2) -> 0 | U9: =SUM(G9+L9+S9) -> 0 | V9: =R9+N9+I9:I9 -> 44 | W9: =SUM(V9/U9) -> #DIV/0! | X9: =X8 -> 2477 | Y9: =X9-X8 -> 0 | Z9: =Z8 -> 139698 | AA9: =Z9-Z8 -> 0 | AB9: =SUM(Y9*$AB$2) -> 0 | AC9: =AC8 -> 1944 | AD9: =AC9-AC8 -> 0 | AE9: =AE8 -> 366312 | AF9: =AE9-AE8 -> 0 | AG9: =IF(AD9>0,AF9/AD9,0) -> 0 | AH9: =AF9+AA9 -> 0 | AI9: =SUM(AH9+V9) -> 44 | AJ9: =-tanks!AW10 -> 44 | AK9: =SUM(AJ9-AI9) -> 0 | AL9: =S9+L9+G9 -> 0 | AM9: =Y9+AD9 -> 0 | AN9: =AN8 -> 65 | AO9: =(AN9/100)*3000 -> 1950 | AP9: =AP8 -> 55 | AQ9: =(AP9/100)*3000 -> 1650 | AR9: =AR8 -> 61 | AS9: =(AR9/100)*3000 -> 1830 | AT9: =SUM(AO9+AQ9+AS9) -> 5430 | AU9: =AT8-AT9+AV9 -> 0 | AX9: =IF(AV9>0,AW9,AX8) -> 0.8
A10: =ELEC!C9 -> 44687 | B10: =B9 -> 215 | C10: =C9 -> 222 | D10: =C9-C10 -> 0 | E10: =D10*8.38 -> 0 | F10: =F9 -> 2242 | G10: =F10-F9 -> 0 | H10: =H9 -> 43494 | I10: =SUM(H10-H9) -> 0 | J10: =IF(G10>0,I10/G10,0) -> 0 | K10: =K9 -> 2419 | L10: =K10-K9 -> 0 | M10: =M9 -> 179248 | N10: =M10-M9 -> 0 | O10: =O9 -> 1869 | P10: =P9 -> 2199 | Q10: =Q9 -> 183983 | R10: =Q10-Q9 -> 0 | S10: =SUM(P10-P9) -> 0 | T10: =SUM(S10*$T$2) -> 0 | U10: =SUM(G10+L10+S10) -> 0 | V10: =R10+N10+I10:I10 -> 0 | W10: =SUM(V10/U10) -> #DIV/0! | X10: =X9 -> 2477 | Y10: =X10-X9 -> 0 | Z10: =Z9 -> 139698 | AA10: =Z10-Z9 -> 0 | AB10: =SUM(Y10*$AB$2) -> 0 | AC10: =AC9 -> 1944 | AD10: =AC10-AC9 -> 0 | AE10: =AE9 -> 366312 | AF10: =AE10-AE9 -> 0 | AG10: =IF(AD10>0,AF10/AD10,0) -> 0 | AH10: =AF10+AA10 -> 0 | AI10: =SUM(AH10+V10) -> 0 | AJ10: =-tanks!AW11 -> 0 | AK10: =SUM(AJ10-AI10) -> 0 | AL10: =S10+L10+G10 -> 0 | AM10: =Y10+AD10 -> 0 | AN10: =AN9 -> 65 | AO10: =(AN10/100)*3000 -> 1950 | AP10: =AP9 -> 55 | AQ10: =(AP10/100)*3000 -> 1650 | AR10: =AR9 -> 61 | AS10: =(AR10/100)*3000 -> 1830 | AT10: =SUM(AO10+AQ10+AS10) -> 5430 | AU10: =AT9-AT10+AV10 -> 0 | AX10: =IF(AV10>0,AW10,AX9) -> 0.8
A11: =ELEC!C10 -> 44688 | B11: =B10 -> 215 | C11: =C10 -> 222 | D11: =C10-C11 -> 0 | E11: =D11*8.38 -> 0 | F11: =F10 -> 2242 | G11: =F11-F10 -> 0 | H11: =H10 -> 43494 | I11: =SUM(H11-H10) -> 0 | J11: =IF(G11>0,I11/G11,0) -> 0 | K11: =K10 -> 2419 | L11: =K11-K10 -> 0 | M11: =M10 -> 179248 | N11: =M11-M10 -> 0 | O11: =O10 -> 1869 | P11: =P10 -> 2199 | Q11: =Q10 -> 183983 | R11: =Q11-Q10 -> 0 | S11: =SUM(P11-P10) -> 0 | T11: =SUM(S11*$T$2) -> 0 | U11: =SUM(G11+L11+S11) -> 0 | V11: =R11+N11+I11:I11 -> 0 | W11: =SUM(V11/U11) -> #DIV/0! | X11: =X10 -> 2477 | Y11: =X11-X10 -> 0 | Z11: =Z10 -> 139698 | AA11: =Z11-Z10 -> 0 | AB11: =SUM(Y11*$AB$2) -> 0 | AC11: =AC10 -> 1944 | AD11: =AC11-AC10 -> 0 | AE11: =AE10 -> 366312 | AF11: =AE11-AE10 -> 0 | AG11: =IF(AD11>0,AF11/AD11,0) -> 0 | AH11: =AF11+AA11 -> 0 | AI11: =SUM(AH11+V11) -> 0 | AJ11: =-tanks!AW12 -> 0 | AK11: =SUM(AJ11-AI11) -> 0 | AL11: =S11+L11+G11 -> 0 | AM11: =Y11+AD11 -> 0 | AN11: =AN10 -> 65 | AO11: =(AN11/100)*3000 -> 1950 | AP11: =AP10 -> 55 | AQ11: =(AP11/100)*3000 -> 1650 | AR11: =AR10 -> 61 | AS11: =(AR11/100)*3000 -> 1830 | AT11: =SUM(AO11+AQ11+AS11) -> 5430 | AU11: =AT10-AT11+AV11 -> 0 | AX11: =IF(AV11>0,AW11,AX10) -> 0.8
A12: =ELEC!C11 -> 44689 | B12: 249 | C12: 255 | D12: =C11-C12 -> -33 | E12: =D12*8.38 -> -276.54 | F12: =F11 -> 2242 | G12: =F12-F11 -> 0 | H12: =H11 -> 43494 | I12: =SUM(H12-H11) -> 0 | J12: =IF(G12>0,I12/G12,0) -> 0 | K12: 2421 | L12: =K12-K11 -> 2 | M12: 179434 | N12: =M12-M11 -> 186 | O12: =O11 -> 1869 | P12: =P11 -> 2199 | Q12: =Q11 -> 183983 | R12: =Q12-Q11 -> 0 | S12: =SUM(P12-P11) -> 0 | T12: =SUM(S12*$T$2) -> 0 | U12: =SUM(G12+L12+S12) -> 2 | V12: =R12+N12+I12:I12 -> 186 | W12: =SUM(V12/U12) -> 93 | X12: 2478 | Y12: =X12-X11 -> 1 | Z12: 139771 | AA12: =Z12-Z11 -> 73 | AB12: =SUM(Y12*$AB$2) -> 0 | AC12: =AC11 -> 1944 | AD12: =AC12-AC11 -> 0 | AE12: =AE11 -> 366312 | AF12: =AE12-AE11 -> 0 | AG12: =IF(AD12>0,AF12/AD12,0) -> 0 | AH12: =AF12+AA12 -> 73 | AI12: =SUM(AH12+V12) -> 259 | AJ12: =-tanks!AW13 -> 259 | AK12: =SUM(AJ12-AI12) -> 0 | AL12: =S12+L12+G12 -> 2 | AM12: =Y12+AD12 -> 1 | AN12: =AN11 -> 65 | AO12: =(AN12/100)*3000 -> 1950 | AP12: =AP11 -> 55 | AQ12: =(AP12/100)*3000 -> 1650 | AR12: =AR11 -> 61 | AS12: =(AR12/100)*3000 -> 1830 | AT12: =SUM(AO12+AQ12+AS12) -> 5430 | AU12: =AT11-AT12+AV12 -> 0 | AX12: =IF(AV12>0,AW12,AX11) -> 0.8
A13: =ELEC!C12 -> 44690 | B13: 245 | C13: 251 | D13: =C12-C13 -> 4 | E13: =D13*8.38 -> 33.52 | F13: =F12 -> 2242 | G13: =F13-F12 -> 0 | H13: =H12 -> 43494 | I13: =SUM(H13-H12) -> 0 | J13: =IF(G13>0,I13/G13,0) -> 0 | K13: 2422 | L13: =K13-K12 -> 1 | M13: 179535 | N13: =M13-M12 -> 101 | O13: =O12 -> 1869 | P13: =P12 -> 2199 | Q13: =Q12 -> 183983 | R13: =Q13-Q12 -> 0 | S13: =SUM(P13-P12) -> 0 | T13: =SUM(S13*$T$2) -> 0 | U13: =SUM(G13+L13+S13) -> 1 | V13: =R13+N13+I13:I13 -> 101 | W13: =SUM(V13/U13) -> 101 | X13: =X12 -> 2478 | Y13: =X13-X12 -> 0 | Z13: =Z12 -> 139771 | AA13: =Z13-Z12 -> 0 | AB13: =SUM(Y13*$AB$2) -> 0 | AC13: =AC12 -> 1944 | AD13: =AC13-AC12 -> 0 | AE13: =AE12 -> 366312 | AF13: =AE13-AE12 -> 0 | AG13: =IF(AD13>0,AF13/AD13,0) -> 0 | AH13: =AF13+AA13 -> 0 | AI13: =SUM(AH13+V13) -> 101 | AJ13: =-tanks!AW14 -> 101 | AK13: =SUM(AJ13-AI13) -> 0 | AL13: =S13+L13+G13 -> 1 | AM13: =Y13+AD13 -> 0 | AN13: =AN12 -> 65 | AO13: =(AN13/100)*3000 -> 1950 | AP13: =AP12 -> 55 | AQ13: =(AP13/100)*3000 -> 1650 | AR13: =AR12 -> 61 | AS13: =(AR13/100)*3000 -> 1830 | AT13: =SUM(AO13+AQ13+AS13) -> 5430 | AU13: =AT12-AT13+AV13 -> 0 | AX13: =IF(AV13>0,AW13,AX12) -> 0.8
A14: =ELEC!C13 -> 44691 | B14: 242 | C14: 248 | D14: =C13-C14 -> 3 | E14: =D14*8.38 -> 25.14 | F14: =F13 -> 2242 | G14: =F14-F13 -> 0 | H14: =H13 -> 43494 | I14: =SUM(H14-H13) -> 0 | J14: =IF(G14>0,I14/G14,0) -> 0 | K14: 2423 | L14: =K14-K13 -> 1 | M14: 179580 | N14: =M14-M13 -> 45 | O14: =O13 -> 1869 | P14: =P13 -> 2199 | Q14: =Q13 -> 183983 | R14: =Q14-Q13 -> 0 | S14: =SUM(P14-P13) -> 0 | T14: =SUM(S14*$T$2) -> 0 | U14: =SUM(G14+L14+S14) -> 1 | V14: =R14+N14+I14:I14 -> 45 | W14: =SUM(V14/U14) -> 45 | X14: =X13 -> 2478 | Y14: =X14-X13 -> 0 | Z14: =Z13 -> 139771 | AA14: =Z14-Z13 -> 0 | AB14: =SUM(Y14*$AB$2) -> 0 | AC14: =AC13 -> 1944 | AD14: =AC14-AC13 -> 0 | AE14: =AE13 -> 366312 | AF14: =AE14-AE13 -> 0 | AG14: =IF(AD14>0,AF14/AD14,0) -> 0 | AH14: =AF14+AA14 -> 0 | AI14: =SUM(AH14+V14) -> 45 | AJ14: =-tanks!AW15 -> 45 | AK14: =SUM(AJ14-AI14) -> 0 | AL14: =S14+L14+G14 -> 1 | AM14: =Y14+AD14 -> 0 | AN14: =AN13 -> 65 | AO14: =(AN14/100)*3000 -> 1950 | AP14: =AP13 -> 55 | AQ14: =(AP14/100)*3000 -> 1650 | AR14: =AR13 -> 61 | AS14: =(AR14/100)*3000 -> 1830 | AT14: =SUM(AO14+AQ14+AS14) -> 5430 | AU14: =AT13-AT14+AV14 -> 0 | AX14: =IF(AV14>0,AW14,AX13) -> 0.8
A15: =ELEC!C14 -> 44692 | B15: 238 | C15: 244 | D15: =C14-C15 -> 4 | E15: =D15*8.38 -> 33.52 | F15: =F14 -> 2242 | G15: =F15-F14 -> 0 | H15: =H14 -> 43494 | I15: =SUM(H15-H14) -> 0 | J15: =IF(G15>0,I15/G15,0) -> 0 | K15: 2424 | L15: =K15-K14 -> 1 | M15: 179756 | N15: =M15-M14 -> 176 | O15: =O14 -> 1869 | P15: =P14 -> 2199 | Q15: 183999 | R15: =Q15-Q14 -> 16 | S15: =SUM(P15-P14) -> 0 | T15: =SUM(S15*$T$2) -> 0 | U15: =SUM(G15+L15+S15) -> 1 | V15: =R15+N15+I15:I15 -> 192 | W15: =SUM(V15/U15) -> 192 | X15: =X14 -> 2478 | Y15: =X15-X14 -> 0 | Z15: =Z14 -> 139771 | AA15: =Z15-Z14 -> 0 | AB15: =SUM(Y15*$AB$2) -> 0 | AC15: =AC14 -> 1944 | AD15: =AC15-AC14 -> 0 | AE15: =AE14 -> 366312 | AF15: =AE15-AE14 -> 0 | AG15: =IF(AD15>0,AF15/AD15,0) -> 0 | AH15: =AF15+AA15 -> 0 | AI15: =SUM(AH15+V15) -> 192 | AJ15: =-tanks!AW16 -> 192 | AK15: =SUM(AJ15-AI15) -> 0 | AL15: =S15+L15+G15 -> 1 | AM15: =Y15+AD15 -> 0 | AN15: =AN14 -> 65 | AO15: =(AN15/100)*3000 -> 1950 | AP15: =AP14 -> 55 | AQ15: =(AP15/100)*3000 -> 1650 | AR15: =AR14 -> 61 | AS15: =(AR15/100)*3000 -> 1830 | AT15: =SUM(AO15+AQ15+AS15) -> 5430 | AU15: =AT14-AT15+AV15 -> 0 | AX15: =IF(AV15>0,AW15,AX14) -> 0.8
A16: =ELEC!C15 -> 44693 | B16: 234 | C16: 240 | D16: =C15-C16 -> 4 | E16: =D16*8.38 -> 33.52 | F16: =F15 -> 2242 | G16: =F16-F15 -> 0 | H16: =H15 -> 43494 | I16: =SUM(H16-H15) -> 0 | J16: =IF(G16>0,I16/G16,0) -> 0 | K16: 2425 | L16: =K16-K15 -> 1 | M16: 179797 | N16: =M16-M15 -> 41 | O16: =O15 -> 1869 | P16: =P15 -> 2199 | Q16: =Q15 -> 183999 | R16: =Q16-Q15 -> 0 | S16: =SUM(P16-P15) -> 0 | T16: =SUM(S16*$T$2) -> 0 | U16: =SUM(G16+L16+S16) -> 1 | V16: =R16+N16+I16:I16 -> 41 | W16: =SUM(V16/U16) -> 41 | X16: 2479 | Y16: =X16-X15 -> 1 | Z16: 139861 | AA16: =Z16-Z15 -> 90 | AB16: =SUM(Y16*$AB$2) -> 0 | AC16: =AC15 -> 1944 | AD16: =AC16-AC15 -> 0 | AE16: =AE15 -> 366312 | AF16: =AE16-AE15 -> 0 | AG16: =IF(AD16>0,AF16/AD16,0) -> 0 | AH16: =AF16+AA16 -> 90 | AI16: =SUM(AH16+V16) -> 131 | AJ16: =-tanks!AW17 -> 131 | AK16: =SUM(AJ16-AI16) -> 0 | AL16: =S16+L16+G16 -> 1 | AM16: =Y16+AD16 -> 1 | AN16: =AN15 -> 65 | AO16: =(AN16/100)*3000 -> 1950 | AP16: =AP15 -> 55 | AQ16: =(AP16/100)*3000 -> 1650 | AR16: =AR15 -> 61 | AS16: =(AR16/100)*3000 -> 1830 | AT16: =SUM(AO16+AQ16+AS16) -> 5430 | AU16: =AT15-AT16+AV16 -> 0 | AX16: =IF(AV16>0,AW16,AX15) -> 0.8
A17: =ELEC!C16 -> 44694 | B17: =B16 -> 234 | C17: =C16 -> 240 | D17: =C16-C17 -> 0 | E17: =D17*8.38 -> 0 | F17: =F16 -> 2242 | G17: =F17-F16 -> 0 | H17: =H16 -> 43494 | I17: =SUM(H17-H16) -> 0 | J17: =IF(G17>0,I17/G17,0) -> 0 | K17: =K16 -> 2425 | L17: =K17-K16 -> 0 | M17: =M16 -> 179797 | N17: =M17-M16 -> 0 | O17: =O16 -> 1869 | P17: =P16 -> 2199 | Q17: =Q16 -> 183999 | R17: =Q17-Q16 -> 0 | S17: =SUM(P17-P16) -> 0 | T17: =SUM(S17*$T$2) -> 0 | U17: =SUM(G17+L17+S17) -> 0 | V17: =R17+N17+I17:I17 -> 0 | X17: =X16 -> 2479 | Y17: =X17-X16 -> 0 | Z17: =Z16 -> 139861 | AA17: =Z17-Z16 -> 0 | AB17: =SUM(Y17*$AB$2) -> 0 | AC17: =AC16 -> 1944 | AD17: =AC17-AC16 -> 0 | AE17: =AE16 -> 366312 | AF17: =AE17-AE16 -> 0 | AG17: =IF(AD17>0,AF17/AD17,0) -> 0 | AH17: =AF17+AA17 -> 0 | AI17: =SUM(AH17+V17) -> 0 | AJ17: =-tanks!AW18 -> 0 | AK17: =SUM(AJ17-AI17) -> 0 | AL17: =S17+L17+G17 -> 0 | AM17: =Y17+AD17 -> 0 | AN17: =AN16 -> 65 | AO17: =(AN17/100)*3000 -> 1950 | AP17: =AP16 -> 55 | AQ17: =(AP17/100)*3000 -> 1650 | AR17: =AR16 -> 61 | AS17: =(AR17/100)*3000 -> 1830 | AT17: =SUM(AO17+AQ17+AS17) -> 5430 | AU17: =AT16-AT17+AV17 -> 0 | AX17: =IF(AV17>0,AW17,AX16) -> 0.8
A18: =ELEC!C17 -> 44695 | B18: =B17 -> 234 | C18: =C17 -> 240 | D18: =C17-C18 -> 0 | E18: =D18*8.38 -> 0 | F18: =F17 -> 2242 | G18: =F18-F17 -> 0 | H18: =H17 -> 43494 | I18: =SUM(H18-H17) -> 0 | J18: =IF(G18>0,I18/G18,0) -> 0 | K18: =K17 -> 2425 | L18: =K18-K17 -> 0 | M18: =M17 -> 179797 | N18: =M18-M17 -> 0 | O18: 1869 | P18: =P17 -> 2199 | Q18: =Q17 -> 183999 | R18: =Q18-Q17 -> 0 | S18: =SUM(P18-P17) -> 0 | T18: =SUM(S18*$T$2) -> 0 | U18: =SUM(G18+L18+S18) -> 0 | V18: =R18+N18+I18:I18 -> 0 | X18: =X17 -> 2479 | Y18: =X18-X17 -> 0 | Z18: =Z17 -> 139861 | AA18: =Z18-Z17 -> 0 | AB18: =SUM(Y18*$AB$2) -> 0 | AC18: =AC17 -> 1944 | AD18: =AC18-AC17 -> 0 | AE18: =AE17 -> 366312 | AF18: =AE18-AE17 -> 0 | AG18: =IF(AD18>0,AF18/AD18,0) -> 0 | AH18: =AF18+AA18 -> 0 | AI18: =SUM(AH18+V18) -> 0 | AJ18: =-tanks!AW19 -> 0 | AK18: =SUM(AJ18-AI18) -> 0 | AL18: =S18+L18+G18 -> 0 | AM18: =Y18+AD18 -> 0 | AN18: =AN17 -> 65 | AO18: =(AN18/100)*3000 -> 1950 | AP18: =AP17 -> 55 | AQ18: =(AP18/100)*3000 -> 1650 | AR18: =AR17 -> 61 | AS18: =(AR18/100)*3000 -> 1830 | AT18: =SUM(AO18+AQ18+AS18) -> 5430 | AU18: =AT17-AT18+AV18 -> 0 | AX18: =IF(AV18>0,AW18,AX17) -> 0.8
A19: =ELEC!C18 -> 44696 | B19: =B18 -> 234 | C19: =C18 -> 240 | D19: =C18-C19 -> 0 | E19: =D19*8.38 -> 0 | F19: =F18 -> 2242 | G19: =F19-F18 -> 0 | H19: =H18 -> 43494 | I19: =SUM(H19-H18) -> 0 | J19: =IF(G19>0,I19/G19,0) -> 0 | K19: =K18 -> 2425 | L19: =K19-K18 -> 0 | M19: =M18 -> 179797 | N19: =M19-M18 -> 0 | O19: =O18 -> 1869 | P19: =P18 -> 2199 | Q19: =Q18 -> 183999 | R19: =Q19-Q18 -> 0 | S19: =SUM(P19-P18) -> 0 | T19: =SUM(S19*$T$2) -> 0 | U19: =SUM(G19+L19+S19) -> 0 | V19: =R19+N19+I19:I19 -> 0 | X19: =X18 -> 2479 | Y19: =X19-X18 -> 0 | Z19: =Z18 -> 139861 | AA19: =Z19-Z18 -> 0 | AB19: =SUM(Y19*$AB$2) -> 0 | AC19: =AC18 -> 1944 | AD19: =AC19-AC18 -> 0 | AE19: =AE18 -> 366312 | AF19: =AE19-AE18 -> 0 | AG19: =IF(AD19>0,AF19/AD19,0) -> 0 | AH19: =AF19+AA19 -> 0 | AI19: =SUM(AH19+V19) -> 0 | AJ19: =-tanks!AW20 -> 0 | AK19: =SUM(AJ19-AI19) -> 0 | AL19: =S19+L19+G19 -> 0 | AM19: =Y19+AD19 -> 0 | AN19: =AN18 -> 65 | AO19: =(AN19/100)*3000 -> 1950 | AP19: =AP18 -> 55 | AQ19: =(AP19/100)*3000 -> 1650 | AR19: =AR18 -> 61 | AS19: =(AR19/100)*3000 -> 1830 | AT19: =SUM(AO19+AQ19+AS19) -> 5430 | AU19: =AT18-AT19+AV19 -> 0 | AX19: =IF(AV19>0,AW19,AX18) -> 0.8
A20: =ELEC!C19 -> 44697 | B20: =B19 -> 234 | C20: =C19 -> 240 | D20: =C19-C20 -> 0 | E20: =D20*8.38 -> 0 | F20: =F19 -> 2242 | G20: =F20-F19 -> 0 | H20: =H19 -> 43494 | I20: =SUM(H20-H19) -> 0 | J20: =IF(G20>0,I20/G20,0) -> 0 | K20: =K19 -> 2425 | L20: =K20-K19 -> 0 | M20: =M19 -> 179797 | N20: =M20-M19 -> 0 | O20: =O19 -> 1869 | P20: =P19 -> 2199 | Q20: =Q19 -> 183999 | R20: =Q20-Q19 -> 0 | S20: =SUM(P20-P19) -> 0 | T20: =SUM(S20*$T$2) -> 0 | U20: =SUM(G20+L20+S20) -> 0 | V20: =R20+N20+I20:I20 -> 0 | X20: =X19 -> 2479 | Y20: =X20-X19 -> 0 | Z20: =Z19 -> 139861 | AA20: =Z20-Z19 -> 0 | AB20: =SUM(Y20*$AB$2) -> 0 | AC20: =AC19 -> 1944 | AD20: =AC20-AC19 -> 0 | AE20: =AE19 -> 366312 | AF20: =AE20-AE19 -> 0 | AG20: =IF(AD20>0,AF20/AD20,0) -> 0 | AH20: =AF20+AA20 -> 0 | AI20: =SUM(AH20+V20) -> 0 | AJ20: =-tanks!AW21 -> 0 | AK20: =SUM(AJ20-AI20) -> 0 | AL20: =S20+L20+G20 -> 0 | AM20: =Y20+AD20 -> 0 | AN20: =AN19 -> 65 | AO20: =(AN20/100)*3000 -> 1950 | AP20: =AP19 -> 55 | AQ20: =(AP20/100)*3000 -> 1650 | AR20: =AR19 -> 61 | AS20: =(AR20/100)*3000 -> 1830 | AT20: =SUM(AO20+AQ20+AS20) -> 5430 | AU20: =AT19-AT20+AV20 -> 0 | AX20: =IF(AV20>0,AW20,AX19) -> 0.8
A21: =ELEC!C20 -> 44698 | B21: =B20 -> 234 | C21: =C20 -> 240 | D21: =C20-C21 -> 0 | E21: =D21*8.38 -> 0 | F21: =F20 -> 2242 | G21: =F21-F20 -> 0 | H21: =H20 -> 43494 | I21: =SUM(H21-H20) -> 0 | J21: =IF(G21>0,I21/G21,0) -> 0 | K21: =K20 -> 2425 | L21: =K21-K20 -> 0 | M21: =M20 -> 179797 | N21: =M21-M20 -> 0 | O21: =O20 -> 1869 | P21: =P20 -> 2199 | Q21: =Q20 -> 183999 | R21: =Q21-Q20 -> 0 | S21: =SUM(P21-P20) -> 0 | T21: =SUM(S21*$T$2) -> 0 | U21: =SUM(G21+L21+S21) -> 0 | V21: =R21+N21+I21:I21 -> 0 | X21: =X20 -> 2479 | Y21: =X21-X20 -> 0 | Z21: =Z20 -> 139861 | AA21: =Z21-Z20 -> 0 | AB21: =SUM(Y21*$AB$2) -> 0 | AC21: =AC20 -> 1944 | AD21: =AC21-AC20 -> 0 | AE21: =AE20 -> 366312 | AF21: =AE21-AE20 -> 0 | AG21: =IF(AD21>0,AF21/AD21,0) -> 0 | AH21: =AF21+AA21 -> 0 | AI21: =SUM(AH21+V21) -> 0 | AJ21: =-tanks!AW22 -> 0 | AK21: =SUM(AJ21-AI21) -> 0 | AL21: =S21+L21+G21 -> 0 | AM21: =Y21+AD21 -> 0 | AN21: =AN20 -> 65 | AO21: =(AN21/100)*3000 -> 1950 | AP21: =AP20 -> 55 | AQ21: =(AP21/100)*3000 -> 1650 | AR21: =AR20 -> 61 | AS21: =(AR21/100)*3000 -> 1830 | AT21: =SUM(AO21+AQ21+AS21) -> 5430 | AU21: =AT20-AT21+AV21 -> 0 | AX21: =IF(AV21>0,AW21,AX20) -> 0.8
A22: =ELEC!C21 -> 44699 | B22: =B21 -> 234 | C22: =C21 -> 240 | D22: =C21-C22 -> 0 | E22: =D22*8.38 -> 0 | F22: =F21 -> 2242 | G22: =F22-F21 -> 0 | H22: =H21 -> 43494 | I22: =SUM(H22-H21) -> 0 | J22: =IF(G22>0,I22/G22,0) -> 0 | K22: =K21 -> 2425 | L22: =K22-K21 -> 0 | M22: =M21 -> 179797 | N22: =M22-M21 -> 0 | O22: =O21 -> 1869 | P22: =P21 -> 2199 | Q22: =Q21 -> 183999 | R22: =Q22-Q21 -> 0 | S22: =SUM(P22-P21) -> 0 | T22: =SUM(S22*$T$2) -> 0 | U22: =SUM(G22+L22+S22) -> 0 | V22: =R22+N22+I22:I22 -> 0 | X22: =X21 -> 2479 | Y22: =X22-X21 -> 0 | Z22: =Z21 -> 139861 | AA22: =Z22-Z21 -> 0 | AB22: =SUM(Y22*$AB$2) -> 0 | AC22: =AC21 -> 1944 | AD22: =AC22-AC21 -> 0 | AE22: =AE21 -> 366312 | AF22: =AE22-AE21 -> 0 | AG22: =IF(AD22>0,AF22/AD22,0) -> 0 | AH22: =AF22+AA22 -> 0 | AI22: =SUM(AH22+V22) -> 0 | AJ22: =-tanks!AW23 -> 0 | AK22: =SUM(AJ22-AI22) -> 0 | AL22: =S22+L22+G22 -> 0 | AM22: =Y22+AD22 -> 0 | AN22: =AN21 -> 65 | AO22: =(AN22/100)*3000 -> 1950 | AP22: =AP21 -> 55 | AQ22: =(AP22/100)*3000 -> 1650 | AR22: =AR21 -> 61 | AS22: =(AR22/100)*3000 -> 1830 | AT22: =SUM(AO22+AQ22+AS22) -> 5430 | AU22: =AT21-AT22+AV22 -> 0 | AX22: =IF(AV22>0,AW22,AX21) -> 0.8
A23: =ELEC!C22 -> 44700 | B23: =B22 -> 234 | C23: =C22 -> 240 | D23: =C22-C23 -> 0 | E23: =D23*8.38 -> 0 | F23: =F22 -> 2242 | G23: =F23-F22 -> 0 | H23: =H22 -> 43494 | I23: =SUM(H23-H22) -> 0 | J23: =IF(G23>0,I23/G23,0) -> 0 | K23: =K22 -> 2425 | L23: =K23-K22 -> 0 | M23: =M22 -> 179797 | N23: =M23-M22 -> 0 | O23: =O22 -> 1869 | P23: =P22 -> 2199 | Q23: =Q22 -> 183999 | R23: =Q23-Q22 -> 0 | S23: =SUM(P23-P22) -> 0 | T23: =SUM(S23*$T$2) -> 0 | U23: =SUM(G23+L23+S23) -> 0 | V23: =R23+N23+I23:I23 -> 0 | X23: =X22 -> 2479 | Y23: =X23-X22 -> 0 | Z23: =Z22 -> 139861 | AA23: =Z23-Z22 -> 0 | AB23: =SUM(Y23*$AB$2) -> 0 | AC23: =AC22 -> 1944 | AD23: =AC23-AC22 -> 0 | AE23: =AE22 -> 366312 | AF23: =AE23-AE22 -> 0 | AG23: =IF(AD23>0,AF23/AD23,0) -> 0 | AH23: =AF23+AA23 -> 0 | AI23: =SUM(AH23+V23) -> 0 | AJ23: =-tanks!AW24 -> 0 | AK23: =SUM(AJ23-AI23) -> 0 | AL23: =S23+L23+G23 -> 0 | AM23: =Y23+AD23 -> 0 | AN23: =AN22 -> 65 | AO23: =(AN23/100)*3000 -> 1950 | AP23: =AP22 -> 55 | AQ23: =(AP23/100)*3000 -> 1650 | AR23: =AR22 -> 61 | AS23: =(AR23/100)*3000 -> 1830 | AT23: =SUM(AO23+AQ23+AS23) -> 5430 | AU23: =AT22-AT23+AV23 -> 0 | AX23: =IF(AV23>0,AW23,AX22) -> 0.8
A24: =ELEC!C23 -> 44701 | B24: =B23 -> 234 | C24: =C23 -> 240 | D24: =C23-C24 -> 0 | E24: =D24*8.38 -> 0 | F24: =F23 -> 2242 | G24: =F24-F23 -> 0 | H24: =H23 -> 43494 | I24: =SUM(H24-H23) -> 0 | J24: =IF(G24>0,I24/G24,0) -> 0 | K24: =K23 -> 2425 | L24: =K24-K23 -> 0 | M24: =M23 -> 179797 | N24: =M24-M23 -> 0 | O24: =O23 -> 1869 | P24: =P23 -> 2199 | Q24: =Q23 -> 183999 | R24: =Q24-Q23 -> 0 | S24: =SUM(P24-P23) -> 0 | T24: =SUM(S24*$T$2) -> 0 | U24: =SUM(G24+L24+S24) -> 0 | V24: =R24+N24+I24:I24 -> 0 | X24: =X23 -> 2479 | Y24: =X24-X23 -> 0 | Z24: =Z23 -> 139861 | AA24: =Z24-Z23 -> 0 | AB24: =SUM(Y24*$AB$2) -> 0 | AC24: =AC23 -> 1944 | AD24: =AC24-AC23 -> 0 | AE24: =AE23 -> 366312 | AF24: =AE24-AE23 -> 0 | AG24: =IF(AD24>0,AF24/AD24,0) -> 0 | AH24: =AF24+AA24 -> 0 | AI24: =SUM(AH24+V24) -> 0 | AJ24: =-tanks!AW25 -> 0 | AK24: =SUM(AJ24-AI24) -> 0 | AL24: =S24+L24+G24 -> 0 | AM24: =Y24+AD24 -> 0 | AN24: =AN23 -> 65 | AO24: =(AN24/100)*3000 -> 1950 | AP24: =AP23 -> 55 | AQ24: =(AP24/100)*3000 -> 1650 | AR24: =AR23 -> 61 | AS24: =(AR24/100)*3000 -> 1830 | AT24: =SUM(AO24+AQ24+AS24) -> 5430 | AU24: =AT23-AT24+AV24 -> 0 | AX24: =IF(AV24>0,AW24,AX23) -> 0.8
A25: =ELEC!C24 -> 44702 | B25: =B24 -> 234 | C25: =C24 -> 240 | D25: =C24-C25 -> 0 | E25: =D25*8.38 -> 0 | F25: =F24 -> 2242 | G25: =F25-F24 -> 0 | H25: =H24 -> 43494 | I25: =SUM(H25-H24) -> 0 | J25: =IF(G25>0,I25/G25,0) -> 0 | K25: =K24 -> 2425 | L25: =K25-K24 -> 0 | M25: =M24 -> 179797 | N25: =M25-M24 -> 0 | O25: =O24 -> 1869 | P25: =P24 -> 2199 | Q25: =Q24 -> 183999 | R25: =Q25-Q24 -> 0 | S25: =SUM(P25-P24) -> 0 | T25: =SUM(S25*$T$2) -> 0 | U25: =SUM(G25+L25+S25) -> 0 | V25: =R25+N25+I25:I25 -> 0 | X25: =X24 -> 2479 | Y25: =X25-X24 -> 0 | Z25: =Z24 -> 139861 | AA25: =Z25-Z24 -> 0 | AB25: =SUM(Y25*$AB$2) -> 0 | AC25: 1944 | AD25: =AC25-AC24 -> 0 | AE25: =AE24 -> 366312 | AF25: =AE25-AE24 -> 0 | AG25: =IF(AD25>0,AF25/AD25,0) -> 0 | AH25: =AF25+AA25 -> 0 | AI25: =SUM(AH25+V25) -> 0 | AJ25: =-tanks!AW26 -> 0 | AK25: =SUM(AJ25-AI25) -> 0 | AL25: =S25+L25+G25 -> 0 | AM25: =Y25+AD25 -> 0 | AN25: =AN24 -> 65 | AO25: =(AN25/100)*3000 -> 1950 | AP25: =AP24 -> 55 | AQ25: =(AP25/100)*3000 -> 1650 | AR25: =AR24 -> 61 | AS25: =(AR25/100)*3000 -> 1830 | AT25: =SUM(AO25+AQ25+AS25) -> 5430 | AU25: =AT24-AT25+AV25 -> 0 | AX25: =IF(AV25>0,AW25,AX24) -> 0.8
A26: =ELEC!C25 -> 44703 | B26: =B25 -> 234 | C26: =C25 -> 240 | D26: =C25-C26 -> 0 | E26: =D26*8.38 -> 0 | F26: =F25 -> 2242 | G26: =F26-F25 -> 0 | H26: =H25 -> 43494 | I26: =SUM(H26-H25) -> 0 | J26: =IF(G26>0,I26/G26,0) -> 0 | K26: =K25 -> 2425 | L26: =K26-K25 -> 0 | M26: =M25 -> 179797 | N26: =M26-M25 -> 0 | O26: =O25 -> 1869 | P26: =P25 -> 2199 | Q26: =Q25 -> 183999 | R26: =Q26-Q25 -> 0 | S26: =SUM(P26-P25) -> 0 | T26: =SUM(S26*$T$2) -> 0 | U26: =SUM(G26+L26+S26) -> 0 | V26: =R26+N26+I26:I26 -> 0 | X26: =X25 -> 2479 | Y26: =X26-X25 -> 0 | Z26: =Z25 -> 139861 | AA26: =Z26-Z25 -> 0 | AB26: =SUM(Y26*$AB$2) -> 0 | AC26: =AC25 -> 1944 | AD26: =AC26-AC25 -> 0 | AE26: =AE25 -> 366312 | AF26: =AE26-AE25 -> 0 | AG26: =IF(AD26>0,AF26/AD26,0) -> 0 | AH26: =AF26+AA26 -> 0 | AI26: =SUM(AH26+V26) -> 0 | AJ26: =-tanks!AW27 -> 0 | AK26: =SUM(AJ26-AI26) -> 0 | AL26: =S26+L26+G26 -> 0 | AM26: =Y26+AD26 -> 0 | AN26: =AN25 -> 65 | AO26: =(AN26/100)*3000 -> 1950 | AP26: =AP25 -> 55 | AQ26: =(AP26/100)*3000 -> 1650 | AR26: =AR25 -> 61 | AS26: =(AR26/100)*3000 -> 1830 | AT26: =SUM(AO26+AQ26+AS26) -> 5430 | AU26: =AT25-AT26+AV26 -> 0 | AX26: =IF(AV26>0,AW26,AX25) -> 0.8
A27: =ELEC!C26 -> 44704 | B27: =B26 -> 234 | C27: =C26 -> 240 | D27: =C26-C27 -> 0 | E27: =D27*8.38 -> 0 | F27: =F26 -> 2242 | G27: =F27-F26 -> 0 | H27: =H26 -> 43494 | I27: =SUM(H27-H26) -> 0 | J27: =IF(G27>0,I27/G27,0) -> 0 | K27: =K26 -> 2425 | L27: =K27-K26 -> 0 | M27: =M26 -> 179797 | N27: =M27-M26 -> 0 | O27: =O26 -> 1869 | P27: =P26 -> 2199 | Q27: =Q26 -> 183999 | R27: =Q27-Q26 -> 0 | S27: =SUM(P27-P26) -> 0 | T27: =SUM(S27*$T$2) -> 0 | U27: =SUM(G27+L27+S27) -> 0 | V27: =R27+N27+I27:I27 -> 0 | X27: =X26 -> 2479 | Y27: =X27-X26 -> 0 | Z27: =Z26 -> 139861 | AA27: =Z27-Z26 -> 0 | AB27: =SUM(Y27*$AB$2) -> 0 | AC27: =AC26 -> 1944 | AD27: =AC27-AC26 -> 0 | AE27: =AE26 -> 366312 | AF27: =AE27-AE26 -> 0 | AG27: =IF(AD27>0,AF27/AD27,0) -> 0 | AH27: =AF27+AA27 -> 0 | AI27: =SUM(AH27+V27) -> 0 | AJ27: =-tanks!AW28 -> 0 | AK27: =SUM(AJ27-AI27) -> 0 | AL27: =S27+L27+G27 -> 0 | AM27: =Y27+AD27 -> 0 | AN27: =AN26 -> 65 | AO27: =(AN27/100)*3000 -> 1950 | AP27: =AP26 -> 55 | AQ27: =(AP27/100)*3000 -> 1650 | AR27: =AR26 -> 61 | AS27: =(AR27/100)*3000 -> 1830 | AT27: =SUM(AO27+AQ27+AS27) -> 5430 | AU27: =AT26-AT27+AV27 -> 0 | AX27: =IF(AV27>0,AW27,AX26) -> 0.8
A28: =ELEC!C27 -> 44705 | B28: =B27 -> 234 | C28: =C27 -> 240 | D28: =C27-C28 -> 0 | E28: =D28*8.38 -> 0 | F28: =F27 -> 2242 | G28: =F28-F27 -> 0 | H28: =H27 -> 43494 | I28: =SUM(H28-H27) -> 0 | J28: =IF(G28>0,I28/G28,0) -> 0 | K28: =K27 -> 2425 | L28: =K28-K27 -> 0 | M28: =M27 -> 179797 | N28: =M28-M27 -> 0 | O28: =O27 -> 1869 | P28: =P27 -> 2199 | Q28: =Q27 -> 183999 | R28: =Q28-Q27 -> 0 | S28: =SUM(P28-P27) -> 0 | T28: =SUM(S28*$T$2) -> 0 | U28: =SUM(G28+L28+S28) -> 0 | V28: =R28+N28+I28:I28 -> 0 | X28: =X27 -> 2479 | Y28: =X28-X27 -> 0 | Z28: =Z27 -> 139861 | AA28: =Z28-Z27 -> 0 | AB28: =SUM(Y28*$AB$2) -> 0 | AC28: =AC27 -> 1944 | AD28: =AC28-AC27 -> 0 | AE28: =AE27 -> 366312 | AF28: =AE28-AE27 -> 0 | AG28: =IF(AD28>0,AF28/AD28,0) -> 0 | AH28: =AF28+AA28 -> 0 | AI28: =SUM(AH28+V28) -> 0 | AJ28: =-tanks!AW29 -> 0 | AK28: =SUM(AJ28-AI28) -> 0 | AL28: =S28+L28+G28 -> 0 | AM28: =Y28+AD28 -> 0 | AN28: =AN27 -> 65 | AO28: =(AN28/100)*3000 -> 1950 | AP28: =AP27 -> 55 | AQ28: =(AP28/100)*3000 -> 1650 | AR28: =AR27 -> 61 | AS28: =(AR28/100)*3000 -> 1830 | AT28: =SUM(AO28+AQ28+AS28) -> 5430 | AU28: =AT27-AT28+AV28 -> 0 | AX28: =IF(AV28>0,AW28,AX27) -> 0.8
A29: =ELEC!C28 -> 44706 | B29: =B28 -> 234 | C29: =C28 -> 240 | D29: =C28-C29 -> 0 | E29: =D29*8.38 -> 0 | F29: =F28 -> 2242 | G29: =F29-F28 -> 0 | H29: =H28 -> 43494 | I29: =SUM(H29-H28) -> 0 | J29: =IF(G29>0,I29/G29,0) -> 0 | K29: =K28 -> 2425 | L29: =K29-K28 -> 0 | M29: =M28 -> 179797 | N29: =M29-M28 -> 0 | O29: =O28 -> 1869 | P29: =P28 -> 2199 | Q29: =Q28 -> 183999 | R29: =Q29-Q28 -> 0 | S29: =SUM(P29-P28) -> 0 | T29: =SUM(S29*$T$2) -> 0 | U29: =SUM(G29+L29+S29) -> 0 | V29: =R29+N29+I29:I29 -> 0 | X29: =X28 -> 2479 | Y29: =X29-X28 -> 0 | Z29: =Z28 -> 139861 | AA29: =Z29-Z28 -> 0 | AB29: =SUM(Y29*$AB$2) -> 0 | AC29: =AC28 -> 1944 | AD29: =AC29-AC28 -> 0 | AE29: =AE28 -> 366312 | AF29: =AE29-AE28 -> 0 | AG29: =IF(AD29>0,AF29/AD29,0) -> 0 | AH29: =AF29+AA29 -> 0 | AI29: =SUM(AH29+V29) -> 0 | AJ29: =-tanks!AW30 -> 0 | AK29: =SUM(AJ29-AI29) -> 0 | AL29: =S29+L29+G29 -> 0 | AM29: =Y29+AD29 -> 0 | AN29: =AN28 -> 65 | AO29: =(AN29/100)*3000 -> 1950 | AP29: =AP28 -> 55 | AQ29: =(AP29/100)*3000 -> 1650 | AR29: =AR28 -> 61 | AS29: =(AR29/100)*3000 -> 1830 | AT29: =SUM(AO29+AQ29+AS29) -> 5430 | AU29: =AT28-AT29+AV29 -> 0 | AX29: =IF(AV29>0,AW29,AX28) -> 0.8
A30: =ELEC!C29 -> 44707 | B30: =B29 -> 234 | C30: =C29 -> 240 | D30: =C29-C30 -> 0 | E30: =D30*8.38 -> 0 | F30: =F29 -> 2242 | G30: =F30-F29 -> 0 | H30: =H29 -> 43494 | I30: =SUM(H30-H29) -> 0 | J30: =IF(G30>0,I30/G30,0) -> 0 | K30: =K29 -> 2425 | L30: =K30-K29 -> 0 | M30: =M29 -> 179797 | N30: =M30-M29 -> 0 | O30: =O29 -> 1869 | P30: =P29 -> 2199 | Q30: =Q29 -> 183999 | R30: =Q30-Q29 -> 0 | S30: =SUM(P30-P29) -> 0 | T30: =SUM(S30*$T$2) -> 0 | U30: =SUM(G30+L30+S30) -> 0 | V30: =R30+N30+I30:I30 -> 0 | X30: =X29 -> 2479 | Y30: =X30-X29 -> 0 | Z30: =Z29 -> 139861 | AA30: =Z30-Z29 -> 0 | AB30: =SUM(Y30*$AB$2) -> 0 | AC30: =AC29 -> 1944 | AD30: =AC30-AC29 -> 0 | AE30: =AE29 -> 366312 | AF30: =AE30-AE29 -> 0 | AG30: =IF(AD30>0,AF30/AD30,0) -> 0 | AH30: =AF30+AA30 -> 0 | AI30: =SUM(AH30+V30) -> 0 | AJ30: =-tanks!AW31 -> 0 | AK30: =SUM(AJ30-AI30) -> 0 | AL30: =S30+L30+G30 -> 0 | AM30: =Y30+AD30 -> 0 | AN30: =AN29 -> 65 | AO30: =(AN30/100)*3000 -> 1950 | AP30: =AP29 -> 55 | AQ30: =(AP30/100)*3000 -> 1650 | AR30: =AR29 -> 61 | AS30: =(AR30/100)*3000 -> 1830 | AT30: =SUM(AO30+AQ30+AS30) -> 5430 | AU30: =AT29-AT30+AV30 -> 0 | AX30: =IF(AV30>0,AW30,AX29) -> 0.8
A31: =ELEC!C30 -> 44708 | B31: =B30 -> 234 | C31: =C30 -> 240 | D31: =C30-C31 -> 0 | E31: =D31*8.38 -> 0 | F31: =F30 -> 2242 | G31: =F31-F30 -> 0 | H31: =H30 -> 43494 | I31: =SUM(H31-H30) -> 0 | J31: =IF(G31>0,I31/G31,0) -> 0 | K31: =K30 -> 2425 | L31: =K31-K30 -> 0 | M31: =M30 -> 179797 | N31: =M31-M30 -> 0 | O31: =O30 -> 1869 | P31: =P30 -> 2199 | Q31: =Q30 -> 183999 | R31: =Q31-Q30 -> 0 | S31: =SUM(P31-P30) -> 0 | T31: =SUM(S31*$T$2) -> 0 | U31: =SUM(G31+L31+S31) -> 0 | V31: =R31+N31+I31:I31 -> 0 | X31: =X30 -> 2479 | Y31: =X31-X30 -> 0 | Z31: =Z30 -> 139861 | AA31: =Z31-Z30 -> 0 | AB31: =SUM(Y31*$AB$2) -> 0 | AC31: =AC30 -> 1944 | AD31: =AC31-AC30 -> 0 | AE31: =AE30 -> 366312 | AF31: =AE31-AE30 -> 0 | AG31: =IF(AD31>0,AF31/AD31,0) -> 0 | AH31: =AF31+AA31 -> 0 | AI31: =SUM(AH31+V31) -> 0 | AJ31: =-tanks!AW32 -> 0 | AK31: =SUM(AJ31-AI31) -> 0 | AL31: =S31+L31+G31 -> 0 | AM31: =Y31+AD31 -> 0 | AN31: =AN30 -> 65 | AO31: =(AN31/100)*3000 -> 1950 | AP31: =AP30 -> 55 | AQ31: =(AP31/100)*3000 -> 1650 | AR31: =AR30 -> 61 | AS31: =(AR31/100)*3000 -> 1830 | AT31: =SUM(AO31+AQ31+AS31) -> 5430 | AU31: =AT30-AT31+AV31 -> 0 | AX31: =IF(AV31>0,AW31,AX30) -> 0.8
A32: =ELEC!C31 -> 44709 | B32: =B31 -> 234 | C32: =C31 -> 240 | D32: =C31-C32 -> 0 | E32: =D32*8.38 -> 0 | F32: =F31 -> 2242 | G32: =F32-F31 -> 0 | H32: =H31 -> 43494 | I32: =SUM(H32-H31) -> 0 | J32: =IF(G32>0,I32/G32,0) -> 0 | K32: =K31 -> 2425 | L32: =K32-K31 -> 0 | M32: =M31 -> 179797 | N32: =M32-M31 -> 0 | O32: =O31 -> 1869 | P32: =P31 -> 2199 | Q32: =Q31 -> 183999 | R32: =Q32-Q31 -> 0 | S32: =SUM(P32-P31) -> 0 | T32: =SUM(S32*$T$2) -> 0 | U32: =SUM(G32+L32+S32) -> 0 | V32: =R32+N32+I32:I32 -> 0 | X32: =X31 -> 2479 | Y32: =X32-X31 -> 0 | Z32: =Z31 -> 139861 | AA32: =Z32-Z31 -> 0 | AB32: =SUM(Y32*$AB$2) -> 0 | AC32: =AC31 -> 1944 | AD32: =AC32-AC31 -> 0 | AE32: =AE31 -> 366312 | AF32: =AE32-AE31 -> 0 | AG32: =IF(AD32>0,AF32/AD32,0) -> 0 | AH32: =AF32+AA32 -> 0 | AI32: =SUM(AH32+V32) -> 0 | AJ32: =-tanks!AW33 -> 0 | AK32: =SUM(AJ32-AI32) -> 0 | AL32: =S32+L32+G32 -> 0 | AM32: =Y32+AD32 -> 0 | AN32: =AN31 -> 65 | AO32: =(AN32/100)*3000 -> 1950 | AP32: =AP31 -> 55 | AQ32: =(AP32/100)*3000 -> 1650 | AR32: =AR31 -> 61 | AS32: =(AR32/100)*3000 -> 1830 | AT32: =SUM(AO32+AQ32+AS32) -> 5430 | AU32: =AT31-AT32+AV32 -> 0 | AX32: =IF(AV32>0,AW32,AX31) -> 0.8
A33: =ELEC!C32 -> 44710 | B33: =B32 -> 234 | C33: =C32 -> 240 | D33: =C32-C33 -> 0 | E33: =D33*8.38 -> 0 | F33: =F32 -> 2242 | G33: =F33-F32 -> 0 | H33: =H32 -> 43494 | I33: =SUM(H33-H32) -> 0 | J33: =IF(G33>0,I33/G33,0) -> 0 | K33: =K32 -> 2425 | L33: =K33-K32 -> 0 | M33: =M32 -> 179797 | N33: =M33-M32 -> 0 | O33: =O32 -> 1869 | P33: =P32 -> 2199 | Q33: =Q32 -> 183999 | R33: =Q33-Q32 -> 0 | S33: =SUM(P33-P32) -> 0 | T33: =SUM(S33*$T$2) -> 0 | U33: =SUM(G33+L33+S33) -> 0 | V33: =R33+N33+I33:I33 -> 0 | X33: =X32 -> 2479 | Y33: =X33-X32 -> 0 | Z33: =Z32 -> 139861 | AA33: =Z33-Z32 -> 0 | AB33: =SUM(Y33*$AB$2) -> 0 | AC33: =AC32 -> 1944 | AD33: =AC33-AC32 -> 0 | AE33: =AE32 -> 366312 | AF33: =AE33-AE32 -> 0 | AG33: =IF(AD33>0,AF33/AD33,0) -> 0 | AH33: =AF33+AA33 -> 0 | AI33: =SUM(AH33+V33) -> 0 | AJ33: =-tanks!AW34 -> 0 | AK33: =SUM(AJ33-AI33) -> 0 | AL33: =S33+L33+G33 -> 0 | AM33: =Y33+AD33 -> 0 | AN33: =AN32 -> 65 | AO33: =(AN33/100)*3000 -> 1950 | AP33: =AP32 -> 55 | AQ33: =(AP33/100)*3000 -> 1650 | AR33: =AR32 -> 61 | AS33: =(AR33/100)*3000 -> 1830 | AT33: =SUM(AO33+AQ33+AS33) -> 5430 | AU33: =AT32-AT33+AV33 -> 0 | AX33: =IF(AV33>0,AW33,AX32) -> 0.8
A34: =ELEC!C33 -> 44711 | B34: =B33 -> 234 | C34: =C33 -> 240 | D34: =C33-C34 -> 0 | E34: =D34*8.38 -> 0 | F34: =F33 -> 2242 | G34: =F34-F33 -> 0 | H34: =H33 -> 43494 | I34: =SUM(H34-H33) -> 0 | J34: =IF(G34>0,I34/G34,0) -> 0 | K34: =K33 -> 2425 | L34: =K34-K33 -> 0 | M34: =M33 -> 179797 | N34: =M34-M33 -> 0 | O34: =O33 -> 1869 | P34: =P33 -> 2199 | Q34: =Q33 -> 183999 | R34: =Q34-Q33 -> 0 | S34: =SUM(P34-P33) -> 0 | T34: =SUM(S34*$T$2) -> 0 | U34: =SUM(G34+L34+S34) -> 0 | V34: =R34+N34+I34:I34 -> 0 | X34: =X33 -> 2479 | Y34: =X34-X33 -> 0 | Z34: =Z33 -> 139861 | AA34: =Z34-Z33 -> 0 | AB34: =SUM(Y34*$AB$2) -> 0 | AC34: =AC33 -> 1944 | AD34: =AC34-AC33 -> 0 | AE34: =AE33 -> 366312 | AF34: =AE34-AE33 -> 0 | AG34: =IF(AD34>0,AF34/AD34,0) -> 0 | AH34: =AF34+AA34 -> 0 | AI34: =SUM(AH34+V34) -> 0 | AJ34: =-tanks!AW35 -> 0 | AK34: =SUM(AJ34-AI34) -> 0 | AL34: =S34+L34+G34 -> 0 | AM34: =Y34+AD34 -> 0 | AN34: =AN33 -> 65 | AO34: =(AN34/100)*3000 -> 1950 | AP34: =AP33 -> 55 | AQ34: =(AP34/100)*3000 -> 1650 | AR34: =AR33 -> 61 | AS34: =(AR34/100)*3000 -> 1830 | AT34: =SUM(AO34+AQ34+AS34) -> 5430 | AU34: =AT33-AT34+AV34 -> 0 | AX34: =IF(AV34>0,AW34,AX33) -> 0.8
A35: =ELEC!C34 -> 44712 | B35: =B34 -> 234 | C35: =C34 -> 240 | D35: =C34-C35 -> 0 | E35: =D35*8.38 -> 0 | F35: =F34 -> 2242 | G35: =F35-F34 -> 0 | H35: =H34 -> 43494 | I35: =SUM(H35-H34) -> 0 | J35: =IF(G35>0,I35/G35,0) -> 0 | K35: =K34 -> 2425 | L35: =K35-K34 -> 0 | M35: =M34 -> 179797 | N35: =M35-M34 -> 0 | O35: =O34 -> 1869 | P35: =P34 -> 2199 | Q35: =Q34 -> 183999 | R35: =Q35-Q34 -> 0 | S35: =SUM(P35-P34) -> 0 | T35: =SUM(S35*$T$2) -> 0 | U35: =SUM(G35+L35+S35) -> 0 | V35: =R35+N35+I35:I35 -> 0 | X35: =X34 -> 2479 | Y35: =X35-X34 -> 0 | Z35: =Z34 -> 139861 | AA35: =Z35-Z34 -> 0 | AB35: =SUM(Y35*$AB$2) -> 0 | AC35: =AC34 -> 1944 | AD35: =AC35-AC34 -> 0 | AE35: =AE34 -> 366312 | AF35: =AE35-AE34 -> 0 | AG35: =IF(AD35>0,AF35/AD35,0) -> 0 | AH35: =AF35+AA35 -> 0 | AI35: =SUM(AH35+V35) -> 0 | AJ35: =-tanks!AW36 -> 0 | AK35: =SUM(AJ35-AI35) -> 0 | AL35: =S35+L35+G35 -> 0 | AM35: =Y35+AD35 -> 0 | AN35: =AN34 -> 65 | AO35: =(AN35/100)*3000 -> 1950 | AP35: =AP34 -> 55 | AQ35: =(AP35/100)*3000 -> 1650 | AR35: =AR34 -> 61 | AS35: =(AR35/100)*3000 -> 1830 | AT35: =SUM(AO35+AQ35+AS35) -> 5430 | AU35: =AT34-AT35+AV35 -> 0 | AX35: =IF(AV35>0,AW35,AX34) -> 0.8
J36: =SUM(J5:J32)/(COUNT(J5:J32)-COUNTIF(J5:J32,0)) -> 1 | U36: =SUM(U5:U35) -> 13 | V36: =SUM(V5:V35) -> 1203 | AE36: . | AH36: =SUM(AH5:AH35) -> 163 | AL36: =SUM(AL5:AL35) -> 13 | AM36: =SUM(AM5:AM35) -> 2 | AR36: Nb Delivery | AS36: =COUNT(AW5:AW35) -> 0 | AU36: =SUM(AU5:AU35) -> 0 | AV36: =SUM(AV5:AV35) -> 0 | AW36: =SUM(AW5:AW35)/AS36 -> #DIV/0!
V37: =V36/U36 -> 92.538462 | AH37: =AF37+AA37 -> 0 | AI37: =SUM(AI5:AI35) -> 1366
AH38: =AF38+AA38 -> 0 | AU38: =AU36*0.51 -> 0 | AV38: =AV36/0.51 -> 0 | AW38: =SUM(AW5:AW32)/AS36 -> #DIV/0!
AV39: =AV36*0.51 -> 0

Sheet WATER
D1: =SUM(G21:G33) -> 8170266 | AR1: Entrance | AT1: Tank 1 | AV1: Tank 2
AR2: Level | AW2: Quantity CM3 | AZ2: Var
A3: Date | B3: Truck | C3: Truck M3/day | D3: N0. Trucks | F3: REQ. # of trucks | G3: City | H3: City/day | I3: Total water delivery | K3: SW | L3: Cosum SW/day | M3: RO Guest/ Liter | O3: RO K&L/ Liter | Q3: TOTAL RO Production | R3: RO 1 RH | S3: RO 2 RH | T3: RO water counter | U3: RO Cons m3 | V3: Steam Boiler | W3: Steam Boiler/day | X3: Softener Guest | Y3: Guest Sotf/day | Z3: Softener K&L | AA3: K&L Soft/Day | AB3: Fire Tank Level | AC3: Fire Tank Counter | AE3: Laundry Hot Water Counter | AF3: Hot Water Cons/day | AG3: Laundry Cold Water Counter | AH3: Cold Water Cons/day | AI3: Laundry Water Total Cons | AJ3: K&L Sotf/day | AK3: Guest / day | AL3: K&L /day | AM3: Avg Outside Temp | AN3: Banquet Activity | AR3: Date | AT3: MainI | AV3: Kitchen and Laundry | AX3: Guest | AY3: Main Tank | AZ3: Kitchen and Laundry | BA3: Guest | BB3: Kitchen and Laundry | BC3: Main | BD3: Guest | BE3: Total VAR | BF3: Hotel Consumption
E4: 1.66 | AN4: Ball R | AO4: Meeting | AP4: outlet | AT4: 180 | AV4: 220 | AX4: 580 | AY4: =SUM(AT4) -> 180 | AZ4: =SUM(AV4) -> 220 | BA4: =SUM(AX4) -> 580
A5: =[2]WATER!$A$35 -> 44681 | B5: =[2]WATER!B35 -> 109443 | C5: =[2]WATER!C35 -> 0 | D5: =[2]WATER!D35 -> 0 | E5: =[2]WATER!E35 -> 250 | F5: =[2]WATER!F35 -> 0 | G5: =[2]WATER!G35 -> 628184 | H5: =[2]WATER!H35 -> 0 | I5: =[2]WATER!I35 -> 0 | ... AP5: =[2]WATER!AP35 -> 0 | AR5: =[2]WATER!$AR$35 -> 44681 | AS5: =[2]WATER!AS35 -> 0.9 | AT5: =[2]WATER!AT35 -> 102 | AU5: =[2]WATER!AU35 -> 1.1 | AV5: =[2]WATER!AV35 -> 95 | AW5: =[2]WATER!AW35 -> 2.9 | AX5: =[2]WATER!AX35 -> 102 | AY5: =[2]WATER!AY35 -> 91.8 | AZ5: =[2]WATER!AZ35 -> 104.5 | ... BG5: =[2]WATER!BG35 -> 0
A6: =ELEC!C4 -> 44682 | B6: =B5 -> 109443 | C6: =B6-B5 -> 0 | D6: =C6/27 -> 0 | E6: =SUM((C6*$E$4)+(7500/'EDl log'!$A$37)) -> 241.93548 | G6: =G5 -> 628184 | H6: =G6-G5 -> 0 | I6: =C6+H6 -> 0 | J6: =IF(I6>0,E6/I6,0) -> 0 | K6: ='Swimming Pool quality check '!H6 -> 7073 | L6: 0 | M6: =M5 -> 457.44 | N6: =SUM(M6-M5) -> 0 | O6: =O5 -> 529.52 | P6: =SUM(O6-O5) -> 0 | Q6: =P6+N6 -> 0 | T6: =T5 -> 5182 | U6: =SUM(T6-T5) -> 0 | V6: =V5 -> 482 | W6: =+V6-V5 -> 0 | X6: =X5 -> 155276 | Y6: =SUM(X6-X5) -> 0 | Z6: =Z5 -> 99356 | AA6: =Z6-Z5 -> 0 | AB6: =AB5 -> 260 | AC6: =AC5 -> 790 | AD6: 0 | AE6: =AE5 -> 240.12 | AF6: =AE6-AE5 -> 0 | AG6: =AG5 -> 2222.14 | AH6: =AG6-AG5 -> 0 | AI6: =AF6+AH6 -> 0 | AJ6: =+Z6-Z5 -> 0 | AK6: =SUM(Y6-L6) -> 0 | AL6: =SUM(AJ6-W6) -> 0 | AM6: ='General information '!D5 -> 0 | AN6: ='General information '!H5 -> 0 | AP6: ='General information '!J5 -> 0 | AR6: =A6 -> 44682 | AS6: =AS5 -> 0.9 | AT6: =AT5 -> 102 | AU6: =AU5 -> 1.1 | AV6: =AV5 -> 95 | AW6: 2.9 | AX6: =AX5 -> 102 | AY6: =AS6*AT6 -> 91.8 | AZ6: =AU6*AV6 -> 104.5 | BA6: =AW6*AX6 -> 295.8 | BB6: =AY6-AY5 -> 0 | BC6: =AZ6-AZ5 -> 0 | BD6: =BA6-BA5 -> 0 | BE6: =SUM(BB6:BD6) -> 0 | BF6: =SUM(I6-BE6) -> 0 | BG6: =SUM(I6-BF6) -> 0
A7: =ELEC!C5 -> 44683 | B7: =B6 -> 109443 | C7: =B7-B6 -> 0 | D7: =C7/27 -> 0 | E7: =SUM((C7*$E$4)+(7500/'EDl log'!$A$37)) -> 241.93548 | G7: =G6 -> 628184 | H7: =G7-G6 -> 0 | I7: =C7+H7 -> 0 | J7: =IF(I7>0,E7/I7,0) -> 0 | K7: ='Swimming Pool quality check '!H7 -> 7073 | L7: =K7-K6 -> 0 | M7: =M6 -> 457.44 | N7: =SUM(M7-M6) -> 0 | O7: =O6 -> 529.52 | P7: =SUM(O7-O6) -> 0 | Q7: =P7+N7 -> 0 | T7: =T6 -> 5182 | U7: =SUM(T7-T6) -> 0 | V7: =V6 -> 482 | W7: =+V7-V6 -> 0 | X7: =X6 -> 155276 | Y7: =SUM(X7-X6) -> 0 | Z7: =Z6 -> 99356 | AA7: =Z7-Z6 -> 0 | AB7: =AB6 -> 260 | AC7: =AC6 -> 790 | AD7: =AC7-AC6 -> 0 | AE7: =AE6 -> 240.12 | AF7: =AE7-AE6 -> 0 | AG7: =AG6 -> 2222.14 | AH7: =AG7-AG6 -> 0 | AI7: =AF7+AH7 -> 0 | AJ7: =+Z7-Z6 -> 0 | AK7: =SUM(Y7-L7) -> 0 | AL7: =SUM(AJ7-W7) -> 0 | AM7: ='General information '!D6 -> 0 | AN7: ='General information '!H6 -> 0 | AP7: ='General information '!J6 -> 0 | AR7: =A7 -> 44683 | AS7: =AS6 -> 0.9 | AT7: =AT6 -> 102 | AU7: =AU6 -> 1.1 | AV7: =AV6 -> 95 | AW7: 2.9 | AX7: =AX6 -> 102 | AY7: =AS7*AT7 -> 91.8 | AZ7: =AU7*AV7 -> 104.5 | BA7: =AW7*AX7 -> 295.8 | BB7: =AY7-AY6 -> 0 | BC7: =AZ7-AZ6 -> 0 | BD7: =BA7-BA6 -> 0 | BE7: =SUM(BB7:BD7) -> 0 | BF7: =SUM(I7-BE7) -> 0 | BG7: =SUM(I7-BF7) -> 0
A8: =ELEC!C6 -> 44684 | B8: =B7 -> 109443 | C8: =B8-B7 -> 0 | D8: =C8/27 -> 0 | E8: =SUM((C8*$E$4)+(7500/'EDl log'!$A$37)) -> 241.93548 | G8: =G7 -> 628184 | H8: =G8-G7 -> 0 | I8: =C8+H8 -> 0 | J8: =IF(I8>0,E8/I8,0) -> 0 | K8: ='Swimming Pool quality check '!H8 -> 7073 | L8: =K8-K7 -> 0 | M8: =M7 -> 457.44 | N8: =SUM(M8-M7) -> 0 | O8: =O7 -> 529.52 | P8: =SUM(O8-O7) -> 0 | Q8: =P8+N8 -> 0 | T8: =T7 -> 5182 | U8: =SUM(T8-T7) -> 0 | V8: 489 | W8: =+V8-V7 -> 7 | X8: =X7 -> 155276 | Y8: =SUM(X8-X7) -> 0 | Z8: =Z7 -> 99356 | AA8: =Z8-Z7 -> 0 | AB8: =AB7 -> 260 | AC8: =AC7 -> 790 | AD8: =AC8-AC7 -> 0 | AE8: =AE7 -> 240.12 | AF8: =AE8-AE7 -> 0 | AG8: =AG7 -> 2222.14 | AH8: =AG8-AG7 -> 0 | AI8: =AF8+AH8 -> 0 | AJ8: =+Z8-Z7 -> 0 | AK8: =SUM(Y8-L8) -> 0 | AL8: =SUM(AJ8-W8) -> -7 | AM8: ='General information '!D7 -> 0 | AN8: ='General information '!H7 -> 0 | AP8: ='General information '!J7 -> 0 | AR8: =A8 -> 44684 | AS8: =AS7 -> 0.9 | AT8: =AT7 -> 102 | AU8: 1.1 | AV8: =AV7 -> 95 | AW8: 2.9 | AX8: =AX7 -> 102 | AY8: =AS8*AT8 -> 91.8 | AZ8: =AU8*AV8 -> 104.5 | BA8: =AW8*AX8 -> 295.8 | BB8: =AY8-AY7 -> 0 | BC8: =AZ8-AZ7 -> 0 | BD8: =BA8-BA7 -> 0 | BE8: =SUM(BB8:BD8) -> 0 | BF8: =SUM(I8-BE8) -> 0 | BG8: =SUM(I8-BF8) -> 0
A9: =ELEC!C7 -> 44685 | B9: 109443 | C9: =B9-B8 -> 0 | D9: =C9/27 -> 0 | E9: =SUM((C9*$E$4)+(7500/'EDl log'!$A$37)) -> 241.93548 | G9: =G8 -> 628184 | H9: =G9-G8 -> 0 | I9: =C9+H9 -> 0 | J9: =IF(I9>0,E9/I9,0) -> 0 | K9: ='Swimming Pool quality check '!H9 -> 7082 | L9: =K9-K8 -> 9 | M9: =M8 -> 457.44 | N9: =SUM(M9-M8) -> 0 | O9: =O8 -> 529.52 | P9: =SUM(O9-O8) -> 0 | Q9: =P9+N9 -> 0 | T9: =T8 -> 5182 | U9: =SUM(T9-T8) -> 0 | V9: 490 | W9: =+V9-V8 -> 1 | X9: =X8 -> 155276 | Y9: =SUM(X9-X8) -> 0 | Z9: =Z8 -> 99356 | AA9: =Z9-Z8 -> 0 | AB9: 283 | AC9: =AC8 -> 790 | AD9: =AC9-AC8 -> 0 | AE9: 242.22 | AF9: =AE9-AE8 -> 2.1 | AG9: 2229.76 | AH9: =AG9-AG8 -> 7.62 | AI9: =AF9+AH9 -> 9.72 | AJ9: =+Z9-Z8 -> 0 | AK9: =SUM(Y9-L9) -> -9 | AL9: =SUM(AJ9-W9) -> -1 | AM9: ='General information '!D8 -> 21 | AN9: ='General information '!H8 -> 0 | AP9: ='General information '!J8 -> 0 | AR9: =A9 -> 44685 | AS9: =AS8 -> 0.9 | AT9: 175 | AU9: =AU8 -> 1.1 | AV9: 84 | AW9: 2.9 | AX9: 99 | AY9: =AS9*AT9 -> 157.5 | AZ9: =AU9*AV9 -> 92.4 | BA9: =AW9*AX9 -> 287.1 | BB9: =AY9-AY8 -> 65.7 | BC9: =AZ9-AZ8 -> -12.1 | BD9: =BA9-BA8 -> -8.7 | BE9: =SUM(BB9:BD9) -> 44.9 | BF9: =SUM(I9-BE9) -> -44.9 | BG9: =SUM(I9-BF9) -> 44.9
A10: =ELEC!C8 -> 44686 | B10: =B9 -> 109443 | C10: =B10-B9 -> 0 | D10: =C10/27 -> 0 | E10: =SUM((C10*$E$4)+(7500/'EDl log'!$A$37)) -> 241.93548 | G10: 628287 | H10: =G10-G9 -> 103 | I10: =C10+H10 -> 103 | J10: =IF(I10>0,E10/I10,0) -> 2.3488882 | K10: ='Swimming Pool quality check '!H10 -> 7082 | L10: =K10-K9 -> 0 | M10: =M9 -> 457.44 | N10: =SUM(M10-M9) -> 0 | O10: =O9 -> 529.52 | P10: =SUM(O10-O9) -> 0 | Q10: =P10+N10 -> 0 | T10: =T9 -> 5182 | U10: =SUM(T10-T9) -> 0 | V10: 490 | W10: =+V10-V9 -> 0 | X10: =X9 -> 155276 | Y10: =SUM(X10-X9) -> 0 | Z10: =Z9 -> 99356 | AA10: =Z10-Z9 -> 0 | AB10: 257 | AC10: =AC9 -> 790 | AD10: =AC10-AC9 -> 0 | AE10: =AE9 -> 242.22 | AF10: =AE10-AE9 -> 0 | AG10: =AG9 -> 2229.76 | AH10: =AG10-AG9 -> 0 | AI10: =AF10+AH10 -> 0 | AJ10: =+Z10-Z9 -> 0 | AK10: =SUM(Y10-L10) -> 0 | AL10: =SUM(AJ10-W10) -> 0 | AM10: ='General information '!D9 -> 20 | AN10: ='General information '!H9 -> 0 | AP10: ='General information '!J9 -> 0 | AR10: =A10 -> 44686 | AS10: =AS9 -> 0.9 | AT10: 163 | AU10: =AU9 -> 1.1 | AV10: 89 | AW10: 2.9 | AX10: 94 | AY10: =AS10*AT10 -> 146.7 | AZ10: =AU10*AV10 -> 97.9 | BA10: =AW10*AX10 -> 272.6 | BB10: =AY10-AY9 -> -10.8 | BC10: =AZ10-AZ9 -> 5.5 | BD10: =BA10-BA9 -> -14.5 | BE10: =SUM(BB10:BD10) -> -19.8 | BF10: =SUM(I10-BE10) -> 122.8 | BG10: =SUM(I10-BF10) -> -19.8
A11: =ELEC!C9 -> 44687 | B11: =B10 -> 109443 | C11: =B11-B10 -> 0 | D11: =C11/27 -> 0 | E11: =SUM((C11*$E$4)+(7500/'EDl log'!$A$37)) -> 241.93548 | G11: =G10 -> 628287 | H11: =G11-G10 -> 0 | I11: =C11+H11 -> 0 | J11: =IF(I11>0,E11/I11,0) -> 0 | K11: ='Swimming Pool quality check '!H11 -> 7082 | L11: =K11-K10 -> 0 | M11: =M10 -> 457.44 | N11: =SUM(M11-M10) -> 0 | O11: =O10 -> 529.52 | P11: =SUM(O11-O10) -> 0 | Q11: =SUM(P11+N11) -> 0 | T11: =T10 -> 5182 | U11: =SUM(T11-T10) -> 0 | V11: =V10 -> 490 | W11: =+V11-V10 -> 0 | X11: =X10 -> 155276 | Y11: =SUM(X11-X10) -> 0 | Z11: =Z10 -> 99356 | AA11: =Z11-Z10 -> 0 | AB11: =AB10 -> 257 | AC11: =AC10 -> 790 | AD11: =AC11-AC10 -> 0 | AE11: =AE10 -> 242.22 | AF11: =AE11-AE10 -> 0 | AG11: =AG10 -> 2229.76 | AH11: =AG11-AG10 -> 0 | AI11: =AF11+AH11 -> 0 | AJ11: =+Z11-Z10 -> 0 | AK11: =SUM(Y11-L11) -> 0 | AL11: =SUM(AJ11-W11) -> 0 | AM11: ='General information '!D10 -> 0 | AN11: ='General information '!H10 -> 0 | AP11: ='General information '!J10 -> 0 | AR11: =A11 -> 44687 | AS11: =AS10 -> 0.9 | AT11: =AT10 -> 163 | AU11: =AU10 -> 1.1 | AV11: =AV10 -> 89 | AW11: 2.9 | AX11: =AX10 -> 94 | AY11: =AS11*AT11 -> 146.7 | AZ11: =AU11*AV11 -> 97.9 | BA11: =AW11*AX11 -> 272.6 | BB11: =AY11-AY10 -> 0 | BC11: =AZ11-AZ10 -> 0 | BD11: =BA11-BA10 -> 0 | BE11: =SUM(BB11:BD11) -> 0 | BF11: =SUM(I11-BE11) -> 0 | BG11: =SUM(I11-BF11) -> 0
A12: =ELEC!C10 -> 44688 | B12: =B11 -> 109443 | C12: =B12-B11 -> 0 | D12: =C12/27 -> 0 | E12: =SUM((C12*$E$4)+(7500/'EDl log'!$A$37)) -> 241.93548 | G12: =G11 -> 628287 | H12: =G12-G11 -> 0 | I12: =C12+H12 -> 0 | J12: =IF(I12>0,E12/I12,0) -> 0 | K12: ='Swimming Pool quality check '!H12 -> 7082 | L12: =K12-K11 -> 0 | M12: =M11 -> 457.44 | N12: =SUM(M12-M11) -> 0 | O12: =O11 -> 529.52 | P12: =SUM(O12-O11) -> 0 | Q12: =SUM(P12+N12) -> 0 | T12: =T11 -> 5182 | U12: =SUM(T12-T11) -> 0 | V12: =V11 -> 490 | W12: =+V12-V11 -> 0 | X12: =X11 -> 155276 | Y12: =SUM(X12-X11) -> 0 | Z12: =Z11 -> 99356 | AA12: =Z12-Z11 -> 0 | AB12: =AB11 -> 257 | AC12: =AC11 -> 790 | AD12: =AC12-AC11 -> 0 | AE12: =AE11 -> 242.22 | AF12: =AE12-AE11 -> 0 | AG12: =AG11 -> 2229.76 | AH12: =AG12-AG11 -> 0 | AI12: =AF12+AH12 -> 0 | AJ12: =+Z12-Z11 -> 0 | AK12: =SUM(Y12-L12) -> 0 | AL12: =SUM(AJ12-W12) -> 0 | AM12: ='General information '!D11 -> 0 | AN12: ='General information '!H11 -> 0 | AP12: ='General information '!J11 -> 0 | AR12: =A12 -> 44688 | AS12: =AS11 -> 0.9 | AT12: =AT11 -> 163 | AU12: =AU11 -> 1.1 | AV12: =AV11 -> 89 | AW12: 2.9 | AX12: =AX11 -> 94 | AY12: =AS12*AT12 -> 146.7 | AZ12: =AU12*AV12 -> 97.9 | BA12: =AW12*AX12 -> 272.6 | BB12: =AY12-AY11 -> 0 | BC12: =AZ12-AZ11 -> 0 | BD12: =BA12-BA11 -> 0 | BE12: =SUM(BB12:BD12) -> 0 | BF12: =SUM(I12-BE12) -> 0 | BG12: =SUM(I12-BF12) -> 0
A13: =ELEC!C11 -> 44689 | B13: =B12 -> 109443 | C13: =B13-B12 -> 0 | D13: =C13/27 -> 0 | E13: =SUM((C13*$E$4)+(7500/'EDl log'!$A$37)) -> 241.93548 | G13: =G12 -> 628287 | H13: =G13-G12 -> 0 | I13: =C13+H13 -> 0 | J13: =IF(I13>0,E13/I13,0) -> 0 | K13: ='Swimming Pool quality check '!H13 -> 7082 | L13: =K13-K12 -> 0 | M13: =M12 -> 457.44 | N13: =SUM(M13-M12) -> 0 | O13: =O12 -> 529.52 | P13: =SUM(O13-O12) -> 0 | Q13: =SUM(P13+N13) -> 0 | T13: =T12 -> 5182 | U13: =SUM(T13-T12) -> 0 | V13: 490 | W13: =+V13-V12 -> 0 | X13: =X12 -> 155276 | Y13: =SUM(X13-X12) -> 0 | Z13: =Z12 -> 99356 | AA13: =Z13-Z12 -> 0 | AB13: =AB12 -> 257 | AC13: =AC12 -> 790 | AD13: =AC13-AC12 -> 0 | AE13: =AE12 -> 242.22 | AF13: =AE13-AE12 -> 0 | AG13: =AG12 -> 2229.76 | AH13: =AG13-AG12 -> 0 | AI13: =AF13+AH13 -> 0 | AJ13: =+Z13-Z12 -> 0 | AK13: =SUM(Y13-L13) -> 0 | AL13: =SUM(AJ13-W13) -> 0 | AM13: ='General information '!D12 -> 19.5 | AN13: ='General information '!J12 -> 0 | AP13: ='General information '!J12 -> 0 | AR13: =A13 -> 44689 | AS13: =AS12 -> 0.9 | AT13: =AT12 -> 163 | AU13: =AU12 -> 1.1 | AV13: 88 | AW13: 2.9 | AX13: 91 | AY13: =AS13*AT13 -> 146.7 | AZ13: =AU13*AV13 -> 96.8 | BA13: =AW13*AX13 -> 263.9 | BB13: =AY13-AY12 -> 0 | BC13: =AZ13-AZ12 -> -1.1 | BD13: =BA13-BA12 -> -8.7 | BE13: =SUM(BB13:BD13) -> -9.8 | BF13: =SUM(I13-BE13) -> 9.8 | BG13: =SUM(I13-BF13) -> -9.8
A14: =ELEC!C12 -> 44690 | B14: =B13 -> 109443 | C14: =B14-B13 -> 0 | D14: =C14/27 -> 0 | E14: =SUM((C14*$E$4)+(7500/'EDl log'!$A$37)) -> 241.93548 | G14: =G13 -> 628287 | H14: =G14-G13 -> 0 | I14: =C14+H14 -> 0 | J14: =IF(I14>0,E14/I14,0) -> 0 | K14: ='Swimming Pool quality check '!H14 -> 7088 | L14: =K14-K13 -> 6 | M14: =M13 -> 457.44 | N14: =SUM(M14-M13) -> 0 | O14: =O13 -> 529.52 | P14: =SUM(O14-O13) -> 0 | Q14: =SUM(P14+N14) -> 0 | T14: =T13 -> 5182 | U14: =SUM(T14-T13) -> 0 | V14: 490 | W14: =+V14-V13 -> 0 | X14: 155365 | Y14: =SUM(X14-X13) -> 89 | Z14: 99383 | AA14: =Z14-Z13 -> 27 | AB14: =AB13 -> 257 | AC14: =AC13 -> 790 | AD14: =AC14-AC13 -> 0 | AE14: =AE13 -> 242.22 | AF14: =AE14-AE13 -> 0 | AG14: =AG13 -> 2229.76 | AH14: =AG14-AG13 -> 0 | AI14: =AF14+AH14 -> 0 | AJ14: =+Z14-Z13 -> 27 | AK14: =SUM(Y14-L14) -> 83 | AL14: =SUM(AJ14-W14) -> 27 | AM14: ='General information '!D13 -> 20.5 | AN14: ='General information '!H13 -> 0 | AP14: ='General information '!J13 -> 0 | AR14: =A14 -> 44690 | AS14: =AS13 -> 0.9 | AT14: 122 | AU14: =AU13 -> 1.1 | AV14: 103 | AW14: 2.9 | AX14: 114 | AY14: =AS14*AT14 -> 109.8 | AZ14: =AU14*AV14 -> 113.3 | BA14: =AW14*AX14 -> 330.6 | BB14: =AY14-AY13 -> -36.9 | BC14: =AZ14-AZ13 -> 16.5 | BD14: =BA14-BA13 -> 66.7 | BE14: =SUM(BB14:BD14) -> 46.3 | BF14: =SUM(I14-BE14) -> -46.3 | BG14: =SUM(I14-BF14) -> 46.3
A15: =ELEC!C13 -> 44691 | B15: =B14 -> 109443 | C15: =B15-B14 -> 0 | D15: =C15/27 -> 0 | E15: =SUM((C15*$E$4)+(7500/'EDl log'!$A$37)) -> 241.93548 | G15: 628414 | H15: =G15-G14 -> 127 | I15: =C15+H15 -> 127 | J15: =IF(I15>0,E15/I15,0) -> 1.9050038 | K15: ='Swimming Pool quality check '!H15 -> 7088 | L15: =K15-K14 -> 0 | M15: =M14 -> 457.44 | N15: =SUM(M15-M14) -> 0 | O15: =O14 -> 529.52 | P15: =SUM(O15-O14) -> 0 | Q15: =SUM(P15+N15) -> 0 | T15: =T14 -> 5182 | U15: =SUM(T15-T14) -> 0 | V15: =V14 -> 490 | W15: =+V15-V14 -> 0 | X15: =X14 -> 155365 | Y15: =SUM(X15-X14) -> 0 | Z15: =Z14 -> 99383 | AA15: =Z15-Z14 -> 0 | AB15: =AB14 -> 257 | AC15: =AC14 -> 790 | AD15: =AC15-AC14 -> 0 | AE15: =AE14 -> 242.22 | AF15: =AE15-AE14 -> 0 | AG15: =AG14 -> 2229.76 | AH15: =AG15-AG14 -> 0 | AI15: =AF15+AH15 -> 0 | AJ15: =+Z15-Z14 -> 0 | AK15: =SUM(Y15-L15) -> 0 | AL15: =SUM(AJ15-W15) -> 0 | AM15: ='General information '!D14 -> 20 | AN15: ='General information '!H14 -> 0 | AP15: ='General information '!J14 -> 0 | AR15: =A15 -> 44691 | AS15: =AS14 -> 0.9 | AT15: 114 | AU15: =AU14 -> 1.1 | AV15: 100 | AW15: 2.9 | AX15: 112 | AY15: =AS15*AT15 -> 102.6 | AZ15: =AU15*AV15 -> 110 | BA15: =AW15*AX15 -> 324.8 | BB15: =AY15-AY14 -> -7.2 | BC15: =AZ15-AZ14 -> -3.3 | BD15: =BA15-BA14 -> -5.8 | BE15: =SUM(BB15:BD15) -> -16.3 | BF15: =SUM(I15-BE15) -> 143.3 | BG15: =SUM(I15-BF15) -> -16.3
A16: =ELEC!C14 -> 44692 | B16: =B15 -> 109443 | C16: =B16-B15 -> 0 | D16: =C16/27 -> 0 | E16: =SUM((C16*$E$4)+(7500/'EDl log'!$A$37)) -> 241.93548 | G16: 628482 | H16: =G16-G15 -> 68 | I16: =C16+H16 -> 68 | J16: =IF(I16>0,E16/I16,0) -> 3.5578748 | K16: ='Swimming Pool quality check '!H16 -> 7089 | L16: =K16-K15 -> 1 | M16: =M15 -> 457.44 | N16: =SUM(M16-M15) -> 0 | O16: =O15 -> 529.52 | P16: =SUM(O16-O15) -> 0 | Q16: =SUM(P16+N16) -> 0 | T16: =T15 -> 5182 | U16: =SUM(T16-T15) -> 0 | V16: =V15 -> 490 | W16: =+V16-V15 -> 0 | X16: =X15 -> 155365 | Y16: =SUM(X16-X15) -> 0 | Z16: =Z15 -> 99383 | AA16: =Z16-Z15 -> 0 | AB16: =AB15 -> 257 | AC16: =AC15 -> 790 | AD16: =AC16-AC15 -> 0 | AE16: 242.23 | AF16: =AE16-AE15 -> 0.01 | AG16: =AG15 -> 2229.76 | AH16: =AG16-AG15 -> 0 | AI16: =AF16+AH16 -> 0.01 | AJ16: =+Z16-Z15 -> 0 | AK16: =SUM(Y16-L16) -> -1 | AL16: =SUM(AJ16-W16) -> 0 | AM16: ='General information '!D15 -> 20 | AN16: ='General information '!H15 -> 0 | AP16: ='General information '!J15 -> 0 | AR16: =A16 -> 44692 | AS16: =AS15 -> 0.9 | AT16: 153 | AU16: =AU15 -> 1.1 | AV16: 99 | AW16: 2.9 | AX16: 110 | AY16: =AS16*AT16 -> 137.7 | AZ16: =AU16*AV16 -> 108.9 | BA16: =AW16*AX16 -> 319 | BB16: =AY16-AY15 -> 35.1 | BC16: =AZ16-AZ15 -> -1.1 | BD16: =BA16-BA15 -> -5.8 | BE16: =SUM(BB16:BD16) -> 28.2 | BF16: =SUM(I16-BE16) -> 39.8 | BG16: =SUM(I16-BF16) -> 28.2
A17: =ELEC!C15 -> 44693 | B17: =B16 -> 109443 | C17: =B17-B16 -> 0 | D17: =C17/27 -> 0 | E17: =SUM((C17*$E$4)+(7500/'EDl log'!$A$37)) -> 241.93548 | G17: =G16 -> 628482 | H17: =G17-G16 -> 0 | I17: =C17+H17 -> 0 | J17: =IF(I17>0,E17/I17,0) -> 0 | K17: ='Swimming Pool quality check '!H17 -> 7089 | L17: =K17-K16 -> 0 | M17: =M16 -> 457.44 | N17: =SUM(M17-M16) -> 0 | O17: =O16 -> 529.52 | P17: =SUM(O17-O16) -> 0 | Q17: =SUM(P17+N17) -> 0 | T17: =T16 -> 5182 | U17: =SUM(T17-T16) -> 0 | V17: 493 | W17: =+V17-V16 -> 3 | X17: =X16 -> 155365 | Y17: =SUM(X17-X16) -> 0 | Z17: =Z16 -> 99383 | AA17: =Z17-Z16 -> 0 | AB17: 249 | AC17: =AC16 -> 790 | AD17: =AC17-AC16 -> 0 | AE17: =AE16 -> 242.23 | AF17: =AE17-AE16 -> 0 | AG17: =AG16 -> 2229.76 | AH17: =AG17-AG16 -> 0 | AI17: =AF17+AH17 -> 0 | AJ17: =+Z17-Z16 -> 0 | AK17: =SUM(Y17-L17) -> 0 | AL17: =SUM(AJ17-W17) -> -3 | AM17: ='General information '!D16 -> 19.5 | AN17: ='General information '!H16 -> 0 | AP17: ='General information '!J16 -> 0 | AR17: =A17 -> 44693 | AS17: =AS16 -> 0.9 | AT17: =AT16 -> 153 | AU17: =AU16 -> 1.1 | AV17: 98 | AW17: 2.9 | AX17: 108 | AY17: =AS17*AT17 -> 137.7 | AZ17: =AU17*AV17 -> 107.8 | BA17: =AW17*AX17 -> 313.2 | BB17: =AY17-AY16 -> 0 | BC17: =AZ17-AZ16 -> -1.1 | BD17: =BA17-BA16 -> -5.8 | BE17: =SUM(BB17:BD17) -> -6.9 | BF17: =SUM(I17-BE17) -> 6.9 | BG17: =SUM(I17-BF17) -> -6.9
A18: =ELEC!C16 -> 44694 | B18: =B17 -> 109443 | C18: =B18-B17 -> 0 | D18: =C18/27 -> 0 | E18: =SUM((C18*$E$4)+(7500/'EDl log'!$A$37)) -> 241.93548 | G18: =G17 -> 628482 | H18: =G18-G17 -> 0 | I18: =C18+H18 -> 0 | J18: =IF(I18>0,E18/I18,0) -> 0 | K18: ='Swimming Pool quality check '!H18 -> 7089 | L18: =K18-K17 -> 0 | M18: =M17 -> 457.44 | N18: =SUM(M18-M17) -> 0 | O18: =O17 -> 529.52 | P18: =SUM(O18-O17) -> 0 | Q18: =SUM(P18+N18) -> 0 | T18: =T17 -> 5182 | U18: =SUM(T18-T17) -> 0 | V18: =V17 -> 493 | W18: =+V18-V17 -> 0 | X18: =X17 -> 155365 | Y18: =SUM(X18-X17) -> 0 | Z18: =Z17 -> 99383 | AA18: =Z18-Z17 -> 0 | AB18: =AB17 -> 249 | AC18: =AC17 -> 790 | AD18: =AC18-AC17 -> 0 | AE18: =AE17 -> 242.23 | AF18: =AE18-AE17 -> 0 | AG18: =AG17 -> 2229.76 | AH18: =AG18-AG17 -> 0 | AI18: =AF18+AH18 -> 0 | AJ18: =+Z18-Z17 -> 0 | AK18: =SUM(Y18-L18) -> 0 | AL18: =SUM(AJ18-W18) -> 0 | AM18: ='General information '!D17 -> 0 | AN18: ='General information '!H17 -> 0 | AP18: ='General information '!J17 -> 0 | AR18: =A18 -> 44694 | AS18: =AS17 -> 0.9 | AT18: =AT17 -> 153 | AU18: =AU17 -> 1.1 | AV18: =AV17 -> 98 | AW18: 2.9 | AX18: =AX17 -> 108 | AY18: =AS18*AT18 -> 137.7 | AZ18: =AU18*AV18 -> 107.8 | BA18: =AW18*AX18 -> 313.2 | BB18: =AY18-AY17 -> 0 | BC18: =AZ18-AZ17 -> 0 | BD18: =BA18-BA17 -> 0 | BE18: =SUM(BB18:BD18) -> 0 | BF18: =SUM(I18-BE18) -> 0 | BG18: =SUM(I18-BF18) -> 0
A19: =ELEC!C17 -> 44695 | B19: =B18 -> 109443 | C19: =B19-B18 -> 0 | D19: =C19/27 -> 0 | E19: =SUM((C19*$E$4)+(7500/'EDl log'!$A$37)) -> 241.93548 | G19: =G18 -> 628482 | H19: =G19-G18 -> 0 | I19: =C19+H19 -> 0 | J19: =IF(I19>0,E19/I19,0) -> 0 | K19: ='Swimming Pool quality check '!H19 -> 7089 | L19: =K19-K18 -> 0 | M19: =M18 -> 457.44 | N19: =SUM(M19-M18) -> 0 | O19: =O18 -> 529.52 | P19: =SUM(O19-O18) -> 0 | Q19: =SUM(P19+N19) -> 0 | T19: =T18 -> 5182 | U19: =SUM(T19-T18) -> 0 | V19: =V18 -> 493 | W19: =+V19-V18 -> 0 | X19: =X18 -> 155365 | Y19: =SUM(X19-X18) -> 0 | Z19: =Z18 -> 99383 | AA19: =Z19-Z18 -> 0 | AB19: =AB18 -> 249 | AC19: =AC18 -> 790 | AD19: =AC19-AC18 -> 0 | AE19: =AE18 -> 242.23 | AF19: =AE19-AE18 -> 0 | AG19: =AG18 -> 2229.76 | AH19: =AG19-AG18 -> 0 | AI19: =AF19+AH19 -> 0 | AJ19: =+Z19-Z18 -> 0 | AK19: =SUM(Y19-L19) -> 0 | AL19: =SUM(AJ19-W19) -> 0 | AM19: ='General information '!D18 -> 0 | AN19: ='General information '!H18 -> 0 | AP19: ='General information '!J18 -> 0 | AR19: =A19 -> 44695 | AS19: =AS18 -> 0.9 | AT19: =AT18 -> 153 | AU19: =AU18 -> 1.1 | AV19: =AV18 -> 98 | AW19: 2.9 | AX19: =AX18 -> 108 | AY19: =AS19*AT19 -> 137.7 | AZ19: =AU19*AV19 -> 107.8 | BA19: =AW19*AX19 -> 313.2 | BB19: =AY19-AY18 -> 0 | BC19: =AZ19-AZ18 -> 0 | BD19: =BA19-BA18 -> 0 | BE19: =SUM(BB19:BD19) -> 0 | BF19: =SUM(I19-BE19) -> 0 | BG19: =SUM(I19-BF19) -> 0
A20: =ELEC!C18 -> 44696 | B20: =B19 -> 109443 | C20: =B20-B19 -> 0 | D20: =C20/27 -> 0 | E20: =SUM((C20*$E$4)+(7500/'EDl log'!$A$37)) -> 241.93548 | G20: =G19 -> 628482 | H20: =G20-G19 -> 0 | I20: =C20+H20 -> 0 | J20: =IF(I20>0,E20/I20,0) -> 0 | K20: ='Swimming Pool quality check '!H20 -> 7089 | L20: =K20-K19 -> 0 | M20: =M19 -> 457.44 | N20: =SUM(M20-M19) -> 0 | O20: =O19 -> 529.52 | P20: =SUM(O20-O19) -> 0 | Q20: =SUM(P20+N20) -> 0 | T20: =T19 -> 5182 | U20: =SUM(T20-T19) -> 0 | V20: =V19 -> 493 | W20: =+V20-V19 -> 0 | X20: =X19 -> 155365 | Y20: =SUM(X20-X19) -> 0 | Z20: =Z19 -> 99383 | AA20: =Z20-Z19 -> 0 | AB20: =AB19 -> 249 | AC20: =AC19 -> 790 | AD20: =AC20-AC19 -> 0 | AE20: =AE19 -> 242.23 | AF20: =AE20-AE19 -> 0 | AG20: =AG19 -> 2229.76 | AH20: =AG20-AG19 -> 0 | AI20: =AF20+AH20 -> 0 | AJ20: =+Z20-Z19 -> 0 | AK20: =SUM(Y20-L20) -> 0 | AL20: =SUM(AJ20-W20) -> 0 | AM20: ='General information '!D19 -> 0 | AN20: ='General information '!H19 -> 0 | AP20: ='General information '!J19 -> 0 | AR20: =A20 -> 44696 | AS20: =AS19 -> 0.9 | AT20: =AT19 -> 153 | AU20: =AU19 -> 1.1 | AV20: =AV19 -> 98 | AW20: 2.9 | AX20: =AX19 -> 108 | AY20: =AS20*AT20 -> 137.7 | AZ20: =AU20*AV20 -> 107.8 | BA20: =AW20*AX20 -> 313.2 | BB20: =AY20-AY19 -> 0 | BC20: =AZ20-AZ19 -> 0 | BD20: =BA20-BA19 -> 0 | BE20: =SUM(BB20:BD20) -> 0 | BF20: =SUM(I20-BE20) -> 0 | BG20: =SUM(I20-BF20) -> 0
A21: =ELEC!C19 -> 44697 | B21: =B20 -> 109443 | C21: =B21-B20 -> 0 | D21: =C21/27 -> 0 | E21: =SUM((C21*$E$4)+(7500/'EDl log'!$A$37)) -> 241.93548 | G21: =G20 -> 628482 | H21: =G21-G20 -> 0 | I21: =C21+H21 -> 0 | J21: =IF(I21>0,E21/I21,0) -> 0 | K21: ='Swimming Pool quality check '!H21 -> 7089 | L21: =K21-K20 -> 0 | M21: =M20 -> 457.44 | N21: =SUM(M21-M20) -> 0 | O21: =O20 -> 529.52 | P21: =SUM(O21-O20) -> 0 | Q21: =SUM(P21+N21) -> 0 | T21: =T20 -> 5182 | U21: =SUM(T21-T20) -> 0 | V21: =V20 -> 493 | W21: =+V21-V20 -> 0 | X21: =X20 -> 155365 | Y21: =SUM(X21-X20) -> 0 | Z21: =Z20 -> 99383 | AA21: =Z21-Z20 -> 0 | AB21: =AB20 -> 249 | AC21: =AC20 -> 790 | AD21: =AC21-AC20 -> 0 | AE21: =AE20 -> 242.23 | AF21: =AE21-AE20 -> 0 | AG21: =AG20 -> 2229.76 | AH21: =AG21-AG20 -> 0 | AI21: =AF21+AH21 -> 0 | AJ21: =+Z21-Z20 -> 0 | AK21: =SUM(Y21-L21) -> 0 | AL21: =SUM(AJ21-W21) -> 0 | AM21: ='General information '!D20 -> 0 | AN21: ='General information '!H20 -> 0 | AP21: ='General information '!J20 -> 0 | AR21: =A21 -> 44697 | AS21: =AS20 -> 0.9 | AT21: =AT20 -> 153 | AU21: =AU20 -> 1.1 | AV21: =AV20 -> 98 | AW21: 2.9 | AX21: =AX20 -> 108 | AY21: =AS21*AT21 -> 137.7 | AZ21: =AU21*AV21 -> 107.8 | BA21: =AW21*AX21 -> 313.2 | BB21: =AY21-AY20 -> 0 | BC21: =AZ21-AZ20 -> 0 | BD21: =BA21-BA20 -> 0 | BE21: =SUM(BB21:BD21) -> 0 | BF21: =SUM(I21-BE21) -> 0 | BG21: =SUM(I21-BF21) -> 0
A22: =ELEC!C20 -> 44698 | B22: =B21 -> 109443 | C22: =B22-B21 -> 0 | D22: =C22/27 -> 0 | E22: =SUM((C22*$E$4)+(7500/'EDl log'!$A$37)) -> 241.93548 | G22: =G21 -> 628482 | H22: =G22-G21 -> 0 | I22: =C22+H22 -> 0 | J22: =IF(I22>0,E22/I22,0) -> 0 | K22: ='Swimming Pool quality check '!H22 -> 7089 | L22: =K22-K21 -> 0 | M22: =M21 -> 457.44 | N22: =SUM(M22-M21) -> 0 | O22: =O21 -> 529.52 | P22: =SUM(O22-O21) -> 0 | Q22: =SUM(P22+N22) -> 0 | T22: =T21 -> 5182 | U22: =SUM(T22-T21) -> 0 | V22: =V21 -> 493 | W22: =+V22-V21 -> 0 | X22: =X21 -> 155365 | Y22: =SUM(X22-X21) -> 0 | Z22: =Z21 -> 99383 | AA22: =Z22-Z21 -> 0 | AB22: =AB21 -> 249 | AC22: =AC21 -> 790 | AD22: =AC22-AC21 -> 0 | AE22: =AE21 -> 242.23 | AF22: =AE22-AE21 -> 0 | AG22: =AG21 -> 2229.76 | AH22: =AG22-AG21 -> 0 | AI22: =AF22+AH22 -> 0 | AJ22: =+Z22-Z21 -> 0 | AK22: =SUM(Y22-L22) -> 0 | AL22: =SUM(AJ22-W22) -> 0 | AM22: ='General information '!D21 -> 0 | AN22: ='General information '!H21 -> 0 | AP22: ='General information '!J21 -> 0 | AR22: =A22 -> 44698 | AS22: =AS21 -> 0.9 | AT22: =AT21 -> 153 | AU22: =AU21 -> 1.1 | AV22: =AV21 -> 98 | AW22: 2.9 | AX22: =AX21 -> 108 | AY22: =AS22*AT22 -> 137.7 | AZ22: =AU22*AV22 -> 107.8 | BA22: =AW22*AX22 -> 313.2 | BB22: =AY22-AY21 -> 0 | BC22: =AZ22-AZ21 -> 0 | BD22: =BA22-BA21 -> 0 | BE22: =SUM(BB22:BD22) -> 0 | BF22: =SUM(I22-BE22) -> 0 | BG22: =SUM(I22-BF22) -> 0
A23: =ELEC!C21 -> 44699 | B23: =B22 -> 109443 | C23: =B23-B22 -> 0 | D23: =C23/27 -> 0 | E23: =SUM((C23*$E$4)+(7500/'EDl log'!$A$37)) -> 241.93548 | G23: =G22 -> 628482 | H23: =G23-G22 -> 0 | I23: =C23+H23 -> 0 | J23: =IF(I23>0,E23/I23,0) -> 0 | K23: ='Swimming Pool quality check '!H23 -> 7089 | L23: =K23-K22 -> 0 | M23: =M22 -> 457.44 | N23: =SUM(M23-M22) -> 0 | O23: =O22 -> 529.52 | P23: =SUM(O23-O22) -> 0 | Q23: =SUM(P23+N23) -> 0 | T23: =T22 -> 5182 | U23: =SUM(T23-T22) -> 0 | V23: =V22 -> 493 | W23: =+V23-V22 -> 0 | X23: =X22 -> 155365 | Y23: =SUM(X23-X22) -> 0 | Z23: =Z22 -> 99383 | AA23: =Z23-Z22 -> 0 | AB23: =AB22 -> 249 | AC23: =AC22 -> 790 | AD23: =AC23-AC22 -> 0 | AE23: =AE22 -> 242.23 | AF23: =AE23-AE22 -> 0 | AG23: =AG22 -> 2229.76 | AH23: =AG23-AG22 -> 0 | AI23: =AF23+AH23 -> 0 | AJ23: =+Z23-Z22 -> 0 | AK23: =SUM(Y23-L23) -> 0 | AL23: =SUM(AJ23-W23) -> 0 | AM23: ='General information '!D22 -> 0 | AN23: ='General information '!H22 -> 0 | AP23: ='General information '!J22 -> 0 | AR23: =A23 -> 44699 | AS23: =AS22 -> 0.9 | AT23: =AT22 -> 153 | AU23: =AU22 -> 1.1 | AV23: =AV22 -> 98 | AW23: 2.9 | AX23: =AX22 -> 108 | AY23: =AS23*AT23 -> 137.7 | AZ23: =AU23*AV23 -> 107.8 | BA23: =AW23*AX23 -> 313.2 | BB23: =AY23-AY22 -> 0 | BC23: =AZ23-AZ22 -> 0 | BD23: =BA23-BA22 -> 0 | BE23: =SUM(BB23:BD23) -> 0 | BF23: =SUM(I23-BE23) -> 0 | BG23: =SUM(I23-BF23) -> 0
A24: =ELEC!C22 -> 44700 | B24: =B23 -> 109443 | C24: =B24-B23 -> 0 | D24: =C24/27 -> 0 | E24: =SUM((C24*$E$4)+(7500/'EDl log'!$A$37)) -> 241.93548 | G24: =G23 -> 628482 | H24: =G24-G23 -> 0 | I24: =C24+H24 -> 0 | J24: =IF(I24>0,E24/I24,0) -> 0 | K24: ='Swimming Pool quality check '!H24 -> 7089 | L24: =K24-K23 -> 0 | M24: =M23 -> 457.44 | N24: =SUM(M24-M23) -> 0 | O24: =O23 -> 529.52 | P24: =SUM(O24-O23) -> 0 | Q24: =SUM(P24+N24) -> 0 | T24: =T23 -> 5182 | U24: =SUM(T24-T23) -> 0 | V24: =V23 -> 493 | W24: =+V24-V23 -> 0 | X24: =X23 -> 155365 | Y24: =SUM(X24-X23) -> 0 | Z24: =Z23 -> 99383 | AA24: =Z24-Z23 -> 0 | AB24: =AB23 -> 249 | AC24: =AC23 -> 790 | AD24: =AC24-AC23 -> 0 | AE24: =AE23 -> 242.23 | AF24: =AE24-AE23 -> 0 | AG24: =AG23 -> 2229.76 | AH24: =AG24-AG23 -> 0 | AI24: =AF24+AH24 -> 0 | AJ24: =+Z24-Z23 -> 0 | AK24: =SUM(Y24-L24) -> 0 | AL24: =SUM(AJ24-W24) -> 0 | AM24: ='General information '!D23 -> 0 | AN24: ='[3]General information '!H24 -> 0 | AP24: ='[3]General information '!J24 -> 0 | AR24: =A24 -> 44700 | AS24: =AS23 -> 0.9 | AT24: =AT23 -> 153 | AU24: =AU23 -> 1.1 | AV24: =AV23 -> 98 | AW24: 2.9 | AX24: =AX23 -> 108 | AY24: =AS24*AT24 -> 137.7 | AZ24: =AU24*AV24 -> 107.8 | BA24: =AW24*AX24 -> 313.2 | BB24: =AY24-AY23 -> 0 | BC24: =AZ24-AZ23 -> 0 | BD24: =BA24-BA23 -> 0 | BE24: =SUM(BB24:BD24) -> 0 | BF24: =SUM(I24-BE24) -> 0 | BG24: =SUM(I24-BF24) -> 0
A25: =ELEC!C23 -> 44701 | B25: =B24 -> 109443 | C25: =B25-B24 -> 0 | D25: =C25/27 -> 0 | E25: =SUM((C25*$E$4)+(7500/'EDl log'!$A$37)) -> 241.93548 | G25: =G24 -> 628482 | H25: =G25-G24 -> 0 | I25: =C25+H25 -> 0 | J25: =IF(I25>0,E25/I25,0) -> 0 | K25: ='Swimming Pool quality check '!H25 -> 7089 | L25: =K25-K24 -> 0 | M25: =M24 -> 457.44 | N25: =SUM(M25-M24) -> 0 | O25: =O24 -> 529.52 | P25: =SUM(O25-O24) -> 0 | Q25: =SUM(P25+N25) -> 0 | T25: =T24 -> 5182 | U25: =SUM(T25-T24) -> 0 | V25: =V24 -> 493 | W25: =+V25-V24 -> 0 | X25: =X24 -> 155365 | Y25: =SUM(X25-X24) -> 0 | Z25: =Z24 -> 99383 | AA25: =Z25-Z24 -> 0 | AB25: =AB24 -> 249 | AC25: =AC24 -> 790 | AD25: =AC25-AC24 -> 0 | AE25: =AE24 -> 242.23 | AF25: =AE25-AE24 -> 0 | AG25: =AG24 -> 2229.76 | AH25: =AG25-AG24 -> 0 | AI25: =AF25+AH25 -> 0 | AJ25: =+Z25-Z24 -> 0 | AK25: =SUM(Y25-L25) -> 0 | AL25: =SUM(AJ25-W25) -> 0 | AM25: ='General information '!D24 -> 0 | AN25: ='General information '!H24 -> 0 | AP25: ='General information '!J24 -> 0 | AR25: =A25 -> 44701 | AS25: =AS24 -> 0.9 | AT25: =AT24 -> 153 | AU25: =AU24 -> 1.1 | AV25: =AV24 -> 98 | AW25: 2.9 | AX25: =AX24 -> 108 | AY25: =AS25*AT25 -> 137.7 | AZ25: =AU25*AV25 -> 107.8 | BA25: =AW25*AX25 -> 313.2 | BB25: =AY25-AY24 -> 0 | BC25: =AZ25-AZ24 -> 0 | BD25: =BA25-BA24 -> 0 | BE25: =SUM(BB25:BD25) -> 0 | BF25: =SUM(I25-BE25) -> 0 | BG25: =SUM(I25-BF25) -> 0
A26: =ELEC!C24 -> 44702 | B26: =B25 -> 109443 | C26: =B26-B25 -> 0 | D26: =C26/27 -> 0 | E26: =SUM((C26*$E$4)+(7500/'EDl log'!$A$37)) -> 241.93548 | G26: =G25 -> 628482 | H26: =G26-G25 -> 0 | I26: =C26+H26 -> 0 | J26: =IF(I26>0,E26/I26,0) -> 0 | K26: ='Swimming Pool quality check '!H26 -> 7089 | L26: =K26-K25 -> 0 | M26: =M25 -> 457.44 | N26: =SUM(M26-M25) -> 0 | O26: =O25 -> 529.52 | P26: =SUM(O26-O25) -> 0 | Q26: =SUM(P26+N26) -> 0 | T26: =T25 -> 5182 | U26: =SUM(T26-T25) -> 0 | V26: 482 | W26: =+V26-V25 -> -11 | X26: =X25 -> 155365 | Y26: =SUM(X26-X25) -> 0 | Z26: =Z25 -> 99383 | AA26: =Z26-Z25 -> 0 | AB26: =AB25 -> 249 | AC26: =AC25 -> 790 | AD26: =AC26-AC25 -> 0 | AE26: =AE25 -> 242.23 | AF26: =AE26-AE25 -> 0 | AG26: =AG25 -> 2229.76 | AH26: =AG26-AG25 -> 0 | AI26: =AF26+AH26 -> 0 | AJ26: =+Z26-Z25 -> 0 | AK26: =SUM(Y26-L26) -> 0 | AL26: =SUM(AJ26-W26) -> 11 | AM26: ='General information '!D25 -> 0 | AN26: ='General information '!H25 -> 0 | AP26: ='General information '!J25 -> 0 | AR26: =A26 -> 44702 | AS26: =AS25 -> 0.9 | AT26: =AT25 -> 153 | AU26: =AU25 -> 1.1 | AV26: =AV25 -> 98 | AW26: 2.9 | AX26: =AX25 -> 108 | AY26: =AS26*AT26 -> 137.7 | AZ26: =AU26*AV26 -> 107.8 | BA26: =AW26*AX26 -> 313.2 | BB26: =AY26-AY25 -> 0 | BC26: =AZ26-AZ25 -> 0 | BD26: =BA26-BA25 -> 0 | BE26: =SUM(BB26:BD26) -> 0 | BF26: =SUM(I26-BE26) -> 0 | BG26: =SUM(I26-BF26) -> 0
A27: =ELEC!C25 -> 44703 | B27: =B26 -> 109443 | C27: =B27-B26 -> 0 | D27: =C27/27 -> 0 | E27: =SUM((C27*$E$4)+(7500/'EDl log'!$A$37)) -> 241.93548 | G27: =G26 -> 628482 | H27: =G27-G26 -> 0 | I27: =C27+H27 -> 0 | J27: =IF(I27>0,E27/I27,0) -> 0 | K27: ='Swimming Pool quality check '!H27 -> 7089 | L27: =K27-K26 -> 0 | M27: =M26 -> 457.44 | N27: =SUM(M27-M26) -> 0 | O27: =O26 -> 529.52 | P27: =SUM(O27-O26) -> 0 | Q27: =SUM(P27+N27) -> 0 | T27: =T26 -> 5182 | U27: =SUM(T27-T26) -> 0 | V27: =V26 -> 482 | W27: =+V27-V26 -> 0 | X27: =X26 -> 155365 | Y27: =SUM(X27-X26) -> 0 | Z27: =Z26 -> 99383 | AA27: =Z27-Z26 -> 0 | AB27: =AB26 -> 249 | AC27: =AC26 -> 790 | AD27: =AC27-AC26 -> 0 | AE27: =AE26 -> 242.23 | AF27: =AE27-AE26 -> 0 | AG27: =AG26 -> 2229.76 | AH27: =AG27-AG26 -> 0 | AI27: =AF27+AH27 -> 0 | AJ27: =+Z27-Z26 -> 0 | AK27: =SUM(Y27-L27) -> 0 | AL27: =SUM(AJ27-W27) -> 0 | AM27: ='General information '!D26 -> 0 | AN27: ='General information '!H26 -> 0 | AP27: ='General information '!J26 -> 0 | AR27: =A27 -> 44703 | AS27: =AS26 -> 0.9 | AT27: =AT26 -> 153 | AU27: =AU26 -> 1.1 | AV27: =AV26 -> 98 | AW27: 2.9 | AX27: =AX26 -> 108 | AY27: =AS27*AT27 -> 137.7 | AZ27: =AU27*AV27 -> 107.8 | BA27: =AW27*AX27 -> 313.2 | BB27: =AY27-AY26 -> 0 | BC27: =AZ27-AZ26 -> 0 | BD27: =BA27-BA26 -> 0 | BE27: =SUM(BB27:BD27) -> 0 | BF27: =SUM(I27-BE27) -> 0 | BG27: =SUM(I27-BF27) -> 0
A28: =ELEC!C26 -> 44704 | B28: =B27 -> 109443 | C28: =B28-B27 -> 0 | D28: =C28/27 -> 0 | E28: =SUM((C28*$E$4)+(7500/'EDl log'!$A$37)) -> 241.93548 | G28: =G27 -> 628482 | H28: =G28-G27 -> 0 | I28: =C28+H28 -> 0 | J28: =IF(I28>0,E28/I28,0) -> 0 | K28: ='Swimming Pool quality check '!H28 -> 7089 | L28: =K28-K27 -> 0 | M28: =M27 -> 457.44 | N28: =SUM(M28-M27) -> 0 | O28: =O27 -> 529.52 | P28: =SUM(O28-O27) -> 0 | Q28: =SUM(P28+N28) -> 0 | T28: =T27 -> 5182 | U28: =SUM(T28-T27) -> 0 | V28: =V27 -> 482 | W28: =+V28-V27 -> 0 | X28: =X27 -> 155365 | Y28: =SUM(X28-X27) -> 0 | Z28: =Z27 -> 99383 | AA28: =Z28-Z27 -> 0 | AB28: =AB27 -> 249 | AC28: =AC27 -> 790 | AD28: =AC28-AC27 -> 0 | AE28: =AE27 -> 242.23 | AF28: =AE28-AE27 -> 0 | AG28: =AG27 -> 2229.76 | AH28: =AG28-AG27 -> 0 | AI28: =AF28+AH28 -> 0 | AJ28: =+Z28-Z27 -> 0 | AK28: =SUM(Y28-L28) -> 0 | AL28: =SUM(AJ28-W28) -> 0 | AM28: ='General information '!D27 -> 0 | AN28: ='General information '!H27 -> 0 | AP28: ='General information '!J27 -> 0 | AR28: =A28 -> 44704 | AS28: =AS27 -> 0.9 | AT28: =AT27 -> 153 | AU28: =AU27 -> 1.1 | AV28: =AV27 -> 98 | AW28: 2.9 | AX28: =AX27 -> 108 | AY28: =AS28*AT28 -> 137.7 | AZ28: =AU28*AV28 -> 107.8 | BA28: =AW28*AX28 -> 313.2 | BB28: =AY28-AY27 -> 0 | BC28: =AZ28-AZ27 -> 0 | BD28: =BA28-BA27 -> 0 | BE28: =SUM(BB28:BD28) -> 0 | BF28: =SUM(I28-BE28) -> 0 | BG28: =SUM(I28-BF28) -> 0
A29: =ELEC!C27 -> 44705 | B29: =B28 -> 109443 | C29: =B29-B28 -> 0 | D29: =C29/27 -> 0 | E29: =SUM((C29*$E$4)+(7500/'EDl log'!$A$37)) -> 241.93548 | G29: =G28 -> 628482 | H29: =G29-G28 -> 0 | I29: =C29+H29 -> 0 | J29: =IF(I29>0,E29/I29,0) -> 0 | K29: ='Swimming Pool quality check '!H29 -> 7089 | L29: =K29-K28 -> 0 | M29: =M28 -> 457.44 | N29: =SUM(M29-M28) -> 0 | O29: =O28 -> 529.52 | P29: =SUM(O29-O28) -> 0 | Q29: =SUM(P29+N29) -> 0 | T29: =T28 -> 5182 | U29: =SUM(T29-T28) -> 0 | V29: =V28 -> 482 | W29: =+V29-V28 -> 0 | X29: =X28 -> 155365 | Y29: =SUM(X29-X28) -> 0 | Z29: =Z28 -> 99383 | AA29: =Z29-Z28 -> 0 | AB29: =AB28 -> 249 | AC29: =AC28 -> 790 | AD29: =AC29-AC28 -> 0 | AE29: =AE28 -> 242.23 | AF29: =AE29-AE28 -> 0 | AG29: =AG28 -> 2229.76 | AH29: =AG29-AG28 -> 0 | AI29: =AF29+AH29 -> 0 | AJ29: =+Z29-Z28 -> 0 | AK29: =SUM(Y29-L29) -> 0 | AL29: =SUM(AJ29-W29) -> 0 | AM29: ='General information '!D28 -> 0 | AN29: ='General information '!H28 -> 0 | AP29: ='General information '!J28 -> 0 | AR29: =A29 -> 44705 | AS29: =AS28 -> 0.9 | AT29: =AT28 -> 153 | AU29: =AU28 -> 1.1 | AV29: =AV28 -> 98 | AW29: 2.9 | AX29: =AX28 -> 108 | AY29: =AS29*AT29 -> 137.7 | AZ29: =AU29*AV29 -> 107.8 | BA29: =AW29*AX29 -> 313.2 | BB29: =AY29-AY28 -> 0 | BC29: =AZ29-AZ28 -> 0 | BD29: =BA29-BA28 -> 0 | BE29: =SUM(BB29:BD29) -> 0 | BF29: =SUM(I29-BE29) -> 0 | BG29: =SUM(I29-BF29) -> 0
A30: =ELEC!C28 -> 44706 | B30: =B29 -> 109443 | C30: =B30-B29 -> 0 | D30: =C30/27 -> 0 | E30: =SUM((C30*$E$4)+(7500/'EDl log'!$A$37)) -> 241.93548 | G30: =G29 -> 628482 | H30: =G30-G29 -> 0 | I30: =C30+H30 -> 0 | J30: =IF(I30>0,E30/I30,0) -> 0 | K30: ='Swimming Pool quality check '!H30 -> 7089 | L30: =K30-K29 -> 0 | M30: =M29 -> 457.44 | N30: =SUM(M30-M29) -> 0 | O30: =O29 -> 529.52 | P30: =SUM(O30-O29) -> 0 | Q30: =SUM(P30+N30) -> 0 | T30: =T29 -> 5182 | U30: =SUM(T30-T29) -> 0 | V30: =V29 -> 482 | W30: =+V30-V29 -> 0 | X30: =X29 -> 155365 | Y30: =SUM(X30-X29) -> 0 | Z30: =Z29 -> 99383 | AA30: =Z30-Z29 -> 0 | AB30: =AB29 -> 249 | AC30: =AC29 -> 790 | AD30: =AC30-AC29 -> 0 | AE30: =AE29 -> 242.23 | AF30: =AE30-AE29 -> 0 | AG30: =AG29 -> 2229.76 | AH30: =AG30-AG29 -> 0 | AI30: =AF30+AH30 -> 0 | AJ30: =+Z30-Z29 -> 0 | AK30: =SUM(Y30-L30) -> 0 | AL30: =SUM(AJ30-W30) -> 0 | AM30: ='General information '!D29 -> 0 | AN30: ='General information '!H29 -> 0 | AP30: ='General information '!J29 -> 0 | AR30: =A30 -> 44706 | AS30: =AS29 -> 0.9 | AT30: =AT29 -> 153 | AU30: =AU29 -> 1.1 | AV30: =AV29 -> 98 | AW30: 2.9 | AX30: =AX29 -> 108 | AY30: =AS30*AT30 -> 137.7 | AZ30: =AU30*AV30 -> 107.8 | BA30: =AW30*AX30 -> 313.2 | BB30: =AY30-AY29 -> 0 | BC30: =AZ30-AZ29 -> 0 | BD30: =BA30-BA29 -> 0 | BE30: =SUM(BB30:BD30) -> 0 | BF30: =SUM(I30-BE30) -> 0 | BG30: =SUM(I30-BF30) -> 0
A31: =ELEC!C29 -> 44707 | B31: =B30 -> 109443 | C31: =B31-B30 -> 0 | D31: =C31/27 -> 0 | E31: =SUM((C31*$E$4)+(7500/'EDl log'!$A$37)) -> 241.93548 | G31: =G30 -> 628482 | H31: =G31-G30 -> 0 | I31: =C31+H31 -> 0 | J31: =IF(I31>0,E31/I31,0) -> 0 | K31: ='Swimming Pool quality check '!H31 -> 7089 | L31: =K31-K30 -> 0 | M31: =M30 -> 457.44 | N31: =SUM(M31-M30) -> 0 | O31: =O30 -> 529.52 | P31: =SUM(O31-O30) -> 0 | Q31: =SUM(P31+N31) -> 0 | T31: =T30 -> 5182 | U31: =SUM(T31-T30) -> 0 | V31: =V30 -> 482 | W31: =+V31-V30 -> 0 | X31: 155276 | Y31: =SUM(X31-X30) -> -89 | Z31: =Z30 -> 99383 | AA31: =Z31-Z30 -> 0 | AB31: =AB30 -> 249 | AC31: =AC30 -> 790 | AD31: =AC31-AC30 -> 0 | AE31: =AE30 -> 242.23 | AF31: =AE31-AE30 -> 0 | AG31: =AG30 -> 2229.76 | AH31: =AG31-AG30 -> 0 | AI31: =AF31+AH31 -> 0 | AJ31: =+Z31-Z30 -> 0 | AK31: =SUM(Y31-L31) -> -89 | AL31: =SUM(AJ31-W31) -> 0 | AM31: ='General information '!D30 -> 0 | AN31: ='General information '!H30 -> 0 | AP31: ='General information '!J30 -> 0 | AR31: =A31 -> 44707 | AS31: =AS30 -> 0.9 | AT31: =AT30 -> 153 | AU31: =AU30 -> 1.1 | AV31: =AV30 -> 98 | AW31: 2.9 | AX31: =AX30 -> 108 | AY31: =AS31*AT31 -> 137.7 | AZ31: =AU31*AV31 -> 107.8 | BA31: =AW31*AX31 -> 313.2 | BB31: =AY31-AY30 -> 0 | BC31: =AZ31-AZ30 -> 0 | BD31: =BA31-BA30 -> 0 | BE31: =SUM(BB31:BD31) -> 0 | BF31: =SUM(I31-BE31) -> 0 | BG31: =SUM(I31-BF31) -> 0
A32: =ELEC!C30 -> 44708 | B32: =B31 -> 109443 | C32: =B32-B31 -> 0 | D32: =C32/27 -> 0 | E32: =SUM((C32*$E$4)+(7500/'EDl log'!$A$37)) -> 241.93548 | G32: =G31 -> 628482 | H32: =G32-G31 -> 0 | I32: =C32+H32 -> 0 | J32: =IF(I32>0,E32/I32,0) -> 0 | K32: ='Swimming Pool quality check '!H32 -> 7089 | L32: =K32-K31 -> 0 | M32: =M31 -> 457.44 | N32: =SUM(M32-M31) -> 0 | O32: =O31 -> 529.52 | P32: =SUM(O32-O31) -> 0 | Q32: =SUM(P32+N32) -> 0 | T32: =T31 -> 5182 | U32: =SUM(T32-T31) -> 0 | V32: =V31 -> 482 | W32: =+V32-V31 -> 0 | X32: =X31 -> 155276 | Y32: =SUM(X32-X31) -> 0 | Z32: =Z31 -> 99383 | AA32: =Z32-Z31 -> 0 | AB32: =AB31 -> 249 | AC32: =AC31 -> 790 | AD32: =AC32-AC31 -> 0 | AE32: =AE31 -> 242.23 | AF32: =AE32-AE31 -> 0 | AG32: =AG31 -> 2229.76 | AH32: =AG32-AG31 -> 0 | AI32: =AF32+AH32 -> 0 | AJ32: =+Z32-Z31 -> 0 | AK32: =SUM(Y32-L32) -> 0 | AL32: =SUM(AJ32-W32) -> 0 | AM32: ='General information '!D31 -> 0 | AN32: ='General information '!H31 -> 0 | AP32: ='General information '!J31 -> 0 | AR32: =A32 -> 44708 | AS32: =AS31 -> 0.9 | AT32: =AT31 -> 153 | AU32: =AU31 -> 1.1 | AV32: =AV31 -> 98 | AW32: 2.9 | AX32: =AX31 -> 108 | AY32: =AS32*AT32 -> 137.7 | AZ32: =AU32*AV32 -> 107.8 | BA32: =AW32*AX32 -> 313.2 | BB32: =AY32-AY31 -> 0 | BC32: =AZ32-AZ31 -> 0 | BD32: =BA32-BA31 -> 0 | BE32: =SUM(BB32:BD32) -> 0 | BF32: =SUM(I32-BE32) -> 0 | BG32: =SUM(I32-BF32) -> 0
A33: =ELEC!C31 -> 44709 | B33: =B32 -> 109443 | C33: =B33-B32 -> 0 | D33: =C33/27 -> 0 | E33: =SUM((C33*$E$4)+(7500/'EDl log'!$A$37)) -> 241.93548 | G33: =G32 -> 628482 | H33: =G33-G32 -> 0 | I33: =C33+H33 -> 0 | J33: =IF(I33>0,E33/I33,0) -> 0 | K33: ='Swimming Pool quality check '!H33 -> 7089 | L33: =K33-K32 -> 0 | M33: =M32 -> 457.44 | N33: =SUM(M33-M32) -> 0 | O33: =O32 -> 529.52 | P33: =SUM(O33-O32) -> 0 | Q33: =SUM(P33+N33) -> 0 | T33: =T32 -> 5182 | U33: =SUM(T33-T32) -> 0 | V33: =V32 -> 482 | W33: =+V33-V32 -> 0 | X33: =X32 -> 155276 | Y33: =SUM(X33-X32) -> 0 | Z33: =Z32 -> 99383 | AA33: =Z33-Z32 -> 0 | AB33: =AB32 -> 249 | AC33: =AC32 -> 790 | AD33: =AC33-AC32 -> 0 | AE33: =AE32 -> 242.23 | AF33: =AE33-AE32 -> 0 | AG33: =AG32 -> 2229.76 | AH33: =AG33-AG32 -> 0 | AI33: =AF33+AH33 -> 0 | AJ33: =+Z33-Z32 -> 0 | AK33: =SUM(Y33-L33) -> 0 | AL33: =SUM(AJ33-W33) -> 0 | AM33: ='General information '!D32 -> 0 | AN33: ='General information '!H32 -> 0 | AP33: ='General information '!J32 -> 0 | AR33: =A33 -> 44709 | AS33: =AS32 -> 0.9 | AT33: =AT32 -> 153 | AU33: =AU32 -> 1.1 | AV33: =AV32 -> 98 | AW33: 2.9 | AX33: =AX32 -> 108 | AY33: =AS33*AT33 -> 137.7 | AZ33: =AU33*AV33 -> 107.8 | BA33: =AW33*AX33 -> 313.2 | BB33: =AY33-AY32 -> 0 | BC33: =AZ33-AZ32 -> 0 | BD33: =BA33-BA32 -> 0 | BE33: =SUM(BB33:BD33) -> 0 | BF33: =SUM(I33-BE33) -> 0 | BG33: =SUM(I33-BF33) -> 0
A34: =ELEC!C32 -> 44710 | B34: =B33 -> 109443 | C34: =B34-B33 -> 0 | D34: =C34/27 -> 0 | E34: =SUM((C34*$E$4)+(7500/'EDl log'!$A$37)) -> 241.93548 | G34: =G33 -> 628482 | H34: =G34-G33 -> 0 | I34: =C34+H34 -> 0 | J34: =IF(I34>0,E34/I34,0) -> 0 | K34: ='Swimming Pool quality check '!H34 -> 7089 | L34: =K34-K33 -> 0 | M34: =M33 -> 457.44 | N34: =SUM(M34-M33) -> 0 | O34: =O33 -> 529.52 | P34: =SUM(O34-O33) -> 0 | Q34: =SUM(P34+N34) -> 0 | T34: =T33 -> 5182 | U34: =SUM(T34-T33) -> 0 | V34: =V33 -> 482 | W34: =+V34-V33 -> 0 | X34: =X33 -> 155276 | Y34: =SUM(X34-X33) -> 0 | Z34: =Z33 -> 99383 | AA34: =Z34-Z33 -> 0 | AB34: =AB33 -> 249 | AC34: =AC33 -> 790 | AD34: =AC34-AC33 -> 0 | AE34: =AE33 -> 242.23 | AF34: =AE34-AE33 -> 0 | AG34: 2222.14 | AH34: =AG34-AG33 -> -7.62 | AI34: =AF34+AH34 -> -7.62 | AJ34: =+Z34-Z33 -> 0 | AK34: =SUM(Y34-L34) -> 0 | AL34: =SUM(AJ34-W34) -> 0 | AM34: ='General information '!D33 -> 0 | AN34: ='General information '!H33 -> 0 | AP34: ='General information '!J33 -> 0 | AR34: =A34 -> 44710 | AS34: =AS33 -> 0.9 | AT34: =AT33 -> 153 | AU34: =AU33 -> 1.1 | AV34: =AV33 -> 98 | AW34: 2.9 | AX34: =AX33 -> 108 | AY34: =AS34*AT34 -> 137.7 | AZ34: =AU34*AV34 -> 107.8 | BA34: =AW34*AX34 -> 313.2 | BB34: =AY34-AY33 -> 0 | BC34: =AZ34-AZ33 -> 0 | BD34: =BA34-BA33 -> 0 | BE34: =SUM(BB34:BD34) -> 0 | BF34: =SUM(I34-BE34) -> 0 | BG34: =SUM(I34-BF34) -> 0
A35: =ELEC!C33 -> 44711 | B35: =B34 -> 109443 | C35: =B35-B34 -> 0 | D35: =C35/27 -> 0 | E35: =SUM((C35*$E$4)+(7500/'EDl log'!$A$37)) -> 241.93548 | G35: =G34 -> 628482 | H35: =G35-G34 -> 0 | I35: =C35+H35 -> 0 | J35: =IF(I35>0,E35/I35,0) -> 0 | K35: ='Swimming Pool quality check '!H35 -> 7089 | L35: =K35-K34 -> 0 | M35: =M34 -> 457.44 | N35: =SUM(M35-M34) -> 0 | O35: =O34 -> 529.52 | P35: =SUM(O35-O34) -> 0 | Q35: =SUM(P35+N35) -> 0 | T35: =T34 -> 5182 | U35: =SUM(T35-T34) -> 0 | V35: =V34 -> 482 | W35: =+V35-V34 -> 0 | X35: =X34 -> 155276 | Y35: =SUM(X35-X34) -> 0 | Z35: =Z34 -> 99383 | AA35: =Z35-Z34 -> 0 | AB35: =AB34 -> 249 | AC35: =AC34 -> 790 | AD35: =AC35-AC34 -> 0 | AE35: =AE34 -> 242.23 | AF35: =AE35-AE34 -> 0 | AG35: =AG34 -> 2222.14 | AH35: =AG35-AG34 -> 0 | AI35: =AF35+AH35 -> 0 | AJ35: =+Z35-Z34 -> 0 | AK35: =SUM(Y35-L35) -> 0 | AL35: =SUM(AJ35-W35) -> 0 | AM35: ='General information '!D34 -> 0 | AN35: ='General information '!H34 -> 0 | AP35: ='General information '!J34 -> 0 | AR35: =A35 -> 44711 | AS35: =AS34 -> 0.9 | AT35: =AT34 -> 153 | AU35: =AU34 -> 1.1 | AV35: =AV34 -> 98 | AW35: 2.9 | AX35: =AX34 -> 108 | AY35: =AS35*AT35 -> 137.7 | AZ35: =AU35*AV35 -> 107.8 | BA35: =AW35*AX35 -> 313.2 | BB35: =AY35-AY34 -> 0 | BC35: =AZ35-AZ34 -> 0 | BD35: =BA35-BA34 -> 0 | BE35: =SUM(BB35:BD35) -> 0 | BF35: =SUM(I35-BE35) -> 0 | BG35: =SUM(I35-BF35) -> 0
A36: =ELEC!C34 -> 44712 | B36: =B35 -> 109443 | C36: =B36-B35 -> 0 | D36: =C36/27 -> 0 | E36: =SUM((C36*$E$4)+(7500/'EDl log'!$A$37)) -> 241.93548 | G36: =G35 -> 628482 | H36: =G36-G35 -> 0 | I36: =C36+H36 -> 0 | J36: =IF(I36>0,E36/I36,0) -> 0 | K36: ='Swimming Pool quality check '!H36 -> 7089 | L36: =K36-K35 -> 0 | M36: =M35 -> 457.44 | N36: =SUM(M36-M35) -> 0 | O36: =O35 -> 529.52 | P36: =SUM(O36-O35) -> 0 | Q36: =SUM(P36+N36) -> 0 | T36: =T35 -> 5182 | U36: =SUM(T36-T35) -> 0 | V36: =V35 -> 482 | W36: =+V36-V35 -> 0 | X36: =X35 -> 155276 | Y36: =SUM(X36-X35) -> 0 | Z36: =Z35 -> 99383 | AA36: =Z36-Z35 -> 0 | AB36: =AB35 -> 249 | AC36: =AC35 -> 790 | AD36: =AC36-AC35 -> 0 | AE36: =AE35 -> 242.23 | AF36: =AE36-AE35 -> 0 | AG36: =AG35 -> 2222.14 | AH36: =AG36-AG35 -> 0 | AI36: =AF36+AH36 -> 0 | AJ36: =+Z36-Z35 -> 0 | AK36: =SUM(Y36-L36) -> 0 | AL36: =SUM(AJ36-W36) -> 0 | AM36: ='General information '!D35 -> 0 | AN36: ='General information '!H35 -> 0 | AP36: ='General information '!J35 -> 0 | AR36: =A36 -> 44712 | AS36: =AS35 -> 0.9 | AT36: =AT35 -> 153 | AU36: =AU35 -> 1.1 | AV36: =AV35 -> 98 | AW36: 2.9 | AX36: =AX35 -> 108 | AY36: =AS36*AT36 -> 137.7 | AZ36: =AU36*AV36 -> 107.8 | BA36: =AW36*AX36 -> 313.2 | BB36: =AY36-AY35 -> 0 | BC36: =AZ36-AZ35 -> 0 | BD36: =BA36-BA35 -> 0 | BE36: =SUM(BB36:BD36) -> 0 | BF36: =SUM(I36-BE36) -> 0 | BG36: =SUM(I36-BF36) -> 0
C37: =SUM(C6:C36) -> 0 | D37: =SUM(D6:D36) -> 0 | F37: =SUM(F6:F36) -> 0 | H37: =SUM(H6:H36) -> 298 | I37: =SUM(I6:I36) -> 298 | L37: =SUM(L7:L36) -> 16 | Q37: =SUM(Q6:Q36) -> 0 | U37: =SUM(U6:U36) -> 0 | Y37: =SUM(Y6,Y33,Y31,Y29,Y27,Y25,Y23,Y21,Y19,Y17,Y15,Y13,Y11,Y9,Y7,Y34,Y35,Y36) -> -89 | AJ37: =SUM(AJ6:AJ36) -> 27 | AK37: =SUM(Y37-L37) -> -105 | AL37: =SUM(AL6:AL36) -> 27
C38: =+C37*1.66 -> 0 | E38: =SUM(E6:E33) -> 6774.1935 | F38: =SUM(F6:F35) -> 0 | H38: 7500 | I38: =SUM('General information '!G36/WATER!I37) -> 0 | O38: =SUM(Q37+I37) -> 298 | Z38: =SUM(Y37:AJ37) -> -62 | AK38: =SUM(Y38-L38) -> 0
B39: =9*31 -> 279 | D39: =SUM(D6:D35) -> 0 | F39: =SUM(F6:F36) -> 0 | G39: =SUM(I37) -> 298 | H39: =SUM(H38+C38) -> 7500 | K39: =SUM(H39/G39) -> 25.167785 | AJ39: =SUM(C38-AK38) -> 0 | AM39: =SUM(AJ39/AO38) -> #DIV/0!

Sheet GEN
B1: GEN1 | C1: RUN HR | D1: Fuel Counter Index | E1: Cons /day | F1: Diesel L/H | H1: next service | I1: ALARM | J1: GEN2 | K1: RUN HR | L1: Fuel Counter Index | M1: Cons /day | N1: Diesel L/H | P1: next service | Q1: ALARM | R1: GEN3 | S1: RUN HR | T1: Fuel Counter Index | U1: Cons /day | V1: Diesel L/H | X1: next service | Y1: ALARM | Z1: RH total | AA1: Gen Con /day | AB1: Total Deisel Cons/day | AC1: H /L | AD1: TOAL KW GEN | AI1: fuel Consuption | AK1: AVG KW/h
A2: =[2]GEN!$A$32 -> 44681 | B2: =[2]GEN!B32 -> 11629 | C2: =[2]GEN!C32 -> 0 | D2: =[2]GEN!D32 -> 670266 | E2: =[2]GEN!E32 -> 0 | F2: =[2]GEN!F32 -> 0 | G2: =[2]GEN!G32 -> 0 | H2: =[2]GEN!H32 -> 11690 | I2: =[2]GEN!I32 -> ok | ... AL2: =[2]GEN!AL32 -> 0
A3: =ELEC!C4 -> 44682 | B3: =B2 -> 11629 | C3: =B3-B2 -> 0 | D3: =D2+C3*250 -> 670266 | E3: =SUM(D3-D2) -> 0 | F3: =IF(C3>0,E3/C3,0) -> 0 | G3: =[4]GEN!G32 -> 0 | H3: =H2 -> 11690 | I3: =IF(B3-H3<=0,"ok","oil change") -> ok | J3: =J2 -> 10796 | K3: =J3-J2 -> 0 | L3: =L2 -> 382191 | M3: =SUM(L3-L2) -> 0 | N3: 250 | O3: =[4]GEN!O32 -> 0 | P3: =P2 -> 10873 | Q3: =IF(J3-P3<=0,"ok","oil change") -> ok | R3: =R2 -> 13880 | S3: =R3-R2 -> 0 | T3: =T2+U3 -> 409512 | U3: =V3*S3 -> 0 | V3: 250 | W3: =[4]GEN!W32 -> 0 | X3: =X2 -> 13873 | Y3: =IF(R3-X3<=0,"ok","oil change") -> oil change | Z3: =C3+K3+S3 -> 0 | AA3: =U3+M3+E3 -> 0 | AB3: =V3+N3+F3 -> 500 | AC3: =IF(Z3>0,AA3/Z3,0) -> 0 | AD3: =ELEC!Q4 -> 0 | AE3: =SUM(AD3/Z3) -> #DIV/0! | AF3: =SUM(AE3/1600) -> #DIV/0! | AG3: =SUM(360*AF3) -> #DIV/0! | AH3: =SUM(AC3-AG3) -> #DIV/0! | AI3: =AD3*AJ3 -> 0 | AJ3: =305/1185 -> 0.25738397 | AK3: =AI3/Z3 -> #DIV/0! | AL3: =IF(Z3=0,0,1) -> 0
A4: =ELEC!C5 -> 44683 | B4: =B3 -> 11629 | C4: =B4-B3 -> 0 | D4: =D3+C4*85 -> 670266 | E4: =SUM(D4-D3) -> 0 | F4: =IF(C4>0,E4/C4,0) -> 0 | H4: =H3 -> 11690 | I4: =IF(B4-H4<=0,"ok","oil change") -> ok | J4: =J3 -> 10796 | K4: =J4-J3 -> 0 | L4: =L3 -> 382191 | M4: =SUM(L4-L3) -> 0 | N4: 250 | P4: =P3 -> 10873 | Q4: =IF(J4-P4<=0,"ok","oil change") -> ok | R4: =R3 -> 13880 | S4: =R4-R3 -> 0 | T4: =T3+U4 -> 409512 | U4: =V4*S4 -> 0 | V4: 250 | X4: =X3 -> 13873 | Y4: =IF(R4-X4<=0,"ok","oil change") -> oil change | Z4: =C4+K4+S4 -> 0 | AA4: =U4+M4+E4 -> 0 | AB4: =V4+N4+F4 -> 500 | AC4: =IF(Z4>0,AA4/Z4,0) -> 0 | AD4: =ELEC!Q5 -> 0 | AE4: =SUM(AD4/Z4) -> #DIV/0! | AF4: =SUM(AE4/1600) -> #DIV/0! | AG4: =SUM(360*AF4) -> #DIV/0! | AH4: =SUM(AC4-AG4) -> #DIV/0! | AI4: =AD4*AJ4 -> 0 | AJ4: =305/1185 -> 0.25738397 | AK4: =AI4/Z4 -> #DIV/0! | AL4: =IF(Z4=0,0,1) -> 0
A5: =ELEC!C6 -> 44684 | B5: 11631 | C5: =B5-B4 -> 2 | D5: =D4+C5*85 -> 670436 | E5: =SUM(D5-D4) -> 170 | F5: =IF(C5>0,E5/C5,0) -> 85 | H5: =H4 -> 11690 | I5: =IF(B5-H5<=0,"ok","oil change") -> ok | J5: 10798 | K5: =J5-J4 -> 2 | L5: =L4 -> 382191 | M5: =SUM(L5-L4) -> 0 | N5: 250 | P5: =P4 -> 10873 | Q5: =IF(J5-P5<=0,"ok","oil change") -> ok | R5: 13891 | S5: =R5-R4 -> 11 | T5: =T4+U5 -> 412262 | U5: =V5*S5 -> 2750 | V5: 250 | X5: =X4 -> 13873 | Y5: =IF(R5-X5<=0,"ok","oil change") -> oil change | Z5: =C5+K5+S5 -> 15 | AA5: =U5+M5+E5 -> 2920 | AB5: =V5+N5+F5 -> 585 | AC5: =IF(Z5>0,AA5/Z5,0) -> 194.66667 | AD5: =ELEC!Q6 -> 6018 | AE5: =SUM(AD5/Z5) -> 401.2 | AF5: =SUM(AE5/1600) -> 0.25075 | AG5: =SUM(320*AF5) -> 80.24 | AH5: =SUM(AC5-AG5) -> 114.42667 | AI5: =AD5*AJ5 -> 1548.9367 | AJ5: =305/1185 -> 0.25738397 | AK5: =AI5/Z5 -> 103.26245 | AL5: =IF(Z5=0,0,1) -> 1
A6: =ELEC!C7 -> 44685 | B6: 11637 | C6: =B6-B5 -> 6 | D6: =D5+C6*85 -> 670946 | E6: =SUM(D6-D5) -> 510 | F6: =IF(C6>0,E6/C6,0) -> 85 | H6: =H5 -> 11690 | I6: =IF(B6-H6<=0,"ok","oil change") -> ok | J6: 10798 | K6: =J6-J5 -> 0 | L6: =(K6*N5)+L5 -> 382191 | M6: =SUM(L6-L5) -> 0 | N6: 250 | P6: =P5 -> 10873 | Q6: =IF(J6-P6<=0,"ok","oil change") -> ok | R6: 13896 | S6: =R6-R5 -> 5 | T6: =T5+U6 -> 413512 | U6: =V6*S6 -> 1250 | V6: 250 | X6: =X5+180 -> 14053 | Y6: =IF(R6-X6<=0,"ok","oil change") -> ok | Z6: =C6+K6+S6 -> 11 | AA6: =U6+M6+E6 -> 1760 | AB6: =V6+N6+F6 -> 585 | AC6: =IF(Z6>0,AA6/Z6,0) -> 160 | AD6: =ELEC!Q7 -> 3974 | AE6: =SUM(AD6/Z6) -> 361.27273 | AF6: =SUM(AE6/1600) -> 0.22579545 | AG6: =SUM(320*AF6) -> 72.254545 | AH6: =SUM(AC6-AG6) -> 87.745455 | AI6: =AD6*AJ6 -> 1022.8439 | AJ6: =305/1185 -> 0.25738397 | AK6: =AI6/Z6 -> 92.985807 | AL6: =IF(Z6=0,0,1) -> 1
A7: =ELEC!C8 -> 44686 | B7: 11645 | C7: =B7-B6 -> 8 | D7: =D6+C7*85 -> 671626 | E7: =SUM(D7-D6) -> 680 | F7: =IF(C7>0,E7/C7,0) -> 85 | H7: =H6 -> 11690 | I7: =IF(B7-H7<=0,"ok","oil change") -> ok | J7: =J6 -> 10798 | L7: =(K7*N6)+L6 -> 382191 | M7: =SUM(L7-L6) -> 0 | N7: 250 | P7: =P6 -> 10873 | Q7: =IF(J7-P7<=0,"ok","oil change") -> ok | R7: 13898 | S7: =R7-R6 -> 2 | T7: =T6+U7 -> 414012 | U7: =V7*S7 -> 500 | V7: 250 | X7: =X6 -> 14053 | Y7: =IF(R7-X7<=0,"ok","oil change") -> ok | Z7: =C7+K7+S7 -> 10 | AA7: =U7+M7+E7 -> 1180 | AB7: =V7+N7+F7 -> 585 | AC7: =IF(Z7>0,AA7/Z7,0) -> 118 | AD7: =ELEC!Q8 -> 2900 | AE7: =SUM(AD7/Z7) -> 290 | AF7: =SUM(AE7/1600) -> 0.18125 | AG7: =SUM(AF7/1600) -> 0.00011328125 | AH7: =SUM(AC7-AG7) -> 117.99989 | AI7: =AD7*AJ7 -> 746.4135 | AJ7: =305/1185 -> 0.25738397 | AK7: =AI7/Z7 -> 74.64135 | AL7: =IF(Z7=0,0,1) -> 1
A8: =ELEC!C9 -> 44687 | B8: 11645 | C8: =B8-B7 -> 0 | D8: =D7+C8*85 -> 671626 | E8: =SUM(D8-D7) -> 0 | F8: =IF(C8>0,E8/C8,0) -> 0 | H8: =H7 -> 11690 | I8: =IF(B8-H8<=0,"ok","oil change") -> ok | J8: =J7 -> 10798 | K8: =J8-J7 -> 0 | L8: =(K8*N7)+L7 -> 382191 | M8: =SUM(L8-L7) -> 0 | N8: 250 | P8: =P7 -> 10873 | Q8: =IF(J8-P8<=0,"ok","oil change") -> ok | R8: 13898 | S8: =R8-R7 -> 0 | T8: =T7+U8 -> 414012 | U8: =V8*S8 -> 0 | V8: 250 | X8: =X7 -> 14053 | Y8: =IF(R8-X8<=0,"ok","oil change") -> ok | Z8: =C8+K8+S8 -> 0 | AA8: =U8+M8+E8 -> 0 | AB8: =V8+N8+F8 -> 500 | AC8: =IF(Z8>0,AA8/Z8,0) -> 0 | AD8: =ELEC!Q9 -> 0 | AE8: =SUM(AD8/Z8) -> #DIV/0! | AF8: =SUM(AE8/1600) -> #DIV/0! | AG8: =SUM(AF8/1600) -> #DIV/0! | AH8: =SUM(AC8-AG8) -> #DIV/0! | AI8: =AD8*AJ8 -> 0 | AJ8: =305/1185 -> 0.25738397 | AK8: =AI8/Z8 -> #DIV/0! | AL8: =IF(Z8=0,0,1) -> 0
A9: =ELEC!C10 -> 44688 | B9: =B8 -> 11645 | C9: =B9-B8 -> 0 | D9: =D8+C9*85 -> 671626 | E9: =SUM(D9-D8) -> 0 | F9: =IF(C9>0,E9/C9,0) -> 0 | H9: =H8 -> 11690 | I9: =IF(B9-H9<=0,"ok","oil change") -> ok | J9: =J8 -> 10798 | K9: =J9-J8 -> 0 | L9: =(K9*N8)+L8 -> 382191 | M9: =SUM(L9-L8) -> 0 | N9: 250 | P9: =P8 -> 10873 | Q9: =IF(J9-P9<=0,"ok","oil change") -> ok | R9: =R8 -> 13898 | S9: =R9-R8 -> 0 | T9: =T8+U9 -> 414012 | U9: =V9*S9 -> 0 | V9: 250 | X9: =X8 -> 14053 | Y9: =IF(R9-X9<=0,"ok","oil change") -> ok | Z9: =C9+K9+S9 -> 0 | AA9: =U9+M9+E9 -> 0 | AB9: =V9+N9+F9 -> 500 | AC9: =IF(Z9>0,AA9/Z9,0) -> 0 | AD9: =ELEC!Q10 -> 0 | AE9: =SUM(AD9/Z9) -> #DIV/0! | AF9: =SUM(AE9/1600) -> #DIV/0! | AG9: =SUM(AF9/1600) -> #DIV/0! | AH9: =SUM(AC9-AG9) -> #DIV/0! | AI9: =AD9*AJ9 -> 0 | AJ9: =305/1185 -> 0.25738397 | AK9: =AI9/Z9 -> #DIV/0! | AL9: =IF(Z9=0,0,1) -> 0
A10: =ELEC!C11 -> 44689 | B10: 11651 | C10: =B10-B9 -> 6 | D10: =D9+C10*85 -> 672136 | E10: =SUM(D10-D9) -> 510 | F10: =IF(C10>0,E10/C10,0) -> 85 | H10: 11690 | I10: =IF(B10-H10<=0,"ok","oil change") -> ok | J10: =J9 -> 10798 | K10: =J10-J9 -> 0 | L10: =(K10*N9)+L9 -> 382191 | M10: =SUM(L10-L9) -> 0 | N10: 250 | P10: =P9 -> 10873 | Q10: =IF(J10-P10<=0,"ok","oil change") -> ok | R10: 13901 | S10: =R10-R9 -> 3 | T10: =T9+U10 -> 414762 | U10: =V10*S10 -> 750 | V10: 250 | X10: =X9 -> 14053 | Y10: =IF(R10-X10<=0,"ok","oil change") -> ok | Z10: =C10+K10+S10 -> 9 | AA10: =U10+M10+E10 -> 1260 | AB10: =V10+N10+F10 -> 585 | AC10: =IF(Z10>0,AA10/Z10,0) -> 140 | AD10: =ELEC!Q11 -> 2980 | AE10: =SUM(AD10/Z10) -> 331.11111 | AF10: =SUM(AE10/1600) -> 0.20694444 | AG10: =SUM(AF10/1600) -> 0.00012934028 | AH10: =SUM(AC10-AG10) -> 139.99987 | AI10: =AD10*AJ10 -> 767.00422 | AJ10: =305/1185 -> 0.25738397 | AK10: =AI10/Z10 -> 85.222691 | AL10: =IF(Z10=0,0,1) -> 1
A11: =ELEC!C12 -> 44690 | B11: 11662 | C11: =B11-B10 -> 11 | D11: =D10+C11*85 -> 673071 | E11: =SUM(D11-D10) -> 935 | F11: =IF(C11>0,E11/C11,0) -> 85 | H11: =H10 -> 11690 | I11: =IF(B11-H11<=0,"ok","oil change") -> ok | J11: =J10 -> 10798 | K11: =J11-J10 -> 0 | L11: =(K11*N10)+L10 -> 382191 | M11: =SUM(L11-L10) -> 0 | N11: 250 | P11: =P10 -> 10873 | Q11: =IF(J11-P11<=0,"ok","oil change") -> ok | R11: =R10 -> 13901 | S11: =R11-R10 -> 0 | T11: =T10+U11 -> 414762 | U11: =V11*S11 -> 0 | V11: 250 | X11: =X10 -> 14053 | Y11: =IF(R11-X11<=0,"ok","oil change") -> ok | Z11: =C11+K11+S11 -> 11 | AA11: =U11+M11+E11 -> 935 | AB11: =V11+N11+F11 -> 585 | AC11: =IF(Z11>0,AA11/Z11,0) -> 85 | AD11: =ELEC!Q12 -> 3134 | AE11: =SUM(AD11/Z11) -> 284.90909 | AF11: =SUM(AE11/1600) -> 0.17806818 | AG11: =SUM(AF11/1600) -> 0.00011129261 | AH11: =SUM(AC11-AG11) -> 84.999889 | AI11: =AD11*AJ11 -> 806.64135 | AJ11: =305/1185 -> 0.25738397 | AK11: =AI11/Z11 -> 73.331032 | AL11: =IF(Z11=0,0,1) -> 1
A12: =ELEC!C13 -> 44691 | B12: 11673 | C12: =B12-B11 -> 11 | D12: =D11+C12*85 -> 674006 | E12: =SUM(D12-D11) -> 935 | F12: =IF(C12>0,E12/C12,0) -> 85 | H12: =H11 -> 11690 | I12: =IF(B12-H12<=0,"ok","oil change") -> ok | J12: =J11 -> 10798 | K12: =J12-J11 -> 0 | L12: =(K12*N11)+L11 -> 382191 | M12: =SUM(L12-L11) -> 0 | N12: 250 | P12: =P11 -> 10873 | Q12: =IF(J12-P12<=0,"ok","oil change") -> ok | R12: =R11 -> 13901 | S12: =R12-R11 -> 0 | T12: =T11+U12 -> 414762 | U12: =V12*S12 -> 0 | V12: 250 | X12: =X11 -> 14053 | Y12: =IF(R12-X12<=0,"ok","oil change") -> ok | Z12: =C12+K12+S12 -> 11 | AA12: =U12+M12+E12 -> 935 | AB12: =V12+N12+F12 -> 585 | AC12: =IF(Z12>0,AA12/Z12,0) -> 85 | AD12: =ELEC!Q13 -> 2868 | AE12: =SUM(AD12/Z12) -> 260.72727 | AF12: =SUM(AE12/1600) -> 0.16295455 | AG12: =SUM(AF12/1600) -> 0.00010184659 | AH12: =SUM(AC12-AG12) -> 84.999898 | AI12: =AD12*AJ12 -> 738.17722 | AJ12: =305/1185 -> 0.25738397 | AK12: =AI12/Z12 -> 67.10702 | AL12: =IF(Z12=0,0,1) -> 1
A13: =ELEC!C14 -> 44692 | B13: 11683 | C13: =B13-B12 -> 10 | D13: =D12+C13*85 -> 674856 | E13: =SUM(D13-D12) -> 850 | F13: =IF(C13>0,E13/C13,0) -> 85 | H13: =H12 -> 11690 | I13: =IF(B13-H13<=0,"ok","oil change") -> ok | J13: =J12 -> 10798 | K13: =J13-J12 -> 0 | L13: =(K13*N12)+L12 -> 382191 | M13: =SUM(L13-L12) -> 0 | N13: 250 | P13: =P12 -> 10873 | Q13: =IF(J13-P13<=0,"ok","oil change") -> ok | R13: =R12 -> 13901 | S13: =R13-R12 -> 0 | T13: =T12+U13 -> 414762 | U13: =V13*S13 -> 0 | V13: 250 | X13: =X12 -> 14053 | Y13: =IF(R13-X13<=0,"ok","oil change") -> ok | Z13: =C13+K13+S13 -> 10 | AA13: =U13+M13+E13 -> 850 | AB13: =V13+N13+F13 -> 585 | AC13: =IF(Z13>0,AA13/Z13,0) -> 85 | AD13: =ELEC!Q14 -> 3001 | AE13: =SUM(AD13/Z13) -> 300.1 | AF13: =SUM(AE13/1600) -> 0.1875625 | AG13: =SUM(AF13/1600) -> 0.00011722656 | AH13: =SUM(AC13-AG13) -> 84.999883 | AI13: =AD13*AJ13 -> 772.40928 | AJ13: =305/1185 -> 0.25738397 | AK13: =AI13/Z13 -> 77.240928 | AL13: =IF(Z13=0,0,1) -> 1
A14: =ELEC!C15 -> 44693 | B14: 11692 | C14: =B14-B13 -> 9 | D14: =D13+C14*85 -> 675621 | E14: =SUM(D14-D13) -> 765 | F14: =IF(C14>0,E14/C14,0) -> 85 | H14: =H13 -> 11690 | I14: =IF(B14-H14<=0,"ok","oil change") -> oil change | J14: =J13 -> 10798 | K14: =J14-J13 -> 0 | L14: =(K14*N13)+L13 -> 382191 | M14: =SUM(L14-L13) -> 0 | N14: 250 | P14: =P13 -> 10873 | Q14: =IF(J14-P14<=0,"ok","oil change") -> ok | R14: =R13 -> 13901 | S14: =R14-R13 -> 0 | T14: =T13+U14 -> 414762 | U14: =V14*S14 -> 0 | V14: 250 | X14: =X13 -> 14053 | Y14: =IF(R14-X14<=0,"ok","oil change") -> ok | Z14: =C14+K14+S14 -> 9 | AA14: =U14+M14+E14 -> 765 | AB14: =V14+N14+F14 -> 585 | AC14: =IF(Z14>0,AA14/Z14,0) -> 85 | AD14: =ELEC!Q15 -> 2606 | AE14: =SUM(AD14/Z14) -> 289.55556 | AF14: =SUM(AE14/1600) -> 0.18097222 | AG14: =SUM(AF14/1600) -> 0.00011310764 | AH14: =SUM(AC14-AG14) -> 84.999887 | AI14: =AD14*AJ14 -> 670.74262 | AJ14: =305/1185 -> 0.25738397 | AK14: =AI14/Z14 -> 74.526957 | AL14: =IF(Z14=0,0,1) -> 1
A15: =ELEC!C16 -> 44694 | B15: =B14 -> 11692 | C15: =B15-B14 -> 0 | D15: =D14+C15*85 -> 675621 | E15: =SUM(D15-D14) -> 0 | F15: =IF(C15>0,E15/C15,0) -> 0 | H15: =H14 -> 11690 | I15: =IF(B15-H15<=0,"ok","oil change") -> oil change | J15: =J14 -> 10798 | K15: =J15-J14 -> 0 | L15: =(K15*N14)+L14 -> 382191 | M15: =SUM(L15-L14) -> 0 | N15: 250 | P15: =P14 -> 10873 | Q15: =IF(J15-P15<=0,"ok","oil change") -> ok | R15: =R14 -> 13901 | S15: =R15-R14 -> 0 | T15: =T14+U15 -> 414762 | U15: =V15*S15 -> 0 | V15: 250 | X15: =X14 -> 14053 | Y15: =IF(R15-X15<=0,"ok","oil change") -> ok | Z15: =C15+K15+S15 -> 0 | AA15: =U15+M15+E15 -> 0 | AB15: =V15+N15+F15 -> 500 | AC15: =IF(Z15>0,AA15/Z15,0) -> 0 | AD15: =ELEC!Q16 -> 0 | AE15: =SUM(AD15/Z15) -> #DIV/0! | AF15: =SUM(AE15/1600) -> #DIV/0! | AG15: =SUM(AF15/1600) -> #DIV/0! | AH15: =SUM(AC15-AG15) -> #DIV/0! | AI15: =AD15*AJ15 -> 0 | AJ15: =305/1185 -> 0.25738397 | AK15: =AI15/Z15 -> #DIV/0! | AL15: =IF(Z15=0,0,1) -> 0
A16: =ELEC!C17 -> 44695 | B16: =B15 -> 11692 | C16: =B16-B15 -> 0 | D16: =D15+C16*85 -> 675621 | E16: =SUM(D16-D15) -> 0 | F16: =IF(C16>0,E16/C16,0) -> 0 | H16: =H15 -> 11690 | I16: =IF(B16-H16<=0,"ok","oil change") -> oil change | J16: =J15 -> 10798 | K16: =J16-J15 -> 0 | L16: =(K16*N15)+L15 -> 382191 | M16: =SUM(L16-L15) -> 0 | N16: 250 | P16: =P15 -> 10873 | Q16: =IF(J16-P16<=0,"ok","oil change") -> ok | R16: =R15 -> 13901 | S16: =R16-R15 -> 0 | T16: =T15+U16 -> 414762 | U16: =V16*S16 -> 0 | V16: 250 | X16: =X15 -> 14053 | Y16: =IF(R16-X16<=0,"ok","oil change") -> ok | Z16: =C16+K16+S16 -> 0 | AA16: =U16+M16+E16 -> 0 | AB16: =V16+N16+F16 -> 500 | AC16: =IF(Z16>0,AA16/Z16,0) -> 0 | AD16: =ELEC!Q17 -> 0 | AE16: =SUM(AD16/Z16) -> #DIV/0! | AF16: =SUM(AE16/1600) -> #DIV/0! | AG16: =SUM(AF16/1600) -> #DIV/0! | AH16: =SUM(AC16-AG16) -> #DIV/0! | AI16: =AD16*AJ16 -> 0 | AJ16: =305/1185 -> 0.25738397 | AK16: =AI16/Z16 -> #DIV/0! | AL16: =IF(Z16=0,0,1) -> 0
A17: =ELEC!C18 -> 44696 | B17: =B16 -> 11692 | C17: =B17-B16 -> 0 | D17: =D16+C17*85 -> 675621 | E17: =SUM(D17-D16) -> 0 | F17: =IF(C17>0,E17/C17,0) -> 0 | H17: =H16 -> 11690 | I17: =IF(B17-H17<=0,"ok","oil change") -> oil change | J17: =J16 -> 10798 | K17: =J17-J16 -> 0 | L17: =(K17*N16)+L16 -> 382191 | M17: =SUM(L17-L16) -> 0 | N17: 250 | P17: =P16 -> 10873 | Q17: =IF(J17-P17<=0,"ok","oil change") -> ok | R17: =R16 -> 13901 | S17: =R17-R16 -> 0 | T17: =T16+U17 -> 414762 | U17: =V17*S17 -> 0 | V17: 250 | X17: =X16 -> 14053 | Y17: =IF(R17-X17<=0,"ok","oil change") -> ok | Z17: =C17+K17+S17 -> 0 | AA17: =U17+M17+E17 -> 0 | AB17: =V17+N17+F17 -> 500 | AC17: =IF(Z17>0,AA17/Z17,0) -> 0 | AD17: =ELEC!Q18 -> 0 | AE17: =SUM(AD17/Z17) -> #DIV/0! | AF17: =SUM(AE17/1600) -> #DIV/0! | AG17: =SUM(AF17/1600) -> #DIV/0! | AH17: =SUM(AC17-AG17) -> #DIV/0! | AI17: =AD17*AJ17 -> 0 | AJ17: =305/1185 -> 0.25738397 | AK17: =AI17/Z17 -> #DIV/0! | AL17: =IF(Z17=0,0,1) -> 0
A18: =ELEC!C19 -> 44697 | B18: =B17 -> 11692 | C18: =B18-B17 -> 0 | D18: =D17+C18*85 -> 675621 | E18: =SUM(D18-D17) -> 0 | F18: =IF(C18>0,E18/C18,0) -> 0 | H18: =H17 -> 11690 | I18: =IF(B18-H18<=0,"ok","oil change") -> oil change | J18: =J17 -> 10798 | K18: =J18-J17 -> 0 | L18: =(K18*N17)+L17 -> 382191 | M18: =SUM(L18-L17) -> 0 | N18: 250 | P18: =P17 -> 10873 | Q18: =IF(J18-P14<=0,"ok","oil change") -> ok | R18: =R17 -> 13901 | S18: =R18-R17 -> 0 | T18: =T17+U18 -> 414762 | U18: =V18*S18 -> 0 | V18: 250 | X18: =X17 -> 14053 | Y18: =IF(R18-X18<=0,"ok","oil change") -> ok | Z18: =C18+K18+S18 -> 0 | AA18: =U18+M18+E18 -> 0 | AB18: =V18+N18+F18 -> 500 | AC18: =IF(Z18>0,AA18/Z18,0) -> 0 | AD18: =ELEC!Q19 -> 0 | AE18: =SUM(AD18/Z18) -> #DIV/0! | AF18: =SUM(AE18/1600) -> #DIV/0! | AG18: =SUM(AF18/1600) -> #DIV/0! | AH18: =SUM(AC18-AG18) -> #DIV/0! | AI18: =AD18*AJ18 -> 0 | AJ18: =305/1185 -> 0.25738397 | AK18: =AI18/Z18 -> #DIV/0! | AL18: =IF(Z18=0,0,1) -> 0
A19: =ELEC!C20 -> 44698 | B19: =B18 -> 11692 | C19: =B19-B18 -> 0 | D19: =D18+C19*85 -> 675621 | E19: =SUM(D19-D18) -> 0 | F19: =IF(C19>0,E19/C19,0) -> 0 | H19: =H18 -> 11690 | I19: =IF(B19-H19<=0,"ok","oil change") -> oil change | J19: =J18 -> 10798 | K19: =J19-J18 -> 0 | L19: =(K19*N18)+L18 -> 382191 | M19: =SUM(L19-L18) -> 0 | N19: 250 | P19: =P18 -> 10873 | Q19: =IF(J19-P19<=0,"ok","oil change") -> ok | R19: =R18 -> 13901 | S19: =R19-R18 -> 0 | T19: =T18+U19 -> 414762 | U19: =V19*S19 -> 0 | V19: 250 | X19: =X18 -> 14053 | Y19: =IF(R19-X19<=0,"ok","oil change") -> ok | Z19: =C19+K19+S19 -> 0 | AA19: =U19+M19+E19 -> 0 | AB19: =V19+N19+F19 -> 500 | AC19: =IF(Z19>0,AA19/Z19,0) -> 0 | AD19: =ELEC!Q20 -> 0 | AE19: =SUM(AD19/Z19) -> #DIV/0! | AF19: =SUM(AE19/1600) -> #DIV/0! | AG19: =SUM(AF19/1600) -> #DIV/0! | AH19: =SUM(AC19-AG19) -> #DIV/0! | AI19: =AD19*AJ19 -> 0 | AJ19: =305/1185 -> 0.25738397 | AK19: =AI19/Z19 -> #DIV/0! | AL19: =IF(Z19=0,0,1) -> 0
A20: =ELEC!C21 -> 44699 | B20: =B19 -> 11692 | C20: =B20-B19 -> 0 | D20: =D19+C20*85 -> 675621 | E20: =SUM(D20-D19) -> 0 | F20: =IF(C20>0,E20/C20,0) -> 0 | H20: =H19 -> 11690 | I20: =IF(B20-H20<=0,"ok","oil change") -> oil change | J20: =J19 -> 10798 | K20: =J20-J19 -> 0 | L20: =(K20*N19)+L19 -> 382191 | M20: =SUM(L20-L19) -> 0 | N20: 250 | P20: =P19 -> 10873 | Q20: =IF(J20-P20<=0,"ok","oil change") -> ok | R20: =R19 -> 13901 | S20: =R20-R19 -> 0 | T20: =T19+U20 -> 414762 | U20: =V20*S20 -> 0 | V20: 250 | X20: =X19 -> 14053 | Y20: =IF(R20-X20<=0,"ok","oil change") -> ok | Z20: =C20+K20+S20 -> 0 | AA20: =U20+M20+E20 -> 0 | AB20: =V20+N20+F20 -> 500 | AC20: =IF(Z20>0,AA20/Z20,0) -> 0 | AD20: =ELEC!Q21 -> 0 | AE20: =SUM(AD20/Z20) -> #DIV/0! | AF20: =SUM(AE20/1600) -> #DIV/0! | AG20: =SUM(AF20/1600) -> #DIV/0! | AH20: =SUM(AC20-AG20) -> #DIV/0! | AI20: =AD20*AJ20 -> 0 | AJ20: =305/1185 -> 0.25738397 | AK20: =AI20/Z20 -> #DIV/0! | AL20: =IF(Z20=0,0,1) -> 0
A21: =ELEC!C22 -> 44700 | B21: =B20 -> 11692 | C21: =B21-B20 -> 0 | D21: =D20+C21*85 -> 675621 | E21: =SUM(D21-D20) -> 0 | F21: =IF(C21>0,E21/C21,0) -> 0 | H21: =H20 -> 11690 | I21: =IF(B21-H21<=0,"ok","oil change") -> oil change | J21: =J20 -> 10798 | K21: =J21-J20 -> 0 | L21: =(K21*N20)+L20 -> 382191 | M21: =SUM(L21-L20) -> 0 | N21: 250 | P21: =P20 -> 10873 | Q21: =IF(J21-P21<=0,"ok","oil change") -> ok | R21: =R20 -> 13901 | S21: =R21-R20 -> 0 | T21: =T20+U21 -> 414762 | U21: =V21*S21 -> 0 | V21: 250 | X21: =X20 -> 14053 | Y21: =IF(R21-X21<=0,"ok","oil change") -> ok | Z21: =C21+K21+S21 -> 0 | AA21: =U21+M21+E21 -> 0 | AB21: =V21+N21+F21 -> 500 | AC21: =IF(Z21>0,AA21/Z21,0) -> 0 | AD21: =ELEC!Q22 -> 0 | AE21: =SUM(AD21/Z21) -> #DIV/0! | AF21: =SUM(AE21/1600) -> #DIV/0! | AG21: =SUM(AF21/1600) -> #DIV/0! | AH21: =SUM(AC21-AG21) -> #DIV/0! | AI21: =AD21*AJ21 -> 0 | AJ21: =305/1185 -> 0.25738397 | AK21: =AI21/Z21 -> #DIV/0! | AL21: =IF(Z21=0,0,1) -> 0
A22: =ELEC!C23 -> 44701 | B22: =B21 -> 11692 | C22: =B22-B21 -> 0 | D22: =D21+C22*85 -> 675621 | E22: =150*C22 -> 0 | F22: =IF(C22>0,E22/C22,0) -> 0 | H22: =H21 -> 11690 | I22: =IF(B22-H22<=0,"ok","oil change") -> oil change | J22: =J21 -> 10798 | K22: =J22-J21 -> 0 | L22: =(K22*N21)+L21 -> 382191 | M22: =SUM(L22-L21) -> 0 | N22: 250 | P22: =P21 -> 10873 | Q22: =IF(J22-P22<=0,"ok","oil change") -> ok | R22: =R21 -> 13901 | S22: =R22-R21 -> 0 | T22: =T21+U22 -> 414762 | U22: =V22*S22 -> 0 | V22: 250 | X22: =X21 -> 14053 | Y22: =IF(R22-X22<=0,"ok","oil change") -> ok | Z22: =C22+K22+S22 -> 0 | AA22: =U22+M22+E22 -> 0 | AB22: =V22+N22+F22 -> 500 | AC22: =IF(Z22>0,AA22/Z22,0) -> 0 | AD22: =ELEC!Q23 -> 0 | AE22: =SUM(AD22/Z22) -> #DIV/0! | AF22: =SUM(AE22/1600) -> #DIV/0! | AG22: =SUM(AF22/1600) -> #DIV/0! | AH22: =SUM(AC22-AG22) -> #DIV/0! | AI22: =AD22*AJ22 -> 0 | AJ22: =305/1185 -> 0.25738397 | AK22: =AI22/Z22 -> #DIV/0! | AL22: =IF(Z22=0,0,1) -> 0
A23: =ELEC!C24 -> 44702 | B23: =B22 -> 11692 | C23: =B23-B22 -> 0 | D23: =D22+C23*85 -> 675621 | E23: =150*C23 -> 0 | F23: =IF(C23>0,E23/C23,0) -> 0 | H23: =H22 -> 11690 | I23: =IF(B23-H23<=0,"ok","oil change") -> oil change | J23: =J22 -> 10798 | K23: =J23-J22 -> 0 | L23: =(K23*N22)+L22 -> 382191 | M23: =SUM(L23-L22) -> 0 | N23: 250 | P23: =P22 -> 10873 | Q23: =IF(J23-P23<=0,"ok","oil change") -> ok | R23: =R22 -> 13901 | S23: =R23-R22 -> 0 | T23: =T22+U23 -> 414762 | U23: =V23*S23 -> 0 | V23: 250 | X23: =X22 -> 14053 | Y23: =IF(R23-X23<=0,"ok","oil change") -> ok | Z23: =C23+K23+S23 -> 0 | AA23: =U23+M23+E23 -> 0 | AB23: =V23+N23+F23 -> 500 | AC23: =IF(Z23>0,AA23/Z23,0) -> 0 | AD23: =ELEC!Q24 -> 0 | AE23: =SUM(AD23/Z23) -> #DIV/0! | AF23: =SUM(AE23/1600) -> #DIV/0! | AG23: =SUM(AF23/1600) -> #DIV/0! | AH23: =SUM(AC23-AG23) -> #DIV/0! | AI23: =AD23*AJ23 -> 0 | AJ23: =305/1185 -> 0.25738397 | AK23: =AI23/Z23 -> #DIV/0! | AL23: =IF(Z23=0,0,1) -> 0
A24: =ELEC!C25 -> 44703 | B24: =B23 -> 11692 | C24: =B24-B23 -> 0 | D24: =D23+C24*85 -> 675621 | E24: =SUM(D24-D23) -> 0 | F24: =IF(C24>0,E24/C24,0) -> 0 | H24: =H23 -> 11690 | I24: =IF(B24-H24<=0,"ok","oil change") -> oil change | J24: =J23 -> 10798 | K24: =J24-J23 -> 0 | L24: =(K24*N23)+L23 -> 382191 | M24: =SUM(L24-L23) -> 0 | N24: 250 | P24: =P23 -> 10873 | Q24: =IF(J24-P24<=0,"ok","oil change") -> ok | R24: =R23 -> 13901 | S24: =R24-R23 -> 0 | T24: =T23+U24 -> 414762 | U24: =V24*S24 -> 0 | V24: 250 | X24: =X23 -> 14053 | Y24: =IF(R24-X24<=0,"ok","oil change") -> ok | Z24: =C24+K24+S24 -> 0 | AA24: =U24+M24+E24 -> 0 | AB24: =V24+N24+F24 -> 500 | AC24: =IF(Z24>0,AA24/Z24,0) -> 0 | AD24: =ELEC!Q25 -> 0 | AE24: =SUM(AD24/Z24) -> #DIV/0! | AF24: =SUM(AE24/1600) -> #DIV/0! | AG24: =SUM(AF24/1600) -> #DIV/0! | AH24: =SUM(AC24-AG24) -> #DIV/0! | AI24: =AD24*AJ24 -> 0 | AJ24: =305/1185 -> 0.25738397 | AK24: =AI24/Z24 -> #DIV/0! | AL24: =IF(Z24=0,0,1) -> 0
A25: =ELEC!C26 -> 44704 | B25: =B24 -> 11692 | C25: =B25-B24 -> 0 | D25: =D24+C25*85 -> 675621 | E25: =SUM(D25-D24) -> 0 | F25: =IF(C25>0,E25/C25,0) -> 0 | H25: =H24 -> 11690 | I25: =IF(B25-H25<=0,"ok","oil change") -> oil change | J25: =J24 -> 10798 | K25: =J25-J24 -> 0 | L25: =(K25*N24)+L24 -> 382191 | M25: =SUM(L25-L24) -> 0 | N25: 250 | P25: =P24 -> 10873 | Q25: =IF(J25-P25<=0,"ok","oil change") -> ok | R25: =R24 -> 13901 | S25: =R25-R24 -> 0 | T25: =T24+U25 -> 414762 | U25: =V25*S25 -> 0 | V25: 250 | X25: =X24 -> 14053 | Y25: =IF(R25-X25<=0,"ok","oil change") -> ok | Z25: =C25+K25+S25 -> 0 | AA25: =U25+M25+E25 -> 0 | AB25: =V25+N25+F25 -> 500 | AC25: =IF(Z25>0,AA25/Z25,0) -> 0 | AD25: =ELEC!Q26 -> 0 | AE25: =SUM(AD25/Z25) -> #DIV/0! | AF25: =SUM(AE25/1600) -> #DIV/0! | AG25: =SUM(AF25/1600) -> #DIV/0! | AH25: =SUM(AC25-AG25) -> #DIV/0! | AI25: =AD25*AJ25 -> 0 | AJ25: =305/1185 -> 0.25738397 | AK25: =AI25/Z25 -> #DIV/0! | AL25: =IF(Z25=0,0,1) -> 0
A26: =ELEC!C27 -> 44705 | B26: =B25 -> 11692 | C26: =B26-B25 -> 0 | D26: =D25+C26*85 -> 675621 | E26: =SUM(D26-D25) -> 0 | F26: =IF(C26>0,E26/C26,0) -> 0 | H26: =H25 -> 11690 | I26: =IF(B26-H26<=0,"ok","oil change") -> oil change | J26: =J25 -> 10798 | K26: =J26-J25 -> 0 | L26: =(K26*N25)+L25 -> 382191 | M26: =SUM(L26-L25) -> 0 | N26: 250 | P26: =P25 -> 10873 | Q26: =IF(J26-P26<=0,"ok","oil change") -> ok | R26: =R25 -> 13901 | S26: =R26-R25 -> 0 | T26: =T25+U26 -> 414762 | U26: =V26*S26 -> 0 | V26: 250 | X26: =X25 -> 14053 | Y26: =IF(R26-X26<=0,"ok","oil change") -> ok | Z26: =C26+K26+S26 -> 0 | AA26: =U26+M26+E26 -> 0 | AB26: =V26+N26+F26 -> 500 | AC26: =IF(Z26>0,AA26/Z26,0) -> 0 | AD26: =ELEC!Q27 -> 0 | AE26: =SUM(AD26/Z26) -> #DIV/0! | AF26: =SUM(AE26/1600) -> #DIV/0! | AG26: =SUM(AF26/1600) -> #DIV/0! | AH26: =SUM(AC26-AG26) -> #DIV/0! | AI26: =AD26*AJ26 -> 0 | AJ26: =305/1185 -> 0.25738397 | AK26: =AI26/Z26 -> #DIV/0! | AL26: =IF(Z26=0,0,1) -> 0
A27: =ELEC!C28 -> 44706 | B27: =B26 -> 11692 | C27: =B27-B26 -> 0 | D27: =D26+C27*85 -> 675621 | E27: =SUM(D27-D26) -> 0 | F27: =IF(C27>0,E27/C27,0) -> 0 | H27: =H26 -> 11690 | I27: =IF(B27-H27<=0,"ok","oil change") -> oil change | J27: =J26 -> 10798 | K27: =J27-J26 -> 0 | L27: =(K27*N26)+L26 -> 382191 | M27: =SUM(L27-L26) -> 0 | N27: 250 | P27: =P26 -> 10873 | Q27: =IF(J27-P27<=0,"ok","oil change") -> ok | R27: =R26 -> 13901 | S27: =R27-R26 -> 0 | T27: =T26+U27 -> 414762 | U27: =V27*S27 -> 0 | V27: 250 | X27: =X26 -> 14053 | Y27: =IF(R27-X27<=0,"ok","oil change") -> ok | Z27: =C27+K27+S27 -> 0 | AA27: =U27+M27+E27 -> 0 | AB27: =V27+N27+F27 -> 500 | AC27: =IF(Z27>0,AA27/Z27,0) -> 0 | AD27: =ELEC!Q28 -> 0 | AE27: =SUM(AD27/Z27) -> #DIV/0! | AF27: =SUM(AE27/1600) -> #DIV/0! | AG27: =SUM(AF27/1600) -> #DIV/0! | AH27: =SUM(AC27-AG27) -> #DIV/0! | AI27: =AD27*AJ27 -> 0 | AJ27: =305/1185 -> 0.25738397 | AK27: =AI27/Z27 -> #DIV/0! | AL27: =IF(Z27=0,0,1) -> 0
A28: =ELEC!C29 -> 44707 | B28: =B27 -> 11692 | C28: =B28-B27 -> 0 | D28: =D27+C28*85 -> 675621 | E28: =SUM(D28-D27) -> 0 | F28: =IF(C28>0,E28/C28,0) -> 0 | H28: =H27 -> 11690 | I28: =IF(B28-H28<=0,"ok","oil change") -> oil change | J28: =J27 -> 10798 | K28: =J28-J27 -> 0 | L28: =(K28*N27)+L27 -> 382191 | M28: =SUM(L28-L27) -> 0 | N28: 250 | P28: =P27 -> 10873 | Q28: =IF(J28-P28<=0,"ok","oil change") -> ok | R28: =R27 -> 13901 | S28: =R28-R27 -> 0 | T28: =T27+U28 -> 414762 | U28: =V28*S28 -> 0 | V28: 250 | X28: =X27 -> 14053 | Y28: =IF(R28-X28<=0,"ok","oil change") -> ok | Z28: =C28+K28+S28 -> 0 | AA28: =U28+M28+E28 -> 0 | AB28: =V28+N28+F28 -> 500 | AC28: =IF(Z28>0,AA28/Z28,0) -> 0 | AD28: =ELEC!Q29 -> 0 | AE28: =SUM(AD28/Z28) -> #DIV/0! | AF28: =SUM(AE28/1600) -> #DIV/0! | AG28: =SUM(AF28/1600) -> #DIV/0! | AH28: =SUM(AC28-AG28) -> #DIV/0! | AI28: =AD28*AJ28 -> 0 | AJ28: =305/1185 -> 0.25738397 | AK28: =AI28/Z28 -> #DIV/0! | AL28: =IF(Z28=0,0,1) -> 0
A29: =ELEC!C30 -> 44708 | B29: =B28 -> 11692 | C29: =B29-B28 -> 0 | D29: =D28+C29*85 -> 675621 | E29: =SUM(D29-D28) -> 0 | F29: =IF(C29>0,E29/C29,0) -> 0 | H29: =H28 -> 11690 | I29: =IF(B29-H29<=0,"ok","oil change") -> oil change | J29: =J28 -> 10798 | K29: =J29-J28 -> 0 | L29: =(K29*N28)+L28 -> 382191 | M29: =SUM(L29-L28) -> 0 | N29: 250 | P29: =P28 -> 10873 | Q29: =IF(J29-P29<=0,"ok","oil change") -> ok | R29: =R28 -> 13901 | S29: =R29-R28 -> 0 | T29: =T28+U29 -> 414762 | U29: =V29*S29 -> 0 | V29: 250 | X29: =X28 -> 14053 | Y29: =IF(R29-X29<=0,"ok","oil change") -> ok | Z29: =C29+K29+S29 -> 0 | AA29: =U29+M29+E29 -> 0 | AB29: =V29+N29+F29 -> 500 | AC29: =IF(Z29>0,AA29/Z29,0) -> 0 | AD29: =ELEC!Q30 -> 0 | AE29: =SUM(AD29/Z29) -> #DIV/0! | AF29: =SUM(AE29/1600) -> #DIV/0! | AG29: =SUM(AF29/1600) -> #DIV/0! | AH29: =SUM(AC29-AG29) -> #DIV/0! | AI29: =AD29*AJ29 -> 0 | AJ29: =305/1185 -> 0.25738397 | AK29: =AI29/Z29 -> #DIV/0! | AL29: =IF(Z29=0,0,1) -> 0
A30: =ELEC!C31 -> 44709 | B30: =B29 -> 11692 | C30: =B30-B29 -> 0 | D30: =D29+C30*85 -> 675621 | E30: =SUM(D30-D29) -> 0 | F30: =IF(C30>0,E30/C30,0) -> 0 | H30: =H29 -> 11690 | I30: =IF(B30-H30<=0,"ok","oil change") -> oil change | J30: =J29 -> 10798 | K30: =J30-J29 -> 0 | L30: =(K30*N29)+L29 -> 382191 | M30: =SUM(L30-L29) -> 0 | N30: 250 | P30: =P29 -> 10873 | Q30: =IF(J30-P30<=0,"ok","oil change") -> ok | R30: =R29 -> 13901 | S30: =R30-R29 -> 0 | T30: =T29+U30 -> 414762 | U30: =V30*S30 -> 0 | V30: 250 | X30: =X29 -> 14053 | Y30: =IF(R30-X30<=0,"ok","oil change") -> ok | Z30: =C30+K30+S30 -> 0 | AA30: =U30+M30+E30 -> 0 | AB30: =V30+N30+F30 -> 500 | AC30: =IF(Z30>0,AA30/Z30,0) -> 0 | AD30: =ELEC!Q31 -> 0 | AE30: =SUM(AD30/Z30) -> #DIV/0! | AF30: =SUM(AE30/1600) -> #DIV/0! | AG30: =SUM(AF30/1600) -> #DIV/0! | AH30: =SUM(AC30-AG30) -> #DIV/0! | AI30: =AD30*AJ30 -> 0 | AJ30: =305/1185 -> 0.25738397 | AK30: =AI30/Z30 -> #DIV/0! | AL30: =IF(Z30=0,0,1) -> 0
A31: =ELEC!C32 -> 44710 | B31: =B30 -> 11692 | C31: =B31-B30 -> 0 | D31: =D30+C31*85 -> 675621 | E31: =SUM(D31-D30) -> 0 | F31: =IF(C31>0,E31/C31,0) -> 0 | H31: =H30 -> 11690 | I31: =IF(B31-H31<=0,"ok","oil change") -> oil change | J31: =J30 -> 10798 | K31: =J31-J30 -> 0 | L31: =(K31*N30)+L30 -> 382191 | M31: =SUM(L31-L30) -> 0 | N31: 250 | P31: =P30 -> 10873 | Q31: =IF(J31-P31<=0,"ok","oil change") -> ok | R31: =R30 -> 13901 | S31: =R31-R30 -> 0 | T31: =T30+U31 -> 414762 | U31: =V31*S31 -> 0 | V31: 250 | X31: =X30 -> 14053 | Y31: =IF(R31-X31<=0,"ok","oil change") -> ok | Z31: =C31+K31+S31 -> 0 | AA31: =U31+M31+E31 -> 0 | AB31: =V31+N31+F31 -> 500 | AC31: =IF(Z31>0,AA31/Z31,0) -> 0 | AD31: =ELEC!Q32 -> 0 | AE31: =SUM(AD31/Z31) -> #DIV/0! | AF31: =SUM(AE31/1600) -> #DIV/0! | AG31: =SUM(AF31/1600) -> #DIV/0! | AH31: =SUM(AC31-AG31) -> #DIV/0! | AI31: =AD31*AJ31 -> 0 | AJ31: =305/1185 -> 0.25738397 | AK31: =AI31/Z31 -> #DIV/0! | AL31: =IF(Z31=0,0,1) -> 0
A32: =ELEC!C33 -> 44711 | B32: =B31 -> 11692 | C32: =B32-B31 -> 0 | D32: =D31+C32*85 -> 675621 | E32: =SUM(D32-D31) -> 0 | F32: =IF(C32>0,E32/C32,0) -> 0 | H32: =H31 -> 11690 | I32: =IF(B32-H32<=0,"ok","oil change") -> oil change | J32: =J31 -> 10798 | K32: =J32-J31 -> 0 | L32: =(K32*N31)+L31 -> 382191 | M32: =SUM(L32-L31) -> 0 | N32: 250 | P32: =P31 -> 10873 | Q32: =IF(J32-P32<=0,"ok","oil change") -> ok | R32: =R31 -> 13901 | S32: =R32-R31 -> 0 | T32: =T31+U32 -> 414762 | U32: =V32*S32 -> 0 | V32: 250 | X32: =X31 -> 14053 | Y32: =IF(R32-X32<=0,"ok","oil change") -> ok | Z32: =C32+K32+S32 -> 0 | AA32: =U32+M32+E32 -> 0 | AB32: =V32+N32+F32 -> 500 | AC32: =IF(Z32>0,AA32/Z32,0) -> 0 | AD32: =ELEC!Q33 -> 0 | AE32: =SUM(AD32/Z32) -> #DIV/0! | AF32: =SUM(AE32/1600) -> #DIV/0! | AG32: =SUM(AF32/1600) -> #DIV/0! | AH32: =SUM(AC32-AG32) -> #DIV/0! | AI32: =AD32*AJ32 -> 0 | AJ32: =305/1185 -> 0.25738397 | AK32: =AI32/Z32 -> #DIV/0! | AL32: =IF(Z32=0,0,1) -> 0
A33: =ELEC!C34 -> 44712 | B33: =B32 -> 11692 | C33: =B33-B32 -> 0 | D33: =D32+C33*85 -> 675621 | E33: =SUM(D33-D32) -> 0 | F33: =IF(C33>0,E33/C33,0) -> 0 | H33: =H32 -> 11690 | I33: =IF(B33-H33<=0,"ok","oil change") -> oil change | J33: =J32 -> 10798 | K33: =J33-J32 -> 0 | L33: =(K33*N32)+L32 -> 382191 | M33: =SUM(L33-L32) -> 0 | N33: 250 | P33: =P32 -> 10873 | Q33: =IF(J33-P33<=0,"ok","oil change") -> ok | R33: =R32 -> 13901 | S33: =R33-R32 -> 0 | T33: =T32+U33 -> 414762 | U33: =V33*S33 -> 0 | V33: 250 | X33: =X32 -> 14053 | Y33: =IF(R33-X33<=0,"ok","oil change") -> ok | Z33: =C33+K33+S33 -> 0 | AA33: =U33+M33+E33 -> 0 | AB33: =V33+N33+F33 -> 500 | AC33: =IF(Z33>0,AA33/Z33,0) -> 0 | AD33: =ELEC!Q34 -> 0 | AE33: =SUM(AD33/Z33) -> #DIV/0! | AF33: =SUM(AE33/1600) -> #DIV/0! | AG33: =SUM(AF33/1600) -> #DIV/0! | AH33: =SUM(AC33-AG33) -> #DIV/0! | AI33: =AD33*AJ33 -> 0 | AJ33: =305/1185 -> 0.25738397 | AK33: =AI33/Z33 -> #DIV/0! | AL33: =IF(Z33=0,0,1) -> 0
P34: =+O34/3 -> 0 | U34: =SUM(C35:S35) -> 86 | X34: 341 | Z34: =SUM(Z3:Z33) -> 86 | AF34: =SUM(AE34/1600) -> 0 | AL34: =SUM(AL3:AL33) -> 8
C35: =SUM(C3:C33) -> 63 | K35: =SUM(K3:K33) -> 2 | S35: =SUM(S3:S33) -> 21

Sheet tanks
B2: Tank 1 | D2: Tank 2 | F2: Tank 3 | H2: Tank 4 | J2: Tank 5 | L2: Tank 6 | N2: Tank 7 | P2: Tank 8 | R2: Tank 9 | T2: Tank 10 | V2: Tank 11 | Z2: Tank 1 | AB2: Tank 2 | AD2: Tank 3 | AF2: Tank 4 | AH2: Tank 5 | AJ2: Tank 6 | AL2: Tank 7
B3: 6670 | D3: =SUM(B3) -> 6670 | F3: =SUM(D3) -> 6670 | H3: =SUM(F3) -> 6670 | J3: =SUM(H3) -> 6670 | L3: =SUM(J3) -> 6670 | N3: =SUM(L3) -> 6670 | P3: =SUM(N3) -> 6670 | R3: =SUM(P3) -> 6670 | T3: =SUM(R3) -> 6670 | V3: =SUM(T3) -> 6670 | W3: =SUM(B3:V3) -> 73370 | Z3: 2800 | AB3: 2800 | AD3: 2800 | AF3: 2800 | AH3: 2800 | AJ3: 2800 | AL3: 2800 | AM3: =SUM(Z3:AL3) -> 19600 | AO3: =SUM(AM3+W3) -> 92970 | AR3: Total sotck | AS3: Diesel Cons Per day | AT3: Diesel Delivery | BE3: Genset Co | BF3: Steam | BG3: Boil | BH3: Outdoor temperature
B4: =B3/310 -> 21.516129 | D4: =SUM(B4) -> 21.516129 | F4: =SUM(D4) -> 21.516129 | H4: =SUM(F4) -> 21.516129 | J4: =SUM(H4) -> 21.516129 | L4: =SUM(J4) -> 21.516129 | N4: =SUM(L4) -> 21.516129 | P4: =SUM(N4) -> 21.516129 | R4: =SUM(P4) -> 21.516129 | T4: =SUM(R4) -> 21.516129 | V4: =SUM(T4) -> 21.516129 | Z4: =Z3/280 -> 10 | AA4: =AA3/280 -> 0 | AB4: =AB3/280 -> 10 | AC4: =AC3/280 -> 0 | AD4: =AD3/280 -> 10 | AE4: =AE3/280 -> 0 | AF4: =AF3/280 -> 10 | AG4: =AG3/280 -> 0 | ... AL4: =AL3/280 -> 10 | AT4: Delivery | AU4: Cost /L | AW4: Boiler+Steam | AX4: Generator | AZ4: Occupancy | BA4: AVE TEPM | BB4: AVE Humidity
A5: =[2]tanks!$A$35 -> 44681 | B5: =[2]tanks!B35 -> 233 | C5: =[2]tanks!C35 -> 5013.2581 | D5: =[2]tanks!D35 -> 233 | E5: =[2]tanks!E35 -> 5013.2581 | F5: =[2]tanks!F35 -> 233 | G5: =[2]tanks!G35 -> 5013.2581 | H5: =[2]tanks!H35 -> 233 | I5: =[2]tanks!I35 -> 5013.2581 | ... AO5: =[2]tanks!AO35 -> 16730 | AQ5: =[2]tanks!AQ35 -> 0.77310787 | AR5: =[2]tanks!AR35 -> 71875.839 | AS5: =[2]tanks!AS35 -> 0 | AT5: =[2]tanks!AT35 -> 0 | AU5: =[2]tanks!AU35 -> 0 | AV5: =[2]tanks!AV35 -> 1.05 | AW5: =[2]tanks!AW35 -> 0 | AX5: =[2]tanks!AX35 -> 0 | ... BH5: =[2]tanks!BH35 -> 0 | BI5: =[5]tanks!BI36 -> 23
A6: =ELEC!C4 -> 44682 | B6: ='B5'!B5 -> 233 | C6: =B6*$B$4 -> 5013.2581 | D6: =SUM(B6) -> 233 | E6: =D6*$B$4 -> 5013.2581 | F6: =SUM(D6) -> 233 | G6: =F6*$B$4 -> 5013.2581 | H6: =SUM(F6) -> 233 | I6: =H6*$B$4 -> 5013.2581 | J6: =SUM(H6) -> 233 | K6: =J6*$B$4 -> 5013.2581 | L6: =SUM(J6) -> 233 | M6: =L6*$B$4 -> 5013.2581 | N6: =SUM(L6) -> 233 | O6: =N6*$B$4 -> 5013.2581 | P6: =SUM(N6) -> 233 | Q6: =P6*$B$4 -> 5013.2581 | R6: =SUM(P6) -> 233 | S6: =R6*$B$4 -> 5013.2581 | T6: =SUM(R6) -> 233 | U6: =T6*$B$4 -> 5013.2581 | V6: =SUM(T6) -> 233 | W6: =V6*$B$4 -> 5013.2581 | X6: =SUM(Y6/73370) -> 0.7516129 | Y6: =SUM(C6+E6+G6+I6+K6+M6+O6+Q6+S6+U6+W6) -> 55145.839 | Z6: ='B5'!C5 -> 239 | AA6: =SUM(Z6*$Z$4) -> 2390 | AB6: =SUM(Z6) -> 239 | AC6: =SUM(AB6*$Z$4) -> 2390 | AD6: =SUM(AB6) -> 239 | AE6: =SUM(AD6*$Z$4) -> 2390 | AF6: =SUM(AD6) -> 239 | AG6: =SUM(AF6*$Z$4) -> 2390 | AH6: =SUM(AF6) -> 239 | AI6: =SUM(AH6*$Z$4) -> 2390 | AJ6: =SUM(AH6) -> 239 | AK6: =SUM(AJ6*$Z$4) -> 2390 | AL6: =SUM(AJ6) -> 239 | AM6: =SUM(AL6*$Z$4) -> 2390 | AN6: =SUM(AO6/19600) -> 0.85357143 | AO6: =SUM(AA6+AC6+AE6+AG6+AI6+AK6+AM6) -> 16730 | AQ6: =SUM(AR6/92970) -> 0.77310787 | AR6: =Y6+AO6 -> 71875.839 | AS6: =SUM(AR6-AR5-AT6) -> 0 | AV6: =IF(AT6>0,AU6,AV5) -> 1.05 | AW6: =-SUM('B5'!AI5) -> 0 | AX6: =-SUM(AW6-AS6) -> 0 | AY6: =SUM(AX6+AW6) -> 0 | AZ6: =ELEC!A4 -> 0 | BA6: ='General information '!D5 -> 0 | BB6: =SUM('General information '!E5) -> 0 | BC6: =IF(AR3>=AR6,0,1) -> 0 | BD6: 19222 | BE6: =(305/1185)*ELEC!Q5 -> 0 | BG6: =#REF!-BE6 -> #REF! | BH6: 21 | BI6: 12 | BJ6: =AX6/BI6 -> 0 | BK6: =GEN!AF3 -> #DIV/0!
A7: =ELEC!C5 -> 44683 | B7: ='B5'!B6 -> 233 | C7: =B7*$B$4 -> 5013.2581 | D7: =SUM(B7) -> 233 | E7: =D7*$B$4 -> 5013.2581 | F7: =SUM(D7) -> 233 | G7: =F7*$B$4 -> 5013.2581 | H7: =SUM(F7) -> 233 | I7: =H7*$B$4 -> 5013.2581 | J7: =SUM(H7) -> 233 | K7: =J7*$B$4 -> 5013.2581 | L7: =SUM(J7) -> 233 | M7: =L7*$B$4 -> 5013.2581 | N7: =SUM(L7) -> 233 | O7: =N7*$B$4 -> 5013.2581 | P7: =SUM(N7) -> 233 | Q7: =P7*$B$4 -> 5013.2581 | R7: =SUM(P7) -> 233 | S7: =R7*$B$4 -> 5013.2581 | T7: =SUM(R7) -> 233 | U7: =T7*$B$4 -> 5013.2581 | V7: =SUM(T7) -> 233 | W7: =V7*$B$4 -> 5013.2581 | X7: =SUM(Y7/73370) -> 0.7516129 | Y7: =SUM(C7+E7+G7+I7+K7+M7+O7+Q7+S7+U7+W7) -> 55145.839 | Z7: ='B5'!C6 -> 239 | AA7: =SUM(Z7*$Z$4) -> 2390 | AB7: =SUM(Z7) -> 239 | AC7: =SUM(AB7*$Z$4) -> 2390 | AD7: =SUM(AB7) -> 239 | AE7: =SUM(AD7*$Z$4) -> 2390 | AF7: =SUM(AD7) -> 239 | AG7: =SUM(AF7*$Z$4) -> 2390 | AH7: =SUM(AF7) -> 239 | AI7: =SUM(AH7*$Z$4) -> 2390 | AJ7: =SUM(AH7) -> 239 | AK7: =SUM(AJ7*$Z$4) -> 2390 | AL7: =SUM(AJ7) -> 239 | AM7: =SUM(AL7*$Z$4) -> 2390 | AN7: =SUM(AO7/19600) -> 0.85357143 | AO7: =SUM(AA7+AC7+AE7+AG7+AI7+AK7+AM7) -> 16730 | AQ7: =SUM(AR7/92970) -> 0.77310787 | AR7: =Y7+AO7 -> 71875.839 | AS7: =SUM(AR7-AR6-AT7) -> 0 | AV7: =IF(AT7>0,AU7,AV6) -> 1.05 | AW7: =-SUM('B5'!AI6) -> 0 | AX7: =-SUM(AW7-AS7) -> 0 | AY7: =SUM(AX7+AW7) -> 0 | AZ7: =ELEC!A5 -> 0 | BA7: ='General information '!D6 -> 0 | BB7: =SUM('General information '!E6) -> 0 | BC7: 0 | BD7: 19222 | BE7: =(305/1185)*ELEC!Q6 -> 1548.9367 | BG7: =#REF!-BE7 -> #REF! | BH7: 19 | BI7: 15 | BJ7: =AX7/BI7 -> 0 | BK7: =GEN!AF4 -> #DIV/0!
A8: =ELEC!C6 -> 44684 | B8: ='B5'!B7 -> 224 | C8: =B8*$B$4 -> 4819.6129 | D8: =SUM(B8) -> 224 | E8: =D8*$B$4 -> 4819.6129 | F8: =SUM(D8) -> 224 | G8: =F8*$B$4 -> 4819.6129 | H8: =SUM(F8) -> 224 | I8: =H8*$B$4 -> 4819.6129 | J8: =SUM(H8) -> 224 | K8: =J8*$B$4 -> 4819.6129 | L8: =SUM(J8) -> 224 | M8: =L8*$B$4 -> 4819.6129 | N8: =SUM(L8) -> 224 | O8: =N8*$B$4 -> 4819.6129 | P8: =SUM(N8) -> 224 | Q8: =P8*$B$4 -> 4819.6129 | R8: =SUM(P8) -> 224 | S8: =R8*$B$4 -> 4819.6129 | T8: =SUM(R8) -> 224 | U8: =T8*$B$4 -> 4819.6129 | V8: =SUM(T8) -> 224 | W8: =V8*$B$4 -> 4819.6129 | X8: =SUM(Y8/73370) -> 0.72258065 | Y8: =SUM(C8+E8+G8+I8+K8+M8+O8+Q8+S8+U8+W8) -> 53015.742 | Z8: ='B5'!C7 -> 231 | AA8: =SUM(Z8*$Z$4) -> 2310 | AB8: =SUM(Z8) -> 231 | AC8: =SUM(AB8*$Z$4) -> 2310 | AD8: =SUM(AB8) -> 231 | AE8: =SUM(AD8*$Z$4) -> 2310 | AF8: =SUM(AD8) -> 231 | AG8: =SUM(AF8*$Z$4) -> 2310 | AH8: =SUM(AF8) -> 231 | AI8: =SUM(AH8*$Z$4) -> 2310 | AJ8: =SUM(AH8) -> 231 | AK8: =SUM(AJ8*$Z$4) -> 2310 | AL8: =SUM(AJ8) -> 231 | AM8: =SUM(AL8*$Z$4) -> 2310 | AN8: =SUM(AO8/19600) -> 0.825 | AO8: =SUM(AA8+AC8+AE8+AG8+AI8+AK8+AM8) -> 16170 | AQ8: =SUM(AR8/92970) -> 0.74417276 | AR8: =Y8+AO8 -> 69185.742 | AS8: =SUM(AR8-AR7-AT8) -> -2690.0968 | AV8: =IF(AT8>0,AU8,AV7) -> 1.05 | AW8: =-SUM('B5'!AI7) -> -289 | AX8: =-SUM(AW8-AS8) -> -2401.0968 | AY8: =SUM(AX8+AW8) -> -2690.0968 | AZ8: =ELEC!A6 -> 0 | BA8: ='General information '!D7 -> 0 | BB8: =SUM('General information '!E7) -> 0 | BC8: =IF(AR7>=AR8,0,1) -> 0 | BD8: 19222 | BE8: =(305/1185)*ELEC!Q7 -> 1022.8439 | BG8: =#REF!-BE8 -> #REF! | BH8: 16 | BI8: 9 | BJ8: =AX8/BI8 -> -266.78853 | BK8: =GEN!AF5 -> 0.25075
A9: =ELEC!C7 -> 44685 | B9: ='B5'!B8 -> 218 | C9: =B9*$B$4 -> 4690.5161 | D9: =SUM(B9) -> 218 | E9: =D9*$B$4 -> 4690.5161 | F9: =SUM(D9) -> 218 | G9: =F9*$B$4 -> 4690.5161 | H9: =SUM(F9) -> 218 | I9: =H9*$B$4 -> 4690.5161 | J9: =SUM(H9) -> 218 | K9: =J9*$B$4 -> 4690.5161 | L9: =SUM(J9) -> 218 | M9: =L9*$B$4 -> 4690.5161 | N9: =SUM(L9) -> 218 | O9: =N9*$B$4 -> 4690.5161 | P9: =SUM(N9) -> 218 | Q9: =P9*$B$4 -> 4690.5161 | R9: =SUM(P9) -> 218 | S9: =R9*$B$4 -> 4690.5161 | T9: =SUM(R9) -> 218 | U9: =T9*$B$4 -> 4690.5161 | V9: =SUM(T9) -> 218 | W9: =V9*$B$4 -> 4690.5161 | X9: =SUM(Y9/73370) -> 0.70322581 | Y9: =SUM(C9+E9+G9+I9+K9+M9+O9+Q9+S9+U9+W9) -> 51595.677 | Z9: ='B5'!C8 -> 225 | AA9: =SUM(Z9*$Z$4) -> 2250 | AB9: =SUM(Z9) -> 225 | AC9: =SUM(AB9*$Z$4) -> 2250 | AD9: =SUM(AB9) -> 225 | AE9: =SUM(AD9*$Z$4) -> 2250 | AF9: =SUM(AD9) -> 225 | AG9: =SUM(AF9*$Z$4) -> 2250 | AH9: =SUM(AF9) -> 225 | AI9: =SUM(AH9*$Z$4) -> 2250 | AJ9: =SUM(AH9) -> 225 | AK9: =SUM(AJ9*$Z$4) -> 2250 | AL9: =SUM(AJ9) -> 225 | AM9: =SUM(AL9*$Z$4) -> 2250 | AN9: =SUM(AO9/19600) -> 0.80357143 | AO9: =SUM(AA9+AC9+AE9+AG9+AI9+AK9+AM9) -> 15750 | AQ9: =SUM(AR9/92970) -> 0.72438074 | AR9: =Y9+AO9 -> 67345.677 | AS9: =SUM(AR9-AR8-AT9) -> -1840.0645 | AV9: =IF(AT9>0,AU9,AV8) -> 1.05 | AW9: =-SUM('B5'!AI8) -> -305 | AX9: =-SUM(AW9-AS9) -> -1535.0645 | AY9: =SUM(AX9+AW9) -> -1840.0645 | AZ9: =ELEC!A7 -> 0 | BA9: ='General information '!D8 -> 21 | BB9: =SUM('General information '!E8) -> 0.77 | BC9: =IF(AR8>=AR9,0,1) -> 0 | BD9: 19222 | BE9: =(305/1185)*ELEC!Q8 -> 746.4135 | BG9: =#REF!-BE9 -> #REF! | BH9: 18 | BI9: 6 | BJ9: =AX9/BI9 -> -255.84409 | BK9: =GEN!AF6 -> 0.22579545
A10: =ELEC!C8 -> 44686 | B10: ='B5'!B9 -> 215 | C10: =B10*$B$4 -> 4625.9677 | D10: =SUM(B10) -> 215 | E10: =D10*$B$4 -> 4625.9677 | F10: =SUM(D10) -> 215 | G10: =F10*$B$4 -> 4625.9677 | H10: =SUM(F10) -> 215 | I10: =H10*$B$4 -> 4625.9677 | J10: =SUM(H10) -> 215 | K10: =J10*$B$4 -> 4625.9677 | L10: =SUM(J10) -> 215 | M10: =L10*$B$4 -> 4625.9677 | N10: =SUM(L10) -> 215 | O10: =N10*$B$4 -> 4625.9677 | P10: =SUM(N10) -> 215 | Q10: =P10*$B$4 -> 4625.9677 | R10: =SUM(P10) -> 215 | S10: =R10*$B$4 -> 4625.9677 | T10: =SUM(R10) -> 215 | U10: =T10*$B$4 -> 4625.9677 | V10: =SUM(T10) -> 215 | W10: =V10*$B$4 -> 4625.9677 | X10: =SUM(Y10/73370) -> 0.69354839 | Y10: =SUM(C10+E10+G10+I10+K10+M10+O10+Q10+S10+U10+W10) -> 50885.645 | Z10: ='B5'!C9 -> 222 | AA10: =SUM(Z10*$Z$4) -> 2220 | AB10: =SUM(Z10) -> 222 | AC10: =SUM(AB10*$Z$4) -> 2220 | AD10: =SUM(AB10) -> 222 | AE10: =SUM(AD10*$Z$4) -> 2220 | AF10: =SUM(AD10) -> 222 | AG10: =SUM(AF10*$Z$4) -> 2220 | AH10: =SUM(AF10) -> 222 | AI10: =SUM(AH10*$Z$4) -> 2220 | AJ10: =SUM(AH10) -> 222 | AK10: =SUM(AJ10*$Z$4) -> 2220 | AL10: =SUM(AJ10) -> 222 | AM10: =SUM(AL10*$Z$4) -> 2220 | AN10: =SUM(AO10/19600) -> 0.79285714 | AO10: =SUM(AA10+AC10+AE10+AG10+AI10+AK10+AM10) -> 15540 | AQ10: =SUM(AR10/92970) -> 0.71448473 | AR10: =Y10+AO10 -> 66425.645 | AS10: =SUM(AR10-AR9-AT10) -> -920.03226 | AV10: =IF(AT10>0,AU10,AV9) -> 1.05 | AW10: =-SUM('B5'!AI9) -> -44 | AX10: =-SUM(AW10-AS10) -> -876.03226 | AY10: =SUM(AX10+AW10) -> -920.03226 | AZ10: =ELEC!A8 -> 0 | BA10: ='General information '!D9 -> 20 | BB10: =SUM('General information '!E9) -> 0.65 | BC10: =IF(AR9>=AR10,0,1) -> 0 | BD10: 19222 | BE10: =(305/1185)*ELEC!Q9 -> 0 | BG10: =#REF!-BE10 -> #REF! | BH10: 16 | BI10: 7 | BJ10: =AX10/BI10 -> -125.14747 | BK10: =GEN!AF7 -> 0.18125
A11: =ELEC!C9 -> 44687 | B11: ='B5'!B10 -> 215 | C11: =B11*$B$4 -> 4625.9677 | D11: =SUM(B11) -> 215 | E11: =D11*$B$4 -> 4625.9677 | F11: =SUM(D11) -> 215 | G11: =F11*$B$4 -> 4625.9677 | H11: =SUM(F11) -> 215 | I11: =H11*$B$4 -> 4625.9677 | J11: =SUM(H11) -> 215 | K11: =J11*$B$4 -> 4625.9677 | L11: =SUM(J11) -> 215 | M11: =L11*$B$4 -> 4625.9677 | N11: =SUM(L11) -> 215 | O11: =N11*$B$4 -> 4625.9677 | P11: =SUM(N11) -> 215 | Q11: =P11*$B$4 -> 4625.9677 | R11: =SUM(P11) -> 215 | S11: =R11*$B$4 -> 4625.9677 | T11: =SUM(R11) -> 215 | U11: =T11*$B$4 -> 4625.9677 | V11: =SUM(T11) -> 215 | W11: =V11*$B$4 -> 4625.9677 | X11: =SUM(Y11/73370) -> 0.69354839 | Y11: =SUM(C11+E11+G11+I11+K11+M11+O11+Q11+S11+U11+W11) -> 50885.645 | Z11: ='B5'!C10 -> 222 | AA11: =SUM(Z11*$Z$4) -> 2220 | AB11: =SUM(Z11) -> 222 | AC11: =SUM(AB11*$Z$4) -> 2220 | AD11: =SUM(AB11) -> 222 | AE11: =SUM(AD11*$Z$4) -> 2220 | AF11: =SUM(AD11) -> 222 | AG11: =SUM(AF11*$Z$4) -> 2220 | AH11: =SUM(AF11) -> 222 | AI11: =SUM(AH11*$Z$4) -> 2220 | AJ11: =SUM(AH11) -> 222 | AK11: =SUM(AJ11*$Z$4) -> 2220 | AL11: =SUM(AJ11) -> 222 | AM11: =SUM(AL11*$Z$4) -> 2220 | AN11: =SUM(AO11/19600) -> 0.79285714 | AO11: =SUM(AA11+AC11+AE11+AG11+AI11+AK11+AM11) -> 15540 | AQ11: =SUM(AR11/92970) -> 0.71448473 | AR11: =Y11+AO11 -> 66425.645 | AS11: =SUM(AR11-AR10-AT11) -> 0 | AV11: =IF(AT11>0,AU11,AV10) -> 1.05 | AW11: =-SUM('B5'!AI10) -> 0 | AX11: =-SUM(AW11-AS11) -> 0 | AY11: =SUM(AX11+AW11) -> 0 | AZ11: =ELEC!A9 -> 0 | BA11: ='General information '!D10 -> 0 | BB11: =SUM('General information '!E10) -> 0 | BC11: =IF(AR10>=AR11,0,1) -> 0 | BD11: 19222 | BE11: =(305/1185)*ELEC!Q10 -> 0 | BG11: =#REF!-BE11 -> #REF! | BH11: 16.5 | BI11: 9.3 | BJ11: =AX11/BI11 -> 0 | BK11: =GEN!AF8 -> #DIV/0!
A12: =ELEC!C10 -> 44688 | B12: ='B5'!B11 -> 215 | C12: =B12*$B$4 -> 4625.9677 | D12: =SUM(B12) -> 215 | E12: =D12*$B$4 -> 4625.9677 | F12: =SUM(D12) -> 215 | G12: =F12*$B$4 -> 4625.9677 | H12: =SUM(F12) -> 215 | I12: =H12*$B$4 -> 4625.9677 | J12: =SUM(H12) -> 215 | K12: =J12*$B$4 -> 4625.9677 | L12: =SUM(J12) -> 215 | M12: =L12*$B$4 -> 4625.9677 | N12: =SUM(L12) -> 215 | O12: =N12*$B$4 -> 4625.9677 | P12: =SUM(N12) -> 215 | Q12: =P12*$B$4 -> 4625.9677 | R12: =SUM(P12) -> 215 | S12: =R12*$B$4 -> 4625.9677 | T12: =SUM(R12) -> 215 | U12: =T12*$B$4 -> 4625.9677 | V12: =SUM(T12) -> 215 | W12: =V12*$B$4 -> 4625.9677 | X12: =SUM(Y12/73370) -> 0.69354839 | Y12: =SUM(C12+E12+G12+I12+K12+M12+O12+Q12+S12+U12+W12) -> 50885.645 | Z12: ='B5'!C11 -> 222 | AA12: =SUM(Z12*$Z$4) -> 2220 | AB12: =SUM(Z12) -> 222 | AC12: =SUM(AB12*$Z$4) -> 2220 | AD12: =SUM(AB12) -> 222 | AE12: =SUM(AD12*$Z$4) -> 2220 | AF12: =SUM(AD12) -> 222 | AG12: =SUM(AF12*$Z$4) -> 2220 | AH12: =SUM(AF12) -> 222 | AI12: =SUM(AH12*$Z$4) -> 2220 | AJ12: =SUM(AH12) -> 222 | AK12: =SUM(AJ12*$Z$4) -> 2220 | AL12: =SUM(AJ12) -> 222 | AM12: =SUM(AL12*$Z$4) -> 2220 | AN12: =SUM(AO12/19600) -> 0.79285714 | AO12: =SUM(AA12+AC12+AE12+AG12+AI12+AK12+AM12) -> 15540 | AQ12: =SUM(AR12/92970) -> 0.71448473 | AR12: =Y12+AO12 -> 66425.645 | AS12: =SUM(AR12-AR11-AT12) -> 0 | AV12: =IF(AT12>0,AU12,AV11) -> 1.05 | AW12: =-SUM('B5'!AI11) -> 0 | AX12: =-SUM(AW12-AS12) -> 0 | AY12: =SUM(AX12+AW12) -> 0 | AZ12: =ELEC!A10 -> 0 | BA12: ='General information '!D11 -> 0 | BB12: =SUM('General information '!E11) -> 0 | BC12: =IF(AR11>=AR12,0,1) -> 0 | BD12: 19222 | BE12: =(305/1185)*ELEC!Q11 -> 767.00422 | BG12: =#REF!-BE12 -> #REF! | BH12: 15.5 | BI12: 3.7 | BJ12: =AX12/BI12 -> 0 | BK12: =GEN!AF9 -> #DIV/0!
A13: =ELEC!C11 -> 44689 | B13: ='B5'!B12 -> 249 | C13: =B13*$B$4 -> 5357.5161 | D13: =SUM(B13) -> 249 | E13: =D13*$B$4 -> 5357.5161 | F13: =SUM(D13) -> 249 | G13: =F13*$B$4 -> 5357.5161 | H13: =SUM(F13) -> 249 | I13: =H13*$B$4 -> 5357.5161 | J13: =SUM(H13) -> 249 | K13: =J13*$B$4 -> 5357.5161 | L13: =SUM(J13) -> 249 | M13: =L13*$B$4 -> 5357.5161 | N13: =SUM(L13) -> 249 | O13: =N13*$B$4 -> 5357.5161 | P13: =SUM(N13) -> 249 | Q13: =P13*$B$4 -> 5357.5161 | R13: =SUM(P13) -> 249 | S13: =R13*$B$4 -> 5357.5161 | T13: =SUM(R13) -> 249 | U13: =T13*$B$4 -> 5357.5161 | V13: =SUM(T13) -> 249 | W13: =V13*$B$4 -> 5357.5161 | X13: =SUM(Y13/73370) -> 0.80322581 | Y13: =SUM(C13+E13+G13+I13+K13+M13+O13+Q13+S13+U13+W13) -> 58932.677 | Z13: ='B5'!C12 -> 255 | AA13: =SUM(Z13*$Z$4) -> 2550 | AB13: =SUM(Z13) -> 255 | AC13: =SUM(AB13*$Z$4) -> 2550 | AD13: =SUM(AB13) -> 255 | AE13: =SUM(AD13*$Z$4) -> 2550 | AF13: =SUM(AD13) -> 255 | AG13: =SUM(AF13*$Z$4) -> 2550 | AH13: =SUM(AF13) -> 255 | AI13: =SUM(AH13*$Z$4) -> 2550 | AJ13: =SUM(AH13) -> 255 | AK13: =SUM(AJ13*$Z$4) -> 2550 | AL13: =SUM(AJ13) -> 255 | AM13: =SUM(AL13*$Z$4) -> 2550 | AN13: =SUM(AO13/19600) -> 0.91071429 | AO13: =SUM(AA13+AC13+AE13+AG13+AI13+AK13+AM13) -> 17850 | AQ13: =SUM(AR13/92970) -> 0.8258866 | AR13: =Y13+AO13 -> 76782.677 | AS13: =SUM(AR13-AR12-AT13) -> 357.03226 | AT13: 10000 | AU13: 1.085 | AV13: =IF(AT13>0,AU13,AV12) -> 1.085 | AW13: =-SUM('B5'!AI12) -> -259 | AX13: =-SUM(AW13-AS13) -> 616.03226 | AY13: =SUM(AX13+AW13) -> 357.03226 | AZ13: =ELEC!A11 -> 0 | BA13: ='General information '!D12 -> 19.5 | BB13: =SUM('General information '!E12) -> 0.61 | BC13: =IF(AR12>=AR13,0,1) -> 1 | BD13: 19222 | BE13: =(305/1185)*ELEC!Q12 -> 806.64135 | BG13: =#REF!-BE13 -> #REF! | BI13: 5 | BJ13: =AX13/BI13 -> 123.20645 | BK13: =GEN!AF10 -> 0.20694444
A14: =ELEC!C12 -> 44690 | B14: ='B5'!B13 -> 245 | C14: =B14*$B$4 -> 5271.4516 | D14: =SUM(B14) -> 245 | E14: =D14*$B$4 -> 5271.4516 | F14: =SUM(D14) -> 245 | G14: =F14*$B$4 -> 5271.4516 | H14: =SUM(F14) -> 245 | I14: =H14*$B$4 -> 5271.4516 | J14: =SUM(H14) -> 245 | K14: =J14*$B$4 -> 5271.4516 | L14: =SUM(J14) -> 245 | M14: =L14*$B$4 -> 5271.4516 | N14: =SUM(L14) -> 245 | O14: =N14*$B$4 -> 5271.4516 | P14: =SUM(N14) -> 245 | Q14: =P14*$B$4 -> 5271.4516 | R14: =SUM(P14) -> 245 | S14: =R14*$B$4 -> 5271.4516 | T14: =SUM(R14) -> 245 | U14: =T14*$B$4 -> 5271.4516 | V14: =SUM(T14) -> 245 | W14: =V14*$B$4 -> 5271.4516 | X14: =SUM(Y14/73370) -> 0.79032258 | Y14: =SUM(C14+E14+G14+I14+K14+M14+O14+Q14+S14+U14+W14) -> 57985.968 | Z14: ='B5'!C13 -> 251 | AA14: =SUM(Z14*$Z$4) -> 2510 | AB14: =SUM(Z14) -> 251 | AC14: =SUM(AB14*$Z$4) -> 2510 | AD14: =SUM(AB14) -> 251 | AE14: =SUM(AD14*$Z$4) -> 2510 | AF14: =SUM(AD14) -> 251 | AG14: =SUM(AF14*$Z$4) -> 2510 | AH14: =SUM(AF14) -> 251 | AI14: =SUM(AH14*$Z$4) -> 2510 | AJ14: =SUM(AH14) -> 251 | AK14: =SUM(AJ14*$Z$4) -> 2510 | AL14: =SUM(AJ14) -> 251 | AM14: =SUM(AL14*$Z$4) -> 2510 | AN14: =SUM(AO14/19600) -> 0.89642857 | AO14: =SUM(AA14+AC14+AE14+AG14+AI14+AK14+AM14) -> 17570 | AQ14: =SUM(AR14/92970) -> 0.81269192 | AR14: =Y14+AO14 -> 75555.968 | AS14: =SUM(AR14-AR13-AT14) -> -1226.7097 | AV14: =IF(AT14>0,AU14,AV13) -> 1.085 | AW14: =-SUM('B5'!AI13) -> -101 | AX14: =-SUM(AW14-AS14) -> -1125.7097 | AY14: =SUM(AX14+AW14) -> -1226.7097 | AZ14: =ELEC!A12 -> 0 | BA14: ='General information '!D13 -> 20.5 | BB14: =SUM('General information '!E13) -> 0.57 | BC14: =IF(AR13>=AR14,0,1) -> 0 | BD14: 19222 | BE14: =(305/1185)*ELEC!Q13 -> 738.17722 | BG14: =#REF!-BE14 -> #REF! | BI14: 3 | BJ14: =AX14/BI14 -> -375.23656 | BK14: =GEN!AF11 -> 0.17806818
A15: =ELEC!C13 -> 44691 | B15: ='B5'!B14 -> 242 | C15: =B15*$B$4 -> 5206.9032 | D15: =SUM(B15) -> 242 | E15: =D15*$B$4 -> 5206.9032 | F15: =SUM(D15) -> 242 | G15: =F15*$B$4 -> 5206.9032 | H15: =SUM(F15) -> 242 | I15: =H15*$B$4 -> 5206.9032 | J15: =SUM(H15) -> 242 | K15: =J15*$B$4 -> 5206.9032 | L15: =SUM(J15) -> 242 | M15: =L15*$B$4 -> 5206.9032 | N15: =SUM(L15) -> 242 | O15: =N15*$B$4 -> 5206.9032 | P15: =SUM(N15) -> 242 | Q15: =P15*$B$4 -> 5206.9032 | R15: =SUM(P15) -> 242 | S15: =R15*$B$4 -> 5206.9032 | T15: =SUM(R15) -> 242 | U15: =T15*$B$4 -> 5206.9032 | V15: =SUM(T15) -> 242 | W15: =V15*$B$4 -> 5206.9032 | X15: =SUM(Y15/73370) -> 0.78064516 | Y15: =SUM(C15+E15+G15+I15+K15+M15+O15+Q15+S15+U15+W15) -> 57275.935 | Z15: ='B5'!C14 -> 248 | AA15: =SUM(Z15*$Z$4) -> 2480 | AB15: =SUM(Z15) -> 248 | AC15: =SUM(AB15*$Z$4) -> 2480 | AD15: =SUM(AB15) -> 248 | AE15: =SUM(AD15*$Z$4) -> 2480 | AF15: =SUM(AD15) -> 248 | AG15: =SUM(AF15*$Z$4) -> 2480 | AH15: =SUM(AF15) -> 248 | AI15: =SUM(AH15*$Z$4) -> 2480 | AJ15: =SUM(AH15) -> 248 | AK15: =SUM(AJ15*$Z$4) -> 2480 | AL15: =SUM(AJ15) -> 248 | AM15: =SUM(AL15*$Z$4) -> 2480 | AN15: =SUM(AO15/19600) -> 0.88571429 | AO15: =SUM(AA15+AC15+AE15+AG15+AI15+AK15+AM15) -> 17360 | AQ15: =SUM(AR15/92970) -> 0.80279591 | AR15: =Y15+AO15 -> 74635.935 | AS15: =SUM(AR15-AR14-AT15) -> -920.03226 | AV15: =IF(AT15>0,AU15,AV14) -> 1.085 | AW15: =-SUM('B5'!AI14) -> -45 | AX15: =-SUM(AW15-AS15) -> -875.03226 | AY15: =SUM(AX15+AW15) -> -920.03226 | AZ15: =ELEC!A13 -> 0 | BA15: ='General information '!D14 -> 20 | BB15: =SUM('General information '!E14) -> 0.64 | BC15: =IF(AR14>=AR15,0,1) -> 0 | BD15: 19222 | BE15: =(305/1185)*ELEC!Q14 -> 772.40928 | BG15: =#REF!-BE15 -> #REF! | BI15: 4 | BJ15: =AX15/BI15 -> -218.75806 | BK15: =GEN!AF12 -> 0.16295455
A16: =ELEC!C14 -> 44692 | B16: ='B5'!B15 -> 238 | C16: =B16*$B$4 -> 5120.8387 | D16: =SUM(B16) -> 238 | E16: =D16*$B$4 -> 5120.8387 | F16: =SUM(D16) -> 238 | G16: =F16*$B$4 -> 5120.8387 | H16: =SUM(F16) -> 238 | I16: =H16*$B$4 -> 5120.8387 | J16: =SUM(H16) -> 238 | K16: =J16*$B$4 -> 5120.8387 | L16: =SUM(J16) -> 238 | M16: =L16*$B$4 -> 5120.8387 | N16: =SUM(L16) -> 238 | O16: =N16*$B$4 -> 5120.8387 | P16: =SUM(N16) -> 238 | Q16: =P16*$B$4 -> 5120.8387 | R16: =SUM(P16) -> 238 | S16: =R16*$B$4 -> 5120.8387 | T16: =SUM(R16) -> 238 | U16: =T16*$B$4 -> 5120.8387 | V16: =SUM(T16) -> 238 | W16: =V16*$B$4 -> 5120.8387 | X16: =SUM(Y16/73370) -> 0.76774194 | Y16: =SUM(C16+E16+G16+I16+K16+M16+O16+Q16+S16+U16+W16) -> 56329.226 | Z16: ='B5'!C15 -> 244 | AA16: =SUM(Z16*$Z$4) -> 2440 | AB16: =SUM(Z16) -> 244 | AC16: =SUM(AB16*$Z$4) -> 2440 | AD16: =SUM(AB16) -> 244 | AE16: =SUM(AD16*$Z$4) -> 2440 | AF16: =SUM(AD16) -> 244 | AG16: =SUM(AF16*$Z$4) -> 2440 | AH16: =SUM(AF16) -> 244 | AI16: =SUM(AH16*$Z$4) -> 2440 | AJ16: =SUM(AH16) -> 244 | AK16: =SUM(AJ16*$Z$4) -> 2440 | AL16: =SUM(AJ16) -> 244 | AM16: =SUM(AL16*$Z$4) -> 2440 | AN16: =SUM(AO16/19600) -> 0.87142857 | AO16: =SUM(AA16+AC16+AE16+AG16+AI16+AK16+AM16) -> 17080 | AQ16: =SUM(AR16/92970) -> 0.78960122 | AR16: =Y16+AO16 -> 73409.226 | AS16: =SUM(AR16-AR15-AT16) -> -1226.7097 | AV16: =IF(AT16>0,AU16,AV15) -> 1.085 | AW16: =-SUM('B5'!AI15) -> -192 | AX16: =-SUM(AW16-AS16) -> -1034.7097 | AY16: =SUM(AX16+AW16) -> -1226.7097 | AZ16: =ELEC!A14 -> 0 | BA16: ='General information '!D15 -> 20 | BB16: =SUM('General information '!E15) -> 0.75 | BC16: =IF(AR15>=AR16,0,1) -> 0 | BD16: 19222 | BE16: =(305/1185)*ELEC!Q15 -> 670.74262 | BG16: =#REF!-BE16 -> #REF! | BI16: 3 | BJ16: =AX16/BI16 -> -344.90323 | BK16: =GEN!AF13 -> 0.1875625
A17: =ELEC!C15 -> 44693 | B17: ='B5'!B16 -> 234 | C17: =B17*$B$4 -> 5034.7742 | D17: =SUM(B17) -> 234 | E17: =D17*$B$4 -> 5034.7742 | F17: =SUM(D17) -> 234 | G17: =F17*$B$4 -> 5034.7742 | H17: =SUM(F17) -> 234 | I17: =H17*$B$4 -> 5034.7742 | J17: =SUM(H17) -> 234 | K17: =J17*$B$4 -> 5034.7742 | L17: =SUM(J17) -> 234 | M17: =L17*$B$4 -> 5034.7742 | N17: =SUM(L17) -> 234 | O17: =N17*$B$4 -> 5034.7742 | P17: =SUM(N17) -> 234 | Q17: =P17*$B$4 -> 5034.7742 | R17: =SUM(P17) -> 234 | S17: =R17*$B$4 -> 5034.7742 | T17: =SUM(R17) -> 234 | U17: =T17*$B$4 -> 5034.7742 | V17: =SUM(T17) -> 234 | W17: =V17*$B$4 -> 5034.7742 | X17: =SUM(Y17/73370) -> 0.75483871 | Y17: =SUM(C17+E17+G17+I17+K17+M17+O17+Q17+S17+U17+W17) -> 55382.516 | Z17: ='B5'!C16 -> 240 | AA17: =SUM(Z17*$Z$4) -> 2400 | AB17: =SUM(Z17) -> 240 | AC17: =SUM(AB17*$Z$4) -> 2400 | AD17: =SUM(AB17) -> 240 | AE17: =SUM(AD17*$Z$4) -> 2400 | AF17: =SUM(AD17) -> 240 | AG17: =SUM(AF17*$Z$4) -> 2400 | AH17: =SUM(AF17) -> 240 | AI17: =SUM(AH17*$Z$4) -> 2400 | AJ17: =SUM(AH17) -> 240 | AK17: =SUM(AJ17*$Z$4) -> 2400 | AL17: =SUM(AJ17) -> 240 | AM17: =SUM(AL17*$Z$4) -> 2400 | AN17: =SUM(AO17/19600) -> 0.85714286 | AO17: =SUM(AA17+AC17+AE17+AG17+AI17+AK17+AM17) -> 16800 | AQ17: =SUM(AR17/92970) -> 0.77640654 | AR17: =Y17+AO17 -> 72182.516 | AS17: =SUM(AR17-AR16-AT17) -> -1226.7097 | AV17: =IF(AT17>0,AU17,AV16) -> 1.085 | AW17: =-SUM('B5'!AI16) -> -131 | AX17: =-SUM(AW17-AS17) -> -1095.7097 | AY17: =SUM(AX17+AW17) -> -1226.7097 | AZ17: =ELEC!A15 -> 0 | BA17: ='General information '!D16 -> 19.5 | BB17: =SUM('General information '!E16) -> 0.72 | BC17: =IF(AR16>=AR17,0,1) -> 0 | BD17: 19222 | BE17: =(305/1185)*ELEC!Q16 -> 0 | BG17: =#REF!-BE17 -> #REF! | BI17: 4 | BJ17: =AX17/BI17 -> -273.92742 | BK17: =GEN!AF14 -> 0.18097222
A18: =ELEC!C16 -> 44694 | B18: ='B5'!B17 -> 234 | C18: =B18*$B$4 -> 5034.7742 | D18: =SUM(B18) -> 234 | E18: =D18*$B$4 -> 5034.7742 | F18: =SUM(D18) -> 234 | G18: =F18*$B$4 -> 5034.7742 | H18: =SUM(F18) -> 234 | I18: =H18*$B$4 -> 5034.7742 | J18: =SUM(H18) -> 234 | K18: =J18*$B$4 -> 5034.7742 | L18: =SUM(J18) -> 234 | M18: =L18*$B$4 -> 5034.7742 | N18: =SUM(L18) -> 234 | O18: =N18*$B$4 -> 5034.7742 | P18: =SUM(N18) -> 234 | Q18: =P18*$B$4 -> 5034.7742 | R18: =SUM(P18) -> 234 | S18: =R18*$B$4 -> 5034.7742 | T18: =SUM(R18) -> 234 | U18: =T18*$B$4 -> 5034.7742 | V18: =SUM(T18) -> 234 | W18: =V18*$B$4 -> 5034.7742 | X18: =SUM(Y18/73370) -> 0.75483871 | Y18: =SUM(C18+E18+G18+I18+K18+M18+O18+Q18+S18+U18+W18) -> 55382.516 | Z18: ='B5'!C17 -> 240 | AA18: =SUM(Z18*$Z$4) -> 2400 | AB18: =SUM(Z18) -> 240 | AC18: =SUM(AB18*$Z$4) -> 2400 | AD18: =SUM(AB18) -> 240 | AE18: =SUM(AD18*$Z$4) -> 2400 | AF18: =SUM(AD18) -> 240 | AG18: =SUM(AF18*$Z$4) -> 2400 | AH18: =SUM(AF18) -> 240 | AI18: =SUM(AH18*$Z$4) -> 2400 | AJ18: =SUM(AH18) -> 240 | AK18: =SUM(AJ18*$Z$4) -> 2400 | AL18: =SUM(AJ18) -> 240 | AM18: =SUM(AL18*$Z$4) -> 2400 | AN18: =SUM(AO18/19600) -> 0.85714286 | AO18: =SUM(AA18+AC18+AE18+AG18+AI18+AK18+AM18) -> 16800 | AQ18: =SUM(AR18/92970) -> 0.77640654 | AR18: =Y18+AO18 -> 72182.516 | AS18: =SUM(AR18-AR17-AT18) -> 0 | AV18: =IF(AT18>0,AU18,AV17) -> 1.085 | AW18: =-SUM('B5'!AI17) -> 0 | AX18: =-SUM(AW18-AS18) -> 0 | AY18: =SUM(AX18+AW18) -> 0 | AZ18: =ELEC!A16 -> 0 | BA18: ='General information '!D17 -> 0 | BB18: =SUM('General information '!E17) -> 0 | BC18: =IF(AR17>=AR18,0,1) -> 0 | BD18: 19222 | BE18: =(305/1185)*ELEC!Q17 -> 0 | BG18: =#REF!-BE18 -> #REF! | BI18: 5 | BJ18: =AX18/BI18 -> 0 | BK18: =GEN!AF15 -> #DIV/0!
A19: =ELEC!C17 -> 44695 | B19: ='B5'!B18 -> 234 | C19: =B19*$B$4 -> 5034.7742 | D19: =SUM(B19) -> 234 | E19: =D19*$B$4 -> 5034.7742 | F19: =SUM(D19) -> 234 | G19: =F19*$B$4 -> 5034.7742 | H19: =SUM(F19) -> 234 | I19: =H19*$B$4 -> 5034.7742 | J19: =SUM(H19) -> 234 | K19: =J19*$B$4 -> 5034.7742 | L19: =SUM(J19) -> 234 | M19: =L19*$B$4 -> 5034.7742 | N19: =SUM(L19) -> 234 | O19: =N19*$B$4 -> 5034.7742 | P19: =SUM(N19) -> 234 | Q19: =P19*$B$4 -> 5034.7742 | R19: =SUM(P19) -> 234 | S19: =R19*$B$4 -> 5034.7742 | T19: =SUM(R19) -> 234 | U19: =T19*$B$4 -> 5034.7742 | V19: =SUM(T19) -> 234 | W19: =V19*$B$4 -> 5034.7742 | X19: =SUM(Y19/73370) -> 0.75483871 | Y19: =SUM(C19+E19+G19+I19+K19+M19+O19+Q19+S19+U19+W19) -> 55382.516 | Z19: ='B5'!C18 -> 240 | AA19: =SUM(Z19*$Z$4) -> 2400 | AB19: =SUM(Z19) -> 240 | AC19: =SUM(AB19*$Z$4) -> 2400 | AD19: =SUM(AB19) -> 240 | AE19: =SUM(AD19*$Z$4) -> 2400 | AF19: =SUM(AD19) -> 240 | AG19: =SUM(AF19*$Z$4) -> 2400 | AH19: =SUM(AF19) -> 240 | AI19: =SUM(AH19*$Z$4) -> 2400 | AJ19: =SUM(AH19) -> 240 | AK19: =SUM(AJ19*$Z$4) -> 2400 | AL19: =SUM(AJ19) -> 240 | AM19: =SUM(AL19*$Z$4) -> 2400 | AN19: =SUM(AO19/19600) -> 0.85714286 | AO19: =SUM(AA19+AC19+AE19+AG19+AI19+AK19+AM19) -> 16800 | AQ19: =SUM(AR19/92970) -> 0.77640654 | AR19: =Y19+AO19 -> 72182.516 | AS19: =SUM(AR19-AR18-AT19) -> 0 | AV19: =IF(AT19>0,AU19,AV18) -> 1.085 | AW19: =-SUM('B5'!AI18) -> 0 | AX19: =-SUM(AW19-AS19) -> 0 | AY19: =SUM(AX19+AW19) -> 0 | AZ19: =ELEC!A17 -> 0 | BA19: ='General information '!D18 -> 0 | BB19: =SUM('General information '!E18) -> 0 | BC19: =IF(AR18>=AR19,0,1) -> 0 | BD19: 19222 | BE19: =(305/1185)*ELEC!Q18 -> 0 | BG19: =#REF!-BE19 -> #REF! | BI19: 6 | BJ19: =AX19/BI19 -> 0 | BK19: =GEN!AF16 -> #DIV/0!
A20: =ELEC!C18 -> 44696 | B20: ='B5'!B19 -> 234 | C20: =B20*$B$4 -> 5034.7742 | D20: =SUM(B20) -> 234 | E20: =D20*$B$4 -> 5034.7742 | F20: =SUM(D20) -> 234 | G20: =F20*$B$4 -> 5034.7742 | H20: =SUM(F20) -> 234 | I20: =H20*$B$4 -> 5034.7742 | J20: =SUM(H20) -> 234 | K20: =J20*$B$4 -> 5034.7742 | L20: =SUM(J20) -> 234 | M20: =L20*$B$4 -> 5034.7742 | N20: =SUM(L20) -> 234 | O20: =N20*$B$4 -> 5034.7742 | P20: =SUM(N20) -> 234 | Q20: =P20*$B$4 -> 5034.7742 | R20: =SUM(P20) -> 234 | S20: =R20*$B$4 -> 5034.7742 | T20: =SUM(R20) -> 234 | U20: =T20*$B$4 -> 5034.7742 | V20: =SUM(T20) -> 234 | W20: =V20*$B$4 -> 5034.7742 | X20: =SUM(Y20/73370) -> 0.75483871 | Y20: =SUM(C20+E20+G20+I20+K20+M20+O20+Q20+S20+U20+W20) -> 55382.516 | Z20: ='B5'!C19 -> 240 | AA20: =SUM(Z20*$Z$4) -> 2400 | AB20: =SUM(Z20) -> 240 | AC20: =SUM(AB20*$Z$4) -> 2400 | AD20: =SUM(AB20) -> 240 | AE20: =SUM(AD20*$Z$4) -> 2400 | AF20: =SUM(AD20) -> 240 | AG20: =SUM(AF20*$Z$4) -> 2400 | AH20: =SUM(AF20) -> 240 | AI20: =SUM(AH20*$Z$4) -> 2400 | AJ20: =SUM(AH20) -> 240 | AK20: =SUM(AJ20*$Z$4) -> 2400 | AL20: =SUM(AJ20) -> 240 | AM20: =SUM(AL20*$Z$4) -> 2400 | AN20: =SUM(AO20/19600) -> 0.85714286 | AO20: =SUM(AA20+AC20+AE20+AG20+AI20+AK20+AM20) -> 16800 | AQ20: =SUM(AR20/92970) -> 0.77640654 | AR20: =Y20+AO20 -> 72182.516 | AS20: =SUM(AR20-AR19-AT20) -> 0 | AV20: =IF(AT20>0,AU20,AV19) -> 1.085 | AW20: =-SUM('B5'!AI19) -> 0 | AX20: =-SUM(AW20-AS20) -> 0 | AY20: =SUM(AX20+AW20) -> 0 | AZ20: =ELEC!A18 -> 0 | BA20: ='General information '!D19 -> 0 | BB20: =SUM('General information '!E19) -> 0 | BC20: =IF(AR19>=AR20,0,1) -> 0 | BD20: 19222 | BE20: =(305/1185)*ELEC!Q19 -> 0 | BG20: =#REF!-BE20 -> #REF! | BI20: 7 | BJ20: =AX20/BI20 -> 0 | BK20: =GEN!AF17 -> #DIV/0!
A21: =ELEC!C19 -> 44697 | B21: ='B5'!B20 -> 234 | C21: =B21*$B$4 -> 5034.7742 | D21: =SUM(B21) -> 234 | E21: =D21*$B$4 -> 5034.7742 | F21: =SUM(D21) -> 234 | G21: =F21*$B$4 -> 5034.7742 | H21: =SUM(F21) -> 234 | I21: =H21*$B$4 -> 5034.7742 | J21: =SUM(H21) -> 234 | K21: =J21*$B$4 -> 5034.7742 | L21: =SUM(J21) -> 234 | M21: =L21*$B$4 -> 5034.7742 | N21: =SUM(L21) -> 234 | O21: =N21*$B$4 -> 5034.7742 | P21: =SUM(N21) -> 234 | Q21: =P21*$B$4 -> 5034.7742 | R21: =SUM(P21) -> 234 | S21: =R21*$B$4 -> 5034.7742 | T21: =SUM(R21) -> 234 | U21: =T21*$B$4 -> 5034.7742 | V21: =SUM(T21) -> 234 | W21: =V21*$B$4 -> 5034.7742 | X21: =SUM(Y21/73370) -> 0.75483871 | Y21: =SUM(C21+E21+G21+I21+K21+M21+O21+Q21+S21+U21+W21) -> 55382.516 | Z21: ='B5'!C20 -> 240 | AA21: =SUM(Z21*$Z$4) -> 2400 | AB21: =SUM(Z21) -> 240 | AC21: =SUM(AB21*$Z$4) -> 2400 | AD21: =SUM(AB21) -> 240 | AE21: =SUM(AD21*$Z$4) -> 2400 | AF21: =SUM(AD21) -> 240 | AG21: =SUM(AF21*$Z$4) -> 2400 | AH21: =SUM(AF21) -> 240 | AI21: =SUM(AH21*$Z$4) -> 2400 | AJ21: =SUM(AH21) -> 240 | AK21: =SUM(AJ21*$Z$4) -> 2400 | AL21: =SUM(AJ21) -> 240 | AM21: =SUM(AL21*$Z$4) -> 2400 | AN21: =SUM(AO21/19600) -> 0.85714286 | AO21: =SUM(AA21+AC21+AE21+AG21+AI21+AK21+AM21) -> 16800 | AQ21: =SUM(AR21/92970) -> 0.77640654 | AR21: =Y21+AO21 -> 72182.516 | AS21: =SUM(AR21-AR20-AT21) -> 0 | AV21: =IF(AT21>0,AU21,AV20) -> 1.085 | AW21: =-SUM('B5'!AI20) -> 0 | AX21: =-SUM(AW21-AS21) -> 0 | AY21: =SUM(AX21+AW21) -> 0 | AZ21: =ELEC!A19 -> 0 | BA21: ='General information '!D20 -> 0 | BB21: =SUM('General information '!E20) -> 0 | BC21: =IF(AR20>=AR21,0,1) -> 0 | BD21: 19222 | BE21: =(305/1185)*ELEC!Q20 -> 0 | BG21: =#REF!-BE21 -> #REF! | BI21: 8 | BJ21: =AX21/BI21 -> 0 | BK21: =GEN!AF18 -> #DIV/0!
A22: =ELEC!C20 -> 44698 | B22: ='B5'!B21 -> 234 | C22: =B22*$B$4 -> 5034.7742 | D22: =SUM(B22) -> 234 | E22: =D22*$B$4 -> 5034.7742 | F22: =SUM(D22) -> 234 | G22: =F22*$B$4 -> 5034.7742 | H22: =SUM(F22) -> 234 | I22: =H22*$B$4 -> 5034.7742 | J22: =SUM(H22) -> 234 | K22: =J22*$B$4 -> 5034.7742 | L22: =SUM(J22) -> 234 | M22: =L22*$B$4 -> 5034.7742 | N22: =SUM(L22) -> 234 | O22: =N22*$B$4 -> 5034.7742 | P22: =SUM(N22) -> 234 | Q22: =P22*$B$4 -> 5034.7742 | R22: =SUM(P22) -> 234 | S22: =R22*$B$4 -> 5034.7742 | T22: =SUM(R22) -> 234 | U22: =T22*$B$4 -> 5034.7742 | V22: =SUM(T22) -> 234 | W22: =V22*$B$4 -> 5034.7742 | X22: =SUM(Y22/73370) -> 0.75483871 | Y22: =SUM(C22+E22+G22+I22+K22+M22+O22+Q22+S22+U22+W22) -> 55382.516 | Z22: ='B5'!C21 -> 240 | AA22: =SUM(Z22*$Z$4) -> 2400 | AB22: =SUM(Z22) -> 240 | AC22: =SUM(AB22*$Z$4) -> 2400 | AD22: =SUM(AB22) -> 240 | AE22: =SUM(AD22*$Z$4) -> 2400 | AF22: =SUM(AD22) -> 240 | AG22: =SUM(AF22*$Z$4) -> 2400 | AH22: =SUM(AF22) -> 240 | AI22: =SUM(AH22*$Z$4) -> 2400 | AJ22: =SUM(AH22) -> 240 | AK22: =SUM(AJ22*$Z$4) -> 2400 | AL22: =SUM(AJ22) -> 240 | AM22: =SUM(AL22*$Z$4) -> 2400 | AN22: =SUM(AO22/19600) -> 0.85714286 | AO22: =SUM(AA22+AC22+AE22+AG22+AI22+AK22+AM22) -> 16800 | AQ22: =SUM(AR22/92970) -> 0.77640654 | AR22: =Y22+AO22 -> 72182.516 | AS22: =SUM(AR22-AR21-AT22) -> 0 | AV22: =IF(AT22>0,AU22,AV21) -> 1.085 | AW22: =-SUM('B5'!AI21) -> 0 | AX22: =-SUM(AW22-AS22) -> 0 | AY22: =SUM(AX22+AW22) -> 0 | AZ22: =ELEC!A20 -> 0 | BA22: ='General information '!D21 -> 0 | BB22: =SUM('General information '!E21) -> 0 | BC22: =IF(AR21>=AR22,0,1) -> 0 | BD22: 19222 | BE22: =(305/1185)*ELEC!Q21 -> 0 | BG22: =#REF!-BE22 -> #REF! | BI22: 9 | BJ22: =AX22/BI22 -> 0 | BK22: =GEN!AF19 -> #DIV/0!
A23: =ELEC!C21 -> 44699 | B23: ='B5'!B22 -> 234 | C23: =B23*$B$4 -> 5034.7742 | D23: =SUM(B23) -> 234 | E23: =D23*$B$4 -> 5034.7742 | F23: =SUM(D23) -> 234 | G23: =F23*$B$4 -> 5034.7742 | H23: =SUM(F23) -> 234 | I23: =H23*$B$4 -> 5034.7742 | J23: =SUM(H23) -> 234 | K23: =J23*$B$4 -> 5034.7742 | L23: =SUM(J23) -> 234 | M23: =L23*$B$4 -> 5034.7742 | N23: =SUM(L23) -> 234 | O23: =N23*$B$4 -> 5034.7742 | P23: =SUM(N23) -> 234 | Q23: =P23*$B$4 -> 5034.7742 | R23: =SUM(P23) -> 234 | S23: =R23*$B$4 -> 5034.7742 | T23: =SUM(R23) -> 234 | U23: =T23*$B$4 -> 5034.7742 | V23: =SUM(T23) -> 234 | W23: =V23*$B$4 -> 5034.7742 | X23: =SUM(Y23/73370) -> 0.75483871 | Y23: =SUM(C23+E23+G23+I23+K23+M23+O23+Q23+S23+U23+W23) -> 55382.516 | Z23: ='B5'!C22 -> 240 | AA23: =SUM(Z23*$Z$4) -> 2400 | AB23: =SUM(Z23) -> 240 | AC23: =SUM(AB23*$Z$4) -> 2400 | AD23: =SUM(AB23) -> 240 | AE23: =SUM(AD23*$Z$4) -> 2400 | AF23: =SUM(AD23) -> 240 | AG23: =SUM(AF23*$Z$4) -> 2400 | AH23: =SUM(AF23) -> 240 | AI23: =SUM(AH23*$Z$4) -> 2400 | AJ23: =SUM(AH23) -> 240 | AK23: =SUM(AJ23*$Z$4) -> 2400 | AL23: =SUM(AJ23) -> 240 | AM23: =SUM(AL23*$Z$4) -> 2400 | AN23: =SUM(AO23/19600) -> 0.85714286 | AO23: =SUM(AA23+AC23+AE23+AG23+AI23+AK23+AM23) -> 16800 | AQ23: =SUM(AR23/92970) -> 0.77640654 | AR23: =Y23+AO23 -> 72182.516 | AS23: =SUM(AR23-AR22-AT23) -> 0 | AV23: =IF(AT23>0,AU23,AV22) -> 1.085 | AW23: =-SUM('B5'!AI22) -> 0 | AX23: =-SUM(AW23-AS23) -> 0 | AY23: =SUM(AX23+AW23) -> 0 | AZ23: =ELEC!A21 -> 0 | BA23: ='General information '!D22 -> 0 | BB23: =SUM('General information '!E22) -> 0 | BC23: =IF(AR22>=AR23,0,1) -> 0 | BD23: 19222 | BE23: =(305/1185)*ELEC!Q22 -> 0 | BG23: =#REF!-BE23 -> #REF! | BI23: 10 | BJ23: =AX23/BI23 -> 0 | BK23: =GEN!AF20 -> #DIV/0!
A24: =ELEC!C22 -> 44700 | B24: ='B5'!B23 -> 234 | C24: =B24*$B$4 -> 5034.7742 | D24: =SUM(B24) -> 234 | E24: =D24*$B$4 -> 5034.7742 | F24: =SUM(D24) -> 234 | G24: =F24*$B$4 -> 5034.7742 | H24: =SUM(F24) -> 234 | I24: =H24*$B$4 -> 5034.7742 | J24: =SUM(H24) -> 234 | K24: =J24*$B$4 -> 5034.7742 | L24: =SUM(J24) -> 234 | M24: =L24*$B$4 -> 5034.7742 | N24: =SUM(L24) -> 234 | O24: =N24*$B$4 -> 5034.7742 | P24: =SUM(N24) -> 234 | Q24: =P24*$B$4 -> 5034.7742 | R24: =SUM(P24) -> 234 | S24: =R24*$B$4 -> 5034.7742 | T24: =SUM(R24) -> 234 | U24: =T24*$B$4 -> 5034.7742 | V24: =SUM(T24) -> 234 | W24: =V24*$B$4 -> 5034.7742 | X24: =SUM(Y24/73370) -> 0.75483871 | Y24: =SUM(C24+E24+G24+I24+K24+M24+O24+Q24+S24+U24+W24) -> 55382.516 | Z24: ='B5'!C23 -> 240 | AA24: =SUM(Z24*$Z$4) -> 2400 | AB24: =SUM(Z24) -> 240 | AC24: =SUM(AB24*$Z$4) -> 2400 | AD24: =SUM(AB24) -> 240 | AE24: =SUM(AD24*$Z$4) -> 2400 | AF24: =SUM(AD24) -> 240 | AG24: =SUM(AF24*$Z$4) -> 2400 | AH24: =SUM(AF24) -> 240 | AI24: =SUM(AH24*$Z$4) -> 2400 | AJ24: =SUM(AH24) -> 240 | AK24: =SUM(AJ24*$Z$4) -> 2400 | AL24: =SUM(AJ24) -> 240 | AM24: =SUM(AL24*$Z$4) -> 2400 | AN24: =SUM(AO24/19600) -> 0.85714286 | AO24: =SUM(AA24+AC24+AE24+AG24+AI24+AK24+AM24) -> 16800 | AQ24: =SUM(AR24/92970) -> 0.77640654 | AR24: =Y24+AO24 -> 72182.516 | AS24: =SUM(AR24-AR23-AT24) -> 0 | AV24: =IF(AT24>0,AU24,AV23) -> 1.085 | AW24: =-SUM('B5'!AI23) -> 0 | AX24: =-SUM(AW24-AS24) -> 0 | AY24: =SUM(AX24+AW24) -> 0 | AZ24: =ELEC!A22 -> 0 | BA24: ='General information '!D23 -> 0 | BB24: =SUM('General information '!E23) -> 0 | BC24: =IF(AR23>=AR24,0,1) -> 0 | BD24: 19222 | BE24: =(305/1185)*ELEC!Q23 -> 0 | BG24: =#REF!-BE24 -> #REF! | BI24: 11 | BJ24: =AX24/BI24 -> 0 | BK24: =GEN!AF21 -> #DIV/0!
A25: =ELEC!C23 -> 44701 | B25: ='B5'!B24 -> 234 | C25: =B25*$B$4 -> 5034.7742 | D25: =SUM(B25) -> 234 | E25: =D25*$B$4 -> 5034.7742 | F25: =SUM(D25) -> 234 | G25: =F25*$B$4 -> 5034.7742 | H25: =SUM(F25) -> 234 | I25: =H25*$B$4 -> 5034.7742 | J25: =SUM(H25) -> 234 | K25: =J25*$B$4 -> 5034.7742 | L25: =SUM(J25) -> 234 | M25: =L25*$B$4 -> 5034.7742 | N25: =SUM(L25) -> 234 | O25: =N25*$B$4 -> 5034.7742 | P25: =SUM(N25) -> 234 | Q25: =P25*$B$4 -> 5034.7742 | R25: =SUM(P25) -> 234 | S25: =R25*$B$4 -> 5034.7742 | T25: =SUM(R25) -> 234 | U25: =T25*$B$4 -> 5034.7742 | V25: =SUM(T25) -> 234 | W25: =V25*$B$4 -> 5034.7742 | X25: =SUM(Y25/73370) -> 0.75483871 | Y25: =SUM(C25+E25+G25+I25+K25+M25+O25+Q25+S25+U25+W25) -> 55382.516 | Z25: ='B5'!C24 -> 240 | AA25: =SUM(Z25*$Z$4) -> 2400 | AB25: =SUM(Z25) -> 240 | AC25: =SUM(AB25*$Z$4) -> 2400 | AD25: =SUM(AB25) -> 240 | AE25: =SUM(AD25*$Z$4) -> 2400 | AF25: =SUM(AD25) -> 240 | AG25: =SUM(AF25*$Z$4) -> 2400 | AH25: =SUM(AF25) -> 240 | AI25: =SUM(AH25*$Z$4) -> 2400 | AJ25: =SUM(AH25) -> 240 | AK25: =SUM(AJ25*$Z$4) -> 2400 | AL25: =SUM(AJ25) -> 240 | AM25: =SUM(AL25*$Z$4) -> 2400 | AN25: =SUM(AO25/19600) -> 0.85714286 | AO25: =SUM(AA25+AC25+AE25+AG25+AI25+AK25+AM25) -> 16800 | AQ25: =SUM(AR25/92970) -> 0.77640654 | AR25: =Y25+AO25 -> 72182.516 | AS25: =SUM(AR25-AR24-AT25) -> 0 | AV25: =IF(AT25>0,AU25,AV24) -> 1.085 | AW25: =-SUM('B5'!AI24) -> 0 | AX25: =-SUM(AW25-AS25) -> 0 | AY25: =SUM(AX25+AW25) -> 0 | AZ25: =ELEC!A23 -> 0 | BA25: ='General information '!D24 -> 0 | BB25: =SUM('General information '!E24) -> 0 | BC25: =IF(AR24>=AR25,0,1) -> 0 | BD25: 19222 | BE25: =(305/1185)*ELEC!Q24 -> 0 | BG25: =#REF!-BE25 -> #REF! | BI25: 12 | BJ25: =AX25/BI25 -> 0 | BK25: =GEN!AF22 -> #DIV/0!
... A32: =ELEC!C30 -> 44708 | B32: ='B5'!B31 -> 234 | C32: =B32*$B$4 -> 5034.7742 | D32: =SUM(B32) -> 234 | E32: =D32*$B$4 -> 5034.7742 | F32: =SUM(D32) -> 234 | G32: =F32*$B$4 -> 5034.7742 | H32: =SUM(F32) -> 234 | I32: =H32*$B$4 -> 5034.7742 | J32: =SUM(H32) -> 234 | K32: =J32*$B$4 -> 5034.7742 | L32: =SUM(J32) -> 234 | M32: =L32*$B$4 -> 5034.7742 | N32: =SUM(L32) -> 234 | O32: =N32*$B$4 -> 5034.7742 | P32: =SUM(N32) -> 234 | Q32: =P32*$B$4 -> 5034.7742 | R32: =SUM(P32) -> 234 | S32: =R32*$B$4 -> 5034.7742 | T32: =SUM(R32) -> 234 | U32: =T32*$B$4 -> 5034.7742 | V32: =SUM(T32) -> 234 | W32: =V32*$B$4 -> 5034.7742 | X32: =SUM(Y32/73370) -> 0.75483871 | Y32: =SUM(C32+E32+G32+I32+K32+M32+O32+Q32+S32+U32+W32) -> 55382.516 | Z32: ='B5'!C31 -> 240 | AA32: =SUM(Z32*$Z$4) -> 2400 | AB32: =SUM(Z32) -> 240 | AC32: =SUM(AB32*$Z$4) -> 2400 | AD32: =SUM(AB32) -> 240 | AE32: =SUM(AD32*$Z$4) -> 2400 | AF32: =SUM(AD32) -> 240 | AG32: =SUM(AF32*$Z$4) -> 2400 | AH32: =SUM(AF32) -> 240 | AI32: =SUM(AH32*$Z$4) -> 2400 | AJ32: =SUM(AH32) -> 240 | AK32: =SUM(AJ32*$Z$4) -> 2400 | AL32: =SUM(AJ32) -> 240 | AM32: =SUM(AL32*$Z$4) -> 2400 | AN32: =SUM(AO32/19600) -> 0.85714286 | AO32: =SUM(AA32+AC32+AE32+AG32+AI32+AK32+AM32) -> 16800 | AQ32: =SUM(AR32/92970) -> 0.77640654 | AR32: =Y32+AO32 -> 72182.516 | AS32: =SUM(AR32-AR31-AT32) -> 0 | AV32: =IF(AT32>0,AU32,AV31) -> 1.085 | AW32: =-SUM('B5'!AI31) -> 0 | AX32: =-SUM(AW32-AS32) -> 0 | AY32: =SUM(AX32+AW32) -> 0 | AZ32: =ELEC!A30 -> 0 | BA32: ='General information '!D31 -> 0 | BB32: =SUM('General information '!E31) -> 0 | BC32: =IF(AR31>=AR32,0,1) -> 0 | BD32: 19222 | BE32: =(305/1185)*ELEC!Q31 -> 0 | BG32: =#REF!-BE32 -> #REF! | BI32: 19 | BJ32: =AX32/BI32 -> 0 | BK32: =GEN!AF29 -> #DIV/0!
A33: =ELEC!C31 -> 44709 | B33: ='B5'!B32 -> 234 | C33: =B33*$B$4 -> 5034.7742 | D33: =SUM(B33) -> 234 | E33: =D33*$B$4 -> 5034.7742 | F33: =SUM(D33) -> 234 | G33: =F33*$B$4 -> 5034.7742 | H33: =SUM(F33) -> 234 | I33: =H33*$B$4 -> 5034.7742 | J33: =SUM(H33) -> 234 | K33: =J33*$B$4 -> 5034.7742 | L33: =SUM(J33) -> 234 | M33: =L33*$B$4 -> 5034.7742 | N33: =SUM(L33) -> 234 | O33: =N33*$B$4 -> 5034.7742 | P33: =SUM(N33) -> 234 | Q33: =P33*$B$4 -> 5034.7742 | R33: =SUM(P33) -> 234 | S33: =R33*$B$4 -> 5034.7742 | T33: =SUM(R33) -> 234 | U33: =T33*$B$4 -> 5034.7742 | V33: =SUM(T33) -> 234 | W33: =V33*$B$4 -> 5034.7742 | X33: =SUM(Y33/73370) -> 0.75483871 | Y33: =SUM(C33+E33+G33+I33+K33+M33+O33+Q33+S33+U33+W33) -> 55382.516 | Z33: ='B5'!C32 -> 240 | AA33: =SUM(Z33*$Z$4) -> 2400 | AB33: =SUM(Z33) -> 240 | AC33: =SUM(AB33*$Z$4) -> 2400 | AD33: =SUM(AB33) -> 240 | AE33: =SUM(AD33*$Z$4) -> 2400 | AF33: =SUM(AD33) -> 240 | AG33: =SUM(AF33*$Z$4) -> 2400 | AH33: =SUM(AF33) -> 240 | AI33: =SUM(AH33*$Z$4) -> 2400 | AJ33: =SUM(AH33) -> 240 | AK33: =SUM(AJ33*$Z$4) -> 2400 | AL33: =SUM(AJ33) -> 240 | AM33: =SUM(AL33*$Z$4) -> 2400 | AN33: =SUM(AO33/19600) -> 0.85714286 | AO33: =SUM(AA33+AC33+AE33+AG33+AI33+AK33+AM33) -> 16800 | AQ33: =SUM(AR33/92970) -> 0.77640654 | AR33: =Y33+AO33 -> 72182.516 | AS33: =SUM(AR33-AR32-AT33) -> 0 | AV33: =IF(AT33>0,AU33,AV32) -> 1.085 | AW33: =-SUM('B5'!AI32) -> 0 | AX33: =-SUM(AW33-AS33) -> 0 | AY33: =SUM(AX33+AW33) -> 0 | AZ33: =ELEC!A31 -> 0 | BA33: ='General information '!D32 -> 0 | BB33: =SUM('General information '!E32) -> 0 | BC33: =IF(AR32>=AR33,0,1) -> 0 | BD33: 19222 | BE33: =(305/1185)*ELEC!#REF! -> #REF! | BG33: =#REF!-BE33 -> #REF! | BI33: 20 | BJ33: =AX33/BI33 -> 0 | BK33: =GEN!AF30 -> #DIV/0!
A34: =ELEC!C32 -> 44710 | B34: ='B5'!B33 -> 234 | C34: =B34*$B$4 -> 5034.7742 | D34: =SUM(B34) -> 234 | E34: =D34*$B$4 -> 5034.7742 | F34: =SUM(D34) -> 234 | G34: =F34*$B$4 -> 5034.7742 | H34: =SUM(F34) -> 234 | I34: =H34*$B$4 -> 5034.7742 | J34: =SUM(H34) -> 234 | K34: =J34*$B$4 -> 5034.7742 | L34: =SUM(J34) -> 234 | M34: =L34*$B$4 -> 5034.7742 | N34: =SUM(L34) -> 234 | O34: =N34*$B$4 -> 5034.7742 | P34: =SUM(N34) -> 234 | Q34: =P34*$B$4 -> 5034.7742 | R34: =SUM(P34) -> 234 | S34: =R34*$B$4 -> 5034.7742 | T34: =SUM(R34) -> 234 | U34: =T34*$B$4 -> 5034.7742 | V34: =SUM(T34) -> 234 | W34: =V34*$B$4 -> 5034.7742 | X34: =SUM(Y34/73370) -> 0.75483871 | Y34: =SUM(C34+E34+G34+I34+K34+M34+O34+Q34+S34+U34+W34) -> 55382.516 | Z34: ='B5'!C33 -> 240 | AA34: =SUM(Z34*$Z$4) -> 2400 | AB34: =SUM(Z34) -> 240 | AC34: =SUM(AB34*$Z$4) -> 2400 | AD34: =SUM(AB34) -> 240 | AE34: =SUM(AD34*$Z$4) -> 2400 | AF34: =SUM(AD34) -> 240 | AG34: =SUM(AF34*$Z$4) -> 2400 | AH34: =SUM(AF34) -> 240 | AI34: =SUM(AH34*$Z$4) -> 2400 | AJ34: =SUM(AH34) -> 240 | AK34: =SUM(AJ34*$Z$4) -> 2400 | AL34: =SUM(AJ34) -> 240 | AM34: =SUM(AL34*$Z$4) -> 2400 | AN34: =SUM(AO34/19600) -> 0.85714286 | AO34: =SUM(AA34+AC34+AE34+AG34+AI34+AK34+AM34) -> 16800 | AQ34: =SUM(AR34/92970) -> 0.77640654 | AR34: =Y34+AO34 -> 72182.516 | AS34: =SUM(AR34-AR33-AT34) -> 0 | AV34: =IF(AT34>0,AU34,AV33) -> 1.085 | AW34: =-SUM('B5'!AI33) -> 0 | AX34: =-SUM(AW34-AS34) -> 0 | AY34: =SUM(AX34+AW34) -> 0 | AZ34: =ELEC!A32 -> 0 | BA34: ='General information '!D33 -> 0 | BB34: =SUM('General information '!E33) -> 0 | BC34: =IF(AR33>=AR34,0,1) -> 0 | BD34: 19223 | BE34: =(305/1185)*ELEC!#REF! -> #REF! | BG34: =#REF!-BE34 -> #REF! | BI34: 21 | BJ34: =AX34/BI34 -> 0 | BK34: =GEN!AF31 -> #DIV/0!
A35: =ELEC!C33 -> 44711 | B35: ='B5'!B34 -> 234 | C35: =B35*$B$4 -> 5034.7742 | D35: =SUM(B35) -> 234 | E35: =D35*$B$4 -> 5034.7742 | F35: =SUM(D35) -> 234 | G35: =F35*$B$4 -> 5034.7742 | H35: =SUM(F35) -> 234 | I35: =H35*$B$4 -> 5034.7742 | J35: =SUM(H35) -> 234 | K35: =J35*$B$4 -> 5034.7742 | L35: =SUM(J35) -> 234 | M35: =L35*$B$4 -> 5034.7742 | N35: =SUM(L35) -> 234 | O35: =N35*$B$4 -> 5034.7742 | P35: =SUM(N35) -> 234 | Q35: =P35*$B$4 -> 5034.7742 | R35: =SUM(P35) -> 234 | S35: =R35*$B$4 -> 5034.7742 | T35: =SUM(R35) -> 234 | U35: =T35*$B$4 -> 5034.7742 | V35: =SUM(T35) -> 234 | W35: =V35*$B$4 -> 5034.7742 | X35: =SUM(Y35/73370) -> 0.75483871 | Y35: =SUM(C35+E35+G35+I35+K35+M35+O35+Q35+S35+U35+W35) -> 55382.516 | Z35: ='B5'!C34 -> 240 | AA35: =SUM(Z35*$Z$4) -> 2400 | AB35: =SUM(Z35) -> 240 | AC35: =SUM(AB35*$Z$4) -> 2400 | AD35: =SUM(AB35) -> 240 | AE35: =SUM(AD35*$Z$4) -> 2400 | AF35: =SUM(AD35) -> 240 | AG35: =SUM(AF35*$Z$4) -> 2400 | AH35: =SUM(AF35) -> 240 | AI35: =SUM(AH35*$Z$4) -> 2400 | AJ35: =SUM(AH35) -> 240 | AK35: =SUM(AJ35*$Z$4) -> 2400 | AL35: =SUM(AJ35) -> 240 | AM35: =SUM(AL35*$Z$4) -> 2400 | AN35: =SUM(AO35/19600) -> 0.85714286 | AO35: =SUM(AA35+AC35+AE35+AG35+AI35+AK35+AM35) -> 16800 | AQ35: =SUM(AR35/92970) -> 0.77640654 | AR35: =Y35+AO35 -> 72182.516 | AS35: =SUM(AR35-AR34-AT35) -> 0 | AV35: =IF(AT35>0,AU35,AV34) -> 1.085 | AW35: =-SUM('B5'!AI34) -> 0 | AX35: =-SUM(AW35-AS35) -> 0 | AY35: =SUM(AX35+AW35) -> 0 | AZ35: =ELEC!A33 -> 0 | BA35: ='General information '!D34 -> 0 | BB35: =SUM('General information '!E34) -> 0 | BC35: =IF(AR34>=AR35,0,1) -> 0 | BD35: 19224 | BE35: =(305/1185)*ELEC!#REF! -> #REF! | BG35: =#REF!-BE35 -> #REF! | BI35: 22 | BJ35: =AX35/BI35 -> 0 | BK35: =GEN!AF32 -> #DIV/0!
A36: =ELEC!C34 -> 44712 | B36: ='B5'!B35 -> 234 | C36: =B36*$B$4 -> 5034.7742 | D36: =SUM(B36) -> 234 | E36: =D36*$B$4 -> 5034.7742 | F36: =SUM(D36) -> 234 | G36: =F36*$B$4 -> 5034.7742 | H36: =SUM(F36) -> 234 | I36: =H36*$B$4 -> 5034.7742 | J36: =SUM(H36) -> 234 | K36: =J36*$B$4 -> 5034.7742 | L36: =SUM(J36) -> 234 | M36: =L36*$B$4 -> 5034.7742 | N36: =SUM(L36) -> 234 | O36: =N36*$B$4 -> 5034.7742 | P36: =SUM(N36) -> 234 | Q36: =P36*$B$4 -> 5034.7742 | R36: =SUM(P36) -> 234 | S36: =R36*$B$4 -> 5034.7742 | T36: =SUM(R36) -> 234 | U36: =T36*$B$4 -> 5034.7742 | V36: =SUM(T36) -> 234 | W36: =V36*$B$4 -> 5034.7742 | X36: =SUM(Y36/73370) -> 0.75483871 | Y36: =SUM(C36+E36+G36+I36+K36+M36+O36+Q36+S36+U36+W36) -> 55382.516 | Z36: ='B5'!C35 -> 240 | AA36: =SUM(Z36*$Z$4) -> 2400 | AB36: =SUM(Z36) -> 240 | AC36: =SUM(AB36*$Z$4) -> 2400 | AD36: =SUM(AB36) -> 240 | AE36: =SUM(AD36*$Z$4) -> 2400 | AF36: =SUM(AD36) -> 240 | AG36: =SUM(AF36*$Z$4) -> 2400 | AH36: =SUM(AF36) -> 240 | AI36: =SUM(AH36*$Z$4) -> 2400 | AJ36: =SUM(AH36) -> 240 | AK36: =SUM(AJ36*$Z$4) -> 2400 | AL36: =SUM(AJ36) -> 240 | AM36: =SUM(AL36*$Z$4) -> 2400 | AN36: =SUM(AO36/19600) -> 0.85714286 | AO36: =SUM(AA36+AC36+AE36+AG36+AI36+AK36+AM36) -> 16800 | AQ36: =SUM(AR36/92970) -> 0.77640654 | AR36: =Y36+AO36 -> 72182.516 | AS36: =SUM(AR36-AR35-AT36) -> 0 | AV36: =IF(AT36>0,AU36,AV35) -> 1.085 | AW36: =-SUM('B5'!AI35) -> 0 | AX36: =-SUM(AW36-AS36) -> 0 | AY36: =SUM(AX36+AW36) -> 0 | AZ36: =ELEC!A34 -> 0 | BA36: ='General information '!D35 -> 0 | BB36: =SUM('General information '!E35) -> 0 | BC36: =IF(AR35>=AR36,0,1) -> 0 | BD36: 19225 | BE36: =(305/1185)*ELEC!#REF! -> #REF! | BG36: =#REF!-BE36 -> #REF! | BI36: 23 | BJ36: =AX36/BI36 -> 0 | BK36: =GEN!AF33 -> #DIV/0!
AR37: NB delivery | AS37: =COUNT(AT6:AT36) -> 1 | AT37: =SUM(AT6:AT36) -> 10000 | AU37: =SUM(AU6:AU36)/AS37 -> 1.085 | AX37: =SUM(AX6:AX36) -> -8327.3226 | AY37: =SUM(AY6:AY36) -> -9693.3226
AT38: =+AT37*AU37 -> 10850
AS40: =SUM(AS6:AS36)/'EDl log'!A35 -> -1615.5538
AX41: 43309
AR42: =AR36-22000 -> 50182.516 | AX42: =AX37/AX41 -> -0.19227695
AR43: =AR42/5500 -> 9.1240938
AR44: =AR43*2 -> 18.248188

Sheet EDl log
A1: Date | B1: EDL | C1: Consu EDL KW | F1: Peak | G1: 320 | H1: Day | I1: 112 | J1: Night | K1: 80
L2: P | M2: D | N2: N | O2: fee | P2: T EDL | Q2: Gen | R2: Elc C
A3: ='[2]EDl log'!$A$33 -> 44681 | B3: ='[2]EDl log'!B33 -> 1117981 | C3: ='[2]EDl log'!C33 -> 0 | D3: ='[2]EDl log'!D33 -> 0 | E3: ='[2]EDl log'!E33 -> 1117981 | F3: ='[2]EDl log'!F33 -> 161410 | G3: ='[2]EDl log'!G33 -> 0 | H3: ='[2]EDl log'!H33 -> 555135 | I3: ='[2]EDl log'!I33 -> 0 | ... T3: ='[2]EDl log'!T33 -> 0 | Z3: VAT | AA3: 0.1
A4: =ELEC!C4 -> 44682 | B4: =B3 -> 1117981 | C4: =SUM(B4-B3) -> 0 | D4: =SUM(G4+I4+K4) -> 0 | E4: =B3+D4 -> 1117981 | F4: =F3 -> 161410 | G4: =F4-F3 -> 0 | H4: =H3 -> 555135 | I4: =H4-H3 -> 0 | J4: =J3 -> 401437 | K4: =J4-J3 -> 0 | L4: =SUM(G4*$Y$28)/1507.5 -> 0 | M4: =SUM(I4*$Y$27)/1507.5 -> 0 | N4: =SUM(K4*$Y$26)/1507.5 -> 0 | O4: =($AC$29/$A$37)/1507.5 -> 154.80304 | P4: =SUM(L4:O4) -> 154.80304 | Q4: =SUM(-tanks!AX6*tanks!$AU$37) -> 0 | R4: =SUM(P4:Q4) -> 154.80304 | S4: =SUM(ELEC!N4) -> 0 | T4: =IF(S4>0,R4/S4,0) -> 0 | V4: EDL | W4: ='[2]EDl log'!$W$21 -> 44673 | Z4: Subscription
A5: =ELEC!C5 -> 44683 | B5: =B4 -> 1117981 | C5: =SUM(B5-B4) -> 0 | D5: =SUM(G5+I5+K5) -> 0 | E5: =B4+D5 -> 1117981 | F5: =F4 -> 161410 | G5: =F5-F4 -> 0 | H5: =H4 -> 555135 | I5: =H5-H4 -> 0 | J5: =J4 -> 401437 | K5: =J5-J4 -> 0 | L5: =SUM(G5*$Y$28)/1507.5 -> 0 | M5: =SUM(I5*$Y$27)/1507.5 -> 0 | N5: =SUM(K5*$Y$26)/1507.5 -> 0 | O5: =($AC$29/$A$37)/1507.5 -> 154.80304 | P5: =SUM(L5:O5) -> 154.80304 | Q5: =SUM(-tanks!AX7*tanks!$AU$37) -> 0 | R5: =SUM(P5:Q5) -> 154.80304 | S5: =SUM(ELEC!N5) -> 0 | T5: =IF(S5>0,R5/S5,0) -> 0 | Z5: KVA | AA5: 5000
A6: =ELEC!C6 -> 44684 | B6: =B5 -> 1117981 | C6: =SUM(B6-B5) -> 0 | D6: =SUM(G6+I6+K6) -> 0 | E6: =B5+D6 -> 1117981 | F6: =F5 -> 161410 | G6: =F6-F5 -> 0 | H6: =H5 -> 555135 | I6: =H6-H5 -> 0 | J6: =J5 -> 401437 | K6: =J6-J5 -> 0 | L6: =SUM(G6*$Y$28)/1507.5 -> 0 | M6: =SUM(I6*$Y$27)/1507.5 -> 0 | N6: =SUM(K6*$Y$26)/1507.5 -> 0 | O6: =($AC$29/$A$37)/1507.5 -> 154.80304 | P6: =SUM(L6:O6) -> 154.80304 | Q6: =SUM(-tanks!AX8*tanks!$AU$37) -> 2605.19 | R6: =SUM(P6:Q6) -> 2759.993 | S6: =SUM(ELEC!N6) -> 6202 | T6: =IF(S6>0,R6/S6,0) -> 0.44501661
A7: =ELEC!C7 -> 44685 | B7: 1118429 | C7: =SUM(B7-B6) -> 448 | D7: =SUM(G7+I7+K7) -> 447 | E7: =B6+D7 -> 1118428 | F7: =F6 -> 161410 | G7: =F7-F6 -> 0 | H7: 555582 | I7: =H7-H6 -> 447 | J7: =J6 -> 401437 | K7: =J7-J6 -> 0 | L7: =SUM(G7*$Y$28)/1507.5 -> 0 | M7: =SUM(I7*$Y$27)/1507.5 -> 33.20995 | N7: =SUM(K7*$Y$26)/1507.5 -> 0 | O7: =($AC$29/$A$37)/1507.5 -> 154.80304 | P7: =SUM(L7:O7) -> 188.01299 | Q7: =SUM(-tanks!AX9*tanks!$AU$37) -> 1665.545 | R7: =SUM(P7:Q7) -> 1853.558 | S7: =SUM(ELEC!N7) -> 4288 | T7: =IF(S7>0,R7/S7,0) -> 0.43226632 | V7: Electricity consumption | X7: Price LL
A8: =ELEC!C8 -> 44686 | B8: =B7 -> 1118429 | C8: =SUM(B8-B7) -> 0 | D8: =SUM(G8+I8+K8) -> 0 | E8: =B7+D8 -> 1118429 | F8: =F7 -> 161410 | G8: =F8-F7 -> 0 | H8: =H7 -> 555582 | I8: =H8-H7 -> 0 | J8: =J7 -> 401437 | K8: =J8-J7 -> 0 | L8: =SUM(G8*$Y$28)/1507.5 -> 0 | M8: =SUM(I8*$Y$27)/1507.5 -> 0 | N8: =SUM(K8*$Y$26)/1507.5 -> 0 | O8: =($AC$29/$A$37)/1507.5 -> 154.80304 | P8: =SUM(L8:O8) -> 154.80304 | Q8: =SUM(-tanks!AX10*tanks!$AU$37) -> 950.495 | R8: =SUM(P8:Q8) -> 1105.298 | S8: =SUM(ELEC!N8) -> 3111 | T8: =IF(S8>0,R8/S8,0) -> 0.35528706 | V8: Index in | W8: Index Out | Y8: Kwh Cost | Z8: K | AA8: Kwh | AB8: Total cost LL | AC8: Fees
A9: =ELEC!C9 -> 44687 | B9: =B8 -> 1118429 | C9: =SUM(B9-B8) -> 0 | D9: =SUM(G9+I9+K9) -> 0 | E9: =B8+D9 -> 1118429 | F9: =F8 -> 161410 | G9: =F9-F8 -> 0 | H9: =H8 -> 555582 | I9: =H9-H8 -> 0 | J9: 401437 | K9: =J9-J8 -> 0 | L9: =SUM(G9*$Y$28)/1507.5 -> 0 | M9: =SUM(I9*$Y$27)/1507.5 -> 0 | N9: =SUM(K9*$Y$26)/1507.5 -> 0 | O9: =($AC$29/$A$37)/1507.5 -> 154.80304 | P9: =SUM(L9:O9) -> 154.80304 | Q9: =SUM(-tanks!AX11*tanks!$AU$37) -> 0 | R9: =SUM(P9:Q9) -> 154.80304 | S9: =SUM(ELEC!N9) -> 0 | T9: =IF(S9>0,R9/S9,0) -> 0 | V9: ='[2]EDl log'!V26 -> 401347 | W9: ='[2]EDl log'!W26 -> 401437 | X9: ='[2]EDl log'!X26 -> Night | Y9: ='[2]EDl log'!Y26 -> 80 | Z9: ='[2]EDl log'!Z26 -> 1 | AA9: ='[2]EDl log'!AA26 -> 90 | AB9: ='[2]EDl log'!AB26 -> 7200 | AC9: ='[2]EDl log'!AC26 -> 1033333 | ... AF9: ='[2]EDl log'!AF26 -> 0
A10: =ELEC!C10 -> 44688 | B10: =B9 -> 1118429 | C10: =SUM(B10-B9) -> 0 | D10: =SUM(G10+I10+K10) -> 0 | E10: =B9+D10 -> 1118429 | F10: =F9 -> 161410 | G10: =F10-F9 -> 0 | H10: =H9 -> 555582 | I10: =H10-H9 -> 0 | J10: =J9 -> 401437 | K10: =J10-J9 -> 0 | L10: =SUM(G10*$Y$28)/1507.5 -> 0 | M10: =SUM(I10*$Y$27)/1507.5 -> 0 | N10: =SUM(K10*$Y$26)/1507.5 -> 0 | O10: =($AC$29/$A$37)/1507.5 -> 154.80304 | P10: =SUM(L10:O10) -> 154.80304 | Q10: =SUM(-tanks!AX12*tanks!$AU$37) -> 0 | R10: =SUM(P10:Q10) -> 154.80304 | S10: =SUM(ELEC!N10) -> 0 | T10: =IF(S10>0,R10/S10,0) -> 0 | V10: ='[2]EDl log'!V27 -> 553475 | W10: ='[2]EDl log'!W27 -> 555135 | X10: ='[2]EDl log'!X27 -> day | Y10: ='[2]EDl log'!Y27 -> 112 | Z10: ='[2]EDl log'!Z27 -> 1 | AA10: ='[2]EDl log'!AA27 -> 1660 | AB10: ='[2]EDl log'!AB27 -> 185920 | AC10: ='[2]EDl log'!AC27 -> 6200000 | ... AF10: ='[2]EDl log'!AF27 -> 0
A11: =ELEC!C11 -> 44689 | B11: 1118855 | C11: =SUM(B11-B10) -> 426 | D11: =SUM(G11+I11+K11) -> 425 | E11: =B10+D11 -> 1118854 | F11: =F10 -> 161410 | G11: =F11-F10 -> 0 | H11: 556006 | I11: =H11-H10 -> 424 | J11: 401438 | K11: =J11-J10 -> 1 | L11: =SUM(G11*$Y$28)/1507.5 -> 0 | M11: =SUM(I11*$Y$27)/1507.5 -> 31.501161 | N11: =SUM(K11*$Y$26)/1507.5 -> 0.053067993 | O11: =($AC$29/$A$37)/1507.5 -> 154.80304 | P11: =SUM(L11:O11) -> 186.35727 | Q11: =SUM(-tanks!AX13*tanks!$AU$37) -> -668.395 | R11: =SUM(P11:Q11) -> -482.03773 | S11: =SUM(ELEC!N11) -> 3135 | T11: =IF(S11>0,R11/S11,0) -> -0.15376004 | V11: ='[2]EDl log'!V28 -> 161410 | W11: ='[2]EDl log'!W28 -> 161410 | X11: ='[2]EDl log'!X28 -> Peak | Y11: ='[2]EDl log'!Y28 -> 320 | Z11: ='[2]EDl log'!Z28 -> 1 | AA11: ='[2]EDl log'!AA28 -> 0 | AB11: ='[2]EDl log'!AB28 -> 0 | AC11: ='[2]EDl log'!AC28 -> 1000 | ... AF11: ='[2]EDl log'!AF28 -> 0
A12: =ELEC!C12 -> 44690 | B12: 1119151 | C12: =SUM(B12-B11) -> 296 | D12: =SUM(G12+I12+K12) -> 297 | E12: =B11+D12 -> 1119152 | F12: =F11 -> 161410 | G12: =F12-F11 -> 0 | H12: 556210 | I12: =H12-H11 -> 204 | J12: 401531 | K12: =J12-J11 -> 93 | L12: =SUM(G12*$Y$28)/1507.5 -> 0 | M12: =SUM(I12*$Y$27)/1507.5 -> 15.156219 | N12: =SUM(K12*$Y$26)/1507.5 -> 4.9353234 | O12: =($AC$29/$A$37)/1507.5 -> 154.80304 | P12: =SUM(L12:O12) -> 174.89458 | Q12: =SUM(-tanks!AX14*tanks!$AU$37) -> 1221.395 | R12: =SUM(P12:Q12) -> 1396.2896 | S12: =SUM(ELEC!N12) -> 3445 | T12: =IF(S12>0,R12/S12,0) -> 0.40530902 | AA12: ='[2]EDl log'!AA29 -> 1750 | AB12: ='[2]EDl log'!AB29 -> 193120 | AC12: ='[2]EDl log'!AC29 -> 7234333
A13: =ELEC!C13 -> 44691 | B13: 1119189 | C13: =SUM(B13-B12) -> 38 | D13: =SUM(G13+I13+K13) -> 37 | E13: =B12+D13 -> 1119188 | F13: =F12 -> 161410 | G13: =F13-F12 -> 0 | H13: 556246 | I13: =H13-H12 -> 36 | J13: 401532 | K13: =J13-J12 -> 1 | L13: =SUM(G13*$Y$28)/1507.5 -> 0 | M13: =SUM(I13*$Y$27)/1507.5 -> 2.6746269 | N13: =SUM(K13*$Y$26)/1507.5 -> 0.053067993 | O13: =($AC$29/$A$37)/1507.5 -> 154.80304 | P13: =SUM(L13:O13) -> 157.53073 | Q13: =SUM(-tanks!AX15*tanks!$AU$37) -> 949.41 | R13: =SUM(P13:Q13) -> 1106.9407 | S13: =SUM(ELEC!N13) -> 3157 | T13: =IF(S13>0,R13/S13,0) -> 0.35063058 | V13: Occ % | W13: ='[2]EDl log'!W30 -> 0 | Y13: Per G | AB13: ='[2]EDl log'!AB30 -> 7427453 | AC13: ='[2]EDl log'!AC30 -> 0
A14: =ELEC!C14 -> 44692 | B14: 1119492 | C14: =SUM(B14-B13) -> 303 | D14: =SUM(G14+I14+K14) -> 304 | E14: =B13+D14 -> 1119493 | F14: =F13 -> 161410 | G14: =F14-F13 -> 0 | H14: 556460 | I14: =H14-H13 -> 214 | J14: 401622 | K14: =J14-J13 -> 90 | L14: =SUM(G14*$Y$28)/1507.5 -> 0 | M14: =SUM(I14*$Y$27)/1507.5 -> 15.899171 | N14: =SUM(K14*$Y$26)/1507.5 -> 4.7761194 | O14: =($AC$29/$A$37)/1507.5 -> 154.80304 | P14: =SUM(L14:O14) -> 175.47833 | Q14: =SUM(-tanks!AX16*tanks!$AU$37) -> 1122.66 | R14: =SUM(P14:Q14) -> 1298.1383 | S14: =SUM(ELEC!N14) -> 3105 | T14: =IF(S14>0,R14/S14,0) -> 0.41807998 | AB14: ='[2]EDl log'!AB31 -> 0 | AC14: ='[2]EDl log'!AC31 -> 0
A15: =ELEC!C15 -> 44693 | B15: 1119539 | C15: =SUM(B15-B14) -> 47 | D15: =SUM(G15+I15+K15) -> 46 | E15: =B14+D15 -> 1119538 | F15: =F14 -> 161410 | G15: =F15-F14 -> 0 | H15: 556506 | I15: =H15-H14 -> 46 | J15: 401622 | K15: =J15-J14 -> 0 | L15: =SUM(G15*$Y$28)/1507.5 -> 0 | M15: =SUM(I15*$Y$27)/1507.5 -> 3.4175788 | N15: =SUM(K15*$Y$26)/1507.5 -> 0 | O15: =($AC$29/$A$37)/1507.5 -> 154.80304 | P15: =SUM(L15:O15) -> 158.22062 | Q15: =SUM(-tanks!AX17*tanks!$AU$37) -> 1188.845 | R15: =SUM(P15:Q15) -> 1347.0656 | S15: =SUM(ELEC!N15) -> 2743 | T15: =IF(S15>0,R15/S15,0) -> 0.4910921 | V15: Gen RH | W15: ='[2]EDl log'!W32 -> 175 | X15: ='[2]EDl log'!X32 -> 29.166667 | Y15: ='[2]EDl log'!Y32 -> 29.166667 | AB15: ='[2]EDl log'!AB32 -> 0 | AC15: ='[2]EDl log'!AC32 -> 0
A16: =ELEC!C16 -> 44694 | B16: =B15 -> 1119539 | C16: =SUM(B16-B15) -> 0 | D16: =SUM(G16+I16+K16) -> 0 | E16: =B15+D16 -> 1119539 | F16: =F15 -> 161410 | G16: =F16-F15 -> 0 | H16: =H15 -> 556506 | I16: =H16-H15 -> 0 | J16: =J15 -> 401622 | K16: =J16-J15 -> 0 | L16: =SUM(G16*$Y$28)/1507.5 -> 0 | M16: =SUM(I16*$Y$27)/1507.5 -> 0 | N16: =SUM(K16*$Y$26)/1507.5 -> 0 | O16: =($AC$29/$A$37)/1507.5 -> 154.80304 | P16: =SUM(L16:O16) -> 154.80304 | Q16: =SUM(-tanks!AX18*tanks!$AU$37) -> 0 | R16: =SUM(P16:Q16) -> 154.80304 | S16: =SUM(ELEC!N16) -> 0 | T16: =IF(S16>0,R16/S16,0) -> 0 | V16: H Deg | Z16: VAT | AA16: ='[6]EDl log'!AA33 -> 0.11 | AB16: ='[2]EDl log'!AB33 -> 817019.83 | AC16: ='[2]EDl log'!AC33 -> 7234333
A17: =ELEC!C17 -> 44695 | B17: =B16 -> 1119539 | C17: =SUM(B17-B16) -> 0 | D17: =SUM(G17+I17+K17) -> 0 | E17: =B16+D17 -> 1119539 | F17: =F16 -> 161410 | G17: =F17-F16 -> 0 | H17: =H16 -> 556506 | I17: =H17-H16 -> 0 | J17: =J16 -> 401622 | K17: =J17-J16 -> 0 | L17: =SUM(G17*$Y$28)/1507.5 -> 0 | M17: =SUM(I17*$Y$27)/1507.5 -> 0 | N17: =SUM(K17*$Y$26)/1507.5 -> 0 | O17: =($AC$29/$A$37)/1507.5 -> 154.80304 | P17: =SUM(L17:O17) -> 154.80304 | Q17: =SUM(-tanks!AX19*tanks!$AU$37) -> 0 | R17: =SUM(P17:Q17) -> 154.80304 | S17: =SUM(ELEC!N17) -> 0 | T17: =IF(S17>0,R17/S17,0) -> 0 | V17: C Deg | AA17: ='[6]EDl log'!AA34 -> 0 | AB17: ='[2]EDl log'!AB34 -> 8244472.8 | AC17: ='[2]EDl log'!AC34 -> 0
A18: =ELEC!C18 -> 44696 | B18: =B17 -> 1119539 | C18: =SUM(B18-B17) -> 0 | D18: =SUM(G18+I18+K18) -> 0 | E18: =B17+D18 -> 1119539 | F18: =F17 -> 161410 | G18: =F18-F17 -> 0 | H18: =H17 -> 556506 | I18: =H18-H17 -> 0 | J18: =J17 -> 401622 | K18: =J18-J17 -> 0 | L18: =SUM(G18*$Y$28)/1507.5 -> 0 | M18: =SUM(I18*$Y$27)/1507.5 -> 0 | N18: =SUM(K18*$Y$26)/1507.5 -> 0 | O18: =($AC$29/$A$37)/1507.5 -> 154.80304 | P18: =SUM(L18:O18) -> 154.80304 | Q18: =SUM(-tanks!AX20*tanks!$AU$37) -> 0 | R18: =SUM(P18:Q18) -> 154.80304 | S18: =SUM(ELEC!N18) -> 0 | T18: =IF(S18>0,R18/S18,0) -> 0 | AA18: ='[6]EDl log'!AA35 -> 0 | AB18: ='[2]EDl log'!AB35 -> 0 | AC18: ='[2]EDl log'!AC35 -> 0
A19: =ELEC!C19 -> 44697 | B19: =B18 -> 1119539 | C19: =SUM(B19-B18) -> 0 | D19: =SUM(G19+I19+K19) -> 0 | E19: =B18+D19 -> 1119539 | F19: =F18 -> 161410 | G19: =F19-F18 -> 0 | H19: =H18 -> 556506 | I19: =H19-H18 -> 0 | J19: =J18 -> 401622 | K19: =J19-J18 -> 0 | L19: =SUM(G19*$Y$28)/1507.5 -> 0 | M19: =SUM(I19*$Y$27)/1507.5 -> 0 | N19: =SUM(K19*$Y$26)/1507.5 -> 0 | O19: =($AC$29/$A$37)/1507.5 -> 154.80304 | P19: =SUM(L19:O19) -> 154.80304 | Q19: =SUM(-tanks!AX21*tanks!$AU$37) -> 0 | R19: =SUM(P19:Q19) -> 154.80304 | S19: =SUM(ELEC!N19) -> 0 | T19: =IF(S19>0,R19/S19,0) -> 0 | AA19: ='[6]EDl log'!AA36 -> $ without VAT | AB19: ='[2]EDl log'!AB36 -> 4927.0003 | AC19: ='[2]EDl log'!AC36 -> 0
A20: =ELEC!C20 -> 44698 | B20: =B19 -> 1119539 | C20: =SUM(B20-B19) -> 0 | D20: =SUM(G20+I20+K20) -> 0 | E20: 160188 | F20: =F19 -> 161410 | G20: =F20-F19 -> 0 | H20: =H19 -> 556506 | I20: =H20-H19 -> 0 | J20: =J19 -> 401622 | K20: =J20-J19 -> 0 | L20: =SUM(G20*$Y$28)/1507.5 -> 0 | M20: =SUM(I20*$Y$27)/1507.5 -> 0 | N20: =SUM(K20*$Y$26)/1507.5 -> 0 | O20: =($AC$29/$A$37)/1507.5 -> 154.80304 | P20: =SUM(L20:O20) -> 154.80304 | Q20: =SUM(-tanks!AX22*tanks!$AU$37) -> 0 | R20: =SUM(P20:Q20) -> 154.80304 | S20: =SUM(ELEC!N20) -> 0 | T20: =IF(S20>0,R20/S20,0) -> 0
A21: =ELEC!C21 -> 44699 | B21: =B20 -> 1119539 | C21: =SUM(B21-B20) -> 0 | D21: =SUM(G21+I21+K21) -> 0 | E21: =B20+D21 -> 1119539 | F21: =F20 -> 161410 | G21: =F21-F20 -> 0 | H21: =H20 -> 556506 | I21: =H21-H20 -> 0 | J21: =J20 -> 401622 | K21: =J21-J20 -> 0 | L21: =SUM(G21*$Y$28)/1507.5 -> 0 | M21: =SUM(I21*$Y$27)/1507.5 -> 0 | N21: =SUM(K21*$Y$26)/1507.5 -> 0 | O21: =($AC$29/$A$37)/1507.5 -> 154.80304 | P21: =SUM(L21:O21) -> 154.80304 | Q21: =SUM(-tanks!AX23*tanks!$AU$37) -> 0 | R21: =SUM(P21:Q21) -> 154.80304 | S21: =SUM(ELEC!N21) -> 0 | T21: =IF(S21>0,R21/S21,0) -> 0 | V21: EDL | W21: 44703 | Z21: Subscription
