Workbook

Sheet Total
A1: Site Name | B1: Day | C1: Month | D1: Year | E1: Total Electricity Kwh | F1: Electricity Tariff ($/Kwh) | G1: Natual Gas (m3) | H1: Natural Gas $/m3 | I1: Water Utility Supply (m3) m3 | J1: Water Utility Supply (m3) $/m3 | K1: Room Nights
A2: Cairo at The First Residence | B2: 1 | C2: 1 | D2: 2021 | E2: 19809.19 | F2: 1.5 | G2: =1102.82+263.03 -> 1365.85 | H2: 3.89 | I2: 256.65 | J2: 10 | K2: 41
A3: Cairo at The First Residence | B3: =B2+1 -> 2 | C3: 1 | D3: 2021 | E3: 19809.19 | F3: =F2 -> 1.5 | G3: =1102.82+263.03 -> 1365.85 | H3: 3.89 | I3: 256.65 | J3: 10 | K3: 41
A4: Cairo at The First Residence | B4: =B3+1 -> 3 | C4: 1 | D4: 2021 | E4: 19809.19 | F4: =F3 -> 1.5 | G4: =1102.82+263.03 -> 1365.85 | H4: 3.89 | I4: 256.65 | J4: 10 | K4: 41
A5: Cairo at The First Residence | B5: =B4+1 -> 4 | C5: 1 | D5: 2021 | E5: 19809.19 | F5: =F4 -> 1.5 | G5: =1102.82+263.03 -> 1365.85 | H5: 3.89 | I5: 256.65 | J5: 10 | K5: 41
A6: Cairo at The First Residence | B6: =B5+1 -> 5 | C6: 1 | D6: 2021 | E6: 19809.19 | F6: =F5 -> 1.5 | G6: =1102.82+263.03 -> 1365.85 | H6: 3.89 | I6: 256.65 | J6: 10 | K6: 41
A7: Cairo at The First Residence | B7: =B6+1 -> 6 | C7: 1 | D7: 2021 | E7: 19809.19 | F7: =F6 -> 1.5 | G7: =1102.82+263.03 -> 1365.85 | H7: 3.89 | I7: 256.65 | J7: 10 | K7: 41
A8: Cairo at The First Residence | B8: =B7+1 -> 7 | C8: 1 | D8: 2021 | E8: 19809.19 | F8: =F7 -> 1.5 | G8: =1102.82+263.03 -> 1365.85 | H8: 3.89 | I8: 256.65 | J8: 10 | K8: 41
A9: Cairo at The First Residence | B9: =B8+1 -> 8 | C9: 1 | D9: 2021 | E9: 19809.19 | F9: =F8 -> 1.5 | G9: =1102.82+263.03 -> 1365.85 | H9: 3.89 | I9: 256.65 | J9: 10 | K9: 41
A10: Cairo at The First Residence | B10: =B9+1 -> 9 | C10: 1 | D10: 2021 | E10: 19809.19 | F10: =F9 -> 1.5 | G10: =1102.82+263.03 -> 1365.85 | H10: 3.89 | I10: 256.65 | J10: 10 | K10: 41
A11: Cairo at The First Residence | B11: =B10+1 -> 10 | C11: 1 | D11: 2021 | E11: 19809.19 | F11: =F10 -> 1.5 | G11: =1102.82+263.03 -> 1365.85 | H11: 3.89 | I11: 256.65 | J11: 10 | K11: 41
A12: Cairo at The First Residence | B12: =B11+1 -> 11 | C12: 1 | D12: 2021 | E12: 19809.19 | F12: =F11 -> 1.5 | G12: =1102.82+263.03 -> 1365.85 | H12: 3.89 | I12: 256.65 | J12: 10 | K12: 41
A13: Cairo at The First Residence | B13: =B12+1 -> 12 | C13: 1 | D13: 2021 | E13: 19809.19 | F13: =F12 -> 1.5 | G13: =1102.82+263.03 -> 1365.85 | H13: 3.89 | I13: 256.65 | J13: 10 | K13: 41
A14: Cairo at The First Residence | B14: =B13+1 -> 13 | C14: 1 | D14: 2021 | E14: 19809.19 | F14: =F13 -> 1.5 | G14: =1102.82+263.03 -> 1365.85 | H14: 3.89 | I14: 256.65 | J14: 10 | K14: 41
... A32: Cairo at The First Residence | B32: =B31+1 -> 31 | C32: 1 | D32: 2021 | E32: 19809.19 | F32: =F31 -> 1.5 | G32: =1102.82+263.03 -> 1365.85 | H32: 3.89 | I32: 256.65 | J32: 10 | K32: 42

Sheet Submetering
A1: Site Name | B1: Day | C1: Month | D1: Year | E1: Electricity | F1: Main Feeder -KWh | G1: T2+T8 -KWh | H1: La Gourmandize -KWh | I1: Casino 3rd floor EM -KWh | J1: Casino 3rd floor Normal -KWh | K1: Chiller 1 -KWh | L1: Chiller 2 -KWh | M1: Chiller 3 -KWh | N1: Chiller 4 -KWh | O1: Cooling towers -KWh | P1: Chiller Pumps -KWh | Q1: LG Bakery -KWh | R1: Mall Ceiling light -KWh | S1: New chiller for Second floor -KWh | T1: LG Bakery light ( Old lockers ) -KWh | U1: MCCR1 -KWh | V1: Children Swimming pool -KWh | W1: DPH1 -KWh | X1: Main G2 -KWh | Y1: Casino Emergency -KWh | Z1: L / A -KWh | AA1: L / B -KWh | AB1: L / C -KWh | AC1: Water | AD1: Main water meter 1 -m3 | AE1: Main water meter 2 -m3 | AF1: Main water meter 3 -m3 | AG1: Gas | AH1: Main Gas Flow Meter -m3 | AI1: Laundry Gas Flow Meter -m3 | AJ1: Gourmandize Gas Flow Meter -m3 | AK1: Room Nights
A2: Cairo at The First Residence | B2: 1 | C2: 1 | D2: 2021 | F2: =Elect!J6 -> 4287 | G2: =Elect!K6 -> 2822 | H2: =Elect!Q6 -> 540 | I2: =Elect!W6 -> 142 | J2: =Elect!Y6 -> 231 | K2: =Elect!AA6 -> 0 | L2: =Elect!AC6 -> 1736.28 | M2: =Elect!AE6 -> 706.49 | N2: =Elect!AG6 -> 0 | O2: =Elect!AI6 -> 305.81 | P2: =Elect!AK6 -> 1786.63 | Q2: =Elect!AN6 -> 378 | R2: =Elect!AP6 -> 262 | S2: =Elect!AR6 -> 9.57 | T2: =Elect!AT6 -> 59 | U2: =Elect!AV6 -> 613 | V2: =Elect!AX6 -> 66 | W2: =Elect!AZ6 -> 3967 | X2: =Elect!BB6 -> 3506.5 | Y2: =Elect!BE6 -> 358 | Z2: =Elect!BG6 -> 560 | AA2: =Elect!BI6 -> 111 | AB2: =Elect!BK6 -> 186 | AD2: =Water!C7 -> 0 | AE2: =Water!E7 -> 237.8 | AF2: =Water!G7 -> 7.54 | AH2: =Gas!C7 -> 894.64 | AI2: =Gas!E7 -> 375.2 | AJ2: =Gas!G7 -> 69 | AK2: 41
A3: Cairo at The First Residence | B3: =B2+1 -> 2 | C3: 1 | D3: 2021 | F3: =Elect!J7 -> 4841 | G3: =Elect!K7 -> 3098 | H3: =Elect!Q7 -> 510 | I3: =Elect!W7 -> 148 | J3: =Elect!Y7 -> 250 | K3: =Elect!AA7 -> 0 | L3: =Elect!AC7 -> 1426.76 | M3: =Elect!AE7 -> 4.77 | N3: =Elect!AG7 -> 0 | O3: =Elect!AI7 -> 264.47 | P3: =Elect!AK7 -> 1919.13 | Q3: =Elect!AN7 -> 935 | R3: =Elect!AP7 -> 217 | S3: =Elect!AR7 -> 13.31 | T3: =Elect!AT7 -> 42 | U3: =Elect!AV7 -> 606 | V3: =Elect!AX7 -> 67 | W3: =Elect!AZ7 -> 3652 | X3: =Elect!BB7 -> 4968 | Y3: =Elect!BE7 -> 358 | Z3: =Elect!BG7 -> 200 | AA3: =Elect!BI7 -> 50 | AB3: =Elect!BK7 -> 100 | AD3: =Water!C8 -> 0 | AE3: =Water!E8 -> 150.8 | AF3: =Water!G8 -> 12.18 | AH3: =Gas!C8 -> 1228.54 | AI3: =Gas!E8 -> 234.5 | AJ3: =Gas!G8 -> 64 | AK3: 41
A4: Cairo at The First Residence | B4: =B3+1 -> 3 | C4: 1 | D4: 2021 | F4: =Elect!J8 -> 4443 | G4: =Elect!K8 -> 2802 | H4: =Elect!Q8 -> 540 | I4: =Elect!W8 -> 139 | J4: =Elect!Y8 -> 233 | K4: =Elect!AA8 -> 0 | L4: =Elect!AC8 -> 2759.18 | M4: =Elect!AE8 -> 0 | N4: =Elect!AG8 -> 0 | O4: =Elect!AI8 -> 235.85 | P4: =Elect!AK8 -> 2025.66 | Q4: =Elect!AN8 -> 838 | R4: =Elect!AP8 -> 278 | S4: =Elect!AR8 -> 13.86 | T4: =Elect!AT8 -> 42 | U4: =Elect!AV8 -> 485 | V4: =Elect!AX8 -> 64 | W4: =Elect!AZ8 -> 3547 | X4: =Elect!BB8 -> 4254.1 | Y4: =Elect!BE8 -> 358 | Z4: =Elect!BG8 -> 679 | AA4: =Elect!BI8 -> 61 | AB4: =Elect!BK8 -> 91 | AD4: =Water!C9 -> 5.8 | AE4: =Water!E9 -> 185.6 | AF4: =Water!G9 -> 10.44 | AH4: =Gas!C9 -> 1025.02 | AI4: =Gas!E9 -> 297.5 | AJ4: =Gas!G9 -> 67 | AK4: 41
A5: Cairo at The First Residence | B5: =B4+1 -> 4 | C5: 1 | D5: 2021 | F5: =Elect!J9 -> 4708 | G5: =Elect!K9 -> 3174 | H5: =Elect!Q9 -> 570 | I5: =Elect!W9 -> 155 | J5: =Elect!Y9 -> 262 | K5: =Elect!AA9 -> 0 | L5: =Elect!AC9 -> 1894.22 | M5: =Elect!AE9 -> 0 | N5: =Elect!AG9 -> 0 | O5: =Elect!AI9 -> 212.53 | P5: =Elect!AK9 -> 1886.27 | Q5: =Elect!AN9 -> 1131 | R5: =Elect!AP9 -> 275 | S5: =Elect!AR9 -> 15.4 | T5: =Elect!AT9 -> 50 | U5: =Elect!AV9 -> 582 | V5: =Elect!AX9 -> 68 | W5: =Elect!AZ9 -> 4103 | X5: =Elect!BB9 -> 4703.4 | Y5: =Elect!BE9 -> 358 | Z5: =Elect!BG9 -> 946 | AA5: =Elect!BI9 -> 120 | AB5: =Elect!BK9 -> 225 | AD5: =Water!C10 -> 0 | AE5: =Water!E10 -> 174 | AF5: =Water!G10 -> 4.64 | AH5: =Gas!C10 -> 700.66 | AI5: =Gas!E10 -> 228.2 | AJ5: =Gas!G10 -> 71 | AK5: 41
A6: Cairo at The First Residence | B6: =B5+1 -> 5 | C6: 1 | D6: 2021 | F6: =Elect!J10 -> 4642 | G6: =Elect!K10 -> 2700 | H6: =Elect!Q10 -> 540 | I6: =Elect!W10 -> 144 | J6: =Elect!Y10 -> 247 | K6: =Elect!AA10 -> 0 | L6: =Elect!AC10 -> 1632.93 | M6: =Elect!AE10 -> 229.49 | N6: =Elect!AG10 -> 0 | O6: =Elect!AI10 -> 297.86 | P6: =Elect!AK10 -> 1744.23 | Q6: =Elect!AN10 -> 1209 | R6: =Elect!AP10 -> 279 | S6: =Elect!AR10 -> 14.41 | T6: =Elect!AT10 -> 37 | U6: =Elect!AV10 -> 498 | V6: =Elect!AX10 -> 67 | W6: =Elect!AZ10 -> 3339 | X6: =Elect!BB10 -> 4735.6 | Y6: =Elect!BE10 -> 358 | Z6: =Elect!BG10 -> 949 | AA6: =Elect!BI10 -> 114 | AB6: =Elect!BK10 -> 229 | AD6: =Water!C11 -> 0 | AE6: =Water!E11 -> 232 | AF6: =Water!G11 -> 8.7 | AH6: =Gas!C11 -> 1176.6 | AI6: =Gas!E11 -> 284.2 | AJ6: =Gas!G11 -> 82 | AK6: 41
A7: Cairo at The First Residence | B7: =B6+1 -> 6 | C7: 1 | D7: 2021 | F7: =Elect!J11 -> 5488 | G7: =Elect!K11 -> 2856 | H7: =Elect!Q11 -> 660 | I7: =Elect!W11 -> 176 | J7: =Elect!Y11 -> 247 | K7: =Elect!AA11 -> 0 | L7: =Elect!AC11 -> 0 | M7: =Elect!AE11 -> 1870.37 | N7: =Elect!AG11 -> 0 | O7: =Elect!AI11 -> 307.4 | P7: =Elect!AK11 -> 1781.86 | Q7: =Elect!AN11 -> 1333 | R7: =Elect!AP11 -> 295 | S7: =Elect!AR11 -> 14.74 | T7: =Elect!AT11 -> 39 | U7: =Elect!AV11 -> 510 | V7: =Elect!AX11 -> 84 | W7: =Elect!AZ11 -> 3744 | X7: =Elect!BB11 -> 4311.3 | Y7: =Elect!BE11 -> 358 | Z7: =Elect!BG11 -> 857 | AA7: =Elect!BI11 -> 97 | AB7: =Elect!BK11 -> 210 | AD7: =Water!C12 -> 5.8 | AE7: =Water!E12 -> 156.6 | AF7: =Water!G12 -> 6.96 | AH7: =Gas!C12 -> 982.62 | AI7: =Gas!E12 -> 289.1 | AJ7: =Gas!G12 -> 61 | AK7: 41
A8: Cairo at The First Residence | B8: =B7+1 -> 7 | C8: 1 | D8: 2021 | F8: =Elect!J12 -> 4353 | G8: =Elect!K12 -> 3602 | H8: =Elect!Q12 -> 570 | I8: =Elect!W12 -> 146 | J8: =Elect!Y12 -> 274 | K8: =Elect!AA12 -> 0 | L8: =Elect!AC12 -> 0 | M8: =Elect!AE12 -> 3138.13 | N8: =Elect!AG12 -> 0 | O8: =Elect!AI12 -> 328.07 | P8: =Elect!AK12 -> 2531.81 | Q8: =Elect!AN12 -> 1170 | R8: =Elect!AP12 -> 235 | S8: =Elect!AR12 -> 14.63 | T8: =Elect!AT12 -> 39 | U8: =Elect!AV12 -> 598 | V8: =Elect!AX12 -> 65 | W8: =Elect!AZ12 -> 4097 | X8: =Elect!BB12 -> 4360.1 | Y8: =Elect!BE12 -> 358 | Z8: =Elect!BG12 -> 874 | AA8: =Elect!BI12 -> 89 | AB8: =Elect!BK12 -> 199 | AD8: =Water!C13 -> 0 | AE8: =Water!E13 -> 232 | AF8: =Water!G13 -> 6.96 | AH8: =Gas!C13 -> 915.84 | AI8: =Gas!E13 -> 235.2 | AJ8: =Gas!G13 -> 54 | AK8: 41
A9: Cairo at The First Residence | B9: =B8+1 -> 8 | C9: 1 | D9: 2021 | F9: =Elect!J13 -> 4426 | G9: =Elect!K13 -> 2785 | H9: =Elect!Q13 -> 450 | I9: =Elect!W13 -> 116 | J9: =Elect!Y13 -> 225 | K9: =Elect!AA13 -> 0 | L9: =Elect!AC13 -> 0 | M9: =Elect!AE13 -> 2217.52 | N9: =Elect!AG13 -> 0 | O9: =Elect!AI13 -> 295.74 | P9: =Elect!AK13 -> 1919.66 | Q9: =Elect!AN13 -> 886 | R9: =Elect!AP13 -> 344 | S9: =Elect!AR13 -> 14.63 | T9: =Elect!AT13 -> 21 | U9: =Elect!AV13 -> 452 | V9: =Elect!AX13 -> 53 | W9: =Elect!AZ13 -> 3383 | X9: =Elect!BB13 -> 4241.5 | Y9: =Elect!BE13 -> 358 | Z9: =Elect!BG13 -> 870 | AA9: =Elect!BI13 -> 93 | AB9: =Elect!BK13 -> 193 | AD9: =Water!C14 -> 0 | AE9: =Water!E14 -> 185.6 | AF9: =Water!G14 -> 6.38 | AH9: =Gas!C14 -> 743.06 | AI9: =Gas!E14 -> 249.9 | AJ9: =Gas!G14 -> 76 | AK9: 41
A10: Cairo at The First Residence | B10: =B9+1 -> 9 | C10: 1 | D10: 2021 | F10: =Elect!J14 -> 4074 | G10: =Elect!K14 -> 2602 | H10: =Elect!Q14 -> 510 | I10: =Elect!W14 -> 152 | J10: =Elect!Y14 -> 263 | K10: =Elect!AA14 -> 0 | L10: =Elect!AC14 -> 0 | M10: =Elect!AE14 -> 0 | N10: =Elect!AG14 -> 1514.74 | O10: =Elect!AI14 -> 156.88 | P10: =Elect!AK14 -> 1643 | Q10: =Elect!AN14 -> 1139 | R10: =Elect!AP14 -> 289 | S10: =Elect!AR14 -> 13.53 | T10: =Elect!AT14 -> 21 | U10: =Elect!AV14 -> 424 | V10: =Elect!AX14 -> 70 | W10: =Elect!AZ14 -> 3798 | X10: =Elect!BB14 -> 3776.6 | Y10: =Elect!BE14 -> 358 | Z10: =Elect!BG14 -> 809 | AA10: =Elect!BI14 -> 110 | AB10: =Elect!BK14 -> 176 | AD10: =Water!C15 -> 0 | AE10: =Water!E15 -> 307.4 | AF10: =Water!G15 -> 10.44 | AH10: =Gas!C15 -> 854.36 | AI10: =Gas!E15 -> 290.5 | AJ10: =Gas!G15 -> 67 | AK10: 41
A11: Cairo at The First Residence | B11: =B10+1 -> 10 | C11: 1 | D11: 2021 | F11: =Elect!J15 -> 5552 | G11: =Elect!K15 -> 2812 | H11: =Elect!Q15 -> 540 | I11: =Elect!W15 -> 135 | J11: =Elect!Y15 -> 236 | K11: =Elect!AA15 -> 0 | L11: =Elect!AC15 -> 0 | M11: =Elect!AE15 -> 0 | N11: =Elect!AG15 -> 2221.23 | O11: =Elect!AI15 -> 209.88 | P11: =Elect!AK15 -> 1989.09 | Q11: =Elect!AN15 -> 1067 | R11: =Elect!AP15 -> 275 | S11: =Elect!AR15 -> 15.18 | T11: =Elect!AT15 -> 38 | U11: =Elect!AV15 -> 447 | V11: =Elect!AX15 -> 62 | W11: =Elect!AZ15 -> 2855 | X11: =Elect!BB15 -> 4956 | Y11: =Elect!BE15 -> 358 | Z11: =Elect!BG15 -> 1065 | AA11: =Elect!BI15 -> 138 | AB11: =Elect!BK15 -> 226 | AD11: =Water!C16 -> 5.8 | AE11: =Water!E16 -> 307.4 | AF11: =Water!G16 -> 8.12 | AH11: =Gas!C16 -> 1020.78 | AI11: =Gas!E16 -> 314.3 | AJ11: =Gas!G16 -> 102 | AK11: 41
A12: Cairo at The First Residence | B12: =B11+1 -> 11 | C12: 1 | D12: 2021 | F12: =Elect!J16 -> 2990 | G12: =Elect!K16 -> 2698 | H12: =Elect!Q16 -> 540 | I12: =Elect!W16 -> 135 | J12: =Elect!Y16 -> 234 | K12: =Elect!AA16 -> 0 | L12: =Elect!AC16 -> 0 | M12: =Elect!AE16 -> 0 | N12: =Elect!AG16 -> 2017.18 | O12: =Elect!AI16 -> 172.78 | P12: =Elect!AK16 -> 1856.59 | Q12: =Elect!AN16 -> 1063 | R12: =Elect!AP16 -> 275 | S12: =Elect!AR16 -> 10.89 | T12: =Elect!AT16 -> 38 | U12: =Elect!AV16 -> 472 | V12: =Elect!AX16 -> 35 | W12: =Elect!AZ16 -> 3367 | X12: =Elect!BB16 -> 3231.7 | Y12: =Elect!BE16 -> 358 | Z12: =Elect!BG16 -> 678 | AA12: =Elect!BI16 -> 87 | AB12: =Elect!BK16 -> 148 | AD12: =Water!C17 -> 0 | AE12: =Water!E17 -> 284.2 | AF12: =Water!G17 -> 6.38 | AH12: =Gas!C17 -> 915.84 | AI12: =Gas!E17 -> 232.4 | AJ12: =Gas!G17 -> 50 | AK12: 41
A13: Cairo at The First Residence | B13: =B12+1 -> 12 | C13: 1 | D13: 2021 | F13: =Elect!J17 -> 4437 | G13: =Elect!K17 -> 2787 | H13: =Elect!Q17 -> 600 | I13: =Elect!W17 -> 152 | J13: =Elect!Y17 -> 263 | K13: =Elect!AA17 -> 0 | L13: =Elect!AC17 -> 0 | M13: =Elect!AE17 -> 0 | N13: =Elect!AG17 -> 2237.13 | O13: =Elect!AI17 -> 208.82 | P13: =Elect!AK17 -> 2083.96 | Q13: =Elect!AN17 -> 1032 | R13: =Elect!AP17 -> 297 | S13: =Elect!AR17 -> 14.85 | T13: =Elect!AT17 -> 44 | U13: =Elect!AV17 -> 505 | V13: =Elect!AX17 -> 17 | W13: =Elect!AZ17 -> 3794 | X13: =Elect!BB17 -> 4736.4 | Y13: =Elect!BE17 -> 358 | Z13: =Elect!BG17 -> 956 | AA13: =Elect!BI17 -> 112 | AB13: =Elect!BK17 -> 211 | AD13: =Water!C18 -> 0 | AE13: =Water!E18 -> 237.8 | AF13: =Water!G18 -> 6.96 | AH13: =Gas!C18 -> 963.54 | AI13: =Gas!E18 -> 209.3 | AJ13: =Gas!G18 -> 80 | AK13: 41
A14: Cairo at The First Residence | B14: =B13+1 -> 13 | C14: 1 | D14: 2021 | F14: =Elect!J18 -> 3726 | G14: =Elect!K18 -> 2485 | H14: =Elect!Q18 -> 480 | I14: =Elect!W18 -> 118 | J14: =Elect!Y18 -> 211 | K14: =Elect!AA18 -> 0 | L14: =Elect!AC18 -> 1437.36 | M14: =Elect!AE18 -> 0 | N14: =Elect!AG18 -> 353.51 | O14: =Elect!AI18 -> 151.58 | P14: =Elect!AK18 -> 1656.25 | Q14: =Elect!AN18 -> 1150 | R14: =Elect!AP18 -> 268 | S14: =Elect!AR18 -> 12.76 | T14: =Elect!AT18 -> 35 | U14: =Elect!AV18 -> 428 | V14: =Elect!AX18 -> 35 | W14: =Elect!AZ18 -> 3082 | X14: =Elect!BB18 -> 3811.4 | Y14: =Elect!BE18 -> 358 | Z14: =Elect!BG18 -> 776 | AA14: =Elect!BI18 -> 84 | AB14: =Elect!BK18 -> 173 | AD14: =Water!C19 -> 5.8 | AE14: =Water!E19 -> 214.6 | AF14: =Water!G19 -> 6.96 | AH14: =Gas!C19 -> 962.48 | AI14: =Gas!E19 -> 179.2 | AJ14: =Gas!G19 -> 71 | AK14: 41
... A32: Cairo at The First Residence | B32: =B31+1 -> 31 | C32: 1 | D32: 2021 | F32: =Elect!J36 -> 4562 | G32: =Elect!K36 -> 2818 | H32: =Elect!Q36 -> 570 | I32: =Elect!W36 -> 144 | J32: =Elect!Y36 -> 243 | K32: =Elect!AA36 -> 0 | L32: =Elect!AC36 -> 1307.51 | M32: =Elect!AE36 -> 0 | N32: =Elect!AG36 -> 0 | O32: =Elect!AI36 -> 160.06 | P32: =Elect!AK36 -> 1604.31 | Q32: =Elect!AN36 -> 679 | R32: =Elect!AP36 -> 284 | S32: =Elect!AR36 -> 12.65 | T32: =Elect!AT36 -> 29 | U32: =Elect!AV36 -> 424 | V32: =Elect!AX36 -> 61 | W32: =Elect!AZ36 -> 3432 | X32: =Elect!BB36 -> 3383 | Y32: =Elect!BE36 -> 351 | Z32: =Elect!BG36 -> 871 | AA32: =Elect!BI36 -> 114 | AB32: =Elect!BK36 -> 201 | AD32: =Water!C37 -> 0 | AE32: =Water!E37 -> 208.8 | AF32: =Water!G37 -> 0 | AH32: =Gas!C37 -> 1490.36 | AI32: =Gas!E37 -> 202.3 | AJ32: =Gas!G37 -> 41 | AK32: 42

Sheet Elect
A1: January | M1: Electricity | BL1: Power Taxes | BM1: 0.0006 | BN1: Max Demand | BP1: 500 | BQ1: Electricity UP | BS1: 0.46
AL2: =SUM(AL22:AL36) -> 46363.34 | BC2: =SUM(BC22:BC36) -> 135013.66 | BL2: Light Taxes | BM2: 0.03 | BN2: PF Penalty | BQ2: Max. Demand UP | BS2: 30
A3: Date | B3: COUNTER (1) | D3: MD | F3: KVAR | H3: n | I3: Guest Rooms Consumption | R3: Casino Consumption | AD3: Plant Room Shared Loads | AW3: To Be Charged By First Arabian | BG3: From Main Panel G2 | BL3: Total Consumption. | BM3: No. Of | BN3: KWH/ | BO3: No. Of | BP3: KWH/ | BQ3: Total Cost | BR3: L.E\ | BS3: L.E\
B4: Reading | C4: Consp. F: *800 | D4: Reading | E4: Consp F: 80 | F4: Reading | G4: Consp. F:*10 | I4: Main Feeder | J4: Consp | K4: T2+T8 | L4: Trans T2 | M4: Consp | N4: Trans T8 | O4: Consp | P4: La Gourmandize | Q4: Consp *30 | R4: Casino 1 | S4: Consp | T4: Casino 2 | U4: Consp | V4: Casino 3rd floor EM | W4: Consp | X4: Casino 3rd floor Normal | Y4: Consp | Z4: Chiller 1 | AA4: Consp 53% | AB4: Chiller 2 | AC4: Consp 53% | AD4: Chiller 3 | AE4: Consp 53% | AF4: Chiller 4 | AG4: Consp 53% | AH4: Cooling towers | AI4: Consp 53% | AJ4: Chiller Pumps | AK4: Consp 53% | AL4: Total Plant Room Consp | AM4: LG Emergency (N24) | AN4: Consp | AO4: Mall Ceiling light | AP4: Consp | AQ4: New chiller for Second floor | AR4: Consp | AS4: LG Bakery light ( Old lockers ) | AT4: Consp | AU4: MCCR1 | AV4: Consp | AW4: Children Swimming pool | AX4: Consp | AY4: DPH1 | AZ4: Consp | BA4: Main G2 | BB4: Consp | BC4: Total Consp From First Arabian | BD4: Casino Emergency | BE4: Consp | BF4: L / A | BG4: Consp | BH4: L / B | BI4: Consp | BJ4: L / C | BK4: Consp | BM4: Rooms | BN4: room | BO4: guest | BP4: guest | BR4: Room | BS4: Guest
A5: Last Month Reading | I5: 21912456 | J5: =IF(I5>=I4,I5-I4,0) -> 0 | K5: =M5+O5 -> 0 | L5: 963064 | M5: =IF(L5>=L4,L5-L4,0) -> 0 | N5: 960763 | O5: =IF(N5>=N4,N5-N4,0) -> 0 | P5: 214160 | Q5: =IF(P5>=P4,P5-P4,0)*30 -> 0 | R5: 702925 | S5: =IF(R5>=R4,R5-R4,0) -> 0 | T5: 344001 | U5: =IF(T5>=T4,T5-T4,0) -> 0 | V5: 126502 | W5: =IF(V5>=V4,V5-V4,0) -> 0 | X5: 230746 | Y5: =IF(X5>=X4,X5-X4,0) -> 0 | Z5: 315108 | AA5: =IF(Z5>=Z4,Z5-Z4,0)*0.53 -> 0 | AB5: 329557 | AC5: =IF(AB5>=AB4,AB5-AB4,0)*0.53 -> 0 | AD5: 536016 | AE5: =IF(AD5>=AD4,AD5-AD4,0)*0.53 -> 0 | AF5: 289399 | AG5: =IF(AF5>=AF4,AF5-AF4,0)*0.53 -> 0 | AH5: 522364 | AI5: =IF(AH5>=AH4,AH5-AH4,0)*0.53 -> 0 | AJ5: 610356 | AK5: =IF(AJ5>=AJ4,AJ5-AJ4,0)*0.53 -> 0 | AL5: =AA5+AC5+AE5+AG5+AI5+AK5 -> 0 | AM5: 7188062 | AN5: =IF(AM5>=AM4,AM5-AM4,0) -> 0 | AO5: 565575 | AP5: =IF(AO5>=AO4,AO5-AO4,0) -> 0 | AQ5: 909729 | AR5: =IF(AQ5>=AQ4,AQ5-AQ4,0)*0.11 -> 0 | AS5: 793687 | AT5: =IF(AS5>=AS4,AS5-AS4,0) -> 0 | AU5: 2322338 | AV5: =IF(AU5>=AU4,AU5-AU4,0) -> 0 | AW5: 207611 | AX5: 0 | AY5: 17561805 | AZ5: =IF(AY5>=AY4,AY5-AY4,0) -> 0 | BA5: 21729015 | BB5: =IF(BA5>=BA4,BA5-BA4,0)-(0.6*BG5)-(0.5*BI5)-BK5-BE5 -> 0 | BC5: =AN5+AP5+AR5+AT5+AV5+AX5+AZ5+BB5 -> 0 | BD5: 1358289 | BE5: =IF(BD5>=BD4,BD5-BD4,0) -> 0 | BF5: 3465261 | BG5: =IF(BF5>=BF4,BF5-BF4,0) -> 0 | BH5: 369481 | BI5: =IF(BH5>=BH4,BH5-BH4,0) -> 0 | BJ5: 446214 | BK5: =IF(BJ5>=BJ4,BJ5-BJ4,0) -> 0
A6: 1 | C6: =IF(+B6-B5>0,B6-B5,(B6-B5)>0)*800 -> 0 | E6: =IF(+D6-D5>0,D6-D5,(D6-D5)>0)*80 -> 0 | G6: =IF(+F6-F5>0,F6-F5,(F6-F5)>0)*10 -> 0 | H6: 56 | I6: 21916743 | J6: =IF(I6>=I5,I6-I5,0) -> 4287 | K6: =M6+O6 -> 2822 | L6: 964445 | M6: =IF(L6>=L5,L6-L5,0) -> 1381 | N6: 962204 | O6: =IF(N6>=N5,N6-N5,0) -> 1441 | P6: 214178 | Q6: =IF(P6>=P5,P6-P5,0)*30 -> 540 | R6: 702925 | S6: =IF(R6>=R5,R6-R5,0) -> 0 | T6: 344001 | U6: =IF(T6>=T5,T6-T5,0) -> 0 | V6: 126644 | W6: =IF(V6>=V5,V6-V5,0) -> 142 | X6: 230977 | Y6: =IF(X6>=X5,X6-X5,0) -> 231 | Z6: 315108 | AA6: =IF(Z6>=Z5,Z6-Z5,0)*0.53 -> 0 | AB6: 332833 | AC6: =IF(AB6>=AB5,AB6-AB5,0)*0.53 -> 1736.28 | AD6: 537349 | AE6: =IF(AD6>=AD5,AD6-AD5,0)*0.53 -> 706.49 | AF6: 289399 | AG6: =IF(AF6>=AF5,AF6-AF5,0)*0.53 -> 0 | AH6: 522941 | AI6: =IF(AH6>=AH5,AH6-AH5,0)*0.53 -> 305.81 | AJ6: 613727 | AK6: =IF(AJ6>=AJ5,AJ6-AJ5,0)*0.53 -> 1786.63 | AL6: =AA6+AC6+AE6+AG6+AI6+AK6 -> 4535.21 | AM6: 7188440 | AN6: =IF(AM6>=AM5,AM6-AM5,0) -> 378 | AO6: 565837 | AP6: =IF(AO6>=AO5,AO6-AO5,0) -> 262 | AQ6: 909816 | AR6: =IF(AQ6>=AQ5,AQ6-AQ5,0)*0.11 -> 9.57 | AS6: 793746 | AT6: =IF(AS6>=AS5,AS6-AS5,0) -> 59 | AU6: 2322951 | AV6: =IF(AU6>=AU5,AU6-AU5,0) -> 613 | AW6: 207677 | AX6: =IF(AW6>=AW5,AW6-AW5,0) -> 66 | AY6: 17565772 | AZ6: =IF(AY6>=AY5,AY6-AY5,0) -> 3967 | BA6: 21733457 | BB6: =IF(BA6>=BA5,BA6-BA5,0)-(0.6*BG6)-(0.5*BI6)-BK6-BE6 -> 3506.5 | BC6: =AN6+AP6+AR6+AT6+AV6+AX6+AZ6+BB6 -> 8861.07 | BD6: 1358647 | BE6: =IF(BD6>=BD5,BD6-BD5,0) -> 358 | BF6: 3465821 | BG6: =IF(BF6>=BF5,BF6-BF5,0) -> 560 | BH6: 369592 | BI6: =IF(BH6>=BH5,BH6-BH5,0) -> 111 | BJ6: 446400 | BK6: =IF(BJ6>=BJ5,BJ6-BJ5,0) -> 186 | BL6: =J6+Q6+AL6+BC6 -> 18223.28 | BM6: 73 | BN6: =IF(BL6>0,BL6/#REF!,0) -> #REF! | BP6: =IF(BL6>0,BL6/BO6,0) -> #DIV/0! | BQ6: =BL6*BS1 -> 8382.7088 | BR6: =IF(BQ6>0,BQ6/#REF!,0) -> #REF! | BS6: =IF(BQ6>0,BQ6/BO6,0) -> #DIV/0!
A7: 2 | I7: 21921584 | J7: =IF(I7>=I6,I7-I6,0) -> 4841 | K7: =M7+O7 -> 3098 | L7: 965956 | M7: =IF(L7>=L6,L7-L6,0) -> 1511 | N7: 963791 | O7: =IF(N7>=N6,N7-N6,0) -> 1587 | P7: 214195 | Q7: =IF(P7>=P6,P7-P6,0)*30 -> 510 | R7: 702925 | S7: =IF(R7>=R6,R7-R6,0) -> 0 | T7: 344001 | U7: =IF(T7>=T6,T7-T6,0) -> 0 | V7: 126792 | W7: =IF(V7>=V6,V7-V6,0) -> 148 | X7: 231227 | Y7: =IF(X7>=X6,X7-X6,0) -> 250 | Z7: 315108 | AA7: =IF(Z7>=Z6,Z7-Z6,0)*0.53 -> 0 | AB7: 335525 | AC7: =IF(AB7>=AB6,AB7-AB6,0)*0.53 -> 1426.76 | AD7: 537358 | AE7: =IF(AD7>=AD6,AD7-AD6,0)*0.53 -> 4.77 | AF7: 289399 | AG7: =IF(AF7>=AF6,AF7-AF6,0)*0.53 -> 0 | AH7: 523440 | AI7: =IF(AH7>=AH6,AH7-AH6,0)*0.53 -> 264.47 | AJ7: 617348 | AK7: =IF(AJ7>=AJ6,AJ7-AJ6,0)*0.53 -> 1919.13 | AL7: =AA7+AC7+AE7+AG7+AI7+AK7 -> 3615.13 | AM7: 7189375 | AN7: =IF(AM7>=AM6,AM7-AM6,0) -> 935 | AO7: 566054 | AP7: =IF(AO7>=AO6,AO7-AO6,0) -> 217 | AQ7: 909937 | AR7: =IF(AQ7>=AQ6,AQ7-AQ6,0)*0.11 -> 13.31 | AS7: 793788 | AT7: =IF(AS7>=AS6,AS7-AS6,0) -> 42 | AU7: 2323557 | AV7: =IF(AU7>=AU6,AU7-AU6,0) -> 606 | AW7: 207744 | AX7: =IF(AW7>=AW6,AW7-AW6,0) -> 67 | AY7: 17569424 | AZ7: =IF(AY7>=AY6,AY7-AY6,0) -> 3652 | BA7: 21739028 | BB7: =IF(BA7>=BA6,BA7-BA6,0)-(0.6*BG7)-(0.5*BI7)-BK7-BE7 -> 4968 | BC7: =AN7+AP7+AR7+AT7+AV7+AX7+AZ7+BB7 -> 10500.31 | BD7: 1359005 | BE7: =IF(BD7>=BD6,BD7-BD6,0) -> 358 | BF7: 3466021 | BG7: =IF(BF7>=BF6,BF7-BF6,0) -> 200 | BH7: 369642 | BI7: =IF(BH7>=BH6,BH7-BH6,0) -> 50 | BJ7: 446500 | BK7: =IF(BJ7>=BJ6,BJ7-BJ6,0) -> 100 | BL7: =J7+Q7+AL7+BC7 -> 19466.44 | BM7: 54 | BN7: =IF(BL7>0,BL7/BM6,0) -> 266.66356 | BP7: =IF(BL7>0,BL7/BO7,0) -> #DIV/0! | BQ7: =BL7*BS1 -> 8954.5624 | BR7: =IF(BQ7>0,BQ7/BM6,0) -> 122.66524 | BS7: =IF(BQ7>0,BQ7/BO7,0) -> #DIV/0!
A8: 3 | C8: =IF(+B8-B7>0,B8-B7,(B8-B7)>0)*800 -> 0 | E8: =IF(+D8-D7>0,D8-D7,(D8-D7)>0)*80 -> 0 | G8: =IF(+F8-F7>0,F8-F7,(F8-F7)>0)*10 -> 0 | H8: 57 | I8: 21926027 | J8: =IF(I8>=I7,I8-I7,0) -> 4443 | K8: =M8+O8 -> 2802 | L8: 967261 | M8: =IF(L8>=L7,L8-L7,0) -> 1305 | N8: 965288 | O8: =IF(N8>=N7,N8-N7,0) -> 1497 | P8: 214213 | Q8: =IF(P8>=P7,P8-P7,0)*30 -> 540 | R8: 702925 | S8: =IF(R8>=R7,R8-R7,0) -> 0 | T8: 344001 | U8: =IF(T8>=T7,T8-T7,0) -> 0 | V8: 126931 | W8: =IF(V8>=V7,V8-V7,0) -> 139 | X8: 231460 | Y8: =IF(X8>=X7,X8-X7,0) -> 233 | Z8: 315108 | AA8: =IF(Z8>=Z7,Z8-Z7,0)*0.53 -> 0 | AB8: 340731 | AC8: =IF(AB8>=AB7,AB8-AB7,0)*0.53 -> 2759.18 | AD8: 537358 | AE8: =IF(AD8>=AD7,AD8-AD7,0)*0.53 -> 0 | AF8: 289399 | AG8: =IF(AF8>=AF7,AF8-AF7,0)*0.53 -> 0 | AH8: 523885 | AI8: =IF(AH8>=AH7,AH8-AH7,0)*0.53 -> 235.85 | AJ8: 621170 | AK8: =IF(AJ8>=AJ7,AJ8-AJ7,0)*0.53 -> 2025.66 | AL8: =AA8+AC8+AE8+AG8+AI8+AK8 -> 5020.69 | AM8: 7190213 | AN8: =IF(AM8>=AM7,AM8-AM7,0) -> 838 | AO8: 566332 | AP8: =IF(AO8>=AO7,AO8-AO7,0) -> 278 | AQ8: 910063 | AR8: =IF(AQ8>=AQ7,AQ8-AQ7,0)*0.11 -> 13.86 | AS8: 793830 | AT8: =IF(AS8>=AS7,AS8-AS7,0) -> 42 | AU8: 2324042 | AV8: =IF(AU8>=AU7,AU8-AU7,0) -> 485 | AW8: 207808 | AX8: =IF(AW8>=AW7,AW8-AW7,0) -> 64 | AY8: 17572971 | AZ8: =IF(AY8>=AY7,AY8-AY7,0) -> 3547 | BA8: 21744169 | BB8: =IF(BA8>=BA7,BA8-BA7,0)-(0.6*BG8)-(0.5*BI8)-BK8-BE8 -> 4254.1 | BC8: =AN8+AP8+AR8+AT8+AV8+AX8+AZ8+BB8 -> 9521.96 | BD8: 1359363 | BE8: =IF(BD8>=BD7,BD8-BD7,0) -> 358 | BF8: 3466700 | BG8: =IF(BF8>=BF7,BF8-BF7,0) -> 679 | BH8: 369703 | BI8: =IF(BH8>=BH7,BH8-BH7,0) -> 61 | BJ8: 446591 | BK8: =IF(BJ8>=BJ7,BJ8-BJ7,0) -> 91 | BL8: =J8+Q8+AL8+BC8 -> 19525.65 | BM8: 43 | BN8: =IF(BL8>0,BL8/BM7,0) -> 361.58611 | BP8: =IF(BL8>0,BL8/BO8,0) -> #DIV/0! | BQ8: =BL8*BS1 -> 8981.799 | BR8: =IF(BQ8>0,BQ8/BM7,0) -> 166.32961 | BS8: =IF(BQ8>0,BQ8/BO8,0) -> #DIV/0!
A9: 4 | C9: =IF(+B9-B8>0,B9-B8,(B9-B8)>0)*800 -> 0 | E9: =IF(+D9-D8>0,D9-D8,(D9-D8)>0)*80 -> 0 | G9: =IF(+F9-F8>0,F9-F8,(F9-F8)>0)*10 -> 0 | I9: 21930735 | J9: =IF(I9>=I8,I9-I8,0) -> 4708 | K9: =M9+O9 -> 3174 | L9: 968671 | M9: =IF(L9>=L8,L9-L8,0) -> 1410 | N9: 967052 | O9: =IF(N9>=N8,N9-N8,0) -> 1764 | P9: 214232 | Q9: =IF(P9>=P8,P9-P8,0)*30 -> 570 | R9: 702925 | S9: =IF(R9>=R8,R9-R8,0) -> 0 | T9: 344001 | U9: =IF(T9>=T8,T9-T8,0) -> 0 | V9: 127086 | W9: =IF(V9>=V8,V9-V8,0) -> 155 | X9: 231722 | Y9: =IF(X9>=X8,X9-X8,0) -> 262 | Z9: 315108 | AA9: =IF(Z9>=Z8,Z9-Z8,0)*0.53 -> 0 | AB9: 344305 | AC9: =IF(AB9>=AB8,AB9-AB8,0)*0.53 -> 1894.22 | AD9: 537358 | AE9: =IF(AD9>=AD8,AD9-AD8,0)*0.53 -> 0 | AF9: 289399 | AG9: =IF(AF9>=AF8,AF9-AF8,0)*0.53 -> 0 | AH9: 524286 | AI9: =IF(AH9>=AH8,AH9-AH8,0)*0.53 -> 212.53 | AJ9: 624729 | AK9: =IF(AJ9>=AJ8,AJ9-AJ8,0)*0.53 -> 1886.27 | AL9: =AA9+AC9+AE9+AG9+AI9+AK9 -> 3993.02 | AM9: 7191344 | AN9: =IF(AM9>=AM8,AM9-AM8,0) -> 1131 | AO9: 566607 | AP9: =IF(AO9>=AO8,AO9-AO8,0) -> 275 | AQ9: 910203 | AR9: =IF(AQ9>=AQ8,AQ9-AQ8,0)*0.11 -> 15.4 | AS9: 793880 | AT9: =IF(AS9>=AS8,AS9-AS8,0) -> 50 | AU9: 2324624 | AV9: =IF(AU9>=AU8,AU9-AU8,0) -> 582 | AW9: 207876 | AX9: =IF(AW9>=AW8,AW9-AW8,0) -> 68 | AY9: 17577074 | AZ9: =IF(AY9>=AY8,AY9-AY8,0) -> 4103 | BA9: 21750083 | BB9: =IF(BA9>=BA8,BA9-BA8,0)-(0.6*BG9)-(0.5*BI9)-BK9-BE9 -> 4703.4 | BC9: =AN9+AP9+AR9+AT9+AV9+AX9+AZ9+BB9 -> 10927.8 | BD9: 1359721 | BE9: =IF(BD9>=BD8,BD9-BD8,0) -> 358 | BF9: 3467646 | BG9: =IF(BF9>=BF8,BF9-BF8,0) -> 946 | BH9: 369823 | BI9: =IF(BH9>=BH8,BH9-BH8,0) -> 120 | BJ9: 446816 | BK9: =IF(BJ9>=BJ8,BJ9-BJ8,0) -> 225 | BL9: =J9+Q9+AL9+BC9 -> 20198.82 | BM9: 50 | BN9: =IF(BL9>0,BL9/BM8,0) -> 469.74 | BP9: =IF(BL9>0,BL9/BO9,0) -> #DIV/0! | BQ9: =BL9*BS1 -> 9291.4572 | BR9: =IF(BQ9>0,BQ9/BM8,0) -> 216.0804 | BS9: =IF(BQ9>0,BQ9/BO9,0) -> #DIV/0!
A10: 5 | C10: =IF(+B10-B9>0,B10-B9,(B10-B9)>0)*800 -> 0 | E10: =IF(+D10-D9>0,D10-D9,(D10-D9)>0)*80 -> 0 | G10: =IF(+F10-F9>0,F10-F9,(F10-F9)>0)*10 -> 0 | H10: 58 | I10: 21935377 | J10: =IF(I10>=I9,I10-I9,0) -> 4642 | K10: =M10+O10 -> 2700 | L10: 969846 | M10: =IF(L10>=L9,L10-L9,0) -> 1175 | N10: 968577 | O10: =IF(N10>=N9,N10-N9,0) -> 1525 | P10: 214250 | Q10: =IF(P10>=P9,P10-P9,0)*30 -> 540 | R10: 702925 | S10: =IF(R10>=R9,R10-R9,0) -> 0 | T10: 344001 | U10: =IF(T10>=T9,T10-T9,0) -> 0 | V10: 127230 | W10: =IF(V10>=V9,V10-V9,0) -> 144 | X10: 231969 | Y10: =IF(X10>=X9,X10-X9,0) -> 247 | Z10: 315108 | AA10: =IF(Z10>=Z9,Z10-Z9,0)*0.53 -> 0 | AB10: 347386 | AC10: =IF(AB10>=AB9,AB10-AB9,0)*0.53 -> 1632.93 | AD10: 537791 | AE10: =IF(AD10>=AD9,AD10-AD9,0)*0.53 -> 229.49 | AF10: 289399 | AG10: =IF(AF10>=AF9,AF10-AF9,0)*0.53 -> 0 | AH10: 524848 | AI10: =IF(AH10>=AH9,AH10-AH9,0)*0.53 -> 297.86 | AJ10: 628020 | AK10: =IF(AJ10>=AJ9,AJ10-AJ9,0)*0.53 -> 1744.23 | AL10: =AA10+AC10+AE10+AG10+AI10+AK10 -> 3904.51 | AM10: 7192553 | AN10: =IF(AM10>=AM9,AM10-AM9,0) -> 1209 | AO10: 566886 | AP10: =IF(AO10>=AO9,AO10-AO9,0) -> 279 | AQ10: 910334 | AR10: =IF(AQ10>=AQ9,AQ10-AQ9,0)*0.11 -> 14.41 | AS10: 793917 | AT10: =IF(AS10>=AS9,AS10-AS9,0) -> 37 | AU10: 2325122 | AV10: =IF(AU10>=AU9,AU10-AU9,0) -> 498 | AW10: 207943 | AX10: =IF(AW10>=AW9,AW10-AW9,0) -> 67 | AY10: 17580413 | AZ10: =IF(AY10>=AY9,AY10-AY9,0) -> 3339 | BA10: 21756032 | BB10: =IF(BA10>=BA9,BA10-BA9,0)-(0.6*BG10)-(0.5*BI10)-BK10-BE10 -> 4735.6 | BC10: =AN10+AP10+AR10+AT10+AV10+AX10+AZ10+BB10 -> 10179.01 | BD10: 1360079 | BE10: =IF(BD10>=BD9,BD10-BD9,0) -> 358 | BF10: 3468595 | BG10: =IF(BF10>=BF9,BF10-BF9,0) -> 949 | BH10: 369937 | BI10: =IF(BH10>=BH9,BH10-BH9,0) -> 114 | BJ10: 447045 | BK10: =IF(BJ10>=BJ9,BJ10-BJ9,0) -> 229 | BL10: =J10+Q10+AL10+BC10 -> 19265.52 | BM10: 53 | BN10: =IF(BL10>0,BL10/BM9,0) -> 385.3104 | BP10: =IF(BL10>0,BL10/BO10,0) -> #DIV/0! | BQ10: =BL10*BS1 -> 8862.1392 | BR10: =IF(BQ10>0,BQ10/BM9,0) -> 177.24278 | BS10: =IF(BQ10>0,BQ10/BO10,0) -> #DIV/0!
A11: 6 | C11: =IF(+B11-B10>0,B11-B10,(B11-B10)>0)*800 -> 0 | E11: =IF(+D11-D10>0,D11-D10,(D11-D10)>0)*80 -> 0 | G11: =IF(+F11-F10>0,F11-F10,(F11-F10)>0)*10 -> 0 | I11: 21940865 | J11: =IF(I11>=I10,I11-I10,0) -> 5488 | K11: =M11+O11 -> 2856 | L11: 971081 | M11: =IF(L11>=L10,L11-L10,0) -> 1235 | N11: 970198 | O11: =IF(N11>=N10,N11-N10,0) -> 1621 | P11: 214272 | Q11: =IF(P11>=P10,P11-P10,0)*30 -> 660 | R11: 702925 | S11: =IF(R11>=R10,R11-R10,0) -> 0 | T11: 344001 | U11: =IF(T11>=T10,T11-T10,0) -> 0 | V11: 127406 | W11: =IF(V11>=V10,V11-V10,0) -> 176 | X11: 232216 | Y11: =IF(X11>=X10,X11-X10,0) -> 247 | Z11: 315108 | AA11: =IF(Z11>=Z10,Z11-Z10,0)*0.53 -> 0 | AB11: 347386 | AC11: =IF(AB11>=AB10,AB11-AB10,0)*0.53 -> 0 | AD11: 541320 | AE11: =IF(AD11>=AD10,AD11-AD10,0)*0.53 -> 1870.37 | AF11: 289399 | AG11: =IF(AF11>=AF10,AF11-AF10,0)*0.53 -> 0 | AH11: 525428 | AI11: =IF(AH11>=AH10,AH11-AH10,0)*0.53 -> 307.4 | AJ11: 631382 | AK11: =IF(AJ11>=AJ10,AJ11-AJ10,0)*0.53 -> 1781.86 | AL11: =AA11+AC11+AE11+AG11+AI11+AK11 -> 3959.63 | AM11: 7193886 | AN11: =IF(AM11>=AM10,AM11-AM10,0) -> 1333 | AO11: 567181 | AP11: =IF(AO11>=AO10,AO11-AO10,0) -> 295 | AQ11: 910468 | AR11: =IF(AQ11>=AQ10,AQ11-AQ10,0)*0.11 -> 14.74 | AS11: 793956 | AT11: =IF(AS11>=AS10,AS11-AS10,0) -> 39 | AU11: 2325632 | AV11: =IF(AU11>=AU10,AU11-AU10,0) -> 510 | AW11: 208027 | AX11: =IF(AW11>=AW10,AW11-AW10,0) -> 84 | AY11: 17584157 | AZ11: =IF(AY11>=AY10,AY11-AY10,0) -> 3744 | BA11: 21761474 | BB11: =IF(BA11>=BA10,BA11-BA10,0)-(0.6*BG11)-(0.5*BI11)-BK11-BE11 -> 4311.3 | BC11: =AN11+AP11+AR11+AT11+AV11+AX11+AZ11+BB11 -> 10331.04 | BD11: 1360437 | BE11: =IF(BD11>=BD10,BD11-BD10,0) -> 358 | BF11: 3469452 | BG11: =IF(BF11>=BF10,BF11-BF10,0) -> 857 | BH11: 370034 | BI11: =IF(BH11>=BH10,BH11-BH10,0) -> 97 | BJ11: 447255 | BK11: =IF(BJ11>=BJ10,BJ11-BJ10,0) -> 210 | BL11: =J11+Q11+AL11+BC11 -> 20438.67 | BM11: 50 | BN11: =IF(BL11>0,BL11/BM10,0) -> 385.63528 | BP11: =IF(BL11>0,BL11/BO11,0) -> #DIV/0! | BQ11: =BL11*BS1 -> 9401.7882 | BR11: =IF(BQ11>0,BQ11/BM10,0) -> 177.39223 | BS11: =IF(BQ11>0,BQ11/BO11,0) -> #DIV/0!
A12: 7 | C12: =IF(+B12-B11>0,B12-B11,(B12-B11)>0)*800 -> 0 | E12: =IF(+D12-D11>0,D12-D11,(D12-D11)>0)*80 -> 0 | G12: =IF(+F12-F11>0,F12-F11,(F12-F11)>0)*10 -> 0 | H12: 59 | I12: 21945218 | J12: =IF(I12>=I11,I12-I11,0) -> 4353 | K12: =M12+O12 -> 3602 | L12: 972687 | M12: =IF(L12>=L11,L12-L11,0) -> 1606 | N12: 972194 | O12: =IF(N12>=N11,N12-N11,0) -> 1996 | P12: 214291 | Q12: =IF(P12>=P11,P12-P11,0)*30 -> 570 | R12: 702925 | S12: =IF(R12>=R11,R12-R11,0) -> 0 | T12: 344001 | U12: =IF(T12>=T11,T12-T11,0) -> 0 | V12: 127552 | W12: =IF(V12>=V11,V12-V11,0) -> 146 | X12: 232490 | Y12: =IF(X12>=X11,X12-X11,0) -> 274 | Z12: 315108 | AA12: =IF(Z12>=Z11,Z12-Z11,0)*0.53 -> 0 | AB12: 347386 | AC12: =IF(AB12>=AB11,AB12-AB11,0)*0.53 -> 0 | AD12: 547241 | AE12: =IF(AD12>=AD11,AD12-AD11,0)*0.53 -> 3138.13 | AF12: 289399 | AG12: =IF(AF12>=AF11,AF12-AF11,0)*0.53 -> 0 | AH12: 526047 | AI12: =IF(AH12>=AH11,AH12-AH11,0)*0.53 -> 328.07 | AJ12: 636159 | AK12: =IF(AJ12>=AJ11,AJ12-AJ11,0)*0.53 -> 2531.81 | AL12: =AA12+AC12+AE12+AG12+AI12+AK12 -> 5998.01 | AM12: 7195056 | AN12: =IF(AM12>=AM11,AM12-AM11,0) -> 1170 | AO12: 567416 | AP12: =IF(AO12>=AO11,AO12-AO11,0) -> 235 | AQ12: 910601 | AR12: =IF(AQ12>=AQ11,AQ12-AQ11,0)*0.11 -> 14.63 | AS12: 793995 | AT12: =IF(AS12>=AS11,AS12-AS11,0) -> 39 | AU12: 2326230 | AV12: =IF(AU12>=AU11,AU12-AU11,0) -> 598 | AW12: 208092 | AX12: =IF(AW12>=AW11,AW12-AW11,0) -> 65 | AY12: 17588254 | AZ12: =IF(AY12>=AY11,AY12-AY11,0) -> 4097 | BA12: 21766960 | BB12: =IF(BA12>=BA11,BA12-BA11,0)-(0.6*BG12)-(0.5*BI12)-BK12-BE12 -> 4360.1 | BC12: =AN12+AP12+AR12+AT12+AV12+AX12+AZ12+BB12 -> 10578.73 | BD12: 1360795 | BE12: =IF(BD12>=BD11,BD12-BD11,0) -> 358 | BF12: 3470326 | BG12: =IF(BF12>=BF11,BF12-BF11,0) -> 874 | BH12: 370123 | BI12: =IF(BH12>=BH11,BH12-BH11,0) -> 89 | BJ12: 447454 | BK12: =IF(BJ12>=BJ11,BJ12-BJ11,0) -> 199 | BL12: =J12+Q12+AL12+BC12 -> 21499.74 | BM12: 62 | BN12: =IF(BL12>0,BL12/BM11,0) -> 429.9948 | BP12: =IF(BL12>0,BL12/BO12,0) -> #DIV/0! | BQ12: =BL12*BS1 -> 9889.8804 | BR12: =IF(BQ12>0,BQ12/BM11,0) -> 197.79761 | BS12: =IF(BQ12>0,BQ12/BO12,0) -> #DIV/0!
A13: 8 | C13: =IF(+B13-B12>0,B13-B12,(B13-B12)>0)*800 -> 0 | E13: =IF(+D13-D12>0,D13-D12,(D13-D12)>0)*80 -> 0 | G13: =IF(+F13-F12>0,F13-F12,(F13-F12)>0)*10 -> 0 | I13: 21949644 | J13: =IF(I13>=I12,I13-I12,0) -> 4426 | K13: =M13+O13 -> 2785 | L13: 973956 | M13: =IF(L13>=L12,L13-L12,0) -> 1269 | N13: 973710 | O13: =IF(N13>=N12,N13-N12,0) -> 1516 | P13: 214306 | Q13: =IF(P13>=P12,P13-P12,0)*30 -> 450 | R13: 702925 | S13: =IF(R13>=R12,R13-R12,0) -> 0 | T13: 344001 | U13: =IF(T13>=T12,T13-T12,0) -> 0 | V13: 127668 | W13: =IF(V13>=V12,V13-V12,0) -> 116 | X13: 232715 | Y13: =IF(X13>=X12,X13-X12,0) -> 225 | Z13: 315108 | AA13: =IF(Z13>=Z12,Z13-Z12,0)*0.53 -> 0 | AB13: 347386 | AC13: =IF(AB13>=AB12,AB13-AB12,0)*0.53 -> 0 | AD13: 551425 | AE13: =IF(AD13>=AD12,AD13-AD12,0)*0.53 -> 2217.52 | AF13: 289399 | AG13: =IF(AF13>=AF12,AF13-AF12,0)*0.53 -> 0 | AH13: 526605 | AI13: =IF(AH13>=AH12,AH13-AH12,0)*0.53 -> 295.74 | AJ13: 639781 | AK13: =IF(AJ13>=AJ12,AJ13-AJ12,0)*0.53 -> 1919.66 | AL13: =AA13+AC13+AE13+AG13+AI13+AK13 -> 4432.92 | AM13: 7195942 | AN13: =IF(AM13>=AM12,AM13-AM12,0) -> 886 | AO13: 567760 | AP13: =IF(AO13>=AO12,AO13-AO12,0) -> 344 | AQ13: 910734 | AR13: =IF(AQ13>=AQ12,AQ13-AQ12,0)*0.11 -> 14.63 | AS13: 794016 | AT13: =IF(AS13>=AS12,AS13-AS12,0) -> 21 | AU13: 2326682 | AV13: =IF(AU13>=AU12,AU13-AU12,0) -> 452 | AW13: 208145 | AX13: =IF(AW13>=AW12,AW13-AW12,0) -> 53 | AY13: 17591637 | AZ13: =IF(AY13>=AY12,AY13-AY12,0) -> 3383 | BA13: 21772321 | BB13: =IF(BA13>=BA12,BA13-BA12,0)-(0.6*BG13)-(0.5*BI13)-BK13-BE13 -> 4241.5 | BC13: =AN13+AP13+AR13+AT13+AV13+AX13+AZ13+BB13 -> 9395.13 | BD13: 1361153 | BE13: =IF(BD13>=BD12,BD13-BD12,0) -> 358 | BF13: 3471196 | BG13: =IF(BF13>=BF12,BF13-BF12,0) -> 870 | BH13: 370216 | BI13: =IF(BH13>=BH12,BH13-BH12,0) -> 93 | BJ13: 447647 | BK13: =IF(BJ13>=BJ12,BJ13-BJ12,0) -> 193 | BL13: =J13+Q13+AL13+BC13 -> 18704.05 | BM13: 61 | BN13: =IF(BL13>0,BL13/BM12,0) -> 301.67823 | BP13: =IF(BL13>0,BL13/BO13,0) -> #DIV/0! | BQ13: =BL13*BS1 -> 8603.863 | BR13: =IF(BQ13>0,BQ13/BM12,0) -> 138.77198 | BS13: =IF(BQ13>0,BQ13/BO13,0) -> #DIV/0!
A14: 9 | C14: =IF(+B14-B13>0,B14-B13,(B14-B13)>0)*800 -> 0 | E14: =IF(+D14-D13>0,D14-D13,(D14-D13)>0)*80 -> 0 | G14: =IF(+F14-F13>0,F14-F13,(F14-F13)>0)*10 -> 0 | H14: 60 | I14: 21953718 | J14: =IF(I14>=I13,I14-I13,0) -> 4074 | K14: =M14+O14 -> 2602 | L14: 975164 | M14: =IF(L14>=L13,L14-L13,0) -> 1208 | N14: 975104 | O14: =IF(N14>=N13,N14-N13,0) -> 1394 | P14: 214323 | Q14: =IF(P14>=P13,P14-P13,0)*30 -> 510 | R14: 702925 | S14: =IF(R14>=R13,R14-R13,0) -> 0 | T14: 344001 | U14: =IF(T14>=T13,T14-T13,0) -> 0 | V14: 127820 | W14: =IF(V14>=V13,V14-V13,0) -> 152 | X14: 232978 | Y14: =IF(X14>=X13,X14-X13,0) -> 263 | Z14: 315108 | AA14: =IF(Z14>=Z13,Z14-Z13,0)*0.53 -> 0 | AB14: 347386 | AC14: =IF(AB14>=AB13,AB14-AB13,0)*0.53 -> 0 | AD14: 551425 | AE14: =IF(AD14>=AD13,AD14-AD13,0)*0.53 -> 0 | AF14: 292257 | AG14: =IF(AF14>=AF13,AF14-AF13,0)*0.53 -> 1514.74 | AH14: 526901 | AI14: =IF(AH14>=AH13,AH14-AH13,0)*0.53 -> 156.88 | AJ14: 642881 | AK14: =IF(AJ14>=AJ13,AJ14-AJ13,0)*0.53 -> 1643 | AL14: =AA14+AC14+AE14+AG14+AI14+AK14 -> 3314.62 | AM14: 7197081 | AN14: =IF(AM14>=AM13,AM14-AM13,0) -> 1139 | AO14: 568049 | AP14: =IF(AO14>=AO13,AO14-AO13,0) -> 289 | AQ14: 910857 | AR14: =IF(AQ14>=AQ13,AQ14-AQ13,0)*0.11 -> 13.53 | AS14: 794037 | AT14: =IF(AS14>=AS13,AS14-AS13,0) -> 21 | AU14: 2327106 | AV14: =IF(AU14>=AU13,AU14-AU13,0) -> 424 | AW14: 208215 | AX14: =IF(AW14>=AW13,AW14-AW13,0) -> 70 | AY14: 17595435 | AZ14: =IF(AY14>=AY13,AY14-AY13,0) -> 3798 | BA14: 21777172 | BB14: =IF(BA14>=BA13,BA14-BA13,0)-(0.6*BG14)-(0.5*BI14)-BK14-BE14 -> 3776.6 | BC14: =AN14+AP14+AR14+AT14+AV14+AX14+AZ14+BB14 -> 9531.13 | BD14: 1361511 | BE14: =IF(BD14>=BD13,BD14-BD13,0) -> 358 | BF14: 3472005 | BG14: =IF(BF14>=BF13,BF14-BF13,0) -> 809 | BH14: 370326 | BI14: =IF(BH14>=BH13,BH14-BH13,0) -> 110 | BJ14: 447823 | BK14: =IF(BJ14>=BJ13,BJ14-BJ13,0) -> 176 | BL14: =J14+Q14+AL14+BC14 -> 17429.75 | BM14: 59 | BN14: =IF(BL14>0,BL14/BM13,0) -> 285.73361 | BP14: =IF(BL14>0,BL14/BO14,0) -> #DIV/0! | BQ14: =BL14*BS1 -> 8017.685 | BR14: =IF(BQ14>0,BQ14/BM13,0) -> 131.43746 | BS14: =IF(BQ14>0,BQ14/BO14,0) -> #DIV/0!
A15: 10 | C15: =IF(+B15-B14>0,B15-B14,(B15-B14)>0)*800 -> 0 | E15: =IF(+D15-D14>0,D15-D14,(D15-D14)>0)*80 -> 0 | G15: =IF(+F15-F14>0,F15-F14,(F15-F14)>0)*10 -> 0 | I15: 21959270 | J15: =IF(I15>=I14,I15-I14,0) -> 5552 | K15: =M15+O15 -> 2812 | L15: 976482 | M15: =IF(L15>=L14,L15-L14,0) -> 1318 | N15: 976598 | O15: =IF(N15>=N14,N15-N14,0) -> 1494 | P15: 214341 | Q15: =IF(P15>=P14,P15-P14,0)*30 -> 540 | R15: 702925 | S15: =IF(R15>=R14,R15-R14,0) -> 0 | T15: 344001 | U15: =IF(T15>=T14,T15-T14,0) -> 0 | V15: 127955 | W15: =IF(V15>=V14,V15-V14,0) -> 135 | X15: 233214 | Y15: =IF(X15>=X14,X15-X14,0) -> 236 | Z15: 315108 | AA15: =IF(Z15>=Z14,Z15-Z14,0)*0.53 -> 0 | AB15: 347386 | AC15: =IF(AB15>=AB14,AB15-AB14,0)*0.53 -> 0 | AD15: 551425 | AE15: =IF(AD15>=AD14,AD15-AD14,0)*0.53 -> 0 | AF15: 296448 | AG15: =IF(AF15>=AF14,AF15-AF14,0)*0.53 -> 2221.23 | AH15: 527297 | AI15: =IF(AH15>=AH14,AH15-AH14,0)*0.53 -> 209.88 | AJ15: 646634 | AK15: =IF(AJ15>=AJ14,AJ15-AJ14,0)*0.53 -> 1989.09 | AL15: =AA15+AC15+AE15+AG15+AI15+AK15 -> 4420.2 | AM15: 7198148 | AN15: =IF(AM15>=AM14,AM15-AM14,0) -> 1067 | AO15: 568324 | AP15: =IF(AO15>=AO14,AO15-AO14,0) -> 275 | AQ15: 910995 | AR15: =IF(AQ15>=AQ14,AQ15-AQ14,0)*0.11 -> 15.18 | AS15: 794075 | AT15: =IF(AS15>=AS14,AS15-AS14,0) -> 38 | AU15: 2327553 | AV15: =IF(AU15>=AU14,AU15-AU14,0) -> 447 | AW15: 208277 | AX15: =IF(AW15>=AW14,AW15-AW14,0) -> 62 | AY15: 17598290 | AZ15: =IF(AY15>=AY14,AY15-AY14,0) -> 2855 | BA15: 21783420 | BB15: =IF(BA15>=BA14,BA15-BA14,0)-(0.6*BG15)-(0.5*BI15)-BK15-BE15 -> 4956 | BC15: =AN15+AP15+AR15+AT15+AV15+AX15+AZ15+BB15 -> 9715.18 | BD15: 1361869 | BE15: =IF(BD15>=BD14,BD15-BD14,0) -> 358 | BF15: 3473070 | BG15: =IF(BF15>=BF14,BF15-BF14,0) -> 1065 | BH15: 370464 | BI15: =IF(BH15>=BH14,BH15-BH14,0) -> 138 | BJ15: 448049 | BK15: =IF(BJ15>=BJ14,BJ15-BJ14,0) -> 226 | BL15: =J15+Q15+AL15+BC15 -> 20227.38 | BM15: 82 | BN15: =IF(BL15>0,BL15/BM14,0) -> 342.83695 | BP15: =IF(BL15>0,BL15/BO15,0) -> #DIV/0! | BQ15: =BL15*BS1 -> 9304.5948 | BR15: =IF(BQ15>0,BQ15/BM14,0) -> 157.705 | BS15: =IF(BQ15>0,BQ15/BO15,0) -> #DIV/0!
A16: 11 | C16: =IF(+B16-B15>0,B16-B15,(B16-B15)>0)*800 -> 0 | E16: =IF(+D16-D15>0,D16-D15,(D16-D15)>0)*80 -> 0 | G16: =IF(+F16-F15>0,F16-F15,(F16-F15)>0)*10 -> 0 | H16: 61 | I16: 21962260 | J16: =IF(I16>=I15,I16-I15,0) -> 2990 | K16: =M16+O16 -> 2698 | L16: 977727 | M16: =IF(L16>=L15,L16-L15,0) -> 1245 | N16: 978051 | O16: =IF(N16>=N15,N16-N15,0) -> 1453 | P16: 214359 | Q16: =IF(P16>=P15,P16-P15,0)*30 -> 540 | R16: 702925 | S16: =IF(R16>=R15,R16-R15,0) -> 0 | T16: 344001 | U16: =IF(T16>=T15,T16-T15,0) -> 0 | V16: 128090 | W16: =IF(V16>=V15,V16-V15,0) -> 135 | X16: 233448 | Y16: =IF(X16>=X15,X16-X15,0) -> 234 | Z16: 315108 | AA16: =IF(Z16>=Z15,Z16-Z15,0)*0.53 -> 0 | AB16: 347386 | AC16: =IF(AB16>=AB15,AB16-AB15,0)*0.53 -> 0 | AD16: 551425 | AE16: =IF(AD16>=AD15,AD16-AD15,0)*0.53 -> 0 | AF16: 300254 | AG16: =IF(AF16>=AF15,AF16-AF15,0)*0.53 -> 2017.18 | AH16: 527623 | AI16: =IF(AH16>=AH15,AH16-AH15,0)*0.53 -> 172.78 | AJ16: 650137 | AK16: =IF(AJ16>=AJ15,AJ16-AJ15,0)*0.53 -> 1856.59 | AL16: =AA16+AC16+AE16+AG16+AI16+AK16 -> 4046.55 | AM16: 7199211 | AN16: =IF(AM16>=AM15,AM16-AM15,0) -> 1063 | AO16: 568599 | AP16: =IF(AO16>=AO15,AO16-AO15,0) -> 275 | AQ16: 911094 | AR16: =IF(AQ16>=AQ15,AQ16-AQ15,0)*0.11 -> 10.89 | AS16: 794113 | AT16: =IF(AS16>=AS15,AS16-AS15,0) -> 38 | AU16: 2328025 | AV16: =IF(AU16>=AU15,AU16-AU15,0) -> 472 | AW16: 208312 | AX16: =IF(AW16>=AW15,AW16-AW15,0) -> 35 | AY16: 17601657 | AZ16: =IF(AY16>=AY15,AY16-AY15,0) -> 3367 | BA16: 21787608 | BB16: =IF(BA16>=BA15,BA16-BA15,0)-(0.6*BG16)-(0.5*BI16)-BK16-BE16 -> 3231.7 | BC16: =AN16+AP16+AR16+AT16+AV16+AX16+AZ16+BB16 -> 8492.59 | BD16: 1362227 | BE16: =IF(BD16>=BD15,BD16-BD15,0) -> 358 | BF16: 3473748 | BG16: =IF(BF16>=BF15,BF16-BF15,0) -> 678 | BH16: 370551 | BI16: =IF(BH16>=BH15,BH16-BH15,0) -> 87 | BJ16: 448197 | BK16: =IF(BJ16>=BJ15,BJ16-BJ15,0) -> 148 | BL16: =J16+Q16+AL16+BC16 -> 16069.14 | BM16: 35 | BN16: =IF(BL16>0,BL16/BM15,0) -> 195.96512 | BP16: =IF(BL16>0,BL16/BO16,0) -> #DIV/0! | BQ16: =BL16*BS1 -> 7391.8044 | BR16: =IF(BQ16>0,BQ16/BM15,0) -> 90.143956 | BS16: =IF(BQ16>0,BQ16/BO16,0) -> #DIV/0!
A17: 12 | C17: =IF(+B17-B16>0,B17-B16,(B17-B16)>0)*800 -> 0 | E17: =IF(+D17-D16>0,D17-D16,(D17-D16)>0)*80 -> 0 | G17: =IF(+F17-F16>0,F17-F16,(F17-F16)>0)*10 -> 0 | I17: 21966697 | J17: =IF(I17>=I16,I17-I16,0) -> 4437 | K17: =M17+O17 -> 2787 | L17: 978936 | M17: =IF(L17>=L16,L17-L16,0) -> 1209 | N17: 979629 | O17: =IF(N17>=N16,N17-N16,0) -> 1578 | P17: 214379 | Q17: =IF(P17>=P16,P17-P16,0)*30 -> 600 | R17: 702925 | S17: =IF(R17>=R16,R17-R16,0) -> 0 | T17: 344001 | U17: =IF(T17>=T16,T17-T16,0) -> 0 | V17: 128242 | W17: =IF(V17>=V16,V17-V16,0) -> 152 | X17: 233711 | Y17: =IF(X17>=X16,X17-X16,0) -> 263 | Z17: 315108 | AA17: =IF(Z17>=Z16,Z17-Z16,0)*0.53 -> 0 | AB17: 347386 | AC17: =IF(AB17>=AB16,AB17-AB16,0)*0.53 -> 0 | AD17: 551425 | AE17: =IF(AD17>=AD16,AD17-AD16,0)*0.53 -> 0 | AF17: 304475 | AG17: =IF(AF17>=AF16,AF17-AF16,0)*0.53 -> 2237.13 | AH17: 528017 | AI17: =IF(AH17>=AH16,AH17-AH16,0)*0.53 -> 208.82 | AJ17: 654069 | AK17: =IF(AJ17>=AJ16,AJ17-AJ16,0)*0.53 -> 2083.96 | AL17: =AA17+AC17+AE17+AG17+AI17+AK17 -> 4529.91 | AM17: 7200243 | AN17: =IF(AM17>=AM16,AM17-AM16,0) -> 1032 | AO17: 568896 | AP17: =IF(AO17>=AO16,AO17-AO16,0) -> 297 | AQ17: 911229 | AR17: =IF(AQ17>=AQ16,AQ17-AQ16,0)*0.11 -> 14.85 | AS17: 794157 | AT17: =IF(AS17>=AS16,AS17-AS16,0) -> 44 | AU17: 2328530 | AV17: =IF(AU17>=AU16,AU17-AU16,0) -> 505 | AW17: 208329 | AX17: =IF(AW17>=AW16,AW17-AW16,0) -> 17 | AY17: 17605451 | AZ17: =IF(AY17>=AY16,AY17-AY16,0) -> 3794 | BA17: 21793543 | BB17: =IF(BA17>=BA16,BA17-BA16,0)-(0.6*BG17)-(0.5*BI17)-BK17-BE17 -> 4736.4 | BC17: =AN17+AP17+AR17+AT17+AV17+AX17+AZ17+BB17 -> 10440.25 | BD17: 1362585 | BE17: =IF(BD17>=BD16,BD17-BD16,0) -> 358 | BF17: 3474704 | BG17: =IF(BF17>=BF16,BF17-BF16,0) -> 956 | BH17: 370663 | BI17: =IF(BH17>=BH16,BH17-BH16,0) -> 112 | BJ17: 448408 | BK17: =IF(BJ17>=BJ16,BJ17-BJ16,0) -> 211 | BL17: =J17+Q17+AL17+BC17 -> 20007.16 | BM17: 36 | BN17: =IF(BL17>0,BL17/BM16,0) -> 571.63314 | BP17: =IF(BL17>0,BL17/BO17,0) -> #DIV/0! | BQ17: =BL17*BS1 -> 9203.2936 | BR17: =IF(BQ17>0,BQ17/BM16,0) -> 262.95125 | BS17: =IF(BQ17>0,BQ17/BO17,0) -> #DIV/0!
A18: 13 | C18: =IF(+B18-B17>0,B18-B17,(B18-B17)>0)*800 -> 0 | E18: =IF(+D18-D17>0,D18-D17,(D18-D17)>0)*80 -> 0 | G18: =IF(+F18-F17>0,F18-F17,(F18-F17)>0)*10 -> 0 | H18: 62 | I18: 21970423 | J18: =IF(I18>=I17,I18-I17,0) -> 3726 | K18: =M18+O18 -> 2485 | L18: 979952 | M18: =IF(L18>=L17,L18-L17,0) -> 1016 | N18: 981098 | O18: =IF(N18>=N17,N18-N17,0) -> 1469 | P18: 214395 | Q18: =IF(P18>=P17,P18-P17,0)*30 -> 480 | R18: 702925 | S18: =IF(R18>=R17,R18-R17,0) -> 0 | T18: 344001 | U18: =IF(T18>=T17,T18-T17,0) -> 0 | V18: 128360 | W18: =IF(V18>=V17,V18-V17,0) -> 118 | X18: 233922 | Y18: =IF(X18>=X17,X18-X17,0) -> 211 | Z18: 315108 | AA18: =IF(Z18>=Z17,Z18-Z17,0)*0.53 -> 0 | AB18: 350098 | AC18: =IF(AB18>=AB17,AB18-AB17,0)*0.53 -> 1437.36 | AD18: 551425 | AE18: =IF(AD18>=AD17,AD18-AD17,0)*0.53 -> 0 | AF18: 305142 | AG18: =IF(AF18>=AF17,AF18-AF17,0)*0.53 -> 353.51 | AH18: 528303 | AI18: =IF(AH18>=AH17,AH18-AH17,0)*0.53 -> 151.58 | AJ18: 657194 | AK18: =IF(AJ18>=AJ17,AJ18-AJ17,0)*0.53 -> 1656.25 | AL18: =AA18+AC18+AE18+AG18+AI18+AK18 -> 3598.7 | AM18: 7201393 | AN18: =IF(AM18>=AM17,AM18-AM17,0) -> 1150 | AO18: 569164 | AP18: =IF(AO18>=AO17,AO18-AO17,0) -> 268 | AQ18: 911345 | AR18: =IF(AQ18>=AQ17,AQ18-AQ17,0)*0.11 -> 12.76 | AS18: 794192 | AT18: =IF(AS18>=AS17,AS18-AS17,0) -> 35 | AU18: 2328958 | AV18: =IF(AU18>=AU17,AU18-AU17,0) -> 428 | AW18: 208364 | AX18: =IF(AW18>=AW17,AW18-AW17,0) -> 35 | AY18: 17608533 | AZ18: =IF(AY18>=AY17,AY18-AY17,0) -> 3082 | BA18: 21798393 | BB18: =IF(BA18>=BA17,BA18-BA17,0)-(0.6*BG18)-(0.5*BI18)-BK18-BE18 -> 3811.4 | BC18: =AN18+AP18+AR18+AT18+AV18+AX18+AZ18+BB18 -> 8822.16 | BD18: 1362943 | BE18: =IF(BD18>=BD17,BD18-BD17,0) -> 358 | BF18: 3475480 | BG18: =IF(BF18>=BF17,BF18-BF17,0) -> 776 | BH18: 370747 | BI18: =IF(BH18>=BH17,BH18-BH17,0) -> 84 | BJ18: 448581 | BK18: =IF(BJ18>=BJ17,BJ18-BJ17,0) -> 173 | BL18: =J18+Q18+AL18+BC18 -> 16626.86 | BM18: 30 | BN18: =IF(BL18>0,BL18/BM17,0) -> 461.85722 | BP18: =IF(BL18>0,BL18/BO18,0) -> #DIV/0! | BQ18: =BL18*BS1 -> 7648.3556 | BR18: =IF(BQ18>0,BQ18/BM17,0) -> 212.45432 | BS18: =IF(BQ18>0,BQ18/BO18,0) -> #DIV/0!
A19: 14 | C19: =IF(+B19-B18>0,B19-B18,(B19-B18)>0)*800 -> 0 | E19: =IF(+D19-D18>0,D19-D18,(D19-D18)>0)*80 -> 0 | G19: =IF(+F19-F18>0,F19-F18,(F19-F18)>0)*10 -> 0 | I19: 21975104 | J19: =IF(I19>=I18,I19-I18,0) -> 4681 | K19: =M19+O19 -> 3188 | L19: 981379 | M19: =IF(L19>=L18,L19-L18,0) -> 1427 | N19: 982859 | O19: =IF(N19>=N18,N19-N18,0) -> 1761 | P19: 214418 | Q19: =IF(P19>=P18,P19-P18,0)*30 -> 690 | R19: 702925 | S19: =IF(R19>=R18,R19-R18,0) -> 0 | T19: 344001 | U19: =IF(T19>=T18,T19-T18,0) -> 0 | V19: 128526 | W19: =IF(V19>=V18,V19-V18,0) -> 166 | X19: 234186 | Y19: =IF(X19>=X18,X19-X18,0) -> 264 | Z19: 315108 | AA19: =IF(Z19>=Z18,Z19-Z18,0)*0.53 -> 0 | AB19: 354509 | AC19: =IF(AB19>=AB18,AB19-AB18,0)*0.53 -> 2337.83 | AD19: 551425 | AE19: =IF(AD19>=AD18,AD19-AD18,0)*0.53 -> 0 | AF19: 305142 | AG19: =IF(AF19>=AF18,AF19-AF18,0)*0.53 -> 0 | AH19: 528712 | AI19: =IF(AH19>=AH18,AH19-AH18,0)*0.53 -> 216.77 | AJ19: 661265 | AK19: =IF(AJ19>=AJ18,AJ19-AJ18,0)*0.53 -> 2157.63 | AL19: =AA19+AC19+AE19+AG19+AI19+AK19 -> 4712.23 | AM19: 7202497 | AN19: =IF(AM19>=AM18,AM19-AM18,0) -> 1104 | AO19: 569474 | AP19: =IF(AO19>=AO18,AO19-AO18,0) -> 310 | AQ19: 911484 | AR19: =IF(AQ19>=AQ18,AQ19-AQ18,0)*0.11 -> 15.29 | AS19: 794231 | AT19: =IF(AS19>=AS18,AS19-AS18,0) -> 39 | AU19: 2329504 | AV19: =IF(AU19>=AU18,AU19-AU18,0) -> 546 | AW19: 208436 | AX19: =IF(AW19>=AW18,AW19-AW18,0) -> 72 | AY19: 17612253 | AZ19: =IF(AY19>=AY18,AY19-AY18,0) -> 3720 | BA19: 21804470 | BB19: =IF(BA19>=BA18,BA19-BA18,0)-(0.6*BG19)-(0.5*BI19)-BK19-BE19 -> 4856.9 | BC19: =AN19+AP19+AR19+AT19+AV19+AX19+AZ19+BB19 -> 10663.19 | BD19: 1363301 | BE19: =IF(BD19>=BD18,BD19-BD18,0) -> 358 | BF19: 3476466 | BG19: =IF(BF19>=BF18,BF19-BF18,0) -> 986 | BH19: 370854 | BI19: =IF(BH19>=BH18,BH19-BH18,0) -> 107 | BJ19: 448798 | BK19: =IF(BJ19>=BJ18,BJ19-BJ18,0) -> 217 | BL19: =J19+Q19+AL19+BC19 -> 20746.42 | BM19: 43 | BN19: =IF(BL19>0,BL19/BM18,0) -> 691.54733 | BP19: =IF(BL19>0,BL19/BO19,0) -> #DIV/0! | BQ19: =BL19*BS1 -> 9543.3532 | BR19: =IF(BQ19>0,BQ19/BM18,0) -> 318.11177 | BS19: =IF(BQ19>0,BQ19/BO19,0) -> #DIV/0!
A20: 15 | C20: =IF(+B20-B19>0,B20-B19,(B20-B19)>0)*800 -> 0 | E20: =IF(+D20-D19>0,D20-D19,(D20-D19)>0)*80 -> 0 | G20: =IF(+F20-F19>0,F20-F19,(F20-F19)>0)*10 -> 0 | H20: 63 | I20: 21979629 | J20: =IF(I20>=I19,I20-I19,0) -> 4525 | K20: =M20+O20 -> 3046 | L20: 982844 | M20: =IF(L20>=L19,L20-L19,0) -> 1465 | N20: 984440 | O20: =IF(N20>=N19,N20-N19,0) -> 1581 | P20: 214437 | Q20: =IF(P20>=P19,P20-P19,0)*30 -> 570 | R20: 702925 | S20: =IF(R20>=R19,R20-R19,0) -> 0 | T20: 344001 | U20: =IF(T20>=T19,T20-T19,0) -> 0 | V20: 128674 | W20: =IF(V20>=V19,V20-V19,0) -> 148 | X20: 234434 | Y20: =IF(X20>=X19,X20-X19,0) -> 248 | Z20: 315108 | AA20: =IF(Z20>=Z19,Z20-Z19,0)*0.53 -> 0 | AB20: 356869 | AC20: =IF(AB20>=AB19,AB20-AB19,0)*0.53 -> 1250.8 | AD20: 551425 | AE20: =IF(AD20>=AD19,AD20-AD19,0)*0.53 -> 0 | AF20: 305142 | AG20: =IF(AF20>=AF19,AF20-AF19,0)*0.53 -> 0 | AH20: 528982 | AI20: =IF(AH20>=AH19,AH20-AH19,0)*0.53 -> 143.1 | AJ20: 664411 | AK20: =IF(AJ20>=AJ19,AJ20-AJ19,0)*0.53 -> 1667.38 | AL20: =AA20+AC20+AE20+AG20+AI20+AK20 -> 3061.28 | AM20: 7202833 | AN20: =IF(AM20>=AM19,AM20-AM19,0) -> 336 | AO20: 569752 | AP20: =IF(AO20>=AO19,AO20-AO19,0) -> 278 | AQ20: 911614 | AR20: =IF(AQ20>=AQ19,AQ20-AQ19,0)*0.11 -> 14.3 | AS20: 794256 | AT20: =IF(AS20>=AS19,AS20-AS19,0) -> 25 | AU20: 2330024 | AV20: =IF(AU20>=AU19,AU20-AU19,0) -> 520 | AW20: 208501 | AX20: =IF(AW20>=AW19,AW20-AW19,0) -> 65 | AY20: 17615799 | AZ20: =IF(AY20>=AY19,AY20-AY19,0) -> 3546 | BA20: 21810061 | BB20: =IF(BA20>=BA19,BA20-BA19,0)-(0.6*BG20)-(0.5*BI20)-BK20-BE20 -> 4455.4 | BC20: =AN20+AP20+AR20+AT20+AV20+AX20+AZ20+BB20 -> 9239.7 | BD20: 1363659 | BE20: =IF(BD20>=BD19,BD20-BD19,0) -> 358 | BF20: 3477342 | BG20: =IF(BF20>=BF19,BF20-BF19,0) -> 876 | BH20: 370954 | BI20: =IF(BH20>=BH19,BH20-BH19,0) -> 100 | BJ20: 449000 | BK20: =IF(BJ20>=BJ19,BJ20-BJ19,0) -> 202 | BL20: =J20+Q20+AL20+BC20 -> 17395.98 | BM20: 65 | BN20: =IF(BL20>0,BL20/BM20,0) -> 267.63046 | BP20: =IF(BL20>0,BL20/BO20,0) -> #DIV/0! | BQ20: =BL20*BS1 -> 8002.1508 | BR20: =IF(BQ20>0,BQ20/BM20,0) -> 123.11001 | BS20: =IF(BQ20>0,BQ20/BO20,0) -> #DIV/0!
A21: 16 | C21: =IF(+B21-B20>0,B21-B20,(B21-B20)>0)*800 -> 0 | E21: =IF(+D21-D20>0,D21-D20,(D21-D20)>0)*80 -> 0 | G21: =IF(+F21-F20>0,F21-F20,(F21-F20)>0)*10 -> 0 | I21: 21983843 | J21: =IF(I21>=I20,I21-I20,0) -> 4214 | K21: =M21+O21 -> 2757 | L21: 984104 | M21: =IF(L21>=L20,L21-L20,0) -> 1260 | N21: 985937 | O21: =IF(N21>=N20,N21-N20,0) -> 1497 | P21: 214454 | Q21: =IF(P21>=P20,P21-P20,0)*30 -> 510 | R21: 702925 | S21: =IF(R21>=R20,R21-R20,0) -> 0 | T21: 344001 | U21: =IF(T21>=T20,T21-T20,0) -> 0 | V21: 128808 | W21: =IF(V21>=V20,V21-V20,0) -> 134 | X21: 234655 | Y21: =IF(X21>=X20,X21-X20,0) -> 221 | Z21: 315108 | AA21: =IF(Z21>=Z20,Z21-Z20,0)*0.53 -> 0 | AB21: 359277 | AC21: =IF(AB21>=AB20,AB21-AB20,0)*0.53 -> 1276.24 | AD21: 551425 | AE21: =IF(AD21>=AD20,AD21-AD20,0)*0.53 -> 0 | AF21: 305142 | AG21: =IF(AF21>=AF20,AF21-AF20,0)*0.53 -> 0 | AH21: 529245 | AI21: =IF(AH21>=AH20,AH21-AH20,0)*0.53 -> 139.39 | AJ21: 667461 | AK21: =IF(AJ21>=AJ20,AJ21-AJ20,0)*0.53 -> 1616.5 | AL21: =AA21+AC21+AE21+AG21+AI21+AK21 -> 3032.13 | AM21: 7203772 | AN21: =IF(AM21>=AM20,AM21-AM20,0) -> 939 | AO21: 570017 | AP21: =IF(AO21>=AO20,AO21-AO20,0) -> 265 | AQ21: 911732 | AR21: =IF(AQ21>=AQ20,AQ21-AQ20,0)*0.11 -> 12.98 | AS21: 794279 | AT21: =IF(AS21>=AS20,AS21-AS20,0) -> 23 | AU21: 2330469 | AV21: =IF(AU21>=AU20,AU21-AU20,0) -> 445 | AW21: 208560 | AX21: =IF(AW21>=AW20,AW21-AW20,0) -> 59 | AY21: 17619002 | AZ21: =IF(AY21>=AY20,AY21-AY20,0) -> 3203 | BA21: 21815170 | BB21: =IF(BA21>=BA20,BA21-BA20,0)-(0.6*BG21)-(0.5*BI21)-BK21-BE21 -> 4043 | BC21: =AN21+AP21+AR21+AT21+AV21+AX21+AZ21+BB21 -> 8989.98 | BD21: 1364017 | BE21: =IF(BD21>=BD20,BD21-BD20,0) -> 358 | BF21: 3478132 | BG21: =IF(BF21>=BF20,BF21-BF20,0) -> 790 | BH21: 371050 | BI21: =IF(BH21>=BH20,BH21-BH20,0) -> 96 | BJ21: 449186 | BK21: =IF(BJ21>=BJ20,BJ21-BJ20,0) -> 186 | BL21: =J21+Q21+AL21+BC21 -> 16746.11 | BM21: 55 | BN21: =IF(BL21>0,BL21/BM21,0) -> 304.47473 | BP21: =IF(BL21>0,BL21/BO21,0) -> #DIV/0! | BQ21: =BL21*BS1 -> 7703.2106 | BR21: =IF(BQ21>0,BQ21/BM21,0) -> 140.05837 | BS21: =IF(BQ21>0,BQ21/BO21,0) -> #DIV/0!
A22: 17 | C22: =IF(+B22-B21>0,B22-B21,(B22-B21)>0)*800 -> 0 | E22: =IF(+D22-D21>0,D22-D21,(D22-D21)>0)*80 -> 0 | G22: =IF(+F22-F21>0,F22-F21,(F22-F21)>0)*10 -> 0 | H22: 64 | I22: 21988928 | J22: =IF(I22>=I21,I22-I21,0) -> 5085 | K22: =M22+O22 -> 3396 | L22: 985714 | M22: =IF(L22>=L21,L22-L21,0) -> 1610 | N22: 987723 | O22: =IF(N22>=N21,N22-N21,0) -> 1786 | P22: 214475 | Q22: =IF(P22>=P21,P22-P21,0)*30 -> 630 | R22: 702925 | S22: =IF(R22>=R21,R22-R21,0) -> 0 | T22: 344001 | U22: =IF(T22>=T21,T22-T21,0) -> 0 | V22: 128964 | W22: =IF(V22>=V21,V22-V21,0) -> 156 | X22: 234914 | Y22: =IF(X22>=X21,X22-X21,0) -> 259 | Z22: 315108 | AA22: =IF(Z22>=Z21,Z22-Z21,0)*0.53 -> 0 | AB22: 363229 | AC22: =IF(AB22>=AB21,AB22-AB21,0)*0.53 -> 2094.56 | AD22: 551425 | AE22: =IF(AD22>=AD21,AD22-AD21,0)*0.53 -> 0 | AF22: 305142 | AG22: =IF(AF22>=AF21,AF22-AF21,0)*0.53 -> 0 | AH22: 529582 | AI22: =IF(AH22>=AH21,AH22-AH21,0)*0.53 -> 178.61 | AJ22: 671689 | AK22: =IF(AJ22>=AJ21,AJ22-AJ21,0)*0.53 -> 2240.84 | AL22: =AA22+AC22+AE22+AG22+AI22+AK22 -> 4514.01 | AM22: 7204464 | AN22: =IF(AM22>=AM21,AM22-AM21,0) -> 692 | AO22: 570312 | AP22: =IF(AO22>=AO21,AO22-AO21,0) -> 295 | AQ22: 911855 | AR22: =IF(AQ22>=AQ21,AQ22-AQ21,0)*0.11 -> 13.53 | AS22: 794314 | AT22: =IF(AS22>=AS21,AS22-AS21,0) -> 35 | AU22: 2330996 | AV22: =IF(AU22>=AU21,AU22-AU21,0) -> 527 | AW22: 208621 | AX22: =IF(AW22>=AW21,AW22-AW21,0) -> 61 | AY22: 17622714 | AZ22: =IF(AY22>=AY21,AY22-AY21,0) -> 3712 | BA22: 21821007 | BB22: =IF(BA22>=BA21,BA22-BA21,0)-(0.6*BG22)-(0.5*BI22)-BK22-BE22 -> 4627.1 | BC22: =AN22+AP22+AR22+AT22+AV22+AX22+AZ22+BB22 -> 9962.63 | BD22: 1364375 | BE22: =IF(BD22>=BD21,BD22-BD21,0) -> 358 | BF22: 3479091 | BG22: =IF(BF22>=BF21,BF22-BF21,0) -> 959 | BH22: 371179 | BI22: =IF(BH22>=BH21,BH22-BH21,0) -> 129 | BJ22: 449398 | BK22: =IF(BJ22>=BJ21,BJ22-BJ21,0) -> 212 | BL22: =J22+Q22+AL22+BC22 -> 20191.64 | BM22: 60 | BN22: =IF(BL22>0,BL22/BM22,0) -> 336.52733 | BP22: =IF(BL22>0,BL22/BO22,0) -> #DIV/0! | BQ22: =BL22*BS1 -> 9288.1544 | BR22: =IF(BQ22>0,BQ22/BM22,0) -> 154.80257 | BS22: =IF(BQ22>0,BQ22/BO22,0) -> #DIV/0!
A23: 18 | C23: =IF(+B23-B22>0,B23-B22,(B23-B22)>0)*800 -> 0 | E23: =IF(+D23-D22>0,D23-D22,(D23-D22)>0)*80 -> 0 | G23: =IF(+F23-F22>0,F23-F22,(F23-F22)>0)*10 -> 0 | I23: 21993782 | J23: =IF(I23>=I22,I23-I22,0) -> 4854 | K23: =M23+O23 -> 3066 | L23: 987190 | M23: =IF(L23>=L22,L23-L22,0) -> 1476 | N23: 989313 | O23: =IF(N23>=N22,N23-N22,0) -> 1590 | P23: 214498 | Q23: =IF(P23>=P22,P23-P22,0)*30 -> 690 | R23: 702925 | S23: =IF(R23>=R22,R23-R22,0) -> 0 | T23: 344001 | U23: =IF(T23>=T22,T23-T22,0) -> 0 | V23: 129105 | W23: =IF(V23>=V22,V23-V22,0) -> 141 | X23: 235146 | Y23: =IF(X23>=X22,X23-X22,0) -> 232 | Z23: 315108 | AA23: =IF(Z23>=Z22,Z23-Z22,0)*0.53 -> 0 | AB23: 363773 | AC23: =IF(AB23>=AB22,AB23-AB22,0)*0.53 -> 288.32 | AD23: 551425 | AE23: =IF(AD23>=AD22,AD23-AD22,0)*0.53 -> 0 | AF23: 306455 | AG23: =IF(AF23>=AF22,AF23-AF22,0)*0.53 -> 695.89 | AH23: 529856 | AI23: =IF(AH23>=AH22,AH23-AH22,0)*0.53 -> 145.22 | AJ23: 674580 | AK23: =IF(AJ23>=AJ22,AJ23-AJ22,0)*0.53 -> 1532.23 | AL23: =AA23+AC23+AE23+AG23+AI23+AK23 -> 2661.66 | AM23: 7205134 | AN23: =IF(AM23>=AM22,AM23-AM22,0) -> 670 | AO23: 570600 | AP23: =IF(AO23>=AO22,AO23-AO22,0) -> 288 | AQ23: 911975 | AR23: =IF(AQ23>=AQ22,AQ23-AQ22,0)*0.11 -> 13.2 | AS23: 794349 | AT23: =IF(AS23>=AS22,AS23-AS22,0) -> 35 | AU23: 2331488 | AV23: =IF(AU23>=AU22,AU23-AU22,0) -> 492 | AW23: 208683 | AX23: =IF(AW23>=AW22,AW23-AW22,0) -> 62 | AY23: 17626217 | AZ23: =IF(AY23>=AY22,AY23-AY22,0) -> 3503 | BA23: 21826285 | BB23: =IF(BA23>=BA22,BA23-BA22,0)-(0.6*BG23)-(0.5*BI23)-BK23-BE23 -> 4143.2 | BC23: =AN23+AP23+AR23+AT23+AV23+AX23+AZ23+BB23 -> 9206.4 | BD23: 1364733 | BE23: =IF(BD23>=BD22,BD23-BD22,0) -> 358 | BF23: 3479969 | BG23: =IF(BF23>=BF22,BF23-BF22,0) -> 878 | BH23: 371285 | BI23: =IF(BH23>=BH22,BH23-BH22,0) -> 106 | BJ23: 449595 | BK23: =IF(BJ23>=BJ22,BJ23-BJ22,0) -> 197 | BL23: =J23+Q23+AL23+BC23 -> 17412.06 | BM23: 44 | BN23: =IF(BL23>0,BL23/BM23,0) -> 395.72864 | BP23: =IF(BL23>0,BL23/BO23,0) -> #DIV/0! | BQ23: =BL23*BS1 -> 8009.5476 | BR23: =IF(BQ23>0,BQ23/BM23,0) -> 182.03517 | BS23: =IF(BQ23>0,BQ23/BO23,0) -> #DIV/0!
A24: 19 | C24: =IF(+B24-B23>0,B24-B23,(B24-B23)>0)*800 -> 0 | E24: =IF(+D24-D23>0,D24-D23,(D24-D23)>0)*80 -> 0 | G24: =IF(+F24-F23>0,F24-F23,(F24-F23)>0)*10 -> 0 | H24: 65 | I24: 21998715 | J24: =IF(I24>=I23,I24-I23,0) -> 4933 | K24: =M24+O24 -> 3070 | L24: 988735 | M24: =IF(L24>=L23,L24-L23,0) -> 1545 | N24: 990838 | O24: =IF(N24>=N23,N24-N23,0) -> 1525 | P24: 214511 | Q24: =IF(P24>=P23,P24-P23,0)*30 -> 390 | R24: 702925 | S24: =IF(R24>=R23,R24-R23,0) -> 0 | T24: 344001 | U24: =IF(T24>=T23,T24-T23,0) -> 0 | V24: 129253 | W24: =IF(V24>=V23,V24-V23,0) -> 148 | X24: 235394 | Y24: =IF(X24>=X23,X24-X23,0) -> 248 | Z24: 315108 | AA24: =IF(Z24>=Z23,Z24-Z23,0)*0.53 -> 0 | AB24: 363773 | AC24: =IF(AB24>=AB23,AB24-AB23,0)*0.53 -> 0 | AD24: 552132 | AE24: =IF(AD24>=AD23,AD24-AD23,0)*0.53 -> 374.71 | AF24: 307674 | AG24: =IF(AF24>=AF23,AF24-AF23,0)*0.53 -> 646.07 | AH24: 530148 | AI24: =IF(AH24>=AH23,AH24-AH23,0)*0.53 -> 154.76 | AJ24: 677439 | AK24: =IF(AJ24>=AJ23,AJ24-AJ23,0)*0.53 -> 1515.27 | AL24: =AA24+AC24+AE24+AG24+AI24+AK24 -> 2690.81 | AM24: 7206055 | AN24: =IF(AM24>=AM23,AM24-AM23,0) -> 921 | AO24: 570875 | AP24: =IF(AO24>=AO23,AO24-AO23,0) -> 275 | AQ24: 912099 | AR24: =IF(AQ24>=AQ23,AQ24-AQ23,0)*0.11 -> 13.64 | AS24: 794383 | AT24: =IF(AS24>=AS23,AS24-AS23,0) -> 34 | AU24: 2332181 | AV24: =IF(AU24>=AU23,AU24-AU23,0) -> 693 | AW24: 208733 | AX24: =IF(AW24>=AW23,AW24-AW23,0) -> 50 | AY24: 17629691 | AZ24: =IF(AY24>=AY23,AY24-AY23,0) -> 3474 | BA24: 21831637 | BB24: =IF(BA24>=BA23,BA24-BA23,0)-(0.6*BG24)-(0.5*BI24)-BK24-BE24 -> 4202 | BC24: =AN24+AP24+AR24+AT24+AV24+AX24+AZ24+BB24 -> 9662.64 | BD24: 1365091 | BE24: =IF(BD24>=BD23,BD24-BD23,0) -> 358 | BF24: 3480859 | BG24: =IF(BF24>=BF23,BF24-BF23,0) -> 890 | BH24: 371395 | BI24: =IF(BH24>=BH23,BH24-BH23,0) -> 110 | BJ24: 449798 | BK24: =IF(BJ24>=BJ23,BJ24-BJ23,0) -> 203 | BL24: =J24+Q24+AL24+BC24 -> 17676.45 | BM24: 51 | BN24: =IF(BL24>0,BL24/BM24,0) -> 346.59706 | BP24: =IF(BL24>0,BL24/BO24,0) -> #DIV/0! | BQ24: =BL24*BS1 -> 8131.167 | BR24: =IF(BQ24>0,BQ24/BM24,0) -> 159.43465 | BS24: =IF(BQ24>0,BQ24/BO24,0) -> #DIV/0!
A25: 20 | C25: =IF(+B25-B24>0,B25-B24,(B25-B24)>0)*800 -> 0 | E25: =IF(+D25-D24>0,D25-D24,(D25-D24)>0)*80 -> 0 | G25: =IF(+F25-F24>0,F25-F24,(F25-F24)>0)*10 -> 0 | I25: 22003726 | J25: =IF(I25>=I24,I25-I24,0) -> 5011 | K25: =M25+O25 -> 3095 | L25: 990323 | M25: =IF(L25>=L24,L25-L24,0) -> 1588 | N25: 992345 | O25: =IF(N25>=N24,N25-N24,0) -> 1507 | P25: 214522 | Q25: =IF(P25>=P24,P25-P24,0)*30 -> 330 | R25: 702925 | S25: =IF(R25>=R24,R25-R24,0) -> 0 | T25: 344001 | U25: =IF(T25>=T24,T25-T24,0) -> 0 | V25: 129399 | W25: =IF(V25>=V24,V25-V24,0) -> 146 | X25: 235634 | Y25: =IF(X25>=X24,X25-X24,0) -> 240 | Z25: 315108 | AA25: =IF(Z25>=Z24,Z25-Z24,0)*0.53 -> 0 | AB25: 363773 | AC25: =IF(AB25>=AB24,AB25-AB24,0)*0.53 -> 0 | AD25: 554474 | AE25: =IF(AD25>=AD24,AD25-AD24,0)*0.53 -> 1241.26 | AF25: 307674 | AG25: =IF(AF25>=AF24,AF25-AF24,0)*0.53 -> 0 | AH25: 530514 | AI25: =IF(AH25>=AH24,AH25-AH24,0)*0.53 -> 193.98 | AJ25: 680516 | AK25: =IF(AJ25>=AJ24,AJ25-AJ24,0)*0.53 -> 1630.81 | AL25: =AA25+AC25+AE25+AG25+AI25+AK25 -> 3066.05 | AM25: 7206792 | AN25: =IF(AM25>=AM24,AM25-AM24,0) -> 737 | AO25: 571161 | AP25: =IF(AO25>=AO24,AO25-AO24,0) -> 286 | AQ25: 912224 | AR25: =IF(AQ25>=AQ24,AQ25-AQ24,0)*0.11 -> 13.75 | AS25: 794416 | AT25: =IF(AS25>=AS24,AS25-AS24,0) -> 33 | AU25: 2332940 | AV25: =IF(AU25>=AU24,AU25-AU24,0) -> 759 | AW25: 208796 | AX25: =IF(AW25>=AW24,AW25-AW24,0) -> 63 | AY25: 17632974 | AZ25: =IF(AY25>=AY24,AY25-AY24,0) -> 3283 | BA25: 21836872 | BB25: =IF(BA25>=BA24,BA25-BA24,0)-(0.6*BG25)-(0.5*BI25)-BK25-BE25 -> 4115.2 | BC25: =AN25+AP25+AR25+AT25+AV25+AX25+AZ25+BB25 -> 9289.95 | BD25: 1365449 | BE25: =IF(BD25>=BD24,BD25-BD24,0) -> 358 | BF25: 3481707 | BG25: =IF(BF25>=BF24,BF25-BF24,0) -> 848 | BH25: 371497 | BI25: =IF(BH25>=BH24,BH25-BH24,0) -> 102 | BJ25: 450000 | BK25: =IF(BJ25>=BJ24,BJ25-BJ24,0) -> 202 | BL25: =J25+Q25+AL25+BC25 -> 17697 | BM25: 48 | BN25: =IF(BL25>0,BL25/BM25,0) -> 368.6875 | BP25: =IF(BL25>0,BL25/BO25,0) -> #DIV/0! | BQ25: =BL25*BS1 -> 8140.62 | BR25: =IF(BQ25>0,BQ25/BM25,0) -> 169.59625 | BS25: =IF(BQ25>0,BQ25/BO25,0) -> #DIV/0!
A26: 21 | C26: =IF(+B26-B25>0,B26-B25,(B26-B25)>0)*800 -> 0 | E26: =IF(+D26-D25>0,D26-D25,(D26-D25)>0)*80 -> 0 | G26: =IF(+F26-F25>0,F26-F25,(F26-F25)>0)*10 -> 0 | H26: 66 | I26: 22008644 | J26: =IF(I26>=I25,I26-I25,0) -> 4918 | K26: =M26+O26 -> 3051 | L26: 991907 | M26: =IF(L26>=L25,L26-L25,0) -> 1584 | N26: 993812 | O26: =IF(N26>=N25,N26-N25,0) -> 1467 | P26: 214544 | Q26: =IF(P26>=P25,P26-P25,0)*30 -> 660 | R26: 702925 | S26: =IF(R26>=R25,R26-R25,0) -> 0 | T26: 344001 | U26: =IF(T26>=T25,T26-T25,0) -> 0 | V26: 129541 | W26: =IF(V26>=V25,V26-V25,0) -> 142 | X26: 235872 | Y26: =IF(X26>=X25,X26-X25,0) -> 238 | Z26: 315108 | AA26: =IF(Z26>=Z25,Z26-Z25,0)*0.53 -> 0 | AB26: 363773 | AC26: =IF(AB26>=AB25,AB26-AB25,0)*0.53 -> 0 | AD26: 557465 | AE26: =IF(AD26>=AD25,AD26-AD25,0)*0.53 -> 1585.23 | AF26: 307674 | AG26: =IF(AF26>=AF25,AF26-AF25,0)*0.53 -> 0 | AH26: 530807 | AI26: =IF(AH26>=AH25,AH26-AH25,0)*0.53 -> 155.29 | AJ26: 683809 | AK26: =IF(AJ26>=AJ25,AJ26-AJ25,0)*0.53 -> 1745.29 | AL26: =AA26+AC26+AE26+AG26+AI26+AK26 -> 3485.81 | AM26: 7207451 | AN26: =IF(AM26>=AM25,AM26-AM25,0) -> 659 | AO26: 571446 | AP26: =IF(AO26>=AO25,AO26-AO25,0) -> 285 | AQ26: 912349 | AR26: =IF(AQ26>=AQ25,AQ26-AQ25,0)*0.11 -> 13.75 | AS26: 794446 | AT26: =IF(AS26>=AS25,AS26-AS25,0) -> 30 | AU26: 2333611 | AV26: =IF(AU26>=AU25,AU26-AU25,0) -> 671 | AW26: 208851 | AX26: =IF(AW26>=AW25,AW26-AW25,0) -> 55 | AY26: 17636253 | AZ26: =IF(AY26>=AY25,AY26-AY25,0) -> 3279 | BA26: 21841925 | BB26: =IF(BA26>=BA25,BA26-BA25,0)-(0.6*BG26)-(0.5*BI26)-BK26-BE26 -> 3961.4 | BC26: =AN26+AP26+AR26+AT26+AV26+AX26+AZ26+BB26 -> 8954.15 | BD26: 1365807 | BE26: =IF(BD26>=BD25,BD26-BD25,0) -> 358 | BF26: 3482513 | BG26: =IF(BF26>=BF25,BF26-BF25,0) -> 806 | BH26: 371599 | BI26: =IF(BH26>=BH25,BH26-BH25,0) -> 102 | BJ26: 450199 | BK26: =IF(BJ26>=BJ25,BJ26-BJ25,0) -> 199 | BL26: =J26+Q26+AL26+BC26 -> 18017.96 | BM26: 50 | BN26: =IF(BL26>0,BL26/BM26,0) -> 360.3592 | BP26: =IF(BL26>0,BL26/BO26,0) -> #DIV/0! | BQ26: =BL26*BS1 -> 8288.2616 | BR26: =IF(BQ26>0,BQ26/BM26,0) -> 165.76523 | BS26: =IF(BQ26>0,BQ26/BO26,0) -> #DIV/0!
A27: 22 | C27: =IF(+B27-B26>0,B27-B26,(B27-B26)>0)*800 -> 0 | E27: =IF(+D27-D26>0,D27-D26,(D27-D26)>0)*80 -> 0 | G27: =IF(+F27-F26>0,F27-F26,(F27-F26)>0)*10 -> 0 | I27: 22013370 | J27: =IF(I27>=I26,I27-I26,0) -> 4726 | K27: =M27+O27 -> 2930 | L27: 993393 | M27: =IF(L27>=L26,L27-L26,0) -> 1486 | N27: 995256 | O27: =IF(N27>=N26,N27-N26,0) -> 1444 | P27: 214564 | Q27: =IF(P27>=P26,P27-P26,0)*30 -> 600 | R27: 702925 | S27: =IF(R27>=R26,R27-R26,0) -> 0 | T27: 344001 | U27: =IF(T27>=T26,T27-T26,0) -> 0 | V27: 129685 | W27: =IF(V27>=V26,V27-V26,0) -> 144 | X27: 236111 | Y27: =IF(X27>=X26,X27-X26,0) -> 239 | Z27: 315108 | AA27: =IF(Z27>=Z26,Z27-Z26,0)*0.53 -> 0 | AB27: 363773 | AC27: =IF(AB27>=AB26,AB27-AB26,0)*0.53 -> 0 | AD27: 558869 | AE27: =IF(AD27>=AD26,AD27-AD26,0)*0.53 -> 744.12 | AF27: 307674 | AG27: =IF(AF27>=AF26,AF27-AF26,0)*0.53 -> 0 | AH27: 531022 | AI27: =IF(AH27>=AH26,AH27-AH26,0)*0.53 -> 113.95 | AJ27: 686101 | AK27: =IF(AJ27>=AJ26,AJ27-AJ26,0)*0.53 -> 1214.76 | AL27: =AA27+AC27+AE27+AG27+AI27+AK27 -> 2072.83 | AM27: 7207952 | AN27: =IF(AM27>=AM26,AM27-AM26,0) -> 501 | AO27: 571753 | AP27: =IF(AO27>=AO26,AO27-AO26,0) -> 307 | AQ27: 912451 | AR27: =IF(AQ27>=AQ26,AQ27-AQ26,0)*0.11 -> 11.22 | AS27: 794465 | AT27: =IF(AS27>=AS26,AS27-AS26,0) -> 19 | AU27: 2333952 | AV27: =IF(AU27>=AU26,AU27-AU26,0) -> 341 | AW27: 208910 | AX27: =IF(AW27>=AW26,AW27-AW26,0) -> 59 | AY27: 17639647 | AZ27: =IF(AY27>=AY26,AY27-AY26,0) -> 3394 | BA27: 21846921 | BB27: =IF(BA27>=BA26,BA27-BA26,0)-(0.6*BG27)-(0.5*BI27)-BK27-BE27 -> 3917.3 | BC27: =AN27+AP27+AR27+AT27+AV27+AX27+AZ27+BB27 -> 8549.52 | BD27: 1366165 | BE27: =IF(BD27>=BD26,BD27-BD26,0) -> 358 | BF27: 3483295 | BG27: =IF(BF27>=BF26,BF27-BF26,0) -> 782 | BH27: 371700 | BI27: =IF(BH27>=BH26,BH27-BH26,0) -> 101 | BJ27: 450400 | BK27: =IF(BJ27>=BJ26,BJ27-BJ26,0) -> 201 | BL27: =J27+Q27+AL27+BC27 -> 15948.35 | BM27: 54 | BN27: =IF(BL27>0,BL27/BM27,0) -> 295.33981 | BP27: =IF(BL27>0,BL27/BO27,0) -> #DIV/0! | BQ27: =BL27*BS1 -> 7336.241 | BR27: =IF(BQ27>0,BQ27/BM27,0) -> 135.85631 | BS27: =IF(BQ27>0,BQ27/BO27,0) -> #DIV/0!
A28: 23 | C28: =IF(+B28-B27>0,B28-B27,(B28-B27)>0)*800 -> 0 | E28: =IF(+D28-D27>0,D28-D27,(D28-D27)>0)*80 -> 0 | G28: =IF(+F28-F27>0,F28-F27,(F28-F27)>0)*10 -> 0 | H28: 67 | I28: 22017926 | J28: =IF(I28>=I27,I28-I27,0) -> 4556 | K28: =M28+O28 -> 2869 | L28: 994781 | M28: =IF(L28>=L27,L28-L27,0) -> 1388 | N28: 996737 | O28: =IF(N28>=N27,N28-N27,0) -> 1481 | P28: 214582 | Q28: =IF(P28>=P27,P28-P27,0)*30 -> 540 | R28: 702925 | S28: =IF(R28>=R27,R28-R27,0) -> 0 | T28: 344001 | U28: =IF(T28>=T27,T28-T27,0) -> 0 | V28: 129830 | W28: =IF(V28>=V27,V28-V27,0) -> 145 | X28: 236350 | Y28: =IF(X28>=X27,X28-X27,0) -> 239 | Z28: 315108 | AA28: =IF(Z28>=Z27,Z28-Z27,0)*0.53 -> 0 | AB28: 363773 | AC28: =IF(AB28>=AB27,AB28-AB27,0)*0.53 -> 0 | AD28: 561065 | AE28: =IF(AD28>=AD27,AD28-AD27,0)*0.53 -> 1163.88 | AF28: 307674 | AG28: =IF(AF28>=AF27,AF28-AF27,0)*0.53 -> 0 | AH28: 531344 | AI28: =IF(AH28>=AH27,AH28-AH27,0)*0.53 -> 170.66 | AJ28: 689156 | AK28: =IF(AJ28>=AJ27,AJ28-AJ27,0)*0.53 -> 1619.15 | AL28: =AA28+AC28+AE28+AG28+AI28+AK28 -> 2953.69 | AM28: 7208590 | AN28: =IF(AM28>=AM27,AM28-AM27,0) -> 638 | AO28: 572047 | AP28: =IF(AO28>=AO27,AO28-AO27,0) -> 294 | AQ28: 912534 | AR28: =IF(AQ28>=AQ27,AQ28-AQ27,0)*0.11 -> 9.13 | AS28: 794484 | AT28: =IF(AS28>=AS27,AS28-AS27,0) -> 19 | AU28: 2334293 | AV28: =IF(AU28>=AU27,AU28-AU27,0) -> 341 | AW28: 208973 | AX28: =IF(AW28>=AW27,AW28-AW27,0) -> 63 | AY28: 17643203 | AZ28: =IF(AY28>=AY27,AY28-AY27,0) -> 3556 | BA28: 21852096 | BB28: =IF(BA28>=BA27,BA28-BA27,0)-(0.6*BG28)-(0.5*BI28)-BK28-BE28 -> 4040.9 | BC28: =AN28+AP28+AR28+AT28+AV28+AX28+AZ28+BB28 -> 8961.03 | BD28: 1366523 | BE28: =IF(BD28>=BD27,BD28-BD27,0) -> 358 | BF28: 3484146 | BG28: =IF(BF28>=BF27,BF28-BF27,0) -> 851 | BH28: 371827 | BI28: =IF(BH28>=BH27,BH28-BH27,0) -> 127 | BJ28: 450602 | BK28: =IF(BJ28>=BJ27,BJ28-BJ27,0) -> 202 | BL28: =J28+Q28+AL28+BC28 -> 17010.72 | BM28: 44 | BN28: =IF(BL28>0,BL28/BM28,0) -> 386.60727 | BP28: =IF(BL28>0,BL28/BO28,0) -> #DIV/0! | BQ28: =BL28*BS1 -> 7824.9312 | BR28: =IF(BQ28>0,BQ28/BM28,0) -> 177.83935 | BS28: =IF(BQ28>0,BQ28/BO28,0) -> #DIV/0!
A29: 24 | C29: =IF(+B29-B28>0,B29-B28,(B29-B28)>0)*800 -> 0 | E29: =IF(+D29-D28>0,D29-D28,(D29-D28)>0)*80 -> 0 | G29: =IF(+F29-F28>0,F29-F28,(F29-F28)>0)*10 -> 0 | I29: 22022614 | J29: =IF(I29>=I28,I29-I28,0) -> 4688 | K29: =M29+O29 -> 2974 | L29: 996175 | M29: =IF(L29>=L28,L29-L28,0) -> 1394 | N29: 998317 | O29: =IF(N29>=N28,N29-N28,0) -> 1580 | P29: 214605 | Q29: =IF(P29>=P28,P29-P28,0)*30 -> 690 | R29: 702925 | S29: =IF(R29>=R28,R29-R28,0) -> 0 | T29: 344001 | U29: =IF(T29>=T28,T29-T28,0) -> 0 | V29: 129973 | W29: =IF(V29>=V28,V29-V28,0) -> 143 | X29: 236587 | Y29: =IF(X29>=X28,X29-X28,0) -> 237 | Z29: 315108 | AA29: =IF(Z29>=Z28,Z29-Z28,0)*0.53 -> 0 | AB29: 365483 | AC29: =IF(AB29>=AB28,AB29-AB28,0)*0.53 -> 906.3 | AD29: 562354 | AE29: =IF(AD29>=AD28,AD29-AD28,0)*0.53 -> 683.17 | AF29: 307674 | AG29: =IF(AF29>=AF28,AF29-AF28,0)*0.53 -> 0 | AH29: 531624 | AI29: =IF(AH29>=AH28,AH29-AH28,0)*0.53 -> 148.4 | AJ29: 692112 | AK29: =IF(AJ29>=AJ28,AJ29-AJ28,0)*0.53 -> 1566.68 | AL29: =AA29+AC29+AE29+AG29+AI29+AK29 -> 3304.55 | AM29: 7209404 | AN29: =IF(AM29>=AM28,AM29-AM28,0) -> 814 | AO29: 572310 | AP29: =IF(AO29>=AO28,AO29-AO28,0) -> 263 | AQ29: 912657 | AR29: =IF(AQ29>=AQ28,AQ29-AQ28,0)*0.11 -> 13.53 | AS29: 794514 | AT29: =IF(AS29>=AS28,AS29-AS28,0) -> 30 | AU29: 2334638 | AV29: =IF(AU29>=AU28,AU29-AU28,0) -> 345 | AW29: 209037 | AX29: =IF(AW29>=AW28,AW29-AW28,0) -> 64 | AY29: 17646681 | AZ29: =IF(AY29>=AY28,AY29-AY28,0) -> 3478 | BA29: 21857291 | BB29: =IF(BA29>=BA28,BA29-BA28,0)-(0.6*BG29)-(0.5*BI29)-BK29-BE29 -> 4041 | BC29: =AN29+AP29+AR29+AT29+AV29+AX29+AZ29+BB29 -> 9048.53 | BD29: 1366881 | BE29: =IF(BD29>=BD28,BD29-BD28,0) -> 358 | BF29: 3485041 | BG29: =IF(BF29>=BF28,BF29-BF28,0) -> 895 | BH29: 371945 | BI29: =IF(BH29>=BH28,BH29-BH28,0) -> 118 | BJ29: 450802 | BK29: =IF(BJ29>=BJ28,BJ29-BJ28,0) -> 200 | BL29: =J29+Q29+AL29+BC29 -> 17731.08 | BM29: 41 | BN29: =IF(BL29>0,BL29/BM29,0) -> 432.46537 | BP29: =IF(BL29>0,BL29/BO29,0) -> #DIV/0! | BQ29: =BL29*BS1 -> 8156.2968 | BR29: =IF(BQ29>0,BQ29/BM29,0) -> 198.93407 | BS29: =IF(BQ29>0,BQ29/BO29,0) -> #DIV/0!
A30: 25 | C30: =IF(+B30-B29>0,B30-B29,(B30-B29)>0)*800 -> 0 | E30: =IF(+D30-D29>0,D30-D29,(D30-D29)>0)*80 -> 0 | G30: =IF(+F30-F29>0,F30-F29,(F30-F29)>0)*10 -> 0 | H30: 68 | I30: 22027555 | J30: =IF(I30>=I29,I30-I29,0) -> 4941 | K30: =M30+O30 -> 3145 | L30: 997638 | M30: =IF(L30>=L29,L30-L29,0) -> 1463 | N30: 999999 | O30: =IF(N30>=N29,N30-N29,0) -> 1682 | P30: 214626 | Q30: =IF(P30>=P29,P30-P29,0)*30 -> 630 | R30: 702925 | S30: =IF(R30>=R29,R30-R29,0) -> 0 | T30: 344001 | U30: =IF(T30>=T29,T30-T29,0) -> 0 | V30: 130130 | W30: =IF(V30>=V29,V30-V29,0) -> 157 | X30: 236849 | Y30: =IF(X30>=X29,X30-X29,0) -> 262 | Z30: 315329 | AA30: =IF(Z30>=Z29,Z30-Z29,0)*0.53 -> 117.13 | AB30: 366985 | AC30: =IF(AB30>=AB29,AB30-AB29,0)*0.53 -> 796.06 | AD30: 562354 | AE30: =IF(AD30>=AD29,AD30-AD29,0)*0.53 -> 0 | AF30: 307674 | AG30: =IF(AF30>=AF29,AF30-AF29,0)*0.53 -> 0 | AH30: 531920 | AI30: =IF(AH30>=AH29,AH30-AH29,0)*0.53 -> 156.88 | AJ30: 695296 | AK30: =IF(AJ30>=AJ29,AJ30-AJ29,0)*0.53 -> 1687.52 | AL30: =AA30+AC30+AE30+AG30+AI30+AK30 -> 2757.59 | AM30: 7210212 | AN30: =IF(AM30>=AM29,AM30-AM29,0) -> 808 | AO30: 572588 | AP30: =IF(AO30>=AO29,AO30-AO29,0) -> 278 | AQ30: 912791 | AR30: =IF(AQ30>=AQ29,AQ30-AQ29,0)*0.11 -> 14.74 | AS30: 794548 | AT30: =IF(AS30>=AS29,AS30-AS29,0) -> 34 | AU30: 2335041 | AV30: =IF(AU30>=AU29,AU30-AU29,0) -> 403 | AW30: 209107 | AX30: =IF(AW30>=AW29,AW30-AW29,0) -> 70 | AY30: 17650353 | AZ30: =IF(AY30>=AY29,AY30-AY29,0) -> 3672 | BA30: 21862713 | BB30: =IF(BA30>=BA29,BA30-BA29,0)-(0.6*BG30)-(0.5*BI30)-BK30-BE30 -> 4240.3 | BC30: =AN30+AP30+AR30+AT30+AV30+AX30+AZ30+BB30 -> 9520.04 | BD30: 1367239 | BE30: =IF(BD30>=BD29,BD30-BD29,0) -> 358 | BF30: 3485958 | BG30: =IF(BF30>=BF29,BF30-BF29,0) -> 917 | BH30: 372056 | BI30: =IF(BH30>=BH29,BH30-BH29,0) -> 111 | BJ30: 451020 | BK30: =IF(BJ30>=BJ29,BJ30-BJ29,0) -> 218 | BL30: =J30+Q30+AL30+BC30 -> 17848.63 | BM30: 37 | BN30: =IF(BL30>0,BL30/BM30,0) -> 482.39541 | BP30: =IF(BL30>0,BL30/BO30,0) -> #DIV/0! | BQ30: =BL30*BS1 -> 8210.3698 | BR30: =IF(BQ30>0,BQ30/BM30,0) -> 221.90189 | BS30: =IF(BQ30>0,BQ30/BO30,0) -> #DIV/0!
A31: 26 | C31: =IF(+B31-B30>0,B31-B30,(B31-B30)>0)*800 -> 0 | E31: =IF(+D31-D30>0,D31-D30,(D31-D30)>0)*80 -> 0 | G31: =IF(+F31-F30>0,F31-F30,(F31-F30)>0)*10 -> 0 | I31: 22031666 | J31: =IF(I31>=I30,I31-I30,0) -> 4111 | K31: =M31+O31 -> 2726 | L31: 998691 | M31: =IF(L31>=L30,L31-L30,0) -> 1053 | N31: 1001672 | O31: =IF(N31>=N30,N31-N30,0) -> 1673 | P31: 214646 | Q31: =IF(P31>=P30,P31-P30,0)*30 -> 600 | R31: 702925 | S31: =IF(R31>=R30,R31-R30,0) -> 0 | T31: 344001 | U31: =IF(T31>=T30,T31-T30,0) -> 0 | V31: 130264 | W31: =IF(V31>=V30,V31-V30,0) -> 134 | X31: 237031 | Y31: =IF(X31>=X30,X31-X30,0) -> 182 | Z31: 315335 | AA31: =IF(Z31>=Z30,Z31-Z30,0)*0.53 -> 3.18 | AB31: 369721 | AC31: =IF(AB31>=AB30,AB31-AB30,0)*0.53 -> 1450.08 | AD31: 562354 | AE31: =IF(AD31>=AD30,AD31-AD30,0)*0.53 -> 0 | AF31: 307674 | AG31: =IF(AF31>=AF30,AF31-AF30,0)*0.53 -> 0 | AH31: 532289 | AI31: =IF(AH31>=AH30,AH31-AH30,0)*0.53 -> 195.57 | AJ31: 698601 | AK31: =IF(AJ31>=AJ30,AJ31-AJ30,0)*0.53 -> 1751.65 | AL31: =AA31+AC31+AE31+AG31+AI31+AK31 -> 3400.48 | AM31: 7210626 | AN31: =IF(AM31>=AM30,AM31-AM30,0) -> 414 | AO31: 572852 | AP31: =IF(AO31>=AO30,AO31-AO30,0) -> 264 | AQ31: 912893 | AR31: =IF(AQ31>=AQ30,AQ31-AQ30,0)*0.11 -> 11.22 | AS31: 794581 | AT31: =IF(AS31>=AS30,AS31-AS30,0) -> 33 | AU31: 2335358 | AV31: =IF(AU31>=AU30,AU31-AU30,0) -> 317 | AW31: 209169 | AX31: =IF(AW31>=AW30,AW31-AW30,0) -> 62 | AY31: 17653637 | AZ31: =IF(AY31>=AY30,AY31-AY30,0) -> 3284 | BA31: 21867429 | BB31: =IF(BA31>=BA30,BA31-BA30,0)-(0.6*BG31)-(0.5*BI31)-BK31-BE31 -> 3603 | BC31: =AN31+AP31+AR31+AT31+AV31+AX31+AZ31+BB31 -> 7988.22 | BD31: 1367597 | BE31: =IF(BD31>=BD30,BD31-BD30,0) -> 358 | BF31: 3486823 | BG31: =IF(BF31>=BF30,BF31-BF30,0) -> 865 | BH31: 372154 | BI31: =IF(BH31>=BH30,BH31-BH30,0) -> 98 | BJ31: 451207 | BK31: =IF(BJ31>=BJ30,BJ31-BJ30,0) -> 187 | BL31: =J31+Q31+AL31+BC31 -> 16099.7 | BM31: 29 | BN31: =IF(BL31>0,BL31/BM31,0) -> 555.16207 | BP31: =IF(BL31>0,BL31/BO31,0) -> #DIV/0! | BQ31: =BL31*BS1 -> 7405.862 | BR31: =IF(BQ31>0,BQ31/BM31,0) -> 255.37455 | BS31: =IF(BQ31>0,BQ31/BO31,0) -> #DIV/0!
A32: 27 | C32: =IF(+B32-B31>0,B32-B31,(B32-B31)>0)*800 -> 0 | E32: =IF(+D32-D31>0,D32-D31,(D32-D31)>0)*80 -> 0 | G32: =IF(+F32-F31>0,F32-F31,(F32-F31)>0)*10 -> 0 | H32: 69 | I32: 22035923 | J32: =IF(I32>=I31,I32-I31,0) -> 4257 | K32: =M32+O32 -> 2692 | L32: 999812 | M32: =IF(L32>=L31,L32-L31,0) -> 1121 | N32: 1003243 | O32: =IF(N32>=N31,N32-N31,0) -> 1571 | P32: 214667 | Q32: =IF(P32>=P31,P32-P31,0)*30 -> 630 | R32: 702925 | S32: =IF(R32>=R31,R32-R31,0) -> 0 | T32: 344001 | U32: =IF(T32>=T31,T32-T31,0) -> 0 | V32: 130415 | W32: =IF(V32>=V31,V32-V31,0) -> 151 | X32: 237321 | Y32: =IF(X32>=X31,X32-X31,0) -> 290 | Z32: 315335 | AA32: =IF(Z32>=Z31,Z32-Z31,0)*0.53 -> 0 | AB32: 372312 | AC32: =IF(AB32>=AB31,AB32-AB31,0)*0.53 -> 1373.23 | AD32: 562354 | AE32: =IF(AD32>=AD31,AD32-AD31,0)*0.53 -> 0 | AF32: 307674 | AG32: =IF(AF32>=AF31,AF32-AF31,0)*0.53 -> 0 | AH32: 532594 | AI32: =IF(AH32>=AH31,AH32-AH31,0)*0.53 -> 161.65 | AJ32: 701872 | AK32: =IF(AJ32>=AJ31,AJ32-AJ31,0)*0.53 -> 1733.63 | AL32: =AA32+AC32+AE32+AG32+AI32+AK32 -> 3268.51 | AM32: 7211268 | AN32: =IF(AM32>=AM31,AM32-AM31,0) -> 642 | AO32: 573128 | AP32: =IF(AO32>=AO31,AO32-AO31,0) -> 276 | AQ32: 913012 | AR32: =IF(AQ32>=AQ31,AQ32-AQ31,0)*0.11 -> 13.09 | AS32: 794621 | AT32: =IF(AS32>=AS31,AS32-AS31,0) -> 40 | AU32: 2335734 | AV32: =IF(AU32>=AU31,AU32-AU31,0) -> 376 | AW32: 209230 | AX32: =IF(AW32>=AW31,AW32-AW31,0) -> 61 | AY32: 17657108 | AZ32: =IF(AY32>=AY31,AY32-AY31,0) -> 3471 | BA32: 21872969 | BB32: =IF(BA32>=BA31,BA32-BA31,0)-(0.6*BG32)-(0.5*BI32)-BK32-BE32 -> 4375.7 | BC32: =AN32+AP32+AR32+AT32+AV32+AX32+AZ32+BB32 -> 9254.79 | BD32: 1367955 | BE32: =IF(BD32>=BD31,BD32-BD31,0) -> 358 | BF32: 3487696 | BG32: =IF(BF32>=BF31,BF32-BF31,0) -> 873 | BH32: 372299 | BI32: =IF(BH32>=BH31,BH32-BH31,0) -> 145 | BJ32: 451417 | BK32: =IF(BJ32>=BJ31,BJ32-BJ31,0) -> 210 | BL32: =J32+Q32+AL32+BC32 -> 17410.3 | BM32: 23 | BN32: =IF(BL32>0,BL32/BM32,0) -> 756.96957 | BP32: =IF(BL32>0,BL32/BO32,0) -> #DIV/0! | BQ32: =BL32*BS1 -> 8008.738 | BR32: =IF(BQ32>0,BQ32/BM32,0) -> 348.206 | BS32: =IF(BQ32>0,BQ32/BO32,0) -> #DIV/0!
A33: 28 | C33: =IF(+B33-B32>0,B33-B32,(B33-B32)>0)*800 -> 0 | E33: =IF(+D33-D32>0,D33-D32,(D33-D32)>0)*80 -> 0 | G33: =IF(+F33-F32>0,F33-F32,(F33-F32)>0)*10 -> 0 | I33: 22040260 | J33: =IF(I33>=I32,I33-I32,0) -> 4337 | K33: =M33+O33 -> 3002 | L33: 1001242 | M33: =IF(L33>=L32,L33-L32,0) -> 1430 | N33: 1004815 | O33: =IF(N33>=N32,N33-N32,0) -> 1572 | P33: 214685 | Q33: =IF(P33>=P32,P33-P32,0)*30 -> 540 | R33: 702925 | S33: =IF(R33>=R32,R33-R32,0) -> 0 | T33: 344001 | U33: =IF(T33>=T32,T33-T32,0) -> 0 | V33: 130555 | W33: =IF(V33>=V32,V33-V32,0) -> 140 | X33: 237553 | Y33: =IF(X33>=X32,X33-X32,0) -> 232 | Z33: 315335 | AA33: =IF(Z33>=Z32,Z33-Z32,0)*0.53 -> 0 | AB33: 375311 | AC33: =IF(AB33>=AB32,AB33-AB32,0)*0.53 -> 1589.47 | AD33: 562354 | AE33: =IF(AD33>=AD32,AD33-AD32,0)*0.53 -> 0 | AF33: 307674 | AG33: =IF(AF33>=AF32,AF33-AF32,0)*0.53 -> 0 | AH33: 532922 | AI33: =IF(AH33>=AH32,AH33-AH32,0)*0.53 -> 173.84 | AJ33: 704923 | AK33: =IF(AJ33>=AJ32,AJ33-AJ32,0)*0.53 -> 1617.03 | AL33: =AA33+AC33+AE33+AG33+AI33+AK33 -> 3380.34 | AM33: 7212100 | AN33: =IF(AM33>=AM32,AM33-AM32,0) -> 832 | AO33: 573419 | AP33: =IF(AO33>=AO32,AO33-AO32,0) -> 291 | AQ33: 913117 | AR33: =IF(AQ33>=AQ32,AQ33-AQ32,0)*0.11 -> 11.55 | AS33: 794641 | AT33: =IF(AS33>=AS32,AS33-AS32,0) -> 20 | AU33: 2336069 | AV33: =IF(AU33>=AU32,AU33-AU32,0) -> 335 | AW33: 209288 | AX33: =IF(AW33>=AW32,AW33-AW32,0) -> 58 | AY33: 17660455 | AZ33: =IF(AY33>=AY32,AY33-AY32,0) -> 3347 | BA33: 21878039 | BB33: =IF(BA33>=BA32,BA33-BA32,0)-(0.6*BG33)-(0.5*BI33)-BK33-BE33 -> 3865.4 | BC33: =AN33+AP33+AR33+AT33+AV33+AX33+AZ33+BB33 -> 8759.95 | BD33: 1368313 | BE33: =IF(BD33>=BD32,BD33-BD32,0) -> 358 | BF33: 3488687 | BG33: =IF(BF33>=BF32,BF33-BF32,0) -> 991 | BH33: 372419 | BI33: =IF(BH33>=BH32,BH33-BH32,0) -> 120 | BJ33: 451609 | BK33: =IF(BJ33>=BJ32,BJ33-BJ32,0) -> 192 | BL33: =J33+Q33+AL33+BC33 -> 17017.29 | BM33: 33 | BN33: =IF(BL33>0,BL33/BM33,0) -> 515.67545 | BP33: =IF(BL33>0,BL33/BO33,0) -> #DIV/0! | BQ33: =BL33*BS1 -> 7827.9534 | BR33: =IF(BQ33>0,BQ33/BM33,0) -> 237.21071 | BS33: =IF(BQ33>0,BQ33/BO33,0) -> #DIV/0!
A34: 29 | C34: =IF(+B34-B33>0,B34-B33,(B34-B33)>0)*800 -> 0 | E34: =IF(+D34-D33>0,D34-D33,(D34-D33)>0)*80 -> 0 | G34: =IF(+F34-F33>0,F34-F33,(F34-F33)>0)*10 -> 0 | I34: 22043930 | J34: =IF(I34>=I33,I34-I33,0) -> 3670 | K34: =M34+O34 -> 0 | L34: 0 | M34: =IF(L34>=L33,L34-L33,0) -> 0 | N34: 0 | O34: =IF(N34>=N33,N34-N33,0) -> 0 | P34: 214703 | Q34: =IF(P34>=P33,P34-P33,0)*30 -> 540 | R34: 702925 | S34: =IF(R34>=R33,R34-R33,0) -> 0 | T34: 344001 | U34: =IF(T34>=T33,T34-T33,0) -> 0 | V34: 130698 | W34: =IF(V34>=V33,V34-V33,0) -> 143 | X34: 237788 | Y34: =IF(X34>=X33,X34-X33,0) -> 235 | Z34: 315335 | AA34: =IF(Z34>=Z33,Z34-Z33,0)*0.53 -> 0 | AB34: 377234 | AC34: =IF(AB34>=AB33,AB34-AB33,0)*0.53 -> 1019.19 | AD34: 562354 | AE34: =IF(AD34>=AD33,AD34-AD33,0)*0.53 -> 0 | AF34: 307674 | AG34: =IF(AF34>=AF33,AF34-AF33,0)*0.53 -> 0 | AH34: 533168 | AI34: =IF(AH34>=AH33,AH34-AH33,0)*0.53 -> 130.38 | AJ34: 707727 | AK34: =IF(AJ34>=AJ33,AJ34-AJ33,0)*0.53 -> 1486.12 | AL34: =AA34+AC34+AE34+AG34+AI34+AK34 -> 2635.69 | AM34: 7212859 | AN34: =IF(AM34>=AM33,AM34-AM33,0) -> 759 | AO34: 573696 | AP34: =IF(AO34>=AO33,AO34-AO33,0) -> 277 | AQ34: 913221 | AR34: =IF(AQ34>=AQ33,AQ34-AQ33,0)*0.11 -> 11.44 | AS34: 794661 | AT34: =IF(AS34>=AS33,AS34-AS33,0) -> 20 | AU34: 2336411 | AV34: =IF(AU34>=AU33,AU34-AU33,0) -> 342 | AW34: 209350 | AX34: =IF(AW34>=AW33,AW34-AW33,0) -> 62 | AY34: 17663780 | AZ34: =IF(AY34>=AY33,AY34-AY33,0) -> 3325 | BA34: 21882981 | BB34: =IF(BA34>=BA33,BA34-BA33,0)-(0.6*BG34)-(0.5*BI34)-BK34-BE34 -> 3820.8 | BC34: =AN34+AP34+AR34+AT34+AV34+AX34+AZ34+BB34 -> 8617.24 | BD34: 1368671 | BE34: =IF(BD34>=BD33,BD34-BD33,0) -> 358 | BF34: 3489549 | BG34: =IF(BF34>=BF33,BF34-BF33,0) -> 862 | BH34: 372521 | BI34: =IF(BH34>=BH33,BH34-BH33,0) -> 102 | BJ34: 451804 | BK34: =IF(BJ34>=BJ33,BJ34-BJ33,0) -> 195 | BL34: =J34+Q34+AL34+BC34 -> 15462.93 | BM34: 34 | BN34: =IF(BL34>0,BL34/BM34,0) -> 454.79206 | BP34: =IF(BL34>0,BL34/BO34,0) -> #DIV/0! | BQ34: =BL34*BS1 -> 7112.9478 | BR34: =IF(BQ34>0,BQ34/BM34,0) -> 209.20435 | BS34: =IF(BQ34>0,BQ34/BO34,0) -> #DIV/0!
A35: 30 | C35: =IF(+B35-B34>0,B35-B34,(B35-B34)>0)*800 -> 0 | E35: =IF(+D35-D34>0,D35-D34,(D35-D34)>0)*80 -> 0 | G35: =IF(+F35-F34>0,F35-F34,(F35-F34)>0)*10 -> 0 | I35: 22049270 | J35: =IF(I35>=I34,I35-I34,0) -> 5340 | K35: =M35+O35 -> 2683 | L35: 1236 | M35: =IF(L35>=L34,L35-L34,0) -> 1236 | N35: 1447 | O35: =IF(N35>=N34,N35-N34,0) -> 1447 | P35: 214717 | Q35: =IF(P35>=P34,P35-P34,0)*30 -> 420 | R35: 702925 | S35: =IF(R35>=R34,R35-R34,0) -> 0 | T35: 344001 | U35: =IF(T35>=T34,T35-T34,0) -> 0 | V35: 130840 | W35: =IF(V35>=V34,V35-V34,0) -> 142 | X35: 238054 | Y35: =IF(X35>=X34,X35-X34,0) -> 266 | Z35: 315335 | AA35: =IF(Z35>=Z34,Z35-Z34,0)*0.53 -> 0 | AB35: 379806 | AC35: =IF(AB35>=AB34,AB35-AB34,0)*0.53 -> 1363.16 | AD35: 562354 | AE35: =IF(AD35>=AD34,AD35-AD34,0)*0.53 -> 0 | AF35: 307674 | AG35: =IF(AF35>=AF34,AF35-AF34,0)*0.53 -> 0 | AH35: 533479 | AI35: =IF(AH35>=AH34,AH35-AH34,0)*0.53 -> 164.83 | AJ35: 710692 | AK35: =IF(AJ35>=AJ34,AJ35-AJ34,0)*0.53 -> 1571.45 | AL35: =AA35+AC35+AE35+AG35+AI35+AK35 -> 3099.44 | AM35: 7213450 | AN35: =IF(AM35>=AM34,AM35-AM34,0) -> 591 | AO35: 573997 | AP35: =IF(AO35>=AO34,AO35-AO34,0) -> 301 | AQ35: 913353 | AR35: =IF(AQ35>=AQ34,AQ35-AQ34,0)*0.11 -> 14.52 | AS35: 794695 | AT35: =IF(AS35>=AS34,AS35-AS34,0) -> 34 | AU35: 2337060 | AV35: =IF(AU35>=AU34,AU35-AU34,0) -> 649 | AW35: 209409 | AX35: =IF(AW35>=AW34,AW35-AW34,0) -> 59 | AY35: 17667307 | AZ35: =IF(AY35>=AY34,AY35-AY34,0) -> 3527 | BA35: 21887870 | BB35: =IF(BA35>=BA34,BA35-BA34,0)-(0.6*BG35)-(0.5*BI35)-BK35-BE35 -> 3758.4 | BC35: =AN35+AP35+AR35+AT35+AV35+AX35+AZ35+BB35 -> 8933.92 | BD35: 1369063 | BE35: =IF(BD35>=BD34,BD35-BD34,0) -> 392 | BF35: 3490340 | BG35: =IF(BF35>=BF34,BF35-BF34,0) -> 791 | BH35: 372631 | BI35: =IF(BH35>=BH34,BH35-BH34,0) -> 110 | BJ35: 452013 | BK35: =IF(BJ35>=BJ34,BJ35-BJ34,0) -> 209 | BL35: =J35+Q35+AL35+BC35 -> 17793.36 | BM35: 32 | BN35: =IF(BL35>0,BL35/BM35,0) -> 556.0425 | BP35: =IF(BL35>0,BL35/BO35,0) -> #DIV/0! | BQ35: =BL35*BS1 -> 8184.9456 | BR35: =IF(BQ35>0,BQ35/BM35,0) -> 255.77955 | BS35: =IF(BQ35>0,BQ35/BO35,0) -> #DIV/0!
A36: 31 | I36: 22053832 | J36: =IF(I36>=I35,I36-I35,0) -> 4562 | K36: =M36+O36 -> 2818 | L36: 2554 | M36: =IF(L36>=L35,L36-L35,0) -> 1318 | N36: 2947 | O36: =IF(N36>=N35,N36-N35,0) -> 1500 | P36: 214736 | Q36: =IF(P36>=P35,P36-P35,0)*30 -> 570 | R36: 702925 | S36: =IF(R36>=R35,R36-R35,0) -> 0 | T36: 344001 | U36: =IF(T36>=T35,T36-T35,0) -> 0 | V36: 130984 | W36: =IF(V36>=V35,V36-V35,0) -> 144 | X36: 238297 | Y36: =IF(X36>=X35,X36-X35,0) -> 243 | Z36: 315335 | AA36: =IF(Z36>=Z35,Z36-Z35,0)*0.53 -> 0 | AB36: 382273 | AC36: =IF(AB36>=AB35,AB36-AB35,0)*0.53 -> 1307.51 | AD36: 562354 | AE36: =IF(AD36>=AD35,AD36-AD35,0)*0.53 -> 0 | AF36: 307674 | AG36: =IF(AF36>=AF35,AF36-AF35,0)*0.53 -> 0 | AH36: 533781 | AI36: =IF(AH36>=AH35,AH36-AH35,0)*0.53 -> 160.06 | AJ36: 713719 | AK36: =IF(AJ36>=AJ35,AJ36-AJ35,0)*0.53 -> 1604.31 | AL36: =AA36+AC36+AE36+AG36+AI36+AK36 -> 3071.88 | AM36: 7214129 | AN36: =IF(AM36>=AM35,AM36-AM35,0) -> 679 | AO36: 574281 | AP36: =IF(AO36>=AO35,AO36-AO35,0) -> 284 | AQ36: 913468 | AR36: =IF(AQ36>=AQ35,AQ36-AQ35,0)*0.11 -> 12.65 | AS36: 794724 | AT36: =IF(AS36>=AS35,AS36-AS35,0) -> 29 | AU36: 2337484 | AV36: =IF(AU36>=AU35,AU36-AU35,0) -> 424 | AW36: 209470 | AX36: =IF(AW36>=AW35,AW36-AW35,0) -> 61 | AY36: 17670739 | AZ36: =IF(AY36>=AY35,AY36-AY35,0) -> 3432 | BA36: 21892385 | BB36: =IF(BA36>=BA35,BA36-BA35,0)-(0.6*BG36)-(0.5*BI36)-BK36-BE36 -> 3383 | BC36: =AN36+AP36+AR36+AT36+AV36+AX36+AZ36+BB36 -> 8304.65 | BD36: 1369414 | BE36: =IF(BD36>=BD35,BD36-BD35,0) -> 351 | BF36: 3491211 | BG36: =IF(BF36>=BF35,BF36-BF35,0) -> 871 | BH36: 372745 | BI36: =IF(BH36>=BH35,BH36-BH35,0) -> 114 | BJ36: 452214 | BK36: =IF(BJ36>=BJ35,BJ36-BJ35,0) -> 201 | BL36: =J36+Q36+AL36+BC36 -> 16508.53 | BM36: 33 | BN36: =IF(BL36>0,BL36/BM36,0) -> 500.25848 | BP36: =IF(BL36>0,BL36/BO36,0) -> #DIV/0! | BQ36: =BL36*BS1 -> 7593.9238 | BR36: =IF(BQ36>0,BQ36/BM36,0) -> 230.1189 | BS36: =IF(BQ36>0,BQ36/BO36,0) -> #DIV/0!
A37: MTD | C37: =SUM(C9:C35) -> 0 | E37: =SUM(E9:E35) -> 0 | F37: =SUM(F9:F35) -> 0 | G37: =SUM(G9:G35) -> 0 | J37: =SUM(J6:J36) -> 141376 | K37: =SUM(K6:K36) -> 87731 | M37: =SUM(M6:M36) -> 40732 | O37: =SUM(O6:O36) -> 46999 | Q37: =SUM(Q6:Q36) -> 17280 | S37: =SUM(S6:S36) -> 0 | U37: =SUM(U6:U36) -> 0 | W37: =SUM(W6:W36) -> 4482 | Y37: =SUM(Y6:Y36) -> 7551 | AA37: =SUM(AA6:AA36) -> 120.31 | AC37: =SUM(AC5:AC36) -> 27939.48 | AE37: =SUM(AE6:AE36) -> 13959.14 | AG37: =SUM(AG6:AG36) -> 9685.75 | AI37: =SUM(AI6:AI36) -> 6051.01 | AK37: =SUM(AK6:AK36) -> 54782.39 | AL37: =SUM(AL6:AL36) -> 112538.08 | AN37: =SUM(AN6:AN36) -> 26067 | AP37: =SUM(AP6:AP36) -> 8706 | AR37: =SUM(AR6:AR36) -> 411.29 | AT37: =SUM(AT6:AT36) -> 1037 | AV37: =SUM(AV6:AV36) -> 15146 | AX37: =SUM(AX6:AX36) -> 1859 | AZ37: =SUM(AZ6:AZ36) -> 108934 | BB37: =SUM(BB6:BB36) -> 129042.6 | BC37: =SUM(BC6:BC36) -> 291202.89 | BE37: =SUM(BE6:BE36) -> 11125 | BG37: =SUM(BG6:BG36) -> 25950 | BI37: =SUM(BI6:BI36) -> 3264 | BK37: =SUM(BK6:BK36) -> 6000 | BL37: =SUM(BL6:BL36) -> 562396.97 | BM37: =SUM(BM6:BM36) -> 1464 | BN37: =IF(BL37>0,BL37/BM37,0) -> 384.15094 | BO37: =SUM(BO6:BO35) -> 0 | BP37: =IF(BL37>0,BL37/BO37,0) -> #DIV/0! | BQ37: =SUM(BQ6:BQ35) -> 251108.68 | BR37: =IF(BQ37>0,BQ37/BM37,0) -> 171.52232 | BS37: =IF(BQ37>0,BQ37/BO37,0) -> #DIV/0!
A38: AVER. Act | C38: =C37/C47 -> #DIV/0! | E38: =E37/C47 -> #DIV/0! | F38: =F37/C47 -> #DIV/0! | G38: =G37/C47 -> #DIV/0! | J38: =J37/J46 -> 4712.5333 | K38: =K37/J46 -> 2924.3667 | M38: =M37/J46 -> 1357.7333 | O38: =O37/J46 -> 1566.6333 | Q38: =Q37/J46 -> 576 | S38: =S37/J46 -> 0 | U38: =U37/J46 -> 0 | W38: =W37/J46 -> 149.4 | Y38: =Y37/J46 -> 251.7 | AA38: =AA37/J46 -> 4.0103333 | AC38: =AC37/J46 -> 931.316 | AE38: =AE37/J46 -> 465.30467 | AG38: =AG37/J46 -> 322.85833 | AI38: =AI37/J46 -> 201.70033 | AK38: =AK37/J46 -> 1826.0797 | AL38: =AL37/J46 -> 3751.2693 | AN38: =AN37/J46 -> 868.9 | AP38: =AP37/J46 -> 290.2 | AR38: =AR37/J46 -> 13.709667 | AT38: =AT37/J46 -> 34.566667 | AV38: =AV37/J46 -> 504.86667 | AX38: =AX37/J46 -> 61.966667 | AZ38: =AZ37/J46 -> 3631.1333 | BB38: =BB37/J46 -> 4301.42 | BE38: =BE37/J46 -> 370.83333 | BG38: =BG37/J46 -> 865 | BI38: =BI37/J46 -> 108.8 | BK38: =BK37/J46 -> 200 | BL38: =BL37/$J$48 -> #DIV/0! | BM38: =BM37/$J$48 -> #DIV/0! | BN38: =BL38/BM38 -> #DIV/0! | BO38: =BO37/$J$48 -> #DIV/0! | BP38: =BL38/BO38 -> #DIV/0! | BQ38: =BQ37/$J$48 -> #DIV/0! | BR38: =BQ38/BM38 -> #DIV/0! | BS38: =BQ38/BO38 -> #DIV/0!
A39: AVER. Bud | BL39: =(BQ39-($T$1*$BE$2+$T$2))/(0.7*$Q$1+0.3*$Q$2+$BE$1) -> #DIV/0! | BM39: =[1]YTD!AY2341 -> 0 | BN39: =IF(BL39>0,BL39/BM39,0) -> #DIV/0! | BO39: =[1]YTD!AY2342 -> 0 | BP39: =IF(BL39>0,BL39/BO39,0) -> #DIV/0! | BQ39: =[1]YTD!AY2345 -> 0 | BR39: =IF(BQ39>0,BQ39/BM39,0) -> 0 | BS39: =IF(BQ39>0,BQ39/BO39,0) -> 0
A40: Total RFC | BL40: =(BL39/$J$49)*$J$48 -> #DIV/0! | BM40: =BM41*BF48 -> #DIV/0! | BN40: =IF(BL40>0,BL40/BM40,0) -> #DIV/0! | BO40: =BO41*$J$48 -> #DIV/0! | BP40: =IF(BL40>0,BL40/BO40,0) -> #DIV/0! | BQ40: =BQ39/$J$49*BF48 -> #DIV/0! | BR40: =IF(BQ40>0,BQ40/BM40,0) -> #DIV/0! | BS40: =IF(BQ40>0,BQ40/BO40,0) -> #DIV/0!
A41: RFC MTD | BL41: =BL39/$J$49 -> #DIV/0! | BM41: =BM39/$J$49 -> #DIV/0! | BO41: =BO39/$J$49 -> #DIV/0! | BQ41: =BQ39/$J$49 -> #DIV/0!
A42: AVER RFC | BL42: =(BQ42-($T$1*$BE$2+$T$2))/(0.7*$Q$1+0.3*$Q$2+$BE$1) -> #DIV/0! | BM42: =[1]YTD!AY2358 -> 0 | BN42: =IF(BL42>0,BL42/BM42,0) -> #DIV/0! | BO42: =[1]YTD!AY2359 -> 0 | BP42: =IF(BL42>0,BL42/BO42,0) -> #DIV/0! | BQ42: =[1]YTD!AY2362 -> 0 | BR42: =IF(BQ42>0,BQ42/BM42,0) -> 0 | BS42: =IF(BQ42>0,BQ42/BO42,0) -> 0
A43: Tot. Act. 13 | BL43: =(BL42/$J$49)*$J$48 -> #DIV/0! | BM43: =BM42/BF49*BF48 -> #DIV/0! | BN43: =IF(BL43>0,BL43/BM43,0) -> #DIV/0! | BO43: =BO42/BF49*BF48 -> #DIV/0! | BP43: =IF(BL43>0,BL43/BO43,0) -> #DIV/0! | BQ43: =BQ42/BF49*BF48 -> #DIV/0! | BR43: =IF(BQ43>0,BQ43/BM43,0) -> #DIV/0! | BS43: =IF(BQ43>0,BQ43/BO43,0) -> #DIV/0!
A44: Ave. Act. 13 | BL44: =BL42/BF49 -> #DIV/0! | BM44: =BM42/BF49 -> #DIV/0! | BO44: =BO42/BF49 -> #DIV/0! | BQ44: =BQ42/BF49 -> #DIV/0!
A45: Accounting Readings | I45: =IF(I33>0,I33,0) -> 22040260 | BL45: =[1]Consp!AJ33 -> 8688.15 | BN45: =[1]Consp!CF33 -> 0 | BP45: =[1]Consp!CG33 -> 0 | BQ45: =[1]Consp!CH33 -> 0 | BR45: =[1]Consp!CI33 -> 0 | BS45: =[1]Consp!CJ33 -> 0
A46: No of Days MTD | J46: =COUNTIF(I6:I35,">0") -> 30 | BL46: =[1]Consp!AJ34 -> 310.29107 | BN46: =[1]Consp!CF34 -> 0 | BP46: =[1]Consp!CG34 -> 0 | BQ46: =[1]Consp!CH34 -> 0 | BR46: =[1]Consp!CI34 -> 0 | BS46: =[1]Consp!CJ34 -> 0
A47: No of Days month | J47: =COUNTIF(A6:A35,">0") -> 30
I56: =-L11 -> -971081

Sheet Gas
A1: =Elect!A1 -> January | E1: Gas | H1: Gas UP | J1: 3.9
A4: NO. | B4: Main Gas Flow Meter | D4: Laundry Gas Flow Meter | F4: Grumandiz Gas Flow Meter | H4: Plant Room Gas Share Cost | I4: Hotel Consumption Cost | J4: La Grumandiz Cost | K4: Total Natural Gas Consumption
B5: Read | C5: Cons | D5: Read | E5: Cons | F5: Read | G5: Cons | H5: LE/DAY | I5: LE/DAY | J5: LE/DAY | K5: Cons
B6: 7948724 | C6: =IF(B6>=B5,B6-B5,0)*1.06 -> 0 | D6: 309621 | E6: =IF(D6>=D5,D6-D5,0)*0.7 -> 0 | F6: 568029 | G6: =IF(F6>=F5,F6-F5,0) -> 0 | K6: =C6+E6 -> 0
A7: 1 | B7: 7949568 | C7: =IF(B7>=B6,B7-B6,0)*1.06 -> 894.64 | D7: 310157 | E7: =IF(D7>=D6,D7-D6,0)*0.7 -> 375.2 | F7: 568098 | G7: =IF(F7>=F6,F7-F6,0) -> 69 | H7: =(E7*0.55)*1.61 -> 332.2396 | I7: =C7*J1 -> 3489.096 | J7: =G7*J1 -> 269.1 | K7: =C7+E7 -> 1269.84
A8: 2 | B8: 7950727 | C8: =IF(B8>=B7,B8-B7,0)*1.06 -> 1228.54 | D8: 310492 | E8: =IF(D8>=D7,D8-D7,0)*0.7 -> 234.5 | F8: 568162 | G8: =IF(F8>=F7,F8-F7,0) -> 64 | H8: =(E8*0.55)*1.61 -> 207.64975 | I8: =C8*J1 -> 4791.306 | J8: =G8*J1 -> 249.6 | K8: =C8+E8 -> 1463.04
A9: 3 | B9: 7951694 | C9: =IF(B9>=B8,B9-B8,0)*1.06 -> 1025.02 | D9: 310917 | E9: =IF(D9>=D8,D9-D8,0)*0.7 -> 297.5 | F9: 568229 | G9: =IF(F9>=F8,F9-F8,0) -> 67 | H9: =(E9*0.55)*1.61 -> 263.43625 | I9: =C9*J1 -> 3997.578 | J9: =G9*J1 -> 261.3 | K9: =C9+E9 -> 1322.52
A10: 4 | B10: 7952355 | C10: =IF(B10>=B9,B10-B9,0)*1.06 -> 700.66 | D10: 311243 | E10: =IF(D10>=D9,D10-D9,0)*0.7 -> 228.2 | F10: 568300 | G10: =IF(F10>=F9,F10-F9,0) -> 71 | H10: =(E10*0.55)*1.61 -> 202.0711 | I10: =C10*J1 -> 2732.574 | J10: =G10*J1 -> 276.9 | K10: =C10+E10 -> 928.86
A11: 5 | B11: 7953465 | C11: =IF(B11>=B10,B11-B10,0)*1.06 -> 1176.6 | D11: 311649 | E11: =IF(D11>=D10,D11-D10,0)*0.7 -> 284.2 | F11: 568382 | G11: =IF(F11>=F10,F11-F10,0) -> 82 | H11: =(E11*0.55)*1.61 -> 251.6591 | I11: =C11*J1 -> 4588.74 | J11: =G11*J1 -> 319.8 | K11: =C11+E11 -> 1460.8
A12: 6 | B12: 7954392 | C12: =IF(B12>=B11,B12-B11,0)*1.06 -> 982.62 | D12: 312062 | E12: =IF(D12>=D11,D12-D11,0)*0.7 -> 289.1 | F12: 568443 | G12: =IF(F12>=F11,F12-F11,0) -> 61 | H12: =(E12*0.55)*1.61 -> 255.99805 | I12: =C12*J1 -> 3832.218 | J12: =G12*J1 -> 237.9 | K12: =C12+E12 -> 1271.72
A13: 7 | B13: 7955256 | C13: =IF(B13>=B12,B13-B12,0)*1.06 -> 915.84 | D13: 312398 | E13: =IF(D13>=D12,D13-D12,0)*0.7 -> 235.2 | F13: 568497 | G13: =IF(F13>=F12,F13-F12,0) -> 54 | H13: =(E13*0.55)*1.61 -> 208.2696 | I13: =C13*J1 -> 3571.776 | J13: =G13*J1 -> 210.6 | K13: =C13+E13 -> 1151.04
A14: 8 | B14: 7955957 | C14: =IF(B14>=B13,B14-B13,0)*1.06 -> 743.06 | D14: 312755 | E14: =IF(D14>=D13,D14-D13,0)*0.7 -> 249.9 | F14: 568573 | G14: =IF(F14>=F13,F14-F13,0) -> 76 | H14: =(E14*0.55)*1.61 -> 221.28645 | I14: =C14*J1 -> 2897.934 | J14: =G14*J1 -> 296.4 | K14: =C14+E14 -> 992.96
A15: 9 | B15: 7956763 | C15: =IF(B15>=B14,B15-B14,0)*1.06 -> 854.36 | D15: 313170 | E15: =IF(D15>=D14,D15-D14,0)*0.7 -> 290.5 | F15: 568640 | G15: =IF(F15>=F14,F15-F14,0) -> 67 | H15: =(E15*0.55)*1.61 -> 257.23775 | I15: =C15*J1 -> 3332.004 | J15: =G15*J1 -> 261.3 | K15: =C15+E15 -> 1144.86
A16: 10 | B16: 7957726 | C16: =IF(B16>=B15,B16-B15,0)*1.06 -> 1020.78 | D16: 313619 | E16: =IF(D16>=D15,D16-D15,0)*0.7 -> 314.3 | F16: 568742 | G16: =IF(F16>=F15,F16-F15,0) -> 102 | H16: =(E16*0.55)*1.61 -> 278.31265 | I16: =C16*J1 -> 3981.042 | J16: =G16*J1 -> 397.8 | K16: =C16+E16 -> 1335.08
A17: 11 | B17: 7958590 | C17: =IF(B17>=B16,B17-B16,0)*1.06 -> 915.84 | D17: 313951 | E17: =IF(D17>=D16,D17-D16,0)*0.7 -> 232.4 | F17: 568792 | G17: =IF(F17>=F16,F17-F16,0) -> 50 | H17: =(E17*0.55)*1.61 -> 205.7902 | I17: =C17*J1 -> 3571.776 | J17: =G17*J1 -> 195 | K17: =C17+E17 -> 1148.24
A18: 12 | B18: 7959499 | C18: =IF(B18>=B17,B18-B17,0)*1.06 -> 963.54 | D18: 314250 | E18: =IF(D18>=D17,D18-D17,0)*0.7 -> 209.3 | F18: 568872 | G18: =IF(F18>=F17,F18-F17,0) -> 80 | H18: =(E18*0.55)*1.61 -> 185.33515 | I18: =C18*J1 -> 3757.806 | J18: =G18*J1 -> 312 | K18: =C18+E18 -> 1172.84
A19: 13 | B19: 7960407 | C19: =IF(B19>=B18,B19-B18,0)*1.06 -> 962.48 | D19: 314506 | E19: =IF(D19>=D18,D19-D18,0)*0.7 -> 179.2 | F19: 568943 | G19: =IF(F19>=F18,F19-F18,0) -> 71 | H19: =(E19*0.55)*1.61 -> 158.6816 | I19: =C19*J1 -> 3753.672 | J19: =G19*J1 -> 276.9 | K19: =C19+E19 -> 1141.68
A20: 14 | B20: 7961290 | C20: =IF(B20>=B19,B20-B19,0)*1.06 -> 935.98 | D20: 315008 | E20: =IF(D20>=D19,D20-D19,0)*0.7 -> 351.4 | F20: 569016 | G20: =IF(F20>=F19,F20-F19,0) -> 73 | H20: =(E20*0.55)*1.61 -> 311.1647 | I20: =C20*J1 -> 3650.322 | J20: =G20*J1 -> 284.7 | K20: =C20+E20 -> 1287.38
A21: 15 | B21: 7962173 | C21: =IF(B21>=B20,B21-B20,0)*1.06 -> 935.98 | D21: 315381 | E21: =IF(D21>=D20,D21-D20,0)*0.7 -> 261.1 | F21: 569089 | G21: =IF(F21>=F20,F21-F20,0) -> 73 | H21: =(E21*0.55)*1.61 -> 231.20405 | I21: =C21*J1 -> 3650.322 | J21: =G21*J1 -> 284.7 | K21: =C21+E21 -> 1197.08
A22: 16 | B22: 7963238 | C22: =IF(B22>=B21,B22-B21,0)*1.06 -> 1128.9 | D22: 315528 | E22: =IF(D22>=D21,D22-D21,0)*0.7 -> 102.9 | F22: 569144 | G22: =IF(F22>=F21,F22-F21,0) -> 55 | H22: =(E22*0.55)*1.61 -> 91.11795 | I22: =C22*J1 -> 4402.71 | J22: =G22*J1 -> 214.5 | K22: =C22+E22 -> 1231.8
A23: 17 | B23: 7964246 | C23: =IF(B23>=B22,B23-B22,0)*1.06 -> 1068.48 | D23: 315876 | E23: =IF(D23>=D22,D23-D22,0)*0.7 -> 243.6 | F23: 569225 | G23: =IF(F23>=F22,F23-F22,0) -> 81 | H23: =(E23*0.55)*1.61 -> 215.7078 | I23: =C23*J1 -> 4167.072 | J23: =G23*J1 -> 315.9 | K23: =C23+E23 -> 1312.08
A24: 18 | B24: 7965107 | C24: =IF(B24>=B23,B24-B23,0)*1.06 -> 912.66 | D24: 316176 | E24: =IF(D24>=D23,D24-D23,0)*0.7 -> 210 | F24: 569299 | G24: =IF(F24>=F23,F24-F23,0) -> 74 | H24: =(E24*0.55)*1.61 -> 185.955 | I24: =C24*J1 -> 3559.374 | J24: =G24*J1 -> 288.6 | K24: =C24+E24 -> 1122.66
A25: 19 | B25: 7966232 | C25: =IF(B25>=B24,B25-B24,0)*1.06 -> 1192.5 | D25: 316600 | E25: =IF(D25>=D24,D25-D24,0)*0.7 -> 296.8 | F25: 569362 | G25: =IF(F25>=F24,F25-F24,0) -> 63 | H25: =(E25*0.55)*1.61 -> 262.8164 | I25: =C25*J1 -> 4650.75 | J25: =G25*J1 -> 245.7 | K25: =C25+E25 -> 1489.3
A26: 20 | B26: 7967337 | C26: =IF(B26>=B25,B26-B25,0)*1.06 -> 1171.3 | D26: 317005 | E26: =IF(D26>=D25,D26-D25,0)*0.7 -> 283.5 | F26: 569441 | G26: =IF(F26>=F25,F26-F25,0) -> 79 | H26: =(E26*0.55)*1.61 -> 251.03925 | I26: =C26*J1 -> 4568.07 | J26: =G26*J1 -> 308.1 | K26: =C26+E26 -> 1454.8
A27: 21 | B27: 7968158 | C27: =IF(B27>=B26,B27-B26,0)*1.06 -> 870.26 | D27: 317262 | E27: =IF(D27>=D26,D27-D26,0)*0.7 -> 179.9 | F27: 569509 | G27: =IF(F27>=F26,F27-F26,0) -> 68 | H27: =(E27*0.55)*1.61 -> 159.30145 | I27: =C27*J1 -> 3394.014 | J27: =G27*J1 -> 265.2 | K27: =C27+E27 -> 1050.16
A28: 22 | B28: 7969253 | C28: =IF(B28>=B27,B28-B27,0)*1.06 -> 1160.7 | D28: 317804 | E28: =IF(D28>=D27,D28-D27,0)*0.7 -> 379.4 | F28: 569582 | G28: =IF(F28>=F27,F28-F27,0) -> 73 | H28: =(E28*0.55)*1.61 -> 335.9587 | I28: =C28*J1 -> 4526.73 | J28: =G28*J1 -> 284.7
A29: 23 | B29: 7970196 | C29: =IF(B29>=B28,B29-B28,0)*1.06 -> 999.58 | D29: 318279 | E29: =IF(D29>=D28,D29-D28,0)*0.7 -> 332.5 | F29: 569647 | G29: =IF(F29>=F28,F29-F28,0) -> 65 | H29: =(E29*0.55)*1.61 -> 294.42875 | I29: =C29*J1 -> 3898.362 | J29: =G29*J1 -> 253.5 | K29: =C29+E29 -> 1332.08
A30: 24 | B30: 7971263 | C30: =IF(B30>=B29,B30-B29,0)*1.06 -> 1131.02 | D30: 318686 | E30: =IF(D30>=D29,D30-D29,0)*0.7 -> 284.9 | F30: 569730 | G30: =IF(F30>=F29,F30-F29,0) -> 83 | H30: =(E30*0.55)*1.61 -> 252.27895 | I30: =C30*J1 -> 4410.978 | J30: =G30*J1 -> 323.7 | K30: =C30+E30 -> 1415.92
A31: 25 | B31: 7972221 | C31: =IF(B31>=B30,B31-B30,0)*1.06 -> 1015.48 | D31: 318959 | E31: =IF(D31>=D30,D31-D30,0)*0.7 -> 191.1 | F31: 569794 | G31: =IF(F31>=F30,F31-F30,0) -> 64 | H31: =(E31*0.55)*1.61 -> 169.21905 | I31: =C31*J3 -> 0 | J31: =G31*J1 -> 249.6 | K31: =C31+E31 -> 1206.58
A32: 26 | B32: 7973078 | C32: =IF(B32>=B31,B32-B31,0)*1.06 -> 908.42 | D32: 319332 | E32: =IF(D32>=D31,D32-D31,0)*0.7 -> 261.1 | F32: 569865 | G32: =IF(F32>=F31,F32-F31,0) -> 71 | H32: =(E32*0.55)*1.61 -> 231.20405 | I32: =C32*J1 -> 3542.838 | J32: =G32*J1 -> 276.9 | K32: =C32+E32 -> 1169.52
A33: 27 | B33: 7974214 | C33: =IF(B33>=B32,B33-B32,0)*1.06 -> 1204.16 | D33: 319788 | E33: =IF(D33>=D32,D33-D32,0)*0.7 -> 319.2 | F33: 569906 | G33: =IF(F33>=F32,F33-F32,0) -> 41 | H33: =(E33*0.55)*1.61 -> 282.6516 | I33: =C33*J1 -> 4696.224 | J33: =G33*J1 -> 159.9 | K33: =C33+E33 -> 1523.36
A34: 28 | B34: 7975316 | C34: =IF(B34>=B33,B34-B33,0)*1.06 -> 1168.12 | D34: 320265 | E34: =IF(D34>=D33,D34-D33,0)*0.7 -> 333.9 | F34: 569957 | G34: =IF(F34>=F33,F34-F33,0) -> 51 | H34: =(E34*0.55)*1.61 -> 295.66845 | I34: =C34*J1 -> 4555.668 | J34: =G34*J1 -> 198.9 | K34: =C34+E34 -> 1502.02
A35: 29 | B35: 7976039 | C35: =IF(B35>=B34,B35-B34,0)*1.06 -> 766.38 | D35: 320599 | E35: =IF(D35>=D34,D35-D34,0)*0.7 -> 233.8 | F35: 570106 | G35: =IF(F35>=F34,F35-F34,0) -> 149 | H35: =(E35*0.55)*1.61 -> 207.0299 | I35: =C35*J1 -> 2988.882 | J35: =G35*J1 -> 581.1 | K35: =C35+E35 -> 1000.18
A36: 30 | B36: 7976609 | C36: =IF(B36>=B35,B36-B35,0)*1.06 -> 604.2 | D36: 320982 | E36: =IF(D36>=D35,D36-D35,0)*0.7 -> 268.1 | F36: 570179 | G36: =IF(F36>=F35,F36-F35,0) -> 73 | H36: =(E36*0.55)*1.61 -> 237.40255 | I36: =C36*J1 -> 2356.38 | J36: =G36*J1 -> 284.7 | K36: =C36+E36 -> 872.3
A37: 31 | B37: 7978015 | C37: =IF(B37>=B36,B37-B36,0)*1.06 -> 1490.36 | D37: 321271 | E37: =IF(D37>=D36,D37-D36,0)*0.7 -> 202.3 | F37: 570220 | G37: =IF(F37>=F36,F37-F36,0) -> 41 | H37: =(E37*0.55)*1.61 -> 179.13665 | I37: =C37*J1 -> 5812.404 | J37: =G37*J1 -> 159.9 | K37: =C37+E37 -> 1692.66
A38: MTD | C38: =SUM(C7:C37) -> 31048.46 | E38: =SUM(E7:E37) -> 8155 | G38: =SUM(G7:G37) -> 2191 | H38: =SUM(H6:H37) -> 7221.2525 | I38: =SUM(I6:I37) -> 117128.62 | J38: =SUM(J6:J37) -> 8544.9 | K38: =SUM(K6:K37) -> 37663.36
A39: Average MTD. | C39: =C38/A42 -> 1034.9487 | E39: =E38/A42 -> 271.83333 | G39: =G38/A42 -> 73.033333 | H39: =H38/A42 -> 240.70842 | I39: =I38/A42 -> 3904.2874 | J39: =J38/A42 -> 284.83
A41: No of Days MTD
A42: =COUNTIF(B7:B36,">0") -> 30

Sheet Water
A1: =Elect!A1 -> January | T1: Main Water UP | V1: 4 | W1: Water Truck UP
A3: Day | E3: Water Incoming | I3: New casino | N3: Rooms Consumption | P3: Public Areas consumption | R3: Swimming pool | T3: No. of rooms | U3: Cons. Per occ. room | V3: No. of guest | W3: Cons. Per guest | X3: Total cost | Y3: L.E\ | Z3: L.E\
B4: Main water meter 1 | D4: Main water meter 2 | F4: Main water meter 3 | H4: Total Inc. | I4: Hot water | K4: Cold water | N4: Express Riser | O4: Consp. | P4: Read. | Q4: Cons. | R4: Read. | S4: Cons. | Y4: Room | Z4: Guest
B5: Counter | C5: Produc 58% | D5: Counter | E5: Produc 58% | F5: Counter | G5: Produc 58% | I5: Counter | K5: Counter
B6: 74313 | C6: =IF(B6>=B5,B6-B5,0)*10*0.58 -> 0 | D6: 153842 | E6: =IF(D6>=D5,D6-D5,0)*10*0.58 -> 0 | F6: 17286 | G6: =IF(F6>=F5,F6-F5,0)*0.58 -> 0 | I6: 210 | K6: 2825
A7: 1 | B7: 74313 | C7: =IF(B7>=B6,B7-B6,0)*10*0.58 -> 0 | D7: 153883 | E7: =IF(D7>=D6,D7-D6,0)*10*0.58 -> 237.8 | F7: 17299 | G7: =IF(F7>=F6,F7-F6,0)*0.58 -> 7.54 | H7: =C7+E7+G7 -> 245.34 | O7: =IF(N7>=N6,N7-N6,0) -> 0 | Q7: =(H7-O7)*0.58 -> 142.2972 | S7: =IF(R7-R6>0,R7-R6,0) -> 0 | T7: =Elect!BM6 -> 73 | U7: =H7/T7 -> 3.3608219 | V7: =Elect!BO6 -> 0 | W7: =H7/V7 -> #DIV/0! | X7: =H7*V1 -> 981.36 | Y7: =IF(X7>0,X7/T7,0) -> 13.443288 | Z7: 0
A8: 2 | B8: 74313 | C8: =IF(B8>=B7,B8-B7,0)*10*0.58 -> 0 | D8: 153909 | E8: =IF(D8>=D7,D8-D7,0)*10*0.58 -> 150.8 | F8: 17320 | G8: =IF(F8>=F7,F8-F7,0)*0.58 -> 12.18 | H8: =C8+E8+G8 -> 162.98 | O8: =IF(N8>=N7,N8-N7,0) -> 0 | Q8: =(H8-O8)*0.58 -> 94.5284 | S8: =IF(R8-R7>0,R8-R7,0) -> 0 | T8: =Elect!BM7 -> 54 | U8: =H8/T8 -> 3.0181481 | V8: =Elect!BO7 -> 0 | W8: =H8/V8 -> #DIV/0! | X8: =H8*V1 -> 651.92 | Y8: =IF(X8>0,X8/T8,0) -> 12.072593 | Z8: =IF(X8>0,X8/V8,0) -> #DIV/0!
A9: 3 | B9: 74314 | C9: =IF(B9>=B8,B9-B8,0)*10*0.58 -> 5.8 | D9: 153941 | E9: =IF(D9>=D8,D9-D8,0)*10*0.58 -> 185.6 | F9: 17338 | G9: =IF(F9>=F8,F9-F8,0)*0.58 -> 10.44 | H9: =C9+E9+G9 -> 201.84 | O9: =IF(N9>=N8,N9-N8,0) -> 0 | Q9: =(H9-O9)*0.58 -> 117.0672 | S9: =IF(R9-R8>0,R9-R8,0) -> 0 | T9: =Elect!BM8 -> 43 | U9: =H9/T9 -> 4.6939535 | V9: =Elect!BO8 -> 0 | W9: =H9/V9 -> #DIV/0! | X9: =H9*V1 -> 807.36 | Y9: =IF(X9>0,X9/T9,0) -> 18.775814 | Z9: =IF(X9>0,X9/V9,0) -> #DIV/0!
A10: 4 | B10: 74314 | C10: =IF(B10>=B9,B10-B9,0)*10*0.58 -> 0 | D10: 153971 | E10: =IF(D10>=D9,D10-D9,0)*10*0.58 -> 174 | F10: 17346 | G10: =IF(F10>=F9,F10-F9,0)*0.58 -> 4.64 | H10: =C10+E10+G10 -> 178.64 | O10: =IF(N10>=N9,N10-N9,0) -> 0 | Q10: =(H10-O10)*0.58 -> 103.6112 | S10: =IF(R10-R9>0,R10-R9,0) -> 0 | T10: =Elect!BM9 -> 50 | U10: =H10/T10 -> 3.5728 | V10: =Elect!BO9 -> 0 | W10: =H10/V10 -> #DIV/0! | X10: =H10*V1 -> 714.56 | Y10: =IF(X10>0,X10/T10,0) -> 14.2912 | Z10: =IF(X10>0,X10/V10,0) -> #DIV/0!
A11: 5 | B11: 74314 | C11: =IF(B11>=B10,B11-B10,0)*10*0.58 -> 0 | D11: 154011 | E11: =IF(D11>=D10,D11-D10,0)*10*0.58 -> 232 | F11: 17361 | G11: =IF(F11>=F10,F11-F10,0)*0.58 -> 8.7 | H11: =C11+E11+G11 -> 240.7 | O11: =IF(N11>=N10,N11-N10,0) -> 0 | Q11: =(H11-O11)*0.58 -> 139.606 | S11: =IF(R11-R10>0,R11-R10,0) -> 0 | T11: =Elect!BM10 -> 53 | U11: =H11/T11 -> 4.5415094 | V11: =Elect!BO10 -> 0 | W11: =H11/V11 -> #DIV/0! | X11: =H11*V1 -> 962.8 | Y11: =IF(X11>0,X11/T11,0) -> 18.166038 | Z11: =IF(X11>0,X11/V11,0) -> #DIV/0!
A12: 6 | B12: 74315 | C12: =IF(B12>=B11,B12-B11,0)*10*0.58 -> 5.8 | D12: 154038 | E12: =IF(D12>=D11,D12-D11,0)*10*0.58 -> 156.6 | F12: 17373 | G12: =IF(F12>=F11,F12-F11,0)*0.58 -> 6.96 | H12: =C12+E12+G12 -> 169.36 | O12: =IF(N12>=N11,N12-N11,0) -> 0 | Q12: =(H12-O12)*0.58 -> 98.2288 | S12: =IF(R12-R11>0,R12-R11,0) -> 0 | T12: =Elect!BM11 -> 50 | U12: =H12/T12 -> 3.3872 | V12: =Elect!BO11 -> 0 | W12: =H12/V12 -> #DIV/0! | X12: =H12*V1 -> 677.44 | Y12: =IF(X12>0,X12/T12,0) -> 13.5488 | Z12: =IF(X12>0,X12/V12,0) -> #DIV/0!
A13: 7 | B13: 74315 | C13: =IF(B13>=B12,B13-B12,0)*10*0.58 -> 0 | D13: 154078 | E13: =IF(D13>=D12,D13-D12,0)*10*0.58 -> 232 | F13: 17385 | G13: =IF(F13>=F12,F13-F12,0)*0.58 -> 6.96 | H13: =C13+E13+G13 -> 238.96 | O13: =IF(N13>=N12,N13-N12,0) -> 0 | Q13: =(H13-O13)*0.58 -> 138.5968 | S13: =IF(R13-R12>0,R13-R12,0) -> 0 | T13: =Elect!BM12 -> 62 | U13: =H13/T13 -> 3.8541935 | V13: =Elect!BO12 -> 0 | W13: =H13/V13 -> #DIV/0! | X13: =H13*V1 -> 955.84 | Y13: =IF(X13>0,X13/T13,0) -> 15.416774 | Z13: =IF(X13>0,X13/V13,0) -> #DIV/0!
A14: 8 | B14: 74315 | C14: =IF(B14>=B13,B14-B13,0)*10*0.58 -> 0 | D14: 154110 | E14: =IF(D14>=D13,D14-D13,0)*10*0.58 -> 185.6 | F14: 17396 | G14: =IF(F14>=F13,F14-F13,0)*0.58 -> 6.38 | H14: =C14+E14+G14 -> 191.98 | O14: =IF(N14>=N13,N14-N13,0) -> 0 | Q14: =(H14-O14)*0.58 -> 111.3484 | S14: =IF(R14-R13>0,R14-R13,0) -> 0 | T14: =Elect!BM13 -> 61 | U14: =H14/T14 -> 3.1472131 | V14: =Elect!BO13 -> 0 | W14: =H14/V14 -> #DIV/0! | X14: =H14*V1 -> 767.92 | Y14: =IF(X14>0,X14/T14,0) -> 12.588852 | Z14: =IF(X14>0,X14/V14,0) -> #DIV/0!
A15: 9 | B15: 74315 | C15: =IF(B15>=B14,B15-B14,0)*10*0.58 -> 0 | D15: 154163 | E15: =IF(D15>=D14,D15-D14,0)*10*0.58 -> 307.4 | F15: 17414 | G15: =IF(F15>=F14,F15-F14,0)*0.58 -> 10.44 | H15: =C15+E15+G15 -> 317.84 | O15: =IF(N15>=N14,N15-N14,0) -> 0 | Q15: =(H15-O15)*0.58 -> 184.3472 | S15: =IF(R15-R14>0,R15-R14,0) -> 0 | T15: =Elect!BM14 -> 59 | U15: =H15/T15 -> 5.3871186 | V15: =Elect!BO14 -> 0 | W15: =H15/V15 -> #DIV/0! | X15: =H15*V1 -> 1271.36 | Y15: =IF(X15>0,X15/T15,0) -> 21.548475 | Z15: =IF(X15>0,X15/V15,0) -> #DIV/0!
A16: 10 | B16: 74316 | C16: =IF(B16>=B15,B16-B15,0)*10*0.58 -> 5.8 | D16: 154216 | E16: =IF(D16>=D15,D16-D15,0)*10*0.58 -> 307.4 | F16: 17428 | G16: =IF(F16>=F15,F16-F15,0)*0.58 -> 8.12 | H16: =C16+E16+G16 -> 321.32 | O16: =IF(N16>=N15,N16-N15,0) -> 0 | Q16: =(H16-O16)*0.58 -> 186.3656 | S16: =IF(R16-R15>0,R16-R15,0) -> 0 | T16: =Elect!BM15 -> 82 | U16: =H16/T16 -> 3.9185366 | V16: =Elect!BO15 -> 0 | W16: =H16/V16 -> #DIV/0! | X16: =H16*V1 -> 1285.28 | Y16: =IF(X16>0,X16/T16,0) -> 15.674146 | Z16: =IF(X16>0,X16/V16,0) -> #DIV/0!
A17: 11 | B17: 74316 | C17: =IF(B17>=B16,B17-B16,0)*10*0.58 -> 0 | D17: 154265 | E17: =IF(D17>=D16,D17-D16,0)*10*0.58 -> 284.2 | F17: 17439 | G17: =IF(F17>=F16,F17-F16,0)*0.58 -> 6.38 | H17: =C17+E17+G17 -> 290.58 | O17: =IF(N17>=N16,N17-N16,0) -> 0 | Q17: =(H17-O17)*0.58 -> 168.5364 | S17: =IF(R17-R16>0,R17-R16,0) -> 0 | T17: =Elect!BM16 -> 35 | U17: =H17/T17 -> 8.3022857 | V17: =Elect!BO16 -> 0 | W17: =H17/V17 -> #DIV/0! | X17: =H17*V1 -> 1162.32 | Y17: =IF(X17>0,X17/T17,0) -> 33.209143 | Z17: =IF(X17>0,X17/V17,0) -> #DIV/0!
A18: 12 | B18: 74316 | C18: =IF(B18>=B17,B18-B17,0)*10*0.58 -> 0 | D18: 154306 | E18: =IF(D18>=D17,D18-D17,0)*10*0.58 -> 237.8 | F18: 17451 | G18: =IF(F18>=F17,F18-F17,0)*0.58 -> 6.96 | H18: =C18+E18+G18 -> 244.76 | O18: =IF(N18>=N17,N18-N17,0) -> 0 | Q18: =(H18-O18)*0.58 -> 141.9608 | S18: =IF(R18-R17>0,R18-R17,0) -> 0 | T18: =Elect!BM17 -> 36 | U18: =H18/T18 -> 6.7988889 | V18: =Elect!BO17 -> 0 | W18: =H18/V18 -> #DIV/0! | X18: =H18*V1 -> 979.04 | Y18: =IF(X18>0,X18/T18,0) -> 27.195556 | Z18: =IF(X18>0,X18/V18,0) -> #DIV/0!
A19: 13 | B19: 74317 | C19: =IF(B19>=B18,B19-B18,0)*10*0.58 -> 5.8 | D19: 154343 | E19: =IF(D19>=D18,D19-D18,0)*10*0.58 -> 214.6 | F19: 17463 | G19: =IF(F19>=F18,F19-F18,0)*0.58 -> 6.96 | H19: =C19+E19+G19 -> 227.36 | O19: =IF(N19>=N18,N19-N18,0) -> 0 | Q19: =(H19-O19)*0.58 -> 131.8688 | S19: =IF(R19-R18>0,R19-R18,0) -> 0 | T19: =Elect!BM18 -> 30 | U19: =H19/T19 -> 7.5786667 | V19: =Elect!BO18 -> 0 | W19: =H19/V19 -> #DIV/0! | X19: =H19*V1 -> 909.44 | Y19: =IF(X19>0,X19/T19,0) -> 30.314667 | Z19: =IF(X19>0,X19/V19,0) -> #DIV/0!
A20: 14 | B20: 74317 | C20: =IF(B20>=B19,B20-B19,0)*10*0.58 -> 0 | D20: 154393 | E20: =IF(D20>=D19,D20-D19,0)*10*0.58 -> 290 | F20: 17477 | G20: =IF(F20>=F19,F20-F19,0)*0.58 -> 8.12 | H20: =C20+E20+G20 -> 298.12 | O20: =IF(N20>=N19,N20-N19,0) -> 0 | Q20: =(H20-O20)*0.58 -> 172.9096 | S20: =IF(R20-R19>0,R20-R19,0) -> 0 | T20: =Elect!BM19 -> 43 | U20: =H20/T20 -> 6.9330233 | V20: =Elect!BO19 -> 0 | W20: =H20/V20 -> #DIV/0! | X20: =H20*V1 -> 1192.48 | Y20: =IF(X20>0,X20/T20,0) -> 27.732093 | Z20: =IF(X20>0,X20/V20,0) -> #DIV/0!
A21: 15 | B21: 74317 | C21: =IF(B21>=B20,B21-B20,0)*10*0.58 -> 0 | D21: 154438 | E21: =IF(D21>=D20,D21-D20,0)*10*0.58 -> 261 | F21: 17490 | G21: =IF(F21>=F20,F21-F20,0)*0.58 -> 7.54 | H21: =C21+E21+G21 -> 268.54 | O21: =IF(N21>=N20,N21-N20,0) -> 0 | Q21: =(H21-O21)*0.58 -> 155.7532 | S21: =IF(R21-R20>0,R21-R20,0) -> 0 | T21: =Elect!BM20 -> 65 | U21: =H21/T21 -> 4.1313846 | V21: =Elect!BO20 -> 0 | W21: =H21/V21 -> #DIV/0! | X21: =H21*V1 -> 1074.16 | Y21: =IF(X21>0,X21/T21,0) -> 16.525538 | Z21: =IF(X21>0,X21/V21,0) -> #DIV/0!
A22: 16 | B22: 74317 | C22: =IF(B22>=B21,B22-B21,0)*10*0.58 -> 0 | D22: 154478 | E22: =IF(D22>=D21,D22-D21,0)*10*0.58 -> 232 | F22: 17507 | G22: =IF(F22>=F21,F22-F21,0)*0.58 -> 9.86 | H22: =C22+E22+G22 -> 241.86 | O22: =IF(N22>=N21,N22-N21,0) -> 0 | Q22: =(H22-O22)*0.58 -> 140.2788 | S22: =IF(R22-R21>0,R22-R21,0) -> 0 | T22: =Elect!BM21 -> 55 | U22: =H22/T22 -> 4.3974545 | V22: =Elect!BO21 -> 0 | W22: =H22/V22 -> #DIV/0! | X22: =H22*V1 -> 967.44 | Y22: =IF(X22>0,X22/T22,0) -> 17.589818 | Z22: =IF(X22>0,X22/V22,0) -> #DIV/0!
A23: 17 | B23: 74317 | C23: =IF(B23>=B22,B23-B22,0)*10*0.58 -> 0 | D23: 154517 | E23: =IF(D23>=D22,D23-D22,0)*10*0.58 -> 226.2 | F23: 17520 | G23: =IF(F23>=F22,F23-F22,0)*0.58 -> 7.54 | H23: =C23+E23+G23 -> 233.74 | O23: =IF(N23>=N22,N23-N22,0) -> 0 | Q23: =(H23-O23)*0.58 -> 135.5692 | S23: =IF(R23-R22>0,R23-R22,0) -> 0 | T23: =Elect!BM22 -> 60 | U23: =H23/T23 -> 3.8956667 | V23: =Elect!BO22 -> 0 | W23: =H23/V23 -> #DIV/0! | X23: =H23*V1 -> 934.96 | Y23: =IF(X23>0,X23/T23,0) -> 15.582667 | Z23: =IF(X23>0,X23/V23,0) -> #DIV/0!
A24: 18 | B24: 74318 | C24: =IF(B24>=B23,B24-B23,0)*10*0.58 -> 5.8 | D24: 154555 | E24: =IF(D24>=D23,D24-D23,0)*10*0.58 -> 220.4 | F24: 17533 | G24: =IF(F24>=F23,F24-F23,0)*0.58 -> 7.54 | H24: =C24+E24+G24 -> 233.74 | O24: =IF(N24>=N23,N24-N23,0) -> 0 | Q24: =(H24-O24)*0.58 -> 135.5692 | S24: =IF(R24-R23>0,R24-R23,0) -> 0 | T24: =Elect!BM23 -> 44 | U24: =H24/T24 -> 5.3122727 | V24: =Elect!BO23 -> 0 | W24: =H24/V24 -> #DIV/0! | X24: =H24*V1 -> 934.96 | Y24: =IF(X24>0,X24/T24,0) -> 21.249091 | Z24: =IF(X24>0,X24/V24,0) -> #DIV/0!
A25: 19 | B25: 74318 | C25: =IF(B25>=B24,B25-B24,0)*10*0.58 -> 0 | D25: 154597 | E25: =IF(D25>=D24,D25-D24,0)*10*0.58 -> 243.6 | F25: 17547 | G25: =IF(F25>=F24,F25-F24,0)*0.58 -> 8.12 | H25: =C25+E25+G25 -> 251.72 | O25: =IF(N25>=N24,N25-N24,0) -> 0 | Q25: =(H25-O25)*0.58 -> 145.9976 | S25: =IF(R25-R24>0,R25-R24,0) -> 0 | T25: =Elect!BM24 -> 51 | U25: =H25/T25 -> 4.9356863 | V25: =Elect!BO24 -> 0 | W25: =H25/V25 -> #DIV/0! | X25: =H25*V1 -> 1006.88 | Y25: =IF(X25>0,X25/T25,0) -> 19.742745 | Z25: =IF(X25>0,X25/V25,0) -> #DIV/0!
A26: 20 | B26: 74318 | C26: =IF(B26>=B25,B26-B25,0)*10*0.58 -> 0 | D26: 154640 | E26: =IF(D26>=D25,D26-D25,0)*10*0.58 -> 249.4 | F26: 17561 | G26: =IF(F26>=F25,F26-F25,0)*0.58 -> 8.12 | H26: =C26+E26+G26 -> 257.52 | O26: =IF(N26>=N25,N26-N25,0) -> 0 | Q26: =(H26-O26)*0.58 -> 149.3616 | S26: =IF(R26-R25>0,R26-R25,0) -> 0 | T26: =Elect!BM25 -> 48 | U26: =H26/T26 -> 5.365 | V26: =Elect!BO25 -> 0 | W26: =H26/V26 -> #DIV/0! | X26: =H26*V1 -> 1030.08 | Y26: =IF(X26>0,X26/T26,0) -> 21.46 | Z26: =IF(X26>0,X26/V26,0) -> #DIV/0!
A27: 21 | B27: 74319 | C27: =IF(B27>=B26,B27-B26,0)*10*0.58 -> 5.8 | D27: 154686 | E27: =IF(D27>=D26,D27-D26,0)*10*0.58 -> 266.8 | F27: 17573 | G27: =IF(F27>=F26,F27-F26,0)*0.58 -> 6.96 | H27: =C27+E27+G27 -> 279.56 | O27: =IF(N27>=N26,N27-N26,0) -> 0 | Q27: =(H27-O27)*0.58 -> 162.1448 | S27: =IF(R27-R26>0,R27-R26,0) -> 0 | T27: =Elect!BM26 -> 50 | U27: =H27/T27 -> 5.5912 | V27: =Elect!BO26 -> 0 | W27: =H27/V27 -> #DIV/0! | X27: =H27*V1 -> 1118.24 | Y27: =IF(X27>0,X27/T27,0) -> 22.3648 | Z27: =IF(X27>0,X27/V27,0) -> #DIV/0!
A28: 22 | B28: 74319 | C28: =IF(B28>=B27,B28-B27,0)*10*0.58 -> 0 | D28: 154731 | E28: =IF(D28>=D27,D28-D27,0)*10*0.58 -> 261 | F28: 17590 | G28: =IF(F28>=F27,F28-F27,0)*0.58 -> 9.86 | H28: =C28+E28+G28 -> 270.86 | O28: =IF(N28>=N27,N28-N27,0) -> 0 | Q28: =(H28-O28)*0.58 -> 157.0988 | S28: =IF(R28-R27>0,R28-R27,0) -> 0 | T28: =Elect!BM27 -> 54 | U28: =H28/T28 -> 5.0159259 | V28: =Elect!BO27 -> 0 | W28: =H28/V28 -> #DIV/0! | X28: =H28*V1 -> 1083.44 | Y28: =IF(X28>0,X28/T28,0) -> 20.063704 | Z28: =IF(X28>0,X28/V28,0) -> #DIV/0!
A29: 23 | B29: 74319 | C29: =IF(B29>=B28,B29-B28,0)*10*0.58 -> 0 | D29: 154768 | E29: =IF(D29>=D28,D29-D28,0)*10*0.58 -> 214.6 | F29: 17604 | G29: =IF(F29>=F28,F29-F28,0)*0.58 -> 8.12 | H29: =C29+E29+G29 -> 222.72 | O29: =IF(N29>=N28,N29-N28,0) -> 0 | Q29: =(H29-O29)*0.58 -> 129.1776 | S29: =IF(R29-R28>0,R29-R28,0) -> 0 | T29: =Elect!BM28 -> 44 | U29: =H29/T29 -> 5.0618182 | V29: =Elect!BO28 -> 0 | W29: =H29/V29 -> #DIV/0! | X29: =H29*V1 -> 890.88 | Y29: =IF(X29>0,X29/T29,0) -> 20.247273 | Z29: =IF(X29>0,X29/V29,0) -> #DIV/0!
A30: 24 | B30: 74319 | C30: =IF(B30>=B29,B30-B29,0)*10*0.58 -> 0 | D30: 154801 | E30: =IF(D30>=D29,D30-D29,0)*10*0.58 -> 191.4 | F30: 17654 | G30: =IF(F30>=F29,F30-F29,0)*0.58 -> 29 | H30: =C30+E30+G30 -> 220.4 | O30: =IF(N30>=N29,N30-N29,0) -> 0 | Q30: =(H30-O30)*0.58 -> 127.832 | S30: =IF(R30-R29>0,R30-R29,0) -> 0 | T30: =Elect!BM29 -> 41 | U30: =H30/T30 -> 5.3756098 | V30: =Elect!BO29 -> 0 | W30: =H30/V30 -> #DIV/0! | X30: =H30*V1 -> 881.6 | Y30: =IF(X30>0,X30/T30,0) -> 21.502439 | Z30: =IF(X30>0,X30/V30,0) -> #DIV/0!
A31: 25 | B31: 74319 | C31: =IF(B31>=B30,B31-B30,0)*10*0.58 -> 0 | D31: 154832 | E31: =IF(D31>=D30,D31-D30,0)*10*0.58 -> 179.8 | F31: 17670 | G31: =IF(F31>=F30,F31-F30,0)*0.58 -> 9.28 | H31: =C31+E31+G31 -> 189.08 | O31: =IF(N31>=N30,N31-N30,0) -> 0 | Q31: =(H31-O31)*0.58 -> 109.6664 | S31: =IF(R31-R30>0,R31-R30,0) -> 0 | T31: =Elect!BM30 -> 37 | U31: =H31/T31 -> 5.1102703 | V31: =Elect!BO30 -> 0 | W31: =H31/V31 -> #DIV/0! | X31: =H31*V1 -> 756.32 | Y31: =IF(X31>0,X31/T31,0) -> 20.441081 | Z31: =IF(X31>0,X31/V31,0) -> #DIV/0!
A32: 26 | B32: 74319 | C32: =IF(B32>=B31,B32-B31,0)*10*0.58 -> 0 | D32: 154872 | E32: =IF(D32>=D31,D32-D31,0)*10*0.58 -> 232 | F32: 17670 | G32: =IF(F32>=F31,F32-F31,0)*0.58 -> 0 | H32: =C32+E32+G32 -> 232 | O32: =IF(N32>=N31,N32-N31,0) -> 0 | Q32: =(H32-O32)*0.58 -> 134.56 | S32: =IF(R32-R31>0,R32-R31,0) -> 0 | T32: =Elect!BM31 -> 29 | U32: =H32/T32 -> 8 | V32: =Elect!BO31 -> 0 | W32: =H32/V32 -> #DIV/0! | X32: =H32*V1 -> 928 | Y32: =IF(X32>0,X32/T32,0) -> 32 | Z32: =IF(X32>0,X32/V32,0) -> #DIV/0!
A33: 27 | B33: 74320 | C33: =IF(B33>=B32,B33-B32,0)*10*0.58 -> 5.8 | D33: 154924 | E33: =IF(D33>=D32,D33-D32,0)*10*0.58 -> 301.6 | F33: 17670 | G33: =IF(F33>=F32,F33-F32,0)*0.58 -> 0 | H33: =C33+E33+G33 -> 307.4 | O33: =IF(N33>=N32,N33-N32,0) -> 0 | Q33: =(H33-O33)*0.58 -> 178.292 | S33: =IF(R33-R32>0,R33-R32,0) -> 0 | T33: =Elect!BM32 -> 23 | U33: =H33/T33 -> 13.365217 | V33: =Elect!BO32 -> 0 | W33: =H33/V33 -> #DIV/0! | X33: =H33*V1 -> 1229.6 | Y33: =IF(X33>0,X33/T33,0) -> 53.46087 | Z33: =IF(X33>0,X33/V33,0) -> #DIV/0!
A34: 28 | B34: 74320 | C34: =IF(B34>=B33,B34-B33,0)*10*0.58 -> 0 | D34: 154975 | E34: =IF(D34>=D33,D34-D33,0)*10*0.58 -> 295.8 | F34: 17670 | G34: =IF(F34>=F33,F34-F33,0)*0.58 -> 0 | H34: =C34+E34+G34 -> 295.8 | O34: =IF(N34>=N33,N34-N33,0) -> 0 | Q34: =(H34-O34)*0.58 -> 171.564 | S34: =IF(R34-R33>0,R34-R33,0) -> 0 | T34: =Elect!BM33 -> 33 | U34: =H34/T34 -> 8.9636364 | V34: =Elect!BO33 -> 0 | W34: =H34/V34 -> #DIV/0! | X34: =H34*V1 -> 1183.2 | Y34: =IF(X34>0,X34/T34,0) -> 35.854545 | Z34: =IF(X34>0,X34/V34,0) -> #DIV/0!
A35: 29 | B35: 74320 | C35: =IF(B35>=B34,B35-B34,0)*10*0.58 -> 0 | D35: 155005 | E35: =IF(D35>=D34,D35-D34,0)*10*0.58 -> 174 | F35: 17670 | G35: =IF(F35>=F34,F35-F34,0)*0.58 -> 0 | H35: =C35+E35+G35 -> 174 | O35: =IF(N35>=N34,N35-N34,0) -> 0 | Q35: =(H35-O35)*0.58 -> 100.92 | S35: =IF(R35-R34>0,R35-R34,0) -> 0 | T35: =Elect!BM34 -> 34 | U35: =H35/T35 -> 5.1176471 | V35: =Elect!BO34 -> 0 | W35: =H35/V35 -> #DIV/0! | X35: =H35*V1 -> 696 | Y35: =IF(X35>0,X35/T35,0) -> 20.470588 | Z35: =IF(X35>0,X35/V35,0) -> #DIV/0!
A36: 30 | B36: 74321 | C36: =IF(B36>=B35,B36-B35,0)*10*0.58 -> 5.8 | D36: 155056 | E36: =IF(D36>=D35,D36-D35,0)*10*0.58 -> 295.8 | F36: 17670 | G36: =IF(F36>=F35,F36-F35,0)*0.58 -> 0 | H36: =C36+E36+G36 -> 301.6 | O36: =IF(N36>=N35,N36-N35,0) -> 0 | Q36: =(H36-O36)*0.58 -> 174.928 | S36: =IF(R36-R35>0,R36-R35,0) -> 0 | T36: =Elect!BM35 -> 32 | U36: =H36/T36 -> 9.425 | V36: =Elect!BO35 -> 0 | W36: =H36/V36 -> #DIV/0! | X36: =H36*V1 -> 1206.4 | Y36: =IF(X36>0,X36/T36,0) -> 37.7 | Z36: =IF(X36>0,X36/V36,0) -> #DIV/0!
A37: 31 | B37: 74321 | C37: =IF(B37>=B36,B37-B36,0)*10*0.58 -> 0 | D37: 155092 | E37: =IF(D37>=D36,D37-D36,0)*10*0.58 -> 208.8 | F37: 17670 | G37: =IF(F37>=F36,F37-F36,0)*0.58 -> 0 | H37: =C37+E37+G37 -> 208.8 | I37: 211 | K37: 2887 | O37: =IF(N37>=N36,N37-N36,0) -> 0 | Q37: =(H37-O37)*0.58 -> 121.104 | S37: =IF(R37-R36>0,R37-R36,0) -> 0 | T37: =Elect!BM36 -> 33 | U37: =H37/T37 -> 6.3272727 | V37: =Elect!BO36 -> 0 | W37: =H37/V37 -> #DIV/0! | X37: =H37*V7 -> 0 | Y37: =IF(X37>0,X37/T37,0) -> 0 | Z37: =IF(X37>0,X37/V37,0) -> 0
A38: MTD | C38: =SUM(C7:C37) -> 46.4 | E38: =SUM(E7:E37) -> 7250 | G38: =SUM(G7:G37) -> 222.72 | H38: =SUM(H7:H37) -> 7519.12 | I38: =I37-I6 -> 1 | K38: =K37-K6 -> 62 | O38: =SUM(O7:O36) -> 0 | Q38: =SUM(Q7:Q34) -> 3964.1376 | S38: =SUM(S7:S34) -> 0 | T38: =SUM(T7:T36) -> 1431 | U38: =IF(H38>0,H38/T38,0) -> 5.2544514 | V38: =SUM(V7:V36) -> 0 | W38: =IF(H38>0,H38/V38,0) -> #DIV/0! | X38: =SUM(X7:X36) -> 29241.28 | Y38: =IF(X38>0,X38/T38,0) -> 20.434158 | Z38: =IF(X38>0,X38/V38,0) -> #DIV/0!
A39: AVER. Act | C39: =C38/B48 -> 1.5466667 | E39: =E38/B48 -> 241.66667 | G39: =G38/B48 -> 7.424 | H39: =H38/B48 -> 250.63733 | O39: =O38/B48 -> 0 | Q39: =Q38/B48 -> 132.13792 | S39: =S38/C48 -> #DIV/0! | T39: =T38/B48 -> 47.7 | U39: =IF(H39>0,H39/T39,0) -> 5.2544514 | V39: =V38/B48 -> 0 | W39: =IF(H39>0,H39/V39,0) -> #DIV/0! | X39: =X38/B48 -> 974.70933 | Y39: =IF(X39>0,X39/T39,0) -> 20.434158 | Z39: =IF(X39>0,X39/V39,0) -> #DIV/0!
A40: TOTAL Budget | T40: =YTD!Q2341 -> 0 | U40: =IF(#REF!>0,#REF!/T40,0) -> #REF! | V40: =YTD!Q2342 -> 0 | W40: =IF(#REF!>0,#REF!/V40,0) -> #REF! | X40: =YTD!Q2346 -> 0 | Y40: =IF(X40>0,X40/T40,0) -> 0 | Z40: =IF(X40>0,X40/V40,0) -> 0
A41: Budget MTD | T41: =T42*C48 -> #VALUE! | U41: =IF(#REF!>0,#REF!/T41,0) -> #REF! | V41: =V42*C48 -> #VALUE! | W41: =IF(#REF!>0,#REF!/V41,0) -> #REF! | X41: =#REF!*5.62 -> #REF! | Y41: =IF(X41>0,X41/T41,0) -> #REF! | Z41: =IF(X41>0,X41/V41,0) -> #REF!
A42: AVER. Bud | T42: =T40/$A$48 -> #VALUE! | V42: =V40/$A$48 -> #VALUE!
A43: Total RFC | T43: =YTD!Q2358 -> 0 | V43: =YTD!Q2359 -> 0 | X43: =YTD!Q2363 -> 0 | Y43: =IF(X43>0,X43/T43,0) -> 0 | Z43: =IF(X43>0,X43/V43,0) -> 0
A44: RFC MTD | T44: =T43/A48*C48 -> #VALUE! | V44: =V43/A48*C48 -> #VALUE! | X44: =X43/A48*C48 -> #VALUE! | Y44: =IF(X44>0,X44/T44,0) -> #VALUE! | Z44: =IF(X44>0,X44/V44,0) -> #VALUE!
A45: AVER RFC | T45: =T43/A48 -> #VALUE! | V45: =V44/A48*C48 -> #VALUE! | X45: =X43/A48 -> #VALUE!
A46: MTD 13 | U46: =Consp!BH33 -> 1.1514679 | W46: =Consp!BI33 -> 0.57929342 | X46: =Consp!BJ33 -> 140121.3 | Y46: =Consp!BK33 -> 6.8331854 | Z46: =Consp!BL33 -> 3.4377159
A47: AVER. Act 13 | U47: =Consp!BH34 -> 1.1761372 | W47: =Consp!BI34 -> 0.60007377 | X47: =Consp!BJ34 -> 5004.3322 | Y47: =Consp!BK34 -> 6.8331854 | Z47: =Consp!BL34 -> 3.4377159
A48: No of Days MTD | B48: =COUNTIF(B7:B36,">0") -> 30
A136: Water Incoming

Sheet Consp
A1: =Elect!A1 -> January | L1: Summary | P1: =Elect!A1 -> January
B2: Elect Consuumption | H2: Water Incoming | U2: Water Consumption | AC2: Irrigation | AG2: Gas | AJ2: Cost | AK2: Solar Meter [ LIT ] | AL2: No. of Eng. | AM2: No. of Gardners | AN2: Cons. (lit) | AO2: Received Gas (tons) | AP2: Fuel Cost | AQ2: Solar level [cm] | AR2: Received Solar (tons) | AS2: Fuel Cost | AT2: Occupancy 10 | AV2: Occupancy07 | AZ2: Elect 2009 | BE2: Elect 2010 | BJ2: Water 2009 | BO2: Water 2010
A3: Date | B3: COUNTER (2) | D3: MD | F3: KVAR | H3: R.O | J3: Qenna | L3: Trucks | N3: Rimievera Line Meter | O3: Total Inc. | Q3: Total Main S.Pool | S3: Total Bar & Beach cons. | U3: Total S. Pool cons. | W3: Hotel consumption. | Y3: Sold Water | AA3: Irr. Water from R.O | AC3: Irr. Consumption. | AE3: Storage Water One tank | AF3: Grand Cons | AG3: % | AH3: Stock | AI3: Cons. | AJ3: 0 | AT3: No of guest | AU3: No. of rooms | AV3: No. of rooms | AW3: No. of guest | AX3: Cons. Per occ. room | AY3: Cons. Per guest | AZ3: Total cost | BA3: cost per room | BB3: cost per guest | BC3: Cons. Per occ. room | BD3: Cons. Per guest | BE3: Total cost | BF3: cost per room | BG3: cost per guest | BH3: Cons. Per occ. room | BI3: Cons. Per guest | BJ3: Total cost | BK3: cost per room | BL3: cost per guest | BM3: Cons. Per occ. room | BN3: Cons. Per guest | BO3: Total cost | BP3: cost per room | BQ3: cost per guest
B4: 2013 | C4: 2014 | D4: 2013 | E4: 2014 | F4: 2013 | G4: 2014 | H4: 2013 | I4: 2014 | J4: 2009 | K4: 2010 | L4: 2009 | M4: 2010 | O4: 2009 | P4: 2010 | Q4: 2009 | R4: 2010 | S4: 2009 | T4: 2010 | U4: 2009 | V4: 2010 | W4: 2009 | X4: 2010 | Y4: 2009 | Z4: 2010 | AA4: 2009 | AB4: 2010 | AC4: 2009 | AD4: 2010
A5: 1 | B5: 33600 | C5: =Elect!J6 -> 4287 | D5: 0 | E5: =Elect!M6 -> 1381 | F5: 20 | G5: =Elect!O6 -> 1441 | H5: 800 | I5: =Water!C7 -> 0 | J5: 0 | K5: =Water!E7 -> 237.8 | L5: 0 | M5: =Water!#REF! -> #REF! | N5: =Water!#REF! -> #REF! | O5: 1005 | P5: =Water!H7 -> 245.34 | Q5: 114 | R5: =Water!O7 -> 0 | S5: 13 | T5: =Water!#REF! -> #REF! | U5: 147 | V5: =Water!#REF! -> #REF! | W5: 755 | X5: =Water!Q7 -> 142.2972 | Y5: 0 | Z5: =Water!#REF! -> #REF! | AA5: 0 | AB5: 0 | AC5: 690 | AD5: =Water!#REF! -> #REF! | AE5: =Water!#REF! -> #REF! | AF5: =Water!#REF! -> #REF! | AG5: =Gas!#REF! -> #REF! | AH5: =Gas!C7 -> 894.64 | AI5: =Gas!#REF! -> #REF! | AJ5: =Gas!J7 -> 269.1 | AK5: =Gas!#REF! -> #REF! | AL5: =Gas!#REF! -> #REF! | AM5: =Gas!#REF! -> #REF! | AN5: =Gas!#REF! -> #REF! | AO5: =Gas!#REF! -> #REF! | AP5: =Gas!#REF! -> #REF! | AQ5: =Gas!#REF! -> #REF! | AR5: =Gas!#REF! -> #REF! | AS5: =Gas!#REF! -> #REF! | AT5: =Elect!BK6 -> 186 | AU5: =Elect!BI6 -> 111 | AV5: =Elect!#REF! -> #REF! | AW5: =Elect!BK6 -> 186 | AX5: 48.695652 | AY5: 24.705882 | AZ5: 8835.4834 | BA5: 12.805048 | BB5: 6.496679 | BC5: =Elect!#REF! -> #REF! | BD5: =Elect!#REF! -> #REF! | BE5: =Elect!#REF! -> #REF! | BF5: =Elect!#REF! -> #REF! | BG5: =Elect!#REF! -> #REF! | BH5: 1.142029 | BI5: 0.57941176 | BJ5: 4569.1158 | BK5: 6.6219069 | BL5: 3.3596439 | BM5: =Water!U7 -> 3.3608219 | BN5: =Water!W7 -> #DIV/0! | BO5: =Water!X7 -> 981.36 | BP5: =Water!Y7 -> 13.443288 | BQ5: =Water!Z7 -> 0
A6: 2 | B6: 31200 | C6: =Elect!J7 -> 4841 | D6: 0 | E6: =Elect!M7 -> 1511 | F6: 20 | G6: =Elect!O7 -> 1587 | H6: 936 | I6: =Water!C8 -> 0 | J6: 0 | K6: =Water!E8 -> 150.8 | L6: 0 | M6: =Water!#REF! -> #REF! | N6: =Water!#REF! -> #REF! | O6: 1006 | P6: =Water!H8 -> 162.98 | Q6: 113 | R6: =Water!O8 -> 0 | S6: 17 | T6: =Water!#REF! -> #REF! | U6: 140 | V6: =Water!#REF! -> #REF! | W6: 792 | X6: =Water!Q8 -> 94.5284 | Y6: 0 | Z6: =Water!#REF! -> #REF! | AA6: 0 | AB6: 0 | AC6: 370 | AD6: =Water!#REF! -> #REF! | AE6: =Water!#REF! -> #REF! | AF6: =Water!#REF! -> #REF! | AG6: =Gas!B7 -> 7949568 | AH6: =Gas!C8 -> 1228.54 | AI6: =Gas!#REF! -> #REF! | AJ6: =Gas!J8 -> 249.6 | AK6: =Gas!#REF! -> #REF! | AL6: =Gas!#REF! -> #REF! | AM6: =Gas!#REF! -> #REF! | AN6: =Gas!#REF! -> #REF! | AO6: =Gas!#REF! -> #REF! | AP6: =Gas!#REF! -> #REF! | AQ6: =Gas!#REF! -> #REF! | AR6: =Gas!#REF! -> #REF! | AS6: =Gas!#REF! -> #REF! | AT6: =Elect!BK7 -> 100 | AU6: =Elect!BI7 -> 50 | AX6: 47.416413 | AY6: 23.981553 | AZ6: 8299.2754 | BA6: 12.612881 | BB6: 6.379151 | BC6: =Elect!BJ7 -> 446500 | BD6: =Elect!#REF! -> #REF! | BE6: =Elect!#REF! -> #REF! | BF6: =Elect!#REF! -> #REF! | BG6: =Elect!#REF! -> #REF! | BH6: 1.2021277 | BI6: 0.60799385 | BJ6: 5345.8654 | BK6: 8.1244156 | BL6: 4.1090434 | BM6: =Water!U8 -> 3.0181481 | BN6: =Water!W8 -> #DIV/0! | BO6: =Water!X8 -> 651.92 | BP6: =Water!Y8 -> 12.072593 | BQ6: =Water!Z8 -> #DIV/0!
A7: 3 | B7: 31200 | C7: =Elect!J8 -> 4443 | D7: 0 | E7: =Elect!M8 -> 1305 | F7: 20 | G7: =Elect!O8 -> 1497 | H7: 685 | I7: =Water!C9 -> 5.8 | J7: 0 | K7: =Water!E9 -> 185.6 | L7: 0 | M7: =Water!#REF! -> #REF! | N7: =Water!#REF! -> #REF! | O7: 902 | P7: =Water!H9 -> 201.84 | Q7: 126 | R7: =Water!O9 -> 0 | S7: 26 | T7: =Water!#REF! -> #REF! | U7: 134 | V7: =Water!#REF! -> #REF! | W7: 766 | X7: =Water!Q9 -> 117.0672 | Y7: 0 | Z7: =Water!#REF! -> #REF! | AA7: 0 | AB7: 0 | AC7: 740 | AD7: =Water!#REF! -> #REF! | AE7: =Water!#REF! -> #REF! | AF7: =Water!#REF! -> #REF! | AG7: =Gas!B9 -> 7951694 | AH7: =Gas!C9 -> 1025.02 | AI7: =Gas!#REF! -> #REF! | AJ7: =Gas!J9 -> 261.3 | AK7: =Gas!#REF! -> #REF! | AL7: =Gas!#REF! -> #REF! | AM7: =Gas!#REF! -> #REF! | AN7: =Gas!#REF! -> #REF! | AO7: =Gas!#REF! -> #REF! | AP7: =Gas!#REF! -> #REF! | AQ7: =Gas!#REF! -> #REF! | AR7: =Gas!#REF! -> #REF! | AS7: =Gas!#REF! -> #REF! | AT7: =Elect!BK8 -> 91 | AU7: =Elect!BI8 -> 61 | AX7: 47.926267 | AY7: 24.223602 | AZ7: 8299.2754 | BA7: 12.748503 | BB7: 6.4435368 | BC7: =Elect!BJ8 -> 446591 | BD7: =Elect!#REF! -> #REF! | BE7: =Elect!#REF! -> #REF! | BF7: =Elect!#REF! -> #REF! | BG7: =Elect!#REF! -> #REF! | BH7: 1.0875576 | BI7: 0.54968944 | BJ7: 3912.3054 | BK7: 6.0096857 | BL7: 3.0375042 | BM7: =Water!U9 -> 4.6939535 | BN7: =Water!W9 -> #DIV/0! | BO7: =Water!X9 -> 807.36 | BP7: =Water!Y9 -> 18.775814 | BQ7: =Water!Z9 -> #DIV/0!
A8: 4 | B8: 33600 | C8: =Elect!J9 -> 4708 | D8: 0 | E8: =Elect!M9 -> 1410 | F8: 20 | G8: =Elect!O9 -> 1764 | H8: 786 | I8: =Water!C10 -> 0 | J8: 0 | K8: =Water!E10 -> 174 | L8: 0 | M8: =Water!#REF! -> #REF! | N8: =Water!#REF! -> #REF! | O8: 930 | P8: =Water!H10 -> 178.64 | Q8: 153 | R8: =Water!O10 -> 0 | S8: 46 | T8: =Water!#REF! -> #REF! | U8: 150 | V8: =Water!#REF! -> #REF! | W8: 766 | X8: =Water!Q10 -> 103.6112 | Y8: 0 | Z8: =Water!#REF! -> #REF! | AA8: 0 | AB8: 0 | AC8: 820 | AD8: =Water!#REF! -> #REF! | AE8: =Water!#REF! -> #REF! | AF8: =Water!#REF! -> #REF! | AG8: =Gas!B10 -> 7952355 | AH8: =Gas!C10 -> 700.66 | AI8: =Gas!#REF! -> #REF! | AJ8: =Gas!J10 -> 276.9 | AK8: =Gas!#REF! -> #REF! | AL8: =Gas!#REF! -> #REF! | AM8: =Gas!#REF! -> #REF! | AN8: =Gas!#REF! -> #REF! | AO8: =Gas!#REF! -> #REF! | AP8: =Gas!#REF! -> #REF! | AQ8: =Gas!#REF! -> #REF! | AR8: =Gas!#REF! -> #REF! | AS8: =Gas!#REF! -> #REF! | AT8: =Elect!BK9 -> 225 | AU8: =Elect!BI9 -> 120 | AX8: 51.06383 | AY8: 25.866051 | AZ8: 8835.4834 | BA8: 13.427786 | BB8: 6.8017578 | BC8: =Elect!BJ9 -> 446816 | BD8: =Elect!#REF! -> #REF! | BE8: =Elect!#REF! -> #REF! | BF8: =Elect!#REF! -> #REF! | BG8: =Elect!#REF! -> #REF! | BH8: 1.2218845 | BI8: 0.61893764 | BJ8: 4489.1562 | BK8: 6.8224259 | BL8: 3.4558555 | BM8: =Water!U10 -> 3.5728 | BN8: =Water!W10 -> #DIV/0! | BO8: =Water!X10 -> 714.56 | BP8: =Water!Y10 -> 14.2912 | BQ8: =Water!Z10 -> #DIV/0!
A9: 5 | B9: 31200 | C9: =Elect!J10 -> 4642 | D9: 0 | E9: =Elect!M10 -> 1175 | F9: 20 | G9: =Elect!O10 -> 1525 | H9: 789 | I9: =Water!C11 -> 0 | J9: 0 | K9: =Water!E11 -> 232 | L9: 0 | M9: =Water!#REF! -> #REF! | N9: =Water!#REF! -> #REF! | O9: 1003 | P9: =Water!H11 -> 240.7 | Q9: 102 | R9: =Water!O11 -> 0 | S9: 8 | T9: =Water!#REF! -> #REF! | U9: 130 | V9: =Water!#REF! -> #REF! | W9: 735 | X9: =Water!Q11 -> 139.606 | Y9: 0 | Z9: =Water!#REF! -> #REF! | AA9: 0 | AB9: 0 | AC9: 640 | AD9: =Water!#REF! -> #REF! | AE9: =Water!#REF! -> #REF! | AF9: =Water!#REF! -> #REF! | AG9: =Gas!B11 -> 7953465 | AH9: =Gas!C11 -> 1176.6 | AI9: =Gas!#REF! -> #REF! | AJ9: =Gas!J11 -> 319.8 | AK9: =Gas!#REF! -> #REF! | AL9: =Gas!#REF! -> #REF! | AM9: =Gas!#REF! -> #REF! | AN9: =Gas!#REF! -> #REF! | AO9: =Gas!#REF! -> #REF! | AP9: =Gas!#REF! -> #REF! | AQ9: =Gas!#REF! -> #REF! | AR9: =Gas!#REF! -> #REF! | AS9: =Gas!#REF! -> #REF! | AT9: =Elect!BK10 -> 229 | AU9: =Elect!BI10 -> 114 | AX9: 49.840256 | AY9: 25.181598 | AZ9: 8299.2754 | BA9: 13.257628 | BB9: 6.698366 | BC9: =Elect!BJ10 -> 447045 | BD9: =Elect!#REF! -> #REF! | BE9: =Elect!#REF! -> #REF! | BF9: =Elect!#REF! -> #REF! | BG9: =Elect!#REF! -> #REF! | BH9: 1.1980831 | BI9: 0.60532688 | BJ9: 4506.2904 | BK9: 7.198547 | BL9: 3.6370383 | BM9: =Water!U11 -> 4.5415094 | BN9: =Water!W11 -> #DIV/0! | BO9: =Water!X11 -> 962.8 | BP9: =Water!Y11 -> 18.166038 | BQ9: =Water!Z11 -> #DIV/0!
A10: 6 | B10: 33600 | C10: =Elect!J11 -> 5488 | D10: 0 | E10: =Elect!M11 -> 1235 | F10: 20 | G10: =Elect!O11 -> 1621 | H10: 805 | I10: =Water!C12 -> 5.8 | J10: 0 | K10: =Water!E12 -> 156.6 | L10: 0 | M10: =Water!#REF! -> #REF! | N10: =Water!#REF! -> #REF! | O10: 1004 | P10: =Water!H12 -> 169.36 | Q10: 115 | R10: =Water!O12 -> 0 | S10: 21 | T10: =Water!#REF! -> #REF! | U10: 141 | V10: =Water!#REF! -> #REF! | W10: 725 | X10: =Water!Q12 -> 98.2288 | Y10: 0 | Z10: =Water!#REF! -> #REF! | AA10: 0 | AB10: 0 | AC10: 510 | AD10: =Water!#REF! -> #REF! | AE10: =Water!#REF! -> #REF! | AF10: =Water!#REF! -> #REF! | AG10: =Gas!B12 -> 7954392 | AH10: =Gas!C12 -> 982.62 | AI10: =Gas!#REF! -> #REF! | AJ10: =Gas!J12 -> 237.9 | AK10: =Gas!#REF! -> #REF! | AL10: =Gas!#REF! -> #REF! | AM10: =Gas!#REF! -> #REF! | AN10: =Gas!#REF! -> #REF! | AO10: =Gas!#REF! -> #REF! | AP10: =Gas!#REF! -> #REF! | AQ10: =Gas!#REF! -> #REF! | AR10: =Gas!#REF! -> #REF! | AS10: =Gas!#REF! -> #REF! | AT10: =Elect!BK11 -> 210 | AU10: =Elect!BI11 -> 97 | AX10: 47.457627 | AY10: 23.512946 | AZ10: 8835.4834 | BA10: 12.479496 | BB10: 6.1829835 | BC10: =Elect!BJ11 -> 447255 | BD10: =Elect!#REF! -> #REF! | BE10: =Elect!#REF! -> #REF! | BF10: =Elect!#REF! -> #REF! | BG10: =Elect!#REF! -> #REF! | BH10: 1.1567797 | BI10: 0.57312806 | BJ10: 4597.6727 | BK10: 6.4938881 | BL10: 3.2174057 | BM10: =Water!U12 -> 3.3872 | BN10: =Water!W12 -> #DIV/0! | BO10: =Water!X12 -> 677.44 | BP10: =Water!Y12 -> 13.5488 | BQ10: =Water!Z12 -> #DIV/0!
A11: 7 | B11: 31200 | C11: =Elect!J12 -> 4353 | D11: 0 | E11: =Elect!M12 -> 1606 | F11: 20 | G11: =Elect!O12 -> 1996 | H11: 871 | I11: =Water!C13 -> 0 | J11: 0 | K11: =Water!E13 -> 232 | L11: 0 | M11: =Water!#REF! -> #REF! | N11: =Water!#REF! -> #REF! | O11: 837 | P11: =Water!H13 -> 238.96 | Q11: 113 | R11: =Water!O13 -> 0 | S11: 1 | T11: =Water!#REF! -> #REF! | U11: 151 | V11: =Water!#REF! -> #REF! | W11: 732 | X11: =Water!Q13 -> 138.5968 | Y11: 0 | Z11: =Water!#REF! -> #REF! | AA11: 0 | AB11: 0 | AC11: 1010 | AD11: =Water!#REF! -> #REF! | AE11: =Water!#REF! -> #REF! | AF11: =Water!#REF! -> #REF! | AG11: =Gas!B13 -> 7955256 | AH11: =Gas!C13 -> 915.84 | AI11: =Gas!#REF! -> #REF! | AJ11: =Gas!J13 -> 210.6 | AK11: =Gas!#REF! -> #REF! | AL11: =Gas!#REF! -> #REF! | AM11: =Gas!#REF! -> #REF! | AN11: =Gas!#REF! -> #REF! | AO11: =Gas!#REF! -> #REF! | AP11: =Gas!#REF! -> #REF! | AQ11: =Gas!#REF! -> #REF! | AR11: =Gas!#REF! -> #REF! | AS11: =Gas!#REF! -> #REF! | AT11: =Elect!BK12 -> 199 | AU11: =Elect!BI12 -> 89 | AX11: 43.454039 | AY11: 21.517241 | AZ11: 8299.2754 | BA11: 11.558879 | BB11: 5.7236382 | BC11: =Elect!BJ12 -> 447454 | BD11: =Elect!#REF! -> #REF! | BE11: =Elect!#REF! -> #REF! | BF11: =Elect!#REF! -> #REF! | BG11: =Elect!#REF! -> #REF! | BH11: 1.1713092 | BI11: 0.58 | BJ11: 4974.6248 | BK11: 6.9284468 | BL11: 3.4307757 | BM11: =Water!U13 -> 3.8541935 | BN11: =Water!W13 -> #DIV/0! | BO11: =Water!X13 -> 955.84 | BP11: =Water!Y13 -> 15.416774 | BQ11: =Water!Z13 -> #DIV/0!
A12: 8 | B12: 33600 | C12: =Elect!J13 -> 4426 | D12: 0 | E12: =Elect!M13 -> 1269 | F12: 20 | G12: =Elect!O13 -> 1516 | H12: 963 | I12: =Water!C14 -> 0 | J12: 0 | K12: =Water!E14 -> 185.6 | L12: 0 | M12: =Water!#REF! -> #REF! | N12: =Water!#REF! -> #REF! | O12: 1000 | P12: =Water!H14 -> 191.98 | Q12: 128 | R12: =Water!O14 -> 0 | S12: 24 | T12: =Water!#REF! -> #REF! | U12: 148 | V12: =Water!#REF! -> #REF! | W12: 719 | X12: =Water!Q14 -> 111.3484 | Y12: 0 | Z12: =Water!#REF! -> #REF! | AA12: 0 | AB12: 0 | AC12: 630 | AD12: =Water!#REF! -> #REF! | AE12: =Water!#REF! -> #REF! | AF12: =Water!#REF! -> #REF! | AG12: =Gas!B14 -> 7955957 | AH12: =Gas!C14 -> 743.06 | AI12: =Gas!#REF! -> #REF! | AJ12: =Gas!J14 -> 296.4 | AK12: =Gas!#REF! -> #REF! | AL12: =Gas!#REF! -> #REF! | AM12: =Gas!#REF! -> #REF! | AN12: =Gas!#REF! -> #REF! | AO12: =Gas!#REF! -> #REF! | AP12: =Gas!#REF! -> #REF! | AQ12: =Gas!#REF! -> #REF! | AR12: =Gas!#REF! -> #REF! | AS12: =Gas!#REF! -> #REF! | AT12: =Elect!BK13 -> 193 | AU12: =Elect!BI13 -> 93 | AX12: 48.837209 | AY12: 24.086022 | AZ12: 8835.4834 | BA12: 12.842272 | BB12: 6.3336799 | BC12: =Elect!BJ13 -> 447647 | BD12: =Elect!#REF! -> #REF! | BE12: =Elect!#REF! -> #REF! | BF12: =Elect!#REF! -> #REF! | BG12: =Elect!#REF! -> #REF! | BH12: 1.2194767 | BI12: 0.60143369 | BJ12: 5500.0731 | BK12: 7.9942923 | BL12: 3.9427047 | BM12: =Water!U14 -> 3.1472131 | BN12: =Water!W14 -> #DIV/0! | BO12: =Water!X14 -> 767.92 | BP12: =Water!Y14 -> 12.588852 | BQ12: =Water!Z14 -> #DIV/0!
A13: 9 | B13: 33600 | C13: =Elect!J14 -> 4074 | D13: 0 | E13: =Elect!M14 -> 1208 | F13: 20 | G13: =Elect!O14 -> 1394 | H13: 790 | I13: =Water!C15 -> 0 | J13: 0 | K13: =Water!E15 -> 307.4 | L13: 0 | M13: =Water!#REF! -> #REF! | N13: =Water!#REF! -> #REF! | O13: 841 | P13: =Water!H15 -> 317.84 | Q13: 127 | R13: =Water!O15 -> 0 | S13: 21 | T13: =Water!#REF! -> #REF! | U13: 139 | V13: =Water!#REF! -> #REF! | W13: 701 | X13: =Water!Q15 -> 184.3472 | Y13: 0 | Z13: =Water!#REF! -> #REF! | AA13: 0 | AB13: 0 | AC13: 440 | AD13: =Water!#REF! -> #REF! | AE13: =Water!#REF! -> #REF! | AF13: =Water!#REF! -> #REF! | AG13: =Gas!B15 -> 7956763 | AH13: =Gas!C15 -> 854.36 | AI13: =Gas!#REF! -> #REF! | AJ13: =Gas!J15 -> 261.3 | AK13: =Gas!#REF! -> #REF! | AL13: =Gas!#REF! -> #REF! | AM13: =Gas!#REF! -> #REF! | AN13: =Gas!#REF! -> #REF! | AO13: =Gas!#REF! -> #REF! | AP13: =Gas!#REF! -> #REF! | AQ13: =Gas!#REF! -> #REF! | AR13: =Gas!#REF! -> #REF! | AS13: =Gas!#REF! -> #REF! | AT13: =Elect!BK14 -> 176 | AU13: =Elect!BI14 -> 110 | AX13: 49.194729 | AY13: 24.1033 | AZ13: 8835.4834 | BA13: 12.936286 | BB13: 6.3382234 | BC13: =Elect!BJ14 -> 447823 | BD13: =Elect!#REF! -> #REF! | BE13: =Elect!#REF! -> #REF! | BF13: =Elect!#REF! -> #REF! | BG13: =Elect!#REF! -> #REF! | BH13: 1.1903367 | BI13: 0.58321377 | BJ13: 4512.0018 | BK13: 6.606152 | BL13: 3.2367301 | BM13: =Water!U15 -> 5.3871186 | BN13: =Water!W15 -> #DIV/0! | BO13: =Water!X15 -> 1271.36 | BP13: =Water!Y15 -> 21.548475 | BQ13: =Water!Z15 -> #DIV/0!
A14: 10 | B14: 31200 | C14: =Elect!J15 -> 5552 | D14: 0 | E14: =Elect!M15 -> 1318 | F14: 20 | G14: =Elect!O15 -> 1494 | H14: 792 | I14: =Water!C16 -> 5.8 | J14: 0 | K14: =Water!E16 -> 307.4 | L14: 0 | M14: =Water!#REF! -> #REF! | N14: =Water!#REF! -> #REF! | O14: 972 | P14: =Water!H16 -> 321.32 | Q14: 126 | R14: =Water!O16 -> 0 | S14: 18 | T14: =Water!#REF! -> #REF! | U14: 145 | V14: =Water!#REF! -> #REF! | W14: 756 | X14: =Water!Q16 -> 186.3656 | Y14: 0 | Z14: =Water!#REF! -> #REF! | AA14: 0 | AB14: 0 | AC14: 580 | AD14: =Water!#REF! -> #REF! | AE14: =Water!#REF! -> #REF! | AF14: =Water!#REF! -> #REF! | AG14: =Gas!B16 -> 7957726 | AH14: =Gas!C16 -> 1020.78 | AI14: =Gas!#REF! -> #REF! | AJ14: =Gas!J16 -> 397.8 | AK14: =Gas!#REF! -> #REF! | AL14: =Gas!#REF! -> #REF! | AM14: =Gas!#REF! -> #REF! | AN14: =Gas!#REF! -> #REF! | AO14: =Gas!#REF! -> #REF! | AP14: =Gas!#REF! -> #REF! | AQ14: =Gas!#REF! -> #REF! | AR14: =Gas!#REF! -> #REF! | AS14: =Gas!#REF! -> #REF! | AT14: =Elect!BK15 -> 226 | AU14: =Elect!BI15 -> 138 | AX14: 49.52381 | AY14: 24.781573 | AZ14: 8299.2754 | BA14: 13.173453 | BB14: 6.5919582 | BC14: =Elect!BJ15 -> 448049 | BD14: =Elect!#REF! -> #REF! | BE14: =Elect!#REF! -> #REF! | BF14: =Elect!#REF! -> #REF! | BG14: =Elect!#REF! -> #REF! | BH14: 1.2730159 | BI14: 0.6370135 | BJ14: 4469.9646 | BK14: 7.0951819 | BL14: 3.5504087 | BM14: =Water!U16 -> 3.9185366 | BN14: =Water!W16 -> #DIV/0! | BO14: =Water!X16 -> 1285.28 | BP14: =Water!Y16 -> 15.674146 | BQ14: =Water!Z16 -> #DIV/0!
A15: 11 | B15: 33600 | C15: =Elect!J16 -> 2990 | D15: 0 | E15: =Elect!M16 -> 1245 | F15: 20 | G15: =Elect!O16 -> 1453 | H15: 817 | I15: =Water!C17 -> 0 | J15: 0 | K15: =Water!E17 -> 284.2 | L15: 0 | M15: =Water!#REF! -> #REF! | N15: =Water!#REF! -> #REF! | O15: 875 | P15: =Water!H17 -> 290.58 | Q15: 122 | R15: =Water!O17 -> 0 | S15: 20 | T15: =Water!#REF! -> #REF! | U15: 156 | V15: =Water!#REF! -> #REF! | W15: 712 | X15: =Water!Q17 -> 168.5364 | Y15: 0 | Z15: =Water!#REF! -> #REF! | AA15: 0 | AB15: 0 | AC15: 850 | AD15: =Water!#REF! -> #REF! | AE15: =Water!#REF! -> #REF! | AF15: =Water!#REF! -> #REF! | AG15: =Gas!#REF! -> #REF! | AH15: =Gas!C17 -> 915.84 | AI15: =Gas!#REF! -> #REF! | AJ15: =Gas!J17 -> 195 | AK15: =Gas!#REF! -> #REF! | AL15: =Gas!#REF! -> #REF! | AM15: =Gas!#REF! -> #REF! | AN15: =Gas!#REF! -> #REF! | AO15: =Gas!#REF! -> #REF! | AP15: =Gas!#REF! -> #REF! | AQ15: =Gas!#REF! -> #REF! | AR15: =Gas!#REF! -> #REF! | AS15: =Gas!#REF! -> #REF! | AT15: =Elect!BK16 -> 148 | AU15: =Elect!BI16 -> 87 | AX15: 53.333333 | AY15: 26.751592 | AZ15: 8835.4834 | BA15: 14.024577 | BB15: 7.0346206 | BC15: =Elect!BJ16 -> 448197 | BD15: =Elect!#REF! -> #REF! | BE15: =Elect!#REF! -> #REF! | BF15: =Elect!#REF! -> #REF! | BG15: =Elect!#REF! -> #REF! | BH15: 1.3460317 | BI15: 0.67515924 | BJ15: 4666.2095 | BK15: 7.4066817 | BL15: 3.7151349 | BM15: =Water!U17 -> 8.3022857 | BN15: =Water!W17 -> #DIV/0! | BO15: =Water!X17 -> 1162.32 | BP15: =Water!Y17 -> 33.209143 | BQ15: =Water!Z17 -> #DIV/0!
A16: 12 | B16: 33600 | C16: =Elect!J17 -> 4437 | D16: 0 | E16: =Elect!M17 -> 1209 | F16: 20 | G16: =Elect!O17 -> 1578 | H16: 907 | I16: =Water!C18 -> 0 | J16: 0 | K16: =Water!E18 -> 237.8 | L16: 0 | M16: =Water!#REF! -> #REF! | N16: =Water!#REF! -> #REF! | O16: 965 | P16: =Water!H18 -> 244.76 | Q16: 125 | R16: =Water!O18 -> 0 | S16: 4 | T16: =Water!#REF! -> #REF! | U16: 167 | V16: =Water!#REF! -> #REF! | W16: 705 | X16: =Water!Q18 -> 141.9608 | Y16: 0 | Z16: =Water!#REF! -> #REF! | AA16: 0 | AB16: 0 | AC16: 880 | AD16: =Water!#REF! -> #REF! | AE16: =Water!#REF! -> #REF! | AF16: =Water!#REF! -> #REF! | AG16: =Gas!B18 -> 7959499 | AH16: =Gas!C18 -> 963.54 | AI16: =Gas!#REF! -> #REF! | AJ16: =Gas!J18 -> 312 | AK16: =Gas!#REF! -> #REF! | AL16: =Gas!#REF! -> #REF! | AM16: =Gas!#REF! -> #REF! | AN16: =Gas!#REF! -> #REF! | AO16: =Gas!#REF! -> #REF! | AP16: =Gas!#REF! -> #REF! | AQ16: =Gas!#REF! -> #REF! | AR16: =Gas!#REF! -> #REF! | AS16: =Gas!#REF! -> #REF! | AT16: =Elect!BK17 -> 211 | AU16: =Elect!BI17 -> 112 | AX16: 50.45045 | AY16: 25.339367 | AZ16: 8835.4834 | BA16: 13.266492 | BB16: 6.6632605 | BC16: =Elect!BJ17 -> 448408 | BD16: =Elect!#REF! -> #REF! | BE16: =Elect!#REF! -> #REF! | BF16: =Elect!#REF! -> #REF! | BG16: =Elect!#REF! -> #REF! | BH16: 1.2162162 | BI16: 0.61085973 | BJ16: 5180.235 | BK16: 7.7781306 | BL16: 3.9066629 | BM16: =Water!U18 -> 6.7988889 | BN16: =Water!W18 -> #DIV/0! | BO16: =Water!X18 -> 979.04 | BP16: =Water!Y18 -> 27.195556 | BQ16: =Water!Z18 -> #DIV/0!
A17: 13 | B17: 31200 | C17: =Elect!J18 -> 3726 | D17: 0 | E17: =Elect!M18 -> 1016 | F17: 20 | G17: =Elect!O18 -> 1469 | H17: 812 | I17: =Water!C19 -> 5.8 | J17: 0 | K17: =Water!E19 -> 214.6 | L17: 0 | M17: =Water!#REF! -> #REF! | N17: =Water!#REF! -> #REF! | O17: 822 | P17: =Water!H19 -> 227.36 | Q17: 123 | R17: =Water!O19 -> 0 | S17: 7 | T17: =Water!#REF! -> #REF! | U17: 163 | V17: =Water!#REF! -> #REF! | W17: 692 | X17: =Water!Q19 -> 131.8688 | Y17: 0 | Z17: =Water!#REF! -> #REF! | AA17: 0 | AB17: 0 | AC17: 460 | AD17: =Water!#REF! -> #REF! | AE17: =Water!#REF! -> #REF! | AF17: =Water!#REF! -> #REF! | AG17: =Gas!B19 -> 7960407 | AH17: =Gas!C19 -> 962.48 | AI17: =Gas!#REF! -> #REF! | AJ17: =Gas!J19 -> 276.9 | AK17: =Gas!#REF! -> #REF! | AL17: =Gas!#REF! -> #REF! | AM17: =Gas!#REF! -> #REF! | AN17: =Gas!#REF! -> #REF! | AO17: =Gas!#REF! -> #REF! | AP17: =Gas!#REF! -> #REF! | AQ17: =Gas!#REF! -> #REF! | AR17: =Gas!#REF! -> #REF! | AS17: =Gas!#REF! -> #REF! | AT17: =Elect!BK18 -> 173 | AU17: =Elect!BI18 -> 84 | AX17: 46.567164 | AY17: 23.214286 | AZ17: 8299.2754 | BA17: 12.386978 | BB17: 6.1750561 | BC17: =Elect!BJ18 -> 448581 | BD17: =Elect!#REF! -> #REF! | BE17: =Elect!#REF! -> #REF! | BF17: =Elect!#REF! -> #REF! | BG17: =Elect!#REF! -> #REF! | BH17: 1.0850746 | BI17: 0.54092262 | BJ17: 4637.6525 | BK17: 6.9218694 | BL17: 3.4506343 | BM17: =Water!U19 -> 7.5786667 | BN17: =Water!W19 -> #DIV/0! | BO17: =Water!X19 -> 909.44 | BP17: =Water!Y19 -> 30.314667 | BQ17: =Water!Z19 -> #DIV/0!
A18: 14 | B18: 33600 | C18: =Elect!J19 -> 4681 | D18: 0 | E18: =Elect!M19 -> 1427 | F18: 30 | G18: =Elect!O19 -> 1761 | H18: 810 | I18: =Water!C20 -> 0 | J18: 0 | K18: =Water!E20 -> 290 | L18: 0 | M18: =Water!#REF! -> #REF! | N18: =Water!#REF! -> #REF! | O18: 943 | P18: =Water!H20 -> 298.12 | Q18: 118 | R18: =Water!O20 -> 0 | S18: 18 | T18: =Water!#REF! -> #REF! | U18: 152 | V18: =Water!#REF! -> #REF! | W18: 708 | X18: =Water!Q20 -> 172.9096 | Y18: 0 | Z18: =Water!#REF! -> #REF! | AA18: 0 | AB18: 0 | AC18: 490 | AD18: =Water!#REF! -> #REF! | AE18: =Water!#REF! -> #REF! | AF18: =Water!#REF! -> #REF! | AG18: =Gas!B20 -> 7961290 | AH18: =Gas!C20 -> 935.98 | AI18: =Gas!#REF! -> #REF! | AJ18: =Gas!J20 -> 284.7 | AK18: =Gas!#REF! -> #REF! | AL18: =Gas!#REF! -> #REF! | AM18: =Gas!#REF! -> #REF! | AN18: =Gas!#REF! -> #REF! | AO18: =Gas!#REF! -> #REF! | AP18: =Gas!#REF! -> #REF! | AQ18: =Gas!#REF! -> #REF! | AR18: =Gas!#REF! -> #REF! | AS18: =Gas!#REF! -> #REF! | AT18: =Elect!BK19 -> 217 | AU18: =Elect!BI19 -> 107 | AX18: 47.795164 | AY18: 24.207493 | AZ18: 8835.4834 | BA18: 12.568255 | BB18: 6.3656221 | BC18: =Elect!BJ6 -> 446400 | BD18: =Elect!#REF! -> #REF! | BE18: =Elect!#REF! -> #REF! | BF18: =Elect!#REF! -> #REF! | BG18: =Elect!#REF! -> #REF! | BH18: 1.1024182 | BI18: 0.55835735 | BJ18: 4626.2297 | BK18: 6.5806966 | BL18: 3.3330185 | BM18: =Water!U20 -> 6.9330233 | BN18: =Water!W20 -> #DIV/0! | BO18: =Water!X20 -> 1192.48 | BP18: =Water!Y20 -> 27.732093 | BQ18: =Water!Z20 -> #DIV/0!
A19: 15 | B19: 31200 | C19: =Elect!J20 -> 4525 | D19: 0 | E19: =Elect!M20 -> 1465 | F19: 20 | G19: =Elect!O20 -> 1581 | H19: 841 | I19: =Water!C21 -> 0 | J19: 0 | K19: =Water!E21 -> 261 | L19: 0 | M19: =Water!#REF! -> #REF! | N19: =Water!#REF! -> #REF! | O19: 947 | P19: =Water!H21 -> 268.54 | Q19: 131 | R19: =Water!O21 -> 0 | S19: 23 | T19: =Water!#REF! -> #REF! | U19: 166 | V19: =Water!#REF! -> #REF! | W19: 787 | X19: =Water!Q21 -> 155.7532 | Y19: 0 | Z19: =Water!#REF! -> #REF! | AA19: 0 | AB19: 0 | AC19: 730 | AD19: =Water!#REF! -> #REF! | AE19: =Water!#REF! -> #REF! | AF19: =Water!#REF! -> #REF! | AG19: =Gas!B21 -> 7962173 | AH19: =Gas!C21 -> 935.98 | AI19: =Gas!#REF! -> #REF! | AJ19: =Gas!J21 -> 284.7 | AK19: =Gas!#REF! -> #REF! | AL19: =Gas!#REF! -> #REF! | AM19: =Gas!#REF! -> #REF! | AN19: =Gas!#REF! -> #REF! | AO19: =Gas!#REF! -> #REF! | AP19: =Gas!#REF! -> #REF! | AQ19: =Gas!#REF! -> #REF! | AR19: =Gas!#REF! -> #REF! | AS19: =Gas!#REF! -> #REF! | AT19: =Elect!BK20 -> 202 | AU19: =Elect!BI20 -> 100 | AX19: 41.6 | AY19: 20.995962 | AZ19: 8299.2754 | BA19: 11.065701 | BB19: 5.5849767 | BC19: =Elect!BJ20 -> 449000 | BD19: =Elect!#REF! -> #REF! | BE19: =Elect!#REF! -> #REF! | BF19: =Elect!#REF! -> #REF! | BG19: =Elect!#REF! -> #REF! | BH19: 1.1506667 | BI19: 0.58114478 | BJ19: 4803.283 | BK19: 6.4043773 | BL19: 3.234534 | BM19: =Water!U21 -> 4.1313846 | BN19: =Water!W21 -> #DIV/0! | BO19: =Water!X21 -> 1074.16 | BP19: =Water!Y21 -> 16.525538 | BQ19: =Water!Z21 -> #DIV/0!
A20: 16 | B20: 36000 | C20: =Elect!J21 -> 4214 | D20: 0 | E20: =Elect!M21 -> 1260 | F20: 20 | G20: =Elect!O21 -> 1497 | H20: 932 | I20: =Water!C22 -> 0 | J20: 0 | K20: =Water!E22 -> 232 | L20: 0 | M20: =Water!#REF! -> #REF! | N20: =Water!#REF! -> #REF! | O20: 998 | P20: =Water!H22 -> 241.86 | Q20: 136 | R20: =Water!O22 -> 0 | S20: 22 | T20: =Water!#REF! -> #REF! | U20: 162 | V20: =Water!#REF! -> #REF! | W20: 703 | X20: =Water!Q22 -> 140.2788 | Y20: 0 | Z20: =Water!#REF! -> #REF! | AA20: 0 | AB20: 0 | AC20: 600 | AD20: =Water!#REF! -> #REF! | AE20: =Water!#REF! -> #REF! | AF20: =Water!#REF! -> #REF! | AG20: =Gas!B22 -> 7963238 | AH20: =Gas!C22 -> 1128.9 | AI20: =Gas!#REF! -> #REF! | AJ20: =Gas!J22 -> 214.5 | AK20: =Gas!#REF! -> #REF! | AL20: =Gas!#REF! -> #REF! | AM20: =Gas!#REF! -> #REF! | AN20: =Gas!#REF! -> #REF! | AO20: =Gas!#REF! -> #REF! | AP20: =Gas!#REF! -> #REF! | AQ20: =Gas!#REF! -> #REF! | AR20: =Gas!#REF! -> #REF! | AS20: =Gas!#REF! -> #REF! | AT20: =Elect!BK21 -> 186 | AU20: =Elect!BI21 -> 96 | AX20: 48 | AY20: 24.22611 | AZ20: 9371.6914 | BA20: 12.495589 | BB20: 6.3066564 | BC20: =Elect!BJ21 -> 449186 | BD20: =Elect!#REF! -> #REF! | BE20: =Elect!#REF! -> #REF! | BF20: =Elect!#REF! -> #REF! | BG20: =Elect!#REF! -> #REF! | BH20: 1.1626667 | BI20: 0.58720539 | BJ20: 5323.0199 | BK20: 7.0973598 | BL20: 3.5845252 | BM20: =Water!U22 -> 4.3974545 | BN20: =Water!W22 -> #DIV/0! | BO20: =Water!X22 -> 967.44 | BP20: =Water!Y22 -> 17.589818 | BQ20: =Water!Z22 -> #DIV/0!
A21: 17 | B21: 33600 | C21: =Elect!J22 -> 5085 | D21: 0 | E21: =Elect!M22 -> 1610 | F21: 20 | G21: =Elect!O22 -> 1786 | H21: 972 | I21: =Water!C23 -> 0 | J21: 0 | K21: =Water!E23 -> 226.2 | L21: 0 | M21: =Water!#REF! -> #REF! | N21: =Water!#REF! -> #REF! | O21: 998 | P21: =Water!H23 -> 233.74 | Q21: 136 | R21: =Water!O23 -> 0 | S21: 38 | T21: =Water!#REF! -> #REF! | U21: 137 | V21: =Water!#REF! -> #REF! | W21: 740 | X21: =Water!Q23 -> 135.5692 | Y21: 0 | Z21: =Water!#REF! -> #REF! | AA21: 0 | AB21: 0 | AC21: 690 | AD21: =Water!#REF! -> #REF! | AE21: =Water!#REF! -> #REF! | AF21: =Water!#REF! -> #REF! | AG21: =Gas!B23 -> 7964246 | AH21: =Gas!C23 -> 1068.48 | AI21: =Gas!#REF! -> #REF! | AJ21: =Gas!J23 -> 315.9 | AK21: =Gas!#REF! -> #REF! | AL21: =Gas!#REF! -> #REF! | AM21: =Gas!#REF! -> #REF! | AN21: =Gas!#REF! -> #REF! | AO21: =Gas!#REF! -> #REF! | AP21: =Gas!#REF! -> #REF! | AQ21: =Gas!#REF! -> #REF! | AR21: =Gas!#REF! -> #REF! | AS21: =Gas!#REF! -> #REF! | AT21: =Elect!BK22 -> 212 | AU21: =Elect!BI22 -> 129 | AX21: 44.385733 | AY21: 22.207535 | AZ21: 8835.4834 | BA21: 11.671709 | BB21: 5.8397115 | BC21: =Elect!#REF! -> #REF! | BD21: =Elect!#REF! -> #REF! | BE21: =Elect!#REF! -> #REF! | BF21: =Elect!#REF! -> #REF! | BG21: =Elect!#REF! -> #REF! | BH21: 1.1770145 | BI21: 0.58889623 | BJ21: 5551.4757 | BK21: 7.3335213 | BL21: 3.6691842 | BM21: =Water!U23 -> 3.8956667 | BN21: =Water!W23 -> #DIV/0! | BO21: =Water!X23 -> 934.96 | BP21: =Water!Y23 -> 15.582667 | BQ21: =Water!Z23 -> #DIV/0!
A22: 18 | B22: 33600 | C22: =Elect!J23 -> 4854 | D22: 0 | E22: =Elect!M23 -> 1476 | F22: 20 | G22: =Elect!O23 -> 1590 | H22: 864 | I22: =Water!C24 -> 5.8 | J22: 0 | K22: =Water!E24 -> 220.4 | L22: 0 | M22: =Water!#REF! -> #REF! | N22: =Water!#REF! -> #REF! | O22: 1002 | P22: =Water!H24 -> 233.74 | Q22: 118 | R22: =Water!O24 -> 0 | S22: 21 | T22: =Water!#REF! -> #REF! | U22: 133 | V22: =Water!#REF! -> #REF! | W22: 769 | X22: =Water!Q24 -> 135.5692 | Y22: 0 | Z22: =Water!#REF! -> #REF! | AA22: 0 | AB22: 0 | AC22: 930 | AD22: =Water!#REF! -> #REF! | AE22: =Water!#REF! -> #REF! | AF22: =Water!#REF! -> #REF! | AG22: =Gas!B24 -> 7965107 | AH22: =Gas!C24 -> 912.66 | AI22: =Gas!#REF! -> #REF! | AJ22: =Gas!J24 -> 288.6 | AK22: =Gas!#REF! -> #REF! | AL22: =Gas!#REF! -> #REF! | AM22: =Gas!#REF! -> #REF! | AN22: =Gas!#REF! -> #REF! | AO22: =Gas!#REF! -> #REF! | AP22: =Gas!#REF! -> #REF! | AQ22: =Gas!#REF! -> #REF! | AR22: =Gas!#REF! -> #REF! | AS22: =Gas!#REF! -> #REF! | AT22: =Elect!BK23 -> 197 | AU22: =Elect!BI23 -> 106 | AX22: 44.680851 | AY22: 22.459893 | AZ22: 8835.4834 | BA22: 11.749313 | BB22: 5.9060718 | BC22: =Elect!BJ23 -> 449595 | BD22: =Elect!#REF! -> #REF! | BE22: =Elect!#REF! -> #REF! | BF22: =Elect!#REF! -> #REF! | BG22: =Elect!#REF! -> #REF! | BH22: 1.1236702 | BI22: 0.56483957 | BJ22: 4934.645 | BK22: 6.562028 | BL22: 3.2985595 | BM22: =Water!U24 -> 5.3122727 | BN22: =Water!W24 -> #DIV/0! | BO22: =Water!X24 -> 934.96 | BP22: =Water!Y24 -> 21.249091 | BQ22: =Water!Z24 -> #DIV/0!
A23: 19 | B23: 33600 | C23: =Elect!J24 -> 4933 | D23: 0 | E23: =Elect!M24 -> 1545 | F23: 30 | G23: =Elect!O24 -> 1525 | H23: 894 | I23: =Water!C25 -> 0 | J23: 0 | K23: =Water!E25 -> 243.6 | L23: 0 | M23: =Water!#REF! -> #REF! | N23: =Water!#REF! -> #REF! | O23: 944 | P23: =Water!H25 -> 251.72 | Q23: 110 | R23: =Water!O25 -> 0 | S23: 14 | T23: =Water!#REF! -> #REF! | U23: 155 | V23: =Water!#REF! -> #REF! | W23: 721 | X23: =Water!Q25 -> 145.9976 | Y23: 0 | Z23: =Water!#REF! -> #REF! | AA23: 0 | AB23: 0 | AC23: 660 | AD23: =Water!#REF! -> #REF! | AE23: =Water!#REF! -> #REF! | AF23: =Water!#REF! -> #REF! | AG23: =Gas!B25 -> 7966232 | AH23: =Gas!C25 -> 1192.5 | AI23: =Gas!#REF! -> #REF! | AJ23: =Gas!J25 -> 245.7 | AK23: =Gas!#REF! -> #REF! | AL23: =Gas!#REF! -> #REF! | AM23: =Gas!#REF! -> #REF! | AN23: =Gas!#REF! -> #REF! | AO23: =Gas!#REF! -> #REF! | AP23: =Gas!#REF! -> #REF! | AQ23: =Gas!#REF! -> #REF! | AR23: =Gas!#REF! -> #REF! | AS23: =Gas!#REF! -> #REF! | AT23: =Elect!BK24 -> 203 | AU23: =Elect!BI24 -> 110 | AX23: 44.8 | AY23: 22.44489 | AZ23: 8835.4834 | BA23: 11.780645 | BB23: 5.9021265 | BC23: =Elect!BJ24 -> 449798 | BD23: =Elect!#REF! -> #REF! | BE23: =Elect!#REF! -> #REF! | BF23: =Elect!#REF! -> #REF! | BG23: =Elect!#REF! -> #REF! | BH23: 1.1346667 | BI23: 0.56847027 | BJ23: 5105.9869 | BK23: 6.8079825 | BL23: 3.4108129 | BM23: =Water!U25 -> 4.9356863 | BN23: =Water!W25 -> #DIV/0! | BO23: =Water!X25 -> 1006.88 | BP23: =Water!Y25 -> 19.742745 | BQ23: =Water!Z25 -> #DIV/0!
A24: 20 | B24: 33600 | C24: =Elect!J25 -> 5011 | D24: 0 | E24: =Elect!M25 -> 1588 | F24: 20 | G24: =Elect!O25 -> 1507 | H24: 944 | I24: =Water!C26 -> 0 | J24: 0 | K24: =Water!E26 -> 249.4 | L24: 0 | M24: =Water!#REF! -> #REF! | N24: =Water!#REF! -> #REF! | O24: 1000 | P24: =Water!H26 -> 257.52 | Q24: 138 | R24: =Water!O26 -> 0 | S24: 15 | T24: =Water!#REF! -> #REF! | U24: 165 | V24: =Water!#REF! -> #REF! | W24: 778 | X24: =Water!Q26 -> 149.3616 | Y24: 0 | Z24: =Water!#REF! -> #REF! | AA24: 0 | AB24: 0 | AC24: 560 | AD24: =Water!#REF! -> #REF! | AE24: =Water!#REF! -> #REF! | AF24: =Water!#REF! -> #REF! | AG24: =Gas!B26 -> 7967337 | AH24: =Gas!C26 -> 1171.3 | AI24: =Gas!#REF! -> #REF! | AJ24: =Gas!J26 -> 308.1 | AK24: =Gas!#REF! -> #REF! | AL24: =Gas!#REF! -> #REF! | AM24: =Gas!#REF! -> #REF! | AN24: =Gas!#REF! -> #REF! | AO24: =Gas!#REF! -> #REF! | AP24: =Gas!#REF! -> #REF! | AQ24: =Gas!#REF! -> #REF! | AR24: =Gas!#REF! -> #REF! | AS24: =Gas!#REF! -> #REF! | AT24: =Elect!BK25 -> 202 | AU24: =Elect!BI25 -> 102 | AX24: 42.857143 | AY24: 21.649485 | AZ24: 8835.4834 | BA24: 11.269749 | BB24: 5.6929661 | BC24: =Elect!BJ25 -> 450000 | BD24: =Elect!#REF! -> #REF! | BE24: =Elect!#REF! -> #REF! | BF24: =Elect!#REF! -> #REF! | BG24: =Elect!#REF! -> #REF! | BH24: 1.1683673 | BI24: 0.59020619 | BJ24: 5391.5566 | BK24: 6.8769855 | BL24: 3.4739411 | BM24: =Water!U26 -> 5.365 | BN24: =Water!W26 -> #DIV/0! | BO24: =Water!X26 -> 1030.08 | BP24: =Water!Y26 -> 21.46 | BQ24: =Water!Z26 -> #DIV/0!
A25: 21 | B25: 36000 | C25: =Elect!J26 -> 4918 | D25: 0 | E25: =Elect!M26 -> 1584 | F25: 20 | G25: =Elect!O26 -> 1467 | H25: 916 | I25: =Water!C27 -> 5.8 | J25: 0 | K25: =Water!E27 -> 266.8 | L25: 0 | M25: =Water!#REF! -> #REF! | N25: =Water!#REF! -> #REF! | O25: 998 | P25: =Water!H27 -> 279.56 | Q25: 186 | R25: =Water!O27 -> 0 | S25: 43 | T25: =Water!#REF! -> #REF! | U25: 176 | V25: =Water!#REF! -> #REF! | W25: 773 | X25: =Water!Q27 -> 162.1448 | Y25: 0 | Z25: =Water!#REF! -> #REF! | AA25: 0 | AB25: 0 | AC25: 950 | AD25: =Water!#REF! -> #REF! | AE25: =Water!#REF! -> #REF! | AF25: =Water!#REF! -> #REF! | AG25: =Gas!B27 -> 7968158 | AH25: =Gas!C27 -> 870.26 | AI25: =Gas!#REF! -> #REF! | AJ25: =Gas!J27 -> 265.2 | AK25: =Gas!#REF! -> #REF! | AL25: =Gas!#REF! -> #REF! | AM25: =Gas!#REF! -> #REF! | AN25: =Gas!#REF! -> #REF! | AO25: =Gas!#REF! -> #REF! | AP25: =Gas!#REF! -> #REF! | AQ25: =Gas!#REF! -> #REF! | AR25: =Gas!#REF! -> #REF! | AS25: =Gas!#REF! -> #REF! | AT25: =Elect!BK26 -> 199 | AU25: =Elect!BI26 -> 102 | AX25: 43.956044 | AY25: 22.222222 | AZ25: 9371.6914 | BA25: 11.442847 | BB25: 5.7849947 | BC25: =Elect!BJ26 -> 450199 | BD25: =Elect!#REF! -> #REF! | BE25: =Elect!#REF! -> #REF! | BF25: =Elect!#REF! -> #REF! | BG25: =Elect!#REF! -> #REF! | BH25: 1.0586081 | BI25: 0.53518519 | BJ25: 5231.6376 | BK25: 6.3878358 | BL25: 3.2294059 | BM25: =Water!U27 -> 5.5912 | BN25: =Water!W27 -> #DIV/0! | BO25: =Water!X27 -> 1118.24 | BP25: =Water!Y27 -> 22.3648 | BQ25: =Water!Z27 -> #DIV/0!
A26: 22 | B26: 33600 | C26: =Elect!J27 -> 4726 | D26: 0 | E26: =Elect!M27 -> 1486 | F26: 20 | G26: =Elect!O27 -> 1444 | H26: 931 | I26: =Water!C28 -> 0 | J26: 0 | K26: =Water!E28 -> 261 | L26: 0 | M26: =Water!#REF! -> #REF! | N26: =Water!#REF! -> #REF! | O26: 969 | P26: =Water!H28 -> 270.86 | Q26: 151 | R26: =Water!O28 -> 0 | S26: 29 | T26: =Water!#REF! -> #REF! | U26: 157 | V26: =Water!#REF! -> #REF! | W26: 697 | X26: =Water!Q28 -> 157.0988 | Y26: 0 | Z26: =Water!#REF! -> #REF! | AA26: 0 | AB26: 0 | AC26: 700 | AD26: =Water!#REF! -> #REF! | AE26: =Water!#REF! -> #REF! | AF26: =Water!#REF! -> #REF! | AG26: =Gas!B28 -> 7969253 | AH26: =Gas!C28 -> 1160.7 | AI26: =Gas!#REF! -> #REF! | AJ26: =Gas!J28 -> 284.7 | AK26: =Gas!#REF! -> #REF! | AL26: =Gas!#REF! -> #REF! | AM26: =Gas!#REF! -> #REF! | AN26: =Gas!#REF! -> #REF! | AO26: =Gas!#REF! -> #REF! | AP26: =Gas!#REF! -> #REF! | AQ26: =Gas!#REF! -> #REF! | AR26: =Gas!#REF! -> #REF! | AS26: =Gas!#REF! -> #REF! | AT26: =Elect!BK27 -> 201 | AU26: =Elect!BI27 -> 101 | AX26: 39.952438 | AY26: 20.253165 | AZ26: 8835.4834 | BA26: 10.505926 | BB26: 5.3257887 | BC26: =Elect!BJ27 -> 450400 | BD26: =Elect!#REF! -> #REF! | BE26: =Elect!#REF! -> #REF! | BF26: =Elect!#REF! -> #REF! | BG26: =Elect!#REF! -> #REF! | BH26: 1.0903686 | BI26: 0.55274262 | BJ26: 5317.3085 | BK26: 6.3226022 | BL26: 3.2051287 | BM26: =Water!U28 -> 5.0159259 | BN26: =Water!W28 -> #DIV/0! | BO26: =Water!X28 -> 1083.44 | BP26: =Water!Y28 -> 20.063704 | BQ26: =Water!Z28 -> #DIV/0!
A27: 23 | B27: 36000 | C27: =Elect!J28 -> 4556 | D27: 0 | E27: =Elect!M28 -> 1388 | F27: 30 | G27: =Elect!O28 -> 1481 | H27: 1009 | I27: =Water!C29 -> 0 | J27: 0 | K27: =Water!E29 -> 214.6 | L27: 0 | M27: =Water!#REF! -> #REF! | N27: =Water!#REF! -> #REF! | O27: 902 | P27: =Water!H29 -> 222.72 | Q27: 131 | R27: =Water!O29 -> 0 | S27: 6 | T27: =Water!#REF! -> #REF! | U27: 167 | V27: =Water!#REF! -> #REF! | W27: 748 | X27: =Water!Q29 -> 129.1776 | Y27: 0 | Z27: =Water!#REF! -> #REF! | AA27: 0 | AB27: 0 | AC27: 690 | AD27: =Water!#REF! -> #REF! | AE27: =Water!#REF! -> #REF! | AF27: =Water!#REF! -> #REF! | AG27: =Gas!B29 -> 7970196 | AH27: =Gas!C29 -> 999.58 | AI27: =Gas!#REF! -> #REF! | AJ27: =Gas!J29 -> 253.5 | AK27: =Gas!#REF! -> #REF! | AL27: =Gas!#REF! -> #REF! | AM27: =Gas!#REF! -> #REF! | AN27: =Gas!#REF! -> #REF! | AO27: =Gas!#REF! -> #REF! | AP27: =Gas!#REF! -> #REF! | AQ27: =Gas!#REF! -> #REF! | AR27: =Gas!#REF! -> #REF! | AS27: =Gas!#REF! -> #REF! | AT27: =Elect!BK28 -> 202 | AU27: =Elect!BI28 -> 127 | AX27: 42.755344 | AY27: 21.543986 | AZ27: 9371.6914 | BA27: 11.130275 | BB27: 5.6084329 | BC27: =Elect!BJ28 -> 450602 | BD27: =Elect!#REF! -> #REF! | BE27: =Elect!#REF! -> #REF! | BF27: =Elect!#REF! -> #REF! | BG27: =Elect!#REF! -> #REF! | BH27: 1.0712589 | BI27: 0.53979653 | BJ27: 5762.7973 | BK27: 6.8441773 | BL27: 3.4487117 | BM27: =Water!U29 -> 5.0618182 | BN27: =Water!W29 -> #DIV/0! | BO27: =Water!X29 -> 890.88 | BP27: =Water!Y29 -> 20.247273 | BQ27: =Water!Z29 -> #DIV/0!
A28: 24 | B28: 33600 | C28: =Elect!J29 -> 4688 | D28: 0 | E28: =Elect!M29 -> 1394 | F28: 20 | G28: =Elect!O29 -> 1580 | H28: 891 | I28: =Water!C30 -> 0 | J28: 0 | K28: =Water!E30 -> 191.4 | L28: 0 | M28: =Water!#REF! -> #REF! | N28: =Water!#REF! -> #REF! | O28: 818 | P28: =Water!H30 -> 220.4 | Q28: 221 | R28: =Water!O30 -> 0 | S28: 93 | T28: =Water!#REF! -> #REF! | U28: 191 | V28: =Water!#REF! -> #REF! | W28: 827 | X28: =Water!Q30 -> 127.832 | Y28: 0 | Z28: =Water!#REF! -> #REF! | AA28: 0 | AB28: 0 | AC28: 470 | AD28: =Water!#REF! -> #REF! | AE28: =Water!#REF! -> #REF! | AF28: =Water!#REF! -> #REF! | AG28: =Gas!B30 -> 7971263 | AH28: =Gas!C30 -> 1131.02 | AI28: =Gas!#REF! -> #REF! | AJ28: =Gas!J30 -> 323.7 | AK28: =Gas!#REF! -> #REF! | AL28: =Gas!#REF! -> #REF! | AM28: =Gas!#REF! -> #REF! | AN28: =Gas!#REF! -> #REF! | AO28: =Gas!#REF! -> #REF! | AP28: =Gas!#REF! -> #REF! | AQ28: =Gas!#REF! -> #REF! | AR28: =Gas!#REF! -> #REF! | AS28: =Gas!#REF! -> #REF! | AT28: =Elect!BK29 -> 200 | AU28: =Elect!BI29 -> 118 | AX28: 39.904988 | AY28: 20.289855 | AZ28: 8835.4834 | BA28: 10.493448 | BB28: 5.3354369 | BC28: =Elect!BJ29 -> 450802 | BD28: =Elect!#REF! -> #REF! | BE28: =Elect!#REF! -> #REF! | BF28: =Elect!#REF! -> #REF! | BG28: =Elect!#REF! -> #REF! | BH28: 1.1104513 | BI28: 0.56461353 | BJ28: 5088.8527 | BK28: 6.043768 | BL28: 3.0729787 | BM28: =Water!U30 -> 5.3756098 | BN28: =Water!W30 -> #DIV/0! | BO28: =Water!X30 -> 881.6 | BP28: =Water!Y30 -> 21.502439 | BQ28: =Water!Z30 -> #DIV/0!
A29: 25 | B29: 33600 | C29: =Elect!J30 -> 4941 | D29: 0 | E29: =Elect!M30 -> 1463 | F29: 20 | G29: =Elect!O30 -> 1682 | H29: 1008 | I29: =Water!C31 -> 0 | J29: 0 | K29: =Water!E31 -> 179.8 | L29: 0 | M29: =Water!#REF! -> #REF! | N29: =Water!#REF! -> #REF! | O29: 1290 | P29: =Water!H31 -> 189.08 | Q29: 34 | R29: =Water!O31 -> 0 | S29: 34 | T29: =Water!#REF! -> #REF! | U29: 55 | V29: =Water!#REF! -> #REF! | W29: 681 | X29: =Water!Q31 -> 109.6664 | Y29: 0 | Z29: =Water!#REF! -> #REF! | AA29: 0 | AB29: 0 | AC29: 1170 | AD29: =Water!#REF! -> #REF! | AE29: =Water!#REF! -> #REF! | AF29: =Water!#REF! -> #REF! | AG29: =Gas!B31 -> 7972221 | AH29: =Gas!C31 -> 1015.48 | AI29: =Gas!#REF! -> #REF! | AJ29: =Gas!J31 -> 249.6 | AK29: =Gas!#REF! -> #REF! | AL29: =Gas!#REF! -> #REF! | AM29: =Gas!#REF! -> #REF! | AN29: =Gas!#REF! -> #REF! | AO29: =Gas!#REF! -> #REF! | AP29: =Gas!#REF! -> #REF! | AQ29: =Gas!#REF! -> #REF! | AR29: =Gas!#REF! -> #REF! | AS29: =Gas!#REF! -> #REF! | AT29: =Elect!BK30 -> 218 | AU29: =Elect!BI30 -> 111 | AX29: 39.763314 | AY29: 20.20445 | AZ29: 8835.4834 | BA29: 10.456193 | BB29: 5.3129786 | BC29: =Elect!BJ30 -> 451020 | BD29: =Elect!#REF! -> #REF! | BE29: =Elect!#REF! -> #REF! | BF29: =Elect!#REF! -> #REF! | BG29: =Elect!#REF! -> #REF! | BH29: 1.0059172 | BI29: 0.51112447 | BJ29: 5757.0859 | BK29: 6.8131194 | BL29: 3.4618676 | BM29: =Water!U31 -> 5.1102703 | BN29: =Water!W31 -> #DIV/0! | BO29: =Water!X31 -> 756.32 | BP29: =Water!Y31 -> 20.441081 | BQ29: =Water!Z31 -> #DIV/0!
A30: 26 | B30: 31200 | C30: =Elect!J31 -> 4111 | D30: 0 | E30: =Elect!M31 -> 1053 | F30: 20 | G30: =Elect!O31 -> 1673 | H30: 760 | I30: =Water!C32 -> 0 | J30: 0 | K30: =Water!E32 -> 232 | L30: 0 | M30: =Water!#REF! -> #REF! | N30: =Water!#REF! -> #REF! | O30: 1004 | P30: =Water!H32 -> 232 | Q30: 131 | R30: =Water!O32 -> 0 | S30: 33 | T30: =Water!#REF! -> #REF! | U30: 145 | V30: =Water!#REF! -> #REF! | W30: 916 | X30: =Water!Q32 -> 134.56 | Y30: 0 | Z30: =Water!#REF! -> #REF! | AA30: 0 | AB30: 0 | AC30: 810 | AD30: =Water!#REF! -> #REF! | AE30: =Water!#REF! -> #REF! | AF30: =Water!#REF! -> #REF! | AG30: =Gas!B32 -> 7973078 | AH30: =Gas!C32 -> 908.42 | AI30: =Gas!#REF! -> #REF! | AJ30: =Gas!J32 -> 276.9 | AK30: =Gas!#REF! -> #REF! | AL30: =Gas!#REF! -> #REF! | AM30: =Gas!#REF! -> #REF! | AN30: =Gas!#REF! -> #REF! | AO30: =Gas!#REF! -> #REF! | AP30: =Gas!#REF! -> #REF! | AQ30: =Gas!#REF! -> #REF! | AR30: =Gas!#REF! -> #REF! | AS30: =Gas!#REF! -> #REF! | AT30: =Elect!BK31 -> 187 | AU30: =Elect!BI31 -> 98 | AX30: 37.275986 | AY30: 18.989653 | AZ30: 8299.2754 | BA30: 9.9155023 | BB30: 5.0512936 | BC30: =Elect!BJ31 -> 451207 | BD30: =Elect!#REF! -> #REF! | BE30: =Elect!#REF! -> #REF! | BF30: =Elect!#REF! -> #REF! | BG30: =Elect!#REF! -> #REF! | BH30: 1.1063321 | BI30: 0.56360316 | BJ30: 4340.66 | BK30: 5.1859737 | BL30: 2.6419111 | BM30: =Water!U32 -> 8 | BN30: =Water!W32 -> #DIV/0! | BO30: =Water!X32 -> 928 | BP30: =Water!Y32 -> 32 | BQ30: =Water!Z32 -> #DIV/0!
A31: 27 | B31: 36000 | C31: =Elect!J32 -> 4257 | D31: 0 | E31: =Elect!M32 -> 1121 | F31: 30 | G31: =Elect!O32 -> 1571 | H31: 1010 | I31: =Water!C33 -> 5.8 | J31: 0 | K31: =Water!E33 -> 301.6 | L31: 0 | M31: =Water!#REF! -> #REF! | N31: =Water!#REF! -> #REF! | O31: 1014 | P31: =Water!H33 -> 307.4 | Q31: 151 | R31: =Water!O33 -> 0 | S31: 30 | T31: =Water!#REF! -> #REF! | U31: 139 | V31: =Water!#REF! -> #REF! | W31: 761 | X31: =Water!Q33 -> 178.292 | Y31: 0 | Z31: =Water!#REF! -> #REF! | AA31: 0 | AB31: 0 | AC31: 930 | AD31: =Water!#REF! -> #REF! | AE31: =Water!#REF! -> #REF! | AF31: =Water!#REF! -> #REF! | AG31: =Gas!B33 -> 7974214 | AH31: =Gas!C33 -> 1204.16 | AI31: =Gas!#REF! -> #REF! | AJ31: =Gas!J33 -> 159.9 | AK31: =Gas!#REF! -> #REF! | AL31: =Gas!#REF! -> #REF! | AM31: =Gas!#REF! -> #REF! | AN31: =Gas!#REF! -> #REF! | AO31: =Gas!#REF! -> #REF! | AP31: =Gas!#REF! -> #REF! | AQ31: =Gas!#REF! -> #REF! | AR31: =Gas!#REF! -> #REF! | AS31: =Gas!#REF! -> #REF! | AT31: =Elect!BK32 -> 210 | AU31: =Elect!BI32 -> 145 | AX31: 44.063647 | AY31: 22.346369 | AZ31: 9371.6914 | BA31: 11.470859 | BB31: 5.8173131 | BC31: =Elect!BJ32 -> 451417 | BD31: =Elect!#REF! -> #REF! | BE31: =Elect!#REF! -> #REF! | BF31: =Elect!#REF! -> #REF! | BG31: =Elect!#REF! -> #REF! | BH31: 1.1640147 | BI31: 0.59031657 | BJ31: 5768.5087 | BK31: 7.0605981 | BL31: 3.5807006 | BM31: =Water!U33 -> 13.365217 | BN31: =Water!W33 -> #DIV/0! | BO31: =Water!X33 -> 1229.6 | BP31: =Water!Y33 -> 53.46087 | BQ31: =Water!Z33 -> #DIV/0!
A32: 28 | B32: 33600 | C32: =Elect!J33 -> 4337 | D32: 0 | E32: =Elect!M33 -> 1430 | F32: 20 | G32: =Elect!O33 -> 1572 | H32: 1008 | I32: =Water!C34 -> 0 | J32: 0 | K32: =Water!E34 -> 295.8 | L32: 1 | M32: =Water!#REF! -> #REF! | N32: =Water!#REF! -> #REF! | O32: 1013 | P32: =Water!H34 -> 295.8 | Q32: 142 | R32: =Water!O34 -> 0 | S32: 13 | T32: =Water!#REF! -> #REF! | U32: 155 | V32: =Water!#REF! -> #REF! | W32: 825 | X32: =Water!Q34 -> 171.564 | Y32: 1 | Z32: =Water!#REF! -> #REF! | AA32: 0 | AB32: 0 | AC32: 650 | AD32: =Water!#REF! -> #REF! | AE32: =Water!#REF! -> #REF! | AF32: =Water!#REF! -> #REF! | AG32: =Gas!B34 -> 7975316 | AH32: =Gas!C34 -> 1168.12 | AI32: =Gas!#REF! -> #REF! | AJ32: =Gas!J34 -> 198.9 | AK32: =Gas!#REF! -> #REF! | AL32: =Gas!#REF! -> #REF! | AM32: =Gas!#REF! -> #REF! | AN32: =Gas!#REF! -> #REF! | AO32: =Gas!#REF! -> #REF! | AP32: =Gas!#REF! -> #REF! | AQ32: =Gas!#REF! -> #REF! | AR32: =Gas!#REF! -> #REF! | AS32: =Gas!#REF! -> #REF! | AT32: =Elect!BK33 -> 192 | AU32: =Elect!BI33 -> 120 | AX32: 45.34413 | AY32: 22.687373 | AZ32: 8835.4834 | BA32: 11.923729 | BB32: 5.9658902 | BC32: =Elect!BJ33 -> 451609 | BD32: =Elect!#REF! -> #REF! | BE32: =Elect!#REF! -> #REF! | BF32: =Elect!#REF! -> #REF! | BG32: =Elect!#REF! -> #REF! | BH32: 1.2294197 | BI32: 0.61512492 | BJ32: 5757.0859 | BK32: 7.7693467 | BL32: 3.8872963 | BM32: =Water!U34 -> 8.9636364 | BN32: =Water!W34 -> #DIV/0! | BO32: =Water!X34 -> 1183.2 | BP32: =Water!Y34 -> 35.854545 | BQ32: =Water!Z34 -> #DIV/0!
A33: MTD | B33: 931200 | C33: =Elect!J34 -> 3670 | D33: 0 | E33: =Elect!M34 -> 0 | F33: 600 | G33: =Elect!O34 -> 0 | H33: 24543 | I33: =Water!C38 -> 46.4 | J33: 0 | K33: =Water!E39 -> 241.66667 | L33: 3 | M33: =Water!#REF! -> #REF! | N33: =Water!#REF! -> #REF! | O33: 1013 | P33: =Water!H38 -> 7519.12 | Q33: 109 | R33: =Water!O38 -> 0 | S33: 15 | T33: =Water!#REF! -> #REF! | U33: 147 | V33: =Water!#REF! -> #REF! | W33: 730 | X33: =Water!Q38 -> 3964.1376 | Y33: 3 | Z33: =Water!#REF! -> #REF! | AA33: 0 | AB33: 0 | AC33: 0 | AD33: =Water!#REF! -> #REF! | AE33: =Water!#REF! -> #REF! | AF33: =Water!#REF! -> #REF! | AG33: =Gas!B38 -> 0 | AH33: =Gas!C38 -> 31048.46 | AI33: =Gas!#REF! -> #REF! | AJ33: =Gas!J38 -> 8544.9 | AK33: =Gas!#REF! -> #REF! | AL33: =Gas!#REF! -> #REF! | AM33: =Gas!#REF! -> #REF! | AN33: =Gas!#REF! -> #REF! | AO33: =Gas!#REF! -> #REF! | AP33: =Gas!#REF! -> #REF! | AQ33: =Gas!#REF! -> #REF! | AR33: =Gas!#REF! -> #REF! | AS33: =Gas!#REF! -> #REF! | AT33: =Elect!BK34 -> 195 | AU33: =Elect!BI34 -> 102 | AX33: 45.411099 | AY33: 22.844806 | AZ33: 245248.7 | BA33: 11.959851 | BB33: 6.0166013 | BC33: =Elect!BJ34 -> 451804 | BD33: =Elect!#REF! -> #REF! | BE33: =Elect!#REF! -> #REF! | BF33: =Elect!#REF! -> #REF! | BG33: =Elect!#REF! -> #REF! | BH33: 1.1514679 | BI33: 0.57929342 | BJ33: 140121.3 | BK33: 6.8331854 | BL33: 3.4377159 | BM33: =Water!U38 -> 5.2544514 | BN33: =Water!W38 -> #DIV/0! | BO33: =Water!X38 -> 29241.28 | BP33: =Water!Y38 -> 20.434158 | BQ33: =Water!Z38 -> #DIV/0!
A34: AVER. Act | B34: 33257.143 | C34: =Elect!J35 -> 5340 | D34: 0 | E34: =Elect!M35 -> 1236 | F34: 21.428571 | G34: =Elect!O35 -> 1447 | H34: 876.53571 | I34: =Water!C39 -> 1.5466667 | J34: 0 | K34: =Water!E40 -> 0 | L34: 4 | M34: =Water!#REF! -> #REF! | N34: =Water!#REF! -> #REF! | O34: 1014 | P34: =Water!H39 -> 250.63733 | Q34: 138 | R34: =Water!O39 -> 0 | S34: 24 | T34: =Water!#REF! -> #REF! | U34: 145 | V34: =Water!#REF! -> #REF! | W34: 877 | X34: =Water!Q39 -> 132.13792 | Y34: 4 | Z34: =Water!#REF! -> #REF! | AA34: 0 | AB34: 0 | AC34: 0 | AD34: =Water!#REF! -> #REF! | AE34: =Water!#REF! -> #REF! | AF34: =Water!#REF! -> #REF! | AG34: =Gas!B39 -> 0 | AH34: =Gas!C39 -> 1034.9487 | AI34: =Gas!#REF! -> #REF! | AJ34: =Gas!J39 -> 284.83 | AK34: =Gas!#REF! -> #REF! | AL34: =Gas!#REF! -> #REF! | AM34: =Gas!#REF! -> #REF! | AN34: =Gas!#REF! -> #REF! | AO34: =Gas!#REF! -> #REF! | AP34: =Gas!#REF! -> #REF! | AQ34: =Gas!#REF! -> #REF! | AR34: =Gas!#REF! -> #REF! | AS34: =Gas!#REF! -> #REF! | AT34: =Elect!BK35 -> 209 | AU34: =Elect!BI35 -> 110 | AX34: 45.411099 | AY34: 22.844806 | AZ34: 8758.8823 | BA34: 11.959851 | BB34: 6.0166013 | BC34: =Elect!BJ35 -> 452013 | BD34: =Elect!#REF! -> #REF! | BE34: =Elect!#REF! -> #REF! | BF34: =Elect!#REF! -> #REF! | BG34: =Elect!#REF! -> #REF! | BH34: 1.1761372 | BI34: 0.60007377 | BJ34: 5004.3322 | BK34: 6.8331854 | BL34: 3.4377159 | BM34: =Water!U39 -> 5.2544514 | BN34: =Water!W39 -> #DIV/0! | BO34: =Water!X39 -> 974.70933 | BP34: =Water!Y39 -> 20.434158 | BQ34: =Water!Z39 -> #DIV/0!
A35: TOTAL Budget | B35: 1040026 | C35: =Elect!J5 -> 0 | D35: 0 | E35: =Elect!M5 -> 0 | F35: 0 | G35: =Elect!O5 -> 0 | H35: 0 | I35: =Water!C40 -> 0 | J35: 0 | K35: =Water!E41 -> 0 | L35: 5 | M35: =Water!#REF! -> #REF! | N35: =Water!#REF! -> #REF! | O35: 1010 | P35: =Water!H40 -> 0 | Q35: 148 | R35: =Water!O40 -> 0 | S35: 22 | T35: =Water!#REF! -> #REF! | U35: 151 | V35: =Water!#REF! -> #REF! | W35: 833 | X35: =Water!Q40 -> 0 | Y35: 5 | Z35: =Water!#REF! -> #REF! | AA35: 0 | AB35: 0 | AC35: 0 | AD35: =Water!#REF! -> #REF! | AE35: =Water!#REF! -> #REF! | AF35: =Water!#REF! -> #REF! | AG35: =Gas!#REF! -> #REF! | AH35: =Gas!#REF! -> #REF! | AI35: =Gas!#REF! -> #REF! | AJ35: =Gas!#REF! -> #REF! | AK35: =Gas!#REF! -> #REF! | AL35: =Gas!#REF! -> #REF! | AM35: =Gas!#REF! -> #REF! | AN35: =Gas!#REF! -> #REF! | ... AS35: =Gas!#REF! -> #REF! | AT35: =Elect!BK5 -> 0 | AU35: =Elect!BI5 -> 0 | AX35: 45.679286 | AY35: 23.305904 | AZ35: 264708.4 | BA35: 11.626335 | BB35: 5.9318409 | BC35: =Elect!BJ5 -> 446214 | BD35: =Elect!#REF! -> #REF! | BE35: =Elect!#REF! -> #REF! | BF35: =Elect!#REF! -> #REF! | BG35: =Elect!#REF! -> #REF! | BH35: 1.1761372 | BI35: 0.60007377 | BJ35: 150494 | BK35: 6.6098911 | BL35: 3.3724146 | BM35: =Water!U40 -> #REF! | BN35: =Water!W40 -> #REF! | BO35: =Water!X40 -> 0 | BP35: =Water!Y40 -> 0 | BQ35: =Water!Z40 -> 0
A36: Budget MTD | B36: 1040026 | C36: =Elect!#REF! -> #REF! | D36: 0 | E36: =Elect!#REF! -> #REF! | F36: 0 | G36: =Elect!#REF! -> #REF! | H36: 0 | I36: =Water!C41 -> 0 | J36: 0 | K36: =Water!E42 -> 0 | L36: 6 | M36: =Water!#REF! -> #REF! | N36: =Water!#REF! -> #REF! | O36: 30039 | P36: =Water!H41 -> 0 | Q36: 129.54839 | R36: =Water!O41 -> 0 | S36: 719 | T36: =Water!#REF! -> #REF! | U36: 4609 | V36: =Water!#REF! -> #REF! | W36: 23430 | X36: =Water!Q41 -> 0 | Y36: 6 | Z36: =Water!#REF! -> #REF! | AA36: 0 | AB36: 0 | AC36: 0 | AD36: =Water!#REF! -> #REF! | AE36: =Water!#REF! -> #REF! | AF36: =Water!#REF! -> #REF! | AG36: =Gas!#REF! -> #REF! | AH36: =Gas!#REF! -> #REF! | AI36: =Gas!#REF! -> #REF! | AJ36: =Gas!#REF! -> #REF! | AK36: =Gas!#REF! -> #REF! | AL36: =Gas!#REF! -> #REF! | AM36: =Gas!#REF! -> #REF! | AN36: =Gas!#REF! -> #REF! | ... AS36: =Gas!#REF! -> #REF! | AT36: =Elect!#REF! -> #REF! | AU36: =Elect!#REF! -> #REF! | AX36: 45.679286 | AY36: 23.305904 | AZ36: 264708.4 | BA36: 11.626335 | BB36: 5.9318409 | BC36: =Elect!#REF! -> #REF! | BD36: =Elect!#REF! -> #REF! | BE36: =Elect!#REF! -> #REF! | BF36: =Elect!#REF! -> #REF! | BG36: =Elect!#REF! -> #REF! | BH36: 0 | BI36: 0 | BJ36: 135930.06 | BK36: 6.6098911 | BL36: 3.3724146 | BM36: =Water!U41 -> #REF! | BN36: =Water!W41 -> #REF! | BO36: =Water!X41 -> #REF! | BP36: =Water!Y41 -> #REF! | BQ36: =Water!Z41 -> #REF!
A37: AVER. Bud | B37: 37143.785 | C37: =Elect!J39 -> 0 | D37: 0 | E37: =Elect!M39 -> 0 | F37: 0 | G37: =Elect!O39 -> 0 | H37: 0 | I37: =Water!C42 -> 0 | J37: 0 | K37: =Water!E43 -> 0 | L37: 7 | M37: =Water!#REF! -> #REF! | N37: =Water!#REF! -> #REF! | O37: 969 | P37: =Water!H42 -> 0 | Q37: 0 | R37: =Water!O42 -> 0 | S37: 23.193548 | T37: =Water!#REF! -> #REF! | U37: 148.67742 | V37: =Water!#REF! -> #REF! | W37: 755.80645 | X37: =Water!Q42 -> 0 | Y37: 7 | Z37: =Water!#REF! -> #REF! | AA37: 0 | AB37: 0 | AC37: 0 | AD37: =Water!#REF! -> #REF! | AE37: =Water!#REF! -> #REF! | AF37: =Water!#REF! -> #REF! | AG37: =Gas!#REF! -> #REF! | AH37: =Gas!#REF! -> #REF! | AI37: =Gas!#REF! -> #REF! | AJ37: =Gas!#REF! -> #REF! | AK37: =Gas!#REF! -> #REF! | AL37: =Gas!#REF! -> #REF! | AM37: =Gas!#REF! -> #REF! | AN37: =Gas!#REF! -> #REF! | ... AS37: =Gas!#REF! -> #REF! | AT37: =Elect!BK39 -> 0 | AU37: =Elect!BI39 -> 0 | AX37: 0 | AY37: 0 | AZ37: 9453.8714 | BA37: 0 | BB37: 0 | BC37: =Elect!BJ39 -> 0 | BD37: =Elect!#REF! -> #REF! | BE37: =Elect!#REF! -> #REF! | BF37: =Elect!#REF! -> #REF! | BG37: =Elect!#REF! -> #REF! | BH37: 0 | BI37: 0 | BJ37: 0 | BK37: 0 | BL37: 0 | BM37: =Water!U42 -> 0 | BN37: =Water!W42 -> 0 | BO37: =Water!X42 -> 0 | BP37: =Water!Y42 -> 0 | BQ37: =Water!Z42 -> 0
A38: Total RFC | B38: 784008.53 | C38: =Elect!J40 -> 0 | D38: 0 | E38: =Elect!M40 -> 0 | F38: 0 | G38: =Elect!O40 -> 0 | H38: 0 | I38: =Water!C43 -> 0 | J38: 0 | K38: =Water!E44 -> 0 | L38: 8 | M38: =Water!#REF! -> #REF! | N38: =Water!#REF! -> #REF! | O38: 0 | P38: =Water!H43 -> 0 | Q38: 0 | R38: =Water!O43 -> 0 | S38: 0 | T38: =Water!#REF! -> #REF! | U38: 0 | V38: =Water!#REF! -> #REF! | W38: 0 | X38: =Water!Q43 -> 0 | Y38: 8 | Z38: =Water!#REF! -> #REF! | AA38: 0 | AB38: 0 | AC38: 0 | AD38: =Water!#REF! -> #REF! | AE38: =Water!#REF! -> #REF! | AF38: =Water!#REF! -> #REF! | AG38: =Gas!#REF! -> #REF! | AH38: =Gas!#REF! -> #REF! | AI38: =Gas!#REF! -> #REF! | AJ38: =Gas!#REF! -> #REF! | AK38: =Gas!#REF! -> #REF! | AL38: =Gas!#REF! -> #REF! | AM38: =Gas!#REF! -> #REF! | AN38: =Gas!#REF! -> #REF! | ... AS38: =Gas!#REF! -> #REF! | AT38: =Elect!BK40 -> 0 | AU38: =Elect!BI40 -> 0 | AX38: 38.173558 | AY38: 19.219193 | AZ38: 208225.85 | BA38: 10.138565 | BB38: 5.1044505 | BC38: =Elect!BJ40 -> 0 | BD38: =Elect!#REF! -> #REF! | BE38: =Elect!#REF! -> #REF! | BF38: =Elect!#REF! -> #REF! | BG38: =Elect!#REF! -> #REF! | BH38: 0 | BI38: 0 | BJ38: 127385.62 | BK38: 6.2024355 | BL38: 3.1227323 | BM38: =Water!U43 -> 0 | BN38: =Water!W43 -> 0 | BO38: =Water!X43 -> 0 | BP38: =Water!Y43 -> 0 | BQ38: =Water!Z43 -> 0
A39: RFC MTD | B39: 784008.53 | C39: =Elect!J41 -> 0 | D39: 0 | E39: =Elect!M41 -> 0 | F39: 0 | G39: =Elect!O41 -> 0 | H39: 0 | I39: =Water!C44 -> 0 | J39: 0 | K39: =Water!E45 -> 0 | L39: 9 | M39: =Water!#REF! -> #REF! | N39: =Water!#REF! -> #REF! | O39: 0 | P39: =Water!H44 -> 0 | Q39: 0 | R39: =Water!O44 -> 0 | S39: 0 | T39: =Water!#REF! -> #REF! | U39: 0 | V39: =Water!#REF! -> #REF! | W39: 0 | X39: =Water!Q44 -> 0 | Y39: 9 | Z39: =Water!#REF! -> #REF! | AA39: 0 | AB39: 0 | AC39: 0 | AD39: =Water!#REF! -> #REF! | AE39: =Water!#REF! -> #REF! | AF39: =Water!#REF! -> #REF! | AG39: =Gas!#REF! -> #REF! | AH39: =Gas!#REF! -> #REF! | AI39: =Gas!#REF! -> #REF! | AJ39: =Gas!#REF! -> #REF! | AK39: =Gas!#REF! -> #REF! | AL39: =Gas!#REF! -> #REF! | AM39: =Gas!#REF! -> #REF! | AN39: =Gas!#REF! -> #REF! | ... AS39: =Gas!#REF! -> #REF! | AT39: =Elect!BK41 -> 0 | AU39: =Elect!BI41 -> 0 | AX39: 38.173558 | AY39: 19.219193 | AZ39: 208225.85 | BA39: 10.138565 | BB39: 5.1044505 | BC39: =Elect!BJ41 -> 0 | BD39: =Elect!#REF! -> #REF! | BE39: =Elect!#REF! -> #REF! | BF39: =Elect!#REF! -> #REF! | BG39: =Elect!#REF! -> #REF! | BH39: 0 | BI39: 0 | BJ39: 115057.98 | BK39: 6.2024355 | BL39: 3.1227323 | BM39: =Water!U44 -> 0 | BN39: =Water!W44 -> 0 | BO39: =Water!X44 -> #VALUE! | BP39: =Water!Y44 -> #VALUE! | BQ39: =Water!Z44 -> #VALUE!
A40: AVER RFC | B40: 28000.305 | C40: =Elect!J42 -> 0 | D40: 0 | E40: =Elect!M42 -> 0 | F40: 0 | G40: =Elect!O42 -> 0 | H40: 0 | I40: =Water!C45 -> 0 | J40: 0 | K40: =Water!E46 -> 0 | L40: 10 | M40: =Water!#REF! -> #REF! | N40: =Water!#REF! -> #REF! | O40: 0 | P40: =Water!H45 -> 0 | Q40: 0 | R40: =Water!O45 -> 0 | S40: 0 | T40: =Water!#REF! -> #REF! | U40: 0 | V40: =Water!#REF! -> #REF! | W40: 0 | X40: =Water!Q45 -> 0 | Y40: 10 | Z40: =Water!#REF! -> #REF! | AA40: 0 | AB40: 0 | AC40: 0 | AD40: =Water!#REF! -> #REF! | AE40: =Water!#REF! -> #REF! | AF40: =Water!#REF! -> #REF! | AG40: =Gas!#REF! -> #REF! | AH40: =Gas!#REF! -> #REF! | AI40: =Gas!#REF! -> #REF! | AJ40: =Gas!#REF! -> #REF! | AK40: =Gas!#REF! -> #REF! | AL40: =Gas!#REF! -> #REF! | AM40: =Gas!#REF! -> #REF! | AN40: =Gas!#REF! -> #REF! | ... AS40: =Gas!#REF! -> #REF! | AT40: =Elect!BK42 -> 0 | AU40: =Elect!BI42 -> 0 | AX40: 0 | AY40: 0 | AZ40: 7436.6375 | BA40: 0 | BB40: 0 | BC40: =Elect!BJ42 -> 0 | BD40: =Elect!#REF! -> #REF! | BE40: =Elect!#REF! -> #REF! | BF40: =Elect!#REF! -> #REF! | BG40: =Elect!#REF! -> #REF! | BH40: 1.1254646 | BI40: 0.57264868 | BJ40: 4109.2135 | BK40: 0 | BL40: 0 | BM40: =Water!U45 -> 0 | BN40: =Water!W45 -> 0 | BO40: =Water!X45 -> #VALUE! | BP40: =Water!Y45 -> 0 | BQ40: =Water!Z45 -> 0

Sheet Temp.
A2: HILTON INTERNATIONAL
A3: GULF, MIDDLE EAST AND ASIA SPECIFIC
A4: HOTEL:HILTON HURGHADA LONG BEACH RESORT | G4: =Elect!A1 -> January
A7: DATE | B7: MAX TEMP | C7: MIN TEMP | D7: MAX TEMP | E7: MIN TEMP | F7: DAY | G7: DD. C | H7: DD. H | I7: MTD | J7: MTD
B8: C | C8: C | D8: F | E8: F | F8: PARAMETER | I8: COOLING | J8: HEATING
A10: 1 | D10: =SUM((B10*9/5)+32) -> 32 | E10: =SUM((C10*9/5)+32) -> 32 | F10: =SUM(((B10+C10)/2)-18.33) -> -18.33 | G10: =SUM(0+(F10)+ABS(F10))/2 -> 0 | H10: =IF((SUM(0-(F10)+ABS(F10))/2)<18,SUM(0-(F10)+ABS(F10))/2,0) -> 0 | I10: =SUM(G10:G10) -> 0 | J10: =SUM(H10:H10) -> 0
A11: 2 | D11: =SUM((B11*9/5)+32) -> 32 | E11: =SUM((C11*9/5)+32) -> 32 | F11: =SUM(((B11+C11)/2)-18.33) -> -18.33 | G11: =SUM(0+(F11)+ABS(F11))/2 -> 0 | H11: =IF((SUM(0-(F11)+ABS(F11))/2)<18,SUM(0-(F11)+ABS(F11))/2,0) -> 0 | I11: =SUM(G10:G11) -> 0 | J11: =SUM(H10:H11) -> 0
A12: 3 | D12: =SUM((B12*9/5)+32) -> 32 | E12: =SUM((C12*9/5)+32) -> 32 | F12: =SUM(((B12+C12)/2)-18.33) -> -18.33 | G12: =SUM(0+(F12)+ABS(F12))/2 -> 0 | H12: =IF((SUM(0-(F12)+ABS(F12))/2)<18,SUM(0-(F12)+ABS(F12))/2,0) -> 0 | I12: =SUM(G10:G12) -> 0 | J12: =SUM(H10:H12) -> 0
A13: 4 | D13: =SUM((B13*9/5)+32) -> 32 | E13: =SUM((C13*9/5)+32) -> 32 | F13: =SUM(((B13+C13)/2)-18.33) -> -18.33 | G13: =SUM(0+(F13)+ABS(F13))/2 -> 0 | H13: =IF((SUM(0-(F13)+ABS(F13))/2)<18,SUM(0-(F13)+ABS(F13))/2,0) -> 0 | I13: =SUM(G10:G13) -> 0 | J13: =SUM(H10:H13) -> 0
A14: 5 | D14: =SUM((B14*9/5)+32) -> 32 | E14: =SUM((C14*9/5)+32) -> 32 | F14: =SUM(((B14+C14)/2)-18.33) -> -18.33 | G14: =SUM(0+(F14)+ABS(F14))/2 -> 0 | H14: =IF((SUM(0-(F14)+ABS(F14))/2)<18,SUM(0-(F14)+ABS(F14))/2,0) -> 0 | I14: =SUM(G10:G14) -> 0 | J14: =SUM(H10:H14) -> 0
A15: 6 | D15: =SUM((B15*9/5)+32) -> 32 | E15: =SUM((C15*9/5)+32) -> 32 | F15: =SUM(((B15+C15)/2)-18.33) -> -18.33 | G15: =SUM(0+(F15)+ABS(F15))/2 -> 0 | H15: =IF((SUM(0-(F15)+ABS(F15))/2)<18,SUM(0-(F15)+ABS(F15))/2,0) -> 0 | I15: =SUM(G10:G15) -> 0 | J15: =SUM(H10:H15) -> 0
A16: 7 | D16: =SUM((B16*9/5)+32) -> 32 | E16: =SUM((C16*9/5)+32) -> 32 | F16: =SUM(((B16+C16)/2)-18.33) -> -18.33 | G16: =SUM(0+(F16)+ABS(F16))/2 -> 0 | H16: =IF((SUM(0-(F16)+ABS(F16))/2)<18,SUM(0-(F16)+ABS(F16))/2,0) -> 0 | I16: =SUM(G10:G16) -> 0 | J16: =SUM(H10:H16) -> 0
A17: 8 | D17: =SUM((B17*9/5)+32) -> 32 | E17: =SUM((C17*9/5)+32) -> 32 | F17: =SUM(((B17+C17)/2)-18.33) -> -18.33 | G17: =SUM(0+(F17)+ABS(F17))/2 -> 0 | H17: =IF((SUM(0-(F17)+ABS(F17))/2)<18,SUM(0-(F17)+ABS(F17))/2,0) -> 0 | I17: =SUM(G10:G17) -> 0 | J17: =SUM(H10:H17) -> 0
A18: 9 | D18: =SUM((B18*9/5)+32) -> 32 | E18: =SUM((C18*9/5)+32) -> 32 | F18: =SUM(((B18+C18)/2)-18.33) -> -18.33 | G18: =SUM(0+(F18)+ABS(F18))/2 -> 0 | H18: =IF((SUM(0-(F18)+ABS(F18))/2)<18,SUM(0-(F18)+ABS(F18))/2,0) -> 0 | I18: =SUM(G10:G18) -> 0 | J18: =SUM(H10:H18) -> 0
A19: 10 | D19: =SUM((B19*9/5)+32) -> 32 | E19: =SUM((C19*9/5)+32) -> 32 | F19: =SUM(((B19+C19)/2)-18.33) -> -18.33 | G19: =SUM(0+(F19)+ABS(F19))/2 -> 0 | H19: =IF((SUM(0-(F19)+ABS(F19))/2)<18,SUM(0-(F19)+ABS(F19))/2,0) -> 0 | I19: =SUM(G10:G19) -> 0 | J19: =SUM(H10:H19) -> 0
A20: 11 | D20: =SUM((B20*9/5)+32) -> 32 | E20: =SUM((C20*9/5)+32) -> 32 | F20: =SUM(((B20+C20)/2)-18.33) -> -18.33 | G20: =SUM(0+(F20)+ABS(F20))/2 -> 0 | H20: =IF((SUM(0-(F20)+ABS(F20))/2)<18,SUM(0-(F20)+ABS(F20))/2,0) -> 0 | I20: =SUM(G10:G20) -> 0 | J20: =SUM(H10:H20) -> 0
A21: 12 | D21: =SUM((B21*9/5)+32) -> 32 | E21: =SUM((C21*9/5)+32) -> 32 | F21: =SUM(((B21+C21)/2)-18.33) -> -18.33 | G21: =SUM(0+(F21)+ABS(F21))/2 -> 0 | H21: =IF((SUM(0-(F21)+ABS(F21))/2)<18,SUM(0-(F21)+ABS(F21))/2,0) -> 0 | I21: =SUM(G10:G21) -> 0 | J21: =SUM(H10:H21) -> 0
A22: 13 | D22: =SUM((B22*9/5)+32) -> 32 | E22: =SUM((C22*9/5)+32) -> 32 | F22: =SUM(((B22+C22)/2)-18.33) -> -18.33 | G22: =SUM(0+(F22)+ABS(F22))/2 -> 0 | H22: =IF((SUM(0-(F22)+ABS(F22))/2)<18,SUM(0-(F22)+ABS(F22))/2,0) -> 0 | I22: =SUM(G10:G22) -> 0 | J22: =SUM(H10:H22) -> 0
A23: 14 | D23: =SUM((B23*9/5)+32) -> 32 | E23: =SUM((C23*9/5)+32) -> 32 | F23: =SUM(((B23+C23)/2)-18.33) -> -18.33 | G23: =SUM(0+(F23)+ABS(F23))/2 -> 0 | H23: =IF((SUM(0-(F23)+ABS(F23))/2)<18,SUM(0-(F23)+ABS(F23))/2,0) -> 0 | I23: =SUM(G10:G23) -> 0 | J23: =SUM(H10:H23) -> 0
A24: 15 | D24: =SUM((B24*9/5)+32) -> 32 | E24: =SUM((C24*9/5)+32) -> 32 | F24: =SUM(((B24+C24)/2)-18.33) -> -18.33 | G24: =SUM(0+(F24)+ABS(F24))/2 -> 0 | H24: =IF((SUM(0-(F24)+ABS(F24))/2)<18,SUM(0-(F24)+ABS(F24))/2,0) -> 0 | I24: =SUM(G11:G24) -> 0 | J24: =SUM(H11:H24) -> 0
A25: 16 | D25: =SUM((B25*9/5)+32) -> 32 | E25: =SUM((C25*9/5)+32) -> 32 | F25: =SUM(((B25+C25)/2)-18.33) -> -18.33 | G25: =SUM(0+(F25)+ABS(F25))/2 -> 0 | H25: =IF((SUM(0-(F25)+ABS(F25))/2)<18,SUM(0-(F25)+ABS(F25))/2,0) -> 0 | I25: =SUM(G12:G25) -> 0 | J25: =SUM(H12:H25) -> 0
A26: 17 | D26: =SUM((B26*9/5)+32) -> 32 | E26: =SUM((C26*9/5)+32) -> 32 | F26: =SUM(((B26+C26)/2)-18.33) -> -18.33 | G26: =SUM(0+(F26)+ABS(F26))/2 -> 0 | H26: =IF((SUM(0-(F26)+ABS(F26))/2)<18,SUM(0-(F26)+ABS(F26))/2,0) -> 0 | I26: =SUM(G13:G26) -> 0 | J26: =SUM(H13:H26) -> 0
A27: 18 | D27: =SUM((B27*9/5)+32) -> 32 | E27: =SUM((C27*9/5)+32) -> 32 | F27: =SUM(((B27+C27)/2)-18.33) -> -18.33 | G27: =SUM(0+(F27)+ABS(F27))/2 -> 0 | H27: =IF((SUM(0-(F27)+ABS(F27))/2)<18,SUM(0-(F27)+ABS(F27))/2,0) -> 0 | I27: =SUM(G14:G27) -> 0 | J27: =SUM(H14:H27) -> 0
A28: 19 | D28: =SUM((B28*9/5)+32) -> 32 | E28: =SUM((C28*9/5)+32) -> 32 | F28: =SUM(((B28+C28)/2)-18.33) -> -18.33 | G28: =SUM(0+(F28)+ABS(F28))/2 -> 0 | H28: =IF((SUM(0-(F28)+ABS(F28))/2)<18,SUM(0-(F28)+ABS(F28))/2,0) -> 0 | I28: =SUM(G15:G28) -> 0 | J28: =SUM(H15:H28) -> 0
A29: 20 | D29: =SUM((B29*9/5)+32) -> 32 | E29: =SUM((C29*9/5)+32) -> 32 | F29: =SUM(((B29+C29)/2)-18.33) -> -18.33 | G29: =SUM(0+(F29)+ABS(F29))/2 -> 0 | H29: =IF((SUM(0-(F29)+ABS(F29))/2)<18,SUM(0-(F29)+ABS(F29))/2,0) -> 0 | I29: =SUM(G16:G29) -> 0 | J29: =SUM(H16:H29) -> 0
A30: 21 | D30: =SUM((B30*9/5)+32) -> 32 | E30: =SUM((C30*9/5)+32) -> 32 | F30: =SUM(((B30+C30)/2)-18.33) -> -18.33 | G30: =SUM(0+(F30)+ABS(F30))/2 -> 0 | H30: =IF((SUM(0-(F30)+ABS(F30))/2)<18,SUM(0-(F30)+ABS(F30))/2,0) -> 0 | I30: =SUM(G17:G30) -> 0 | J30: =SUM(H17:H30) -> 0
A31: 22 | D31: =SUM((B31*9/5)+32) -> 32 | E31: =SUM((C31*9/5)+32) -> 32 | F31: =SUM(((B31+C31)/2)-18.33) -> -18.33 | G31: =SUM(0+(F31)+ABS(F31))/2 -> 0 | H31: =IF((SUM(0-(F31)+ABS(F31))/2)<18,SUM(0-(F31)+ABS(F31))/2,0) -> 0 | I31: =SUM(G18:G31) -> 0 | J31: =SUM(H18:H31) -> 0
A32: 23 | D32: =SUM((B32*9/5)+32) -> 32 | E32: =SUM((C32*9/5)+32) -> 32 | F32: =SUM(((B32+C32)/2)-18.33) -> -18.33 | G32: =SUM(0+(F32)+ABS(F32))/2 -> 0 | H32: =IF((SUM(0-(F32)+ABS(F32))/2)<18,SUM(0-(F32)+ABS(F32))/2,0) -> 0 | I32: =SUM(G19:G32) -> 0 | J32: =SUM(H19:H32) -> 0
A33: 24 | D33: =SUM((B33*9/5)+32) -> 32 | E33: =SUM((C33*9/5)+32) -> 32 | F33: =SUM(((B33+C33)/2)-18.33) -> -18.33 | G33: =SUM(0+(F33)+ABS(F33))/2 -> 0 | H33: =IF((SUM(0-(F33)+ABS(F33))/2)<18,SUM(0-(F33)+ABS(F33))/2,0) -> 0 | I33: =SUM(G20:G33) -> 0 | J33: =SUM(H20:H33) -> 0
A34: 25 | D34: =SUM((B34*9/5)+32) -> 32 | E34: =SUM((C34*9/5)+32) -> 32 | F34: =SUM(((B34+C34)/2)-18.33) -> -18.33 | G34: =SUM(0+(F34)+ABS(F34))/2 -> 0 | H34: =IF((SUM(0-(F34)+ABS(F34))/2)<18,SUM(0-(F34)+ABS(F34))/2,0) -> 0 | I34: =SUM(G21:G34) -> 0 | J34: =SUM(H21:H34) -> 0
... A40: 31 | D40: =SUM((B40*9/5)+32) -> 32 | E40: =SUM((C40*9/5)+32) -> 32 | F40: =SUM(((B40+C40)/2)-18.33) -> -18.33 | G40: =SUM(0+(F40)+ABS(F40))/2 -> 0 | H40: =IF((SUM(0-(F40)+ABS(F40))/2)<18,SUM(0-(F40)+ABS(F40))/2,0) -> 0 | I40: =SUM(G27:G40) -> 0 | J40: =SUM(H27:H40) -> 0
E42: =SUM(G10:G40) -> 0 | F42: deg c
E44: =SUM(H10:H40) -> 0 | F44: deg c

Sheet M-Rep
B3: =Elect!A1 -> January
D4: Y.T.D
A5: Energy breakdown | C5: 2009 | D5: 2005 | E5: 2006
A6: Elect.
A7: Chillers KWH | C7: N/A | D7: N/A | E7: N/A
A8: Laundry KWH | C8: N/A | D8: N/A | E8: N/A
A9: Kitchen KWH | C9: N/A | D9: N/A | E9: N/A
A10: Gas
A11: Kit M3 | C11: =Gas!#REF!/1000 -> #REF!
A12: Laundry M3 | C12: N/A | D12: 0 | E12: #REF!
A13: Water | D13: N/A | E13: N/A
A14: Laundry HW | C14: N/A
A15: Laundry CW | C15: N/A
A16: Kit HW | C16: N/A
A17: kIt CW | C17: N/A | D17: N/A | E17: N/A
A18: Dmstc HW | C18: N/A | D18: N/A | E18: N/A
A19: Dmstc CW | C19: N/A | D19: N/A | E19: N/A
A20: S.Pool MKUP | C20: =#REF! -> #REF! | D20: N/A | E20: N/A
A21: Ctower MKUP | C21: N/A | D21: N/A | E21: N/A
A22: Gardens Irrigat. | C22: =Water!S38 -> 0 | D22: N/A | E22: N/A
A23: Swage water treatment | C23: =Water!#REF! -> #REF! | D23: 27437 | E23: #REF!
A24: Utilities consumption | D24: N/A | E24: N/A
A25: Elect. Kwh | C25: =Elect!J34 -> 3670 | D25: 12266 | E25: 814
A26: M.D (9.5 LE) | D26: 147773 | E26: #REF!
A27: Water M3 | C27: =Water!H38 -> 7519.12
A28: Fuel Ltr | C28: =Gas!#REF!*1000 -> #REF! | D28: 12876868 | E28: 14500800
A29: Gas M3/ Boilers, chillers,..etc | C29: N/A | D29: 28880 | E29: 32980
A30: Gas M3 Kitchen | C30: =Gas!#REF!/1000 -> #REF! | D30: 244283 | E30: 252530.66
A31: Total Energy | D31: 620770 | E31: #REF!
A32: Control Parameters | D32: #REF! | E32: N/A
A33: No. of Rooms % occ. | C33: =YTD!Q4 -> 0 | D33: 39.395 | E33: #REF!
A34: No. of Occ. Rooms | C34: =YTD!Q5 -> 0
A35: guest count | C35: =YTD!Q6 -> 0
A36: Food covers | D36: #REF! | E36: #REF!
A37: Laundry W. Kg | D37: 0.8807 | E37: 0.46351998
A38: DDC | C38: =Temp.!E42 -> 0 | D38: 196150 | E38: 237021
A39: DDH | C39: =Temp.!E44 -> 0 | D39: 400070 | E39: 466105
A40: Utilities Entergy cost | D40: 1583714 | E40: 1940567
A41: Elect. | C41: =Elect!#REF! -> #REF! | D41: 1690339 | E41: 3118671.6
A42: M.D | C42: =C26*Elect!#REF! -> #REF! | D42: 2381.51 | E42: 2480.24
A43: Water | C43: =Water!X38 -> 29241.28 | D43: 112 | E43: 97.53
A44: Fuel | C44: =Gas!#REF! -> #REF!
A45: Gas Boilers, chillers,etc.. | C45: N/A | D45: 2138156.8 | E45: #REF!
A46: Gas Kitchen | C46: =C30*Gas!M2*1000 -> #REF! | D46: 223044.2 | E46: #REF!
A47: TOTAL LE | C47: =SUM(C41:C46) -> #REF! | D47: 1330535.7 | E47: 1382037.4
A48: No. of POMEC Staff | D48: 330278 | E48: #REF!
A49: Hotel Age | C49: 6 | D49: N/A | E49: N/A
A50: No. of rooms | C50: =31*912 -> 28272 | D50: 36597.525 | E50: #REF!
A51: Building Volume | C51: 243175 | D51: =SUM(D45:D50) -> 4058612.3 | E51: =SUM(E45:E50) -> #REF!
A52: Building area | C52: 75064
A53: US$ Rate | C53: 5.59402 | D53: 61 | E53: 72
A54: Total R&M MTD | C54: =YTD!Q65 -> 0 | D54: #REF! | E54: 243175 | F54: =YTD!Q64 -> 0
A55: Staff - HLP | D55: #REF! | E55: 75064
A56: Staff - R&M | D56: 5.755 | E56: 5.65951
A57: Staff - Grounds

Sheet YTD
A1: =Elect!A1 -> January | H1: Actual 2014
C3: JAN | D3: FEB | E3: MAR | F3: APR | G3: MAY | H3: JUN | I3: JUL | J3: AUG | K3: SEP | L3: OCT | M3: NOV | N3: DEC | O3: TOTAL | P3: YTD | Q3: Month Act
A4: Occ Room % | O4: =SUM(C4:N4) -> 0 | P4: =(IF($A$1=39814,C4,(IF($A$1=39845,SUM(C4:D4),(IF($A$1=39873,SUM(C4:E4),(IF($A$1=39904,SUM(C4:F4),(IF($A$1=39934,SUM(C4:G4),(IF($A$1=39965,SUM(C4:H4),(IF($A$1=39995,SUM(C4:I4),0)))))))))))))+(IF($A$1=40026,SUM(C4:J4),(IF($A$1=40057,SUM(C4:K4),(IF($A$1=40087,SUM(C4:L4),(IF($A$1=40118,SUM(C4:M4))))))))))+(IF($A$1=40148,SUM(C4:N4),0)) -> 0 | Q4: =(IF($A$1=39814,C4,(IF($A$1=39845,D4,(IF($A$1=39873,E4,(IF($A$1=39904,F4,(IF($A$1=39934,G4,(IF($A$1=39965,H4,(IF($A$1=39995,I4,0)))))))))))))+(IF($A$1=40026,J4,(IF($A$1=40057,K4,(IF($A$1=40087,L4,(IF($A$1=40118,M4)))))))))+(IF($A$1=40148,N4,0)) -> 0 | S4: 40179 | DE4: 1
A5: Occ Room | C5: 25072 | D5: =Elect!BI34 -> 102 | O5: =SUM(C5:N5) -> 25174 | P5: =(IF($A$1=40179,C5,(IF($A$1=40210,SUM(C5:D5),(IF($A$1=40238,SUM(C5:E5),(IF($A$1=40269,SUM(C5:F5),(IF($A$1=40299,SUM(C5:G5),(IF($A$1=40330,SUM(C5:H5),(IF($A$1=40360,SUM(C5:I5),0)))))))))))))+(IF($A$1=40391,SUM(C5:J5),(IF($A$1=40422,SUM(C5:K5),(IF($A$1=40452,SUM(C5:L5),(IF($A$1=40483,SUM(C5:M5))))))))))+(IF($A$1=40513,SUM(C5:N5),0)) -> 0 | Q5: =(IF($A$1=40179,C5,(IF($A$1=40210,D5,(IF($A$1=40238,E5,(IF($A$1=40269,F5,(IF($A$1=40299,G5,(IF($A$1=40330,H5,(IF($A$1=40360,I5,0)))))))))))))+(IF($A$1=40391,J5,(IF($A$1=40422,K5,(IF($A$1=40452,L5,(IF($A$1=40483,M5)))))))))+(IF($A$1=40513,N5,0)) -> 0 | S5: 40210 | DE5: 2
A6: Number of Guest | C6: 50662 | D6: =Elect!BK34 -> 195 | O6: =SUM(C6:N6) -> 50857 | P6: =(IF($A$1=40179,C6,(IF($A$1=40210,SUM(C6:D6),(IF($A$1=40238,SUM(C6:E6),(IF($A$1=40269,SUM(C6:F6),(IF($A$1=40299,SUM(C6:G6),(IF($A$1=40330,SUM(C6:H6),(IF($A$1=40360,SUM(C6:I6),0)))))))))))))+(IF($A$1=40391,SUM(C6:J6),(IF($A$1=40422,SUM(C6:K6),(IF($A$1=40452,SUM(C6:L6),(IF($A$1=40483,SUM(C6:M6))))))))))+(IF($A$1=40513,SUM(C6:N6),0)) -> 0 | Q6: =(IF($A$1=40179,C6,(IF($A$1=40210,D6,(IF($A$1=40238,E6,(IF($A$1=40269,F6,(IF($A$1=40299,G6,(IF($A$1=40330,H6,(IF($A$1=40360,I6,0)))))))))))))+(IF($A$1=40391,J6,(IF($A$1=40422,K6,(IF($A$1=40452,L6,(IF($A$1=40483,M6)))))))))+(IF($A$1=40513,N6,0)) -> 0 | S6: 40238 | DE6: 3
A7: PAY & REL. EXP. | O7: =SUM(C7:N7) -> 0 | P7: =(IF($A$1=40179,C7,(IF($A$1=40210,SUM(C7:D7),(IF($A$1=40238,SUM(C7:E7),(IF($A$1=40269,SUM(C7:F7),(IF($A$1=40299,SUM(C7:G7),(IF($A$1=40330,SUM(C7:H7),(IF($A$1=40360,SUM(C7:I7),0)))))))))))))+(IF($A$1=40391,SUM(C7:J7),(IF($A$1=40422,SUM(C7:K7),(IF($A$1=40452,SUM(C7:L7),(IF($A$1=40483,SUM(C7:M7))))))))))+(IF($A$1=40513,SUM(C7:N7),0)) -> 0 | Q7: =(IF($A$1=40179,C7,(IF($A$1=40210,D7,(IF($A$1=40238,E7,(IF($A$1=40269,F7,(IF($A$1=40299,G7,(IF($A$1=40330,H7,(IF($A$1=40360,I7,0)))))))))))))+(IF($A$1=40391,J7,(IF($A$1=40422,K7,(IF($A$1=40452,L7,(IF($A$1=40483,M7)))))))))+(IF($A$1=40513,N7,0)) -> 0
A8: SALARIES | B8: 53241001 | O8: =SUM(C8:N8) -> 0 | P8: =(IF($A$1=40179,C8,(IF($A$1=40210,SUM(C8:D8),(IF($A$1=40238,SUM(C8:E8),(IF($A$1=40269,SUM(C8:F8),(IF($A$1=40299,SUM(C8:G8),(IF($A$1=40330,SUM(C8:H8),(IF($A$1=40360,SUM(C8:I8),0)))))))))))))+(IF($A$1=40391,SUM(C8:J8),(IF($A$1=40422,SUM(C8:K8),(IF($A$1=40452,SUM(C8:L8),(IF($A$1=40483,SUM(C8:M8))))))))))+(IF($A$1=40513,SUM(C8:N8),0)) -> 0 | Q8: =(IF($A$1=40179,C8,(IF($A$1=40210,D8,(IF($A$1=40238,E8,(IF($A$1=40269,F8,(IF($A$1=40299,G8,(IF($A$1=40330,H8,(IF($A$1=40360,I8,0)))))))))))))+(IF($A$1=40391,J8,(IF($A$1=40422,K8,(IF($A$1=40452,L8,(IF($A$1=40483,M8)))))))))+(IF($A$1=40513,N8,0)) -> 0
A9: EXTRA WAGES | B9: 53242099 | O9: =SUM(C9:N9) -> 0 | P9: =(IF($A$1=40179,C9,(IF($A$1=40210,SUM(C9:D9),(IF($A$1=40238,SUM(C9:E9),(IF($A$1=40269,SUM(C9:F9),(IF($A$1=40299,SUM(C9:G9),(IF($A$1=40330,SUM(C9:H9),(IF($A$1=40360,SUM(C9:I9),0)))))))))))))+(IF($A$1=40391,SUM(C9:J9),(IF($A$1=40422,SUM(C9:K9),(IF($A$1=40452,SUM(C9:L9),(IF($A$1=40483,SUM(C9:M9))))))))))+(IF($A$1=40513,SUM(C9:N9),0)) -> 0 | Q9: =(IF($A$1=40179,C9,(IF($A$1=40210,D9,(IF($A$1=40238,E9,(IF($A$1=40269,F9,(IF($A$1=40299,G9,(IF($A$1=40330,H9,(IF($A$1=40360,I9,0)))))))))))))+(IF($A$1=40391,J9,(IF($A$1=40422,K9,(IF($A$1=40452,L9,(IF($A$1=40483,M9)))))))))+(IF($A$1=40513,N9,0)) -> 0
A10: SERVICE | B10: 53243001 | O10: =SUM(C10:N10) -> 0 | P10: =(IF($A$1=40179,C10,(IF($A$1=40210,SUM(C10:D10),(IF($A$1=40238,SUM(C10:E10),(IF($A$1=40269,SUM(C10:F10),(IF($A$1=40299,SUM(C10:G10),(IF($A$1=40330,SUM(C10:H10),(IF($A$1=40360,SUM(C10:I10),0)))))))))))))+(IF($A$1=40391,SUM(C10:J10),(IF($A$1=40422,SUM(C10:K10),(IF($A$1=40452,SUM(C10:L10),(IF($A$1=40483,SUM(C10:M10))))))))))+(IF($A$1=40513,SUM(C10:N10),0)) -> 0 | Q10: =(IF($A$1=40179,C10,(IF($A$1=40210,D10,(IF($A$1=40238,E10,(IF($A$1=40269,F10,(IF($A$1=40299,G10,(IF($A$1=40330,H10,(IF($A$1=40360,I10,0)))))))))))))+(IF($A$1=40391,J10,(IF($A$1=40422,K10,(IF($A$1=40452,L10,(IF($A$1=40483,M10)))))))))+(IF($A$1=40513,N10,0)) -> 0
A11: RELATED EXP. | B11: 53244001 | O11: =SUM(C11:N11) -> 0 | P11: =(IF($A$1=40179,C11,(IF($A$1=40210,SUM(C11:D11),(IF($A$1=40238,SUM(C11:E11),(IF($A$1=40269,SUM(C11:F11),(IF($A$1=40299,SUM(C11:G11),(IF($A$1=40330,SUM(C11:H11),(IF($A$1=40360,SUM(C11:I11),0)))))))))))))+(IF($A$1=40391,SUM(C11:J11),(IF($A$1=40422,SUM(C11:K11),(IF($A$1=40452,SUM(C11:L11),(IF($A$1=40483,SUM(C11:M11))))))))))+(IF($A$1=40513,SUM(C11:N11),0)) -> 0 | Q11: =(IF($A$1=40179,C11,(IF($A$1=40210,D11,(IF($A$1=40238,E11,(IF($A$1=40269,F11,(IF($A$1=40299,G11,(IF($A$1=40330,H11,(IF($A$1=40360,I11,0)))))))))))))+(IF($A$1=40391,J11,(IF($A$1=40422,K11,(IF($A$1=40452,L11,(IF($A$1=40483,M11)))))))))+(IF($A$1=40513,N11,0)) -> 0
A12: EMPL. MEALS | B12: 53245001 | O12: =SUM(C12:N12) -> 0 | P12: =(IF($A$1=40179,C12,(IF($A$1=40210,SUM(C12:D12),(IF($A$1=40238,SUM(C12:E12),(IF($A$1=40269,SUM(C12:F12),(IF($A$1=40299,SUM(C12:G12),(IF($A$1=40330,SUM(C12:H12),(IF($A$1=40360,SUM(C12:I12),0)))))))))))))+(IF($A$1=40391,SUM(C12:J12),(IF($A$1=40422,SUM(C12:K12),(IF($A$1=40452,SUM(C12:L12),(IF($A$1=40483,SUM(C12:M12))))))))))+(IF($A$1=40513,SUM(C12:N12),0)) -> 0 | Q12: =(IF($A$1=40179,C12,(IF($A$1=40210,D12,(IF($A$1=40238,E12,(IF($A$1=40269,F12,(IF($A$1=40299,G12,(IF($A$1=40330,H12,(IF($A$1=40360,I12,0)))))))))))))+(IF($A$1=40391,J12,(IF($A$1=40422,K12,(IF($A$1=40452,L12,(IF($A$1=40483,M12)))))))))+(IF($A$1=40513,N12,0)) -> 0
O13: =SUM(C13:N13) -> 0 | P13: =(IF($A$1=40179,C13,(IF($A$1=40210,SUM(C13:D13),(IF($A$1=40238,SUM(C13:E13),(IF($A$1=40269,SUM(C13:F13),(IF($A$1=40299,SUM(C13:G13),(IF($A$1=40330,SUM(C13:H13),(IF($A$1=40360,SUM(C13:I13),0)))))))))))))+(IF($A$1=40391,SUM(C13:J13),(IF($A$1=40422,SUM(C13:K13),(IF($A$1=40452,SUM(C13:L13),(IF($A$1=40483,SUM(C13:M13))))))))))+(IF($A$1=40513,SUM(C13:N13),0)) -> 0 | Q13: =(IF($A$1=40179,C13,(IF($A$1=40210,D13,(IF($A$1=40238,E13,(IF($A$1=40269,F13,(IF($A$1=40299,G13,(IF($A$1=40330,H13,(IF($A$1=40360,I13,0)))))))))))))+(IF($A$1=40391,J13,(IF($A$1=40422,K13,(IF($A$1=40452,L13,(IF($A$1=40483,M13)))))))))+(IF($A$1=40513,N13,0)) -> 0
A14: TOTAL PAY & REL. | C14: 147832.84 | D14: 158624 | O14: =SUM(C14:N14) -> 306456.84 | P14: =(IF($A$1=40179,C14,(IF($A$1=40210,SUM(C14:D14),(IF($A$1=40238,SUM(C14:E14),(IF($A$1=40269,SUM(C14:F14),(IF($A$1=40299,SUM(C14:G14),(IF($A$1=40330,SUM(C14:H14),(IF($A$1=40360,SUM(C14:I14),0)))))))))))))+(IF($A$1=40391,SUM(C14:J14),(IF($A$1=40422,SUM(C14:K14),(IF($A$1=40452,SUM(C14:L14),(IF($A$1=40483,SUM(C14:M14))))))))))+(IF($A$1=40513,SUM(C14:N14),0)) -> 0 | Q14: =(IF($A$1=40179,C14,(IF($A$1=40210,D14,(IF($A$1=40238,E14,(IF($A$1=40269,F14,(IF($A$1=40299,G14,(IF($A$1=40330,H14,(IF($A$1=40360,I14,0)))))))))))))+(IF($A$1=40391,J14,(IF($A$1=40422,K14,(IF($A$1=40452,L14,(IF($A$1=40483,M14)))))))))+(IF($A$1=40513,N14,0)) -> 0 | S14: 40269 | DE14: 4
A15: ELECRICITY | B15: 53257511 | C15: 267068.09 | D15: 312865.7 | O15: =SUM(C15:N15) -> 579933.79 | P15: =(IF($A$1=40179,C15,(IF($A$1=40210,SUM(C15:D15),(IF($A$1=40238,SUM(C15:E15),(IF($A$1=40269,SUM(C15:F15),(IF($A$1=40299,SUM(C15:G15),(IF($A$1=40330,SUM(C15:H15),(IF($A$1=40360,SUM(C15:I15),0)))))))))))))+(IF($A$1=40391,SUM(C15:J15),(IF($A$1=40422,SUM(C15:K15),(IF($A$1=40452,SUM(C15:L15),(IF($A$1=40483,SUM(C15:M15))))))))))+(IF($A$1=40513,SUM(C15:N15),0)) -> 0 | Q15: =(IF($A$1=40179,C15,(IF($A$1=40210,D15,(IF($A$1=40238,E15,(IF($A$1=40269,F15,(IF($A$1=40299,G15,(IF($A$1=40330,H15,(IF($A$1=40360,I15,0)))))))))))))+(IF($A$1=40391,J15,(IF($A$1=40422,K15,(IF($A$1=40452,L15,(IF($A$1=40483,M15)))))))))+(IF($A$1=40513,N15,0)) -> 0 | S15: 40299 | DE15: 5
A16: WATER & SEWAGE | B16: 53257551 | C16: 178948 | D16: 189620 | O16: =SUM(C16:N16) -> 368568 | P16: =(IF($A$1=40179,C16,(IF($A$1=40210,SUM(C16:D16),(IF($A$1=40238,SUM(C16:E16),(IF($A$1=40269,SUM(C16:F16),(IF($A$1=40299,SUM(C16:G16),(IF($A$1=40330,SUM(C16:H16),(IF($A$1=40360,SUM(C16:I16),0)))))))))))))+(IF($A$1=40391,SUM(C16:J16),(IF($A$1=40422,SUM(C16:K16),(IF($A$1=40452,SUM(C16:L16),(IF($A$1=40483,SUM(C16:M16))))))))))+(IF($A$1=40513,SUM(C16:N16),0)) -> 0 | Q16: =(IF($A$1=40179,C16,(IF($A$1=40210,D16,(IF($A$1=40238,E16,(IF($A$1=40269,F16,(IF($A$1=40299,G16,(IF($A$1=40330,H16,(IF($A$1=40360,I16,0)))))))))))))+(IF($A$1=40391,J16,(IF($A$1=40422,K16,(IF($A$1=40452,L16,(IF($A$1=40483,M16)))))))))+(IF($A$1=40513,N16,0)) -> 0 | S16: 40330 | DE16: 6
A17: FUEL | B17: 53257571 | C17: 82735 | D17: 123809 | O17: =SUM(C17:N17) -> 206544 | P17: =(IF($A$1=40179,C17,(IF($A$1=40210,SUM(C17:D17),(IF($A$1=40238,SUM(C17:E17),(IF($A$1=40269,SUM(C17:F17),(IF($A$1=40299,SUM(C17:G17),(IF($A$1=40330,SUM(C17:H17),(IF($A$1=40360,SUM(C17:I17),0)))))))))))))+(IF($A$1=40391,SUM(C17:J17),(IF($A$1=40422,SUM(C17:K17),(IF($A$1=40452,SUM(C17:L17),(IF($A$1=40483,SUM(C17:M17))))))))))+(IF($A$1=40513,SUM(C17:N17),0)) -> 0 | Q17: =(IF($A$1=40179,C17,(IF($A$1=40210,D17,(IF($A$1=40238,E17,(IF($A$1=40269,F17,(IF($A$1=40299,G17,(IF($A$1=40330,H17,(IF($A$1=40360,I17,0)))))))))))))+(IF($A$1=40391,J17,(IF($A$1=40422,K17,(IF($A$1=40452,L17,(IF($A$1=40483,M17)))))))))+(IF($A$1=40513,N17,0)) -> 0 | S17: 40360 | DE17: 7
A18: gas | B18: 0 | C18: 0 | D18: 0 | E18: 0 | F18: 0 | G18: 0 | H18: 0 | O18: =SUM(C18:N18) -> 0 | P18: =(IF($A$1=40179,C18,(IF($A$1=40210,SUM(C18:D18),(IF($A$1=40238,SUM(C18:E18),(IF($A$1=40269,SUM(C18:F18),(IF($A$1=40299,SUM(C18:G18),(IF($A$1=40330,SUM(C18:H18),(IF($A$1=40360,SUM(C18:I18),0)))))))))))))+(IF($A$1=40391,SUM(C18:J18),(IF($A$1=40422,SUM(C18:K18),(IF($A$1=40452,SUM(C18:L18),(IF($A$1=40483,SUM(C18:M18))))))))))+(IF($A$1=40513,SUM(C18:N18),0)) -> 0 | Q18: =(IF($A$1=40179,C18,(IF($A$1=40210,D18,(IF($A$1=40238,E18,(IF($A$1=40269,F18,(IF($A$1=40299,G18,(IF($A$1=40330,H18,(IF($A$1=40360,I18,0)))))))))))))+(IF($A$1=40391,J18,(IF($A$1=40422,K18,(IF($A$1=40452,L18,(IF($A$1=40483,M18)))))))))+(IF($A$1=40513,N18,0)) -> 0 | S18: 40391 | DE18: 8
A19: TOTAL ENERGY | C19: =SUM(C15:C18) -> 528751.09 | D19: =SUM(D15:D18) -> 626294.7 | E19: =SUM(E15:E18) -> 0 | F19: =SUM(F15:F18) -> 0 | G19: =SUM(G15:G18) -> 0 | H19: =SUM(H15:H18) -> 0 | I19: =SUM(I15:I18) -> 0 | J19: =SUM(J15:J18) -> 0 | ... O19: =SUM(O15:O18) -> 1155045.8 | P19: =(IF($A$1=40179,C19,(IF($A$1=40210,SUM(C19:D19),(IF($A$1=40238,SUM(C19:E19),(IF($A$1=40269,SUM(C19:F19),(IF($A$1=40299,SUM(C19:G19),(IF($A$1=40330,SUM(C19:H19),(IF($A$1=40360,SUM(C19:I19),0)))))))))))))+(IF($A$1=40391,SUM(C19:J19),(IF($A$1=40422,SUM(C19:K19),(IF($A$1=40452,SUM(C19:L19),(IF($A$1=40483,SUM(C19:M19))))))))))+(IF($A$1=40513,SUM(C19:N19),0)) -> 0 | Q19: =(IF($A$1=40179,C19,(IF($A$1=40210,D19,(IF($A$1=40238,E19,(IF($A$1=40269,F19,(IF($A$1=40299,G19,(IF($A$1=40330,H19,(IF($A$1=40360,I19,0)))))))))))))+(IF($A$1=40391,J19,(IF($A$1=40422,K19,(IF($A$1=40452,L19,(IF($A$1=40483,M19)))))))))+(IF($A$1=40513,N19,0)) -> 0 | S19: 40422 | DE19: 9
P20: =(IF($A$1=40179,C20,(IF($A$1=40210,SUM(C20:D20),(IF($A$1=40238,SUM(C20:E20),(IF($A$1=40269,SUM(C20:F20),(IF($A$1=40299,SUM(C20:G20),(IF($A$1=40330,SUM(C20:H20),(IF($A$1=40360,SUM(C20:I20),0)))))))))))))+(IF($A$1=40391,SUM(C20:J20),(IF($A$1=40422,SUM(C20:K20),(IF($A$1=40452,SUM(C20:L20),(IF($A$1=40483,SUM(C20:M20))))))))))+(IF($A$1=40513,SUM(C20:N20),0)) -> 0 | Q20: =(IF($A$1=40179,C20,(IF($A$1=40210,D20,(IF($A$1=40238,E20,(IF($A$1=40269,F20,(IF($A$1=40299,G20,(IF($A$1=40330,H20,(IF($A$1=40360,I20,0)))))))))))))+(IF($A$1=40391,J20,(IF($A$1=40422,K20,(IF($A$1=40452,L20,(IF($A$1=40483,M20)))))))))+(IF($A$1=40513,N20,0)) -> 0
A21: OTHER EXPENSES | P21: =(IF($A$1=40179,C21,(IF($A$1=40210,SUM(C21:D21),(IF($A$1=40238,SUM(C21:E21),(IF($A$1=40269,SUM(C21:F21),(IF($A$1=40299,SUM(C21:G21),(IF($A$1=40330,SUM(C21:H21),(IF($A$1=40360,SUM(C21:I21),0)))))))))))))+(IF($A$1=40391,SUM(C21:J21),(IF($A$1=40422,SUM(C21:K21),(IF($A$1=40452,SUM(C21:L21),(IF($A$1=40483,SUM(C21:M21))))))))))+(IF($A$1=40513,SUM(C21:N21),0)) -> 0 | Q21: =(IF($A$1=40179,C21,(IF($A$1=40210,D21,(IF($A$1=40238,E21,(IF($A$1=40269,F21,(IF($A$1=40299,G21,(IF($A$1=40330,H21,(IF($A$1=40360,I21,0)))))))))))))+(IF($A$1=40391,J21,(IF($A$1=40422,K21,(IF($A$1=40452,L21,(IF($A$1=40483,M21)))))))))+(IF($A$1=40513,N21,0)) -> 0
A22: P. & ST. | B22: 53251503 | C22: 2782.3724 | D22: 2209.2805 | E22: 3205.3202 | F22: 2604.6091 | G22: 3235.6987 | H22: 2482.8474 | I22: 3129.5287 | J22: 4085.8967 | K22: 4096.0234 | L22: 4111.0374 | M22: 4007.7194 | N22: 3115.8679 | O22: 39066.202 | P22: =(IF($A$1=40179,C22,(IF($A$1=40210,SUM(C22:D22),(IF($A$1=40238,SUM(C22:E22),(IF($A$1=40269,SUM(C22:F22),(IF($A$1=40299,SUM(C22:G22),(IF($A$1=40330,SUM(C22:H22),(IF($A$1=40360,SUM(C22:I22),0)))))))))))))+(IF($A$1=40391,SUM(C22:J22),(IF($A$1=40422,SUM(C22:K22),(IF($A$1=40452,SUM(C22:L22),(IF($A$1=40483,SUM(C22:M22))))))))))+(IF($A$1=40513,SUM(C22:N22),0)) -> 0 | Q22: =(IF($A$1=40179,C22,(IF($A$1=40210,D22,(IF($A$1=40238,E22,(IF($A$1=40269,F22,(IF($A$1=40299,G22,(IF($A$1=40330,H22,(IF($A$1=40360,I22,0)))))))))))))+(IF($A$1=40391,J22,(IF($A$1=40422,K22,(IF($A$1=40452,L22,(IF($A$1=40483,M22)))))))))+(IF($A$1=40513,N22,0)) -> 0
A23: POSTAGE | B23: 53251912 | C23: 0 | D23: 0 | E23: 0 | F23: 0 | G23: 0 | H23: 0 | I23: 0 | J23: 0 | K23: 0 | L23: 0 | M23: 0 | N23: 0 | O23: 0 | P23: =(IF($A$1=40179,C23,(IF($A$1=40210,SUM(C23:D23),(IF($A$1=40238,SUM(C23:E23),(IF($A$1=40269,SUM(C23:F23),(IF($A$1=40299,SUM(C23:G23),(IF($A$1=40330,SUM(C23:H23),(IF($A$1=40360,SUM(C23:I23),0)))))))))))))+(IF($A$1=40391,SUM(C23:J23),(IF($A$1=40422,SUM(C23:K23),(IF($A$1=40452,SUM(C23:L23),(IF($A$1=40483,SUM(C23:M23))))))))))+(IF($A$1=40513,SUM(C23:N23),0)) -> 0 | Q23: =(IF($A$1=40179,C23,(IF($A$1=40210,D23,(IF($A$1=40238,E23,(IF($A$1=40269,F23,(IF($A$1=40299,G23,(IF($A$1=40330,H23,(IF($A$1=40360,I23,0)))))))))))))+(IF($A$1=40391,J23,(IF($A$1=40422,K23,(IF($A$1=40452,L23,(IF($A$1=40483,M23)))))))))+(IF($A$1=40513,N23,0)) -> 0
A24: TAXICAB | B24: 53251919 | C24: 11276.363 | D24: 10009.133 | E24: 9350.2819 | F24: 12862.267 | G24: 10806.952 | H24: 11155.64 | I24: 12970.205 | J24: 10165.751 | K24: 10061.171 | L24: 10190.726 | M24: 10023.319 | N24: 7435.7374 | O24: 126307.55 | P24: =(IF($A$1=40179,C24,(IF($A$1=40210,SUM(C24:D24),(IF($A$1=40238,SUM(C24:E24),(IF($A$1=40269,SUM(C24:F24),(IF($A$1=40299,SUM(C24:G24),(IF($A$1=40330,SUM(C24:H24),(IF($A$1=40360,SUM(C24:I24),0)))))))))))))+(IF($A$1=40391,SUM(C24:J24),(IF($A$1=40422,SUM(C24:K24),(IF($A$1=40452,SUM(C24:L24),(IF($A$1=40483,SUM(C24:M24))))))))))+(IF($A$1=40513,SUM(C24:N24),0)) -> 0 | Q24: =(IF($A$1=40179,C24,(IF($A$1=40210,D24,(IF($A$1=40238,E24,(IF($A$1=40269,F24,(IF($A$1=40299,G24,(IF($A$1=40330,H24,(IF($A$1=40360,I24,0)))))))))))))+(IF($A$1=40391,J24,(IF($A$1=40422,K24,(IF($A$1=40452,L24,(IF($A$1=40483,M24)))))))))+(IF($A$1=40513,N24,0)) -> 0
A25: R&M DATA PROCESSING | B25: 53252601 | C25: 0 | D25: 0 | E25: 0 | F25: 0 | G25: 0 | H25: 0 | I25: 0 | J25: 0 | K25: 0 | L25: 0 | M25: 0 | N25: 0 | O25: 0 | P25: =(IF($A$1=40179,C25,(IF($A$1=40210,SUM(C25:D25),(IF($A$1=40238,SUM(C25:E25),(IF($A$1=40269,SUM(C25:F25),(IF($A$1=40299,SUM(C25:G25),(IF($A$1=40330,SUM(C25:H25),(IF($A$1=40360,SUM(C25:I25),0)))))))))))))+(IF($A$1=40391,SUM(C25:J25),(IF($A$1=40422,SUM(C25:K25),(IF($A$1=40452,SUM(C25:L25),(IF($A$1=40483,SUM(C25:M25))))))))))+(IF($A$1=40513,SUM(C25:N25),0)) -> 0 | Q25: =(IF($A$1=40179,C25,(IF($A$1=40210,D25,(IF($A$1=40238,E25,(IF($A$1=40269,F25,(IF($A$1=40299,G25,(IF($A$1=40330,H25,(IF($A$1=40360,I25,0)))))))))))))+(IF($A$1=40391,J25,(IF($A$1=40422,K25,(IF($A$1=40452,L25,(IF($A$1=40483,M25)))))))))+(IF($A$1=40513,N25,0)) -> 0
A26: R&M TELEPHONE | B26: 53252603 | C26: 29.374709 | D26: 15.100235 | E26: 33.209819 | F26: 40.453905 | G26: 120.16145 | H26: 0 | I26: 0 | J26: 1532.6831 | K26: 1577.9928 | L26: 1553.3432 | M26: 1485.7035 | N26: 1074.5974 | O26: 7462.6202 | P26: =(IF($A$1=40179,C26,(IF($A$1=40210,SUM(C26:D26),(IF($A$1=40238,SUM(C26:E26),(IF($A$1=40269,SUM(C26:F26),(IF($A$1=40299,SUM(C26:G26),(IF($A$1=40330,SUM(C26:H26),(IF($A$1=40360,SUM(C26:I26),0)))))))))))))+(IF($A$1=40391,SUM(C26:J26),(IF($A$1=40422,SUM(C26:K26),(IF($A$1=40452,SUM(C26:L26),(IF($A$1=40483,SUM(C26:M26))))))))))+(IF($A$1=40513,SUM(C26:N26),0)) -> 0 | Q26: =(IF($A$1=40179,C26,(IF($A$1=40210,D26,(IF($A$1=40238,E26,(IF($A$1=40269,F26,(IF($A$1=40299,G26,(IF($A$1=40330,H26,(IF($A$1=40360,I26,0)))))))))))))+(IF($A$1=40391,J26,(IF($A$1=40422,K26,(IF($A$1=40452,L26,(IF($A$1=40483,M26)))))))))+(IF($A$1=40513,N26,0)) -> 0
A27: R&M KITCHEN EQUIP. | B27: 53252703 | C27: 18610.98 | D27: 7247.7121 | E27: 5707.4428 | F27: 12222.516 | G27: 5623.8033 | H27: 6509.5046 | I27: 15311.566 | J27: 21902.26 | K27: 18614.51 | L27: 19231.518 | M27: 20212.925 | N27: 15102.401 | O27: 166297.14 | P27: =(IF($A$1=40179,C27,(IF($A$1=40210,SUM(C27:D27),(IF($A$1=40238,SUM(C27:E27),(IF($A$1=40269,SUM(C27:F27),(IF($A$1=40299,SUM(C27:G27),(IF($A$1=40330,SUM(C27:H27),(IF($A$1=40360,SUM(C27:I27),0)))))))))))))+(IF($A$1=40391,SUM(C27:J27),(IF($A$1=40422,SUM(C27:K27),(IF($A$1=40452,SUM(C27:L27),(IF($A$1=40483,SUM(C27:M27))))))))))+(IF($A$1=40513,SUM(C27:N27),0)) -> 0 | Q27: =(IF($A$1=40179,C27,(IF($A$1=40210,D27,(IF($A$1=40238,E27,(IF($A$1=40269,F27,(IF($A$1=40299,G27,(IF($A$1=40330,H27,(IF($A$1=40360,I27,0)))))))))))))+(IF($A$1=40391,J27,(IF($A$1=40422,K27,(IF($A$1=40452,L27,(IF($A$1=40483,M27)))))))))+(IF($A$1=40513,N27,0)) -> 0
A28: R&M LAUNDRY & VALET | B28: 53252704 | C28: 5275.9524 | D28: 3912.9834 | E28: 5168.9448 | F28: 3995.7884 | G28: 23112.428 | H28: 3000 | I28: 25530.47 | J28: 10393.274 | K28: 10317.215 | L28: 10411.437 | M28: 8163.5282 | N28: 8407.809 | O28: 117689.83 | P28: =(IF($A$1=40179,C28,(IF($A$1=40210,SUM(C28:D28),(IF($A$1=40238,SUM(C28:E28),(IF($A$1=40269,SUM(C28:F28),(IF($A$1=40299,SUM(C28:G28),(IF($A$1=40330,SUM(C28:H28),(IF($A$1=40360,SUM(C28:I28),0)))))))))))))+(IF($A$1=40391,SUM(C28:J28),(IF($A$1=40422,SUM(C28:K28),(IF($A$1=40452,SUM(C28:L28),(IF($A$1=40483,SUM(C28:M28))))))))))+(IF($A$1=40513,SUM(C28:N28),0)) -> 0 | Q28: =(IF($A$1=40179,C28,(IF($A$1=40210,D28,(IF($A$1=40238,E28,(IF($A$1=40269,F28,(IF($A$1=40299,G28,(IF($A$1=40330,H28,(IF($A$1=40360,I28,0)))))))))))))+(IF($A$1=40391,J28,(IF($A$1=40422,K28,(IF($A$1=40452,L28,(IF($A$1=40483,M28)))))))))+(IF($A$1=40513,N28,0)) -> 0
