Workbook

Sheet Total
A1: Site Name | B1: Day | C1: Month | D1: Year | E1: Total Electricity Kwh | F1: Electricity Tariff ($/Kwh) | G1: Natual Gas (m3) | H1: Natural Gas $/m3 | I1: Water Utility Supply (m3) m3 | J1: Water Utility Supply (m3) $/m3 | K1: Room Nights
A2: Cairo at The First Residence | B2: 1 | C2: 6 | D2: 2021 | E2: 32736.34 | F2: 1.35 | G2: =1025.57+228.17 -> 1253.74 | H2: 3.89 | I2: 279.02 | J2: 10 | K2: 158
A3: Cairo at The First Residence | B3: =B2+1 -> 2 | C3: 6 | D3: 2021 | E3: 32736.34 | F3: =F2 -> 1.35 | G3: =1025.57+228.17 -> 1253.74 | H3: 3.89 | I3: 279.02 | J3: 10 | K3: 158
A4: Cairo at The First Residence | B4: =B3+1 -> 3 | C4: 6 | D4: 2021 | E4: 32736.34 | F4: =F3 -> 1.35 | G4: =1025.57+228.17 -> 1253.74 | H4: 3.89 | I4: 279.02 | J4: 10 | K4: 158
A5: Cairo at The First Residence | B5: =B4+1 -> 4 | C5: 6 | D5: 2021 | E5: 32736.34 | F5: =F4 -> 1.35 | G5: =1025.57+228.17 -> 1253.74 | H5: 3.89 | I5: 279.02 | J5: 10 | K5: 158
A6: Cairo at The First Residence | B6: =B5+1 -> 5 | C6: 6 | D6: 2021 | E6: 32736.34 | F6: =F5 -> 1.35 | G6: =1025.57+228.17 -> 1253.74 | H6: 3.89 | I6: 279.02 | J6: 10 | K6: 158
A7: Cairo at The First Residence | B7: =B6+1 -> 6 | C7: 6 | D7: 2021 | E7: 32736.34 | F7: =F6 -> 1.35 | G7: =1025.57+228.17 -> 1253.74 | H7: 3.89 | I7: 279.02 | J7: 10 | K7: 158
A8: Cairo at The First Residence | B8: =B7+1 -> 7 | C8: 6 | D8: 2021 | E8: 32736.34 | F8: =F7 -> 1.35 | G8: =1025.57+228.17 -> 1253.74 | H8: 3.89 | I8: 279.02 | J8: 10 | K8: 158
A9: Cairo at The First Residence | B9: =B8+1 -> 8 | C9: 6 | D9: 2021 | E9: 32736.34 | F9: =F8 -> 1.35 | G9: =1025.57+228.17 -> 1253.74 | H9: 3.89 | I9: 279.02 | J9: 10 | K9: 158
A10: Cairo at The First Residence | B10: =B9+1 -> 9 | C10: 6 | D10: 2021 | E10: 32736.34 | F10: =F9 -> 1.35 | G10: =1025.57+228.17 -> 1253.74 | H10: 3.89 | I10: 279.02 | J10: 10 | K10: 158
A11: Cairo at The First Residence | B11: =B10+1 -> 10 | C11: 6 | D11: 2021 | E11: 32736.34 | F11: =F10 -> 1.35 | G11: =1025.57+228.17 -> 1253.74 | H11: 3.89 | I11: 279.02 | J11: 10 | K11: 158
A12: Cairo at The First Residence | B12: =B11+1 -> 11 | C12: 6 | D12: 2021 | E12: 32736.34 | F12: =F11 -> 1.35 | G12: =1025.57+228.17 -> 1253.74 | H12: 3.89 | I12: 279.02 | J12: 10 | K12: 158
A13: Cairo at The First Residence | B13: =B12+1 -> 12 | C13: 6 | D13: 2021 | E13: 32736.34 | F13: =F12 -> 1.35 | G13: =1025.57+228.17 -> 1253.74 | H13: 3.89 | I13: 279.02 | J13: 10 | K13: 158
A14: Cairo at The First Residence | B14: =B13+1 -> 13 | C14: 6 | D14: 2021 | E14: 32736.34 | F14: =F13 -> 1.35 | G14: =1025.57+228.17 -> 1253.74 | H14: 3.89 | I14: 279.02 | J14: 10 | K14: 158
... A31: Cairo at The First Residence | B31: =B30+1 -> 30 | C31: 6 | D31: 2021 | E31: 32736.34 | F31: =F30 -> 1.35 | G31: =1025.57+228.17 -> 1253.74 | H31: 3.89 | I31: 279.02 | J31: 10 | K31: 158
A32: Cairo at The First Residence | B32: =B31+1 -> 31 | C32: 6 | D32: 2021 | E32: =Elect!BS36 -> 0 | F32: =F31 -> 1.35 | G32: =Gas!K37 -> 0 | H32: 3.89 | I32: =Water!H37 -> 0 | J32: 10 | K32: =Elect!BT36 -> 0

Sheet Submetering
A1: Site Name | B1: Day | C1: Month | D1: Year | E1: Electricity | F1: Main Feeder -KWh | G1: T2+T8 -KWh | H1: La Gourmandize -KWh | I1: Casino 3rd floor EM -KWh | J1: Casino 3rd floor Normal -KWh | K1: Chiller 1 -KWh | L1: Chiller 2 -KWh | M1: Chiller 3 -KWh | N1: Chiller 4 -KWh | O1: Chiller 5 -KWh | P1: Chiller 6 -KWh | Q1: Cooling towers -KWh | R1: Chiller Pumps -KWh | S1: Cooling Tower Pumps -KWh | T1: Fiber Chiller -KWh | U1: Mall Ceiling light -KWh | V1: LG Bakery -KWh | W1: LG Bakery light ( Old lockers ) -KWh | X1: MCCR1 -KWh | Y1: Children Swimming Pool -KWh | Z1: DPH1 -KWh | AA1: Guest Rooms Emerg. -KWh | AB1: Hotel Hoods -KWh | AC1: Main G2 -KWh | AD1: Old Casino Emergency -KWh | AE1: L / A -KWh | AF1: L / B -KWh | AG1: L / C -KWh | AH1: Water | AI1: Main water meter 1 -m3 | AJ1: Main water meter 2 -m3 | AK1: Main water meter 3 -m3 | AL1: Gas | AM1: Main Gas Flow Meter -m3 | AN1: Laundry Gas Flow Meter -m3 | AO1: Gourmandize Gas Flow Meter -m3 | AP1: Room Nights
A2: Cairo at The First Residence | B2: 1 | C2: 6 | D2: 2021 | F2: =Elect!J6 -> 4739 | G2: =Elect!K6 -> 3106 | H2: =Elect!Q6 -> 510 | I2: =Elect!S6 -> 168 | J2: =Elect!U6 -> 300 | K2: =Elect!W6 -> 2728.44 | L2: =Elect!Y6 -> 0 | M2: =Elect!AA6 -> 2163.99 | N2: =Elect!AC6 -> 2095.62 | O2: =Elect!AE6 -> 0 | P2: =Elect!AG6 -> 1886.27 | Q2: =Elect!AI6 -> 1136.85 | R2: =Elect!AK6 -> 3993.02 | S2: =Elect!AM6 -> 179.67 | T2: =Elect!AP6 -> 206.6625 | U2: =Elect!AR6 -> 247 | V2: =Elect!AT6 -> 151 | W2: =Elect!AV6 -> 72 | X2: =Elect!AX6 -> 1175 | Y2: =Elect!AZ6 -> 79 | Z2: =Elect!BB6 -> 5068 | AA2: =Elect!BD6 -> 153 | AB2: =Elect!BF6 -> 89 | AC2: =Elect!BH6 -> 7923.95 | AD2: =Elect!BL6 -> 386 | AE2: =Elect!BN6 -> 1441 | AF2: =Elect!BP6 -> 128 | AG2: =Elect!BR6 -> 226 | AI2: =Water!C7 -> 203 | AJ2: =Water!E7 -> 0 | AK2: =Water!G7 -> 10.44 | AM2: =Gas!C7 -> 941.28 | AN2: =Gas!E7 -> 186.9 | AO2: =Gas!G7 -> 76 | AP2: 158
A3: Cairo at The First Residence | B3: =B2+1 -> 2 | C3: 6 | D3: 2021 | F3: =Elect!J7 -> 4842 | G3: =Elect!K7 -> 2936 | H3: =Elect!Q7 -> 480 | I3: =Elect!S7 -> 139 | J3: =Elect!U7 -> 263 | K3: =Elect!W7 -> 2643.64 | L3: =Elect!Y7 -> 2155.51 | M3: =Elect!AA7 -> 0 | N3: =Elect!AC7 -> 168.54 | O3: =Elect!AE7 -> 0 | P3: =Elect!AG7 -> 1419.34 | Q3: =Elect!AI7 -> 1122.01 | R3: =Elect!AK7 -> 3796.39 | S3: =Elect!AM7 -> 171.19 | T3: =Elect!AP7 -> 270.225 | U3: =Elect!AR7 -> 311 | V3: =Elect!AT7 -> 162 | W3: =Elect!AV7 -> 47 | X3: =Elect!AX7 -> 1109 | Y3: =Elect!AZ7 -> 70 | Z3: =Elect!BB7 -> 4673 | AA3: =Elect!BD7 -> 135 | AB3: =Elect!BF7 -> 50 | AC3: =Elect!BH7 -> 5696.4 | AD3: =Elect!BL7 -> 265 | AE3: =Elect!BN7 -> 1456 | AF3: =Elect!BP7 -> 112 | AG3: =Elect!BR7 -> 212 | AI3: =Water!C8 -> 226.2 | AJ3: =Water!E8 -> 0 | AK3: =Water!G8 -> 32.48 | AM3: =Gas!C8 -> 1069.54 | AN3: =Gas!E8 -> 148.4 | AO3: =Gas!G8 -> 80 | AP3: 158
A4: Cairo at The First Residence | B4: =B3+1 -> 3 | C4: 6 | D4: 2021 | F4: =Elect!J8 -> 4825 | G4: =Elect!K8 -> 3117 | H4: =Elect!Q8 -> 570 | I4: =Elect!S8 -> 148 | J4: =Elect!U8 -> 268 | K4: =Elect!W8 -> 2406.2 | L4: =Elect!Y8 -> 2371.22 | M4: =Elect!AA8 -> 0 | N4: =Elect!AC8 -> 0 | O4: =Elect!AE8 -> 0 | P4: =Elect!AG8 -> 1513.68 | Q4: =Elect!AI8 -> 1094.98 | R4: =Elect!AK8 -> 3894.44 | S4: =Elect!AM8 -> 183.91 | T4: =Elect!AP8 -> 239.625 | U4: =Elect!AR8 -> 386 | V4: =Elect!AT8 -> 165 | W4: =Elect!AV8 -> 50 | X4: =Elect!AX8 -> 1047 | Y4: =Elect!AZ8 -> 74 | Z4: =Elect!BB8 -> 4762 | AA4: =Elect!BD8 -> 155 | AB4: =Elect!BF8 -> 157 | AC4: =Elect!BH8 -> 5829.05 | AD4: =Elect!BL8 -> 280 | AE4: =Elect!BN8 -> 1514 | AF4: =Elect!BP8 -> 117 | AG4: =Elect!BR8 -> 223 | AI4: =Water!C9 -> 237.8 | AJ4: =Water!E9 -> 0 | AK4: =Water!G9 -> 20.3 | AM4: =Gas!C9 -> 1028.2 | AN4: =Gas!E9 -> 141.4 | AO4: =Gas!G9 -> 88 | AP4: 158
A5: Cairo at The First Residence | B5: =B4+1 -> 4 | C5: 6 | D5: 2021 | F5: =Elect!J9 -> 4408 | G5: =Elect!K9 -> 2704 | H5: =Elect!Q9 -> 450 | I5: =Elect!S9 -> 128 | J5: =Elect!U9 -> 241 | K5: =Elect!W9 -> 2819.07 | L5: =Elect!Y9 -> 1028.73 | M5: =Elect!AA9 -> 0 | N5: =Elect!AC9 -> 0 | O5: =Elect!AE9 -> 0 | P5: =Elect!AG9 -> 1275.18 | Q5: =Elect!AI9 -> 780.16 | R5: =Elect!AK9 -> 2910.76 | S5: =Elect!AM9 -> 157.94 | T5: =Elect!AP9 -> 230.85 | U5: =Elect!AR9 -> 322 | V5: =Elect!AT9 -> 144 | W5: =Elect!AV9 -> 23 | X5: =Elect!AX9 -> 726 | Y5: =Elect!AZ9 -> 64 | Z5: =Elect!BB9 -> 3881 | AA5: =Elect!BD9 -> 147 | AB5: =Elect!BF9 -> 61 | AC5: =Elect!BH9 -> 5196.6 | AD5: =Elect!BL9 -> 248 | AE5: =Elect!BN9 -> 1307 | AF5: =Elect!BP9 -> 105 | AG5: =Elect!BR9 -> 198 | AI5: =Water!C10 -> 313.2 | AJ5: =Water!E10 -> 0 | AK5: =Water!G10 -> 23.78 | AM5: =Gas!C10 -> 850.12 | AN5: =Gas!E10 -> 284.2 | AO5: =Gas!G10 -> 96 | AP5: 158
A6: Cairo at The First Residence | B6: =B5+1 -> 5 | C6: 6 | D6: 2021 | F6: =Elect!J10 -> 4951 | G6: =Elect!K10 -> 3044 | H6: =Elect!Q10 -> 510 | I6: =Elect!S10 -> 140 | J6: =Elect!U10 -> 265 | K6: =Elect!W10 -> 2545.06 | L6: =Elect!Y10 -> 1586.29 | M6: =Elect!AA10 -> 0 | N6: =Elect!AC10 -> 0 | O6: =Elect!AE10 -> 0 | P6: =Elect!AG10 -> 1370.05 | Q6: =Elect!AI10 -> 917.96 | R6: =Elect!AK10 -> 3371.33 | S6: =Elect!AM10 -> 166.95 | T6: =Elect!AP10 -> 210.9375 | U6: =Elect!AR10 -> 304 | V6: =Elect!AT10 -> 142 | W6: =Elect!AV10 -> 32 | X6: =Elect!AX10 -> 740 | Y6: =Elect!AZ10 -> 73 | Z6: =Elect!BB10 -> 4564 | AA6: =Elect!BD10 -> 162 | AB6: =Elect!BF10 -> 108 | AC6: =Elect!BH10 -> 5511.6 | AD6: =Elect!BL10 -> 213 | AE6: =Elect!BN10 -> 1368 | AF6: =Elect!BP10 -> 104 | AG6: =Elect!BR10 -> 210 | AI6: =Water!C11 -> 249.4 | AJ6: =Water!E11 -> 0 | AK6: =Water!G11 -> 27.26 | AM6: =Gas!C11 -> 1089.68 | AN6: =Gas!E11 -> 298.9 | AO6: =Gas!G11 -> 101 | AP6: 158
A7: Cairo at The First Residence | B7: =B6+1 -> 6 | C7: 6 | D7: 2021 | F7: =Elect!J11 -> 5148 | G7: =Elect!K11 -> 3203 | H7: =Elect!Q11 -> 600 | I7: =Elect!S11 -> 140 | J7: =Elect!U11 -> 263 | K7: =Elect!W11 -> 2509.55 | L7: =Elect!Y11 -> 0 | M7: =Elect!AA11 -> 2450.72 | N7: =Elect!AC11 -> 0 | O7: =Elect!AE11 -> 0 | P7: =Elect!AG11 -> 1335.6 | Q7: =Elect!AI11 -> 1023.96 | R7: =Elect!AK11 -> 3574.85 | S7: =Elect!AM11 -> 166.42 | T7: =Elect!AP11 -> 205.9875 | U7: =Elect!AR11 -> 293 | V7: =Elect!AT11 -> 137 | W7: =Elect!AV11 -> 46 | X7: =Elect!AX11 -> 750 | Y7: =Elect!AZ11 -> 72 | Z7: =Elect!BB11 -> 4275 | AA7: =Elect!BD11 -> 165 | AB7: =Elect!BF11 -> 123 | AC7: =Elect!BH11 -> 5192.6 | AD7: =Elect!BL11 -> 0 | AE7: =Elect!BN11 -> 1300 | AF7: =Elect!BP11 -> 112 | AG7: =Elect!BR11 -> 209 | AI7: =Water!C12 -> 208.8 | AJ7: =Water!E12 -> 0 | AK7: =Water!G12 -> 23.78 | AM7: =Gas!C12 -> 1062.12 | AN7: =Gas!E12 -> 308 | AO7: =Gas!G12 -> 106 | AP7: 158
A8: Cairo at The First Residence | B8: =B7+1 -> 7 | C8: 6 | D8: 2021 | F8: =Elect!J12 -> 5028 | G8: =Elect!K12 -> 3083 | H8: =Elect!Q12 -> 360 | I8: =Elect!S12 -> 138 | J8: =Elect!U12 -> 261 | K8: =Elect!W12 -> 2559.9 | L8: =Elect!Y12 -> 0 | M8: =Elect!AA12 -> 151.05 | N8: =Elect!AC12 -> 2162.93 | O8: =Elect!AE12 -> 0 | P8: =Elect!AG12 -> 1499.37 | Q8: =Elect!AI12 -> 849.06 | R8: =Elect!AK12 -> 3567.43 | S8: =Elect!AM12 -> 166.95 | T8: =Elect!AP12 -> 236.1375 | U8: =Elect!AR12 -> 295 | V8: =Elect!AT12 -> 147 | W8: =Elect!AV12 -> 52 | X8: =Elect!AX12 -> 768 | Y8: =Elect!AZ12 -> 72 | Z8: =Elect!BB12 -> 4332 | AA8: =Elect!BD12 -> 165 | AB8: =Elect!BF12 -> 139 | AC8: =Elect!BH12 -> 5686.1 | AD8: =Elect!BL12 -> 209 | AE8: =Elect!BN12 -> 1408 | AF8: =Elect!BP12 -> 114 | AG8: =Elect!BR12 -> 211 | AI8: =Water!C13 -> 197.2 | AJ8: =Water!E13 -> 0 | AK8: =Water!G13 -> 45.24 | AM8: =Gas!C13 -> 930.68 | AN8: =Gas!E13 -> 235.9 | AO8: =Gas!G13 -> 93 | AP8: 158
A9: Cairo at The First Residence | B9: =B8+1 -> 8 | C9: 6 | D9: 2021 | F9: =Elect!J13 -> 5556 | G9: =Elect!K13 -> 3452 | H9: =Elect!Q13 -> 510 | I9: =Elect!S13 -> 148 | J9: =Elect!U13 -> 282 | K9: =Elect!W13 -> 2915.53 | L9: =Elect!Y13 -> 2408.85 | M9: =Elect!AA13 -> 0 | N9: =Elect!AC13 -> 0 | O9: =Elect!AE13 -> 0 | P9: =Elect!AG13 -> 681.05 | Q9: =Elect!AI13 -> 921.14 | R9: =Elect!AK13 -> 3879.07 | S9: =Elect!AM13 -> 175.96 | T9: =Elect!AP13 -> 271.4625 | U9: =Elect!AR13 -> 283 | V9: =Elect!AT13 -> 149 | W9: =Elect!AV13 -> 52 | X9: =Elect!AX13 -> 846 | Y9: =Elect!AZ13 -> 77 | Z9: =Elect!BB13 -> 4532 | AA9: =Elect!BD13 -> 179 | AB9: =Elect!BF13 -> 34 | AC9: =Elect!BH13 -> 5772.4 | AD9: =Elect!BL13 -> 117 | AE9: =Elect!BN13 -> 1394 | AF9: =Elect!BP13 -> 114 | AG9: =Elect!BR13 -> 222 | AI9: =Water!C14 -> 208.8 | AJ9: =Water!E14 -> 0 | AK9: =Water!G14 -> 37.12 | AM9: =Gas!C14 -> 382.66 | AN9: =Gas!E14 -> 261.1 | AO9: =Gas!G14 -> 91 | AP9: 158
A10: Cairo at The First Residence | B10: =B9+1 -> 9 | C10: 6 | D10: 2021 | F10: =Elect!J14 -> 4703 | G10: =Elect!K14 -> 3078 | H10: =Elect!Q14 -> 630 | I10: =Elect!S14 -> 131 | J10: =Elect!U14 -> 253 | K10: =Elect!W14 -> 3164.63 | L10: =Elect!Y14 -> 0 | M10: =Elect!AA14 -> 1683.81 | N10: =Elect!AC14 -> 0 | O10: =Elect!AE14 -> 0 | P10: =Elect!AG14 -> 10.6 | Q10: =Elect!AI14 -> 958.77 | R10: =Elect!AK14 -> 3440.76 | S10: =Elect!AM14 -> 166.42 | T10: =Elect!AP14 -> 213.6375 | U10: =Elect!AR14 -> 275 | V10: =Elect!AT14 -> 127 | W10: =Elect!AV14 -> 56 | X10: =Elect!AX14 -> 836 | Y10: =Elect!AZ14 -> 69 | Z10: =Elect!BB14 -> 4203 | AA10: =Elect!BD14 -> 161 | AB10: =Elect!BF14 -> 121 | AC10: =Elect!BH14 -> 5080.85 | AD10: =Elect!BL14 -> 2 | AE10: =Elect!BN14 -> 1291 | AF10: =Elect!BP14 -> 96 | AG10: =Elect!BR14 -> 202 | AI10: =Water!C15 -> 201.06667 | AJ10: =Water!E15 -> 0 | AK10: =Water!G15 -> 42.533333 | AM10: =Gas!C15 -> 1322.88 | AN10: =Gas!E15 -> 182 | AO10: =Gas!G15 -> 18 | AP10: 158
A11: Cairo at The First Residence | B11: =B10+1 -> 10 | C11: 6 | D11: 2021 | F11: =Elect!J15 -> 4927 | G11: =Elect!K15 -> 3158 | H11: =Elect!Q15 -> 570 | I11: =Elect!S15 -> 140 | J11: =Elect!U15 -> 268 | K11: =Elect!W15 -> 3035.31 | L11: =Elect!Y15 -> 0 | M11: =Elect!AA15 -> 3027.36 | N11: =Elect!AC15 -> 0 | O11: =Elect!AE15 -> 9.54 | P11: =Elect!AG15 -> 11.13 | Q11: =Elect!AI15 -> 1131.02 | R11: =Elect!AK15 -> 3911.93 | S11: =Elect!AM15 -> 171.72 | T11: =Elect!AP15 -> 192.6 | U11: =Elect!AR15 -> 276 | V11: =Elect!AT15 -> 173 | W11: =Elect!AV15 -> 66 | X11: =Elect!AX15 -> 862 | Y11: =Elect!AZ15 -> 74 | Z11: =Elect!BB15 -> 4135 | AA11: =Elect!BD15 -> 170 | AB11: =Elect!BF15 -> 100 | AC11: =Elect!BH15 -> 6305.9 | AD11: =Elect!BL15 -> 251 | AE11: =Elect!BN15 -> 1446 | AF11: =Elect!BP15 -> 112 | AG11: =Elect!BR15 -> 220 | AI11: =Water!C16 -> 291.93333 | AJ11: =Water!E16 -> 0 | AK11: =Water!G16 -> 0 | AM11: =Gas!C16 -> 519.4 | AN11: =Gas!E16 -> 304.5 | AO11: =Gas!G16 -> 61 | AP11: 158
A12: Cairo at The First Residence | B12: =B11+1 -> 11 | C12: 6 | D12: 2021 | F12: =Elect!J16 -> 5329 | G12: =Elect!K16 -> 3142 | H12: =Elect!Q16 -> 540 | I12: =Elect!S16 -> 141 | J12: =Elect!U16 -> 269 | K12: =Elect!W16 -> 2849.81 | L12: =Elect!Y16 -> 0 | M12: =Elect!AA16 -> 2613.96 | N12: =Elect!AC16 -> 0 | O12: =Elect!AE16 -> 4.24 | P12: =Elect!AG16 -> 11.13 | Q12: =Elect!AI16 -> 965.13 | R12: =Elect!AK16 -> 3505.95 | S12: =Elect!AM16 -> 158.47 | T12: =Elect!AP16 -> 212.0625 | U12: =Elect!AR16 -> 304 | V12: =Elect!AT16 -> 178 | W12: =Elect!AV16 -> 53 | X12: =Elect!AX16 -> 801 | Y12: =Elect!AZ16 -> 74 | Z12: =Elect!BB16 -> 4562 | AA12: =Elect!BD16 -> 171 | AB12: =Elect!BF16 -> 125 | AC12: =Elect!BH16 -> 5843.65 | AD12: =Elect!BL16 -> 256 | AE12: =Elect!BN16 -> 1325 | AF12: =Elect!BP16 -> 98 | AG12: =Elect!BR16 -> 203 | AI12: =Water!C17 -> 179.8 | AJ12: =Water!E17 -> 0 | AK12: =Water!G17 -> 0 | AM12: =Gas!C17 -> 1094.98 | AN12: =Gas!E17 -> 279.3 | AO12: =Gas!G17 -> 75 | AP12: 158
A13: Cairo at The First Residence | B13: =B12+1 -> 12 | C13: 6 | D13: 2021 | F13: =Elect!J17 -> 5210 | G13: =Elect!K17 -> 3334 | H13: =Elect!Q17 -> 540 | I13: =Elect!S17 -> 141 | J13: =Elect!U17 -> 275 | K13: =Elect!W17 -> 3205.44 | L13: =Elect!Y17 -> 2405.14 | M13: =Elect!AA17 -> 35.51 | N13: =Elect!AC17 -> 0 | O13: =Elect!AE17 -> 8.48 | P13: =Elect!AG17 -> 11.13 | Q13: =Elect!AI17 -> 1041.98 | R13: =Elect!AK17 -> 3879.07 | S13: =Elect!AM17 -> 172.78 | T13: =Elect!AP17 -> 201.6 | U13: =Elect!AR17 -> 244 | V13: =Elect!AT17 -> 153 | W13: =Elect!AV17 -> 59 | X13: =Elect!AX17 -> 856 | Y13: =Elect!AZ17 -> 75 | Z13: =Elect!BB17 -> 4891 | AA13: =Elect!BD17 -> 179 | AB13: =Elect!BF17 -> 114 | AC13: =Elect!BH17 -> 6214.2 | AD13: =Elect!BL17 -> 270 | AE13: =Elect!BN17 -> 1401 | AF13: =Elect!BP17 -> 103 | AG13: =Elect!BR17 -> 212 | AI13: =Water!C18 -> 336.4 | AJ13: =Water!E18 -> 0 | AK13: =Water!G18 -> 0 | AM13: =Gas!C18 -> 1193.56 | AN13: =Gas!E18 -> 212.8 | AO13: =Gas!G18 -> 64 | AP13: 158
A14: Cairo at The First Residence | B14: =B13+1 -> 13 | C14: 6 | D14: 2021 | F14: =Elect!J18 -> 5191 | G14: =Elect!K18 -> 3314 | H14: =Elect!Q18 -> 630 | I14: =Elect!S18 -> 137 | J14: =Elect!U18 -> 267 | K14: =Elect!W18 -> 3123.29 | L14: =Elect!Y18 -> 2871.54 | M14: =Elect!AA18 -> 0 | N14: =Elect!AC18 -> 0 | O14: =Elect!AE18 -> 5.83 | P14: =Elect!AG18 -> 19.61 | Q14: =Elect!AI18 -> 1076.96 | R14: =Elect!AK18 -> 3978.18 | S14: =Elect!AM18 -> 169.6 | T14: =Elect!AP18 -> 203.4 | U14: =Elect!AR18 -> 281 | V14: =Elect!AT18 -> 151 | W14: =Elect!AV18 -> 60 | X14: =Elect!AX18 -> 849 | Y14: =Elect!AZ18 -> 74 | Z14: =Elect!BB18 -> 4662 | AA14: =Elect!BD18 -> 171 | AB14: =Elect!BF18 -> 119 | AC14: =Elect!BH18 -> 5828.3 | AD14: =Elect!BL18 -> 253 | AE14: =Elect!BN18 -> 1340 | AF14: =Elect!BP18 -> 106 | AG14: =Elect!BR18 -> 204 | AI14: =Water!C19 -> 168.2 | AJ14: =Water!E19 -> 0 | AK14: =Water!G19 -> 0 | AM14: =Gas!C19 -> 776.98 | AN14: =Gas!E19 -> 179.2 | AO14: =Gas!G19 -> 63 | AP14: 158
... A31: Cairo at The First Residence | B31: =B30+1 -> 30 | C31: 6 | D31: 2021 | F31: =Elect!J35 -> 5721 | G31: =Elect!K35 -> 3425 | H31: =Elect!Q35 -> 540 | I31: =Elect!S35 -> 147 | J31: =Elect!U35 -> 293 | K31: =Elect!W35 -> 3454.01 | L31: =Elect!Y35 -> 1867.19 | M31: =Elect!AA35 -> 3451.89 | N31: =Elect!AC35 -> 33.92 | O31: =Elect!AE35 -> 1196.21 | P31: =Elect!AG35 -> 1436.83 | Q31: =Elect!AI35 -> 1291.08 | R31: =Elect!AK35 -> 4313.14 | S31: =Elect!AM35 -> 184.97 | T31: =Elect!AP35 -> 197.4375 | U31: =Elect!AR35 -> 243 | V31: =Elect!AT35 -> 160 | W31: =Elect!AV35 -> 53 | X31: =Elect!AX35 -> 937 | Y31: =Elect!AZ35 -> 66 | Z31: =Elect!BB35 -> 4746 | AA31: =Elect!BD35 -> 192 | AB31: =Elect!BF35 -> 83 | AC31: =Elect!BH35 -> 5949.95 | AD31: =Elect!BL35 -> 59 | AE31: =Elect!BN35 -> 1522 | AF31: =Elect!BP35 -> 107 | AG31: =Elect!BR35 -> 230 | AI31: =Water!C36 -> 284.2 | AJ31: =Water!E36 -> 0 | AK31: =Water!G36 -> 0 | AM31: =Gas!C36 -> 831.04 | AN31: =Gas!E36 -> 162.4 | AO31: =Gas!G36 -> 65 | AP31: 158
A32: Cairo at The First Residence | B32: =B31+1 -> 31 | C32: 6 | D32: 2021 | F32: =Elect!J36 -> 0 | G32: =Elect!K36 -> 0 | H32: =Elect!Q36 -> 0 | I32: =Elect!S36 -> 0 | J32: =Elect!U36 -> 0 | K32: =Elect!W36 -> 0 | L32: =Elect!Y36 -> 0 | M32: =Elect!AA36 -> 0 | N32: =Elect!AC36 -> 0 | O32: =Elect!AE36 -> 0 | P32: =Elect!AG36 -> 0 | Q32: =Elect!AI36 -> 0 | R32: =Elect!AK36 -> 0 | S32: =Elect!AM36 -> 0 | T32: =Elect!AP36 -> 0 | U32: =Elect!AR36 -> 0 | V32: =Elect!AT36 -> 0 | W32: =Elect!AV36 -> 0 | X32: =Elect!AX36 -> 0 | Y32: =Elect!AZ36 -> 0 | Z32: =Elect!BB36 -> 0 | AA32: =Elect!BD36 -> 0 | AB32: =Elect!BF36 -> 0 | AC32: =Elect!BH36 -> 0 | AD32: =Elect!BL36 -> 0 | AE32: =Elect!BN36 -> 0 | AF32: =Elect!BP36 -> 0 | AG32: =Elect!BR36 -> 0 | AI32: =Water!C37 -> 0 | AJ32: =Water!E37 -> 0 | AK32: =Water!G37 -> 0 | AM32: =Gas!C37 -> 0 | AN32: =Gas!E37 -> 0 | AO32: =Gas!G37 -> 0 | AP32: =Elect!CY36 -> 0

Sheet Elect
A1: June | M1: Electricity | BP1: Gourmandise UP | BR1: 1.6 | BS1: Power Taxes | BU1: Max Demand | BW1: 500 | BX1: Electricity UP | BZ1: 1.15
AD2: Chiller 5 Meter was miswired and was corrected on 21st | BS2: Light Taxes | BU2: PF Penalty | BX2: Max. Demand UP | BZ2: 30
A3: Date | B3: COUNTER (1) | D3: MD | F3: KVAR | H3: n | I3: Guest Rooms Consumption | R3: Casino Consumption | V3: Plant Room Shared Loads | AO3: To Be Charged By First Arabian | BK3: From Main Panel G2 | BS3: Total Consumption. | BT3: No. Of | BU3: KWH/ | BV3: No. Of | BW3: KWH/ | BX3: Total Cost | BY3: L.E\ | BZ3: L.E\
B4: Reading | C4: Consp. F: *800 | D4: Reading | E4: Consp F: 80 | F4: Reading | G4: Consp. F:*10 | I4: Main Feeder | J4: Consp | K4: T2+T8 | L4: Trans T2 | M4: Consp | N4: Trans T8 | O4: Consp | P4: La Gourmandize | Q4: Consp *30 | R4: Casino 3rd floor EM | S4: Consp | T4: Casino 3rd floor Normal | U4: Consp | V4: Chiller 1 | W4: Consp 53% | X4: Chiller 2 | Y4: Consp 53% | Z4: Chiller 3 | AA4: Consp 53% | AB4: Chiller 4 | AC4: Consp 53% | AD4: Chiller 5 | AE4: Consp 53% | AF4: Chiller 6 | AG4: Consp 53% | AH4: Cooling Towers | AI4: Consp 53% | AJ4: Chiller Pumps | AK4: Consp 53% | AL4: Cooling Tower Pumps | AM4: Consp 53% | AN4: Total Plant Room Consp | AO4: Fiber Chiller (N24) | AP4: Consp | AQ4: Mall Ceiling light (N4) | AR4: Consp | AS4: LG Bakery (N2) | AT4: Consp | AU4: LG Bakery light ( Old lockers ) | AV4: Consp | AW4: MCCR1 | AX4: Consp | AY4: Children Swimming pool | AZ4: Consp | BA4: DPH1 | BB4: Consp | BC4: Guest Rooms Emergency | BD4: Consp | BE4: Hotel Hoods | BF4: Consp | BG4: Main G2 | BH4: Consp | BI4: Total Consp From First Arabian | BJ4: First Arabian Charge Back | BK4: Old Casino Emergency | BL4: Consp | BM4: L / A | BN4: Consp | BO4: L / B | BP4: Consp | BQ4: L / C | BR4: Consp | BT4: Rooms | BU4: room | BV4: guest | BW4: guest | BY4: Room | BZ4: Guest
A5: Last Month Reading | I5: 22590286 | J5: =IF(I5>=I4,I5-I4,0) -> 0 | K5: =M5+O5 -> 0 | L5: 164375 | M5: =IF(L5>=L4,L5-L4,0) -> 0 | N5: 181359 | O5: =IF(N5>=N4,N5-N4,0) -> 0 | P5: 217068 | Q5: =IF(P5>=P4,P5-P4,0)*30 -> 0 | R5: 148148 | S5: =IF(R5>=R4,R5-R4,0) -> 0 | T5: 268811 | U5: =IF(T5>=T4,T5-T4,0) -> 0 | V5: 740296 | W5: =IF(V5>=V4,V5-V4,0)*0.53 -> 0 | X5: 434694 | Y5: =IF(X5>=X4,X5-X4,0)*0.53 -> 0 | Z5: 690715 | AA5: =IF(Z5>=Z4,Z5-Z4,0)*0.53 -> 0 | AB5: 324857 | AC5: =IF(AB5>=AB4,AB5-AB4,0)*0.53 -> 0 | AD5: 421367.4 | AE5: =IF(AD5>=AD4,AD5-AD4,0)*0.53 -> 0 | AF5: 745569 | AG5: =IF(AF5>=AF4,AF5-AF4,0)*0.53 -> 0 | AH5: 648195 | AI5: =IF(AH5>=AH4,AH5-AH4,0)*0.53 -> 0 | AJ5: 277404 | AK5: =IF(AJ5>=AJ4,AJ5-AJ4,0)*0.53 -> 0 | AL5: 417958 | AM5: =IF(AL5>=AL4,AL5-AL4,0)*0.53 -> 0 | AN5: =W5+Y5+AA5+AC5+AE5+AG5+AI5+AK5+AM5 -> 0 | AO5: 7315006 | AP5: =IF(AO5>=AO4,AO5-AO4,0)*0.1125 -> 0 | AQ5: 611191 | AR5: =IF(AQ5>=AQ4,AQ5-AQ4,0) -> 0 | AS5: 927541 | AT5: =IF(AS5>=AS4,AS5-AS4,0) -> 0 | AU5: 798914 | AV5: =IF(AU5>=AU4,AU5-AU4,0) -> 0 | AW5: 2406790 | AX5: =IF(AW5>=AW4,AW5-AW4,0) -> 0 | AY5: 215052 | AZ5: =IF(AY5>=AY4,AY5-AY4,0) -> 0 | BA5: 18119598 | BB5: =IF(BA5>=BA4,BA5-BA4,0) -> 0 | BC5: 512642 | BD5: =IF(BC5>=BC4,BC5-BC4,0) -> 0 | BE5: 9263 | BF5: =IF(BE5>=BE4,BE5-BE4,0) -> 0 | BG5: 22567804 | BH5: =IF(BG5>=BG4,BG5-BG4,0)-(0.45*BN5)-(0.45*BP5)-BR5 -> 0 | BI5: =AP5+AR5+AT5+AV5+AX5+AZ5+BB5+BD5+BF5+BH5 -> 0 | BJ5: =BI5+AN5 -> 0 | BK5: 1389277 | BL5: =IF(BK5>=BK4,BK5-BK4,0) -> 0 | BM5: 3618486 | BN5: =IF(BM5>=BM4,BM5-BM4,0) -> 0 | BO5: 385840 | BP5: =IF(BO5>=BO4,BO5-BO4,0) -> 0 | BQ5: 476466 | BR5: =IF(BQ5>=BQ4,BQ5-BQ4,0) -> 0
A6: 1 | C6: =IF(+B6-B5>0,B6-B5,(B6-B5)>0)*800 -> 0 | E6: =IF(+D6-D5>0,D6-D5,(D6-D5)>0)*80 -> 0 | G6: =IF(+F6-F5>0,F6-F5,(F6-F5)>0)*10 -> 0 | H6: 56 | I6: 22595025 | J6: =IF(I6>=I5,I6-I5,0) -> 4739 | K6: =M6+O6 -> 3106 | L6: 165884 | M6: =IF(L6>=L5,L6-L5,0) -> 1509 | N6: 182956 | O6: =IF(N6>=N5,N6-N5,0) -> 1597 | P6: 217085 | Q6: =IF(P6>=P5,P6-P5,0)*30 -> 510 | R6: 148316 | S6: =IF(R6>=R5,R6-R5,0) -> 168 | T6: 269111 | U6: =IF(T6>=T5,T6-T5,0) -> 300 | V6: 745444 | W6: =IF(V6>=V5,V6-V5,0)*0.53 -> 2728.44 | X6: 434694 | Y6: =IF(X6>=X5,X6-X5,0)*0.53 -> 0 | Z6: 694798 | AA6: =IF(Z6>=Z5,Z6-Z5,0)*0.53 -> 2163.99 | AB6: 328811 | AC6: =IF(AB6>=AB5,AB6-AB5,0)*0.53 -> 2095.62 | AD6: 421367.4 | AE6: =IF(AD6>=AD5,AD6-AD5,0)*0.53 -> 0 | AF6: 749128 | AG6: =IF(AF6>=AF5,AF6-AF5,0)*0.53 -> 1886.27 | AH6: 650340 | AI6: =IF(AH6>=AH5,AH6-AH5,0)*0.53 -> 1136.85 | AJ6: 284938 | AK6: =IF(AJ6>=AJ5,AJ6-AJ5,0)*0.53 -> 3993.02 | AL6: 418297 | AM6: =IF(AL6>=AL5,AL6-AL5,0)*0.53 -> 179.67 | AN6: =W6+Y6+AA6+AC6+AE6+AG6+AI6+AK6+AM6 -> 14183.86 | AO6: 7316843 | AP6: =IF(AO6>=AO5,AO6-AO5,0)*0.1125 -> 206.6625 | AQ6: 611438 | AR6: =IF(AQ6>=AQ5,AQ6-AQ5,0) -> 247 | AS6: 927692 | AT6: =IF(AS6>=AS5,AS6-AS5,0) -> 151 | AU6: 798986 | AV6: =IF(AU6>=AU5,AU6-AU5,0) -> 72 | AW6: 2407965 | AX6: =IF(AW6>=AW5,AW6-AW5,0) -> 1175 | AY6: 215131 | AZ6: =IF(AY6>=AY5,AY6-AY5,0) -> 79 | BA6: 18124666 | BB6: =IF(BA6>=BA5,BA6-BA5,0) -> 5068 | BC6: 512795 | BD6: =IF(BC6>=BC5,BC6-BC5,0) -> 153 | BE6: 9352 | BF6: =IF(BE6>=BE5,BE6-BE5,0) -> 89 | BG6: 22576660 | BH6: =IF(BG6>=BG5,BG6-BG5,0)-(0.45*BN6)-(0.45*BP6)-BR6 -> 7923.95 | BI6: =AP6+AR6+AT6+AV6+AX6+AZ6+BB6+BD6+BF6+BH6 -> 15164.612 | BJ6: =BI6+AN6 -> 29348.472 | BK6: 1389663 | BL6: =IF(BK6>=BK5,BK6-BK5,0) -> 386 | BM6: 3619927 | BN6: =IF(BM6>=BM5,BM6-BM5,0) -> 1441 | BO6: 385968 | BP6: =IF(BO6>=BO5,BO6-BO5,0) -> 128 | BQ6: 476692 | BR6: =IF(BQ6>=BQ5,BQ6-BQ5,0) -> 226 | BS6: =J6+Q6+AN6+BI6 -> 34597.473 | BT6: 94 | BU6: =IF(BS6>0,BS6/BT5,0) -> #DIV/0! | BW6: =IF(BS6>0,BS6/BV6,0) -> #DIV/0! | BX6: =((BS6-Q6)*$BZ$1)+(Q6*$BR$1) -> 40016.593 | BY6: =IF(BX6>0,BX6/BT5,0) -> #DIV/0! | BZ6: =IF(BX6>0,BX6/BV6,0) -> #DIV/0!
A7: 2 | I7: 22599867 | J7: =IF(I7>=I6,I7-I6,0) -> 4842 | K7: =M7+O7 -> 2936 | L7: 167264 | M7: =IF(L7>=L6,L7-L6,0) -> 1380 | N7: 184512 | O7: =IF(N7>=N6,N7-N6,0) -> 1556 | P7: 217101 | Q7: =IF(P7>=P6,P7-P6,0)*30 -> 480 | R7: 148455 | S7: =IF(R7>=R6,R7-R6,0) -> 139 | T7: 269374 | U7: =IF(T7>=T6,T7-T6,0) -> 263 | V7: 750432 | W7: =IF(V7>=V6,V7-V6,0)*0.53 -> 2643.64 | X7: 438761 | Y7: =IF(X7>=X6,X7-X6,0)*0.53 -> 2155.51 | Z7: 694798 | AA7: =IF(Z7>=Z6,Z7-Z6,0)*0.53 -> 0 | AB7: 329129 | AC7: =IF(AB7>=AB6,AB7-AB6,0)*0.53 -> 168.54 | AD7: 421367.4 | AE7: =IF(AD7>=AD6,AD7-AD6,0)*0.53 -> 0 | AF7: 751806 | AG7: =IF(AF7>=AF6,AF7-AF6,0)*0.53 -> 1419.34 | AH7: 652457 | AI7: =IF(AH7>=AH6,AH7-AH6,0)*0.53 -> 1122.01 | AJ7: 292101 | AK7: =IF(AJ7>=AJ6,AJ7-AJ6,0)*0.53 -> 3796.39 | AL7: 418620 | AM7: =IF(AL7>=AL6,AL7-AL6,0)*0.53 -> 171.19 | AN7: =W7+Y7+AA7+AC7+AE7+AG7+AI7+AK7+AM7 -> 11476.62 | AO7: 7319245 | AP7: =IF(AO7>=AO6,AO7-AO6,0)*0.1125 -> 270.225 | AQ7: 611749 | AR7: =IF(AQ7>=AQ6,AQ7-AQ6,0) -> 311 | AS7: 927854 | AT7: =IF(AS7>=AS6,AS7-AS6,0) -> 162 | AU7: 799033 | AV7: =IF(AU7>=AU6,AU7-AU6,0) -> 47 | AW7: 2409074 | AX7: =IF(AW7>=AW6,AW7-AW6,0) -> 1109 | AY7: 215201 | AZ7: =IF(AY7>=AY6,AY7-AY6,0) -> 70 | BA7: 18129339 | BB7: =IF(BA7>=BA6,BA7-BA6,0) -> 4673 | BC7: 512930 | BD7: =IF(BC7>=BC6,BC7-BC6,0) -> 135 | BE7: 9402 | BF7: =IF(BE7>=BE6,BE7-BE6,0) -> 50 | BG7: 22583274 | BH7: =IF(BG7>=BG6,BG7-BG6,0)-(0.45*BN7)-(0.45*BP7)-BR7 -> 5696.4 | BI7: =AP7+AR7+AT7+AV7+AX7+AZ7+BB7+BD7+BF7+BH7 -> 12523.625 | BJ7: =BI7+AN7 -> 24000.245 | BK7: 1389928 | BL7: =IF(BK7>=BK6,BK7-BK6,0) -> 265 | BM7: 3621383 | BN7: =IF(BM7>=BM6,BM7-BM6,0) -> 1456 | BO7: 386080 | BP7: =IF(BO7>=BO6,BO7-BO6,0) -> 112 | BQ7: 476904 | BR7: =IF(BQ7>=BQ6,BQ7-BQ6,0) -> 212 | BS7: =J7+Q7+AN7+BI7 -> 29322.245 | BT7: 125 | BU7: =IF(BS7>0,BS7/BT6,0) -> 311.93878 | BW7: =IF(BS7>0,BS7/BV7,0) -> #DIV/0! | BX7: =((BS7-Q7)*$BZ$1)+(Q7*$BR$1) -> 33936.582 | BY7: =IF(BX7>0,BX7/BT6,0) -> 361.02747 | BZ7: =IF(BX7>0,BX7/BV7,0) -> #DIV/0!
A8: 3 | C8: =IF(+B8-B7>0,B8-B7,(B8-B7)>0)*800 -> 0 | E8: =IF(+D8-D7>0,D8-D7,(D8-D7)>0)*80 -> 0 | G8: =IF(+F8-F7>0,F8-F7,(F8-F7)>0)*10 -> 0 | H8: 57 | I8: 22604692 | J8: =IF(I8>=I7,I8-I7,0) -> 4825 | K8: =M8+O8 -> 3117 | L8: 168812 | M8: =IF(L8>=L7,L8-L7,0) -> 1548 | N8: 186081 | O8: =IF(N8>=N7,N8-N7,0) -> 1569 | P8: 217120 | Q8: =IF(P8>=P7,P8-P7,0)*30 -> 570 | R8: 148603 | S8: =IF(R8>=R7,R8-R7,0) -> 148 | T8: 269642 | U8: =IF(T8>=T7,T8-T7,0) -> 268 | V8: 754972 | W8: =IF(V8>=V7,V8-V7,0)*0.53 -> 2406.2 | X8: 443235 | Y8: =IF(X8>=X7,X8-X7,0)*0.53 -> 2371.22 | Z8: 694798 | AA8: =IF(Z8>=Z7,Z8-Z7,0)*0.53 -> 0 | AB8: 329129 | AC8: =IF(AB8>=AB7,AB8-AB7,0)*0.53 -> 0 | AD8: 421367.4 | AE8: =IF(AD8>=AD7,AD8-AD7,0)*0.53 -> 0 | AF8: 754662 | AG8: =IF(AF8>=AF7,AF8-AF7,0)*0.53 -> 1513.68 | AH8: 654523 | AI8: =IF(AH8>=AH7,AH8-AH7,0)*0.53 -> 1094.98 | AJ8: 299449 | AK8: =IF(AJ8>=AJ7,AJ8-AJ7,0)*0.53 -> 3894.44 | AL8: 418967 | AM8: =IF(AL8>=AL7,AL8-AL7,0)*0.53 -> 183.91 | AN8: =W8+Y8+AA8+AC8+AE8+AG8+AI8+AK8+AM8 -> 11464.43 | AO8: 7321375 | AP8: =IF(AO8>=AO7,AO8-AO7,0)*0.1125 -> 239.625 | AQ8: 612135 | AR8: =IF(AQ8>=AQ7,AQ8-AQ7,0) -> 386 | AS8: 928019 | AT8: =IF(AS8>=AS7,AS8-AS7,0) -> 165 | AU8: 799083 | AV8: =IF(AU8>=AU7,AU8-AU7,0) -> 50 | AW8: 2410121 | AX8: =IF(AW8>=AW7,AW8-AW7,0) -> 1047 | AY8: 215275 | AZ8: =IF(AY8>=AY7,AY8-AY7,0) -> 74 | BA8: 18134101 | BB8: =IF(BA8>=BA7,BA8-BA7,0) -> 4762 | BC8: 513085 | BD8: =IF(BC8>=BC7,BC8-BC7,0) -> 155 | BE8: 9559 | BF8: =IF(BE8>=BE7,BE8-BE7,0) -> 157 | BG8: 22590060 | BH8: =IF(BG8>=BG7,BG8-BG7,0)-(0.45*BN8)-(0.45*BP8)-BR8 -> 5829.05 | BI8: =AP8+AR8+AT8+AV8+AX8+AZ8+BB8+BD8+BF8+BH8 -> 12864.675 | BJ8: =BI8+AN8 -> 24329.105 | BK8: 1390208 | BL8: =IF(BK8>=BK7,BK8-BK7,0) -> 280 | BM8: 3622897 | BN8: =IF(BM8>=BM7,BM8-BM7,0) -> 1514 | BO8: 386197 | BP8: =IF(BO8>=BO7,BO8-BO7,0) -> 117 | BQ8: 477127 | BR8: =IF(BQ8>=BQ7,BQ8-BQ7,0) -> 223 | BS8: =J8+Q8+AN8+BI8 -> 29724.105 | BT8: 135 | BU8: =IF(BS8>0,BS8/BT7,0) -> 237.79284 | BW8: =IF(BS8>0,BS8/BV8,0) -> #DIV/0! | BX8: =((BS8-Q8)*$BZ$1)+(Q8*$BR$1) -> 34439.221 | BY8: =IF(BX8>0,BX8/BT7,0) -> 275.51377 | BZ8: =IF(BX8>0,BX8/BV8,0) -> #DIV/0!
A9: 4 | C9: =IF(+B9-B8>0,B9-B8,(B9-B8)>0)*800 -> 0 | E9: =IF(+D9-D8>0,D9-D8,(D9-D8)>0)*80 -> 0 | G9: =IF(+F9-F8>0,F9-F8,(F9-F8)>0)*10 -> 0 | I9: 22609100 | J9: =IF(I9>=I8,I9-I8,0) -> 4408 | K9: =M9+O9 -> 2704 | L9: 170292 | M9: =IF(L9>=L8,L9-L8,0) -> 1480 | N9: 187305 | O9: =IF(N9>=N8,N9-N8,0) -> 1224 | P9: 217135 | Q9: =IF(P9>=P8,P9-P8,0)*30 -> 450 | R9: 148731 | S9: =IF(R9>=R8,R9-R8,0) -> 128 | T9: 269883 | U9: =IF(T9>=T8,T9-T8,0) -> 241 | V9: 760291 | W9: =IF(V9>=V8,V9-V8,0)*0.53 -> 2819.07 | X9: 445176 | Y9: =IF(X9>=X8,X9-X8,0)*0.53 -> 1028.73 | Z9: 694798 | AA9: =IF(Z9>=Z8,Z9-Z8,0)*0.53 -> 0 | AB9: 329129 | AC9: =IF(AB9>=AB8,AB9-AB8,0)*0.53 -> 0 | AD9: 421367.4 | AE9: =IF(AD9>=AD8,AD9-AD8,0)*0.53 -> 0 | AF9: 757068 | AG9: =IF(AF9>=AF8,AF9-AF8,0)*0.53 -> 1275.18 | AH9: 655995 | AI9: =IF(AH9>=AH8,AH9-AH8,0)*0.53 -> 780.16 | AJ9: 304941 | AK9: =IF(AJ9>=AJ8,AJ9-AJ8,0)*0.53 -> 2910.76 | AL9: 419265 | AM9: =IF(AL9>=AL8,AL9-AL8,0)*0.53 -> 157.94 | AN9: =W9+Y9+AA9+AC9+AE9+AG9+AI9+AK9+AM9 -> 8971.84 | AO9: 7323427 | AP9: =IF(AO9>=AO8,AO9-AO8,0)*0.1125 -> 230.85 | AQ9: 612457 | AR9: =IF(AQ9>=AQ8,AQ9-AQ8,0) -> 322 | AS9: 928163 | AT9: =IF(AS9>=AS8,AS9-AS8,0) -> 144 | AU9: 799106 | AV9: =IF(AU9>=AU8,AU9-AU8,0) -> 23 | AW9: 2410847 | AX9: =IF(AW9>=AW8,AW9-AW8,0) -> 726 | AY9: 215339 | AZ9: =IF(AY9>=AY8,AY9-AY8,0) -> 64 | BA9: 18137982 | BB9: =IF(BA9>=BA8,BA9-BA8,0) -> 3881 | BC9: 513232 | BD9: =IF(BC9>=BC8,BC9-BC8,0) -> 147 | BE9: 9620 | BF9: =IF(BE9>=BE8,BE9-BE8,0) -> 61 | BG9: 22596090 | BH9: =IF(BG9>=BG8,BG9-BG8,0)-(0.45*BN9)-(0.45*BP9)-BR9 -> 5196.6 | BI9: =AP9+AR9+AT9+AV9+AX9+AZ9+BB9+BD9+BF9+BH9 -> 10795.45 | BJ9: =BI9+AN9 -> 19767.29 | BK9: 1390456 | BL9: =IF(BK9>=BK8,BK9-BK8,0) -> 248 | BM9: 3624204 | BN9: =IF(BM9>=BM8,BM9-BM8,0) -> 1307 | BO9: 386302 | BP9: =IF(BO9>=BO8,BO9-BO8,0) -> 105 | BQ9: 477325 | BR9: =IF(BQ9>=BQ8,BQ9-BQ8,0) -> 198 | BS9: =J9+Q9+AN9+BI9 -> 24625.29 | BT9: 171 | BU9: =IF(BS9>0,BS9/BT8,0) -> 182.40956 | BW9: =IF(BS9>0,BS9/BV9,0) -> #DIV/0! | BX9: =((BS9-Q9)*$BZ$1)+(Q9*$BR$1) -> 28521.584 | BY9: =IF(BX9>0,BX9/BT8,0) -> 211.27099 | BZ9: =IF(BX9>0,BX9/BV9,0) -> #DIV/0!
A10: 5 | C10: =IF(+B10-B9>0,B10-B9,(B10-B9)>0)*800 -> 0 | E10: =IF(+D10-D9>0,D10-D9,(D10-D9)>0)*80 -> 0 | G10: =IF(+F10-F9>0,F10-F9,(F10-F9)>0)*10 -> 0 | H10: 58 | I10: 22614051 | J10: =IF(I10>=I9,I10-I9,0) -> 4951 | K10: =M10+O10 -> 3044 | L10: 171920 | M10: =IF(L10>=L9,L10-L9,0) -> 1628 | N10: 188721 | O10: =IF(N10>=N9,N10-N9,0) -> 1416 | P10: 217152 | Q10: =IF(P10>=P9,P10-P9,0)*30 -> 510 | R10: 148871 | S10: =IF(R10>=R9,R10-R9,0) -> 140 | T10: 270148 | U10: =IF(T10>=T9,T10-T9,0) -> 265 | V10: 765093 | W10: =IF(V10>=V9,V10-V9,0)*0.53 -> 2545.06 | X10: 448169 | Y10: =IF(X10>=X9,X10-X9,0)*0.53 -> 1586.29 | Z10: 694798 | AA10: =IF(Z10>=Z9,Z10-Z9,0)*0.53 -> 0 | AB10: 329129 | AC10: =IF(AB10>=AB9,AB10-AB9,0)*0.53 -> 0 | AD10: 421367.4 | AE10: =IF(AD10>=AD9,AD10-AD9,0)*0.53 -> 0 | AF10: 759653 | AG10: =IF(AF10>=AF9,AF10-AF9,0)*0.53 -> 1370.05 | AH10: 657727 | AI10: =IF(AH10>=AH9,AH10-AH9,0)*0.53 -> 917.96 | AJ10: 311302 | AK10: =IF(AJ10>=AJ9,AJ10-AJ9,0)*0.53 -> 3371.33 | AL10: 419580 | AM10: =IF(AL10>=AL9,AL10-AL9,0)*0.53 -> 166.95 | AN10: =W10+Y10+AA10+AC10+AE10+AG10+AI10+AK10+AM10 -> 9957.64 | AO10: 7325302 | AP10: =IF(AO10>=AO9,AO10-AO9,0)*0.1125 -> 210.9375 | AQ10: 612761 | AR10: =IF(AQ10>=AQ9,AQ10-AQ9,0) -> 304 | AS10: 928305 | AT10: =IF(AS10>=AS9,AS10-AS9,0) -> 142 | AU10: 799138 | AV10: =IF(AU10>=AU9,AU10-AU9,0) -> 32 | AW10: 2411587 | AX10: =IF(AW10>=AW9,AW10-AW9,0) -> 740 | AY10: 215412 | AZ10: =IF(AY10>=AY9,AY10-AY9,0) -> 73 | BA10: 18142546 | BB10: =IF(BA10>=BA9,BA10-BA9,0) -> 4564 | BC10: 513394 | BD10: =IF(BC10>=BC9,BC10-BC9,0) -> 162 | BE10: 9728 | BF10: =IF(BE10>=BE9,BE10-BE9,0) -> 108 | BG10: 22602474 | BH10: =IF(BG10>=BG9,BG10-BG9,0)-(0.45*BN10)-(0.45*BP10)-BR10 -> 5511.6 | BI10: =AP10+AR10+AT10+AV10+AX10+AZ10+BB10+BD10+BF10+BH10 -> 11847.537 | BJ10: =BI10+AN10 -> 21805.177 | BK10: 1390669 | BL10: =IF(BK10>=BK9,BK10-BK9,0) -> 213 | BM10: 3625572 | BN10: =IF(BM10>=BM9,BM10-BM9,0) -> 1368 | BO10: 386406 | BP10: =IF(BO10>=BO9,BO10-BO9,0) -> 104 | BQ10: 477535 | BR10: =IF(BQ10>=BQ9,BQ10-BQ9,0) -> 210 | BS10: =J10+Q10+AN10+BI10 -> 27266.177 | BT10: 160 | BU10: =IF(BS10>0,BS10/BT9,0) -> 159.45133 | BW10: =IF(BS10>0,BS10/BV10,0) -> #DIV/0! | BX10: =((BS10-Q10)*$BZ$1)+(Q10*$BR$1) -> 31585.604 | BY10: =IF(BX10>0,BX10/BT9,0) -> 184.71114 | BZ10: =IF(BX10>0,BX10/BV10,0) -> #DIV/0!
A11: 6 | C11: =IF(+B11-B10>0,B11-B10,(B11-B10)>0)*800 -> 0 | E11: =IF(+D11-D10>0,D11-D10,(D11-D10)>0)*80 -> 0 | G11: =IF(+F11-F10>0,F11-F10,(F11-F10)>0)*10 -> 0 | I11: 22619199 | J11: =IF(I11>=I10,I11-I10,0) -> 5148 | K11: =M11+O11 -> 3203 | L11: 173548 | M11: =IF(L11>=L10,L11-L10,0) -> 1628 | N11: 190296 | O11: =IF(N11>=N10,N11-N10,0) -> 1575 | P11: 217172 | Q11: =IF(P11>=P10,P11-P10,0)*30 -> 600 | R11: 149011 | S11: =IF(R11>=R10,R11-R10,0) -> 140 | T11: 270411 | U11: =IF(T11>=T10,T11-T10,0) -> 263 | V11: 769828 | W11: =IF(V11>=V10,V11-V10,0)*0.53 -> 2509.55 | X11: 448169 | Y11: =IF(X11>=X10,X11-X10,0)*0.53 -> 0 | Z11: 699422 | AA11: =IF(Z11>=Z10,Z11-Z10,0)*0.53 -> 2450.72 | AB11: 329129 | AC11: =IF(AB11>=AB10,AB11-AB10,0)*0.53 -> 0 | AD11: 421367.4 | AE11: =IF(AD11>=AD10,AD11-AD10,0)*0.53 -> 0 | AF11: 762173 | AG11: =IF(AF11>=AF10,AF11-AF10,0)*0.53 -> 1335.6 | AH11: 659659 | AI11: =IF(AH11>=AH10,AH11-AH10,0)*0.53 -> 1023.96 | AJ11: 318047 | AK11: =IF(AJ11>=AJ10,AJ11-AJ10,0)*0.53 -> 3574.85 | AL11: 419894 | AM11: =IF(AL11>=AL10,AL11-AL10,0)*0.53 -> 166.42 | AN11: =W11+Y11+AA11+AC11+AE11+AG11+AI11+AK11+AM11 -> 11061.1 | AO11: 7327133 | AP11: =IF(AO11>=AO10,AO11-AO10,0)*0.1125 -> 205.9875 | AQ11: 613054 | AR11: =IF(AQ11>=AQ10,AQ11-AQ10,0) -> 293 | AS11: 928442 | AT11: =IF(AS11>=AS10,AS11-AS10,0) -> 137 | AU11: 799184 | AV11: =IF(AU11>=AU10,AU11-AU10,0) -> 46 | AW11: 2412337 | AX11: =IF(AW11>=AW10,AW11-AW10,0) -> 750 | AY11: 215484 | AZ11: =IF(AY11>=AY10,AY11-AY10,0) -> 72 | BA11: 18146821 | BB11: =IF(BA11>=BA10,BA11-BA10,0) -> 4275 | BC11: 513559 | BD11: =IF(BC11>=BC10,BC11-BC10,0) -> 165 | BE11: 9851 | BF11: =IF(BE11>=BE10,BE11-BE10,0) -> 123 | BG11: 22608511 | BH11: =IF(BG11>=BG10,BG11-BG10,0)-(0.45*BN11)-(0.45*BP11)-BR11 -> 5192.6 | BI11: =AP11+AR11+AT11+AV11+AX11+AZ11+BB11+BD11+BF11+BH11 -> 11259.588 | BJ11: =BI11+AN11 -> 22320.688 | BK11: 1390669 | BL11: =IF(BK11>=BK10,BK11-BK10,0) -> 0 | BM11: 3626872 | BN11: =IF(BM11>=BM10,BM11-BM10,0) -> 1300 | BO11: 386518 | BP11: =IF(BO11>=BO10,BO11-BO10,0) -> 112 | BQ11: 477744 | BR11: =IF(BQ11>=BQ10,BQ11-BQ10,0) -> 209 | BS11: =J11+Q11+AN11+BI11 -> 28068.688 | BT11: 152 | BU11: =IF(BS11>0,BS11/BT10,0) -> 175.4293 | BW11: =IF(BS11>0,BS11/BV11,0) -> #DIV/0! | BX11: =((BS11-Q11)*$BZ$1)+(Q11*$BR$1) -> 32548.991 | BY11: =IF(BX11>0,BX11/BT10,0) -> 203.43119 | BZ11: =IF(BX11>0,BX11/BV11,0) -> #DIV/0!
A12: 7 | C12: =IF(+B12-B11>0,B12-B11,(B12-B11)>0)*800 -> 0 | E12: =IF(+D12-D11>0,D12-D11,(D12-D11)>0)*80 -> 0 | G12: =IF(+F12-F11>0,F12-F11,(F12-F11)>0)*10 -> 0 | H12: 59 | I12: 22624227 | J12: =IF(I12>=I11,I12-I11,0) -> 5028 | K12: =M12+O12 -> 3083 | L12: 175216 | M12: =IF(L12>=L11,L12-L11,0) -> 1668 | N12: 191711 | O12: =IF(N12>=N11,N12-N11,0) -> 1415 | P12: 217184 | Q12: =IF(P12>=P11,P12-P11,0)*30 -> 360 | R12: 149149 | S12: =IF(R12>=R11,R12-R11,0) -> 138 | T12: 270672 | U12: =IF(T12>=T11,T12-T11,0) -> 261 | V12: 774658 | W12: =IF(V12>=V11,V12-V11,0)*0.53 -> 2559.9 | X12: 448169 | Y12: =IF(X12>=X11,X12-X11,0)*0.53 -> 0 | Z12: 699707 | AA12: =IF(Z12>=Z11,Z12-Z11,0)*0.53 -> 151.05 | AB12: 333210 | AC12: =IF(AB12>=AB11,AB12-AB11,0)*0.53 -> 2162.93 | AD12: 421367.4 | AE12: =IF(AD12>=AD11,AD12-AD11,0)*0.53 -> 0 | AF12: 765002 | AG12: =IF(AF12>=AF11,AF12-AF11,0)*0.53 -> 1499.37 | AH12: 661261 | AI12: =IF(AH12>=AH11,AH12-AH11,0)*0.53 -> 849.06 | AJ12: 324778 | AK12: =IF(AJ12>=AJ11,AJ12-AJ11,0)*0.53 -> 3567.43 | AL12: 420209 | AM12: =IF(AL12>=AL11,AL12-AL11,0)*0.53 -> 166.95 | AN12: =W12+Y12+AA12+AC12+AE12+AG12+AI12+AK12+AM12 -> 10956.69 | AO12: 7329232 | AP12: =IF(AO12>=AO11,AO12-AO11,0)*0.1125 -> 236.1375 | AQ12: 613349 | AR12: =IF(AQ12>=AQ11,AQ12-AQ11,0) -> 295 | AS12: 928589 | AT12: =IF(AS12>=AS11,AS12-AS11,0) -> 147 | AU12: 799236 | AV12: =IF(AU12>=AU11,AU12-AU11,0) -> 52 | AW12: 2413105 | AX12: =IF(AW12>=AW11,AW12-AW11,0) -> 768 | AY12: 215556 | AZ12: =IF(AY12>=AY11,AY12-AY11,0) -> 72 | BA12: 18151153 | BB12: =IF(BA12>=BA11,BA12-BA11,0) -> 4332 | BC12: 513724 | BD12: =IF(BC12>=BC11,BC12-BC11,0) -> 165 | BE12: 9990 | BF12: =IF(BE12>=BE11,BE12-BE11,0) -> 139 | BG12: 22615093 | BH12: =IF(BG12>=BG11,BG12-BG11,0)-(0.45*BN12)-(0.45*BP12)-BR12 -> 5686.1 | BI12: =AP12+AR12+AT12+AV12+AX12+AZ12+BB12+BD12+BF12+BH12 -> 11892.237 | BJ12: =BI12+AN12 -> 22848.928 | BK12: 1390878 | BL12: =IF(BK12>=BK11,BK12-BK11,0) -> 209 | BM12: 3628280 | BN12: =IF(BM12>=BM11,BM12-BM11,0) -> 1408 | BO12: 386632 | BP12: =IF(BO12>=BO11,BO12-BO11,0) -> 114 | BQ12: 477955 | BR12: =IF(BQ12>=BQ11,BQ12-BQ11,0) -> 211 | BS12: =J12+Q12+AN12+BI12 -> 28236.928 | BT12: 161 | BU12: =IF(BS12>0,BS12/BT11,0) -> 185.76926 | BW12: =IF(BS12>0,BS12/BV12,0) -> #DIV/0! | BX12: =((BS12-Q12)*$BZ$1)+(Q12*$BR$1) -> 32634.467 | BY12: =IF(BX12>0,BX12/BT11,0) -> 214.70044 | BZ12: =IF(BX12>0,BX12/BV12,0) -> #DIV/0!
A13: 8 | C13: =IF(+B13-B12>0,B13-B12,(B13-B12)>0)*800 -> 0 | E13: =IF(+D13-D12>0,D13-D12,(D13-D12)>0)*80 -> 0 | G13: =IF(+F13-F12>0,F13-F12,(F13-F12)>0)*10 -> 0 | I13: 22629783 | J13: =IF(I13>=I12,I13-I12,0) -> 5556 | K13: =M13+O13 -> 3452 | L13: 177062 | M13: =IF(L13>=L12,L13-L12,0) -> 1846 | N13: 193317 | O13: =IF(N13>=N12,N13-N12,0) -> 1606 | P13: 217201 | Q13: =IF(P13>=P12,P13-P12,0)*30 -> 510 | R13: 149297 | S13: =IF(R13>=R12,R13-R12,0) -> 148 | T13: 270954 | U13: =IF(T13>=T12,T13-T12,0) -> 282 | V13: 780159 | W13: =IF(V13>=V12,V13-V12,0)*0.53 -> 2915.53 | X13: 452714 | Y13: =IF(X13>=X12,X13-X12,0)*0.53 -> 2408.85 | Z13: 699707 | AA13: =IF(Z13>=Z12,Z13-Z12,0)*0.53 -> 0 | AB13: 333210 | AC13: =IF(AB13>=AB12,AB13-AB12,0)*0.53 -> 0 | AD13: 421367.4 | AE13: =IF(AD13>=AD12,AD13-AD12,0)*0.53 -> 0 | AF13: 766287 | AG13: =IF(AF13>=AF12,AF13-AF12,0)*0.53 -> 681.05 | AH13: 662999 | AI13: =IF(AH13>=AH12,AH13-AH12,0)*0.53 -> 921.14 | AJ13: 332097 | AK13: =IF(AJ13>=AJ12,AJ13-AJ12,0)*0.53 -> 3879.07 | AL13: 420541 | AM13: =IF(AL13>=AL12,AL13-AL12,0)*0.53 -> 175.96 | AN13: =W13+Y13+AA13+AC13+AE13+AG13+AI13+AK13+AM13 -> 10981.6 | AO13: 7331645 | AP13: =IF(AO13>=AO12,AO13-AO12,0)*0.1125 -> 271.4625 | AQ13: 613632 | AR13: =IF(AQ13>=AQ12,AQ13-AQ12,0) -> 283 | AS13: 928738 | AT13: =IF(AS13>=AS12,AS13-AS12,0) -> 149 | AU13: 799288 | AV13: =IF(AU13>=AU12,AU13-AU12,0) -> 52 | AW13: 2413951 | AX13: =IF(AW13>=AW12,AW13-AW12,0) -> 846 | AY13: 215633 | AZ13: =IF(AY13>=AY12,AY13-AY12,0) -> 77 | BA13: 18155685 | BB13: =IF(BA13>=BA12,BA13-BA12,0) -> 4532 | BC13: 513903 | BD13: =IF(BC13>=BC12,BC13-BC12,0) -> 179 | BE13: 10024 | BF13: =IF(BE13>=BE12,BE13-BE12,0) -> 34 | BG13: 22621766 | BH13: =IF(BG13>=BG12,BG13-BG12,0)-(0.45*BN13)-(0.45*BP13)-BR13 -> 5772.4 | BI13: =AP13+AR13+AT13+AV13+AX13+AZ13+BB13+BD13+BF13+BH13 -> 12195.862 | BJ13: =BI13+AN13 -> 23177.463 | BK13: 1390995 | BL13: =IF(BK13>=BK12,BK13-BK12,0) -> 117 | BM13: 3629674 | BN13: =IF(BM13>=BM12,BM13-BM12,0) -> 1394 | BO13: 386746 | BP13: =IF(BO13>=BO12,BO13-BO12,0) -> 114 | BQ13: 478177 | BR13: =IF(BQ13>=BQ12,BQ13-BQ12,0) -> 222 | BS13: =J13+Q13+AN13+BI13 -> 29243.462 | BT13: 91 | BU13: =IF(BS13>0,BS13/BT12,0) -> 181.63641 | BW13: =IF(BS13>0,BS13/BV13,0) -> #DIV/0! | BX13: =((BS13-Q13)*$BZ$1)+(Q13*$BR$1) -> 33859.482 | BY13: =IF(BX13>0,BX13/BT12,0) -> 210.30734 | BZ13: =IF(BX13>0,BX13/BV13,0) -> #DIV/0!
A14: 9 | C14: =IF(+B14-B13>0,B14-B13,(B14-B13)>0)*800 -> 0 | E14: =IF(+D14-D13>0,D14-D13,(D14-D13)>0)*80 -> 0 | G14: =IF(+F14-F13>0,F14-F13,(F14-F13)>0)*10 -> 0 | H14: 60 | I14: 22634486 | J14: =IF(I14>=I13,I14-I13,0) -> 4703 | K14: =M14+O14 -> 3078 | L14: 178713 | M14: =IF(L14>=L13,L14-L13,0) -> 1651 | N14: 194744 | O14: =IF(N14>=N13,N14-N13,0) -> 1427 | P14: 217222 | Q14: =IF(P14>=P13,P14-P13,0)*30 -> 630 | R14: 149428 | S14: =IF(R14>=R13,R14-R13,0) -> 131 | T14: 271207 | U14: =IF(T14>=T13,T14-T13,0) -> 253 | V14: 786130 | W14: =IF(V14>=V13,V14-V13,0)*0.53 -> 3164.63 | X14: 452714 | Y14: =IF(X14>=X13,X14-X13,0)*0.53 -> 0 | Z14: 702884 | AA14: =IF(Z14>=Z13,Z14-Z13,0)*0.53 -> 1683.81 | AB14: 333210 | AC14: =IF(AB14>=AB13,AB14-AB13,0)*0.53 -> 0 | AD14: 366331 | AE14: =IF(AD14>=AD13,AD14-AD13,0)*0.53 -> 0 | AF14: 766307 | AG14: =IF(AF14>=AF13,AF14-AF13,0)*0.53 -> 10.6 | AH14: 664808 | AI14: =IF(AH14>=AH13,AH14-AH13,0)*0.53 -> 958.77 | AJ14: 338589 | AK14: =IF(AJ14>=AJ13,AJ14-AJ13,0)*0.53 -> 3440.76 | AL14: 420855 | AM14: =IF(AL14>=AL13,AL14-AL13,0)*0.53 -> 166.42 | AN14: =W14+Y14+AA14+AC14+AE14+AG14+AI14+AK14+AM14 -> 9424.99 | AO14: 7333544 | AP14: =IF(AO14>=AO13,AO14-AO13,0)*0.1125 -> 213.6375 | AQ14: 613907 | AR14: =IF(AQ14>=AQ13,AQ14-AQ13,0) -> 275 | AS14: 928865 | AT14: =IF(AS14>=AS13,AS14-AS13,0) -> 127 | AU14: 799344 | AV14: =IF(AU14>=AU13,AU14-AU13,0) -> 56 | AW14: 2414787 | AX14: =IF(AW14>=AW13,AW14-AW13,0) -> 836 | AY14: 215702 | AZ14: =IF(AY14>=AY13,AY14-AY13,0) -> 69 | BA14: 18159888 | BB14: =IF(BA14>=BA13,BA14-BA13,0) -> 4203 | BC14: 514064 | BD14: =IF(BC14>=BC13,BC14-BC13,0) -> 161 | BE14: 10145 | BF14: =IF(BE14>=BE13,BE14-BE13,0) -> 121 | BG14: 22627673 | BH14: =IF(BG14>=BG13,BG14-BG13,0)-(0.45*BN14)-(0.45*BP14)-BR14 -> 5080.85 | BI14: =AP14+AR14+AT14+AV14+AX14+AZ14+BB14+BD14+BF14+BH14 -> 11142.487 | BJ14: =BI14+AN14 -> 20567.478 | BK14: 1390997 | BL14: =IF(BK14>=BK13,BK14-BK13,0) -> 2 | BM14: 3630965 | BN14: =IF(BM14>=BM13,BM14-BM13,0) -> 1291 | BO14: 386842 | BP14: =IF(BO14>=BO13,BO14-BO13,0) -> 96 | BQ14: 478379 | BR14: =IF(BQ14>=BQ13,BQ14-BQ13,0) -> 202 | BS14: =J14+Q14+AN14+BI14 -> 25900.478 | BT14: 156 | BU14: =IF(BS14>0,BS14/BT13,0) -> 284.62063 | BW14: =IF(BS14>0,BS14/BV14,0) -> #DIV/0! | BX14: =((BS14-Q14)*$BZ$1)+(Q14*$BR$1) -> 30069.049 | BY14: =IF(BX14>0,BX14/BT13,0) -> 330.42911 | BZ14: =IF(BX14>0,BX14/BV14,0) -> #DIV/0!
A15: 10 | C15: =IF(+B15-B14>0,B15-B14,(B15-B14)>0)*800 -> 0 | E15: =IF(+D15-D14>0,D15-D14,(D15-D14)>0)*80 -> 0 | G15: =IF(+F15-F14>0,F15-F14,(F15-F14)>0)*10 -> 0 | I15: 22639413 | J15: =IF(I15>=I14,I15-I14,0) -> 4927 | K15: =M15+O15 -> 3158 | L15: 180405 | M15: =IF(L15>=L14,L15-L14,0) -> 1692 | N15: 196210 | O15: =IF(N15>=N14,N15-N14,0) -> 1466 | P15: 217241 | Q15: =IF(P15>=P14,P15-P14,0)*30 -> 570 | R15: 149568 | S15: =IF(R15>=R14,R15-R14,0) -> 140 | T15: 271475 | U15: =IF(T15>=T14,T15-T14,0) -> 268 | V15: 791857 | W15: =IF(V15>=V14,V15-V14,0)*0.53 -> 3035.31 | X15: 452714 | Y15: =IF(X15>=X14,X15-X14,0)*0.53 -> 0 | Z15: 708596 | AA15: =IF(Z15>=Z14,Z15-Z14,0)*0.53 -> 3027.36 | AB15: 333210 | AC15: =IF(AB15>=AB14,AB15-AB14,0)*0.53 -> 0 | AD15: 366349 | AE15: =IF(AD15>=AD14,AD15-AD14,0)*0.53 -> 9.54 | AF15: 766328 | AG15: =IF(AF15>=AF14,AF15-AF14,0)*0.53 -> 11.13 | AH15: 666942 | AI15: =IF(AH15>=AH14,AH15-AH14,0)*0.53 -> 1131.02 | AJ15: 345970 | AK15: =IF(AJ15>=AJ14,AJ15-AJ14,0)*0.53 -> 3911.93 | AL15: 421179 | AM15: =IF(AL15>=AL14,AL15-AL14,0)*0.53 -> 171.72 | AN15: =W15+Y15+AA15+AC15+AE15+AG15+AI15+AK15+AM15 -> 11298.01 | AO15: 7335256 | AP15: =IF(AO15>=AO14,AO15-AO14,0)*0.1125 -> 192.6 | AQ15: 614183 | AR15: =IF(AQ15>=AQ14,AQ15-AQ14,0) -> 276 | AS15: 929038 | AT15: =IF(AS15>=AS14,AS15-AS14,0) -> 173 | AU15: 799410 | AV15: =IF(AU15>=AU14,AU15-AU14,0) -> 66 | AW15: 2415649 | AX15: =IF(AW15>=AW14,AW15-AW14,0) -> 862 | AY15: 215776 | AZ15: =IF(AY15>=AY14,AY15-AY14,0) -> 74 | BA15: 18164023 | BB15: =IF(BA15>=BA14,BA15-BA14,0) -> 4135 | BC15: 514234 | BD15: =IF(BC15>=BC14,BC15-BC14,0) -> 170 | BE15: 10245 | BF15: =IF(BE15>=BE14,BE15-BE14,0) -> 100 | BG15: 22634900 | BH15: =IF(BG15>=BG14,BG15-BG14,0)-(0.45*BN15)-(0.45*BP15)-BR15 -> 6305.9 | BI15: =AP15+AR15+AT15+AV15+AX15+AZ15+BB15+BD15+BF15+BH15 -> 12354.5 | BJ15: =BI15+AN15 -> 23652.51 | BK15: 1391248 | BL15: =IF(BK15>=BK14,BK15-BK14,0) -> 251 | BM15: 3632411 | BN15: =IF(BM15>=BM14,BM15-BM14,0) -> 1446 | BO15: 386954 | BP15: =IF(BO15>=BO14,BO15-BO14,0) -> 112 | BQ15: 478599 | BR15: =IF(BQ15>=BQ14,BQ15-BQ14,0) -> 220 | BS15: =J15+Q15+AN15+BI15 -> 29149.51 | BT15: 154 | BU15: =IF(BS15>0,BS15/BT14,0) -> 186.85583 | BW15: =IF(BS15>0,BS15/BV15,0) -> #DIV/0! | BX15: =((BS15-Q15)*$BZ$1)+(Q15*$BR$1) -> 33778.437 | BY15: =IF(BX15>0,BX15/BT14,0) -> 216.52844 | BZ15: =IF(BX15>0,BX15/BV15,0) -> #DIV/0!
A16: 11 | C16: =IF(+B16-B15>0,B16-B15,(B16-B15)>0)*800 -> 0 | E16: =IF(+D16-D15>0,D16-D15,(D16-D15)>0)*80 -> 0 | G16: =IF(+F16-F15>0,F16-F15,(F16-F15)>0)*10 -> 0 | H16: 61 | I16: 22644742 | J16: =IF(I16>=I15,I16-I15,0) -> 5329 | K16: =M16+O16 -> 3142 | L16: 182097 | M16: =IF(L16>=L15,L16-L15,0) -> 1692 | N16: 197660 | O16: =IF(N16>=N15,N16-N15,0) -> 1450 | P16: 217259 | Q16: =IF(P16>=P15,P16-P15,0)*30 -> 540 | R16: 149709 | S16: =IF(R16>=R15,R16-R15,0) -> 141 | T16: 271744 | U16: =IF(T16>=T15,T16-T15,0) -> 269 | V16: 797234 | W16: =IF(V16>=V15,V16-V15,0)*0.53 -> 2849.81 | X16: 452714 | Y16: =IF(X16>=X15,X16-X15,0)*0.53 -> 0 | Z16: 713528 | AA16: =IF(Z16>=Z15,Z16-Z15,0)*0.53 -> 2613.96 | AB16: 333210 | AC16: =IF(AB16>=AB15,AB16-AB15,0)*0.53 -> 0 | AD16: 366357 | AE16: =IF(AD16>=AD15,AD16-AD15,0)*0.53 -> 4.24 | AF16: 766349 | AG16: =IF(AF16>=AF15,AF16-AF15,0)*0.53 -> 11.13 | AH16: 668763 | AI16: =IF(AH16>=AH15,AH16-AH15,0)*0.53 -> 965.13 | AJ16: 352585 | AK16: =IF(AJ16>=AJ15,AJ16-AJ15,0)*0.53 -> 3505.95 | AL16: 421478 | AM16: =IF(AL16>=AL15,AL16-AL15,0)*0.53 -> 158.47 | AN16: =W16+Y16+AA16+AC16+AE16+AG16+AI16+AK16+AM16 -> 10108.69 | AO16: 7337141 | AP16: =IF(AO16>=AO15,AO16-AO15,0)*0.1125 -> 212.0625 | AQ16: 614487 | AR16: =IF(AQ16>=AQ15,AQ16-AQ15,0) -> 304 | AS16: 929216 | AT16: =IF(AS16>=AS15,AS16-AS15,0) -> 178 | AU16: 799463 | AV16: =IF(AU16>=AU15,AU16-AU15,0) -> 53 | AW16: 2416450 | AX16: =IF(AW16>=AW15,AW16-AW15,0) -> 801 | AY16: 215850 | AZ16: =IF(AY16>=AY15,AY16-AY15,0) -> 74 | BA16: 18168585 | BB16: =IF(BA16>=BA15,BA16-BA15,0) -> 4562 | BC16: 514405 | BD16: =IF(BC16>=BC15,BC16-BC15,0) -> 171 | BE16: 10370 | BF16: =IF(BE16>=BE15,BE16-BE15,0) -> 125 | BG16: 22641587 | BH16: =IF(BG16>=BG15,BG16-BG15,0)-(0.45*BN16)-(0.45*BP16)-BR16 -> 5843.65 | BI16: =AP16+AR16+AT16+AV16+AX16+AZ16+BB16+BD16+BF16+BH16 -> 12323.712 | BJ16: =BI16+AN16 -> 22432.403 | BK16: 1391504 | BL16: =IF(BK16>=BK15,BK16-BK15,0) -> 256 | BM16: 3633736 | BN16: =IF(BM16>=BM15,BM16-BM15,0) -> 1325 | BO16: 387052 | BP16: =IF(BO16>=BO15,BO16-BO15,0) -> 98 | BQ16: 478802 | BR16: =IF(BQ16>=BQ15,BQ16-BQ15,0) -> 203 | BS16: =J16+Q16+AN16+BI16 -> 28301.403 | BT16: 164 | BU16: =IF(BS16>0,BS16/BT15,0) -> 183.77534 | BW16: =IF(BS16>0,BS16/BV16,0) -> #DIV/0! | BX16: =((BS16-Q16)*$BZ$1)+(Q16*$BR$1) -> 32789.613 | BY16: =IF(BX16>0,BX16/BT15,0) -> 212.91956 | BZ16: =IF(BX16>0,BX16/BV16,0) -> #DIV/0!
A17: 12 | C17: =IF(+B17-B16>0,B17-B16,(B17-B16)>0)*800 -> 0 | E17: =IF(+D17-D16>0,D17-D16,(D17-D16)>0)*80 -> 0 | G17: =IF(+F17-F16>0,F17-F16,(F17-F16)>0)*10 -> 0 | I17: 22649952 | J17: =IF(I17>=I16,I17-I16,0) -> 5210 | K17: =M17+O17 -> 3334 | L17: 183888 | M17: =IF(L17>=L16,L17-L16,0) -> 1791 | N17: 199203 | O17: =IF(N17>=N16,N17-N16,0) -> 1543 | P17: 217277 | Q17: =IF(P17>=P16,P17-P16,0)*30 -> 540 | R17: 149850 | S17: =IF(R17>=R16,R17-R16,0) -> 141 | T17: 272019 | U17: =IF(T17>=T16,T17-T16,0) -> 275 | V17: 803282 | W17: =IF(V17>=V16,V17-V16,0)*0.53 -> 3205.44 | X17: 457252 | Y17: =IF(X17>=X16,X17-X16,0)*0.53 -> 2405.14 | Z17: 713595 | AA17: =IF(Z17>=Z16,Z17-Z16,0)*0.53 -> 35.51 | AB17: 333210 | AC17: =IF(AB17>=AB16,AB17-AB16,0)*0.53 -> 0 | AD17: 366373 | AE17: =IF(AD17>=AD16,AD17-AD16,0)*0.53 -> 8.48 | AF17: 766370 | AG17: =IF(AF17>=AF16,AF17-AF16,0)*0.53 -> 11.13 | AH17: 670729 | AI17: =IF(AH17>=AH16,AH17-AH16,0)*0.53 -> 1041.98 | AJ17: 359904 | AK17: =IF(AJ17>=AJ16,AJ17-AJ16,0)*0.53 -> 3879.07 | AL17: 421804 | AM17: =IF(AL17>=AL16,AL17-AL16,0)*0.53 -> 172.78 | AN17: =W17+Y17+AA17+AC17+AE17+AG17+AI17+AK17+AM17 -> 10759.53 | AO17: 7338933 | AP17: =IF(AO17>=AO16,AO17-AO16,0)*0.1125 -> 201.6 | AQ17: 614731 | AR17: =IF(AQ17>=AQ16,AQ17-AQ16,0) -> 244 | AS17: 929369 | AT17: =IF(AS17>=AS16,AS17-AS16,0) -> 153 | AU17: 799522 | AV17: =IF(AU17>=AU16,AU17-AU16,0) -> 59 | AW17: 2417306 | AX17: =IF(AW17>=AW16,AW17-AW16,0) -> 856 | AY17: 215925 | AZ17: =IF(AY17>=AY16,AY17-AY16,0) -> 75 | BA17: 18173476 | BB17: =IF(BA17>=BA16,BA17-BA16,0) -> 4891 | BC17: 514584 | BD17: =IF(BC17>=BC16,BC17-BC16,0) -> 179 | BE17: 10484 | BF17: =IF(BE17>=BE16,BE17-BE16,0) -> 114 | BG17: 22648690 | BH17: =IF(BG17>=BG16,BG17-BG16,0)-(0.45*BN17)-(0.45*BP17)-BR17 -> 6214.2 | BI17: =AP17+AR17+AT17+AV17+AX17+AZ17+BB17+BD17+BF17+BH17 -> 12986.8 | BJ17: =BI17+AN17 -> 23746.33 | BK17: 1391774 | BL17: =IF(BK17>=BK16,BK17-BK16,0) -> 270 | BM17: 3635137 | BN17: =IF(BM17>=BM16,BM17-BM16,0) -> 1401 | BO17: 387155 | BP17: =IF(BO17>=BO16,BO17-BO16,0) -> 103 | BQ17: 479014 | BR17: =IF(BQ17>=BQ16,BQ17-BQ16,0) -> 212 | BS17: =J17+Q17+AN17+BI17 -> 29496.33 | BT17: 147 | BU17: =IF(BS17>0,BS17/BT16,0) -> 179.85567 | BW17: =IF(BS17>0,BS17/BV17,0) -> #DIV/0! | BX17: =((BS17-Q17)*$BZ$1)+(Q17*$BR$1) -> 34163.779 | BY17: =IF(BX17>0,BX17/BT16,0) -> 208.31573 | BZ17: =IF(BX17>0,BX17/BV17,0) -> #DIV/0!
A18: 13 | C18: =IF(+B18-B17>0,B18-B17,(B18-B17)>0)*800 -> 0 | E18: =IF(+D18-D17>0,D18-D17,(D18-D17)>0)*80 -> 0 | G18: =IF(+F18-F17>0,F18-F17,(F18-F17)>0)*10 -> 0 | H18: 62 | I18: 22655143 | J18: =IF(I18>=I17,I18-I17,0) -> 5191 | K18: =M18+O18 -> 3314 | L18: 185662 | M18: =IF(L18>=L17,L18-L17,0) -> 1774 | N18: 200743 | O18: =IF(N18>=N17,N18-N17,0) -> 1540 | P18: 217298 | Q18: =IF(P18>=P17,P18-P17,0)*30 -> 630 | R18: 149987 | S18: =IF(R18>=R17,R18-R17,0) -> 137 | T18: 272286 | U18: =IF(T18>=T17,T18-T17,0) -> 267 | V18: 809175 | W18: =IF(V18>=V17,V18-V17,0)*0.53 -> 3123.29 | X18: 462670 | Y18: =IF(X18>=X17,X18-X17,0)*0.53 -> 2871.54 | Z18: 713595 | AA18: =IF(Z18>=Z17,Z18-Z17,0)*0.53 -> 0 | AB18: 333210 | AC18: =IF(AB18>=AB17,AB18-AB17,0)*0.53 -> 0 | AD18: 366384 | AE18: =IF(AD18>=AD17,AD18-AD17,0)*0.53 -> 5.83 | AF18: 766407 | AG18: =IF(AF18>=AF17,AF18-AF17,0)*0.53 -> 19.61 | AH18: 672761 | AI18: =IF(AH18>=AH17,AH18-AH17,0)*0.53 -> 1076.96 | AJ18: 367410 | AK18: =IF(AJ18>=AJ17,AJ18-AJ17,0)*0.53 -> 3978.18 | AL18: 422124 | AM18: =IF(AL18>=AL17,AL18-AL17,0)*0.53 -> 169.6 | AN18: =W18+Y18+AA18+AC18+AE18+AG18+AI18+AK18+AM18 -> 11245.01 | AO18: 7340741 | AP18: =IF(AO18>=AO17,AO18-AO17,0)*0.1125 -> 203.4 | AQ18: 615012 | AR18: =IF(AQ18>=AQ17,AQ18-AQ17,0) -> 281 | AS18: 929520 | AT18: =IF(AS18>=AS17,AS18-AS17,0) -> 151 | AU18: 799582 | AV18: =IF(AU18>=AU17,AU18-AU17,0) -> 60 | AW18: 2418155 | AX18: =IF(AW18>=AW17,AW18-AW17,0) -> 849 | AY18: 215999 | AZ18: =IF(AY18>=AY17,AY18-AY17,0) -> 74 | BA18: 18178138 | BB18: =IF(BA18>=BA17,BA18-BA17,0) -> 4662 | BC18: 514755 | BD18: =IF(BC18>=BC17,BC18-BC17,0) -> 171 | BE18: 10603 | BF18: =IF(BE18>=BE17,BE18-BE17,0) -> 119 | BG18: 22655373 | BH18: =IF(BG18>=BG17,BG18-BG17,0)-(0.45*BN18)-(0.45*BP18)-BR18 -> 5828.3 | BI18: =AP18+AR18+AT18+AV18+AX18+AZ18+BB18+BD18+BF18+BH18 -> 12398.7 | BJ18: =BI18+AN18 -> 23643.71 | BK18: 1392027 | BL18: =IF(BK18>=BK17,BK18-BK17,0) -> 253 | BM18: 3636477 | BN18: =IF(BM18>=BM17,BM18-BM17,0) -> 1340 | BO18: 387261 | BP18: =IF(BO18>=BO17,BO18-BO17,0) -> 106 | BQ18: 479218 | BR18: =IF(BQ18>=BQ17,BQ18-BQ17,0) -> 204 | BS18: =J18+Q18+AN18+BI18 -> 29464.71 | BT18: 131 | BU18: =IF(BS18>0,BS18/BT17,0) -> 200.4402 | BW18: =IF(BS18>0,BS18/BV18,0) -> #DIV/0! | BX18: =((BS18-Q18)*$BZ$1)+(Q18*$BR$1) -> 34167.916 | BY18: =IF(BX18>0,BX18/BT17,0) -> 232.43481 | BZ18: =IF(BX18>0,BX18/BV18,0) -> #DIV/0!
A19: 14 | C19: =IF(+B19-B18>0,B19-B18,(B19-B18)>0)*800 -> 0 | E19: =IF(+D19-D18>0,D19-D18,(D19-D18)>0)*80 -> 0 | G19: =IF(+F19-F18>0,F19-F18,(F19-F18)>0)*10 -> 0 | I19: 22660136 | J19: =IF(I19>=I18,I19-I18,0) -> 4993 | K19: =M19+O19 -> 3278 | L19: 187336 | M19: =IF(L19>=L18,L19-L18,0) -> 1674 | N19: 202347 | O19: =IF(N19>=N18,N19-N18,0) -> 1604 | P19: 217316 | Q19: =IF(P19>=P18,P19-P18,0)*30 -> 540 | R19: 150123 | S19: =IF(R19>=R18,R19-R18,0) -> 136 | T19: 272544 | U19: =IF(T19>=T18,T19-T18,0) -> 258 | V19: 813696 | W19: =IF(V19>=V18,V19-V18,0)*0.53 -> 2396.13 | X19: 469390 | Y19: =IF(X19>=X18,X19-X18,0)*0.53 -> 3561.6 | Z19: 713595 | AA19: =IF(Z19>=Z18,Z19-Z18,0)*0.53 -> 0 | AB19: 333210 | AC19: =IF(AB19>=AB18,AB19-AB18,0)*0.53 -> 0 | AD19: 366403 | AE19: =IF(AD19>=AD18,AD19-AD18,0)*0.53 -> 10.07 | AF19: 766427 | AG19: =IF(AF19>=AF18,AF19-AF18,0)*0.53 -> 10.6 | AH19: 674778 | AI19: =IF(AH19>=AH18,AH19-AH18,0)*0.53 -> 1069.01 | AJ19: 375004 | AK19: =IF(AJ19>=AJ18,AJ19-AJ18,0)*0.53 -> 4024.82 | AL19: 422435 | AM19: =IF(AL19>=AL18,AL19-AL18,0)*0.53 -> 164.83 | AN19: =W19+Y19+AA19+AC19+AE19+AG19+AI19+AK19+AM19 -> 11237.06 | AO19: 7342612 | AP19: =IF(AO19>=AO18,AO19-AO18,0)*0.1125 -> 210.4875 | AQ19: 615297 | AR19: =IF(AQ19>=AQ18,AQ19-AQ18,0) -> 285 | AS19: 929686 | AT19: =IF(AS19>=AS18,AS19-AS18,0) -> 166 | AU19: 799630 | AV19: =IF(AU19>=AU18,AU19-AU18,0) -> 48 | AW19: 2418983 | AX19: =IF(AW19>=AW18,AW19-AW18,0) -> 828 | AY19: 216072 | AZ19: =IF(AY19>=AY18,AY19-AY18,0) -> 73 | BA19: 18182463 | BB19: =IF(BA19>=BA18,BA19-BA18,0) -> 4325 | BC19: 514911 | BD19: =IF(BC19>=BC18,BC19-BC18,0) -> 156 | BE19: 10709 | BF19: =IF(BE19>=BE18,BE19-BE18,0) -> 106 | BG19: 22662077 | BH19: =IF(BG19>=BG18,BG19-BG18,0)-(0.45*BN19)-(0.45*BP19)-BR19 -> 5826.05 | BI19: =AP19+AR19+AT19+AV19+AX19+AZ19+BB19+BD19+BF19+BH19 -> 12023.538 | BJ19: =BI19+AN19 -> 23260.598 | BK19: 1392288 | BL19: =IF(BK19>=BK18,BK19-BK18,0) -> 261 | BM19: 3637858 | BN19: =IF(BM19>=BM18,BM19-BM18,0) -> 1381 | BO19: 387371 | BP19: =IF(BO19>=BO18,BO19-BO18,0) -> 110 | BQ19: 479425 | BR19: =IF(BQ19>=BQ18,BQ19-BQ18,0) -> 207 | BS19: =J19+Q19+AN19+BI19 -> 28793.598 | BT19: 146 | BU19: =IF(BS19>0,BS19/BT18,0) -> 219.79845 | BW19: =IF(BS19>0,BS19/BV19,0) -> #DIV/0! | BX19: =((BS19-Q19)*$BZ$1)+(Q19*$BR$1) -> 33355.637 | BY19: =IF(BX19>0,BX19/BT18,0) -> 254.62318 | BZ19: =IF(BX19>0,BX19/BV19,0) -> #DIV/0!
A20: 15 | C20: =IF(+B20-B19>0,B20-B19,(B20-B19)>0)*800 -> 0 | E20: =IF(+D20-D19>0,D20-D19,(D20-D19)>0)*80 -> 0 | G20: =IF(+F20-F19>0,F20-F19,(F20-F19)>0)*10 -> 0 | H20: 63 | I20: 22665686 | J20: =IF(I20>=I19,I20-I19,0) -> 5550 | K20: =M20+O20 -> 3319 | L20: 189007 | M20: =IF(L20>=L19,L20-L19,0) -> 1671 | N20: 203995 | O20: =IF(N20>=N19,N20-N19,0) -> 1648 | P20: 217334 | Q20: =IF(P20>=P19,P20-P19,0)*30 -> 540 | R20: 150263 | S20: =IF(R20>=R19,R20-R19,0) -> 140 | T20: 272809 | U20: =IF(T20>=T19,T20-T19,0) -> 265 | V20: 819233 | W20: =IF(V20>=V19,V20-V19,0)*0.53 -> 2934.61 | X20: 474105 | Y20: =IF(X20>=X19,X20-X19,0)*0.53 -> 2498.95 | Z20: 713595 | AA20: =IF(Z20>=Z19,Z20-Z19,0)*0.53 -> 0 | AB20: 333210 | AC20: =IF(AB20>=AB19,AB20-AB19,0)*0.53 -> 0 | AD20: 366419 | AE20: =IF(AD20>=AD19,AD20-AD19,0)*0.53 -> 8.48 | AF20: 766447 | AG20: =IF(AF20>=AF19,AF20-AF19,0)*0.53 -> 10.6 | AH20: 676660 | AI20: =IF(AH20>=AH19,AH20-AH19,0)*0.53 -> 997.46 | AJ20: 381673 | AK20: =IF(AJ20>=AJ19,AJ20-AJ19,0)*0.53 -> 3534.57 | AL20: 422737 | AM20: =IF(AL20>=AL19,AL20-AL19,0)*0.53 -> 160.06 | AN20: =W20+Y20+AA20+AC20+AE20+AG20+AI20+AK20+AM20 -> 10144.73 | AO20: 7344495 | AP20: =IF(AO20>=AO19,AO20-AO19,0)*0.1125 -> 211.8375 | AQ20: 615577 | AR20: =IF(AQ20>=AQ19,AQ20-AQ19,0) -> 280 | AS20: 929831 | AT20: =IF(AS20>=AS19,AS20-AS19,0) -> 145 | AU20: 799679 | AV20: =IF(AU20>=AU19,AU20-AU19,0) -> 49 | AW20: 2419790 | AX20: =IF(AW20>=AW19,AW20-AW19,0) -> 807 | AY20: 216147 | AZ20: =IF(AY20>=AY19,AY20-AY19,0) -> 75 | BA20: 18186808 | BB20: =IF(BA20>=BA19,BA20-BA19,0) -> 4345 | BC20: 515082 | BD20: =IF(BC20>=BC19,BC20-BC19,0) -> 171 | BE20: 10796 | BF20: =IF(BE20>=BE19,BE20-BE19,0) -> 87 | BG20: 22669060 | BH20: =IF(BG20>=BG19,BG20-BG19,0)-(0.45*BN20)-(0.45*BP20)-BR20 -> 6114.85 | BI20: =AP20+AR20+AT20+AV20+AX20+AZ20+BB20+BD20+BF20+BH20 -> 12285.688 | BJ20: =BI20+AN20 -> 22430.417 | BK20: 1392552 | BL20: =IF(BK20>=BK19,BK20-BK19,0) -> 264 | BM20: 3639216 | BN20: =IF(BM20>=BM19,BM20-BM19,0) -> 1358 | BO20: 387480 | BP20: =IF(BO20>=BO19,BO20-BO19,0) -> 109 | BQ20: 479633 | BR20: =IF(BQ20>=BQ19,BQ20-BQ19,0) -> 208 | BS20: =J20+Q20+AN20+BI20 -> 28520.417 | BT20: 147 | BU20: =IF(BS20>0,BS20/BT20,0) -> 194.01645 | BW20: =IF(BS20>0,BS20/BV20,0) -> #DIV/0! | BX20: =((BS20-Q20)*$BZ$1)+(Q20*$BR$1) -> 33041.48 | BY20: =IF(BX20>0,BX20/BT20,0) -> 224.77197 | BZ20: =IF(BX20>0,BX20/BV20,0) -> #DIV/0!
A21: 16 | C21: =IF(+B21-B20>0,B21-B20,(B21-B20)>0)*800 -> 0 | E21: =IF(+D21-D20>0,D21-D20,(D21-D20)>0)*80 -> 0 | G21: =IF(+F21-F20>0,F21-F20,(F21-F20)>0)*10 -> 0 | I21: 22671296 | J21: =IF(I21>=I20,I21-I20,0) -> 5610 | K21: =M21+O21 -> 3495 | L21: 190818 | M21: =IF(L21>=L20,L21-L20,0) -> 1811 | N21: 205679 | O21: =IF(N21>=N20,N21-N20,0) -> 1684 | P21: 217354 | Q21: =IF(P21>=P20,P21-P20,0)*30 -> 600 | R21: 150401 | S21: =IF(R21>=R20,R21-R20,0) -> 138 | T21: 273068 | U21: =IF(T21>=T20,T21-T20,0) -> 259 | V21: 824638 | W21: =IF(V21>=V20,V21-V20,0)*0.53 -> 2864.65 | X21: 479163 | Y21: =IF(X21>=X20,X21-X20,0)*0.53 -> 2680.74 | Z21: 713595 | AA21: =IF(Z21>=Z20,Z21-Z20,0)*0.53 -> 0 | AB21: 333210 | AC21: =IF(AB21>=AB20,AB21-AB20,0)*0.53 -> 0 | AD21: 364960 | AE21: =IF(AD21>=AD20,AD21-AD20,0)*0.53 -> 0 | AF21: 768432 | AG21: =IF(AF21>=AF20,AF21-AF20,0)*0.53 -> 1052.05 | AH21: 678569 | AI21: =IF(AH21>=AH20,AH21-AH20,0)*0.53 -> 1011.77 | AJ21: 388739 | AK21: =IF(AJ21>=AJ20,AJ21-AJ20,0)*0.53 -> 3744.98 | AL21: 423042 | AM21: =IF(AL21>=AL20,AL21-AL20,0)*0.53 -> 161.65 | AN21: =W21+Y21+AA21+AC21+AE21+AG21+AI21+AK21+AM21 -> 11515.84 | AO21: 7346240 | AP21: =IF(AO21>=AO20,AO21-AO20,0)*0.1125 -> 196.3125 | AQ21: 615812 | AR21: =IF(AQ21>=AQ20,AQ21-AQ20,0) -> 235 | AS21: 929970 | AT21: =IF(AS21>=AS20,AS21-AS20,0) -> 139 | AU21: 799730 | AV21: =IF(AU21>=AU20,AU21-AU20,0) -> 51 | AW21: 2420634 | AX21: =IF(AW21>=AW20,AW21-AW20,0) -> 844 | AY21: 216220 | AZ21: =IF(AY21>=AY20,AY21-AY20,0) -> 73 | BA21: 18191288 | BB21: =IF(BA21>=BA20,BA21-BA20,0) -> 4480 | BC21: 515236 | BD21: =IF(BC21>=BC20,BC21-BC20,0) -> 154 | BE21: 10908 | BF21: =IF(BE21>=BE20,BE21-BE20,0) -> 112 | BG21: 22675797 | BH21: =IF(BG21>=BG20,BG21-BG20,0)-(0.45*BN21)-(0.45*BP21)-BR21 -> 5880.5 | BI21: =AP21+AR21+AT21+AV21+AX21+AZ21+BB21+BD21+BF21+BH21 -> 12164.812 | BJ21: =BI21+AN21 -> 23680.653 | BK21: 1392811 | BL21: =IF(BK21>=BK20,BK21-BK20,0) -> 259 | BM21: 3640559 | BN21: =IF(BM21>=BM20,BM21-BM20,0) -> 1343 | BO21: 387587 | BP21: =IF(BO21>=BO20,BO21-BO20,0) -> 107 | BQ21: 479837 | BR21: =IF(BQ21>=BQ20,BQ21-BQ20,0) -> 204 | BS21: =J21+Q21+AN21+BI21 -> 29890.653 | BT21: 160 | BU21: =IF(BS21>0,BS21/BT21,0) -> 186.81658 | BW21: =IF(BS21>0,BS21/BV21,0) -> #DIV/0! | BX21: =((BS21-Q21)*$BZ$1)+(Q21*$BR$1) -> 34644.25 | BY21: =IF(BX21>0,BX21/BT21,0) -> 216.52656 | BZ21: =IF(BX21>0,BX21/BV21,0) -> #DIV/0!
A22: 17 | C22: =IF(+B22-B21>0,B22-B21,(B22-B21)>0)*800 -> 0 | E22: =IF(+D22-D21>0,D22-D21,(D22-D21)>0)*80 -> 0 | G22: =IF(+F22-F21>0,F22-F21,(F22-F21)>0)*10 -> 0 | H22: 64 | I22: 22676560 | J22: =IF(I22>=I21,I22-I21,0) -> 5264 | K22: =M22+O22 -> 3447 | L22: 192680 | M22: =IF(L22>=L21,L22-L21,0) -> 1862 | N22: 207264 | O22: =IF(N22>=N21,N22-N21,0) -> 1585 | P22: 217372 | Q22: =IF(P22>=P21,P22-P21,0)*30 -> 540 | R22: 150539 | S22: =IF(R22>=R21,R22-R21,0) -> 138 | T22: 273326 | U22: =IF(T22>=T21,T22-T21,0) -> 258 | V22: 830018 | W22: =IF(V22>=V21,V22-V21,0)*0.53 -> 2851.4 | X22: 482107 | Y22: =IF(X22>=X21,X22-X21,0)*0.53 -> 1560.32 | Z22: 715622 | AA22: =IF(Z22>=Z21,Z22-Z21,0)*0.53 -> 1074.31 | AB22: 333210 | AC22: =IF(AB22>=AB21,AB22-AB21,0)*0.53 -> 0 | AD22: 364937 | AE22: =IF(AD22>=AD21,AD22-AD21,0)*0.53 -> 0 | AF22: 771351 | AG22: =IF(AF22>=AF21,AF22-AF21,0)*0.53 -> 1547.07 | AH22: 680109 | AI22: =IF(AH22>=AH21,AH22-AH21,0)*0.53 -> 816.2 | AJ22: 395637 | AK22: =IF(AJ22>=AJ21,AJ22-AJ21,0)*0.53 -> 3655.94 | AL22: 423363 | AM22: =IF(AL22>=AL21,AL22-AL21,0)*0.53 -> 170.13 | AN22: =W22+Y22+AA22+AC22+AE22+AG22+AI22+AK22+AM22 -> 11675.37 | AO22: 7347902 | AP22: =IF(AO22>=AO21,AO22-AO21,0)*0.1125 -> 186.975 | AQ22: 616057 | AR22: =IF(AQ22>=AQ21,AQ22-AQ21,0) -> 245 | AS22: 930115 | AT22: =IF(AS22>=AS21,AS22-AS21,0) -> 145 | AU22: 799778 | AV22: =IF(AU22>=AU21,AU22-AU21,0) -> 48 | AW22: 2421466 | AX22: =IF(AW22>=AW21,AW22-AW21,0) -> 832 | AY22: 216288 | AZ22: =IF(AY22>=AY21,AY22-AY21,0) -> 68 | BA22: 18196105 | BB22: =IF(BA22>=BA21,BA22-BA21,0) -> 4817 | BC22: 515383 | BD22: =IF(BC22>=BC21,BC22-BC21,0) -> 147 | BE22: 10975 | BF22: =IF(BE22>=BE21,BE22-BE21,0) -> 67 | BG22: 22682262 | BH22: =IF(BG22>=BG21,BG22-BG21,0)-(0.45*BN22)-(0.45*BP22)-BR22 -> 5645.9 | BI22: =AP22+AR22+AT22+AV22+AX22+AZ22+BB22+BD22+BF22+BH22 -> 12201.875 | BJ22: =BI22+AN22 -> 23877.245 | BK22: 1392937 | BL22: =IF(BK22>=BK21,BK22-BK21,0) -> 126 | BM22: 3641811 | BN22: =IF(BM22>=BM21,BM22-BM21,0) -> 1252 | BO22: 387693 | BP22: =IF(BO22>=BO21,BO22-BO21,0) -> 106 | BQ22: 480045 | BR22: =IF(BQ22>=BQ21,BQ22-BQ21,0) -> 208 | BS22: =J22+Q22+AN22+BI22 -> 29681.245 | BT22: 168 | BU22: =IF(BS22>0,BS22/BT22,0) -> 176.67408 | BW22: =IF(BS22>0,BS22/BV22,0) -> #DIV/0! | BX22: =((BS22-Q22)*$BZ$1)+(Q22*$BR$1) -> 34376.432 | BY22: =IF(BX22>0,BX22/BT22,0) -> 204.62162 | BZ22: =IF(BX22>0,BX22/BV22,0) -> #DIV/0!
A23: 18 | C23: =IF(+B23-B22>0,B23-B22,(B23-B22)>0)*800 -> 0 | E23: =IF(+D23-D22>0,D23-D22,(D23-D22)>0)*80 -> 0 | G23: =IF(+F23-F22>0,F23-F22,(F23-F22)>0)*10 -> 0 | I23: 22681838 | J23: =IF(I23>=I22,I23-I22,0) -> 5278 | K23: =M23+O23 -> 3193 | L23: 194427 | M23: =IF(L23>=L22,L23-L22,0) -> 1747 | N23: 208710 | O23: =IF(N23>=N22,N23-N22,0) -> 1446 | P23: 217392 | Q23: =IF(P23>=P22,P23-P22,0)*30 -> 600 | R23: 150680 | S23: =IF(R23>=R22,R23-R22,0) -> 141 | T23: 273597 | U23: =IF(T23>=T22,T23-T22,0) -> 271 | V23: 835439 | W23: =IF(V23>=V22,V23-V22,0)*0.53 -> 2873.13 | X23: 482107 | Y23: =IF(X23>=X22,X23-X22,0)*0.53 -> 0 | Z23: 719624 | AA23: =IF(Z23>=Z22,Z23-Z22,0)*0.53 -> 2121.06 | AB23: 333210 | AC23: =IF(AB23>=AB22,AB23-AB22,0)*0.53 -> 0 | AD23: 364914 | AE23: =IF(AD23>=AD22,AD23-AD22,0)*0.53 -> 0 | AF23: 774220 | AG23: =IF(AF23>=AF22,AF23-AF22,0)*0.53 -> 1520.57 | AH23: 681821 | AI23: =IF(AH23>=AH22,AH23-AH22,0)*0.53 -> 907.36 | AJ23: 401907 | AK23: =IF(AJ23>=AJ22,AJ23-AJ22,0)*0.53 -> 3323.1 | AL23: 423672 | AM23: =IF(AL23>=AL22,AL23-AL22,0)*0.53 -> 163.77 | AN23: =W23+Y23+AA23+AC23+AE23+AG23+AI23+AK23+AM23 -> 10908.99 | AO23: 7349565 | AP23: =IF(AO23>=AO22,AO23-AO22,0)*0.1125 -> 187.0875 | AQ23: 616256 | AR23: =IF(AQ23>=AQ22,AQ23-AQ22,0) -> 199 | AS23: 930269 | AT23: =IF(AS23>=AS22,AS23-AS22,0) -> 154 | AU23: 799815 | AV23: =IF(AU23>=AU22,AU23-AU22,0) -> 37 | AW23: 2422237 | AX23: =IF(AW23>=AW22,AW23-AW22,0) -> 771 | AY23: 216362 | AZ23: =IF(AY23>=AY22,AY23-AY22,0) -> 74 | BA23: 18200596 | BB23: =IF(BA23>=BA22,BA23-BA22,0) -> 4491 | BC23: 515557 | BD23: =IF(BC23>=BC22,BC23-BC22,0) -> 174 | BE23: 11025 | BF23: =IF(BE23>=BE22,BE23-BE22,0) -> 50 | BG23: 22688850 | BH23: =IF(BG23>=BG22,BG23-BG22,0)-(0.45*BN23)-(0.45*BP23)-BR23 -> 5733.55 | BI23: =AP23+AR23+AT23+AV23+AX23+AZ23+BB23+BD23+BF23+BH23 -> 11870.637 | BJ23: =BI23+AN23 -> 22779.628 | BK23: 1392939 | BL23: =IF(BK23>=BK22,BK23-BK22,0) -> 2 | BM23: 3643129 | BN23: =IF(BM23>=BM22,BM23-BM22,0) -> 1318 | BO23: 387796 | BP23: =IF(BO23>=BO22,BO23-BO22,0) -> 103 | BQ23: 480260 | BR23: =IF(BQ23>=BQ22,BQ23-BQ22,0) -> 215 | BS23: =J23+Q23+AN23+BI23 -> 28657.628 | BT23: 177 | BU23: =IF(BS23>0,BS23/BT23,0) -> 161.9075 | BW23: =IF(BS23>0,BS23/BV23,0) -> #DIV/0! | BX23: =((BS23-Q23)*$BZ$1)+(Q23*$BR$1) -> 33226.272 | BY23: =IF(BX23>0,BX23/BT23,0) -> 187.71905 | BZ23: =IF(BX23>0,BX23/BV23,0) -> #DIV/0!
A24: 19 | C24: =IF(+B24-B23>0,B24-B23,(B24-B23)>0)*800 -> 0 | E24: =IF(+D24-D23>0,D24-D23,(D24-D23)>0)*80 -> 0 | G24: =IF(+F24-F23>0,F24-F23,(F24-F23)>0)*10 -> 0 | H24: 65 | I24: 22687088 | J24: =IF(I24>=I23,I24-I23,0) -> 5250 | K24: =M24+O24 -> 3177 | L24: 196152 | M24: =IF(L24>=L23,L24-L23,0) -> 1725 | N24: 210162 | O24: =IF(N24>=N23,N24-N23,0) -> 1452 | P24: 217409 | Q24: =IF(P24>=P23,P24-P23,0)*30 -> 510 | R24: 150818 | S24: =IF(R24>=R23,R24-R23,0) -> 138 | T24: 273865 | U24: =IF(T24>=T23,T24-T23,0) -> 268 | V24: 840598 | W24: =IF(V24>=V23,V24-V23,0)*0.53 -> 2734.27 | X24: 486185 | Y24: =IF(X24>=X23,X24-X23,0)*0.53 -> 2161.34 | Z24: 719624 | AA24: =IF(Z24>=Z23,Z24-Z23,0)*0.53 -> 0 | AB24: 333210 | AC24: =IF(AB24>=AB23,AB24-AB23,0)*0.53 -> 0 | AD24: 364893 | AE24: =IF(AD24>=AD23,AD24-AD23,0)*0.53 -> 0 | AF24: 775738 | AG24: =IF(AF24>=AF23,AF24-AF23,0)*0.53 -> 804.54 | AH24: 683520 | AI24: =IF(AH24>=AH23,AH24-AH23,0)*0.53 -> 900.47 | AJ24: 407980 | AK24: =IF(AJ24>=AJ23,AJ24-AJ23,0)*0.53 -> 3218.69 | AL24: 423979 | AM24: =IF(AL24>=AL23,AL24-AL23,0)*0.53 -> 162.71 | AN24: =W24+Y24+AA24+AC24+AE24+AG24+AI24+AK24+AM24 -> 9982.02 | AO24: 7351198 | AP24: =IF(AO24>=AO23,AO24-AO23,0)*0.1125 -> 183.7125 | AQ24: 616579 | AR24: =IF(AQ24>=AQ23,AQ24-AQ23,0) -> 323 | AS24: 930420 | AT24: =IF(AS24>=AS23,AS24-AS23,0) -> 151 | AU24: 799851 | AV24: =IF(AU24>=AU23,AU24-AU23,0) -> 36 | AW24: 2423002 | AX24: =IF(AW24>=AW23,AW24-AW23,0) -> 765 | AY24: 216412 | AZ24: =IF(AY24>=AY23,AY24-AY23,0) -> 50 | BA24: 18205149 | BB24: =IF(BA24>=BA23,BA24-BA23,0) -> 4553 | BC24: 515742 | BD24: =IF(BC24>=BC23,BC24-BC23,0) -> 185 | BE24: 11137 | BF24: =IF(BE24>=BE23,BE24-BE23,0) -> 112 | BG24: 22695180 | BH24: =IF(BG24>=BG23,BG24-BG23,0)-(0.45*BN24)-(0.45*BP24)-BR24 -> 5443.75 | BI24: =AP24+AR24+AT24+AV24+AX24+AZ24+BB24+BD24+BF24+BH24 -> 11802.462 | BJ24: =BI24+AN24 -> 21784.482 | BK24: 1392942 | BL24: =IF(BK24>=BK23,BK24-BK23,0) -> 3 | BM24: 3644534 | BN24: =IF(BM24>=BM23,BM24-BM23,0) -> 1405 | BO24: 387896 | BP24: =IF(BO24>=BO23,BO24-BO23,0) -> 100 | BQ24: 480469 | BR24: =IF(BQ24>=BQ23,BQ24-BQ23,0) -> 209 | BS24: =J24+Q24+AN24+BI24 -> 27544.482 | BT24: 163 | BU24: =IF(BS24>0,BS24/BT24,0) -> 168.98456 | BW24: =IF(BS24>0,BS24/BV24,0) -> #DIV/0! | BX24: =((BS24-Q24)*$BZ$1)+(Q24*$BR$1) -> 31905.655 | BY24: =IF(BX24>0,BX24/BT24,0) -> 195.74021 | BZ24: =IF(BX24>0,BX24/BV24,0) -> #DIV/0!
A25: 20 | C25: =IF(+B25-B24>0,B25-B24,(B25-B24)>0)*800 -> 0 | E25: =IF(+D25-D24>0,D25-D24,(D25-D24)>0)*80 -> 0 | G25: =IF(+F25-F24>0,F25-F24,(F25-F24)>0)*10 -> 0 | I25: 22692277 | J25: =IF(I25>=I24,I25-I24,0) -> 5189 | K25: =M25+O25 -> 3408 | L25: 197983 | M25: =IF(L25>=L24,L25-L24,0) -> 1831 | N25: 211739 | O25: =IF(N25>=N24,N25-N24,0) -> 1577 | P25: 217427 | Q25: =IF(P25>=P24,P25-P24,0)*30 -> 540 | R25: 150954 | S25: =IF(R25>=R24,R25-R24,0) -> 136 | T25: 274164 | U25: =IF(T25>=T24,T25-T24,0) -> 299 | V25: 845797 | W25: =IF(V25>=V24,V25-V24,0)*0.53 -> 2755.47 | X25: 490948 | Y25: =IF(X25>=X24,X25-X24,0)*0.53 -> 2524.39 | Z25: 719624 | AA25: =IF(Z25>=Z24,Z25-Z24,0)*0.53 -> 0 | AB25: 333210 | AC25: =IF(AB25>=AB24,AB25-AB24,0)*0.53 -> 0 | AD25: 364877 | AE25: =IF(AD25>=AD24,AD25-AD24,0)*0.53 -> 0 | AF25: 777582 | AG25: =IF(AF25>=AF24,AF25-AF24,0)*0.53 -> 977.32 | AH25: 685284 | AI25: =IF(AH25>=AH24,AH25-AH24,0)*0.53 -> 934.92 | AJ25: 414739 | AK25: =IF(AJ25>=AJ24,AJ25-AJ24,0)*0.53 -> 3582.27 | AL25: 424302 | AM25: =IF(AL25>=AL24,AL25-AL24,0)*0.53 -> 171.19 | AN25: =W25+Y25+AA25+AC25+AE25+AG25+AI25+AK25+AM25 -> 10945.56 | AO25: 7353052 | AP25: =IF(AO25>=AO24,AO25-AO24,0)*0.1125 -> 208.575 | AQ25: 616835 | AR25: =IF(AQ25>=AQ24,AQ25-AQ24,0) -> 256 | AS25: 930585 | AT25: =IF(AS25>=AS24,AS25-AS24,0) -> 165 | AU25: 799898 | AV25: =IF(AU25>=AU24,AU25-AU24,0) -> 47 | AW25: 2423843 | AX25: =IF(AW25>=AW24,AW25-AW24,0) -> 841 | AY25: 216487 | AZ25: =IF(AY25>=AY24,AY25-AY24,0) -> 75 | BA25: 18209824 | BB25: =IF(BA25>=BA24,BA25-BA24,0) -> 4675 | BC25: 515925 | BD25: =IF(BC25>=BC24,BC25-BC24,0) -> 183 | BE25: 11192 | BF25: =IF(BE25>=BE24,BE25-BE24,0) -> 55 | BG25: 22701520 | BH25: =IF(BG25>=BG24,BG25-BG24,0)-(0.45*BN25)-(0.45*BP25)-BR25 -> 5439 | BI25: =AP25+AR25+AT25+AV25+AX25+AZ25+BB25+BD25+BF25+BH25 -> 11944.575 | BJ25: =BI25+AN25 -> 22890.135 | BK25: 1392943 | BL25: =IF(BK25>=BK24,BK25-BK24,0) -> 1 | BM25: 3645965 | BN25: =IF(BM25>=BM24,BM25-BM24,0) -> 1431 | BO25: 388005 | BP25: =IF(BO25>=BO24,BO25-BO24,0) -> 109 | BQ25: 480677 | BR25: =IF(BQ25>=BQ24,BQ25-BQ24,0) -> 208 | BS25: =J25+Q25+AN25+BI25 -> 28619.135 | BT25: 165 | BU25: =IF(BS25>0,BS25/BT25,0) -> 173.4493 | BW25: =IF(BS25>0,BS25/BV25,0) -> #DIV/0! | BX25: =((BS25-Q25)*$BZ$1)+(Q25*$BR$1) -> 33155.005 | BY25: =IF(BX25>0,BX25/BT25,0) -> 200.93943 | BZ25: =IF(BX25>0,BX25/BV25,0) -> #DIV/0!
A26: 21 | C26: =IF(+B26-B25>0,B26-B25,(B26-B25)>0)*800 -> 0 | E26: =IF(+D26-D25>0,D26-D25,(D26-D25)>0)*80 -> 0 | G26: =IF(+F26-F25>0,F26-F25,(F26-F25)>0)*10 -> 0 | H26: 66 | I26: 22697763 | J26: =IF(I26>=I25,I26-I25,0) -> 5486 | K26: =M26+O26 -> 4033 | L26: 200145 | M26: =IF(L26>=L25,L26-L25,0) -> 2162 | N26: 213610 | O26: =IF(N26>=N25,N26-N25,0) -> 1871 | P26: 217446 | Q26: =IF(P26>=P25,P26-P25,0)*30 -> 570 | R26: 151115 | S26: =IF(R26>=R25,R26-R25,0) -> 161 | T26: 274455 | U26: =IF(T26>=T25,T26-T25,0) -> 291 | V26: 852415 | W26: =IF(V26>=V25,V26-V25,0)*0.53 -> 3507.54 | X26: 496856 | Y26: =IF(X26>=X25,X26-X25,0)*0.53 -> 3131.24 | Z26: 719624 | AA26: =IF(Z26>=Z25,Z26-Z25,0)*0.53 -> 0 | AB26: 333210 | AC26: =IF(AB26>=AB25,AB26-AB25,0)*0.53 -> 0 | AD26: 365976 | AE26: =IF(AD26>=AD25,AD26-AD25,0)*0.53 -> 582.47 | AF26: 779760 | AG26: =IF(AF26>=AF25,AF26-AF25,0)*0.53 -> 1154.34 | AH26: 687775 | AI26: =IF(AH26>=AH25,AH26-AH25,0)*0.53 -> 1320.23 | AJ26: 423308 | AK26: =IF(AJ26>=AJ25,AJ26-AJ25,0)*0.53 -> 4541.57 | AL26: 424696 | AM26: =IF(AL26>=AL25,AL26-AL25,0)*0.53 -> 208.82 | AN26: =W26+Y26+AA26+AC26+AE26+AG26+AI26+AK26+AM26 -> 14446.21 | AO26: 7355009 | AP26: =IF(AO26>=AO25,AO26-AO25,0)*0.1125 -> 220.1625 | AQ26: 617121 | AR26: =IF(AQ26>=AQ25,AQ26-AQ25,0) -> 286 | AS26: 930759 | AT26: =IF(AS26>=AS25,AS26-AS25,0) -> 174 | AU26: 799952 | AV26: =IF(AU26>=AU25,AU26-AU25,0) -> 54 | AW26: 2424902 | AX26: =IF(AW26>=AW25,AW26-AW25,0) -> 1059 | AY26: 216574 | AZ26: =IF(AY26>=AY25,AY26-AY25,0) -> 87 | BA26: 18214493 | BB26: =IF(BA26>=BA25,BA26-BA25,0) -> 4669 | BC26: 516105 | BD26: =IF(BC26>=BC25,BC26-BC25,0) -> 180 | BE26: 11354 | BF26: =IF(BE26>=BE25,BE26-BE25,0) -> 162 | BG26: 22708336 | BH26: =IF(BG26>=BG25,BG26-BG25,0)-(0.45*BN26)-(0.45*BP26)-BR26 -> 5901.3 | BI26: =AP26+AR26+AT26+AV26+AX26+AZ26+BB26+BD26+BF26+BH26 -> 12792.462 | BJ26: =BI26+AN26 -> 27238.673 | BK26: 1392972 | BL26: =IF(BK26>=BK25,BK26-BK25,0) -> 29 | BM26: 3647403 | BN26: =IF(BM26>=BM25,BM26-BM25,0) -> 1438 | BO26: 388113 | BP26: =IF(BO26>=BO25,BO26-BO25,0) -> 108 | BQ26: 480896 | BR26: =IF(BQ26>=BQ25,BQ26-BQ25,0) -> 219 | BS26: =J26+Q26+AN26+BI26 -> 33294.673 | BT26: 173 | BU26: =IF(BS26>0,BS26/BT26,0) -> 192.45475 | BW26: =IF(BS26>0,BS26/BV26,0) -> #DIV/0! | BX26: =((BS26-Q26)*$BZ$1)+(Q26*$BR$1) -> 38545.373 | BY26: =IF(BX26>0,BX26/BT26,0) -> 222.80563 | BZ26: =IF(BX26>0,BX26/BV26,0) -> #DIV/0!
A27: 22 | C27: =IF(+B27-B26>0,B27-B26,(B27-B26)>0)*800 -> 0 | E27: =IF(+D27-D26>0,D27-D26,(D27-D26)>0)*80 -> 0 | G27: =IF(+F27-F26>0,F27-F26,(F27-F26)>0)*10 -> 0 | I27: 22704245 | J27: =IF(I27>=I26,I27-I26,0) -> 6482 | K27: =M27+O27 -> 3258 | L27: 201871 | M27: =IF(L27>=L26,L27-L26,0) -> 1726 | N27: 215142 | O27: =IF(N27>=N26,N27-N26,0) -> 1532 | P27: 217463 | Q27: =IF(P27>=P26,P27-P26,0)*30 -> 510 | R27: 151265 | S27: =IF(R27>=R26,R27-R26,0) -> 150 | T27: 274751 | U27: =IF(T27>=T26,T27-T26,0) -> 296 | V27: 857578 | W27: =IF(V27>=V26,V27-V26,0)*0.53 -> 2736.39 | X27: 503060 | Y27: =IF(X27>=X26,X27-X26,0)*0.53 -> 3288.12 | Z27: 719624 | AA27: =IF(Z27>=Z26,Z27-Z26,0)*0.53 -> 0 | AB27: 333210 | AC27: =IF(AB27>=AB26,AB27-AB26,0)*0.53 -> 0 | AD27: 366001 | AE27: =IF(AD27>=AD26,AD27-AD26,0)*0.53 -> 13.25 | AF27: 783063 | AG27: =IF(AF27>=AF26,AF27-AF26,0)*0.53 -> 1750.59 | AH27: 689875 | AI27: =IF(AH27>=AH26,AH27-AH26,0)*0.53 -> 1113 | AJ27: 430213 | AK27: =IF(AJ27>=AJ26,AJ27-AJ26,0)*0.53 -> 3659.65 | AL27: 425013 | AM27: =IF(AL27>=AL26,AL27-AL26,0)*0.53 -> 168.01 | AN27: =W27+Y27+AA27+AC27+AE27+AG27+AI27+AK27+AM27 -> 12729.01 | AO27: 7356861 | AP27: =IF(AO27>=AO26,AO27-AO26,0)*0.1125 -> 208.35 | AQ27: 617399 | AR27: =IF(AQ27>=AQ26,AQ27-AQ26,0) -> 278 | AS27: 930927 | AT27: =IF(AS27>=AS26,AS27-AS26,0) -> 168 | AU27: 800010 | AV27: =IF(AU27>=AU26,AU27-AU26,0) -> 58 | AW27: 2425808 | AX27: =IF(AW27>=AW26,AW27-AW26,0) -> 906 | AY27: 216656 | AZ27: =IF(AY27>=AY26,AY27-AY26,0) -> 82 | BA27: 18219394 | BB27: =IF(BA27>=BA26,BA27-BA26,0) -> 4901 | BC27: 516338 | BD27: =IF(BC27>=BC26,BC27-BC26,0) -> 233 | BE27: 11505 | BF27: =IF(BE27>=BE26,BE27-BE26,0) -> 151 | BG27: 22715898 | BH27: =IF(BG27>=BG26,BG27-BG26,0)-(0.45*BN27)-(0.45*BP27)-BR27 -> 6576.5 | BI27: =AP27+AR27+AT27+AV27+AX27+AZ27+BB27+BD27+BF27+BH27 -> 13561.85 | BJ27: =BI27+AN27 -> 26290.86 | BK27: 1393004 | BL27: =IF(BK27>=BK26,BK27-BK26,0) -> 32 | BM27: 3648915 | BN27: =IF(BM27>=BM26,BM27-BM26,0) -> 1512 | BO27: 388231 | BP27: =IF(BO27>=BO26,BO27-BO26,0) -> 118 | BQ27: 481148 | BR27: =IF(BQ27>=BQ26,BQ27-BQ26,0) -> 252 | BS27: =J27+Q27+AN27+BI27 -> 33282.86 | BT27: 187 | BU27: =IF(BS27>0,BS27/BT27,0) -> 177.98321 | BW27: =IF(BS27>0,BS27/BV27,0) -> #DIV/0! | BX27: =((BS27-Q27)*$BZ$1)+(Q27*$BR$1) -> 38504.789 | BY27: =IF(BX27>0,BX27/BT27,0) -> 205.90796 | BZ27: =IF(BX27>0,BX27/BV27,0) -> #DIV/0!
A28: 23 | C28: =IF(+B28-B27>0,B28-B27,(B28-B27)>0)*800 -> 0 | E28: =IF(+D28-D27>0,D28-D27,(D28-D27)>0)*80 -> 0 | G28: =IF(+F28-F27>0,F28-F27,(F28-F27)>0)*10 -> 0 | H28: 67 | I28: 22708262 | J28: =IF(I28>=I27,I28-I27,0) -> 4017 | K28: =M28+O28 -> 3252 | L28: 203592 | M28: =IF(L28>=L27,L28-L27,0) -> 1721 | N28: 216673 | O28: =IF(N28>=N27,N28-N27,0) -> 1531 | P28: 217480 | Q28: =IF(P28>=P27,P28-P27,0)*30 -> 510 | R28: 151371 | S28: =IF(R28>=R27,R28-R27,0) -> 106 | T28: 274958 | U28: =IF(T28>=T27,T28-T27,0) -> 207 | V28: 862785 | W28: =IF(V28>=V27,V28-V27,0)*0.53 -> 2759.71 | X28: 510105 | Y28: =IF(X28>=X27,X28-X27,0)*0.53 -> 3733.85 | Z28: 719624 | AA28: =IF(Z28>=Z27,Z28-Z27,0)*0.53 -> 0 | AB28: 333210 | AC28: =IF(AB28>=AB27,AB28-AB27,0)*0.53 -> 0 | AD28: 366022 | AE28: =IF(AD28>=AD27,AD28-AD27,0)*0.53 -> 11.13 | AF28: 786196 | AG28: =IF(AF28>=AF27,AF28-AF27,0)*0.53 -> 1660.49 | AH28: 692111 | AI28: =IF(AH28>=AH27,AH28-AH27,0)*0.53 -> 1185.08 | AJ28: 437697 | AK28: =IF(AJ28>=AJ27,AJ28-AJ27,0)*0.53 -> 3966.52 | AL28: 425331 | AM28: =IF(AL28>=AL27,AL28-AL27,0)*0.53 -> 168.54 | AN28: =W28+Y28+AA28+AC28+AE28+AG28+AI28+AK28+AM28 -> 13485.32 | AO28: 7358540 | AP28: =IF(AO28>=AO27,AO28-AO27,0)*0.1125 -> 188.8875 | AQ28: 617602 | AR28: =IF(AQ28>=AQ27,AQ28-AQ27,0) -> 203 | AS28: 931072 | AT28: =IF(AS28>=AS27,AS28-AS27,0) -> 145 | AU28: 800057 | AV28: =IF(AU28>=AU27,AU28-AU27,0) -> 47 | AW28: 2426726 | AX28: =IF(AW28>=AW27,AW28-AW27,0) -> 918 | AY28: 216714 | AZ28: =IF(AY28>=AY27,AY28-AY27,0) -> 58 | BA28: 18223513 | BB28: =IF(BA28>=BA27,BA28-BA27,0) -> 4119 | BC28: 516484 | BD28: =IF(BC28>=BC27,BC28-BC27,0) -> 146 | BE28: 11613 | BF28: =IF(BE28>=BE27,BE28-BE27,0) -> 108 | BG28: 22721428 | BH28: =IF(BG28>=BG27,BG28-BG27,0)-(0.45*BN28)-(0.45*BP28)-BR28 -> 5143.1 | BI28: =AP28+AR28+AT28+AV28+AX28+AZ28+BB28+BD28+BF28+BH28 -> 11075.987 | BJ28: =BI28+AN28 -> 24561.308 | BK28: 1393051 | BL28: =IF(BK28>=BK27,BK28-BK27,0) -> 47 | BM28: 3649534 | BN28: =IF(BM28>=BM27,BM28-BM27,0) -> 619 | BO28: 388274 | BP28: =IF(BO28>=BO27,BO28-BO27,0) -> 43 | BQ28: 481237 | BR28: =IF(BQ28>=BQ27,BQ28-BQ27,0) -> 89 | BS28: =J28+Q28+AN28+BI28 -> 29088.307 | BT28: 194 | BU28: =IF(BS28>0,BS28/BT28,0) -> 149.93973 | BW28: =IF(BS28>0,BS28/BV28,0) -> #DIV/0! | BX28: =((BS28-Q28)*$BZ$1)+(Q28*$BR$1) -> 33681.054 | BY28: =IF(BX28>0,BX28/BT28,0) -> 173.61368 | BZ28: =IF(BX28>0,BX28/BV28,0) -> #DIV/0!
A29: 24 | C29: =IF(+B29-B28>0,B29-B28,(B29-B28)>0)*800 -> 0 | E29: =IF(+D29-D28>0,D29-D28,(D29-D28)>0)*80 -> 0 | G29: =IF(+F29-F28>0,F29-F28,(F29-F28)>0)*10 -> 0 | I29: 22714457 | J29: =IF(I29>=I28,I29-I28,0) -> 6195 | K29: =M29+O29 -> 2695 | L29: 205003 | M29: =IF(L29>=L28,L29-L28,0) -> 1411 | N29: 217957 | O29: =IF(N29>=N28,N29-N28,0) -> 1284 | P29: 217498 | Q29: =IF(P29>=P28,P29-P28,0)*30 -> 540 | R29: 151508 | S29: =IF(R29>=R28,R29-R28,0) -> 137 | T29: 275233 | U29: =IF(T29>=T28,T29-T28,0) -> 275 | V29: 867561 | W29: =IF(V29>=V28,V29-V28,0)*0.53 -> 2531.28 | X29: 515977 | Y29: =IF(X29>=X28,X29-X28,0)*0.53 -> 3112.16 | Z29: 719624 | AA29: =IF(Z29>=Z28,Z29-Z28,0)*0.53 -> 0 | AB29: 333210 | AC29: =IF(AB29>=AB28,AB29-AB28,0)*0.53 -> 0 | AD29: 367051 | AE29: =IF(AD29>=AD28,AD29-AD28,0)*0.53 -> 545.37 | AF29: 787825 | AG29: =IF(AF29>=AF28,AF29-AF28,0)*0.53 -> 863.37 | AH29: 693868 | AI29: =IF(AH29>=AH28,AH29-AH28,0)*0.53 -> 931.21 | AJ29: 443718 | AK29: =IF(AJ29>=AJ28,AJ29-AJ28,0)*0.53 -> 3191.13 | AL29: 425588 | AM29: =IF(AL29>=AL28,AL29-AL28,0)*0.53 -> 136.21 | AN29: =W29+Y29+AA29+AC29+AE29+AG29+AI29+AK29+AM29 -> 11310.73 | AO29: 7360260 | AP29: =IF(AO29>=AO28,AO29-AO28,0)*0.1125 -> 193.5 | AQ29: 617847 | AR29: =IF(AQ29>=AQ28,AQ29-AQ28,0) -> 245 | AS29: 931233 | AT29: =IF(AS29>=AS28,AS29-AS28,0) -> 161 | AU29: 800106 | AV29: =IF(AU29>=AU28,AU29-AU28,0) -> 49 | AW29: 2427487 | AX29: =IF(AW29>=AW28,AW29-AW28,0) -> 761 | AY29: 216791 | AZ29: =IF(AY29>=AY28,AY29-AY28,0) -> 77 | BA29: 18228641 | BB29: =IF(BA29>=BA28,BA29-BA28,0) -> 5128 | BC29: 516662 | BD29: =IF(BC29>=BC28,BC29-BC28,0) -> 178 | BE29: 11703 | BF29: =IF(BE29>=BE28,BE29-BE28,0) -> 90 | BG29: 22728014 | BH29: =IF(BG29>=BG28,BG29-BG28,0)-(0.45*BN29)-(0.45*BP29)-BR29 -> 5706.85 | BI29: =AP29+AR29+AT29+AV29+AX29+AZ29+BB29+BD29+BF29+BH29 -> 12589.35 | BJ29: =BI29+AN29 -> 23900.08 | BK29: 1393109 | BL29: =IF(BK29>=BK28,BK29-BK28,0) -> 58 | BM29: 3650938 | BN29: =IF(BM29>=BM28,BM29-BM28,0) -> 1404 | BO29: 388377 | BP29: =IF(BO29>=BO28,BO29-BO28,0) -> 103 | BQ29: 481438 | BR29: =IF(BQ29>=BQ28,BQ29-BQ28,0) -> 201 | BS29: =J29+Q29+AN29+BI29 -> 30635.08 | BT29: 191 | BU29: =IF(BS29>0,BS29/BT29,0) -> 160.39309 | BW29: =IF(BS29>0,BS29/BV29,0) -> #DIV/0! | BX29: =((BS29-Q29)*$BZ$1)+(Q29*$BR$1) -> 35473.342 | BY29: =IF(BX29>0,BX29/BT29,0) -> 185.7243 | BZ29: =IF(BX29>0,BX29/BV29,0) -> #DIV/0!
A30: 25 | C30: =IF(+B30-B29>0,B30-B29,(B30-B29)>0)*800 -> 0 | E30: =IF(+D30-D29>0,D30-D29,(D30-D29)>0)*80 -> 0 | G30: =IF(+F30-F29>0,F30-F29,(F30-F29)>0)*10 -> 0 | H30: 68 | I30: 22719440 | J30: =IF(I30>=I29,I30-I29,0) -> 4983 | K30: =M30+O30 -> 3182 | L30: 206724 | M30: =IF(L30>=L29,L30-L29,0) -> 1721 | N30: 219418 | O30: =IF(N30>=N29,N30-N29,0) -> 1461 | P30: 217520 | Q30: =IF(P30>=P29,P30-P29,0)*30 -> 660 | R30: 151646 | S30: =IF(R30>=R29,R30-R29,0) -> 138 | T30: 275504 | U30: =IF(T30>=T29,T30-T29,0) -> 271 | V30: 872697 | W30: =IF(V30>=V29,V30-V29,0)*0.53 -> 2722.08 | X30: 523278 | Y30: =IF(X30>=X29,X30-X29,0)*0.53 -> 3869.53 | Z30: 719624 | AA30: =IF(Z30>=Z29,Z30-Z29,0)*0.53 -> 0 | AB30: 333210 | AC30: =IF(AB30>=AB29,AB30-AB29,0)*0.53 -> 0 | AD30: 367073 | AE30: =IF(AD30>=AD29,AD30-AD29,0)*0.53 -> 11.66 | AF30: 790664 | AG30: =IF(AF30>=AF29,AF30-AF29,0)*0.53 -> 1504.67 | AH30: 696034 | AI30: =IF(AH30>=AH29,AH30-AH29,0)*0.53 -> 1147.98 | AJ30: 450669 | AK30: =IF(AJ30>=AJ29,AJ30-AJ29,0)*0.53 -> 3684.03 | AL30: 425899 | AM30: =IF(AL30>=AL29,AL30-AL29,0)*0.53 -> 164.83 | AN30: =W30+Y30+AA30+AC30+AE30+AG30+AI30+AK30+AM30 -> 13104.78 | AO30: 7361910 | AP30: =IF(AO30>=AO29,AO30-AO29,0)*0.1125 -> 185.625 | AQ30: 618161 | AR30: =IF(AQ30>=AQ29,AQ30-AQ29,0) -> 314 | AS30: 931390 | AT30: =IF(AS30>=AS29,AS30-AS29,0) -> 157 | AU30: 800139 | AV30: =IF(AU30>=AU29,AU30-AU29,0) -> 33 | AW30: 2428369 | AX30: =IF(AW30>=AW29,AW30-AW29,0) -> 882 | AY30: 216867 | AZ30: =IF(AY30>=AY29,AY30-AY29,0) -> 76 | BA30: 18233097 | BB30: =IF(BA30>=BA29,BA30-BA29,0) -> 4456 | BC30: 516851 | BD30: =IF(BC30>=BC29,BC30-BC29,0) -> 189 | BE30: 11810 | BF30: =IF(BE30>=BE29,BE30-BE29,0) -> 107 | BG30: 22734600 | BH30: =IF(BG30>=BG29,BG30-BG29,0)-(0.45*BN30)-(0.45*BP30)-BR30 -> 5710.25 | BI30: =AP30+AR30+AT30+AV30+AX30+AZ30+BB30+BD30+BF30+BH30 -> 12109.875 | BJ30: =BI30+AN30 -> 25214.655 | BK30: 1393168 | BL30: =IF(BK30>=BK29,BK30-BK29,0) -> 59 | BM30: 3652334 | BN30: =IF(BM30>=BM29,BM30-BM29,0) -> 1396 | BO30: 388476 | BP30: =IF(BO30>=BO29,BO30-BO29,0) -> 99 | BQ30: 481641 | BR30: =IF(BQ30>=BQ29,BQ30-BQ29,0) -> 203 | BS30: =J30+Q30+AN30+BI30 -> 30857.655 | BT30: 194 | BU30: =IF(BS30>0,BS30/BT30,0) -> 159.06008 | BW30: =IF(BS30>0,BS30/BV30,0) -> #DIV/0! | BX30: =((BS30-Q30)*$BZ$1)+(Q30*$BR$1) -> 35783.303 | BY30: =IF(BX30>0,BX30/BT30,0) -> 184.45002 | BZ30: =IF(BX30>0,BX30/BV30,0) -> #DIV/0!
A31: 26 | C31: =IF(+B31-B30>0,B31-B30,(B31-B30)>0)*800 -> 0 | E31: =IF(+D31-D30>0,D31-D30,(D31-D30)>0)*80 -> 0 | G31: =IF(+F31-F30>0,F31-F30,(F31-F30)>0)*10 -> 0 | I31: 22724578 | J31: =IF(I31>=I30,I31-I30,0) -> 5138 | K31: =M31+O31 -> 3989 | L31: 208930 | M31: =IF(L31>=L30,L31-L30,0) -> 2206 | N31: 221201 | O31: =IF(N31>=N30,N31-N30,0) -> 1783 | P31: 217542 | Q31: =IF(P31>=P30,P31-P30,0)*30 -> 660 | R31: 151796 | S31: =IF(R31>=R30,R31-R30,0) -> 150 | T31: 275795 | U31: =IF(T31>=T30,T31-T30,0) -> 291 | V31: 879232 | W31: =IF(V31>=V30,V31-V30,0)*0.53 -> 3463.55 | X31: 530788 | Y31: =IF(X31>=X30,X31-X30,0)*0.53 -> 3980.3 | Z31: 719624 | AA31: =IF(Z31>=Z30,Z31-Z30,0)*0.53 -> 0 | AB31: 333210 | AC31: =IF(AB31>=AB30,AB31-AB30,0)*0.53 -> 0 | AD31: 367096 | AE31: =IF(AD31>=AD30,AD31-AD30,0)*0.53 -> 12.19 | AF31: 793829 | AG31: =IF(AF31>=AF30,AF31-AF30,0)*0.53 -> 1677.45 | AH31: 698882 | AI31: =IF(AH31>=AH30,AH31-AH30,0)*0.53 -> 1509.44 | AJ31: 460054 | AK31: =IF(AJ31>=AJ30,AJ31-AJ30,0)*0.53 -> 4974.05 | AL31: 426303 | AM31: =IF(AL31>=AL30,AL31-AL30,0)*0.53 -> 214.12 | AN31: =W31+Y31+AA31+AC31+AE31+AG31+AI31+AK31+AM31 -> 15831.1 | AO31: 7363653 | AP31: =IF(AO31>=AO30,AO31-AO30,0)*0.1125 -> 196.0875 | AQ31: 618342 | AR31: =IF(AQ31>=AQ30,AQ31-AQ30,0) -> 181 | AS31: 931542 | AT31: =IF(AS31>=AS30,AS31-AS30,0) -> 152 | AU31: 800180 | AV31: =IF(AU31>=AU30,AU31-AU30,0) -> 41 | AW31: 2429469 | AX31: =IF(AW31>=AW30,AW31-AW30,0) -> 1100 | AY31: 216950 | AZ31: =IF(AY31>=AY30,AY31-AY30,0) -> 83 | BA31: 18237563 | BB31: =IF(BA31>=BA30,BA31-BA30,0) -> 4466 | BC31: 517034 | BD31: =IF(BC31>=BC30,BC31-BC30,0) -> 183 | BE31: 11902 | BF31: =IF(BE31>=BE30,BE31-BE30,0) -> 92 | BG31: 22741331 | BH31: =IF(BG31>=BG30,BG31-BG30,0)-(0.45*BN31)-(0.45*BP31)-BR31 -> 5842.9 | BI31: =AP31+AR31+AT31+AV31+AX31+AZ31+BB31+BD31+BF31+BH31 -> 12336.987 | BJ31: =BI31+AN31 -> 28168.088 | BK31: 1393227 | BL31: =IF(BK31>=BK30,BK31-BK30,0) -> 59 | BM31: 3653752 | BN31: =IF(BM31>=BM30,BM31-BM30,0) -> 1418 | BO31: 388576 | BP31: =IF(BO31>=BO30,BO31-BO30,0) -> 100 | BQ31: 481846 | BR31: =IF(BQ31>=BQ30,BQ31-BQ30,0) -> 205 | BS31: =J31+Q31+AN31+BI31 -> 33966.087 | BT31: 191 | BU31: =IF(BS31>0,BS31/BT31,0) -> 177.83292 | BW31: =IF(BS31>0,BS31/BV31,0) -> #DIV/0! | BX31: =((BS31-Q31)*$BZ$1)+(Q31*$BR$1) -> 39358.001 | BY31: =IF(BX31>0,BX31/BT31,0) -> 206.06283 | BZ31: =IF(BX31>0,BX31/BV31,0) -> #DIV/0!
A32: 27 | C32: =IF(+B32-B31>0,B32-B31,(B32-B31)>0)*800 -> 0 | E32: =IF(+D32-D31>0,D32-D31,(D32-D31)>0)*80 -> 0 | G32: =IF(+F32-F31>0,F32-F31,(F32-F31)>0)*10 -> 0 | H32: 69 | I32: 22730323 | J32: =IF(I32>=I31,I32-I31,0) -> 5745 | K32: =M32+O32 -> 3153 | L32: 210604 | M32: =IF(L32>=L31,L32-L31,0) -> 1674 | N32: 222680 | O32: =IF(N32>=N31,N32-N31,0) -> 1479 | P32: 217561 | Q32: =IF(P32>=P31,P32-P31,0)*30 -> 570 | R32: 151928 | S32: =IF(R32>=R31,R32-R31,0) -> 132 | T32: 276090 | U32: =IF(T32>=T31,T32-T31,0) -> 295 | V32: 884443 | W32: =IF(V32>=V31,V32-V31,0)*0.53 -> 2761.83 | X32: 537819 | Y32: =IF(X32>=X31,X32-X31,0)*0.53 -> 3726.43 | Z32: 720392 | AA32: =IF(Z32>=Z31,Z32-Z31,0)*0.53 -> 407.04 | AB32: 333248 | AC32: =IF(AB32>=AB31,AB32-AB31,0)*0.53 -> 20.14 | AD32: 367761 | AE32: =IF(AD32>=AD31,AD32-AD31,0)*0.53 -> 352.45 | AF32: 797032 | AG32: =IF(AF32>=AF31,AF32-AF31,0)*0.53 -> 1697.59 | AH32: 700947 | AI32: =IF(AH32>=AH31,AH32-AH31,0)*0.53 -> 1094.45 | AJ32: 467574 | AK32: =IF(AJ32>=AJ31,AJ32-AJ31,0)*0.53 -> 3985.6 | AL32: 426601 | AM32: =IF(AL32>=AL31,AL32-AL31,0)*0.53 -> 157.94 | AN32: =W32+Y32+AA32+AC32+AE32+AG32+AI32+AK32+AM32 -> 14203.47 | AO32: 7365427 | AP32: =IF(AO32>=AO31,AO32-AO31,0)*0.1125 -> 199.575 | AQ32: 618606 | AR32: =IF(AQ32>=AQ31,AQ32-AQ31,0) -> 264 | AS32: 931715 | AT32: =IF(AS32>=AS31,AS32-AS31,0) -> 173 | AU32: 800237 | AV32: =IF(AU32>=AU31,AU32-AU31,0) -> 57 | AW32: 2430277 | AX32: =IF(AW32>=AW31,AW32-AW31,0) -> 808 | AY32: 217023 | AZ32: =IF(AY32>=AY31,AY32-AY31,0) -> 73 | BA32: 18242942 | BB32: =IF(BA32>=BA31,BA32-BA31,0) -> 5379 | BC32: 517231 | BD32: =IF(BC32>=BC31,BC32-BC31,0) -> 197 | BE32: 11997 | BF32: =IF(BE32>=BE31,BE32-BE31,0) -> 95 | BG32: 22748399 | BH32: =IF(BG32>=BG31,BG32-BG31,0)-(0.45*BN32)-(0.45*BP32)-BR32 -> 6144.45 | BI32: =AP32+AR32+AT32+AV32+AX32+AZ32+BB32+BD32+BF32+BH32 -> 13390.025 | BJ32: =BI32+AN32 -> 27593.495 | BK32: 1393233 | BL32: =IF(BK32>=BK31,BK32-BK31,0) -> 6 | BM32: 3655207 | BN32: =IF(BM32>=BM31,BM32-BM31,0) -> 1455 | BO32: 388680 | BP32: =IF(BO32>=BO31,BO32-BO31,0) -> 104 | BQ32: 482068 | BR32: =IF(BQ32>=BQ31,BQ32-BQ31,0) -> 222 | BS32: =J32+Q32+AN32+BI32 -> 33908.495 | BT32: 191 | BU32: =IF(BS32>0,BS32/BT32,0) -> 177.53139 | BW32: =IF(BS32>0,BS32/BV32,0) -> #DIV/0! | BX32: =((BS32-Q32)*$BZ$1)+(Q32*$BR$1) -> 39251.269 | BY32: =IF(BX32>0,BX32/BT32,0) -> 205.50403 | BZ32: =IF(BX32>0,BX32/BV32,0) -> #DIV/0!
A33: 28 | C33: =IF(+B33-B32>0,B33-B32,(B33-B32)>0)*800 -> 0 | E33: =IF(+D33-D32>0,D33-D32,(D33-D32)>0)*80 -> 0 | G33: =IF(+F33-F32>0,F33-F32,(F33-F32)>0)*10 -> 0 | I33: 22736722 | J33: =IF(I33>=I32,I33-I32,0) -> 6399 | K33: =M33+O33 -> 3598 | L33: 212508 | M33: =IF(L33>=L32,L33-L32,0) -> 1904 | N33: 224374 | O33: =IF(N33>=N32,N33-N32,0) -> 1694 | P33: 217579 | Q33: =IF(P33>=P32,P33-P32,0)*30 -> 540 | R33: 152090 | S33: =IF(R33>=R32,R33-R32,0) -> 162 | T33: 276382 | U33: =IF(T33>=T32,T33-T32,0) -> 292 | V33: 890893 | W33: =IF(V33>=V32,V33-V32,0)*0.53 -> 3418.5 | X33: 541963 | Y33: =IF(X33>=X32,X33-X32,0)*0.53 -> 2196.32 | Z33: 726454 | AA33: =IF(Z33>=Z32,Z33-Z32,0)*0.53 -> 3212.86 | AB33: 333301 | AC33: =IF(AB33>=AB32,AB33-AB32,0)*0.53 -> 28.09 | AD33: 369562 | AE33: =IF(AD33>=AD32,AD33-AD32,0)*0.53 -> 954.53 | AF33: 799252 | AG33: =IF(AF33>=AF32,AF33-AF32,0)*0.53 -> 1176.6 | AH33: 703319 | AI33: =IF(AH33>=AH32,AH33-AH32,0)*0.53 -> 1257.16 | AJ33: 476624 | AK33: =IF(AJ33>=AJ32,AJ33-AJ32,0)*0.53 -> 4796.5 | AL33: 426946 | AM33: =IF(AL33>=AL32,AL33-AL32,0)*0.53 -> 182.85 | AN33: =W33+Y33+AA33+AC33+AE33+AG33+AI33+AK33+AM33 -> 17223.41 | AO33: 7367241 | AP33: =IF(AO33>=AO32,AO33-AO32,0)*0.1125 -> 204.075 | AQ33: 618896 | AR33: =IF(AQ33>=AQ32,AQ33-AQ32,0) -> 290 | AS33: 931879 | AT33: =IF(AS33>=AS32,AS33-AS32,0) -> 164 | AU33: 800306 | AV33: =IF(AU33>=AU32,AU33-AU32,0) -> 69 | AW33: 2431207 | AX33: =IF(AW33>=AW32,AW33-AW32,0) -> 930 | AY33: 217082 | AZ33: =IF(AY33>=AY32,AY33-AY32,0) -> 59 | BA33: 18247560 | BB33: =IF(BA33>=BA32,BA33-BA32,0) -> 4618 | BC33: 517446 | BD33: =IF(BC33>=BC32,BC33-BC32,0) -> 215 | BE33: 12025 | BF33: =IF(BE33>=BE32,BE33-BE32,0) -> 28 | BG33: 22756055 | BH33: =IF(BG33>=BG32,BG33-BG32,0)-(0.45*BN33)-(0.45*BP33)-BR33 -> 6651.1 | BI33: =AP33+AR33+AT33+AV33+AX33+AZ33+BB33+BD33+BF33+BH33 -> 13228.175 | BJ33: =BI33+AN33 -> 30451.585 | BK33: 1393301 | BL33: =IF(BK33>=BK32,BK33-BK32,0) -> 68 | BM33: 3656796 | BN33: =IF(BM33>=BM32,BM33-BM32,0) -> 1589 | BO33: 388793 | BP33: =IF(BO33>=BO32,BO33-BO32,0) -> 113 | BQ33: 482307 | BR33: =IF(BQ33>=BQ32,BQ33-BQ32,0) -> 239 | BS33: =J33+Q33+AN33+BI33 -> 37390.585 | BT33: 176 | BU33: =IF(BS33>0,BS33/BT33,0) -> 212.44651 | BW33: =IF(BS33>0,BS33/BV33,0) -> #DIV/0! | BX33: =((BS33-Q33)*$BZ$1)+(Q33*$BR$1) -> 43242.173 | BY33: =IF(BX33>0,BX33/BT33,0) -> 245.69416 | BZ33: =IF(BX33>0,BX33/BV33,0) -> #DIV/0!
A34: 29 | C34: =IF(+B34-B33>0,B34-B33,(B34-B33)>0)*800 -> 0 | E34: =IF(+D34-D33>0,D34-D33,(D34-D33)>0)*80 -> 0 | G34: =IF(+F34-F33>0,F34-F33,(F34-F33)>0)*10 -> 0 | I34: 22740953 | J34: =IF(I34>=I33,I34-I33,0) -> 4231 | K34: =M34+O34 -> 3411 | L34: 214335 | M34: =IF(L34>=L33,L34-L33,0) -> 1827 | N34: 225958 | O34: =IF(N34>=N33,N34-N33,0) -> 1584 | P34: 217600 | Q34: =IF(P34>=P33,P34-P33,0)*30 -> 630 | R34: 152231 | S34: =IF(R34>=R33,R34-R33,0) -> 141 | T34: 276659 | U34: =IF(T34>=T33,T34-T33,0) -> 277 | V34: 897545 | W34: =IF(V34>=V33,V34-V33,0)*0.53 -> 3525.56 | X34: 544245 | Y34: =IF(X34>=X33,X34-X33,0)*0.53 -> 1209.46 | Z34: 733869 | AA34: =IF(Z34>=Z33,Z34-Z33,0)*0.53 -> 3929.95 | AB34: 333388 | AC34: =IF(AB34>=AB33,AB34-AB33,0)*0.53 -> 46.11 | AD34: 372732 | AE34: =IF(AD34>=AD33,AD34-AD33,0)*0.53 -> 1680.1 | AF34: 799601 | AG34: =IF(AF34>=AF33,AF34-AF33,0)*0.53 -> 184.97 | AH34: 705589 | AI34: =IF(AH34>=AH33,AH34-AH33,0)*0.53 -> 1203.1 | AJ34: 484943 | AK34: =IF(AJ34>=AJ33,AJ34-AJ33,0)*0.53 -> 4409.07 | AL34: 427268 | AM34: =IF(AL34>=AL33,AL34-AL33,0)*0.53 -> 170.66 | AN34: =W34+Y34+AA34+AC34+AE34+AG34+AI34+AK34+AM34 -> 16358.98 | AO34: 7368920 | AP34: =IF(AO34>=AO33,AO34-AO33,0)*0.1125 -> 188.8875 | AQ34: 619138 | AR34: =IF(AQ34>=AQ33,AQ34-AQ33,0) -> 242 | AS34: 932042 | AT34: =IF(AS34>=AS33,AS34-AS33,0) -> 163 | AU34: 800366 | AV34: =IF(AU34>=AU33,AU34-AU33,0) -> 60 | AW34: 2432136 | AX34: =IF(AW34>=AW33,AW34-AW33,0) -> 929 | AY34: 217100 | AZ34: =IF(AY34>=AY33,AY34-AY33,0) -> 18 | BA34: 18253134 | BB34: =IF(BA34>=BA33,BA34-BA33,0) -> 5574 | BC34: 517636 | BD34: =IF(BC34>=BC33,BC34-BC33,0) -> 190 | BE34: 12136 | BF34: =IF(BE34>=BE33,BE34-BE33,0) -> 111 | BG34: 22762869 | BH34: =IF(BG34>=BG33,BG34-BG33,0)-(0.45*BN34)-(0.45*BP34)-BR34 -> 5867.1 | BI34: =AP34+AR34+AT34+AV34+AX34+AZ34+BB34+BD34+BF34+BH34 -> 13342.987 | BJ34: =BI34+AN34 -> 29701.968 | BK34: 1393360 | BL34: =IF(BK34>=BK33,BK34-BK33,0) -> 59 | BM34: 3658346 | BN34: =IF(BM34>=BM33,BM34-BM33,0) -> 1550 | BO34: 388885 | BP34: =IF(BO34>=BO33,BO34-BO33,0) -> 92 | BQ34: 482515 | BR34: =IF(BQ34>=BQ33,BQ34-BQ33,0) -> 208 | BS34: =J34+Q34+AN34+BI34 -> 34562.967 | BT34: 175 | BU34: =IF(BS34>0,BS34/BT34,0) -> 197.50267 | BW34: =IF(BS34>0,BS34/BV34,0) -> #DIV/0! | BX34: =((BS34-Q34)*$BZ$1)+(Q34*$BR$1) -> 40030.913 | BY34: =IF(BX34>0,BX34/BT34,0) -> 228.74807 | BZ34: =IF(BX34>0,BX34/BV34,0) -> #DIV/0!
A35: 30 | C35: =IF(+B35-B34>0,B35-B34,(B35-B34)>0)*800 -> 0 | E35: =IF(+D35-D34>0,D35-D34,(D35-D34)>0)*80 -> 0 | G35: =IF(+F35-F34>0,F35-F34,(F35-F34)>0)*10 -> 0 | I35: 22746674 | J35: =IF(I35>=I34,I35-I34,0) -> 5721 | K35: =M35+O35 -> 3425 | L35: 216116 | M35: =IF(L35>=L34,L35-L34,0) -> 1781 | N35: 227602 | O35: =IF(N35>=N34,N35-N34,0) -> 1644 | P35: 217618 | Q35: =IF(P35>=P34,P35-P34,0)*30 -> 540 | R35: 152378 | S35: =IF(R35>=R34,R35-R34,0) -> 147 | T35: 276952 | U35: =IF(T35>=T34,T35-T34,0) -> 293 | V35: 904062 | W35: =IF(V35>=V34,V35-V34,0)*0.53 -> 3454.01 | X35: 547768 | Y35: =IF(X35>=X34,X35-X34,0)*0.53 -> 1867.19 | Z35: 740382 | AA35: =IF(Z35>=Z34,Z35-Z34,0)*0.53 -> 3451.89 | AB35: 333452 | AC35: =IF(AB35>=AB34,AB35-AB34,0)*0.53 -> 33.92 | AD35: 374989 | AE35: =IF(AD35>=AD34,AD35-AD34,0)*0.53 -> 1196.21 | AF35: 802312 | AG35: =IF(AF35>=AF34,AF35-AF34,0)*0.53 -> 1436.83 | AH35: 708025 | AI35: =IF(AH35>=AH34,AH35-AH34,0)*0.53 -> 1291.08 | AJ35: 493081 | AK35: =IF(AJ35>=AJ34,AJ35-AJ34,0)*0.53 -> 4313.14 | AL35: 427617 | AM35: =IF(AL35>=AL34,AL35-AL34,0)*0.53 -> 184.97 | AN35: =W35+Y35+AA35+AC35+AE35+AG35+AI35+AK35+AM35 -> 17229.24 | AO35: 7370675 | AP35: =IF(AO35>=AO34,AO35-AO34,0)*0.1125 -> 197.4375 | AQ35: 619381 | AR35: =IF(AQ35>=AQ34,AQ35-AQ34,0) -> 243 | AS35: 932202 | AT35: =IF(AS35>=AS34,AS35-AS34,0) -> 160 | AU35: 800419 | AV35: =IF(AU35>=AU34,AU35-AU34,0) -> 53 | AW35: 2433073 | AX35: =IF(AW35>=AW34,AW35-AW34,0) -> 937 | AY35: 217166 | AZ35: =IF(AY35>=AY34,AY35-AY34,0) -> 66 | BA35: 18257880 | BB35: =IF(BA35>=BA34,BA35-BA34,0) -> 4746 | BC35: 517828 | BD35: =IF(BC35>=BC34,BC35-BC34,0) -> 192 | BE35: 12219 | BF35: =IF(BE35>=BE34,BE35-BE34,0) -> 83 | BG35: 22769782 | BH35: =IF(BG35>=BG34,BG35-BG34,0)-(0.45*BN35)-(0.45*BP35)-BR35 -> 5949.95 | BI35: =AP35+AR35+AT35+AV35+AX35+AZ35+BB35+BD35+BF35+BH35 -> 12627.388 | BJ35: =BI35+AN35 -> 29856.628 | BK35: 1393419 | BL35: =IF(BK35>=BK34,BK35-BK34,0) -> 59 | BM35: 3659868 | BN35: =IF(BM35>=BM34,BM35-BM34,0) -> 1522 | BO35: 388992 | BP35: =IF(BO35>=BO34,BO35-BO34,0) -> 107 | BQ35: 482745 | BR35: =IF(BQ35>=BQ34,BQ35-BQ34,0) -> 230 | BS35: =J35+Q35+AN35+BI35 -> 36117.628 | BT35: 175 | BU35: =IF(BS35>0,BS35/BT35,0) -> 206.38644 | BW35: =IF(BS35>0,BS35/BV35,0) -> #DIV/0! | BX35: =((BS35-Q35)*$BZ$1)+(Q35*$BR$1) -> 41778.272 | BY35: =IF(BX35>0,BX35/BT35,0) -> 238.73298 | BZ35: =IF(BX35>0,BX35/BV35,0) -> #DIV/0!
A36: 31 | I36: 22746674 | J36: =IF(I36>=I35,I36-I35,0) -> 0 | K36: =M36+O36 -> 0 | L36: 216116 | M36: =IF(L36>=L35,L36-L35,0) -> 0 | N36: 227602 | O36: =IF(N36>=N35,N36-N35,0) -> 0 | P36: 217618 | Q36: =IF(P36>=P35,P36-P35,0)*30 -> 0 | R36: 152378 | S36: =IF(R36>=R35,R36-R35,0) -> 0 | T36: 276952 | U36: =IF(T36>=T35,T36-T35,0) -> 0 | V36: 904062 | W36: =IF(V36>=V35,V36-V35,0)*0.53 -> 0 | X36: 547768 | Y36: =IF(X36>=X35,X36-X35,0)*0.53 -> 0 | Z36: 740382 | AA36: =IF(Z36>=Z35,Z36-Z35,0)*0.53 -> 0 | AB36: 333452 | AC36: =IF(AB36>=AB35,AB36-AB35,0)*0.53 -> 0 | AD36: 374989 | AE36: =IF(AD36>=AD35,AD36-AD35,0)*0.53 -> 0 | AF36: 802312 | AG36: =IF(AF36>=AF35,AF36-AF35,0)*0.53 -> 0 | AH36: 708025 | AI36: =IF(AH36>=AH35,AH36-AH35,0)*0.53 -> 0 | AJ36: 493081 | AK36: =IF(AJ36>=AJ35,AJ36-AJ35,0)*0.53 -> 0 | AL36: 427617 | AM36: =IF(AL36>=AL35,AL36-AL35,0)*0.53 -> 0 | AN36: =W36+Y36+AA36+AC36+AE36+AG36+AI36+AK36+AM36 -> 0 | AO36: 7370675 | AP36: =IF(AO36>=AO35,AO36-AO35,0)*0.1125 -> 0 | AQ36: 619381 | AR36: =IF(AQ36>=AQ35,AQ36-AQ35,0) -> 0 | AS36: 932202 | AT36: =IF(AS36>=AS35,AS36-AS35,0) -> 0 | AU36: 800419 | AV36: =IF(AU36>=AU35,AU36-AU35,0) -> 0 | AW36: 2433073 | AX36: =IF(AW36>=AW35,AW36-AW35,0) -> 0 | AY36: 217166 | AZ36: =IF(AY36>=AY35,AY36-AY35,0) -> 0 | BA36: 18257880 | BB36: =IF(BA36>=BA35,BA36-BA35,0) -> 0 | BC36: 517828 | BD36: =IF(BC36>=BC35,BC36-BC35,0) -> 0 | BE36: 12219 | BF36: =IF(BE36>=BE35,BE36-BE35,0) -> 0 | BG36: 22769782 | BH36: =IF(BG36>=BG35,BG36-BG35,0)-(0.45*BN36)-(0.45*BP36)-BR36 -> 0 | BI36: =AP36+AR36+AT36+AV36+AX36+AZ36+BB36+BD36+BF36+BH36 -> 0 | BJ36: =BI36+AN36 -> 0 | BK36: 1393419 | BL36: =IF(BK36>=BK35,BK36-BK35,0) -> 0 | BM36: 3659868 | BN36: =IF(BM36>=BM35,BM36-BM35,0) -> 0 | BO36: 388992 | BP36: =IF(BO36>=BO35,BO36-BO35,0) -> 0 | BQ36: 482745 | BR36: =IF(BQ36>=BQ35,BQ36-BQ35,0) -> 0 | BS36: =J36+Q36+AN36+BI36 -> 0 | BU36: =IF(BS36>0,BS36/BT36,0) -> 0 | BW36: =IF(BS36>0,BS36/BV36,0) -> 0 | BX36: =((BS36-Q36)*$BZ$1)+(Q36*$BR$1) -> 0 | BY36: =IF(BX36>0,BX36/BT36,0) -> 0 | BZ36: =IF(BX36>0,BX36/BV36,0) -> 0
A37: MTD | C37: =SUM(C9:C35) -> 0 | E37: =SUM(E9:E35) -> 0 | F37: =SUM(F9:F35) -> 0 | G37: =SUM(G9:G35) -> 0 | J37: =SUM(J6:J36) -> 156388 | K37: =SUM(K6:K36) -> 97984 | M37: =SUM(M6:M36) -> 51741 | O37: =SUM(O6:O36) -> 46243 | Q37: =SUM(Q6:Q36) -> 16500 | S37: =SUM(S6:S36) -> 4230 | U37: =SUM(U6:U36) -> 8141 | W37: =SUM(W6:W36) -> 86795.98 | Y37: =SUM(Y5:Y36) -> 59929.22 | AA37: =SUM(AA6:AA36) -> 26323.51 | AC37: =SUM(AC6:AC36) -> 4555.35 | AE37: =SUM(AE6:AE36) -> 5406 | AG37: =SUM(AG6:AG36) -> 30073.79 | AI37: =SUM(AI6:AI36) -> 31709.9 | AK37: =SUM(AK6:AK36) -> 114308.81 | AM37: =SUM(AM6:AM36) -> 5119.27 | AN37: =SUM(AN6:AN36) -> 364221.83 | AP37: =SUM(AP6:AP36) -> 6262.7625 | AR37: =SUM(AR6:AR36) -> 8190 | AT37: =SUM(AT6:AT36) -> 4661 | AV37: =SUM(AV6:AV36) -> 1505 | AX37: =SUM(AX6:AX36) -> 26283 | AZ37: =SUM(AZ6:AZ36) -> 2114 | BB37: =SUM(BB6:BB36) -> 138282 | BD37: =SUM(BD6:BD36) -> 5186 | BF37: =SUM(BF6:BF36) -> 2956 | BH37: =SUM(BH6:BH36) -> 175658.7 | BI37: =SUM(BI6:BI36) -> 371098.46 | BJ37: =SUM(BJ6:BJ36) -> 735320.29 | BL37: =SUM(BL6:BL36) -> 4142 | BN37: =SUM(BN6:BN36) -> 41382 | BP37: =SUM(BP6:BP36) -> 3152 | BR37: =SUM(BR6:BR36) -> 6279 | BS37: =SUM(BS6:BS36) -> 908208.29 | BT37: =SUM(BT6:BT36) -> 4814 | BU37: =IF(BS37>0,BS37/BT37,0) -> 188.6598 | BV37: =SUM(BV6:BV35) -> 0 | BW37: =IF(BS37>0,BS37/BV37,0) -> #DIV/0! | BX37: =SUM(BX6:BX35) -> 1051864.5 | BY37: =IF(BX37>0,BX37/BT37,0) -> 218.50115 | BZ37: =IF(BX37>0,BX37/BV37,0) -> #DIV/0!
A38: AVER. Act | C38: =C37/C40 -> #DIV/0! | E38: =E37/C40 -> #DIV/0! | F38: =F37/C40 -> #DIV/0! | G38: =G37/C40 -> #DIV/0! | J38: =J37/J39 -> 5212.9333 | K38: =K37/J39 -> 3266.1333 | M38: =M37/J39 -> 1724.7 | O38: =O37/J39 -> 1541.4333 | Q38: =Q37/J39 -> 550 | S38: =S37/J39 -> 141 | U38: =U37/J39 -> 271.36667 | W38: =W37/J39 -> 2893.1993 | Y38: =Y37/J39 -> 1997.6407 | AA38: =AA37/J39 -> 877.45033 | AC38: =AC37/J39 -> 151.845 | AE38: =AE37/J39 -> 180.2 | AG38: =AG37/J39 -> 1002.4597 | AI38: =AI37/J39 -> 1056.9967 | AK38: =AK37/J39 -> 3810.2937 | AM38: =AM37/J39 -> 170.64233 | AN38: =AN37/J39 -> 12140.728 | AP38: =AP37/J39 -> 208.75875 | AR38: =AR37/J39 -> 273 | AT38: =AT37/J39 -> 155.36667 | AV38: =AV37/J39 -> 50.166667 | AX38: =AX37/J39 -> 876.1 | AZ38: =AZ37/J39 -> 70.466667 | BB38: =BB37/J39 -> 4609.4 | BD38: =BD37/J39 -> 172.86667 | BF38: =BF37/J39 -> 98.533333 | BH38: =BH37/J39 -> 5855.29 | BL38: =BL37/J39 -> 138.06667 | BN38: =BN37/J39 -> 1379.4 | BP38: =BP37/J39 -> 105.06667 | BR38: =BR37/J39 -> 209.3 | BS38: =BS37/$J$41 -> #DIV/0! | BT38: =BT37/$J$41 -> #DIV/0! | BU38: =BS38/BT38 -> #DIV/0! | BV38: =BV37/$J$41 -> #DIV/0! | BW38: =BS38/BV38 -> #DIV/0! | BX38: =BX37/$J$41 -> #DIV/0! | BY38: =BX38/BT38 -> #DIV/0! | BZ38: =BX38/BV38 -> #DIV/0!
A39: No of Days MTD | J39: =COUNTIF(I6:I35,">0") -> 30
A40: No of Days month | J40: =COUNTIF(A6:A35,">0") -> 30

Sheet Gas
A1: =Elect!A1 -> June | E1: Gas | H1: Gas UP | J1: 3.9
A4: NO. | B4: Main Gas Flow Meter | D4: Laundry Gas Flow Meter | F4: Grumandiz Gas Flow Meter | H4: Plant Room Gas Share Cost | I4: Hotel Consumption Cost | J4: La Grumandiz Cost | K4: Total Natural Gas Consumption
B5: Read | C5: Cons | D5: Read | E5: Cons | F5: Read | G5: Cons | H5: LE/DAY | I5: LE/DAY | J5: LE/DAY | K5: Cons
B6: 8085324 | C6: =IF(B6>=B5,B6-B5,0)*1.06 -> 0 | D6: 363833 | E6: =IF(D6>=D5,D6-D5,0)*0.7 -> 0 | F6: 578465 | G6: =IF(F6>=F5,F6-F5,0) -> 0 | K6: =C6+E6 -> 0
A7: 1 | B7: 8086212 | C7: =IF(B7>=B6,B7-B6,0)*1.06 -> 941.28 | D7: 364100 | E7: =IF(D7>=D6,D7-D6,0)*0.7 -> 186.9 | F7: 578541 | G7: =IF(F7>=F6,F7-F6,0) -> 76 | H7: =(E7*0.55)*1.61 -> 165.49995 | I7: =C7*J1 -> 3670.992 | J7: =G7*J1 -> 296.4 | K7: =C7+E7 -> 1128.18
A8: 2 | B8: 8087221 | C8: =IF(B8>=B7,B8-B7,0)*1.06 -> 1069.54 | D8: 364312 | E8: =IF(D8>=D7,D8-D7,0)*0.7 -> 148.4 | F8: 578621 | G8: =IF(F8>=F7,F8-F7,0) -> 80 | H8: =(E8*0.55)*1.61 -> 131.4082 | I8: =C8*J1 -> 4171.206 | J8: =G8*J1 -> 312 | K8: =C8+E8 -> 1217.94
A9: 3 | B9: 8088191 | C9: =IF(B9>=B8,B9-B8,0)*1.06 -> 1028.2 | D9: 364514 | E9: =IF(D9>=D8,D9-D8,0)*0.7 -> 141.4 | F9: 578709 | G9: =IF(F9>=F8,F9-F8,0) -> 88 | H9: =(E9*0.55)*1.61 -> 125.2097 | I9: =C9*J1 -> 4009.98 | J9: =G9*J1 -> 343.2 | K9: =C9+E9 -> 1169.6
A10: 4 | B10: 8088993 | C10: =IF(B10>=B9,B10-B9,0)*1.06 -> 850.12 | D10: 364920 | E10: =IF(D10>=D9,D10-D9,0)*0.7 -> 284.2 | F10: 578805 | G10: =IF(F10>=F9,F10-F9,0) -> 96 | H10: =(E10*0.55)*1.61 -> 251.6591 | I10: =C10*J1 -> 3315.468 | J10: =G10*J1 -> 374.4 | K10: =C10+E10 -> 1134.32
A11: 5 | B11: 8090021 | C11: =IF(B11>=B10,B11-B10,0)*1.06 -> 1089.68 | D11: 365347 | E11: =IF(D11>=D10,D11-D10,0)*0.7 -> 298.9 | F11: 578906 | G11: =IF(F11>=F10,F11-F10,0) -> 101 | H11: =(E11*0.55)*1.61 -> 264.67595 | I11: =C11*J1 -> 4249.752 | J11: =G11*J1 -> 393.9 | K11: =C11+E11 -> 1388.58
A12: 6 | B12: 8091023 | C12: =IF(B12>=B11,B12-B11,0)*1.06 -> 1062.12 | D12: 365787 | E12: =IF(D12>=D11,D12-D11,0)*0.7 -> 308 | F12: 579012 | G12: =IF(F12>=F11,F12-F11,0) -> 106 | H12: =(E12*0.55)*1.61 -> 272.734 | I12: =C12*J1 -> 4142.268 | J12: =G12*J1 -> 413.4 | K12: =C12+E12 -> 1370.12
A13: 7 | B13: 8091901 | C13: =IF(B13>=B12,B13-B12,0)*1.06 -> 930.68 | D13: 366124 | E13: =IF(D13>=D12,D13-D12,0)*0.7 -> 235.9 | F13: 579105 | G13: =IF(F13>=F12,F13-F12,0) -> 93 | H13: =(E13*0.55)*1.61 -> 208.88945 | I13: =C13*J1 -> 3629.652 | J13: =G13*J1 -> 362.7 | K13: =C13+E13 -> 1166.58
A14: 8 | B14: 8092262 | C14: =IF(B14>=B13,B14-B13,0)*1.06 -> 382.66 | D14: 366497 | E14: =IF(D14>=D13,D14-D13,0)*0.7 -> 261.1 | F14: 579196 | G14: =IF(F14>=F13,F14-F13,0) -> 91 | H14: =(E14*0.55)*1.61 -> 231.20405 | I14: =C14*J1 -> 1492.374 | J14: =G14*J1 -> 354.9 | K14: =C14+E14 -> 643.76
A15: 9 | B15: 8093510 | C15: =IF(B15>=B14,B15-B14,0)*1.06 -> 1322.88 | D15: 366757 | E15: =IF(D15>=D14,D15-D14,0)*0.7 -> 182 | F15: 579214 | G15: =IF(F15>=F14,F15-F14,0) -> 18 | H15: =(E15*0.55)*1.61 -> 161.161 | I15: =C15*J1 -> 5159.232 | J15: =G15*J1 -> 70.2 | K15: =C15+E15 -> 1504.88
A16: 10 | B16: 8094000 | C16: =IF(B16>=B15,B16-B15,0)*1.06 -> 519.4 | D16: 367192 | E16: =IF(D16>=D15,D16-D15,0)*0.7 -> 304.5 | F16: 579275 | G16: =IF(F16>=F15,F16-F15,0) -> 61 | H16: =(E16*0.55)*1.61 -> 269.63475 | I16: =C16*J1 -> 2025.66 | J16: =G16*J1 -> 237.9 | K16: =C16+E16 -> 823.9
A17: 11 | B17: 8095033 | C17: =IF(B17>=B16,B17-B16,0)*1.06 -> 1094.98 | D17: 367591 | E17: =IF(D17>=D16,D17-D16,0)*0.7 -> 279.3 | F17: 579350 | G17: =IF(F17>=F16,F17-F16,0) -> 75 | H17: =(E17*0.55)*1.61 -> 247.32015 | I17: =C17*J1 -> 4270.422 | J17: =G17*J1 -> 292.5 | K17: =C17+E17 -> 1374.28
A18: 12 | B18: 8096159 | C18: =IF(B18>=B17,B18-B17,0)*1.06 -> 1193.56 | D18: 367895 | E18: =IF(D18>=D17,D18-D17,0)*0.7 -> 212.8 | F18: 579414 | G18: =IF(F18>=F17,F18-F17,0) -> 64 | H18: =(E18*0.55)*1.61 -> 188.4344 | I18: =C18*J1 -> 4654.884 | J18: =G18*J1 -> 249.6 | K18: =C18+E18 -> 1406.36
A19: 13 | B19: 8096892 | C19: =IF(B19>=B18,B19-B18,0)*1.06 -> 776.98 | D19: 368151 | E19: =IF(D19>=D18,D19-D18,0)*0.7 -> 179.2 | F19: 579477 | G19: =IF(F19>=F18,F19-F18,0) -> 63 | H19: =(E19*0.55)*1.61 -> 158.6816 | I19: =C19*J1 -> 3030.222 | J19: =G19*J1 -> 245.7 | K19: =C19+E19 -> 956.18
A20: 14 | B20: 8097844 | C20: =IF(B20>=B19,B20-B19,0)*1.06 -> 1009.12 | D20: 368442 | E20: =IF(D20>=D19,D20-D19,0)*0.7 -> 203.7 | F20: 579638 | G20: =IF(F20>=F19,F20-F19,0) -> 161 | H20: =(E20*0.55)*1.61 -> 180.37635 | I20: =C20*J1 -> 3935.568 | J20: =G20*J1 -> 627.9 | K20: =C20+E20 -> 1212.82
A21: 15 | B21: 8098650 | C21: =IF(B21>=B20,B21-B20,0)*1.06 -> 854.36 | D21: 368933 | E21: =IF(D21>=D20,D21-D20,0)*0.7 -> 343.7 | F21: 579673 | G21: =IF(F21>=F20,F21-F20,0) -> 35 | H21: =(E21*0.55)*1.61 -> 304.34635 | I21: =C21*J1 -> 3332.004 | J21: =G21*J1 -> 136.5 | K21: =C21+E21 -> 1198.06
A22: 16 | B22: 8099527 | C22: =IF(B22>=B21,B22-B21,0)*1.06 -> 929.62 | D22: 369132 | E22: =IF(D22>=D21,D22-D21,0)*0.7 -> 139.3 | F22: 579753 | G22: =IF(F22>=F21,F22-F21,0) -> 80 | H22: =(E22*0.55)*1.61 -> 123.35015 | I22: =C22*J1 -> 3625.518 | J22: =G22*J1 -> 312 | K22: =C22+E22 -> 1068.92
A23: 17 | B23: 8100488 | C23: =IF(B23>=B22,B23-B22,0)*1.06 -> 1018.66 | D23: 369533 | E23: =IF(D23>=D22,D23-D22,0)*0.7 -> 280.7 | F23: 579908 | G23: =IF(F23>=F22,F23-F22,0) -> 155 | H23: =(E23*0.55)*1.61 -> 248.55985 | I23: =C23*J1 -> 3972.774 | J23: =G23*J1 -> 604.5 | K23: =C23+E23 -> 1299.36
A24: 18 | B24: 8101389 | C24: =IF(B24>=B23,B24-B23,0)*1.06 -> 955.06 | D24: 369862 | E24: =IF(D24>=D23,D24-D23,0)*0.7 -> 230.3 | F24: 579980 | G24: =IF(F24>=F23,F24-F23,0) -> 72 | H24: =(E24*0.55)*1.61 -> 203.93065 | I24: =C24*J1 -> 3724.734 | J24: =G24*J1 -> 280.8 | K24: =C24+E24 -> 1185.36
A25: 19 | B25: 8102259 | C25: =IF(B25>=B24,B25-B24,0)*1.06 -> 922.2 | D25: 370201 | E25: =IF(D25>=D24,D25-D24,0)*0.7 -> 237.3 | F25: 580053 | G25: =IF(F25>=F24,F25-F24,0) -> 73 | H25: =(E25*0.55)*1.61 -> 210.12915 | I25: =C25*J1 -> 3596.58 | J25: =G25*J1 -> 284.7 | K25: =C25+E25 -> 1159.5
A26: 20 | B26: 8103189 | C26: =IF(B26>=B25,B26-B25,0)*1.06 -> 985.8 | D26: 370550 | E26: =IF(D26>=D25,D26-D25,0)*0.7 -> 244.3 | F26: 580145 | G26: =IF(F26>=F25,F26-F25,0) -> 92 | H26: =(E26*0.55)*1.61 -> 216.32765 | I26: =C26*J1 -> 3844.62 | J26: =G26*J1 -> 358.8 | K26: =C26+E26 -> 1230.1
A27: 21 | B27: 8104166 | C27: =IF(B27>=B26,B27-B26,0)*1.06 -> 1035.62 | D27: 370840 | E27: =IF(D27>=D26,D27-D26,0)*0.7 -> 203 | F27: 580241 | G27: =IF(F27>=F26,F27-F26,0) -> 96 | H27: =(E27*0.55)*1.61 -> 179.7565 | I27: =C27*J1 -> 4038.918 | J27: =G27*J1 -> 374.4 | K27: =C27+E27 -> 1238.62
A28: 22 | B28: 8105135 | C28: =IF(B28>=B27,B28-B27,0)*1.06 -> 1027.14 | D28: 371113 | E28: =IF(D28>=D27,D28-D27,0)*0.7 -> 191.1 | F28: 580325 | G28: =IF(F28>=F27,F28-F27,0) -> 84 | H28: =(E28*0.55)*1.61 -> 169.21905 | I28: =C28*J1 -> 4005.846 | J28: =G28*J1 -> 327.6
A29: 23 | B29: 8106130 | C29: =IF(B29>=B28,B29-B28,0)*1.06 -> 1054.7 | D29: 371421 | E29: =IF(D29>=D28,D29-D28,0)*0.7 -> 215.6 | F29: 580401 | G29: =IF(F29>=F28,F29-F28,0) -> 76 | H29: =(E29*0.55)*1.61 -> 190.9138 | I29: =C29*J1 -> 4113.33 | J29: =G29*J1 -> 296.4 | K29: =C29+E29 -> 1270.3
A30: 24 | B30: 8107107 | C30: =IF(B30>=B29,B30-B29,0)*1.06 -> 1035.62 | D30: 371705 | E30: =IF(D30>=D29,D30-D29,0)*0.7 -> 198.8 | F30: 580482 | G30: =IF(F30>=F29,F30-F29,0) -> 81 | H30: =(E30*0.55)*1.61 -> 176.0374 | I30: =C30*J1 -> 4038.918 | J30: =G30*J1 -> 315.9 | K30: =C30+E30 -> 1234.42
A31: 25 | B31: 8108089 | C31: =IF(B31>=B30,B31-B30,0)*1.06 -> 1040.92 | D31: 371996 | E31: =IF(D31>=D30,D31-D30,0)*0.7 -> 203.7 | F31: 580562 | G31: =IF(F31>=F30,F31-F30,0) -> 80 | H31: =(E31*0.55)*1.61 -> 180.37635 | I31: =C31*J3 -> 0 | J31: =G31*J1 -> 312 | K31: =C31+E31 -> 1244.62
A32: 26 | B32: 8109268 | C32: =IF(B32>=B31,B32-B31,0)*1.06 -> 1249.74 | D32: 372466 | E32: =IF(D32>=D31,D32-D31,0)*0.7 -> 329 | F32: 580651 | G32: =IF(F32>=F31,F32-F31,0) -> 89 | H32: =(E32*0.55)*1.61 -> 291.3295 | I32: =C32*J1 -> 4873.986 | J32: =G32*J1 -> 347.1 | K32: =C32+E32 -> 1578.74
A33: 27 | B33: 8109960 | C33: =IF(B33>=B32,B33-B32,0)*1.06 -> 733.52 | D33: 372774 | E33: =IF(D33>=D32,D33-D32,0)*0.7 -> 215.6 | F33: 580702 | G33: =IF(F33>=F32,F33-F32,0) -> 51 | H33: =(E33*0.55)*1.61 -> 190.9138 | I33: =C33*J1 -> 2860.728 | J33: =G33*J1 -> 198.9 | K33: =C33+E33 -> 949.12
A34: 28 | B34: 8110682 | C34: =IF(B34>=B33,B34-B33,0)*1.06 -> 765.32 | D34: 373086 | E34: =IF(D34>=D33,D34-D33,0)*0.7 -> 218.4 | F34: 580758 | G34: =IF(F34>=F33,F34-F33,0) -> 56 | H34: =(E34*0.55)*1.61 -> 193.3932 | I34: =C34*J1 -> 2984.748 | J34: =G34*J1 -> 218.4 | K34: =C34+E34 -> 983.72
A35: 29 | B35: 8111344 | C35: =IF(B35>=B34,B35-B34,0)*1.06 -> 701.72 | D35: 373380 | E35: =IF(D35>=D34,D35-D34,0)*0.7 -> 205.8 | F35: 580800 | G35: =IF(F35>=F34,F35-F34,0) -> 42 | H35: =(E35*0.55)*1.61 -> 182.2359 | I35: =C35*J1 -> 2736.708 | J35: =G35*J1 -> 163.8 | K35: =C35+E35 -> 907.52
A36: 30 | B36: 8112128 | C36: =IF(B36>=B35,B36-B35,0)*1.06 -> 831.04 | D36: 373612 | E36: =IF(D36>=D35,D36-D35,0)*0.7 -> 162.4 | F36: 580865 | G36: =IF(F36>=F35,F36-F35,0) -> 65 | H36: =(E36*0.55)*1.61 -> 143.8052 | I36: =C36*J1 -> 3241.056 | J36: =G36*J1 -> 253.5 | K36: =C36+E36 -> 993.44
A37: 31 | B37: 8112128 | C37: =IF(B37>=B36,B37-B36,0)*1.06 -> 0 | D37: 373612 | E37: =IF(D37>=D36,D37-D36,0)*0.7 -> 0 | F37: 580865 | G37: =IF(F37>=F36,F37-F36,0) -> 0 | H37: =(E37*0.55)*1.61 -> 0 | I37: =C37*J1 -> 0 | J37: =G37*J1 -> 0 | K37: =C37+E37 -> 0
A38: MTD | C38: =SUM(C7:C37) -> 28412.24 | E38: =SUM(E7:E37) -> 6845.3 | G38: =SUM(G7:G37) -> 2400 | H38: =SUM(H6:H37) -> 6061.5132 | I38: =SUM(I6:I37) -> 106748.15 | J38: =SUM(J6:J37) -> 9360 | K38: =SUM(K6:K37) -> 34039.3
A39: Average MTD. | C39: =C38/A42 -> 947.07467 | E39: =E38/A42 -> 228.17667 | G39: =G38/A42 -> 80 | H39: =H38/A42 -> 202.05044 | I39: =I38/A42 -> 3558.2716 | J39: =J38/A42 -> 312
A41: No of Days MTD
A42: =COUNTIF(B7:B36,">0") -> 30

Sheet Water
A1: =Elect!A1 -> June | T1: Main Water UP | V1: 4 | W1: Water Truck UP
A3: Day | E3: Water Incoming | I3: New casino | N3: Rooms Consumption | P3: Public Areas consumption | R3: Swimming pool | T3: No. of rooms | U3: Cons. Per occ. room | V3: No. of guest | W3: Cons. Per guest | X3: Total cost | Y3: L.E\ | Z3: L.E\
B4: Main water meter 1 | D4: Main water meter 2 | F4: Main water meter 3 | H4: Total Inc. | I4: Hot water | K4: Cold water | N4: Express Riser | O4: Consp. | P4: Read. | Q4: Cons. | R4: Read. | S4: Cons. | Y4: Room | Z4: Guest
B5: Counter | C5: Produc 58% | D5: Counter | E5: Produc 58% | F5: Counter | G5: Produc 58% | I5: Counter | K5: Counter
B6: 77615 | C6: =IF(B6>=B5,B6-B5,0)*10*0.58 -> 0 | D6: 155358 | E6: =IF(D6>=D5,D6-D5,0)*10*0.58 -> 0 | F6: 18883 | G6: =IF(F6>=F5,F6-F5,0)*0.58 -> 0 | I6: 220 | K6: 3211
A7: 1 | B7: 77650 | C7: =IF(B7>=B6,B7-B6,0)*10*0.58 -> 203 | D7: 155358 | E7: =IF(D7>=D6,D7-D6,0)*10*0.58 -> 0 | F7: 18901 | G7: =IF(F7>=F6,F7-F6,0)*0.58 -> 10.44 | H7: =C7+E7+G7 -> 213.44 | O7: =IF(N7>=N6,N7-N6,0) -> 0 | Q7: =(H7-O7)*0.58 -> 123.7952 | S7: =IF(R7-R6>0,R7-R6,0) -> 0 | T7: =Elect!BT6 -> 94 | U7: =H7/T7 -> 2.2706383 | V7: =Elect!BV6 -> 0 | W7: =H7/V7 -> #DIV/0! | X7: =H7*V1 -> 853.76 | Y7: =IF(X7>0,X7/T7,0) -> 9.0825532 | Z7: 0
A8: 2 | B8: 77689 | C8: =IF(B8>=B7,B8-B7,0)*10*0.58 -> 226.2 | D8: 155358 | E8: =IF(D8>=D7,D8-D7,0)*10*0.58 -> 0 | F8: 18957 | G8: =IF(F8>=F7,F8-F7,0)*0.58 -> 32.48 | H8: =C8+E8+G8 -> 258.68 | O8: =IF(N8>=N7,N8-N7,0) -> 0 | Q8: =(H8-O8)*0.58 -> 150.0344 | S8: =IF(R8-R7>0,R8-R7,0) -> 0 | T8: =Elect!BT7 -> 125 | U8: =H8/T8 -> 2.06944 | V8: =Elect!BV7 -> 0 | W8: =H8/V8 -> #DIV/0! | X8: =H8*V1 -> 1034.72 | Y8: =IF(X8>0,X8/T8,0) -> 8.27776 | Z8: =IF(X8>0,X8/V8,0) -> #DIV/0!
A9: 3 | B9: 77730 | C9: =IF(B9>=B8,B9-B8,0)*10*0.58 -> 237.8 | D9: 155358 | E9: =IF(D9>=D8,D9-D8,0)*10*0.58 -> 0 | F9: 18992 | G9: =IF(F9>=F8,F9-F8,0)*0.58 -> 20.3 | H9: =C9+E9+G9 -> 258.1 | O9: =IF(N9>=N8,N9-N8,0) -> 0 | Q9: =(H9-O9)*0.58 -> 149.698 | S9: =IF(R9-R8>0,R9-R8,0) -> 0 | T9: =Elect!BT8 -> 135 | U9: =H9/T9 -> 1.9118519 | V9: =Elect!BV8 -> 0 | W9: =H9/V9 -> #DIV/0! | X9: =H9*V1 -> 1032.4 | Y9: =IF(X9>0,X9/T9,0) -> 7.6474074 | Z9: =IF(X9>0,X9/V9,0) -> #DIV/0!
A10: 4 | B10: 77784 | C10: =IF(B10>=B9,B10-B9,0)*10*0.58 -> 313.2 | D10: 155358 | E10: =IF(D10>=D9,D10-D9,0)*10*0.58 -> 0 | F10: 19033 | G10: =IF(F10>=F9,F10-F9,0)*0.58 -> 23.78 | H10: =C10+E10+G10 -> 336.98 | O10: =IF(N10>=N9,N10-N9,0) -> 0 | Q10: =(H10-O10)*0.58 -> 195.4484 | S10: =IF(R10-R9>0,R10-R9,0) -> 0 | T10: =Elect!BT9 -> 171 | U10: =H10/T10 -> 1.9706433 | V10: =Elect!BV9 -> 0 | W10: =H10/V10 -> #DIV/0! | X10: =H10*V1 -> 1347.92 | Y10: =IF(X10>0,X10/T10,0) -> 7.8825731 | Z10: =IF(X10>0,X10/V10,0) -> #DIV/0!
A11: 5 | B11: 77827 | C11: =IF(B11>=B10,B11-B10,0)*10*0.58 -> 249.4 | D11: 155358 | E11: =IF(D11>=D10,D11-D10,0)*10*0.58 -> 0 | F11: 19080 | G11: =IF(F11>=F10,F11-F10,0)*0.58 -> 27.26 | H11: =C11+E11+G11 -> 276.66 | O11: =IF(N11>=N10,N11-N10,0) -> 0 | Q11: =(H11-O11)*0.58 -> 160.4628 | S11: =IF(R11-R10>0,R11-R10,0) -> 0 | T11: =Elect!BT10 -> 160 | U11: =H11/T11 -> 1.729125 | V11: =Elect!BV10 -> 0 | W11: =H11/V11 -> #DIV/0! | X11: =H11*V1 -> 1106.64 | Y11: =IF(X11>0,X11/T11,0) -> 6.9165 | Z11: =IF(X11>0,X11/V11,0) -> #DIV/0!
A12: 6 | B12: 77863 | C12: =IF(B12>=B11,B12-B11,0)*10*0.58 -> 208.8 | D12: 155358 | E12: =IF(D12>=D11,D12-D11,0)*10*0.58 -> 0 | F12: 19121 | G12: =IF(F12>=F11,F12-F11,0)*0.58 -> 23.78 | H12: =C12+E12+G12 -> 232.58 | O12: =IF(N12>=N11,N12-N11,0) -> 0 | Q12: =(H12-O12)*0.58 -> 134.8964 | S12: =IF(R12-R11>0,R12-R11,0) -> 0 | T12: =Elect!BT11 -> 152 | U12: =H12/T12 -> 1.5301316 | V12: =Elect!BV11 -> 0 | W12: =H12/V12 -> #DIV/0! | X12: =H12*V1 -> 930.32 | Y12: =IF(X12>0,X12/T12,0) -> 6.1205263 | Z12: =IF(X12>0,X12/V12,0) -> #DIV/0!
A13: 7 | B13: 77897 | C13: =IF(B13>=B12,B13-B12,0)*10*0.58 -> 197.2 | D13: 155358 | E13: =IF(D13>=D12,D13-D12,0)*10*0.58 -> 0 | F13: 19199 | G13: =IF(F13>=F12,F13-F12,0)*0.58 -> 45.24 | H13: =C13+E13+G13 -> 242.44 | O13: =IF(N13>=N12,N13-N12,0) -> 0 | Q13: =(H13-O13)*0.58 -> 140.6152 | S13: =IF(R13-R12>0,R13-R12,0) -> 0 | T13: =Elect!BT12 -> 161 | U13: =H13/T13 -> 1.5058385 | V13: =Elect!BV12 -> 0 | W13: =H13/V13 -> #DIV/0! | X13: =H13*V1 -> 969.76 | Y13: =IF(X13>0,X13/T13,0) -> 6.023354 | Z13: =IF(X13>0,X13/V13,0) -> #DIV/0!
A14: 8 | B14: 77933 | C14: =IF(B14>=B13,B14-B13,0)*10*0.58 -> 208.8 | D14: 155358 | E14: =IF(D14>=D13,D14-D13,0)*10*0.58 -> 0 | F14: 19263 | G14: =IF(F14>=F13,F14-F13,0)*0.58 -> 37.12 | H14: =C14+E14+G14 -> 245.92 | O14: =IF(N14>=N13,N14-N13,0) -> 0 | Q14: =(H14-O14)*0.58 -> 142.6336 | S14: =IF(R14-R13>0,R14-R13,0) -> 0 | T14: =Elect!BT13 -> 91 | U14: =H14/T14 -> 2.7024176 | V14: =Elect!BV13 -> 0 | W14: =H14/V14 -> #DIV/0! | X14: =H14*V1 -> 983.68 | Y14: =IF(X14>0,X14/T14,0) -> 10.80967 | Z14: =IF(X14>0,X14/V14,0) -> #DIV/0!
A15: 9 | B15: 77967.667 | C15: =IF(B15>=B14,B15-B14,0)*10*0.58 -> 201.06667 | D15: 155358 | E15: =IF(D15>=D14,D15-D14,0)*10*0.58 -> 0 | F15: 19336.333 | G15: =IF(F15>=F14,F15-F14,0)*0.58 -> 42.533333 | H15: =C15+E15+G15 -> 243.6 | O15: =IF(N15>=N14,N15-N14,0) -> 0 | Q15: =(H15-O15)*0.58 -> 141.288 | S15: =IF(R15-R14>0,R15-R14,0) -> 0 | T15: =Elect!BT14 -> 156 | U15: =H15/T15 -> 1.5615385 | V15: =Elect!BV14 -> 0 | W15: =H15/V15 -> #DIV/0! | X15: =H15*V1 -> 974.4 | Y15: =IF(X15>0,X15/T15,0) -> 6.2461538 | Z15: =IF(X15>0,X15/V15,0) -> #DIV/0!
A16: 10 | B16: 78018 | C16: =IF(B16>=B15,B16-B15,0)*10*0.58 -> 291.93333 | D16: 155358 | E16: =IF(D16>=D15,D16-D15,0)*10*0.58 -> 0 | F16: 19263 | G16: =IF(F16>=F15,F16-F15,0)*0.58 -> 0 | H16: =C16+E16+G16 -> 291.93333 | O16: =IF(N16>=N15,N16-N15,0) -> 0 | Q16: =(H16-O16)*0.58 -> 169.32133 | S16: =IF(R16-R15>0,R16-R15,0) -> 0 | T16: =Elect!BT15 -> 154 | U16: =H16/T16 -> 1.895671 | V16: =Elect!BV15 -> 0 | W16: =H16/V16 -> #DIV/0! | X16: =H16*V1 -> 1167.7333 | Y16: =IF(X16>0,X16/T16,0) -> 7.582684 | Z16: =IF(X16>0,X16/V16,0) -> #DIV/0!
A17: 11 | B17: 78049 | C17: =IF(B17>=B16,B17-B16,0)*10*0.58 -> 179.8 | D17: 155358 | E17: =IF(D17>=D16,D17-D16,0)*10*0.58 -> 0 | F17: 19263 | G17: =IF(F17>=F16,F17-F16,0)*0.58 -> 0 | H17: =C17+E17+G17 -> 179.8 | O17: =IF(N17>=N16,N17-N16,0) -> 0 | Q17: =(H17-O17)*0.58 -> 104.284 | S17: =IF(R17-R16>0,R17-R16,0) -> 0 | T17: =Elect!BT16 -> 164 | U17: =H17/T17 -> 1.0963415 | V17: =Elect!BV16 -> 0 | W17: =H17/V17 -> #DIV/0! | X17: =H17*V1 -> 719.2 | Y17: =IF(X17>0,X17/T17,0) -> 4.3853659 | Z17: =IF(X17>0,X17/V17,0) -> #DIV/0!
A18: 12 | B18: 78107 | C18: =IF(B18>=B17,B18-B17,0)*10*0.58 -> 336.4 | D18: 155358 | E18: =IF(D18>=D17,D18-D17,0)*10*0.58 -> 0 | F18: 19263 | G18: =IF(F18>=F17,F18-F17,0)*0.58 -> 0 | H18: =C18+E18+G18 -> 336.4 | O18: =IF(N18>=N17,N18-N17,0) -> 0 | Q18: =(H18-O18)*0.58 -> 195.112 | S18: =IF(R18-R17>0,R18-R17,0) -> 0 | T18: =Elect!BT17 -> 147 | U18: =H18/T18 -> 2.2884354 | V18: =Elect!BV17 -> 0 | W18: =H18/V18 -> #DIV/0! | X18: =H18*V1 -> 1345.6 | Y18: =IF(X18>0,X18/T18,0) -> 9.1537415 | Z18: =IF(X18>0,X18/V18,0) -> #DIV/0!
A19: 13 | B19: 78136 | C19: =IF(B19>=B18,B19-B18,0)*10*0.58 -> 168.2 | D19: 155358 | E19: =IF(D19>=D18,D19-D18,0)*10*0.58 -> 0 | F19: 19263 | G19: =IF(F19>=F18,F19-F18,0)*0.58 -> 0 | H19: =C19+E19+G19 -> 168.2 | O19: =IF(N19>=N18,N19-N18,0) -> 0 | Q19: =(H19-O19)*0.58 -> 97.556 | S19: =IF(R19-R18>0,R19-R18,0) -> 0 | T19: =Elect!BT18 -> 131 | U19: =H19/T19 -> 1.2839695 | V19: =Elect!BV18 -> 0 | W19: =H19/V19 -> #DIV/0! | X19: =H19*V1 -> 672.8 | Y19: =IF(X19>0,X19/T19,0) -> 5.1358779 | Z19: =IF(X19>0,X19/V19,0) -> #DIV/0!
A20: 14 | B20: 78176 | C20: =IF(B20>=B19,B20-B19,0)*10*0.58 -> 232 | D20: 155358 | E20: =IF(D20>=D19,D20-D19,0)*10*0.58 -> 0 | F20: 19263 | G20: =IF(F20>=F19,F20-F19,0)*0.58 -> 0 | H20: =C20+E20+G20 -> 232 | O20: =IF(N20>=N19,N20-N19,0) -> 0 | Q20: =(H20-O20)*0.58 -> 134.56 | S20: =IF(R20-R19>0,R20-R19,0) -> 0 | T20: =Elect!BT19 -> 146 | U20: =H20/T20 -> 1.5890411 | V20: =Elect!BV19 -> 0 | W20: =H20/V20 -> #DIV/0! | X20: =H20*V1 -> 928 | Y20: =IF(X20>0,X20/T20,0) -> 6.3561644 | Z20: =IF(X20>0,X20/V20,0) -> #DIV/0!
A21: 15 | B21: 78220 | C21: =IF(B21>=B20,B21-B20,0)*10*0.58 -> 255.2 | D21: 155358 | E21: =IF(D21>=D20,D21-D20,0)*10*0.58 -> 0 | F21: 19263 | G21: =IF(F21>=F20,F21-F20,0)*0.58 -> 0 | H21: =C21+E21+G21 -> 255.2 | O21: =IF(N21>=N20,N21-N20,0) -> 0 | Q21: =(H21-O21)*0.58 -> 148.016 | S21: =IF(R21-R20>0,R21-R20,0) -> 0 | T21: =Elect!BT20 -> 147 | U21: =H21/T21 -> 1.7360544 | V21: =Elect!BV20 -> 0 | W21: =H21/V21 -> #DIV/0! | X21: =H21*V1 -> 1020.8 | Y21: =IF(X21>0,X21/T21,0) -> 6.9442177 | Z21: =IF(X21>0,X21/V21,0) -> #DIV/0!
A22: 16 | B22: 78262 | C22: =IF(B22>=B21,B22-B21,0)*10*0.58 -> 243.6 | D22: 155358 | E22: =IF(D22>=D21,D22-D21,0)*10*0.58 -> 0 | F22: 19263 | G22: =IF(F22>=F21,F22-F21,0)*0.58 -> 0 | H22: =C22+E22+G22 -> 243.6 | O22: =IF(N22>=N21,N22-N21,0) -> 0 | Q22: =(H22-O22)*0.58 -> 141.288 | S22: =IF(R22-R21>0,R22-R21,0) -> 0 | T22: =Elect!BT21 -> 160 | U22: =H22/T22 -> 1.5225 | V22: =Elect!BV21 -> 0 | W22: =H22/V22 -> #DIV/0! | X22: =H22*V1 -> 974.4 | Y22: =IF(X22>0,X22/T22,0) -> 6.09 | Z22: =IF(X22>0,X22/V22,0) -> #DIV/0!
A23: 17 | B23: 78301 | C23: =IF(B23>=B22,B23-B22,0)*10*0.58 -> 226.2 | D23: 155358 | E23: =IF(D23>=D22,D23-D22,0)*10*0.58 -> 0 | F23: 19263 | G23: =IF(F23>=F22,F23-F22,0)*0.58 -> 0 | H23: =C23+E23+G23 -> 226.2 | O23: =IF(N23>=N22,N23-N22,0) -> 0 | Q23: =(H23-O23)*0.58 -> 131.196 | S23: =IF(R23-R22>0,R23-R22,0) -> 0 | T23: =Elect!BT22 -> 168 | U23: =H23/T23 -> 1.3464286 | V23: =Elect!BV22 -> 0 | W23: =H23/V23 -> #DIV/0! | X23: =H23*V1 -> 904.8 | Y23: =IF(X23>0,X23/T23,0) -> 5.3857143 | Z23: =IF(X23>0,X23/V23,0) -> #DIV/0!
A24: 18 | B24: 78342 | C24: =IF(B24>=B23,B24-B23,0)*10*0.58 -> 237.8 | D24: 155358 | E24: =IF(D24>=D23,D24-D23,0)*10*0.58 -> 0 | F24: 19263 | G24: =IF(F24>=F23,F24-F23,0)*0.58 -> 0 | H24: =C24+E24+G24 -> 237.8 | O24: =IF(N24>=N23,N24-N23,0) -> 0 | Q24: =(H24-O24)*0.58 -> 137.924 | S24: =IF(R24-R23>0,R24-R23,0) -> 0 | T24: =Elect!BT23 -> 177 | U24: =H24/T24 -> 1.3435028 | V24: =Elect!BV23 -> 0 | W24: =H24/V24 -> #DIV/0! | X24: =H24*V1 -> 951.2 | Y24: =IF(X24>0,X24/T24,0) -> 5.3740113 | Z24: =IF(X24>0,X24/V24,0) -> #DIV/0!
A25: 19 | B25: 78383 | C25: =IF(B25>=B24,B25-B24,0)*10*0.58 -> 237.8 | D25: 155358 | E25: =IF(D25>=D24,D25-D24,0)*10*0.58 -> 0 | F25: 19263 | G25: =IF(F25>=F24,F25-F24,0)*0.58 -> 0 | H25: =C25+E25+G25 -> 237.8 | O25: =IF(N25>=N24,N25-N24,0) -> 0 | Q25: =(H25-O25)*0.58 -> 137.924 | S25: =IF(R25-R24>0,R25-R24,0) -> 0 | T25: =Elect!BT24 -> 163 | U25: =H25/T25 -> 1.4588957 | V25: =Elect!BV24 -> 0 | W25: =H25/V25 -> #DIV/0! | X25: =H25*V1 -> 951.2 | Y25: =IF(X25>0,X25/T25,0) -> 5.8355828 | Z25: =IF(X25>0,X25/V25,0) -> #DIV/0!
A26: 20 | B26: 78424 | C26: =IF(B26>=B25,B26-B25,0)*10*0.58 -> 237.8 | D26: 155358 | E26: =IF(D26>=D25,D26-D25,0)*10*0.58 -> 0 | F26: 19263 | G26: =IF(F26>=F25,F26-F25,0)*0.58 -> 0 | H26: =C26+E26+G26 -> 237.8 | O26: =IF(N26>=N25,N26-N25,0) -> 0 | Q26: =(H26-O26)*0.58 -> 137.924 | S26: =IF(R26-R25>0,R26-R25,0) -> 0 | T26: =Elect!BT25 -> 165 | U26: =H26/T26 -> 1.4412121 | V26: =Elect!BV25 -> 0 | W26: =H26/V26 -> #DIV/0! | X26: =H26*V1 -> 951.2 | Y26: =IF(X26>0,X26/T26,0) -> 5.7648485 | Z26: =IF(X26>0,X26/V26,0) -> #DIV/0!
A27: 21 | B27: 78464 | C27: =IF(B27>=B26,B27-B26,0)*10*0.58 -> 232 | D27: 155358 | E27: =IF(D27>=D26,D27-D26,0)*10*0.58 -> 0 | F27: 19263 | G27: =IF(F27>=F26,F27-F26,0)*0.58 -> 0 | H27: =C27+E27+G27 -> 232 | O27: =IF(N27>=N26,N27-N26,0) -> 0 | Q27: =(H27-O27)*0.58 -> 134.56 | S27: =IF(R27-R26>0,R27-R26,0) -> 0 | T27: =Elect!BT26 -> 173 | U27: =H27/T27 -> 1.3410405 | V27: =Elect!BV26 -> 0 | W27: =H27/V27 -> #DIV/0! | X27: =H27*V1 -> 928 | Y27: =IF(X27>0,X27/T27,0) -> 5.3641618 | Z27: =IF(X27>0,X27/V27,0) -> #DIV/0!
A28: 22 | B28: 78483 | C28: =IF(B28>=B27,B28-B27,0)*10*0.58 -> 110.2 | D28: 155358 | E28: =IF(D28>=D27,D28-D27,0)*10*0.58 -> 0 | F28: 20015 | G28: =IF(F28>=F27,F28-F27,0)*0.58 -> 436.16 | H28: =C28+E28+G28 -> 546.36 | O28: =IF(N28>=N27,N28-N27,0) -> 0 | Q28: =(H28-O28)*0.58 -> 316.8888 | S28: =IF(R28-R27>0,R28-R27,0) -> 0 | T28: =Elect!BT27 -> 187 | U28: =H28/T28 -> 2.9217112 | V28: =Elect!BV27 -> 0 | W28: =H28/V28 -> #DIV/0! | X28: =H28*V1 -> 2185.44 | Y28: =IF(X28>0,X28/T28,0) -> 11.686845 | Z28: =IF(X28>0,X28/V28,0) -> #DIV/0!
A29: 23 | B29: 78518 | C29: =IF(B29>=B28,B29-B28,0)*10*0.58 -> 203 | D29: 155358 | E29: =IF(D29>=D28,D29-D28,0)*10*0.58 -> 0 | F29: 20190 | G29: =IF(F29>=F28,F29-F28,0)*0.58 -> 101.5 | H29: =C29+E29+G29 -> 304.5 | O29: =IF(N29>=N28,N29-N28,0) -> 0 | Q29: =(H29-O29)*0.58 -> 176.61 | S29: =IF(R29-R28>0,R29-R28,0) -> 0 | T29: =Elect!BT28 -> 194 | U29: =H29/T29 -> 1.5695876 | V29: =Elect!BV28 -> 0 | W29: =H29/V29 -> #DIV/0! | X29: =H29*V1 -> 1218 | Y29: =IF(X29>0,X29/T29,0) -> 6.2783505 | Z29: =IF(X29>0,X29/V29,0) -> #DIV/0!
A30: 24 | B30: 78555 | C30: =IF(B30>=B29,B30-B29,0)*10*0.58 -> 214.6 | D30: 155358 | E30: =IF(D30>=D29,D30-D29,0)*10*0.58 -> 0 | F30: 20384 | G30: =IF(F30>=F29,F30-F29,0)*0.58 -> 112.52 | H30: =C30+E30+G30 -> 327.12 | O30: =IF(N30>=N29,N30-N29,0) -> 0 | Q30: =(H30-O30)*0.58 -> 189.7296 | S30: =IF(R30-R29>0,R30-R29,0) -> 0 | T30: =Elect!BT29 -> 191 | U30: =H30/T30 -> 1.7126702 | V30: =Elect!BV29 -> 0 | W30: =H30/V30 -> #DIV/0! | X30: =H30*V1 -> 1308.48 | Y30: =IF(X30>0,X30/T30,0) -> 6.8506806 | Z30: =IF(X30>0,X30/V30,0) -> #DIV/0!
A31: 25 | B31: 78591 | C31: =IF(B31>=B30,B31-B30,0)*10*0.58 -> 208.8 | D31: 155358 | E31: =IF(D31>=D30,D31-D30,0)*10*0.58 -> 0 | F31: 20384 | G31: =IF(F31>=F30,F31-F30,0)*0.58 -> 0 | H31: =C31+E31+G31 -> 208.8 | O31: =IF(N31>=N30,N31-N30,0) -> 0 | Q31: =(H31-O31)*0.58 -> 121.104 | S31: =IF(R31-R30>0,R31-R30,0) -> 0 | T31: =Elect!BT30 -> 194 | U31: =H31/T31 -> 1.0762887 | V31: =Elect!BV30 -> 0 | W31: =H31/V31 -> #DIV/0! | X31: =H31*V1 -> 835.2 | Y31: =IF(X31>0,X31/T31,0) -> 4.3051546 | Z31: =IF(X31>0,X31/V31,0) -> #DIV/0!
A32: 26 | B32: 78644 | C32: =IF(B32>=B31,B32-B31,0)*10*0.58 -> 307.4 | D32: 155358 | E32: =IF(D32>=D31,D32-D31,0)*10*0.58 -> 0 | F32: 20507 | G32: =IF(F32>=F31,F32-F31,0)*0.58 -> 71.34 | H32: =C32+E32+G32 -> 378.74 | O32: =IF(N32>=N31,N32-N31,0) -> 0 | Q32: =(H32-O32)*0.58 -> 219.6692 | S32: =IF(R32-R31>0,R32-R31,0) -> 0 | T32: =Elect!BT31 -> 191 | U32: =H32/T32 -> 1.9829319 | V32: =Elect!BV31 -> 0 | W32: =H32/V32 -> #DIV/0! | X32: =H32*V1 -> 1514.96 | Y32: =IF(X32>0,X32/T32,0) -> 7.9317277 | Z32: =IF(X32>0,X32/V32,0) -> #DIV/0!
A33: 27 | B33: 78685 | C33: =IF(B33>=B32,B33-B32,0)*10*0.58 -> 237.8 | D33: 155361 | E33: =IF(D33>=D32,D33-D32,0)*10*0.58 -> 17.4 | F33: 20507 | G33: =IF(F33>=F32,F33-F32,0)*0.58 -> 0 | H33: =C33+E33+G33 -> 255.2 | O33: =IF(N33>=N32,N33-N32,0) -> 0 | Q33: =(H33-O33)*0.58 -> 148.016 | S33: =IF(R33-R32>0,R33-R32,0) -> 0 | T33: =Elect!BT32 -> 191 | U33: =H33/T33 -> 1.3361257 | V33: =Elect!BV32 -> 0 | W33: =H33/V33 -> #DIV/0! | X33: =H33*V1 -> 1020.8 | Y33: =IF(X33>0,X33/T33,0) -> 5.3445026 | Z33: =IF(X33>0,X33/V33,0) -> #DIV/0!
A34: 28 | B34: 78729 | C34: =IF(B34>=B33,B34-B33,0)*10*0.58 -> 255.2 | D34: 155361 | E34: =IF(D34>=D33,D34-D33,0)*10*0.58 -> 0 | F34: 20507 | G34: =IF(F34>=F33,F34-F33,0)*0.58 -> 0 | H34: =C34+E34+G34 -> 255.2 | O34: =IF(N34>=N33,N34-N33,0) -> 0 | Q34: =(H34-O34)*0.58 -> 148.016 | S34: =IF(R34-R33>0,R34-R33,0) -> 0 | T34: =Elect!BT33 -> 176 | U34: =H34/T34 -> 1.45 | V34: =Elect!BV33 -> 0 | W34: =H34/V34 -> #DIV/0! | X34: =H34*V1 -> 1020.8 | Y34: =IF(X34>0,X34/T34,0) -> 5.8 | Z34: =IF(X34>0,X34/V34,0) -> #DIV/0!
A35: 29 | B35: 78769 | C35: =IF(B35>=B34,B35-B34,0)*10*0.58 -> 232 | D35: 155362 | E35: =IF(D35>=D34,D35-D34,0)*10*0.58 -> 5.8 | F35: 20508 | G35: =IF(F35>=F34,F35-F34,0)*0.58 -> 0.58 | H35: =C35+E35+G35 -> 238.38 | O35: =IF(N35>=N34,N35-N34,0) -> 0 | Q35: =(H35-O35)*0.58 -> 138.2604 | S35: =IF(R35-R34>0,R35-R34,0) -> 0 | T35: =Elect!BT34 -> 175 | U35: =H35/T35 -> 1.3621714 | V35: =Elect!BV34 -> 0 | W35: =H35/V35 -> #DIV/0! | X35: =H35*V1 -> 953.52 | Y35: =IF(X35>0,X35/T35,0) -> 5.4486857 | Z35: =IF(X35>0,X35/V35,0) -> #DIV/0!
A36: 30 | B36: 78818 | C36: =IF(B36>=B35,B36-B35,0)*10*0.58 -> 284.2 | D36: 155362 | E36: =IF(D36>=D35,D36-D35,0)*10*0.58 -> 0 | F36: 20508 | G36: =IF(F36>=F35,F36-F35,0)*0.58 -> 0 | H36: =C36+E36+G36 -> 284.2 | O36: =IF(N36>=N35,N36-N35,0) -> 0 | Q36: =(H36-O36)*0.58 -> 164.836 | S36: =IF(R36-R35>0,R36-R35,0) -> 0 | T36: =Elect!BT35 -> 175 | U36: =H36/T36 -> 1.624 | V36: =Elect!BV35 -> 0 | W36: =H36/V36 -> #DIV/0! | X36: =H36*V1 -> 1136.8 | Y36: =IF(X36>0,X36/T36,0) -> 6.496 | Z36: =IF(X36>0,X36/V36,0) -> #DIV/0!
A37: 31 | B37: 78818 | C37: =IF(B37>=B36,B37-B36,0)*10*0.58 -> 0 | D37: 155362 | E37: =IF(D37>=D36,D37-D36,0)*10*0.58 -> 0 | F37: 20508 | G37: =IF(F37>=F36,F37-F36,0)*0.58 -> 0 | H37: =C37+E37+G37 -> 0 | I37: 224 | K37: 3322 | O37: =IF(N37>=N36,N37-N36,0) -> 0 | Q37: =(H37-O37)*0.58 -> 0 | S37: =IF(R37-R36>0,R37-R36,0) -> 0 | T37: =Elect!BT36 -> 0 | U37: =H37/T37 -> #DIV/0! | V37: =Elect!BV36 -> 0 | W37: =H37/V37 -> #DIV/0! | X37: =H37*V7 -> 0 | Y37: =IF(X37>0,X37/T37,0) -> 0 | Z37: =IF(X37>0,X37/V37,0) -> 0
A38: MTD | C38: =SUM(C7:C37) -> 6977.4 | E38: =SUM(E7:E37) -> 23.2 | G38: =SUM(G7:G37) -> 985.03333 | H38: =SUM(H7:H37) -> 7985.6333 | I38: =I37-I6 -> 4 | K38: =K37-K6 -> 111 | O38: =SUM(O7:O36) -> 0 | Q38: =SUM(Q7:Q34) -> 4328.5709 | S38: =SUM(S7:S34) -> 0 | T38: =SUM(T7:T36) -> 4814 | U38: =IF(H38>0,H38/T38,0) -> 1.6588353 | V38: =SUM(V7:V36) -> 0 | W38: =IF(H38>0,H38/V38,0) -> #DIV/0! | X38: =SUM(X7:X36) -> 31942.533 | Y38: =IF(X38>0,X38/T38,0) -> 6.6353414 | Z38: =IF(X38>0,X38/V38,0) -> #DIV/0!
A39: AVER. Act | C39: =C38/B48 -> 232.58 | E39: =E38/B48 -> 0.77333333 | G39: =G38/B48 -> 32.834444 | H39: =H38/B48 -> 266.18778 | O39: =O38/B48 -> 0 | Q39: =Q38/B48 -> 144.2857 | S39: =S38/C48 -> #DIV/0! | T39: =T38/B48 -> 160.46667 | U39: =IF(H39>0,H39/T39,0) -> 1.6588353 | V39: =V38/B48 -> 0 | W39: =IF(H39>0,H39/V39,0) -> #DIV/0! | X39: =X38/B48 -> 1064.7511 | Y39: =IF(X39>0,X39/T39,0) -> 6.6353414 | Z39: =IF(X39>0,X39/V39,0) -> #DIV/0!
A40: TOTAL Budget | T40: =YTD!Q2341 -> 0 | U40: =IF(#REF!>0,#REF!/T40,0) -> #REF! | V40: =YTD!Q2342 -> 0 | W40: =IF(#REF!>0,#REF!/V40,0) -> #REF! | X40: =YTD!Q2346 -> 0 | Y40: =IF(X40>0,X40/T40,0) -> 0 | Z40: =IF(X40>0,X40/V40,0) -> 0
A41: Budget MTD | T41: =T42*C48 -> #VALUE! | U41: =IF(#REF!>0,#REF!/T41,0) -> #REF! | V41: =V42*C48 -> #VALUE! | W41: =IF(#REF!>0,#REF!/V41,0) -> #REF! | X41: =#REF!*5.62 -> #REF! | Y41: =IF(X41>0,X41/T41,0) -> #REF! | Z41: =IF(X41>0,X41/V41,0) -> #REF!
A42: AVER. Bud | T42: =T40/$A$48 -> #VALUE! | V42: =V40/$A$48 -> #VALUE!
A43: Total RFC | T43: =YTD!Q2358 -> 0 | V43: =YTD!Q2359 -> 0 | X43: =YTD!Q2363 -> 0 | Y43: =IF(X43>0,X43/T43,0) -> 0 | Z43: =IF(X43>0,X43/V43,0) -> 0
A44: RFC MTD | T44: =T43/A48*C48 -> #VALUE! | V44: =V43/A48*C48 -> #VALUE! | X44: =X43/A48*C48 -> #VALUE! | Y44: =IF(X44>0,X44/T44,0) -> #VALUE! | Z44: =IF(X44>0,X44/V44,0) -> #VALUE!
A45: AVER RFC | T45: =T43/A48 -> #VALUE! | V45: =V44/A48*C48 -> #VALUE! | X45: =X43/A48 -> #VALUE!
A46: MTD 13 | U46: =Consp!BH33 -> 1.1514679 | W46: =Consp!BI33 -> 0.57929342 | X46: =Consp!BJ33 -> 140121.3 | Y46: =Consp!BK33 -> 6.8331854 | Z46: =Consp!BL33 -> 3.4377159
A47: AVER. Act 13 | U47: =Consp!BH34 -> 1.1761372 | W47: =Consp!BI34 -> 0.60007377 | X47: =Consp!BJ34 -> 5004.3322 | Y47: =Consp!BK34 -> 6.8331854 | Z47: =Consp!BL34 -> 3.4377159
A48: No of Days MTD | B48: =COUNTIF(B7:B36,">0") -> 30
A136: Water Incoming

Sheet Consp
A1: =Elect!A1 -> June | L1: Summary | P1: =Elect!A1 -> June
B2: Elect Consuumption | H2: Water Incoming | U2: Water Consumption | AC2: Irrigation | AG2: Gas | AJ2: Cost | AK2: Solar Meter [ LIT ] | AL2: No. of Eng. | AM2: No. of Gardners | AN2: Cons. (lit) | AO2: Received Gas (tons) | AP2: Fuel Cost | AQ2: Solar level [cm] | AR2: Received Solar (tons) | AS2: Fuel Cost | AT2: Occupancy 10 | AV2: Occupancy07 | AZ2: Elect 2009 | BE2: Elect 2010 | BJ2: Water 2009 | BO2: Water 2010
A3: Date | B3: COUNTER (2) | D3: MD | F3: KVAR | H3: R.O | J3: Qenna | L3: Trucks | N3: Rimievera Line Meter | O3: Total Inc. | Q3: Total Main S.Pool | S3: Total Bar & Beach cons. | U3: Total S. Pool cons. | W3: Hotel consumption. | Y3: Sold Water | AA3: Irr. Water from R.O | AC3: Irr. Consumption. | AE3: Storage Water One tank | AF3: Grand Cons | AG3: % | AH3: Stock | AI3: Cons. | AJ3: 0 | AT3: No of guest | AU3: No. of rooms | AV3: No. of rooms | AW3: No. of guest | AX3: Cons. Per occ. room | AY3: Cons. Per guest | AZ3: Total cost | BA3: cost per room | BB3: cost per guest | BC3: Cons. Per occ. room | BD3: Cons. Per guest | BE3: Total cost | BF3: cost per room | BG3: cost per guest | BH3: Cons. Per occ. room | BI3: Cons. Per guest | BJ3: Total cost | BK3: cost per room | BL3: cost per guest | BM3: Cons. Per occ. room | BN3: Cons. Per guest | BO3: Total cost | BP3: cost per room | BQ3: cost per guest
B4: 2013 | C4: 2014 | D4: 2013 | E4: 2014 | F4: 2013 | G4: 2014 | H4: 2013 | I4: 2014 | J4: 2009 | K4: 2010 | L4: 2009 | M4: 2010 | O4: 2009 | P4: 2010 | Q4: 2009 | R4: 2010 | S4: 2009 | T4: 2010 | U4: 2009 | V4: 2010 | W4: 2009 | X4: 2010 | Y4: 2009 | Z4: 2010 | AA4: 2009 | AB4: 2010 | AC4: 2009 | AD4: 2010
A5: 1 | B5: 33600 | C5: =Elect!J6 -> 4739 | D5: 0 | E5: =Elect!M6 -> 1509 | F5: 20 | G5: =Elect!O6 -> 1597 | H5: 800 | I5: =Water!C7 -> 203 | J5: 0 | K5: =Water!E7 -> 0 | L5: 0 | M5: =Water!#REF! -> #REF! | N5: =Water!#REF! -> #REF! | O5: 1005 | P5: =Water!H7 -> 213.44 | Q5: 114 | R5: =Water!O7 -> 0 | S5: 13 | T5: =Water!#REF! -> #REF! | U5: 147 | V5: =Water!#REF! -> #REF! | W5: 755 | X5: =Water!Q7 -> 123.7952 | Y5: 0 | Z5: =Water!#REF! -> #REF! | AA5: 0 | AB5: 0 | AC5: 690 | AD5: =Water!#REF! -> #REF! | AE5: =Water!#REF! -> #REF! | AF5: =Water!#REF! -> #REF! | AG5: =Gas!#REF! -> #REF! | AH5: =Gas!C7 -> 941.28 | AI5: =Gas!#REF! -> #REF! | AJ5: =Gas!J7 -> 296.4 | AK5: =Gas!#REF! -> #REF! | AL5: =Gas!#REF! -> #REF! | AM5: =Gas!#REF! -> #REF! | AN5: =Gas!#REF! -> #REF! | AO5: =Gas!#REF! -> #REF! | AP5: =Gas!#REF! -> #REF! | AQ5: =Gas!#REF! -> #REF! | AR5: =Gas!#REF! -> #REF! | AS5: =Gas!#REF! -> #REF! | AT5: =Elect!BR6 -> 226 | AU5: =Elect!BP6 -> 128 | AV5: =Elect!#REF! -> #REF! | AW5: =Elect!BR6 -> 226 | AX5: 48.695652 | AY5: 24.705882 | AZ5: 8835.4834 | BA5: 12.805048 | BB5: 6.496679 | BC5: =Elect!#REF! -> #REF! | BD5: =Elect!#REF! -> #REF! | BE5: =Elect!#REF! -> #REF! | BF5: =Elect!#REF! -> #REF! | BG5: =Elect!#REF! -> #REF! | BH5: 1.142029 | BI5: 0.57941176 | BJ5: 4569.1158 | BK5: 6.6219069 | BL5: 3.3596439 | BM5: =Water!U7 -> 2.2706383 | BN5: =Water!W7 -> #DIV/0! | BO5: =Water!X7 -> 853.76 | BP5: =Water!Y7 -> 9.0825532 | BQ5: =Water!Z7 -> 0
A6: 2 | B6: 31200 | C6: =Elect!J7 -> 4842 | D6: 0 | E6: =Elect!M7 -> 1380 | F6: 20 | G6: =Elect!O7 -> 1556 | H6: 936 | I6: =Water!C8 -> 226.2 | J6: 0 | K6: =Water!E8 -> 0 | L6: 0 | M6: =Water!#REF! -> #REF! | N6: =Water!#REF! -> #REF! | O6: 1006 | P6: =Water!H8 -> 258.68 | Q6: 113 | R6: =Water!O8 -> 0 | S6: 17 | T6: =Water!#REF! -> #REF! | U6: 140 | V6: =Water!#REF! -> #REF! | W6: 792 | X6: =Water!Q8 -> 150.0344 | Y6: 0 | Z6: =Water!#REF! -> #REF! | AA6: 0 | AB6: 0 | AC6: 370 | AD6: =Water!#REF! -> #REF! | AE6: =Water!#REF! -> #REF! | AF6: =Water!#REF! -> #REF! | AG6: =Gas!B7 -> 8086212 | AH6: =Gas!C8 -> 1069.54 | AI6: =Gas!#REF! -> #REF! | AJ6: =Gas!J8 -> 312 | AK6: =Gas!#REF! -> #REF! | AL6: =Gas!#REF! -> #REF! | AM6: =Gas!#REF! -> #REF! | AN6: =Gas!#REF! -> #REF! | AO6: =Gas!#REF! -> #REF! | AP6: =Gas!#REF! -> #REF! | AQ6: =Gas!#REF! -> #REF! | AR6: =Gas!#REF! -> #REF! | AS6: =Gas!#REF! -> #REF! | AT6: =Elect!BR7 -> 212 | AU6: =Elect!BP7 -> 112 | AX6: 47.416413 | AY6: 23.981553 | AZ6: 8299.2754 | BA6: 12.612881 | BB6: 6.379151 | BC6: =Elect!BQ7 -> 476904 | BD6: =Elect!#REF! -> #REF! | BE6: =Elect!#REF! -> #REF! | BF6: =Elect!#REF! -> #REF! | BG6: =Elect!#REF! -> #REF! | BH6: 1.2021277 | BI6: 0.60799385 | BJ6: 5345.8654 | BK6: 8.1244156 | BL6: 4.1090434 | BM6: =Water!U8 -> 2.06944 | BN6: =Water!W8 -> #DIV/0! | BO6: =Water!X8 -> 1034.72 | BP6: =Water!Y8 -> 8.27776 | BQ6: =Water!Z8 -> #DIV/0!
A7: 3 | B7: 31200 | C7: =Elect!J8 -> 4825 | D7: 0 | E7: =Elect!M8 -> 1548 | F7: 20 | G7: =Elect!O8 -> 1569 | H7: 685 | I7: =Water!C9 -> 237.8 | J7: 0 | K7: =Water!E9 -> 0 | L7: 0 | M7: =Water!#REF! -> #REF! | N7: =Water!#REF! -> #REF! | O7: 902 | P7: =Water!H9 -> 258.1 | Q7: 126 | R7: =Water!O9 -> 0 | S7: 26 | T7: =Water!#REF! -> #REF! | U7: 134 | V7: =Water!#REF! -> #REF! | W7: 766 | X7: =Water!Q9 -> 149.698 | Y7: 0 | Z7: =Water!#REF! -> #REF! | AA7: 0 | AB7: 0 | AC7: 740 | AD7: =Water!#REF! -> #REF! | AE7: =Water!#REF! -> #REF! | AF7: =Water!#REF! -> #REF! | AG7: =Gas!B9 -> 8088191 | AH7: =Gas!C9 -> 1028.2 | AI7: =Gas!#REF! -> #REF! | AJ7: =Gas!J9 -> 343.2 | AK7: =Gas!#REF! -> #REF! | AL7: =Gas!#REF! -> #REF! | AM7: =Gas!#REF! -> #REF! | AN7: =Gas!#REF! -> #REF! | AO7: =Gas!#REF! -> #REF! | AP7: =Gas!#REF! -> #REF! | AQ7: =Gas!#REF! -> #REF! | AR7: =Gas!#REF! -> #REF! | AS7: =Gas!#REF! -> #REF! | AT7: =Elect!BR8 -> 223 | AU7: =Elect!BP8 -> 117 | AX7: 47.926267 | AY7: 24.223602 | AZ7: 8299.2754 | BA7: 12.748503 | BB7: 6.4435368 | BC7: =Elect!BQ8 -> 477127 | BD7: =Elect!#REF! -> #REF! | BE7: =Elect!#REF! -> #REF! | BF7: =Elect!#REF! -> #REF! | BG7: =Elect!#REF! -> #REF! | BH7: 1.0875576 | BI7: 0.54968944 | BJ7: 3912.3054 | BK7: 6.0096857 | BL7: 3.0375042 | BM7: =Water!U9 -> 1.9118519 | BN7: =Water!W9 -> #DIV/0! | BO7: =Water!X9 -> 1032.4 | BP7: =Water!Y9 -> 7.6474074 | BQ7: =Water!Z9 -> #DIV/0!
A8: 4 | B8: 33600 | C8: =Elect!J9 -> 4408 | D8: 0 | E8: =Elect!M9 -> 1480 | F8: 20 | G8: =Elect!O9 -> 1224 | H8: 786 | I8: =Water!C10 -> 313.2 | J8: 0 | K8: =Water!E10 -> 0 | L8: 0 | M8: =Water!#REF! -> #REF! | N8: =Water!#REF! -> #REF! | O8: 930 | P8: =Water!H10 -> 336.98 | Q8: 153 | R8: =Water!O10 -> 0 | S8: 46 | T8: =Water!#REF! -> #REF! | U8: 150 | V8: =Water!#REF! -> #REF! | W8: 766 | X8: =Water!Q10 -> 195.4484 | Y8: 0 | Z8: =Water!#REF! -> #REF! | AA8: 0 | AB8: 0 | AC8: 820 | AD8: =Water!#REF! -> #REF! | AE8: =Water!#REF! -> #REF! | AF8: =Water!#REF! -> #REF! | AG8: =Gas!B10 -> 8088993 | AH8: =Gas!C10 -> 850.12 | AI8: =Gas!#REF! -> #REF! | AJ8: =Gas!J10 -> 374.4 | AK8: =Gas!#REF! -> #REF! | AL8: =Gas!#REF! -> #REF! | AM8: =Gas!#REF! -> #REF! | AN8: =Gas!#REF! -> #REF! | AO8: =Gas!#REF! -> #REF! | AP8: =Gas!#REF! -> #REF! | AQ8: =Gas!#REF! -> #REF! | AR8: =Gas!#REF! -> #REF! | AS8: =Gas!#REF! -> #REF! | AT8: =Elect!BR9 -> 198 | AU8: =Elect!BP9 -> 105 | AX8: 51.06383 | AY8: 25.866051 | AZ8: 8835.4834 | BA8: 13.427786 | BB8: 6.8017578 | BC8: =Elect!BQ9 -> 477325 | BD8: =Elect!#REF! -> #REF! | BE8: =Elect!#REF! -> #REF! | BF8: =Elect!#REF! -> #REF! | BG8: =Elect!#REF! -> #REF! | BH8: 1.2218845 | BI8: 0.61893764 | BJ8: 4489.1562 | BK8: 6.8224259 | BL8: 3.4558555 | BM8: =Water!U10 -> 1.9706433 | BN8: =Water!W10 -> #DIV/0! | BO8: =Water!X10 -> 1347.92 | BP8: =Water!Y10 -> 7.8825731 | BQ8: =Water!Z10 -> #DIV/0!
A9: 5 | B9: 31200 | C9: =Elect!J10 -> 4951 | D9: 0 | E9: =Elect!M10 -> 1628 | F9: 20 | G9: =Elect!O10 -> 1416 | H9: 789 | I9: =Water!C11 -> 249.4 | J9: 0 | K9: =Water!E11 -> 0 | L9: 0 | M9: =Water!#REF! -> #REF! | N9: =Water!#REF! -> #REF! | O9: 1003 | P9: =Water!H11 -> 276.66 | Q9: 102 | R9: =Water!O11 -> 0 | S9: 8 | T9: =Water!#REF! -> #REF! | U9: 130 | V9: =Water!#REF! -> #REF! | W9: 735 | X9: =Water!Q11 -> 160.4628 | Y9: 0 | Z9: =Water!#REF! -> #REF! | AA9: 0 | AB9: 0 | AC9: 640 | AD9: =Water!#REF! -> #REF! | AE9: =Water!#REF! -> #REF! | AF9: =Water!#REF! -> #REF! | AG9: =Gas!B11 -> 8090021 | AH9: =Gas!C11 -> 1089.68 | AI9: =Gas!#REF! -> #REF! | AJ9: =Gas!J11 -> 393.9 | AK9: =Gas!#REF! -> #REF! | AL9: =Gas!#REF! -> #REF! | AM9: =Gas!#REF! -> #REF! | AN9: =Gas!#REF! -> #REF! | AO9: =Gas!#REF! -> #REF! | AP9: =Gas!#REF! -> #REF! | AQ9: =Gas!#REF! -> #REF! | AR9: =Gas!#REF! -> #REF! | AS9: =Gas!#REF! -> #REF! | AT9: =Elect!BR10 -> 210 | AU9: =Elect!BP10 -> 104 | AX9: 49.840256 | AY9: 25.181598 | AZ9: 8299.2754 | BA9: 13.257628 | BB9: 6.698366 | BC9: =Elect!BQ10 -> 477535 | BD9: =Elect!#REF! -> #REF! | BE9: =Elect!#REF! -> #REF! | BF9: =Elect!#REF! -> #REF! | BG9: =Elect!#REF! -> #REF! | BH9: 1.1980831 | BI9: 0.60532688 | BJ9: 4506.2904 | BK9: 7.198547 | BL9: 3.6370383 | BM9: =Water!U11 -> 1.729125 | BN9: =Water!W11 -> #DIV/0! | BO9: =Water!X11 -> 1106.64 | BP9: =Water!Y11 -> 6.9165 | BQ9: =Water!Z11 -> #DIV/0!
A10: 6 | B10: 33600 | C10: =Elect!J11 -> 5148 | D10: 0 | E10: =Elect!M11 -> 1628 | F10: 20 | G10: =Elect!O11 -> 1575 | H10: 805 | I10: =Water!C12 -> 208.8 | J10: 0 | K10: =Water!E12 -> 0 | L10: 0 | M10: =Water!#REF! -> #REF! | N10: =Water!#REF! -> #REF! | O10: 1004 | P10: =Water!H12 -> 232.58 | Q10: 115 | R10: =Water!O12 -> 0 | S10: 21 | T10: =Water!#REF! -> #REF! | U10: 141 | V10: =Water!#REF! -> #REF! | W10: 725 | X10: =Water!Q12 -> 134.8964 | Y10: 0 | Z10: =Water!#REF! -> #REF! | AA10: 0 | AB10: 0 | AC10: 510 | AD10: =Water!#REF! -> #REF! | AE10: =Water!#REF! -> #REF! | AF10: =Water!#REF! -> #REF! | AG10: =Gas!B12 -> 8091023 | AH10: =Gas!C12 -> 1062.12 | AI10: =Gas!#REF! -> #REF! | AJ10: =Gas!J12 -> 413.4 | AK10: =Gas!#REF! -> #REF! | AL10: =Gas!#REF! -> #REF! | AM10: =Gas!#REF! -> #REF! | AN10: =Gas!#REF! -> #REF! | AO10: =Gas!#REF! -> #REF! | AP10: =Gas!#REF! -> #REF! | AQ10: =Gas!#REF! -> #REF! | AR10: =Gas!#REF! -> #REF! | AS10: =Gas!#REF! -> #REF! | AT10: =Elect!BR11 -> 209 | AU10: =Elect!BP11 -> 112 | AX10: 47.457627 | AY10: 23.512946 | AZ10: 8835.4834 | BA10: 12.479496 | BB10: 6.1829835 | BC10: =Elect!BQ11 -> 477744 | BD10: =Elect!#REF! -> #REF! | BE10: =Elect!#REF! -> #REF! | BF10: =Elect!#REF! -> #REF! | BG10: =Elect!#REF! -> #REF! | BH10: 1.1567797 | BI10: 0.57312806 | BJ10: 4597.6727 | BK10: 6.4938881 | BL10: 3.2174057 | BM10: =Water!U12 -> 1.5301316 | BN10: =Water!W12 -> #DIV/0! | BO10: =Water!X12 -> 930.32 | BP10: =Water!Y12 -> 6.1205263 | BQ10: =Water!Z12 -> #DIV/0!
A11: 7 | B11: 31200 | C11: =Elect!J12 -> 5028 | D11: 0 | E11: =Elect!M12 -> 1668 | F11: 20 | G11: =Elect!O12 -> 1415 | H11: 871 | I11: =Water!C13 -> 197.2 | J11: 0 | K11: =Water!E13 -> 0 | L11: 0 | M11: =Water!#REF! -> #REF! | N11: =Water!#REF! -> #REF! | O11: 837 | P11: =Water!H13 -> 242.44 | Q11: 113 | R11: =Water!O13 -> 0 | S11: 1 | T11: =Water!#REF! -> #REF! | U11: 151 | V11: =Water!#REF! -> #REF! | W11: 732 | X11: =Water!Q13 -> 140.6152 | Y11: 0 | Z11: =Water!#REF! -> #REF! | AA11: 0 | AB11: 0 | AC11: 1010 | AD11: =Water!#REF! -> #REF! | AE11: =Water!#REF! -> #REF! | AF11: =Water!#REF! -> #REF! | AG11: =Gas!B13 -> 8091901 | AH11: =Gas!C13 -> 930.68 | AI11: =Gas!#REF! -> #REF! | AJ11: =Gas!J13 -> 362.7 | AK11: =Gas!#REF! -> #REF! | AL11: =Gas!#REF! -> #REF! | AM11: =Gas!#REF! -> #REF! | AN11: =Gas!#REF! -> #REF! | AO11: =Gas!#REF! -> #REF! | AP11: =Gas!#REF! -> #REF! | AQ11: =Gas!#REF! -> #REF! | AR11: =Gas!#REF! -> #REF! | AS11: =Gas!#REF! -> #REF! | AT11: =Elect!BR12 -> 211 | AU11: =Elect!BP12 -> 114 | AX11: 43.454039 | AY11: 21.517241 | AZ11: 8299.2754 | BA11: 11.558879 | BB11: 5.7236382 | BC11: =Elect!BQ12 -> 477955 | BD11: =Elect!#REF! -> #REF! | BE11: =Elect!#REF! -> #REF! | BF11: =Elect!#REF! -> #REF! | BG11: =Elect!#REF! -> #REF! | BH11: 1.1713092 | BI11: 0.58 | BJ11: 4974.6248 | BK11: 6.9284468 | BL11: 3.4307757 | BM11: =Water!U13 -> 1.5058385 | BN11: =Water!W13 -> #DIV/0! | BO11: =Water!X13 -> 969.76 | BP11: =Water!Y13 -> 6.023354 | BQ11: =Water!Z13 -> #DIV/0!
A12: 8 | B12: 33600 | C12: =Elect!J13 -> 5556 | D12: 0 | E12: =Elect!M13 -> 1846 | F12: 20 | G12: =Elect!O13 -> 1606 | H12: 963 | I12: =Water!C14 -> 208.8 | J12: 0 | K12: =Water!E14 -> 0 | L12: 0 | M12: =Water!#REF! -> #REF! | N12: =Water!#REF! -> #REF! | O12: 1000 | P12: =Water!H14 -> 245.92 | Q12: 128 | R12: =Water!O14 -> 0 | S12: 24 | T12: =Water!#REF! -> #REF! | U12: 148 | V12: =Water!#REF! -> #REF! | W12: 719 | X12: =Water!Q14 -> 142.6336 | Y12: 0 | Z12: =Water!#REF! -> #REF! | AA12: 0 | AB12: 0 | AC12: 630 | AD12: =Water!#REF! -> #REF! | AE12: =Water!#REF! -> #REF! | AF12: =Water!#REF! -> #REF! | AG12: =Gas!B14 -> 8092262 | AH12: =Gas!C14 -> 382.66 | AI12: =Gas!#REF! -> #REF! | AJ12: =Gas!J14 -> 354.9 | AK12: =Gas!#REF! -> #REF! | AL12: =Gas!#REF! -> #REF! | AM12: =Gas!#REF! -> #REF! | AN12: =Gas!#REF! -> #REF! | AO12: =Gas!#REF! -> #REF! | AP12: =Gas!#REF! -> #REF! | AQ12: =Gas!#REF! -> #REF! | AR12: =Gas!#REF! -> #REF! | AS12: =Gas!#REF! -> #REF! | AT12: =Elect!BR13 -> 222 | AU12: =Elect!BP13 -> 114 | AX12: 48.837209 | AY12: 24.086022 | AZ12: 8835.4834 | BA12: 12.842272 | BB12: 6.3336799 | BC12: =Elect!BQ13 -> 478177 | BD12: =Elect!#REF! -> #REF! | BE12: =Elect!#REF! -> #REF! | BF12: =Elect!#REF! -> #REF! | BG12: =Elect!#REF! -> #REF! | BH12: 1.2194767 | BI12: 0.60143369 | BJ12: 5500.0731 | BK12: 7.9942923 | BL12: 3.9427047 | BM12: =Water!U14 -> 2.7024176 | BN12: =Water!W14 -> #DIV/0! | BO12: =Water!X14 -> 983.68 | BP12: =Water!Y14 -> 10.80967 | BQ12: =Water!Z14 -> #DIV/0!
A13: 9 | B13: 33600 | C13: =Elect!J14 -> 4703 | D13: 0 | E13: =Elect!M14 -> 1651 | F13: 20 | G13: =Elect!O14 -> 1427 | H13: 790 | I13: =Water!C15 -> 201.06667 | J13: 0 | K13: =Water!E15 -> 0 | L13: 0 | M13: =Water!#REF! -> #REF! | N13: =Water!#REF! -> #REF! | O13: 841 | P13: =Water!H15 -> 243.6 | Q13: 127 | R13: =Water!O15 -> 0 | S13: 21 | T13: =Water!#REF! -> #REF! | U13: 139 | V13: =Water!#REF! -> #REF! | W13: 701 | X13: =Water!Q15 -> 141.288 | Y13: 0 | Z13: =Water!#REF! -> #REF! | AA13: 0 | AB13: 0 | AC13: 440 | AD13: =Water!#REF! -> #REF! | AE13: =Water!#REF! -> #REF! | AF13: =Water!#REF! -> #REF! | AG13: =Gas!B15 -> 8093510 | AH13: =Gas!C15 -> 1322.88 | AI13: =Gas!#REF! -> #REF! | AJ13: =Gas!J15 -> 70.2 | AK13: =Gas!#REF! -> #REF! | AL13: =Gas!#REF! -> #REF! | AM13: =Gas!#REF! -> #REF! | AN13: =Gas!#REF! -> #REF! | AO13: =Gas!#REF! -> #REF! | AP13: =Gas!#REF! -> #REF! | AQ13: =Gas!#REF! -> #REF! | AR13: =Gas!#REF! -> #REF! | AS13: =Gas!#REF! -> #REF! | AT13: =Elect!BR14 -> 202 | AU13: =Elect!BP14 -> 96 | AX13: 49.194729 | AY13: 24.1033 | AZ13: 8835.4834 | BA13: 12.936286 | BB13: 6.3382234 | BC13: =Elect!BQ14 -> 478379 | BD13: =Elect!#REF! -> #REF! | BE13: =Elect!#REF! -> #REF! | BF13: =Elect!#REF! -> #REF! | BG13: =Elect!#REF! -> #REF! | BH13: 1.1903367 | BI13: 0.58321377 | BJ13: 4512.0018 | BK13: 6.606152 | BL13: 3.2367301 | BM13: =Water!U15 -> 1.5615385 | BN13: =Water!W15 -> #DIV/0! | BO13: =Water!X15 -> 974.4 | BP13: =Water!Y15 -> 6.2461538 | BQ13: =Water!Z15 -> #DIV/0!
A14: 10 | B14: 31200 | C14: =Elect!J15 -> 4927 | D14: 0 | E14: =Elect!M15 -> 1692 | F14: 20 | G14: =Elect!O15 -> 1466 | H14: 792 | I14: =Water!C16 -> 291.93333 | J14: 0 | K14: =Water!E16 -> 0 | L14: 0 | M14: =Water!#REF! -> #REF! | N14: =Water!#REF! -> #REF! | O14: 972 | P14: =Water!H16 -> 291.93333 | Q14: 126 | R14: =Water!O16 -> 0 | S14: 18 | T14: =Water!#REF! -> #REF! | U14: 145 | V14: =Water!#REF! -> #REF! | W14: 756 | X14: =Water!Q16 -> 169.32133 | Y14: 0 | Z14: =Water!#REF! -> #REF! | AA14: 0 | AB14: 0 | AC14: 580 | AD14: =Water!#REF! -> #REF! | AE14: =Water!#REF! -> #REF! | AF14: =Water!#REF! -> #REF! | AG14: =Gas!B16 -> 8094000 | AH14: =Gas!C16 -> 519.4 | AI14: =Gas!#REF! -> #REF! | AJ14: =Gas!J16 -> 237.9 | AK14: =Gas!#REF! -> #REF! | AL14: =Gas!#REF! -> #REF! | AM14: =Gas!#REF! -> #REF! | AN14: =Gas!#REF! -> #REF! | AO14: =Gas!#REF! -> #REF! | AP14: =Gas!#REF! -> #REF! | AQ14: =Gas!#REF! -> #REF! | AR14: =Gas!#REF! -> #REF! | AS14: =Gas!#REF! -> #REF! | AT14: =Elect!BR15 -> 220 | AU14: =Elect!BP15 -> 112 | AX14: 49.52381 | AY14: 24.781573 | AZ14: 8299.2754 | BA14: 13.173453 | BB14: 6.5919582 | BC14: =Elect!BQ15 -> 478599 | BD14: =Elect!#REF! -> #REF! | BE14: =Elect!#REF! -> #REF! | BF14: =Elect!#REF! -> #REF! | BG14: =Elect!#REF! -> #REF! | BH14: 1.2730159 | BI14: 0.6370135 | BJ14: 4469.9646 | BK14: 7.0951819 | BL14: 3.5504087 | BM14: =Water!U16 -> 1.895671 | BN14: =Water!W16 -> #DIV/0! | BO14: =Water!X16 -> 1167.7333 | BP14: =Water!Y16 -> 7.582684 | BQ14: =Water!Z16 -> #DIV/0!
A15: 11 | B15: 33600 | C15: =Elect!J16 -> 5329 | D15: 0 | E15: =Elect!M16 -> 1692 | F15: 20 | G15: =Elect!O16 -> 1450 | H15: 817 | I15: =Water!C17 -> 179.8 | J15: 0 | K15: =Water!E17 -> 0 | L15: 0 | M15: =Water!#REF! -> #REF! | N15: =Water!#REF! -> #REF! | O15: 875 | P15: =Water!H17 -> 179.8 | Q15: 122 | R15: =Water!O17 -> 0 | S15: 20 | T15: =Water!#REF! -> #REF! | U15: 156 | V15: =Water!#REF! -> #REF! | W15: 712 | X15: =Water!Q17 -> 104.284 | Y15: 0 | Z15: =Water!#REF! -> #REF! | AA15: 0 | AB15: 0 | AC15: 850 | AD15: =Water!#REF! -> #REF! | AE15: =Water!#REF! -> #REF! | AF15: =Water!#REF! -> #REF! | AG15: =Gas!#REF! -> #REF! | AH15: =Gas!C17 -> 1094.98 | AI15: =Gas!#REF! -> #REF! | AJ15: =Gas!J17 -> 292.5 | AK15: =Gas!#REF! -> #REF! | AL15: =Gas!#REF! -> #REF! | AM15: =Gas!#REF! -> #REF! | AN15: =Gas!#REF! -> #REF! | AO15: =Gas!#REF! -> #REF! | AP15: =Gas!#REF! -> #REF! | AQ15: =Gas!#REF! -> #REF! | AR15: =Gas!#REF! -> #REF! | AS15: =Gas!#REF! -> #REF! | AT15: =Elect!BR16 -> 203 | AU15: =Elect!BP16 -> 98 | AX15: 53.333333 | AY15: 26.751592 | AZ15: 8835.4834 | BA15: 14.024577 | BB15: 7.0346206 | BC15: =Elect!BQ16 -> 478802 | BD15: =Elect!#REF! -> #REF! | BE15: =Elect!#REF! -> #REF! | BF15: =Elect!#REF! -> #REF! | BG15: =Elect!#REF! -> #REF! | BH15: 1.3460317 | BI15: 0.67515924 | BJ15: 4666.2095 | BK15: 7.4066817 | BL15: 3.7151349 | BM15: =Water!U17 -> 1.0963415 | BN15: =Water!W17 -> #DIV/0! | BO15: =Water!X17 -> 719.2 | BP15: =Water!Y17 -> 4.3853659 | BQ15: =Water!Z17 -> #DIV/0!
A16: 12 | B16: 33600 | C16: =Elect!J17 -> 5210 | D16: 0 | E16: =Elect!M17 -> 1791 | F16: 20 | G16: =Elect!O17 -> 1543 | H16: 907 | I16: =Water!C18 -> 336.4 | J16: 0 | K16: =Water!E18 -> 0 | L16: 0 | M16: =Water!#REF! -> #REF! | N16: =Water!#REF! -> #REF! | O16: 965 | P16: =Water!H18 -> 336.4 | Q16: 125 | R16: =Water!O18 -> 0 | S16: 4 | T16: =Water!#REF! -> #REF! | U16: 167 | V16: =Water!#REF! -> #REF! | W16: 705 | X16: =Water!Q18 -> 195.112 | Y16: 0 | Z16: =Water!#REF! -> #REF! | AA16: 0 | AB16: 0 | AC16: 880 | AD16: =Water!#REF! -> #REF! | AE16: =Water!#REF! -> #REF! | AF16: =Water!#REF! -> #REF! | AG16: =Gas!B18 -> 8096159 | AH16: =Gas!C18 -> 1193.56 | AI16: =Gas!#REF! -> #REF! | AJ16: =Gas!J18 -> 249.6 | AK16: =Gas!#REF! -> #REF! | AL16: =Gas!#REF! -> #REF! | AM16: =Gas!#REF! -> #REF! | AN16: =Gas!#REF! -> #REF! | AO16: =Gas!#REF! -> #REF! | AP16: =Gas!#REF! -> #REF! | AQ16: =Gas!#REF! -> #REF! | AR16: =Gas!#REF! -> #REF! | AS16: =Gas!#REF! -> #REF! | AT16: =Elect!BR17 -> 212 | AU16: =Elect!BP17 -> 103 | AX16: 50.45045 | AY16: 25.339367 | AZ16: 8835.4834 | BA16: 13.266492 | BB16: 6.6632605 | BC16: =Elect!BQ17 -> 479014 | BD16: =Elect!#REF! -> #REF! | BE16: =Elect!#REF! -> #REF! | BF16: =Elect!#REF! -> #REF! | BG16: =Elect!#REF! -> #REF! | BH16: 1.2162162 | BI16: 0.61085973 | BJ16: 5180.235 | BK16: 7.7781306 | BL16: 3.9066629 | BM16: =Water!U18 -> 2.2884354 | BN16: =Water!W18 -> #DIV/0! | BO16: =Water!X18 -> 1345.6 | BP16: =Water!Y18 -> 9.1537415 | BQ16: =Water!Z18 -> #DIV/0!
A17: 13 | B17: 31200 | C17: =Elect!J18 -> 5191 | D17: 0 | E17: =Elect!M18 -> 1774 | F17: 20 | G17: =Elect!O18 -> 1540 | H17: 812 | I17: =Water!C19 -> 168.2 | J17: 0 | K17: =Water!E19 -> 0 | L17: 0 | M17: =Water!#REF! -> #REF! | N17: =Water!#REF! -> #REF! | O17: 822 | P17: =Water!H19 -> 168.2 | Q17: 123 | R17: =Water!O19 -> 0 | S17: 7 | T17: =Water!#REF! -> #REF! | U17: 163 | V17: =Water!#REF! -> #REF! | W17: 692 | X17: =Water!Q19 -> 97.556 | Y17: 0 | Z17: =Water!#REF! -> #REF! | AA17: 0 | AB17: 0 | AC17: 460 | AD17: =Water!#REF! -> #REF! | AE17: =Water!#REF! -> #REF! | AF17: =Water!#REF! -> #REF! | AG17: =Gas!B19 -> 8096892 | AH17: =Gas!C19 -> 776.98 | AI17: =Gas!#REF! -> #REF! | AJ17: =Gas!J19 -> 245.7 | AK17: =Gas!#REF! -> #REF! | AL17: =Gas!#REF! -> #REF! | AM17: =Gas!#REF! -> #REF! | AN17: =Gas!#REF! -> #REF! | AO17: =Gas!#REF! -> #REF! | AP17: =Gas!#REF! -> #REF! | AQ17: =Gas!#REF! -> #REF! | AR17: =Gas!#REF! -> #REF! | AS17: =Gas!#REF! -> #REF! | AT17: =Elect!BR18 -> 204 | AU17: =Elect!BP18 -> 106 | AX17: 46.567164 | AY17: 23.214286 | AZ17: 8299.2754 | BA17: 12.386978 | BB17: 6.1750561 | BC17: =Elect!BQ18 -> 479218 | BD17: =Elect!#REF! -> #REF! | BE17: =Elect!#REF! -> #REF! | BF17: =Elect!#REF! -> #REF! | BG17: =Elect!#REF! -> #REF! | BH17: 1.0850746 | BI17: 0.54092262 | BJ17: 4637.6525 | BK17: 6.9218694 | BL17: 3.4506343 | BM17: =Water!U19 -> 1.2839695 | BN17: =Water!W19 -> #DIV/0! | BO17: =Water!X19 -> 672.8 | BP17: =Water!Y19 -> 5.1358779 | BQ17: =Water!Z19 -> #DIV/0!
A18: 14 | B18: 33600 | C18: =Elect!J19 -> 4993 | D18: 0 | E18: =Elect!M19 -> 1674 | F18: 30 | G18: =Elect!O19 -> 1604 | H18: 810 | I18: =Water!C20 -> 232 | J18: 0 | K18: =Water!E20 -> 0 | L18: 0 | M18: =Water!#REF! -> #REF! | N18: =Water!#REF! -> #REF! | O18: 943 | P18: =Water!H20 -> 232 | Q18: 118 | R18: =Water!O20 -> 0 | S18: 18 | T18: =Water!#REF! -> #REF! | U18: 152 | V18: =Water!#REF! -> #REF! | W18: 708 | X18: =Water!Q20 -> 134.56 | Y18: 0 | Z18: =Water!#REF! -> #REF! | AA18: 0 | AB18: 0 | AC18: 490 | AD18: =Water!#REF! -> #REF! | AE18: =Water!#REF! -> #REF! | AF18: =Water!#REF! -> #REF! | AG18: =Gas!B20 -> 8097844 | AH18: =Gas!C20 -> 1009.12 | AI18: =Gas!#REF! -> #REF! | AJ18: =Gas!J20 -> 627.9 | AK18: =Gas!#REF! -> #REF! | AL18: =Gas!#REF! -> #REF! | AM18: =Gas!#REF! -> #REF! | AN18: =Gas!#REF! -> #REF! | AO18: =Gas!#REF! -> #REF! | AP18: =Gas!#REF! -> #REF! | AQ18: =Gas!#REF! -> #REF! | AR18: =Gas!#REF! -> #REF! | AS18: =Gas!#REF! -> #REF! | AT18: =Elect!BR19 -> 207 | AU18: =Elect!BP19 -> 110 | AX18: 47.795164 | AY18: 24.207493 | AZ18: 8835.4834 | BA18: 12.568255 | BB18: 6.3656221 | BC18: =Elect!BQ6 -> 476692 | BD18: =Elect!#REF! -> #REF! | BE18: =Elect!#REF! -> #REF! | BF18: =Elect!#REF! -> #REF! | BG18: =Elect!#REF! -> #REF! | BH18: 1.1024182 | BI18: 0.55835735 | BJ18: 4626.2297 | BK18: 6.5806966 | BL18: 3.3330185 | BM18: =Water!U20 -> 1.5890411 | BN18: =Water!W20 -> #DIV/0! | BO18: =Water!X20 -> 928 | BP18: =Water!Y20 -> 6.3561644 | BQ18: =Water!Z20 -> #DIV/0!
A19: 15 | B19: 31200 | C19: =Elect!J20 -> 5550 | D19: 0 | E19: =Elect!M20 -> 1671 | F19: 20 | G19: =Elect!O20 -> 1648 | H19: 841 | I19: =Water!C21 -> 255.2 | J19: 0 | K19: =Water!E21 -> 0 | L19: 0 | M19: =Water!#REF! -> #REF! | N19: =Water!#REF! -> #REF! | O19: 947 | P19: =Water!H21 -> 255.2 | Q19: 131 | R19: =Water!O21 -> 0 | S19: 23 | T19: =Water!#REF! -> #REF! | U19: 166 | V19: =Water!#REF! -> #REF! | W19: 787 | X19: =Water!Q21 -> 148.016 | Y19: 0 | Z19: =Water!#REF! -> #REF! | AA19: 0 | AB19: 0 | AC19: 730 | AD19: =Water!#REF! -> #REF! | AE19: =Water!#REF! -> #REF! | AF19: =Water!#REF! -> #REF! | AG19: =Gas!B21 -> 8098650 | AH19: =Gas!C21 -> 854.36 | AI19: =Gas!#REF! -> #REF! | AJ19: =Gas!J21 -> 136.5 | AK19: =Gas!#REF! -> #REF! | AL19: =Gas!#REF! -> #REF! | AM19: =Gas!#REF! -> #REF! | AN19: =Gas!#REF! -> #REF! | AO19: =Gas!#REF! -> #REF! | AP19: =Gas!#REF! -> #REF! | AQ19: =Gas!#REF! -> #REF! | AR19: =Gas!#REF! -> #REF! | AS19: =Gas!#REF! -> #REF! | AT19: =Elect!BR20 -> 208 | AU19: =Elect!BP20 -> 109 | AX19: 41.6 | AY19: 20.995962 | AZ19: 8299.2754 | BA19: 11.065701 | BB19: 5.5849767 | BC19: =Elect!BQ20 -> 479633 | BD19: =Elect!#REF! -> #REF! | BE19: =Elect!#REF! -> #REF! | BF19: =Elect!#REF! -> #REF! | BG19: =Elect!#REF! -> #REF! | BH19: 1.1506667 | BI19: 0.58114478 | BJ19: 4803.283 | BK19: 6.4043773 | BL19: 3.234534 | BM19: =Water!U21 -> 1.7360544 | BN19: =Water!W21 -> #DIV/0! | BO19: =Water!X21 -> 1020.8 | BP19: =Water!Y21 -> 6.9442177 | BQ19: =Water!Z21 -> #DIV/0!
A20: 16 | B20: 36000 | C20: =Elect!J21 -> 5610 | D20: 0 | E20: =Elect!M21 -> 1811 | F20: 20 | G20: =Elect!O21 -> 1684 | H20: 932 | I20: =Water!C22 -> 243.6 | J20: 0 | K20: =Water!E22 -> 0 | L20: 0 | M20: =Water!#REF! -> #REF! | N20: =Water!#REF! -> #REF! | O20: 998 | P20: =Water!H22 -> 243.6 | Q20: 136 | R20: =Water!O22 -> 0 | S20: 22 | T20: =Water!#REF! -> #REF! | U20: 162 | V20: =Water!#REF! -> #REF! | W20: 703 | X20: =Water!Q22 -> 141.288 | Y20: 0 | Z20: =Water!#REF! -> #REF! | AA20: 0 | AB20: 0 | AC20: 600 | AD20: =Water!#REF! -> #REF! | AE20: =Water!#REF! -> #REF! | AF20: =Water!#REF! -> #REF! | AG20: =Gas!B22 -> 8099527 | AH20: =Gas!C22 -> 929.62 | AI20: =Gas!#REF! -> #REF! | AJ20: =Gas!J22 -> 312 | AK20: =Gas!#REF! -> #REF! | AL20: =Gas!#REF! -> #REF! | AM20: =Gas!#REF! -> #REF! | AN20: =Gas!#REF! -> #REF! | AO20: =Gas!#REF! -> #REF! | AP20: =Gas!#REF! -> #REF! | AQ20: =Gas!#REF! -> #REF! | AR20: =Gas!#REF! -> #REF! | AS20: =Gas!#REF! -> #REF! | AT20: =Elect!BR21 -> 204 | AU20: =Elect!BP21 -> 107 | AX20: 48 | AY20: 24.22611 | AZ20: 9371.6914 | BA20: 12.495589 | BB20: 6.3066564 | BC20: =Elect!BQ21 -> 479837 | BD20: =Elect!#REF! -> #REF! | BE20: =Elect!#REF! -> #REF! | BF20: =Elect!#REF! -> #REF! | BG20: =Elect!#REF! -> #REF! | BH20: 1.1626667 | BI20: 0.58720539 | BJ20: 5323.0199 | BK20: 7.0973598 | BL20: 3.5845252 | BM20: =Water!U22 -> 1.5225 | BN20: =Water!W22 -> #DIV/0! | BO20: =Water!X22 -> 974.4 | BP20: =Water!Y22 -> 6.09 | BQ20: =Water!Z22 -> #DIV/0!
A21: 17 | B21: 33600 | C21: =Elect!J22 -> 5264 | D21: 0 | E21: =Elect!M22 -> 1862 | F21: 20 | G21: =Elect!O22 -> 1585 | H21: 972 | I21: =Water!C23 -> 226.2 | J21: 0 | K21: =Water!E23 -> 0 | L21: 0 | M21: =Water!#REF! -> #REF! | N21: =Water!#REF! -> #REF! | O21: 998 | P21: =Water!H23 -> 226.2 | Q21: 136 | R21: =Water!O23 -> 0 | S21: 38 | T21: =Water!#REF! -> #REF! | U21: 137 | V21: =Water!#REF! -> #REF! | W21: 740 | X21: =Water!Q23 -> 131.196 | Y21: 0 | Z21: =Water!#REF! -> #REF! | AA21: 0 | AB21: 0 | AC21: 690 | AD21: =Water!#REF! -> #REF! | AE21: =Water!#REF! -> #REF! | AF21: =Water!#REF! -> #REF! | AG21: =Gas!B23 -> 8100488 | AH21: =Gas!C23 -> 1018.66 | AI21: =Gas!#REF! -> #REF! | AJ21: =Gas!J23 -> 604.5 | AK21: =Gas!#REF! -> #REF! | AL21: =Gas!#REF! -> #REF! | AM21: =Gas!#REF! -> #REF! | AN21: =Gas!#REF! -> #REF! | AO21: =Gas!#REF! -> #REF! | AP21: =Gas!#REF! -> #REF! | AQ21: =Gas!#REF! -> #REF! | AR21: =Gas!#REF! -> #REF! | AS21: =Gas!#REF! -> #REF! | AT21: =Elect!BR22 -> 208 | AU21: =Elect!BP22 -> 106 | AX21: 44.385733 | AY21: 22.207535 | AZ21: 8835.4834 | BA21: 11.671709 | BB21: 5.8397115 | BC21: =Elect!#REF! -> #REF! | BD21: =Elect!#REF! -> #REF! | BE21: =Elect!#REF! -> #REF! | BF21: =Elect!#REF! -> #REF! | BG21: =Elect!#REF! -> #REF! | BH21: 1.1770145 | BI21: 0.58889623 | BJ21: 5551.4757 | BK21: 7.3335213 | BL21: 3.6691842 | BM21: =Water!U23 -> 1.3464286 | BN21: =Water!W23 -> #DIV/0! | BO21: =Water!X23 -> 904.8 | BP21: =Water!Y23 -> 5.3857143 | BQ21: =Water!Z23 -> #DIV/0!
A22: 18 | B22: 33600 | C22: =Elect!J23 -> 5278 | D22: 0 | E22: =Elect!M23 -> 1747 | F22: 20 | G22: =Elect!O23 -> 1446 | H22: 864 | I22: =Water!C24 -> 237.8 | J22: 0 | K22: =Water!E24 -> 0 | L22: 0 | M22: =Water!#REF! -> #REF! | N22: =Water!#REF! -> #REF! | O22: 1002 | P22: =Water!H24 -> 237.8 | Q22: 118 | R22: =Water!O24 -> 0 | S22: 21 | T22: =Water!#REF! -> #REF! | U22: 133 | V22: =Water!#REF! -> #REF! | W22: 769 | X22: =Water!Q24 -> 137.924 | Y22: 0 | Z22: =Water!#REF! -> #REF! | AA22: 0 | AB22: 0 | AC22: 930 | AD22: =Water!#REF! -> #REF! | AE22: =Water!#REF! -> #REF! | AF22: =Water!#REF! -> #REF! | AG22: =Gas!B24 -> 8101389 | AH22: =Gas!C24 -> 955.06 | AI22: =Gas!#REF! -> #REF! | AJ22: =Gas!J24 -> 280.8 | AK22: =Gas!#REF! -> #REF! | AL22: =Gas!#REF! -> #REF! | AM22: =Gas!#REF! -> #REF! | AN22: =Gas!#REF! -> #REF! | AO22: =Gas!#REF! -> #REF! | AP22: =Gas!#REF! -> #REF! | AQ22: =Gas!#REF! -> #REF! | AR22: =Gas!#REF! -> #REF! | AS22: =Gas!#REF! -> #REF! | AT22: =Elect!BR23 -> 215 | AU22: =Elect!BP23 -> 103 | AX22: 44.680851 | AY22: 22.459893 | AZ22: 8835.4834 | BA22: 11.749313 | BB22: 5.9060718 | BC22: =Elect!BQ23 -> 480260 | BD22: =Elect!#REF! -> #REF! | BE22: =Elect!#REF! -> #REF! | BF22: =Elect!#REF! -> #REF! | BG22: =Elect!#REF! -> #REF! | BH22: 1.1236702 | BI22: 0.56483957 | BJ22: 4934.645 | BK22: 6.562028 | BL22: 3.2985595 | BM22: =Water!U24 -> 1.3435028 | BN22: =Water!W24 -> #DIV/0! | BO22: =Water!X24 -> 951.2 | BP22: =Water!Y24 -> 5.3740113 | BQ22: =Water!Z24 -> #DIV/0!
A23: 19 | B23: 33600 | C23: =Elect!J24 -> 5250 | D23: 0 | E23: =Elect!M24 -> 1725 | F23: 30 | G23: =Elect!O24 -> 1452 | H23: 894 | I23: =Water!C25 -> 237.8 | J23: 0 | K23: =Water!E25 -> 0 | L23: 0 | M23: =Water!#REF! -> #REF! | N23: =Water!#REF! -> #REF! | O23: 944 | P23: =Water!H25 -> 237.8 | Q23: 110 | R23: =Water!O25 -> 0 | S23: 14 | T23: =Water!#REF! -> #REF! | U23: 155 | V23: =Water!#REF! -> #REF! | W23: 721 | X23: =Water!Q25 -> 137.924 | Y23: 0 | Z23: =Water!#REF! -> #REF! | AA23: 0 | AB23: 0 | AC23: 660 | AD23: =Water!#REF! -> #REF! | AE23: =Water!#REF! -> #REF! | AF23: =Water!#REF! -> #REF! | AG23: =Gas!B25 -> 8102259 | AH23: =Gas!C25 -> 922.2 | AI23: =Gas!#REF! -> #REF! | AJ23: =Gas!J25 -> 284.7 | AK23: =Gas!#REF! -> #REF! | AL23: =Gas!#REF! -> #REF! | AM23: =Gas!#REF! -> #REF! | AN23: =Gas!#REF! -> #REF! | AO23: =Gas!#REF! -> #REF! | AP23: =Gas!#REF! -> #REF! | AQ23: =Gas!#REF! -> #REF! | AR23: =Gas!#REF! -> #REF! | AS23: =Gas!#REF! -> #REF! | AT23: =Elect!BR24 -> 209 | AU23: =Elect!BP24 -> 100 | AX23: 44.8 | AY23: 22.44489 | AZ23: 8835.4834 | BA23: 11.780645 | BB23: 5.9021265 | BC23: =Elect!BQ24 -> 480469 | BD23: =Elect!#REF! -> #REF! | BE23: =Elect!#REF! -> #REF! | BF23: =Elect!#REF! -> #REF! | BG23: =Elect!#REF! -> #REF! | BH23: 1.1346667 | BI23: 0.56847027 | BJ23: 5105.9869 | BK23: 6.8079825 | BL23: 3.4108129 | BM23: =Water!U25 -> 1.4588957 | BN23: =Water!W25 -> #DIV/0! | BO23: =Water!X25 -> 951.2 | BP23: =Water!Y25 -> 5.8355828 | BQ23: =Water!Z25 -> #DIV/0!
A24: 20 | B24: 33600 | C24: =Elect!J25 -> 5189 | D24: 0 | E24: =Elect!M25 -> 1831 | F24: 20 | G24: =Elect!O25 -> 1577 | H24: 944 | I24: =Water!C26 -> 237.8 | J24: 0 | K24: =Water!E26 -> 0 | L24: 0 | M24: =Water!#REF! -> #REF! | N24: =Water!#REF! -> #REF! | O24: 1000 | P24: =Water!H26 -> 237.8 | Q24: 138 | R24: =Water!O26 -> 0 | S24: 15 | T24: =Water!#REF! -> #REF! | U24: 165 | V24: =Water!#REF! -> #REF! | W24: 778 | X24: =Water!Q26 -> 137.924 | Y24: 0 | Z24: =Water!#REF! -> #REF! | AA24: 0 | AB24: 0 | AC24: 560 | AD24: =Water!#REF! -> #REF! | AE24: =Water!#REF! -> #REF! | AF24: =Water!#REF! -> #REF! | AG24: =Gas!B26 -> 8103189 | AH24: =Gas!C26 -> 985.8 | AI24: =Gas!#REF! -> #REF! | AJ24: =Gas!J26 -> 358.8 | AK24: =Gas!#REF! -> #REF! | AL24: =Gas!#REF! -> #REF! | AM24: =Gas!#REF! -> #REF! | AN24: =Gas!#REF! -> #REF! | AO24: =Gas!#REF! -> #REF! | AP24: =Gas!#REF! -> #REF! | AQ24: =Gas!#REF! -> #REF! | AR24: =Gas!#REF! -> #REF! | AS24: =Gas!#REF! -> #REF! | AT24: =Elect!BR25 -> 208 | AU24: =Elect!BP25 -> 109 | AX24: 42.857143 | AY24: 21.649485 | AZ24: 8835.4834 | BA24: 11.269749 | BB24: 5.6929661 | BC24: =Elect!BQ25 -> 480677 | BD24: =Elect!#REF! -> #REF! | BE24: =Elect!#REF! -> #REF! | BF24: =Elect!#REF! -> #REF! | BG24: =Elect!#REF! -> #REF! | BH24: 1.1683673 | BI24: 0.59020619 | BJ24: 5391.5566 | BK24: 6.8769855 | BL24: 3.4739411 | BM24: =Water!U26 -> 1.4412121 | BN24: =Water!W26 -> #DIV/0! | BO24: =Water!X26 -> 951.2 | BP24: =Water!Y26 -> 5.7648485 | BQ24: =Water!Z26 -> #DIV/0!
A25: 21 | B25: 36000 | C25: =Elect!J26 -> 5486 | D25: 0 | E25: =Elect!M26 -> 2162 | F25: 20 | G25: =Elect!O26 -> 1871 | H25: 916 | I25: =Water!C27 -> 232 | J25: 0 | K25: =Water!E27 -> 0 | L25: 0 | M25: =Water!#REF! -> #REF! | N25: =Water!#REF! -> #REF! | O25: 998 | P25: =Water!H27 -> 232 | Q25: 186 | R25: =Water!O27 -> 0 | S25: 43 | T25: =Water!#REF! -> #REF! | U25: 176 | V25: =Water!#REF! -> #REF! | W25: 773 | X25: =Water!Q27 -> 134.56 | Y25: 0 | Z25: =Water!#REF! -> #REF! | AA25: 0 | AB25: 0 | AC25: 950 | AD25: =Water!#REF! -> #REF! | AE25: =Water!#REF! -> #REF! | AF25: =Water!#REF! -> #REF! | AG25: =Gas!B27 -> 8104166 | AH25: =Gas!C27 -> 1035.62 | AI25: =Gas!#REF! -> #REF! | AJ25: =Gas!J27 -> 374.4 | AK25: =Gas!#REF! -> #REF! | AL25: =Gas!#REF! -> #REF! | AM25: =Gas!#REF! -> #REF! | AN25: =Gas!#REF! -> #REF! | AO25: =Gas!#REF! -> #REF! | AP25: =Gas!#REF! -> #REF! | AQ25: =Gas!#REF! -> #REF! | AR25: =Gas!#REF! -> #REF! | AS25: =Gas!#REF! -> #REF! | AT25: =Elect!BR26 -> 219 | AU25: =Elect!BP26 -> 108 | AX25: 43.956044 | AY25: 22.222222 | AZ25: 9371.6914 | BA25: 11.442847 | BB25: 5.7849947 | BC25: =Elect!BQ26 -> 480896 | BD25: =Elect!#REF! -> #REF! | BE25: =Elect!#REF! -> #REF! | BF25: =Elect!#REF! -> #REF! | BG25: =Elect!#REF! -> #REF! | BH25: 1.0586081 | BI25: 0.53518519 | BJ25: 5231.6376 | BK25: 6.3878358 | BL25: 3.2294059 | BM25: =Water!U27 -> 1.3410405 | BN25: =Water!W27 -> #DIV/0! | BO25: =Water!X27 -> 928 | BP25: =Water!Y27 -> 5.3641618 | BQ25: =Water!Z27 -> #DIV/0!
A26: 22 | B26: 33600 | C26: =Elect!J27 -> 6482 | D26: 0 | E26: =Elect!M27 -> 1726 | F26: 20 | G26: =Elect!O27 -> 1532 | H26: 931 | I26: =Water!C28 -> 110.2 | J26: 0 | K26: =Water!E28 -> 0 | L26: 0 | M26: =Water!#REF! -> #REF! | N26: =Water!#REF! -> #REF! | O26: 969 | P26: =Water!H28 -> 546.36 | Q26: 151 | R26: =Water!O28 -> 0 | S26: 29 | T26: =Water!#REF! -> #REF! | U26: 157 | V26: =Water!#REF! -> #REF! | W26: 697 | X26: =Water!Q28 -> 316.8888 | Y26: 0 | Z26: =Water!#REF! -> #REF! | AA26: 0 | AB26: 0 | AC26: 700 | AD26: =Water!#REF! -> #REF! | AE26: =Water!#REF! -> #REF! | AF26: =Water!#REF! -> #REF! | AG26: =Gas!B28 -> 8105135 | AH26: =Gas!C28 -> 1027.14 | AI26: =Gas!#REF! -> #REF! | AJ26: =Gas!J28 -> 327.6 | AK26: =Gas!#REF! -> #REF! | AL26: =Gas!#REF! -> #REF! | AM26: =Gas!#REF! -> #REF! | AN26: =Gas!#REF! -> #REF! | AO26: =Gas!#REF! -> #REF! | AP26: =Gas!#REF! -> #REF! | AQ26: =Gas!#REF! -> #REF! | AR26: =Gas!#REF! -> #REF! | AS26: =Gas!#REF! -> #REF! | AT26: =Elect!BR27 -> 252 | AU26: =Elect!BP27 -> 118 | AX26: 39.952438 | AY26: 20.253165 | AZ26: 8835.4834 | BA26: 10.505926 | BB26: 5.3257887 | BC26: =Elect!BQ27 -> 481148 | BD26: =Elect!#REF! -> #REF! | BE26: =Elect!#REF! -> #REF! | BF26: =Elect!#REF! -> #REF! | BG26: =Elect!#REF! -> #REF! | BH26: 1.0903686 | BI26: 0.55274262 | BJ26: 5317.3085 | BK26: 6.3226022 | BL26: 3.2051287 | BM26: =Water!U28 -> 2.9217112 | BN26: =Water!W28 -> #DIV/0! | BO26: =Water!X28 -> 2185.44 | BP26: =Water!Y28 -> 11.686845 | BQ26: =Water!Z28 -> #DIV/0!
A27: 23 | B27: 36000 | C27: =Elect!J28 -> 4017 | D27: 0 | E27: =Elect!M28 -> 1721 | F27: 30 | G27: =Elect!O28 -> 1531 | H27: 1009 | I27: =Water!C29 -> 203 | J27: 0 | K27: =Water!E29 -> 0 | L27: 0 | M27: =Water!#REF! -> #REF! | N27: =Water!#REF! -> #REF! | O27: 902 | P27: =Water!H29 -> 304.5 | Q27: 131 | R27: =Water!O29 -> 0 | S27: 6 | T27: =Water!#REF! -> #REF! | U27: 167 | V27: =Water!#REF! -> #REF! | W27: 748 | X27: =Water!Q29 -> 176.61 | Y27: 0 | Z27: =Water!#REF! -> #REF! | AA27: 0 | AB27: 0 | AC27: 690 | AD27: =Water!#REF! -> #REF! | AE27: =Water!#REF! -> #REF! | AF27: =Water!#REF! -> #REF! | AG27: =Gas!B29 -> 8106130 | AH27: =Gas!C29 -> 1054.7 | AI27: =Gas!#REF! -> #REF! | AJ27: =Gas!J29 -> 296.4 | AK27: =Gas!#REF! -> #REF! | AL27: =Gas!#REF! -> #REF! | AM27: =Gas!#REF! -> #REF! | AN27: =Gas!#REF! -> #REF! | AO27: =Gas!#REF! -> #REF! | AP27: =Gas!#REF! -> #REF! | AQ27: =Gas!#REF! -> #REF! | AR27: =Gas!#REF! -> #REF! | AS27: =Gas!#REF! -> #REF! | AT27: =Elect!BR28 -> 89 | AU27: =Elect!BP28 -> 43 | AX27: 42.755344 | AY27: 21.543986 | AZ27: 9371.6914 | BA27: 11.130275 | BB27: 5.6084329 | BC27: =Elect!BQ28 -> 481237 | BD27: =Elect!#REF! -> #REF! | BE27: =Elect!#REF! -> #REF! | BF27: =Elect!#REF! -> #REF! | BG27: =Elect!#REF! -> #REF! | BH27: 1.0712589 | BI27: 0.53979653 | BJ27: 5762.7973 | BK27: 6.8441773 | BL27: 3.4487117 | BM27: =Water!U29 -> 1.5695876 | BN27: =Water!W29 -> #DIV/0! | BO27: =Water!X29 -> 1218 | BP27: =Water!Y29 -> 6.2783505 | BQ27: =Water!Z29 -> #DIV/0!
A28: 24 | B28: 33600 | C28: =Elect!J29 -> 6195 | D28: 0 | E28: =Elect!M29 -> 1411 | F28: 20 | G28: =Elect!O29 -> 1284 | H28: 891 | I28: =Water!C30 -> 214.6 | J28: 0 | K28: =Water!E30 -> 0 | L28: 0 | M28: =Water!#REF! -> #REF! | N28: =Water!#REF! -> #REF! | O28: 818 | P28: =Water!H30 -> 327.12 | Q28: 221 | R28: =Water!O30 -> 0 | S28: 93 | T28: =Water!#REF! -> #REF! | U28: 191 | V28: =Water!#REF! -> #REF! | W28: 827 | X28: =Water!Q30 -> 189.7296 | Y28: 0 | Z28: =Water!#REF! -> #REF! | AA28: 0 | AB28: 0 | AC28: 470 | AD28: =Water!#REF! -> #REF! | AE28: =Water!#REF! -> #REF! | AF28: =Water!#REF! -> #REF! | AG28: =Gas!B30 -> 8107107 | AH28: =Gas!C30 -> 1035.62 | AI28: =Gas!#REF! -> #REF! | AJ28: =Gas!J30 -> 315.9 | AK28: =Gas!#REF! -> #REF! | AL28: =Gas!#REF! -> #REF! | AM28: =Gas!#REF! -> #REF! | AN28: =Gas!#REF! -> #REF! | AO28: =Gas!#REF! -> #REF! | AP28: =Gas!#REF! -> #REF! | AQ28: =Gas!#REF! -> #REF! | AR28: =Gas!#REF! -> #REF! | AS28: =Gas!#REF! -> #REF! | AT28: =Elect!BR29 -> 201 | AU28: =Elect!BP29 -> 103 | AX28: 39.904988 | AY28: 20.289855 | AZ28: 8835.4834 | BA28: 10.493448 | BB28: 5.3354369 | BC28: =Elect!BQ29 -> 481438 | BD28: =Elect!#REF! -> #REF! | BE28: =Elect!#REF! -> #REF! | BF28: =Elect!#REF! -> #REF! | BG28: =Elect!#REF! -> #REF! | BH28: 1.1104513 | BI28: 0.56461353 | BJ28: 5088.8527 | BK28: 6.043768 | BL28: 3.0729787 | BM28: =Water!U30 -> 1.7126702 | BN28: =Water!W30 -> #DIV/0! | BO28: =Water!X30 -> 1308.48 | BP28: =Water!Y30 -> 6.8506806 | BQ28: =Water!Z30 -> #DIV/0!
A29: 25 | B29: 33600 | C29: =Elect!J30 -> 4983 | D29: 0 | E29: =Elect!M30 -> 1721 | F29: 20 | G29: =Elect!O30 -> 1461 | H29: 1008 | I29: =Water!C31 -> 208.8 | J29: 0 | K29: =Water!E31 -> 0 | L29: 0 | M29: =Water!#REF! -> #REF! | N29: =Water!#REF! -> #REF! | O29: 1290 | P29: =Water!H31 -> 208.8 | Q29: 34 | R29: =Water!O31 -> 0 | S29: 34 | T29: =Water!#REF! -> #REF! | U29: 55 | V29: =Water!#REF! -> #REF! | W29: 681 | X29: =Water!Q31 -> 121.104 | Y29: 0 | Z29: =Water!#REF! -> #REF! | AA29: 0 | AB29: 0 | AC29: 1170 | AD29: =Water!#REF! -> #REF! | AE29: =Water!#REF! -> #REF! | AF29: =Water!#REF! -> #REF! | AG29: =Gas!B31 -> 8108089 | AH29: =Gas!C31 -> 1040.92 | AI29: =Gas!#REF! -> #REF! | AJ29: =Gas!J31 -> 312 | AK29: =Gas!#REF! -> #REF! | AL29: =Gas!#REF! -> #REF! | AM29: =Gas!#REF! -> #REF! | AN29: =Gas!#REF! -> #REF! | AO29: =Gas!#REF! -> #REF! | AP29: =Gas!#REF! -> #REF! | AQ29: =Gas!#REF! -> #REF! | AR29: =Gas!#REF! -> #REF! | AS29: =Gas!#REF! -> #REF! | AT29: =Elect!BR30 -> 203 | AU29: =Elect!BP30 -> 99 | AX29: 39.763314 | AY29: 20.20445 | AZ29: 8835.4834 | BA29: 10.456193 | BB29: 5.3129786 | BC29: =Elect!BQ30 -> 481641 | BD29: =Elect!#REF! -> #REF! | BE29: =Elect!#REF! -> #REF! | BF29: =Elect!#REF! -> #REF! | BG29: =Elect!#REF! -> #REF! | BH29: 1.0059172 | BI29: 0.51112447 | BJ29: 5757.0859 | BK29: 6.8131194 | BL29: 3.4618676 | BM29: =Water!U31 -> 1.0762887 | BN29: =Water!W31 -> #DIV/0! | BO29: =Water!X31 -> 835.2 | BP29: =Water!Y31 -> 4.3051546 | BQ29: =Water!Z31 -> #DIV/0!
A30: 26 | B30: 31200 | C30: =Elect!J31 -> 5138 | D30: 0 | E30: =Elect!M31 -> 2206 | F30: 20 | G30: =Elect!O31 -> 1783 | H30: 760 | I30: =Water!C32 -> 307.4 | J30: 0 | K30: =Water!E32 -> 0 | L30: 0 | M30: =Water!#REF! -> #REF! | N30: =Water!#REF! -> #REF! | O30: 1004 | P30: =Water!H32 -> 378.74 | Q30: 131 | R30: =Water!O32 -> 0 | S30: 33 | T30: =Water!#REF! -> #REF! | U30: 145 | V30: =Water!#REF! -> #REF! | W30: 916 | X30: =Water!Q32 -> 219.6692 | Y30: 0 | Z30: =Water!#REF! -> #REF! | AA30: 0 | AB30: 0 | AC30: 810 | AD30: =Water!#REF! -> #REF! | AE30: =Water!#REF! -> #REF! | AF30: =Water!#REF! -> #REF! | AG30: =Gas!B32 -> 8109268 | AH30: =Gas!C32 -> 1249.74 | AI30: =Gas!#REF! -> #REF! | AJ30: =Gas!J32 -> 347.1 | AK30: =Gas!#REF! -> #REF! | AL30: =Gas!#REF! -> #REF! | AM30: =Gas!#REF! -> #REF! | AN30: =Gas!#REF! -> #REF! | AO30: =Gas!#REF! -> #REF! | AP30: =Gas!#REF! -> #REF! | AQ30: =Gas!#REF! -> #REF! | AR30: =Gas!#REF! -> #REF! | AS30: =Gas!#REF! -> #REF! | AT30: =Elect!BR31 -> 205 | AU30: =Elect!BP31 -> 100 | AX30: 37.275986 | AY30: 18.989653 | AZ30: 8299.2754 | BA30: 9.9155023 | BB30: 5.0512936 | BC30: =Elect!BQ31 -> 481846 | BD30: =Elect!#REF! -> #REF! | BE30: =Elect!#REF! -> #REF! | BF30: =Elect!#REF! -> #REF! | BG30: =Elect!#REF! -> #REF! | BH30: 1.1063321 | BI30: 0.56360316 | BJ30: 4340.66 | BK30: 5.1859737 | BL30: 2.6419111 | BM30: =Water!U32 -> 1.9829319 | BN30: =Water!W32 -> #DIV/0! | BO30: =Water!X32 -> 1514.96 | BP30: =Water!Y32 -> 7.9317277 | BQ30: =Water!Z32 -> #DIV/0!
A31: 27 | B31: 36000 | C31: =Elect!J32 -> 5745 | D31: 0 | E31: =Elect!M32 -> 1674 | F31: 30 | G31: =Elect!O32 -> 1479 | H31: 1010 | I31: =Water!C33 -> 237.8 | J31: 0 | K31: =Water!E33 -> 17.4 | L31: 0 | M31: =Water!#REF! -> #REF! | N31: =Water!#REF! -> #REF! | O31: 1014 | P31: =Water!H33 -> 255.2 | Q31: 151 | R31: =Water!O33 -> 0 | S31: 30 | T31: =Water!#REF! -> #REF! | U31: 139 | V31: =Water!#REF! -> #REF! | W31: 761 | X31: =Water!Q33 -> 148.016 | Y31: 0 | Z31: =Water!#REF! -> #REF! | AA31: 0 | AB31: 0 | AC31: 930 | AD31: =Water!#REF! -> #REF! | AE31: =Water!#REF! -> #REF! | AF31: =Water!#REF! -> #REF! | AG31: =Gas!B33 -> 8109960 | AH31: =Gas!C33 -> 733.52 | AI31: =Gas!#REF! -> #REF! | AJ31: =Gas!J33 -> 198.9 | AK31: =Gas!#REF! -> #REF! | AL31: =Gas!#REF! -> #REF! | AM31: =Gas!#REF! -> #REF! | AN31: =Gas!#REF! -> #REF! | AO31: =Gas!#REF! -> #REF! | AP31: =Gas!#REF! -> #REF! | AQ31: =Gas!#REF! -> #REF! | AR31: =Gas!#REF! -> #REF! | AS31: =Gas!#REF! -> #REF! | AT31: =Elect!BR32 -> 222 | AU31: =Elect!BP32 -> 104 | AX31: 44.063647 | AY31: 22.346369 | AZ31: 9371.6914 | BA31: 11.470859 | BB31: 5.8173131 | BC31: =Elect!BQ32 -> 482068 | BD31: =Elect!#REF! -> #REF! | BE31: =Elect!#REF! -> #REF! | BF31: =Elect!#REF! -> #REF! | BG31: =Elect!#REF! -> #REF! | BH31: 1.1640147 | BI31: 0.59031657 | BJ31: 5768.5087 | BK31: 7.0605981 | BL31: 3.5807006 | BM31: =Water!U33 -> 1.3361257 | BN31: =Water!W33 -> #DIV/0! | BO31: =Water!X33 -> 1020.8 | BP31: =Water!Y33 -> 5.3445026 | BQ31: =Water!Z33 -> #DIV/0!
A32: 28 | B32: 33600 | C32: =Elect!J33 -> 6399 | D32: 0 | E32: =Elect!M33 -> 1904 | F32: 20 | G32: =Elect!O33 -> 1694 | H32: 1008 | I32: =Water!C34 -> 255.2 | J32: 0 | K32: =Water!E34 -> 0 | L32: 1 | M32: =Water!#REF! -> #REF! | N32: =Water!#REF! -> #REF! | O32: 1013 | P32: =Water!H34 -> 255.2 | Q32: 142 | R32: =Water!O34 -> 0 | S32: 13 | T32: =Water!#REF! -> #REF! | U32: 155 | V32: =Water!#REF! -> #REF! | W32: 825 | X32: =Water!Q34 -> 148.016 | Y32: 1 | Z32: =Water!#REF! -> #REF! | AA32: 0 | AB32: 0 | AC32: 650 | AD32: =Water!#REF! -> #REF! | AE32: =Water!#REF! -> #REF! | AF32: =Water!#REF! -> #REF! | AG32: =Gas!B34 -> 8110682 | AH32: =Gas!C34 -> 765.32 | AI32: =Gas!#REF! -> #REF! | AJ32: =Gas!J34 -> 218.4 | AK32: =Gas!#REF! -> #REF! | AL32: =Gas!#REF! -> #REF! | AM32: =Gas!#REF! -> #REF! | AN32: =Gas!#REF! -> #REF! | AO32: =Gas!#REF! -> #REF! | AP32: =Gas!#REF! -> #REF! | AQ32: =Gas!#REF! -> #REF! | AR32: =Gas!#REF! -> #REF! | AS32: =Gas!#REF! -> #REF! | AT32: =Elect!BR33 -> 239 | AU32: =Elect!BP33 -> 113 | AX32: 45.34413 | AY32: 22.687373 | AZ32: 8835.4834 | BA32: 11.923729 | BB32: 5.9658902 | BC32: =Elect!BQ33 -> 482307 | BD32: =Elect!#REF! -> #REF! | BE32: =Elect!#REF! -> #REF! | BF32: =Elect!#REF! -> #REF! | BG32: =Elect!#REF! -> #REF! | BH32: 1.2294197 | BI32: 0.61512492 | BJ32: 5757.0859 | BK32: 7.7693467 | BL32: 3.8872963 | BM32: =Water!U34 -> 1.45 | BN32: =Water!W34 -> #DIV/0! | BO32: =Water!X34 -> 1020.8 | BP32: =Water!Y34 -> 5.8 | BQ32: =Water!Z34 -> #DIV/0!
A33: MTD | B33: 931200 | C33: =Elect!J34 -> 4231 | D33: 0 | E33: =Elect!M34 -> 1827 | F33: 600 | G33: =Elect!O34 -> 1584 | H33: 24543 | I33: =Water!C38 -> 6977.4 | J33: 0 | K33: =Water!E39 -> 0.77333333 | L33: 3 | M33: =Water!#REF! -> #REF! | N33: =Water!#REF! -> #REF! | O33: 1013 | P33: =Water!H38 -> 7985.6333 | Q33: 109 | R33: =Water!O38 -> 0 | S33: 15 | T33: =Water!#REF! -> #REF! | U33: 147 | V33: =Water!#REF! -> #REF! | W33: 730 | X33: =Water!Q38 -> 4328.5709 | Y33: 3 | Z33: =Water!#REF! -> #REF! | AA33: 0 | AB33: 0 | AC33: 0 | AD33: =Water!#REF! -> #REF! | AE33: =Water!#REF! -> #REF! | AF33: =Water!#REF! -> #REF! | AG33: =Gas!B38 -> 0 | AH33: =Gas!C38 -> 28412.24 | AI33: =Gas!#REF! -> #REF! | AJ33: =Gas!J38 -> 9360 | AK33: =Gas!#REF! -> #REF! | AL33: =Gas!#REF! -> #REF! | AM33: =Gas!#REF! -> #REF! | AN33: =Gas!#REF! -> #REF! | AO33: =Gas!#REF! -> #REF! | AP33: =Gas!#REF! -> #REF! | AQ33: =Gas!#REF! -> #REF! | AR33: =Gas!#REF! -> #REF! | AS33: =Gas!#REF! -> #REF! | AT33: =Elect!BR34 -> 208 | AU33: =Elect!BP34 -> 92 | AX33: 45.411099 | AY33: 22.844806 | AZ33: 245248.7 | BA33: 11.959851 | BB33: 6.0166013 | BC33: =Elect!BQ34 -> 482515 | BD33: =Elect!#REF! -> #REF! | BE33: =Elect!#REF! -> #REF! | BF33: =Elect!#REF! -> #REF! | BG33: =Elect!#REF! -> #REF! | BH33: 1.1514679 | BI33: 0.57929342 | BJ33: 140121.3 | BK33: 6.8331854 | BL33: 3.4377159 | BM33: =Water!U38 -> 1.6588353 | BN33: =Water!W38 -> #DIV/0! | BO33: =Water!X38 -> 31942.533 | BP33: =Water!Y38 -> 6.6353414 | BQ33: =Water!Z38 -> #DIV/0!
A34: AVER. Act | B34: 33257.143 | C34: =Elect!J35 -> 5721 | D34: 0 | E34: =Elect!M35 -> 1781 | F34: 21.428571 | G34: =Elect!O35 -> 1644 | H34: 876.53571 | I34: =Water!C39 -> 232.58 | J34: 0 | K34: =Water!E40 -> 0 | L34: 4 | M34: =Water!#REF! -> #REF! | N34: =Water!#REF! -> #REF! | O34: 1014 | P34: =Water!H39 -> 266.18778 | Q34: 138 | R34: =Water!O39 -> 0 | S34: 24 | T34: =Water!#REF! -> #REF! | U34: 145 | V34: =Water!#REF! -> #REF! | W34: 877 | X34: =Water!Q39 -> 144.2857 | Y34: 4 | Z34: =Water!#REF! -> #REF! | AA34: 0 | AB34: 0 | AC34: 0 | AD34: =Water!#REF! -> #REF! | AE34: =Water!#REF! -> #REF! | AF34: =Water!#REF! -> #REF! | AG34: =Gas!B39 -> 0 | AH34: =Gas!C39 -> 947.07467 | AI34: =Gas!#REF! -> #REF! | AJ34: =Gas!J39 -> 312 | AK34: =Gas!#REF! -> #REF! | AL34: =Gas!#REF! -> #REF! | AM34: =Gas!#REF! -> #REF! | AN34: =Gas!#REF! -> #REF! | AO34: =Gas!#REF! -> #REF! | AP34: =Gas!#REF! -> #REF! | AQ34: =Gas!#REF! -> #REF! | AR34: =Gas!#REF! -> #REF! | AS34: =Gas!#REF! -> #REF! | AT34: =Elect!BR35 -> 230 | AU34: =Elect!BP35 -> 107 | AX34: 45.411099 | AY34: 22.844806 | AZ34: 8758.8823 | BA34: 11.959851 | BB34: 6.0166013 | BC34: =Elect!BQ35 -> 482745 | BD34: =Elect!#REF! -> #REF! | BE34: =Elect!#REF! -> #REF! | BF34: =Elect!#REF! -> #REF! | BG34: =Elect!#REF! -> #REF! | BH34: 1.1761372 | BI34: 0.60007377 | BJ34: 5004.3322 | BK34: 6.8331854 | BL34: 3.4377159 | BM34: =Water!U39 -> 1.6588353 | BN34: =Water!W39 -> #DIV/0! | BO34: =Water!X39 -> 1064.7511 | BP34: =Water!Y39 -> 6.6353414 | BQ34: =Water!Z39 -> #DIV/0!
A35: TOTAL Budget | B35: 1040026 | C35: =Elect!J5 -> 0 | D35: 0 | E35: =Elect!M5 -> 0 | F35: 0 | G35: =Elect!O5 -> 0 | H35: 0 | I35: =Water!C40 -> 0 | J35: 0 | K35: =Water!E41 -> 0 | L35: 5 | M35: =Water!#REF! -> #REF! | N35: =Water!#REF! -> #REF! | O35: 1010 | P35: =Water!H40 -> 0 | Q35: 148 | R35: =Water!O40 -> 0 | S35: 22 | T35: =Water!#REF! -> #REF! | U35: 151 | V35: =Water!#REF! -> #REF! | W35: 833 | X35: =Water!Q40 -> 0 | Y35: 5 | Z35: =Water!#REF! -> #REF! | AA35: 0 | AB35: 0 | AC35: 0 | AD35: =Water!#REF! -> #REF! | AE35: =Water!#REF! -> #REF! | AF35: =Water!#REF! -> #REF! | AG35: =Gas!#REF! -> #REF! | AH35: =Gas!#REF! -> #REF! | AI35: =Gas!#REF! -> #REF! | AJ35: =Gas!#REF! -> #REF! | AK35: =Gas!#REF! -> #REF! | AL35: =Gas!#REF! -> #REF! | AM35: =Gas!#REF! -> #REF! | AN35: =Gas!#REF! -> #REF! | ... AS35: =Gas!#REF! -> #REF! | AT35: =Elect!BR5 -> 0 | AU35: =Elect!BP5 -> 0 | AX35: 45.679286 | AY35: 23.305904 | AZ35: 264708.4 | BA35: 11.626335 | BB35: 5.9318409 | BC35: =Elect!BQ5 -> 476466 | BD35: =Elect!#REF! -> #REF! | BE35: =Elect!#REF! -> #REF! | BF35: =Elect!#REF! -> #REF! | BG35: =Elect!#REF! -> #REF! | BH35: 1.1761372 | BI35: 0.60007377 | BJ35: 150494 | BK35: 6.6098911 | BL35: 3.3724146 | BM35: =Water!U40 -> #REF! | BN35: =Water!W40 -> #REF! | BO35: =Water!X40 -> 0 | BP35: =Water!Y40 -> 0 | BQ35: =Water!Z40 -> 0
A36: Budget MTD | B36: 1040026 | C36: =Elect!#REF! -> #REF! | D36: 0 | E36: =Elect!#REF! -> #REF! | F36: 0 | G36: =Elect!#REF! -> #REF! | H36: 0 | I36: =Water!C41 -> 0 | J36: 0 | K36: =Water!E42 -> 0 | L36: 6 | M36: =Water!#REF! -> #REF! | N36: =Water!#REF! -> #REF! | O36: 30039 | P36: =Water!H41 -> 0 | Q36: 129.54839 | R36: =Water!O41 -> 0 | S36: 719 | T36: =Water!#REF! -> #REF! | U36: 4609 | V36: =Water!#REF! -> #REF! | W36: 23430 | X36: =Water!Q41 -> 0 | Y36: 6 | Z36: =Water!#REF! -> #REF! | AA36: 0 | AB36: 0 | AC36: 0 | AD36: =Water!#REF! -> #REF! | AE36: =Water!#REF! -> #REF! | AF36: =Water!#REF! -> #REF! | AG36: =Gas!#REF! -> #REF! | AH36: =Gas!#REF! -> #REF! | AI36: =Gas!#REF! -> #REF! | AJ36: =Gas!#REF! -> #REF! | AK36: =Gas!#REF! -> #REF! | AL36: =Gas!#REF! -> #REF! | AM36: =Gas!#REF! -> #REF! | AN36: =Gas!#REF! -> #REF! | ... AS36: =Gas!#REF! -> #REF! | AT36: =Elect!#REF! -> #REF! | AU36: =Elect!#REF! -> #REF! | AX36: 45.679286 | AY36: 23.305904 | AZ36: 264708.4 | BA36: 11.626335 | BB36: 5.9318409 | BC36: =Elect!#REF! -> #REF! | BD36: =Elect!#REF! -> #REF! | BE36: =Elect!#REF! -> #REF! | BF36: =Elect!#REF! -> #REF! | BG36: =Elect!#REF! -> #REF! | BH36: 0 | BI36: 0 | BJ36: 135930.06 | BK36: 6.6098911 | BL36: 3.3724146 | BM36: =Water!U41 -> #REF! | BN36: =Water!W41 -> #REF! | BO36: =Water!X41 -> #REF! | BP36: =Water!Y41 -> #REF! | BQ36: =Water!Z41 -> #REF!
A37: AVER. Bud | B37: 37143.785 | C37: =Elect!#REF! -> #REF! | D37: 0 | E37: =Elect!#REF! -> #REF! | F37: 0 | G37: =Elect!#REF! -> #REF! | H37: 0 | I37: =Water!C42 -> 0 | J37: 0 | K37: =Water!E43 -> 0 | L37: 7 | M37: =Water!#REF! -> #REF! | N37: =Water!#REF! -> #REF! | O37: 969 | P37: =Water!H42 -> 0 | Q37: 0 | R37: =Water!O42 -> 0 | S37: 23.193548 | T37: =Water!#REF! -> #REF! | U37: 148.67742 | V37: =Water!#REF! -> #REF! | W37: 755.80645 | X37: =Water!Q42 -> 0 | Y37: 7 | Z37: =Water!#REF! -> #REF! | AA37: 0 | AB37: 0 | AC37: 0 | AD37: =Water!#REF! -> #REF! | AE37: =Water!#REF! -> #REF! | AF37: =Water!#REF! -> #REF! | AG37: =Gas!#REF! -> #REF! | AH37: =Gas!#REF! -> #REF! | AI37: =Gas!#REF! -> #REF! | AJ37: =Gas!#REF! -> #REF! | AK37: =Gas!#REF! -> #REF! | AL37: =Gas!#REF! -> #REF! | AM37: =Gas!#REF! -> #REF! | AN37: =Gas!#REF! -> #REF! | ... AS37: =Gas!#REF! -> #REF! | AT37: =Elect!#REF! -> #REF! | AU37: =Elect!#REF! -> #REF! | AX37: 0 | AY37: 0 | AZ37: 9453.8714 | BA37: 0 | BB37: 0 | BC37: =Elect!#REF! -> #REF! | BD37: =Elect!#REF! -> #REF! | BE37: =Elect!#REF! -> #REF! | BF37: =Elect!#REF! -> #REF! | BG37: =Elect!#REF! -> #REF! | BH37: 0 | BI37: 0 | BJ37: 0 | BK37: 0 | BL37: 0 | BM37: =Water!U42 -> 0 | BN37: =Water!W42 -> 0 | BO37: =Water!X42 -> 0 | BP37: =Water!Y42 -> 0 | BQ37: =Water!Z42 -> 0
A38: Total RFC | B38: 784008.53 | C38: =Elect!#REF! -> #REF! | D38: 0 | E38: =Elect!#REF! -> #REF! | F38: 0 | G38: =Elect!#REF! -> #REF! | H38: 0 | I38: =Water!C43 -> 0 | J38: 0 | K38: =Water!E44 -> 0 | L38: 8 | M38: =Water!#REF! -> #REF! | N38: =Water!#REF! -> #REF! | O38: 0 | P38: =Water!H43 -> 0 | Q38: 0 | R38: =Water!O43 -> 0 | S38: 0 | T38: =Water!#REF! -> #REF! | U38: 0 | V38: =Water!#REF! -> #REF! | W38: 0 | X38: =Water!Q43 -> 0 | Y38: 8 | Z38: =Water!#REF! -> #REF! | AA38: 0 | AB38: 0 | AC38: 0 | AD38: =Water!#REF! -> #REF! | AE38: =Water!#REF! -> #REF! | AF38: =Water!#REF! -> #REF! | AG38: =Gas!#REF! -> #REF! | AH38: =Gas!#REF! -> #REF! | AI38: =Gas!#REF! -> #REF! | AJ38: =Gas!#REF! -> #REF! | AK38: =Gas!#REF! -> #REF! | AL38: =Gas!#REF! -> #REF! | AM38: =Gas!#REF! -> #REF! | AN38: =Gas!#REF! -> #REF! | ... AS38: =Gas!#REF! -> #REF! | AT38: =Elect!#REF! -> #REF! | AU38: =Elect!#REF! -> #REF! | AX38: 38.173558 | AY38: 19.219193 | AZ38: 208225.85 | BA38: 10.138565 | BB38: 5.1044505 | BC38: =Elect!#REF! -> #REF! | BD38: =Elect!#REF! -> #REF! | BE38: =Elect!#REF! -> #REF! | BF38: =Elect!#REF! -> #REF! | BG38: =Elect!#REF! -> #REF! | BH38: 0 | BI38: 0 | BJ38: 127385.62 | BK38: 6.2024355 | BL38: 3.1227323 | BM38: =Water!U43 -> 0 | BN38: =Water!W43 -> 0 | BO38: =Water!X43 -> 0 | BP38: =Water!Y43 -> 0 | BQ38: =Water!Z43 -> 0
A39: RFC MTD | B39: 784008.53 | C39: =Elect!#REF! -> #REF! | D39: 0 | E39: =Elect!#REF! -> #REF! | F39: 0 | G39: =Elect!#REF! -> #REF! | H39: 0 | I39: =Water!C44 -> 0 | J39: 0 | K39: =Water!E45 -> 0 | L39: 9 | M39: =Water!#REF! -> #REF! | N39: =Water!#REF! -> #REF! | O39: 0 | P39: =Water!H44 -> 0 | Q39: 0 | R39: =Water!O44 -> 0 | S39: 0 | T39: =Water!#REF! -> #REF! | U39: 0 | V39: =Water!#REF! -> #REF! | W39: 0 | X39: =Water!Q44 -> 0 | Y39: 9 | Z39: =Water!#REF! -> #REF! | AA39: 0 | AB39: 0 | AC39: 0 | AD39: =Water!#REF! -> #REF! | AE39: =Water!#REF! -> #REF! | AF39: =Water!#REF! -> #REF! | AG39: =Gas!#REF! -> #REF! | AH39: =Gas!#REF! -> #REF! | AI39: =Gas!#REF! -> #REF! | AJ39: =Gas!#REF! -> #REF! | AK39: =Gas!#REF! -> #REF! | AL39: =Gas!#REF! -> #REF! | AM39: =Gas!#REF! -> #REF! | AN39: =Gas!#REF! -> #REF! | ... AS39: =Gas!#REF! -> #REF! | AT39: =Elect!#REF! -> #REF! | AU39: =Elect!#REF! -> #REF! | AX39: 38.173558 | AY39: 19.219193 | AZ39: 208225.85 | BA39: 10.138565 | BB39: 5.1044505 | BC39: =Elect!#REF! -> #REF! | BD39: =Elect!#REF! -> #REF! | BE39: =Elect!#REF! -> #REF! | BF39: =Elect!#REF! -> #REF! | BG39: =Elect!#REF! -> #REF! | BH39: 0 | BI39: 0 | BJ39: 115057.98 | BK39: 6.2024355 | BL39: 3.1227323 | BM39: =Water!U44 -> 0 | BN39: =Water!W44 -> 0 | BO39: =Water!X44 -> #VALUE! | BP39: =Water!Y44 -> #VALUE! | BQ39: =Water!Z44 -> #VALUE!
A40: AVER RFC | B40: 28000.305 | C40: =Elect!#REF! -> #REF! | D40: 0 | E40: =Elect!#REF! -> #REF! | F40: 0 | G40: =Elect!#REF! -> #REF! | H40: 0 | I40: =Water!C45 -> 0 | J40: 0 | K40: =Water!E46 -> 0 | L40: 10 | M40: =Water!#REF! -> #REF! | N40: =Water!#REF! -> #REF! | O40: 0 | P40: =Water!H45 -> 0 | Q40: 0 | R40: =Water!O45 -> 0 | S40: 0 | T40: =Water!#REF! -> #REF! | U40: 0 | V40: =Water!#REF! -> #REF! | W40: 0 | X40: =Water!Q45 -> 0 | Y40: 10 | Z40: =Water!#REF! -> #REF! | AA40: 0 | AB40: 0 | AC40: 0 | AD40: =Water!#REF! -> #REF! | AE40: =Water!#REF! -> #REF! | AF40: =Water!#REF! -> #REF! | AG40: =Gas!#REF! -> #REF! | AH40: =Gas!#REF! -> #REF! | AI40: =Gas!#REF! -> #REF! | AJ40: =Gas!#REF! -> #REF! | AK40: =Gas!#REF! -> #REF! | AL40: =Gas!#REF! -> #REF! | AM40: =Gas!#REF! -> #REF! | AN40: =Gas!#REF! -> #REF! | ... AS40: =Gas!#REF! -> #REF! | AT40: =Elect!#REF! -> #REF! | AU40: =Elect!#REF! -> #REF! | AX40: 0 | AY40: 0 | AZ40: 7436.6375 | BA40: 0 | BB40: 0 | BC40: =Elect!#REF! -> #REF! | BD40: =Elect!#REF! -> #REF! | BE40: =Elect!#REF! -> #REF! | BF40: =Elect!#REF! -> #REF! | BG40: =Elect!#REF! -> #REF! | BH40: 1.1254646 | BI40: 0.57264868 | BJ40: 4109.2135 | BK40: 0 | BL40: 0 | BM40: =Water!U45 -> 0 | BN40: =Water!W45 -> 0 | BO40: =Water!X45 -> #VALUE! | BP40: =Water!Y45 -> 0 | BQ40: =Water!Z45 -> 0

Sheet Temp.
A2: HILTON INTERNATIONAL
A3: GULF, MIDDLE EAST AND ASIA SPECIFIC
A4: HOTEL:HILTON HURGHADA LONG BEACH RESORT | G4: =Elect!A1 -> June
A7: DATE | B7: MAX TEMP | C7: MIN TEMP | D7: MAX TEMP | E7: MIN TEMP | F7: DAY | G7: DD. C | H7: DD. H | I7: MTD | J7: MTD
B8: C | C8: C | D8: F | E8: F | F8: PARAMETER | I8: COOLING | J8: HEATING
A10: 1 | D10: =SUM((B10*9/5)+32) -> 32 | E10: =SUM((C10*9/5)+32) -> 32 | F10: =SUM(((B10+C10)/2)-18.33) -> -18.33 | G10: =SUM(0+(F10)+ABS(F10))/2 -> 0 | H10: =IF((SUM(0-(F10)+ABS(F10))/2)<18,SUM(0-(F10)+ABS(F10))/2,0) -> 0 | I10: =SUM(G10:G10) -> 0 | J10: =SUM(H10:H10) -> 0
A11: 2 | D11: =SUM((B11*9/5)+32) -> 32 | E11: =SUM((C11*9/5)+32) -> 32 | F11: =SUM(((B11+C11)/2)-18.33) -> -18.33 | G11: =SUM(0+(F11)+ABS(F11))/2 -> 0 | H11: =IF((SUM(0-(F11)+ABS(F11))/2)<18,SUM(0-(F11)+ABS(F11))/2,0) -> 0 | I11: =SUM(G10:G11) -> 0 | J11: =SUM(H10:H11) -> 0
A12: 3 | D12: =SUM((B12*9/5)+32) -> 32 | E12: =SUM((C12*9/5)+32) -> 32 | F12: =SUM(((B12+C12)/2)-18.33) -> -18.33 | G12: =SUM(0+(F12)+ABS(F12))/2 -> 0 | H12: =IF((SUM(0-(F12)+ABS(F12))/2)<18,SUM(0-(F12)+ABS(F12))/2,0) -> 0 | I12: =SUM(G10:G12) -> 0 | J12: =SUM(H10:H12) -> 0
A13: 4 | D13: =SUM((B13*9/5)+32) -> 32 | E13: =SUM((C13*9/5)+32) -> 32 | F13: =SUM(((B13+C13)/2)-18.33) -> -18.33 | G13: =SUM(0+(F13)+ABS(F13))/2 -> 0 | H13: =IF((SUM(0-(F13)+ABS(F13))/2)<18,SUM(0-(F13)+ABS(F13))/2,0) -> 0 | I13: =SUM(G10:G13) -> 0 | J13: =SUM(H10:H13) -> 0
A14: 5 | D14: =SUM((B14*9/5)+32) -> 32 | E14: =SUM((C14*9/5)+32) -> 32 | F14: =SUM(((B14+C14)/2)-18.33) -> -18.33 | G14: =SUM(0+(F14)+ABS(F14))/2 -> 0 | H14: =IF((SUM(0-(F14)+ABS(F14))/2)<18,SUM(0-(F14)+ABS(F14))/2,0) -> 0 | I14: =SUM(G10:G14) -> 0 | J14: =SUM(H10:H14) -> 0
A15: 6 | D15: =SUM((B15*9/5)+32) -> 32 | E15: =SUM((C15*9/5)+32) -> 32 | F15: =SUM(((B15+C15)/2)-18.33) -> -18.33 | G15: =SUM(0+(F15)+ABS(F15))/2 -> 0 | H15: =IF((SUM(0-(F15)+ABS(F15))/2)<18,SUM(0-(F15)+ABS(F15))/2,0) -> 0 | I15: =SUM(G10:G15) -> 0 | J15: =SUM(H10:H15) -> 0
A16: 7 | D16: =SUM((B16*9/5)+32) -> 32 | E16: =SUM((C16*9/5)+32) -> 32 | F16: =SUM(((B16+C16)/2)-18.33) -> -18.33 | G16: =SUM(0+(F16)+ABS(F16))/2 -> 0 | H16: =IF((SUM(0-(F16)+ABS(F16))/2)<18,SUM(0-(F16)+ABS(F16))/2,0) -> 0 | I16: =SUM(G10:G16) -> 0 | J16: =SUM(H10:H16) -> 0
A17: 8 | D17: =SUM((B17*9/5)+32) -> 32 | E17: =SUM((C17*9/5)+32) -> 32 | F17: =SUM(((B17+C17)/2)-18.33) -> -18.33 | G17: =SUM(0+(F17)+ABS(F17))/2 -> 0 | H17: =IF((SUM(0-(F17)+ABS(F17))/2)<18,SUM(0-(F17)+ABS(F17))/2,0) -> 0 | I17: =SUM(G10:G17) -> 0 | J17: =SUM(H10:H17) -> 0
A18: 9 | D18: =SUM((B18*9/5)+32) -> 32 | E18: =SUM((C18*9/5)+32) -> 32 | F18: =SUM(((B18+C18)/2)-18.33) -> -18.33 | G18: =SUM(0+(F18)+ABS(F18))/2 -> 0 | H18: =IF((SUM(0-(F18)+ABS(F18))/2)<18,SUM(0-(F18)+ABS(F18))/2,0) -> 0 | I18: =SUM(G10:G18) -> 0 | J18: =SUM(H10:H18) -> 0
A19: 10 | D19: =SUM((B19*9/5)+32) -> 32 | E19: =SUM((C19*9/5)+32) -> 32 | F19: =SUM(((B19+C19)/2)-18.33) -> -18.33 | G19: =SUM(0+(F19)+ABS(F19))/2 -> 0 | H19: =IF((SUM(0-(F19)+ABS(F19))/2)<18,SUM(0-(F19)+ABS(F19))/2,0) -> 0 | I19: =SUM(G10:G19) -> 0 | J19: =SUM(H10:H19) -> 0
A20: 11 | D20: =SUM((B20*9/5)+32) -> 32 | E20: =SUM((C20*9/5)+32) -> 32 | F20: =SUM(((B20+C20)/2)-18.33) -> -18.33 | G20: =SUM(0+(F20)+ABS(F20))/2 -> 0 | H20: =IF((SUM(0-(F20)+ABS(F20))/2)<18,SUM(0-(F20)+ABS(F20))/2,0) -> 0 | I20: =SUM(G10:G20) -> 0 | J20: =SUM(H10:H20) -> 0
A21: 12 | D21: =SUM((B21*9/5)+32) -> 32 | E21: =SUM((C21*9/5)+32) -> 32 | F21: =SUM(((B21+C21)/2)-18.33) -> -18.33 | G21: =SUM(0+(F21)+ABS(F21))/2 -> 0 | H21: =IF((SUM(0-(F21)+ABS(F21))/2)<18,SUM(0-(F21)+ABS(F21))/2,0) -> 0 | I21: =SUM(G10:G21) -> 0 | J21: =SUM(H10:H21) -> 0
A22: 13 | D22: =SUM((B22*9/5)+32) -> 32 | E22: =SUM((C22*9/5)+32) -> 32 | F22: =SUM(((B22+C22)/2)-18.33) -> -18.33 | G22: =SUM(0+(F22)+ABS(F22))/2 -> 0 | H22: =IF((SUM(0-(F22)+ABS(F22))/2)<18,SUM(0-(F22)+ABS(F22))/2,0) -> 0 | I22: =SUM(G10:G22) -> 0 | J22: =SUM(H10:H22) -> 0
A23: 14 | D23: =SUM((B23*9/5)+32) -> 32 | E23: =SUM((C23*9/5)+32) -> 32 | F23: =SUM(((B23+C23)/2)-18.33) -> -18.33 | G23: =SUM(0+(F23)+ABS(F23))/2 -> 0 | H23: =IF((SUM(0-(F23)+ABS(F23))/2)<18,SUM(0-(F23)+ABS(F23))/2,0) -> 0 | I23: =SUM(G10:G23) -> 0 | J23: =SUM(H10:H23) -> 0
A24: 15 | D24: =SUM((B24*9/5)+32) -> 32 | E24: =SUM((C24*9/5)+32) -> 32 | F24: =SUM(((B24+C24)/2)-18.33) -> -18.33 | G24: =SUM(0+(F24)+ABS(F24))/2 -> 0 | H24: =IF((SUM(0-(F24)+ABS(F24))/2)<18,SUM(0-(F24)+ABS(F24))/2,0) -> 0 | I24: =SUM(G11:G24) -> 0 | J24: =SUM(H11:H24) -> 0
A25: 16 | D25: =SUM((B25*9/5)+32) -> 32 | E25: =SUM((C25*9/5)+32) -> 32 | F25: =SUM(((B25+C25)/2)-18.33) -> -18.33 | G25: =SUM(0+(F25)+ABS(F25))/2 -> 0 | H25: =IF((SUM(0-(F25)+ABS(F25))/2)<18,SUM(0-(F25)+ABS(F25))/2,0) -> 0 | I25: =SUM(G12:G25) -> 0 | J25: =SUM(H12:H25) -> 0
A26: 17 | D26: =SUM((B26*9/5)+32) -> 32 | E26: =SUM((C26*9/5)+32) -> 32 | F26: =SUM(((B26+C26)/2)-18.33) -> -18.33 | G26: =SUM(0+(F26)+ABS(F26))/2 -> 0 | H26: =IF((SUM(0-(F26)+ABS(F26))/2)<18,SUM(0-(F26)+ABS(F26))/2,0) -> 0 | I26: =SUM(G13:G26) -> 0 | J26: =SUM(H13:H26) -> 0
A27: 18 | D27: =SUM((B27*9/5)+32) -> 32 | E27: =SUM((C27*9/5)+32) -> 32 | F27: =SUM(((B27+C27)/2)-18.33) -> -18.33 | G27: =SUM(0+(F27)+ABS(F27))/2 -> 0 | H27: =IF((SUM(0-(F27)+ABS(F27))/2)<18,SUM(0-(F27)+ABS(F27))/2,0) -> 0 | I27: =SUM(G14:G27) -> 0 | J27: =SUM(H14:H27) -> 0
A28: 19 | D28: =SUM((B28*9/5)+32) -> 32 | E28: =SUM((C28*9/5)+32) -> 32 | F28: =SUM(((B28+C28)/2)-18.33) -> -18.33 | G28: =SUM(0+(F28)+ABS(F28))/2 -> 0 | H28: =IF((SUM(0-(F28)+ABS(F28))/2)<18,SUM(0-(F28)+ABS(F28))/2,0) -> 0 | I28: =SUM(G15:G28) -> 0 | J28: =SUM(H15:H28) -> 0
A29: 20 | D29: =SUM((B29*9/5)+32) -> 32 | E29: =SUM((C29*9/5)+32) -> 32 | F29: =SUM(((B29+C29)/2)-18.33) -> -18.33 | G29: =SUM(0+(F29)+ABS(F29))/2 -> 0 | H29: =IF((SUM(0-(F29)+ABS(F29))/2)<18,SUM(0-(F29)+ABS(F29))/2,0) -> 0 | I29: =SUM(G16:G29) -> 0 | J29: =SUM(H16:H29) -> 0
A30: 21 | D30: =SUM((B30*9/5)+32) -> 32 | E30: =SUM((C30*9/5)+32) -> 32 | F30: =SUM(((B30+C30)/2)-18.33) -> -18.33 | G30: =SUM(0+(F30)+ABS(F30))/2 -> 0 | H30: =IF((SUM(0-(F30)+ABS(F30))/2)<18,SUM(0-(F30)+ABS(F30))/2,0) -> 0 | I30: =SUM(G17:G30) -> 0 | J30: =SUM(H17:H30) -> 0
A31: 22 | D31: =SUM((B31*9/5)+32) -> 32 | E31: =SUM((C31*9/5)+32) -> 32 | F31: =SUM(((B31+C31)/2)-18.33) -> -18.33 | G31: =SUM(0+(F31)+ABS(F31))/2 -> 0 | H31: =IF((SUM(0-(F31)+ABS(F31))/2)<18,SUM(0-(F31)+ABS(F31))/2,0) -> 0 | I31: =SUM(G18:G31) -> 0 | J31: =SUM(H18:H31) -> 0
A32: 23 | D32: =SUM((B32*9/5)+32) -> 32 | E32: =SUM((C32*9/5)+32) -> 32 | F32: =SUM(((B32+C32)/2)-18.33) -> -18.33 | G32: =SUM(0+(F32)+ABS(F32))/2 -> 0 | H32: =IF((SUM(0-(F32)+ABS(F32))/2)<18,SUM(0-(F32)+ABS(F32))/2,0) -> 0 | I32: =SUM(G19:G32) -> 0 | J32: =SUM(H19:H32) -> 0
A33: 24 | D33: =SUM((B33*9/5)+32) -> 32 | E33: =SUM((C33*9/5)+32) -> 32 | F33: =SUM(((B33+C33)/2)-18.33) -> -18.33 | G33: =SUM(0+(F33)+ABS(F33))/2 -> 0 | H33: =IF((SUM(0-(F33)+ABS(F33))/2)<18,SUM(0-(F33)+ABS(F33))/2,0) -> 0 | I33: =SUM(G20:G33) -> 0 | J33: =SUM(H20:H33) -> 0
A34: 25 | D34: =SUM((B34*9/5)+32) -> 32 | E34: =SUM((C34*9/5)+32) -> 32 | F34: =SUM(((B34+C34)/2)-18.33) -> -18.33 | G34: =SUM(0+(F34)+ABS(F34))/2 -> 0 | H34: =IF((SUM(0-(F34)+ABS(F34))/2)<18,SUM(0-(F34)+ABS(F34))/2,0) -> 0 | I34: =SUM(G21:G34) -> 0 | J34: =SUM(H21:H34) -> 0
... A40: 31 | D40: =SUM((B40*9/5)+32) -> 32 | E40: =SUM((C40*9/5)+32) -> 32 | F40: =SUM(((B40+C40)/2)-18.33) -> -18.33 | G40: =SUM(0+(F40)+ABS(F40))/2 -> 0 | H40: =IF((SUM(0-(F40)+ABS(F40))/2)<18,SUM(0-(F40)+ABS(F40))/2,0) -> 0 | I40: =SUM(G27:G40) -> 0 | J40: =SUM(H27:H40) -> 0
E42: =SUM(G10:G40) -> 0 | F42: deg c
E44: =SUM(H10:H40) -> 0 | F44: deg c

Sheet M-Rep
B3: =Elect!A1 -> June
D4: Y.T.D
A5: Energy breakdown | C5: 2009 | D5: 2005 | E5: 2006
A6: Elect.
A7: Chillers KWH | C7: N/A | D7: N/A | E7: N/A
A8: Laundry KWH | C8: N/A | D8: N/A | E8: N/A
A9: Kitchen KWH | C9: N/A | D9: N/A | E9: N/A
A10: Gas
A11: Kit M3 | C11: =Gas!#REF!/1000 -> #REF!
A12: Laundry M3 | C12: N/A | D12: 0 | E12: #REF!
A13: Water | D13: N/A | E13: N/A
A14: Laundry HW | C14: N/A
A15: Laundry CW | C15: N/A
A16: Kit HW | C16: N/A
A17: kIt CW | C17: N/A | D17: N/A | E17: N/A
A18: Dmstc HW | C18: N/A | D18: N/A | E18: N/A
A19: Dmstc CW | C19: N/A | D19: N/A | E19: N/A
A20: S.Pool MKUP | C20: =#REF! -> #REF! | D20: N/A | E20: N/A
A21: Ctower MKUP | C21: N/A | D21: N/A | E21: N/A
A22: Gardens Irrigat. | C22: =Water!S38 -> 0 | D22: N/A | E22: N/A
A23: Swage water treatment | C23: =Water!#REF! -> #REF! | D23: 27437 | E23: #REF!
A24: Utilities consumption | D24: N/A | E24: N/A
A25: Elect. Kwh | C25: =Elect!J34 -> 4231 | D25: 12266 | E25: 814
A26: M.D (9.5 LE) | D26: 147773 | E26: #REF!
A27: Water M3 | C27: =Water!H38 -> 7985.6333
A28: Fuel Ltr | C28: =Gas!#REF!*1000 -> #REF! | D28: 12876868 | E28: 14500800
A29: Gas M3/ Boilers, chillers,..etc | C29: N/A | D29: 28880 | E29: 32980
A30: Gas M3 Kitchen | C30: =Gas!#REF!/1000 -> #REF! | D30: 244283 | E30: 252530.66
A31: Total Energy | D31: 620770 | E31: #REF!
A32: Control Parameters | D32: #REF! | E32: N/A
A33: No. of Rooms % occ. | C33: =YTD!Q4 -> 0 | D33: 39.395 | E33: #REF!
A34: No. of Occ. Rooms | C34: =YTD!Q5 -> 0
A35: guest count | C35: =YTD!Q6 -> 0
A36: Food covers | D36: #REF! | E36: #REF!
A37: Laundry W. Kg | D37: 0.8807 | E37: 0.46351998
A38: DDC | C38: =Temp.!E42 -> 0 | D38: 196150 | E38: 237021
A39: DDH | C39: =Temp.!E44 -> 0 | D39: 400070 | E39: 466105
A40: Utilities Entergy cost | D40: 1583714 | E40: 1940567
A41: Elect. | C41: =Elect!#REF! -> #REF! | D41: 1690339 | E41: 3118671.6
A42: M.D | C42: =C26*Elect!#REF! -> #REF! | D42: 2381.51 | E42: 2480.24
A43: Water | C43: =Water!X38 -> 31942.533 | D43: 112 | E43: 97.53
A44: Fuel | C44: =Gas!#REF! -> #REF!
A45: Gas Boilers, chillers,etc.. | C45: N/A | D45: 2138156.8 | E45: #REF!
A46: Gas Kitchen | C46: =C30*Gas!M2*1000 -> #REF! | D46: 223044.2 | E46: #REF!
A47: TOTAL LE | C47: =SUM(C41:C46) -> #REF! | D47: 1330535.7 | E47: 1382037.4
A48: No. of POMEC Staff | D48: 330278 | E48: #REF!
A49: Hotel Age | C49: 6 | D49: N/A | E49: N/A
A50: No. of rooms | C50: =31*912 -> 28272 | D50: 36597.525 | E50: #REF!
A51: Building Volume | C51: 243175 | D51: =SUM(D45:D50) -> 4058612.3 | E51: =SUM(E45:E50) -> #REF!
A52: Building area | C52: 75064
A53: US$ Rate | C53: 5.59402 | D53: 61 | E53: 72
A54: Total R&M MTD | C54: =YTD!Q65 -> 0 | D54: #REF! | E54: 243175 | F54: =YTD!Q64 -> 0
A55: Staff - HLP | D55: #REF! | E55: 75064
A56: Staff - R&M | D56: 5.755 | E56: 5.65951
A57: Staff - Grounds

Sheet YTD
A1: =Elect!A1 -> June | H1: Actual 2014
C3: JAN | D3: FEB | E3: MAR | F3: APR | G3: MAY | H3: JUN | I3: JUL | J3: AUG | K3: SEP | L3: OCT | M3: NOV | N3: DEC | O3: TOTAL | P3: YTD | Q3: Month Act
A4: Occ Room % | O4: =SUM(C4:N4) -> 0 | P4: =(IF($A$1=39814,C4,(IF($A$1=39845,SUM(C4:D4),(IF($A$1=39873,SUM(C4:E4),(IF($A$1=39904,SUM(C4:F4),(IF($A$1=39934,SUM(C4:G4),(IF($A$1=39965,SUM(C4:H4),(IF($A$1=39995,SUM(C4:I4),0)))))))))))))+(IF($A$1=40026,SUM(C4:J4),(IF($A$1=40057,SUM(C4:K4),(IF($A$1=40087,SUM(C4:L4),(IF($A$1=40118,SUM(C4:M4))))))))))+(IF($A$1=40148,SUM(C4:N4),0)) -> 0 | Q4: =(IF($A$1=39814,C4,(IF($A$1=39845,D4,(IF($A$1=39873,E4,(IF($A$1=39904,F4,(IF($A$1=39934,G4,(IF($A$1=39965,H4,(IF($A$1=39995,I4,0)))))))))))))+(IF($A$1=40026,J4,(IF($A$1=40057,K4,(IF($A$1=40087,L4,(IF($A$1=40118,M4)))))))))+(IF($A$1=40148,N4,0)) -> 0 | S4: 40179 | DE4: 1
A5: Occ Room | C5: 25072 | D5: =Elect!BP34 -> 92 | O5: =SUM(C5:N5) -> 25164 | P5: =(IF($A$1=40179,C5,(IF($A$1=40210,SUM(C5:D5),(IF($A$1=40238,SUM(C5:E5),(IF($A$1=40269,SUM(C5:F5),(IF($A$1=40299,SUM(C5:G5),(IF($A$1=40330,SUM(C5:H5),(IF($A$1=40360,SUM(C5:I5),0)))))))))))))+(IF($A$1=40391,SUM(C5:J5),(IF($A$1=40422,SUM(C5:K5),(IF($A$1=40452,SUM(C5:L5),(IF($A$1=40483,SUM(C5:M5))))))))))+(IF($A$1=40513,SUM(C5:N5),0)) -> 0 | Q5: =(IF($A$1=40179,C5,(IF($A$1=40210,D5,(IF($A$1=40238,E5,(IF($A$1=40269,F5,(IF($A$1=40299,G5,(IF($A$1=40330,H5,(IF($A$1=40360,I5,0)))))))))))))+(IF($A$1=40391,J5,(IF($A$1=40422,K5,(IF($A$1=40452,L5,(IF($A$1=40483,M5)))))))))+(IF($A$1=40513,N5,0)) -> 0 | S5: 40210 | DE5: 2
A6: Number of Guest | C6: 50662 | D6: =Elect!BR34 -> 208 | O6: =SUM(C6:N6) -> 50870 | P6: =(IF($A$1=40179,C6,(IF($A$1=40210,SUM(C6:D6),(IF($A$1=40238,SUM(C6:E6),(IF($A$1=40269,SUM(C6:F6),(IF($A$1=40299,SUM(C6:G6),(IF($A$1=40330,SUM(C6:H6),(IF($A$1=40360,SUM(C6:I6),0)))))))))))))+(IF($A$1=40391,SUM(C6:J6),(IF($A$1=40422,SUM(C6:K6),(IF($A$1=40452,SUM(C6:L6),(IF($A$1=40483,SUM(C6:M6))))))))))+(IF($A$1=40513,SUM(C6:N6),0)) -> 0 | Q6: =(IF($A$1=40179,C6,(IF($A$1=40210,D6,(IF($A$1=40238,E6,(IF($A$1=40269,F6,(IF($A$1=40299,G6,(IF($A$1=40330,H6,(IF($A$1=40360,I6,0)))))))))))))+(IF($A$1=40391,J6,(IF($A$1=40422,K6,(IF($A$1=40452,L6,(IF($A$1=40483,M6)))))))))+(IF($A$1=40513,N6,0)) -> 0 | S6: 40238 | DE6: 3
A7: PAY & REL. EXP. | O7: =SUM(C7:N7) -> 0 | P7: =(IF($A$1=40179,C7,(IF($A$1=40210,SUM(C7:D7),(IF($A$1=40238,SUM(C7:E7),(IF($A$1=40269,SUM(C7:F7),(IF($A$1=40299,SUM(C7:G7),(IF($A$1=40330,SUM(C7:H7),(IF($A$1=40360,SUM(C7:I7),0)))))))))))))+(IF($A$1=40391,SUM(C7:J7),(IF($A$1=40422,SUM(C7:K7),(IF($A$1=40452,SUM(C7:L7),(IF($A$1=40483,SUM(C7:M7))))))))))+(IF($A$1=40513,SUM(C7:N7),0)) -> 0 | Q7: =(IF($A$1=40179,C7,(IF($A$1=40210,D7,(IF($A$1=40238,E7,(IF($A$1=40269,F7,(IF($A$1=40299,G7,(IF($A$1=40330,H7,(IF($A$1=40360,I7,0)))))))))))))+(IF($A$1=40391,J7,(IF($A$1=40422,K7,(IF($A$1=40452,L7,(IF($A$1=40483,M7)))))))))+(IF($A$1=40513,N7,0)) -> 0
A8: SALARIES | B8: 53241001 | O8: =SUM(C8:N8) -> 0 | P8: =(IF($A$1=40179,C8,(IF($A$1=40210,SUM(C8:D8),(IF($A$1=40238,SUM(C8:E8),(IF($A$1=40269,SUM(C8:F8),(IF($A$1=40299,SUM(C8:G8),(IF($A$1=40330,SUM(C8:H8),(IF($A$1=40360,SUM(C8:I8),0)))))))))))))+(IF($A$1=40391,SUM(C8:J8),(IF($A$1=40422,SUM(C8:K8),(IF($A$1=40452,SUM(C8:L8),(IF($A$1=40483,SUM(C8:M8))))))))))+(IF($A$1=40513,SUM(C8:N8),0)) -> 0 | Q8: =(IF($A$1=40179,C8,(IF($A$1=40210,D8,(IF($A$1=40238,E8,(IF($A$1=40269,F8,(IF($A$1=40299,G8,(IF($A$1=40330,H8,(IF($A$1=40360,I8,0)))))))))))))+(IF($A$1=40391,J8,(IF($A$1=40422,K8,(IF($A$1=40452,L8,(IF($A$1=40483,M8)))))))))+(IF($A$1=40513,N8,0)) -> 0
A9: EXTRA WAGES | B9: 53242099 | O9: =SUM(C9:N9) -> 0 | P9: =(IF($A$1=40179,C9,(IF($A$1=40210,SUM(C9:D9),(IF($A$1=40238,SUM(C9:E9),(IF($A$1=40269,SUM(C9:F9),(IF($A$1=40299,SUM(C9:G9),(IF($A$1=40330,SUM(C9:H9),(IF($A$1=40360,SUM(C9:I9),0)))))))))))))+(IF($A$1=40391,SUM(C9:J9),(IF($A$1=40422,SUM(C9:K9),(IF($A$1=40452,SUM(C9:L9),(IF($A$1=40483,SUM(C9:M9))))))))))+(IF($A$1=40513,SUM(C9:N9),0)) -> 0 | Q9: =(IF($A$1=40179,C9,(IF($A$1=40210,D9,(IF($A$1=40238,E9,(IF($A$1=40269,F9,(IF($A$1=40299,G9,(IF($A$1=40330,H9,(IF($A$1=40360,I9,0)))))))))))))+(IF($A$1=40391,J9,(IF($A$1=40422,K9,(IF($A$1=40452,L9,(IF($A$1=40483,M9)))))))))+(IF($A$1=40513,N9,0)) -> 0
A10: SERVICE | B10: 53243001 | O10: =SUM(C10:N10) -> 0 | P10: =(IF($A$1=40179,C10,(IF($A$1=40210,SUM(C10:D10),(IF($A$1=40238,SUM(C10:E10),(IF($A$1=40269,SUM(C10:F10),(IF($A$1=40299,SUM(C10:G10),(IF($A$1=40330,SUM(C10:H10),(IF($A$1=40360,SUM(C10:I10),0)))))))))))))+(IF($A$1=40391,SUM(C10:J10),(IF($A$1=40422,SUM(C10:K10),(IF($A$1=40452,SUM(C10:L10),(IF($A$1=40483,SUM(C10:M10))))))))))+(IF($A$1=40513,SUM(C10:N10),0)) -> 0 | Q10: =(IF($A$1=40179,C10,(IF($A$1=40210,D10,(IF($A$1=40238,E10,(IF($A$1=40269,F10,(IF($A$1=40299,G10,(IF($A$1=40330,H10,(IF($A$1=40360,I10,0)))))))))))))+(IF($A$1=40391,J10,(IF($A$1=40422,K10,(IF($A$1=40452,L10,(IF($A$1=40483,M10)))))))))+(IF($A$1=40513,N10,0)) -> 0
A11: RELATED EXP. | B11: 53244001 | O11: =SUM(C11:N11) -> 0 | P11: =(IF($A$1=40179,C11,(IF($A$1=40210,SUM(C11:D11),(IF($A$1=40238,SUM(C11:E11),(IF($A$1=40269,SUM(C11:F11),(IF($A$1=40299,SUM(C11:G11),(IF($A$1=40330,SUM(C11:H11),(IF($A$1=40360,SUM(C11:I11),0)))))))))))))+(IF($A$1=40391,SUM(C11:J11),(IF($A$1=40422,SUM(C11:K11),(IF($A$1=40452,SUM(C11:L11),(IF($A$1=40483,SUM(C11:M11))))))))))+(IF($A$1=40513,SUM(C11:N11),0)) -> 0 | Q11: =(IF($A$1=40179,C11,(IF($A$1=40210,D11,(IF($A$1=40238,E11,(IF($A$1=40269,F11,(IF($A$1=40299,G11,(IF($A$1=40330,H11,(IF($A$1=40360,I11,0)))))))))))))+(IF($A$1=40391,J11,(IF($A$1=40422,K11,(IF($A$1=40452,L11,(IF($A$1=40483,M11)))))))))+(IF($A$1=40513,N11,0)) -> 0
A12: EMPL. MEALS | B12: 53245001 | O12: =SUM(C12:N12) -> 0 | P12: =(IF($A$1=40179,C12,(IF($A$1=40210,SUM(C12:D12),(IF($A$1=40238,SUM(C12:E12),(IF($A$1=40269,SUM(C12:F12),(IF($A$1=40299,SUM(C12:G12),(IF($A$1=40330,SUM(C12:H12),(IF($A$1=40360,SUM(C12:I12),0)))))))))))))+(IF($A$1=40391,SUM(C12:J12),(IF($A$1=40422,SUM(C12:K12),(IF($A$1=40452,SUM(C12:L12),(IF($A$1=40483,SUM(C12:M12))))))))))+(IF($A$1=40513,SUM(C12:N12),0)) -> 0 | Q12: =(IF($A$1=40179,C12,(IF($A$1=40210,D12,(IF($A$1=40238,E12,(IF($A$1=40269,F12,(IF($A$1=40299,G12,(IF($A$1=40330,H12,(IF($A$1=40360,I12,0)))))))))))))+(IF($A$1=40391,J12,(IF($A$1=40422,K12,(IF($A$1=40452,L12,(IF($A$1=40483,M12)))))))))+(IF($A$1=40513,N12,0)) -> 0
O13: =SUM(C13:N13) -> 0 | P13: =(IF($A$1=40179,C13,(IF($A$1=40210,SUM(C13:D13),(IF($A$1=40238,SUM(C13:E13),(IF($A$1=40269,SUM(C13:F13),(IF($A$1=40299,SUM(C13:G13),(IF($A$1=40330,SUM(C13:H13),(IF($A$1=40360,SUM(C13:I13),0)))))))))))))+(IF($A$1=40391,SUM(C13:J13),(IF($A$1=40422,SUM(C13:K13),(IF($A$1=40452,SUM(C13:L13),(IF($A$1=40483,SUM(C13:M13))))))))))+(IF($A$1=40513,SUM(C13:N13),0)) -> 0 | Q13: =(IF($A$1=40179,C13,(IF($A$1=40210,D13,(IF($A$1=40238,E13,(IF($A$1=40269,F13,(IF($A$1=40299,G13,(IF($A$1=40330,H13,(IF($A$1=40360,I13,0)))))))))))))+(IF($A$1=40391,J13,(IF($A$1=40422,K13,(IF($A$1=40452,L13,(IF($A$1=40483,M13)))))))))+(IF($A$1=40513,N13,0)) -> 0
A14: TOTAL PAY & REL. | C14: 147832.84 | D14: 158624 | O14: =SUM(C14:N14) -> 306456.84 | P14: =(IF($A$1=40179,C14,(IF($A$1=40210,SUM(C14:D14),(IF($A$1=40238,SUM(C14:E14),(IF($A$1=40269,SUM(C14:F14),(IF($A$1=40299,SUM(C14:G14),(IF($A$1=40330,SUM(C14:H14),(IF($A$1=40360,SUM(C14:I14),0)))))))))))))+(IF($A$1=40391,SUM(C14:J14),(IF($A$1=40422,SUM(C14:K14),(IF($A$1=40452,SUM(C14:L14),(IF($A$1=40483,SUM(C14:M14))))))))))+(IF($A$1=40513,SUM(C14:N14),0)) -> 0 | Q14: =(IF($A$1=40179,C14,(IF($A$1=40210,D14,(IF($A$1=40238,E14,(IF($A$1=40269,F14,(IF($A$1=40299,G14,(IF($A$1=40330,H14,(IF($A$1=40360,I14,0)))))))))))))+(IF($A$1=40391,J14,(IF($A$1=40422,K14,(IF($A$1=40452,L14,(IF($A$1=40483,M14)))))))))+(IF($A$1=40513,N14,0)) -> 0 | S14: 40269 | DE14: 4
