Workbook

Sheet Total
A1: Site Name | B1: Day | C1: Month | D1: Year | E1: Total Electricity Kwh | F1: Electricity Tariff ($/Kwh) | G1: Natual Gas (m3) | H1: Natural Gas $/m3 | I1: Water Utility Supply (m3) m3 | J1: Water Utility Supply (m3) $/m3 | K1: Room Nights
A2: Cairo at The First Residence | B2: 1 | C2: 2 | D2: 2021 | E2: 20187.71 | F2: 1.53 | G2: =1099.84+269.4 -> 1369.24 | H2: 3.89 | I2: 212.28 | J2: 10 | K2: 55
A3: Cairo at The First Residence | B3: =B2+1 -> 2 | C3: 2 | D3: 2021 | E3: 20187.71 | F3: =F2 -> 1.53 | G3: =1099.84+269.4 -> 1369.24 | H3: 3.89 | I3: 212.28 | J3: 10 | K3: 55
A4: Cairo at The First Residence | B4: =B3+1 -> 3 | C4: 2 | D4: 2021 | E4: 20187.71 | F4: =F3 -> 1.53 | G4: =1099.84+269.4 -> 1369.24 | H4: 3.89 | I4: 212.28 | J4: 10 | K4: 55
A5: Cairo at The First Residence | B5: =B4+1 -> 4 | C5: 2 | D5: 2021 | E5: 20187.71 | F5: =F4 -> 1.53 | G5: =1099.84+269.4 -> 1369.24 | H5: 3.89 | I5: 212.28 | J5: 10 | K5: 55
A6: Cairo at The First Residence | B6: =B5+1 -> 5 | C6: 2 | D6: 2021 | E6: 20187.71 | F6: =F5 -> 1.53 | G6: =1099.84+269.4 -> 1369.24 | H6: 3.89 | I6: 212.28 | J6: 10 | K6: 55
A7: Cairo at The First Residence | B7: =B6+1 -> 6 | C7: 2 | D7: 2021 | E7: 20187.71 | F7: =F6 -> 1.53 | G7: =1099.84+269.4 -> 1369.24 | H7: 3.89 | I7: 212.28 | J7: 10 | K7: 55
A8: Cairo at The First Residence | B8: =B7+1 -> 7 | C8: 2 | D8: 2021 | E8: 20187.71 | F8: =F7 -> 1.53 | G8: =1099.84+269.4 -> 1369.24 | H8: 3.89 | I8: 212.28 | J8: 10 | K8: 55
A9: Cairo at The First Residence | B9: =B8+1 -> 8 | C9: 2 | D9: 2021 | E9: 20187.71 | F9: =F8 -> 1.53 | G9: =1099.84+269.4 -> 1369.24 | H9: 3.89 | I9: 212.28 | J9: 10 | K9: 55
A10: Cairo at The First Residence | B10: =B9+1 -> 9 | C10: 2 | D10: 2021 | E10: 20187.71 | F10: =F9 -> 1.53 | G10: =1099.84+269.4 -> 1369.24 | H10: 3.89 | I10: 212.28 | J10: 10 | K10: 55
A11: Cairo at The First Residence | B11: =B10+1 -> 10 | C11: 2 | D11: 2021 | E11: 20187.71 | F11: =F10 -> 1.53 | G11: =1099.84+269.4 -> 1369.24 | H11: 3.89 | I11: 212.28 | J11: 10 | K11: 55
A12: Cairo at The First Residence | B12: =B11+1 -> 11 | C12: 2 | D12: 2021 | E12: 20187.71 | F12: =F11 -> 1.53 | G12: =1099.84+269.4 -> 1369.24 | H12: 3.89 | I12: 212.28 | J12: 10 | K12: 55
A13: Cairo at The First Residence | B13: =B12+1 -> 12 | C13: 2 | D13: 2021 | E13: 20187.71 | F13: =F12 -> 1.53 | G13: =1099.84+269.4 -> 1369.24 | H13: 3.89 | I13: 212.28 | J13: 10 | K13: 55
A14: Cairo at The First Residence | B14: =B13+1 -> 13 | C14: 2 | D14: 2021 | E14: 20187.71 | F14: =F13 -> 1.53 | G14: =1099.84+269.4 -> 1369.24 | H14: 3.89 | I14: 212.28 | J14: 10 | K14: 55
... A29: Cairo at The First Residence | B29: =B28+1 -> 28 | C29: 2 | D29: 2021 | E29: 20187.71 | F29: =F28 -> 1.53 | G29: =1099.84+269.4 -> 1369.24 | H29: 3.89 | I29: 212.28 | J29: 10 | K29: 56
A30: Cairo at The First Residence | B30: =B29+1 -> 29 | C30: 2 | D30: 2021 | E30: =Elect!BW34 -> 0 | F30: =F29 -> 1.53 | G30: =Gas!K35 -> 0 | H30: 3.89 | I30: =Water!H35 -> 0 | J30: 10 | K30: =Elect!BX34 -> 0
A31: Cairo at The First Residence | B31: =B30+1 -> 30 | C31: 2 | D31: 2021 | E31: =Elect!BW35 -> 0 | F31: =F30 -> 1.53 | G31: =Gas!K36 -> 0 | H31: 3.89 | I31: =Water!H36 -> 0 | J31: 10 | K31: =Elect!BX35 -> 0
A32: Cairo at The First Residence | B32: =B31+1 -> 31 | C32: 2 | D32: 2021 | E32: =Elect!BW36 -> 0 | F32: =F31 -> 1.53 | G32: =Gas!K37 -> 0 | H32: 3.89 | I32: =Water!H37 -> 0 | J32: 10 | K32: =Elect!BX36 -> 0

Sheet Submetering
A1: Site Name | B1: Day | C1: Month | D1: Year | E1: Electricity | F1: Main Feeder -KWh | G1: T2+T8 -KWh | H1: La Gourmandize -KWh | I1: Casino 3rd floor EM -KWh | J1: Casino 3rd floor Normal -KWh | K1: Chiller 1 -KWh | L1: Chiller 2 -KWh | M1: Chiller 3 -KWh | N1: Chiller 4 -KWh | O1: Chiller 5 -KWh | P1: Chiller 6 -KWh | Q1: Cooling towers -KWh | R1: Chiller Pumps -KWh | S1: Cooling Tower Pumps -KWh | T1: Fiber Chiller -KWh | U1: Mall Ceiling light -KWh | V1: LG Bakery -KWh | W1: LG Bakery light ( Old lockers ) -KWh | X1: MCCR1 -KWh | Y1: Children Swimming Pool -KWh | Z1: DPH1 -KWh | AA1: Guest Rooms Emerg. -KWh | AB1: Hotel Hoods -KWh | AC1: Main G2 -KWh | AD1: Old Casino Emergency -KWh | AE1: L / A -KWh | AF1: L / B -KWh | AG1: L / C -KWh | AH1: Water | AI1: Main water meter 1 -m3 | AJ1: Main water meter 2 -m3 | AK1: Main water meter 3 -m3 | AL1: Gas | AM1: Main Gas Flow Meter -m3 | AN1: Laundry Gas Flow Meter -m3 | AO1: Gourmandize Gas Flow Meter -m3 | AP1: Room Nights
A2: Cairo at The First Residence | B2: 1 | C2: 2 | D2: 2021 | F2: =Elect!J6 -> 2651 | G2: =Elect!K6 -> 2851 | H2: =Elect!Q6 -> 600 | I2: =Elect!W6 -> 154 | J2: =Elect!Y6 -> 240 | K2: =Elect!AA6 -> 0 | L2: =Elect!AC6 -> 1045.69 | M2: =Elect!AE6 -> 0 | N2: =Elect!AG6 -> 0 | O2: =Elect!AI6 -> 12.215238 | P2: =Elect!AK6 -> 12.164762 | Q2: =Elect!AM6 -> 108.65 | R2: =Elect!AO6 -> 1529.58 | S2: =Elect!AQ6 -> 172.81786 | T2: =Elect!AT6 -> 85.8375 | U2: =Elect!AV6 -> 220 | V2: =Elect!AX6 -> 127 | W2: =Elect!AZ6 -> 28 | X2: =Elect!BB6 -> 192 | Y2: =Elect!BD6 -> 68 | Z2: =Elect!BF6 -> 2693 | AA2: =Elect!BH6 -> 107.67857 | AB2: =Elect!BJ6 -> 0 | AC2: =Elect!BL6 -> 5078.2 | AD2: =Elect!BP6 -> 273 | AE2: =Elect!BR6 -> 946 | AF2: =Elect!BT6 -> 110 | AG2: =Elect!BV6 -> 197 | AI2: =Water!C7 -> 75.4 | AJ2: =Water!E7 -> 203 | AK2: =Water!G7 -> 0 | AM2: =Gas!C7 -> 608.44 | AN2: =Gas!E7 -> 331.8 | AO2: =Gas!G7 -> 30 | AP2: 55
A3: Cairo at The First Residence | B3: =B2+1 -> 2 | C3: 2 | D3: 2021 | F3: =Elect!J7 -> 4448 | G3: =Elect!K7 -> 2845 | H3: =Elect!Q7 -> 420 | I3: =Elect!W7 -> 148 | J3: =Elect!Y7 -> 258 | K3: =Elect!AA7 -> 297.33 | L3: =Elect!AC7 -> 1240.73 | M3: =Elect!AE7 -> 0 | N3: =Elect!AG7 -> 255.46 | O3: =Elect!AI7 -> 12.215238 | P3: =Elect!AK7 -> 12.164762 | Q3: =Elect!AM7 -> 238.5 | R3: =Elect!AO7 -> 404.39 | S3: =Elect!AQ7 -> 172.81786 | T3: =Elect!AT7 -> 80.2125 | U3: =Elect!AV7 -> 266 | V3: =Elect!AX7 -> 121 | W3: =Elect!AZ7 -> 38 | X3: =Elect!BB7 -> 200 | Y3: =Elect!BD7 -> 65 | Z3: =Elect!BF7 -> 3241 | AA3: =Elect!BH7 -> 107.67857 | AB3: =Elect!BJ7 -> 0 | AC3: =Elect!BL7 -> 4604.05 | AD3: =Elect!BP7 -> 273 | AE3: =Elect!BR7 -> 773 | AF3: =Elect!BT7 -> 118 | AG3: =Elect!BV7 -> 206 | AI3: =Water!C8 -> 98.6 | AJ3: =Water!E8 -> 110.2 | AK3: =Water!G8 -> 0 | AM3: =Gas!C8 -> 931.74 | AN3: =Gas!E8 -> 248.5 | AO3: =Gas!G8 -> 56 | AP3: 55
A4: Cairo at The First Residence | B4: =B3+1 -> 3 | C4: 2 | D4: 2021 | F4: =Elect!J8 -> 4078 | G4: =Elect!K8 -> 2734 | H4: =Elect!Q8 -> 390 | I4: =Elect!W8 -> 142 | J4: =Elect!Y8 -> 248 | K4: =Elect!AA8 -> 82.68 | L4: =Elect!AC8 -> 629.11 | M4: =Elect!AE8 -> 36.57 | N4: =Elect!AG8 -> 498.73 | O4: =Elect!AI8 -> 12.215238 | P4: =Elect!AK8 -> 12.164762 | Q4: =Elect!AM8 -> 242.21 | R4: =Elect!AO8 -> 3525.56 | S4: =Elect!AQ8 -> 172.81786 | T4: =Elect!AT8 -> 85.275 | U4: =Elect!AV8 -> 266 | V4: =Elect!AX8 -> 109 | W4: =Elect!AZ8 -> 39 | X4: =Elect!BB8 -> 398 | Y4: =Elect!BD8 -> 62 | Z4: =Elect!BF8 -> 3433 | AA4: =Elect!BH8 -> 107.67857 | AB4: =Elect!BJ8 -> 0 | AC4: =Elect!BL8 -> 4510.75 | AD4: =Elect!BP8 -> 273 | AE4: =Elect!BR8 -> 809 | AF4: =Elect!BT8 -> 116 | AG4: =Elect!BV8 -> 197 | AI4: =Water!C9 -> 110.2 | AJ4: =Water!E9 -> 75.4 | AK4: =Water!G9 -> 0 | AM4: =Gas!C9 -> 851.18 | AN4: =Gas!E9 -> 267.4 | AO4: =Gas!G9 -> 65 | AP4: 55
A5: Cairo at The First Residence | B5: =B4+1 -> 4 | C5: 2 | D5: 2021 | F5: =Elect!J9 -> 4608 | G5: =Elect!K9 -> 2854 | H5: =Elect!Q9 -> 540 | I5: =Elect!W9 -> 144 | J5: =Elect!Y9 -> 246 | K5: =Elect!AA9 -> 277.72 | L5: =Elect!AC9 -> 0 | M5: =Elect!AE9 -> 2401.43 | N5: =Elect!AG9 -> 0 | O5: =Elect!AI9 -> 12.215238 | P5: =Elect!AK9 -> 12.164762 | Q5: =Elect!AM9 -> 244.33 | R5: =Elect!AO9 -> 2289.6 | S5: =Elect!AQ9 -> 172.81786 | T5: =Elect!AT9 -> 87.8625 | U5: =Elect!AV9 -> 287 | V5: =Elect!AX9 -> 114 | W5: =Elect!AZ9 -> 41 | X5: =Elect!BB9 -> 383 | Y5: =Elect!BD9 -> 64 | Z5: =Elect!BF9 -> 3474 | AA5: =Elect!BH9 -> 107.67857 | AB5: =Elect!BJ9 -> 0 | AC5: =Elect!BL9 -> 4548 | AD5: =Elect!BP9 -> 273 | AE5: =Elect!BR9 -> 935 | AF5: =Elect!BT9 -> 125 | AG5: =Elect!BV9 -> 198 | AI5: =Water!C10 -> 174 | AJ5: =Water!E10 -> 179.8 | AK5: =Water!G10 -> 0 | AM5: =Gas!C10 -> 891.46 | AN5: =Gas!E10 -> 289.8 | AO5: =Gas!G10 -> 53 | AP5: 55
A6: Cairo at The First Residence | B6: =B5+1 -> 5 | C6: 2 | D6: 2021 | F6: =Elect!J10 -> 4629 | G6: =Elect!K10 -> 2786 | H6: =Elect!Q10 -> 510 | I6: =Elect!W10 -> 145 | J6: =Elect!Y10 -> 253 | K6: =Elect!AA10 -> 0 | L6: =Elect!AC10 -> 0 | M6: =Elect!AE10 -> 1743.17 | N6: =Elect!AG10 -> 0 | O6: =Elect!AI10 -> 12.215238 | P6: =Elect!AK10 -> 12.164762 | Q6: =Elect!AM10 -> 149.46 | R6: =Elect!AO10 -> 1706.6 | S6: =Elect!AQ10 -> 172.81786 | T6: =Elect!AT10 -> 68.7375 | U6: =Elect!AV10 -> 300 | V6: =Elect!AX10 -> 115 | W6: =Elect!AZ10 -> 35 | X6: =Elect!BB10 -> 359 | Y6: =Elect!BD10 -> 55 | Z6: =Elect!BF10 -> 3623 | AA6: =Elect!BH10 -> 107.67857 | AB6: =Elect!BJ10 -> 0 | AC6: =Elect!BL10 -> 5068 | AD6: =Elect!BP10 -> 273 | AE6: =Elect!BR10 -> 300 | AF6: =Elect!BT10 -> 80 | AG6: =Elect!BV10 -> 90 | AI6: =Water!C11 -> 174 | AJ6: =Water!E11 -> 150.8 | AK6: =Water!G11 -> 0 | AM6: =Gas!C11 -> 998.52 | AN6: =Gas!E11 -> 312.9 | AO6: =Gas!G11 -> 81 | AP6: 55
A7: Cairo at The First Residence | B7: =B6+1 -> 6 | C7: 2 | D7: 2021 | F7: =Elect!J11 -> 4466 | G7: =Elect!K11 -> 2826 | H7: =Elect!Q11 -> 600 | I7: =Elect!W11 -> 146 | J7: =Elect!Y11 -> 246 | K7: =Elect!AA11 -> 0 | L7: =Elect!AC11 -> 0 | M7: =Elect!AE11 -> 1742.11 | N7: =Elect!AG11 -> 0 | O7: =Elect!AI11 -> 12.215238 | P7: =Elect!AK11 -> 12.164762 | Q7: =Elect!AM11 -> 291.5 | R7: =Elect!AO11 -> 1824.79 | S7: =Elect!AQ11 -> 172.81786 | T7: =Elect!AT11 -> 86.9625 | U7: =Elect!AV11 -> 285 | V7: =Elect!AX11 -> 125 | W7: =Elect!AZ11 -> 29 | X7: =Elect!BB11 -> 378 | Y7: =Elect!BD11 -> 62 | Z7: =Elect!BF11 -> 3448 | AA7: =Elect!BH11 -> 107.67857 | AB7: =Elect!BJ11 -> 0 | AC7: =Elect!BL11 -> 4899.65 | AD7: =Elect!BP11 -> 273 | AE7: =Elect!BR11 -> 728 | AF7: =Elect!BT11 -> 35 | AG7: =Elect!BV11 -> 112 | AI7: =Water!C12 -> 116 | AJ7: =Water!E12 -> 58 | AK7: =Water!G12 -> 0 | AM7: =Gas!C12 -> 945.52 | AN7: =Gas!E12 -> 262.5 | AO7: =Gas!G12 -> 86 | AP7: 55
A8: Cairo at The First Residence | B8: =B7+1 -> 7 | C8: 2 | D8: 2021 | F8: =Elect!J12 -> 4626 | G8: =Elect!K12 -> 2998 | H8: =Elect!Q12 -> 600 | I8: =Elect!W12 -> 146 | J8: =Elect!Y12 -> 254 | K8: =Elect!AA12 -> 0 | L8: =Elect!AC12 -> 0 | M8: =Elect!AE12 -> 2625.62 | N8: =Elect!AG12 -> 0 | O8: =Elect!AI12 -> 12.215238 | P8: =Elect!AK12 -> 12.164762 | Q8: =Elect!AM12 -> 248.57 | R8: =Elect!AO12 -> 2170.88 | S8: =Elect!AQ12 -> 172.81786 | T8: =Elect!AT12 -> 80.2125 | U8: =Elect!AV12 -> 301 | V8: =Elect!AX12 -> 125 | W8: =Elect!AZ12 -> 44 | X8: =Elect!BB12 -> 396 | Y8: =Elect!BD12 -> 63 | Z8: =Elect!BF12 -> 3649 | AA8: =Elect!BH12 -> 107.67857 | AB8: =Elect!BJ12 -> 0 | AC8: =Elect!BL12 -> 4808.25 | AD8: =Elect!BP12 -> 273 | AE8: =Elect!BR12 -> 964 | AF8: =Elect!BT12 -> 111 | AG8: =Elect!BV12 -> 203 | AI8: =Water!C13 -> 111.02857 | AJ8: =Water!E13 -> 75.4 | AK8: =Water!G13 -> 0 | AM8: =Gas!C13 -> 786.52 | AN8: =Gas!E13 -> 254.1 | AO8: =Gas!G13 -> 79 | AP8: 55
A9: Cairo at The First Residence | B9: =B8+1 -> 8 | C9: 2 | D9: 2021 | F9: =Elect!J13 -> 4853 | G9: =Elect!K13 -> 3115 | H9: =Elect!Q13 -> 690 | I9: =Elect!W13 -> 147 | J9: =Elect!Y13 -> 251 | K9: =Elect!AA13 -> 1101.87 | L9: =Elect!AC13 -> 0 | M9: =Elect!AE13 -> 1019.19 | N9: =Elect!AG13 -> 0 | O9: =Elect!AI13 -> 12.215238 | P9: =Elect!AK13 -> 12.164762 | Q9: =Elect!AM13 -> 365.7 | R9: =Elect!AO13 -> 2178.83 | S9: =Elect!AQ13 -> 172.81786 | T9: =Elect!AT13 -> 72.45 | U9: =Elect!AV13 -> 257 | V9: =Elect!AX13 -> 126 | W9: =Elect!AZ13 -> 37 | X9: =Elect!BB13 -> 392 | Y9: =Elect!BD13 -> 62 | Z9: =Elect!BF13 -> 3504 | AA9: =Elect!BH13 -> 107.67857 | AB9: =Elect!BJ13 -> 0 | AC9: =Elect!BL13 -> 4719 | AD9: =Elect!BP13 -> 273 | AE9: =Elect!BR13 -> 1055 | AF9: =Elect!BT13 -> 125 | AG9: =Elect!BV13 -> 203 | AI9: =Water!C14 -> 120.97143 | AJ9: =Water!E14 -> 63.8 | AK9: =Water!G14 -> 0 | AM9: =Gas!C14 -> 906.3 | AN9: =Gas!E14 -> 251.3 | AO9: =Gas!G14 -> 88 | AP9: 55
A10: Cairo at The First Residence | B10: =B9+1 -> 9 | C10: 2 | D10: 2021 | F10: =Elect!J14 -> 4910 | G10: =Elect!K14 -> 3099 | H10: =Elect!Q14 -> 630 | I10: =Elect!W14 -> 143 | J10: =Elect!Y14 -> 244 | K10: =Elect!AA14 -> 2077.07 | L10: =Elect!AC14 -> 0 | M10: =Elect!AE14 -> 0 | N10: =Elect!AG14 -> 0 | O10: =Elect!AI14 -> 12.215238 | P10: =Elect!AK14 -> 12.164762 | Q10: =Elect!AM14 -> 488.66 | R10: =Elect!AO14 -> 2249.85 | S10: =Elect!AQ14 -> 172.81786 | T10: =Elect!AT14 -> 71.6625 | U10: =Elect!AV14 -> 284 | V10: =Elect!AX14 -> 126 | W10: =Elect!AZ14 -> 39 | X10: =Elect!BB14 -> 405 | Y10: =Elect!BD14 -> 64 | Z10: =Elect!BF14 -> 3376 | AA10: =Elect!BH14 -> 107.67857 | AB10: =Elect!BJ14 -> 0 | AC10: =Elect!BL14 -> 4720.55 | AD10: =Elect!BP14 -> 273 | AE10: =Elect!BR14 -> 1102 | AF10: =Elect!BT14 -> 119 | AG10: =Elect!BV14 -> 199 | AI10: =Water!C15 -> 139.2 | AJ10: =Water!E15 -> 52.2 | AK10: =Water!G15 -> 0 | AM10: =Gas!C15 -> 862.84 | AN10: =Gas!E15 -> 263.9 | AO10: =Gas!G15 -> 79 | AP10: 55
A11: Cairo at The First Residence | B11: =B10+1 -> 10 | C11: 2 | D11: 2021 | F11: =Elect!J15 -> 4535 | G11: =Elect!K15 -> 3305 | H11: =Elect!Q15 -> 570 | I11: =Elect!W15 -> 151 | J11: =Elect!Y15 -> 219 | K11: =Elect!AA15 -> 2177.24 | L11: =Elect!AC15 -> 0 | M11: =Elect!AE15 -> 0 | N11: =Elect!AG15 -> 0 | O11: =Elect!AI15 -> 12.215238 | P11: =Elect!AK15 -> 12.164762 | Q11: =Elect!AM15 -> 515.16 | R11: =Elect!AO15 -> 2374.4 | S11: =Elect!AQ15 -> 172.81786 | T11: =Elect!AT15 -> 76.05 | U11: =Elect!AV15 -> 272 | V11: =Elect!AX15 -> 130 | W11: =Elect!AZ15 -> 43 | X11: =Elect!BB15 -> 412 | Y11: =Elect!BD15 -> 68 | Z11: =Elect!BF15 -> 3545 | AA11: =Elect!BH15 -> 107.67857 | AB11: =Elect!BJ15 -> 0 | AC11: =Elect!BL15 -> 4813.25 | AD11: =Elect!BP15 -> 353 | AE11: =Elect!BR15 -> 1155 | AF11: =Elect!BT15 -> 120 | AG11: =Elect!BV15 -> 208 | AI11: =Water!C16 -> 127.6 | AJ11: =Water!E16 -> 69.6 | AK11: =Water!G16 -> 0 | AM11: =Gas!C16 -> 897.82 | AN11: =Gas!E16 -> 256.9 | AO11: =Gas!G16 -> 75 | AP11: 55
A12: Cairo at The First Residence | B12: =B11+1 -> 11 | C12: 2 | D12: 2021 | F12: =Elect!J16 -> 5806 | G12: =Elect!K16 -> 3134 | H12: =Elect!Q16 -> 690 | I12: =Elect!W16 -> 138 | J12: =Elect!Y16 -> 275 | K12: =Elect!AA16 -> 1860.83 | L12: =Elect!AC16 -> 0 | M12: =Elect!AE16 -> 0 | N12: =Elect!AG16 -> 0 | O12: =Elect!AI16 -> 12.215238 | P12: =Elect!AK16 -> 12.164762 | Q12: =Elect!AM16 -> 467.46 | R12: =Elect!AO16 -> 2121.06 | S12: =Elect!AQ16 -> 172.81786 | T12: =Elect!AT16 -> 82.2375 | U12: =Elect!AV16 -> 282 | V12: =Elect!AX16 -> 122 | W12: =Elect!AZ16 -> 36 | X12: =Elect!BB16 -> 340 | Y12: =Elect!BD16 -> 62 | Z12: =Elect!BF16 -> 3239 | AA12: =Elect!BH16 -> 107.67857 | AB12: =Elect!BJ16 -> 0 | AC12: =Elect!BL16 -> 4321.3 | AD12: =Elect!BP16 -> 222 | AE12: =Elect!BR16 -> 899 | AF12: =Elect!BT16 -> 107 | AG12: =Elect!BV16 -> 189 | AI12: =Water!C17 -> 127.6 | AJ12: =Water!E17 -> 52.2 | AK12: =Water!G17 -> 0 | AM12: =Gas!C17 -> 874.5 | AN12: =Gas!E17 -> 255.5 | AO12: =Gas!G17 -> 76 | AP12: 55
A13: Cairo at The First Residence | B13: =B12+1 -> 12 | C13: 2 | D13: 2021 | F13: =Elect!J17 -> 4685 | G13: =Elect!K17 -> 3241 | H13: =Elect!Q17 -> 570 | I13: =Elect!W17 -> 143 | J13: =Elect!Y17 -> 243 | K13: =Elect!AA17 -> 2070.18 | L13: =Elect!AC17 -> 0 | M13: =Elect!AE17 -> 0 | N13: =Elect!AG17 -> 0 | O13: =Elect!AI17 -> 12.215238 | P13: =Elect!AK17 -> 12.164762 | Q13: =Elect!AM17 -> 491.31 | R13: =Elect!AO17 -> 2177.24 | S13: =Elect!AQ17 -> 172.81786 | T13: =Elect!AT17 -> 63.675 | U13: =Elect!AV17 -> 289 | V13: =Elect!AX17 -> 127 | W13: =Elect!AZ17 -> 21 | X13: =Elect!BB17 -> 379 | Y13: =Elect!BD17 -> 65 | Z13: =Elect!BF17 -> 3327 | AA13: =Elect!BH17 -> 107.67857 | AB13: =Elect!BJ17 -> 0 | AC13: =Elect!BL17 -> 4467.8 | AD13: =Elect!BP17 -> 276 | AE13: =Elect!BR17 -> 936 | AF13: =Elect!BT17 -> 100 | AG13: =Elect!BV17 -> 200 | AI13: =Water!C18 -> 133.4 | AJ13: =Water!E18 -> 63.8 | AK13: =Water!G18 -> 0 | AM13: =Gas!C18 -> 896.76 | AN13: =Gas!E18 -> 261.1 | AO13: =Gas!G18 -> 72 | AP13: 55
A14: Cairo at The First Residence | B14: =B13+1 -> 13 | C14: 2 | D14: 2021 | F14: =Elect!J18 -> 5904 | G14: =Elect!K18 -> 3255 | H14: =Elect!Q18 -> 600 | I14: =Elect!W18 -> 148 | J14: =Elect!Y18 -> 249 | K14: =Elect!AA18 -> 2098.27 | L14: =Elect!AC18 -> 0 | M14: =Elect!AE18 -> 0 | N14: =Elect!AG18 -> 0 | O14: =Elect!AI18 -> 12.215238 | P14: =Elect!AK18 -> 12.164762 | Q14: =Elect!AM18 -> 506.68 | R14: =Elect!AO18 -> 2244.55 | S14: =Elect!AQ18 -> 172.81786 | T14: =Elect!AT18 -> 78.8625 | U14: =Elect!AV18 -> 250 | V14: =Elect!AX18 -> 104 | W14: =Elect!AZ18 -> 21 | X14: =Elect!BB18 -> 388 | Y14: =Elect!BD18 -> 66 | Z14: =Elect!BF18 -> 3465 | AA14: =Elect!BH18 -> 107.67857 | AB14: =Elect!BJ18 -> 0 | AC14: =Elect!BL18 -> 4660 | AD14: =Elect!BP18 -> 277 | AE14: =Elect!BR18 -> 938 | AF14: =Elect!BT18 -> 122 | AG14: =Elect!BV18 -> 204 | AI14: =Water!C19 -> 133.4 | AJ14: =Water!E19 -> 58 | AK14: =Water!G19 -> 0 | AM14: =Gas!C19 -> 870.26 | AN14: =Gas!E19 -> 256.9 | AO14: =Gas!G19 -> 78 | AP14: 55
... A29: Cairo at The First Residence | B29: =B28+1 -> 28 | C29: 2 | D29: 2021 | F29: =Elect!J33 -> 4950 | G29: =Elect!K33 -> 3334 | H29: =Elect!Q33 -> 540 | I29: =Elect!W33 -> 145 | J29: =Elect!Y33 -> 247 | K29: =Elect!AA33 -> 1445.84 | L29: =Elect!AC33 -> 203.52 | M29: =Elect!AE33 -> 0 | N29: =Elect!AG33 -> 0 | O29: =Elect!AI33 -> 12.19 | P29: =Elect!AK33 -> 12.19 | Q29: =Elect!AM33 -> 169.6 | R29: =Elect!AO33 -> 2031.49 | S29: =Elect!AQ33 -> 173.84 | T29: =Elect!AT33 -> 15.8625 | U29: =Elect!AV33 -> 305 | V29: =Elect!AX33 -> 104 | W29: =Elect!AZ33 -> 32 | X29: =Elect!BB33 -> 368 | Y29: =Elect!BD33 -> 63 | Z29: =Elect!BF33 -> 3342 | AA29: =Elect!BH33 -> 116 | AB29: =Elect!BJ33 -> 0 | AC29: =Elect!BL33 -> 4724.1 | AD29: =Elect!BP33 -> 399 | AE29: =Elect!BR33 -> 950 | AF29: =Elect!BT33 -> 112 | AG29: =Elect!BV33 -> 194 | AI29: =Water!C34 -> 116 | AJ29: =Water!E34 -> 5.8 | AK29: =Water!G34 -> 5.22 | AM29: =Gas!C34 -> 1092.86 | AN29: =Gas!E34 -> 264.6 | AO29: =Gas!G34 -> 69 | AP29: 56
A30: Cairo at The First Residence | B30: =B29+1 -> 29 | C30: 2 | D30: 2021 | F30: =Elect!J34 -> 0 | G30: =Elect!K34 -> 0 | H30: =Elect!Q34 -> 0 | I30: =Elect!W34 -> 0 | J30: =Elect!Y34 -> 0 | K30: =Elect!AA34 -> 0 | L30: =Elect!AC34 -> 0 | M30: =Elect!AE34 -> 0 | N30: =Elect!AG34 -> 0 | O30: =Elect!AI34 -> 0 | P30: =Elect!AK34 -> 0 | Q30: =Elect!AM34 -> 0 | R30: =Elect!AO34 -> 0 | S30: =Elect!AQ34 -> 0 | T30: =Elect!AT34 -> 0 | U30: =Elect!AV34 -> 0 | V30: =Elect!AX34 -> 0 | W30: =Elect!AZ34 -> 0 | X30: =Elect!BB34 -> 0 | Y30: =Elect!BD34 -> 0 | Z30: =Elect!BF34 -> 0 | AA30: =Elect!BH34 -> 0 | AB30: =Elect!BJ34 -> 0 | AC30: =Elect!BL34 -> 0 | AD30: =Elect!BP34 -> 0 | AE30: =Elect!BR34 -> 0 | AF30: =Elect!BT34 -> 0 | AG30: =Elect!BV34 -> 0 | AI30: =Water!C35 -> 0 | AJ30: =Water!E35 -> 0 | AK30: =Water!G35 -> 0 | AM30: =Gas!C35 -> 0 | AN30: =Gas!E35 -> 0 | AO30: =Gas!G35 -> 0 | AP30: =Elect!DC34 -> 0
A31: Cairo at The First Residence | B31: =B30+1 -> 30 | C31: 2 | D31: 2021 | F31: =Elect!J35 -> 0 | G31: =Elect!K35 -> 0 | H31: =Elect!Q35 -> 0 | I31: =Elect!W35 -> 0 | J31: =Elect!Y35 -> 0 | K31: =Elect!AA35 -> 0 | L31: =Elect!AC35 -> 0 | M31: =Elect!AE35 -> 0 | N31: =Elect!AG35 -> 0 | O31: =Elect!AI35 -> 0 | P31: =Elect!AK35 -> 0 | Q31: =Elect!AM35 -> 0 | R31: =Elect!AO35 -> 0 | S31: =Elect!AQ35 -> 0 | T31: =Elect!AT35 -> 0 | U31: =Elect!AV35 -> 0 | V31: =Elect!AX35 -> 0 | W31: =Elect!AZ35 -> 0 | X31: =Elect!BB35 -> 0 | Y31: =Elect!BD35 -> 0 | Z31: =Elect!BF35 -> 0 | AA31: =Elect!BH35 -> 0 | AB31: =Elect!BJ35 -> 0 | AC31: =Elect!BL35 -> 0 | AD31: =Elect!BP35 -> 0 | AE31: =Elect!BR35 -> 0 | AF31: =Elect!BT35 -> 0 | AG31: =Elect!BV35 -> 0 | AI31: =Water!C36 -> 0 | AJ31: =Water!E36 -> 0 | AK31: =Water!G36 -> 0 | AM31: =Gas!C36 -> 0 | AN31: =Gas!E36 -> 0 | AO31: =Gas!G36 -> 0 | AP31: =Elect!DC35 -> 0
A32: Cairo at The First Residence | B32: =B31+1 -> 31 | C32: 2 | D32: 2021 | F32: =Elect!J36 -> 0 | G32: =Elect!K36 -> 0 | H32: =Elect!Q36 -> 0 | I32: =Elect!W36 -> 0 | J32: =Elect!Y36 -> 0 | K32: =Elect!AA36 -> 0 | L32: =Elect!AC36 -> 0 | M32: =Elect!AE36 -> 0 | N32: =Elect!AG36 -> 0 | O32: =Elect!AI36 -> 0 | P32: =Elect!AK36 -> 0 | Q32: =Elect!AM36 -> 0 | R32: =Elect!AO36 -> 0 | S32: =Elect!AQ36 -> 0 | T32: =Elect!AT36 -> 0 | U32: =Elect!AV36 -> 0 | V32: =Elect!AX36 -> 0 | W32: =Elect!AZ36 -> 0 | X32: =Elect!BB36 -> 0 | Y32: =Elect!BD36 -> 0 | Z32: =Elect!BF36 -> 0 | AA32: =Elect!BH36 -> 0 | AB32: =Elect!BJ36 -> 0 | AC32: =Elect!BL36 -> 0 | AD32: =Elect!BP36 -> 0 | AE32: =Elect!BR36 -> 0 | AF32: =Elect!BT36 -> 0 | AG32: =Elect!BV36 -> 0 | AI32: =Water!C37 -> 0 | AJ32: =Water!E37 -> 0 | AK32: =Water!G37 -> 0 | AM32: =Gas!C37 -> 0 | AN32: =Gas!E37 -> 0 | AO32: =Gas!G37 -> 0 | AP32: =Elect!DC36 -> 0

Sheet Elect
A1: February | M1: Electricity | BW1: Power Taxes | BX1: 0.0006 | BY1: Max Demand | CA1: 500 | CB1: Electricity UP | CD1: 1.15
BW2: Light Taxes | BX2: 0.03 | BY2: PF Penalty | CB2: Max. Demand UP | CD2: 30
A3: Date | B3: COUNTER (1) | D3: MD | F3: KVAR | H3: n | I3: Guest Rooms Consumption | R3: Casino Consumption | Z3: Plant Room Shared Loads | AS3: To Be Charged By First Arabian | BO3: From Main Panel G2 | BW3: Total Consumption. | BX3: No. Of | BY3: KWH/ | BZ3: No. Of | CA3: KWH/ | CB3: Total Cost | CC3: L.E\ | CD3: L.E\
B4: Reading | C4: Consp. F: *800 | D4: Reading | E4: Consp F: 80 | F4: Reading | G4: Consp. F:*10 | I4: Main Feeder | J4: Consp | K4: T2+T8 | L4: Trans T2 | M4: Consp | N4: Trans T8 | O4: Consp | P4: La Gourmandize | Q4: Consp *30 | R4: Casino 1 | S4: Consp | T4: Casino 2 | U4: Consp | V4: Casino 3rd floor EM | W4: Consp | X4: Casino 3rd floor Normal | Y4: Consp | Z4: Chiller 1 | AA4: Consp 53% | AB4: Chiller 2 | AC4: Consp 53% | AD4: Chiller 3 | AE4: Consp 53% | AF4: Chiller 4 | AG4: Consp 53% | AH4: Chiller 5 | AI4: Consp 53% | AJ4: Chiller 6 | AK4: Consp 53% | AL4: Cooling Towers | AM4: Consp 53% | AN4: Chiller Pumps | AO4: Consp 53% | AP4: Cooling Tower Pumps | AQ4: Consp 53% | AR4: Total Plant Room Consp | AS4: Fiber Chiller (N24) | AT4: Consp | AU4: Mall Ceiling light (N4) | AV4: Consp | AW4: LG Bakery (N2) | AX4: Consp | AY4: LG Bakery light ( Old lockers ) | AZ4: Consp | BA4: MCCR1 | BB4: Consp | BC4: Children Swimming pool | BD4: Consp | BE4: DPH1 | BF4: Consp | BG4: Guest Rooms Emergency | BH4: Consp | BI4: Hotel Hoods | BJ4: Consp | BK4: Main G2 | BL4: Consp | BM4: Total Consp From First Arabian | BN4: First Arabian Charge Back | BO4: Old Casino Emergency | BP4: Consp | BQ4: L / A | BR4: Consp | BS4: L / B | BT4: Consp | BU4: L / C | BV4: Consp | BX4: Rooms | BY4: room | BZ4: guest | CA4: guest | CC4: Room | CD4: Guest
A5: Last Month Reading | I5: 22053832 | J5: =IF(I5>=I4,I5-I4,0) -> 0 | K5: =M5+O5 -> 0 | L5: 2554 | M5: =IF(L5>=L4,L5-L4,0) -> 0 | N5: 2947 | O5: =IF(N5>=N4,N5-N4,0) -> 0 | P5: 214736 | Q5: =IF(P5>=P4,P5-P4,0)*30 -> 0 | R5: 702925 | S5: =IF(R5>=R4,R5-R4,0) -> 0 | T5: 344001 | U5: =IF(T5>=T4,T5-T4,0) -> 0 | V5: 130984 | W5: =IF(V5>=V4,V5-V4,0) -> 0 | X5: 238297 | Y5: =IF(X5>=X4,X5-X4,0) -> 0 | Z5: 315335 | AA5: =IF(Z5>=Z4,Z5-Z4,0)*0.53 -> 0 | AB5: 382273 | AC5: =IF(AB5>=AB4,AB5-AB4,0)*0.53 -> 0 | AD5: 562354 | AE5: =IF(AD5>=AD4,AD5-AD4,0)*0.53 -> 0 | AF5: 307674 | AG5: =IF(AF5>=AF4,AF5-AF4,0)*0.53 -> 0 | AH5: 329500.27 | AI5: =IF(AH5>=AH4,AH5-AH4,0)*0.53 -> 0 | AJ5: 707620.73 | AK5: =IF(AJ5>=AJ4,AJ5-AJ4,0)*0.53 -> 0 | AL5: 533781 | AM5: =IF(AL5>=AL4,AL5-AL4,0)*0.53 -> 0 | AN5: 713719 | AO5: =IF(AN5>=AN4,AN5-AN4,0)*0.53 -> 0 | AP5: 380115.79 | AQ5: =IF(AP5>=AP4,AP5-AP4,0)*0.53 -> 0 | AR5: =AA5+AC5+AE5+AG5+AI5+AK5+AM5+AO5+AQ5 -> 0 | AS5: 7214129 | AT5: =IF(AS5>=AS4,AS5-AS4,0)*0.1125 -> 0 | AU5: 574281 | AV5: =IF(AU5>=AU4,AU5-AU4,0) -> 0 | AW5: 913468 | AX5: =IF(AW5>=AW4,AW5-AW4,0) -> 0 | AY5: 794724 | AZ5: =IF(AY5>=AY4,AY5-AY4,0) -> 0 | BA5: 2337484 | BB5: =IF(BA5>=BA4,BA5-BA4,0) -> 0 | BC5: 209470 | BD5: =IF(BC5>=BC4,BC5-BC4,0) -> 0 | BE5: 17670739 | BF5: =IF(BE5>=BE4,BE5-BE4,0) -> 0 | BG5: 498031.71 | BH5: =IF(BG5>=BG4,BG5-BG4,0) -> 0 | BI5: 8805 | BJ5: =IF(BI5>=BI4,BI5-BI4,0) -> 0 | BK5: 21892385 | BL5: =IF(BK5>=BK4,BK5-BK4,0)-(0.45*BR5)-(0.45*BT5)-BV5 -> 0 | BM5: =AT5+AV5+AX5+AZ5+BB5+BD5+BF5+BH5+BJ5+BL5 -> 0 | BN5: =BM5+AR5 -> 0 | BO5: 1369414 | BP5: =IF(BO5>=BO4,BO5-BO4,0) -> 0 | BQ5: 3491211 | BR5: =IF(BQ5>=BQ4,BQ5-BQ4,0) -> 0 | BS5: 372745 | BT5: =IF(BS5>=BS4,BS5-BS4,0) -> 0 | BU5: 452214 | BV5: =IF(BU5>=BU4,BU5-BU4,0) -> 0
A6: 1 | C6: =IF(+B6-B5>0,B6-B5,(B6-B5)>0)*800 -> 0 | E6: =IF(+D6-D5>0,D6-D5,(D6-D5)>0)*80 -> 0 | G6: =IF(+F6-F5>0,F6-F5,(F6-F5)>0)*10 -> 0 | H6: 56 | I6: 22056483 | J6: =IF(I6>=I5,I6-I5,0) -> 2651 | K6: =M6+O6 -> 2851 | L6: 3246 | M6: =IF(L6>=L5,L6-L5,0) -> 692 | N6: 5106 | O6: =IF(N6>=N5,N6-N5,0) -> 2159 | P6: 214756 | Q6: =IF(P6>=P5,P6-P5,0)*30 -> 600 | R6: 702925 | S6: =IF(R6>=R5,R6-R5,0) -> 0 | T6: 344001 | U6: =IF(T6>=T5,T6-T5,0) -> 0 | V6: 131138 | W6: =IF(V6>=V5,V6-V5,0) -> 154 | X6: 238537 | Y6: =IF(X6>=X5,X6-X5,0) -> 240 | Z6: 315335 | AA6: =IF(Z6>=Z5,Z6-Z5,0)*0.53 -> 0 | AB6: 384246 | AC6: =IF(AB6>=AB5,AB6-AB5,0)*0.53 -> 1045.69 | AD6: 562354 | AE6: =IF(AD6>=AD5,AD6-AD5,0)*0.53 -> 0 | AF6: 307674 | AG6: =IF(AF6>=AF5,AF6-AF5,0)*0.53 -> 0 | AH6: 329523.32 | AI6: =IF(AH6>=AH5,AH6-AH5,0)*0.53 -> 12.215238 | AJ6: 707643.68 | AK6: =IF(AJ6>=AJ5,AJ6-AJ5,0)*0.53 -> 12.164762 | AL6: 533986 | AM6: =IF(AL6>=AL5,AL6-AL5,0)*0.53 -> 108.65 | AN6: 716605 | AO6: =IF(AN6>=AN5,AN6-AN5,0)*0.53 -> 1529.58 | AP6: 380441.86 | AQ6: =IF(AP6>=AP5,AP6-AP5,0)*0.53 -> 172.81786 | AR6: =AA6+AC6+AE6+AG6+AI6+AK6+AM6+AO6+AQ6 -> 2881.1179 | AS6: 7214892 | AT6: =IF(AS6>=AS5,AS6-AS5,0)*0.1125 -> 85.8375 | AU6: 574501 | AV6: =IF(AU6>=AU5,AU6-AU5,0) -> 220 | AW6: 913595 | AX6: =IF(AW6>=AW5,AW6-AW5,0) -> 127 | AY6: 794752 | AZ6: =IF(AY6>=AY5,AY6-AY5,0) -> 28 | BA6: 2337676 | BB6: =IF(BA6>=BA5,BA6-BA5,0) -> 192 | BC6: 209538 | BD6: =IF(BC6>=BC5,BC6-BC5,0) -> 68 | BE6: 17673432 | BF6: =IF(BE6>=BE5,BE6-BE5,0) -> 2693 | BG6: 498139.39 | BH6: =IF(BG6>=BG5,BG6-BG5,0) -> 107.67857 | BI6: 8805 | BJ6: =IF(BI6>=BI5,BI6-BI5,0) -> 0 | BK6: 21898135 | BL6: =IF(BK6>=BK5,BK6-BK5,0)-(0.45*BR6)-(0.45*BT6)-BV6 -> 5078.2 | BM6: =AT6+AV6+AX6+AZ6+BB6+BD6+BF6+BH6+BJ6+BL6 -> 8599.7161 | BN6: =BM6+AR6 -> 11480.834 | BO6: 1369687 | BP6: =IF(BO6>=BO5,BO6-BO5,0) -> 273 | BQ6: 3492157 | BR6: =IF(BQ6>=BQ5,BQ6-BQ5,0) -> 946 | BS6: 372855 | BT6: =IF(BS6>=BS5,BS6-BS5,0) -> 110 | BU6: 452411 | BV6: =IF(BU6>=BU5,BU6-BU5,0) -> 197 | BW6: =J6+Q6+AR6+BM6 -> 14731.834 | BX6: 32 | BY6: =IF(BW6>0,BW6/BX5,0) -> #DIV/0! | CA6: =IF(BW6>0,BW6/BZ6,0) -> #DIV/0! | CB6: =BW6*CD1 -> 16941.609 | CC6: =IF(CB6>0,CB6/BX5,0) -> #DIV/0! | CD6: =IF(CB6>0,CB6/BZ6,0) -> #DIV/0!
A7: 2 | I7: 22060931 | J7: =IF(I7>=I6,I7-I6,0) -> 4448 | K7: =M7+O7 -> 2845 | L7: 4406 | M7: =IF(L7>=L6,L7-L6,0) -> 1160 | N7: 6791 | O7: =IF(N7>=N6,N7-N6,0) -> 1685 | P7: 214770 | Q7: =IF(P7>=P6,P7-P6,0)*30 -> 420 | R7: 702925 | S7: =IF(R7>=R6,R7-R6,0) -> 0 | T7: 344001 | U7: =IF(T7>=T6,T7-T6,0) -> 0 | V7: 131286 | W7: =IF(V7>=V6,V7-V6,0) -> 148 | X7: 238795 | Y7: =IF(X7>=X6,X7-X6,0) -> 258 | Z7: 315896 | AA7: =IF(Z7>=Z6,Z7-Z6,0)*0.53 -> 297.33 | AB7: 386587 | AC7: =IF(AB7>=AB6,AB7-AB6,0)*0.53 -> 1240.73 | AD7: 562354 | AE7: =IF(AD7>=AD6,AD7-AD6,0)*0.53 -> 0 | AF7: 308156 | AG7: =IF(AF7>=AF6,AF7-AF6,0)*0.53 -> 255.46 | AH7: 329546.37 | AI7: =IF(AH7>=AH6,AH7-AH6,0)*0.53 -> 12.215238 | AJ7: 707666.63 | AK7: =IF(AJ7>=AJ6,AJ7-AJ6,0)*0.53 -> 12.164762 | AL7: 534436 | AM7: =IF(AL7>=AL6,AL7-AL6,0)*0.53 -> 238.5 | AN7: 717368 | AO7: =IF(AN7>=AN6,AN7-AN6,0)*0.53 -> 404.39 | AP7: 380767.93 | AQ7: =IF(AP7>=AP6,AP7-AP6,0)*0.53 -> 172.81786 | AR7: =AA7+AC7+AE7+AG7+AI7+AK7+AM7+AO7+AQ7 -> 2633.6079 | AS7: 7215605 | AT7: =IF(AS7>=AS6,AS7-AS6,0)*0.1125 -> 80.2125 | AU7: 574767 | AV7: =IF(AU7>=AU6,AU7-AU6,0) -> 266 | AW7: 913716 | AX7: =IF(AW7>=AW6,AW7-AW6,0) -> 121 | AY7: 794790 | AZ7: =IF(AY7>=AY6,AY7-AY6,0) -> 38 | BA7: 2337876 | BB7: =IF(BA7>=BA6,BA7-BA6,0) -> 200 | BC7: 209603 | BD7: =IF(BC7>=BC6,BC7-BC6,0) -> 65 | BE7: 17676673 | BF7: =IF(BE7>=BE6,BE7-BE6,0) -> 3241 | BG7: 498247.07 | BH7: =IF(BG7>=BG6,BG7-BG6,0) -> 107.67857 | BI7: 8805 | BJ7: =IF(BI7>=BI6,BI7-BI6,0) -> 0 | BK7: 21903346 | BL7: =IF(BK7>=BK6,BK7-BK6,0)-(0.45*BR7)-(0.45*BT7)-BV7 -> 4604.05 | BM7: =AT7+AV7+AX7+AZ7+BB7+BD7+BF7+BH7+BJ7+BL7 -> 8722.9411 | BN7: =BM7+AR7 -> 11356.549 | BO7: 1369960 | BP7: =IF(BO7>=BO6,BO7-BO6,0) -> 273 | BQ7: 3492930 | BR7: =IF(BQ7>=BQ6,BQ7-BQ6,0) -> 773 | BS7: 372973 | BT7: =IF(BS7>=BS6,BS7-BS6,0) -> 118 | BU7: 452617 | BV7: =IF(BU7>=BU6,BU7-BU6,0) -> 206 | BW7: =J7+Q7+AR7+BM7 -> 16224.549 | BX7: 36 | BY7: =IF(BW7>0,BW7/BX6,0) -> 507.01715 | CA7: =IF(BW7>0,BW7/BZ7,0) -> #DIV/0! | CB7: =BW7*CD1 -> 18658.231 | CC7: =IF(CB7>0,CB7/BX6,0) -> 583.06973 | CD7: =IF(CB7>0,CB7/BZ7,0) -> #DIV/0!
A8: 3 | C8: =IF(+B8-B7>0,B8-B7,(B8-B7)>0)*800 -> 0 | E8: =IF(+D8-D7>0,D8-D7,(D8-D7)>0)*80 -> 0 | G8: =IF(+F8-F7>0,F8-F7,(F8-F7)>0)*10 -> 0 | H8: 57 | I8: 22065009 | J8: =IF(I8>=I7,I8-I7,0) -> 4078 | K8: =M8+O8 -> 2734 | L8: 5616 | M8: =IF(L8>=L7,L8-L7,0) -> 1210 | N8: 8315 | O8: =IF(N8>=N7,N8-N7,0) -> 1524 | P8: 214783 | Q8: =IF(P8>=P7,P8-P7,0)*30 -> 390 | R8: 702925 | S8: =IF(R8>=R7,R8-R7,0) -> 0 | T8: 344001 | U8: =IF(T8>=T7,T8-T7,0) -> 0 | V8: 131428 | W8: =IF(V8>=V7,V8-V7,0) -> 142 | X8: 239043 | Y8: =IF(X8>=X7,X8-X7,0) -> 248 | Z8: 316052 | AA8: =IF(Z8>=Z7,Z8-Z7,0)*0.53 -> 82.68 | AB8: 387774 | AC8: =IF(AB8>=AB7,AB8-AB7,0)*0.53 -> 629.11 | AD8: 562423 | AE8: =IF(AD8>=AD7,AD8-AD7,0)*0.53 -> 36.57 | AF8: 309097 | AG8: =IF(AF8>=AF7,AF8-AF7,0)*0.53 -> 498.73 | AH8: 329569.42 | AI8: =IF(AH8>=AH7,AH8-AH7,0)*0.53 -> 12.215238 | AJ8: 707689.58 | AK8: =IF(AJ8>=AJ7,AJ8-AJ7,0)*0.53 -> 12.164762 | AL8: 534893 | AM8: =IF(AL8>=AL7,AL8-AL7,0)*0.53 -> 242.21 | AN8: 724020 | AO8: =IF(AN8>=AN7,AN8-AN7,0)*0.53 -> 3525.56 | AP8: 381094 | AQ8: =IF(AP8>=AP7,AP8-AP7,0)*0.53 -> 172.81786 | AR8: =AA8+AC8+AE8+AG8+AI8+AK8+AM8+AO8+AQ8 -> 5212.0579 | AS8: 7216363 | AT8: =IF(AS8>=AS7,AS8-AS7,0)*0.1125 -> 85.275 | AU8: 575033 | AV8: =IF(AU8>=AU7,AU8-AU7,0) -> 266 | AW8: 913825 | AX8: =IF(AW8>=AW7,AW8-AW7,0) -> 109 | AY8: 794829 | AZ8: =IF(AY8>=AY7,AY8-AY7,0) -> 39 | BA8: 2338274 | BB8: =IF(BA8>=BA7,BA8-BA7,0) -> 398 | BC8: 209665 | BD8: =IF(BC8>=BC7,BC8-BC7,0) -> 62 | BE8: 17680106 | BF8: =IF(BE8>=BE7,BE8-BE7,0) -> 3433 | BG8: 498354.75 | BH8: =IF(BG8>=BG7,BG8-BG7,0) -> 107.67857 | BI8: 8805 | BJ8: =IF(BI8>=BI7,BI8-BI7,0) -> 0 | BK8: 21908470 | BL8: =IF(BK8>=BK7,BK8-BK7,0)-(0.45*BR8)-(0.45*BT8)-BV8 -> 4510.75 | BM8: =AT8+AV8+AX8+AZ8+BB8+BD8+BF8+BH8+BJ8+BL8 -> 9010.7036 | BN8: =BM8+AR8 -> 14222.761 | BO8: 1370233 | BP8: =IF(BO8>=BO7,BO8-BO7,0) -> 273 | BQ8: 3493739 | BR8: =IF(BQ8>=BQ7,BQ8-BQ7,0) -> 809 | BS8: 373089 | BT8: =IF(BS8>=BS7,BS8-BS7,0) -> 116 | BU8: 452814 | BV8: =IF(BU8>=BU7,BU8-BU7,0) -> 197 | BW8: =J8+Q8+AR8+BM8 -> 18690.761 | BX8: 43 | BY8: =IF(BW8>0,BW8/BX7,0) -> 519.18782 | CA8: =IF(BW8>0,BW8/BZ8,0) -> #DIV/0! | CB8: =BW8*CD1 -> 21494.376 | CC8: =IF(CB8>0,CB8/BX7,0) -> 597.06599 | CD8: =IF(CB8>0,CB8/BZ8,0) -> #DIV/0!
A9: 4 | C9: =IF(+B9-B8>0,B9-B8,(B9-B8)>0)*800 -> 0 | E9: =IF(+D9-D8>0,D9-D8,(D9-D8)>0)*80 -> 0 | G9: =IF(+F9-F8>0,F9-F8,(F9-F8)>0)*10 -> 0 | I9: 22069617 | J9: =IF(I9>=I8,I9-I8,0) -> 4608 | K9: =M9+O9 -> 2854 | L9: 6960 | M9: =IF(L9>=L8,L9-L8,0) -> 1344 | N9: 9825 | O9: =IF(N9>=N8,N9-N8,0) -> 1510 | P9: 214801 | Q9: =IF(P9>=P8,P9-P8,0)*30 -> 540 | R9: 702925 | S9: =IF(R9>=R8,R9-R8,0) -> 0 | T9: 344001 | U9: =IF(T9>=T8,T9-T8,0) -> 0 | V9: 131572 | W9: =IF(V9>=V8,V9-V8,0) -> 144 | X9: 239289 | Y9: =IF(X9>=X8,X9-X8,0) -> 246 | Z9: 316576 | AA9: =IF(Z9>=Z8,Z9-Z8,0)*0.53 -> 277.72 | AB9: 387774 | AC9: =IF(AB9>=AB8,AB9-AB8,0)*0.53 -> 0 | AD9: 566954 | AE9: =IF(AD9>=AD8,AD9-AD8,0)*0.53 -> 2401.43 | AF9: 309097 | AG9: =IF(AF9>=AF8,AF9-AF8,0)*0.53 -> 0 | AH9: 329592.46 | AI9: =IF(AH9>=AH8,AH9-AH8,0)*0.53 -> 12.215238 | AJ9: 707712.54 | AK9: =IF(AJ9>=AJ8,AJ9-AJ8,0)*0.53 -> 12.164762 | AL9: 535354 | AM9: =IF(AL9>=AL8,AL9-AL8,0)*0.53 -> 244.33 | AN9: 728340 | AO9: =IF(AN9>=AN8,AN9-AN8,0)*0.53 -> 2289.6 | AP9: 381420.07 | AQ9: =IF(AP9>=AP8,AP9-AP8,0)*0.53 -> 172.81786 | AR9: =AA9+AC9+AE9+AG9+AI9+AK9+AM9+AO9+AQ9 -> 5410.2779 | AS9: 7217144 | AT9: =IF(AS9>=AS8,AS9-AS8,0)*0.1125 -> 87.8625 | AU9: 575320 | AV9: =IF(AU9>=AU8,AU9-AU8,0) -> 287 | AW9: 913939 | AX9: =IF(AW9>=AW8,AW9-AW8,0) -> 114 | AY9: 794870 | AZ9: =IF(AY9>=AY8,AY9-AY8,0) -> 41 | BA9: 2338657 | BB9: =IF(BA9>=BA8,BA9-BA8,0) -> 383 | BC9: 209729 | BD9: =IF(BC9>=BC8,BC9-BC8,0) -> 64 | BE9: 17683580 | BF9: =IF(BE9>=BE8,BE9-BE8,0) -> 3474 | BG9: 498462.43 | BH9: =IF(BG9>=BG8,BG9-BG8,0) -> 107.67857 | BI9: 8805 | BJ9: =IF(BI9>=BI8,BI9-BI8,0) -> 0 | BK9: 21913693 | BL9: =IF(BK9>=BK8,BK9-BK8,0)-(0.45*BR9)-(0.45*BT9)-BV9 -> 4548 | BM9: =AT9+AV9+AX9+AZ9+BB9+BD9+BF9+BH9+BJ9+BL9 -> 9106.5411 | BN9: =BM9+AR9 -> 14516.819 | BO9: 1370506 | BP9: =IF(BO9>=BO8,BO9-BO8,0) -> 273 | BQ9: 3494674 | BR9: =IF(BQ9>=BQ8,BQ9-BQ8,0) -> 935 | BS9: 373214 | BT9: =IF(BS9>=BS8,BS9-BS8,0) -> 125 | BU9: 453012 | BV9: =IF(BU9>=BU8,BU9-BU8,0) -> 198 | BW9: =J9+Q9+AR9+BM9 -> 19664.819 | BX9: 66 | BY9: =IF(BW9>0,BW9/BX8,0) -> 457.32137 | CA9: =IF(BW9>0,BW9/BZ9,0) -> #DIV/0! | CB9: =BW9*CD1 -> 22614.542 | CC9: =IF(CB9>0,CB9/BX8,0) -> 525.91958 | CD9: =IF(CB9>0,CB9/BZ9,0) -> #DIV/0!
A10: 5 | C10: =IF(+B10-B9>0,B10-B9,(B10-B9)>0)*800 -> 0 | E10: =IF(+D10-D9>0,D10-D9,(D10-D9)>0)*80 -> 0 | G10: =IF(+F10-F9>0,F10-F9,(F10-F9)>0)*10 -> 0 | H10: 58 | I10: 22074246 | J10: =IF(I10>=I9,I10-I9,0) -> 4629 | K10: =M10+O10 -> 2786 | L10: 8261 | M10: =IF(L10>=L9,L10-L9,0) -> 1301 | N10: 11310 | O10: =IF(N10>=N9,N10-N9,0) -> 1485 | P10: 214818 | Q10: =IF(P10>=P9,P10-P9,0)*30 -> 510 | R10: 702925 | S10: =IF(R10>=R9,R10-R9,0) -> 0 | T10: 344001 | U10: =IF(T10>=T9,T10-T9,0) -> 0 | V10: 131717 | W10: =IF(V10>=V9,V10-V9,0) -> 145 | X10: 239542 | Y10: =IF(X10>=X9,X10-X9,0) -> 253 | Z10: 316576 | AA10: =IF(Z10>=Z9,Z10-Z9,0)*0.53 -> 0 | AB10: 387774 | AC10: =IF(AB10>=AB9,AB10-AB9,0)*0.53 -> 0 | AD10: 570243 | AE10: =IF(AD10>=AD9,AD10-AD9,0)*0.53 -> 1743.17 | AF10: 309097 | AG10: =IF(AF10>=AF9,AF10-AF9,0)*0.53 -> 0 | AH10: 329615.51 | AI10: =IF(AH10>=AH9,AH10-AH9,0)*0.53 -> 12.215238 | AJ10: 707735.49 | AK10: =IF(AJ10>=AJ9,AJ10-AJ9,0)*0.53 -> 12.164762 | AL10: 535636 | AM10: =IF(AL10>=AL9,AL10-AL9,0)*0.53 -> 149.46 | AN10: 731560 | AO10: =IF(AN10>=AN9,AN10-AN9,0)*0.53 -> 1706.6 | AP10: 381746.14 | AQ10: =IF(AP10>=AP9,AP10-AP9,0)*0.53 -> 172.81786 | AR10: =AA10+AC10+AE10+AG10+AI10+AK10+AM10+AO10+AQ10 -> 3796.4279 | AS10: 7217755 | AT10: =IF(AS10>=AS9,AS10-AS9,0)*0.1125 -> 68.7375 | AU10: 575620 | AV10: =IF(AU10>=AU9,AU10-AU9,0) -> 300 | AW10: 914054 | AX10: =IF(AW10>=AW9,AW10-AW9,0) -> 115 | AY10: 794905 | AZ10: =IF(AY10>=AY9,AY10-AY9,0) -> 35 | BA10: 2339016 | BB10: =IF(BA10>=BA9,BA10-BA9,0) -> 359 | BC10: 209784 | BD10: =IF(BC10>=BC9,BC10-BC9,0) -> 55 | BE10: 17687203 | BF10: =IF(BE10>=BE9,BE10-BE9,0) -> 3623 | BG10: 498570.11 | BH10: =IF(BG10>=BG9,BG10-BG9,0) -> 107.67857 | BI10: 8805 | BJ10: =IF(BI10>=BI9,BI10-BI9,0) -> 0 | BK10: 21919022 | BL10: =IF(BK10>=BK9,BK10-BK9,0)-(0.45*BR10)-(0.45*BT10)-BV10 -> 5068 | BM10: =AT10+AV10+AX10+AZ10+BB10+BD10+BF10+BH10+BJ10+BL10 -> 9731.4161 | BN10: =BM10+AR10 -> 13527.844 | BO10: 1370779 | BP10: =IF(BO10>=BO9,BO10-BO9,0) -> 273 | BQ10: 3494974 | BR10: =IF(BQ10>=BQ9,BQ10-BQ9,0) -> 300 | BS10: 373294 | BT10: =IF(BS10>=BS9,BS10-BS9,0) -> 80 | BU10: 453102 | BV10: =IF(BU10>=BU9,BU10-BU9,0) -> 90 | BW10: =J10+Q10+AR10+BM10 -> 18666.844 | BX10: 68 | BY10: =IF(BW10>0,BW10/BX9,0) -> 282.83097 | CA10: =IF(BW10>0,BW10/BZ10,0) -> #DIV/0! | CB10: =BW10*CD1 -> 21466.871 | CC10: =IF(CB10>0,CB10/BX9,0) -> 325.25561 | CD10: =IF(CB10>0,CB10/BZ10,0) -> #DIV/0!
A11: 6 | C11: =IF(+B11-B10>0,B11-B10,(B11-B10)>0)*800 -> 0 | E11: =IF(+D11-D10>0,D11-D10,(D11-D10)>0)*80 -> 0 | G11: =IF(+F11-F10>0,F11-F10,(F11-F10)>0)*10 -> 0 | I11: 22078712 | J11: =IF(I11>=I10,I11-I10,0) -> 4466 | K11: =M11+O11 -> 2826 | L11: 9539 | M11: =IF(L11>=L10,L11-L10,0) -> 1278 | N11: 12858 | O11: =IF(N11>=N10,N11-N10,0) -> 1548 | P11: 214838 | Q11: =IF(P11>=P10,P11-P10,0)*30 -> 600 | R11: 702925 | S11: =IF(R11>=R10,R11-R10,0) -> 0 | T11: 344001 | U11: =IF(T11>=T10,T11-T10,0) -> 0 | V11: 131863 | W11: =IF(V11>=V10,V11-V10,0) -> 146 | X11: 239788 | Y11: =IF(X11>=X10,X11-X10,0) -> 246 | Z11: 316576 | AA11: =IF(Z11>=Z10,Z11-Z10,0)*0.53 -> 0 | AB11: 387774 | AC11: =IF(AB11>=AB10,AB11-AB10,0)*0.53 -> 0 | AD11: 573530 | AE11: =IF(AD11>=AD10,AD11-AD10,0)*0.53 -> 1742.11 | AF11: 309097 | AG11: =IF(AF11>=AF10,AF11-AF10,0)*0.53 -> 0 | AH11: 329638.56 | AI11: =IF(AH11>=AH10,AH11-AH10,0)*0.53 -> 12.215238 | AJ11: 707758.44 | AK11: =IF(AJ11>=AJ10,AJ11-AJ10,0)*0.53 -> 12.164762 | AL11: 536186 | AM11: =IF(AL11>=AL10,AL11-AL10,0)*0.53 -> 291.5 | AN11: 735003 | AO11: =IF(AN11>=AN10,AN11-AN10,0)*0.53 -> 1824.79 | AP11: 382072.21 | AQ11: =IF(AP11>=AP10,AP11-AP10,0)*0.53 -> 172.81786 | AR11: =AA11+AC11+AE11+AG11+AI11+AK11+AM11+AO11+AQ11 -> 4055.5979 | AS11: 7218528 | AT11: =IF(AS11>=AS10,AS11-AS10,0)*0.1125 -> 86.9625 | AU11: 575905 | AV11: =IF(AU11>=AU10,AU11-AU10,0) -> 285 | AW11: 914179 | AX11: =IF(AW11>=AW10,AW11-AW10,0) -> 125 | AY11: 794934 | AZ11: =IF(AY11>=AY10,AY11-AY10,0) -> 29 | BA11: 2339394 | BB11: =IF(BA11>=BA10,BA11-BA10,0) -> 378 | BC11: 209846 | BD11: =IF(BC11>=BC10,BC11-BC10,0) -> 62 | BE11: 17690651 | BF11: =IF(BE11>=BE10,BE11-BE10,0) -> 3448 | BG11: 498677.79 | BH11: =IF(BG11>=BG10,BG11-BG10,0) -> 107.67857 | BI11: 8805 | BJ11: =IF(BI11>=BI10,BI11-BI10,0) -> 0 | BK11: 21924377 | BL11: =IF(BK11>=BK10,BK11-BK10,0)-(0.45*BR11)-(0.45*BT11)-BV11 -> 4899.65 | BM11: =AT11+AV11+AX11+AZ11+BB11+BD11+BF11+BH11+BJ11+BL11 -> 9421.2911 | BN11: =BM11+AR11 -> 13476.889 | BO11: 1371052 | BP11: =IF(BO11>=BO10,BO11-BO10,0) -> 273 | BQ11: 3495702 | BR11: =IF(BQ11>=BQ10,BQ11-BQ10,0) -> 728 | BS11: 373329 | BT11: =IF(BS11>=BS10,BS11-BS10,0) -> 35 | BU11: 453214 | BV11: =IF(BU11>=BU10,BU11-BU10,0) -> 112 | BW11: =J11+Q11+AR11+BM11 -> 18542.889 | BX11: 75 | BY11: =IF(BW11>0,BW11/BX10,0) -> 272.68954 | CA11: =IF(BW11>0,BW11/BZ11,0) -> #DIV/0! | CB11: =BW11*CD1 -> 21324.322 | CC11: =IF(CB11>0,CB11/BX10,0) -> 313.59297 | CD11: =IF(CB11>0,CB11/BZ11,0) -> #DIV/0!
A12: 7 | C12: =IF(+B12-B11>0,B12-B11,(B12-B11)>0)*800 -> 0 | E12: =IF(+D12-D11>0,D12-D11,(D12-D11)>0)*80 -> 0 | G12: =IF(+F12-F11>0,F12-F11,(F12-F11)>0)*10 -> 0 | H12: 59 | I12: 22083338 | J12: =IF(I12>=I11,I12-I11,0) -> 4626 | K12: =M12+O12 -> 2998 | L12: 10912 | M12: =IF(L12>=L11,L12-L11,0) -> 1373 | N12: 14483 | O12: =IF(N12>=N11,N12-N11,0) -> 1625 | P12: 214858 | Q12: =IF(P12>=P11,P12-P11,0)*30 -> 600 | R12: 702925 | S12: =IF(R12>=R11,R12-R11,0) -> 0 | T12: 344001 | U12: =IF(T12>=T11,T12-T11,0) -> 0 | V12: 132009 | W12: =IF(V12>=V11,V12-V11,0) -> 146 | X12: 240042 | Y12: =IF(X12>=X11,X12-X11,0) -> 254 | Z12: 316576 | AA12: =IF(Z12>=Z11,Z12-Z11,0)*0.53 -> 0 | AB12: 387774 | AC12: =IF(AB12>=AB11,AB12-AB11,0)*0.53 -> 0 | AD12: 578484 | AE12: =IF(AD12>=AD11,AD12-AD11,0)*0.53 -> 2625.62 | AF12: 309097 | AG12: =IF(AF12>=AF11,AF12-AF11,0)*0.53 -> 0 | AH12: 329661.61 | AI12: =IF(AH12>=AH11,AH12-AH11,0)*0.53 -> 12.215238 | AJ12: 707781.39 | AK12: =IF(AJ12>=AJ11,AJ12-AJ11,0)*0.53 -> 12.164762 | AL12: 536655 | AM12: =IF(AL12>=AL11,AL12-AL11,0)*0.53 -> 248.57 | AN12: 739099 | AO12: =IF(AN12>=AN11,AN12-AN11,0)*0.53 -> 2170.88 | AP12: 382398.29 | AQ12: =IF(AP12>=AP11,AP12-AP11,0)*0.53 -> 172.81786 | AR12: =AA12+AC12+AE12+AG12+AI12+AK12+AM12+AO12+AQ12 -> 5242.2679 | AS12: 7219241 | AT12: =IF(AS12>=AS11,AS12-AS11,0)*0.1125 -> 80.2125 | AU12: 576206 | AV12: =IF(AU12>=AU11,AU12-AU11,0) -> 301 | AW12: 914304 | AX12: =IF(AW12>=AW11,AW12-AW11,0) -> 125 | AY12: 794978 | AZ12: =IF(AY12>=AY11,AY12-AY11,0) -> 44 | BA12: 2339790 | BB12: =IF(BA12>=BA11,BA12-BA11,0) -> 396 | BC12: 209909 | BD12: =IF(BC12>=BC11,BC12-BC11,0) -> 63 | BE12: 17694300 | BF12: =IF(BE12>=BE11,BE12-BE11,0) -> 3649 | BG12: 498785.46 | BH12: =IF(BG12>=BG11,BG12-BG11,0) -> 107.67857 | BI12: 8805 | BJ12: =IF(BI12>=BI11,BI12-BI11,0) -> 0 | BK12: 21929872 | BL12: =IF(BK12>=BK11,BK12-BK11,0)-(0.45*BR12)-(0.45*BT12)-BV12 -> 4808.25 | BM12: =AT12+AV12+AX12+AZ12+BB12+BD12+BF12+BH12+BJ12+BL12 -> 9574.1411 | BN12: =BM12+AR12 -> 14816.409 | BO12: 1371325 | BP12: =IF(BO12>=BO11,BO12-BO11,0) -> 273 | BQ12: 3496666 | BR12: =IF(BQ12>=BQ11,BQ12-BQ11,0) -> 964 | BS12: 373440 | BT12: =IF(BS12>=BS11,BS12-BS11,0) -> 111 | BU12: 453417 | BV12: =IF(BU12>=BU11,BU12-BU11,0) -> 203 | BW12: =J12+Q12+AR12+BM12 -> 20042.409 | BX12: 59 | BY12: =IF(BW12>0,BW12/BX11,0) -> 267.23212 | CA12: =IF(BW12>0,BW12/BZ12,0) -> #DIV/0! | CB12: =BW12*CD1 -> 23048.77 | CC12: =IF(CB12>0,CB12/BX11,0) -> 307.31694 | CD12: =IF(CB12>0,CB12/BZ12,0) -> #DIV/0!
A13: 8 | C13: =IF(+B13-B12>0,B13-B12,(B13-B12)>0)*800 -> 0 | E13: =IF(+D13-D12>0,D13-D12,(D13-D12)>0)*80 -> 0 | G13: =IF(+F13-F12>0,F13-F12,(F13-F12)>0)*10 -> 0 | I13: 22088191 | J13: =IF(I13>=I12,I13-I12,0) -> 4853 | K13: =M13+O13 -> 3115 | L13: 12354 | M13: =IF(L13>=L12,L13-L12,0) -> 1442 | N13: 16156 | O13: =IF(N13>=N12,N13-N12,0) -> 1673 | P13: 214881 | Q13: =IF(P13>=P12,P13-P12,0)*30 -> 690 | R13: 702925 | S13: =IF(R13>=R12,R13-R12,0) -> 0 | T13: 344001 | U13: =IF(T13>=T12,T13-T12,0) -> 0 | V13: 132156 | W13: =IF(V13>=V12,V13-V12,0) -> 147 | X13: 240293 | Y13: =IF(X13>=X12,X13-X12,0) -> 251 | Z13: 318655 | AA13: =IF(Z13>=Z12,Z13-Z12,0)*0.53 -> 1101.87 | AB13: 387774 | AC13: =IF(AB13>=AB12,AB13-AB12,0)*0.53 -> 0 | AD13: 580407 | AE13: =IF(AD13>=AD12,AD13-AD12,0)*0.53 -> 1019.19 | AF13: 309097 | AG13: =IF(AF13>=AF12,AF13-AF12,0)*0.53 -> 0 | AH13: 329684.65 | AI13: =IF(AH13>=AH12,AH13-AH12,0)*0.53 -> 12.215238 | AJ13: 707804.35 | AK13: =IF(AJ13>=AJ12,AJ13-AJ12,0)*0.53 -> 12.164762 | AL13: 537345 | AM13: =IF(AL13>=AL12,AL13-AL12,0)*0.53 -> 365.7 | AN13: 743210 | AO13: =IF(AN13>=AN12,AN13-AN12,0)*0.53 -> 2178.83 | AP13: 382724.36 | AQ13: =IF(AP13>=AP12,AP13-AP12,0)*0.53 -> 172.81786 | AR13: =AA13+AC13+AE13+AG13+AI13+AK13+AM13+AO13+AQ13 -> 4862.7879 | AS13: 7219885 | AT13: =IF(AS13>=AS12,AS13-AS12,0)*0.1125 -> 72.45 | AU13: 576463 | AV13: =IF(AU13>=AU12,AU13-AU12,0) -> 257 | AW13: 914430 | AX13: =IF(AW13>=AW12,AW13-AW12,0) -> 126 | AY13: 795015 | AZ13: =IF(AY13>=AY12,AY13-AY12,0) -> 37 | BA13: 2340182 | BB13: =IF(BA13>=BA12,BA13-BA12,0) -> 392 | BC13: 209971 | BD13: =IF(BC13>=BC12,BC13-BC12,0) -> 62 | BE13: 17697804 | BF13: =IF(BE13>=BE12,BE13-BE12,0) -> 3504 | BG13: 498893.14 | BH13: =IF(BG13>=BG12,BG13-BG12,0) -> 107.67857 | BI13: 8805 | BJ13: =IF(BI13>=BI12,BI13-BI12,0) -> 0 | BK13: 21935325 | BL13: =IF(BK13>=BK12,BK13-BK12,0)-(0.45*BR13)-(0.45*BT13)-BV13 -> 4719 | BM13: =AT13+AV13+AX13+AZ13+BB13+BD13+BF13+BH13+BJ13+BL13 -> 9277.1286 | BN13: =BM13+AR13 -> 14139.916 | BO13: 1371598 | BP13: =IF(BO13>=BO12,BO13-BO12,0) -> 273 | BQ13: 3497721 | BR13: =IF(BQ13>=BQ12,BQ13-BQ12,0) -> 1055 | BS13: 373565 | BT13: =IF(BS13>=BS12,BS13-BS12,0) -> 125 | BU13: 453620 | BV13: =IF(BU13>=BU12,BU13-BU12,0) -> 203 | BW13: =J13+Q13+AR13+BM13 -> 19682.916 | BX13: 49 | BY13: =IF(BW13>0,BW13/BX12,0) -> 333.60875 | CA13: =IF(BW13>0,BW13/BZ13,0) -> #DIV/0! | CB13: =BW13*CD1 -> 22635.354 | CC13: =IF(CB13>0,CB13/BX12,0) -> 383.65007 | CD13: =IF(CB13>0,CB13/BZ13,0) -> #DIV/0!
A14: 9 | C14: =IF(+B14-B13>0,B14-B13,(B14-B13)>0)*800 -> 0 | E14: =IF(+D14-D13>0,D14-D13,(D14-D13)>0)*80 -> 0 | G14: =IF(+F14-F13>0,F14-F13,(F14-F13)>0)*10 -> 0 | H14: 60 | I14: 22093101 | J14: =IF(I14>=I13,I14-I13,0) -> 4910 | K14: =M14+O14 -> 3099 | L14: 13763 | M14: =IF(L14>=L13,L14-L13,0) -> 1409 | N14: 17846 | O14: =IF(N14>=N13,N14-N13,0) -> 1690 | P14: 214902 | Q14: =IF(P14>=P13,P14-P13,0)*30 -> 630 | R14: 702925 | S14: =IF(R14>=R13,R14-R13,0) -> 0 | T14: 344001 | U14: =IF(T14>=T13,T14-T13,0) -> 0 | V14: 132299 | W14: =IF(V14>=V13,V14-V13,0) -> 143 | X14: 240537 | Y14: =IF(X14>=X13,X14-X13,0) -> 244 | Z14: 322574 | AA14: =IF(Z14>=Z13,Z14-Z13,0)*0.53 -> 2077.07 | AB14: 387774 | AC14: =IF(AB14>=AB13,AB14-AB13,0)*0.53 -> 0 | AD14: 580407 | AE14: =IF(AD14>=AD13,AD14-AD13,0)*0.53 -> 0 | AF14: 309097 | AG14: =IF(AF14>=AF13,AF14-AF13,0)*0.53 -> 0 | AH14: 329707.7 | AI14: =IF(AH14>=AH13,AH14-AH13,0)*0.53 -> 12.215238 | AJ14: 707827.3 | AK14: =IF(AJ14>=AJ13,AJ14-AJ13,0)*0.53 -> 12.164762 | AL14: 538267 | AM14: =IF(AL14>=AL13,AL14-AL13,0)*0.53 -> 488.66 | AN14: 747455 | AO14: =IF(AN14>=AN13,AN14-AN13,0)*0.53 -> 2249.85 | AP14: 383050.43 | AQ14: =IF(AP14>=AP13,AP14-AP13,0)*0.53 -> 172.81786 | AR14: =AA14+AC14+AE14+AG14+AI14+AK14+AM14+AO14+AQ14 -> 5012.7779 | AS14: 7220522 | AT14: =IF(AS14>=AS13,AS14-AS13,0)*0.1125 -> 71.6625 | AU14: 576747 | AV14: =IF(AU14>=AU13,AU14-AU13,0) -> 284 | AW14: 914556 | AX14: =IF(AW14>=AW13,AW14-AW13,0) -> 126 | AY14: 795054 | AZ14: =IF(AY14>=AY13,AY14-AY13,0) -> 39 | BA14: 2340587 | BB14: =IF(BA14>=BA13,BA14-BA13,0) -> 405 | BC14: 210035 | BD14: =IF(BC14>=BC13,BC14-BC13,0) -> 64 | BE14: 17701180 | BF14: =IF(BE14>=BE13,BE14-BE13,0) -> 3376 | BG14: 499000.82 | BH14: =IF(BG14>=BG13,BG14-BG13,0) -> 107.67857 | BI14: 8805 | BJ14: =IF(BI14>=BI13,BI14-BI13,0) -> 0 | BK14: 21940794 | BL14: =IF(BK14>=BK13,BK14-BK13,0)-(0.45*BR14)-(0.45*BT14)-BV14 -> 4720.55 | BM14: =AT14+AV14+AX14+AZ14+BB14+BD14+BF14+BH14+BJ14+BL14 -> 9193.8911 | BN14: =BM14+AR14 -> 14206.669 | BO14: 1371871 | BP14: =IF(BO14>=BO13,BO14-BO13,0) -> 273 | BQ14: 3498823 | BR14: =IF(BQ14>=BQ13,BQ14-BQ13,0) -> 1102 | BS14: 373684 | BT14: =IF(BS14>=BS13,BS14-BS13,0) -> 119 | BU14: 453819 | BV14: =IF(BU14>=BU13,BU14-BU13,0) -> 199 | BW14: =J14+Q14+AR14+BM14 -> 19746.669 | BX14: 53 | BY14: =IF(BW14>0,BW14/BX13,0) -> 402.99324 | CA14: =IF(BW14>0,BW14/BZ14,0) -> #DIV/0! | CB14: =BW14*CD1 -> 22708.669 | CC14: =IF(CB14>0,CB14/BX13,0) -> 463.44223 | CD14: =IF(CB14>0,CB14/BZ14,0) -> #DIV/0!
A15: 10 | C15: =IF(+B15-B14>0,B15-B14,(B15-B14)>0)*800 -> 0 | E15: =IF(+D15-D14>0,D15-D14,(D15-D14)>0)*80 -> 0 | G15: =IF(+F15-F14>0,F15-F14,(F15-F14)>0)*10 -> 0 | I15: 22097636 | J15: =IF(I15>=I14,I15-I14,0) -> 4535 | K15: =M15+O15 -> 3305 | L15: 15269 | M15: =IF(L15>=L14,L15-L14,0) -> 1506 | N15: 19645 | O15: =IF(N15>=N14,N15-N14,0) -> 1799 | P15: 214921 | Q15: =IF(P15>=P14,P15-P14,0)*30 -> 570 | R15: 702925 | S15: =IF(R15>=R14,R15-R14,0) -> 0 | T15: 344001 | U15: =IF(T15>=T14,T15-T14,0) -> 0 | V15: 132450 | W15: =IF(V15>=V14,V15-V14,0) -> 151 | X15: 240756 | Y15: =IF(X15>=X14,X15-X14,0) -> 219 | Z15: 326682 | AA15: =IF(Z15>=Z14,Z15-Z14,0)*0.53 -> 2177.24 | AB15: 387774 | AC15: =IF(AB15>=AB14,AB15-AB14,0)*0.53 -> 0 | AD15: 580407 | AE15: =IF(AD15>=AD14,AD15-AD14,0)*0.53 -> 0 | AF15: 309097 | AG15: =IF(AF15>=AF14,AF15-AF14,0)*0.53 -> 0 | AH15: 329730.75 | AI15: =IF(AH15>=AH14,AH15-AH14,0)*0.53 -> 12.215238 | AJ15: 707850.25 | AK15: =IF(AJ15>=AJ14,AJ15-AJ14,0)*0.53 -> 12.164762 | AL15: 539239 | AM15: =IF(AL15>=AL14,AL15-AL14,0)*0.53 -> 515.16 | AN15: 751935 | AO15: =IF(AN15>=AN14,AN15-AN14,0)*0.53 -> 2374.4 | AP15: 383376.5 | AQ15: =IF(AP15>=AP14,AP15-AP14,0)*0.53 -> 172.81786 | AR15: =AA15+AC15+AE15+AG15+AI15+AK15+AM15+AO15+AQ15 -> 5263.9979 | AS15: 7221198 | AT15: =IF(AS15>=AS14,AS15-AS14,0)*0.1125 -> 76.05 | AU15: 577019 | AV15: =IF(AU15>=AU14,AU15-AU14,0) -> 272 | AW15: 914686 | AX15: =IF(AW15>=AW14,AW15-AW14,0) -> 130 | AY15: 795097 | AZ15: =IF(AY15>=AY14,AY15-AY14,0) -> 43 | BA15: 2340999 | BB15: =IF(BA15>=BA14,BA15-BA14,0) -> 412 | BC15: 210103 | BD15: =IF(BC15>=BC14,BC15-BC14,0) -> 68 | BE15: 17704725 | BF15: =IF(BE15>=BE14,BE15-BE14,0) -> 3545 | BG15: 499108.5 | BH15: =IF(BG15>=BG14,BG15-BG14,0) -> 107.67857 | BI15: 8805 | BJ15: =IF(BI15>=BI14,BI15-BI14,0) -> 0 | BK15: 21946389 | BL15: =IF(BK15>=BK14,BK15-BK14,0)-(0.45*BR15)-(0.45*BT15)-BV15 -> 4813.25 | BM15: =AT15+AV15+AX15+AZ15+BB15+BD15+BF15+BH15+BJ15+BL15 -> 9466.9786 | BN15: =BM15+AR15 -> 14730.976 | BO15: 1372224 | BP15: =IF(BO15>=BO14,BO15-BO14,0) -> 353 | BQ15: 3499978 | BR15: =IF(BQ15>=BQ14,BQ15-BQ14,0) -> 1155 | BS15: 373804 | BT15: =IF(BS15>=BS14,BS15-BS14,0) -> 120 | BU15: 454027 | BV15: =IF(BU15>=BU14,BU15-BU14,0) -> 208 | BW15: =J15+Q15+AR15+BM15 -> 19835.976 | BX15: 52 | BY15: =IF(BW15>0,BW15/BX14,0) -> 374.26371 | CA15: =IF(BW15>0,BW15/BZ15,0) -> #DIV/0! | CB15: =BW15*CD1 -> 22811.373 | CC15: =IF(CB15>0,CB15/BX14,0) -> 430.40326 | CD15: =IF(CB15>0,CB15/BZ15,0) -> #DIV/0!
A16: 11 | C16: =IF(+B16-B15>0,B16-B15,(B16-B15)>0)*800 -> 0 | E16: =IF(+D16-D15>0,D16-D15,(D16-D15)>0)*80 -> 0 | G16: =IF(+F16-F15>0,F16-F15,(F16-F15)>0)*10 -> 0 | H16: 61 | I16: 22103442 | J16: =IF(I16>=I15,I16-I15,0) -> 5806 | K16: =M16+O16 -> 3134 | L16: 16806 | M16: =IF(L16>=L15,L16-L15,0) -> 1537 | N16: 21242 | O16: =IF(N16>=N15,N16-N15,0) -> 1597 | P16: 214944 | Q16: =IF(P16>=P15,P16-P15,0)*30 -> 690 | R16: 702925 | S16: =IF(R16>=R15,R16-R15,0) -> 0 | T16: 344001 | U16: =IF(T16>=T15,T16-T15,0) -> 0 | V16: 132588 | W16: =IF(V16>=V15,V16-V15,0) -> 138 | X16: 241031 | Y16: =IF(X16>=X15,X16-X15,0) -> 275 | Z16: 330193 | AA16: =IF(Z16>=Z15,Z16-Z15,0)*0.53 -> 1860.83 | AB16: 387774 | AC16: =IF(AB16>=AB15,AB16-AB15,0)*0.53 -> 0 | AD16: 580407 | AE16: =IF(AD16>=AD15,AD16-AD15,0)*0.53 -> 0 | AF16: 309097 | AG16: =IF(AF16>=AF15,AF16-AF15,0)*0.53 -> 0 | AH16: 329753.8 | AI16: =IF(AH16>=AH15,AH16-AH15,0)*0.53 -> 12.215238 | AJ16: 707873.2 | AK16: =IF(AJ16>=AJ15,AJ16-AJ15,0)*0.53 -> 12.164762 | AL16: 540121 | AM16: =IF(AL16>=AL15,AL16-AL15,0)*0.53 -> 467.46 | AN16: 755937 | AO16: =IF(AN16>=AN15,AN16-AN15,0)*0.53 -> 2121.06 | AP16: 383702.57 | AQ16: =IF(AP16>=AP15,AP16-AP15,0)*0.53 -> 172.81786 | AR16: =AA16+AC16+AE16+AG16+AI16+AK16+AM16+AO16+AQ16 -> 4646.5479 | AS16: 7221929 | AT16: =IF(AS16>=AS15,AS16-AS15,0)*0.1125 -> 82.2375 | AU16: 577301 | AV16: =IF(AU16>=AU15,AU16-AU15,0) -> 282 | AW16: 914808 | AX16: =IF(AW16>=AW15,AW16-AW15,0) -> 122 | AY16: 795133 | AZ16: =IF(AY16>=AY15,AY16-AY15,0) -> 36 | BA16: 2341339 | BB16: =IF(BA16>=BA15,BA16-BA15,0) -> 340 | BC16: 210165 | BD16: =IF(BC16>=BC15,BC16-BC15,0) -> 62 | BE16: 17707964 | BF16: =IF(BE16>=BE15,BE16-BE15,0) -> 3239 | BG16: 499216.18 | BH16: =IF(BG16>=BG15,BG16-BG15,0) -> 107.67857 | BI16: 8805 | BJ16: =IF(BI16>=BI15,BI16-BI15,0) -> 0 | BK16: 21951352 | BL16: =IF(BK16>=BK15,BK16-BK15,0)-(0.45*BR16)-(0.45*BT16)-BV16 -> 4321.3 | BM16: =AT16+AV16+AX16+AZ16+BB16+BD16+BF16+BH16+BJ16+BL16 -> 8592.2161 | BN16: =BM16+AR16 -> 13238.764 | BO16: 1372446 | BP16: =IF(BO16>=BO15,BO16-BO15,0) -> 222 | BQ16: 3500877 | BR16: =IF(BQ16>=BQ15,BQ16-BQ15,0) -> 899 | BS16: 373911 | BT16: =IF(BS16>=BS15,BS16-BS15,0) -> 107 | BU16: 454216 | BV16: =IF(BU16>=BU15,BU16-BU15,0) -> 189 | BW16: =J16+Q16+AR16+BM16 -> 19734.764 | BX16: 54 | BY16: =IF(BW16>0,BW16/BX15,0) -> 379.51469 | CA16: =IF(BW16>0,BW16/BZ16,0) -> #DIV/0! | CB16: =BW16*CD1 -> 22694.979 | CC16: =IF(CB16>0,CB16/BX15,0) -> 436.44189 | CD16: =IF(CB16>0,CB16/BZ16,0) -> #DIV/0!
A17: 12 | C17: =IF(+B17-B16>0,B17-B16,(B17-B16)>0)*800 -> 0 | E17: =IF(+D17-D16>0,D17-D16,(D17-D16)>0)*80 -> 0 | G17: =IF(+F17-F16>0,F17-F16,(F17-F16)>0)*10 -> 0 | I17: 22108127 | J17: =IF(I17>=I16,I17-I16,0) -> 4685 | K17: =M17+O17 -> 3241 | L17: 18393 | M17: =IF(L17>=L16,L17-L16,0) -> 1587 | N17: 22896 | O17: =IF(N17>=N16,N17-N16,0) -> 1654 | P17: 214963 | Q17: =IF(P17>=P16,P17-P16,0)*30 -> 570 | R17: 702925 | S17: =IF(R17>=R16,R17-R16,0) -> 0 | T17: 344001 | U17: =IF(T17>=T16,T17-T16,0) -> 0 | V17: 132731 | W17: =IF(V17>=V16,V17-V16,0) -> 143 | X17: 241274 | Y17: =IF(X17>=X16,X17-X16,0) -> 243 | Z17: 334099 | AA17: =IF(Z17>=Z16,Z17-Z16,0)*0.53 -> 2070.18 | AB17: 387774 | AC17: =IF(AB17>=AB16,AB17-AB16,0)*0.53 -> 0 | AD17: 580407 | AE17: =IF(AD17>=AD16,AD17-AD16,0)*0.53 -> 0 | AF17: 309097 | AG17: =IF(AF17>=AF16,AF17-AF16,0)*0.53 -> 0 | AH17: 329776.85 | AI17: =IF(AH17>=AH16,AH17-AH16,0)*0.53 -> 12.215238 | AJ17: 707896.15 | AK17: =IF(AJ17>=AJ16,AJ17-AJ16,0)*0.53 -> 12.164762 | AL17: 541048 | AM17: =IF(AL17>=AL16,AL17-AL16,0)*0.53 -> 491.31 | AN17: 760045 | AO17: =IF(AN17>=AN16,AN17-AN16,0)*0.53 -> 2177.24 | AP17: 384028.64 | AQ17: =IF(AP17>=AP16,AP17-AP16,0)*0.53 -> 172.81786 | AR17: =AA17+AC17+AE17+AG17+AI17+AK17+AM17+AO17+AQ17 -> 4935.9279 | AS17: 7222495 | AT17: =IF(AS17>=AS16,AS17-AS16,0)*0.1125 -> 63.675 | AU17: 577590 | AV17: =IF(AU17>=AU16,AU17-AU16,0) -> 289 | AW17: 914935 | AX17: =IF(AW17>=AW16,AW17-AW16,0) -> 127 | AY17: 795154 | AZ17: =IF(AY17>=AY16,AY17-AY16,0) -> 21 | BA17: 2341718 | BB17: =IF(BA17>=BA16,BA17-BA16,0) -> 379 | BC17: 210230 | BD17: =IF(BC17>=BC16,BC17-BC16,0) -> 65 | BE17: 17711291 | BF17: =IF(BE17>=BE16,BE17-BE16,0) -> 3327 | BG17: 499323.86 | BH17: =IF(BG17>=BG16,BG17-BG16,0) -> 107.67857 | BI17: 8805 | BJ17: =IF(BI17>=BI16,BI17-BI16,0) -> 0 | BK17: 21956486 | BL17: =IF(BK17>=BK16,BK17-BK16,0)-(0.45*BR17)-(0.45*BT17)-BV17 -> 4467.8 | BM17: =AT17+AV17+AX17+AZ17+BB17+BD17+BF17+BH17+BJ17+BL17 -> 8847.1536 | BN17: =BM17+AR17 -> 13783.081 | BO17: 1372722 | BP17: =IF(BO17>=BO16,BO17-BO16,0) -> 276 | BQ17: 3501813 | BR17: =IF(BQ17>=BQ16,BQ17-BQ16,0) -> 936 | BS17: 374011 | BT17: =IF(BS17>=BS16,BS17-BS16,0) -> 100 | BU17: 454416 | BV17: =IF(BU17>=BU16,BU17-BU16,0) -> 200 | BW17: =J17+Q17+AR17+BM17 -> 19038.081 | BX17: 69 | BY17: =IF(BW17>0,BW17/BX16,0) -> 352.55706 | CA17: =IF(BW17>0,BW17/BZ17,0) -> #DIV/0! | CB17: =BW17*CD1 -> 21893.794 | CC17: =IF(CB17>0,CB17/BX16,0) -> 405.44062 | CD17: =IF(CB17>0,CB17/BZ17,0) -> #DIV/0!
A18: 13 | C18: =IF(+B18-B17>0,B18-B17,(B18-B17)>0)*800 -> 0 | E18: =IF(+D18-D17>0,D18-D17,(D18-D17)>0)*80 -> 0 | G18: =IF(+F18-F17>0,F18-F17,(F18-F17)>0)*10 -> 0 | H18: 62 | I18: 22114031 | J18: =IF(I18>=I17,I18-I17,0) -> 5904 | K18: =M18+O18 -> 3255 | L18: 20020 | M18: =IF(L18>=L17,L18-L17,0) -> 1627 | N18: 24524 | O18: =IF(N18>=N17,N18-N17,0) -> 1628 | P18: 214983 | Q18: =IF(P18>=P17,P18-P17,0)*30 -> 600 | R18: 702925 | S18: =IF(R18>=R17,R18-R17,0) -> 0 | T18: 344001 | U18: =IF(T18>=T17,T18-T17,0) -> 0 | V18: 132879 | W18: =IF(V18>=V17,V18-V17,0) -> 148 | X18: 241523 | Y18: =IF(X18>=X17,X18-X17,0) -> 249 | Z18: 338058 | AA18: =IF(Z18>=Z17,Z18-Z17,0)*0.53 -> 2098.27 | AB18: 387774 | AC18: =IF(AB18>=AB17,AB18-AB17,0)*0.53 -> 0 | AD18: 580407 | AE18: =IF(AD18>=AD17,AD18-AD17,0)*0.53 -> 0 | AF18: 309097 | AG18: =IF(AF18>=AF17,AF18-AF17,0)*0.53 -> 0 | AH18: 329799.89 | AI18: =IF(AH18>=AH17,AH18-AH17,0)*0.53 -> 12.215238 | AJ18: 707919.11 | AK18: =IF(AJ18>=AJ17,AJ18-AJ17,0)*0.53 -> 12.164762 | AL18: 542004 | AM18: =IF(AL18>=AL17,AL18-AL17,0)*0.53 -> 506.68 | AN18: 764280 | AO18: =IF(AN18>=AN17,AN18-AN17,0)*0.53 -> 2244.55 | AP18: 384354.71 | AQ18: =IF(AP18>=AP17,AP18-AP17,0)*0.53 -> 172.81786 | AR18: =AA18+AC18+AE18+AG18+AI18+AK18+AM18+AO18+AQ18 -> 5046.6979 | AS18: 7223196 | AT18: =IF(AS18>=AS17,AS18-AS17,0)*0.1125 -> 78.8625 | AU18: 577840 | AV18: =IF(AU18>=AU17,AU18-AU17,0) -> 250 | AW18: 915039 | AX18: =IF(AW18>=AW17,AW18-AW17,0) -> 104 | AY18: 795175 | AZ18: =IF(AY18>=AY17,AY18-AY17,0) -> 21 | BA18: 2342106 | BB18: =IF(BA18>=BA17,BA18-BA17,0) -> 388 | BC18: 210296 | BD18: =IF(BC18>=BC17,BC18-BC17,0) -> 66 | BE18: 17714756 | BF18: =IF(BE18>=BE17,BE18-BE17,0) -> 3465 | BG18: 499431.54 | BH18: =IF(BG18>=BG17,BG18-BG17,0) -> 107.67857 | BI18: 8805 | BJ18: =IF(BI18>=BI17,BI18-BI17,0) -> 0 | BK18: 21961827 | BL18: =IF(BK18>=BK17,BK18-BK17,0)-(0.45*BR18)-(0.45*BT18)-BV18 -> 4660 | BM18: =AT18+AV18+AX18+AZ18+BB18+BD18+BF18+BH18+BJ18+BL18 -> 9140.5411 | BN18: =BM18+AR18 -> 14187.239 | BO18: 1372999 | BP18: =IF(BO18>=BO17,BO18-BO17,0) -> 277 | BQ18: 3502751 | BR18: =IF(BQ18>=BQ17,BQ18-BQ17,0) -> 938 | BS18: 374133 | BT18: =IF(BS18>=BS17,BS18-BS17,0) -> 122 | BU18: 454620 | BV18: =IF(BU18>=BU17,BU18-BU17,0) -> 204 | BW18: =J18+Q18+AR18+BM18 -> 20691.239 | BX18: 54 | BY18: =IF(BW18>0,BW18/BX17,0) -> 299.87303 | CA18: =IF(BW18>0,BW18/BZ18,0) -> #DIV/0! | CB18: =BW18*CD1 -> 23794.925 | CC18: =IF(CB18>0,CB18/BX17,0) -> 344.85398 | CD18: =IF(CB18>0,CB18/BZ18,0) -> #DIV/0!
A19: 14 | C19: =IF(+B19-B18>0,B19-B18,(B19-B18)>0)*800 -> 0 | E19: =IF(+D19-D18>0,D19-D18,(D19-D18)>0)*80 -> 0 | G19: =IF(+F19-F18>0,F19-F18,(F19-F18)>0)*10 -> 0 | I19: 22119160 | J19: =IF(I19>=I18,I19-I18,0) -> 5129 | K19: =M19+O19 -> 3144 | L19: 21586 | M19: =IF(L19>=L18,L19-L18,0) -> 1566 | N19: 26102 | O19: =IF(N19>=N18,N19-N18,0) -> 1578 | P19: 215001 | Q19: =IF(P19>=P18,P19-P18,0)*30 -> 540 | R19: 702925 | S19: =IF(R19>=R18,R19-R18,0) -> 0 | T19: 344001 | U19: =IF(T19>=T18,T19-T18,0) -> 0 | V19: 133023 | W19: =IF(V19>=V18,V19-V18,0) -> 144 | X19: 241763 | Y19: =IF(X19>=X18,X19-X18,0) -> 240 | Z19: 341930 | AA19: =IF(Z19>=Z18,Z19-Z18,0)*0.53 -> 2052.16 | AB19: 387774 | AC19: =IF(AB19>=AB18,AB19-AB18,0)*0.53 -> 0 | AD19: 580407 | AE19: =IF(AD19>=AD18,AD19-AD18,0)*0.53 -> 0 | AF19: 309097 | AG19: =IF(AF19>=AF18,AF19-AF18,0)*0.53 -> 0 | AH19: 329822.94 | AI19: =IF(AH19>=AH18,AH19-AH18,0)*0.53 -> 12.215238 | AJ19: 707942.06 | AK19: =IF(AJ19>=AJ18,AJ19-AJ18,0)*0.53 -> 12.164762 | AL19: 542928 | AM19: =IF(AL19>=AL18,AL19-AL18,0)*0.53 -> 489.72 | AN19: 768409 | AO19: =IF(AN19>=AN18,AN19-AN18,0)*0.53 -> 2188.37 | AP19: 384680.79 | AQ19: =IF(AP19>=AP18,AP19-AP18,0)*0.53 -> 172.81786 | AR19: =AA19+AC19+AE19+AG19+AI19+AK19+AM19+AO19+AQ19 -> 4927.4479 | AS19: 7223872 | AT19: =IF(AS19>=AS18,AS19-AS18,0)*0.1125 -> 76.05 | AU19: 578099 | AV19: =IF(AU19>=AU18,AU19-AU18,0) -> 259 | AW19: 915111 | AX19: =IF(AW19>=AW18,AW19-AW18,0) -> 72 | AY19: 795210 | AZ19: =IF(AY19>=AY18,AY19-AY18,0) -> 35 | BA19: 2342479 | BB19: =IF(BA19>=BA18,BA19-BA18,0) -> 373 | BC19: 210360 | BD19: =IF(BC19>=BC18,BC19-BC18,0) -> 64 | BE19: 17718257 | BF19: =IF(BE19>=BE18,BE19-BE18,0) -> 3501 | BG19: 499539.21 | BH19: =IF(BG19>=BG18,BG19-BG18,0) -> 107.67857 | BI19: 8805 | BJ19: =IF(BI19>=BI18,BI19-BI18,0) -> 0 | BK19: 21967195 | BL19: =IF(BK19>=BK18,BK19-BK18,0)-(0.45*BR19)-(0.45*BT19)-BV19 -> 4674.65 | BM19: =AT19+AV19+AX19+AZ19+BB19+BD19+BF19+BH19+BJ19+BL19 -> 9162.3786 | BN19: =BM19+AR19 -> 14089.826 | BO19: 1373276 | BP19: =IF(BO19>=BO18,BO19-BO18,0) -> 277 | BQ19: 3503738 | BR19: =IF(BQ19>=BQ18,BQ19-BQ18,0) -> 987 | BS19: 374249 | BT19: =IF(BS19>=BS18,BS19-BS18,0) -> 116 | BU19: 454817 | BV19: =IF(BU19>=BU18,BU19-BU18,0) -> 197 | BW19: =J19+Q19+AR19+BM19 -> 19758.826 | BX19: 68 | BY19: =IF(BW19>0,BW19/BX18,0) -> 365.90419 | CA19: =IF(BW19>0,BW19/BZ19,0) -> #DIV/0! | CB19: =BW19*CD1 -> 22722.65 | CC19: =IF(CB19>0,CB19/BX18,0) -> 420.78982 | CD19: =IF(CB19>0,CB19/BZ19,0) -> #DIV/0!
A20: 15 | C20: =IF(+B20-B19>0,B20-B19,(B20-B19)>0)*800 -> 0 | E20: =IF(+D20-D19>0,D20-D19,(D20-D19)>0)*80 -> 0 | G20: =IF(+F20-F19>0,F20-F19,(F20-F19)>0)*10 -> 0 | H20: 63 | I20: 22124273 | J20: =IF(I20>=I19,I20-I19,0) -> 5113 | K20: =M20+O20 -> 3160 | L20: 23159 | M20: =IF(L20>=L19,L20-L19,0) -> 1573 | N20: 27689 | O20: =IF(N20>=N19,N20-N19,0) -> 1587 | P20: 215018 | Q20: =IF(P20>=P19,P20-P19,0)*30 -> 510 | R20: 702925 | S20: =IF(R20>=R19,R20-R19,0) -> 0 | T20: 344001 | U20: =IF(T20>=T19,T20-T19,0) -> 0 | V20: 133170 | W20: =IF(V20>=V19,V20-V19,0) -> 147 | X20: 242008 | Y20: =IF(X20>=X19,X20-X19,0) -> 245 | Z20: 345979 | AA20: =IF(Z20>=Z19,Z20-Z19,0)*0.53 -> 2145.97 | AB20: 387774 | AC20: =IF(AB20>=AB19,AB20-AB19,0)*0.53 -> 0 | AD20: 580407 | AE20: =IF(AD20>=AD19,AD20-AD19,0)*0.53 -> 0 | AF20: 309097 | AG20: =IF(AF20>=AF19,AF20-AF19,0)*0.53 -> 0 | AH20: 329845.99 | AI20: =IF(AH20>=AH19,AH20-AH19,0)*0.53 -> 12.215238 | AJ20: 707965.01 | AK20: =IF(AJ20>=AJ19,AJ20-AJ19,0)*0.53 -> 12.164762 | AL20: 543877 | AM20: =IF(AL20>=AL19,AL20-AL19,0)*0.53 -> 502.97 | AN20: 772693 | AO20: =IF(AN20>=AN19,AN20-AN19,0)*0.53 -> 2270.52 | AP20: 385006.86 | AQ20: =IF(AP20>=AP19,AP20-AP19,0)*0.53 -> 172.81786 | AR20: =AA20+AC20+AE20+AG20+AI20+AK20+AM20+AO20+AQ20 -> 5116.6579 | AS20: 7224533 | AT20: =IF(AS20>=AS19,AS20-AS19,0)*0.1125 -> 74.3625 | AU20: 578369 | AV20: =IF(AU20>=AU19,AU20-AU19,0) -> 270 | AW20: 915189 | AX20: =IF(AW20>=AW19,AW20-AW19,0) -> 78 | AY20: 795245 | AZ20: =IF(AY20>=AY19,AY20-AY19,0) -> 35 | BA20: 2342830 | BB20: =IF(BA20>=BA19,BA20-BA19,0) -> 351 | BC20: 210424 | BD20: =IF(BC20>=BC19,BC20-BC19,0) -> 64 | BE20: 17721774 | BF20: =IF(BE20>=BE19,BE20-BE19,0) -> 3517 | BG20: 499646.89 | BH20: =IF(BG20>=BG19,BG20-BG19,0) -> 107.67857 | BI20: 8805 | BJ20: =IF(BI20>=BI19,BI20-BI19,0) -> 0 | BK20: 21972581 | BL20: =IF(BK20>=BK19,BK20-BK19,0)-(0.45*BR20)-(0.45*BT20)-BV20 -> 4666.3 | BM20: =AT20+AV20+AX20+AZ20+BB20+BD20+BF20+BH20+BJ20+BL20 -> 9163.3411 | BN20: =BM20+AR20 -> 14279.999 | BO20: 1373552 | BP20: =IF(BO20>=BO19,BO20-BO19,0) -> 276 | BQ20: 3504763 | BR20: =IF(BQ20>=BQ19,BQ20-BQ19,0) -> 1025 | BS20: 374370 | BT20: =IF(BS20>=BS19,BS20-BS19,0) -> 121 | BU20: 455021 | BV20: =IF(BU20>=BU19,BU20-BU19,0) -> 204 | BW20: =J20+Q20+AR20+BM20 -> 19902.999 | BX20: 62 | BY20: =IF(BW20>0,BW20/BX20,0) -> 321.01611 | CA20: =IF(BW20>0,BW20/BZ20,0) -> #DIV/0! | CB20: =BW20*CD1 -> 22888.449 | CC20: =IF(CB20>0,CB20/BX20,0) -> 369.16853 | CD20: =IF(CB20>0,CB20/BZ20,0) -> #DIV/0!
A21: 16 | C21: =IF(+B21-B20>0,B21-B20,(B21-B20)>0)*800 -> 0 | E21: =IF(+D21-D20>0,D21-D20,(D21-D20)>0)*80 -> 0 | G21: =IF(+F21-F20>0,F21-F20,(F21-F20)>0)*10 -> 0 | I21: 22129155 | J21: =IF(I21>=I20,I21-I20,0) -> 4882 | K21: =M21+O21 -> 3069 | L21: 24657 | M21: =IF(L21>=L20,L21-L20,0) -> 1498 | N21: 29260 | O21: =IF(N21>=N20,N21-N20,0) -> 1571 | P21: 215034 | Q21: =IF(P21>=P20,P21-P20,0)*30 -> 480 | R21: 702925 | S21: =IF(R21>=R20,R21-R20,0) -> 0 | T21: 344001 | U21: =IF(T21>=T20,T21-T20,0) -> 0 | V21: 133311 | W21: =IF(V21>=V20,V21-V20,0) -> 141 | X21: 242248 | Y21: =IF(X21>=X20,X21-X20,0) -> 240 | Z21: 347132 | AA21: =IF(Z21>=Z20,Z21-Z20,0)*0.53 -> 611.09 | AB21: 388739 | AC21: =IF(AB21>=AB20,AB21-AB20,0)*0.53 -> 511.45 | AD21: 580407 | AE21: =IF(AD21>=AD20,AD21-AD20,0)*0.53 -> 0 | AF21: 309097 | AG21: =IF(AF21>=AF20,AF21-AF20,0)*0.53 -> 0 | AH21: 329869.04 | AI21: =IF(AH21>=AH20,AH21-AH20,0)*0.53 -> 12.215238 | AJ21: 707987.96 | AK21: =IF(AJ21>=AJ20,AJ21-AJ20,0)*0.53 -> 12.164762 | AL21: 544420 | AM21: =IF(AL21>=AL20,AL21-AL20,0)*0.53 -> 287.79 | AN21: 776248 | AO21: =IF(AN21>=AN20,AN21-AN20,0)*0.53 -> 1884.15 | AP21: 385332.93 | AQ21: =IF(AP21>=AP20,AP21-AP20,0)*0.53 -> 172.81786 | AR21: =AA21+AC21+AE21+AG21+AI21+AK21+AM21+AO21+AQ21 -> 3491.6779 | AS21: 7225085 | AT21: =IF(AS21>=AS20,AS21-AS20,0)*0.1125 -> 62.1 | AU21: 578675 | AV21: =IF(AU21>=AU20,AU21-AU20,0) -> 306 | AW21: 915279 | AX21: =IF(AW21>=AW20,AW21-AW20,0) -> 90 | AY21: 795274 | AZ21: =IF(AY21>=AY20,AY21-AY20,0) -> 29 | BA21: 2343206 | BB21: =IF(BA21>=BA20,BA21-BA20,0) -> 376 | BC21: 210487 | BD21: =IF(BC21>=BC20,BC21-BC20,0) -> 63 | BE21: 17725058 | BF21: =IF(BE21>=BE20,BE21-BE20,0) -> 3284 | BG21: 499754.57 | BH21: =IF(BG21>=BG20,BG21-BG20,0) -> 107.67857 | BI21: 8805 | BJ21: =IF(BI21>=BI20,BI21-BI20,0) -> 0 | BK21: 21978165 | BL21: =IF(BK21>=BK20,BK21-BK20,0)-(0.45*BR21)-(0.45*BT21)-BV21 -> 4891.05 | BM21: =AT21+AV21+AX21+AZ21+BB21+BD21+BF21+BH21+BJ21+BL21 -> 9208.8286 | BN21: =BM21+AR21 -> 12700.506 | BO21: 1374177 | BP21: =IF(BO21>=BO20,BO21-BO20,0) -> 625 | BQ21: 3505763 | BR21: =IF(BQ21>=BQ20,BQ21-BQ20,0) -> 1000 | BS21: 374481 | BT21: =IF(BS21>=BS20,BS21-BS20,0) -> 111 | BU21: 455214 | BV21: =IF(BU21>=BU20,BU21-BU20,0) -> 193 | BW21: =J21+Q21+AR21+BM21 -> 18062.506 | BX21: 69 | BY21: =IF(BW21>0,BW21/BX21,0) -> 261.77546 | CA21: =IF(BW21>0,BW21/BZ21,0) -> #DIV/0! | CB21: =BW21*CD1 -> 20771.882 | CC21: =IF(CB21>0,CB21/BX21,0) -> 301.04177 | CD21: =IF(CB21>0,CB21/BZ21,0) -> #DIV/0!
A22: 17 | C22: =IF(+B22-B21>0,B22-B21,(B22-B21)>0)*800 -> 0 | E22: =IF(+D22-D21>0,D22-D21,(D22-D21)>0)*80 -> 0 | G22: =IF(+F22-F21>0,F22-F21,(F22-F21)>0)*10 -> 0 | H22: 64 | I22: 22133878 | J22: =IF(I22>=I21,I22-I21,0) -> 4723 | K22: =M22+O22 -> 3084 | L22: 26361 | M22: =IF(L22>=L21,L22-L21,0) -> 1704 | N22: 30640 | O22: =IF(N22>=N21,N22-N21,0) -> 1380 | P22: 215048 | Q22: =IF(P22>=P21,P22-P21,0)*30 -> 420 | R22: 702925 | S22: =IF(R22>=R21,R22-R21,0) -> 0 | T22: 344001 | U22: =IF(T22>=T21,T22-T21,0) -> 0 | V22: 133455 | W22: =IF(V22>=V21,V22-V21,0) -> 144 | X22: 242491 | Y22: =IF(X22>=X21,X22-X21,0) -> 243 | Z22: 347132 | AA22: =IF(Z22>=Z21,Z22-Z21,0)*0.53 -> 0 | AB22: 388739 | AC22: =IF(AB22>=AB21,AB22-AB21,0)*0.53 -> 0 | AD22: 580407 | AE22: =IF(AD22>=AD21,AD22-AD21,0)*0.53 -> 0 | AF22: 309097 | AG22: =IF(AF22>=AF21,AF22-AF21,0)*0.53 -> 0 | AH22: 329893 | AI22: =IF(AH22>=AH21,AH22-AH21,0)*0.53 -> 12.701071 | AJ22: 708012 | AK22: =IF(AJ22>=AJ21,AJ22-AJ21,0)*0.53 -> 12.738929 | AL22: 544480 | AM22: =IF(AL22>=AL21,AL22-AL21,0)*0.53 -> 31.8 | AN22: 778940 | AO22: =IF(AN22>=AN21,AN22-AN21,0)*0.53 -> 1426.76 | AP22: 385659 | AQ22: =IF(AP22>=AP21,AP22-AP21,0)*0.53 -> 172.81786 | AR22: =AA22+AC22+AE22+AG22+AI22+AK22+AM22+AO22+AQ22 -> 1656.8179 | AS22: 7225126 | AT22: =IF(AS22>=AS21,AS22-AS21,0)*0.1125 -> 4.6125 | AU22: 578840 | AV22: =IF(AU22>=AU21,AU22-AU21,0) -> 165 | AW22: 915357 | AX22: =IF(AW22>=AW21,AW22-AW21,0) -> 78 | AY22: 795302 | AZ22: =IF(AY22>=AY21,AY22-AY21,0) -> 28 | BA22: 2343533 | BB22: =IF(BA22>=BA21,BA22-BA21,0) -> 327 | BC22: 210548 | BD22: =IF(BC22>=BC21,BC22-BC21,0) -> 61 | BE22: 17728178 | BF22: =IF(BE22>=BE21,BE22-BE21,0) -> 3120 | BG22: 499875 | BH22: =IF(BG22>=BG21,BG22-BG21,0) -> 120.42857 | BI22: 8805 | BJ22: =IF(BI22>=BI21,BI22-BI21,0) -> 0 | BK22: 21983973 | BL22: =IF(BK22>=BK21,BK22-BK21,0)-(0.45*BR22)-(0.45*BT22)-BV22 -> 5114.7 | BM22: =AT22+AV22+AX22+AZ22+BB22+BD22+BF22+BH22+BJ22+BL22 -> 9018.7411 | BN22: =BM22+AR22 -> 10675.559 | BO22: 1374949 | BP22: =IF(BO22>=BO21,BO22-BO21,0) -> 772 | BQ22: 3506739 | BR22: =IF(BQ22>=BQ21,BQ22-BQ21,0) -> 976 | BS22: 374599 | BT22: =IF(BS22>=BS21,BS22-BS21,0) -> 118 | BU22: 455415 | BV22: =IF(BU22>=BU21,BU22-BU21,0) -> 201 | BW22: =J22+Q22+AR22+BM22 -> 15818.559 | BX22: 80 | BY22: =IF(BW22>0,BW22/BX22,0) -> 197.73199 | CA22: =IF(BW22>0,BW22/BZ22,0) -> #DIV/0! | CB22: =BW22*CD1 -> 18191.343 | CC22: =IF(CB22>0,CB22/BX22,0) -> 227.39178 | CD22: =IF(CB22>0,CB22/BZ22,0) -> #DIV/0!
A23: 18 | C23: =IF(+B23-B22>0,B23-B22,(B23-B22)>0)*800 -> 0 | E23: =IF(+D23-D22>0,D23-D22,(D23-D22)>0)*80 -> 0 | G23: =IF(+F23-F22>0,F23-F22,(F23-F22)>0)*10 -> 0 | I23: 22138713 | J23: =IF(I23>=I22,I23-I22,0) -> 4835 | K23: =M23+O23 -> 3111 | L23: 28019 | M23: =IF(L23>=L22,L23-L22,0) -> 1658 | N23: 32093 | O23: =IF(N23>=N22,N23-N22,0) -> 1453 | P23: 215064 | Q23: =IF(P23>=P22,P23-P22,0)*30 -> 480 | R23: 702925 | S23: =IF(R23>=R22,R23-R22,0) -> 0 | T23: 344001 | U23: =IF(T23>=T22,T23-T22,0) -> 0 | V23: 133599 | W23: =IF(V23>=V22,V23-V22,0) -> 144 | X23: 242731 | Y23: =IF(X23>=X22,X23-X22,0) -> 240 | Z23: 347132 | AA23: =IF(Z23>=Z22,Z23-Z22,0)*0.53 -> 0 | AB23: 388739 | AC23: =IF(AB23>=AB22,AB23-AB22,0)*0.53 -> 0 | AD23: 580657 | AE23: =IF(AD23>=AD22,AD23-AD22,0)*0.53 -> 132.5 | AF23: 309938 | AG23: =IF(AF23>=AF22,AF23-AF22,0)*0.53 -> 445.73 | AH23: 329916 | AI23: =IF(AH23>=AH22,AH23-AH22,0)*0.53 -> 12.19 | AJ23: 708034 | AK23: =IF(AJ23>=AJ22,AJ23-AJ22,0)*0.53 -> 11.66 | AL23: 544587 | AM23: =IF(AL23>=AL22,AL23-AL22,0)*0.53 -> 56.71 | AN23: 781793 | AO23: =IF(AN23>=AN22,AN23-AN22,0)*0.53 -> 1512.09 | AP23: 386044 | AQ23: =IF(AP23>=AP22,AP23-AP22,0)*0.53 -> 204.05 | AR23: =AA23+AC23+AE23+AG23+AI23+AK23+AM23+AO23+AQ23 -> 2374.93 | AS23: 7225151 | AT23: =IF(AS23>=AS22,AS23-AS22,0)*0.1125 -> 2.8125 | AU23: 579166 | AV23: =IF(AU23>=AU22,AU23-AU22,0) -> 326 | AW23: 915446 | AX23: =IF(AW23>=AW22,AW23-AW22,0) -> 89 | AY23: 795331 | AZ23: =IF(AY23>=AY22,AY23-AY22,0) -> 29 | BA23: 2343873 | BB23: =IF(BA23>=BA22,BA23-BA22,0) -> 340 | BC23: 210611 | BD23: =IF(BC23>=BC22,BC23-BC22,0) -> 63 | BE23: 17731132 | BF23: =IF(BE23>=BE22,BE23-BE22,0) -> 2954 | BG23: 499990 | BH23: =IF(BG23>=BG22,BG23-BG22,0) -> 115 | BI23: 8805 | BJ23: =IF(BI23>=BI22,BI23-BI22,0) -> 0 | BK23: 21989377 | BL23: =IF(BK23>=BK22,BK23-BK22,0)-(0.45*BR23)-(0.45*BT23)-BV23 -> 4699.4 | BM23: =AT23+AV23+AX23+AZ23+BB23+BD23+BF23+BH23+BJ23+BL23 -> 8618.2125 | BN23: =BM23+AR23 -> 10993.143 | BO23: 1375430 | BP23: =IF(BO23>=BO22,BO23-BO22,0) -> 481 | BQ23: 3507751 | BR23: =IF(BQ23>=BQ22,BQ23-BQ22,0) -> 1012 | BS23: 374715 | BT23: =IF(BS23>=BS22,BS23-BS22,0) -> 116 | BU23: 455612 | BV23: =IF(BU23>=BU22,BU23-BU22,0) -> 197 | BW23: =J23+Q23+AR23+BM23 -> 16308.143 | BX23: 70 | BY23: =IF(BW23>0,BW23/BX23,0) -> 232.97346 | CA23: =IF(BW23>0,BW23/BZ23,0) -> #DIV/0! | CB23: =BW23*CD1 -> 18754.364 | CC23: =IF(CB23>0,CB23/BX23,0) -> 267.91948 | CD23: =IF(CB23>0,CB23/BZ23,0) -> #DIV/0!
A24: 19 | C24: =IF(+B24-B23>0,B24-B23,(B24-B23)>0)*800 -> 0 | E24: =IF(+D24-D23>0,D24-D23,(D24-D23)>0)*80 -> 0 | G24: =IF(+F24-F23>0,F24-F23,(F24-F23)>0)*10 -> 0 | H24: 65 | I24: 22143096 | J24: =IF(I24>=I23,I24-I23,0) -> 4383 | K24: =M24+O24 -> 2769 | L24: 29430 | M24: =IF(L24>=L23,L24-L23,0) -> 1411 | N24: 33451 | O24: =IF(N24>=N23,N24-N23,0) -> 1358 | P24: 215081 | Q24: =IF(P24>=P23,P24-P23,0)*30 -> 510 | R24: 702925 | S24: =IF(R24>=R23,R24-R23,0) -> 0 | T24: 344001 | U24: =IF(T24>=T23,T24-T23,0) -> 0 | V24: 133745 | W24: =IF(V24>=V23,V24-V23,0) -> 146 | X24: 242928 | Y24: =IF(X24>=X23,X24-X23,0) -> 197 | Z24: 347132 | AA24: =IF(Z24>=Z23,Z24-Z23,0)*0.53 -> 0 | AB24: 389651 | AC24: =IF(AB24>=AB23,AB24-AB23,0)*0.53 -> 483.36 | AD24: 580657 | AE24: =IF(AD24>=AD23,AD24-AD23,0)*0.53 -> 0 | AF24: 309938 | AG24: =IF(AF24>=AF23,AF24-AF23,0)*0.53 -> 0 | AH24: 329938 | AI24: =IF(AH24>=AH23,AH24-AH23,0)*0.53 -> 11.66 | AJ24: 708057 | AK24: =IF(AJ24>=AJ23,AJ24-AJ23,0)*0.53 -> 12.19 | AL24: 544727 | AM24: =IF(AL24>=AL23,AL24-AL23,0)*0.53 -> 74.2 | AN24: 784451 | AO24: =IF(AN24>=AN23,AN24-AN23,0)*0.53 -> 1408.74 | AP24: 386294 | AQ24: =IF(AP24>=AP23,AP24-AP23,0)*0.53 -> 132.5 | AR24: =AA24+AC24+AE24+AG24+AI24+AK24+AM24+AO24+AQ24 -> 2122.65 | AS24: 7225173 | AT24: =IF(AS24>=AS23,AS24-AS23,0)*0.1125 -> 2.475 | AU24: 579353 | AV24: =IF(AU24>=AU23,AU24-AU23,0) -> 187 | AW24: 915540 | AX24: =IF(AW24>=AW23,AW24-AW23,0) -> 94 | AY24: 795350 | AZ24: =IF(AY24>=AY23,AY24-AY23,0) -> 19 | BA24: 2344210 | BB24: =IF(BA24>=BA23,BA24-BA23,0) -> 337 | BC24: 210674 | BD24: =IF(BC24>=BC23,BC24-BC23,0) -> 63 | BE24: 17734164 | BF24: =IF(BE24>=BE23,BE24-BE23,0) -> 3032 | BG24: 500059 | BH24: =IF(BG24>=BG23,BG24-BG23,0) -> 69 | BI24: 8820 | BJ24: =IF(BI24>=BI23,BI24-BI23,0) -> 15 | BK24: 21994425 | BL24: =IF(BK24>=BK23,BK24-BK23,0)-(0.45*BR24)-(0.45*BT24)-BV24 -> 4364.3 | BM24: =AT24+AV24+AX24+AZ24+BB24+BD24+BF24+BH24+BJ24+BL24 -> 8182.775 | BN24: =BM24+AR24 -> 10305.425 | BO24: 1375714 | BP24: =IF(BO24>=BO23,BO24-BO23,0) -> 284 | BQ24: 3508729 | BR24: =IF(BQ24>=BQ23,BQ24-BQ23,0) -> 978 | BS24: 374823 | BT24: =IF(BS24>=BS23,BS24-BS23,0) -> 108 | BU24: 455807 | BV24: =IF(BU24>=BU23,BU24-BU23,0) -> 195 | BW24: =J24+Q24+AR24+BM24 -> 15198.425 | BX24: 63 | BY24: =IF(BW24>0,BW24/BX24,0) -> 241.24484 | CA24: =IF(BW24>0,BW24/BZ24,0) -> #DIV/0! | CB24: =BW24*CD1 -> 17478.189 | CC24: =IF(CB24>0,CB24/BX24,0) -> 277.43157 | CD24: =IF(CB24>0,CB24/BZ24,0) -> #DIV/0!
A25: 20 | C25: =IF(+B25-B24>0,B25-B24,(B25-B24)>0)*800 -> 0 | E25: =IF(+D25-D24>0,D25-D24,(D25-D24)>0)*80 -> 0 | G25: =IF(+F25-F24>0,F25-F24,(F25-F24)>0)*10 -> 0 | I25: 22147471 | J25: =IF(I25>=I24,I25-I24,0) -> 4375 | K25: =M25+O25 -> 4445 | L25: 31078 | M25: =IF(L25>=L24,L25-L24,0) -> 1648 | N25: 36248 | O25: =IF(N25>=N24,N25-N24,0) -> 2797 | P25: 215094 | Q25: =IF(P25>=P24,P25-P24,0)*30 -> 390 | R25: 702925 | S25: =IF(R25>=R24,R25-R24,0) -> 0 | T25: 344001 | U25: =IF(T25>=T24,T25-T24,0) -> 0 | V25: 133883 | W25: =IF(V25>=V24,V25-V24,0) -> 138 | X25: 243214 | Y25: =IF(X25>=X24,X25-X24,0) -> 286 | Z25: 347132 | AA25: =IF(Z25>=Z24,Z25-Z24,0)*0.53 -> 0 | AB25: 391752 | AC25: =IF(AB25>=AB24,AB25-AB24,0)*0.53 -> 1113.53 | AD25: 580657 | AE25: =IF(AD25>=AD24,AD25-AD24,0)*0.53 -> 0 | AF25: 309938 | AG25: =IF(AF25>=AF24,AF25-AF24,0)*0.53 -> 0 | AH25: 329959 | AI25: =IF(AH25>=AH24,AH25-AH24,0)*0.53 -> 11.13 | AJ25: 708078 | AK25: =IF(AJ25>=AJ24,AJ25-AJ24,0)*0.53 -> 11.13 | AL25: 544998 | AM25: =IF(AL25>=AL24,AL25-AL24,0)*0.53 -> 143.63 | AN25: 787807 | AO25: =IF(AN25>=AN24,AN25-AN24,0)*0.53 -> 1778.68 | AP25: 386601 | AQ25: =IF(AP25>=AP24,AP25-AP24,0)*0.53 -> 162.71 | AR25: =AA25+AC25+AE25+AG25+AI25+AK25+AM25+AO25+AQ25 -> 3220.81 | AS25: 7225198 | AT25: =IF(AS25>=AS24,AS25-AS24,0)*0.1125 -> 2.8125 | AU25: 579614 | AV25: =IF(AU25>=AU24,AU25-AU24,0) -> 261 | AW25: 915638 | AX25: =IF(AW25>=AW24,AW25-AW24,0) -> 98 | AY25: 795370 | AZ25: =IF(AY25>=AY24,AY25-AY24,0) -> 20 | BA25: 2344538 | BB25: =IF(BA25>=BA24,BA25-BA24,0) -> 328 | BC25: 210733 | BD25: =IF(BC25>=BC24,BC25-BC24,0) -> 59 | BE25: 17737242 | BF25: =IF(BE25>=BE24,BE25-BE24,0) -> 3078 | BG25: 500165 | BH25: =IF(BG25>=BG24,BG25-BG24,0) -> 106 | BI25: 8820 | BJ25: =IF(BI25>=BI24,BI25-BI24,0) -> 0 | BK25: 21999319 | BL25: =IF(BK25>=BK24,BK25-BK24,0)-(0.45*BR25)-(0.45*BT25)-BV25 -> 4216.65 | BM25: =AT25+AV25+AX25+AZ25+BB25+BD25+BF25+BH25+BJ25+BL25 -> 8169.4625 | BN25: =BM25+AR25 -> 11390.273 | BO25: 1375978 | BP25: =IF(BO25>=BO24,BO25-BO24,0) -> 264 | BQ25: 3509701 | BR25: =IF(BQ25>=BQ24,BQ25-BQ24,0) -> 972 | BS25: 374934 | BT25: =IF(BS25>=BS24,BS25-BS24,0) -> 111 | BU25: 455997 | BV25: =IF(BU25>=BU24,BU25-BU24,0) -> 190 | BW25: =J25+Q25+AR25+BM25 -> 16155.273 | BX25: 56 | BY25: =IF(BW25>0,BW25/BX25,0) -> 288.48701 | CA25: =IF(BW25>0,BW25/BZ25,0) -> #DIV/0! | CB25: =BW25*CD1 -> 18578.563 | CC25: =IF(CB25>0,CB25/BX25,0) -> 331.76006 | CD25: =IF(CB25>0,CB25/BZ25,0) -> #DIV/0!
A26: 21 | C26: =IF(+B26-B25>0,B26-B25,(B26-B25)>0)*800 -> 0 | E26: =IF(+D26-D25>0,D26-D25,(D26-D25)>0)*80 -> 0 | G26: =IF(+F26-F25>0,F26-F25,(F26-F25)>0)*10 -> 0 | H26: 66 | I26: 22153337 | J26: =IF(I26>=I25,I26-I25,0) -> 5866 | K26: =M26+O26 -> 3572 | L26: 32792 | M26: =IF(L26>=L25,L26-L25,0) -> 1714 | N26: 38106 | O26: =IF(N26>=N25,N26-N25,0) -> 1858 | P26: 215112 | Q26: =IF(P26>=P25,P26-P25,0)*30 -> 540 | R26: 702925 | S26: =IF(R26>=R25,R26-R25,0) -> 0 | T26: 344001 | U26: =IF(T26>=T25,T26-T25,0) -> 0 | V26: 134038 | W26: =IF(V26>=V25,V26-V25,0) -> 155 | X26: 243479 | Y26: =IF(X26>=X25,X26-X25,0) -> 265 | Z26: 348926 | AA26: =IF(Z26>=Z25,Z26-Z25,0)*0.53 -> 950.82 | AB26: 391752 | AC26: =IF(AB26>=AB25,AB26-AB25,0)*0.53 -> 0 | AD26: 580657 | AE26: =IF(AD26>=AD25,AD26-AD25,0)*0.53 -> 0 | AF26: 309938 | AG26: =IF(AF26>=AF25,AF26-AF25,0)*0.53 -> 0 | AH26: 329983 | AI26: =IF(AH26>=AH25,AH26-AH25,0)*0.53 -> 12.72 | AJ26: 708101 | AK26: =IF(AJ26>=AJ25,AJ26-AJ25,0)*0.53 -> 12.19 | AL26: 545366 | AM26: =IF(AL26>=AL25,AL26-AL25,0)*0.53 -> 195.04 | AN26: 791787 | AO26: =IF(AN26>=AN25,AN26-AN25,0)*0.53 -> 2109.4 | AP26: 386923 | AQ26: =IF(AP26>=AP25,AP26-AP25,0)*0.53 -> 170.66 | AR26: =AA26+AC26+AE26+AG26+AI26+AK26+AM26+AO26+AQ26 -> 3450.83 | AS26: 7225237 | AT26: =IF(AS26>=AS25,AS26-AS25,0)*0.1125 -> 4.3875 | AU26: 579889 | AV26: =IF(AU26>=AU25,AU26-AU25,0) -> 275 | AW26: 915732 | AX26: =IF(AW26>=AW25,AW26-AW25,0) -> 94 | AY26: 795402 | AZ26: =IF(AY26>=AY25,AY26-AY25,0) -> 32 | BA26: 2344915 | BB26: =IF(BA26>=BA25,BA26-BA25,0) -> 377 | BC26: 210799 | BD26: =IF(BC26>=BC25,BC26-BC25,0) -> 66 | BE26: 17740516 | BF26: =IF(BE26>=BE25,BE26-BE25,0) -> 3274 | BG26: 500278 | BH26: =IF(BG26>=BG25,BG26-BG25,0) -> 113 | BI26: 8820 | BJ26: =IF(BI26>=BI25,BI26-BI25,0) -> 0 | BK26: 22004807 | BL26: =IF(BK26>=BK25,BK26-BK25,0)-(0.45*BR26)-(0.45*BT26)-BV26 -> 4783.7 | BM26: =AT26+AV26+AX26+AZ26+BB26+BD26+BF26+BH26+BJ26+BL26 -> 9019.0875 | BN26: =BM26+AR26 -> 12469.918 | BO26: 1376263 | BP26: =IF(BO26>=BO25,BO26-BO25,0) -> 285 | BQ26: 3510663 | BR26: =IF(BQ26>=BQ25,BQ26-BQ25,0) -> 962 | BS26: 375066 | BT26: =IF(BS26>=BS25,BS26-BS25,0) -> 132 | BU26: 456209 | BV26: =IF(BU26>=BU25,BU26-BU25,0) -> 212 | BW26: =J26+Q26+AR26+BM26 -> 18875.918 | BX26: 87 | BY26: =IF(BW26>0,BW26/BX26,0) -> 216.96457 | CA26: =IF(BW26>0,BW26/BZ26,0) -> #DIV/0! | CB26: =BW26*CD1 -> 21707.305 | CC26: =IF(CB26>0,CB26/BX26,0) -> 249.50925 | CD26: =IF(CB26>0,CB26/BZ26,0) -> #DIV/0!
A27: 22 | C27: =IF(+B27-B26>0,B27-B26,(B27-B26)>0)*800 -> 0 | E27: =IF(+D27-D26>0,D27-D26,(D27-D26)>0)*80 -> 0 | G27: =IF(+F27-F26>0,F27-F26,(F27-F26)>0)*10 -> 0 | I27: 22159656 | J27: =IF(I27>=I26,I27-I26,0) -> 6319 | K27: =M27+O27 -> 3200 | L27: 34736 | M27: =IF(L27>=L26,L27-L26,0) -> 1944 | N27: 39362 | O27: =IF(N27>=N26,N27-N26,0) -> 1256 | P27: 215131 | Q27: =IF(P27>=P26,P27-P26,0)*30 -> 570 | R27: 702925 | S27: =IF(R27>=R26,R27-R26,0) -> 0 | T27: 344001 | U27: =IF(T27>=T26,T27-T26,0) -> 0 | V27: 134197 | W27: =IF(V27>=V26,V27-V26,0) -> 159 | X27: 243755 | Y27: =IF(X27>=X26,X27-X26,0) -> 276 | Z27: 351008 | AA27: =IF(Z27>=Z26,Z27-Z26,0)*0.53 -> 1103.46 | AB27: 391752 | AC27: =IF(AB27>=AB26,AB27-AB26,0)*0.53 -> 0 | AD27: 580657 | AE27: =IF(AD27>=AD26,AD27-AD26,0)*0.53 -> 0 | AF27: 310194 | AG27: =IF(AF27>=AF26,AF27-AF26,0)*0.53 -> 135.68 | AH27: 330010 | AI27: =IF(AH27>=AH26,AH27-AH26,0)*0.53 -> 14.31 | AJ27: 708129 | AK27: =IF(AJ27>=AJ26,AJ27-AJ26,0)*0.53 -> 14.84 | AL27: 545728 | AM27: =IF(AL27>=AL26,AL27-AL26,0)*0.53 -> 191.86 | AN27: 795657 | AO27: =IF(AN27>=AN26,AN27-AN26,0)*0.53 -> 2051.1 | AP27: 387279 | AQ27: =IF(AP27>=AP26,AP27-AP26,0)*0.53 -> 188.68 | AR27: =AA27+AC27+AE27+AG27+AI27+AK27+AM27+AO27+AQ27 -> 3699.93 | AS27: 7225274 | AT27: =IF(AS27>=AS26,AS27-AS26,0)*0.1125 -> 4.1625 | AU27: 580091 | AV27: =IF(AU27>=AU26,AU27-AU26,0) -> 202 | AW27: 915818 | AX27: =IF(AW27>=AW26,AW27-AW26,0) -> 86 | AY27: 795434 | AZ27: =IF(AY27>=AY26,AY27-AY26,0) -> 32 | BA27: 2345318 | BB27: =IF(BA27>=BA26,BA27-BA26,0) -> 403 | BC27: 210867 | BD27: =IF(BC27>=BC26,BC27-BC26,0) -> 68 | BE27: 17743928 | BF27: =IF(BE27>=BE26,BE27-BE26,0) -> 3412 | BG27: 500404 | BH27: =IF(BG27>=BG26,BG27-BG26,0) -> 126 | BI27: 8820 | BJ27: =IF(BI27>=BI26,BI27-BI26,0) -> 0 | BK27: 22011429 | BL27: =IF(BK27>=BK26,BK27-BK26,0)-(0.45*BR27)-(0.45*BT27)-BV27 -> 5872.2 | BM27: =AT27+AV27+AX27+AZ27+BB27+BD27+BF27+BH27+BJ27+BL27 -> 10205.362 | BN27: =BM27+AR27 -> 13905.292 | BO27: 1377028 | BP27: =IF(BO27>=BO26,BO27-BO26,0) -> 765 | BQ27: 3511711 | BR27: =IF(BQ27>=BQ26,BQ27-BQ26,0) -> 1048 | BS27: 375202 | BT27: =IF(BS27>=BS26,BS27-BS26,0) -> 136 | BU27: 456426 | BV27: =IF(BU27>=BU26,BU27-BU26,0) -> 217 | BW27: =J27+Q27+AR27+BM27 -> 20794.292 | BX27: 88 | BY27: =IF(BW27>0,BW27/BX27,0) -> 236.29878 | CA27: =IF(BW27>0,BW27/BZ27,0) -> #DIV/0! | CB27: =BW27*CD1 -> 23913.436 | CC27: =IF(CB27>0,CB27/BX27,0) -> 271.7436 | CD27: =IF(CB27>0,CB27/BZ27,0) -> #DIV/0!
A28: 23 | C28: =IF(+B28-B27>0,B28-B27,(B28-B27)>0)*800 -> 0 | E28: =IF(+D28-D27>0,D28-D27,(D28-D27)>0)*80 -> 0 | G28: =IF(+F28-F27>0,F28-F27,(F28-F27)>0)*10 -> 0 | H28: 67 | I28: 22165213 | J28: =IF(I28>=I27,I28-I27,0) -> 5557 | K28: =M28+O28 -> 3709 | L28: 36672 | M28: =IF(L28>=L27,L28-L27,0) -> 1936 | N28: 41135 | O28: =IF(N28>=N27,N28-N27,0) -> 1773 | P28: 215148 | Q28: =IF(P28>=P27,P28-P27,0)*30 -> 510 | R28: 702925 | S28: =IF(R28>=R27,R28-R27,0) -> 0 | T28: 344001 | U28: =IF(T28>=T27,T28-T27,0) -> 0 | V28: 134334 | W28: =IF(V28>=V27,V28-V27,0) -> 137 | X28: 243990 | Y28: =IF(X28>=X27,X28-X27,0) -> 235 | Z28: 354039 | AA28: =IF(Z28>=Z27,Z28-Z27,0)*0.53 -> 1606.43 | AB28: 391752 | AC28: =IF(AB28>=AB27,AB28-AB27,0)*0.53 -> 0 | AD28: 580657 | AE28: =IF(AD28>=AD27,AD28-AD27,0)*0.53 -> 0 | AF28: 310194 | AG28: =IF(AF28>=AF27,AF28-AF27,0)*0.53 -> 0 | AH28: 330027 | AI28: =IF(AH28>=AH27,AH28-AH27,0)*0.53 -> 9.01 | AJ28: 708145 | AK28: =IF(AJ28>=AJ27,AJ28-AJ27,0)*0.53 -> 8.48 | AL28: 546441 | AM28: =IF(AL28>=AL27,AL28-AL27,0)*0.53 -> 377.89 | AN28: 800366 | AO28: =IF(AN28>=AN27,AN28-AN27,0)*0.53 -> 2495.77 | AP28: 387634 | AQ28: =IF(AP28>=AP27,AP28-AP27,0)*0.53 -> 188.15 | AR28: =AA28+AC28+AE28+AG28+AI28+AK28+AM28+AO28+AQ28 -> 4685.73 | AS28: 7225309 | AT28: =IF(AS28>=AS27,AS28-AS27,0)*0.1125 -> 3.9375 | AU28: 580362 | AV28: =IF(AU28>=AU27,AU28-AU27,0) -> 271 | AW28: 915894 | AX28: =IF(AW28>=AW27,AW28-AW27,0) -> 76 | AY28: 795471 | AZ28: =IF(AY28>=AY27,AY28-AY27,0) -> 37 | BA28: 2345713 | BB28: =IF(BA28>=BA27,BA28-BA27,0) -> 395 | BC28: 210927 | BD28: =IF(BC28>=BC27,BC28-BC27,0) -> 60 | BE28: 17747111 | BF28: =IF(BE28>=BE27,BE28-BE27,0) -> 3183 | BG28: 500511 | BH28: =IF(BG28>=BG27,BG28-BG27,0) -> 107 | BI28: 8820 | BJ28: =IF(BI28>=BI27,BI28-BI27,0) -> 0 | BK28: 22016789 | BL28: =IF(BK28>=BK27,BK28-BK27,0)-(0.45*BR28)-(0.45*BT28)-BV28 -> 4693 | BM28: =AT28+AV28+AX28+AZ28+BB28+BD28+BF28+BH28+BJ28+BL28 -> 8825.9375 | BN28: =BM28+AR28 -> 13511.667 | BO28: 1377460 | BP28: =IF(BO28>=BO27,BO28-BO27,0) -> 432 | BQ28: 3512651 | BR28: =IF(BQ28>=BQ27,BQ28-BQ27,0) -> 940 | BS28: 375322 | BT28: =IF(BS28>=BS27,BS28-BS27,0) -> 120 | BU28: 456616 | BV28: =IF(BU28>=BU27,BU28-BU27,0) -> 190 | BW28: =J28+Q28+AR28+BM28 -> 19578.667 | BX28: 83 | BY28: =IF(BW28>0,BW28/BX28,0) -> 235.88756 | CA28: =IF(BW28>0,BW28/BZ28,0) -> #DIV/0! | CB28: =BW28*CD1 -> 22515.468 | CC28: =IF(CB28>0,CB28/BX28,0) -> 271.27069 | CD28: =IF(CB28>0,CB28/BZ28,0) -> #DIV/0!
A29: 24 | C29: =IF(+B29-B28>0,B29-B28,(B29-B28)>0)*800 -> 0 | E29: =IF(+D29-D28>0,D29-D28,(D29-D28)>0)*80 -> 0 | G29: =IF(+F29-F28>0,F29-F28,(F29-F28)>0)*10 -> 0 | I29: 22170653 | J29: =IF(I29>=I28,I29-I28,0) -> 5440 | K29: =M29+O29 -> 3410 | L29: 38316 | M29: =IF(L29>=L28,L29-L28,0) -> 1644 | N29: 42901 | O29: =IF(N29>=N28,N29-N28,0) -> 1766 | P29: 215167 | Q29: =IF(P29>=P28,P29-P28,0)*30 -> 570 | R29: 702925 | S29: =IF(R29>=R28,R29-R28,0) -> 0 | T29: 344001 | U29: =IF(T29>=T28,T29-T28,0) -> 0 | V29: 134491 | W29: =IF(V29>=V28,V29-V28,0) -> 157 | X29: 244263 | Y29: =IF(X29>=X28,X29-X28,0) -> 273 | Z29: 356387 | AA29: =IF(Z29>=Z28,Z29-Z28,0)*0.53 -> 1244.44 | AB29: 391968 | AC29: =IF(AB29>=AB28,AB29-AB28,0)*0.53 -> 114.48 | AD29: 580657 | AE29: =IF(AD29>=AD28,AD29-AD28,0)*0.53 -> 0 | AF29: 310194 | AG29: =IF(AF29>=AF28,AF29-AF28,0)*0.53 -> 0 | AH29: 330056 | AI29: =IF(AH29>=AH28,AH29-AH28,0)*0.53 -> 15.37 | AJ29: 708174 | AK29: =IF(AJ29>=AJ28,AJ29-AJ28,0)*0.53 -> 15.37 | AL29: 546976 | AM29: =IF(AL29>=AL28,AL29-AL28,0)*0.53 -> 283.55 | AN29: 804409 | AO29: =IF(AN29>=AN28,AN29-AN28,0)*0.53 -> 2142.79 | AP29: 387968 | AQ29: =IF(AP29>=AP28,AP29-AP28,0)*0.53 -> 177.02 | AR29: =AA29+AC29+AE29+AG29+AI29+AK29+AM29+AO29+AQ29 -> 3993.02 | AS29: 7225359 | AT29: =IF(AS29>=AS28,AS29-AS28,0)*0.1125 -> 5.625 | AU29: 580677 | AV29: =IF(AU29>=AU28,AU29-AU28,0) -> 315 | AW29: 915976 | AX29: =IF(AW29>=AW28,AW29-AW28,0) -> 82 | AY29: 795503 | AZ29: =IF(AY29>=AY28,AY29-AY28,0) -> 32 | BA29: 2346090 | BB29: =IF(BA29>=BA28,BA29-BA28,0) -> 377 | BC29: 210994 | BD29: =IF(BC29>=BC28,BC29-BC28,0) -> 67 | BE29: 17750161 | BF29: =IF(BE29>=BE28,BE29-BE28,0) -> 3050 | BG29: 500631 | BH29: =IF(BG29>=BG28,BG29-BG28,0) -> 120 | BI29: 8820 | BJ29: =IF(BI29>=BI28,BI29-BI28,0) -> 0 | BK29: 22022769 | BL29: =IF(BK29>=BK28,BK29-BK28,0)-(0.45*BR29)-(0.45*BT29)-BV29 -> 5219.85 | BM29: =AT29+AV29+AX29+AZ29+BB29+BD29+BF29+BH29+BJ29+BL29 -> 9268.475 | BN29: =BM29+AR29 -> 13261.495 | BO29: 1377768 | BP29: =IF(BO29>=BO28,BO29-BO28,0) -> 308 | BQ29: 3513712 | BR29: =IF(BQ29>=BQ28,BQ29-BQ28,0) -> 1061 | BS29: 375448 | BT29: =IF(BS29>=BS28,BS29-BS28,0) -> 126 | BU29: 456842 | BV29: =IF(BU29>=BU28,BU29-BU28,0) -> 226 | BW29: =J29+Q29+AR29+BM29 -> 19271.495 | BX29: 88 | BY29: =IF(BW29>0,BW29/BX29,0) -> 218.99426 | CA29: =IF(BW29>0,BW29/BZ29,0) -> #DIV/0! | CB29: =BW29*CD1 -> 22162.219 | CC29: =IF(CB29>0,CB29/BX29,0) -> 251.8434 | CD29: =IF(CB29>0,CB29/BZ29,0) -> #DIV/0!
A30: 25 | C30: =IF(+B30-B29>0,B30-B29,(B30-B29)>0)*800 -> 0 | E30: =IF(+D30-D29>0,D30-D29,(D30-D29)>0)*80 -> 0 | G30: =IF(+F30-F29>0,F30-F29,(F30-F29)>0)*10 -> 0 | H30: 68 | I30: 22175711 | J30: =IF(I30>=I29,I30-I29,0) -> 5058 | K30: =M30+O30 -> 3157 | L30: 39946 | M30: =IF(L30>=L29,L30-L29,0) -> 1630 | N30: 44428 | O30: =IF(N30>=N29,N30-N29,0) -> 1527 | P30: 215183 | Q30: =IF(P30>=P29,P30-P29,0)*30 -> 480 | R30: 702925 | S30: =IF(R30>=R29,R30-R29,0) -> 0 | T30: 344001 | U30: =IF(T30>=T29,T30-T29,0) -> 0 | V30: 134624 | W30: =IF(V30>=V29,V30-V29,0) -> 133 | X30: 244492 | Y30: =IF(X30>=X29,X30-X29,0) -> 229 | Z30: 359877 | AA30: =IF(Z30>=Z29,Z30-Z29,0)*0.53 -> 1849.7 | AB30: 392348 | AC30: =IF(AB30>=AB29,AB30-AB29,0)*0.53 -> 201.4 | AD30: 580657 | AE30: =IF(AD30>=AD29,AD30-AD29,0)*0.53 -> 0 | AF30: 310194 | AG30: =IF(AF30>=AF29,AF30-AF29,0)*0.53 -> 0 | AH30: 330076 | AI30: =IF(AH30>=AH29,AH30-AH29,0)*0.53 -> 10.6 | AJ30: 708193 | AK30: =IF(AJ30>=AJ29,AJ30-AJ29,0)*0.53 -> 10.07 | AL30: 547490 | AM30: =IF(AL30>=AL29,AL30-AL29,0)*0.53 -> 272.42 | AN30: 809179 | AO30: =IF(AN30>=AN29,AN30-AN29,0)*0.53 -> 2528.1 | AP30: 388298 | AQ30: =IF(AP30>=AP29,AP30-AP29,0)*0.53 -> 174.9 | AR30: =AA30+AC30+AE30+AG30+AI30+AK30+AM30+AO30+AQ30 -> 5047.19 | AS30: 7225588 | AT30: =IF(AS30>=AS29,AS30-AS29,0)*0.1125 -> 25.7625 | AU30: 580977 | AV30: =IF(AU30>=AU29,AU30-AU29,0) -> 300 | AW30: 916061 | AX30: =IF(AW30>=AW29,AW30-AW29,0) -> 85 | AY30: 795536 | AZ30: =IF(AY30>=AY29,AY30-AY29,0) -> 33 | BA30: 2346478 | BB30: =IF(BA30>=BA29,BA30-BA29,0) -> 388 | BC30: 211051 | BD30: =IF(BC30>=BC29,BC30-BC29,0) -> 57 | BE30: 17753531 | BF30: =IF(BE30>=BE29,BE30-BE29,0) -> 3370 | BG30: 500736 | BH30: =IF(BG30>=BG29,BG30-BG29,0) -> 105 | BI30: 8820 | BJ30: =IF(BI30>=BI29,BI30-BI29,0) -> 0 | BK30: 22027489 | BL30: =IF(BK30>=BK29,BK30-BK29,0)-(0.45*BR30)-(0.45*BT30)-BV30 -> 4181.3 | BM30: =AT30+AV30+AX30+AZ30+BB30+BD30+BF30+BH30+BJ30+BL30 -> 8545.0625 | BN30: =BM30+AR30 -> 13592.252 | BO30: 1377971 | BP30: =IF(BO30>=BO29,BO30-BO29,0) -> 203 | BQ30: 3514433 | BR30: =IF(BQ30>=BQ29,BQ30-BQ29,0) -> 721 | BS30: 375533 | BT30: =IF(BS30>=BS29,BS30-BS29,0) -> 85 | BU30: 457018 | BV30: =IF(BU30>=BU29,BU30-BU29,0) -> 176 | BW30: =J30+Q30+AR30+BM30 -> 19130.252 | BX30: 77 | BY30: =IF(BW30>0,BW30/BX30,0) -> 248.44484 | CA30: =IF(BW30>0,BW30/BZ30,0) -> #DIV/0! | CB30: =BW30*CD1 -> 21999.79 | CC30: =IF(CB30>0,CB30/BX30,0) -> 285.71156 | CD30: =IF(CB30>0,CB30/BZ30,0) -> #DIV/0!
A31: 26 | C31: =IF(+B31-B30>0,B31-B30,(B31-B30)>0)*800 -> 0 | E31: =IF(+D31-D30>0,D31-D30,(D31-D30)>0)*80 -> 0 | G31: =IF(+F31-F30>0,F31-F30,(F31-F30)>0)*10 -> 0 | I31: 22178632 | J31: =IF(I31>=I30,I31-I30,0) -> 2921 | K31: =M31+O31 -> 2989 | L31: 41540 | M31: =IF(L31>=L30,L31-L30,0) -> 1594 | N31: 45823 | O31: =IF(N31>=N30,N31-N30,0) -> 1395 | P31: 215208 | Q31: =IF(P31>=P30,P31-P30,0)*30 -> 750 | R31: 702925 | S31: =IF(R31>=R30,R31-R30,0) -> 0 | T31: 344001 | U31: =IF(T31>=T30,T31-T30,0) -> 0 | V31: 134767 | W31: =IF(V31>=V30,V31-V30,0) -> 143 | X31: 244722 | Y31: =IF(X31>=X30,X31-X30,0) -> 230 | Z31: 362231 | AA31: =IF(Z31>=Z30,Z31-Z30,0)*0.53 -> 1247.62 | AB31: 392711 | AC31: =IF(AB31>=AB30,AB31-AB30,0)*0.53 -> 192.39 | AD31: 580657 | AE31: =IF(AD31>=AD30,AD31-AD30,0)*0.53 -> 0 | AF31: 310194 | AG31: =IF(AF31>=AF30,AF31-AF30,0)*0.53 -> 0 | AH31: 330098 | AI31: =IF(AH31>=AH30,AH31-AH30,0)*0.53 -> 11.66 | AJ31: 708217 | AK31: =IF(AJ31>=AJ30,AJ31-AJ30,0)*0.53 -> 12.72 | AL31: 547875 | AM31: =IF(AL31>=AL30,AL31-AL30,0)*0.53 -> 204.05 | AN31: 812535 | AO31: =IF(AN31>=AN30,AN31-AN30,0)*0.53 -> 1778.68 | AP31: 388607 | AQ31: =IF(AP31>=AP30,AP31-AP30,0)*0.53 -> 163.77 | AR31: =AA31+AC31+AE31+AG31+AI31+AK31+AM31+AO31+AQ31 -> 3610.89 | AS31: 7225697 | AT31: =IF(AS31>=AS30,AS31-AS30,0)*0.1125 -> 12.2625 | AU31: 581253 | AV31: =IF(AU31>=AU30,AU31-AU30,0) -> 276 | AW31: 916274 | AX31: =IF(AW31>=AW30,AW31-AW30,0) -> 213 | AY31: 795580 | AZ31: =IF(AY31>=AY30,AY31-AY30,0) -> 44 | BA31: 2346818 | BB31: =IF(BA31>=BA30,BA31-BA30,0) -> 340 | BC31: 211116 | BD31: =IF(BC31>=BC30,BC31-BC30,0) -> 65 | BE31: 17757636 | BF31: =IF(BE31>=BE30,BE31-BE30,0) -> 4105 | BG31: 500836 | BH31: =IF(BG31>=BG30,BG31-BG30,0) -> 100 | BI31: 8820 | BJ31: =IF(BI31>=BI30,BI31-BI30,0) -> 0 | BK31: 22032459 | BL31: =IF(BK31>=BK30,BK31-BK30,0)-(0.45*BR31)-(0.45*BT31)-BV31 -> 4389.15 | BM31: =AT31+AV31+AX31+AZ31+BB31+BD31+BF31+BH31+BJ31+BL31 -> 9544.4125 | BN31: =BM31+AR31 -> 13155.302 | BO31: 1378424 | BP31: =IF(BO31>=BO30,BO31-BO30,0) -> 453 | BQ31: 3515302 | BR31: =IF(BQ31>=BQ30,BQ31-BQ30,0) -> 869 | BS31: 375617 | BT31: =IF(BS31>=BS30,BS31-BS30,0) -> 84 | BU31: 457170 | BV31: =IF(BU31>=BU30,BU31-BU30,0) -> 152 | BW31: =J31+Q31+AR31+BM31 -> 16826.302 | BX31: 58 | BY31: =IF(BW31>0,BW31/BX31,0) -> 290.10866 | CA31: =IF(BW31>0,BW31/BZ31,0) -> #DIV/0! | CB31: =BW31*CD1 -> 19350.248 | CC31: =IF(CB31>0,CB31/BX31,0) -> 333.62496 | CD31: =IF(CB31>0,CB31/BZ31,0) -> #DIV/0!
A32: 27 | C32: =IF(+B32-B31>0,B32-B31,(B32-B31)>0)*800 -> 0 | E32: =IF(+D32-D31>0,D32-D31,(D32-D31)>0)*80 -> 0 | G32: =IF(+F32-F31>0,F32-F31,(F32-F31)>0)*10 -> 0 | H32: 69 | I32: 22183582 | J32: =IF(I32>=I31,I32-I31,0) -> 4950 | K32: =M32+O32 -> 3335 | L32: 43234 | M32: =IF(L32>=L31,L32-L31,0) -> 1694 | N32: 47464 | O32: =IF(N32>=N31,N32-N31,0) -> 1641 | P32: 215226 | Q32: =IF(P32>=P31,P32-P31,0)*30 -> 540 | R32: 702925 | S32: =IF(R32>=R31,R32-R31,0) -> 0 | T32: 344001 | U32: =IF(T32>=T31,T32-T31,0) -> 0 | V32: 134913 | W32: =IF(V32>=V31,V32-V31,0) -> 146 | X32: 244969 | Y32: =IF(X32>=X31,X32-X31,0) -> 247 | Z32: 364959 | AA32: =IF(Z32>=Z31,Z32-Z31,0)*0.53 -> 1445.84 | AB32: 393104 | AC32: =IF(AB32>=AB31,AB32-AB31,0)*0.53 -> 208.29 | AD32: 580657 | AE32: =IF(AD32>=AD31,AD32-AD31,0)*0.53 -> 0 | AF32: 310194 | AG32: =IF(AF32>=AF31,AF32-AF31,0)*0.53 -> 0 | AH32: 330122 | AI32: =IF(AH32>=AH31,AH32-AH31,0)*0.53 -> 12.72 | AJ32: 708240 | AK32: =IF(AJ32>=AJ31,AJ32-AJ31,0)*0.53 -> 12.19 | AL32: 548428 | AM32: =IF(AL32>=AL31,AL32-AL31,0)*0.53 -> 293.09 | AN32: 816369 | AO32: =IF(AN32>=AN31,AN32-AN31,0)*0.53 -> 2032.02 | AP32: 388935 | AQ32: =IF(AP32>=AP31,AP32-AP31,0)*0.53 -> 173.84 | AR32: =AA32+AC32+AE32+AG32+AI32+AK32+AM32+AO32+AQ32 -> 4177.99 | AS32: 7225837 | AT32: =IF(AS32>=AS31,AS32-AS31,0)*0.1125 -> 15.75 | AU32: 581520 | AV32: =IF(AU32>=AU31,AU32-AU31,0) -> 267 | AW32: 916378 | AX32: =IF(AW32>=AW31,AW32-AW31,0) -> 104 | AY32: 795612 | AZ32: =IF(AY32>=AY31,AY32-AY31,0) -> 32 | BA32: 2347185 | BB32: =IF(BA32>=BA31,BA32-BA31,0) -> 367 | BC32: 211180 | BD32: =IF(BC32>=BC31,BC32-BC31,0) -> 64 | BE32: 17760978 | BF32: =IF(BE32>=BE31,BE32-BE31,0) -> 3342 | BG32: 500945 | BH32: =IF(BG32>=BG31,BG32-BG31,0) -> 109 | BI32: 8820 | BJ32: =IF(BI32>=BI31,BI32-BI31,0) -> 0 | BK32: 22037855 | BL32: =IF(BK32>=BK31,BK32-BK31,0)-(0.45*BR32)-(0.45*BT32)-BV32 -> 4724.1 | BM32: =AT32+AV32+AX32+AZ32+BB32+BD32+BF32+BH32+BJ32+BL32 -> 9024.85 | BN32: =BM32+AR32 -> 13202.84 | BO32: 1378823 | BP32: =IF(BO32>=BO31,BO32-BO31,0) -> 399 | BQ32: 3516252 | BR32: =IF(BQ32>=BQ31,BQ32-BQ31,0) -> 950 | BS32: 375729 | BT32: =IF(BS32>=BS31,BS32-BS31,0) -> 112 | BU32: 457364 | BV32: =IF(BU32>=BU31,BU32-BU31,0) -> 194 | BW32: =J32+Q32+AR32+BM32 -> 18692.84 | BX32: 59 | BY32: =IF(BW32>0,BW32/BX32,0) -> 316.8278 | CA32: =IF(BW32>0,BW32/BZ32,0) -> #DIV/0! | CB32: =BW32*CD1 -> 21496.766 | CC32: =IF(CB32>0,CB32/BX32,0) -> 364.35197 | CD32: =IF(CB32>0,CB32/BZ32,0) -> #DIV/0!
A33: 28 | C33: =IF(+B33-B32>0,B33-B32,(B33-B32)>0)*800 -> 0 | E33: =IF(+D33-D32>0,D33-D32,(D33-D32)>0)*80 -> 0 | G33: =IF(+F33-F32>0,F33-F32,(F33-F32)>0)*10 -> 0 | I33: 22188532 | J33: =IF(I33>=I32,I33-I32,0) -> 4950 | K33: =M33+O33 -> 3334 | L33: 44927 | M33: =IF(L33>=L32,L33-L32,0) -> 1693 | N33: 49105 | O33: =IF(N33>=N32,N33-N32,0) -> 1641 | P33: 215244 | Q33: =IF(P33>=P32,P33-P32,0)*30 -> 540 | R33: 702925 | S33: =IF(R33>=R32,R33-R32,0) -> 0 | T33: 344001 | U33: =IF(T33>=T32,T33-T32,0) -> 0 | V33: 135058 | W33: =IF(V33>=V32,V33-V32,0) -> 145 | X33: 245216 | Y33: =IF(X33>=X32,X33-X32,0) -> 247 | Z33: 367687 | AA33: =IF(Z33>=Z32,Z33-Z32,0)*0.53 -> 1445.84 | AB33: 393488 | AC33: =IF(AB33>=AB32,AB33-AB32,0)*0.53 -> 203.52 | AD33: 580657 | AE33: =IF(AD33>=AD32,AD33-AD32,0)*0.53 -> 0 | AF33: 310194 | AG33: =IF(AF33>=AF32,AF33-AF32,0)*0.53 -> 0 | AH33: 330145 | AI33: =IF(AH33>=AH32,AH33-AH32,0)*0.53 -> 12.19 | AJ33: 708263 | AK33: =IF(AJ33>=AJ32,AJ33-AJ32,0)*0.53 -> 12.19 | AL33: 548748 | AM33: =IF(AL33>=AL32,AL33-AL32,0)*0.53 -> 169.6 | AN33: 820202 | AO33: =IF(AN33>=AN32,AN33-AN32,0)*0.53 -> 2031.49 | AP33: 389263 | AQ33: =IF(AP33>=AP32,AP33-AP32,0)*0.53 -> 173.84 | AR33: =AA33+AC33+AE33+AG33+AI33+AK33+AM33+AO33+AQ33 -> 4048.67 | AS33: 7225978 | AT33: =IF(AS33>=AS32,AS33-AS32,0)*0.1125 -> 15.8625 | AU33: 581825 | AV33: =IF(AU33>=AU32,AU33-AU32,0) -> 305 | AW33: 916482 | AX33: =IF(AW33>=AW32,AW33-AW32,0) -> 104 | AY33: 795644 | AZ33: =IF(AY33>=AY32,AY33-AY32,0) -> 32 | BA33: 2347553 | BB33: =IF(BA33>=BA32,BA33-BA32,0) -> 368 | BC33: 211243 | BD33: =IF(BC33>=BC32,BC33-BC32,0) -> 63 | BE33: 17764320 | BF33: =IF(BE33>=BE32,BE33-BE32,0) -> 3342 | BG33: 501061 | BH33: =IF(BG33>=BG32,BG33-BG32,0) -> 116 | BI33: 8820 | BJ33: =IF(BI33>=BI32,BI33-BI32,0) -> 0 | BK33: 22043251 | BL33: =IF(BK33>=BK32,BK33-BK32,0)-(0.45*BR33)-(0.45*BT33)-BV33 -> 4724.1 | BM33: =AT33+AV33+AX33+AZ33+BB33+BD33+BF33+BH33+BJ33+BL33 -> 9069.9625 | BN33: =BM33+AR33 -> 13118.633 | BO33: 1379222 | BP33: =IF(BO33>=BO32,BO33-BO32,0) -> 399 | BQ33: 3517202 | BR33: =IF(BQ33>=BQ32,BQ33-BQ32,0) -> 950 | BS33: 375841 | BT33: =IF(BS33>=BS32,BS33-BS32,0) -> 112 | BU33: 457558 | BV33: =IF(BU33>=BU32,BU33-BU32,0) -> 194 | BW33: =J33+Q33+AR33+BM33 -> 18608.632 | BX33: 58 | BY33: =IF(BW33>0,BW33/BX33,0) -> 320.83849 | CA33: =IF(BW33>0,BW33/BZ33,0) -> #DIV/0! | CB33: =BW33*CD1 -> 21399.927 | CC33: =IF(CB33>0,CB33/BX33,0) -> 368.96427 | CD33: =IF(CB33>0,CB33/BZ33,0) -> #DIV/0!
A34: 29 | C34: =IF(+B34-B33>0,B34-B33,(B34-B33)>0)*800 -> 0 | E34: =IF(+D34-D33>0,D34-D33,(D34-D33)>0)*80 -> 0 | G34: =IF(+F34-F33>0,F34-F33,(F34-F33)>0)*10 -> 0 | I34: 22188532 | J34: =IF(I34>=I33,I34-I33,0) -> 0 | K34: =M34+O34 -> 0 | L34: 44927 | M34: =IF(L34>=L33,L34-L33,0) -> 0 | N34: 49105 | O34: =IF(N34>=N33,N34-N33,0) -> 0 | P34: 215244 | Q34: =IF(P34>=P33,P34-P33,0)*30 -> 0 | R34: 702925 | S34: =IF(R34>=R33,R34-R33,0) -> 0 | T34: 344001 | U34: =IF(T34>=T33,T34-T33,0) -> 0 | V34: 135058 | W34: =IF(V34>=V33,V34-V33,0) -> 0 | X34: 245216 | Y34: =IF(X34>=X33,X34-X33,0) -> 0 | Z34: 367687 | AA34: =IF(Z34>=Z33,Z34-Z33,0)*0.53 -> 0 | AB34: 393488 | AC34: =IF(AB34>=AB33,AB34-AB33,0)*0.53 -> 0 | AD34: 580657 | AE34: =IF(AD34>=AD33,AD34-AD33,0)*0.53 -> 0 | AF34: 310194 | AG34: =IF(AF34>=AF33,AF34-AF33,0)*0.53 -> 0 | AH34: 330145 | AI34: =IF(AH34>=AH33,AH34-AH33,0)*0.53 -> 0 | AJ34: 708263 | AK34: =IF(AJ34>=AJ33,AJ34-AJ33,0)*0.53 -> 0 | AL34: 548748 | AM34: =IF(AL34>=AL33,AL34-AL33,0)*0.53 -> 0 | AN34: 820202 | AO34: =IF(AN34>=AN33,AN34-AN33,0)*0.53 -> 0 | AP34: 389263 | AQ34: =IF(AP34>=AP33,AP34-AP33,0)*0.53 -> 0 | AR34: =AA34+AC34+AE34+AG34+AI34+AK34+AM34+AO34+AQ34 -> 0 | AS34: 7225978 | AT34: =IF(AS34>=AS33,AS34-AS33,0)*0.1125 -> 0 | AU34: 581825 | AV34: =IF(AU34>=AU33,AU34-AU33,0) -> 0 | AW34: 916482 | AX34: =IF(AW34>=AW33,AW34-AW33,0) -> 0 | AY34: 795644 | AZ34: =IF(AY34>=AY33,AY34-AY33,0) -> 0 | BA34: 2347553 | BB34: =IF(BA34>=BA33,BA34-BA33,0) -> 0 | BC34: 211243 | BD34: =IF(BC34>=BC33,BC34-BC33,0) -> 0 | BE34: 17764320 | BF34: =IF(BE34>=BE33,BE34-BE33,0) -> 0 | BG34: 501061 | BH34: =IF(BG34>=BG33,BG34-BG33,0) -> 0 | BI34: 8820 | BJ34: =IF(BI34>=BI33,BI34-BI33,0) -> 0 | BK34: 22043251 | BL34: =IF(BK34>=BK33,BK34-BK33,0)-(0.45*BR34)-(0.45*BT34)-BV34 -> 0 | BM34: =AT34+AV34+AX34+AZ34+BB34+BD34+BF34+BH34+BJ34+BL34 -> 0 | BN34: =BM34+AR34 -> 0 | BO34: 1379222 | BP34: =IF(BO34>=BO33,BO34-BO33,0) -> 0 | BQ34: 3517202 | BR34: =IF(BQ34>=BQ33,BQ34-BQ33,0) -> 0 | BS34: 375841 | BT34: =IF(BS34>=BS33,BS34-BS33,0) -> 0 | BU34: 457558 | BV34: =IF(BU34>=BU33,BU34-BU33,0) -> 0 | BW34: =J34+Q34+AR34+BM34 -> 0 | BY34: =IF(BW34>0,BW34/BX34,0) -> 0 | CA34: =IF(BW34>0,BW34/BZ34,0) -> 0 | CB34: =BW34*CD1 -> 0 | CC34: =IF(CB34>0,CB34/BX34,0) -> 0 | CD34: =IF(CB34>0,CB34/BZ34,0) -> 0
A35: 30 | C35: =IF(+B35-B34>0,B35-B34,(B35-B34)>0)*800 -> 0 | E35: =IF(+D35-D34>0,D35-D34,(D35-D34)>0)*80 -> 0 | G35: =IF(+F35-F34>0,F35-F34,(F35-F34)>0)*10 -> 0 | I35: 22188532 | J35: =IF(I35>=I34,I35-I34,0) -> 0 | K35: =M35+O35 -> 0 | L35: 44927 | M35: =IF(L35>=L34,L35-L34,0) -> 0 | N35: 49105 | O35: =IF(N35>=N34,N35-N34,0) -> 0 | P35: 215244 | Q35: =IF(P35>=P34,P35-P34,0)*30 -> 0 | R35: 702925 | S35: =IF(R35>=R34,R35-R34,0) -> 0 | T35: 344001 | U35: =IF(T35>=T34,T35-T34,0) -> 0 | V35: 135058 | W35: =IF(V35>=V34,V35-V34,0) -> 0 | X35: 245216 | Y35: =IF(X35>=X34,X35-X34,0) -> 0 | Z35: 367687 | AA35: =IF(Z35>=Z34,Z35-Z34,0)*0.53 -> 0 | AB35: 393488 | AC35: =IF(AB35>=AB34,AB35-AB34,0)*0.53 -> 0 | AD35: 580657 | AE35: =IF(AD35>=AD34,AD35-AD34,0)*0.53 -> 0 | AF35: 310194 | AG35: =IF(AF35>=AF34,AF35-AF34,0)*0.53 -> 0 | AH35: 330145 | AI35: =IF(AH35>=AH34,AH35-AH34,0)*0.53 -> 0 | AJ35: 708263 | AK35: =IF(AJ35>=AJ34,AJ35-AJ34,0)*0.53 -> 0 | AL35: 548748 | AM35: =IF(AL35>=AL34,AL35-AL34,0)*0.53 -> 0 | AN35: 820202 | AO35: =IF(AN35>=AN34,AN35-AN34,0)*0.53 -> 0 | AP35: 389263 | AQ35: =IF(AP35>=AP34,AP35-AP34,0)*0.53 -> 0 | AR35: =AA35+AC35+AE35+AG35+AI35+AK35+AM35+AO35+AQ35 -> 0 | AS35: 7225978 | AT35: =IF(AS35>=AS34,AS35-AS34,0)*0.1125 -> 0 | AU35: 581825 | AV35: =IF(AU35>=AU34,AU35-AU34,0) -> 0 | AW35: 916482 | AX35: =IF(AW35>=AW34,AW35-AW34,0) -> 0 | AY35: 795644 | AZ35: =IF(AY35>=AY34,AY35-AY34,0) -> 0 | BA35: 2347553 | BB35: =IF(BA35>=BA34,BA35-BA34,0) -> 0 | BC35: 211243 | BD35: =IF(BC35>=BC34,BC35-BC34,0) -> 0 | BE35: 17764320 | BF35: =IF(BE35>=BE34,BE35-BE34,0) -> 0 | BG35: 501061 | BH35: =IF(BG35>=BG34,BG35-BG34,0) -> 0 | BI35: 8820 | BJ35: =IF(BI35>=BI34,BI35-BI34,0) -> 0 | BK35: 22043251 | BL35: =IF(BK35>=BK34,BK35-BK34,0)-(0.45*BR35)-(0.45*BT35)-BV35 -> 0 | BM35: =AT35+AV35+AX35+AZ35+BB35+BD35+BF35+BH35+BJ35+BL35 -> 0 | BN35: =BM35+AR35 -> 0 | BO35: 1379222 | BP35: =IF(BO35>=BO34,BO35-BO34,0) -> 0 | BQ35: 3517202 | BR35: =IF(BQ35>=BQ34,BQ35-BQ34,0) -> 0 | BS35: 375841 | BT35: =IF(BS35>=BS34,BS35-BS34,0) -> 0 | BU35: 457558 | BV35: =IF(BU35>=BU34,BU35-BU34,0) -> 0 | BW35: =J35+Q35+AR35+BM35 -> 0 | BY35: =IF(BW35>0,BW35/BX35,0) -> 0 | CA35: =IF(BW35>0,BW35/BZ35,0) -> 0 | CB35: =BW35*CD1 -> 0 | CC35: =IF(CB35>0,CB35/BX35,0) -> 0 | CD35: =IF(CB35>0,CB35/BZ35,0) -> 0
A36: 31 | I36: 22188532 | J36: =IF(I36>=I35,I36-I35,0) -> 0 | K36: =M36+O36 -> 0 | L36: 44927 | M36: =IF(L36>=L35,L36-L35,0) -> 0 | N36: 49105 | O36: =IF(N36>=N35,N36-N35,0) -> 0 | P36: 215244 | Q36: =IF(P36>=P35,P36-P35,0)*30 -> 0 | R36: 702925 | S36: =IF(R36>=R35,R36-R35,0) -> 0 | T36: 344001 | U36: =IF(T36>=T35,T36-T35,0) -> 0 | V36: 135058 | W36: =IF(V36>=V35,V36-V35,0) -> 0 | X36: 245216 | Y36: =IF(X36>=X35,X36-X35,0) -> 0 | Z36: 367687 | AA36: =IF(Z36>=Z35,Z36-Z35,0)*0.53 -> 0 | AB36: 393488 | AC36: =IF(AB36>=AB35,AB36-AB35,0)*0.53 -> 0 | AD36: 580657 | AE36: =IF(AD36>=AD35,AD36-AD35,0)*0.53 -> 0 | AF36: 310194 | AG36: =IF(AF36>=AF35,AF36-AF35,0)*0.53 -> 0 | AH36: 330145 | AI36: =IF(AH36>=AH35,AH36-AH35,0)*0.53 -> 0 | AJ36: 708263 | AK36: =IF(AJ36>=AJ35,AJ36-AJ35,0)*0.53 -> 0 | AL36: 548748 | AM36: =IF(AL36>=AL35,AL36-AL35,0)*0.53 -> 0 | AN36: 820202 | AO36: =IF(AN36>=AN35,AN36-AN35,0)*0.53 -> 0 | AP36: 389263 | AQ36: =IF(AP36>=AP35,AP36-AP35,0)*0.53 -> 0 | AR36: =AA36+AC36+AE36+AG36+AI36+AK36+AM36+AO36+AQ36 -> 0 | AS36: 7225978 | AT36: =IF(AS36>=AS35,AS36-AS35,0)*0.1125 -> 0 | AU36: 581825 | AV36: =IF(AU36>=AU35,AU36-AU35,0) -> 0 | AW36: 916482 | AX36: =IF(AW36>=AW35,AW36-AW35,0) -> 0 | AY36: 795644 | AZ36: =IF(AY36>=AY35,AY36-AY35,0) -> 0 | BA36: 2347553 | BB36: =IF(BA36>=BA35,BA36-BA35,0) -> 0 | BC36: 211243 | BD36: =IF(BC36>=BC35,BC36-BC35,0) -> 0 | BE36: 17764320 | BF36: =IF(BE36>=BE35,BE36-BE35,0) -> 0 | BG36: 501061 | BH36: =IF(BG36>=BG35,BG36-BG35,0) -> 0 | BI36: 8820 | BJ36: =IF(BI36>=BI35,BI36-BI35,0) -> 0 | BK36: 22043251 | BL36: =IF(BK36>=BK35,BK36-BK35,0)-(0.45*BR36)-(0.45*BT36)-BV36 -> 0 | BM36: =AT36+AV36+AX36+AZ36+BB36+BD36+BF36+BH36+BJ36+BL36 -> 0 | BN36: =BM36+AR36 -> 0 | BO36: 1379222 | BP36: =IF(BO36>=BO35,BO36-BO35,0) -> 0 | BQ36: 3517202 | BR36: =IF(BQ36>=BQ35,BQ36-BQ35,0) -> 0 | BS36: 375841 | BT36: =IF(BS36>=BS35,BS36-BS35,0) -> 0 | BU36: 457558 | BV36: =IF(BU36>=BU35,BU36-BU35,0) -> 0 | BW36: =J36+Q36+AR36+BM36 -> 0 | BY36: =IF(BW36>0,BW36/BX36,0) -> 0 | CA36: =IF(BW36>0,BW36/BZ36,0) -> 0 | CB36: =BW36*CD1 -> 0 | CC36: =IF(CB36>0,CB36/BX36,0) -> 0 | CD36: =IF(CB36>0,CB36/BZ36,0) -> 0
A37: MTD | C37: =SUM(C9:C35) -> 0 | E37: =SUM(E9:E35) -> 0 | F37: =SUM(F9:F35) -> 0 | G37: =SUM(G9:G35) -> 0 | J37: =SUM(J6:J36) -> 134700 | K37: =SUM(K6:K36) -> 88531 | M37: =SUM(M6:M36) -> 42373 | O37: =SUM(O6:O36) -> 46158 | Q37: =SUM(Q6:Q36) -> 15240 | S37: =SUM(S6:S36) -> 0 | U37: =SUM(U6:U36) -> 0 | W37: =SUM(W6:W36) -> 4074 | Y37: =SUM(Y6:Y36) -> 6919 | AA37: =SUM(AA6:AA36) -> 27746.56 | AC37: =SUM(AC5:AC36) -> 5943.95 | AE37: =SUM(AE6:AE36) -> 9700.59 | AG37: =SUM(AG6:AG36) -> 1335.6 | AI37: =SUM(AI6:AI36) -> 341.70488 | AK37: =SUM(AK6:AK36) -> 340.40512 | AM37: =SUM(AM6:AM36) -> 7932.51 | AO37: =SUM(AO6:AO36) -> 56435.99 | AQ37: =SUM(AQ6:AQ36) -> 4848.0236 | AR37: =SUM(AR6:AR36) -> 114625.33 | AT37: =SUM(AT6:AT36) -> 1333.0125 | AV37: =SUM(AV6:AV36) -> 7544 | AX37: =SUM(AX6:AX36) -> 3014 | AZ37: =SUM(AZ6:AZ36) -> 920 | BB37: =SUM(BB6:BB36) -> 10069 | BD37: =SUM(BD6:BD36) -> 1773 | BF37: =SUM(BF6:BF36) -> 93581 | BH37: =SUM(BH6:BH36) -> 3029.2857 | BJ37: =SUM(BJ6:BJ36) -> 15 | BL37: =SUM(BL6:BL36) -> 132433.25 | BM37: =SUM(BM6:BM36) -> 253711.55 | BN37: =SUM(BN6:BN36) -> 368336.88 | BP37: =SUM(BP6:BP36) -> 9808 | BR37: =SUM(BR6:BR36) -> 25991 | BT37: =SUM(BT6:BT36) -> 3096 | BV37: =SUM(BV6:BV36) -> 5344 | BW37: =SUM(BW6:BW36) -> 518276.88 | BX37: =SUM(BX6:BX36) -> 1776 | BY37: =IF(BW37>0,BW37/BX37,0) -> 291.82257 | BZ37: =SUM(BZ6:BZ35) -> 0 | CA37: =IF(BW37>0,BW37/BZ37,0) -> #DIV/0! | CB37: =SUM(CB6:CB35) -> 596018.41 | CC37: =IF(CB37>0,CB37/BX37,0) -> 335.59595 | CD37: =IF(CB37>0,CB37/BZ37,0) -> #DIV/0!
A38: AVER. Act | C38: =C37/C40 -> #DIV/0! | E38: =E37/C40 -> #DIV/0! | F38: =F37/C40 -> #DIV/0! | G38: =G37/C40 -> #DIV/0! | J38: =J37/J39 -> 4490 | K38: =K37/J39 -> 2951.0333 | M38: =M37/J39 -> 1412.4333 | O38: =O37/J39 -> 1538.6 | Q38: =Q37/J39 -> 508 | S38: =S37/J39 -> 0 | U38: =U37/J39 -> 0 | W38: =W37/J39 -> 135.8 | Y38: =Y37/J39 -> 230.63333 | AA38: =AA37/J39 -> 924.88533 | AC38: =AC37/J39 -> 198.13167 | AE38: =AE37/J39 -> 323.353 | AG38: =AG37/J39 -> 44.52 | AI38: =AI37/J39 -> 11.390163 | AK38: =AK37/J39 -> 11.346837 | AM38: =AM37/J39 -> 264.417 | AO38: =AO37/J39 -> 1881.1997 | AQ38: =AQ37/J39 -> 161.60079 | AR38: =AR37/J39 -> 3820.8445 | AT38: =AT37/J39 -> 44.43375 | AV38: =AV37/J39 -> 251.46667 | AX38: =AX37/J39 -> 100.46667 | AZ38: =AZ37/J39 -> 30.666667 | BB38: =BB37/J39 -> 335.63333 | BD38: =BD37/J39 -> 59.1 | BF38: =BF37/J39 -> 3119.3667 | BH38: =BH37/J39 -> 100.97619 | BJ38: =BJ37/J39 -> 0.5 | BL38: =BL37/J39 -> 4414.4417 | BP38: =BP37/J39 -> 326.93333 | BR38: =BR37/J39 -> 866.36667 | BT38: =BT37/J39 -> 103.2 | BV38: =BV37/J39 -> 178.13333 | BW38: =BW37/$J$41 -> #DIV/0! | BX38: =BX37/$J$41 -> #DIV/0! | BY38: =BW38/BX38 -> #DIV/0! | BZ38: =BZ37/$J$41 -> #DIV/0! | CA38: =BW38/BZ38 -> #DIV/0! | CB38: =CB37/$J$41 -> #DIV/0! | CC38: =CB38/BX38 -> #DIV/0! | CD38: =CB38/BZ38 -> #DIV/0!
A39: No of Days MTD | J39: =COUNTIF(I6:I35,">0") -> 30
A40: No of Days month | J40: =COUNTIF(A6:A35,">0") -> 30

Sheet Gas
A1: =Elect!A1 -> February | E1: Gas | H1: Gas UP | J1: 3.9
A4: NO. | B4: Main Gas Flow Meter | D4: Laundry Gas Flow Meter | F4: Grumandiz Gas Flow Meter | H4: Plant Room Gas Share Cost | I4: Hotel Consumption Cost | J4: La Grumandiz Cost | K4: Total Natural Gas Consumption
B5: Read | C5: Cons | D5: Read | E5: Cons | F5: Read | G5: Cons | H5: LE/DAY | I5: LE/DAY | J5: LE/DAY | K5: Cons
B6: 7978015 | C6: =IF(B6>=B5,B6-B5,0)*1.06 -> 0 | D6: 321271 | E6: =IF(D6>=D5,D6-D5,0)*0.7 -> 0 | F6: 570220 | G6: =IF(F6>=F5,F6-F5,0) -> 0 | K6: =C6+E6 -> 0
A7: 1 | B7: 7978589 | C7: =IF(B7>=B6,B7-B6,0)*1.06 -> 608.44 | D7: 321745 | E7: =IF(D7>=D6,D7-D6,0)*0.7 -> 331.8 | F7: 570250 | G7: =IF(F7>=F6,F7-F6,0) -> 30 | H7: =(E7*0.55)*1.61 -> 293.8089 | I7: =C7*J1 -> 2372.916 | J7: =G7*J1 -> 117 | K7: =C7+E7 -> 940.24
A8: 2 | B8: 7979468 | C8: =IF(B8>=B7,B8-B7,0)*1.06 -> 931.74 | D8: 322100 | E8: =IF(D8>=D7,D8-D7,0)*0.7 -> 248.5 | F8: 570306 | G8: =IF(F8>=F7,F8-F7,0) -> 56 | H8: =(E8*0.55)*1.61 -> 220.04675 | I8: =C8*J1 -> 3633.786 | J8: =G8*J1 -> 218.4 | K8: =C8+E8 -> 1180.24
A9: 3 | B9: 7980271 | C9: =IF(B9>=B8,B9-B8,0)*1.06 -> 851.18 | D9: 322482 | E9: =IF(D9>=D8,D9-D8,0)*0.7 -> 267.4 | F9: 570371 | G9: =IF(F9>=F8,F9-F8,0) -> 65 | H9: =(E9*0.55)*1.61 -> 236.7827 | I9: =C9*J1 -> 3319.602 | J9: =G9*J1 -> 253.5 | K9: =C9+E9 -> 1118.58
A10: 4 | B10: 7981112 | C10: =IF(B10>=B9,B10-B9,0)*1.06 -> 891.46 | D10: 322896 | E10: =IF(D10>=D9,D10-D9,0)*0.7 -> 289.8 | F10: 570424 | G10: =IF(F10>=F9,F10-F9,0) -> 53 | H10: =(E10*0.55)*1.61 -> 256.6179 | I10: =C10*J1 -> 3476.694 | J10: =G10*J1 -> 206.7 | K10: =C10+E10 -> 1181.26
A11: 5 | B11: 7982054 | C11: =IF(B11>=B10,B11-B10,0)*1.06 -> 998.52 | D11: 323343 | E11: =IF(D11>=D10,D11-D10,0)*0.7 -> 312.9 | F11: 570505 | G11: =IF(F11>=F10,F11-F10,0) -> 81 | H11: =(E11*0.55)*1.61 -> 277.07295 | I11: =C11*J1 -> 3894.228 | J11: =G11*J1 -> 315.9 | K11: =C11+E11 -> 1311.42
A12: 6 | B12: 7982946 | C12: =IF(B12>=B11,B12-B11,0)*1.06 -> 945.52 | D12: 323718 | E12: =IF(D12>=D11,D12-D11,0)*0.7 -> 262.5 | F12: 570591 | G12: =IF(F12>=F11,F12-F11,0) -> 86 | H12: =(E12*0.55)*1.61 -> 232.44375 | I12: =C12*J1 -> 3687.528 | J12: =G12*J1 -> 335.4 | K12: =C12+E12 -> 1208.02
A13: 7 | B13: 7983688 | C13: =IF(B13>=B12,B13-B12,0)*1.06 -> 786.52 | D13: 324081 | E13: =IF(D13>=D12,D13-D12,0)*0.7 -> 254.1 | F13: 570670 | G13: =IF(F13>=F12,F13-F12,0) -> 79 | H13: =(E13*0.55)*1.61 -> 225.00555 | I13: =C13*J1 -> 3067.428 | J13: =G13*J1 -> 308.1 | K13: =C13+E13 -> 1040.62
A14: 8 | B14: 7984543 | C14: =IF(B14>=B13,B14-B13,0)*1.06 -> 906.3 | D14: 324440 | E14: =IF(D14>=D13,D14-D13,0)*0.7 -> 251.3 | F14: 570758 | G14: =IF(F14>=F13,F14-F13,0) -> 88 | H14: =(E14*0.55)*1.61 -> 222.52615 | I14: =C14*J1 -> 3534.57 | J14: =G14*J1 -> 343.2 | K14: =C14+E14 -> 1157.6
A15: 9 | B15: 7985357 | C15: =IF(B15>=B14,B15-B14,0)*1.06 -> 862.84 | D15: 324817 | E15: =IF(D15>=D14,D15-D14,0)*0.7 -> 263.9 | F15: 570837 | G15: =IF(F15>=F14,F15-F14,0) -> 79 | H15: =(E15*0.55)*1.61 -> 233.68345 | I15: =C15*J1 -> 3365.076 | J15: =G15*J1 -> 308.1 | K15: =C15+E15 -> 1126.74
A16: 10 | B16: 7986204 | C16: =IF(B16>=B15,B16-B15,0)*1.06 -> 897.82 | D16: 325184 | E16: =IF(D16>=D15,D16-D15,0)*0.7 -> 256.9 | F16: 570912 | G16: =IF(F16>=F15,F16-F15,0) -> 75 | H16: =(E16*0.55)*1.61 -> 227.48495 | I16: =C16*J1 -> 3501.498 | J16: =G16*J1 -> 292.5 | K16: =C16+E16 -> 1154.72
A17: 11 | B17: 7987029 | C17: =IF(B17>=B16,B17-B16,0)*1.06 -> 874.5 | D17: 325549 | E17: =IF(D17>=D16,D17-D16,0)*0.7 -> 255.5 | F17: 570988 | G17: =IF(F17>=F16,F17-F16,0) -> 76 | H17: =(E17*0.55)*1.61 -> 226.24525 | I17: =C17*J1 -> 3410.55 | J17: =G17*J1 -> 296.4 | K17: =C17+E17 -> 1130
A18: 12 | B18: 7987875 | C18: =IF(B18>=B17,B18-B17,0)*1.06 -> 896.76 | D18: 325922 | E18: =IF(D18>=D17,D18-D17,0)*0.7 -> 261.1 | F18: 571060 | G18: =IF(F18>=F17,F18-F17,0) -> 72 | H18: =(E18*0.55)*1.61 -> 231.20405 | I18: =C18*J1 -> 3497.364 | J18: =G18*J1 -> 280.8 | K18: =C18+E18 -> 1157.86
A19: 13 | B19: 7988696 | C19: =IF(B19>=B18,B19-B18,0)*1.06 -> 870.26 | D19: 326289 | E19: =IF(D19>=D18,D19-D18,0)*0.7 -> 256.9 | F19: 571138 | G19: =IF(F19>=F18,F19-F18,0) -> 78 | H19: =(E19*0.55)*1.61 -> 227.48495 | I19: =C19*J1 -> 3394.014 | J19: =G19*J1 -> 304.2 | K19: =C19+E19 -> 1127.16
A20: 14 | B20: 7989530 | C20: =IF(B20>=B19,B20-B19,0)*1.06 -> 884.04 | D20: 326647 | E20: =IF(D20>=D19,D20-D19,0)*0.7 -> 250.6 | F20: 571174 | G20: =IF(F20>=F19,F20-F19,0) -> 36 | H20: =(E20*0.55)*1.61 -> 221.9063 | I20: =C20*J1 -> 3447.756 | J20: =G20*J1 -> 140.4 | K20: =C20+E20 -> 1134.64
A21: 15 | B21: 7991038 | C21: =IF(B21>=B20,B21-B20,0)*1.06 -> 1598.48 | D21: 327099 | E21: =IF(D21>=D20,D21-D20,0)*0.7 -> 316.4 | F21: 571240 | G21: =IF(F21>=F20,F21-F20,0) -> 66 | H21: =(E21*0.55)*1.61 -> 280.1722 | I21: =C21*J1 -> 6234.072 | J21: =G21*J1 -> 257.4 | K21: =C21+E21 -> 1914.88
A22: 16 | B22: 7992388 | C22: =IF(B22>=B21,B22-B21,0)*1.06 -> 1431 | D22: 327524 | E22: =IF(D22>=D21,D22-D21,0)*0.7 -> 297.5 | F22: 571297 | G22: =IF(F22>=F21,F22-F21,0) -> 57 | H22: =(E22*0.55)*1.61 -> 263.43625 | I22: =C22*J1 -> 5580.9 | J22: =G22*J1 -> 222.3 | K22: =C22+E22 -> 1728.5
A23: 17 | B23: 7993137 | C23: =IF(B23>=B22,B23-B22,0)*1.06 -> 793.94 | D23: 327929 | E23: =IF(D23>=D22,D23-D22,0)*0.7 -> 283.5 | F23: 571361 | G23: =IF(F23>=F22,F23-F22,0) -> 64 | H23: =(E23*0.55)*1.61 -> 251.03925 | I23: =C23*J1 -> 3096.366 | J23: =G23*J1 -> 249.6 | K23: =C23+E23 -> 1077.44
A24: 18 | B24: 7994198 | C24: =IF(B24>=B23,B24-B23,0)*1.06 -> 1124.66 | D24: 328344 | E24: =IF(D24>=D23,D24-D23,0)*0.7 -> 290.5 | F24: 571422 | G24: =IF(F24>=F23,F24-F23,0) -> 61 | H24: =(E24*0.55)*1.61 -> 257.23775 | I24: =C24*J1 -> 4386.174 | J24: =G24*J1 -> 237.9 | K24: =C24+E24 -> 1415.16
A25: 19 | B25: 7995488 | C25: =IF(B25>=B24,B25-B24,0)*1.06 -> 1367.4 | D25: 328759 | E25: =IF(D25>=D24,D25-D24,0)*0.7 -> 290.5 | F25: 571483 | G25: =IF(F25>=F24,F25-F24,0) -> 61 | H25: =(E25*0.55)*1.61 -> 257.23775 | I25: =C25*J1 -> 5332.86 | J25: =G25*J1 -> 237.9 | K25: =C25+E25 -> 1657.9
A26: 20 | B26: 7996255 | C26: =IF(B26>=B25,B26-B25,0)*1.06 -> 813.02 | D26: 328937 | E26: =IF(D26>=D25,D26-D25,0)*0.7 -> 124.6 | F26: 571512 | G26: =IF(F26>=F25,F26-F25,0) -> 29 | H26: =(E26*0.55)*1.61 -> 110.3333 | I26: =C26*J1 -> 3170.778 | J26: =G26*J1 -> 113.1 | K26: =C26+E26 -> 937.62
A27: 21 | B27: 7997301 | C27: =IF(B27>=B26,B27-B26,0)*1.06 -> 1108.76 | D27: 329420 | E27: =IF(D27>=D26,D27-D26,0)*0.7 -> 338.1 | F27: 571646 | G27: =IF(F27>=F26,F27-F26,0) -> 134 | H27: =(E27*0.55)*1.61 -> 299.38755 | I27: =C27*J1 -> 4324.164 | J27: =G27*J1 -> 522.6 | K27: =C27+E27 -> 1446.86
A28: 22 | B28: 7998087 | C28: =IF(B28>=B27,B28-B27,0)*1.06 -> 833.16 | D28: 329654 | E28: =IF(D28>=D27,D28-D27,0)*0.7 -> 163.8 | F28: 571672 | G28: =IF(F28>=F27,F28-F27,0) -> 26 | H28: =(E28*0.55)*1.61 -> 145.0449 | I28: =C28*J1 -> 3249.324 | J28: =G28*J1 -> 101.4
A29: 23 | B29: 7998845 | C29: =IF(B29>=B28,B29-B28,0)*1.06 -> 803.48 | D29: 330169 | E29: =IF(D29>=D28,D29-D28,0)*0.7 -> 360.5 | F29: 571777 | G29: =IF(F29>=F28,F29-F28,0) -> 105 | H29: =(E29*0.55)*1.61 -> 319.22275 | I29: =C29*J1 -> 3133.572 | J29: =G29*J1 -> 409.5 | K29: =C29+E29 -> 1163.98
A30: 24 | B30: 7999998 | C30: =IF(B30>=B29,B30-B29,0)*1.06 -> 1222.18 | D30: 330552 | E30: =IF(D30>=D29,D30-D29,0)*0.7 -> 268.1 | F30: 571846 | G30: =IF(F30>=F29,F30-F29,0) -> 69 | H30: =(E30*0.55)*1.61 -> 237.40255 | I30: =C30*J1 -> 4766.502 | J30: =G30*J1 -> 269.1 | K30: =C30+E30 -> 1490.28
A31: 25 | B31: 8001532 | C31: =IF(B31>=B30,B31-B30,0)*1.06 -> 1626.04 | D31: 330936 | E31: =IF(D31>=D30,D31-D30,0)*0.7 -> 268.8 | F31: 571915 | G31: =IF(F31>=F30,F31-F30,0) -> 69 | H31: =(E31*0.55)*1.61 -> 238.0224 | I31: =C31*J3 -> 0 | J31: =G31*J1 -> 269.1 | K31: =C31+E31 -> 1894.84
A32: 26 | B32: 8002524 | C32: =IF(B32>=B31,B32-B31,0)*1.06 -> 1051.52 | D32: 331311 | E32: =IF(D32>=D31,D32-D31,0)*0.7 -> 262.5 | F32: 572009 | G32: =IF(F32>=F31,F32-F31,0) -> 94 | H32: =(E32*0.55)*1.61 -> 232.44375 | I32: =C32*J1 -> 4100.928 | J32: =G32*J1 -> 366.6 | K32: =C32+E32 -> 1314.02
A33: 27 | B33: 8003393 | C33: =IF(B33>=B32,B33-B32,0)*1.06 -> 921.14 | D33: 331669 | E33: =IF(D33>=D32,D33-D32,0)*0.7 -> 250.6 | F33: 572050 | G33: =IF(F33>=F32,F33-F32,0) -> 41 | H33: =(E33*0.55)*1.61 -> 221.9063 | I33: =C33*J1 -> 3592.446 | J33: =G33*J1 -> 159.9 | K33: =C33+E33 -> 1171.74
A34: 28 | B34: 8004424 | C34: =IF(B34>=B33,B34-B33,0)*1.06 -> 1092.86 | D34: 332047 | E34: =IF(D34>=D33,D34-D33,0)*0.7 -> 264.6 | F34: 572119 | G34: =IF(F34>=F33,F34-F33,0) -> 69 | H34: =(E34*0.55)*1.61 -> 234.3033 | I34: =C34*J1 -> 4262.154 | J34: =G34*J1 -> 269.1 | K34: =C34+E34 -> 1357.46
A35: 29 | B35: 8004424 | C35: =IF(B35>=B34,B35-B34,0)*1.06 -> 0 | D35: 332047 | E35: =IF(D35>=D34,D35-D34,0)*0.7 -> 0 | F35: 572119 | G35: =IF(F35>=F34,F35-F34,0) -> 0 | H35: =(E35*0.55)*1.61 -> 0 | I35: =C35*J1 -> 0 | J35: =G35*J1 -> 0 | K35: =C35+E35 -> 0
A36: 30 | B36: 8004424 | C36: =IF(B36>=B35,B36-B35,0)*1.06 -> 0 | D36: 332047 | E36: =IF(D36>=D35,D36-D35,0)*0.7 -> 0 | F36: 572119 | G36: =IF(F36>=F35,F36-F35,0) -> 0 | H36: =(E36*0.55)*1.61 -> 0 | I36: =C36*J1 -> 0 | J36: =G36*J1 -> 0 | K36: =C36+E36 -> 0
A37: 31 | B37: 8004424 | C37: =IF(B37>=B36,B37-B36,0)*1.06 -> 0 | D37: 332047 | E37: =IF(D37>=D36,D37-D36,0)*0.7 -> 0 | F37: 572119 | G37: =IF(F37>=F36,F37-F36,0) -> 0 | H37: =(E37*0.55)*1.61 -> 0 | I37: =C37*J1 -> 0 | J37: =G37*J1 -> 0 | K37: =C37+E37 -> 0
A38: MTD | C38: =SUM(C7:C37) -> 27993.54 | E38: =SUM(E7:E37) -> 7543.2 | G38: =SUM(G7:G37) -> 1899 | H38: =SUM(H6:H37) -> 6679.5036 | I38: =SUM(I6:I37) -> 102833.25 | J38: =SUM(J6:J37) -> 7406.1 | K38: =SUM(K6:K37) -> 34539.78
A39: Average MTD. | C39: =C38/A42 -> 933.118 | E39: =E38/A42 -> 251.44 | G39: =G38/A42 -> 63.3 | H39: =H38/A42 -> 222.65012 | I39: =I38/A42 -> 3427.775 | J39: =J38/A42 -> 246.87
A41: No of Days MTD
A42: =COUNTIF(B7:B36,">0") -> 30

Sheet Water
A1: =Elect!A1 -> February | T1: Main Water UP | V1: 4 | W1: Water Truck UP
A3: Day | E3: Water Incoming | I3: New casino | N3: Rooms Consumption | P3: Public Areas consumption | R3: Swimming pool | T3: No. of rooms | U3: Cons. Per occ. room | V3: No. of guest | W3: Cons. Per guest | X3: Total cost | Y3: L.E\ | Z3: L.E\
B4: Main water meter 1 | D4: Main water meter 2 | F4: Main water meter 3 | H4: Total Inc. | I4: Hot water | K4: Cold water | N4: Express Riser | O4: Consp. | P4: Read. | Q4: Cons. | R4: Read. | S4: Cons. | Y4: Room | Z4: Guest
B5: Counter | C5: Produc 58% | D5: Counter | E5: Produc 58% | F5: Counter | G5: Produc 58% | I5: Counter | K5: Counter
B6: 74321 | C6: =IF(B6>=B5,B6-B5,0)*10*0.58 -> 0 | D6: 155092 | E6: =IF(D6>=D5,D6-D5,0)*10*0.58 -> 0 | F6: 17670 | G6: =IF(F6>=F5,F6-F5,0)*0.58 -> 0 | I6: 211 | K6: 2887
A7: 1 | B7: 74334 | C7: =IF(B7>=B6,B7-B6,0)*10*0.58 -> 75.4 | D7: 155127 | E7: =IF(D7>=D6,D7-D6,0)*10*0.58 -> 203 | F7: 17670 | G7: =IF(F7>=F6,F7-F6,0)*0.58 -> 0 | H7: =C7+E7+G7 -> 278.4 | O7: =IF(N7>=N6,N7-N6,0) -> 0 | Q7: =(H7-O7)*0.58 -> 161.472 | S7: =IF(R7-R6>0,R7-R6,0) -> 0 | T7: =Elect!BX6 -> 32 | U7: =H7/T7 -> 8.7 | V7: =Elect!BZ6 -> 0 | W7: =H7/V7 -> #DIV/0! | X7: =H7*V1 -> 1113.6 | Y7: =IF(X7>0,X7/T7,0) -> 34.8 | Z7: 0
A8: 2 | B8: 74351 | C8: =IF(B8>=B7,B8-B7,0)*10*0.58 -> 98.6 | D8: 155146 | E8: =IF(D8>=D7,D8-D7,0)*10*0.58 -> 110.2 | F8: 17670 | G8: =IF(F8>=F7,F8-F7,0)*0.58 -> 0 | H8: =C8+E8+G8 -> 208.8 | O8: =IF(N8>=N7,N8-N7,0) -> 0 | Q8: =(H8-O8)*0.58 -> 121.104 | S8: =IF(R8-R7>0,R8-R7,0) -> 0 | T8: =Elect!BX7 -> 36 | U8: =H8/T8 -> 5.8 | V8: =Elect!BZ7 -> 0 | W8: =H8/V8 -> #DIV/0! | X8: =H8*V1 -> 835.2 | Y8: =IF(X8>0,X8/T8,0) -> 23.2 | Z8: =IF(X8>0,X8/V8,0) -> #DIV/0!
A9: 3 | B9: 74370 | C9: =IF(B9>=B8,B9-B8,0)*10*0.58 -> 110.2 | D9: 155159 | E9: =IF(D9>=D8,D9-D8,0)*10*0.58 -> 75.4 | F9: 17670 | G9: =IF(F9>=F8,F9-F8,0)*0.58 -> 0 | H9: =C9+E9+G9 -> 185.6 | O9: =IF(N9>=N8,N9-N8,0) -> 0 | Q9: =(H9-O9)*0.58 -> 107.648 | S9: =IF(R9-R8>0,R9-R8,0) -> 0 | T9: =Elect!BX8 -> 43 | U9: =H9/T9 -> 4.3162791 | V9: =Elect!BZ8 -> 0 | W9: =H9/V9 -> #DIV/0! | X9: =H9*V1 -> 742.4 | Y9: =IF(X9>0,X9/T9,0) -> 17.265116 | Z9: =IF(X9>0,X9/V9,0) -> #DIV/0!
A10: 4 | B10: 74400 | C10: =IF(B10>=B9,B10-B9,0)*10*0.58 -> 174 | D10: 155190 | E10: =IF(D10>=D9,D10-D9,0)*10*0.58 -> 179.8 | F10: 17670 | G10: =IF(F10>=F9,F10-F9,0)*0.58 -> 0 | H10: =C10+E10+G10 -> 353.8 | O10: =IF(N10>=N9,N10-N9,0) -> 0 | Q10: =(H10-O10)*0.58 -> 205.204 | S10: =IF(R10-R9>0,R10-R9,0) -> 0 | T10: =Elect!BX9 -> 66 | U10: =H10/T10 -> 5.3606061 | V10: =Elect!BZ9 -> 0 | W10: =H10/V10 -> #DIV/0! | X10: =H10*V1 -> 1415.2 | Y10: =IF(X10>0,X10/T10,0) -> 21.442424 | Z10: =IF(X10>0,X10/V10,0) -> #DIV/0!
A11: 5 | B11: 74430 | C11: =IF(B11>=B10,B11-B10,0)*10*0.58 -> 174 | D11: 155216 | E11: =IF(D11>=D10,D11-D10,0)*10*0.58 -> 150.8 | F11: 17670 | G11: =IF(F11>=F10,F11-F10,0)*0.58 -> 0 | H11: =C11+E11+G11 -> 324.8 | O11: =IF(N11>=N10,N11-N10,0) -> 0 | Q11: =(H11-O11)*0.58 -> 188.384 | S11: =IF(R11-R10>0,R11-R10,0) -> 0 | T11: =Elect!BX10 -> 68 | U11: =H11/T11 -> 4.7764706 | V11: =Elect!BZ10 -> 0 | W11: =H11/V11 -> #DIV/0! | X11: =H11*V1 -> 1299.2 | Y11: =IF(X11>0,X11/T11,0) -> 19.105882 | Z11: =IF(X11>0,X11/V11,0) -> #DIV/0!
A12: 6 | B12: 74450 | C12: =IF(B12>=B11,B12-B11,0)*10*0.58 -> 116 | D12: 155226 | E12: =IF(D12>=D11,D12-D11,0)*10*0.58 -> 58 | F12: 17670 | G12: =IF(F12>=F11,F12-F11,0)*0.58 -> 0 | H12: =C12+E12+G12 -> 174 | O12: =IF(N12>=N11,N12-N11,0) -> 0 | Q12: =(H12-O12)*0.58 -> 100.92 | S12: =IF(R12-R11>0,R12-R11,0) -> 0 | T12: =Elect!BX11 -> 75 | U12: =H12/T12 -> 2.32 | V12: =Elect!BZ11 -> 0 | W12: =H12/V12 -> #DIV/0! | X12: =H12*V1 -> 696 | Y12: =IF(X12>0,X12/T12,0) -> 9.28 | Z12: =IF(X12>0,X12/V12,0) -> #DIV/0!
A13: 7 | B13: 74469.143 | C13: =IF(B13>=B12,B13-B12,0)*10*0.58 -> 111.02857 | D13: 155239 | E13: =IF(D13>=D12,D13-D12,0)*10*0.58 -> 75.4 | F13: 17670 | G13: =IF(F13>=F12,F13-F12,0)*0.58 -> 0 | H13: =C13+E13+G13 -> 186.42857 | O13: =IF(N13>=N12,N13-N12,0) -> 0 | Q13: =(H13-O13)*0.58 -> 108.12857 | S13: =IF(R13-R12>0,R13-R12,0) -> 0 | T13: =Elect!BX12 -> 59 | U13: =H13/T13 -> 3.1598063 | V13: =Elect!BZ12 -> 0 | W13: =H13/V13 -> #DIV/0! | X13: =H13*V1 -> 745.71429 | Y13: =IF(X13>0,X13/T13,0) -> 12.639225 | Z13: =IF(X13>0,X13/V13,0) -> #DIV/0!
A14: 8 | B14: 74490 | C14: =IF(B14>=B13,B14-B13,0)*10*0.58 -> 120.97143 | D14: 155250 | E14: =IF(D14>=D13,D14-D13,0)*10*0.58 -> 63.8 | F14: 17670 | G14: =IF(F14>=F13,F14-F13,0)*0.58 -> 0 | H14: =C14+E14+G14 -> 184.77143 | O14: =IF(N14>=N13,N14-N13,0) -> 0 | Q14: =(H14-O14)*0.58 -> 107.16743 | S14: =IF(R14-R13>0,R14-R13,0) -> 0 | T14: =Elect!BX13 -> 49 | U14: =H14/T14 -> 3.7708455 | V14: =Elect!BZ13 -> 0 | W14: =H14/V14 -> #DIV/0! | X14: =H14*V1 -> 739.08571 | Y14: =IF(X14>0,X14/T14,0) -> 15.083382 | Z14: =IF(X14>0,X14/V14,0) -> #DIV/0!
A15: 9 | B15: 74514 | C15: =IF(B15>=B14,B15-B14,0)*10*0.58 -> 139.2 | D15: 155259 | E15: =IF(D15>=D14,D15-D14,0)*10*0.58 -> 52.2 | F15: 17670 | G15: =IF(F15>=F14,F15-F14,0)*0.58 -> 0 | H15: =C15+E15+G15 -> 191.4 | O15: =IF(N15>=N14,N15-N14,0) -> 0 | Q15: =(H15-O15)*0.58 -> 111.012 | S15: =IF(R15-R14>0,R15-R14,0) -> 0 | T15: =Elect!BX14 -> 53 | U15: =H15/T15 -> 3.6113208 | V15: =Elect!BZ14 -> 0 | W15: =H15/V15 -> #DIV/0! | X15: =H15*V1 -> 765.6 | Y15: =IF(X15>0,X15/T15,0) -> 14.445283 | Z15: =IF(X15>0,X15/V15,0) -> #DIV/0!
A16: 10 | B16: 74536 | C16: =IF(B16>=B15,B16-B15,0)*10*0.58 -> 127.6 | D16: 155271 | E16: =IF(D16>=D15,D16-D15,0)*10*0.58 -> 69.6 | F16: 17670 | G16: =IF(F16>=F15,F16-F15,0)*0.58 -> 0 | H16: =C16+E16+G16 -> 197.2 | O16: =IF(N16>=N15,N16-N15,0) -> 0 | Q16: =(H16-O16)*0.58 -> 114.376 | S16: =IF(R16-R15>0,R16-R15,0) -> 0 | T16: =Elect!BX15 -> 52 | U16: =H16/T16 -> 3.7923077 | V16: =Elect!BZ15 -> 0 | W16: =H16/V16 -> #DIV/0! | X16: =H16*V1 -> 788.8 | Y16: =IF(X16>0,X16/T16,0) -> 15.169231 | Z16: =IF(X16>0,X16/V16,0) -> #DIV/0!
A17: 11 | B17: 74558 | C17: =IF(B17>=B16,B17-B16,0)*10*0.58 -> 127.6 | D17: 155280 | E17: =IF(D17>=D16,D17-D16,0)*10*0.58 -> 52.2 | F17: 17670 | G17: =IF(F17>=F16,F17-F16,0)*0.58 -> 0 | H17: =C17+E17+G17 -> 179.8 | O17: =IF(N17>=N16,N17-N16,0) -> 0 | Q17: =(H17-O17)*0.58 -> 104.284 | S17: =IF(R17-R16>0,R17-R16,0) -> 0 | T17: =Elect!BX16 -> 54 | U17: =H17/T17 -> 3.3296296 | V17: =Elect!BZ16 -> 0 | W17: =H17/V17 -> #DIV/0! | X17: =H17*V1 -> 719.2 | Y17: =IF(X17>0,X17/T17,0) -> 13.318519 | Z17: =IF(X17>0,X17/V17,0) -> #DIV/0!
A18: 12 | B18: 74581 | C18: =IF(B18>=B17,B18-B17,0)*10*0.58 -> 133.4 | D18: 155291 | E18: =IF(D18>=D17,D18-D17,0)*10*0.58 -> 63.8 | F18: 17670 | G18: =IF(F18>=F17,F18-F17,0)*0.58 -> 0 | H18: =C18+E18+G18 -> 197.2 | O18: =IF(N18>=N17,N18-N17,0) -> 0 | Q18: =(H18-O18)*0.58 -> 114.376 | S18: =IF(R18-R17>0,R18-R17,0) -> 0 | T18: =Elect!BX17 -> 69 | U18: =H18/T18 -> 2.857971 | V18: =Elect!BZ17 -> 0 | W18: =H18/V18 -> #DIV/0! | X18: =H18*V1 -> 788.8 | Y18: =IF(X18>0,X18/T18,0) -> 11.431884 | Z18: =IF(X18>0,X18/V18,0) -> #DIV/0!
A19: 13 | B19: 74604 | C19: =IF(B19>=B18,B19-B18,0)*10*0.58 -> 133.4 | D19: 155301 | E19: =IF(D19>=D18,D19-D18,0)*10*0.58 -> 58 | F19: 17670 | G19: =IF(F19>=F18,F19-F18,0)*0.58 -> 0 | H19: =C19+E19+G19 -> 191.4 | O19: =IF(N19>=N18,N19-N18,0) -> 0 | Q19: =(H19-O19)*0.58 -> 111.012 | S19: =IF(R19-R18>0,R19-R18,0) -> 0 | T19: =Elect!BX18 -> 54 | U19: =H19/T19 -> 3.5444444 | V19: =Elect!BZ18 -> 0 | W19: =H19/V19 -> #DIV/0! | X19: =H19*V1 -> 765.6 | Y19: =IF(X19>0,X19/T19,0) -> 14.177778 | Z19: =IF(X19>0,X19/V19,0) -> #DIV/0!
A20: 14 | B20: 74626 | C20: =IF(B20>=B19,B20-B19,0)*10*0.58 -> 127.6 | D20: 155310 | E20: =IF(D20>=D19,D20-D19,0)*10*0.58 -> 52.2 | F20: 17670 | G20: =IF(F20>=F19,F20-F19,0)*0.58 -> 0 | H20: =C20+E20+G20 -> 179.8 | O20: =IF(N20>=N19,N20-N19,0) -> 0 | Q20: =(H20-O20)*0.58 -> 104.284 | S20: =IF(R20-R19>0,R20-R19,0) -> 0 | T20: =Elect!BX19 -> 68 | U20: =H20/T20 -> 2.6441176 | V20: =Elect!BZ19 -> 0 | W20: =H20/V20 -> #DIV/0! | X20: =H20*V1 -> 719.2 | Y20: =IF(X20>0,X20/T20,0) -> 10.576471 | Z20: =IF(X20>0,X20/V20,0) -> #DIV/0!
A21: 15 | B21: 74648 | C21: =IF(B21>=B20,B21-B20,0)*10*0.58 -> 127.6 | D21: 155315 | E21: =IF(D21>=D20,D21-D20,0)*10*0.58 -> 29 | F21: 17670 | G21: =IF(F21>=F20,F21-F20,0)*0.58 -> 0 | H21: =C21+E21+G21 -> 156.6 | O21: =IF(N21>=N20,N21-N20,0) -> 0 | Q21: =(H21-O21)*0.58 -> 90.828 | S21: =IF(R21-R20>0,R21-R20,0) -> 0 | T21: =Elect!BX20 -> 62 | U21: =H21/T21 -> 2.5258065 | V21: =Elect!BZ20 -> 0 | W21: =H21/V21 -> #DIV/0! | X21: =H21*V1 -> 626.4 | Y21: =IF(X21>0,X21/T21,0) -> 10.103226 | Z21: =IF(X21>0,X21/V21,0) -> #DIV/0!
A22: 16 | B22: 74674 | C22: =IF(B22>=B21,B22-B21,0)*10*0.58 -> 150.8 | D22: 155321 | E22: =IF(D22>=D21,D22-D21,0)*10*0.58 -> 34.8 | F22: 17670 | G22: =IF(F22>=F21,F22-F21,0)*0.58 -> 0 | H22: =C22+E22+G22 -> 185.6 | O22: =IF(N22>=N21,N22-N21,0) -> 0 | Q22: =(H22-O22)*0.58 -> 107.648 | S22: =IF(R22-R21>0,R22-R21,0) -> 0 | T22: =Elect!BX21 -> 69 | U22: =H22/T22 -> 2.6898551 | V22: =Elect!BZ21 -> 0 | W22: =H22/V22 -> #DIV/0! | X22: =H22*V1 -> 742.4 | Y22: =IF(X22>0,X22/T22,0) -> 10.75942 | Z22: =IF(X22>0,X22/V22,0) -> #DIV/0!
A23: 17 | B23: 74693 | C23: =IF(B23>=B22,B23-B22,0)*10*0.58 -> 110.2 | D23: 155329 | E23: =IF(D23>=D22,D23-D22,0)*10*0.58 -> 46.4 | F23: 17670 | G23: =IF(F23>=F22,F23-F22,0)*0.58 -> 0 | H23: =C23+E23+G23 -> 156.6 | O23: =IF(N23>=N22,N23-N22,0) -> 0 | Q23: =(H23-O23)*0.58 -> 90.828 | S23: =IF(R23-R22>0,R23-R22,0) -> 0 | T23: =Elect!BX22 -> 80 | U23: =H23/T23 -> 1.9575 | V23: =Elect!BZ22 -> 0 | W23: =H23/V23 -> #DIV/0! | X23: =H23*V1 -> 626.4 | Y23: =IF(X23>0,X23/T23,0) -> 7.83 | Z23: =IF(X23>0,X23/V23,0) -> #DIV/0!
A24: 18 | B24: 74710 | C24: =IF(B24>=B23,B24-B23,0)*10*0.58 -> 98.6 | D24: 155332 | E24: =IF(D24>=D23,D24-D23,0)*10*0.58 -> 17.4 | F24: 17670 | G24: =IF(F24>=F23,F24-F23,0)*0.58 -> 0 | H24: =C24+E24+G24 -> 116 | O24: =IF(N24>=N23,N24-N23,0) -> 0 | Q24: =(H24-O24)*0.58 -> 67.28 | S24: =IF(R24-R23>0,R24-R23,0) -> 0 | T24: =Elect!BX23 -> 70 | U24: =H24/T24 -> 1.6571429 | V24: =Elect!BZ23 -> 0 | W24: =H24/V24 -> #DIV/0! | X24: =H24*V1 -> 464 | Y24: =IF(X24>0,X24/T24,0) -> 6.6285714 | Z24: =IF(X24>0,X24/V24,0) -> #DIV/0!
A25: 19 | B25: 74721 | C25: =IF(B25>=B24,B25-B24,0)*10*0.58 -> 63.8 | D25: 155338 | E25: =IF(D25>=D24,D25-D24,0)*10*0.58 -> 34.8 | F25: 17670 | G25: =IF(F25>=F24,F25-F24,0)*0.58 -> 0 | H25: =C25+E25+G25 -> 98.6 | O25: =IF(N25>=N24,N25-N24,0) -> 0 | Q25: =(H25-O25)*0.58 -> 57.188 | S25: =IF(R25-R24>0,R25-R24,0) -> 0 | T25: =Elect!BX24 -> 63 | U25: =H25/T25 -> 1.5650794 | V25: =Elect!BZ24 -> 0 | W25: =H25/V25 -> #DIV/0! | X25: =H25*V1 -> 394.4 | Y25: =IF(X25>0,X25/T25,0) -> 6.2603175 | Z25: =IF(X25>0,X25/V25,0) -> #DIV/0!
A26: 20 | B26: 74738 | C26: =IF(B26>=B25,B26-B25,0)*10*0.58 -> 98.6 | D26: 155343 | E26: =IF(D26>=D25,D26-D25,0)*10*0.58 -> 29 | F26: 17670 | G26: =IF(F26>=F25,F26-F25,0)*0.58 -> 0 | H26: =C26+E26+G26 -> 127.6 | O26: =IF(N26>=N25,N26-N25,0) -> 0 | Q26: =(H26-O26)*0.58 -> 74.008 | S26: =IF(R26-R25>0,R26-R25,0) -> 0 | T26: =Elect!BX25 -> 56 | U26: =H26/T26 -> 2.2785714 | V26: =Elect!BZ25 -> 0 | W26: =H26/V26 -> #DIV/0! | X26: =H26*V1 -> 510.4 | Y26: =IF(X26>0,X26/T26,0) -> 9.1142857 | Z26: =IF(X26>0,X26/V26,0) -> #DIV/0!
A27: 21 | B27: 74754 | C27: =IF(B27>=B26,B27-B26,0)*10*0.58 -> 92.8 | D27: 155344 | E27: =IF(D27>=D26,D27-D26,0)*10*0.58 -> 5.8 | F27: 17670 | G27: =IF(F27>=F26,F27-F26,0)*0.58 -> 0 | H27: =C27+E27+G27 -> 98.6 | O27: =IF(N27>=N26,N27-N26,0) -> 0 | Q27: =(H27-O27)*0.58 -> 57.188 | S27: =IF(R27-R26>0,R27-R26,0) -> 0 | T27: =Elect!BX26 -> 87 | U27: =H27/T27 -> 1.1333333 | V27: =Elect!BZ26 -> 0 | W27: =H27/V27 -> #DIV/0! | X27: =H27*V1 -> 394.4 | Y27: =IF(X27>0,X27/T27,0) -> 4.5333333 | Z27: =IF(X27>0,X27/V27,0) -> #DIV/0!
A28: 22 | B28: 74773 | C28: =IF(B28>=B27,B28-B27,0)*10*0.58 -> 110.2 | D28: 155346 | E28: =IF(D28>=D27,D28-D27,0)*10*0.58 -> 11.6 | F28: 17670 | G28: =IF(F28>=F27,F28-F27,0)*0.58 -> 0 | H28: =C28+E28+G28 -> 121.8 | O28: =IF(N28>=N27,N28-N27,0) -> 0 | Q28: =(H28-O28)*0.58 -> 70.644 | S28: =IF(R28-R27>0,R28-R27,0) -> 0 | T28: =Elect!BX27 -> 88 | U28: =H28/T28 -> 1.3840909 | V28: =Elect!BZ27 -> 0 | W28: =H28/V28 -> #DIV/0! | X28: =H28*V1 -> 487.2 | Y28: =IF(X28>0,X28/T28,0) -> 5.5363636 | Z28: =IF(X28>0,X28/V28,0) -> #DIV/0!
A29: 23 | B29: 74800 | C29: =IF(B29>=B28,B29-B28,0)*10*0.58 -> 156.6 | D29: 155347 | E29: =IF(D29>=D28,D29-D28,0)*10*0.58 -> 5.8 | F29: 17680 | G29: =IF(F29>=F28,F29-F28,0)*0.58 -> 5.8 | H29: =C29+E29+G29 -> 168.2 | O29: =IF(N29>=N28,N29-N28,0) -> 0 | Q29: =(H29-O29)*0.58 -> 97.556 | S29: =IF(R29-R28>0,R29-R28,0) -> 0 | T29: =Elect!BX28 -> 83 | U29: =H29/T29 -> 2.026506 | V29: =Elect!BZ28 -> 0 | W29: =H29/V29 -> #DIV/0! | X29: =H29*V1 -> 672.8 | Y29: =IF(X29>0,X29/T29,0) -> 8.1060241 | Z29: =IF(X29>0,X29/V29,0) -> #DIV/0!
A30: 24 | B30: 74832 | C30: =IF(B30>=B29,B30-B29,0)*10*0.58 -> 185.6 | D30: 155348 | E30: =IF(D30>=D29,D30-D29,0)*10*0.58 -> 5.8 | F30: 17690 | G30: =IF(F30>=F29,F30-F29,0)*0.58 -> 5.8 | H30: =C30+E30+G30 -> 197.2 | O30: =IF(N30>=N29,N30-N29,0) -> 0 | Q30: =(H30-O30)*0.58 -> 114.376 | S30: =IF(R30-R29>0,R30-R29,0) -> 0 | T30: =Elect!BX29 -> 88 | U30: =H30/T30 -> 2.2409091 | V30: =Elect!BZ29 -> 0 | W30: =H30/V30 -> #DIV/0! | X30: =H30*V1 -> 788.8 | Y30: =IF(X30>0,X30/T30,0) -> 8.9636364 | Z30: =IF(X30>0,X30/V30,0) -> #DIV/0!
A31: 25 | B31: 74854 | C31: =IF(B31>=B30,B31-B30,0)*10*0.58 -> 127.6 | D31: 155349 | E31: =IF(D31>=D30,D31-D30,0)*10*0.58 -> 5.8 | F31: 17700 | G31: =IF(F31>=F30,F31-F30,0)*0.58 -> 5.8 | H31: =C31+E31+G31 -> 139.2 | O31: =IF(N31>=N30,N31-N30,0) -> 0 | Q31: =(H31-O31)*0.58 -> 80.736 | S31: =IF(R31-R30>0,R31-R30,0) -> 0 | T31: =Elect!BX30 -> 77 | U31: =H31/T31 -> 1.8077922 | V31: =Elect!BZ30 -> 0 | W31: =H31/V31 -> #DIV/0! | X31: =H31*V1 -> 556.8 | Y31: =IF(X31>0,X31/T31,0) -> 7.2311688 | Z31: =IF(X31>0,X31/V31,0) -> #DIV/0!
A32: 26 | B32: 74878 | C32: =IF(B32>=B31,B32-B31,0)*10*0.58 -> 139.2 | D32: 155350 | E32: =IF(D32>=D31,D32-D31,0)*10*0.58 -> 5.8 | F32: 17709 | G32: =IF(F32>=F31,F32-F31,0)*0.58 -> 5.22 | H32: =C32+E32+G32 -> 150.22 | O32: =IF(N32>=N31,N32-N31,0) -> 0 | Q32: =(H32-O32)*0.58 -> 87.1276 | S32: =IF(R32-R31>0,R32-R31,0) -> 0 | T32: =Elect!BX31 -> 58 | U32: =H32/T32 -> 2.59 | V32: =Elect!BZ31 -> 0 | W32: =H32/V32 -> #DIV/0! | X32: =H32*V1 -> 600.88 | Y32: =IF(X32>0,X32/T32,0) -> 10.36 | Z32: =IF(X32>0,X32/V32,0) -> #DIV/0!
A33: 27 | B33: 74900 | C33: =IF(B33>=B32,B33-B32,0)*10*0.58 -> 127.6 | D33: 155351 | E33: =IF(D33>=D32,D33-D32,0)*10*0.58 -> 5.8 | F33: 17719 | G33: =IF(F33>=F32,F33-F32,0)*0.58 -> 5.8 | H33: =C33+E33+G33 -> 139.2 | O33: =IF(N33>=N32,N33-N32,0) -> 0 | Q33: =(H33-O33)*0.58 -> 80.736 | S33: =IF(R33-R32>0,R33-R32,0) -> 0 | T33: =Elect!BX32 -> 59 | U33: =H33/T33 -> 2.359322 | V33: =Elect!BZ32 -> 0 | W33: =H33/V33 -> #DIV/0! | X33: =H33*V1 -> 556.8 | Y33: =IF(X33>0,X33/T33,0) -> 9.4372881 | Z33: =IF(X33>0,X33/V33,0) -> #DIV/0!
A34: 28 | B34: 74920 | C34: =IF(B34>=B33,B34-B33,0)*10*0.58 -> 116 | D34: 155352 | E34: =IF(D34>=D33,D34-D33,0)*10*0.58 -> 5.8 | F34: 17728 | G34: =IF(F34>=F33,F34-F33,0)*0.58 -> 5.22 | H34: =C34+E34+G34 -> 127.02 | O34: =IF(N34>=N33,N34-N33,0) -> 0 | Q34: =(H34-O34)*0.58 -> 73.6716 | S34: =IF(R34-R33>0,R34-R33,0) -> 0 | T34: =Elect!BX33 -> 58 | U34: =H34/T34 -> 2.19 | V34: =Elect!BZ33 -> 0 | W34: =H34/V34 -> #DIV/0! | X34: =H34*V1 -> 508.08 | Y34: =IF(X34>0,X34/T34,0) -> 8.76 | Z34: =IF(X34>0,X34/V34,0) -> #DIV/0!
A35: 29 | B35: 74920 | C35: =IF(B35>=B34,B35-B34,0)*10*0.58 -> 0 | D35: 155352 | E35: =IF(D35>=D34,D35-D34,0)*10*0.58 -> 0 | F35: 17728 | G35: =IF(F35>=F34,F35-F34,0)*0.58 -> 0 | H35: =C35+E35+G35 -> 0 | O35: =IF(N35>=N34,N35-N34,0) -> 0 | Q35: =(H35-O35)*0.58 -> 0 | S35: =IF(R35-R34>0,R35-R34,0) -> 0 | T35: =Elect!BX34 -> 0 | U35: =H35/T35 -> #DIV/0! | V35: =Elect!BZ34 -> 0 | W35: =H35/V35 -> #DIV/0! | X35: =H35*V1 -> 0 | Y35: =IF(X35>0,X35/T35,0) -> 0 | Z35: =IF(X35>0,X35/V35,0) -> 0
A36: 30 | B36: 74920 | C36: =IF(B36>=B35,B36-B35,0)*10*0.58 -> 0 | D36: 155352 | E36: =IF(D36>=D35,D36-D35,0)*10*0.58 -> 0 | F36: 17728 | G36: =IF(F36>=F35,F36-F35,0)*0.58 -> 0 | H36: =C36+E36+G36 -> 0 | O36: =IF(N36>=N35,N36-N35,0) -> 0 | Q36: =(H36-O36)*0.58 -> 0 | S36: =IF(R36-R35>0,R36-R35,0) -> 0 | T36: =Elect!BX35 -> 0 | U36: =H36/T36 -> #DIV/0! | V36: =Elect!BZ35 -> 0 | W36: =H36/V36 -> #DIV/0! | X36: =H36*V1 -> 0 | Y36: =IF(X36>0,X36/T36,0) -> 0 | Z36: =IF(X36>0,X36/V36,0) -> 0
A37: 31 | B37: 74920 | C37: =IF(B37>=B36,B37-B36,0)*10*0.58 -> 0 | D37: 155352 | E37: =IF(D37>=D36,D37-D36,0)*10*0.58 -> 0 | F37: 17728 | G37: =IF(F37>=F36,F37-F36,0)*0.58 -> 0 | H37: =C37+E37+G37 -> 0 | I37: 212.2 | K37: 2958 | O37: =IF(N37>=N36,N37-N36,0) -> 0 | Q37: =(H37-O37)*0.58 -> 0 | S37: =IF(R37-R36>0,R37-R36,0) -> 0 | T37: =Elect!BX36 -> 0 | U37: =H37/T37 -> #DIV/0! | V37: =Elect!BZ36 -> 0 | W37: =H37/V37 -> #DIV/0! | X37: =H37*V7 -> 0 | Y37: =IF(X37>0,X37/T37,0) -> 0 | Z37: =IF(X37>0,X37/V37,0) -> 0
A38: MTD | C38: =SUM(C7:C37) -> 3474.2 | E38: =SUM(E7:E37) -> 1508 | G38: =SUM(G7:G37) -> 33.64 | H38: =SUM(H7:H37) -> 5015.84 | I38: =I37-I6 -> 1.2 | K38: =K37-K6 -> 71 | O38: =SUM(O7:O36) -> 0 | Q38: =SUM(Q7:Q34) -> 2909.1872 | S38: =SUM(S7:S34) -> 0 | T38: =SUM(T7:T36) -> 1776 | U38: =IF(H38>0,H38/T38,0) -> 2.8242342 | V38: =SUM(V7:V36) -> 0 | W38: =IF(H38>0,H38/V38,0) -> #DIV/0! | X38: =SUM(X7:X36) -> 20063.36 | Y38: =IF(X38>0,X38/T38,0) -> 11.296937 | Z38: =IF(X38>0,X38/V38,0) -> #DIV/0!
A39: AVER. Act | C39: =C38/B48 -> 115.80667 | E39: =E38/B48 -> 50.266667 | G39: =G38/B48 -> 1.1213333 | H39: =H38/B48 -> 167.19467 | O39: =O38/B48 -> 0 | Q39: =Q38/B48 -> 96.972907 | S39: =S38/C48 -> #DIV/0! | T39: =T38/B48 -> 59.2 | U39: =IF(H39>0,H39/T39,0) -> 2.8242342 | V39: =V38/B48 -> 0 | W39: =IF(H39>0,H39/V39,0) -> #DIV/0! | X39: =X38/B48 -> 668.77867 | Y39: =IF(X39>0,X39/T39,0) -> 11.296937 | Z39: =IF(X39>0,X39/V39,0) -> #DIV/0!
A40: TOTAL Budget | T40: =YTD!Q2341 -> 0 | U40: =IF(#REF!>0,#REF!/T40,0) -> #REF! | V40: =YTD!Q2342 -> 0 | W40: =IF(#REF!>0,#REF!/V40,0) -> #REF! | X40: =YTD!Q2346 -> 0 | Y40: =IF(X40>0,X40/T40,0) -> 0 | Z40: =IF(X40>0,X40/V40,0) -> 0
A41: Budget MTD | T41: =T42*C48 -> #VALUE! | U41: =IF(#REF!>0,#REF!/T41,0) -> #REF! | V41: =V42*C48 -> #VALUE! | W41: =IF(#REF!>0,#REF!/V41,0) -> #REF! | X41: =#REF!*5.62 -> #REF! | Y41: =IF(X41>0,X41/T41,0) -> #REF! | Z41: =IF(X41>0,X41/V41,0) -> #REF!
A42: AVER. Bud | T42: =T40/$A$48 -> #VALUE! | V42: =V40/$A$48 -> #VALUE!
A43: Total RFC | T43: =YTD!Q2358 -> 0 | V43: =YTD!Q2359 -> 0 | X43: =YTD!Q2363 -> 0 | Y43: =IF(X43>0,X43/T43,0) -> 0 | Z43: =IF(X43>0,X43/V43,0) -> 0
A44: RFC MTD | T44: =T43/A48*C48 -> #VALUE! | V44: =V43/A48*C48 -> #VALUE! | X44: =X43/A48*C48 -> #VALUE! | Y44: =IF(X44>0,X44/T44,0) -> #VALUE! | Z44: =IF(X44>0,X44/V44,0) -> #VALUE!
A45: AVER RFC | T45: =T43/A48 -> #VALUE! | V45: =V44/A48*C48 -> #VALUE! | X45: =X43/A48 -> #VALUE!
A46: MTD 13 | U46: =Consp!BH33 -> 1.1514679 | W46: =Consp!BI33 -> 0.57929342 | X46: =Consp!BJ33 -> 140121.3 | Y46: =Consp!BK33 -> 6.8331854 | Z46: =Consp!BL33 -> 3.4377159
A47: AVER. Act 13 | U47: =Consp!BH34 -> 1.1761372 | W47: =Consp!BI34 -> 0.60007377 | X47: =Consp!BJ34 -> 5004.3322 | Y47: =Consp!BK34 -> 6.8331854 | Z47: =Consp!BL34 -> 3.4377159
A48: No of Days MTD | B48: =COUNTIF(B7:B36,">0") -> 30
A136: Water Incoming

Sheet Consp
A1: =Elect!A1 -> February | L1: Summary | P1: =Elect!A1 -> February
B2: Elect Consuumption | H2: Water Incoming | U2: Water Consumption | AC2: Irrigation | AG2: Gas | AJ2: Cost | AK2: Solar Meter [ LIT ] | AL2: No. of Eng. | AM2: No. of Gardners | AN2: Cons. (lit) | AO2: Received Gas (tons) | AP2: Fuel Cost | AQ2: Solar level [cm] | AR2: Received Solar (tons) | AS2: Fuel Cost | AT2: Occupancy 10 | AV2: Occupancy07 | AZ2: Elect 2009 | BE2: Elect 2010 | BJ2: Water 2009 | BO2: Water 2010
A3: Date | B3: COUNTER (2) | D3: MD | F3: KVAR | H3: R.O | J3: Qenna | L3: Trucks | N3: Rimievera Line Meter | O3: Total Inc. | Q3: Total Main S.Pool | S3: Total Bar & Beach cons. | U3: Total S. Pool cons. | W3: Hotel consumption. | Y3: Sold Water | AA3: Irr. Water from R.O | AC3: Irr. Consumption. | AE3: Storage Water One tank | AF3: Grand Cons | AG3: % | AH3: Stock | AI3: Cons. | AJ3: 0 | AT3: No of guest | AU3: No. of rooms | AV3: No. of rooms | AW3: No. of guest | AX3: Cons. Per occ. room | AY3: Cons. Per guest | AZ3: Total cost | BA3: cost per room | BB3: cost per guest | BC3: Cons. Per occ. room | BD3: Cons. Per guest | BE3: Total cost | BF3: cost per room | BG3: cost per guest | BH3: Cons. Per occ. room | BI3: Cons. Per guest | BJ3: Total cost | BK3: cost per room | BL3: cost per guest | BM3: Cons. Per occ. room | BN3: Cons. Per guest | BO3: Total cost | BP3: cost per room | BQ3: cost per guest
B4: 2013 | C4: 2014 | D4: 2013 | E4: 2014 | F4: 2013 | G4: 2014 | H4: 2013 | I4: 2014 | J4: 2009 | K4: 2010 | L4: 2009 | M4: 2010 | O4: 2009 | P4: 2010 | Q4: 2009 | R4: 2010 | S4: 2009 | T4: 2010 | U4: 2009 | V4: 2010 | W4: 2009 | X4: 2010 | Y4: 2009 | Z4: 2010 | AA4: 2009 | AB4: 2010 | AC4: 2009 | AD4: 2010
A5: 1 | B5: 33600 | C5: =Elect!J6 -> 2651 | D5: 0 | E5: =Elect!M6 -> 692 | F5: 20 | G5: =Elect!O6 -> 2159 | H5: 800 | I5: =Water!C7 -> 75.4 | J5: 0 | K5: =Water!E7 -> 203 | L5: 0 | M5: =Water!#REF! -> #REF! | N5: =Water!#REF! -> #REF! | O5: 1005 | P5: =Water!H7 -> 278.4 | Q5: 114 | R5: =Water!O7 -> 0 | S5: 13 | T5: =Water!#REF! -> #REF! | U5: 147 | V5: =Water!#REF! -> #REF! | W5: 755 | X5: =Water!Q7 -> 161.472 | Y5: 0 | Z5: =Water!#REF! -> #REF! | AA5: 0 | AB5: 0 | AC5: 690 | AD5: =Water!#REF! -> #REF! | AE5: =Water!#REF! -> #REF! | AF5: =Water!#REF! -> #REF! | AG5: =Gas!#REF! -> #REF! | AH5: =Gas!C7 -> 608.44 | AI5: =Gas!#REF! -> #REF! | AJ5: =Gas!J7 -> 117 | AK5: =Gas!#REF! -> #REF! | AL5: =Gas!#REF! -> #REF! | AM5: =Gas!#REF! -> #REF! | AN5: =Gas!#REF! -> #REF! | AO5: =Gas!#REF! -> #REF! | AP5: =Gas!#REF! -> #REF! | AQ5: =Gas!#REF! -> #REF! | AR5: =Gas!#REF! -> #REF! | AS5: =Gas!#REF! -> #REF! | AT5: =Elect!BV6 -> 197 | AU5: =Elect!BT6 -> 110 | AV5: =Elect!#REF! -> #REF! | AW5: =Elect!BV6 -> 197 | AX5: 48.695652 | AY5: 24.705882 | AZ5: 8835.4834 | BA5: 12.805048 | BB5: 6.496679 | BC5: =Elect!#REF! -> #REF! | BD5: =Elect!#REF! -> #REF! | BE5: =Elect!#REF! -> #REF! | BF5: =Elect!#REF! -> #REF! | BG5: =Elect!#REF! -> #REF! | BH5: 1.142029 | BI5: 0.57941176 | BJ5: 4569.1158 | BK5: 6.6219069 | BL5: 3.3596439 | BM5: =Water!U7 -> 8.7 | BN5: =Water!W7 -> #DIV/0! | BO5: =Water!X7 -> 1113.6 | BP5: =Water!Y7 -> 34.8 | BQ5: =Water!Z7 -> 0
A6: 2 | B6: 31200 | C6: =Elect!J7 -> 4448 | D6: 0 | E6: =Elect!M7 -> 1160 | F6: 20 | G6: =Elect!O7 -> 1685 | H6: 936 | I6: =Water!C8 -> 98.6 | J6: 0 | K6: =Water!E8 -> 110.2 | L6: 0 | M6: =Water!#REF! -> #REF! | N6: =Water!#REF! -> #REF! | O6: 1006 | P6: =Water!H8 -> 208.8 | Q6: 113 | R6: =Water!O8 -> 0 | S6: 17 | T6: =Water!#REF! -> #REF! | U6: 140 | V6: =Water!#REF! -> #REF! | W6: 792 | X6: =Water!Q8 -> 121.104 | Y6: 0 | Z6: =Water!#REF! -> #REF! | AA6: 0 | AB6: 0 | AC6: 370 | AD6: =Water!#REF! -> #REF! | AE6: =Water!#REF! -> #REF! | AF6: =Water!#REF! -> #REF! | AG6: =Gas!B7 -> 7978589 | AH6: =Gas!C8 -> 931.74 | AI6: =Gas!#REF! -> #REF! | AJ6: =Gas!J8 -> 218.4 | AK6: =Gas!#REF! -> #REF! | AL6: =Gas!#REF! -> #REF! | AM6: =Gas!#REF! -> #REF! | AN6: =Gas!#REF! -> #REF! | AO6: =Gas!#REF! -> #REF! | AP6: =Gas!#REF! -> #REF! | AQ6: =Gas!#REF! -> #REF! | AR6: =Gas!#REF! -> #REF! | AS6: =Gas!#REF! -> #REF! | AT6: =Elect!BV7 -> 206 | AU6: =Elect!BT7 -> 118 | AX6: 47.416413 | AY6: 23.981553 | AZ6: 8299.2754 | BA6: 12.612881 | BB6: 6.379151 | BC6: =Elect!BU7 -> 452617 | BD6: =Elect!#REF! -> #REF! | BE6: =Elect!#REF! -> #REF! | BF6: =Elect!#REF! -> #REF! | BG6: =Elect!#REF! -> #REF! | BH6: 1.2021277 | BI6: 0.60799385 | BJ6: 5345.8654 | BK6: 8.1244156 | BL6: 4.1090434 | BM6: =Water!U8 -> 5.8 | BN6: =Water!W8 -> #DIV/0! | BO6: =Water!X8 -> 835.2 | BP6: =Water!Y8 -> 23.2 | BQ6: =Water!Z8 -> #DIV/0!
A7: 3 | B7: 31200 | C7: =Elect!J8 -> 4078 | D7: 0 | E7: =Elect!M8 -> 1210 | F7: 20 | G7: =Elect!O8 -> 1524 | H7: 685 | I7: =Water!C9 -> 110.2 | J7: 0 | K7: =Water!E9 -> 75.4 | L7: 0 | M7: =Water!#REF! -> #REF! | N7: =Water!#REF! -> #REF! | O7: 902 | P7: =Water!H9 -> 185.6 | Q7: 126 | R7: =Water!O9 -> 0 | S7: 26 | T7: =Water!#REF! -> #REF! | U7: 134 | V7: =Water!#REF! -> #REF! | W7: 766 | X7: =Water!Q9 -> 107.648 | Y7: 0 | Z7: =Water!#REF! -> #REF! | AA7: 0 | AB7: 0 | AC7: 740 | AD7: =Water!#REF! -> #REF! | AE7: =Water!#REF! -> #REF! | AF7: =Water!#REF! -> #REF! | AG7: =Gas!B9 -> 7980271 | AH7: =Gas!C9 -> 851.18 | AI7: =Gas!#REF! -> #REF! | AJ7: =Gas!J9 -> 253.5 | AK7: =Gas!#REF! -> #REF! | AL7: =Gas!#REF! -> #REF! | AM7: =Gas!#REF! -> #REF! | AN7: =Gas!#REF! -> #REF! | AO7: =Gas!#REF! -> #REF! | AP7: =Gas!#REF! -> #REF! | AQ7: =Gas!#REF! -> #REF! | AR7: =Gas!#REF! -> #REF! | AS7: =Gas!#REF! -> #REF! | AT7: =Elect!BV8 -> 197 | AU7: =Elect!BT8 -> 116 | AX7: 47.926267 | AY7: 24.223602 | AZ7: 8299.2754 | BA7: 12.748503 | BB7: 6.4435368 | BC7: =Elect!BU8 -> 452814 | BD7: =Elect!#REF! -> #REF! | BE7: =Elect!#REF! -> #REF! | BF7: =Elect!#REF! -> #REF! | BG7: =Elect!#REF! -> #REF! | BH7: 1.0875576 | BI7: 0.54968944 | BJ7: 3912.3054 | BK7: 6.0096857 | BL7: 3.0375042 | BM7: =Water!U9 -> 4.3162791 | BN7: =Water!W9 -> #DIV/0! | BO7: =Water!X9 -> 742.4 | BP7: =Water!Y9 -> 17.265116 | BQ7: =Water!Z9 -> #DIV/0!
A8: 4 | B8: 33600 | C8: =Elect!J9 -> 4608 | D8: 0 | E8: =Elect!M9 -> 1344 | F8: 20 | G8: =Elect!O9 -> 1510 | H8: 786 | I8: =Water!C10 -> 174 | J8: 0 | K8: =Water!E10 -> 179.8 | L8: 0 | M8: =Water!#REF! -> #REF! | N8: =Water!#REF! -> #REF! | O8: 930 | P8: =Water!H10 -> 353.8 | Q8: 153 | R8: =Water!O10 -> 0 | S8: 46 | T8: =Water!#REF! -> #REF! | U8: 150 | V8: =Water!#REF! -> #REF! | W8: 766 | X8: =Water!Q10 -> 205.204 | Y8: 0 | Z8: =Water!#REF! -> #REF! | AA8: 0 | AB8: 0 | AC8: 820 | AD8: =Water!#REF! -> #REF! | AE8: =Water!#REF! -> #REF! | AF8: =Water!#REF! -> #REF! | AG8: =Gas!B10 -> 7981112 | AH8: =Gas!C10 -> 891.46 | AI8: =Gas!#REF! -> #REF! | AJ8: =Gas!J10 -> 206.7 | AK8: =Gas!#REF! -> #REF! | AL8: =Gas!#REF! -> #REF! | AM8: =Gas!#REF! -> #REF! | AN8: =Gas!#REF! -> #REF! | AO8: =Gas!#REF! -> #REF! | AP8: =Gas!#REF! -> #REF! | AQ8: =Gas!#REF! -> #REF! | AR8: =Gas!#REF! -> #REF! | AS8: =Gas!#REF! -> #REF! | AT8: =Elect!BV9 -> 198 | AU8: =Elect!BT9 -> 125 | AX8: 51.06383 | AY8: 25.866051 | AZ8: 8835.4834 | BA8: 13.427786 | BB8: 6.8017578 | BC8: =Elect!BU9 -> 453012 | BD8: =Elect!#REF! -> #REF! | BE8: =Elect!#REF! -> #REF! | BF8: =Elect!#REF! -> #REF! | BG8: =Elect!#REF! -> #REF! | BH8: 1.2218845 | BI8: 0.61893764 | BJ8: 4489.1562 | BK8: 6.8224259 | BL8: 3.4558555 | BM8: =Water!U10 -> 5.3606061 | BN8: =Water!W10 -> #DIV/0! | BO8: =Water!X10 -> 1415.2 | BP8: =Water!Y10 -> 21.442424 | BQ8: =Water!Z10 -> #DIV/0!
A9: 5 | B9: 31200 | C9: =Elect!J10 -> 4629 | D9: 0 | E9: =Elect!M10 -> 1301 | F9: 20 | G9: =Elect!O10 -> 1485 | H9: 789 | I9: =Water!C11 -> 174 | J9: 0 | K9: =Water!E11 -> 150.8 | L9: 0 | M9: =Water!#REF! -> #REF! | N9: =Water!#REF! -> #REF! | O9: 1003 | P9: =Water!H11 -> 324.8 | Q9: 102 | R9: =Water!O11 -> 0 | S9: 8 | T9: =Water!#REF! -> #REF! | U9: 130 | V9: =Water!#REF! -> #REF! | W9: 735 | X9: =Water!Q11 -> 188.384 | Y9: 0 | Z9: =Water!#REF! -> #REF! | AA9: 0 | AB9: 0 | AC9: 640 | AD9: =Water!#REF! -> #REF! | AE9: =Water!#REF! -> #REF! | AF9: =Water!#REF! -> #REF! | AG9: =Gas!B11 -> 7982054 | AH9: =Gas!C11 -> 998.52 | AI9: =Gas!#REF! -> #REF! | AJ9: =Gas!J11 -> 315.9 | AK9: =Gas!#REF! -> #REF! | AL9: =Gas!#REF! -> #REF! | AM9: =Gas!#REF! -> #REF! | AN9: =Gas!#REF! -> #REF! | AO9: =Gas!#REF! -> #REF! | AP9: =Gas!#REF! -> #REF! | AQ9: =Gas!#REF! -> #REF! | AR9: =Gas!#REF! -> #REF! | AS9: =Gas!#REF! -> #REF! | AT9: =Elect!BV10 -> 90 | AU9: =Elect!BT10 -> 80 | AX9: 49.840256 | AY9: 25.181598 | AZ9: 8299.2754 | BA9: 13.257628 | BB9: 6.698366 | BC9: =Elect!BU10 -> 453102 | BD9: =Elect!#REF! -> #REF! | BE9: =Elect!#REF! -> #REF! | BF9: =Elect!#REF! -> #REF! | BG9: =Elect!#REF! -> #REF! | BH9: 1.1980831 | BI9: 0.60532688 | BJ9: 4506.2904 | BK9: 7.198547 | BL9: 3.6370383 | BM9: =Water!U11 -> 4.7764706 | BN9: =Water!W11 -> #DIV/0! | BO9: =Water!X11 -> 1299.2 | BP9: =Water!Y11 -> 19.105882 | BQ9: =Water!Z11 -> #DIV/0!
A10: 6 | B10: 33600 | C10: =Elect!J11 -> 4466 | D10: 0 | E10: =Elect!M11 -> 1278 | F10: 20 | G10: =Elect!O11 -> 1548 | H10: 805 | I10: =Water!C12 -> 116 | J10: 0 | K10: =Water!E12 -> 58 | L10: 0 | M10: =Water!#REF! -> #REF! | N10: =Water!#REF! -> #REF! | O10: 1004 | P10: =Water!H12 -> 174 | Q10: 115 | R10: =Water!O12 -> 0 | S10: 21 | T10: =Water!#REF! -> #REF! | U10: 141 | V10: =Water!#REF! -> #REF! | W10: 725 | X10: =Water!Q12 -> 100.92 | Y10: 0 | Z10: =Water!#REF! -> #REF! | AA10: 0 | AB10: 0 | AC10: 510 | AD10: =Water!#REF! -> #REF! | AE10: =Water!#REF! -> #REF! | AF10: =Water!#REF! -> #REF! | AG10: =Gas!B12 -> 7982946 | AH10: =Gas!C12 -> 945.52 | AI10: =Gas!#REF! -> #REF! | AJ10: =Gas!J12 -> 335.4 | AK10: =Gas!#REF! -> #REF! | AL10: =Gas!#REF! -> #REF! | AM10: =Gas!#REF! -> #REF! | AN10: =Gas!#REF! -> #REF! | AO10: =Gas!#REF! -> #REF! | AP10: =Gas!#REF! -> #REF! | AQ10: =Gas!#REF! -> #REF! | AR10: =Gas!#REF! -> #REF! | AS10: =Gas!#REF! -> #REF! | AT10: =Elect!BV11 -> 112 | AU10: =Elect!BT11 -> 35 | AX10: 47.457627 | AY10: 23.512946 | AZ10: 8835.4834 | BA10: 12.479496 | BB10: 6.1829835 | BC10: =Elect!BU11 -> 453214 | BD10: =Elect!#REF! -> #REF! | BE10: =Elect!#REF! -> #REF! | BF10: =Elect!#REF! -> #REF! | BG10: =Elect!#REF! -> #REF! | BH10: 1.1567797 | BI10: 0.57312806 | BJ10: 4597.6727 | BK10: 6.4938881 | BL10: 3.2174057 | BM10: =Water!U12 -> 2.32 | BN10: =Water!W12 -> #DIV/0! | BO10: =Water!X12 -> 696 | BP10: =Water!Y12 -> 9.28 | BQ10: =Water!Z12 -> #DIV/0!
A11: 7 | B11: 31200 | C11: =Elect!J12 -> 4626 | D11: 0 | E11: =Elect!M12 -> 1373 | F11: 20 | G11: =Elect!O12 -> 1625 | H11: 871 | I11: =Water!C13 -> 111.02857 | J11: 0 | K11: =Water!E13 -> 75.4 | L11: 0 | M11: =Water!#REF! -> #REF! | N11: =Water!#REF! -> #REF! | O11: 837 | P11: =Water!H13 -> 186.42857 | Q11: 113 | R11: =Water!O13 -> 0 | S11: 1 | T11: =Water!#REF! -> #REF! | U11: 151 | V11: =Water!#REF! -> #REF! | W11: 732 | X11: =Water!Q13 -> 108.12857 | Y11: 0 | Z11: =Water!#REF! -> #REF! | AA11: 0 | AB11: 0 | AC11: 1010 | AD11: =Water!#REF! -> #REF! | AE11: =Water!#REF! -> #REF! | AF11: =Water!#REF! -> #REF! | AG11: =Gas!B13 -> 7983688 | AH11: =Gas!C13 -> 786.52 | AI11: =Gas!#REF! -> #REF! | AJ11: =Gas!J13 -> 308.1 | AK11: =Gas!#REF! -> #REF! | AL11: =Gas!#REF! -> #REF! | AM11: =Gas!#REF! -> #REF! | AN11: =Gas!#REF! -> #REF! | AO11: =Gas!#REF! -> #REF! | AP11: =Gas!#REF! -> #REF! | AQ11: =Gas!#REF! -> #REF! | AR11: =Gas!#REF! -> #REF! | AS11: =Gas!#REF! -> #REF! | AT11: =Elect!BV12 -> 203 | AU11: =Elect!BT12 -> 111 | AX11: 43.454039 | AY11: 21.517241 | AZ11: 8299.2754 | BA11: 11.558879 | BB11: 5.7236382 | BC11: =Elect!BU12 -> 453417 | BD11: =Elect!#REF! -> #REF! | BE11: =Elect!#REF! -> #REF! | BF11: =Elect!#REF! -> #REF! | BG11: =Elect!#REF! -> #REF! | BH11: 1.1713092 | BI11: 0.58 | BJ11: 4974.6248 | BK11: 6.9284468 | BL11: 3.4307757 | BM11: =Water!U13 -> 3.1598063 | BN11: =Water!W13 -> #DIV/0! | BO11: =Water!X13 -> 745.71429 | BP11: =Water!Y13 -> 12.639225 | BQ11: =Water!Z13 -> #DIV/0!
A12: 8 | B12: 33600 | C12: =Elect!J13 -> 4853 | D12: 0 | E12: =Elect!M13 -> 1442 | F12: 20 | G12: =Elect!O13 -> 1673 | H12: 963 | I12: =Water!C14 -> 120.97143 | J12: 0 | K12: =Water!E14 -> 63.8 | L12: 0 | M12: =Water!#REF! -> #REF! | N12: =Water!#REF! -> #REF! | O12: 1000 | P12: =Water!H14 -> 184.77143 | Q12: 128 | R12: =Water!O14 -> 0 | S12: 24 | T12: =Water!#REF! -> #REF! | U12: 148 | V12: =Water!#REF! -> #REF! | W12: 719 | X12: =Water!Q14 -> 107.16743 | Y12: 0 | Z12: =Water!#REF! -> #REF! | AA12: 0 | AB12: 0 | AC12: 630 | AD12: =Water!#REF! -> #REF! | AE12: =Water!#REF! -> #REF! | AF12: =Water!#REF! -> #REF! | AG12: =Gas!B14 -> 7984543 | AH12: =Gas!C14 -> 906.3 | AI12: =Gas!#REF! -> #REF! | AJ12: =Gas!J14 -> 343.2 | AK12: =Gas!#REF! -> #REF! | AL12: =Gas!#REF! -> #REF! | AM12: =Gas!#REF! -> #REF! | AN12: =Gas!#REF! -> #REF! | AO12: =Gas!#REF! -> #REF! | AP12: =Gas!#REF! -> #REF! | AQ12: =Gas!#REF! -> #REF! | AR12: =Gas!#REF! -> #REF! | AS12: =Gas!#REF! -> #REF! | AT12: =Elect!BV13 -> 203 | AU12: =Elect!BT13 -> 125 | AX12: 48.837209 | AY12: 24.086022 | AZ12: 8835.4834 | BA12: 12.842272 | BB12: 6.3336799 | BC12: =Elect!BU13 -> 453620 | BD12: =Elect!#REF! -> #REF! | BE12: =Elect!#REF! -> #REF! | BF12: =Elect!#REF! -> #REF! | BG12: =Elect!#REF! -> #REF! | BH12: 1.2194767 | BI12: 0.60143369 | BJ12: 5500.0731 | BK12: 7.9942923 | BL12: 3.9427047 | BM12: =Water!U14 -> 3.7708455 | BN12: =Water!W14 -> #DIV/0! | BO12: =Water!X14 -> 739.08571 | BP12: =Water!Y14 -> 15.083382 | BQ12: =Water!Z14 -> #DIV/0!
A13: 9 | B13: 33600 | C13: =Elect!J14 -> 4910 | D13: 0 | E13: =Elect!M14 -> 1409 | F13: 20 | G13: =Elect!O14 -> 1690 | H13: 790 | I13: =Water!C15 -> 139.2 | J13: 0 | K13: =Water!E15 -> 52.2 | L13: 0 | M13: =Water!#REF! -> #REF! | N13: =Water!#REF! -> #REF! | O13: 841 | P13: =Water!H15 -> 191.4 | Q13: 127 | R13: =Water!O15 -> 0 | S13: 21 | T13: =Water!#REF! -> #REF! | U13: 139 | V13: =Water!#REF! -> #REF! | W13: 701 | X13: =Water!Q15 -> 111.012 | Y13: 0 | Z13: =Water!#REF! -> #REF! | AA13: 0 | AB13: 0 | AC13: 440 | AD13: =Water!#REF! -> #REF! | AE13: =Water!#REF! -> #REF! | AF13: =Water!#REF! -> #REF! | AG13: =Gas!B15 -> 7985357 | AH13: =Gas!C15 -> 862.84 | AI13: =Gas!#REF! -> #REF! | AJ13: =Gas!J15 -> 308.1 | AK13: =Gas!#REF! -> #REF! | AL13: =Gas!#REF! -> #REF! | AM13: =Gas!#REF! -> #REF! | AN13: =Gas!#REF! -> #REF! | AO13: =Gas!#REF! -> #REF! | AP13: =Gas!#REF! -> #REF! | AQ13: =Gas!#REF! -> #REF! | AR13: =Gas!#REF! -> #REF! | AS13: =Gas!#REF! -> #REF! | AT13: =Elect!BV14 -> 199 | AU13: =Elect!BT14 -> 119 | AX13: 49.194729 | AY13: 24.1033 | AZ13: 8835.4834 | BA13: 12.936286 | BB13: 6.3382234 | BC13: =Elect!BU14 -> 453819 | BD13: =Elect!#REF! -> #REF! | BE13: =Elect!#REF! -> #REF! | BF13: =Elect!#REF! -> #REF! | BG13: =Elect!#REF! -> #REF! | BH13: 1.1903367 | BI13: 0.58321377 | BJ13: 4512.0018 | BK13: 6.606152 | BL13: 3.2367301 | BM13: =Water!U15 -> 3.6113208 | BN13: =Water!W15 -> #DIV/0! | BO13: =Water!X15 -> 765.6 | BP13: =Water!Y15 -> 14.445283 | BQ13: =Water!Z15 -> #DIV/0!
A14: 10 | B14: 31200 | C14: =Elect!J15 -> 4535 | D14: 0 | E14: =Elect!M15 -> 1506 | F14: 20 | G14: =Elect!O15 -> 1799 | H14: 792 | I14: =Water!C16 -> 127.6 | J14: 0 | K14: =Water!E16 -> 69.6 | L14: 0 | M14: =Water!#REF! -> #REF! | N14: =Water!#REF! -> #REF! | O14: 972 | P14: =Water!H16 -> 197.2 | Q14: 126 | R14: =Water!O16 -> 0 | S14: 18 | T14: =Water!#REF! -> #REF! | U14: 145 | V14: =Water!#REF! -> #REF! | W14: 756 | X14: =Water!Q16 -> 114.376 | Y14: 0 | Z14: =Water!#REF! -> #REF! | AA14: 0 | AB14: 0 | AC14: 580 | AD14: =Water!#REF! -> #REF! | AE14: =Water!#REF! -> #REF! | AF14: =Water!#REF! -> #REF! | AG14: =Gas!B16 -> 7986204 | AH14: =Gas!C16 -> 897.82 | AI14: =Gas!#REF! -> #REF! | AJ14: =Gas!J16 -> 292.5 | AK14: =Gas!#REF! -> #REF! | AL14: =Gas!#REF! -> #REF! | AM14: =Gas!#REF! -> #REF! | AN14: =Gas!#REF! -> #REF! | AO14: =Gas!#REF! -> #REF! | AP14: =Gas!#REF! -> #REF! | AQ14: =Gas!#REF! -> #REF! | AR14: =Gas!#REF! -> #REF! | AS14: =Gas!#REF! -> #REF! | AT14: =Elect!BV15 -> 208 | AU14: =Elect!BT15 -> 120 | AX14: 49.52381 | AY14: 24.781573 | AZ14: 8299.2754 | BA14: 13.173453 | BB14: 6.5919582 | BC14: =Elect!BU15 -> 454027 | BD14: =Elect!#REF! -> #REF! | BE14: =Elect!#REF! -> #REF! | BF14: =Elect!#REF! -> #REF! | BG14: =Elect!#REF! -> #REF! | BH14: 1.2730159 | BI14: 0.6370135 | BJ14: 4469.9646 | BK14: 7.0951819 | BL14: 3.5504087 | BM14: =Water!U16 -> 3.7923077 | BN14: =Water!W16 -> #DIV/0! | BO14: =Water!X16 -> 788.8 | BP14: =Water!Y16 -> 15.169231 | BQ14: =Water!Z16 -> #DIV/0!
A15: 11 | B15: 33600 | C15: =Elect!J16 -> 5806 | D15: 0 | E15: =Elect!M16 -> 1537 | F15: 20 | G15: =Elect!O16 -> 1597 | H15: 817 | I15: =Water!C17 -> 127.6 | J15: 0 | K15: =Water!E17 -> 52.2 | L15: 0 | M15: =Water!#REF! -> #REF! | N15: =Water!#REF! -> #REF! | O15: 875 | P15: =Water!H17 -> 179.8 | Q15: 122 | R15: =Water!O17 -> 0 | S15: 20 | T15: =Water!#REF! -> #REF! | U15: 156 | V15: =Water!#REF! -> #REF! | W15: 712 | X15: =Water!Q17 -> 104.284 | Y15: 0 | Z15: =Water!#REF! -> #REF! | AA15: 0 | AB15: 0 | AC15: 850 | AD15: =Water!#REF! -> #REF! | AE15: =Water!#REF! -> #REF! | AF15: =Water!#REF! -> #REF! | AG15: =Gas!#REF! -> #REF! | AH15: =Gas!C17 -> 874.5 | AI15: =Gas!#REF! -> #REF! | AJ15: =Gas!J17 -> 296.4 | AK15: =Gas!#REF! -> #REF! | AL15: =Gas!#REF! -> #REF! | AM15: =Gas!#REF! -> #REF! | AN15: =Gas!#REF! -> #REF! | AO15: =Gas!#REF! -> #REF! | AP15: =Gas!#REF! -> #REF! | AQ15: =Gas!#REF! -> #REF! | AR15: =Gas!#REF! -> #REF! | AS15: =Gas!#REF! -> #REF! | AT15: =Elect!BV16 -> 189 | AU15: =Elect!BT16 -> 107 | AX15: 53.333333 | AY15: 26.751592 | AZ15: 8835.4834 | BA15: 14.024577 | BB15: 7.0346206 | BC15: =Elect!BU16 -> 454216 | BD15: =Elect!#REF! -> #REF! | BE15: =Elect!#REF! -> #REF! | BF15: =Elect!#REF! -> #REF! | BG15: =Elect!#REF! -> #REF! | BH15: 1.3460317 | BI15: 0.67515924 | BJ15: 4666.2095 | BK15: 7.4066817 | BL15: 3.7151349 | BM15: =Water!U17 -> 3.3296296 | BN15: =Water!W17 -> #DIV/0! | BO15: =Water!X17 -> 719.2 | BP15: =Water!Y17 -> 13.318519 | BQ15: =Water!Z17 -> #DIV/0!
A16: 12 | B16: 33600 | C16: =Elect!J17 -> 4685 | D16: 0 | E16: =Elect!M17 -> 1587 | F16: 20 | G16: =Elect!O17 -> 1654 | H16: 907 | I16: =Water!C18 -> 133.4 | J16: 0 | K16: =Water!E18 -> 63.8 | L16: 0 | M16: =Water!#REF! -> #REF! | N16: =Water!#REF! -> #REF! | O16: 965 | P16: =Water!H18 -> 197.2 | Q16: 125 | R16: =Water!O18 -> 0 | S16: 4 | T16: =Water!#REF! -> #REF! | U16: 167 | V16: =Water!#REF! -> #REF! | W16: 705 | X16: =Water!Q18 -> 114.376 | Y16: 0 | Z16: =Water!#REF! -> #REF! | AA16: 0 | AB16: 0 | AC16: 880 | AD16: =Water!#REF! -> #REF! | AE16: =Water!#REF! -> #REF! | AF16: =Water!#REF! -> #REF! | AG16: =Gas!B18 -> 7987875 | AH16: =Gas!C18 -> 896.76 | AI16: =Gas!#REF! -> #REF! | AJ16: =Gas!J18 -> 280.8 | AK16: =Gas!#REF! -> #REF! | AL16: =Gas!#REF! -> #REF! | AM16: =Gas!#REF! -> #REF! | AN16: =Gas!#REF! -> #REF! | AO16: =Gas!#REF! -> #REF! | AP16: =Gas!#REF! -> #REF! | AQ16: =Gas!#REF! -> #REF! | AR16: =Gas!#REF! -> #REF! | AS16: =Gas!#REF! -> #REF! | AT16: =Elect!BV17 -> 200 | AU16: =Elect!BT17 -> 100 | AX16: 50.45045 | AY16: 25.339367 | AZ16: 8835.4834 | BA16: 13.266492 | BB16: 6.6632605 | BC16: =Elect!BU17 -> 454416 | BD16: =Elect!#REF! -> #REF! | BE16: =Elect!#REF! -> #REF! | BF16: =Elect!#REF! -> #REF! | BG16: =Elect!#REF! -> #REF! | BH16: 1.2162162 | BI16: 0.61085973 | BJ16: 5180.235 | BK16: 7.7781306 | BL16: 3.9066629 | BM16: =Water!U18 -> 2.857971 | BN16: =Water!W18 -> #DIV/0! | BO16: =Water!X18 -> 788.8 | BP16: =Water!Y18 -> 11.431884 | BQ16: =Water!Z18 -> #DIV/0!
A17: 13 | B17: 31200 | C17: =Elect!J18 -> 5904 | D17: 0 | E17: =Elect!M18 -> 1627 | F17: 20 | G17: =Elect!O18 -> 1628 | H17: 812 | I17: =Water!C19 -> 133.4 | J17: 0 | K17: =Water!E19 -> 58 | L17: 0 | M17: =Water!#REF! -> #REF! | N17: =Water!#REF! -> #REF! | O17: 822 | P17: =Water!H19 -> 191.4 | Q17: 123 | R17: =Water!O19 -> 0 | S17: 7 | T17: =Water!#REF! -> #REF! | U17: 163 | V17: =Water!#REF! -> #REF! | W17: 692 | X17: =Water!Q19 -> 111.012 | Y17: 0 | Z17: =Water!#REF! -> #REF! | AA17: 0 | AB17: 0 | AC17: 460 | AD17: =Water!#REF! -> #REF! | AE17: =Water!#REF! -> #REF! | AF17: =Water!#REF! -> #REF! | AG17: =Gas!B19 -> 7988696 | AH17: =Gas!C19 -> 870.26 | AI17: =Gas!#REF! -> #REF! | AJ17: =Gas!J19 -> 304.2 | AK17: =Gas!#REF! -> #REF! | AL17: =Gas!#REF! -> #REF! | AM17: =Gas!#REF! -> #REF! | AN17: =Gas!#REF! -> #REF! | AO17: =Gas!#REF! -> #REF! | AP17: =Gas!#REF! -> #REF! | AQ17: =Gas!#REF! -> #REF! | AR17: =Gas!#REF! -> #REF! | AS17: =Gas!#REF! -> #REF! | AT17: =Elect!BV18 -> 204 | AU17: =Elect!BT18 -> 122 | AX17: 46.567164 | AY17: 23.214286 | AZ17: 8299.2754 | BA17: 12.386978 | BB17: 6.1750561 | BC17: =Elect!BU18 -> 454620 | BD17: =Elect!#REF! -> #REF! | BE17: =Elect!#REF! -> #REF! | BF17: =Elect!#REF! -> #REF! | BG17: =Elect!#REF! -> #REF! | BH17: 1.0850746 | BI17: 0.54092262 | BJ17: 4637.6525 | BK17: 6.9218694 | BL17: 3.4506343 | BM17: =Water!U19 -> 3.5444444 | BN17: =Water!W19 -> #DIV/0! | BO17: =Water!X19 -> 765.6 | BP17: =Water!Y19 -> 14.177778 | BQ17: =Water!Z19 -> #DIV/0!
A18: 14 | B18: 33600 | C18: =Elect!J19 -> 5129 | D18: 0 | E18: =Elect!M19 -> 1566 | F18: 30 | G18: =Elect!O19 -> 1578 | H18: 810 | I18: =Water!C20 -> 127.6 | J18: 0 | K18: =Water!E20 -> 52.2 | L18: 0 | M18: =Water!#REF! -> #REF! | N18: =Water!#REF! -> #REF! | O18: 943 | P18: =Water!H20 -> 179.8 | Q18: 118 | R18: =Water!O20 -> 0 | S18: 18 | T18: =Water!#REF! -> #REF! | U18: 152 | V18: =Water!#REF! -> #REF! | W18: 708 | X18: =Water!Q20 -> 104.284 | Y18: 0 | Z18: =Water!#REF! -> #REF! | AA18: 0 | AB18: 0 | AC18: 490 | AD18: =Water!#REF! -> #REF! | AE18: =Water!#REF! -> #REF! | AF18: =Water!#REF! -> #REF! | AG18: =Gas!B20 -> 7989530 | AH18: =Gas!C20 -> 884.04 | AI18: =Gas!#REF! -> #REF! | AJ18: =Gas!J20 -> 140.4 | AK18: =Gas!#REF! -> #REF! | AL18: =Gas!#REF! -> #REF! | AM18: =Gas!#REF! -> #REF! | AN18: =Gas!#REF! -> #REF! | AO18: =Gas!#REF! -> #REF! | AP18: =Gas!#REF! -> #REF! | AQ18: =Gas!#REF! -> #REF! | AR18: =Gas!#REF! -> #REF! | AS18: =Gas!#REF! -> #REF! | AT18: =Elect!BV19 -> 197 | AU18: =Elect!BT19 -> 116 | AX18: 47.795164 | AY18: 24.207493 | AZ18: 8835.4834 | BA18: 12.568255 | BB18: 6.3656221 | BC18: =Elect!BU6 -> 452411 | BD18: =Elect!#REF! -> #REF! | BE18: =Elect!#REF! -> #REF! | BF18: =Elect!#REF! -> #REF! | BG18: =Elect!#REF! -> #REF! | BH18: 1.1024182 | BI18: 0.55835735 | BJ18: 4626.2297 | BK18: 6.5806966 | BL18: 3.3330185 | BM18: =Water!U20 -> 2.6441176 | BN18: =Water!W20 -> #DIV/0! | BO18: =Water!X20 -> 719.2 | BP18: =Water!Y20 -> 10.576471 | BQ18: =Water!Z20 -> #DIV/0!
A19: 15 | B19: 31200 | C19: =Elect!J20 -> 5113 | D19: 0 | E19: =Elect!M20 -> 1573 | F19: 20 | G19: =Elect!O20 -> 1587 | H19: 841 | I19: =Water!C21 -> 127.6 | J19: 0 | K19: =Water!E21 -> 29 | L19: 0 | M19: =Water!#REF! -> #REF! | N19: =Water!#REF! -> #REF! | O19: 947 | P19: =Water!H21 -> 156.6 | Q19: 131 | R19: =Water!O21 -> 0 | S19: 23 | T19: =Water!#REF! -> #REF! | U19: 166 | V19: =Water!#REF! -> #REF! | W19: 787 | X19: =Water!Q21 -> 90.828 | Y19: 0 | Z19: =Water!#REF! -> #REF! | AA19: 0 | AB19: 0 | AC19: 730 | AD19: =Water!#REF! -> #REF! | AE19: =Water!#REF! -> #REF! | AF19: =Water!#REF! -> #REF! | AG19: =Gas!B21 -> 7991038 | AH19: =Gas!C21 -> 1598.48 | AI19: =Gas!#REF! -> #REF! | AJ19: =Gas!J21 -> 257.4 | AK19: =Gas!#REF! -> #REF! | AL19: =Gas!#REF! -> #REF! | AM19: =Gas!#REF! -> #REF! | AN19: =Gas!#REF! -> #REF! | AO19: =Gas!#REF! -> #REF! | AP19: =Gas!#REF! -> #REF! | AQ19: =Gas!#REF! -> #REF! | AR19: =Gas!#REF! -> #REF! | AS19: =Gas!#REF! -> #REF! | AT19: =Elect!BV20 -> 204 | AU19: =Elect!BT20 -> 121 | AX19: 41.6 | AY19: 20.995962 | AZ19: 8299.2754 | BA19: 11.065701 | BB19: 5.5849767 | BC19: =Elect!BU20 -> 455021 | BD19: =Elect!#REF! -> #REF! | BE19: =Elect!#REF! -> #REF! | BF19: =Elect!#REF! -> #REF! | BG19: =Elect!#REF! -> #REF! | BH19: 1.1506667 | BI19: 0.58114478 | BJ19: 4803.283 | BK19: 6.4043773 | BL19: 3.234534 | BM19: =Water!U21 -> 2.5258065 | BN19: =Water!W21 -> #DIV/0! | BO19: =Water!X21 -> 626.4 | BP19: =Water!Y21 -> 10.103226 | BQ19: =Water!Z21 -> #DIV/0!
A20: 16 | B20: 36000 | C20: =Elect!J21 -> 4882 | D20: 0 | E20: =Elect!M21 -> 1498 | F20: 20 | G20: =Elect!O21 -> 1571 | H20: 932 | I20: =Water!C22 -> 150.8 | J20: 0 | K20: =Water!E22 -> 34.8 | L20: 0 | M20: =Water!#REF! -> #REF! | N20: =Water!#REF! -> #REF! | O20: 998 | P20: =Water!H22 -> 185.6 | Q20: 136 | R20: =Water!O22 -> 0 | S20: 22 | T20: =Water!#REF! -> #REF! | U20: 162 | V20: =Water!#REF! -> #REF! | W20: 703 | X20: =Water!Q22 -> 107.648 | Y20: 0 | Z20: =Water!#REF! -> #REF! | AA20: 0 | AB20: 0 | AC20: 600 | AD20: =Water!#REF! -> #REF! | AE20: =Water!#REF! -> #REF! | AF20: =Water!#REF! -> #REF! | AG20: =Gas!B22 -> 7992388 | AH20: =Gas!C22 -> 1431 | AI20: =Gas!#REF! -> #REF! | AJ20: =Gas!J22 -> 222.3 | AK20: =Gas!#REF! -> #REF! | AL20: =Gas!#REF! -> #REF! | AM20: =Gas!#REF! -> #REF! | AN20: =Gas!#REF! -> #REF! | AO20: =Gas!#REF! -> #REF! | AP20: =Gas!#REF! -> #REF! | AQ20: =Gas!#REF! -> #REF! | AR20: =Gas!#REF! -> #REF! | AS20: =Gas!#REF! -> #REF! | AT20: =Elect!BV21 -> 193 | AU20: =Elect!BT21 -> 111 | AX20: 48 | AY20: 24.22611 | AZ20: 9371.6914 | BA20: 12.495589 | BB20: 6.3066564 | BC20: =Elect!BU21 -> 455214 | BD20: =Elect!#REF! -> #REF! | BE20: =Elect!#REF! -> #REF! | BF20: =Elect!#REF! -> #REF! | BG20: =Elect!#REF! -> #REF! | BH20: 1.1626667 | BI20: 0.58720539 | BJ20: 5323.0199 | BK20: 7.0973598 | BL20: 3.5845252 | BM20: =Water!U22 -> 2.6898551 | BN20: =Water!W22 -> #DIV/0! | BO20: =Water!X22 -> 742.4 | BP20: =Water!Y22 -> 10.75942 | BQ20: =Water!Z22 -> #DIV/0!
A21: 17 | B21: 33600 | C21: =Elect!J22 -> 4723 | D21: 0 | E21: =Elect!M22 -> 1704 | F21: 20 | G21: =Elect!O22 -> 1380 | H21: 972 | I21: =Water!C23 -> 110.2 | J21: 0 | K21: =Water!E23 -> 46.4 | L21: 0 | M21: =Water!#REF! -> #REF! | N21: =Water!#REF! -> #REF! | O21: 998 | P21: =Water!H23 -> 156.6 | Q21: 136 | R21: =Water!O23 -> 0 | S21: 38 | T21: =Water!#REF! -> #REF! | U21: 137 | V21: =Water!#REF! -> #REF! | W21: 740 | X21: =Water!Q23 -> 90.828 | Y21: 0 | Z21: =Water!#REF! -> #REF! | AA21: 0 | AB21: 0 | AC21: 690 | AD21: =Water!#REF! -> #REF! | AE21: =Water!#REF! -> #REF! | AF21: =Water!#REF! -> #REF! | AG21: =Gas!B23 -> 7993137 | AH21: =Gas!C23 -> 793.94 | AI21: =Gas!#REF! -> #REF! | AJ21: =Gas!J23 -> 249.6 | AK21: =Gas!#REF! -> #REF! | AL21: =Gas!#REF! -> #REF! | AM21: =Gas!#REF! -> #REF! | AN21: =Gas!#REF! -> #REF! | AO21: =Gas!#REF! -> #REF! | AP21: =Gas!#REF! -> #REF! | AQ21: =Gas!#REF! -> #REF! | AR21: =Gas!#REF! -> #REF! | AS21: =Gas!#REF! -> #REF! | AT21: =Elect!BV22 -> 201 | AU21: =Elect!BT22 -> 118 | AX21: 44.385733 | AY21: 22.207535 | AZ21: 8835.4834 | BA21: 11.671709 | BB21: 5.8397115 | BC21: =Elect!#REF! -> #REF! | BD21: =Elect!#REF! -> #REF! | BE21: =Elect!#REF! -> #REF! | BF21: =Elect!#REF! -> #REF! | BG21: =Elect!#REF! -> #REF! | BH21: 1.1770145 | BI21: 0.58889623 | BJ21: 5551.4757 | BK21: 7.3335213 | BL21: 3.6691842 | BM21: =Water!U23 -> 1.9575 | BN21: =Water!W23 -> #DIV/0! | BO21: =Water!X23 -> 626.4 | BP21: =Water!Y23 -> 7.83 | BQ21: =Water!Z23 -> #DIV/0!
A22: 18 | B22: 33600 | C22: =Elect!J23 -> 4835 | D22: 0 | E22: =Elect!M23 -> 1658 | F22: 20 | G22: =Elect!O23 -> 1453 | H22: 864 | I22: =Water!C24 -> 98.6 | J22: 0 | K22: =Water!E24 -> 17.4 | L22: 0 | M22: =Water!#REF! -> #REF! | N22: =Water!#REF! -> #REF! | O22: 1002 | P22: =Water!H24 -> 116 | Q22: 118 | R22: =Water!O24 -> 0 | S22: 21 | T22: =Water!#REF! -> #REF! | U22: 133 | V22: =Water!#REF! -> #REF! | W22: 769 | X22: =Water!Q24 -> 67.28 | Y22: 0 | Z22: =Water!#REF! -> #REF! | AA22: 0 | AB22: 0 | AC22: 930 | AD22: =Water!#REF! -> #REF! | AE22: =Water!#REF! -> #REF! | AF22: =Water!#REF! -> #REF! | AG22: =Gas!B24 -> 7994198 | AH22: =Gas!C24 -> 1124.66 | AI22: =Gas!#REF! -> #REF! | AJ22: =Gas!J24 -> 237.9 | AK22: =Gas!#REF! -> #REF! | AL22: =Gas!#REF! -> #REF! | AM22: =Gas!#REF! -> #REF! | AN22: =Gas!#REF! -> #REF! | AO22: =Gas!#REF! -> #REF! | AP22: =Gas!#REF! -> #REF! | AQ22: =Gas!#REF! -> #REF! | AR22: =Gas!#REF! -> #REF! | AS22: =Gas!#REF! -> #REF! | AT22: =Elect!BV23 -> 197 | AU22: =Elect!BT23 -> 116 | AX22: 44.680851 | AY22: 22.459893 | AZ22: 8835.4834 | BA22: 11.749313 | BB22: 5.9060718 | BC22: =Elect!BU23 -> 455612 | BD22: =Elect!#REF! -> #REF! | BE22: =Elect!#REF! -> #REF! | BF22: =Elect!#REF! -> #REF! | BG22: =Elect!#REF! -> #REF! | BH22: 1.1236702 | BI22: 0.56483957 | BJ22: 4934.645 | BK22: 6.562028 | BL22: 3.2985595 | BM22: =Water!U24 -> 1.6571429 | BN22: =Water!W24 -> #DIV/0! | BO22: =Water!X24 -> 464 | BP22: =Water!Y24 -> 6.6285714 | BQ22: =Water!Z24 -> #DIV/0!
A23: 19 | B23: 33600 | C23: =Elect!J24 -> 4383 | D23: 0 | E23: =Elect!M24 -> 1411 | F23: 30 | G23: =Elect!O24 -> 1358 | H23: 894 | I23: =Water!C25 -> 63.8 | J23: 0 | K23: =Water!E25 -> 34.8 | L23: 0 | M23: =Water!#REF! -> #REF! | N23: =Water!#REF! -> #REF! | O23: 944 | P23: =Water!H25 -> 98.6 | Q23: 110 | R23: =Water!O25 -> 0 | S23: 14 | T23: =Water!#REF! -> #REF! | U23: 155 | V23: =Water!#REF! -> #REF! | W23: 721 | X23: =Water!Q25 -> 57.188 | Y23: 0 | Z23: =Water!#REF! -> #REF! | AA23: 0 | AB23: 0 | AC23: 660 | AD23: =Water!#REF! -> #REF! | AE23: =Water!#REF! -> #REF! | AF23: =Water!#REF! -> #REF! | AG23: =Gas!B25 -> 7995488 | AH23: =Gas!C25 -> 1367.4 | AI23: =Gas!#REF! -> #REF! | AJ23: =Gas!J25 -> 237.9 | AK23: =Gas!#REF! -> #REF! | AL23: =Gas!#REF! -> #REF! | AM23: =Gas!#REF! -> #REF! | AN23: =Gas!#REF! -> #REF! | AO23: =Gas!#REF! -> #REF! | AP23: =Gas!#REF! -> #REF! | AQ23: =Gas!#REF! -> #REF! | AR23: =Gas!#REF! -> #REF! | AS23: =Gas!#REF! -> #REF! | AT23: =Elect!BV24 -> 195 | AU23: =Elect!BT24 -> 108 | AX23: 44.8 | AY23: 22.44489 | AZ23: 8835.4834 | BA23: 11.780645 | BB23: 5.9021265 | BC23: =Elect!BU24 -> 455807 | BD23: =Elect!#REF! -> #REF! | BE23: =Elect!#REF! -> #REF! | BF23: =Elect!#REF! -> #REF! | BG23: =Elect!#REF! -> #REF! | BH23: 1.1346667 | BI23: 0.56847027 | BJ23: 5105.9869 | BK23: 6.8079825 | BL23: 3.4108129 | BM23: =Water!U25 -> 1.5650794 | BN23: =Water!W25 -> #DIV/0! | BO23: =Water!X25 -> 394.4 | BP23: =Water!Y25 -> 6.2603175 | BQ23: =Water!Z25 -> #DIV/0!
A24: 20 | B24: 33600 | C24: =Elect!J25 -> 4375 | D24: 0 | E24: =Elect!M25 -> 1648 | F24: 20 | G24: =Elect!O25 -> 2797 | H24: 944 | I24: =Water!C26 -> 98.6 | J24: 0 | K24: =Water!E26 -> 29 | L24: 0 | M24: =Water!#REF! -> #REF! | N24: =Water!#REF! -> #REF! | O24: 1000 | P24: =Water!H26 -> 127.6 | Q24: 138 | R24: =Water!O26 -> 0 | S24: 15 | T24: =Water!#REF! -> #REF! | U24: 165 | V24: =Water!#REF! -> #REF! | W24: 778 | X24: =Water!Q26 -> 74.008 | Y24: 0 | Z24: =Water!#REF! -> #REF! | AA24: 0 | AB24: 0 | AC24: 560 | AD24: =Water!#REF! -> #REF! | AE24: =Water!#REF! -> #REF! | AF24: =Water!#REF! -> #REF! | AG24: =Gas!B26 -> 7996255 | AH24: =Gas!C26 -> 813.02 | AI24: =Gas!#REF! -> #REF! | AJ24: =Gas!J26 -> 113.1 | AK24: =Gas!#REF! -> #REF! | AL24: =Gas!#REF! -> #REF! | AM24: =Gas!#REF! -> #REF! | AN24: =Gas!#REF! -> #REF! | AO24: =Gas!#REF! -> #REF! | AP24: =Gas!#REF! -> #REF! | AQ24: =Gas!#REF! -> #REF! | AR24: =Gas!#REF! -> #REF! | AS24: =Gas!#REF! -> #REF! | AT24: =Elect!BV25 -> 190 | AU24: =Elect!BT25 -> 111 | AX24: 42.857143 | AY24: 21.649485 | AZ24: 8835.4834 | BA24: 11.269749 | BB24: 5.6929661 | BC24: =Elect!BU25 -> 455997 | BD24: =Elect!#REF! -> #REF! | BE24: =Elect!#REF! -> #REF! | BF24: =Elect!#REF! -> #REF! | BG24: =Elect!#REF! -> #REF! | BH24: 1.1683673 | BI24: 0.59020619 | BJ24: 5391.5566 | BK24: 6.8769855 | BL24: 3.4739411 | BM24: =Water!U26 -> 2.2785714 | BN24: =Water!W26 -> #DIV/0! | BO24: =Water!X26 -> 510.4 | BP24: =Water!Y26 -> 9.1142857 | BQ24: =Water!Z26 -> #DIV/0!
A25: 21 | B25: 36000 | C25: =Elect!J26 -> 5866 | D25: 0 | E25: =Elect!M26 -> 1714 | F25: 20 | G25: =Elect!O26 -> 1858 | H25: 916 | I25: =Water!C27 -> 92.8 | J25: 0 | K25: =Water!E27 -> 5.8 | L25: 0 | M25: =Water!#REF! -> #REF! | N25: =Water!#REF! -> #REF! | O25: 998 | P25: =Water!H27 -> 98.6 | Q25: 186 | R25: =Water!O27 -> 0 | S25: 43 | T25: =Water!#REF! -> #REF! | U25: 176 | V25: =Water!#REF! -> #REF! | W25: 773 | X25: =Water!Q27 -> 57.188 | Y25: 0 | Z25: =Water!#REF! -> #REF! | AA25: 0 | AB25: 0 | AC25: 950 | AD25: =Water!#REF! -> #REF! | AE25: =Water!#REF! -> #REF! | AF25: =Water!#REF! -> #REF! | AG25: =Gas!B27 -> 7997301 | AH25: =Gas!C27 -> 1108.76 | AI25: =Gas!#REF! -> #REF! | AJ25: =Gas!J27 -> 522.6 | AK25: =Gas!#REF! -> #REF! | AL25: =Gas!#REF! -> #REF! | AM25: =Gas!#REF! -> #REF! | AN25: =Gas!#REF! -> #REF! | AO25: =Gas!#REF! -> #REF! | AP25: =Gas!#REF! -> #REF! | AQ25: =Gas!#REF! -> #REF! | AR25: =Gas!#REF! -> #REF! | AS25: =Gas!#REF! -> #REF! | AT25: =Elect!BV26 -> 212 | AU25: =Elect!BT26 -> 132 | AX25: 43.956044 | AY25: 22.222222 | AZ25: 9371.6914 | BA25: 11.442847 | BB25: 5.7849947 | BC25: =Elect!BU26 -> 456209 | BD25: =Elect!#REF! -> #REF! | BE25: =Elect!#REF! -> #REF! | BF25: =Elect!#REF! -> #REF! | BG25: =Elect!#REF! -> #REF! | BH25: 1.0586081 | BI25: 0.53518519 | BJ25: 5231.6376 | BK25: 6.3878358 | BL25: 3.2294059 | BM25: =Water!U27 -> 1.1333333 | BN25: =Water!W27 -> #DIV/0! | BO25: =Water!X27 -> 394.4 | BP25: =Water!Y27 -> 4.5333333 | BQ25: =Water!Z27 -> #DIV/0!
A26: 22 | B26: 33600 | C26: =Elect!J27 -> 6319 | D26: 0 | E26: =Elect!M27 -> 1944 | F26: 20 | G26: =Elect!O27 -> 1256 | H26: 931 | I26: =Water!C28 -> 110.2 | J26: 0 | K26: =Water!E28 -> 11.6 | L26: 0 | M26: =Water!#REF! -> #REF! | N26: =Water!#REF! -> #REF! | O26: 969 | P26: =Water!H28 -> 121.8 | Q26: 151 | R26: =Water!O28 -> 0 | S26: 29 | T26: =Water!#REF! -> #REF! | U26: 157 | V26: =Water!#REF! -> #REF! | W26: 697 | X26: =Water!Q28 -> 70.644 | Y26: 0 | Z26: =Water!#REF! -> #REF! | AA26: 0 | AB26: 0 | AC26: 700 | AD26: =Water!#REF! -> #REF! | AE26: =Water!#REF! -> #REF! | AF26: =Water!#REF! -> #REF! | AG26: =Gas!B28 -> 7998087 | AH26: =Gas!C28 -> 833.16 | AI26: =Gas!#REF! -> #REF! | AJ26: =Gas!J28 -> 101.4 | AK26: =Gas!#REF! -> #REF! | AL26: =Gas!#REF! -> #REF! | AM26: =Gas!#REF! -> #REF! | AN26: =Gas!#REF! -> #REF! | AO26: =Gas!#REF! -> #REF! | AP26: =Gas!#REF! -> #REF! | AQ26: =Gas!#REF! -> #REF! | AR26: =Gas!#REF! -> #REF! | AS26: =Gas!#REF! -> #REF! | AT26: =Elect!BV27 -> 217 | AU26: =Elect!BT27 -> 136 | AX26: 39.952438 | AY26: 20.253165 | AZ26: 8835.4834 | BA26: 10.505926 | BB26: 5.3257887 | BC26: =Elect!BU27 -> 456426 | BD26: =Elect!#REF! -> #REF! | BE26: =Elect!#REF! -> #REF! | BF26: =Elect!#REF! -> #REF! | BG26: =Elect!#REF! -> #REF! | BH26: 1.0903686 | BI26: 0.55274262 | BJ26: 5317.3085 | BK26: 6.3226022 | BL26: 3.2051287 | BM26: =Water!U28 -> 1.3840909 | BN26: =Water!W28 -> #DIV/0! | BO26: =Water!X28 -> 487.2 | BP26: =Water!Y28 -> 5.5363636 | BQ26: =Water!Z28 -> #DIV/0!
A27: 23 | B27: 36000 | C27: =Elect!J28 -> 5557 | D27: 0 | E27: =Elect!M28 -> 1936 | F27: 30 | G27: =Elect!O28 -> 1773 | H27: 1009 | I27: =Water!C29 -> 156.6 | J27: 0 | K27: =Water!E29 -> 5.8 | L27: 0 | M27: =Water!#REF! -> #REF! | N27: =Water!#REF! -> #REF! | O27: 902 | P27: =Water!H29 -> 168.2 | Q27: 131 | R27: =Water!O29 -> 0 | S27: 6 | T27: =Water!#REF! -> #REF! | U27: 167 | V27: =Water!#REF! -> #REF! | W27: 748 | X27: =Water!Q29 -> 97.556 | Y27: 0 | Z27: =Water!#REF! -> #REF! | AA27: 0 | AB27: 0 | AC27: 690 | AD27: =Water!#REF! -> #REF! | AE27: =Water!#REF! -> #REF! | AF27: =Water!#REF! -> #REF! | AG27: =Gas!B29 -> 7998845 | AH27: =Gas!C29 -> 803.48 | AI27: =Gas!#REF! -> #REF! | AJ27: =Gas!J29 -> 409.5 | AK27: =Gas!#REF! -> #REF! | AL27: =Gas!#REF! -> #REF! | AM27: =Gas!#REF! -> #REF! | AN27: =Gas!#REF! -> #REF! | AO27: =Gas!#REF! -> #REF! | AP27: =Gas!#REF! -> #REF! | AQ27: =Gas!#REF! -> #REF! | AR27: =Gas!#REF! -> #REF! | AS27: =Gas!#REF! -> #REF! | AT27: =Elect!BV28 -> 190 | AU27: =Elect!BT28 -> 120 | AX27: 42.755344 | AY27: 21.543986 | AZ27: 9371.6914 | BA27: 11.130275 | BB27: 5.6084329 | BC27: =Elect!BU28 -> 456616 | BD27: =Elect!#REF! -> #REF! | BE27: =Elect!#REF! -> #REF! | BF27: =Elect!#REF! -> #REF! | BG27: =Elect!#REF! -> #REF! | BH27: 1.0712589 | BI27: 0.53979653 | BJ27: 5762.7973 | BK27: 6.8441773 | BL27: 3.4487117 | BM27: =Water!U29 -> 2.026506 | BN27: =Water!W29 -> #DIV/0! | BO27: =Water!X29 -> 672.8 | BP27: =Water!Y29 -> 8.1060241 | BQ27: =Water!Z29 -> #DIV/0!
A28: 24 | B28: 33600 | C28: =Elect!J29 -> 5440 | D28: 0 | E28: =Elect!M29 -> 1644 | F28: 20 | G28: =Elect!O29 -> 1766 | H28: 891 | I28: =Water!C30 -> 185.6 | J28: 0 | K28: =Water!E30 -> 5.8 | L28: 0 | M28: =Water!#REF! -> #REF! | N28: =Water!#REF! -> #REF! | O28: 818 | P28: =Water!H30 -> 197.2 | Q28: 221 | R28: =Water!O30 -> 0 | S28: 93 | T28: =Water!#REF! -> #REF! | U28: 191 | V28: =Water!#REF! -> #REF! | W28: 827 | X28: =Water!Q30 -> 114.376 | Y28: 0 | Z28: =Water!#REF! -> #REF! | AA28: 0 | AB28: 0 | AC28: 470 | AD28: =Water!#REF! -> #REF! | AE28: =Water!#REF! -> #REF! | AF28: =Water!#REF! -> #REF! | AG28: =Gas!B30 -> 7999998 | AH28: =Gas!C30 -> 1222.18 | AI28: =Gas!#REF! -> #REF! | AJ28: =Gas!J30 -> 269.1 | AK28: =Gas!#REF! -> #REF! | AL28: =Gas!#REF! -> #REF! | AM28: =Gas!#REF! -> #REF! | AN28: =Gas!#REF! -> #REF! | AO28: =Gas!#REF! -> #REF! | AP28: =Gas!#REF! -> #REF! | AQ28: =Gas!#REF! -> #REF! | AR28: =Gas!#REF! -> #REF! | AS28: =Gas!#REF! -> #REF! | AT28: =Elect!BV29 -> 226 | AU28: =Elect!BT29 -> 126 | AX28: 39.904988 | AY28: 20.289855 | AZ28: 8835.4834 | BA28: 10.493448 | BB28: 5.3354369 | BC28: =Elect!BU29 -> 456842 | BD28: =Elect!#REF! -> #REF! | BE28: =Elect!#REF! -> #REF! | BF28: =Elect!#REF! -> #REF! | BG28: =Elect!#REF! -> #REF! | BH28: 1.1104513 | BI28: 0.56461353 | BJ28: 5088.8527 | BK28: 6.043768 | BL28: 3.0729787 | BM28: =Water!U30 -> 2.2409091 | BN28: =Water!W30 -> #DIV/0! | BO28: =Water!X30 -> 788.8 | BP28: =Water!Y30 -> 8.9636364 | BQ28: =Water!Z30 -> #DIV/0!
A29: 25 | B29: 33600 | C29: =Elect!J30 -> 5058 | D29: 0 | E29: =Elect!M30 -> 1630 | F29: 20 | G29: =Elect!O30 -> 1527 | H29: 1008 | I29: =Water!C31 -> 127.6 | J29: 0 | K29: =Water!E31 -> 5.8 | L29: 0 | M29: =Water!#REF! -> #REF! | N29: =Water!#REF! -> #REF! | O29: 1290 | P29: =Water!H31 -> 139.2 | Q29: 34 | R29: =Water!O31 -> 0 | S29: 34 | T29: =Water!#REF! -> #REF! | U29: 55 | V29: =Water!#REF! -> #REF! | W29: 681 | X29: =Water!Q31 -> 80.736 | Y29: 0 | Z29: =Water!#REF! -> #REF! | AA29: 0 | AB29: 0 | AC29: 1170 | AD29: =Water!#REF! -> #REF! | AE29: =Water!#REF! -> #REF! | AF29: =Water!#REF! -> #REF! | AG29: =Gas!B31 -> 8001532 | AH29: =Gas!C31 -> 1626.04 | AI29: =Gas!#REF! -> #REF! | AJ29: =Gas!J31 -> 269.1 | AK29: =Gas!#REF! -> #REF! | AL29: =Gas!#REF! -> #REF! | AM29: =Gas!#REF! -> #REF! | AN29: =Gas!#REF! -> #REF! | AO29: =Gas!#REF! -> #REF! | AP29: =Gas!#REF! -> #REF! | AQ29: =Gas!#REF! -> #REF! | AR29: =Gas!#REF! -> #REF! | AS29: =Gas!#REF! -> #REF! | AT29: =Elect!BV30 -> 176 | AU29: =Elect!BT30 -> 85 | AX29: 39.763314 | AY29: 20.20445 | AZ29: 8835.4834 | BA29: 10.456193 | BB29: 5.3129786 | BC29: =Elect!BU30 -> 457018 | BD29: =Elect!#REF! -> #REF! | BE29: =Elect!#REF! -> #REF! | BF29: =Elect!#REF! -> #REF! | BG29: =Elect!#REF! -> #REF! | BH29: 1.0059172 | BI29: 0.51112447 | BJ29: 5757.0859 | BK29: 6.8131194 | BL29: 3.4618676 | BM29: =Water!U31 -> 1.8077922 | BN29: =Water!W31 -> #DIV/0! | BO29: =Water!X31 -> 556.8 | BP29: =Water!Y31 -> 7.2311688 | BQ29: =Water!Z31 -> #DIV/0!
A30: 26 | B30: 31200 | C30: =Elect!J31 -> 2921 | D30: 0 | E30: =Elect!M31 -> 1594 | F30: 20 | G30: =Elect!O31 -> 1395 | H30: 760 | I30: =Water!C32 -> 139.2 | J30: 0 | K30: =Water!E32 -> 5.8 | L30: 0 | M30: =Water!#REF! -> #REF! | N30: =Water!#REF! -> #REF! | O30: 1004 | P30: =Water!H32 -> 150.22 | Q30: 131 | R30: =Water!O32 -> 0 | S30: 33 | T30: =Water!#REF! -> #REF! | U30: 145 | V30: =Water!#REF! -> #REF! | W30: 916 | X30: =Water!Q32 -> 87.1276 | Y30: 0 | Z30: =Water!#REF! -> #REF! | AA30: 0 | AB30: 0 | AC30: 810 | AD30: =Water!#REF! -> #REF! | AE30: =Water!#REF! -> #REF! | AF30: =Water!#REF! -> #REF! | AG30: =Gas!B32 -> 8002524 | AH30: =Gas!C32 -> 1051.52 | AI30: =Gas!#REF! -> #REF! | AJ30: =Gas!J32 -> 366.6 | AK30: =Gas!#REF! -> #REF! | AL30: =Gas!#REF! -> #REF! | AM30: =Gas!#REF! -> #REF! | AN30: =Gas!#REF! -> #REF! | AO30: =Gas!#REF! -> #REF! | AP30: =Gas!#REF! -> #REF! | AQ30: =Gas!#REF! -> #REF! | AR30: =Gas!#REF! -> #REF! | AS30: =Gas!#REF! -> #REF! | AT30: =Elect!BV31 -> 152 | AU30: =Elect!BT31 -> 84 | AX30: 37.275986 | AY30: 18.989653 | AZ30: 8299.2754 | BA30: 9.9155023 | BB30: 5.0512936 | BC30: =Elect!BU31 -> 457170 | BD30: =Elect!#REF! -> #REF! | BE30: =Elect!#REF! -> #REF! | BF30: =Elect!#REF! -> #REF! | BG30: =Elect!#REF! -> #REF! | BH30: 1.1063321 | BI30: 0.56360316 | BJ30: 4340.66 | BK30: 5.1859737 | BL30: 2.6419111 | BM30: =Water!U32 -> 2.59 | BN30: =Water!W32 -> #DIV/0! | BO30: =Water!X32 -> 600.88 | BP30: =Water!Y32 -> 10.36 | BQ30: =Water!Z32 -> #DIV/0!
A31: 27 | B31: 36000 | C31: =Elect!J32 -> 4950 | D31: 0 | E31: =Elect!M32 -> 1694 | F31: 30 | G31: =Elect!O32 -> 1641 | H31: 1010 | I31: =Water!C33 -> 127.6 | J31: 0 | K31: =Water!E33 -> 5.8 | L31: 0 | M31: =Water!#REF! -> #REF! | N31: =Water!#REF! -> #REF! | O31: 1014 | P31: =Water!H33 -> 139.2 | Q31: 151 | R31: =Water!O33 -> 0 | S31: 30 | T31: =Water!#REF! -> #REF! | U31: 139 | V31: =Water!#REF! -> #REF! | W31: 761 | X31: =Water!Q33 -> 80.736 | Y31: 0 | Z31: =Water!#REF! -> #REF! | AA31: 0 | AB31: 0 | AC31: 930 | AD31: =Water!#REF! -> #REF! | AE31: =Water!#REF! -> #REF! | AF31: =Water!#REF! -> #REF! | AG31: =Gas!B33 -> 8003393 | AH31: =Gas!C33 -> 921.14 | AI31: =Gas!#REF! -> #REF! | AJ31: =Gas!J33 -> 159.9 | AK31: =Gas!#REF! -> #REF! | AL31: =Gas!#REF! -> #REF! | AM31: =Gas!#REF! -> #REF! | AN31: =Gas!#REF! -> #REF! | AO31: =Gas!#REF! -> #REF! | AP31: =Gas!#REF! -> #REF! | AQ31: =Gas!#REF! -> #REF! | AR31: =Gas!#REF! -> #REF! | AS31: =Gas!#REF! -> #REF! | AT31: =Elect!BV32 -> 194 | AU31: =Elect!BT32 -> 112 | AX31: 44.063647 | AY31: 22.346369 | AZ31: 9371.6914 | BA31: 11.470859 | BB31: 5.8173131 | BC31: =Elect!BU32 -> 457364 | BD31: =Elect!#REF! -> #REF! | BE31: =Elect!#REF! -> #REF! | BF31: =Elect!#REF! -> #REF! | BG31: =Elect!#REF! -> #REF! | BH31: 1.1640147 | BI31: 0.59031657 | BJ31: 5768.5087 | BK31: 7.0605981 | BL31: 3.5807006 | BM31: =Water!U33 -> 2.359322 | BN31: =Water!W33 -> #DIV/0! | BO31: =Water!X33 -> 556.8 | BP31: =Water!Y33 -> 9.4372881 | BQ31: =Water!Z33 -> #DIV/0!
A32: 28 | B32: 33600 | C32: =Elect!J33 -> 4950 | D32: 0 | E32: =Elect!M33 -> 1693 | F32: 20 | G32: =Elect!O33 -> 1641 | H32: 1008 | I32: =Water!C34 -> 116 | J32: 0 | K32: =Water!E34 -> 5.8 | L32: 1 | M32: =Water!#REF! -> #REF! | N32: =Water!#REF! -> #REF! | O32: 1013 | P32: =Water!H34 -> 127.02 | Q32: 142 | R32: =Water!O34 -> 0 | S32: 13 | T32: =Water!#REF! -> #REF! | U32: 155 | V32: =Water!#REF! -> #REF! | W32: 825 | X32: =Water!Q34 -> 73.6716 | Y32: 1 | Z32: =Water!#REF! -> #REF! | AA32: 0 | AB32: 0 | AC32: 650 | AD32: =Water!#REF! -> #REF! | AE32: =Water!#REF! -> #REF! | AF32: =Water!#REF! -> #REF! | AG32: =Gas!B34 -> 8004424 | AH32: =Gas!C34 -> 1092.86 | AI32: =Gas!#REF! -> #REF! | AJ32: =Gas!J34 -> 269.1 | AK32: =Gas!#REF! -> #REF! | AL32: =Gas!#REF! -> #REF! | AM32: =Gas!#REF! -> #REF! | AN32: =Gas!#REF! -> #REF! | AO32: =Gas!#REF! -> #REF! | AP32: =Gas!#REF! -> #REF! | AQ32: =Gas!#REF! -> #REF! | AR32: =Gas!#REF! -> #REF! | AS32: =Gas!#REF! -> #REF! | AT32: =Elect!BV33 -> 194 | AU32: =Elect!BT33 -> 112 | AX32: 45.34413 | AY32: 22.687373 | AZ32: 8835.4834 | BA32: 11.923729 | BB32: 5.9658902 | BC32: =Elect!BU33 -> 457558 | BD32: =Elect!#REF! -> #REF! | BE32: =Elect!#REF! -> #REF! | BF32: =Elect!#REF! -> #REF! | BG32: =Elect!#REF! -> #REF! | BH32: 1.2294197 | BI32: 0.61512492 | BJ32: 5757.0859 | BK32: 7.7693467 | BL32: 3.8872963 | BM32: =Water!U34 -> 2.19 | BN32: =Water!W34 -> #DIV/0! | BO32: =Water!X34 -> 508.08 | BP32: =Water!Y34 -> 8.76 | BQ32: =Water!Z34 -> #DIV/0!
A33: MTD | B33: 931200 | C33: =Elect!J34 -> 0 | D33: 0 | E33: =Elect!M34 -> 0 | F33: 600 | G33: =Elect!O34 -> 0 | H33: 24543 | I33: =Water!C38 -> 3474.2 | J33: 0 | K33: =Water!E39 -> 50.266667 | L33: 3 | M33: =Water!#REF! -> #REF! | N33: =Water!#REF! -> #REF! | O33: 1013 | P33: =Water!H38 -> 5015.84 | Q33: 109 | R33: =Water!O38 -> 0 | S33: 15 | T33: =Water!#REF! -> #REF! | U33: 147 | V33: =Water!#REF! -> #REF! | W33: 730 | X33: =Water!Q38 -> 2909.1872 | Y33: 3 | Z33: =Water!#REF! -> #REF! | AA33: 0 | AB33: 0 | AC33: 0 | AD33: =Water!#REF! -> #REF! | AE33: =Water!#REF! -> #REF! | AF33: =Water!#REF! -> #REF! | AG33: =Gas!B38 -> 0 | AH33: =Gas!C38 -> 27993.54 | AI33: =Gas!#REF! -> #REF! | AJ33: =Gas!J38 -> 7406.1 | AK33: =Gas!#REF! -> #REF! | AL33: =Gas!#REF! -> #REF! | AM33: =Gas!#REF! -> #REF! | AN33: =Gas!#REF! -> #REF! | AO33: =Gas!#REF! -> #REF! | AP33: =Gas!#REF! -> #REF! | AQ33: =Gas!#REF! -> #REF! | AR33: =Gas!#REF! -> #REF! | AS33: =Gas!#REF! -> #REF! | AT33: =Elect!BV34 -> 0 | AU33: =Elect!BT34 -> 0 | AX33: 45.411099 | AY33: 22.844806 | AZ33: 245248.7 | BA33: 11.959851 | BB33: 6.0166013 | BC33: =Elect!BU34 -> 457558 | BD33: =Elect!#REF! -> #REF! | BE33: =Elect!#REF! -> #REF! | BF33: =Elect!#REF! -> #REF! | BG33: =Elect!#REF! -> #REF! | BH33: 1.1514679 | BI33: 0.57929342 | BJ33: 140121.3 | BK33: 6.8331854 | BL33: 3.4377159 | BM33: =Water!U38 -> 2.8242342 | BN33: =Water!W38 -> #DIV/0! | BO33: =Water!X38 -> 20063.36 | BP33: =Water!Y38 -> 11.296937 | BQ33: =Water!Z38 -> #DIV/0!
A34: AVER. Act | B34: 33257.143 | C34: =Elect!J35 -> 0 | D34: 0 | E34: =Elect!M35 -> 0 | F34: 21.428571 | G34: =Elect!O35 -> 0 | H34: 876.53571 | I34: =Water!C39 -> 115.80667 | J34: 0 | K34: =Water!E40 -> 0 | L34: 4 | M34: =Water!#REF! -> #REF! | N34: =Water!#REF! -> #REF! | O34: 1014 | P34: =Water!H39 -> 167.19467 | Q34: 138 | R34: =Water!O39 -> 0 | S34: 24 | T34: =Water!#REF! -> #REF! | U34: 145 | V34: =Water!#REF! -> #REF! | W34: 877 | X34: =Water!Q39 -> 96.972907 | Y34: 4 | Z34: =Water!#REF! -> #REF! | AA34: 0 | AB34: 0 | AC34: 0 | AD34: =Water!#REF! -> #REF! | AE34: =Water!#REF! -> #REF! | AF34: =Water!#REF! -> #REF! | AG34: =Gas!B39 -> 0 | AH34: =Gas!C39 -> 933.118 | AI34: =Gas!#REF! -> #REF! | AJ34: =Gas!J39 -> 246.87 | AK34: =Gas!#REF! -> #REF! | AL34: =Gas!#REF! -> #REF! | AM34: =Gas!#REF! -> #REF! | AN34: =Gas!#REF! -> #REF! | AO34: =Gas!#REF! -> #REF! | AP34: =Gas!#REF! -> #REF! | AQ34: =Gas!#REF! -> #REF! | AR34: =Gas!#REF! -> #REF! | AS34: =Gas!#REF! -> #REF! | AT34: =Elect!BV35 -> 0 | AU34: =Elect!BT35 -> 0 | AX34: 45.411099 | AY34: 22.844806 | AZ34: 8758.8823 | BA34: 11.959851 | BB34: 6.0166013 | BC34: =Elect!BU35 -> 457558 | BD34: =Elect!#REF! -> #REF! | BE34: =Elect!#REF! -> #REF! | BF34: =Elect!#REF! -> #REF! | BG34: =Elect!#REF! -> #REF! | BH34: 1.1761372 | BI34: 0.60007377 | BJ34: 5004.3322 | BK34: 6.8331854 | BL34: 3.4377159 | BM34: =Water!U39 -> 2.8242342 | BN34: =Water!W39 -> #DIV/0! | BO34: =Water!X39 -> 668.77867 | BP34: =Water!Y39 -> 11.296937 | BQ34: =Water!Z39 -> #DIV/0!
A35: TOTAL Budget | B35: 1040026 | C35: =Elect!J5 -> 0 | D35: 0 | E35: =Elect!M5 -> 0 | F35: 0 | G35: =Elect!O5 -> 0 | H35: 0 | I35: =Water!C40 -> 0 | J35: 0 | K35: =Water!E41 -> 0 | L35: 5 | M35: =Water!#REF! -> #REF! | N35: =Water!#REF! -> #REF! | O35: 1010 | P35: =Water!H40 -> 0 | Q35: 148 | R35: =Water!O40 -> 0 | S35: 22 | T35: =Water!#REF! -> #REF! | U35: 151 | V35: =Water!#REF! -> #REF! | W35: 833 | X35: =Water!Q40 -> 0 | Y35: 5 | Z35: =Water!#REF! -> #REF! | AA35: 0 | AB35: 0 | AC35: 0 | AD35: =Water!#REF! -> #REF! | AE35: =Water!#REF! -> #REF! | AF35: =Water!#REF! -> #REF! | AG35: =Gas!#REF! -> #REF! | AH35: =Gas!#REF! -> #REF! | AI35: =Gas!#REF! -> #REF! | AJ35: =Gas!#REF! -> #REF! | AK35: =Gas!#REF! -> #REF! | AL35: =Gas!#REF! -> #REF! | AM35: =Gas!#REF! -> #REF! | AN35: =Gas!#REF! -> #REF! | ... AS35: =Gas!#REF! -> #REF! | AT35: =Elect!BV5 -> 0 | AU35: =Elect!BT5 -> 0 | AX35: 45.679286 | AY35: 23.305904 | AZ35: 264708.4 | BA35: 11.626335 | BB35: 5.9318409 | BC35: =Elect!BU5 -> 452214 | BD35: =Elect!#REF! -> #REF! | BE35: =Elect!#REF! -> #REF! | BF35: =Elect!#REF! -> #REF! | BG35: =Elect!#REF! -> #REF! | BH35: 1.1761372 | BI35: 0.60007377 | BJ35: 150494 | BK35: 6.6098911 | BL35: 3.3724146 | BM35: =Water!U40 -> #REF! | BN35: =Water!W40 -> #REF! | BO35: =Water!X40 -> 0 | BP35: =Water!Y40 -> 0 | BQ35: =Water!Z40 -> 0
A36: Budget MTD | B36: 1040026 | C36: =Elect!#REF! -> #REF! | D36: 0 | E36: =Elect!#REF! -> #REF! | F36: 0 | G36: =Elect!#REF! -> #REF! | H36: 0 | I36: =Water!C41 -> 0 | J36: 0 | K36: =Water!E42 -> 0 | L36: 6 | M36: =Water!#REF! -> #REF! | N36: =Water!#REF! -> #REF! | O36: 30039 | P36: =Water!H41 -> 0 | Q36: 129.54839 | R36: =Water!O41 -> 0 | S36: 719 | T36: =Water!#REF! -> #REF! | U36: 4609 | V36: =Water!#REF! -> #REF! | W36: 23430 | X36: =Water!Q41 -> 0 | Y36: 6 | Z36: =Water!#REF! -> #REF! | AA36: 0 | AB36: 0 | AC36: 0 | AD36: =Water!#REF! -> #REF! | AE36: =Water!#REF! -> #REF! | AF36: =Water!#REF! -> #REF! | AG36: =Gas!#REF! -> #REF! | AH36: =Gas!#REF! -> #REF! | AI36: =Gas!#REF! -> #REF! | AJ36: =Gas!#REF! -> #REF! | AK36: =Gas!#REF! -> #REF! | AL36: =Gas!#REF! -> #REF! | AM36: =Gas!#REF! -> #REF! | AN36: =Gas!#REF! -> #REF! | ... AS36: =Gas!#REF! -> #REF! | AT36: =Elect!#REF! -> #REF! | AU36: =Elect!#REF! -> #REF! | AX36: 45.679286 | AY36: 23.305904 | AZ36: 264708.4 | BA36: 11.626335 | BB36: 5.9318409 | BC36: =Elect!#REF! -> #REF! | BD36: =Elect!#REF! -> #REF! | BE36: =Elect!#REF! -> #REF! | BF36: =Elect!#REF! -> #REF! | BG36: =Elect!#REF! -> #REF! | BH36: 0 | BI36: 0 | BJ36: 135930.06 | BK36: 6.6098911 | BL36: 3.3724146 | BM36: =Water!U41 -> #REF! | BN36: =Water!W41 -> #REF! | BO36: =Water!X41 -> #REF! | BP36: =Water!Y41 -> #REF! | BQ36: =Water!Z41 -> #REF!
A37: AVER. Bud | B37: 37143.785 | C37: =Elect!#REF! -> #REF! | D37: 0 | E37: =Elect!#REF! -> #REF! | F37: 0 | G37: =Elect!#REF! -> #REF! | H37: 0 | I37: =Water!C42 -> 0 | J37: 0 | K37: =Water!E43 -> 0 | L37: 7 | M37: =Water!#REF! -> #REF! | N37: =Water!#REF! -> #REF! | O37: 969 | P37: =Water!H42 -> 0 | Q37: 0 | R37: =Water!O42 -> 0 | S37: 23.193548 | T37: =Water!#REF! -> #REF! | U37: 148.67742 | V37: =Water!#REF! -> #REF! | W37: 755.80645 | X37: =Water!Q42 -> 0 | Y37: 7 | Z37: =Water!#REF! -> #REF! | AA37: 0 | AB37: 0 | AC37: 0 | AD37: =Water!#REF! -> #REF! | AE37: =Water!#REF! -> #REF! | AF37: =Water!#REF! -> #REF! | AG37: =Gas!#REF! -> #REF! | AH37: =Gas!#REF! -> #REF! | AI37: =Gas!#REF! -> #REF! | AJ37: =Gas!#REF! -> #REF! | AK37: =Gas!#REF! -> #REF! | AL37: =Gas!#REF! -> #REF! | AM37: =Gas!#REF! -> #REF! | AN37: =Gas!#REF! -> #REF! | ... AS37: =Gas!#REF! -> #REF! | AT37: =Elect!#REF! -> #REF! | AU37: =Elect!#REF! -> #REF! | AX37: 0 | AY37: 0 | AZ37: 9453.8714 | BA37: 0 | BB37: 0 | BC37: =Elect!#REF! -> #REF! | BD37: =Elect!#REF! -> #REF! | BE37: =Elect!#REF! -> #REF! | BF37: =Elect!#REF! -> #REF! | BG37: =Elect!#REF! -> #REF! | BH37: 0 | BI37: 0 | BJ37: 0 | BK37: 0 | BL37: 0 | BM37: =Water!U42 -> 0 | BN37: =Water!W42 -> 0 | BO37: =Water!X42 -> 0 | BP37: =Water!Y42 -> 0 | BQ37: =Water!Z42 -> 0
A38: Total RFC | B38: 784008.53 | C38: =Elect!#REF! -> #REF! | D38: 0 | E38: =Elect!#REF! -> #REF! | F38: 0 | G38: =Elect!#REF! -> #REF! | H38: 0 | I38: =Water!C43 -> 0 | J38: 0 | K38: =Water!E44 -> 0 | L38: 8 | M38: =Water!#REF! -> #REF! | N38: =Water!#REF! -> #REF! | O38: 0 | P38: =Water!H43 -> 0 | Q38: 0 | R38: =Water!O43 -> 0 | S38: 0 | T38: =Water!#REF! -> #REF! | U38: 0 | V38: =Water!#REF! -> #REF! | W38: 0 | X38: =Water!Q43 -> 0 | Y38: 8 | Z38: =Water!#REF! -> #REF! | AA38: 0 | AB38: 0 | AC38: 0 | AD38: =Water!#REF! -> #REF! | AE38: =Water!#REF! -> #REF! | AF38: =Water!#REF! -> #REF! | AG38: =Gas!#REF! -> #REF! | AH38: =Gas!#REF! -> #REF! | AI38: =Gas!#REF! -> #REF! | AJ38: =Gas!#REF! -> #REF! | AK38: =Gas!#REF! -> #REF! | AL38: =Gas!#REF! -> #REF! | AM38: =Gas!#REF! -> #REF! | AN38: =Gas!#REF! -> #REF! | ... AS38: =Gas!#REF! -> #REF! | AT38: =Elect!#REF! -> #REF! | AU38: =Elect!#REF! -> #REF! | AX38: 38.173558 | AY38: 19.219193 | AZ38: 208225.85 | BA38: 10.138565 | BB38: 5.1044505 | BC38: =Elect!#REF! -> #REF! | BD38: =Elect!#REF! -> #REF! | BE38: =Elect!#REF! -> #REF! | BF38: =Elect!#REF! -> #REF! | BG38: =Elect!#REF! -> #REF! | BH38: 0 | BI38: 0 | BJ38: 127385.62 | BK38: 6.2024355 | BL38: 3.1227323 | BM38: =Water!U43 -> 0 | BN38: =Water!W43 -> 0 | BO38: =Water!X43 -> 0 | BP38: =Water!Y43 -> 0 | BQ38: =Water!Z43 -> 0
A39: RFC MTD | B39: 784008.53 | C39: =Elect!#REF! -> #REF! | D39: 0 | E39: =Elect!#REF! -> #REF! | F39: 0 | G39: =Elect!#REF! -> #REF! | H39: 0 | I39: =Water!C44 -> 0 | J39: 0 | K39: =Water!E45 -> 0 | L39: 9 | M39: =Water!#REF! -> #REF! | N39: =Water!#REF! -> #REF! | O39: 0 | P39: =Water!H44 -> 0 | Q39: 0 | R39: =Water!O44 -> 0 | S39: 0 | T39: =Water!#REF! -> #REF! | U39: 0 | V39: =Water!#REF! -> #REF! | W39: 0 | X39: =Water!Q44 -> 0 | Y39: 9 | Z39: =Water!#REF! -> #REF! | AA39: 0 | AB39: 0 | AC39: 0 | AD39: =Water!#REF! -> #REF! | AE39: =Water!#REF! -> #REF! | AF39: =Water!#REF! -> #REF! | AG39: =Gas!#REF! -> #REF! | AH39: =Gas!#REF! -> #REF! | AI39: =Gas!#REF! -> #REF! | AJ39: =Gas!#REF! -> #REF! | AK39: =Gas!#REF! -> #REF! | AL39: =Gas!#REF! -> #REF! | AM39: =Gas!#REF! -> #REF! | AN39: =Gas!#REF! -> #REF! | ... AS39: =Gas!#REF! -> #REF! | AT39: =Elect!#REF! -> #REF! | AU39: =Elect!#REF! -> #REF! | AX39: 38.173558 | AY39: 19.219193 | AZ39: 208225.85 | BA39: 10.138565 | BB39: 5.1044505 | BC39: =Elect!#REF! -> #REF! | BD39: =Elect!#REF! -> #REF! | BE39: =Elect!#REF! -> #REF! | BF39: =Elect!#REF! -> #REF! | BG39: =Elect!#REF! -> #REF! | BH39: 0 | BI39: 0 | BJ39: 115057.98 | BK39: 6.2024355 | BL39: 3.1227323 | BM39: =Water!U44 -> 0 | BN39: =Water!W44 -> 0 | BO39: =Water!X44 -> #VALUE! | BP39: =Water!Y44 -> #VALUE! | BQ39: =Water!Z44 -> #VALUE!
A40: AVER RFC | B40: 28000.305 | C40: =Elect!#REF! -> #REF! | D40: 0 | E40: =Elect!#REF! -> #REF! | F40: 0 | G40: =Elect!#REF! -> #REF! | H40: 0 | I40: =Water!C45 -> 0 | J40: 0 | K40: =Water!E46 -> 0 | L40: 10 | M40: =Water!#REF! -> #REF! | N40: =Water!#REF! -> #REF! | O40: 0 | P40: =Water!H45 -> 0 | Q40: 0 | R40: =Water!O45 -> 0 | S40: 0 | T40: =Water!#REF! -> #REF! | U40: 0 | V40: =Water!#REF! -> #REF! | W40: 0 | X40: =Water!Q45 -> 0 | Y40: 10 | Z40: =Water!#REF! -> #REF! | AA40: 0 | AB40: 0 | AC40: 0 | AD40: =Water!#REF! -> #REF! | AE40: =Water!#REF! -> #REF! | AF40: =Water!#REF! -> #REF! | AG40: =Gas!#REF! -> #REF! | AH40: =Gas!#REF! -> #REF! | AI40: =Gas!#REF! -> #REF! | AJ40: =Gas!#REF! -> #REF! | AK40: =Gas!#REF! -> #REF! | AL40: =Gas!#REF! -> #REF! | AM40: =Gas!#REF! -> #REF! | AN40: =Gas!#REF! -> #REF! | ... AS40: =Gas!#REF! -> #REF! | AT40: =Elect!#REF! -> #REF! | AU40: =Elect!#REF! -> #REF! | AX40: 0 | AY40: 0 | AZ40: 7436.6375 | BA40: 0 | BB40: 0 | BC40: =Elect!#REF! -> #REF! | BD40: =Elect!#REF! -> #REF! | BE40: =Elect!#REF! -> #REF! | BF40: =Elect!#REF! -> #REF! | BG40: =Elect!#REF! -> #REF! | BH40: 1.1254646 | BI40: 0.57264868 | BJ40: 4109.2135 | BK40: 0 | BL40: 0 | BM40: =Water!U45 -> 0 | BN40: =Water!W45 -> 0 | BO40: =Water!X45 -> #VALUE! | BP40: =Water!Y45 -> 0 | BQ40: =Water!Z45 -> 0

Sheet Temp.
A2: HILTON INTERNATIONAL
A3: GULF, MIDDLE EAST AND ASIA SPECIFIC
A4: HOTEL:HILTON HURGHADA LONG BEACH RESORT | G4: =Elect!A1 -> February
A7: DATE | B7: MAX TEMP | C7: MIN TEMP | D7: MAX TEMP | E7: MIN TEMP | F7: DAY | G7: DD. C | H7: DD. H | I7: MTD | J7: MTD
B8: C | C8: C | D8: F | E8: F | F8: PARAMETER | I8: COOLING | J8: HEATING
A10: 1 | D10: =SUM((B10*9/5)+32) -> 32 | E10: =SUM((C10*9/5)+32) -> 32 | F10: =SUM(((B10+C10)/2)-18.33) -> -18.33 | G10: =SUM(0+(F10)+ABS(F10))/2 -> 0 | H10: =IF((SUM(0-(F10)+ABS(F10))/2)<18,SUM(0-(F10)+ABS(F10))/2,0) -> 0 | I10: =SUM(G10:G10) -> 0 | J10: =SUM(H10:H10) -> 0
A11: 2 | D11: =SUM((B11*9/5)+32) -> 32 | E11: =SUM((C11*9/5)+32) -> 32 | F11: =SUM(((B11+C11)/2)-18.33) -> -18.33 | G11: =SUM(0+(F11)+ABS(F11))/2 -> 0 | H11: =IF((SUM(0-(F11)+ABS(F11))/2)<18,SUM(0-(F11)+ABS(F11))/2,0) -> 0 | I11: =SUM(G10:G11) -> 0 | J11: =SUM(H10:H11) -> 0
A12: 3 | D12: =SUM((B12*9/5)+32) -> 32 | E12: =SUM((C12*9/5)+32) -> 32 | F12: =SUM(((B12+C12)/2)-18.33) -> -18.33 | G12: =SUM(0+(F12)+ABS(F12))/2 -> 0 | H12: =IF((SUM(0-(F12)+ABS(F12))/2)<18,SUM(0-(F12)+ABS(F12))/2,0) -> 0 | I12: =SUM(G10:G12) -> 0 | J12: =SUM(H10:H12) -> 0
A13: 4 | D13: =SUM((B13*9/5)+32) -> 32 | E13: =SUM((C13*9/5)+32) -> 32 | F13: =SUM(((B13+C13)/2)-18.33) -> -18.33 | G13: =SUM(0+(F13)+ABS(F13))/2 -> 0 | H13: =IF((SUM(0-(F13)+ABS(F13))/2)<18,SUM(0-(F13)+ABS(F13))/2,0) -> 0 | I13: =SUM(G10:G13) -> 0 | J13: =SUM(H10:H13) -> 0
A14: 5 | D14: =SUM((B14*9/5)+32) -> 32 | E14: =SUM((C14*9/5)+32) -> 32 | F14: =SUM(((B14+C14)/2)-18.33) -> -18.33 | G14: =SUM(0+(F14)+ABS(F14))/2 -> 0 | H14: =IF((SUM(0-(F14)+ABS(F14))/2)<18,SUM(0-(F14)+ABS(F14))/2,0) -> 0 | I14: =SUM(G10:G14) -> 0 | J14: =SUM(H10:H14) -> 0
A15: 6 | D15: =SUM((B15*9/5)+32) -> 32 | E15: =SUM((C15*9/5)+32) -> 32 | F15: =SUM(((B15+C15)/2)-18.33) -> -18.33 | G15: =SUM(0+(F15)+ABS(F15))/2 -> 0 | H15: =IF((SUM(0-(F15)+ABS(F15))/2)<18,SUM(0-(F15)+ABS(F15))/2,0) -> 0 | I15: =SUM(G10:G15) -> 0 | J15: =SUM(H10:H15) -> 0
A16: 7 | D16: =SUM((B16*9/5)+32) -> 32 | E16: =SUM((C16*9/5)+32) -> 32 | F16: =SUM(((B16+C16)/2)-18.33) -> -18.33 | G16: =SUM(0+(F16)+ABS(F16))/2 -> 0 | H16: =IF((SUM(0-(F16)+ABS(F16))/2)<18,SUM(0-(F16)+ABS(F16))/2,0) -> 0 | I16: =SUM(G10:G16) -> 0 | J16: =SUM(H10:H16) -> 0
A17: 8 | D17: =SUM((B17*9/5)+32) -> 32 | E17: =SUM((C17*9/5)+32) -> 32 | F17: =SUM(((B17+C17)/2)-18.33) -> -18.33 | G17: =SUM(0+(F17)+ABS(F17))/2 -> 0 | H17: =IF((SUM(0-(F17)+ABS(F17))/2)<18,SUM(0-(F17)+ABS(F17))/2,0) -> 0 | I17: =SUM(G10:G17) -> 0 | J17: =SUM(H10:H17) -> 0
A18: 9 | D18: =SUM((B18*9/5)+32) -> 32 | E18: =SUM((C18*9/5)+32) -> 32 | F18: =SUM(((B18+C18)/2)-18.33) -> -18.33 | G18: =SUM(0+(F18)+ABS(F18))/2 -> 0 | H18: =IF((SUM(0-(F18)+ABS(F18))/2)<18,SUM(0-(F18)+ABS(F18))/2,0) -> 0 | I18: =SUM(G10:G18) -> 0 | J18: =SUM(H10:H18) -> 0
A19: 10 | D19: =SUM((B19*9/5)+32) -> 32 | E19: =SUM((C19*9/5)+32) -> 32 | F19: =SUM(((B19+C19)/2)-18.33) -> -18.33 | G19: =SUM(0+(F19)+ABS(F19))/2 -> 0 | H19: =IF((SUM(0-(F19)+ABS(F19))/2)<18,SUM(0-(F19)+ABS(F19))/2,0) -> 0 | I19: =SUM(G10:G19) -> 0 | J19: =SUM(H10:H19) -> 0
A20: 11 | D20: =SUM((B20*9/5)+32) -> 32 | E20: =SUM((C20*9/5)+32) -> 32 | F20: =SUM(((B20+C20)/2)-18.33) -> -18.33 | G20: =SUM(0+(F20)+ABS(F20))/2 -> 0 | H20: =IF((SUM(0-(F20)+ABS(F20))/2)<18,SUM(0-(F20)+ABS(F20))/2,0) -> 0 | I20: =SUM(G10:G20) -> 0 | J20: =SUM(H10:H20) -> 0
A21: 12 | D21: =SUM((B21*9/5)+32) -> 32 | E21: =SUM((C21*9/5)+32) -> 32 | F21: =SUM(((B21+C21)/2)-18.33) -> -18.33 | G21: =SUM(0+(F21)+ABS(F21))/2 -> 0 | H21: =IF((SUM(0-(F21)+ABS(F21))/2)<18,SUM(0-(F21)+ABS(F21))/2,0) -> 0 | I21: =SUM(G10:G21) -> 0 | J21: =SUM(H10:H21) -> 0
A22: 13 | D22: =SUM((B22*9/5)+32) -> 32 | E22: =SUM((C22*9/5)+32) -> 32 | F22: =SUM(((B22+C22)/2)-18.33) -> -18.33 | G22: =SUM(0+(F22)+ABS(F22))/2 -> 0 | H22: =IF((SUM(0-(F22)+ABS(F22))/2)<18,SUM(0-(F22)+ABS(F22))/2,0) -> 0 | I22: =SUM(G10:G22) -> 0 | J22: =SUM(H10:H22) -> 0
A23: 14 | D23: =SUM((B23*9/5)+32) -> 32 | E23: =SUM((C23*9/5)+32) -> 32 | F23: =SUM(((B23+C23)/2)-18.33) -> -18.33 | G23: =SUM(0+(F23)+ABS(F23))/2 -> 0 | H23: =IF((SUM(0-(F23)+ABS(F23))/2)<18,SUM(0-(F23)+ABS(F23))/2,0) -> 0 | I23: =SUM(G10:G23) -> 0 | J23: =SUM(H10:H23) -> 0
A24: 15 | D24: =SUM((B24*9/5)+32) -> 32 | E24: =SUM((C24*9/5)+32) -> 32 | F24: =SUM(((B24+C24)/2)-18.33) -> -18.33 | G24: =SUM(0+(F24)+ABS(F24))/2 -> 0 | H24: =IF((SUM(0-(F24)+ABS(F24))/2)<18,SUM(0-(F24)+ABS(F24))/2,0) -> 0 | I24: =SUM(G11:G24) -> 0 | J24: =SUM(H11:H24) -> 0
A25: 16 | D25: =SUM((B25*9/5)+32) -> 32 | E25: =SUM((C25*9/5)+32) -> 32 | F25: =SUM(((B25+C25)/2)-18.33) -> -18.33 | G25: =SUM(0+(F25)+ABS(F25))/2 -> 0 | H25: =IF((SUM(0-(F25)+ABS(F25))/2)<18,SUM(0-(F25)+ABS(F25))/2,0) -> 0 | I25: =SUM(G12:G25) -> 0 | J25: =SUM(H12:H25) -> 0
A26: 17 | D26: =SUM((B26*9/5)+32) -> 32 | E26: =SUM((C26*9/5)+32) -> 32 | F26: =SUM(((B26+C26)/2)-18.33) -> -18.33 | G26: =SUM(0+(F26)+ABS(F26))/2 -> 0 | H26: =IF((SUM(0-(F26)+ABS(F26))/2)<18,SUM(0-(F26)+ABS(F26))/2,0) -> 0 | I26: =SUM(G13:G26) -> 0 | J26: =SUM(H13:H26) -> 0
A27: 18 | D27: =SUM((B27*9/5)+32) -> 32 | E27: =SUM((C27*9/5)+32) -> 32 | F27: =SUM(((B27+C27)/2)-18.33) -> -18.33 | G27: =SUM(0+(F27)+ABS(F27))/2 -> 0 | H27: =IF((SUM(0-(F27)+ABS(F27))/2)<18,SUM(0-(F27)+ABS(F27))/2,0) -> 0 | I27: =SUM(G14:G27) -> 0 | J27: =SUM(H14:H27) -> 0
A28: 19 | D28: =SUM((B28*9/5)+32) -> 32 | E28: =SUM((C28*9/5)+32) -> 32 | F28: =SUM(((B28+C28)/2)-18.33) -> -18.33 | G28: =SUM(0+(F28)+ABS(F28))/2 -> 0 | H28: =IF((SUM(0-(F28)+ABS(F28))/2)<18,SUM(0-(F28)+ABS(F28))/2,0) -> 0 | I28: =SUM(G15:G28) -> 0 | J28: =SUM(H15:H28) -> 0
A29: 20 | D29: =SUM((B29*9/5)+32) -> 32 | E29: =SUM((C29*9/5)+32) -> 32 | F29: =SUM(((B29+C29)/2)-18.33) -> -18.33 | G29: =SUM(0+(F29)+ABS(F29))/2 -> 0 | H29: =IF((SUM(0-(F29)+ABS(F29))/2)<18,SUM(0-(F29)+ABS(F29))/2,0) -> 0 | I29: =SUM(G16:G29) -> 0 | J29: =SUM(H16:H29) -> 0
A30: 21 | D30: =SUM((B30*9/5)+32) -> 32 | E30: =SUM((C30*9/5)+32) -> 32 | F30: =SUM(((B30+C30)/2)-18.33) -> -18.33 | G30: =SUM(0+(F30)+ABS(F30))/2 -> 0 | H30: =IF((SUM(0-(F30)+ABS(F30))/2)<18,SUM(0-(F30)+ABS(F30))/2,0) -> 0 | I30: =SUM(G17:G30) -> 0 | J30: =SUM(H17:H30) -> 0
A31: 22 | D31: =SUM((B31*9/5)+32) -> 32 | E31: =SUM((C31*9/5)+32) -> 32 | F31: =SUM(((B31+C31)/2)-18.33) -> -18.33 | G31: =SUM(0+(F31)+ABS(F31))/2 -> 0 | H31: =IF((SUM(0-(F31)+ABS(F31))/2)<18,SUM(0-(F31)+ABS(F31))/2,0) -> 0 | I31: =SUM(G18:G31) -> 0 | J31: =SUM(H18:H31) -> 0
A32: 23 | D32: =SUM((B32*9/5)+32) -> 32 | E32: =SUM((C32*9/5)+32) -> 32 | F32: =SUM(((B32+C32)/2)-18.33) -> -18.33 | G32: =SUM(0+(F32)+ABS(F32))/2 -> 0 | H32: =IF((SUM(0-(F32)+ABS(F32))/2)<18,SUM(0-(F32)+ABS(F32))/2,0) -> 0 | I32: =SUM(G19:G32) -> 0 | J32: =SUM(H19:H32) -> 0
A33: 24 | D33: =SUM((B33*9/5)+32) -> 32 | E33: =SUM((C33*9/5)+32) -> 32 | F33: =SUM(((B33+C33)/2)-18.33) -> -18.33 | G33: =SUM(0+(F33)+ABS(F33))/2 -> 0 | H33: =IF((SUM(0-(F33)+ABS(F33))/2)<18,SUM(0-(F33)+ABS(F33))/2,0) -> 0 | I33: =SUM(G20:G33) -> 0 | J33: =SUM(H20:H33) -> 0
A34: 25 | D34: =SUM((B34*9/5)+32) -> 32 | E34: =SUM((C34*9/5)+32) -> 32 | F34: =SUM(((B34+C34)/2)-18.33) -> -18.33 | G34: =SUM(0+(F34)+ABS(F34))/2 -> 0 | H34: =IF((SUM(0-(F34)+ABS(F34))/2)<18,SUM(0-(F34)+ABS(F34))/2,0) -> 0 | I34: =SUM(G21:G34) -> 0 | J34: =SUM(H21:H34) -> 0
... A40: 31 | D40: =SUM((B40*9/5)+32) -> 32 | E40: =SUM((C40*9/5)+32) -> 32 | F40: =SUM(((B40+C40)/2)-18.33) -> -18.33 | G40: =SUM(0+(F40)+ABS(F40))/2 -> 0 | H40: =IF((SUM(0-(F40)+ABS(F40))/2)<18,SUM(0-(F40)+ABS(F40))/2,0) -> 0 | I40: =SUM(G27:G40) -> 0 | J40: =SUM(H27:H40) -> 0
E42: =SUM(G10:G40) -> 0 | F42: deg c
E44: =SUM(H10:H40) -> 0 | F44: deg c

Sheet M-Rep
B3: =Elect!A1 -> February
D4: Y.T.D
A5: Energy breakdown | C5: 2009 | D5: 2005 | E5: 2006
A6: Elect.
A7: Chillers KWH | C7: N/A | D7: N/A | E7: N/A
A8: Laundry KWH | C8: N/A | D8: N/A | E8: N/A
A9: Kitchen KWH | C9: N/A | D9: N/A | E9: N/A
A10: Gas
A11: Kit M3 | C11: =Gas!#REF!/1000 -> #REF!
A12: Laundry M3 | C12: N/A | D12: 0 | E12: #REF!
A13: Water | D13: N/A | E13: N/A
A14: Laundry HW | C14: N/A
A15: Laundry CW | C15: N/A
A16: Kit HW | C16: N/A
A17: kIt CW | C17: N/A | D17: N/A | E17: N/A
A18: Dmstc HW | C18: N/A | D18: N/A | E18: N/A
A19: Dmstc CW | C19: N/A | D19: N/A | E19: N/A
A20: S.Pool MKUP | C20: =#REF! -> #REF! | D20: N/A | E20: N/A
A21: Ctower MKUP | C21: N/A | D21: N/A | E21: N/A
A22: Gardens Irrigat. | C22: =Water!S38 -> 0 | D22: N/A | E22: N/A
A23: Swage water treatment | C23: =Water!#REF! -> #REF! | D23: 27437 | E23: #REF!
A24: Utilities consumption | D24: N/A | E24: N/A
A25: Elect. Kwh | C25: =Elect!J34 -> 0 | D25: 12266 | E25: 814
A26: M.D (9.5 LE) | D26: 147773 | E26: #REF!
A27: Water M3 | C27: =Water!H38 -> 5015.84
A28: Fuel Ltr | C28: =Gas!#REF!*1000 -> #REF! | D28: 12876868 | E28: 14500800
A29: Gas M3/ Boilers, chillers,..etc | C29: N/A | D29: 28880 | E29: 32980
A30: Gas M3 Kitchen | C30: =Gas!#REF!/1000 -> #REF! | D30: 244283 | E30: 252530.66
A31: Total Energy | D31: 620770 | E31: #REF!
A32: Control Parameters | D32: #REF! | E32: N/A
A33: No. of Rooms % occ. | C33: =YTD!Q4 -> 0 | D33: 39.395 | E33: #REF!
A34: No. of Occ. Rooms | C34: =YTD!Q5 -> 0
A35: guest count | C35: =YTD!Q6 -> 0
A36: Food covers | D36: #REF! | E36: #REF!
A37: Laundry W. Kg | D37: 0.8807 | E37: 0.46351998
A38: DDC | C38: =Temp.!E42 -> 0 | D38: 196150 | E38: 237021
A39: DDH | C39: =Temp.!E44 -> 0 | D39: 400070 | E39: 466105
A40: Utilities Entergy cost | D40: 1583714 | E40: 1940567
A41: Elect. | C41: =Elect!#REF! -> #REF! | D41: 1690339 | E41: 3118671.6
A42: M.D | C42: =C26*Elect!#REF! -> #REF! | D42: 2381.51 | E42: 2480.24
A43: Water | C43: =Water!X38 -> 20063.36 | D43: 112 | E43: 97.53
A44: Fuel | C44: =Gas!#REF! -> #REF!
A45: Gas Boilers, chillers,etc.. | C45: N/A | D45: 2138156.8 | E45: #REF!
A46: Gas Kitchen | C46: =C30*Gas!M2*1000 -> #REF! | D46: 223044.2 | E46: #REF!
A47: TOTAL LE | C47: =SUM(C41:C46) -> #REF! | D47: 1330535.7 | E47: 1382037.4
A48: No. of POMEC Staff | D48: 330278 | E48: #REF!
A49: Hotel Age | C49: 6 | D49: N/A | E49: N/A
A50: No. of rooms | C50: =31*912 -> 28272 | D50: 36597.525 | E50: #REF!
A51: Building Volume | C51: 243175 | D51: =SUM(D45:D50) -> 4058612.3 | E51: =SUM(E45:E50) -> #REF!
A52: Building area | C52: 75064
A53: US$ Rate | C53: 5.59402 | D53: 61 | E53: 72
A54: Total R&M MTD | C54: =YTD!Q65 -> 0 | D54: #REF! | E54: 243175 | F54: =YTD!Q64 -> 0
A55: Staff - HLP | D55: #REF! | E55: 75064
A56: Staff - R&M | D56: 5.755 | E56: 5.65951
A57: Staff - Grounds

Sheet YTD
A1: =Elect!A1 -> February | H1: Actual 2014
C3: JAN | D3: FEB | E3: MAR | F3: APR | G3: MAY | H3: JUN | I3: JUL | J3: AUG | K3: SEP | L3: OCT | M3: NOV | N3: DEC | O3: TOTAL | P3: YTD | Q3: Month Act
A4: Occ Room % | O4: =SUM(C4:N4) -> 0 | P4: =(IF($A$1=39814,C4,(IF($A$1=39845,SUM(C4:D4),(IF($A$1=39873,SUM(C4:E4),(IF($A$1=39904,SUM(C4:F4),(IF($A$1=39934,SUM(C4:G4),(IF($A$1=39965,SUM(C4:H4),(IF($A$1=39995,SUM(C4:I4),0)))))))))))))+(IF($A$1=40026,SUM(C4:J4),(IF($A$1=40057,SUM(C4:K4),(IF($A$1=40087,SUM(C4:L4),(IF($A$1=40118,SUM(C4:M4))))))))))+(IF($A$1=40148,SUM(C4:N4),0)) -> 0 | Q4: =(IF($A$1=39814,C4,(IF($A$1=39845,D4,(IF($A$1=39873,E4,(IF($A$1=39904,F4,(IF($A$1=39934,G4,(IF($A$1=39965,H4,(IF($A$1=39995,I4,0)))))))))))))+(IF($A$1=40026,J4,(IF($A$1=40057,K4,(IF($A$1=40087,L4,(IF($A$1=40118,M4)))))))))+(IF($A$1=40148,N4,0)) -> 0 | S4: 40179 | DE4: 1
A5: Occ Room | C5: 25072 | D5: =Elect!BT34 -> 0 | O5: =SUM(C5:N5) -> 25072 | P5: =(IF($A$1=40179,C5,(IF($A$1=40210,SUM(C5:D5),(IF($A$1=40238,SUM(C5:E5),(IF($A$1=40269,SUM(C5:F5),(IF($A$1=40299,SUM(C5:G5),(IF($A$1=40330,SUM(C5:H5),(IF($A$1=40360,SUM(C5:I5),0)))))))))))))+(IF($A$1=40391,SUM(C5:J5),(IF($A$1=40422,SUM(C5:K5),(IF($A$1=40452,SUM(C5:L5),(IF($A$1=40483,SUM(C5:M5))))))))))+(IF($A$1=40513,SUM(C5:N5),0)) -> 0 | Q5: =(IF($A$1=40179,C5,(IF($A$1=40210,D5,(IF($A$1=40238,E5,(IF($A$1=40269,F5,(IF($A$1=40299,G5,(IF($A$1=40330,H5,(IF($A$1=40360,I5,0)))))))))))))+(IF($A$1=40391,J5,(IF($A$1=40422,K5,(IF($A$1=40452,L5,(IF($A$1=40483,M5)))))))))+(IF($A$1=40513,N5,0)) -> 0 | S5: 40210 | DE5: 2
A6: Number of Guest | C6: 50662 | D6: =Elect!BV34 -> 0 | O6: =SUM(C6:N6) -> 50662 | P6: =(IF($A$1=40179,C6,(IF($A$1=40210,SUM(C6:D6),(IF($A$1=40238,SUM(C6:E6),(IF($A$1=40269,SUM(C6:F6),(IF($A$1=40299,SUM(C6:G6),(IF($A$1=40330,SUM(C6:H6),(IF($A$1=40360,SUM(C6:I6),0)))))))))))))+(IF($A$1=40391,SUM(C6:J6),(IF($A$1=40422,SUM(C6:K6),(IF($A$1=40452,SUM(C6:L6),(IF($A$1=40483,SUM(C6:M6))))))))))+(IF($A$1=40513,SUM(C6:N6),0)) -> 0 | Q6: =(IF($A$1=40179,C6,(IF($A$1=40210,D6,(IF($A$1=40238,E6,(IF($A$1=40269,F6,(IF($A$1=40299,G6,(IF($A$1=40330,H6,(IF($A$1=40360,I6,0)))))))))))))+(IF($A$1=40391,J6,(IF($A$1=40422,K6,(IF($A$1=40452,L6,(IF($A$1=40483,M6)))))))))+(IF($A$1=40513,N6,0)) -> 0 | S6: 40238 | DE6: 3
A7: PAY & REL. EXP. | O7: =SUM(C7:N7) -> 0 | P7: =(IF($A$1=40179,C7,(IF($A$1=40210,SUM(C7:D7),(IF($A$1=40238,SUM(C7:E7),(IF($A$1=40269,SUM(C7:F7),(IF($A$1=40299,SUM(C7:G7),(IF($A$1=40330,SUM(C7:H7),(IF($A$1=40360,SUM(C7:I7),0)))))))))))))+(IF($A$1=40391,SUM(C7:J7),(IF($A$1=40422,SUM(C7:K7),(IF($A$1=40452,SUM(C7:L7),(IF($A$1=40483,SUM(C7:M7))))))))))+(IF($A$1=40513,SUM(C7:N7),0)) -> 0 | Q7: =(IF($A$1=40179,C7,(IF($A$1=40210,D7,(IF($A$1=40238,E7,(IF($A$1=40269,F7,(IF($A$1=40299,G7,(IF($A$1=40330,H7,(IF($A$1=40360,I7,0)))))))))))))+(IF($A$1=40391,J7,(IF($A$1=40422,K7,(IF($A$1=40452,L7,(IF($A$1=40483,M7)))))))))+(IF($A$1=40513,N7,0)) -> 0
