Workbook

Sheet Total
A1: Site Name | B1: Day | C1: Month | D1: Year | E1: Total Electricity Kwh | F1: Electricity Tariff ($/Kwh) | G1: Total Fuel Oil (Liter) | H1: Fuel Oil $/Liter | I1: LPG (Kg) | J1: LPG $/Kg | K1: Water Utility Supply (m3) m3 | L1: Water Utility Supply (m3) $/m3 | M1: Irrigation Water (m3) m3 | N1: Irrigation water $/m3 | O1: Room Nights
A2: Beirut | B2: 1 | C2: 9 | D2: 2022 | E2: =ELEC!N4 -> 3873 | F2: =SUM('EDl log'!T4) -> 0.41941108 | G2: =-tanks!AW6 -> 25 | H2: =tanks!AV6 -> 0 | I2: =('B5'!AU5)*0.51 -> 0 | J2: ='B5'!AX5/0.51 -> 1.5686275 | K2: =WATER!I6 -> 0 | L2: =SUM(WATER!J6) -> 0 | M2: =WATER!Q6 -> 0 | N2: 0.6 | O2: =ELEC!B4 -> 0
A3: Beirut | B3: =B2+1 -> 2 | C3: 9 | D3: =D2 -> 2022 | E3: =ELEC!N5 -> 0 | F3: =SUM('EDl log'!T5) -> 0 | G3: =-tanks!AW7 -> 0 | H3: =tanks!AV7 -> 0 | I3: =('B5'!AU6)*0.51 -> 0 | J3: ='B5'!AX6/0.51 -> 1.5686275 | K3: =WATER!I7 -> 0 | L3: =SUM(WATER!J7) -> 0 | M3: =WATER!Q7 -> 0 | N3: 0.6 | O3: =ELEC!B5 -> 0
A4: Beirut | B4: =B3+1 -> 3 | C4: 9 | D4: =D3 -> 2022 | E4: =ELEC!N6 -> 0 | F4: =SUM('EDl log'!T6) -> 0 | G4: =-tanks!AW8 -> 0 | H4: =tanks!AV8 -> 0 | I4: =('B5'!AU7)*0.51 -> 0 | J4: ='B5'!AX7/0.51 -> 1.5686275 | K4: =WATER!I8 -> 0 | L4: =SUM(WATER!J8) -> 0 | M4: =WATER!Q8 -> 0 | N4: 0.6 | O4: =ELEC!B6 -> 0
A5: Beirut | B5: =B4+1 -> 4 | C5: 9 | D5: =D4 -> 2022 | E5: =ELEC!N7 -> 3120 | F5: =SUM('EDl log'!T7) -> 0.39187141 | G5: =-tanks!AW9 -> 148 | H5: =tanks!AV9 -> 0 | I5: =('B5'!AU8)*0.51 -> 0 | J5: ='B5'!AX8/0.51 -> 1.5686275 | K5: =WATER!I9 -> 134 | L5: =SUM(WATER!J9) -> 1.8656716 | M5: =WATER!Q9 -> 0 | N5: 0.6 | O5: =ELEC!B7 -> 0
A6: Beirut | B6: =B5+1 -> 5 | C6: 9 | D6: =D5 -> 2022 | E6: =ELEC!N8 -> 3326 | F6: =SUM('EDl log'!T8) -> 0.38554764 | G6: =-tanks!AW10 -> 113 | H6: =tanks!AV10 -> 0 | I6: =('B5'!AU9)*0.51 -> 0 | J6: ='B5'!AX9/0.51 -> 1.5686275 | K6: =WATER!I10 -> 0 | L6: =SUM(WATER!J10) -> 0 | M6: =WATER!Q10 -> 0 | N6: 0.6 | O6: =ELEC!B8 -> 0
A7: Beirut | B7: =B6+1 -> 6 | C7: 9 | D7: =D6 -> 2022 | E7: =ELEC!N9 -> 5010 | F7: =SUM('EDl log'!T9) -> 0.45306423 | G7: =-tanks!AW11 -> 74 | H7: =tanks!AV11 -> 0 | I7: =('B5'!AU10)*0.51 -> 0 | J7: ='B5'!AX10/0.51 -> 1.5686275 | K7: =WATER!I11 -> 0 | L7: =SUM(WATER!J11) -> 0 | M7: =WATER!Q11 -> 0 | N7: 0.6 | O7: =ELEC!B9 -> 0
A8: Beirut | B8: =B7+1 -> 7 | C8: 9 | D8: =D7 -> 2022 | E8: =ELEC!N10 -> 4771 | F8: =SUM('EDl log'!T10) -> 0.4405369 | G8: =-tanks!AW12 -> 90 | H8: =tanks!AV12 -> 1.111 | I8: =('B5'!AU11)*0.51 -> -45.9 | J8: ='B5'!AX11/0.51 -> 1.5686275 | K8: =WATER!I12 -> 112 | L8: =SUM(WATER!J12) -> 2.2321429 | M8: =WATER!Q12 -> 0 | N8: 0.6 | O8: =ELEC!B10 -> 0
A9: Beirut | B9: =B8+1 -> 8 | C9: 9 | D9: =D8 -> 2022 | E9: =ELEC!N11 -> 3693 | F9: =SUM('EDl log'!T11) -> 0.32574117 | G9: =-tanks!AW13 -> 0 | H9: =tanks!AV13 -> 1.111 | I9: =('B5'!AU12)*0.51 -> 0 | J9: ='B5'!AX12/0.51 -> 1.5686275 | K9: =WATER!I13 -> 0 | L9: =SUM(WATER!J13) -> 0 | M9: =WATER!Q13 -> 0 | N9: 0.6 | O9: =ELEC!B11 -> 0
A10: Beirut | B10: =B9+1 -> 9 | C10: 9 | D10: =D9 -> 2022 | E10: =ELEC!N12 -> 0 | F10: =SUM('EDl log'!T12) -> 0 | G10: =-tanks!AW14 -> 0 | H10: =tanks!AV14 -> 1.111 | I10: =('B5'!AU13)*0.51 -> 0 | J10: ='B5'!AX13/0.51 -> 1.5686275 | K10: =WATER!I14 -> 0 | L10: =SUM(WATER!J14) -> 0 | M10: =WATER!Q14 -> 0 | N10: 0.6 | O10: =ELEC!B12 -> 0
A11: Beirut | B11: =B10+1 -> 10 | C11: 9 | D11: =D10 -> 2022 | E11: =ELEC!N13 -> 0 | F11: =SUM('EDl log'!T13) -> 0 | G11: =-tanks!AW15 -> 0 | H11: =tanks!AV15 -> 1.111 | I11: =('B5'!AU14)*0.51 -> 0 | J11: ='B5'!AX14/0.51 -> 1.5686275 | K11: =WATER!I15 -> 0 | L11: =SUM(WATER!J15) -> 0 | M11: =WATER!Q15 -> 0 | N11: 0.6 | O11: =ELEC!B13 -> 0
A12: Beirut | B12: =B11+1 -> 11 | C12: 9 | D12: =D11 -> 2022 | E12: =ELEC!N14 -> 4209.4 | F12: =SUM('EDl log'!T14) -> 0.32032169 | G12: =-tanks!AW16 -> 217 | H12: =tanks!AV16 -> 1.111 | I12: =('B5'!AU15)*0.51 -> 0 | J12: ='B5'!AX15/0.51 -> 1.5686275 | K12: =WATER!I16 -> 97 | L12: =SUM(WATER!J16) -> 2.5773196 | M12: =WATER!Q16 -> 0 | N12: 0.6 | O12: =ELEC!B14 -> 0
A13: Beirut | B13: =B12+1 -> 12 | C13: 9 | D13: =D12 -> 2022 | E13: =ELEC!N15 -> 3162.6 | F13: =SUM('EDl log'!T15) -> -0.31491408 | G13: =-tanks!AW17 -> 8 | H13: =tanks!AV17 -> 1.063 | I13: =('B5'!AU16)*0.51 -> 0 | J13: ='B5'!AX16/0.51 -> 1.5686275 | K13: =WATER!I17 -> 0 | L13: =SUM(WATER!J17) -> 0 | M13: =WATER!Q17 -> 0 | N13: 0.6 | O13: =ELEC!B15 -> 0
A14: Beirut | B14: =B13+1 -> 13 | C14: 9 | D14: =D13 -> 2022 | E14: =ELEC!N16 -> 2901 | F14: =SUM('EDl log'!T16) -> 0.40729138 | G14: =-tanks!AW18 -> 187 | H14: =tanks!AV18 -> 1.063 | I14: =('B5'!AU17)*0.51 -> 0 | J14: ='B5'!AX17/0.51 -> 1.5686275 | K14: =WATER!I18 -> 0 | L14: =SUM(WATER!J18) -> 0 | M14: =WATER!Q18 -> 0 | N14: 0.6 | O14: =ELEC!B16 -> 0
... A32: Beirut | B32: =B31+1 -> 31 | C32: 9 | D32: =D31 -> 2022 | E32: =ELEC!N34 -> 0 | F32: =SUM('EDl log'!T34) -> 0 | G32: =-tanks!AW36 -> 0 | H32: =tanks!AV36 -> 0 | I32: =('B5'!AU35)*0.51 -> 0 | J32: ='B5'!AX35/0.51 -> 1.5686275 | K32: =WATER!I36 -> 0 | L32: =SUM(WATER!J36) -> 0 | M32: =WATER!Q36 -> 0 | N32: 0.6 | O32: =ELEC!B34 -> 0

Sheet Submetering
A1: Site Name | B1: Day | C1: Month | D1: Year | E1: ATS1 Kwh | F1: ATS2 Kwh | G1: ATS3 Kwh | H1: ATS4 Kwh | I1: ATS5 Kwh | J1: Guest (m3) | K1: Kitchen & Laundry (m3) | L1: Room Nights
A2: Beirut | B2: 1 | C2: 9 | D2: 2022 | E2: =ELEC!M4 -> 1168 | F2: =ELEC!K4 -> 888 | G2: =ELEC!I4 -> 488 | H2: =ELEC!E4 -> 770 | I2: =ELEC!G4 -> 559 | J2: =WATER!Y6 -> 0 | K2: =WATER!AJ6 -> 0 | L2: =ELEC!B4 -> 0
A3: Beirut | B3: =B2+1 -> 2 | C3: 9 | D3: 2022 | E3: =ELEC!M5 -> 0 | F3: =ELEC!K5 -> 0 | G3: =ELEC!I5 -> 0 | H3: =ELEC!E5 -> 0 | I3: =ELEC!G5 -> 0 | J3: =WATER!Y7 -> 0 | K3: =WATER!AJ7 -> 0 | L3: =ELEC!B5 -> 0
A4: Beirut | B4: =B3+1 -> 3 | C4: 9 | D4: 2022 | E4: =ELEC!M6 -> 0 | F4: =ELEC!K6 -> 0 | G4: =ELEC!I6 -> 0 | H4: =ELEC!E6 -> 0 | I4: =ELEC!G6 -> 0 | J4: =WATER!Y8 -> 0 | K4: =WATER!AJ8 -> 0 | L4: =ELEC!B6 -> 0
A5: Beirut | B5: =B4+1 -> 4 | C5: 9 | D5: 2022 | E5: =ELEC!M7 -> 856 | F5: =ELEC!K7 -> 652 | G5: =ELEC!I7 -> 434 | H5: =ELEC!E7 -> 730 | I5: =ELEC!G7 -> 448 | J5: =WATER!Y9 -> 0 | K5: =WATER!AJ9 -> 0 | L5: =ELEC!B7 -> 0
A6: Beirut | B6: =B5+1 -> 5 | C6: 9 | D6: 2022 | E6: =ELEC!M8 -> 1090 | F6: =ELEC!K8 -> 568 | G6: =ELEC!I8 -> 442 | H6: =ELEC!E8 -> 760 | I6: =ELEC!G8 -> 466 | J6: =WATER!Y10 -> 0 | K6: =WATER!AJ10 -> 0 | L6: =ELEC!B8 -> 0
A7: Beirut | B7: =B6+1 -> 6 | C7: 9 | D7: 2022 | E7: =ELEC!M9 -> 1136 | F7: =ELEC!K9 -> 1512 | G7: =ELEC!I9 -> 454 | H7: =ELEC!E9 -> 1400 | I7: =ELEC!G9 -> 508 | J7: =WATER!Y11 -> 0 | K7: =WATER!AJ11 -> 0 | L7: =ELEC!B9 -> 0
A8: Beirut | B8: =B7+1 -> 7 | C8: 9 | D8: 2022 | E8: =ELEC!M10 -> 954 | F8: =ELEC!K10 -> 932 | G8: =ELEC!I10 -> 326 | H8: =ELEC!E10 -> 2080 | I8: =ELEC!G10 -> 479 | J8: =WATER!Y12 -> 0 | K8: =WATER!AJ12 -> 0 | L8: =ELEC!B10 -> 0
A9: Beirut | B9: =B8+1 -> 8 | C9: 9 | D9: 2022 | E9: =ELEC!M11 -> 844 | F9: =ELEC!K11 -> 530 | G9: =ELEC!I11 -> 246 | H9: =ELEC!E11 -> 1570 | I9: =ELEC!G11 -> 503 | J9: =WATER!Y13 -> 0 | K9: =WATER!AJ13 -> 0 | L9: =ELEC!B11 -> 0
A10: Beirut | B10: =B9+1 -> 9 | C10: 9 | D10: 2022 | E10: =ELEC!M12 -> 0 | F10: =ELEC!K12 -> 0 | G10: =ELEC!I12 -> 0 | H10: =ELEC!E12 -> 0 | I10: =ELEC!G12 -> 0 | J10: =WATER!Y14 -> 0 | K10: =WATER!AJ14 -> 0 | L10: =ELEC!B12 -> 0
A11: Beirut | B11: =B10+1 -> 10 | C11: 9 | D11: 2022 | E11: =ELEC!M13 -> 0 | F11: =ELEC!K13 -> 0 | G11: =ELEC!I13 -> 0 | H11: =ELEC!E13 -> 0 | I11: =ELEC!G13 -> 0 | J11: =WATER!Y15 -> 0 | K11: =WATER!AJ15 -> 0 | L11: =ELEC!B13 -> 0
A12: Beirut | B12: =B11+1 -> 11 | C12: 9 | D12: 2022 | E12: =ELEC!M14 -> 892 | F12: =ELEC!K14 -> 882 | G12: =ELEC!I14 -> 262 | H12: =ELEC!E14 -> 1680 | I12: =ELEC!G14 -> 493.4 | J12: =WATER!Y16 -> 0 | K12: =WATER!AJ16 -> 0 | L12: =ELEC!B14 -> 0
A13: Beirut | B13: =B12+1 -> 12 | C13: 9 | D13: 2022 | E13: =ELEC!M15 -> 1050 | F13: =ELEC!K15 -> 480 | G13: =ELEC!I15 -> 316 | H13: =ELEC!E15 -> 820 | I13: =ELEC!G15 -> 496.6 | J13: =WATER!Y17 -> 123 | K13: =WATER!AJ17 -> 0 | L13: =ELEC!B15 -> 0
A14: Beirut | B14: =B13+1 -> 13 | C14: 9 | D14: 2022 | E14: =ELEC!M16 -> 990 | F14: =ELEC!K16 -> 464 | G14: =ELEC!I16 -> 282 | H14: =ELEC!E16 -> 730 | I14: =ELEC!G16 -> 435 | J14: =WATER!Y18 -> 0 | K14: =WATER!AJ18 -> 0 | L14: =ELEC!B16 -> 0
... A32: Beirut | B32: =B31+1 -> 31 | C32: 9 | D32: 2022 | E32: =ELEC!M34 -> 0 | F32: =ELEC!K34 -> 0 | G32: =ELEC!I34 -> 0 | H32: =ELEC!E34 -> 0 | I32: =ELEC!G34 -> 0 | J32: =WATER!Y36 -> 0 | K32: =WATER!AJ36 -> 0 | L32: =ELEC!B34 -> 0
D45: .

Sheet ELEC
A2: OOC | B2: Room OCC | D2: MDB3 | E2: MDB3/day | F2: EMDB2 | G2: EMDB2/day | H2: EMDB1 | I2: EMDB1/day | J2: MDB2 | K2: mdb2/day | L2: MDB1 | M2: MDB1/Day | N2: Total KWH | O2: KWH/Rooc | P2: Gen MHW | Q2: Gen/Day KWH | R2: EDL KWH | S2: CH1 RH | T2: RH | U2: C1h1 power | V2: CH1 Con KWH | W2: CH2 RH | X2: RH | Y2: Ch2 power | Z2: CH2 Con KWH | AA2: CH3 RH | AB2: RH | AC2: Ch3 power | AD2: CH3 Con KWH | AE2: RH total | AF2: KWH total | AG2: AVG chiller KW/Hr
A3: =[1]ELEC!$A$34 -> 0 | B3: =[1]ELEC!$B$34 -> 0 | C3: =[2]ELEC!$C$34 -> 44804 | D3: =[2]ELEC!D34 -> 356220 | E3: =[2]ELEC!E34 -> 920 | F3: =[2]ELEC!F34 -> 4159064 | G3: =[2]ELEC!G34 -> 602.8 | H3: =[2]ELEC!H34 -> 18074738 | I3: =[2]ELEC!I34 -> 568 | J3: =[2]ELEC!J34 -> 29843550 | K3: =[2]ELEC!K34 -> 878 | ... AG3: =[2]ELEC!AG34 -> 0
A4: ='General information '!F5 -> 0 | B4: =SUM(230*A4) -> 0 | C4: 44805 | D4: 356990 | E4: =D4-D3 -> 770 | F4: 4159623 | G4: =F4-F3 -> 559 | H4: 18075226 | I4: =H4-H3 -> 488 | J4: 29844438 | K4: =J4-J3 -> 888 | L4: 24652750 | M4: =L4-L3 -> 1168 | N4: =M4+K4+I4+G4+E4 -> 3873 | O4: =IF(B4>0,N4/B4,0) -> 0 | P4: 19467.342 | Q4: =(P4-P3)*1000 -> 3974 | R4: =+N4-Q4 -> -101 | S4: =S3 -> 10175 | T4: =S4-S3 -> 0 | U4: =U3 -> 429166 | V4: =U4-U3 -> 0 | W4: =W3 -> 33489 | X4: =W4-W3 -> 0 | Y4: =Y3 -> 998162 | Z4: =Y4-Y3 -> 0 | AA4: =AA3 -> 36796 | AB4: =AA4-AA3 -> 0 | AC4: =AC3 -> 1170516 | AD4: =AC4-AC3 -> 0 | AE4: =AB4+X4+T4 -> 0 | AF4: =V4+Z4+AD4 -> 0 | AG4: =IF(AE4>0,AF4/AE4,0) -> 0
A5: ='General information '!F6 -> 0 | B5: =SUM(230*A5) -> 0 | C5: 44806 | D5: =D4 -> 356990 | E5: =D5-D4 -> 0 | F5: =F4 -> 4159623 | G5: =F5-F4 -> 0 | H5: =H4 -> 18075226 | I5: =H5-H4 -> 0 | J5: =J4 -> 29844438 | K5: =J5-J4 -> 0 | L5: =L4 -> 24652750 | M5: =L5-L4 -> 0 | N5: =M5+K5+I5+G5+E5 -> 0 | O5: =IF(B5>0,N5/B5,0) -> 0 | P5: =P4 -> 19467.342 | Q5: =(P5-P4)*1000 -> 0 | R5: =N5-Q5 -> 0 | S5: =S4 -> 10175 | T5: =S5-S4 -> 0 | U5: =U4 -> 429166 | V5: =U5-U4 -> 0 | W5: =W4 -> 33489 | X5: =W5-W4 -> 0 | Y5: =Y4 -> 998162 | Z5: =Y5-Y4 -> 0 | AA5: =AA4 -> 36796 | AB5: =AA5-AA4 -> 0 | AC5: =AC4 -> 1170516 | AD5: =AC5-AC4 -> 0 | AE5: =AB5+X5+T5 -> 0 | AF5: =V5+Z5+AD5 -> 0 | AG5: =IF(AE5>0,AF5/AE5,0) -> 0
A6: ='General information '!F7 -> 0 | B6: =SUM(230*A6) -> 0 | C6: 44807 | D6: =D5 -> 356990 | E6: =D6-D5 -> 0 | F6: =F5 -> 4159623 | G6: =F6-F5 -> 0 | H6: =H5 -> 18075226 | I6: =H6-H5 -> 0 | J6: =J5 -> 29844438 | K6: =J6-J5 -> 0 | L6: =L5 -> 24652750 | M6: =L6-L5 -> 0 | N6: =M6+K6+I6+G6+E6 -> 0 | O6: =IF(B6>0,N6/B6,0) -> 0 | P6: =P5 -> 19467.342 | Q6: =(P6-P5)*1000 -> 0 | R6: =N6-Q6 -> 0 | S6: =S5 -> 10175 | T6: =S6-S5 -> 0 | U6: =U5 -> 429166 | V6: =U6-U5 -> 0 | W6: =W5 -> 33489 | X6: =W6-W5 -> 0 | Y6: =Y5 -> 998162 | Z6: =Y6-Y5 -> 0 | AA6: =AA5 -> 36796 | AB6: =AA6-AA5 -> 0 | AC6: =AC5 -> 1170516 | AD6: =AC6-AC5 -> 0 | AE6: =AB6+X6+T6 -> 0 | AF6: =V6+Z6+AD6 -> 0 | AG6: =IF(AE6>0,AF6/AE6,0) -> 0
A7: ='General information '!F8 -> 0 | B7: =SUM(230*A7) -> 0 | C7: 44808 | D7: 357720 | E7: =D7-D6 -> 730 | F7: 4160071 | G7: =F7-F6 -> 448 | H7: 18075660 | I7: =H7-H6 -> 434 | J7: 29845090 | K7: =J7-J6 -> 652 | L7: 24653606 | M7: =L7-L6 -> 856 | N7: =M7+K7+I7+G7+E7 -> 3120 | O7: =IF(B7>0,N7/B7,0) -> 0 | P7: 19470.544 | Q7: =(P7-P6)*1000 -> 3202 | R7: =N7-Q7 -> -82 | S7: =S6 -> 10175 | T7: =S7-S6 -> 0 | U7: =U6 -> 429166 | V7: =U7-U6 -> 0 | W7: =W6 -> 33489 | X7: =W7-W6 -> 0 | Y7: =Y6 -> 998162 | Z7: =Y7-Y6 -> 0 | AA7: 36796 | AB7: =AA7-AA6 -> 0 | AC7: 1170516 | AD7: =AC7-AC6 -> 0 | AE7: =AB7+X7+T7 -> 0 | AF7: =V7+Z7+AD7 -> 0 | AG7: =IF(AE7>0,AF7/AE7,0) -> 0
A8: ='General information '!F9 -> 0 | B8: =SUM(230*A8) -> 0 | C8: 44809 | D8: 358480 | E8: =D8-D7 -> 760 | F8: 4160537 | G8: =F8-F7 -> 466 | H8: 18076102 | I8: =H8-H7 -> 442 | J8: 29845658 | K8: =J8-J7 -> 568 | L8: 24654696 | M8: =L8-L7 -> 1090 | N8: =M8+K8+I8+G8+E8 -> 3326 | O8: =IF(B8>0,N8/B8,0) -> 0 | P8: 19473.965 | Q8: =(P8-P7)*1000 -> 3421 | R8: =N8-Q8 -> -95 | S8: =S7 -> 10175 | T8: =S8-S7 -> 0 | U8: =U7 -> 429166 | V8: =U8-U7 -> 0 | W8: =W7 -> 33489 | X8: =W8-W7 -> 0 | Y8: =Y7 -> 998162 | Z8: =Y8-Y7 -> 0 | AA8: =AA7 -> 36796 | AB8: =AA8-AA7 -> 0 | AC8: =AC7 -> 1170516 | AD8: =AC8-AC7 -> 0 | AE8: =AB8+X8+T8 -> 0 | AF8: =V8+Z8+AD8 -> 0 | AG8: =IF(AE8>0,AF8/AE8,0) -> 0
A9: ='General information '!F10 -> 0 | B9: =SUM(230*A9) -> 0 | C9: 44810 | D9: 359880 | E9: =D9-D8 -> 1400 | F9: 4161045 | G9: =F9-F8 -> 508 | H9: 18076556 | I9: =H9-H8 -> 454 | J9: 29847170 | K9: =J9-J8 -> 1512 | L9: 24655832 | M9: =L9-L8 -> 1136 | N9: =M9+K9+I9+G9+E9 -> 5010 | O9: =IF(B9>0,N9/B9,0) -> 0 | P9: 19479.102 | Q9: =(P9-P8)*1000 -> 5137 | R9: =N9-Q9 -> -127 | S9: =S8 -> 10175 | T9: =S9-S8 -> 0 | U9: =U8 -> 429166 | V9: =U9-U8 -> 0 | W9: 33492 | X9: =W9-W8 -> 3 | Y9: 998816 | Z9: =Y9-Y8 -> 654 | AA9: =AA8 -> 36796 | AB9: =AA9-AA8 -> 0 | AC9: =AC8 -> 1170516 | AD9: =AC9-AC8 -> 0 | AE9: =AB9+X9+T9 -> 3 | AF9: =V9+Z9+AD9 -> 654 | AG9: =IF(AE9>0,AF9/AE9,0) -> 218
A10: ='General information '!F11 -> 0 | B10: =SUM(230*A10) -> 0 | C10: 44811 | D10: 361960 | E10: =D10-D9 -> 2080 | F10: 4161524 | G10: =F10-F9 -> 479 | H10: 18076882 | I10: =H10-H9 -> 326 | J10: 29848102 | K10: =J10-J9 -> 932 | L10: 24656786 | M10: =L10-L9 -> 954 | N10: =M10+K10+I10+G10+E10 -> 4771 | O10: =IF(B10>0,N10/B10,0) -> 0 | P10: 19483.965 | Q10: =(P10-P9)*1000 -> 4863 | R10: =N10-Q10 -> -92 | S10: =S9 -> 10175 | T10: =S10-S9 -> 0 | U10: =U9 -> 429166 | V10: =U10-U9 -> 0 | W10: 33493 | X10: =W10-W9 -> 1 | Y10: 999111 | Z10: =Y10-Y9 -> 295 | AA10: 36798 | AB10: =AA10-AA9 -> 2 | AC10: 1171060 | AD10: =AC10-AC9 -> 544 | AE10: =AB10+X10+T10 -> 3 | AF10: =V10+Z10+AD10 -> 839 | AG10: =IF(AE10>0,AF10/AE10,0) -> 279.66667
A11: ='General information '!F12 -> 0 | B11: =SUM(230*A11) -> 0 | C11: 44812 | D11: 363530 | E11: =D11-D10 -> 1570 | F11: 4162027 | G11: =F11-F10 -> 503 | H11: 18077128 | I11: =H11-H10 -> 246 | J11: 29848632 | K11: =J11-J10 -> 530 | L11: 24657630 | M11: =L11-L10 -> 844 | N11: =M11+K11+I11+G11+E11 -> 3693 | O11: =IF(B11>0,N11/B11,0) -> 0 | P11: 19487.754 | Q11: =(P11-P10)*1000 -> 3789 | R11: =N11-Q11 -> -96 | S11: =S10 -> 10175 | T11: =S11-S10 -> 0 | U11: =U10 -> 429166 | V11: =U11-U10 -> 0 | W11: =W10 -> 33493 | X11: =W11-W10 -> 0 | Y11: =Y10 -> 999111 | Z11: =Y11-Y10 -> 0 | AA11: =AA10 -> 36798 | AB11: =AA11-AA10 -> 0 | AC11: =AC10 -> 1171060 | AD11: =AC11-AC10 -> 0 | AE11: =AB11+X11+T11 -> 0 | AF11: =V11+Z11+AD11 -> 0 | AG11: =IF(AE11>0,AF11/AE11,0) -> 0
A12: ='General information '!F13 -> 0 | B12: =SUM(230*A12) -> 0 | C12: 44813 | D12: =D11 -> 363530 | E12: =D12-D11 -> 0 | F12: =F11 -> 4162027 | G12: =F12-F11 -> 0 | H12: =H11 -> 18077128 | I12: =H12-H11 -> 0 | J12: =J11 -> 29848632 | K12: =J12-J11 -> 0 | L12: =L11 -> 24657630 | M12: =L12-L11 -> 0 | N12: =M12+K12+I12+G12+E12 -> 0 | O12: =IF(B12>0,N12/B12,0) -> 0 | P12: =P11 -> 19487.754 | Q12: =(P12-P11)*1000 -> 0 | R12: =N12-Q12 -> 0 | S12: =S11 -> 10175 | T12: =S12-S11 -> 0 | U12: =U11 -> 429166 | V12: =U12-U11 -> 0 | W12: =W11 -> 33493 | X12: =W12-W11 -> 0 | Y12: =Y11 -> 999111 | Z12: =Y12-Y11 -> 0 | AA12: =AA11 -> 36798 | AB12: =AA12-AA11 -> 0 | AC12: =AC11 -> 1171060 | AD12: =AC12-AC11 -> 0 | AE12: =AB12+X12+T12 -> 0 | AF12: =V12+Z12+AD12 -> 0 | AG12: =IF(AE12>0,AF12/AE12,0) -> 0
A13: ='General information '!F14 -> 0 | B13: =SUM(230*A13) -> 0 | C13: 44814 | D13: =D12 -> 363530 | E13: =D13-D12 -> 0 | F13: =F12 -> 4162027 | G13: =F13-F12 -> 0 | H13: =H12 -> 18077128 | I13: =H13-H12 -> 0 | J13: =J12 -> 29848632 | K13: =J13-J12 -> 0 | L13: =L12 -> 24657630 | M13: =L13-L12 -> 0 | N13: =M13+K13+I13+G13+E13 -> 0 | O13: =IF(B13>0,N13/B13,0) -> 0 | P13: =P12 -> 19487.754 | Q13: =(P13-P12)*1000 -> 0 | R13: =N13-Q13 -> 0 | S13: =S12 -> 10175 | T13: =S13-S12 -> 0 | U13: =U12 -> 429166 | V13: =U13-U12 -> 0 | W13: =W12 -> 33493 | X13: =W13-W12 -> 0 | Y13: =Y12 -> 999111 | Z13: =Y13-Y12 -> 0 | AA13: =AA12 -> 36798 | AB13: =AA13-AA12 -> 0 | AC13: =AC12 -> 1171060 | AD13: =AC13-AC12 -> 0 | AE13: =AB13+X13+T13 -> 0 | AF13: =V13+Z13+AD13 -> 0 | AG13: =IF(AE13>0,AF13/AE13,0) -> 0
A14: ='General information '!F15 -> 0 | B14: =SUM(230*A14) -> 0 | C14: 44815 | D14: 365210 | E14: =D14-D13 -> 1680 | F14: 4162520.4 | G14: =F14-F13 -> 493.4 | H14: 18077390 | I14: =H14-H13 -> 262 | J14: 29849514 | K14: =J14-J13 -> 882 | L14: 24658522 | M14: =L14-L13 -> 892 | N14: =M14+K14+I14+G14+E14 -> 4209.4 | O14: =IF(B14>0,N14/B14,0) -> 0 | P14: 19492.051 | Q14: =(P14-P13)*1000 -> 4297 | R14: =N14-Q14 -> -87.6 | S14: =S13 -> 10175 | T14: =S14-S13 -> 0 | U14: =U13 -> 429166 | V14: =U14-U13 -> 0 | W14: 33495 | X14: =W14-W13 -> 2 | Y14: 999495 | Z14: =Y14-Y13 -> 384 | AA14: =AA13 -> 36798 | AB14: =AA14-AA13 -> 0 | AC14: =AC13 -> 1171060 | AD14: =AC14-AC13 -> 0 | AE14: =AB14+X14+T14 -> 2 | AF14: =V14+Z14+AD14 -> 384 | AG14: =IF(AE14>0,AF14/AE14,0) -> 192
A15: ='General information '!F16 -> 0 | B15: =SUM(230*A15) -> 0 | C15: 44816 | D15: 366030 | E15: =D15-D14 -> 820 | F15: 4163017 | G15: =F15-F14 -> 496.6 | H15: 18077706 | I15: =H15-H14 -> 316 | J15: 29849994 | K15: =J15-J14 -> 480 | L15: 24659572 | M15: =L15-L14 -> 1050 | N15: =M15+K15+I15+G15+E15 -> 3162.6 | O15: =IF(B15>0,N15/B15,0) -> 0 | P15: 19495.307 | Q15: =(P15-P14)*1000 -> 3256 | R15: =N15-Q15 -> -93.4 | S15: =S14 -> 10175 | T15: =S15-S14 -> 0 | U15: =U14 -> 429166 | V15: =U15-U14 -> 0 | W15: =W14 -> 33495 | X15: =W15-W14 -> 0 | Y15: =Y14 -> 999495 | Z15: =Y15-Y14 -> 0 | AA15: =AA14 -> 36798 | AB15: =AA15-AA14 -> 0 | AC15: =AC14 -> 1171060 | AD15: =AC15-AC14 -> 0 | AE15: =AB15+X15+T15 -> 0 | AF15: =V15+Z15+AD15 -> 0 | AG15: =IF(AE15>0,AF15/AE15,0) -> 0
A16: ='General information '!F17 -> 0 | B16: =SUM(230*A16) -> 0 | C16: 44817 | D16: 366760 | E16: =D16-D15 -> 730 | F16: 4163452 | G16: =F16-F15 -> 435 | H16: 18077988 | I16: =H16-H15 -> 282 | J16: 29850458 | K16: =J16-J15 -> 464 | L16: 24660562 | M16: =L16-L15 -> 990 | N16: =M16+K16+I16+G16+E16 -> 2901 | O16: =IF(B16>0,N16/B16,0) -> 0 | P16: 19498.302 | Q16: =(P16-P15)*1000 -> 2995 | R16: =N16-Q16 -> -94 | S16: =S15 -> 10175 | T16: =S16-S15 -> 0 | U16: =U15 -> 429166 | V16: =U16-U15 -> 0 | W16: =W15 -> 33495 | X16: =W16-W15 -> 0 | Y16: =Y15 -> 999495 | Z16: =Y16-Y15 -> 0 | AA16: =AA15 -> 36798 | AB16: =AA16-AA15 -> 0 | AC16: =AC15 -> 1171060 | AD16: =AC16-AC15 -> 0 | AE16: =AB16+X16+T16 -> 0 | AF16: =V16+Z16+AD16 -> 0 | AG16: =IF(AE16>0,AF16/AE16,0) -> 0
A17: ='General information '!F18 -> 0 | B17: =SUM(230*A17) -> 0 | C17: 44818 | D17: 367530 | E17: =D17-D16 -> 770 | F17: 4163824.4 | G17: =F17-F16 -> 372.4 | H17: 18078286 | I17: =H17-H16 -> 298 | J17: 29850998 | K17: =J17-J16 -> 540 | L17: 24661562 | M17: =L17-L16 -> 1000 | N17: =M17+K17+I17+G17+E17 -> 2980.4 | O17: =IF(B17>0,N17/B17,0) -> 0 | P17: 19501.461 | Q17: =(P17-P16)*1000 -> 3159 | R17: =N17-Q17 -> -178.6 | S17: =S16 -> 10175 | T17: =S17-S16 -> 0 | U17: =U16 -> 429166 | V17: =U17-U16 -> 0 | W17: =W16 -> 33495 | X17: =W17-W16 -> 0 | Y17: =Y16 -> 999495 | Z17: =Y17-Y16 -> 0 | AA17: =AA16 -> 36798 | AB17: =AA17-AA16 -> 0 | AC17: =AC16 -> 1171060 | AD17: =AC17-AC16 -> 0 | AE17: =AB17+X17+T17 -> 0 | AF17: =V17+Z17+AD17 -> 0 | AG17: =IF(AE17>0,AF17/AE17,0) -> 0
A18: ='General information '!F19 -> 0 | B18: =SUM(230*A18) -> 0 | C18: 44819 | D18: 368280 | E18: =D18-D17 -> 750 | F18: 4164380 | G18: =F18-F17 -> 555.6 | H18: 18078578 | I18: =H18-H17 -> 292 | J18: 29851332 | K18: =J18-J17 -> 334 | L18: 24662550 | M18: =L18-L17 -> 988 | N18: =M18+K18+I18+G18+E18 -> 2919.6 | O18: =IF(B18>0,N18/B18,0) -> 0 | P18: =P17 -> 19501.461 | Q18: =(P18-P17)*1000 -> 0 | R18: =N18-Q18 -> 2919.6 | S18: =S17 -> 10175 | T18: =S18-S17 -> 0 | U18: =U17 -> 429166 | V18: =U18-U17 -> 0 | W18: =W17 -> 33495 | X18: =W18-W17 -> 0 | Y18: =Y17 -> 999495 | Z18: =Y18-Y17 -> 0 | AA18: =AA17 -> 36798 | AB18: =AA18-AA17 -> 0 | AC18: =AC17 -> 1171060 | AD18: =AC18-AC17 -> 0 | AE18: =AB18+X18+T18 -> 0 | AF18: =V18+Z18+AD18 -> 0 | AG18: =IF(AE18>0,AF18/AE18,0) -> 0
A19: ='General information '!F20 -> 0 | B19: =SUM(230*A19) -> 0 | C19: 44820 | D19: =D18 -> 368280 | E19: =D19-D18 -> 0 | F19: =F18 -> 4164380 | G19: =F19-F18 -> 0 | H19: =H18 -> 18078578 | I19: =H19-H18 -> 0 | J19: =J18 -> 29851332 | K19: =J19-J18 -> 0 | L19: =L18 -> 24662550 | M19: =L19-L18 -> 0 | N19: =M19+K19+I19+G19+E19 -> 0 | O19: =IF(B19>0,N19/B19,0) -> 0 | P19: =P18 -> 19501.461 | Q19: =(P19-P18)*1000 -> 0 | R19: =N19-Q19 -> 0 | S19: =S18 -> 10175 | T19: =S19-S18 -> 0 | U19: =U18 -> 429166 | V19: =U19-U18 -> 0 | W19: =W18 -> 33495 | X19: =W19-W18 -> 0 | Y19: =Y18 -> 999495 | Z19: =Y19-Y18 -> 0 | AA19: =AA18 -> 36798 | AB19: =AA19-AA18 -> 0 | AC19: =AC18 -> 1171060 | AD19: =AC19-AC18 -> 0 | AE19: =AB19+X19+T19 -> 0 | AF19: =V19+Z19+AD19 -> 0 | AG19: =IF(AE19>0,AF19/AE19,0) -> 0
A20: ='General information '!F21 -> 0 | B20: =SUM(230*A20) -> 0 | C20: 44821 | D20: =D19 -> 368280 | E20: =D20-D19 -> 0 | F20: =F19 -> 4164380 | G20: =F20-F19 -> 0 | H20: =H19 -> 18078578 | I20: =H20-H19 -> 0 | J20: =J19 -> 29851332 | K20: =J20-J19 -> 0 | L20: =L19 -> 24662550 | M20: =L20-L19 -> 0 | N20: =M20+K20+I20+G20+E20 -> 0 | O20: =IF(B20>0,N20/B20,0) -> 0 | P20: =P19 -> 19501.461 | Q20: =(P20-P19)*1000 -> 0 | R20: =N20-Q20 -> 0 | S20: =S19 -> 10175 | T20: =S20-S19 -> 0 | U20: =U19 -> 429166 | V20: =U20-U19 -> 0 | W20: =W19 -> 33495 | X20: =W20-W19 -> 0 | Y20: =Y19 -> 999495 | Z20: =Y20-Y19 -> 0 | AA20: =AA19 -> 36798 | AB20: =AA20-AA19 -> 0 | AC20: =AC19 -> 1171060 | AD20: =AC20-AC19 -> 0 | AE20: =AB20+X20+T20 -> 0 | AF20: =V20+Z20+AD20 -> 0 | AG20: =IF(AE20>0,AF20/AE20,0) -> 0
A21: ='General information '!F22 -> 0 | B21: =SUM(230*A21) -> 0 | C21: 44822 | D21: 369080 | E21: =D21-D20 -> 800 | F21: 4164872 | G21: =F21-F20 -> 492 | H21: 18078910 | I21: =H21-H20 -> 332 | J21: 29851834 | K21: =J21-J20 -> 502 | L21: 24663598 | M21: =L21-L20 -> 1048 | N21: =M21+K21+I21+G21+E21 -> 3174 | O21: =IF(B21>0,N21/B21,0) -> 0 | P21: 19507.623 | Q21: =(P21-P20)*1000 -> 6162 | R21: =N21-Q21 -> -2988 | S21: =S20 -> 10175 | T21: =S21-S20 -> 0 | U21: =U20 -> 429166 | V21: =U21-U20 -> 0 | W21: 33495 | X21: =W21-W20 -> 0 | Y21: 998162 | Z21: =Y21-Y20 -> -1333 | AA21: =AA20 -> 36798 | AB21: =AA21-AA20 -> 0 | AC21: =AC20 -> 1171060 | AD21: =AC21-AC20 -> 0 | AE21: =AB21+X21+T21 -> 0 | AF21: =V21+Z21+AD21 -> -1333 | AG21: =IF(AE21>0,AF21/AE21,0) -> 0
A22: ='General information '!F23 -> 0 | B22: =SUM(230*A22) -> 0 | C22: 44823 | D22: 369810 | E22: =D22-D21 -> 730 | F22: 4165314 | G22: =F22-F21 -> 442 | H22: 18079196 | I22: =H22-H21 -> 286 | J22: 29852314 | K22: =J22-J21 -> 480 | L22: 24664422 | M22: =L22-L21 -> 824 | N22: =M22+K22+I22+G22+E22 -> 2762 | O22: =IF(B22>0,N22/B22,0) -> 0 | P22: 19510.451 | Q22: =(P22-P21)*1000 -> 2828 | R22: =N22-Q22 -> -66 | S22: =S21 -> 10175 | T22: =S22-S21 -> 0 | U22: =U21 -> 429166 | V22: =U22-U21 -> 0 | W22: =W21 -> 33495 | X22: =W22-W21 -> 0 | Y22: =Y21 -> 998162 | Z22: =Y22-Y21 -> 0 | AA22: =AA21 -> 36798 | AB22: =AA22-AA21 -> 0 | AC22: =AC21 -> 1171060 | AD22: =AC22-AC21 -> 0 | AE22: =AB22+X22+T22 -> 0 | AF22: =V22+Z22+AD22 -> 0 | AG22: =IF(AE22>0,AF22/AE22,0) -> 0
A23: ='General information '!F24 -> 0 | B23: =SUM(230*A23) -> 0 | C23: 44824 | D23: 371130 | E23: =D23-D22 -> 1320 | F23: 4165762 | G23: =F23-F22 -> 448 | H23: 18079484 | I23: =H23-H22 -> 288 | J23: 29853092 | K23: =J23-J22 -> 778 | L23: 24665358 | M23: =L23-L22 -> 936 | N23: =M23+K23+I23+G23+E23 -> 3770 | O23: =IF(B23>0,N23/B23,0) -> 0 | P23: 19514.301 | Q23: =(P23-P22)*1000 -> 3850 | R23: =N23-Q23 -> -80 | S23: =S22 -> 10175 | T23: =S23-S22 -> 0 | U23: =U22 -> 429166 | V23: =U23-U22 -> 0 | W23: 33495 | X23: =W23-W22 -> 0 | Y23: =Y22 -> 998162 | Z23: =Y23-Y22 -> 0 | AA23: 36801 | AB23: =AA23-AA22 -> 3 | AC23: 1171535 | AD23: =AC23-AC22 -> 475 | AE23: =AB23+X23+T23 -> 3 | AF23: =V23+Z23+AD23 -> 475 | AG23: =IF(AE23>0,AF23/AE23,0) -> 158.33333
A24: ='General information '!F25 -> 0 | B24: =SUM(230*A24) -> 0 | C24: 44825 | D24: 371940 | E24: =D24-D23 -> 810 | F24: 4166150 | G24: =F24-F23 -> 388 | H24: 18079758 | I24: =H24-H23 -> 274 | J24: 29853708 | K24: =J24-J23 -> 616 | L24: 24666126 | M24: =L24-L23 -> 768 | N24: =M24+K24+I24+G24+E24 -> 2856 | O24: =IF(B24>0,N24/B24,0) -> 0 | P24: 19517.226 | Q24: =(P24-P23)*1000 -> 2925 | R24: =N24-Q24 -> -69 | S24: =S23 -> 10175 | T24: =S24-S23 -> 0 | U24: =U23 -> 429166 | V24: =U24-U23 -> 0 | W24: 33498 | X24: =W24-W23 -> 3 | Y24: 999659 | Z24: =Y24-Y23 -> 1497 | AA24: =AA23 -> 36801 | AB24: =AA24-AA23 -> 0 | AC24: =AC23 -> 1171535 | AD24: =AC24-AC23 -> 0 | AE24: =AB24+X24+T24 -> 3 | AF24: =V24+Z24+AD24 -> 1497 | AG24: =IF(AE24>0,AF24/AE24,0) -> 499
A25: ='General information '!F26 -> 0 | B25: =SUM(230*A25) -> 0 | C25: 44826 | D25: 372650 | E25: =D25-D24 -> 710 | F25: 4166326 | G25: =F25-F24 -> 176 | H25: 18080022 | I25: =H25-H24 -> 264 | J25: 29854318 | K25: =J25-J24 -> 610 | L25: 24666876 | M25: =L25-L24 -> 750 | N25: =M25+K25+I25+G25+E25 -> 2510 | O25: =IF(B25>0,N25/B25,0) -> 0 | P25: 19520.006 | Q25: =(P25-P24)*1000 -> 2780 | R25: =N25-Q25 -> -270 | S25: =S24 -> 10175 | T25: =S25-S24 -> 0 | U25: =U24 -> 429166 | V25: =U25-U24 -> 0 | W25: =W24 -> 33498 | X25: =W25-W24 -> 0 | Y25: =Y24 -> 999659 | Z25: =Y25-Y24 -> 0 | AA25: =AA24 -> 36801 | AB25: =AA25-AA24 -> 0 | AC25: =AC24 -> 1171535 | AD25: =AC25-AC24 -> 0 | AE25: =AB25+X25+T25 -> 0 | AF25: =V25+Z25+AD25 -> 0 | AG25: =IF(AE25>0,AF25/AE25,0) -> 0
A26: ='General information '!F27 -> 0 | B26: =SUM(230*A26) -> 0 | C26: 44827 | D26: =D25 -> 372650 | E26: =D26-D25 -> 0 | F26: =F25 -> 4166326 | G26: =F26-F25 -> 0 | H26: =H25 -> 18080022 | I26: =H26-H25 -> 0 | J26: =J25 -> 29854318 | K26: =J26-J25 -> 0 | L26: =L25 -> 24666876 | M26: =L26-L25 -> 0 | N26: =M26+K26+I26+G26+E26 -> 0 | O26: =IF(B26>0,N26/B26,0) -> 0 | P26: =P25 -> 19520.006 | Q26: =(P26-P25)*1000 -> 0 | R26: =N26-Q26 -> 0 | S26: =S25 -> 10175 | T26: =S26-S25 -> 0 | U26: =U25 -> 429166 | V26: =U26-U25 -> 0 | W26: =W25 -> 33498 | X26: =W26-W25 -> 0 | Y26: =Y25 -> 999659 | Z26: =Y26-Y25 -> 0 | AA26: =AA25 -> 36801 | AB26: =AA26-AA25 -> 0 | AC26: =AC25 -> 1171535 | AD26: =AC26-AC25 -> 0 | AE26: =AB26+X26+T26 -> 0 | AF26: =V26+Z26+AD26 -> 0 | AG26: =IF(AE26>0,AF26/AE26,0) -> 0
A27: ='General information '!F28 -> 0 | B27: =SUM(230*A27) -> 0 | C27: 44828 | D27: =D26 -> 372650 | E27: =D27-D26 -> 0 | F27: =F26 -> 4166326 | G27: =F27-F26 -> 0 | H27: =H26 -> 18080022 | I27: =H27-H26 -> 0 | J27: =J26 -> 29854318 | K27: =J27-J26 -> 0 | L27: =L26 -> 24666876 | M27: =L27-L26 -> 0 | N27: =M27+K27+I27+G27+E27 -> 0 | O27: =IF(B27>0,N27/B27,0) -> 0 | P27: =P26 -> 19520.006 | Q27: =(P27-P26)*1000 -> 0 | R27: =N27-Q27 -> 0 | S27: =S26 -> 10175 | T27: =S27-S26 -> 0 | U27: =U26 -> 429166 | V27: =U27-U26 -> 0 | W27: =W26 -> 33498 | X27: =W27-W26 -> 0 | Y27: =Y26 -> 999659 | Z27: =Y27-Y26 -> 0 | AA27: =AA26 -> 36801 | AB27: =AA27-AA26 -> 0 | AC27: =AC26 -> 1171535 | AD27: =AC27-AC26 -> 0 | AE27: =AB27+X27+T27 -> 0 | AF27: =V27+Z27+AD27 -> 0 | AG27: =IF(AE27>0,AF27/AE27,0) -> 0
A28: ='General information '!F29 -> 0 | B28: =SUM(230*A28) -> 0 | C28: 44829 | D28: 373380 | E28: =D28-D27 -> 730 | F28: 4166951 | G28: =F28-F27 -> 625 | H28: 18080306 | I28: =H28-H27 -> 284 | J28: 29855006 | K28: =J28-J27 -> 688 | L28: 24667684 | M28: =L28-L27 -> 808 | N28: =M28+K28+I28+G28+E28 -> 3135 | O28: =IF(B28>0,N28/B28,0) -> 0 | P28: 19522.791 | Q28: =(P28-P27)*1000 -> 2785 | R28: =N28-Q28 -> 350 | S28: =S27 -> 10175 | T28: =S28-S27 -> 0 | U28: =U27 -> 429166 | V28: =U28-U27 -> 0 | W28: =W27 -> 33498 | X28: =W28-W27 -> 0 | Y28: =Y27 -> 999659 | Z28: =Y28-Y27 -> 0 | AA28: =AA27 -> 36801 | AB28: =AA28-AA27 -> 0 | AC28: =AC27 -> 1171535 | AD28: =AC28-AC27 -> 0 | AE28: =AB28+X28+T28 -> 0 | AF28: =V28+Z28+AD28 -> 0 | AG28: =IF(AE28>0,AF28/AE28,0) -> 0
A29: ='General information '!F30 -> 0 | B29: =SUM(230*A29) -> 0 | C29: 44830 | D29: 374110 | E29: =D29-D28 -> 730 | F29: 4167365 | G29: =F29-F28 -> 414 | H29: 18080706 | I29: =H29-H28 -> 400 | J29: 29855602 | K29: =J29-J28 -> 596 | L29: 24668538 | M29: =L29-L28 -> 854 | N29: =M29+K29+I29+G29+E29 -> 2994 | O29: =IF(B29>0,N29/B29,0) -> 0 | P29: 19525.873 | Q29: =(P29-P28)*1000 -> 3082 | R29: =N29-Q29 -> -88 | S29: =S28 -> 10175 | T29: =S29-S28 -> 0 | U29: =U28 -> 429166 | V29: =U29-U28 -> 0 | W29: =W28 -> 33498 | X29: =W29-W28 -> 0 | Y29: =Y28 -> 999659 | Z29: =Y29-Y28 -> 0 | AA29: =AA28 -> 36801 | AB29: =AA29-AA28 -> 0 | AC29: =AC28 -> 1171535 | AD29: =AC29-AC28 -> 0 | AE29: =AB29+X29+T29 -> 0 | AF29: =V29+Z29+AD29 -> 0 | AG29: =IF(AE29>0,AF29/AE29,0) -> 0
A30: ='General information '!F31 -> 0 | B30: =SUM(230*A30) -> 0 | C30: 44831 | D30: 375010 | E30: =D30-D29 -> 900 | F30: 4167871 | G30: =F30-F29 -> 506 | H30: 18081195 | I30: =H30-H29 -> 489 | J30: 29856392 | K30: =J30-J29 -> 790 | L30: 24669454 | M30: =L30-L29 -> 916 | N30: =M30+K30+I30+G30+E30 -> 3601 | O30: =IF(B30>0,N30/B30,0) -> 0 | P30: 19529.549 | Q30: =(P30-P29)*1000 -> 3676 | R30: =N30-Q30 -> -75 | S30: =S29 -> 10175 | T30: =S30-S29 -> 0 | U30: =U29 -> 429166 | V30: =U30-U29 -> 0 | W30: =W29 -> 33498 | X30: =W30-W29 -> 0 | Y30: =Y29 -> 999659 | Z30: =Y30-Y29 -> 0 | AA30: =AA29 -> 36801 | AB30: =AA30-AA29 -> 0 | AC30: =AC29 -> 1171535 | AD30: =AC30-AC29 -> 0 | AE30: =AB30+X30+T30 -> 0 | AF30: =V30+Z30+AD30 -> 0 | AG30: =IF(AE30>0,AF30/AE30,0) -> 0
A31: ='General information '!F32 -> 0 | B31: =SUM(230*A31) -> 0 | C31: 44832 | D31: 375660 | E31: =D31-D30 -> 650 | F31: 4168217 | G31: =F31-F30 -> 346 | H31: 18081530 | I31: =H31-H30 -> 335 | J31: 29856664 | K31: =J31-J30 -> 272 | L31: 24670086 | M31: =L31-L30 -> 632 | N31: =M31+K31+I31+G31+E31 -> 2235 | O31: =IF(B31>0,N31/B31,0) -> 0 | P31: 19531.831 | Q31: =(P31-P30)*1000 -> 2282 | R31: =N31-Q31 -> -47 | S31: =S30 -> 10175 | T31: =S31-S30 -> 0 | U31: =U30 -> 429166 | V31: =U31-U30 -> 0 | W31: =W30 -> 33498 | X31: =W31-W30 -> 0 | Y31: =Y30 -> 999659 | Z31: =Y31-Y30 -> 0 | AA31: =AA30 -> 36801 | AB31: =AA31-AA30 -> 0 | AC31: =AC30 -> 1171535 | AD31: =AC31-AC30 -> 0 | AE31: =AB31+X31+T31 -> 0 | AF31: =V31+Z31+AD31 -> 0 | AG31: =IF(AE31>0,AF31/AE31,0) -> 0
A32: ='General information '!F33 -> 0 | B32: =SUM(230*A32) -> 0 | C32: 44833 | D32: 376630 | E32: =D32-D31 -> 970 | F32: 4168766 | G32: =F32-F31 -> 549 | H32: 18082090 | I32: =H32-H31 -> 560 | J32: 29857148 | K32: =J32-J31 -> 484 | L32: 24671166 | M32: =L32-L31 -> 1080 | N32: =M32+K32+I32+G32+E32 -> 3643 | O32: =IF(B32>0,N32/B32,0) -> 0 | P32: 19535.339 | Q32: =(P32-P31)*1000 -> 3508 | R32: =N32-Q32 -> 135 | S32: =S31 -> 10175 | T32: =S32-S31 -> 0 | U32: =U31 -> 429166 | V32: =U32-U31 -> 0 | W32: =W31 -> 33498 | X32: =W32-W31 -> 0 | Y32: =Y31 -> 999659 | Z32: =Y32-Y31 -> 0 | AA32: =AA31 -> 36801 | AB32: =AA32-AA31 -> 0 | AC32: =AC31 -> 1171535 | AD32: =AC32-AC31 -> 0 | AE32: =AB32+X32+T32 -> 0 | AF32: =V32+Z32+AD32 -> 0 | AG32: =IF(AE32>0,AF32/AE32,0) -> 0
A33: ='General information '!F34 -> 0 | B33: =SUM(230*A33) -> 0 | C33: 44834 | D33: =D32 -> 376630 | E33: =D33-D32 -> 0 | F33: =F32 -> 4168766 | G33: =F33-F32 -> 0 | H33: =H32 -> 18082090 | I33: =H33-H32 -> 0 | J33: =J32 -> 29857148 | K33: =J33-J32 -> 0 | L33: =L32 -> 24671166 | M33: =L33-L32 -> 0 | N33: =M33+K33+I33+G33+E33 -> 0 | O33: =IF(B33>0,N33/B33,0) -> 0 | P33: =P32 -> 19535.339 | Q33: =(P33-P32)*1000 -> 0 | R33: =N33-Q33 -> 0 | S33: =S32 -> 10175 | T33: =S33-S32 -> 0 | U33: =U32 -> 429166 | V33: =U33-U32 -> 0 | W33: =W32 -> 33498 | X33: =W33-W32 -> 0 | Y33: =Y32 -> 999659 | Z33: =Y33-Y32 -> 0 | AA33: =AA32 -> 36801 | AB33: =AA33-AA32 -> 0 | AC33: =AC32 -> 1171535 | AD33: =AC33-AC32 -> 0 | AE33: =AB33+X33+T33 -> 0 | AF33: =V33+Z33+AD33 -> 0 | AG33: =IF(AE33>0,AF33/AE33,0) -> 0
A34: ='General information '!F35 -> 0 | B34: =SUM(230*A34) -> 0 | C34: 44835 | D34: =D33 -> 376630 | E34: =D34-D33 -> 0 | F34: =F33 -> 4168766 | G34: =F34-F33 -> 0 | H34: =H33 -> 18082090 | I34: =H34-H33 -> 0 | J34: =J33 -> 29857148 | K34: =J34-J33 -> 0 | L34: =L33 -> 24671166 | M34: =L34-L33 -> 0 | N34: =M34+K34+I34+G34+E34 -> 0 | O34: =IF(B34>0,N34/B34,0) -> 0 | P34: =P33 -> 19535.339 | Q34: =(P34-P33)*1000 -> 0 | R34: =N34-Q34 -> 0 | S34: =S33 -> 10175 | T34: =S34-S33 -> 0 | U34: =U33 -> 429166 | V34: =U34-U33 -> 0 | W34: =W33 -> 33498 | X34: =W34-W33 -> 0 | Y34: =Y33 -> 999659 | Z34: =Y34-Y33 -> 0 | AA34: =AA33 -> 36801 | AB34: =AA34-AA33 -> 0 | AC34: =AC33 -> 1171535 | AD34: =AC34-AC33 -> 0 | AE34: =AB34+X34+T34 -> 0 | AF34: =V34+Z34+AD34 -> 0 | AG34: =IF(AE34>0,AF34/AE34,0) -> 0

Sheet B5
F1: Boiler A | J1: =J36 -> 67.333333 | K1: Boiler B | P1: Boiler C | V1: Boiler | X1: SteamA | AC1: SteamB | AH1: Steam | AI1: Boiler & steam | AL1: Total Boiler Runing H | AM1: Total Steam Runing H | AN1: GAS1 % | AO1: GAS1/L | AP1: GAS2% | AQ1: Gas2/L | AR1: GAS3% | AS1: GAS3/L | AU1: Gas Cons | AV1: Delivery | AW1: Cost/L
B2: Level Tank Gen | C2: Level tank Boiler | D2: Daily Cons Bo. | E2: Boiler litter | F2: Boiler A | G2: Run Hr a | H2: Boiler A fuel | I2: Daily consumption | J2: AVG | K2: index Run H | L2: Run Hrb | M2: Boiler B Fuel | O2: Daily consumption | P2: Boiler C | S2: Run C | U2: Total RH | V2: Total Fuel | X2: SteamA | Y2: Run SA | Z2: Steam A Conter | AA2: Liters | AC2: SteamB | AD2: Run SteamB | AE2: Steam B Conter | AF2: SB Litters | AG2: Avg | AH2: Total Fuel | AI2: Total Fuel
S3: 0
A4: =[2]B5!$A$35 -> 44804 | B4: =[2]B5!B35 -> 199 | C4: =[2]B5!C35 -> 206 | D4: =[2]B5!D35 -> 5 | E4: =[2]B5!E35 -> 41.9 | F4: =[2]B5!F35 -> 2278 | G4: =[2]B5!G35 -> 0 | H4: =[2]B5!H35 -> 46144 | I4: =[2]B5!I35 -> 0 | ... AX4: =[2]B5!AX35 -> 0.8
A5: =ELEC!C4 -> 44805 | B5: 194.5 | C5: 201 | D5: =C4-C5 -> 5 | E5: =D5*8.38 -> 41.9 | F5: =F4 -> 2278 | G5: =F5-F4 -> 0 | H5: =H4 -> 46144 | I5: =SUM(H5-H4) -> 0 | J5: 1 | K5: =K4 -> 2453 | L5: =K5-K4 -> 0 | M5: 182441 | N5: =M5-M4 -> 25 | O5: =O4 -> 1869 | P5: =P4 -> 2226 | Q5: =Q4 -> 186049 | R5: =Q5-Q4 -> 0 | S5: =SUM(P5-P4) -> 0 | T5: =SUM(S5*$T$2) -> 0 | U5: =SUM(G5+L5+S5) -> 0 | V5: =R5+N5+I5:I5 -> 25 | W5: =SUM(V5/U5) -> #DIV/0! | X5: =X4 -> 2492 | Y5: =X5-X4 -> 0 | Z5: =Z4 -> 140886 | AA5: =Z5-Z4 -> 0 | AB5: =SUM(Y5*$AB$2) -> 0 | AC5: =AC4 -> 1948 | AD5: =AC5-AC4 -> 0 | AE5: =AE4 -> 366628 | AF5: =AE5-AE4 -> 0 | AG5: =IF(AD5>0,AF5/AD5,0) -> 0 | AH5: =AF5+AA5 -> 0 | AI5: =SUM(AH5+V5) -> 25 | AJ5: =-tanks!AW6 -> 25 | AK5: =SUM(AJ5-AI5) -> 0 | AL5: =S5+L5+G5 -> 0 | AM5: =Y5+AD5 -> 0 | AN5: =AN4 -> 66 | AO5: =(AN5/100)*3000 -> 1980 | AP5: =AP4 -> 31 | AQ5: =(AP5/100)*3000 -> 930 | AR5: =AR4 -> 73 | AS5: =(AR5/100)*3000 -> 2190 | AT5: =SUM(AO5+AQ5+AS5) -> 5100 | AU5: =AT4-AT5+AV5 -> 0 | AX5: =IF(AV5>0,AW5,AX4) -> 0.8
A6: =ELEC!C5 -> 44806 | B6: =B5 -> 194.5 | C6: =C5 -> 201 | D6: =C5-C6 -> 0 | E6: =D6*8.38 -> 0 | F6: =F5 -> 2278 | G6: =F6-F5 -> 0 | H6: =H5 -> 46144 | I6: =SUM(H6-H5) -> 0 | J6: =IF(G6>0,I6/G6,0) -> 0 | K6: =K5 -> 2453 | L6: =K6-K5 -> 0 | M6: =M5 -> 182441 | N6: =M6-M5 -> 0 | O6: =O5 -> 1869 | P6: =P5 -> 2226 | Q6: =Q5 -> 186049 | R6: =Q6-Q5 -> 0 | S6: =SUM(P6-P5) -> 0 | T6: =SUM(S6*$T$2) -> 0 | U6: =SUM(G6+L6+S6) -> 0 | V6: =R6+N6+I6:I6 -> 0 | W6: =SUM(V6/U6) -> #DIV/0! | X6: =X5 -> 2492 | Y6: =X6-X5 -> 0 | Z6: =Z5 -> 140886 | AA6: =Z6-Z5 -> 0 | AB6: =SUM(Y6*$AB$2) -> 0 | AC6: =AC5 -> 1948 | AD6: =AC6-AC5 -> 0 | AE6: =AE5 -> 366628 | AF6: =AE6-AE5 -> 0 | AG6: =IF(AD6>0,AF6/AD6,0) -> 0 | AH6: =AF6+AA6 -> 0 | AI6: =SUM(AH6+V6) -> 0 | AJ6: =-tanks!AW7 -> 0 | AK6: =SUM(AJ6-AI6) -> 0 | AL6: =S6+L6+G6 -> 0 | AM6: =Y6+AD6 -> 0 | AN6: =AN5 -> 66 | AO6: =(AN6/100)*3000 -> 1980 | AP6: =AP5 -> 31 | AQ6: =(AP6/100)*3000 -> 930 | AR6: =AR5 -> 73 | AS6: =(AR6/100)*3000 -> 2190 | AT6: =SUM(AO6+AQ6+AS6) -> 5100 | AU6: =AT5-AT6+AV6 -> 0 | AX6: =IF(AV6>0,AW6,AX5) -> 0.8
A7: =ELEC!C6 -> 44807 | B7: =B6 -> 194.5 | C7: =C6 -> 201 | D7: =C6-C7 -> 0 | E7: =D7*8.38 -> 0 | F7: =F6 -> 2278 | G7: =F7-F6 -> 0 | H7: =H6 -> 46144 | I7: =SUM(H7-H6) -> 0 | J7: =IF(G7>0,I7/G7,0) -> 0 | K7: =K6 -> 2453 | L7: =K7-K6 -> 0 | M7: =M6 -> 182441 | N7: =M7-M6 -> 0 | O7: =O6 -> 1869 | P7: =P6 -> 2226 | Q7: =Q6 -> 186049 | R7: =Q7-Q6 -> 0 | S7: =SUM(P7-P6) -> 0 | T7: =SUM(S7*$T$2) -> 0 | U7: =SUM(G7+L7+S7) -> 0 | V7: =R7+N7+I7:I7 -> 0 | W7: =SUM(V7/U7) -> #DIV/0! | X7: =X6 -> 2492 | Y7: =X7-X6 -> 0 | Z7: =Z6 -> 140886 | AA7: =Z7-Z6 -> 0 | AB7: =SUM(Y7*$AB$2) -> 0 | AC7: =AC6 -> 1948 | AD7: =AC7-AC6 -> 0 | AE7: =AE6 -> 366628 | AF7: =AE7-AE6 -> 0 | AG7: =IF(AD7>0,AF7/AD7,0) -> 0 | AH7: =AF7+AA7 -> 0 | AI7: =SUM(AH7+V7) -> 0 | AJ7: =-tanks!AW8 -> 0 | AK7: =SUM(AJ7-AI7) -> 0 | AL7: =S7+L7+G7 -> 0 | AM7: =Y7+AD7 -> 0 | AN7: =AN6 -> 66 | AO7: =(AN7/100)*3000 -> 1980 | AP7: =AP6 -> 31 | AQ7: =(AP7/100)*3000 -> 930 | AR7: =AR6 -> 73 | AS7: =(AR7/100)*3000 -> 2190 | AT7: =SUM(AO7+AQ7+AS7) -> 5100 | AU7: =AT6-AT7+AV7 -> 0 | AX7: =IF(AV7>0,AW7,AX6) -> 0.8
A8: =ELEC!C7 -> 44808 | B8: 190.5 | C8: 198 | D8: =C7-C8 -> 3 | E8: =D8*8.38 -> 25.14 | F8: =F7 -> 2278 | G8: =F8-F7 -> 0 | H8: =H7 -> 46144 | I8: =SUM(H8-H7) -> 0 | J8: =IF(G8>0,I8/G8,0) -> 0 | K8: 2455 | L8: =K8-K7 -> 2 | M8: 182589 | N8: =M8-M7 -> 148 | O8: =O7 -> 1869 | P8: =P7 -> 2226 | Q8: =Q7 -> 186049 | R8: =Q8-Q7 -> 0 | S8: =SUM(P8-P7) -> 0 | T8: =SUM(S8*$T$2) -> 0 | U8: =SUM(G8+L8+S8) -> 2 | V8: =R8+N8+I8:I8 -> 148 | W8: =SUM(V8/U8) -> 74 | X8: =X7 -> 2492 | Y8: =X8-X7 -> 0 | Z8: =Z7 -> 140886 | AA8: =Z8-Z7 -> 0 | AB8: =SUM(Y8*$AB$2) -> 0 | AC8: =AC7 -> 1948 | AD8: =AC8-AC7 -> 0 | AE8: =AE7 -> 366628 | AF8: =AE8-AE7 -> 0 | AG8: =IF(AD8>0,AF8/AD8,0) -> 0 | AH8: =AF8+AA8 -> 0 | AI8: =SUM(AH8+V8) -> 148 | AJ8: =-tanks!AW9 -> 148 | AK8: =SUM(AJ8-AI8) -> 0 | AL8: =S8+L8+G8 -> 2 | AM8: =Y8+AD8 -> 0 | AN8: =AN7 -> 66 | AO8: =(AN8/100)*3000 -> 1980 | AP8: =AP7 -> 31 | AQ8: =(AP8/100)*3000 -> 930 | AR8: =AR7 -> 73 | AS8: =(AR8/100)*3000 -> 2190 | AT8: =SUM(AO8+AQ8+AS8) -> 5100 | AU8: =AT7-AT8+AV8 -> 0 | AX8: =IF(AV8>0,AW8,AX7) -> 0.8
A9: =ELEC!C8 -> 44809 | B9: 187 | C9: 193 | D9: =C8-C9 -> 5 | E9: =D9*8.38 -> 41.9 | F9: =F8 -> 2278 | G9: =F9-F8 -> 0 | H9: =H8 -> 46144 | I9: =SUM(H9-H8) -> 0 | J9: =IF(G9>0,I9/G9,0) -> 0 | K9: 2456 | L9: =K9-K8 -> 1 | M9: 182702 | N9: =M9-M8 -> 113 | O9: =O8 -> 1869 | P9: =P8 -> 2226 | Q9: =Q8 -> 186049 | R9: =Q9-Q8 -> 0 | S9: =SUM(P9-P8) -> 0 | T9: =SUM(S9*$T$2) -> 0 | U9: =SUM(G9+L9+S9) -> 1 | V9: =R9+N9+I9:I9 -> 113 | W9: =SUM(V9/U9) -> 113 | X9: =X8 -> 2492 | Y9: =X9-X8 -> 0 | Z9: =Z8 -> 140886 | AA9: =Z9-Z8 -> 0 | AB9: =SUM(Y9*$AB$2) -> 0 | AC9: =AC8 -> 1948 | AD9: =AC9-AC8 -> 0 | AE9: =AE8 -> 366628 | AF9: =AE9-AE8 -> 0 | AG9: =IF(AD9>0,AF9/AD9,0) -> 0 | AH9: =AF9+AA9 -> 0 | AI9: =SUM(AH9+V9) -> 113 | AJ9: =-tanks!AW10 -> 113 | AK9: =SUM(AJ9-AI9) -> 0 | AL9: =S9+L9+G9 -> 1 | AM9: =Y9+AD9 -> 0 | AN9: =AN8 -> 66 | AO9: =(AN9/100)*3000 -> 1980 | AP9: =AP8 -> 31 | AQ9: =(AP9/100)*3000 -> 930 | AR9: =AR8 -> 73 | AS9: =(AR9/100)*3000 -> 2190 | AT9: =SUM(AO9+AQ9+AS9) -> 5100 | AU9: =AT8-AT9+AV9 -> 0 | AX9: =IF(AV9>0,AW9,AX8) -> 0.8
A10: =ELEC!C9 -> 44810 | B10: 180 | C10: 187 | D10: =C9-C10 -> 6 | E10: =D10*8.38 -> 50.28 | F10: =F9 -> 2278 | G10: =F10-F9 -> 0 | H10: =H9 -> 46144 | I10: =SUM(H10-H9) -> 0 | J10: =IF(G10>0,I10/G10,0) -> 0 | K10: 2457 | L10: =K10-K9 -> 1 | M10: 182776 | N10: =M10-M9 -> 74 | O10: =O9 -> 1869 | P10: =P9 -> 2226 | Q10: =Q9 -> 186049 | R10: =Q10-Q9 -> 0 | S10: =SUM(P10-P9) -> 0 | T10: =SUM(S10*$T$2) -> 0 | U10: =SUM(G10+L10+S10) -> 1 | V10: =R10+N10+I10:I10 -> 74 | W10: =SUM(V10/U10) -> 74 | X10: =X9 -> 2492 | Y10: =X10-X9 -> 0 | Z10: =Z9 -> 140886 | AA10: =Z10-Z9 -> 0 | AB10: =SUM(Y10*$AB$2) -> 0 | AC10: =AC9 -> 1948 | AD10: =AC10-AC9 -> 0 | AE10: =AE9 -> 366628 | AF10: =AE10-AE9 -> 0 | AG10: =IF(AD10>0,AF10/AD10,0) -> 0 | AH10: =AF10+AA10 -> 0 | AI10: =SUM(AH10+V10) -> 74 | AJ10: =-tanks!AW11 -> 74 | AK10: =SUM(AJ10-AI10) -> 0 | AL10: =S10+L10+G10 -> 1 | AM10: =Y10+AD10 -> 0 | AN10: =AN9 -> 66 | AO10: =(AN10/100)*3000 -> 1980 | AP10: =AP9 -> 31 | AQ10: =(AP10/100)*3000 -> 930 | AR10: =AR9 -> 73 | AS10: =(AR10/100)*3000 -> 2190 | AT10: =SUM(AO10+AQ10+AS10) -> 5100 | AU10: =AT9-AT10+AV10 -> 0 | AX10: =IF(AV10>0,AW10,AX9) -> 0.8
A11: =ELEC!C10 -> 44811 | B11: 190 | C11: 197 | D11: =C10-C11 -> -10 | E11: =D11*8.38 -> -83.8 | F11: =F10 -> 2278 | G11: =F11-F10 -> 0 | H11: =H10 -> 46144 | I11: =SUM(H11-H10) -> 0 | J11: =IF(G11>0,I11/G11,0) -> 0 | K11: 2458 | L11: =K11-K10 -> 1 | M11: 182855 | N11: =M11-M10 -> 79 | O11: =O10 -> 1869 | P11: =P10 -> 2226 | Q11: =Q10 -> 186049 | R11: =Q11-Q10 -> 0 | S11: =SUM(P11-P10) -> 0 | T11: =SUM(S11*$T$2) -> 0 | U11: =SUM(G11+L11+S11) -> 1 | V11: =R11+N11+I11:I11 -> 79 | W11: =SUM(V11/U11) -> 79 | X11: =X10 -> 2492 | Y11: =X11-X10 -> 0 | Z11: =Z10 -> 140886 | AA11: =Z11-Z10 -> 0 | AB11: =SUM(Y11*$AB$2) -> 0 | AC11: =AC10 -> 1948 | AD11: =AC11-AC10 -> 0 | AE11: 366639 | AF11: =AE11-AE10 -> 11 | AG11: =IF(AD11>0,AF11/AD11,0) -> 0 | AH11: =AF11+AA11 -> 11 | AI11: =SUM(AH11+V11) -> 90 | AJ11: =-tanks!AW12 -> 90 | AK11: =SUM(AJ11-AI11) -> 0 | AL11: =S11+L11+G11 -> 1 | AM11: =Y11+AD11 -> 0 | AN11: 65 | AO11: =(AN11/100)*3000 -> 1950 | AP11: 35 | AQ11: =(AP11/100)*3000 -> 1050 | AR11: =AR10 -> 73 | AS11: =(AR11/100)*3000 -> 2190 | AT11: =SUM(AO11+AQ11+AS11) -> 5190 | AU11: =AT10-AT11+AV11 -> -90 | AX11: =IF(AV11>0,AW11,AX10) -> 0.8
A12: =ELEC!C11 -> 44812 | B12: 187 | C12: 193 | D12: =C11-C12 -> 4 | E12: =D12*8.38 -> 33.52 | F12: =F11 -> 2278 | G12: =F12-F11 -> 0 | H12: =H11 -> 46144 | I12: =SUM(H12-H11) -> 0 | J12: =IF(G12>0,I12/G12,0) -> 0 | K12: =K11 -> 2458 | L12: =K12-K11 -> 0 | M12: =M11 -> 182855 | N12: =M12-M11 -> 0 | O12: =O11 -> 1869 | P12: =P11 -> 2226 | Q12: =Q11 -> 186049 | R12: =Q12-Q11 -> 0 | S12: =SUM(P12-P11) -> 0 | T12: =SUM(S12*$T$2) -> 0 | U12: =SUM(G12+L12+S12) -> 0 | V12: =R12+N12+I12:I12 -> 0 | W12: =SUM(V12/U12) -> #DIV/0! | X12: =X11 -> 2492 | Y12: =X12-X11 -> 0 | Z12: =Z11 -> 140886 | AA12: =Z12-Z11 -> 0 | AB12: =SUM(Y12*$AB$2) -> 0 | AC12: =AC11 -> 1948 | AD12: =AC12-AC11 -> 0 | AE12: 366639 | AF12: =AE12-AE11 -> 0 | AG12: =IF(AD12>0,AF12/AD12,0) -> 0 | AH12: =AF12+AA12 -> 0 | AI12: =SUM(AH12+V12) -> 0 | AJ12: =-tanks!AW13 -> 0 | AK12: =SUM(AJ12-AI12) -> 0 | AL12: =S12+L12+G12 -> 0 | AM12: =Y12+AD12 -> 0 | AN12: =AN11 -> 65 | AO12: =(AN12/100)*3000 -> 1950 | AP12: =AP11 -> 35 | AQ12: =(AP12/100)*3000 -> 1050 | AR12: =AR11 -> 73 | AS12: =(AR12/100)*3000 -> 2190 | AT12: =SUM(AO12+AQ12+AS12) -> 5190 | AU12: =AT11-AT12+AV12 -> 0 | AX12: =IF(AV12>0,AW12,AX11) -> 0.8
A13: =ELEC!C12 -> 44813 | B13: =B12 -> 187 | C13: =C12 -> 193 | D13: =C12-C13 -> 0 | E13: =D13*8.38 -> 0 | F13: =F12 -> 2278 | G13: =F13-F12 -> 0 | H13: =H12 -> 46144 | I13: =SUM(H13-H12) -> 0 | J13: =IF(G13>0,I13/G13,0) -> 0 | K13: =K12 -> 2458 | L13: =K13-K12 -> 0 | M13: =M12 -> 182855 | N13: =M13-M12 -> 0 | O13: =O12 -> 1869 | P13: =P12 -> 2226 | Q13: =Q12 -> 186049 | R13: =Q13-Q12 -> 0 | S13: =SUM(P13-P12) -> 0 | T13: =SUM(S13*$T$2) -> 0 | U13: =SUM(G13+L13+S13) -> 0 | V13: =R13+N13+I13:I13 -> 0 | W13: =SUM(V13/U13) -> #DIV/0! | X13: =X12 -> 2492 | Y13: =X13-X12 -> 0 | Z13: =Z12 -> 140886 | AA13: =Z13-Z12 -> 0 | AB13: =SUM(Y13*$AB$2) -> 0 | AC13: =AC12 -> 1948 | AD13: =AC13-AC12 -> 0 | AE13: 366639 | AF13: =AE13-AE12 -> 0 | AG13: =IF(AD13>0,AF13/AD13,0) -> 0 | AH13: =AF13+AA13 -> 0 | AI13: =SUM(AH13+V13) -> 0 | AJ13: =-tanks!AW14 -> 0 | AK13: =SUM(AJ13-AI13) -> 0 | AL13: =S13+L13+G13 -> 0 | AM13: =Y13+AD13 -> 0 | AN13: =AN12 -> 65 | AO13: =(AN13/100)*3000 -> 1950 | AP13: =AP12 -> 35 | AQ13: =(AP13/100)*3000 -> 1050 | AR13: =AR12 -> 73 | AS13: =(AR13/100)*3000 -> 2190 | AT13: =SUM(AO13+AQ13+AS13) -> 5190 | AU13: =AT12-AT13+AV13 -> 0 | AX13: =IF(AV13>0,AW13,AX12) -> 0.8
A14: =ELEC!C13 -> 44814 | B14: =B13 -> 187 | C14: =C13 -> 193 | D14: =C13-C14 -> 0 | E14: =D14*8.38 -> 0 | F14: =F13 -> 2278 | G14: =F14-F13 -> 0 | H14: =H13 -> 46144 | I14: =SUM(H14-H13) -> 0 | J14: =IF(G14>0,I14/G14,0) -> 0 | K14: =K13 -> 2458 | L14: =K14-K13 -> 0 | M14: =M13 -> 182855 | N14: =M14-M13 -> 0 | O14: =O13 -> 1869 | P14: =P13 -> 2226 | Q14: =Q13 -> 186049 | R14: =Q14-Q13 -> 0 | S14: =SUM(P14-P13) -> 0 | T14: =SUM(S14*$T$2) -> 0 | U14: =SUM(G14+L14+S14) -> 0 | V14: =R14+N14+I14:I14 -> 0 | W14: =SUM(V14/U14) -> #DIV/0! | X14: =X13 -> 2492 | Y14: =X14-X13 -> 0 | Z14: =Z13 -> 140886 | AA14: =Z14-Z13 -> 0 | AB14: =SUM(Y14*$AB$2) -> 0 | AC14: =AC13 -> 1948 | AD14: =AC14-AC13 -> 0 | AE14: 366639 | AF14: =AE14-AE13 -> 0 | AG14: =IF(AD14>0,AF14/AD14,0) -> 0 | AH14: =AF14+AA14 -> 0 | AI14: =SUM(AH14+V14) -> 0 | AJ14: =-tanks!AW15 -> 0 | AK14: =SUM(AJ14-AI14) -> 0 | AL14: =S14+L14+G14 -> 0 | AM14: =Y14+AD14 -> 0 | AN14: =AN13 -> 65 | AO14: =(AN14/100)*3000 -> 1950 | AP14: =AP13 -> 35 | AQ14: =(AP14/100)*3000 -> 1050 | AR14: =AR13 -> 73 | AS14: =(AR14/100)*3000 -> 2190 | AT14: =SUM(AO14+AQ14+AS14) -> 5190 | AU14: =AT13-AT14+AV14 -> 0 | AX14: =IF(AV14>0,AW14,AX13) -> 0.8
A15: =ELEC!C14 -> 44815 | B15: 182.5 | C15: 189 | D15: =C14-C15 -> 4 | E15: =D15*8.38 -> 33.52 | F15: =F14 -> 2278 | G15: =F15-F14 -> 0 | H15: =H14 -> 46144 | I15: =SUM(H15-H14) -> 0 | J15: =IF(G15>0,I15/G15,0) -> 0 | K15: 2459 | L15: =K15-K14 -> 1 | M15: 182937 | N15: =M15-M14 -> 82 | O15: =O14 -> 1869 | P15: 2228 | Q15: 186184 | R15: =Q15-Q14 -> 135 | S15: =SUM(P15-P14) -> 2 | T15: =SUM(S15*$T$2) -> 0 | U15: =SUM(G15+L15+S15) -> 3 | V15: =R15+N15+I15:I15 -> 217 | W15: =SUM(V15/U15) -> 72.333333 | X15: =X14 -> 2492 | Y15: =X15-X14 -> 0 | Z15: =Z14 -> 140886 | AA15: =Z15-Z14 -> 0 | AB15: =SUM(Y15*$AB$2) -> 0 | AC15: =AC14 -> 1948 | AD15: =AC15-AC14 -> 0 | AE15: 366639 | AF15: =AE15-AE14 -> 0 | AG15: =IF(AD15>0,AF15/AD15,0) -> 0 | AH15: =AF15+AA15 -> 0 | AI15: =SUM(AH15+V15) -> 217 | AJ15: =-tanks!AW16 -> 217 | AK15: =SUM(AJ15-AI15) -> 0 | AL15: =S15+L15+G15 -> 3 | AM15: =Y15+AD15 -> 0 | AN15: =AN14 -> 65 | AO15: =(AN15/100)*3000 -> 1950 | AP15: =AP14 -> 35 | AQ15: =(AP15/100)*3000 -> 1050 | AR15: =AR14 -> 73 | AS15: =(AR15/100)*3000 -> 2190 | AT15: =SUM(AO15+AQ15+AS15) -> 5190 | AU15: =AT14-AT15+AV15 -> 0 | AX15: =IF(AV15>0,AW15,AX14) -> 0.8
A16: =ELEC!C15 -> 44816 | B16: 233 | C16: 239 | D16: =C15-C16 -> -50 | E16: =D16*8.38 -> -419 | F16: =F15 -> 2278 | G16: =F16-F15 -> 0 | H16: =H15 -> 46144 | I16: =SUM(H16-H15) -> 0 | J16: =IF(G16>0,I16/G16,0) -> 0 | K16: =K15 -> 2459 | L16: =K16-K15 -> 0 | M16: =M15 -> 182937 | N16: =M16-M15 -> 0 | O16: =O15 -> 1869 | P16: =P15 -> 2228 | Q16: 186192 | R16: =Q16-Q15 -> 8 | S16: =SUM(P16-P15) -> 0 | T16: =SUM(S16*$T$2) -> 0 | U16: =SUM(G16+L16+S16) -> 0 | V16: =R16+N16+I16:I16 -> 8 | W16: =SUM(V16/U16) -> #DIV/0! | X16: =X15 -> 2492 | Y16: =X16-X15 -> 0 | Z16: =Z15 -> 140886 | AA16: =Z16-Z15 -> 0 | AB16: =SUM(Y16*$AB$2) -> 0 | AC16: =AC15 -> 1948 | AD16: =AC16-AC15 -> 0 | AE16: 366639 | AF16: =AE16-AE15 -> 0 | AG16: =IF(AD16>0,AF16/AD16,0) -> 0 | AH16: =AF16+AA16 -> 0 | AI16: =SUM(AH16+V16) -> 8 | AJ16: =-tanks!AW17 -> 8 | AK16: =SUM(AJ16-AI16) -> 0 | AL16: =S16+L16+G16 -> 0 | AM16: =Y16+AD16 -> 0 | AN16: =AN15 -> 65 | AO16: =(AN16/100)*3000 -> 1950 | AP16: =AP15 -> 35 | AQ16: =(AP16/100)*3000 -> 1050 | AR16: =AR15 -> 73 | AS16: =(AR16/100)*3000 -> 2190 | AT16: =SUM(AO16+AQ16+AS16) -> 5190 | AU16: =AT15-AT16+AV16 -> 0 | AX16: =IF(AV16>0,AW16,AX15) -> 0.8
A17: =ELEC!C16 -> 44817 | B17: 229 | C17: 236 | D17: =C16-C17 -> 3 | E17: =D17*8.38 -> 25.14 | F17: =F16 -> 2278 | G17: =F17-F16 -> 0 | H17: =H16 -> 46144 | I17: =SUM(H17-H16) -> 0 | J17: =IF(G17>0,I17/G17,0) -> 0 | K17: =K16 -> 2459 | L17: =K17-K16 -> 0 | M17: =M16 -> 182937 | N17: =M17-M16 -> 0 | O17: =O16 -> 1869 | P17: =P16 -> 2228 | Q17: 186247 | R17: =Q17-Q16 -> 55 | S17: =SUM(P17-P16) -> 0 | T17: =SUM(S17*$T$2) -> 0 | U17: =SUM(G17+L17+S17) -> 0 | V17: =R17+N17+I17:I17 -> 55 | X17: 2493 | Y17: =X17-X16 -> 1 | Z17: 141018 | AA17: =Z17-Z16 -> 132 | AB17: =SUM(Y17*$AB$2) -> 0 | AC17: =AC16 -> 1948 | AD17: =AC17-AC16 -> 0 | AE17: 366639 | AF17: =AE17-AE16 -> 0 | AG17: =IF(AD17>0,AF17/AD17,0) -> 0 | AH17: =AF17+AA17 -> 132 | AI17: =SUM(AH17+V17) -> 187 | AJ17: =-tanks!AW18 -> 187 | AK17: =SUM(AJ17-AI17) -> 0 | AL17: =S17+L17+G17 -> 0 | AM17: =Y17+AD17 -> 1 | AN17: =AN16 -> 65 | AO17: =(AN17/100)*3000 -> 1950 | AP17: =AP16 -> 35 | AQ17: =(AP17/100)*3000 -> 1050 | AR17: =AR16 -> 73 | AS17: =(AR17/100)*3000 -> 2190 | AT17: =SUM(AO17+AQ17+AS17) -> 5190 | AU17: =AT16-AT17+AV17 -> 0 | AX17: =IF(AV17>0,AW17,AX16) -> 0.8
A18: =ELEC!C17 -> 44818 | B18: 226 | C18: 232 | D18: =C17-C18 -> 4 | E18: =D18*8.38 -> 33.52 | F18: =F17 -> 2278 | G18: =F18-F17 -> 0 | H18: =H17 -> 46144 | I18: =SUM(H18-H17) -> 0 | J18: =IF(G18>0,I18/G18,0) -> 0 | K18: =K17 -> 2459 | L18: =K18-K17 -> 0 | M18: =M17 -> 182937 | N18: =M18-M17 -> 0 | O18: 1869 | P18: 2230 | Q18: 186328 | R18: =Q18-Q17 -> 81 | S18: =SUM(P18-P17) -> 2 | T18: =SUM(S18*$T$2) -> 0 | U18: =SUM(G18+L18+S18) -> 2 | V18: =R18+N18+I18:I18 -> 81 | X18: =X17 -> 2493 | Y18: =X18-X17 -> 0 | Z18: =Z17 -> 141018 | AA18: =Z18-Z17 -> 0 | AB18: =SUM(Y18*$AB$2) -> 0 | AC18: =AC17 -> 1948 | AD18: =AC18-AC17 -> 0 | AE18: 366639 | AF18: =AE18-AE17 -> 0 | AG18: =IF(AD18>0,AF18/AD18,0) -> 0 | AH18: =AF18+AA18 -> 0 | AI18: =SUM(AH18+V18) -> 81 | AJ18: =-tanks!AW19 -> 81 | AK18: =SUM(AJ18-AI18) -> 0 | AL18: =S18+L18+G18 -> 2 | AM18: =Y18+AD18 -> 0 | AN18: =AN17 -> 65 | AO18: =(AN18/100)*3000 -> 1950 | AP18: =AP17 -> 35 | AQ18: =(AP18/100)*3000 -> 1050 | AR18: =AR17 -> 73 | AS18: =(AR18/100)*3000 -> 2190 | AT18: =SUM(AO18+AQ18+AS18) -> 5190 | AU18: =AT17-AT18+AV18 -> 0 | AX18: =IF(AV18>0,AW18,AX17) -> 0.8
A19: =ELEC!C18 -> 44819 | B19: 223 | C19: 229 | D19: =C18-C19 -> 3 | E19: =D19*8.38 -> 25.14 | F19: =F18 -> 2278 | G19: =F19-F18 -> 0 | H19: =H18 -> 46144 | I19: =SUM(H19-H18) -> 0 | J19: =IF(G19>0,I19/G19,0) -> 0 | K19: =K18 -> 2459 | L19: =K19-K18 -> 0 | M19: =M18 -> 182937 | N19: =M19-M18 -> 0 | O19: =O18 -> 1869 | P19: =P18 -> 2230 | Q19: =Q18 -> 186328 | R19: =Q19-Q18 -> 0 | S19: =SUM(P19-P18) -> 0 | T19: =SUM(S19*$T$2) -> 0 | U19: =SUM(G19+L19+S19) -> 0 | V19: =R19+N19+I19:I19 -> 0 | X19: =X18 -> 2493 | Y19: =X19-X18 -> 0 | Z19: =Z18 -> 141018 | AA19: =Z19-Z18 -> 0 | AB19: =SUM(Y19*$AB$2) -> 0 | AC19: =AC18 -> 1948 | AD19: =AC19-AC18 -> 0 | AE19: 366639 | AF19: =AE19-AE18 -> 0 | AG19: =IF(AD19>0,AF19/AD19,0) -> 0 | AH19: =AF19+AA19 -> 0 | AI19: =SUM(AH19+V19) -> 0 | AJ19: =-tanks!AW20 -> 0 | AK19: =SUM(AJ19-AI19) -> 0 | AL19: =S19+L19+G19 -> 0 | AM19: =Y19+AD19 -> 0 | AN19: =AN18 -> 65 | AO19: =(AN19/100)*3000 -> 1950 | AP19: =AP18 -> 35 | AQ19: =(AP19/100)*3000 -> 1050 | AR19: =AR18 -> 73 | AS19: =(AR19/100)*3000 -> 2190 | AT19: =SUM(AO19+AQ19+AS19) -> 5190 | AU19: =AT18-AT19+AV19 -> 0 | AX19: =IF(AV19>0,AW19,AX18) -> 0.8
A20: =ELEC!C19 -> 44820 | B20: =B19 -> 223 | C20: =C19 -> 229 | D20: =C19-C20 -> 0 | E20: =D20*8.38 -> 0 | F20: =F19 -> 2278 | G20: =F20-F19 -> 0 | H20: =H19 -> 46144 | I20: =SUM(H20-H19) -> 0 | J20: =IF(G20>0,I20/G20,0) -> 0 | K20: =K19 -> 2459 | L20: =K20-K19 -> 0 | M20: =M19 -> 182937 | N20: =M20-M19 -> 0 | O20: =O19 -> 1869 | P20: =P19 -> 2230 | Q20: =Q19 -> 186328 | R20: =Q20-Q19 -> 0 | S20: =SUM(P20-P19) -> 0 | T20: =SUM(S20*$T$2) -> 0 | U20: =SUM(G20+L20+S20) -> 0 | V20: =R20+N20+I20:I20 -> 0 | X20: =X19 -> 2493 | Y20: =X20-X19 -> 0 | Z20: =Z19 -> 141018 | AA20: =Z20-Z19 -> 0 | AB20: =SUM(Y20*$AB$2) -> 0 | AC20: =AC19 -> 1948 | AD20: =AC20-AC19 -> 0 | AE20: 366639 | AF20: =AE20-AE19 -> 0 | AG20: =IF(AD20>0,AF20/AD20,0) -> 0 | AH20: =AF20+AA20 -> 0 | AI20: =SUM(AH20+V20) -> 0 | AJ20: =-tanks!AW21 -> 0 | AK20: =SUM(AJ20-AI20) -> 0 | AL20: =S20+L20+G20 -> 0 | AM20: =Y20+AD20 -> 0 | AN20: =AN19 -> 65 | AO20: =(AN20/100)*3000 -> 1950 | AP20: =AP19 -> 35 | AQ20: =(AP20/100)*3000 -> 1050 | AR20: =AR19 -> 73 | AS20: =(AR20/100)*3000 -> 2190 | AT20: =SUM(AO20+AQ20+AS20) -> 5190 | AU20: =AT19-AT20+AV20 -> 0 | AX20: =IF(AV20>0,AW20,AX19) -> 0.8
A21: =ELEC!C20 -> 44821 | B21: =B20 -> 223 | C21: =C20 -> 229 | D21: =C20-C21 -> 0 | E21: =D21*8.38 -> 0 | F21: =F20 -> 2278 | G21: =F21-F20 -> 0 | H21: =H20 -> 46144 | I21: =SUM(H21-H20) -> 0 | J21: =IF(G21>0,I21/G21,0) -> 0 | K21: =K20 -> 2459 | L21: =K21-K20 -> 0 | M21: =M20 -> 182937 | N21: =M21-M20 -> 0 | O21: =O20 -> 1869 | P21: =P20 -> 2230 | Q21: =Q20 -> 186328 | R21: =Q21-Q20 -> 0 | S21: =SUM(P21-P20) -> 0 | T21: =SUM(S21*$T$2) -> 0 | U21: =SUM(G21+L21+S21) -> 0 | V21: =R21+N21+I21:I21 -> 0 | X21: =X20 -> 2493 | Y21: =X21-X20 -> 0 | Z21: =Z20 -> 141018 | AA21: =Z21-Z20 -> 0 | AB21: =SUM(Y21*$AB$2) -> 0 | AC21: =AC20 -> 1948 | AD21: =AC21-AC20 -> 0 | AE21: 366639 | AF21: =AE21-AE20 -> 0 | AG21: =IF(AD21>0,AF21/AD21,0) -> 0 | AH21: =AF21+AA21 -> 0 | AI21: =SUM(AH21+V21) -> 0 | AJ21: =-tanks!AW22 -> 0 | AK21: =SUM(AJ21-AI21) -> 0 | AL21: =S21+L21+G21 -> 0 | AM21: =Y21+AD21 -> 0 | AN21: =AN20 -> 65 | AO21: =(AN21/100)*3000 -> 1950 | AP21: =AP20 -> 35 | AQ21: =(AP21/100)*3000 -> 1050 | AR21: =AR20 -> 73 | AS21: =(AR21/100)*3000 -> 2190 | AT21: =SUM(AO21+AQ21+AS21) -> 5190 | AU21: =AT20-AT21+AV21 -> 0 | AX21: =IF(AV21>0,AW21,AX20) -> 0.8
A22: =ELEC!C21 -> 44822 | B22: 239 | C22: 245 | D22: =C21-C22 -> -16 | E22: =D22*8.38 -> -134.08 | F22: =F21 -> 2278 | G22: =F22-F21 -> 0 | H22: =H21 -> 46144 | I22: =SUM(H22-H21) -> 0 | J22: =IF(G22>0,I22/G22,0) -> 0 | K22: =K21 -> 2459 | L22: =K22-K21 -> 0 | M22: =M21 -> 182937 | N22: =M22-M21 -> 0 | O22: =O21 -> 1869 | P22: 2231 | Q22: 186441 | R22: =Q22-Q21 -> 113 | S22: =SUM(P22-P21) -> 1 | T22: =SUM(S22*$T$2) -> 0 | U22: =SUM(G22+L22+S22) -> 1 | V22: =R22+N22+I22:I22 -> 113 | X22: =X21 -> 2493 | Y22: =X22-X21 -> 0 | Z22: =Z21 -> 141018 | AA22: =Z22-Z21 -> 0 | AB22: =SUM(Y22*$AB$2) -> 0 | AC22: =AC21 -> 1948 | AD22: =AC22-AC21 -> 0 | AE22: 366639 | AF22: =AE22-AE21 -> 0 | AG22: =IF(AD22>0,AF22/AD22,0) -> 0 | AH22: =AF22+AA22 -> 0 | AI22: =SUM(AH22+V22) -> 113 | AJ22: =-tanks!AW23 -> 113 | AK22: =SUM(AJ22-AI22) -> 0 | AL22: =S22+L22+G22 -> 1 | AM22: =Y22+AD22 -> 0 | AN22: =AN21 -> 65 | AO22: =(AN22/100)*3000 -> 1950 | AP22: =AP21 -> 35 | AQ22: =(AP22/100)*3000 -> 1050 | AR22: =AR21 -> 73 | AS22: =(AR22/100)*3000 -> 2190 | AT22: =SUM(AO22+AQ22+AS22) -> 5190 | AU22: =AT21-AT22+AV22 -> 0 | AX22: =IF(AV22>0,AW22,AX21) -> 0.8
A23: =ELEC!C22 -> 44823 | B23: 235 | C23: 241 | D23: =C22-C23 -> 4 | E23: =D23*8.38 -> 33.52 | F23: 2279 | G23: =F23-F22 -> 1 | H23: 46257 | I23: =SUM(H23-H22) -> 113 | J23: =IF(G23>0,I23/G23,0) -> 113 | K23: =K22 -> 2459 | L23: =K23-K22 -> 0 | M23: =M22 -> 182937 | N23: =M23-M22 -> 0 | O23: =O22 -> 1869 | P23: =P22 -> 2231 | Q23: =Q22 -> 186441 | R23: =Q23-Q22 -> 0 | S23: =SUM(P23-P22) -> 0 | T23: =SUM(S23*$T$2) -> 0 | U23: =SUM(G23+L23+S23) -> 1 | V23: =R23+N23+I23:I23 -> 113 | X23: =X22 -> 2493 | Y23: =X23-X22 -> 0 | Z23: =Z22 -> 141018 | AA23: =Z23-Z22 -> 0 | AB23: =SUM(Y23*$AB$2) -> 0 | AC23: =AC22 -> 1948 | AD23: =AC23-AC22 -> 0 | AE23: 366639 | AF23: =AE23-AE22 -> 0 | AG23: =IF(AD23>0,AF23/AD23,0) -> 0 | AH23: =AF23+AA23 -> 0 | AI23: =SUM(AH23+V23) -> 113 | AJ23: =-tanks!AW24 -> 113 | AK23: =SUM(AJ23-AI23) -> 0 | AL23: =S23+L23+G23 -> 1 | AM23: =Y23+AD23 -> 0 | AN23: =AN22 -> 65 | AO23: =(AN23/100)*3000 -> 1950 | AP23: =AP22 -> 35 | AQ23: =(AP23/100)*3000 -> 1050 | AR23: =AR22 -> 73 | AS23: =(AR23/100)*3000 -> 2190 | AT23: =SUM(AO23+AQ23+AS23) -> 5190 | AU23: =AT22-AT23+AV23 -> 0 | AX23: =IF(AV23>0,AW23,AX22) -> 0.8
A24: =ELEC!C23 -> 44824 | B24: 231 | C24: 237 | D24: =C23-C24 -> 4 | E24: =D24*8.38 -> 33.52 | F24: 2280 | G24: =F24-F23 -> 1 | H24: 46288 | I24: =SUM(H24-H23) -> 31 | J24: =IF(G24>0,I24/G24,0) -> 31 | K24: =K23 -> 2459 | L24: =K24-K23 -> 0 | M24: =M23 -> 182937 | N24: =M24-M23 -> 0 | O24: =O23 -> 1869 | P24: =P23 -> 2231 | Q24: =Q23 -> 186441 | R24: =Q24-Q23 -> 0 | S24: =SUM(P24-P23) -> 0 | T24: =SUM(S24*$T$2) -> 0 | U24: =SUM(G24+L24+S24) -> 1 | V24: =R24+N24+I24:I24 -> 31 | X24: =X23 -> 2493 | Y24: =X24-X23 -> 0 | Z24: =Z23 -> 141018 | AA24: =Z24-Z23 -> 0 | AB24: =SUM(Y24*$AB$2) -> 0 | AC24: =AC23 -> 1948 | AD24: =AC24-AC23 -> 0 | AE24: 366639 | AF24: =AE24-AE23 -> 0 | AG24: =IF(AD24>0,AF24/AD24,0) -> 0 | AH24: =AF24+AA24 -> 0 | AI24: =SUM(AH24+V24) -> 31 | AJ24: =-tanks!AW25 -> 31 | AK24: =SUM(AJ24-AI24) -> 0 | AL24: =S24+L24+G24 -> 1 | AM24: =Y24+AD24 -> 0 | AN24: =AN23 -> 65 | AO24: =(AN24/100)*3000 -> 1950 | AP24: =AP23 -> 35 | AQ24: =(AP24/100)*3000 -> 1050 | AR24: =AR23 -> 73 | AS24: =(AR24/100)*3000 -> 2190 | AT24: =SUM(AO24+AQ24+AS24) -> 5190 | AU24: =AT23-AT24+AV24 -> 0 | AX24: =IF(AV24>0,AW24,AX23) -> 0.8
A25: =ELEC!C24 -> 44825 | B25: 227 | C25: 233 | D25: =C24-C25 -> 4 | E25: =D25*8.38 -> 33.52 | F25: 2281 | G25: =F25-F24 -> 1 | H25: 46407 | I25: =SUM(H25-H24) -> 119 | J25: =IF(G25>0,I25/G25,0) -> 119 | K25: =K24 -> 2459 | L25: =K25-K24 -> 0 | M25: =M24 -> 182937 | N25: =M25-M24 -> 0 | O25: =O24 -> 1869 | P25: =P24 -> 2231 | Q25: =Q24 -> 186441 | R25: =Q25-Q24 -> 0 | S25: =SUM(P25-P24) -> 0 | T25: =SUM(S25*$T$2) -> 0 | U25: =SUM(G25+L25+S25) -> 1 | V25: =R25+N25+I25:I25 -> 119 | X25: =X24 -> 2493 | Y25: =X25-X24 -> 0 | Z25: =Z24 -> 141018 | AA25: =Z25-Z24 -> 0 | AB25: =SUM(Y25*$AB$2) -> 0 | AC25: =AC24 -> 1948 | AD25: =AC25-AC24 -> 0 | AE25: 366639 | AF25: =AE25-AE24 -> 0 | AG25: =IF(AD25>0,AF25/AD25,0) -> 0 | AH25: =AF25+AA25 -> 0 | AI25: =SUM(AH25+V25) -> 119 | AJ25: =-tanks!AW26 -> 119 | AK25: =SUM(AJ25-AI25) -> 0 | AL25: =S25+L25+G25 -> 1 | AM25: =Y25+AD25 -> 0 | AN25: =AN24 -> 65 | AO25: =(AN25/100)*3000 -> 1950 | AP25: =AP24 -> 35 | AQ25: =(AP25/100)*3000 -> 1050 | AR25: =AR24 -> 73 | AS25: =(AR25/100)*3000 -> 2190 | AT25: =SUM(AO25+AQ25+AS25) -> 5190 | AU25: =AT24-AT25+AV25 -> 0 | AX25: =IF(AV25>0,AW25,AX24) -> 0.8
A26: =ELEC!C25 -> 44826 | B26: 246 | C26: 251 | D26: =C25-C26 -> -18 | E26: =D26*8.38 -> -150.84 | F26: =F25 -> 2281 | G26: =F26-F25 -> 0 | H26: 46415 | I26: =SUM(H26-H25) -> 8 | J26: =IF(G26>0,I26/G26,0) -> 0 | K26: =K25 -> 2459 | L26: =K26-K25 -> 0 | M26: =M25 -> 182937 | N26: =M26-M25 -> 0 | O26: =O25 -> 1869 | P26: =P25 -> 2231 | Q26: =Q25 -> 186441 | R26: =Q26-Q25 -> 0 | S26: =SUM(P26-P25) -> 0 | T26: =SUM(S26*$T$2) -> 0 | U26: =SUM(G26+L26+S26) -> 0 | V26: =R26+N26+I26:I26 -> 8 | X26: 2494 | Y26: =X26-X25 -> 1 | Z26: 141111 | AA26: =Z26-Z25 -> 93 | AB26: =SUM(Y26*$AB$2) -> 0 | AC26: =AC25 -> 1948 | AD26: =AC26-AC25 -> 0 | AE26: 366639 | AF26: =AE26-AE25 -> 0 | AG26: =IF(AD26>0,AF26/AD26,0) -> 0 | AH26: =AF26+AA26 -> 93 | AI26: =SUM(AH26+V26) -> 101 | AJ26: =-tanks!AW27 -> 101 | AK26: =SUM(AJ26-AI26) -> 0 | AL26: =S26+L26+G26 -> 0 | AM26: =Y26+AD26 -> 1 | AN26: =AN25 -> 65 | AO26: =(AN26/100)*3000 -> 1950 | AP26: =AP25 -> 35 | AQ26: =(AP26/100)*3000 -> 1050 | AR26: =AR25 -> 73 | AS26: =(AR26/100)*3000 -> 2190 | AT26: =SUM(AO26+AQ26+AS26) -> 5190 | AU26: =AT25-AT26+AV26 -> 0 | AX26: =IF(AV26>0,AW26,AX25) -> 0.8
A27: =ELEC!C26 -> 44827 | B27: =B26 -> 246 | C27: =C26 -> 251 | D27: =C26-C27 -> 0 | E27: =D27*8.38 -> 0 | F27: =F26 -> 2281 | G27: =F27-F26 -> 0 | H27: =H26 -> 46415 | I27: =SUM(H27-H26) -> 0 | J27: =IF(G27>0,I27/G27,0) -> 0 | K27: =K26 -> 2459 | L27: =K27-K26 -> 0 | M27: =M26 -> 182937 | N27: =M27-M26 -> 0 | O27: =O26 -> 1869 | P27: =P26 -> 2231 | Q27: =Q26 -> 186441 | R27: =Q27-Q26 -> 0 | S27: =SUM(P27-P26) -> 0 | T27: =SUM(S27*$T$2) -> 0 | U27: =SUM(G27+L27+S27) -> 0 | V27: =R27+N27+I27:I27 -> 0 | X27: =X26 -> 2494 | Y27: =X27-X26 -> 0 | Z27: =Z26 -> 141111 | AA27: =Z27-Z26 -> 0 | AB27: =SUM(Y27*$AB$2) -> 0 | AC27: =AC26 -> 1948 | AD27: =AC27-AC26 -> 0 | AE27: 366639 | AF27: =AE27-AE26 -> 0 | AG27: =IF(AD27>0,AF27/AD27,0) -> 0 | AH27: =AF27+AA27 -> 0 | AI27: =SUM(AH27+V27) -> 0 | AJ27: =-tanks!AW28 -> 0 | AK27: =SUM(AJ27-AI27) -> 0 | AL27: =S27+L27+G27 -> 0 | AM27: =Y27+AD27 -> 0 | AN27: =AN26 -> 65 | AO27: =(AN27/100)*3000 -> 1950 | AP27: =AP26 -> 35 | AQ27: =(AP27/100)*3000 -> 1050 | AR27: =AR26 -> 73 | AS27: =(AR27/100)*3000 -> 2190 | AT27: =SUM(AO27+AQ27+AS27) -> 5190 | AU27: =AT26-AT27+AV27 -> 0 | AX27: =IF(AV27>0,AW27,AX26) -> 0.8
A28: =ELEC!C27 -> 44828 | B28: =B27 -> 246 | C28: =C27 -> 251 | D28: =C27-C28 -> 0 | E28: =D28*8.38 -> 0 | F28: =F27 -> 2281 | G28: =F28-F27 -> 0 | H28: =H27 -> 46415 | I28: =SUM(H28-H27) -> 0 | J28: =IF(G28>0,I28/G28,0) -> 0 | K28: =K27 -> 2459 | L28: =K28-K27 -> 0 | M28: =M27 -> 182937 | N28: =M28-M27 -> 0 | O28: =O27 -> 1869 | P28: =P27 -> 2231 | Q28: =Q27 -> 186441 | R28: =Q28-Q27 -> 0 | S28: =SUM(P28-P27) -> 0 | T28: =SUM(S28*$T$2) -> 0 | U28: =SUM(G28+L28+S28) -> 0 | V28: =R28+N28+I28:I28 -> 0 | X28: =X27 -> 2494 | Y28: =X28-X27 -> 0 | Z28: =Z27 -> 141111 | AA28: =Z28-Z27 -> 0 | AB28: =SUM(Y28*$AB$2) -> 0 | AC28: =AC27 -> 1948 | AD28: =AC28-AC27 -> 0 | AE28: 366639 | AF28: =AE28-AE27 -> 0 | AG28: =IF(AD28>0,AF28/AD28,0) -> 0 | AH28: =AF28+AA28 -> 0 | AI28: =SUM(AH28+V28) -> 0 | AJ28: =-tanks!AW29 -> 0 | AK28: =SUM(AJ28-AI28) -> 0 | AL28: =S28+L28+G28 -> 0 | AM28: =Y28+AD28 -> 0 | AN28: =AN27 -> 65 | AO28: =(AN28/100)*3000 -> 1950 | AP28: =AP27 -> 35 | AQ28: =(AP28/100)*3000 -> 1050 | AR28: =AR27 -> 73 | AS28: =(AR28/100)*3000 -> 2190 | AT28: =SUM(AO28+AQ28+AS28) -> 5190 | AU28: =AT27-AT28+AV28 -> 0 | AX28: =IF(AV28>0,AW28,AX27) -> 0.8
A29: =ELEC!C28 -> 44829 | B29: 240 | C29: 247 | D29: =C28-C29 -> 4 | E29: =D29*8.38 -> 33.52 | F29: 2284 | G29: =F29-F28 -> 3 | H29: 46612 | I29: =SUM(H29-H28) -> 197 | J29: =IF(G29>0,I29/G29,0) -> 65.666667 | K29: =K28 -> 2459 | L29: =K29-K28 -> 0 | M29: =M28 -> 182937 | N29: =M29-M28 -> 0 | O29: =O28 -> 1869 | P29: =P28 -> 2231 | Q29: =Q28 -> 186441 | R29: =Q29-Q28 -> 0 | S29: =SUM(P29-P28) -> 0 | T29: =SUM(S29*$T$2) -> 0 | U29: =SUM(G29+L29+S29) -> 3 | V29: =R29+N29+I29:I29 -> 197 | X29: =X28 -> 2494 | Y29: =X29-X28 -> 0 | Z29: =Z28 -> 141111 | AA29: =Z29-Z28 -> 0 | AB29: =SUM(Y29*$AB$2) -> 0 | AC29: =AC28 -> 1948 | AD29: =AC29-AC28 -> 0 | AE29: 366639 | AF29: =AE29-AE28 -> 0 | AG29: =IF(AD29>0,AF29/AD29,0) -> 0 | AH29: =AF29+AA29 -> 0 | AI29: =SUM(AH29+V29) -> 197 | AJ29: =-tanks!AW30 -> 197 | AK29: =SUM(AJ29-AI29) -> 0 | AL29: =S29+L29+G29 -> 3 | AM29: =Y29+AD29 -> 0 | AN29: =AN28 -> 65 | AO29: =(AN29/100)*3000 -> 1950 | AP29: =AP28 -> 35 | AQ29: =(AP29/100)*3000 -> 1050 | AR29: =AR28 -> 73 | AS29: =(AR29/100)*3000 -> 2190 | AT29: =SUM(AO29+AQ29+AS29) -> 5190 | AU29: =AT28-AT29+AV29 -> 0 | AX29: =IF(AV29>0,AW29,AX28) -> 0.8
A30: =ELEC!C29 -> 44830 | B30: 236 | C30: 243 | D30: =C29-C30 -> 4 | E30: =D30*8.38 -> 33.52 | F30: 2285 | G30: =F30-F29 -> 1 | H30: 46671 | I30: =SUM(H30-H29) -> 59 | J30: =IF(G30>0,I30/G30,0) -> 59 | K30: =K29 -> 2459 | L30: =K30-K29 -> 0 | M30: =M29 -> 182937 | N30: =M30-M29 -> 0 | O30: =O29 -> 1869 | P30: =P29 -> 2231 | Q30: =Q29 -> 186441 | R30: =Q30-Q29 -> 0 | S30: =SUM(P30-P29) -> 0 | T30: =SUM(S30*$T$2) -> 0 | U30: =SUM(G30+L30+S30) -> 1 | V30: =R30+N30+I30:I30 -> 59 | X30: =X29 -> 2494 | Y30: =X30-X29 -> 0 | Z30: =Z29 -> 141111 | AA30: =Z30-Z29 -> 0 | AB30: =SUM(Y30*$AB$2) -> 0 | AC30: =AC29 -> 1948 | AD30: =AC30-AC29 -> 0 | AE30: 366639 | AF30: =AE30-AE29 -> 0 | AG30: =IF(AD30>0,AF30/AD30,0) -> 0 | AH30: =AF30+AA30 -> 0 | AI30: =SUM(AH30+V30) -> 59 | AJ30: =-tanks!AW31 -> 59 | AK30: =SUM(AJ30-AI30) -> 0 | AL30: =S30+L30+G30 -> 1 | AM30: =Y30+AD30 -> 0 | AN30: =AN29 -> 65 | AO30: =(AN30/100)*3000 -> 1950 | AP30: =AP29 -> 35 | AQ30: =(AP30/100)*3000 -> 1050 | AR30: =AR29 -> 73 | AS30: =(AR30/100)*3000 -> 2190 | AT30: =SUM(AO30+AQ30+AS30) -> 5190 | AU30: =AT29-AT30+AV30 -> 0 | AX30: =IF(AV30>0,AW30,AX29) -> 0.8
A31: =ELEC!C30 -> 44831 | B31: 233 | C31: 239 | D31: =C30-C31 -> 4 | E31: =D31*8.38 -> 33.52 | F31: 2286 | G31: =F31-F30 -> 1 | H31: 46780 | I31: =SUM(H31-H30) -> 109 | J31: =IF(G31>0,I31/G31,0) -> 109 | K31: =K30 -> 2459 | L31: =K31-K30 -> 0 | M31: =M30 -> 182937 | N31: =M31-M30 -> 0 | O31: =O30 -> 1869 | P31: =P30 -> 2231 | Q31: =Q30 -> 186441 | R31: =Q31-Q30 -> 0 | S31: =SUM(P31-P30) -> 0 | T31: =SUM(S31*$T$2) -> 0 | U31: =SUM(G31+L31+S31) -> 1 | V31: =R31+N31+I31:I31 -> 109 | X31: =X30 -> 2494 | Y31: =X31-X30 -> 0 | Z31: =Z30 -> 141111 | AA31: =Z31-Z30 -> 0 | AB31: =SUM(Y31*$AB$2) -> 0 | AC31: =AC30 -> 1948 | AD31: =AC31-AC30 -> 0 | AE31: 366639 | AF31: =AE31-AE30 -> 0 | AG31: =IF(AD31>0,AF31/AD31,0) -> 0 | AH31: =AF31+AA31 -> 0 | AI31: =SUM(AH31+V31) -> 109 | AJ31: =-tanks!AW32 -> 109 | AK31: =SUM(AJ31-AI31) -> 0 | AL31: =S31+L31+G31 -> 1 | AM31: =Y31+AD31 -> 0 | AN31: =AN30 -> 65 | AO31: =(AN31/100)*3000 -> 1950 | AP31: =AP30 -> 35 | AQ31: =(AP31/100)*3000 -> 1050 | AR31: =AR30 -> 73 | AS31: =(AR31/100)*3000 -> 2190 | AT31: =SUM(AO31+AQ31+AS31) -> 5190 | AU31: =AT30-AT31+AV31 -> 0 | AX31: =IF(AV31>0,AW31,AX30) -> 0.8
A32: =ELEC!C31 -> 44832 | B32: 229 | C32: 235 | D32: =C31-C32 -> 4 | E32: =D32*8.38 -> 33.52 | F32: 2287 | G32: =F32-F31 -> 1 | H32: 46821 | I32: =SUM(H32-H31) -> 41 | J32: =IF(G32>0,I32/G32,0) -> 41 | K32: =K31 -> 2459 | L32: =K32-K31 -> 0 | M32: =M31 -> 182937 | N32: =M32-M31 -> 0 | O32: =O31 -> 1869 | P32: =P31 -> 2231 | Q32: =Q31 -> 186441 | R32: =Q32-Q31 -> 0 | S32: =SUM(P32-P31) -> 0 | T32: =SUM(S32*$T$2) -> 0 | U32: =SUM(G32+L32+S32) -> 1 | V32: =R32+N32+I32:I32 -> 41 | X32: =X31 -> 2494 | Y32: =X32-X31 -> 0 | Z32: =Z31 -> 141111 | AA32: =Z32-Z31 -> 0 | AB32: =SUM(Y32*$AB$2) -> 0 | AC32: =AC31 -> 1948 | AD32: =AC32-AC31 -> 0 | AE32: 366639 | AF32: =AE32-AE31 -> 0 | AG32: =IF(AD32>0,AF32/AD32,0) -> 0 | AH32: =AF32+AA32 -> 0 | AI32: =SUM(AH32+V32) -> 41 | AJ32: =-tanks!AW33 -> 41 | AK32: =SUM(AJ32-AI32) -> 0 | AL32: =S32+L32+G32 -> 1 | AM32: =Y32+AD32 -> 0 | AN32: =AN31 -> 65 | AO32: =(AN32/100)*3000 -> 1950 | AP32: =AP31 -> 35 | AQ32: =(AP32/100)*3000 -> 1050 | AR32: =AR31 -> 73 | AS32: =(AR32/100)*3000 -> 2190 | AT32: =SUM(AO32+AQ32+AS32) -> 5190 | AU32: =AT31-AT32+AV32 -> 0 | AX32: =IF(AV32>0,AW32,AX31) -> 0.8
A33: =ELEC!C32 -> 44833 | B33: 226 | C33: 232 | D33: =C32-C33 -> 3 | E33: =D33*8.38 -> 25.14 | F33: 2287 | G33: =F33-F32 -> 0 | H33: 46848 | I33: =SUM(H33-H32) -> 27 | J33: =IF(G33>0,I33/G33,0) -> 0 | K33: =K32 -> 2459 | L33: =K33-K32 -> 0 | M33: =M32 -> 182937 | N33: =M33-M32 -> 0 | O33: =O32 -> 1869 | P33: =P32 -> 2231 | Q33: =Q32 -> 186441 | R33: =Q33-Q32 -> 0 | S33: =SUM(P33-P32) -> 0 | T33: =SUM(S33*$T$2) -> 0 | U33: =SUM(G33+L33+S33) -> 0 | V33: =R33+N33+I33:I33 -> 27 | X33: =X32 -> 2494 | Y33: =X33-X32 -> 0 | Z33: =Z32 -> 141111 | AA33: =Z33-Z32 -> 0 | AB33: =SUM(Y33*$AB$2) -> 0 | AC33: =AC32 -> 1948 | AD33: =AC33-AC32 -> 0 | AE33: 366639 | AF33: =AE33-AE32 -> 0 | AG33: =IF(AD33>0,AF33/AD33,0) -> 0 | AH33: =AF33+AA33 -> 0 | AI33: =SUM(AH33+V33) -> 27 | AJ33: =-tanks!AW34 -> 27 | AK33: =SUM(AJ33-AI33) -> 0 | AL33: =S33+L33+G33 -> 0 | AM33: =Y33+AD33 -> 0 | AN33: =AN32 -> 65 | AO33: =(AN33/100)*3000 -> 1950 | AP33: =AP32 -> 35 | AQ33: =(AP33/100)*3000 -> 1050 | AR33: =AR32 -> 73 | AS33: =(AR33/100)*3000 -> 2190 | AT33: =SUM(AO33+AQ33+AS33) -> 5190 | AU33: =AT32-AT33+AV33 -> 0 | AX33: =IF(AV33>0,AW33,AX32) -> 0.8
A34: =ELEC!C33 -> 44834 | B34: =B33 -> 226 | C34: =C33 -> 232 | D34: =C33-C34 -> 0 | E34: =D34*8.38 -> 0 | F34: =F33 -> 2287 | G34: =F34-F33 -> 0 | H34: =H33 -> 46848 | I34: =SUM(H34-H33) -> 0 | J34: =IF(G34>0,I34/G34,0) -> 0 | K34: =K33 -> 2459 | L34: =K34-K33 -> 0 | M34: =M33 -> 182937 | N34: =M34-M33 -> 0 | O34: =O33 -> 1869 | P34: =P33 -> 2231 | Q34: =Q33 -> 186441 | R34: =Q34-Q33 -> 0 | S34: =SUM(P34-P33) -> 0 | T34: =SUM(S34*$T$2) -> 0 | U34: =SUM(G34+L34+S34) -> 0 | V34: =R34+N34+I34:I34 -> 0 | X34: =X33 -> 2494 | Y34: =X34-X33 -> 0 | Z34: =Z33 -> 141111 | AA34: =Z34-Z33 -> 0 | AB34: =SUM(Y34*$AB$2) -> 0 | AC34: =AC33 -> 1948 | AD34: =AC34-AC33 -> 0 | AE34: 366639 | AF34: =AE34-AE33 -> 0 | AG34: =IF(AD34>0,AF34/AD34,0) -> 0 | AH34: =AF34+AA34 -> 0 | AI34: =SUM(AH34+V34) -> 0 | AJ34: =-tanks!AW35 -> 0 | AK34: =SUM(AJ34-AI34) -> 0 | AL34: =S34+L34+G34 -> 0 | AM34: =Y34+AD34 -> 0 | AN34: =AN33 -> 65 | AO34: =(AN34/100)*3000 -> 1950 | AP34: =AP33 -> 35 | AQ34: =(AP34/100)*3000 -> 1050 | AR34: =AR33 -> 73 | AS34: =(AR34/100)*3000 -> 2190 | AT34: =SUM(AO34+AQ34+AS34) -> 5190 | AU34: =AT33-AT34+AV34 -> 0 | AX34: =IF(AV34>0,AW34,AX33) -> 0.8
A35: =ELEC!C34 -> 44835 | B35: =B34 -> 226 | C35: =C34 -> 232 | D35: =C34-C35 -> 0 | E35: =D35*8.38 -> 0 | F35: =F34 -> 2287 | G35: =F35-F34 -> 0 | H35: =H34 -> 46848 | I35: =SUM(H35-H34) -> 0 | J35: =IF(G35>0,I35/G35,0) -> 0 | K35: =K34 -> 2459 | L35: =K35-K34 -> 0 | M35: =M34 -> 182937 | N35: =M35-M34 -> 0 | O35: =O34 -> 1869 | P35: =P34 -> 2231 | Q35: =Q34 -> 186441 | R35: =Q35-Q34 -> 0 | S35: =SUM(P35-P34) -> 0 | T35: =SUM(S35*$T$2) -> 0 | U35: =SUM(G35+L35+S35) -> 0 | V35: =R35+N35+I35:I35 -> 0 | X35: =X34 -> 2494 | Y35: =X35-X34 -> 0 | Z35: =Z34 -> 141111 | AA35: =Z35-Z34 -> 0 | AB35: =SUM(Y35*$AB$2) -> 0 | AC35: =AC34 -> 1948 | AD35: =AC35-AC34 -> 0 | AE35: 366639 | AF35: =AE35-AE34 -> 0 | AG35: =IF(AD35>0,AF35/AD35,0) -> 0 | AH35: =AF35+AA35 -> 0 | AI35: =SUM(AH35+V35) -> 0 | AJ35: =-tanks!AW36 -> 0 | AK35: =SUM(AJ35-AI35) -> 0 | AL35: =S35+L35+G35 -> 0 | AM35: =Y35+AD35 -> 0 | AN35: =AN34 -> 65 | AO35: =(AN35/100)*3000 -> 1950 | AP35: =AP34 -> 35 | AQ35: =(AP35/100)*3000 -> 1050 | AR35: =AR34 -> 73 | AS35: =(AR35/100)*3000 -> 2190 | AT35: =SUM(AO35+AQ35+AS35) -> 5190 | AU35: =AT34-AT35+AV35 -> 0 | AX35: =IF(AV35>0,AW35,AX34) -> 0.8
J36: =SUM(J5:J32)/(COUNT(J5:J32)-COUNTIF(J5:J32,0)) -> 67.333333 | U36: =SUM(U5:U35) -> 20 | V36: =SUM(V5:V35) -> 1617 | AE36: . | AH36: =SUM(AH5:AH35) -> 236 | AL36: =SUM(AL5:AL35) -> 20 | AM36: =SUM(AM5:AM35) -> 2 | AR36: Nb Delivery | AS36: =COUNT(AW5:AW35) -> 0 | AU36: =SUM(AU5:AU35) -> -90 | AV36: =SUM(AV5:AV35) -> 0 | AW36: =SUM(AW5:AW35)/AS36 -> #DIV/0!
V37: =V36/U36 -> 80.85 | AH37: =AF37+AA37 -> 0 | AI37: =SUM(AI5:AI35) -> 1853
AH38: =AF38+AA38 -> 0 | AU38: =AU36*0.51 -> -45.9 | AV38: =AV36/0.51 -> 0 | AW38: =SUM(AW5:AW32)/AS36 -> #DIV/0!
AV39: =AV36*0.51 -> 0

Sheet WATER
D1: =SUM(G21:G33) -> 8197384 | AR1: Entrance | AT1: Tank 1 | AV1: Tank 2
AR2: Level | AW2: Quantity CM3 | AZ2: Var
A3: Date | B3: Truck | C3: Truck M3/day | D3: N0. Trucks | F3: REQ. # of trucks | G3: City | H3: City/day | I3: Total water delivery | K3: SW | L3: Cosum SW/day | M3: RO Guest/ Liter | O3: RO K&L/ Liter | Q3: TOTAL RO Production | R3: RO 1 RH | S3: RO 2 RH | T3: RO water counter | U3: RO Cons m3 | V3: Steam Boiler | W3: Steam Boiler/day | X3: Softener Guest | Y3: Guest Sotf/day | Z3: Softener K&L | AA3: K&L Soft/Day | AB3: Fire Tank Level | AC3: Fire Tank Counter | AE3: Laundry Hot Water Counter | AF3: Hot Water Cons/day | AG3: Laundry Cold Water Counter | AH3: Cold Water Cons/day | AI3: Laundry Water Total Cons | AJ3: K&L Sotf/day | AK3: Guest / day | AL3: K&L /day | AM3: Avg Outside Temp | AN3: Banquet Activity | AR3: Date | AT3: MainI | AV3: Kitchen and Laundry | AX3: Guest | AY3: Main Tank | AZ3: Kitchen and Laundry | BA3: Guest | BB3: Kitchen and Laundry | BC3: Main | BD3: Guest | BE3: Total VAR | BF3: Hotel Consumption
E4: 1.66 | AN4: Ball R | AO4: Meeting | AP4: outlet | AT4: 180 | AV4: 220 | AX4: 580 | AY4: =SUM(AT4) -> 180 | AZ4: =SUM(AV4) -> 220 | BA4: =SUM(AX4) -> 580
A5: =[2]WATER!$A$36 -> 44804 | B5: =[2]WATER!B36 -> 109443 | C5: =[2]WATER!C36 -> 0 | D5: =[2]WATER!D36 -> 0 | E5: =[2]WATER!E36 -> 241.93548 | F5: =[2]WATER!F36 -> 0 | G5: =[2]WATER!G36 -> 630225 | H5: =[2]WATER!H36 -> 122 | I5: =[2]WATER!I36 -> 122 | ... AP5: =[2]WATER!AP36 -> 0 | AR5: =[2]WATER!$AR$36 -> 44804 | AS5: =[2]WATER!AS36 -> 0.9 | AT5: =[2]WATER!AT36 -> 59 | AU5: =[2]WATER!AU36 -> 1.1 | AV5: =[2]WATER!AV36 -> 153 | AW5: =[2]WATER!AW36 -> 2.9 | AX5: =[2]WATER!AX36 -> 102 | AY5: =[2]WATER!AY36 -> 53.1 | AZ5: =[2]WATER!AZ36 -> 168.3 | ... BG5: =[2]WATER!BG36 -> 119.8
A6: =ELEC!C4 -> 44805 | B6: =B5 -> 109443 | C6: =B6-B5 -> 0 | D6: =C6/27 -> 0 | E6: =SUM((C6*$E$4)+(7500/'EDl log'!$A$37)) -> 250 | G6: =G5 -> 630225 | H6: =G6-G5 -> 0 | I6: =C6+H6 -> 0 | J6: =IF(I6>0,E6/I6,0) -> 0 | K6: =K5 -> 7089 | L6: 0 | M6: =M5 -> 457.44 | N6: =SUM(M6-M5) -> 0 | O6: =O5 -> 529.52 | P6: =SUM(O6-O5) -> 0 | Q6: =P6+N6 -> 0 | T6: =T5 -> 5190 | U6: =SUM(T6-T5) -> 0 | V6: =V5 -> 499 | W6: =+V6-V5 -> 0 | X6: =X5 -> 155837 | Y6: =SUM(X6-X5) -> 0 | Z6: =Z5 -> 99668 | AA6: =Z6-Z5 -> 0 | AB6: =AB5 -> 258 | AC6: =AC5 -> 855 | AD6: 0 | AE6: =AE5 -> 248.42 | AF6: =AE6-AE5 -> 0 | AG6: =AG5 -> 2247.41 | AH6: =AG6-AG5 -> 0 | AI6: =AF6+AH6 -> 0 | AJ6: =+Z6-Z5 -> 0 | AK6: =SUM(Y6-L6) -> 0 | AL6: =SUM(AJ6-W6) -> 0 | AM6: ='General information '!D5 -> 29.5 | AN6: ='General information '!H5 -> 0 | AP6: ='General information '!J5 -> 0 | AR6: =A6 -> 44805 | AS6: =AS5 -> 0.9 | AT6: =AT5 -> 59 | AU6: =AU5 -> 1.1 | AV6: 151 | AW6: 2.9 | AX6: 100 | AY6: =AS6*AT6 -> 53.1 | AZ6: =AU6*AV6 -> 166.1 | BA6: =AW6*AX6 -> 290 | BB6: =AY6-AY5 -> 0 | BC6: =AZ6-AZ5 -> -2.2 | BD6: =BA6-BA5 -> -5.8 | BE6: =SUM(BB6:BD6) -> -8 | BF6: =SUM(I6-BE6) -> 8 | BG6: =SUM(I6-BF6) -> -8
A7: =ELEC!C5 -> 44806 | B7: =B6 -> 109443 | C7: =B7-B6 -> 0 | D7: =C7/27 -> 0 | E7: =SUM((C7*$E$4)+(7500/'EDl log'!$A$37)) -> 250 | G7: =G6 -> 630225 | H7: =G7-G6 -> 0 | I7: =C7+H7 -> 0 | J7: =IF(I7>0,E7/I7,0) -> 0 | K7: =K6 -> 7089 | L7: =K7-K6 -> 0 | M7: =M6 -> 457.44 | N7: =SUM(M7-M6) -> 0 | O7: =O6 -> 529.52 | P7: =SUM(O7-O6) -> 0 | Q7: =P7+N7 -> 0 | T7: =T6 -> 5190 | U7: =SUM(T7-T6) -> 0 | V7: =V6 -> 499 | W7: =+V7-V6 -> 0 | X7: =X6 -> 155837 | Y7: =SUM(X7-X6) -> 0 | Z7: =Z6 -> 99668 | AA7: =Z7-Z6 -> 0 | AB7: =AB6 -> 258 | AC7: =AC6 -> 855 | AD7: =AC7-AC6 -> 0 | AE7: =AE6 -> 248.42 | AF7: =AE7-AE6 -> 0 | AG7: =AG6 -> 2247.41 | AH7: =AG7-AG6 -> 0 | AI7: =AF7+AH7 -> 0 | AJ7: =+Z7-Z6 -> 0 | AK7: =SUM(Y7-L7) -> 0 | AL7: =SUM(AJ7-W7) -> 0 | AM7: ='General information '!D6 -> 0 | AN7: ='General information '!H6 -> 0 | AP7: ='General information '!J6 -> 0 | AR7: =A7 -> 44806 | AS7: =AS6 -> 0.9 | AT7: =AT6 -> 59 | AU7: =AU6 -> 1.1 | AV7: =AV6 -> 151 | AW7: 2.9 | AX7: =AX6 -> 100 | AY7: =AS7*AT7 -> 53.1 | AZ7: =AU7*AV7 -> 166.1 | BA7: =AW7*AX7 -> 290 | BB7: =AY7-AY6 -> 0 | BC7: =AZ7-AZ6 -> 0 | BD7: =BA7-BA6 -> 0 | BE7: =SUM(BB7:BD7) -> 0 | BF7: =SUM(I7-BE7) -> 0 | BG7: =SUM(I7-BF7) -> 0
A8: =ELEC!C6 -> 44807 | B8: =B7 -> 109443 | C8: =B8-B7 -> 0 | D8: =C8/27 -> 0 | E8: =SUM((C8*$E$4)+(7500/'EDl log'!$A$37)) -> 250 | G8: =G7 -> 630225 | H8: =G8-G7 -> 0 | I8: =C8+H8 -> 0 | J8: =IF(I8>0,E8/I8,0) -> 0 | K8: =K7 -> 7089 | L8: =K8-K7 -> 0 | M8: =M7 -> 457.44 | N8: =SUM(M8-M7) -> 0 | O8: =O7 -> 529.52 | P8: =SUM(O8-O7) -> 0 | Q8: =P8+N8 -> 0 | T8: =T7 -> 5190 | U8: =SUM(T8-T7) -> 0 | V8: =V7 -> 499 | W8: =+V8-V7 -> 0 | X8: =X7 -> 155837 | Y8: =SUM(X8-X7) -> 0 | Z8: =Z7 -> 99668 | AA8: =Z8-Z7 -> 0 | AB8: =AB7 -> 258 | AC8: =AC7 -> 855 | AD8: =AC8-AC7 -> 0 | AE8: =AE7 -> 248.42 | AF8: =AE8-AE7 -> 0 | AG8: =AG7 -> 2247.41 | AH8: =AG8-AG7 -> 0 | AI8: =AF8+AH8 -> 0 | AJ8: =+Z8-Z7 -> 0 | AK8: =SUM(Y8-L8) -> 0 | AL8: =SUM(AJ8-W8) -> 0 | AM8: ='General information '!D7 -> 0 | AN8: ='General information '!H7 -> 0 | AP8: ='General information '!J7 -> 0 | AR8: =A8 -> 44807 | AS8: =AS7 -> 0.9 | AT8: =AT7 -> 59 | AU8: 1.1 | AV8: =AV7 -> 151 | AW8: 2.9 | AX8: =AX7 -> 100 | AY8: =AS8*AT8 -> 53.1 | AZ8: =AU8*AV8 -> 166.1 | BA8: =AW8*AX8 -> 290 | BB8: =AY8-AY7 -> 0 | BC8: =AZ8-AZ7 -> 0 | BD8: =BA8-BA7 -> 0 | BE8: =SUM(BB8:BD8) -> 0 | BF8: =SUM(I8-BE8) -> 0 | BG8: =SUM(I8-BF8) -> 0
A9: =ELEC!C7 -> 44808 | B9: =B8 -> 109443 | C9: =B9-B8 -> 0 | D9: =C9/27 -> 0 | E9: =SUM((C9*$E$4)+(7500/'EDl log'!$A$37)) -> 250 | G9: 630359 | H9: =G9-G8 -> 134 | I9: =C9+H9 -> 134 | J9: =IF(I9>0,E9/I9,0) -> 1.8656716 | K9: =K8 -> 7089 | L9: =K9-K8 -> 0 | M9: =M8 -> 457.44 | N9: =SUM(M9-M8) -> 0 | O9: =O8 -> 529.52 | P9: =SUM(O9-O8) -> 0 | Q9: =P9+N9 -> 0 | T9: =T8 -> 5190 | U9: =SUM(T9-T8) -> 0 | V9: =V8 -> 499 | W9: =+V9-V8 -> 0 | X9: =X8 -> 155837 | Y9: =SUM(X9-X8) -> 0 | Z9: =Z8 -> 99668 | AA9: =Z9-Z8 -> 0 | AB9: =AB8 -> 258 | AC9: =AC8 -> 855 | AD9: =AC9-AC8 -> 0 | AE9: =AE8 -> 248.42 | AF9: =AE9-AE8 -> 0 | AG9: =AG8 -> 2247.41 | AH9: =AG9-AG8 -> 0 | AI9: =AF9+AH9 -> 0 | AJ9: =+Z9-Z8 -> 0 | AK9: =SUM(Y9-L9) -> 0 | AL9: =SUM(AJ9-W9) -> 0 | AM9: ='General information '!D8 -> 27.5 | AN9: ='General information '!H8 -> 0 | AP9: ='General information '!J8 -> 0 | AR9: =A9 -> 44808 | AS9: =AS8 -> 0.9 | AT9: 140 | AU9: =AU8 -> 1.1 | AV9: =AV8 -> 151 | AW9: 2.9 | AX9: 99 | AY9: =AS9*AT9 -> 126 | AZ9: =AU9*AV9 -> 166.1 | BA9: =AW9*AX9 -> 287.1 | BB9: =AY9-AY8 -> 72.9 | BC9: =AZ9-AZ8 -> 0 | BD9: =BA9-BA8 -> -2.9 | BE9: =SUM(BB9:BD9) -> 70 | BF9: =SUM(I9-BE9) -> 64 | BG9: =SUM(I9-BF9) -> 70
A10: =ELEC!C8 -> 44809 | B10: =B9 -> 109443 | C10: =B10-B9 -> 0 | D10: =C10/27 -> 0 | E10: =SUM((C10*$E$4)+(7500/'EDl log'!$A$37)) -> 250 | G10: =G9 -> 630359 | H10: =G10-G9 -> 0 | I10: =C10+H10 -> 0 | J10: =IF(I10>0,E10/I10,0) -> 0 | K10: =K9 -> 7089 | L10: =K10-K9 -> 0 | M10: =M9 -> 457.44 | N10: =SUM(M10-M9) -> 0 | O10: =O9 -> 529.52 | P10: =SUM(O10-O9) -> 0 | Q10: =P10+N10 -> 0 | T10: =T9 -> 5190 | U10: =SUM(T10-T9) -> 0 | V10: =V9 -> 499 | W10: =+V10-V9 -> 0 | X10: =X9 -> 155837 | Y10: =SUM(X10-X9) -> 0 | Z10: =Z9 -> 99668 | AA10: =Z10-Z9 -> 0 | AB10: =AB9 -> 258 | AC10: =AC9 -> 855 | AD10: =AC10-AC9 -> 0 | AE10: =AE9 -> 248.42 | AF10: =AE10-AE9 -> 0 | AG10: =AG9 -> 2247.41 | AH10: =AG10-AG9 -> 0 | AI10: =AF10+AH10 -> 0 | AJ10: =+Z10-Z9 -> 0 | AK10: =SUM(Y10-L10) -> 0 | AL10: =SUM(AJ10-W10) -> 0 | AM10: ='General information '!D9 -> 27.5 | AN10: ='General information '!H9 -> 0 | AP10: ='General information '!J9 -> 0 | AR10: =A10 -> 44809 | AS10: =AS9 -> 0.9 | AT10: 90 | AU10: =AU9 -> 1.1 | AV10: 149 | AW10: 2.9 | AX10: 110 | AY10: =AS10*AT10 -> 81 | AZ10: =AU10*AV10 -> 163.9 | BA10: =AW10*AX10 -> 319 | BB10: =AY10-AY9 -> -45 | BC10: =AZ10-AZ9 -> -2.2 | BD10: =BA10-BA9 -> 31.9 | BE10: =SUM(BB10:BD10) -> -15.3 | BF10: =SUM(I10-BE10) -> 15.3 | BG10: =SUM(I10-BF10) -> -15.3
A11: =ELEC!C9 -> 44810 | B11: =B10 -> 109443 | C11: =B11-B10 -> 0 | D11: =C11/27 -> 0 | E11: =SUM((C11*$E$4)+(7500/'EDl log'!$A$37)) -> 250 | G11: =G10 -> 630359 | H11: =G11-G10 -> 0 | I11: =C11+H11 -> 0 | J11: =IF(I11>0,E11/I11,0) -> 0 | K11: =K10 -> 7089 | L11: =K11-K10 -> 0 | M11: =M10 -> 457.44 | N11: =SUM(M11-M10) -> 0 | O11: =O10 -> 529.52 | P11: =SUM(O11-O10) -> 0 | Q11: =SUM(P11+N11) -> 0 | T11: =T10 -> 5190 | U11: =SUM(T11-T10) -> 0 | V11: =V10 -> 499 | W11: =+V11-V10 -> 0 | X11: =X10 -> 155837 | Y11: =SUM(X11-X10) -> 0 | Z11: =Z10 -> 99668 | AA11: =Z11-Z10 -> 0 | AB11: =AB10 -> 258 | AC11: =AC10 -> 855 | AD11: =AC11-AC10 -> 0 | AE11: =AE10 -> 248.42 | AF11: =AE11-AE10 -> 0 | AG11: =AG10 -> 2247.41 | AH11: =AG11-AG10 -> 0 | AI11: =AF11+AH11 -> 0 | AJ11: =+Z11-Z10 -> 0 | AK11: =SUM(Y11-L11) -> 0 | AL11: =SUM(AJ11-W11) -> 0 | AM11: ='General information '!D10 -> 28 | AN11: ='General information '!H10 -> 0 | AP11: ='General information '!J10 -> 0 | AR11: =A11 -> 44810 | AS11: =AS10 -> 0.9 | AT11: 79 | AU11: =AU10 -> 1.1 | AV11: 147 | AW11: 2.9 | AX11: 109 | AY11: =AS11*AT11 -> 71.1 | AZ11: =AU11*AV11 -> 161.7 | BA11: =AW11*AX11 -> 316.1 | BB11: =AY11-AY10 -> -9.9 | BC11: =AZ11-AZ10 -> -2.2 | BD11: =BA11-BA10 -> -2.9 | BE11: =SUM(BB11:BD11) -> -15 | BF11: =SUM(I11-BE11) -> 15 | BG11: =SUM(I11-BF11) -> -15
A12: =ELEC!C10 -> 44811 | B12: =B11 -> 109443 | C12: =B12-B11 -> 0 | D12: =C12/27 -> 0 | E12: =SUM((C12*$E$4)+(7500/'EDl log'!$A$37)) -> 250 | G12: 630471 | H12: =G12-G11 -> 112 | I12: =C12+H12 -> 112 | J12: =IF(I12>0,E12/I12,0) -> 2.2321429 | K12: =K11 -> 7089 | L12: =K12-K11 -> 0 | M12: =M11 -> 457.44 | N12: =SUM(M12-M11) -> 0 | O12: =O11 -> 529.52 | P12: =SUM(O12-O11) -> 0 | Q12: =SUM(P12+N12) -> 0 | T12: =T11 -> 5190 | U12: =SUM(T12-T11) -> 0 | V12: =V11 -> 499 | W12: =+V12-V11 -> 0 | X12: =X11 -> 155837 | Y12: =SUM(X12-X11) -> 0 | Z12: =Z11 -> 99668 | AA12: =Z12-Z11 -> 0 | AB12: =AB11 -> 258 | AC12: =AC11 -> 855 | AD12: =AC12-AC11 -> 0 | AE12: 248.9 | AF12: =AE12-AE11 -> 0.48 | AG12: =AG11 -> 2247.41 | AH12: =AG12-AG11 -> 0 | AI12: =AF12+AH12 -> 0.48 | AJ12: =+Z12-Z11 -> 0 | AK12: =SUM(Y12-L12) -> 0 | AL12: =SUM(AJ12-W12) -> 0 | AM12: ='General information '!D11 -> 28 | AN12: ='General information '!H11 -> 0 | AP12: ='General information '!J11 -> 0 | AR12: =A12 -> 44811 | AS12: =AS11 -> 0.9 | AT12: 146 | AU12: =AU11 -> 1.1 | AV12: 144 | AW12: 2.9 | AX12: 104 | AY12: =AS12*AT12 -> 131.4 | AZ12: =AU12*AV12 -> 158.4 | BA12: =AW12*AX12 -> 301.6 | BB12: =AY12-AY11 -> 60.3 | BC12: =AZ12-AZ11 -> -3.3 | BD12: =BA12-BA11 -> -14.5 | BE12: =SUM(BB12:BD12) -> 42.5 | BF12: =SUM(I12-BE12) -> 69.5 | BG12: =SUM(I12-BF12) -> 42.5
A13: =ELEC!C11 -> 44812 | B13: =B12 -> 109443 | C13: =B13-B12 -> 0 | D13: =C13/27 -> 0 | E13: =SUM((C13*$E$4)+(7500/'EDl log'!$A$37)) -> 250 | G13: =G12 -> 630471 | H13: =G13-G12 -> 0 | I13: =C13+H13 -> 0 | J13: =IF(I13>0,E13/I13,0) -> 0 | K13: =K12 -> 7089 | L13: =K13-K12 -> 0 | M13: =M12 -> 457.44 | N13: =SUM(M13-M12) -> 0 | O13: =O12 -> 529.52 | P13: =SUM(O13-O12) -> 0 | Q13: =SUM(P13+N13) -> 0 | T13: 5191 | U13: =SUM(T13-T12) -> 1 | V13: =V12 -> 499 | W13: =+V13-V12 -> 0 | X13: =X12 -> 155837 | Y13: =SUM(X13-X12) -> 0 | Z13: =Z12 -> 99668 | AA13: =Z13-Z12 -> 0 | AB13: =AB12 -> 258 | AC13: =AC12 -> 855 | AD13: =AC13-AC12 -> 0 | AE13: =AE12 -> 248.9 | AF13: =AE13-AE12 -> 0 | AG13: =AG12 -> 2247.41 | AH13: =AG13-AG12 -> 0 | AI13: =AF13+AH13 -> 0 | AJ13: =+Z13-Z12 -> 0 | AK13: =SUM(Y13-L13) -> 0 | AL13: =SUM(AJ13-W13) -> 0 | AM13: ='General information '!D12 -> 29 | AN13: ='General information '!J12 -> 0 | AP13: ='General information '!J12 -> 0 | AR13: =A13 -> 44812 | AS13: =AS12 -> 0.9 | AT13: =AT12 -> 146 | AU13: =AU12 -> 1.1 | AV13: 143 | AW13: 2.9 | AX13: 109 | AY13: =AS13*AT13 -> 131.4 | AZ13: =AU13*AV13 -> 157.3 | BA13: =AW13*AX13 -> 316.1 | BB13: =AY13-AY12 -> 0 | BC13: =AZ13-AZ12 -> -1.1 | BD13: =BA13-BA12 -> 14.5 | BE13: =SUM(BB13:BD13) -> 13.4 | BF13: =SUM(I13-BE13) -> -13.4 | BG13: =SUM(I13-BF13) -> 13.4
A14: =ELEC!C12 -> 44813 | B14: =B13 -> 109443 | C14: =B14-B13 -> 0 | D14: =C14/27 -> 0 | E14: =SUM((C14*$E$4)+(7500/'EDl log'!$A$37)) -> 250 | G14: =G13 -> 630471 | H14: =G14-G13 -> 0 | I14: =C14+H14 -> 0 | J14: =IF(I14>0,E14/I14,0) -> 0 | K14: =K13 -> 7089 | L14: =K14-K13 -> 0 | M14: =M13 -> 457.44 | N14: =SUM(M14-M13) -> 0 | O14: =O13 -> 529.52 | P14: =SUM(O14-O13) -> 0 | Q14: =SUM(P14+N14) -> 0 | T14: =T13 -> 5191 | U14: =SUM(T14-T13) -> 0 | V14: =V13 -> 499 | W14: =+V14-V13 -> 0 | X14: =X13 -> 155837 | Y14: =SUM(X14-X13) -> 0 | Z14: =Z13 -> 99668 | AA14: =Z14-Z13 -> 0 | AB14: =AB13 -> 258 | AC14: =AC13 -> 855 | AD14: =AC14-AC13 -> 0 | AE14: =AE13 -> 248.9 | AF14: =AE14-AE13 -> 0 | AG14: 2247.41 | AH14: =AG14-AG13 -> 0 | AI14: =AF14+AH14 -> 0 | AJ14: =+Z14-Z13 -> 0 | AK14: =SUM(Y14-L14) -> 0 | AL14: =SUM(AJ14-W14) -> 0 | AM14: ='General information '!D13 -> 0 | AN14: ='General information '!H13 -> 0 | AP14: ='General information '!J13 -> 0 | AR14: =A14 -> 44813 | AS14: =AS13 -> 0.9 | AT14: =AT13 -> 146 | AU14: =AU13 -> 1.1 | AV14: =AV13 -> 143 | AW14: 2.9 | AX14: =AX13 -> 109 | AY14: =AS14*AT14 -> 131.4 | AZ14: =AU14*AV14 -> 157.3 | BA14: =AW14*AX14 -> 316.1 | BB14: =AY14-AY13 -> 0 | BC14: =AZ14-AZ13 -> 0 | BD14: =BA14-BA13 -> 0 | BE14: =SUM(BB14:BD14) -> 0 | BF14: =SUM(I14-BE14) -> 0 | BG14: =SUM(I14-BF14) -> 0
A15: =ELEC!C13 -> 44814 | B15: =B14 -> 109443 | C15: =B15-B14 -> 0 | D15: =C15/27 -> 0 | E15: =SUM((C15*$E$4)+(7500/'EDl log'!$A$37)) -> 250 | G15: =G14 -> 630471 | H15: =G15-G14 -> 0 | I15: =C15+H15 -> 0 | J15: =IF(I15>0,E15/I15,0) -> 0 | K15: =K14 -> 7089 | L15: =K15-K14 -> 0 | M15: =M14 -> 457.44 | N15: =SUM(M15-M14) -> 0 | O15: =O14 -> 529.52 | P15: =SUM(O15-O14) -> 0 | Q15: =SUM(P15+N15) -> 0 | T15: =T14 -> 5191 | U15: =SUM(T15-T14) -> 0 | V15: =V14 -> 499 | W15: =+V15-V14 -> 0 | X15: =X14 -> 155837 | Y15: =SUM(X15-X14) -> 0 | Z15: =Z14 -> 99668 | AA15: =Z15-Z14 -> 0 | AB15: =AB14 -> 258 | AC15: =AC14 -> 855 | AD15: =AC15-AC14 -> 0 | AE15: =AE14 -> 248.9 | AF15: =AE15-AE14 -> 0 | AG15: =AG14 -> 2247.41 | AH15: =AG15-AG14 -> 0 | AI15: =AF15+AH15 -> 0 | AJ15: =+Z15-Z14 -> 0 | AK15: =SUM(Y15-L15) -> 0 | AL15: =SUM(AJ15-W15) -> 0 | AM15: ='General information '!D14 -> 0 | AN15: ='General information '!H14 -> 0 | AP15: ='General information '!J14 -> 0 | AR15: =A15 -> 44814 | AS15: =AS14 -> 0.9 | AT15: =AT14 -> 146 | AU15: =AU14 -> 1.1 | AV15: =AV14 -> 143 | AW15: 2.9 | AX15: =AX14 -> 109 | AY15: =AS15*AT15 -> 131.4 | AZ15: =AU15*AV15 -> 157.3 | BA15: =AW15*AX15 -> 316.1 | BB15: =AY15-AY14 -> 0 | BC15: =AZ15-AZ14 -> 0 | BD15: =BA15-BA14 -> 0 | BE15: =SUM(BB15:BD15) -> 0 | BF15: =SUM(I15-BE15) -> 0 | BG15: =SUM(I15-BF15) -> 0
A16: =ELEC!C14 -> 44815 | B16: =B15 -> 109443 | C16: =B16-B15 -> 0 | D16: =C16/27 -> 0 | E16: =SUM((C16*$E$4)+(7500/'EDl log'!$A$37)) -> 250 | G16: 630568 | H16: =G16-G15 -> 97 | I16: =C16+H16 -> 97 | J16: =IF(I16>0,E16/I16,0) -> 2.5773196 | K16: =K15 -> 7089 | L16: =K16-K15 -> 0 | M16: =M15 -> 457.44 | N16: =SUM(M16-M15) -> 0 | O16: =O15 -> 529.52 | P16: =SUM(O16-O15) -> 0 | Q16: =SUM(P16+N16) -> 0 | T16: =T15 -> 5191 | U16: =SUM(T16-T15) -> 0 | V16: =V15 -> 499 | W16: =+V16-V15 -> 0 | X16: =X15 -> 155837 | Y16: =SUM(X16-X15) -> 0 | Z16: =Z15 -> 99668 | AA16: =Z16-Z15 -> 0 | AB16: =AB15 -> 258 | AC16: =AC15 -> 855 | AD16: =AC16-AC15 -> 0 | AE16: =AE15 -> 248.9 | AF16: =AE16-AE15 -> 0 | AG16: =AG15 -> 2247.41 | AH16: =AG16-AG15 -> 0 | AI16: =AF16+AH16 -> 0 | AJ16: =+Z16-Z15 -> 0 | AK16: =SUM(Y16-L16) -> 0 | AL16: =SUM(AJ16-W16) -> 0 | AM16: ='General information '!D15 -> 27 | AN16: ='General information '!H15 -> 0 | AP16: ='General information '!J15 -> 0 | AR16: =A16 -> 44815 | AS16: =AS15 -> 0.9 | AT16: 210 | AU16: =AU15 -> 1.1 | AV16: 139 | AW16: 2.9 | AX16: 100 | AY16: =AS16*AT16 -> 189 | AZ16: =AU16*AV16 -> 152.9 | BA16: =AW16*AX16 -> 290 | BB16: =AY16-AY15 -> 57.6 | BC16: =AZ16-AZ15 -> -4.4 | BD16: =BA16-BA15 -> -26.1 | BE16: =SUM(BB16:BD16) -> 27.1 | BF16: =SUM(I16-BE16) -> 69.9 | BG16: =SUM(I16-BF16) -> 27.1
A17: =ELEC!C15 -> 44816 | B17: =B16 -> 109443 | C17: =B17-B16 -> 0 | D17: =C17/27 -> 0 | E17: =SUM((C17*$E$4)+(7500/'EDl log'!$A$37)) -> 250 | G17: =G16 -> 630568 | H17: =G17-G16 -> 0 | I17: =C17+H17 -> 0 | J17: =IF(I17>0,E17/I17,0) -> 0 | K17: =K16 -> 7089 | L17: =K17-K16 -> 0 | M17: =M16 -> 457.44 | N17: =SUM(M17-M16) -> 0 | O17: =O16 -> 529.52 | P17: =SUM(O17-O16) -> 0 | Q17: =SUM(P17+N17) -> 0 | T17: =T16 -> 5191 | U17: =SUM(T17-T16) -> 0 | V17: =V16 -> 499 | W17: =+V17-V16 -> 0 | X17: 155960 | Y17: =SUM(X17-X16) -> 123 | Z17: =Z16 -> 99668 | AA17: =Z17-Z16 -> 0 | AB17: =AB16 -> 258 | AC17: =AC16 -> 855 | AD17: =AC17-AC16 -> 0 | AE17: =AE16 -> 248.9 | AF17: =AE17-AE16 -> 0 | AG17: =AG16 -> 2247.41 | AH17: =AG17-AG16 -> 0 | AI17: =AF17+AH17 -> 0 | AJ17: =+Z17-Z16 -> 0 | AK17: =SUM(Y17-L17) -> 123 | AL17: =SUM(AJ17-W17) -> 0 | AM17: ='General information '!D16 -> 27 | AN17: ='General information '!H16 -> 0 | AP17: ='General information '!J16 -> 0 | AR17: =A17 -> 44816 | AS17: =AS16 -> 0.9 | AT17: 105 | AU17: =AU16 -> 1.1 | AV17: 138 | AW17: 2.9 | AX17: 120 | AY17: =AS17*AT17 -> 94.5 | AZ17: =AU17*AV17 -> 151.8 | BA17: =AW17*AX17 -> 348 | BB17: =AY17-AY16 -> -94.5 | BC17: =AZ17-AZ16 -> -1.1 | BD17: =BA17-BA16 -> 58 | BE17: =SUM(BB17:BD17) -> -37.6 | BF17: =SUM(I17-BE17) -> 37.6 | BG17: =SUM(I17-BF17) -> -37.6
A18: =ELEC!C16 -> 44817 | B18: =B17 -> 109443 | C18: =B18-B17 -> 0 | D18: =C18/27 -> 0 | E18: =SUM((C18*$E$4)+(7500/'EDl log'!$A$37)) -> 250 | G18: =G17 -> 630568 | H18: =G18-G17 -> 0 | I18: =C18+H18 -> 0 | J18: =IF(I18>0,E18/I18,0) -> 0 | K18: =K17 -> 7089 | L18: =K18-K17 -> 0 | M18: =M17 -> 457.44 | N18: =SUM(M18-M17) -> 0 | O18: =O17 -> 529.52 | P18: =SUM(O18-O17) -> 0 | Q18: =SUM(P18+N18) -> 0 | T18: =T17 -> 5191 | U18: =SUM(T18-T17) -> 0 | V18: =V17 -> 499 | W18: =+V18-V17 -> 0 | X18: =X17 -> 155960 | Y18: =SUM(X18-X17) -> 0 | Z18: =Z17 -> 99668 | AA18: =Z18-Z17 -> 0 | AB18: =AB17 -> 258 | AC18: =AC17 -> 855 | AD18: =AC18-AC17 -> 0 | AE18: =AE17 -> 248.9 | AF18: =AE18-AE17 -> 0 | AG18: =AG17 -> 2247.41 | AH18: =AG18-AG17 -> 0 | AI18: =AF18+AH18 -> 0 | AJ18: =+Z18-Z17 -> 0 | AK18: =SUM(Y18-L18) -> 0 | AL18: =SUM(AJ18-W18) -> 0 | AM18: ='General information '!D17 -> 26 | AN18: ='General information '!H17 -> 0 | AP18: ='General information '!J17 -> 0 | AR18: =A18 -> 44817 | AS18: =AS17 -> 0.9 | AT18: 91 | AU18: =AU17 -> 1.1 | AV18: 136 | AW18: 2.9 | AX18: 119 | AY18: =AS18*AT18 -> 81.9 | AZ18: =AU18*AV18 -> 149.6 | BA18: =AW18*AX18 -> 345.1 | BB18: =AY18-AY17 -> -12.6 | BC18: =AZ18-AZ17 -> -2.2 | BD18: =BA18-BA17 -> -2.9 | BE18: =SUM(BB18:BD18) -> -17.7 | BF18: =SUM(I18-BE18) -> 17.7 | BG18: =SUM(I18-BF18) -> -17.7
A19: =ELEC!C17 -> 44818 | B19: =B18 -> 109443 | C19: =B19-B18 -> 0 | D19: =C19/27 -> 0 | E19: =SUM((C19*$E$4)+(7500/'EDl log'!$A$37)) -> 250 | G19: =G18 -> 630568 | H19: =G19-G18 -> 0 | I19: =C19+H19 -> 0 | J19: =IF(I19>0,E19/I19,0) -> 0 | K19: =K18 -> 7089 | L19: =K19-K18 -> 0 | M19: =M18 -> 457.44 | N19: =SUM(M19-M18) -> 0 | O19: =O18 -> 529.52 | P19: =SUM(O19-O18) -> 0 | Q19: =SUM(P19+N19) -> 0 | T19: =T18 -> 5191 | U19: =SUM(T19-T18) -> 0 | V19: =V18 -> 499 | W19: =+V19-V18 -> 0 | X19: =X18 -> 155960 | Y19: =SUM(X19-X18) -> 0 | Z19: =Z18 -> 99668 | AA19: =Z19-Z18 -> 0 | AB19: =AB18 -> 258 | AC19: =AC18 -> 855 | AD19: =AC19-AC18 -> 0 | AE19: =AE18 -> 248.9 | AF19: =AE19-AE18 -> 0 | AG19: =AG18 -> 2247.41 | AH19: =AG19-AG18 -> 0 | AI19: =AF19+AH19 -> 0 | AJ19: =+Z19-Z18 -> 0 | AK19: =SUM(Y19-L19) -> 0 | AL19: =SUM(AJ19-W19) -> 0 | AM19: ='General information '!D18 -> 28 | AN19: ='General information '!H18 -> 0 | AP19: ='General information '!J18 -> 0 | AR19: =A19 -> 44818 | AS19: =AS18 -> 0.9 | AT19: =AT18 -> 91 | AU19: =AU18 -> 1.1 | AV19: 132 | AW19: 2.9 | AX19: 117 | AY19: =AS19*AT19 -> 81.9 | AZ19: =AU19*AV19 -> 145.2 | BA19: =AW19*AX19 -> 339.3 | BB19: =AY19-AY18 -> 0 | BC19: =AZ19-AZ18 -> -4.4 | BD19: =BA19-BA18 -> -5.8 | BE19: =SUM(BB19:BD19) -> -10.2 | BF19: =SUM(I19-BE19) -> 10.2 | BG19: =SUM(I19-BF19) -> -10.2
A20: =ELEC!C18 -> 44819 | B20: =B19 -> 109443 | C20: =B20-B19 -> 0 | D20: =C20/27 -> 0 | E20: =SUM((C20*$E$4)+(7500/'EDl log'!$A$37)) -> 250 | G20: =G19 -> 630568 | H20: =G20-G19 -> 0 | I20: =C20+H20 -> 0 | J20: =IF(I20>0,E20/I20,0) -> 0 | K20: =K19 -> 7089 | L20: =K20-K19 -> 0 | M20: =M19 -> 457.44 | N20: =SUM(M20-M19) -> 0 | O20: =O19 -> 529.52 | P20: =SUM(O20-O19) -> 0 | Q20: =SUM(P20+N20) -> 0 | T20: =T19 -> 5191 | U20: =SUM(T20-T19) -> 0 | V20: =V19 -> 499 | W20: =+V20-V19 -> 0 | X20: =X19 -> 155960 | Y20: =SUM(X20-X19) -> 0 | Z20: =Z19 -> 99668 | AA20: =Z20-Z19 -> 0 | AB20: =AB19 -> 258 | AC20: =AC19 -> 855 | AD20: =AC20-AC19 -> 0 | AE20: =AE19 -> 248.9 | AF20: =AE20-AE19 -> 0 | AG20: =AG19 -> 2247.41 | AH20: =AG20-AG19 -> 0 | AI20: =AF20+AH20 -> 0 | AJ20: =+Z20-Z19 -> 0 | AK20: =SUM(Y20-L20) -> 0 | AL20: =SUM(AJ20-W20) -> 0 | AM20: ='General information '!D19 -> 27 | AN20: ='General information '!H19 -> 0 | AP20: ='General information '!J19 -> 0 | AR20: =A20 -> 44819 | AS20: =AS19 -> 0.9 | AT20: =AT19 -> 91 | AU20: =AU19 -> 1.1 | AV20: =AV19 -> 132 | AW20: 2.9 | AX20: =AX19 -> 117 | AY20: =AS20*AT20 -> 81.9 | AZ20: =AU20*AV20 -> 145.2 | BA20: =AW20*AX20 -> 339.3 | BB20: =AY20-AY19 -> 0 | BC20: =AZ20-AZ19 -> 0 | BD20: =BA20-BA19 -> 0 | BE20: =SUM(BB20:BD20) -> 0 | BF20: =SUM(I20-BE20) -> 0 | BG20: =SUM(I20-BF20) -> 0
A21: =ELEC!C19 -> 44820 | B21: =B20 -> 109443 | C21: =B21-B20 -> 0 | D21: =C21/27 -> 0 | E21: =SUM((C21*$E$4)+(7500/'EDl log'!$A$37)) -> 250 | G21: =G20 -> 630568 | H21: =G21-G20 -> 0 | I21: =C21+H21 -> 0 | J21: =IF(I21>0,E21/I21,0) -> 0 | K21: =K20 -> 7089 | L21: =K21-K20 -> 0 | M21: =M20 -> 457.44 | N21: =SUM(M21-M20) -> 0 | O21: =O20 -> 529.52 | P21: =SUM(O21-O20) -> 0 | Q21: =SUM(P21+N21) -> 0 | T21: =T20 -> 5191 | U21: =SUM(T21-T20) -> 0 | V21: =V20 -> 499 | W21: =+V21-V20 -> 0 | X21: =X20 -> 155960 | Y21: =SUM(X21-X20) -> 0 | Z21: =Z20 -> 99668 | AA21: =Z21-Z20 -> 0 | AB21: =AB20 -> 258 | AC21: =AC20 -> 855 | AD21: =AC21-AC20 -> 0 | AE21: =AE20 -> 248.9 | AF21: =AE21-AE20 -> 0 | AG21: =AG20 -> 2247.41 | AH21: =AG21-AG20 -> 0 | AI21: =AF21+AH21 -> 0 | AJ21: =+Z21-Z20 -> 0 | AK21: =SUM(Y21-L21) -> 0 | AL21: =SUM(AJ21-W21) -> 0 | AM21: ='General information '!D20 -> 0 | AN21: ='General information '!H20 -> 0 | AP21: ='General information '!J20 -> 0 | AR21: =A21 -> 44820 | AS21: =AS20 -> 0.9 | AT21: =AT20 -> 91 | AU21: =AU20 -> 1.1 | AV21: =AV20 -> 132 | AW21: 2.9 | AX21: =AX20 -> 117 | AY21: =AS21*AT21 -> 81.9 | AZ21: =AU21*AV21 -> 145.2 | BA21: =AW21*AX21 -> 339.3 | BB21: =AY21-AY20 -> 0 | BC21: =AZ21-AZ20 -> 0 | BD21: =BA21-BA20 -> 0 | BE21: =SUM(BB21:BD21) -> 0 | BF21: =SUM(I21-BE21) -> 0 | BG21: =SUM(I21-BF21) -> 0
A22: =ELEC!C20 -> 44821 | B22: =B21 -> 109443 | C22: =B22-B21 -> 0 | D22: =C22/27 -> 0 | E22: =SUM((C22*$E$4)+(7500/'EDl log'!$A$37)) -> 250 | G22: =G21 -> 630568 | H22: =G22-G21 -> 0 | I22: =C22+H22 -> 0 | J22: =IF(I22>0,E22/I22,0) -> 0 | K22: =K21 -> 7089 | L22: =K22-K21 -> 0 | M22: =M21 -> 457.44 | N22: =SUM(M22-M21) -> 0 | O22: =O21 -> 529.52 | P22: =SUM(O22-O21) -> 0 | Q22: =SUM(P22+N22) -> 0 | T22: =T21 -> 5191 | U22: =SUM(T22-T21) -> 0 | V22: =V21 -> 499 | W22: =+V22-V21 -> 0 | X22: =X21 -> 155960 | Y22: =SUM(X22-X21) -> 0 | Z22: =Z21 -> 99668 | AA22: =Z22-Z21 -> 0 | AB22: =AB21 -> 258 | AC22: =AC21 -> 855 | AD22: =AC22-AC21 -> 0 | AE22: =AE21 -> 248.9 | AF22: =AE22-AE21 -> 0 | AG22: =AG21 -> 2247.41 | AH22: =AG22-AG21 -> 0 | AI22: =AF22+AH22 -> 0 | AJ22: =+Z22-Z21 -> 0 | AK22: =SUM(Y22-L22) -> 0 | AL22: =SUM(AJ22-W22) -> 0 | AM22: ='General information '!D21 -> 0 | AN22: ='General information '!H21 -> 0 | AP22: ='General information '!J21 -> 0 | AR22: =A22 -> 44821 | AS22: =AS21 -> 0.9 | AT22: =AT21 -> 91 | AU22: =AU21 -> 1.1 | AV22: =AV21 -> 132 | AW22: 2.9 | AX22: =AX21 -> 117 | AY22: =AS22*AT22 -> 81.9 | AZ22: =AU22*AV22 -> 145.2 | BA22: =AW22*AX22 -> 339.3 | BB22: =AY22-AY21 -> 0 | BC22: =AZ22-AZ21 -> 0 | BD22: =BA22-BA21 -> 0 | BE22: =SUM(BB22:BD22) -> 0 | BF22: =SUM(I22-BE22) -> 0 | BG22: =SUM(I22-BF22) -> 0
A23: =ELEC!C21 -> 44822 | B23: =B22 -> 109443 | C23: =B23-B22 -> 0 | D23: =C23/27 -> 0 | E23: =SUM((C23*$E$4)+(7500/'EDl log'!$A$37)) -> 250 | G23: =G22 -> 630568 | H23: =G23-G22 -> 0 | I23: =C23+H23 -> 0 | J23: =IF(I23>0,E23/I23,0) -> 0 | K23: =K22 -> 7089 | L23: =K23-K22 -> 0 | M23: =M22 -> 457.44 | N23: =SUM(M23-M22) -> 0 | O23: =O22 -> 529.52 | P23: =SUM(O23-O22) -> 0 | Q23: =SUM(P23+N23) -> 0 | T23: =T22 -> 5191 | U23: =SUM(T23-T22) -> 0 | V23: =V22 -> 499 | W23: =+V23-V22 -> 0 | X23: =X22 -> 155960 | Y23: =SUM(X23-X22) -> 0 | Z23: =Z22 -> 99668 | AA23: =Z23-Z22 -> 0 | AB23: =AB22 -> 258 | AC23: =AC22 -> 855 | AD23: =AC23-AC22 -> 0 | AE23: =AE22 -> 248.9 | AF23: =AE23-AE22 -> 0 | AG23: =AG22 -> 2247.41 | AH23: =AG23-AG22 -> 0 | AI23: =AF23+AH23 -> 0 | AJ23: =+Z23-Z22 -> 0 | AK23: =SUM(Y23-L23) -> 0 | AL23: =SUM(AJ23-W23) -> 0 | AM23: ='General information '!D22 -> 27 | AN23: ='General information '!H22 -> 0 | AP23: ='General information '!J22 -> 0 | AR23: =A23 -> 44822 | AS23: =AS22 -> 0.9 | AT23: 90 | AU23: =AU22 -> 1.1 | AV23: 130 | AW23: 2.9 | AX23: 113 | AY23: =AS23*AT23 -> 81 | AZ23: =AU23*AV23 -> 143 | BA23: =AW23*AX23 -> 327.7 | BB23: =AY23-AY22 -> -0.9 | BC23: =AZ23-AZ22 -> -2.2 | BD23: =BA23-BA22 -> -11.6 | BE23: =SUM(BB23:BD23) -> -14.7 | BF23: =SUM(I23-BE23) -> 14.7 | BG23: =SUM(I23-BF23) -> -14.7
A24: =ELEC!C22 -> 44823 | B24: =B23 -> 109443 | C24: =B24-B23 -> 0 | D24: =C24/27 -> 0 | E24: =SUM((C24*$E$4)+(7500/'EDl log'!$A$37)) -> 250 | G24: =G23 -> 630568 | H24: =G24-G23 -> 0 | I24: =C24+H24 -> 0 | J24: =IF(I24>0,E24/I24,0) -> 0 | K24: =K23 -> 7089 | L24: =K24-K23 -> 0 | M24: =M23 -> 457.44 | N24: =SUM(M24-M23) -> 0 | O24: =O23 -> 529.52 | P24: =SUM(O24-O23) -> 0 | Q24: =SUM(P24+N24) -> 0 | T24: =T23 -> 5191 | U24: =SUM(T24-T23) -> 0 | V24: =V23 -> 499 | W24: =+V24-V23 -> 0 | X24: =X23 -> 155960 | Y24: =SUM(X24-X23) -> 0 | Z24: =Z23 -> 99668 | AA24: =Z24-Z23 -> 0 | AB24: =AB23 -> 258 | AC24: =AC23 -> 855 | AD24: =AC24-AC23 -> 0 | AE24: =AE23 -> 248.9 | AF24: =AE24-AE23 -> 0 | AG24: =AG23 -> 2247.41 | AH24: =AG24-AG23 -> 0 | AI24: =AF24+AH24 -> 0 | AJ24: =+Z24-Z23 -> 0 | AK24: =SUM(Y24-L24) -> 0 | AL24: =SUM(AJ24-W24) -> 0 | AM24: ='General information '!D23 -> 26 | AN24: ='[3]General information '!H24 -> 0 | AP24: ='[3]General information '!J24 -> 0 | AR24: =A24 -> 44823 | AS24: =AS23 -> 0.9 | AT24: 135 | AU24: =AU23 -> 1.1 | AV24: =AV23 -> 130 | AW24: 2.9 | AX24: =AX23 -> 113 | AY24: =AS24*AT24 -> 121.5 | AZ24: =AU24*AV24 -> 143 | BA24: =AW24*AX24 -> 327.7 | BB24: =AY24-AY23 -> 40.5 | BC24: =AZ24-AZ23 -> 0 | BD24: =BA24-BA23 -> 0 | BE24: =SUM(BB24:BD24) -> 40.5 | BF24: =SUM(I24-BE24) -> -40.5 | BG24: =SUM(I24-BF24) -> 40.5
A25: =ELEC!C23 -> 44824 | B25: =B24 -> 109443 | C25: =B25-B24 -> 0 | D25: =C25/27 -> 0 | E25: =SUM((C25*$E$4)+(7500/'EDl log'!$A$37)) -> 250 | G25: =G24 -> 630568 | H25: =G25-G24 -> 0 | I25: =C25+H25 -> 0 | J25: =IF(I25>0,E25/I25,0) -> 0 | K25: =K24 -> 7089 | L25: =K25-K24 -> 0 | M25: =M24 -> 457.44 | N25: =SUM(M25-M24) -> 0 | O25: =O24 -> 529.52 | P25: =SUM(O25-O24) -> 0 | Q25: =SUM(P25+N25) -> 0 | T25: =T24 -> 5191 | U25: =SUM(T25-T24) -> 0 | V25: =V24 -> 499 | W25: =+V25-V24 -> 0 | X25: =X24 -> 155960 | Y25: =SUM(X25-X24) -> 0 | Z25: =Z24 -> 99668 | AA25: =Z25-Z24 -> 0 | AB25: =AB24 -> 258 | AC25: =AC24 -> 855 | AD25: =AC25-AC24 -> 0 | AE25: =AE24 -> 248.9 | AF25: =AE25-AE24 -> 0 | AG25: =AG24 -> 2247.41 | AH25: =AG25-AG24 -> 0 | AI25: =AF25+AH25 -> 0 | AJ25: =+Z25-Z24 -> 0 | AK25: =SUM(Y25-L25) -> 0 | AL25: =SUM(AJ25-W25) -> 0 | AM25: ='General information '!D24 -> 25.5 | AN25: ='General information '!H24 -> 0 | AP25: ='General information '!J24 -> 0 | AR25: =A25 -> 44824 | AS25: =AS24 -> 0.9 | AT25: 135 | AU25: =AU24 -> 1.1 | AV25: 129 | AW25: 2.9 | AX25: 110 | AY25: =AS25*AT25 -> 121.5 | AZ25: =AU25*AV25 -> 141.9 | BA25: =AW25*AX25 -> 319 | BB25: =AY25-AY24 -> 0 | BC25: =AZ25-AZ24 -> -1.1 | BD25: =BA25-BA24 -> -8.7 | BE25: =SUM(BB25:BD25) -> -9.8 | BF25: =SUM(I25-BE25) -> 9.8 | BG25: =SUM(I25-BF25) -> -9.8
A26: =ELEC!C24 -> 44825 | B26: =B25 -> 109443 | C26: =B26-B25 -> 0 | D26: =C26/27 -> 0 | E26: =SUM((C26*$E$4)+(7500/'EDl log'!$A$37)) -> 250 | G26: =G25 -> 630568 | H26: =G26-G25 -> 0 | I26: =C26+H26 -> 0 | J26: =IF(I26>0,E26/I26,0) -> 0 | K26: =K25 -> 7089 | L26: =K26-K25 -> 0 | M26: =M25 -> 457.44 | N26: =SUM(M26-M25) -> 0 | O26: =O25 -> 529.52 | P26: =SUM(O26-O25) -> 0 | Q26: =SUM(P26+N26) -> 0 | T26: =T25 -> 5191 | U26: =SUM(T26-T25) -> 0 | V26: =V25 -> 499 | W26: =+V26-V25 -> 0 | X26: =X25 -> 155960 | Y26: =SUM(X26-X25) -> 0 | Z26: =Z25 -> 99668 | AA26: =Z26-Z25 -> 0 | AB26: =AB25 -> 258 | AC26: =AC25 -> 855 | AD26: =AC26-AC25 -> 0 | AE26: =AE25 -> 248.9 | AF26: =AE26-AE25 -> 0 | AG26: =AG25 -> 2247.41 | AH26: =AG26-AG25 -> 0 | AI26: =AF26+AH26 -> 0 | AJ26: =+Z26-Z25 -> 0 | AK26: =SUM(Y26-L26) -> 0 | AL26: =SUM(AJ26-W26) -> 0 | AM26: ='General information '!D25 -> 26 | AN26: ='General information '!H25 -> 0 | AP26: ='General information '!J25 -> 0 | AR26: =A26 -> 44825 | AS26: =AS25 -> 0.9 | AT26: 190 | AU26: =AU25 -> 1.1 | AV26: 122 | AW26: 2.9 | AX26: 106 | AY26: =AS26*AT26 -> 171 | AZ26: =AU26*AV26 -> 134.2 | BA26: =AW26*AX26 -> 307.4 | BB26: =AY26-AY25 -> 49.5 | BC26: =AZ26-AZ25 -> -7.7 | BD26: =BA26-BA25 -> -11.6 | BE26: =SUM(BB26:BD26) -> 30.2 | BF26: =SUM(I26-BE26) -> -30.2 | BG26: =SUM(I26-BF26) -> 30.2
A27: =ELEC!C25 -> 44826 | B27: =B26 -> 109443 | C27: =B27-B26 -> 0 | D27: =C27/27 -> 0 | E27: =SUM((C27*$E$4)+(7500/'EDl log'!$A$37)) -> 250 | G27: =G26 -> 630568 | H27: =G27-G26 -> 0 | I27: =C27+H27 -> 0 | J27: =IF(I27>0,E27/I27,0) -> 0 | K27: =K26 -> 7089 | L27: =K27-K26 -> 0 | M27: =M26 -> 457.44 | N27: =SUM(M27-M26) -> 0 | O27: =O26 -> 529.52 | P27: =SUM(O27-O26) -> 0 | Q27: =SUM(P27+N27) -> 0 | T27: =T26 -> 5191 | U27: =SUM(T27-T26) -> 0 | V27: =V26 -> 499 | W27: =+V27-V26 -> 0 | X27: =X26 -> 155960 | Y27: =SUM(X27-X26) -> 0 | Z27: =Z26 -> 99668 | AA27: =Z27-Z26 -> 0 | AB27: =AB26 -> 258 | AC27: =AC26 -> 855 | AD27: =AC27-AC26 -> 0 | AE27: =AE26 -> 248.9 | AF27: =AE27-AE26 -> 0 | AG27: =AG26 -> 2247.41 | AH27: =AG27-AG26 -> 0 | AI27: =AF27+AH27 -> 0 | AJ27: =+Z27-Z26 -> 0 | AK27: =SUM(Y27-L27) -> 0 | AL27: =SUM(AJ27-W27) -> 0 | AM27: ='General information '!D26 -> 26 | AN27: ='General information '!H26 -> 0 | AP27: ='General information '!J26 -> 0 | AR27: =A27 -> 44826 | AS27: =AS26 -> 0.9 | AT27: 192 | AU27: =AU26 -> 1.1 | AV27: =AV26 -> 122 | AW27: 2.9 | AX27: 105 | AY27: =AS27*AT27 -> 172.8 | AZ27: =AU27*AV27 -> 134.2 | BA27: =AW27*AX27 -> 304.5 | BB27: =AY27-AY26 -> 1.8 | BC27: =AZ27-AZ26 -> 0 | BD27: =BA27-BA26 -> -2.9 | BE27: =SUM(BB27:BD27) -> -1.1 | BF27: =SUM(I27-BE27) -> 1.1 | BG27: =SUM(I27-BF27) -> -1.1
A28: =ELEC!C26 -> 44827 | B28: =B27 -> 109443 | C28: =B28-B27 -> 0 | D28: =C28/27 -> 0 | E28: =SUM((C28*$E$4)+(7500/'EDl log'!$A$37)) -> 250 | G28: =G27 -> 630568 | H28: =G28-G27 -> 0 | I28: =C28+H28 -> 0 | J28: =IF(I28>0,E28/I28,0) -> 0 | K28: =K27 -> 7089 | L28: =K28-K27 -> 0 | M28: =M27 -> 457.44 | N28: =SUM(M28-M27) -> 0 | O28: =O27 -> 529.52 | P28: =SUM(O28-O27) -> 0 | Q28: =SUM(P28+N28) -> 0 | T28: =T27 -> 5191 | U28: =SUM(T28-T27) -> 0 | V28: =V27 -> 499 | W28: =+V28-V27 -> 0 | X28: =X27 -> 155960 | Y28: =SUM(X28-X27) -> 0 | Z28: =Z27 -> 99668 | AA28: =Z28-Z27 -> 0 | AB28: =AB27 -> 258 | AC28: =AC27 -> 855 | AD28: =AC28-AC27 -> 0 | AE28: =AE27 -> 248.9 | AF28: =AE28-AE27 -> 0 | AG28: =AG27 -> 2247.41 | AH28: =AG28-AG27 -> 0 | AI28: =AF28+AH28 -> 0 | AJ28: =+Z28-Z27 -> 0 | AK28: =SUM(Y28-L28) -> 0 | AL28: =SUM(AJ28-W28) -> 0 | AM28: ='General information '!D27 -> 0 | AN28: ='General information '!H27 -> 0 | AP28: ='General information '!J27 -> 0 | AR28: =A28 -> 44827 | AS28: =AS27 -> 0.9 | AT28: =AT27 -> 192 | AU28: =AU27 -> 1.1 | AV28: =AV27 -> 122 | AW28: 2.9 | AX28: =AX27 -> 105 | AY28: =AS28*AT28 -> 172.8 | AZ28: =AU28*AV28 -> 134.2 | BA28: =AW28*AX28 -> 304.5 | BB28: =AY28-AY27 -> 0 | BC28: =AZ28-AZ27 -> 0 | BD28: =BA28-BA27 -> 0 | BE28: =SUM(BB28:BD28) -> 0 | BF28: =SUM(I28-BE28) -> 0 | BG28: =SUM(I28-BF28) -> 0
A29: =ELEC!C27 -> 44828 | B29: =B28 -> 109443 | C29: =B29-B28 -> 0 | D29: =C29/27 -> 0 | E29: =SUM((C29*$E$4)+(7500/'EDl log'!$A$37)) -> 250 | G29: =G28 -> 630568 | H29: =G29-G28 -> 0 | I29: =C29+H29 -> 0 | J29: =IF(I29>0,E29/I29,0) -> 0 | K29: =K28 -> 7089 | L29: =K29-K28 -> 0 | M29: =M28 -> 457.44 | N29: =SUM(M29-M28) -> 0 | O29: =O28 -> 529.52 | P29: =SUM(O29-O28) -> 0 | Q29: =SUM(P29+N29) -> 0 | T29: =T28 -> 5191 | U29: =SUM(T29-T28) -> 0 | V29: =V28 -> 499 | W29: =+V29-V28 -> 0 | X29: =X28 -> 155960 | Y29: =SUM(X29-X28) -> 0 | Z29: =Z28 -> 99668 | AA29: =Z29-Z28 -> 0 | AB29: =AB28 -> 258 | AC29: =AC28 -> 855 | AD29: =AC29-AC28 -> 0 | AE29: =AE28 -> 248.9 | AF29: =AE29-AE28 -> 0 | AG29: =AG28 -> 2247.41 | AH29: =AG29-AG28 -> 0 | AI29: =AF29+AH29 -> 0 | AJ29: =+Z29-Z28 -> 0 | AK29: =SUM(Y29-L29) -> 0 | AL29: =SUM(AJ29-W29) -> 0 | AM29: ='General information '!D28 -> 0 | AN29: ='General information '!H28 -> 0 | AP29: ='General information '!J28 -> 0 | AR29: =A29 -> 44828 | AS29: =AS28 -> 0.9 | AT29: =AT28 -> 192 | AU29: =AU28 -> 1.1 | AV29: =AV28 -> 122 | AW29: 2.9 | AX29: =AX28 -> 105 | AY29: =AS29*AT29 -> 172.8 | AZ29: =AU29*AV29 -> 134.2 | BA29: =AW29*AX29 -> 304.5 | BB29: =AY29-AY28 -> 0 | BC29: =AZ29-AZ28 -> 0 | BD29: =BA29-BA28 -> 0 | BE29: =SUM(BB29:BD29) -> 0 | BF29: =SUM(I29-BE29) -> 0 | BG29: =SUM(I29-BF29) -> 0
A30: =ELEC!C28 -> 44829 | B30: =B29 -> 109443 | C30: =B30-B29 -> 0 | D30: =C30/27 -> 0 | E30: =SUM((C30*$E$4)+(7500/'EDl log'!$A$37)) -> 250 | G30: =G29 -> 630568 | H30: =G30-G29 -> 0 | I30: =C30+H30 -> 0 | J30: =IF(I30>0,E30/I30,0) -> 0 | K30: =K29 -> 7089 | L30: =K30-K29 -> 0 | M30: =M29 -> 457.44 | N30: =SUM(M30-M29) -> 0 | O30: =O29 -> 529.52 | P30: =SUM(O30-O29) -> 0 | Q30: =SUM(P30+N30) -> 0 | T30: =T29 -> 5191 | U30: =SUM(T30-T29) -> 0 | V30: =V29 -> 499 | W30: =+V30-V29 -> 0 | X30: =X29 -> 155960 | Y30: =SUM(X30-X29) -> 0 | Z30: =Z29 -> 99668 | AA30: =Z30-Z29 -> 0 | AB30: =AB29 -> 258 | AC30: =AC29 -> 855 | AD30: =AC30-AC29 -> 0 | AE30: =AE29 -> 248.9 | AF30: =AE30-AE29 -> 0 | AG30: =AG29 -> 2247.41 | AH30: =AG30-AG29 -> 0 | AI30: =AF30+AH30 -> 0 | AJ30: =+Z30-Z29 -> 0 | AK30: =SUM(Y30-L30) -> 0 | AL30: =SUM(AJ30-W30) -> 0 | AM30: ='General information '!D29 -> 27.5 | AN30: ='General information '!H29 -> 0 | AP30: ='General information '!J29 -> 0 | AR30: =A30 -> 44829 | AS30: =AS29 -> 0.9 | AT30: 175 | AU30: =AU29 -> 1.1 | AV30: 120 | AW30: 2.9 | AX30: 101 | AY30: =AS30*AT30 -> 157.5 | AZ30: =AU30*AV30 -> 132 | BA30: =AW30*AX30 -> 292.9 | BB30: =AY30-AY29 -> -15.3 | BC30: =AZ30-AZ29 -> -2.2 | BD30: =BA30-BA29 -> -11.6 | BE30: =SUM(BB30:BD30) -> -29.1 | BF30: =SUM(I30-BE30) -> 29.1 | BG30: =SUM(I30-BF30) -> -29.1
A31: =ELEC!C29 -> 44830 | B31: =B30 -> 109443 | C31: =B31-B30 -> 0 | D31: =C31/27 -> 0 | E31: =SUM((C31*$E$4)+(7500/'EDl log'!$A$37)) -> 250 | G31: =G30 -> 630568 | H31: =G31-G30 -> 0 | I31: =C31+H31 -> 0 | J31: =IF(I31>0,E31/I31,0) -> 0 | K31: =K30 -> 7089 | L31: =K31-K30 -> 0 | M31: =M30 -> 457.44 | N31: =SUM(M31-M30) -> 0 | O31: =O30 -> 529.52 | P31: =SUM(O31-O30) -> 0 | Q31: =SUM(P31+N31) -> 0 | T31: =T30 -> 5191 | U31: =SUM(T31-T30) -> 0 | V31: =V30 -> 499 | W31: =+V31-V30 -> 0 | X31: =X30 -> 155960 | Y31: =SUM(X31-X30) -> 0 | Z31: =Z30 -> 99668 | AA31: =Z31-Z30 -> 0 | AB31: =AB30 -> 258 | AC31: =AC30 -> 855 | AD31: =AC31-AC30 -> 0 | AE31: =AE30 -> 248.9 | AF31: =AE31-AE30 -> 0 | AG31: =AG30 -> 2247.41 | AH31: =AG31-AG30 -> 0 | AI31: =AF31+AH31 -> 0 | AJ31: =+Z31-Z30 -> 0 | AK31: =SUM(Y31-L31) -> 0 | AL31: =SUM(AJ31-W31) -> 0 | AM31: ='General information '!D30 -> 26.5 | AN31: ='General information '!H30 -> 0 | AP31: ='General information '!J30 -> 0 | AR31: =A31 -> 44830 | AS31: =AS30 -> 0.9 | AT31: 175 | AU31: =AU30 -> 1.1 | AV31: 119 | AW31: 2.9 | AX31: 100 | AY31: =AS31*AT31 -> 157.5 | AZ31: =AU31*AV31 -> 130.9 | BA31: =AW31*AX31 -> 290 | BB31: =AY31-AY30 -> 0 | BC31: =AZ31-AZ30 -> -1.1 | BD31: =BA31-BA30 -> -2.9 | BE31: =SUM(BB31:BD31) -> -4 | BF31: =SUM(I31-BE31) -> 4 | BG31: =SUM(I31-BF31) -> -4
A32: =ELEC!C30 -> 44831 | B32: =B31 -> 109443 | C32: =B32-B31 -> 0 | D32: =C32/27 -> 0 | E32: =SUM((C32*$E$4)+(7500/'EDl log'!$A$37)) -> 250 | G32: =G31 -> 630568 | H32: =G32-G31 -> 0 | I32: =C32+H32 -> 0 | J32: =IF(I32>0,E32/I32,0) -> 0 | K32: =K31 -> 7089 | L32: =K32-K31 -> 0 | M32: =M31 -> 457.44 | N32: =SUM(M32-M31) -> 0 | O32: =O31 -> 529.52 | P32: =SUM(O32-O31) -> 0 | Q32: =SUM(P32+N32) -> 0 | T32: =T31 -> 5191 | U32: =SUM(T32-T31) -> 0 | V32: =V31 -> 499 | W32: =+V32-V31 -> 0 | X32: =X31 -> 155960 | Y32: =SUM(X32-X31) -> 0 | Z32: =Z31 -> 99668 | AA32: =Z32-Z31 -> 0 | AB32: =AB31 -> 258 | AC32: =AC31 -> 855 | AD32: =AC32-AC31 -> 0 | AE32: =AE31 -> 248.9 | AF32: =AE32-AE31 -> 0 | AG32: =AG31 -> 2247.41 | AH32: =AG32-AG31 -> 0 | AI32: =AF32+AH32 -> 0 | AJ32: =+Z32-Z31 -> 0 | AK32: =SUM(Y32-L32) -> 0 | AL32: =SUM(AJ32-W32) -> 0 | AM32: ='General information '!D31 -> 26 | AN32: ='General information '!H31 -> 0 | AP32: ='General information '!J31 -> 0 | AR32: =A32 -> 44831 | AS32: =AS31 -> 0.9 | AT32: 164 | AU32: =AU31 -> 1.1 | AV32: 118 | AW32: 2.9 | AX32: 98 | AY32: =AS32*AT32 -> 147.6 | AZ32: =AU32*AV32 -> 129.8 | BA32: =AW32*AX32 -> 284.2 | BB32: =AY32-AY31 -> -9.9 | BC32: =AZ32-AZ31 -> -1.1 | BD32: =BA32-BA31 -> -5.8 | BE32: =SUM(BB32:BD32) -> -16.8 | BF32: =SUM(I32-BE32) -> 16.8 | BG32: =SUM(I32-BF32) -> -16.8
A33: =ELEC!C31 -> 44832 | B33: =B32 -> 109443 | C33: =B33-B32 -> 0 | D33: =C33/27 -> 0 | E33: =SUM((C33*$E$4)+(7500/'EDl log'!$A$37)) -> 250 | G33: =G32 -> 630568 | H33: =G33-G32 -> 0 | I33: =C33+H33 -> 0 | J33: =IF(I33>0,E33/I33,0) -> 0 | K33: =K32 -> 7089 | L33: =K33-K32 -> 0 | M33: =M32 -> 457.44 | N33: =SUM(M33-M32) -> 0 | O33: =O32 -> 529.52 | P33: =SUM(O33-O32) -> 0 | Q33: =SUM(P33+N33) -> 0 | T33: =T32 -> 5191 | U33: =SUM(T33-T32) -> 0 | V33: =V32 -> 499 | W33: =+V33-V32 -> 0 | X33: =X32 -> 155960 | Y33: =SUM(X33-X32) -> 0 | Z33: =Z32 -> 99668 | AA33: =Z33-Z32 -> 0 | AB33: =AB32 -> 258 | AC33: =AC32 -> 855 | AD33: =AC33-AC32 -> 0 | AE33: 248.42 | AF33: =AE33-AE32 -> -0.48 | AG33: =AG32 -> 2247.41 | AH33: =AG33-AG32 -> 0 | AI33: =AF33+AH33 -> -0.48 | AJ33: =+Z33-Z32 -> 0 | AK33: =SUM(Y33-L33) -> 0 | AL33: =SUM(AJ33-W33) -> 0 | AM33: ='General information '!D32 -> 26 | AN33: ='General information '!H32 -> 0 | AP33: ='General information '!J32 -> 0 | AR33: =A33 -> 44832 | AS33: =AS32 -> 0.9 | AT33: 164 | AU33: =AU32 -> 1.1 | AV33: 116 | AW33: 2.9 | AX33: 96 | AY33: =AS33*AT33 -> 147.6 | AZ33: =AU33*AV33 -> 127.6 | BA33: =AW33*AX33 -> 278.4 | BB33: =AY33-AY32 -> 0 | BC33: =AZ33-AZ32 -> -2.2 | BD33: =BA33-BA32 -> -5.8 | BE33: =SUM(BB33:BD33) -> -8 | BF33: =SUM(I33-BE33) -> 8 | BG33: =SUM(I33-BF33) -> -8
A34: =ELEC!C32 -> 44833 | B34: =B33 -> 109443 | C34: =B34-B33 -> 0 | D34: =C34/27 -> 0 | E34: =SUM((C34*$E$4)+(7500/'EDl log'!$A$37)) -> 250 | G34: =G33 -> 630568 | H34: =G34-G33 -> 0 | I34: =C34+H34 -> 0 | J34: =IF(I34>0,E34/I34,0) -> 0 | K34: =K33 -> 7089 | L34: =K34-K33 -> 0 | M34: =M33 -> 457.44 | N34: =SUM(M34-M33) -> 0 | O34: =O33 -> 529.52 | P34: =SUM(O34-O33) -> 0 | Q34: =SUM(P34+N34) -> 0 | T34: =T33 -> 5191 | U34: =SUM(T34-T33) -> 0 | V34: =V33 -> 499 | W34: =+V34-V33 -> 0 | X34: =X33 -> 155960 | Y34: =SUM(X34-X33) -> 0 | Z34: =Z33 -> 99668 | AA34: =Z34-Z33 -> 0 | AB34: =AB33 -> 258 | AC34: =AC33 -> 855 | AD34: =AC34-AC33 -> 0 | AE34: =AE33 -> 248.42 | AF34: =AE34-AE33 -> 0 | AG34: =AG33 -> 2247.41 | AH34: =AG34-AG33 -> 0 | AI34: =AF34+AH34 -> 0 | AJ34: =+Z34-Z33 -> 0 | AK34: =SUM(Y34-L34) -> 0 | AL34: =SUM(AJ34-W34) -> 0 | AM34: ='General information '!D33 -> 26.5 | AN34: ='General information '!H33 -> 0 | AP34: ='General information '!J33 -> 0 | AR34: =A34 -> 44833 | AS34: =AS33 -> 0.9 | AT34: 164 | AU34: =AU33 -> 1.1 | AV34: 110 | AW34: 2.9 | AX34: 94 | AY34: =AS34*AT34 -> 147.6 | AZ34: =AU34*AV34 -> 121 | BA34: =AW34*AX34 -> 272.6 | BB34: =AY34-AY33 -> 0 | BC34: =AZ34-AZ33 -> -6.6 | BD34: =BA34-BA33 -> -5.8 | BE34: =SUM(BB34:BD34) -> -12.4 | BF34: =SUM(I34-BE34) -> 12.4 | BG34: =SUM(I34-BF34) -> -12.4
A35: =ELEC!C33 -> 44834 | B35: =B34 -> 109443 | C35: =B35-B34 -> 0 | D35: =C35/27 -> 0 | E35: =SUM((C35*$E$4)+(7500/'EDl log'!$A$37)) -> 250 | G35: =G34 -> 630568 | H35: =G35-G34 -> 0 | I35: =C35+H35 -> 0 | J35: =IF(I35>0,E35/I35,0) -> 0 | K35: =K34 -> 7089 | L35: =K35-K34 -> 0 | M35: =M34 -> 457.44 | N35: =SUM(M35-M34) -> 0 | O35: =O34 -> 529.52 | P35: =SUM(O35-O34) -> 0 | Q35: =SUM(P35+N35) -> 0 | T35: =T34 -> 5191 | U35: =SUM(T35-T34) -> 0 | V35: =V34 -> 499 | W35: =+V35-V34 -> 0 | X35: =X34 -> 155960 | Y35: =SUM(X35-X34) -> 0 | Z35: =Z34 -> 99668 | AA35: =Z35-Z34 -> 0 | AB35: =AB34 -> 258 | AC35: =AC34 -> 855 | AD35: =AC35-AC34 -> 0 | AE35: =AE34 -> 248.42 | AF35: =AE35-AE34 -> 0 | AG35: =AG34 -> 2247.41 | AH35: =AG35-AG34 -> 0 | AI35: =AF35+AH35 -> 0 | AJ35: =+Z35-Z34 -> 0 | AK35: =SUM(Y35-L35) -> 0 | AL35: =SUM(AJ35-W35) -> 0 | AM35: ='General information '!D34 -> 0 | AN35: ='General information '!H34 -> 0 | AP35: ='General information '!J34 -> 0 | AR35: =A35 -> 44834 | AS35: =AS34 -> 0.9 | AT35: =AT34 -> 164 | AU35: =AU34 -> 1.1 | AV35: =AV34 -> 110 | AW35: 2.9 | AX35: =AX34 -> 94 | AY35: =AS35*AT35 -> 147.6 | AZ35: =AU35*AV35 -> 121 | BA35: =AW35*AX35 -> 272.6 | BB35: =AY35-AY34 -> 0 | BC35: =AZ35-AZ34 -> 0 | BD35: =BA35-BA34 -> 0 | BE35: =SUM(BB35:BD35) -> 0 | BF35: =SUM(I35-BE35) -> 0 | BG35: =SUM(I35-BF35) -> 0
A36: =ELEC!C34 -> 44835 | B36: =B35 -> 109443 | C36: =B36-B35 -> 0 | D36: =C36/27 -> 0 | E36: =SUM((C36*$E$4)+(7500/'EDl log'!$A$37)) -> 250 | G36: =G35 -> 630568 | H36: =G36-G35 -> 0 | I36: =C36+H36 -> 0 | J36: =IF(I36>0,E36/I36,0) -> 0 | K36: =K35 -> 7089 | L36: =K36-K35 -> 0 | M36: =M35 -> 457.44 | N36: =SUM(M36-M35) -> 0 | O36: =O35 -> 529.52 | P36: =SUM(O36-O35) -> 0 | Q36: =SUM(P36+N36) -> 0 | T36: =T35 -> 5191 | U36: =SUM(T36-T35) -> 0 | V36: =V35 -> 499 | W36: =+V36-V35 -> 0 | X36: =X35 -> 155960 | Y36: =SUM(X36-X35) -> 0 | Z36: =Z35 -> 99668 | AA36: =Z36-Z35 -> 0 | AB36: =AB35 -> 258 | AC36: =AC35 -> 855 | AD36: =AC36-AC35 -> 0 | AE36: =AE35 -> 248.42 | AF36: =AE36-AE35 -> 0 | AG36: =AG35 -> 2247.41 | AH36: =AG36-AG35 -> 0 | AI36: =AF36+AH36 -> 0 | AJ36: =+Z36-Z35 -> 0 | AK36: =SUM(Y36-L36) -> 0 | AL36: =SUM(AJ36-W36) -> 0 | AM36: ='General information '!D35 -> 0 | AN36: ='General information '!H35 -> 0 | AP36: ='General information '!J35 -> 0 | AR36: =A36 -> 44835 | AS36: =AS35 -> 0.9 | AT36: =AT35 -> 164 | AU36: =AU35 -> 1.1 | AV36: =AV35 -> 110 | AW36: 2.9 | AX36: =AX35 -> 94 | AY36: =AS36*AT36 -> 147.6 | AZ36: =AU36*AV36 -> 121 | BA36: =AW36*AX36 -> 272.6 | BB36: =AY36-AY35 -> 0 | BC36: =AZ36-AZ35 -> 0 | BD36: =BA36-BA35 -> 0 | BE36: =SUM(BB36:BD36) -> 0 | BF36: =SUM(I36-BE36) -> 0 | BG36: =SUM(I36-BF36) -> 0
C37: =SUM(C6:C36) -> 0 | D37: =SUM(D6:D36) -> 0 | F37: =SUM(F6:F36) -> 0 | H37: =SUM(H6:H36) -> 343 | I37: =SUM(I6:I36) -> 343 | L37: =SUM(L7:L36) -> 0 | Q37: =SUM(Q6:Q36) -> 0 | U37: =SUM(U6:U36) -> 1 | Y37: =SUM(Y6,Y33,Y31,Y29,Y27,Y25,Y23,Y21,Y19,Y17,Y15,Y13,Y11,Y9,Y7,Y34,Y35,Y36) -> 123 | AJ37: =SUM(AJ6:AJ36) -> 0 | AK37: =SUM(Y37-L37) -> 123 | AL37: =SUM(AL6:AL36) -> 0
C38: =+C37*1.66 -> 0 | E38: =SUM(E6:E33) -> 7000 | F38: =SUM(F6:F35) -> 0 | H38: 7500 | I38: =SUM('General information '!G36/WATER!I37) -> 0 | O38: =SUM(Q37+I37) -> 343 | Z38: =SUM(Y37:AJ37) -> 123 | AK38: =SUM(Y38-L38) -> 0
B39: =9*31 -> 279 | D39: =SUM(D6:D35) -> 0 | F39: =SUM(F6:F36) -> 0 | G39: =SUM(I37) -> 343 | H39: =SUM(H38+C38) -> 7500 | K39: =SUM(H39/G39) -> 21.865889 | AJ39: =SUM(C38-AK38) -> 0 | AM39: =SUM(AJ39/AO38) -> #DIV/0!

Sheet GEN
B1: GEN1 | C1: RUN HR | D1: Fuel Counter Index | E1: Cons /day | F1: Diesel L/H | H1: next service | I1: ALARM | J1: GEN2 | K1: RUN HR | L1: Fuel Counter Index | M1: Cons /day | N1: Diesel L/H | P1: next service | Q1: ALARM | R1: GEN3 | S1: RUN HR | T1: Fuel Counter Index | U1: Cons /day | V1: Diesel L/H | X1: next service | Y1: ALARM | Z1: RH total | AA1: Gen Con /day | AB1: Total Deisel Cons/day | AC1: H /L | AD1: TOAL KW GEN | AI1: fuel Consuption | AK1: AVG KW/h
A2: =[2]GEN!$A$33 -> 44804 | B2: =[2]GEN!B33 -> 837 | C2: =[2]GEN!C33 -> 15 | D2: =[2]GEN!D33 -> 744446 | E2: =[2]GEN!E33 -> 1275 | F2: =[2]GEN!F33 -> 85 | G2: =[2]GEN!G33 -> 0 | H2: =[2]GEN!H33 -> 12231 | I2: =[2]GEN!I33 -> ok | ... AL2: =[2]GEN!AL33 -> 1
A3: =ELEC!C4 -> 44805 | B3: 850 | C3: =B3-B2 -> 13 | D3: =D2+C3*250 -> 747696 | E3: =SUM(D3-D2) -> 3250 | F3: =IF(C3>0,E3/C3,0) -> 250 | G3: =[4]GEN!G32 -> 0 | H3: =H2 -> 12231 | I3: =IF(B3-H3<=0,"ok","oil change") -> ok | J3: =J2 -> 125 | K3: =J3-J2 -> 0 | L3: =L2 -> 388191 | M3: =SUM(L3-L2) -> 0 | N3: 250 | O3: =[4]GEN!O32 -> 0 | P3: =P2 -> 10873 | Q3: =IF(J3-P3<=0,"ok","oil change") -> ok | R3: =R2 -> 13908 | S3: =R3-R2 -> 0 | T3: =T2+U3 -> 416512 | U3: =V3*S3 -> 0 | V3: 250 | W3: =[4]GEN!W32 -> 0 | X3: =X2 -> 14593 | Y3: =IF(R3-X3<=0,"ok","oil change") -> ok | Z3: =C3+K3+S3 -> 13 | AA3: =U3+M3+E3 -> 3250 | AB3: =V3+N3+F3 -> 750 | AC3: =IF(Z3>0,AA3/Z3,0) -> 250 | AD3: =ELEC!Q4 -> 3974 | AE3: =SUM(AD3/Z3) -> 305.69231 | AF3: =SUM(AE3/1600) -> 0.19105769 | AG3: =SUM(360*AF3) -> 68.780769 | AH3: =SUM(AC3-AG3) -> 181.21923 | AI3: =AD3*AJ3 -> 1022.8439 | AJ3: =305/1185 -> 0.25738397 | AK3: =AI3/Z3 -> 78.680299 | AL3: =IF(Z3=0,0,1) -> 1
A4: =ELEC!C5 -> 44806 | B4: =B3 -> 850 | C4: =B4-B3 -> 0 | D4: =D3+C4*85 -> 747696 | E4: =SUM(D4-D3) -> 0 | F4: =IF(C4>0,E4/C4,0) -> 0 | H4: =H3 -> 12231 | I4: =IF(B4-H4<=0,"ok","oil change") -> ok | J4: =J3 -> 125 | K4: =J4-J3 -> 0 | L4: =L3 -> 388191 | M4: =SUM(L4-L3) -> 0 | N4: 250 | P4: =P3 -> 10873 | Q4: =IF(J4-P4<=0,"ok","oil change") -> ok | R4: =R3 -> 13908 | S4: =R4-R3 -> 0 | T4: =T3+U4 -> 416512 | U4: =V4*S4 -> 0 | V4: 250 | X4: =X3 -> 14593 | Y4: =IF(R4-X4<=0,"ok","oil change") -> ok | Z4: =C4+K4+S4 -> 0 | AA4: =U4+M4+E4 -> 0 | AB4: =V4+N4+F4 -> 500 | AC4: =IF(Z4>0,AA4/Z4,0) -> 0 | AD4: =ELEC!Q5 -> 0 | AE4: =SUM(AD4/Z4) -> #DIV/0! | AF4: =SUM(AE4/1600) -> #DIV/0! | AG4: =SUM(360*AF4) -> #DIV/0! | AH4: =SUM(AC4-AG4) -> #DIV/0! | AI4: =AD4*AJ4 -> 0 | AJ4: =305/1185 -> 0.25738397 | AK4: =AI4/Z4 -> #DIV/0! | AL4: =IF(Z4=0,0,1) -> 0
A5: =ELEC!C6 -> 44807 | B5: =B4 -> 850 | C5: =B5-B4 -> 0 | D5: =D4+C5*85 -> 747696 | E5: =SUM(D5-D4) -> 0 | F5: =IF(C5>0,E5/C5,0) -> 0 | H5: =H4 -> 12231 | I5: =IF(B5-H5<=0,"ok","oil change") -> ok | J5: =J4 -> 125 | K5: =J5-J4 -> 0 | L5: =L4 -> 388191 | M5: =SUM(L5-L4) -> 0 | N5: 250 | P5: =P4 -> 10873 | Q5: =IF(J5-P5<=0,"ok","oil change") -> ok | R5: =R4 -> 13908 | S5: =R5-R4 -> 0 | T5: =T4+U5 -> 416512 | U5: =V5*S5 -> 0 | V5: 250 | X5: =X4 -> 14593 | Y5: =IF(R5-X5<=0,"ok","oil change") -> ok | Z5: =C5+K5+S5 -> 0 | AA5: =U5+M5+E5 -> 0 | AB5: =V5+N5+F5 -> 500 | AC5: =IF(Z5>0,AA5/Z5,0) -> 0 | AD5: =ELEC!Q6 -> 0 | AE5: =SUM(AD5/Z5) -> #DIV/0! | AF5: =SUM(AE5/1600) -> #DIV/0! | AG5: =SUM(320*AF5) -> #DIV/0! | AH5: =SUM(AC5-AG5) -> #DIV/0! | AI5: =AD5*AJ5 -> 0 | AJ5: =305/1185 -> 0.25738397 | AK5: =AI5/Z5 -> #DIV/0! | AL5: =IF(Z5=0,0,1) -> 0
A6: =ELEC!C7 -> 44808 | B6: 861 | C6: =B6-B5 -> 11 | D6: =D5+C6*85 -> 748631 | E6: =SUM(D6-D5) -> 935 | F6: =IF(C6>0,E6/C6,0) -> 85 | H6: =H5 -> 12231 | I6: =IF(B6-H6<=0,"ok","oil change") -> ok | J6: =J5 -> 125 | K6: =J6-J5 -> 0 | L6: =(K6*N5)+L5 -> 388191 | M6: =SUM(L6-L5) -> 0 | N6: 250 | P6: =P5 -> 10873 | Q6: =IF(J6-P6<=0,"ok","oil change") -> ok | R6: =R5 -> 13908 | S6: =R6-R5 -> 0 | T6: =T5+U6 -> 416512 | U6: =V6*S6 -> 0 | V6: 250 | X6: =X5+180 -> 14773 | Y6: =IF(R6-X6<=0,"ok","oil change") -> ok | Z6: =C6+K6+S6 -> 11 | AA6: =U6+M6+E6 -> 935 | AB6: =V6+N6+F6 -> 585 | AC6: =IF(Z6>0,AA6/Z6,0) -> 85 | AD6: =ELEC!Q7 -> 3202 | AE6: =SUM(AD6/Z6) -> 291.09091 | AF6: =SUM(AE6/1600) -> 0.18193182 | AG6: =SUM(320*AF6) -> 58.218182 | AH6: =SUM(AC6-AG6) -> 26.781818 | AI6: =AD6*AJ6 -> 824.14346 | AJ6: =305/1185 -> 0.25738397 | AK6: =AI6/Z6 -> 74.922133 | AL6: =IF(Z6=0,0,1) -> 1
A7: =ELEC!C8 -> 44809 | B7: 872 | C7: =B7-B6 -> 11 | D7: =D6+C7*85 -> 749566 | E7: =SUM(D7-D6) -> 935 | F7: =IF(C7>0,E7/C7,0) -> 85 | H7: =H6 -> 12231 | I7: =IF(B7-H7<=0,"ok","oil change") -> ok | J7: =J6 -> 125 | L7: =(K7*N6)+L6 -> 388191 | M7: =SUM(L7-L6) -> 0 | N7: 250 | P7: =P6 -> 10873 | Q7: =IF(J7-P7<=0,"ok","oil change") -> ok | R7: =R6 -> 13908 | S7: =R7-R6 -> 0 | T7: =T6+U7 -> 416512 | U7: =V7*S7 -> 0 | V7: 250 | X7: =X6 -> 14773 | Y7: =IF(R7-X7<=0,"ok","oil change") -> ok | Z7: =C7+K7+S7 -> 11 | AA7: =U7+M7+E7 -> 935 | AB7: =V7+N7+F7 -> 585 | AC7: =IF(Z7>0,AA7/Z7,0) -> 85 | AD7: =ELEC!Q8 -> 3421 | AE7: =SUM(AD7/Z7) -> 311 | AF7: =SUM(AE7/1600) -> 0.194375 | AG7: =SUM(AF7/1600) -> 0.00012148437 | AH7: =SUM(AC7-AG7) -> 84.999879 | AI7: =AD7*AJ7 -> 880.51055 | AJ7: =305/1185 -> 0.25738397 | AK7: =AI7/Z7 -> 80.046414 | AL7: =IF(Z7=0,0,1) -> 1
A8: =ELEC!C9 -> 44810 | B8: 879 | C8: =B8-B7 -> 7 | D8: =D7+C8*85 -> 750161 | E8: =SUM(D8-D7) -> 595 | F8: =IF(C8>0,E8/C8,0) -> 85 | H8: =H7 -> 12231 | I8: =IF(B8-H8<=0,"ok","oil change") -> ok | J8: 129 | K8: =J8-J7 -> 4 | L8: =(K8*N7)+L7 -> 389191 | M8: =SUM(L8-L7) -> 1000 | N8: 250 | P8: =P7 -> 10873 | Q8: =IF(J8-P8<=0,"ok","oil change") -> ok | R8: =R7 -> 13908 | S8: =R8-R7 -> 0 | T8: =T7+U8 -> 416512 | U8: =V8*S8 -> 0 | V8: 250 | X8: =X7 -> 14773 | Y8: =IF(R8-X8<=0,"ok","oil change") -> ok | Z8: =C8+K8+S8 -> 11 | AA8: =U8+M8+E8 -> 1595 | AB8: =V8+N8+F8 -> 585 | AC8: =IF(Z8>0,AA8/Z8,0) -> 145 | AD8: =ELEC!Q9 -> 5137 | AE8: =SUM(AD8/Z8) -> 467 | AF8: =SUM(AE8/1600) -> 0.291875 | AG8: =SUM(AF8/1600) -> 0.00018242187 | AH8: =SUM(AC8-AG8) -> 144.99982 | AI8: =AD8*AJ8 -> 1322.1814 | AJ8: =305/1185 -> 0.25738397 | AK8: =AI8/Z8 -> 120.19831 | AL8: =IF(Z8=0,0,1) -> 1
A9: =ELEC!C10 -> 44811 | B9: 887 | C9: =B9-B8 -> 8 | D9: =D8+C9*85 -> 750841 | E9: =SUM(D9-D8) -> 680 | F9: =IF(C9>0,E9/C9,0) -> 85 | H9: =H8 -> 12231 | I9: =IF(B9-H9<=0,"ok","oil change") -> ok | J9: 132 | K9: =J9-J8 -> 3 | L9: =(K9*N8)+L8 -> 389941 | M9: =SUM(L9-L8) -> 750 | N9: 250 | P9: =P8 -> 10873 | Q9: =IF(J9-P9<=0,"ok","oil change") -> ok | R9: =R8 -> 13908 | S9: =R9-R8 -> 0 | T9: =T8+U9 -> 416512 | U9: =V9*S9 -> 0 | V9: 250 | X9: =X8 -> 14773 | Y9: =IF(R9-X9<=0,"ok","oil change") -> ok | Z9: =C9+K9+S9 -> 11 | AA9: =U9+M9+E9 -> 1430 | AB9: =V9+N9+F9 -> 585 | AC9: =IF(Z9>0,AA9/Z9,0) -> 130 | AD9: =ELEC!Q10 -> 4863 | AE9: =SUM(AD9/Z9) -> 442.09091 | AF9: =SUM(AE9/1600) -> 0.27630682 | AG9: =SUM(AF9/1600) -> 0.00017269176 | AH9: =SUM(AC9-AG9) -> 129.99983 | AI9: =AD9*AJ9 -> 1251.6582 | AJ9: =305/1185 -> 0.25738397 | AK9: =AI9/Z9 -> 113.78711 | AL9: =IF(Z9=0,0,1) -> 1
A10: =ELEC!C11 -> 44812 | B10: 898 | C10: =B10-B9 -> 11 | D10: =D9+C10*85 -> 751776 | E10: =SUM(D10-D9) -> 935 | F10: =IF(C10>0,E10/C10,0) -> 85 | H10: =H9 -> 12231 | I10: =IF(B10-H10<=0,"ok","oil change") -> ok | J10: =J9 -> 132 | K10: =J10-J9 -> 0 | L10: =(K10*N9)+L9 -> 389941 | M10: =SUM(L10-L9) -> 0 | N10: 250 | P10: =P9 -> 10873 | Q10: =IF(J10-P10<=0,"ok","oil change") -> ok | R10: =R9 -> 13908 | S10: =R10-R9 -> 0 | T10: =T9+U10 -> 416512 | U10: =V10*S10 -> 0 | V10: 250 | X10: =X9 -> 14773 | Y10: =IF(R10-X10<=0,"ok","oil change") -> ok | Z10: =C10+K10+S10 -> 11 | AA10: =U10+M10+E10 -> 935 | AB10: =V10+N10+F10 -> 585 | AC10: =IF(Z10>0,AA10/Z10,0) -> 85 | AD10: =ELEC!Q11 -> 3789 | AE10: =SUM(AD10/Z10) -> 344.45455 | AF10: =SUM(AE10/1600) -> 0.21528409 | AG10: =SUM(AF10/1600) -> 0.00013455256 | AH10: =SUM(AC10-AG10) -> 84.999865 | AI10: =AD10*AJ10 -> 975.22785 | AJ10: =305/1185 -> 0.25738397 | AK10: =AI10/Z10 -> 88.657077 | AL10: =IF(Z10=0,0,1) -> 1
A11: =ELEC!C12 -> 44813 | B11: =B10 -> 898 | C11: =B11-B10 -> 0 | D11: =D10+C11*85 -> 751776 | E11: =SUM(D11-D10) -> 0 | F11: =IF(C11>0,E11/C11,0) -> 0 | H11: =H10 -> 12231 | I11: =IF(B11-H11<=0,"ok","oil change") -> ok | J11: =J10 -> 132 | K11: =J11-J10 -> 0 | L11: =(K11*N10)+L10 -> 389941 | M11: =SUM(L11-L10) -> 0 | N11: 250 | P11: =P10 -> 10873 | Q11: =IF(J11-P11<=0,"ok","oil change") -> ok | R11: 13909 | S11: =R11-R10 -> 1 | T11: =T10+U11 -> 416762 | U11: =V11*S11 -> 250 | V11: 250 | X11: =X10 -> 14773 | Y11: =IF(R11-X11<=0,"ok","oil change") -> ok | Z11: =C11+K11+S11 -> 1 | AA11: =U11+M11+E11 -> 250 | AB11: =V11+N11+F11 -> 500 | AC11: =IF(Z11>0,AA11/Z11,0) -> 250 | AD11: =ELEC!Q12 -> 0 | AE11: =SUM(AD11/Z11) -> 0 | AF11: =SUM(AE11/1600) -> 0 | AG11: =SUM(AF11/1600) -> 0 | AH11: =SUM(AC11-AG11) -> 250 | AI11: =AD11*AJ11 -> 0 | AJ11: =305/1185 -> 0.25738397 | AK11: =AI11/Z11 -> 0 | AL11: =IF(Z11=0,0,1) -> 1
A12: =ELEC!C13 -> 44814 | B12: =B11 -> 898 | C12: =B12-B11 -> 0 | D12: =D11+C12*85 -> 751776 | E12: =SUM(D12-D11) -> 0 | F12: =IF(C12>0,E12/C12,0) -> 0 | H12: =H11 -> 12231 | I12: =IF(B12-H12<=0,"ok","oil change") -> ok | J12: =J11 -> 132 | K12: =J12-J11 -> 0 | L12: =(K12*N11)+L11 -> 389941 | M12: =SUM(L12-L11) -> 0 | N12: 250 | P12: =P11 -> 10873 | Q12: =IF(J12-P12<=0,"ok","oil change") -> ok | R12: =R11 -> 13909 | S12: =R12-R11 -> 0 | T12: =T11+U12 -> 416762 | U12: =V12*S12 -> 0 | V12: 250 | X12: =X11 -> 14773 | Y12: =IF(R12-X12<=0,"ok","oil change") -> ok | Z12: =C12+K12+S12 -> 0 | AA12: =U12+M12+E12 -> 0 | AB12: =V12+N12+F12 -> 500 | AC12: =IF(Z12>0,AA12/Z12,0) -> 0 | AD12: =ELEC!Q13 -> 0 | AE12: =SUM(AD12/Z12) -> #DIV/0! | AF12: =SUM(AE12/1600) -> #DIV/0! | AG12: =SUM(AF12/1600) -> #DIV/0! | AH12: =SUM(AC12-AG12) -> #DIV/0! | AI12: =AD12*AJ12 -> 0 | AJ12: =305/1185 -> 0.25738397 | AK12: =AI12/Z12 -> #DIV/0! | AL12: =IF(Z12=0,0,1) -> 0
A13: =ELEC!C14 -> 44815 | B13: 908 | C13: =B13-B12 -> 10 | D13: =D12+C13*85 -> 752626 | E13: =SUM(D13-D12) -> 850 | F13: =IF(C13>0,E13/C13,0) -> 85 | H13: =H12 -> 12231 | I13: =IF(B13-H13<=0,"ok","oil change") -> ok | J13: =J12 -> 132 | K13: =J13-J12 -> 0 | L13: =(K13*N12)+L12 -> 389941 | M13: =SUM(L13-L12) -> 0 | N13: 250 | P13: =P12 -> 10873 | Q13: =IF(J13-P13<=0,"ok","oil change") -> ok | R13: 13910 | S13: =R13-R12 -> 1 | T13: =T12+U13 -> 417012 | U13: =V13*S13 -> 250 | V13: 250 | X13: =X12 -> 14773 | Y13: =IF(R13-X13<=0,"ok","oil change") -> ok | Z13: =C13+K13+S13 -> 11 | AA13: =U13+M13+E13 -> 1100 | AB13: =V13+N13+F13 -> 585 | AC13: =IF(Z13>0,AA13/Z13,0) -> 100 | AD13: =ELEC!Q14 -> 4297 | AE13: =SUM(AD13/Z13) -> 390.63636 | AF13: =SUM(AE13/1600) -> 0.24414773 | AG13: =SUM(AF13/1600) -> 0.00015259233 | AH13: =SUM(AC13-AG13) -> 99.999847 | AI13: =AD13*AJ13 -> 1105.9789 | AJ13: =305/1185 -> 0.25738397 | AK13: =AI13/Z13 -> 100.54354 | AL13: =IF(Z13=0,0,1) -> 1
A14: =ELEC!C15 -> 44816 | B14: 919 | C14: =B14-B13 -> 11 | D14: =D13+C14*85 -> 753561 | E14: =SUM(D14-D13) -> 935 | F14: =IF(C14>0,E14/C14,0) -> 85 | H14: =H13 -> 12231 | I14: =IF(B14-H14<=0,"ok","oil change") -> ok | J14: =J13 -> 132 | K14: =J14-J13 -> 0 | L14: =(K14*N13)+L13 -> 389941 | M14: =SUM(L14-L13) -> 0 | N14: 250 | P14: =P13 -> 10873 | Q14: =IF(J14-P14<=0,"ok","oil change") -> ok | R14: 13910 | S14: =R14-R13 -> 0 | T14: =T13+U14 -> 417012 | U14: =V14*S14 -> 0 | V14: 250 | X14: =X13 -> 14773 | Y14: =IF(R14-X14<=0,"ok","oil change") -> ok | Z14: =C14+K14+S14 -> 11 | AA14: =U14+M14+E14 -> 935 | AB14: =V14+N14+F14 -> 585 | AC14: =IF(Z14>0,AA14/Z14,0) -> 85 | AD14: =ELEC!Q15 -> 3256 | AE14: =SUM(AD14/Z14) -> 296 | AF14: =SUM(AE14/1600) -> 0.185 | AG14: =SUM(AF14/1600) -> 0.000115625 | AH14: =SUM(AC14-AG14) -> 84.999884 | AI14: =AD14*AJ14 -> 838.04219 | AJ14: =305/1185 -> 0.25738397 | AK14: =AI14/Z14 -> 76.185654 | AL14: =IF(Z14=0,0,1) -> 1
A15: =ELEC!C16 -> 44817 | B15: 929 | C15: =B15-B14 -> 10 | D15: =D14+C15*85 -> 754411 | E15: =SUM(D15-D14) -> 850 | F15: =IF(C15>0,E15/C15,0) -> 85 | H15: =H14 -> 12231 | I15: =IF(B15-H15<=0,"ok","oil change") -> ok | J15: =J14 -> 132 | K15: =J15-J14 -> 0 | L15: =(K15*N14)+L14 -> 389941 | M15: =SUM(L15-L14) -> 0 | N15: 250 | P15: =P14 -> 10873 | Q15: =IF(J15-P15<=0,"ok","oil change") -> ok | R15: =R14 -> 13910 | S15: =R15-R14 -> 0 | T15: =T14+U15 -> 417012 | U15: =V15*S15 -> 0 | V15: 250 | X15: =X14 -> 14773 | Y15: =IF(R15-X15<=0,"ok","oil change") -> ok | Z15: =C15+K15+S15 -> 10 | AA15: =U15+M15+E15 -> 850 | AB15: =V15+N15+F15 -> 585 | AC15: =IF(Z15>0,AA15/Z15,0) -> 85 | AD15: =ELEC!Q16 -> 2995 | AE15: =SUM(AD15/Z15) -> 299.5 | AF15: =SUM(AE15/1600) -> 0.1871875 | AG15: =SUM(AF15/1600) -> 0.00011699219 | AH15: =SUM(AC15-AG15) -> 84.999883 | AI15: =AD15*AJ15 -> 770.86498 | AJ15: =305/1185 -> 0.25738397 | AK15: =AI15/Z15 -> 77.086498 | AL15: =IF(Z15=0,0,1) -> 1
A16: =ELEC!C17 -> 44818 | B16: 939 | C16: =B16-B15 -> 10 | D16: =D15+C16*85 -> 755261 | E16: =SUM(D16-D15) -> 850 | F16: =IF(C16>0,E16/C16,0) -> 85 | H16: =H15 -> 12231 | I16: =IF(B16-H16<=0,"ok","oil change") -> ok | J16: 133 | K16: =J16-J15 -> 1 | L16: =(K16*N15)+L15 -> 390191 | M16: =SUM(L16-L15) -> 250 | N16: 250 | P16: =P15 -> 10873 | Q16: =IF(J16-P16<=0,"ok","oil change") -> ok | R16: =R15 -> 13910 | S16: =R16-R15 -> 0 | T16: =T15+U16 -> 417012 | U16: =V16*S16 -> 0 | V16: 250 | X16: =X15 -> 14773 | Y16: =IF(R16-X16<=0,"ok","oil change") -> ok | Z16: =C16+K16+S16 -> 11 | AA16: =U16+M16+E16 -> 1100 | AB16: =V16+N16+F16 -> 585 | AC16: =IF(Z16>0,AA16/Z16,0) -> 100 | AD16: =ELEC!Q17 -> 3159 | AE16: =SUM(AD16/Z16) -> 287.18182 | AF16: =SUM(AE16/1600) -> 0.17948864 | AG16: =SUM(AF16/1600) -> 0.0001121804 | AH16: =SUM(AC16-AG16) -> 99.999888 | AI16: =AD16*AJ16 -> 813.07595 | AJ16: =305/1185 -> 0.25738397 | AK16: =AI16/Z16 -> 73.915995 | AL16: =IF(Z16=0,0,1) -> 1
A17: =ELEC!C18 -> 44819 | B17: 949 | C17: =B17-B16 -> 10 | D17: =D16+C17*85 -> 756111 | E17: =SUM(D17-D16) -> 850 | F17: =IF(C17>0,E17/C17,0) -> 85 | H17: =H16 -> 12231 | I17: =IF(B17-H17<=0,"ok","oil change") -> ok | J17: =J16 -> 133 | K17: =J17-J16 -> 0 | L17: =(K17*N16)+L16 -> 390191 | M17: =SUM(L17-L16) -> 0 | N17: 250 | P17: =P16 -> 10873 | Q17: =IF(J17-P17<=0,"ok","oil change") -> ok | R17: =R16 -> 13910 | S17: =R17-R16 -> 0 | T17: =T16+U17 -> 417012 | U17: =V17*S17 -> 0 | V17: 250 | X17: =X16 -> 14773 | Y17: =IF(R17-X17<=0,"ok","oil change") -> ok | Z17: =C17+K17+S17 -> 10 | AA17: =U17+M17+E17 -> 850 | AB17: =V17+N17+F17 -> 585 | AC17: =IF(Z17>0,AA17/Z17,0) -> 85 | AD17: =ELEC!Q18 -> 0 | AE17: =SUM(AD17/Z17) -> 0 | AF17: =SUM(AE17/1600) -> 0 | AG17: =SUM(AF17/1600) -> 0 | AH17: =SUM(AC17-AG17) -> 85 | AI17: =AD17*AJ17 -> 0 | AJ17: =305/1185 -> 0.25738397 | AK17: =AI17/Z17 -> 0 | AL17: =IF(Z17=0,0,1) -> 1
A18: =ELEC!C19 -> 44820 | B18: =B17 -> 949 | C18: =B18-B17 -> 0 | D18: =D17+C18*85 -> 756111 | E18: =SUM(D18-D17) -> 0 | F18: =IF(C18>0,E18/C18,0) -> 0 | H18: =H17 -> 12231 | I18: =IF(B18-H18<=0,"ok","oil change") -> ok | J18: =J17 -> 133 | K18: =J18-J17 -> 0 | L18: =(K18*N17)+L17 -> 390191 | M18: =SUM(L18-L17) -> 0 | N18: 250 | P18: =P17 -> 10873 | Q18: =IF(J18-P14<=0,"ok","oil change") -> ok | R18: =R17 -> 13910 | S18: =R18-R17 -> 0 | T18: =T17+U18 -> 417012 | U18: =V18*S18 -> 0 | V18: 250 | X18: =X17 -> 14773 | Y18: =IF(R18-X18<=0,"ok","oil change") -> ok | Z18: =C18+K18+S18 -> 0 | AA18: =U18+M18+E18 -> 0 | AB18: =V18+N18+F18 -> 500 | AC18: =IF(Z18>0,AA18/Z18,0) -> 0 | AD18: =ELEC!Q19 -> 0 | AE18: =SUM(AD18/Z18) -> #DIV/0! | AF18: =SUM(AE18/1600) -> #DIV/0! | AG18: =SUM(AF18/1600) -> #DIV/0! | AH18: =SUM(AC18-AG18) -> #DIV/0! | AI18: =AD18*AJ18 -> 0 | AJ18: =305/1185 -> 0.25738397 | AK18: =AI18/Z18 -> #DIV/0! | AL18: =IF(Z18=0,0,1) -> 0
A19: =ELEC!C20 -> 44821 | B19: =B18 -> 949 | C19: =B19-B18 -> 0 | D19: =D18+C19*85 -> 756111 | E19: =SUM(D19-D18) -> 0 | F19: =IF(C19>0,E19/C19,0) -> 0 | H19: =H18 -> 12231 | I19: =IF(B19-H19<=0,"ok","oil change") -> ok | J19: =J18 -> 133 | K19: =J19-J18 -> 0 | L19: =(K19*N18)+L18 -> 390191 | M19: =SUM(L19-L18) -> 0 | N19: 250 | P19: =P18 -> 10873 | Q19: =IF(J19-P19<=0,"ok","oil change") -> ok | R19: =R18 -> 13910 | S19: =R19-R18 -> 0 | T19: =T18+U19 -> 417012 | U19: =V19*S19 -> 0 | V19: 250 | X19: =X18 -> 14773 | Y19: =IF(R19-X19<=0,"ok","oil change") -> ok | Z19: =C19+K19+S19 -> 0 | AA19: =U19+M19+E19 -> 0 | AB19: =V19+N19+F19 -> 500 | AC19: =IF(Z19>0,AA19/Z19,0) -> 0 | AD19: =ELEC!Q20 -> 0 | AE19: =SUM(AD19/Z19) -> #DIV/0! | AF19: =SUM(AE19/1600) -> #DIV/0! | AG19: =SUM(AF19/1600) -> #DIV/0! | AH19: =SUM(AC19-AG19) -> #DIV/0! | AI19: =AD19*AJ19 -> 0 | AJ19: =305/1185 -> 0.25738397 | AK19: =AI19/Z19 -> #DIV/0! | AL19: =IF(Z19=0,0,1) -> 0
A20: =ELEC!C21 -> 44822 | B20: 961 | C20: =B20-B19 -> 12 | D20: =D19+C20*85 -> 757131 | E20: =SUM(D20-D19) -> 1020 | F20: =IF(C20>0,E20/C20,0) -> 85 | H20: =H19 -> 12231 | I20: =IF(B20-H20<=0,"ok","oil change") -> ok | J20: =J19 -> 133 | K20: =J20-J19 -> 0 | L20: =(K20*N19)+L19 -> 390191 | M20: =SUM(L20-L19) -> 0 | N20: 250 | P20: =P19 -> 10873 | Q20: =IF(J20-P20<=0,"ok","oil change") -> ok | R20: =R19 -> 13910 | S20: =R20-R19 -> 0 | T20: =T19+U20 -> 417012 | U20: =V20*S20 -> 0 | V20: 250 | X20: =X19 -> 14773 | Y20: =IF(R20-X20<=0,"ok","oil change") -> ok | Z20: =C20+K20+S20 -> 12 | AA20: =U20+M20+E20 -> 1020 | AB20: =V20+N20+F20 -> 585 | AC20: =IF(Z20>0,AA20/Z20,0) -> 85 | AD20: =ELEC!Q21 -> 6162 | AE20: =SUM(AD20/Z20) -> 513.5 | AF20: =SUM(AE20/1600) -> 0.3209375 | AG20: =SUM(AF20/1600) -> 0.00020058594 | AH20: =SUM(AC20-AG20) -> 84.999799 | AI20: =AD20*AJ20 -> 1586 | AJ20: =305/1185 -> 0.25738397 | AK20: =AI20/Z20 -> 132.16667 | AL20: =IF(Z20=0,0,1) -> 1
A21: =ELEC!C22 -> 44823 | B21: 971 | C21: =B21-B20 -> 10 | D21: =D20+C21*85 -> 757981 | E21: =SUM(D21-D20) -> 850 | F21: =IF(C21>0,E21/C21,0) -> 85 | H21: =H20 -> 12231 | I21: =IF(B21-H21<=0,"ok","oil change") -> ok | J21: =J20 -> 133 | K21: =J21-J20 -> 0 | L21: =(K21*N20)+L20 -> 390191 | M21: =SUM(L21-L20) -> 0 | N21: 250 | P21: =P20 -> 10873 | Q21: =IF(J21-P21<=0,"ok","oil change") -> ok | R21: =R20 -> 13910 | S21: =R21-R20 -> 0 | T21: =T20+U21 -> 417012 | U21: =V21*S21 -> 0 | V21: 250 | X21: =X20 -> 14773 | Y21: =IF(R21-X21<=0,"ok","oil change") -> ok | Z21: =C21+K21+S21 -> 10 | AA21: =U21+M21+E21 -> 850 | AB21: =V21+N21+F21 -> 585 | AC21: =IF(Z21>0,AA21/Z21,0) -> 85 | AD21: =ELEC!Q22 -> 2828 | AE21: =SUM(AD21/Z21) -> 282.8 | AF21: =SUM(AE21/1600) -> 0.17675 | AG21: =SUM(AF21/1600) -> 0.00011046875 | AH21: =SUM(AC21-AG21) -> 84.99989 | AI21: =AD21*AJ21 -> 727.88186 | AJ21: =305/1185 -> 0.25738397 | AK21: =AI21/Z21 -> 72.788186 | AL21: =IF(Z21=0,0,1) -> 1
A22: =ELEC!C23 -> 44824 | B22: 981 | C22: =B22-B21 -> 10 | D22: =D21+C22*85 -> 758831 | E22: =SUM(D22-D21) -> 850 | F22: =IF(C22>0,E22/C22,0) -> 85 | H22: =H21 -> 12231 | I22: =IF(B22-H22<=0,"ok","oil change") -> ok | J22: =J21 -> 133 | K22: =J22-J21 -> 0 | L22: =(K22*N21)+L21 -> 390191 | M22: =SUM(L22-L21) -> 0 | N22: 250 | P22: =P21 -> 10873 | Q22: =IF(J22-P22<=0,"ok","oil change") -> ok | R22: 13912 | S22: =R22-R21 -> 2 | T22: =T21+U22 -> 417512 | U22: =V22*S22 -> 500 | V22: 250 | X22: =X21 -> 14773 | Y22: =IF(R22-X22<=0,"ok","oil change") -> ok | Z22: =C22+K22+S22 -> 12 | AA22: =U22+M22+E22 -> 1350 | AB22: =V22+N22+F22 -> 585 | AC22: =IF(Z22>0,AA22/Z22,0) -> 112.5 | AD22: =ELEC!Q23 -> 3850 | AE22: =SUM(AD22/Z22) -> 320.83333 | AF22: =SUM(AE22/1600) -> 0.20052083 | AG22: =SUM(AF22/1600) -> 0.00012532552 | AH22: =SUM(AC22-AG22) -> 112.49987 | AI22: =AD22*AJ22 -> 990.92827 | AJ22: =305/1185 -> 0.25738397 | AK22: =AI22/Z22 -> 82.577356 | AL22: =IF(Z22=0,0,1) -> 1
A23: =ELEC!C24 -> 44825 | B23: 991 | C23: =B23-B22 -> 10 | D23: =D22+C23*85 -> 759681 | E23: =SUM(D23-D22) -> 850 | F23: =IF(C23>0,E23/C23,0) -> 85 | H23: =H22 -> 12231 | I23: =IF(B23-H23<=0,"ok","oil change") -> ok | J23: =J22 -> 133 | K23: =J23-J22 -> 0 | L23: =(K23*N22)+L22 -> 390191 | M23: =SUM(L23-L22) -> 0 | N23: 250 | P23: =P22 -> 10873 | Q23: =IF(J23-P23<=0,"ok","oil change") -> ok | R23: =R22 -> 13912 | S23: =R23-R22 -> 0 | T23: =T22+U23 -> 417512 | U23: =V23*S23 -> 0 | V23: 250 | X23: =X22 -> 14773 | Y23: =IF(R23-X23<=0,"ok","oil change") -> ok | Z23: =C23+K23+S23 -> 10 | AA23: =U23+M23+E23 -> 850 | AB23: =V23+N23+F23 -> 585 | AC23: =IF(Z23>0,AA23/Z23,0) -> 85 | AD23: =ELEC!Q24 -> 2925 | AE23: =SUM(AD23/Z23) -> 292.5 | AF23: =SUM(AE23/1600) -> 0.1828125 | AG23: =SUM(AF23/1600) -> 0.00011425781 | AH23: =SUM(AC23-AG23) -> 84.999886 | AI23: =AD23*AJ23 -> 752.8481 | AJ23: =305/1185 -> 0.25738397 | AK23: =AI23/Z23 -> 75.28481 | AL23: =IF(Z23=0,0,1) -> 1
A24: =ELEC!C25 -> 44826 | B24: 1001 | C24: =B24-B23 -> 10 | D24: =D23+C24*85 -> 760531 | E24: =SUM(D24-D23) -> 850 | F24: =IF(C24>0,E24/C24,0) -> 85 | H24: =H23 -> 12231 | I24: =IF(B24-H24<=0,"ok","oil change") -> ok | J24: =J23 -> 133 | K24: =J24-J23 -> 0 | L24: =(K24*N23)+L23 -> 390191 | M24: =SUM(L24-L23) -> 0 | N24: 250 | P24: =P23 -> 10873 | Q24: =IF(J24-P24<=0,"ok","oil change") -> ok | R24: =R23 -> 13912 | S24: =R24-R23 -> 0 | T24: =T23+U24 -> 417512 | U24: =V24*S24 -> 0 | V24: 250 | X24: =X23 -> 14773 | Y24: =IF(R24-X24<=0,"ok","oil change") -> ok | Z24: =C24+K24+S24 -> 10 | AA24: =U24+M24+E24 -> 850 | AB24: =V24+N24+F24 -> 585 | AC24: =IF(Z24>0,AA24/Z24,0) -> 85 | AD24: =ELEC!Q25 -> 2780 | AE24: =SUM(AD24/Z24) -> 278 | AF24: =SUM(AE24/1600) -> 0.17375 | AG24: =SUM(AF24/1600) -> 0.00010859375 | AH24: =SUM(AC24-AG24) -> 84.999891 | AI24: =AD24*AJ24 -> 715.52743 | AJ24: =305/1185 -> 0.25738397 | AK24: =AI24/Z24 -> 71.552743 | AL24: =IF(Z24=0,0,1) -> 1
A25: =ELEC!C26 -> 44827 | B25: =B24 -> 1001 | C25: =B25-B24 -> 0 | D25: =D24+C25*85 -> 760531 | E25: =SUM(D25-D24) -> 0 | F25: =IF(C25>0,E25/C25,0) -> 0 | H25: =H24 -> 12231 | I25: =IF(B25-H25<=0,"ok","oil change") -> ok | J25: =J24 -> 133 | K25: =J25-J24 -> 0 | L25: =(K25*N24)+L24 -> 390191 | M25: =SUM(L25-L24) -> 0 | N25: 250 | P25: =P24 -> 10873 | Q25: =IF(J25-P25<=0,"ok","oil change") -> ok | R25: =R24 -> 13912 | S25: =R25-R24 -> 0 | T25: =T24+U25 -> 417512 | U25: =V25*S25 -> 0 | V25: 250 | X25: =X24 -> 14773 | Y25: =IF(R25-X25<=0,"ok","oil change") -> ok | Z25: =C25+K25+S25 -> 0 | AA25: =U25+M25+E25 -> 0 | AB25: =V25+N25+F25 -> 500 | AC25: =IF(Z25>0,AA25/Z25,0) -> 0 | AD25: =ELEC!Q26 -> 0 | AE25: =SUM(AD25/Z25) -> #DIV/0! | AF25: =SUM(AE25/1600) -> #DIV/0! | AG25: =SUM(AF25/1600) -> #DIV/0! | AH25: =SUM(AC25-AG25) -> #DIV/0! | AI25: =AD25*AJ25 -> 0 | AJ25: =305/1185 -> 0.25738397 | AK25: =AI25/Z25 -> #DIV/0! | AL25: =IF(Z25=0,0,1) -> 0
A26: =ELEC!C27 -> 44828 | B26: =B25 -> 1001 | C26: =B26-B25 -> 0 | D26: =D25+C26*85 -> 760531 | E26: =SUM(D26-D25) -> 0 | F26: =IF(C26>0,E26/C26,0) -> 0 | H26: =H25 -> 12231 | I26: =IF(B26-H26<=0,"ok","oil change") -> ok | J26: =J25 -> 133 | K26: =J26-J25 -> 0 | L26: =(K26*N25)+L25 -> 390191 | M26: =SUM(L26-L25) -> 0 | N26: 250 | P26: =P25 -> 10873 | Q26: =IF(J26-P26<=0,"ok","oil change") -> ok | R26: =R25 -> 13912 | S26: =R26-R25 -> 0 | T26: =T25+U26 -> 417512 | U26: =V26*S26 -> 0 | V26: 250 | X26: =X25 -> 14773 | Y26: =IF(R26-X26<=0,"ok","oil change") -> ok | Z26: =C26+K26+S26 -> 0 | AA26: =U26+M26+E26 -> 0 | AB26: =V26+N26+F26 -> 500 | AC26: =IF(Z26>0,AA26/Z26,0) -> 0 | AD26: =ELEC!Q27 -> 0 | AE26: =SUM(AD26/Z26) -> #DIV/0! | AF26: =SUM(AE26/1600) -> #DIV/0! | AG26: =SUM(AF26/1600) -> #DIV/0! | AH26: =SUM(AC26-AG26) -> #DIV/0! | AI26: =AD26*AJ26 -> 0 | AJ26: =305/1185 -> 0.25738397 | AK26: =AI26/Z26 -> #DIV/0! | AL26: =IF(Z26=0,0,1) -> 0
A27: =ELEC!C28 -> 44829 | B27: 1012 | C27: =B27-B26 -> 11 | D27: =D26+C27*85 -> 761466 | E27: =SUM(D27-D26) -> 935 | F27: =IF(C27>0,E27/C27,0) -> 85 | H27: =H26 -> 12231 | I27: =IF(B27-H27<=0,"ok","oil change") -> ok | J27: =J26 -> 133 | K27: =J27-J26 -> 0 | L27: =(K27*N26)+L26 -> 390191 | M27: =SUM(L27-L26) -> 0 | N27: 250 | P27: =P26 -> 10873 | Q27: =IF(J27-P27<=0,"ok","oil change") -> ok | R27: =R26 -> 13912 | S27: =R27-R26 -> 0 | T27: =T26+U27 -> 417512 | U27: =V27*S27 -> 0 | V27: 250 | X27: =X26 -> 14773 | Y27: =IF(R27-X27<=0,"ok","oil change") -> ok | Z27: =C27+K27+S27 -> 11 | AA27: =U27+M27+E27 -> 935 | AB27: =V27+N27+F27 -> 585 | AC27: =IF(Z27>0,AA27/Z27,0) -> 85 | AD27: =ELEC!Q28 -> 2785 | AE27: =SUM(AD27/Z27) -> 253.18182 | AF27: =SUM(AE27/1600) -> 0.15823864 | AG27: =SUM(AF27/1600) -> 9.8899148e-05 | AH27: =SUM(AC27-AG27) -> 84.999901 | AI27: =AD27*AJ27 -> 716.81435 | AJ27: =305/1185 -> 0.25738397 | AK27: =AI27/Z27 -> 65.164941 | AL27: =IF(Z27=0,0,1) -> 1
A28: =ELEC!C29 -> 44830 | B28: 1022 | C28: =B28-B27 -> 10 | D28: =D27+C28*85 -> 762316 | E28: =SUM(D28-D27) -> 850 | F28: =IF(C28>0,E28/C28,0) -> 85 | H28: =H27 -> 12231 | I28: =IF(B28-H28<=0,"ok","oil change") -> ok | J28: =J27 -> 133 | K28: =J28-J27 -> 0 | L28: =(K28*N27)+L27 -> 390191 | M28: =SUM(L28-L27) -> 0 | N28: 250 | P28: =P27 -> 10873 | Q28: =IF(J28-P28<=0,"ok","oil change") -> ok | R28: =R27 -> 13912 | S28: =R28-R27 -> 0 | T28: =T27+U28 -> 417512 | U28: =V28*S28 -> 0 | V28: 250 | X28: =X27 -> 14773 | Y28: =IF(R28-X28<=0,"ok","oil change") -> ok | Z28: =C28+K28+S28 -> 10 | AA28: =U28+M28+E28 -> 850 | AB28: =V28+N28+F28 -> 585 | AC28: =IF(Z28>0,AA28/Z28,0) -> 85 | AD28: =ELEC!Q29 -> 3082 | AE28: =SUM(AD28/Z28) -> 308.2 | AF28: =SUM(AE28/1600) -> 0.192625 | AG28: =SUM(AF28/1600) -> 0.00012039062 | AH28: =SUM(AC28-AG28) -> 84.99988 | AI28: =AD28*AJ28 -> 793.25738 | AJ28: =305/1185 -> 0.25738397 | AK28: =AI28/Z28 -> 79.325738 | AL28: =IF(Z28=0,0,1) -> 1
A29: =ELEC!C30 -> 44831 | B29: 1034 | C29: =B29-B28 -> 12 | D29: =D28+C29*85 -> 763336 | E29: =SUM(D29-D28) -> 1020 | F29: =IF(C29>0,E29/C29,0) -> 85 | H29: =H28 -> 12231 | I29: =IF(B29-H29<=0,"ok","oil change") -> ok | J29: =J28 -> 133 | K29: =J29-J28 -> 0 | L29: =(K29*N28)+L28 -> 390191 | M29: =SUM(L29-L28) -> 0 | N29: 250 | P29: =P28 -> 10873 | Q29: =IF(J29-P29<=0,"ok","oil change") -> ok | R29: =R28 -> 13912 | S29: =R29-R28 -> 0 | T29: =T28+U29 -> 417512 | U29: =V29*S29 -> 0 | V29: 250 | X29: =X28 -> 14773 | Y29: =IF(R29-X29<=0,"ok","oil change") -> ok | Z29: =C29+K29+S29 -> 12 | AA29: =U29+M29+E29 -> 1020 | AB29: =V29+N29+F29 -> 585 | AC29: =IF(Z29>0,AA29/Z29,0) -> 85 | AD29: =ELEC!Q30 -> 3676 | AE29: =SUM(AD29/Z29) -> 306.33333 | AF29: =SUM(AE29/1600) -> 0.19145833 | AG29: =SUM(AF29/1600) -> 0.00011966146 | AH29: =SUM(AC29-AG29) -> 84.99988 | AI29: =AD29*AJ29 -> 946.14346 | AJ29: =305/1185 -> 0.25738397 | AK29: =AI29/Z29 -> 78.845288 | AL29: =IF(Z29=0,0,1) -> 1
A30: =ELEC!C31 -> 44832 | B30: 1043 | C30: =B30-B29 -> 9 | D30: =D29+C30*85 -> 764101 | E30: =SUM(D30-D29) -> 765 | F30: =IF(C30>0,E30/C30,0) -> 85 | H30: =H29 -> 12231 | I30: =IF(B30-H30<=0,"ok","oil change") -> ok | J30: =J29 -> 133 | K30: =J30-J29 -> 0 | L30: =(K30*N29)+L29 -> 390191 | M30: =SUM(L30-L29) -> 0 | N30: 250 | P30: =P29 -> 10873 | Q30: =IF(J30-P30<=0,"ok","oil change") -> ok | R30: =R29 -> 13912 | S30: =R30-R29 -> 0 | T30: =T29+U30 -> 417512 | U30: =V30*S30 -> 0 | V30: 250 | X30: =X29 -> 14773 | Y30: =IF(R30-X30<=0,"ok","oil change") -> ok | Z30: =C30+K30+S30 -> 9 | AA30: =U30+M30+E30 -> 765 | AB30: =V30+N30+F30 -> 585 | AC30: =IF(Z30>0,AA30/Z30,0) -> 85 | AD30: =ELEC!Q31 -> 2282 | AE30: =SUM(AD30/Z30) -> 253.55556 | AF30: =SUM(AE30/1600) -> 0.15847222 | AG30: =SUM(AF30/1600) -> 9.9045139e-05 | AH30: =SUM(AC30-AG30) -> 84.999901 | AI30: =AD30*AJ30 -> 587.35021 | AJ30: =305/1185 -> 0.25738397 | AK30: =AI30/Z30 -> 65.261135 | AL30: =IF(Z30=0,0,1) -> 1
A31: =ELEC!C32 -> 44833 | B31: 1058 | C31: =B31-B30 -> 15 | D31: =D30+C31*85 -> 765376 | E31: =SUM(D31-D30) -> 1275 | F31: =IF(C31>0,E31/C31,0) -> 85 | H31: =H30 -> 12231 | I31: =IF(B31-H31<=0,"ok","oil change") -> ok | J31: =J30 -> 133 | K31: =J31-J30 -> 0 | L31: =(K31*N30)+L30 -> 390191 | M31: =SUM(L31-L30) -> 0 | N31: 250 | P31: =P30 -> 10873 | Q31: =IF(J31-P31<=0,"ok","oil change") -> ok | R31: =R30 -> 13912 | S31: =R31-R30 -> 0 | T31: =T30+U31 -> 417512 | U31: =V31*S31 -> 0 | V31: 250 | X31: =X30 -> 14773 | Y31: =IF(R31-X31<=0,"ok","oil change") -> ok | Z31: =C31+K31+S31 -> 15 | AA31: =U31+M31+E31 -> 1275 | AB31: =V31+N31+F31 -> 585 | AC31: =IF(Z31>0,AA31/Z31,0) -> 85 | AD31: =ELEC!Q32 -> 3508 | AE31: =SUM(AD31/Z31) -> 233.86667 | AF31: =SUM(AE31/1600) -> 0.14616667 | AG31: =SUM(AF31/1600) -> 9.1354167e-05 | AH31: =SUM(AC31-AG31) -> 84.999909 | AI31: =AD31*AJ31 -> 902.90295 | AJ31: =305/1185 -> 0.25738397 | AK31: =AI31/Z31 -> 60.19353 | AL31: =IF(Z31=0,0,1) -> 1
A32: =ELEC!C33 -> 44834 | B32: =B31 -> 1058 | C32: =B32-B31 -> 0 | D32: =D31+C32*85 -> 765376 | E32: =SUM(D32-D31) -> 0 | F32: =IF(C32>0,E32/C32,0) -> 0 | H32: =H31 -> 12231 | I32: =IF(B32-H32<=0,"ok","oil change") -> ok | J32: =J31 -> 133 | K32: =J32-J31 -> 0 | L32: =(K32*N31)+L31 -> 390191 | M32: =SUM(L32-L31) -> 0 | N32: 250 | P32: =P31 -> 10873 | Q32: =IF(J32-P32<=0,"ok","oil change") -> ok | R32: =R31 -> 13912 | S32: =R32-R31 -> 0 | T32: =T31+U32 -> 417512 | U32: =V32*S32 -> 0 | V32: 250 | X32: =X31 -> 14773 | Y32: =IF(R32-X32<=0,"ok","oil change") -> ok | Z32: =C32+K32+S32 -> 0 | AA32: =U32+M32+E32 -> 0 | AB32: =V32+N32+F32 -> 500 | AC32: =IF(Z32>0,AA32/Z32,0) -> 0 | AD32: =ELEC!Q33 -> 0 | AE32: =SUM(AD32/Z32) -> #DIV/0! | AF32: =SUM(AE32/1600) -> #DIV/0! | AG32: =SUM(AF32/1600) -> #DIV/0! | AH32: =SUM(AC32-AG32) -> #DIV/0! | AI32: =AD32*AJ32 -> 0 | AJ32: =305/1185 -> 0.25738397 | AK32: =AI32/Z32 -> #DIV/0! | AL32: =IF(Z32=0,0,1) -> 0
A33: =ELEC!C34 -> 44835 | B33: =B32 -> 1058 | C33: =B33-B32 -> 0 | D33: =D32+C33*85 -> 765376 | E33: =SUM(D33-D32) -> 0 | F33: =IF(C33>0,E33/C33,0) -> 0 | H33: =H32 -> 12231 | I33: =IF(B33-H33<=0,"ok","oil change") -> ok | J33: =J32 -> 133 | K33: =J33-J32 -> 0 | L33: =(K33*N32)+L32 -> 390191 | M33: =SUM(L33-L32) -> 0 | N33: 250 | P33: =P32 -> 10873 | Q33: =IF(J33-P33<=0,"ok","oil change") -> ok | R33: =R32 -> 13912 | S33: =R33-R32 -> 0 | T33: =T32+U33 -> 417512 | U33: =V33*S33 -> 0 | V33: 250 | X33: =X32 -> 14773 | Y33: =IF(R33-X33<=0,"ok","oil change") -> ok | Z33: =C33+K33+S33 -> 0 | AA33: =U33+M33+E33 -> 0 | AB33: =V33+N33+F33 -> 500 | AC33: =IF(Z33>0,AA33/Z33,0) -> 0 | AD33: =ELEC!Q34 -> 0 | AE33: =SUM(AD33/Z33) -> #DIV/0! | AF33: =SUM(AE33/1600) -> #DIV/0! | AG33: =SUM(AF33/1600) -> #DIV/0! | AH33: =SUM(AC33-AG33) -> #DIV/0! | AI33: =AD33*AJ33 -> 0 | AJ33: =305/1185 -> 0.25738397 | AK33: =AI33/Z33 -> #DIV/0! | AL33: =IF(Z33=0,0,1) -> 0
P34: =+O34/3 -> 0 | U34: =SUM(C35:S35) -> 233 | X34: 341 | Z34: =SUM(Z3:Z33) -> 233 | AF34: =SUM(AE34/1600) -> 0 | AL34: =SUM(AL3:AL33) -> 22
C35: =SUM(C3:C33) -> 221 | K35: =SUM(K3:K33) -> 8 | S35: =SUM(S3:S33) -> 4
T38: 14
T39: 10
D40: 193 | T40: 10
D41: =193+10 -> 203 | T41: 0
D42: =203+10 -> 213 | I42: =266-79 -> 187 | T42: 0
B43: =187+6 -> 193 | D43: =D42 -> 213 | T43: 8
D44: =D43 -> 213 | T44: 9
D45: =213+8 -> 221 | T45: 10
D46: =221+9 -> 230 | T46: 9
D47: =230+10 -> 240 | T47: 9
D48: =240+9 -> 249
D49: =249+9 -> 258
D50: 266

Sheet tanks
B2: Tank 1 | D2: Tank 2 | F2: Tank 3 | H2: Tank 4 | J2: Tank 5 | L2: Tank 6 | N2: Tank 7 | P2: Tank 8 | R2: Tank 9 | T2: Tank 10 | V2: Tank 11 | Z2: Tank 1 | AB2: Tank 2 | AD2: Tank 3 | AF2: Tank 4 | AH2: Tank 5 | AJ2: Tank 6 | AL2: Tank 7
B3: 6670 | D3: =SUM(B3) -> 6670 | F3: =SUM(D3) -> 6670 | H3: =SUM(F3) -> 6670 | J3: =SUM(H3) -> 6670 | L3: =SUM(J3) -> 6670 | N3: =SUM(L3) -> 6670 | P3: =SUM(N3) -> 6670 | R3: =SUM(P3) -> 6670 | T3: =SUM(R3) -> 6670 | V3: =SUM(T3) -> 6670 | W3: =SUM(B3:V3) -> 73370 | Z3: 2800 | AB3: 2800 | AD3: 2800 | AF3: 2800 | AH3: 2800 | AJ3: 2800 | AL3: 2800 | AM3: =SUM(Z3:AL3) -> 19600 | AO3: =SUM(AM3+W3) -> 92970 | AR3: Total sotck | AS3: Diesel Cons Per day | AT3: Diesel Delivery | BE3: Genset Co | BF3: Steam | BG3: Boil | BH3: Outdoor temperature
B4: =B3/310 -> 21.516129 | D4: =SUM(B4) -> 21.516129 | F4: =SUM(D4) -> 21.516129 | H4: =SUM(F4) -> 21.516129 | J4: =SUM(H4) -> 21.516129 | L4: =SUM(J4) -> 21.516129 | N4: =SUM(L4) -> 21.516129 | P4: =SUM(N4) -> 21.516129 | R4: =SUM(P4) -> 21.516129 | T4: =SUM(R4) -> 21.516129 | V4: =SUM(T4) -> 21.516129 | Z4: =Z3/280 -> 10 | AA4: =AA3/280 -> 0 | AB4: =AB3/280 -> 10 | AC4: =AC3/280 -> 0 | AD4: =AD3/280 -> 10 | AE4: =AE3/280 -> 0 | AF4: =AF3/280 -> 10 | AG4: =AG3/280 -> 0 | ... AL4: =AL3/280 -> 10 | AT4: Delivery | AU4: Cost /L | AW4: Boiler+Steam | AX4: Generator | AZ4: Occupancy | BA4: AVE TEPM | BB4: AVE Humidity
A5: =[2]tanks!$A$36 -> 44804 | B5: =[2]tanks!B36 -> 199 | C5: =[2]tanks!C36 -> 4281.7097 | D5: =[2]tanks!D36 -> 199 | E5: =[2]tanks!E36 -> 4281.7097 | F5: =[2]tanks!F36 -> 199 | G5: =[2]tanks!G36 -> 4281.7097 | H5: =[2]tanks!H36 -> 199 | I5: =[2]tanks!I36 -> 4281.7097 | ... AO5: =[2]tanks!AO36 -> 14420 | AQ5: =[2]tanks!AQ36 -> 0.661706 | AR5: =[2]tanks!AR36 -> 61518.806 | AS5: =[2]tanks!AS36 -> -1533.3871 | AT5: =[2]tanks!AT36 -> 0 | AU5: =[2]tanks!AU36 -> 0 | AV5: =[2]tanks!AV36 -> 0 | AW5: =[2]tanks!AW36 -> -144 | AX5: =[2]tanks!AX36 -> -1389.3871 | ... BB5: =[2]tanks!BB36 -> 0.8 | BC5: =[5]tanks!BC36 -> 0 | BD5: =[5]tanks!BD36 -> 19225 | BE5: =[5]tanks!BE36 -> #REF! | BF5: =[5]tanks!BF36 -> 0 | BG5: =[5]tanks!BG36 -> #REF! | BH5: =[5]tanks!BH36 -> 0 | BI5: =[5]tanks!BI36 -> 23
A6: =ELEC!C4 -> 44805 | B6: ='B5'!B5 -> 194.5 | C6: =B6*$B$4 -> 4184.8871 | D6: =SUM(B6) -> 194.5 | E6: =D6*$B$4 -> 4184.8871 | F6: =SUM(D6) -> 194.5 | G6: =F6*$B$4 -> 4184.8871 | H6: =SUM(F6) -> 194.5 | I6: =H6*$B$4 -> 4184.8871 | J6: =SUM(H6) -> 194.5 | K6: =J6*$B$4 -> 4184.8871 | L6: =SUM(J6) -> 194.5 | M6: =L6*$B$4 -> 4184.8871 | N6: =SUM(L6) -> 194.5 | O6: =N6*$B$4 -> 4184.8871 | P6: =SUM(N6) -> 194.5 | Q6: =P6*$B$4 -> 4184.8871 | R6: =SUM(P6) -> 194.5 | S6: =R6*$B$4 -> 4184.8871 | T6: =SUM(R6) -> 194.5 | U6: =T6*$B$4 -> 4184.8871 | V6: =SUM(T6) -> 194.5 | W6: =V6*$B$4 -> 4184.8871 | X6: =SUM(Y6/73370) -> 0.62741935 | Y6: =SUM(C6+E6+G6+I6+K6+M6+O6+Q6+S6+U6+W6) -> 46033.758 | Z6: ='B5'!C5 -> 201 | AA6: =SUM(Z6*$Z$4) -> 2010 | AB6: =SUM(Z6) -> 201 | AC6: =SUM(AB6*$Z$4) -> 2010 | AD6: =SUM(AB6) -> 201 | AE6: =SUM(AD6*$Z$4) -> 2010 | AF6: =SUM(AD6) -> 201 | AG6: =SUM(AF6*$Z$4) -> 2010 | AH6: =SUM(AF6) -> 201 | AI6: =SUM(AH6*$Z$4) -> 2010 | AJ6: =SUM(AH6) -> 201 | AK6: =SUM(AJ6*$Z$4) -> 2010 | AL6: =SUM(AJ6) -> 201 | AM6: =SUM(AL6*$Z$4) -> 2010 | AN6: =SUM(AO6/19600) -> 0.71785714 | AO6: =SUM(AA6+AC6+AE6+AG6+AI6+AK6+AM6) -> 14070 | AQ6: =SUM(AR6/92970) -> 0.64648551 | AR6: =Y6+AO6 -> 60103.758 | AS6: =SUM(AR6-AR5-AT6) -> -1415.0484 | AV6: =IF(AT6>0,AU6,AV5) -> 0 | AW6: =-SUM('B5'!AI5) -> -25 | AX6: =-SUM(AW6-AS6) -> -1390.0484 | AY6: =SUM(AX6+AW6) -> -1415.0484 | AZ6: =ELEC!A4 -> 0 | BA6: ='General information '!D5 -> 29.5 | BB6: =SUM('General information '!E5) -> 0.79 | BC6: =IF(AR3>=AR6,0,1) -> 0 | BD6: 19222 | BE6: =(305/1185)*ELEC!Q5 -> 0 | BG6: =#REF!-BE6 -> #REF! | BH6: 21 | BI6: 12 | BJ6: =AX6/BI6 -> -115.83737
A7: =ELEC!C5 -> 44806 | B7: ='B5'!B6 -> 194.5 | C7: =B7*$B$4 -> 4184.8871 | D7: =SUM(B7) -> 194.5 | E7: =D7*$B$4 -> 4184.8871 | F7: =SUM(D7) -> 194.5 | G7: =F7*$B$4 -> 4184.8871 | H7: =SUM(F7) -> 194.5 | I7: =H7*$B$4 -> 4184.8871 | J7: =SUM(H7) -> 194.5 | K7: =J7*$B$4 -> 4184.8871 | L7: =SUM(J7) -> 194.5 | M7: =L7*$B$4 -> 4184.8871 | N7: =SUM(L7) -> 194.5 | O7: =N7*$B$4 -> 4184.8871 | P7: =SUM(N7) -> 194.5 | Q7: =P7*$B$4 -> 4184.8871 | R7: =SUM(P7) -> 194.5 | S7: =R7*$B$4 -> 4184.8871 | T7: =SUM(R7) -> 194.5 | U7: =T7*$B$4 -> 4184.8871 | V7: =SUM(T7) -> 194.5 | W7: =V7*$B$4 -> 4184.8871 | X7: =SUM(Y7/73370) -> 0.62741935 | Y7: =SUM(C7+E7+G7+I7+K7+M7+O7+Q7+S7+U7+W7) -> 46033.758 | Z7: ='B5'!C6 -> 201 | AA7: =SUM(Z7*$Z$4) -> 2010 | AB7: =SUM(Z7) -> 201 | AC7: =SUM(AB7*$Z$4) -> 2010 | AD7: =SUM(AB7) -> 201 | AE7: =SUM(AD7*$Z$4) -> 2010 | AF7: =SUM(AD7) -> 201 | AG7: =SUM(AF7*$Z$4) -> 2010 | AH7: =SUM(AF7) -> 201 | AI7: =SUM(AH7*$Z$4) -> 2010 | AJ7: =SUM(AH7) -> 201 | AK7: =SUM(AJ7*$Z$4) -> 2010 | AL7: =SUM(AJ7) -> 201 | AM7: =SUM(AL7*$Z$4) -> 2010 | AN7: =SUM(AO7/19600) -> 0.71785714 | AO7: =SUM(AA7+AC7+AE7+AG7+AI7+AK7+AM7) -> 14070 | AQ7: =SUM(AR7/92970) -> 0.64648551 | AR7: =Y7+AO7 -> 60103.758 | AS7: =SUM(AR7-AR6-AT7) -> 0 | AV7: =IF(AT7>0,AU7,AV6) -> 0 | AW7: =-SUM('B5'!AI6) -> 0 | AX7: =-SUM(AW7-AS7) -> 0 | AY7: =SUM(AX7+AW7) -> 0 | AZ7: =ELEC!A5 -> 0 | BA7: ='General information '!D6 -> 0 | BB7: =SUM('General information '!E6) -> 0 | BC7: 0 | BD7: 19222 | BE7: =(305/1185)*ELEC!Q6 -> 0 | BG7: =#REF!-BE7 -> #REF! | BH7: 19 | BI7: 15 | BJ7: =AX7/BI7 -> 0
A8: =ELEC!C6 -> 44807 | B8: ='B5'!B7 -> 194.5 | C8: =B8*$B$4 -> 4184.8871 | D8: =SUM(B8) -> 194.5 | E8: =D8*$B$4 -> 4184.8871 | F8: =SUM(D8) -> 194.5 | G8: =F8*$B$4 -> 4184.8871 | H8: =SUM(F8) -> 194.5 | I8: =H8*$B$4 -> 4184.8871 | J8: =SUM(H8) -> 194.5 | K8: =J8*$B$4 -> 4184.8871 | L8: =SUM(J8) -> 194.5 | M8: =L8*$B$4 -> 4184.8871 | N8: =SUM(L8) -> 194.5 | O8: =N8*$B$4 -> 4184.8871 | P8: =SUM(N8) -> 194.5 | Q8: =P8*$B$4 -> 4184.8871 | R8: =SUM(P8) -> 194.5 | S8: =R8*$B$4 -> 4184.8871 | T8: =SUM(R8) -> 194.5 | U8: =T8*$B$4 -> 4184.8871 | V8: =SUM(T8) -> 194.5 | W8: =V8*$B$4 -> 4184.8871 | X8: =SUM(Y8/73370) -> 0.62741935 | Y8: =SUM(C8+E8+G8+I8+K8+M8+O8+Q8+S8+U8+W8) -> 46033.758 | Z8: ='B5'!C7 -> 201 | AA8: =SUM(Z8*$Z$4) -> 2010 | AB8: =SUM(Z8) -> 201 | AC8: =SUM(AB8*$Z$4) -> 2010 | AD8: =SUM(AB8) -> 201 | AE8: =SUM(AD8*$Z$4) -> 2010 | AF8: =SUM(AD8) -> 201 | AG8: =SUM(AF8*$Z$4) -> 2010 | AH8: =SUM(AF8) -> 201 | AI8: =SUM(AH8*$Z$4) -> 2010 | AJ8: =SUM(AH8) -> 201 | AK8: =SUM(AJ8*$Z$4) -> 2010 | AL8: =SUM(AJ8) -> 201 | AM8: =SUM(AL8*$Z$4) -> 2010 | AN8: =SUM(AO8/19600) -> 0.71785714 | AO8: =SUM(AA8+AC8+AE8+AG8+AI8+AK8+AM8) -> 14070 | AQ8: =SUM(AR8/92970) -> 0.64648551 | AR8: =Y8+AO8 -> 60103.758 | AS8: =SUM(AR8-AR7-AT8) -> 0 | AV8: =IF(AT8>0,AU8,AV7) -> 0 | AW8: =-SUM('B5'!AI7) -> 0 | AX8: =-SUM(AW8-AS8) -> 0 | AY8: =SUM(AX8+AW8) -> 0 | AZ8: =ELEC!A6 -> 0 | BA8: ='General information '!D7 -> 0 | BB8: =SUM('General information '!E7) -> 0 | BC8: =IF(AR7>=AR8,0,1) -> 0 | BD8: 19222 | BE8: =(305/1185)*ELEC!Q7 -> 824.14346 | BG8: =#REF!-BE8 -> #REF! | BH8: 16 | BI8: 9 | BJ8: =AX8/BI8 -> 0 | BK8: =GEN!AF5 -> #DIV/0!
A9: =ELEC!C7 -> 44808 | B9: ='B5'!B8 -> 190.5 | C9: =B9*$B$4 -> 4098.8226 | D9: =SUM(B9) -> 190.5 | E9: =D9*$B$4 -> 4098.8226 | F9: =SUM(D9) -> 190.5 | G9: =F9*$B$4 -> 4098.8226 | H9: =SUM(F9) -> 190.5 | I9: =H9*$B$4 -> 4098.8226 | J9: =SUM(H9) -> 190.5 | K9: =J9*$B$4 -> 4098.8226 | L9: =SUM(J9) -> 190.5 | M9: =L9*$B$4 -> 4098.8226 | N9: =SUM(L9) -> 190.5 | O9: =N9*$B$4 -> 4098.8226 | P9: =SUM(N9) -> 190.5 | Q9: =P9*$B$4 -> 4098.8226 | R9: =SUM(P9) -> 190.5 | S9: =R9*$B$4 -> 4098.8226 | T9: =SUM(R9) -> 190.5 | U9: =T9*$B$4 -> 4098.8226 | V9: =SUM(T9) -> 190.5 | W9: =V9*$B$4 -> 4098.8226 | X9: =SUM(Y9/73370) -> 0.61451613 | Y9: =SUM(C9+E9+G9+I9+K9+M9+O9+Q9+S9+U9+W9) -> 45087.048 | Z9: ='B5'!C8 -> 198 | AA9: =SUM(Z9*$Z$4) -> 1980 | AB9: =SUM(Z9) -> 198 | AC9: =SUM(AB9*$Z$4) -> 1980 | AD9: =SUM(AB9) -> 198 | AE9: =SUM(AD9*$Z$4) -> 1980 | AF9: =SUM(AD9) -> 198 | AG9: =SUM(AF9*$Z$4) -> 1980 | AH9: =SUM(AF9) -> 198 | AI9: =SUM(AH9*$Z$4) -> 1980 | AJ9: =SUM(AH9) -> 198 | AK9: =SUM(AJ9*$Z$4) -> 1980 | AL9: =SUM(AJ9) -> 198 | AM9: =SUM(AL9*$Z$4) -> 1980 | AN9: =SUM(AO9/19600) -> 0.70714286 | AO9: =SUM(AA9+AC9+AE9+AG9+AI9+AK9+AM9) -> 13860 | AQ9: =SUM(AR9/92970) -> 0.63404376 | AR9: =Y9+AO9 -> 58947.048 | AS9: =SUM(AR9-AR8-AT9) -> -1156.7097 | AV9: =IF(AT9>0,AU9,AV8) -> 0 | AW9: =-SUM('B5'!AI8) -> -148 | AX9: =-SUM(AW9-AS9) -> -1008.7097 | AY9: =SUM(AX9+AW9) -> -1156.7097 | AZ9: =ELEC!A7 -> 0 | BA9: ='General information '!D8 -> 27.5 | BB9: =SUM('General information '!E8) -> 0.69 | BC9: =IF(AR8>=AR9,0,1) -> 0 | BD9: 19222 | BE9: =(305/1185)*ELEC!Q8 -> 880.51055 | BG9: =#REF!-BE9 -> #REF! | BH9: 18 | BI9: 6 | BJ9: =AX9/BI9 -> -168.11828 | BK9: =GEN!AF6 -> 0.18193182
A10: =ELEC!C8 -> 44809 | B10: ='B5'!B9 -> 187 | C10: =B10*$B$4 -> 4023.5161 | D10: =SUM(B10) -> 187 | E10: =D10*$B$4 -> 4023.5161 | F10: =SUM(D10) -> 187 | G10: =F10*$B$4 -> 4023.5161 | H10: =SUM(F10) -> 187 | I10: =H10*$B$4 -> 4023.5161 | J10: =SUM(H10) -> 187 | K10: =J10*$B$4 -> 4023.5161 | L10: =SUM(J10) -> 187 | M10: =L10*$B$4 -> 4023.5161 | N10: =SUM(L10) -> 187 | O10: =N10*$B$4 -> 4023.5161 | P10: =SUM(N10) -> 187 | Q10: =P10*$B$4 -> 4023.5161 | R10: =SUM(P10) -> 187 | S10: =R10*$B$4 -> 4023.5161 | T10: =SUM(R10) -> 187 | U10: =T10*$B$4 -> 4023.5161 | V10: =SUM(T10) -> 187 | W10: =V10*$B$4 -> 4023.5161 | X10: =SUM(Y10/73370) -> 0.60322581 | Y10: =SUM(C10+E10+G10+I10+K10+M10+O10+Q10+S10+U10+W10) -> 44258.677 | Z10: ='B5'!C9 -> 193 | AA10: =SUM(Z10*$Z$4) -> 1930 | AB10: =SUM(Z10) -> 193 | AC10: =SUM(AB10*$Z$4) -> 1930 | AD10: =SUM(AB10) -> 193 | AE10: =SUM(AD10*$Z$4) -> 1930 | AF10: =SUM(AD10) -> 193 | AG10: =SUM(AF10*$Z$4) -> 1930 | AH10: =SUM(AF10) -> 193 | AI10: =SUM(AH10*$Z$4) -> 1930 | AJ10: =SUM(AH10) -> 193 | AK10: =SUM(AJ10*$Z$4) -> 1930 | AL10: =SUM(AJ10) -> 193 | AM10: =SUM(AL10*$Z$4) -> 1930 | AN10: =SUM(AO10/19600) -> 0.68928571 | AO10: =SUM(AA10+AC10+AE10+AG10+AI10+AK10+AM10) -> 13510 | AQ10: =SUM(AR10/92970) -> 0.62136902 | AR10: =Y10+AO10 -> 57768.677 | AS10: =SUM(AR10-AR9-AT10) -> -1178.371 | AV10: =IF(AT10>0,AU10,AV9) -> 0 | AW10: =-SUM('B5'!AI9) -> -113 | AX10: =-SUM(AW10-AS10) -> -1065.371 | AY10: =SUM(AX10+AW10) -> -1178.371 | AZ10: =ELEC!A8 -> 0 | BA10: ='General information '!D9 -> 27.5 | BB10: =SUM('General information '!E9) -> 0.69 | BC10: =IF(AR9>=AR10,0,1) -> 0 | BD10: 19222 | BE10: =(305/1185)*ELEC!Q9 -> 1322.1814 | BG10: =#REF!-BE10 -> #REF! | BH10: 16 | BI10: 7 | BJ10: =AX10/BI10 -> -152.19585 | BK10: =GEN!AF7 -> 0.194375
A11: =ELEC!C9 -> 44810 | B11: ='B5'!B10 -> 180 | C11: =B11*$B$4 -> 3872.9032 | D11: =SUM(B11) -> 180 | E11: =D11*$B$4 -> 3872.9032 | F11: =SUM(D11) -> 180 | G11: =F11*$B$4 -> 3872.9032 | H11: =SUM(F11) -> 180 | I11: =H11*$B$4 -> 3872.9032 | J11: =SUM(H11) -> 180 | K11: =J11*$B$4 -> 3872.9032 | L11: =SUM(J11) -> 180 | M11: =L11*$B$4 -> 3872.9032 | N11: =SUM(L11) -> 180 | O11: =N11*$B$4 -> 3872.9032 | P11: =SUM(N11) -> 180 | Q11: =P11*$B$4 -> 3872.9032 | R11: =SUM(P11) -> 180 | S11: =R11*$B$4 -> 3872.9032 | T11: =SUM(R11) -> 180 | U11: =T11*$B$4 -> 3872.9032 | V11: =SUM(T11) -> 180 | W11: =V11*$B$4 -> 3872.9032 | X11: =SUM(Y11/73370) -> 0.58064516 | Y11: =SUM(C11+E11+G11+I11+K11+M11+O11+Q11+S11+U11+W11) -> 42601.935 | Z11: ='B5'!C10 -> 187 | AA11: =SUM(Z11*$Z$4) -> 1870 | AB11: =SUM(Z11) -> 187 | AC11: =SUM(AB11*$Z$4) -> 1870 | AD11: =SUM(AB11) -> 187 | AE11: =SUM(AD11*$Z$4) -> 1870 | AF11: =SUM(AD11) -> 187 | AG11: =SUM(AF11*$Z$4) -> 1870 | AH11: =SUM(AF11) -> 187 | AI11: =SUM(AH11*$Z$4) -> 1870 | AJ11: =SUM(AH11) -> 187 | AK11: =SUM(AJ11*$Z$4) -> 1870 | AL11: =SUM(AJ11) -> 187 | AM11: =SUM(AL11*$Z$4) -> 1870 | AN11: =SUM(AO11/19600) -> 0.66785714 | AO11: =SUM(AA11+AC11+AE11+AG11+AI11+AK11+AM11) -> 13090 | AQ11: =SUM(AR11/92970) -> 0.59903125 | AR11: =Y11+AO11 -> 55691.935 | AS11: =SUM(AR11-AR10-AT11) -> -2076.7419 | AV11: =IF(AT11>0,AU11,AV10) -> 0 | AW11: =-SUM('B5'!AI10) -> -74 | AX11: =-SUM(AW11-AS11) -> -2002.7419 | AY11: =SUM(AX11+AW11) -> -2076.7419 | AZ11: =ELEC!A9 -> 0 | BA11: ='General information '!D10 -> 28 | BB11: =SUM('General information '!E10) -> 0.65 | BC11: =IF(AR10>=AR11,0,1) -> 0 | BD11: 19222 | BE11: =(305/1185)*ELEC!Q10 -> 1251.6582 | BG11: =#REF!-BE11 -> #REF! | BH11: 16.5 | BI11: 9.3 | BJ11: =AX11/BI11 -> -215.3486
A12: =ELEC!C10 -> 44811 | B12: ='B5'!B11 -> 190 | C12: =B12*$B$4 -> 4088.0645 | D12: =SUM(B12) -> 190 | E12: =D12*$B$4 -> 4088.0645 | F12: =SUM(D12) -> 190 | G12: =F12*$B$4 -> 4088.0645 | H12: =SUM(F12) -> 190 | I12: =H12*$B$4 -> 4088.0645 | J12: =SUM(H12) -> 190 | K12: =J12*$B$4 -> 4088.0645 | L12: =SUM(J12) -> 190 | M12: =L12*$B$4 -> 4088.0645 | N12: =SUM(L12) -> 190 | O12: =N12*$B$4 -> 4088.0645 | P12: =SUM(N12) -> 190 | Q12: =P12*$B$4 -> 4088.0645 | R12: =SUM(P12) -> 190 | S12: =R12*$B$4 -> 4088.0645 | T12: =SUM(R12) -> 190 | U12: =T12*$B$4 -> 4088.0645 | V12: =SUM(T12) -> 190 | W12: =V12*$B$4 -> 4088.0645 | X12: =SUM(Y12/73370) -> 0.61290323 | Y12: =SUM(C12+E12+G12+I12+K12+M12+O12+Q12+S12+U12+W12) -> 44968.71 | Z12: ='B5'!C11 -> 197 | AA12: =SUM(Z12*$Z$4) -> 1970 | AB12: =SUM(Z12) -> 197 | AC12: =SUM(AB12*$Z$4) -> 1970 | AD12: =SUM(AB12) -> 197 | AE12: =SUM(AD12*$Z$4) -> 1970 | AF12: =SUM(AD12) -> 197 | AG12: =SUM(AF12*$Z$4) -> 1970 | AH12: =SUM(AF12) -> 197 | AI12: =SUM(AH12*$Z$4) -> 1970 | AJ12: =SUM(AH12) -> 197 | AK12: =SUM(AJ12*$Z$4) -> 1970 | AL12: =SUM(AJ12) -> 197 | AM12: =SUM(AL12*$Z$4) -> 1970 | AN12: =SUM(AO12/19600) -> 0.70357143 | AO12: =SUM(AA12+AC12+AE12+AG12+AI12+AK12+AM12) -> 13790 | AQ12: =SUM(AR12/92970) -> 0.63201796 | AR12: =Y12+AO12 -> 58758.71 | AS12: =SUM(AR12-AR11-AT12) -> -1933.2258 | AT12: 5000 | AU12: 1.111 | AV12: =IF(AT12>0,AU12,AV11) -> 1.111 | AW12: =-SUM('B5'!AI11) -> -90 | AX12: =-SUM(AW12-AS12) -> -1843.2258 | AY12: =SUM(AX12+AW12) -> -1933.2258 | AZ12: =ELEC!A10 -> 0 | BA12: ='General information '!D11 -> 28 | BB12: =SUM('General information '!E11) -> 0.67 | BC12: =IF(AR11>=AR12,0,1) -> 1 | BD12: 19222 | BE12: =(305/1185)*ELEC!Q11 -> 975.22785 | BG12: =#REF!-BE12 -> #REF! | BH12: 15.5 | BI12: 3.7 | BJ12: =AX12/BI12 -> -498.16914
A13: =ELEC!C11 -> 44812 | B13: ='B5'!B12 -> 187 | C13: =B13*$B$4 -> 4023.5161 | D13: =SUM(B13) -> 187 | E13: =D13*$B$4 -> 4023.5161 | F13: =SUM(D13) -> 187 | G13: =F13*$B$4 -> 4023.5161 | H13: =SUM(F13) -> 187 | I13: =H13*$B$4 -> 4023.5161 | J13: =SUM(H13) -> 187 | K13: =J13*$B$4 -> 4023.5161 | L13: =SUM(J13) -> 187 | M13: =L13*$B$4 -> 4023.5161 | N13: =SUM(L13) -> 187 | O13: =N13*$B$4 -> 4023.5161 | P13: =SUM(N13) -> 187 | Q13: =P13*$B$4 -> 4023.5161 | R13: =SUM(P13) -> 187 | S13: =R13*$B$4 -> 4023.5161 | T13: =SUM(R13) -> 187 | U13: =T13*$B$4 -> 4023.5161 | V13: =SUM(T13) -> 187 | W13: =V13*$B$4 -> 4023.5161 | X13: =SUM(Y13/73370) -> 0.60322581 | Y13: =SUM(C13+E13+G13+I13+K13+M13+O13+Q13+S13+U13+W13) -> 44258.677 | Z13: ='B5'!C12 -> 193 | AA13: =SUM(Z13*$Z$4) -> 1930 | AB13: =SUM(Z13) -> 193 | AC13: =SUM(AB13*$Z$4) -> 1930 | AD13: =SUM(AB13) -> 193 | AE13: =SUM(AD13*$Z$4) -> 1930 | AF13: =SUM(AD13) -> 193 | AG13: =SUM(AF13*$Z$4) -> 1930 | AH13: =SUM(AF13) -> 193 | AI13: =SUM(AH13*$Z$4) -> 1930 | AJ13: =SUM(AH13) -> 193 | AK13: =SUM(AJ13*$Z$4) -> 1930 | AL13: =SUM(AJ13) -> 193 | AM13: =SUM(AL13*$Z$4) -> 1930 | AN13: =SUM(AO13/19600) -> 0.68928571 | AO13: =SUM(AA13+AC13+AE13+AG13+AI13+AK13+AM13) -> 13510 | AQ13: =SUM(AR13/92970) -> 0.62136902 | AR13: =Y13+AO13 -> 57768.677 | AS13: =SUM(AR13-AR12-AT13) -> -990.03226 | AV13: =IF(AT13>0,AU13,AV12) -> 1.111 | AW13: =-SUM('B5'!AI12) -> 0 | AX13: =-SUM(AW13-AS13) -> -990.03226 | AY13: =SUM(AX13+AW13) -> -990.03226 | AZ13: =ELEC!A11 -> 0 | BA13: ='General information '!D12 -> 29 | BB13: =SUM('General information '!E12) -> 0.62 | BC13: =IF(AR12>=AR13,0,1) -> 0 | BD13: 19222 | BE13: =(305/1185)*ELEC!Q12 -> 0 | BG13: =#REF!-BE13 -> #REF! | BI13: 5 | BJ13: =AX13/BI13 -> -198.00645 | BK13: =GEN!AF10 -> 0.21528409
A14: =ELEC!C12 -> 44813 | B14: ='B5'!B13 -> 187 | C14: =B14*$B$4 -> 4023.5161 | D14: =SUM(B14) -> 187 | E14: =D14*$B$4 -> 4023.5161 | F14: =SUM(D14) -> 187 | G14: =F14*$B$4 -> 4023.5161 | H14: =SUM(F14) -> 187 | I14: =H14*$B$4 -> 4023.5161 | J14: =SUM(H14) -> 187 | K14: =J14*$B$4 -> 4023.5161 | L14: =SUM(J14) -> 187 | M14: =L14*$B$4 -> 4023.5161 | N14: =SUM(L14) -> 187 | O14: =N14*$B$4 -> 4023.5161 | P14: =SUM(N14) -> 187 | Q14: =P14*$B$4 -> 4023.5161 | R14: =SUM(P14) -> 187 | S14: =R14*$B$4 -> 4023.5161 | T14: =SUM(R14) -> 187 | U14: =T14*$B$4 -> 4023.5161 | V14: =SUM(T14) -> 187 | W14: =V14*$B$4 -> 4023.5161 | X14: =SUM(Y14/73370) -> 0.60322581 | Y14: =SUM(C14+E14+G14+I14+K14+M14+O14+Q14+S14+U14+W14) -> 44258.677 | Z14: ='B5'!C13 -> 193 | AA14: =SUM(Z14*$Z$4) -> 1930 | AB14: =SUM(Z14) -> 193 | AC14: =SUM(AB14*$Z$4) -> 1930 | AD14: =SUM(AB14) -> 193 | AE14: =SUM(AD14*$Z$4) -> 1930 | AF14: =SUM(AD14) -> 193 | AG14: =SUM(AF14*$Z$4) -> 1930 | AH14: =SUM(AF14) -> 193 | AI14: =SUM(AH14*$Z$4) -> 1930 | AJ14: =SUM(AH14) -> 193 | AK14: =SUM(AJ14*$Z$4) -> 1930 | AL14: =SUM(AJ14) -> 193 | AM14: =SUM(AL14*$Z$4) -> 1930 | AN14: =SUM(AO14/19600) -> 0.68928571 | AO14: =SUM(AA14+AC14+AE14+AG14+AI14+AK14+AM14) -> 13510 | AQ14: =SUM(AR14/92970) -> 0.62136902 | AR14: =Y14+AO14 -> 57768.677 | AS14: =SUM(AR14-AR13-AT14) -> 0 | AV14: =IF(AT14>0,AU14,AV13) -> 1.111 | AW14: =-SUM('B5'!AI13) -> 0 | AX14: =-SUM(AW14-AS14) -> 0 | AY14: =SUM(AX14+AW14) -> 0 | AZ14: =ELEC!A12 -> 0 | BA14: ='General information '!D13 -> 0 | BB14: =SUM('General information '!E13) -> 0 | BC14: =IF(AR13>=AR14,0,1) -> 0 | BD14: 19222 | BE14: =(305/1185)*ELEC!Q13 -> 0 | BG14: =#REF!-BE14 -> #REF! | BI14: 3 | BJ14: =AX14/BI14 -> 0 | BK14: =GEN!AF11 -> 0
A15: =ELEC!C13 -> 44814 | B15: ='B5'!B14 -> 187 | C15: =B15*$B$4 -> 4023.5161 | D15: =SUM(B15) -> 187 | E15: =D15*$B$4 -> 4023.5161 | F15: =SUM(D15) -> 187 | G15: =F15*$B$4 -> 4023.5161 | H15: =SUM(F15) -> 187 | I15: =H15*$B$4 -> 4023.5161 | J15: =SUM(H15) -> 187 | K15: =J15*$B$4 -> 4023.5161 | L15: =SUM(J15) -> 187 | M15: =L15*$B$4 -> 4023.5161 | N15: =SUM(L15) -> 187 | O15: =N15*$B$4 -> 4023.5161 | P15: =SUM(N15) -> 187 | Q15: =P15*$B$4 -> 4023.5161 | R15: =SUM(P15) -> 187 | S15: =R15*$B$4 -> 4023.5161 | T15: =SUM(R15) -> 187 | U15: =T15*$B$4 -> 4023.5161 | V15: =SUM(T15) -> 187 | W15: =V15*$B$4 -> 4023.5161 | X15: =SUM(Y15/73370) -> 0.60322581 | Y15: =SUM(C15+E15+G15+I15+K15+M15+O15+Q15+S15+U15+W15) -> 44258.677 | Z15: ='B5'!C14 -> 193 | AA15: =SUM(Z15*$Z$4) -> 1930 | AB15: =SUM(Z15) -> 193 | AC15: =SUM(AB15*$Z$4) -> 1930 | AD15: =SUM(AB15) -> 193 | AE15: =SUM(AD15*$Z$4) -> 1930 | AF15: =SUM(AD15) -> 193 | AG15: =SUM(AF15*$Z$4) -> 1930 | AH15: =SUM(AF15) -> 193 | AI15: =SUM(AH15*$Z$4) -> 1930 | AJ15: =SUM(AH15) -> 193 | AK15: =SUM(AJ15*$Z$4) -> 1930 | AL15: =SUM(AJ15) -> 193 | AM15: =SUM(AL15*$Z$4) -> 1930 | AN15: =SUM(AO15/19600) -> 0.68928571 | AO15: =SUM(AA15+AC15+AE15+AG15+AI15+AK15+AM15) -> 13510 | AQ15: =SUM(AR15/92970) -> 0.62136902 | AR15: =Y15+AO15 -> 57768.677 | AS15: =SUM(AR15-AR14-AT15) -> 0 | AV15: =IF(AT15>0,AU15,AV14) -> 1.111 | AW15: =-SUM('B5'!AI14) -> 0 | AX15: =-SUM(AW15-AS15) -> 0 | AY15: =SUM(AX15+AW15) -> 0 | AZ15: =ELEC!A13 -> 0 | BA15: ='General information '!D14 -> 0 | BB15: =SUM('General information '!E14) -> 0 | BC15: =IF(AR14>=AR15,0,1) -> 0 | BD15: 19222 | BE15: =(305/1185)*ELEC!Q14 -> 1105.9789 | BG15: =#REF!-BE15 -> #REF! | BI15: 4 | BJ15: =AX15/BI15 -> 0 | BK15: =GEN!AF12 -> #DIV/0!
A16: =ELEC!C14 -> 44815 | B16: ='B5'!B15 -> 182.5 | C16: =B16*$B$4 -> 3926.6935 | D16: =SUM(B16) -> 182.5 | E16: =D16*$B$4 -> 3926.6935 | F16: =SUM(D16) -> 182.5 | G16: =F16*$B$4 -> 3926.6935 | H16: =SUM(F16) -> 182.5 | I16: =H16*$B$4 -> 3926.6935 | J16: =SUM(H16) -> 182.5 | K16: =J16*$B$4 -> 3926.6935 | L16: =SUM(J16) -> 182.5 | M16: =L16*$B$4 -> 3926.6935 | N16: =SUM(L16) -> 182.5 | O16: =N16*$B$4 -> 3926.6935 | P16: =SUM(N16) -> 182.5 | Q16: =P16*$B$4 -> 3926.6935 | R16: =SUM(P16) -> 182.5 | S16: =R16*$B$4 -> 3926.6935 | T16: =SUM(R16) -> 182.5 | U16: =T16*$B$4 -> 3926.6935 | V16: =SUM(T16) -> 182.5 | W16: =V16*$B$4 -> 3926.6935 | X16: =SUM(Y16/73370) -> 0.58870968 | Y16: =SUM(C16+E16+G16+I16+K16+M16+O16+Q16+S16+U16+W16) -> 43193.629 | Z16: ='B5'!C15 -> 189 | AA16: =SUM(Z16*$Z$4) -> 1890 | AB16: =SUM(Z16) -> 189 | AC16: =SUM(AB16*$Z$4) -> 1890 | AD16: =SUM(AB16) -> 189 | AE16: =SUM(AD16*$Z$4) -> 1890 | AF16: =SUM(AD16) -> 189 | AG16: =SUM(AF16*$Z$4) -> 1890 | AH16: =SUM(AF16) -> 189 | AI16: =SUM(AH16*$Z$4) -> 1890 | AJ16: =SUM(AH16) -> 189 | AK16: =SUM(AJ16*$Z$4) -> 1890 | AL16: =SUM(AJ16) -> 189 | AM16: =SUM(AL16*$Z$4) -> 1890 | AN16: =SUM(AO16/19600) -> 0.675 | AO16: =SUM(AA16+AC16+AE16+AG16+AI16+AK16+AM16) -> 13230 | AQ16: =SUM(AR16/92970) -> 0.60690146 | AR16: =Y16+AO16 -> 56423.629 | AS16: =SUM(AR16-AR15-AT16) -> -1345.0484 | AV16: =IF(AT16>0,AU16,AV15) -> 1.111 | AW16: =-SUM('B5'!AI15) -> -217 | AX16: =-SUM(AW16-AS16) -> -1128.0484 | AY16: =SUM(AX16+AW16) -> -1345.0484 | AZ16: =ELEC!A14 -> 0 | BA16: ='General information '!D15 -> 27 | BB16: =SUM('General information '!E15) -> 0.66 | BC16: =IF(AR15>=AR16,0,1) -> 0 | BD16: 19222 | BE16: =(305/1185)*ELEC!Q15 -> 838.04219 | BG16: =#REF!-BE16 -> #REF! | BI16: 3 | BJ16: =AX16/BI16 -> -376.01613 | BK16: =GEN!AF13 -> 0.24414773
A17: =ELEC!C15 -> 44816 | B17: ='B5'!B16 -> 233 | C17: =B17*$B$4 -> 5013.2581 | D17: =SUM(B17) -> 233 | E17: =D17*$B$4 -> 5013.2581 | F17: =SUM(D17) -> 233 | G17: =F17*$B$4 -> 5013.2581 | H17: =SUM(F17) -> 233 | I17: =H17*$B$4 -> 5013.2581 | J17: =SUM(H17) -> 233 | K17: =J17*$B$4 -> 5013.2581 | L17: =SUM(J17) -> 233 | M17: =L17*$B$4 -> 5013.2581 | N17: =SUM(L17) -> 233 | O17: =N17*$B$4 -> 5013.2581 | P17: =SUM(N17) -> 233 | Q17: =P17*$B$4 -> 5013.2581 | R17: =SUM(P17) -> 233 | S17: =R17*$B$4 -> 5013.2581 | T17: =SUM(R17) -> 233 | U17: =T17*$B$4 -> 5013.2581 | V17: =SUM(T17) -> 233 | W17: =V17*$B$4 -> 5013.2581 | X17: =SUM(Y17/73370) -> 0.7516129 | Y17: =SUM(C17+E17+G17+I17+K17+M17+O17+Q17+S17+U17+W17) -> 55145.839 | Z17: ='B5'!C16 -> 239 | AA17: =SUM(Z17*$Z$4) -> 2390 | AB17: =SUM(Z17) -> 239 | AC17: =SUM(AB17*$Z$4) -> 2390 | AD17: =SUM(AB17) -> 239 | AE17: =SUM(AD17*$Z$4) -> 2390 | AF17: =SUM(AD17) -> 239 | AG17: =SUM(AF17*$Z$4) -> 2390 | AH17: =SUM(AF17) -> 239 | AI17: =SUM(AH17*$Z$4) -> 2390 | AJ17: =SUM(AH17) -> 239 | AK17: =SUM(AJ17*$Z$4) -> 2390 | AL17: =SUM(AJ17) -> 239 | AM17: =SUM(AL17*$Z$4) -> 2390 | AN17: =SUM(AO17/19600) -> 0.85357143 | AO17: =SUM(AA17+AC17+AE17+AG17+AI17+AK17+AM17) -> 16730 | AQ17: =SUM(AR17/92970) -> 0.77310787 | AR17: =Y17+AO17 -> 71875.839 | AS17: =SUM(AR17-AR16-AT17) -> 1089.2097 | AT17: 14363 | AU17: 1.063 | AV17: =IF(AT17>0,AU17,AV16) -> 1.063 | AW17: =-SUM('B5'!AI16) -> -8 | AX17: =-SUM(AW17-AS17) -> 1097.2097 | AY17: =SUM(AX17+AW17) -> 1089.2097 | AZ17: =ELEC!A15 -> 0 | BA17: ='General information '!D16 -> 27 | BB17: =SUM('General information '!E16) -> 0.67 | BC17: =IF(AR16>=AR17,0,1) -> 1 | BD17: 19222 | BE17: =(305/1185)*ELEC!Q16 -> 770.86498 | BG17: =#REF!-BE17 -> #REF! | BI17: 4 | BJ17: =AX17/BI17 -> 274.30242 | BK17: =GEN!AF14 -> 0.185
A18: =ELEC!C16 -> 44817 | B18: ='B5'!B17 -> 229 | C18: =B18*$B$4 -> 4927.1935 | D18: =SUM(B18) -> 229 | E18: =D18*$B$4 -> 4927.1935 | F18: =SUM(D18) -> 229 | G18: =F18*$B$4 -> 4927.1935 | H18: =SUM(F18) -> 229 | I18: =H18*$B$4 -> 4927.1935 | J18: =SUM(H18) -> 229 | K18: =J18*$B$4 -> 4927.1935 | L18: =SUM(J18) -> 229 | M18: =L18*$B$4 -> 4927.1935 | N18: =SUM(L18) -> 229 | O18: =N18*$B$4 -> 4927.1935 | P18: =SUM(N18) -> 229 | Q18: =P18*$B$4 -> 4927.1935 | R18: =SUM(P18) -> 229 | S18: =R18*$B$4 -> 4927.1935 | T18: =SUM(R18) -> 229 | U18: =T18*$B$4 -> 4927.1935 | V18: =SUM(T18) -> 229 | W18: =V18*$B$4 -> 4927.1935 | X18: =SUM(Y18/73370) -> 0.73870968 | Y18: =SUM(C18+E18+G18+I18+K18+M18+O18+Q18+S18+U18+W18) -> 54199.129 | Z18: ='B5'!C17 -> 236 | AA18: =SUM(Z18*$Z$4) -> 2360 | AB18: =SUM(Z18) -> 236 | AC18: =SUM(AB18*$Z$4) -> 2360 | AD18: =SUM(AB18) -> 236 | AE18: =SUM(AD18*$Z$4) -> 2360 | AF18: =SUM(AD18) -> 236 | AG18: =SUM(AF18*$Z$4) -> 2360 | AH18: =SUM(AF18) -> 236 | AI18: =SUM(AH18*$Z$4) -> 2360 | AJ18: =SUM(AH18) -> 236 | AK18: =SUM(AJ18*$Z$4) -> 2360 | AL18: =SUM(AJ18) -> 236 | AM18: =SUM(AL18*$Z$4) -> 2360 | AN18: =SUM(AO18/19600) -> 0.84285714 | AO18: =SUM(AA18+AC18+AE18+AG18+AI18+AK18+AM18) -> 16520 | AQ18: =SUM(AR18/92970) -> 0.76066612 | AR18: =Y18+AO18 -> 70719.129 | AS18: =SUM(AR18-AR17-AT18) -> -1156.7097 | AV18: =IF(AT18>0,AU18,AV17) -> 1.063 | AW18: =-SUM('B5'!AI17) -> -187 | AX18: =-SUM(AW18-AS18) -> -969.70968 | AY18: =SUM(AX18+AW18) -> -1156.7097 | AZ18: =ELEC!A16 -> 0 | BA18: ='General information '!D17 -> 26 | BB18: =SUM('General information '!E17) -> 0.57 | BC18: =IF(AR17>=AR18,0,1) -> 0 | BD18: 19222 | BE18: =(305/1185)*ELEC!Q17 -> 813.07595 | BG18: =#REF!-BE18 -> #REF! | BI18: 5 | BJ18: =AX18/BI18 -> -193.94194
A19: =ELEC!C17 -> 44818 | B19: ='B5'!B18 -> 226 | C19: =B19*$B$4 -> 4862.6452 | D19: =SUM(B19) -> 226 | E19: =D19*$B$4 -> 4862.6452 | F19: =SUM(D19) -> 226 | G19: =F19*$B$4 -> 4862.6452 | H19: =SUM(F19) -> 226 | I19: =H19*$B$4 -> 4862.6452 | J19: =SUM(H19) -> 226 | K19: =J19*$B$4 -> 4862.6452 | L19: =SUM(J19) -> 226 | M19: =L19*$B$4 -> 4862.6452 | N19: =SUM(L19) -> 226 | O19: =N19*$B$4 -> 4862.6452 | P19: =SUM(N19) -> 226 | Q19: =P19*$B$4 -> 4862.6452 | R19: =SUM(P19) -> 226 | S19: =R19*$B$4 -> 4862.6452 | T19: =SUM(R19) -> 226 | U19: =T19*$B$4 -> 4862.6452 | V19: =SUM(T19) -> 226 | W19: =V19*$B$4 -> 4862.6452 | X19: =SUM(Y19/73370) -> 0.72903226 | Y19: =SUM(C19+E19+G19+I19+K19+M19+O19+Q19+S19+U19+W19) -> 53489.097 | Z19: ='B5'!C18 -> 232 | AA19: =SUM(Z19*$Z$4) -> 2320 | AB19: =SUM(Z19) -> 232 | AC19: =SUM(AB19*$Z$4) -> 2320 | AD19: =SUM(AB19) -> 232 | AE19: =SUM(AD19*$Z$4) -> 2320 | AF19: =SUM(AD19) -> 232 | AG19: =SUM(AF19*$Z$4) -> 2320 | AH19: =SUM(AF19) -> 232 | AI19: =SUM(AH19*$Z$4) -> 2320 | AJ19: =SUM(AH19) -> 232 | AK19: =SUM(AJ19*$Z$4) -> 2320 | AL19: =SUM(AJ19) -> 232 | AM19: =SUM(AL19*$Z$4) -> 2320 | AN19: =SUM(AO19/19600) -> 0.82857143 | AO19: =SUM(AA19+AC19+AE19+AG19+AI19+AK19+AM19) -> 16240 | AQ19: =SUM(AR19/92970) -> 0.75001718 | AR19: =Y19+AO19 -> 69729.097 | AS19: =SUM(AR19-AR18-AT19) -> -990.03226 | AV19: =IF(AT19>0,AU19,AV18) -> 1.063 | AW19: =-SUM('B5'!AI18) -> -81 | AX19: =-SUM(AW19-AS19) -> -909.03226 | AY19: =SUM(AX19+AW19) -> -990.03226 | AZ19: =ELEC!A17 -> 0 | BA19: ='General information '!D18 -> 28 | BB19: =SUM('General information '!E18) -> 0.58 | BC19: =IF(AR18>=AR19,0,1) -> 0 | BD19: 19222 | BE19: =(305/1185)*ELEC!Q18 -> 0 | BG19: =#REF!-BE19 -> #REF! | BI19: 6 | BJ19: =AX19/BI19 -> -151.50538
A20: =ELEC!C18 -> 44819 | B20: ='B5'!B19 -> 223 | C20: =B20*$B$4 -> 4798.0968 | D20: =SUM(B20) -> 223 | E20: =D20*$B$4 -> 4798.0968 | F20: =SUM(D20) -> 223 | G20: =F20*$B$4 -> 4798.0968 | H20: =SUM(F20) -> 223 | I20: =H20*$B$4 -> 4798.0968 | J20: =SUM(H20) -> 223 | K20: =J20*$B$4 -> 4798.0968 | L20: =SUM(J20) -> 223 | M20: =L20*$B$4 -> 4798.0968 | N20: =SUM(L20) -> 223 | O20: =N20*$B$4 -> 4798.0968 | P20: =SUM(N20) -> 223 | Q20: =P20*$B$4 -> 4798.0968 | R20: =SUM(P20) -> 223 | S20: =R20*$B$4 -> 4798.0968 | T20: =SUM(R20) -> 223 | U20: =T20*$B$4 -> 4798.0968 | V20: =SUM(T20) -> 223 | W20: =V20*$B$4 -> 4798.0968 | X20: =SUM(Y20/73370) -> 0.71935484 | Y20: =SUM(C20+E20+G20+I20+K20+M20+O20+Q20+S20+U20+W20) -> 52779.065 | Z20: ='B5'!C19 -> 229 | AA20: =SUM(Z20*$Z$4) -> 2290 | AB20: =SUM(Z20) -> 229 | AC20: =SUM(AB20*$Z$4) -> 2290 | AD20: =SUM(AB20) -> 229 | AE20: =SUM(AD20*$Z$4) -> 2290 | AF20: =SUM(AD20) -> 229 | AG20: =SUM(AF20*$Z$4) -> 2290 | AH20: =SUM(AF20) -> 229 | AI20: =SUM(AH20*$Z$4) -> 2290 | AJ20: =SUM(AH20) -> 229 | AK20: =SUM(AJ20*$Z$4) -> 2290 | AL20: =SUM(AJ20) -> 229 | AM20: =SUM(AL20*$Z$4) -> 2290 | AN20: =SUM(AO20/19600) -> 0.81785714 | AO20: =SUM(AA20+AC20+AE20+AG20+AI20+AK20+AM20) -> 16030 | AQ20: =SUM(AR20/92970) -> 0.74012116 | AR20: =Y20+AO20 -> 68809.065 | AS20: =SUM(AR20-AR19-AT20) -> -920.03226 | AV20: =IF(AT20>0,AU20,AV19) -> 1.063 | AW20: =-SUM('B5'!AI19) -> 0 | AX20: =-SUM(AW20-AS20) -> -920.03226 | AY20: =SUM(AX20+AW20) -> -920.03226 | AZ20: =ELEC!A18 -> 0 | BA20: ='General information '!D19 -> 27 | BB20: =SUM('General information '!E19) -> 0.57 | BC20: =IF(AR19>=AR20,0,1) -> 0 | BD20: 19222 | BE20: =(305/1185)*ELEC!Q19 -> 0 | BG20: =#REF!-BE20 -> #REF! | BI20: 7 | BJ20: =AX20/BI20 -> -131.43318 | BK20: =GEN!AF17 -> 0
A21: =ELEC!C19 -> 44820 | B21: ='B5'!B20 -> 223 | C21: =B21*$B$4 -> 4798.0968 | D21: =SUM(B21) -> 223 | E21: =D21*$B$4 -> 4798.0968 | F21: =SUM(D21) -> 223 | G21: =F21*$B$4 -> 4798.0968 | H21: =SUM(F21) -> 223 | I21: =H21*$B$4 -> 4798.0968 | J21: =SUM(H21) -> 223 | K21: =J21*$B$4 -> 4798.0968 | L21: =SUM(J21) -> 223 | M21: =L21*$B$4 -> 4798.0968 | N21: =SUM(L21) -> 223 | O21: =N21*$B$4 -> 4798.0968 | P21: =SUM(N21) -> 223 | Q21: =P21*$B$4 -> 4798.0968 | R21: =SUM(P21) -> 223 | S21: =R21*$B$4 -> 4798.0968 | T21: =SUM(R21) -> 223 | U21: =T21*$B$4 -> 4798.0968 | V21: =SUM(T21) -> 223 | W21: =V21*$B$4 -> 4798.0968 | X21: =SUM(Y21/73370) -> 0.71935484 | Y21: =SUM(C21+E21+G21+I21+K21+M21+O21+Q21+S21+U21+W21) -> 52779.065 | Z21: ='B5'!C20 -> 229 | AA21: =SUM(Z21*$Z$4) -> 2290 | AB21: =SUM(Z21) -> 229 | AC21: =SUM(AB21*$Z$4) -> 2290 | AD21: =SUM(AB21) -> 229 | AE21: =SUM(AD21*$Z$4) -> 2290 | AF21: =SUM(AD21) -> 229 | AG21: =SUM(AF21*$Z$4) -> 2290 | AH21: =SUM(AF21) -> 229 | AI21: =SUM(AH21*$Z$4) -> 2290 | AJ21: =SUM(AH21) -> 229 | AK21: =SUM(AJ21*$Z$4) -> 2290 | AL21: =SUM(AJ21) -> 229 | AM21: =SUM(AL21*$Z$4) -> 2290 | AN21: =SUM(AO21/19600) -> 0.81785714 | AO21: =SUM(AA21+AC21+AE21+AG21+AI21+AK21+AM21) -> 16030 | AQ21: =SUM(AR21/92970) -> 0.74012116 | AR21: =Y21+AO21 -> 68809.065 | AS21: =SUM(AR21-AR20-AT21) -> 0 | AV21: =IF(AT21>0,AU21,AV20) -> 1.063 | AW21: =-SUM('B5'!AI20) -> 0 | AX21: =-SUM(AW21-AS21) -> 0 | AY21: =SUM(AX21+AW21) -> 0 | AZ21: =ELEC!A19 -> 0 | BA21: ='General information '!D20 -> 0 | BB21: =SUM('General information '!E20) -> 0 | BC21: =IF(AR20>=AR21,0,1) -> 0 | BD21: 19222 | BE21: =(305/1185)*ELEC!Q20 -> 0 | BG21: =#REF!-BE21 -> #REF! | BI21: 8 | BJ21: =AX21/BI21 -> 0 | BK21: =GEN!AF18 -> #DIV/0!
A22: =ELEC!C20 -> 44821 | B22: ='B5'!B21 -> 223 | C22: =B22*$B$4 -> 4798.0968 | D22: =SUM(B22) -> 223 | E22: =D22*$B$4 -> 4798.0968 | F22: =SUM(D22) -> 223 | G22: =F22*$B$4 -> 4798.0968 | H22: =SUM(F22) -> 223 | I22: =H22*$B$4 -> 4798.0968 | J22: =SUM(H22) -> 223 | K22: =J22*$B$4 -> 4798.0968 | L22: =SUM(J22) -> 223 | M22: =L22*$B$4 -> 4798.0968 | N22: =SUM(L22) -> 223 | O22: =N22*$B$4 -> 4798.0968 | P22: =SUM(N22) -> 223 | Q22: =P22*$B$4 -> 4798.0968 | R22: =SUM(P22) -> 223 | S22: =R22*$B$4 -> 4798.0968 | T22: =SUM(R22) -> 223 | U22: =T22*$B$4 -> 4798.0968 | V22: =SUM(T22) -> 223 | W22: =V22*$B$4 -> 4798.0968 | X22: =SUM(Y22/73370) -> 0.71935484 | Y22: =SUM(C22+E22+G22+I22+K22+M22+O22+Q22+S22+U22+W22) -> 52779.065 | Z22: ='B5'!C21 -> 229 | AA22: =SUM(Z22*$Z$4) -> 2290 | AB22: =SUM(Z22) -> 229 | AC22: =SUM(AB22*$Z$4) -> 2290 | AD22: =SUM(AB22) -> 229 | AE22: =SUM(AD22*$Z$4) -> 2290 | AF22: =SUM(AD22) -> 229 | AG22: =SUM(AF22*$Z$4) -> 2290 | AH22: =SUM(AF22) -> 229 | AI22: =SUM(AH22*$Z$4) -> 2290 | AJ22: =SUM(AH22) -> 229 | AK22: =SUM(AJ22*$Z$4) -> 2290 | AL22: =SUM(AJ22) -> 229 | AM22: =SUM(AL22*$Z$4) -> 2290 | AN22: =SUM(AO22/19600) -> 0.81785714 | AO22: =SUM(AA22+AC22+AE22+AG22+AI22+AK22+AM22) -> 16030 | AQ22: =SUM(AR22/92970) -> 0.74012116 | AR22: =Y22+AO22 -> 68809.065 | AS22: =SUM(AR22-AR21-AT22) -> 0 | AV22: =IF(AT22>0,AU22,AV21) -> 1.063 | AW22: =-SUM('B5'!AI21) -> 0 | AX22: =-SUM(AW22-AS22) -> 0 | AY22: =SUM(AX22+AW22) -> 0 | AZ22: =ELEC!A20 -> 0 | BA22: ='General information '!D21 -> 0 | BB22: =SUM('General information '!E21) -> 0 | BC22: =IF(AR21>=AR22,0,1) -> 0 | BD22: 19222 | BE22: =(305/1185)*ELEC!Q21 -> 1586 | BG22: =#REF!-BE22 -> #REF! | BI22: 9 | BJ22: =AX22/BI22 -> 0 | BK22: =GEN!AF19 -> #DIV/0!
A23: =ELEC!C21 -> 44822 | B23: ='B5'!B22 -> 239 | C23: =B23*$B$4 -> 5142.3548 | D23: =SUM(B23) -> 239 | E23: =D23*$B$4 -> 5142.3548 | F23: =SUM(D23) -> 239 | G23: =F23*$B$4 -> 5142.3548 | H23: =SUM(F23) -> 239 | I23: =H23*$B$4 -> 5142.3548 | J23: =SUM(H23) -> 239 | K23: =J23*$B$4 -> 5142.3548 | L23: =SUM(J23) -> 239 | M23: =L23*$B$4 -> 5142.3548 | N23: =SUM(L23) -> 239 | O23: =N23*$B$4 -> 5142.3548 | P23: =SUM(N23) -> 239 | Q23: =P23*$B$4 -> 5142.3548 | R23: =SUM(P23) -> 239 | S23: =R23*$B$4 -> 5142.3548 | T23: =SUM(R23) -> 239 | U23: =T23*$B$4 -> 5142.3548 | V23: =SUM(T23) -> 239 | W23: =V23*$B$4 -> 5142.3548 | X23: =SUM(Y23/73370) -> 0.77096774 | Y23: =SUM(C23+E23+G23+I23+K23+M23+O23+Q23+S23+U23+W23) -> 56565.903 | Z23: ='B5'!C22 -> 245 | AA23: =SUM(Z23*$Z$4) -> 2450 | AB23: =SUM(Z23) -> 245 | AC23: =SUM(AB23*$Z$4) -> 2450 | AD23: =SUM(AB23) -> 245 | AE23: =SUM(AD23*$Z$4) -> 2450 | AF23: =SUM(AD23) -> 245 | AG23: =SUM(AF23*$Z$4) -> 2450 | AH23: =SUM(AF23) -> 245 | AI23: =SUM(AH23*$Z$4) -> 2450 | AJ23: =SUM(AH23) -> 245 | AK23: =SUM(AJ23*$Z$4) -> 2450 | AL23: =SUM(AJ23) -> 245 | AM23: =SUM(AL23*$Z$4) -> 2450 | AN23: =SUM(AO23/19600) -> 0.875 | AO23: =SUM(AA23+AC23+AE23+AG23+AI23+AK23+AM23) -> 17150 | AQ23: =SUM(AR23/92970) -> 0.79289989 | AR23: =Y23+AO23 -> 73715.903 | AS23: =SUM(AR23-AR22-AT23) -> -123.16129 | AT23: 5030 | AU23: 1.01 | AV23: =IF(AT23>0,AU23,AV22) -> 1.01 | AW23: =-SUM('B5'!AI22) -> -113 | AX23: =-SUM(AW23-AS23) -> -10.16129 | AY23: =SUM(AX23+AW23) -> -123.16129 | AZ23: =ELEC!A21 -> 0 | BA23: ='General information '!D22 -> 27 | BB23: =SUM('General information '!E22) -> 0.7 | BC23: =IF(AR22>=AR23,0,1) -> 1 | BD23: 19222 | BE23: =(305/1185)*ELEC!Q22 -> 727.88186 | BG23: =#REF!-BE23 -> #REF! | BI23: 10 | BJ23: =AX23/BI23 -> -1.016129 | BK23: =GEN!AF20 -> 0.3209375
A24: =ELEC!C22 -> 44823 | B24: ='B5'!B23 -> 235 | C24: =B24*$B$4 -> 5056.2903 | D24: =SUM(B24) -> 235 | E24: =D24*$B$4 -> 5056.2903 | F24: =SUM(D24) -> 235 | G24: =F24*$B$4 -> 5056.2903 | H24: =SUM(F24) -> 235 | I24: =H24*$B$4 -> 5056.2903 | J24: =SUM(H24) -> 235 | K24: =J24*$B$4 -> 5056.2903 | L24: =SUM(J24) -> 235 | M24: =L24*$B$4 -> 5056.2903 | N24: =SUM(L24) -> 235 | O24: =N24*$B$4 -> 5056.2903 | P24: =SUM(N24) -> 235 | Q24: =P24*$B$4 -> 5056.2903 | R24: =SUM(P24) -> 235 | S24: =R24*$B$4 -> 5056.2903 | T24: =SUM(R24) -> 235 | U24: =T24*$B$4 -> 5056.2903 | V24: =SUM(T24) -> 235 | W24: =V24*$B$4 -> 5056.2903 | X24: =SUM(Y24/73370) -> 0.75806452 | Y24: =SUM(C24+E24+G24+I24+K24+M24+O24+Q24+S24+U24+W24) -> 55619.194 | Z24: ='B5'!C23 -> 241 | AA24: =SUM(Z24*$Z$4) -> 2410 | AB24: =SUM(Z24) -> 241 | AC24: =SUM(AB24*$Z$4) -> 2410 | AD24: =SUM(AB24) -> 241 | AE24: =SUM(AD24*$Z$4) -> 2410 | AF24: =SUM(AD24) -> 241 | AG24: =SUM(AF24*$Z$4) -> 2410 | AH24: =SUM(AF24) -> 241 | AI24: =SUM(AH24*$Z$4) -> 2410 | AJ24: =SUM(AH24) -> 241 | AK24: =SUM(AJ24*$Z$4) -> 2410 | AL24: =SUM(AJ24) -> 241 | AM24: =SUM(AL24*$Z$4) -> 2410 | AN24: =SUM(AO24/19600) -> 0.86071429 | AO24: =SUM(AA24+AC24+AE24+AG24+AI24+AK24+AM24) -> 16870 | AQ24: =SUM(AR24/92970) -> 0.77970521 | AR24: =Y24+AO24 -> 72489.194 | AS24: =SUM(AR24-AR23-AT24) -> -1226.7097 | AV24: =IF(AT24>0,AU24,AV23) -> 1.01 | AW24: =-SUM('B5'!AI23) -> -113 | AX24: =-SUM(AW24-AS24) -> -1113.7097 | AY24: =SUM(AX24+AW24) -> -1226.7097 | AZ24: =ELEC!A22 -> 0 | BA24: ='General information '!D23 -> 26 | BB24: =SUM('General information '!E23) -> 0.6 | BC24: =IF(AR23>=AR24,0,1) -> 0 | BD24: 19222 | BE24: =(305/1185)*ELEC!Q23 -> 990.92827 | BG24: =#REF!-BE24 -> #REF! | BI24: 11 | BJ24: =AX24/BI24 -> -101.24633 | BK24: =GEN!AF21 -> 0.17675
A25: =ELEC!C23 -> 44824 | B25: ='B5'!B24 -> 231 | C25: =B25*$B$4 -> 4970.2258 | D25: =SUM(B25) -> 231 | E25: =D25*$B$4 -> 4970.2258 | F25: =SUM(D25) -> 231 | G25: =F25*$B$4 -> 4970.2258 | H25: =SUM(F25) -> 231 | I25: =H25*$B$4 -> 4970.2258 | J25: =SUM(H25) -> 231 | K25: =J25*$B$4 -> 4970.2258 | L25: =SUM(J25) -> 231 | M25: =L25*$B$4 -> 4970.2258 | N25: =SUM(L25) -> 231 | O25: =N25*$B$4 -> 4970.2258 | P25: =SUM(N25) -> 231 | Q25: =P25*$B$4 -> 4970.2258 | R25: =SUM(P25) -> 231 | S25: =R25*$B$4 -> 4970.2258 | T25: =SUM(R25) -> 231 | U25: =T25*$B$4 -> 4970.2258 | V25: =SUM(T25) -> 231 | W25: =V25*$B$4 -> 4970.2258 | X25: =SUM(Y25/73370) -> 0.74516129 | Y25: =SUM(C25+E25+G25+I25+K25+M25+O25+Q25+S25+U25+W25) -> 54672.484 | Z25: ='B5'!C24 -> 237 | AA25: =SUM(Z25*$Z$4) -> 2370 | AB25: =SUM(Z25) -> 237 | AC25: =SUM(AB25*$Z$4) -> 2370 | AD25: =SUM(AB25) -> 237 | AE25: =SUM(AD25*$Z$4) -> 2370 | AF25: =SUM(AD25) -> 237 | AG25: =SUM(AF25*$Z$4) -> 2370 | AH25: =SUM(AF25) -> 237 | AI25: =SUM(AH25*$Z$4) -> 2370 | AJ25: =SUM(AH25) -> 237 | AK25: =SUM(AJ25*$Z$4) -> 2370 | AL25: =SUM(AJ25) -> 237 | AM25: =SUM(AL25*$Z$4) -> 2370 | AN25: =SUM(AO25/19600) -> 0.84642857 | AO25: =SUM(AA25+AC25+AE25+AG25+AI25+AK25+AM25) -> 16590 | AQ25: =SUM(AR25/92970) -> 0.76651053 | AR25: =Y25+AO25 -> 71262.484 | AS25: =SUM(AR25-AR24-AT25) -> -1226.7097 | AV25: =IF(AT25>0,AU25,AV24) -> 1.01 | AW25: =-SUM('B5'!AI24) -> -31 | AX25: =-SUM(AW25-AS25) -> -1195.7097 | AY25: =SUM(AX25+AW25) -> -1226.7097 | AZ25: =ELEC!A23 -> 0 | BA25: ='General information '!D24 -> 25.5 | BB25: =SUM('General information '!E24) -> 0.53 | BC25: =IF(AR24>=AR25,0,1) -> 0 | BD25: 19222 | BE25: =(305/1185)*ELEC!Q24 -> 752.8481 | BG25: =#REF!-BE25 -> #REF! | BI25: 12 | BJ25: =AX25/BI25 -> -99.642473
A26: =ELEC!C24 -> 44825 | B26: ='B5'!B25 -> 227 | C26: =B26*$B$4 -> 4884.1613 | D26: =SUM(B26) -> 227 | E26: =D26*$B$4 -> 4884.1613 | F26: =SUM(D26) -> 227 | G26: =F26*$B$4 -> 4884.1613 | H26: =SUM(F26) -> 227 | I26: =H26*$B$4 -> 4884.1613 | J26: =SUM(H26) -> 227 | K26: =J26*$B$4 -> 4884.1613 | L26: =SUM(J26) -> 227 | M26: =L26*$B$4 -> 4884.1613 | N26: =SUM(L26) -> 227 | O26: =N26*$B$4 -> 4884.1613 | P26: =SUM(N26) -> 227 | Q26: =P26*$B$4 -> 4884.1613 | R26: =SUM(P26) -> 227 | S26: =R26*$B$4 -> 4884.1613 | T26: =SUM(R26) -> 227 | U26: =T26*$B$4 -> 4884.1613 | V26: =SUM(T26) -> 227 | W26: =V26*$B$4 -> 4884.1613 | X26: =SUM(Y26/73370) -> 0.73225806 | Y26: =SUM(C26+E26+G26+I26+K26+M26+O26+Q26+S26+U26+W26) -> 53725.774 | Z26: ='B5'!C25 -> 233 | AA26: =SUM(Z26*$Z$4) -> 2330 | AB26: =SUM(Z26) -> 233 | AC26: =SUM(AB26*$Z$4) -> 2330 | AD26: =SUM(AB26) -> 233 | AE26: =SUM(AD26*$Z$4) -> 2330 | AF26: =SUM(AD26) -> 233 | AG26: =SUM(AF26*$Z$4) -> 2330 | AH26: =SUM(AF26) -> 233 | AI26: =SUM(AH26*$Z$4) -> 2330 | AJ26: =SUM(AH26) -> 233 | AK26: =SUM(AJ26*$Z$4) -> 2330 | AL26: =SUM(AJ26) -> 233 | AM26: =SUM(AL26*$Z$4) -> 2330 | AN26: =SUM(AO26/19600) -> 0.83214286 | AO26: =SUM(AA26+AC26+AE26+AG26+AI26+AK26+AM26) -> 16310 | AQ26: =SUM(AR26/92970) -> 0.75331585 | AR26: =Y26+AO26 -> 70035.774 | AS26: =SUM(AR26-AR25-AT26) -> -1226.7097 | AV26: =IF(AT26>0,AU26,AV25) -> 1.01 | AW26: =-SUM('B5'!AI25) -> -119 | AX26: =-SUM(AW26-AS26) -> -1107.7097 | AY26: =SUM(AX26+AW26) -> -1226.7097 | AZ26: =ELEC!A24 -> 0 | BA26: ='General information '!D25 -> 26 | BB26: =SUM('General information '!E25) -> 0.51 | BC26: =IF(AR25>=AR26,0,1) -> 0 | BD26: 19222 | BE26: =(305/1185)*ELEC!Q25 -> 715.52743 | BG26: =#REF!-BE26 -> #REF! | BI26: 13 | BJ26: =AX26/BI26 -> -85.208437
A27: =ELEC!C25 -> 44826 | B27: ='B5'!B26 -> 246 | C27: =B27*$B$4 -> 5292.9677 | D27: =SUM(B27) -> 246 | E27: =D27*$B$4 -> 5292.9677 | F27: =SUM(D27) -> 246 | G27: =F27*$B$4 -> 5292.9677 | H27: =SUM(F27) -> 246 | I27: =H27*$B$4 -> 5292.9677 | J27: =SUM(H27) -> 246 | K27: =J27*$B$4 -> 5292.9677 | L27: =SUM(J27) -> 246 | M27: =L27*$B$4 -> 5292.9677 | N27: =SUM(L27) -> 246 | O27: =N27*$B$4 -> 5292.9677 | P27: =SUM(N27) -> 246 | Q27: =P27*$B$4 -> 5292.9677 | R27: =SUM(P27) -> 246 | S27: =R27*$B$4 -> 5292.9677 | T27: =SUM(R27) -> 246 | U27: =T27*$B$4 -> 5292.9677 | V27: =SUM(T27) -> 246 | W27: =V27*$B$4 -> 5292.9677 | X27: =SUM(Y27/73370) -> 0.79354839 | Y27: =SUM(C27+E27+G27+I27+K27+M27+O27+Q27+S27+U27+W27) -> 58222.645 | Z27: ='B5'!C26 -> 251 | AA27: =SUM(Z27*$Z$4) -> 2510 | AB27: =SUM(Z27) -> 251 | AC27: =SUM(AB27*$Z$4) -> 2510 | AD27: =SUM(AB27) -> 251 | AE27: =SUM(AD27*$Z$4) -> 2510 | AF27: =SUM(AD27) -> 251 | AG27: =SUM(AF27*$Z$4) -> 2510 | AH27: =SUM(AF27) -> 251 | AI27: =SUM(AH27*$Z$4) -> 2510 | AJ27: =SUM(AH27) -> 251 | AK27: =SUM(AJ27*$Z$4) -> 2510 | AL27: =SUM(AJ27) -> 251 | AM27: =SUM(AL27*$Z$4) -> 2510 | AN27: =SUM(AO27/19600) -> 0.89642857 | AO27: =SUM(AA27+AC27+AE27+AG27+AI27+AK27+AM27) -> 17570 | AQ27: =SUM(AR27/92970) -> 0.81523766 | AR27: =Y27+AO27 -> 75792.645 | AS27: =SUM(AR27-AR26-AT27) -> 630.87097 | AT27: 5126 | AU27: 1.03 | AV27: 0 | AW27: =-SUM('B5'!AI26) -> -101 | AX27: =-SUM(AW27-AS27) -> 731.87097 | AY27: =SUM(AX27+AW27) -> 630.87097 | AZ27: =ELEC!A25 -> 0 | BA27: ='General information '!D26 -> 26 | BB27: =SUM('General information '!E26) -> 0.52 | BC27: =IF(AR26>=AR27,0,1) -> 1 | BD27: 19222 | BE27: =(305/1185)*ELEC!Q26 -> 0 | BG27: =#REF!-BE27 -> #REF! | BI27: 14 | BJ27: =AX27/BI27 -> 52.276498 | BK27: =GEN!AF24 -> 0.17375
A28: =ELEC!C26 -> 44827 | B28: ='B5'!B27 -> 246 | C28: =B28*$B$4 -> 5292.9677 | D28: =SUM(B28) -> 246 | E28: =D28*$B$4 -> 5292.9677 | F28: =SUM(D28) -> 246 | G28: =F28*$B$4 -> 5292.9677 | H28: =SUM(F28) -> 246 | I28: =H28*$B$4 -> 5292.9677 | J28: =SUM(H28) -> 246 | K28: =J28*$B$4 -> 5292.9677 | L28: =SUM(J28) -> 246 | M28: =L28*$B$4 -> 5292.9677 | N28: =SUM(L28) -> 246 | O28: =N28*$B$4 -> 5292.9677 | P28: =SUM(N28) -> 246 | Q28: =P28*$B$4 -> 5292.9677 | R28: =SUM(P28) -> 246 | S28: =R28*$B$4 -> 5292.9677 | T28: =SUM(R28) -> 246 | U28: =T28*$B$4 -> 5292.9677 | V28: =SUM(T28) -> 246 | W28: =V28*$B$4 -> 5292.9677 | X28: =SUM(Y28/73370) -> 0.79354839 | Y28: =SUM(C28+E28+G28+I28+K28+M28+O28+Q28+S28+U28+W28) -> 58222.645 | Z28: ='B5'!C27 -> 251 | AA28: =SUM(Z28*$Z$4) -> 2510 | AB28: =SUM(Z28) -> 251 | AC28: =SUM(AB28*$Z$4) -> 2510 | AD28: =SUM(AB28) -> 251 | AE28: =SUM(AD28*$Z$4) -> 2510 | AF28: =SUM(AD28) -> 251 | AG28: =SUM(AF28*$Z$4) -> 2510 | AH28: =SUM(AF28) -> 251 | AI28: =SUM(AH28*$Z$4) -> 2510 | AJ28: =SUM(AH28) -> 251 | AK28: =SUM(AJ28*$Z$4) -> 2510 | AL28: =SUM(AJ28) -> 251 | AM28: =SUM(AL28*$Z$4) -> 2510 | AN28: =SUM(AO28/19600) -> 0.89642857 | AO28: =SUM(AA28+AC28+AE28+AG28+AI28+AK28+AM28) -> 17570 | AQ28: =SUM(AR28/92970) -> 0.81523766 | AR28: =Y28+AO28 -> 75792.645 | AS28: =SUM(AR28-AR27-AT28) -> 0 | AV28: =IF(AT28>0,AU28,AV27) -> 0 | AW28: =-SUM('B5'!AI27) -> 0 | AX28: =-SUM(AW28-AS28) -> 0 | AY28: =SUM(AX28+AW28) -> 0 | AZ28: =ELEC!A26 -> 0 | BA28: ='General information '!D27 -> 0 | BB28: =SUM('General information '!E27) -> 0 | BC28: =IF(AR27>=AR28,0,1) -> 0 | BD28: 19222 | BE28: =(305/1185)*ELEC!Q27 -> 0 | BG28: =#REF!-BE28 -> #REF! | BI28: 15 | BJ28: =AX28/BI28 -> 0 | BK28: =GEN!AF25 -> #DIV/0!
A29: =ELEC!C27 -> 44828 | B29: ='B5'!B28 -> 246 | C29: =B29*$B$4 -> 5292.9677 | D29: =SUM(B29) -> 246 | E29: =D29*$B$4 -> 5292.9677 | F29: =SUM(D29) -> 246 | G29: =F29*$B$4 -> 5292.9677 | H29: =SUM(F29) -> 246 | I29: =H29*$B$4 -> 5292.9677 | J29: =SUM(H29) -> 246 | K29: =J29*$B$4 -> 5292.9677 | L29: =SUM(J29) -> 246 | M29: =L29*$B$4 -> 5292.9677 | N29: =SUM(L29) -> 246 | O29: =N29*$B$4 -> 5292.9677 | P29: =SUM(N29) -> 246 | Q29: =P29*$B$4 -> 5292.9677 | R29: =SUM(P29) -> 246 | S29: =R29*$B$4 -> 5292.9677 | T29: =SUM(R29) -> 246 | U29: =T29*$B$4 -> 5292.9677 | V29: =SUM(T29) -> 246 | W29: =V29*$B$4 -> 5292.9677 | X29: =SUM(Y29/73370) -> 0.79354839 | Y29: =SUM(C29+E29+G29+I29+K29+M29+O29+Q29+S29+U29+W29) -> 58222.645 | Z29: ='B5'!C28 -> 251 | AA29: =SUM(Z29*$Z$4) -> 2510 | AB29: =SUM(Z29) -> 251 | AC29: =SUM(AB29*$Z$4) -> 2510 | AD29: =SUM(AB29) -> 251 | AE29: =SUM(AD29*$Z$4) -> 2510 | AF29: =SUM(AD29) -> 251 | AG29: =SUM(AF29*$Z$4) -> 2510 | AH29: =SUM(AF29) -> 251 | AI29: =SUM(AH29*$Z$4) -> 2510 | AJ29: =SUM(AH29) -> 251 | AK29: =SUM(AJ29*$Z$4) -> 2510 | AL29: =SUM(AJ29) -> 251 | AM29: =SUM(AL29*$Z$4) -> 2510 | AN29: =SUM(AO29/19600) -> 0.89642857 | AO29: =SUM(AA29+AC29+AE29+AG29+AI29+AK29+AM29) -> 17570 | AQ29: =SUM(AR29/92970) -> 0.81523766 | AR29: =Y29+AO29 -> 75792.645 | AS29: =SUM(AR29-AR28-AT29) -> 0 | AV29: =IF(AT29>0,AU29,AV28) -> 0 | AW29: =-SUM('B5'!AI28) -> 0 | AX29: =-SUM(AW29-AS29) -> 0 | AY29: =SUM(AX29+AW29) -> 0 | AZ29: =ELEC!A27 -> 0 | BA29: ='General information '!D28 -> 0 | BB29: =SUM('General information '!E28) -> 0 | BC29: =IF(AR28>=AR29,0,1) -> 0 | BD29: 19222 | BE29: =(305/1185)*ELEC!Q28 -> 716.81435 | BG29: =#REF!-BE29 -> #REF! | BI29: 16 | BJ29: =AX29/BI29 -> 0 | BK29: =GEN!AF26 -> #DIV/0!
A30: =ELEC!C28 -> 44829 | B30: ='B5'!B29 -> 240 | C30: =B30*$B$4 -> 5163.871 | D30: =SUM(B30) -> 240 | E30: =D30*$B$4 -> 5163.871 | F30: =SUM(D30) -> 240 | G30: =F30*$B$4 -> 5163.871 | H30: =SUM(F30) -> 240 | I30: =H30*$B$4 -> 5163.871 | J30: =SUM(H30) -> 240 | K30: =J30*$B$4 -> 5163.871 | L30: =SUM(J30) -> 240 | M30: =L30*$B$4 -> 5163.871 | N30: =SUM(L30) -> 240 | O30: =N30*$B$4 -> 5163.871 | P30: =SUM(N30) -> 240 | Q30: =P30*$B$4 -> 5163.871 | R30: =SUM(P30) -> 240 | S30: =R30*$B$4 -> 5163.871 | T30: =SUM(R30) -> 240 | U30: =T30*$B$4 -> 5163.871 | V30: =SUM(T30) -> 240 | W30: =V30*$B$4 -> 5163.871 | X30: =SUM(Y30/73370) -> 0.77419355 | Y30: =SUM(C30+E30+G30+I30+K30+M30+O30+Q30+S30+U30+W30) -> 56802.581 | Z30: ='B5'!C29 -> 247 | AA30: =SUM(Z30*$Z$4) -> 2470 | AB30: =SUM(Z30) -> 247 | AC30: =SUM(AB30*$Z$4) -> 2470 | AD30: =SUM(AB30) -> 247 | AE30: =SUM(AD30*$Z$4) -> 2470 | AF30: =SUM(AD30) -> 247 | AG30: =SUM(AF30*$Z$4) -> 2470 | AH30: =SUM(AF30) -> 247 | AI30: =SUM(AH30*$Z$4) -> 2470 | AJ30: =SUM(AH30) -> 247 | AK30: =SUM(AJ30*$Z$4) -> 2470 | AL30: =SUM(AJ30) -> 247 | AM30: =SUM(AL30*$Z$4) -> 2470 | AN30: =SUM(AO30/19600) -> 0.88214286 | AO30: =SUM(AA30+AC30+AE30+AG30+AI30+AK30+AM30) -> 17290 | AQ30: =SUM(AR30/92970) -> 0.7969515 | AR30: =Y30+AO30 -> 74092.581 | AS30: =SUM(AR30-AR29-AT30) -> -1700.0645 | AV30: =IF(AT30>0,AU30,AV29) -> 0 | AW30: =-SUM('B5'!AI29) -> -197 | AX30: =-SUM(AW30-AS30) -> -1503.0645 | AY30: =SUM(AX30+AW30) -> -1700.0645 | AZ30: =ELEC!A28 -> 0 | BA30: ='General information '!D29 -> 27.5 | BB30: =SUM('General information '!E29) -> 0.49 | BC30: =IF(AR29>=AR30,0,1) -> 0 | BD30: 19222 | BE30: =(305/1185)*ELEC!Q29 -> 793.25738 | BG30: =#REF!-BE30 -> #REF! | BI30: 17 | BJ30: =AX30/BI30 -> -88.41556 | BK30: =GEN!AF27 -> 0.15823864
A31: =ELEC!C29 -> 44830 | B31: ='B5'!B30 -> 236 | C31: =B31*$B$4 -> 5077.8065 | D31: =SUM(B31) -> 236 | E31: =D31*$B$4 -> 5077.8065 | F31: =SUM(D31) -> 236 | G31: =F31*$B$4 -> 5077.8065 | H31: =SUM(F31) -> 236 | I31: =H31*$B$4 -> 5077.8065 | J31: =SUM(H31) -> 236 | K31: =J31*$B$4 -> 5077.8065 | L31: =SUM(J31) -> 236 | M31: =L31*$B$4 -> 5077.8065 | N31: =SUM(L31) -> 236 | O31: =N31*$B$4 -> 5077.8065 | P31: =SUM(N31) -> 236 | Q31: =P31*$B$4 -> 5077.8065 | R31: =SUM(P31) -> 236 | S31: =R31*$B$4 -> 5077.8065 | T31: =SUM(R31) -> 236 | U31: =T31*$B$4 -> 5077.8065 | V31: =SUM(T31) -> 236 | W31: =V31*$B$4 -> 5077.8065 | X31: =SUM(Y31/73370) -> 0.76129032 | Y31: =SUM(C31+E31+G31+I31+K31+M31+O31+Q31+S31+U31+W31) -> 55855.871 | Z31: ='B5'!C30 -> 243 | AA31: =SUM(Z31*$Z$4) -> 2430 | AB31: =SUM(Z31) -> 243 | AC31: =SUM(AB31*$Z$4) -> 2430 | AD31: =SUM(AB31) -> 243 | AE31: =SUM(AD31*$Z$4) -> 2430 | AF31: =SUM(AD31) -> 243 | AG31: =SUM(AF31*$Z$4) -> 2430 | AH31: =SUM(AF31) -> 243 | AI31: =SUM(AH31*$Z$4) -> 2430 | AJ31: =SUM(AH31) -> 243 | AK31: =SUM(AJ31*$Z$4) -> 2430 | AL31: =SUM(AJ31) -> 243 | AM31: =SUM(AL31*$Z$4) -> 2430 | AN31: =SUM(AO31/19600) -> 0.86785714 | AO31: =SUM(AA31+AC31+AE31+AG31+AI31+AK31+AM31) -> 17010 | AQ31: =SUM(AR31/92970) -> 0.78375681 | AR31: =Y31+AO31 -> 72865.871 | AS31: =SUM(AR31-AR30-AT31) -> -1226.7097 | AV31: =IF(AT31>0,AU31,AV30) -> 0 | AW31: =-SUM('B5'!AI30) -> -59 | AX31: =-SUM(AW31-AS31) -> -1167.7097 | AY31: =SUM(AX31+AW31) -> -1226.7097 | AZ31: =ELEC!A29 -> 0 | BA31: ='General information '!D30 -> 26.5 | BB31: =SUM('General information '!E30) -> 0.48 | BC31: =IF(AR30>=AR31,0,1) -> 0 | BD31: 19222 | BE31: =(305/1185)*ELEC!Q30 -> 946.14346 | BG31: =#REF!-BE31 -> #REF! | BI31: 18 | BJ31: =AX31/BI31 -> -64.87276 | BK31: =GEN!AF28 -> 0.192625
A32: =ELEC!C30 -> 44831 | B32: ='B5'!B31 -> 233 | C32: =B32*$B$4 -> 5013.2581 | D32: =SUM(B32) -> 233 | E32: =D32*$B$4 -> 5013.2581 | F32: =SUM(D32) -> 233 | G32: =F32*$B$4 -> 5013.2581 | H32: =SUM(F32) -> 233 | I32: =H32*$B$4 -> 5013.2581 | J32: =SUM(H32) -> 233 | K32: =J32*$B$4 -> 5013.2581 | L32: =SUM(J32) -> 233 | M32: =L32*$B$4 -> 5013.2581 | N32: =SUM(L32) -> 233 | O32: =N32*$B$4 -> 5013.2581 | P32: =SUM(N32) -> 233 | Q32: =P32*$B$4 -> 5013.2581 | R32: =SUM(P32) -> 233 | S32: =R32*$B$4 -> 5013.2581 | T32: =SUM(R32) -> 233 | U32: =T32*$B$4 -> 5013.2581 | V32: =SUM(T32) -> 233 | W32: =V32*$B$4 -> 5013.2581 | X32: =SUM(Y32/73370) -> 0.7516129 | Y32: =SUM(C32+E32+G32+I32+K32+M32+O32+Q32+S32+U32+W32) -> 55145.839 | Z32: ='B5'!C31 -> 239 | AA32: =SUM(Z32*$Z$4) -> 2390 | AB32: =SUM(Z32) -> 239 | AC32: =SUM(AB32*$Z$4) -> 2390 | AD32: =SUM(AB32) -> 239 | AE32: =SUM(AD32*$Z$4) -> 2390 | AF32: =SUM(AD32) -> 239 | AG32: =SUM(AF32*$Z$4) -> 2390 | AH32: =SUM(AF32) -> 239 | AI32: =SUM(AH32*$Z$4) -> 2390 | AJ32: =SUM(AH32) -> 239 | AK32: =SUM(AJ32*$Z$4) -> 2390 | AL32: =SUM(AJ32) -> 239 | AM32: =SUM(AL32*$Z$4) -> 2390 | AN32: =SUM(AO32/19600) -> 0.85357143 | AO32: =SUM(AA32+AC32+AE32+AG32+AI32+AK32+AM32) -> 16730 | AQ32: =SUM(AR32/92970) -> 0.77310787 | AR32: =Y32+AO32 -> 71875.839 | AS32: =SUM(AR32-AR31-AT32) -> -990.03226 | AV32: =IF(AT32>0,AU32,AV31) -> 0 | AW32: =-SUM('B5'!AI31) -> -109 | AX32: =-SUM(AW32-AS32) -> -881.03226 | AY32: =SUM(AX32+AW32) -> -990.03226 | AZ32: =ELEC!A30 -> 0 | BA32: ='General information '!D31 -> 26 | BB32: =SUM('General information '!E31) -> 0.55 | BC32: =IF(AR31>=AR32,0,1) -> 0 | BD32: 19222 | BE32: =(305/1185)*ELEC!Q31 -> 587.35021 | BG32: =#REF!-BE32 -> #REF! | BI32: 19 | BJ32: =AX32/BI32 -> -46.370119 | BK32: =GEN!AF29 -> 0.19145833
A33: =ELEC!C31 -> 44832 | B33: ='B5'!B32 -> 229 | C33: =B33*$B$4 -> 4927.1935 | D33: =SUM(B33) -> 229 | E33: =D33*$B$4 -> 4927.1935 | F33: =SUM(D33) -> 229 | G33: =F33*$B$4 -> 4927.1935 | H33: =SUM(F33) -> 229 | I33: =H33*$B$4 -> 4927.1935 | J33: =SUM(H33) -> 229 | K33: =J33*$B$4 -> 4927.1935 | L33: =SUM(J33) -> 229 | M33: =L33*$B$4 -> 4927.1935 | N33: =SUM(L33) -> 229 | O33: =N33*$B$4 -> 4927.1935 | P33: =SUM(N33) -> 229 | Q33: =P33*$B$4 -> 4927.1935 | R33: =SUM(P33) -> 229 | S33: =R33*$B$4 -> 4927.1935 | T33: =SUM(R33) -> 229 | U33: =T33*$B$4 -> 4927.1935 | V33: =SUM(T33) -> 229 | W33: =V33*$B$4 -> 4927.1935 | X33: =SUM(Y33/73370) -> 0.73870968 | Y33: =SUM(C33+E33+G33+I33+K33+M33+O33+Q33+S33+U33+W33) -> 54199.129 | Z33: ='B5'!C32 -> 235 | AA33: =SUM(Z33*$Z$4) -> 2350 | AB33: =SUM(Z33) -> 235 | AC33: =SUM(AB33*$Z$4) -> 2350 | AD33: =SUM(AB33) -> 235 | AE33: =SUM(AD33*$Z$4) -> 2350 | AF33: =SUM(AD33) -> 235 | AG33: =SUM(AF33*$Z$4) -> 2350 | AH33: =SUM(AF33) -> 235 | AI33: =SUM(AH33*$Z$4) -> 2350 | AJ33: =SUM(AH33) -> 235 | AK33: =SUM(AJ33*$Z$4) -> 2350 | AL33: =SUM(AJ33) -> 235 | AM33: =SUM(AL33*$Z$4) -> 2350 | AN33: =SUM(AO33/19600) -> 0.83928571 | AO33: =SUM(AA33+AC33+AE33+AG33+AI33+AK33+AM33) -> 16450 | AQ33: =SUM(AR33/92970) -> 0.75991319 | AR33: =Y33+AO33 -> 70649.129 | AS33: =SUM(AR33-AR32-AT33) -> -1226.7097 | AV33: =IF(AT33>0,AU33,AV32) -> 0 | AW33: =-SUM('B5'!AI32) -> -41 | AX33: =-SUM(AW33-AS33) -> -1185.7097 | AY33: =SUM(AX33+AW33) -> -1226.7097 | AZ33: =ELEC!A31 -> 0 | BA33: ='General information '!D32 -> 26 | BB33: =SUM('General information '!E32) -> 0.52 | BC33: =IF(AR32>=AR33,0,1) -> 0 | BD33: 19222 | BE33: =(305/1185)*ELEC!#REF! -> #REF! | BG33: =#REF!-BE33 -> #REF! | BI33: 20 | BJ33: =AX33/BI33 -> -59.285484 | BK33: =GEN!AF30 -> 0.15847222
A34: =ELEC!C32 -> 44833 | B34: ='B5'!B33 -> 226 | C34: =B34*$B$4 -> 4862.6452 | D34: =SUM(B34) -> 226 | E34: =D34*$B$4 -> 4862.6452 | F34: =SUM(D34) -> 226 | G34: =F34*$B$4 -> 4862.6452 | H34: =SUM(F34) -> 226 | I34: =H34*$B$4 -> 4862.6452 | J34: =SUM(H34) -> 226 | K34: =J34*$B$4 -> 4862.6452 | L34: =SUM(J34) -> 226 | M34: =L34*$B$4 -> 4862.6452 | N34: =SUM(L34) -> 226 | O34: =N34*$B$4 -> 4862.6452 | P34: =SUM(N34) -> 226 | Q34: =P34*$B$4 -> 4862.6452 | R34: =SUM(P34) -> 226 | S34: =R34*$B$4 -> 4862.6452 | T34: =SUM(R34) -> 226 | U34: =T34*$B$4 -> 4862.6452 | V34: =SUM(T34) -> 226 | W34: =V34*$B$4 -> 4862.6452 | X34: =SUM(Y34/73370) -> 0.72903226 | Y34: =SUM(C34+E34+G34+I34+K34+M34+O34+Q34+S34+U34+W34) -> 53489.097 | Z34: ='B5'!C33 -> 232 | AA34: =SUM(Z34*$Z$4) -> 2320 | AB34: =SUM(Z34) -> 232 | AC34: =SUM(AB34*$Z$4) -> 2320 | AD34: =SUM(AB34) -> 232 | AE34: =SUM(AD34*$Z$4) -> 2320 | AF34: =SUM(AD34) -> 232 | AG34: =SUM(AF34*$Z$4) -> 2320 | AH34: =SUM(AF34) -> 232 | AI34: =SUM(AH34*$Z$4) -> 2320 | AJ34: =SUM(AH34) -> 232 | AK34: =SUM(AJ34*$Z$4) -> 2320 | AL34: =SUM(AJ34) -> 232 | AM34: =SUM(AL34*$Z$4) -> 2320 | AN34: =SUM(AO34/19600) -> 0.82857143 | AO34: =SUM(AA34+AC34+AE34+AG34+AI34+AK34+AM34) -> 16240 | AQ34: =SUM(AR34/92970) -> 0.75001718 | AR34: =Y34+AO34 -> 69729.097 | AS34: =SUM(AR34-AR33-AT34) -> -920.03226 | AV34: =IF(AT34>0,AU34,AV33) -> 0 | AW34: =-SUM('B5'!AI33) -> -27 | AX34: =-SUM(AW34-AS34) -> -893.03226 | AY34: =SUM(AX34+AW34) -> -920.03226 | AZ34: =ELEC!A32 -> 0 | BA34: ='General information '!D33 -> 26.5 | BB34: =SUM('General information '!E33) -> 0.7 | BC34: =IF(AR33>=AR34,0,1) -> 0 | BD34: 19223 | BE34: =(305/1185)*ELEC!#REF! -> #REF! | BG34: =#REF!-BE34 -> #REF! | BI34: 21 | BJ34: =AX34/BI34 -> -42.525346 | BK34: =GEN!AF31 -> 0.14616667
A35: =ELEC!C33 -> 44834 | B35: ='B5'!B34 -> 226 | C35: =B35*$B$4 -> 4862.6452 | D35: =SUM(B35) -> 226 | E35: =D35*$B$4 -> 4862.6452 | F35: =SUM(D35) -> 226 | G35: =F35*$B$4 -> 4862.6452 | H35: =SUM(F35) -> 226 | I35: =H35*$B$4 -> 4862.6452 | J35: =SUM(H35) -> 226 | K35: =J35*$B$4 -> 4862.6452 | L35: =SUM(J35) -> 226 | M35: =L35*$B$4 -> 4862.6452 | N35: =SUM(L35) -> 226 | O35: =N35*$B$4 -> 4862.6452 | P35: =SUM(N35) -> 226 | Q35: =P35*$B$4 -> 4862.6452 | R35: =SUM(P35) -> 226 | S35: =R35*$B$4 -> 4862.6452 | T35: =SUM(R35) -> 226 | U35: =T35*$B$4 -> 4862.6452 | V35: =SUM(T35) -> 226 | W35: =V35*$B$4 -> 4862.6452 | X35: =SUM(Y35/73370) -> 0.72903226 | Y35: =SUM(C35+E35+G35+I35+K35+M35+O35+Q35+S35+U35+W35) -> 53489.097 | Z35: ='B5'!C34 -> 232 | AA35: =SUM(Z35*$Z$4) -> 2320 | AB35: =SUM(Z35) -> 232 | AC35: =SUM(AB35*$Z$4) -> 2320 | AD35: =SUM(AB35) -> 232 | AE35: =SUM(AD35*$Z$4) -> 2320 | AF35: =SUM(AD35) -> 232 | AG35: =SUM(AF35*$Z$4) -> 2320 | AH35: =SUM(AF35) -> 232 | AI35: =SUM(AH35*$Z$4) -> 2320 | AJ35: =SUM(AH35) -> 232 | AK35: =SUM(AJ35*$Z$4) -> 2320 | AL35: =SUM(AJ35) -> 232 | AM35: =SUM(AL35*$Z$4) -> 2320 | AN35: =SUM(AO35/19600) -> 0.82857143 | AO35: =SUM(AA35+AC35+AE35+AG35+AI35+AK35+AM35) -> 16240 | AQ35: =SUM(AR35/92970) -> 0.75001718 | AR35: =Y35+AO35 -> 69729.097 | AS35: =SUM(AR35-AR34-AT35) -> 0 | AV35: =IF(AT35>0,AU35,AV34) -> 0 | AW35: =-SUM('B5'!AI34) -> 0 | AX35: =-SUM(AW35-AS35) -> 0 | AY35: =SUM(AX35+AW35) -> 0 | AZ35: =ELEC!A33 -> 0 | BA35: ='General information '!D34 -> 0 | BB35: =SUM('General information '!E34) -> 0 | BC35: =IF(AR34>=AR35,0,1) -> 0 | BD35: 19224 | BE35: =(305/1185)*ELEC!#REF! -> #REF! | BG35: =#REF!-BE35 -> #REF! | BI35: 22 | BJ35: =AX35/BI35 -> 0 | BK35: =GEN!AF32 -> #DIV/0!
