Workbook

Sheet Total
A1: Site Name | B1: Day | C1: Month | D1: Year | E1: Total Electricity Kwh | F1: Electricity Tariff ($/Kwh) | G1: Natual Gas (m3) | H1: Natural Gas $/m3 | I1: Water Utility Supply (m3) m3 | J1: Water Utility Supply (m3) $/m3 | K1: Room Nights
A2: Cairo at The First Residence | B2: 1 | C2: 8 | D2: 2022 | E2: =Elect!BS6+Submetering!AH2 -> 37716.658 | F2: ='Utility Consnsumption'!K13/'Utility Consnsumption'!J13 -> 1.3444936 | G2: =Gas!K7+Submetering!AR2 -> 1701.02 | H2: 3.8 | I2: =Water!H7+Submetering!AM2 -> 425.46 | J2: 10 | K2: =Elect!BT6 -> 227
A3: Cairo at The First Residence | B3: =B2+1 -> 2 | C3: 8 | D3: 2022 | E3: =Elect!BS7+Submetering!AH3 -> 32447.179 | F3: =F2 -> 1.3444936 | G3: =Gas!K8+Submetering!AR3 -> 1708.84 | H3: 3.8 | I3: =Water!H8+Submetering!AM3 -> 456.9 | J3: 10 | K3: =Elect!BT7 -> 243
A4: Cairo at The First Residence | B4: =B3+1 -> 3 | C4: 8 | D4: 2022 | E4: =Elect!BS8+Submetering!AH4 -> 43550.145 | F4: =F3 -> 1.3444936 | G4: =Gas!K9+Submetering!AR4 -> 1779.26 | H4: 3.8 | I4: =Water!H9+Submetering!AM4 -> 439.18 | J4: 10 | K4: =Elect!BT8 -> 220
A5: Cairo at The First Residence | B5: =B4+1 -> 4 | C5: 8 | D5: 2022 | E5: =Elect!BS9+Submetering!AH5 -> 34563.173 | F5: =F4 -> 1.3444936 | G5: =Gas!K10+Submetering!AR5 -> 1556.96 | H5: 3.8 | I5: =Water!H10+Submetering!AM5 -> 468.4 | J5: 10 | K5: =Elect!BT9 -> 203
A6: Cairo at The First Residence | B6: =B5+1 -> 5 | C6: 8 | D6: 2022 | E6: =Elect!BS10+Submetering!AH6 -> 41780.65 | F6: =F5 -> 1.3444936 | G6: =Gas!K11+Submetering!AR6 -> 1726.72 | H6: 3.8 | I6: =Water!H11+Submetering!AM6 -> 459.16 | J6: 10 | K6: =Elect!BT10 -> 187
A7: Cairo at The First Residence | B7: =B6+1 -> 6 | C7: 8 | D7: 2022 | E7: =Elect!BS11+Submetering!AH7 -> 37544.313 | F7: =F6 -> 1.3444936 | G7: =Gas!K12+Submetering!AR7 -> 1690.68 | H7: 3.8 | I7: =Water!H12+Submetering!AM7 -> 442.24 | J7: 10 | K7: =Elect!BT11 -> 203
A8: Cairo at The First Residence | B8: =B7+1 -> 7 | C8: 8 | D8: 2022 | E8: =Elect!BS12+Submetering!AH8 -> 33954.184 | F8: =F7 -> 1.3444936 | G8: =Gas!K13+Submetering!AR8 -> 1786.74 | H8: 3.8 | I8: =Water!H13+Submetering!AM8 -> 452.1 | J8: 10 | K8: =Elect!BT12 -> 234
A9: Cairo at The First Residence | B9: =B8+1 -> 8 | C9: 8 | D9: 2022 | E9: =Elect!BS13+Submetering!AH9 -> 34826.414 | F9: =F8 -> 1.3444936 | G9: =Gas!K14+Submetering!AR9 -> 1814.12 | H9: 3.8 | I9: =Water!H14+Submetering!AM9 -> 465.8 | J9: 10 | K9: =Elect!BT13 -> 248
A10: Cairo at The First Residence | B10: =B9+1 -> 9 | C10: 8 | D10: 2022 | E10: =Elect!BS14+Submetering!AH10 -> 30403.21 | F10: =F9 -> 1.3444936 | G10: =Gas!K15+Submetering!AR10 -> 1780.4067 | H10: 3.8 | I10: =Water!H15+Submetering!AM10 -> 431.32 | J10: 10 | K10: =Elect!BT14 -> 252
A11: Cairo at The First Residence | B11: =B10+1 -> 10 | C11: 8 | D11: 2022 | E11: =Elect!BS15+Submetering!AH11 -> 33600.61 | F11: =F10 -> 1.3444936 | G11: =Gas!K16+Submetering!AR11 -> 1832.6533 | H11: 3.8 | I11: =Water!H16+Submetering!AM11 -> 437.5 | J11: 10 | K11: =Elect!BT15 -> 246
A12: Cairo at The First Residence | B12: =B11+1 -> 11 | C12: 8 | D12: 2022 | E12: =Elect!BS16+Submetering!AH12 -> 37892.73 | F12: =F11 -> 1.3444936 | G12: =Gas!K17+Submetering!AR12 -> 1791.8222 | H12: 3.8 | I12: =Water!H17+Submetering!AM12 -> 432.38 | J12: 10 | K12: =Elect!BT16 -> 206
A13: Cairo at The First Residence | B13: =B12+1 -> 12 | C13: 8 | D13: 2022 | E13: =Elect!BS17+Submetering!AH13 -> 38359.069 | F13: =F12 -> 1.3444936 | G13: =Gas!K18+Submetering!AR13 -> 1799.2578 | H13: 3.8 | I13: =Water!H18+Submetering!AM13 -> 437.8 | J13: 10 | K13: =Elect!BT17 -> 174
A14: Cairo at The First Residence | B14: =B13+1 -> 13 | C14: 8 | D14: 2022 | E14: =Elect!BS18+Submetering!AH14 -> 32800.977 | F14: =F13 -> 1.3444936 | G14: =Gas!K19+Submetering!AR14 -> 1800.74 | H14: 3.8 | I14: =Water!H19+Submetering!AM14 -> 412.96 | J14: 10 | K14: =Elect!BT18 -> 162
... A32: Cairo at The First Residence | B32: =B31+1 -> 31 | C32: 8 | D32: 2022 | E32: =Elect!BS36+Submetering!AH32 -> 22919.465 | F32: =F31 -> 1.3444936 | G32: =Gas!K37+Submetering!AR32 -> 1663.8733 | H32: 3.8 | I32: =Water!H37+Submetering!AM32 -> 303.14667 | J32: 10 | K32: =Elect!BT36 -> 238

Sheet Submetering
A1: Site Name | B1: Day | C1: Month | D1: Year | E1: Electricity | F1: Main Feeder -KWh | G1: T2+T8 -KWh | H1: La Gourmandize -KWh | I1: Casino 3rd floor EM -KWh | J1: Casino 3rd floor Normal -KWh | K1: Chiller 1 -KWh | L1: Chiller 2 -KWh | M1: Chiller 3 -KWh | N1: Chiller 4 -KWh | O1: Chiller 5 -KWh | P1: Chiller 6 -KWh | Q1: Cooling towers -KWh | R1: Chiller Pumps -KWh | S1: Cooling Tower Pumps -KWh | T1: Fiber Chiller -KWh | U1: Mall Ceiling light -KWh | V1: LG Bakery -KWh | W1: LG Bakery light ( Old lockers ) -KWh | X1: MCCR1 -KWh | Y1: Children Swimming Pool -KWh | Z1: DPH1 -KWh | AA1: Guest Rooms Emerg. -KWh | AB1: Hotel Hoods -KWh | AC1: Main G2 -KWh | AD1: Old Casino Emergency -KWh | AE1: L / A -KWh | AF1: L / B -KWh | AG1: L / C -KWh | AH1: Boat -KWh | AI1: Water | AJ1: Main water meter 1 -m3 | AK1: Main water meter 2 -m3 | AL1: Main water meter 3 -m3 | AM1: Boat -m3 | AN1: Gas | AO1: Main Gas Flow Meter -m3 | AP1: Laundry Gas Flow Meter -m3 | AQ1: Gourmandize Gas Flow Meter -m3 | AR1: Boat -m3 | AS1: Room Nights
A2: Cairo at The First Residence | B2: 1 | C2: 8 | D2: 2022 | F2: =Elect!J6 -> 2039 | G2: =Elect!K6 -> 1738 | H2: =Elect!Q6 -> 810 | I2: =Elect!S6 -> 145 | J2: =Elect!U6 -> 258 | K2: =Elect!W6 -> 3414.26 | L2: =Elect!Y6 -> 4526.73 | M2: =Elect!AA6 -> 0 | N2: =Elect!AC6 -> 0 | O2: =Elect!AE6 -> 84.27 | P2: =Elect!AG6 -> 1672.68 | Q2: =Elect!AI6 -> 1172.36 | R2: =Elect!AK6 -> 3972.35 | S2: =Elect!AM6 -> 101.76 | T2: =Elect!AP6 -> 347.5125 | U2: =Elect!AR6 -> 193 | V2: =Elect!AT6 -> 304.68585 | W2: =Elect!AV6 -> 45 | X2: =Elect!AX6 -> 930 | Y2: =Elect!AZ6 -> 12 | Z2: =Elect!BB6 -> 4938 | AA2: =Elect!BD6 -> 284 | AB2: =Elect!BF6 -> 55 | AC2: =Elect!BH6 -> 6683.05 | AD2: =Elect!BL6 -> 265 | AE2: =Elect!BN6 -> 1564 | AF2: =Elect!BP6 -> 127 | AG2: =Elect!BR6 -> 171 | AH2: =Boat!C4 -> 6131 | AJ2: =Water!C7 -> 121.8 | AK2: =Water!E7 -> 150.8 | AL2: =Water!G7 -> 125.86 | AM2: =Boat!E4 -> 27 | AO2: =Gas!C7 -> 1258.22 | AP2: =Gas!E7 -> 317.8 | AQ2: =Gas!G7 -> 68 | AR2: =Boat!G4 -> 125 | AS2: =Elect!BT6 -> 227
A3: Cairo at The First Residence | B3: =B2+1 -> 2 | C3: 8 | D3: 2022 | F3: =Elect!J7 -> 0 | G3: =Elect!K7 -> 3340 | H3: =Elect!Q7 -> 570 | I3: =Elect!S7 -> 134 | J3: =Elect!U7 -> 257 | K3: =Elect!W7 -> 3476.8 | L3: =Elect!Y7 -> 3827.66 | M3: =Elect!AA7 -> 0 | N3: =Elect!AC7 -> 0 | O3: =Elect!AE7 -> 1726.74 | P3: =Elect!AG7 -> 10.6 | Q3: =Elect!AI7 -> 1035.62 | R3: =Elect!AK7 -> 3576.97 | S3: =Elect!AM7 -> 102.29 | T3: =Elect!AP7 -> 290.1375 | U3: =Elect!AR7 -> 154 | V3: =Elect!AT7 -> 179.76179 | W3: =Elect!AV7 -> 61 | X3: =Elect!AX7 -> 804 | Y3: =Elect!AZ7 -> 10 | Z3: =Elect!BB7 -> 5316 | AA3: =Elect!BD7 -> 252 | AB3: =Elect!BF7 -> 112 | AC3: =Elect!BH7 -> 6520.6 | AD3: =Elect!BL7 -> 293 | AE3: =Elect!BN7 -> 1399 | AF3: =Elect!BP7 -> 113 | AG3: =Elect!BR7 -> 150 | AH3: =Boat!C5 -> 4421 | AJ3: =Water!C8 -> 133.4 | AK3: =Water!E8 -> 174 | AL3: =Water!G8 -> 130.5 | AM3: =Boat!E5 -> 19 | AO3: =Gas!C8 -> 1361.04 | AP3: =Gas!E8 -> 254.8 | AQ3: =Gas!G8 -> 97 | AR3: =Boat!G5 -> 93 | AS3: =Elect!BT7 -> 243
A4: Cairo at The First Residence | B4: =B3+1 -> 3 | C4: 8 | D4: 2022 | F4: =Elect!J8 -> 5969.1111 | G4: =Elect!K8 -> 4452 | H4: =Elect!Q8 -> 750 | I4: =Elect!S8 -> 147 | J4: =Elect!U8 -> 268 | K4: =Elect!W8 -> 3896.03 | L4: =Elect!Y8 -> 4479.03 | M4: =Elect!AA8 -> 102.29 | N4: =Elect!AC8 -> 0 | O4: =Elect!AE8 -> 1694.41 | P4: =Elect!AG8 -> 11.13 | Q4: =Elect!AI8 -> 1181.37 | R4: =Elect!AK8 -> 4571.78 | S4: =Elect!AM8 -> 134.62 | T4: =Elect!AP8 -> 310.1625 | U4: =Elect!AR8 -> 153 | V4: =Elect!AT8 -> 179.76179 | W4: =Elect!AV8 -> 69 | X4: =Elect!AX8 -> 1062 | Y4: =Elect!AZ8 -> 12 | Z4: =Elect!BB8 -> 6552 | AA4: =Elect!BD8 -> 247 | AB4: =Elect!BF8 -> 55 | AC4: =Elect!BH8 -> 6852.45 | AD4: =Elect!BL8 -> 282 | AE4: =Elect!BN8 -> 1350 | AF4: =Elect!BP8 -> 109 | AG4: =Elect!BR8 -> 140 | AH4: =Boat!C6 -> 5268 | AJ4: =Water!C9 -> 127.6 | AK4: =Water!E9 -> 156.6 | AL4: =Water!G9 -> 133.98 | AM4: =Boat!E6 -> 21 | AO4: =Gas!C9 -> 1246.56 | AP4: =Gas!E9 -> 385.7 | AQ4: =Gas!G9 -> 96 | AR4: =Boat!G6 -> 147 | AS4: =Elect!BT8 -> 220
A5: Cairo at The First Residence | B5: =B4+1 -> 4 | C5: 8 | D5: 2022 | F5: =Elect!J9 -> 5969.1111 | G5: =Elect!K9 -> 3105 | H5: =Elect!Q9 -> 720 | I5: =Elect!S9 -> 139 | J5: =Elect!U9 -> 240 | K5: =Elect!W9 -> 2661.13 | L5: =Elect!Y9 -> 0 | M5: =Elect!AA9 -> 3184.24 | N5: =Elect!AC9 -> 0 | O5: =Elect!AE9 -> 1634.52 | P5: =Elect!AG9 -> 11.13 | Q5: =Elect!AI9 -> 969.9 | R5: =Elect!AK9 -> 3366.56 | S5: =Elect!AM9 -> 102.82 | T5: =Elect!AP9 -> 286.2 | U5: =Elect!AR9 -> 148 | V5: =Elect!AT9 -> 179.76179 | W5: =Elect!AV9 -> 57 | X5: =Elect!AX9 -> 775 | Y5: =Elect!AZ9 -> 11 | Z5: =Elect!BB9 -> 3775 | AA5: =Elect!BD9 -> 286 | AB5: =Elect!BF9 -> 35 | AC5: =Elect!BH9 -> 6274.8 | AD5: =Elect!BL9 -> 248 | AE5: =Elect!BN9 -> 1290 | AF5: =Elect!BP9 -> 106 | AG5: =Elect!BR9 -> 143 | AH5: =Boat!C7 -> 4116 | AJ5: =Water!C10 -> 139.2 | AK5: =Water!E10 -> 185.6 | AL5: =Water!G10 -> 127.6 | AM5: =Boat!E7 -> 16 | AO5: =Gas!C10 -> 1182.96 | AP5: =Gas!E10 -> 287 | AQ5: =Gas!G10 -> 79 | AR5: =Boat!G7 -> 87 | AS5: =Elect!BT9 -> 203
A6: Cairo at The First Residence | B6: =B5+1 -> 5 | C6: 8 | D6: 2022 | F6: =Elect!J10 -> 5969.1111 | G6: =Elect!K10 -> 3812 | H6: =Elect!Q10 -> 540 | I6: =Elect!S10 -> 149 | J6: =Elect!U10 -> 264 | K6: =Elect!W10 -> 3505.95 | L6: =Elect!Y10 -> 0 | M6: =Elect!AA10 -> 4058.21 | N6: =Elect!AC10 -> 0 | O6: =Elect!AE10 -> 1595.3 | P6: =Elect!AG10 -> 10.07 | Q6: =Elect!AI10 -> 1115.12 | R6: =Elect!AK10 -> 4081.53 | S6: =Elect!AM10 -> 120.31 | T6: =Elect!AP10 -> 276.6375 | U6: =Elect!AR10 -> 150 | V6: =Elect!AT10 -> 179.76179 | W6: =Elect!AV10 -> 65 | X6: =Elect!AX10 -> 963 | Y6: =Elect!AZ10 -> 12 | Z6: =Elect!BB10 -> 6654 | AA6: =Elect!BD10 -> 273 | AB6: =Elect!BF10 -> 55 | AC6: =Elect!BH10 -> 6417.65 | AD6: =Elect!BL10 -> 247 | AE6: =Elect!BN10 -> 1315 | AF6: =Elect!BP10 -> 108 | AG6: =Elect!BR10 -> 152 | AH6: =Boat!C8 -> 5739 | AJ6: =Water!C11 -> 127.6 | AK6: =Water!E11 -> 174 | AL6: =Water!G11 -> 134.56 | AM6: =Boat!E8 -> 23 | AO6: =Gas!C11 -> 1321.82 | AP6: =Gas!E11 -> 284.9 | AQ6: =Gas!G11 -> 90 | AR6: =Boat!G8 -> 120 | AS6: =Elect!BT10 -> 187
A7: Cairo at The First Residence | B7: =B6+1 -> 6 | C7: 8 | D7: 2022 | F7: =Elect!J11 -> 5969.1111 | G7: =Elect!K11 -> 3532 | H7: =Elect!Q11 -> 540 | I7: =Elect!S11 -> 136 | J7: =Elect!U11 -> 231 | K7: =Elect!W11 -> 2624.56 | L7: =Elect!Y11 -> 0 | M7: =Elect!AA11 -> 3516.02 | N7: =Elect!AC11 -> 0 | O7: =Elect!AE11 -> 1488.24 | P7: =Elect!AG11 -> 11.66 | Q7: =Elect!AI11 -> 915.84 | R7: =Elect!AK11 -> 3757.7 | S7: =Elect!AM11 -> 110.24 | T7: =Elect!AP11 -> 263.025 | U7: =Elect!AR11 -> 138 | V7: =Elect!AT11 -> 230.26701 | W7: =Elect!AV11 -> 49 | X7: =Elect!AX11 -> 909 | Y7: =Elect!AZ11 -> 10 | Z7: =Elect!BB11 -> 4910 | AA7: =Elect!BD11 -> 286 | AB7: =Elect!BF11 -> 50 | AC7: =Elect!BH11 -> 6297.65 | AD7: =Elect!BL11 -> 273 | AE7: =Elect!BN11 -> 1231 | AF7: =Elect!BP11 -> 112 | AG7: =Elect!BR11 -> 124 | AH7: =Boat!C9 -> 5468 | AJ7: =Water!C12 -> 127.6 | AK7: =Water!E12 -> 162.4 | AL7: =Water!G12 -> 132.24 | AM7: =Boat!E9 -> 20 | AO7: =Gas!C12 -> 1185.08 | AP7: =Gas!E12 -> 285.6 | AQ7: =Gas!G12 -> 80 | AR7: =Boat!G9 -> 220 | AS7: =Elect!BT11 -> 203
A8: Cairo at The First Residence | B8: =B7+1 -> 7 | C8: 8 | D8: 2022 | F8: =Elect!J12 -> 5969.1111 | G8: =Elect!K12 -> 2492 | H8: =Elect!Q12 -> 510 | I8: =Elect!S12 -> 150 | J8: =Elect!U12 -> 254 | K8: =Elect!W12 -> 1480.29 | L8: =Elect!Y12 -> 0 | M8: =Elect!AA12 -> 3054.92 | N8: =Elect!AC12 -> 0 | O8: =Elect!AE12 -> 1375.88 | P8: =Elect!AG12 -> 11.13 | Q8: =Elect!AI12 -> 669.92 | R8: =Elect!AK12 -> 2972.77 | S8: =Elect!AM12 -> 98.05 | T8: =Elect!AP12 -> 235.4625 | U8: =Elect!AR12 -> 175 | V8: =Elect!AT12 -> 170 | W8: =Elect!AV12 -> 33 | X8: =Elect!AX12 -> 790 | Y8: =Elect!AZ12 -> 12 | Z8: =Elect!BB12 -> 5256 | AA8: =Elect!BD12 -> 285 | AB8: =Elect!BF12 -> 45 | AC8: =Elect!BH12 -> 6744.65 | AD8: =Elect!BL12 -> 332 | AE8: =Elect!BN12 -> 1459 | AF8: =Elect!BP12 -> 124 | AG8: =Elect!BR12 -> 150 | AH8: =Boat!C10 -> 4066 | AJ8: =Water!C13 -> 127.6 | AK8: =Water!E13 -> 168.2 | AL8: =Water!G13 -> 136.3 | AM8: =Boat!E10 -> 20 | AO8: =Gas!C13 -> 1414.04 | AP8: =Gas!E13 -> 301.7 | AQ8: =Gas!G13 -> 90 | AR8: =Boat!G10 -> 71 | AS8: =Elect!BT12 -> 234
A9: Cairo at The First Residence | B9: =B8+1 -> 8 | C9: 8 | D9: 2022 | F9: =Elect!J13 -> 5969.1111 | G9: =Elect!K13 -> 4301 | H9: =Elect!Q13 -> 570 | I9: =Elect!S13 -> 156 | J9: =Elect!U13 -> 271 | K9: =Elect!W13 -> 0 | L9: =Elect!Y13 -> 0 | M9: =Elect!AA13 -> 4574.43 | N9: =Elect!AC13 -> 320.12 | O9: =Elect!AE13 -> 198.22 | P9: =Elect!AG13 -> 976.79 | Q9: =Elect!AI13 -> 621.16 | R9: =Elect!AK13 -> 3209.15 | S9: =Elect!AM13 -> 126.67 | T9: =Elect!AP13 -> 266.5125 | U9: =Elect!AR13 -> 176 | V9: =Elect!AT13 -> 163 | W9: =Elect!AV13 -> 45 | X9: =Elect!AX13 -> 927 | Y9: =Elect!AZ13 -> 12 | Z9: =Elect!BB13 -> 5256 | AA9: =Elect!BD13 -> 234 | AB9: =Elect!BF13 -> 50 | AC9: =Elect!BH13 -> 6065.25 | AD9: =Elect!BL13 -> 290 | AE9: =Elect!BN13 -> 1159 | AF9: =Elect!BP13 -> 116 | AG9: =Elect!BR13 -> 134 | AH9: =Boat!C11 -> 5066 | AJ9: =Water!C14 -> 139.2 | AK9: =Water!E14 -> 179.8 | AL9: =Water!G14 -> 121.8 | AM9: =Boat!E11 -> 25 | AO9: =Gas!C14 -> 1406.62 | AP9: =Gas!E14 -> 311.5 | AQ9: =Gas!G14 -> 85 | AR9: =Boat!G11 -> 96 | AS9: =Elect!BT13 -> 248
A10: Cairo at The First Residence | B10: =B9+1 -> 9 | C10: 8 | D10: 2022 | F10: =Elect!J14 -> 5969.1111 | G10: =Elect!K14 -> 2717 | H10: =Elect!Q14 -> 450 | I10: =Elect!S14 -> 112 | J10: =Elect!U14 -> 191 | K10: =Elect!W14 -> 1423.05 | L10: =Elect!Y14 -> 0 | M10: =Elect!AA14 -> 3030.01 | N10: =Elect!AC14 -> 0 | O10: =Elect!AE14 -> 9.54 | P10: =Elect!AG14 -> 820.44 | Q10: =Elect!AI14 -> 380.01 | R10: =Elect!AK14 -> 2541.35 | S10: =Elect!AM14 -> 94.87 | T10: =Elect!AP14 -> 226.4625 | U10: =Elect!AR14 -> 152 | V10: =Elect!AT14 -> 167.66667 | W10: =Elect!AV14 -> 30 | X10: =Elect!AX14 -> 681 | Y10: =Elect!AZ14 -> 8 | Z10: =Elect!BB14 -> 3823 | AA10: =Elect!BD14 -> 184 | AB10: =Elect!BF14 -> 201 | AC10: =Elect!BH14 -> 4679.7 | AD10: =Elect!BL14 -> 219 | AE10: =Elect!BN14 -> 1566 | AF10: =Elect!BP14 -> 88 | AG10: =Elect!BR14 -> 102 | AH10: =Boat!C12 -> 5532 | AJ10: =Water!C15 -> 121.8 | AK10: =Water!E15 -> 162.4 | AL10: =Water!G15 -> 124.12 | AM10: =Boat!E12 -> 23 | AO10: =Gas!C15 -> 1350.44 | AP10: =Gas!E15 -> 304.96667 | AQ10: =Gas!G15 -> 90 | AR10: =Boat!G12 -> 125 | AS10: =Elect!BT14 -> 252
A11: Cairo at The First Residence | B11: =B10+1 -> 10 | C11: 8 | D11: 2022 | F11: =Elect!J15 -> 5969.1111 | G11: =Elect!K15 -> 3773 | H11: =Elect!Q15 -> 530 | I11: =Elect!S15 -> 141.33333 | J11: =Elect!U15 -> 244.33333 | K11: =Elect!W15 -> 1984.85 | L11: =Elect!Y15 -> 0 | M11: =Elect!AA15 -> 4059.6233 | N11: =Elect!AC15 -> 0 | O11: =Elect!AE15 -> 29.326667 | P11: =Elect!AG15 -> 924.67333 | Q11: =Elect!AI15 -> 540.77667 | R11: =Elect!AK15 -> 2986.55 | S11: =Elect!AM15 -> 116.07 | T11: =Elect!AP15 -> 253.1625 | U11: =Elect!AR15 -> 168 | V11: =Elect!AT15 -> 166.5 | W11: =Elect!AV15 -> 40 | X11: =Elect!AX15 -> 845 | Y11: =Elect!AZ15 -> 10.666667 | Z11: =Elect!BB15 -> 4778.3333 | AA11: =Elect!BD15 -> 217.33333 | AB11: =Elect!BF15 -> 100.33333 | AC11: =Elect!BH15 -> 5481.3 | AD11: =Elect!BL15 -> 266.33333 | AE11: =Elect!BN15 -> 1566 | AF11: =Elect!BP15 -> 106.66667 | AG11: =Elect!BR15 -> 123.33333 | AH11: =Boat!C13 -> 4399 | AJ11: =Water!C16 -> 127.6 | AK11: =Water!E16 -> 162.4 | AL11: =Water!G16 -> 130.5 | AM11: =Boat!E13 -> 17 | AO11: =Gas!C16 -> 1427.82 | AP11: =Gas!E16 -> 306.83333 | AQ11: =Gas!G16 -> 92 | AR11: =Boat!G13 -> 98 | AS11: =Elect!BT15 -> 246
A12: Cairo at The First Residence | B12: =B11+1 -> 11 | C12: 8 | D12: 2022 | F12: =Elect!J16 -> 5969.1111 | G12: =Elect!K16 -> 3190 | H12: =Elect!Q16 -> 490 | I12: =Elect!S16 -> 139.66667 | J12: =Elect!U16 -> 274.66667 | K12: =Elect!W16 -> 3870.06 | L12: =Elect!Y16 -> 0 | M12: =Elect!AA16 -> 3559.6567 | N12: =Elect!AC16 -> 0 | O12: =Elect!AE16 -> 0 | P12: =Elect!AG16 -> 0 | Q12: =Elect!AI16 -> 467.81333 | R12: =Elect!AK16 -> 3479.45 | S12: =Elect!AM16 -> 104.41 | T12: =Elect!AP16 -> 270.4125 | U12: =Elect!AR16 -> 153 | V12: =Elect!AT16 -> 80.833333 | W12: =Elect!AV16 -> 69 | X12: =Elect!AX16 -> 832 | Y12: =Elect!AZ16 -> 11.333333 | Z12: =Elect!BB16 -> 5508.6667 | AA12: =Elect!BD16 -> 251.66667 | AB12: =Elect!BF16 -> 38.666667 | AC12: =Elect!BH16 -> 7703.65 | AD12: =Elect!BL16 -> 297.66667 | AE12: =Elect!BN16 -> 549 | AF12: =Elect!BP16 -> 147.33333 | AG12: =Elect!BR16 -> 135.66667 | AH12: =Boat!C14 -> 5033 | AJ12: =Water!C17 -> 123.73333 | AK12: =Water!E17 -> 162.4 | AL12: =Water!G17 -> 126.24667 | AM12: =Boat!E14 -> 20 | AO12: =Gas!C17 -> 1376.2333 | AP12: =Gas!E17 -> 305.58889 | AQ12: =Gas!G17 -> 90.666667 | AR12: =Boat!G14 -> 110 | AS12: =Elect!BT16 -> 206
A13: Cairo at The First Residence | B13: =B12+1 -> 12 | C13: 8 | D13: 2022 | F13: =Elect!J17 -> 5969.1111 | G13: =Elect!K17 -> 4248 | H13: =Elect!Q17 -> 510 | I13: =Elect!S17 -> 152 | J13: =Elect!U17 -> 283 | K13: =Elect!W17 -> 3870.06 | L13: =Elect!Y17 -> 0 | M13: =Elect!AA17 -> 3884.9 | N13: =Elect!AC17 -> 0 | O13: =Elect!AE17 -> 8.8333333 | P13: =Elect!AG17 -> 164.3 | Q13: =Elect!AI17 -> 566.57 | R13: =Elect!AK17 -> 3818.65 | S13: =Elect!AM17 -> 119.25 | T13: =Elect!AP17 -> 257.4 | U13: =Elect!AR17 -> 266 | V13: =Elect!AT17 -> 137.94444 | W13: =Elect!AV17 -> 55 | X13: =Elect!AX17 -> 884 | Y13: =Elect!AZ17 -> 12 | Z13: =Elect!BB17 -> 5828 | AA13: =Elect!BD17 -> 240 | AB13: =Elect!BF17 -> 70 | AC13: =Elect!BH17 -> 6664.05 | AD13: =Elect!BL17 -> 265 | AE13: =Elect!BN17 -> 1487 | AF13: =Elect!BP17 -> 84 | AG13: =Elect!BR17 -> 140 | AH13: =Boat!C15 -> 5033 | AJ13: =Water!C18 -> 125.66667 | AK13: =Water!E18 -> 156.6 | AL13: =Water!G18 -> 129.53333 | AM13: =Boat!E15 -> 26 | AO13: =Gas!C18 -> 1324.6467 | AP13: =Gas!E18 -> 293.61111 | AQ13: =Gas!G18 -> 82.333333 | AR13: =Boat!G15 -> 181 | AS13: =Elect!BT17 -> 174
A14: Cairo at The First Residence | B14: =B13+1 -> 13 | C14: 8 | D14: 2022 | F14: =Elect!J18 -> 5969.1111 | G14: =Elect!K18 -> 3683 | H14: =Elect!Q18 -> 510 | I14: =Elect!S18 -> 130 | J14: =Elect!U18 -> 233 | K14: =Elect!W18 -> 906.3 | L14: =Elect!Y18 -> 0 | M14: =Elect!AA18 -> 3556.83 | N14: =Elect!AC18 -> 0 | O14: =Elect!AE18 -> 11.13 | P14: =Elect!AG18 -> 630.7 | Q14: =Elect!AI18 -> 445.73 | R14: =Elect!AK18 -> 3116.4 | S14: =Elect!AM18 -> 102.82 | T14: =Elect!AP18 -> 193.95 | U14: =Elect!AR18 -> 144 | V14: =Elect!AT18 -> 306.05556 | W14: =Elect!AV18 -> 45 | X14: =Elect!AX18 -> 767 | Y14: =Elect!AZ18 -> 10 | Z14: =Elect!BB18 -> 4491 | AA14: =Elect!BD18 -> 199 | AB14: =Elect!BF18 -> 65 | AC14: =Elect!BH18 -> 5618.95 | AD14: =Elect!BL18 -> 197 | AE14: =Elect!BN18 -> 1268 | AF14: =Elect!BP18 -> 101 | AG14: =Elect!BR18 -> 134 | AH14: =Boat!C16 -> 5712 | AJ14: =Water!C19 -> 121.8 | AK14: =Water!E19 -> 162.4 | AL14: =Water!G19 -> 128.76 | AM14: =Boat!E16 -> 0 | AO14: =Gas!C19 -> 1355.74 | AP14: =Gas!E19 -> 308 | AQ14: =Gas!G19 -> 100 | AR14: =Boat!G16 -> 137 | AS14: =Elect!BT18 -> 162
... A32: Cairo at The First Residence | B32: =B31+1 -> 31 | C32: 8 | D32: 2022 | F32: =Elect!J36 -> 5783.5 | G32: =Elect!K36 -> 3567.1111 | H32: =Elect!Q36 -> 570 | I32: =Elect!S36 -> 142.22222 | J32: =Elect!U36 -> 264 | K32: =Elect!W36 -> 0 | L32: =Elect!Y36 -> 0 | M32: =Elect!AA36 -> 0 | N32: =Elect!AC36 -> 0 | O32: =Elect!AE36 -> 12.985 | P32: =Elect!AG36 -> 11.66 | Q32: =Elect!AI36 -> 0 | R32: =Elect!AK36 -> 3256.585 | S32: =Elect!AM36 -> 108.385 | T32: =Elect!AP36 -> 242.325 | U32: =Elect!AR36 -> 194 | V32: =Elect!AT36 -> 164 | W32: =Elect!AV36 -> 41.5 | X32: =Elect!AX36 -> 918 | Y32: =Elect!AZ36 -> 11 | Z32: =Elect!BB36 -> 5314 | AA32: =Elect!BD36 -> 271.5 | AB32: =Elect!BF36 -> 70 | AC32: =Elect!BH36 -> 5950.025 | AD32: =Elect!BL36 -> 234 | AE32: =Elect!BN36 -> 1295 | AF32: =Elect!BP36 -> 110.5 | AG32: =Elect!BR36 -> 141 | AH32: =Boat!C34 -> 0 | AJ32: =Water!C37 -> 108.26667 | AK32: =Water!E37 -> 145 | AL32: =Water!G37 -> 49.88 | AM32: =Boat!E34 -> 0 | AO32: =Gas!C37 -> 1357.5067 | AP32: =Gas!E37 -> 306.36667 | AQ32: =Gas!G37 -> 79 | AR32: =Boat!G34 -> 0 | AS32: =Elect!BT36 -> 238

Sheet Boat
B1: Electricity | D1: Water | F1: Gas
B2: Read | C2: Cons | D2: Read | E2: Cons | F2: Read | G2: Cons
B3: 3231504 | D3: 3897 | F3: 94828
A4: 1 | B4: 3237635 | C4: =B4-B3 -> 6131 | D4: 3924 | E4: =D4-D3 -> 27 | F4: 94953 | G4: =F4-F3 -> 125
A5: 2 | B5: 3242056 | C5: =B5-B4 -> 4421 | D5: 3943 | E5: =D5-D4 -> 19 | F5: 95046 | G5: =F5-F4 -> 93
A6: 3 | B6: 3247324 | C6: =B6-B5 -> 5268 | D6: 3964 | E6: =D6-D5 -> 21 | F6: 95193 | G6: =F6-F5 -> 147
A7: 4 | B7: 3251440 | C7: =B7-B6 -> 4116 | D7: 3980 | E7: =D7-D6 -> 16 | F7: 95280 | G7: =F7-F6 -> 87
A8: 5 | B8: 3257179 | C8: =B8-B7 -> 5739 | D8: 4003 | E8: =D8-D7 -> 23 | F8: 95400 | G8: =F8-F7 -> 120
A9: 6 | B9: 3262647 | C9: =B9-B8 -> 5468 | D9: 4023 | E9: =D9-D8 -> 20 | F9: 95620 | G9: =F9-F8 -> 220
A10: 7 | B10: 3266713 | C10: =B10-B9 -> 4066 | D10: 4043 | E10: =D10-D9 -> 20 | F10: 95691 | G10: =F10-F9 -> 71
A11: 8 | B11: 3271779 | C11: =B11-B10 -> 5066 | D11: 4068 | E11: =D11-D10 -> 25 | F11: 95787 | G11: =F11-F10 -> 96
A12: 9 | B12: 3277311 | C12: =B12-B11 -> 5532 | D12: 4091 | E12: =D12-D11 -> 23 | F12: 95912 | G12: =F12-F11 -> 125
A13: 10 | B13: 3281710 | C13: =B13-B12 -> 4399 | D13: 4108 | E13: =D13-D12 -> 17 | F13: 96010 | G13: =F13-F12 -> 98
A14: 11 | B14: 3286743 | C14: =B14-B13 -> 5033 | D14: 4128 | E14: =D14-D13 -> 20 | F14: 96120 | G14: =F14-F13 -> 110
A15: 12 | B15: 3291776 | C15: =B15-B14 -> 5033 | D15: 4154 | E15: =D15-D14 -> 26 | F15: 96301 | G15: =F15-F14 -> 181
A16: 13 | B16: 3297488 | C16: =B16-B15 -> 5712 | D16: 4154 | E16: =D16-D15 -> 0 | F16: 96438 | G16: =F16-F15 -> 137
A17: 14 | C17: =B17-B16 -> -3297488 | E17: =D17-D16 -> -4154 | G17: =F17-F16 -> -96438
A18: 15 | C18: =B18-B17 -> 0 | E18: =D18-D17 -> 0 | G18: =F18-F17 -> 0
A19: 16 | C19: =B19-B18 -> 0 | E19: =D19-D18 -> 0 | G19: =F19-F18 -> 0
A20: 17 | C20: =B20-B19 -> 0 | E20: =D20-D19 -> 0 | G20: =F20-F19 -> 0
A21: 18 | C21: =B21-B20 -> 0 | E21: =D21-D20 -> 0 | G21: =F21-F20 -> 0
A22: 19 | C22: =B22-B21 -> 0 | E22: =D22-D21 -> 0 | G22: =F22-F21 -> 0
A23: 20 | C23: =B23-B22 -> 0 | E23: =D23-D22 -> 0 | G23: =F23-F22 -> 0
A24: 21 | C24: =B24-B23 -> 0 | E24: =D24-D23 -> 0 | G24: =F24-F23 -> 0
A25: 22 | C25: =B25-B24 -> 0 | E25: =D25-D24 -> 0 | G25: =F25-F24 -> 0
A26: 23 | C26: =B26-B25 -> 0 | E26: =D26-D25 -> 0 | G26: =F26-F25 -> 0
A27: 24 | C27: =B27-B26 -> 0 | E27: =D27-D26 -> 0 | G27: =F27-F26 -> 0
A28: 25 | C28: =B28-B27 -> 0 | E28: =D28-D27 -> 0 | G28: =F28-F27 -> 0
... A34: 31 | C34: =B34-B33 -> 0 | E34: =D34-D33 -> 0 | G34: =F34-F33 -> 0
A35: Sum | C35: =SUM(C4:C34) -> -3231504 | E35: =SUM(E4:E34) -> -3897 | G35: =SUM(G4:G34) -> -94828

Sheet Elect
A1: 44835 | M1: Electricity | BP1: Gourmandise UP | BR1: 1.6 | BS1: Power Taxes | BU1: Max Demand | BW1: 500 | BX1: Electricity UP | BZ1: 1.15
BS2: Light Taxes | BU2: PF Penalty | BX2: Max. Demand UP | BZ2: 30
A3: Date | B3: COUNTER (1) | D3: MD | F3: KVAR | H3: n | I3: Guest Rooms Consumption | R3: Casino Consumption | V3: Plant Room Shared Loads | AO3: To Be Charged By First Arabian | BK3: From Main Panel G2 | BS3: Total Consumption. | BT3: No. Of | BU3: KWH/ | BV3: No. Of | BW3: KWH/ | BX3: Total Cost | BY3: L.E\ | BZ3: L.E\
B4: Reading | C4: Consp. F: *800 | D4: Reading | E4: Consp F: 80 | F4: Reading | G4: Consp. F:*10 | I4: Main Feeder | J4: Consp | K4: T2+T8 | L4: Trans T2 | M4: Consp | N4: Trans T8 | O4: Consp | P4: La Gourmandize | Q4: Consp *30 | R4: Casino 3rd floor EM | S4: Consp | T4: Casino 3rd floor Normal | U4: Consp | V4: Chiller 1 | W4: Consp 53% | X4: Chiller 2 | Y4: Consp 53% | Z4: Chiller 3 | AA4: Consp 53% | AB4: Chiller 4 | AC4: Consp 53% | AD4: Chiller 5 | AE4: Consp 53% | AF4: Chiller 6 | AG4: Consp 53% | AH4: Cooling Towers | AI4: Consp 53% | AJ4: Chiller Pumps | AK4: Consp 53% | AL4: Cooling Tower Pumps | AM4: Consp 53% | AN4: Total Plant Room Consp | AO4: Fiber Chiller (N24) | AP4: Consp | AQ4: Mall Ceiling light (N4) | AR4: Consp | AS4: LG Bakery (N2) | AT4: Consp | AU4: LG Bakery light ( Old lockers ) | AV4: Consp | AW4: MCCR1 | AX4: Consp | AY4: Children Swimming pool | AZ4: Consp | BA4: DPH1 | BB4: Consp | BC4: Guest Rooms Emergency | BD4: Consp | BE4: Hotel Hoods | BF4: Consp | BG4: Main G2 | BH4: Consp | BI4: Total Consp From First Arabian | BJ4: First Arabian Charge Back | BK4: Old Casino Emergency | BL4: Consp | BM4: L / A | BN4: Consp | BO4: L / B | BP4: Consp | BQ4: L / C | BR4: Consp | BT4: Rooms | BU4: room | BV4: guest | BW4: guest | BY4: Room | BZ4: Guest
A5: Last Month Reading | I5: 25358857 | J5: =IF(I5>=I4,I5-I4,0) -> 0 | K5: =M5+O5 -> 0 | L5: 153545 | M5: =IF(L5>=L4,L5-L4,0) -> 0 | N5: 194426 | O5: =IF(N5>=N4,N5-N4,0) -> 0 | P5: 226098 | Q5: =IF(P5>=P4,P5-P4,0)*30 -> 0 | R5: 217431 | S5: =IF(R5>=R4,R5-R4,0) -> 0 | T5: 396865 | U5: =IF(T5>=T4,T5-T4,0) -> 0 | V5: 472400 | W5: =IF(V5>=V4,V5-V4,0)*0.53 -> 0 | X5: 734024 | Y5: =IF(X5>=X4,X5-X4,0)*0.53 -> 0 | Z5: 684478 | AA5: =IF(Z5>=Z4,Z5-Z4,0)*0.53 -> 0 | AB5: 68783 | AC5: =IF(AB5>=AB4,AB5-AB4,0)*0.53 -> 0 | AD5: 842083 | AE5: =IF(AD5>=AD4,AD5-AD4,0)*0.53 -> 0 | AF5: 996740 | AG5: =IF(AF5>=AF4,AF5-AF4,0)*0.53 -> 0 | AH5: 358033 | AI5: =IF(AH5>=AH4,AH5-AH4,0)*0.53 -> 0 | AJ5: 178289 | AK5: =IF(AJ5>=AJ4,AJ5-AJ4,0)*0.53 -> 0 | AL5: 554371 | AM5: =IF(AL5>=AL4,AL5-AL4,0)*0.53 -> 0 | AN5: =W5+Y5+AA5+AC5+AE5+AG5+AI5+AK5+AM5 -> 0 | AO5: 8049644 | AP5: =IF(AO5>=AO4,AO5-AO4,0)*0.1125 -> 0 | AQ5: 737609 | AR5: =IF(AQ5>=AQ4,AQ5-AQ4,0) -> 0 | AS5: 4234 | AT5: =IF(AS5>=AS4,AS5-AS4,0) -> 0 | AU5: 823094 | AV5: =IF(AU5>=AU4,AU5-AU4,0) -> 0 | AW5: 2827168 | AX5: =IF(AW5>=AW4,AW5-AW4,0) -> 0 | AY5: 230844 | AZ5: =IF(AY5>=AY4,AY5-AY4,0) -> 0 | BA5: 20483962 | BB5: =IF(BA5>=BA4,BA5-BA4,0) -> 0 | BC5: 624512 | BD5: =IF(BC5>=BC4,BC5-BC4,0) -> 0 | BE5: 41468 | BF5: =IF(BE5>=BE4,BE5-BE4,0) -> 0 | BG5: 25720443 | BH5: =IF(BG5>=BG4,BG5-BG4,0)-(0.45*BN5)-(0.45*BP5)-BR5 -> 0 | BI5: =AP5+AR5+AT5+AV5+AX5+AZ5+BB5+BD5+BF5+BH5 -> 0 | BJ5: =BI5+AN5 -> 0 | BK5: 1480954 | BL5: =IF(BK5>=BK4,BK5-BK4,0) -> 0 | BM5: 4229427 | BN5: =IF(BM5>=BM4,BM5-BM4,0) -> 0 | BO5: 442405 | BP5: =IF(BO5>=BO4,BO5-BO4,0) -> 0 | BQ5: 553744 | BR5: =IF(BQ5>=BQ4,BQ5-BQ4,0) -> 0
A6: 1 | C6: =IF(+B6-B5>0,B6-B5,(B6-B5)>0)*800 -> 0 | E6: =IF(+D6-D5>0,D6-D5,(D6-D5)>0)*80 -> 0 | G6: =IF(+F6-F5>0,F6-F5,(F6-F5)>0)*10 -> 0 | H6: 56 | I6: 25360896 | J6: =IF(I6>=I5,I6-I5,0) -> 2039 | K6: =M6+O6 -> 1738 | L6: 155159 | M6: =IF(L6>=L5,L6-L5,0) -> 1614 | N6: 194550 | O6: =IF(N6>=N5,N6-N5,0) -> 124 | P6: 226125 | Q6: =IF(P6>=P5,P6-P5,0)*30 -> 810 | R6: 217576 | S6: =IF(R6>=R5,R6-R5,0) -> 145 | T6: 397123 | U6: =IF(T6>=T5,T6-T5,0) -> 258 | V6: 478842 | W6: =IF(V6>=V5,V6-V5,0)*0.53 -> 3414.26 | X6: 742565 | Y6: =IF(X6>=X5,X6-X5,0)*0.53 -> 4526.73 | Z6: 684478 | AA6: =IF(Z6>=Z5,Z6-Z5,0)*0.53 -> 0 | AB6: 68783 | AC6: =IF(AB6>=AB5,AB6-AB5,0)*0.53 -> 0 | AD6: 842242 | AE6: =IF(AD6>=AD5,AD6-AD5,0)*0.53 -> 84.27 | AF6: 999896 | AG6: =IF(AF6>=AF5,AF6-AF5,0)*0.53 -> 1672.68 | AH6: 360245 | AI6: =IF(AH6>=AH5,AH6-AH5,0)*0.53 -> 1172.36 | AJ6: 185784 | AK6: =IF(AJ6>=AJ5,AJ6-AJ5,0)*0.53 -> 3972.35 | AL6: 554563 | AM6: =IF(AL6>=AL5,AL6-AL5,0)*0.53 -> 101.76 | AN6: =W6+Y6+AA6+AC6+AE6+AG6+AI6+AK6+AM6 -> 14944.41 | AO6: 8052733 | AP6: =IF(AO6>=AO5,AO6-AO5,0)*0.1125 -> 347.5125 | AQ6: 737802 | AR6: =IF(AQ6>=AQ5,AQ6-AQ5,0) -> 193 | AS6: 4538.6858 | AT6: =IF(AS6>=AS5,AS6-AS5,0) -> 304.68585 | AU6: 823139 | AV6: =IF(AU6>=AU5,AU6-AU5,0) -> 45 | AW6: 2828098 | AX6: =IF(AW6>=AW5,AW6-AW5,0) -> 930 | AY6: 230856 | AZ6: =IF(AY6>=AY5,AY6-AY5,0) -> 12 | BA6: 20488900 | BB6: =IF(BA6>=BA5,BA6-BA5,0) -> 4938 | BC6: 624796 | BD6: =IF(BC6>=BC5,BC6-BC5,0) -> 284 | BE6: 41523 | BF6: =IF(BE6>=BE5,BE6-BE5,0) -> 55 | BG6: 25728058 | BH6: =IF(BG6>=BG5,BG6-BG5,0)-(0.45*BN6)-(0.45*BP6)-BR6 -> 6683.05 | BI6: =AP6+AR6+AT6+AV6+AX6+AZ6+BB6+BD6+BF6+BH6 -> 13792.248 | BJ6: =BI6+AN6 -> 28736.658 | BK6: 1481219 | BL6: =IF(BK6>=BK5,BK6-BK5,0) -> 265 | BM6: 4230991 | BN6: =IF(BM6>=BM5,BM6-BM5,0) -> 1564 | BO6: 442532 | BP6: =IF(BO6>=BO5,BO6-BO5,0) -> 127 | BQ6: 553915 | BR6: =IF(BQ6>=BQ5,BQ6-BQ5,0) -> 171 | BS6: =J6+Q6+AN6+BI6 -> 31585.658 | BT6: 227 | BU6: =IF(BS6>0,BS6/BT5,0) -> #DIV/0! | BW6: =IF(BS6>0,BS6/BV6,0) -> #DIV/0! | BX6: =((BS6-Q6)*$BZ$1)+(Q6*$BR$1) -> 36688.007 | BY6: =IF(BX6>0,BX6/BT5,0) -> #DIV/0! | BZ6: =IF(BX6>0,BX6/BV6,0) -> #DIV/0!
A7: 2 | I7: 25250634 | J7: =IF(I7>=I6,I7-I6,0) -> 0 | K7: =M7+O7 -> 3340 | L7: 156963 | M7: =IF(L7>=L6,L7-L6,0) -> 1804 | N7: 196086 | O7: =IF(N7>=N6,N7-N6,0) -> 1536 | P7: 226144 | Q7: =IF(P7>=P6,P7-P6,0)*30 -> 570 | R7: 217710 | S7: =IF(R7>=R6,R7-R6,0) -> 134 | T7: 397380 | U7: =IF(T7>=T6,T7-T6,0) -> 257 | V7: 485402 | W7: =IF(V7>=V6,V7-V6,0)*0.53 -> 3476.8 | X7: 749787 | Y7: =IF(X7>=X6,X7-X6,0)*0.53 -> 3827.66 | Z7: 684478 | AA7: =IF(Z7>=Z6,Z7-Z6,0)*0.53 -> 0 | AB7: 68783 | AC7: =IF(AB7>=AB6,AB7-AB6,0)*0.53 -> 0 | AD7: 845500 | AE7: =IF(AD7>=AD6,AD7-AD6,0)*0.53 -> 1726.74 | AF7: 999916 | AG7: =IF(AF7>=AF6,AF7-AF6,0)*0.53 -> 10.6 | AH7: 362199 | AI7: =IF(AH7>=AH6,AH7-AH6,0)*0.53 -> 1035.62 | AJ7: 192533 | AK7: =IF(AJ7>=AJ6,AJ7-AJ6,0)*0.53 -> 3576.97 | AL7: 554756 | AM7: =IF(AL7>=AL6,AL7-AL6,0)*0.53 -> 102.29 | AN7: =W7+Y7+AA7+AC7+AE7+AG7+AI7+AK7+AM7 -> 13756.68 | AO7: 8055312 | AP7: =IF(AO7>=AO6,AO7-AO6,0)*0.1125 -> 290.1375 | AQ7: 737956 | AR7: =IF(AQ7>=AQ6,AQ7-AQ6,0) -> 154 | AS7: 4718.4476 | AT7: =IF(AS7>=AS6,AS7-AS6,0) -> 179.76179 | AU7: 823200 | AV7: =IF(AU7>=AU6,AU7-AU6,0) -> 61 | AW7: 2828902 | AX7: =IF(AW7>=AW6,AW7-AW6,0) -> 804 | AY7: 230866 | AZ7: =IF(AY7>=AY6,AY7-AY6,0) -> 10 | BA7: 20494216 | BB7: =IF(BA7>=BA6,BA7-BA6,0) -> 5316 | BC7: 625048 | BD7: =IF(BC7>=BC6,BC7-BC6,0) -> 252 | BE7: 41635 | BF7: =IF(BE7>=BE6,BE7-BE6,0) -> 112 | BG7: 25735409 | BH7: =IF(BG7>=BG6,BG7-BG6,0)-(0.45*BN7)-(0.45*BP7)-BR7 -> 6520.6 | BI7: =AP7+AR7+AT7+AV7+AX7+AZ7+BB7+BD7+BF7+BH7 -> 13699.499 | BJ7: =BI7+AN7 -> 27456.179 | BK7: 1481512 | BL7: =IF(BK7>=BK6,BK7-BK6,0) -> 293 | BM7: 4232390 | BN7: =IF(BM7>=BM6,BM7-BM6,0) -> 1399 | BO7: 442645 | BP7: =IF(BO7>=BO6,BO7-BO6,0) -> 113 | BQ7: 554065 | BR7: =IF(BQ7>=BQ6,BQ7-BQ6,0) -> 150 | BS7: =J7+Q7+AN7+BI7 -> 28026.179 | BT7: 243 | BU7: =IF(BS7>0,BS7/BT6,0) -> 123.46334 | BW7: =IF(BS7>0,BS7/BV7,0) -> #DIV/0! | BX7: =((BS7-Q7)*$BZ$1)+(Q7*$BR$1) -> 32486.606 | BY7: =IF(BX7>0,BX7/BT6,0) -> 143.1128 | BZ7: =IF(BX7>0,BX7/BV7,0) -> #DIV/0!
A8: 3 | C8: =IF(+B8-B7>0,B8-B7,(B8-B7)>0)*800 -> 0 | E8: =IF(+D8-D7>0,D8-D7,(D8-D7)>0)*80 -> 0 | G8: =IF(+F8-F7>0,F8-F7,(F8-F7)>0)*10 -> 0 | H8: 57 | I8: 25256603 | J8: =IF(I8>=I7,I8-I7,0) -> 5969.1111 | K8: =M8+O8 -> 4452 | L8: 159406 | M8: =IF(L8>=L7,L8-L7,0) -> 2443 | N8: 198095 | O8: =IF(N8>=N7,N8-N7,0) -> 2009 | P8: 226169 | Q8: =IF(P8>=P7,P8-P7,0)*30 -> 750 | R8: 217857 | S8: =IF(R8>=R7,R8-R7,0) -> 147 | T8: 397648 | U8: =IF(T8>=T7,T8-T7,0) -> 268 | V8: 492753 | W8: =IF(V8>=V7,V8-V7,0)*0.53 -> 3896.03 | X8: 758238 | Y8: =IF(X8>=X7,X8-X7,0)*0.53 -> 4479.03 | Z8: 684671 | AA8: =IF(Z8>=Z7,Z8-Z7,0)*0.53 -> 102.29 | AB8: 68783 | AC8: =IF(AB8>=AB7,AB8-AB7,0)*0.53 -> 0 | AD8: 848697 | AE8: =IF(AD8>=AD7,AD8-AD7,0)*0.53 -> 1694.41 | AF8: 999937 | AG8: =IF(AF8>=AF7,AF8-AF7,0)*0.53 -> 11.13 | AH8: 364428 | AI8: =IF(AH8>=AH7,AH8-AH7,0)*0.53 -> 1181.37 | AJ8: 201159 | AK8: =IF(AJ8>=AJ7,AJ8-AJ7,0)*0.53 -> 4571.78 | AL8: 555010 | AM8: =IF(AL8>=AL7,AL8-AL7,0)*0.53 -> 134.62 | AN8: =W8+Y8+AA8+AC8+AE8+AG8+AI8+AK8+AM8 -> 16070.66 | AO8: 8058069 | AP8: =IF(AO8>=AO7,AO8-AO7,0)*0.1125 -> 310.1625 | AQ8: 738109 | AR8: =IF(AQ8>=AQ7,AQ8-AQ7,0) -> 153 | AS8: 4898.2094 | AT8: =IF(AS8>=AS7,AS8-AS7,0) -> 179.76179 | AU8: 823269 | AV8: =IF(AU8>=AU7,AU8-AU7,0) -> 69 | AW8: 2829964 | AX8: =IF(AW8>=AW7,AW8-AW7,0) -> 1062 | AY8: 230878 | AZ8: =IF(AY8>=AY7,AY8-AY7,0) -> 12 | BA8: 20500768 | BB8: =IF(BA8>=BA7,BA8-BA7,0) -> 6552 | BC8: 625295 | BD8: =IF(BC8>=BC7,BC8-BC7,0) -> 247 | BE8: 41690 | BF8: =IF(BE8>=BE7,BE8-BE7,0) -> 55 | BG8: 25743058 | BH8: =IF(BG8>=BG7,BG8-BG7,0)-(0.45*BN8)-(0.45*BP8)-BR8 -> 6852.45 | BI8: =AP8+AR8+AT8+AV8+AX8+AZ8+BB8+BD8+BF8+BH8 -> 15492.374 | BJ8: =BI8+AN8 -> 31563.034 | BK8: 1481794 | BL8: =IF(BK8>=BK7,BK8-BK7,0) -> 282 | BM8: 4233740 | BN8: =IF(BM8>=BM7,BM8-BM7,0) -> 1350 | BO8: 442754 | BP8: =IF(BO8>=BO7,BO8-BO7,0) -> 109 | BQ8: 554205 | BR8: =IF(BQ8>=BQ7,BQ8-BQ7,0) -> 140 | BS8: =J8+Q8+AN8+BI8 -> 38282.145 | BT8: 220 | BU8: =IF(BS8>0,BS8/BT7,0) -> 157.53969 | BW8: =IF(BS8>0,BS8/BV8,0) -> #DIV/0! | BX8: =((BS8-Q8)*$BZ$1)+(Q8*$BR$1) -> 44361.967 | BY8: =IF(BX8>0,BX8/BT7,0) -> 182.55954 | BZ8: =IF(BX8>0,BX8/BV8,0) -> #DIV/0!
A9: 4 | C9: =IF(+B9-B8>0,B9-B8,(B9-B8)>0)*800 -> 0 | E9: =IF(+D9-D8>0,D9-D8,(D9-D8)>0)*80 -> 0 | G9: =IF(+F9-F8>0,F9-F8,(F9-F8)>0)*10 -> 0 | I9: 25262572 | J9: =IF(I9>=I8,I9-I8,0) -> 5969.1111 | K9: =M9+O9 -> 3105 | L9: 161132 | M9: =IF(L9>=L8,L9-L8,0) -> 1726 | N9: 199474 | O9: =IF(N9>=N8,N9-N8,0) -> 1379 | P9: 226193 | Q9: =IF(P9>=P8,P9-P8,0)*30 -> 720 | R9: 217996 | S9: =IF(R9>=R8,R9-R8,0) -> 139 | T9: 397888 | U9: =IF(T9>=T8,T9-T8,0) -> 240 | V9: 497774 | W9: =IF(V9>=V8,V9-V8,0)*0.53 -> 2661.13 | X9: 758238 | Y9: =IF(X9>=X8,X9-X8,0)*0.53 -> 0 | Z9: 690679 | AA9: =IF(Z9>=Z8,Z9-Z8,0)*0.53 -> 3184.24 | AB9: 68783 | AC9: =IF(AB9>=AB8,AB9-AB8,0)*0.53 -> 0 | AD9: 851781 | AE9: =IF(AD9>=AD8,AD9-AD8,0)*0.53 -> 1634.52 | AF9: 999958 | AG9: =IF(AF9>=AF8,AF9-AF8,0)*0.53 -> 11.13 | AH9: 366258 | AI9: =IF(AH9>=AH8,AH9-AH8,0)*0.53 -> 969.9 | AJ9: 207511 | AK9: =IF(AJ9>=AJ8,AJ9-AJ8,0)*0.53 -> 3366.56 | AL9: 555204 | AM9: =IF(AL9>=AL8,AL9-AL8,0)*0.53 -> 102.82 | AN9: =W9+Y9+AA9+AC9+AE9+AG9+AI9+AK9+AM9 -> 11930.3 | AO9: 8060613 | AP9: =IF(AO9>=AO8,AO9-AO8,0)*0.1125 -> 286.2 | AQ9: 738257 | AR9: =IF(AQ9>=AQ8,AQ9-AQ8,0) -> 148 | AS9: 5077.9712 | AT9: =IF(AS9>=AS8,AS9-AS8,0) -> 179.76179 | AU9: 823326 | AV9: =IF(AU9>=AU8,AU9-AU8,0) -> 57 | AW9: 2830739 | AX9: =IF(AW9>=AW8,AW9-AW8,0) -> 775 | AY9: 230889 | AZ9: =IF(AY9>=AY8,AY9-AY8,0) -> 11 | BA9: 20504543 | BB9: =IF(BA9>=BA8,BA9-BA8,0) -> 3775 | BC9: 625581 | BD9: =IF(BC9>=BC8,BC9-BC8,0) -> 286 | BE9: 41725 | BF9: =IF(BE9>=BE8,BE9-BE8,0) -> 35 | BG9: 25750104 | BH9: =IF(BG9>=BG8,BG9-BG8,0)-(0.45*BN9)-(0.45*BP9)-BR9 -> 6274.8 | BI9: =AP9+AR9+AT9+AV9+AX9+AZ9+BB9+BD9+BF9+BH9 -> 11827.762 | BJ9: =BI9+AN9 -> 23758.062 | BK9: 1482042 | BL9: =IF(BK9>=BK8,BK9-BK8,0) -> 248 | BM9: 4235030 | BN9: =IF(BM9>=BM8,BM9-BM8,0) -> 1290 | BO9: 442860 | BP9: =IF(BO9>=BO8,BO9-BO8,0) -> 106 | BQ9: 554348 | BR9: =IF(BQ9>=BQ8,BQ9-BQ8,0) -> 143 | BS9: =J9+Q9+AN9+BI9 -> 30447.173 | BT9: 203 | BU9: =IF(BS9>0,BS9/BT8,0) -> 138.39624 | BW9: =IF(BS9>0,BS9/BV9,0) -> #DIV/0! | BX9: =((BS9-Q9)*$BZ$1)+(Q9*$BR$1) -> 35338.249 | BY9: =IF(BX9>0,BX9/BT8,0) -> 160.6284 | BZ9: =IF(BX9>0,BX9/BV9,0) -> #DIV/0!
A10: 5 | C10: =IF(+B10-B9>0,B10-B9,(B10-B9)>0)*800 -> 0 | E10: =IF(+D10-D9>0,D10-D9,(D10-D9)>0)*80 -> 0 | G10: =IF(+F10-F9>0,F10-F9,(F10-F9)>0)*10 -> 0 | H10: 58 | I10: 25268541 | J10: =IF(I10>=I9,I10-I9,0) -> 5969.1111 | K10: =M10+O10 -> 3812 | L10: 163245 | M10: =IF(L10>=L9,L10-L9,0) -> 2113 | N10: 201173 | O10: =IF(N10>=N9,N10-N9,0) -> 1699 | P10: 226211 | Q10: =IF(P10>=P9,P10-P9,0)*30 -> 540 | R10: 218145 | S10: =IF(R10>=R9,R10-R9,0) -> 149 | T10: 398152 | U10: =IF(T10>=T9,T10-T9,0) -> 264 | V10: 504389 | W10: =IF(V10>=V9,V10-V9,0)*0.53 -> 3505.95 | X10: 758238 | Y10: =IF(X10>=X9,X10-X9,0)*0.53 -> 0 | Z10: 698336 | AA10: =IF(Z10>=Z9,Z10-Z9,0)*0.53 -> 4058.21 | AB10: 68783 | AC10: =IF(AB10>=AB9,AB10-AB9,0)*0.53 -> 0 | AD10: 854791 | AE10: =IF(AD10>=AD9,AD10-AD9,0)*0.53 -> 1595.3 | AF10: 999977 | AG10: =IF(AF10>=AF9,AF10-AF9,0)*0.53 -> 10.07 | AH10: 368362 | AI10: =IF(AH10>=AH9,AH10-AH9,0)*0.53 -> 1115.12 | AJ10: 215212 | AK10: =IF(AJ10>=AJ9,AJ10-AJ9,0)*0.53 -> 4081.53 | AL10: 555431 | AM10: =IF(AL10>=AL9,AL10-AL9,0)*0.53 -> 120.31 | AN10: =W10+Y10+AA10+AC10+AE10+AG10+AI10+AK10+AM10 -> 14486.49 | AO10: 8063072 | AP10: =IF(AO10>=AO9,AO10-AO9,0)*0.1125 -> 276.6375 | AQ10: 738407 | AR10: =IF(AQ10>=AQ9,AQ10-AQ9,0) -> 150 | AS10: 5257.733 | AT10: =IF(AS10>=AS9,AS10-AS9,0) -> 179.76179 | AU10: 823391 | AV10: =IF(AU10>=AU9,AU10-AU9,0) -> 65 | AW10: 2831702 | AX10: =IF(AW10>=AW9,AW10-AW9,0) -> 963 | AY10: 230901 | AZ10: =IF(AY10>=AY9,AY10-AY9,0) -> 12 | BA10: 20511197 | BB10: =IF(BA10>=BA9,BA10-BA9,0) -> 6654 | BC10: 625854 | BD10: =IF(BC10>=BC9,BC10-BC9,0) -> 273 | BE10: 41780 | BF10: =IF(BE10>=BE9,BE10-BE9,0) -> 55 | BG10: 25757314 | BH10: =IF(BG10>=BG9,BG10-BG9,0)-(0.45*BN10)-(0.45*BP10)-BR10 -> 6417.65 | BI10: =AP10+AR10+AT10+AV10+AX10+AZ10+BB10+BD10+BF10+BH10 -> 15046.049 | BJ10: =BI10+AN10 -> 29532.539 | BK10: 1482289 | BL10: =IF(BK10>=BK9,BK10-BK9,0) -> 247 | BM10: 4236345 | BN10: =IF(BM10>=BM9,BM10-BM9,0) -> 1315 | BO10: 442968 | BP10: =IF(BO10>=BO9,BO10-BO9,0) -> 108 | BQ10: 554500 | BR10: =IF(BQ10>=BQ9,BQ10-BQ9,0) -> 152 | BS10: =J10+Q10+AN10+BI10 -> 36041.65 | BT10: 187 | BU10: =IF(BS10>0,BS10/BT9,0) -> 177.54508 | BW10: =IF(BS10>0,BS10/BV10,0) -> #DIV/0! | BX10: =((BS10-Q10)*$BZ$1)+(Q10*$BR$1) -> 41690.898 | BY10: =IF(BX10>0,BX10/BT9,0) -> 205.37388 | BZ10: =IF(BX10>0,BX10/BV10,0) -> #DIV/0!
A11: 6 | C11: =IF(+B11-B10>0,B11-B10,(B11-B10)>0)*800 -> 0 | E11: =IF(+D11-D10>0,D11-D10,(D11-D10)>0)*80 -> 0 | G11: =IF(+F11-F10>0,F11-F10,(F11-F10)>0)*10 -> 0 | I11: 25274511 | J11: =IF(I11>=I10,I11-I10,0) -> 5969.1111 | K11: =M11+O11 -> 3532 | L11: 165229 | M11: =IF(L11>=L10,L11-L10,0) -> 1984 | N11: 202721 | O11: =IF(N11>=N10,N11-N10,0) -> 1548 | P11: 226229 | Q11: =IF(P11>=P10,P11-P10,0)*30 -> 540 | R11: 218281 | S11: =IF(R11>=R10,R11-R10,0) -> 136 | T11: 398383 | U11: =IF(T11>=T10,T11-T10,0) -> 231 | V11: 509341 | W11: =IF(V11>=V10,V11-V10,0)*0.53 -> 2624.56 | X11: 758238 | Y11: =IF(X11>=X10,X11-X10,0)*0.53 -> 0 | Z11: 704970 | AA11: =IF(Z11>=Z10,Z11-Z10,0)*0.53 -> 3516.02 | AB11: 68783 | AC11: =IF(AB11>=AB10,AB11-AB10,0)*0.53 -> 0 | AD11: 857599 | AE11: =IF(AD11>=AD10,AD11-AD10,0)*0.53 -> 1488.24 | AF11: 999999 | AG11: =IF(AF11>=AF10,AF11-AF10,0)*0.53 -> 11.66 | AH11: 370090 | AI11: =IF(AH11>=AH10,AH11-AH10,0)*0.53 -> 915.84 | AJ11: 222302 | AK11: =IF(AJ11>=AJ10,AJ11-AJ10,0)*0.53 -> 3757.7 | AL11: 555639 | AM11: =IF(AL11>=AL10,AL11-AL10,0)*0.53 -> 110.24 | AN11: =W11+Y11+AA11+AC11+AE11+AG11+AI11+AK11+AM11 -> 12424.26 | AO11: 8065410 | AP11: =IF(AO11>=AO10,AO11-AO10,0)*0.1125 -> 263.025 | AQ11: 738545 | AR11: =IF(AQ11>=AQ10,AQ11-AQ10,0) -> 138 | AS11: 5488 | AT11: =IF(AS11>=AS10,AS11-AS10,0) -> 230.26701 | AU11: 823440 | AV11: =IF(AU11>=AU10,AU11-AU10,0) -> 49 | AW11: 2832611 | AX11: =IF(AW11>=AW10,AW11-AW10,0) -> 909 | AY11: 230911 | AZ11: =IF(AY11>=AY10,AY11-AY10,0) -> 10 | BA11: 20516107 | BB11: =IF(BA11>=BA10,BA11-BA10,0) -> 4910 | BC11: 626140 | BD11: =IF(BC11>=BC10,BC11-BC10,0) -> 286 | BE11: 41830 | BF11: =IF(BE11>=BE10,BE11-BE10,0) -> 50 | BG11: 25764340 | BH11: =IF(BG11>=BG10,BG11-BG10,0)-(0.45*BN11)-(0.45*BP11)-BR11 -> 6297.65 | BI11: =AP11+AR11+AT11+AV11+AX11+AZ11+BB11+BD11+BF11+BH11 -> 13142.942 | BJ11: =BI11+AN11 -> 25567.202 | BK11: 1482562 | BL11: =IF(BK11>=BK10,BK11-BK10,0) -> 273 | BM11: 4237576 | BN11: =IF(BM11>=BM10,BM11-BM10,0) -> 1231 | BO11: 443080 | BP11: =IF(BO11>=BO10,BO11-BO10,0) -> 112 | BQ11: 554624 | BR11: =IF(BQ11>=BQ10,BQ11-BQ10,0) -> 124 | BS11: =J11+Q11+AN11+BI11 -> 32076.313 | BT11: 203 | BU11: =IF(BS11>0,BS11/BT10,0) -> 171.53109 | BW11: =IF(BS11>0,BS11/BV11,0) -> #DIV/0! | BX11: =((BS11-Q11)*$BZ$1)+(Q11*$BR$1) -> 37130.76 | BY11: =IF(BX11>0,BX11/BT10,0) -> 198.56021 | BZ11: =IF(BX11>0,BX11/BV11,0) -> #DIV/0!
A12: 7 | C12: =IF(+B12-B11>0,B12-B11,(B12-B11)>0)*800 -> 0 | E12: =IF(+D12-D11>0,D12-D11,(D12-D11)>0)*80 -> 0 | G12: =IF(+F12-F11>0,F12-F11,(F12-F11)>0)*10 -> 0 | H12: 59 | I12: 25280480 | J12: =IF(I12>=I11,I12-I11,0) -> 5969.1111 | K12: =M12+O12 -> 2492 | L12: 166992 | M12: =IF(L12>=L11,L12-L11,0) -> 1763 | N12: 203450 | O12: =IF(N12>=N11,N12-N11,0) -> 729 | P12: 226246 | Q12: =IF(P12>=P11,P12-P11,0)*30 -> 510 | R12: 218431 | S12: =IF(R12>=R11,R12-R11,0) -> 150 | T12: 398637 | U12: =IF(T12>=T11,T12-T11,0) -> 254 | V12: 512134 | W12: =IF(V12>=V11,V12-V11,0)*0.53 -> 1480.29 | X12: 758238 | Y12: =IF(X12>=X11,X12-X11,0)*0.53 -> 0 | Z12: 710734 | AA12: =IF(Z12>=Z11,Z12-Z11,0)*0.53 -> 3054.92 | AB12: 68783 | AC12: =IF(AB12>=AB11,AB12-AB11,0)*0.53 -> 0 | AD12: 860195 | AE12: =IF(AD12>=AD11,AD12-AD11,0)*0.53 -> 1375.88 | AF12: 1000020 | AG12: =IF(AF12>=AF11,AF12-AF11,0)*0.53 -> 11.13 | AH12: 371354 | AI12: =IF(AH12>=AH11,AH12-AH11,0)*0.53 -> 669.92 | AJ12: 227911 | AK12: =IF(AJ12>=AJ11,AJ12-AJ11,0)*0.53 -> 2972.77 | AL12: 555824 | AM12: =IF(AL12>=AL11,AL12-AL11,0)*0.53 -> 98.05 | AN12: =W12+Y12+AA12+AC12+AE12+AG12+AI12+AK12+AM12 -> 9662.96 | AO12: 8067503 | AP12: =IF(AO12>=AO11,AO12-AO11,0)*0.1125 -> 235.4625 | AQ12: 738720 | AR12: =IF(AQ12>=AQ11,AQ12-AQ11,0) -> 175 | AS12: 5658 | AT12: =IF(AS12>=AS11,AS12-AS11,0) -> 170 | AU12: 823473 | AV12: =IF(AU12>=AU11,AU12-AU11,0) -> 33 | AW12: 2833401 | AX12: =IF(AW12>=AW11,AW12-AW11,0) -> 790 | AY12: 230923 | AZ12: =IF(AY12>=AY11,AY12-AY11,0) -> 12 | BA12: 20521363 | BB12: =IF(BA12>=BA11,BA12-BA11,0) -> 5256 | BC12: 626425 | BD12: =IF(BC12>=BC11,BC12-BC11,0) -> 285 | BE12: 41875 | BF12: =IF(BE12>=BE11,BE12-BE11,0) -> 45 | BG12: 25771947 | BH12: =IF(BG12>=BG11,BG12-BG11,0)-(0.45*BN12)-(0.45*BP12)-BR12 -> 6744.65 | BI12: =AP12+AR12+AT12+AV12+AX12+AZ12+BB12+BD12+BF12+BH12 -> 13746.112 | BJ12: =BI12+AN12 -> 23409.072 | BK12: 1482894 | BL12: =IF(BK12>=BK11,BK12-BK11,0) -> 332 | BM12: 4239035 | BN12: =IF(BM12>=BM11,BM12-BM11,0) -> 1459 | BO12: 443204 | BP12: =IF(BO12>=BO11,BO12-BO11,0) -> 124 | BQ12: 554774 | BR12: =IF(BQ12>=BQ11,BQ12-BQ11,0) -> 150 | BS12: =J12+Q12+AN12+BI12 -> 29888.184 | BT12: 234 | BU12: =IF(BS12>0,BS12/BT11,0) -> 147.23243 | BW12: =IF(BS12>0,BS12/BV12,0) -> #DIV/0! | BX12: =((BS12-Q12)*$BZ$1)+(Q12*$BR$1) -> 34600.911 | BY12: =IF(BX12>0,BX12/BT11,0) -> 170.44784 | BZ12: =IF(BX12>0,BX12/BV12,0) -> #DIV/0!
A13: 8 | C13: =IF(+B13-B12>0,B13-B12,(B13-B12)>0)*800 -> 0 | E13: =IF(+D13-D12>0,D13-D12,(D13-D12)>0)*80 -> 0 | G13: =IF(+F13-F12>0,F13-F12,(F13-F12)>0)*10 -> 0 | I13: 25286449 | J13: =IF(I13>=I12,I13-I12,0) -> 5969.1111 | K13: =M13+O13 -> 4301 | L13: 169145 | M13: =IF(L13>=L12,L13-L12,0) -> 2153 | N13: 205598 | O13: =IF(N13>=N12,N13-N12,0) -> 2148 | P13: 226265 | Q13: =IF(P13>=P12,P13-P12,0)*30 -> 570 | R13: 218587 | S13: =IF(R13>=R12,R13-R12,0) -> 156 | T13: 398908 | U13: =IF(T13>=T12,T13-T12,0) -> 271 | V13: 512134 | W13: =IF(V13>=V12,V13-V12,0)*0.53 -> 0 | X13: 758238 | Y13: =IF(X13>=X12,X13-X12,0)*0.53 -> 0 | Z13: 719365 | AA13: =IF(Z13>=Z12,Z13-Z12,0)*0.53 -> 4574.43 | AB13: 69387 | AC13: =IF(AB13>=AB12,AB13-AB12,0)*0.53 -> 320.12 | AD13: 860569 | AE13: =IF(AD13>=AD12,AD13-AD12,0)*0.53 -> 198.22 | AF13: 1001863 | AG13: =IF(AF13>=AF12,AF13-AF12,0)*0.53 -> 976.79 | AH13: 372526 | AI13: =IF(AH13>=AH12,AH13-AH12,0)*0.53 -> 621.16 | AJ13: 233966 | AK13: =IF(AJ13>=AJ12,AJ13-AJ12,0)*0.53 -> 3209.15 | AL13: 556063 | AM13: =IF(AL13>=AL12,AL13-AL12,0)*0.53 -> 126.67 | AN13: =W13+Y13+AA13+AC13+AE13+AG13+AI13+AK13+AM13 -> 10026.54 | AO13: 8069872 | AP13: =IF(AO13>=AO12,AO13-AO12,0)*0.1125 -> 266.5125 | AQ13: 738896 | AR13: =IF(AQ13>=AQ12,AQ13-AQ12,0) -> 176 | AS13: 5821 | AT13: =IF(AS13>=AS12,AS13-AS12,0) -> 163 | AU13: 823518 | AV13: =IF(AU13>=AU12,AU13-AU12,0) -> 45 | AW13: 2834328 | AX13: =IF(AW13>=AW12,AW13-AW12,0) -> 927 | AY13: 230935 | AZ13: =IF(AY13>=AY12,AY13-AY12,0) -> 12 | BA13: 20526619 | BB13: =IF(BA13>=BA12,BA13-BA12,0) -> 5256 | BC13: 626659 | BD13: =IF(BC13>=BC12,BC13-BC12,0) -> 234 | BE13: 41925 | BF13: =IF(BE13>=BE12,BE13-BE12,0) -> 50 | BG13: 25778720 | BH13: =IF(BG13>=BG12,BG13-BG12,0)-(0.45*BN13)-(0.45*BP13)-BR13 -> 6065.25 | BI13: =AP13+AR13+AT13+AV13+AX13+AZ13+BB13+BD13+BF13+BH13 -> 13194.763 | BJ13: =BI13+AN13 -> 23221.303 | BK13: 1483184 | BL13: =IF(BK13>=BK12,BK13-BK12,0) -> 290 | BM13: 4240194 | BN13: =IF(BM13>=BM12,BM13-BM12,0) -> 1159 | BO13: 443320 | BP13: =IF(BO13>=BO12,BO13-BO12,0) -> 116 | BQ13: 554908 | BR13: =IF(BQ13>=BQ12,BQ13-BQ12,0) -> 134 | BS13: =J13+Q13+AN13+BI13 -> 29760.414 | BT13: 248 | BU13: =IF(BS13>0,BS13/BT12,0) -> 127.18125 | BW13: =IF(BS13>0,BS13/BV13,0) -> #DIV/0! | BX13: =((BS13-Q13)*$BZ$1)+(Q13*$BR$1) -> 34480.976 | BY13: =IF(BX13>0,BX13/BT12,0) -> 147.3546 | BZ13: =IF(BX13>0,BX13/BV13,0) -> #DIV/0!
A14: 9 | C14: =IF(+B14-B13>0,B14-B13,(B14-B13)>0)*800 -> 0 | E14: =IF(+D14-D13>0,D14-D13,(D14-D13)>0)*80 -> 0 | G14: =IF(+F14-F13>0,F14-F13,(F14-F13)>0)*10 -> 0 | H14: 60 | I14: 25292418 | J14: =IF(I14>=I13,I14-I13,0) -> 5969.1111 | K14: =M14+O14 -> 2717 | L14: 170677 | M14: =IF(L14>=L13,L14-L13,0) -> 1532 | N14: 206783 | O14: =IF(N14>=N13,N14-N13,0) -> 1185 | P14: 226280 | Q14: =IF(P14>=P13,P14-P13,0)*30 -> 450 | R14: 218699 | S14: =IF(R14>=R13,R14-R13,0) -> 112 | T14: 399099 | U14: =IF(T14>=T13,T14-T13,0) -> 191 | V14: 514819 | W14: =IF(V14>=V13,V14-V13,0)*0.53 -> 1423.05 | X14: 758238 | Y14: =IF(X14>=X13,X14-X13,0)*0.53 -> 0 | Z14: 725082 | AA14: =IF(Z14>=Z13,Z14-Z13,0)*0.53 -> 3030.01 | AB14: 69387 | AC14: =IF(AB14>=AB13,AB14-AB13,0)*0.53 -> 0 | AD14: 860587 | AE14: =IF(AD14>=AD13,AD14-AD13,0)*0.53 -> 9.54 | AF14: 1003411 | AG14: =IF(AF14>=AF13,AF14-AF13,0)*0.53 -> 820.44 | AH14: 373243 | AI14: =IF(AH14>=AH13,AH14-AH13,0)*0.53 -> 380.01 | AJ14: 238761 | AK14: =IF(AJ14>=AJ13,AJ14-AJ13,0)*0.53 -> 2541.35 | AL14: 556242 | AM14: =IF(AL14>=AL13,AL14-AL13,0)*0.53 -> 94.87 | AN14: =W14+Y14+AA14+AC14+AE14+AG14+AI14+AK14+AM14 -> 8299.27 | AO14: 8071885 | AP14: =IF(AO14>=AO13,AO14-AO13,0)*0.1125 -> 226.4625 | AQ14: 739048 | AR14: =IF(AQ14>=AQ13,AQ14-AQ13,0) -> 152 | AS14: 5988.6667 | AT14: =IF(AS14>=AS13,AS14-AS13,0) -> 167.66667 | AU14: 823548 | AV14: =IF(AU14>=AU13,AU14-AU13,0) -> 30 | AW14: 2835009 | AX14: =IF(AW14>=AW13,AW14-AW13,0) -> 681 | AY14: 230943 | AZ14: =IF(AY14>=AY13,AY14-AY13,0) -> 8 | BA14: 20530442 | BB14: =IF(BA14>=BA13,BA14-BA13,0) -> 3823 | BC14: 626843 | BD14: =IF(BC14>=BC13,BC14-BC13,0) -> 184 | BE14: 42126 | BF14: =IF(BE14>=BE13,BE14-BE13,0) -> 201 | BG14: 25784246 | BH14: =IF(BG14>=BG13,BG14-BG13,0)-(0.45*BN14)-(0.45*BP14)-BR14 -> 4679.7 | BI14: =AP14+AR14+AT14+AV14+AX14+AZ14+BB14+BD14+BF14+BH14 -> 10152.829 | BJ14: =BI14+AN14 -> 18452.099 | BK14: 1483403 | BL14: =IF(BK14>=BK13,BK14-BK13,0) -> 219 | BM14: 4241760 | BN14: =IF(BM14>=BM13,BM14-BM13,0) -> 1566 | BO14: 443408 | BP14: =IF(BO14>=BO13,BO14-BO13,0) -> 88 | BQ14: 555010 | BR14: =IF(BQ14>=BQ13,BQ14-BQ13,0) -> 102 | BS14: =J14+Q14+AN14+BI14 -> 24871.21 | BT14: 252 | BU14: =IF(BS14>0,BS14/BT13,0) -> 100.28714 | BW14: =IF(BS14>0,BS14/BV14,0) -> #DIV/0! | BX14: =((BS14-Q14)*$BZ$1)+(Q14*$BR$1) -> 28804.392 | BY14: =IF(BX14>0,BX14/BT13,0) -> 116.14674 | BZ14: =IF(BX14>0,BX14/BV14,0) -> #DIV/0!
A15: 10 | C15: =IF(+B15-B14>0,B15-B14,(B15-B14)>0)*800 -> 0 | E15: =IF(+D15-D14>0,D15-D14,(D15-D14)>0)*80 -> 0 | G15: =IF(+F15-F14>0,F15-F14,(F15-F14)>0)*10 -> 0 | I15: 25298387 | J15: =IF(I15>=I14,I15-I14,0) -> 5969.1111 | K15: =M15+O15 -> 3773 | L15: 172623 | M15: =IF(L15>=L14,L15-L14,0) -> 1946 | N15: 208610 | O15: =IF(N15>=N14,N15-N14,0) -> 1827 | P15: 226297.67 | Q15: =IF(P15>=P14,P15-P14,0)*30 -> 530 | R15: 218840.33 | S15: =IF(R15>=R14,R15-R14,0) -> 141.33333 | T15: 399343.33 | U15: =IF(T15>=T14,T15-T14,0) -> 244.33333 | V15: 518564 | W15: =IF(V15>=V14,V15-V14,0)*0.53 -> 1984.85 | X15: 758238 | Y15: =IF(X15>=X14,X15-X14,0)*0.53 -> 0 | Z15: 732741.67 | AA15: =IF(Z15>=Z14,Z15-Z14,0)*0.53 -> 4059.6233 | AB15: 69387 | AC15: =IF(AB15>=AB14,AB15-AB14,0)*0.53 -> 0 | AD15: 860642.33 | AE15: =IF(AD15>=AD14,AD15-AD14,0)*0.53 -> 29.326667 | AF15: 1005155.7 | AG15: =IF(AF15>=AF14,AF15-AF14,0)*0.53 -> 924.67333 | AH15: 374263.33 | AI15: =IF(AH15>=AH14,AH15-AH14,0)*0.53 -> 540.77667 | AJ15: 244396 | AK15: =IF(AJ15>=AJ14,AJ15-AJ14,0)*0.53 -> 2986.55 | AL15: 556461 | AM15: =IF(AL15>=AL14,AL15-AL14,0)*0.53 -> 116.07 | AN15: =W15+Y15+AA15+AC15+AE15+AG15+AI15+AK15+AM15 -> 10641.87 | AO15: 8074135.3 | AP15: =IF(AO15>=AO14,AO15-AO14,0)*0.1125 -> 253.1625 | AQ15: 739216 | AR15: =IF(AQ15>=AQ14,AQ15-AQ14,0) -> 168 | AS15: 6155.1667 | AT15: =IF(AS15>=AS14,AS15-AS14,0) -> 166.5 | AU15: 823588 | AV15: =IF(AU15>=AU14,AU15-AU14,0) -> 40 | AW15: 2835854 | AX15: =IF(AW15>=AW14,AW15-AW14,0) -> 845 | AY15: 230953.67 | AZ15: =IF(AY15>=AY14,AY15-AY14,0) -> 10.666667 | BA15: 20535220 | BB15: =IF(BA15>=BA14,BA15-BA14,0) -> 4778.3333 | BC15: 627060.33 | BD15: =IF(BC15>=BC14,BC15-BC14,0) -> 217.33333 | BE15: 42226.333 | BF15: =IF(BE15>=BE14,BE15-BE14,0) -> 100.33333 | BG15: 25790603 | BH15: =IF(BG15>=BG14,BG15-BG14,0)-(0.45*BN15)-(0.45*BP15)-BR15 -> 5481.3 | BI15: =AP15+AR15+AT15+AV15+AX15+AZ15+BB15+BD15+BF15+BH15 -> 12060.629 | BJ15: =BI15+AN15 -> 22702.499 | BK15: 1483669.3 | BL15: =IF(BK15>=BK14,BK15-BK14,0) -> 266.33333 | BM15: 4243326 | BN15: =IF(BM15>=BM14,BM15-BM14,0) -> 1566 | BO15: 443514.67 | BP15: =IF(BO15>=BO14,BO15-BO14,0) -> 106.66667 | BQ15: 555133.33 | BR15: =IF(BQ15>=BQ14,BQ15-BQ14,0) -> 123.33333 | BS15: =J15+Q15+AN15+BI15 -> 29201.61 | BT15: 246 | BU15: =IF(BS15>0,BS15/BT14,0) -> 115.87941 | BW15: =IF(BS15>0,BS15/BV15,0) -> #DIV/0! | BX15: =((BS15-Q15)*$BZ$1)+(Q15*$BR$1) -> 33820.352 | BY15: =IF(BX15>0,BX15/BT14,0) -> 134.20775 | BZ15: =IF(BX15>0,BX15/BV15,0) -> #DIV/0!
A16: 11 | C16: =IF(+B16-B15>0,B16-B15,(B16-B15)>0)*800 -> 0 | E16: =IF(+D16-D15>0,D16-D15,(D16-D15)>0)*80 -> 0 | G16: =IF(+F16-F15>0,F16-F15,(F16-F15)>0)*10 -> 0 | H16: 61 | I16: 25304356 | J16: =IF(I16>=I15,I16-I15,0) -> 5969.1111 | K16: =M16+O16 -> 3190 | L16: 174448 | M16: =IF(L16>=L15,L16-L15,0) -> 1825 | N16: 209975 | O16: =IF(N16>=N15,N16-N15,0) -> 1365 | P16: 226314 | Q16: =IF(P16>=P15,P16-P15,0)*30 -> 490 | R16: 218980 | S16: =IF(R16>=R15,R16-R15,0) -> 139.66667 | T16: 399618 | U16: =IF(T16>=T15,T16-T15,0) -> 274.66667 | V16: 525866 | W16: =IF(V16>=V15,V16-V15,0)*0.53 -> 3870.06 | X16: 758238 | Y16: =IF(X16>=X15,X16-X15,0)*0.53 -> 0 | Z16: 739458 | AA16: =IF(Z16>=Z15,Z16-Z15,0)*0.53 -> 3559.6567 | AB16: 69387 | AC16: =IF(AB16>=AB15,AB16-AB15,0)*0.53 -> 0 | AD16: 860642.33 | AE16: =IF(AD16>=AD15,AD16-AD15,0)*0.53 -> 0 | AF16: 1005130 | AG16: =IF(AF16>=AF15,AF16-AF15,0)*0.53 -> 0 | AH16: 375146 | AI16: =IF(AH16>=AH15,AH16-AH15,0)*0.53 -> 467.81333 | AJ16: 250961 | AK16: =IF(AJ16>=AJ15,AJ16-AJ15,0)*0.53 -> 3479.45 | AL16: 556658 | AM16: =IF(AL16>=AL15,AL16-AL15,0)*0.53 -> 104.41 | AN16: =W16+Y16+AA16+AC16+AE16+AG16+AI16+AK16+AM16 -> 11481.39 | AO16: 8076539 | AP16: =IF(AO16>=AO15,AO16-AO15,0)*0.1125 -> 270.4125 | AQ16: 739369 | AR16: =IF(AQ16>=AQ15,AQ16-AQ15,0) -> 153 | AS16: 6236 | AT16: =IF(AS16>=AS15,AS16-AS15,0) -> 80.833333 | AU16: 823657 | AV16: =IF(AU16>=AU15,AU16-AU15,0) -> 69 | AW16: 2836686 | AX16: =IF(AW16>=AW15,AW16-AW15,0) -> 832 | AY16: 230965 | AZ16: =IF(AY16>=AY15,AY16-AY15,0) -> 11.333333 | BA16: 20540729 | BB16: =IF(BA16>=BA15,BA16-BA15,0) -> 5508.6667 | BC16: 627312 | BD16: =IF(BC16>=BC15,BC16-BC15,0) -> 251.66667 | BE16: 42265 | BF16: =IF(BE16>=BE15,BE16-BE15,0) -> 38.666667 | BG16: 25798756 | BH16: =IF(BG16>=BG15,BG16-BG15,0)-(0.45*BN16)-(0.45*BP16)-BR16 -> 7703.65 | BI16: =AP16+AR16+AT16+AV16+AX16+AZ16+BB16+BD16+BF16+BH16 -> 14919.229 | BJ16: =BI16+AN16 -> 26400.619 | BK16: 1483967 | BL16: =IF(BK16>=BK15,BK16-BK15,0) -> 297.66667 | BM16: 4243875 | BN16: =IF(BM16>=BM15,BM16-BM15,0) -> 549 | BO16: 443662 | BP16: =IF(BO16>=BO15,BO16-BO15,0) -> 147.33333 | BQ16: 555269 | BR16: =IF(BQ16>=BQ15,BQ16-BQ15,0) -> 135.66667 | BS16: =J16+Q16+AN16+BI16 -> 32859.73 | BT16: 206 | BU16: =IF(BS16>0,BS16/BT15,0) -> 133.57614 | BW16: =IF(BS16>0,BS16/BV16,0) -> #DIV/0! | BX16: =((BS16-Q16)*$BZ$1)+(Q16*$BR$1) -> 38009.19 | BY16: =IF(BX16>0,BX16/BT15,0) -> 154.5089 | BZ16: =IF(BX16>0,BX16/BV16,0) -> #DIV/0!
A17: 12 | C17: =IF(+B17-B16>0,B17-B16,(B17-B16)>0)*800 -> 0 | E17: =IF(+D17-D16>0,D17-D16,(D17-D16)>0)*80 -> 0 | G17: =IF(+F17-F16>0,F17-F16,(F17-F16)>0)*10 -> 0 | I17: 25310325 | J17: =IF(I17>=I16,I17-I16,0) -> 5969.1111 | K17: =M17+O17 -> 4248 | L17: 176584 | M17: =IF(L17>=L16,L17-L16,0) -> 2136 | N17: 212087 | O17: =IF(N17>=N16,N17-N16,0) -> 2112 | P17: 226331 | Q17: =IF(P17>=P16,P17-P16,0)*30 -> 510 | R17: 219132 | S17: =IF(R17>=R16,R17-R16,0) -> 152 | T17: 399901 | U17: =IF(T17>=T16,T17-T16,0) -> 283 | V17: 533168 | W17: =IF(V17>=V16,V17-V16,0)*0.53 -> 3870.06 | X17: 758238 | Y17: =IF(X17>=X16,X17-X16,0)*0.53 -> 0 | Z17: 746788 | AA17: =IF(Z17>=Z16,Z17-Z16,0)*0.53 -> 3884.9 | AB17: 69387 | AC17: =IF(AB17>=AB16,AB17-AB16,0)*0.53 -> 0 | AD17: 860659 | AE17: =IF(AD17>=AD16,AD17-AD16,0)*0.53 -> 8.8333333 | AF17: 1005440 | AG17: =IF(AF17>=AF16,AF17-AF16,0)*0.53 -> 164.3 | AH17: 376215 | AI17: =IF(AH17>=AH16,AH17-AH16,0)*0.53 -> 566.57 | AJ17: 258166 | AK17: =IF(AJ17>=AJ16,AJ17-AJ16,0)*0.53 -> 3818.65 | AL17: 556883 | AM17: =IF(AL17>=AL16,AL17-AL16,0)*0.53 -> 119.25 | AN17: =W17+Y17+AA17+AC17+AE17+AG17+AI17+AK17+AM17 -> 12432.563 | AO17: 8078827 | AP17: =IF(AO17>=AO16,AO17-AO16,0)*0.1125 -> 257.4 | AQ17: 739635 | AR17: =IF(AQ17>=AQ16,AQ17-AQ16,0) -> 266 | AS17: 6373.9444 | AT17: =IF(AS17>=AS16,AS17-AS16,0) -> 137.94444 | AU17: 823712 | AV17: =IF(AU17>=AU16,AU17-AU16,0) -> 55 | AW17: 2837570 | AX17: =IF(AW17>=AW16,AW17-AW16,0) -> 884 | AY17: 230977 | AZ17: =IF(AY17>=AY16,AY17-AY16,0) -> 12 | BA17: 20546557 | BB17: =IF(BA17>=BA16,BA17-BA16,0) -> 5828 | BC17: 627552 | BD17: =IF(BC17>=BC16,BC17-BC16,0) -> 240 | BE17: 42335 | BF17: =IF(BE17>=BE16,BE17-BE16,0) -> 70 | BG17: 25806267 | BH17: =IF(BG17>=BG16,BG17-BG16,0)-(0.45*BN17)-(0.45*BP17)-BR17 -> 6664.05 | BI17: =AP17+AR17+AT17+AV17+AX17+AZ17+BB17+BD17+BF17+BH17 -> 14414.394 | BJ17: =BI17+AN17 -> 26846.958 | BK17: 1484232 | BL17: =IF(BK17>=BK16,BK17-BK16,0) -> 265 | BM17: 4245362 | BN17: =IF(BM17>=BM16,BM17-BM16,0) -> 1487 | BO17: 443746 | BP17: =IF(BO17>=BO16,BO17-BO16,0) -> 84 | BQ17: 555409 | BR17: =IF(BQ17>=BQ16,BQ17-BQ16,0) -> 140 | BS17: =J17+Q17+AN17+BI17 -> 33326.069 | BT17: 174 | BU17: =IF(BS17>0,BS17/BT16,0) -> 161.77703 | BW17: =IF(BS17>0,BS17/BV17,0) -> #DIV/0! | BX17: =((BS17-Q17)*$BZ$1)+(Q17*$BR$1) -> 38554.479 | BY17: =IF(BX17>0,BX17/BT16,0) -> 187.15767 | BZ17: =IF(BX17>0,BX17/BV17,0) -> #DIV/0!
A18: 13 | C18: =IF(+B18-B17>0,B18-B17,(B18-B17)>0)*800 -> 0 | E18: =IF(+D18-D17>0,D18-D17,(D18-D17)>0)*80 -> 0 | G18: =IF(+F18-F17>0,F18-F17,(F18-F17)>0)*10 -> 0 | H18: 62 | I18: 25316294 | J18: =IF(I18>=I17,I18-I17,0) -> 5969.1111 | K18: =M18+O18 -> 3683 | L18: 178414 | M18: =IF(L18>=L17,L18-L17,0) -> 1830 | N18: 213940 | O18: =IF(N18>=N17,N18-N17,0) -> 1853 | P18: 226348 | Q18: =IF(P18>=P17,P18-P17,0)*30 -> 510 | R18: 219262 | S18: =IF(R18>=R17,R18-R17,0) -> 130 | T18: 400134 | U18: =IF(T18>=T17,T18-T17,0) -> 233 | V18: 534878 | W18: =IF(V18>=V17,V18-V17,0)*0.53 -> 906.3 | X18: 758238 | Y18: =IF(X18>=X17,X18-X17,0)*0.53 -> 0 | Z18: 753499 | AA18: =IF(Z18>=Z17,Z18-Z17,0)*0.53 -> 3556.83 | AB18: 69387 | AC18: =IF(AB18>=AB17,AB18-AB17,0)*0.53 -> 0 | AD18: 860680 | AE18: =IF(AD18>=AD17,AD18-AD17,0)*0.53 -> 11.13 | AF18: 1006630 | AG18: =IF(AF18>=AF17,AF18-AF17,0)*0.53 -> 630.7 | AH18: 377056 | AI18: =IF(AH18>=AH17,AH18-AH17,0)*0.53 -> 445.73 | AJ18: 264046 | AK18: =IF(AJ18>=AJ17,AJ18-AJ17,0)*0.53 -> 3116.4 | AL18: 557077 | AM18: =IF(AL18>=AL17,AL18-AL17,0)*0.53 -> 102.82 | AN18: =W18+Y18+AA18+AC18+AE18+AG18+AI18+AK18+AM18 -> 8769.91 | AO18: 8080551 | AP18: =IF(AO18>=AO17,AO18-AO17,0)*0.1125 -> 193.95 | AQ18: 739779 | AR18: =IF(AQ18>=AQ17,AQ18-AQ17,0) -> 144 | AS18: 6680 | AT18: =IF(AS18>=AS17,AS18-AS17,0) -> 306.05556 | AU18: 823757 | AV18: =IF(AU18>=AU17,AU18-AU17,0) -> 45 | AW18: 2838337 | AX18: =IF(AW18>=AW17,AW18-AW17,0) -> 767 | AY18: 230987 | AZ18: =IF(AY18>=AY17,AY18-AY17,0) -> 10 | BA18: 20551048 | BB18: =IF(BA18>=BA17,BA18-BA17,0) -> 4491 | BC18: 627751 | BD18: =IF(BC18>=BC17,BC18-BC17,0) -> 199 | BE18: 42400 | BF18: =IF(BE18>=BE17,BE18-BE17,0) -> 65 | BG18: 25812636 | BH18: =IF(BG18>=BG17,BG18-BG17,0)-(0.45*BN18)-(0.45*BP18)-BR18 -> 5618.95 | BI18: =AP18+AR18+AT18+AV18+AX18+AZ18+BB18+BD18+BF18+BH18 -> 11839.956 | BJ18: =BI18+AN18 -> 20609.866 | BK18: 1484429 | BL18: =IF(BK18>=BK17,BK18-BK17,0) -> 197 | BM18: 4246630 | BN18: =IF(BM18>=BM17,BM18-BM17,0) -> 1268 | BO18: 443847 | BP18: =IF(BO18>=BO17,BO18-BO17,0) -> 101 | BQ18: 555543 | BR18: =IF(BQ18>=BQ17,BQ18-BQ17,0) -> 134 | BS18: =J18+Q18+AN18+BI18 -> 27088.977 | BT18: 162 | BU18: =IF(BS18>0,BS18/BT17,0) -> 155.68377 | BW18: =IF(BS18>0,BS18/BV18,0) -> #DIV/0! | BX18: =((BS18-Q18)*$BZ$1)+(Q18*$BR$1) -> 31381.823 | BY18: =IF(BX18>0,BX18/BT17,0) -> 180.35531 | BZ18: =IF(BX18>0,BX18/BV18,0) -> #DIV/0!
A19: 14 | C19: =IF(+B19-B18>0,B19-B18,(B19-B18)>0)*800 -> 0 | E19: =IF(+D19-D18>0,D19-D18,(D19-D18)>0)*80 -> 0 | G19: =IF(+F19-F18>0,F19-F18,(F19-F18)>0)*10 -> 0 | I19: 25322263 | J19: =IF(I19>=I18,I19-I18,0) -> 5969.1111 | K19: =M19+O19 -> 3870 | L19: 180433 | M19: =IF(L19>=L18,L19-L18,0) -> 2019 | N19: 215791 | O19: =IF(N19>=N18,N19-N18,0) -> 1851 | P19: 226367 | Q19: =IF(P19>=P18,P19-P18,0)*30 -> 570 | R19: 219410 | S19: =IF(R19>=R18,R19-R18,0) -> 148 | T19: 400405 | U19: =IF(T19>=T18,T19-T18,0) -> 271 | V19: 537153 | W19: =IF(V19>=V18,V19-V18,0)*0.53 -> 1205.75 | X19: 758048 | Y19: =IF(X19>=X18,X19-X18,0)*0.53 -> 0 | Z19: 759048 | AA19: =IF(Z19>=Z18,Z19-Z18,0)*0.53 -> 2940.97 | AB19: 70768 | AC19: =IF(AB19>=AB18,AB19-AB18,0)*0.53 -> 731.93 | AD19: 860705 | AE19: =IF(AD19>=AD18,AD19-AD18,0)*0.53 -> 13.25 | AF19: 1007983 | AG19: =IF(AF19>=AF18,AF19-AF18,0)*0.53 -> 717.09 | AH19: 377982 | AI19: =IF(AH19>=AH18,AH19-AH18,0)*0.53 -> 490.78 | AJ19: 270905 | AK19: =IF(AJ19>=AJ18,AJ19-AJ18,0)*0.53 -> 3635.27 | AL19: 557289 | AM19: =IF(AL19>=AL18,AL19-AL18,0)*0.53 -> 112.36 | AN19: =W19+Y19+AA19+AC19+AE19+AG19+AI19+AK19+AM19 -> 9847.4 | AO19: 8082560 | AP19: =IF(AO19>=AO18,AO19-AO18,0)*0.1125 -> 226.0125 | AQ19: 739944 | AR19: =IF(AQ19>=AQ18,AQ19-AQ18,0) -> 165 | AS19: 6847 | AT19: =IF(AS19>=AS18,AS19-AS18,0) -> 167 | AU19: 823798 | AV19: =IF(AU19>=AU18,AU19-AU18,0) -> 41 | AW19: 2839169 | AX19: =IF(AW19>=AW18,AW19-AW18,0) -> 832 | AY19: 230998 | AZ19: =IF(AY19>=AY18,AY19-AY18,0) -> 11 | BA19: 20556233 | BB19: =IF(BA19>=BA18,BA19-BA18,0) -> 5185 | BC19: 627977 | BD19: =IF(BC19>=BC18,BC19-BC18,0) -> 226 | BE19: 42463 | BF19: =IF(BE19>=BE18,BE19-BE18,0) -> 63 | BG19: 25819849 | BH19: =IF(BG19>=BG18,BG19-BG18,0)-(0.45*BN19)-(0.45*BP19)-BR19 -> 6394.7 | BI19: =AP19+AR19+AT19+AV19+AX19+AZ19+BB19+BD19+BF19+BH19 -> 13310.712 | BJ19: =BI19+AN19 -> 23158.113 | BK19: 1484688 | BL19: =IF(BK19>=BK18,BK19-BK18,0) -> 259 | BM19: 4248011 | BN19: =IF(BM19>=BM18,BM19-BM18,0) -> 1381 | BO19: 443960 | BP19: =IF(BO19>=BO18,BO19-BO18,0) -> 113 | BQ19: 555689 | BR19: =IF(BQ19>=BQ18,BQ19-BQ18,0) -> 146 | BS19: =J19+Q19+AN19+BI19 -> 29697.224 | BT19: 207 | BU19: =IF(BS19>0,BS19/BT18,0) -> 183.3162 | BW19: =IF(BS19>0,BS19/BV19,0) -> #DIV/0! | BX19: =((BS19-Q19)*$BZ$1)+(Q19*$BR$1) -> 34408.307 | BY19: =IF(BX19>0,BX19/BT18,0) -> 212.39696 | BZ19: =IF(BX19>0,BX19/BV19,0) -> #DIV/0!
A20: 15 | C20: =IF(+B20-B19>0,B20-B19,(B20-B19)>0)*800 -> 0 | E20: =IF(+D20-D19>0,D20-D19,(D20-D19)>0)*80 -> 0 | G20: =IF(+F20-F19>0,F20-F19,(F20-F19)>0)*10 -> 0 | H20: 63 | I20: 25328233 | J20: =IF(I20>=I19,I20-I19,0) -> 5969.1111 | K20: =M20+O20 -> 3614 | L20: 182393 | M20: =IF(L20>=L19,L20-L19,0) -> 1960 | N20: 217445 | O20: =IF(N20>=N19,N20-N19,0) -> 1654 | P20: 226384 | Q20: =IF(P20>=P19,P20-P19,0)*30 -> 510 | R20: 219548 | S20: =IF(R20>=R19,R20-R19,0) -> 138 | T20: 400661 | U20: =IF(T20>=T19,T20-T19,0) -> 256 | V20: 540440 | W20: =IF(V20>=V19,V20-V19,0)*0.53 -> 1742.11 | X20: 758238 | Y20: =IF(X20>=X19,X20-X19,0)*0.53 -> 100.7 | Z20: 762604 | AA20: =IF(Z20>=Z19,Z20-Z19,0)*0.53 -> 1884.68 | AB20: 74541 | AC20: =IF(AB20>=AB19,AB20-AB19,0)*0.53 -> 1999.69 | AD20: 860728 | AE20: =IF(AD20>=AD19,AD20-AD19,0)*0.53 -> 12.19 | AF20: 1008528 | AG20: =IF(AF20>=AF19,AF20-AF19,0)*0.53 -> 288.85 | AH20: 378723 | AI20: =IF(AH20>=AH19,AH20-AH19,0)*0.53 -> 392.73 | AJ20: 277517 | AK20: =IF(AJ20>=AJ19,AJ20-AJ19,0)*0.53 -> 3504.36 | AL20: 557504 | AM20: =IF(AL20>=AL19,AL20-AL19,0)*0.53 -> 113.95 | AN20: =W20+Y20+AA20+AC20+AE20+AG20+AI20+AK20+AM20 -> 10039.26 | AO20: 8084706 | AP20: =IF(AO20>=AO19,AO20-AO19,0)*0.1125 -> 241.425 | AQ20: 740124 | AR20: =IF(AQ20>=AQ19,AQ20-AQ19,0) -> 180 | AS20: 7065 | AT20: =IF(AS20>=AS19,AS20-AS19,0) -> 218 | AU20: 823844 | AV20: =IF(AU20>=AU19,AU20-AU19,0) -> 46 | AW20: 2839952 | AX20: =IF(AW20>=AW19,AW20-AW19,0) -> 783 | AY20: 231009 | AZ20: =IF(AY20>=AY19,AY20-AY19,0) -> 11 | BA20: 20561609 | BB20: =IF(BA20>=BA19,BA20-BA19,0) -> 5376 | BC20: 628218 | BD20: =IF(BC20>=BC19,BC20-BC19,0) -> 241 | BE20: 42528 | BF20: =IF(BE20>=BE19,BE20-BE19,0) -> 65 | BG20: 25827228 | BH20: =IF(BG20>=BG19,BG20-BG19,0)-(0.45*BN20)-(0.45*BP20)-BR20 -> 6548.55 | BI20: =AP20+AR20+AT20+AV20+AX20+AZ20+BB20+BD20+BF20+BH20 -> 13709.975 | BJ20: =BI20+AN20 -> 23749.235 | BK20: 1484887 | BL20: =IF(BK20>=BK19,BK20-BK19,0) -> 199 | BM20: 4249452 | BN20: =IF(BM20>=BM19,BM20-BM19,0) -> 1441 | BO20: 444080 | BP20: =IF(BO20>=BO19,BO20-BO19,0) -> 120 | BQ20: 555817 | BR20: =IF(BQ20>=BQ19,BQ20-BQ19,0) -> 128 | BS20: =J20+Q20+AN20+BI20 -> 30228.346 | BT20: 248 | BU20: =IF(BS20>0,BS20/BT20,0) -> 121.88849 | BW20: =IF(BS20>0,BS20/BV20,0) -> #DIV/0! | BX20: =((BS20-Q20)*$BZ$1)+(Q20*$BR$1) -> 34992.098 | BY20: =IF(BX20>0,BX20/BT20,0) -> 141.09717 | BZ20: =IF(BX20>0,BX20/BV20,0) -> #DIV/0!
A21: 16 | C21: =IF(+B21-B20>0,B21-B20,(B21-B20)>0)*800 -> 0 | E21: =IF(+D21-D20>0,D21-D20,(D21-D20)>0)*80 -> 0 | G21: =IF(+F21-F20>0,F21-F20,(F21-F20)>0)*10 -> 0 | I21: 25334202 | J21: =IF(I21>=I20,I21-I20,0) -> 5969.1111 | K21: =M21+O21 -> 3616 | L21: 184223 | M21: =IF(L21>=L20,L21-L20,0) -> 1830 | N21: 219231 | O21: =IF(N21>=N20,N21-N20,0) -> 1786 | P21: 226401 | Q21: =IF(P21>=P20,P21-P20,0)*30 -> 510 | R21: 219691 | S21: =IF(R21>=R20,R21-R20,0) -> 143 | T21: 400918 | U21: =IF(T21>=T20,T21-T20,0) -> 257 | V21: 542721 | W21: =IF(V21>=V20,V21-V20,0)*0.53 -> 1208.93 | X21: 758238 | Y21: =IF(X21>=X20,X21-X20,0)*0.53 -> 0 | Z21: 762604 | AA21: =IF(Z21>=Z20,Z21-Z20,0)*0.53 -> 0 | AB21: 81950 | AC21: =IF(AB21>=AB20,AB21-AB20,0)*0.53 -> 3926.77 | AD21: 860752 | AE21: =IF(AD21>=AD20,AD21-AD20,0)*0.53 -> 12.72 | AF21: 1008550 | AG21: =IF(AF21>=AF20,AF21-AF20,0)*0.53 -> 11.66 | AH21: 379429 | AI21: =IF(AH21>=AH20,AH21-AH20,0)*0.53 -> 374.18 | AJ21: 283663 | AK21: =IF(AJ21>=AJ20,AJ21-AJ20,0)*0.53 -> 3257.38 | AL21: 557712 | AM21: =IF(AL21>=AL20,AL21-AL20,0)*0.53 -> 110.24 | AN21: =W21+Y21+AA21+AC21+AE21+AG21+AI21+AK21+AM21 -> 8901.88 | AO21: 8086834 | AP21: =IF(AO21>=AO20,AO21-AO20,0)*0.1125 -> 239.4 | AQ21: 740305 | AR21: =IF(AQ21>=AQ20,AQ21-AQ20,0) -> 181 | AS21: 7223 | AT21: =IF(AS21>=AS20,AS21-AS20,0) -> 158 | AU21: 823900 | AV21: =IF(AU21>=AU20,AU21-AU20,0) -> 56 | AW21: 2840766 | AX21: =IF(AW21>=AW20,AW21-AW20,0) -> 814 | AY21: 231020 | AZ21: =IF(AY21>=AY20,AY21-AY20,0) -> 11 | BA21: 20566816 | BB21: =IF(BA21>=BA20,BA21-BA20,0) -> 5207 | BC21: 628451 | BD21: =IF(BC21>=BC20,BC21-BC20,0) -> 233 | BE21: 42594 | BF21: =IF(BE21>=BE20,BE21-BE20,0) -> 66 | BG21: 25833851 | BH21: =IF(BG21>=BG20,BG21-BG20,0)-(0.45*BN21)-(0.45*BP21)-BR21 -> 5818.35 | BI21: =AP21+AR21+AT21+AV21+AX21+AZ21+BB21+BD21+BF21+BH21 -> 12783.75 | BJ21: =BI21+AN21 -> 21685.63 | BK21: 1484992 | BL21: =IF(BK21>=BK20,BK21-BK20,0) -> 105 | BM21: 4250824 | BN21: =IF(BM21>=BM20,BM21-BM20,0) -> 1372 | BO21: 444185 | BP21: =IF(BO21>=BO20,BO21-BO20,0) -> 105 | BQ21: 555957 | BR21: =IF(BQ21>=BQ20,BQ21-BQ20,0) -> 140 | BS21: =J21+Q21+AN21+BI21 -> 28164.741 | BT21: 248 | BU21: =IF(BS21>0,BS21/BT21,0) -> 113.5675 | BW21: =IF(BS21>0,BS21/BV21,0) -> #DIV/0! | BX21: =((BS21-Q21)*$BZ$1)+(Q21*$BR$1) -> 32618.952 | BY21: =IF(BX21>0,BX21/BT21,0) -> 131.52803 | BZ21: =IF(BX21>0,BX21/BV21,0) -> #DIV/0!
A22: 17 | C22: =IF(+B22-B21>0,B22-B21,(B22-B21)>0)*800 -> 0 | E22: =IF(+D22-D21>0,D22-D21,(D22-D21)>0)*80 -> 0 | G22: =IF(+F22-F21>0,F22-F21,(F22-F21)>0)*10 -> 0 | H22: 64 | I22: 25340171 | J22: =IF(I22>=I21,I22-I21,0) -> 5969.1111 | K22: =M22+O22 -> 3825 | L22: 186121 | M22: =IF(L22>=L21,L22-L21,0) -> 1898 | N22: 221158 | O22: =IF(N22>=N21,N22-N21,0) -> 1927 | P22: 226418 | Q22: =IF(P22>=P21,P22-P21,0)*30 -> 510 | R22: 219830 | S22: =IF(R22>=R21,R22-R21,0) -> 139 | T22: 401171 | U22: =IF(T22>=T21,T22-T21,0) -> 253 | V22: 546789 | W22: =IF(V22>=V21,V22-V21,0)*0.53 -> 2156.04 | X22: 758238 | Y22: =IF(X22>=X21,X22-X21,0)*0.53 -> 0 | Z22: 762604 | AA22: =IF(Z22>=Z21,Z22-Z21,0)*0.53 -> 0 | AB22: 88706 | AC22: =IF(AB22>=AB21,AB22-AB21,0)*0.53 -> 3580.68 | AD22: 860773 | AE22: =IF(AD22>=AD21,AD22-AD21,0)*0.53 -> 11.13 | AF22: 1008570 | AG22: =IF(AF22>=AF21,AF22-AF21,0)*0.53 -> 10.6 | AH22: 380224 | AI22: =IF(AH22>=AH21,AH22-AH21,0)*0.53 -> 421.35 | AJ22: 289399 | AK22: =IF(AJ22>=AJ21,AJ22-AJ21,0)*0.53 -> 3040.08 | AL22: 557917 | AM22: =IF(AL22>=AL21,AL22-AL21,0)*0.53 -> 108.65 | AN22: =W22+Y22+AA22+AC22+AE22+AG22+AI22+AK22+AM22 -> 9328.53 | AO22: 8089224 | AP22: =IF(AO22>=AO21,AO22-AO21,0)*0.1125 -> 268.875 | AQ22: 740571 | AR22: =IF(AQ22>=AQ21,AQ22-AQ21,0) -> 266 | AS22: 7407 | AT22: =IF(AS22>=AS21,AS22-AS21,0) -> 184 | AU22: 823957 | AV22: =IF(AU22>=AU21,AU22-AU21,0) -> 57 | AW22: 2841595 | AX22: =IF(AW22>=AW21,AW22-AW21,0) -> 829 | AY22: 231031 | AZ22: =IF(AY22>=AY21,AY22-AY21,0) -> 11 | BA22: 20572078 | BB22: =IF(BA22>=BA21,BA22-BA21,0) -> 5262 | BC22: 628709 | BD22: =IF(BC22>=BC21,BC22-BC21,0) -> 258 | BE22: 42661 | BF22: =IF(BE22>=BE21,BE22-BE21,0) -> 67 | BG22: 25840550 | BH22: =IF(BG22>=BG21,BG22-BG21,0)-(0.45*BN22)-(0.45*BP22)-BR22 -> 5913.1 | BI22: =AP22+AR22+AT22+AV22+AX22+AZ22+BB22+BD22+BF22+BH22 -> 13115.975 | BJ22: =BI22+AN22 -> 22444.505 | BK22: 1485099 | BL22: =IF(BK22>=BK21,BK22-BK21,0) -> 107 | BM22: 4252197 | BN22: =IF(BM22>=BM21,BM22-BM21,0) -> 1373 | BO22: 444294 | BP22: =IF(BO22>=BO21,BO22-BO21,0) -> 109 | BQ22: 556076 | BR22: =IF(BQ22>=BQ21,BQ22-BQ21,0) -> 119 | BS22: =J22+Q22+AN22+BI22 -> 28923.616 | BT22: 244 | BU22: =IF(BS22>0,BS22/BT22,0) -> 118.53941 | BW22: =IF(BS22>0,BS22/BV22,0) -> #DIV/0! | BX22: =((BS22-Q22)*$BZ$1)+(Q22*$BR$1) -> 33491.659 | BY22: =IF(BX22>0,BX22/BT22,0) -> 137.2609 | BZ22: =IF(BX22>0,BX22/BV22,0) -> #DIV/0!
A23: 18 | C23: =IF(+B23-B22>0,B23-B22,(B23-B22)>0)*800 -> 0 | E23: =IF(+D23-D22>0,D23-D22,(D23-D22)>0)*80 -> 0 | G23: =IF(+F23-F22>0,F23-F22,(F23-F22)>0)*10 -> 0 | I23: 25346132 | J23: =IF(I23>=I22,I23-I22,0) -> 5960.963 | K23: =M23+O23 -> 4240 | L23: 188254 | M23: =IF(L23>=L22,L23-L22,0) -> 2133 | N23: 223265 | O23: =IF(N23>=N22,N23-N22,0) -> 2107 | P23: 226435 | Q23: =IF(P23>=P22,P23-P22,0)*30 -> 510 | R23: 219983 | S23: =IF(R23>=R22,R23-R22,0) -> 153 | T23: 401447 | U23: =IF(T23>=T22,T23-T22,0) -> 276 | V23: 550567 | W23: =IF(V23>=V22,V23-V22,0)*0.53 -> 2002.34 | X23: 758238 | Y23: =IF(X23>=X22,X23-X22,0)*0.53 -> 0 | Z23: 762604 | AA23: =IF(Z23>=Z22,Z23-Z22,0)*0.53 -> 0 | AB23: 95299 | AC23: =IF(AB23>=AB22,AB23-AB22,0)*0.53 -> 3494.29 | AD23: 860798 | AE23: =IF(AD23>=AD22,AD23-AD22,0)*0.53 -> 13.25 | AF23: 1008593 | AG23: =IF(AF23>=AF22,AF23-AF22,0)*0.53 -> 12.19 | AH23: 380798 | AI23: =IF(AH23>=AH22,AH23-AH22,0)*0.53 -> 304.22 | AJ23: 295341 | AK23: =IF(AJ23>=AJ22,AJ23-AJ22,0)*0.53 -> 3149.26 | AL23: 558149 | AM23: =IF(AL23>=AL22,AL23-AL22,0)*0.53 -> 122.96 | AN23: =W23+Y23+AA23+AC23+AE23+AG23+AI23+AK23+AM23 -> 9098.51 | AO23: 8091410 | AP23: =IF(AO23>=AO22,AO23-AO22,0)*0.1125 -> 245.925 | AQ23: 740761 | AR23: =IF(AQ23>=AQ22,AQ23-AQ22,0) -> 190 | AS23: 7604 | AT23: =IF(AS23>=AS22,AS23-AS22,0) -> 197 | AU23: 824011 | AV23: =IF(AU23>=AU22,AU23-AU22,0) -> 54 | AW23: 2842445 | AX23: =IF(AW23>=AW22,AW23-AW22,0) -> 850 | AY23: 231043 | AZ23: =IF(AY23>=AY22,AY23-AY22,0) -> 12 | BA23: 20577974 | BB23: =IF(BA23>=BA22,BA23-BA22,0) -> 5896 | BC23: 628991 | BD23: =IF(BC23>=BC22,BC23-BC22,0) -> 282 | BE23: 42751 | BF23: =IF(BE23>=BE22,BE23-BE22,0) -> 90 | BG23: 25847872 | BH23: =IF(BG23>=BG22,BG23-BG22,0)-(0.45*BN23)-(0.45*BP23)-BR23 -> 6478.85 | BI23: =AP23+AR23+AT23+AV23+AX23+AZ23+BB23+BD23+BF23+BH23 -> 14295.775 | BJ23: =BI23+AN23 -> 23394.285 | BK23: 1485217 | BL23: =IF(BK23>=BK22,BK23-BK22,0) -> 118 | BM23: 4253666 | BN23: =IF(BM23>=BM22,BM23-BM22,0) -> 1469 | BO23: 444412 | BP23: =IF(BO23>=BO22,BO23-BO22,0) -> 118 | BQ23: 556205 | BR23: =IF(BQ23>=BQ22,BQ23-BQ22,0) -> 129 | BS23: =J23+Q23+AN23+BI23 -> 29865.248 | BT23: 228 | BU23: =IF(BS23>0,BS23/BT23,0) -> 130.98793 | BW23: =IF(BS23>0,BS23/BV23,0) -> #DIV/0! | BX23: =((BS23-Q23)*$BZ$1)+(Q23*$BR$1) -> 34574.535 | BY23: =IF(BX23>0,BX23/BT23,0) -> 151.6427 | BZ23: =IF(BX23>0,BX23/BV23,0) -> #DIV/0!
A24: 19 | C24: =IF(+B24-B23>0,B24-B23,(B24-B23)>0)*800 -> 0 | E24: =IF(+D24-D23>0,D24-D23,(D24-D23)>0)*80 -> 0 | G24: =IF(+F24-F23>0,F24-F23,(F24-F23)>0)*10 -> 0 | H24: 65 | I24: 25352125 | J24: =IF(I24>=I23,I24-I23,0) -> 5993.5556 | K24: =M24+O24 -> 3465 | L24: 190053 | M24: =IF(L24>=L23,L24-L23,0) -> 1799 | N24: 224931 | O24: =IF(N24>=N23,N24-N23,0) -> 1666 | P24: 226456 | Q24: =IF(P24>=P23,P24-P23,0)*30 -> 630 | R24: 220117 | S24: =IF(R24>=R23,R24-R23,0) -> 134 | T24: 401686 | U24: =IF(T24>=T23,T24-T23,0) -> 239 | V24: 553938 | W24: =IF(V24>=V23,V24-V23,0)*0.53 -> 1786.63 | X24: 763680 | Y24: =IF(X24>=X23,X24-X23,0)*0.53 -> 2884.26 | Z24: 762604 | AA24: =IF(Z24>=Z23,Z24-Z23,0)*0.53 -> 0 | AB24: 95505 | AC24: =IF(AB24>=AB23,AB24-AB23,0)*0.53 -> 109.18 | AD24: 860820 | AE24: =IF(AD24>=AD23,AD24-AD23,0)*0.53 -> 11.66 | AF24: 1008613 | AG24: =IF(AF24>=AF23,AF24-AF23,0)*0.53 -> 10.6 | AH24: 382428 | AI24: =IF(AH24>=AH23,AH24-AH23,0)*0.53 -> 863.9 | AJ24: 300787 | AK24: =IF(AJ24>=AJ23,AJ24-AJ23,0)*0.53 -> 2886.38 | AL24: 558347 | AM24: =IF(AL24>=AL23,AL24-AL23,0)*0.53 -> 104.94 | AN24: =W24+Y24+AA24+AC24+AE24+AG24+AI24+AK24+AM24 -> 8657.55 | AO24: 8093365 | AP24: =IF(AO24>=AO23,AO24-AO23,0)*0.1125 -> 219.9375 | AQ24: 740918 | AR24: =IF(AQ24>=AQ23,AQ24-AQ23,0) -> 157 | AS24: 7804 | AT24: =IF(AS24>=AS23,AS24-AS23,0) -> 200 | AU24: 824061 | AV24: =IF(AU24>=AU23,AU24-AU23,0) -> 50 | AW24: 2843196 | AX24: =IF(AW24>=AW23,AW24-AW23,0) -> 751 | AY24: 231053 | AZ24: =IF(AY24>=AY23,AY24-AY23,0) -> 10 | BA24: 20582750 | BB24: =IF(BA24>=BA23,BA24-BA23,0) -> 4776 | BC24: 629244 | BD24: =IF(BC24>=BC23,BC24-BC23,0) -> 253 | BE24: 42816 | BF24: =IF(BE24>=BE23,BE24-BE23,0) -> 65 | BG24: 25854505 | BH24: =IF(BG24>=BG23,BG24-BG23,0)-(0.45*BN24)-(0.45*BP24)-BR24 -> 5859.1 | BI24: =AP24+AR24+AT24+AV24+AX24+AZ24+BB24+BD24+BF24+BH24 -> 12341.038 | BJ24: =BI24+AN24 -> 20998.588 | BK24: 1485424 | BL24: =IF(BK24>=BK23,BK24-BK23,0) -> 207 | BM24: 4254987 | BN24: =IF(BM24>=BM23,BM24-BM23,0) -> 1321 | BO24: 444513 | BP24: =IF(BO24>=BO23,BO24-BO23,0) -> 101 | BQ24: 556339 | BR24: =IF(BQ24>=BQ23,BQ24-BQ23,0) -> 134 | BS24: =J24+Q24+AN24+BI24 -> 27622.143 | BT24: 203 | BU24: =IF(BS24>0,BS24/BT24,0) -> 136.06967 | BW24: =IF(BS24>0,BS24/BV24,0) -> #DIV/0! | BX24: =((BS24-Q24)*$BZ$1)+(Q24*$BR$1) -> 32048.965 | BY24: =IF(BX24>0,BX24/BT24,0) -> 157.87667 | BZ24: =IF(BX24>0,BX24/BV24,0) -> #DIV/0!
A25: 20 | C25: =IF(+B25-B24>0,B25-B24,(B25-B24)>0)*800 -> 0 | E25: =IF(+D25-D24>0,D25-D24,(D25-D24)>0)*80 -> 0 | G25: =IF(+F25-F24>0,F25-F24,(F25-F24)>0)*10 -> 0 | I25: 25358070 | J25: =IF(I25>=I24,I25-I24,0) -> 5944.6667 | K25: =M25+O25 -> 3690 | L25: 191932 | M25: =IF(L25>=L24,L25-L24,0) -> 1879 | N25: 226742 | O25: =IF(N25>=N24,N25-N24,0) -> 1811 | P25: 226473 | Q25: =IF(P25>=P24,P25-P24,0)*30 -> 510 | R25: 220260 | S25: =IF(R25>=R24,R25-R24,0) -> 143 | T25: 401949 | U25: =IF(T25>=T24,T25-T24,0) -> 263 | V25: 555227 | W25: =IF(V25>=V24,V25-V24,0)*0.53 -> 683.17 | X25: 771431 | Y25: =IF(X25>=X24,X25-X24,0)*0.53 -> 4108.03 | Z25: 762604 | AA25: =IF(Z25>=Z24,Z25-Z24,0)*0.53 -> 0 | AB25: 95505 | AC25: =IF(AB25>=AB24,AB25-AB24,0)*0.53 -> 0 | AD25: 860844 | AE25: =IF(AD25>=AD24,AD25-AD24,0)*0.53 -> 12.72 | AF25: 1008635 | AG25: =IF(AF25>=AF24,AF25-AF24,0)*0.53 -> 11.66 | AH25: 383558 | AI25: =IF(AH25>=AH24,AH25-AH24,0)*0.53 -> 598.9 | AJ25: 306974 | AK25: =IF(AJ25>=AJ24,AJ25-AJ24,0)*0.53 -> 3279.11 | AL25: 558557 | AM25: =IF(AL25>=AL24,AL25-AL24,0)*0.53 -> 111.3 | AN25: =W25+Y25+AA25+AC25+AE25+AG25+AI25+AK25+AM25 -> 8804.89 | AO25: 8095589 | AP25: =IF(AO25>=AO24,AO25-AO24,0)*0.1125 -> 250.2 | AQ25: 741112 | AR25: =IF(AQ25>=AQ24,AQ25-AQ24,0) -> 194 | AS25: 7986 | AT25: =IF(AS25>=AS24,AS25-AS24,0) -> 182 | AU25: 824116 | AV25: =IF(AU25>=AU24,AU25-AU24,0) -> 55 | AW25: 2843943 | AX25: =IF(AW25>=AW24,AW25-AW24,0) -> 747 | AY25: 231065 | AZ25: =IF(AY25>=AY24,AY25-AY24,0) -> 12 | BA25: 20588351 | BB25: =IF(BA25>=BA24,BA25-BA24,0) -> 5601 | BC25: 629540 | BD25: =IF(BC25>=BC24,BC25-BC24,0) -> 296 | BE25: 42892 | BF25: =IF(BE25>=BE24,BE25-BE24,0) -> 76 | BG25: 25861742 | BH25: =IF(BG25>=BG24,BG25-BG24,0)-(0.45*BN25)-(0.45*BP25)-BR25 -> 6407.6 | BI25: =AP25+AR25+AT25+AV25+AX25+AZ25+BB25+BD25+BF25+BH25 -> 13820.8 | BJ25: =BI25+AN25 -> 22625.69 | BK25: 1485689 | BL25: =IF(BK25>=BK24,BK25-BK24,0) -> 265 | BM25: 4256383 | BN25: =IF(BM25>=BM24,BM25-BM24,0) -> 1396 | BO25: 444629 | BP25: =IF(BO25>=BO24,BO25-BO24,0) -> 116 | BQ25: 556488 | BR25: =IF(BQ25>=BQ24,BQ25-BQ24,0) -> 149 | BS25: =J25+Q25+AN25+BI25 -> 29080.357 | BT25: 203 | BU25: =IF(BS25>0,BS25/BT25,0) -> 143.25299 | BW25: =IF(BS25>0,BS25/BV25,0) -> #DIV/0! | BX25: =((BS25-Q25)*$BZ$1)+(Q25*$BR$1) -> 33671.91 | BY25: =IF(BX25>0,BX25/BT25,0) -> 165.87148 | BZ25: =IF(BX25>0,BX25/BV25,0) -> #DIV/0!
A26: 21 | C26: =IF(+B26-B25>0,B26-B25,(B26-B25)>0)*800 -> 0 | E26: =IF(+D26-D25>0,D26-D25,(D26-D25)>0)*80 -> 0 | G26: =IF(+F26-F25>0,F26-F25,(F26-F25)>0)*10 -> 0 | H26: 66 | I26: 25364088 | J26: =IF(I26>=I25,I26-I25,0) -> 6018 | K26: =M26+O26 -> 3494 | L26: 193741 | M26: =IF(L26>=L25,L26-L25,0) -> 1809 | N26: 228427 | O26: =IF(N26>=N25,N26-N25,0) -> 1685 | P26: 226492 | Q26: =IF(P26>=P25,P26-P25,0)*30 -> 570 | R26: 220395 | S26: =IF(R26>=R25,R26-R25,0) -> 135 | T26: 402190 | U26: =IF(T26>=T25,T26-T25,0) -> 241 | V26: 557705 | W26: =IF(V26>=V25,V26-V25,0)*0.53 -> 1313.34 | X26: 778159 | Y26: =IF(X26>=X25,X26-X25,0)*0.53 -> 3565.84 | Z26: 762618 | AA26: =IF(Z26>=Z25,Z26-Z25,0)*0.53 -> 7.42 | AB26: 95569 | AC26: =IF(AB26>=AB25,AB26-AB25,0)*0.53 -> 33.92 | AD26: 862430 | AE26: =IF(AD26>=AD25,AD26-AD25,0)*0.53 -> 840.58 | AF26: 1008657 | AG26: =IF(AF26>=AF25,AF26-AF25,0)*0.53 -> 11.66 | AH26: 384634 | AI26: =IF(AH26>=AH25,AH26-AH25,0)*0.53 -> 570.28 | AJ26: 313057 | AK26: =IF(AJ26>=AJ25,AJ26-AJ25,0)*0.53 -> 3223.99 | AL26: 558754 | AM26: =IF(AL26>=AL25,AL26-AL25,0)*0.53 -> 104.41 | AN26: =W26+Y26+AA26+AC26+AE26+AG26+AI26+AK26+AM26 -> 9671.44 | AO26: 8097421 | AP26: =IF(AO26>=AO25,AO26-AO25,0)*0.1125 -> 206.1 | AQ26: 741270 | AR26: =IF(AQ26>=AQ25,AQ26-AQ25,0) -> 158 | AS26: 8166 | AT26: =IF(AS26>=AS25,AS26-AS25,0) -> 180 | AU26: 824158 | AV26: =IF(AU26>=AU25,AU26-AU25,0) -> 42 | AW26: 2844656 | AX26: =IF(AW26>=AW25,AW26-AW25,0) -> 713 | AY26: 231506 | AZ26: =IF(AY26>=AY25,AY26-AY25,0) -> 441 | BA26: 20593686 | BB26: =IF(BA26>=BA25,BA26-BA25,0) -> 5335 | BC26: 629794 | BD26: =IF(BC26>=BC25,BC26-BC25,0) -> 254 | BE26: 42959 | BF26: =IF(BE26>=BE25,BE26-BE25,0) -> 67 | BG26: 25868155 | BH26: =IF(BG26>=BG25,BG26-BG25,0)-(0.45*BN26)-(0.45*BP26)-BR26 -> 5709.1 | BI26: =AP26+AR26+AT26+AV26+AX26+AZ26+BB26+BD26+BF26+BH26 -> 13105.2 | BJ26: =BI26+AN26 -> 22776.64 | BK26: 1485884 | BL26: =IF(BK26>=BK25,BK26-BK25,0) -> 195 | BM26: 4257537 | BN26: =IF(BM26>=BM25,BM26-BM25,0) -> 1154 | BO26: 444737 | BP26: =IF(BO26>=BO25,BO26-BO25,0) -> 108 | BQ26: 556624 | BR26: =IF(BQ26>=BQ25,BQ26-BQ25,0) -> 136 | BS26: =J26+Q26+AN26+BI26 -> 29364.64 | BT26: 202 | BU26: =IF(BS26>0,BS26/BT26,0) -> 145.3695 | BW26: =IF(BS26>0,BS26/BV26,0) -> #DIV/0! | BX26: =((BS26-Q26)*$BZ$1)+(Q26*$BR$1) -> 34025.836 | BY26: =IF(BX26>0,BX26/BT26,0) -> 168.44473 | BZ26: =IF(BX26>0,BX26/BV26,0) -> #DIV/0!
A27: 22 | C27: =IF(+B27-B26>0,B27-B26,(B27-B26)>0)*800 -> 0 | E27: =IF(+D27-D26>0,D27-D26,(D27-D26)>0)*80 -> 0 | G27: =IF(+F27-F26>0,F27-F26,(F27-F26)>0)*10 -> 0 | I27: 25369996 | J27: =IF(I27>=I26,I27-I26,0) -> 5908 | K27: =M27+O27 -> 3268 | L27: 195484 | M27: =IF(L27>=L26,L27-L26,0) -> 1743 | N27: 229952 | O27: =IF(N27>=N26,N27-N26,0) -> 1525 | P27: 226511 | Q27: =IF(P27>=P26,P27-P26,0)*30 -> 570 | R27: 220529 | S27: =IF(R27>=R26,R27-R26,0) -> 134 | T27: 402341 | U27: =IF(T27>=T26,T27-T26,0) -> 151 | V27: 560431 | W27: =IF(V27>=V26,V27-V26,0)*0.53 -> 1444.78 | X27: 785198 | Y27: =IF(X27>=X26,X27-X26,0)*0.53 -> 3730.67 | Z27: 762618 | AA27: =IF(Z27>=Z26,Z27-Z26,0)*0.53 -> 0 | AB27: 95569 | AC27: =IF(AB27>=AB26,AB27-AB26,0)*0.53 -> 0 | AD27: 862450 | AE27: =IF(AD27>=AD26,AD27-AD26,0)*0.53 -> 10.6 | AF27: 1008676 | AG27: =IF(AF27>=AF26,AF27-AF26,0)*0.53 -> 10.07 | AH27: 385279 | AI27: =IF(AH27>=AH26,AH27-AH26,0)*0.53 -> 341.85 | AJ27: 318571 | AK27: =IF(AJ27>=AJ26,AJ27-AJ26,0)*0.53 -> 2922.42 | AL27: 558950 | AM27: =IF(AL27>=AL26,AL27-AL26,0)*0.53 -> 103.88 | AN27: =W27+Y27+AA27+AC27+AE27+AG27+AI27+AK27+AM27 -> 8564.27 | AO27: 8099501 | AP27: =IF(AO27>=AO26,AO27-AO26,0)*0.1125 -> 234 | AQ27: 741414 | AR27: =IF(AQ27>=AQ26,AQ27-AQ26,0) -> 144 | AS27: 8368 | AT27: =IF(AS27>=AS26,AS27-AS26,0) -> 202 | AU27: 824193 | AV27: =IF(AU27>=AU26,AU27-AU26,0) -> 35 | AW27: 2845432 | AX27: =IF(AW27>=AW26,AW27-AW26,0) -> 776 | AY27: 231517 | AZ27: =IF(AY27>=AY26,AY27-AY26,0) -> 11 | BA27: 20598794 | BB27: =IF(BA27>=BA26,BA27-BA26,0) -> 5108 | BC27: 630050 | BD27: =IF(BC27>=BC26,BC27-BC26,0) -> 256 | BE27: 43029 | BF27: =IF(BE27>=BE26,BE27-BE26,0) -> 70 | BG27: 25874513 | BH27: =IF(BG27>=BG26,BG27-BG26,0)-(0.45*BN27)-(0.45*BP27)-BR27 -> 5632.6 | BI27: =AP27+AR27+AT27+AV27+AX27+AZ27+BB27+BD27+BF27+BH27 -> 12468.6 | BJ27: =BI27+AN27 -> 21032.87 | BK27: 1486104 | BL27: =IF(BK27>=BK26,BK27-BK26,0) -> 220 | BM27: 4258734 | BN27: =IF(BM27>=BM26,BM27-BM26,0) -> 1197 | BO27: 444852 | BP27: =IF(BO27>=BO26,BO27-BO26,0) -> 115 | BQ27: 556759 | BR27: =IF(BQ27>=BQ26,BQ27-BQ26,0) -> 135 | BS27: =J27+Q27+AN27+BI27 -> 27510.87 | BT27: 237 | BU27: =IF(BS27>0,BS27/BT27,0) -> 116.07962 | BW27: =IF(BS27>0,BS27/BV27,0) -> #DIV/0! | BX27: =((BS27-Q27)*$BZ$1)+(Q27*$BR$1) -> 31894 | BY27: =IF(BX27>0,BX27/BT27,0) -> 134.57384 | BZ27: =IF(BX27>0,BX27/BV27,0) -> #DIV/0!
A28: 23 | C28: =IF(+B28-B27>0,B28-B27,(B28-B27)>0)*800 -> 0 | E28: =IF(+D28-D27>0,D28-D27,(D28-D27)>0)*80 -> 0 | G28: =IF(+F28-F27>0,F28-F27,(F28-F27)>0)*10 -> 0 | H28: 67 | I28: 25376069 | J28: =IF(I28>=I27,I28-I27,0) -> 6073 | K28: =M28+O28 -> 3361 | L28: 197354 | M28: =IF(L28>=L27,L28-L27,0) -> 1870 | N28: 231443 | O28: =IF(N28>=N27,N28-N27,0) -> 1491 | P28: 226530 | Q28: =IF(P28>=P27,P28-P27,0)*30 -> 570 | R28: 220669 | S28: =IF(R28>=R27,R28-R27,0) -> 140 | T28: 402678 | U28: =IF(T28>=T27,T28-T27,0) -> 337 | V28: 564448 | W28: =IF(V28>=V27,V28-V27,0)*0.53 -> 2129.01 | X28: 792162 | Y28: =IF(X28>=X27,X28-X27,0)*0.53 -> 3690.92 | Z28: 762618 | AA28: =IF(Z28>=Z27,Z28-Z27,0)*0.53 -> 0 | AB28: 95569 | AC28: =IF(AB28>=AB27,AB28-AB27,0)*0.53 -> 0 | AD28: 862473 | AE28: =IF(AD28>=AD27,AD28-AD27,0)*0.53 -> 12.19 | AF28: 1008697 | AG28: =IF(AF28>=AF27,AF28-AF27,0)*0.53 -> 11.13 | AH28: 386163 | AI28: =IF(AH28>=AH27,AH28-AH27,0)*0.53 -> 468.52 | AJ28: 324796 | AK28: =IF(AJ28>=AJ27,AJ28-AJ27,0)*0.53 -> 3299.25 | AL28: 559154 | AM28: =IF(AL28>=AL27,AL28-AL27,0)*0.53 -> 108.12 | AN28: =W28+Y28+AA28+AC28+AE28+AG28+AI28+AK28+AM28 -> 9719.14 | AO28: 8101438 | AP28: =IF(AO28>=AO27,AO28-AO27,0)*0.1125 -> 217.9125 | AQ28: 741578 | AR28: =IF(AQ28>=AQ27,AQ28-AQ27,0) -> 164 | AS28: 8544 | AT28: =IF(AS28>=AS27,AS28-AS27,0) -> 176 | AU28: 824240 | AV28: =IF(AU28>=AU27,AU28-AU27,0) -> 47 | AW28: 2846266 | AX28: =IF(AW28>=AW27,AW28-AW27,0) -> 834 | AY28: 231528 | AZ28: =IF(AY28>=AY27,AY28-AY27,0) -> 11 | BA28: 20604093 | BB28: =IF(BA28>=BA27,BA28-BA27,0) -> 5299 | BC28: 630309 | BD28: =IF(BC28>=BC27,BC28-BC27,0) -> 259 | BE28: 43099 | BF28: =IF(BE28>=BE27,BE28-BE27,0) -> 70 | BG28: 25881099 | BH28: =IF(BG28>=BG27,BG28-BG27,0)-(0.45*BN28)-(0.45*BP28)-BR28 -> 5862.1 | BI28: =AP28+AR28+AT28+AV28+AX28+AZ28+BB28+BD28+BF28+BH28 -> 12940.013 | BJ28: =BI28+AN28 -> 22659.153 | BK28: 1486334 | BL28: =IF(BK28>=BK27,BK28-BK27,0) -> 230 | BM28: 4259924 | BN28: =IF(BM28>=BM27,BM28-BM27,0) -> 1190 | BO28: 444964 | BP28: =IF(BO28>=BO27,BO28-BO27,0) -> 112 | BQ28: 556897 | BR28: =IF(BQ28>=BQ27,BQ28-BQ27,0) -> 138 | BS28: =J28+Q28+AN28+BI28 -> 29302.153 | BT28: 182 | BU28: =IF(BS28>0,BS28/BT28,0) -> 161.00084 | BW28: =IF(BS28>0,BS28/BV28,0) -> #DIV/0! | BX28: =((BS28-Q28)*$BZ$1)+(Q28*$BR$1) -> 33953.975 | BY28: =IF(BX28>0,BX28/BT28,0) -> 186.5603 | BZ28: =IF(BX28>0,BX28/BV28,0) -> #DIV/0!
A29: 24 | C29: =IF(+B29-B28>0,B29-B28,(B29-B28)>0)*800 -> 0 | E29: =IF(+D29-D28>0,D29-D28,(D29-D28)>0)*80 -> 0 | G29: =IF(+F29-F28>0,F29-F28,(F29-F28)>0)*10 -> 0 | I29: 25382116 | J29: =IF(I29>=I28,I29-I28,0) -> 6047 | K29: =M29+O29 -> 3431 | L29: 199331 | M29: =IF(L29>=L28,L29-L28,0) -> 1977 | N29: 232897 | O29: =IF(N29>=N28,N29-N28,0) -> 1454 | P29: 226550 | Q29: =IF(P29>=P28,P29-P28,0)*30 -> 600 | R29: 220810 | S29: =IF(R29>=R28,R29-R28,0) -> 141 | T29: 402934 | U29: =IF(T29>=T28,T29-T28,0) -> 256 | V29: 565558 | W29: =IF(V29>=V28,V29-V28,0)*0.53 -> 588.3 | X29: 799631 | Y29: =IF(X29>=X28,X29-X28,0)*0.53 -> 3958.57 | Z29: 762618 | AA29: =IF(Z29>=Z28,Z29-Z28,0)*0.53 -> 0 | AB29: 95569 | AC29: =IF(AB29>=AB28,AB29-AB28,0)*0.53 -> 0 | AD29: 862495 | AE29: =IF(AD29>=AD28,AD29-AD28,0)*0.53 -> 11.66 | AF29: 1008720 | AG29: =IF(AF29>=AF28,AF29-AF28,0)*0.53 -> 12.19 | AH29: 387044 | AI29: =IF(AH29>=AH28,AH29-AH28,0)*0.53 -> 466.93 | AJ29: 331109 | AK29: =IF(AJ29>=AJ28,AJ29-AJ28,0)*0.53 -> 3345.89 | AL29: 559369 | AM29: =IF(AL29>=AL28,AL29-AL28,0)*0.53 -> 113.95 | AN29: =W29+Y29+AA29+AC29+AE29+AG29+AI29+AK29+AM29 -> 8497.49 | AO29: 8103595 | AP29: =IF(AO29>=AO28,AO29-AO28,0)*0.1125 -> 242.6625 | AQ29: 741983 | AR29: =IF(AQ29>=AQ28,AQ29-AQ28,0) -> 405 | AS29: 8724 | AT29: =IF(AS29>=AS28,AS29-AS28,0) -> 180 | AU29: 824290 | AV29: =IF(AU29>=AU28,AU29-AU28,0) -> 50 | AW29: 2847101 | AX29: =IF(AW29>=AW28,AW29-AW28,0) -> 835 | AY29: 231539 | AZ29: =IF(AY29>=AY28,AY29-AY28,0) -> 11 | BA29: 20609778 | BB29: =IF(BA29>=BA28,BA29-BA28,0) -> 5685 | BC29: 630570 | BD29: =IF(BC29>=BC28,BC29-BC28,0) -> 261 | BE29: 43169 | BF29: =IF(BE29>=BE28,BE29-BE28,0) -> 70 | BG29: 25887460 | BH29: =IF(BG29>=BG28,BG29-BG28,0)-(0.45*BN29)-(0.45*BP29)-BR29 -> 5698.2 | BI29: =AP29+AR29+AT29+AV29+AX29+AZ29+BB29+BD29+BF29+BH29 -> 13437.862 | BJ29: =BI29+AN29 -> 21935.353 | BK29: 1486566 | BL29: =IF(BK29>=BK28,BK29-BK28,0) -> 232 | BM29: 4261020 | BN29: =IF(BM29>=BM28,BM29-BM28,0) -> 1096 | BO29: 445072 | BP29: =IF(BO29>=BO28,BO29-BO28,0) -> 108 | BQ29: 557018 | BR29: =IF(BQ29>=BQ28,BQ29-BQ28,0) -> 121 | BS29: =J29+Q29+AN29+BI29 -> 28582.353 | BT29: 212 | BU29: =IF(BS29>0,BS29/BT29,0) -> 134.82242 | BW29: =IF(BS29>0,BS29/BV29,0) -> #DIV/0! | BX29: =((BS29-Q29)*$BZ$1)+(Q29*$BR$1) -> 33139.705 | BY29: =IF(BX29>0,BX29/BT29,0) -> 156.31936 | BZ29: =IF(BX29>0,BX29/BV29,0) -> #DIV/0!
A30: 25 | C30: =IF(+B30-B29>0,B30-B29,(B30-B29)>0)*800 -> 0 | E30: =IF(+D30-D29>0,D30-D29,(D30-D29)>0)*80 -> 0 | G30: =IF(+F30-F29>0,F30-F29,(F30-F29)>0)*10 -> 0 | H30: 68 | I30: 25388191 | J30: =IF(I30>=I29,I30-I29,0) -> 6075 | K30: =M30+O30 -> 3601 | L30: 201300 | M30: =IF(L30>=L29,L30-L29,0) -> 1969 | N30: 234529 | O30: =IF(N30>=N29,N30-N29,0) -> 1632 | P30: 226569 | Q30: =IF(P30>=P29,P30-P29,0)*30 -> 570 | R30: 220954 | S30: =IF(R30>=R29,R30-R29,0) -> 144 | T30: 403188 | U30: =IF(T30>=T29,T30-T29,0) -> 254 | V30: 568426 | W30: =IF(V30>=V29,V30-V29,0)*0.53 -> 1520.04 | X30: 801657 | Y30: =IF(X30>=X29,X30-X29,0)*0.53 -> 1073.78 | Z30: 767527 | AA30: =IF(Z30>=Z29,Z30-Z29,0)*0.53 -> 2601.77 | AB30: 95569 | AC30: =IF(AB30>=AB29,AB30-AB29,0)*0.53 -> 0 | AD30: 862519 | AE30: =IF(AD30>=AD29,AD30-AD29,0)*0.53 -> 12.72 | AF30: 1008740 | AG30: =IF(AF30>=AF29,AF30-AF29,0)*0.53 -> 10.6 | AH30: 388096 | AI30: =IF(AH30>=AH29,AH30-AH29,0)*0.53 -> 557.56 | AJ30: 337502 | AK30: =IF(AJ30>=AJ29,AJ30-AJ29,0)*0.53 -> 3388.29 | AL30: 559579 | AM30: =IF(AL30>=AL29,AL30-AL29,0)*0.53 -> 111.3 | AN30: =W30+Y30+AA30+AC30+AE30+AG30+AI30+AK30+AM30 -> 9276.06 | AO30: 8105774 | AP30: =IF(AO30>=AO29,AO30-AO29,0)*0.1125 -> 245.1375 | AQ30: 742377 | AR30: =IF(AQ30>=AQ29,AQ30-AQ29,0) -> 394 | AS30: 8894 | AT30: =IF(AS30>=AS29,AS30-AS29,0) -> 170 | AU30: 824339 | AV30: =IF(AU30>=AU29,AU30-AU29,0) -> 49 | AW30: 2847916 | AX30: =IF(AW30>=AW29,AW30-AW29,0) -> 815 | AY30: 231550 | AZ30: =IF(AY30>=AY29,AY30-AY29,0) -> 11 | BA30: 20614647 | BB30: =IF(BA30>=BA29,BA30-BA29,0) -> 4869 | BC30: 630804 | BD30: =IF(BC30>=BC29,BC30-BC29,0) -> 234 | BE30: 43239 | BF30: =IF(BE30>=BE29,BE30-BE29,0) -> 70 | BG30: 25893812 | BH30: =IF(BG30>=BG29,BG30-BG29,0)-(0.45*BN30)-(0.45*BP30)-BR30 -> 5687.6 | BI30: =AP30+AR30+AT30+AV30+AX30+AZ30+BB30+BD30+BF30+BH30 -> 12544.737 | BJ30: =BI30+AN30 -> 21820.798 | BK30: 1486800 | BL30: =IF(BK30>=BK29,BK30-BK29,0) -> 234 | BM30: 4262063 | BN30: =IF(BM30>=BM29,BM30-BM29,0) -> 1043 | BO30: 445181 | BP30: =IF(BO30>=BO29,BO30-BO29,0) -> 109 | BQ30: 557164 | BR30: =IF(BQ30>=BQ29,BQ30-BQ29,0) -> 146 | BS30: =J30+Q30+AN30+BI30 -> 28465.798 | BT30: 188 | BU30: =IF(BS30>0,BS30/BT30,0) -> 151.41382 | BW30: =IF(BS30>0,BS30/BV30,0) -> #DIV/0! | BX30: =((BS30-Q30)*$BZ$1)+(Q30*$BR$1) -> 32992.167 | BY30: =IF(BX30>0,BX30/BT30,0) -> 175.49025 | BZ30: =IF(BX30>0,BX30/BV30,0) -> #DIV/0!
A31: 26 | C31: =IF(+B31-B30>0,B31-B30,(B31-B30)>0)*800 -> 0 | E31: =IF(+D31-D30>0,D31-D30,(D31-D30)>0)*80 -> 0 | G31: =IF(+F31-F30>0,F31-F30,(F31-F30)>0)*10 -> 0 | I31: 25394299 | J31: =IF(I31>=I30,I31-I30,0) -> 6108 | K31: =M31+O31 -> 3489 | L31: 203233 | M31: =IF(L31>=L30,L31-L30,0) -> 1933 | N31: 236085 | O31: =IF(N31>=N30,N31-N30,0) -> 1556 | P31: 226589 | Q31: =IF(P31>=P30,P31-P30,0)*30 -> 600 | R31: 221096 | S31: =IF(R31>=R30,R31-R30,0) -> 142 | T31: 403437 | U31: =IF(T31>=T30,T31-T30,0) -> 249 | V31: 572063 | W31: =IF(V31>=V30,V31-V30,0)*0.53 -> 1927.61 | X31: 801657 | Y31: =IF(X31>=X30,X31-X30,0)*0.53 -> 0 | Z31: 774063 | AA31: =IF(Z31>=Z30,Z31-Z30,0)*0.53 -> 3464.08 | AB31: 95569 | AC31: =IF(AB31>=AB30,AB31-AB30,0)*0.53 -> 0 | AD31: 862542 | AE31: =IF(AD31>=AD30,AD31-AD30,0)*0.53 -> 12.19 | AF31: 1008761 | AG31: =IF(AF31>=AF30,AF31-AF30,0)*0.53 -> 11.13 | AH31: 389419 | AI31: =IF(AH31>=AH30,AH31-AH30,0)*0.53 -> 701.19 | AJ31: 343917 | AK31: =IF(AJ31>=AJ30,AJ31-AJ30,0)*0.53 -> 3399.95 | AL31: 559780 | AM31: =IF(AL31>=AL30,AL31-AL30,0)*0.53 -> 106.53 | AN31: =W31+Y31+AA31+AC31+AE31+AG31+AI31+AK31+AM31 -> 9622.68 | AO31: 8108065 | AP31: =IF(AO31>=AO30,AO31-AO30,0)*0.1125 -> 257.7375 | AQ31: 742659 | AR31: =IF(AQ31>=AQ30,AQ31-AQ30,0) -> 282 | AS31: 9048 | AT31: =IF(AS31>=AS30,AS31-AS30,0) -> 154 | AU31: 824384 | AV31: =IF(AU31>=AU30,AU31-AU30,0) -> 45 | AW31: 2848806 | AX31: =IF(AW31>=AW30,AW31-AW30,0) -> 890 | AY31: 231561 | AZ31: =IF(AY31>=AY30,AY31-AY30,0) -> 11 | BA31: 20619915 | BB31: =IF(BA31>=BA30,BA31-BA30,0) -> 5268 | BC31: 631076 | BD31: =IF(BC31>=BC30,BC31-BC30,0) -> 272 | BE31: 43309 | BF31: =IF(BE31>=BE30,BE31-BE30,0) -> 70 | BG31: 25900284 | BH31: =IF(BG31>=BG30,BG31-BG30,0)-(0.45*BN31)-(0.45*BP31)-BR31 -> 5796.8 | BI31: =AP31+AR31+AT31+AV31+AX31+AZ31+BB31+BD31+BF31+BH31 -> 13046.538 | BJ31: =BI31+AN31 -> 22669.218 | BK31: 1487031 | BL31: =IF(BK31>=BK30,BK31-BK30,0) -> 231 | BM31: 4263170 | BN31: =IF(BM31>=BM30,BM31-BM30,0) -> 1107 | BO31: 445290 | BP31: =IF(BO31>=BO30,BO31-BO30,0) -> 109 | BQ31: 557292 | BR31: =IF(BQ31>=BQ30,BQ31-BQ30,0) -> 128 | BS31: =J31+Q31+AN31+BI31 -> 29377.218 | BT31: 219 | BU31: =IF(BS31>0,BS31/BT31,0) -> 134.14255 | BW31: =IF(BS31>0,BS31/BV31,0) -> #DIV/0! | BX31: =((BS31-Q31)*$BZ$1)+(Q31*$BR$1) -> 34053.8 | BY31: =IF(BX31>0,BX31/BT31,0) -> 155.4968 | BZ31: =IF(BX31>0,BX31/BV31,0) -> #DIV/0!
A32: 27 | C32: =IF(+B32-B31>0,B32-B31,(B32-B31)>0)*800 -> 0 | E32: =IF(+D32-D31>0,D32-D31,(D32-D31)>0)*80 -> 0 | G32: =IF(+F32-F31>0,F32-F31,(F32-F31)>0)*10 -> 0 | H32: 69 | I32: 25400044 | J32: =IF(I32>=I31,I32-I31,0) -> 5745 | K32: =M32+O32 -> 3491 | L32: 205069 | M32: =IF(L32>=L31,L32-L31,0) -> 1836 | N32: 237740 | O32: =IF(N32>=N31,N32-N31,0) -> 1655 | P32: 226608 | Q32: =IF(P32>=P31,P32-P31,0)*30 -> 570 | R32: 221236 | S32: =IF(R32>=R31,R32-R31,0) -> 140 | T32: 403668 | U32: =IF(T32>=T31,T32-T31,0) -> 231 | V32: 575813 | W32: =IF(V32>=V31,V32-V31,0)*0.53 -> 1987.5 | X32: 801657 | Y32: =IF(X32>=X31,X32-X31,0)*0.53 -> 0 | Z32: 781104 | AA32: =IF(Z32>=Z31,Z32-Z31,0)*0.53 -> 3731.73 | AB32: 95569 | AC32: =IF(AB32>=AB31,AB32-AB31,0)*0.53 -> 0 | AD32: 862565 | AE32: =IF(AD32>=AD31,AD32-AD31,0)*0.53 -> 12.19 | AF32: 1008783 | AG32: =IF(AF32>=AF31,AF32-AF31,0)*0.53 -> 11.66 | AH32: 391068 | AI32: =IF(AH32>=AH31,AH32-AH31,0)*0.53 -> 873.97 | AJ32: 350501 | AK32: =IF(AJ32>=AJ31,AJ32-AJ31,0)*0.53 -> 3489.52 | AL32: 559991 | AM32: =IF(AL32>=AL31,AL32-AL31,0)*0.53 -> 111.83 | AN32: =W32+Y32+AA32+AC32+AE32+AG32+AI32+AK32+AM32 -> 10218.4 | AO32: 8110149 | AP32: =IF(AO32>=AO31,AO32-AO31,0)*0.1125 -> 234.45 | AQ32: 742847 | AR32: =IF(AQ32>=AQ31,AQ32-AQ31,0) -> 188 | AS32: 9216 | AT32: =IF(AS32>=AS31,AS32-AS31,0) -> 168 | AU32: 824434 | AV32: =IF(AU32>=AU31,AU32-AU31,0) -> 50 | AW32: 2849844 | AX32: =IF(AW32>=AW31,AW32-AW31,0) -> 1038 | AY32: 231571 | AZ32: =IF(AY32>=AY31,AY32-AY31,0) -> 10 | BA32: 20624918 | BB32: =IF(BA32>=BA31,BA32-BA31,0) -> 5003 | BC32: 631372 | BD32: =IF(BC32>=BC31,BC32-BC31,0) -> 296 | BE32: 43379 | BF32: =IF(BE32>=BE31,BE32-BE31,0) -> 70 | BG32: 25906951 | BH32: =IF(BG32>=BG31,BG32-BG31,0)-(0.45*BN32)-(0.45*BP32)-BR32 -> 5963.3 | BI32: =AP32+AR32+AT32+AV32+AX32+AZ32+BB32+BD32+BF32+BH32 -> 13020.75 | BJ32: =BI32+AN32 -> 23239.15 | BK32: 1487264 | BL32: =IF(BK32>=BK31,BK32-BK31,0) -> 233 | BM32: 4264307 | BN32: =IF(BM32>=BM31,BM32-BM31,0) -> 1137 | BO32: 445399 | BP32: =IF(BO32>=BO31,BO32-BO31,0) -> 109 | BQ32: 557435 | BR32: =IF(BQ32>=BQ31,BQ32-BQ31,0) -> 143 | BS32: =J32+Q32+AN32+BI32 -> 29554.15 | BT32: 212 | BU32: =IF(BS32>0,BS32/BT32,0) -> 139.40637 | BW32: =IF(BS32>0,BS32/BV32,0) -> #DIV/0! | BX32: =((BS32-Q32)*$BZ$1)+(Q32*$BR$1) -> 34243.772 | BY32: =IF(BX32>0,BX32/BT32,0) -> 161.52723 | BZ32: =IF(BX32>0,BX32/BV32,0) -> #DIV/0!
A33: 28 | C33: =IF(+B33-B32>0,B33-B32,(B33-B32)>0)*800 -> 0 | E33: =IF(+D33-D32>0,D33-D32,(D33-D32)>0)*80 -> 0 | G33: =IF(+F33-F32>0,F33-F32,(F33-F32)>0)*10 -> 0 | I33: 25409885 | J33: =IF(I33>=I32,I33-I32,0) -> 9841 | K33: =M33+O33 -> 3480 | L33: 206975 | M33: =IF(L33>=L32,L33-L32,0) -> 1906 | N33: 239314 | O33: =IF(N33>=N32,N33-N32,0) -> 1574 | P33: 226626 | Q33: =IF(P33>=P32,P33-P32,0)*30 -> 540 | R33: 221379 | S33: =IF(R33>=R32,R33-R32,0) -> 143 | T33: 403942 | U33: =IF(T33>=T32,T33-T32,0) -> 274 | V33: 579997 | W33: =IF(V33>=V32,V33-V32,0)*0.53 -> 2217.52 | X33: 801657 | Y33: =IF(X33>=X32,X33-X32,0)*0.53 -> 0 | Z33: 787430 | AA33: =IF(Z33>=Z32,Z33-Z32,0)*0.53 -> 3352.78 | AB33: 95569 | AC33: =IF(AB33>=AB32,AB33-AB32,0)*0.53 -> 0 | AD33: 862589 | AE33: =IF(AD33>=AD32,AD33-AD32,0)*0.53 -> 12.72 | AF33: 1008805 | AG33: =IF(AF33>=AF32,AF33-AF32,0)*0.53 -> 11.66 | AH33: 392609 | AI33: =IF(AH33>=AH32,AH33-AH32,0)*0.53 -> 816.73 | AJ33: 357003 | AK33: =IF(AJ33>=AJ32,AJ33-AJ32,0)*0.53 -> 3446.06 | AL33: 560195 | AM33: =IF(AL33>=AL32,AL33-AL32,0)*0.53 -> 108.12 | AN33: =W33+Y33+AA33+AC33+AE33+AG33+AI33+AK33+AM33 -> 9965.59 | AO33: 8112399 | AP33: =IF(AO33>=AO32,AO33-AO32,0)*0.1125 -> 253.125 | AQ33: 743040 | AR33: =IF(AQ33>=AQ32,AQ33-AQ32,0) -> 193 | AS33: 9378 | AT33: =IF(AS33>=AS32,AS33-AS32,0) -> 162 | AU33: 824476 | AV33: =IF(AU33>=AU32,AU33-AU32,0) -> 42 | AW33: 2850826 | AX33: =IF(AW33>=AW32,AW33-AW32,0) -> 982 | AY33: 231582 | AZ33: =IF(AY33>=AY32,AY33-AY32,0) -> 11 | BA33: 20630236 | BB33: =IF(BA33>=BA32,BA33-BA32,0) -> 5318 | BC33: 631652 | BD33: =IF(BC33>=BC32,BC33-BC32,0) -> 280 | BE33: 43449 | BF33: =IF(BE33>=BE32,BE33-BE32,0) -> 70 | BG33: 25913798 | BH33: =IF(BG33>=BG32,BG33-BG32,0)-(0.45*BN33)-(0.45*BP33)-BR33 -> 6069.9 | BI33: =AP33+AR33+AT33+AV33+AX33+AZ33+BB33+BD33+BF33+BH33 -> 13381.025 | BJ33: =BI33+AN33 -> 23346.615 | BK33: 1487500 | BL33: =IF(BK33>=BK32,BK33-BK32,0) -> 236 | BM33: 4265615 | BN33: =IF(BM33>=BM32,BM33-BM32,0) -> 1308 | BO33: 445509 | BP33: =IF(BO33>=BO32,BO33-BO32,0) -> 110 | BQ33: 557574 | BR33: =IF(BQ33>=BQ32,BQ33-BQ32,0) -> 139 | BS33: =J33+Q33+AN33+BI33 -> 33727.615 | BT33: 243 | BU33: =IF(BS33>0,BS33/BT33,0) -> 138.79677 | BW33: =IF(BS33>0,BS33/BV33,0) -> #DIV/0! | BX33: =((BS33-Q33)*$BZ$1)+(Q33*$BR$1) -> 39029.757 | BY33: =IF(BX33>0,BX33/BT33,0) -> 160.61628 | BZ33: =IF(BX33>0,BX33/BV33,0) -> #DIV/0!
A34: 29 | C34: =IF(+B34-B33>0,B34-B33,(B34-B33)>0)*800 -> 0 | E34: =IF(+D34-D33>0,D34-D33,(D34-D33)>0)*80 -> 0 | G34: =IF(+F34-F33>0,F34-F33,(F34-F33)>0)*10 -> 0 | I34: 25411611 | J34: =IF(I34>=I33,I34-I33,0) -> 1726 | K34: =M34+O34 -> 3592 | L34: 208947 | M34: =IF(L34>=L33,L34-L33,0) -> 1972 | N34: 240934 | O34: =IF(N34>=N33,N34-N33,0) -> 1620 | P34: 226646 | Q34: =IF(P34>=P33,P34-P33,0)*30 -> 600 | R34: 221521 | S34: =IF(R34>=R33,R34-R33,0) -> 142 | T34: 404196 | U34: =IF(T34>=T33,T34-T33,0) -> 254 | V34: 581983 | W34: =IF(V34>=V33,V34-V33,0)*0.53 -> 1052.58 | X34: 801657 | Y34: =IF(X34>=X33,X34-X33,0)*0.53 -> 0 | Z34: 794369 | AA34: =IF(Z34>=Z33,Z34-Z33,0)*0.53 -> 3677.67 | AB34: 95569 | AC34: =IF(AB34>=AB33,AB34-AB33,0)*0.53 -> 0 | AD34: 862614 | AE34: =IF(AD34>=AD33,AD34-AD33,0)*0.53 -> 13.25 | AF34: 1008827 | AG34: =IF(AF34>=AF33,AF34-AF33,0)*0.53 -> 11.66 | AH34: 393895 | AI34: =IF(AH34>=AH33,AH34-AH33,0)*0.53 -> 681.58 | AJ34: 362790 | AK34: =IF(AJ34>=AJ33,AJ34-AJ33,0)*0.53 -> 3067.11 | AL34: 560400 | AM34: =IF(AL34>=AL33,AL34-AL33,0)*0.53 -> 108.65 | AN34: =W34+Y34+AA34+AC34+AE34+AG34+AI34+AK34+AM34 -> 8612.5 | AO34: 8114457 | AP34: =IF(AO34>=AO33,AO34-AO33,0)*0.1125 -> 231.525 | AQ34: 743235 | AR34: =IF(AQ34>=AQ33,AQ34-AQ33,0) -> 195 | AS34: 9544 | AT34: =IF(AS34>=AS33,AS34-AS33,0) -> 166 | AU34: 824517 | AV34: =IF(AU34>=AU33,AU34-AU33,0) -> 41 | AW34: 2851744 | AX34: =IF(AW34>=AW33,AW34-AW33,0) -> 918 | AY34: 231593 | AZ34: =IF(AY34>=AY33,AY34-AY33,0) -> 11 | BA34: 20635546 | BB34: =IF(BA34>=BA33,BA34-BA33,0) -> 5310 | BC34: 631915 | BD34: =IF(BC34>=BC33,BC34-BC33,0) -> 263 | BE34: 43519 | BF34: =IF(BE34>=BE33,BE34-BE33,0) -> 70 | BG34: 25920398 | BH34: =IF(BG34>=BG33,BG34-BG33,0)-(0.45*BN34)-(0.45*BP34)-BR34 -> 5830.15 | BI34: =AP34+AR34+AT34+AV34+AX34+AZ34+BB34+BD34+BF34+BH34 -> 13035.675 | BJ34: =BI34+AN34 -> 21648.175 | BK34: 1487732 | BL34: =IF(BK34>=BK33,BK34-BK33,0) -> 232 | BM34: 4266897 | BN34: =IF(BM34>=BM33,BM34-BM33,0) -> 1282 | BO34: 445620 | BP34: =IF(BO34>=BO33,BO34-BO33,0) -> 111 | BQ34: 557717 | BR34: =IF(BQ34>=BQ33,BQ34-BQ33,0) -> 143 | BS34: =J34+Q34+AN34+BI34 -> 23974.175 | BT34: 247 | BU34: =IF(BS34>0,BS34/BT34,0) -> 97.061437 | BW34: =IF(BS34>0,BS34/BV34,0) -> #DIV/0! | BX34: =((BS34-Q34)*$BZ$1)+(Q34*$BR$1) -> 27840.301 | BY34: =IF(BX34>0,BX34/BT34,0) -> 112.71377 | BZ34: =IF(BX34>0,BX34/BV34,0) -> #DIV/0!
A35: 30 | C35: =IF(+B35-B34>0,B35-B34,(B35-B34)>0)*800 -> 0 | E35: =IF(+D35-D34>0,D35-D34,(D35-D34)>0)*80 -> 0 | G35: =IF(+F35-F34>0,F35-F34,(F35-F34)>0)*10 -> 0 | I35: 25418747 | J35: =IF(I35>=I34,I35-I34,0) -> 7136 | K35: =M35+O35 -> 3517.3333 | L35: 210875 | M35: =IF(L35>=L34,L35-L34,0) -> 1928 | N35: 242523.33 | O35: =IF(N35>=N34,N35-N34,0) -> 1589.3333 | P35: 226664.67 | Q35: =IF(P35>=P34,P35-P34,0)*30 -> 560 | R35: 221663.67 | S35: =IF(R35>=R34,R35-R34,0) -> 142.66667 | T35: 404463.33 | U35: =IF(T35>=T34,T35-T34,0) -> 267.33333 | V35: 585434.33 | W35: =IF(V35>=V34,V35-V34,0)*0.53 -> 1829.2067 | X35: 801657 | Y35: =IF(X35>=X34,X35-X34,0)*0.53 -> 0 | Z35: 794369 | AA35: =IF(Z35>=Z34,Z35-Z34,0)*0.53 -> 0 | AB35: 95569 | AC35: =IF(AB35>=AB34,AB35-AB34,0)*0.53 -> 0 | AD35: 862638.33 | AE35: =IF(AD35>=AD34,AD35-AD34,0)*0.53 -> 12.896667 | AF35: 1008849 | AG35: =IF(AF35>=AF34,AF35-AF34,0)*0.53 -> 11.66 | AH35: 393895 | AI35: =IF(AH35>=AH34,AH35-AH34,0)*0.53 -> 0 | AJ35: 369053.67 | AK35: =IF(AJ35>=AJ34,AJ35-AJ34,0)*0.53 -> 3319.7433 | AL35: 560604.33 | AM35: =IF(AL35>=AL34,AL35-AL34,0)*0.53 -> 108.29667 | AN35: =W35+Y35+AA35+AC35+AE35+AG35+AI35+AK35+AM35 -> 5281.8033 | AO35: 8116643 | AP35: =IF(AO35>=AO34,AO35-AO34,0)*0.1125 -> 245.925 | AQ35: 743428.67 | AR35: =IF(AQ35>=AQ34,AQ35-AQ34,0) -> 193.66667 | AS35: 9707.3333 | AT35: =IF(AS35>=AS34,AS35-AS34,0) -> 163.33333 | AU35: 824558.67 | AV35: =IF(AU35>=AU34,AU35-AU34,0) -> 41.666667 | AW35: 2852662 | AX35: =IF(AW35>=AW34,AW35-AW34,0) -> 918 | AY35: 231604 | AZ35: =IF(AY35>=AY34,AY35-AY34,0) -> 11 | BA35: 20640861 | BB35: =IF(BA35>=BA34,BA35-BA34,0) -> 5315.3333 | BC35: 632189.33 | BD35: =IF(BC35>=BC34,BC35-BC34,0) -> 274.33333 | BE35: 43589 | BF35: =IF(BE35>=BE34,BE35-BE34,0) -> 70 | BG35: 25927163 | BH35: =IF(BG35>=BG34,BG35-BG34,0)-(0.45*BN35)-(0.45*BP35)-BR35 -> 5989.9833 | BI35: =AP35+AR35+AT35+AV35+AX35+AZ35+BB35+BD35+BF35+BH35 -> 13223.242 | BJ35: =BI35+AN35 -> 18505.045 | BK35: 1487966.7 | BL35: =IF(BK35>=BK34,BK35-BK34,0) -> 234.66667 | BM35: 4268196.3 | BN35: =IF(BM35>=BM34,BM35-BM34,0) -> 1299.3333 | BO35: 445730.33 | BP35: =IF(BO35>=BO34,BO35-BO34,0) -> 110.33333 | BQ35: 557857.33 | BR35: =IF(BQ35>=BQ34,BQ35-BQ34,0) -> 140.33333 | BS35: =J35+Q35+AN35+BI35 -> 26201.045 | BT35: 247 | BU35: =IF(BS35>0,BS35/BT35,0) -> 106.07711 | BW35: =IF(BS35>0,BS35/BV35,0) -> #DIV/0! | BX35: =((BS35-Q35)*$BZ$1)+(Q35*$BR$1) -> 30383.202 | BY35: =IF(BX35>0,BX35/BT35,0) -> 123.00891 | BZ35: =IF(BX35>0,BX35/BV35,0) -> #DIV/0!
A36: 31 | I36: 25424530 | J36: =IF(I36>=I35,I36-I35,0) -> 5783.5 | K36: =M36+O36 -> 3567.1111 | L36: 212832.33 | M36: =IF(L36>=L35,L36-L35,0) -> 1957.3333 | N36: 244133.11 | O36: =IF(N36>=N35,N36-N35,0) -> 1609.7778 | P36: 226683.67 | Q36: =IF(P36>=P35,P36-P35,0)*30 -> 570 | R36: 221805.89 | S36: =IF(R36>=R35,R36-R35,0) -> 142.22222 | T36: 404727.33 | U36: =IF(T36>=T35,T36-T35,0) -> 264 | V36: 585434.33 | W36: =IF(V36>=V35,V36-V35,0)*0.53 -> 0 | X36: 801657 | Y36: =IF(X36>=X35,X36-X35,0)*0.53 -> 0 | Z36: 794369 | AA36: =IF(Z36>=Z35,Z36-Z35,0)*0.53 -> 0 | AB36: 95569 | AC36: =IF(AB36>=AB35,AB36-AB35,0)*0.53 -> 0 | AD36: 862662.83 | AE36: =IF(AD36>=AD35,AD36-AD35,0)*0.53 -> 12.985 | AF36: 1008871 | AG36: =IF(AF36>=AF35,AF36-AF35,0)*0.53 -> 11.66 | AH36: 393895 | AI36: =IF(AH36>=AH35,AH36-AH35,0)*0.53 -> 0 | AJ36: 375198.17 | AK36: =IF(AJ36>=AJ35,AJ36-AJ35,0)*0.53 -> 3256.585 | AL36: 560808.83 | AM36: =IF(AL36>=AL35,AL36-AL35,0)*0.53 -> 108.385 | AN36: =W36+Y36+AA36+AC36+AE36+AG36+AI36+AK36+AM36 -> 3389.615 | AO36: 8118797 | AP36: =IF(AO36>=AO35,AO36-AO35,0)*0.1125 -> 242.325 | AQ36: 743622.67 | AR36: =IF(AQ36>=AQ35,AQ36-AQ35,0) -> 194 | AS36: 9871.3333 | AT36: =IF(AS36>=AS35,AS36-AS35,0) -> 164 | AU36: 824600.17 | AV36: =IF(AU36>=AU35,AU36-AU35,0) -> 41.5 | AW36: 2853580 | AX36: =IF(AW36>=AW35,AW36-AW35,0) -> 918 | AY36: 231615 | AZ36: =IF(AY36>=AY35,AY36-AY35,0) -> 11 | BA36: 20646175 | BB36: =IF(BA36>=BA35,BA36-BA35,0) -> 5314 | BC36: 632460.83 | BD36: =IF(BC36>=BC35,BC36-BC35,0) -> 271.5 | BE36: 43659 | BF36: =IF(BE36>=BE35,BE36-BE35,0) -> 70 | BG36: 25933886 | BH36: =IF(BG36>=BG35,BG36-BG35,0)-(0.45*BN36)-(0.45*BP36)-BR36 -> 5950.025 | BI36: =AP36+AR36+AT36+AV36+AX36+AZ36+BB36+BD36+BF36+BH36 -> 13176.35 | BJ36: =BI36+AN36 -> 16565.965 | BK36: 1488200.7 | BL36: =IF(BK36>=BK35,BK36-BK35,0) -> 234 | BM36: 4269491.3 | BN36: =IF(BM36>=BM35,BM36-BM35,0) -> 1295 | BO36: 445840.83 | BP36: =IF(BO36>=BO35,BO36-BO35,0) -> 110.5 | BQ36: 557998.33 | BR36: =IF(BQ36>=BQ35,BQ36-BQ35,0) -> 141 | BS36: =J36+Q36+AN36+BI36 -> 22919.465 | BT36: 238 | BU36: =IF(BS36>0,BS36/BT36,0) -> 96.300273 | BW36: =IF(BS36>0,BS36/BV36,0) -> #DIV/0! | BX36: =((BS36-Q36)*$BZ$1)+(Q36*$BR$1) -> 26613.885 | BY36: =IF(BX36>0,BX36/BT36,0) -> 111.82305 | BZ36: =IF(BX36>0,BX36/BV36,0) -> #DIV/0!
A37: MTD | C37: =SUM(C9:C35) -> 0 | E37: =SUM(E9:E35) -> 0 | F37: =SUM(F9:F35) -> 0 | G37: =SUM(G9:G35) -> 0 | J37: =SUM(J6:J36) -> 175935.35 | K37: =SUM(K6:K36) -> 108994.44 | M37: =SUM(M6:M36) -> 59287.333 | O37: =SUM(O6:O36) -> 49707.111 | Q37: =SUM(Q6:Q36) -> 17570 | S37: =SUM(S6:S36) -> 4374.8889 | U37: =SUM(U6:U36) -> 7862.3333 | W37: =SUM(W6:W36) -> 59908.197 | Y37: =SUM(Y5:Y36) -> 35946.19 | AA37: =SUM(AA6:AA36) -> 58242.23 | AC37: =SUM(AC6:AC36) -> 14196.58 | AE37: =SUM(AE6:AE36) -> 10907.312 | AG37: =SUM(AG6:AG36) -> 6443.0333 | AI37: =SUM(AI6:AI36) -> 19006.86 | AK37: =SUM(AK6:AK36) -> 104361.86 | AM37: =SUM(AM6:AM36) -> 3412.0517 | AN37: =SUM(AN6:AN36) -> 312424.31 | AP37: =SUM(AP6:AP36) -> 7779.7125 | AR37: =SUM(AR6:AR36) -> 6013.6667 | AT37: =SUM(AT6:AT36) -> 5637.3333 | AV37: =SUM(AV6:AV36) -> 1506.1667 | AX37: =SUM(AX6:AX36) -> 26412 | AZ37: =SUM(AZ6:AZ36) -> 771 | BB37: =SUM(BB6:BB36) -> 162213.33 | BD37: =SUM(BD6:BD36) -> 7948.8333 | BF37: =SUM(BF6:BF36) -> 2191 | BH37: =SUM(BH6:BH36) -> 189613.76 | BI37: =SUM(BI6:BI36) -> 410086.8 | BJ37: =SUM(BJ6:BJ36) -> 722511.12 | BL37: =SUM(BL6:BL36) -> 7246.6667 | BN37: =SUM(BN6:BN36) -> 40064.333 | BP37: =SUM(BP6:BP36) -> 3435.8333 | BR37: =SUM(BR6:BR36) -> 4254.3333 | BS37: =SUM(BS6:BS36) -> 916016.47 | BT37: =SUM(BT6:BT36) -> 6813 | BU37: =IF(BS37>0,BS37/BT37,0) -> 134.45126 | BV37: =SUM(BV6:BV35) -> 0 | BW37: =IF(BS37>0,BS37/BV37,0) -> #DIV/0! | BX37: =SUM(BX6:BX35) -> 1034711.6 | BY37: =IF(BX37>0,BX37/BT37,0) -> 151.87312 | BZ37: =IF(BX37>0,BX37/BV37,0) -> #DIV/0!
A38: AVER. Act | C38: =C37/C40 -> #DIV/0! | E38: =E37/C40 -> #DIV/0! | F38: =F37/C40 -> #DIV/0! | G38: =G37/C40 -> #DIV/0! | J38: =J37/J39 -> 5864.5117 | K38: =K37/J39 -> 3633.1481 | M38: =M37/J39 -> 1976.2444 | O38: =O37/J39 -> 1656.9037 | Q38: =Q37/J39 -> 585.66667 | S38: =S37/J39 -> 145.82963 | U38: =U37/J39 -> 262.07778 | W38: =W37/J39 -> 1996.9399 | Y38: =Y37/J39 -> 1198.2063 | AA38: =AA37/J39 -> 1941.4077 | AC38: =AC37/J39 -> 473.21933 | AE38: =AE37/J39 -> 363.57706 | AG38: =AG37/J39 -> 214.76778 | AI38: =AI37/J39 -> 633.562 | AK38: =AK37/J39 -> 3478.7286 | AM38: =AM37/J39 -> 113.73506 | AN38: =AN37/J39 -> 10414.144 | AP38: =AP37/J39 -> 259.32375 | AR38: =AR37/J39 -> 200.45556 | AT38: =AT37/J39 -> 187.91111 | AV38: =AV37/J39 -> 50.205556 | AX38: =AX37/J39 -> 880.4 | AZ38: =AZ37/J39 -> 25.7 | BB38: =BB37/J39 -> 5407.1111 | BD38: =BD37/J39 -> 264.96111 | BF38: =BF37/J39 -> 73.033333 | BH38: =BH37/J39 -> 6320.4586 | BL38: =BL37/J39 -> 241.55556 | BN38: =BN37/J39 -> 1335.4778 | BP38: =BP37/J39 -> 114.52778 | BR38: =BR37/J39 -> 141.81111 | BS38: =BS37/$J$41 -> #DIV/0! | BT38: =BT37/$J$41 -> #DIV/0! | BU38: =BS38/BT38 -> #DIV/0! | BV38: =BV37/$J$41 -> #DIV/0! | BW38: =BS38/BV38 -> #DIV/0! | BX38: =BX37/$J$41 -> #DIV/0! | BY38: =BX38/BT38 -> #DIV/0! | BZ38: =BX38/BV38 -> #DIV/0!
A39: No of Days MTD | J39: =COUNTIF(I6:I35,">0") -> 30
A40: No of Days month | J40: =COUNTIF(A6:A35,">0") -> 30

Sheet Water
A1: =Elect!A1 -> 44835 | T1: Main Water UP | V1: 4 | W1: Water Truck UP
A3: Day | E3: Water Incoming | I3: New casino | N3: Rooms Consumption | P3: Public Areas consumption | R3: Swimming pool | T3: No. of rooms | U3: Cons. Per occ. room | V3: No. of guest | W3: Cons. Per guest | X3: Total cost | Y3: L.E\ | Z3: L.E\
B4: Main water meter 1 | D4: Main water meter 2 | F4: Main water meter 3 | H4: Total Inc. | I4: Hot water | K4: Cold water | N4: Express Riser | O4: Consp. | P4: Read. | Q4: Cons. | R4: Read. | S4: Cons. | Y4: Room | Z4: Guest
B5: Counter | C5: Produc 58% | D5: Counter | E5: Produc 58% | F5: Counter | G5: Produc 58% | I5: Counter | K5: Counter
B6: 88821 | C6: =IF(B6>=B5,B6-B5,0)*10*0.58 -> 0 | D6: 11683 | E6: =IF(D6>=D5,D6-D5,0)*10*0.58 -> 0 | F6: 48399 | G6: =IF(F6>=F5,F6-F5,0)*0.58 -> 0 | I6: 302 | K6: 5261
A7: 1 | B7: 88842 | C7: =IF(B7>=B6,B7-B6,0)*10*0.58 -> 121.8 | D7: 11709 | E7: =IF(D7>=D6,D7-D6,0)*10*0.58 -> 150.8 | F7: 48616 | G7: =IF(F7>=F6,F7-F6,0)*0.58 -> 125.86 | H7: =C7+E7+G7 -> 398.46 | O7: =IF(N7>=N6,N7-N6,0) -> 0 | Q7: =(H7-O7)*0.58 -> 231.1068 | S7: =IF(R7-R6>0,R7-R6,0) -> 0 | T7: =Elect!BT6 -> 227 | U7: =H7/T7 -> 1.7553304 | V7: =Elect!BV6 -> 0 | W7: =H7/V7 -> #DIV/0! | X7: =H7*V1 -> 1593.84 | Y7: =IF(X7>0,X7/T7,0) -> 7.0213216 | Z7: 0
A8: 2 | B8: 88865 | C8: =IF(B8>=B7,B8-B7,0)*10*0.58 -> 133.4 | D8: 11739 | E8: =IF(D8>=D7,D8-D7,0)*10*0.58 -> 174 | F8: 48841 | G8: =IF(F8>=F7,F8-F7,0)*0.58 -> 130.5 | H8: =C8+E8+G8 -> 437.9 | O8: =IF(N8>=N7,N8-N7,0) -> 0 | Q8: =(H8-O8)*0.58 -> 253.982 | S8: =IF(R8-R7>0,R8-R7,0) -> 0 | T8: =Elect!BT7 -> 243 | U8: =H8/T8 -> 1.8020576 | V8: =Elect!BV7 -> 0 | W8: =H8/V8 -> #DIV/0! | X8: =H8*V1 -> 1751.6 | Y8: =IF(X8>0,X8/T8,0) -> 7.2082305 | Z8: =IF(X8>0,X8/V8,0) -> #DIV/0!
A9: 3 | B9: 88887 | C9: =IF(B9>=B8,B9-B8,0)*10*0.58 -> 127.6 | D9: 11766 | E9: =IF(D9>=D8,D9-D8,0)*10*0.58 -> 156.6 | F9: 49072 | G9: =IF(F9>=F8,F9-F8,0)*0.58 -> 133.98 | H9: =C9+E9+G9 -> 418.18 | O9: =IF(N9>=N8,N9-N8,0) -> 0 | Q9: =(H9-O9)*0.58 -> 242.5444 | S9: =IF(R9-R8>0,R9-R8,0) -> 0 | T9: =Elect!BT8 -> 220 | U9: =H9/T9 -> 1.9008182 | V9: =Elect!BV8 -> 0 | W9: =H9/V9 -> #DIV/0! | X9: =H9*V1 -> 1672.72 | Y9: =IF(X9>0,X9/T9,0) -> 7.6032727 | Z9: =IF(X9>0,X9/V9,0) -> #DIV/0!
A10: 4 | B10: 88911 | C10: =IF(B10>=B9,B10-B9,0)*10*0.58 -> 139.2 | D10: 11798 | E10: =IF(D10>=D9,D10-D9,0)*10*0.58 -> 185.6 | F10: 49292 | G10: =IF(F10>=F9,F10-F9,0)*0.58 -> 127.6 | H10: =C10+E10+G10 -> 452.4 | O10: =IF(N10>=N9,N10-N9,0) -> 0 | Q10: =(H10-O10)*0.58 -> 262.392 | S10: =IF(R10-R9>0,R10-R9,0) -> 0 | T10: =Elect!BT9 -> 203 | U10: =H10/T10 -> 2.2285714 | V10: =Elect!BV9 -> 0 | W10: =H10/V10 -> #DIV/0! | X10: =H10*V1 -> 1809.6 | Y10: =IF(X10>0,X10/T10,0) -> 8.9142857 | Z10: =IF(X10>0,X10/V10,0) -> #DIV/0!
A11: 5 | B11: 88933 | C11: =IF(B11>=B10,B11-B10,0)*10*0.58 -> 127.6 | D11: 11828 | E11: =IF(D11>=D10,D11-D10,0)*10*0.58 -> 174 | F11: 49524 | G11: =IF(F11>=F10,F11-F10,0)*0.58 -> 134.56 | H11: =C11+E11+G11 -> 436.16 | O11: =IF(N11>=N10,N11-N10,0) -> 0 | Q11: =(H11-O11)*0.58 -> 252.9728 | S11: =IF(R11-R10>0,R11-R10,0) -> 0 | T11: =Elect!BT10 -> 187 | U11: =H11/T11 -> 2.3324064 | V11: =Elect!BV10 -> 0 | W11: =H11/V11 -> #DIV/0! | X11: =H11*V1 -> 1744.64 | Y11: =IF(X11>0,X11/T11,0) -> 9.3296257 | Z11: =IF(X11>0,X11/V11,0) -> #DIV/0!
A12: 6 | B12: 88955 | C12: =IF(B12>=B11,B12-B11,0)*10*0.58 -> 127.6 | D12: 11856 | E12: =IF(D12>=D11,D12-D11,0)*10*0.58 -> 162.4 | F12: 49752 | G12: =IF(F12>=F11,F12-F11,0)*0.58 -> 132.24 | H12: =C12+E12+G12 -> 422.24 | O12: =IF(N12>=N11,N12-N11,0) -> 0 | Q12: =(H12-O12)*0.58 -> 244.8992 | S12: =IF(R12-R11>0,R12-R11,0) -> 0 | T12: =Elect!BT11 -> 203 | U12: =H12/T12 -> 2.08 | V12: =Elect!BV11 -> 0 | W12: =H12/V12 -> #DIV/0! | X12: =H12*V1 -> 1688.96 | Y12: =IF(X12>0,X12/T12,0) -> 8.32 | Z12: =IF(X12>0,X12/V12,0) -> #DIV/0!
A13: 7 | B13: 88977 | C13: =IF(B13>=B12,B13-B12,0)*10*0.58 -> 127.6 | D13: 11885 | E13: =IF(D13>=D12,D13-D12,0)*10*0.58 -> 168.2 | F13: 49987 | G13: =IF(F13>=F12,F13-F12,0)*0.58 -> 136.3 | H13: =C13+E13+G13 -> 432.1 | O13: =IF(N13>=N12,N13-N12,0) -> 0 | Q13: =(H13-O13)*0.58 -> 250.618 | S13: =IF(R13-R12>0,R13-R12,0) -> 0 | T13: =Elect!BT12 -> 234 | U13: =H13/T13 -> 1.8465812 | V13: =Elect!BV12 -> 0 | W13: =H13/V13 -> #DIV/0! | X13: =H13*V1 -> 1728.4 | Y13: =IF(X13>0,X13/T13,0) -> 7.3863248 | Z13: =IF(X13>0,X13/V13,0) -> #DIV/0!
A14: 8 | B14: 89001 | C14: =IF(B14>=B13,B14-B13,0)*10*0.58 -> 139.2 | D14: 11916 | E14: =IF(D14>=D13,D14-D13,0)*10*0.58 -> 179.8 | F14: 50197 | G14: =IF(F14>=F13,F14-F13,0)*0.58 -> 121.8 | H14: =C14+E14+G14 -> 440.8 | O14: =IF(N14>=N13,N14-N13,0) -> 0 | Q14: =(H14-O14)*0.58 -> 255.664 | S14: =IF(R14-R13>0,R14-R13,0) -> 0 | T14: =Elect!BT13 -> 248 | U14: =H14/T14 -> 1.7774194 | V14: =Elect!BV13 -> 0 | W14: =H14/V14 -> #DIV/0! | X14: =H14*V1 -> 1763.2 | Y14: =IF(X14>0,X14/T14,0) -> 7.1096774 | Z14: =IF(X14>0,X14/V14,0) -> #DIV/0!
A15: 9 | B15: 89022 | C15: =IF(B15>=B14,B15-B14,0)*10*0.58 -> 121.8 | D15: 11944 | E15: =IF(D15>=D14,D15-D14,0)*10*0.58 -> 162.4 | F15: 50411 | G15: =IF(F15>=F14,F15-F14,0)*0.58 -> 124.12 | H15: =C15+E15+G15 -> 408.32 | O15: =IF(N15>=N14,N15-N14,0) -> 0 | Q15: =(H15-O15)*0.58 -> 236.8256 | S15: =IF(R15-R14>0,R15-R14,0) -> 0 | T15: =Elect!BT14 -> 252 | U15: =H15/T15 -> 1.6203175 | V15: =Elect!BV14 -> 0 | W15: =H15/V15 -> #DIV/0! | X15: =H15*V1 -> 1633.28 | Y15: =IF(X15>0,X15/T15,0) -> 6.4812698 | Z15: =IF(X15>0,X15/V15,0) -> #DIV/0!
A16: 10 | B16: 89044 | C16: =IF(B16>=B15,B16-B15,0)*10*0.58 -> 127.6 | D16: 11972 | E16: =IF(D16>=D15,D16-D15,0)*10*0.58 -> 162.4 | F16: 50636 | G16: =IF(F16>=F15,F16-F15,0)*0.58 -> 130.5 | H16: =C16+E16+G16 -> 420.5 | O16: =IF(N16>=N15,N16-N15,0) -> 0 | Q16: =(H16-O16)*0.58 -> 243.89 | S16: =IF(R16-R15>0,R16-R15,0) -> 0 | T16: =Elect!BT15 -> 246 | U16: =H16/T16 -> 1.7093496 | V16: =Elect!BV15 -> 0 | W16: =H16/V16 -> #DIV/0! | X16: =H16*V1 -> 1682 | Y16: =IF(X16>0,X16/T16,0) -> 6.8373984 | Z16: =IF(X16>0,X16/V16,0) -> #DIV/0!
A17: 11 | B17: 89065.333 | C17: =IF(B17>=B16,B17-B16,0)*10*0.58 -> 123.73333 | D17: 12000 | E17: =IF(D17>=D16,D17-D16,0)*10*0.58 -> 162.4 | F17: 50853.667 | G17: =IF(F17>=F16,F17-F16,0)*0.58 -> 126.24667 | H17: =C17+E17+G17 -> 412.38 | O17: =IF(N17>=N16,N17-N16,0) -> 0 | Q17: =(H17-O17)*0.58 -> 239.1804 | S17: =IF(R17-R16>0,R17-R16,0) -> 0 | T17: =Elect!BT16 -> 206 | U17: =H17/T17 -> 2.0018447 | V17: =Elect!BV16 -> 0 | W17: =H17/V17 -> #DIV/0! | X17: =H17*V1 -> 1649.52 | Y17: =IF(X17>0,X17/T17,0) -> 8.0073786 | Z17: =IF(X17>0,X17/V17,0) -> #DIV/0!
A18: 12 | B18: 89087 | C18: =IF(B18>=B17,B18-B17,0)*10*0.58 -> 125.66667 | D18: 12027 | E18: =IF(D18>=D17,D18-D17,0)*10*0.58 -> 156.6 | F18: 51077 | G18: =IF(F18>=F17,F18-F17,0)*0.58 -> 129.53333 | H18: =C18+E18+G18 -> 411.8 | O18: =IF(N18>=N17,N18-N17,0) -> 0 | Q18: =(H18-O18)*0.58 -> 238.844 | S18: =IF(R18-R17>0,R18-R17,0) -> 0 | T18: =Elect!BT17 -> 174 | U18: =H18/T18 -> 2.3666667 | V18: =Elect!BV17 -> 0 | W18: =H18/V18 -> #DIV/0! | X18: =H18*V1 -> 1647.2 | Y18: =IF(X18>0,X18/T18,0) -> 9.4666667 | Z18: =IF(X18>0,X18/V18,0) -> #DIV/0!
A19: 13 | B19: 89108 | C19: =IF(B19>=B18,B19-B18,0)*10*0.58 -> 121.8 | D19: 12055 | E19: =IF(D19>=D18,D19-D18,0)*10*0.58 -> 162.4 | F19: 51299 | G19: =IF(F19>=F18,F19-F18,0)*0.58 -> 128.76 | H19: =C19+E19+G19 -> 412.96 | O19: =IF(N19>=N18,N19-N18,0) -> 0 | Q19: =(H19-O19)*0.58 -> 239.5168 | S19: =IF(R19-R18>0,R19-R18,0) -> 0 | T19: =Elect!BT18 -> 162 | U19: =H19/T19 -> 2.5491358 | V19: =Elect!BV18 -> 0 | W19: =H19/V19 -> #DIV/0! | X19: =H19*V1 -> 1651.84 | Y19: =IF(X19>0,X19/T19,0) -> 10.196543 | Z19: =IF(X19>0,X19/V19,0) -> #DIV/0!
A20: 14 | B20: 89129 | C20: =IF(B20>=B19,B20-B19,0)*10*0.58 -> 121.8 | D20: 12083 | E20: =IF(D20>=D19,D20-D19,0)*10*0.58 -> 162.4 | F20: 51527 | G20: =IF(F20>=F19,F20-F19,0)*0.58 -> 132.24 | H20: =C20+E20+G20 -> 416.44 | O20: =IF(N20>=N19,N20-N19,0) -> 0 | Q20: =(H20-O20)*0.58 -> 241.5352 | S20: =IF(R20-R19>0,R20-R19,0) -> 0 | T20: =Elect!BT19 -> 207 | U20: =H20/T20 -> 2.0117874 | V20: =Elect!BV19 -> 0 | W20: =H20/V20 -> #DIV/0! | X20: =H20*V1 -> 1665.76 | Y20: =IF(X20>0,X20/T20,0) -> 8.0471498 | Z20: =IF(X20>0,X20/V20,0) -> #DIV/0!
A21: 15 | B21: 89152 | C21: =IF(B21>=B20,B21-B20,0)*10*0.58 -> 133.4 | D21: 12111 | E21: =IF(D21>=D20,D21-D20,0)*10*0.58 -> 162.4 | F21: 51757 | G21: =IF(F21>=F20,F21-F20,0)*0.58 -> 133.4 | H21: =C21+E21+G21 -> 429.2 | O21: =IF(N21>=N20,N21-N20,0) -> 0 | Q21: =(H21-O21)*0.58 -> 248.936 | S21: =IF(R21-R20>0,R21-R20,0) -> 0 | T21: =Elect!BT20 -> 248 | U21: =H21/T21 -> 1.7306452 | V21: =Elect!BV20 -> 0 | W21: =H21/V21 -> #DIV/0! | X21: =H21*V1 -> 1716.8 | Y21: =IF(X21>0,X21/T21,0) -> 6.9225806 | Z21: =IF(X21>0,X21/V21,0) -> #DIV/0!
A22: 16 | B22: 89176 | C22: =IF(B22>=B21,B22-B21,0)*10*0.58 -> 139.2 | D22: 12143 | E22: =IF(D22>=D21,D22-D21,0)*10*0.58 -> 185.6 | F22: 51980 | G22: =IF(F22>=F21,F22-F21,0)*0.58 -> 129.34 | H22: =C22+E22+G22 -> 454.14 | O22: =IF(N22>=N21,N22-N21,0) -> 0 | Q22: =(H22-O22)*0.58 -> 263.4012 | S22: =IF(R22-R21>0,R22-R21,0) -> 0 | T22: =Elect!BT21 -> 248 | U22: =H22/T22 -> 1.8312097 | V22: =Elect!BV21 -> 0 | W22: =H22/V22 -> #DIV/0! | X22: =H22*V1 -> 1816.56 | Y22: =IF(X22>0,X22/T22,0) -> 7.3248387 | Z22: =IF(X22>0,X22/V22,0) -> #DIV/0!
A23: 17 | B23: 89198 | C23: =IF(B23>=B22,B23-B22,0)*10*0.58 -> 127.6 | D23: 12172 | E23: =IF(D23>=D22,D23-D22,0)*10*0.58 -> 168.2 | F23: 52200 | G23: =IF(F23>=F22,F23-F22,0)*0.58 -> 127.6 | H23: =C23+E23+G23 -> 423.4 | O23: =IF(N23>=N22,N23-N22,0) -> 0 | Q23: =(H23-O23)*0.58 -> 245.572 | S23: =IF(R23-R22>0,R23-R22,0) -> 0 | T23: =Elect!BT22 -> 244 | U23: =H23/T23 -> 1.7352459 | V23: =Elect!BV22 -> 0 | W23: =H23/V23 -> #DIV/0! | X23: =H23*V1 -> 1693.6 | Y23: =IF(X23>0,X23/T23,0) -> 6.9409836 | Z23: =IF(X23>0,X23/V23,0) -> #DIV/0!
A24: 18 | B24: 89222 | C24: =IF(B24>=B23,B24-B23,0)*10*0.58 -> 139.2 | D24: 12202 | E24: =IF(D24>=D23,D24-D23,0)*10*0.58 -> 174 | F24: 52428 | G24: =IF(F24>=F23,F24-F23,0)*0.58 -> 132.24 | H24: =C24+E24+G24 -> 445.44 | O24: =IF(N24>=N23,N24-N23,0) -> 0 | Q24: =(H24-O24)*0.58 -> 258.3552 | S24: =IF(R24-R23>0,R24-R23,0) -> 0 | T24: =Elect!BT23 -> 228 | U24: =H24/T24 -> 1.9536842 | V24: =Elect!BV23 -> 0 | W24: =H24/V24 -> #DIV/0! | X24: =H24*V1 -> 1781.76 | Y24: =IF(X24>0,X24/T24,0) -> 7.8147368 | Z24: =IF(X24>0,X24/V24,0) -> #DIV/0!
A25: 19 | B25: 89247 | C25: =IF(B25>=B24,B25-B24,0)*10*0.58 -> 145 | D25: 12232 | E25: =IF(D25>=D24,D25-D24,0)*10*0.58 -> 174 | F25: 52664 | G25: =IF(F25>=F24,F25-F24,0)*0.58 -> 136.88 | H25: =C25+E25+G25 -> 455.88 | O25: =IF(N25>=N24,N25-N24,0) -> 0 | Q25: =(H25-O25)*0.58 -> 264.4104 | S25: =IF(R25-R24>0,R25-R24,0) -> 0 | T25: =Elect!BT24 -> 203 | U25: =H25/T25 -> 2.2457143 | V25: =Elect!BV24 -> 0 | W25: =H25/V25 -> #DIV/0! | X25: =H25*V1 -> 1823.52 | Y25: =IF(X25>0,X25/T25,0) -> 8.9828571 | Z25: =IF(X25>0,X25/V25,0) -> #DIV/0!
A26: 20 | B26: 89266 | C26: =IF(B26>=B25,B26-B25,0)*10*0.58 -> 110.2 | D26: 12259 | E26: =IF(D26>=D25,D26-D25,0)*10*0.58 -> 156.6 | F26: 52872 | G26: =IF(F26>=F25,F26-F25,0)*0.58 -> 120.64 | H26: =C26+E26+G26 -> 387.44 | O26: =IF(N26>=N25,N26-N25,0) -> 0 | Q26: =(H26-O26)*0.58 -> 224.7152 | S26: =IF(R26-R25>0,R26-R25,0) -> 0 | T26: =Elect!BT25 -> 203 | U26: =H26/T26 -> 1.9085714 | V26: =Elect!BV25 -> 0 | W26: =H26/V26 -> #DIV/0! | X26: =H26*V1 -> 1549.76 | Y26: =IF(X26>0,X26/T26,0) -> 7.6342857 | Z26: =IF(X26>0,X26/V26,0) -> #DIV/0!
A27: 21 | B27: 89286 | C27: =IF(B27>=B26,B27-B26,0)*10*0.58 -> 116 | D27: 12284 | E27: =IF(D27>=D26,D27-D26,0)*10*0.58 -> 145 | F27: 53084 | G27: =IF(F27>=F26,F27-F26,0)*0.58 -> 122.96 | H27: =C27+E27+G27 -> 383.96 | O27: =IF(N27>=N26,N27-N26,0) -> 0 | Q27: =(H27-O27)*0.58 -> 222.6968 | S27: =IF(R27-R26>0,R27-R26,0) -> 0 | T27: =Elect!BT26 -> 202 | U27: =H27/T27 -> 1.9007921 | V27: =Elect!BV26 -> 0 | W27: =H27/V27 -> #DIV/0! | X27: =H27*V1 -> 1535.84 | Y27: =IF(X27>0,X27/T27,0) -> 7.6031683 | Z27: =IF(X27>0,X27/V27,0) -> #DIV/0!
A28: 22 | B28: 89308 | C28: =IF(B28>=B27,B28-B27,0)*10*0.58 -> 127.6 | D28: 12312 | E28: =IF(D28>=D27,D28-D27,0)*10*0.58 -> 162.4 | F28: 53298 | G28: =IF(F28>=F27,F28-F27,0)*0.58 -> 124.12 | H28: =C28+E28+G28 -> 414.12 | O28: =IF(N28>=N27,N28-N27,0) -> 0 | Q28: =(H28-O28)*0.58 -> 240.1896 | S28: =IF(R28-R27>0,R28-R27,0) -> 0 | T28: =Elect!BT27 -> 237 | U28: =H28/T28 -> 1.7473418 | V28: =Elect!BV27 -> 0 | W28: =H28/V28 -> #DIV/0! | X28: =H28*V1 -> 1656.48 | Y28: =IF(X28>0,X28/T28,0) -> 6.9893671 | Z28: =IF(X28>0,X28/V28,0) -> #DIV/0!
A29: 23 | B29: 89328 | C29: =IF(B29>=B28,B29-B28,0)*10*0.58 -> 116 | D29: 12337 | E29: =IF(D29>=D28,D29-D28,0)*10*0.58 -> 145 | F29: 53513 | G29: =IF(F29>=F28,F29-F28,0)*0.58 -> 124.7 | H29: =C29+E29+G29 -> 385.7 | O29: =IF(N29>=N28,N29-N28,0) -> 0 | Q29: =(H29-O29)*0.58 -> 223.706 | S29: =IF(R29-R28>0,R29-R28,0) -> 0 | T29: =Elect!BT28 -> 182 | U29: =H29/T29 -> 2.1192308 | V29: =Elect!BV28 -> 0 | W29: =H29/V29 -> #DIV/0! | X29: =H29*V1 -> 1542.8 | Y29: =IF(X29>0,X29/T29,0) -> 8.4769231 | Z29: =IF(X29>0,X29/V29,0) -> #DIV/0!
A30: 24 | B30: 89349 | C30: =IF(B30>=B29,B30-B29,0)*10*0.58 -> 121.8 | D30: 12364 | E30: =IF(D30>=D29,D30-D29,0)*10*0.58 -> 156.6 | F30: 53730 | G30: =IF(F30>=F29,F30-F29,0)*0.58 -> 125.86 | H30: =C30+E30+G30 -> 404.26 | O30: =IF(N30>=N29,N30-N29,0) -> 0 | Q30: =(H30-O30)*0.58 -> 234.4708 | S30: =IF(R30-R29>0,R30-R29,0) -> 0 | T30: =Elect!BT29 -> 212 | U30: =H30/T30 -> 1.9068868 | V30: =Elect!BV29 -> 0 | W30: =H30/V30 -> #DIV/0! | X30: =H30*V1 -> 1617.04 | Y30: =IF(X30>0,X30/T30,0) -> 7.6275472 | Z30: =IF(X30>0,X30/V30,0) -> #DIV/0!
A31: 25 | B31: 89372 | C31: =IF(B31>=B30,B31-B30,0)*10*0.58 -> 133.4 | D31: 12394 | E31: =IF(D31>=D30,D31-D30,0)*10*0.58 -> 174 | F31: 53992 | G31: =IF(F31>=F30,F31-F30,0)*0.58 -> 151.96 | H31: =C31+E31+G31 -> 459.36 | O31: =IF(N31>=N30,N31-N30,0) -> 0 | Q31: =(H31-O31)*0.58 -> 266.4288 | S31: =IF(R31-R30>0,R31-R30,0) -> 0 | T31: =Elect!BT30 -> 188 | U31: =H31/T31 -> 2.4434043 | V31: =Elect!BV30 -> 0 | W31: =H31/V31 -> #DIV/0! | X31: =H31*V1 -> 1837.44 | Y31: =IF(X31>0,X31/T31,0) -> 9.773617 | Z31: =IF(X31>0,X31/V31,0) -> #DIV/0!
A32: 26 | B32: 89389 | C32: =IF(B32>=B31,B32-B31,0)*10*0.58 -> 98.6 | D32: 12416 | E32: =IF(D32>=D31,D32-D31,0)*10*0.58 -> 127.6 | F32: 54188 | G32: =IF(F32>=F31,F32-F31,0)*0.58 -> 113.68 | H32: =C32+E32+G32 -> 339.88 | O32: =IF(N32>=N31,N32-N31,0) -> 0 | Q32: =(H32-O32)*0.58 -> 197.1304 | S32: =IF(R32-R31>0,R32-R31,0) -> 0 | T32: =Elect!BT31 -> 219 | U32: =H32/T32 -> 1.5519635 | V32: =Elect!BV31 -> 0 | W32: =H32/V32 -> #DIV/0! | X32: =H32*V1 -> 1359.52 | Y32: =IF(X32>0,X32/T32,0) -> 6.2078539 | Z32: =IF(X32>0,X32/V32,0) -> #DIV/0!
A33: 27 | B33: 89410 | C33: =IF(B33>=B32,B33-B32,0)*10*0.58 -> 121.8 | D33: 12443 | E33: =IF(D33>=D32,D33-D32,0)*10*0.58 -> 156.6 | F33: 54407 | G33: =IF(F33>=F32,F33-F32,0)*0.58 -> 127.02 | H33: =C33+E33+G33 -> 405.42 | O33: =IF(N33>=N32,N33-N32,0) -> 0 | Q33: =(H33-O33)*0.58 -> 235.1436 | S33: =IF(R33-R32>0,R33-R32,0) -> 0 | T33: =Elect!BT32 -> 212 | U33: =H33/T33 -> 1.9123585 | V33: =Elect!BV32 -> 0 | W33: =H33/V33 -> #DIV/0! | X33: =H33*V1 -> 1621.68 | Y33: =IF(X33>0,X33/T33,0) -> 7.649434 | Z33: =IF(X33>0,X33/V33,0) -> #DIV/0!
A34: 28 | B34: 89431 | C34: =IF(B34>=B33,B34-B33,0)*10*0.58 -> 121.8 | D34: 12470 | E34: =IF(D34>=D33,D34-D33,0)*10*0.58 -> 156.6 | F34: 54844 | G34: =IF(F34>=F33,F34-F33,0)*0.58 -> 253.46 | H34: =C34+E34+G34 -> 531.86 | O34: =IF(N34>=N33,N34-N33,0) -> 0 | Q34: =(H34-O34)*0.58 -> 308.4788 | S34: =IF(R34-R33>0,R34-R33,0) -> 0 | T34: =Elect!BT33 -> 243 | U34: =H34/T34 -> 2.1887243 | V34: =Elect!BV33 -> 0 | W34: =H34/V34 -> #DIV/0! | X34: =H34*V1 -> 2127.44 | Y34: =IF(X34>0,X34/T34,0) -> 8.7548971 | Z34: =IF(X34>0,X34/V34,0) -> #DIV/0!
A35: 29 | B35: 89449 | C35: =IF(B35>=B34,B35-B34,0)*10*0.58 -> 104.4 | D35: 12494 | E35: =IF(D35>=D34,D35-D34,0)*10*0.58 -> 139.2 | F35: 54860 | G35: =IF(F35>=F34,F35-F34,0)*0.58 -> 9.28 | H35: =C35+E35+G35 -> 252.88 | O35: =IF(N35>=N34,N35-N34,0) -> 0 | Q35: =(H35-O35)*0.58 -> 146.6704 | S35: =IF(R35-R34>0,R35-R34,0) -> 0 | T35: =Elect!BT34 -> 247 | U35: =H35/T35 -> 1.0238057 | V35: =Elect!BV34 -> 0 | W35: =H35/V35 -> #DIV/0! | X35: =H35*V1 -> 1011.52 | Y35: =IF(X35>0,X35/T35,0) -> 4.0952227 | Z35: =IF(X35>0,X35/V35,0) -> #DIV/0!
A36: 30 | B36: 89469 | C36: =IF(B36>=B35,B36-B35,0)*10*0.58 -> 116 | D36: 12521 | E36: =IF(D36>=D35,D36-D35,0)*10*0.58 -> 156.6 | F36: 55086 | G36: =IF(F36>=F35,F36-F35,0)*0.58 -> 131.08 | H36: =C36+E36+G36 -> 403.68 | O36: =IF(N36>=N35,N36-N35,0) -> 0 | Q36: =(H36-O36)*0.58 -> 234.1344 | S36: =IF(R36-R35>0,R36-R35,0) -> 0 | T36: =Elect!BT35 -> 247 | U36: =H36/T36 -> 1.634332 | V36: =Elect!BV35 -> 0 | W36: =H36/V36 -> #DIV/0! | X36: =H36*V1 -> 1614.72 | Y36: =IF(X36>0,X36/T36,0) -> 6.5373279 | Z36: =IF(X36>0,X36/V36,0) -> #DIV/0!
A37: 31 | B37: 89487.667 | C37: =IF(B37>=B36,B37-B36,0)*10*0.58 -> 108.26667 | D37: 12546 | E37: =IF(D37>=D36,D37-D36,0)*10*0.58 -> 145 | F37: 55172 | G37: =IF(F37>=F36,F37-F36,0)*0.58 -> 49.88 | H37: =C37+E37+G37 -> 303.14667 | I37: 309 | K37: 5365 | O37: =IF(N37>=N36,N37-N36,0) -> 0 | Q37: =(H37-O37)*0.58 -> 175.82507 | S37: =IF(R37-R36>0,R37-R36,0) -> 0 | T37: =Elect!BT36 -> 238 | U37: =H37/T37 -> 1.2737255 | V37: =Elect!BV36 -> 0 | W37: =H37/V37 -> #DIV/0! | X37: =H37*V7 -> 0 | Y37: =IF(X37>0,X37/T37,0) -> 0 | Z37: =IF(X37>0,X37/V37,0) -> 0
A38: MTD | C38: =SUM(C7:C37) -> 3866.6667 | E38: =SUM(E7:E37) -> 5005.4 | G38: =SUM(G7:G37) -> 3928.34 | H38: =SUM(H7:H37) -> 12800.407 | I38: =I37-I6 -> 7 | K38: =K37-K6 -> 104 | O38: =SUM(O7:O36) -> 0 | Q38: =SUM(Q7:Q34) -> 6867.606 | S38: =SUM(S7:S34) -> 0 | T38: =SUM(T7:T36) -> 6575 | U38: =IF(H38>0,H38/T38,0) -> 1.9468299 | V38: =SUM(V7:V36) -> 0 | W38: =IF(H38>0,H38/V38,0) -> #DIV/0! | X38: =SUM(X7:X36) -> 49989.04 | Y38: =IF(X38>0,X38/T38,0) -> 7.6028958 | Z38: =IF(X38>0,X38/V38,0) -> #DIV/0!
A39: AVER. Act | C39: =C38/B48 -> 128.88889 | E39: =E38/B48 -> 166.84667 | G39: =G38/B48 -> 130.94467 | H39: =H38/B48 -> 426.68022 | O39: =O38/B48 -> 0 | Q39: =Q38/B48 -> 228.9202 | S39: =S38/C48 -> #DIV/0! | T39: =T38/B48 -> 219.16667 | U39: =IF(H39>0,H39/T39,0) -> 1.9468299 | V39: =V38/B48 -> 0 | W39: =IF(H39>0,H39/V39,0) -> #DIV/0! | X39: =X38/B48 -> 1666.3013 | Y39: =IF(X39>0,X39/T39,0) -> 7.6028958 | Z39: =IF(X39>0,X39/V39,0) -> #DIV/0!
A40: TOTAL Budget | T40: =YTD!Q2341 -> 0 | U40: =IF(#REF!>0,#REF!/T40,0) -> #REF! | V40: =YTD!Q2342 -> 0 | W40: =IF(#REF!>0,#REF!/V40,0) -> #REF! | X40: =YTD!Q2346 -> 0 | Y40: =IF(X40>0,X40/T40,0) -> 0 | Z40: =IF(X40>0,X40/V40,0) -> 0
A41: Budget MTD | T41: =T42*C48 -> #VALUE! | U41: =IF(#REF!>0,#REF!/T41,0) -> #REF! | V41: =V42*C48 -> #VALUE! | W41: =IF(#REF!>0,#REF!/V41,0) -> #REF! | X41: =#REF!*5.62 -> #REF! | Y41: =IF(X41>0,X41/T41,0) -> #REF! | Z41: =IF(X41>0,X41/V41,0) -> #REF!
A42: AVER. Bud | T42: =T40/$A$48 -> #VALUE! | V42: =V40/$A$48 -> #VALUE!
A43: Total RFC | T43: =YTD!Q2358 -> 0 | V43: =YTD!Q2359 -> 0 | X43: =YTD!Q2363 -> 0 | Y43: =IF(X43>0,X43/T43,0) -> 0 | Z43: =IF(X43>0,X43/V43,0) -> 0
A44: RFC MTD | T44: =T43/A48*C48 -> #VALUE! | V44: =V43/A48*C48 -> #VALUE! | X44: =X43/A48*C48 -> #VALUE! | Y44: =IF(X44>0,X44/T44,0) -> #VALUE! | Z44: =IF(X44>0,X44/V44,0) -> #VALUE!
A45: AVER RFC | T45: =T43/A48 -> #VALUE! | V45: =V44/A48*C48 -> #VALUE! | X45: =X43/A48 -> #VALUE!
A46: MTD 13 | U46: =Consp!BH33 -> 1.1514679 | W46: =Consp!BI33 -> 0.57929342 | X46: =Consp!BJ33 -> 140121.3 | Y46: =Consp!BK33 -> 6.8331854 | Z46: =Consp!BL33 -> 3.4377159
A47: AVER. Act 13 | U47: =Consp!BH34 -> 1.1761372 | W47: =Consp!BI34 -> 0.60007377 | X47: =Consp!BJ34 -> 5004.3322 | Y47: =Consp!BK34 -> 6.8331854 | Z47: =Consp!BL34 -> 3.4377159
A48: No of Days MTD | B48: =COUNTIF(B7:B36,">0") -> 30
A136: Water Incoming

Sheet Gas
A1: =Elect!A1 -> 44835 | E1: Gas | H1: Gas UP | J1: 3.9
A4: NO. | B4: Main Gas Flow Meter | D4: Laundry Gas Flow Meter | F4: Grumandiz Gas Flow Meter | H4: Plant Room Gas Share Cost | I4: Hotel Consumption Cost | J4: La Grumandiz Cost | K4: Total Natural Gas Consumption
B5: Read | C5: Cons | D5: Read | E5: Cons | F5: Read | G5: Cons | H5: LE/DAY | I5: LE/DAY | J5: LE/DAY | K5: Cons
B6: 8325662 | C6: =IF(B6>=B5,B6-B5,0)*1.06 -> 0 | D6: 570405 | E6: =IF(D6>=D5,D6-D5,0)*0.7 -> 0 | F6: 623957 | G6: =IF(F6>=F5,F6-F5,0) -> 0 | K6: =C6+E6 -> 0
A7: 1 | B7: 8326849 | C7: =IF(B7>=B6,B7-B6,0)*1.06 -> 1258.22 | D7: 570859 | E7: =IF(D7>=D6,D7-D6,0)*0.7 -> 317.8 | F7: 624025 | G7: =IF(F7>=F6,F7-F6,0) -> 68 | H7: =(E7*0.55)*1.61 -> 281.4119 | I7: =C7*J1 -> 4907.058 | J7: =G7*J1 -> 265.2 | K7: =C7+E7 -> 1576.02
A8: 2 | B8: 8328133 | C8: =IF(B8>=B7,B8-B7,0)*1.06 -> 1361.04 | D8: 571223 | E8: =IF(D8>=D7,D8-D7,0)*0.7 -> 254.8 | F8: 624122 | G8: =IF(F8>=F7,F8-F7,0) -> 97 | H8: =(E8*0.55)*1.61 -> 225.6254 | I8: =C8*J1 -> 5308.056 | J8: =G8*J1 -> 378.3 | K8: =C8+E8 -> 1615.84
A9: 3 | B9: 8329309 | C9: =IF(B9>=B8,B9-B8,0)*1.06 -> 1246.56 | D9: 571774 | E9: =IF(D9>=D8,D9-D8,0)*0.7 -> 385.7 | F9: 624218 | G9: =IF(F9>=F8,F9-F8,0) -> 96 | H9: =(E9*0.55)*1.61 -> 341.53735 | I9: =C9*J1 -> 4861.584 | J9: =G9*J1 -> 374.4 | K9: =C9+E9 -> 1632.26
A10: 4 | B10: 8330425 | C10: =IF(B10>=B9,B10-B9,0)*1.06 -> 1182.96 | D10: 572184 | E10: =IF(D10>=D9,D10-D9,0)*0.7 -> 287 | F10: 624297 | G10: =IF(F10>=F9,F10-F9,0) -> 79 | H10: =(E10*0.55)*1.61 -> 254.1385 | I10: =C10*J1 -> 4613.544 | J10: =G10*J1 -> 308.1 | K10: =C10+E10 -> 1469.96
A11: 5 | B11: 8331672 | C11: =IF(B11>=B10,B11-B10,0)*1.06 -> 1321.82 | D11: 572591 | E11: =IF(D11>=D10,D11-D10,0)*0.7 -> 284.9 | F11: 624387 | G11: =IF(F11>=F10,F11-F10,0) -> 90 | H11: =(E11*0.55)*1.61 -> 252.27895 | I11: =C11*J1 -> 5155.098 | J11: =G11*J1 -> 351 | K11: =C11+E11 -> 1606.72
A12: 6 | B12: 8332790 | C12: =IF(B12>=B11,B12-B11,0)*1.06 -> 1185.08 | D12: 572999 | E12: =IF(D12>=D11,D12-D11,0)*0.7 -> 285.6 | F12: 624467 | G12: =IF(F12>=F11,F12-F11,0) -> 80 | H12: =(E12*0.55)*1.61 -> 252.8988 | I12: =C12*J1 -> 4621.812 | J12: =G12*J1 -> 312 | K12: =C12+E12 -> 1470.68
A13: 7 | B13: 8334124 | C13: =IF(B13>=B12,B13-B12,0)*1.06 -> 1414.04 | D13: 573430 | E13: =IF(D13>=D12,D13-D12,0)*0.7 -> 301.7 | F13: 624557 | G13: =IF(F13>=F12,F13-F12,0) -> 90 | H13: =(E13*0.55)*1.61 -> 267.15535 | I13: =C13*J1 -> 5514.756 | J13: =G13*J1 -> 351 | K13: =C13+E13 -> 1715.74
A14: 8 | B14: 8335451 | C14: =IF(B14>=B13,B14-B13,0)*1.06 -> 1406.62 | D14: 573875 | E14: =IF(D14>=D13,D14-D13,0)*0.7 -> 311.5 | F14: 624642 | G14: =IF(F14>=F13,F14-F13,0) -> 85 | H14: =(E14*0.55)*1.61 -> 275.83325 | I14: =C14*J1 -> 5485.818 | J14: =G14*J1 -> 331.5 | K14: =C14+E14 -> 1718.12
A15: 9 | B15: 8336725 | C15: =IF(B15>=B14,B15-B14,0)*1.06 -> 1350.44 | D15: 574310.67 | E15: =IF(D15>=D14,D15-D14,0)*0.7 -> 304.96667 | F15: 624732 | G15: =IF(F15>=F14,F15-F14,0) -> 90 | H15: =(E15*0.55)*1.61 -> 270.04798 | I15: =C15*J1 -> 5266.716 | J15: =G15*J1 -> 351 | K15: =C15+E15 -> 1655.4067
A16: 10 | B16: 8338072 | C16: =IF(B16>=B15,B16-B15,0)*1.06 -> 1427.82 | D16: 574749 | E16: =IF(D16>=D15,D16-D15,0)*0.7 -> 306.83333 | F16: 624824 | G16: =IF(F16>=F15,F16-F15,0) -> 92 | H16: =(E16*0.55)*1.61 -> 271.70092 | I16: =C16*J1 -> 5568.498 | J16: =G16*J1 -> 358.8 | K16: =C16+E16 -> 1734.6533
A17: 11 | B17: 8339370.3 | C17: =IF(B17>=B16,B17-B16,0)*1.06 -> 1376.2333 | D17: 575185.56 | E17: =IF(D17>=D16,D17-D16,0)*0.7 -> 305.58889 | F17: 624914.67 | G17: =IF(F17>=F16,F17-F16,0) -> 90.666667 | H17: =(E17*0.55)*1.61 -> 270.59896 | I17: =C17*J1 -> 5367.31 | J17: =G17*J1 -> 353.6 | K17: =C17+E17 -> 1681.8222
A18: 12 | B18: 8340620 | C18: =IF(B18>=B17,B18-B17,0)*1.06 -> 1324.6467 | D18: 575605 | E18: =IF(D18>=D17,D18-D17,0)*0.7 -> 293.61111 | F18: 624997 | G18: =IF(F18>=F17,F18-F17,0) -> 82.333333 | H18: =(E18*0.55)*1.61 -> 259.99264 | I18: =C18*J1 -> 5166.122 | J18: =G18*J1 -> 321.1 | K18: =C18+E18 -> 1618.2578
A19: 13 | B19: 8341899 | C19: =IF(B19>=B18,B19-B18,0)*1.06 -> 1355.74 | D19: 576045 | E19: =IF(D19>=D18,D19-D18,0)*0.7 -> 308 | F19: 625097 | G19: =IF(F19>=F18,F19-F18,0) -> 100 | H19: =(E19*0.55)*1.61 -> 272.734 | I19: =C19*J1 -> 5287.386 | J19: =G19*J1 -> 390 | K19: =C19+E19 -> 1663.74
A20: 14 | B20: 8343169 | C20: =IF(B20>=B19,B20-B19,0)*1.06 -> 1346.2 | D20: 576481 | E20: =IF(D20>=D19,D20-D19,0)*0.7 -> 305.2 | F20: 625181 | G20: =IF(F20>=F19,F20-F19,0) -> 84 | H20: =(E20*0.55)*1.61 -> 270.2546 | I20: =C20*J1 -> 5250.18 | J20: =G20*J1 -> 327.6 | K20: =C20+E20 -> 1651.4
A21: 15 | B21: 8344440 | C21: =IF(B21>=B20,B21-B20,0)*1.06 -> 1347.26 | D21: 576950 | E21: =IF(D21>=D20,D21-D20,0)*0.7 -> 328.3 | F21: 625271 | G21: =IF(F21>=F20,F21-F20,0) -> 90 | H21: =(E21*0.55)*1.61 -> 290.70965 | I21: =C21*J1 -> 5254.314 | J21: =G21*J1 -> 351 | K21: =C21+E21 -> 1675.56
A22: 16 | B22: 8345828 | C22: =IF(B22>=B21,B22-B21,0)*1.06 -> 1471.28 | D22: 577505 | E22: =IF(D22>=D21,D22-D21,0)*0.7 -> 388.5 | F22: 625362 | G22: =IF(F22>=F21,F22-F21,0) -> 91 | H22: =(E22*0.55)*1.61 -> 344.01675 | I22: =C22*J1 -> 5737.992 | J22: =G22*J1 -> 354.9 | K22: =C22+E22 -> 1859.78
A23: 17 | B23: 8347209 | C23: =IF(B23>=B22,B23-B22,0)*1.06 -> 1463.86 | D23: 577887 | E23: =IF(D23>=D22,D23-D22,0)*0.7 -> 267.4 | F23: 625436 | G23: =IF(F23>=F22,F23-F22,0) -> 74 | H23: =(E23*0.55)*1.61 -> 236.7827 | I23: =C23*J1 -> 5709.054 | J23: =G23*J1 -> 288.6 | K23: =C23+E23 -> 1731.26
A24: 18 | B24: 8348566 | C24: =IF(B24>=B23,B24-B23,0)*1.06 -> 1438.42 | D24: 578371 | E24: =IF(D24>=D23,D24-D23,0)*0.7 -> 338.8 | F24: 625532 | G24: =IF(F24>=F23,F24-F23,0) -> 96 | H24: =(E24*0.55)*1.61 -> 300.0074 | I24: =C24*J1 -> 5609.838 | J24: =G24*J1 -> 374.4 | K24: =C24+E24 -> 1777.22
A25: 19 | B25: 8349939 | C25: =IF(B25>=B24,B25-B24,0)*1.06 -> 1455.38 | D25: 578839 | E25: =IF(D25>=D24,D25-D24,0)*0.7 -> 327.6 | F25: 625620 | G25: =IF(F25>=F24,F25-F24,0) -> 88 | H25: =(E25*0.55)*1.61 -> 290.0898 | I25: =C25*J1 -> 5675.982 | J25: =G25*J1 -> 343.2 | K25: =C25+E25 -> 1782.98
A26: 20 | B26: 8351103 | C26: =IF(B26>=B25,B26-B25,0)*1.06 -> 1233.84 | D26: 579275 | E26: =IF(D26>=D25,D26-D25,0)*0.7 -> 305.2 | F26: 625706 | G26: =IF(F26>=F25,F26-F25,0) -> 86 | H26: =(E26*0.55)*1.61 -> 270.2546 | I26: =C26*J1 -> 4811.976 | J26: =G26*J1 -> 335.4 | K26: =C26+E26 -> 1539.04
A27: 21 | B27: 8352441 | C27: =IF(B27>=B26,B27-B26,0)*1.06 -> 1418.28 | D27: 579738 | E27: =IF(D27>=D26,D27-D26,0)*0.7 -> 324.1 | F27: 625797 | G27: =IF(F27>=F26,F27-F26,0) -> 91 | H27: =(E27*0.55)*1.61 -> 286.99055 | I27: =C27*J1 -> 5531.292 | J27: =G27*J1 -> 354.9 | K27: =C27+E27 -> 1742.38
A28: 22 | B28: 8353743 | C28: =IF(B28>=B27,B28-B27,0)*1.06 -> 1380.12 | D28: 580257 | E28: =IF(D28>=D27,D28-D27,0)*0.7 -> 363.3 | F28: 625892 | G28: =IF(F28>=F27,F28-F27,0) -> 95 | H28: =(E28*0.55)*1.61 -> 321.70215 | I28: =C28*J1 -> 5382.468 | J28: =G28*J1 -> 370.5
A29: 23 | B29: 8354914 | C29: =IF(B29>=B28,B29-B28,0)*1.06 -> 1241.26 | D29: 580692 | E29: =IF(D29>=D28,D29-D28,0)*0.7 -> 304.5 | F29: 625979 | G29: =IF(F29>=F28,F29-F28,0) -> 87 | H29: =(E29*0.55)*1.61 -> 269.63475 | I29: =C29*J1 -> 4840.914 | J29: =G29*J1 -> 339.3 | K29: =C29+E29 -> 1545.76
A30: 24 | B30: 8356215 | C30: =IF(B30>=B29,B30-B29,0)*1.06 -> 1379.06 | D30: 581142 | E30: =IF(D30>=D29,D30-D29,0)*0.7 -> 315 | F30: 626067 | G30: =IF(F30>=F29,F30-F29,0) -> 88 | H30: =(E30*0.55)*1.61 -> 278.9325 | I30: =C30*J1 -> 5378.334 | J30: =G30*J1 -> 343.2 | K30: =C30+E30 -> 1694.06
A31: 25 | B31: 8357899 | C31: =IF(B31>=B30,B31-B30,0)*1.06 -> 1785.04 | D31: 581609 | E31: =IF(D31>=D30,D31-D30,0)*0.7 -> 326.9 | F31: 626177 | G31: =IF(F31>=F30,F31-F30,0) -> 110 | H31: =(E31*0.55)*1.61 -> 289.46995 | I31: =C31*J3 -> 0 | J31: =G31*J1 -> 429 | K31: =C31+E31 -> 2111.94
A32: 26 | B32: 8359164 | C32: =IF(B32>=B31,B32-B31,0)*1.06 -> 1340.9 | D32: 581964 | E32: =IF(D32>=D31,D32-D31,0)*0.7 -> 248.5 | F32: 626201 | G32: =IF(F32>=F31,F32-F31,0) -> 24 | H32: =(E32*0.55)*1.61 -> 220.04675 | I32: =C32*J1 -> 5229.51 | J32: =G32*J1 -> 93.6 | K32: =C32+E32 -> 1589.4
A33: 27 | B33: 8360290 | C33: =IF(B33>=B32,B33-B32,0)*1.06 -> 1193.56 | D33: 582449 | E33: =IF(D33>=D32,D33-D32,0)*0.7 -> 339.5 | F33: 626230 | G33: =IF(F33>=F32,F33-F32,0) -> 29 | H33: =(E33*0.55)*1.61 -> 300.62725 | I33: =C33*J1 -> 4654.884 | J33: =G33*J1 -> 113.1 | K33: =C33+E33 -> 1533.06
A34: 28 | B34: 8361770 | C34: =IF(B34>=B33,B34-B33,0)*1.06 -> 1568.8 | D34: 582920 | E34: =IF(D34>=D33,D34-D33,0)*0.7 -> 329.7 | F34: 626420 | G34: =IF(F34>=F33,F34-F33,0) -> 190 | H34: =(E34*0.55)*1.61 -> 291.94935 | I34: =C34*J1 -> 6118.32 | J34: =G34*J1 -> 741 | K34: =C34+E34 -> 1898.5
A35: 29 | B35: 8363041 | C35: =IF(B35>=B34,B35-B34,0)*1.06 -> 1347.26 | D35: 583332 | E35: =IF(D35>=D34,D35-D34,0)*0.7 -> 288.4 | F35: 626502 | G35: =IF(F35>=F34,F35-F34,0) -> 82 | H35: =(E35*0.55)*1.61 -> 255.3782 | I35: =C35*J1 -> 5254.314 | J35: =G35*J1 -> 319.8 | K35: =C35+E35 -> 1635.66
A36: 30 | B36: 8364341 | C36: =IF(B36>=B35,B36-B35,0)*1.06 -> 1378 | D36: 583821 | E36: =IF(D36>=D35,D36-D35,0)*0.7 -> 342.3 | F36: 626575 | G36: =IF(F36>=F35,F36-F35,0) -> 73 | H36: =(E36*0.55)*1.61 -> 303.10665 | I36: =C36*J1 -> 5374.2 | J36: =G36*J1 -> 284.7 | K36: =C36+E36 -> 1720.3
A37: 31 | B37: 8365621.7 | C37: =IF(B37>=B36,B37-B36,0)*1.06 -> 1357.5067 | D37: 584258.67 | E37: =IF(D37>=D36,D37-D36,0)*0.7 -> 306.36667 | F37: 626654 | G37: =IF(F37>=F36,F37-F36,0) -> 79 | H37: =(E37*0.55)*1.61 -> 271.28768 | I37: =C37*J1 -> 5294.276 | J37: =G37*J1 -> 308.1 | K37: =C37+E37 -> 1663.8733
A38: MTD | C38: =SUM(C7:C37) -> 42357.247 | E38: =SUM(E7:E37) -> 9697.5667 | G38: =SUM(G7:G37) -> 2697 | H38: =SUM(H6:H37) -> 8587.1953 | I38: =SUM(I6:I37) -> 158231.61 | J38: =SUM(J6:J37) -> 10518.3 | K38: =SUM(K6:K37) -> 50311.393
A39: Average MTD. | C39: =C38/A42 -> 1411.9082 | E39: =E38/A42 -> 323.25222 | G39: =G38/A42 -> 89.9 | H39: =H38/A42 -> 286.23984 | I39: =I38/A42 -> 5274.3869 | J39: =J38/A42 -> 350.61
A41: No of Days MTD
A42: =COUNTIF(B7:B36,">0") -> 30

Sheet Sheet1

Sheet Sheet2

Sheet Consp
A1: =Elect!A1 -> 44835 | L1: Summary | P1: =Elect!A1 -> 44835
B2: Elect Consuumption | H2: Water Incoming | U2: Water Consumption | AC2: Irrigation | AG2: Gas | AJ2: Cost | AK2: Solar Meter [ LIT ] | AL2: No. of Eng. | AM2: No. of Gardners | AN2: Cons. (lit) | AO2: Received Gas (tons) | AP2: Fuel Cost | AQ2: Solar level [cm] | AR2: Received Solar (tons) | AS2: Fuel Cost | AT2: Occupancy 10 | AV2: Occupancy07 | AZ2: Elect 2009 | BE2: Elect 2010 | BJ2: Water 2009 | BO2: Water 2010
A3: Date | B3: COUNTER (2) | D3: MD | F3: KVAR | H3: R.O | J3: Qenna | L3: Trucks | N3: Rimievera Line Meter | O3: Total Inc. | Q3: Total Main S.Pool | S3: Total Bar & Beach cons. | U3: Total S. Pool cons. | W3: Hotel consumption. | Y3: Sold Water | AA3: Irr. Water from R.O | AC3: Irr. Consumption. | AE3: Storage Water One tank | AF3: Grand Cons | AG3: % | AH3: Stock | AI3: Cons. | AJ3: 0 | AT3: No of guest | AU3: No. of rooms | AV3: No. of rooms | AW3: No. of guest | AX3: Cons. Per occ. room | AY3: Cons. Per guest | AZ3: Total cost | BA3: cost per room | BB3: cost per guest | BC3: Cons. Per occ. room | BD3: Cons. Per guest | BE3: Total cost | BF3: cost per room | BG3: cost per guest | BH3: Cons. Per occ. room | BI3: Cons. Per guest | BJ3: Total cost | BK3: cost per room | BL3: cost per guest | BM3: Cons. Per occ. room | BN3: Cons. Per guest | BO3: Total cost | BP3: cost per room | BQ3: cost per guest
B4: 2013 | C4: 2014 | D4: 2013 | E4: 2014 | F4: 2013 | G4: 2014 | H4: 2013 | I4: 2014 | J4: 2009 | K4: 2010 | L4: 2009 | M4: 2010 | O4: 2009 | P4: 2010 | Q4: 2009 | R4: 2010 | S4: 2009 | T4: 2010 | U4: 2009 | V4: 2010 | W4: 2009 | X4: 2010 | Y4: 2009 | Z4: 2010 | AA4: 2009 | AB4: 2010 | AC4: 2009 | AD4: 2010
A5: 1 | B5: 33600 | C5: =Elect!J6 -> 2039 | D5: 0 | E5: =Elect!M6 -> 1614 | F5: 20 | G5: =Elect!O6 -> 124 | H5: 800 | I5: =Water!C7 -> 121.8 | J5: 0 | K5: =Water!E7 -> 150.8 | L5: 0 | M5: =Water!#REF! -> #REF! | N5: =Water!#REF! -> #REF! | O5: 1005 | P5: =Water!H7 -> 398.46 | Q5: 114 | R5: =Water!O7 -> 0 | S5: 13 | T5: =Water!#REF! -> #REF! | U5: 147 | V5: =Water!#REF! -> #REF! | W5: 755 | X5: =Water!Q7 -> 231.1068 | Y5: 0 | Z5: =Water!#REF! -> #REF! | AA5: 0 | AB5: 0 | AC5: 690 | AD5: =Water!#REF! -> #REF! | AE5: =Water!#REF! -> #REF! | AF5: =Water!#REF! -> #REF! | AG5: =Gas!#REF! -> #REF! | AH5: =Gas!C7 -> 1258.22 | AI5: =Gas!#REF! -> #REF! | AJ5: =Gas!J7 -> 265.2 | AK5: =Gas!#REF! -> #REF! | AL5: =Gas!#REF! -> #REF! | AM5: =Gas!#REF! -> #REF! | AN5: =Gas!#REF! -> #REF! | AO5: =Gas!#REF! -> #REF! | AP5: =Gas!#REF! -> #REF! | AQ5: =Gas!#REF! -> #REF! | AR5: =Gas!#REF! -> #REF! | AS5: =Gas!#REF! -> #REF! | AT5: =Elect!BR6 -> 171 | AU5: =Elect!BP6 -> 127 | AV5: =Elect!#REF! -> #REF! | AW5: =Elect!BR6 -> 171 | AX5: 48.695652 | AY5: 24.705882 | AZ5: 8835.4834 | BA5: 12.805048 | BB5: 6.496679 | BC5: =Elect!#REF! -> #REF! | BD5: =Elect!#REF! -> #REF! | BE5: =Elect!#REF! -> #REF! | BF5: =Elect!#REF! -> #REF! | BG5: =Elect!#REF! -> #REF! | BH5: 1.142029 | BI5: 0.57941176 | BJ5: 4569.1158 | BK5: 6.6219069 | BL5: 3.3596439 | BM5: =Water!U7 -> 1.7553304 | BN5: =Water!W7 -> #DIV/0! | BO5: =Water!X7 -> 1593.84 | BP5: =Water!Y7 -> 7.0213216 | BQ5: =Water!Z7 -> 0
A6: 2 | B6: 31200 | C6: =Elect!J7 -> 0 | D6: 0 | E6: =Elect!M7 -> 1804 | F6: 20 | G6: =Elect!O7 -> 1536 | H6: 936 | I6: =Water!C8 -> 133.4 | J6: 0 | K6: =Water!E8 -> 174 | L6: 0 | M6: =Water!#REF! -> #REF! | N6: =Water!#REF! -> #REF! | O6: 1006 | P6: =Water!H8 -> 437.9 | Q6: 113 | R6: =Water!O8 -> 0 | S6: 17 | T6: =Water!#REF! -> #REF! | U6: 140 | V6: =Water!#REF! -> #REF! | W6: 792 | X6: =Water!Q8 -> 253.982 | Y6: 0 | Z6: =Water!#REF! -> #REF! | AA6: 0 | AB6: 0 | AC6: 370 | AD6: =Water!#REF! -> #REF! | AE6: =Water!#REF! -> #REF! | AF6: =Water!#REF! -> #REF! | AG6: =Gas!B7 -> 8326849 | AH6: =Gas!C8 -> 1361.04 | AI6: =Gas!#REF! -> #REF! | AJ6: =Gas!J8 -> 378.3 | AK6: =Gas!#REF! -> #REF! | AL6: =Gas!#REF! -> #REF! | AM6: =Gas!#REF! -> #REF! | AN6: =Gas!#REF! -> #REF! | AO6: =Gas!#REF! -> #REF! | AP6: =Gas!#REF! -> #REF! | AQ6: =Gas!#REF! -> #REF! | AR6: =Gas!#REF! -> #REF! | AS6: =Gas!#REF! -> #REF! | AT6: =Elect!BR7 -> 150 | AU6: =Elect!BP7 -> 113 | AX6: 47.416413 | AY6: 23.981553 | AZ6: 8299.2754 | BA6: 12.612881 | BB6: 6.379151 | BC6: =Elect!BQ7 -> 554065 | BD6: =Elect!#REF! -> #REF! | BE6: =Elect!#REF! -> #REF! | BF6: =Elect!#REF! -> #REF! | BG6: =Elect!#REF! -> #REF! | BH6: 1.2021277 | BI6: 0.60799385 | BJ6: 5345.8654 | BK6: 8.1244156 | BL6: 4.1090434 | BM6: =Water!U8 -> 1.8020576 | BN6: =Water!W8 -> #DIV/0! | BO6: =Water!X8 -> 1751.6 | BP6: =Water!Y8 -> 7.2082305 | BQ6: =Water!Z8 -> #DIV/0!
A7: 3 | B7: 31200 | C7: =Elect!J8 -> 5969.1111 | D7: 0 | E7: =Elect!M8 -> 2443 | F7: 20 | G7: =Elect!O8 -> 2009 | H7: 685 | I7: =Water!C9 -> 127.6 | J7: 0 | K7: =Water!E9 -> 156.6 | L7: 0 | M7: =Water!#REF! -> #REF! | N7: =Water!#REF! -> #REF! | O7: 902 | P7: =Water!H9 -> 418.18 | Q7: 126 | R7: =Water!O9 -> 0 | S7: 26 | T7: =Water!#REF! -> #REF! | U7: 134 | V7: =Water!#REF! -> #REF! | W7: 766 | X7: =Water!Q9 -> 242.5444 | Y7: 0 | Z7: =Water!#REF! -> #REF! | AA7: 0 | AB7: 0 | AC7: 740 | AD7: =Water!#REF! -> #REF! | AE7: =Water!#REF! -> #REF! | AF7: =Water!#REF! -> #REF! | AG7: =Gas!B9 -> 8329309 | AH7: =Gas!C9 -> 1246.56 | AI7: =Gas!#REF! -> #REF! | AJ7: =Gas!J9 -> 374.4 | AK7: =Gas!#REF! -> #REF! | AL7: =Gas!#REF! -> #REF! | AM7: =Gas!#REF! -> #REF! | AN7: =Gas!#REF! -> #REF! | AO7: =Gas!#REF! -> #REF! | AP7: =Gas!#REF! -> #REF! | AQ7: =Gas!#REF! -> #REF! | AR7: =Gas!#REF! -> #REF! | AS7: =Gas!#REF! -> #REF! | AT7: =Elect!BR8 -> 140 | AU7: =Elect!BP8 -> 109 | AX7: 47.926267 | AY7: 24.223602 | AZ7: 8299.2754 | BA7: 12.748503 | BB7: 6.4435368 | BC7: =Elect!BQ8 -> 554205 | BD7: =Elect!#REF! -> #REF! | BE7: =Elect!#REF! -> #REF! | BF7: =Elect!#REF! -> #REF! | BG7: =Elect!#REF! -> #REF! | BH7: 1.0875576 | BI7: 0.54968944 | BJ7: 3912.3054 | BK7: 6.0096857 | BL7: 3.0375042 | BM7: =Water!U9 -> 1.9008182 | BN7: =Water!W9 -> #DIV/0! | BO7: =Water!X9 -> 1672.72 | BP7: =Water!Y9 -> 7.6032727 | BQ7: =Water!Z9 -> #DIV/0!
A8: 4 | B8: 33600 | C8: =Elect!J9 -> 5969.1111 | D8: 0 | E8: =Elect!M9 -> 1726 | F8: 20 | G8: =Elect!O9 -> 1379 | H8: 786 | I8: =Water!C10 -> 139.2 | J8: 0 | K8: =Water!E10 -> 185.6 | L8: 0 | M8: =Water!#REF! -> #REF! | N8: =Water!#REF! -> #REF! | O8: 930 | P8: =Water!H10 -> 452.4 | Q8: 153 | R8: =Water!O10 -> 0 | S8: 46 | T8: =Water!#REF! -> #REF! | U8: 150 | V8: =Water!#REF! -> #REF! | W8: 766 | X8: =Water!Q10 -> 262.392 | Y8: 0 | Z8: =Water!#REF! -> #REF! | AA8: 0 | AB8: 0 | AC8: 820 | AD8: =Water!#REF! -> #REF! | AE8: =Water!#REF! -> #REF! | AF8: =Water!#REF! -> #REF! | AG8: =Gas!B10 -> 8330425 | AH8: =Gas!C10 -> 1182.96 | AI8: =Gas!#REF! -> #REF! | AJ8: =Gas!J10 -> 308.1 | AK8: =Gas!#REF! -> #REF! | AL8: =Gas!#REF! -> #REF! | AM8: =Gas!#REF! -> #REF! | AN8: =Gas!#REF! -> #REF! | AO8: =Gas!#REF! -> #REF! | AP8: =Gas!#REF! -> #REF! | AQ8: =Gas!#REF! -> #REF! | AR8: =Gas!#REF! -> #REF! | AS8: =Gas!#REF! -> #REF! | AT8: =Elect!BR9 -> 143 | AU8: =Elect!BP9 -> 106 | AX8: 51.06383 | AY8: 25.866051 | AZ8: 8835.4834 | BA8: 13.427786 | BB8: 6.8017578 | BC8: =Elect!BQ9 -> 554348 | BD8: =Elect!#REF! -> #REF! | BE8: =Elect!#REF! -> #REF! | BF8: =Elect!#REF! -> #REF! | BG8: =Elect!#REF! -> #REF! | BH8: 1.2218845 | BI8: 0.61893764 | BJ8: 4489.1562 | BK8: 6.8224259 | BL8: 3.4558555 | BM8: =Water!U10 -> 2.2285714 | BN8: =Water!W10 -> #DIV/0! | BO8: =Water!X10 -> 1809.6 | BP8: =Water!Y10 -> 8.9142857 | BQ8: =Water!Z10 -> #DIV/0!
A9: 5 | B9: 31200 | C9: =Elect!J10 -> 5969.1111 | D9: 0 | E9: =Elect!M10 -> 2113 | F9: 20 | G9: =Elect!O10 -> 1699 | H9: 789 | I9: =Water!C11 -> 127.6 | J9: 0 | K9: =Water!E11 -> 174 | L9: 0 | M9: =Water!#REF! -> #REF! | N9: =Water!#REF! -> #REF! | O9: 1003 | P9: =Water!H11 -> 436.16 | Q9: 102 | R9: =Water!O11 -> 0 | S9: 8 | T9: =Water!#REF! -> #REF! | U9: 130 | V9: =Water!#REF! -> #REF! | W9: 735 | X9: =Water!Q11 -> 252.9728 | Y9: 0 | Z9: =Water!#REF! -> #REF! | AA9: 0 | AB9: 0 | AC9: 640 | AD9: =Water!#REF! -> #REF! | AE9: =Water!#REF! -> #REF! | AF9: =Water!#REF! -> #REF! | AG9: =Gas!B11 -> 8331672 | AH9: =Gas!C11 -> 1321.82 | AI9: =Gas!#REF! -> #REF! | AJ9: =Gas!J11 -> 351 | AK9: =Gas!#REF! -> #REF! | AL9: =Gas!#REF! -> #REF! | AM9: =Gas!#REF! -> #REF! | AN9: =Gas!#REF! -> #REF! | AO9: =Gas!#REF! -> #REF! | AP9: =Gas!#REF! -> #REF! | AQ9: =Gas!#REF! -> #REF! | AR9: =Gas!#REF! -> #REF! | AS9: =Gas!#REF! -> #REF! | AT9: =Elect!BR10 -> 152 | AU9: =Elect!BP10 -> 108 | AX9: 49.840256 | AY9: 25.181598 | AZ9: 8299.2754 | BA9: 13.257628 | BB9: 6.698366 | BC9: =Elect!BQ10 -> 554500 | BD9: =Elect!#REF! -> #REF! | BE9: =Elect!#REF! -> #REF! | BF9: =Elect!#REF! -> #REF! | BG9: =Elect!#REF! -> #REF! | BH9: 1.1980831 | BI9: 0.60532688 | BJ9: 4506.2904 | BK9: 7.198547 | BL9: 3.6370383 | BM9: =Water!U11 -> 2.3324064 | BN9: =Water!W11 -> #DIV/0! | BO9: =Water!X11 -> 1744.64 | BP9: =Water!Y11 -> 9.3296257 | BQ9: =Water!Z11 -> #DIV/0!
A10: 6 | B10: 33600 | C10: =Elect!J11 -> 5969.1111 | D10: 0 | E10: =Elect!M11 -> 1984 | F10: 20 | G10: =Elect!O11 -> 1548 | H10: 805 | I10: =Water!C12 -> 127.6 | J10: 0 | K10: =Water!E12 -> 162.4 | L10: 0 | M10: =Water!#REF! -> #REF! | N10: =Water!#REF! -> #REF! | O10: 1004 | P10: =Water!H12 -> 422.24 | Q10: 115 | R10: =Water!O12 -> 0 | S10: 21 | T10: =Water!#REF! -> #REF! | U10: 141 | V10: =Water!#REF! -> #REF! | W10: 725 | X10: =Water!Q12 -> 244.8992 | Y10: 0 | Z10: =Water!#REF! -> #REF! | AA10: 0 | AB10: 0 | AC10: 510 | AD10: =Water!#REF! -> #REF! | AE10: =Water!#REF! -> #REF! | AF10: =Water!#REF! -> #REF! | AG10: =Gas!B12 -> 8332790 | AH10: =Gas!C12 -> 1185.08 | AI10: =Gas!#REF! -> #REF! | AJ10: =Gas!J12 -> 312 | AK10: =Gas!#REF! -> #REF! | AL10: =Gas!#REF! -> #REF! | AM10: =Gas!#REF! -> #REF! | AN10: =Gas!#REF! -> #REF! | AO10: =Gas!#REF! -> #REF! | AP10: =Gas!#REF! -> #REF! | AQ10: =Gas!#REF! -> #REF! | AR10: =Gas!#REF! -> #REF! | AS10: =Gas!#REF! -> #REF! | AT10: =Elect!BR11 -> 124 | AU10: =Elect!BP11 -> 112 | AX10: 47.457627 | AY10: 23.512946 | AZ10: 8835.4834 | BA10: 12.479496 | BB10: 6.1829835 | BC10: =Elect!BQ11 -> 554624 | BD10: =Elect!#REF! -> #REF! | BE10: =Elect!#REF! -> #REF! | BF10: =Elect!#REF! -> #REF! | BG10: =Elect!#REF! -> #REF! | BH10: 1.1567797 | BI10: 0.57312806 | BJ10: 4597.6727 | BK10: 6.4938881 | BL10: 3.2174057 | BM10: =Water!U12 -> 2.08 | BN10: =Water!W12 -> #DIV/0! | BO10: =Water!X12 -> 1688.96 | BP10: =Water!Y12 -> 8.32 | BQ10: =Water!Z12 -> #DIV/0!
A11: 7 | B11: 31200 | C11: =Elect!J12 -> 5969.1111 | D11: 0 | E11: =Elect!M12 -> 1763 | F11: 20 | G11: =Elect!O12 -> 729 | H11: 871 | I11: =Water!C13 -> 127.6 | J11: 0 | K11: =Water!E13 -> 168.2 | L11: 0 | M11: =Water!#REF! -> #REF! | N11: =Water!#REF! -> #REF! | O11: 837 | P11: =Water!H13 -> 432.1 | Q11: 113 | R11: =Water!O13 -> 0 | S11: 1 | T11: =Water!#REF! -> #REF! | U11: 151 | V11: =Water!#REF! -> #REF! | W11: 732 | X11: =Water!Q13 -> 250.618 | Y11: 0 | Z11: =Water!#REF! -> #REF! | AA11: 0 | AB11: 0 | AC11: 1010 | AD11: =Water!#REF! -> #REF! | AE11: =Water!#REF! -> #REF! | AF11: =Water!#REF! -> #REF! | AG11: =Gas!B13 -> 8334124 | AH11: =Gas!C13 -> 1414.04 | AI11: =Gas!#REF! -> #REF! | AJ11: =Gas!J13 -> 351 | AK11: =Gas!#REF! -> #REF! | AL11: =Gas!#REF! -> #REF! | AM11: =Gas!#REF! -> #REF! | AN11: =Gas!#REF! -> #REF! | AO11: =Gas!#REF! -> #REF! | AP11: =Gas!#REF! -> #REF! | AQ11: =Gas!#REF! -> #REF! | AR11: =Gas!#REF! -> #REF! | AS11: =Gas!#REF! -> #REF! | AT11: =Elect!BR12 -> 150 | AU11: =Elect!BP12 -> 124 | AX11: 43.454039 | AY11: 21.517241 | AZ11: 8299.2754 | BA11: 11.558879 | BB11: 5.7236382 | BC11: =Elect!BQ12 -> 554774 | BD11: =Elect!#REF! -> #REF! | BE11: =Elect!#REF! -> #REF! | BF11: =Elect!#REF! -> #REF! | BG11: =Elect!#REF! -> #REF! | BH11: 1.1713092 | BI11: 0.58 | BJ11: 4974.6248 | BK11: 6.9284468 | BL11: 3.4307757 | BM11: =Water!U13 -> 1.8465812 | BN11: =Water!W13 -> #DIV/0! | BO11: =Water!X13 -> 1728.4 | BP11: =Water!Y13 -> 7.3863248 | BQ11: =Water!Z13 -> #DIV/0!
A12: 8 | B12: 33600 | C12: =Elect!J13 -> 5969.1111 | D12: 0 | E12: =Elect!M13 -> 2153 | F12: 20 | G12: =Elect!O13 -> 2148 | H12: 963 | I12: =Water!C14 -> 139.2 | J12: 0 | K12: =Water!E14 -> 179.8 | L12: 0 | M12: =Water!#REF! -> #REF! | N12: =Water!#REF! -> #REF! | O12: 1000 | P12: =Water!H14 -> 440.8 | Q12: 128 | R12: =Water!O14 -> 0 | S12: 24 | T12: =Water!#REF! -> #REF! | U12: 148 | V12: =Water!#REF! -> #REF! | W12: 719 | X12: =Water!Q14 -> 255.664 | Y12: 0 | Z12: =Water!#REF! -> #REF! | AA12: 0 | AB12: 0 | AC12: 630 | AD12: =Water!#REF! -> #REF! | AE12: =Water!#REF! -> #REF! | AF12: =Water!#REF! -> #REF! | AG12: =Gas!B14 -> 8335451 | AH12: =Gas!C14 -> 1406.62 | AI12: =Gas!#REF! -> #REF! | AJ12: =Gas!J14 -> 331.5 | AK12: =Gas!#REF! -> #REF! | AL12: =Gas!#REF! -> #REF! | AM12: =Gas!#REF! -> #REF! | AN12: =Gas!#REF! -> #REF! | AO12: =Gas!#REF! -> #REF! | AP12: =Gas!#REF! -> #REF! | AQ12: =Gas!#REF! -> #REF! | AR12: =Gas!#REF! -> #REF! | AS12: =Gas!#REF! -> #REF! | AT12: =Elect!BR13 -> 134 | AU12: =Elect!BP13 -> 116 | AX12: 48.837209 | AY12: 24.086022 | AZ12: 8835.4834 | BA12: 12.842272 | BB12: 6.3336799 | BC12: =Elect!BQ13 -> 554908 | BD12: =Elect!#REF! -> #REF! | BE12: =Elect!#REF! -> #REF! | BF12: =Elect!#REF! -> #REF! | BG12: =Elect!#REF! -> #REF! | BH12: 1.2194767 | BI12: 0.60143369 | BJ12: 5500.0731 | BK12: 7.9942923 | BL12: 3.9427047 | BM12: =Water!U14 -> 1.7774194 | BN12: =Water!W14 -> #DIV/0! | BO12: =Water!X14 -> 1763.2 | BP12: =Water!Y14 -> 7.1096774 | BQ12: =Water!Z14 -> #DIV/0!
A13: 9 | B13: 33600 | C13: =Elect!J14 -> 5969.1111 | D13: 0 | E13: =Elect!M14 -> 1532 | F13: 20 | G13: =Elect!O14 -> 1185 | H13: 790 | I13: =Water!C15 -> 121.8 | J13: 0 | K13: =Water!E15 -> 162.4 | L13: 0 | M13: =Water!#REF! -> #REF! | N13: =Water!#REF! -> #REF! | O13: 841 | P13: =Water!H15 -> 408.32 | Q13: 127 | R13: =Water!O15 -> 0 | S13: 21 | T13: =Water!#REF! -> #REF! | U13: 139 | V13: =Water!#REF! -> #REF! | W13: 701 | X13: =Water!Q15 -> 236.8256 | Y13: 0 | Z13: =Water!#REF! -> #REF! | AA13: 0 | AB13: 0 | AC13: 440 | AD13: =Water!#REF! -> #REF! | AE13: =Water!#REF! -> #REF! | AF13: =Water!#REF! -> #REF! | AG13: =Gas!B15 -> 8336725 | AH13: =Gas!C15 -> 1350.44 | AI13: =Gas!#REF! -> #REF! | AJ13: =Gas!J15 -> 351 | AK13: =Gas!#REF! -> #REF! | AL13: =Gas!#REF! -> #REF! | AM13: =Gas!#REF! -> #REF! | AN13: =Gas!#REF! -> #REF! | AO13: =Gas!#REF! -> #REF! | AP13: =Gas!#REF! -> #REF! | AQ13: =Gas!#REF! -> #REF! | AR13: =Gas!#REF! -> #REF! | AS13: =Gas!#REF! -> #REF! | AT13: =Elect!BR14 -> 102 | AU13: =Elect!BP14 -> 88 | AX13: 49.194729 | AY13: 24.1033 | AZ13: 8835.4834 | BA13: 12.936286 | BB13: 6.3382234 | BC13: =Elect!BQ14 -> 555010 | BD13: =Elect!#REF! -> #REF! | BE13: =Elect!#REF! -> #REF! | BF13: =Elect!#REF! -> #REF! | BG13: =Elect!#REF! -> #REF! | BH13: 1.1903367 | BI13: 0.58321377 | BJ13: 4512.0018 | BK13: 6.606152 | BL13: 3.2367301 | BM13: =Water!U15 -> 1.6203175 | BN13: =Water!W15 -> #DIV/0! | BO13: =Water!X15 -> 1633.28 | BP13: =Water!Y15 -> 6.4812698 | BQ13: =Water!Z15 -> #DIV/0!
A14: 10 | B14: 31200 | C14: =Elect!J15 -> 5969.1111 | D14: 0 | E14: =Elect!M15 -> 1946 | F14: 20 | G14: =Elect!O15 -> 1827 | H14: 792 | I14: =Water!C16 -> 127.6 | J14: 0 | K14: =Water!E16 -> 162.4 | L14: 0 | M14: =Water!#REF! -> #REF! | N14: =Water!#REF! -> #REF! | O14: 972 | P14: =Water!H16 -> 420.5 | Q14: 126 | R14: =Water!O16 -> 0 | S14: 18 | T14: =Water!#REF! -> #REF! | U14: 145 | V14: =Water!#REF! -> #REF! | W14: 756 | X14: =Water!Q16 -> 243.89 | Y14: 0 | Z14: =Water!#REF! -> #REF! | AA14: 0 | AB14: 0 | AC14: 580 | AD14: =Water!#REF! -> #REF! | AE14: =Water!#REF! -> #REF! | AF14: =Water!#REF! -> #REF! | AG14: =Gas!B16 -> 8338072 | AH14: =Gas!C16 -> 1427.82 | AI14: =Gas!#REF! -> #REF! | AJ14: =Gas!J16 -> 358.8 | AK14: =Gas!#REF! -> #REF! | AL14: =Gas!#REF! -> #REF! | AM14: =Gas!#REF! -> #REF! | AN14: =Gas!#REF! -> #REF! | AO14: =Gas!#REF! -> #REF! | AP14: =Gas!#REF! -> #REF! | AQ14: =Gas!#REF! -> #REF! | AR14: =Gas!#REF! -> #REF! | AS14: =Gas!#REF! -> #REF! | AT14: =Elect!BR15 -> 123.33333 | AU14: =Elect!BP15 -> 106.66667 | AX14: 49.52381 | AY14: 24.781573 | AZ14: 8299.2754 | BA14: 13.173453 | BB14: 6.5919582 | BC14: =Elect!BQ15 -> 555133.33 | BD14: =Elect!#REF! -> #REF! | BE14: =Elect!#REF! -> #REF! | BF14: =Elect!#REF! -> #REF! | BG14: =Elect!#REF! -> #REF! | BH14: 1.2730159 | BI14: 0.6370135 | BJ14: 4469.9646 | BK14: 7.0951819 | BL14: 3.5504087 | BM14: =Water!U16 -> 1.7093496 | BN14: =Water!W16 -> #DIV/0! | BO14: =Water!X16 -> 1682 | BP14: =Water!Y16 -> 6.8373984 | BQ14: =Water!Z16 -> #DIV/0!
A15: 11 | B15: 33600 | C15: =Elect!J16 -> 5969.1111 | D15: 0 | E15: =Elect!M16 -> 1825 | F15: 20 | G15: =Elect!O16 -> 1365 | H15: 817 | I15: =Water!C17 -> 123.73333 | J15: 0 | K15: =Water!E17 -> 162.4 | L15: 0 | M15: =Water!#REF! -> #REF! | N15: =Water!#REF! -> #REF! | O15: 875 | P15: =Water!H17 -> 412.38 | Q15: 122 | R15: =Water!O17 -> 0 | S15: 20 | T15: =Water!#REF! -> #REF! | U15: 156 | V15: =Water!#REF! -> #REF! | W15: 712 | X15: =Water!Q17 -> 239.1804 | Y15: 0 | Z15: =Water!#REF! -> #REF! | AA15: 0 | AB15: 0 | AC15: 850 | AD15: =Water!#REF! -> #REF! | AE15: =Water!#REF! -> #REF! | AF15: =Water!#REF! -> #REF! | AG15: =Gas!#REF! -> #REF! | AH15: =Gas!C17 -> 1376.2333 | AI15: =Gas!#REF! -> #REF! | AJ15: =Gas!J17 -> 353.6 | AK15: =Gas!#REF! -> #REF! | AL15: =Gas!#REF! -> #REF! | AM15: =Gas!#REF! -> #REF! | AN15: =Gas!#REF! -> #REF! | AO15: =Gas!#REF! -> #REF! | AP15: =Gas!#REF! -> #REF! | AQ15: =Gas!#REF! -> #REF! | AR15: =Gas!#REF! -> #REF! | AS15: =Gas!#REF! -> #REF! | AT15: =Elect!BR16 -> 135.66667 | AU15: =Elect!BP16 -> 147.33333 | AX15: 53.333333 | AY15: 26.751592 | AZ15: 8835.4834 | BA15: 14.024577 | BB15: 7.0346206 | BC15: =Elect!BQ16 -> 555269 | BD15: =Elect!#REF! -> #REF! | BE15: =Elect!#REF! -> #REF! | BF15: =Elect!#REF! -> #REF! | BG15: =Elect!#REF! -> #REF! | BH15: 1.3460317 | BI15: 0.67515924 | BJ15: 4666.2095 | BK15: 7.4066817 | BL15: 3.7151349 | BM15: =Water!U17 -> 2.0018447 | BN15: =Water!W17 -> #DIV/0! | BO15: =Water!X17 -> 1649.52 | BP15: =Water!Y17 -> 8.0073786 | BQ15: =Water!Z17 -> #DIV/0!
A16: 12 | B16: 33600 | C16: =Elect!J17 -> 5969.1111 | D16: 0 | E16: =Elect!M17 -> 2136 | F16: 20 | G16: =Elect!O17 -> 2112 | H16: 907 | I16: =Water!C18 -> 125.66667 | J16: 0 | K16: =Water!E18 -> 156.6 | L16: 0 | M16: =Water!#REF! -> #REF! | N16: =Water!#REF! -> #REF! | O16: 965 | P16: =Water!H18 -> 411.8 | Q16: 125 | R16: =Water!O18 -> 0 | S16: 4 | T16: =Water!#REF! -> #REF! | U16: 167 | V16: =Water!#REF! -> #REF! | W16: 705 | X16: =Water!Q18 -> 238.844 | Y16: 0 | Z16: =Water!#REF! -> #REF! | AA16: 0 | AB16: 0 | AC16: 880 | AD16: =Water!#REF! -> #REF! | AE16: =Water!#REF! -> #REF! | AF16: =Water!#REF! -> #REF! | AG16: =Gas!B18 -> 8340620 | AH16: =Gas!C18 -> 1324.6467 | AI16: =Gas!#REF! -> #REF! | AJ16: =Gas!J18 -> 321.1 | AK16: =Gas!#REF! -> #REF! | AL16: =Gas!#REF! -> #REF! | AM16: =Gas!#REF! -> #REF! | AN16: =Gas!#REF! -> #REF! | AO16: =Gas!#REF! -> #REF! | AP16: =Gas!#REF! -> #REF! | AQ16: =Gas!#REF! -> #REF! | AR16: =Gas!#REF! -> #REF! | AS16: =Gas!#REF! -> #REF! | AT16: =Elect!BR17 -> 140 | AU16: =Elect!BP17 -> 84 | AX16: 50.45045 | AY16: 25.339367 | AZ16: 8835.4834 | BA16: 13.266492 | BB16: 6.6632605 | BC16: =Elect!BQ17 -> 555409 | BD16: =Elect!#REF! -> #REF! | BE16: =Elect!#REF! -> #REF! | BF16: =Elect!#REF! -> #REF! | BG16: =Elect!#REF! -> #REF! | BH16: 1.2162162 | BI16: 0.61085973 | BJ16: 5180.235 | BK16: 7.7781306 | BL16: 3.9066629 | BM16: =Water!U18 -> 2.3666667 | BN16: =Water!W18 -> #DIV/0! | BO16: =Water!X18 -> 1647.2 | BP16: =Water!Y18 -> 9.4666667 | BQ16: =Water!Z18 -> #DIV/0!
A17: 13 | B17: 31200 | C17: =Elect!J18 -> 5969.1111 | D17: 0 | E17: =Elect!M18 -> 1830 | F17: 20 | G17: =Elect!O18 -> 1853 | H17: 812 | I17: =Water!C19 -> 121.8 | J17: 0 | K17: =Water!E19 -> 162.4 | L17: 0 | M17: =Water!#REF! -> #REF! | N17: =Water!#REF! -> #REF! | O17: 822 | P17: =Water!H19 -> 412.96 | Q17: 123 | R17: =Water!O19 -> 0 | S17: 7 | T17: =Water!#REF! -> #REF! | U17: 163 | V17: =Water!#REF! -> #REF! | W17: 692 | X17: =Water!Q19 -> 239.5168 | Y17: 0 | Z17: =Water!#REF! -> #REF! | AA17: 0 | AB17: 0 | AC17: 460 | AD17: =Water!#REF! -> #REF! | AE17: =Water!#REF! -> #REF! | AF17: =Water!#REF! -> #REF! | AG17: =Gas!B19 -> 8341899 | AH17: =Gas!C19 -> 1355.74 | AI17: =Gas!#REF! -> #REF! | AJ17: =Gas!J19 -> 390 | AK17: =Gas!#REF! -> #REF! | AL17: =Gas!#REF! -> #REF! | AM17: =Gas!#REF! -> #REF! | AN17: =Gas!#REF! -> #REF! | AO17: =Gas!#REF! -> #REF! | AP17: =Gas!#REF! -> #REF! | AQ17: =Gas!#REF! -> #REF! | AR17: =Gas!#REF! -> #REF! | AS17: =Gas!#REF! -> #REF! | AT17: =Elect!BR18 -> 134 | AU17: =Elect!BP18 -> 101 | AX17: 46.567164 | AY17: 23.214286 | AZ17: 8299.2754 | BA17: 12.386978 | BB17: 6.1750561 | BC17: =Elect!BQ18 -> 555543 | BD17: =Elect!#REF! -> #REF! | BE17: =Elect!#REF! -> #REF! | BF17: =Elect!#REF! -> #REF! | BG17: =Elect!#REF! -> #REF! | BH17: 1.0850746 | BI17: 0.54092262 | BJ17: 4637.6525 | BK17: 6.9218694 | BL17: 3.4506343 | BM17: =Water!U19 -> 2.5491358 | BN17: =Water!W19 -> #DIV/0! | BO17: =Water!X19 -> 1651.84 | BP17: =Water!Y19 -> 10.196543 | BQ17: =Water!Z19 -> #DIV/0!
A18: 14 | B18: 33600 | C18: =Elect!J19 -> 5969.1111 | D18: 0 | E18: =Elect!M19 -> 2019 | F18: 30 | G18: =Elect!O19 -> 1851 | H18: 810 | I18: =Water!C20 -> 121.8 | J18: 0 | K18: =Water!E20 -> 162.4 | L18: 0 | M18: =Water!#REF! -> #REF! | N18: =Water!#REF! -> #REF! | O18: 943 | P18: =Water!H20 -> 416.44 | Q18: 118 | R18: =Water!O20 -> 0 | S18: 18 | T18: =Water!#REF! -> #REF! | U18: 152 | V18: =Water!#REF! -> #REF! | W18: 708 | X18: =Water!Q20 -> 241.5352 | Y18: 0 | Z18: =Water!#REF! -> #REF! | AA18: 0 | AB18: 0 | AC18: 490 | AD18: =Water!#REF! -> #REF! | AE18: =Water!#REF! -> #REF! | AF18: =Water!#REF! -> #REF! | AG18: =Gas!B20 -> 8343169 | AH18: =Gas!C20 -> 1346.2 | AI18: =Gas!#REF! -> #REF! | AJ18: =Gas!J20 -> 327.6 | AK18: =Gas!#REF! -> #REF! | AL18: =Gas!#REF! -> #REF! | AM18: =Gas!#REF! -> #REF! | AN18: =Gas!#REF! -> #REF! | AO18: =Gas!#REF! -> #REF! | AP18: =Gas!#REF! -> #REF! | AQ18: =Gas!#REF! -> #REF! | AR18: =Gas!#REF! -> #REF! | AS18: =Gas!#REF! -> #REF! | AT18: =Elect!BR19 -> 146 | AU18: =Elect!BP19 -> 113 | AX18: 47.795164 | AY18: 24.207493 | AZ18: 8835.4834 | BA18: 12.568255 | BB18: 6.3656221 | BC18: =Elect!BQ6 -> 553915 | BD18: =Elect!#REF! -> #REF! | BE18: =Elect!#REF! -> #REF! | BF18: =Elect!#REF! -> #REF! | BG18: =Elect!#REF! -> #REF! | BH18: 1.1024182 | BI18: 0.55835735 | BJ18: 4626.2297 | BK18: 6.5806966 | BL18: 3.3330185 | BM18: =Water!U20 -> 2.0117874 | BN18: =Water!W20 -> #DIV/0! | BO18: =Water!X20 -> 1665.76 | BP18: =Water!Y20 -> 8.0471498 | BQ18: =Water!Z20 -> #DIV/0!
A19: 15 | B19: 31200 | C19: =Elect!J20 -> 5969.1111 | D19: 0 | E19: =Elect!M20 -> 1960 | F19: 20 | G19: =Elect!O20 -> 1654 | H19: 841 | I19: =Water!C21 -> 133.4 | J19: 0 | K19: =Water!E21 -> 162.4 | L19: 0 | M19: =Water!#REF! -> #REF! | N19: =Water!#REF! -> #REF! | O19: 947 | P19: =Water!H21 -> 429.2 | Q19: 131 | R19: =Water!O21 -> 0 | S19: 23 | T19: =Water!#REF! -> #REF! | U19: 166 | V19: =Water!#REF! -> #REF! | W19: 787 | X19: =Water!Q21 -> 248.936 | Y19: 0 | Z19: =Water!#REF! -> #REF! | AA19: 0 | AB19: 0 | AC19: 730 | AD19: =Water!#REF! -> #REF! | AE19: =Water!#REF! -> #REF! | AF19: =Water!#REF! -> #REF! | AG19: =Gas!B21 -> 8344440 | AH19: =Gas!C21 -> 1347.26 | AI19: =Gas!#REF! -> #REF! | AJ19: =Gas!J21 -> 351 | AK19: =Gas!#REF! -> #REF! | AL19: =Gas!#REF! -> #REF! | AM19: =Gas!#REF! -> #REF! | AN19: =Gas!#REF! -> #REF! | AO19: =Gas!#REF! -> #REF! | AP19: =Gas!#REF! -> #REF! | AQ19: =Gas!#REF! -> #REF! | AR19: =Gas!#REF! -> #REF! | AS19: =Gas!#REF! -> #REF! | AT19: =Elect!BR20 -> 128 | AU19: =Elect!BP20 -> 120 | AX19: 41.6 | AY19: 20.995962 | AZ19: 8299.2754 | BA19: 11.065701 | BB19: 5.5849767 | BC19: =Elect!BQ20 -> 555817 | BD19: =Elect!#REF! -> #REF! | BE19: =Elect!#REF! -> #REF! | BF19: =Elect!#REF! -> #REF! | BG19: =Elect!#REF! -> #REF! | BH19: 1.1506667 | BI19: 0.58114478 | BJ19: 4803.283 | BK19: 6.4043773 | BL19: 3.234534 | BM19: =Water!U21 -> 1.7306452 | BN19: =Water!W21 -> #DIV/0! | BO19: =Water!X21 -> 1716.8 | BP19: =Water!Y21 -> 6.9225806 | BQ19: =Water!Z21 -> #DIV/0!
A20: 16 | B20: 36000 | C20: =Elect!J21 -> 5969.1111 | D20: 0 | E20: =Elect!M21 -> 1830 | F20: 20 | G20: =Elect!O21 -> 1786 | H20: 932 | I20: =Water!C22 -> 139.2 | J20: 0 | K20: =Water!E22 -> 185.6 | L20: 0 | M20: =Water!#REF! -> #REF! | N20: =Water!#REF! -> #REF! | O20: 998 | P20: =Water!H22 -> 454.14 | Q20: 136 | R20: =Water!O22 -> 0 | S20: 22 | T20: =Water!#REF! -> #REF! | U20: 162 | V20: =Water!#REF! -> #REF! | W20: 703 | X20: =Water!Q22 -> 263.4012 | Y20: 0 | Z20: =Water!#REF! -> #REF! | AA20: 0 | AB20: 0 | AC20: 600 | AD20: =Water!#REF! -> #REF! | AE20: =Water!#REF! -> #REF! | AF20: =Water!#REF! -> #REF! | AG20: =Gas!B22 -> 8345828 | AH20: =Gas!C22 -> 1471.28 | AI20: =Gas!#REF! -> #REF! | AJ20: =Gas!J22 -> 354.9 | AK20: =Gas!#REF! -> #REF! | AL20: =Gas!#REF! -> #REF! | AM20: =Gas!#REF! -> #REF! | AN20: =Gas!#REF! -> #REF! | AO20: =Gas!#REF! -> #REF! | AP20: =Gas!#REF! -> #REF! | AQ20: =Gas!#REF! -> #REF! | AR20: =Gas!#REF! -> #REF! | AS20: =Gas!#REF! -> #REF! | AT20: =Elect!BR21 -> 140 | AU20: =Elect!BP21 -> 105 | AX20: 48 | AY20: 24.22611 | AZ20: 9371.6914 | BA20: 12.495589 | BB20: 6.3066564 | BC20: =Elect!BQ21 -> 555957 | BD20: =Elect!#REF! -> #REF! | BE20: =Elect!#REF! -> #REF! | BF20: =Elect!#REF! -> #REF! | BG20: =Elect!#REF! -> #REF! | BH20: 1.1626667 | BI20: 0.58720539 | BJ20: 5323.0199 | BK20: 7.0973598 | BL20: 3.5845252 | BM20: =Water!U22 -> 1.8312097 | BN20: =Water!W22 -> #DIV/0! | BO20: =Water!X22 -> 1816.56 | BP20: =Water!Y22 -> 7.3248387 | BQ20: =Water!Z22 -> #DIV/0!
A21: 17 | B21: 33600 | C21: =Elect!J22 -> 5969.1111 | D21: 0 | E21: =Elect!M22 -> 1898 | F21: 20 | G21: =Elect!O22 -> 1927 | H21: 972 | I21: =Water!C23 -> 127.6 | J21: 0 | K21: =Water!E23 -> 168.2 | L21: 0 | M21: =Water!#REF! -> #REF! | N21: =Water!#REF! -> #REF! | O21: 998 | P21: =Water!H23 -> 423.4 | Q21: 136 | R21: =Water!O23 -> 0 | S21: 38 | T21: =Water!#REF! -> #REF! | U21: 137 | V21: =Water!#REF! -> #REF! | W21: 740 | X21: =Water!Q23 -> 245.572 | Y21: 0 | Z21: =Water!#REF! -> #REF! | AA21: 0 | AB21: 0 | AC21: 690 | AD21: =Water!#REF! -> #REF! | AE21: =Water!#REF! -> #REF! | AF21: =Water!#REF! -> #REF! | AG21: =Gas!B23 -> 8347209 | AH21: =Gas!C23 -> 1463.86 | AI21: =Gas!#REF! -> #REF! | AJ21: =Gas!J23 -> 288.6 | AK21: =Gas!#REF! -> #REF! | AL21: =Gas!#REF! -> #REF! | AM21: =Gas!#REF! -> #REF! | AN21: =Gas!#REF! -> #REF! | AO21: =Gas!#REF! -> #REF! | AP21: =Gas!#REF! -> #REF! | AQ21: =Gas!#REF! -> #REF! | AR21: =Gas!#REF! -> #REF! | AS21: =Gas!#REF! -> #REF! | AT21: =Elect!BR22 -> 119 | AU21: =Elect!BP22 -> 109 | AX21: 44.385733 | AY21: 22.207535 | AZ21: 8835.4834 | BA21: 11.671709 | BB21: 5.8397115 | BC21: =Elect!#REF! -> #REF! | BD21: =Elect!#REF! -> #REF! | BE21: =Elect!#REF! -> #REF! | BF21: =Elect!#REF! -> #REF! | BG21: =Elect!#REF! -> #REF! | BH21: 1.1770145 | BI21: 0.58889623 | BJ21: 5551.4757 | BK21: 7.3335213 | BL21: 3.6691842 | BM21: =Water!U23 -> 1.7352459 | BN21: =Water!W23 -> #DIV/0! | BO21: =Water!X23 -> 1693.6 | BP21: =Water!Y23 -> 6.9409836 | BQ21: =Water!Z23 -> #DIV/0!
A22: 18 | B22: 33600 | C22: =Elect!J23 -> 5960.963 | D22: 0 | E22: =Elect!M23 -> 2133 | F22: 20 | G22: =Elect!O23 -> 2107 | H22: 864 | I22: =Water!C24 -> 139.2 | J22: 0 | K22: =Water!E24 -> 174 | L22: 0 | M22: =Water!#REF! -> #REF! | N22: =Water!#REF! -> #REF! | O22: 1002 | P22: =Water!H24 -> 445.44 | Q22: 118 | R22: =Water!O24 -> 0 | S22: 21 | T22: =Water!#REF! -> #REF! | U22: 133 | V22: =Water!#REF! -> #REF! | W22: 769 | X22: =Water!Q24 -> 258.3552 | Y22: 0 | Z22: =Water!#REF! -> #REF! | AA22: 0 | AB22: 0 | AC22: 930 | AD22: =Water!#REF! -> #REF! | AE22: =Water!#REF! -> #REF! | AF22: =Water!#REF! -> #REF! | AG22: =Gas!B24 -> 8348566 | AH22: =Gas!C24 -> 1438.42 | AI22: =Gas!#REF! -> #REF! | AJ22: =Gas!J24 -> 374.4 | AK22: =Gas!#REF! -> #REF! | AL22: =Gas!#REF! -> #REF! | AM22: =Gas!#REF! -> #REF! | AN22: =Gas!#REF! -> #REF! | AO22: =Gas!#REF! -> #REF! | AP22: =Gas!#REF! -> #REF! | AQ22: =Gas!#REF! -> #REF! | AR22: =Gas!#REF! -> #REF! | AS22: =Gas!#REF! -> #REF! | AT22: =Elect!BR23 -> 129 | AU22: =Elect!BP23 -> 118 | AX22: 44.680851 | AY22: 22.459893 | AZ22: 8835.4834 | BA22: 11.749313 | BB22: 5.9060718 | BC22: =Elect!BQ23 -> 556205 | BD22: =Elect!#REF! -> #REF! | BE22: =Elect!#REF! -> #REF! | BF22: =Elect!#REF! -> #REF! | BG22: =Elect!#REF! -> #REF! | BH22: 1.1236702 | BI22: 0.56483957 | BJ22: 4934.645 | BK22: 6.562028 | BL22: 3.2985595 | BM22: =Water!U24 -> 1.9536842 | BN22: =Water!W24 -> #DIV/0! | BO22: =Water!X24 -> 1781.76 | BP22: =Water!Y24 -> 7.8147368 | BQ22: =Water!Z24 -> #DIV/0!
A23: 19 | B23: 33600 | C23: =Elect!J24 -> 5993.5556 | D23: 0 | E23: =Elect!M24 -> 1799 | F23: 30 | G23: =Elect!O24 -> 1666 | H23: 894 | I23: =Water!C25 -> 145 | J23: 0 | K23: =Water!E25 -> 174 | L23: 0 | M23: =Water!#REF! -> #REF! | N23: =Water!#REF! -> #REF! | O23: 944 | P23: =Water!H25 -> 455.88 | Q23: 110 | R23: =Water!O25 -> 0 | S23: 14 | T23: =Water!#REF! -> #REF! | U23: 155 | V23: =Water!#REF! -> #REF! | W23: 721 | X23: =Water!Q25 -> 264.4104 | Y23: 0 | Z23: =Water!#REF! -> #REF! | AA23: 0 | AB23: 0 | AC23: 660 | AD23: =Water!#REF! -> #REF! | AE23: =Water!#REF! -> #REF! | AF23: =Water!#REF! -> #REF! | AG23: =Gas!B25 -> 8349939 | AH23: =Gas!C25 -> 1455.38 | AI23: =Gas!#REF! -> #REF! | AJ23: =Gas!J25 -> 343.2 | AK23: =Gas!#REF! -> #REF! | AL23: =Gas!#REF! -> #REF! | AM23: =Gas!#REF! -> #REF! | AN23: =Gas!#REF! -> #REF! | AO23: =Gas!#REF! -> #REF! | AP23: =Gas!#REF! -> #REF! | AQ23: =Gas!#REF! -> #REF! | AR23: =Gas!#REF! -> #REF! | AS23: =Gas!#REF! -> #REF! | AT23: =Elect!BR24 -> 134 | AU23: =Elect!BP24 -> 101 | AX23: 44.8 | AY23: 22.44489 | AZ23: 8835.4834 | BA23: 11.780645 | BB23: 5.9021265 | BC23: =Elect!BQ24 -> 556339 | BD23: =Elect!#REF! -> #REF! | BE23: =Elect!#REF! -> #REF! | BF23: =Elect!#REF! -> #REF! | BG23: =Elect!#REF! -> #REF! | BH23: 1.1346667 | BI23: 0.56847027 | BJ23: 5105.9869 | BK23: 6.8079825 | BL23: 3.4108129 | BM23: =Water!U25 -> 2.2457143 | BN23: =Water!W25 -> #DIV/0! | BO23: =Water!X25 -> 1823.52 | BP23: =Water!Y25 -> 8.9828571 | BQ23: =Water!Z25 -> #DIV/0!
A24: 20 | B24: 33600 | C24: =Elect!J25 -> 5944.6667 | D24: 0 | E24: =Elect!M25 -> 1879 | F24: 20 | G24: =Elect!O25 -> 1811 | H24: 944 | I24: =Water!C26 -> 110.2 | J24: 0 | K24: =Water!E26 -> 156.6 | L24: 0 | M24: =Water!#REF! -> #REF! | N24: =Water!#REF! -> #REF! | O24: 1000 | P24: =Water!H26 -> 387.44 | Q24: 138 | R24: =Water!O26 -> 0 | S24: 15 | T24: =Water!#REF! -> #REF! | U24: 165 | V24: =Water!#REF! -> #REF! | W24: 778 | X24: =Water!Q26 -> 224.7152 | Y24: 0 | Z24: =Water!#REF! -> #REF! | AA24: 0 | AB24: 0 | AC24: 560 | AD24: =Water!#REF! -> #REF! | AE24: =Water!#REF! -> #REF! | AF24: =Water!#REF! -> #REF! | AG24: =Gas!B26 -> 8351103 | AH24: =Gas!C26 -> 1233.84 | AI24: =Gas!#REF! -> #REF! | AJ24: =Gas!J26 -> 335.4 | AK24: =Gas!#REF! -> #REF! | AL24: =Gas!#REF! -> #REF! | AM24: =Gas!#REF! -> #REF! | AN24: =Gas!#REF! -> #REF! | AO24: =Gas!#REF! -> #REF! | AP24: =Gas!#REF! -> #REF! | AQ24: =Gas!#REF! -> #REF! | AR24: =Gas!#REF! -> #REF! | AS24: =Gas!#REF! -> #REF! | AT24: =Elect!BR25 -> 149 | AU24: =Elect!BP25 -> 116 | AX24: 42.857143 | AY24: 21.649485 | AZ24: 8835.4834 | BA24: 11.269749 | BB24: 5.6929661 | BC24: =Elect!BQ25 -> 556488 | BD24: =Elect!#REF! -> #REF! | BE24: =Elect!#REF! -> #REF! | BF24: =Elect!#REF! -> #REF! | BG24: =Elect!#REF! -> #REF! | BH24: 1.1683673 | BI24: 0.59020619 | BJ24: 5391.5566 | BK24: 6.8769855 | BL24: 3.4739411 | BM24: =Water!U26 -> 1.9085714 | BN24: =Water!W26 -> #DIV/0! | BO24: =Water!X26 -> 1549.76 | BP24: =Water!Y26 -> 7.6342857 | BQ24: =Water!Z26 -> #DIV/0!
A25: 21 | B25: 36000 | C25: =Elect!J26 -> 6018 | D25: 0 | E25: =Elect!M26 -> 1809 | F25: 20 | G25: =Elect!O26 -> 1685 | H25: 916 | I25: =Water!C27 -> 116 | J25: 0 | K25: =Water!E27 -> 145 | L25: 0 | M25: =Water!#REF! -> #REF! | N25: =Water!#REF! -> #REF! | O25: 998 | P25: =Water!H27 -> 383.96 | Q25: 186 | R25: =Water!O27 -> 0 | S25: 43 | T25: =Water!#REF! -> #REF! | U25: 176 | V25: =Water!#REF! -> #REF! | W25: 773 | X25: =Water!Q27 -> 222.6968 | Y25: 0 | Z25: =Water!#REF! -> #REF! | AA25: 0 | AB25: 0 | AC25: 950 | AD25: =Water!#REF! -> #REF! | AE25: =Water!#REF! -> #REF! | AF25: =Water!#REF! -> #REF! | AG25: =Gas!B27 -> 8352441 | AH25: =Gas!C27 -> 1418.28 | AI25: =Gas!#REF! -> #REF! | AJ25: =Gas!J27 -> 354.9 | AK25: =Gas!#REF! -> #REF! | AL25: =Gas!#REF! -> #REF! | AM25: =Gas!#REF! -> #REF! | AN25: =Gas!#REF! -> #REF! | AO25: =Gas!#REF! -> #REF! | AP25: =Gas!#REF! -> #REF! | AQ25: =Gas!#REF! -> #REF! | AR25: =Gas!#REF! -> #REF! | AS25: =Gas!#REF! -> #REF! | AT25: =Elect!BR26 -> 136 | AU25: =Elect!BP26 -> 108 | AX25: 43.956044 | AY25: 22.222222 | AZ25: 9371.6914 | BA25: 11.442847 | BB25: 5.7849947 | BC25: =Elect!BQ26 -> 556624 | BD25: =Elect!#REF! -> #REF! | BE25: =Elect!#REF! -> #REF! | BF25: =Elect!#REF! -> #REF! | BG25: =Elect!#REF! -> #REF! | BH25: 1.0586081 | BI25: 0.53518519 | BJ25: 5231.6376 | BK25: 6.3878358 | BL25: 3.2294059 | BM25: =Water!U27 -> 1.9007921 | BN25: =Water!W27 -> #DIV/0! | BO25: =Water!X27 -> 1535.84 | BP25: =Water!Y27 -> 7.6031683 | BQ25: =Water!Z27 -> #DIV/0!
A26: 22 | B26: 33600 | C26: =Elect!J27 -> 5908 | D26: 0 | E26: =Elect!M27 -> 1743 | F26: 20 | G26: =Elect!O27 -> 1525 | H26: 931 | I26: =Water!C28 -> 127.6 | J26: 0 | K26: =Water!E28 -> 162.4 | L26: 0 | M26: =Water!#REF! -> #REF! | N26: =Water!#REF! -> #REF! | O26: 969 | P26: =Water!H28 -> 414.12 | Q26: 151 | R26: =Water!O28 -> 0 | S26: 29 | T26: =Water!#REF! -> #REF! | U26: 157 | V26: =Water!#REF! -> #REF! | W26: 697 | X26: =Water!Q28 -> 240.1896 | Y26: 0 | Z26: =Water!#REF! -> #REF! | AA26: 0 | AB26: 0 | AC26: 700 | AD26: =Water!#REF! -> #REF! | AE26: =Water!#REF! -> #REF! | AF26: =Water!#REF! -> #REF! | AG26: =Gas!B28 -> 8353743 | AH26: =Gas!C28 -> 1380.12 | AI26: =Gas!#REF! -> #REF! | AJ26: =Gas!J28 -> 370.5 | AK26: =Gas!#REF! -> #REF! | AL26: =Gas!#REF! -> #REF! | AM26: =Gas!#REF! -> #REF! | AN26: =Gas!#REF! -> #REF! | AO26: =Gas!#REF! -> #REF! | AP26: =Gas!#REF! -> #REF! | AQ26: =Gas!#REF! -> #REF! | AR26: =Gas!#REF! -> #REF! | AS26: =Gas!#REF! -> #REF! | AT26: =Elect!BR27 -> 135 | AU26: =Elect!BP27 -> 115 | AX26: 39.952438 | AY26: 20.253165 | AZ26: 8835.4834 | BA26: 10.505926 | BB26: 5.3257887 | BC26: =Elect!BQ27 -> 556759 | BD26: =Elect!#REF! -> #REF! | BE26: =Elect!#REF! -> #REF! | BF26: =Elect!#REF! -> #REF! | BG26: =Elect!#REF! -> #REF! | BH26: 1.0903686 | BI26: 0.55274262 | BJ26: 5317.3085 | BK26: 6.3226022 | BL26: 3.2051287 | BM26: =Water!U28 -> 1.7473418 | BN26: =Water!W28 -> #DIV/0! | BO26: =Water!X28 -> 1656.48 | BP26: =Water!Y28 -> 6.9893671 | BQ26: =Water!Z28 -> #DIV/0!
A27: 23 | B27: 36000 | C27: =Elect!J28 -> 6073 | D27: 0 | E27: =Elect!M28 -> 1870 | F27: 30 | G27: =Elect!O28 -> 1491 | H27: 1009 | I27: =Water!C29 -> 116 | J27: 0 | K27: =Water!E29 -> 145 | L27: 0 | M27: =Water!#REF! -> #REF! | N27: =Water!#REF! -> #REF! | O27: 902 | P27: =Water!H29 -> 385.7 | Q27: 131 | R27: =Water!O29 -> 0 | S27: 6 | T27: =Water!#REF! -> #REF! | U27: 167 | V27: =Water!#REF! -> #REF! | W27: 748 | X27: =Water!Q29 -> 223.706 | Y27: 0 | Z27: =Water!#REF! -> #REF! | AA27: 0 | AB27: 0 | AC27: 690 | AD27: =Water!#REF! -> #REF! | AE27: =Water!#REF! -> #REF! | AF27: =Water!#REF! -> #REF! | AG27: =Gas!B29 -> 8354914 | AH27: =Gas!C29 -> 1241.26 | AI27: =Gas!#REF! -> #REF! | AJ27: =Gas!J29 -> 339.3 | AK27: =Gas!#REF! -> #REF! | AL27: =Gas!#REF! -> #REF! | AM27: =Gas!#REF! -> #REF! | AN27: =Gas!#REF! -> #REF! | AO27: =Gas!#REF! -> #REF! | AP27: =Gas!#REF! -> #REF! | AQ27: =Gas!#REF! -> #REF! | AR27: =Gas!#REF! -> #REF! | AS27: =Gas!#REF! -> #REF! | AT27: =Elect!BR28 -> 138 | AU27: =Elect!BP28 -> 112 | AX27: 42.755344 | AY27: 21.543986 | AZ27: 9371.6914 | BA27: 11.130275 | BB27: 5.6084329 | BC27: =Elect!BQ28 -> 556897 | BD27: =Elect!#REF! -> #REF! | BE27: =Elect!#REF! -> #REF! | BF27: =Elect!#REF! -> #REF! | BG27: =Elect!#REF! -> #REF! | BH27: 1.0712589 | BI27: 0.53979653 | BJ27: 5762.7973 | BK27: 6.8441773 | BL27: 3.4487117 | BM27: =Water!U29 -> 2.1192308 | BN27: =Water!W29 -> #DIV/0! | BO27: =Water!X29 -> 1542.8 | BP27: =Water!Y29 -> 8.4769231 | BQ27: =Water!Z29 -> #DIV/0!
A28: 24 | B28: 33600 | C28: =Elect!J29 -> 6047 | D28: 0 | E28: =Elect!M29 -> 1977 | F28: 20 | G28: =Elect!O29 -> 1454 | H28: 891 | I28: =Water!C30 -> 121.8 | J28: 0 | K28: =Water!E30 -> 156.6 | L28: 0 | M28: =Water!#REF! -> #REF! | N28: =Water!#REF! -> #REF! | O28: 818 | P28: =Water!H30 -> 404.26 | Q28: 221 | R28: =Water!O30 -> 0 | S28: 93 | T28: =Water!#REF! -> #REF! | U28: 191 | V28: =Water!#REF! -> #REF! | W28: 827 | X28: =Water!Q30 -> 234.4708 | Y28: 0 | Z28: =Water!#REF! -> #REF! | AA28: 0 | AB28: 0 | AC28: 470 | AD28: =Water!#REF! -> #REF! | AE28: =Water!#REF! -> #REF! | AF28: =Water!#REF! -> #REF! | AG28: =Gas!B30 -> 8356215 | AH28: =Gas!C30 -> 1379.06 | AI28: =Gas!#REF! -> #REF! | AJ28: =Gas!J30 -> 343.2 | AK28: =Gas!#REF! -> #REF! | AL28: =Gas!#REF! -> #REF! | AM28: =Gas!#REF! -> #REF! | AN28: =Gas!#REF! -> #REF! | AO28: =Gas!#REF! -> #REF! | AP28: =Gas!#REF! -> #REF! | AQ28: =Gas!#REF! -> #REF! | AR28: =Gas!#REF! -> #REF! | AS28: =Gas!#REF! -> #REF! | AT28: =Elect!BR29 -> 121 | AU28: =Elect!BP29 -> 108 | AX28: 39.904988 | AY28: 20.289855 | AZ28: 8835.4834 | BA28: 10.493448 | BB28: 5.3354369 | BC28: =Elect!BQ29 -> 557018 | BD28: =Elect!#REF! -> #REF! | BE28: =Elect!#REF! -> #REF! | BF28: =Elect!#REF! -> #REF! | BG28: =Elect!#REF! -> #REF! | BH28: 1.1104513 | BI28: 0.56461353 | BJ28: 5088.8527 | BK28: 6.043768 | BL28: 3.0729787 | BM28: =Water!U30 -> 1.9068868 | BN28: =Water!W30 -> #DIV/0! | BO28: =Water!X30 -> 1617.04 | BP28: =Water!Y30 -> 7.6275472 | BQ28: =Water!Z30 -> #DIV/0!
A29: 25 | B29: 33600 | C29: =Elect!J30 -> 6075 | D29: 0 | E29: =Elect!M30 -> 1969 | F29: 20 | G29: =Elect!O30 -> 1632 | H29: 1008 | I29: =Water!C31 -> 133.4 | J29: 0 | K29: =Water!E31 -> 174 | L29: 0 | M29: =Water!#REF! -> #REF! | N29: =Water!#REF! -> #REF! | O29: 1290 | P29: =Water!H31 -> 459.36 | Q29: 34 | R29: =Water!O31 -> 0 | S29: 34 | T29: =Water!#REF! -> #REF! | U29: 55 | V29: =Water!#REF! -> #REF! | W29: 681 | X29: =Water!Q31 -> 266.4288 | Y29: 0 | Z29: =Water!#REF! -> #REF! | AA29: 0 | AB29: 0 | AC29: 1170 | AD29: =Water!#REF! -> #REF! | AE29: =Water!#REF! -> #REF! | AF29: =Water!#REF! -> #REF! | AG29: =Gas!B31 -> 8357899 | AH29: =Gas!C31 -> 1785.04 | AI29: =Gas!#REF! -> #REF! | AJ29: =Gas!J31 -> 429 | AK29: =Gas!#REF! -> #REF! | AL29: =Gas!#REF! -> #REF! | AM29: =Gas!#REF! -> #REF! | AN29: =Gas!#REF! -> #REF! | AO29: =Gas!#REF! -> #REF! | AP29: =Gas!#REF! -> #REF! | AQ29: =Gas!#REF! -> #REF! | AR29: =Gas!#REF! -> #REF! | AS29: =Gas!#REF! -> #REF! | AT29: =Elect!BR30 -> 146 | AU29: =Elect!BP30 -> 109 | AX29: 39.763314 | AY29: 20.20445 | AZ29: 8835.4834 | BA29: 10.456193 | BB29: 5.3129786 | BC29: =Elect!BQ30 -> 557164 | BD29: =Elect!#REF! -> #REF! | BE29: =Elect!#REF! -> #REF! | BF29: =Elect!#REF! -> #REF! | BG29: =Elect!#REF! -> #REF! | BH29: 1.0059172 | BI29: 0.51112447 | BJ29: 5757.0859 | BK29: 6.8131194 | BL29: 3.4618676 | BM29: =Water!U31 -> 2.4434043 | BN29: =Water!W31 -> #DIV/0! | BO29: =Water!X31 -> 1837.44 | BP29: =Water!Y31 -> 9.773617 | BQ29: =Water!Z31 -> #DIV/0!
A30: 26 | B30: 31200 | C30: =Elect!J31 -> 6108 | D30: 0 | E30: =Elect!M31 -> 1933 | F30: 20 | G30: =Elect!O31 -> 1556 | H30: 760 | I30: =Water!C32 -> 98.6 | J30: 0 | K30: =Water!E32 -> 127.6 | L30: 0 | M30: =Water!#REF! -> #REF! | N30: =Water!#REF! -> #REF! | O30: 1004 | P30: =Water!H32 -> 339.88 | Q30: 131 | R30: =Water!O32 -> 0 | S30: 33 | T30: =Water!#REF! -> #REF! | U30: 145 | V30: =Water!#REF! -> #REF! | W30: 916 | X30: =Water!Q32 -> 197.1304 | Y30: 0 | Z30: =Water!#REF! -> #REF! | AA30: 0 | AB30: 0 | AC30: 810 | AD30: =Water!#REF! -> #REF! | AE30: =Water!#REF! -> #REF! | AF30: =Water!#REF! -> #REF! | AG30: =Gas!B32 -> 8359164 | AH30: =Gas!C32 -> 1340.9 | AI30: =Gas!#REF! -> #REF! | AJ30: =Gas!J32 -> 93.6 | AK30: =Gas!#REF! -> #REF! | AL30: =Gas!#REF! -> #REF! | AM30: =Gas!#REF! -> #REF! | AN30: =Gas!#REF! -> #REF! | AO30: =Gas!#REF! -> #REF! | AP30: =Gas!#REF! -> #REF! | AQ30: =Gas!#REF! -> #REF! | AR30: =Gas!#REF! -> #REF! | AS30: =Gas!#REF! -> #REF! | AT30: =Elect!BR31 -> 128 | AU30: =Elect!BP31 -> 109 | AX30: 37.275986 | AY30: 18.989653 | AZ30: 8299.2754 | BA30: 9.9155023 | BB30: 5.0512936 | BC30: =Elect!BQ31 -> 557292 | BD30: =Elect!#REF! -> #REF! | BE30: =Elect!#REF! -> #REF! | BF30: =Elect!#REF! -> #REF! | BG30: =Elect!#REF! -> #REF! | BH30: 1.1063321 | BI30: 0.56360316 | BJ30: 4340.66 | BK30: 5.1859737 | BL30: 2.6419111 | BM30: =Water!U32 -> 1.5519635 | BN30: =Water!W32 -> #DIV/0! | BO30: =Water!X32 -> 1359.52 | BP30: =Water!Y32 -> 6.2078539 | BQ30: =Water!Z32 -> #DIV/0!
A31: 27 | B31: 36000 | C31: =Elect!J32 -> 5745 | D31: 0 | E31: =Elect!M32 -> 1836 | F31: 30 | G31: =Elect!O32 -> 1655 | H31: 1010 | I31: =Water!C33 -> 121.8 | J31: 0 | K31: =Water!E33 -> 156.6 | L31: 0 | M31: =Water!#REF! -> #REF! | N31: =Water!#REF! -> #REF! | O31: 1014 | P31: =Water!H33 -> 405.42 | Q31: 151 | R31: =Water!O33 -> 0 | S31: 30 | T31: =Water!#REF! -> #REF! | U31: 139 | V31: =Water!#REF! -> #REF! | W31: 761 | X31: =Water!Q33 -> 235.1436 | Y31: 0 | Z31: =Water!#REF! -> #REF! | AA31: 0 | AB31: 0 | AC31: 930 | AD31: =Water!#REF! -> #REF! | AE31: =Water!#REF! -> #REF! | AF31: =Water!#REF! -> #REF! | AG31: =Gas!B33 -> 8360290 | AH31: =Gas!C33 -> 1193.56 | AI31: =Gas!#REF! -> #REF! | AJ31: =Gas!J33 -> 113.1 | AK31: =Gas!#REF! -> #REF! | AL31: =Gas!#REF! -> #REF! | AM31: =Gas!#REF! -> #REF! | AN31: =Gas!#REF! -> #REF! | AO31: =Gas!#REF! -> #REF! | AP31: =Gas!#REF! -> #REF! | AQ31: =Gas!#REF! -> #REF! | AR31: =Gas!#REF! -> #REF! | AS31: =Gas!#REF! -> #REF! | AT31: =Elect!BR32 -> 143 | AU31: =Elect!BP32 -> 109 | AX31: 44.063647 | AY31: 22.346369 | AZ31: 9371.6914 | BA31: 11.470859 | BB31: 5.8173131 | BC31: =Elect!BQ32 -> 557435 | BD31: =Elect!#REF! -> #REF! | BE31: =Elect!#REF! -> #REF! | BF31: =Elect!#REF! -> #REF! | BG31: =Elect!#REF! -> #REF! | BH31: 1.1640147 | BI31: 0.59031657 | BJ31: 5768.5087 | BK31: 7.0605981 | BL31: 3.5807006 | BM31: =Water!U33 -> 1.9123585 | BN31: =Water!W33 -> #DIV/0! | BO31: =Water!X33 -> 1621.68 | BP31: =Water!Y33 -> 7.649434 | BQ31: =Water!Z33 -> #DIV/0!
A32: 28 | B32: 33600 | C32: =Elect!J33 -> 9841 | D32: 0 | E32: =Elect!M33 -> 1906 | F32: 20 | G32: =Elect!O33 -> 1574 | H32: 1008 | I32: =Water!C34 -> 121.8 | J32: 0 | K32: =Water!E34 -> 156.6 | L32: 1 | M32: =Water!#REF! -> #REF! | N32: =Water!#REF! -> #REF! | O32: 1013 | P32: =Water!H34 -> 531.86 | Q32: 142 | R32: =Water!O34 -> 0 | S32: 13 | T32: =Water!#REF! -> #REF! | U32: 155 | V32: =Water!#REF! -> #REF! | W32: 825 | X32: =Water!Q34 -> 308.4788 | Y32: 1 | Z32: =Water!#REF! -> #REF! | AA32: 0 | AB32: 0 | AC32: 650 | AD32: =Water!#REF! -> #REF! | AE32: =Water!#REF! -> #REF! | AF32: =Water!#REF! -> #REF! | AG32: =Gas!B34 -> 8361770 | AH32: =Gas!C34 -> 1568.8 | AI32: =Gas!#REF! -> #REF! | AJ32: =Gas!J34 -> 741 | AK32: =Gas!#REF! -> #REF! | AL32: =Gas!#REF! -> #REF! | AM32: =Gas!#REF! -> #REF! | AN32: =Gas!#REF! -> #REF! | AO32: =Gas!#REF! -> #REF! | AP32: =Gas!#REF! -> #REF! | AQ32: =Gas!#REF! -> #REF! | AR32: =Gas!#REF! -> #REF! | AS32: =Gas!#REF! -> #REF! | AT32: =Elect!BR33 -> 139 | AU32: =Elect!BP33 -> 110 | AX32: 45.34413 | AY32: 22.687373 | AZ32: 8835.4834 | BA32: 11.923729 | BB32: 5.9658902 | BC32: =Elect!BQ33 -> 557574 | BD32: =Elect!#REF! -> #REF! | BE32: =Elect!#REF! -> #REF! | BF32: =Elect!#REF! -> #REF! | BG32: =Elect!#REF! -> #REF! | BH32: 1.2294197 | BI32: 0.61512492 | BJ32: 5757.0859 | BK32: 7.7693467 | BL32: 3.8872963 | BM32: =Water!U34 -> 2.1887243 | BN32: =Water!W34 -> #DIV/0! | BO32: =Water!X34 -> 2127.44 | BP32: =Water!Y34 -> 8.7548971 | BQ32: =Water!Z34 -> #DIV/0!
A33: MTD | B33: 931200 | C33: =Elect!J34 -> 1726 | D33: 0 | E33: =Elect!M34 -> 1972 | F33: 600 | G33: =Elect!O34 -> 1620 | H33: 24543 | I33: =Water!C38 -> 3866.6667 | J33: 0 | K33: =Water!E39 -> 166.84667 | L33: 3 | M33: =Water!#REF! -> #REF! | N33: =Water!#REF! -> #REF! | O33: 1013 | P33: =Water!H38 -> 12800.407 | Q33: 109 | R33: =Water!O38 -> 0 | S33: 15 | T33: =Water!#REF! -> #REF! | U33: 147 | V33: =Water!#REF! -> #REF! | W33: 730 | X33: =Water!Q38 -> 6867.606 | Y33: 3 | Z33: =Water!#REF! -> #REF! | AA33: 0 | AB33: 0 | AC33: 0 | AD33: =Water!#REF! -> #REF! | AE33: =Water!#REF! -> #REF! | AF33: =Water!#REF! -> #REF! | AG33: =Gas!B38 -> 0 | AH33: =Gas!C38 -> 42357.247 | AI33: =Gas!#REF! -> #REF! | AJ33: =Gas!J38 -> 10518.3 | AK33: =Gas!#REF! -> #REF! | AL33: =Gas!#REF! -> #REF! | AM33: =Gas!#REF! -> #REF! | AN33: =Gas!#REF! -> #REF! | AO33: =Gas!#REF! -> #REF! | AP33: =Gas!#REF! -> #REF! | AQ33: =Gas!#REF! -> #REF! | AR33: =Gas!#REF! -> #REF! | AS33: =Gas!#REF! -> #REF! | AT33: =Elect!BR34 -> 143 | AU33: =Elect!BP34 -> 111 | AX33: 45.411099 | AY33: 22.844806 | AZ33: 245248.7 | BA33: 11.959851 | BB33: 6.0166013 | BC33: =Elect!BQ34 -> 557717 | BD33: =Elect!#REF! -> #REF! | BE33: =Elect!#REF! -> #REF! | BF33: =Elect!#REF! -> #REF! | BG33: =Elect!#REF! -> #REF! | BH33: 1.1514679 | BI33: 0.57929342 | BJ33: 140121.3 | BK33: 6.8331854 | BL33: 3.4377159 | BM33: =Water!U38 -> 1.9468299 | BN33: =Water!W38 -> #DIV/0! | BO33: =Water!X38 -> 49989.04 | BP33: =Water!Y38 -> 7.6028958 | BQ33: =Water!Z38 -> #DIV/0!
A34: AVER. Act | B34: 33257.143 | C34: =Elect!J35 -> 7136 | D34: 0 | E34: =Elect!M35 -> 1928 | F34: 21.428571 | G34: =Elect!O35 -> 1589.3333 | H34: 876.53571 | I34: =Water!C39 -> 128.88889 | J34: 0 | K34: =Water!E40 -> 0 | L34: 4 | M34: =Water!#REF! -> #REF! | N34: =Water!#REF! -> #REF! | O34: 1014 | P34: =Water!H39 -> 426.68022 | Q34: 138 | R34: =Water!O39 -> 0 | S34: 24 | T34: =Water!#REF! -> #REF! | U34: 145 | V34: =Water!#REF! -> #REF! | W34: 877 | X34: =Water!Q39 -> 228.9202 | Y34: 4 | Z34: =Water!#REF! -> #REF! | AA34: 0 | AB34: 0 | AC34: 0 | AD34: =Water!#REF! -> #REF! | AE34: =Water!#REF! -> #REF! | AF34: =Water!#REF! -> #REF! | AG34: =Gas!B39 -> 0 | AH34: =Gas!C39 -> 1411.9082 | AI34: =Gas!#REF! -> #REF! | AJ34: =Gas!J39 -> 350.61 | AK34: =Gas!#REF! -> #REF! | AL34: =Gas!#REF! -> #REF! | AM34: =Gas!#REF! -> #REF! | AN34: =Gas!#REF! -> #REF! | AO34: =Gas!#REF! -> #REF! | AP34: =Gas!#REF! -> #REF! | AQ34: =Gas!#REF! -> #REF! | AR34: =Gas!#REF! -> #REF! | AS34: =Gas!#REF! -> #REF! | AT34: =Elect!BR35 -> 140.33333 | AU34: =Elect!BP35 -> 110.33333 | AX34: 45.411099 | AY34: 22.844806 | AZ34: 8758.8823 | BA34: 11.959851 | BB34: 6.0166013 | BC34: =Elect!BQ35 -> 557857.33 | BD34: =Elect!#REF! -> #REF! | BE34: =Elect!#REF! -> #REF! | BF34: =Elect!#REF! -> #REF! | BG34: =Elect!#REF! -> #REF! | BH34: 1.1761372 | BI34: 0.60007377 | BJ34: 5004.3322 | BK34: 6.8331854 | BL34: 3.4377159 | BM34: =Water!U39 -> 1.9468299 | BN34: =Water!W39 -> #DIV/0! | BO34: =Water!X39 -> 1666.3013 | BP34: =Water!Y39 -> 7.6028958 | BQ34: =Water!Z39 -> #DIV/0!
A35: TOTAL Budget | B35: 1040026 | C35: =Elect!J5 -> 0 | D35: 0 | E35: =Elect!M5 -> 0 | F35: 0 | G35: =Elect!O5 -> 0 | H35: 0 | I35: =Water!C40 -> 0 | J35: 0 | K35: =Water!E41 -> 0 | L35: 5 | M35: =Water!#REF! -> #REF! | N35: =Water!#REF! -> #REF! | O35: 1010 | P35: =Water!H40 -> 0 | Q35: 148 | R35: =Water!O40 -> 0 | S35: 22 | T35: =Water!#REF! -> #REF! | U35: 151 | V35: =Water!#REF! -> #REF! | W35: 833 | X35: =Water!Q40 -> 0 | Y35: 5 | Z35: =Water!#REF! -> #REF! | AA35: 0 | AB35: 0 | AC35: 0 | AD35: =Water!#REF! -> #REF! | AE35: =Water!#REF! -> #REF! | AF35: =Water!#REF! -> #REF! | AG35: =Gas!#REF! -> #REF! | AH35: =Gas!#REF! -> #REF! | AI35: =Gas!#REF! -> #REF! | AJ35: =Gas!#REF! -> #REF! | AK35: =Gas!#REF! -> #REF! | AL35: =Gas!#REF! -> #REF! | AM35: =Gas!#REF! -> #REF! | AN35: =Gas!#REF! -> #REF! | ... AS35: =Gas!#REF! -> #REF! | AT35: =Elect!BR5 -> 0 | AU35: =Elect!BP5 -> 0 | AX35: 45.679286 | AY35: 23.305904 | AZ35: 264708.4 | BA35: 11.626335 | BB35: 5.9318409 | BC35: =Elect!BQ5 -> 553744 | BD35: =Elect!#REF! -> #REF! | BE35: =Elect!#REF! -> #REF! | BF35: =Elect!#REF! -> #REF! | BG35: =Elect!#REF! -> #REF! | BH35: 1.1761372 | BI35: 0.60007377 | BJ35: 150494 | BK35: 6.6098911 | BL35: 3.3724146 | BM35: =Water!U40 -> #REF! | BN35: =Water!W40 -> #REF! | BO35: =Water!X40 -> 0 | BP35: =Water!Y40 -> 0 | BQ35: =Water!Z40 -> 0
A36: Budget MTD | B36: 1040026 | C36: =Elect!#REF! -> #REF! | D36: 0 | E36: =Elect!#REF! -> #REF! | F36: 0 | G36: =Elect!#REF! -> #REF! | H36: 0 | I36: =Water!C41 -> 0 | J36: 0 | K36: =Water!E42 -> 0 | L36: 6 | M36: =Water!#REF! -> #REF! | N36: =Water!#REF! -> #REF! | O36: 30039 | P36: =Water!H41 -> 0 | Q36: 129.54839 | R36: =Water!O41 -> 0 | S36: 719 | T36: =Water!#REF! -> #REF! | U36: 4609 | V36: =Water!#REF! -> #REF! | W36: 23430 | X36: =Water!Q41 -> 0 | Y36: 6 | Z36: =Water!#REF! -> #REF! | AA36: 0 | AB36: 0 | AC36: 0 | AD36: =Water!#REF! -> #REF! | AE36: =Water!#REF! -> #REF! | AF36: =Water!#REF! -> #REF! | AG36: =Gas!#REF! -> #REF! | AH36: =Gas!#REF! -> #REF! | AI36: =Gas!#REF! -> #REF! | AJ36: =Gas!#REF! -> #REF! | AK36: =Gas!#REF! -> #REF! | AL36: =Gas!#REF! -> #REF! | AM36: =Gas!#REF! -> #REF! | AN36: =Gas!#REF! -> #REF! | ... AS36: =Gas!#REF! -> #REF! | AT36: =Elect!#REF! -> #REF! | AU36: =Elect!#REF! -> #REF! | AX36: 45.679286 | AY36: 23.305904 | AZ36: 264708.4 | BA36: 11.626335 | BB36: 5.9318409 | BC36: =Elect!#REF! -> #REF! | BD36: =Elect!#REF! -> #REF! | BE36: =Elect!#REF! -> #REF! | BF36: =Elect!#REF! -> #REF! | BG36: =Elect!#REF! -> #REF! | BH36: 0 | BI36: 0 | BJ36: 135930.06 | BK36: 6.6098911 | BL36: 3.3724146 | BM36: =Water!U41 -> #REF! | BN36: =Water!W41 -> #REF! | BO36: =Water!X41 -> #REF! | BP36: =Water!Y41 -> #REF! | BQ36: =Water!Z41 -> #REF!
A37: AVER. Bud | B37: 37143.785 | C37: =Elect!#REF! -> #REF! | D37: 0 | E37: =Elect!#REF! -> #REF! | F37: 0 | G37: =Elect!#REF! -> #REF! | H37: 0 | I37: =Water!C42 -> 0 | J37: 0 | K37: =Water!E43 -> 0 | L37: 7 | M37: =Water!#REF! -> #REF! | N37: =Water!#REF! -> #REF! | O37: 969 | P37: =Water!H42 -> 0 | Q37: 0 | R37: =Water!O42 -> 0 | S37: 23.193548 | T37: =Water!#REF! -> #REF! | U37: 148.67742 | V37: =Water!#REF! -> #REF! | W37: 755.80645 | X37: =Water!Q42 -> 0 | Y37: 7 | Z37: =Water!#REF! -> #REF! | AA37: 0 | AB37: 0 | AC37: 0 | AD37: =Water!#REF! -> #REF! | AE37: =Water!#REF! -> #REF! | AF37: =Water!#REF! -> #REF! | AG37: =Gas!#REF! -> #REF! | AH37: =Gas!#REF! -> #REF! | AI37: =Gas!#REF! -> #REF! | AJ37: =Gas!#REF! -> #REF! | AK37: =Gas!#REF! -> #REF! | AL37: =Gas!#REF! -> #REF! | AM37: =Gas!#REF! -> #REF! | AN37: =Gas!#REF! -> #REF! | ... AS37: =Gas!#REF! -> #REF! | AT37: =Elect!#REF! -> #REF! | AU37: =Elect!#REF! -> #REF! | AX37: 0 | AY37: 0 | AZ37: 9453.8714 | BA37: 0 | BB37: 0 | BC37: =Elect!#REF! -> #REF! | BD37: =Elect!#REF! -> #REF! | BE37: =Elect!#REF! -> #REF! | BF37: =Elect!#REF! -> #REF! | BG37: =Elect!#REF! -> #REF! | BH37: 0 | BI37: 0 | BJ37: 0 | BK37: 0 | BL37: 0 | BM37: =Water!U42 -> 0 | BN37: =Water!W42 -> 0 | BO37: =Water!X42 -> 0 | BP37: =Water!Y42 -> 0 | BQ37: =Water!Z42 -> 0
A38: Total RFC | B38: 784008.53 | C38: =Elect!#REF! -> #REF! | D38: 0 | E38: =Elect!#REF! -> #REF! | F38: 0 | G38: =Elect!#REF! -> #REF! | H38: 0 | I38: =Water!C43 -> 0 | J38: 0 | K38: =Water!E44 -> 0 | L38: 8 | M38: =Water!#REF! -> #REF! | N38: =Water!#REF! -> #REF! | O38: 0 | P38: =Water!H43 -> 0 | Q38: 0 | R38: =Water!O43 -> 0 | S38: 0 | T38: =Water!#REF! -> #REF! | U38: 0 | V38: =Water!#REF! -> #REF! | W38: 0 | X38: =Water!Q43 -> 0 | Y38: 8 | Z38: =Water!#REF! -> #REF! | AA38: 0 | AB38: 0 | AC38: 0 | AD38: =Water!#REF! -> #REF! | AE38: =Water!#REF! -> #REF! | AF38: =Water!#REF! -> #REF! | AG38: =Gas!#REF! -> #REF! | AH38: =Gas!#REF! -> #REF! | AI38: =Gas!#REF! -> #REF! | AJ38: =Gas!#REF! -> #REF! | AK38: =Gas!#REF! -> #REF! | AL38: =Gas!#REF! -> #REF! | AM38: =Gas!#REF! -> #REF! | AN38: =Gas!#REF! -> #REF! | ... AS38: =Gas!#REF! -> #REF! | AT38: =Elect!#REF! -> #REF! | AU38: =Elect!#REF! -> #REF! | AX38: 38.173558 | AY38: 19.219193 | AZ38: 208225.85 | BA38: 10.138565 | BB38: 5.1044505 | BC38: =Elect!#REF! -> #REF! | BD38: =Elect!#REF! -> #REF! | BE38: =Elect!#REF! -> #REF! | BF38: =Elect!#REF! -> #REF! | BG38: =Elect!#REF! -> #REF! | BH38: 0 | BI38: 0 | BJ38: 127385.62 | BK38: 6.2024355 | BL38: 3.1227323 | BM38: =Water!U43 -> 0 | BN38: =Water!W43 -> 0 | BO38: =Water!X43 -> 0 | BP38: =Water!Y43 -> 0 | BQ38: =Water!Z43 -> 0
A39: RFC MTD | B39: 784008.53 | C39: =Elect!#REF! -> #REF! | D39: 0 | E39: =Elect!#REF! -> #REF! | F39: 0 | G39: =Elect!#REF! -> #REF! | H39: 0 | I39: =Water!C44 -> 0 | J39: 0 | K39: =Water!E45 -> 0 | L39: 9 | M39: =Water!#REF! -> #REF! | N39: =Water!#REF! -> #REF! | O39: 0 | P39: =Water!H44 -> 0 | Q39: 0 | R39: =Water!O44 -> 0 | S39: 0 | T39: =Water!#REF! -> #REF! | U39: 0 | V39: =Water!#REF! -> #REF! | W39: 0 | X39: =Water!Q44 -> 0 | Y39: 9 | Z39: =Water!#REF! -> #REF! | AA39: 0 | AB39: 0 | AC39: 0 | AD39: =Water!#REF! -> #REF! | AE39: =Water!#REF! -> #REF! | AF39: =Water!#REF! -> #REF! | AG39: =Gas!#REF! -> #REF! | AH39: =Gas!#REF! -> #REF! | AI39: =Gas!#REF! -> #REF! | AJ39: =Gas!#REF! -> #REF! | AK39: =Gas!#REF! -> #REF! | AL39: =Gas!#REF! -> #REF! | AM39: =Gas!#REF! -> #REF! | AN39: =Gas!#REF! -> #REF! | ... AS39: =Gas!#REF! -> #REF! | AT39: =Elect!#REF! -> #REF! | AU39: =Elect!#REF! -> #REF! | AX39: 38.173558 | AY39: 19.219193 | AZ39: 208225.85 | BA39: 10.138565 | BB39: 5.1044505 | BC39: =Elect!#REF! -> #REF! | BD39: =Elect!#REF! -> #REF! | BE39: =Elect!#REF! -> #REF! | BF39: =Elect!#REF! -> #REF! | BG39: =Elect!#REF! -> #REF! | BH39: 0 | BI39: 0 | BJ39: 115057.98 | BK39: 6.2024355 | BL39: 3.1227323 | BM39: =Water!U44 -> 0 | BN39: =Water!W44 -> 0 | BO39: =Water!X44 -> #VALUE! | BP39: =Water!Y44 -> #VALUE! | BQ39: =Water!Z44 -> #VALUE!
A40: AVER RFC | B40: 28000.305 | C40: =Elect!#REF! -> #REF! | D40: 0 | E40: =Elect!#REF! -> #REF! | F40: 0 | G40: =Elect!#REF! -> #REF! | H40: 0 | I40: =Water!C45 -> 0 | J40: 0 | K40: =Water!E46 -> 0 | L40: 10 | M40: =Water!#REF! -> #REF! | N40: =Water!#REF! -> #REF! | O40: 0 | P40: =Water!H45 -> 0 | Q40: 0 | R40: =Water!O45 -> 0 | S40: 0 | T40: =Water!#REF! -> #REF! | U40: 0 | V40: =Water!#REF! -> #REF! | W40: 0 | X40: =Water!Q45 -> 0 | Y40: 10 | Z40: =Water!#REF! -> #REF! | AA40: 0 | AB40: 0 | AC40: 0 | AD40: =Water!#REF! -> #REF! | AE40: =Water!#REF! -> #REF! | AF40: =Water!#REF! -> #REF! | AG40: =Gas!#REF! -> #REF! | AH40: =Gas!#REF! -> #REF! | AI40: =Gas!#REF! -> #REF! | AJ40: =Gas!#REF! -> #REF! | AK40: =Gas!#REF! -> #REF! | AL40: =Gas!#REF! -> #REF! | AM40: =Gas!#REF! -> #REF! | AN40: =Gas!#REF! -> #REF! | ... AS40: =Gas!#REF! -> #REF! | AT40: =Elect!#REF! -> #REF! | AU40: =Elect!#REF! -> #REF! | AX40: 0 | AY40: 0 | AZ40: 7436.6375 | BA40: 0 | BB40: 0 | BC40: =Elect!#REF! -> #REF! | BD40: =Elect!#REF! -> #REF! | BE40: =Elect!#REF! -> #REF! | BF40: =Elect!#REF! -> #REF! | BG40: =Elect!#REF! -> #REF! | BH40: 1.1254646 | BI40: 0.57264868 | BJ40: 4109.2135 | BK40: 0 | BL40: 0 | BM40: =Water!U45 -> 0 | BN40: =Water!W45 -> 0 | BO40: =Water!X45 -> #VALUE! | BP40: =Water!Y45 -> 0 | BQ40: =Water!Z45 -> 0

Sheet Temp.
A2: HILTON INTERNATIONAL
A3: GULF, MIDDLE EAST AND ASIA SPECIFIC
A4: HOTEL:HILTON HURGHADA LONG BEACH RESORT | G4: =Elect!A1 -> 44835
A7: DATE | B7: MAX TEMP | C7: MIN TEMP | D7: MAX TEMP | E7: MIN TEMP | F7: DAY | G7: DD. C | H7: DD. H | I7: MTD | J7: MTD
B8: C | C8: C | D8: F | E8: F | F8: PARAMETER | I8: COOLING | J8: HEATING
A10: 1 | D10: =SUM((B10*9/5)+32) -> 32 | E10: =SUM((C10*9/5)+32) -> 32 | F10: =SUM(((B10+C10)/2)-18.33) -> -18.33 | G10: =SUM(0+(F10)+ABS(F10))/2 -> 0 | H10: =IF((SUM(0-(F10)+ABS(F10))/2)<18,SUM(0-(F10)+ABS(F10))/2,0) -> 0 | I10: =SUM(G10:G10) -> 0 | J10: =SUM(H10:H10) -> 0
A11: 2 | D11: =SUM((B11*9/5)+32) -> 32 | E11: =SUM((C11*9/5)+32) -> 32 | F11: =SUM(((B11+C11)/2)-18.33) -> -18.33 | G11: =SUM(0+(F11)+ABS(F11))/2 -> 0 | H11: =IF((SUM(0-(F11)+ABS(F11))/2)<18,SUM(0-(F11)+ABS(F11))/2,0) -> 0 | I11: =SUM(G10:G11) -> 0 | J11: =SUM(H10:H11) -> 0
A12: 3 | D12: =SUM((B12*9/5)+32) -> 32 | E12: =SUM((C12*9/5)+32) -> 32 | F12: =SUM(((B12+C12)/2)-18.33) -> -18.33 | G12: =SUM(0+(F12)+ABS(F12))/2 -> 0 | H12: =IF((SUM(0-(F12)+ABS(F12))/2)<18,SUM(0-(F12)+ABS(F12))/2,0) -> 0 | I12: =SUM(G10:G12) -> 0 | J12: =SUM(H10:H12) -> 0
A13: 4 | D13: =SUM((B13*9/5)+32) -> 32 | E13: =SUM((C13*9/5)+32) -> 32 | F13: =SUM(((B13+C13)/2)-18.33) -> -18.33 | G13: =SUM(0+(F13)+ABS(F13))/2 -> 0 | H13: =IF((SUM(0-(F13)+ABS(F13))/2)<18,SUM(0-(F13)+ABS(F13))/2,0) -> 0 | I13: =SUM(G10:G13) -> 0 | J13: =SUM(H10:H13) -> 0
A14: 5 | D14: =SUM((B14*9/5)+32) -> 32 | E14: =SUM((C14*9/5)+32) -> 32 | F14: =SUM(((B14+C14)/2)-18.33) -> -18.33 | G14: =SUM(0+(F14)+ABS(F14))/2 -> 0 | H14: =IF((SUM(0-(F14)+ABS(F14))/2)<18,SUM(0-(F14)+ABS(F14))/2,0) -> 0 | I14: =SUM(G10:G14) -> 0 | J14: =SUM(H10:H14) -> 0
A15: 6 | D15: =SUM((B15*9/5)+32) -> 32 | E15: =SUM((C15*9/5)+32) -> 32 | F15: =SUM(((B15+C15)/2)-18.33) -> -18.33 | G15: =SUM(0+(F15)+ABS(F15))/2 -> 0 | H15: =IF((SUM(0-(F15)+ABS(F15))/2)<18,SUM(0-(F15)+ABS(F15))/2,0) -> 0 | I15: =SUM(G10:G15) -> 0 | J15: =SUM(H10:H15) -> 0
A16: 7 | D16: =SUM((B16*9/5)+32) -> 32 | E16: =SUM((C16*9/5)+32) -> 32 | F16: =SUM(((B16+C16)/2)-18.33) -> -18.33 | G16: =SUM(0+(F16)+ABS(F16))/2 -> 0 | H16: =IF((SUM(0-(F16)+ABS(F16))/2)<18,SUM(0-(F16)+ABS(F16))/2,0) -> 0 | I16: =SUM(G10:G16) -> 0 | J16: =SUM(H10:H16) -> 0
A17: 8 | D17: =SUM((B17*9/5)+32) -> 32 | E17: =SUM((C17*9/5)+32) -> 32 | F17: =SUM(((B17+C17)/2)-18.33) -> -18.33 | G17: =SUM(0+(F17)+ABS(F17))/2 -> 0 | H17: =IF((SUM(0-(F17)+ABS(F17))/2)<18,SUM(0-(F17)+ABS(F17))/2,0) -> 0 | I17: =SUM(G10:G17) -> 0 | J17: =SUM(H10:H17) -> 0
A18: 9 | D18: =SUM((B18*9/5)+32) -> 32 | E18: =SUM((C18*9/5)+32) -> 32 | F18: =SUM(((B18+C18)/2)-18.33) -> -18.33 | G18: =SUM(0+(F18)+ABS(F18))/2 -> 0 | H18: =IF((SUM(0-(F18)+ABS(F18))/2)<18,SUM(0-(F18)+ABS(F18))/2,0) -> 0 | I18: =SUM(G10:G18) -> 0 | J18: =SUM(H10:H18) -> 0
A19: 10 | D19: =SUM((B19*9/5)+32) -> 32 | E19: =SUM((C19*9/5)+32) -> 32 | F19: =SUM(((B19+C19)/2)-18.33) -> -18.33 | G19: =SUM(0+(F19)+ABS(F19))/2 -> 0 | H19: =IF((SUM(0-(F19)+ABS(F19))/2)<18,SUM(0-(F19)+ABS(F19))/2,0) -> 0 | I19: =SUM(G10:G19) -> 0 | J19: =SUM(H10:H19) -> 0
A20: 11 | D20: =SUM((B20*9/5)+32) -> 32 | E20: =SUM((C20*9/5)+32) -> 32 | F20: =SUM(((B20+C20)/2)-18.33) -> -18.33 | G20: =SUM(0+(F20)+ABS(F20))/2 -> 0 | H20: =IF((SUM(0-(F20)+ABS(F20))/2)<18,SUM(0-(F20)+ABS(F20))/2,0) -> 0 | I20: =SUM(G10:G20) -> 0 | J20: =SUM(H10:H20) -> 0
A21: 12 | D21: =SUM((B21*9/5)+32) -> 32 | E21: =SUM((C21*9/5)+32) -> 32 | F21: =SUM(((B21+C21)/2)-18.33) -> -18.33 | G21: =SUM(0+(F21)+ABS(F21))/2 -> 0 | H21: =IF((SUM(0-(F21)+ABS(F21))/2)<18,SUM(0-(F21)+ABS(F21))/2,0) -> 0 | I21: =SUM(G10:G21) -> 0 | J21: =SUM(H10:H21) -> 0
A22: 13 | D22: =SUM((B22*9/5)+32) -> 32 | E22: =SUM((C22*9/5)+32) -> 32 | F22: =SUM(((B22+C22)/2)-18.33) -> -18.33 | G22: =SUM(0+(F22)+ABS(F22))/2 -> 0 | H22: =IF((SUM(0-(F22)+ABS(F22))/2)<18,SUM(0-(F22)+ABS(F22))/2,0) -> 0 | I22: =SUM(G10:G22) -> 0 | J22: =SUM(H10:H22) -> 0
A23: 14 | D23: =SUM((B23*9/5)+32) -> 32 | E23: =SUM((C23*9/5)+32) -> 32 | F23: =SUM(((B23+C23)/2)-18.33) -> -18.33 | G23: =SUM(0+(F23)+ABS(F23))/2 -> 0 | H23: =IF((SUM(0-(F23)+ABS(F23))/2)<18,SUM(0-(F23)+ABS(F23))/2,0) -> 0 | I23: =SUM(G10:G23) -> 0 | J23: =SUM(H10:H23) -> 0
A24: 15 | D24: =SUM((B24*9/5)+32) -> 32 | E24: =SUM((C24*9/5)+32) -> 32 | F24: =SUM(((B24+C24)/2)-18.33) -> -18.33 | G24: =SUM(0+(F24)+ABS(F24))/2 -> 0 | H24: =IF((SUM(0-(F24)+ABS(F24))/2)<18,SUM(0-(F24)+ABS(F24))/2,0) -> 0 | I24: =SUM(G11:G24) -> 0 | J24: =SUM(H11:H24) -> 0
A25: 16 | D25: =SUM((B25*9/5)+32) -> 32 | E25: =SUM((C25*9/5)+32) -> 32 | F25: =SUM(((B25+C25)/2)-18.33) -> -18.33 | G25: =SUM(0+(F25)+ABS(F25))/2 -> 0 | H25: =IF((SUM(0-(F25)+ABS(F25))/2)<18,SUM(0-(F25)+ABS(F25))/2,0) -> 0 | I25: =SUM(G12:G25) -> 0 | J25: =SUM(H12:H25) -> 0
A26: 17 | D26: =SUM((B26*9/5)+32) -> 32 | E26: =SUM((C26*9/5)+32) -> 32 | F26: =SUM(((B26+C26)/2)-18.33) -> -18.33 | G26: =SUM(0+(F26)+ABS(F26))/2 -> 0 | H26: =IF((SUM(0-(F26)+ABS(F26))/2)<18,SUM(0-(F26)+ABS(F26))/2,0) -> 0 | I26: =SUM(G13:G26) -> 0 | J26: =SUM(H13:H26) -> 0
A27: 18 | D27: =SUM((B27*9/5)+32) -> 32 | E27: =SUM((C27*9/5)+32) -> 32 | F27: =SUM(((B27+C27)/2)-18.33) -> -18.33 | G27: =SUM(0+(F27)+ABS(F27))/2 -> 0 | H27: =IF((SUM(0-(F27)+ABS(F27))/2)<18,SUM(0-(F27)+ABS(F27))/2,0) -> 0 | I27: =SUM(G14:G27) -> 0 | J27: =SUM(H14:H27) -> 0
A28: 19 | D28: =SUM((B28*9/5)+32) -> 32 | E28: =SUM((C28*9/5)+32) -> 32 | F28: =SUM(((B28+C28)/2)-18.33) -> -18.33 | G28: =SUM(0+(F28)+ABS(F28))/2 -> 0 | H28: =IF((SUM(0-(F28)+ABS(F28))/2)<18,SUM(0-(F28)+ABS(F28))/2,0) -> 0 | I28: =SUM(G15:G28) -> 0 | J28: =SUM(H15:H28) -> 0
A29: 20 | D29: =SUM((B29*9/5)+32) -> 32 | E29: =SUM((C29*9/5)+32) -> 32 | F29: =SUM(((B29+C29)/2)-18.33) -> -18.33 | G29: =SUM(0+(F29)+ABS(F29))/2 -> 0 | H29: =IF((SUM(0-(F29)+ABS(F29))/2)<18,SUM(0-(F29)+ABS(F29))/2,0) -> 0 | I29: =SUM(G16:G29) -> 0 | J29: =SUM(H16:H29) -> 0
A30: 21 | D30: =SUM((B30*9/5)+32) -> 32 | E30: =SUM((C30*9/5)+32) -> 32 | F30: =SUM(((B30+C30)/2)-18.33) -> -18.33 | G30: =SUM(0+(F30)+ABS(F30))/2 -> 0 | H30: =IF((SUM(0-(F30)+ABS(F30))/2)<18,SUM(0-(F30)+ABS(F30))/2,0) -> 0 | I30: =SUM(G17:G30) -> 0 | J30: =SUM(H17:H30) -> 0
A31: 22 | D31: =SUM((B31*9/5)+32) -> 32 | E31: =SUM((C31*9/5)+32) -> 32 | F31: =SUM(((B31+C31)/2)-18.33) -> -18.33 | G31: =SUM(0+(F31)+ABS(F31))/2 -> 0 | H31: =IF((SUM(0-(F31)+ABS(F31))/2)<18,SUM(0-(F31)+ABS(F31))/2,0) -> 0 | I31: =SUM(G18:G31) -> 0 | J31: =SUM(H18:H31) -> 0
A32: 23 | D32: =SUM((B32*9/5)+32) -> 32 | E32: =SUM((C32*9/5)+32) -> 32 | F32: =SUM(((B32+C32)/2)-18.33) -> -18.33 | G32: =SUM(0+(F32)+ABS(F32))/2 -> 0 | H32: =IF((SUM(0-(F32)+ABS(F32))/2)<18,SUM(0-(F32)+ABS(F32))/2,0) -> 0 | I32: =SUM(G19:G32) -> 0 | J32: =SUM(H19:H32) -> 0
A33: 24 | D33: =SUM((B33*9/5)+32) -> 32 | E33: =SUM((C33*9/5)+32) -> 32 | F33: =SUM(((B33+C33)/2)-18.33) -> -18.33 | G33: =SUM(0+(F33)+ABS(F33))/2 -> 0 | H33: =IF((SUM(0-(F33)+ABS(F33))/2)<18,SUM(0-(F33)+ABS(F33))/2,0) -> 0 | I33: =SUM(G20:G33) -> 0 | J33: =SUM(H20:H33) -> 0
A34: 25 | D34: =SUM((B34*9/5)+32) -> 32 | E34: =SUM((C34*9/5)+32) -> 32 | F34: =SUM(((B34+C34)/2)-18.33) -> -18.33 | G34: =SUM(0+(F34)+ABS(F34))/2 -> 0 | H34: =IF((SUM(0-(F34)+ABS(F34))/2)<18,SUM(0-(F34)+ABS(F34))/2,0) -> 0 | I34: =SUM(G21:G34) -> 0 | J34: =SUM(H21:H34) -> 0
... A40: 31 | D40: =SUM((B40*9/5)+32) -> 32 | E40: =SUM((C40*9/5)+32) -> 32 | F40: =SUM(((B40+C40)/2)-18.33) -> -18.33 | G40: =SUM(0+(F40)+ABS(F40))/2 -> 0 | H40: =IF((SUM(0-(F40)+ABS(F40))/2)<18,SUM(0-(F40)+ABS(F40))/2,0) -> 0 | I40: =SUM(G27:G40) -> 0 | J40: =SUM(H27:H40) -> 0
E42: =SUM(G10:G40) -> 0 | F42: deg c
E44: =SUM(H10:H40) -> 0 | F44: deg c

Sheet M-Rep
B3: =Elect!A1 -> 44835
D4: Y.T.D
A5: Energy breakdown | C5: 2009 | D5: 2005 | E5: 2006
A6: Elect.
A7: Chillers KWH | C7: N/A | D7: N/A | E7: N/A
A8: Laundry KWH | C8: N/A | D8: N/A | E8: N/A
A9: Kitchen KWH | C9: N/A | D9: N/A | E9: N/A
A10: Gas
A11: Kit M3 | C11: =Gas!#REF!/1000 -> #REF!
A12: Laundry M3 | C12: N/A | D12: 0 | E12: #REF!
A13: Water | D13: N/A | E13: N/A
A14: Laundry HW | C14: N/A
A15: Laundry CW | C15: N/A
A16: Kit HW | C16: N/A
A17: kIt CW | C17: N/A | D17: N/A | E17: N/A
A18: Dmstc HW | C18: N/A | D18: N/A | E18: N/A
A19: Dmstc CW | C19: N/A | D19: N/A | E19: N/A
A20: S.Pool MKUP | C20: =#REF! -> #REF! | D20: N/A | E20: N/A
A21: Ctower MKUP | C21: N/A | D21: N/A | E21: N/A
A22: Gardens Irrigat. | C22: =Water!S38 -> 0 | D22: N/A | E22: N/A
A23: Swage water treatment | C23: =Water!#REF! -> #REF! | D23: 27437 | E23: #REF!
A24: Utilities consumption | D24: N/A | E24: N/A
A25: Elect. Kwh | C25: =Elect!J34 -> 1726 | D25: 12266 | E25: 814
A26: M.D (9.5 LE) | D26: 147773 | E26: #REF!
A27: Water M3 | C27: =Water!H38 -> 12800.407
A28: Fuel Ltr | C28: =Gas!#REF!*1000 -> #REF! | D28: 12876868 | E28: 14500800
A29: Gas M3/ Boilers, chillers,..etc | C29: N/A | D29: 28880 | E29: 32980
A30: Gas M3 Kitchen | C30: =Gas!#REF!/1000 -> #REF! | D30: 244283 | E30: 252530.66
A31: Total Energy | D31: 620770 | E31: #REF!
A32: Control Parameters | D32: #REF! | E32: N/A
A33: No. of Rooms % occ. | C33: =YTD!Q4 -> 0 | D33: 39.395 | E33: #REF!
A34: No. of Occ. Rooms | C34: =YTD!Q5 -> 0
A35: guest count | C35: =YTD!Q6 -> 0
A36: Food covers | D36: #REF! | E36: #REF!
A37: Laundry W. Kg | D37: 0.8807 | E37: 0.46351998
A38: DDC | C38: =Temp.!E42 -> 0 | D38: 196150 | E38: 237021
A39: DDH | C39: =Temp.!E44 -> 0 | D39: 400070 | E39: 466105
A40: Utilities Entergy cost | D40: 1583714 | E40: 1940567
A41: Elect. | C41: =Elect!#REF! -> #REF! | D41: 1690339 | E41: 3118671.6
A42: M.D | C42: =C26*Elect!#REF! -> #REF! | D42: 2381.51 | E42: 2480.24
A43: Water | C43: =Water!X38 -> 49989.04 | D43: 112 | E43: 97.53
A44: Fuel | C44: =Gas!#REF! -> #REF!
A45: Gas Boilers, chillers,etc.. | C45: N/A | D45: 2138156.8 | E45: #REF!
A46: Gas Kitchen | C46: =C30*Gas!M2*1000 -> #REF! | D46: 223044.2 | E46: #REF!
A47: TOTAL LE | C47: =SUM(C41:C46) -> #REF! | D47: 1330535.7 | E47: 1382037.4
A48: No. of POMEC Staff | D48: 330278 | E48: #REF!
A49: Hotel Age | C49: 6 | D49: N/A | E49: N/A
A50: No. of rooms | C50: =31*912 -> 28272 | D50: 36597.525 | E50: #REF!
A51: Building Volume | C51: 243175 | D51: =SUM(D45:D50) -> 4058612.3 | E51: =SUM(E45:E50) -> #REF!
A52: Building area | C52: 75064
A53: US$ Rate | C53: 5.59402 | D53: 61 | E53: 72
A54: Total R&M MTD | C54: =YTD!Q65 -> 0 | D54: #REF! | E54: 243175 | F54: =YTD!Q64 -> 0
A55: Staff - HLP | D55: #REF! | E55: 75064
A56: Staff - R&M | D56: 5.755 | E56: 5.65951
A57: Staff - Grounds

Sheet YTD
A1: =Elect!A1 -> 44835 | H1: Actual 2014
C3: JAN | D3: FEB | E3: MAR | F3: APR | G3: MAY | H3: JUN | I3: JUL | J3: AUG | K3: SEP | L3: OCT | M3: NOV | N3: DEC | O3: TOTAL | P3: YTD | Q3: Month Act
A4: Occ Room % | O4: =SUM(C4:N4) -> 0 | P4: =(IF($A$1=39814,C4,(IF($A$1=39845,SUM(C4:D4),(IF($A$1=39873,SUM(C4:E4),(IF($A$1=39904,SUM(C4:F4),(IF($A$1=39934,SUM(C4:G4),(IF($A$1=39965,SUM(C4:H4),(IF($A$1=39995,SUM(C4:I4),0)))))))))))))+(IF($A$1=40026,SUM(C4:J4),(IF($A$1=40057,SUM(C4:K4),(IF($A$1=40087,SUM(C4:L4),(IF($A$1=40118,SUM(C4:M4))))))))))+(IF($A$1=40148,SUM(C4:N4),0)) -> 0 | Q4: =(IF($A$1=39814,C4,(IF($A$1=39845,D4,(IF($A$1=39873,E4,(IF($A$1=39904,F4,(IF($A$1=39934,G4,(IF($A$1=39965,H4,(IF($A$1=39995,I4,0)))))))))))))+(IF($A$1=40026,J4,(IF($A$1=40057,K4,(IF($A$1=40087,L4,(IF($A$1=40118,M4)))))))))+(IF($A$1=40148,N4,0)) -> 0 | S4: 40179 | DE4: 1
A5: Occ Room | C5: 25072 | D5: =Elect!BP34 -> 111 | O5: =SUM(C5:N5) -> 25183 | P5: =(IF($A$1=40179,C5,(IF($A$1=40210,SUM(C5:D5),(IF($A$1=40238,SUM(C5:E5),(IF($A$1=40269,SUM(C5:F5),(IF($A$1=40299,SUM(C5:G5),(IF($A$1=40330,SUM(C5:H5),(IF($A$1=40360,SUM(C5:I5),0)))))))))))))+(IF($A$1=40391,SUM(C5:J5),(IF($A$1=40422,SUM(C5:K5),(IF($A$1=40452,SUM(C5:L5),(IF($A$1=40483,SUM(C5:M5))))))))))+(IF($A$1=40513,SUM(C5:N5),0)) -> 0 | Q5: =(IF($A$1=40179,C5,(IF($A$1=40210,D5,(IF($A$1=40238,E5,(IF($A$1=40269,F5,(IF($A$1=40299,G5,(IF($A$1=40330,H5,(IF($A$1=40360,I5,0)))))))))))))+(IF($A$1=40391,J5,(IF($A$1=40422,K5,(IF($A$1=40452,L5,(IF($A$1=40483,M5)))))))))+(IF($A$1=40513,N5,0)) -> 0 | S5: 40210 | DE5: 2
A6: Number of Guest | C6: 50662 | D6: =Elect!BR34 -> 143 | O6: =SUM(C6:N6) -> 50805 | P6: =(IF($A$1=40179,C6,(IF($A$1=40210,SUM(C6:D6),(IF($A$1=40238,SUM(C6:E6),(IF($A$1=40269,SUM(C6:F6),(IF($A$1=40299,SUM(C6:G6),(IF($A$1=40330,SUM(C6:H6),(IF($A$1=40360,SUM(C6:I6),0)))))))))))))+(IF($A$1=40391,SUM(C6:J6),(IF($A$1=40422,SUM(C6:K6),(IF($A$1=40452,SUM(C6:L6),(IF($A$1=40483,SUM(C6:M6))))))))))+(IF($A$1=40513,SUM(C6:N6),0)) -> 0 | Q6: =(IF($A$1=40179,C6,(IF($A$1=40210,D6,(IF($A$1=40238,E6,(IF($A$1=40269,F6,(IF($A$1=40299,G6,(IF($A$1=40330,H6,(IF($A$1=40360,I6,0)))))))))))))+(IF($A$1=40391,J6,(IF($A$1=40422,K6,(IF($A$1=40452,L6,(IF($A$1=40483,M6)))))))))+(IF($A$1=40513,N6,0)) -> 0 | S6: 40238 | DE6: 3
