Workbook

Sheet Total
A1: Site Name | B1: Day | C1: Month | D1: Year | E1: Total Electricity Kwh | F1: Electricity Tariff ($/Kwh) | G1: Total Fuel Oil (Liter) | H1: Fuel Oil $/Liter | I1: LPG (Kg) | J1: LPG $/Kg | K1: Water Utility Supply (m3) m3 | L1: Water Utility Supply (m3) $/m3 | M1: Irrigation Water (m3) m3 | N1: Irrigation water $/m3 | O1: Room Nights
A2: Beirut | B2: 1 | C2: 1 | D2: 2023 | E2: =ELEC!N4 -> 0 | F2: =SUM('EDl log'!T4) -> 0 | G2: =-tanks!AW6 -> 0 | H2: =tanks!AV6 -> 0 | I2: =('B5'!AU5)*0.51 -> 0 | J2: ='B5'!AX5/0.51 -> 1.5686275 | K2: =WATER!I6 -> 0 | L2: =SUM(WATER!J6) -> 0 | M2: =WATER!Q6 -> 0 | N2: 0.6 | O2: =ELEC!B4 -> 0
A3: Beirut | B3: =B2+1 -> 2 | C3: 1 | D3: 2023 | E3: =ELEC!N5 -> 0 | F3: =SUM('EDl log'!T5) -> 0 | G3: =-tanks!AW7 -> 0 | H3: =tanks!AV7 -> 0 | I3: =('B5'!AU6)*0.51 -> 0 | J3: ='B5'!AX6/0.51 -> 1.5686275 | K3: =WATER!I7 -> 0 | L3: =SUM(WATER!J7) -> 0 | M3: =WATER!Q7 -> 0 | N3: 0.6 | O3: =ELEC!B5 -> 0
A4: Beirut | B4: =B3+1 -> 3 | C4: 1 | D4: 2023 | E4: =ELEC!N6 -> 2464 | F4: =SUM('EDl log'!T6) -> 0.44985468 | G4: =-tanks!AW8 -> 84 | H4: =tanks!AV8 -> 0 | I4: =('B5'!AU7)*0.51 -> 0 | J4: ='B5'!AX7/0.51 -> 1.5686275 | K4: =WATER!I8 -> 0 | L4: =SUM(WATER!J8) -> 0 | M4: =WATER!Q8 -> 0 | N4: 0.6 | O4: =ELEC!B6 -> 0
A5: Beirut | B5: =B4+1 -> 4 | C5: 1 | D5: 2023 | E5: =ELEC!N7 -> 2763 | F5: =SUM('EDl log'!T7) -> 0.091762357 | G5: =-tanks!AW9 -> 297 | H5: =tanks!AV9 -> 0.89 | I5: =('B5'!AU8)*0.51 -> 0 | J5: ='B5'!AX8/0.51 -> 1.5686275 | K5: =WATER!I9 -> 0 | L5: =SUM(WATER!J9) -> 0 | M5: =WATER!Q9 -> 0 | N5: 0.6 | O5: =ELEC!B7 -> 0
A6: Beirut | B6: =B5+1 -> 5 | C6: 1 | D6: 2023 | E6: =ELEC!N8 -> 2299 | F6: =SUM('EDl log'!T8) -> 0.37940614 | G6: =-tanks!AW10 -> 113 | H6: =tanks!AV10 -> 0.89 | I6: =('B5'!AU9)*0.51 -> 0 | J6: ='B5'!AX9/0.51 -> 1.5686275 | K6: =WATER!I10 -> 0 | L6: =SUM(WATER!J10) -> 0 | M6: =WATER!Q10 -> 0 | N6: 0.6 | O6: =ELEC!B8 -> 0
A7: Beirut | B7: =B6+1 -> 6 | C7: 1 | D7: 2023 | E7: =ELEC!N9 -> 0 | F7: =SUM('EDl log'!T9) -> 0 | G7: =-tanks!AW11 -> 0 | H7: =tanks!AV11 -> 0.89 | I7: =('B5'!AU10)*0.51 -> 0 | J7: ='B5'!AX10/0.51 -> 1.5686275 | K7: =WATER!I11 -> 0 | L7: =SUM(WATER!J11) -> 0 | M7: =WATER!Q11 -> 0 | N7: 0.6 | O7: =ELEC!B9 -> 0
A8: Beirut | B8: =B7+1 -> 7 | C8: 1 | D8: 2023 | E8: =ELEC!N10 -> 0 | F8: =SUM('EDl log'!T10) -> 0 | G8: =-tanks!AW12 -> 0 | H8: =tanks!AV12 -> 0.89 | I8: =('B5'!AU11)*0.51 -> 0 | J8: ='B5'!AX11/0.51 -> 1.5686275 | K8: =WATER!I12 -> 0 | L8: =SUM(WATER!J12) -> 0 | M8: =WATER!Q12 -> 0 | N8: 0.6 | O8: =ELEC!B10 -> 0
A9: Beirut | B9: =B8+1 -> 8 | C9: 1 | D9: 2023 | E9: =ELEC!N11 -> 2330 | F9: =SUM('EDl log'!T11) -> 0.34879473 | G9: =-tanks!AW13 -> 180 | H9: =tanks!AV13 -> 0.89 | I9: =('B5'!AU12)*0.51 -> 0 | J9: ='B5'!AX12/0.51 -> 1.5686275 | K9: =WATER!I13 -> 5 | L9: =SUM(WATER!J13) -> 48.387097 | M9: =WATER!Q13 -> 0 | N9: 0.6 | O9: =ELEC!B11 -> 0
A10: Beirut | B10: =B9+1 -> 9 | C10: 1 | D10: 2023 | E10: =ELEC!N12 -> 3064 | F10: =SUM('EDl log'!T12) -> 0.14825946 | G10: =-tanks!AW14 -> 276.5 | H10: =tanks!AV14 -> 0.89 | I10: =('B5'!AU13)*0.51 -> 0 | J10: ='B5'!AX13/0.51 -> 1.5686275 | K10: =WATER!I14 -> 0 | L10: =SUM(WATER!J14) -> 0 | M10: =WATER!Q14 -> 0 | N10: 0.6 | O10: =ELEC!B12 -> 0
A11: Beirut | B11: =B10+1 -> 10 | C11: 1 | D11: 2023 | E11: =ELEC!N13 -> 2908 | F11: =SUM('EDl log'!T13) -> 0.31401263 | G11: =-tanks!AW15 -> 67 | H11: =tanks!AV15 -> 0.89 | I11: =('B5'!AU14)*0.51 -> 0 | J11: ='B5'!AX14/0.51 -> 1.5686275 | K11: =WATER!I15 -> 0 | L11: =SUM(WATER!J15) -> 0 | M11: =WATER!Q15 -> 0 | N11: 0.6 | O11: =ELEC!B13 -> 0
A12: Beirut | B12: =B11+1 -> 11 | C12: 1 | D12: 2023 | E12: =ELEC!N14 -> 1839 | F12: =SUM('EDl log'!T14) -> 0.44118742 | G12: =-tanks!AW16 -> 205 | H12: =tanks!AV16 -> 0.89 | I12: =('B5'!AU15)*0.51 -> 0 | J12: ='B5'!AX15/0.51 -> 1.5686275 | K12: =WATER!I16 -> 0 | L12: =SUM(WATER!J16) -> 0 | M12: =WATER!Q16 -> 0 | N12: 0.6 | O12: =ELEC!B14 -> 0
A13: Beirut | B13: =B12+1 -> 12 | C13: 1 | D13: 2023 | E13: =ELEC!N15 -> 4552 | F13: =SUM('EDl log'!T15) -> 0.27589467 | G13: =-tanks!AW17 -> 141.5 | H13: =tanks!AV17 -> 0.89 | I13: =('B5'!AU16)*0.51 -> 0 | J13: ='B5'!AX16/0.51 -> 1.5686275 | K13: =WATER!I17 -> 63 | L13: =SUM(WATER!J17) -> 3.8402458 | M13: =WATER!Q17 -> 0 | N13: 0.6 | O13: =ELEC!B15 -> 0
A14: Beirut | B14: =B13+1 -> 13 | C14: 1 | D14: 2023 | E14: =ELEC!N16 -> 0 | F14: =SUM('EDl log'!T16) -> 0 | G14: =-tanks!AW18 -> 0 | H14: =tanks!AV18 -> 0.89 | I14: =('B5'!AU17)*0.51 -> 0 | J14: ='B5'!AX17/0.51 -> 1.5686275 | K14: =WATER!I18 -> 0 | L14: =SUM(WATER!J18) -> 0 | M14: =WATER!Q18 -> 0 | N14: 0.6 | O14: =ELEC!B16 -> 0
... A32: Beirut | B32: =B31+1 -> 31 | C32: 1 | D32: 2023 | E32: =ELEC!N34 -> 0 | F32: =SUM('EDl log'!T34) -> 0 | G32: =-tanks!AW36 -> 0 | H32: =tanks!AV36 -> 0.915 | I32: =('B5'!AU35)*0.51 -> 0 | J32: ='B5'!AX35/0.51 -> 1.5686275 | K32: =WATER!I36 -> 0 | L32: =SUM(WATER!J36) -> 0 | M32: =WATER!Q36 -> 0 | N32: 0.6 | O32: =ELEC!B34 -> 0

Sheet Submetering
A1: Site Name | B1: Day | C1: Month | D1: Year | E1: ATS1 Kwh | F1: ATS2 Kwh | G1: ATS3 Kwh | H1: ATS4 Kwh | I1: ATS5 Kwh | J1: Guest (m3) | K1: Kitchen & Laundry (m3) | L1: Room Nights
A2: Beirut | B2: 1 | C2: 1 | D2: 2023 | E2: =ELEC!M4 -> 0 | F2: =ELEC!K4 -> 0 | G2: =ELEC!I4 -> 0 | H2: =ELEC!E4 -> 0 | I2: =ELEC!G4 -> 0 | J2: =WATER!Y6 -> 0 | K2: =WATER!AJ6 -> 0 | L2: =ELEC!B4 -> 0
A3: Beirut | B3: =B2+1 -> 2 | C3: 1 | D3: 2023 | E3: =ELEC!M5 -> 0 | F3: =ELEC!K5 -> 0 | G3: =ELEC!I5 -> 0 | H3: =ELEC!E5 -> 0 | I3: =ELEC!G5 -> 0 | J3: =WATER!Y7 -> 0 | K3: =WATER!AJ7 -> 0 | L3: =ELEC!B5 -> 0
A4: Beirut | B4: =B3+1 -> 3 | C4: 1 | D4: 2023 | E4: =ELEC!M6 -> 598 | F4: =ELEC!K6 -> 756 | G4: =ELEC!I6 -> 352 | H4: =ELEC!E6 -> 500 | I4: =ELEC!G6 -> 258 | J4: =WATER!Y8 -> 0 | K4: =WATER!AJ8 -> 0 | L4: =ELEC!B6 -> 0
A5: Beirut | B5: =B4+1 -> 4 | C5: 1 | D5: 2023 | E5: =ELEC!M7 -> 834 | F5: =ELEC!K7 -> 760 | G5: =ELEC!I7 -> 360 | H5: =ELEC!E7 -> 520 | I5: =ELEC!G7 -> 289 | J5: =WATER!Y9 -> 0 | K5: =WATER!AJ9 -> 0 | L5: =ELEC!B7 -> 0
A6: Beirut | B6: =B5+1 -> 5 | C6: 1 | D6: 2023 | E6: =ELEC!M8 -> 584 | F6: =ELEC!K8 -> 760 | G6: =ELEC!I8 -> 272 | H6: =ELEC!E8 -> 460 | I6: =ELEC!G8 -> 223 | J6: =WATER!Y10 -> 0 | K6: =WATER!AJ10 -> 0 | L6: =ELEC!B8 -> 0
A7: Beirut | B7: =B6+1 -> 6 | C7: 1 | D7: 2023 | E7: =ELEC!M9 -> 0 | F7: =ELEC!K9 -> 0 | G7: =ELEC!I9 -> 0 | H7: =ELEC!E9 -> 0 | I7: =ELEC!G9 -> 0 | J7: =WATER!Y11 -> 0 | K7: =WATER!AJ11 -> 0 | L7: =ELEC!B9 -> 0
A8: Beirut | B8: =B7+1 -> 7 | C8: 1 | D8: 2023 | E8: =ELEC!M10 -> 0 | F8: =ELEC!K10 -> 0 | G8: =ELEC!I10 -> 0 | H8: =ELEC!E10 -> 0 | I8: =ELEC!G10 -> 0 | J8: =WATER!Y12 -> 0 | K8: =WATER!AJ12 -> 0 | L8: =ELEC!B10 -> 0
A9: Beirut | B9: =B8+1 -> 8 | C9: 1 | D9: 2023 | E9: =ELEC!M11 -> 632 | F9: =ELEC!K11 -> 668 | G9: =ELEC!I11 -> 308 | H9: =ELEC!E11 -> 470 | I9: =ELEC!G11 -> 252 | J9: =WATER!Y13 -> 0 | K9: =WATER!AJ13 -> 0 | L9: =ELEC!B11 -> 0
A10: Beirut | B10: =B9+1 -> 9 | C10: 1 | D10: 2023 | E10: =ELEC!M12 -> 888 | F10: =ELEC!K12 -> 804 | G10: =ELEC!I12 -> 394 | H10: =ELEC!E12 -> 610 | I10: =ELEC!G12 -> 368 | J10: =WATER!Y14 -> 0 | K10: =WATER!AJ14 -> 0 | L10: =ELEC!B12 -> 0
A11: Beirut | B11: =B10+1 -> 10 | C11: 1 | D11: 2023 | E11: =ELEC!M13 -> 816 | F11: =ELEC!K13 -> 752 | G11: =ELEC!I13 -> 364 | H11: =ELEC!E13 -> 620 | I11: =ELEC!G13 -> 356 | J11: =WATER!Y15 -> 0 | K11: =WATER!AJ15 -> 0 | L11: =ELEC!B13 -> 0
A12: Beirut | B12: =B11+1 -> 11 | C12: 1 | D12: 2023 | E12: =ELEC!M14 -> 482 | F12: =ELEC!K14 -> 464 | G12: =ELEC!I14 -> 238 | H12: =ELEC!E14 -> 420 | I12: =ELEC!G14 -> 235 | J12: =WATER!Y16 -> 0 | K12: =WATER!AJ16 -> 0 | L12: =ELEC!B14 -> 0
A13: Beirut | B13: =B12+1 -> 12 | C13: 1 | D13: 2023 | E13: =ELEC!M15 -> 1220 | F13: =ELEC!K15 -> 1342 | G13: =ELEC!I15 -> 683 | H13: =ELEC!E15 -> 810 | I13: =ELEC!G15 -> 497 | J13: =WATER!Y17 -> 0 | K13: =WATER!AJ17 -> 0 | L13: =ELEC!B15 -> 0
A14: Beirut | B14: =B13+1 -> 13 | C14: 1 | D14: 2023 | E14: =ELEC!M16 -> 0 | F14: =ELEC!K16 -> 0 | G14: =ELEC!I16 -> 0 | H14: =ELEC!E16 -> 0 | I14: =ELEC!G16 -> 0 | J14: =WATER!Y18 -> 0 | K14: =WATER!AJ18 -> 0 | L14: =ELEC!B16 -> 0
... A32: Beirut | B32: =B31+1 -> 31 | C32: 1 | D32: 2023 | E32: =ELEC!M34 -> 0 | F32: =ELEC!K34 -> 0 | G32: =ELEC!I34 -> 0 | H32: =ELEC!E34 -> 0 | I32: =ELEC!G34 -> 0 | J32: =WATER!Y36 -> 0 | K32: =WATER!AJ36 -> 0 | L32: =ELEC!B34 -> 0
D45: .

Sheet ELEC
A2: OOC | B2: Room OCC | D2: MDB3 | E2: MDB3/day | F2: EMDB2 | G2: EMDB2/day | H2: EMDB1 | I2: EMDB1/day | J2: MDB2 | K2: mdb2/day | L2: MDB1 | M2: MDB1/Day | N2: Total KWH | O2: KWH/Rooc | P2: Gen MHW | Q2: Gen/Day KWH | R2: EDL KWH | S2: CH1 RH | T2: RH | U2: C1h1 power | V2: CH1 Con KWH | W2: CH2 RH | X2: RH | Y2: Ch2 power | Z2: CH2 Con KWH | AA2: CH3 RH | AB2: RH | AC2: Ch3 power | AD2: CH3 Con KWH | AE2: RH total | AF2: KWH total | AG2: AVG chiller KW/Hr
A3: =[1]ELEC!$A$34 -> 0 | B3: =[1]ELEC!$B$34 -> 0 | C3: 44926 | D3: 420100 | E3: 0 | F3: 4189432 | G3: 0 | H3: 18106834 | I3: 0 | J3: 29896978 | K3: 0 | L3: 24716266 | M3: 0 | N3: =[2]ELEC!N33 -> 3572 | O3: =[2]ELEC!O33 -> 0 | P3: 19706.333 | Q3: 0 | R3: 0 | S3: =[2]ELEC!S33 -> 10175 | T3: =[2]ELEC!T33 -> 0 | U3: =[2]ELEC!U33 -> 429166 | V3: =[2]ELEC!V33 -> 0 | W3: 33500 | X3: =[2]ELEC!X33 -> 0 | Y3: 1000643 | Z3: =[2]ELEC!Z33 -> 0 | AA3: 36804 | AB3: =[2]ELEC!AB33 -> 0 | AC3: 1173391 | AD3: =[2]ELEC!AD33 -> 0 | AE3: =[2]ELEC!AE33 -> 0 | AF3: =[2]ELEC!AF33 -> 0 | AG3: =[2]ELEC!AG33 -> 0
A4: ='General information '!F5 -> 0 | B4: =SUM(230*A4) -> 0 | C4: =C3+1 -> 44927 | D4: 420100 | E4: =D4-D3 -> 0 | F4: 4189432 | G4: =F4-F3 -> 0 | H4: 18106834 | I4: =H4-H3 -> 0 | J4: 29896978 | K4: =J4-J3 -> 0 | L4: 24716266 | M4: =L4-L3 -> 0 | N4: =M4+K4+I4+G4+E4 -> 0 | O4: =IF(B4>0,N4/B4,0) -> 0 | P4: 19706.333 | Q4: =(P4-P3)*1000 -> 0 | R4: =+N4-Q4 -> 0 | S4: =S3 -> 10175 | T4: =S4-S3 -> 0 | U4: =U3 -> 429166 | V4: =U4-U3 -> 0 | W4: 33500 | X4: =W4-W3 -> 0 | Y4: 1000643 | Z4: =Y4-Y3 -> 0 | AA4: =AA3 -> 36804 | AB4: =AA4-AA3 -> 0 | AC4: =AC3 -> 1173391 | AD4: =AC4-AC3 -> 0 | AE4: =AB4+X4+T4 -> 0 | AF4: =V4+Z4+AD4 -> 0 | AG4: =IF(AE4>0,AF4/AE4,0) -> 0
A5: ='General information '!F6 -> 0 | B5: =SUM(230*A5) -> 0 | C5: =C4+1 -> 44928 | D5: =D4 -> 420100 | E5: =D5-D4 -> 0 | F5: 4189432 | G5: =F5-F4 -> 0 | H5: =H4 -> 18106834 | I5: =H5-H4 -> 0 | J5: =J4 -> 29896978 | K5: =J5-J4 -> 0 | L5: =L4 -> 24716266 | M5: =L5-L4 -> 0 | N5: =M5+K5+I5+G5+E5 -> 0 | O5: =IF(B5>0,N5/B5,0) -> 0 | P5: =P4 -> 19706.333 | Q5: =(P5-P4)*1000 -> 0 | R5: =+N5-Q5 -> 0 | S5: =S4 -> 10175 | T5: =S5-S4 -> 0 | U5: =U4 -> 429166 | V5: =U5-U4 -> 0 | W5: 33500 | X5: =W5-W4 -> 0 | Y5: 1000644 | Z5: =Y5-Y4 -> 1 | AA5: =AA4 -> 36804 | AB5: =AA5-AA4 -> 0 | AC5: =AC4 -> 1173391 | AD5: =AC5-AC4 -> 0 | AE5: =AB5+X5+T5 -> 0 | AF5: =V5+Z5+AD5 -> 1 | AG5: =IF(AE5>0,AF5/AE5,0) -> 0
A6: ='General information '!F7 -> 0 | B6: =SUM(230*A6) -> 0 | C6: =C5+1 -> 44929 | D6: 420600 | E6: =D6-D5 -> 500 | F6: 4189690 | G6: =F6-F5 -> 258 | H6: 18107186 | I6: =H6-H5 -> 352 | J6: 29897734 | K6: =J6-J5 -> 756 | L6: 24716864 | M6: =L6-L5 -> 598 | N6: =M6+K6+I6+G6+E6 -> 2464 | O6: =IF(B6>0,N6/B6,0) -> 0 | P6: 19709.752 | Q6: =(P6-P5)*1000 -> 3419 | R6: =+N6-Q6 -> -955 | S6: =S5 -> 10175 | T6: =S6-S5 -> 0 | U6: =U5 -> 429166 | V6: =U6-U5 -> 0 | W6: 33500 | X6: =W6-W5 -> 0 | Y6: 1000645 | Z6: =Y6-Y5 -> 1 | AA6: =AA5 -> 36804 | AB6: =AA6-AA5 -> 0 | AC6: =AC5 -> 1173391 | AD6: =AC6-AC5 -> 0 | AE6: =AB6+X6+T6 -> 0 | AF6: =V6+Z6+AD6 -> 1 | AG6: =IF(AE6>0,AF6/AE6,0) -> 0
A7: ='General information '!F8 -> 0 | B7: =SUM(230*A7) -> 0 | C7: =C6+1 -> 44930 | D7: 421120 | E7: =D7-D6 -> 520 | F7: 4189979 | G7: =F7-F6 -> 289 | H7: 18107546 | I7: =H7-H6 -> 360 | J7: 29898494 | K7: =J7-J6 -> 760 | L7: 24717698 | M7: =L7-L6 -> 834 | N7: =M7+K7+I7+G7+E7 -> 2763 | O7: =IF(B7>0,N7/B7,0) -> 0 | P7: 19712.489 | Q7: =(P7-P6)*1000 -> 2737 | R7: =+N7-Q7 -> 26 | S7: =S6 -> 10175 | T7: =S7-S6 -> 0 | U7: =U6 -> 429166 | V7: =U7-U6 -> 0 | W7: 33500 | X7: =W7-W6 -> 0 | Y7: 1000646 | Z7: =Y7-Y6 -> 1 | AA7: =AA6 -> 36804 | AB7: =AA7-AA6 -> 0 | AC7: =AC6 -> 1173391 | AD7: =AC7-AC6 -> 0 | AE7: =AB7+X7+T7 -> 0 | AF7: =V7+Z7+AD7 -> 1 | AG7: =IF(AE7>0,AF7/AE7,0) -> 0
A8: ='General information '!F9 -> 0 | B8: =SUM(230*A8) -> 0 | C8: =C7+1 -> 44931 | D8: 421580 | E8: =D8-D7 -> 460 | F8: 4190202 | G8: =F8-F7 -> 223 | H8: 18107818 | I8: =H8-H7 -> 272 | J8: 29899254 | K8: =J8-J7 -> 760 | L8: 24718282 | M8: =L8-L7 -> 584 | N8: =M8+K8+I8+G8+E8 -> 2299 | O8: =IF(B8>0,N8/B8,0) -> 0 | P8: 19714.831 | Q8: =(P8-P7)*1000 -> 2342 | R8: =+N8-Q8 -> -43 | S8: =S7 -> 10175 | T8: =S8-S7 -> 0 | U8: =U7 -> 429166 | V8: =U8-U7 -> 0 | W8: 33500 | X8: =W8-W7 -> 0 | Y8: 1000647 | Z8: =Y8-Y7 -> 1 | AA8: =AA7 -> 36804 | AB8: =AA8-AA7 -> 0 | AC8: =AC7 -> 1173391 | AD8: =AC8-AC7 -> 0 | AE8: =AB8+X8+T8 -> 0 | AF8: =V8+Z8+AD8 -> 1 | AG8: =IF(AE8>0,AF8/AE8,0) -> 0
A9: ='General information '!F10 -> 0 | B9: =SUM(230*A9) -> 0 | C9: =C8+1 -> 44932 | D9: 421580 | E9: =D9-D8 -> 0 | F9: =F8 -> 4190202 | G9: =F9-F8 -> 0 | H9: =H8 -> 18107818 | I9: =H9-H8 -> 0 | J9: =J8 -> 29899254 | K9: =J9-J8 -> 0 | L9: =L8 -> 24718282 | M9: =L9-L8 -> 0 | N9: =M9+K9+I9+G9+E9 -> 0 | O9: =IF(B9>0,N9/B9,0) -> 0 | P9: =P8 -> 19714.831 | Q9: =(P9-P8)*1000 -> 0 | R9: =+N9-Q9 -> 0 | S9: =S8 -> 10175 | T9: =S9-S8 -> 0 | U9: =U8 -> 429166 | V9: =U9-U8 -> 0 | W9: 33500 | X9: =W9-W8 -> 0 | Y9: 1000648 | Z9: =Y9-Y8 -> 1 | AA9: =AA8 -> 36804 | AB9: =AA9-AA8 -> 0 | AC9: =AC8 -> 1173391 | AD9: =AC9-AC8 -> 0 | AE9: =AB9+X9+T9 -> 0 | AF9: =V9+Z9+AD9 -> 1 | AG9: =IF(AE9>0,AF9/AE9,0) -> 0
A10: ='General information '!F11 -> 0 | B10: =SUM(230*A10) -> 0 | C10: =C9+1 -> 44933 | D10: =D9 -> 421580 | E10: =D10-D9 -> 0 | F10: =F9 -> 4190202 | G10: =F10-F9 -> 0 | H10: =H9 -> 18107818 | I10: =H10-H9 -> 0 | J10: =J9 -> 29899254 | K10: =J10-J9 -> 0 | L10: =L9 -> 24718282 | M10: =L10-L9 -> 0 | N10: =M10+K10+I10+G10+E10 -> 0 | O10: =IF(B10>0,N10/B10,0) -> 0 | P10: =P9 -> 19714.831 | Q10: =(P10-P9)*1000 -> 0 | R10: =+N10-Q10 -> 0 | S10: =S9 -> 10175 | T10: =S10-S9 -> 0 | U10: =U9 -> 429166 | V10: =U10-U9 -> 0 | W10: 33500 | X10: =W10-W9 -> 0 | Y10: 1000649 | Z10: =Y10-Y9 -> 1 | AA10: =AA9 -> 36804 | AB10: =AA10-AA9 -> 0 | AC10: =AC9 -> 1173391 | AD10: =AC10-AC9 -> 0 | AE10: =AB10+X10+T10 -> 0 | AF10: =V10+Z10+AD10 -> 1 | AG10: =IF(AE10>0,AF10/AE10,0) -> 0
A11: ='General information '!F12 -> 0 | B11: =SUM(230*A11) -> 0 | C11: =C10+1 -> 44934 | D11: 422050 | E11: =D11-D10 -> 470 | F11: 4190454 | G11: =F11-F10 -> 252 | H11: 18108126 | I11: =H11-H10 -> 308 | J11: 29899922 | K11: =J11-J10 -> 668 | L11: 24718914 | M11: =L11-L10 -> 632 | N11: =M11+K11+I11+G11+E11 -> 2330 | O11: =IF(B11>0,N11/B11,0) -> 0 | P11: 19717.193 | Q11: =(P11-P10)*1000 -> 2362 | R11: =N11-Q11 -> -32 | S11: =S10 -> 10175 | T11: =S11-S10 -> 0 | U11: =U10 -> 429166 | V11: =U11-U10 -> 0 | W11: 33501 | X11: =W11-W10 -> 1 | Y11: 1000894 | Z11: =Y11-Y10 -> 245 | AA11: =AA10 -> 36804 | AB11: =AA11-AA10 -> 0 | AC11: =AC10 -> 1173391 | AD11: =AC11-AC10 -> 0 | AE11: =AB11+X11+T11 -> 1 | AF11: =V11+Z11+AD11 -> 245 | AG11: =IF(AE11>0,AF11/AE11,0) -> 245
A12: ='General information '!F13 -> 0 | B12: =SUM(230*A12) -> 0 | C12: =C11+1 -> 44935 | D12: 422660 | E12: =D12-D11 -> 610 | F12: 4190822 | G12: =F12-F11 -> 368 | H12: 18108520 | I12: =H12-H11 -> 394 | J12: 29900726 | K12: =J12-J11 -> 804 | L12: 24719802 | M12: =L12-L11 -> 888 | N12: =M12+K12+I12+G12+E12 -> 3064 | O12: =IF(B12>0,N12/B12,0) -> 0 | P12: 19720.326 | Q12: =(P12-P11)*1000 -> 3133 | R12: =N12-Q12 -> -69 | S12: =S11 -> 10175 | T12: =S12-S11 -> 0 | U12: =U11 -> 429166 | V12: =U12-U11 -> 0 | W12: =W11 -> 33501 | X12: =W12-W11 -> 0 | Y12: =Y11 -> 1000894 | Z12: =Y12-Y11 -> 0 | AA12: =AA11 -> 36804 | AB12: =AA12-AA11 -> 0 | AC12: =AC11 -> 1173391 | AD12: =AC12-AC11 -> 0 | AE12: =AB12+X12+T12 -> 0 | AF12: =V12+Z12+AD12 -> 0 | AG12: =IF(AE12>0,AF12/AE12,0) -> 0
A13: ='General information '!F14 -> 0 | B13: =SUM(230*A13) -> 0 | C13: =C12+1 -> 44936 | D13: 423280 | E13: =D13-D12 -> 620 | F13: 4191178 | G13: =F13-F12 -> 356 | H13: 18108884 | I13: =H13-H12 -> 364 | J13: 29901478 | K13: =J13-J12 -> 752 | L13: 24720618 | M13: =L13-L12 -> 816 | N13: =M13+K13+I13+G13+E13 -> 2908 | O13: =IF(B13>0,N13/B13,0) -> 0 | P13: 19723.284 | Q13: =(P13-P12)*1000 -> 2958 | R13: =N13-Q13 -> -50 | S13: =S12 -> 10175 | T13: =S13-S12 -> 0 | U13: =U12 -> 429166 | V13: =U13-U12 -> 0 | W13: =W12 -> 33501 | X13: =W13-W12 -> 0 | Y13: =Y12 -> 1000894 | Z13: =Y13-Y12 -> 0 | AA13: =AA12 -> 36804 | AB13: =AA13-AA12 -> 0 | AC13: =AC12 -> 1173391 | AD13: =AC13-AC12 -> 0 | AE13: =AB13+X13+T13 -> 0 | AF13: =V13+Z13+AD13 -> 0 | AG13: =IF(AE13>0,AF13/AE13,0) -> 0
A14: ='General information '!F15 -> 0 | B14: =SUM(230*A14) -> 0 | C14: =C13+1 -> 44937 | D14: 423700 | E14: =D14-D13 -> 420 | F14: 4191413 | G14: =F14-F13 -> 235 | H14: 18109122 | I14: =H14-H13 -> 238 | J14: 29901942 | K14: =J14-J13 -> 464 | L14: 24721100 | M14: =L14-L13 -> 482 | N14: =M14+K14+I14+G14+E14 -> 1839 | O14: =IF(B14>0,N14/B14,0) -> 0 | P14: 19724.741 | Q14: =(P14-P13)*1000 -> 1457 | R14: =N14-Q14 -> 382 | S14: =S13 -> 10175 | T14: =S14-S13 -> 0 | U14: =U13 -> 429166 | V14: =U14-U13 -> 0 | W14: =W13 -> 33501 | X14: =W14-W13 -> 0 | Y14: =Y13 -> 1000894 | Z14: =Y14-Y13 -> 0 | AA14: =AA13 -> 36804 | AB14: =AA14-AA13 -> 0 | AC14: =AC13 -> 1173391 | AD14: =AC14-AC13 -> 0 | AE14: =AB14+X14+T14 -> 0 | AF14: =V14+Z14+AD14 -> 0 | AG14: =IF(AE14>0,AF14/AE14,0) -> 0
A15: ='General information '!F16 -> 0 | B15: =SUM(230*A15) -> 0 | C15: =C14+1 -> 44938 | D15: 424510 | E15: =D15-D14 -> 810 | F15: 4191910 | G15: =F15-F14 -> 497 | H15: 18109805 | I15: =H15-H14 -> 683 | J15: 29903284 | K15: =J15-J14 -> 1342 | L15: 24722320 | M15: =L15-L14 -> 1220 | N15: =M15+K15+I15+G15+E15 -> 4552 | O15: =IF(B15>0,N15/B15,0) -> 0 | P15: 19727.982 | Q15: =(P15-P14)*1000 -> 3241 | R15: =N15-Q15 -> 1311 | S15: =S14 -> 10175 | T15: =S15-S14 -> 0 | U15: =U14 -> 429166 | V15: =U15-U14 -> 0 | W15: =W14 -> 33501 | X15: =W15-W14 -> 0 | Y15: =Y14 -> 1000894 | Z15: =Y15-Y14 -> 0 | AA15: =AA14 -> 36804 | AB15: =AA15-AA14 -> 0 | AC15: =AC14 -> 1173391 | AD15: =AC15-AC14 -> 0 | AE15: =AB15+X15+T15 -> 0 | AF15: =V15+Z15+AD15 -> 0 | AG15: =IF(AE15>0,AF15/AE15,0) -> 0
A16: ='General information '!F17 -> 0 | B16: =SUM(230*A16) -> 0 | C16: =C15+1 -> 44939 | D16: =D15 -> 424510 | E16: =D16-D15 -> 0 | F16: =F15 -> 4191910 | G16: =F16-F15 -> 0 | H16: =H15 -> 18109805 | I16: =H16-H15 -> 0 | J16: =J15 -> 29903284 | K16: =J16-J15 -> 0 | L16: =L15 -> 24722320 | M16: =L16-L15 -> 0 | N16: =M16+K16+I16+G16+E16 -> 0 | O16: =IF(B16>0,N16/B16,0) -> 0 | P16: =P15 -> 19727.982 | Q16: =(P16-P15)*1000 -> 0 | R16: =N16-Q16 -> 0 | S16: =S15 -> 10175 | T16: =S16-S15 -> 0 | U16: =U15 -> 429166 | V16: =U16-U15 -> 0 | W16: =W15 -> 33501 | X16: =W16-W15 -> 0 | Y16: =Y15 -> 1000894 | Z16: =Y16-Y15 -> 0 | AA16: =AA15 -> 36804 | AB16: =AA16-AA15 -> 0 | AC16: =AC15 -> 1173391 | AD16: =AC16-AC15 -> 0 | AE16: =AB16+X16+T16 -> 0 | AF16: =V16+Z16+AD16 -> 0 | AG16: =IF(AE16>0,AF16/AE16,0) -> 0
A17: ='General information '!F18 -> 0 | B17: =SUM(230*A17) -> 0 | C17: =C16+1 -> 44940 | D17: =D16 -> 424510 | E17: =D17-D16 -> 0 | F17: =F16 -> 4191910 | G17: =F17-F16 -> 0 | H17: =H16 -> 18109805 | I17: =H17-H16 -> 0 | J17: =J16 -> 29903284 | K17: =J17-J16 -> 0 | L17: =L16 -> 24722320 | M17: =L17-L16 -> 0 | N17: =M17+K17+I17+G17+E17 -> 0 | O17: =IF(B17>0,N17/B17,0) -> 0 | P17: =P16 -> 19727.982 | Q17: =(P17-P16)*1000 -> 0 | R17: =N17-Q17 -> 0 | S17: =S16 -> 10175 | T17: =S17-S16 -> 0 | U17: =U16 -> 429166 | V17: =U17-U16 -> 0 | W17: =W16 -> 33501 | X17: =W17-W16 -> 0 | Y17: =Y16 -> 1000894 | Z17: =Y17-Y16 -> 0 | AA17: =AA16 -> 36804 | AB17: =AA17-AA16 -> 0 | AC17: =AC16 -> 1173391 | AD17: =AC17-AC16 -> 0 | AE17: =AB17+X17+T17 -> 0 | AF17: =V17+Z17+AD17 -> 0 | AG17: =IF(AE17>0,AF17/AE17,0) -> 0
A18: ='General information '!F19 -> 0 | B18: =SUM(230*A18) -> 0 | C18: =C17+1 -> 44941 | D18: 425910 | E18: =D18-D17 -> 1400 | F18: 4192142 | G18: =F18-F17 -> 232 | H18: 18110010 | I18: =H18-H17 -> 205 | J18: 29903642 | K18: =J18-J17 -> 358 | L18: 24722772 | M18: =L18-L17 -> 452 | N18: =M18+K18+I18+G18+E18 -> 2647 | O18: =IF(B18>0,N18/B18,0) -> 0 | P18: 19732.078 | Q18: =(P18-P17)*1000 -> 4096 | R18: =N18-Q18 -> -1449 | S18: =S17 -> 10175 | T18: =S18-S17 -> 0 | U18: =U17 -> 429166 | V18: =U18-U17 -> 0 | W18: =W17 -> 33501 | X18: =W18-W17 -> 0 | Y18: =Y17 -> 1000894 | Z18: =Y18-Y17 -> 0 | AA18: =AA17 -> 36804 | AB18: =AA18-AA17 -> 0 | AC18: =AC17 -> 1173391 | AD18: =AC18-AC17 -> 0 | AE18: =AB18+X18+T18 -> 0 | AF18: =V18+Z18+AD18 -> 0 | AG18: =IF(AE18>0,AF18/AE18,0) -> 0
A19: ='General information '!F20 -> 0 | B19: =SUM(230*A19) -> 0 | C19: =C18+1 -> 44942 | D19: 427040 | E19: =D19-D18 -> 1130 | F19: 4192454 | G19: =F19-F18 -> 312 | H19: 18110434 | I19: =H19-H18 -> 424 | J19: 29904400 | K19: =J19-J18 -> 758 | L19: 24723458 | M19: =L19-L18 -> 686 | N19: =M19+K19+I19+G19+E19 -> 3310 | O19: =IF(B19>0,N19/B19,0) -> 0 | P19: 19735.41 | Q19: =(P19-P18)*1000 -> 3332 | R19: =N19-Q19 -> -22 | S19: =S18 -> 10175 | T19: =S19-S18 -> 0 | U19: =U18 -> 429166 | V19: =U19-U18 -> 0 | W19: 33502 | X19: =W19-W18 -> 1 | Y19: 1001172 | Z19: =Y19-Y18 -> 278 | AA19: =AA18 -> 36804 | AB19: =AA19-AA18 -> 0 | AC19: =AC18 -> 1173391 | AD19: =AC19-AC18 -> 0 | AE19: =AB19+X19+T19 -> 1 | AF19: =V19+Z19+AD19 -> 278 | AG19: =IF(AE19>0,AF19/AE19,0) -> 278
A20: ='General information '!F21 -> 0 | B20: =SUM(230*A20) -> 0 | C20: =C19+1 -> 44943 | D20: 427980 | E20: =D20-D19 -> 940 | F20: 4192751 | G20: =F20-F19 -> 297 | H20: 18110854 | I20: =H20-H19 -> 420 | J20: 29905286 | K20: =J20-J19 -> 886 | L20: 24724194 | M20: =L20-L19 -> 736 | N20: =M20+K20+I20+G20+E20 -> 3279 | O20: =IF(B20>0,N20/B20,0) -> 0 | P20: 19738.583 | Q20: =(P20-P19)*1000 -> 3173 | R20: =N20-Q20 -> 106 | S20: =S19 -> 10175 | T20: =S20-S19 -> 0 | U20: =U19 -> 429166 | V20: =U20-U19 -> 0 | W20: =W19 -> 33502 | X20: =W20-W19 -> 0 | Y20: =Y19 -> 1001172 | Z20: =Y20-Y19 -> 0 | AA20: =AA19 -> 36804 | AB20: =AA20-AA19 -> 0 | AC20: =AC19 -> 1173391 | AD20: =AC20-AC19 -> 0 | AE20: =AB20+X20+T20 -> 0 | AF20: =V20+Z20+AD20 -> 0 | AG20: =IF(AE20>0,AF20/AE20,0) -> 0
A21: ='General information '!F22 -> 0 | B21: =SUM(230*A21) -> 0 | C21: =C20+1 -> 44944 | D21: 428980 | E21: =D21-D20 -> 1000 | F21: 4193101 | G21: =F21-F20 -> 350 | H21: 18111312 | I21: =H21-H20 -> 458 | J21: 29906106 | K21: =J21-J20 -> 820 | L21: 24725070 | M21: =L21-L20 -> 876 | N21: =M21+K21+I21+G21+E21 -> 3504 | O21: =IF(B21>0,N21/B21,0) -> 0 | P21: 19742.163 | Q21: =(P21-P20)*1000 -> 3580 | R21: =N21-Q21 -> -76 | S21: =S20 -> 10175 | T21: =S21-S20 -> 0 | U21: =U20 -> 429166 | V21: =U21-U20 -> 0 | W21: =W20 -> 33502 | X21: =W21-W20 -> 0 | Y21: =Y20 -> 1001172 | Z21: =Y21-Y20 -> 0 | AA21: =AA20 -> 36804 | AB21: =AA21-AA20 -> 0 | AC21: =AC20 -> 1173391 | AD21: =AC21-AC20 -> 0 | AE21: =AB21+X21+T21 -> 0 | AF21: =V21+Z21+AD21 -> 0 | AG21: =IF(AE21>0,AF21/AE21,0) -> 0
A22: ='General information '!F23 -> 0 | B22: =SUM(230*A22) -> 0 | C22: =C21+1 -> 44945 | D22: 429890 | E22: =D22-D21 -> 910 | F22: 4193384 | G22: =F22-F21 -> 283 | H22: 18111716 | I22: =H22-H21 -> 404 | J22: 29906942 | K22: =J22-J21 -> 836 | L22: 24725866 | M22: =L22-L21 -> 796 | N22: =M22+K22+I22+G22+E22 -> 3229 | O22: =IF(B22>0,N22/B22,0) -> 0 | P22: 19745.453 | Q22: =(P22-P21)*1000 -> 3290 | R22: =N22-Q22 -> -61 | S22: =S21 -> 10175 | T22: =S22-S21 -> 0 | U22: =U21 -> 429166 | V22: =U22-U21 -> 0 | W22: =W21 -> 33502 | X22: =W22-W21 -> 0 | Y22: 1001280 | Z22: =Y22-Y21 -> 108 | AA22: =AA21 -> 36804 | AB22: =AA22-AA21 -> 0 | AC22: =AC21 -> 1173391 | AD22: =AC22-AC21 -> 0 | AE22: =AB22+X22+T22 -> 0 | AF22: =V22+Z22+AD22 -> 108 | AG22: =IF(AE22>0,AF22/AE22,0) -> 0
A23: ='General information '!F24 -> 0 | B23: =SUM(230*A23) -> 0 | C23: =C22+1 -> 44946 | D23: =D22 -> 429890 | E23: =D23-D22 -> 0 | F23: =F22 -> 4193384 | G23: =F23-F22 -> 0 | H23: =H22 -> 18111716 | I23: =H23-H22 -> 0 | J23: =J22 -> 29906942 | K23: =J23-J22 -> 0 | L23: =L22 -> 24725866 | M23: =L23-L22 -> 0 | N23: =M23+K23+I23+G23+E23 -> 0 | O23: =IF(B23>0,N23/B23,0) -> 0 | P23: =P22 -> 19745.453 | Q23: =(P23-P22)*1000 -> 0 | R23: =N23-Q23 -> 0 | S23: =S22 -> 10175 | T23: =S23-S22 -> 0 | U23: =U22 -> 429166 | V23: =U23-U22 -> 0 | W23: =W22 -> 33502 | X23: =W23-W22 -> 0 | Y23: =Y22 -> 1001280 | Z23: =Y23-Y22 -> 0 | AA23: =AA22 -> 36804 | AB23: =AA23-AA22 -> 0 | AC23: =AC22 -> 1173391 | AD23: =AC23-AC22 -> 0 | AE23: =AB23+X23+T23 -> 0 | AF23: =V23+Z23+AD23 -> 0 | AG23: =IF(AE23>0,AF23/AE23,0) -> 0
A24: ='General information '!F25 -> 0 | B24: =SUM(230*A24) -> 0 | C24: =C23+1 -> 44947 | D24: =D23 -> 429890 | E24: =D24-D23 -> 0 | F24: =F23 -> 4193384 | G24: =F24-F23 -> 0 | H24: =H23 -> 18111716 | I24: =H24-H23 -> 0 | J24: =J23 -> 29906942 | K24: =J24-J23 -> 0 | L24: =L23 -> 24725866 | M24: =L24-L23 -> 0 | N24: =M24+K24+I24+G24+E24 -> 0 | O24: =IF(B24>0,N24/B24,0) -> 0 | P24: =P23 -> 19745.453 | Q24: =(P24-P23)*1000 -> 0 | R24: =N24-Q24 -> 0 | S24: =S23 -> 10175 | T24: =S24-S23 -> 0 | U24: =U23 -> 429166 | V24: =U24-U23 -> 0 | W24: =W23 -> 33502 | X24: =W24-W23 -> 0 | Y24: =Y23 -> 1001280 | Z24: =Y24-Y23 -> 0 | AA24: =AA23 -> 36804 | AB24: =AA24-AA23 -> 0 | AC24: =AC23 -> 1173391 | AD24: =AC24-AC23 -> 0 | AE24: =AB24+X24+T24 -> 0 | AF24: =V24+Z24+AD24 -> 0 | AG24: =IF(AE24>0,AF24/AE24,0) -> 0
A25: ='General information '!F26 -> 0 | B25: =SUM(230*A25) -> 0 | C25: =C24+1 -> 44948 | D25: 430650 | E25: =D25-D24 -> 760 | F25: 4193678 | G25: =F25-F24 -> 294 | H25: 18112122 | I25: =H25-H24 -> 406 | J25: 29907566 | K25: =J25-J24 -> 624 | L25: 24726676 | M25: =L25-L24 -> 810 | N25: =M25+K25+I25+G25+E25 -> 2894 | O25: =IF(B25>0,N25/B25,0) -> 0 | P25: 19748.401 | Q25: =(P25-P24)*1000 -> 2948 | R25: =N25-Q25 -> -54 | S25: =S24 -> 10175 | T25: =S25-S24 -> 0 | U25: =U24 -> 429166 | V25: =U25-U24 -> 0 | W25: =W24 -> 33502 | X25: =W25-W24 -> 0 | Y25: =Y24 -> 1001280 | Z25: =Y25-Y24 -> 0 | AA25: =AA24 -> 36804 | AB25: =AA25-AA24 -> 0 | AC25: =AC24 -> 1173391 | AD25: =AC25-AC24 -> 0 | AE25: =AB25+X25+T25 -> 0 | AF25: =V25+Z25+AD25 -> 0 | AG25: =IF(AE25>0,AF25/AE25,0) -> 0
A26: ='General information '!F27 -> 0 | B26: =SUM(230*A26) -> 0 | C26: =C25+1 -> 44949 | D26: 431200 | E26: =D26-D25 -> 550 | F26: 4193958 | G26: =F26-F25 -> 280 | H26: 18112502 | I26: =H26-H25 -> 380 | J26: 29908118 | K26: =J26-J25 -> 552 | L26: 24727406 | M26: =L26-L25 -> 730 | N26: =M26+K26+I26+G26+E26 -> 2492 | O26: =IF(B26>0,N26/B26,0) -> 0 | P26: 19750.903 | Q26: =(P26-P25)*1000 -> 2502 | R26: =N26-Q26 -> -10 | S26: =S25 -> 10175 | T26: =S26-S25 -> 0 | U26: =U25 -> 429166 | V26: =U26-U25 -> 0 | W26: =W25 -> 33502 | X26: =W26-W25 -> 0 | Y26: =Y25 -> 1001280 | Z26: =Y26-Y25 -> 0 | AA26: =AA25 -> 36804 | AB26: =AA26-AA25 -> 0 | AC26: =AC25 -> 1173391 | AD26: =AC26-AC25 -> 0 | AE26: =AB26+X26+T26 -> 0 | AF26: =V26+Z26+AD26 -> 0 | AG26: =IF(AE26>0,AF26/AE26,0) -> 0
A27: ='General information '!F28 -> 0 | B27: =SUM(230*A27) -> 0 | C27: =C26+1 -> 44950 | D27: 431600 | E27: =D27-D26 -> 400 | F27: 4194199 | G27: =F27-F26 -> 241 | H27: 18112840 | I27: =H27-H26 -> 338 | J27: 29908570 | K27: =J27-J26 -> 452 | L27: 24727928 | M27: =L27-L26 -> 522 | N27: =M27+K27+I27+G27+E27 -> 1953 | O27: =IF(B27>0,N27/B27,0) -> 0 | P27: 19752.78 | Q27: =(P27-P26)*1000 -> 1877 | R27: =N27-Q27 -> 76 | S27: =S26 -> 10175 | T27: =S27-S26 -> 0 | U27: =U26 -> 429166 | V27: =U27-U26 -> 0 | W27: =W26 -> 33502 | X27: =W27-W26 -> 0 | Y27: =Y26 -> 1001280 | Z27: =Y27-Y26 -> 0 | AA27: =AA26 -> 36804 | AB27: =AA27-AA26 -> 0 | AC27: =AC26 -> 1173391 | AD27: =AC27-AC26 -> 0 | AE27: =AB27+X27+T27 -> 0 | AF27: =V27+Z27+AD27 -> 0 | AG27: =IF(AE27>0,AF27/AE27,0) -> 0
A28: ='General information '!F29 -> 0 | B28: =SUM(230*A28) -> 0 | C28: =C27+1 -> 44951 | D28: 432050 | E28: =D28-D27 -> 450 | F28: 4194483 | G28: =F28-F27 -> 284 | H28: 18113216 | I28: =H28-H27 -> 376 | J28: 29909148 | K28: =J28-J27 -> 578 | L28: 24728634 | M28: =L28-L27 -> 706 | N28: =M28+K28+I28+G28+E28 -> 2394 | O28: =IF(B28>0,N28/B28,0) -> 0 | P28: 19755.154 | Q28: =(P28-P27)*1000 -> 2374 | R28: =N28-Q28 -> 20 | S28: =S27 -> 10175 | T28: =S28-S27 -> 0 | U28: =U27 -> 429166 | V28: =U28-U27 -> 0 | W28: =W27 -> 33502 | X28: =W28-W27 -> 0 | Y28: =Y27 -> 1001280 | Z28: =Y28-Y27 -> 0 | AA28: =AA27 -> 36804 | AB28: =AA28-AA27 -> 0 | AC28: =AC27 -> 1173391 | AD28: =AC28-AC27 -> 0 | AE28: =AB28+X28+T28 -> 0 | AF28: =V28+Z28+AD28 -> 0 | AG28: =IF(AE28>0,AF28/AE28,0) -> 0
A29: ='General information '!F30 -> 0 | B29: =SUM(230*A29) -> 0 | C29: =C28+1 -> 44952 | D29: 432550 | E29: =D29-D28 -> 500 | F29: 4194779.6 | G29: =F29-F28 -> 296.6 | H29: 18113612 | I29: =H29-H28 -> 396 | J29: 29909784 | K29: =J29-J28 -> 636 | L29: 24729294 | M29: =L29-L28 -> 660 | N29: =M29+K29+I29+G29+E29 -> 2488.6 | O29: =IF(B29>0,N29/B29,0) -> 0 | P29: 19757.699 | Q29: =(P29-P28)*1000 -> 2545 | R29: =N29-Q29 -> -56.4 | S29: =S28 -> 10175 | T29: =S29-S28 -> 0 | U29: =U28 -> 429166 | V29: =U29-U28 -> 0 | W29: =W28 -> 33502 | X29: =W29-W28 -> 0 | Y29: =Y28 -> 1001280 | Z29: =Y29-Y28 -> 0 | AA29: =AA28 -> 36804 | AB29: =AA29-AA28 -> 0 | AC29: =AC28 -> 1173391 | AD29: =AC29-AC28 -> 0 | AE29: =AB29+X29+T29 -> 0 | AF29: =V29+Z29+AD29 -> 0 | AG29: =IF(AE29>0,AF29/AE29,0) -> 0
A30: ='General information '!F31 -> 0 | B30: =SUM(230*A30) -> 0 | C30: =C29+1 -> 44953 | D30: =D29 -> 432550 | E30: =D30-D29 -> 0 | F30: =F29 -> 4194779.6 | G30: =F30-F29 -> 0 | H30: =H29 -> 18113612 | I30: =H30-H29 -> 0 | J30: =J29 -> 29909784 | K30: =J30-J29 -> 0 | L30: =L29 -> 24729294 | M30: =L30-L29 -> 0 | N30: =M30+K30+I30+G30+E30 -> 0 | O30: =IF(B30>0,N30/B30,0) -> 0 | P30: =P29 -> 19757.699 | Q30: =(P30-P29)*1000 -> 0 | R30: =N30-Q30 -> 0 | S30: =S29 -> 10175 | T30: =S30-S29 -> 0 | U30: =U29 -> 429166 | V30: =U30-U29 -> 0 | W30: =W29 -> 33502 | X30: =W30-W29 -> 0 | Y30: =Y29 -> 1001280 | Z30: =Y30-Y29 -> 0 | AA30: =AA29 -> 36804 | AB30: =AA30-AA29 -> 0 | AC30: =AC29 -> 1173391 | AD30: =AC30-AC29 -> 0 | AE30: =AB30+X30+T30 -> 0 | AF30: =V30+Z30+AD30 -> 0 | AG30: =IF(AE30>0,AF30/AE30,0) -> 0
A31: ='General information '!F32 -> 0 | B31: =SUM(230*A31) -> 0 | C31: =C30+1 -> 44954 | D31: =D30 -> 432550 | E31: =D31-D30 -> 0 | F31: =F30 -> 4194779.6 | G31: =F31-F30 -> 0 | H31: =H30 -> 18113612 | I31: =H31-H30 -> 0 | J31: =J30 -> 29909784 | K31: =J31-J30 -> 0 | L31: =L30 -> 24729294 | M31: =L31-L30 -> 0 | N31: =M31+K31+I31+G31+E31 -> 0 | O31: =IF(B31>0,N31/B31,0) -> 0 | P31: =P30 -> 19757.699 | Q31: =(P31-P30)*1000 -> 0 | R31: =N31-Q31 -> 0 | S31: =S30 -> 10175 | T31: =S31-S30 -> 0 | U31: =U30 -> 429166 | V31: =U31-U30 -> 0 | W31: =W30 -> 33502 | X31: =W31-W30 -> 0 | Y31: =Y30 -> 1001280 | Z31: =Y31-Y30 -> 0 | AA31: =AA30 -> 36804 | AB31: =AA31-AA30 -> 0 | AC31: =AC30 -> 1173391 | AD31: =AC31-AC30 -> 0 | AE31: =AB31+X31+T31 -> 0 | AF31: =V31+Z31+AD31 -> 0 | AG31: =IF(AE31>0,AF31/AE31,0) -> 0
A32: ='General information '!F33 -> 0 | B32: =SUM(230*A32) -> 0 | C32: =C31+1 -> 44955 | D32: 433080 | E32: =D32-D31 -> 530 | F32: 4195088.4 | G32: =F32-F31 -> 308.8 | H32: 18114030 | I32: =H32-H31 -> 418 | J32: 29910482 | K32: =J32-J31 -> 698 | L32: 24730010 | M32: =L32-L31 -> 716 | N32: =M32+K32+I32+G32+E32 -> 2670.8 | O32: =IF(B32>0,N32/B32,0) -> 0 | P32: 19760.427 | Q32: =(P32-P31)*1000 -> 2728 | R32: =N32-Q32 -> -57.2 | S32: =S31 -> 10175 | T32: =S32-S31 -> 0 | U32: =U31 -> 429166 | V32: =U32-U31 -> 0 | W32: =W31 -> 33502 | X32: =W32-W31 -> 0 | Y32: =Y31 -> 1001280 | Z32: =Y32-Y31 -> 0 | AA32: =AA31 -> 36804 | AB32: =AA32-AA31 -> 0 | AC32: =AC31 -> 1173391 | AD32: =AC32-AC31 -> 0 | AE32: =AB32+X32+T32 -> 0 | AF32: =V32+Z32+AD32 -> 0 | AG32: =IF(AE32>0,AF32/AE32,0) -> 0
A33: ='General information '!F34 -> 0 | B33: =SUM(230*A33) -> 0 | C33: =C32+1 -> 44956 | D33: 434550 | E33: =D33-D32 -> 1470 | F33: 4195506 | G33: =F33-F32 -> 417.6 | H33: 18114450 | I33: =H33-H32 -> 420 | J33: 29911174 | K33: =J33-J32 -> 692 | L33: 24730782 | M33: =L33-L32 -> 772 | N33: =M33+K33+I33+G33+E33 -> 3771.6 | O33: =IF(B33>0,N33/B33,0) -> 0 | P33: 19763.9 | Q33: =(P33-P32)*1000 -> 3473 | R33: =N33-Q33 -> 298.6 | S33: =S32 -> 10175 | T33: =S33-S32 -> 0 | U33: =U32 -> 429166 | V33: =U33-U32 -> 0 | W33: =W32 -> 33502 | X33: =W33-W32 -> 0 | Y33: 1001284 | Z33: =Y33-Y32 -> 4 | AA33: =AA32 -> 36804 | AB33: =AA33-AA32 -> 0 | AC33: =AC32 -> 1173391 | AD33: =AC33-AC32 -> 0 | AE33: =AB33+X33+T33 -> 0 | AF33: =V33+Z33+AD33 -> 4 | AG33: =IF(AE33>0,AF33/AE33,0) -> 0
A34: ='General information '!F35 -> 0 | B34: =SUM(230*A34) -> 0 | C34: =C33+1 -> 44957 | D34: =D33 -> 434550 | E34: =D34-D33 -> 0 | F34: =F33 -> 4195506 | G34: =F34-F33 -> 0 | H34: =H33 -> 18114450 | I34: =H34-H33 -> 0 | J34: =J33 -> 29911174 | K34: =J34-J33 -> 0 | L34: =L33 -> 24730782 | M34: =L34-L33 -> 0 | N34: =M34+K34+I34+G34+E34 -> 0 | O34: =IF(B34>0,N34/B34,0) -> 0 | P34: =P33 -> 19763.9 | Q34: =(P34-P33)*1000 -> 0 | R34: =N34-Q34 -> 0 | S34: =S33 -> 10175 | T34: =S34-S33 -> 0 | U34: =U33 -> 429166 | V34: =U34-U33 -> 0 | W34: =W33 -> 33502 | X34: =W34-W33 -> 0 | Y34: =Y33 -> 1001284 | Z34: =Y34-Y33 -> 0 | AA34: =AA33 -> 36804 | AB34: =AA34-AA33 -> 0 | AC34: =AC33 -> 1173391 | AD34: =AC34-AC33 -> 0 | AE34: =AB34+X34+T34 -> 0 | AF34: =V34+Z34+AD34 -> 0 | AG34: =IF(AE34>0,AF34/AE34,0) -> 0

Sheet B5
F1: Boiler A | J1: =J36 -> 57.708333 | K1: Boiler B | P1: Boiler C | V1: Boiler | X1: SteamA | AC1: SteamB | AH1: Steam | AI1: Boiler & steam | AL1: Total Boiler Runing H | AM1: Total Steam Runing H | AN1: GAS1 % | AO1: GAS1/L | AP1: GAS2% | AQ1: Gas2/L | AR1: GAS3% | AS1: GAS3/L | AU1: Gas Cons | AV1: Delivery | AW1: Cost/L
B2: Level Tank Gen | C2: Level tank Boiler | D2: Daily Cons Bo. | E2: Boiler litter | F2: Boiler A | G2: Run Hr a | H2: Boiler A fuel | I2: Daily consumption | J2: AVG | K2: index Run H | L2: Run Hrb | M2: Boiler B Fuel | O2: Daily consumption | P2: Boiler C | S2: Run C | U2: Total RH | V2: Total Fuel | X2: SteamA | Y2: Run SA | Z2: Steam A Conter | AA2: Liters | AC2: SteamB | AD2: Run SteamB | AE2: Steam B Conter | AF2: SB Litters | AG2: Avg | AH2: Total Fuel | AI2: Total Fuel
S3: 0
A4: 44926 | B4: 218 | C4: 224 | D4: 0 | E4: 0 | F4: 2361 | G4: =[2]B5!G34 -> 0 | H4: 52474 | I4: =[2]B5!I34 -> 0 | J4: =[2]B5!J34 -> 0 | K4: 2482 | L4: 0 | M4: 185022 | N4: 0 | O4: =[2]B5!O34 -> 1869 | P4: 2240 | Q4: 187109 | R4: =[2]B5!R34 -> 0 | S4: =[2]B5!S34 -> 0 | T4: =[2]B5!T34 -> 0 | U4: 0 | V4: 0 | W4: =[2]B5!W34 -> 0 | X4: 2498 | Y4: =[2]B5!Y34 -> 0 | Z4: =[2]B5!Z34 -> 141419 | AA4: =[2]B5!AA34 -> 0 | AB4: =[2]B5!AB34 -> 0 | AC4: 1959 | AD4: =[2]B5!AD34 -> 0 | AE4: 367689 | AF4: =[2]B5!AF34 -> 0 | AG4: =[2]B5!AG34 -> 0 | AH4: =[2]B5!AH34 -> 0 | AI4: 0 | AJ4: 0 | AK4: =[2]B5!AK34 -> 0 | AL4: 0 | AM4: =[2]B5!AM34 -> 0 | AN4: =[2]B5!AN34 -> 65 | AO4: =[2]B5!AO34 -> 1950 | AP4: =[2]B5!AP34 -> 35 | AQ4: =[2]B5!AQ34 -> 1050 | AR4: =[2]B5!AR34 -> 73 | AS4: =[2]B5!AS34 -> 2190 | AT4: =[2]B5!AT34 -> 5190 | ... AX4: =[2]B5!AX34 -> 0.8
A5: 44927 | B5: =B4 -> 218 | C5: 224 | D5: =C4-C5 -> 0 | E5: =D5*8.38 -> 0 | F5: =F4 -> 2361 | G5: =F5-F4 -> 0 | H5: =H4 -> 52474 | I5: =SUM(H5-H4) -> 0 | J5: 1 | K5: 2482 | L5: =K5-K4 -> 0 | M5: 185022 | N5: =M5-M4 -> 0 | O5: =O4 -> 1869 | P5: =P4 -> 2240 | Q5: =Q4 -> 187109 | R5: =Q5-Q4 -> 0 | S5: =SUM(P5-P4) -> 0 | T5: =SUM(S5*$T$2) -> 0 | U5: =SUM(G5+L5+S5) -> 0 | V5: =R5+N5+I5:I5 -> 0 | W5: =SUM(V5/U5) -> #DIV/0! | X5: =X4 -> 2498 | Y5: =X5-X4 -> 0 | Z5: =Z4 -> 141419 | AA5: =Z5-Z4 -> 0 | AB5: =SUM(Y5*$AB$2) -> 0 | AC5: 1959 | AD5: =AC5-AC4 -> 0 | AE5: 367689 | AF5: =AE5-AE4 -> 0 | AG5: =IF(AD5>0,AF5/AD5,0) -> 0 | AH5: =AF5+AA5 -> 0 | AI5: =SUM(AH5+V5) -> 0 | AJ5: =-tanks!AW6 -> 0 | AK5: =SUM(AJ5-AI5) -> 0 | AL5: =S5+L5+G5 -> 0 | AM5: =Y5+AD5 -> 0 | AN5: =AN4 -> 65 | AO5: =(AN5/100)*3000 -> 1950 | AP5: =AP4 -> 35 | AQ5: =(AP5/100)*3000 -> 1050 | AR5: =AR4 -> 73 | AS5: =(AR5/100)*3000 -> 2190 | AT5: =SUM(AO5+AQ5+AS5) -> 5190 | AU5: =AT4-AT5+AV5 -> 0 | AX5: =IF(AV5>0,AW5,AX4) -> 0.8
A6: 44928 | B6: 218 | C6: 224 | D6: =C5-C6 -> 0 | E6: =D6*8.38 -> 0 | F6: =F5 -> 2361 | G6: =F6-F5 -> 0 | H6: =H5 -> 52474 | I6: =SUM(H6-H5) -> 0 | J6: =IF(G6>0,I6/G6,0) -> 0 | K6: 2482 | L6: =K6-K5 -> 0 | M6: =M5 -> 185022 | N6: =M6-M5 -> 0 | O6: =O5 -> 1869 | P6: =P5 -> 2240 | Q6: =Q5 -> 187109 | R6: =Q6-Q5 -> 0 | S6: =SUM(P6-P5) -> 0 | T6: =SUM(S6*$T$2) -> 0 | U6: =SUM(G6+L6+S6) -> 0 | V6: =R6+N6+I6:I6 -> 0 | W6: =SUM(V6/U6) -> #DIV/0! | X6: =X5 -> 2498 | Y6: =X6-X5 -> 0 | Z6: =Z5 -> 141419 | AA6: =Z6-Z5 -> 0 | AB6: =SUM(Y6*$AB$2) -> 0 | AC6: 1959 | AD6: =AC6-AC5 -> 0 | AE6: =AE5 -> 367689 | AF6: =AE6-AE5 -> 0 | AG6: =IF(AD6>0,AF6/AD6,0) -> 0 | AH6: =AF6+AA6 -> 0 | AI6: =SUM(AH6+V6) -> 0 | AJ6: =-tanks!AW7 -> 0 | AK6: =SUM(AJ6-AI6) -> 0 | AL6: =S6+L6+G6 -> 0 | AM6: =Y6+AD6 -> 0 | AN6: =AN5 -> 65 | AO6: =(AN6/100)*3000 -> 1950 | AP6: =AP5 -> 35 | AQ6: =(AP6/100)*3000 -> 1050 | AR6: =AR5 -> 73 | AS6: =(AR6/100)*3000 -> 2190 | AT6: =SUM(AO6+AQ6+AS6) -> 5190 | AU6: =AT5-AT6+AV6 -> 0 | AX6: =IF(AV6>0,AW6,AX5) -> 0.8
A7: 44929 | B7: 214 | C7: 221 | D7: =C6-C7 -> 3 | E7: =D7*8.38 -> 25.14 | F7: =F6 -> 2361 | G7: =F7-F6 -> 0 | H7: 52558 | I7: =SUM(H7-H6) -> 84 | J7: =IF(G7>0,I7/G7,0) -> 0 | K7: 2482 | L7: =K7-K6 -> 0 | M7: =M6 -> 185022 | N7: =M7-M6 -> 0 | O7: =O6 -> 1869 | P7: =P6 -> 2240 | Q7: =Q6 -> 187109 | R7: =Q7-Q6 -> 0 | S7: =SUM(P7-P6) -> 0 | T7: =SUM(S7*$T$2) -> 0 | U7: =SUM(G7+L7+S7) -> 0 | V7: =R7+N7+I7:I7 -> 84 | W7: =SUM(V7/U7) -> #DIV/0! | X7: =X6 -> 2498 | Y7: =X7-X6 -> 0 | Z7: =Z6 -> 141419 | AA7: =Z7-Z6 -> 0 | AB7: =SUM(Y7*$AB$2) -> 0 | AC7: =AC6 -> 1959 | AD7: =AC7-AC6 -> 0 | AE7: =AE6 -> 367689 | AF7: =AE7-AE6 -> 0 | AG7: =IF(AD7>0,AF7/AD7,0) -> 0 | AH7: =AF7+AA7 -> 0 | AI7: =SUM(AH7+V7) -> 84 | AJ7: =-tanks!AW8 -> 84 | AK7: =SUM(AJ7-AI7) -> 0 | AL7: =S7+L7+G7 -> 0 | AM7: =Y7+AD7 -> 0 | AN7: =AN6 -> 65 | AO7: =(AN7/100)*3000 -> 1950 | AP7: =AP6 -> 35 | AQ7: =(AP7/100)*3000 -> 1050 | AR7: =AR6 -> 73 | AS7: =(AR7/100)*3000 -> 2190 | AT7: =SUM(AO7+AQ7+AS7) -> 5190 | AU7: =AT6-AT7+AV7 -> 0 | AX7: =IF(AV7>0,AW7,AX6) -> 0.8
A8: 44930 | B8: 239 | C8: 242 | D8: =C7-C8 -> -21 | E8: =D8*8.38 -> -175.98 | F8: 2365 | G8: =F8-F7 -> 4 | H8: 52754 | I8: =SUM(H8-H7) -> 196 | J8: =IF(G8>0,I8/G8,0) -> 49 | K8: 2482 | L8: =K8-K7 -> 0 | M8: 185032 | N8: =M8-M7 -> 10 | O8: =O7 -> 1869 | P8: =P7 -> 2240 | Q8: =Q7 -> 187109 | R8: =Q8-Q7 -> 0 | S8: =SUM(P8-P7) -> 0 | T8: =SUM(S8*$T$2) -> 0 | U8: =SUM(G8+L8+S8) -> 4 | V8: =R8+N8+I8:I8 -> 206 | W8: =SUM(V8/U8) -> 51.5 | X8: =X7 -> 2498 | Y8: =X8-X7 -> 0 | Z8: =Z7 -> 141419 | AA8: =Z8-Z7 -> 0 | AB8: =SUM(Y8*$AB$2) -> 0 | AC8: 1960 | AD8: =AC8-AC7 -> 1 | AE8: 367780 | AF8: =AE8-AE7 -> 91 | AG8: =IF(AD8>0,AF8/AD8,0) -> 91 | AH8: =AF8+AA8 -> 91 | AI8: =SUM(AH8+V8) -> 297 | AJ8: =-tanks!AW9 -> 297 | AK8: =SUM(AJ8-AI8) -> 0 | AL8: =S8+L8+G8 -> 4 | AM8: =Y8+AD8 -> 1 | AN8: =AN7 -> 65 | AO8: =(AN8/100)*3000 -> 1950 | AP8: =AP7 -> 35 | AQ8: =(AP8/100)*3000 -> 1050 | AR8: =AR7 -> 73 | AS8: =(AR8/100)*3000 -> 2190 | AT8: =SUM(AO8+AQ8+AS8) -> 5190 | AU8: =AT7-AT8+AV8 -> 0 | AX8: =IF(AV8>0,AW8,AX7) -> 0.8
A9: 44931 | B9: 236 | C9: 239 | D9: =C8-C9 -> 3 | E9: =D9*8.38 -> 25.14 | F9: 2366 | G9: =F9-F8 -> 1 | H9: 52811 | I9: =SUM(H9-H8) -> 57 | J9: =IF(G9>0,I9/G9,0) -> 57 | K9: 2483 | L9: =K9-K8 -> 1 | M9: 185088 | N9: =M9-M8 -> 56 | O9: =O8 -> 1869 | P9: =P8 -> 2240 | Q9: =Q8 -> 187109 | R9: =Q9-Q8 -> 0 | S9: =SUM(P9-P8) -> 0 | T9: =SUM(S9*$T$2) -> 0 | U9: =SUM(G9+L9+S9) -> 2 | V9: =R9+N9+I9:I9 -> 113 | W9: =SUM(V9/U9) -> 56.5 | X9: =X8 -> 2498 | Y9: =X9-X8 -> 0 | Z9: =Z8 -> 141419 | AA9: =Z9-Z8 -> 0 | AB9: =SUM(Y9*$AB$2) -> 0 | AC9: =AC8 -> 1960 | AD9: =AC9-AC8 -> 0 | AE9: =AE8 -> 367780 | AF9: =AE9-AE8 -> 0 | AG9: =IF(AD9>0,AF9/AD9,0) -> 0 | AH9: =AF9+AA9 -> 0 | AI9: =SUM(AH9+V9) -> 113 | AJ9: =-tanks!AW10 -> 113 | AK9: =SUM(AJ9-AI9) -> 0 | AL9: =S9+L9+G9 -> 2 | AM9: =Y9+AD9 -> 0 | AN9: =AN8 -> 65 | AO9: =(AN9/100)*3000 -> 1950 | AP9: =AP8 -> 35 | AQ9: =(AP9/100)*3000 -> 1050 | AR9: =AR8 -> 73 | AS9: =(AR9/100)*3000 -> 2190 | AT9: =SUM(AO9+AQ9+AS9) -> 5190 | AU9: =AT8-AT9+AV9 -> 0 | AX9: =IF(AV9>0,AW9,AX8) -> 0.8
A10: 44932 | B10: 233 | C10: 239 | D10: =C9-C10 -> 0 | E10: =D10*8.38 -> 0 | F10: 2366 | G10: =F10-F9 -> 0 | H10: 52811 | I10: =SUM(H10-H9) -> 0 | J10: =IF(G10>0,I10/G10,0) -> 0 | K10: 2483 | L10: =K10-K9 -> 0 | M10: 185088 | N10: =M10-M9 -> 0 | O10: =O9 -> 1869 | P10: =P9 -> 2240 | Q10: =Q9 -> 187109 | R10: =Q10-Q9 -> 0 | S10: =SUM(P10-P9) -> 0 | T10: =SUM(S10*$T$2) -> 0 | U10: =SUM(G10+L10+S10) -> 0 | V10: =R10+N10+I10:I10 -> 0 | W10: =SUM(V10/U10) -> #DIV/0! | X10: =X9 -> 2498 | Y10: =X10-X9 -> 0 | Z10: =Z9 -> 141419 | AA10: =Z10-Z9 -> 0 | AB10: =SUM(Y10*$AB$2) -> 0 | AC10: =AC9 -> 1960 | AD10: =AC10-AC9 -> 0 | AE10: =AE9 -> 367780 | AF10: =AE10-AE9 -> 0 | AG10: =IF(AD10>0,AF10/AD10,0) -> 0 | AH10: =AF10+AA10 -> 0 | AI10: =SUM(AH10+V10) -> 0 | AJ10: =-tanks!AW11 -> 0 | AK10: =SUM(AJ10-AI10) -> 0 | AL10: =S10+L10+G10 -> 0 | AM10: =Y10+AD10 -> 0 | AN10: =AN9 -> 65 | AO10: =(AN10/100)*3000 -> 1950 | AP10: =AP9 -> 35 | AQ10: =(AP10/100)*3000 -> 1050 | AR10: =AR9 -> 73 | AS10: =(AR10/100)*3000 -> 2190 | AT10: =SUM(AO10+AQ10+AS10) -> 5190 | AU10: =AT9-AT10+AV10 -> 0 | AX10: =IF(AV10>0,AW10,AX9) -> 0.8
A11: 44933 | B11: 233 | C11: 239 | D11: =C10-C11 -> 0 | E11: =D11*8.38 -> 0 | F11: =F10 -> 2366 | G11: =F11-F10 -> 0 | H11: =H10 -> 52811 | I11: =SUM(H11-H10) -> 0 | J11: =IF(G11>0,I11/G11,0) -> 0 | K11: =K10 -> 2483 | L11: =K11-K10 -> 0 | M11: =M10 -> 185088 | N11: =M11-M10 -> 0 | O11: =O10 -> 1869 | P11: =P10 -> 2240 | Q11: =Q10 -> 187109 | R11: =Q11-Q10 -> 0 | S11: =SUM(P11-P10) -> 0 | T11: =SUM(S11*$T$2) -> 0 | U11: =SUM(G11+L11+S11) -> 0 | V11: =R11+N11+I11:I11 -> 0 | W11: =SUM(V11/U11) -> #DIV/0! | X11: =X10 -> 2498 | Y11: =X11-X10 -> 0 | Z11: =Z10 -> 141419 | AA11: =Z11-Z10 -> 0 | AB11: =SUM(Y11*$AB$2) -> 0 | AC11: =AC10 -> 1960 | AD11: =AC11-AC10 -> 0 | AE11: =AE10 -> 367780 | AF11: =AE11-AE10 -> 0 | AG11: =IF(AD11>0,AF11/AD11,0) -> 0 | AH11: =AF11+AA11 -> 0 | AI11: =SUM(AH11+V11) -> 0 | AJ11: =-tanks!AW12 -> 0 | AK11: =SUM(AJ11-AI11) -> 0 | AL11: =S11+L11+G11 -> 0 | AM11: =Y11+AD11 -> 0 | AN11: 65 | AO11: =(AN11/100)*3000 -> 1950 | AP11: 35 | AQ11: =(AP11/100)*3000 -> 1050 | AR11: =AR10 -> 73 | AS11: =(AR11/100)*3000 -> 2190 | AT11: =SUM(AO11+AQ11+AS11) -> 5190 | AU11: =AT10-AT11+AV11 -> 0 | AX11: =IF(AV11>0,AW11,AX10) -> 0.8
A12: 44934 | B12: 230 | C12: 236 | D12: =C11-C12 -> 3 | E12: =D12*8.38 -> 25.14 | F12: 2368 | G12: =F12-F11 -> 2 | H12: 52991 | I12: =SUM(H12-H11) -> 180 | J12: =IF(G12>0,I12/G12,0) -> 90 | K12: =K11 -> 2483 | L12: =K12-K11 -> 0 | M12: =M11 -> 185088 | N12: =M12-M11 -> 0 | O12: =O11 -> 1869 | P12: =P11 -> 2240 | Q12: =Q11 -> 187109 | R12: =Q12-Q11 -> 0 | S12: =SUM(P12-P11) -> 0 | T12: =SUM(S12*$T$2) -> 0 | U12: =SUM(G12+L12+S12) -> 2 | V12: =R12+N12+I12:I12 -> 180 | W12: =SUM(V12/U12) -> 90 | X12: =X11 -> 2498 | Y12: =X12-X11 -> 0 | Z12: =Z11 -> 141419 | AA12: =Z12-Z11 -> 0 | AB12: =SUM(Y12*$AB$2) -> 0 | AC12: =AC11 -> 1960 | AD12: =AC12-AC11 -> 0 | AE12: =AE11 -> 367780 | AF12: =AE12-AE11 -> 0 | AG12: =IF(AD12>0,AF12/AD12,0) -> 0 | AH12: =AF12+AA12 -> 0 | AI12: =SUM(AH12+V12) -> 180 | AJ12: =-tanks!AW13 -> 180 | AK12: =SUM(AJ12-AI12) -> 0 | AL12: =S12+L12+G12 -> 2 | AM12: =Y12+AD12 -> 0 | AN12: =AN11 -> 65 | AO12: =(AN12/100)*3000 -> 1950 | AP12: =AP11 -> 35 | AQ12: =(AP12/100)*3000 -> 1050 | AR12: =AR11 -> 73 | AS12: =(AR12/100)*3000 -> 2190 | AT12: =SUM(AO12+AQ12+AS12) -> 5190 | AU12: =AT11-AT12+AV12 -> 0 | AX12: =IF(AV12>0,AW12,AX11) -> 0.8
A13: 44935 | B13: 228 | C13: 234 | D13: =C12-C13 -> 2 | E13: =D13*8.38 -> 16.76 | F13: =F12 -> 2368 | G13: =F13-F12 -> 0 | H13: =H12 -> 52991 | I13: =SUM(H13-H12) -> 0 | J13: =IF(G13>0,I13/G13,0) -> 0 | K13: =K12 -> 2483 | L13: =K13-K12 -> 0 | M13: =M12 -> 185088 | N13: =M13-M12 -> 0 | O13: =O12 -> 1869 | P13: 2242 | Q13: 187316 | R13: =Q13-Q12 -> 207 | S13: =SUM(P13-P12) -> 2 | T13: =SUM(S13*$T$2) -> 0 | U13: =SUM(G13+L13+S13) -> 2 | V13: =R13+N13+I13:I13 -> 207 | W13: =SUM(V13/U13) -> 103.5 | X13: =X12 -> 2498 | Y13: =X13-X12 -> 0 | Z13: =Z12 -> 141419 | AA13: =Z13-Z12 -> 0 | AB13: =SUM(Y13*$AB$2) -> 0 | AC13: 1961 | AD13: =AC13-AC12 -> 1 | AE13: 367849.5 | AF13: =AE13-AE12 -> 69.5 | AG13: =IF(AD13>0,AF13/AD13,0) -> 69.5 | AH13: =AF13+AA13 -> 69.5 | AI13: =SUM(AH13+V13) -> 276.5 | AJ13: =-tanks!AW14 -> 276.5 | AK13: =SUM(AJ13-AI13) -> 0 | AL13: =S13+L13+G13 -> 2 | AM13: =Y13+AD13 -> 1 | AN13: =AN12 -> 65 | AO13: =(AN13/100)*3000 -> 1950 | AP13: =AP12 -> 35 | AQ13: =(AP13/100)*3000 -> 1050 | AR13: =AR12 -> 73 | AS13: =(AR13/100)*3000 -> 2190 | AT13: =SUM(AO13+AQ13+AS13) -> 5190 | AU13: =AT12-AT13+AV13 -> 0 | AX13: =IF(AV13>0,AW13,AX12) -> 0.8
A14: 44936 | B14: 225 | C14: 231 | D14: =C13-C14 -> 3 | E14: =D14*8.38 -> 25.14 | F14: =F13 -> 2368 | G14: =F14-F13 -> 0 | H14: =H13 -> 52991 | I14: =SUM(H14-H13) -> 0 | J14: =IF(G14>0,I14/G14,0) -> 0 | K14: =K13 -> 2483 | L14: =K14-K13 -> 0 | M14: =M13 -> 185088 | N14: =M14-M13 -> 0 | O14: =O13 -> 1869 | P14: 2243 | Q14: 187383 | R14: =Q14-Q13 -> 67 | S14: =SUM(P14-P13) -> 1 | T14: =SUM(S14*$T$2) -> 0 | U14: =SUM(G14+L14+S14) -> 1 | V14: =R14+N14+I14:I14 -> 67 | W14: =SUM(V14/U14) -> 67 | X14: =X13 -> 2498 | Y14: =X14-X13 -> 0 | Z14: =Z13 -> 141419 | AA14: =Z14-Z13 -> 0 | AB14: =SUM(Y14*$AB$2) -> 0 | AC14: =AC13 -> 1961 | AD14: =AC14-AC13 -> 0 | AE14: =AE13 -> 367849.5 | AF14: =AE14-AE13 -> 0 | AG14: =IF(AD14>0,AF14/AD14,0) -> 0 | AH14: =AF14+AA14 -> 0 | AI14: =SUM(AH14+V14) -> 67 | AJ14: =-tanks!AW15 -> 67 | AK14: =SUM(AJ14-AI14) -> 0 | AL14: =S14+L14+G14 -> 1 | AM14: =Y14+AD14 -> 0 | AN14: =AN13 -> 65 | AO14: =(AN14/100)*3000 -> 1950 | AP14: =AP13 -> 35 | AQ14: =(AP14/100)*3000 -> 1050 | AR14: =AR13 -> 73 | AS14: =(AR14/100)*3000 -> 2190 | AT14: =SUM(AO14+AQ14+AS14) -> 5190 | AU14: =AT13-AT14+AV14 -> 0 | AX14: =IF(AV14>0,AW14,AX13) -> 0.8
A15: 44937 | B15: 222 | C15: 228 | D15: =C14-C15 -> 3 | E15: =D15*8.38 -> 25.14 | F15: =F14 -> 2368 | G15: =F15-F14 -> 0 | H15: =H14 -> 52991 | I15: =SUM(H15-H14) -> 0 | J15: =IF(G15>0,I15/G15,0) -> 0 | K15: =K14 -> 2483 | L15: =K15-K14 -> 0 | M15: =M14 -> 185088 | N15: =M15-M14 -> 0 | O15: =O14 -> 1869 | P15: 2246 | Q15: 187588 | R15: =Q15-Q14 -> 205 | S15: =SUM(P15-P14) -> 3 | T15: =SUM(S15*$T$2) -> 0 | U15: =SUM(G15+L15+S15) -> 3 | V15: =R15+N15+I15:I15 -> 205 | W15: =SUM(V15/U15) -> 68.333333 | X15: =X14 -> 2498 | Y15: =X15-X14 -> 0 | Z15: =Z14 -> 141419 | AA15: =Z15-Z14 -> 0 | AB15: =SUM(Y15*$AB$2) -> 0 | AC15: =AC14 -> 1961 | AD15: =AC15-AC14 -> 0 | AE15: =AE14 -> 367849.5 | AF15: =AE15-AE14 -> 0 | AG15: =IF(AD15>0,AF15/AD15,0) -> 0 | AH15: =AF15+AA15 -> 0 | AI15: =SUM(AH15+V15) -> 205 | AJ15: =-tanks!AW16 -> 205 | AK15: =SUM(AJ15-AI15) -> 0 | AL15: =S15+L15+G15 -> 3 | AM15: =Y15+AD15 -> 0 | AN15: =AN14 -> 65 | AO15: =(AN15/100)*3000 -> 1950 | AP15: =AP14 -> 35 | AQ15: =(AP15/100)*3000 -> 1050 | AR15: =AR14 -> 73 | AS15: =(AR15/100)*3000 -> 2190 | AT15: =SUM(AO15+AQ15+AS15) -> 5190 | AU15: =AT14-AT15+AV15 -> 0 | AX15: =IF(AV15>0,AW15,AX14) -> 0.8
A16: 44938 | B16: 217.5 | C16: 223.5 | D16: =C15-C16 -> 4.5 | E16: =D16*8.38 -> 37.71 | F16: =F15 -> 2368 | G16: =F16-F15 -> 0 | H16: =H15 -> 52991 | I16: =SUM(H16-H15) -> 0 | J16: =IF(G16>0,I16/G16,0) -> 0 | K16: =K15 -> 2483 | L16: =K16-K15 -> 0 | M16: =M15 -> 185088 | N16: =M16-M15 -> 0 | O16: =O15 -> 1869 | P16: 2247 | Q16: 187674 | R16: =Q16-Q15 -> 86 | S16: =SUM(P16-P15) -> 1 | T16: =SUM(S16*$T$2) -> 0 | U16: =SUM(G16+L16+S16) -> 1 | V16: =R16+N16+I16:I16 -> 86 | W16: =SUM(V16/U16) -> 86 | X16: =X15 -> 2498 | Y16: =X16-X15 -> 0 | Z16: =Z15 -> 141419 | AA16: =Z16-Z15 -> 0 | AB16: =SUM(Y16*$AB$2) -> 0 | AC16: 1962 | AD16: =AC16-AC15 -> 1 | AE16: 367905 | AF16: =AE16-AE15 -> 55.5 | AG16: =IF(AD16>0,AF16/AD16,0) -> 55.5 | AH16: =AF16+AA16 -> 55.5 | AI16: =SUM(AH16+V16) -> 141.5 | AJ16: =-tanks!AW17 -> 141.5 | AK16: =SUM(AJ16-AI16) -> 0 | AL16: =S16+L16+G16 -> 1 | AM16: =Y16+AD16 -> 1 | AN16: =AN15 -> 65 | AO16: =(AN16/100)*3000 -> 1950 | AP16: =AP15 -> 35 | AQ16: =(AP16/100)*3000 -> 1050 | AR16: =AR15 -> 73 | AS16: =(AR16/100)*3000 -> 2190 | AT16: =SUM(AO16+AQ16+AS16) -> 5190 | AU16: =AT15-AT16+AV16 -> 0 | AX16: =IF(AV16>0,AW16,AX15) -> 0.8
A17: 44939 | B17: =B16 -> 217.5 | C17: =C16 -> 223.5 | D17: =C16-C17 -> 0 | E17: =D17*8.38 -> 0 | F17: =F16 -> 2368 | G17: =F17-F16 -> 0 | H17: =H16 -> 52991 | I17: =SUM(H17-H16) -> 0 | J17: =IF(G17>0,I17/G17,0) -> 0 | K17: =K16 -> 2483 | L17: =K17-K16 -> 0 | M17: =M16 -> 185088 | N17: =M17-M16 -> 0 | O17: =O16 -> 1869 | P17: =P16 -> 2247 | Q17: =Q16 -> 187674 | R17: =Q17-Q16 -> 0 | S17: =SUM(P17-P16) -> 0 | T17: =SUM(S17*$T$2) -> 0 | U17: =SUM(G17+L17+S17) -> 0 | V17: =R17+N17+I17:I17 -> 0 | X17: =X16 -> 2498 | Y17: =X17-X16 -> 0 | Z17: =Z16 -> 141419 | AA17: =Z17-Z16 -> 0 | AB17: =SUM(Y17*$AB$2) -> 0 | AC17: =AC16 -> 1962 | AD17: =AC17-AC16 -> 0 | AE17: =AE16 -> 367905 | AF17: =AE17-AE16 -> 0 | AG17: =IF(AD17>0,AF17/AD17,0) -> 0 | AH17: =AF17+AA17 -> 0 | AI17: =SUM(AH17+V17) -> 0 | AJ17: =-tanks!AW18 -> 0 | AK17: =SUM(AJ17-AI17) -> 0 | AL17: =S17+L17+G17 -> 0 | AM17: =Y17+AD17 -> 0 | AN17: =AN16 -> 65 | AO17: =(AN17/100)*3000 -> 1950 | AP17: =AP16 -> 35 | AQ17: =(AP17/100)*3000 -> 1050 | AR17: =AR16 -> 73 | AS17: =(AR17/100)*3000 -> 2190 | AT17: =SUM(AO17+AQ17+AS17) -> 5190 | AU17: =AT16-AT17+AV17 -> 0 | AX17: =IF(AV17>0,AW17,AX16) -> 0.8
A18: 44940 | B18: =B17 -> 217.5 | C18: =C17 -> 223.5 | D18: =C17-C18 -> 0 | E18: =D18*8.38 -> 0 | F18: =F17 -> 2368 | G18: =F18-F17 -> 0 | H18: =H17 -> 52991 | I18: =SUM(H18-H17) -> 0 | J18: =IF(G18>0,I18/G18,0) -> 0 | K18: =K17 -> 2483 | L18: =K18-K17 -> 0 | M18: =M17 -> 185088 | N18: =M18-M17 -> 0 | O18: 1869 | P18: =P17 -> 2247 | Q18: =Q17 -> 187674 | R18: =Q18-Q17 -> 0 | S18: =SUM(P18-P17) -> 0 | T18: =SUM(S18*$T$2) -> 0 | U18: =SUM(G18+L18+S18) -> 0 | V18: =R18+N18+I18:I18 -> 0 | X18: =X17 -> 2498 | Y18: =X18-X17 -> 0 | Z18: =Z17 -> 141419 | AA18: =Z18-Z17 -> 0 | AB18: =SUM(Y18*$AB$2) -> 0 | AC18: =AC17 -> 1962 | AD18: =AC18-AC17 -> 0 | AE18: =AE17 -> 367905 | AF18: =AE18-AE17 -> 0 | AG18: =IF(AD18>0,AF18/AD18,0) -> 0 | AH18: =AF18+AA18 -> 0 | AI18: =SUM(AH18+V18) -> 0 | AJ18: =-tanks!AW19 -> 0 | AK18: =SUM(AJ18-AI18) -> 0 | AL18: =S18+L18+G18 -> 0 | AM18: =Y18+AD18 -> 0 | AN18: =AN17 -> 65 | AO18: =(AN18/100)*3000 -> 1950 | AP18: =AP17 -> 35 | AQ18: =(AP18/100)*3000 -> 1050 | AR18: =AR17 -> 73 | AS18: =(AR18/100)*3000 -> 2190 | AT18: =SUM(AO18+AQ18+AS18) -> 5190 | AU18: =AT17-AT18+AV18 -> 0 | AX18: =IF(AV18>0,AW18,AX17) -> 0.8
A19: 44941 | B19: 232 | C19: 239 | D19: =C18-C19 -> -15.5 | E19: =D19*8.38 -> -129.89 | F19: =F18 -> 2368 | G19: =F19-F18 -> 0 | H19: 53005 | I19: =SUM(H19-H18) -> 14 | J19: =IF(G19>0,I19/G19,0) -> 0 | K19: =K18 -> 2483 | L19: =K19-K18 -> 0 | M19: 185088 | N19: =M19-M18 -> 0 | O19: =O18 -> 1869 | P19: 2250 | Q19: 187918 | R19: =Q19-Q18 -> 244 | S19: =SUM(P19-P18) -> 3 | T19: =SUM(S19*$T$2) -> 0 | U19: =SUM(G19+L19+S19) -> 3 | V19: =R19+N19+I19:I19 -> 258 | X19: =X18 -> 2498 | Y19: =X19-X18 -> 0 | Z19: =Z18 -> 141419 | AA19: =Z19-Z18 -> 0 | AB19: =SUM(Y19*$AB$2) -> 0 | AC19: =AC18 -> 1962 | AD19: =AC19-AC18 -> 0 | AE19: =AE18 -> 367905 | AF19: =AE19-AE18 -> 0 | AG19: =IF(AD19>0,AF19/AD19,0) -> 0 | AH19: =AF19+AA19 -> 0 | AI19: =SUM(AH19+V19) -> 258 | AJ19: =-tanks!AW20 -> 258 | AK19: =SUM(AJ19-AI19) -> 0 | AL19: =S19+L19+G19 -> 3 | AM19: =Y19+AD19 -> 0 | AN19: =AN18 -> 65 | AO19: =(AN19/100)*3000 -> 1950 | AP19: =AP18 -> 35 | AQ19: =(AP19/100)*3000 -> 1050 | AR19: =AR18 -> 73 | AS19: =(AR19/100)*3000 -> 2190 | AT19: =SUM(AO19+AQ19+AS19) -> 5190 | AU19: =AT18-AT19+AV19 -> 0 | AX19: =IF(AV19>0,AW19,AX18) -> 0.8
A20: 44942 | B20: 229 | C20: 235 | D20: =C19-C20 -> 4 | E20: =D20*8.38 -> 33.52 | F20: =F19 -> 2368 | G20: =F20-F19 -> 0 | H20: =H19 -> 53005 | I20: =SUM(H20-H19) -> 0 | J20: =IF(G20>0,I20/G20,0) -> 0 | K20: 2484 | L20: =K20-K19 -> 1 | M20: 185203 | N20: =M20-M19 -> 115 | O20: =O19 -> 1869 | P20: =P19 -> 2250 | Q20: =Q19 -> 187918 | R20: =Q20-Q19 -> 0 | S20: =SUM(P20-P19) -> 0 | T20: =SUM(S20*$T$2) -> 0 | U20: =SUM(G20+L20+S20) -> 1 | V20: =R20+N20+I20:I20 -> 115 | X20: =X19 -> 2498 | Y20: =X20-X19 -> 0 | Z20: =Z19 -> 141419 | AA20: =Z20-Z19 -> 0 | AB20: =SUM(Y20*$AB$2) -> 0 | AC20: 1963 | AD20: =AC20-AC19 -> 1 | AE20: 367972 | AF20: =AE20-AE19 -> 67 | AG20: =IF(AD20>0,AF20/AD20,0) -> 67 | AH20: =AF20+AA20 -> 67 | AI20: =SUM(AH20+V20) -> 182 | AJ20: =-tanks!AW21 -> 182 | AK20: =SUM(AJ20-AI20) -> 0 | AL20: =S20+L20+G20 -> 1 | AM20: =Y20+AD20 -> 1 | AN20: =AN19 -> 65 | AO20: =(AN20/100)*3000 -> 1950 | AP20: =AP19 -> 35 | AQ20: =(AP20/100)*3000 -> 1050 | AR20: =AR19 -> 73 | AS20: =(AR20/100)*3000 -> 2190 | AT20: =SUM(AO20+AQ20+AS20) -> 5190 | AU20: =AT19-AT20+AV20 -> 0 | AX20: =IF(AV20>0,AW20,AX19) -> 0.8
A21: 44943 | B21: 224 | C21: 230 | D21: =C20-C21 -> 5 | E21: =D21*8.38 -> 41.9 | F21: =F20 -> 2368 | G21: =F21-F20 -> 0 | H21: =H20 -> 53005 | I21: =SUM(H21-H20) -> 0 | J21: =IF(G21>0,I21/G21,0) -> 0 | K21: 2486 | L21: =K21-K20 -> 2 | M21: 185388 | N21: =M21-M20 -> 185 | O21: =O20 -> 1869 | P21: =P20 -> 2250 | Q21: =Q20 -> 187918 | R21: =Q21-Q20 -> 0 | S21: =SUM(P21-P20) -> 0 | T21: =SUM(S21*$T$2) -> 0 | U21: =SUM(G21+L21+S21) -> 2 | V21: =R21+N21+I21:I21 -> 185 | X21: =X20 -> 2498 | Y21: =X21-X20 -> 0 | Z21: =Z20 -> 141419 | AA21: =Z21-Z20 -> 0 | AB21: =SUM(Y21*$AB$2) -> 0 | AC21: =AC20 -> 1963 | AD21: =AC21-AC20 -> 0 | AE21: =AE20 -> 367972 | AF21: =AE21-AE20 -> 0 | AG21: =IF(AD21>0,AF21/AD21,0) -> 0 | AH21: =AF21+AA21 -> 0 | AI21: =SUM(AH21+V21) -> 185 | AJ21: =-tanks!AW22 -> 185 | AK21: =SUM(AJ21-AI21) -> 0 | AL21: =S21+L21+G21 -> 2 | AM21: =Y21+AD21 -> 0 | AN21: =AN20 -> 65 | AO21: =(AN21/100)*3000 -> 1950 | AP21: =AP20 -> 35 | AQ21: =(AP21/100)*3000 -> 1050 | AR21: =AR20 -> 73 | AS21: =(AR21/100)*3000 -> 2190 | AT21: =SUM(AO21+AQ21+AS21) -> 5190 | AU21: =AT20-AT21+AV21 -> 0 | AX21: =IF(AV21>0,AW21,AX20) -> 0.8
A22: 44944 | B22: 240 | C22: 246 | D22: =C21-C22 -> -16 | E22: =D22*8.38 -> -134.08 | F22: =F21 -> 2368 | G22: =F22-F21 -> 0 | H22: =H21 -> 53005 | I22: =SUM(H22-H21) -> 0 | J22: =IF(G22>0,I22/G22,0) -> 0 | K22: 2488 | L22: =K22-K21 -> 2 | M22: 185531 | N22: =M22-M21 -> 143 | O22: =O21 -> 1869 | P22: =P21 -> 2250 | Q22: =Q21 -> 187918 | R22: =Q22-Q21 -> 0 | S22: =SUM(P22-P21) -> 0 | T22: =SUM(S22*$T$2) -> 0 | U22: =SUM(G22+L22+S22) -> 2 | V22: =R22+N22+I22:I22 -> 143 | X22: =X21 -> 2498 | Y22: =X22-X21 -> 0 | Z22: =Z21 -> 141419 | AA22: =Z22-Z21 -> 0 | AB22: =SUM(Y22*$AB$2) -> 0 | AC22: =AC21 -> 1963 | AD22: =AC22-AC21 -> 0 | AE22: =AE21 -> 367972 | AF22: =AE22-AE21 -> 0 | AG22: =IF(AD22>0,AF22/AD22,0) -> 0 | AH22: =AF22+AA22 -> 0 | AI22: =SUM(AH22+V22) -> 143 | AJ22: =-tanks!AW23 -> 143 | AK22: =SUM(AJ22-AI22) -> 0 | AL22: =S22+L22+G22 -> 2 | AM22: =Y22+AD22 -> 0 | AN22: =AN21 -> 65 | AO22: =(AN22/100)*3000 -> 1950 | AP22: =AP21 -> 35 | AQ22: =(AP22/100)*3000 -> 1050 | AR22: =AR21 -> 73 | AS22: =(AR22/100)*3000 -> 2190 | AT22: =SUM(AO22+AQ22+AS22) -> 5190 | AU22: =AT21-AT22+AV22 -> 0 | AX22: =IF(AV22>0,AW22,AX21) -> 0.8
A23: 44945 | B23: 236 | C23: 242 | D23: =C22-C23 -> 4 | E23: =D23*8.38 -> 33.52 | F23: =F22 -> 2368 | G23: =F23-F22 -> 0 | H23: =H22 -> 53005 | I23: =SUM(H23-H22) -> 0 | J23: =IF(G23>0,I23/G23,0) -> 0 | K23: 2489 | L23: =K23-K22 -> 1 | M23: 185614 | N23: =M23-M22 -> 83 | O23: =O22 -> 1869 | P23: =P22 -> 2250 | Q23: =Q22 -> 187918 | R23: =Q23-Q22 -> 0 | S23: =SUM(P23-P22) -> 0 | T23: =SUM(S23*$T$2) -> 0 | U23: =SUM(G23+L23+S23) -> 1 | V23: =R23+N23+I23:I23 -> 83 | X23: =X22 -> 2498 | Y23: =X23-X22 -> 0 | Z23: =Z22 -> 141419 | AA23: =Z23-Z22 -> 0 | AB23: =SUM(Y23*$AB$2) -> 0 | AC23: 1964 | AD23: =AC23-AC22 -> 1 | AE23: 368039 | AF23: =AE23-AE22 -> 67 | AG23: =IF(AD23>0,AF23/AD23,0) -> 67 | AH23: =AF23+AA23 -> 67 | AI23: =SUM(AH23+V23) -> 150 | AJ23: =-tanks!AW24 -> 150 | AK23: =SUM(AJ23-AI23) -> 0 | AL23: =S23+L23+G23 -> 1 | AM23: =Y23+AD23 -> 1 | AN23: =AN22 -> 65 | AO23: =(AN23/100)*3000 -> 1950 | AP23: =AP22 -> 35 | AQ23: =(AP23/100)*3000 -> 1050 | AR23: =AR22 -> 73 | AS23: =(AR23/100)*3000 -> 2190 | AT23: =SUM(AO23+AQ23+AS23) -> 5190 | AU23: =AT22-AT23+AV23 -> 0 | AX23: =IF(AV23>0,AW23,AX22) -> 0.8
A24: 44946 | B24: =B23 -> 236 | C24: =C23 -> 242 | D24: =C23-C24 -> 0 | E24: =D24*8.38 -> 0 | F24: =F23 -> 2368 | G24: =F24-F23 -> 0 | H24: =H23 -> 53005 | I24: =SUM(H24-H23) -> 0 | J24: =IF(G24>0,I24/G24,0) -> 0 | K24: =K23 -> 2489 | L24: =K24-K23 -> 0 | M24: =M23 -> 185614 | N24: =M24-M23 -> 0 | O24: =O23 -> 1869 | P24: =P23 -> 2250 | Q24: =Q23 -> 187918 | R24: =Q24-Q23 -> 0 | S24: =SUM(P24-P23) -> 0 | T24: =SUM(S24*$T$2) -> 0 | U24: =SUM(G24+L24+S24) -> 0 | V24: =R24+N24+I24:I24 -> 0 | X24: =X23 -> 2498 | Y24: =X24-X23 -> 0 | Z24: =Z23 -> 141419 | AA24: =Z24-Z23 -> 0 | AB24: =SUM(Y24*$AB$2) -> 0 | AC24: =AC23 -> 1964 | AD24: =AC24-AC23 -> 0 | AE24: =AE23 -> 368039 | AF24: =AE24-AE23 -> 0 | AG24: =IF(AD24>0,AF24/AD24,0) -> 0 | AH24: =AF24+AA24 -> 0 | AI24: =SUM(AH24+V24) -> 0 | AJ24: =-tanks!AW25 -> 0 | AK24: =SUM(AJ24-AI24) -> 0 | AL24: =S24+L24+G24 -> 0 | AM24: =Y24+AD24 -> 0 | AN24: =AN23 -> 65 | AO24: =(AN24/100)*3000 -> 1950 | AP24: =AP23 -> 35 | AQ24: =(AP24/100)*3000 -> 1050 | AR24: =AR23 -> 73 | AS24: =(AR24/100)*3000 -> 2190 | AT24: =SUM(AO24+AQ24+AS24) -> 5190 | AU24: =AT23-AT24+AV24 -> 0 | AX24: =IF(AV24>0,AW24,AX23) -> 0.8
A25: 44947 | B25: =B24 -> 236 | C25: =C24 -> 242 | D25: =C24-C25 -> 0 | E25: =D25*8.38 -> 0 | F25: =F24 -> 2368 | G25: =F25-F24 -> 0 | H25: =H24 -> 53005 | I25: =SUM(H25-H24) -> 0 | J25: =IF(G25>0,I25/G25,0) -> 0 | K25: =K24 -> 2489 | L25: =K25-K24 -> 0 | M25: =M24 -> 185614 | N25: =M25-M24 -> 0 | O25: =O24 -> 1869 | P25: =P24 -> 2250 | Q25: =Q24 -> 187918 | R25: =Q25-Q24 -> 0 | S25: =SUM(P25-P24) -> 0 | T25: =SUM(S25*$T$2) -> 0 | U25: =SUM(G25+L25+S25) -> 0 | V25: =R25+N25+I25:I25 -> 0 | X25: =X24 -> 2498 | Y25: =X25-X24 -> 0 | Z25: =Z24 -> 141419 | AA25: =Z25-Z24 -> 0 | AB25: =SUM(Y25*$AB$2) -> 0 | AC25: =AC24 -> 1964 | AD25: =AC25-AC24 -> 0 | AE25: =AE24 -> 368039 | AF25: =AE25-AE24 -> 0 | AG25: =IF(AD25>0,AF25/AD25,0) -> 0 | AH25: =AF25+AA25 -> 0 | AI25: =SUM(AH25+V25) -> 0 | AJ25: =-tanks!AW26 -> 0 | AK25: =SUM(AJ25-AI25) -> 0 | AL25: =S25+L25+G25 -> 0 | AM25: =Y25+AD25 -> 0 | AN25: =AN24 -> 65 | AO25: =(AN25/100)*3000 -> 1950 | AP25: =AP24 -> 35 | AQ25: =(AP25/100)*3000 -> 1050 | AR25: =AR24 -> 73 | AS25: =(AR25/100)*3000 -> 2190 | AT25: =SUM(AO25+AQ25+AS25) -> 5190 | AU25: =AT24-AT25+AV25 -> 0 | AX25: =IF(AV25>0,AW25,AX24) -> 0.8
A26: 44948 | B26: 232 | C26: 239 | D26: =C25-C26 -> 3 | E26: =D26*8.38 -> 25.14 | F26: 2370 | G26: =F26-F25 -> 2 | H26: 53157 | I26: =SUM(H26-H25) -> 152 | J26: =IF(G26>0,I26/G26,0) -> 76 | K26: 2490 | L26: =K26-K25 -> 1 | M26: 185690 | N26: =M26-M25 -> 76 | O26: 2251 | P26: 2251 | Q26: 187951 | R26: =Q26-Q25 -> 33 | S26: =SUM(P26-P25) -> 1 | T26: =SUM(S26*$T$2) -> 0 | U26: =SUM(G26+L26+S26) -> 4 | V26: =R26+N26+I26:I26 -> 261 | X26: =X25 -> 2498 | Y26: =X26-X25 -> 0 | Z26: =Z25 -> 141419 | AA26: =Z26-Z25 -> 0 | AB26: =SUM(Y26*$AB$2) -> 0 | AC26: =AC25 -> 1964 | AD26: =AC26-AC25 -> 0 | AE26: =AE25 -> 368039 | AF26: =AE26-AE25 -> 0 | AG26: =IF(AD26>0,AF26/AD26,0) -> 0 | AH26: =AF26+AA26 -> 0 | AI26: =SUM(AH26+V26) -> 261 | AJ26: =-tanks!AW27 -> 261 | AK26: =SUM(AJ26-AI26) -> 0 | AL26: =S26+L26+G26 -> 4 | AM26: =Y26+AD26 -> 0 | AN26: =AN25 -> 65 | AO26: =(AN26/100)*3000 -> 1950 | AP26: =AP25 -> 35 | AQ26: =(AP26/100)*3000 -> 1050 | AR26: =AR25 -> 73 | AS26: =(AR26/100)*3000 -> 2190 | AT26: =SUM(AO26+AQ26+AS26) -> 5190 | AU26: =AT25-AT26+AV26 -> 0 | AX26: =IF(AV26>0,AW26,AX25) -> 0.8
A27: 44949 | B27: 229 | C27: 235 | D27: =C26-C27 -> 4 | E27: =D27*8.38 -> 33.52 | F27: 2371 | G27: =F27-F26 -> 1 | H27: 53227 | I27: =SUM(H27-H26) -> 70 | J27: =IF(G27>0,I27/G27,0) -> 70 | K27: =K26 -> 2490 | L27: =K27-K26 -> 0 | M27: =M26 -> 185690 | N27: =M27-M26 -> 0 | O27: =O26 -> 2251 | P27: =P26 -> 2251 | Q27: =Q26 -> 187951 | R27: =Q27-Q26 -> 0 | S27: =SUM(P27-P26) -> 0 | T27: =SUM(S27*$T$2) -> 0 | U27: =SUM(G27+L27+S27) -> 1 | V27: =R27+N27+I27:I27 -> 70 | X27: =X26 -> 2498 | Y27: =X27-X26 -> 0 | Z27: =Z26 -> 141419 | AA27: =Z27-Z26 -> 0 | AB27: =SUM(Y27*$AB$2) -> 0 | AC27: 1966 | AD27: =AC27-AC26 -> 2 | AE27: 368122 | AF27: =AE27-AE26 -> 83 | AG27: =IF(AD27>0,AF27/AD27,0) -> 41.5 | AH27: =AF27+AA27 -> 83 | AI27: =SUM(AH27+V27) -> 153 | AJ27: =-tanks!AW28 -> 153 | AK27: =SUM(AJ27-AI27) -> 0 | AL27: =S27+L27+G27 -> 1 | AM27: =Y27+AD27 -> 2 | AN27: =AN26 -> 65 | AO27: =(AN27/100)*3000 -> 1950 | AP27: =AP26 -> 35 | AQ27: =(AP27/100)*3000 -> 1050 | AR27: =AR26 -> 73 | AS27: =(AR27/100)*3000 -> 2190 | AT27: =SUM(AO27+AQ27+AS27) -> 5190 | AU27: =AT26-AT27+AV27 -> 0 | AX27: =IF(AV27>0,AW27,AX26) -> 0.8
A28: 44950 | B28: 227 | C28: 233 | D28: =C27-C28 -> 2 | E28: =D28*8.38 -> 16.76 | F28: 2372 | G28: =F28-F27 -> 1 | H28: 53273 | I28: =SUM(H28-H27) -> 46 | J28: =IF(G28>0,I28/G28,0) -> 46 | K28: 2490 | L28: =K28-K27 -> 0 | M28: =M27 -> 185690 | N28: =M28-M27 -> 0 | O28: =O27 -> 2251 | P28: 2251 | Q28: 187961 | R28: =Q28-Q27 -> 10 | S28: =SUM(P28-P27) -> 0 | T28: =SUM(S28*$T$2) -> 0 | U28: =SUM(G28+L28+S28) -> 1 | V28: =R28+N28+I28:I28 -> 56 | X28: =X27 -> 2498 | Y28: =X28-X27 -> 0 | Z28: =Z27 -> 141419 | AA28: =Z28-Z27 -> 0 | AB28: =SUM(Y28*$AB$2) -> 0 | AC28: =AC27 -> 1966 | AD28: =AC28-AC27 -> 0 | AE28: =AE27 -> 368122 | AF28: =AE28-AE27 -> 0 | AG28: =IF(AD28>0,AF28/AD28,0) -> 0 | AH28: =AF28+AA28 -> 0 | AI28: =SUM(AH28+V28) -> 56 | AJ28: =-tanks!AW29 -> 56 | AK28: =SUM(AJ28-AI28) -> 0 | AL28: =S28+L28+G28 -> 1 | AM28: =Y28+AD28 -> 0 | AN28: =AN27 -> 65 | AO28: =(AN28/100)*3000 -> 1950 | AP28: =AP27 -> 35 | AQ28: =(AP28/100)*3000 -> 1050 | AR28: =AR27 -> 73 | AS28: =(AR28/100)*3000 -> 2190 | AT28: =SUM(AO28+AQ28+AS28) -> 5190 | AU28: =AT27-AT28+AV28 -> 0 | AX28: =IF(AV28>0,AW28,AX27) -> 0.8
A29: 44951 | B29: 223 | C29: 229 | D29: =C28-C29 -> 4 | E29: =D29*8.38 -> 33.52 | F29: 2375 | G29: =F29-F28 -> 3 | H29: 53491 | I29: =SUM(H29-H28) -> 218 | J29: =IF(G29>0,I29/G29,0) -> 72.666667 | K29: =K28 -> 2490 | L29: =K29-K28 -> 0 | M29: 185720 | N29: =M29-M28 -> 30 | O29: =O28 -> 2251 | P29: =P28 -> 2251 | Q29: =Q28 -> 187961 | R29: =Q29-Q28 -> 0 | S29: =SUM(P29-P28) -> 0 | T29: =SUM(S29*$T$2) -> 0 | U29: =SUM(G29+L29+S29) -> 3 | V29: =R29+N29+I29:I29 -> 248 | X29: =X28 -> 2498 | Y29: =X29-X28 -> 0 | Z29: 141480 | AA29: =Z29-Z28 -> 61 | AB29: =SUM(Y29*$AB$2) -> 0 | AC29: =AC28 -> 1966 | AD29: =AC29-AC28 -> 0 | AE29: =AE28 -> 368122 | AF29: =AE29-AE28 -> 0 | AG29: =IF(AD29>0,AF29/AD29,0) -> 0 | AH29: =AF29+AA29 -> 61 | AI29: =SUM(AH29+V29) -> 309 | AJ29: =-tanks!AW30 -> 309 | AK29: =SUM(AJ29-AI29) -> 0 | AL29: =S29+L29+G29 -> 3 | AM29: =Y29+AD29 -> 0 | AN29: =AN28 -> 65 | AO29: =(AN29/100)*3000 -> 1950 | AP29: =AP28 -> 35 | AQ29: =(AP29/100)*3000 -> 1050 | AR29: =AR28 -> 73 | AS29: =(AR29/100)*3000 -> 2190 | AT29: =SUM(AO29+AQ29+AS29) -> 5190 | AU29: =AT28-AT29+AV29 -> 0 | AX29: =IF(AV29>0,AW29,AX28) -> 0.8
A30: 44952 | B30: 220 | C30: 226 | D30: =C29-C30 -> 3 | E30: =D30*8.38 -> 25.14 | F30: =F29 -> 2375 | G30: =F30-F29 -> 0 | H30: 53624 | I30: =SUM(H30-H29) -> 133 | J30: =IF(G30>0,I30/G30,0) -> 0 | K30: =K29 -> 2490 | L30: =K30-K29 -> 0 | M30: 185727 | N30: =M30-M29 -> 7 | O30: =O29 -> 2251 | P30: =P29 -> 2251 | Q30: =Q29 -> 187961 | R30: =Q30-Q29 -> 0 | S30: =SUM(P30-P29) -> 0 | T30: =SUM(S30*$T$2) -> 0 | U30: =SUM(G30+L30+S30) -> 0 | V30: =R30+N30+I30:I30 -> 140 | X30: =X29 -> 2498 | Y30: =X30-X29 -> 0 | Z30: =Z29 -> 141480 | AA30: =Z30-Z29 -> 0 | AB30: =SUM(Y30*$AB$2) -> 0 | AC30: =AC29 -> 1966 | AD30: =AC30-AC29 -> 0 | AE30: =AE29 -> 368122 | AF30: =AE30-AE29 -> 0 | AG30: =IF(AD30>0,AF30/AD30,0) -> 0 | AH30: =AF30+AA30 -> 0 | AI30: =SUM(AH30+V30) -> 140 | AJ30: =-tanks!AW31 -> 140 | AK30: =SUM(AJ30-AI30) -> 0 | AL30: =S30+L30+G30 -> 0 | AM30: =Y30+AD30 -> 0 | AN30: =AN29 -> 65 | AO30: =(AN30/100)*3000 -> 1950 | AP30: =AP29 -> 35 | AQ30: =(AP30/100)*3000 -> 1050 | AR30: =AR29 -> 73 | AS30: =(AR30/100)*3000 -> 2190 | AT30: =SUM(AO30+AQ30+AS30) -> 5190 | AU30: =AT29-AT30+AV30 -> 0 | AX30: =IF(AV30>0,AW30,AX29) -> 0.8
A31: 44953 | B31: =B30 -> 220 | C31: =C30 -> 226 | D31: =C30-C31 -> 0 | E31: =D31*8.38 -> 0 | F31: 2377 | G31: =F31-F30 -> 2 | H31: =H30 -> 53624 | I31: =SUM(H31-H30) -> 0 | J31: =IF(G31>0,I31/G31,0) -> 0 | K31: =K30 -> 2490 | L31: =K31-K30 -> 0 | M31: =M30 -> 185727 | N31: =M31-M30 -> 0 | O31: =O30 -> 2251 | P31: =P30 -> 2251 | Q31: =Q30 -> 187961 | R31: =Q31-Q30 -> 0 | S31: =SUM(P31-P30) -> 0 | T31: =SUM(S31*$T$2) -> 0 | U31: =SUM(G31+L31+S31) -> 2 | V31: =R31+N31+I31:I31 -> 0 | X31: =X30 -> 2498 | Y31: =X31-X30 -> 0 | Z31: =Z30 -> 141480 | AA31: =Z31-Z30 -> 0 | AB31: =SUM(Y31*$AB$2) -> 0 | AC31: =AC30 -> 1966 | AD31: =AC31-AC30 -> 0 | AE31: =AE30 -> 368122 | AF31: =AE31-AE30 -> 0 | AG31: =IF(AD31>0,AF31/AD31,0) -> 0 | AH31: =AF31+AA31 -> 0 | AI31: =SUM(AH31+V31) -> 0 | AJ31: =-tanks!AW32 -> 0 | AK31: =SUM(AJ31-AI31) -> 0 | AL31: =S31+L31+G31 -> 2 | AM31: =Y31+AD31 -> 0 | AN31: =AN30 -> 65 | AO31: =(AN31/100)*3000 -> 1950 | AP31: =AP30 -> 35 | AQ31: =(AP31/100)*3000 -> 1050 | AR31: =AR30 -> 73 | AS31: =(AR31/100)*3000 -> 2190 | AT31: =SUM(AO31+AQ31+AS31) -> 5190 | AU31: =AT30-AT31+AV31 -> 0 | AX31: =IF(AV31>0,AW31,AX30) -> 0.8
A32: 44954 | B32: =B31 -> 220 | C32: =C31 -> 226 | D32: =C31-C32 -> 0 | E32: =D32*8.38 -> 0 | F32: =F31 -> 2377 | G32: =F32-F31 -> 0 | H32: =H31 -> 53624 | I32: =SUM(H32-H31) -> 0 | J32: =IF(G32>0,I32/G32,0) -> 0 | K32: =K31 -> 2490 | L32: =K32-K31 -> 0 | M32: =M31 -> 185727 | N32: =M32-M31 -> 0 | O32: =O31 -> 2251 | P32: =P31 -> 2251 | Q32: =Q31 -> 187961 | R32: =Q32-Q31 -> 0 | S32: =SUM(P32-P31) -> 0 | T32: =SUM(S32*$T$2) -> 0 | U32: =SUM(G32+L32+S32) -> 0 | V32: =R32+N32+I32:I32 -> 0 | X32: =X31 -> 2498 | Y32: =X32-X31 -> 0 | Z32: =Z31 -> 141480 | AA32: =Z32-Z31 -> 0 | AB32: =SUM(Y32*$AB$2) -> 0 | AC32: =AC31 -> 1966 | AD32: =AC32-AC31 -> 0 | AE32: =AE31 -> 368122 | AF32: =AE32-AE31 -> 0 | AG32: =IF(AD32>0,AF32/AD32,0) -> 0 | AH32: =AF32+AA32 -> 0 | AI32: =SUM(AH32+V32) -> 0 | AJ32: =-tanks!AW33 -> 0 | AK32: =SUM(AJ32-AI32) -> 0 | AL32: =S32+L32+G32 -> 0 | AM32: =Y32+AD32 -> 0 | AN32: =AN31 -> 65 | AO32: =(AN32/100)*3000 -> 1950 | AP32: =AP31 -> 35 | AQ32: =(AP32/100)*3000 -> 1050 | AR32: =AR31 -> 73 | AS32: =(AR32/100)*3000 -> 2190 | AT32: =SUM(AO32+AQ32+AS32) -> 5190 | AU32: =AT31-AT32+AV32 -> 0 | AX32: =IF(AV32>0,AW32,AX31) -> 0.8
A33: 44955 | B33: 216 | C33: 222 | D33: =C32-C33 -> 4 | E33: =D33*8.38 -> 33.52 | F33: 2379 | G33: =F33-F32 -> 2 | H33: 53845 | I33: =SUM(H33-H32) -> 221 | J33: =IF(G33>0,I33/G33,0) -> 110.5 | K33: =K32 -> 2490 | L33: =K33-K32 -> 0 | M33: =M32 -> 185727 | N33: =M33-M32 -> 0 | O33: =O32 -> 2251 | P33: =P32 -> 2251 | Q33: =Q32 -> 187961 | R33: =Q33-Q32 -> 0 | S33: =SUM(P33-P32) -> 0 | T33: =SUM(S33*$T$2) -> 0 | U33: =SUM(G33+L33+S33) -> 2 | V33: =R33+N33+I33:I33 -> 221 | X33: =X32 -> 2498 | Y33: =X33-X32 -> 0 | Z33: =Z32 -> 141480 | AA33: =Z33-Z32 -> 0 | AB33: =SUM(Y33*$AB$2) -> 0 | AC33: =AC32 -> 1966 | AD33: =AC33-AC32 -> 0 | AE33: =AE32 -> 368122 | AF33: =AE33-AE32 -> 0 | AG33: =IF(AD33>0,AF33/AD33,0) -> 0 | AH33: =AF33+AA33 -> 0 | AI33: =SUM(AH33+V33) -> 221 | AJ33: =-tanks!AW34 -> 221 | AK33: =SUM(AJ33-AI33) -> 0 | AL33: =S33+L33+G33 -> 2 | AM33: =Y33+AD33 -> 0 | AN33: =AN32 -> 65 | AO33: =(AN33/100)*3000 -> 1950 | AP33: =AP32 -> 35 | AQ33: =(AP33/100)*3000 -> 1050 | AR33: =AR32 -> 73 | AS33: =(AR33/100)*3000 -> 2190 | AT33: =SUM(AO33+AQ33+AS33) -> 5190 | AU33: =AT32-AT33+AV33 -> 0 | AX33: =IF(AV33>0,AW33,AX32) -> 0.8
A34: 44956 | B34: 240.5 | C34: 246.5 | D34: =C33-C34 -> -24.5 | E34: =D34*8.38 -> -205.31 | F34: 2381 | G34: =F34-F33 -> 2 | H34: 53995 | I34: =SUM(H34-H33) -> 150 | J34: =IF(G34>0,I34/G34,0) -> 75 | K34: =K33 -> 2490 | L34: =K34-K33 -> 0 | M34: =M33 -> 185727 | N34: =M34-M33 -> 0 | O34: =O33 -> 2251 | P34: 2252 | Q34: 188058 | R34: =Q34-Q33 -> 97 | S34: =SUM(P34-P33) -> 1 | T34: =SUM(S34*$T$2) -> 0 | U34: =SUM(G34+L34+S34) -> 3 | V34: =R34+N34+I34:I34 -> 247 | X34: =X33 -> 2498 | Y34: =X34-X33 -> 0 | Z34: =Z33 -> 141480 | AA34: =Z34-Z33 -> 0 | AB34: =SUM(Y34*$AB$2) -> 0 | AC34: 1968 | AD34: =AC34-AC33 -> 2 | AE34: 368258 | AF34: =AE34-AE33 -> 136 | AG34: =IF(AD34>0,AF34/AD34,0) -> 68 | AH34: =AF34+AA34 -> 136 | AI34: =SUM(AH34+V34) -> 383 | AJ34: =-tanks!AW35 -> 383 | AK34: =SUM(AJ34-AI34) -> 0 | AL34: =S34+L34+G34 -> 3 | AM34: =Y34+AD34 -> 2 | AN34: =AN33 -> 65 | AO34: =(AN34/100)*3000 -> 1950 | AP34: =AP33 -> 35 | AQ34: =(AP34/100)*3000 -> 1050 | AR34: =AR33 -> 73 | AS34: =(AR34/100)*3000 -> 2190 | AT34: =SUM(AO34+AQ34+AS34) -> 5190 | AU34: =AT33-AT34+AV34 -> 0 | AX34: =IF(AV34>0,AW34,AX33) -> 0.8
A35: 44957 | B35: =B34 -> 240.5 | C35: =C34 -> 246.5 | D35: =C34-C35 -> 0 | E35: =D35*8.38 -> 0 | F35: =F34 -> 2381 | G35: =F35-F34 -> 0 | H35: =H34 -> 53995 | I35: =SUM(H35-H34) -> 0 | J35: =IF(G35>0,I35/G35,0) -> 0 | K35: =K34 -> 2490 | L35: =K35-K34 -> 0 | M35: =M34 -> 185727 | N35: =M35-M34 -> 0 | O35: =O34 -> 2251 | P35: =P34 -> 2252 | Q35: =Q34 -> 188058 | R35: =Q35-Q34 -> 0 | S35: =SUM(P35-P34) -> 0 | T35: =SUM(S35*$T$2) -> 0 | U35: =SUM(G35+L35+S35) -> 0 | V35: =R35+N35+I35:I35 -> 0 | X35: =X34 -> 2498 | Y35: =X35-X34 -> 0 | Z35: =Z34 -> 141480 | AA35: =Z35-Z34 -> 0 | AB35: =SUM(Y35*$AB$2) -> 0 | AC35: =AC34 -> 1968 | AD35: =AC35-AC34 -> 0 | AE35: =AE34 -> 368258 | AF35: =AE35-AE34 -> 0 | AG35: =IF(AD35>0,AF35/AD35,0) -> 0 | AH35: =AF35+AA35 -> 0 | AI35: =SUM(AH35+V35) -> 0 | AJ35: =-tanks!AW36 -> 0 | AK35: =SUM(AJ35-AI35) -> 0 | AL35: =S35+L35+G35 -> 0 | AM35: =Y35+AD35 -> 0 | AN35: =AN34 -> 65 | AO35: =(AN35/100)*3000 -> 1950 | AP35: =AP34 -> 35 | AQ35: =(AP35/100)*3000 -> 1050 | AR35: =AR34 -> 73 | AS35: =(AR35/100)*3000 -> 2190 | AT35: =SUM(AO35+AQ35+AS35) -> 5190 | AU35: =AT34-AT35+AV35 -> 0 | AX35: =IF(AV35>0,AW35,AX34) -> 0.8
J36: =SUM(J5:J32)/(COUNT(J5:J32)-COUNTIF(J5:J32,0)) -> 57.708333 | U36: =SUM(U5:U35) -> 40 | V36: =SUM(V5:V35) -> 3175 | AE36: . | AH36: =SUM(AH5:AH35) -> 630 | AL36: =SUM(AL5:AL35) -> 40 | AM36: =SUM(AM5:AM35) -> 9 | AR36: Nb Delivery | AS36: =COUNT(AW5:AW35) -> 0 | AU36: =SUM(AU5:AU35) -> 0 | AV36: =SUM(AV5:AV35) -> 0 | AW36: =SUM(AW5:AW35)/AS36 -> #DIV/0!
V37: =V36/U36 -> 79.375 | AH37: =AF37+AA37 -> 0 | AI37: =SUM(AI5:AI35) -> 3805
AH38: =AF38+AA38 -> 0 | AU38: =AU36*0.51 -> 0 | AV38: =AV36/0.51 -> 0 | AW38: =SUM(AW5:AW32)/AS36 -> #DIV/0!
AV39: =AV36*0.51 -> 0

Sheet tanks
B2: Tank 1 | D2: Tank 2 | F2: Tank 3 | H2: Tank 4 | J2: Tank 5 | L2: Tank 6 | N2: Tank 7 | P2: Tank 8 | R2: Tank 9 | T2: Tank 10 | V2: Tank 11 | Z2: Tank 1 | AB2: Tank 2 | AD2: Tank 3 | AF2: Tank 4 | AH2: Tank 5 | AJ2: Tank 6 | AL2: Tank 7
B3: 6670 | D3: =SUM(B3) -> 6670 | F3: =SUM(D3) -> 6670 | H3: =SUM(F3) -> 6670 | J3: =SUM(H3) -> 6670 | L3: =SUM(J3) -> 6670 | N3: =SUM(L3) -> 6670 | P3: =SUM(N3) -> 6670 | R3: =SUM(P3) -> 6670 | T3: =SUM(R3) -> 6670 | V3: =SUM(T3) -> 6670 | W3: =SUM(B3:V3) -> 73370 | Z3: 2800 | AB3: 2800 | AD3: 2800 | AF3: 2800 | AH3: 2800 | AJ3: 2800 | AL3: 2800 | AM3: =SUM(Z3:AL3) -> 19600 | AO3: =SUM(AM3+W3) -> 92970 | AR3: Total sotck | AS3: Diesel Cons Per day | AT3: Diesel Delivery | BE3: Genset Co | BF3: Steam | BG3: Boil | BH3: Outdoor temperature
B4: =B3/310 -> 21.516129 | D4: =SUM(B4) -> 21.516129 | F4: =SUM(D4) -> 21.516129 | H4: =SUM(F4) -> 21.516129 | J4: =SUM(H4) -> 21.516129 | L4: =SUM(J4) -> 21.516129 | N4: =SUM(L4) -> 21.516129 | P4: =SUM(N4) -> 21.516129 | R4: =SUM(P4) -> 21.516129 | T4: =SUM(R4) -> 21.516129 | V4: =SUM(T4) -> 21.516129 | Z4: =Z3/280 -> 10 | AA4: =AA3/280 -> 0 | AB4: =AB3/280 -> 10 | AC4: =AC3/280 -> 0 | AD4: =AD3/280 -> 10 | AE4: =AE3/280 -> 0 | AF4: =AF3/280 -> 10 | AG4: =AG3/280 -> 0 | ... AL4: =AL3/280 -> 10 | AT4: Delivery | AU4: Cost /L | AW4: Boiler+Steam | AX4: Generator | AZ4: Occupancy | BA4: AVE TEPM | BB4: AVE Humidity
A5: 44926 | B5: ='B5'!B4 -> 218 | C5: =B5*$B$4 -> 4690.5161 | D5: =SUM(B5) -> 218 | E5: =D5*$B$4 -> 4690.5161 | F5: =SUM(D5) -> 218 | G5: =F5*$B$4 -> 4690.5161 | H5: =SUM(F5) -> 218 | I5: =H5*$B$4 -> 4690.5161 | J5: =SUM(H5) -> 218 | K5: =J5*$B$4 -> 4690.5161 | L5: =SUM(J5) -> 218 | M5: =L5*$B$4 -> 4690.5161 | N5: =SUM(L5) -> 218 | O5: =N5*$B$4 -> 4690.5161 | P5: =SUM(N5) -> 218 | Q5: =P5*$B$4 -> 4690.5161 | R5: =SUM(P5) -> 218 | S5: =R5*$B$4 -> 4690.5161 | T5: =SUM(R5) -> 218 | U5: =T5*$B$4 -> 4690.5161 | V5: =SUM(T5) -> 218 | W5: =V5*$B$4 -> 4690.5161 | X5: =SUM(Y5/73370) -> 0.70322581 | Y5: =SUM(C5+E5+G5+I5+K5+M5+O5+Q5+S5+U5+W5) -> 51595.677 | Z5: ='B5'!C4 -> 224 | AA5: =SUM(Z5*$Z$4) -> 2240 | AB5: =SUM(Z5) -> 224 | AC5: =SUM(AB5*$Z$4) -> 2240 | AD5: =SUM(AB5) -> 224 | AE5: =SUM(AD5*$Z$4) -> 2240 | AF5: =SUM(AD5) -> 224 | AG5: =SUM(AF5*$Z$4) -> 2240 | AH5: =SUM(AF5) -> 224 | AI5: =SUM(AH5*$Z$4) -> 2240 | AJ5: =SUM(AH5) -> 224 | AK5: =SUM(AJ5*$Z$4) -> 2240 | AL5: =SUM(AJ5) -> 224 | AM5: =SUM(AL5*$Z$4) -> 2240 | AN5: =SUM(AO5/19600) -> 0.8 | AO5: =SUM(AA5+AC5+AE5+AG5+AI5+AK5+AM5) -> 15680 | AQ5: =SUM(AR5/92970) -> 0.72362781 | AR5: =AO5+Y5 -> 67275.677 | AS5: 0 | AT5: 0 | AU5: 0 | AV5: 0 | AW5: 0 | AX5: 0 | AY5: 0 | AZ5: =[2]tanks!AZ35 -> 0 | BA5: =[2]tanks!BA35 -> 19.5 | BB5: =[2]tanks!BB35 -> 0.76 | BC5: =[2]tanks!BC35 -> 1 | BD5: =[2]tanks!BD35 -> 19224 | BE5: =[2]tanks!BE35 -> #REF! | BF5: =[2]tanks!BF35 -> 0 | BG5: =[2]tanks!BG35 -> #REF! | ... BK5: =[2]tanks!BK35 -> 0.16013393
A6: =ELEC!C4 -> 44927 | B6: ='B5'!B5 -> 218 | C6: =B6*$B$4 -> 4690.5161 | D6: =SUM(B6) -> 218 | E6: =D6*$B$4 -> 4690.5161 | F6: =SUM(D6) -> 218 | G6: =F6*$B$4 -> 4690.5161 | H6: =SUM(F6) -> 218 | I6: =H6*$B$4 -> 4690.5161 | J6: =SUM(H6) -> 218 | K6: =J6*$B$4 -> 4690.5161 | L6: =SUM(J6) -> 218 | M6: =L6*$B$4 -> 4690.5161 | N6: =SUM(L6) -> 218 | O6: =N6*$B$4 -> 4690.5161 | P6: =SUM(N6) -> 218 | Q6: =P6*$B$4 -> 4690.5161 | R6: =SUM(P6) -> 218 | S6: =R6*$B$4 -> 4690.5161 | T6: =SUM(R6) -> 218 | U6: =T6*$B$4 -> 4690.5161 | V6: =SUM(T6) -> 218 | W6: =V6*$B$4 -> 4690.5161 | X6: =SUM(Y6/73370) -> 0.70322581 | Y6: =SUM(C6+E6+G6+I6+K6+M6+O6+Q6+S6+U6+W6) -> 51595.677 | Z6: ='B5'!C5 -> 224 | AA6: =SUM(Z6*$Z$4) -> 2240 | AB6: =SUM(Z6) -> 224 | AC6: =SUM(AB6*$Z$4) -> 2240 | AD6: =SUM(AB6) -> 224 | AE6: =SUM(AD6*$Z$4) -> 2240 | AF6: =SUM(AD6) -> 224 | AG6: =SUM(AF6*$Z$4) -> 2240 | AH6: =SUM(AF6) -> 224 | AI6: =SUM(AH6*$Z$4) -> 2240 | AJ6: =SUM(AH6) -> 224 | AK6: =SUM(AJ6*$Z$4) -> 2240 | AL6: =SUM(AJ6) -> 224 | AM6: =SUM(AL6*$Z$4) -> 2240 | AN6: =SUM(AO6/19600) -> 0.8 | AO6: =SUM(AA6+AC6+AE6+AG6+AI6+AK6+AM6) -> 15680 | AQ6: =SUM(AR6/92970) -> 0.72362781 | AR6: =Y6+AO6 -> 67275.677 | AS6: =SUM(AR6-AR5-AT6) -> 0 | AV6: =IF(AT6>0,AU6,AV5) -> 0 | AW6: =-SUM('B5'!AI5) -> 0 | AX6: =-SUM(AW6-AS6) -> 0 | AY6: =SUM(AX6+AW6) -> 0 | AZ6: =ELEC!A4 -> 0 | BA6: ='General information '!D5 -> 16 | BB6: =SUM('General information '!E5) -> 0.69 | BC6: =IF(AR3>=AR6,0,1) -> 0 | BD6: 19222 | BE6: =(305/1185)*ELEC!Q5 -> 0 | BG6: =#REF!-BE6 -> #REF! | BH6: 21 | BI6: 12 | BJ6: =AX6/BI6 -> 0
A7: =ELEC!C5 -> 44928 | B7: ='B5'!B6 -> 218 | C7: =B7*$B$4 -> 4690.5161 | D7: =SUM(B7) -> 218 | E7: =D7*$B$4 -> 4690.5161 | F7: =SUM(D7) -> 218 | G7: =F7*$B$4 -> 4690.5161 | H7: =SUM(F7) -> 218 | I7: =H7*$B$4 -> 4690.5161 | J7: =SUM(H7) -> 218 | K7: =J7*$B$4 -> 4690.5161 | L7: =SUM(J7) -> 218 | M7: =L7*$B$4 -> 4690.5161 | N7: =SUM(L7) -> 218 | O7: =N7*$B$4 -> 4690.5161 | P7: =SUM(N7) -> 218 | Q7: =P7*$B$4 -> 4690.5161 | R7: =SUM(P7) -> 218 | S7: =R7*$B$4 -> 4690.5161 | T7: =SUM(R7) -> 218 | U7: =T7*$B$4 -> 4690.5161 | V7: =SUM(T7) -> 218 | W7: =V7*$B$4 -> 4690.5161 | X7: =SUM(Y7/73370) -> 0.70322581 | Y7: =SUM(C7+E7+G7+I7+K7+M7+O7+Q7+S7+U7+W7) -> 51595.677 | Z7: ='B5'!C6 -> 224 | AA7: =SUM(Z7*$Z$4) -> 2240 | AB7: =SUM(Z7) -> 224 | AC7: =SUM(AB7*$Z$4) -> 2240 | AD7: =SUM(AB7) -> 224 | AE7: =SUM(AD7*$Z$4) -> 2240 | AF7: =SUM(AD7) -> 224 | AG7: =SUM(AF7*$Z$4) -> 2240 | AH7: =SUM(AF7) -> 224 | AI7: =SUM(AH7*$Z$4) -> 2240 | AJ7: =SUM(AH7) -> 224 | AK7: =SUM(AJ7*$Z$4) -> 2240 | AL7: =SUM(AJ7) -> 224 | AM7: =SUM(AL7*$Z$4) -> 2240 | AN7: =SUM(AO7/19600) -> 0.8 | AO7: =SUM(AA7+AC7+AE7+AG7+AI7+AK7+AM7) -> 15680 | AQ7: =SUM(AR7/92970) -> 0.72362781 | AR7: =Y7+AO7 -> 67275.677 | AS7: =SUM(AR7-AR6-AT7) -> 0 | AV7: =IF(AT7>0,AU7,AV6) -> 0 | AW7: =-SUM('B5'!AI6) -> 0 | AX7: =-SUM(AW7-AS7) -> 0 | AY7: =SUM(AX7+AW7) -> 0 | AZ7: =ELEC!A5 -> 0 | BA7: ='General information '!D6 -> 17 | BB7: =SUM('General information '!E6) -> 0.69 | BC7: 0 | BD7: 19222 | BE7: =(305/1185)*ELEC!Q6 -> 879.99578 | BG7: =#REF!-BE7 -> #REF! | BH7: 19 | BI7: 15 | BJ7: =AX7/BI7 -> 0
A8: =ELEC!C6 -> 44929 | B8: ='B5'!B7 -> 214 | C8: =B8*$B$4 -> 4604.4516 | D8: =SUM(B8) -> 214 | E8: =D8*$B$4 -> 4604.4516 | F8: =SUM(D8) -> 214 | G8: =F8*$B$4 -> 4604.4516 | H8: =SUM(F8) -> 214 | I8: =H8*$B$4 -> 4604.4516 | J8: =SUM(H8) -> 214 | K8: =J8*$B$4 -> 4604.4516 | L8: =SUM(J8) -> 214 | M8: =L8*$B$4 -> 4604.4516 | N8: =SUM(L8) -> 214 | O8: =N8*$B$4 -> 4604.4516 | P8: =SUM(N8) -> 214 | Q8: =P8*$B$4 -> 4604.4516 | R8: =SUM(P8) -> 214 | S8: =R8*$B$4 -> 4604.4516 | T8: =SUM(R8) -> 214 | U8: =T8*$B$4 -> 4604.4516 | V8: =SUM(T8) -> 214 | W8: =V8*$B$4 -> 4604.4516 | X8: =SUM(Y8/73370) -> 0.69032258 | Y8: =SUM(C8+E8+G8+I8+K8+M8+O8+Q8+S8+U8+W8) -> 50648.968 | Z8: ='B5'!C7 -> 221 | AA8: =SUM(Z8*$Z$4) -> 2210 | AB8: =SUM(Z8) -> 221 | AC8: =SUM(AB8*$Z$4) -> 2210 | AD8: =SUM(AB8) -> 221 | AE8: =SUM(AD8*$Z$4) -> 2210 | AF8: =SUM(AD8) -> 221 | AG8: =SUM(AF8*$Z$4) -> 2210 | AH8: =SUM(AF8) -> 221 | AI8: =SUM(AH8*$Z$4) -> 2210 | AJ8: =SUM(AH8) -> 221 | AK8: =SUM(AJ8*$Z$4) -> 2210 | AL8: =SUM(AJ8) -> 221 | AM8: =SUM(AL8*$Z$4) -> 2210 | AN8: =SUM(AO8/19600) -> 0.78928571 | AO8: =SUM(AA8+AC8+AE8+AG8+AI8+AK8+AM8) -> 15470 | AQ8: =SUM(AR8/92970) -> 0.71118606 | AR8: =Y8+AO8 -> 66118.968 | AS8: =SUM(AR8-AR7-AT8) -> -1156.7097 | AV8: =IF(AT8>0,AU8,AV7) -> 0 | AW8: =-SUM('B5'!AI7) -> -84 | AX8: =-SUM(AW8-AS8) -> -1072.7097 | AY8: =SUM(AX8+AW8) -> -1156.7097 | AZ8: =ELEC!A6 -> 0 | BA8: ='General information '!D7 -> 19 | BB8: =SUM('General information '!E7) -> 0.69 | BC8: =IF(AR7>=AR8,0,1) -> 0 | BD8: 19222 | BE8: =(305/1185)*ELEC!Q7 -> 704.45992 | BG8: =#REF!-BE8 -> #REF! | BH8: 16 | BI8: 9 | BJ8: =AX8/BI8 -> -119.18996 | BK8: =GEN!AF5 -> 0.2136875
A9: =ELEC!C7 -> 44930 | B9: ='B5'!B8 -> 239 | C9: =B9*$B$4 -> 5142.3548 | D9: =SUM(B9) -> 239 | E9: =D9*$B$4 -> 5142.3548 | F9: =SUM(D9) -> 239 | G9: =F9*$B$4 -> 5142.3548 | H9: =SUM(F9) -> 239 | I9: =H9*$B$4 -> 5142.3548 | J9: =SUM(H9) -> 239 | K9: =J9*$B$4 -> 5142.3548 | L9: =SUM(J9) -> 239 | M9: =L9*$B$4 -> 5142.3548 | N9: =SUM(L9) -> 239 | O9: =N9*$B$4 -> 5142.3548 | P9: =SUM(N9) -> 239 | Q9: =P9*$B$4 -> 5142.3548 | R9: =SUM(P9) -> 239 | S9: =R9*$B$4 -> 5142.3548 | T9: =SUM(R9) -> 239 | U9: =T9*$B$4 -> 5142.3548 | V9: =SUM(T9) -> 239 | W9: =V9*$B$4 -> 5142.3548 | X9: =SUM(Y9/73370) -> 0.77096774 | Y9: =SUM(C9+E9+G9+I9+K9+M9+O9+Q9+S9+U9+W9) -> 56565.903 | Z9: ='B5'!C8 -> 242 | AA9: =SUM(Z9*$Z$4) -> 2420 | AB9: =SUM(Z9) -> 242 | AC9: =SUM(AB9*$Z$4) -> 2420 | AD9: =SUM(AB9) -> 242 | AE9: =SUM(AD9*$Z$4) -> 2420 | AF9: =SUM(AD9) -> 242 | AG9: =SUM(AF9*$Z$4) -> 2420 | AH9: =SUM(AF9) -> 242 | AI9: =SUM(AH9*$Z$4) -> 2420 | AJ9: =SUM(AH9) -> 242 | AK9: =SUM(AJ9*$Z$4) -> 2420 | AL9: =SUM(AJ9) -> 242 | AM9: =SUM(AL9*$Z$4) -> 2420 | AN9: =SUM(AO9/19600) -> 0.86428571 | AO9: =SUM(AA9+AC9+AE9+AG9+AI9+AK9+AM9) -> 16940 | AQ9: =SUM(AR9/92970) -> 0.7906411 | AR9: =Y9+AO9 -> 73505.903 | AS9: =SUM(AR9-AR8-AT9) -> -408.06452 | AT9: 7795 | AU9: 0.89 | AV9: =IF(AT9>0,AU9,AV8) -> 0.89 | AW9: =-SUM('B5'!AI8) -> -297 | AX9: =-SUM(AW9-AS9) -> -111.06452 | AY9: =SUM(AX9+AW9) -> -408.06452 | AZ9: =ELEC!A7 -> 0 | BA9: ='General information '!D8 -> 17 | BB9: =SUM('General information '!E8) -> 0.55 | BC9: =IF(AR8>=AR9,0,1) -> 1 | BD9: 19222 | BE9: =(305/1185)*ELEC!Q8 -> 602.79325 | BG9: =#REF!-BE9 -> #REF! | BH9: 18 | BI9: 6 | BJ9: =AX9/BI9 -> -18.510753 | BK9: =GEN!AF6 -> 0.100625
A10: =ELEC!C8 -> 44931 | B10: ='B5'!B9 -> 236 | C10: =B10*$B$4 -> 5077.8065 | D10: =SUM(B10) -> 236 | E10: =D10*$B$4 -> 5077.8065 | F10: =SUM(D10) -> 236 | G10: =F10*$B$4 -> 5077.8065 | H10: =SUM(F10) -> 236 | I10: =H10*$B$4 -> 5077.8065 | J10: =SUM(H10) -> 236 | K10: =J10*$B$4 -> 5077.8065 | L10: =SUM(J10) -> 236 | M10: =L10*$B$4 -> 5077.8065 | N10: =SUM(L10) -> 236 | O10: =N10*$B$4 -> 5077.8065 | P10: =SUM(N10) -> 236 | Q10: =P10*$B$4 -> 5077.8065 | R10: =SUM(P10) -> 236 | S10: =R10*$B$4 -> 5077.8065 | T10: =SUM(R10) -> 236 | U10: =T10*$B$4 -> 5077.8065 | V10: =SUM(T10) -> 236 | W10: =V10*$B$4 -> 5077.8065 | X10: =SUM(Y10/73370) -> 0.76129032 | Y10: =SUM(C10+E10+G10+I10+K10+M10+O10+Q10+S10+U10+W10) -> 55855.871 | Z10: ='B5'!C9 -> 239 | AA10: =SUM(Z10*$Z$4) -> 2390 | AB10: =SUM(Z10) -> 239 | AC10: =SUM(AB10*$Z$4) -> 2390 | AD10: =SUM(AB10) -> 239 | AE10: =SUM(AD10*$Z$4) -> 2390 | AF10: =SUM(AD10) -> 239 | AG10: =SUM(AF10*$Z$4) -> 2390 | AH10: =SUM(AF10) -> 239 | AI10: =SUM(AH10*$Z$4) -> 2390 | AJ10: =SUM(AH10) -> 239 | AK10: =SUM(AJ10*$Z$4) -> 2390 | AL10: =SUM(AJ10) -> 239 | AM10: =SUM(AL10*$Z$4) -> 2390 | AN10: =SUM(AO10/19600) -> 0.85357143 | AO10: =SUM(AA10+AC10+AE10+AG10+AI10+AK10+AM10) -> 16730 | AQ10: =SUM(AR10/92970) -> 0.78074509 | AR10: =Y10+AO10 -> 72585.871 | AS10: =SUM(AR10-AR9-AT10) -> -920.03226 | AV10: =IF(AT10>0,AU10,AV9) -> 0.89 | AW10: =-SUM('B5'!AI9) -> -113 | AX10: =-SUM(AW10-AS10) -> -807.03226 | AY10: =SUM(AX10+AW10) -> -920.03226 | AZ10: =ELEC!A8 -> 0 | BA10: ='General information '!D9 -> 17 | BB10: =SUM('General information '!E9) -> 0.64 | BC10: =IF(AR9>=AR10,0,1) -> 0 | BD10: 19222 | BE10: =(305/1185)*ELEC!Q9 -> 0 | BG10: =#REF!-BE10 -> #REF! | BH10: 16 | BI10: 7 | BJ10: =AX10/BI10 -> -115.29032 | BK10: =GEN!AF7 -> 0.146375
A11: =ELEC!C9 -> 44932 | B11: ='B5'!B10 -> 233 | C11: =B11*$B$4 -> 5013.2581 | D11: =SUM(B11) -> 233 | E11: =D11*$B$4 -> 5013.2581 | F11: =SUM(D11) -> 233 | G11: =F11*$B$4 -> 5013.2581 | H11: =SUM(F11) -> 233 | I11: =H11*$B$4 -> 5013.2581 | J11: =SUM(H11) -> 233 | K11: =J11*$B$4 -> 5013.2581 | L11: =SUM(J11) -> 233 | M11: =L11*$B$4 -> 5013.2581 | N11: =SUM(L11) -> 233 | O11: =N11*$B$4 -> 5013.2581 | P11: =SUM(N11) -> 233 | Q11: =P11*$B$4 -> 5013.2581 | R11: =SUM(P11) -> 233 | S11: =R11*$B$4 -> 5013.2581 | T11: =SUM(R11) -> 233 | U11: =T11*$B$4 -> 5013.2581 | V11: =SUM(T11) -> 233 | W11: =V11*$B$4 -> 5013.2581 | X11: =SUM(Y11/73370) -> 0.7516129 | Y11: =SUM(C11+E11+G11+I11+K11+M11+O11+Q11+S11+U11+W11) -> 55145.839 | Z11: ='B5'!C10 -> 239 | AA11: =SUM(Z11*$Z$4) -> 2390 | AB11: =SUM(Z11) -> 239 | AC11: =SUM(AB11*$Z$4) -> 2390 | AD11: =SUM(AB11) -> 239 | AE11: =SUM(AD11*$Z$4) -> 2390 | AF11: =SUM(AD11) -> 239 | AG11: =SUM(AF11*$Z$4) -> 2390 | AH11: =SUM(AF11) -> 239 | AI11: =SUM(AH11*$Z$4) -> 2390 | AJ11: =SUM(AH11) -> 239 | AK11: =SUM(AJ11*$Z$4) -> 2390 | AL11: =SUM(AJ11) -> 239 | AM11: =SUM(AL11*$Z$4) -> 2390 | AN11: =SUM(AO11/19600) -> 0.85357143 | AO11: =SUM(AA11+AC11+AE11+AG11+AI11+AK11+AM11) -> 16730 | AQ11: =SUM(AR11/92970) -> 0.77310787 | AR11: =Y11+AO11 -> 71875.839 | AS11: =SUM(AR11-AR10-AT11) -> -710.03226 | AV11: =IF(AT11>0,AU11,AV10) -> 0.89 | AW11: =-SUM('B5'!AI10) -> 0 | AX11: =-SUM(AW11-AS11) -> -710.03226 | AY11: =SUM(AX11+AW11) -> -710.03226 | AZ11: =ELEC!A9 -> 0 | BA11: ='General information '!D10 -> 0 | BB11: =SUM('General information '!E10) -> 0 | BC11: =IF(AR10>=AR11,0,1) -> 0 | BD11: 19222 | BE11: =(305/1185)*ELEC!Q10 -> 0 | BG11: =#REF!-BE11 -> #REF! | BH11: 16.5 | BI11: 9.3 | BJ11: =AX11/BI11 -> -76.347555
A12: =ELEC!C10 -> 44933 | B12: ='B5'!B11 -> 233 | C12: =B12*$B$4 -> 5013.2581 | D12: =SUM(B12) -> 233 | E12: =D12*$B$4 -> 5013.2581 | F12: =SUM(D12) -> 233 | G12: =F12*$B$4 -> 5013.2581 | H12: =SUM(F12) -> 233 | I12: =H12*$B$4 -> 5013.2581 | J12: =SUM(H12) -> 233 | K12: =J12*$B$4 -> 5013.2581 | L12: =SUM(J12) -> 233 | M12: =L12*$B$4 -> 5013.2581 | N12: =SUM(L12) -> 233 | O12: =N12*$B$4 -> 5013.2581 | P12: =SUM(N12) -> 233 | Q12: =P12*$B$4 -> 5013.2581 | R12: =SUM(P12) -> 233 | S12: =R12*$B$4 -> 5013.2581 | T12: =SUM(R12) -> 233 | U12: =T12*$B$4 -> 5013.2581 | V12: =SUM(T12) -> 233 | W12: =V12*$B$4 -> 5013.2581 | X12: =SUM(Y12/73370) -> 0.7516129 | Y12: =SUM(C12+E12+G12+I12+K12+M12+O12+Q12+S12+U12+W12) -> 55145.839 | Z12: ='B5'!C11 -> 239 | AA12: =SUM(Z12*$Z$4) -> 2390 | AB12: =SUM(Z12) -> 239 | AC12: =SUM(AB12*$Z$4) -> 2390 | AD12: =SUM(AB12) -> 239 | AE12: =SUM(AD12*$Z$4) -> 2390 | AF12: =SUM(AD12) -> 239 | AG12: =SUM(AF12*$Z$4) -> 2390 | AH12: =SUM(AF12) -> 239 | AI12: =SUM(AH12*$Z$4) -> 2390 | AJ12: =SUM(AH12) -> 239 | AK12: =SUM(AJ12*$Z$4) -> 2390 | AL12: =SUM(AJ12) -> 239 | AM12: =SUM(AL12*$Z$4) -> 2390 | AN12: =SUM(AO12/19600) -> 0.85357143 | AO12: =SUM(AA12+AC12+AE12+AG12+AI12+AK12+AM12) -> 16730 | AQ12: =SUM(AR12/92970) -> 0.77310787 | AR12: =Y12+AO12 -> 71875.839 | AS12: =SUM(AR12-AR11-AT12) -> 0 | AV12: =IF(AT12>0,AU12,AV11) -> 0.89 | AW12: =-SUM('B5'!AI11) -> 0 | AX12: =-SUM(AW12-AS12) -> 0 | AY12: =SUM(AX12+AW12) -> 0 | AZ12: =ELEC!A10 -> 0 | BA12: ='General information '!D11 -> 0 | BB12: =SUM('General information '!E11) -> 0 | BC12: =IF(AR11>=AR12,0,1) -> 0 | BD12: 19222 | BE12: =(305/1185)*ELEC!Q11 -> 607.94093 | BG12: =#REF!-BE12 -> #REF! | BH12: 15.5 | BI12: 3.7 | BJ12: =AX12/BI12 -> 0
A13: =ELEC!C11 -> 44934 | B13: ='B5'!B12 -> 230 | C13: =B13*$B$4 -> 4948.7097 | D13: =SUM(B13) -> 230 | E13: =D13*$B$4 -> 4948.7097 | F13: =SUM(D13) -> 230 | G13: =F13*$B$4 -> 4948.7097 | H13: =SUM(F13) -> 230 | I13: =H13*$B$4 -> 4948.7097 | J13: =SUM(H13) -> 230 | K13: =J13*$B$4 -> 4948.7097 | L13: =SUM(J13) -> 230 | M13: =L13*$B$4 -> 4948.7097 | N13: =SUM(L13) -> 230 | O13: =N13*$B$4 -> 4948.7097 | P13: =SUM(N13) -> 230 | Q13: =P13*$B$4 -> 4948.7097 | R13: =SUM(P13) -> 230 | S13: =R13*$B$4 -> 4948.7097 | T13: =SUM(R13) -> 230 | U13: =T13*$B$4 -> 4948.7097 | V13: =SUM(T13) -> 230 | W13: =V13*$B$4 -> 4948.7097 | X13: =SUM(Y13/73370) -> 0.74193548 | Y13: =SUM(C13+E13+G13+I13+K13+M13+O13+Q13+S13+U13+W13) -> 54435.806 | Z13: ='B5'!C12 -> 236 | AA13: =SUM(Z13*$Z$4) -> 2360 | AB13: =SUM(Z13) -> 236 | AC13: =SUM(AB13*$Z$4) -> 2360 | AD13: =SUM(AB13) -> 236 | AE13: =SUM(AD13*$Z$4) -> 2360 | AF13: =SUM(AD13) -> 236 | AG13: =SUM(AF13*$Z$4) -> 2360 | AH13: =SUM(AF13) -> 236 | AI13: =SUM(AH13*$Z$4) -> 2360 | AJ13: =SUM(AH13) -> 236 | AK13: =SUM(AJ13*$Z$4) -> 2360 | AL13: =SUM(AJ13) -> 236 | AM13: =SUM(AL13*$Z$4) -> 2360 | AN13: =SUM(AO13/19600) -> 0.84285714 | AO13: =SUM(AA13+AC13+AE13+AG13+AI13+AK13+AM13) -> 16520 | AQ13: =SUM(AR13/92970) -> 0.76321186 | AR13: =Y13+AO13 -> 70955.806 | AS13: =SUM(AR13-AR12-AT13) -> -920.03226 | AV13: =IF(AT13>0,AU13,AV12) -> 0.89 | AW13: =-SUM('B5'!AI12) -> -180 | AX13: =-SUM(AW13-AS13) -> -740.03226 | AY13: =SUM(AX13+AW13) -> -920.03226 | AZ13: =ELEC!A11 -> 0 | BA13: ='General information '!D12 -> 17 | BB13: =SUM('General information '!E12) -> 0.62 | BC13: =IF(AR12>=AR13,0,1) -> 0 | BD13: 19222 | BE13: =(305/1185)*ELEC!Q12 -> 806.38397 | BG13: =#REF!-BE13 -> #REF! | BI13: 5 | BJ13: =AX13/BI13 -> -148.00645 | BK13: =GEN!AF10 -> 0.12302083
A14: =ELEC!C12 -> 44935 | B14: ='B5'!B13 -> 228 | C14: =B14*$B$4 -> 4905.6774 | D14: =SUM(B14) -> 228 | E14: =D14*$B$4 -> 4905.6774 | F14: =SUM(D14) -> 228 | G14: =F14*$B$4 -> 4905.6774 | H14: =SUM(F14) -> 228 | I14: =H14*$B$4 -> 4905.6774 | J14: =SUM(H14) -> 228 | K14: =J14*$B$4 -> 4905.6774 | L14: =SUM(J14) -> 228 | M14: =L14*$B$4 -> 4905.6774 | N14: =SUM(L14) -> 228 | O14: =N14*$B$4 -> 4905.6774 | P14: =SUM(N14) -> 228 | Q14: =P14*$B$4 -> 4905.6774 | R14: =SUM(P14) -> 228 | S14: =R14*$B$4 -> 4905.6774 | T14: =SUM(R14) -> 228 | U14: =T14*$B$4 -> 4905.6774 | V14: =SUM(T14) -> 228 | W14: =V14*$B$4 -> 4905.6774 | X14: =SUM(Y14/73370) -> 0.73548387 | Y14: =SUM(C14+E14+G14+I14+K14+M14+O14+Q14+S14+U14+W14) -> 53962.452 | Z14: ='B5'!C13 -> 234 | AA14: =SUM(Z14*$Z$4) -> 2340 | AB14: =SUM(Z14) -> 234 | AC14: =SUM(AB14*$Z$4) -> 2340 | AD14: =SUM(AB14) -> 234 | AE14: =SUM(AD14*$Z$4) -> 2340 | AF14: =SUM(AD14) -> 234 | AG14: =SUM(AF14*$Z$4) -> 2340 | AH14: =SUM(AF14) -> 234 | AI14: =SUM(AH14*$Z$4) -> 2340 | AJ14: =SUM(AH14) -> 234 | AK14: =SUM(AJ14*$Z$4) -> 2340 | AL14: =SUM(AJ14) -> 234 | AM14: =SUM(AL14*$Z$4) -> 2340 | AN14: =SUM(AO14/19600) -> 0.83571429 | AO14: =SUM(AA14+AC14+AE14+AG14+AI14+AK14+AM14) -> 16380 | AQ14: =SUM(AR14/92970) -> 0.75661452 | AR14: =Y14+AO14 -> 70342.452 | AS14: =SUM(AR14-AR13-AT14) -> -613.35484 | AV14: =IF(AT14>0,AU14,AV13) -> 0.89 | AW14: =-SUM('B5'!AI13) -> -276.5 | AX14: =-SUM(AW14-AS14) -> -336.85484 | AY14: =SUM(AX14+AW14) -> -613.35484 | AZ14: =ELEC!A12 -> 0 | BA14: ='General information '!D13 -> 16 | BB14: =SUM('General information '!E13) -> 0.6 | BC14: =IF(AR13>=AR14,0,1) -> 0 | BD14: 19222 | BE14: =(305/1185)*ELEC!Q13 -> 761.34177 | BG14: =#REF!-BE14 -> #REF! | BI14: 3 | BJ14: =AX14/BI14 -> -112.28495 | BK14: =GEN!AF11 -> 0.13054167
A15: =ELEC!C13 -> 44936 | B15: ='B5'!B14 -> 225 | C15: =B15*$B$4 -> 4841.129 | D15: =SUM(B15) -> 225 | E15: =D15*$B$4 -> 4841.129 | F15: =SUM(D15) -> 225 | G15: =F15*$B$4 -> 4841.129 | H15: =SUM(F15) -> 225 | I15: =H15*$B$4 -> 4841.129 | J15: =SUM(H15) -> 225 | K15: =J15*$B$4 -> 4841.129 | L15: =SUM(J15) -> 225 | M15: =L15*$B$4 -> 4841.129 | N15: =SUM(L15) -> 225 | O15: =N15*$B$4 -> 4841.129 | P15: =SUM(N15) -> 225 | Q15: =P15*$B$4 -> 4841.129 | R15: =SUM(P15) -> 225 | S15: =R15*$B$4 -> 4841.129 | T15: =SUM(R15) -> 225 | U15: =T15*$B$4 -> 4841.129 | V15: =SUM(T15) -> 225 | W15: =V15*$B$4 -> 4841.129 | X15: =SUM(Y15/73370) -> 0.72580645 | Y15: =SUM(C15+E15+G15+I15+K15+M15+O15+Q15+S15+U15+W15) -> 53252.419 | Z15: ='B5'!C14 -> 231 | AA15: =SUM(Z15*$Z$4) -> 2310 | AB15: =SUM(Z15) -> 231 | AC15: =SUM(AB15*$Z$4) -> 2310 | AD15: =SUM(AB15) -> 231 | AE15: =SUM(AD15*$Z$4) -> 2310 | AF15: =SUM(AD15) -> 231 | AG15: =SUM(AF15*$Z$4) -> 2310 | AH15: =SUM(AF15) -> 231 | AI15: =SUM(AH15*$Z$4) -> 2310 | AJ15: =SUM(AH15) -> 231 | AK15: =SUM(AJ15*$Z$4) -> 2310 | AL15: =SUM(AJ15) -> 231 | AM15: =SUM(AL15*$Z$4) -> 2310 | AN15: =SUM(AO15/19600) -> 0.825 | AO15: =SUM(AA15+AC15+AE15+AG15+AI15+AK15+AM15) -> 16170 | AQ15: =SUM(AR15/92970) -> 0.7467185 | AR15: =Y15+AO15 -> 69422.419 | AS15: =SUM(AR15-AR14-AT15) -> -920.03226 | AV15: =IF(AT15>0,AU15,AV14) -> 0.89 | AW15: =-SUM('B5'!AI14) -> -67 | AX15: =-SUM(AW15-AS15) -> -853.03226 | AY15: =SUM(AX15+AW15) -> -920.03226 | AZ15: =ELEC!A13 -> 0 | BA15: ='General information '!D14 -> 16 | BB15: =SUM('General information '!E14) -> 0.44 | BC15: =IF(AR14>=AR15,0,1) -> 0 | BD15: 19222 | BE15: =(305/1185)*ELEC!Q14 -> 375.00844 | BG15: =#REF!-BE15 -> #REF! | BI15: 4 | BJ15: =AX15/BI15 -> -213.25806 | BK15: =GEN!AF12 -> 0.14221154
A16: =ELEC!C14 -> 44937 | B16: ='B5'!B15 -> 222 | C16: =B16*$B$4 -> 4776.5806 | D16: =SUM(B16) -> 222 | E16: =D16*$B$4 -> 4776.5806 | F16: =SUM(D16) -> 222 | G16: =F16*$B$4 -> 4776.5806 | H16: =SUM(F16) -> 222 | I16: =H16*$B$4 -> 4776.5806 | J16: =SUM(H16) -> 222 | K16: =J16*$B$4 -> 4776.5806 | L16: =SUM(J16) -> 222 | M16: =L16*$B$4 -> 4776.5806 | N16: =SUM(L16) -> 222 | O16: =N16*$B$4 -> 4776.5806 | P16: =SUM(N16) -> 222 | Q16: =P16*$B$4 -> 4776.5806 | R16: =SUM(P16) -> 222 | S16: =R16*$B$4 -> 4776.5806 | T16: =SUM(R16) -> 222 | U16: =T16*$B$4 -> 4776.5806 | V16: =SUM(T16) -> 222 | W16: =V16*$B$4 -> 4776.5806 | X16: =SUM(Y16/73370) -> 0.71612903 | Y16: =SUM(C16+E16+G16+I16+K16+M16+O16+Q16+S16+U16+W16) -> 52542.387 | Z16: ='B5'!C15 -> 228 | AA16: =SUM(Z16*$Z$4) -> 2280 | AB16: =SUM(Z16) -> 228 | AC16: =SUM(AB16*$Z$4) -> 2280 | AD16: =SUM(AB16) -> 228 | AE16: =SUM(AD16*$Z$4) -> 2280 | AF16: =SUM(AD16) -> 228 | AG16: =SUM(AF16*$Z$4) -> 2280 | AH16: =SUM(AF16) -> 228 | AI16: =SUM(AH16*$Z$4) -> 2280 | AJ16: =SUM(AH16) -> 228 | AK16: =SUM(AJ16*$Z$4) -> 2280 | AL16: =SUM(AJ16) -> 228 | AM16: =SUM(AL16*$Z$4) -> 2280 | AN16: =SUM(AO16/19600) -> 0.81428571 | AO16: =SUM(AA16+AC16+AE16+AG16+AI16+AK16+AM16) -> 15960 | AQ16: =SUM(AR16/92970) -> 0.73682249 | AR16: =Y16+AO16 -> 68502.387 | AS16: =SUM(AR16-AR15-AT16) -> -920.03226 | AV16: =IF(AT16>0,AU16,AV15) -> 0.89 | AW16: =-SUM('B5'!AI15) -> -205 | AX16: =-SUM(AW16-AS16) -> -715.03226 | AY16: =SUM(AX16+AW16) -> -920.03226 | AZ16: =ELEC!A14 -> 0 | BA16: ='General information '!D15 -> 16 | BB16: =SUM('General information '!E15) -> 0.49 | BC16: =IF(AR15>=AR16,0,1) -> 0 | BD16: 19222 | BE16: =(305/1185)*ELEC!Q15 -> 834.18143 | BG16: =#REF!-BE16 -> #REF! | BI16: 3 | BJ16: =AX16/BI16 -> -238.34409 | BK16: =GEN!AF13 -> 0.10118056
A17: =ELEC!C15 -> 44938 | B17: ='B5'!B16 -> 217.5 | C17: =B17*$B$4 -> 4679.7581 | D17: =SUM(B17) -> 217.5 | E17: =D17*$B$4 -> 4679.7581 | F17: =SUM(D17) -> 217.5 | G17: =F17*$B$4 -> 4679.7581 | H17: =SUM(F17) -> 217.5 | I17: =H17*$B$4 -> 4679.7581 | J17: =SUM(H17) -> 217.5 | K17: =J17*$B$4 -> 4679.7581 | L17: =SUM(J17) -> 217.5 | M17: =L17*$B$4 -> 4679.7581 | N17: =SUM(L17) -> 217.5 | O17: =N17*$B$4 -> 4679.7581 | P17: =SUM(N17) -> 217.5 | Q17: =P17*$B$4 -> 4679.7581 | R17: =SUM(P17) -> 217.5 | S17: =R17*$B$4 -> 4679.7581 | T17: =SUM(R17) -> 217.5 | U17: =T17*$B$4 -> 4679.7581 | V17: =SUM(T17) -> 217.5 | W17: =V17*$B$4 -> 4679.7581 | X17: =SUM(Y17/73370) -> 0.7016129 | Y17: =SUM(C17+E17+G17+I17+K17+M17+O17+Q17+S17+U17+W17) -> 51477.339 | Z17: ='B5'!C16 -> 223.5 | AA17: =SUM(Z17*$Z$4) -> 2235 | AB17: =SUM(Z17) -> 223.5 | AC17: =SUM(AB17*$Z$4) -> 2235 | AD17: =SUM(AB17) -> 223.5 | AE17: =SUM(AD17*$Z$4) -> 2235 | AF17: =SUM(AD17) -> 223.5 | AG17: =SUM(AF17*$Z$4) -> 2235 | AH17: =SUM(AF17) -> 223.5 | AI17: =SUM(AH17*$Z$4) -> 2235 | AJ17: =SUM(AH17) -> 223.5 | AK17: =SUM(AJ17*$Z$4) -> 2235 | AL17: =SUM(AJ17) -> 223.5 | AM17: =SUM(AL17*$Z$4) -> 2235 | AN17: =SUM(AO17/19600) -> 0.79821429 | AO17: =SUM(AA17+AC17+AE17+AG17+AI17+AK17+AM17) -> 15645 | AQ17: =SUM(AR17/92970) -> 0.72197847 | AR17: =Y17+AO17 -> 67122.339 | AS17: =SUM(AR17-AR16-AT17) -> -1380.0484 | AV17: =IF(AT17>0,AU17,AV16) -> 0.89 | AW17: =-SUM('B5'!AI16) -> -141.5 | AX17: =-SUM(AW17-AS17) -> -1238.5484 | AY17: =SUM(AX17+AW17) -> -1380.0484 | AZ17: =ELEC!A15 -> 0 | BA17: ='General information '!D16 -> 0 | BB17: =SUM('General information '!E16) -> 0 | BC17: =IF(AR16>=AR17,0,1) -> 0 | BD17: 19222 | BE17: =(305/1185)*ELEC!Q16 -> 0 | BG17: =#REF!-BE17 -> #REF! | BI17: 4 | BJ17: =AX17/BI17 -> -309.6371 | BK17: =GEN!AF14 -> 0.1446875
A18: =ELEC!C16 -> 44939 | B18: ='B5'!B17 -> 217.5 | C18: =B18*$B$4 -> 4679.7581 | D18: =SUM(B18) -> 217.5 | E18: =D18*$B$4 -> 4679.7581 | F18: =SUM(D18) -> 217.5 | G18: =F18*$B$4 -> 4679.7581 | H18: =SUM(F18) -> 217.5 | I18: =H18*$B$4 -> 4679.7581 | J18: =SUM(H18) -> 217.5 | K18: =J18*$B$4 -> 4679.7581 | L18: =SUM(J18) -> 217.5 | M18: =L18*$B$4 -> 4679.7581 | N18: =SUM(L18) -> 217.5 | O18: =N18*$B$4 -> 4679.7581 | P18: =SUM(N18) -> 217.5 | Q18: =P18*$B$4 -> 4679.7581 | R18: =SUM(P18) -> 217.5 | S18: =R18*$B$4 -> 4679.7581 | T18: =SUM(R18) -> 217.5 | U18: =T18*$B$4 -> 4679.7581 | V18: =SUM(T18) -> 217.5 | W18: =V18*$B$4 -> 4679.7581 | X18: =SUM(Y18/73370) -> 0.7016129 | Y18: =SUM(C18+E18+G18+I18+K18+M18+O18+Q18+S18+U18+W18) -> 51477.339 | Z18: ='B5'!C17 -> 223.5 | AA18: =SUM(Z18*$Z$4) -> 2235 | AB18: =SUM(Z18) -> 223.5 | AC18: =SUM(AB18*$Z$4) -> 2235 | AD18: =SUM(AB18) -> 223.5 | AE18: =SUM(AD18*$Z$4) -> 2235 | AF18: =SUM(AD18) -> 223.5 | AG18: =SUM(AF18*$Z$4) -> 2235 | AH18: =SUM(AF18) -> 223.5 | AI18: =SUM(AH18*$Z$4) -> 2235 | AJ18: =SUM(AH18) -> 223.5 | AK18: =SUM(AJ18*$Z$4) -> 2235 | AL18: =SUM(AJ18) -> 223.5 | AM18: =SUM(AL18*$Z$4) -> 2235 | AN18: =SUM(AO18/19600) -> 0.79821429 | AO18: =SUM(AA18+AC18+AE18+AG18+AI18+AK18+AM18) -> 15645 | AQ18: =SUM(AR18/92970) -> 0.72197847 | AR18: =Y18+AO18 -> 67122.339 | AS18: =SUM(AR18-AR17-AT18) -> 0 | AV18: =IF(AT18>0,AU18,AV17) -> 0.89 | AW18: =-SUM('B5'!AI17) -> 0 | AX18: =-SUM(AW18-AS18) -> 0 | AY18: =SUM(AX18+AW18) -> 0 | AZ18: =ELEC!A16 -> 0 | BA18: ='General information '!D17 -> 0 | BB18: =SUM('General information '!E17) -> 0 | BC18: =IF(AR17>=AR18,0,1) -> 0 | BD18: 19222 | BE18: =(305/1185)*ELEC!Q17 -> 0 | BG18: =#REF!-BE18 -> #REF! | BI18: 5 | BJ18: =AX18/BI18 -> 0
A19: =ELEC!C17 -> 44940 | B19: ='B5'!B18 -> 217.5 | C19: =B19*$B$4 -> 4679.7581 | D19: =SUM(B19) -> 217.5 | E19: =D19*$B$4 -> 4679.7581 | F19: =SUM(D19) -> 217.5 | G19: =F19*$B$4 -> 4679.7581 | H19: =SUM(F19) -> 217.5 | I19: =H19*$B$4 -> 4679.7581 | J19: =SUM(H19) -> 217.5 | K19: =J19*$B$4 -> 4679.7581 | L19: =SUM(J19) -> 217.5 | M19: =L19*$B$4 -> 4679.7581 | N19: =SUM(L19) -> 217.5 | O19: =N19*$B$4 -> 4679.7581 | P19: =SUM(N19) -> 217.5 | Q19: =P19*$B$4 -> 4679.7581 | R19: =SUM(P19) -> 217.5 | S19: =R19*$B$4 -> 4679.7581 | T19: =SUM(R19) -> 217.5 | U19: =T19*$B$4 -> 4679.7581 | V19: =SUM(T19) -> 217.5 | W19: =V19*$B$4 -> 4679.7581 | X19: =SUM(Y19/73370) -> 0.7016129 | Y19: =SUM(C19+E19+G19+I19+K19+M19+O19+Q19+S19+U19+W19) -> 51477.339 | Z19: ='B5'!C18 -> 223.5 | AA19: =SUM(Z19*$Z$4) -> 2235 | AB19: =SUM(Z19) -> 223.5 | AC19: =SUM(AB19*$Z$4) -> 2235 | AD19: =SUM(AB19) -> 223.5 | AE19: =SUM(AD19*$Z$4) -> 2235 | AF19: =SUM(AD19) -> 223.5 | AG19: =SUM(AF19*$Z$4) -> 2235 | AH19: =SUM(AF19) -> 223.5 | AI19: =SUM(AH19*$Z$4) -> 2235 | AJ19: =SUM(AH19) -> 223.5 | AK19: =SUM(AJ19*$Z$4) -> 2235 | AL19: =SUM(AJ19) -> 223.5 | AM19: =SUM(AL19*$Z$4) -> 2235 | AN19: =SUM(AO19/19600) -> 0.79821429 | AO19: =SUM(AA19+AC19+AE19+AG19+AI19+AK19+AM19) -> 15645 | AQ19: =SUM(AR19/92970) -> 0.72197847 | AR19: =Y19+AO19 -> 67122.339 | AS19: =SUM(AR19-AR18-AT19) -> 0 | AV19: =IF(AT19>0,AU19,AV18) -> 0.89 | AW19: =-SUM('B5'!AI18) -> 0 | AX19: =-SUM(AW19-AS19) -> 0 | AY19: =SUM(AX19+AW19) -> 0 | AZ19: =ELEC!A17 -> 0 | BA19: ='General information '!D18 -> 15.5 | BB19: =SUM('General information '!E18) -> 0.63 | BC19: =IF(AR18>=AR19,0,1) -> 0 | BD19: 19222 | BE19: =(305/1185)*ELEC!Q18 -> 1054.2447 | BG19: =#REF!-BE19 -> #REF! | BI19: 6 | BJ19: =AX19/BI19 -> 0
A20: =ELEC!C18 -> 44941 | B20: ='B5'!B19 -> 232 | C20: =B20*$B$4 -> 4991.7419 | D20: =SUM(B20) -> 232 | E20: =D20*$B$4 -> 4991.7419 | F20: =SUM(D20) -> 232 | G20: =F20*$B$4 -> 4991.7419 | H20: =SUM(F20) -> 232 | I20: =H20*$B$4 -> 4991.7419 | J20: =SUM(H20) -> 232 | K20: =J20*$B$4 -> 4991.7419 | L20: =SUM(J20) -> 232 | M20: =L20*$B$4 -> 4991.7419 | N20: =SUM(L20) -> 232 | O20: =N20*$B$4 -> 4991.7419 | P20: =SUM(N20) -> 232 | Q20: =P20*$B$4 -> 4991.7419 | R20: =SUM(P20) -> 232 | S20: =R20*$B$4 -> 4991.7419 | T20: =SUM(R20) -> 232 | U20: =T20*$B$4 -> 4991.7419 | V20: =SUM(T20) -> 232 | W20: =V20*$B$4 -> 4991.7419 | X20: =SUM(Y20/73370) -> 0.7483871 | Y20: =SUM(C20+E20+G20+I20+K20+M20+O20+Q20+S20+U20+W20) -> 54909.161 | Z20: ='B5'!C19 -> 239 | AA20: =SUM(Z20*$Z$4) -> 2390 | AB20: =SUM(Z20) -> 239 | AC20: =SUM(AB20*$Z$4) -> 2390 | AD20: =SUM(AB20) -> 239 | AE20: =SUM(AD20*$Z$4) -> 2390 | AF20: =SUM(AD20) -> 239 | AG20: =SUM(AF20*$Z$4) -> 2390 | AH20: =SUM(AF20) -> 239 | AI20: =SUM(AH20*$Z$4) -> 2390 | AJ20: =SUM(AH20) -> 239 | AK20: =SUM(AJ20*$Z$4) -> 2390 | AL20: =SUM(AJ20) -> 239 | AM20: =SUM(AL20*$Z$4) -> 2390 | AN20: =SUM(AO20/19600) -> 0.85357143 | AO20: =SUM(AA20+AC20+AE20+AG20+AI20+AK20+AM20) -> 16730 | AQ20: =SUM(AR20/92970) -> 0.77056213 | AR20: =Y20+AO20 -> 71639.161 | AS20: =SUM(AR20-AR19-AT20) -> -1013.1774 | AT20: 5530 | AU20: 0.868 | AV20: =IF(AT20>0,AU20,AV19) -> 0.868 | AW20: =-SUM('B5'!AI19) -> -258 | AX20: =-SUM(AW20-AS20) -> -755.17742 | AY20: =SUM(AX20+AW20) -> -1013.1774 | AZ20: =ELEC!A18 -> 0 | BA20: ='General information '!D19 -> 15.5 | BB20: =SUM('General information '!E19) -> 0.7 | BC20: =IF(AR19>=AR20,0,1) -> 1 | BD20: 19222 | BE20: =(305/1185)*ELEC!Q19 -> 857.60338 | BG20: =#REF!-BE20 -> #REF! | BI20: 7 | BJ20: =AX20/BI20 -> -107.88249 | BK20: =GEN!AF17 -> 0.18285714
A21: =ELEC!C19 -> 44942 | B21: ='B5'!B20 -> 229 | C21: =B21*$B$4 -> 4927.1935 | D21: =SUM(B21) -> 229 | E21: =D21*$B$4 -> 4927.1935 | F21: =SUM(D21) -> 229 | G21: =F21*$B$4 -> 4927.1935 | H21: =SUM(F21) -> 229 | I21: =H21*$B$4 -> 4927.1935 | J21: =SUM(H21) -> 229 | K21: =J21*$B$4 -> 4927.1935 | L21: =SUM(J21) -> 229 | M21: =L21*$B$4 -> 4927.1935 | N21: =SUM(L21) -> 229 | O21: =N21*$B$4 -> 4927.1935 | P21: =SUM(N21) -> 229 | Q21: =P21*$B$4 -> 4927.1935 | R21: =SUM(P21) -> 229 | S21: =R21*$B$4 -> 4927.1935 | T21: =SUM(R21) -> 229 | U21: =T21*$B$4 -> 4927.1935 | V21: =SUM(T21) -> 229 | W21: =V21*$B$4 -> 4927.1935 | X21: =SUM(Y21/73370) -> 0.73870968 | Y21: =SUM(C21+E21+G21+I21+K21+M21+O21+Q21+S21+U21+W21) -> 54199.129 | Z21: ='B5'!C20 -> 235 | AA21: =SUM(Z21*$Z$4) -> 2350 | AB21: =SUM(Z21) -> 235 | AC21: =SUM(AB21*$Z$4) -> 2350 | AD21: =SUM(AB21) -> 235 | AE21: =SUM(AD21*$Z$4) -> 2350 | AF21: =SUM(AD21) -> 235 | AG21: =SUM(AF21*$Z$4) -> 2350 | AH21: =SUM(AF21) -> 235 | AI21: =SUM(AH21*$Z$4) -> 2350 | AJ21: =SUM(AH21) -> 235 | AK21: =SUM(AJ21*$Z$4) -> 2350 | AL21: =SUM(AJ21) -> 235 | AM21: =SUM(AL21*$Z$4) -> 2350 | AN21: =SUM(AO21/19600) -> 0.83928571 | AO21: =SUM(AA21+AC21+AE21+AG21+AI21+AK21+AM21) -> 16450 | AQ21: =SUM(AR21/92970) -> 0.75991319 | AR21: =Y21+AO21 -> 70649.129 | AS21: =SUM(AR21-AR20-AT21) -> -990.03226 | AV21: =IF(AT21>0,AU21,AV20) -> 0.868 | AW21: =-SUM('B5'!AI20) -> -182 | AX21: =-SUM(AW21-AS21) -> -808.03226 | AY21: =SUM(AX21+AW21) -> -990.03226 | AZ21: =ELEC!A19 -> 0 | BA21: ='General information '!D20 -> 16 | BB21: =SUM('General information '!E20) -> 0.7 | BC21: =IF(AR20>=AR21,0,1) -> 0 | BD21: 19222 | BE21: =(305/1185)*ELEC!Q20 -> 816.67932 | BG21: =#REF!-BE21 -> #REF! | BI21: 8 | BJ21: =AX21/BI21 -> -101.00403 | BK21: =GEN!AF18 -> 0.16019231
A22: =ELEC!C20 -> 44943 | B22: ='B5'!B21 -> 224 | C22: =B22*$B$4 -> 4819.6129 | D22: =SUM(B22) -> 224 | E22: =D22*$B$4 -> 4819.6129 | F22: =SUM(D22) -> 224 | G22: =F22*$B$4 -> 4819.6129 | H22: =SUM(F22) -> 224 | I22: =H22*$B$4 -> 4819.6129 | J22: =SUM(H22) -> 224 | K22: =J22*$B$4 -> 4819.6129 | L22: =SUM(J22) -> 224 | M22: =L22*$B$4 -> 4819.6129 | N22: =SUM(L22) -> 224 | O22: =N22*$B$4 -> 4819.6129 | P22: =SUM(N22) -> 224 | Q22: =P22*$B$4 -> 4819.6129 | R22: =SUM(P22) -> 224 | S22: =R22*$B$4 -> 4819.6129 | T22: =SUM(R22) -> 224 | U22: =T22*$B$4 -> 4819.6129 | V22: =SUM(T22) -> 224 | W22: =V22*$B$4 -> 4819.6129 | X22: =SUM(Y22/73370) -> 0.72258065 | Y22: =SUM(C22+E22+G22+I22+K22+M22+O22+Q22+S22+U22+W22) -> 53015.742 | Z22: ='B5'!C21 -> 230 | AA22: =SUM(Z22*$Z$4) -> 2300 | AB22: =SUM(Z22) -> 230 | AC22: =SUM(AB22*$Z$4) -> 2300 | AD22: =SUM(AB22) -> 230 | AE22: =SUM(AD22*$Z$4) -> 2300 | AF22: =SUM(AD22) -> 230 | AG22: =SUM(AF22*$Z$4) -> 2300 | AH22: =SUM(AF22) -> 230 | AI22: =SUM(AH22*$Z$4) -> 2300 | AJ22: =SUM(AH22) -> 230 | AK22: =SUM(AJ22*$Z$4) -> 2300 | AL22: =SUM(AJ22) -> 230 | AM22: =SUM(AL22*$Z$4) -> 2300 | AN22: =SUM(AO22/19600) -> 0.82142857 | AO22: =SUM(AA22+AC22+AE22+AG22+AI22+AK22+AM22) -> 16100 | AQ22: =SUM(AR22/92970) -> 0.74341983 | AR22: =Y22+AO22 -> 69115.742 | AS22: =SUM(AR22-AR21-AT22) -> -1533.3871 | AV22: =IF(AT22>0,AU22,AV21) -> 0.868 | AW22: =-SUM('B5'!AI21) -> -185 | AX22: =-SUM(AW22-AS22) -> -1348.3871 | AY22: =SUM(AX22+AW22) -> -1533.3871 | AZ22: =ELEC!A20 -> 0 | BA22: ='General information '!D21 -> 16 | BB22: =SUM('General information '!E21) -> 0.65 | BC22: =IF(AR21>=AR22,0,1) -> 0 | BD22: 19222 | BE22: =(305/1185)*ELEC!Q21 -> 921.4346 | BG22: =#REF!-BE22 -> #REF! | BI22: 9 | BJ22: =AX22/BI22 -> -149.82079 | BK22: =GEN!AF19 -> 0.1983125
A23: =ELEC!C21 -> 44944 | B23: ='B5'!B22 -> 240 | C23: =B23*$B$4 -> 5163.871 | D23: =SUM(B23) -> 240 | E23: =D23*$B$4 -> 5163.871 | F23: =SUM(D23) -> 240 | G23: =F23*$B$4 -> 5163.871 | H23: =SUM(F23) -> 240 | I23: =H23*$B$4 -> 5163.871 | J23: =SUM(H23) -> 240 | K23: =J23*$B$4 -> 5163.871 | L23: =SUM(J23) -> 240 | M23: =L23*$B$4 -> 5163.871 | N23: =SUM(L23) -> 240 | O23: =N23*$B$4 -> 5163.871 | P23: =SUM(N23) -> 240 | Q23: =P23*$B$4 -> 5163.871 | R23: =SUM(P23) -> 240 | S23: =R23*$B$4 -> 5163.871 | T23: =SUM(R23) -> 240 | U23: =T23*$B$4 -> 5163.871 | V23: =SUM(T23) -> 240 | W23: =V23*$B$4 -> 5163.871 | X23: =SUM(Y23/73370) -> 0.77419355 | Y23: =SUM(C23+E23+G23+I23+K23+M23+O23+Q23+S23+U23+W23) -> 56802.581 | Z23: ='B5'!C22 -> 246 | AA23: =SUM(Z23*$Z$4) -> 2460 | AB23: =SUM(Z23) -> 246 | AC23: =SUM(AB23*$Z$4) -> 2460 | AD23: =SUM(AB23) -> 246 | AE23: =SUM(AD23*$Z$4) -> 2460 | AF23: =SUM(AD23) -> 246 | AG23: =SUM(AF23*$Z$4) -> 2460 | AH23: =SUM(AF23) -> 246 | AI23: =SUM(AH23*$Z$4) -> 2460 | AJ23: =SUM(AH23) -> 246 | AK23: =SUM(AJ23*$Z$4) -> 2460 | AL23: =SUM(AJ23) -> 246 | AM23: =SUM(AL23*$Z$4) -> 2460 | AN23: =SUM(AO23/19600) -> 0.87857143 | AO23: =SUM(AA23+AC23+AE23+AG23+AI23+AK23+AM23) -> 17220 | AQ23: =SUM(AR23/92970) -> 0.79619857 | AR23: =Y23+AO23 -> 74022.581 | AS23: =SUM(AR23-AR22-AT23) -> -623.16129 | AT23: 5530 | AU23: 0.883 | AV23: =IF(AT23>0,AU23,AV22) -> 0.883 | AW23: =-SUM('B5'!AI22) -> -143 | AX23: =-SUM(AW23-AS23) -> -480.16129 | AY23: =SUM(AX23+AW23) -> -623.16129 | AZ23: =ELEC!A21 -> 0 | BA23: ='General information '!D22 -> 16.5 | BB23: =SUM('General information '!E22) -> 0.68 | BC23: =IF(AR22>=AR23,0,1) -> 1 | BD23: 19222 | BE23: =(305/1185)*ELEC!Q22 -> 846.79325 | BG23: =#REF!-BE23 -> #REF! | BI23: 10 | BJ23: =AX23/BI23 -> -48.016129 | BK23: =GEN!AF20 -> 0.15982143
A24: =ELEC!C22 -> 44945 | B24: ='B5'!B23 -> 236 | C24: =B24*$B$4 -> 5077.8065 | D24: =SUM(B24) -> 236 | E24: =D24*$B$4 -> 5077.8065 | F24: =SUM(D24) -> 236 | G24: =F24*$B$4 -> 5077.8065 | H24: =SUM(F24) -> 236 | I24: =H24*$B$4 -> 5077.8065 | J24: =SUM(H24) -> 236 | K24: =J24*$B$4 -> 5077.8065 | L24: =SUM(J24) -> 236 | M24: =L24*$B$4 -> 5077.8065 | N24: =SUM(L24) -> 236 | O24: =N24*$B$4 -> 5077.8065 | P24: =SUM(N24) -> 236 | Q24: =P24*$B$4 -> 5077.8065 | R24: =SUM(P24) -> 236 | S24: =R24*$B$4 -> 5077.8065 | T24: =SUM(R24) -> 236 | U24: =T24*$B$4 -> 5077.8065 | V24: =SUM(T24) -> 236 | W24: =V24*$B$4 -> 5077.8065 | X24: =SUM(Y24/73370) -> 0.76129032 | Y24: =SUM(C24+E24+G24+I24+K24+M24+O24+Q24+S24+U24+W24) -> 55855.871 | Z24: ='B5'!C23 -> 242 | AA24: =SUM(Z24*$Z$4) -> 2420 | AB24: =SUM(Z24) -> 242 | AC24: =SUM(AB24*$Z$4) -> 2420 | AD24: =SUM(AB24) -> 242 | AE24: =SUM(AD24*$Z$4) -> 2420 | AF24: =SUM(AD24) -> 242 | AG24: =SUM(AF24*$Z$4) -> 2420 | AH24: =SUM(AF24) -> 242 | AI24: =SUM(AH24*$Z$4) -> 2420 | AJ24: =SUM(AH24) -> 242 | AK24: =SUM(AJ24*$Z$4) -> 2420 | AL24: =SUM(AJ24) -> 242 | AM24: =SUM(AL24*$Z$4) -> 2420 | AN24: =SUM(AO24/19600) -> 0.86428571 | AO24: =SUM(AA24+AC24+AE24+AG24+AI24+AK24+AM24) -> 16940 | AQ24: =SUM(AR24/92970) -> 0.78300388 | AR24: =Y24+AO24 -> 72795.871 | AS24: =SUM(AR24-AR23-AT24) -> -1226.7097 | AV24: =IF(AT24>0,AU24,AV23) -> 0.883 | AW24: =-SUM('B5'!AI23) -> -150 | AX24: =-SUM(AW24-AS24) -> -1076.7097 | AY24: =SUM(AX24+AW24) -> -1226.7097 | AZ24: =ELEC!A22 -> 0 | BA24: ='General information '!D23 -> 16.5 | BB24: =SUM('General information '!E23) -> 0.41 | BC24: =IF(AR23>=AR24,0,1) -> 0 | BD24: 19222 | BE24: =(305/1185)*ELEC!Q23 -> 0 | BG24: =#REF!-BE24 -> #REF! | BI24: 11 | BJ24: =AX24/BI24 -> -97.882698 | BK24: =GEN!AF21 -> 0.18693182
A25: =ELEC!C23 -> 44946 | B25: ='B5'!B24 -> 236 | C25: =B25*$B$4 -> 5077.8065 | D25: =SUM(B25) -> 236 | E25: =D25*$B$4 -> 5077.8065 | F25: =SUM(D25) -> 236 | G25: =F25*$B$4 -> 5077.8065 | H25: =SUM(F25) -> 236 | I25: =H25*$B$4 -> 5077.8065 | J25: =SUM(H25) -> 236 | K25: =J25*$B$4 -> 5077.8065 | L25: =SUM(J25) -> 236 | M25: =L25*$B$4 -> 5077.8065 | N25: =SUM(L25) -> 236 | O25: =N25*$B$4 -> 5077.8065 | P25: =SUM(N25) -> 236 | Q25: =P25*$B$4 -> 5077.8065 | R25: =SUM(P25) -> 236 | S25: =R25*$B$4 -> 5077.8065 | T25: =SUM(R25) -> 236 | U25: =T25*$B$4 -> 5077.8065 | V25: =SUM(T25) -> 236 | W25: =V25*$B$4 -> 5077.8065 | X25: =SUM(Y25/73370) -> 0.76129032 | Y25: =SUM(C25+E25+G25+I25+K25+M25+O25+Q25+S25+U25+W25) -> 55855.871 | Z25: ='B5'!C24 -> 242 | AA25: =SUM(Z25*$Z$4) -> 2420 | AB25: =SUM(Z25) -> 242 | AC25: =SUM(AB25*$Z$4) -> 2420 | AD25: =SUM(AB25) -> 242 | AE25: =SUM(AD25*$Z$4) -> 2420 | AF25: =SUM(AD25) -> 242 | AG25: =SUM(AF25*$Z$4) -> 2420 | AH25: =SUM(AF25) -> 242 | AI25: =SUM(AH25*$Z$4) -> 2420 | AJ25: =SUM(AH25) -> 242 | AK25: =SUM(AJ25*$Z$4) -> 2420 | AL25: =SUM(AJ25) -> 242 | AM25: =SUM(AL25*$Z$4) -> 2420 | AN25: =SUM(AO25/19600) -> 0.86428571 | AO25: =SUM(AA25+AC25+AE25+AG25+AI25+AK25+AM25) -> 16940 | AQ25: =SUM(AR25/92970) -> 0.78300388 | AR25: =Y25+AO25 -> 72795.871 | AS25: =SUM(AR25-AR24-AT25) -> 0 | AV25: =IF(AT25>0,AU25,AV24) -> 0.883 | AW25: =-SUM('B5'!AI24) -> 0 | AX25: =-SUM(AW25-AS25) -> 0 | AY25: =SUM(AX25+AW25) -> 0 | AZ25: =ELEC!A23 -> 0 | BA25: ='General information '!D24 -> 0 | BB25: =SUM('General information '!E24) -> 0 | BC25: =IF(AR24>=AR25,0,1) -> 0 | BD25: 19222 | BE25: =(305/1185)*ELEC!Q24 -> 0 | BG25: =#REF!-BE25 -> #REF! | BI25: 12 | BJ25: =AX25/BI25 -> 0
A26: =ELEC!C24 -> 44947 | B26: ='B5'!B25 -> 236 | C26: =B26*$B$4 -> 5077.8065 | D26: =SUM(B26) -> 236 | E26: =D26*$B$4 -> 5077.8065 | F26: =SUM(D26) -> 236 | G26: =F26*$B$4 -> 5077.8065 | H26: =SUM(F26) -> 236 | I26: =H26*$B$4 -> 5077.8065 | J26: =SUM(H26) -> 236 | K26: =J26*$B$4 -> 5077.8065 | L26: =SUM(J26) -> 236 | M26: =L26*$B$4 -> 5077.8065 | N26: =SUM(L26) -> 236 | O26: =N26*$B$4 -> 5077.8065 | P26: =SUM(N26) -> 236 | Q26: =P26*$B$4 -> 5077.8065 | R26: =SUM(P26) -> 236 | S26: =R26*$B$4 -> 5077.8065 | T26: =SUM(R26) -> 236 | U26: =T26*$B$4 -> 5077.8065 | V26: =SUM(T26) -> 236 | W26: =V26*$B$4 -> 5077.8065 | X26: =SUM(Y26/73370) -> 0.76129032 | Y26: =SUM(C26+E26+G26+I26+K26+M26+O26+Q26+S26+U26+W26) -> 55855.871 | Z26: ='B5'!C25 -> 242 | AA26: =SUM(Z26*$Z$4) -> 2420 | AB26: =SUM(Z26) -> 242 | AC26: =SUM(AB26*$Z$4) -> 2420 | AD26: =SUM(AB26) -> 242 | AE26: =SUM(AD26*$Z$4) -> 2420 | AF26: =SUM(AD26) -> 242 | AG26: =SUM(AF26*$Z$4) -> 2420 | AH26: =SUM(AF26) -> 242 | AI26: =SUM(AH26*$Z$4) -> 2420 | AJ26: =SUM(AH26) -> 242 | AK26: =SUM(AJ26*$Z$4) -> 2420 | AL26: =SUM(AJ26) -> 242 | AM26: =SUM(AL26*$Z$4) -> 2420 | AN26: =SUM(AO26/19600) -> 0.86428571 | AO26: =SUM(AA26+AC26+AE26+AG26+AI26+AK26+AM26) -> 16940 | AQ26: =SUM(AR26/92970) -> 0.78300388 | AR26: =Y26+AO26 -> 72795.871 | AS26: =SUM(AR26-AR25-AT26) -> 0 | AV26: =IF(AT26>0,AU26,AV25) -> 0.883 | AW26: =-SUM('B5'!AI25) -> 0 | AX26: =-SUM(AW26-AS26) -> 0 | AY26: =SUM(AX26+AW26) -> 0 | AZ26: =ELEC!A24 -> 0 | BA26: ='General information '!D25 -> 0 | BB26: =SUM('General information '!E25) -> 0 | BC26: =IF(AR25>=AR26,0,1) -> 0 | BD26: 19222 | BE26: =(305/1185)*ELEC!Q25 -> 758.76793 | BG26: =#REF!-BE26 -> #REF! | BI26: 13 | BJ26: =AX26/BI26 -> 0
A27: =ELEC!C25 -> 44948 | B27: ='B5'!B26 -> 232 | C27: =B27*$B$4 -> 4991.7419 | D27: =SUM(B27) -> 232 | E27: =D27*$B$4 -> 4991.7419 | F27: =SUM(D27) -> 232 | G27: =F27*$B$4 -> 4991.7419 | H27: =SUM(F27) -> 232 | I27: =H27*$B$4 -> 4991.7419 | J27: =SUM(H27) -> 232 | K27: =J27*$B$4 -> 4991.7419 | L27: =SUM(J27) -> 232 | M27: =L27*$B$4 -> 4991.7419 | N27: =SUM(L27) -> 232 | O27: =N27*$B$4 -> 4991.7419 | P27: =SUM(N27) -> 232 | Q27: =P27*$B$4 -> 4991.7419 | R27: =SUM(P27) -> 232 | S27: =R27*$B$4 -> 4991.7419 | T27: =SUM(R27) -> 232 | U27: =T27*$B$4 -> 4991.7419 | V27: =SUM(T27) -> 232 | W27: =V27*$B$4 -> 4991.7419 | X27: =SUM(Y27/73370) -> 0.7483871 | Y27: =SUM(C27+E27+G27+I27+K27+M27+O27+Q27+S27+U27+W27) -> 54909.161 | Z27: ='B5'!C26 -> 239 | AA27: =SUM(Z27*$Z$4) -> 2390 | AB27: =SUM(Z27) -> 239 | AC27: =SUM(AB27*$Z$4) -> 2390 | AD27: =SUM(AB27) -> 239 | AE27: =SUM(AD27*$Z$4) -> 2390 | AF27: =SUM(AD27) -> 239 | AG27: =SUM(AF27*$Z$4) -> 2390 | AH27: =SUM(AF27) -> 239 | AI27: =SUM(AH27*$Z$4) -> 2390 | AJ27: =SUM(AH27) -> 239 | AK27: =SUM(AJ27*$Z$4) -> 2390 | AL27: =SUM(AJ27) -> 239 | AM27: =SUM(AL27*$Z$4) -> 2390 | AN27: =SUM(AO27/19600) -> 0.85357143 | AO27: =SUM(AA27+AC27+AE27+AG27+AI27+AK27+AM27) -> 16730 | AQ27: =SUM(AR27/92970) -> 0.77056213 | AR27: =Y27+AO27 -> 71639.161 | AS27: =SUM(AR27-AR26-AT27) -> -1156.7097 | AV27: =IF(AT27>0,AU27,AV26) -> 0.883 | AW27: =-SUM('B5'!AI26) -> -261 | AX27: =-SUM(AW27-AS27) -> -895.70968 | AY27: =SUM(AX27+AW27) -> -1156.7097 | AZ27: =ELEC!A25 -> 0 | BA27: ='General information '!D26 -> 21.5 | BB27: =SUM('General information '!E26) -> 0.65 | BC27: =IF(AR26>=AR27,0,1) -> 0 | BD27: 19222 | BE27: =(305/1185)*ELEC!Q26 -> 643.97468 | BG27: =#REF!-BE27 -> #REF! | BI27: 14 | BJ27: =AX27/BI27 -> -63.979263 | BK27: =GEN!AF24 -> 0.15354167
A28: =ELEC!C26 -> 44949 | B28: ='B5'!B27 -> 229 | C28: =B28*$B$4 -> 4927.1935 | D28: =SUM(B28) -> 229 | E28: =D28*$B$4 -> 4927.1935 | F28: =SUM(D28) -> 229 | G28: =F28*$B$4 -> 4927.1935 | H28: =SUM(F28) -> 229 | I28: =H28*$B$4 -> 4927.1935 | J28: =SUM(H28) -> 229 | K28: =J28*$B$4 -> 4927.1935 | L28: =SUM(J28) -> 229 | M28: =L28*$B$4 -> 4927.1935 | N28: =SUM(L28) -> 229 | O28: =N28*$B$4 -> 4927.1935 | P28: =SUM(N28) -> 229 | Q28: =P28*$B$4 -> 4927.1935 | R28: =SUM(P28) -> 229 | S28: =R28*$B$4 -> 4927.1935 | T28: =SUM(R28) -> 229 | U28: =T28*$B$4 -> 4927.1935 | V28: =SUM(T28) -> 229 | W28: =V28*$B$4 -> 4927.1935 | X28: =SUM(Y28/73370) -> 0.73870968 | Y28: =SUM(C28+E28+G28+I28+K28+M28+O28+Q28+S28+U28+W28) -> 54199.129 | Z28: ='B5'!C27 -> 235 | AA28: =SUM(Z28*$Z$4) -> 2350 | AB28: =SUM(Z28) -> 235 | AC28: =SUM(AB28*$Z$4) -> 2350 | AD28: =SUM(AB28) -> 235 | AE28: =SUM(AD28*$Z$4) -> 2350 | AF28: =SUM(AD28) -> 235 | AG28: =SUM(AF28*$Z$4) -> 2350 | AH28: =SUM(AF28) -> 235 | AI28: =SUM(AH28*$Z$4) -> 2350 | AJ28: =SUM(AH28) -> 235 | AK28: =SUM(AJ28*$Z$4) -> 2350 | AL28: =SUM(AJ28) -> 235 | AM28: =SUM(AL28*$Z$4) -> 2350 | AN28: =SUM(AO28/19600) -> 0.83928571 | AO28: =SUM(AA28+AC28+AE28+AG28+AI28+AK28+AM28) -> 16450 | AQ28: =SUM(AR28/92970) -> 0.75991319 | AR28: =Y28+AO28 -> 70649.129 | AS28: =SUM(AR28-AR27-AT28) -> -990.03226 | AV28: =IF(AT28>0,AU28,AV27) -> 0.883 | AW28: =-SUM('B5'!AI27) -> -153 | AX28: =-SUM(AW28-AS28) -> -837.03226 | AY28: =SUM(AX28+AW28) -> -990.03226 | AZ28: =ELEC!A26 -> 0 | BA28: ='General information '!D27 -> 17.5 | BB28: =SUM('General information '!E27) -> 0.49 | BC28: =IF(AR27>=AR28,0,1) -> 0 | BD28: 19222 | BE28: =(305/1185)*ELEC!Q27 -> 483.1097 | BG28: =#REF!-BE28 -> #REF! | BI28: 15 | BJ28: =AX28/BI28 -> -55.802151 | BK28: =GEN!AF25 -> 0.156375
A29: =ELEC!C27 -> 44950 | B29: ='B5'!B28 -> 227 | C29: =B29*$B$4 -> 4884.1613 | D29: =SUM(B29) -> 227 | E29: =D29*$B$4 -> 4884.1613 | F29: =SUM(D29) -> 227 | G29: =F29*$B$4 -> 4884.1613 | H29: =SUM(F29) -> 227 | I29: =H29*$B$4 -> 4884.1613 | J29: =SUM(H29) -> 227 | K29: =J29*$B$4 -> 4884.1613 | L29: =SUM(J29) -> 227 | M29: =L29*$B$4 -> 4884.1613 | N29: =SUM(L29) -> 227 | O29: =N29*$B$4 -> 4884.1613 | P29: =SUM(N29) -> 227 | Q29: =P29*$B$4 -> 4884.1613 | R29: =SUM(P29) -> 227 | S29: =R29*$B$4 -> 4884.1613 | T29: =SUM(R29) -> 227 | U29: =T29*$B$4 -> 4884.1613 | V29: =SUM(T29) -> 227 | W29: =V29*$B$4 -> 4884.1613 | X29: =SUM(Y29/73370) -> 0.73225806 | Y29: =SUM(C29+E29+G29+I29+K29+M29+O29+Q29+S29+U29+W29) -> 53725.774 | Z29: ='B5'!C28 -> 233 | AA29: =SUM(Z29*$Z$4) -> 2330 | AB29: =SUM(Z29) -> 233 | AC29: =SUM(AB29*$Z$4) -> 2330 | AD29: =SUM(AB29) -> 233 | AE29: =SUM(AD29*$Z$4) -> 2330 | AF29: =SUM(AD29) -> 233 | AG29: =SUM(AF29*$Z$4) -> 2330 | AH29: =SUM(AF29) -> 233 | AI29: =SUM(AH29*$Z$4) -> 2330 | AJ29: =SUM(AH29) -> 233 | AK29: =SUM(AJ29*$Z$4) -> 2330 | AL29: =SUM(AJ29) -> 233 | AM29: =SUM(AL29*$Z$4) -> 2330 | AN29: =SUM(AO29/19600) -> 0.83214286 | AO29: =SUM(AA29+AC29+AE29+AG29+AI29+AK29+AM29) -> 16310 | AQ29: =SUM(AR29/92970) -> 0.75331585 | AR29: =Y29+AO29 -> 70035.774 | AS29: =SUM(AR29-AR28-AT29) -> -613.35484 | AV29: =IF(AT29>0,AU29,AV28) -> 0.883 | AW29: =-SUM('B5'!AI28) -> -56 | AX29: =-SUM(AW29-AS29) -> -557.35484 | AY29: =SUM(AX29+AW29) -> -613.35484 | AZ29: =ELEC!A27 -> 0 | BA29: ='General information '!D28 -> 16 | BB29: =SUM('General information '!E28) -> 0.56 | BC29: =IF(AR28>=AR29,0,1) -> 0 | BD29: 19222 | BE29: =(305/1185)*ELEC!Q28 -> 611.02954 | BG29: =#REF!-BE29 -> #REF! | BI29: 16 | BJ29: =AX29/BI29 -> -34.834677 | BK29: =GEN!AF26 -> 0.14664063
A30: =ELEC!C28 -> 44951 | B30: ='B5'!B29 -> 223 | C30: =B30*$B$4 -> 4798.0968 | D30: =SUM(B30) -> 223 | E30: =D30*$B$4 -> 4798.0968 | F30: =SUM(D30) -> 223 | G30: =F30*$B$4 -> 4798.0968 | H30: =SUM(F30) -> 223 | I30: =H30*$B$4 -> 4798.0968 | J30: =SUM(H30) -> 223 | K30: =J30*$B$4 -> 4798.0968 | L30: =SUM(J30) -> 223 | M30: =L30*$B$4 -> 4798.0968 | N30: =SUM(L30) -> 223 | O30: =N30*$B$4 -> 4798.0968 | P30: =SUM(N30) -> 223 | Q30: =P30*$B$4 -> 4798.0968 | R30: =SUM(P30) -> 223 | S30: =R30*$B$4 -> 4798.0968 | T30: =SUM(R30) -> 223 | U30: =T30*$B$4 -> 4798.0968 | V30: =SUM(T30) -> 223 | W30: =V30*$B$4 -> 4798.0968 | X30: =SUM(Y30/73370) -> 0.71935484 | Y30: =SUM(C30+E30+G30+I30+K30+M30+O30+Q30+S30+U30+W30) -> 52779.065 | Z30: ='B5'!C29 -> 229 | AA30: =SUM(Z30*$Z$4) -> 2290 | AB30: =SUM(Z30) -> 229 | AC30: =SUM(AB30*$Z$4) -> 2290 | AD30: =SUM(AB30) -> 229 | AE30: =SUM(AD30*$Z$4) -> 2290 | AF30: =SUM(AD30) -> 229 | AG30: =SUM(AF30*$Z$4) -> 2290 | AH30: =SUM(AF30) -> 229 | AI30: =SUM(AH30*$Z$4) -> 2290 | AJ30: =SUM(AH30) -> 229 | AK30: =SUM(AJ30*$Z$4) -> 2290 | AL30: =SUM(AJ30) -> 229 | AM30: =SUM(AL30*$Z$4) -> 2290 | AN30: =SUM(AO30/19600) -> 0.81785714 | AO30: =SUM(AA30+AC30+AE30+AG30+AI30+AK30+AM30) -> 16030 | AQ30: =SUM(AR30/92970) -> 0.74012116 | AR30: =Y30+AO30 -> 68809.065 | AS30: =SUM(AR30-AR29-AT30) -> -1226.7097 | AV30: =IF(AT30>0,AU30,AV29) -> 0.883 | AW30: =-SUM('B5'!AI29) -> -309 | AX30: =-SUM(AW30-AS30) -> -917.70968 | AY30: =SUM(AX30+AW30) -> -1226.7097 | AZ30: =ELEC!A28 -> 0 | BA30: ='General information '!D29 -> 16 | BB30: =SUM('General information '!E29) -> 0.56 | BC30: =IF(AR29>=AR30,0,1) -> 0 | BD30: 19222 | BE30: =(305/1185)*ELEC!Q29 -> 655.04219 | BG30: =#REF!-BE30 -> #REF! | BI30: 17 | BJ30: =AX30/BI30 -> -53.982922 | BK30: =GEN!AF27 -> 0.13488636
A31: =ELEC!C29 -> 44952 | B31: ='B5'!B30 -> 220 | C31: =B31*$B$4 -> 4733.5484 | D31: =SUM(B31) -> 220 | E31: =D31*$B$4 -> 4733.5484 | F31: =SUM(D31) -> 220 | G31: =F31*$B$4 -> 4733.5484 | H31: =SUM(F31) -> 220 | I31: =H31*$B$4 -> 4733.5484 | J31: =SUM(H31) -> 220 | K31: =J31*$B$4 -> 4733.5484 | L31: =SUM(J31) -> 220 | M31: =L31*$B$4 -> 4733.5484 | N31: =SUM(L31) -> 220 | O31: =N31*$B$4 -> 4733.5484 | P31: =SUM(N31) -> 220 | Q31: =P31*$B$4 -> 4733.5484 | R31: =SUM(P31) -> 220 | S31: =R31*$B$4 -> 4733.5484 | T31: =SUM(R31) -> 220 | U31: =T31*$B$4 -> 4733.5484 | V31: =SUM(T31) -> 220 | W31: =V31*$B$4 -> 4733.5484 | X31: =SUM(Y31/73370) -> 0.70967742 | Y31: =SUM(C31+E31+G31+I31+K31+M31+O31+Q31+S31+U31+W31) -> 52069.032 | Z31: ='B5'!C30 -> 226 | AA31: =SUM(Z31*$Z$4) -> 2260 | AB31: =SUM(Z31) -> 226 | AC31: =SUM(AB31*$Z$4) -> 2260 | AD31: =SUM(AB31) -> 226 | AE31: =SUM(AD31*$Z$4) -> 2260 | AF31: =SUM(AD31) -> 226 | AG31: =SUM(AF31*$Z$4) -> 2260 | AH31: =SUM(AF31) -> 226 | AI31: =SUM(AH31*$Z$4) -> 2260 | AJ31: =SUM(AH31) -> 226 | AK31: =SUM(AJ31*$Z$4) -> 2260 | AL31: =SUM(AJ31) -> 226 | AM31: =SUM(AL31*$Z$4) -> 2260 | AN31: =SUM(AO31/19600) -> 0.80714286 | AO31: =SUM(AA31+AC31+AE31+AG31+AI31+AK31+AM31) -> 15820 | AQ31: =SUM(AR31/92970) -> 0.73022515 | AR31: =Y31+AO31 -> 67889.032 | AS31: =SUM(AR31-AR30-AT31) -> -920.03226 | AV31: =IF(AT31>0,AU31,AV30) -> 0.883 | AW31: =-SUM('B5'!AI30) -> -140 | AX31: =-SUM(AW31-AS31) -> -780.03226 | AY31: =SUM(AX31+AW31) -> -920.03226 | AZ31: =ELEC!A29 -> 0 | BA31: ='General information '!D30 -> 16 | BB31: =SUM('General information '!E30) -> 0.49 | BC31: =IF(AR30>=AR31,0,1) -> 0 | BD31: 19222 | BE31: =(305/1185)*ELEC!Q30 -> 0 | BG31: =#REF!-BE31 -> #REF! | BI31: 18 | BJ31: =AX31/BI31 -> -43.335125 | BK31: =GEN!AF28 -> 0.14460227
A32: =ELEC!C30 -> 44953 | B32: ='B5'!B31 -> 220 | C32: =B32*$B$4 -> 4733.5484 | D32: =SUM(B32) -> 220 | E32: =D32*$B$4 -> 4733.5484 | F32: =SUM(D32) -> 220 | G32: =F32*$B$4 -> 4733.5484 | H32: =SUM(F32) -> 220 | I32: =H32*$B$4 -> 4733.5484 | J32: =SUM(H32) -> 220 | K32: =J32*$B$4 -> 4733.5484 | L32: =SUM(J32) -> 220 | M32: =L32*$B$4 -> 4733.5484 | N32: =SUM(L32) -> 220 | O32: =N32*$B$4 -> 4733.5484 | P32: =SUM(N32) -> 220 | Q32: =P32*$B$4 -> 4733.5484 | R32: =SUM(P32) -> 220 | S32: =R32*$B$4 -> 4733.5484 | T32: =SUM(R32) -> 220 | U32: =T32*$B$4 -> 4733.5484 | V32: =SUM(T32) -> 220 | W32: =V32*$B$4 -> 4733.5484 | X32: =SUM(Y32/73370) -> 0.70967742 | Y32: =SUM(C32+E32+G32+I32+K32+M32+O32+Q32+S32+U32+W32) -> 52069.032 | Z32: ='B5'!C31 -> 226 | AA32: =SUM(Z32*$Z$4) -> 2260 | AB32: =SUM(Z32) -> 226 | AC32: =SUM(AB32*$Z$4) -> 2260 | AD32: =SUM(AB32) -> 226 | AE32: =SUM(AD32*$Z$4) -> 2260 | AF32: =SUM(AD32) -> 226 | AG32: =SUM(AF32*$Z$4) -> 2260 | AH32: =SUM(AF32) -> 226 | AI32: =SUM(AH32*$Z$4) -> 2260 | AJ32: =SUM(AH32) -> 226 | AK32: =SUM(AJ32*$Z$4) -> 2260 | AL32: =SUM(AJ32) -> 226 | AM32: =SUM(AL32*$Z$4) -> 2260 | AN32: =SUM(AO32/19600) -> 0.80714286 | AO32: =SUM(AA32+AC32+AE32+AG32+AI32+AK32+AM32) -> 15820 | AQ32: =SUM(AR32/92970) -> 0.73022515 | AR32: =Y32+AO32 -> 67889.032 | AS32: =SUM(AR32-AR31-AT32) -> 0 | AV32: =IF(AT32>0,AU32,AV31) -> 0.883 | AW32: =-SUM('B5'!AI31) -> 0 | AX32: =-SUM(AW32-AS32) -> 0 | AY32: =SUM(AX32+AW32) -> 0 | AZ32: =ELEC!A30 -> 0 | BA32: ='General information '!D31 -> 0 | BB32: =SUM('General information '!E31) -> 0 | BC32: =IF(AR31>=AR32,0,1) -> 0 | BD32: 19222 | BE32: =(305/1185)*ELEC!Q31 -> 0 | BG32: =#REF!-BE32 -> #REF! | BI32: 19 | BJ32: =AX32/BI32 -> 0 | BK32: =GEN!AF29 -> #DIV/0!
A33: =ELEC!C31 -> 44954 | B33: ='B5'!B32 -> 220 | C33: =B33*$B$4 -> 4733.5484 | D33: =SUM(B33) -> 220 | E33: =D33*$B$4 -> 4733.5484 | F33: =SUM(D33) -> 220 | G33: =F33*$B$4 -> 4733.5484 | H33: =SUM(F33) -> 220 | I33: =H33*$B$4 -> 4733.5484 | J33: =SUM(H33) -> 220 | K33: =J33*$B$4 -> 4733.5484 | L33: =SUM(J33) -> 220 | M33: =L33*$B$4 -> 4733.5484 | N33: =SUM(L33) -> 220 | O33: =N33*$B$4 -> 4733.5484 | P33: =SUM(N33) -> 220 | Q33: =P33*$B$4 -> 4733.5484 | R33: =SUM(P33) -> 220 | S33: =R33*$B$4 -> 4733.5484 | T33: =SUM(R33) -> 220 | U33: =T33*$B$4 -> 4733.5484 | V33: =SUM(T33) -> 220 | W33: =V33*$B$4 -> 4733.5484 | X33: =SUM(Y33/73370) -> 0.70967742 | Y33: =SUM(C33+E33+G33+I33+K33+M33+O33+Q33+S33+U33+W33) -> 52069.032 | Z33: ='B5'!C32 -> 226 | AA33: =SUM(Z33*$Z$4) -> 2260 | AB33: =SUM(Z33) -> 226 | AC33: =SUM(AB33*$Z$4) -> 2260 | AD33: =SUM(AB33) -> 226 | AE33: =SUM(AD33*$Z$4) -> 2260 | AF33: =SUM(AD33) -> 226 | AG33: =SUM(AF33*$Z$4) -> 2260 | AH33: =SUM(AF33) -> 226 | AI33: =SUM(AH33*$Z$4) -> 2260 | AJ33: =SUM(AH33) -> 226 | AK33: =SUM(AJ33*$Z$4) -> 2260 | AL33: =SUM(AJ33) -> 226 | AM33: =SUM(AL33*$Z$4) -> 2260 | AN33: =SUM(AO33/19600) -> 0.80714286 | AO33: =SUM(AA33+AC33+AE33+AG33+AI33+AK33+AM33) -> 15820 | AQ33: =SUM(AR33/92970) -> 0.73022515 | AR33: =Y33+AO33 -> 67889.032 | AS33: =SUM(AR33-AR32-AT33) -> 0 | AV33: =IF(AT33>0,AU33,AV32) -> 0.883 | AW33: =-SUM('B5'!AI32) -> 0 | AX33: =-SUM(AW33-AS33) -> 0 | AY33: =SUM(AX33+AW33) -> 0 | AZ33: =ELEC!A31 -> 0 | BA33: ='General information '!D32 -> 0 | BB33: =SUM('General information '!E32) -> 0 | BC33: =IF(AR32>=AR33,0,1) -> 0 | BD33: 19222 | BE33: =(305/1185)*ELEC!#REF! -> #REF! | BG33: =#REF!-BE33 -> #REF! | BI33: 20 | BJ33: =AX33/BI33 -> 0 | BK33: =GEN!AF30 -> #DIV/0!
A34: =ELEC!C32 -> 44955 | B34: ='B5'!B33 -> 216 | C34: =B34*$B$4 -> 4647.4839 | D34: =SUM(B34) -> 216 | E34: =D34*$B$4 -> 4647.4839 | F34: =SUM(D34) -> 216 | G34: =F34*$B$4 -> 4647.4839 | H34: =SUM(F34) -> 216 | I34: =H34*$B$4 -> 4647.4839 | J34: =SUM(H34) -> 216 | K34: =J34*$B$4 -> 4647.4839 | L34: =SUM(J34) -> 216 | M34: =L34*$B$4 -> 4647.4839 | N34: =SUM(L34) -> 216 | O34: =N34*$B$4 -> 4647.4839 | P34: =SUM(N34) -> 216 | Q34: =P34*$B$4 -> 4647.4839 | R34: =SUM(P34) -> 216 | S34: =R34*$B$4 -> 4647.4839 | T34: =SUM(R34) -> 216 | U34: =T34*$B$4 -> 4647.4839 | V34: =SUM(T34) -> 216 | W34: =V34*$B$4 -> 4647.4839 | X34: =SUM(Y34/73370) -> 0.69677419 | Y34: =SUM(C34+E34+G34+I34+K34+M34+O34+Q34+S34+U34+W34) -> 51122.323 | Z34: ='B5'!C33 -> 222 | AA34: =SUM(Z34*$Z$4) -> 2220 | AB34: =SUM(Z34) -> 222 | AC34: =SUM(AB34*$Z$4) -> 2220 | AD34: =SUM(AB34) -> 222 | AE34: =SUM(AD34*$Z$4) -> 2220 | AF34: =SUM(AD34) -> 222 | AG34: =SUM(AF34*$Z$4) -> 2220 | AH34: =SUM(AF34) -> 222 | AI34: =SUM(AH34*$Z$4) -> 2220 | AJ34: =SUM(AH34) -> 222 | AK34: =SUM(AJ34*$Z$4) -> 2220 | AL34: =SUM(AJ34) -> 222 | AM34: =SUM(AL34*$Z$4) -> 2220 | AN34: =SUM(AO34/19600) -> 0.79285714 | AO34: =SUM(AA34+AC34+AE34+AG34+AI34+AK34+AM34) -> 15540 | AQ34: =SUM(AR34/92970) -> 0.71703047 | AR34: =Y34+AO34 -> 66662.323 | AS34: =SUM(AR34-AR33-AT34) -> -1226.7097 | AV34: =IF(AT34>0,AU34,AV33) -> 0.883 | AW34: =-SUM('B5'!AI33) -> -221 | AX34: =-SUM(AW34-AS34) -> -1005.7097 | AY34: =SUM(AX34+AW34) -> -1226.7097 | AZ34: =ELEC!A32 -> 0 | BA34: ='General information '!D33 -> 16.5 | BB34: =SUM('General information '!E33) -> 0.73 | BC34: =IF(AR33>=AR34,0,1) -> 0 | BD34: 19223 | BE34: =(305/1185)*ELEC!#REF! -> #REF! | BG34: =#REF!-BE34 -> #REF! | BI34: 21 | BJ34: =AX34/BI34 -> -47.890937 | BK34: =GEN!AF31 -> 0.155
A35: =ELEC!C33 -> 44956 | B35: ='B5'!B34 -> 240.5 | C35: =B35*$B$4 -> 5174.629 | D35: =SUM(B35) -> 240.5 | E35: =D35*$B$4 -> 5174.629 | F35: =SUM(D35) -> 240.5 | G35: =F35*$B$4 -> 5174.629 | H35: =SUM(F35) -> 240.5 | I35: =H35*$B$4 -> 5174.629 | J35: =SUM(H35) -> 240.5 | K35: =J35*$B$4 -> 5174.629 | L35: =SUM(J35) -> 240.5 | M35: =L35*$B$4 -> 5174.629 | N35: =SUM(L35) -> 240.5 | O35: =N35*$B$4 -> 5174.629 | P35: =SUM(N35) -> 240.5 | Q35: =P35*$B$4 -> 5174.629 | R35: =SUM(P35) -> 240.5 | S35: =R35*$B$4 -> 5174.629 | T35: =SUM(R35) -> 240.5 | U35: =T35*$B$4 -> 5174.629 | V35: =SUM(T35) -> 240.5 | W35: =V35*$B$4 -> 5174.629 | X35: =SUM(Y35/73370) -> 0.77580645 | Y35: =SUM(C35+E35+G35+I35+K35+M35+O35+Q35+S35+U35+W35) -> 56920.919 | Z35: ='B5'!C34 -> 246.5 | AA35: =SUM(Z35*$Z$4) -> 2465 | AB35: =SUM(Z35) -> 246.5 | AC35: =SUM(AB35*$Z$4) -> 2465 | AD35: =SUM(AB35) -> 246.5 | AE35: =SUM(AD35*$Z$4) -> 2465 | AF35: =SUM(AD35) -> 246.5 | AG35: =SUM(AF35*$Z$4) -> 2465 | AH35: =SUM(AF35) -> 246.5 | AI35: =SUM(AH35*$Z$4) -> 2465 | AJ35: =SUM(AH35) -> 246.5 | AK35: =SUM(AJ35*$Z$4) -> 2465 | AL35: =SUM(AJ35) -> 246.5 | AM35: =SUM(AL35*$Z$4) -> 2465 | AN35: =SUM(AO35/19600) -> 0.88035714 | AO35: =SUM(AA35+AC35+AE35+AG35+AI35+AK35+AM35) -> 17255 | AQ35: =SUM(AR35/92970) -> 0.7978479 | AR35: =Y35+AO35 -> 74175.919 | AS35: =SUM(AR35-AR34-AT35) -> -281.40323 | AT35: 7795 | AU35: 0.915 | AV35: =IF(AT35>0,AU35,AV34) -> 0.915 | AW35: =-SUM('B5'!AI34) -> -383 | AX35: =-SUM(AW35-AS35) -> 101.59677 | AY35: =SUM(AX35+AW35) -> -281.40323 | AZ35: =ELEC!A33 -> 0 | BA35: ='General information '!D34 -> 14.5 | BB35: =SUM('General information '!E34) -> 0.75 | BC35: =IF(AR34>=AR35,0,1) -> 1 | BD35: 19224 | BE35: =(305/1185)*ELEC!#REF! -> #REF! | BG35: =#REF!-BE35 -> #REF! | BI35: 22 | BJ35: =AX35/BI35 -> 4.6180352 | BK35: =GEN!AF32 -> 0.19732955
A36: =ELEC!C34 -> 44957 | B36: ='B5'!B35 -> 240.5 | C36: =B36*$B$4 -> 5174.629 | D36: =SUM(B36) -> 240.5 | E36: =D36*$B$4 -> 5174.629 | F36: =SUM(D36) -> 240.5 | G36: =F36*$B$4 -> 5174.629 | H36: =SUM(F36) -> 240.5 | I36: =H36*$B$4 -> 5174.629 | J36: =SUM(H36) -> 240.5 | K36: =J36*$B$4 -> 5174.629 | L36: =SUM(J36) -> 240.5 | M36: =L36*$B$4 -> 5174.629 | N36: =SUM(L36) -> 240.5 | O36: =N36*$B$4 -> 5174.629 | P36: =SUM(N36) -> 240.5 | Q36: =P36*$B$4 -> 5174.629 | R36: =SUM(P36) -> 240.5 | S36: =R36*$B$4 -> 5174.629 | T36: =SUM(R36) -> 240.5 | U36: =T36*$B$4 -> 5174.629 | V36: =SUM(T36) -> 240.5 | W36: =V36*$B$4 -> 5174.629 | X36: =SUM(Y36/73370) -> 0.77580645 | Y36: =SUM(C36+E36+G36+I36+K36+M36+O36+Q36+S36+U36+W36) -> 56920.919 | Z36: ='B5'!C35 -> 246.5 | AA36: =SUM(Z36*$Z$4) -> 2465 | AB36: =SUM(Z36) -> 246.5 | AC36: =SUM(AB36*$Z$4) -> 2465 | AD36: =SUM(AB36) -> 246.5 | AE36: =SUM(AD36*$Z$4) -> 2465 | AF36: =SUM(AD36) -> 246.5 | AG36: =SUM(AF36*$Z$4) -> 2465 | AH36: =SUM(AF36) -> 246.5 | AI36: =SUM(AH36*$Z$4) -> 2465 | AJ36: =SUM(AH36) -> 246.5 | AK36: =SUM(AJ36*$Z$4) -> 2465 | AL36: =SUM(AJ36) -> 246.5 | AM36: =SUM(AL36*$Z$4) -> 2465 | AN36: =SUM(AO36/19600) -> 0.88035714 | AO36: =SUM(AA36+AC36+AE36+AG36+AI36+AK36+AM36) -> 17255 | AQ36: =SUM(AR36/92970) -> 0.7978479 | AR36: =Y36+AO36 -> 74175.919 | AS36: =SUM(AR36-AR35-AT36) -> 0 | AV36: =IF(AT36>0,AU36,AV35) -> 0.915 | AW36: =-SUM('B5'!AI35) -> 0 | AX36: =-SUM(AW36-AS36) -> 0 | AY36: =SUM(AX36+AW36) -> 0 | AZ36: =ELEC!A34 -> 0 | BA36: ='General information '!D35 -> 0 | BB36: =SUM('General information '!E35) -> 0 | BC36: =IF(AR35>=AR36,0,1) -> 0 | BD36: 19225 | BE36: =(305/1185)*ELEC!#REF! -> #REF! | BG36: =#REF!-BE36 -> #REF! | BI36: 23 | BJ36: =AX36/BI36 -> 0 | BK36: =GEN!AF33 -> #DIV/0!
AR37: NB delivery | AS37: =COUNT(AT6:AT36) -> 4 | AT37: =SUM(AT6:AT36) -> 26650 | AU37: =SUM(AU6:AU36)/AS37 -> 0.889 | AX37: =SUM(AX6:AX36) -> -15944.758 | AY37: =SUM(AY6:AY36) -> -19749.758
AT38: =+AT37*AU37 -> 23691.85
AS40: =SUM(AS6:AS36)/'EDl log'!A35 -> -4937.4395
AX41: 43309
AR42: =AR36-22000 -> 52175.919 | AX42: =AX37/AX41 -> -0.36816269
AR43: =AR42/5500 -> 9.4865308
AR44: =AR43*2 -> 18.973062

Sheet WATER
D1: =SUM(G21:G33) -> 8224606 | AR1: Entrance | AT1: Tank 1 | AV1: Tank 2
AR2: Level | AW2: Quantity CM3 | AZ2: Var
A3: Date | B3: Truck | C3: Truck M3/day | D3: N0. Trucks | F3: REQ. # of trucks | G3: City | H3: City/day | I3: Total water delivery | K3: SW | L3: Cosum SW/day | M3: RO Guest/ Liter | O3: RO K&L/ Liter | Q3: TOTAL RO Production | R3: RO 1 RH | S3: RO 2 RH | T3: RO water counter | U3: RO Cons m3 | V3: Steam Boiler | W3: Steam Boiler/day | X3: Softener Guest | Y3: Guest Sotf/day | Z3: Softener K&L | AA3: K&L Soft/Day | AB3: Fire Tank Level | AC3: Fire Tank Counter | AE3: Laundry Hot Water Counter | AF3: Hot Water Cons/day | AG3: Laundry Cold Water Counter | AH3: Cold Water Cons/day | AI3: Laundry Water Total Cons | AJ3: K&L Sotf/day | AK3: Guest / day | AL3: K&L /day | AM3: Avg Outside Temp | AN3: Banquet Activity | AR3: Date | AT3: MainI | AV3: Kitchen and Laundry | AX3: Guest | AY3: Main Tank | AZ3: Kitchen and Laundry | BA3: Guest | BB3: Kitchen and Laundry | BC3: Main | BD3: Guest | BE3: Total VAR | BF3: Hotel Consumption
E4: 1.66 | AN4: Ball R | AO4: Meeting | AP4: outlet | AT4: 180 | AV4: 220 | AX4: 580 | AY4: =SUM(AT4) -> 180 | AZ4: =SUM(AV4) -> 220 | BA4: =SUM(AX4) -> 580
A5: 44926 | B5: =[2]WATER!B35 -> 109443 | C5: =[2]WATER!C35 -> 0 | D5: =[2]WATER!D35 -> 0 | E5: 2419355 | F5: =[2]WATER!F35 -> 0 | G5: 632594 | H5: 0 | I5: 0 | J5: 0 | K5: =[2]WATER!K35 -> 7089 | L5: =[2]WATER!L35 -> 0 | M5: =[2]WATER!M35 -> 457.44 | N5: =[2]WATER!N35 -> 0 | O5: =[2]WATER!O35 -> 529.52 | P5: =[2]WATER!P35 -> 0 | Q5: =[2]WATER!Q35 -> 0 | R5: =[2]WATER!R35 -> 0 | S5: =[2]WATER!S35 -> 0 | T5: 5198 | U5: =[2]WATER!U35 -> 0 | V5: 512 | W5: =[2]WATER!W35 -> 0 | X5: 156588 | Y5: =[2]WATER!Y35 -> 0 | Z5: 99898 | AA5: =[2]WATER!AA35 -> 0 | AB5: =[2]WATER!AB35 -> 251 | AC5: =[2]WATER!AC35 -> 855 | AD5: =[2]WATER!AD35 -> 0 | AE5: 262.47 | AF5: =[2]WATER!AF35 -> 0 | AG5: =[2]WATER!AG35 -> 2247.41 | AH5: =[2]WATER!AH35 -> 0 | AI5: =[2]WATER!AI35 -> 0 | AJ5: =[2]WATER!AJ35 -> 0 | AK5: =[2]WATER!AK35 -> 0 | AL5: =[2]WATER!AL35 -> 0 | AM5: =[2]WATER!AM35 -> 19.5 | ... AP5: =[2]WATER!AP35 -> 0 | AR5: 44926 | AS5: =[2]WATER!AS36 -> 0.9 | AT5: 185 | AU5: =[2]WATER!AU36 -> 1.1 | AV5: 117 | AW5: =[2]WATER!AW36 -> 2.9 | AX5: 144 | AY5: 166.5 | AZ5: 128.7 | BA5: 417.6 | BB5: =[2]WATER!BB36 -> 0 | BC5: =[2]WATER!BC36 -> 0 | BD5: =[2]WATER!BD36 -> 0 | BE5: =[2]WATER!BE36 -> 0 | BF5: =[2]WATER!BF36 -> 0 | BG5: =[2]WATER!BG36 -> 0
A6: =ELEC!C4 -> 44927 | B6: =B5 -> 109443 | C6: =B6-B5 -> 0 | D6: =C6/27 -> 0 | E6: =SUM((C6*$E$4)+(7500/'EDl log'!$A$37)) -> 241.93548 | G6: =G5 -> 632594 | H6: =G6-G5 -> 0 | I6: =C6+H6 -> 0 | J6: =IF(I6>0,E6/I6,0) -> 0 | K6: =K5 -> 7089 | L6: 0 | M6: =M5 -> 457.44 | N6: =SUM(M6-M5) -> 0 | O6: =O5 -> 529.52 | P6: =SUM(O6-O5) -> 0 | Q6: =P6+N6 -> 0 | T6: =T5 -> 5198 | U6: =SUM(T6-T5) -> 0 | V6: =V5 -> 512 | W6: =+V6-V5 -> 0 | X6: =X5 -> 156588 | Y6: =SUM(X6-X5) -> 0 | Z6: =Z5 -> 99898 | AA6: =Z6-Z5 -> 0 | AB6: =AB5 -> 251 | AC6: =AC5 -> 855 | AD6: 0 | AE6: =AE5 -> 262.47 | AF6: =AE6-AE5 -> 0 | AG6: =AG5 -> 2247.41 | AH6: =AG6-AG5 -> 0 | AI6: =AF6+AH6 -> 0 | AJ6: =+Z6-Z5 -> 0 | AK6: =SUM(Y6-L6) -> 0 | AL6: =SUM(AJ6-W6) -> 0 | AM6: ='General information '!D5 -> 16 | AN6: ='General information '!H5 -> 0 | AP6: ='General information '!J5 -> 0 | AR6: =A6 -> 44927 | AS6: =AS5 -> 0.9 | AT6: =AT5 -> 185 | AU6: =AU5 -> 1.1 | AV6: 117 | AW6: 2.9 | AX6: 144 | AY6: =AS6*AT6 -> 166.5 | AZ6: =AU6*AV6 -> 128.7 | BA6: =AW6*AX6 -> 417.6 | BB6: =AY6-AY5 -> 0 | BC6: =AZ6-AZ5 -> 0 | BD6: =BA6-BA5 -> 0 | BE6: =SUM(BB6:BD6) -> 0 | BF6: =SUM(I6-BE6) -> 0 | BG6: =SUM(I6-BF6) -> 0
A7: =ELEC!C5 -> 44928 | B7: =B6 -> 109443 | C7: =B7-B6 -> 0 | D7: =C7/27 -> 0 | E7: =SUM((C7*$E$4)+(7500/'EDl log'!$A$37)) -> 241.93548 | G7: =G6 -> 632594 | H7: =G7-G6 -> 0 | I7: =C7+H7 -> 0 | J7: =IF(I7>0,E7/I7,0) -> 0 | K7: =K6 -> 7089 | L7: =K7-K6 -> 0 | M7: =M6 -> 457.44 | N7: =SUM(M7-M6) -> 0 | O7: =O6 -> 529.52 | P7: =SUM(O7-O6) -> 0 | Q7: =P7+N7 -> 0 | T7: =T6 -> 5198 | U7: =SUM(T7-T6) -> 0 | V7: =V6 -> 512 | W7: =+V7-V6 -> 0 | X7: =X6 -> 156588 | Y7: =SUM(X7-X6) -> 0 | Z7: =Z6 -> 99898 | AA7: =Z7-Z6 -> 0 | AB7: =AB6 -> 251 | AC7: =AC6 -> 855 | AD7: =AC7-AC6 -> 0 | AE7: =AE6 -> 262.47 | AF7: =AE7-AE6 -> 0 | AG7: =AG6 -> 2247.41 | AH7: =AG7-AG6 -> 0 | AI7: =AF7+AH7 -> 0 | AJ7: =+Z7-Z6 -> 0 | AK7: =SUM(Y7-L7) -> 0 | AL7: =SUM(AJ7-W7) -> 0 | AM7: ='General information '!D6 -> 17 | AN7: ='General information '!H6 -> 0 | AP7: ='General information '!J6 -> 0 | AR7: =A7 -> 44928 | AS7: =AS6 -> 0.9 | AT7: =AT6 -> 185 | AU7: =AU6 -> 1.1 | AV7: =AV6 -> 117 | AW7: 2.9 | AX7: =AX6 -> 144 | AY7: =AS7*AT7 -> 166.5 | AZ7: =AU7*AV7 -> 128.7 | BA7: =AW7*AX7 -> 417.6 | BB7: =AY7-AY6 -> 0 | BC7: =AZ7-AZ6 -> 0 | BD7: =BA7-BA6 -> 0 | BE7: =SUM(BB7:BD7) -> 0 | BF7: =SUM(I7-BE7) -> 0 | BG7: =SUM(I7-BF7) -> 0
A8: =ELEC!C6 -> 44929 | B8: =B7 -> 109443 | C8: =B8-B7 -> 0 | D8: =C8/27 -> 0 | E8: =SUM((C8*$E$4)+(7500/'EDl log'!$A$37)) -> 241.93548 | G8: =G7 -> 632594 | H8: =G8-G7 -> 0 | I8: =C8+H8 -> 0 | J8: =IF(I8>0,E8/I8,0) -> 0 | K8: =K7 -> 7089 | L8: =K8-K7 -> 0 | M8: =M7 -> 457.44 | N8: =SUM(M8-M7) -> 0 | O8: =O7 -> 529.52 | P8: =SUM(O8-O7) -> 0 | Q8: =P8+N8 -> 0 | T8: =T7 -> 5198 | U8: =SUM(T8-T7) -> 0 | V8: =V7 -> 512 | W8: =+V8-V7 -> 0 | X8: =X7 -> 156588 | Y8: =SUM(X8-X7) -> 0 | Z8: =Z7 -> 99898 | AA8: =Z8-Z7 -> 0 | AB8: 242 | AC8: =AC7 -> 855 | AD8: =AC8-AC7 -> 0 | AE8: =AE7 -> 262.47 | AF8: =AE8-AE7 -> 0 | AG8: =AG7 -> 2247.41 | AH8: =AG8-AG7 -> 0 | AI8: =AF8+AH8 -> 0 | AJ8: =+Z8-Z7 -> 0 | AK8: =SUM(Y8-L8) -> 0 | AL8: =SUM(AJ8-W8) -> 0 | AM8: ='General information '!D7 -> 19 | AN8: ='General information '!H7 -> 0 | AP8: ='General information '!J7 -> 0 | AR8: =A8 -> 44929 | AS8: =AS7 -> 0.9 | AT8: 171 | AU8: 1.1 | AV8: 115 | AW8: 2.9 | AX8: 143 | AY8: =AS8*AT8 -> 153.9 | AZ8: =AU8*AV8 -> 126.5 | BA8: =AW8*AX8 -> 414.7 | BB8: =AY8-AY7 -> -12.6 | BC8: =AZ8-AZ7 -> -2.2 | BD8: =BA8-BA7 -> -2.9 | BE8: =SUM(BB8:BD8) -> -17.7 | BF8: =SUM(I8-BE8) -> 17.7 | BG8: =SUM(I8-BF8) -> -17.7
A9: =ELEC!C7 -> 44930 | B9: =B8 -> 109443 | C9: =B9-B8 -> 0 | D9: =C9/27 -> 0 | E9: =SUM((C9*$E$4)+(7500/'EDl log'!$A$37)) -> 241.93548 | G9: 632594 | H9: =G9-G8 -> 0 | I9: =C9+H9 -> 0 | J9: =IF(I9>0,E9/I9,0) -> 0 | K9: =K8 -> 7089 | L9: =K9-K8 -> 0 | M9: =M8 -> 457.44 | N9: =SUM(M9-M8) -> 0 | O9: =O8 -> 529.52 | P9: =SUM(O9-O8) -> 0 | Q9: =P9+N9 -> 0 | T9: =T8 -> 5198 | U9: =SUM(T9-T8) -> 0 | V9: =V8 -> 512 | W9: =+V9-V8 -> 0 | X9: =X8 -> 156588 | Y9: =SUM(X9-X8) -> 0 | Z9: =Z8 -> 99898 | AA9: =Z9-Z8 -> 0 | AB9: =AB8 -> 242 | AC9: =AC8 -> 855 | AD9: =AC9-AC8 -> 0 | AE9: =AE8 -> 262.47 | AF9: =AE9-AE8 -> 0 | AG9: =AG8 -> 2247.41 | AH9: =AG9-AG8 -> 0 | AI9: =AF9+AH9 -> 0 | AJ9: =+Z9-Z8 -> 0 | AK9: =SUM(Y9-L9) -> 0 | AL9: =SUM(AJ9-W9) -> 0 | AM9: ='General information '!D8 -> 17 | AN9: ='General information '!H8 -> 0 | AP9: ='General information '!J8 -> 0 | AR9: =A9 -> 44930 | AS9: =AS8 -> 0.9 | AT9: =AT8 -> 171 | AU9: =AU8 -> 1.1 | AV9: 109 | AW9: 2.9 | AX9: 142 | AY9: =AS9*AT9 -> 153.9 | AZ9: =AU9*AV9 -> 119.9 | BA9: =AW9*AX9 -> 411.8 | BB9: =AY9-AY8 -> 0 | BC9: =AZ9-AZ8 -> -6.6 | BD9: =BA9-BA8 -> -2.9 | BE9: =SUM(BB9:BD9) -> -9.5 | BF9: =SUM(I9-BE9) -> 9.5 | BG9: =SUM(I9-BF9) -> -9.5
A10: =ELEC!C8 -> 44931 | B10: =B9 -> 109443 | C10: =B10-B9 -> 0 | D10: =C10/27 -> 0 | E10: =SUM((C10*$E$4)+(7500/'EDl log'!$A$37)) -> 241.93548 | G10: =G9 -> 632594 | H10: =G10-G9 -> 0 | I10: =C10+H10 -> 0 | J10: =IF(I10>0,E10/I10,0) -> 0 | K10: =K9 -> 7089 | L10: =K10-K9 -> 0 | M10: =M9 -> 457.44 | N10: =SUM(M10-M9) -> 0 | O10: =O9 -> 529.52 | P10: =SUM(O10-O9) -> 0 | Q10: =P10+N10 -> 0 | T10: 5197 | U10: =SUM(T10-T9) -> -1 | V10: =V9 -> 512 | W10: =+V10-V9 -> 0 | X10: =X9 -> 156588 | Y10: =SUM(X10-X9) -> 0 | Z10: =Z9 -> 99898 | AA10: =Z10-Z9 -> 0 | AB10: =AB9 -> 242 | AC10: =AC9 -> 855 | AD10: =AC10-AC9 -> 0 | AE10: =AE9 -> 262.47 | AF10: =AE10-AE9 -> 0 | AG10: =AG9 -> 2247.41 | AH10: =AG10-AG9 -> 0 | AI10: =AF10+AH10 -> 0 | AJ10: =+Z10-Z9 -> 0 | AK10: =SUM(Y10-L10) -> 0 | AL10: =SUM(AJ10-W10) -> 0 | AM10: ='General information '!D9 -> 17 | AN10: ='General information '!H9 -> 0 | AP10: ='General information '!J9 -> 0 | AR10: =A10 -> 44931 | AS10: =AS9 -> 0.9 | AT10: =AT9 -> 171 | AU10: =AU9 -> 1.1 | AV10: 108 | AW10: 2.9 | AX10: 140 | AY10: =AS10*AT10 -> 153.9 | AZ10: =AU10*AV10 -> 118.8 | BA10: =AW10*AX10 -> 406 | BB10: =AY10-AY9 -> 0 | BC10: =AZ10-AZ9 -> -1.1 | BD10: =BA10-BA9 -> -5.8 | BE10: =SUM(BB10:BD10) -> -6.9 | BF10: =SUM(I10-BE10) -> 6.9 | BG10: =SUM(I10-BF10) -> -6.9
A11: =ELEC!C9 -> 44932 | B11: =B10 -> 109443 | C11: =B11-B10 -> 0 | D11: =C11/27 -> 0 | E11: =SUM((C11*$E$4)+(7500/'EDl log'!$A$37)) -> 241.93548 | G11: =G10 -> 632594 | H11: =G11-G10 -> 0 | I11: =C11+H11 -> 0 | J11: =IF(I11>0,E11/I11,0) -> 0 | K11: =K10 -> 7089 | L11: =K11-K10 -> 0 | M11: =M10 -> 457.44 | N11: =SUM(M11-M10) -> 0 | O11: =O10 -> 529.52 | P11: =SUM(O11-O10) -> 0 | Q11: =SUM(P11+N11) -> 0 | T11: =T10 -> 5197 | U11: =SUM(T11-T10) -> 0 | V11: =V10 -> 512 | W11: =+V11-V10 -> 0 | X11: =X10 -> 156588 | Y11: =SUM(X11-X10) -> 0 | Z11: =Z10 -> 99898 | AA11: =Z11-Z10 -> 0 | AB11: =AB10 -> 242 | AC11: =AC10 -> 855 | AD11: =AC11-AC10 -> 0 | AE11: =AE10 -> 262.47 | AF11: =AE11-AE10 -> 0 | AG11: =AG10 -> 2247.41 | AH11: =AG11-AG10 -> 0 | AI11: =AF11+AH11 -> 0 | AJ11: =+Z11-Z10 -> 0 | AK11: =SUM(Y11-L11) -> 0 | AL11: =SUM(AJ11-W11) -> 0 | AM11: ='General information '!D10 -> 0 | AN11: ='General information '!H10 -> 0 | AP11: ='General information '!J10 -> 0 | AR11: =A11 -> 44932 | AS11: =AS10 -> 0.9 | AT11: =AT10 -> 171 | AU11: =AU10 -> 1.1 | AV11: =AV10 -> 108 | AW11: 2.9 | AX11: =AX10 -> 140 | AY11: =AS11*AT11 -> 153.9 | AZ11: =AU11*AV11 -> 118.8 | BA11: =AW11*AX11 -> 406 | BB11: =AY11-AY10 -> 0 | BC11: =AZ11-AZ10 -> 0 | BD11: =BA11-BA10 -> 0 | BE11: =SUM(BB11:BD11) -> 0 | BF11: =SUM(I11-BE11) -> 0 | BG11: =SUM(I11-BF11) -> 0
A12: =ELEC!C10 -> 44933 | B12: =B11 -> 109443 | C12: =B12-B11 -> 0 | D12: =C12/27 -> 0 | E12: =SUM((C12*$E$4)+(7500/'EDl log'!$A$37)) -> 241.93548 | G12: =G11 -> 632594 | H12: =G12-G11 -> 0 | I12: =C12+H12 -> 0 | J12: =IF(I12>0,E12/I12,0) -> 0 | K12: =K11 -> 7089 | L12: =K12-K11 -> 0 | M12: =M11 -> 457.44 | N12: =SUM(M12-M11) -> 0 | O12: =O11 -> 529.52 | P12: =SUM(O12-O11) -> 0 | Q12: =SUM(P12+N12) -> 0 | T12: =T11 -> 5197 | U12: =SUM(T12-T11) -> 0 | V12: =V11 -> 512 | W12: =+V12-V11 -> 0 | X12: =X11 -> 156588 | Y12: =SUM(X12-X11) -> 0 | Z12: =Z11 -> 99898 | AA12: =Z12-Z11 -> 0 | AB12: =AB11 -> 242 | AC12: =AC11 -> 855 | AD12: =AC12-AC11 -> 0 | AE12: =AE11 -> 262.47 | AF12: =AE12-AE11 -> 0 | AG12: =AG11 -> 2247.41 | AH12: =AG12-AG11 -> 0 | AI12: =AF12+AH12 -> 0 | AJ12: =+Z12-Z11 -> 0 | AK12: =SUM(Y12-L12) -> 0 | AL12: =SUM(AJ12-W12) -> 0 | AM12: ='General information '!D11 -> 0 | AN12: ='General information '!H11 -> 0 | AP12: ='General information '!J11 -> 0 | AR12: =A12 -> 44933 | AS12: =AS11 -> 0.9 | AT12: =AT11 -> 171 | AU12: =AU11 -> 1.1 | AV12: =AV11 -> 108 | AW12: 2.9 | AX12: =AX11 -> 140 | AY12: =AS12*AT12 -> 153.9 | AZ12: =AU12*AV12 -> 118.8 | BA12: =AW12*AX12 -> 406 | BB12: =AY12-AY11 -> 0 | BC12: =AZ12-AZ11 -> 0 | BD12: =BA12-BA11 -> 0 | BE12: =SUM(BB12:BD12) -> 0 | BF12: =SUM(I12-BE12) -> 0 | BG12: =SUM(I12-BF12) -> 0
A13: =ELEC!C11 -> 44934 | B13: 109443 | C13: =B13-B12 -> 0 | D13: =C13/27 -> 0 | E13: =SUM((C13*$E$4)+(7500/'EDl log'!$A$37)) -> 241.93548 | G13: 632599 | H13: =G13-G12 -> 5 | I13: =C13+H13 -> 5 | J13: =IF(I13>0,E13/I13,0) -> 48.387097 | K13: =K12 -> 7089 | L13: =K13-K12 -> 0 | M13: =M12 -> 457.44 | N13: =SUM(M13-M12) -> 0 | O13: =O12 -> 529.52 | P13: =SUM(O13-O12) -> 0 | Q13: =SUM(P13+N13) -> 0 | T13: =T12 -> 5197 | U13: =SUM(T13-T12) -> 0 | V13: 515 | W13: =+V13-V12 -> 3 | X13: 156588 | Y13: =SUM(X13-X12) -> 0 | Z13: =Z12 -> 99898 | AA13: =Z13-Z12 -> 0 | AB13: =AB12 -> 242 | AC13: =AC12 -> 855 | AD13: =AC13-AC12 -> 0 | AE13: =AE12 -> 262.47 | AF13: =AE13-AE12 -> 0 | AG13: =AG12 -> 2247.41 | AH13: =AG13-AG12 -> 0 | AI13: =AF13+AH13 -> 0 | AJ13: =+Z13-Z12 -> 0 | AK13: =SUM(Y13-L13) -> 0 | AL13: =SUM(AJ13-W13) -> -3 | AM13: ='General information '!D12 -> 17 | AN13: ='General information '!J12 -> 0 | AP13: ='General information '!J12 -> 0 | AR13: =A13 -> 44934 | AS13: =AS12 -> 0.9 | AT13: =AT12 -> 171 | AU13: =AU12 -> 1.1 | AV13: 107 | AW13: 2.9 | AX13: 137 | AY13: =AS13*AT13 -> 153.9 | AZ13: =AU13*AV13 -> 117.7 | BA13: =AW13*AX13 -> 397.3 | BB13: =AY13-AY12 -> 0 | BC13: =AZ13-AZ12 -> -1.1 | BD13: =BA13-BA12 -> -8.7 | BE13: =SUM(BB13:BD13) -> -9.8 | BF13: =SUM(I13-BE13) -> 14.8 | BG13: =SUM(I13-BF13) -> -9.8
A14: =ELEC!C12 -> 44935 | B14: =B13 -> 109443 | C14: =B14-B13 -> 0 | D14: =C14/27 -> 0 | E14: =SUM((C14*$E$4)+(7500/'EDl log'!$A$37)) -> 241.93548 | G14: =G13 -> 632599 | H14: =G14-G13 -> 0 | I14: =C14+H14 -> 0 | J14: =IF(I14>0,E14/I14,0) -> 0 | K14: =K13 -> 7089 | L14: =K14-K13 -> 0 | M14: =M13 -> 457.44 | N14: =SUM(M14-M13) -> 0 | O14: =O13 -> 529.52 | P14: =SUM(O14-O13) -> 0 | Q14: =SUM(P14+N14) -> 0 | T14: 5199 | U14: =SUM(T14-T13) -> 2 | V14: =V13 -> 515 | W14: =+V14-V13 -> 0 | X14: =X13 -> 156588 | Y14: =SUM(X14-X13) -> 0 | Z14: =Z13 -> 99898 | AA14: =Z14-Z13 -> 0 | AB14: =AB13 -> 242 | AC14: =AC13 -> 855 | AD14: =AC14-AC13 -> 0 | AE14: =AE13 -> 262.47 | AF14: =AE14-AE13 -> 0 | AG14: 2247.41 | AH14: =AG14-AG13 -> 0 | AI14: =AF14+AH14 -> 0 | AJ14: =+Z14-Z13 -> 0 | AK14: =SUM(Y14-L14) -> 0 | AL14: =SUM(AJ14-W14) -> 0 | AM14: ='General information '!D13 -> 16 | AN14: ='General information '!H13 -> 0 | AP14: ='General information '!J13 -> 0 | AR14: =A14 -> 44935 | AS14: =AS13 -> 0.9 | AT14: =AT13 -> 171 | AU14: =AU13 -> 1.1 | AV14: 101 | AW14: 2.9 | AX14: 136 | AY14: =AS14*AT14 -> 153.9 | AZ14: =AU14*AV14 -> 111.1 | BA14: =AW14*AX14 -> 394.4 | BB14: =AY14-AY13 -> 0 | BC14: =AZ14-AZ13 -> -6.6 | BD14: =BA14-BA13 -> -2.9 | BE14: =SUM(BB14:BD14) -> -9.5 | BF14: =SUM(I14-BE14) -> 9.5 | BG14: =SUM(I14-BF14) -> -9.5
A15: =ELEC!C13 -> 44936 | B15: =B14 -> 109443 | C15: =B15-B14 -> 0 | D15: =C15/27 -> 0 | E15: =SUM((C15*$E$4)+(7500/'EDl log'!$A$37)) -> 241.93548 | G15: =G14 -> 632599 | H15: =G15-G14 -> 0 | I15: =C15+H15 -> 0 | J15: =IF(I15>0,E15/I15,0) -> 0 | K15: =K14 -> 7089 | L15: =K15-K14 -> 0 | M15: =M14 -> 457.44 | N15: =SUM(M15-M14) -> 0 | O15: =O14 -> 529.52 | P15: =SUM(O15-O14) -> 0 | Q15: =SUM(P15+N15) -> 0 | T15: =T14 -> 5199 | U15: =SUM(T15-T14) -> 0 | V15: =V14 -> 515 | W15: =+V15-V14 -> 0 | X15: =X14 -> 156588 | Y15: =SUM(X15-X14) -> 0 | Z15: =Z14 -> 99898 | AA15: =Z15-Z14 -> 0 | AB15: =AB14 -> 242 | AC15: =AC14 -> 855 | AD15: =AC15-AC14 -> 0 | AE15: =AE14 -> 262.47 | AF15: =AE15-AE14 -> 0 | AG15: =AG14 -> 2247.41 | AH15: =AG15-AG14 -> 0 | AI15: =AF15+AH15 -> 0 | AJ15: =+Z15-Z14 -> 0 | AK15: =SUM(Y15-L15) -> 0 | AL15: =SUM(AJ15-W15) -> 0 | AM15: ='General information '!D14 -> 16 | AN15: ='General information '!H14 -> 0 | AP15: ='General information '!J14 -> 0 | AR15: =A15 -> 44936 | AS15: =AS14 -> 0.9 | AT15: 140 | AU15: =AU14 -> 1.1 | AV15: 100 | AW15: 2.9 | AX15: 135 | AY15: =AS15*AT15 -> 126 | AZ15: =AU15*AV15 -> 110 | BA15: =AW15*AX15 -> 391.5 | BB15: =AY15-AY14 -> -27.9 | BC15: =AZ15-AZ14 -> -1.1 | BD15: =BA15-BA14 -> -2.9 | BE15: =SUM(BB15:BD15) -> -31.9 | BF15: =SUM(I15-BE15) -> 31.9 | BG15: =SUM(I15-BF15) -> -31.9
A16: =ELEC!C14 -> 44937 | B16: =B15 -> 109443 | C16: =B16-B15 -> 0 | D16: =C16/27 -> 0 | E16: =SUM((C16*$E$4)+(7500/'EDl log'!$A$37)) -> 241.93548 | G16: =G15 -> 632599 | H16: =G16-G15 -> 0 | I16: =C16+H16 -> 0 | J16: =IF(I16>0,E16/I16,0) -> 0 | K16: =K15 -> 7089 | L16: =K16-K15 -> 0 | M16: =M15 -> 457.44 | N16: =SUM(M16-M15) -> 0 | O16: =O15 -> 529.52 | P16: =SUM(O16-O15) -> 0 | Q16: =SUM(P16+N16) -> 0 | T16: =T15 -> 5199 | U16: =SUM(T16-T15) -> 0 | V16: 516 | W16: =+V16-V15 -> 1 | X16: =X15 -> 156588 | Y16: =SUM(X16-X15) -> 0 | Z16: =Z15 -> 99898 | AA16: =Z16-Z15 -> 0 | AB16: =AB15 -> 242 | AC16: =AC15 -> 855 | AD16: =AC16-AC15 -> 0 | AE16: =AE15 -> 262.47 | AF16: =AE16-AE15 -> 0 | AG16: =AG15 -> 2247.41 | AH16: =AG16-AG15 -> 0 | AI16: =AF16+AH16 -> 0 | AJ16: =+Z16-Z15 -> 0 | AK16: =SUM(Y16-L16) -> 0 | AL16: =SUM(AJ16-W16) -> -1 | AM16: ='General information '!D15 -> 16 | AN16: ='General information '!H15 -> 0 | AP16: ='General information '!J15 -> 0 | AR16: =A16 -> 44937 | AS16: =AS15 -> 0.9 | AT16: =AT15 -> 140 | AU16: =AU15 -> 1.1 | AV16: 99 | AW16: 2.9 | AX16: 133 | AY16: =AS16*AT16 -> 126 | AZ16: =AU16*AV16 -> 108.9 | BA16: =AW16*AX16 -> 385.7 | BB16: =AY16-AY15 -> 0 | BC16: =AZ16-AZ15 -> -1.1 | BD16: =BA16-BA15 -> -5.8 | BE16: =SUM(BB16:BD16) -> -6.9 | BF16: =SUM(I16-BE16) -> 6.9 | BG16: =SUM(I16-BF16) -> -6.9
A17: =ELEC!C15 -> 44938 | B17: =B16 -> 109443 | C17: =B17-B16 -> 0 | D17: =C17/27 -> 0 | E17: =SUM((C17*$E$4)+(7500/'EDl log'!$A$37)) -> 241.93548 | G17: 632662 | H17: =G17-G16 -> 63 | I17: =C17+H17 -> 63 | J17: =IF(I17>0,E17/I17,0) -> 3.8402458 | K17: =K16 -> 7089 | L17: =K17-K16 -> 0 | M17: =M16 -> 457.44 | N17: =SUM(M17-M16) -> 0 | O17: =O16 -> 529.52 | P17: =SUM(O17-O16) -> 0 | Q17: =SUM(P17+N17) -> 0 | T17: =T16 -> 5199 | U17: =SUM(T17-T16) -> 0 | V17: =V16 -> 516 | W17: =+V17-V16 -> 0 | X17: =X16 -> 156588 | Y17: =SUM(X17-X16) -> 0 | Z17: =Z16 -> 99898 | AA17: =Z17-Z16 -> 0 | AB17: =AB16 -> 242 | AC17: =AC16 -> 855 | AD17: =AC17-AC16 -> 0 | AE17: =AE16 -> 262.47 | AF17: =AE17-AE16 -> 0 | AG17: =AG16 -> 2247.41 | AH17: =AG17-AG16 -> 0 | AI17: =AF17+AH17 -> 0 | AJ17: =+Z17-Z16 -> 0 | AK17: =SUM(Y17-L17) -> 0 | AL17: =SUM(AJ17-W17) -> 0 | AM17: ='General information '!D16 -> 0 | AN17: ='General information '!H16 -> 0 | AP17: ='General information '!J16 -> 0 | AR17: =A17 -> 44938 | AS17: =AS16 -> 0.9 | AT17: 175 | AU17: =AU16 -> 1.1 | AV17: 95 | AW17: 2.9 | AX17: 130 | AY17: =AS17*AT17 -> 157.5 | AZ17: =AU17*AV17 -> 104.5 | BA17: =AW17*AX17 -> 377 | BB17: =AY17-AY16 -> 31.5 | BC17: =AZ17-AZ16 -> -4.4 | BD17: =BA17-BA16 -> -8.7 | BE17: =SUM(BB17:BD17) -> 18.4 | BF17: =SUM(I17-BE17) -> 44.6 | BG17: =SUM(I17-BF17) -> 18.4
A18: =ELEC!C16 -> 44939 | B18: =B17 -> 109443 | C18: =B18-B17 -> 0 | D18: =C18/27 -> 0 | E18: =SUM((C18*$E$4)+(7500/'EDl log'!$A$37)) -> 241.93548 | G18: =G17 -> 632662 | H18: =G18-G17 -> 0 | I18: =C18+H18 -> 0 | J18: =IF(I18>0,E18/I18,0) -> 0 | K18: =K17 -> 7089 | L18: =K18-K17 -> 0 | M18: =M17 -> 457.44 | N18: =SUM(M18-M17) -> 0 | O18: =O17 -> 529.52 | P18: =SUM(O18-O17) -> 0 | Q18: =SUM(P18+N18) -> 0 | T18: =T17 -> 5199 | U18: =SUM(T18-T17) -> 0 | V18: =V17 -> 516 | W18: =+V18-V17 -> 0 | X18: =X17 -> 156588 | Y18: =SUM(X18-X17) -> 0 | Z18: 99898 | AA18: =Z18-Z17 -> 0 | AB18: =AB17 -> 242 | AC18: =AC17 -> 855 | AD18: =AC18-AC17 -> 0 | AE18: =AE17 -> 262.47 | AF18: =AE18-AE17 -> 0 | AG18: =AG17 -> 2247.41 | AH18: =AG18-AG17 -> 0 | AI18: =AF18+AH18 -> 0 | AJ18: =+Z18-Z17 -> 0 | AK18: =SUM(Y18-L18) -> 0 | AL18: =SUM(AJ18-W18) -> 0 | AM18: ='General information '!D17 -> 0 | AN18: ='General information '!H17 -> 0 | AP18: ='General information '!J17 -> 0 | AR18: =A18 -> 44939 | AS18: =AS17 -> 0.9 | AT18: =AT17 -> 175 | AU18: =AU17 -> 1.1 | AV18: =AV17 -> 95 | AW18: 2.9 | AX18: =AX17 -> 130 | AY18: =AS18*AT18 -> 157.5 | AZ18: =AU18*AV18 -> 104.5 | BA18: =AW18*AX18 -> 377 | BB18: =AY18-AY17 -> 0 | BC18: =AZ18-AZ17 -> 0 | BD18: =BA18-BA17 -> 0 | BE18: =SUM(BB18:BD18) -> 0 | BF18: =SUM(I18-BE18) -> 0 | BG18: =SUM(I18-BF18) -> 0
A19: =ELEC!C17 -> 44940 | B19: =B18 -> 109443 | C19: =B19-B18 -> 0 | D19: =C19/27 -> 0 | E19: =SUM((C19*$E$4)+(7500/'EDl log'!$A$37)) -> 241.93548 | G19: =G18 -> 632662 | H19: =G19-G18 -> 0 | I19: =C19+H19 -> 0 | J19: =IF(I19>0,E19/I19,0) -> 0 | K19: =K18 -> 7089 | L19: =K19-K18 -> 0 | M19: =M18 -> 457.44 | N19: =SUM(M19-M18) -> 0 | O19: =O18 -> 529.52 | P19: =SUM(O19-O18) -> 0 | Q19: =SUM(P19+N19) -> 0 | T19: =T18 -> 5199 | U19: =SUM(T19-T18) -> 0 | V19: =V18 -> 516 | W19: =+V19-V18 -> 0 | X19: =X18 -> 156588 | Y19: =SUM(X19-X18) -> 0 | Z19: =Z18 -> 99898 | AA19: =Z19-Z18 -> 0 | AB19: =AB18 -> 242 | AC19: =AC18 -> 855 | AD19: =AC19-AC18 -> 0 | AE19: =AE18 -> 262.47 | AF19: =AE19-AE18 -> 0 | AG19: =AG18 -> 2247.41 | AH19: =AG19-AG18 -> 0 | AI19: =AF19+AH19 -> 0 | AJ19: =+Z19-Z18 -> 0 | AK19: =SUM(Y19-L19) -> 0 | AL19: =SUM(AJ19-W19) -> 0 | AM19: ='General information '!D18 -> 15.5 | AN19: ='General information '!H18 -> 0 | AP19: ='General information '!J18 -> 0 | AR19: =A19 -> 44940 | AS19: =AS18 -> 0.9 | AT19: =AT18 -> 175 | AU19: =AU18 -> 1.1 | AV19: =AV18 -> 95 | AW19: 2.9 | AX19: =AX18 -> 130 | AY19: =AS19*AT19 -> 157.5 | AZ19: =AU19*AV19 -> 104.5 | BA19: =AW19*AX19 -> 377 | BB19: =AY19-AY18 -> 0 | BC19: =AZ19-AZ18 -> 0 | BD19: =BA19-BA18 -> 0 | BE19: =SUM(BB19:BD19) -> 0 | BF19: =SUM(I19-BE19) -> 0 | BG19: =SUM(I19-BF19) -> 0
A20: =ELEC!C18 -> 44941 | B20: =B19 -> 109443 | C20: =B20-B19 -> 0 | D20: =C20/27 -> 0 | E20: =SUM((C20*$E$4)+(7500/'EDl log'!$A$37)) -> 241.93548 | G20: =G19 -> 632662 | H20: =G20-G19 -> 0 | I20: =C20+H20 -> 0 | J20: =IF(I20>0,E20/I20,0) -> 0 | K20: =K19 -> 7089 | L20: =K20-K19 -> 0 | M20: =M19 -> 457.44 | N20: =SUM(M20-M19) -> 0 | O20: =O19 -> 529.52 | P20: =SUM(O20-O19) -> 0 | Q20: =SUM(P20+N20) -> 0 | T20: =T19 -> 5199 | U20: =SUM(T20-T19) -> 0 | V20: =V19 -> 516 | W20: =+V20-V19 -> 0 | X20: =X19 -> 156588 | Y20: =SUM(X20-X19) -> 0 | Z20: =Z19 -> 99898 | AA20: =Z20-Z19 -> 0 | AB20: =AB19 -> 242 | AC20: =AC19 -> 855 | AD20: =AC20-AC19 -> 0 | AE20: =AE19 -> 262.47 | AF20: =AE20-AE19 -> 0 | AG20: =AG19 -> 2247.41 | AH20: =AG20-AG19 -> 0 | AI20: =AF20+AH20 -> 0 | AJ20: =+Z20-Z19 -> 0 | AK20: =SUM(Y20-L20) -> 0 | AL20: =SUM(AJ20-W20) -> 0 | AM20: ='General information '!D19 -> 15.5 | AN20: ='General information '!H19 -> 0 | AP20: ='General information '!J19 -> 0 | AR20: =A20 -> 44941 | AS20: =AS19 -> 0.9 | AT20: =AT19 -> 175 | AU20: =AU19 -> 1.1 | AV20: 90 | AW20: 2.9 | AX20: 126 | AY20: =AS20*AT20 -> 157.5 | AZ20: =AU20*AV20 -> 99 | BA20: =AW20*AX20 -> 365.4 | BB20: =AY20-AY19 -> 0 | BC20: =AZ20-AZ19 -> -5.5 | BD20: =BA20-BA19 -> -11.6 | BE20: =SUM(BB20:BD20) -> -17.1 | BF20: =SUM(I20-BE20) -> 17.1 | BG20: =SUM(I20-BF20) -> -17.1
A21: =ELEC!C19 -> 44942 | B21: =B20 -> 109443 | C21: =B21-B20 -> 0 | D21: =C21/27 -> 0 | E21: =SUM((C21*$E$4)+(7500/'EDl log'!$A$37)) -> 241.93548 | G21: =G20 -> 632662 | H21: =G21-G20 -> 0 | I21: =C21+H21 -> 0 | J21: =IF(I21>0,E21/I21,0) -> 0 | K21: =K20 -> 7089 | L21: =K21-K20 -> 0 | M21: =M20 -> 457.44 | N21: =SUM(M21-M20) -> 0 | O21: =O20 -> 529.52 | P21: =SUM(O21-O20) -> 0 | Q21: =SUM(P21+N21) -> 0 | T21: =T20 -> 5199 | U21: =SUM(T21-T20) -> 0 | V21: =V20 -> 516 | W21: =+V21-V20 -> 0 | X21: =X20 -> 156588 | Y21: =SUM(X21-X20) -> 0 | Z21: =Z20 -> 99898 | AA21: =Z21-Z20 -> 0 | AB21: =AB20 -> 242 | AC21: =AC20 -> 855 | AD21: =AC21-AC20 -> 0 | AE21: =AE20 -> 262.47 | AF21: =AE21-AE20 -> 0 | AG21: =AG20 -> 2247.41 | AH21: =AG21-AG20 -> 0 | AI21: =AF21+AH21 -> 0 | AJ21: =+Z21-Z20 -> 0 | AK21: =SUM(Y21-L21) -> 0 | AL21: =SUM(AJ21-W21) -> 0 | AM21: ='General information '!D20 -> 16 | AN21: ='General information '!H20 -> 0 | AP21: ='General information '!J20 -> 0 | AR21: =A21 -> 44942 | AS21: =AS20 -> 0.9 | AT21: =AT20 -> 175 | AU21: =AU20 -> 1.1 | AV21: 87 | AW21: 2.9 | AX21: 122 | AY21: =AS21*AT21 -> 157.5 | AZ21: =AU21*AV21 -> 95.7 | BA21: =AW21*AX21 -> 353.8 | BB21: =AY21-AY20 -> 0 | BC21: =AZ21-AZ20 -> -3.3 | BD21: =BA21-BA20 -> -11.6 | BE21: =SUM(BB21:BD21) -> -14.9 | BF21: =SUM(I21-BE21) -> 14.9 | BG21: =SUM(I21-BF21) -> -14.9
A22: =ELEC!C20 -> 44943 | B22: 109443 | C22: =B22-B21 -> 0 | D22: =C22/27 -> 0 | E22: =SUM((C22*$E$4)+(7500/'EDl log'!$A$37)) -> 241.93548 | G22: =G21 -> 632662 | H22: =G22-G21 -> 0 | I22: =C22+H22 -> 0 | J22: =IF(I22>0,E22/I22,0) -> 0 | K22: =K21 -> 7089 | L22: =K22-K21 -> 0 | M22: =M21 -> 457.44 | N22: =SUM(M22-M21) -> 0 | O22: =O21 -> 529.52 | P22: =SUM(O22-O21) -> 0 | Q22: =SUM(P22+N22) -> 0 | T22: =T21 -> 5199 | U22: =SUM(T22-T21) -> 0 | V22: 517 | W22: =+V22-V21 -> 1 | X22: =X21 -> 156588 | Y22: =SUM(X22-X21) -> 0 | Z22: =Z21 -> 99898 | AA22: =Z22-Z21 -> 0 | AB22: =AB21 -> 242 | AC22: =AC21 -> 855 | AD22: =AC22-AC21 -> 0 | AE22: =AE21 -> 262.47 | AF22: =AE22-AE21 -> 0 | AG22: =AG21 -> 2247.41 | AH22: =AG22-AG21 -> 0 | AI22: =AF22+AH22 -> 0 | AJ22: =+Z22-Z21 -> 0 | AK22: =SUM(Y22-L22) -> 0 | AL22: =SUM(AJ22-W22) -> -1 | AM22: ='General information '!D21 -> 16 | AN22: ='General information '!H21 -> 0 | AP22: ='General information '!J21 -> 0 | AR22: =A22 -> 44943 | AS22: =AS21 -> 0.9 | AT22: =AT21 -> 175 | AU22: =AU21 -> 1.1 | AV22: 85 | AW22: 2.9 | AX22: 118 | AY22: =AS22*AT22 -> 157.5 | AZ22: =AU22*AV22 -> 93.5 | BA22: =AW22*AX22 -> 342.2 | BB22: =AY22-AY21 -> 0 | BC22: =AZ22-AZ21 -> -2.2 | BD22: =BA22-BA21 -> -11.6 | BE22: =SUM(BB22:BD22) -> -13.8 | BF22: =SUM(I22-BE22) -> 13.8 | BG22: =SUM(I22-BF22) -> -13.8
A23: =ELEC!C21 -> 44944 | B23: =B22 -> 109443 | C23: =B23-B22 -> 0 | D23: =C23/27 -> 0 | E23: =SUM((C23*$E$4)+(7500/'EDl log'!$A$37)) -> 241.93548 | G23: =G22 -> 632662 | H23: =G23-G22 -> 0 | I23: =C23+H23 -> 0 | J23: =IF(I23>0,E23/I23,0) -> 0 | K23: =K22 -> 7089 | L23: =K23-K22 -> 0 | M23: =M22 -> 457.44 | N23: =SUM(M23-M22) -> 0 | O23: =O22 -> 529.52 | P23: =SUM(O23-O22) -> 0 | Q23: =SUM(P23+N23) -> 0 | T23: =T22 -> 5199 | U23: =SUM(T23-T22) -> 0 | V23: =V22 -> 517 | W23: =+V23-V22 -> 0 | X23: =X22 -> 156588 | Y23: =SUM(X23-X22) -> 0 | Z23: =Z22 -> 99898 | AA23: =Z23-Z22 -> 0 | AB23: =AB22 -> 242 | AC23: =AC22 -> 855 | AD23: =AC23-AC22 -> 0 | AE23: =AE22 -> 262.47 | AF23: =AE23-AE22 -> 0 | AG23: =AG22 -> 2247.41 | AH23: =AG23-AG22 -> 0 | AI23: =AF23+AH23 -> 0 | AJ23: =+Z23-Z22 -> 0 | AK23: =SUM(Y23-L23) -> 0 | AL23: =SUM(AJ23-W23) -> 0 | AM23: ='General information '!D22 -> 16.5 | AN23: ='General information '!H22 -> 0 | AP23: ='General information '!J22 -> 0 | AR23: =A23 -> 44944 | AS23: =AS22 -> 0.9 | AT23: =AT22 -> 175 | AU23: =AU22 -> 1.1 | AV23: =AV22 -> 85 | AW23: 2.9 | AX23: =AX22 -> 118 | AY23: =AS23*AT23 -> 157.5 | AZ23: =AU23*AV23 -> 93.5 | BA23: =AW23*AX23 -> 342.2 | BB23: =AY23-AY22 -> 0 | BC23: =AZ23-AZ22 -> 0 | BD23: =BA23-BA22 -> 0 | BE23: =SUM(BB23:BD23) -> 0 | BF23: =SUM(I23-BE23) -> 0 | BG23: =SUM(I23-BF23) -> 0
A24: =ELEC!C22 -> 44945 | B24: =B23 -> 109443 | C24: =B24-B23 -> 0 | D24: =C24/27 -> 0 | E24: =SUM((C24*$E$4)+(7500/'EDl log'!$A$37)) -> 241.93548 | G24: =G23 -> 632662 | H24: =G24-G23 -> 0 | I24: =C24+H24 -> 0 | J24: =IF(I24>0,E24/I24,0) -> 0 | K24: =K23 -> 7089 | L24: =K24-K23 -> 0 | M24: =M23 -> 457.44 | N24: =SUM(M24-M23) -> 0 | O24: =O23 -> 529.52 | P24: =SUM(O24-O23) -> 0 | Q24: =SUM(P24+N24) -> 0 | T24: =T23 -> 5199 | U24: =SUM(T24-T23) -> 0 | V24: =V23 -> 517 | W24: =+V24-V23 -> 0 | X24: =X23 -> 156588 | Y24: =SUM(X24-X23) -> 0 | Z24: =Z23 -> 99898 | AA24: =Z24-Z23 -> 0 | AB24: =AB23 -> 242 | AC24: =AC23 -> 855 | AD24: =AC24-AC23 -> 0 | AE24: =AE23 -> 262.47 | AF24: =AE24-AE23 -> 0 | AG24: =AG23 -> 2247.41 | AH24: =AG24-AG23 -> 0 | AI24: =AF24+AH24 -> 0 | AJ24: =+Z24-Z23 -> 0 | AK24: =SUM(Y24-L24) -> 0 | AL24: =SUM(AJ24-W24) -> 0 | AM24: ='General information '!D23 -> 16.5 | AN24: ='[3]General information '!H24 -> 0 | AP24: ='[3]General information '!J24 -> 0 | AR24: =A24 -> 44945 | AS24: =AS23 -> 0.9 | AT24: =AT23 -> 175 | AU24: =AU23 -> 1.1 | AV24: =AV23 -> 85 | AW24: 2.9 | AX24: 111 | AY24: =AS24*AT24 -> 157.5 | AZ24: =AU24*AV24 -> 93.5 | BA24: =AW24*AX24 -> 321.9 | BB24: =AY24-AY23 -> 0 | BC24: =AZ24-AZ23 -> 0 | BD24: =BA24-BA23 -> -20.3 | BE24: =SUM(BB24:BD24) -> -20.3 | BF24: =SUM(I24-BE24) -> 20.3 | BG24: =SUM(I24-BF24) -> -20.3
A25: =ELEC!C23 -> 44946 | B25: =B24 -> 109443 | C25: =B25-B24 -> 0 | D25: =C25/27 -> 0 | E25: =SUM((C25*$E$4)+(7500/'EDl log'!$A$37)) -> 241.93548 | G25: =G24 -> 632662 | H25: =G25-G24 -> 0 | I25: =C25+H25 -> 0 | J25: =IF(I25>0,E25/I25,0) -> 0 | K25: =K24 -> 7089 | L25: =K25-K24 -> 0 | M25: =M24 -> 457.44 | N25: =SUM(M25-M24) -> 0 | O25: =O24 -> 529.52 | P25: =SUM(O25-O24) -> 0 | Q25: =SUM(P25+N25) -> 0 | T25: =T24 -> 5199 | U25: =SUM(T25-T24) -> 0 | V25: =V24 -> 517 | W25: =+V25-V24 -> 0 | X25: =X24 -> 156588 | Y25: =SUM(X25-X24) -> 0 | Z25: =Z24 -> 99898 | AA25: =Z25-Z24 -> 0 | AB25: =AB24 -> 242 | AC25: =AC24 -> 855 | AD25: =AC25-AC24 -> 0 | AE25: =AE24 -> 262.47 | AF25: =AE25-AE24 -> 0 | AG25: =AG24 -> 2247.41 | AH25: =AG25-AG24 -> 0 | AI25: =AF25+AH25 -> 0 | AJ25: =+Z25-Z24 -> 0 | AK25: =SUM(Y25-L25) -> 0 | AL25: =SUM(AJ25-W25) -> 0 | AM25: ='General information '!D24 -> 0 | AN25: ='General information '!H24 -> 0 | AP25: ='General information '!J24 -> 0 | AR25: =A25 -> 44946 | AS25: =AS24 -> 0.9 | AT25: =AT24 -> 175 | AU25: =AU24 -> 1.1 | AV25: =AV24 -> 85 | AW25: 2.9 | AX25: =AX24 -> 111 | AY25: =AS25*AT25 -> 157.5 | AZ25: =AU25*AV25 -> 93.5 | BA25: =AW25*AX25 -> 321.9 | BB25: =AY25-AY24 -> 0 | BC25: =AZ25-AZ24 -> 0 | BD25: =BA25-BA24 -> 0 | BE25: =SUM(BB25:BD25) -> 0 | BF25: =SUM(I25-BE25) -> 0 | BG25: =SUM(I25-BF25) -> 0
A26: =ELEC!C24 -> 44947 | B26: =B25 -> 109443 | C26: =B26-B25 -> 0 | D26: =C26/27 -> 0 | E26: =SUM((C26*$E$4)+(7500/'EDl log'!$A$37)) -> 241.93548 | G26: =G25 -> 632662 | H26: =G26-G25 -> 0 | I26: =C26+H26 -> 0 | J26: =IF(I26>0,E26/I26,0) -> 0 | K26: =K25 -> 7089 | L26: =K26-K25 -> 0 | M26: =M25 -> 457.44 | N26: =SUM(M26-M25) -> 0 | O26: =O25 -> 529.52 | P26: =SUM(O26-O25) -> 0 | Q26: =SUM(P26+N26) -> 0 | T26: =T25 -> 5199 | U26: =SUM(T26-T25) -> 0 | V26: =V25 -> 517 | W26: =+V26-V25 -> 0 | X26: =X25 -> 156588 | Y26: =SUM(X26-X25) -> 0 | Z26: =Z25 -> 99898 | AA26: =Z26-Z25 -> 0 | AB26: =AB25 -> 242 | AC26: =AC25 -> 855 | AD26: =AC26-AC25 -> 0 | AE26: =AE25 -> 262.47 | AF26: =AE26-AE25 -> 0 | AG26: =AG25 -> 2247.41 | AH26: =AG26-AG25 -> 0 | AI26: =AF26+AH26 -> 0 | AJ26: =+Z26-Z25 -> 0 | AK26: =SUM(Y26-L26) -> 0 | AL26: =SUM(AJ26-W26) -> 0 | AM26: ='General information '!D25 -> 0 | AN26: ='General information '!H25 -> 0 | AP26: ='General information '!J25 -> 0 | AR26: =A26 -> 44947 | AS26: =AS25 -> 0.9 | AT26: =AT25 -> 175 | AU26: =AU25 -> 1.1 | AV26: =AV25 -> 85 | AW26: 2.9 | AX26: =AX25 -> 111 | AY26: =AS26*AT26 -> 157.5 | AZ26: =AU26*AV26 -> 93.5 | BA26: =AW26*AX26 -> 321.9 | BB26: =AY26-AY25 -> 0 | BC26: =AZ26-AZ25 -> 0 | BD26: =BA26-BA25 -> 0 | BE26: =SUM(BB26:BD26) -> 0 | BF26: =SUM(I26-BE26) -> 0 | BG26: =SUM(I26-BF26) -> 0
A27: =ELEC!C25 -> 44948 | B27: =B26 -> 109443 | C27: =B27-B26 -> 0 | D27: =C27/27 -> 0 | E27: =SUM((C27*$E$4)+(7500/'EDl log'!$A$37)) -> 241.93548 | G27: =G26 -> 632662 | H27: =G27-G26 -> 0 | I27: =C27+H27 -> 0 | J27: =IF(I27>0,E27/I27,0) -> 0 | K27: =K26 -> 7089 | L27: =K27-K26 -> 0 | M27: =M26 -> 457.44 | N27: =SUM(M27-M26) -> 0 | O27: =O26 -> 529.52 | P27: =SUM(O27-O26) -> 0 | Q27: =SUM(P27+N27) -> 0 | T27: =T26 -> 5199 | U27: =SUM(T27-T26) -> 0 | V27: =V26 -> 517 | W27: =+V27-V26 -> 0 | X27: =X26 -> 156588 | Y27: =SUM(X27-X26) -> 0 | Z27: =Z26 -> 99898 | AA27: =Z27-Z26 -> 0 | AB27: =AB26 -> 242 | AC27: =AC26 -> 855 | AD27: =AC27-AC26 -> 0 | AE27: 262.47 | AF27: =AE27-AE26 -> 0 | AG27: =AG26 -> 2247.41 | AH27: =AG27-AG26 -> 0 | AI27: =AF27+AH27 -> 0 | AJ27: =+Z27-Z26 -> 0 | AK27: =SUM(Y27-L27) -> 0 | AL27: =SUM(AJ27-W27) -> 0 | AM27: ='General information '!D26 -> 21.5 | AN27: ='General information '!H26 -> 0 | AP27: ='General information '!J26 -> 0 | AR27: =A27 -> 44948 | AS27: =AS26 -> 0.9 | AT27: =AT26 -> 175 | AU27: =AU26 -> 1.1 | AV27: 80 | AW27: 2.9 | AX27: 109 | AY27: =AS27*AT27 -> 157.5 | AZ27: =AU27*AV27 -> 88 | BA27: =AW27*AX27 -> 316.1 | BB27: =AY27-AY26 -> 0 | BC27: =AZ27-AZ26 -> -5.5 | BD27: =BA27-BA26 -> -5.8 | BE27: =SUM(BB27:BD27) -> -11.3 | BF27: =SUM(I27-BE27) -> 11.3 | BG27: =SUM(I27-BF27) -> -11.3
A28: =ELEC!C26 -> 44949 | B28: =B27 -> 109443 | C28: =B28-B27 -> 0 | D28: =C28/27 -> 0 | E28: =SUM((C28*$E$4)+(7500/'EDl log'!$A$37)) -> 241.93548 | G28: =G27 -> 632662 | H28: =G28-G27 -> 0 | I28: =C28+H28 -> 0 | J28: =IF(I28>0,E28/I28,0) -> 0 | K28: =K27 -> 7089 | L28: =K28-K27 -> 0 | M28: =M27 -> 457.44 | N28: =SUM(M28-M27) -> 0 | O28: =O27 -> 529.52 | P28: =SUM(O28-O27) -> 0 | Q28: =SUM(P28+N28) -> 0 | T28: =T27 -> 5199 | U28: =SUM(T28-T27) -> 0 | V28: =V27 -> 517 | W28: =+V28-V27 -> 0 | X28: =X27 -> 156588 | Y28: =SUM(X28-X27) -> 0 | Z28: =Z27 -> 99898 | AA28: =Z28-Z27 -> 0 | AB28: =AB27 -> 242 | AC28: =AC27 -> 855 | AD28: =AC28-AC27 -> 0 | AE28: =AE27 -> 262.47 | AF28: =AE28-AE27 -> 0 | AG28: =AG27 -> 2247.41 | AH28: =AG28-AG27 -> 0 | AI28: =AF28+AH28 -> 0 | AJ28: =+Z28-Z27 -> 0 | AK28: =SUM(Y28-L28) -> 0 | AL28: =SUM(AJ28-W28) -> 0 | AM28: ='General information '!D27 -> 17.5 | AN28: ='General information '!H27 -> 0 | AP28: ='General information '!J27 -> 0 | AR28: =A28 -> 44949 | AS28: =AS27 -> 0.9 | AT28: 177 | AU28: =AU27 -> 1.1 | AV28: 74 | AW28: 2.9 | AX28: 107 | AY28: =AS28*AT28 -> 159.3 | AZ28: =AU28*AV28 -> 81.4 | BA28: =AW28*AX28 -> 310.3 | BB28: =AY28-AY27 -> 1.8 | BC28: =AZ28-AZ27 -> -6.6 | BD28: =BA28-BA27 -> -5.8 | BE28: =SUM(BB28:BD28) -> -10.6 | BF28: =SUM(I28-BE28) -> 10.6 | BG28: =SUM(I28-BF28) -> -10.6
A29: =ELEC!C27 -> 44950 | B29: =B28 -> 109443 | C29: =B29-B28 -> 0 | D29: =C29/27 -> 0 | E29: =SUM((C29*$E$4)+(7500/'EDl log'!$A$37)) -> 241.93548 | G29: =G28 -> 632662 | H29: =G29-G28 -> 0 | I29: =C29+H29 -> 0 | J29: =IF(I29>0,E29/I29,0) -> 0 | K29: =K28 -> 7089 | L29: =K29-K28 -> 0 | M29: =M28 -> 457.44 | N29: =SUM(M29-M28) -> 0 | O29: =O28 -> 529.52 | P29: =SUM(O29-O28) -> 0 | Q29: =SUM(P29+N29) -> 0 | T29: =T28 -> 5199 | U29: =SUM(T29-T28) -> 0 | V29: =V28 -> 517 | W29: =+V29-V28 -> 0 | X29: =X28 -> 156588 | Y29: =SUM(X29-X28) -> 0 | Z29: =Z28 -> 99898 | AA29: =Z29-Z28 -> 0 | AB29: =AB28 -> 242 | AC29: =AC28 -> 855 | AD29: =AC29-AC28 -> 0 | AE29: =AE28 -> 262.47 | AF29: =AE29-AE28 -> 0 | AG29: =AG28 -> 2247.41 | AH29: =AG29-AG28 -> 0 | AI29: =AF29+AH29 -> 0 | AJ29: =+Z29-Z28 -> 0 | AK29: =SUM(Y29-L29) -> 0 | AL29: =SUM(AJ29-W29) -> 0 | AM29: ='General information '!D28 -> 16 | AN29: ='General information '!H28 -> 0 | AP29: ='General information '!J28 -> 0 | AR29: =A29 -> 44950 | AS29: =AS28 -> 0.9 | AT29: 141 | AU29: =AU28 -> 1.1 | AV29: 73 | AW29: 2.9 | AX29: 105 | AY29: =AS29*AT29 -> 126.9 | AZ29: =AU29*AV29 -> 80.3 | BA29: =AW29*AX29 -> 304.5 | BB29: =AY29-AY28 -> -32.4 | BC29: =AZ29-AZ28 -> -1.1 | BD29: =BA29-BA28 -> -5.8 | BE29: =SUM(BB29:BD29) -> -39.3 | BF29: =SUM(I29-BE29) -> 39.3 | BG29: =SUM(I29-BF29) -> -39.3
A30: =ELEC!C28 -> 44951 | B30: =B29 -> 109443 | C30: =B30-B29 -> 0 | D30: =C30/27 -> 0 | E30: =SUM((C30*$E$4)+(7500/'EDl log'!$A$37)) -> 241.93548 | G30: =G29 -> 632662 | H30: =G30-G29 -> 0 | I30: =C30+H30 -> 0 | J30: =IF(I30>0,E30/I30,0) -> 0 | K30: =K29 -> 7089 | L30: =K30-K29 -> 0 | M30: =M29 -> 457.44 | N30: =SUM(M30-M29) -> 0 | O30: =O29 -> 529.52 | P30: =SUM(O30-O29) -> 0 | Q30: =SUM(P30+N30) -> 0 | T30: =T29 -> 5199 | U30: =SUM(T30-T29) -> 0 | V30: =V29 -> 517 | W30: =+V30-V29 -> 0 | X30: =X29 -> 156588 | Y30: =SUM(X30-X29) -> 0 | Z30: =Z29 -> 99898 | AA30: =Z30-Z29 -> 0 | AB30: =AB29 -> 242 | AC30: =AC29 -> 855 | AD30: =AC30-AC29 -> 0 | AE30: =AE29 -> 262.47 | AF30: =AE30-AE29 -> 0 | AG30: =AG29 -> 2247.41 | AH30: =AG30-AG29 -> 0 | AI30: =AF30+AH30 -> 0 | AJ30: =+Z30-Z29 -> 0 | AK30: =SUM(Y30-L30) -> 0 | AL30: =SUM(AJ30-W30) -> 0 | AM30: ='General information '!D29 -> 16 | AN30: ='General information '!H29 -> 0 | AP30: ='General information '!J29 -> 0 | AR30: =A30 -> 44951 | AS30: =AS29 -> 0.9 | AT30: 138 | AU30: =AU29 -> 1.1 | AV30: =AV29 -> 73 | AW30: 2.9 | AX30: 103 | AY30: =AS30*AT30 -> 124.2 | AZ30: =AU30*AV30 -> 80.3 | BA30: =AW30*AX30 -> 298.7 | BB30: =AY30-AY29 -> -2.7 | BC30: =AZ30-AZ29 -> 0 | BD30: =BA30-BA29 -> -5.8 | BE30: =SUM(BB30:BD30) -> -8.5 | BF30: =SUM(I30-BE30) -> 8.5 | BG30: =SUM(I30-BF30) -> -8.5
A31: =ELEC!C29 -> 44952 | B31: =B30 -> 109443 | C31: =B31-B30 -> 0 | D31: =C31/27 -> 0 | E31: =SUM((C31*$E$4)+(7500/'EDl log'!$A$37)) -> 241.93548 | G31: =G30 -> 632662 | H31: =G31-G30 -> 0 | I31: =C31+H31 -> 0 | J31: =IF(I31>0,E31/I31,0) -> 0 | K31: =K30 -> 7089 | L31: =K31-K30 -> 0 | M31: =M30 -> 457.44 | N31: =SUM(M31-M30) -> 0 | O31: =O30 -> 529.52 | P31: =SUM(O31-O30) -> 0 | Q31: =SUM(P31+N31) -> 0 | T31: =T30 -> 5199 | U31: =SUM(T31-T30) -> 0 | V31: =V30 -> 517 | W31: =+V31-V30 -> 0 | X31: =X30 -> 156588 | Y31: =SUM(X31-X30) -> 0 | Z31: =Z30 -> 99898 | AA31: =Z31-Z30 -> 0 | AB31: =AB30 -> 242 | AC31: =AC30 -> 855 | AD31: =AC31-AC30 -> 0 | AE31: =AE30 -> 262.47 | AF31: =AE31-AE30 -> 0 | AG31: =AG30 -> 2247.41 | AH31: =AG31-AG30 -> 0 | AI31: =AF31+AH31 -> 0 | AJ31: =+Z31-Z30 -> 0 | AK31: =SUM(Y31-L31) -> 0 | AL31: =SUM(AJ31-W31) -> 0 | AM31: ='General information '!D30 -> 16 | AN31: ='General information '!H30 -> 0 | AP31: ='General information '!J30 -> 0 | AR31: =A31 -> 44952 | AS31: =AS30 -> 0.9 | AT31: 133 | AU31: =AU30 -> 1.1 | AV31: 72 | AW31: 2.9 | AX31: 102 | AY31: =AS31*AT31 -> 119.7 | AZ31: =AU31*AV31 -> 79.2 | BA31: =AW31*AX31 -> 295.8 | BB31: =AY31-AY30 -> -4.5 | BC31: =AZ31-AZ30 -> -1.1 | BD31: =BA31-BA30 -> -2.9 | BE31: =SUM(BB31:BD31) -> -8.5 | BF31: =SUM(I31-BE31) -> 8.5 | BG31: =SUM(I31-BF31) -> -8.5
A32: =ELEC!C30 -> 44953 | B32: =B31 -> 109443 | C32: =B32-B31 -> 0 | D32: =C32/27 -> 0 | E32: =SUM((C32*$E$4)+(7500/'EDl log'!$A$37)) -> 241.93548 | G32: =G31 -> 632662 | H32: =G32-G31 -> 0 | I32: =C32+H32 -> 0 | J32: =IF(I32>0,E32/I32,0) -> 0 | K32: =K31 -> 7089 | L32: =K32-K31 -> 0 | M32: =M31 -> 457.44 | N32: =SUM(M32-M31) -> 0 | O32: =O31 -> 529.52 | P32: =SUM(O32-O31) -> 0 | Q32: =SUM(P32+N32) -> 0 | T32: 5196 | U32: =SUM(T32-T31) -> -3 | V32: =V31 -> 517 | W32: =+V32-V31 -> 0 | X32: =X31 -> 156588 | Y32: =SUM(X32-X31) -> 0 | Z32: =Z31 -> 99898 | AA32: =Z32-Z31 -> 0 | AB32: =AB31 -> 242 | AC32: =AC31 -> 855 | AD32: =AC32-AC31 -> 0 | AE32: =AE31 -> 262.47 | AF32: =AE32-AE31 -> 0 | AG32: =AG31 -> 2247.41 | AH32: =AG32-AG31 -> 0 | AI32: =AF32+AH32 -> 0 | AJ32: =+Z32-Z31 -> 0 | AK32: =SUM(Y32-L32) -> 0 | AL32: =SUM(AJ32-W32) -> 0 | AM32: ='General information '!D31 -> 0 | AN32: ='General information '!H31 -> 0 | AP32: ='General information '!J31 -> 0 | AR32: =A32 -> 44953 | AS32: =AS31 -> 0.9 | AT32: =AT31 -> 133 | AU32: =AU31 -> 1.1 | AV32: =AV31 -> 72 | AW32: 2.9 | AX32: =AX31 -> 102 | AY32: =AS32*AT32 -> 119.7 | AZ32: =AU32*AV32 -> 79.2 | BA32: =AW32*AX32 -> 295.8 | BB32: =AY32-AY31 -> 0 | BC32: =AZ32-AZ31 -> 0 | BD32: =BA32-BA31 -> 0 | BE32: =SUM(BB32:BD32) -> 0 | BF32: =SUM(I32-BE32) -> 0 | BG32: =SUM(I32-BF32) -> 0
A33: =ELEC!C31 -> 44954 | B33: =B32 -> 109443 | C33: =B33-B32 -> 0 | D33: =C33/27 -> 0 | E33: =SUM((C33*$E$4)+(7500/'EDl log'!$A$37)) -> 241.93548 | G33: =G32 -> 632662 | H33: =G33-G32 -> 0 | I33: =C33+H33 -> 0 | J33: =IF(I33>0,E33/I33,0) -> 0 | K33: =K32 -> 7089 | L33: =K33-K32 -> 0 | M33: =M32 -> 457.44 | N33: =SUM(M33-M32) -> 0 | O33: =O32 -> 529.52 | P33: =SUM(O33-O32) -> 0 | Q33: =SUM(P33+N33) -> 0 | T33: =T32 -> 5196 | U33: =SUM(T33-T32) -> 0 | V33: =V32 -> 517 | W33: =+V33-V32 -> 0 | X33: =X32 -> 156588 | Y33: =SUM(X33-X32) -> 0 | Z33: =Z32 -> 99898 | AA33: =Z33-Z32 -> 0 | AB33: =AB32 -> 242 | AC33: =AC32 -> 855 | AD33: =AC33-AC32 -> 0 | AE33: =AE32 -> 262.47 | AF33: =AE33-AE32 -> 0 | AG33: =AG32 -> 2247.41 | AH33: =AG33-AG32 -> 0 | AI33: =AF33+AH33 -> 0 | AJ33: =+Z33-Z32 -> 0 | AK33: =SUM(Y33-L33) -> 0 | AL33: =SUM(AJ33-W33) -> 0 | AM33: ='General information '!D32 -> 0 | AN33: ='General information '!H32 -> 0 | AP33: ='General information '!J32 -> 0 | AR33: =A33 -> 44954 | AS33: =AS32 -> 0.9 | AT33: =AT32 -> 133 | AU33: =AU32 -> 1.1 | AV33: =AV32 -> 72 | AW33: 2.9 | AX33: =AX32 -> 102 | AY33: =AS33*AT33 -> 119.7 | AZ33: =AU33*AV33 -> 79.2 | BA33: =AW33*AX33 -> 295.8 | BB33: =AY33-AY32 -> 0 | BC33: =AZ33-AZ32 -> 0 | BD33: =BA33-BA32 -> 0 | BE33: =SUM(BB33:BD33) -> 0 | BF33: =SUM(I33-BE33) -> 0 | BG33: =SUM(I33-BF33) -> 0
A34: =ELEC!C32 -> 44955 | B34: =B33 -> 109443 | C34: =B34-B33 -> 0 | D34: =C34/27 -> 0 | E34: =SUM((C34*$E$4)+(7500/'EDl log'!$A$37)) -> 241.93548 | G34: =G33 -> 632662 | H34: =G34-G33 -> 0 | I34: =C34+H34 -> 0 | J34: =IF(I34>0,E34/I34,0) -> 0 | K34: =K33 -> 7089 | L34: =K34-K33 -> 0 | M34: =M33 -> 457.44 | N34: =SUM(M34-M33) -> 0 | O34: =O33 -> 529.52 | P34: =SUM(O34-O33) -> 0 | Q34: =SUM(P34+N34) -> 0 | T34: 5201 | U34: =SUM(T34-T33) -> 5 | V34: 518 | W34: =+V34-V33 -> 1 | X34: =X33 -> 156588 | Y34: =SUM(X34-X33) -> 0 | Z34: =Z33 -> 99898 | AA34: =Z34-Z33 -> 0 | AB34: =AB33 -> 242 | AC34: =AC33 -> 855 | AD34: =AC34-AC33 -> 0 | AE34: =AE33 -> 262.47 | AF34: =AE34-AE33 -> 0 | AG34: =AG33 -> 2247.41 | AH34: =AG34-AG33 -> 0 | AI34: =AF34+AH34 -> 0 | AJ34: =+Z34-Z33 -> 0 | AK34: =SUM(Y34-L34) -> 0 | AL34: =SUM(AJ34-W34) -> -1 | AM34: ='General information '!D33 -> 16.5 | AN34: ='General information '!H33 -> 0 | AP34: ='General information '!J33 -> 0 | AR34: =A34 -> 44955 | AS34: =AS33 -> 0.9 | AT34: 131 | AU34: =AU33 -> 1.1 | AV34: 67 | AW34: 2.9 | AX34: 100 | AY34: =AS34*AT34 -> 117.9 | AZ34: =AU34*AV34 -> 73.7 | BA34: =AW34*AX34 -> 290 | BB34: =AY34-AY33 -> -1.8 | BC34: =AZ34-AZ33 -> -5.5 | BD34: =BA34-BA33 -> -5.8 | BE34: =SUM(BB34:BD34) -> -13.1 | BF34: =SUM(I34-BE34) -> 13.1 | BG34: =SUM(I34-BF34) -> -13.1
A35: =ELEC!C33 -> 44956 | B35: =B34 -> 109443 | C35: =B35-B34 -> 0 | D35: =C35/27 -> 0 | E35: =SUM((C35*$E$4)+(7500/'EDl log'!$A$37)) -> 241.93548 | G35: =G34 -> 632662 | H35: =G35-G34 -> 0 | I35: =C35+H35 -> 0 | J35: =IF(I35>0,E35/I35,0) -> 0 | K35: =K34 -> 7089 | L35: =K35-K34 -> 0 | M35: =M34 -> 457.44 | N35: =SUM(M35-M34) -> 0 | O35: =O34 -> 529.52 | P35: =SUM(O35-O34) -> 0 | Q35: =SUM(P35+N35) -> 0 | T35: =T34 -> 5201 | U35: =SUM(T35-T34) -> 0 | V35: =V34 -> 518 | W35: =+V35-V34 -> 0 | X35: =X34 -> 156588 | Y35: =SUM(X35-X34) -> 0 | Z35: =Z34 -> 99898 | AA35: =Z35-Z34 -> 0 | AB35: =AB34 -> 242 | AC35: =AC34 -> 855 | AD35: =AC35-AC34 -> 0 | AE35: =AE34 -> 262.47 | AF35: =AE35-AE34 -> 0 | AG35: =AG34 -> 2247.41 | AH35: =AG35-AG34 -> 0 | AI35: =AF35+AH35 -> 0 | AJ35: =+Z35-Z34 -> 0 | AK35: =SUM(Y35-L35) -> 0 | AL35: =SUM(AJ35-W35) -> 0 | AM35: ='General information '!D34 -> 14.5 | AN35: ='General information '!H34 -> 0 | AP35: ='General information '!J34 -> 0 | AR35: =A35 -> 44956 | AS35: =AS34 -> 0.9 | AT35: =AT34 -> 131 | AU35: =AU34 -> 1.1 | AV35: 62 | AW35: 2.9 | AX35: 98 | AY35: =AS35*AT35 -> 117.9 | AZ35: =AU35*AV35 -> 68.2 | BA35: =AW35*AX35 -> 284.2 | BB35: =AY35-AY34 -> 0 | BC35: =AZ35-AZ34 -> -5.5 | BD35: =BA35-BA34 -> -5.8 | BE35: =SUM(BB35:BD35) -> -11.3 | BF35: =SUM(I35-BE35) -> 11.3 | BG35: =SUM(I35-BF35) -> -11.3
A36: =ELEC!C34 -> 44957 | B36: =B35 -> 109443 | C36: =B36-B35 -> 0 | D36: =C36/27 -> 0 | E36: =SUM((C36*$E$4)+(7500/'EDl log'!$A$37)) -> 241.93548 | G36: =G35 -> 632662 | H36: =G36-G35 -> 0 | I36: =C36+H36 -> 0 | J36: =IF(I36>0,E36/I36,0) -> 0 | K36: =K35 -> 7089 | L36: =K36-K35 -> 0 | M36: =M35 -> 457.44 | N36: =SUM(M36-M35) -> 0 | O36: =O35 -> 529.52 | P36: =SUM(O36-O35) -> 0 | Q36: =SUM(P36+N36) -> 0 | T36: =T35 -> 5201 | U36: =SUM(T36-T35) -> 0 | V36: =V35 -> 518 | W36: =+V36-V35 -> 0 | X36: =X35 -> 156588 | Y36: =SUM(X36-X35) -> 0 | Z36: =Z35 -> 99898 | AA36: =Z36-Z35 -> 0 | AB36: =AB35 -> 242 | AC36: =AC35 -> 855 | AD36: =AC36-AC35 -> 0 | AE36: =AE35 -> 262.47 | AF36: =AE36-AE35 -> 0 | AG36: =AG35 -> 2247.41 | AH36: =AG36-AG35 -> 0 | AI36: =AF36+AH36 -> 0 | AJ36: =+Z36-Z35 -> 0 | AK36: =SUM(Y36-L36) -> 0 | AL36: =SUM(AJ36-W36) -> 0 | AM36: ='General information '!D35 -> 0 | AN36: ='General information '!H35 -> 0 | AP36: ='General information '!J35 -> 0 | AR36: =A36 -> 44957 | AS36: =AS35 -> 0.9 | AT36: =AT35 -> 131 | AU36: =AU35 -> 1.1 | AV36: =AV35 -> 62 | AW36: 2.9 | AX36: =AX35 -> 98 | AY36: =AS36*AT36 -> 117.9 | AZ36: =AU36*AV36 -> 68.2 | BA36: =AW36*AX36 -> 284.2 | BB36: =AY36-AY35 -> 0 | BC36: =AZ36-AZ35 -> 0 | BD36: =BA36-BA35 -> 0 | BE36: =SUM(BB36:BD36) -> 0 | BF36: =SUM(I36-BE36) -> 0 | BG36: =SUM(I36-BF36) -> 0
C37: =SUM(C6:C36) -> 0 | D37: =SUM(D6:D36) -> 0 | F37: =SUM(F6:F36) -> 0 | H37: =SUM(H6:H36) -> 68 | I37: =SUM(I6:I36) -> 68 | L37: =SUM(L7:L36) -> 0 | Q37: =SUM(Q6:Q36) -> 0 | U37: =SUM(U6:U36) -> 3 | Y37: =SUM(Y6,Y33,Y31,Y29,Y27,Y25,Y23,Y21,Y19,Y17,Y15,Y13,Y11,Y9,Y7,Y34,Y35,Y36) -> 0 | AJ37: =SUM(AJ6:AJ36) -> 0 | AK37: =SUM(Y37-L37) -> 0 | AL37: =SUM(AL6:AL36) -> -6
C38: =+C37*1.66 -> 0 | E38: =SUM(E6:E33) -> 6774.1935 | F38: =SUM(F6:F35) -> 0 | H38: 7500 | I38: =SUM('General information '!G36/WATER!I37) -> 0 | O38: =SUM(Q37+I37) -> 68 | Z38: =SUM(Y37:AJ37) -> 0 | AK38: =SUM(Y38-L38) -> 0
B39: =9*31 -> 279 | D39: =SUM(D6:D35) -> 0 | F39: =SUM(F6:F36) -> 0 | G39: =SUM(I37) -> 68 | H39: =SUM(H38+C38) -> 7500 | K39: =SUM(H39/G39) -> 110.29412 | AJ39: =SUM(C38-AK38) -> 0 | AM39: =SUM(AJ39/AO38) -> #DIV/0!

Sheet General information 
A1: GENERAL & HOTEL'S INFORMATION SHEET
B4: Max Temp | C4: MIN TEMP | D4: AVE TEMP | E4: AVE Humidity | F4: AVE OCC | G4: # of OCC Rooms | H4: Ball room | I4: Meeting rooms | J4: Outlets | K4: Total covers | L4: # of permenant Emp | M4: # of casuals | N4: Total # of EMP | O4: # of EMP/OCC Room
A5: 44926 | B5: 19 | C5: 13 | D5: =(C5+B5)/2 -> 16 | E5: 0.69 | F5: 0 | G5: =F5*230 -> 0 | H5: 0 | I5: 0 | J5: 0 | K5: =+J5+H5 -> 0
A6: =A5+1 -> 44927 | B6: 20 | C6: 14 | D6: =(C6+B6)/2 -> 17 | E6: 0.69 | F6: 0 | G6: =F6*230 -> 0 | H6: 0 | I6: 0 | J6: 0 | K6: =+J6+H6 -> 0
A7: =ELEC!C6 -> 44929 | B7: 20 | C7: 18 | D7: =(C7+B7)/2 -> 19 | E7: 0.69 | F7: 0 | G7: =F7*230 -> 0 | H7: 0 | I7: 0 | J7: 0 | K7: =+J7+H7 -> 0
A8: =ELEC!C7 -> 44930 | B8: 21 | C8: 13 | D8: =(C8+B8)/2 -> 17 | E8: 0.55 | F8: 0 | G8: =F8*230 -> 0 | H8: 0 | I8: 0 | J8: 0 | K8: =+J8+H8 -> 0
A9: =ELEC!C8 -> 44931 | B9: 20 | C9: 14 | D9: =(C9+B9)/2 -> 17 | E9: 0.64 | F9: 0 | G9: =F9*230 -> 0 | H9: 0 | I9: 0 | J9: 0 | K9: =+J9+H9 -> 0
A10: =ELEC!C9 -> 44932 | D10: =(C10+B10)/2 -> 0 | F10: 0 | G10: =F10*230 -> 0 | H10: 0 | I10: 0 | J10: 0 | K10: =+J10+H10 -> 0
A11: =ELEC!C10 -> 44933 | D11: =(C11+B11)/2 -> 0 | F11: 0 | G11: =F11*230 -> 0 | H11: 0 | I11: 0 | J11: 0 | K11: =+J11+H11 -> 0
A12: =ELEC!C11 -> 44934 | B12: 18 | C12: 16 | D12: =(C12+B12)/2 -> 17 | E12: 0.62 | F12: 0 | G12: =F12*230 -> 0 | H12: 0 | I12: 0 | J12: 0 | K12: =+J12+H12 -> 0
A13: =ELEC!C12 -> 44935 | B13: 19 | C13: 13 | D13: =(C13+B13)/2 -> 16 | E13: 0.6 | F13: 0 | G13: =F13*230 -> 0 | H13: 0 | I13: 0 | J13: 0 | K13: =+J13+H13 -> 0
A14: =ELEC!C13 -> 44936 | B14: 19 | C14: 13 | D14: =(C14+B14)/2 -> 16 | E14: 0.44 | F14: 0 | G14: =F14*230 -> 0 | H14: 0 | I14: 0 | J14: 0 | K14: =+J14+H14 -> 0
A15: =ELEC!C14 -> 44937 | B15: 19 | C15: 13 | D15: =(C15+B15)/2 -> 16 | E15: 0.49 | F15: 0 | G15: =F15*230 -> 0 | H15: 0 | I15: 0 | J15: 0 | K15: =+J15+H15 -> 0
A16: =ELEC!C15 -> 44938 | D16: =(C16+B16)/2 -> 0 | F16: 0 | G16: =F16*230 -> 0 | H16: 0 | I16: 0 | J16: 0 | K16: =+J16+H16 -> 0
A17: =ELEC!C16 -> 44939 | D17: =(C17+B17)/2 -> 0 | F17: 0 | G17: =F17*230 -> 0 | H17: 0 | I17: 0 | J17: 0 | K17: =+J17+H17 -> 0
A18: =ELEC!C17 -> 44940 | B18: 18 | C18: 13 | D18: =(C18+B18)/2 -> 15.5 | E18: 0.63 | F18: 0 | G18: =F18*230 -> 0 | H18: 0 | I18: 0 | J18: 0 | K18: =+J18+H18 -> 0
A19: =ELEC!C18 -> 44941 | B19: 19 | C19: 12 | D19: =(C19+B19)/2 -> 15.5 | E19: 0.7 | F19: 0 | G19: =F19*230 -> 0 | H19: 0 | I19: 0 | J19: 0 | K19: =+J19+H19 -> 0
A20: =ELEC!C19 -> 44942 | B20: 19 | C20: 13 | D20: =(C20+B20)/2 -> 16 | E20: 0.7 | F20: 0 | G20: =F20*230 -> 0 | H20: 0 | I20: 0 | J20: 0 | K20: =+J20+H20 -> 0
A21: =ELEC!C20 -> 44943 | B21: 19 | C21: 13 | D21: =(C21+B21)/2 -> 16 | E21: 0.65 | F21: 0 | G21: =F21*230 -> 0 | H21: 0 | I21: 0 | J21: 0 | K21: =+J21+H21 -> 0
A22: =ELEC!C21 -> 44944 | B22: 19 | C22: 14 | D22: =(C22+B22)/2 -> 16.5 | E22: 0.68 | F22: 0 | G22: =F22*230 -> 0 | H22: 0 | I22: 0 | J22: 0 | K22: =+J22+H22 -> 0
A23: =ELEC!C22 -> 44945 | B23: 20 | C23: 13 | D23: =(C23+B23)/2 -> 16.5 | E23: 0.41 | F23: 0 | G23: =F23*230 -> 0 | H23: 0 | I23: 0 | J23: 0 | K23: =+J23+H23 -> 0
A24: =ELEC!C23 -> 44946 | F24: 0 | G24: =F24*230 -> 0 | H24: 0 | I24: 0 | J24: 0 | K24: =+J24+H24 -> 0
A25: =ELEC!C24 -> 44947 | F25: 0 | G25: =F25*230 -> 0 | H25: 0 | I25: 0 | J25: 0 | K25: =+J25+H25 -> 0
A26: =ELEC!C25 -> 44948 | B26: 20 | C26: 23 | D26: =(C26+B26)/2 -> 21.5 | E26: 0.65 | F26: 0 | G26: =F26*230 -> 0 | H26: 0 | I26: 0 | J26: 0 | K26: =+J26+H26+I26 -> 0
A27: =ELEC!C26 -> 44949 | B27: 22 | C27: 13 | D27: =(C27+B27)/2 -> 17.5 | E27: 0.49 | F27: 0 | G27: =F27*230 -> 0 | H27: 0 | I27: 0 | J27: 0 | K27: =+J27+H27+I27 -> 0
A28: =ELEC!C27 -> 44950 | B28: 19 | C28: 13 | D28: =(C28+B28)/2 -> 16 | E28: 0.56 | F28: 0 | G28: =F28*230 -> 0 | H28: 0 | I28: 0 | J28: 0 | K28: =+J28+H28+I28 -> 0
A29: =ELEC!C28 -> 44951 | B29: 19 | C29: 13 | D29: =(C29+B29)/2 -> 16 | E29: 0.56 | F29: 0 | G29: =F29*230 -> 0 | H29: 0 | I29: 0 | J29: 0 | K29: =+J29+H29+I29 -> 0
A30: =ELEC!C29 -> 44952 | B30: 18 | C30: 14 | D30: =(C30+B30)/2 -> 16 | E30: 0.49 | F30: 0 | G30: =F30*230 -> 0 | H30: 0 | I30: 0 | J30: 0 | K30: =+J30+H30+I30 -> 0
A31: =ELEC!C30 -> 44953 | D31: =(C31+B31)/2 -> 0 | F31: 0 | G31: =F31*230 -> 0 | H31: 0 | I31: 0 | J31: 0 | K31: =+J31+H31+I31 -> 0
A32: =ELEC!C31 -> 44954 | D32: =(C32+B32)/2 -> 0 | F32: 0 | G32: =F32*230 -> 0 | H32: 0 | I32: 0 | J32: 0 | K32: =+J32+H32+I32 -> 0
A33: =ELEC!C32 -> 44955 | B33: 18 | C33: 15 | D33: =(C33+B33)/2 -> 16.5 | E33: 0.73 | F33: 0 | G33: =F33*230 -> 0 | H33: 0 | I33: 0 | J33: 0 | K33: =+J33+H33+I33 -> 0
A34: =ELEC!C33 -> 44956 | B34: 18 | C34: 11 | D34: =(C34+B34)/2 -> 14.5 | E34: 0.75 | F34: 0 | G34: =F34*230 -> 0 | H34: 0 | I34: 0 | J34: 0 | K34: =+J34+H34+I34 -> 0
A35: =ELEC!C34 -> 44957 | D35: =(C35+B35)/2 -> 0 | F35: 0 | G35: =F35*230 -> 0 | H35: 0 | I35: 0 | J35: 0 | K35: =+J35+H35+I35 -> 0
F36: =AVERAGE(F5:F35) -> 0 | G36: =SUM(G5:G35) -> 0
D37: =SUM(D5:D35)/'EDl log'!A35 -> 91.25
I40: http://www.accuweather.com/en/lb/lebanon-weather

Sheet GEN
B1: GEN1 | C1: RUN HR | D1: Fuel Counter Index | E1: Cons /day | F1: Diesel L/H | H1: next service | I1: ALARM | J1: GEN2 | K1: RUN HR | L1: Fuel Counter Index | M1: Cons /day | N1: Diesel L/H | P1: next service | Q1: ALARM | R1: GEN3 | S1: RUN HR | T1: Fuel Counter Index | U1: Cons /day | V1: Diesel L/H | X1: next service | Y1: ALARM | Z1: RH total | AA1: Gen Con /day | AB1: Total Deisel Cons/day | AC1: H /L | AD1: TOAL KW GEN | AI1: fuel Consuption | AK1: AVG KW/h
A2: 44926 | B2: 1724 | C2: 0 | D2: =[2]GEN!D32 -> 805681 | E2: =[2]GEN!E32 -> 1190 | F2: =[2]GEN!F32 -> 85 | G2: =[2]GEN!G32 -> 0 | H2: =[2]GEN!H32 -> 12231 | I2: =[2]GEN!I32 -> ok | J2: 146 | K2: =[2]GEN!K32 -> 0 | L2: =[2]GEN!L32 -> 392191 | M2: =[2]GEN!M32 -> 0 | N2: =[2]GEN!N32 -> 250 | O2: =[2]GEN!O32 -> 0 | P2: =[2]GEN!P32 -> 10873 | Q2: =[2]GEN!Q32 -> ok | R2: =[2]GEN!R32 -> 13917 | ... AL2: =[2]GEN!AL32 -> 1
A3: =ELEC!C4 -> 44927 | B3: 1724 | C3: =B3-B2 -> 0 | D3: =D2+C3*250 -> 805681 | E3: =SUM(D3-D2) -> 0 | F3: =IF(C3>0,E3/C3,0) -> 0 | G3: =[4]GEN!G32 -> #VALUE! | H3: =H2 -> 12231 | I3: =IF(B3-H3<=0,"ok","oil change") -> ok | J3: =J2 -> 146 | K3: =J3-J2 -> 0 | L3: =L2 -> 392191 | M3: =SUM(L3-L2) -> 0 | N3: 250 | O3: =[4]GEN!O32 -> #VALUE! | P3: =P2 -> 10873 | Q3: =IF(J3-P3<=0,"ok","oil change") -> ok | R3: =R2 -> 13917 | S3: =R3-R2 -> 0 | T3: =T2+U3 -> 418512 | U3: =V3*S3 -> 0 | V3: 250 | W3: =[4]GEN!W32 -> #VALUE! | X3: =X2 -> 14773 | Y3: =IF(R3-X3<=0,"ok","oil change") -> ok | Z3: =C3+K3+S3 -> 0 | AA3: =U3+M3+E3 -> 0 | AB3: =V3+N3+F3 -> 500 | AC3: =IF(Z3>0,AA3/Z3,0) -> 0 | AD3: =ELEC!Q4 -> 0 | AE3: =SUM(AD3/Z3) -> #DIV/0! | AF3: =SUM(AE3/1600) -> #DIV/0! | AG3: =SUM(360*AF3) -> #DIV/0! | AH3: =SUM(AC3-AG3) -> #DIV/0! | AI3: =AD3*AJ3 -> 0 | AJ3: =305/1185 -> 0.25738397 | AK3: =AI3/Z3 -> #DIV/0! | AL3: =IF(Z3=0,0,1) -> 0
A4: =ELEC!C5 -> 44928 | B4: 1724 | C4: =B4-B3 -> 0 | D4: =D3+C4*85 -> 805681 | E4: =SUM(D4-D3) -> 0 | F4: =IF(C4>0,E4/C4,0) -> 0 | H4: =H3 -> 12231 | I4: =IF(B4-H4<=0,"ok","oil change") -> ok | J4: =J3 -> 146 | K4: =J4-J3 -> 0 | L4: =L3 -> 392191 | M4: =SUM(L4-L3) -> 0 | N4: 250 | P4: =P3 -> 10873 | Q4: =IF(J4-P4<=0,"ok","oil change") -> ok | R4: =R3 -> 13917 | S4: =R4-R3 -> 0 | T4: =T3+U4 -> 418512 | U4: =V4*S4 -> 0 | V4: 250 | X4: =X3 -> 14773 | Y4: =IF(R4-X4<=0,"ok","oil change") -> ok | Z4: =C4+K4+S4 -> 0 | AA4: =U4+M4+E4 -> 0 | AB4: =V4+N4+F4 -> 500 | AC4: =IF(Z4>0,AA4/Z4,0) -> 0 | AD4: =ELEC!Q5 -> 0 | AE4: =SUM(AD4/Z4) -> #DIV/0! | AF4: =SUM(AE4/1600) -> #DIV/0! | AG4: =SUM(360*AF4) -> #DIV/0! | AH4: =SUM(AC4-AG4) -> #DIV/0! | AI4: =AD4*AJ4 -> 0 | AJ4: =305/1185 -> 0.25738397 | AK4: =AI4/Z4 -> #DIV/0! | AL4: =IF(Z4=0,0,1) -> 0
A5: =ELEC!C6 -> 44929 | B5: 1734 | C5: =B5-B4 -> 10 | D5: =D4+C5*85 -> 806531 | E5: =SUM(D5-D4) -> 850 | F5: =IF(C5>0,E5/C5,0) -> 85 | H5: =H4 -> 12231 | I5: =IF(B5-H5<=0,"ok","oil change") -> ok | J5: =J4 -> 146 | K5: =J5-J4 -> 0 | L5: =L4 -> 392191 | M5: =SUM(L5-L4) -> 0 | N5: 250 | P5: =P4 -> 10873 | Q5: =IF(J5-P5<=0,"ok","oil change") -> ok | R5: =R4 -> 13917 | S5: =R5-R4 -> 0 | T5: =T4+U5 -> 418512 | U5: =V5*S5 -> 0 | V5: 250 | X5: =X4 -> 14773 | Y5: =IF(R5-X5<=0,"ok","oil change") -> ok | Z5: =C5+K5+S5 -> 10 | AA5: =U5+M5+E5 -> 850 | AB5: =V5+N5+F5 -> 585 | AC5: =IF(Z5>0,AA5/Z5,0) -> 85 | AD5: =ELEC!Q6 -> 3419 | AE5: =SUM(AD5/Z5) -> 341.9 | AF5: =SUM(AE5/1600) -> 0.2136875 | AG5: =SUM(320*AF5) -> 68.38 | AH5: =SUM(AC5-AG5) -> 16.62 | AI5: =AD5*AJ5 -> 879.99578 | AJ5: =305/1185 -> 0.25738397 | AK5: =AI5/Z5 -> 87.999578 | AL5: =IF(Z5=0,0,1) -> 1
A6: =ELEC!C7 -> 44930 | B6: 1751 | C6: =B6-B5 -> 17 | D6: =D5+C6*85 -> 807976 | E6: =SUM(D6-D5) -> 1445 | F6: =IF(C6>0,E6/C6,0) -> 85 | H6: =H5 -> 12231 | I6: =IF(B6-H6<=0,"ok","oil change") -> ok | J6: =J5 -> 146 | K6: =J6-J5 -> 0 | L6: =(K6*N5)+L5 -> 392191 | M6: =SUM(L6-L5) -> 0 | N6: 250 | P6: =P5 -> 10873 | Q6: =IF(J6-P6<=0,"ok","oil change") -> ok | R6: =R5 -> 13917 | S6: =R6-R5 -> 0 | T6: =T5+U6 -> 418512 | U6: =V6*S6 -> 0 | V6: 250 | X6: =X5 -> 14773 | Y6: =IF(R6-X6<=0,"ok","oil change") -> ok | Z6: =C6+K6+S6 -> 17 | AA6: =U6+M6+E6 -> 1445 | AB6: =V6+N6+F6 -> 585 | AC6: =IF(Z6>0,AA6/Z6,0) -> 85 | AD6: =ELEC!Q7 -> 2737 | AE6: =SUM(AD6/Z6) -> 161 | AF6: =SUM(AE6/1600) -> 0.100625 | AG6: =SUM(320*AF6) -> 32.2 | AH6: =SUM(AC6-AG6) -> 52.8 | AI6: =AD6*AJ6 -> 704.45992 | AJ6: =305/1185 -> 0.25738397 | AK6: =AI6/Z6 -> 41.438819 | AL6: =IF(Z6=0,0,1) -> 1
A7: =ELEC!C8 -> 44931 | B7: 1761 | C7: =B7-B6 -> 10 | D7: =D6+C7*85 -> 808826 | E7: =SUM(D7-D6) -> 850 | F7: =IF(C7>0,E7/C7,0) -> 85 | H7: =H6 -> 12231 | I7: =IF(B7-H7<=0,"ok","oil change") -> ok | J7: 147 | L7: =(K7*N6)+L6 -> 392191 | M7: =SUM(L7-L6) -> 0 | N7: 250 | P7: =P6 -> 10873 | Q7: =IF(J7-P7<=0,"ok","oil change") -> ok | R7: =R6 -> 13917 | S7: =R7-R6 -> 0 | T7: =T6+U7 -> 418512 | U7: =V7*S7 -> 0 | V7: 250 | X7: =X6 -> 14773 | Y7: =IF(R7-X7<=0,"ok","oil change") -> ok | Z7: =C7+K7+S7 -> 10 | AA7: =U7+M7+E7 -> 850 | AB7: =V7+N7+F7 -> 585 | AC7: =IF(Z7>0,AA7/Z7,0) -> 85 | AD7: =ELEC!Q8 -> 2342 | AE7: =SUM(AD7/Z7) -> 234.2 | AF7: =SUM(AE7/1600) -> 0.146375 | AG7: =SUM(AF7/1600) -> 9.1484375e-05 | AH7: =SUM(AC7-AG7) -> 84.999909 | AI7: =AD7*AJ7 -> 602.79325 | AJ7: =305/1185 -> 0.25738397 | AK7: =AI7/Z7 -> 60.279325 | AL7: =IF(Z7=0,0,1) -> 1
A8: =ELEC!C9 -> 44932 | B8: =B7 -> 1761 | C8: =B8-B7 -> 0 | D8: =D7+C8*85 -> 808826 | E8: =SUM(D8-D7) -> 0 | F8: =IF(C8>0,E8/C8,0) -> 0 | H8: =H7 -> 12231 | I8: =IF(B8-H8<=0,"ok","oil change") -> ok | J8: =J7 -> 147 | K8: =J8-J7 -> 0 | L8: =(K8*N7)+L7 -> 392191 | M8: =SUM(L8-L7) -> 0 | N8: 250 | P8: =P7 -> 10873 | Q8: =IF(J8-P8<=0,"ok","oil change") -> ok | R8: =R7 -> 13917 | S8: =R8-R7 -> 0 | T8: =T7+U8 -> 418512 | U8: =V8*S8 -> 0 | V8: 250 | X8: =X7 -> 14773 | Y8: =IF(R8-X8<=0,"ok","oil change") -> ok | Z8: =C8+K8+S8 -> 0 | AA8: =U8+M8+E8 -> 0 | AB8: =V8+N8+F8 -> 500 | AC8: =IF(Z8>0,AA8/Z8,0) -> 0 | AD8: =ELEC!Q9 -> 0 | AE8: =SUM(AD8/Z8) -> #DIV/0! | AF8: =SUM(AE8/1600) -> #DIV/0! | AG8: =SUM(AF8/1600) -> #DIV/0! | AH8: =SUM(AC8-AG8) -> #DIV/0! | AI8: =AD8*AJ8 -> 0 | AJ8: =305/1185 -> 0.25738397 | AK8: =AI8/Z8 -> #DIV/0! | AL8: =IF(Z8=0,0,1) -> 0
A9: =ELEC!C10 -> 44933 | B9: =B8 -> 1761 | C9: =B9-B8 -> 0 | D9: =D8+C9*85 -> 808826 | E9: =SUM(D9-D8) -> 0 | F9: =IF(C9>0,E9/C9,0) -> 0 | H9: =H8 -> 12231 | I9: =IF(B9-H9<=0,"ok","oil change") -> ok | J9: =J8 -> 147 | K9: =J9-J8 -> 0 | L9: =(K9*N8)+L8 -> 392191 | M9: =SUM(L9-L8) -> 0 | N9: 250 | P9: =P8 -> 10873 | Q9: =IF(J9-P9<=0,"ok","oil change") -> ok | R9: =R8 -> 13917 | S9: =R9-R8 -> 0 | T9: =T8+U9 -> 418512 | U9: =V9*S9 -> 0 | V9: 250 | X9: =X8 -> 14773 | Y9: =IF(R9-X9<=0,"ok","oil change") -> ok | Z9: =C9+K9+S9 -> 0 | AA9: =U9+M9+E9 -> 0 | AB9: =V9+N9+F9 -> 500 | AC9: =IF(Z9>0,AA9/Z9,0) -> 0 | AD9: =ELEC!Q10 -> 0 | AE9: =SUM(AD9/Z9) -> #DIV/0! | AF9: =SUM(AE9/1600) -> #DIV/0! | AG9: =SUM(AF9/1600) -> #DIV/0! | AH9: =SUM(AC9-AG9) -> #DIV/0! | AI9: =AD9*AJ9 -> 0 | AJ9: =305/1185 -> 0.25738397 | AK9: =AI9/Z9 -> #DIV/0! | AL9: =IF(Z9=0,0,1) -> 0
A10: =ELEC!C11 -> 44934 | B10: 1772 | C10: =B10-B9 -> 11 | D10: =D9+C10*85 -> 809761 | E10: =SUM(D10-D9) -> 935 | F10: =IF(C10>0,E10/C10,0) -> 85 | H10: =H9 -> 12231 | I10: =IF(B10-H10<=0,"ok","oil change") -> ok | J10: =J9 -> 147 | K10: =J10-J9 -> 0 | L10: =(K10*N9)+L9 -> 392191 | M10: =SUM(L10-L9) -> 0 | N10: 250 | P10: =P9 -> 10873 | Q10: =IF(J10-P10<=0,"ok","oil change") -> ok | R10: 13918 | S10: =R10-R9 -> 1 | T10: =T9+U10 -> 418762 | U10: =V10*S10 -> 250 | V10: 250 | X10: =X9 -> 14773 | Y10: =IF(R10-X10<=0,"ok","oil change") -> ok | Z10: =C10+K10+S10 -> 12 | AA10: =U10+M10+E10 -> 1185 | AB10: =V10+N10+F10 -> 585 | AC10: =IF(Z10>0,AA10/Z10,0) -> 98.75 | AD10: =ELEC!Q11 -> 2362 | AE10: =SUM(AD10/Z10) -> 196.83333 | AF10: =SUM(AE10/1600) -> 0.12302083 | AG10: =SUM(AF10/1600) -> 7.6888021e-05 | AH10: =SUM(AC10-AG10) -> 98.749923 | AI10: =AD10*AJ10 -> 607.94093 | AJ10: =305/1185 -> 0.25738397 | AK10: =AI10/Z10 -> 50.661744 | AL10: =IF(Z10=0,0,1) -> 1
A11: =ELEC!C12 -> 44935 | B11: 1787 | C11: =B11-B10 -> 15 | D11: =D10+C11*85 -> 811036 | E11: =SUM(D11-D10) -> 1275 | F11: =IF(C11>0,E11/C11,0) -> 85 | H11: =H10 -> 12231 | I11: =IF(B11-H11<=0,"ok","oil change") -> ok | J11: =J10 -> 147 | K11: =J11-J10 -> 0 | L11: =(K11*N10)+L10 -> 392191 | M11: =SUM(L11-L10) -> 0 | N11: 250 | P11: =P10 -> 10873 | Q11: =IF(J11-P11<=0,"ok","oil change") -> ok | R11: =R10 -> 13918 | S11: =R11-R10 -> 0 | T11: =T10+U11 -> 418762 | U11: =V11*S11 -> 0 | V11: 250 | X11: =X10 -> 14773 | Y11: =IF(R11-X11<=0,"ok","oil change") -> ok | Z11: =C11+K11+S11 -> 15 | AA11: =U11+M11+E11 -> 1275 | AB11: =V11+N11+F11 -> 585 | AC11: =IF(Z11>0,AA11/Z11,0) -> 85 | AD11: =ELEC!Q12 -> 3133 | AE11: =SUM(AD11/Z11) -> 208.86667 | AF11: =SUM(AE11/1600) -> 0.13054167 | AG11: =SUM(AF11/1600) -> 8.1588542e-05 | AH11: =SUM(AC11-AG11) -> 84.999918 | AI11: =AD11*AJ11 -> 806.38397 | AJ11: =305/1185 -> 0.25738397 | AK11: =AI11/Z11 -> 53.758931 | AL11: =IF(Z11=0,0,1) -> 1
A12: =ELEC!C13 -> 44936 | B12: 1800 | C12: =B12-B11 -> 13 | D12: =D11+C12*85 -> 812141 | E12: =SUM(D12-D11) -> 1105 | F12: =IF(C12>0,E12/C12,0) -> 85 | H12: =H11 -> 12231 | I12: =IF(B12-H12<=0,"ok","oil change") -> ok | J12: =J11 -> 147 | K12: =J12-J11 -> 0 | L12: =(K12*N11)+L11 -> 392191 | M12: =SUM(L12-L11) -> 0 | N12: 250 | P12: =P11 -> 10873 | Q12: =IF(J12-P12<=0,"ok","oil change") -> ok | R12: =R11 -> 13918 | S12: =R12-R11 -> 0 | T12: =T11+U12 -> 418762 | U12: =V12*S12 -> 0 | V12: 250 | X12: =X11 -> 14773 | Y12: =IF(R12-X12<=0,"ok","oil change") -> ok | Z12: =C12+K12+S12 -> 13 | AA12: =U12+M12+E12 -> 1105 | AB12: =V12+N12+F12 -> 585 | AC12: =IF(Z12>0,AA12/Z12,0) -> 85 | AD12: =ELEC!Q13 -> 2958 | AE12: =SUM(AD12/Z12) -> 227.53846 | AF12: =SUM(AE12/1600) -> 0.14221154 | AG12: =SUM(AF12/1600) -> 8.8882212e-05 | AH12: =SUM(AC12-AG12) -> 84.999911 | AI12: =AD12*AJ12 -> 761.34177 | AJ12: =305/1185 -> 0.25738397 | AK12: =AI12/Z12 -> 58.564752 | AL12: =IF(Z12=0,0,1) -> 1
A13: =ELEC!C14 -> 44937 | B13: 1809 | C13: =B13-B12 -> 9 | D13: =D12+C13*85 -> 812906 | E13: =SUM(D13-D12) -> 765 | F13: =IF(C13>0,E13/C13,0) -> 85 | H13: =H12 -> 12231 | I13: =IF(B13-H13<=0,"ok","oil change") -> ok | J13: =J12 -> 147 | K13: =J13-J12 -> 0 | L13: =(K13*N12)+L12 -> 392191 | M13: =SUM(L13-L12) -> 0 | N13: 250 | P13: =P12 -> 10873 | Q13: =IF(J13-P13<=0,"ok","oil change") -> ok | R13: =R12 -> 13918 | S13: =R13-R12 -> 0 | T13: =T12+U13 -> 418762 | U13: =V13*S13 -> 0 | V13: 250 | X13: =X12 -> 14773 | Y13: =IF(R13-X13<=0,"ok","oil change") -> ok | Z13: =C13+K13+S13 -> 9 | AA13: =U13+M13+E13 -> 765 | AB13: =V13+N13+F13 -> 585 | AC13: =IF(Z13>0,AA13/Z13,0) -> 85 | AD13: =ELEC!Q14 -> 1457 | AE13: =SUM(AD13/Z13) -> 161.88889 | AF13: =SUM(AE13/1600) -> 0.10118056 | AG13: =SUM(AF13/1600) -> 6.3237847e-05 | AH13: =SUM(AC13-AG13) -> 84.999937 | AI13: =AD13*AJ13 -> 375.00844 | AJ13: =305/1185 -> 0.25738397 | AK13: =AI13/Z13 -> 41.667604 | AL13: =IF(Z13=0,0,1) -> 1
A14: =ELEC!C15 -> 44938 | B14: 1823 | C14: =B14-B13 -> 14 | D14: =D13+C14*85 -> 814096 | E14: =SUM(D14-D13) -> 1190 | F14: =IF(C14>0,E14/C14,0) -> 85 | H14: =H13 -> 12231 | I14: =IF(B14-H14<=0,"ok","oil change") -> ok | J14: =J13 -> 147 | K14: =J14-J13 -> 0 | L14: =(K14*N13)+L13 -> 392191 | M14: =SUM(L14-L13) -> 0 | N14: 250 | P14: =P13 -> 10873 | Q14: =IF(J14-P14<=0,"ok","oil change") -> ok | R14: =R13 -> 13918 | S14: =R14-R13 -> 0 | T14: =T13+U14 -> 418762 | U14: =V14*S14 -> 0 | V14: 250 | X14: =X13 -> 14773 | Y14: =IF(R14-X14<=0,"ok","oil change") -> ok | Z14: =C14+K14+S14 -> 14 | AA14: =U14+M14+E14 -> 1190 | AB14: =V14+N14+F14 -> 585 | AC14: =IF(Z14>0,AA14/Z14,0) -> 85 | AD14: =ELEC!Q15 -> 3241 | AE14: =SUM(AD14/Z14) -> 231.5 | AF14: =SUM(AE14/1600) -> 0.1446875 | AG14: =SUM(AF14/1600) -> 9.0429687e-05 | AH14: =SUM(AC14-AG14) -> 84.99991 | AI14: =AD14*AJ14 -> 834.18143 | AJ14: =305/1185 -> 0.25738397 | AK14: =AI14/Z14 -> 59.584388 | AL14: =IF(Z14=0,0,1) -> 1
A15: =ELEC!C16 -> 44939 | B15: =B14 -> 1823 | C15: =B15-B14 -> 0 | D15: =D14+C15*85 -> 814096 | E15: =SUM(D15-D14) -> 0 | F15: =IF(C15>0,E15/C15,0) -> 0 | H15: =H14 -> 12231 | I15: =IF(B15-H15<=0,"ok","oil change") -> ok | J15: =J14 -> 147 | K15: =J15-J14 -> 0 | L15: =(K15*N14)+L14 -> 392191 | M15: =SUM(L15-L14) -> 0 | N15: 250 | P15: =P14 -> 10873 | Q15: =IF(J15-P15<=0,"ok","oil change") -> ok | R15: =R14 -> 13918 | S15: =R15-R14 -> 0 | T15: =T14+U15 -> 418762 | U15: =V15*S15 -> 0 | V15: 250 | X15: =X14 -> 14773 | Y15: =IF(R15-X15<=0,"ok","oil change") -> ok | Z15: =C15+K15+S15 -> 0 | AA15: =U15+M15+E15 -> 0 | AB15: =V15+N15+F15 -> 500 | AC15: =IF(Z15>0,AA15/Z15,0) -> 0 | AD15: =ELEC!Q16 -> 0 | AE15: =SUM(AD15/Z15) -> #DIV/0! | AF15: =SUM(AE15/1600) -> #DIV/0! | AG15: =SUM(AF15/1600) -> #DIV/0! | AH15: =SUM(AC15-AG15) -> #DIV/0! | AI15: =AD15*AJ15 -> 0 | AJ15: =305/1185 -> 0.25738397 | AK15: =AI15/Z15 -> #DIV/0! | AL15: =IF(Z15=0,0,1) -> 0
A16: =ELEC!C17 -> 44940 | B16: =B15 -> 1823 | C16: =B16-B15 -> 0 | D16: =D15+C16*85 -> 814096 | E16: =SUM(D16-D15) -> 0 | F16: =IF(C16>0,E16/C16,0) -> 0 | H16: =H15 -> 12231 | I16: =IF(B16-H16<=0,"ok","oil change") -> ok | J16: =J15 -> 147 | K16: =J16-J15 -> 0 | L16: =(K16*N15)+L15 -> 392191 | M16: =SUM(L16-L15) -> 0 | N16: 250 | P16: =P15 -> 10873 | Q16: =IF(J16-P16<=0,"ok","oil change") -> ok | R16: =R15 -> 13918 | S16: =R16-R15 -> 0 | T16: =T15+U16 -> 418762 | U16: =V16*S16 -> 0 | V16: 250 | X16: =X15 -> 14773 | Y16: =IF(R16-X16<=0,"ok","oil change") -> ok | Z16: =C16+K16+S16 -> 0 | AA16: =U16+M16+E16 -> 0 | AB16: =V16+N16+F16 -> 500 | AC16: =IF(Z16>0,AA16/Z16,0) -> 0 | AD16: =ELEC!Q17 -> 0 | AE16: =SUM(AD16/Z16) -> #DIV/0! | AF16: =SUM(AE16/1600) -> #DIV/0! | AG16: =SUM(AF16/1600) -> #DIV/0! | AH16: =SUM(AC16-AG16) -> #DIV/0! | AI16: =AD16*AJ16 -> 0 | AJ16: =305/1185 -> 0.25738397 | AK16: =AI16/Z16 -> #DIV/0! | AL16: =IF(Z16=0,0,1) -> 0
A17: =ELEC!C18 -> 44941 | B17: 1837 | C17: =B17-B16 -> 14 | D17: =D16+C17*85 -> 815286 | E17: =SUM(D17-D16) -> 1190 | F17: =IF(C17>0,E17/C17,0) -> 85 | H17: =H16 -> 12231 | I17: =IF(B17-H17<=0,"ok","oil change") -> ok | J17: =J16 -> 147 | K17: =J17-J16 -> 0 | L17: =(K17*N16)+L16 -> 392191 | M17: =SUM(L17-L16) -> 0 | N17: 250 | P17: =P16 -> 10873 | Q17: =IF(J17-P17<=0,"ok","oil change") -> ok | R17: =R16 -> 13918 | S17: =R17-R16 -> 0 | T17: =T16+U17 -> 418762 | U17: =V17*S17 -> 0 | V17: 250 | X17: =X16 -> 14773 | Y17: =IF(R17-X17<=0,"ok","oil change") -> ok | Z17: =C17+K17+S17 -> 14 | AA17: =U17+M17+E17 -> 1190 | AB17: =V17+N17+F17 -> 585 | AC17: =IF(Z17>0,AA17/Z17,0) -> 85 | AD17: =ELEC!Q18 -> 4096 | AE17: =SUM(AD17/Z17) -> 292.57143 | AF17: =SUM(AE17/1600) -> 0.18285714 | AG17: =SUM(AF17/1600) -> 0.00011428571 | AH17: =SUM(AC17-AG17) -> 84.999886 | AI17: =AD17*AJ17 -> 1054.2447 | AJ17: =305/1185 -> 0.25738397 | AK17: =AI17/Z17 -> 75.303195 | AL17: =IF(Z17=0,0,1) -> 1
A18: =ELEC!C19 -> 44942 | B18: 1850 | C18: =B18-B17 -> 13 | D18: =D17+C18*85 -> 816391 | E18: =SUM(D18-D17) -> 1105 | F18: =IF(C18>0,E18/C18,0) -> 85 | H18: =H17 -> 12231 | I18: =IF(B18-H18<=0,"ok","oil change") -> ok | J18: =J17 -> 147 | K18: =J18-J17 -> 0 | L18: =(K18*N17)+L17 -> 392191 | M18: =SUM(L18-L17) -> 0 | N18: 250 | P18: =P17 -> 10873 | Q18: =IF(J18-P14<=0,"ok","oil change") -> ok | R18: =R17 -> 13918 | S18: =R18-R17 -> 0 | T18: =T17+U18 -> 418762 | U18: =V18*S18 -> 0 | V18: 250 | X18: =X17 -> 14773 | Y18: =IF(R18-X18<=0,"ok","oil change") -> ok | Z18: =C18+K18+S18 -> 13 | AA18: =U18+M18+E18 -> 1105 | AB18: =V18+N18+F18 -> 585 | AC18: =IF(Z18>0,AA18/Z18,0) -> 85 | AD18: =ELEC!Q19 -> 3332 | AE18: =SUM(AD18/Z18) -> 256.30769 | AF18: =SUM(AE18/1600) -> 0.16019231 | AG18: =SUM(AF18/1600) -> 0.00010012019 | AH18: =SUM(AC18-AG18) -> 84.9999 | AI18: =AD18*AJ18 -> 857.60338 | AJ18: =305/1185 -> 0.25738397 | AK18: =AI18/Z18 -> 65.96949 | AL18: =IF(Z18=0,0,1) -> 1
A19: =ELEC!C20 -> 44943 | B19: 1860 | C19: =B19-B18 -> 10 | D19: =D18+C19*85 -> 817241 | E19: =SUM(D19-D18) -> 850 | F19: =IF(C19>0,E19/C19,0) -> 85 | H19: =H18 -> 12231 | I19: =IF(B19-H19<=0,"ok","oil change") -> ok | J19: =J18 -> 147 | K19: =J19-J18 -> 0 | L19: =(K19*N18)+L18 -> 392191 | M19: =SUM(L19-L18) -> 0 | N19: 250 | P19: =P18 -> 10873 | Q19: =IF(J19-P19<=0,"ok","oil change") -> ok | R19: =R18 -> 13918 | S19: =R19-R18 -> 0 | T19: =T18+U19 -> 418762 | U19: =V19*S19 -> 0 | V19: 250 | X19: =X18 -> 14773 | Y19: =IF(R19-X19<=0,"ok","oil change") -> ok | Z19: =C19+K19+S19 -> 10 | AA19: =U19+M19+E19 -> 850 | AB19: =V19+N19+F19 -> 585 | AC19: =IF(Z19>0,AA19/Z19,0) -> 85 | AD19: =ELEC!Q20 -> 3173 | AE19: =SUM(AD19/Z19) -> 317.3 | AF19: =SUM(AE19/1600) -> 0.1983125 | AG19: =SUM(AF19/1600) -> 0.00012394531 | AH19: =SUM(AC19-AG19) -> 84.999876 | AI19: =AD19*AJ19 -> 816.67932 | AJ19: =305/1185 -> 0.25738397 | AK19: =AI19/Z19 -> 81.667932 | AL19: =IF(Z19=0,0,1) -> 1
A20: =ELEC!C21 -> 44944 | B20: 1874 | C20: =B20-B19 -> 14 | D20: =D19+C20*85 -> 818431 | E20: =SUM(D20-D19) -> 1190 | F20: =IF(C20>0,E20/C20,0) -> 85 | H20: =H19 -> 12231 | I20: =IF(B20-H20<=0,"ok","oil change") -> ok | J20: =J19 -> 147 | K20: =J20-J19 -> 0 | L20: =(K20*N19)+L19 -> 392191 | M20: =SUM(L20-L19) -> 0 | N20: 250 | P20: =P19 -> 10873 | Q20: =IF(J20-P20<=0,"ok","oil change") -> ok | R20: 13918 | S20: =R20-R19 -> 0 | T20: =T19+U20 -> 418762 | U20: =V20*S20 -> 0 | V20: 250 | X20: =X19 -> 14773 | Y20: =IF(R20-X20<=0,"ok","oil change") -> ok | Z20: =C20+K20+S20 -> 14 | AA20: =U20+M20+E20 -> 1190 | AB20: =V20+N20+F20 -> 585 | AC20: =IF(Z20>0,AA20/Z20,0) -> 85 | AD20: =ELEC!Q21 -> 3580 | AE20: =SUM(AD20/Z20) -> 255.71429 | AF20: =SUM(AE20/1600) -> 0.15982143 | AG20: =SUM(AF20/1600) -> 9.9888393e-05 | AH20: =SUM(AC20-AG20) -> 84.9999 | AI20: =AD20*AJ20 -> 921.4346 | AJ20: =305/1185 -> 0.25738397 | AK20: =AI20/Z20 -> 65.816757 | AL20: =IF(Z20=0,0,1) -> 1
A21: =ELEC!C22 -> 44945 | B21: 1883 | C21: =B21-B20 -> 9 | D21: =D20+C21*85 -> 819196 | E21: =SUM(D21-D20) -> 765 | F21: =IF(C21>0,E21/C21,0) -> 85 | H21: =H20 -> 12231 | I21: =IF(B21-H21<=0,"ok","oil change") -> ok | J21: =J20 -> 147 | K21: =J21-J20 -> 0 | L21: =(K21*N20)+L20 -> 392191 | M21: =SUM(L21-L20) -> 0 | N21: 250 | P21: =P20 -> 10873 | Q21: =IF(J21-P21<=0,"ok","oil change") -> ok | R21: 13920 | S21: =R21-R20 -> 2 | T21: =T20+U21 -> 419262 | U21: =V21*S21 -> 500 | V21: 250 | X21: =X20 -> 14773 | Y21: =IF(R21-X21<=0,"ok","oil change") -> ok | Z21: =C21+K21+S21 -> 11 | AA21: =U21+M21+E21 -> 1265 | AB21: =V21+N21+F21 -> 585 | AC21: =IF(Z21>0,AA21/Z21,0) -> 115 | AD21: =ELEC!Q22 -> 3290 | AE21: =SUM(AD21/Z21) -> 299.09091 | AF21: =SUM(AE21/1600) -> 0.18693182 | AG21: =SUM(AF21/1600) -> 0.00011683239 | AH21: =SUM(AC21-AG21) -> 114.99988 | AI21: =AD21*AJ21 -> 846.79325 | AJ21: =305/1185 -> 0.25738397 | AK21: =AI21/Z21 -> 76.981204 | AL21: =IF(Z21=0,0,1) -> 1
A22: =ELEC!C23 -> 44946 | B22: =B21 -> 1883 | C22: =B22-B21 -> 0 | D22: =D21+C22*85 -> 819196 | E22: =SUM(D22-D21) -> 0 | F22: =IF(C22>0,E22/C22,0) -> 0 | H22: =H21 -> 12231 | I22: =IF(B22-H22<=0,"ok","oil change") -> ok | J22: =J21 -> 147 | K22: =J22-J21 -> 0 | L22: =(K22*N21)+L21 -> 392191 | M22: =SUM(L22-L21) -> 0 | N22: 250 | P22: =P21 -> 10873 | Q22: =IF(J22-P22<=0,"ok","oil change") -> ok | R22: =R21 -> 13920 | S22: =R22-R21 -> 0 | T22: =T21+U22 -> 419262 | U22: =V22*S22 -> 0 | V22: 250 | X22: =X21 -> 14773 | Y22: =IF(R22-X22<=0,"ok","oil change") -> ok | Z22: =C22+K22+S22 -> 0 | AA22: =U22+M22+E22 -> 0 | AB22: =V22+N22+F22 -> 500 | AC22: =IF(Z22>0,AA22/Z22,0) -> 0 | AD22: =ELEC!Q23 -> 0 | AE22: =SUM(AD22/Z22) -> #DIV/0! | AF22: =SUM(AE22/1600) -> #DIV/0! | AG22: =SUM(AF22/1600) -> #DIV/0! | AH22: =SUM(AC22-AG22) -> #DIV/0! | AI22: =AD22*AJ22 -> 0 | AJ22: =305/1185 -> 0.25738397 | AK22: =AI22/Z22 -> #DIV/0! | AL22: =IF(Z22=0,0,1) -> 0
A23: =ELEC!C24 -> 44947 | B23: =B22 -> 1883 | C23: =B23-B22 -> 0 | D23: =D22+C23*85 -> 819196 | E23: =SUM(D23-D22) -> 0 | F23: =IF(C23>0,E23/C23,0) -> 0 | H23: =H22 -> 12231 | I23: =IF(B23-H23<=0,"ok","oil change") -> ok | J23: =J22 -> 147 | K23: =J23-J22 -> 0 | L23: =(K23*N22)+L22 -> 392191 | M23: =SUM(L23-L22) -> 0 | N23: 250 | P23: =P22 -> 10873 | Q23: =IF(J23-P23<=0,"ok","oil change") -> ok | R23: =R22 -> 13920 | S23: =R23-R22 -> 0 | T23: =T22+U23 -> 419262 | U23: =V23*S23 -> 0 | V23: 250 | X23: =X22 -> 14773 | Y23: =IF(R23-X23<=0,"ok","oil change") -> ok | Z23: =C23+K23+S23 -> 0 | AA23: =U23+M23+E23 -> 0 | AB23: =V23+N23+F23 -> 500 | AC23: =IF(Z23>0,AA23/Z23,0) -> 0 | AD23: =ELEC!Q24 -> 0 | AE23: =SUM(AD23/Z23) -> #DIV/0! | AF23: =SUM(AE23/1600) -> #DIV/0! | AG23: =SUM(AF23/1600) -> #DIV/0! | AH23: =SUM(AC23-AG23) -> #DIV/0! | AI23: =AD23*AJ23 -> 0 | AJ23: =305/1185 -> 0.25738397 | AK23: =AI23/Z23 -> #DIV/0! | AL23: =IF(Z23=0,0,1) -> 0
A24: =ELEC!C25 -> 44948 | B24: 1894 | C24: =B24-B23 -> 11 | D24: =D23+C24*85 -> 820131 | E24: =SUM(D24-D23) -> 935 | F24: =IF(C24>0,E24/C24,0) -> 85 | H24: =H23 -> 12231 | I24: =IF(B24-H24<=0,"ok","oil change") -> ok | J24: 148 | K24: =J24-J23 -> 1 | L24: =(K24*N23)+L23 -> 392441 | M24: =SUM(L24-L23) -> 250 | N24: 250 | P24: =P23 -> 10873 | Q24: =IF(J24-P24<=0,"ok","oil change") -> ok | R24: =R23 -> 13920 | S24: =R24-R23 -> 0 | T24: =T23+U24 -> 419262 | U24: =V24*S24 -> 0 | V24: 250 | X24: =X23 -> 14773 | Y24: =IF(R24-X24<=0,"ok","oil change") -> ok | Z24: =C24+K24+S24 -> 12 | AA24: =U24+M24+E24 -> 1185 | AB24: =V24+N24+F24 -> 585 | AC24: =IF(Z24>0,AA24/Z24,0) -> 98.75 | AD24: =ELEC!Q25 -> 2948 | AE24: =SUM(AD24/Z24) -> 245.66667 | AF24: =SUM(AE24/1600) -> 0.15354167 | AG24: =SUM(AF24/1600) -> 9.5963542e-05 | AH24: =SUM(AC24-AG24) -> 98.749904 | AI24: =AD24*AJ24 -> 758.76793 | AJ24: =305/1185 -> 0.25738397 | AK24: =AI24/Z24 -> 63.230661 | AL24: =IF(Z24=0,0,1) -> 1
A25: =ELEC!C26 -> 44949 | B25: 1904 | C25: =B25-B24 -> 10 | D25: =D24+C25*85 -> 820981 | E25: =SUM(D25-D24) -> 850 | F25: =IF(C25>0,E25/C25,0) -> 85 | H25: =H24 -> 12231 | I25: =IF(B25-H25<=0,"ok","oil change") -> ok | J25: =J24 -> 148 | K25: =J25-J24 -> 0 | L25: =(K25*N24)+L24 -> 392441 | M25: =SUM(L25-L24) -> 0 | N25: 250 | P25: =P24 -> 10873 | Q25: =IF(J25-P25<=0,"ok","oil change") -> ok | R25: =R24 -> 13920 | S25: =R25-R24 -> 0 | T25: =T24+U25 -> 419262 | U25: =V25*S25 -> 0 | V25: 250 | X25: =X24 -> 14773 | Y25: =IF(R25-X25<=0,"ok","oil change") -> ok | Z25: =C25+K25+S25 -> 10 | AA25: =U25+M25+E25 -> 850 | AB25: =V25+N25+F25 -> 585 | AC25: =IF(Z25>0,AA25/Z25,0) -> 85 | AD25: =ELEC!Q26 -> 2502 | AE25: =SUM(AD25/Z25) -> 250.2 | AF25: =SUM(AE25/1600) -> 0.156375 | AG25: =SUM(AF25/1600) -> 9.7734375e-05 | AH25: =SUM(AC25-AG25) -> 84.999902 | AI25: =AD25*AJ25 -> 643.97468 | AJ25: =305/1185 -> 0.25738397 | AK25: =AI25/Z25 -> 64.397468 | AL25: =IF(Z25=0,0,1) -> 1
