Workbook

Sheet Utility Consnsumption
E6: HL&P Utility Consumption | H6: =Elect!A1 -> 44896
B9: Electric Power Consumption
B11: Chiller Central Plant | D11: Guest Rooms | F11: Public areas / Utilities Power & Light | H11: Grumandize | J11: Total Consumption | L11: Total First Arabian bill
B12: KW.hr | C12: LE | D12: KW.hr | E12: LE | F12: KW.hr | G12: LE | H12: KW.hr | I12: LE | J12: KW.hr | K12: LE | L12: KW.hr | M12: LE
B13: =Elect!AN37 -> 172525.16 | C13: =(B13*1.15)+(2879*60*0.72) -> 322776.73 | D13: =Elect!J37 -> 195595.22 | E13: =(D13*1.15)+(573*60)+10000 -> 269314.51 | F13: =Elect!BI37 -> 382141.79 | G13: =(F13*1.15) -> 439463.06 | H13: =Elect!Q37 -> 14785 | I13: =H13*1.6+1500 -> 25156 | J13: =B13+D13+F13+H13 -> 765047.17 | K13: =G13+E13+C13+I13 -> 1056710.3 | L13: =B13+F13 -> 554666.95 | M13: =C13+G13 -> 762239.79
K16: =K18 -> 1389950.4
E17: Water Consumption / As per share ratio | J17: Average elec Tariff | K17: =K13/J13 -> 1.3812355
J18: Utilties total EGP | K18: =K13+F20+F27+G35 -> 1389950.4
E19: M3 | F19: LE
E20: =Water!H38 -> 10279.968 | F20: =E20*10 -> 102799.68
E24: Natural Gas Consumption
E26: M3 | F26: LE
E27: =Gas!C38 -> 47727.118 | F27: =E27*3.9 -> 186135.76
D31: Plant Room Gas Share ( STEAM)
D33: Last Reading | E33: Present Reading | F33: M 3 | G33: LE
D34: =Gas!D6 -> 598602.33 | E34: =Gas!D36 -> 614265.22 | F34: =Gas!E38 -> 11360.164 | G34: =F34*3.9 -> 44304.639
D35: Total Amount | G35: =G34 -> 44304.639
D38: Casino Electricity Charge
D40: Last Reading | E40: Present Reading | F40: KW.hr | G40: LE
C41: Casino 3rd floor EM | D41: =Elect!R5 -> 226100.67 | E41: =Elect!R36 -> 230535.33 | F41: =E41-D41 -> 4434.6667 | G41: =F41*1.15 -> 5099.8667
C42: Casino 3rd floor Normal | D42: =Elect!T5 -> 412645.67 | E42: =Elect!T36 -> 420593.17 | F42: =E42-D42 -> 7947.5 | G42: =F42*1.15 -> 9139.625
D43: Total Amount | G43: =G42+G41 -> 14239.492
D49: New Casino Water Charge
D51: Last Reading | E51: Present Reading | F51: M3 | G51: LE
C52: Hot Water | D52: 310 | E52: 322 | F52: 12 | G52: =F52*10 -> 120
C53: Cold Water | D53: 5476 | E53: 5583 | F53: 107 | G53: =F53*10 -> 1070
D54: Total Amount | G54: =G52+G53 -> 1190

Sheet Total
A1: Site Name | B1: Day | C1: Month | D1: Year | E1: Total Electricity Kwh | F1: Electricity Tariff ($/Kwh) | G1: Natual Gas (m3) | H1: Natural Gas $/m3 | I1: Water Utility Supply (m3) m3 | J1: Water Utility Supply (m3) $/m3 | K1: Room Nights
A2: Cairo at The First Residence | B2: 1 | C2: 12 | D2: 2022 | E2: =Elect!BS6+Submetering!AH2 -> 26916.463 | F2: ='Utility Consnsumption'!K13/'Utility Consnsumption'!J13 -> 1.3812355 | G2: =Gas!K7+Submetering!AR2 -> 1803.1867 | H2: 3.8 | I2: =Water!H7+Submetering!AM2 -> 819.15333 | J2: 10 | K2: =Elect!BT6 -> 210
A3: Cairo at The First Residence | B3: =B2+1 -> 2 | C3: 12 | D3: 2022 | E3: =Elect!BS7+Submetering!AH3 -> 24471.715 | F3: =F2 -> 1.3812355 | G3: =Gas!K8+Submetering!AR3 -> 1988.8 | H3: 3.8 | I3: =Water!H8+Submetering!AM3 -> 179.54222 | J3: 10 | K3: =Elect!BT7 -> 242
A4: Cairo at The First Residence | B4: =B3+1 -> 3 | C4: 12 | D4: 2022 | E4: =Elect!BS8+Submetering!AH4 -> 25340.555 | F4: =F3 -> 1.3812355 | G4: =Gas!K9+Submetering!AR4 -> 1988.8 | H4: 3.8 | I4: =Water!H9+Submetering!AM4 -> 239.41111 | J4: 10 | K4: =Elect!BT8 -> 225
A5: Cairo at The First Residence | B5: =B4+1 -> 4 | C5: 12 | D5: 2022 | E5: =Elect!BS9+Submetering!AH5 -> 25596.628 | F5: =F4 -> 1.3812355 | G5: =Gas!K10+Submetering!AR5 -> 1981.8 | H5: 3.8 | I5: =Water!H10+Submetering!AM5 -> 272.98667 | J5: 10 | K5: =Elect!BT9 -> 236
A6: Cairo at The First Residence | B6: =B5+1 -> 5 | C6: 12 | D6: 2022 | E6: =Elect!BS10+Submetering!AH6 -> 25205.725 | F6: =F5 -> 1.3812355 | G6: =Gas!K11+Submetering!AR6 -> 1981.8 | H6: 3.8 | I6: =Water!H11+Submetering!AM6 -> 325.38 | J6: 10 | K6: =Elect!BT10 -> 216
A7: Cairo at The First Residence | B7: =B6+1 -> 6 | C7: 12 | D7: 2022 | E7: =Elect!BS11+Submetering!AH7 -> 23281.213 | F7: =F6 -> 1.3812355 | G7: =Gas!K12+Submetering!AR7 -> 1960.1 | H7: 3.8 | I7: =Water!H12+Submetering!AM7 -> 314.94 | J7: 10 | K7: =Elect!BT11 -> 198
A8: Cairo at The First Residence | B8: =B7+1 -> 7 | C8: 12 | D8: 2022 | E8: =Elect!BS12+Submetering!AH8 -> 28001.118 | F8: =F7 -> 1.3812355 | G8: =Gas!K13+Submetering!AR8 -> 1974.5667 | H8: 3.8 | I8: =Water!H13+Submetering!AM8 -> 258.29333 | J8: 10 | K8: =Elect!BT12 -> 184
A9: Cairo at The First Residence | B9: =B8+1 -> 8 | C9: 12 | D9: 2022 | E9: =Elect!BS13+Submetering!AH9 -> 24074.52 | F9: =F8 -> 1.3812355 | G9: =Gas!K14+Submetering!AR9 -> 1970.95 | H9: 3.8 | I9: =Water!H14+Submetering!AM9 -> 307.4 | J9: 10 | K9: =Elect!BT13 -> 184
A10: Cairo at The First Residence | B10: =B9+1 -> 9 | C10: 12 | D10: 2022 | E10: =Elect!BS14+Submetering!AH10 -> 23862.13 | F10: =F9 -> 1.3812355 | G10: =Gas!K15+Submetering!AR10 -> 1258.6833 | H10: 3.8 | I10: =Water!H15+Submetering!AM10 -> 380.28667 | J10: 10 | K10: =Elect!BT14 -> 183
A11: Cairo at The First Residence | B11: =B10+1 -> 10 | C11: 12 | D11: 2022 | E11: =Elect!BS15+Submetering!AH11 -> 23009.75 | F11: =F10 -> 1.3812355 | G11: =Gas!K16+Submetering!AR11 -> 1777.88 | H11: 3.8 | I11: =Water!H16+Submetering!AM11 -> 290.58 | J11: 10 | K11: =Elect!BT15 -> 207
A12: Cairo at The First Residence | B12: =B11+1 -> 11 | C12: 12 | D12: 2022 | E12: =Elect!BS16+Submetering!AH12 -> 26167.805 | F12: =F11 -> 1.3812355 | G12: =Gas!K17+Submetering!AR12 -> 1747.92 | H12: 3.8 | I12: =Water!H17+Submetering!AM12 -> 309.14 | J12: 10 | K12: =Elect!BT16 -> 236
A13: Cairo at The First Residence | B13: =B12+1 -> 12 | C13: 12 | D13: 2022 | E13: =Elect!BS17+Submetering!AH13 -> 24475.062 | F13: =F12 -> 1.3812355 | G13: =Gas!K18+Submetering!AR13 -> 1865.68 | H13: 3.8 | I13: =Water!H18+Submetering!AM13 -> 311.46 | J13: 10 | K13: =Elect!BT17 -> 236
A14: Cairo at The First Residence | B14: =B13+1 -> 13 | C14: 12 | D14: 2022 | E14: =Elect!BS18+Submetering!AH14 -> 26495.435 | F14: =F13 -> 1.3812355 | G14: =Gas!K19+Submetering!AR14 -> 1566.7613 | H14: 3.8 | I14: =Water!H19+Submetering!AM14 -> 327.85467 | J14: 10 | K14: =Elect!BT18 -> 234
... A32: Cairo at The First Residence | B32: =B31+1 -> 31 | C32: 12 | D32: 2022 | E32: =Elect!BS36+Submetering!AH32 -> 22940.956 | F32: =F31 -> 1.3812355 | G32: =Gas!K37+Submetering!AR32 -> 1818.9267 | H32: 3.8 | I32: =Water!H37+Submetering!AM32 -> 327.555 | J32: 10 | K32: =Elect!BT36 -> 236.33333

Sheet Submetering
A1: Site Name | B1: Day | C1: Month | D1: Year | E1: Electricity | F1: Main Feeder -KWh | G1: T2+T8 -KWh | H1: La Gourmandize -KWh | I1: Casino 3rd floor EM -KWh | J1: Casino 3rd floor Normal -KWh | K1: Chiller 1 -KWh | L1: Chiller 2 -KWh | M1: Chiller 3 -KWh | N1: Chiller 4 -KWh | O1: Chiller 5 -KWh | P1: Chiller 6 -KWh | Q1: Cooling towers -KWh | R1: Chiller Pumps -KWh | S1: Cooling Tower Pumps -KWh | T1: Fiber Chiller -KWh | U1: Mall Ceiling light -KWh | V1: LG Bakery -KWh | W1: LG Bakery light ( Old lockers ) -KWh | X1: MCCR1 -KWh | Y1: Children Swimming Pool -KWh | Z1: DPH1 -KWh | AA1: Guest Rooms Emerg. -KWh | AB1: Hotel Hoods -KWh | AC1: Main G2 -KWh | AD1: Old Casino Emergency -KWh | AE1: L / A -KWh | AF1: L / B -KWh | AG1: L / C -KWh | AH1: Boat -KWh | AI1: Water | AJ1: Main water meter 1 -m3 | AK1: Main water meter 2 -m3 | AL1: Main water meter 3 -m3 | AM1: Boat -m3 | AN1: Gas | AO1: Main Gas Flow Meter -m3 | AP1: Laundry Gas Flow Meter -m3 | AQ1: Gourmandize Gas Flow Meter -m3 | AR1: Boat -m3 | AS1: Room Nights
A2: Cairo at The First Residence | B2: 1 | C2: 12 | D2: 2022 | F2: =Elect!J6 -> 5035.1667 | G2: =Elect!K6 -> 4149.3333 | H2: =Elect!Q6 -> 510 | I2: =Elect!S6 -> 138.33333 | J2: =Elect!U6 -> 224.33333 | K2: =Elect!W6 -> 3837.5533 | L2: =Elect!Y6 -> 0 | M2: =Elect!AA6 -> 2646.82 | N2: =Elect!AC6 -> 0 | O2: =Elect!AE6 -> 12.72 | P2: =Elect!AG6 -> 8.3033333 | Q2: =Elect!AI6 -> 368.085 | R2: =Elect!AK6 -> 2130.9533 | S2: =Elect!AM6 -> 126.67 | T2: =Elect!AP6 -> 173.325 | U2: =Elect!AR6 -> 187 | V2: =Elect!AT6 -> 117.33333 | W2: =Elect!AV6 -> 46.166667 | X2: =Elect!AX6 -> 1079.1667 | Y2: =Elect!AZ6 -> 10.333333 | Z2: =Elect!BB6 -> 4754.6667 | AA2: =Elect!BD6 -> 236 | AB2: =Elect!BF6 -> 0 | AC2: =Elect!BH6 -> 5636.2 | AD2: =Elect!BL6 -> 338 | AE2: =Elect!BN6 -> 967 | AF2: =Elect!BP6 -> 137 | AG2: =Elect!BR6 -> 136.33333 | AH2: =Boat!C4 -> 0 | AJ2: =Water!C7 -> 253.26667 | AK2: =Water!E7 -> 322.86667 | AL2: =Water!G7 -> 243.02 | AM2: =Boat!E4 -> 0 | AO2: =Gas!C7 -> 1396.02 | AP2: =Gas!E7 -> 407.16667 | AQ2: =Gas!G7 -> 65.444444 | AR2: =Boat!G4 -> 0 | AS2: =Elect!BT6 -> 210
A3: Cairo at The First Residence | B3: =B2+1 -> 2 | C3: 12 | D3: 2022 | F3: =Elect!J7 -> 6579 | G3: =Elect!K7 -> 3507 | H3: =Elect!Q7 -> 510 | I3: =Elect!S7 -> 137 | J3: =Elect!U7 -> 251 | K3: =Elect!W7 -> 988.98 | L3: =Elect!Y7 -> 0 | M3: =Elect!AA7 -> 2176.71 | N3: =Elect!AC7 -> 0 | O3: =Elect!AE7 -> 9.54 | P3: =Elect!AG7 -> 11.66 | Q3: =Elect!AI7 -> 328.6 | R3: =Elect!AK7 -> 2198.97 | S3: =Elect!AM7 -> 111.83 | T3: =Elect!AP7 -> 125.325 | U3: =Elect!AR7 -> 211 | V3: =Elect!AT7 -> 155 | W3: =Elect!AV7 -> 30 | X3: =Elect!AX7 -> 922 | Y3: =Elect!AZ7 -> 10 | Z3: =Elect!BB7 -> 4485 | AA3: =Elect!BD7 -> 201 | AB3: =Elect!BF7 -> 10 | AC3: =Elect!BH7 -> 5407.1 | AD3: =Elect!BL7 -> 263 | AE3: =Elect!BN7 -> 875 | AF3: =Elect!BP7 -> 127 | AG3: =Elect!BR7 -> 134 | AH3: =Boat!C5 -> 0 | AJ3: =Water!C8 -> 22.555556 | AK3: =Water!E8 -> 35.766667 | AL3: =Water!G8 -> 121.22 | AM3: =Boat!E5 -> 0 | AO3: =Gas!C8 -> 1643 | AP3: =Gas!E8 -> 345.8 | AQ3: =Gas!G8 -> 90.888889 | AR3: =Boat!G5 -> 0 | AS3: =Elect!BT7 -> 242
A4: Cairo at The First Residence | B4: =B3+1 -> 3 | C4: 12 | D4: 2022 | F4: =Elect!J8 -> 5998 | G4: =Elect!K8 -> 3618 | H4: =Elect!Q8 -> 480 | I4: =Elect!S8 -> 139 | J4: =Elect!U8 -> 257 | K4: =Elect!W8 -> 3490.05 | L4: =Elect!Y8 -> 0 | M4: =Elect!AA8 -> 0 | N4: =Elect!AC8 -> 0 | O4: =Elect!AE8 -> 13.25 | P4: =Elect!AG8 -> 12.19 | Q4: =Elect!AI8 -> 393.79 | R4: =Elect!AK8 -> 2473.51 | S4: =Elect!AM8 -> 115.54 | T4: =Elect!AP8 -> 147.375 | U4: =Elect!AR8 -> 183 | V4: =Elect!AT8 -> 144 | W4: =Elect!AV8 -> 32 | X4: =Elect!AX8 -> 976 | Y4: =Elect!AZ8 -> 11 | Z4: =Elect!BB8 -> 4908 | AA4: =Elect!BD8 -> 216 | AB4: =Elect!BF8 -> 100 | AC4: =Elect!BH8 -> 5646.85 | AD4: =Elect!BL8 -> 270 | AE4: =Elect!BN8 -> 1040 | AF4: =Elect!BP8 -> 107 | AG4: =Elect!BR8 -> 149 | AH4: =Boat!C6 -> 0 | AJ4: =Water!C9 -> 85.711111 | AK4: =Water!E9 -> 107.3 | AL4: =Water!G9 -> 46.4 | AM4: =Boat!E6 -> 0 | AO4: =Gas!C9 -> 1643 | AP4: =Gas!E9 -> 345.8 | AQ4: =Gas!G9 -> 81.333333 | AR4: =Boat!G6 -> 0 | AS4: =Elect!BT8 -> 225
A5: Cairo at The First Residence | B5: =B4+1 -> 4 | C5: 12 | D5: 2022 | F5: =Elect!J9 -> 6469 | G5: =Elect!K9 -> 3537 | H5: =Elect!Q9 -> 510 | I5: =Elect!S9 -> 143 | J5: =Elect!U9 -> 263 | K5: =Elect!W9 -> 448.38 | L5: =Elect!Y9 -> 0 | M5: =Elect!AA9 -> 2972.24 | N5: =Elect!AC9 -> 0 | O5: =Elect!AE9 -> 13.78 | P5: =Elect!AG9 -> 12.19 | Q5: =Elect!AI9 -> 204.05 | R5: =Elect!AK9 -> 2271.05 | S5: =Elect!AM9 -> 111.3 | T5: =Elect!AP9 -> 151.5375 | U5: =Elect!AR9 -> 191 | V5: =Elect!AT9 -> 160 | W5: =Elect!AV9 -> 32 | X5: =Elect!AX9 -> 924 | Y5: =Elect!AZ9 -> 10 | Z5: =Elect!BB9 -> 5200 | AA5: =Elect!BD9 -> 227 | AB5: =Elect!BF9 -> 0 | AC5: =Elect!BH9 -> 5689.1 | AD5: =Elect!BL9 -> 278 | AE5: =Elect!BN9 -> 1025 | AF5: =Elect!BP9 -> 137 | AG5: =Elect!BR9 -> 153 | AH5: =Boat!C7 -> 0 | AJ5: =Water!C10 -> 83.133333 | AK5: =Water!E10 -> 106.33333 | AL5: =Water!G10 -> 83.52 | AM5: =Boat!E7 -> 0 | AO5: =Gas!C10 -> 1643 | AP5: =Gas!E10 -> 338.8 | AQ5: =Gas!G10 -> 95.666667 | AR5: =Boat!G7 -> 0 | AS5: =Elect!BT9 -> 236
A6: Cairo at The First Residence | B6: =B5+1 -> 5 | C6: 12 | D6: 2022 | F6: =Elect!J10 -> 6327 | G6: =Elect!K10 -> 4093 | H6: =Elect!Q10 -> 450 | I6: =Elect!S10 -> 144 | J6: =Elect!U10 -> 257 | K6: =Elect!W10 -> 2495.24 | L6: =Elect!Y10 -> 0 | M6: =Elect!AA10 -> 958.24 | N6: =Elect!AC10 -> 0 | O6: =Elect!AE10 -> 13.25 | P6: =Elect!AG10 -> 12.19 | Q6: =Elect!AI10 -> 191.86 | R6: =Elect!AK10 -> 2385 | S6: =Elect!AM10 -> 118.72 | T6: =Elect!AP10 -> 131.625 | U6: =Elect!AR10 -> 203 | V6: =Elect!AT10 -> 150 | W6: =Elect!AV10 -> 34 | X6: =Elect!AX10 -> 951 | Y6: =Elect!AZ10 -> 11 | Z6: =Elect!BB10 -> 4895 | AA6: =Elect!BD10 -> 242 | AB6: =Elect!BF10 -> 5 | AC6: =Elect!BH10 -> 5631.6 | AD6: =Elect!BL10 -> 281 | AE6: =Elect!BN10 -> 986 | AF6: =Elect!BP10 -> 146 | AG6: =Elect!BR10 -> 157 | AH6: =Boat!C8 -> 0 | AJ6: =Water!C11 -> 87 | AK6: =Water!E11 -> 110.2 | AL6: =Water!G11 -> 128.18 | AM6: =Boat!E8 -> 0 | AO6: =Gas!C11 -> 1643 | AP6: =Gas!E11 -> 338.8 | AQ6: =Gas!G11 -> 97 | AR6: =Boat!G8 -> 0 | AS6: =Elect!BT10 -> 216
A7: Cairo at The First Residence | B7: =B6+1 -> 6 | C7: 12 | D7: 2022 | F7: =Elect!J11 -> 6729 | G7: =Elect!K11 -> 3438 | H7: =Elect!Q11 -> 450 | I7: =Elect!S11 -> 148 | J7: =Elect!U11 -> 268 | K7: =Elect!W11 -> 620.63 | L7: =Elect!Y11 -> 0 | M7: =Elect!AA11 -> 169.6 | N7: =Elect!AC11 -> 0 | O7: =Elect!AE11 -> 13.78 | P7: =Elect!AG11 -> 11.66 | Q7: =Elect!AI11 -> 160.59 | R7: =Elect!AK11 -> 2593.82 | S7: =Elect!AM11 -> 116.07 | T7: =Elect!AP11 -> 125.2125 | U7: =Elect!AR11 -> 200 | V7: =Elect!AT11 -> 131 | W7: =Elect!AV11 -> 33 | X7: =Elect!AX11 -> 1073 | Y7: =Elect!AZ11 -> 11 | Z7: =Elect!BB11 -> 4663 | AA7: =Elect!BD11 -> 233 | AB7: =Elect!BF11 -> 108 | AC7: =Elect!BH11 -> 5838.85 | AD7: =Elect!BL11 -> 286 | AE7: =Elect!BN11 -> 1042 | AF7: =Elect!BP11 -> 145 | AG7: =Elect!BR11 -> 158 | AH7: =Boat!C9 -> 0 | AJ7: =Water!C12 -> 81.2 | AK7: =Water!E12 -> 104.4 | AL7: =Water!G12 -> 129.34 | AM7: =Boat!E9 -> 0 | AO7: =Gas!C12 -> 1643 | AP7: =Gas!E12 -> 317.1 | AQ7: =Gas!G12 -> 95 | AR7: =Boat!G9 -> 0 | AS7: =Elect!BT11 -> 198
A8: Cairo at The First Residence | B8: =B7+1 -> 7 | C8: 12 | D8: 2022 | F8: =Elect!J12 -> 6469 | G8: =Elect!K12 -> 4925 | H8: =Elect!Q12 -> 480 | I8: =Elect!S12 -> 139 | J8: =Elect!U12 -> 254 | K8: =Elect!W12 -> 5764.81 | L8: =Elect!Y12 -> 0 | M8: =Elect!AA12 -> 43.46 | N8: =Elect!AC12 -> 0 | O8: =Elect!AE12 -> 13.25 | P8: =Elect!AG12 -> 12.19 | Q8: =Elect!AI12 -> 216.77 | R8: =Elect!AK12 -> 2291.19 | S8: =Elect!AM12 -> 117.66 | T8: =Elect!AP12 -> 157.3875 | U8: =Elect!AR12 -> 195 | V8: =Elect!AT12 -> 162 | W8: =Elect!AV12 -> 46 | X8: =Elect!AX12 -> 827 | Y8: =Elect!AZ12 -> 11 | Z8: =Elect!BB12 -> 5060 | AA8: =Elect!BD12 -> 246 | AB8: =Elect!BF12 -> 72 | AC8: =Elect!BH12 -> 5816.4 | AD8: =Elect!BL12 -> 275 | AE8: =Elect!BN12 -> 1145 | AF8: =Elect!BP12 -> 143 | AG8: =Elect!BR12 -> 153 | AH8: =Boat!C10 -> 0 | AJ8: =Water!C13 -> 85.066667 | AK8: =Water!E13 -> 108.26667 | AL8: =Water!G13 -> 64.96 | AM8: =Boat!E10 -> 0 | AO8: =Gas!C13 -> 1643 | AP8: =Gas!E13 -> 331.56667 | AQ8: =Gas!G13 -> 96.333333 | AR8: =Boat!G10 -> 0 | AS8: =Elect!BT12 -> 184
A9: Cairo at The First Residence | B9: =B8+1 -> 8 | C9: 12 | D9: 2022 | F9: =Elect!J13 -> 6399 | G9: =Elect!K13 -> 4015 | H9: =Elect!Q13 -> 510 | I9: =Elect!S13 -> 142 | J9: =Elect!U13 -> 256 | K9: =Elect!W13 -> 2300.73 | L9: =Elect!Y13 -> 0 | M9: =Elect!AA13 -> 37.1 | N9: =Elect!AC13 -> 1.59 | O9: =Elect!AE13 -> 13.25 | P9: =Elect!AG13 -> 12.19 | Q9: =Elect!AI13 -> 286.73 | R9: =Elect!AK13 -> 2312.39 | S9: =Elect!AM13 -> 112.89 | T9: =Elect!AP13 -> 70.65 | U9: =Elect!AR13 -> 197 | V9: =Elect!AT13 -> 201 | W9: =Elect!AV13 -> 41 | X9: =Elect!AX13 -> 923 | Y9: =Elect!AZ13 -> 124 | Z9: =Elect!BB13 -> 4707 | AA9: =Elect!BD13 -> 241 | AB9: =Elect!BF13 -> 70 | AC9: =Elect!BH13 -> 5514 | AD9: =Elect!BL13 -> 167 | AE9: =Elect!BN13 -> 1204 | AF9: =Elect!BP13 -> 136 | AG9: =Elect!BR13 -> 151 | AH9: =Boat!C11 -> 0 | AJ9: =Water!C14 -> 84.1 | AK9: =Water!E14 -> 107.3 | AL9: =Water!G14 -> 116 | AM9: =Boat!E11 -> 0 | AO9: =Gas!C14 -> 1643 | AP9: =Gas!E14 -> 327.95 | AQ9: =Gas!G14 -> 96 | AR9: =Boat!G11 -> 0 | AS9: =Elect!BT13 -> 184
A10: Cairo at The First Residence | B10: =B9+1 -> 9 | C10: 12 | D10: 2022 | F10: =Elect!J14 -> 6217 | G10: =Elect!K14 -> 4022 | H10: =Elect!Q14 -> 450 | I10: =Elect!S14 -> 141 | J10: =Elect!U14 -> 257 | K10: =Elect!W14 -> 2243.49 | L10: =Elect!Y14 -> 0 | M10: =Elect!AA14 -> 251.22 | N10: =Elect!AC14 -> 0 | O10: =Elect!AE14 -> 12.19 | P10: =Elect!AG14 -> 11.13 | Q10: =Elect!AI14 -> 311.11 | R10: =Elect!AK14 -> 2160.28 | S10: =Elect!AM14 -> 115.01 | T10: =Elect!AP14 -> 84.15 | U10: =Elect!AR14 -> 217 | V10: =Elect!AT14 -> 171 | W10: =Elect!AV14 -> 41 | X10: =Elect!AX14 -> 917 | Y10: =Elect!AZ14 -> 493 | Z10: =Elect!BB14 -> 4453 | AA10: =Elect!BD14 -> 228 | AB10: =Elect!BF14 -> 89 | AC10: =Elect!BH14 -> 5397.55 | AD10: =Elect!BL14 -> 75 | AE10: =Elect!BN14 -> 1147 | AF10: =Elect!BP14 -> 134 | AG10: =Elect!BR14 -> 152 | AH10: =Boat!C12 -> 0 | AJ10: =Water!C15 -> 80.233333 | AK10: =Water!E15 -> 103.43333 | AL10: =Water!G15 -> 196.62 | AM10: =Boat!E12 -> 0 | AO10: =Gas!C15 -> 874.5 | AP10: =Gas!E15 -> 384.18333 | AQ10: =Gas!G15 -> 90.666667 | AR10: =Boat!G12 -> 0 | AS10: =Elect!BT14 -> 183
A11: Cairo at The First Residence | B11: =B10+1 -> 10 | C11: 12 | D11: 2022 | F11: =Elect!J15 -> 6463 | G11: =Elect!K15 -> 4149 | H11: =Elect!Q15 -> 510 | I11: =Elect!S15 -> 142 | J11: =Elect!U15 -> 265 | K11: =Elect!W15 -> 2414.68 | L11: =Elect!Y15 -> 0 | M11: =Elect!AA15 -> 0 | N11: =Elect!AC15 -> 0 | O11: =Elect!AE15 -> 12.19 | P11: =Elect!AG15 -> 11.66 | Q11: =Elect!AI15 -> 236.91 | R11: =Elect!AK15 -> 1837.51 | S11: =Elect!AM15 -> 116.6 | T11: =Elect!AP15 -> 93.15 | U11: =Elect!AR15 -> 197 | V11: =Elect!AT15 -> 176 | W11: =Elect!AV15 -> 40 | X11: =Elect!AX15 -> 900 | Y11: =Elect!AZ15 -> 10 | Z11: =Elect!BB15 -> 4001 | AA11: =Elect!BD15 -> 213 | AB11: =Elect!BF15 -> 70 | AC11: =Elect!BH15 -> 5707.05 | AD11: =Elect!BL15 -> 189 | AE11: =Elect!BN15 -> 1182 | AF11: =Elect!BP15 -> 129 | AG11: =Elect!BR15 -> 135 | AH11: =Boat!C13 -> 0 | AJ11: =Water!C16 -> 75.4 | AK11: =Water!E16 -> 92.8 | AL11: =Water!G16 -> 122.38 | AM11: =Boat!E13 -> 0 | AO11: =Gas!C16 -> 1471.28 | AP11: =Gas!E16 -> 306.6 | AQ11: =Gas!G16 -> 90 | AR11: =Boat!G13 -> 0 | AS11: =Elect!BT15 -> 207
A12: Cairo at The First Residence | B12: =B11+1 -> 11 | C12: 12 | D12: 2022 | F12: =Elect!J16 -> 6856 | G12: =Elect!K16 -> 4055 | H12: =Elect!Q16 -> 450 | I12: =Elect!S16 -> 143 | J12: =Elect!U16 -> 267 | K12: =Elect!W16 -> 2371.22 | L12: =Elect!Y16 -> 0 | M12: =Elect!AA16 -> 132.5 | N12: =Elect!AC16 -> 0 | O12: =Elect!AE16 -> 12.72 | P12: =Elect!AG16 -> 11.66 | Q12: =Elect!AI16 -> 248.04 | R12: =Elect!AK16 -> 2050.04 | S12: =Elect!AM16 -> 116.6 | T12: =Elect!AP16 -> 76.725 | U12: =Elect!AR16 -> 198 | V12: =Elect!AT16 -> 184 | W12: =Elect!AV16 -> 42 | X12: =Elect!AX16 -> 933 | Y12: =Elect!AZ16 -> 477 | Z12: =Elect!BB16 -> 5759 | AA12: =Elect!BD16 -> 248 | AB12: =Elect!BF16 -> 50 | AC12: =Elect!BH16 -> 5951.3 | AD12: =Elect!BL16 -> 231 | AE12: =Elect!BN16 -> 1198 | AF12: =Elect!BP16 -> 148 | AG12: =Elect!BR16 -> 129 | AH12: =Boat!C14 -> 0 | AJ12: =Water!C17 -> 81.2 | AK12: =Water!E17 -> 104.4 | AL12: =Water!G17 -> 123.54 | AM12: =Boat!E14 -> 0 | AO12: =Gas!C17 -> 1411.92 | AP12: =Gas!E17 -> 336 | AQ12: =Gas!G17 -> 88 | AR12: =Boat!G14 -> 0 | AS12: =Elect!BT16 -> 236
A13: Cairo at The First Residence | B13: =B12+1 -> 12 | C13: 12 | D13: 2022 | F13: =Elect!J17 -> 6916 | G13: =Elect!K17 -> 3705 | H13: =Elect!Q17 -> 420 | I13: =Elect!S17 -> 142 | J13: =Elect!U17 -> 264 | K13: =Elect!W17 -> 2666.43 | L13: =Elect!Y17 -> 0 | M13: =Elect!AA17 -> 0 | N13: =Elect!AC17 -> 0 | O13: =Elect!AE17 -> 13.25 | P13: =Elect!AG17 -> 11.66 | Q13: =Elect!AI17 -> 278.25 | R13: =Elect!AK17 -> 2156.04 | S13: =Elect!AM17 -> 116.07 | T13: =Elect!AP17 -> 96.4125 | U13: =Elect!AR17 -> 208 | V13: =Elect!AT17 -> 194 | W13: =Elect!AV17 -> 43 | X13: =Elect!AX17 -> 899 | Y13: =Elect!AZ17 -> 10 | Z13: =Elect!BB17 -> 4536 | AA13: =Elect!BD17 -> 249 | AB13: =Elect!BF17 -> 15 | AC13: =Elect!BH17 -> 5646.95 | AD13: =Elect!BL17 -> 240 | AE13: =Elect!BN17 -> 1167 | AF13: =Elect!BP17 -> 162 | AG13: =Elect!BR17 -> 136 | AH13: =Boat!C15 -> 0 | AJ13: =Water!C18 -> 87 | AK13: =Water!E18 -> 104.4 | AL13: =Water!G18 -> 120.06 | AM13: =Boat!E15 -> 0 | AO13: =Gas!C18 -> 1503.08 | AP13: =Gas!E18 -> 362.6 | AQ13: =Gas!G18 -> 91 | AR13: =Boat!G15 -> 0 | AS13: =Elect!BT17 -> 236
A14: Cairo at The First Residence | B14: =B13+1 -> 13 | C14: 12 | D14: 2022 | F14: =Elect!J18 -> 8015 | G14: =Elect!K18 -> 3681 | H14: =Elect!Q18 -> 450 | I14: =Elect!S18 -> 144 | J14: =Elect!U18 -> 264 | K14: =Elect!W18 -> 3150.85 | L14: =Elect!Y18 -> 0 | M14: =Elect!AA18 -> 0 | N14: =Elect!AC18 -> 0 | O14: =Elect!AE18 -> 12.72 | P14: =Elect!AG18 -> 12.19 | Q14: =Elect!AI18 -> 307.4 | R14: =Elect!AK18 -> 2283.24 | S14: =Elect!AM18 -> 117.66 | T14: =Elect!AP18 -> 86.625 | U14: =Elect!AR18 -> 195 | V14: =Elect!AT18 -> 200 | W14: =Elect!AV18 -> 44 | X14: =Elect!AX18 -> 921 | Y14: =Elect!AZ18 -> 11 | Z14: =Elect!BB18 -> 4783 | AA14: =Elect!BD18 -> 253 | AB14: =Elect!BF18 -> 59 | AC14: =Elect!BH18 -> 5593.75 | AD14: =Elect!BL18 -> 245 | AE14: =Elect!BN18 -> 1176 | AF14: =Elect!BP18 -> 149 | AG14: =Elect!BR18 -> 146 | AH14: =Boat!C16 -> 0 | AJ14: =Water!C19 -> 76.753333 | AK14: =Water!E19 -> 98.213333 | AL14: =Water!G19 -> 152.888 | AM14: =Boat!E16 -> 0 | AO14: =Gas!C19 -> 1231.508 | AP14: =Gas!E19 -> 335.25333 | AQ14: =Gas!G19 -> 91.711111 | AR14: =Boat!G16 -> 0 | AS14: =Elect!BT18 -> 234
... A32: Cairo at The First Residence | B32: =B31+1 -> 31 | C32: 12 | D32: 2022 | F32: =Elect!J36 -> 5918.5 | G32: =Elect!K36 -> 4221 | H32: =Elect!Q36 -> 525 | I32: =Elect!S36 -> 146 | J32: =Elect!U36 -> 238.5 | K32: =Elect!W36 -> 2183.865 | L32: =Elect!Y36 -> 0 | M32: =Elect!AA36 -> 0 | N32: =Elect!AC36 -> 0 | O32: =Elect!AE36 -> 12.985 | P32: =Elect!AG36 -> 12.19 | Q32: =Elect!AI36 -> 272.685 | R32: =Elect!AK36 -> 1550.78 | S32: =Elect!AM36 -> 114.745 | T32: =Elect!AP36 -> 139.33125 | U32: =Elect!AR36 -> 216 | V32: =Elect!AT36 -> 107.5 | W32: =Elect!AV36 -> 43.5 | X32: =Elect!AX36 -> 927.5 | Y32: =Elect!AZ36 -> 11 | Z32: =Elect!BB36 -> 5346.5 | AA32: =Elect!BD36 -> 203.5 | AB32: =Elect!BF36 -> 40 | AC32: =Elect!BH36 -> 5315.375 | AD32: =Elect!BL36 -> 238.5 | AE32: =Elect!BN36 -> 1103.5 | AF32: =Elect!BP36 -> 129 | AG32: =Elect!BR36 -> 153 | AH32: =Boat!C34 -> 0 | AJ32: =Water!C37 -> 88.45 | AK32: =Water!E37 -> 124.12 | AL32: =Water!G37 -> 114.985 | AM32: =Boat!E34 -> 0 | AO32: =Gas!C37 -> 1422.785 | AP32: =Gas!E37 -> 396.14167 | AQ32: =Gas!G37 -> 84.361111 | AR32: =Boat!G34 -> 0 | AS32: =Elect!BT36 -> 236.33333

Sheet Boat
B1: Electricity | D1: Water | F1: Gas
B2: Read | C2: Cons | D2: Read | E2: Cons | F2: Read | G2: Cons
B3: 0 | D3: 0 | F3: 0
A4: 1 | B4: 0 | C4: =B4-B3 -> 0 | D4: 0 | E4: =D4-D3 -> 0 | F4: 0 | G4: =F4-F3 -> 0
A5: 2 | B5: 0 | C5: =B5-B4 -> 0 | D5: 0 | E5: =D5-D4 -> 0 | F5: 0 | G5: =F5-F4 -> 0
A6: 3 | B6: 0 | C6: =B6-B5 -> 0 | D6: 0 | E6: =D6-D5 -> 0 | F6: 0 | G6: =F6-F5 -> 0
A7: 4 | B7: 0 | C7: =B7-B6 -> 0 | D7: 0 | E7: =D7-D6 -> 0 | F7: 0 | G7: =F7-F6 -> 0
A8: 5 | B8: 0 | C8: =B8-B7 -> 0 | D8: 0 | E8: =D8-D7 -> 0 | F8: 0 | G8: =F8-F7 -> 0
A9: 6 | B9: 0 | C9: =B9-B8 -> 0 | D9: 0 | E9: =D9-D8 -> 0 | F9: 0 | G9: =F9-F8 -> 0
A10: 7 | B10: 0 | C10: =B10-B9 -> 0 | D10: 0 | E10: =D10-D9 -> 0 | F10: 0 | G10: =F10-F9 -> 0
A11: 8 | B11: 0 | C11: =B11-B10 -> 0 | D11: 0 | E11: =D11-D10 -> 0 | F11: 0 | G11: =F11-F10 -> 0
A12: 9 | B12: 0 | C12: =B12-B11 -> 0 | D12: 0 | E12: =D12-D11 -> 0 | F12: 0 | G12: =F12-F11 -> 0
A13: 10 | B13: 0 | C13: =B13-B12 -> 0 | D13: 0 | E13: =D13-D12 -> 0 | F13: 0 | G13: =F13-F12 -> 0
A14: 11 | B14: 0 | C14: =B14-B13 -> 0 | D14: 0 | E14: =D14-D13 -> 0 | F14: 0 | G14: =F14-F13 -> 0
A15: 12 | B15: 0 | C15: =B15-B14 -> 0 | D15: 0 | E15: =D15-D14 -> 0 | F15: 0 | G15: =F15-F14 -> 0
... A34: 31 | B34: 0 | C34: =B34-B33 -> 0 | D34: 0 | E34: =D34-D33 -> 0 | F34: 0 | G34: =F34-F33 -> 0
A35: Sum | C35: =SUM(C4:C34) -> 0 | E35: =SUM(E4:E34) -> 0 | G35: =SUM(G4:G34) -> 0

Sheet Water
A1: =Elect!A1 -> 44896 | T1: Main Water UP | V1: 4 | W1: Water Truck UP
A3: Day | E3: Water Incoming | I3: New casino | N3: Rooms Consumption | P3: Public Areas consumption | R3: Swimming pool | T3: No. of rooms | U3: Cons. Per occ. room | V3: No. of guest | W3: Cons. Per guest | X3: Total cost | Y3: L.E\ | Z3: L.E\
B4: Main water meter 1 | D4: Main water meter 2 | F4: Main water meter 3 | H4: Total Inc. | I4: Hot water | K4: Cold water | N4: Express Riser | O4: Consp. | P4: Read. | Q4: Cons. | R4: Read. | S4: Cons. | Y4: Room | Z4: Guest
B5: Counter | C5: Produc 58% | D5: Counter | E5: Produc 58% | F5: Counter | G5: Produc 58% | I5: Counter | K5: Counter
B6: 90135.333 | C6: =IF(B6>=B5,B6-B5,0)*10*0.58 -> 0 | D6: 13386.333 | E6: =IF(D6>=D5,D6-D5,0)*10*0.58 -> 0 | F6: 61792 | G6: =IF(F6>=F5,F6-F5,0)*0.58 -> 0 | I6: 310 | K6: 5476
A7: 1 | B7: 90179 | C7: =IF(B7>=B6,B7-B6,0)*10*0.58 -> 253.26667 | D7: 13442 | E7: =IF(D7>=D6,D7-D6,0)*10*0.58 -> 322.86667 | F7: 62211 | G7: =IF(F7>=F6,F7-F6,0)*0.58 -> 243.02 | H7: =C7+E7+G7 -> 819.15333 | O7: =IF(N7>=N6,N7-N6,0) -> 0 | Q7: =(H7-O7)*0.58 -> 475.10893 | S7: =IF(R7-R6>0,R7-R6,0) -> 0 | T7: =Elect!BT6 -> 210 | U7: =H7/T7 -> 3.9007302 | V7: =Elect!BV6 -> 0 | W7: =H7/V7 -> #DIV/0! | X7: =H7*V1 -> 3276.6133 | Y7: =IF(X7>0,X7/T7,0) -> 15.602921 | Z7: 0
A8: 2 | B8: 90182.889 | C8: =IF(B8>=B7,B8-B7,0)*10*0.58 -> 22.555556 | D8: 13448.167 | E8: =IF(D8>=D7,D8-D7,0)*10*0.58 -> 35.766667 | F8: 62420 | G8: =IF(F8>=F7,F8-F7,0)*0.58 -> 121.22 | H8: =C8+E8+G8 -> 179.54222 | O8: =IF(N8>=N7,N8-N7,0) -> 0 | Q8: =(H8-O8)*0.58 -> 104.13449 | S8: =IF(R8-R7>0,R8-R7,0) -> 0 | T8: =Elect!BT7 -> 242 | U8: =H8/T8 -> 0.74191001 | V8: =Elect!BV7 -> 0 | W8: =H8/V8 -> #DIV/0! | X8: =H8*V1 -> 718.16889 | Y8: =IF(X8>0,X8/T8,0) -> 2.96764 | Z8: =IF(X8>0,X8/V8,0) -> #DIV/0!
A9: 3 | B9: 90197.667 | C9: =IF(B9>=B8,B9-B8,0)*10*0.58 -> 85.711111 | D9: 13466.667 | E9: =IF(D9>=D8,D9-D8,0)*10*0.58 -> 107.3 | F9: 62500 | G9: =IF(F9>=F8,F9-F8,0)*0.58 -> 46.4 | H9: =C9+E9+G9 -> 239.41111 | O9: =IF(N9>=N8,N9-N8,0) -> 0 | Q9: =(H9-O9)*0.58 -> 138.85844 | S9: =IF(R9-R8>0,R9-R8,0) -> 0 | T9: =Elect!BT8 -> 225 | U9: =H9/T9 -> 1.0640494 | V9: =Elect!BV8 -> 0 | W9: =H9/V9 -> #DIV/0! | X9: =H9*V1 -> 957.64444 | Y9: =IF(X9>0,X9/T9,0) -> 4.2561975 | Z9: =IF(X9>0,X9/V9,0) -> #DIV/0!
A10: 4 | B10: 90212 | C10: =IF(B10>=B9,B10-B9,0)*10*0.58 -> 83.133333 | D10: 13485 | E10: =IF(D10>=D9,D10-D9,0)*10*0.58 -> 106.33333 | F10: 62644 | G10: =IF(F10>=F9,F10-F9,0)*0.58 -> 83.52 | H10: =C10+E10+G10 -> 272.98667 | O10: =IF(N10>=N9,N10-N9,0) -> 0 | Q10: =(H10-O10)*0.58 -> 158.33227 | S10: =IF(R10-R9>0,R10-R9,0) -> 0 | T10: =Elect!BT9 -> 236 | U10: =H10/T10 -> 1.1567232 | V10: =Elect!BV9 -> 0 | W10: =H10/V10 -> #DIV/0! | X10: =H10*V1 -> 1091.9467 | Y10: =IF(X10>0,X10/T10,0) -> 4.6268927 | Z10: =IF(X10>0,X10/V10,0) -> #DIV/0!
A11: 5 | B11: 90227 | C11: =IF(B11>=B10,B11-B10,0)*10*0.58 -> 87 | D11: 13504 | E11: =IF(D11>=D10,D11-D10,0)*10*0.58 -> 110.2 | F11: 62865 | G11: =IF(F11>=F10,F11-F10,0)*0.58 -> 128.18 | H11: =C11+E11+G11 -> 325.38 | O11: =IF(N11>=N10,N11-N10,0) -> 0 | Q11: =(H11-O11)*0.58 -> 188.7204 | S11: =IF(R11-R10>0,R11-R10,0) -> 0 | T11: =Elect!BT10 -> 216 | U11: =H11/T11 -> 1.5063889 | V11: =Elect!BV10 -> 0 | W11: =H11/V11 -> #DIV/0! | X11: =H11*V1 -> 1301.52 | Y11: =IF(X11>0,X11/T11,0) -> 6.0255556 | Z11: =IF(X11>0,X11/V11,0) -> #DIV/0!
A12: 6 | B12: 90241 | C12: =IF(B12>=B11,B12-B11,0)*10*0.58 -> 81.2 | D12: 13522 | E12: =IF(D12>=D11,D12-D11,0)*10*0.58 -> 104.4 | F12: 63088 | G12: =IF(F12>=F11,F12-F11,0)*0.58 -> 129.34 | H12: =C12+E12+G12 -> 314.94 | O12: =IF(N12>=N11,N12-N11,0) -> 0 | Q12: =(H12-O12)*0.58 -> 182.6652 | S12: =IF(R12-R11>0,R12-R11,0) -> 0 | T12: =Elect!BT11 -> 198 | U12: =H12/T12 -> 1.5906061 | V12: =Elect!BV11 -> 0 | W12: =H12/V12 -> #DIV/0! | X12: =H12*V1 -> 1259.76 | Y12: =IF(X12>0,X12/T12,0) -> 6.3624242 | Z12: =IF(X12>0,X12/V12,0) -> #DIV/0!
A13: 7 | B13: 90255.667 | C13: =IF(B13>=B12,B13-B12,0)*10*0.58 -> 85.066667 | D13: 13540.667 | E13: =IF(D13>=D12,D13-D12,0)*10*0.58 -> 108.26667 | F13: 63200 | G13: =IF(F13>=F12,F13-F12,0)*0.58 -> 64.96 | H13: =C13+E13+G13 -> 258.29333 | O13: =IF(N13>=N12,N13-N12,0) -> 0 | Q13: =(H13-O13)*0.58 -> 149.81013 | S13: =IF(R13-R12>0,R13-R12,0) -> 0 | T13: =Elect!BT12 -> 184 | U13: =H13/T13 -> 1.4037681 | V13: =Elect!BV12 -> 0 | W13: =H13/V13 -> #DIV/0! | X13: =H13*V1 -> 1033.1733 | Y13: =IF(X13>0,X13/T13,0) -> 5.6150725 | Z13: =IF(X13>0,X13/V13,0) -> #DIV/0!
A14: 8 | B14: 90270.167 | C14: =IF(B14>=B13,B14-B13,0)*10*0.58 -> 84.1 | D14: 13559.167 | E14: =IF(D14>=D13,D14-D13,0)*10*0.58 -> 107.3 | F14: 63400 | G14: =IF(F14>=F13,F14-F13,0)*0.58 -> 116 | H14: =C14+E14+G14 -> 307.4 | O14: =IF(N14>=N13,N14-N13,0) -> 0 | Q14: =(H14-O14)*0.58 -> 178.292 | S14: =IF(R14-R13>0,R14-R13,0) -> 0 | T14: =Elect!BT13 -> 184 | U14: =H14/T14 -> 1.6706522 | V14: =Elect!BV13 -> 0 | W14: =H14/V14 -> #DIV/0! | X14: =H14*V1 -> 1229.6 | Y14: =IF(X14>0,X14/T14,0) -> 6.6826087 | Z14: =IF(X14>0,X14/V14,0) -> #DIV/0!
A15: 9 | B15: 90284 | C15: =IF(B15>=B14,B15-B14,0)*10*0.58 -> 80.233333 | D15: 13577 | E15: =IF(D15>=D14,D15-D14,0)*10*0.58 -> 103.43333 | F15: 63739 | G15: =IF(F15>=F14,F15-F14,0)*0.58 -> 196.62 | H15: =C15+E15+G15 -> 380.28667 | O15: =IF(N15>=N14,N15-N14,0) -> 0 | Q15: =(H15-O15)*0.58 -> 220.56627 | S15: =IF(R15-R14>0,R15-R14,0) -> 0 | T15: =Elect!BT14 -> 183 | U15: =H15/T15 -> 2.0780692 | V15: =Elect!BV14 -> 0 | W15: =H15/V15 -> #DIV/0! | X15: =H15*V1 -> 1521.1467 | Y15: =IF(X15>0,X15/T15,0) -> 8.3122769 | Z15: =IF(X15>0,X15/V15,0) -> #DIV/0!
A16: 10 | B16: 90297 | C16: =IF(B16>=B15,B16-B15,0)*10*0.58 -> 75.4 | D16: 13593 | E16: =IF(D16>=D15,D16-D15,0)*10*0.58 -> 92.8 | F16: 63950 | G16: =IF(F16>=F15,F16-F15,0)*0.58 -> 122.38 | H16: =C16+E16+G16 -> 290.58 | O16: =IF(N16>=N15,N16-N15,0) -> 0 | Q16: =(H16-O16)*0.58 -> 168.5364 | S16: =IF(R16-R15>0,R16-R15,0) -> 0 | T16: =Elect!BT15 -> 207 | U16: =H16/T16 -> 1.4037681 | V16: =Elect!BV15 -> 0 | W16: =H16/V16 -> #DIV/0! | X16: =H16*V1 -> 1162.32 | Y16: =IF(X16>0,X16/T16,0) -> 5.6150725 | Z16: =IF(X16>0,X16/V16,0) -> #DIV/0!
A17: 11 | B17: 90311 | C17: =IF(B17>=B16,B17-B16,0)*10*0.58 -> 81.2 | D17: 13611 | E17: =IF(D17>=D16,D17-D16,0)*10*0.58 -> 104.4 | F17: 64163 | G17: =IF(F17>=F16,F17-F16,0)*0.58 -> 123.54 | H17: =C17+E17+G17 -> 309.14 | O17: =IF(N17>=N16,N17-N16,0) -> 0 | Q17: =(H17-O17)*0.58 -> 179.3012 | S17: =IF(R17-R16>0,R17-R16,0) -> 0 | T17: =Elect!BT16 -> 236 | U17: =H17/T17 -> 1.3099153 | V17: =Elect!BV16 -> 0 | W17: =H17/V17 -> #DIV/0! | X17: =H17*V1 -> 1236.56 | Y17: =IF(X17>0,X17/T17,0) -> 5.239661 | Z17: =IF(X17>0,X17/V17,0) -> #DIV/0!
A18: 12 | B18: 90326 | C18: =IF(B18>=B17,B18-B17,0)*10*0.58 -> 87 | D18: 13629 | E18: =IF(D18>=D17,D18-D17,0)*10*0.58 -> 104.4 | F18: 64370 | G18: =IF(F18>=F17,F18-F17,0)*0.58 -> 120.06 | H18: =C18+E18+G18 -> 311.46 | O18: =IF(N18>=N17,N18-N17,0) -> 0 | Q18: =(H18-O18)*0.58 -> 180.6468 | S18: =IF(R18-R17>0,R18-R17,0) -> 0 | T18: =Elect!BT17 -> 236 | U18: =H18/T18 -> 1.3197458 | V18: =Elect!BV17 -> 0 | W18: =H18/V18 -> #DIV/0! | X18: =H18*V1 -> 1245.84 | Y18: =IF(X18>0,X18/T18,0) -> 5.2789831 | Z18: =IF(X18>0,X18/V18,0) -> #DIV/0!
A19: 13 | B19: 90339.233 | C19: =IF(B19>=B18,B19-B18,0)*10*0.58 -> 76.753333 | D19: 13645.933 | E19: =IF(D19>=D18,D19-D18,0)*10*0.58 -> 98.213333 | F19: 64633.6 | G19: =IF(F19>=F18,F19-F18,0)*0.58 -> 152.888 | H19: =C19+E19+G19 -> 327.85467 | O19: =IF(N19>=N18,N19-N18,0) -> 0 | Q19: =(H19-O19)*0.58 -> 190.15571 | S19: =IF(R19-R18>0,R19-R18,0) -> 0 | T19: =Elect!BT18 -> 234 | U19: =H19/T19 -> 1.4010883 | V19: =Elect!BV18 -> 0 | W19: =H19/V19 -> #DIV/0! | X19: =H19*V1 -> 1311.4187 | Y19: =IF(X19>0,X19/T19,0) -> 5.6043533 | Z19: =IF(X19>0,X19/V19,0) -> #DIV/0!
A20: 14 | B20: 90353.1 | C20: =IF(B20>=B19,B20-B19,0)*10*0.58 -> 80.426667 | D20: 13663.3 | E20: =IF(D20>=D19,D20-D19,0)*10*0.58 -> 100.72667 | F20: 64870 | G20: =IF(F20>=F19,F20-F19,0)*0.58 -> 137.112 | H20: =C20+E20+G20 -> 318.26533 | O20: =IF(N20>=N19,N20-N19,0) -> 0 | Q20: =(H20-O20)*0.58 -> 184.59389 | S20: =IF(R20-R19>0,R20-R19,0) -> 0 | T20: =Elect!BT19 -> 234 | U20: =H20/T20 -> 1.3601083 | V20: =Elect!BV19 -> 0 | W20: =H20/V20 -> #DIV/0! | X20: =H20*V1 -> 1273.0613 | Y20: =IF(X20>0,X20/T20,0) -> 5.440433 | Z20: =IF(X20>0,X20/V20,0) -> #DIV/0!
A21: 15 | B21: 90366.967 | C21: =IF(B21>=B20,B21-B20,0)*10*0.58 -> 80.426667 | D21: 13680.667 | E21: =IF(D21>=D20,D21-D20,0)*10*0.58 -> 100.72667 | F21: 65106.4 | G21: =IF(F21>=F20,F21-F20,0)*0.58 -> 137.112 | H21: =C21+E21+G21 -> 318.26533 | O21: =IF(N21>=N20,N21-N20,0) -> 0 | Q21: =(H21-O21)*0.58 -> 184.59389 | S21: =IF(R21-R20>0,R21-R20,0) -> 0 | T21: =Elect!BT20 -> 234 | U21: =H21/T21 -> 1.3601083 | V21: =Elect!BV20 -> 0 | W21: =H21/V21 -> #DIV/0! | X21: =H21*V1 -> 1273.0613 | Y21: =IF(X21>0,X21/T21,0) -> 5.440433 | Z21: =IF(X21>0,X21/V21,0) -> #DIV/0!
A22: 16 | B22: 90380.833 | C22: =IF(B22>=B21,B22-B21,0)*10*0.58 -> 80.426667 | D22: 13698.033 | E22: =IF(D22>=D21,D22-D21,0)*10*0.58 -> 100.72667 | F22: 65342.8 | G22: =IF(F22>=F21,F22-F21,0)*0.58 -> 137.112 | H22: =C22+E22+G22 -> 318.26533 | O22: =IF(N22>=N21,N22-N21,0) -> 0 | Q22: =(H22-O22)*0.58 -> 184.59389 | S22: =IF(R22-R21>0,R22-R21,0) -> 0 | T22: =Elect!BT21 -> 232 | U22: =H22/T22 -> 1.3718333 | V22: =Elect!BV21 -> 0 | W22: =H22/V22 -> #DIV/0! | X22: =H22*V1 -> 1273.0613 | Y22: =IF(X22>0,X22/T22,0) -> 5.4873333 | Z22: =IF(X22>0,X22/V22,0) -> #DIV/0!
A23: 17 | B23: 90405 | C23: =IF(B23>=B22,B23-B22,0)*10*0.58 -> 140.16667 | D23: 13729 | E23: =IF(D23>=D22,D23-D22,0)*10*0.58 -> 179.60667 | F23: 65424 | G23: =IF(F23>=F22,F23-F22,0)*0.58 -> 47.096 | H23: =C23+E23+G23 -> 366.86933 | O23: =IF(N23>=N22,N23-N22,0) -> 0 | Q23: =(H23-O23)*0.58 -> 212.78421 | S23: =IF(R23-R22>0,R23-R22,0) -> 0 | T23: =Elect!BT22 -> 216 | U23: =H23/T23 -> 1.6984691 | V23: =Elect!BV22 -> 0 | W23: =H23/V23 -> #DIV/0! | X23: =H23*V1 -> 1467.4773 | Y23: =IF(X23>0,X23/T23,0) -> 6.7938765 | Z23: =IF(X23>0,X23/V23,0) -> #DIV/0!
A24: 18 | B24: 90419 | C24: =IF(B24>=B23,B24-B23,0)*10*0.58 -> 81.2 | D24: 13748 | E24: =IF(D24>=D23,D24-D23,0)*10*0.58 -> 110.2 | F24: 65633 | G24: =IF(F24>=F23,F24-F23,0)*0.58 -> 121.22 | H24: =C24+E24+G24 -> 312.62 | O24: =IF(N24>=N23,N24-N23,0) -> 0 | Q24: =(H24-O24)*0.58 -> 181.3196 | S24: =IF(R24-R23>0,R24-R23,0) -> 0 | T24: =Elect!BT23 -> 167 | U24: =H24/T24 -> 1.871976 | V24: =Elect!BV23 -> 0 | W24: =H24/V24 -> #DIV/0! | X24: =H24*V1 -> 1250.48 | Y24: =IF(X24>0,X24/T24,0) -> 7.4879042 | Z24: =IF(X24>0,X24/V24,0) -> #DIV/0!
A25: 19 | B25: 90433 | C25: =IF(B25>=B24,B25-B24,0)*10*0.58 -> 81.2 | D25: 13765 | E25: =IF(D25>=D24,D25-D24,0)*10*0.58 -> 98.6 | F25: 65844 | G25: =IF(F25>=F24,F25-F24,0)*0.58 -> 122.38 | H25: =C25+E25+G25 -> 302.18 | O25: =IF(N25>=N24,N25-N24,0) -> 0 | Q25: =(H25-O25)*0.58 -> 175.2644 | S25: =IF(R25-R24>0,R25-R24,0) -> 0 | T25: =Elect!BT24 -> 191 | U25: =H25/T25 -> 1.5820942 | V25: =Elect!BV24 -> 0 | W25: =H25/V25 -> #DIV/0! | X25: =H25*V1 -> 1208.72 | Y25: =IF(X25>0,X25/T25,0) -> 6.328377 | Z25: =IF(X25>0,X25/V25,0) -> #DIV/0!
A26: 20 | B26: 90450 | C26: =IF(B26>=B25,B26-B25,0)*10*0.58 -> 98.6 | D26: 13787 | E26: =IF(D26>=D25,D26-D25,0)*10*0.58 -> 127.6 | F26: 66066 | G26: =IF(F26>=F25,F26-F25,0)*0.58 -> 128.76 | H26: =C26+E26+G26 -> 354.96 | O26: =IF(N26>=N25,N26-N25,0) -> 0 | Q26: =(H26-O26)*0.58 -> 205.8768 | S26: =IF(R26-R25>0,R26-R25,0) -> 0 | T26: =Elect!BT25 -> 233 | U26: =H26/T26 -> 1.5234335 | V26: =Elect!BV25 -> 0 | W26: =H26/V26 -> #DIV/0! | X26: =H26*V1 -> 1419.84 | Y26: =IF(X26>0,X26/T26,0) -> 6.0937339 | Z26: =IF(X26>0,X26/V26,0) -> #DIV/0!
A27: 21 | B27: 90464 | C27: =IF(B27>=B26,B27-B26,0)*10*0.58 -> 81.2 | D27: 13805 | E27: =IF(D27>=D26,D27-D26,0)*10*0.58 -> 104.4 | F27: 66276 | G27: =IF(F27>=F26,F27-F26,0)*0.58 -> 121.8 | H27: =C27+E27+G27 -> 307.4 | O27: =IF(N27>=N26,N27-N26,0) -> 0 | Q27: =(H27-O27)*0.58 -> 178.292 | S27: =IF(R27-R26>0,R27-R26,0) -> 0 | T27: =Elect!BT26 -> 202 | U27: =H27/T27 -> 1.5217822 | V27: =Elect!BV26 -> 0 | W27: =H27/V27 -> #DIV/0! | X27: =H27*V1 -> 1229.6 | Y27: =IF(X27>0,X27/T27,0) -> 6.0871287 | Z27: =IF(X27>0,X27/V27,0) -> #DIV/0!
A28: 22 | B28: 90478.9 | C28: =IF(B28>=B27,B28-B27,0)*10*0.58 -> 86.42 | D28: 13824.1 | E28: =IF(D28>=D27,D28-D27,0)*10*0.58 -> 110.78 | F28: 66489.7 | G28: =IF(F28>=F27,F28-F27,0)*0.58 -> 123.946 | H28: =C28+E28+G28 -> 321.146 | O28: =IF(N28>=N27,N28-N27,0) -> 0 | Q28: =(H28-O28)*0.58 -> 186.26468 | S28: =IF(R28-R27>0,R28-R27,0) -> 0 | T28: =Elect!BT27 -> 209 | U28: =H28/T28 -> 1.5365837 | V28: =Elect!BV27 -> 0 | W28: =H28/V28 -> #DIV/0! | X28: =H28*V1 -> 1284.584 | Y28: =IF(X28>0,X28/T28,0) -> 6.1463349 | Z28: =IF(X28>0,X28/V28,0) -> #DIV/0!
A29: 23 | B29: 90498 | C29: =IF(B29>=B28,B29-B28,0)*10*0.58 -> 110.78 | D29: 13847 | E29: =IF(D29>=D28,D29-D28,0)*10*0.58 -> 132.82 | F29: 66684 | G29: =IF(F29>=F28,F29-F28,0)*0.58 -> 112.694 | H29: =C29+E29+G29 -> 356.294 | O29: =IF(N29>=N28,N29-N28,0) -> 0 | Q29: =(H29-O29)*0.58 -> 206.65052 | S29: =IF(R29-R28>0,R29-R28,0) -> 0 | T29: =Elect!BT28 -> 229 | U29: =H29/T29 -> 1.555869 | V29: =Elect!BV28 -> 0 | W29: =H29/V29 -> #DIV/0! | X29: =H29*V1 -> 1425.176 | Y29: =IF(X29>0,X29/T29,0) -> 6.223476 | Z29: =IF(X29>0,X29/V29,0) -> #DIV/0!
A30: 24 | B30: 90515 | C30: =IF(B30>=B29,B30-B29,0)*10*0.58 -> 98.6 | D30: 13868 | E30: =IF(D30>=D29,D30-D29,0)*10*0.58 -> 121.8 | F30: 66902 | G30: =IF(F30>=F29,F30-F29,0)*0.58 -> 126.44 | H30: =C30+E30+G30 -> 346.84 | O30: =IF(N30>=N29,N30-N29,0) -> 0 | Q30: =(H30-O30)*0.58 -> 201.1672 | S30: =IF(R30-R29>0,R30-R29,0) -> 0 | T30: =Elect!BT29 -> 215 | U30: =H30/T30 -> 1.6132093 | V30: =Elect!BV29 -> 0 | W30: =H30/V30 -> #DIV/0! | X30: =H30*V1 -> 1387.36 | Y30: =IF(X30>0,X30/T30,0) -> 6.4528372 | Z30: =IF(X30>0,X30/V30,0) -> #DIV/0!
A31: 25 | B31: 90534 | C31: =IF(B31>=B30,B31-B30,0)*10*0.58 -> 110.2 | D31: 13889 | E31: =IF(D31>=D30,D31-D30,0)*10*0.58 -> 121.8 | F31: 67110 | G31: =IF(F31>=F30,F31-F30,0)*0.58 -> 120.64 | H31: =C31+E31+G31 -> 352.64 | O31: =IF(N31>=N30,N31-N30,0) -> 0 | Q31: =(H31-O31)*0.58 -> 204.5312 | S31: =IF(R31-R30>0,R31-R30,0) -> 0 | T31: =Elect!BT30 -> 221 | U31: =H31/T31 -> 1.5956561 | V31: =Elect!BV30 -> 0 | W31: =H31/V31 -> #DIV/0! | X31: =H31*V1 -> 1410.56 | Y31: =IF(X31>0,X31/T31,0) -> 6.3826244 | Z31: =IF(X31>0,X31/V31,0) -> #DIV/0!
A32: 26 | B32: 90548 | C32: =IF(B32>=B31,B32-B31,0)*10*0.58 -> 81.2 | D32: 13911 | E32: =IF(D32>=D31,D32-D31,0)*10*0.58 -> 127.6 | F32: 67317 | G32: =IF(F32>=F31,F32-F31,0)*0.58 -> 120.06 | H32: =C32+E32+G32 -> 328.86 | O32: =IF(N32>=N31,N32-N31,0) -> 0 | Q32: =(H32-O32)*0.58 -> 190.7388 | S32: =IF(R32-R31>0,R32-R31,0) -> 0 | T32: =Elect!BT31 -> 231 | U32: =H32/T32 -> 1.4236364 | V32: =Elect!BV31 -> 0 | W32: =H32/V32 -> #DIV/0! | X32: =H32*V1 -> 1315.44 | Y32: =IF(X32>0,X32/T32,0) -> 5.6945455 | Z32: =IF(X32>0,X32/V32,0) -> #DIV/0!
A33: 27 | B33: 90565 | C33: =IF(B33>=B32,B33-B32,0)*10*0.58 -> 98.6 | D33: 13932 | E33: =IF(D33>=D32,D33-D32,0)*10*0.58 -> 121.8 | F33: 67503 | G33: =IF(F33>=F32,F33-F32,0)*0.58 -> 107.88 | H33: =C33+E33+G33 -> 328.28 | O33: =IF(N33>=N32,N33-N32,0) -> 0 | Q33: =(H33-O33)*0.58 -> 190.4024 | S33: =IF(R33-R32>0,R33-R32,0) -> 0 | T33: =Elect!BT32 -> 200 | U33: =H33/T33 -> 1.6414 | V33: =Elect!BV32 -> 0 | W33: =H33/V33 -> #DIV/0! | X33: =H33*V1 -> 1313.12 | Y33: =IF(X33>0,X33/T33,0) -> 6.5656 | Z33: =IF(X33>0,X33/V33,0) -> #DIV/0!
A34: 28 | B34: 90580 | C34: =IF(B34>=B33,B34-B33,0)*10*0.58 -> 87 | D34: 13953.5 | E34: =IF(D34>=D33,D34-D33,0)*10*0.58 -> 124.7 | F34: 67703 | G34: =IF(F34>=F33,F34-F33,0)*0.58 -> 116 | H34: =C34+E34+G34 -> 327.7 | O34: =IF(N34>=N33,N34-N33,0) -> 0 | Q34: =(H34-O34)*0.58 -> 190.066 | S34: =IF(R34-R33>0,R34-R33,0) -> 0 | T34: =Elect!BT33 -> 243 | U34: =H34/T34 -> 1.3485597 | V34: =Elect!BV33 -> 0 | W34: =H34/V34 -> #DIV/0! | X34: =H34*V1 -> 1310.8 | Y34: =IF(X34>0,X34/T34,0) -> 5.3942387 | Z34: =IF(X34>0,X34/V34,0) -> #DIV/0!
A35: 29 | B35: 90595.5 | C35: =IF(B35>=B34,B35-B34,0)*10*0.58 -> 89.9 | D35: 13974.9 | E35: =IF(D35>=D34,D35-D34,0)*10*0.58 -> 124.12 | F35: 67899.5 | G35: =IF(F35>=F34,F35-F34,0)*0.58 -> 113.97 | H35: =C35+E35+G35 -> 327.99 | O35: =IF(N35>=N34,N35-N34,0) -> 0 | Q35: =(H35-O35)*0.58 -> 190.2342 | S35: =IF(R35-R34>0,R35-R34,0) -> 0 | T35: =Elect!BT34 -> 235 | U35: =H35/T35 -> 1.3957021 | V35: =Elect!BV34 -> 0 | W35: =H35/V35 -> #DIV/0! | X35: =H35*V1 -> 1311.96 | Y35: =IF(X35>0,X35/T35,0) -> 5.5828085 | Z35: =IF(X35>0,X35/V35,0) -> #DIV/0!
A36: 30 | B36: 90610.667 | C36: =IF(B36>=B35,B36-B35,0)*10*0.58 -> 87.966667 | D36: 13996.3 | E36: =IF(D36>=D35,D36-D35,0)*10*0.58 -> 124.12 | F36: 68098.333 | G36: =IF(F36>=F35,F36-F35,0)*0.58 -> 115.32333 | H36: =C36+E36+G36 -> 327.41 | O36: =IF(N36>=N35,N36-N35,0) -> 0 | Q36: =(H36-O36)*0.58 -> 189.8978 | S36: =IF(R36-R35>0,R36-R35,0) -> 0 | T36: =Elect!BT35 -> 240 | U36: =H36/T36 -> 1.3642083 | V36: =Elect!BV35 -> 0 | W36: =H36/V36 -> #DIV/0! | X36: =H36*V1 -> 1309.64 | Y36: =IF(X36>0,X36/T36,0) -> 5.4568333 | Z36: =IF(X36>0,X36/V36,0) -> #DIV/0!
A37: 31 | B37: 90625.917 | C37: =IF(B37>=B36,B37-B36,0)*10*0.58 -> 88.45 | D37: 14017.7 | E37: =IF(D37>=D36,D37-D36,0)*10*0.58 -> 124.12 | F37: 68296.583 | G37: =IF(F37>=F36,F37-F36,0)*0.58 -> 114.985 | H37: =C37+E37+G37 -> 327.555 | I37: 322 | K37: 5583 | O37: =IF(N37>=N36,N37-N36,0) -> 0 | Q37: =(H37-O37)*0.58 -> 189.9819 | S37: =IF(R37-R36>0,R37-R36,0) -> 0 | T37: =Elect!BT36 -> 236.33333 | U37: =H37/T37 -> 1.3859873 | V37: =Elect!BV36 -> 0 | W37: =H37/V37 -> #DIV/0! | X37: =H37*V7 -> 0 | Y37: =IF(X37>0,X37/T37,0) -> 0 | Z37: =IF(X37>0,X37/V37,0) -> 0
A38: MTD | C38: =SUM(C7:C37) -> 2845.3833 | E38: =SUM(E7:E37) -> 3661.9267 | G38: =SUM(G7:G37) -> 3772.6583 | H38: =SUM(H7:H37) -> 10279.968 | I38: =I37-I6 -> 12 | K38: =K37-K6 -> 107 | O38: =SUM(O7:O36) -> 0 | Q38: =SUM(Q7:Q34) -> 5392.2677 | S38: =SUM(S7:S34) -> 0 | T38: =SUM(T7:T36) -> 6523 | U38: =IF(H38>0,H38/T38,0) -> 1.5759571 | V38: =SUM(V7:V36) -> 0 | W38: =IF(H38>0,H38/V38,0) -> #DIV/0! | X38: =SUM(X7:X36) -> 39809.653 | Y38: =IF(X38>0,X38/T38,0) -> 6.1029669 | Z38: =IF(X38>0,X38/V38,0) -> #DIV/0!
A39: AVER. Act | C39: =C38/B48 -> 94.846111 | E39: =E38/B48 -> 122.06422 | G39: =G38/B48 -> 125.75528 | H39: =H38/B48 -> 342.66561 | O39: =O38/B48 -> 0 | Q39: =Q38/B48 -> 179.74226 | S39: =S38/C48 -> #DIV/0! | T39: =T38/B48 -> 217.43333 | U39: =IF(H39>0,H39/T39,0) -> 1.5759571 | V39: =V38/B48 -> 0 | W39: =IF(H39>0,H39/V39,0) -> #DIV/0! | X39: =X38/B48 -> 1326.9884 | Y39: =IF(X39>0,X39/T39,0) -> 6.1029669 | Z39: =IF(X39>0,X39/V39,0) -> #DIV/0!
A40: TOTAL Budget | T40: =YTD!Q2341 -> 0 | U40: =IF(#REF!>0,#REF!/T40,0) -> #REF! | V40: =YTD!Q2342 -> 0 | W40: =IF(#REF!>0,#REF!/V40,0) -> #REF! | X40: =YTD!Q2346 -> 0 | Y40: =IF(X40>0,X40/T40,0) -> 0 | Z40: =IF(X40>0,X40/V40,0) -> 0
A41: Budget MTD | F41: 66684 | T41: =T42*C48 -> #VALUE! | U41: =IF(#REF!>0,#REF!/T41,0) -> #REF! | V41: =V42*C48 -> #VALUE! | W41: =IF(#REF!>0,#REF!/V41,0) -> #REF! | X41: =#REF!*5.62 -> #REF! | Y41: =IF(X41>0,X41/T41,0) -> #REF! | Z41: =IF(X41>0,X41/V41,0) -> #REF!
A42: AVER. Bud | F42: 66684 | T42: =T40/$A$48 -> #VALUE! | V42: =V40/$A$48 -> #VALUE!
A43: Total RFC | F43: 66684 | T43: =YTD!Q2358 -> 0 | V43: =YTD!Q2359 -> 0 | X43: =YTD!Q2363 -> 0 | Y43: =IF(X43>0,X43/T43,0) -> 0 | Z43: =IF(X43>0,X43/V43,0) -> 0
A44: RFC MTD | F44: 66684 | T44: =T43/A48*C48 -> #VALUE! | V44: =V43/A48*C48 -> #VALUE! | X44: =X43/A48*C48 -> #VALUE! | Y44: =IF(X44>0,X44/T44,0) -> #VALUE! | Z44: =IF(X44>0,X44/V44,0) -> #VALUE!
A45: AVER RFC | F45: 66684 | T45: =T43/A48 -> #VALUE! | V45: =V44/A48*C48 -> #VALUE! | X45: =X43/A48 -> #VALUE!
A46: MTD 13 | F46: 66684 | U46: =Consp!BH33 -> 1.1514679 | W46: =Consp!BI33 -> 0.57929342 | X46: =Consp!BJ33 -> 140121.3 | Y46: =Consp!BK33 -> 6.8331854 | Z46: =Consp!BL33 -> 3.4377159
A47: AVER. Act 13 | F47: 66684 | U47: =Consp!BH34 -> 1.1761372 | W47: =Consp!BI34 -> 0.60007377 | X47: =Consp!BJ34 -> 5004.3322 | Y47: =Consp!BK34 -> 6.8331854 | Z47: =Consp!BL34 -> 3.4377159
A48: No of Days MTD | B48: =COUNTIF(B7:B36,">0") -> 30 | F48: 66684
A136: Water Incoming

Sheet Gas
A1: =Elect!A1 -> 44896 | E1: Gas | H1: Gas UP | J1: 3.9
A4: NO. | B4: Main Gas Flow Meter | D4: Laundry Gas Flow Meter | F4: Grumandiz Gas Flow Meter | H4: Plant Room Gas Share Cost | I4: Hotel Consumption Cost | J4: La Grumandiz Cost | K4: Total Natural Gas Consumption
B5: Read | C5: Cons | D5: Read | E5: Cons | F5: Read | G5: Cons | H5: LE/DAY | I5: LE/DAY | J5: LE/DAY | K5: Cons
B6: 8406888 | C6: =IF(B6>=B5,B6-B5,0)*1.06 -> 0 | D6: 598602.33 | E6: =IF(D6>=D5,D6-D5,0)*0.7 -> 0 | F6: 629322.67 | G6: =IF(F6>=F5,F6-F5,0) -> 0 | K6: =C6+E6 -> 0
A7: 1 | B7: 8408205 | C7: =IF(B7>=B6,B7-B6,0)*1.06 -> 1396.02 | D7: 599184 | E7: =IF(D7>=D6,D7-D6,0)*0.7 -> 407.16667 | F7: 629388.11 | G7: =IF(F7>=F6,F7-F6,0) -> 65.444444 | H7: =(E7*0.55)*1.61 -> 360.54608 | I7: =C7*J1 -> 5444.478 | J7: =G7*J1 -> 255.23333 | K7: =C7+E7 -> 1803.1867
A8: 2 | B8: 8409755 | C8: =IF(B8>=B7,B8-B7,0)*1.06 -> 1643 | D8: 599678 | E8: =IF(D8>=D7,D8-D7,0)*0.7 -> 345.8 | F8: 629479 | G8: =IF(F8>=F7,F8-F7,0) -> 90.888889 | H8: =(E8*0.55)*1.61 -> 306.2059 | I8: =C8*J1 -> 6407.7 | J8: =G8*J1 -> 354.46667 | K8: =C8+E8 -> 1988.8
A9: 3 | B9: 8411305 | C9: =IF(B9>=B8,B9-B8,0)*1.06 -> 1643 | D9: 600172 | E9: =IF(D9>=D8,D9-D8,0)*0.7 -> 345.8 | F9: 629560.33 | G9: =IF(F9>=F8,F9-F8,0) -> 81.333333 | H9: =(E9*0.55)*1.61 -> 306.2059 | I9: =C9*J1 -> 6407.7 | J9: =G9*J1 -> 317.2 | K9: =C9+E9 -> 1988.8
A10: 4 | B10: 8412855 | C10: =IF(B10>=B9,B10-B9,0)*1.06 -> 1643 | D10: 600656 | E10: =IF(D10>=D9,D10-D9,0)*0.7 -> 338.8 | F10: 629656 | G10: =IF(F10>=F9,F10-F9,0) -> 95.666667 | H10: =(E10*0.55)*1.61 -> 300.0074 | I10: =C10*J1 -> 6407.7 | J10: =G10*J1 -> 373.1 | K10: =C10+E10 -> 1981.8
A11: 5 | B11: 8414405 | C11: =IF(B11>=B10,B11-B10,0)*1.06 -> 1643 | D11: 601140 | E11: =IF(D11>=D10,D11-D10,0)*0.7 -> 338.8 | F11: 629753 | G11: =IF(F11>=F10,F11-F10,0) -> 97 | H11: =(E11*0.55)*1.61 -> 300.0074 | I11: =C11*J1 -> 6407.7 | J11: =G11*J1 -> 378.3 | K11: =C11+E11 -> 1981.8
A12: 6 | B12: 8415955 | C12: =IF(B12>=B11,B12-B11,0)*1.06 -> 1643 | D12: 601593 | E12: =IF(D12>=D11,D12-D11,0)*0.7 -> 317.1 | F12: 629848 | G12: =IF(F12>=F11,F12-F11,0) -> 95 | H12: =(E12*0.55)*1.61 -> 280.79205 | I12: =C12*J1 -> 6407.7 | J12: =G12*J1 -> 370.5 | K12: =C12+E12 -> 1960.1
A13: 7 | B13: 8417505 | C13: =IF(B13>=B12,B13-B12,0)*1.06 -> 1643 | D13: 602066.67 | E13: =IF(D13>=D12,D13-D12,0)*0.7 -> 331.56667 | F13: 629944.33 | G13: =IF(F13>=F12,F13-F12,0) -> 96.333333 | H13: =(E13*0.55)*1.61 -> 293.60228 | I13: =C13*J1 -> 6407.7 | J13: =G13*J1 -> 375.7 | K13: =C13+E13 -> 1974.5667
A14: 8 | B14: 8419055 | C14: =IF(B14>=B13,B14-B13,0)*1.06 -> 1643 | D14: 602535.17 | E14: =IF(D14>=D13,D14-D13,0)*0.7 -> 327.95 | F14: 630040.33 | G14: =IF(F14>=F13,F14-F13,0) -> 96 | H14: =(E14*0.55)*1.61 -> 290.39973 | I14: =C14*J1 -> 6407.7 | J14: =G14*J1 -> 374.4 | K14: =C14+E14 -> 1970.95
A15: 9 | B15: 8419880 | C15: =IF(B15>=B14,B15-B14,0)*1.06 -> 874.5 | D15: 603084 | E15: =IF(D15>=D14,D15-D14,0)*0.7 -> 384.18333 | F15: 630131 | G15: =IF(F15>=F14,F15-F14,0) -> 90.666667 | H15: =(E15*0.55)*1.61 -> 340.19434 | I15: =C15*J1 -> 3410.55 | J15: =G15*J1 -> 353.6 | K15: =C15+E15 -> 1258.6833
A16: 10 | B16: 8421268 | C16: =IF(B16>=B15,B16-B15,0)*1.06 -> 1471.28 | D16: 603522 | E16: =IF(D16>=D15,D16-D15,0)*0.7 -> 306.6 | F16: 630221 | G16: =IF(F16>=F15,F16-F15,0) -> 90 | H16: =(E16*0.55)*1.61 -> 271.4943 | I16: =C16*J1 -> 5737.992 | J16: =G16*J1 -> 351 | K16: =C16+E16 -> 1777.88
A17: 11 | B17: 8422600 | C17: =IF(B17>=B16,B17-B16,0)*1.06 -> 1411.92 | D17: 604002 | E17: =IF(D17>=D16,D17-D16,0)*0.7 -> 336 | F17: 630309 | G17: =IF(F17>=F16,F17-F16,0) -> 88 | H17: =(E17*0.55)*1.61 -> 297.528 | I17: =C17*J1 -> 5506.488 | J17: =G17*J1 -> 343.2 | K17: =C17+E17 -> 1747.92
A18: 12 | B18: 8424018 | C18: =IF(B18>=B17,B18-B17,0)*1.06 -> 1503.08 | D18: 604520 | E18: =IF(D18>=D17,D18-D17,0)*0.7 -> 362.6 | F18: 630400 | G18: =IF(F18>=F17,F18-F17,0) -> 91 | H18: =(E18*0.55)*1.61 -> 321.0823 | I18: =C18*J1 -> 5862.012 | J18: =G18*J1 -> 354.9 | K18: =C18+E18 -> 1865.68
A19: 13 | B19: 8425179.8 | C19: =IF(B19>=B18,B19-B18,0)*1.06 -> 1231.508 | D19: 604998.93 | E19: =IF(D19>=D18,D19-D18,0)*0.7 -> 335.25333 | F19: 630491.71 | G19: =IF(F19>=F18,F19-F18,0) -> 91.711111 | H19: =(E19*0.55)*1.61 -> 296.86683 | I19: =C19*J1 -> 4802.8812 | J19: =G19*J1 -> 357.67333 | K19: =C19+E19 -> 1566.7613
A20: 14 | B20: 8426453.7 | C20: =IF(B20>=B19,B20-B19,0)*1.06 -> 1350.3794 | D20: 605487.7 | E20: =IF(D20>=D19,D20-D19,0)*0.7 -> 342.13667 | F20: 630582.41 | G20: =IF(F20>=F19,F20-F19,0) -> 90.695238 | H20: =(E20*0.55)*1.61 -> 302.96202 | I20: =C20*J1 -> 5266.4798 | J20: =G20*J1 -> 353.71143 | K20: =C20+E20 -> 1692.5161
A21: 15 | B21: 8427727.7 | C21: =IF(B21>=B20,B21-B20,0)*1.06 -> 1350.3794 | D21: 605976.47 | E21: =IF(D21>=D20,D21-D20,0)*0.7 -> 342.13667 | F21: 630673.1 | G21: =IF(F21>=F20,F21-F20,0) -> 90.695238 | H21: =(E21*0.55)*1.61 -> 302.96202 | I21: =C21*J1 -> 5266.4798 | J21: =G21*J1 -> 353.71143 | K21: =C21+E21 -> 1692.5161
A22: 16 | B22: 8429001.6 | C22: =IF(B22>=B21,B22-B21,0)*1.06 -> 1350.3794 | D22: 606465.23 | E22: =IF(D22>=D21,D22-D21,0)*0.7 -> 342.13667 | F22: 630763.8 | G22: =IF(F22>=F21,F22-F21,0) -> 90.695238 | H22: =(E22*0.55)*1.61 -> 302.96202 | I22: =C22*J1 -> 5266.4798 | J22: =G22*J1 -> 353.71143 | K22: =C22+E22 -> 1692.5161
A23: 17 | B23: 8431136 | C23: =IF(B23>=B22,B23-B22,0)*1.06 -> 2262.4337 | D23: 607160 | E23: =IF(D23>=D22,D23-D22,0)*0.7 -> 486.33667 | F23: 630863 | G23: =IF(F23>=F22,F23-F22,0) -> 99.203175 | H23: =(E23*0.55)*1.61 -> 430.65112 | I23: =C23*J1 -> 8823.4915 | J23: =G23*J1 -> 386.89238 | K23: =C23+E23 -> 2748.7704
A24: 18 | B24: 8432635 | C24: =IF(B24>=B23,B24-B23,0)*1.06 -> 1588.94 | D24: 607670 | E24: =IF(D24>=D23,D24-D23,0)*0.7 -> 357 | F24: 630965 | G24: =IF(F24>=F23,F24-F23,0) -> 102 | H24: =(E24*0.55)*1.61 -> 316.1235 | I24: =C24*J1 -> 6196.866 | J24: =G24*J1 -> 397.8 | K24: =C24+E24 -> 1945.94
A25: 19 | B25: 8434106 | C25: =IF(B25>=B24,B25-B24,0)*1.06 -> 1559.26 | D25: 608174 | E25: =IF(D25>=D24,D25-D24,0)*0.7 -> 352.8 | F25: 631041 | G25: =IF(F25>=F24,F25-F24,0) -> 76 | H25: =(E25*0.55)*1.61 -> 312.4044 | I25: =C25*J1 -> 6081.114 | J25: =G25*J1 -> 296.4 | K25: =C25+E25 -> 1912.06
A26: 20 | B26: 8435595.7 | C26: =IF(B26>=B25,B26-B25,0)*1.06 -> 1579.0467 | D26: 608735 | E26: =IF(D26>=D25,D26-D25,0)*0.7 -> 392.7 | F26: 631126 | G26: =IF(F26>=F25,F26-F25,0) -> 85 | H26: =(E26*0.55)*1.61 -> 347.73585 | I26: =C26*J1 -> 6158.282 | J26: =G26*J1 -> 331.5 | K26: =C26+E26 -> 1971.7467
A27: 21 | B27: 8437080.7 | C27: =IF(B27>=B26,B27-B26,0)*1.06 -> 1574.1 | D27: 609258 | E27: =IF(D27>=D26,D27-D26,0)*0.7 -> 366.1 | F27: 631203 | G27: =IF(F27>=F26,F27-F26,0) -> 77 | H27: =(E27*0.55)*1.61 -> 324.18155 | I27: =C27*J1 -> 6138.99 | J27: =G27*J1 -> 300.3 | K27: =C27+E27 -> 1940.2
A28: 22 | B28: 8438565.7 | C28: =IF(B28>=B27,B28-B27,0)*1.06 -> 1574.1 | D28: 609790.5 | E28: =IF(D28>=D27,D28-D27,0)*0.7 -> 372.75 | F28: 631285.5 | G28: =IF(F28>=F27,F28-F27,0) -> 82.5 | H28: =(E28*0.55)*1.61 -> 330.07013 | I28: =C28*J1 -> 6138.99 | J28: =G28*J1 -> 321.75
A29: 23 | B29: 8440031 | C29: =IF(B29>=B28,B29-B28,0)*1.06 -> 1553.2533 | D29: 610311 | E29: =IF(D29>=D28,D29-D28,0)*0.7 -> 364.35 | F29: 631391 | G29: =IF(F29>=F28,F29-F28,0) -> 105.5 | H29: =(E29*0.55)*1.61 -> 322.63192 | I29: =C29*J1 -> 6057.688 | J29: =G29*J1 -> 411.45 | K29: =C29+E29 -> 1917.6033
A30: 24 | B30: 8441593 | C30: =IF(B30>=B29,B30-B29,0)*1.06 -> 1655.72 | D30: 610839.5 | E30: =IF(D30>=D29,D30-D29,0)*0.7 -> 369.95 | F30: 631481 | G30: =IF(F30>=F29,F30-F29,0) -> 90 | H30: =(E30*0.55)*1.61 -> 327.59073 | I30: =C30*J1 -> 6457.308 | J30: =G30*J1 -> 351 | K30: =C30+E30 -> 2025.67
A31: 25 | B31: 8443788 | C31: =IF(B31>=B30,B31-B30,0)*1.06 -> 2326.7 | D31: 611443 | E31: =IF(D31>=D30,D31-D30,0)*0.7 -> 422.45 | F31: 631567 | G31: =IF(F31>=F30,F31-F30,0) -> 86 | H31: =(E31*0.55)*1.61 -> 374.07948 | I31: =C31*J3 -> 0 | J31: =G31*J1 -> 335.4 | K31: =C31+E31 -> 2749.15
A32: 26 | B32: 8444914 | C32: =IF(B32>=B31,B32-B31,0)*1.06 -> 1193.56 | D32: 612031 | E32: =IF(D32>=D31,D32-D31,0)*0.7 -> 411.6 | F32: 631655.67 | G32: =IF(F32>=F31,F32-F31,0) -> 88.666667 | H32: =(E32*0.55)*1.61 -> 364.4718 | I32: =C32*J1 -> 4654.884 | J32: =G32*J1 -> 345.8 | K32: =C32+E32 -> 1605.16
A33: 27 | B33: 8446559 | C33: =IF(B33>=B32,B33-B32,0)*1.06 -> 1743.7 | D33: 612566 | E33: =IF(D33>=D32,D33-D32,0)*0.7 -> 374.5 | F33: 631734 | G33: =IF(F33>=F32,F33-F32,0) -> 78.333333 | H33: =(E33*0.55)*1.61 -> 331.61975 | I33: =C33*J1 -> 6800.43 | J33: =G33*J1 -> 305.5 | K33: =C33+E33 -> 2118.2
A34: 28 | B34: 8447858 | C34: =IF(B34>=B33,B34-B33,0)*1.06 -> 1376.94 | D34: 613136.33 | E34: =IF(D34>=D33,D34-D33,0)*0.7 -> 399.23333 | F34: 631819.22 | G34: =IF(F34>=F33,F34-F33,0) -> 85.222222 | H34: =(E34*0.55)*1.61 -> 353.52112 | I34: =C34*J1 -> 5370.066 | J34: =G34*J1 -> 332.36667 | K34: =C34+E34 -> 1776.1733
A35: 29 | B35: 8449243.5 | C35: =IF(B35>=B34,B35-B34,0)*1.06 -> 1468.63 | D35: 613697.83 | E35: =IF(D35>=D34,D35-D34,0)*0.7 -> 393.05 | F35: 631902.72 | G35: =IF(F35>=F34,F35-F34,0) -> 83.5 | H35: =(E35*0.55)*1.61 -> 348.04577 | I35: =C35*J1 -> 5727.657 | J35: =G35*J1 -> 325.65 | K35: =C35+E35 -> 1861.68
A36: 30 | B36: 8450571.3 | C36: =IF(B36>=B35,B36-B35,0)*1.06 -> 1407.5033 | D36: 614265.22 | E36: =IF(D36>=D35,D36-D35,0)*0.7 -> 397.17222 | F36: 631987.37 | G36: =IF(F36>=F35,F36-F35,0) -> 84.648148 | H36: =(E36*0.55)*1.61 -> 351.696 | I36: =C36*J1 -> 5489.263 | J36: =G36*J1 -> 330.12778 | K36: =C36+E36 -> 1804.6756
A37: 31 | B37: 8451913.6 | C37: =IF(B37>=B36,B37-B36,0)*1.06 -> 1422.785 | D37: 614831.14 | E37: =IF(D37>=D36,D37-D36,0)*0.7 -> 396.14167 | F37: 632071.73 | G37: =IF(F37>=F36,F37-F36,0) -> 84.361111 | H37: =(E37*0.55)*1.61 -> 350.78345 | I37: =C37*J1 -> 5548.8615 | J37: =G37*J1 -> 329.00833 | K37: =C37+E37 -> 1818.9267
A38: MTD | C38: =SUM(C7:C37) -> 47727.118 | E38: =SUM(E7:E37) -> 11360.164 | G38: =SUM(G7:G37) -> 2749.0648 | H38: =SUM(H6:H37) -> 10059.425 | I38: =SUM(I6:I37) -> 177061.63 | J38: =SUM(J6:J37) -> 10721.353 | K38: =SUM(K6:K37) -> 57140.432
A39: Average MTD. | C39: =C38/A42 -> 1590.9039 | E39: =E38/A42 -> 378.67213 | G39: =G38/A42 -> 91.635494 | H39: =H38/A42 -> 335.31417 | I39: =I38/A42 -> 5902.0544 | J39: =J38/A42 -> 357.37843
A41: No of Days MTD
A42: =COUNTIF(B7:B36,">0") -> 30

Sheet Sheet1

Sheet Sheet2

Sheet Consp
A1: =Elect!A1 -> 44896 | L1: Summary | P1: =Elect!A1 -> 44896
B2: Elect Consuumption | H2: Water Incoming | U2: Water Consumption | AC2: Irrigation | AG2: Gas | AJ2: Cost | AK2: Solar Meter [ LIT ] | AL2: No. of Eng. | AM2: No. of Gardners | AN2: Cons. (lit) | AO2: Received Gas (tons) | AP2: Fuel Cost | AQ2: Solar level [cm] | AR2: Received Solar (tons) | AS2: Fuel Cost | AT2: Occupancy 10 | AV2: Occupancy07 | AZ2: Elect 2009 | BE2: Elect 2010 | BJ2: Water 2009 | BO2: Water 2010
A3: Date | B3: COUNTER (2) | D3: MD | F3: KVAR | H3: R.O | J3: Qenna | L3: Trucks | N3: Rimievera Line Meter | O3: Total Inc. | Q3: Total Main S.Pool | S3: Total Bar & Beach cons. | U3: Total S. Pool cons. | W3: Hotel consumption. | Y3: Sold Water | AA3: Irr. Water from R.O | AC3: Irr. Consumption. | AE3: Storage Water One tank | AF3: Grand Cons | AG3: % | AH3: Stock | AI3: Cons. | AJ3: 0 | AT3: No of guest | AU3: No. of rooms | AV3: No. of rooms | AW3: No. of guest | AX3: Cons. Per occ. room | AY3: Cons. Per guest | AZ3: Total cost | BA3: cost per room | BB3: cost per guest | BC3: Cons. Per occ. room | BD3: Cons. Per guest | BE3: Total cost | BF3: cost per room | BG3: cost per guest | BH3: Cons. Per occ. room | BI3: Cons. Per guest | BJ3: Total cost | BK3: cost per room | BL3: cost per guest | BM3: Cons. Per occ. room | BN3: Cons. Per guest | BO3: Total cost | BP3: cost per room | BQ3: cost per guest
B4: 2013 | C4: 2014 | D4: 2013 | E4: 2014 | F4: 2013 | G4: 2014 | H4: 2013 | I4: 2014 | J4: 2009 | K4: 2010 | L4: 2009 | M4: 2010 | O4: 2009 | P4: 2010 | Q4: 2009 | R4: 2010 | S4: 2009 | T4: 2010 | U4: 2009 | V4: 2010 | W4: 2009 | X4: 2010 | Y4: 2009 | Z4: 2010 | AA4: 2009 | AB4: 2010 | AC4: 2009 | AD4: 2010
A5: 1 | B5: 33600 | C5: =Elect!J6 -> 5035.1667 | D5: 0 | E5: =Elect!M6 -> 1759.3333 | F5: 20 | G5: =Elect!O6 -> 2390 | H5: 800 | I5: =Water!C7 -> 253.26667 | J5: 0 | K5: =Water!E7 -> 322.86667 | L5: 0 | M5: =Water!#REF! -> #REF! | N5: =Water!#REF! -> #REF! | O5: 1005 | P5: =Water!H7 -> 819.15333 | Q5: 114 | R5: =Water!O7 -> 0 | S5: 13 | T5: =Water!#REF! -> #REF! | U5: 147 | V5: =Water!#REF! -> #REF! | W5: 755 | X5: =Water!Q7 -> 475.10893 | Y5: 0 | Z5: =Water!#REF! -> #REF! | AA5: 0 | AB5: 0 | AC5: 690 | AD5: =Water!#REF! -> #REF! | AE5: =Water!#REF! -> #REF! | AF5: =Water!#REF! -> #REF! | AG5: =Gas!#REF! -> #REF! | AH5: =Gas!C7 -> 1396.02 | AI5: =Gas!#REF! -> #REF! | AJ5: =Gas!J7 -> 255.23333 | AK5: =Gas!#REF! -> #REF! | AL5: =Gas!#REF! -> #REF! | AM5: =Gas!#REF! -> #REF! | AN5: =Gas!#REF! -> #REF! | AO5: =Gas!#REF! -> #REF! | AP5: =Gas!#REF! -> #REF! | AQ5: =Gas!#REF! -> #REF! | AR5: =Gas!#REF! -> #REF! | AS5: =Gas!#REF! -> #REF! | AT5: =Elect!BR6 -> 136.33333 | AU5: =Elect!BP6 -> 137 | AV5: =Elect!#REF! -> #REF! | AW5: =Elect!BR6 -> 136.33333 | AX5: 48.695652 | AY5: 24.705882 | AZ5: 8835.4834 | BA5: 12.805048 | BB5: 6.496679 | BC5: =Elect!#REF! -> #REF! | BD5: =Elect!#REF! -> #REF! | BE5: =Elect!#REF! -> #REF! | BF5: =Elect!#REF! -> #REF! | BG5: =Elect!#REF! -> #REF! | BH5: 1.142029 | BI5: 0.57941176 | BJ5: 4569.1158 | BK5: 6.6219069 | BL5: 3.3596439 | BM5: =Water!U7 -> 3.9007302 | BN5: =Water!W7 -> #DIV/0! | BO5: =Water!X7 -> 3276.6133 | BP5: =Water!Y7 -> 15.602921 | BQ5: =Water!Z7 -> 0
A6: 2 | B6: 31200 | C6: =Elect!J7 -> 6579 | D6: 0 | E6: =Elect!M7 -> 1977 | F6: 20 | G6: =Elect!O7 -> 1530 | H6: 936 | I6: =Water!C8 -> 22.555556 | J6: 0 | K6: =Water!E8 -> 35.766667 | L6: 0 | M6: =Water!#REF! -> #REF! | N6: =Water!#REF! -> #REF! | O6: 1006 | P6: =Water!H8 -> 179.54222 | Q6: 113 | R6: =Water!O8 -> 0 | S6: 17 | T6: =Water!#REF! -> #REF! | U6: 140 | V6: =Water!#REF! -> #REF! | W6: 792 | X6: =Water!Q8 -> 104.13449 | Y6: 0 | Z6: =Water!#REF! -> #REF! | AA6: 0 | AB6: 0 | AC6: 370 | AD6: =Water!#REF! -> #REF! | AE6: =Water!#REF! -> #REF! | AF6: =Water!#REF! -> #REF! | AG6: =Gas!B7 -> 8408205 | AH6: =Gas!C8 -> 1643 | AI6: =Gas!#REF! -> #REF! | AJ6: =Gas!J8 -> 354.46667 | AK6: =Gas!#REF! -> #REF! | AL6: =Gas!#REF! -> #REF! | AM6: =Gas!#REF! -> #REF! | AN6: =Gas!#REF! -> #REF! | AO6: =Gas!#REF! -> #REF! | AP6: =Gas!#REF! -> #REF! | AQ6: =Gas!#REF! -> #REF! | AR6: =Gas!#REF! -> #REF! | AS6: =Gas!#REF! -> #REF! | AT6: =Elect!BR7 -> 134 | AU6: =Elect!BP7 -> 127 | AX6: 47.416413 | AY6: 23.981553 | AZ6: 8299.2754 | BA6: 12.612881 | BB6: 6.379151 | BC6: =Elect!BQ7 -> 562255 | BD6: =Elect!#REF! -> #REF! | BE6: =Elect!#REF! -> #REF! | BF6: =Elect!#REF! -> #REF! | BG6: =Elect!#REF! -> #REF! | BH6: 1.2021277 | BI6: 0.60799385 | BJ6: 5345.8654 | BK6: 8.1244156 | BL6: 4.1090434 | BM6: =Water!U8 -> 0.74191001 | BN6: =Water!W8 -> #DIV/0! | BO6: =Water!X8 -> 718.16889 | BP6: =Water!Y8 -> 2.96764 | BQ6: =Water!Z8 -> #DIV/0!
A7: 3 | B7: 31200 | C7: =Elect!J8 -> 5998 | D7: 0 | E7: =Elect!M8 -> 2024 | F7: 20 | G7: =Elect!O8 -> 1594 | H7: 685 | I7: =Water!C9 -> 85.711111 | J7: 0 | K7: =Water!E9 -> 107.3 | L7: 0 | M7: =Water!#REF! -> #REF! | N7: =Water!#REF! -> #REF! | O7: 902 | P7: =Water!H9 -> 239.41111 | Q7: 126 | R7: =Water!O9 -> 0 | S7: 26 | T7: =Water!#REF! -> #REF! | U7: 134 | V7: =Water!#REF! -> #REF! | W7: 766 | X7: =Water!Q9 -> 138.85844 | Y7: 0 | Z7: =Water!#REF! -> #REF! | AA7: 0 | AB7: 0 | AC7: 740 | AD7: =Water!#REF! -> #REF! | AE7: =Water!#REF! -> #REF! | AF7: =Water!#REF! -> #REF! | AG7: =Gas!B9 -> 8411305 | AH7: =Gas!C9 -> 1643 | AI7: =Gas!#REF! -> #REF! | AJ7: =Gas!J9 -> 317.2 | AK7: =Gas!#REF! -> #REF! | AL7: =Gas!#REF! -> #REF! | AM7: =Gas!#REF! -> #REF! | AN7: =Gas!#REF! -> #REF! | AO7: =Gas!#REF! -> #REF! | AP7: =Gas!#REF! -> #REF! | AQ7: =Gas!#REF! -> #REF! | AR7: =Gas!#REF! -> #REF! | AS7: =Gas!#REF! -> #REF! | AT7: =Elect!BR8 -> 149 | AU7: =Elect!BP8 -> 107 | AX7: 47.926267 | AY7: 24.223602 | AZ7: 8299.2754 | BA7: 12.748503 | BB7: 6.4435368 | BC7: =Elect!BQ8 -> 562404 | BD7: =Elect!#REF! -> #REF! | BE7: =Elect!#REF! -> #REF! | BF7: =Elect!#REF! -> #REF! | BG7: =Elect!#REF! -> #REF! | BH7: 1.0875576 | BI7: 0.54968944 | BJ7: 3912.3054 | BK7: 6.0096857 | BL7: 3.0375042 | BM7: =Water!U9 -> 1.0640494 | BN7: =Water!W9 -> #DIV/0! | BO7: =Water!X9 -> 957.64444 | BP7: =Water!Y9 -> 4.2561975 | BQ7: =Water!Z9 -> #DIV/0!
A8: 4 | B8: 33600 | C8: =Elect!J9 -> 6469 | D8: 0 | E8: =Elect!M9 -> 1987 | F8: 20 | G8: =Elect!O9 -> 1550 | H8: 786 | I8: =Water!C10 -> 83.133333 | J8: 0 | K8: =Water!E10 -> 106.33333 | L8: 0 | M8: =Water!#REF! -> #REF! | N8: =Water!#REF! -> #REF! | O8: 930 | P8: =Water!H10 -> 272.98667 | Q8: 153 | R8: =Water!O10 -> 0 | S8: 46 | T8: =Water!#REF! -> #REF! | U8: 150 | V8: =Water!#REF! -> #REF! | W8: 766 | X8: =Water!Q10 -> 158.33227 | Y8: 0 | Z8: =Water!#REF! -> #REF! | AA8: 0 | AB8: 0 | AC8: 820 | AD8: =Water!#REF! -> #REF! | AE8: =Water!#REF! -> #REF! | AF8: =Water!#REF! -> #REF! | AG8: =Gas!B10 -> 8412855 | AH8: =Gas!C10 -> 1643 | AI8: =Gas!#REF! -> #REF! | AJ8: =Gas!J10 -> 373.1 | AK8: =Gas!#REF! -> #REF! | AL8: =Gas!#REF! -> #REF! | AM8: =Gas!#REF! -> #REF! | AN8: =Gas!#REF! -> #REF! | AO8: =Gas!#REF! -> #REF! | AP8: =Gas!#REF! -> #REF! | AQ8: =Gas!#REF! -> #REF! | AR8: =Gas!#REF! -> #REF! | AS8: =Gas!#REF! -> #REF! | AT8: =Elect!BR9 -> 153 | AU8: =Elect!BP9 -> 137 | AX8: 51.06383 | AY8: 25.866051 | AZ8: 8835.4834 | BA8: 13.427786 | BB8: 6.8017578 | BC8: =Elect!BQ9 -> 562557 | BD8: =Elect!#REF! -> #REF! | BE8: =Elect!#REF! -> #REF! | BF8: =Elect!#REF! -> #REF! | BG8: =Elect!#REF! -> #REF! | BH8: 1.2218845 | BI8: 0.61893764 | BJ8: 4489.1562 | BK8: 6.8224259 | BL8: 3.4558555 | BM8: =Water!U10 -> 1.1567232 | BN8: =Water!W10 -> #DIV/0! | BO8: =Water!X10 -> 1091.9467 | BP8: =Water!Y10 -> 4.6268927 | BQ8: =Water!Z10 -> #DIV/0!
A9: 5 | B9: 31200 | C9: =Elect!J10 -> 6327 | D9: 0 | E9: =Elect!M10 -> 2106 | F9: 20 | G9: =Elect!O10 -> 1987 | H9: 789 | I9: =Water!C11 -> 87 | J9: 0 | K9: =Water!E11 -> 110.2 | L9: 0 | M9: =Water!#REF! -> #REF! | N9: =Water!#REF! -> #REF! | O9: 1003 | P9: =Water!H11 -> 325.38 | Q9: 102 | R9: =Water!O11 -> 0 | S9: 8 | T9: =Water!#REF! -> #REF! | U9: 130 | V9: =Water!#REF! -> #REF! | W9: 735 | X9: =Water!Q11 -> 188.7204 | Y9: 0 | Z9: =Water!#REF! -> #REF! | AA9: 0 | AB9: 0 | AC9: 640 | AD9: =Water!#REF! -> #REF! | AE9: =Water!#REF! -> #REF! | AF9: =Water!#REF! -> #REF! | AG9: =Gas!B11 -> 8414405 | AH9: =Gas!C11 -> 1643 | AI9: =Gas!#REF! -> #REF! | AJ9: =Gas!J11 -> 378.3 | AK9: =Gas!#REF! -> #REF! | AL9: =Gas!#REF! -> #REF! | AM9: =Gas!#REF! -> #REF! | AN9: =Gas!#REF! -> #REF! | AO9: =Gas!#REF! -> #REF! | AP9: =Gas!#REF! -> #REF! | AQ9: =Gas!#REF! -> #REF! | AR9: =Gas!#REF! -> #REF! | AS9: =Gas!#REF! -> #REF! | AT9: =Elect!BR10 -> 157 | AU9: =Elect!BP10 -> 146 | AX9: 49.840256 | AY9: 25.181598 | AZ9: 8299.2754 | BA9: 13.257628 | BB9: 6.698366 | BC9: =Elect!BQ10 -> 562714 | BD9: =Elect!#REF! -> #REF! | BE9: =Elect!#REF! -> #REF! | BF9: =Elect!#REF! -> #REF! | BG9: =Elect!#REF! -> #REF! | BH9: 1.1980831 | BI9: 0.60532688 | BJ9: 4506.2904 | BK9: 7.198547 | BL9: 3.6370383 | BM9: =Water!U11 -> 1.5063889 | BN9: =Water!W11 -> #DIV/0! | BO9: =Water!X11 -> 1301.52 | BP9: =Water!Y11 -> 6.0255556 | BQ9: =Water!Z11 -> #DIV/0!
A10: 6 | B10: 33600 | C10: =Elect!J11 -> 6729 | D10: 0 | E10: =Elect!M11 -> 1800 | F10: 20 | G10: =Elect!O11 -> 1638 | H10: 805 | I10: =Water!C12 -> 81.2 | J10: 0 | K10: =Water!E12 -> 104.4 | L10: 0 | M10: =Water!#REF! -> #REF! | N10: =Water!#REF! -> #REF! | O10: 1004 | P10: =Water!H12 -> 314.94 | Q10: 115 | R10: =Water!O12 -> 0 | S10: 21 | T10: =Water!#REF! -> #REF! | U10: 141 | V10: =Water!#REF! -> #REF! | W10: 725 | X10: =Water!Q12 -> 182.6652 | Y10: 0 | Z10: =Water!#REF! -> #REF! | AA10: 0 | AB10: 0 | AC10: 510 | AD10: =Water!#REF! -> #REF! | AE10: =Water!#REF! -> #REF! | AF10: =Water!#REF! -> #REF! | AG10: =Gas!B12 -> 8415955 | AH10: =Gas!C12 -> 1643 | AI10: =Gas!#REF! -> #REF! | AJ10: =Gas!J12 -> 370.5 | AK10: =Gas!#REF! -> #REF! | AL10: =Gas!#REF! -> #REF! | AM10: =Gas!#REF! -> #REF! | AN10: =Gas!#REF! -> #REF! | AO10: =Gas!#REF! -> #REF! | AP10: =Gas!#REF! -> #REF! | AQ10: =Gas!#REF! -> #REF! | AR10: =Gas!#REF! -> #REF! | AS10: =Gas!#REF! -> #REF! | AT10: =Elect!BR11 -> 158 | AU10: =Elect!BP11 -> 145 | AX10: 47.457627 | AY10: 23.512946 | AZ10: 8835.4834 | BA10: 12.479496 | BB10: 6.1829835 | BC10: =Elect!BQ11 -> 562872 | BD10: =Elect!#REF! -> #REF! | BE10: =Elect!#REF! -> #REF! | BF10: =Elect!#REF! -> #REF! | BG10: =Elect!#REF! -> #REF! | BH10: 1.1567797 | BI10: 0.57312806 | BJ10: 4597.6727 | BK10: 6.4938881 | BL10: 3.2174057 | BM10: =Water!U12 -> 1.5906061 | BN10: =Water!W12 -> #DIV/0! | BO10: =Water!X12 -> 1259.76 | BP10: =Water!Y12 -> 6.3624242 | BQ10: =Water!Z12 -> #DIV/0!
A11: 7 | B11: 31200 | C11: =Elect!J12 -> 6469 | D11: 0 | E11: =Elect!M12 -> 2432 | F11: 20 | G11: =Elect!O12 -> 2493 | H11: 871 | I11: =Water!C13 -> 85.066667 | J11: 0 | K11: =Water!E13 -> 108.26667 | L11: 0 | M11: =Water!#REF! -> #REF! | N11: =Water!#REF! -> #REF! | O11: 837 | P11: =Water!H13 -> 258.29333 | Q11: 113 | R11: =Water!O13 -> 0 | S11: 1 | T11: =Water!#REF! -> #REF! | U11: 151 | V11: =Water!#REF! -> #REF! | W11: 732 | X11: =Water!Q13 -> 149.81013 | Y11: 0 | Z11: =Water!#REF! -> #REF! | AA11: 0 | AB11: 0 | AC11: 1010 | AD11: =Water!#REF! -> #REF! | AE11: =Water!#REF! -> #REF! | AF11: =Water!#REF! -> #REF! | AG11: =Gas!B13 -> 8417505 | AH11: =Gas!C13 -> 1643 | AI11: =Gas!#REF! -> #REF! | AJ11: =Gas!J13 -> 375.7 | AK11: =Gas!#REF! -> #REF! | AL11: =Gas!#REF! -> #REF! | AM11: =Gas!#REF! -> #REF! | AN11: =Gas!#REF! -> #REF! | AO11: =Gas!#REF! -> #REF! | AP11: =Gas!#REF! -> #REF! | AQ11: =Gas!#REF! -> #REF! | AR11: =Gas!#REF! -> #REF! | AS11: =Gas!#REF! -> #REF! | AT11: =Elect!BR12 -> 153 | AU11: =Elect!BP12 -> 143 | AX11: 43.454039 | AY11: 21.517241 | AZ11: 8299.2754 | BA11: 11.558879 | BB11: 5.7236382 | BC11: =Elect!BQ12 -> 563025 | BD11: =Elect!#REF! -> #REF! | BE11: =Elect!#REF! -> #REF! | BF11: =Elect!#REF! -> #REF! | BG11: =Elect!#REF! -> #REF! | BH11: 1.1713092 | BI11: 0.58 | BJ11: 4974.6248 | BK11: 6.9284468 | BL11: 3.4307757 | BM11: =Water!U13 -> 1.4037681 | BN11: =Water!W13 -> #DIV/0! | BO11: =Water!X13 -> 1033.1733 | BP11: =Water!Y13 -> 5.6150725 | BQ11: =Water!Z13 -> #DIV/0!
A12: 8 | B12: 33600 | C12: =Elect!J13 -> 6399 | D12: 0 | E12: =Elect!M13 -> 2016 | F12: 20 | G12: =Elect!O13 -> 1999 | H12: 963 | I12: =Water!C14 -> 84.1 | J12: 0 | K12: =Water!E14 -> 107.3 | L12: 0 | M12: =Water!#REF! -> #REF! | N12: =Water!#REF! -> #REF! | O12: 1000 | P12: =Water!H14 -> 307.4 | Q12: 128 | R12: =Water!O14 -> 0 | S12: 24 | T12: =Water!#REF! -> #REF! | U12: 148 | V12: =Water!#REF! -> #REF! | W12: 719 | X12: =Water!Q14 -> 178.292 | Y12: 0 | Z12: =Water!#REF! -> #REF! | AA12: 0 | AB12: 0 | AC12: 630 | AD12: =Water!#REF! -> #REF! | AE12: =Water!#REF! -> #REF! | AF12: =Water!#REF! -> #REF! | AG12: =Gas!B14 -> 8419055 | AH12: =Gas!C14 -> 1643 | AI12: =Gas!#REF! -> #REF! | AJ12: =Gas!J14 -> 374.4 | AK12: =Gas!#REF! -> #REF! | AL12: =Gas!#REF! -> #REF! | AM12: =Gas!#REF! -> #REF! | AN12: =Gas!#REF! -> #REF! | AO12: =Gas!#REF! -> #REF! | AP12: =Gas!#REF! -> #REF! | AQ12: =Gas!#REF! -> #REF! | AR12: =Gas!#REF! -> #REF! | AS12: =Gas!#REF! -> #REF! | AT12: =Elect!BR13 -> 151 | AU12: =Elect!BP13 -> 136 | AX12: 48.837209 | AY12: 24.086022 | AZ12: 8835.4834 | BA12: 12.842272 | BB12: 6.3336799 | BC12: =Elect!BQ13 -> 563176 | BD12: =Elect!#REF! -> #REF! | BE12: =Elect!#REF! -> #REF! | BF12: =Elect!#REF! -> #REF! | BG12: =Elect!#REF! -> #REF! | BH12: 1.2194767 | BI12: 0.60143369 | BJ12: 5500.0731 | BK12: 7.9942923 | BL12: 3.9427047 | BM12: =Water!U14 -> 1.6706522 | BN12: =Water!W14 -> #DIV/0! | BO12: =Water!X14 -> 1229.6 | BP12: =Water!Y14 -> 6.6826087 | BQ12: =Water!Z14 -> #DIV/0!
A13: 9 | B13: 33600 | C13: =Elect!J14 -> 6217 | D13: 0 | E13: =Elect!M14 -> 2020 | F13: 20 | G13: =Elect!O14 -> 2002 | H13: 790 | I13: =Water!C15 -> 80.233333 | J13: 0 | K13: =Water!E15 -> 103.43333 | L13: 0 | M13: =Water!#REF! -> #REF! | N13: =Water!#REF! -> #REF! | O13: 841 | P13: =Water!H15 -> 380.28667 | Q13: 127 | R13: =Water!O15 -> 0 | S13: 21 | T13: =Water!#REF! -> #REF! | U13: 139 | V13: =Water!#REF! -> #REF! | W13: 701 | X13: =Water!Q15 -> 220.56627 | Y13: 0 | Z13: =Water!#REF! -> #REF! | AA13: 0 | AB13: 0 | AC13: 440 | AD13: =Water!#REF! -> #REF! | AE13: =Water!#REF! -> #REF! | AF13: =Water!#REF! -> #REF! | AG13: =Gas!B15 -> 8419880 | AH13: =Gas!C15 -> 874.5 | AI13: =Gas!#REF! -> #REF! | AJ13: =Gas!J15 -> 353.6 | AK13: =Gas!#REF! -> #REF! | AL13: =Gas!#REF! -> #REF! | AM13: =Gas!#REF! -> #REF! | AN13: =Gas!#REF! -> #REF! | AO13: =Gas!#REF! -> #REF! | AP13: =Gas!#REF! -> #REF! | AQ13: =Gas!#REF! -> #REF! | AR13: =Gas!#REF! -> #REF! | AS13: =Gas!#REF! -> #REF! | AT13: =Elect!BR14 -> 152 | AU13: =Elect!BP14 -> 134 | AX13: 49.194729 | AY13: 24.1033 | AZ13: 8835.4834 | BA13: 12.936286 | BB13: 6.3382234 | BC13: =Elect!BQ14 -> 563328 | BD13: =Elect!#REF! -> #REF! | BE13: =Elect!#REF! -> #REF! | BF13: =Elect!#REF! -> #REF! | BG13: =Elect!#REF! -> #REF! | BH13: 1.1903367 | BI13: 0.58321377 | BJ13: 4512.0018 | BK13: 6.606152 | BL13: 3.2367301 | BM13: =Water!U15 -> 2.0780692 | BN13: =Water!W15 -> #DIV/0! | BO13: =Water!X15 -> 1521.1467 | BP13: =Water!Y15 -> 8.3122769 | BQ13: =Water!Z15 -> #DIV/0!
A14: 10 | B14: 31200 | C14: =Elect!J15 -> 6463 | D14: 0 | E14: =Elect!M15 -> 2043 | F14: 20 | G14: =Elect!O15 -> 2106 | H14: 792 | I14: =Water!C16 -> 75.4 | J14: 0 | K14: =Water!E16 -> 92.8 | L14: 0 | M14: =Water!#REF! -> #REF! | N14: =Water!#REF! -> #REF! | O14: 972 | P14: =Water!H16 -> 290.58 | Q14: 126 | R14: =Water!O16 -> 0 | S14: 18 | T14: =Water!#REF! -> #REF! | U14: 145 | V14: =Water!#REF! -> #REF! | W14: 756 | X14: =Water!Q16 -> 168.5364 | Y14: 0 | Z14: =Water!#REF! -> #REF! | AA14: 0 | AB14: 0 | AC14: 580 | AD14: =Water!#REF! -> #REF! | AE14: =Water!#REF! -> #REF! | AF14: =Water!#REF! -> #REF! | AG14: =Gas!B16 -> 8421268 | AH14: =Gas!C16 -> 1471.28 | AI14: =Gas!#REF! -> #REF! | AJ14: =Gas!J16 -> 351 | AK14: =Gas!#REF! -> #REF! | AL14: =Gas!#REF! -> #REF! | AM14: =Gas!#REF! -> #REF! | AN14: =Gas!#REF! -> #REF! | AO14: =Gas!#REF! -> #REF! | AP14: =Gas!#REF! -> #REF! | AQ14: =Gas!#REF! -> #REF! | AR14: =Gas!#REF! -> #REF! | AS14: =Gas!#REF! -> #REF! | AT14: =Elect!BR15 -> 135 | AU14: =Elect!BP15 -> 129 | AX14: 49.52381 | AY14: 24.781573 | AZ14: 8299.2754 | BA14: 13.173453 | BB14: 6.5919582 | BC14: =Elect!BQ15 -> 563463 | BD14: =Elect!#REF! -> #REF! | BE14: =Elect!#REF! -> #REF! | BF14: =Elect!#REF! -> #REF! | BG14: =Elect!#REF! -> #REF! | BH14: 1.2730159 | BI14: 0.6370135 | BJ14: 4469.9646 | BK14: 7.0951819 | BL14: 3.5504087 | BM14: =Water!U16 -> 1.4037681 | BN14: =Water!W16 -> #DIV/0! | BO14: =Water!X16 -> 1162.32 | BP14: =Water!Y16 -> 5.6150725 | BQ14: =Water!Z16 -> #DIV/0!
A15: 11 | B15: 33600 | C15: =Elect!J16 -> 6856 | D15: 0 | E15: =Elect!M16 -> 2189 | F15: 20 | G15: =Elect!O16 -> 1866 | H15: 817 | I15: =Water!C17 -> 81.2 | J15: 0 | K15: =Water!E17 -> 104.4 | L15: 0 | M15: =Water!#REF! -> #REF! | N15: =Water!#REF! -> #REF! | O15: 875 | P15: =Water!H17 -> 309.14 | Q15: 122 | R15: =Water!O17 -> 0 | S15: 20 | T15: =Water!#REF! -> #REF! | U15: 156 | V15: =Water!#REF! -> #REF! | W15: 712 | X15: =Water!Q17 -> 179.3012 | Y15: 0 | Z15: =Water!#REF! -> #REF! | AA15: 0 | AB15: 0 | AC15: 850 | AD15: =Water!#REF! -> #REF! | AE15: =Water!#REF! -> #REF! | AF15: =Water!#REF! -> #REF! | AG15: =Gas!#REF! -> #REF! | AH15: =Gas!C17 -> 1411.92 | AI15: =Gas!#REF! -> #REF! | AJ15: =Gas!J17 -> 343.2 | AK15: =Gas!#REF! -> #REF! | AL15: =Gas!#REF! -> #REF! | AM15: =Gas!#REF! -> #REF! | AN15: =Gas!#REF! -> #REF! | AO15: =Gas!#REF! -> #REF! | AP15: =Gas!#REF! -> #REF! | AQ15: =Gas!#REF! -> #REF! | AR15: =Gas!#REF! -> #REF! | AS15: =Gas!#REF! -> #REF! | AT15: =Elect!BR16 -> 129 | AU15: =Elect!BP16 -> 148 | AX15: 53.333333 | AY15: 26.751592 | AZ15: 8835.4834 | BA15: 14.024577 | BB15: 7.0346206 | BC15: =Elect!BQ16 -> 563592 | BD15: =Elect!#REF! -> #REF! | BE15: =Elect!#REF! -> #REF! | BF15: =Elect!#REF! -> #REF! | BG15: =Elect!#REF! -> #REF! | BH15: 1.3460317 | BI15: 0.67515924 | BJ15: 4666.2095 | BK15: 7.4066817 | BL15: 3.7151349 | BM15: =Water!U17 -> 1.3099153 | BN15: =Water!W17 -> #DIV/0! | BO15: =Water!X17 -> 1236.56 | BP15: =Water!Y17 -> 5.239661 | BQ15: =Water!Z17 -> #DIV/0!
A16: 12 | B16: 33600 | C16: =Elect!J17 -> 6916 | D16: 0 | E16: =Elect!M17 -> 2119 | F16: 20 | G16: =Elect!O17 -> 1586 | H16: 907 | I16: =Water!C18 -> 87 | J16: 0 | K16: =Water!E18 -> 104.4 | L16: 0 | M16: =Water!#REF! -> #REF! | N16: =Water!#REF! -> #REF! | O16: 965 | P16: =Water!H18 -> 311.46 | Q16: 125 | R16: =Water!O18 -> 0 | S16: 4 | T16: =Water!#REF! -> #REF! | U16: 167 | V16: =Water!#REF! -> #REF! | W16: 705 | X16: =Water!Q18 -> 180.6468 | Y16: 0 | Z16: =Water!#REF! -> #REF! | AA16: 0 | AB16: 0 | AC16: 880 | AD16: =Water!#REF! -> #REF! | AE16: =Water!#REF! -> #REF! | AF16: =Water!#REF! -> #REF! | AG16: =Gas!B18 -> 8424018 | AH16: =Gas!C18 -> 1503.08 | AI16: =Gas!#REF! -> #REF! | AJ16: =Gas!J18 -> 354.9 | AK16: =Gas!#REF! -> #REF! | AL16: =Gas!#REF! -> #REF! | AM16: =Gas!#REF! -> #REF! | AN16: =Gas!#REF! -> #REF! | AO16: =Gas!#REF! -> #REF! | AP16: =Gas!#REF! -> #REF! | AQ16: =Gas!#REF! -> #REF! | AR16: =Gas!#REF! -> #REF! | AS16: =Gas!#REF! -> #REF! | AT16: =Elect!BR17 -> 136 | AU16: =Elect!BP17 -> 162 | AX16: 50.45045 | AY16: 25.339367 | AZ16: 8835.4834 | BA16: 13.266492 | BB16: 6.6632605 | BC16: =Elect!BQ17 -> 563728 | BD16: =Elect!#REF! -> #REF! | BE16: =Elect!#REF! -> #REF! | BF16: =Elect!#REF! -> #REF! | BG16: =Elect!#REF! -> #REF! | BH16: 1.2162162 | BI16: 0.61085973 | BJ16: 5180.235 | BK16: 7.7781306 | BL16: 3.9066629 | BM16: =Water!U18 -> 1.3197458 | BN16: =Water!W18 -> #DIV/0! | BO16: =Water!X18 -> 1245.84 | BP16: =Water!Y18 -> 5.2789831 | BQ16: =Water!Z18 -> #DIV/0!
A17: 13 | B17: 31200 | C17: =Elect!J18 -> 8015 | D17: 0 | E17: =Elect!M18 -> 2095 | F17: 20 | G17: =Elect!O18 -> 1586 | H17: 812 | I17: =Water!C19 -> 76.753333 | J17: 0 | K17: =Water!E19 -> 98.213333 | L17: 0 | M17: =Water!#REF! -> #REF! | N17: =Water!#REF! -> #REF! | O17: 822 | P17: =Water!H19 -> 327.85467 | Q17: 123 | R17: =Water!O19 -> 0 | S17: 7 | T17: =Water!#REF! -> #REF! | U17: 163 | V17: =Water!#REF! -> #REF! | W17: 692 | X17: =Water!Q19 -> 190.15571 | Y17: 0 | Z17: =Water!#REF! -> #REF! | AA17: 0 | AB17: 0 | AC17: 460 | AD17: =Water!#REF! -> #REF! | AE17: =Water!#REF! -> #REF! | AF17: =Water!#REF! -> #REF! | AG17: =Gas!B19 -> 8425179.8 | AH17: =Gas!C19 -> 1231.508 | AI17: =Gas!#REF! -> #REF! | AJ17: =Gas!J19 -> 357.67333 | AK17: =Gas!#REF! -> #REF! | AL17: =Gas!#REF! -> #REF! | AM17: =Gas!#REF! -> #REF! | AN17: =Gas!#REF! -> #REF! | AO17: =Gas!#REF! -> #REF! | AP17: =Gas!#REF! -> #REF! | AQ17: =Gas!#REF! -> #REF! | AR17: =Gas!#REF! -> #REF! | AS17: =Gas!#REF! -> #REF! | AT17: =Elect!BR18 -> 146 | AU17: =Elect!BP18 -> 149 | AX17: 46.567164 | AY17: 23.214286 | AZ17: 8299.2754 | BA17: 12.386978 | BB17: 6.1750561 | BC17: =Elect!BQ18 -> 563874 | BD17: =Elect!#REF! -> #REF! | BE17: =Elect!#REF! -> #REF! | BF17: =Elect!#REF! -> #REF! | BG17: =Elect!#REF! -> #REF! | BH17: 1.0850746 | BI17: 0.54092262 | BJ17: 4637.6525 | BK17: 6.9218694 | BL17: 3.4506343 | BM17: =Water!U19 -> 1.4010883 | BN17: =Water!W19 -> #DIV/0! | BO17: =Water!X19 -> 1311.4187 | BP17: =Water!Y19 -> 5.6043533 | BQ17: =Water!Z19 -> #DIV/0!
A18: 14 | B18: 33600 | C18: =Elect!J19 -> 4600 | D18: 0 | E18: =Elect!M19 -> 2075 | F18: 30 | G18: =Elect!O19 -> 1575 | H18: 810 | I18: =Water!C20 -> 80.426667 | J18: 0 | K18: =Water!E20 -> 100.72667 | L18: 0 | M18: =Water!#REF! -> #REF! | N18: =Water!#REF! -> #REF! | O18: 943 | P18: =Water!H20 -> 318.26533 | Q18: 118 | R18: =Water!O20 -> 0 | S18: 18 | T18: =Water!#REF! -> #REF! | U18: 152 | V18: =Water!#REF! -> #REF! | W18: 708 | X18: =Water!Q20 -> 184.59389 | Y18: 0 | Z18: =Water!#REF! -> #REF! | AA18: 0 | AB18: 0 | AC18: 490 | AD18: =Water!#REF! -> #REF! | AE18: =Water!#REF! -> #REF! | AF18: =Water!#REF! -> #REF! | AG18: =Gas!B20 -> 8426453.7 | AH18: =Gas!C20 -> 1350.3794 | AI18: =Gas!#REF! -> #REF! | AJ18: =Gas!J20 -> 353.71143 | AK18: =Gas!#REF! -> #REF! | AL18: =Gas!#REF! -> #REF! | AM18: =Gas!#REF! -> #REF! | AN18: =Gas!#REF! -> #REF! | AO18: =Gas!#REF! -> #REF! | AP18: =Gas!#REF! -> #REF! | AQ18: =Gas!#REF! -> #REF! | AR18: =Gas!#REF! -> #REF! | AS18: =Gas!#REF! -> #REF! | AT18: =Elect!BR19 -> 128 | AU18: =Elect!BP19 -> 141 | AX18: 47.795164 | AY18: 24.207493 | AZ18: 8835.4834 | BA18: 12.568255 | BB18: 6.3656221 | BC18: =Elect!BQ6 -> 562121 | BD18: =Elect!#REF! -> #REF! | BE18: =Elect!#REF! -> #REF! | BF18: =Elect!#REF! -> #REF! | BG18: =Elect!#REF! -> #REF! | BH18: 1.1024182 | BI18: 0.55835735 | BJ18: 4626.2297 | BK18: 6.5806966 | BL18: 3.3330185 | BM18: =Water!U20 -> 1.3601083 | BN18: =Water!W20 -> #DIV/0! | BO18: =Water!X20 -> 1273.0613 | BP18: =Water!Y20 -> 5.440433 | BQ18: =Water!Z20 -> #DIV/0!
A19: 15 | B19: 31200 | C19: =Elect!J20 -> 6393 | D19: 0 | E19: =Elect!M20 -> 2024 | F19: 20 | G19: =Elect!O20 -> 1609 | H19: 841 | I19: =Water!C21 -> 80.426667 | J19: 0 | K19: =Water!E21 -> 100.72667 | L19: 0 | M19: =Water!#REF! -> #REF! | N19: =Water!#REF! -> #REF! | O19: 947 | P19: =Water!H21 -> 318.26533 | Q19: 131 | R19: =Water!O21 -> 0 | S19: 23 | T19: =Water!#REF! -> #REF! | U19: 166 | V19: =Water!#REF! -> #REF! | W19: 787 | X19: =Water!Q21 -> 184.59389 | Y19: 0 | Z19: =Water!#REF! -> #REF! | AA19: 0 | AB19: 0 | AC19: 730 | AD19: =Water!#REF! -> #REF! | AE19: =Water!#REF! -> #REF! | AF19: =Water!#REF! -> #REF! | AG19: =Gas!B21 -> 8427727.7 | AH19: =Gas!C21 -> 1350.3794 | AI19: =Gas!#REF! -> #REF! | AJ19: =Gas!J21 -> 353.71143 | AK19: =Gas!#REF! -> #REF! | AL19: =Gas!#REF! -> #REF! | AM19: =Gas!#REF! -> #REF! | AN19: =Gas!#REF! -> #REF! | AO19: =Gas!#REF! -> #REF! | AP19: =Gas!#REF! -> #REF! | AQ19: =Gas!#REF! -> #REF! | AR19: =Gas!#REF! -> #REF! | AS19: =Gas!#REF! -> #REF! | AT19: =Elect!BR20 -> 128 | AU19: =Elect!BP20 -> 141 | AX19: 41.6 | AY19: 20.995962 | AZ19: 8299.2754 | BA19: 11.065701 | BB19: 5.5849767 | BC19: =Elect!BQ20 -> 564130 | BD19: =Elect!#REF! -> #REF! | BE19: =Elect!#REF! -> #REF! | BF19: =Elect!#REF! -> #REF! | BG19: =Elect!#REF! -> #REF! | BH19: 1.1506667 | BI19: 0.58114478 | BJ19: 4803.283 | BK19: 6.4043773 | BL19: 3.234534 | BM19: =Water!U21 -> 1.3601083 | BN19: =Water!W21 -> #DIV/0! | BO19: =Water!X21 -> 1273.0613 | BP19: =Water!Y21 -> 5.440433 | BQ19: =Water!Z21 -> #DIV/0!
A20: 16 | B20: 36000 | C20: =Elect!J21 -> 6311 | D20: 0 | E20: =Elect!M21 -> 2045 | F20: 20 | G20: =Elect!O21 -> 1607 | H20: 932 | I20: =Water!C22 -> 80.426667 | J20: 0 | K20: =Water!E22 -> 100.72667 | L20: 0 | M20: =Water!#REF! -> #REF! | N20: =Water!#REF! -> #REF! | O20: 998 | P20: =Water!H22 -> 318.26533 | Q20: 136 | R20: =Water!O22 -> 0 | S20: 22 | T20: =Water!#REF! -> #REF! | U20: 162 | V20: =Water!#REF! -> #REF! | W20: 703 | X20: =Water!Q22 -> 184.59389 | Y20: 0 | Z20: =Water!#REF! -> #REF! | AA20: 0 | AB20: 0 | AC20: 600 | AD20: =Water!#REF! -> #REF! | AE20: =Water!#REF! -> #REF! | AF20: =Water!#REF! -> #REF! | AG20: =Gas!B22 -> 8429001.6 | AH20: =Gas!C22 -> 1350.3794 | AI20: =Gas!#REF! -> #REF! | AJ20: =Gas!J22 -> 353.71143 | AK20: =Gas!#REF! -> #REF! | AL20: =Gas!#REF! -> #REF! | AM20: =Gas!#REF! -> #REF! | AN20: =Gas!#REF! -> #REF! | AO20: =Gas!#REF! -> #REF! | AP20: =Gas!#REF! -> #REF! | AQ20: =Gas!#REF! -> #REF! | AR20: =Gas!#REF! -> #REF! | AS20: =Gas!#REF! -> #REF! | AT20: =Elect!BR21 -> 124 | AU20: =Elect!BP21 -> 139 | AX20: 48 | AY20: 24.22611 | AZ20: 9371.6914 | BA20: 12.495589 | BB20: 6.3066564 | BC20: =Elect!BQ21 -> 564254 | BD20: =Elect!#REF! -> #REF! | BE20: =Elect!#REF! -> #REF! | BF20: =Elect!#REF! -> #REF! | BG20: =Elect!#REF! -> #REF! | BH20: 1.1626667 | BI20: 0.58720539 | BJ20: 5323.0199 | BK20: 7.0973598 | BL20: 3.5845252 | BM20: =Water!U22 -> 1.3718333 | BN20: =Water!W22 -> #DIV/0! | BO20: =Water!X22 -> 1273.0613 | BP20: =Water!Y22 -> 5.4873333 | BQ20: =Water!Z22 -> #DIV/0!
A21: 17 | B21: 33600 | C21: =Elect!J22 -> 6212 | D21: 0 | E21: =Elect!M22 -> 1978 | F21: 20 | G21: =Elect!O22 -> 1861 | H21: 972 | I21: =Water!C23 -> 140.16667 | J21: 0 | K21: =Water!E23 -> 179.60667 | L21: 0 | M21: =Water!#REF! -> #REF! | N21: =Water!#REF! -> #REF! | O21: 998 | P21: =Water!H23 -> 366.86933 | Q21: 136 | R21: =Water!O23 -> 0 | S21: 38 | T21: =Water!#REF! -> #REF! | U21: 137 | V21: =Water!#REF! -> #REF! | W21: 740 | X21: =Water!Q23 -> 212.78421 | Y21: 0 | Z21: =Water!#REF! -> #REF! | AA21: 0 | AB21: 0 | AC21: 690 | AD21: =Water!#REF! -> #REF! | AE21: =Water!#REF! -> #REF! | AF21: =Water!#REF! -> #REF! | AG21: =Gas!B23 -> 8431136 | AH21: =Gas!C23 -> 2262.4337 | AI21: =Gas!#REF! -> #REF! | AJ21: =Gas!J23 -> 386.89238 | AK21: =Gas!#REF! -> #REF! | AL21: =Gas!#REF! -> #REF! | AM21: =Gas!#REF! -> #REF! | AN21: =Gas!#REF! -> #REF! | AO21: =Gas!#REF! -> #REF! | AP21: =Gas!#REF! -> #REF! | AQ21: =Gas!#REF! -> #REF! | AR21: =Gas!#REF! -> #REF! | AS21: =Gas!#REF! -> #REF! | AT21: =Elect!BR22 -> 125 | AU21: =Elect!BP22 -> 144 | AX21: 44.385733 | AY21: 22.207535 | AZ21: 8835.4834 | BA21: 11.671709 | BB21: 5.8397115 | BC21: =Elect!#REF! -> #REF! | BD21: =Elect!#REF! -> #REF! | BE21: =Elect!#REF! -> #REF! | BF21: =Elect!#REF! -> #REF! | BG21: =Elect!#REF! -> #REF! | BH21: 1.1770145 | BI21: 0.58889623 | BJ21: 5551.4757 | BK21: 7.3335213 | BL21: 3.6691842 | BM21: =Water!U23 -> 1.6984691 | BN21: =Water!W23 -> #DIV/0! | BO21: =Water!X23 -> 1467.4773 | BP21: =Water!Y23 -> 6.7938765 | BQ21: =Water!Z23 -> #DIV/0!
A22: 18 | B22: 33600 | C22: =Elect!J23 -> 6311 | D22: 0 | E22: =Elect!M23 -> 1956 | F22: 20 | G22: =Elect!O23 -> 1529 | H22: 864 | I22: =Water!C24 -> 81.2 | J22: 0 | K22: =Water!E24 -> 110.2 | L22: 0 | M22: =Water!#REF! -> #REF! | N22: =Water!#REF! -> #REF! | O22: 1002 | P22: =Water!H24 -> 312.62 | Q22: 118 | R22: =Water!O24 -> 0 | S22: 21 | T22: =Water!#REF! -> #REF! | U22: 133 | V22: =Water!#REF! -> #REF! | W22: 769 | X22: =Water!Q24 -> 181.3196 | Y22: 0 | Z22: =Water!#REF! -> #REF! | AA22: 0 | AB22: 0 | AC22: 930 | AD22: =Water!#REF! -> #REF! | AE22: =Water!#REF! -> #REF! | AF22: =Water!#REF! -> #REF! | AG22: =Gas!B24 -> 8432635 | AH22: =Gas!C24 -> 1588.94 | AI22: =Gas!#REF! -> #REF! | AJ22: =Gas!J24 -> 397.8 | AK22: =Gas!#REF! -> #REF! | AL22: =Gas!#REF! -> #REF! | AM22: =Gas!#REF! -> #REF! | AN22: =Gas!#REF! -> #REF! | AO22: =Gas!#REF! -> #REF! | AP22: =Gas!#REF! -> #REF! | AQ22: =Gas!#REF! -> #REF! | AR22: =Gas!#REF! -> #REF! | AS22: =Gas!#REF! -> #REF! | AT22: =Elect!BR23 -> 152 | AU22: =Elect!BP23 -> 144 | AX22: 44.680851 | AY22: 22.459893 | AZ22: 8835.4834 | BA22: 11.749313 | BB22: 5.9060718 | BC22: =Elect!BQ23 -> 564531 | BD22: =Elect!#REF! -> #REF! | BE22: =Elect!#REF! -> #REF! | BF22: =Elect!#REF! -> #REF! | BG22: =Elect!#REF! -> #REF! | BH22: 1.1236702 | BI22: 0.56483957 | BJ22: 4934.645 | BK22: 6.562028 | BL22: 3.2985595 | BM22: =Water!U24 -> 1.871976 | BN22: =Water!W24 -> #DIV/0! | BO22: =Water!X24 -> 1250.48 | BP22: =Water!Y24 -> 7.4879042 | BQ22: =Water!Z24 -> #DIV/0!
A23: 19 | B23: 33600 | C23: =Elect!J24 -> 6667 | D23: 0 | E23: =Elect!M24 -> 2037 | F23: 30 | G23: =Elect!O24 -> 1588 | H23: 894 | I23: =Water!C25 -> 81.2 | J23: 0 | K23: =Water!E25 -> 98.6 | L23: 0 | M23: =Water!#REF! -> #REF! | N23: =Water!#REF! -> #REF! | O23: 944 | P23: =Water!H25 -> 302.18 | Q23: 110 | R23: =Water!O25 -> 0 | S23: 14 | T23: =Water!#REF! -> #REF! | U23: 155 | V23: =Water!#REF! -> #REF! | W23: 721 | X23: =Water!Q25 -> 175.2644 | Y23: 0 | Z23: =Water!#REF! -> #REF! | AA23: 0 | AB23: 0 | AC23: 660 | AD23: =Water!#REF! -> #REF! | AE23: =Water!#REF! -> #REF! | AF23: =Water!#REF! -> #REF! | AG23: =Gas!B25 -> 8434106 | AH23: =Gas!C25 -> 1559.26 | AI23: =Gas!#REF! -> #REF! | AJ23: =Gas!J25 -> 296.4 | AK23: =Gas!#REF! -> #REF! | AL23: =Gas!#REF! -> #REF! | AM23: =Gas!#REF! -> #REF! | AN23: =Gas!#REF! -> #REF! | AO23: =Gas!#REF! -> #REF! | AP23: =Gas!#REF! -> #REF! | AQ23: =Gas!#REF! -> #REF! | AR23: =Gas!#REF! -> #REF! | AS23: =Gas!#REF! -> #REF! | AT23: =Elect!BR24 -> 130 | AU23: =Elect!BP24 -> 154 | AX23: 44.8 | AY23: 22.44489 | AZ23: 8835.4834 | BA23: 11.780645 | BB23: 5.9021265 | BC23: =Elect!BQ24 -> 564661 | BD23: =Elect!#REF! -> #REF! | BE23: =Elect!#REF! -> #REF! | BF23: =Elect!#REF! -> #REF! | BG23: =Elect!#REF! -> #REF! | BH23: 1.1346667 | BI23: 0.56847027 | BJ23: 5105.9869 | BK23: 6.8079825 | BL23: 3.4108129 | BM23: =Water!U25 -> 1.5820942 | BN23: =Water!W25 -> #DIV/0! | BO23: =Water!X25 -> 1208.72 | BP23: =Water!Y25 -> 6.328377 | BQ23: =Water!Z25 -> #DIV/0!
A24: 20 | B24: 33600 | C24: =Elect!J25 -> 6132 | D24: 0 | E24: =Elect!M25 -> 1978 | F24: 20 | G24: =Elect!O25 -> 1569 | H24: 944 | I24: =Water!C26 -> 98.6 | J24: 0 | K24: =Water!E26 -> 127.6 | L24: 0 | M24: =Water!#REF! -> #REF! | N24: =Water!#REF! -> #REF! | O24: 1000 | P24: =Water!H26 -> 354.96 | Q24: 138 | R24: =Water!O26 -> 0 | S24: 15 | T24: =Water!#REF! -> #REF! | U24: 165 | V24: =Water!#REF! -> #REF! | W24: 778 | X24: =Water!Q26 -> 205.8768 | Y24: 0 | Z24: =Water!#REF! -> #REF! | AA24: 0 | AB24: 0 | AC24: 560 | AD24: =Water!#REF! -> #REF! | AE24: =Water!#REF! -> #REF! | AF24: =Water!#REF! -> #REF! | AG24: =Gas!B26 -> 8435595.7 | AH24: =Gas!C26 -> 1579.0467 | AI24: =Gas!#REF! -> #REF! | AJ24: =Gas!J26 -> 331.5 | AK24: =Gas!#REF! -> #REF! | AL24: =Gas!#REF! -> #REF! | AM24: =Gas!#REF! -> #REF! | AN24: =Gas!#REF! -> #REF! | AO24: =Gas!#REF! -> #REF! | AP24: =Gas!#REF! -> #REF! | AQ24: =Gas!#REF! -> #REF! | AR24: =Gas!#REF! -> #REF! | AS24: =Gas!#REF! -> #REF! | AT24: =Elect!BR25 -> 129 | AU24: =Elect!BP25 -> 154 | AX24: 42.857143 | AY24: 21.649485 | AZ24: 8835.4834 | BA24: 11.269749 | BB24: 5.6929661 | BC24: =Elect!BQ25 -> 564790 | BD24: =Elect!#REF! -> #REF! | BE24: =Elect!#REF! -> #REF! | BF24: =Elect!#REF! -> #REF! | BG24: =Elect!#REF! -> #REF! | BH24: 1.1683673 | BI24: 0.59020619 | BJ24: 5391.5566 | BK24: 6.8769855 | BL24: 3.4739411 | BM24: =Water!U26 -> 1.5234335 | BN24: =Water!W26 -> #DIV/0! | BO24: =Water!X26 -> 1419.84 | BP24: =Water!Y26 -> 6.0937339 | BQ24: =Water!Z26 -> #DIV/0!
A25: 21 | B25: 36000 | C25: =Elect!J26 -> 6439 | D25: 0 | E25: =Elect!M26 -> 2117 | F25: 20 | G25: =Elect!O26 -> 2968 | H25: 916 | I25: =Water!C27 -> 81.2 | J25: 0 | K25: =Water!E27 -> 104.4 | L25: 0 | M25: =Water!#REF! -> #REF! | N25: =Water!#REF! -> #REF! | O25: 998 | P25: =Water!H27 -> 307.4 | Q25: 186 | R25: =Water!O27 -> 0 | S25: 43 | T25: =Water!#REF! -> #REF! | U25: 176 | V25: =Water!#REF! -> #REF! | W25: 773 | X25: =Water!Q27 -> 178.292 | Y25: 0 | Z25: =Water!#REF! -> #REF! | AA25: 0 | AB25: 0 | AC25: 950 | AD25: =Water!#REF! -> #REF! | AE25: =Water!#REF! -> #REF! | AF25: =Water!#REF! -> #REF! | AG25: =Gas!B27 -> 8437080.7 | AH25: =Gas!C27 -> 1574.1 | AI25: =Gas!#REF! -> #REF! | AJ25: =Gas!J27 -> 300.3 | AK25: =Gas!#REF! -> #REF! | AL25: =Gas!#REF! -> #REF! | AM25: =Gas!#REF! -> #REF! | AN25: =Gas!#REF! -> #REF! | AO25: =Gas!#REF! -> #REF! | AP25: =Gas!#REF! -> #REF! | AQ25: =Gas!#REF! -> #REF! | AR25: =Gas!#REF! -> #REF! | AS25: =Gas!#REF! -> #REF! | AT25: =Elect!BR26 -> 129 | AU25: =Elect!BP26 -> 138 | AX25: 43.956044 | AY25: 22.222222 | AZ25: 9371.6914 | BA25: 11.442847 | BB25: 5.7849947 | BC25: =Elect!BQ26 -> 564919 | BD25: =Elect!#REF! -> #REF! | BE25: =Elect!#REF! -> #REF! | BF25: =Elect!#REF! -> #REF! | BG25: =Elect!#REF! -> #REF! | BH25: 1.0586081 | BI25: 0.53518519 | BJ25: 5231.6376 | BK25: 6.3878358 | BL25: 3.2294059 | BM25: =Water!U27 -> 1.5217822 | BN25: =Water!W27 -> #DIV/0! | BO25: =Water!X27 -> 1229.6 | BP25: =Water!Y27 -> 6.0871287 | BQ25: =Water!Z27 -> #DIV/0!
A26: 22 | B26: 33600 | C26: =Elect!J27 -> 6321 | D26: 0 | E26: =Elect!M27 -> 1935 | F26: 20 | G26: =Elect!O27 -> 2969 | H26: 931 | I26: =Water!C28 -> 86.42 | J26: 0 | K26: =Water!E28 -> 110.78 | L26: 0 | M26: =Water!#REF! -> #REF! | N26: =Water!#REF! -> #REF! | O26: 969 | P26: =Water!H28 -> 321.146 | Q26: 151 | R26: =Water!O28 -> 0 | S26: 29 | T26: =Water!#REF! -> #REF! | U26: 157 | V26: =Water!#REF! -> #REF! | W26: 697 | X26: =Water!Q28 -> 186.26468 | Y26: 0 | Z26: =Water!#REF! -> #REF! | AA26: 0 | AB26: 0 | AC26: 700 | AD26: =Water!#REF! -> #REF! | AE26: =Water!#REF! -> #REF! | AF26: =Water!#REF! -> #REF! | AG26: =Gas!B28 -> 8438565.7 | AH26: =Gas!C28 -> 1574.1 | AI26: =Gas!#REF! -> #REF! | AJ26: =Gas!J28 -> 321.75 | AK26: =Gas!#REF! -> #REF! | AL26: =Gas!#REF! -> #REF! | AM26: =Gas!#REF! -> #REF! | AN26: =Gas!#REF! -> #REF! | AO26: =Gas!#REF! -> #REF! | AP26: =Gas!#REF! -> #REF! | AQ26: =Gas!#REF! -> #REF! | AR26: =Gas!#REF! -> #REF! | AS26: =Gas!#REF! -> #REF! | AT26: =Elect!BR27 -> 128 | AU26: =Elect!BP27 -> 129 | AX26: 39.952438 | AY26: 20.253165 | AZ26: 8835.4834 | BA26: 10.505926 | BB26: 5.3257887 | BC26: =Elect!BQ27 -> 565047 | BD26: =Elect!#REF! -> #REF! | BE26: =Elect!#REF! -> #REF! | BF26: =Elect!#REF! -> #REF! | BG26: =Elect!#REF! -> #REF! | BH26: 1.0903686 | BI26: 0.55274262 | BJ26: 5317.3085 | BK26: 6.3226022 | BL26: 3.2051287 | BM26: =Water!U28 -> 1.5365837 | BN26: =Water!W28 -> #DIV/0! | BO26: =Water!X28 -> 1284.584 | BP26: =Water!Y28 -> 6.1463349 | BQ26: =Water!Z28 -> #DIV/0!
A27: 23 | B27: 36000 | C27: =Elect!J28 -> 6483 | D27: 0 | E27: =Elect!M28 -> 2061 | F27: 30 | G27: =Elect!O28 -> 3079 | H27: 1009 | I27: =Water!C29 -> 110.78 | J27: 0 | K27: =Water!E29 -> 132.82 | L27: 0 | M27: =Water!#REF! -> #REF! | N27: =Water!#REF! -> #REF! | O27: 902 | P27: =Water!H29 -> 356.294 | Q27: 131 | R27: =Water!O29 -> 0 | S27: 6 | T27: =Water!#REF! -> #REF! | U27: 167 | V27: =Water!#REF! -> #REF! | W27: 748 | X27: =Water!Q29 -> 206.65052 | Y27: 0 | Z27: =Water!#REF! -> #REF! | AA27: 0 | AB27: 0 | AC27: 690 | AD27: =Water!#REF! -> #REF! | AE27: =Water!#REF! -> #REF! | AF27: =Water!#REF! -> #REF! | AG27: =Gas!B29 -> 8440031 | AH27: =Gas!C29 -> 1553.2533 | AI27: =Gas!#REF! -> #REF! | AJ27: =Gas!J29 -> 411.45 | AK27: =Gas!#REF! -> #REF! | AL27: =Gas!#REF! -> #REF! | AM27: =Gas!#REF! -> #REF! | AN27: =Gas!#REF! -> #REF! | AO27: =Gas!#REF! -> #REF! | AP27: =Gas!#REF! -> #REF! | AQ27: =Gas!#REF! -> #REF! | AR27: =Gas!#REF! -> #REF! | AS27: =Gas!#REF! -> #REF! | AT27: =Elect!BR28 -> 138 | AU27: =Elect!BP28 -> 129 | AX27: 42.755344 | AY27: 21.543986 | AZ27: 9371.6914 | BA27: 11.130275 | BB27: 5.6084329 | BC27: =Elect!BQ28 -> 565185 | BD27: =Elect!#REF! -> #REF! | BE27: =Elect!#REF! -> #REF! | BF27: =Elect!#REF! -> #REF! | BG27: =Elect!#REF! -> #REF! | BH27: 1.0712589 | BI27: 0.53979653 | BJ27: 5762.7973 | BK27: 6.8441773 | BL27: 3.4487117 | BM27: =Water!U29 -> 1.555869 | BN27: =Water!W29 -> #DIV/0! | BO27: =Water!X29 -> 1425.176 | BP27: =Water!Y29 -> 6.223476 | BQ27: =Water!Z29 -> #DIV/0!
A28: 24 | B28: 33600 | C28: =Elect!J29 -> 5914 | D28: 0 | E28: =Elect!M29 -> 2064 | F28: 20 | G28: =Elect!O29 -> 2254 | H28: 891 | I28: =Water!C30 -> 98.6 | J28: 0 | K28: =Water!E30 -> 121.8 | L28: 0 | M28: =Water!#REF! -> #REF! | N28: =Water!#REF! -> #REF! | O28: 818 | P28: =Water!H30 -> 346.84 | Q28: 221 | R28: =Water!O30 -> 0 | S28: 93 | T28: =Water!#REF! -> #REF! | U28: 191 | V28: =Water!#REF! -> #REF! | W28: 827 | X28: =Water!Q30 -> 201.1672 | Y28: 0 | Z28: =Water!#REF! -> #REF! | AA28: 0 | AB28: 0 | AC28: 470 | AD28: =Water!#REF! -> #REF! | AE28: =Water!#REF! -> #REF! | AF28: =Water!#REF! -> #REF! | AG28: =Gas!B30 -> 8441593 | AH28: =Gas!C30 -> 1655.72 | AI28: =Gas!#REF! -> #REF! | AJ28: =Gas!J30 -> 351 | AK28: =Gas!#REF! -> #REF! | AL28: =Gas!#REF! -> #REF! | AM28: =Gas!#REF! -> #REF! | AN28: =Gas!#REF! -> #REF! | AO28: =Gas!#REF! -> #REF! | AP28: =Gas!#REF! -> #REF! | AQ28: =Gas!#REF! -> #REF! | AR28: =Gas!#REF! -> #REF! | AS28: =Gas!#REF! -> #REF! | AT28: =Elect!BR29 -> 154 | AU28: =Elect!BP29 -> 127 | AX28: 39.904988 | AY28: 20.289855 | AZ28: 8835.4834 | BA28: 10.493448 | BB28: 5.3354369 | BC28: =Elect!BQ29 -> 565339 | BD28: =Elect!#REF! -> #REF! | BE28: =Elect!#REF! -> #REF! | BF28: =Elect!#REF! -> #REF! | BG28: =Elect!#REF! -> #REF! | BH28: 1.1104513 | BI28: 0.56461353 | BJ28: 5088.8527 | BK28: 6.043768 | BL28: 3.0729787 | BM28: =Water!U30 -> 1.6132093 | BN28: =Water!W30 -> #DIV/0! | BO28: =Water!X30 -> 1387.36 | BP28: =Water!Y30 -> 6.4528372 | BQ28: =Water!Z30 -> #DIV/0!
A29: 25 | B29: 33600 | C29: =Elect!J30 -> 5790 | D29: 0 | E29: =Elect!M30 -> 1785 | F29: 20 | G29: =Elect!O30 -> 1996 | H29: 1008 | I29: =Water!C31 -> 110.2 | J29: 0 | K29: =Water!E31 -> 121.8 | L29: 0 | M29: =Water!#REF! -> #REF! | N29: =Water!#REF! -> #REF! | O29: 1290 | P29: =Water!H31 -> 352.64 | Q29: 34 | R29: =Water!O31 -> 0 | S29: 34 | T29: =Water!#REF! -> #REF! | U29: 55 | V29: =Water!#REF! -> #REF! | W29: 681 | X29: =Water!Q31 -> 204.5312 | Y29: 0 | Z29: =Water!#REF! -> #REF! | AA29: 0 | AB29: 0 | AC29: 1170 | AD29: =Water!#REF! -> #REF! | AE29: =Water!#REF! -> #REF! | AF29: =Water!#REF! -> #REF! | AG29: =Gas!B31 -> 8443788 | AH29: =Gas!C31 -> 2326.7 | AI29: =Gas!#REF! -> #REF! | AJ29: =Gas!J31 -> 335.4 | AK29: =Gas!#REF! -> #REF! | AL29: =Gas!#REF! -> #REF! | AM29: =Gas!#REF! -> #REF! | AN29: =Gas!#REF! -> #REF! | AO29: =Gas!#REF! -> #REF! | AP29: =Gas!#REF! -> #REF! | AQ29: =Gas!#REF! -> #REF! | AR29: =Gas!#REF! -> #REF! | AS29: =Gas!#REF! -> #REF! | AT29: =Elect!BR30 -> 122 | AU29: =Elect!BP30 -> 101 | AX29: 39.763314 | AY29: 20.20445 | AZ29: 8835.4834 | BA29: 10.456193 | BB29: 5.3129786 | BC29: =Elect!BQ30 -> 565461 | BD29: =Elect!#REF! -> #REF! | BE29: =Elect!#REF! -> #REF! | BF29: =Elect!#REF! -> #REF! | BG29: =Elect!#REF! -> #REF! | BH29: 1.0059172 | BI29: 0.51112447 | BJ29: 5757.0859 | BK29: 6.8131194 | BL29: 3.4618676 | BM29: =Water!U31 -> 1.5956561 | BN29: =Water!W31 -> #DIV/0! | BO29: =Water!X31 -> 1410.56 | BP29: =Water!Y31 -> 6.3826244 | BQ29: =Water!Z31 -> #DIV/0!
A30: 26 | B30: 31200 | C30: =Elect!J31 -> 5700 | D30: 0 | E30: =Elect!M31 -> 2247 | F30: 20 | G30: =Elect!O31 -> 2461 | H30: 760 | I30: =Water!C32 -> 81.2 | J30: 0 | K30: =Water!E32 -> 127.6 | L30: 0 | M30: =Water!#REF! -> #REF! | N30: =Water!#REF! -> #REF! | O30: 1004 | P30: =Water!H32 -> 328.86 | Q30: 131 | R30: =Water!O32 -> 0 | S30: 33 | T30: =Water!#REF! -> #REF! | U30: 145 | V30: =Water!#REF! -> #REF! | W30: 916 | X30: =Water!Q32 -> 190.7388 | Y30: 0 | Z30: =Water!#REF! -> #REF! | AA30: 0 | AB30: 0 | AC30: 810 | AD30: =Water!#REF! -> #REF! | AE30: =Water!#REF! -> #REF! | AF30: =Water!#REF! -> #REF! | AG30: =Gas!B32 -> 8444914 | AH30: =Gas!C32 -> 1193.56 | AI30: =Gas!#REF! -> #REF! | AJ30: =Gas!J32 -> 345.8 | AK30: =Gas!#REF! -> #REF! | AL30: =Gas!#REF! -> #REF! | AM30: =Gas!#REF! -> #REF! | AN30: =Gas!#REF! -> #REF! | AO30: =Gas!#REF! -> #REF! | AP30: =Gas!#REF! -> #REF! | AQ30: =Gas!#REF! -> #REF! | AR30: =Gas!#REF! -> #REF! | AS30: =Gas!#REF! -> #REF! | AT30: =Elect!BR31 -> 188 | AU30: =Elect!BP31 -> 156 | AX30: 37.275986 | AY30: 18.989653 | AZ30: 8299.2754 | BA30: 9.9155023 | BB30: 5.0512936 | BC30: =Elect!BQ31 -> 565649 | BD30: =Elect!#REF! -> #REF! | BE30: =Elect!#REF! -> #REF! | BF30: =Elect!#REF! -> #REF! | BG30: =Elect!#REF! -> #REF! | BH30: 1.1063321 | BI30: 0.56360316 | BJ30: 4340.66 | BK30: 5.1859737 | BL30: 2.6419111 | BM30: =Water!U32 -> 1.4236364 | BN30: =Water!W32 -> #DIV/0! | BO30: =Water!X32 -> 1315.44 | BP30: =Water!Y32 -> 5.6945455 | BQ30: =Water!Z32 -> #DIV/0!
A31: 27 | B31: 36000 | C31: =Elect!J32 -> 7994 | D31: 0 | E31: =Elect!M32 -> 2280 | F31: 30 | G31: =Elect!O32 -> 1918 | H31: 1010 | I31: =Water!C33 -> 98.6 | J31: 0 | K31: =Water!E33 -> 121.8 | L31: 0 | M31: =Water!#REF! -> #REF! | N31: =Water!#REF! -> #REF! | O31: 1014 | P31: =Water!H33 -> 328.28 | Q31: 151 | R31: =Water!O33 -> 0 | S31: 30 | T31: =Water!#REF! -> #REF! | U31: 139 | V31: =Water!#REF! -> #REF! | W31: 761 | X31: =Water!Q33 -> 190.4024 | Y31: 0 | Z31: =Water!#REF! -> #REF! | AA31: 0 | AB31: 0 | AC31: 930 | AD31: =Water!#REF! -> #REF! | AE31: =Water!#REF! -> #REF! | AF31: =Water!#REF! -> #REF! | AG31: =Gas!B33 -> 8446559 | AH31: =Gas!C33 -> 1743.7 | AI31: =Gas!#REF! -> #REF! | AJ31: =Gas!J33 -> 305.5 | AK31: =Gas!#REF! -> #REF! | AL31: =Gas!#REF! -> #REF! | AM31: =Gas!#REF! -> #REF! | AN31: =Gas!#REF! -> #REF! | AO31: =Gas!#REF! -> #REF! | AP31: =Gas!#REF! -> #REF! | AQ31: =Gas!#REF! -> #REF! | AR31: =Gas!#REF! -> #REF! | AS31: =Gas!#REF! -> #REF! | AT31: =Elect!BR32 -> 163 | AU31: =Elect!BP32 -> 134 | AX31: 44.063647 | AY31: 22.346369 | AZ31: 9371.6914 | BA31: 11.470859 | BB31: 5.8173131 | BC31: =Elect!BQ32 -> 565812 | BD31: =Elect!#REF! -> #REF! | BE31: =Elect!#REF! -> #REF! | BF31: =Elect!#REF! -> #REF! | BG31: =Elect!#REF! -> #REF! | BH31: 1.1640147 | BI31: 0.59031657 | BJ31: 5768.5087 | BK31: 7.0605981 | BL31: 3.5807006 | BM31: =Water!U33 -> 1.6414 | BN31: =Water!W33 -> #DIV/0! | BO31: =Water!X33 -> 1313.12 | BP31: =Water!Y33 -> 6.5656 | BQ31: =Water!Z33 -> #DIV/0!
A32: 28 | B32: 33600 | C32: =Elect!J33 -> 6464.6667 | D32: 0 | E32: =Elect!M33 -> 2121 | F32: 20 | G32: =Elect!O33 -> 2051 | H32: 1008 | I32: =Water!C34 -> 87 | J32: 0 | K32: =Water!E34 -> 124.7 | L32: 1 | M32: =Water!#REF! -> #REF! | N32: =Water!#REF! -> #REF! | O32: 1013 | P32: =Water!H34 -> 327.7 | Q32: 142 | R32: =Water!O34 -> 0 | S32: 13 | T32: =Water!#REF! -> #REF! | U32: 155 | V32: =Water!#REF! -> #REF! | W32: 825 | X32: =Water!Q34 -> 190.066 | Y32: 1 | Z32: =Water!#REF! -> #REF! | AA32: 0 | AB32: 0 | AC32: 650 | AD32: =Water!#REF! -> #REF! | AE32: =Water!#REF! -> #REF! | AF32: =Water!#REF! -> #REF! | AG32: =Gas!B34 -> 8447858 | AH32: =Gas!C34 -> 1376.94 | AI32: =Gas!#REF! -> #REF! | AJ32: =Gas!J34 -> 332.36667 | AK32: =Gas!#REF! -> #REF! | AL32: =Gas!#REF! -> #REF! | AM32: =Gas!#REF! -> #REF! | AN32: =Gas!#REF! -> #REF! | AO32: =Gas!#REF! -> #REF! | AP32: =Gas!#REF! -> #REF! | AQ32: =Gas!#REF! -> #REF! | AR32: =Gas!#REF! -> #REF! | AS32: =Gas!#REF! -> #REF! | AT32: =Elect!BR33 -> 152 | AU32: =Elect!BP33 -> 126 | AX32: 45.34413 | AY32: 22.687373 | AZ32: 8835.4834 | BA32: 11.923729 | BB32: 5.9658902 | BC32: =Elect!BQ33 -> 565964 | BD32: =Elect!#REF! -> #REF! | BE32: =Elect!#REF! -> #REF! | BF32: =Elect!#REF! -> #REF! | BG32: =Elect!#REF! -> #REF! | BH32: 1.2294197 | BI32: 0.61512492 | BJ32: 5757.0859 | BK32: 7.7693467 | BL32: 3.8872963 | BM32: =Water!U34 -> 1.3485597 | BN32: =Water!W34 -> #DIV/0! | BO32: =Water!X34 -> 1310.8 | BP32: =Water!Y34 -> 5.3942387 | BQ32: =Water!Z34 -> #DIV/0!
A33: MTD | B33: 931200 | C33: =Elect!J34 -> 5372.3333 | D33: 0 | E33: =Elect!M34 -> 2137 | F33: 600 | G33: =Elect!O34 -> 2044 | H33: 24543 | I33: =Water!C38 -> 2845.3833 | J33: 0 | K33: =Water!E39 -> 122.06422 | L33: 3 | M33: =Water!#REF! -> #REF! | N33: =Water!#REF! -> #REF! | O33: 1013 | P33: =Water!H38 -> 10279.968 | Q33: 109 | R33: =Water!O38 -> 0 | S33: 15 | T33: =Water!#REF! -> #REF! | U33: 147 | V33: =Water!#REF! -> #REF! | W33: 730 | X33: =Water!Q38 -> 5392.2677 | Y33: 3 | Z33: =Water!#REF! -> #REF! | AA33: 0 | AB33: 0 | AC33: 0 | AD33: =Water!#REF! -> #REF! | AE33: =Water!#REF! -> #REF! | AF33: =Water!#REF! -> #REF! | AG33: =Gas!B38 -> 0 | AH33: =Gas!C38 -> 47727.118 | AI33: =Gas!#REF! -> #REF! | AJ33: =Gas!J38 -> 10721.353 | AK33: =Gas!#REF! -> #REF! | AL33: =Gas!#REF! -> #REF! | AM33: =Gas!#REF! -> #REF! | AN33: =Gas!#REF! -> #REF! | AO33: =Gas!#REF! -> #REF! | AP33: =Gas!#REF! -> #REF! | AQ33: =Gas!#REF! -> #REF! | AR33: =Gas!#REF! -> #REF! | AS33: =Gas!#REF! -> #REF! | AT33: =Elect!BR34 -> 154 | AU33: =Elect!BP34 -> 132 | AX33: 45.411099 | AY33: 22.844806 | AZ33: 245248.7 | BA33: 11.959851 | BB33: 6.0166013 | BC33: =Elect!BQ34 -> 566118 | BD33: =Elect!#REF! -> #REF! | BE33: =Elect!#REF! -> #REF! | BF33: =Elect!#REF! -> #REF! | BG33: =Elect!#REF! -> #REF! | BH33: 1.1514679 | BI33: 0.57929342 | BJ33: 140121.3 | BK33: 6.8331854 | BL33: 3.4377159 | BM33: =Water!U38 -> 1.5759571 | BN33: =Water!W38 -> #DIV/0! | BO33: =Water!X38 -> 39809.653 | BP33: =Water!Y38 -> 6.1029669 | BQ33: =Water!Z38 -> #DIV/0!
A34: AVER. Act | B34: 33257.143 | C34: =Elect!J35 -> 6100.5556 | D34: 0 | E34: =Elect!M35 -> 2200.5 | F34: 21.428571 | G34: =Elect!O35 -> 2048.6667 | H34: 876.53571 | I34: =Water!C39 -> 94.846111 | J34: 0 | K34: =Water!E40 -> 0 | L34: 4 | M34: =Water!#REF! -> #REF! | N34: =Water!#REF! -> #REF! | O34: 1014 | P34: =Water!H39 -> 342.66561 | Q34: 138 | R34: =Water!O39 -> 0 | S34: 24 | T34: =Water!#REF! -> #REF! | U34: 145 | V34: =Water!#REF! -> #REF! | W34: 877 | X34: =Water!Q39 -> 179.74226 | Y34: 4 | Z34: =Water!#REF! -> #REF! | AA34: 0 | AB34: 0 | AC34: 0 | AD34: =Water!#REF! -> #REF! | AE34: =Water!#REF! -> #REF! | AF34: =Water!#REF! -> #REF! | AG34: =Gas!B39 -> 0 | AH34: =Gas!C39 -> 1590.9039 | AI34: =Gas!#REF! -> #REF! | AJ34: =Gas!J39 -> 357.37843 | AK34: =Gas!#REF! -> #REF! | AL34: =Gas!#REF! -> #REF! | AM34: =Gas!#REF! -> #REF! | AN34: =Gas!#REF! -> #REF! | AO34: =Gas!#REF! -> #REF! | AP34: =Gas!#REF! -> #REF! | AQ34: =Gas!#REF! -> #REF! | AR34: =Gas!#REF! -> #REF! | AS34: =Gas!#REF! -> #REF! | AT34: =Elect!BR35 -> 152.66667 | AU34: =Elect!BP35 -> 128 | AX34: 45.411099 | AY34: 22.844806 | AZ34: 8758.8823 | BA34: 11.959851 | BB34: 6.0166013 | BC34: =Elect!BQ35 -> 566270.67 | BD34: =Elect!#REF! -> #REF! | BE34: =Elect!#REF! -> #REF! | BF34: =Elect!#REF! -> #REF! | BG34: =Elect!#REF! -> #REF! | BH34: 1.1761372 | BI34: 0.60007377 | BJ34: 5004.3322 | BK34: 6.8331854 | BL34: 3.4377159 | BM34: =Water!U39 -> 1.5759571 | BN34: =Water!W39 -> #DIV/0! | BO34: =Water!X39 -> 1326.9884 | BP34: =Water!Y39 -> 6.1029669 | BQ34: =Water!Z39 -> #DIV/0!
A35: TOTAL Budget | B35: 1040026 | C35: =Elect!J5 -> 0 | D35: 0 | E35: =Elect!M5 -> 0 | F35: 0 | G35: =Elect!O5 -> 0 | H35: 0 | I35: =Water!C40 -> 0 | J35: 0 | K35: =Water!E41 -> 0 | L35: 5 | M35: =Water!#REF! -> #REF! | N35: =Water!#REF! -> #REF! | O35: 1010 | P35: =Water!H40 -> 0 | Q35: 148 | R35: =Water!O40 -> 0 | S35: 22 | T35: =Water!#REF! -> #REF! | U35: 151 | V35: =Water!#REF! -> #REF! | W35: 833 | X35: =Water!Q40 -> 0 | Y35: 5 | Z35: =Water!#REF! -> #REF! | AA35: 0 | AB35: 0 | AC35: 0 | AD35: =Water!#REF! -> #REF! | AE35: =Water!#REF! -> #REF! | AF35: =Water!#REF! -> #REF! | AG35: =Gas!#REF! -> #REF! | AH35: =Gas!#REF! -> #REF! | AI35: =Gas!#REF! -> #REF! | AJ35: =Gas!#REF! -> #REF! | AK35: =Gas!#REF! -> #REF! | AL35: =Gas!#REF! -> #REF! | AM35: =Gas!#REF! -> #REF! | AN35: =Gas!#REF! -> #REF! | ... AS35: =Gas!#REF! -> #REF! | AT35: =Elect!BR5 -> 0 | AU35: =Elect!BP5 -> 0 | AX35: 45.679286 | AY35: 23.305904 | AZ35: 264708.4 | BA35: 11.626335 | BB35: 5.9318409 | BC35: =Elect!BQ5 -> 561984.67 | BD35: =Elect!#REF! -> #REF! | BE35: =Elect!#REF! -> #REF! | BF35: =Elect!#REF! -> #REF! | BG35: =Elect!#REF! -> #REF! | BH35: 1.1761372 | BI35: 0.60007377 | BJ35: 150494 | BK35: 6.6098911 | BL35: 3.3724146 | BM35: =Water!U40 -> #REF! | BN35: =Water!W40 -> #REF! | BO35: =Water!X40 -> 0 | BP35: =Water!Y40 -> 0 | BQ35: =Water!Z40 -> 0
A36: Budget MTD | B36: 1040026 | C36: =Elect!#REF! -> #REF! | D36: 0 | E36: =Elect!#REF! -> #REF! | F36: 0 | G36: =Elect!#REF! -> #REF! | H36: 0 | I36: =Water!C41 -> 0 | J36: 0 | K36: =Water!E42 -> 0 | L36: 6 | M36: =Water!#REF! -> #REF! | N36: =Water!#REF! -> #REF! | O36: 30039 | P36: =Water!H41 -> 0 | Q36: 129.54839 | R36: =Water!O41 -> 0 | S36: 719 | T36: =Water!#REF! -> #REF! | U36: 4609 | V36: =Water!#REF! -> #REF! | W36: 23430 | X36: =Water!Q41 -> 0 | Y36: 6 | Z36: =Water!#REF! -> #REF! | AA36: 0 | AB36: 0 | AC36: 0 | AD36: =Water!#REF! -> #REF! | AE36: =Water!#REF! -> #REF! | AF36: =Water!#REF! -> #REF! | AG36: =Gas!#REF! -> #REF! | AH36: =Gas!#REF! -> #REF! | AI36: =Gas!#REF! -> #REF! | AJ36: =Gas!#REF! -> #REF! | AK36: =Gas!#REF! -> #REF! | AL36: =Gas!#REF! -> #REF! | AM36: =Gas!#REF! -> #REF! | AN36: =Gas!#REF! -> #REF! | ... AS36: =Gas!#REF! -> #REF! | AT36: =Elect!#REF! -> #REF! | AU36: =Elect!#REF! -> #REF! | AX36: 45.679286 | AY36: 23.305904 | AZ36: 264708.4 | BA36: 11.626335 | BB36: 5.9318409 | BC36: =Elect!#REF! -> #REF! | BD36: =Elect!#REF! -> #REF! | BE36: =Elect!#REF! -> #REF! | BF36: =Elect!#REF! -> #REF! | BG36: =Elect!#REF! -> #REF! | BH36: 0 | BI36: 0 | BJ36: 135930.06 | BK36: 6.6098911 | BL36: 3.3724146 | BM36: =Water!U41 -> #REF! | BN36: =Water!W41 -> #REF! | BO36: =Water!X41 -> #REF! | BP36: =Water!Y41 -> #REF! | BQ36: =Water!Z41 -> #REF!
A37: AVER. Bud | B37: 37143.785 | C37: =Elect!#REF! -> #REF! | D37: 0 | E37: =Elect!#REF! -> #REF! | F37: 0 | G37: =Elect!#REF! -> #REF! | H37: 0 | I37: =Water!C42 -> 0 | J37: 0 | K37: =Water!E43 -> 0 | L37: 7 | M37: =Water!#REF! -> #REF! | N37: =Water!#REF! -> #REF! | O37: 969 | P37: =Water!H42 -> 0 | Q37: 0 | R37: =Water!O42 -> 0 | S37: 23.193548 | T37: =Water!#REF! -> #REF! | U37: 148.67742 | V37: =Water!#REF! -> #REF! | W37: 755.80645 | X37: =Water!Q42 -> 0 | Y37: 7 | Z37: =Water!#REF! -> #REF! | AA37: 0 | AB37: 0 | AC37: 0 | AD37: =Water!#REF! -> #REF! | AE37: =Water!#REF! -> #REF! | AF37: =Water!#REF! -> #REF! | AG37: =Gas!#REF! -> #REF! | AH37: =Gas!#REF! -> #REF! | AI37: =Gas!#REF! -> #REF! | AJ37: =Gas!#REF! -> #REF! | AK37: =Gas!#REF! -> #REF! | AL37: =Gas!#REF! -> #REF! | AM37: =Gas!#REF! -> #REF! | AN37: =Gas!#REF! -> #REF! | ... AS37: =Gas!#REF! -> #REF! | AT37: =Elect!#REF! -> #REF! | AU37: =Elect!#REF! -> #REF! | AX37: 0 | AY37: 0 | AZ37: 9453.8714 | BA37: 0 | BB37: 0 | BC37: =Elect!#REF! -> #REF! | BD37: =Elect!#REF! -> #REF! | BE37: =Elect!#REF! -> #REF! | BF37: =Elect!#REF! -> #REF! | BG37: =Elect!#REF! -> #REF! | BH37: 0 | BI37: 0 | BJ37: 0 | BK37: 0 | BL37: 0 | BM37: =Water!U42 -> 0 | BN37: =Water!W42 -> 0 | BO37: =Water!X42 -> 0 | BP37: =Water!Y42 -> 0 | BQ37: =Water!Z42 -> 0
A38: Total RFC | B38: 784008.53 | C38: =Elect!#REF! -> #REF! | D38: 0 | E38: =Elect!#REF! -> #REF! | F38: 0 | G38: =Elect!#REF! -> #REF! | H38: 0 | I38: =Water!C43 -> 0 | J38: 0 | K38: =Water!E44 -> 0 | L38: 8 | M38: =Water!#REF! -> #REF! | N38: =Water!#REF! -> #REF! | O38: 0 | P38: =Water!H43 -> 0 | Q38: 0 | R38: =Water!O43 -> 0 | S38: 0 | T38: =Water!#REF! -> #REF! | U38: 0 | V38: =Water!#REF! -> #REF! | W38: 0 | X38: =Water!Q43 -> 0 | Y38: 8 | Z38: =Water!#REF! -> #REF! | AA38: 0 | AB38: 0 | AC38: 0 | AD38: =Water!#REF! -> #REF! | AE38: =Water!#REF! -> #REF! | AF38: =Water!#REF! -> #REF! | AG38: =Gas!#REF! -> #REF! | AH38: =Gas!#REF! -> #REF! | AI38: =Gas!#REF! -> #REF! | AJ38: =Gas!#REF! -> #REF! | AK38: =Gas!#REF! -> #REF! | AL38: =Gas!#REF! -> #REF! | AM38: =Gas!#REF! -> #REF! | AN38: =Gas!#REF! -> #REF! | ... AS38: =Gas!#REF! -> #REF! | AT38: =Elect!#REF! -> #REF! | AU38: =Elect!#REF! -> #REF! | AX38: 38.173558 | AY38: 19.219193 | AZ38: 208225.85 | BA38: 10.138565 | BB38: 5.1044505 | BC38: =Elect!#REF! -> #REF! | BD38: =Elect!#REF! -> #REF! | BE38: =Elect!#REF! -> #REF! | BF38: =Elect!#REF! -> #REF! | BG38: =Elect!#REF! -> #REF! | BH38: 0 | BI38: 0 | BJ38: 127385.62 | BK38: 6.2024355 | BL38: 3.1227323 | BM38: =Water!U43 -> 0 | BN38: =Water!W43 -> 0 | BO38: =Water!X43 -> 0 | BP38: =Water!Y43 -> 0 | BQ38: =Water!Z43 -> 0
A39: RFC MTD | B39: 784008.53 | C39: =Elect!#REF! -> #REF! | D39: 0 | E39: =Elect!#REF! -> #REF! | F39: 0 | G39: =Elect!#REF! -> #REF! | H39: 0 | I39: =Water!C44 -> 0 | J39: 0 | K39: =Water!E45 -> 0 | L39: 9 | M39: =Water!#REF! -> #REF! | N39: =Water!#REF! -> #REF! | O39: 0 | P39: =Water!H44 -> 0 | Q39: 0 | R39: =Water!O44 -> 0 | S39: 0 | T39: =Water!#REF! -> #REF! | U39: 0 | V39: =Water!#REF! -> #REF! | W39: 0 | X39: =Water!Q44 -> 0 | Y39: 9 | Z39: =Water!#REF! -> #REF! | AA39: 0 | AB39: 0 | AC39: 0 | AD39: =Water!#REF! -> #REF! | AE39: =Water!#REF! -> #REF! | AF39: =Water!#REF! -> #REF! | AG39: =Gas!#REF! -> #REF! | AH39: =Gas!#REF! -> #REF! | AI39: =Gas!#REF! -> #REF! | AJ39: =Gas!#REF! -> #REF! | AK39: =Gas!#REF! -> #REF! | AL39: =Gas!#REF! -> #REF! | AM39: =Gas!#REF! -> #REF! | AN39: =Gas!#REF! -> #REF! | ... AS39: =Gas!#REF! -> #REF! | AT39: =Elect!#REF! -> #REF! | AU39: =Elect!#REF! -> #REF! | AX39: 38.173558 | AY39: 19.219193 | AZ39: 208225.85 | BA39: 10.138565 | BB39: 5.1044505 | BC39: =Elect!#REF! -> #REF! | BD39: =Elect!#REF! -> #REF! | BE39: =Elect!#REF! -> #REF! | BF39: =Elect!#REF! -> #REF! | BG39: =Elect!#REF! -> #REF! | BH39: 0 | BI39: 0 | BJ39: 115057.98 | BK39: 6.2024355 | BL39: 3.1227323 | BM39: =Water!U44 -> 0 | BN39: =Water!W44 -> 0 | BO39: =Water!X44 -> #VALUE! | BP39: =Water!Y44 -> #VALUE! | BQ39: =Water!Z44 -> #VALUE!
A40: AVER RFC | B40: 28000.305 | C40: =Elect!#REF! -> #REF! | D40: 0 | E40: =Elect!#REF! -> #REF! | F40: 0 | G40: =Elect!#REF! -> #REF! | H40: 0 | I40: =Water!C45 -> 0 | J40: 0 | K40: =Water!E46 -> 0 | L40: 10 | M40: =Water!#REF! -> #REF! | N40: =Water!#REF! -> #REF! | O40: 0 | P40: =Water!H45 -> 0 | Q40: 0 | R40: =Water!O45 -> 0 | S40: 0 | T40: =Water!#REF! -> #REF! | U40: 0 | V40: =Water!#REF! -> #REF! | W40: 0 | X40: =Water!Q45 -> 0 | Y40: 10 | Z40: =Water!#REF! -> #REF! | AA40: 0 | AB40: 0 | AC40: 0 | AD40: =Water!#REF! -> #REF! | AE40: =Water!#REF! -> #REF! | AF40: =Water!#REF! -> #REF! | AG40: =Gas!#REF! -> #REF! | AH40: =Gas!#REF! -> #REF! | AI40: =Gas!#REF! -> #REF! | AJ40: =Gas!#REF! -> #REF! | AK40: =Gas!#REF! -> #REF! | AL40: =Gas!#REF! -> #REF! | AM40: =Gas!#REF! -> #REF! | AN40: =Gas!#REF! -> #REF! | ... AS40: =Gas!#REF! -> #REF! | AT40: =Elect!#REF! -> #REF! | AU40: =Elect!#REF! -> #REF! | AX40: 0 | AY40: 0 | AZ40: 7436.6375 | BA40: 0 | BB40: 0 | BC40: =Elect!#REF! -> #REF! | BD40: =Elect!#REF! -> #REF! | BE40: =Elect!#REF! -> #REF! | BF40: =Elect!#REF! -> #REF! | BG40: =Elect!#REF! -> #REF! | BH40: 1.1254646 | BI40: 0.57264868 | BJ40: 4109.2135 | BK40: 0 | BL40: 0 | BM40: =Water!U45 -> 0 | BN40: =Water!W45 -> 0 | BO40: =Water!X45 -> #VALUE! | BP40: =Water!Y45 -> 0 | BQ40: =Water!Z45 -> 0

Sheet Temp.
A2: HILTON INTERNATIONAL
A3: GULF, MIDDLE EAST AND ASIA SPECIFIC
A4: HOTEL:HILTON HURGHADA LONG BEACH RESORT | G4: =Elect!A1 -> 44896
A7: DATE | B7: MAX TEMP | C7: MIN TEMP | D7: MAX TEMP | E7: MIN TEMP | F7: DAY | G7: DD. C | H7: DD. H | I7: MTD | J7: MTD
B8: C | C8: C | D8: F | E8: F | F8: PARAMETER | I8: COOLING | J8: HEATING
A10: 1 | D10: =SUM((B10*9/5)+32) -> 32 | E10: =SUM((C10*9/5)+32) -> 32 | F10: =SUM(((B10+C10)/2)-18.33) -> -18.33 | G10: =SUM(0+(F10)+ABS(F10))/2 -> 0 | H10: =IF((SUM(0-(F10)+ABS(F10))/2)<18,SUM(0-(F10)+ABS(F10))/2,0) -> 0 | I10: =SUM(G10:G10) -> 0 | J10: =SUM(H10:H10) -> 0
A11: 2 | D11: =SUM((B11*9/5)+32) -> 32 | E11: =SUM((C11*9/5)+32) -> 32 | F11: =SUM(((B11+C11)/2)-18.33) -> -18.33 | G11: =SUM(0+(F11)+ABS(F11))/2 -> 0 | H11: =IF((SUM(0-(F11)+ABS(F11))/2)<18,SUM(0-(F11)+ABS(F11))/2,0) -> 0 | I11: =SUM(G10:G11) -> 0 | J11: =SUM(H10:H11) -> 0
A12: 3 | D12: =SUM((B12*9/5)+32) -> 32 | E12: =SUM((C12*9/5)+32) -> 32 | F12: =SUM(((B12+C12)/2)-18.33) -> -18.33 | G12: =SUM(0+(F12)+ABS(F12))/2 -> 0 | H12: =IF((SUM(0-(F12)+ABS(F12))/2)<18,SUM(0-(F12)+ABS(F12))/2,0) -> 0 | I12: =SUM(G10:G12) -> 0 | J12: =SUM(H10:H12) -> 0
A13: 4 | D13: =SUM((B13*9/5)+32) -> 32 | E13: =SUM((C13*9/5)+32) -> 32 | F13: =SUM(((B13+C13)/2)-18.33) -> -18.33 | G13: =SUM(0+(F13)+ABS(F13))/2 -> 0 | H13: =IF((SUM(0-(F13)+ABS(F13))/2)<18,SUM(0-(F13)+ABS(F13))/2,0) -> 0 | I13: =SUM(G10:G13) -> 0 | J13: =SUM(H10:H13) -> 0
A14: 5 | D14: =SUM((B14*9/5)+32) -> 32 | E14: =SUM((C14*9/5)+32) -> 32 | F14: =SUM(((B14+C14)/2)-18.33) -> -18.33 | G14: =SUM(0+(F14)+ABS(F14))/2 -> 0 | H14: =IF((SUM(0-(F14)+ABS(F14))/2)<18,SUM(0-(F14)+ABS(F14))/2,0) -> 0 | I14: =SUM(G10:G14) -> 0 | J14: =SUM(H10:H14) -> 0
A15: 6 | D15: =SUM((B15*9/5)+32) -> 32 | E15: =SUM((C15*9/5)+32) -> 32 | F15: =SUM(((B15+C15)/2)-18.33) -> -18.33 | G15: =SUM(0+(F15)+ABS(F15))/2 -> 0 | H15: =IF((SUM(0-(F15)+ABS(F15))/2)<18,SUM(0-(F15)+ABS(F15))/2,0) -> 0 | I15: =SUM(G10:G15) -> 0 | J15: =SUM(H10:H15) -> 0
A16: 7 | D16: =SUM((B16*9/5)+32) -> 32 | E16: =SUM((C16*9/5)+32) -> 32 | F16: =SUM(((B16+C16)/2)-18.33) -> -18.33 | G16: =SUM(0+(F16)+ABS(F16))/2 -> 0 | H16: =IF((SUM(0-(F16)+ABS(F16))/2)<18,SUM(0-(F16)+ABS(F16))/2,0) -> 0 | I16: =SUM(G10:G16) -> 0 | J16: =SUM(H10:H16) -> 0
A17: 8 | D17: =SUM((B17*9/5)+32) -> 32 | E17: =SUM((C17*9/5)+32) -> 32 | F17: =SUM(((B17+C17)/2)-18.33) -> -18.33 | G17: =SUM(0+(F17)+ABS(F17))/2 -> 0 | H17: =IF((SUM(0-(F17)+ABS(F17))/2)<18,SUM(0-(F17)+ABS(F17))/2,0) -> 0 | I17: =SUM(G10:G17) -> 0 | J17: =SUM(H10:H17) -> 0
A18: 9 | D18: =SUM((B18*9/5)+32) -> 32 | E18: =SUM((C18*9/5)+32) -> 32 | F18: =SUM(((B18+C18)/2)-18.33) -> -18.33 | G18: =SUM(0+(F18)+ABS(F18))/2 -> 0 | H18: =IF((SUM(0-(F18)+ABS(F18))/2)<18,SUM(0-(F18)+ABS(F18))/2,0) -> 0 | I18: =SUM(G10:G18) -> 0 | J18: =SUM(H10:H18) -> 0
A19: 10 | D19: =SUM((B19*9/5)+32) -> 32 | E19: =SUM((C19*9/5)+32) -> 32 | F19: =SUM(((B19+C19)/2)-18.33) -> -18.33 | G19: =SUM(0+(F19)+ABS(F19))/2 -> 0 | H19: =IF((SUM(0-(F19)+ABS(F19))/2)<18,SUM(0-(F19)+ABS(F19))/2,0) -> 0 | I19: =SUM(G10:G19) -> 0 | J19: =SUM(H10:H19) -> 0
A20: 11 | D20: =SUM((B20*9/5)+32) -> 32 | E20: =SUM((C20*9/5)+32) -> 32 | F20: =SUM(((B20+C20)/2)-18.33) -> -18.33 | G20: =SUM(0+(F20)+ABS(F20))/2 -> 0 | H20: =IF((SUM(0-(F20)+ABS(F20))/2)<18,SUM(0-(F20)+ABS(F20))/2,0) -> 0 | I20: =SUM(G10:G20) -> 0 | J20: =SUM(H10:H20) -> 0
A21: 12 | D21: =SUM((B21*9/5)+32) -> 32 | E21: =SUM((C21*9/5)+32) -> 32 | F21: =SUM(((B21+C21)/2)-18.33) -> -18.33 | G21: =SUM(0+(F21)+ABS(F21))/2 -> 0 | H21: =IF((SUM(0-(F21)+ABS(F21))/2)<18,SUM(0-(F21)+ABS(F21))/2,0) -> 0 | I21: =SUM(G10:G21) -> 0 | J21: =SUM(H10:H21) -> 0
A22: 13 | D22: =SUM((B22*9/5)+32) -> 32 | E22: =SUM((C22*9/5)+32) -> 32 | F22: =SUM(((B22+C22)/2)-18.33) -> -18.33 | G22: =SUM(0+(F22)+ABS(F22))/2 -> 0 | H22: =IF((SUM(0-(F22)+ABS(F22))/2)<18,SUM(0-(F22)+ABS(F22))/2,0) -> 0 | I22: =SUM(G10:G22) -> 0 | J22: =SUM(H10:H22) -> 0
A23: 14 | D23: =SUM((B23*9/5)+32) -> 32 | E23: =SUM((C23*9/5)+32) -> 32 | F23: =SUM(((B23+C23)/2)-18.33) -> -18.33 | G23: =SUM(0+(F23)+ABS(F23))/2 -> 0 | H23: =IF((SUM(0-(F23)+ABS(F23))/2)<18,SUM(0-(F23)+ABS(F23))/2,0) -> 0 | I23: =SUM(G10:G23) -> 0 | J23: =SUM(H10:H23) -> 0
A24: 15 | D24: =SUM((B24*9/5)+32) -> 32 | E24: =SUM((C24*9/5)+32) -> 32 | F24: =SUM(((B24+C24)/2)-18.33) -> -18.33 | G24: =SUM(0+(F24)+ABS(F24))/2 -> 0 | H24: =IF((SUM(0-(F24)+ABS(F24))/2)<18,SUM(0-(F24)+ABS(F24))/2,0) -> 0 | I24: =SUM(G11:G24) -> 0 | J24: =SUM(H11:H24) -> 0
A25: 16 | D25: =SUM((B25*9/5)+32) -> 32 | E25: =SUM((C25*9/5)+32) -> 32 | F25: =SUM(((B25+C25)/2)-18.33) -> -18.33 | G25: =SUM(0+(F25)+ABS(F25))/2 -> 0 | H25: =IF((SUM(0-(F25)+ABS(F25))/2)<18,SUM(0-(F25)+ABS(F25))/2,0) -> 0 | I25: =SUM(G12:G25) -> 0 | J25: =SUM(H12:H25) -> 0
A26: 17 | D26: =SUM((B26*9/5)+32) -> 32 | E26: =SUM((C26*9/5)+32) -> 32 | F26: =SUM(((B26+C26)/2)-18.33) -> -18.33 | G26: =SUM(0+(F26)+ABS(F26))/2 -> 0 | H26: =IF((SUM(0-(F26)+ABS(F26))/2)<18,SUM(0-(F26)+ABS(F26))/2,0) -> 0 | I26: =SUM(G13:G26) -> 0 | J26: =SUM(H13:H26) -> 0
A27: 18 | D27: =SUM((B27*9/5)+32) -> 32 | E27: =SUM((C27*9/5)+32) -> 32 | F27: =SUM(((B27+C27)/2)-18.33) -> -18.33 | G27: =SUM(0+(F27)+ABS(F27))/2 -> 0 | H27: =IF((SUM(0-(F27)+ABS(F27))/2)<18,SUM(0-(F27)+ABS(F27))/2,0) -> 0 | I27: =SUM(G14:G27) -> 0 | J27: =SUM(H14:H27) -> 0
A28: 19 | D28: =SUM((B28*9/5)+32) -> 32 | E28: =SUM((C28*9/5)+32) -> 32 | F28: =SUM(((B28+C28)/2)-18.33) -> -18.33 | G28: =SUM(0+(F28)+ABS(F28))/2 -> 0 | H28: =IF((SUM(0-(F28)+ABS(F28))/2)<18,SUM(0-(F28)+ABS(F28))/2,0) -> 0 | I28: =SUM(G15:G28) -> 0 | J28: =SUM(H15:H28) -> 0
A29: 20 | D29: =SUM((B29*9/5)+32) -> 32 | E29: =SUM((C29*9/5)+32) -> 32 | F29: =SUM(((B29+C29)/2)-18.33) -> -18.33 | G29: =SUM(0+(F29)+ABS(F29))/2 -> 0 | H29: =IF((SUM(0-(F29)+ABS(F29))/2)<18,SUM(0-(F29)+ABS(F29))/2,0) -> 0 | I29: =SUM(G16:G29) -> 0 | J29: =SUM(H16:H29) -> 0
A30: 21 | D30: =SUM((B30*9/5)+32) -> 32 | E30: =SUM((C30*9/5)+32) -> 32 | F30: =SUM(((B30+C30)/2)-18.33) -> -18.33 | G30: =SUM(0+(F30)+ABS(F30))/2 -> 0 | H30: =IF((SUM(0-(F30)+ABS(F30))/2)<18,SUM(0-(F30)+ABS(F30))/2,0) -> 0 | I30: =SUM(G17:G30) -> 0 | J30: =SUM(H17:H30) -> 0
A31: 22 | D31: =SUM((B31*9/5)+32) -> 32 | E31: =SUM((C31*9/5)+32) -> 32 | F31: =SUM(((B31+C31)/2)-18.33) -> -18.33 | G31: =SUM(0+(F31)+ABS(F31))/2 -> 0 | H31: =IF((SUM(0-(F31)+ABS(F31))/2)<18,SUM(0-(F31)+ABS(F31))/2,0) -> 0 | I31: =SUM(G18:G31) -> 0 | J31: =SUM(H18:H31) -> 0
A32: 23 | D32: =SUM((B32*9/5)+32) -> 32 | E32: =SUM((C32*9/5)+32) -> 32 | F32: =SUM(((B32+C32)/2)-18.33) -> -18.33 | G32: =SUM(0+(F32)+ABS(F32))/2 -> 0 | H32: =IF((SUM(0-(F32)+ABS(F32))/2)<18,SUM(0-(F32)+ABS(F32))/2,0) -> 0 | I32: =SUM(G19:G32) -> 0 | J32: =SUM(H19:H32) -> 0
A33: 24 | D33: =SUM((B33*9/5)+32) -> 32 | E33: =SUM((C33*9/5)+32) -> 32 | F33: =SUM(((B33+C33)/2)-18.33) -> -18.33 | G33: =SUM(0+(F33)+ABS(F33))/2 -> 0 | H33: =IF((SUM(0-(F33)+ABS(F33))/2)<18,SUM(0-(F33)+ABS(F33))/2,0) -> 0 | I33: =SUM(G20:G33) -> 0 | J33: =SUM(H20:H33) -> 0
A34: 25 | D34: =SUM((B34*9/5)+32) -> 32 | E34: =SUM((C34*9/5)+32) -> 32 | F34: =SUM(((B34+C34)/2)-18.33) -> -18.33 | G34: =SUM(0+(F34)+ABS(F34))/2 -> 0 | H34: =IF((SUM(0-(F34)+ABS(F34))/2)<18,SUM(0-(F34)+ABS(F34))/2,0) -> 0 | I34: =SUM(G21:G34) -> 0 | J34: =SUM(H21:H34) -> 0
... A40: 31 | D40: =SUM((B40*9/5)+32) -> 32 | E40: =SUM((C40*9/5)+32) -> 32 | F40: =SUM(((B40+C40)/2)-18.33) -> -18.33 | G40: =SUM(0+(F40)+ABS(F40))/2 -> 0 | H40: =IF((SUM(0-(F40)+ABS(F40))/2)<18,SUM(0-(F40)+ABS(F40))/2,0) -> 0 | I40: =SUM(G27:G40) -> 0 | J40: =SUM(H27:H40) -> 0
E42: =SUM(G10:G40) -> 0 | F42: deg c
E44: =SUM(H10:H40) -> 0 | F44: deg c

Sheet M-Rep
B3: =Elect!A1 -> 44896
D4: Y.T.D
A5: Energy breakdown | C5: 2009 | D5: 2005 | E5: 2006
A6: Elect.
A7: Chillers KWH | C7: N/A | D7: N/A | E7: N/A
A8: Laundry KWH | C8: N/A | D8: N/A | E8: N/A
A9: Kitchen KWH | C9: N/A | D9: N/A | E9: N/A
A10: Gas
A11: Kit M3 | C11: =Gas!#REF!/1000 -> #REF!
A12: Laundry M3 | C12: N/A | D12: 0 | E12: #REF!
A13: Water | D13: N/A | E13: N/A
A14: Laundry HW | C14: N/A
A15: Laundry CW | C15: N/A
A16: Kit HW | C16: N/A
A17: kIt CW | C17: N/A | D17: N/A | E17: N/A
A18: Dmstc HW | C18: N/A | D18: N/A | E18: N/A
A19: Dmstc CW | C19: N/A | D19: N/A | E19: N/A
A20: S.Pool MKUP | C20: =#REF! -> #REF! | D20: N/A | E20: N/A
A21: Ctower MKUP | C21: N/A | D21: N/A | E21: N/A
A22: Gardens Irrigat. | C22: =Water!S38 -> 0 | D22: N/A | E22: N/A
A23: Swage water treatment | C23: =Water!#REF! -> #REF! | D23: 27437 | E23: #REF!
A24: Utilities consumption | D24: N/A | E24: N/A
A25: Elect. Kwh | C25: =Elect!J34 -> 5372.3333 | D25: 12266 | E25: 814
A26: M.D (9.5 LE) | D26: 147773 | E26: #REF!
A27: Water M3 | C27: =Water!H38 -> 10279.968
A28: Fuel Ltr | C28: =Gas!#REF!*1000 -> #REF! | D28: 12876868 | E28: 14500800
A29: Gas M3/ Boilers, chillers,..etc | C29: N/A | D29: 28880 | E29: 32980
A30: Gas M3 Kitchen | C30: =Gas!#REF!/1000 -> #REF! | D30: 244283 | E30: 252530.66
A31: Total Energy | D31: 620770 | E31: #REF!
A32: Control Parameters | D32: #REF! | E32: N/A
A33: No. of Rooms % occ. | C33: =YTD!Q4 -> 0 | D33: 39.395 | E33: #REF!
A34: No. of Occ. Rooms | C34: =YTD!Q5 -> 0
A35: guest count | C35: =YTD!Q6 -> 0
A36: Food covers | D36: #REF! | E36: #REF!
A37: Laundry W. Kg | D37: 0.8807 | E37: 0.46351998
A38: DDC | C38: =Temp.!E42 -> 0 | D38: 196150 | E38: 237021
A39: DDH | C39: =Temp.!E44 -> 0 | D39: 400070 | E39: 466105
A40: Utilities Entergy cost | D40: 1583714 | E40: 1940567
A41: Elect. | C41: =Elect!#REF! -> #REF! | D41: 1690339 | E41: 3118671.6
A42: M.D | C42: =C26*Elect!#REF! -> #REF! | D42: 2381.51 | E42: 2480.24
A43: Water | C43: =Water!X38 -> 39809.653 | D43: 112 | E43: 97.53
A44: Fuel | C44: =Gas!#REF! -> #REF!
A45: Gas Boilers, chillers,etc.. | C45: N/A | D45: 2138156.8 | E45: #REF!
A46: Gas Kitchen | C46: =C30*Gas!M2*1000 -> #REF! | D46: 223044.2 | E46: #REF!
A47: TOTAL LE | C47: =SUM(C41:C46) -> #REF! | D47: 1330535.7 | E47: 1382037.4
A48: No. of POMEC Staff | D48: 330278 | E48: #REF!
A49: Hotel Age | C49: 6 | D49: N/A | E49: N/A
A50: No. of rooms | C50: =31*912 -> 28272 | D50: 36597.525 | E50: #REF!
A51: Building Volume | C51: 243175 | D51: =SUM(D45:D50) -> 4058612.3 | E51: =SUM(E45:E50) -> #REF!
A52: Building area | C52: 75064
A53: US$ Rate | C53: 5.59402 | D53: 61 | E53: 72
A54: Total R&M MTD | C54: =YTD!Q65 -> 0 | D54: #REF! | E54: 243175 | F54: =YTD!Q64 -> 0
A55: Staff - HLP | D55: #REF! | E55: 75064
A56: Staff - R&M | D56: 5.755 | E56: 5.65951
A57: Staff - Grounds

Sheet YTD
A1: =Elect!A1 -> 44896 | H1: Actual 2014
C3: JAN | D3: FEB | E3: MAR | F3: APR | G3: MAY | H3: JUN | I3: JUL | J3: AUG | K3: SEP | L3: OCT | M3: NOV | N3: DEC | O3: TOTAL | P3: YTD | Q3: Month Act
A4: Occ Room % | O4: =SUM(C4:N4) -> 0 | P4: =(IF($A$1=39814,C4,(IF($A$1=39845,SUM(C4:D4),(IF($A$1=39873,SUM(C4:E4),(IF($A$1=39904,SUM(C4:F4),(IF($A$1=39934,SUM(C4:G4),(IF($A$1=39965,SUM(C4:H4),(IF($A$1=39995,SUM(C4:I4),0)))))))))))))+(IF($A$1=40026,SUM(C4:J4),(IF($A$1=40057,SUM(C4:K4),(IF($A$1=40087,SUM(C4:L4),(IF($A$1=40118,SUM(C4:M4))))))))))+(IF($A$1=40148,SUM(C4:N4),0)) -> 0 | Q4: =(IF($A$1=39814,C4,(IF($A$1=39845,D4,(IF($A$1=39873,E4,(IF($A$1=39904,F4,(IF($A$1=39934,G4,(IF($A$1=39965,H4,(IF($A$1=39995,I4,0)))))))))))))+(IF($A$1=40026,J4,(IF($A$1=40057,K4,(IF($A$1=40087,L4,(IF($A$1=40118,M4)))))))))+(IF($A$1=40148,N4,0)) -> 0 | S4: 40179 | DE4: 1
A5: Occ Room | C5: 25072 | D5: =Elect!BP34 -> 132 | O5: =SUM(C5:N5) -> 25204 | P5: =(IF($A$1=40179,C5,(IF($A$1=40210,SUM(C5:D5),(IF($A$1=40238,SUM(C5:E5),(IF($A$1=40269,SUM(C5:F5),(IF($A$1=40299,SUM(C5:G5),(IF($A$1=40330,SUM(C5:H5),(IF($A$1=40360,SUM(C5:I5),0)))))))))))))+(IF($A$1=40391,SUM(C5:J5),(IF($A$1=40422,SUM(C5:K5),(IF($A$1=40452,SUM(C5:L5),(IF($A$1=40483,SUM(C5:M5))))))))))+(IF($A$1=40513,SUM(C5:N5),0)) -> 0 | Q5: =(IF($A$1=40179,C5,(IF($A$1=40210,D5,(IF($A$1=40238,E5,(IF($A$1=40269,F5,(IF($A$1=40299,G5,(IF($A$1=40330,H5,(IF($A$1=40360,I5,0)))))))))))))+(IF($A$1=40391,J5,(IF($A$1=40422,K5,(IF($A$1=40452,L5,(IF($A$1=40483,M5)))))))))+(IF($A$1=40513,N5,0)) -> 0 | S5: 40210 | DE5: 2
A6: Number of Guest | C6: 50662 | D6: =Elect!BR34 -> 154 | O6: =SUM(C6:N6) -> 50816 | P6: =(IF($A$1=40179,C6,(IF($A$1=40210,SUM(C6:D6),(IF($A$1=40238,SUM(C6:E6),(IF($A$1=40269,SUM(C6:F6),(IF($A$1=40299,SUM(C6:G6),(IF($A$1=40330,SUM(C6:H6),(IF($A$1=40360,SUM(C6:I6),0)))))))))))))+(IF($A$1=40391,SUM(C6:J6),(IF($A$1=40422,SUM(C6:K6),(IF($A$1=40452,SUM(C6:L6),(IF($A$1=40483,SUM(C6:M6))))))))))+(IF($A$1=40513,SUM(C6:N6),0)) -> 0 | Q6: =(IF($A$1=40179,C6,(IF($A$1=40210,D6,(IF($A$1=40238,E6,(IF($A$1=40269,F6,(IF($A$1=40299,G6,(IF($A$1=40330,H6,(IF($A$1=40360,I6,0)))))))))))))+(IF($A$1=40391,J6,(IF($A$1=40422,K6,(IF($A$1=40452,L6,(IF($A$1=40483,M6)))))))))+(IF($A$1=40513,N6,0)) -> 0 | S6: 40238 | DE6: 3
A7: PAY & REL. EXP. | O7: =SUM(C7:N7) -> 0 | P7: =(IF($A$1=40179,C7,(IF($A$1=40210,SUM(C7:D7),(IF($A$1=40238,SUM(C7:E7),(IF($A$1=40269,SUM(C7:F7),(IF($A$1=40299,SUM(C7:G7),(IF($A$1=40330,SUM(C7:H7),(IF($A$1=40360,SUM(C7:I7),0)))))))))))))+(IF($A$1=40391,SUM(C7:J7),(IF($A$1=40422,SUM(C7:K7),(IF($A$1=40452,SUM(C7:L7),(IF($A$1=40483,SUM(C7:M7))))))))))+(IF($A$1=40513,SUM(C7:N7),0)) -> 0 | Q7: =(IF($A$1=40179,C7,(IF($A$1=40210,D7,(IF($A$1=40238,E7,(IF($A$1=40269,F7,(IF($A$1=40299,G7,(IF($A$1=40330,H7,(IF($A$1=40360,I7,0)))))))))))))+(IF($A$1=40391,J7,(IF($A$1=40422,K7,(IF($A$1=40452,L7,(IF($A$1=40483,M7)))))))))+(IF($A$1=40513,N7,0)) -> 0
A8: SALARIES | B8: 53241001 | O8: =SUM(C8:N8) -> 0 | P8: =(IF($A$1=40179,C8,(IF($A$1=40210,SUM(C8:D8),(IF($A$1=40238,SUM(C8:E8),(IF($A$1=40269,SUM(C8:F8),(IF($A$1=40299,SUM(C8:G8),(IF($A$1=40330,SUM(C8:H8),(IF($A$1=40360,SUM(C8:I8),0)))))))))))))+(IF($A$1=40391,SUM(C8:J8),(IF($A$1=40422,SUM(C8:K8),(IF($A$1=40452,SUM(C8:L8),(IF($A$1=40483,SUM(C8:M8))))))))))+(IF($A$1=40513,SUM(C8:N8),0)) -> 0 | Q8: =(IF($A$1=40179,C8,(IF($A$1=40210,D8,(IF($A$1=40238,E8,(IF($A$1=40269,F8,(IF($A$1=40299,G8,(IF($A$1=40330,H8,(IF($A$1=40360,I8,0)))))))))))))+(IF($A$1=40391,J8,(IF($A$1=40422,K8,(IF($A$1=40452,L8,(IF($A$1=40483,M8)))))))))+(IF($A$1=40513,N8,0)) -> 0
A9: EXTRA WAGES | B9: 53242099 | O9: =SUM(C9:N9) -> 0 | P9: =(IF($A$1=40179,C9,(IF($A$1=40210,SUM(C9:D9),(IF($A$1=40238,SUM(C9:E9),(IF($A$1=40269,SUM(C9:F9),(IF($A$1=40299,SUM(C9:G9),(IF($A$1=40330,SUM(C9:H9),(IF($A$1=40360,SUM(C9:I9),0)))))))))))))+(IF($A$1=40391,SUM(C9:J9),(IF($A$1=40422,SUM(C9:K9),(IF($A$1=40452,SUM(C9:L9),(IF($A$1=40483,SUM(C9:M9))))))))))+(IF($A$1=40513,SUM(C9:N9),0)) -> 0 | Q9: =(IF($A$1=40179,C9,(IF($A$1=40210,D9,(IF($A$1=40238,E9,(IF($A$1=40269,F9,(IF($A$1=40299,G9,(IF($A$1=40330,H9,(IF($A$1=40360,I9,0)))))))))))))+(IF($A$1=40391,J9,(IF($A$1=40422,K9,(IF($A$1=40452,L9,(IF($A$1=40483,M9)))))))))+(IF($A$1=40513,N9,0)) -> 0
A10: SERVICE | B10: 53243001 | O10: =SUM(C10:N10) -> 0 | P10: =(IF($A$1=40179,C10,(IF($A$1=40210,SUM(C10:D10),(IF($A$1=40238,SUM(C10:E10),(IF($A$1=40269,SUM(C10:F10),(IF($A$1=40299,SUM(C10:G10),(IF($A$1=40330,SUM(C10:H10),(IF($A$1=40360,SUM(C10:I10),0)))))))))))))+(IF($A$1=40391,SUM(C10:J10),(IF($A$1=40422,SUM(C10:K10),(IF($A$1=40452,SUM(C10:L10),(IF($A$1=40483,SUM(C10:M10))))))))))+(IF($A$1=40513,SUM(C10:N10),0)) -> 0 | Q10: =(IF($A$1=40179,C10,(IF($A$1=40210,D10,(IF($A$1=40238,E10,(IF($A$1=40269,F10,(IF($A$1=40299,G10,(IF($A$1=40330,H10,(IF($A$1=40360,I10,0)))))))))))))+(IF($A$1=40391,J10,(IF($A$1=40422,K10,(IF($A$1=40452,L10,(IF($A$1=40483,M10)))))))))+(IF($A$1=40513,N10,0)) -> 0
A11: RELATED EXP. | B11: 53244001 | O11: =SUM(C11:N11) -> 0 | P11: =(IF($A$1=40179,C11,(IF($A$1=40210,SUM(C11:D11),(IF($A$1=40238,SUM(C11:E11),(IF($A$1=40269,SUM(C11:F11),(IF($A$1=40299,SUM(C11:G11),(IF($A$1=40330,SUM(C11:H11),(IF($A$1=40360,SUM(C11:I11),0)))))))))))))+(IF($A$1=40391,SUM(C11:J11),(IF($A$1=40422,SUM(C11:K11),(IF($A$1=40452,SUM(C11:L11),(IF($A$1=40483,SUM(C11:M11))))))))))+(IF($A$1=40513,SUM(C11:N11),0)) -> 0 | Q11: =(IF($A$1=40179,C11,(IF($A$1=40210,D11,(IF($A$1=40238,E11,(IF($A$1=40269,F11,(IF($A$1=40299,G11,(IF($A$1=40330,H11,(IF($A$1=40360,I11,0)))))))))))))+(IF($A$1=40391,J11,(IF($A$1=40422,K11,(IF($A$1=40452,L11,(IF($A$1=40483,M11)))))))))+(IF($A$1=40513,N11,0)) -> 0
A12: EMPL. MEALS | B12: 53245001 | O12: =SUM(C12:N12) -> 0 | P12: =(IF($A$1=40179,C12,(IF($A$1=40210,SUM(C12:D12),(IF($A$1=40238,SUM(C12:E12),(IF($A$1=40269,SUM(C12:F12),(IF($A$1=40299,SUM(C12:G12),(IF($A$1=40330,SUM(C12:H12),(IF($A$1=40360,SUM(C12:I12),0)))))))))))))+(IF($A$1=40391,SUM(C12:J12),(IF($A$1=40422,SUM(C12:K12),(IF($A$1=40452,SUM(C12:L12),(IF($A$1=40483,SUM(C12:M12))))))))))+(IF($A$1=40513,SUM(C12:N12),0)) -> 0 | Q12: =(IF($A$1=40179,C12,(IF($A$1=40210,D12,(IF($A$1=40238,E12,(IF($A$1=40269,F12,(IF($A$1=40299,G12,(IF($A$1=40330,H12,(IF($A$1=40360,I12,0)))))))))))))+(IF($A$1=40391,J12,(IF($A$1=40422,K12,(IF($A$1=40452,L12,(IF($A$1=40483,M12)))))))))+(IF($A$1=40513,N12,0)) -> 0
O13: =SUM(C13:N13) -> 0 | P13: =(IF($A$1=40179,C13,(IF($A$1=40210,SUM(C13:D13),(IF($A$1=40238,SUM(C13:E13),(IF($A$1=40269,SUM(C13:F13),(IF($A$1=40299,SUM(C13:G13),(IF($A$1=40330,SUM(C13:H13),(IF($A$1=40360,SUM(C13:I13),0)))))))))))))+(IF($A$1=40391,SUM(C13:J13),(IF($A$1=40422,SUM(C13:K13),(IF($A$1=40452,SUM(C13:L13),(IF($A$1=40483,SUM(C13:M13))))))))))+(IF($A$1=40513,SUM(C13:N13),0)) -> 0 | Q13: =(IF($A$1=40179,C13,(IF($A$1=40210,D13,(IF($A$1=40238,E13,(IF($A$1=40269,F13,(IF($A$1=40299,G13,(IF($A$1=40330,H13,(IF($A$1=40360,I13,0)))))))))))))+(IF($A$1=40391,J13,(IF($A$1=40422,K13,(IF($A$1=40452,L13,(IF($A$1=40483,M13)))))))))+(IF($A$1=40513,N13,0)) -> 0
A14: TOTAL PAY & REL. | C14: 147832.84 | D14: 158624 | O14: =SUM(C14:N14) -> 306456.84 | P14: =(IF($A$1=40179,C14,(IF($A$1=40210,SUM(C14:D14),(IF($A$1=40238,SUM(C14:E14),(IF($A$1=40269,SUM(C14:F14),(IF($A$1=40299,SUM(C14:G14),(IF($A$1=40330,SUM(C14:H14),(IF($A$1=40360,SUM(C14:I14),0)))))))))))))+(IF($A$1=40391,SUM(C14:J14),(IF($A$1=40422,SUM(C14:K14),(IF($A$1=40452,SUM(C14:L14),(IF($A$1=40483,SUM(C14:M14))))))))))+(IF($A$1=40513,SUM(C14:N14),0)) -> 0 | Q14: =(IF($A$1=40179,C14,(IF($A$1=40210,D14,(IF($A$1=40238,E14,(IF($A$1=40269,F14,(IF($A$1=40299,G14,(IF($A$1=40330,H14,(IF($A$1=40360,I14,0)))))))))))))+(IF($A$1=40391,J14,(IF($A$1=40422,K14,(IF($A$1=40452,L14,(IF($A$1=40483,M14)))))))))+(IF($A$1=40513,N14,0)) -> 0 | S14: 40269 | DE14: 4
A15: ELECRICITY | B15: 53257511 | C15: 267068.09 | D15: 312865.7 | O15: =SUM(C15:N15) -> 579933.79 | P15: =(IF($A$1=40179,C15,(IF($A$1=40210,SUM(C15:D15),(IF($A$1=40238,SUM(C15:E15),(IF($A$1=40269,SUM(C15:F15),(IF($A$1=40299,SUM(C15:G15),(IF($A$1=40330,SUM(C15:H15),(IF($A$1=40360,SUM(C15:I15),0)))))))))))))+(IF($A$1=40391,SUM(C15:J15),(IF($A$1=40422,SUM(C15:K15),(IF($A$1=40452,SUM(C15:L15),(IF($A$1=40483,SUM(C15:M15))))))))))+(IF($A$1=40513,SUM(C15:N15),0)) -> 0 | Q15: =(IF($A$1=40179,C15,(IF($A$1=40210,D15,(IF($A$1=40238,E15,(IF($A$1=40269,F15,(IF($A$1=40299,G15,(IF($A$1=40330,H15,(IF($A$1=40360,I15,0)))))))))))))+(IF($A$1=40391,J15,(IF($A$1=40422,K15,(IF($A$1=40452,L15,(IF($A$1=40483,M15)))))))))+(IF($A$1=40513,N15,0)) -> 0 | S15: 40299 | DE15: 5
A16: WATER & SEWAGE | B16: 53257551 | C16: 178948 | D16: 189620 | O16: =SUM(C16:N16) -> 368568 | P16: =(IF($A$1=40179,C16,(IF($A$1=40210,SUM(C16:D16),(IF($A$1=40238,SUM(C16:E16),(IF($A$1=40269,SUM(C16:F16),(IF($A$1=40299,SUM(C16:G16),(IF($A$1=40330,SUM(C16:H16),(IF($A$1=40360,SUM(C16:I16),0)))))))))))))+(IF($A$1=40391,SUM(C16:J16),(IF($A$1=40422,SUM(C16:K16),(IF($A$1=40452,SUM(C16:L16),(IF($A$1=40483,SUM(C16:M16))))))))))+(IF($A$1=40513,SUM(C16:N16),0)) -> 0 | Q16: =(IF($A$1=40179,C16,(IF($A$1=40210,D16,(IF($A$1=40238,E16,(IF($A$1=40269,F16,(IF($A$1=40299,G16,(IF($A$1=40330,H16,(IF($A$1=40360,I16,0)))))))))))))+(IF($A$1=40391,J16,(IF($A$1=40422,K16,(IF($A$1=40452,L16,(IF($A$1=40483,M16)))))))))+(IF($A$1=40513,N16,0)) -> 0 | S16: 40330 | DE16: 6
A17: FUEL | B17: 53257571 | C17: 82735 | D17: 123809 | O17: =SUM(C17:N17) -> 206544 | P17: =(IF($A$1=40179,C17,(IF($A$1=40210,SUM(C17:D17),(IF($A$1=40238,SUM(C17:E17),(IF($A$1=40269,SUM(C17:F17),(IF($A$1=40299,SUM(C17:G17),(IF($A$1=40330,SUM(C17:H17),(IF($A$1=40360,SUM(C17:I17),0)))))))))))))+(IF($A$1=40391,SUM(C17:J17),(IF($A$1=40422,SUM(C17:K17),(IF($A$1=40452,SUM(C17:L17),(IF($A$1=40483,SUM(C17:M17))))))))))+(IF($A$1=40513,SUM(C17:N17),0)) -> 0 | Q17: =(IF($A$1=40179,C17,(IF($A$1=40210,D17,(IF($A$1=40238,E17,(IF($A$1=40269,F17,(IF($A$1=40299,G17,(IF($A$1=40330,H17,(IF($A$1=40360,I17,0)))))))))))))+(IF($A$1=40391,J17,(IF($A$1=40422,K17,(IF($A$1=40452,L17,(IF($A$1=40483,M17)))))))))+(IF($A$1=40513,N17,0)) -> 0 | S17: 40360 | DE17: 7
A18: gas | B18: 0 | C18: 0 | D18: 0 | E18: 0 | F18: 0 | G18: 0 | H18: 0 | O18: =SUM(C18:N18) -> 0 | P18: =(IF($A$1=40179,C18,(IF($A$1=40210,SUM(C18:D18),(IF($A$1=40238,SUM(C18:E18),(IF($A$1=40269,SUM(C18:F18),(IF($A$1=40299,SUM(C18:G18),(IF($A$1=40330,SUM(C18:H18),(IF($A$1=40360,SUM(C18:I18),0)))))))))))))+(IF($A$1=40391,SUM(C18:J18),(IF($A$1=40422,SUM(C18:K18),(IF($A$1=40452,SUM(C18:L18),(IF($A$1=40483,SUM(C18:M18))))))))))+(IF($A$1=40513,SUM(C18:N18),0)) -> 0 | Q18: =(IF($A$1=40179,C18,(IF($A$1=40210,D18,(IF($A$1=40238,E18,(IF($A$1=40269,F18,(IF($A$1=40299,G18,(IF($A$1=40330,H18,(IF($A$1=40360,I18,0)))))))))))))+(IF($A$1=40391,J18,(IF($A$1=40422,K18,(IF($A$1=40452,L18,(IF($A$1=40483,M18)))))))))+(IF($A$1=40513,N18,0)) -> 0 | S18: 40391 | DE18: 8
A19: TOTAL ENERGY | C19: =SUM(C15:C18) -> 528751.09 | D19: =SUM(D15:D18) -> 626294.7 | E19: =SUM(E15:E18) -> 0 | F19: =SUM(F15:F18) -> 0 | G19: =SUM(G15:G18) -> 0 | H19: =SUM(H15:H18) -> 0 | I19: =SUM(I15:I18) -> 0 | J19: =SUM(J15:J18) -> 0 | ... O19: =SUM(O15:O18) -> 1155045.8 | P19: =(IF($A$1=40179,C19,(IF($A$1=40210,SUM(C19:D19),(IF($A$1=40238,SUM(C19:E19),(IF($A$1=40269,SUM(C19:F19),(IF($A$1=40299,SUM(C19:G19),(IF($A$1=40330,SUM(C19:H19),(IF($A$1=40360,SUM(C19:I19),0)))))))))))))+(IF($A$1=40391,SUM(C19:J19),(IF($A$1=40422,SUM(C19:K19),(IF($A$1=40452,SUM(C19:L19),(IF($A$1=40483,SUM(C19:M19))))))))))+(IF($A$1=40513,SUM(C19:N19),0)) -> 0 | Q19: =(IF($A$1=40179,C19,(IF($A$1=40210,D19,(IF($A$1=40238,E19,(IF($A$1=40269,F19,(IF($A$1=40299,G19,(IF($A$1=40330,H19,(IF($A$1=40360,I19,0)))))))))))))+(IF($A$1=40391,J19,(IF($A$1=40422,K19,(IF($A$1=40452,L19,(IF($A$1=40483,M19)))))))))+(IF($A$1=40513,N19,0)) -> 0 | S19: 40422 | DE19: 9
P20: =(IF($A$1=40179,C20,(IF($A$1=40210,SUM(C20:D20),(IF($A$1=40238,SUM(C20:E20),(IF($A$1=40269,SUM(C20:F20),(IF($A$1=40299,SUM(C20:G20),(IF($A$1=40330,SUM(C20:H20),(IF($A$1=40360,SUM(C20:I20),0)))))))))))))+(IF($A$1=40391,SUM(C20:J20),(IF($A$1=40422,SUM(C20:K20),(IF($A$1=40452,SUM(C20:L20),(IF($A$1=40483,SUM(C20:M20))))))))))+(IF($A$1=40513,SUM(C20:N20),0)) -> 0 | Q20: =(IF($A$1=40179,C20,(IF($A$1=40210,D20,(IF($A$1=40238,E20,(IF($A$1=40269,F20,(IF($A$1=40299,G20,(IF($A$1=40330,H20,(IF($A$1=40360,I20,0)))))))))))))+(IF($A$1=40391,J20,(IF($A$1=40422,K20,(IF($A$1=40452,L20,(IF($A$1=40483,M20)))))))))+(IF($A$1=40513,N20,0)) -> 0
A21: OTHER EXPENSES | P21: =(IF($A$1=40179,C21,(IF($A$1=40210,SUM(C21:D21),(IF($A$1=40238,SUM(C21:E21),(IF($A$1=40269,SUM(C21:F21),(IF($A$1=40299,SUM(C21:G21),(IF($A$1=40330,SUM(C21:H21),(IF($A$1=40360,SUM(C21:I21),0)))))))))))))+(IF($A$1=40391,SUM(C21:J21),(IF($A$1=40422,SUM(C21:K21),(IF($A$1=40452,SUM(C21:L21),(IF($A$1=40483,SUM(C21:M21))))))))))+(IF($A$1=40513,SUM(C21:N21),0)) -> 0 | Q21: =(IF($A$1=40179,C21,(IF($A$1=40210,D21,(IF($A$1=40238,E21,(IF($A$1=40269,F21,(IF($A$1=40299,G21,(IF($A$1=40330,H21,(IF($A$1=40360,I21,0)))))))))))))+(IF($A$1=40391,J21,(IF($A$1=40422,K21,(IF($A$1=40452,L21,(IF($A$1=40483,M21)))))))))+(IF($A$1=40513,N21,0)) -> 0
A22: P. & ST. | B22: 53251503 | C22: 2782.3724 | D22: 2209.2805 | E22: 3205.3202 | F22: 2604.6091 | G22: 3235.6987 | H22: 2482.8474 | I22: 3129.5287 | J22: 4085.8967 | K22: 4096.0234 | L22: 4111.0374 | M22: 4007.7194 | N22: 3115.8679 | O22: 39066.202 | P22: =(IF($A$1=40179,C22,(IF($A$1=40210,SUM(C22:D22),(IF($A$1=40238,SUM(C22:E22),(IF($A$1=40269,SUM(C22:F22),(IF($A$1=40299,SUM(C22:G22),(IF($A$1=40330,SUM(C22:H22),(IF($A$1=40360,SUM(C22:I22),0)))))))))))))+(IF($A$1=40391,SUM(C22:J22),(IF($A$1=40422,SUM(C22:K22),(IF($A$1=40452,SUM(C22:L22),(IF($A$1=40483,SUM(C22:M22))))))))))+(IF($A$1=40513,SUM(C22:N22),0)) -> 0 | Q22: =(IF($A$1=40179,C22,(IF($A$1=40210,D22,(IF($A$1=40238,E22,(IF($A$1=40269,F22,(IF($A$1=40299,G22,(IF($A$1=40330,H22,(IF($A$1=40360,I22,0)))))))))))))+(IF($A$1=40391,J22,(IF($A$1=40422,K22,(IF($A$1=40452,L22,(IF($A$1=40483,M22)))))))))+(IF($A$1=40513,N22,0)) -> 0
A23: POSTAGE | B23: 53251912 | C23: 0 | D23: 0 | E23: 0 | F23: 0 | G23: 0 | H23: 0 | I23: 0 | J23: 0 | K23: 0 | L23: 0 | M23: 0 | N23: 0 | O23: 0 | P23: =(IF($A$1=40179,C23,(IF($A$1=40210,SUM(C23:D23),(IF($A$1=40238,SUM(C23:E23),(IF($A$1=40269,SUM(C23:F23),(IF($A$1=40299,SUM(C23:G23),(IF($A$1=40330,SUM(C23:H23),(IF($A$1=40360,SUM(C23:I23),0)))))))))))))+(IF($A$1=40391,SUM(C23:J23),(IF($A$1=40422,SUM(C23:K23),(IF($A$1=40452,SUM(C23:L23),(IF($A$1=40483,SUM(C23:M23))))))))))+(IF($A$1=40513,SUM(C23:N23),0)) -> 0 | Q23: =(IF($A$1=40179,C23,(IF($A$1=40210,D23,(IF($A$1=40238,E23,(IF($A$1=40269,F23,(IF($A$1=40299,G23,(IF($A$1=40330,H23,(IF($A$1=40360,I23,0)))))))))))))+(IF($A$1=40391,J23,(IF($A$1=40422,K23,(IF($A$1=40452,L23,(IF($A$1=40483,M23)))))))))+(IF($A$1=40513,N23,0)) -> 0
A24: TAXICAB | B24: 53251919 | C24: 11276.363 | D24: 10009.133 | E24: 9350.2819 | F24: 12862.267 | G24: 10806.952 | H24: 11155.64 | I24: 12970.205 | J24: 10165.751 | K24: 10061.171 | L24: 10190.726 | M24: 10023.319 | N24: 7435.7374 | O24: 126307.55 | P24: =(IF($A$1=40179,C24,(IF($A$1=40210,SUM(C24:D24),(IF($A$1=40238,SUM(C24:E24),(IF($A$1=40269,SUM(C24:F24),(IF($A$1=40299,SUM(C24:G24),(IF($A$1=40330,SUM(C24:H24),(IF($A$1=40360,SUM(C24:I24),0)))))))))))))+(IF($A$1=40391,SUM(C24:J24),(IF($A$1=40422,SUM(C24:K24),(IF($A$1=40452,SUM(C24:L24),(IF($A$1=40483,SUM(C24:M24))))))))))+(IF($A$1=40513,SUM(C24:N24),0)) -> 0 | Q24: =(IF($A$1=40179,C24,(IF($A$1=40210,D24,(IF($A$1=40238,E24,(IF($A$1=40269,F24,(IF($A$1=40299,G24,(IF($A$1=40330,H24,(IF($A$1=40360,I24,0)))))))))))))+(IF($A$1=40391,J24,(IF($A$1=40422,K24,(IF($A$1=40452,L24,(IF($A$1=40483,M24)))))))))+(IF($A$1=40513,N24,0)) -> 0
A25: R&M DATA PROCESSING | B25: 53252601 | C25: 0 | D25: 0 | E25: 0 | F25: 0 | G25: 0 | H25: 0 | I25: 0 | J25: 0 | K25: 0 | L25: 0 | M25: 0 | N25: 0 | O25: 0 | P25: =(IF($A$1=40179,C25,(IF($A$1=40210,SUM(C25:D25),(IF($A$1=40238,SUM(C25:E25),(IF($A$1=40269,SUM(C25:F25),(IF($A$1=40299,SUM(C25:G25),(IF($A$1=40330,SUM(C25:H25),(IF($A$1=40360,SUM(C25:I25),0)))))))))))))+(IF($A$1=40391,SUM(C25:J25),(IF($A$1=40422,SUM(C25:K25),(IF($A$1=40452,SUM(C25:L25),(IF($A$1=40483,SUM(C25:M25))))))))))+(IF($A$1=40513,SUM(C25:N25),0)) -> 0 | Q25: =(IF($A$1=40179,C25,(IF($A$1=40210,D25,(IF($A$1=40238,E25,(IF($A$1=40269,F25,(IF($A$1=40299,G25,(IF($A$1=40330,H25,(IF($A$1=40360,I25,0)))))))))))))+(IF($A$1=40391,J25,(IF($A$1=40422,K25,(IF($A$1=40452,L25,(IF($A$1=40483,M25)))))))))+(IF($A$1=40513,N25,0)) -> 0
A26: R&M TELEPHONE | B26: 53252603 | C26: 29.374709 | D26: 15.100235 | E26: 33.209819 | F26: 40.453905 | G26: 120.16145 | H26: 0 | I26: 0 | J26: 1532.6831 | K26: 1577.9928 | L26: 1553.3432 | M26: 1485.7035 | N26: 1074.5974 | O26: 7462.6202 | P26: =(IF($A$1=40179,C26,(IF($A$1=40210,SUM(C26:D26),(IF($A$1=40238,SUM(C26:E26),(IF($A$1=40269,SUM(C26:F26),(IF($A$1=40299,SUM(C26:G26),(IF($A$1=40330,SUM(C26:H26),(IF($A$1=40360,SUM(C26:I26),0)))))))))))))+(IF($A$1=40391,SUM(C26:J26),(IF($A$1=40422,SUM(C26:K26),(IF($A$1=40452,SUM(C26:L26),(IF($A$1=40483,SUM(C26:M26))))))))))+(IF($A$1=40513,SUM(C26:N26),0)) -> 0 | Q26: =(IF($A$1=40179,C26,(IF($A$1=40210,D26,(IF($A$1=40238,E26,(IF($A$1=40269,F26,(IF($A$1=40299,G26,(IF($A$1=40330,H26,(IF($A$1=40360,I26,0)))))))))))))+(IF($A$1=40391,J26,(IF($A$1=40422,K26,(IF($A$1=40452,L26,(IF($A$1=40483,M26)))))))))+(IF($A$1=40513,N26,0)) -> 0
A27: R&M KITCHEN EQUIP. | B27: 53252703 | C27: 18610.98 | D27: 7247.7121 | E27: 5707.4428 | F27: 12222.516 | G27: 5623.8033 | H27: 6509.5046 | I27: 15311.566 | J27: 21902.26 | K27: 18614.51 | L27: 19231.518 | M27: 20212.925 | N27: 15102.401 | O27: 166297.14 | P27: =(IF($A$1=40179,C27,(IF($A$1=40210,SUM(C27:D27),(IF($A$1=40238,SUM(C27:E27),(IF($A$1=40269,SUM(C27:F27),(IF($A$1=40299,SUM(C27:G27),(IF($A$1=40330,SUM(C27:H27),(IF($A$1=40360,SUM(C27:I27),0)))))))))))))+(IF($A$1=40391,SUM(C27:J27),(IF($A$1=40422,SUM(C27:K27),(IF($A$1=40452,SUM(C27:L27),(IF($A$1=40483,SUM(C27:M27))))))))))+(IF($A$1=40513,SUM(C27:N27),0)) -> 0 | Q27: =(IF($A$1=40179,C27,(IF($A$1=40210,D27,(IF($A$1=40238,E27,(IF($A$1=40269,F27,(IF($A$1=40299,G27,(IF($A$1=40330,H27,(IF($A$1=40360,I27,0)))))))))))))+(IF($A$1=40391,J27,(IF($A$1=40422,K27,(IF($A$1=40452,L27,(IF($A$1=40483,M27)))))))))+(IF($A$1=40513,N27,0)) -> 0
A28: R&M LAUNDRY & VALET | B28: 53252704 | C28: 5275.9524 | D28: 3912.9834 | E28: 5168.9448 | F28: 3995.7884 | G28: 23112.428 | H28: 3000 | I28: 25530.47 | J28: 10393.274 | K28: 10317.215 | L28: 10411.437 | M28: 8163.5282 | N28: 8407.809 | O28: 117689.83 | P28: =(IF($A$1=40179,C28,(IF($A$1=40210,SUM(C28:D28),(IF($A$1=40238,SUM(C28:E28),(IF($A$1=40269,SUM(C28:F28),(IF($A$1=40299,SUM(C28:G28),(IF($A$1=40330,SUM(C28:H28),(IF($A$1=40360,SUM(C28:I28),0)))))))))))))+(IF($A$1=40391,SUM(C28:J28),(IF($A$1=40422,SUM(C28:K28),(IF($A$1=40452,SUM(C28:L28),(IF($A$1=40483,SUM(C28:M28))))))))))+(IF($A$1=40513,SUM(C28:N28),0)) -> 0 | Q28: =(IF($A$1=40179,C28,(IF($A$1=40210,D28,(IF($A$1=40238,E28,(IF($A$1=40269,F28,(IF($A$1=40299,G28,(IF($A$1=40330,H28,(IF($A$1=40360,I28,0)))))))))))))+(IF($A$1=40391,J28,(IF($A$1=40422,K28,(IF($A$1=40452,L28,(IF($A$1=40483,M28)))))))))+(IF($A$1=40513,N28,0)) -> 0
A29: R&M MINIBARS | B29: 53252705 | C29: 79.899208 | D29: 0 | E29: 0 | F29: 0 | G29: 0 | H29: 0 | I29: 0 | J29: 95.285728 | K29: 102.18196 | L29: 111.19935 | M29: 111.86032 | N29: 108.77325 | O29: 609.19982 | P29: =(IF($A$1=40179,C29,(IF($A$1=40210,SUM(C29:D29),(IF($A$1=40238,SUM(C29:E29),(IF($A$1=40269,SUM(C29:F29),(IF($A$1=40299,SUM(C29:G29),(IF($A$1=40330,SUM(C29:H29),(IF($A$1=40360,SUM(C29:I29),0)))))))))))))+(IF($A$1=40391,SUM(C29:J29),(IF($A$1=40422,SUM(C29:K29),(IF($A$1=40452,SUM(C29:L29),(IF($A$1=40483,SUM(C29:M29))))))))))+(IF($A$1=40513,SUM(C29:N29),0)) -> 0 | Q29: =(IF($A$1=40179,C29,(IF($A$1=40210,D29,(IF($A$1=40238,E29,(IF($A$1=40269,F29,(IF($A$1=40299,G29,(IF($A$1=40330,H29,(IF($A$1=40360,I29,0)))))))))))))+(IF($A$1=40391,J29,(IF($A$1=40422,K29,(IF($A$1=40452,L29,(IF($A$1=40483,M29)))))))))+(IF($A$1=40513,N29,0)) -> 0
A30: R&M REFRIGERATION | B30: 53252706 | C30: 0 | D30: 0 | E30: 0 | F30: 0 | G30: 274.098 | H30: 0 | I30: 0 | J30: 3304.6661 | K30: 3307.9378 | L30: 3323.0619 | M30: 3118.4419 | N30: 2387.0892 | O30: 15715.295 | P30: =(IF($A$1=40179,C30,(IF($A$1=40210,SUM(C30:D30),(IF($A$1=40238,SUM(C30:E30),(IF($A$1=40269,SUM(C30:F30),(IF($A$1=40299,SUM(C30:G30),(IF($A$1=40330,SUM(C30:H30),(IF($A$1=40360,SUM(C30:I30),0)))))))))))))+(IF($A$1=40391,SUM(C30:J30),(IF($A$1=40422,SUM(C30:K30),(IF($A$1=40452,SUM(C30:L30),(IF($A$1=40483,SUM(C30:M30))))))))))+(IF($A$1=40513,SUM(C30:N30),0)) -> 0 | Q30: =(IF($A$1=40179,C30,(IF($A$1=40210,D30,(IF($A$1=40238,E30,(IF($A$1=40269,F30,(IF($A$1=40299,G30,(IF($A$1=40330,H30,(IF($A$1=40360,I30,0)))))))))))))+(IF($A$1=40391,J30,(IF($A$1=40422,K30,(IF($A$1=40452,L30,(IF($A$1=40483,M30)))))))))+(IF($A$1=40513,N30,0)) -> 0
A31: R&M SPRINGS , MATTRESS | B31: 53252707 | C31: 0 | D31: 0 | E31: 0 | F31: 0 | G31: 0 | H31: 0 | I31: 0 | J31: 43.311695 | K31: 52.252139 | L31: 49.058539 | M31: 49.35014 | N31: 47.522294 | O31: 241.49481 | P31: =(IF($A$1=40179,C31,(IF($A$1=40210,SUM(C31:D31),(IF($A$1=40238,SUM(C31:E31),(IF($A$1=40269,SUM(C31:F31),(IF($A$1=40299,SUM(C31:G31),(IF($A$1=40330,SUM(C31:H31),(IF($A$1=40360,SUM(C31:I31),0)))))))))))))+(IF($A$1=40391,SUM(C31:J31),(IF($A$1=40422,SUM(C31:K31),(IF($A$1=40452,SUM(C31:L31),(IF($A$1=40483,SUM(C31:M31))))))))))+(IF($A$1=40513,SUM(C31:N31),0)) -> 0 | Q31: =(IF($A$1=40179,C31,(IF($A$1=40210,D31,(IF($A$1=40238,E31,(IF($A$1=40269,F31,(IF($A$1=40299,G31,(IF($A$1=40330,H31,(IF($A$1=40360,I31,0)))))))))))))+(IF($A$1=40391,J31,(IF($A$1=40422,K31,(IF($A$1=40452,L31,(IF($A$1=40483,M31)))))))))+(IF($A$1=40513,N31,0)) -> 0
A32: R&M T.V & VIDEOS&Singn&Elevator | B32: 53252708 | C32: 26271.989 | D32: 24991.55 | E32: 25766.444 | F32: 14083.458 | G32: 32760.542 | H32: 30820.265 | I32: 27093.718 | J32: 32921.826 | K32: 34279.573 | L32: 31548.543 | M32: 31011.051 | N32: 25248.971 | O32: 336797.93 | P32: =(IF($A$1=40179,C32,(IF($A$1=40210,SUM(C32:D32),(IF($A$1=40238,SUM(C32:E32),(IF($A$1=40269,SUM(C32:F32),(IF($A$1=40299,SUM(C32:G32),(IF($A$1=40330,SUM(C32:H32),(IF($A$1=40360,SUM(C32:I32),0)))))))))))))+(IF($A$1=40391,SUM(C32:J32),(IF($A$1=40422,SUM(C32:K32),(IF($A$1=40452,SUM(C32:L32),(IF($A$1=40483,SUM(C32:M32))))))))))+(IF($A$1=40513,SUM(C32:N32),0)) -> 0 | Q32: =(IF($A$1=40179,C32,(IF($A$1=40210,D32,(IF($A$1=40238,E32,(IF($A$1=40269,F32,(IF($A$1=40299,G32,(IF($A$1=40330,H32,(IF($A$1=40360,I32,0)))))))))))))+(IF($A$1=40391,J32,(IF($A$1=40422,K32,(IF($A$1=40452,L32,(IF($A$1=40483,M32)))))))))+(IF($A$1=40513,N32,0)) -> 0
A33: R&M A/C | B33: 53252801 | C33: 7155.9338 | D33: 13666.574 | E33: 13288.173 | F33: 18794.657 | G33: 26304.825 | H33: 33052.365 | I33: 42520.56 | J33: 22963.856 | K33: 23657.049 | L33: 21575.007 | M33: 16832.206 | N33: 15606.795 | O33: 255418 | P33: =(IF($A$1=40179,C33,(IF($A$1=40210,SUM(C33:D33),(IF($A$1=40238,SUM(C33:E33),(IF($A$1=40269,SUM(C33:F33),(IF($A$1=40299,SUM(C33:G33),(IF($A$1=40330,SUM(C33:H33),(IF($A$1=40360,SUM(C33:I33),0)))))))))))))+(IF($A$1=40391,SUM(C33:J33),(IF($A$1=40422,SUM(C33:K33),(IF($A$1=40452,SUM(C33:L33),(IF($A$1=40483,SUM(C33:M33))))))))))+(IF($A$1=40513,SUM(C33:N33),0)) -> 0 | Q33: =(IF($A$1=40179,C33,(IF($A$1=40210,D33,(IF($A$1=40238,E33,(IF($A$1=40269,F33,(IF($A$1=40299,G33,(IF($A$1=40330,H33,(IF($A$1=40360,I33,0)))))))))))))+(IF($A$1=40391,J33,(IF($A$1=40422,K33,(IF($A$1=40452,L33,(IF($A$1=40483,M33)))))))))+(IF($A$1=40513,N33,0)) -> 0
... A47: TRAVEL EXP. | B47: 53254201 | C47: 3803.5222 | D47: 2648.7794 | E47: 2552.6776 | F47: 3045.5154 | G47: 2357.4996 | H47: 2726.555 | I47: 2399.97 | J47: 5298.415 | K47: 4970.582 | L47: 5021.71 | M47: 4955.644 | N47: 3934.47 | O47: 43715.34 | P47: =(IF($A$1=40179,C47,(IF($A$1=40210,SUM(C47:D47),(IF($A$1=40238,SUM(C47:E47),(IF($A$1=40269,SUM(C47:F47),(IF($A$1=40299,SUM(C47:G47),(IF($A$1=40330,SUM(C47:H47),(IF($A$1=40360,SUM(C47:I47),0)))))))))))))+(IF($A$1=40391,SUM(C47:J47),(IF($A$1=40422,SUM(C47:K47),(IF($A$1=40452,SUM(C47:L47),(IF($A$1=40483,SUM(C47:M47))))))))))+(IF($A$1=40513,SUM(C47:N47),0)) -> 0 | Q47: =(IF($A$1=40179,C47,(IF($A$1=40210,D47,(IF($A$1=40238,E47,(IF($A$1=40269,F47,(IF($A$1=40299,G47,(IF($A$1=40330,H47,(IF($A$1=40360,I47,0)))))))))))))+(IF($A$1=40391,J47,(IF($A$1=40422,K47,(IF($A$1=40452,L47,(IF($A$1=40483,M47)))))))))+(IF($A$1=40513,N47,0)) -> 0
A48: DATA PROCESSING | C48: 0 | D48: 0 | E48: 0 | F48: 0 | G48: 0 | H48: 0 | I48: 0 | J48: 0 | K48: 0 | L48: 0 | M48: 0 | N48: 0 | O48: 0 | P48: =(IF($A$1=40179,C48,(IF($A$1=40210,SUM(C48:D48),(IF($A$1=40238,SUM(C48:E48),(IF($A$1=40269,SUM(C48:F48),(IF($A$1=40299,SUM(C48:G48),(IF($A$1=40330,SUM(C48:H48),(IF($A$1=40360,SUM(C48:I48),0)))))))))))))+(IF($A$1=40391,SUM(C48:J48),(IF($A$1=40422,SUM(C48:K48),(IF($A$1=40452,SUM(C48:L48),(IF($A$1=40483,SUM(C48:M48))))))))))+(IF($A$1=40513,SUM(C48:N48),0)) -> 0 | Q48: =(IF($A$1=40179,C48,(IF($A$1=40210,D48,(IF($A$1=40238,E48,(IF($A$1=40269,F48,(IF($A$1=40299,G48,(IF($A$1=40330,H48,(IF($A$1=40360,I48,0)))))))))))))+(IF($A$1=40391,J48,(IF($A$1=40422,K48,(IF($A$1=40452,L48,(IF($A$1=40483,M48)))))))))+(IF($A$1=40513,N48,0)) -> 0
A49: TELEPHONE | B49: 53255308 | C49: 3220.6431 | D49: 3431.238 | E49: 3826.0002 | F49: 2718.7099 | G49: 2041.662 | H49: 1621.007 | I49: 2137.2499 | J49: 2579.049 | K49: 2552.517 | L49: 2585.385 | M49: 2542.914 | N49: 1886.445 | O49: 31142.82 | P49: =(IF($A$1=40179,C49,(IF($A$1=40210,SUM(C49:D49),(IF($A$1=40238,SUM(C49:E49),(IF($A$1=40269,SUM(C49:F49),(IF($A$1=40299,SUM(C49:G49),(IF($A$1=40330,SUM(C49:H49),(IF($A$1=40360,SUM(C49:I49),0)))))))))))))+(IF($A$1=40391,SUM(C49:J49),(IF($A$1=40422,SUM(C49:K49),(IF($A$1=40452,SUM(C49:L49),(IF($A$1=40483,SUM(C49:M49))))))))))+(IF($A$1=40513,SUM(C49:N49),0)) -> 0 | Q49: =(IF($A$1=40179,C49,(IF($A$1=40210,D49,(IF($A$1=40238,E49,(IF($A$1=40269,F49,(IF($A$1=40299,G49,(IF($A$1=40330,H49,(IF($A$1=40360,I49,0)))))))))))))+(IF($A$1=40391,J49,(IF($A$1=40422,K49,(IF($A$1=40452,L49,(IF($A$1=40483,M49)))))))))+(IF($A$1=40513,N49,0)) -> 0
A50: LICENCE | B50: 53255799 | C50: 0 | D50: 1138.3254 | E50: 0 | F50: 0 | G50: 0 | H50: 0 | I50: 0 | J50: 64.967542 | K50: 69.669519 | L50: 65.411385 | M50: 65.800186 | N50: 63.363059 | O50: 1467.5371 | P50: =(IF($A$1=40179,C50,(IF($A$1=40210,SUM(C50:D50),(IF($A$1=40238,SUM(C50:E50),(IF($A$1=40269,SUM(C50:F50),(IF($A$1=40299,SUM(C50:G50),(IF($A$1=40330,SUM(C50:H50),(IF($A$1=40360,SUM(C50:I50),0)))))))))))))+(IF($A$1=40391,SUM(C50:J50),(IF($A$1=40422,SUM(C50:K50),(IF($A$1=40452,SUM(C50:L50),(IF($A$1=40483,SUM(C50:M50))))))))))+(IF($A$1=40513,SUM(C50:N50),0)) -> 0 | Q50: =(IF($A$1=40179,C50,(IF($A$1=40210,D50,(IF($A$1=40238,E50,(IF($A$1=40269,F50,(IF($A$1=40299,G50,(IF($A$1=40330,H50,(IF($A$1=40360,I50,0)))))))))))))+(IF($A$1=40391,J50,(IF($A$1=40422,K50,(IF($A$1=40452,L50,(IF($A$1=40483,M50)))))))))+(IF($A$1=40513,N50,0)) -> 0
A51: ALLOCATED EXP. | B51: 60-300-143 | C51: 0 | D51: 0 | E51: 0 | F51: 0 | G51: 0 | H51: 0 | I51: 0 | J51: 0 | K51: 0 | L51: 0 | M51: 0 | N51: 0 | O51: 0 | P51: =(IF($A$1=40179,C51,(IF($A$1=40210,SUM(C51:D51),(IF($A$1=40238,SUM(C51:E51),(IF($A$1=40269,SUM(C51:F51),(IF($A$1=40299,SUM(C51:G51),(IF($A$1=40330,SUM(C51:H51),(IF($A$1=40360,SUM(C51:I51),0)))))))))))))+(IF($A$1=40391,SUM(C51:J51),(IF($A$1=40422,SUM(C51:K51),(IF($A$1=40452,SUM(C51:L51),(IF($A$1=40483,SUM(C51:M51))))))))))+(IF($A$1=40513,SUM(C51:N51),0)) -> 0 | Q51: =(IF($A$1=40179,C51,(IF($A$1=40210,D51,(IF($A$1=40238,E51,(IF($A$1=40269,F51,(IF($A$1=40299,G51,(IF($A$1=40330,H51,(IF($A$1=40360,I51,0)))))))))))))+(IF($A$1=40391,J51,(IF($A$1=40422,K51,(IF($A$1=40452,L51,(IF($A$1=40483,M51)))))))))+(IF($A$1=40513,N51,0)) -> 0
A52: LAUNDRY | B52: 53257201 | C52: 3299.3673 | D52: 3398.7144 | E52: 3454.9664 | F52: 3663.6716 | G52: 3888.4677 | H52: 3828.3628 | I52: 3852.9614 | J52: 3943.9156 | K52: 4100.3771 | L52: 3864.66 | M52: 3853.7423 | N52: 3406.3851 | O52: 44555.592 | P52: =(IF($A$1=40179,C52,(IF($A$1=40210,SUM(C52:D52),(IF($A$1=40238,SUM(C52:E52),(IF($A$1=40269,SUM(C52:F52),(IF($A$1=40299,SUM(C52:G52),(IF($A$1=40330,SUM(C52:H52),(IF($A$1=40360,SUM(C52:I52),0)))))))))))))+(IF($A$1=40391,SUM(C52:J52),(IF($A$1=40422,SUM(C52:K52),(IF($A$1=40452,SUM(C52:L52),(IF($A$1=40483,SUM(C52:M52))))))))))+(IF($A$1=40513,SUM(C52:N52),0)) -> 0 | Q52: =(IF($A$1=40179,C52,(IF($A$1=40210,D52,(IF($A$1=40238,E52,(IF($A$1=40269,F52,(IF($A$1=40299,G52,(IF($A$1=40330,H52,(IF($A$1=40360,I52,0)))))))))))))+(IF($A$1=40391,J52,(IF($A$1=40422,K52,(IF($A$1=40452,L52,(IF($A$1=40483,M52)))))))))+(IF($A$1=40513,N52,0)) -> 0
A53: SUPP. TOOLS | B53: 53257498 | C53: 0 | D53: 0 | E53: 0 | F53: 0 | G53: 0 | H53: 221.58981 | I53: 55.885854 | J53: 2436.0121 | K53: 2590.2547 | L53: 2489.4483 | M53: 2183.0308 | N53: 1083.2971 | O53: 11059.519 | P53: =(IF($A$1=40179,C53,(IF($A$1=40210,SUM(C53:D53),(IF($A$1=40238,SUM(C53:E53),(IF($A$1=40269,SUM(C53:F53),(IF($A$1=40299,SUM(C53:G53),(IF($A$1=40330,SUM(C53:H53),(IF($A$1=40360,SUM(C53:I53),0)))))))))))))+(IF($A$1=40391,SUM(C53:J53),(IF($A$1=40422,SUM(C53:K53),(IF($A$1=40452,SUM(C53:L53),(IF($A$1=40483,SUM(C53:M53))))))))))+(IF($A$1=40513,SUM(C53:N53),0)) -> 0 | Q53: =(IF($A$1=40179,C53,(IF($A$1=40210,D53,(IF($A$1=40238,E53,(IF($A$1=40269,F53,(IF($A$1=40299,G53,(IF($A$1=40330,H53,(IF($A$1=40360,I53,0)))))))))))))+(IF($A$1=40391,J53,(IF($A$1=40422,K53,(IF($A$1=40452,L53,(IF($A$1=40483,M53)))))))))+(IF($A$1=40513,N53,0)) -> 0
A54: UNIFORMS | B54: 53257814 | C54: 4376 | D54: 4376 | E54: 4376 | F54: 4376 | G54: 4376 | H54: 4376 | I54: 4376 | J54: 4376 | K54: 4376 | L54: 4376 | M54: 4376 | N54: 4376 | O54: 52512 | P54: =(IF($A$1=40179,C54,(IF($A$1=40210,SUM(C54:D54),(IF($A$1=40238,SUM(C54:E54),(IF($A$1=40269,SUM(C54:F54),(IF($A$1=40299,SUM(C54:G54),(IF($A$1=40330,SUM(C54:H54),(IF($A$1=40360,SUM(C54:I54),0)))))))))))))+(IF($A$1=40391,SUM(C54:J54),(IF($A$1=40422,SUM(C54:K54),(IF($A$1=40452,SUM(C54:L54),(IF($A$1=40483,SUM(C54:M54))))))))))+(IF($A$1=40513,SUM(C54:N54),0)) -> 0 | Q54: =(IF($A$1=40179,C54,(IF($A$1=40210,D54,(IF($A$1=40238,E54,(IF($A$1=40269,F54,(IF($A$1=40299,G54,(IF($A$1=40330,H54,(IF($A$1=40360,I54,0)))))))))))))+(IF($A$1=40391,J54,(IF($A$1=40422,K54,(IF($A$1=40452,L54,(IF($A$1=40483,M54)))))))))+(IF($A$1=40513,N54,0)) -> 0
A55: RUBBISH REMOVAL | B55: 53258201 | C55: 453.992 | D55: 2255.3123 | E55: 588.478 | F55: 829.554 | G55: 1128.3963 | H55: 323.88675 | I55: 559.988 | J55: 7020.7445 | K55: 6948.5185 | L55: 7037.9925 | M55: 6922.377 | N55: 5135.3225 | O55: 39204.562 | P55: =(IF($A$1=40179,C55,(IF($A$1=40210,SUM(C55:D55),(IF($A$1=40238,SUM(C55:E55),(IF($A$1=40269,SUM(C55:F55),(IF($A$1=40299,SUM(C55:G55),(IF($A$1=40330,SUM(C55:H55),(IF($A$1=40360,SUM(C55:I55),0)))))))))))))+(IF($A$1=40391,SUM(C55:J55),(IF($A$1=40422,SUM(C55:K55),(IF($A$1=40452,SUM(C55:L55),(IF($A$1=40483,SUM(C55:M55))))))))))+(IF($A$1=40513,SUM(C55:N55),0)) -> 0 | Q55: =(IF($A$1=40179,C55,(IF($A$1=40210,D55,(IF($A$1=40238,E55,(IF($A$1=40269,F55,(IF($A$1=40299,G55,(IF($A$1=40330,H55,(IF($A$1=40360,I55,0)))))))))))))+(IF($A$1=40391,J55,(IF($A$1=40422,K55,(IF($A$1=40452,L55,(IF($A$1=40483,M55)))))))))+(IF($A$1=40513,N55,0)) -> 0
A56: SUPP. CLEANING | B56: 53258402 | C56: 2050.3547 | D56: 1148.7794 | E56: 1691.4105 | F56: 1208.4308 | G56: 1876.0341 | H56: 2458.9932 | I56: 2102.7674 | J56: 2579.049 | K56: 2552.517 | L56: 2585.385 | M56: 2542.914 | N56: 1886.445 | O56: 24683.08 | P56: =(IF($A$1=40179,C56,(IF($A$1=40210,SUM(C56:D56),(IF($A$1=40238,SUM(C56:E56),(IF($A$1=40269,SUM(C56:F56),(IF($A$1=40299,SUM(C56:G56),(IF($A$1=40330,SUM(C56:H56),(IF($A$1=40360,SUM(C56:I56),0)))))))))))))+(IF($A$1=40391,SUM(C56:J56),(IF($A$1=40422,SUM(C56:K56),(IF($A$1=40452,SUM(C56:L56),(IF($A$1=40483,SUM(C56:M56))))))))))+(IF($A$1=40513,SUM(C56:N56),0)) -> 0 | Q56: =(IF($A$1=40179,C56,(IF($A$1=40210,D56,(IF($A$1=40238,E56,(IF($A$1=40269,F56,(IF($A$1=40299,G56,(IF($A$1=40330,H56,(IF($A$1=40360,I56,0)))))))))))))+(IF($A$1=40391,J56,(IF($A$1=40422,K56,(IF($A$1=40452,L56,(IF($A$1=40483,M56)))))))))+(IF($A$1=40513,N56,0)) -> 0
A57: ELECTRIC BULBS&R.M Electreical | B57: 53258403 | C57: 6986.4807 | D57: 5398.9148 | E57: 4490.1966 | F57: 5754.8273 | G57: 7546.3553 | H57: 20454.424 | I57: 10212.744 | J57: 17235.817 | K57: 16638.924 | L57: 15327.741 | M57: 15931.17 | N57: 12126.666 | O57: 138104.26 | P57: =(IF($A$1=40179,C57,(IF($A$1=40210,SUM(C57:D57),(IF($A$1=40238,SUM(C57:E57),(IF($A$1=40269,SUM(C57:F57),(IF($A$1=40299,SUM(C57:G57),(IF($A$1=40330,SUM(C57:H57),(IF($A$1=40360,SUM(C57:I57),0)))))))))))))+(IF($A$1=40391,SUM(C57:J57),(IF($A$1=40422,SUM(C57:K57),(IF($A$1=40452,SUM(C57:L57),(IF($A$1=40483,SUM(C57:M57))))))))))+(IF($A$1=40513,SUM(C57:N57),0)) -> 0 | Q57: =(IF($A$1=40179,C57,(IF($A$1=40210,D57,(IF($A$1=40238,E57,(IF($A$1=40269,F57,(IF($A$1=40299,G57,(IF($A$1=40330,H57,(IF($A$1=40360,I57,0)))))))))))))+(IF($A$1=40391,J57,(IF($A$1=40422,K57,(IF($A$1=40452,L57,(IF($A$1=40483,M57)))))))))+(IF($A$1=40513,N57,0)) -> 0
A58: Safty | B58: 53258404 | C58: 3349.8918 | D58: 4340.7368 | E58: 11679.55 | F58: 6561.8309 | G58: 9199.3871 | H58: 3376.2975 | I58: 3522.7853 | J58: 4298.415 | K58: 4254.195 | L58: 4308.975 | M58: 4238.19 | N58: 3144.075 | O58: 62274.329 | P58: =(IF($A$1=40179,C58,(IF($A$1=40210,SUM(C58:D58),(IF($A$1=40238,SUM(C58:E58),(IF($A$1=40269,SUM(C58:F58),(IF($A$1=40299,SUM(C58:G58),(IF($A$1=40330,SUM(C58:H58),(IF($A$1=40360,SUM(C58:I58),0)))))))))))))+(IF($A$1=40391,SUM(C58:J58),(IF($A$1=40422,SUM(C58:K58),(IF($A$1=40452,SUM(C58:L58),(IF($A$1=40483,SUM(C58:M58))))))))))+(IF($A$1=40513,SUM(C58:N58),0)) -> 0 | Q58: =(IF($A$1=40179,C58,(IF($A$1=40210,D58,(IF($A$1=40238,E58,(IF($A$1=40269,F58,(IF($A$1=40299,G58,(IF($A$1=40330,H58,(IF($A$1=40360,I58,0)))))))))))))+(IF($A$1=40391,J58,(IF($A$1=40422,K58,(IF($A$1=40452,L58,(IF($A$1=40483,M58)))))))))+(IF($A$1=40513,N58,0)) -> 0
A59: SUPP. MECHANICAL | B59: 53258405 | C59: 0 | D59: 0 | E59: 0 | F59: 0 | G59: 0 | H59: 232.6693 | I59: 8.2224942 | J59: 263.44338 | K59: 290.87024 | L59: 273.63763 | M59: 241.57442 | N59: 167.86986 | O59: 1478.2873 | P59: =(IF($A$1=40179,C59,(IF($A$1=40210,SUM(C59:D59),(IF($A$1=40238,SUM(C59:E59),(IF($A$1=40269,SUM(C59:F59),(IF($A$1=40299,SUM(C59:G59),(IF($A$1=40330,SUM(C59:H59),(IF($A$1=40360,SUM(C59:I59),0)))))))))))))+(IF($A$1=40391,SUM(C59:J59),(IF($A$1=40422,SUM(C59:K59),(IF($A$1=40452,SUM(C59:L59),(IF($A$1=40483,SUM(C59:M59))))))))))+(IF($A$1=40513,SUM(C59:N59),0)) -> 0 | Q59: =(IF($A$1=40179,C59,(IF($A$1=40210,D59,(IF($A$1=40238,E59,(IF($A$1=40269,F59,(IF($A$1=40299,G59,(IF($A$1=40330,H59,(IF($A$1=40360,I59,0)))))))))))))+(IF($A$1=40391,J59,(IF($A$1=40422,K59,(IF($A$1=40452,L59,(IF($A$1=40483,M59)))))))))+(IF($A$1=40513,N59,0)) -> 0
A60: PAINTING & DECORATION | B60: 53258510 | C60: 0 | D60: 7796.3675 | E60: 3412.5952 | F60: 9297.1372 | G60: 5217.8213 | H60: 5608.6819 | I60: 5213.7503 | J60: 17616.944 | K60: 18321.305 | L60: 18209.508 | M60: 17587.288 | N60: 12427.274 | O60: 120708.67 | P60: =(IF($A$1=40179,C60,(IF($A$1=40210,SUM(C60:D60),(IF($A$1=40238,SUM(C60:E60),(IF($A$1=40269,SUM(C60:F60),(IF($A$1=40299,SUM(C60:G60),(IF($A$1=40330,SUM(C60:H60),(IF($A$1=40360,SUM(C60:I60),0)))))))))))))+(IF($A$1=40391,SUM(C60:J60),(IF($A$1=40422,SUM(C60:K60),(IF($A$1=40452,SUM(C60:L60),(IF($A$1=40483,SUM(C60:M60))))))))))+(IF($A$1=40513,SUM(C60:N60),0)) -> 0 | Q60: =(IF($A$1=40179,C60,(IF($A$1=40210,D60,(IF($A$1=40238,E60,(IF($A$1=40269,F60,(IF($A$1=40299,G60,(IF($A$1=40330,H60,(IF($A$1=40360,I60,0)))))))))))))+(IF($A$1=40391,J60,(IF($A$1=40422,K60,(IF($A$1=40452,L60,(IF($A$1=40483,M60)))))))))+(IF($A$1=40513,N60,0)) -> 0
A61: Medical Care | C61: 7031 | D61: 7225 | E61: 7031 | F61: 7225 | G61: 8128 | H61: 7802 | I61: 7700 | J61: 7955 | K61: 7939 | L61: 7347 | M61: 7319 | N61: 7423 | O61: 90125 | P61: =(IF($A$1=40179,C61,(IF($A$1=40210,SUM(C61:D61),(IF($A$1=40238,SUM(C61:E61),(IF($A$1=40269,SUM(C61:F61),(IF($A$1=40299,SUM(C61:G61),(IF($A$1=40330,SUM(C61:H61),(IF($A$1=40360,SUM(C61:I61),0)))))))))))))+(IF($A$1=40391,SUM(C61:J61),(IF($A$1=40422,SUM(C61:K61),(IF($A$1=40452,SUM(C61:L61),(IF($A$1=40483,SUM(C61:M61))))))))))+(IF($A$1=40513,SUM(C61:N61),0)) -> 0 | Q61: =(IF($A$1=40179,C61,(IF($A$1=40210,D61,(IF($A$1=40238,E61,(IF($A$1=40269,F61,(IF($A$1=40299,G61,(IF($A$1=40330,H61,(IF($A$1=40360,I61,0)))))))))))))+(IF($A$1=40391,J61,(IF($A$1=40422,K61,(IF($A$1=40452,L61,(IF($A$1=40483,M61)))))))))+(IF($A$1=40513,N61,0)) -> 0
A62: Employee Housing | C62: 23243.5 | D62: 23243.5 | E62: 23243.5 | F62: 23243.5 | G62: 23243.5 | H62: 23243.5 | I62: 23243.5 | J62: 23243.5 | K62: 23243.5 | L62: 23243.5 | M62: 23243.5 | N62: 23243.5 | O62: 278922 | P62: =(IF($A$1=40179,C62,(IF($A$1=40210,SUM(C62:D62),(IF($A$1=40238,SUM(C62:E62),(IF($A$1=40269,SUM(C62:F62),(IF($A$1=40299,SUM(C62:G62),(IF($A$1=40330,SUM(C62:H62),(IF($A$1=40360,SUM(C62:I62),0)))))))))))))+(IF($A$1=40391,SUM(C62:J62),(IF($A$1=40422,SUM(C62:K62),(IF($A$1=40452,SUM(C62:L62),(IF($A$1=40483,SUM(C62:M62))))))))))+(IF($A$1=40513,SUM(C62:N62),0)) -> 0 | Q62: =(IF($A$1=40179,C62,(IF($A$1=40210,D62,(IF($A$1=40238,E62,(IF($A$1=40269,F62,(IF($A$1=40299,G62,(IF($A$1=40330,H62,(IF($A$1=40360,I62,0)))))))))))))+(IF($A$1=40391,J62,(IF($A$1=40422,K62,(IF($A$1=40452,L62,(IF($A$1=40483,M62)))))))))+(IF($A$1=40513,N62,0)) -> 0
A63: TOTAL OTH EXP Cal. | C63: 341532.7 | D63: 345440.64 | O63: =SUM(C63:N63) -> 686973.34 | P63: =(IF($A$1=40179,C63,(IF($A$1=40210,SUM(C63:D63),(IF($A$1=40238,SUM(C63:E63),(IF($A$1=40269,SUM(C63:F63),(IF($A$1=40299,SUM(C63:G63),(IF($A$1=40330,SUM(C63:H63),(IF($A$1=40360,SUM(C63:I63),0)))))))))))))+(IF($A$1=40391,SUM(C63:J63),(IF($A$1=40422,SUM(C63:K63),(IF($A$1=40452,SUM(C63:L63),(IF($A$1=40483,SUM(C63:M63))))))))))+(IF($A$1=40513,SUM(C63:N63),0)) -> 0 | Q63: =(IF($A$1=40179,C63,(IF($A$1=40210,D63,(IF($A$1=40238,E63,(IF($A$1=40269,F63,(IF($A$1=40299,G63,(IF($A$1=40330,H63,(IF($A$1=40360,I63,0)))))))))))))+(IF($A$1=40391,J63,(IF($A$1=40422,K63,(IF($A$1=40452,L63,(IF($A$1=40483,M63)))))))))+(IF($A$1=40513,N63,0)) -> 0 | S63: 40452 | DE63: 10
A64: TOTAL OTH EXP. | C64: 341533 | D64: 345441 | O64: =SUM(C64:N64) -> 686974 | P64: =(IF($A$1=40179,C64,(IF($A$1=40210,SUM(C64:D64),(IF($A$1=40238,SUM(C64:E64),(IF($A$1=40269,SUM(C64:F64),(IF($A$1=40299,SUM(C64:G64),(IF($A$1=40330,SUM(C64:H64),(IF($A$1=40360,SUM(C64:I64),0)))))))))))))+(IF($A$1=40391,SUM(C64:J64),(IF($A$1=40422,SUM(C64:K64),(IF($A$1=40452,SUM(C64:L64),(IF($A$1=40483,SUM(C64:M64))))))))))+(IF($A$1=40513,SUM(C64:N64),0)) -> 0 | Q64: =(IF($A$1=40179,C64,(IF($A$1=40210,D64,(IF($A$1=40238,E64,(IF($A$1=40269,F64,(IF($A$1=40299,G64,(IF($A$1=40330,H64,(IF($A$1=40360,I64,0)))))))))))))+(IF($A$1=40391,J64,(IF($A$1=40422,K64,(IF($A$1=40452,L64,(IF($A$1=40483,M64)))))))))+(IF($A$1=40513,N64,0)) -> 0 | S64: 40483 | DE64: 11
A65: TOT. EXP. | C65: =C14+C64 -> 489365.84 | D65: =D14+D64 -> 504065 | E65: =E14+E64 -> 0 | F65: =F14+F64 -> 0 | G65: =G14+G64 -> 0 | H65: =H14+H64 -> 0 | I65: =I14+I64 -> 0 | J65: =J14+J64 -> 0 | ... O65: =O14+O64 -> 993430.84 | P65: =(IF($A$1=40179,C65,(IF($A$1=40210,SUM(C65:D65),(IF($A$1=40238,SUM(C65:E65),(IF($A$1=40269,SUM(C65:F65),(IF($A$1=40299,SUM(C65:G65),(IF($A$1=40330,SUM(C65:H65),(IF($A$1=40360,SUM(C65:I65),0)))))))))))))+(IF($A$1=40391,SUM(C65:J65),(IF($A$1=40422,SUM(C65:K65),(IF($A$1=40452,SUM(C65:L65),(IF($A$1=40483,SUM(C65:M65))))))))))+(IF($A$1=40513,SUM(C65:N65),0)) -> 0 | Q65: =(IF($A$1=40179,C65,(IF($A$1=40210,D65,(IF($A$1=40238,E65,(IF($A$1=40269,F65,(IF($A$1=40299,G65,(IF($A$1=40330,H65,(IF($A$1=40360,I65,0)))))))))))))+(IF($A$1=40391,J65,(IF($A$1=40422,K65,(IF($A$1=40452,L65,(IF($A$1=40483,M65)))))))))+(IF($A$1=40513,N65,0)) -> 0 | S65: 40513 | DE65: 12
A66: DEPT. EXPENSES | C66: =C19+C65 -> 1018116.9 | D66: =D19+D65 -> 1130359.7 | E66: =E19+E65 -> 0 | F66: =F19+F65 -> 0 | G66: =G19+G65 -> 0 | H66: =H19+H65 -> 0 | I66: =I19+I65 -> 0 | J66: =J19+J65 -> 0 | ... O66: =O19+O65 -> 2148476.6 | P66: =(IF($A$1=40179,C66,(IF($A$1=40210,SUM(C66:D66),(IF($A$1=40238,SUM(C66:E66),(IF($A$1=40269,SUM(C66:F66),(IF($A$1=40299,SUM(C66:G66),(IF($A$1=40330,SUM(C66:H66),(IF($A$1=40360,SUM(C66:I66),0)))))))))))))+(IF($A$1=40391,SUM(C66:J66),(IF($A$1=40422,SUM(C66:K66),(IF($A$1=40452,SUM(C66:L66),(IF($A$1=40483,SUM(C66:M66))))))))))+(IF($A$1=40513,SUM(C66:N66),0)) -> 0 | Q66: =(IF($A$1=40179,C66,(IF($A$1=40210,D66,(IF($A$1=40238,E66,(IF($A$1=40269,F66,(IF($A$1=40299,G66,(IF($A$1=40330,H66,(IF($A$1=40360,I66,0)))))))))))))+(IF($A$1=40391,J66,(IF($A$1=40422,K66,(IF($A$1=40452,L66,(IF($A$1=40483,M66)))))))))+(IF($A$1=40513,N66,0)) -> 0
A67: GROSS REV. | C67: -9127696.8 | D67: -8962592.4 | E67: -11948019 | F67: -11262665 | G67: -10044681 | H67: -8495470.5 | I67: -10251812 | J67: -12532073 | K67: -10857055 | L67: -12330933 | M67: -11053212 | N67: -9652677.5 | O67: -1.2651889e+08 | P67: -1.2651889e+08 | Q67: =(IF($A$1=40179,C67,(IF($A$1=40210,D67,(IF($A$1=40238,E67,(IF($A$1=40269,F67,(IF($A$1=40299,G67,(IF($A$1=40330,H67,(IF($A$1=40360,I67,0)))))))))))))+(IF($A$1=40391,J67,(IF($A$1=40422,K67,(IF($A$1=40452,L67,(IF($A$1=40483,M67)))))))))+(IF($A$1=40513,N67,0)) -> 0
Q68: =(IF($A$1=40179,C68,(IF($A$1=40210,D68,(IF($A$1=40238,E68,(IF($A$1=40269,F68,(IF($A$1=40299,G68,(IF($A$1=40330,H68,(IF($A$1=40360,I68,0)))))))))))))+(IF($A$1=40391,J68,(IF($A$1=40422,K68,(IF($A$1=40452,L68,(IF($A$1=40483,M68)))))))))+(IF($A$1=40513,N68,0)) -> 0
Q69: =(IF($A$1=40179,C69,(IF($A$1=40210,D69,(IF($A$1=40238,E69,(IF($A$1=40269,F69,(IF($A$1=40299,G69,(IF($A$1=40330,H69,(IF($A$1=40360,I69,0)))))))))))))+(IF($A$1=40391,J69,(IF($A$1=40422,K69,(IF($A$1=40452,L69,(IF($A$1=40483,M69)))))))))+(IF($A$1=40513,N69,0)) -> 0
A70: TOTAL HOTEL EXP. | C70: 4339688.7 | D70: 4402174.6 | E70: 4820027.1 | F70: 4798444.4 | G70: 4801586.5 | H70: 4583696.2 | I70: 5079828.8 | J70: 5224781 | K70: 5108244.5 | L70: 5240588.5 | M70: 5121633.1 | N70: 5022738.7 | O70: 58543432 | P70: 58543433 | Q70: =(IF($A$1=40179,C70,(IF($A$1=40210,D70,(IF($A$1=40238,E70,(IF($A$1=40269,F70,(IF($A$1=40299,G70,(IF($A$1=40330,H70,(IF($A$1=40360,I70,0)))))))))))))+(IF($A$1=40391,J70,(IF($A$1=40422,K70,(IF($A$1=40452,L70,(IF($A$1=40483,M70)))))))))+(IF($A$1=40513,N70,0)) -> 0
Q71: =(IF($A$1=40179,C71,(IF($A$1=40210,D71,(IF($A$1=40238,E71,(IF($A$1=40269,F71,(IF($A$1=40299,G71,(IF($A$1=40330,H71,(IF($A$1=40360,I71,0)))))))))))))+(IF($A$1=40391,J71,(IF($A$1=40422,K71,(IF($A$1=40452,L71,(IF($A$1=40483,M71)))))))))+(IF($A$1=40513,N71,0)) -> 0
A72: G.O.P. | C72: -4788008.1 | D72: -4560417.8 | E72: -7127992.3 | F72: -6464220.8 | G72: -5243094.1 | H72: -3911774.2 | I72: -5170982.8 | J72: -7307291.6 | K72: -5748810.9 | L72: -7090344.9 | M72: -5931579.3 | N72: -4629938.8 | O72: -67974456 | P72: -67974455 | Q72: =(IF($A$1=40179,C72,(IF($A$1=40210,D72,(IF($A$1=40238,E72,(IF($A$1=40269,F72,(IF($A$1=40299,G72,(IF($A$1=40330,H72,(IF($A$1=40360,I72,0)))))))))))))+(IF($A$1=40391,J72,(IF($A$1=40422,K72,(IF($A$1=40452,L72,(IF($A$1=40483,M72)))))))))+(IF($A$1=40513,N72,0)) -> 0
Q73: =(IF($A$1=40179,C73,(IF($A$1=40210,D73,(IF($A$1=40238,E73,(IF($A$1=40269,F73,(IF($A$1=40299,G73,(IF($A$1=40330,H73,(IF($A$1=40360,I73,0)))))))))))))+(IF($A$1=40391,J73,(IF($A$1=40422,K73,(IF($A$1=40452,L73,(IF($A$1=40483,M73)))))))))+(IF($A$1=40513,N73,0)) -> 0
C74: 20636 | D74: 22021 | E74: 26749 | F74: 25138 | G74: 24918 | H74: 22301 | I74: 25454 | J74: 26051 | K74: 25783 | L74: 26115 | M74: 25686 | N74: 19055 | O74: 289907 | P74: 289908 | Q74: =(IF($A$1=40179,C74,(IF($A$1=40210,D74,(IF($A$1=40238,E74,(IF($A$1=40269,F74,(IF($A$1=40299,G74,(IF($A$1=40330,H74,(IF($A$1=40360,I74,0)))))))))))))+(IF($A$1=40391,J74,(IF($A$1=40422,K74,(IF($A$1=40452,L74,(IF($A$1=40483,M74)))))))))+(IF($A$1=40513,N74,0)) -> 0
C75: 11.586234 | D75: 10.630652 | E75: 9.1936995 | F75: 9.789965 | G75: 13.270516 | H75: 16.399437 | I75: 17.267995 | J75: 16.028578 | Q75: =(IF($A$1=40179,C75,(IF($A$1=40210,D75,(IF($A$1=40238,E75,(IF($A$1=40269,F75,(IF($A$1=40299,G75,(IF($A$1=40330,H75,(IF($A$1=40360,I75,0)))))))))))))+(IF($A$1=40391,J75,(IF($A$1=40422,K75,(IF($A$1=40452,L75,(IF($A$1=40483,M75)))))))))+(IF($A$1=40513,N75,0)) -> 0
Q76: =(IF($A$1=40179,C76,(IF($A$1=40210,D76,(IF($A$1=40238,E76,(IF($A$1=40269,F76,(IF($A$1=40299,G76,(IF($A$1=40330,H76,(IF($A$1=40360,I76,0)))))))))))))+(IF($A$1=40391,J76,(IF($A$1=40422,K76,(IF($A$1=40452,L76,(IF($A$1=40483,M76)))))))))+(IF($A$1=40513,N76,0)) -> 0
A77: BRM | B77: ENRGY | C77: 25.912451 | D77: 23.814305 | E77: 19.967275 | F77: 21.979437 | G77: 22.78727 | H77: 27.077185 | I77: 26.680467 | J77: 28.146048 | K77: 26.264429 | L77: 26.002224 | M77: 23.993503 | N77: 28.932986 | O77: 25.020526 | P77: 26.020526 | Q77: =(IF($A$1=40179,C77,(IF($A$1=40210,D77,(IF($A$1=40238,E77,(IF($A$1=40269,F77,(IF($A$1=40299,G77,(IF($A$1=40330,H77,(IF($A$1=40360,I77,0)))))))))))))+(IF($A$1=40391,J77,(IF($A$1=40422,K77,(IF($A$1=40452,L77,(IF($A$1=40483,M77)))))))))+(IF($A$1=40513,N77,0)) -> 0
A78: PLAN | C78: 31.709013 | D78: 31.669965 | E78: 31.737435 | F78: 31.750688 | G78: 31.701568 | H78: 31.669724 | I78: 30.902486 | J78: 30.917958 | K78: 31.877764 | L78: 31.892454 | M78: 31.893063 | N78: 30.864895 | O78: 31.481775 | P78: 32.481775 | Q78: =(IF($A$1=40179,C78,(IF($A$1=40210,D78,(IF($A$1=40238,E78,(IF($A$1=40269,F78,(IF($A$1=40299,G78,(IF($A$1=40330,H78,(IF($A$1=40360,I78,0)))))))))))))+(IF($A$1=40391,J78,(IF($A$1=40422,K78,(IF($A$1=40452,L78,(IF($A$1=40483,M78)))))))))+(IF($A$1=40513,N78,0)) -> 0
I79: 33.077812 | J79: 21.968969 | K79: 21.467505 | L79: 18.132301 | M79: 22.328025 | N79: 29.022465 | Q79: =(IF($A$1=40179,C79,(IF($A$1=40210,D79,(IF($A$1=40238,E79,(IF($A$1=40269,F79,(IF($A$1=40299,G79,(IF($A$1=40330,H79,(IF($A$1=40360,I79,0)))))))))))))+(IF($A$1=40391,J79,(IF($A$1=40422,K79,(IF($A$1=40452,L79,(IF($A$1=40483,M79)))))))))+(IF($A$1=40513,N79,0)) -> 0
D80: 0 | I80: 7.4792985 | Q80: =(IF($A$1=40179,C80,(IF($A$1=40210,D80,(IF($A$1=40238,E80,(IF($A$1=40269,F80,(IF($A$1=40299,G80,(IF($A$1=40330,H80,(IF($A$1=40360,I80,0)))))))))))))+(IF($A$1=40391,J80,(IF($A$1=40422,K80,(IF($A$1=40452,L80,(IF($A$1=40483,M80)))))))))+(IF($A$1=40513,N80,0)) -> 0
Q81: =(IF($A$1=40179,C81,(IF($A$1=40210,D81,(IF($A$1=40238,E81,(IF($A$1=40269,F81,(IF($A$1=40299,G81,(IF($A$1=40330,H81,(IF($A$1=40360,I81,0)))))))))))))+(IF($A$1=40391,J81,(IF($A$1=40422,K81,(IF($A$1=40452,L81,(IF($A$1=40483,M81)))))))))+(IF($A$1=40513,N81,0)) -> 0
A82: BRM | C82: 17.389222 | D82: 15.836902 | E82: 12.879108 | F82: 14.233447 | G82: 16.1692 | H82: 18.324236 | I82: 19.379726 | J82: 18.779652 | K82: 19.045552 | L82: 18.731174 | M82: 18.225018 | N82: 21.1084 | O82: 17.435004 | P82: 18.435004 | Q82: =(IF($A$1=40179,C82,(IF($A$1=40210,D82,(IF($A$1=40238,E82,(IF($A$1=40269,F82,(IF($A$1=40299,G82,(IF($A$1=40330,H82,(IF($A$1=40360,I82,0)))))))))))))+(IF($A$1=40391,J82,(IF($A$1=40422,K82,(IF($A$1=40452,L82,(IF($A$1=40483,M82)))))))))+(IF($A$1=40513,N82,0)) -> 0
A83: PLAN | C83: 19.980275 | D83: 22.122904 | E83: 18.39799 | F83: 17.68532 | G83: 20.37327 | H83: 22.127222 | I83: 11.774944 | J83: 10.699441 | K83: 13.703179 | L83: 12.648051 | M83: 12.574183 | N83: 14.697918 | O83: 14.881456 | P83: 15.881456 | Q83: =(IF($A$1=40179,C83,(IF($A$1=40210,D83,(IF($A$1=40238,E83,(IF($A$1=40269,F83,(IF($A$1=40299,G83,(IF($A$1=40330,H83,(IF($A$1=40360,I83,0)))))))))))))+(IF($A$1=40391,J83,(IF($A$1=40422,K83,(IF($A$1=40452,L83,(IF($A$1=40483,M83)))))))))+(IF($A$1=40513,N83,0)) -> 0
I84: 9.9758479 | J84: 6.7279967 | K84: 12.997904 | L84: 12.470436 | M84: 22.08176 | N84: 29.386764 | Q84: =(IF($A$1=40179,C84,(IF($A$1=40210,D84,(IF($A$1=40238,E84,(IF($A$1=40269,F84,(IF($A$1=40299,G84,(IF($A$1=40330,H84,(IF($A$1=40360,I84,0)))))))))))))+(IF($A$1=40391,J84,(IF($A$1=40422,K84,(IF($A$1=40452,L84,(IF($A$1=40483,M84)))))))))+(IF($A$1=40513,N84,0)) -> 0
Q85: =(IF($A$1=40179,C85,(IF($A$1=40210,D85,(IF($A$1=40238,E85,(IF($A$1=40269,F85,(IF($A$1=40299,G85,(IF($A$1=40330,H85,(IF($A$1=40360,I85,0)))))))))))))+(IF($A$1=40391,J85,(IF($A$1=40422,K85,(IF($A$1=40452,L85,(IF($A$1=40483,M85)))))))))+(IF($A$1=40513,N85,0)) -> 0
A86: BRM | C86: 43.301673 | D86: 39.651207 | E86: 32.846383 | F86: 36.212884 | G86: 38.956469 | H86: 45.401421 | I86: 46.060193 | J86: 46.9257 | K86: 45.309982 | L86: 44.733398 | M86: 42.218521 | N86: 50.041385 | O86: 42.45553 | P86: 43.45553 | Q86: =(IF($A$1=40179,C86,(IF($A$1=40210,D86,(IF($A$1=40238,E86,(IF($A$1=40269,F86,(IF($A$1=40299,G86,(IF($A$1=40330,H86,(IF($A$1=40360,I86,0)))))))))))))+(IF($A$1=40391,J86,(IF($A$1=40422,K86,(IF($A$1=40452,L86,(IF($A$1=40483,M86)))))))))+(IF($A$1=40513,N86,0)) -> 0
A87: PLAN | C87: 51.689288 | D87: 53.792869 | E87: 50.135425 | F87: 49.436008 | G87: 52.074838 | H87: 53.796945 | I87: 42.67743 | J87: 41.617399 | K87: 45.580943 | L87: 44.540505 | M87: 44.467247 | N87: 45.562813 | O87: 46.363231 | P87: 47.363231 | Q87: =(IF($A$1=40179,C87,(IF($A$1=40210,D87,(IF($A$1=40238,E87,(IF($A$1=40269,F87,(IF($A$1=40299,G87,(IF($A$1=40330,H87,(IF($A$1=40360,I87,0)))))))))))))+(IF($A$1=40391,J87,(IF($A$1=40422,K87,(IF($A$1=40452,L87,(IF($A$1=40483,M87)))))))))+(IF($A$1=40513,N87,0)) -> 0
A88: LAST YEAR | I88: 43.05366 | J88: 28.696966 | K88: 34.465409 | L88: 30.602738 | M88: 44.409785 | N88: 58.409229 | Q88: =(IF($A$1=40179,C88,(IF($A$1=40210,D88,(IF($A$1=40238,E88,(IF($A$1=40269,F88,(IF($A$1=40299,G88,(IF($A$1=40330,H88,(IF($A$1=40360,I88,0)))))))))))))+(IF($A$1=40391,J88,(IF($A$1=40422,K88,(IF($A$1=40452,L88,(IF($A$1=40483,M88)))))))))+(IF($A$1=40513,N88,0)) -> 0
Q89: =(IF($A$1=40179,C89,(IF($A$1=40210,D89,(IF($A$1=40238,E89,(IF($A$1=40269,F89,(IF($A$1=40299,G89,(IF($A$1=40330,H89,(IF($A$1=40360,I89,0)))))))))))))+(IF($A$1=40391,J89,(IF($A$1=40422,K89,(IF($A$1=40452,L89,(IF($A$1=40483,M89)))))))))+(IF($A$1=40513,N89,0)) -> 0
I90: 9523 | J90: 14566 | K90: 11925 | L90: 13953 | M90: 12182 | N90: 8235 | Q90: =(IF($A$1=40179,C90,(IF($A$1=40210,D90,(IF($A$1=40238,E90,(IF($A$1=40269,F90,(IF($A$1=40299,G90,(IF($A$1=40330,H90,(IF($A$1=40360,I90,0)))))))))))))+(IF($A$1=40391,J90,(IF($A$1=40422,K90,(IF($A$1=40452,L90,(IF($A$1=40483,M90)))))))))+(IF($A$1=40513,N90,0)) -> 0
Q91: =(IF($A$1=40179,C91,(IF($A$1=40210,D91,(IF($A$1=40238,E91,(IF($A$1=40269,F91,(IF($A$1=40299,G91,(IF($A$1=40330,H91,(IF($A$1=40360,I91,0)))))))))))))+(IF($A$1=40391,J91,(IF($A$1=40422,K91,(IF($A$1=40452,L91,(IF($A$1=40483,M91)))))))))+(IF($A$1=40513,N91,0)) -> 0
A92: Per Occ.Rooms | O92: 13.28324 | P92: 14.28324 | Q92: =(IF($A$1=40179,C92,(IF($A$1=40210,D92,(IF($A$1=40238,E92,(IF($A$1=40269,F92,(IF($A$1=40299,G92,(IF($A$1=40330,H92,(IF($A$1=40360,I92,0)))))))))))))+(IF($A$1=40391,J92,(IF($A$1=40422,K92,(IF($A$1=40452,L92,(IF($A$1=40483,M92)))))))))+(IF($A$1=40513,N92,0)) -> 0
A93: ENERGY COSTS | Q93: =(IF($A$1=40179,C93,(IF($A$1=40210,D93,(IF($A$1=40238,E93,(IF($A$1=40269,F93,(IF($A$1=40299,G93,(IF($A$1=40330,H93,(IF($A$1=40360,I93,0)))))))))))))+(IF($A$1=40391,J93,(IF($A$1=40422,K93,(IF($A$1=40452,L93,(IF($A$1=40483,M93)))))))))+(IF($A$1=40513,N93,0)) -> 0
A94: ELECRICITY | C94: 9.3027833 | D94: 8.3311928 | E94: 9.6786446 | F94: 8.8408989 | G94: 11.408475 | H94: 13.925292 | I94: 14.083571 | J94: 14 | K94: 12.55 | L94: 11 | M94: 9.73 | N94: 9.85 | O94: 11.079544 | P94: 12.079544 | Q94: =(IF($A$1=40179,C94,(IF($A$1=40210,D94,(IF($A$1=40238,E94,(IF($A$1=40269,F94,(IF($A$1=40299,G94,(IF($A$1=40330,H94,(IF($A$1=40360,I94,0)))))))))))))+(IF($A$1=40391,J94,(IF($A$1=40422,K94,(IF($A$1=40452,L94,(IF($A$1=40483,M94)))))))))+(IF($A$1=40513,N94,0)) -> 0
A95: WATER & SEWAGE | C95: 6.7445825 | D95: 5.8947395 | E95: 5.8752562 | F95: 5.9011104 | G95: 5.7837343 | H95: 6.5260624 | I95: 5.9452909 | J95: 8.7330288 | K95: 9.5 | L95: 7.4 | M95: 6.8 | N95: 6.88 | O95: 6.8012938 | P95: 7.8012938 | Q95: =(IF($A$1=40179,C95,(IF($A$1=40210,D95,(IF($A$1=40238,E95,(IF($A$1=40269,F95,(IF($A$1=40299,G95,(IF($A$1=40330,H95,(IF($A$1=40360,I95,0)))))))))))))+(IF($A$1=40391,J95,(IF($A$1=40422,K95,(IF($A$1=40452,L95,(IF($A$1=40483,M95)))))))))+(IF($A$1=40513,N95,0)) -> 0
A96: FUEL | C96: 2.3654573 | D96: 2.4605466 | E96: 1.8873252 | F96: 1.905012 | G96: 1.5736817 | H96: 1.7856361 | I96: 1.8119245 | J96: 1.6 | K96: 1.6 | L96: 2.5 | M96: 2.53 | N96: 2.7 | O96: 2.1710695 | P96: 3.1710695 | Q96: =(IF($A$1=40179,C96,(IF($A$1=40210,D96,(IF($A$1=40238,E96,(IF($A$1=40269,F96,(IF($A$1=40299,G96,(IF($A$1=40330,H96,(IF($A$1=40360,I96,0)))))))))))))+(IF($A$1=40391,J96,(IF($A$1=40422,K96,(IF($A$1=40452,L96,(IF($A$1=40483,M96)))))))))+(IF($A$1=40513,N96,0)) -> 0
A97: gas | C97: 0.2 | D97: 0.2 | E97: 0.2 | F97: 0.2 | G97: 0.2 | H97: 0.2 | I97: 0.41038028 | J97: 0.11981877 | K97: 0.15165877 | L97: 0.22091902 | M97: 0.21409109 | N97: 0.28555111 | O97: 0.11753947 | P97: 1.1175395 | Q97: =(IF($A$1=40179,C97,(IF($A$1=40210,D97,(IF($A$1=40238,E97,(IF($A$1=40269,F97,(IF($A$1=40299,G97,(IF($A$1=40330,H97,(IF($A$1=40360,I97,0)))))))))))))+(IF($A$1=40391,J97,(IF($A$1=40422,K97,(IF($A$1=40452,L97,(IF($A$1=40483,M97)))))))))+(IF($A$1=40513,N97,0)) -> 0
A98: TOTAL ENERGY | C98: 18.412823 | D98: 18.686479 | E98: 17.441226 | F98: 16.647021 | G98: 18.765891 | H98: 22.236991 | I98: 22.251166 | J98: 24.452848 | K98: 23.801659 | L98: 21.120919 | M98: 19.274091 | N98: 19.715551 | O98: 20.169447 | P98: 21.169447 | Q98: =(IF($A$1=40179,C98,(IF($A$1=40210,D98,(IF($A$1=40238,E98,(IF($A$1=40269,F98,(IF($A$1=40299,G98,(IF($A$1=40330,H98,(IF($A$1=40360,I98,0)))))))))))))+(IF($A$1=40391,J98,(IF($A$1=40422,K98,(IF($A$1=40452,L98,(IF($A$1=40483,M98)))))))))+(IF($A$1=40513,N98,0)) -> 0
A99: OTHER EXPENSES | Q99: =(IF($A$1=40179,C99,(IF($A$1=40210,D99,(IF($A$1=40238,E99,(IF($A$1=40269,F99,(IF($A$1=40299,G99,(IF($A$1=40330,H99,(IF($A$1=40360,I99,0)))))))))))))+(IF($A$1=40391,J99,(IF($A$1=40422,K99,(IF($A$1=40452,L99,(IF($A$1=40483,M99)))))))))+(IF($A$1=40513,N99,0)) -> 0
A100: P. & ST. | C100: 0.05 | D100: 0.07 | E100: 0.058887826 | F100: 0.11682173 | G100: 0.11255377 | H100: 0.070112478 | I100: 0.090011974 | J100: 0.15 | K100: 0.15 | L100: 0.15 | M100: 0.15 | N100: 0.15 | O100: 0.11484106 | P100: 1.1148411 | Q100: =(IF($A$1=40179,C100,(IF($A$1=40210,D100,(IF($A$1=40238,E100,(IF($A$1=40269,F100,(IF($A$1=40299,G100,(IF($A$1=40330,H100,(IF($A$1=40360,I100,0)))))))))))))+(IF($A$1=40391,J100,(IF($A$1=40422,K100,(IF($A$1=40452,L100,(IF($A$1=40483,M100)))))))))+(IF($A$1=40513,N100,0)) -> 0
A101: POSTAGE | C101: 0 | D101: 0 | E101: 0 | F101: 0 | G101: 0 | H101: 0 | I101: 0 | J101: 0 | K101: 0 | L101: 0 | M101: 0 | N101: 0 | O101: 0 | P101: 1 | Q101: =(IF($A$1=40179,C101,(IF($A$1=40210,D101,(IF($A$1=40238,E101,(IF($A$1=40269,F101,(IF($A$1=40299,G101,(IF($A$1=40330,H101,(IF($A$1=40360,I101,0)))))))))))))+(IF($A$1=40391,J101,(IF($A$1=40422,K101,(IF($A$1=40452,L101,(IF($A$1=40483,M101)))))))))+(IF($A$1=40513,N101,0)) -> 0
A102: TAXICAB | C102: 0.22 | D102: 0.24 | E102: 0.22 | F102: 0.25735294 | G102: 0.33805958 | H102: 0.31791326 | I102: 0.25302448 | J102: 0.33 | K102: 0.33 | L102: 0.33 | M102: 0.33 | N102: 0.33 | O102: 0.29221052 | P102: 1.2922105 | Q102: =(IF($A$1=40179,C102,(IF($A$1=40210,D102,(IF($A$1=40238,E102,(IF($A$1=40269,F102,(IF($A$1=40299,G102,(IF($A$1=40330,H102,(IF($A$1=40360,I102,0)))))))))))))+(IF($A$1=40391,J102,(IF($A$1=40422,K102,(IF($A$1=40452,L102,(IF($A$1=40483,M102)))))))))+(IF($A$1=40513,N102,0)) -> 0
A103: R&M DATA PROCESSING | C103: 0 | D103: 0 | E103: 0 | F103: 0 | G103: 0 | H103: 0 | I103: 0 | J103: 0 | K103: 0 | L103: 0 | M103: 0 | N103: 0 | O103: 0 | P103: 1 | Q103: =(IF($A$1=40179,C103,(IF($A$1=40210,D103,(IF($A$1=40238,E103,(IF($A$1=40269,F103,(IF($A$1=40299,G103,(IF($A$1=40330,H103,(IF($A$1=40360,I103,0)))))))))))))+(IF($A$1=40391,J103,(IF($A$1=40422,K103,(IF($A$1=40452,L103,(IF($A$1=40483,M103)))))))))+(IF($A$1=40513,N103,0)) -> 0
A104: R&M TELEPHONE | C104: 0.07 | D104: 0.07 | E104: 0.07 | F104: 0.07 | G104: 0.07 | H104: 0.07 | I104: 0.07 | J104: 0.07 | K104: 0.07 | L104: 0.07 | M104: 0.07 | N104: 0.07 | O104: 0.064126105 | P104: 1.0641261 | Q104: =(IF($A$1=40179,C104,(IF($A$1=40210,D104,(IF($A$1=40238,E104,(IF($A$1=40269,F104,(IF($A$1=40299,G104,(IF($A$1=40330,H104,(IF($A$1=40360,I104,0)))))))))))))+(IF($A$1=40391,J104,(IF($A$1=40422,K104,(IF($A$1=40452,L104,(IF($A$1=40483,M104)))))))))+(IF($A$1=40513,N104,0)) -> 0
A105: R&M KITCHEN EQUIP. | C105: 0.21 | D105: 0.26 | E105: 0.08 | F105: 0.34543818 | G105: 0.19332484 | H105: 0.41463521 | I105: 0.43672323 | J105: 0.65 | K105: 0.53 | L105: 0.55 | M105: 0.6 | N105: 0.55 | O105: 0.40816824 | P105: 1.4081682 | Q105: =(IF($A$1=40179,C105,(IF($A$1=40210,D105,(IF($A$1=40238,E105,(IF($A$1=40269,F105,(IF($A$1=40299,G105,(IF($A$1=40330,H105,(IF($A$1=40360,I105,0)))))))))))))+(IF($A$1=40391,J105,(IF($A$1=40422,K105,(IF($A$1=40452,L105,(IF($A$1=40483,M105)))))))))+(IF($A$1=40513,N105,0)) -> 0
A106: R&M LAUNDRY & VALET | C106: 0.08 | D106: 0.14 | E106: 0.04 | F106: 0 | G106: 0.26461686 | H106: 0.05033043 | I106: 0.45410628 | J106: 0.24 | K106: 0.24 | L106: 0.24 | M106: 0.17 | N106: 0.24 | O106: 0.1810881 | P106: 1.1810881 | Q106: =(IF($A$1=40179,C106,(IF($A$1=40210,D106,(IF($A$1=40238,E106,(IF($A$1=40269,F106,(IF($A$1=40299,G106,(IF($A$1=40330,H106,(IF($A$1=40360,I106,0)))))))))))))+(IF($A$1=40391,J106,(IF($A$1=40422,K106,(IF($A$1=40452,L106,(IF($A$1=40483,M106)))))))))+(IF($A$1=40513,N106,0)) -> 0
A107: R&M MINIBARS | C107: 0 | D107: 0 | E107: 0 | F107: 0 | G107: 0 | H107: 0 | I107: 0 | J107: 0 | K107: 0 | L107: 0 | M107: 0 | N107: 0 | O107: 0 | P107: 1 | Q107: =(IF($A$1=40179,C107,(IF($A$1=40210,D107,(IF($A$1=40238,E107,(IF($A$1=40269,F107,(IF($A$1=40299,G107,(IF($A$1=40330,H107,(IF($A$1=40360,I107,0)))))))))))))+(IF($A$1=40391,J107,(IF($A$1=40422,K107,(IF($A$1=40452,L107,(IF($A$1=40483,M107)))))))))+(IF($A$1=40513,N107,0)) -> 0
A108: R&M REFRIGERATION | C108: 0 | D108: 0.10274324 | E108: 0.022817325 | F108: 0 | G108: 0.36255377 | H108: 0 | I108: 0.21801065 | J108: 0.12 | K108: 0.12 | L108: 0.12 | M108: 0.12 | N108: 0.12 | O108: 0.11096608 | P108: 1.1109661 | Q108: =(IF($A$1=40179,C108,(IF($A$1=40210,D108,(IF($A$1=40238,E108,(IF($A$1=40269,F108,(IF($A$1=40299,G108,(IF($A$1=40330,H108,(IF($A$1=40360,I108,0)))))))))))))+(IF($A$1=40391,J108,(IF($A$1=40422,K108,(IF($A$1=40452,L108,(IF($A$1=40483,M108)))))))))+(IF($A$1=40513,N108,0)) -> 0
A109: R&M SPRINGS , MATTRESS | C109: 0 | D109: 0 | E109: 0 | F109: 0 | G109: 0 | H109: 0 | I109: 0 | J109: 0.018721683 | K109: 0.023696682 | L109: 0.020083548 | M109: 0.019462826 | N109: 0.025959192 | O109: 0.0089481615 | P109: 1.0089482 | Q109: =(IF($A$1=40179,C109,(IF($A$1=40210,D109,(IF($A$1=40238,E109,(IF($A$1=40269,F109,(IF($A$1=40299,G109,(IF($A$1=40330,H109,(IF($A$1=40360,I109,0)))))))))))))+(IF($A$1=40391,J109,(IF($A$1=40422,K109,(IF($A$1=40452,L109,(IF($A$1=40483,M109)))))))))+(IF($A$1=40513,N109,0)) -> 0
A110: R&M T.V & VIDEOS | C110: 0.73 | D110: 0.71 | E110: 0.73 | F110: 0.69927971 | G110: 0.73 | H110: 0.73 | I110: 0.70147405 | J110: 0.9 | K110: 0.95 | L110: 0.9234 | M110: 0.921 | N110: 0.96775868 | O110: 0.81580659 | P110: 1.8158066 | Q110: =(IF($A$1=40179,C110,(IF($A$1=40210,D110,(IF($A$1=40238,E110,(IF($A$1=40269,F110,(IF($A$1=40299,G110,(IF($A$1=40330,H110,(IF($A$1=40360,I110,0)))))))))))))+(IF($A$1=40391,J110,(IF($A$1=40422,K110,(IF($A$1=40452,L110,(IF($A$1=40483,M110)))))))))+(IF($A$1=40513,N110,0)) -> 0
A111: R&M A/C | C111: 0.19 | D111: 0.55 | E111: 0.25 | F111: 0.29104142 | G111: 0.30328979 | H111: 0.72025034 | I111: 0.86659234 | J111: 0.95 | K111: 0.95 | L111: 0.9 | M111: 0.9 | N111: 0.9 | O111: 0.65198077 | P111: 1.6519808 | Q111: =(IF($A$1=40179,C111,(IF($A$1=40210,D111,(IF($A$1=40238,E111,(IF($A$1=40269,F111,(IF($A$1=40299,G111,(IF($A$1=40330,H111,(IF($A$1=40360,I111,0)))))))))))))+(IF($A$1=40391,J111,(IF($A$1=40422,K111,(IF($A$1=40452,L111,(IF($A$1=40483,M111)))))))))+(IF($A$1=40513,N111,0)) -> 0
... A140: TOT. EXP. | C140: 10.635984 | D140: 13.575362 | E140: 10.734208 | F140: 10.108118 | G140: 11.396766 | H140: 12.553591 | I140: 13.837937 | J140: 17.530081 | K140: 17.981959 | L140: 17.372576 | M140: 17.098316 | N140: 18.384779 | O140: 14.191723 | P140: 15.191723 | Q140: =(IF($A$1=40179,C140,(IF($A$1=40210,D140,(IF($A$1=40238,E140,(IF($A$1=40269,F140,(IF($A$1=40299,G140,(IF($A$1=40330,H140,(IF($A$1=40360,I140,0)))))))))))))+(IF($A$1=40391,J140,(IF($A$1=40422,K140,(IF($A$1=40452,L140,(IF($A$1=40483,M140)))))))))+(IF($A$1=40513,N140,0)) -> 0
Q141: =(IF($A$1=40179,C141,(IF($A$1=40210,D141,(IF($A$1=40238,E141,(IF($A$1=40269,F141,(IF($A$1=40299,G141,(IF($A$1=40330,H141,(IF($A$1=40360,I141,0)))))))))))))+(IF($A$1=40391,J141,(IF($A$1=40422,K141,(IF($A$1=40452,L141,(IF($A$1=40483,M141)))))))))+(IF($A$1=40513,N141,0)) -> 0
A142: Per No.Of.Guest | Q142: =(IF($A$1=40179,C142,(IF($A$1=40210,D142,(IF($A$1=40238,E142,(IF($A$1=40269,F142,(IF($A$1=40299,G142,(IF($A$1=40330,H142,(IF($A$1=40360,I142,0)))))))))))))+(IF($A$1=40391,J142,(IF($A$1=40422,K142,(IF($A$1=40452,L142,(IF($A$1=40483,M142)))))))))+(IF($A$1=40513,N142,0)) -> 0
...

Sheet Elect
A1: 44896 | M1: Electricity | BP1: Gourmandise UP | BR1: 1.6 | BS1: Power Taxes | BU1: Max Demand | BW1: 500 | BX1: Electricity UP | BZ1: 1.15
BS2: Light Taxes | BU2: PF Penalty | BX2: Max. Demand UP | BZ2: 30
A3: Date | B3: COUNTER (1) | D3: MD | F3: KVAR | H3: n | I3: Guest Rooms Consumption | R3: Casino Consumption | V3: Plant Room Shared Loads | AO3: To Be Charged By First Arabian | BK3: From Main Panel G2 | BS3: Total Consumption. | BT3: No. Of | BU3: KWH/ | BV3: No. Of | BW3: KWH/ | BX3: Total Cost | BY3: L.E\ | BZ3: L.E\
B4: Reading | C4: Consp. F: *800 | D4: Reading | E4: Consp F: 80 | F4: Reading | G4: Consp. F:*10 | I4: Main Feeder | J4: Consp | K4: T2+T8 | L4: Trans T2 | M4: Consp | N4: Trans T8 | O4: Consp | P4: La Gourmandize | Q4: Consp *30 | R4: Casino 3rd floor EM | S4: Consp | T4: Casino 3rd floor Normal | U4: Consp | V4: Chiller 1 | W4: Consp 53% | X4: Chiller 2 | Y4: Consp 53% | Z4: Chiller 3 | AA4: Consp 53% | AB4: Chiller 4 | AC4: Consp 53% | AD4: Chiller 5 | AE4: Consp 53% | AF4: Chiller 6 | AG4: Consp 53% | AH4: Cooling Towers | AI4: Consp 53% | AJ4: Chiller Pumps | AK4: Consp 53% | AL4: Cooling Tower Pumps | AM4: Consp 53% | AN4: Total Plant Room Consp | AO4: Fiber Chiller (N24) | AP4: Consp | AQ4: Mall Ceiling light (N4) | AR4: Consp | AS4: LG Bakery (N2) | AT4: Consp | AU4: LG Bakery light ( Old lockers ) | AV4: Consp | AW4: MCCR1 | AX4: Consp | AY4: Children Swimming pool | AZ4: Consp | BA4: DPH1 | BB4: Consp | BC4: Guest Rooms Emergency | BD4: Consp | BE4: Hotel Hoods | BF4: Consp | BG4: Main G2 | BH4: Consp | BI4: Total Consp From First Arabian | BJ4: First Arabian Charge Back | BK4: Old Casino Emergency | BL4: Consp | BM4: L / A | BN4: Consp | BO4: L / B | BP4: Consp | BQ4: L / C | BR4: Consp | BT4: Rooms | BU4: room | BV4: guest | BW4: guest | BY4: Room | BZ4: Guest
A5: Last Month Reading | I5: 25597718 | J5: =IF(I5>=I4,I5-I4,0) -> 0 | K5: =M5+O5 -> 0 | L5: 272958.67 | M5: =IF(L5>=L4,L5-L4,0) -> 0 | N5: 294716 | O5: =IF(N5>=N4,N5-N4,0) -> 0 | P5: 227190 | Q5: =IF(P5>=P4,P5-P4,0)*30 -> 0 | R5: 226100.67 | S5: =IF(R5>=R4,R5-R4,0) -> 0 | T5: 412645.67 | U5: =IF(T5>=T4,T5-T4,0) -> 0 | V5: 641433.33 | W5: =IF(V5>=V4,V5-V4,0)*0.53 -> 0 | X5: 829692 | Y5: =IF(X5>=X4,X5-X4,0)*0.53 -> 0 | Z5: 840351 | AA5: =IF(Z5>=Z4,Z5-Z4,0)*0.53 -> 0 | AB5: 184735 | AC5: =IF(AB5>=AB4,AB5-AB4,0)*0.53 -> 0 | AD5: 861815 | AE5: =IF(AD5>=AD4,AD5-AD4,0)*0.53 -> 0 | AF5: 1009533.3 | AG5: =IF(AF5>=AF4,AF5-AF4,0)*0.53 -> 0 | AH5: 417412.5 | AI5: =IF(AH5>=AH4,AH5-AH4,0)*0.53 -> 0 | AJ5: 510596.33 | AK5: =IF(AJ5>=AJ4,AJ5-AJ4,0)*0.53 -> 0 | AL5: 567281 | AM5: =IF(AL5>=AL4,AL5-AL4,0)*0.53 -> 0 | AN5: =W5+Y5+AA5+AC5+AE5+AG5+AI5+AK5+AM5 -> 0 | AO5: 8168866.3 | AP5: =IF(AO5>=AO4,AO5-AO4,0)*0.1125 -> 0 | AQ5: 749961 | AR5: =IF(AQ5>=AQ4,AQ5-AQ4,0) -> 0 | AS5: 15375.667 | AT5: =IF(AS5>=AS4,AS5-AS4,0) -> 0 | AU5: 825880.83 | AV5: =IF(AU5>=AU4,AU5-AU4,0) -> 0 | AW5: 2878624.8 | AX5: =IF(AW5>=AW4,AW5-AW4,0) -> 0 | AY5: 232290.67 | AZ5: =IF(AY5>=AY4,AY5-AY4,0) -> 0 | BA5: 20790094 | BB5: =IF(BA5>=BA4,BA5-BA4,0) -> 0 | BC5: 638949 | BD5: =IF(BC5>=BC4,BC5-BC4,0) -> 0 | BE5: 44912 | BF5: =IF(BE5>=BE4,BE5-BE4,0) -> 0 | BG5: 26126946 | BH5: =IF(BG5>=BG4,BG5-BG4,0)-(0.45*BN5)-(0.45*BP5)-BR5 -> 0 | BI5: =AP5+AR5+AT5+AV5+AX5+AZ5+BB5+BD5+BF5+BH5 -> 0 | BJ5: =BI5+AN5 -> 0 | BK5: 1492737 | BL5: =IF(BK5>=BK4,BK5-BK4,0) -> 0 | BM5: 4303840 | BN5: =IF(BM5>=BM4,BM5-BM4,0) -> 0 | BO5: 449492 | BP5: =IF(BO5>=BO4,BO5-BO4,0) -> 0 | BQ5: 561984.67 | BR5: =IF(BQ5>=BQ4,BQ5-BQ4,0) -> 0
A6: 1 | C6: =IF(+B6-B5>0,B6-B5,(B6-B5)>0)*800 -> 0 | E6: =IF(+D6-D5>0,D6-D5,(D6-D5)>0)*80 -> 0 | G6: =IF(+F6-F5>0,F6-F5,(F6-F5)>0)*10 -> 0 | H6: 56 | I6: 25602753 | J6: =IF(I6>=I5,I6-I5,0) -> 5035.1667 | K6: =M6+O6 -> 4149.3333 | L6: 274718 | M6: =IF(L6>=L5,L6-L5,0) -> 1759.3333 | N6: 297106 | O6: =IF(N6>=N5,N6-N5,0) -> 2390 | P6: 227207 | Q6: =IF(P6>=P5,P6-P5,0)*30 -> 510 | R6: 226239 | S6: =IF(R6>=R5,R6-R5,0) -> 138.33333 | T6: 412870 | U6: =IF(T6>=T5,T6-T5,0) -> 224.33333 | V6: 648674 | W6: =IF(V6>=V5,V6-V5,0)*0.53 -> 3837.5533 | X6: 829692 | Y6: =IF(X6>=X5,X6-X5,0)*0.53 -> 0 | Z6: 845345 | AA6: =IF(Z6>=Z5,Z6-Z5,0)*0.53 -> 2646.82 | AB6: 184735 | AC6: =IF(AB6>=AB5,AB6-AB5,0)*0.53 -> 0 | AD6: 861839 | AE6: =IF(AD6>=AD5,AD6-AD5,0)*0.53 -> 12.72 | AF6: 1009549 | AG6: =IF(AF6>=AF5,AF6-AF5,0)*0.53 -> 8.3033333 | AH6: 418107 | AI6: =IF(AH6>=AH5,AH6-AH5,0)*0.53 -> 368.085 | AJ6: 514617 | AK6: =IF(AJ6>=AJ5,AJ6-AJ5,0)*0.53 -> 2130.9533 | AL6: 567520 | AM6: =IF(AL6>=AL5,AL6-AL5,0)*0.53 -> 126.67 | AN6: =W6+Y6+AA6+AC6+AE6+AG6+AI6+AK6+AM6 -> 9131.105 | AO6: 8170407 | AP6: =IF(AO6>=AO5,AO6-AO5,0)*0.1125 -> 173.325 | AQ6: 750148 | AR6: =IF(AQ6>=AQ5,AQ6-AQ5,0) -> 187 | AS6: 15493 | AT6: =IF(AS6>=AS5,AS6-AS5,0) -> 117.33333 | AU6: 825927 | AV6: =IF(AU6>=AU5,AU6-AU5,0) -> 46.166667 | AW6: 2879704 | AX6: =IF(AW6>=AW5,AW6-AW5,0) -> 1079.1667 | AY6: 232301 | AZ6: =IF(AY6>=AY5,AY6-AY5,0) -> 10.333333 | BA6: 20794849 | BB6: =IF(BA6>=BA5,BA6-BA5,0) -> 4754.6667 | BC6: 639185 | BD6: =IF(BC6>=BC5,BC6-BC5,0) -> 236 | BE6: 44912 | BF6: =IF(BE6>=BE5,BE6-BE5,0) -> 0 | BG6: 26133215 | BH6: =IF(BG6>=BG5,BG6-BG5,0)-(0.45*BN6)-(0.45*BP6)-BR6 -> 5636.2 | BI6: =AP6+AR6+AT6+AV6+AX6+AZ6+BB6+BD6+BF6+BH6 -> 12240.192 | BJ6: =BI6+AN6 -> 21371.297 | BK6: 1493075 | BL6: =IF(BK6>=BK5,BK6-BK5,0) -> 338 | BM6: 4304807 | BN6: =IF(BM6>=BM5,BM6-BM5,0) -> 967 | BO6: 449629 | BP6: =IF(BO6>=BO5,BO6-BO5,0) -> 137 | BQ6: 562121 | BR6: =IF(BQ6>=BQ5,BQ6-BQ5,0) -> 136.33333 | BS6: =J6+Q6+AN6+BI6 -> 26916.463 | BT6: 210 | BU6: =IF(BS6>0,BS6/BT5,0) -> #DIV/0! | BW6: =IF(BS6>0,BS6/BV6,0) -> #DIV/0! | BX6: =((BS6-Q6)*$BZ$1)+(Q6*$BR$1) -> 31183.433 | BY6: =IF(BX6>0,BX6/BT5,0) -> #DIV/0! | BZ6: =IF(BX6>0,BX6/BV6,0) -> #DIV/0!
A7: 2 | I7: 25609332 | J7: =IF(I7>=I6,I7-I6,0) -> 6579 | K7: =M7+O7 -> 3507 | L7: 276695 | M7: =IF(L7>=L6,L7-L6,0) -> 1977 | N7: 298636 | O7: =IF(N7>=N6,N7-N6,0) -> 1530 | P7: 227224 | Q7: =IF(P7>=P6,P7-P6,0)*30 -> 510 | R7: 226376 | S7: =IF(R7>=R6,R7-R6,0) -> 137 | T7: 413121 | U7: =IF(T7>=T6,T7-T6,0) -> 251 | V7: 650540 | W7: =IF(V7>=V6,V7-V6,0)*0.53 -> 988.98 | X7: 829692 | Y7: =IF(X7>=X6,X7-X6,0)*0.53 -> 0 | Z7: 849452 | AA7: =IF(Z7>=Z6,Z7-Z6,0)*0.53 -> 2176.71 | AB7: 184735 | AC7: =IF(AB7>=AB6,AB7-AB6,0)*0.53 -> 0 | AD7: 861857 | AE7: =IF(AD7>=AD6,AD7-AD6,0)*0.53 -> 9.54 | AF7: 1009571 | AG7: =IF(AF7>=AF6,AF7-AF6,0)*0.53 -> 11.66 | AH7: 418727 | AI7: =IF(AH7>=AH6,AH7-AH6,0)*0.53 -> 328.6 | AJ7: 518766 | AK7: =IF(AJ7>=AJ6,AJ7-AJ6,0)*0.53 -> 2198.97 | AL7: 567731 | AM7: =IF(AL7>=AL6,AL7-AL6,0)*0.53 -> 111.83 | AN7: =W7+Y7+AA7+AC7+AE7+AG7+AI7+AK7+AM7 -> 5826.29 | AO7: 8171521 | AP7: =IF(AO7>=AO6,AO7-AO6,0)*0.1125 -> 125.325 | AQ7: 750359 | AR7: =IF(AQ7>=AQ6,AQ7-AQ6,0) -> 211 | AS7: 15648 | AT7: =IF(AS7>=AS6,AS7-AS6,0) -> 155 | AU7: 825957 | AV7: =IF(AU7>=AU6,AU7-AU6,0) -> 30 | AW7: 2880626 | AX7: =IF(AW7>=AW6,AW7-AW6,0) -> 922 | AY7: 232311 | AZ7: =IF(AY7>=AY6,AY7-AY6,0) -> 10 | BA7: 20799334 | BB7: =IF(BA7>=BA6,BA7-BA6,0) -> 4485 | BC7: 639386 | BD7: =IF(BC7>=BC6,BC7-BC6,0) -> 201 | BE7: 44922 | BF7: =IF(BE7>=BE6,BE7-BE6,0) -> 10 | BG7: 26139207 | BH7: =IF(BG7>=BG6,BG7-BG6,0)-(0.45*BN7)-(0.45*BP7)-BR7 -> 5407.1 | BI7: =AP7+AR7+AT7+AV7+AX7+AZ7+BB7+BD7+BF7+BH7 -> 11556.425 | BJ7: =BI7+AN7 -> 17382.715 | BK7: 1493338 | BL7: =IF(BK7>=BK6,BK7-BK6,0) -> 263 | BM7: 4305682 | BN7: =IF(BM7>=BM6,BM7-BM6,0) -> 875 | BO7: 449756 | BP7: =IF(BO7>=BO6,BO7-BO6,0) -> 127 | BQ7: 562255 | BR7: =IF(BQ7>=BQ6,BQ7-BQ6,0) -> 134 | BS7: =J7+Q7+AN7+BI7 -> 24471.715 | BT7: 242 | BU7: =IF(BS7>0,BS7/BT6,0) -> 116.53198 | BW7: =IF(BS7>0,BS7/BV7,0) -> #DIV/0! | BX7: =((BS7-Q7)*$BZ$1)+(Q7*$BR$1) -> 28371.972 | BY7: =IF(BX7>0,BX7/BT6,0) -> 135.10463 | BZ7: =IF(BX7>0,BX7/BV7,0) -> #DIV/0!
A8: 3 | C8: =IF(+B8-B7>0,B8-B7,(B8-B7)>0)*800 -> 0 | E8: =IF(+D8-D7>0,D8-D7,(D8-D7)>0)*80 -> 0 | G8: =IF(+F8-F7>0,F8-F7,(F8-F7)>0)*10 -> 0 | H8: 57 | I8: 25615330 | J8: =IF(I8>=I7,I8-I7,0) -> 5998 | K8: =M8+O8 -> 3618 | L8: 278719 | M8: =IF(L8>=L7,L8-L7,0) -> 2024 | N8: 300230 | O8: =IF(N8>=N7,N8-N7,0) -> 1594 | P8: 227240 | Q8: =IF(P8>=P7,P8-P7,0)*30 -> 480 | R8: 226515 | S8: =IF(R8>=R7,R8-R7,0) -> 139 | T8: 413378 | U8: =IF(T8>=T7,T8-T7,0) -> 257 | V8: 657125 | W8: =IF(V8>=V7,V8-V7,0)*0.53 -> 3490.05 | X8: 829692 | Y8: =IF(X8>=X7,X8-X7,0)*0.53 -> 0 | Z8: 849452 | AA8: =IF(Z8>=Z7,Z8-Z7,0)*0.53 -> 0 | AB8: 184735 | AC8: =IF(AB8>=AB7,AB8-AB7,0)*0.53 -> 0 | AD8: 861882 | AE8: =IF(AD8>=AD7,AD8-AD7,0)*0.53 -> 13.25 | AF8: 1009594 | AG8: =IF(AF8>=AF7,AF8-AF7,0)*0.53 -> 12.19 | AH8: 419470 | AI8: =IF(AH8>=AH7,AH8-AH7,0)*0.53 -> 393.79 | AJ8: 523433 | AK8: =IF(AJ8>=AJ7,AJ8-AJ7,0)*0.53 -> 2473.51 | AL8: 567949 | AM8: =IF(AL8>=AL7,AL8-AL7,0)*0.53 -> 115.54 | AN8: =W8+Y8+AA8+AC8+AE8+AG8+AI8+AK8+AM8 -> 6498.33 | AO8: 8172831 | AP8: =IF(AO8>=AO7,AO8-AO7,0)*0.1125 -> 147.375 | AQ8: 750542 | AR8: =IF(AQ8>=AQ7,AQ8-AQ7,0) -> 183 | AS8: 15792 | AT8: =IF(AS8>=AS7,AS8-AS7,0) -> 144 | AU8: 825989 | AV8: =IF(AU8>=AU7,AU8-AU7,0) -> 32 | AW8: 2881602 | AX8: =IF(AW8>=AW7,AW8-AW7,0) -> 976 | AY8: 232322 | AZ8: =IF(AY8>=AY7,AY8-AY7,0) -> 11 | BA8: 20804242 | BB8: =IF(BA8>=BA7,BA8-BA7,0) -> 4908 | BC8: 639602 | BD8: =IF(BC8>=BC7,BC8-BC7,0) -> 216 | BE8: 45022 | BF8: =IF(BE8>=BE7,BE8-BE7,0) -> 100 | BG8: 26145519 | BH8: =IF(BG8>=BG7,BG8-BG7,0)-(0.45*BN8)-(0.45*BP8)-BR8 -> 5646.85 | BI8: =AP8+AR8+AT8+AV8+AX8+AZ8+BB8+BD8+BF8+BH8 -> 12364.225 | BJ8: =BI8+AN8 -> 18862.555 | BK8: 1493608 | BL8: =IF(BK8>=BK7,BK8-BK7,0) -> 270 | BM8: 4306722 | BN8: =IF(BM8>=BM7,BM8-BM7,0) -> 1040 | BO8: 449863 | BP8: =IF(BO8>=BO7,BO8-BO7,0) -> 107 | BQ8: 562404 | BR8: =IF(BQ8>=BQ7,BQ8-BQ7,0) -> 149 | BS8: =J8+Q8+AN8+BI8 -> 25340.555 | BT8: 225 | BU8: =IF(BS8>0,BS8/BT7,0) -> 104.71304 | BW8: =IF(BS8>0,BS8/BV8,0) -> #DIV/0! | BX8: =((BS8-Q8)*$BZ$1)+(Q8*$BR$1) -> 29357.638 | BY8: =IF(BX8>0,BX8/BT7,0) -> 121.31255 | BZ8: =IF(BX8>0,BX8/BV8,0) -> #DIV/0!
A9: 4 | C9: =IF(+B9-B8>0,B9-B8,(B9-B8)>0)*800 -> 0 | E9: =IF(+D9-D8>0,D9-D8,(D9-D8)>0)*80 -> 0 | G9: =IF(+F9-F8>0,F9-F8,(F9-F8)>0)*10 -> 0 | I9: 25621799 | J9: =IF(I9>=I8,I9-I8,0) -> 6469 | K9: =M9+O9 -> 3537 | L9: 280706 | M9: =IF(L9>=L8,L9-L8,0) -> 1987 | N9: 301780 | O9: =IF(N9>=N8,N9-N8,0) -> 1550 | P9: 227257 | Q9: =IF(P9>=P8,P9-P8,0)*30 -> 510 | R9: 226658 | S9: =IF(R9>=R8,R9-R8,0) -> 143 | T9: 413641 | U9: =IF(T9>=T8,T9-T8,0) -> 263 | V9: 657971 | W9: =IF(V9>=V8,V9-V8,0)*0.53 -> 448.38 | X9: 829692 | Y9: =IF(X9>=X8,X9-X8,0)*0.53 -> 0 | Z9: 855060 | AA9: =IF(Z9>=Z8,Z9-Z8,0)*0.53 -> 2972.24 | AB9: 184735 | AC9: =IF(AB9>=AB8,AB9-AB8,0)*0.53 -> 0 | AD9: 861908 | AE9: =IF(AD9>=AD8,AD9-AD8,0)*0.53 -> 13.78 | AF9: 1009617 | AG9: =IF(AF9>=AF8,AF9-AF8,0)*0.53 -> 12.19 | AH9: 419855 | AI9: =IF(AH9>=AH8,AH9-AH8,0)*0.53 -> 204.05 | AJ9: 527718 | AK9: =IF(AJ9>=AJ8,AJ9-AJ8,0)*0.53 -> 2271.05 | AL9: 568159 | AM9: =IF(AL9>=AL8,AL9-AL8,0)*0.53 -> 111.3 | AN9: =W9+Y9+AA9+AC9+AE9+AG9+AI9+AK9+AM9 -> 6032.99 | AO9: 8174178 | AP9: =IF(AO9>=AO8,AO9-AO8,0)*0.1125 -> 151.5375 | AQ9: 750733 | AR9: =IF(AQ9>=AQ8,AQ9-AQ8,0) -> 191 | AS9: 15952 | AT9: =IF(AS9>=AS8,AS9-AS8,0) -> 160 | AU9: 826021 | AV9: =IF(AU9>=AU8,AU9-AU8,0) -> 32 | AW9: 2882526 | AX9: =IF(AW9>=AW8,AW9-AW8,0) -> 924 | AY9: 232332 | AZ9: =IF(AY9>=AY8,AY9-AY8,0) -> 10 | BA9: 20809442 | BB9: =IF(BA9>=BA8,BA9-BA8,0) -> 5200 | BC9: 639829 | BD9: =IF(BC9>=BC8,BC9-BC8,0) -> 227 | BE9: 44927 | BF9: =IF(BE9>=BE8,BE9-BE8,0) -> 0 | BG9: 26151884 | BH9: =IF(BG9>=BG8,BG9-BG8,0)-(0.45*BN9)-(0.45*BP9)-BR9 -> 5689.1 | BI9: =AP9+AR9+AT9+AV9+AX9+AZ9+BB9+BD9+BF9+BH9 -> 12584.638 | BJ9: =BI9+AN9 -> 18617.628 | BK9: 1493886 | BL9: =IF(BK9>=BK8,BK9-BK8,0) -> 278 | BM9: 4307747 | BN9: =IF(BM9>=BM8,BM9-BM8,0) -> 1025 | BO9: 450000 | BP9: =IF(BO9>=BO8,BO9-BO8,0) -> 137 | BQ9: 562557 | BR9: =IF(BQ9>=BQ8,BQ9-BQ8,0) -> 153 | BS9: =J9+Q9+AN9+BI9 -> 25596.628 | BT9: 236 | BU9: =IF(BS9>0,BS9/BT8,0) -> 113.76279 | BW9: =IF(BS9>0,BS9/BV9,0) -> #DIV/0! | BX9: =((BS9-Q9)*$BZ$1)+(Q9*$BR$1) -> 29665.622 | BY9: =IF(BX9>0,BX9/BT8,0) -> 131.84721 | BZ9: =IF(BX9>0,BX9/BV9,0) -> #DIV/0!
A10: 5 | C10: =IF(+B10-B9>0,B10-B9,(B10-B9)>0)*800 -> 0 | E10: =IF(+D10-D9>0,D10-D9,(D10-D9)>0)*80 -> 0 | G10: =IF(+F10-F9>0,F10-F9,(F10-F9)>0)*10 -> 0 | H10: 58 | I10: 25628126 | J10: =IF(I10>=I9,I10-I9,0) -> 6327 | K10: =M10+O10 -> 4093 | L10: 282812 | M10: =IF(L10>=L9,L10-L9,0) -> 2106 | N10: 303767 | O10: =IF(N10>=N9,N10-N9,0) -> 1987 | P10: 227272 | Q10: =IF(P10>=P9,P10-P9,0)*30 -> 450 | R10: 226802 | S10: =IF(R10>=R9,R10-R9,0) -> 144 | T10: 413898 | U10: =IF(T10>=T9,T10-T9,0) -> 257 | V10: 662679 | W10: =IF(V10>=V9,V10-V9,0)*0.53 -> 2495.24 | X10: 829692 | Y10: =IF(X10>=X9,X10-X9,0)*0.53 -> 0 | Z10: 856868 | AA10: =IF(Z10>=Z9,Z10-Z9,0)*0.53 -> 958.24 | AB10: 184735 | AC10: =IF(AB10>=AB9,AB10-AB9,0)*0.53 -> 0 | AD10: 861933 | AE10: =IF(AD10>=AD9,AD10-AD9,0)*0.53 -> 13.25 | AF10: 1009640 | AG10: =IF(AF10>=AF9,AF10-AF9,0)*0.53 -> 12.19 | AH10: 420217 | AI10: =IF(AH10>=AH9,AH10-AH9,0)*0.53 -> 191.86 | AJ10: 532218 | AK10: =IF(AJ10>=AJ9,AJ10-AJ9,0)*0.53 -> 2385 | AL10: 568383 | AM10: =IF(AL10>=AL9,AL10-AL9,0)*0.53 -> 118.72 | AN10: =W10+Y10+AA10+AC10+AE10+AG10+AI10+AK10+AM10 -> 6174.5 | AO10: 8175348 | AP10: =IF(AO10>=AO9,AO10-AO9,0)*0.1125 -> 131.625 | AQ10: 750936 | AR10: =IF(AQ10>=AQ9,AQ10-AQ9,0) -> 203 | AS10: 16102 | AT10: =IF(AS10>=AS9,AS10-AS9,0) -> 150 | AU10: 826055 | AV10: =IF(AU10>=AU9,AU10-AU9,0) -> 34 | AW10: 2883477 | AX10: =IF(AW10>=AW9,AW10-AW9,0) -> 951 | AY10: 232343 | AZ10: =IF(AY10>=AY9,AY10-AY9,0) -> 11 | BA10: 20814337 | BB10: =IF(BA10>=BA9,BA10-BA9,0) -> 4895 | BC10: 640071 | BD10: =IF(BC10>=BC9,BC10-BC9,0) -> 242 | BE10: 44932 | BF10: =IF(BE10>=BE9,BE10-BE9,0) -> 5 | BG10: 26158182 | BH10: =IF(BG10>=BG9,BG10-BG9,0)-(0.45*BN10)-(0.45*BP10)-BR10 -> 5631.6 | BI10: =AP10+AR10+AT10+AV10+AX10+AZ10+BB10+BD10+BF10+BH10 -> 12254.225 | BJ10: =BI10+AN10 -> 18428.725 | BK10: 1494167 | BL10: =IF(BK10>=BK9,BK10-BK9,0) -> 281 | BM10: 4308733 | BN10: =IF(BM10>=BM9,BM10-BM9,0) -> 986 | BO10: 450146 | BP10: =IF(BO10>=BO9,BO10-BO9,0) -> 146 | BQ10: 562714 | BR10: =IF(BQ10>=BQ9,BQ10-BQ9,0) -> 157 | BS10: =J10+Q10+AN10+BI10 -> 25205.725 | BT10: 216 | BU10: =IF(BS10>0,BS10/BT9,0) -> 106.80392 | BW10: =IF(BS10>0,BS10/BV10,0) -> #DIV/0! | BX10: =((BS10-Q10)*$BZ$1)+(Q10*$BR$1) -> 29189.084 | BY10: =IF(BX10>0,BX10/BT9,0) -> 123.68256 | BZ10: =IF(BX10>0,BX10/BV10,0) -> #DIV/0!
A11: 6 | C11: =IF(+B11-B10>0,B11-B10,(B11-B10)>0)*800 -> 0 | E11: =IF(+D11-D10>0,D11-D10,(D11-D10)>0)*80 -> 0 | G11: =IF(+F11-F10>0,F11-F10,(F11-F10)>0)*10 -> 0 | I11: 25634855 | J11: =IF(I11>=I10,I11-I10,0) -> 6729 | K11: =M11+O11 -> 3438 | L11: 284612 | M11: =IF(L11>=L10,L11-L10,0) -> 1800 | N11: 305405 | O11: =IF(N11>=N10,N11-N10,0) -> 1638 | P11: 227287 | Q11: =IF(P11>=P10,P11-P10,0)*30 -> 450 | R11: 226950 | S11: =IF(R11>=R10,R11-R10,0) -> 148 | T11: 414166 | U11: =IF(T11>=T10,T11-T10,0) -> 268 | V11: 663850 | W11: =IF(V11>=V10,V11-V10,0)*0.53 -> 620.63 | X11: 829692 | Y11: =IF(X11>=X10,X11-X10,0)*0.53 -> 0 | Z11: 857188 | AA11: =IF(Z11>=Z10,Z11-Z10,0)*0.53 -> 169.6 | AB11: 184735 | AC11: =IF(AB11>=AB10,AB11-AB10,0)*0.53 -> 0 | AD11: 861959 | AE11: =IF(AD11>=AD10,AD11-AD10,0)*0.53 -> 13.78 | AF11: 1009662 | AG11: =IF(AF11>=AF10,AF11-AF10,0)*0.53 -> 11.66 | AH11: 420520 | AI11: =IF(AH11>=AH10,AH11-AH10,0)*0.53 -> 160.59 | AJ11: 537112 | AK11: =IF(AJ11>=AJ10,AJ11-AJ10,0)*0.53 -> 2593.82 | AL11: 568602 | AM11: =IF(AL11>=AL10,AL11-AL10,0)*0.53 -> 116.07 | AN11: =W11+Y11+AA11+AC11+AE11+AG11+AI11+AK11+AM11 -> 3686.15 | AO11: 8176461 | AP11: =IF(AO11>=AO10,AO11-AO10,0)*0.1125 -> 125.2125 | AQ11: 751136 | AR11: =IF(AQ11>=AQ10,AQ11-AQ10,0) -> 200 | AS11: 16233 | AT11: =IF(AS11>=AS10,AS11-AS10,0) -> 131 | AU11: 826088 | AV11: =IF(AU11>=AU10,AU11-AU10,0) -> 33 | AW11: 2884550 | AX11: =IF(AW11>=AW10,AW11-AW10,0) -> 1073 | AY11: 232354 | AZ11: =IF(AY11>=AY10,AY11-AY10,0) -> 11 | BA11: 20819000 | BB11: =IF(BA11>=BA10,BA11-BA10,0) -> 4663 | BC11: 640304 | BD11: =IF(BC11>=BC10,BC11-BC10,0) -> 233 | BE11: 45040 | BF11: =IF(BE11>=BE10,BE11-BE10,0) -> 108 | BG11: 26164713 | BH11: =IF(BG11>=BG10,BG11-BG10,0)-(0.45*BN11)-(0.45*BP11)-BR11 -> 5838.85 | BI11: =AP11+AR11+AT11+AV11+AX11+AZ11+BB11+BD11+BF11+BH11 -> 12416.062 | BJ11: =BI11+AN11 -> 16102.212 | BK11: 1494453 | BL11: =IF(BK11>=BK10,BK11-BK10,0) -> 286 | BM11: 4309775 | BN11: =IF(BM11>=BM10,BM11-BM10,0) -> 1042 | BO11: 450291 | BP11: =IF(BO11>=BO10,BO11-BO10,0) -> 145 | BQ11: 562872 | BR11: =IF(BQ11>=BQ10,BQ11-BQ10,0) -> 158 | BS11: =J11+Q11+AN11+BI11 -> 23281.213 | BT11: 198 | BU11: =IF(BS11>0,BS11/BT10,0) -> 107.78339 | BW11: =IF(BS11>0,BS11/BV11,0) -> #DIV/0! | BX11: =((BS11-Q11)*$BZ$1)+(Q11*$BR$1) -> 26975.894 | BY11: =IF(BX11>0,BX11/BT10,0) -> 124.8884 | BZ11: =IF(BX11>0,BX11/BV11,0) -> #DIV/0!
A12: 7 | C12: =IF(+B12-B11>0,B12-B11,(B12-B11)>0)*800 -> 0 | E12: =IF(+D12-D11>0,D12-D11,(D12-D11)>0)*80 -> 0 | G12: =IF(+F12-F11>0,F12-F11,(F12-F11)>0)*10 -> 0 | H12: 59 | I12: 25641324 | J12: =IF(I12>=I11,I12-I11,0) -> 6469 | K12: =M12+O12 -> 4925 | L12: 287044 | M12: =IF(L12>=L11,L12-L11,0) -> 2432 | N12: 307898 | O12: =IF(N12>=N11,N12-N11,0) -> 2493 | P12: 227303 | Q12: =IF(P12>=P11,P12-P11,0)*30 -> 480 | R12: 227089 | S12: =IF(R12>=R11,R12-R11,0) -> 139 | T12: 414420 | U12: =IF(T12>=T11,T12-T11,0) -> 254 | V12: 674727 | W12: =IF(V12>=V11,V12-V11,0)*0.53 -> 5764.81 | X12: 829692 | Y12: =IF(X12>=X11,X12-X11,0)*0.53 -> 0 | Z12: 857270 | AA12: =IF(Z12>=Z11,Z12-Z11,0)*0.53 -> 43.46 | AB12: 184735 | AC12: =IF(AB12>=AB11,AB12-AB11,0)*0.53 -> 0 | AD12: 861984 | AE12: =IF(AD12>=AD11,AD12-AD11,0)*0.53 -> 13.25 | AF12: 1009685 | AG12: =IF(AF12>=AF11,AF12-AF11,0)*0.53 -> 12.19 | AH12: 420929 | AI12: =IF(AH12>=AH11,AH12-AH11,0)*0.53 -> 216.77 | AJ12: 541435 | AK12: =IF(AJ12>=AJ11,AJ12-AJ11,0)*0.53 -> 2291.19 | AL12: 568824 | AM12: =IF(AL12>=AL11,AL12-AL11,0)*0.53 -> 117.66 | AN12: =W12+Y12+AA12+AC12+AE12+AG12+AI12+AK12+AM12 -> 8459.33 | AO12: 8177860 | AP12: =IF(AO12>=AO11,AO12-AO11,0)*0.1125 -> 157.3875 | AQ12: 751331 | AR12: =IF(AQ12>=AQ11,AQ12-AQ11,0) -> 195 | AS12: 16395 | AT12: =IF(AS12>=AS11,AS12-AS11,0) -> 162 | AU12: 826134 | AV12: =IF(AU12>=AU11,AU12-AU11,0) -> 46 | AW12: 2885377 | AX12: =IF(AW12>=AW11,AW12-AW11,0) -> 827 | AY12: 232365 | AZ12: =IF(AY12>=AY11,AY12-AY11,0) -> 11 | BA12: 20824060 | BB12: =IF(BA12>=BA11,BA12-BA11,0) -> 5060 | BC12: 640550 | BD12: =IF(BC12>=BC11,BC12-BC11,0) -> 246 | BE12: 45112 | BF12: =IF(BE12>=BE11,BE12-BE11,0) -> 72 | BG12: 26171262 | BH12: =IF(BG12>=BG11,BG12-BG11,0)-(0.45*BN12)-(0.45*BP12)-BR12 -> 5816.4 | BI12: =AP12+AR12+AT12+AV12+AX12+AZ12+BB12+BD12+BF12+BH12 -> 12592.787 | BJ12: =BI12+AN12 -> 21052.118 | BK12: 1494728 | BL12: =IF(BK12>=BK11,BK12-BK11,0) -> 275 | BM12: 4310920 | BN12: =IF(BM12>=BM11,BM12-BM11,0) -> 1145 | BO12: 450434 | BP12: =IF(BO12>=BO11,BO12-BO11,0) -> 143 | BQ12: 563025 | BR12: =IF(BQ12>=BQ11,BQ12-BQ11,0) -> 153 | BS12: =J12+Q12+AN12+BI12 -> 28001.118 | BT12: 184 | BU12: =IF(BS12>0,BS12/BT11,0) -> 141.41979 | BW12: =IF(BS12>0,BS12/BV12,0) -> #DIV/0! | BX12: =((BS12-Q12)*$BZ$1)+(Q12*$BR$1) -> 32417.285 | BY12: =IF(BX12>0,BX12/BT11,0) -> 163.72366 | BZ12: =IF(BX12>0,BX12/BV12,0) -> #DIV/0!
