Workbook

Sheet Submetering
A1: Site Name | B1: Day | C1: Month | D1: Year | E1: ATS1 Kwh | F1: ATS2 Kwh | G1: ATS3 Kwh | H1: ATS4 Kwh | I1: ATS5 Kwh | J1: Guest (m3) | K1: Kitchen & Laundry (m3) | L1: Room Nights
A2: Beirut | B2: 1 | C2: 2 | D2: 2023 | E2: =ELEC!M4 -> 978 | F2: =ELEC!K4 -> 708 | G2: =ELEC!I4 -> 444 | H2: =ELEC!E4 -> 1020 | I2: =ELEC!G4 -> 314 | J2: =WATER!Y6 -> 0 | K2: =WATER!AJ6 -> 0 | L2: =ELEC!B4 -> 0
A3: Beirut | B3: =B2+1 -> 2 | C3: 2 | D3: 2023 | E3: =ELEC!M5 -> 852 | F3: =ELEC!K5 -> 898 | G3: =ELEC!I5 -> 410 | H3: =ELEC!E5 -> 640 | I3: =ELEC!G5 -> 265 | J3: =WATER!Y7 -> 0 | K3: =WATER!AJ7 -> 0 | L3: =ELEC!B5 -> 0
A4: Beirut | B4: =B3+1 -> 3 | C4: 2 | D4: 2023 | E4: =ELEC!M6 -> 0 | F4: =ELEC!K6 -> 0 | G4: =ELEC!I6 -> 0 | H4: =ELEC!E6 -> 0 | I4: =ELEC!G6 -> 0 | J4: =WATER!Y8 -> 0 | K4: =WATER!AJ8 -> 0 | L4: =ELEC!B6 -> 0
A5: Beirut | B5: =B4+1 -> 4 | C5: 2 | D5: 2023 | E5: =ELEC!M7 -> 0 | F5: =ELEC!K7 -> 0 | G5: =ELEC!I7 -> 0 | H5: =ELEC!E7 -> 0 | I5: =ELEC!G7 -> 0 | J5: =WATER!Y9 -> 0 | K5: =WATER!AJ9 -> 0 | L5: =ELEC!B7 -> 0
A6: Beirut | B6: =B5+1 -> 5 | C6: 2 | D6: 2023 | E6: =ELEC!M8 -> 890 | F6: =ELEC!K8 -> 806 | G6: =ELEC!I8 -> 470 | H6: =ELEC!E8 -> 760 | I6: =ELEC!G8 -> 335 | J6: =WATER!Y10 -> 0 | K6: =WATER!AJ10 -> 0 | L6: =ELEC!B8 -> 0
A7: Beirut | B7: =B6+1 -> 6 | C7: 2 | D7: 2023 | E7: =ELEC!M9 -> 890 | F7: =ELEC!K9 -> 810 | G7: =ELEC!I9 -> 462 | H7: =ELEC!E9 -> 780 | I7: =ELEC!G9 -> 356 | J7: =WATER!Y11 -> 0 | K7: =WATER!AJ11 -> 0 | L7: =ELEC!B9 -> 0
A8: Beirut | B8: =B7+1 -> 7 | C8: 2 | D8: 2023 | E8: =ELEC!M10 -> 1112 | F8: =ELEC!K10 -> 1048 | G8: =ELEC!I10 -> 450 | H8: =ELEC!E10 -> 750 | I8: =ELEC!G10 -> 352 | J8: =WATER!Y12 -> 0 | K8: =WATER!AJ12 -> 0 | L8: =ELEC!B10 -> 0
A9: Beirut | B9: =B8+1 -> 8 | C9: 2 | D9: 2023 | E9: =ELEC!M11 -> 872 | F9: =ELEC!K11 -> 874 | G9: =ELEC!I11 -> 384 | H9: =ELEC!E11 -> 1010 | I9: =ELEC!G11 -> 298 | J9: =WATER!Y13 -> 0 | K9: =WATER!AJ13 -> 0 | L9: =ELEC!B11 -> 0
A10: Beirut | B10: =B9+1 -> 9 | C10: 2 | D10: 2023 | E10: =ELEC!M12 -> 0 | F10: =ELEC!K12 -> 0 | G10: =ELEC!I12 -> 0 | H10: =ELEC!E12 -> 0 | I10: =ELEC!G12 -> 0 | J10: =WATER!Y14 -> 0 | K10: =WATER!AJ14 -> 0 | L10: =ELEC!B12 -> 0
A11: Beirut | B11: =B10+1 -> 10 | C11: 2 | D11: 2023 | E11: =ELEC!M13 -> 0 | F11: =ELEC!K13 -> 0 | G11: =ELEC!I13 -> 0 | H11: =ELEC!E13 -> 0 | I11: =ELEC!G13 -> 0 | J11: =WATER!Y15 -> 0 | K11: =WATER!AJ15 -> 0 | L11: =ELEC!B13 -> 0
A12: Beirut | B12: =B11+1 -> 11 | C12: 2 | D12: 2023 | E12: =ELEC!M14 -> 0 | F12: =ELEC!K14 -> 0 | G12: =ELEC!I14 -> 0 | H12: =ELEC!E14 -> 0 | I12: =ELEC!G14 -> 0 | J12: =WATER!Y16 -> 0 | K12: =WATER!AJ16 -> 0 | L12: =ELEC!B14 -> 0
A13: Beirut | B13: =B12+1 -> 12 | C13: 2 | D13: 2023 | E13: =ELEC!M15 -> 820 | F13: =ELEC!K15 -> 680 | G13: =ELEC!I15 -> 408 | H13: =ELEC!E15 -> 800 | I13: =ELEC!G15 -> 295 | J13: =WATER!Y17 -> 0 | K13: =WATER!AJ17 -> 0 | L13: =ELEC!B15 -> 0
A14: Beirut | B14: =B13+1 -> 13 | C14: 2 | D14: 2023 | E14: =ELEC!M16 -> 866 | F14: =ELEC!K16 -> 780 | G14: =ELEC!I16 -> 464 | H14: =ELEC!E16 -> 710 | I14: =ELEC!G16 -> 405 | J14: =WATER!Y18 -> 0 | K14: =WATER!AJ18 -> -57 | L14: =ELEC!B16 -> 0
... A29: Beirut | B29: =B28+1 -> 28 | C29: 2 | D29: 2023 | E29: =ELEC!M31 -> 0 | F29: =ELEC!K31 -> 0 | G29: =ELEC!I31 -> 0 | H29: =ELEC!E31 -> 0 | I29: =ELEC!G31 -> 0 | J29: =WATER!Y33 -> 0 | K29: =WATER!AJ33 -> 0 | L29: =ELEC!B31 -> 0
A30: Beirut
A31: Beirut
A32: Beirut
D45: .

Sheet Total
A1: Site Name | B1: Day | C1: Month | D1: Year | E1: Total Electricity Kwh | F1: Electricity Tariff ($/Kwh) | G1: Total Fuel Oil (Liter) | H1: Fuel Oil $/Liter | I1: LPG (Kg) | J1: LPG $/Kg | K1: Water Utility Supply (m3) m3 | L1: Water Utility Supply (m3) $/m3 | M1: Irrigation Water (m3) m3 | N1: Irrigation water $/m3 | O1: Room Nights
A2: Beirut | B2: 1 | C2: 2 | D2: 2023 | E2: =ELEC!N4 -> 3464 | F2: =SUM('EDl log'!T4) -> 0.4893128 | G2: =-tanks!AW6 -> 49 | H2: =tanks!AV6 -> 0.915 | I2: =('B5'!AU4)*0.51 -> 0 | J2: ='B5'!AX4/0.51 -> 1.5686275 | K2: =WATER!I6 -> 0 | L2: =SUM(WATER!J6) -> 0 | M2: =WATER!Q6 -> 0 | N2: 0.6 | O2: =ELEC!B4 -> 0
A3: Beirut | B3: =B2+1 -> 2 | C3: 2 | D3: 2023 | E3: =ELEC!N5 -> 3065 | F3: =SUM('EDl log'!T5) -> 0.24657687 | G3: =-tanks!AW7 -> 548 | H3: =tanks!AV7 -> 0.915 | I3: =('B5'!AU5)*0.51 -> 0 | J3: ='B5'!AX5/0.51 -> 1.5686275 | K3: =WATER!I7 -> 0 | L3: =SUM(WATER!J7) -> 0 | M3: =WATER!Q7 -> 0 | N3: 0.6 | O3: =ELEC!B5 -> 0
A4: Beirut | B4: =B3+1 -> 3 | C4: 2 | D4: 2023 | E4: =ELEC!N6 -> 0 | F4: =SUM('EDl log'!T6) -> 0 | G4: =-tanks!AW8 -> 0.6 | H4: =tanks!AV8 -> 0.915 | I4: =('B5'!AU6)*0.51 -> 0 | J4: ='B5'!AX6/0.51 -> 1.5686275 | K4: =WATER!I8 -> 0 | L4: =SUM(WATER!J8) -> 0 | M4: =WATER!Q8 -> 0 | N4: 0.6 | O4: =ELEC!B6 -> 0
A5: Beirut | B5: =B4+1 -> 4 | C5: 2 | D5: 2023 | E5: =ELEC!N7 -> 0 | F5: =SUM('EDl log'!T7) -> 0 | G5: =-tanks!AW9 -> 0 | H5: =tanks!AV9 -> 0.915 | I5: =('B5'!AU7)*0.51 -> 0 | J5: ='B5'!AX7/0.51 -> 1.5686275 | K5: =WATER!I9 -> 0 | L5: =SUM(WATER!J9) -> 0 | M5: =WATER!Q9 -> 0 | N5: 0.6 | O5: =ELEC!B7 -> 0
A6: Beirut | B6: =B5+1 -> 5 | C6: 2 | D6: 2023 | E6: =ELEC!N8 -> 3261 | F6: =SUM('EDl log'!T8) -> 0.32284671 | G6: =-tanks!AW10 -> 203 | H6: =tanks!AV10 -> 0.915 | I6: =('B5'!AU8)*0.51 -> 0 | J6: ='B5'!AX8/0.51 -> 1.5686275 | K6: =WATER!I10 -> 0 | L6: =SUM(WATER!J10) -> 0 | M6: =WATER!Q10 -> 0 | N6: 0.6 | O6: =ELEC!B8 -> 0
A7: Beirut | B7: =B6+1 -> 6 | C7: 2 | D7: 2023 | E7: =ELEC!N9 -> 3298 | F7: =SUM('EDl log'!T9) -> 0.37908156 | G7: =-tanks!AW11 -> 280.4 | H7: =tanks!AV11 -> 0.915 | I7: =('B5'!AU9)*0.51 -> 0 | J7: ='B5'!AX9/0.51 -> 1.5686275 | K7: =WATER!I11 -> 0 | L7: =SUM(WATER!J11) -> 0 | M7: =WATER!Q11 -> 0 | N7: 0.6 | O7: =ELEC!B9 -> 0
A8: Beirut | B8: =B7+1 -> 7 | C8: 2 | D8: 2023 | E8: =ELEC!N10 -> 3712 | F8: =SUM('EDl log'!T10) -> 0.34130236 | G8: =-tanks!AW12 -> 191 | H8: =tanks!AV12 -> 0.915 | I8: =('B5'!AU10)*0.51 -> 0 | J8: ='B5'!AX10/0.51 -> 1.5686275 | K8: =WATER!I12 -> 0 | L8: =SUM(WATER!J12) -> 0 | M8: =WATER!Q12 -> 0 | N8: 0.6 | O8: =ELEC!B10 -> 0
A9: Beirut | B9: =B8+1 -> 8 | C9: 2 | D9: 2023 | E9: =ELEC!N11 -> 3438 | F9: =SUM('EDl log'!T11) -> 0.026149855 | G9: =-tanks!AW13 -> 321 | H9: =tanks!AV13 -> 0.868 | I9: =('B5'!AU11)*0.51 -> 0 | J9: ='B5'!AX11/0.51 -> 1.5686275 | K9: =WATER!I13 -> 7 | L9: =SUM(WATER!J13) -> 38.265306 | M9: =WATER!Q13 -> 0 | N9: 0.6 | O9: =ELEC!B11 -> 0
A10: Beirut | B10: =B9+1 -> 9 | C10: 2 | D10: 2023 | E10: =ELEC!N12 -> 0 | F10: =SUM('EDl log'!T12) -> 0 | G10: =-tanks!AW14 -> 0 | H10: =tanks!AV14 -> 0.868 | I10: =('B5'!AU12)*0.51 -> 0 | J10: ='B5'!AX12/0.51 -> 1.5686275 | K10: =WATER!I14 -> 0 | L10: =SUM(WATER!J14) -> 0 | M10: =WATER!Q14 -> 0 | N10: 0.6 | O10: =ELEC!B12 -> 0
A11: Beirut | B11: =B10+1 -> 10 | C11: 2 | D11: 2023 | E11: =ELEC!N13 -> 0 | F11: =SUM('EDl log'!T13) -> 0 | G11: =-tanks!AW15 -> 0 | H11: =tanks!AV15 -> 0.868 | I11: =('B5'!AU13)*0.51 -> 0 | J11: ='B5'!AX13/0.51 -> 1.5686275 | K11: =WATER!I15 -> 0 | L11: =SUM(WATER!J15) -> 0 | M11: =WATER!Q15 -> 0 | N11: 0.6 | O11: =ELEC!B13 -> 0
A12: Beirut | B12: =B11+1 -> 11 | C12: 2 | D12: 2023 | E12: =ELEC!N14 -> 0 | F12: =SUM('EDl log'!T14) -> 0 | G12: =-tanks!AW16 -> 0 | H12: =tanks!AV16 -> 0.868 | I12: =('B5'!AU14)*0.51 -> 0 | J12: ='B5'!AX14/0.51 -> 1.5686275 | K12: =WATER!I16 -> 0 | L12: =SUM(WATER!J16) -> 0 | M12: =WATER!Q16 -> 0 | N12: 0.6 | O12: =ELEC!B14 -> 0
A13: Beirut | B13: =B12+1 -> 12 | C13: 2 | D13: 2023 | E13: =ELEC!N15 -> 3003 | F13: =SUM('EDl log'!T15) -> 0.31436542 | G13: =-tanks!AW17 -> 636 | H13: =tanks!AV17 -> 0.868 | I13: =('B5'!AU15)*0.51 -> 0 | J13: ='B5'!AX15/0.51 -> 1.5686275 | K13: =WATER!I17 -> 368 | L13: =SUM(WATER!J17) -> 0.72787267 | M13: =WATER!Q17 -> 0 | N13: 0.6 | O13: =ELEC!B15 -> 0
A14: Beirut | B14: =B13+1 -> 13 | C14: 2 | D14: 2023 | E14: =ELEC!N16 -> 3225 | F14: =SUM('EDl log'!T16) -> 0.265666 | G14: =-tanks!AW18 -> 124 | H14: =tanks!AV18 -> 0.868 | I14: =('B5'!AU16)*0.51 -> 0 | J14: ='B5'!AX16/0.51 -> 1.5686275 | K14: =WATER!I18 -> 0 | L14: =SUM(WATER!J18) -> 0 | M14: =WATER!Q18 -> 0 | N14: 0.6 | O14: =ELEC!B16 -> 0
... A29: Beirut | B29: =B28+1 -> 28 | C29: 2 | D29: 2023 | E29: =ELEC!N31 -> 0 | F29: =SUM('EDl log'!T31) -> 0 | G29: =-tanks!AW33 -> 0 | H29: =tanks!AV33 -> 0.88 | I29: =('B5'!AU31)*0.51 -> 0 | J29: ='B5'!AX31/0.51 -> 1.5686275 | K29: =WATER!I33 -> 0 | L29: =SUM(WATER!J33) -> 0 | M29: =WATER!Q33 -> 0 | N29: 0.6 | O29: =ELEC!B31 -> 0
A30: Beirut
A31: Beirut
A32: Beirut

Sheet ELEC
A2: OOC | B2: Room OCC | D2: MDB3 | E2: MDB3/day | F2: EMDB2 | G2: EMDB2/day | H2: EMDB1 | I2: EMDB1/day | J2: MDB2 | K2: mdb2/day | L2: MDB1 | M2: MDB1/Day | N2: Total KWH | O2: KWH/Rooc | P2: Gen MHW | Q2: Gen/Day KWH | R2: EDL KWH | S2: CH1 RH | T2: RH | U2: C1h1 power | V2: CH1 Con KWH | W2: CH2 RH | X2: RH | Y2: Ch2 power | Z2: CH2 Con KWH | AA2: CH3 RH | AB2: RH | AC2: Ch3 power | AD2: CH3 Con KWH | AE2: RH total | AF2: KWH total | AG2: AVG chiller KW/Hr
A3: =[1]ELEC!$A$34 -> 0 | B3: =[1]ELEC!$B$34 -> 0 | C3: 44957 | D3: 436570 | E3: =[2]ELEC!E34 -> 2020 | F3: 4195798 | G3: =[2]ELEC!G34 -> 292 | H3: 18114990 | I3: =[2]ELEC!I34 -> 540 | J3: 29912234 | K3: =[2]ELEC!K34 -> 1060 | L3: 24731876 | M3: =[2]ELEC!M34 -> 1094 | N3: =[2]ELEC!N34 -> 5006 | O3: =[2]ELEC!O34 -> 0 | P3: 19768.966 | Q3: =[2]ELEC!Q34 -> 5066 | R3: =[2]ELEC!R34 -> -60 | S3: =[2]ELEC!S34 -> 10175 | T3: =[2]ELEC!T34 -> 0 | U3: =[2]ELEC!U34 -> 429166 | V3: =[2]ELEC!V34 -> 0 | W3: =[2]ELEC!W34 -> 33502 | X3: =[2]ELEC!X34 -> 0 | ... AG3: =[2]ELEC!AG34 -> 0
A4: ='General information '!F5 -> 0 | B4: =SUM(230*A4) -> 0 | C4: =C3+1 -> 44958 | D4: 437590 | E4: =D4-D3 -> 1020 | F4: 4196112 | G4: =F4-F3 -> 314 | H4: 18115434 | I4: =H4-H3 -> 444 | J4: 29912942 | K4: =J4-J3 -> 708 | L4: 24732854 | M4: =L4-L3 -> 978 | N4: =M4+K4+I4+G4+E4 -> 3464 | O4: =IF(B4>0,N4/B4,0) -> 0 | P4: 19772.488 | Q4: =(P4-P3)*1000 -> 3522 | R4: =+N4-Q4 -> -58 | S4: =S3 -> 10175 | T4: =S4-S3 -> 0 | U4: =U3 -> 429166 | V4: =U4-U3 -> 0 | W4: =W3 -> 33502 | X4: =W4-W3 -> 0 | Y4: =Y3 -> 1001284 | Z4: =Y4-Y3 -> 0 | AA4: =AA3 -> 36804 | AB4: =AA4-AA3 -> 0 | AC4: =AC3 -> 1173391 | AD4: =AC4-AC3 -> 0 | AE4: =AB4+X4+T4 -> 0 | AF4: =V4+Z4+AD4 -> 0 | AG4: =IF(AE4>0,AF4/AE4,0) -> 0
A5: ='General information '!F6 -> 0 | B5: =SUM(230*A5) -> 0 | C5: =C4+1 -> 44959 | D5: 438230 | E5: =D5-D4 -> 640 | F5: 4196377 | G5: =F5-F4 -> 265 | H5: 18115844 | I5: =H5-H4 -> 410 | J5: 29913840 | K5: =J5-J4 -> 898 | L5: 24733706 | M5: =L5-L4 -> 852 | N5: =M5+K5+I5+G5+E5 -> 3065 | O5: =IF(B5>0,N5/B5,0) -> 0 | P5: 19775.337 | Q5: =(P5-P4)*1000 -> 2849 | R5: =+N5-Q5 -> 216 | S5: =S4 -> 10175 | T5: =S5-S4 -> 0 | U5: =U4 -> 429166 | V5: =U5-U4 -> 0 | W5: =W4 -> 33502 | X5: =W5-W4 -> 0 | Y5: =Y4 -> 1001284 | Z5: =Y5-Y4 -> 0 | AA5: =AA4 -> 36804 | AB5: =AA5-AA4 -> 0 | AC5: =AC4 -> 1173391 | AD5: =AC5-AC4 -> 0 | AE5: =AB5+X5+T5 -> 0 | AF5: =V5+Z5+AD5 -> 0 | AG5: =IF(AE5>0,AF5/AE5,0) -> 0
A6: ='General information '!F7 -> 0 | B6: =SUM(230*A6) -> 0 | C6: =C5+1 -> 44960 | D6: 438230 | E6: =D6-D5 -> 0 | F6: 4196377 | G6: =F6-F5 -> 0 | H6: 18115844 | I6: =H6-H5 -> 0 | J6: 29913840 | K6: =J6-J5 -> 0 | L6: 24733706 | M6: =L6-L5 -> 0 | N6: =M6+K6+I6+G6+E6 -> 0 | O6: =IF(B6>0,N6/B6,0) -> 0 | P6: 19775.337 | Q6: =(P6-P5)*1000 -> 0 | R6: =+N6-Q6 -> 0 | S6: =S5 -> 10175 | T6: =S6-S5 -> 0 | U6: =U5 -> 429166 | V6: =U6-U5 -> 0 | W6: =W5 -> 33502 | X6: =W6-W5 -> 0 | Y6: =Y5 -> 1001284 | Z6: =Y6-Y5 -> 0 | AA6: =AA5 -> 36804 | AB6: =AA6-AA5 -> 0 | AC6: =AC5 -> 1173391 | AD6: =AC6-AC5 -> 0 | AE6: =AB6+X6+T6 -> 0 | AF6: =V6+Z6+AD6 -> 0 | AG6: =IF(AE6>0,AF6/AE6,0) -> 0
A7: ='General information '!F8 -> 0 | B7: =SUM(230*A7) -> 0 | C7: =C6+1 -> 44961 | D7: =D6 -> 438230 | E7: =D7-D6 -> 0 | F7: =F6 -> 4196377 | G7: =F7-F6 -> 0 | H7: =H6 -> 18115844 | I7: =H7-H6 -> 0 | J7: =J6 -> 29913840 | K7: =J7-J6 -> 0 | L7: =L6 -> 24733706 | M7: =L7-L6 -> 0 | N7: =M7+K7+I7+G7+E7 -> 0 | O7: =IF(B7>0,N7/B7,0) -> 0 | P7: =P6 -> 19775.337 | Q7: =(P7-P6)*1000 -> 0 | R7: =+N7-Q7 -> 0 | S7: =S6 -> 10175 | T7: =S7-S6 -> 0 | U7: =U6 -> 429166 | V7: =U7-U6 -> 0 | W7: =W6 -> 33502 | X7: =W7-W6 -> 0 | Y7: =Y6 -> 1001284 | Z7: =Y7-Y6 -> 0 | AA7: =AA6 -> 36804 | AB7: =AA7-AA6 -> 0 | AC7: =AC6 -> 1173391 | AD7: =AC7-AC6 -> 0 | AE7: =AB7+X7+T7 -> 0 | AF7: =V7+Z7+AD7 -> 0 | AG7: =IF(AE7>0,AF7/AE7,0) -> 0
A8: ='General information '!F9 -> 0 | B8: =SUM(230*A8) -> 0 | C8: =C7+1 -> 44962 | D8: 438990 | E8: =D8-D7 -> 760 | F8: 4196712 | G8: =F8-F7 -> 335 | H8: 18116314 | I8: =H8-H7 -> 470 | J8: 29914646 | K8: =J8-J7 -> 806 | L8: 24734596 | M8: =L8-L7 -> 890 | N8: =M8+K8+I8+G8+E8 -> 3261 | O8: =IF(B8>0,N8/B8,0) -> 0 | P8: 19778.14 | Q8: =(P8-P7)*1000 -> 2803 | R8: =+N8-Q8 -> 458 | S8: =S7 -> 10175 | T8: =S8-S7 -> 0 | U8: =U7 -> 429166 | V8: =U8-U7 -> 0 | W8: =W7 -> 33502 | X8: =W8-W7 -> 0 | Y8: =Y7 -> 1001284 | Z8: =Y8-Y7 -> 0 | AA8: =AA7 -> 36804 | AB8: =AA8-AA7 -> 0 | AC8: =AC7 -> 1173391 | AD8: =AC8-AC7 -> 0 | AE8: =AB8+X8+T8 -> 0 | AF8: =V8+Z8+AD8 -> 0 | AG8: =IF(AE8>0,AF8/AE8,0) -> 0
A9: ='General information '!F10 -> 0 | B9: =SUM(230*A9) -> 0 | C9: =C8+1 -> 44963 | D9: 439770 | E9: =D9-D8 -> 780 | F9: 4197068 | G9: =F9-F8 -> 356 | H9: 18116776 | I9: =H9-H8 -> 462 | J9: 29915456 | K9: =J9-J8 -> 810 | L9: 24735486 | M9: =L9-L8 -> 890 | N9: =M9+K9+I9+G9+E9 -> 3298 | O9: =IF(B9>0,N9/B9,0) -> 0 | P9: 19781.484 | Q9: =(P9-P8)*1000 -> 3344 | R9: =+N9-Q9 -> -46 | S9: =S8 -> 10175 | T9: =S9-S8 -> 0 | U9: =U8 -> 429166 | V9: =U9-U8 -> 0 | W9: =W8 -> 33502 | X9: =W9-W8 -> 0 | Y9: =Y8 -> 1001284 | Z9: =Y9-Y8 -> 0 | AA9: =AA8 -> 36804 | AB9: =AA9-AA8 -> 0 | AC9: =AC8 -> 1173391 | AD9: =AC9-AC8 -> 0 | AE9: =AB9+X9+T9 -> 0 | AF9: =V9+Z9+AD9 -> 0 | AG9: =IF(AE9>0,AF9/AE9,0) -> 0
A10: ='General information '!F11 -> 0 | B10: =SUM(230*A10) -> 0 | C10: =C9+1 -> 44964 | D10: 440520 | E10: =D10-D9 -> 750 | F10: 4197420 | G10: =F10-F9 -> 352 | H10: 18117226 | I10: =H10-H9 -> 450 | J10: 29916504 | K10: =J10-J9 -> 1048 | L10: 24736598 | M10: =L10-L9 -> 1112 | N10: =M10+K10+I10+G10+E10 -> 3712 | O10: =IF(B10>0,N10/B10,0) -> 0 | P10: 19785.276 | Q10: =(P10-P9)*1000 -> 3792 | R10: =+N10-Q10 -> -80 | S10: =S9 -> 10175 | T10: =S10-S9 -> 0 | U10: =U9 -> 429166 | V10: =U10-U9 -> 0 | W10: =W9 -> 33502 | X10: =W10-W9 -> 0 | Y10: =Y9 -> 1001284 | Z10: =Y10-Y9 -> 0 | AA10: =AA9 -> 36804 | AB10: =AA10-AA9 -> 0 | AC10: =AC9 -> 1173391 | AD10: =AC10-AC9 -> 0 | AE10: =AB10+X10+T10 -> 0 | AF10: =V10+Z10+AD10 -> 0 | AG10: =IF(AE10>0,AF10/AE10,0) -> 0
A11: ='General information '!F12 -> 0 | B11: =SUM(230*A11) -> 0 | C11: =C10+1 -> 44965 | D11: 441530 | E11: =D11-D10 -> 1010 | F11: 4197718 | G11: =F11-F10 -> 298 | H11: 18117610 | I11: =H11-H10 -> 384 | J11: 29917378 | K11: =J11-J10 -> 874 | L11: 24737470 | M11: =L11-L10 -> 872 | N11: =M11+K11+I11+G11+E11 -> 3438 | O11: =IF(B11>0,N11/B11,0) -> 0 | P11: 19788.774 | Q11: =(P11-P10)*1000 -> 3498 | R11: =N11-Q11 -> -60 | S11: =S10 -> 10175 | T11: =S11-S10 -> 0 | U11: =U10 -> 429166 | V11: =U11-U10 -> 0 | W11: =W10 -> 33502 | X11: =W11-W10 -> 0 | Y11: =Y10 -> 1001284 | Z11: =Y11-Y10 -> 0 | AA11: =AA10 -> 36804 | AB11: =AA11-AA10 -> 0 | AC11: =AC10 -> 1173391 | AD11: =AC11-AC10 -> 0 | AE11: =AB11+X11+T11 -> 0 | AF11: =V11+Z11+AD11 -> 0 | AG11: =IF(AE11>0,AF11/AE11,0) -> 0
A12: ='General information '!F13 -> 0 | B12: =SUM(230*A12) -> 0 | C12: =C11+1 -> 44966 | D12: =D11 -> 441530 | E12: =D12-D11 -> 0 | F12: =F11 -> 4197718 | G12: =F12-F11 -> 0 | H12: =H11 -> 18117610 | I12: =H12-H11 -> 0 | J12: =J11 -> 29917378 | K12: =J12-J11 -> 0 | L12: =L11 -> 24737470 | M12: =L12-L11 -> 0 | N12: =M12+K12+I12+G12+E12 -> 0 | O12: =IF(B12>0,N12/B12,0) -> 0 | P12: =P11 -> 19788.774 | Q12: =(P12-P11)*1000 -> 0 | R12: =N12-Q12 -> 0 | S12: =S11 -> 10175 | T12: =S12-S11 -> 0 | U12: =U11 -> 429166 | V12: =U12-U11 -> 0 | W12: =W11 -> 33502 | X12: =W12-W11 -> 0 | Y12: =Y11 -> 1001284 | Z12: =Y12-Y11 -> 0 | AA12: =AA11 -> 36804 | AB12: =AA12-AA11 -> 0 | AC12: =AC11 -> 1173391 | AD12: =AC12-AC11 -> 0 | AE12: =AB12+X12+T12 -> 0 | AF12: =V12+Z12+AD12 -> 0 | AG12: =IF(AE12>0,AF12/AE12,0) -> 0
A13: ='General information '!F14 -> 0 | B13: =SUM(230*A13) -> 0 | C13: =C12+1 -> 44967 | D13: =D12 -> 441530 | E13: =D13-D12 -> 0 | F13: =F12 -> 4197718 | G13: =F13-F12 -> 0 | H13: =H12 -> 18117610 | I13: =H13-H12 -> 0 | J13: =J12 -> 29917378 | K13: =J13-J12 -> 0 | L13: =L12 -> 24737470 | M13: =L13-L12 -> 0 | N13: =M13+K13+I13+G13+E13 -> 0 | O13: =IF(B13>0,N13/B13,0) -> 0 | P13: =P12 -> 19788.774 | Q13: =(P13-P12)*1000 -> 0 | R13: =N13-Q13 -> 0 | S13: =S12 -> 10175 | T13: =S13-S12 -> 0 | U13: =U12 -> 429166 | V13: =U13-U12 -> 0 | W13: =W12 -> 33502 | X13: =W13-W12 -> 0 | Y13: =Y12 -> 1001284 | Z13: =Y13-Y12 -> 0 | AA13: =AA12 -> 36804 | AB13: =AA13-AA12 -> 0 | AC13: =AC12 -> 1173391 | AD13: =AC13-AC12 -> 0 | AE13: =AB13+X13+T13 -> 0 | AF13: =V13+Z13+AD13 -> 0 | AG13: =IF(AE13>0,AF13/AE13,0) -> 0
A14: ='General information '!F15 -> 0 | B14: =SUM(230*A14) -> 0 | C14: =C13+1 -> 44968 | D14: =D13 -> 441530 | E14: =D14-D13 -> 0 | F14: =F13 -> 4197718 | G14: =F14-F13 -> 0 | H14: =H13 -> 18117610 | I14: =H14-H13 -> 0 | J14: =J13 -> 29917378 | K14: =J14-J13 -> 0 | L14: =L13 -> 24737470 | M14: =L14-L13 -> 0 | N14: =M14+K14+I14+G14+E14 -> 0 | O14: =IF(B14>0,N14/B14,0) -> 0 | P14: =P13 -> 19788.774 | Q14: =(P14-P13)*1000 -> 0 | R14: =N14-Q14 -> 0 | S14: =S13 -> 10175 | T14: =S14-S13 -> 0 | U14: =U13 -> 429166 | V14: =U14-U13 -> 0 | W14: =W13 -> 33502 | X14: =W14-W13 -> 0 | Y14: =Y13 -> 1001284 | Z14: =Y14-Y13 -> 0 | AA14: =AA13 -> 36804 | AB14: =AA14-AA13 -> 0 | AC14: =AC13 -> 1173391 | AD14: =AC14-AC13 -> 0 | AE14: =AB14+X14+T14 -> 0 | AF14: =V14+Z14+AD14 -> 0 | AG14: =IF(AE14>0,AF14/AE14,0) -> 0
A15: ='General information '!F16 -> 0 | B15: =SUM(230*A15) -> 0 | C15: =C14+1 -> 44969 | D15: 442330 | E15: =D15-D14 -> 800 | F15: 4198013 | G15: =F15-F14 -> 295 | H15: 18118018 | I15: =H15-H14 -> 408 | J15: 29918058 | K15: =J15-J14 -> 680 | L15: 24738290 | M15: =L15-L14 -> 820 | N15: =M15+K15+I15+G15+E15 -> 3003 | O15: =IF(B15>0,N15/B15,0) -> 0 | P15: 19791.026 | Q15: =(P15-P14)*1000 -> 2252 | R15: =N15-Q15 -> 751 | S15: =S14 -> 10175 | T15: =S15-S14 -> 0 | U15: =U14 -> 429166 | V15: =U15-U14 -> 0 | W15: =W14 -> 33502 | X15: =W15-W14 -> 0 | Y15: =Y14 -> 1001284 | Z15: =Y15-Y14 -> 0 | AA15: =AA14 -> 36804 | AB15: =AA15-AA14 -> 0 | AC15: =AC14 -> 1173391 | AD15: =AC15-AC14 -> 0 | AE15: =AB15+X15+T15 -> 0 | AF15: =V15+Z15+AD15 -> 0 | AG15: =IF(AE15>0,AF15/AE15,0) -> 0
A16: ='General information '!F17 -> 0 | B16: =SUM(230*A16) -> 0 | C16: =C15+1 -> 44970 | D16: 443040 | E16: =D16-D15 -> 710 | F16: 4198418 | G16: =F16-F15 -> 405 | H16: 18118482 | I16: =H16-H15 -> 464 | J16: 29918838 | K16: =J16-J15 -> 780 | L16: 24739156 | M16: =L16-L15 -> 866 | N16: =M16+K16+I16+G16+E16 -> 3225 | O16: =IF(B16>0,N16/B16,0) -> 0 | P16: 19793.798 | Q16: =(P16-P15)*1000 -> 2772 | R16: =N16-Q16 -> 453 | S16: =S15 -> 10175 | T16: =S16-S15 -> 0 | U16: =U15 -> 429166 | V16: =U16-U15 -> 0 | W16: =W15 -> 33502 | X16: =W16-W15 -> 0 | Y16: =Y15 -> 1001284 | Z16: =Y16-Y15 -> 0 | AA16: =AA15 -> 36804 | AB16: =AA16-AA15 -> 0 | AC16: =AC15 -> 1173391 | AD16: =AC16-AC15 -> 0 | AE16: =AB16+X16+T16 -> 0 | AF16: =V16+Z16+AD16 -> 0 | AG16: =IF(AE16>0,AF16/AE16,0) -> 0
A17: ='General information '!F18 -> 0 | B17: =SUM(230*A17) -> 0 | C17: =C16+1 -> 44971 | D17: 443700 | E17: =D17-D16 -> 660 | F17: 4198782 | G17: =F17-F16 -> 364 | H17: 18118866 | I17: =H17-H16 -> 384 | J17: 29919532 | K17: =J17-J16 -> 694 | L17: 24739842 | M17: =L17-L16 -> 686 | N17: =M17+K17+I17+G17+E17 -> 2788 | O17: =IF(B17>0,N17/B17,0) -> 0 | P17: 19796.117 | Q17: =(P17-P16)*1000 -> 2319 | R17: =N17-Q17 -> 469 | S17: =S16 -> 10175 | T17: =S17-S16 -> 0 | U17: =U16 -> 429166 | V17: =U17-U16 -> 0 | W17: 33503 | X17: =W17-W16 -> 1 | Y17: 1001544 | Z17: =Y17-Y16 -> 260 | AA17: =AA16 -> 36804 | AB17: =AA17-AA16 -> 0 | AC17: =AC16 -> 1173391 | AD17: =AC17-AC16 -> 0 | AE17: =AB17+X17+T17 -> 1 | AF17: =V17+Z17+AD17 -> 260 | AG17: =IF(AE17>0,AF17/AE17,0) -> 260
A18: ='General information '!F19 -> 0 | B18: =SUM(230*A18) -> 0 | C18: =C17+1 -> 44972 | D18: 444300 | E18: =D18-D17 -> 600 | F18: 4199089 | G18: =F18-F17 -> 307 | H18: 18119198 | I18: =H18-H17 -> 332 | J18: 29920082 | K18: =J18-J17 -> 550 | L18: 24740358 | M18: =L18-L17 -> 516 | N18: =M18+K18+I18+G18+E18 -> 2305 | O18: =IF(B18>0,N18/B18,0) -> 0 | P18: 19797.964 | Q18: =(P18-P17)*1000 -> 1847 | R18: =N18-Q18 -> 458 | S18: =S17 -> 10175 | T18: =S18-S17 -> 0 | U18: =U17 -> 429166 | V18: =U18-U17 -> 0 | W18: =W17 -> 33503 | X18: =W18-W17 -> 0 | Y18: =Y17 -> 1001544 | Z18: =Y18-Y17 -> 0 | AA18: =AA17 -> 36804 | AB18: =AA18-AA17 -> 0 | AC18: =AC17 -> 1173391 | AD18: =AC18-AC17 -> 0 | AE18: =AB18+X18+T18 -> 0 | AF18: =V18+Z18+AD18 -> 0 | AG18: =IF(AE18>0,AF18/AE18,0) -> 0
A19: ='General information '!F20 -> 0 | B19: =SUM(230*A19) -> 0 | C19: =C18+1 -> 44973 | D19: 444960 | E19: =D19-D18 -> 660 | F19: 4199434 | G19: =F19-F18 -> 345 | H19: 18119606 | I19: =H19-H18 -> 408 | J19: 29920778 | K19: =J19-J18 -> 696 | L19: 24741038 | M19: =L19-L18 -> 680 | N19: =M19+K19+I19+G19+E19 -> 2789 | O19: =IF(B19>0,N19/B19,0) -> 0 | P19: 19800.593 | Q19: =(P19-P18)*1000 -> 2629 | R19: =N19-Q19 -> 160 | S19: =S18 -> 10175 | T19: =S19-S18 -> 0 | U19: =U18 -> 429166 | V19: =U19-U18 -> 0 | W19: =W18 -> 33503 | X19: =W19-W18 -> 0 | Y19: =Y18 -> 1001544 | Z19: =Y19-Y18 -> 0 | AA19: =AA18 -> 36804 | AB19: =AA19-AA18 -> 0 | AC19: =AC18 -> 1173391 | AD19: =AC19-AC18 -> 0 | AE19: =AB19+X19+T19 -> 0 | AF19: =V19+Z19+AD19 -> 0 | AG19: =IF(AE19>0,AF19/AE19,0) -> 0
A20: ='General information '!F21 -> 0 | B20: =SUM(230*A20) -> 0 | C20: =C19+1 -> 44974 | D20: 444960 | E20: =D20-D19 -> 0 | F20: 4199434 | G20: =F20-F19 -> 0 | H20: 18119606 | I20: =H20-H19 -> 0 | J20: 29920778 | K20: =J20-J19 -> 0 | L20: 24741038 | M20: =L20-L19 -> 0 | N20: =M20+K20+I20+G20+E20 -> 0 | O20: =IF(B20>0,N20/B20,0) -> 0 | P20: 19800.593 | Q20: =(P20-P19)*1000 -> 0 | R20: =N20-Q20 -> 0 | S20: =S19 -> 10175 | T20: =S20-S19 -> 0 | U20: =U19 -> 429166 | V20: =U20-U19 -> 0 | W20: =W19 -> 33503 | X20: =W20-W19 -> 0 | Y20: =Y19 -> 1001544 | Z20: =Y20-Y19 -> 0 | AA20: =AA19 -> 36804 | AB20: =AA20-AA19 -> 0 | AC20: =AC19 -> 1173391 | AD20: =AC20-AC19 -> 0 | AE20: =AB20+X20+T20 -> 0 | AF20: =V20+Z20+AD20 -> 0 | AG20: =IF(AE20>0,AF20/AE20,0) -> 0
A21: ='General information '!F22 -> 0 | B21: =SUM(230*A21) -> 0 | C21: =C20+1 -> 44975 | D21: 444960 | E21: =D21-D20 -> 0 | F21: 4199434 | G21: =F21-F20 -> 0 | H21: =H20 -> 18119606 | I21: =H21-H20 -> 0 | J21: =J20 -> 29920778 | K21: =J21-J20 -> 0 | L21: 24741038 | M21: =L21-L20 -> 0 | N21: =M21+K21+I21+G21+E21 -> 0 | O21: =IF(B21>0,N21/B21,0) -> 0 | P21: =P20 -> 19800.593 | Q21: =(P21-P20)*1000 -> 0 | R21: =N21-Q21 -> 0 | S21: =S20 -> 10175 | T21: =S21-S20 -> 0 | U21: =U20 -> 429166 | V21: =U21-U20 -> 0 | W21: =W20 -> 33503 | X21: =W21-W20 -> 0 | Y21: =Y20 -> 1001544 | Z21: =Y21-Y20 -> 0 | AA21: =AA20 -> 36804 | AB21: =AA21-AA20 -> 0 | AC21: =AC20 -> 1173391 | AD21: =AC21-AC20 -> 0 | AE21: =AB21+X21+T21 -> 0 | AF21: =V21+Z21+AD21 -> 0 | AG21: =IF(AE21>0,AF21/AE21,0) -> 0
A22: ='General information '!F23 -> 0 | B22: =SUM(230*A22) -> 0 | C22: =C21+1 -> 44976 | D22: 445550 | E22: =D22-D21 -> 590 | F22: 4199765 | G22: =F22-F21 -> 331 | H22: 18120036 | I22: =H22-H21 -> 430 | J22: 29921452 | K22: =J22-J21 -> 674 | L22: 24741812 | M22: =L22-L21 -> 774 | N22: =M22+K22+I22+G22+E22 -> 2799 | O22: =IF(B22>0,N22/B22,0) -> 0 | P22: 19802.984 | Q22: =(P22-P21)*1000 -> 2391 | R22: =N22-Q22 -> 408 | S22: =S21 -> 10175 | T22: =S22-S21 -> 0 | U22: =U21 -> 429166 | V22: =U22-U21 -> 0 | W22: =W21 -> 33503 | X22: =W22-W21 -> 0 | Y22: =Y21 -> 1001544 | Z22: =Y22-Y21 -> 0 | AA22: =AA21 -> 36804 | AB22: =AA22-AA21 -> 0 | AC22: =AC21 -> 1173391 | AD22: =AC22-AC21 -> 0 | AE22: =AB22+X22+T22 -> 0 | AF22: =V22+Z22+AD22 -> 0 | AG22: =IF(AE22>0,AF22/AE22,0) -> 0
A23: ='General information '!F24 -> 0 | B23: =SUM(230*A23) -> 0 | C23: =C22+1 -> 44977 | D23: 446070 | E23: =D23-D22 -> 520 | F23: 4200073 | G23: =F23-F22 -> 308 | H23: 18120444 | I23: =H23-H22 -> 408 | J23: 29922190 | K23: =J23-J22 -> 738 | L23: 24742606 | M23: =L23-L22 -> 794 | N23: =M23+K23+I23+G23+E23 -> 2768 | O23: =IF(B23>0,N23/B23,0) -> 0 | P23: 19805.325 | Q23: =(P23-P22)*1000 -> 2341 | R23: =N23-Q23 -> 427 | S23: =S22 -> 10175 | T23: =S23-S22 -> 0 | U23: =U22 -> 429166 | V23: =U23-U22 -> 0 | W23: =W22 -> 33503 | X23: =W23-W22 -> 0 | Y23: =Y22 -> 1001544 | Z23: =Y23-Y22 -> 0 | AA23: =AA22 -> 36804 | AB23: =AA23-AA22 -> 0 | AC23: =AC22 -> 1173391 | AD23: =AC23-AC22 -> 0 | AE23: =AB23+X23+T23 -> 0 | AF23: =V23+Z23+AD23 -> 0 | AG23: =IF(AE23>0,AF23/AE23,0) -> 0
A24: ='General information '!F25 -> 0 | B24: =SUM(230*A24) -> 0 | C24: =C23+1 -> 44978 | D24: 446660 | E24: =D24-D23 -> 590 | F24: 4200383 | G24: =F24-F23 -> 310 | H24: 18120838 | I24: =H24-H23 -> 394 | J24: 29922894 | K24: =J24-J23 -> 704 | L24: 24743290 | M24: =L24-L23 -> 684 | N24: =M24+K24+I24+G24+E24 -> 2682 | O24: =IF(B24>0,N24/B24,0) -> 0 | P24: 19808 | Q24: =(P24-P23)*1000 -> 2675 | R24: =N24-Q24 -> 7 | S24: =S23 -> 10175 | T24: =S24-S23 -> 0 | U24: =U23 -> 429166 | V24: =U24-U23 -> 0 | W24: =W23 -> 33503 | X24: =W24-W23 -> 0 | Y24: =Y23 -> 1001544 | Z24: =Y24-Y23 -> 0 | AA24: =AA23 -> 36804 | AB24: =AA24-AA23 -> 0 | AC24: =AC23 -> 1173391 | AD24: =AC24-AC23 -> 0 | AE24: =AB24+X24+T24 -> 0 | AF24: =V24+Z24+AD24 -> 0 | AG24: =IF(AE24>0,AF24/AE24,0) -> 0
A25: ='General information '!F26 -> 0 | B25: =SUM(230*A25) -> 0 | C25: =C24+1 -> 44979 | D25: 447160 | E25: =D25-D24 -> 500 | F25: 4200688 | G25: =F25-F24 -> 305 | H25: 18121232 | I25: =H25-H24 -> 394 | J25: 29923556 | K25: =J25-J24 -> 662 | L25: 24743950 | M25: =L25-L24 -> 660 | N25: =M25+K25+I25+G25+E25 -> 2521 | O25: =IF(B25>0,N25/B25,0) -> 0 | P25: 19810.14 | Q25: =(P25-P24)*1000 -> 2140 | R25: =N25-Q25 -> 381 | S25: =S24 -> 10175 | T25: =S25-S24 -> 0 | U25: =U24 -> 429166 | V25: =U25-U24 -> 0 | W25: =W24 -> 33503 | X25: =W25-W24 -> 0 | Y25: =Y24 -> 1001544 | Z25: =Y25-Y24 -> 0 | AA25: =AA24 -> 36804 | AB25: =AA25-AA24 -> 0 | AC25: =AC24 -> 1173391 | AD25: =AC25-AC24 -> 0 | AE25: =AB25+X25+T25 -> 0 | AF25: =V25+Z25+AD25 -> 0 | AG25: =IF(AE25>0,AF25/AE25,0) -> 0
A26: ='General information '!F27 -> 0 | B26: =SUM(230*A26) -> 0 | C26: =C25+1 -> 44980 | D26: 447720 | E26: =D26-D25 -> 560 | F26: 4201030 | G26: =F26-F25 -> 342 | H26: 18121674 | I26: =H26-H25 -> 442 | J26: 29924350 | K26: =J26-J25 -> 794 | L26: 24744706 | M26: =L26-L25 -> 756 | N26: =M26+K26+I26+G26+E26 -> 2894 | O26: =IF(B26>0,N26/B26,0) -> 0 | P26: 19812.964 | Q26: =(P26-P25)*1000 -> 2824 | R26: =N26-Q26 -> 70 | S26: =S25 -> 10175 | T26: =S26-S25 -> 0 | U26: =U25 -> 429166 | V26: =U26-U25 -> 0 | W26: =W25 -> 33503 | X26: =W26-W25 -> 0 | Y26: =Y25 -> 1001544 | Z26: =Y26-Y25 -> 0 | AA26: =AA25 -> 36804 | AB26: =AA26-AA25 -> 0 | AC26: =AC25 -> 1173391 | AD26: =AC26-AC25 -> 0 | AE26: =AB26+X26+T26 -> 0 | AF26: =V26+Z26+AD26 -> 0 | AG26: =IF(AE26>0,AF26/AE26,0) -> 0
A27: ='General information '!F28 -> 0 | B27: =SUM(230*A27) -> 0 | C27: =C26+1 -> 44981 | D27: =D26 -> 447720 | E27: =D27-D26 -> 0 | F27: =F26 -> 4201030 | G27: =F27-F26 -> 0 | H27: =H26 -> 18121674 | I27: =H27-H26 -> 0 | J27: =J26 -> 29924350 | K27: =J27-J26 -> 0 | L27: =L26 -> 24744706 | M27: =L27-L26 -> 0 | N27: =M27+K27+I27+G27+E27 -> 0 | O27: =IF(B27>0,N27/B27,0) -> 0 | P27: =P26 -> 19812.964 | Q27: =(P27-P26)*1000 -> 0 | R27: =N27-Q27 -> 0 | S27: =S26 -> 10175 | T27: =S27-S26 -> 0 | U27: =U26 -> 429166 | V27: =U27-U26 -> 0 | W27: =W26 -> 33503 | X27: =W27-W26 -> 0 | Y27: =Y26 -> 1001544 | Z27: =Y27-Y26 -> 0 | AA27: =AA26 -> 36804 | AB27: =AA27-AA26 -> 0 | AC27: =AC26 -> 1173391 | AD27: =AC27-AC26 -> 0 | AE27: =AB27+X27+T27 -> 0 | AF27: =V27+Z27+AD27 -> 0 | AG27: =IF(AE27>0,AF27/AE27,0) -> 0
A28: ='General information '!F29 -> 0 | B28: =SUM(230*A28) -> 0 | C28: =C27+1 -> 44982 | D28: =D27 -> 447720 | E28: =D28-D27 -> 0 | F28: =F27 -> 4201030 | G28: =F28-F27 -> 0 | H28: =H27 -> 18121674 | I28: =H28-H27 -> 0 | J28: =J27 -> 29924350 | K28: =J28-J27 -> 0 | L28: =L27 -> 24744706 | M28: =L28-L27 -> 0 | N28: =M28+K28+I28+G28+E28 -> 0 | O28: =IF(B28>0,N28/B28,0) -> 0 | P28: =P27 -> 19812.964 | Q28: =(P28-P27)*1000 -> 0 | R28: =N28-Q28 -> 0 | S28: =S27 -> 10175 | T28: =S28-S27 -> 0 | U28: =U27 -> 429166 | V28: =U28-U27 -> 0 | W28: =W27 -> 33503 | X28: =W28-W27 -> 0 | Y28: =Y27 -> 1001544 | Z28: =Y28-Y27 -> 0 | AA28: =AA27 -> 36804 | AB28: =AA28-AA27 -> 0 | AC28: =AC27 -> 1173391 | AD28: =AC28-AC27 -> 0 | AE28: =AB28+X28+T28 -> 0 | AF28: =V28+Z28+AD28 -> 0 | AG28: =IF(AE28>0,AF28/AE28,0) -> 0
A29: ='General information '!F30 -> 0 | B29: =SUM(230*A29) -> 0 | C29: =C28+1 -> 44983 | D29: 448240 | E29: =D29-D28 -> 520 | F29: 4201386 | G29: =F29-F28 -> 356 | H29: 18122118 | I29: =H29-H28 -> 444 | J29: 29925106 | K29: =J29-J28 -> 756 | L29: 24745510 | M29: =L29-L28 -> 804 | N29: =M29+K29+I29+G29+E29 -> 2880 | O29: =IF(B29>0,N29/B29,0) -> 0 | P29: 19815.371 | Q29: =(P29-P28)*1000 -> 2407 | R29: =N29-Q29 -> 473 | S29: =S28 -> 10175 | T29: =S29-S28 -> 0 | U29: =U28 -> 429166 | V29: =U29-U28 -> 0 | W29: =W28 -> 33503 | X29: =W29-W28 -> 0 | Y29: =Y28 -> 1001544 | Z29: =Y29-Y28 -> 0 | AA29: =AA28 -> 36804 | AB29: =AA29-AA28 -> 0 | AC29: =AC28 -> 1173391 | AD29: =AC29-AC28 -> 0 | AE29: =AB29+X29+T29 -> 0 | AF29: =V29+Z29+AD29 -> 0 | AG29: =IF(AE29>0,AF29/AE29,0) -> 0
A30: ='General information '!F31 -> 0 | B30: =SUM(230*A30) -> 0 | C30: =C29+1 -> 44984 | D30: 449010 | E30: =D30-D29 -> 770 | F30: 4201728 | G30: =F30-F29 -> 342 | H30: 18122546 | I30: =H30-H29 -> 428 | J30: 29925752 | K30: =J30-J29 -> 646 | L30: 24746262 | M30: =L30-L29 -> 752 | N30: =M30+K30+I30+G30+E30 -> 2938 | O30: =IF(B30>0,N30/B30,0) -> 0 | P30: 19817.695 | Q30: =(P30-P29)*1000 -> 2324 | R30: =N30-Q30 -> 614 | S30: =S29 -> 10175 | T30: =S30-S29 -> 0 | U30: =U29 -> 429166 | V30: =U30-U29 -> 0 | W30: =W29 -> 33503 | X30: =W30-W29 -> 0 | Y30: =Y29 -> 1001544 | Z30: =Y30-Y29 -> 0 | AA30: =AA29 -> 36804 | AB30: =AA30-AA29 -> 0 | AC30: =AC29 -> 1173391 | AD30: =AC30-AC29 -> 0 | AE30: =AB30+X30+T30 -> 0 | AF30: =V30+Z30+AD30 -> 0 | AG30: =IF(AE30>0,AF30/AE30,0) -> 0
A31: ='General information '!F32 -> 0 | B31: =SUM(230*A31) -> 0 | C31: =C30+1 -> 44985 | D31: =D30 -> 449010 | E31: =D31-D30 -> 0 | F31: =F30 -> 4201728 | G31: =F31-F30 -> 0 | H31: =H30 -> 18122546 | I31: =H31-H30 -> 0 | J31: =J30 -> 29925752 | K31: =J31-J30 -> 0 | L31: =L30 -> 24746262 | M31: =L31-L30 -> 0 | N31: =M31+K31+I31+G31+E31 -> 0 | O31: =IF(B31>0,N31/B31,0) -> 0 | P31: =P30 -> 19817.695 | Q31: =(P31-P30)*1000 -> 0 | R31: =N31-Q31 -> 0 | S31: =S30 -> 10175 | T31: =S31-S30 -> 0 | U31: =U30 -> 429166 | V31: =U31-U30 -> 0 | W31: =W30 -> 33503 | X31: =W31-W30 -> 0 | Y31: =Y30 -> 1001544 | Z31: =Y31-Y30 -> 0 | AA31: =AA30 -> 36804 | AB31: =AA31-AA30 -> 0 | AC31: =AC30 -> 1173391 | AD31: =AC31-AC30 -> 0 | AE31: =AB31+X31+T31 -> 0 | AF31: =V31+Z31+AD31 -> 0 | AG31: =IF(AE31>0,AF31/AE31,0) -> 0
A32: ='General information '!F33 -> 0 | B32: =SUM(230*A32) -> 0 | C32: =C31+1 -> 44986 | D32: =D31 -> 449010 | E32: =D32-D31 -> 0 | F32: =F31 -> 4201728 | G32: =F32-F31 -> 0 | H32: =H31 -> 18122546 | I32: =H32-H31 -> 0 | J32: =J31 -> 29925752 | K32: =J32-J31 -> 0 | L32: =L31 -> 24746262 | M32: =L32-L31 -> 0 | N32: =M32+K32+I32+G32+E32 -> 0 | O32: =IF(B32>0,N32/B32,0) -> 0 | P32: =P31 -> 19817.695 | Q32: =(P32-P31)*1000 -> 0 | R32: =N32-Q32 -> 0 | S32: =S31 -> 10175 | T32: =S32-S31 -> 0 | U32: =U31 -> 429166 | V32: =U32-U31 -> 0 | W32: =W31 -> 33503 | X32: =W32-W31 -> 0 | Y32: =Y31 -> 1001544 | Z32: =Y32-Y31 -> 0 | AA32: =AA31 -> 36804 | AB32: =AA32-AA31 -> 0 | AC32: =AC31 -> 1173391 | AD32: =AC32-AC31 -> 0 | AE32: =AB32+X32+T32 -> 0 | AF32: =V32+Z32+AD32 -> 0 | AG32: =IF(AE32>0,AF32/AE32,0) -> 0
A33: ='General information '!F34 -> 0 | B33: =SUM(230*A33) -> 0
A34: ='General information '!F35 -> 0 | B34: =SUM(230*A34) -> 0

Sheet B5
F1: Boiler A | J1: =#REF! -> #REF! | K1: Boiler B | P1: Boiler C | V1: Boiler | X1: SteamA | AC1: SteamB | AH1: Steam | AI1: Boiler & steam | AL1: Total Boiler Runing H | AM1: Total Steam Runing H | AN1: GAS1 % | AO1: GAS1/L | AP1: GAS2% | AQ1: Gas2/L | AR1: GAS3% | AS1: GAS3/L | AU1: Gas Cons | AV1: Delivery | AW1: Cost/L
B2: Level Tank Gen | C2: Level tank Boiler | D2: Daily Cons Bo. | E2: Boiler litter | F2: Boiler A | G2: Run Hr a | H2: Boiler A fuel | I2: Daily consumption | J2: AVG | K2: index Run H | L2: Run Hrb | M2: Boiler B Fuel | O2: Daily consumption | P2: Boiler C | S2: Run C | U2: Total RH | V2: Total Fuel | X2: SteamA | Y2: Run SA | Z2: Steam A Conter | AA2: Liters | AC2: SteamB | AD2: Run SteamB | AE2: Steam B Conter | AF2: SB Litters | AG2: Avg | AH2: Total Fuel | AI2: Total Fuel
S3: 0
A4: =ELEC!C3 -> 44957 | B4: 236 | C4: =[2]B5!C35 -> 241 | D4: =[2]B5!D35 -> 5.5 | E4: =[2]B5!E35 -> 46.09 | F4: =[2]B5!F35 -> 2382 | G4: =[2]B5!G35 -> 1 | H4: =[2]B5!H35 -> 54048 | I4: =[2]B5!I35 -> 53 | J4: =[2]B5!J35 -> 53 | ... L4: =[2]B5!L35 -> 0 | M4: 185690 | N4: =[2]B5!N35 -> 63 | O4: =[2]B5!O35 -> 2251 | P4: =[2]B5!P35 -> 2254 | Q4: =[2]B5!Q35 -> 188186 | R4: =[2]B5!R35 -> 128 | S4: =[2]B5!S35 -> 2 | T4: =[2]B5!T35 -> 0 | U4: =[2]B5!U35 -> 3 | ... AB4: =[2]B5!AB35 -> 0 | AC4: 1966 | AD4: =[2]B5!AD35 -> 0 | AE4: 368122 | AF4: =[2]B5!AF35 -> 0 | AG4: =[2]B5!AG35 -> 0 | AH4: =[2]B5!AH35 -> 0 | AI4: =[2]B5!AI35 -> 244 | AJ4: =[2]B5!AJ35 -> 244 | AK4: =[2]B5!AK35 -> 0 | AL4: =[2]B5!AL35 -> 3 | AM4: =[2]B5!AM35 -> 0 | ... AX4: =[2]B5!AX35 -> 0.8
A5: =ELEC!C4 -> 44958 | B5: 230 | C5: 236 | D5: =C4-C5 -> 5 | E5: =D5*8.38 -> 41.9 | F5: =F4 -> 2382 | G5: =F5-F4 -> 0 | H5: =H4 -> 54048 | I5: =SUM(H5-H4) -> 0 | J5: =IF(G5>0,I5/G5,0) -> 0 | K5: =K4 -> 2490 | L5: =K5-K4 -> 0 | M5: 185739 | N5: =M5-M4 -> 49 | O5: =O4 -> 2251 | P5: =P4 -> 2254 | Q5: =Q4 -> 188186 | R5: =Q5-Q4 -> 0 | S5: =SUM(P5-P4) -> 0 | T5: =SUM(S5*$T$2) -> 0 | U5: =SUM(G5+L5+S5) -> 0 | V5: =R5+N5+I5:I5 -> 49 | W5: =SUM(V5/U5) -> #DIV/0! | X5: =X4 -> 2498 | Y5: =X5-X4 -> 0 | Z5: =Z4 -> 141480 | AA5: =Z5-Z4 -> 0 | AB5: =SUM(Y5*$AB$2) -> 0 | AC5: 1966 | AD5: =AC5-AC4 -> 0 | AE5: 368122 | AF5: =AE5-AE4 -> 0 | AG5: =IF(AD5>0,AF5/AD5,0) -> 0 | AH5: =AF5+AA5 -> 0 | AI5: =SUM(AH5+V5) -> 49 | AJ5: =-tanks!AW7 -> 548 | AK5: =SUM(AJ5-AI5) -> 499 | AL5: =S5+L5+G5 -> 0 | AM5: =Y5+AD5 -> 0 | AN5: =AN4 -> 65 | AO5: =(AN5/100)*3000 -> 1950 | AP5: =AP4 -> 35 | AQ5: =(AP5/100)*3000 -> 1050 | AR5: =AR4 -> 73 | AS5: =(AR5/100)*3000 -> 2190 | AT5: =SUM(AO5+AQ5+AS5) -> 5190 | AU5: =AT4-AT5+AV5 -> 0 | AX5: =IF(AV5>0,AW5,AX4) -> 0.8
A6: =ELEC!C5 -> 44959 | B6: 226 | C6: 232 | D6: =C5-C6 -> 4 | E6: =D6*8.38 -> 33.52 | F6: 2382 | G6: =F6-F5 -> 0 | H6: 54054 | I6: =SUM(H6-H5) -> 6 | J6: =IF(G6>0,I6/G6,0) -> 0 | K6: =K5 -> 2490 | L6: =K6-K5 -> 0 | M6: 185739 | N6: =M6-M5 -> 0 | O6: =O5 -> 2251 | P6: 2258 | Q6: 188538 | R6: =Q6-Q5 -> 352 | S6: =SUM(P6-P5) -> 4 | T6: =SUM(S6*$T$2) -> 0 | U6: =SUM(G6+L6+S6) -> 4 | V6: =R6+N6+I6:I6 -> 358 | W6: =SUM(V6/U6) -> 89.5 | X6: =X5 -> 2498 | Y6: =X6-X5 -> 0 | Z6: =Z5 -> 141480 | AA6: =Z6-Z5 -> 0 | AB6: =SUM(Y6*$AB$2) -> 0 | AC6: 1968 | AD6: =AC6-AC5 -> 2 | AE6: 368312 | AF6: =AE6-AE5 -> 190 | AG6: =IF(AD6>0,AF6/AD6,0) -> 95 | AH6: =AF6+AA6 -> 190 | AI6: =SUM(AH6+V6) -> 548 | AJ6: =-tanks!AW8 -> 0.6 | AK6: =SUM(AJ6-AI6) -> -547.4 | AL6: =S6+L6+G6 -> 4 | AM6: =Y6+AD6 -> 2 | AN6: =AN5 -> 65 | AO6: =(AN6/100)*3000 -> 1950 | AP6: =AP5 -> 35 | AQ6: =(AP6/100)*3000 -> 1050 | AR6: =AR5 -> 73 | AS6: =(AR6/100)*3000 -> 2190 | AT6: =SUM(AO6+AQ6+AS6) -> 5190 | AU6: =AT5-AT6+AV6 -> 0 | AX6: =IF(AV6>0,AW6,AX5) -> 0.8
A7: =ELEC!C6 -> 44960 | B7: 226 | C7: 232 | D7: =C6-C7 -> 0 | E7: =D7*8.38 -> 0 | F7: 2382 | G7: =F7-F6 -> 0 | H7: 54054 | I7: =SUM(H7-H6) -> 0 | J7: =IF(G7>0,I7/G7,0) -> 0 | K7: 2490 | L7: =K7-K6 -> 0 | M7: 185739 | N7: =M7-M6 -> 0 | O7: =O6 -> 2251 | P7: 2258 | Q7: 188538 | R7: =Q7-Q6 -> 0 | S7: =SUM(P7-P6) -> 0 | T7: =SUM(S7*$T$2) -> 0 | U7: =SUM(G7+L7+S7) -> 0 | V7: =R7+N7+I7:I7 -> 0 | W7: =SUM(V7/U7) -> #DIV/0! | X7: =X6 -> 2498 | Y7: =X7-X6 -> 0 | Z7: =Z6 -> 141480 | AA7: =Z7-Z6 -> 0 | AB7: =SUM(Y7*$AB$2) -> 0 | AC7: =AC6 -> 1968 | AD7: =AC7-AC6 -> 0 | AE7: 368312.6 | AF7: =AE7-AE6 -> 0.6 | AG7: =IF(AD7>0,AF7/AD7,0) -> 0 | AH7: =AF7+AA7 -> 0.6 | AI7: =SUM(AH7+V7) -> 0.6 | AJ7: =-tanks!AW9 -> 0 | AK7: =SUM(AJ7-AI7) -> -0.6 | AL7: =S7+L7+G7 -> 0 | AM7: =Y7+AD7 -> 0 | AN7: =AN6 -> 65 | AO7: =(AN7/100)*3000 -> 1950 | AP7: =AP6 -> 35 | AQ7: =(AP7/100)*3000 -> 1050 | AR7: =AR6 -> 73 | AS7: =(AR7/100)*3000 -> 2190 | AT7: =SUM(AO7+AQ7+AS7) -> 5190 | AU7: =AT6-AT7+AV7 -> 0 | AX7: =IF(AV7>0,AW7,AX6) -> 0.8
A8: =ELEC!C7 -> 44961 | B8: =B7 -> 226 | C8: =C7 -> 232 | D8: =C7-C8 -> 0 | E8: =D8*8.38 -> 0 | F8: =F7 -> 2382 | G8: =F8-F7 -> 0 | H8: =H7 -> 54054 | I8: =SUM(H8-H7) -> 0 | J8: =IF(G8>0,I8/G8,0) -> 0 | K8: =K7 -> 2490 | L8: =K8-K7 -> 0 | M8: =M7 -> 185739 | N8: =M8-M7 -> 0 | O8: =O7 -> 2251 | P8: =P7 -> 2258 | Q8: =Q7 -> 188538 | R8: =Q8-Q7 -> 0 | S8: =SUM(P8-P7) -> 0 | T8: =SUM(S8*$T$2) -> 0 | U8: =SUM(G8+L8+S8) -> 0 | V8: =R8+N8+I8:I8 -> 0 | W8: =SUM(V8/U8) -> #DIV/0! | X8: =X7 -> 2498 | Y8: =X8-X7 -> 0 | Z8: =Z7 -> 141480 | AA8: =Z8-Z7 -> 0 | AB8: =SUM(Y8*$AB$2) -> 0 | AC8: =AC7 -> 1968 | AD8: =AC8-AC7 -> 0 | AE8: =AE7 -> 368312.6 | AF8: =AE8-AE7 -> 0 | AG8: =IF(AD8>0,AF8/AD8,0) -> 0 | AH8: =AF8+AA8 -> 0 | AI8: =SUM(AH8+V8) -> 0 | AJ8: =-tanks!AW10 -> 203 | AK8: =SUM(AJ8-AI8) -> 203 | AL8: =S8+L8+G8 -> 0 | AM8: =Y8+AD8 -> 0 | AN8: =AN7 -> 65 | AO8: =(AN8/100)*3000 -> 1950 | AP8: =AP7 -> 35 | AQ8: =(AP8/100)*3000 -> 1050 | AR8: =AR7 -> 73 | AS8: =(AR8/100)*3000 -> 2190 | AT8: =SUM(AO8+AQ8+AS8) -> 5190 | AU8: =AT7-AT8+AV8 -> 0 | AX8: =IF(AV8>0,AW8,AX7) -> 0.8
A9: =ELEC!C8 -> 44962 | B9: 222 | C9: 228 | D9: =C8-C9 -> 4 | E9: =D9*8.38 -> 33.52 | F9: =F8 -> 2382 | G9: =F9-F8 -> 0 | H9: =H8 -> 54054 | I9: =SUM(H9-H8) -> 0 | J9: =IF(G9>0,I9/G9,0) -> 0 | K9: =K8 -> 2490 | L9: =K9-K8 -> 0 | M9: 185760 | N9: =M9-M8 -> 21 | O9: =O8 -> 2251 | P9: 2261 | Q9: 188720 | R9: =Q9-Q8 -> 182 | S9: =SUM(P9-P8) -> 3 | T9: =SUM(S9*$T$2) -> 0 | U9: =SUM(G9+L9+S9) -> 3 | V9: =R9+N9+I9:I9 -> 203 | W9: =SUM(V9/U9) -> 67.666667 | X9: =X8 -> 2498 | Y9: =X9-X8 -> 0 | Z9: =Z8 -> 141480 | AA9: =Z9-Z8 -> 0 | AB9: =SUM(Y9*$AB$2) -> 0 | AC9: =AC8 -> 1968 | AD9: =AC9-AC8 -> 0 | AE9: =AE8 -> 368312.6 | AF9: =AE9-AE8 -> 0 | AG9: =IF(AD9>0,AF9/AD9,0) -> 0 | AH9: =AF9+AA9 -> 0 | AI9: =SUM(AH9+V9) -> 203 | AJ9: =-tanks!AW11 -> 280.4 | AK9: =SUM(AJ9-AI9) -> 77.4 | AL9: =S9+L9+G9 -> 3 | AM9: =Y9+AD9 -> 0 | AN9: =AN8 -> 65 | AO9: =(AN9/100)*3000 -> 1950 | AP9: =AP8 -> 35 | AQ9: =(AP9/100)*3000 -> 1050 | AR9: =AR8 -> 73 | AS9: =(AR9/100)*3000 -> 2190 | AT9: =SUM(AO9+AQ9+AS9) -> 5190 | AU9: =AT8-AT9+AV9 -> 0 | AX9: =IF(AV9>0,AW9,AX8) -> 0.8
A10: =ELEC!C9 -> 44963 | B10: 217 | C10: 223 | D10: =C9-C10 -> 5 | E10: =D10*8.38 -> 41.9 | F10: =F9 -> 2382 | G10: =F10-F9 -> 0 | H10: =H9 -> 54054 | I10: =SUM(H10-H9) -> 0 | J10: =IF(G10>0,I10/G10,0) -> 0 | K10: 2492 | L10: =K10-K9 -> 2 | M10: 185870 | N10: =M10-M9 -> 110 | O10: =O9 -> 2251 | P10: 2262 | Q10: 188821 | R10: =Q10-Q9 -> 101 | S10: =SUM(P10-P9) -> 1 | T10: =SUM(S10*$T$2) -> 0 | U10: =SUM(G10+L10+S10) -> 3 | V10: =R10+N10+I10:I10 -> 211 | W10: =SUM(V10/U10) -> 70.333333 | X10: =X9 -> 2498 | Y10: =X10-X9 -> 0 | Z10: =Z9 -> 141480 | AA10: =Z10-Z9 -> 0 | AB10: =SUM(Y10*$AB$2) -> 0 | AC10: 1969 | AD10: =AC10-AC9 -> 1 | AE10: 368382 | AF10: =AE10-AE9 -> 69.4 | AG10: =IF(AD10>0,AF10/AD10,0) -> 69.4 | AH10: =AF10+AA10 -> 69.4 | AI10: =SUM(AH10+V10) -> 280.4 | AJ10: =-tanks!AW12 -> 191 | AK10: =SUM(AJ10-AI10) -> -89.4 | AL10: =S10+L10+G10 -> 3 | AM10: =Y10+AD10 -> 1 | AN10: =AN9 -> 65 | AO10: =(AN10/100)*3000 -> 1950 | AP10: =AP9 -> 35 | AQ10: =(AP10/100)*3000 -> 1050 | AR10: =AR9 -> 73 | AS10: =(AR10/100)*3000 -> 2190 | AT10: =SUM(AO10+AQ10+AS10) -> 5190 | AU10: =AT9-AT10+AV10 -> 0 | AX10: =IF(AV10>0,AW10,AX9) -> 0.8
A11: =ELEC!C10 -> 44964 | B11: 212 | C11: 219 | D11: =C10-C11 -> 4 | E11: =D11*8.38 -> 33.52 | F11: =F10 -> 2382 | G11: =F11-F10 -> 0 | H11: =H10 -> 54054 | I11: =SUM(H11-H10) -> 0 | J11: =IF(G11>0,I11/G11,0) -> 0 | K11: =K10 -> 2492 | L11: =K11-K10 -> 0 | M11: 185894 | N11: =M11-M10 -> 24 | O11: =O10 -> 2251 | P11: 2264 | Q11: 188988 | R11: =Q11-Q10 -> 167 | S11: =SUM(P11-P10) -> 2 | T11: =SUM(S11*$T$2) -> 0 | U11: =SUM(G11+L11+S11) -> 2 | V11: =R11+N11+I11:I11 -> 191 | W11: =SUM(V11/U11) -> 95.5 | X11: =X10 -> 2498 | Y11: =X11-X10 -> 0 | Z11: =Z10 -> 141480 | AA11: =Z11-Z10 -> 0 | AB11: =SUM(Y11*$AB$2) -> 0 | AC11: =AC10 -> 1969 | AD11: =AC11-AC10 -> 0 | AE11: =AE10 -> 368382 | AF11: =AE11-AE10 -> 0 | AG11: =IF(AD11>0,AF11/AD11,0) -> 0 | AH11: =AF11+AA11 -> 0 | AI11: =SUM(AH11+V11) -> 191 | AJ11: =-tanks!AW13 -> 321 | AK11: =SUM(AJ11-AI11) -> 130 | AL11: =S11+L11+G11 -> 2 | AM11: =Y11+AD11 -> 0 | AN11: =AN10 -> 65 | AO11: =(AN11/100)*3000 -> 1950 | AP11: =AP10 -> 35 | AQ11: =(AP11/100)*3000 -> 1050 | AR11: =AR10 -> 73 | AS11: =(AR11/100)*3000 -> 2190 | AT11: =SUM(AO11+AQ11+AS11) -> 5190 | AU11: =AT10-AT11+AV11 -> 0 | AX11: =IF(AV11>0,AW11,AX10) -> 0.8
A12: =ELEC!C11 -> 44965 | B12: 235 | C12: 241 | D12: =C11-C12 -> -22 | E12: =D12*8.38 -> -184.36 | F12: =F11 -> 2382 | G12: =F12-F11 -> 0 | H12: =H11 -> 54054 | I12: =SUM(H12-H11) -> 0 | J12: =IF(G12>0,I12/G12,0) -> 0 | K12: =K11 -> 2492 | L12: =K12-K11 -> 0 | M12: =M11 -> 185894 | N12: =M12-M11 -> 0 | O12: =O11 -> 2251 | P12: 2268 | Q12: 189309 | R12: =Q12-Q11 -> 321 | S12: =SUM(P12-P11) -> 4 | T12: =SUM(S12*$T$2) -> 0 | U12: =SUM(G12+L12+S12) -> 4 | V12: =R12+N12+I12:I12 -> 321 | W12: =SUM(V12/U12) -> 80.25 | X12: =X11 -> 2498 | Y12: =X12-X11 -> 0 | Z12: =Z11 -> 141480 | AA12: =Z12-Z11 -> 0 | AB12: =SUM(Y12*$AB$2) -> 0 | AC12: =AC11 -> 1969 | AD12: =AC12-AC11 -> 0 | AE12: =AE11 -> 368382 | AF12: =AE12-AE11 -> 0 | AG12: =IF(AD12>0,AF12/AD12,0) -> 0 | AH12: =AF12+AA12 -> 0 | AI12: =SUM(AH12+V12) -> 321 | AJ12: =-tanks!AW14 -> 0 | AK12: =SUM(AJ12-AI12) -> -321 | AL12: =S12+L12+G12 -> 4 | AM12: =Y12+AD12 -> 0 | AN12: =AN11 -> 65 | AO12: =(AN12/100)*3000 -> 1950 | AP12: =AP11 -> 35 | AQ12: =(AP12/100)*3000 -> 1050 | AR12: =AR11 -> 73 | AS12: =(AR12/100)*3000 -> 2190 | AT12: =SUM(AO12+AQ12+AS12) -> 5190 | AU12: =AT11-AT12+AV12 -> 0 | AX12: =IF(AV12>0,AW12,AX11) -> 0.8
A13: =ELEC!C12 -> 44966 | B13: =B12 -> 235 | C13: =C12 -> 241 | D13: =C12-C13 -> 0 | E13: =D13*8.38 -> 0 | F13: =F12 -> 2382 | G13: =F13-F12 -> 0 | H13: =H12 -> 54054 | I13: =SUM(H13-H12) -> 0 | J13: =IF(G13>0,I13/G13,0) -> 0 | K13: =K12 -> 2492 | L13: =K13-K12 -> 0 | M13: =M12 -> 185894 | N13: =M13-M12 -> 0 | O13: =O12 -> 2251 | P13: =P12 -> 2268 | Q13: =Q12 -> 189309 | R13: =Q13-Q12 -> 0 | S13: =SUM(P13-P12) -> 0 | T13: =SUM(S13*$T$2) -> 0 | U13: =SUM(G13+L13+S13) -> 0 | V13: =R13+N13+I13:I13 -> 0 | W13: =SUM(V13/U13) -> #DIV/0! | X13: =X12 -> 2498 | Y13: =X13-X12 -> 0 | Z13: =Z12 -> 141480 | AA13: =Z13-Z12 -> 0 | AB13: =SUM(Y13*$AB$2) -> 0 | AC13: =AC12 -> 1969 | AD13: =AC13-AC12 -> 0 | AE13: =AE12 -> 368382 | AF13: =AE13-AE12 -> 0 | AG13: =IF(AD13>0,AF13/AD13,0) -> 0 | AH13: =AF13+AA13 -> 0 | AI13: =SUM(AH13+V13) -> 0 | AJ13: =-tanks!AW15 -> 0 | AK13: =SUM(AJ13-AI13) -> 0 | AL13: =S13+L13+G13 -> 0 | AM13: =Y13+AD13 -> 0 | AN13: =AN12 -> 65 | AO13: =(AN13/100)*3000 -> 1950 | AP13: =AP12 -> 35 | AQ13: =(AP13/100)*3000 -> 1050 | AR13: =AR12 -> 73 | AS13: =(AR13/100)*3000 -> 2190 | AT13: =SUM(AO13+AQ13+AS13) -> 5190 | AU13: =AT12-AT13+AV13 -> 0 | AX13: =IF(AV13>0,AW13,AX12) -> 0.8
A14: =ELEC!C13 -> 44967 | B14: =B13 -> 235 | C14: =C13 -> 241 | D14: =C13-C14 -> 0 | E14: =D14*8.38 -> 0 | F14: =F13 -> 2382 | G14: =F14-F13 -> 0 | H14: =H13 -> 54054 | I14: =SUM(H14-H13) -> 0 | J14: =IF(G14>0,I14/G14,0) -> 0 | K14: =K13 -> 2492 | L14: =K14-K13 -> 0 | M14: =M13 -> 185894 | N14: =M14-M13 -> 0 | O14: =O13 -> 2251 | P14: =P13 -> 2268 | Q14: =Q13 -> 189309 | R14: =Q14-Q13 -> 0 | S14: =SUM(P14-P13) -> 0 | T14: =SUM(S14*$T$2) -> 0 | U14: =SUM(G14+L14+S14) -> 0 | V14: =R14+N14+I14:I14 -> 0 | W14: =SUM(V14/U14) -> #DIV/0! | X14: =X13 -> 2498 | Y14: =X14-X13 -> 0 | Z14: =Z13 -> 141480 | AA14: =Z14-Z13 -> 0 | AB14: =SUM(Y14*$AB$2) -> 0 | AC14: =AC13 -> 1969 | AD14: =AC14-AC13 -> 0 | AE14: =AE13 -> 368382 | AF14: =AE14-AE13 -> 0 | AG14: =IF(AD14>0,AF14/AD14,0) -> 0 | AH14: =AF14+AA14 -> 0 | AI14: =SUM(AH14+V14) -> 0 | AJ14: =-tanks!AW16 -> 0 | AK14: =SUM(AJ14-AI14) -> 0 | AL14: =S14+L14+G14 -> 0 | AM14: =Y14+AD14 -> 0 | AN14: =AN13 -> 65 | AO14: =(AN14/100)*3000 -> 1950 | AP14: =AP13 -> 35 | AQ14: =(AP14/100)*3000 -> 1050 | AR14: =AR13 -> 73 | AS14: =(AR14/100)*3000 -> 2190 | AT14: =SUM(AO14+AQ14+AS14) -> 5190 | AU14: =AT13-AT14+AV14 -> 0 | AX14: =IF(AV14>0,AW14,AX13) -> 0.8
A15: =ELEC!C14 -> 44968 | B15: =B14 -> 235 | C15: =C14 -> 241 | D15: =C14-C15 -> 0 | E15: =D15*8.38 -> 0 | F15: =F14 -> 2382 | G15: =F15-F14 -> 0 | H15: =H14 -> 54054 | I15: =SUM(H15-H14) -> 0 | J15: =IF(G15>0,I15/G15,0) -> 0 | K15: =K14 -> 2492 | L15: =K15-K14 -> 0 | M15: =M14 -> 185894 | N15: =M15-M14 -> 0 | O15: =O14 -> 2251 | P15: =P14 -> 2268 | Q15: =Q14 -> 189309 | R15: =Q15-Q14 -> 0 | S15: =SUM(P15-P14) -> 0 | T15: =SUM(S15*$T$2) -> 0 | U15: =SUM(G15+L15+S15) -> 0 | V15: =R15+N15+I15:I15 -> 0 | W15: =SUM(V15/U15) -> #DIV/0! | X15: =X14 -> 2498 | Y15: =X15-X14 -> 0 | Z15: =Z14 -> 141480 | AA15: =Z15-Z14 -> 0 | AB15: =SUM(Y15*$AB$2) -> 0 | AC15: =AC14 -> 1969 | AD15: =AC15-AC14 -> 0 | AE15: =AE14 -> 368382 | AF15: =AE15-AE14 -> 0 | AG15: =IF(AD15>0,AF15/AD15,0) -> 0 | AH15: =AF15+AA15 -> 0 | AI15: =SUM(AH15+V15) -> 0 | AJ15: =-tanks!AW17 -> 636 | AK15: =SUM(AJ15-AI15) -> 636 | AL15: =S15+L15+G15 -> 0 | AM15: =Y15+AD15 -> 0 | AN15: =AN14 -> 65 | AO15: =(AN15/100)*3000 -> 1950 | AP15: =AP14 -> 35 | AQ15: =(AP15/100)*3000 -> 1050 | AR15: =AR14 -> 73 | AS15: =(AR15/100)*3000 -> 2190 | AT15: =SUM(AO15+AQ15+AS15) -> 5190 | AU15: =AT14-AT15+AV15 -> 0 | AX15: =IF(AV15>0,AW15,AX14) -> 0.8
A16: =ELEC!C15 -> 44969 | B16: 230 | C16: 236 | D16: =C15-C16 -> 5 | E16: =D16*8.38 -> 41.9 | F16: =F15 -> 2382 | G16: =F16-F15 -> 0 | H16: =H15 -> 54054 | I16: =SUM(H16-H15) -> 0 | J16: =IF(G16>0,I16/G16,0) -> 0 | K16: =K15 -> 2492 | L16: =K16-K15 -> 0 | M16: =M15 -> 185894 | N16: =M16-M15 -> 0 | O16: =O15 -> 2251 | P16: 2275 | Q16: 189801 | R16: =Q16-Q15 -> 492 | S16: =SUM(P16-P15) -> 7 | T16: =SUM(S16*$T$2) -> 0 | U16: =SUM(G16+L16+S16) -> 7 | V16: =R16+N16+I16:I16 -> 492 | X16: 2499 | Y16: =X16-X15 -> 1 | Z16: 141557 | AA16: =Z16-Z15 -> 77 | AB16: =SUM(Y16*$AB$2) -> 0 | AC16: 1970 | AD16: =AC16-AC15 -> 1 | AE16: 368449 | AF16: =AE16-AE15 -> 67 | AG16: =IF(AD16>0,AF16/AD16,0) -> 67 | AH16: =AF16+AA16 -> 144 | AI16: =SUM(AH16+V16) -> 636 | AJ16: =-tanks!AW18 -> 124 | AK16: =SUM(AJ16-AI16) -> -512 | AL16: =S16+L16+G16 -> 7 | AM16: =Y16+AD16 -> 2 | AN16: =AN15 -> 65 | AO16: =(AN16/100)*3000 -> 1950 | AP16: =AP15 -> 35 | AQ16: =(AP16/100)*3000 -> 1050 | AR16: =AR15 -> 73 | AS16: =(AR16/100)*3000 -> 2190 | AT16: =SUM(AO16+AQ16+AS16) -> 5190 | AU16: =AT15-AT16+AV16 -> 0 | AX16: =IF(AV16>0,AW16,AX15) -> 0.8
A17: =ELEC!C16 -> 44970 | B17: 227 | C17: 233 | D17: =C16-C17 -> 3 | E17: =D17*8.38 -> 25.14 | F17: 2383 | G17: =F17-F16 -> 1 | H17: 54097 | I17: =SUM(H17-H16) -> 43 | J17: =IF(G17>0,I17/G17,0) -> 43 | K17: 2492 | L17: =K17-K16 -> 0 | M17: =M16 -> 185894 | N17: =M17-M16 -> 0 | O17: 1869 | P17: =P16 -> 2275 | Q17: 189842 | R17: =Q17-Q16 -> 41 | S17: =SUM(P17-P16) -> 0 | T17: =SUM(S17*$T$2) -> 0 | U17: =SUM(G17+L17+S17) -> 1 | V17: =R17+N17+I17:I17 -> 84 | X17: =X16 -> 2499 | Y17: =X17-X16 -> 0 | Z17: 141597 | AA17: =Z17-Z16 -> 40 | AB17: =SUM(Y17*$AB$2) -> 0 | AC17: =AC16 -> 1970 | AD17: =AC17-AC16 -> 0 | AE17: =AE16 -> 368449 | AF17: =AE17-AE16 -> 0 | AG17: =IF(AD17>0,AF17/AD17,0) -> 0 | AH17: =AF17+AA17 -> 40 | AI17: =SUM(AH17+V17) -> 124 | AJ17: =-tanks!AW19 -> 300 | AK17: =SUM(AJ17-AI17) -> 176 | AL17: =S17+L17+G17 -> 1 | AM17: =Y17+AD17 -> 0 | AN17: =AN16 -> 65 | AO17: =(AN17/100)*3000 -> 1950 | AP17: =AP16 -> 35 | AQ17: =(AP17/100)*3000 -> 1050 | AR17: =AR16 -> 73 | AS17: =(AR17/100)*3000 -> 2190 | AT17: =SUM(AO17+AQ17+AS17) -> 5190 | AU17: =AT16-AT17+AV17 -> 0 | AX17: =IF(AV17>0,AW17,AX16) -> 0.8
A18: =ELEC!C17 -> 44971 | B18: 223 | C18: 230 | D18: =C17-C18 -> 3 | E18: =D18*8.38 -> 25.14 | F18: 2387 | G18: =F18-F17 -> 4 | H18: 54397 | I18: =SUM(H18-H17) -> 300 | J18: =IF(G18>0,I18/G18,0) -> 75 | K18: =K17 -> 2492 | L18: =K18-K17 -> 0 | M18: =M17 -> 185894 | N18: =M18-M17 -> 0 | O18: =O17 -> 1869 | P18: =P17 -> 2275 | Q18: =Q17 -> 189842 | R18: =Q18-Q17 -> 0 | S18: =SUM(P18-P17) -> 0 | T18: =SUM(S18*$T$2) -> 0 | U18: =SUM(G18+L18+S18) -> 4 | V18: =R18+N18+I18:I18 -> 300 | X18: =X17 -> 2499 | Y18: =X18-X17 -> 0 | Z18: =Z17 -> 141597 | AA18: =Z18-Z17 -> 0 | AB18: =SUM(Y18*$AB$2) -> 0 | AC18: =AC17 -> 1970 | AD18: =AC18-AC17 -> 0 | AE18: =AE17 -> 368449 | AF18: =AE18-AE17 -> 0 | AG18: =IF(AD18>0,AF18/AD18,0) -> 0 | AH18: =AF18+AA18 -> 0 | AI18: =SUM(AH18+V18) -> 300 | AJ18: =-tanks!AW20 -> 310 | AK18: =SUM(AJ18-AI18) -> 10 | AL18: =S18+L18+G18 -> 4 | AM18: =Y18+AD18 -> 0 | AN18: =AN17 -> 65 | AO18: =(AN18/100)*3000 -> 1950 | AP18: =AP17 -> 35 | AQ18: =(AP18/100)*3000 -> 1050 | AR18: =AR17 -> 73 | AS18: =(AR18/100)*3000 -> 2190 | AT18: =SUM(AO18+AQ18+AS18) -> 5190 | AU18: =AT17-AT18+AV18 -> 0 | AX18: =IF(AV18>0,AW18,AX17) -> 0.8
A19: =ELEC!C18 -> 44972 | B19: 220 | C19: 226 | D19: =C18-C19 -> 4 | E19: =D19*8.38 -> 33.52 | F19: 2391 | G19: =F19-F18 -> 4 | H19: 54707 | I19: =SUM(H19-H18) -> 310 | J19: =IF(G19>0,I19/G19,0) -> 77.5 | K19: =K18 -> 2492 | L19: =K19-K18 -> 0 | M19: =M18 -> 185894 | N19: =M19-M18 -> 0 | O19: =O18 -> 1869 | P19: =P18 -> 2275 | Q19: =Q18 -> 189842 | R19: =Q19-Q18 -> 0 | S19: =SUM(P19-P18) -> 0 | T19: =SUM(S19*$T$2) -> 0 | U19: =SUM(G19+L19+S19) -> 4 | V19: =R19+N19+I19:I19 -> 310 | X19: =X18 -> 2499 | Y19: =X19-X18 -> 0 | Z19: =Z18 -> 141597 | AA19: =Z19-Z18 -> 0 | AB19: =SUM(Y19*$AB$2) -> 0 | AC19: =AC18 -> 1970 | AD19: =AC19-AC18 -> 0 | AE19: =AE18 -> 368449 | AF19: =AE19-AE18 -> 0 | AG19: =IF(AD19>0,AF19/AD19,0) -> 0 | AH19: =AF19+AA19 -> 0 | AI19: =SUM(AH19+V19) -> 310 | AJ19: =-tanks!AW21 -> 263 | AK19: =SUM(AJ19-AI19) -> -47 | AL19: =S19+L19+G19 -> 4 | AM19: =Y19+AD19 -> 0 | AN19: =AN18 -> 65 | AO19: =(AN19/100)*3000 -> 1950 | AP19: =AP18 -> 35 | AQ19: =(AP19/100)*3000 -> 1050 | AR19: =AR18 -> 73 | AS19: =(AR19/100)*3000 -> 2190 | AT19: =SUM(AO19+AQ19+AS19) -> 5190 | AU19: =AT18-AT19+AV19 -> 0 | AX19: =IF(AV19>0,AW19,AX18) -> 0.8
A20: =ELEC!C19 -> 44973 | B20: 237 | C20: 243 | D20: =C19-C20 -> -17 | E20: =D20*8.38 -> -142.46 | F20: 2393 | G20: =F20-F19 -> 2 | H20: 54894 | I20: =SUM(H20-H19) -> 187 | J20: =IF(G20>0,I20/G20,0) -> 93.5 | K20: =K19 -> 2492 | L20: =K20-K19 -> 0 | M20: =M19 -> 185894 | N20: =M20-M19 -> 0 | O20: =O19 -> 1869 | P20: =P19 -> 2275 | Q20: =Q19 -> 189842 | R20: =Q20-Q19 -> 0 | S20: =SUM(P20-P19) -> 0 | T20: =SUM(S20*$T$2) -> 0 | U20: =SUM(G20+L20+S20) -> 2 | V20: =R20+N20+I20:I20 -> 187 | X20: =X19 -> 2499 | Y20: =X20-X19 -> 0 | Z20: =Z19 -> 141597 | AA20: =Z20-Z19 -> 0 | AB20: =SUM(Y20*$AB$2) -> 0 | AC20: 1972 | AD20: =AC20-AC19 -> 2 | AE20: 368525 | AF20: =AE20-AE19 -> 76 | AG20: =IF(AD20>0,AF20/AD20,0) -> 38 | AH20: =AF20+AA20 -> 76 | AI20: =SUM(AH20+V20) -> 263 | AJ20: =-tanks!AW22 -> 0 | AK20: =SUM(AJ20-AI20) -> -263 | AL20: =S20+L20+G20 -> 2 | AM20: =Y20+AD20 -> 2 | AN20: =AN19 -> 65 | AO20: =(AN20/100)*3000 -> 1950 | AP20: =AP19 -> 35 | AQ20: =(AP20/100)*3000 -> 1050 | AR20: =AR19 -> 73 | AS20: =(AR20/100)*3000 -> 2190 | AT20: =SUM(AO20+AQ20+AS20) -> 5190 | AU20: =AT19-AT20+AV20 -> 0 | AX20: =IF(AV20>0,AW20,AX19) -> 0.8
A21: =ELEC!C20 -> 44974 | B21: =B20 -> 237 | C21: =C20 -> 243 | D21: =C20-C21 -> 0 | E21: =D21*8.38 -> 0 | F21: =F20 -> 2393 | G21: =F21-F20 -> 0 | H21: =H20 -> 54894 | I21: =SUM(H21-H20) -> 0 | J21: =IF(G21>0,I21/G21,0) -> 0 | K21: =K20 -> 2492 | L21: =K21-K20 -> 0 | M21: =M20 -> 185894 | N21: =M21-M20 -> 0 | O21: =O20 -> 1869 | P21: =P20 -> 2275 | Q21: =Q20 -> 189842 | R21: =Q21-Q20 -> 0 | S21: =SUM(P21-P20) -> 0 | T21: =SUM(S21*$T$2) -> 0 | U21: =SUM(G21+L21+S21) -> 0 | V21: =R21+N21+I21:I21 -> 0 | X21: =X20 -> 2499 | Y21: =X21-X20 -> 0 | Z21: =Z20 -> 141597 | AA21: =Z21-Z20 -> 0 | AB21: =SUM(Y21*$AB$2) -> 0 | AC21: =AC20 -> 1972 | AD21: =AC21-AC20 -> 0 | AE21: =AE20 -> 368525 | AF21: =AE21-AE20 -> 0 | AG21: =IF(AD21>0,AF21/AD21,0) -> 0 | AH21: =AF21+AA21 -> 0 | AI21: =SUM(AH21+V21) -> 0 | AJ21: =-tanks!AW23 -> 0 | AK21: =SUM(AJ21-AI21) -> 0 | AL21: =S21+L21+G21 -> 0 | AM21: =Y21+AD21 -> 0 | AN21: =AN20 -> 65 | AO21: =(AN21/100)*3000 -> 1950 | AP21: =AP20 -> 35 | AQ21: =(AP21/100)*3000 -> 1050 | AR21: =AR20 -> 73 | AS21: =(AR21/100)*3000 -> 2190 | AT21: =SUM(AO21+AQ21+AS21) -> 5190 | AU21: =AT20-AT21+AV21 -> 0 | AX21: =IF(AV21>0,AW21,AX20) -> 0.8
A22: =ELEC!C21 -> 44975 | B22: =B21 -> 237 | C22: =C21 -> 243 | D22: =C21-C22 -> 0 | E22: =D22*8.38 -> 0 | F22: =F21 -> 2393 | G22: =F22-F21 -> 0 | H22: =H21 -> 54894 | I22: =SUM(H22-H21) -> 0 | J22: =IF(G22>0,I22/G22,0) -> 0 | K22: =K21 -> 2492 | L22: =K22-K21 -> 0 | M22: =M21 -> 185894 | N22: =M22-M21 -> 0 | O22: =O21 -> 1869 | P22: =P21 -> 2275 | Q22: =Q21 -> 189842 | R22: =Q22-Q21 -> 0 | S22: =SUM(P22-P21) -> 0 | T22: =SUM(S22*$T$2) -> 0 | U22: =SUM(G22+L22+S22) -> 0 | V22: =R22+N22+I22:I22 -> 0 | X22: =X21 -> 2499 | Y22: =X22-X21 -> 0 | Z22: =Z21 -> 141597 | AA22: =Z22-Z21 -> 0 | AB22: =SUM(Y22*$AB$2) -> 0 | AC22: =AC21 -> 1972 | AD22: =AC22-AC21 -> 0 | AE22: =AE21 -> 368525 | AF22: =AE22-AE21 -> 0 | AG22: =IF(AD22>0,AF22/AD22,0) -> 0 | AH22: =AF22+AA22 -> 0 | AI22: =SUM(AH22+V22) -> 0 | AJ22: =-tanks!AW24 -> 180 | AK22: =SUM(AJ22-AI22) -> 180 | AL22: =S22+L22+G22 -> 0 | AM22: =Y22+AD22 -> 0 | AN22: =AN21 -> 65 | AO22: =(AN22/100)*3000 -> 1950 | AP22: =AP21 -> 35 | AQ22: =(AP22/100)*3000 -> 1050 | AR22: =AR21 -> 73 | AS22: =(AR22/100)*3000 -> 2190 | AT22: =SUM(AO22+AQ22+AS22) -> 5190 | AU22: =AT21-AT22+AV22 -> 0 | AX22: =IF(AV22>0,AW22,AX21) -> 0.8
A23: =ELEC!C22 -> 44976 | B23: 234 | C23: 240 | D23: =C22-C23 -> 3 | E23: =D23*8.38 -> 25.14 | F23: 2396 | G23: =F23-F22 -> 3 | H23: 55074 | I23: =SUM(H23-H22) -> 180 | J23: =IF(G23>0,I23/G23,0) -> 60 | K23: 2492 | L23: =K23-K22 -> 0 | M23: =M22 -> 185894 | N23: =M23-M22 -> 0 | O23: =O22 -> 1869 | P23: =P22 -> 2275 | Q23: =Q22 -> 189842 | R23: =Q23-Q22 -> 0 | S23: =SUM(P23-P22) -> 0 | T23: =SUM(S23*$T$2) -> 0 | U23: =SUM(G23+L23+S23) -> 3 | V23: =R23+N23+I23:I23 -> 180 | X23: =X22 -> 2499 | Y23: =X23-X22 -> 0 | Z23: =Z22 -> 141597 | AA23: =Z23-Z22 -> 0 | AB23: =SUM(Y23*$AB$2) -> 0 | AC23: =AC22 -> 1972 | AD23: =AC23-AC22 -> 0 | AE23: =AE22 -> 368525 | AF23: =AE23-AE22 -> 0 | AG23: =IF(AD23>0,AF23/AD23,0) -> 0 | AH23: =AF23+AA23 -> 0 | AI23: =SUM(AH23+V23) -> 180 | AJ23: =-tanks!AW25 -> 474 | AK23: =SUM(AJ23-AI23) -> 294 | AL23: =S23+L23+G23 -> 3 | AM23: =Y23+AD23 -> 0 | AN23: =AN22 -> 65 | AO23: =(AN23/100)*3000 -> 1950 | AP23: =AP22 -> 35 | AQ23: =(AP23/100)*3000 -> 1050 | AR23: =AR22 -> 73 | AS23: =(AR23/100)*3000 -> 2190 | AT23: =SUM(AO23+AQ23+AS23) -> 5190 | AU23: =AT22-AT23+AV23 -> 0 | AX23: =IF(AV23>0,AW23,AX22) -> 0.8
A24: =ELEC!C23 -> 44977 | B24: 229.5 | C24: 236 | D24: =C23-C24 -> 4 | E24: =D24*8.38 -> 33.52 | F24: 2401 | G24: =F24-F23 -> 5 | H24: 55465 | I24: =SUM(H24-H23) -> 391 | J24: =IF(G24>0,I24/G24,0) -> 78.2 | K24: 2492 | L24: =K24-K23 -> 0 | M24: 185894 | N24: =M24-M23 -> 0 | O24: =O23 -> 1869 | P24: =P23 -> 2275 | Q24: =Q23 -> 189842 | R24: =Q24-Q23 -> 0 | S24: =SUM(P24-P23) -> 0 | T24: =SUM(S24*$T$2) -> 0 | U24: =SUM(G24+L24+S24) -> 5 | V24: =R24+N24+I24:I24 -> 391 | X24: =X23 -> 2499 | Y24: =X24-X23 -> 0 | Z24: 141680 | AA24: =Z24-Z23 -> 83 | AB24: =SUM(Y24*$AB$2) -> 0 | AC24: =AC23 -> 1972 | AD24: =AC24-AC23 -> 0 | AE24: =AE23 -> 368525 | AF24: =AE24-AE23 -> 0 | AG24: =IF(AD24>0,AF24/AD24,0) -> 0 | AH24: =AF24+AA24 -> 83 | AI24: =SUM(AH24+V24) -> 474 | AJ24: =-tanks!AW26 -> 236 | AK24: =SUM(AJ24-AI24) -> -238 | AL24: =S24+L24+G24 -> 5 | AM24: =Y24+AD24 -> 0 | AN24: =AN23 -> 65 | AO24: =(AN24/100)*3000 -> 1950 | AP24: =AP23 -> 35 | AQ24: =(AP24/100)*3000 -> 1050 | AR24: =AR23 -> 73 | AS24: =(AR24/100)*3000 -> 2190 | AT24: =SUM(AO24+AQ24+AS24) -> 5190 | AU24: =AT23-AT24+AV24 -> 0 | AX24: =IF(AV24>0,AW24,AX23) -> 0.8
A25: =ELEC!C24 -> 44978 | B25: 224 | C25: 232 | D25: =C24-C25 -> 4 | E25: =D25*8.38 -> 33.52 | F25: 2404 | G25: =F25-F24 -> 3 | H25: 55701 | I25: =SUM(H25-H24) -> 236 | J25: =IF(G25>0,I25/G25,0) -> 78.666667 | K25: 2492 | L25: =K25-K24 -> 0 | M25: =M24 -> 185894 | N25: =M25-M24 -> 0 | O25: 2251 | P25: =P24 -> 2275 | Q25: =Q24 -> 189842 | R25: =Q25-Q24 -> 0 | S25: =SUM(P25-P24) -> 0 | T25: =SUM(S25*$T$2) -> 0 | U25: =SUM(G25+L25+S25) -> 3 | V25: =R25+N25+I25:I25 -> 236 | X25: =X24 -> 2499 | Y25: =X25-X24 -> 0 | Z25: =Z24 -> 141680 | AA25: =Z25-Z24 -> 0 | AB25: =SUM(Y25*$AB$2) -> 0 | AC25: =AC24 -> 1972 | AD25: =AC25-AC24 -> 0 | AE25: =AE24 -> 368525 | AF25: =AE25-AE24 -> 0 | AG25: =IF(AD25>0,AF25/AD25,0) -> 0 | AH25: =AF25+AA25 -> 0 | AI25: =SUM(AH25+V25) -> 236 | AJ25: =-tanks!AW27 -> 283 | AK25: =SUM(AJ25-AI25) -> 47 | AL25: =S25+L25+G25 -> 3 | AM25: =Y25+AD25 -> 0 | AN25: =AN24 -> 65 | AO25: =(AN25/100)*3000 -> 1950 | AP25: =AP24 -> 35 | AQ25: =(AP25/100)*3000 -> 1050 | AR25: =AR24 -> 73 | AS25: =(AR25/100)*3000 -> 2190 | AT25: =SUM(AO25+AQ25+AS25) -> 5190 | AU25: =AT24-AT25+AV25 -> 0 | AX25: =IF(AV25>0,AW25,AX24) -> 0.8
A26: =ELEC!C25 -> 44979 | B26: 222 | C26: 229 | D26: =C25-C26 -> 3 | E26: =D26*8.38 -> 25.14 | F26: 2408 | G26: =F26-F25 -> 4 | H26: 55984 | I26: =SUM(H26-H25) -> 283 | J26: =IF(G26>0,I26/G26,0) -> 70.75 | K26: =K25 -> 2492 | L26: =K26-K25 -> 0 | M26: =M25 -> 185894 | N26: =M26-M25 -> 0 | O26: =O25 -> 2251 | P26: =P25 -> 2275 | Q26: =Q25 -> 189842 | R26: =Q26-Q25 -> 0 | S26: =SUM(P26-P25) -> 0 | T26: =SUM(S26*$T$2) -> 0 | U26: =SUM(G26+L26+S26) -> 4 | V26: =R26+N26+I26:I26 -> 283 | X26: =X25 -> 2499 | Y26: =X26-X25 -> 0 | Z26: =Z25 -> 141680 | AA26: =Z26-Z25 -> 0 | AB26: =SUM(Y26*$AB$2) -> 0 | AC26: =AC25 -> 1972 | AD26: =AC26-AC25 -> 0 | AE26: =AE25 -> 368525 | AF26: =AE26-AE25 -> 0 | AG26: =IF(AD26>0,AF26/AD26,0) -> 0 | AH26: =AF26+AA26 -> 0 | AI26: =SUM(AH26+V26) -> 283 | AJ26: =-tanks!AW28 -> 306 | AK26: =SUM(AJ26-AI26) -> 23 | AL26: =S26+L26+G26 -> 4 | AM26: =Y26+AD26 -> 0 | AN26: =AN25 -> 65 | AO26: =(AN26/100)*3000 -> 1950 | AP26: =AP25 -> 35 | AQ26: =(AP26/100)*3000 -> 1050 | AR26: =AR25 -> 73 | AS26: =(AR26/100)*3000 -> 2190 | AT26: =SUM(AO26+AQ26+AS26) -> 5190 | AU26: =AT25-AT26+AV26 -> 0 | AX26: =IF(AV26>0,AW26,AX25) -> 0.8
A27: =ELEC!C26 -> 44980 | B27: 218 | C27: 225 | D27: =C26-C27 -> 4 | E27: =D27*8.38 -> 33.52 | F27: 2410 | G27: =F27-F26 -> 2 | H27: 56188 | I27: =SUM(H27-H26) -> 204 | J27: =IF(G27>0,I27/G27,0) -> 102 | K27: 2492 | L27: =K27-K26 -> 0 | M27: =M26 -> 185894 | N27: =M27-M26 -> 0 | O27: =O26 -> 2251 | P27: =P26 -> 2275 | Q27: =Q26 -> 189842 | R27: =Q27-Q26 -> 0 | S27: =SUM(P27-P26) -> 0 | T27: =SUM(S27*$T$2) -> 0 | U27: =SUM(G27+L27+S27) -> 2 | V27: =R27+N27+I27:I27 -> 204 | X27: =X26 -> 2499 | Y27: =X27-X26 -> 0 | Z27: =Z26 -> 141680 | AA27: =Z27-Z26 -> 0 | AB27: =SUM(Y27*$AB$2) -> 0 | AC27: 1973 | AD27: =AC27-AC26 -> 1 | AE27: 368627 | AF27: =AE27-AE26 -> 102 | AG27: =IF(AD27>0,AF27/AD27,0) -> 102 | AH27: =AF27+AA27 -> 102 | AI27: =SUM(AH27+V27) -> 306 | AJ27: =-tanks!AW29 -> 0 | AK27: =SUM(AJ27-AI27) -> -306 | AL27: =S27+L27+G27 -> 2 | AM27: =Y27+AD27 -> 1 | AN27: =AN26 -> 65 | AO27: =(AN27/100)*3000 -> 1950 | AP27: =AP26 -> 35 | AQ27: =(AP27/100)*3000 -> 1050 | AR27: =AR26 -> 73 | AS27: =(AR27/100)*3000 -> 2190 | AT27: =SUM(AO27+AQ27+AS27) -> 5190 | AU27: =AT26-AT27+AV27 -> 0 | AX27: =IF(AV27>0,AW27,AX26) -> 0.8
A28: =ELEC!C27 -> 44981 | B28: =B27 -> 218 | C28: =C27 -> 225 | D28: =C27-C28 -> 0 | E28: =D28*8.38 -> 0 | F28: =F27 -> 2410 | G28: =F28-F27 -> 0 | H28: =H27 -> 56188 | I28: =SUM(H28-H27) -> 0 | J28: =IF(G28>0,I28/G28,0) -> 0 | K28: =K27 -> 2492 | L28: =K28-K27 -> 0 | M28: =M27 -> 185894 | N28: =M28-M27 -> 0 | O28: =O27 -> 2251 | P28: =P27 -> 2275 | Q28: =Q27 -> 189842 | R28: =Q28-Q27 -> 0 | S28: =SUM(P28-P27) -> 0 | T28: =SUM(S28*$T$2) -> 0 | U28: =SUM(G28+L28+S28) -> 0 | V28: =R28+N28+I28:I28 -> 0 | X28: =X27 -> 2499 | Y28: =X28-X27 -> 0 | Z28: =Z27 -> 141680 | AA28: =Z28-Z27 -> 0 | AB28: =SUM(Y28*$AB$2) -> 0 | AC28: =AC27 -> 1973 | AD28: =AC28-AC27 -> 0 | AE28: =AE27 -> 368627 | AF28: =AE28-AE27 -> 0 | AG28: =IF(AD28>0,AF28/AD28,0) -> 0 | AH28: =AF28+AA28 -> 0 | AI28: =SUM(AH28+V28) -> 0 | AJ28: =-tanks!AW30 -> 0 | AK28: =SUM(AJ28-AI28) -> 0 | AL28: =S28+L28+G28 -> 0 | AM28: =Y28+AD28 -> 0 | AN28: =AN27 -> 65 | AO28: =(AN28/100)*3000 -> 1950 | AP28: =AP27 -> 35 | AQ28: =(AP28/100)*3000 -> 1050 | AR28: =AR27 -> 73 | AS28: =(AR28/100)*3000 -> 2190 | AT28: =SUM(AO28+AQ28+AS28) -> 5190 | AU28: =AT27-AT28+AV28 -> 0 | AX28: =IF(AV28>0,AW28,AX27) -> 0.8
A29: =ELEC!C28 -> 44982 | B29: =B28 -> 218 | C29: =C28 -> 225 | D29: =C28-C29 -> 0 | E29: =D29*8.38 -> 0 | F29: =F28 -> 2410 | G29: =F29-F28 -> 0 | H29: =H28 -> 56188 | I29: =SUM(H29-H28) -> 0 | J29: =IF(G29>0,I29/G29,0) -> 0 | K29: =K28 -> 2492 | L29: =K29-K28 -> 0 | M29: =M28 -> 185894 | N29: =M29-M28 -> 0 | O29: =O28 -> 2251 | P29: =P28 -> 2275 | Q29: =Q28 -> 189842 | R29: =Q29-Q28 -> 0 | S29: =SUM(P29-P28) -> 0 | T29: =SUM(S29*$T$2) -> 0 | U29: =SUM(G29+L29+S29) -> 0 | V29: =R29+N29+I29:I29 -> 0 | X29: =X28 -> 2499 | Y29: =X29-X28 -> 0 | Z29: =Z28 -> 141680 | AA29: =Z29-Z28 -> 0 | AB29: =SUM(Y29*$AB$2) -> 0 | AC29: =AC28 -> 1973 | AD29: =AC29-AC28 -> 0 | AE29: =AE28 -> 368627 | AF29: =AE29-AE28 -> 0 | AG29: =IF(AD29>0,AF29/AD29,0) -> 0 | AH29: =AF29+AA29 -> 0 | AI29: =SUM(AH29+V29) -> 0 | AJ29: =-tanks!AW31 -> 242 | AK29: =SUM(AJ29-AI29) -> 242 | AL29: =S29+L29+G29 -> 0 | AM29: =Y29+AD29 -> 0 | AN29: =AN28 -> 65 | AO29: =(AN29/100)*3000 -> 1950 | AP29: =AP28 -> 35 | AQ29: =(AP29/100)*3000 -> 1050 | AR29: =AR28 -> 73 | AS29: =(AR29/100)*3000 -> 2190 | AT29: =SUM(AO29+AQ29+AS29) -> 5190 | AU29: =AT28-AT29+AV29 -> 0 | AX29: =IF(AV29>0,AW29,AX28) -> 0.8
A30: =ELEC!C29 -> 44983 | B30: 235 | C30: 241 | D30: =C29-C30 -> -16 | E30: =D30*8.38 -> -134.08 | F30: 2414 | G30: =F30-F29 -> 4 | H30: 56430 | I30: =SUM(H30-H29) -> 242 | J30: =IF(G30>0,I30/G30,0) -> 60.5 | K30: 2492 | L30: =K30-K29 -> 0 | M30: =M29 -> 185894 | N30: =M30-M29 -> 0 | O30: =O29 -> 2251 | P30: =P29 -> 2275 | Q30: =Q29 -> 189842 | R30: =Q30-Q29 -> 0 | S30: =SUM(P30-P29) -> 0 | T30: =SUM(S30*$T$2) -> 0 | U30: =SUM(G30+L30+S30) -> 4 | V30: =R30+N30+I30:I30 -> 242 | X30: =X29 -> 2499 | Y30: =X30-X29 -> 0 | Z30: =Z29 -> 141680 | AA30: =Z30-Z29 -> 0 | AB30: =SUM(Y30*$AB$2) -> 0 | AC30: =AC29 -> 1973 | AD30: =AC30-AC29 -> 0 | AE30: =AE29 -> 368627 | AF30: =AE30-AE29 -> 0 | AG30: =IF(AD30>0,AF30/AD30,0) -> 0 | AH30: =AF30+AA30 -> 0 | AI30: =SUM(AH30+V30) -> 242 | AJ30: =-tanks!AW32 -> 385 | AK30: =SUM(AJ30-AI30) -> 143 | AL30: =S30+L30+G30 -> 4 | AM30: =Y30+AD30 -> 0 | AN30: =AN29 -> 65 | AO30: =(AN30/100)*3000 -> 1950 | AP30: =AP29 -> 35 | AQ30: =(AP30/100)*3000 -> 1050 | AR30: =AR29 -> 73 | AS30: =(AR30/100)*3000 -> 2190 | AT30: =SUM(AO30+AQ30+AS30) -> 5190 | AU30: =AT29-AT30+AV30 -> 0 | AX30: =IF(AV30>0,AW30,AX29) -> 0.8
A31: =ELEC!C30 -> 44984 | B31: 231 | C31: 238 | D31: =C30-C31 -> 3 | E31: =D31*8.38 -> 25.14 | F31: 2417 | G31: =F31-F30 -> 3 | H31: 56668 | I31: =SUM(H31-H30) -> 238 | J31: =IF(G31>0,I31/G31,0) -> 79.333333 | K31: 2493 | L31: =K31-K30 -> 1 | M31: 185960 | N31: =M31-M30 -> 66 | O31: =O30 -> 2251 | P31: =P30 -> 2275 | Q31: =Q30 -> 189842 | R31: =Q31-Q30 -> 0 | S31: =SUM(P31-P30) -> 0 | T31: =SUM(S31*$T$2) -> 0 | U31: =SUM(G31+L31+S31) -> 4 | V31: =R31+N31+I31:I31 -> 304 | X31: =X30 -> 2499 | Y31: =X31-X30 -> 0 | Z31: 141761 | AA31: =Z31-Z30 -> 81 | AB31: =SUM(Y31*$AB$2) -> 0 | AC31: 1973 | AD31: =AC31-AC30 -> 0 | AE31: =AE30 -> 368627 | AF31: =AE31-AE30 -> 0 | AG31: =IF(AD31>0,AF31/AD31,0) -> 0 | AH31: =AF31+AA31 -> 81 | AI31: =SUM(AH31+V31) -> 385 | AJ31: =-tanks!AW33 -> 0 | AK31: =SUM(AJ31-AI31) -> -385 | AL31: =S31+L31+G31 -> 4 | AM31: =Y31+AD31 -> 0 | AN31: =AN30 -> 65 | AO31: =(AN31/100)*3000 -> 1950 | AP31: =AP30 -> 35 | AQ31: =(AP31/100)*3000 -> 1050 | AR31: =AR30 -> 73 | AS31: =(AR31/100)*3000 -> 2190 | AT31: =SUM(AO31+AQ31+AS31) -> 5190 | AU31: =AT30-AT31+AV31 -> 0 | AX31: =IF(AV31>0,AW31,AX30) -> 0.8
A32: =ELEC!C31 -> 44985 | B32: =B31 -> 231 | C32: =C31 -> 238 | D32: =C31-C32 -> 0 | E32: =D32*8.38 -> 0 | F32: =F31 -> 2417 | G32: =F32-F31 -> 0 | H32: =H31 -> 56668 | I32: =SUM(H32-H31) -> 0 | J32: =IF(G32>0,I32/G32,0) -> 0 | K32: =K31 -> 2493 | L32: =K32-K31 -> 0 | M32: =M31 -> 185960 | N32: =M32-M31 -> 0 | O32: =O31 -> 2251 | P32: =P31 -> 2275 | Q32: =Q31 -> 189842 | R32: =Q32-Q31 -> 0 | S32: =SUM(P32-P31) -> 0 | T32: =SUM(S32*$T$2) -> 0 | U32: =SUM(G32+L32+S32) -> 0 | V32: =R32+N32+I32:I32 -> 0 | X32: =X31 -> 2499 | Y32: =X32-X31 -> 0 | Z32: =Z31 -> 141761 | AA32: =Z32-Z31 -> 0 | AB32: =SUM(Y32*$AB$2) -> 0 | AC32: =AC31 -> 1973 | AD32: =AC32-AC31 -> 0 | AE32: =AE31 -> 368627 | AF32: =AE32-AE31 -> 0 | AG32: =IF(AD32>0,AF32/AD32,0) -> 0 | AH32: =AF32+AA32 -> 0 | AI32: =SUM(AH32+V32) -> 0 | AJ32: =-tanks!AW34 -> 0 | AK32: =SUM(AJ32-AI32) -> 0 | AL32: =S32+L32+G32 -> 0 | AM32: =Y32+AD32 -> 0 | AN32: =AN31 -> 65 | AO32: =(AN32/100)*3000 -> 1950 | AP32: =AP31 -> 35 | AQ32: =(AP32/100)*3000 -> 1050 | AR32: =AR31 -> 73 | AS32: =(AR32/100)*3000 -> 2190 | AT32: =SUM(AO32+AQ32+AS32) -> 5190 | AU32: =AT31-AT32+AV32 -> 0 | AX32: =IF(AV32>0,AW32,AX31) -> 0.8
A33: =ELEC!C32 -> 44986 | B33: =B32 -> 231 | C33: =C32 -> 238 | D33: =C32-C33 -> 0 | E33: =D33*8.38 -> 0 | F33: =F32 -> 2417 | G33: =F33-F32 -> 0 | H33: =H32 -> 56668 | I33: =SUM(H33-H32) -> 0 | J33: =IF(G33>0,I33/G33,0) -> 0 | K33: =K32 -> 2493 | L33: =K33-K32 -> 0 | M33: =M32 -> 185960 | N33: =M33-M32 -> 0 | O33: =O32 -> 2251 | P33: =P32 -> 2275 | Q33: =Q32 -> 189842 | R33: =Q33-Q32 -> 0 | S33: =SUM(P33-P32) -> 0 | T33: =SUM(S33*$T$2) -> 0 | U33: =SUM(G33+L33+S33) -> 0 | V33: =R33+N33+I33:I33 -> 0 | X33: =X32 -> 2499 | Y33: =X33-X32 -> 0 | Z33: =Z32 -> 141761 | AA33: =Z33-Z32 -> 0 | AB33: =SUM(Y33*$AB$2) -> 0 | AC33: =AC32 -> 1973 | AD33: =AC33-AC32 -> 0 | AE33: =AE32 -> 368627 | AF33: =AE33-AE32 -> 0 | AG33: =IF(AD33>0,AF33/AD33,0) -> 0 | AH33: =AF33+AA33 -> 0 | AI33: =SUM(AH33+V33) -> 0 | AJ33: =-tanks!AW35 -> 0 | AK33: =SUM(AJ33-AI33) -> 0 | AL33: =S33+L33+G33 -> 0 | AM33: =Y33+AD33 -> 0 | AN33: =AN32 -> 65 | AO33: =(AN33/100)*3000 -> 1950 | AP33: =AP32 -> 35 | AQ33: =(AP33/100)*3000 -> 1050 | AR33: =AR32 -> 73 | AS33: =(AR33/100)*3000 -> 2190 | AT33: =SUM(AO33+AQ33+AS33) -> 5190 | AU33: =AT32-AT33+AV33 -> 0 | AX33: =IF(AV33>0,AW33,AX32) -> 0.8
V35: =#REF!/#REF! -> #REF! | AH35: =AF35+AA35 -> 0 | AI35: =SUM(AI4:AI34) -> 5576
AH36: =AF36+AA36 -> 0 | AU36: =#REF!*0.51 -> #REF! | AV36: =#REF!/0.51 -> #REF! | AW36: =SUM(AW4:AW31)/#REF! -> #REF!
AV37: =#REF!*0.51 -> #REF!

Sheet tanks
B2: Tank 1 | D2: Tank 2 | F2: Tank 3 | H2: Tank 4 | J2: Tank 5 | L2: Tank 6 | N2: Tank 7 | P2: Tank 8 | R2: Tank 9 | T2: Tank 10 | V2: Tank 11 | Z2: Tank 1 | AB2: Tank 2 | AD2: Tank 3 | AF2: Tank 4 | AH2: Tank 5 | AJ2: Tank 6 | AL2: Tank 7
B3: 6670 | D3: =SUM(B3) -> 6670 | F3: =SUM(D3) -> 6670 | H3: =SUM(F3) -> 6670 | J3: =SUM(H3) -> 6670 | L3: =SUM(J3) -> 6670 | N3: =SUM(L3) -> 6670 | P3: =SUM(N3) -> 6670 | R3: =SUM(P3) -> 6670 | T3: =SUM(R3) -> 6670 | V3: =SUM(T3) -> 6670 | W3: =SUM(B3:V3) -> 73370 | Z3: 2800 | AB3: 2800 | AD3: 2800 | AF3: 2800 | AH3: 2800 | AJ3: 2800 | AL3: 2800 | AM3: =SUM(Z3:AL3) -> 19600 | AO3: =SUM(AM3+W3) -> 92970 | AR3: Total sotck | AS3: Diesel Cons Per day | AT3: Diesel Delivery | BE3: Genset Co | BF3: Steam | BG3: Boil | BH3: Outdoor temperature
B4: =B3/310 -> 21.516129 | D4: =SUM(B4) -> 21.516129 | F4: =SUM(D4) -> 21.516129 | H4: =SUM(F4) -> 21.516129 | J4: =SUM(H4) -> 21.516129 | L4: =SUM(J4) -> 21.516129 | N4: =SUM(L4) -> 21.516129 | P4: =SUM(N4) -> 21.516129 | R4: =SUM(P4) -> 21.516129 | T4: =SUM(R4) -> 21.516129 | V4: =SUM(T4) -> 21.516129 | Z4: =Z3/280 -> 10 | AA4: =AA3/280 -> 0 | AB4: =AB3/280 -> 10 | AC4: =AC3/280 -> 0 | AD4: =AD3/280 -> 10 | AE4: =AE3/280 -> 0 | AF4: =AF3/280 -> 10 | AG4: =AG3/280 -> 0 | ... AL4: =AL3/280 -> 10 | AT4: Delivery | AU4: Cost /L | AW4: Boiler+Steam | AX4: Generator | AZ4: Occupancy | BA4: AVE TEPM | BB4: AVE Humidity
A5: =[2]tanks!$A$36 -> 44957 | B5: =[2]tanks!B36 -> 236 | C5: =[2]tanks!C36 -> 5077.8065 | D5: =[2]tanks!D36 -> 236 | E5: =[2]tanks!E36 -> 5077.8065 | F5: =[2]tanks!F36 -> 236 | G5: =[2]tanks!G36 -> 5077.8065 | H5: =[2]tanks!H36 -> 236 | I5: =[2]tanks!I36 -> 5077.8065 | ... AO5: =[2]tanks!AO36 -> 16870 | AQ5: =[2]tanks!AQ36 -> 0.78225095 | AR5: =[2]tanks!AR36 -> 72725.871 | AS5: =[2]tanks!AS36 -> -1450.0484 | AT5: =[2]tanks!AT36 -> 0 | AU5: =[2]tanks!AU36 -> 0 | AV5: =[2]tanks!AV36 -> 0.915 | AW5: =[2]tanks!AW36 -> -244 | AX5: =[2]tanks!AX36 -> -1206.0484 | ... BK5: =[2]tanks!BK36 -> 0.18625
A6: =ELEC!C4 -> 44958 | B6: ='B5'!B5 -> 230 | C6: =B6*$B$4 -> 4948.7097 | D6: =SUM(B6) -> 230 | E6: =D6*$B$4 -> 4948.7097 | F6: =SUM(D6) -> 230 | G6: =F6*$B$4 -> 4948.7097 | H6: =SUM(F6) -> 230 | I6: =H6*$B$4 -> 4948.7097 | J6: =SUM(H6) -> 230 | K6: =J6*$B$4 -> 4948.7097 | L6: =SUM(J6) -> 230 | M6: =L6*$B$4 -> 4948.7097 | N6: =SUM(L6) -> 230 | O6: =N6*$B$4 -> 4948.7097 | P6: =SUM(N6) -> 230 | Q6: =P6*$B$4 -> 4948.7097 | R6: =SUM(P6) -> 230 | S6: =R6*$B$4 -> 4948.7097 | T6: =SUM(R6) -> 230 | U6: =T6*$B$4 -> 4948.7097 | V6: =SUM(T6) -> 230 | W6: =V6*$B$4 -> 4948.7097 | X6: =SUM(Y6/73370) -> 0.74193548 | Y6: =SUM(C6+E6+G6+I6+K6+M6+O6+Q6+S6+U6+W6) -> 54435.806 | Z6: ='B5'!C5 -> 236 | AA6: =SUM(Z6*$Z$4) -> 2360 | AB6: =SUM(Z6) -> 236 | AC6: =SUM(AB6*$Z$4) -> 2360 | AD6: =SUM(AB6) -> 236 | AE6: =SUM(AD6*$Z$4) -> 2360 | AF6: =SUM(AD6) -> 236 | AG6: =SUM(AF6*$Z$4) -> 2360 | AH6: =SUM(AF6) -> 236 | AI6: =SUM(AH6*$Z$4) -> 2360 | AJ6: =SUM(AH6) -> 236 | AK6: =SUM(AJ6*$Z$4) -> 2360 | AL6: =SUM(AJ6) -> 236 | AM6: =SUM(AL6*$Z$4) -> 2360 | AN6: =SUM(AO6/19600) -> 0.84285714 | AO6: =SUM(AA6+AC6+AE6+AG6+AI6+AK6+AM6) -> 16520 | AQ6: =SUM(AR6/92970) -> 0.76321186 | AR6: =Y6+AO6 -> 70955.806 | AS6: =SUM(AR6-AR5-AT6) -> -1770.0645 | AV6: =IF(AT6>0,AU6,AV5) -> 0.915 | AW6: =-SUM('B5'!AI5) -> -49 | AX6: =-SUM(AW6-AS6) -> -1721.0645 | AY6: =SUM(AX6+AW6) -> -1770.0645 | AZ6: =ELEC!A4 -> 0 | BA6: ='General information '!D5 -> 13 | BB6: =SUM('General information '!E5) -> 0.55 | BC6: =IF(AR3>=AR6,0,1) -> 0 | BD6: 19222 | BE6: =(305/1185)*ELEC!Q5 -> 733.28692 | BG6: =#REF!-BE6 -> #REF! | BH6: 21 | BI6: 12 | BJ6: =AX6/BI6 -> -143.42204
A7: =ELEC!C5 -> 44959 | B7: ='B5'!B6 -> 226 | C7: =B7*$B$4 -> 4862.6452 | D7: =SUM(B7) -> 226 | E7: =D7*$B$4 -> 4862.6452 | F7: =SUM(D7) -> 226 | G7: =F7*$B$4 -> 4862.6452 | H7: =SUM(F7) -> 226 | I7: =H7*$B$4 -> 4862.6452 | J7: =SUM(H7) -> 226 | K7: =J7*$B$4 -> 4862.6452 | L7: =SUM(J7) -> 226 | M7: =L7*$B$4 -> 4862.6452 | N7: =SUM(L7) -> 226 | O7: =N7*$B$4 -> 4862.6452 | P7: =SUM(N7) -> 226 | Q7: =P7*$B$4 -> 4862.6452 | R7: =SUM(P7) -> 226 | S7: =R7*$B$4 -> 4862.6452 | T7: =SUM(R7) -> 226 | U7: =T7*$B$4 -> 4862.6452 | V7: =SUM(T7) -> 226 | W7: =V7*$B$4 -> 4862.6452 | X7: =SUM(Y7/73370) -> 0.72903226 | Y7: =SUM(C7+E7+G7+I7+K7+M7+O7+Q7+S7+U7+W7) -> 53489.097 | Z7: ='B5'!C6 -> 232 | AA7: =SUM(Z7*$Z$4) -> 2320 | AB7: =SUM(Z7) -> 232 | AC7: =SUM(AB7*$Z$4) -> 2320 | AD7: =SUM(AB7) -> 232 | AE7: =SUM(AD7*$Z$4) -> 2320 | AF7: =SUM(AD7) -> 232 | AG7: =SUM(AF7*$Z$4) -> 2320 | AH7: =SUM(AF7) -> 232 | AI7: =SUM(AH7*$Z$4) -> 2320 | AJ7: =SUM(AH7) -> 232 | AK7: =SUM(AJ7*$Z$4) -> 2320 | AL7: =SUM(AJ7) -> 232 | AM7: =SUM(AL7*$Z$4) -> 2320 | AN7: =SUM(AO7/19600) -> 0.82857143 | AO7: =SUM(AA7+AC7+AE7+AG7+AI7+AK7+AM7) -> 16240 | AQ7: =SUM(AR7/92970) -> 0.75001718 | AR7: =Y7+AO7 -> 69729.097 | AS7: =SUM(AR7-AR6-AT7) -> -1226.7097 | AV7: =IF(AT7>0,AU7,AV6) -> 0.915 | AW7: =-SUM('B5'!AI6) -> -548 | AX7: =-SUM(AW7-AS7) -> -678.70968 | AY7: =SUM(AX7+AW7) -> -1226.7097 | AZ7: =ELEC!A5 -> 0 | BA7: ='General information '!D6 -> 13.5 | BB7: =SUM('General information '!E6) -> 0.53 | BC7: 0 | BD7: 19222 | BE7: =(305/1185)*ELEC!Q6 -> 0 | BG7: =#REF!-BE7 -> #REF! | BH7: 19 | BI7: 15 | BJ7: =AX7/BI7 -> -45.247312
A8: =ELEC!C6 -> 44960 | B8: ='B5'!B7 -> 226 | C8: =B8*$B$4 -> 4862.6452 | D8: =SUM(B8) -> 226 | E8: =D8*$B$4 -> 4862.6452 | F8: =SUM(D8) -> 226 | G8: =F8*$B$4 -> 4862.6452 | H8: =SUM(F8) -> 226 | I8: =H8*$B$4 -> 4862.6452 | J8: =SUM(H8) -> 226 | K8: =J8*$B$4 -> 4862.6452 | L8: =SUM(J8) -> 226 | M8: =L8*$B$4 -> 4862.6452 | N8: =SUM(L8) -> 226 | O8: =N8*$B$4 -> 4862.6452 | P8: =SUM(N8) -> 226 | Q8: =P8*$B$4 -> 4862.6452 | R8: =SUM(P8) -> 226 | S8: =R8*$B$4 -> 4862.6452 | T8: =SUM(R8) -> 226 | U8: =T8*$B$4 -> 4862.6452 | V8: =SUM(T8) -> 226 | W8: =V8*$B$4 -> 4862.6452 | X8: =SUM(Y8/73370) -> 0.72903226 | Y8: =SUM(C8+E8+G8+I8+K8+M8+O8+Q8+S8+U8+W8) -> 53489.097 | Z8: ='B5'!C7 -> 232 | AA8: =SUM(Z8*$Z$4) -> 2320 | AB8: =SUM(Z8) -> 232 | AC8: =SUM(AB8*$Z$4) -> 2320 | AD8: =SUM(AB8) -> 232 | AE8: =SUM(AD8*$Z$4) -> 2320 | AF8: =SUM(AD8) -> 232 | AG8: =SUM(AF8*$Z$4) -> 2320 | AH8: =SUM(AF8) -> 232 | AI8: =SUM(AH8*$Z$4) -> 2320 | AJ8: =SUM(AH8) -> 232 | AK8: =SUM(AJ8*$Z$4) -> 2320 | AL8: =SUM(AJ8) -> 232 | AM8: =SUM(AL8*$Z$4) -> 2320 | AN8: =SUM(AO8/19600) -> 0.82857143 | AO8: =SUM(AA8+AC8+AE8+AG8+AI8+AK8+AM8) -> 16240 | AQ8: =SUM(AR8/92970) -> 0.75001718 | AR8: =Y8+AO8 -> 69729.097 | AS8: =SUM(AR8-AR7-AT8) -> 0 | AV8: =IF(AT8>0,AU8,AV7) -> 0.915 | AW8: =-SUM('B5'!AI7) -> -0.6 | AX8: =-SUM(AW8-AS8) -> 0.6 | AY8: =SUM(AX8+AW8) -> 0 | AZ8: =ELEC!A6 -> 0 | BA8: ='General information '!D7 -> 0 | BB8: =SUM('General information '!E7) -> 0 | BC8: =IF(AR7>=AR8,0,1) -> 0 | BD8: 19222 | BE8: =(305/1185)*ELEC!Q7 -> 0 | BG8: =#REF!-BE8 -> #REF! | BH8: 16 | BI8: 9 | BJ8: =AX8/BI8 -> 0.066666667 | BK8: =GEN!AF5 -> #DIV/0!
A9: =ELEC!C7 -> 44961 | B9: ='B5'!B8 -> 226 | C9: =B9*$B$4 -> 4862.6452 | D9: =SUM(B9) -> 226 | E9: =D9*$B$4 -> 4862.6452 | F9: =SUM(D9) -> 226 | G9: =F9*$B$4 -> 4862.6452 | H9: =SUM(F9) -> 226 | I9: =H9*$B$4 -> 4862.6452 | J9: =SUM(H9) -> 226 | K9: =J9*$B$4 -> 4862.6452 | L9: =SUM(J9) -> 226 | M9: =L9*$B$4 -> 4862.6452 | N9: =SUM(L9) -> 226 | O9: =N9*$B$4 -> 4862.6452 | P9: =SUM(N9) -> 226 | Q9: =P9*$B$4 -> 4862.6452 | R9: =SUM(P9) -> 226 | S9: =R9*$B$4 -> 4862.6452 | T9: =SUM(R9) -> 226 | U9: =T9*$B$4 -> 4862.6452 | V9: =SUM(T9) -> 226 | W9: =V9*$B$4 -> 4862.6452 | X9: =SUM(Y9/73370) -> 0.72903226 | Y9: =SUM(C9+E9+G9+I9+K9+M9+O9+Q9+S9+U9+W9) -> 53489.097 | Z9: ='B5'!C8 -> 232 | AA9: =SUM(Z9*$Z$4) -> 2320 | AB9: =SUM(Z9) -> 232 | AC9: =SUM(AB9*$Z$4) -> 2320 | AD9: =SUM(AB9) -> 232 | AE9: =SUM(AD9*$Z$4) -> 2320 | AF9: =SUM(AD9) -> 232 | AG9: =SUM(AF9*$Z$4) -> 2320 | AH9: =SUM(AF9) -> 232 | AI9: =SUM(AH9*$Z$4) -> 2320 | AJ9: =SUM(AH9) -> 232 | AK9: =SUM(AJ9*$Z$4) -> 2320 | AL9: =SUM(AJ9) -> 232 | AM9: =SUM(AL9*$Z$4) -> 2320 | AN9: =SUM(AO9/19600) -> 0.82857143 | AO9: =SUM(AA9+AC9+AE9+AG9+AI9+AK9+AM9) -> 16240 | AQ9: =SUM(AR9/92970) -> 0.75001718 | AR9: =Y9+AO9 -> 69729.097 | AS9: =SUM(AR9-AR8-AT9) -> 0 | AV9: =IF(AT9>0,AU9,AV8) -> 0.915 | AW9: =-SUM('B5'!AI8) -> 0 | AX9: =-SUM(AW9-AS9) -> 0 | AY9: =SUM(AX9+AW9) -> 0 | AZ9: =ELEC!A7 -> 0 | BA9: ='General information '!D8 -> 0 | BB9: =SUM('General information '!E8) -> 0 | BC9: =IF(AR8>=AR9,0,1) -> 0 | BD9: 19222 | BE9: =(305/1185)*ELEC!Q8 -> 721.44726 | BG9: =#REF!-BE9 -> #REF! | BH9: 18 | BI9: 6 | BJ9: =AX9/BI9 -> 0 | BK9: =GEN!AF6 -> #DIV/0!
A10: =ELEC!C8 -> 44962 | B10: ='B5'!B9 -> 222 | C10: =B10*$B$4 -> 4776.5806 | D10: =SUM(B10) -> 222 | E10: =D10*$B$4 -> 4776.5806 | F10: =SUM(D10) -> 222 | G10: =F10*$B$4 -> 4776.5806 | H10: =SUM(F10) -> 222 | I10: =H10*$B$4 -> 4776.5806 | J10: =SUM(H10) -> 222 | K10: =J10*$B$4 -> 4776.5806 | L10: =SUM(J10) -> 222 | M10: =L10*$B$4 -> 4776.5806 | N10: =SUM(L10) -> 222 | O10: =N10*$B$4 -> 4776.5806 | P10: =SUM(N10) -> 222 | Q10: =P10*$B$4 -> 4776.5806 | R10: =SUM(P10) -> 222 | S10: =R10*$B$4 -> 4776.5806 | T10: =SUM(R10) -> 222 | U10: =T10*$B$4 -> 4776.5806 | V10: =SUM(T10) -> 222 | W10: =V10*$B$4 -> 4776.5806 | X10: =SUM(Y10/73370) -> 0.71612903 | Y10: =SUM(C10+E10+G10+I10+K10+M10+O10+Q10+S10+U10+W10) -> 52542.387 | Z10: ='B5'!C9 -> 228 | AA10: =SUM(Z10*$Z$4) -> 2280 | AB10: =SUM(Z10) -> 228 | AC10: =SUM(AB10*$Z$4) -> 2280 | AD10: =SUM(AB10) -> 228 | AE10: =SUM(AD10*$Z$4) -> 2280 | AF10: =SUM(AD10) -> 228 | AG10: =SUM(AF10*$Z$4) -> 2280 | AH10: =SUM(AF10) -> 228 | AI10: =SUM(AH10*$Z$4) -> 2280 | AJ10: =SUM(AH10) -> 228 | AK10: =SUM(AJ10*$Z$4) -> 2280 | AL10: =SUM(AJ10) -> 228 | AM10: =SUM(AL10*$Z$4) -> 2280 | AN10: =SUM(AO10/19600) -> 0.81428571 | AO10: =SUM(AA10+AC10+AE10+AG10+AI10+AK10+AM10) -> 15960 | AQ10: =SUM(AR10/92970) -> 0.73682249 | AR10: =Y10+AO10 -> 68502.387 | AS10: =SUM(AR10-AR9-AT10) -> -1226.7097 | AV10: =IF(AT10>0,AU10,AV9) -> 0.915 | AW10: =-SUM('B5'!AI9) -> -203 | AX10: =-SUM(AW10-AS10) -> -1023.7097 | AY10: =SUM(AX10+AW10) -> -1226.7097 | AZ10: =ELEC!A8 -> 0 | BA10: ='General information '!D9 -> 11.5 | BB10: =SUM('General information '!E9) -> 0.63 | BC10: =IF(AR9>=AR10,0,1) -> 0 | BD10: 19222 | BE10: =(305/1185)*ELEC!Q9 -> 860.69198 | BG10: =#REF!-BE10 -> #REF! | BH10: 16 | BI10: 7 | BJ10: =AX10/BI10 -> -146.24424 | BK10: =GEN!AF7 -> 0.14598958
A11: =ELEC!C9 -> 44963 | B11: ='B5'!B10 -> 217 | C11: =B11*$B$4 -> 4669 | D11: =SUM(B11) -> 217 | E11: =D11*$B$4 -> 4669 | F11: =SUM(D11) -> 217 | G11: =F11*$B$4 -> 4669 | H11: =SUM(F11) -> 217 | I11: =H11*$B$4 -> 4669 | J11: =SUM(H11) -> 217 | K11: =J11*$B$4 -> 4669 | L11: =SUM(J11) -> 217 | M11: =L11*$B$4 -> 4669 | N11: =SUM(L11) -> 217 | O11: =N11*$B$4 -> 4669 | P11: =SUM(N11) -> 217 | Q11: =P11*$B$4 -> 4669 | R11: =SUM(P11) -> 217 | S11: =R11*$B$4 -> 4669 | T11: =SUM(R11) -> 217 | U11: =T11*$B$4 -> 4669 | V11: =SUM(T11) -> 217 | W11: =V11*$B$4 -> 4669 | X11: =SUM(Y11/73370) -> 0.7 | Y11: =SUM(C11+E11+G11+I11+K11+M11+O11+Q11+S11+U11+W11) -> 51359 | Z11: ='B5'!C10 -> 223 | AA11: =SUM(Z11*$Z$4) -> 2230 | AB11: =SUM(Z11) -> 223 | AC11: =SUM(AB11*$Z$4) -> 2230 | AD11: =SUM(AB11) -> 223 | AE11: =SUM(AD11*$Z$4) -> 2230 | AF11: =SUM(AD11) -> 223 | AG11: =SUM(AF11*$Z$4) -> 2230 | AH11: =SUM(AF11) -> 223 | AI11: =SUM(AH11*$Z$4) -> 2230 | AJ11: =SUM(AH11) -> 223 | AK11: =SUM(AJ11*$Z$4) -> 2230 | AL11: =SUM(AJ11) -> 223 | AM11: =SUM(AL11*$Z$4) -> 2230 | AN11: =SUM(AO11/19600) -> 0.79642857 | AO11: =SUM(AA11+AC11+AE11+AG11+AI11+AK11+AM11) -> 15610 | AQ11: =SUM(AR11/92970) -> 0.72032914 | AR11: =Y11+AO11 -> 66969 | AS11: =SUM(AR11-AR10-AT11) -> -1533.3871 | AV11: =IF(AT11>0,AU11,AV10) -> 0.915 | AW11: =-SUM('B5'!AI10) -> -280.4 | AX11: =-SUM(AW11-AS11) -> -1252.9871 | AY11: =SUM(AX11+AW11) -> -1533.3871 | AZ11: =ELEC!A9 -> 0 | BA11: ='General information '!D10 -> 11 | BB11: =SUM('General information '!E10) -> 0.56 | BC11: =IF(AR10>=AR11,0,1) -> 0 | BD11: 19222 | BE11: =(305/1185)*ELEC!Q10 -> 976 | BG11: =#REF!-BE11 -> #REF! | BH11: 16.5 | BI11: 9.3 | BJ11: =AX11/BI11 -> -134.7298
A12: =ELEC!C10 -> 44964 | B12: ='B5'!B11 -> 212 | C12: =B12*$B$4 -> 4561.4194 | D12: =SUM(B12) -> 212 | E12: =D12*$B$4 -> 4561.4194 | F12: =SUM(D12) -> 212 | G12: =F12*$B$4 -> 4561.4194 | H12: =SUM(F12) -> 212 | I12: =H12*$B$4 -> 4561.4194 | J12: =SUM(H12) -> 212 | K12: =J12*$B$4 -> 4561.4194 | L12: =SUM(J12) -> 212 | M12: =L12*$B$4 -> 4561.4194 | N12: =SUM(L12) -> 212 | O12: =N12*$B$4 -> 4561.4194 | P12: =SUM(N12) -> 212 | Q12: =P12*$B$4 -> 4561.4194 | R12: =SUM(P12) -> 212 | S12: =R12*$B$4 -> 4561.4194 | T12: =SUM(R12) -> 212 | U12: =T12*$B$4 -> 4561.4194 | V12: =SUM(T12) -> 212 | W12: =V12*$B$4 -> 4561.4194 | X12: =SUM(Y12/73370) -> 0.68387097 | Y12: =SUM(C12+E12+G12+I12+K12+M12+O12+Q12+S12+U12+W12) -> 50175.613 | Z12: ='B5'!C11 -> 219 | AA12: =SUM(Z12*$Z$4) -> 2190 | AB12: =SUM(Z12) -> 219 | AC12: =SUM(AB12*$Z$4) -> 2190 | AD12: =SUM(AB12) -> 219 | AE12: =SUM(AD12*$Z$4) -> 2190 | AF12: =SUM(AD12) -> 219 | AG12: =SUM(AF12*$Z$4) -> 2190 | AH12: =SUM(AF12) -> 219 | AI12: =SUM(AH12*$Z$4) -> 2190 | AJ12: =SUM(AH12) -> 219 | AK12: =SUM(AJ12*$Z$4) -> 2190 | AL12: =SUM(AJ12) -> 219 | AM12: =SUM(AL12*$Z$4) -> 2190 | AN12: =SUM(AO12/19600) -> 0.78214286 | AO12: =SUM(AA12+AC12+AE12+AG12+AI12+AK12+AM12) -> 15330 | AQ12: =SUM(AR12/92970) -> 0.70458872 | AR12: =Y12+AO12 -> 65505.613 | AS12: =SUM(AR12-AR11-AT12) -> -1463.3871 | AV12: =IF(AT12>0,AU12,AV11) -> 0.915 | AW12: =-SUM('B5'!AI11) -> -191 | AX12: =-SUM(AW12-AS12) -> -1272.3871 | AY12: =SUM(AX12+AW12) -> -1463.3871 | AZ12: =ELEC!A10 -> 0 | BA12: ='General information '!D11 -> 11 | BB12: =SUM('General information '!E11) -> 0.56 | BC12: =IF(AR11>=AR12,0,1) -> 0 | BD12: 19222 | BE12: =(305/1185)*ELEC!Q11 -> 900.32911 | BG12: =#REF!-BE12 -> #REF! | BH12: 15.5 | BI12: 3.7 | BJ12: =AX12/BI12 -> -343.8884
A13: =ELEC!C11 -> 44965 | B13: ='B5'!B12 -> 235 | C13: =B13*$B$4 -> 5056.2903 | D13: =SUM(B13) -> 235 | E13: =D13*$B$4 -> 5056.2903 | F13: =SUM(D13) -> 235 | G13: =F13*$B$4 -> 5056.2903 | H13: =SUM(F13) -> 235 | I13: =H13*$B$4 -> 5056.2903 | J13: =SUM(H13) -> 235 | K13: =J13*$B$4 -> 5056.2903 | L13: =SUM(J13) -> 235 | M13: =L13*$B$4 -> 5056.2903 | N13: =SUM(L13) -> 235 | O13: =N13*$B$4 -> 5056.2903 | P13: =SUM(N13) -> 235 | Q13: =P13*$B$4 -> 5056.2903 | R13: =SUM(P13) -> 235 | S13: =R13*$B$4 -> 5056.2903 | T13: =SUM(R13) -> 235 | U13: =T13*$B$4 -> 5056.2903 | V13: =SUM(T13) -> 235 | W13: =V13*$B$4 -> 5056.2903 | X13: =SUM(Y13/73370) -> 0.75806452 | Y13: =SUM(C13+E13+G13+I13+K13+M13+O13+Q13+S13+U13+W13) -> 55619.194 | Z13: ='B5'!C12 -> 241 | AA13: =SUM(Z13*$Z$4) -> 2410 | AB13: =SUM(Z13) -> 241 | AC13: =SUM(AB13*$Z$4) -> 2410 | AD13: =SUM(AB13) -> 241 | AE13: =SUM(AD13*$Z$4) -> 2410 | AF13: =SUM(AD13) -> 241 | AG13: =SUM(AF13*$Z$4) -> 2410 | AH13: =SUM(AF13) -> 241 | AI13: =SUM(AH13*$Z$4) -> 2410 | AJ13: =SUM(AH13) -> 241 | AK13: =SUM(AJ13*$Z$4) -> 2410 | AL13: =SUM(AJ13) -> 241 | AM13: =SUM(AL13*$Z$4) -> 2410 | AN13: =SUM(AO13/19600) -> 0.86071429 | AO13: =SUM(AA13+AC13+AE13+AG13+AI13+AK13+AM13) -> 16870 | AQ13: =SUM(AR13/92970) -> 0.77970521 | AR13: =Y13+AO13 -> 72489.194 | AS13: =SUM(AR13-AR12-AT13) -> -186.41935 | AT13: 7170 | AU13: 0.868 | AV13: =IF(AT13>0,AU13,AV12) -> 0.868 | AW13: =-SUM('B5'!AI12) -> -321 | AX13: =-SUM(AW13-AS13) -> 134.58065 | AY13: =SUM(AX13+AW13) -> -186.41935 | AZ13: =ELEC!A11 -> 0 | BA13: ='General information '!D12 -> 11 | BB13: =SUM('General information '!E12) -> 0.56 | BC13: =IF(AR12>=AR13,0,1) -> 1 | BD13: 19222 | BE13: =(305/1185)*ELEC!Q12 -> 0 | BG13: =#REF!-BE13 -> #REF! | BI13: 5 | BJ13: =AX13/BI13 -> 26.916129 | BK13: =GEN!AF10 -> 0.218625
A14: =ELEC!C12 -> 44966 | B14: ='B5'!B13 -> 235 | C14: =B14*$B$4 -> 5056.2903 | D14: =SUM(B14) -> 235 | E14: =D14*$B$4 -> 5056.2903 | F14: =SUM(D14) -> 235 | G14: =F14*$B$4 -> 5056.2903 | H14: =SUM(F14) -> 235 | I14: =H14*$B$4 -> 5056.2903 | J14: =SUM(H14) -> 235 | K14: =J14*$B$4 -> 5056.2903 | L14: =SUM(J14) -> 235 | M14: =L14*$B$4 -> 5056.2903 | N14: =SUM(L14) -> 235 | O14: =N14*$B$4 -> 5056.2903 | P14: =SUM(N14) -> 235 | Q14: =P14*$B$4 -> 5056.2903 | R14: =SUM(P14) -> 235 | S14: =R14*$B$4 -> 5056.2903 | T14: =SUM(R14) -> 235 | U14: =T14*$B$4 -> 5056.2903 | V14: =SUM(T14) -> 235 | W14: =V14*$B$4 -> 5056.2903 | X14: =SUM(Y14/73370) -> 0.75806452 | Y14: =SUM(C14+E14+G14+I14+K14+M14+O14+Q14+S14+U14+W14) -> 55619.194 | Z14: ='B5'!C13 -> 241 | AA14: =SUM(Z14*$Z$4) -> 2410 | AB14: =SUM(Z14) -> 241 | AC14: =SUM(AB14*$Z$4) -> 2410 | AD14: =SUM(AB14) -> 241 | AE14: =SUM(AD14*$Z$4) -> 2410 | AF14: =SUM(AD14) -> 241 | AG14: =SUM(AF14*$Z$4) -> 2410 | AH14: =SUM(AF14) -> 241 | AI14: =SUM(AH14*$Z$4) -> 2410 | AJ14: =SUM(AH14) -> 241 | AK14: =SUM(AJ14*$Z$4) -> 2410 | AL14: =SUM(AJ14) -> 241 | AM14: =SUM(AL14*$Z$4) -> 2410 | AN14: =SUM(AO14/19600) -> 0.86071429 | AO14: =SUM(AA14+AC14+AE14+AG14+AI14+AK14+AM14) -> 16870 | AQ14: =SUM(AR14/92970) -> 0.77970521 | AR14: =Y14+AO14 -> 72489.194 | AS14: =SUM(AR14-AR13-AT14) -> 0 | AV14: =IF(AT14>0,AU14,AV13) -> 0.868 | AW14: =-SUM('B5'!AI13) -> 0 | AX14: =-SUM(AW14-AS14) -> 0 | AY14: =SUM(AX14+AW14) -> 0 | AZ14: =ELEC!A12 -> 0 | BA14: ='General information '!D13 -> 0 | BB14: =SUM('General information '!E13) -> 0 | BC14: =IF(AR13>=AR14,0,1) -> 0 | BD14: 19222 | BE14: =(305/1185)*ELEC!Q13 -> 0 | BG14: =#REF!-BE14 -> #REF! | BI14: 3 | BJ14: =AX14/BI14 -> 0 | BK14: =GEN!AF11 -> #DIV/0!
A15: =ELEC!C13 -> 44967 | B15: ='B5'!B14 -> 235 | C15: =B15*$B$4 -> 5056.2903 | D15: =SUM(B15) -> 235 | E15: =D15*$B$4 -> 5056.2903 | F15: =SUM(D15) -> 235 | G15: =F15*$B$4 -> 5056.2903 | H15: =SUM(F15) -> 235 | I15: =H15*$B$4 -> 5056.2903 | J15: =SUM(H15) -> 235 | K15: =J15*$B$4 -> 5056.2903 | L15: =SUM(J15) -> 235 | M15: =L15*$B$4 -> 5056.2903 | N15: =SUM(L15) -> 235 | O15: =N15*$B$4 -> 5056.2903 | P15: =SUM(N15) -> 235 | Q15: =P15*$B$4 -> 5056.2903 | R15: =SUM(P15) -> 235 | S15: =R15*$B$4 -> 5056.2903 | T15: =SUM(R15) -> 235 | U15: =T15*$B$4 -> 5056.2903 | V15: =SUM(T15) -> 235 | W15: =V15*$B$4 -> 5056.2903 | X15: =SUM(Y15/73370) -> 0.75806452 | Y15: =SUM(C15+E15+G15+I15+K15+M15+O15+Q15+S15+U15+W15) -> 55619.194 | Z15: ='B5'!C14 -> 241 | AA15: =SUM(Z15*$Z$4) -> 2410 | AB15: =SUM(Z15) -> 241 | AC15: =SUM(AB15*$Z$4) -> 2410 | AD15: =SUM(AB15) -> 241 | AE15: =SUM(AD15*$Z$4) -> 2410 | AF15: =SUM(AD15) -> 241 | AG15: =SUM(AF15*$Z$4) -> 2410 | AH15: =SUM(AF15) -> 241 | AI15: =SUM(AH15*$Z$4) -> 2410 | AJ15: =SUM(AH15) -> 241 | AK15: =SUM(AJ15*$Z$4) -> 2410 | AL15: =SUM(AJ15) -> 241 | AM15: =SUM(AL15*$Z$4) -> 2410 | AN15: =SUM(AO15/19600) -> 0.86071429 | AO15: =SUM(AA15+AC15+AE15+AG15+AI15+AK15+AM15) -> 16870 | AQ15: =SUM(AR15/92970) -> 0.77970521 | AR15: =Y15+AO15 -> 72489.194 | AS15: =SUM(AR15-AR14-AT15) -> 0 | AV15: =IF(AT15>0,AU15,AV14) -> 0.868 | AW15: =-SUM('B5'!AI14) -> 0 | AX15: =-SUM(AW15-AS15) -> 0 | AY15: =SUM(AX15+AW15) -> 0 | AZ15: =ELEC!A13 -> 0 | BA15: ='General information '!D14 -> 11 | BB15: =SUM('General information '!E14) -> 0.51 | BC15: =IF(AR14>=AR15,0,1) -> 0 | BD15: 19222 | BE15: =(305/1185)*ELEC!Q14 -> 0 | BG15: =#REF!-BE15 -> #REF! | BI15: 4 | BJ15: =AX15/BI15 -> 0 | BK15: =GEN!AF12 -> #DIV/0!
A16: =ELEC!C14 -> 44968 | B16: ='B5'!B15 -> 235 | C16: =B16*$B$4 -> 5056.2903 | D16: =SUM(B16) -> 235 | E16: =D16*$B$4 -> 5056.2903 | F16: =SUM(D16) -> 235 | G16: =F16*$B$4 -> 5056.2903 | H16: =SUM(F16) -> 235 | I16: =H16*$B$4 -> 5056.2903 | J16: =SUM(H16) -> 235 | K16: =J16*$B$4 -> 5056.2903 | L16: =SUM(J16) -> 235 | M16: =L16*$B$4 -> 5056.2903 | N16: =SUM(L16) -> 235 | O16: =N16*$B$4 -> 5056.2903 | P16: =SUM(N16) -> 235 | Q16: =P16*$B$4 -> 5056.2903 | R16: =SUM(P16) -> 235 | S16: =R16*$B$4 -> 5056.2903 | T16: =SUM(R16) -> 235 | U16: =T16*$B$4 -> 5056.2903 | V16: =SUM(T16) -> 235 | W16: =V16*$B$4 -> 5056.2903 | X16: =SUM(Y16/73370) -> 0.75806452 | Y16: =SUM(C16+E16+G16+I16+K16+M16+O16+Q16+S16+U16+W16) -> 55619.194 | Z16: ='B5'!C15 -> 241 | AA16: =SUM(Z16*$Z$4) -> 2410 | AB16: =SUM(Z16) -> 241 | AC16: =SUM(AB16*$Z$4) -> 2410 | AD16: =SUM(AB16) -> 241 | AE16: =SUM(AD16*$Z$4) -> 2410 | AF16: =SUM(AD16) -> 241 | AG16: =SUM(AF16*$Z$4) -> 2410 | AH16: =SUM(AF16) -> 241 | AI16: =SUM(AH16*$Z$4) -> 2410 | AJ16: =SUM(AH16) -> 241 | AK16: =SUM(AJ16*$Z$4) -> 2410 | AL16: =SUM(AJ16) -> 241 | AM16: =SUM(AL16*$Z$4) -> 2410 | AN16: =SUM(AO16/19600) -> 0.86071429 | AO16: =SUM(AA16+AC16+AE16+AG16+AI16+AK16+AM16) -> 16870 | AQ16: =SUM(AR16/92970) -> 0.77970521 | AR16: =Y16+AO16 -> 72489.194 | AS16: =SUM(AR16-AR15-AT16) -> 0 | AV16: =IF(AT16>0,AU16,AV15) -> 0.868 | AW16: =-SUM('B5'!AI15) -> 0 | AX16: =-SUM(AW16-AS16) -> 0 | AY16: =SUM(AX16+AW16) -> 0 | AZ16: =ELEC!A14 -> 0 | BA16: ='General information '!D15 -> 0 | BB16: =SUM('General information '!E15) -> 0 | BC16: =IF(AR15>=AR16,0,1) -> 0 | BD16: 19222 | BE16: =(305/1185)*ELEC!Q15 -> 579.62869 | BG16: =#REF!-BE16 -> #REF! | BI16: 3 | BJ16: =AX16/BI16 -> 0 | BK16: =GEN!AF13 -> #DIV/0!
A17: =ELEC!C15 -> 44969 | B17: ='B5'!B16 -> 230 | C17: =B17*$B$4 -> 4948.7097 | D17: =SUM(B17) -> 230 | E17: =D17*$B$4 -> 4948.7097 | F17: =SUM(D17) -> 230 | G17: =F17*$B$4 -> 4948.7097 | H17: =SUM(F17) -> 230 | I17: =H17*$B$4 -> 4948.7097 | J17: =SUM(H17) -> 230 | K17: =J17*$B$4 -> 4948.7097 | L17: =SUM(J17) -> 230 | M17: =L17*$B$4 -> 4948.7097 | N17: =SUM(L17) -> 230 | O17: =N17*$B$4 -> 4948.7097 | P17: =SUM(N17) -> 230 | Q17: =P17*$B$4 -> 4948.7097 | R17: =SUM(P17) -> 230 | S17: =R17*$B$4 -> 4948.7097 | T17: =SUM(R17) -> 230 | U17: =T17*$B$4 -> 4948.7097 | V17: =SUM(T17) -> 230 | W17: =V17*$B$4 -> 4948.7097 | X17: =SUM(Y17/73370) -> 0.74193548 | Y17: =SUM(C17+E17+G17+I17+K17+M17+O17+Q17+S17+U17+W17) -> 54435.806 | Z17: ='B5'!C16 -> 236 | AA17: =SUM(Z17*$Z$4) -> 2360 | AB17: =SUM(Z17) -> 236 | AC17: =SUM(AB17*$Z$4) -> 2360 | AD17: =SUM(AB17) -> 236 | AE17: =SUM(AD17*$Z$4) -> 2360 | AF17: =SUM(AD17) -> 236 | AG17: =SUM(AF17*$Z$4) -> 2360 | AH17: =SUM(AF17) -> 236 | AI17: =SUM(AH17*$Z$4) -> 2360 | AJ17: =SUM(AH17) -> 236 | AK17: =SUM(AJ17*$Z$4) -> 2360 | AL17: =SUM(AJ17) -> 236 | AM17: =SUM(AL17*$Z$4) -> 2360 | AN17: =SUM(AO17/19600) -> 0.84285714 | AO17: =SUM(AA17+AC17+AE17+AG17+AI17+AK17+AM17) -> 16520 | AQ17: =SUM(AR17/92970) -> 0.76321186 | AR17: =Y17+AO17 -> 70955.806 | AS17: =SUM(AR17-AR16-AT17) -> -1533.3871 | AV17: =IF(AT17>0,AU17,AV16) -> 0.868 | AW17: =-SUM('B5'!AI16) -> -636 | AX17: =-SUM(AW17-AS17) -> -897.3871 | AY17: =SUM(AX17+AW17) -> -1533.3871 | AZ17: =ELEC!A15 -> 0 | BA17: ='General information '!D16 -> 12 | BB17: =SUM('General information '!E16) -> 0.43 | BC17: =IF(AR16>=AR17,0,1) -> 0 | BD17: 19222 | BE17: =(305/1185)*ELEC!Q16 -> 713.46835 | BG17: =#REF!-BE17 -> #REF! | BI17: 4 | BJ17: =AX17/BI17 -> -224.34677 | BK17: =GEN!AF14 -> 0.1759375
A18: =ELEC!C16 -> 44970 | B18: ='B5'!B17 -> 227 | C18: =B18*$B$4 -> 4884.1613 | D18: =SUM(B18) -> 227 | E18: =D18*$B$4 -> 4884.1613 | F18: =SUM(D18) -> 227 | G18: =F18*$B$4 -> 4884.1613 | H18: =SUM(F18) -> 227 | I18: =H18*$B$4 -> 4884.1613 | J18: =SUM(H18) -> 227 | K18: =J18*$B$4 -> 4884.1613 | L18: =SUM(J18) -> 227 | M18: =L18*$B$4 -> 4884.1613 | N18: =SUM(L18) -> 227 | O18: =N18*$B$4 -> 4884.1613 | P18: =SUM(N18) -> 227 | Q18: =P18*$B$4 -> 4884.1613 | R18: =SUM(P18) -> 227 | S18: =R18*$B$4 -> 4884.1613 | T18: =SUM(R18) -> 227 | U18: =T18*$B$4 -> 4884.1613 | V18: =SUM(T18) -> 227 | W18: =V18*$B$4 -> 4884.1613 | X18: =SUM(Y18/73370) -> 0.73225806 | Y18: =SUM(C18+E18+G18+I18+K18+M18+O18+Q18+S18+U18+W18) -> 53725.774 | Z18: ='B5'!C17 -> 233 | AA18: =SUM(Z18*$Z$4) -> 2330 | AB18: =SUM(Z18) -> 233 | AC18: =SUM(AB18*$Z$4) -> 2330 | AD18: =SUM(AB18) -> 233 | AE18: =SUM(AD18*$Z$4) -> 2330 | AF18: =SUM(AD18) -> 233 | AG18: =SUM(AF18*$Z$4) -> 2330 | AH18: =SUM(AF18) -> 233 | AI18: =SUM(AH18*$Z$4) -> 2330 | AJ18: =SUM(AH18) -> 233 | AK18: =SUM(AJ18*$Z$4) -> 2330 | AL18: =SUM(AJ18) -> 233 | AM18: =SUM(AL18*$Z$4) -> 2330 | AN18: =SUM(AO18/19600) -> 0.83214286 | AO18: =SUM(AA18+AC18+AE18+AG18+AI18+AK18+AM18) -> 16310 | AQ18: =SUM(AR18/92970) -> 0.75331585 | AR18: =Y18+AO18 -> 70035.774 | AS18: =SUM(AR18-AR17-AT18) -> -920.03226 | AV18: =IF(AT18>0,AU18,AV17) -> 0.868 | AW18: =-SUM('B5'!AI17) -> -124 | AX18: =-SUM(AW18-AS18) -> -796.03226 | AY18: =SUM(AX18+AW18) -> -920.03226 | AZ18: =ELEC!A16 -> 0 | BA18: ='General information '!D17 -> 13 | BB18: =SUM('General information '!E17) -> 0.37 | BC18: =IF(AR17>=AR18,0,1) -> 0 | BD18: 19222 | BE18: =(305/1185)*ELEC!Q17 -> 596.87342 | BG18: =#REF!-BE18 -> #REF! | BI18: 5 | BJ18: =AX18/BI18 -> -159.20645
A19: =ELEC!C17 -> 44971 | B19: ='B5'!B18 -> 223 | C19: =B19*$B$4 -> 4798.0968 | D19: =SUM(B19) -> 223 | E19: =D19*$B$4 -> 4798.0968 | F19: =SUM(D19) -> 223 | G19: =F19*$B$4 -> 4798.0968 | H19: =SUM(F19) -> 223 | I19: =H19*$B$4 -> 4798.0968 | J19: =SUM(H19) -> 223 | K19: =J19*$B$4 -> 4798.0968 | L19: =SUM(J19) -> 223 | M19: =L19*$B$4 -> 4798.0968 | N19: =SUM(L19) -> 223 | O19: =N19*$B$4 -> 4798.0968 | P19: =SUM(N19) -> 223 | Q19: =P19*$B$4 -> 4798.0968 | R19: =SUM(P19) -> 223 | S19: =R19*$B$4 -> 4798.0968 | T19: =SUM(R19) -> 223 | U19: =T19*$B$4 -> 4798.0968 | V19: =SUM(T19) -> 223 | W19: =V19*$B$4 -> 4798.0968 | X19: =SUM(Y19/73370) -> 0.71935484 | Y19: =SUM(C19+E19+G19+I19+K19+M19+O19+Q19+S19+U19+W19) -> 52779.065 | Z19: ='B5'!C18 -> 230 | AA19: =SUM(Z19*$Z$4) -> 2300 | AB19: =SUM(Z19) -> 230 | AC19: =SUM(AB19*$Z$4) -> 2300 | AD19: =SUM(AB19) -> 230 | AE19: =SUM(AD19*$Z$4) -> 2300 | AF19: =SUM(AD19) -> 230 | AG19: =SUM(AF19*$Z$4) -> 2300 | AH19: =SUM(AF19) -> 230 | AI19: =SUM(AH19*$Z$4) -> 2300 | AJ19: =SUM(AH19) -> 230 | AK19: =SUM(AJ19*$Z$4) -> 2300 | AL19: =SUM(AJ19) -> 230 | AM19: =SUM(AL19*$Z$4) -> 2300 | AN19: =SUM(AO19/19600) -> 0.82142857 | AO19: =SUM(AA19+AC19+AE19+AG19+AI19+AK19+AM19) -> 16100 | AQ19: =SUM(AR19/92970) -> 0.74087409 | AR19: =Y19+AO19 -> 68879.065 | AS19: =SUM(AR19-AR18-AT19) -> -1156.7097 | AV19: =IF(AT19>0,AU19,AV18) -> 0.868 | AW19: =-SUM('B5'!AI18) -> -300 | AX19: =-SUM(AW19-AS19) -> -856.70968 | AY19: =SUM(AX19+AW19) -> -1156.7097 | AZ19: =ELEC!A17 -> 0 | BA19: ='General information '!D18 -> 12.5 | BB19: =SUM('General information '!E18) -> 0.4 | BC19: =IF(AR18>=AR19,0,1) -> 0 | BD19: 19222 | BE19: =(305/1185)*ELEC!Q18 -> 475.38819 | BG19: =#REF!-BE19 -> #REF! | BI19: 6 | BJ19: =AX19/BI19 -> -142.78495
A20: =ELEC!C18 -> 44972 | B20: ='B5'!B19 -> 220 | C20: =B20*$B$4 -> 4733.5484 | D20: =SUM(B20) -> 220 | E20: =D20*$B$4 -> 4733.5484 | F20: =SUM(D20) -> 220 | G20: =F20*$B$4 -> 4733.5484 | H20: =SUM(F20) -> 220 | I20: =H20*$B$4 -> 4733.5484 | J20: =SUM(H20) -> 220 | K20: =J20*$B$4 -> 4733.5484 | L20: =SUM(J20) -> 220 | M20: =L20*$B$4 -> 4733.5484 | N20: =SUM(L20) -> 220 | O20: =N20*$B$4 -> 4733.5484 | P20: =SUM(N20) -> 220 | Q20: =P20*$B$4 -> 4733.5484 | R20: =SUM(P20) -> 220 | S20: =R20*$B$4 -> 4733.5484 | T20: =SUM(R20) -> 220 | U20: =T20*$B$4 -> 4733.5484 | V20: =SUM(T20) -> 220 | W20: =V20*$B$4 -> 4733.5484 | X20: =SUM(Y20/73370) -> 0.70967742 | Y20: =SUM(C20+E20+G20+I20+K20+M20+O20+Q20+S20+U20+W20) -> 52069.032 | Z20: ='B5'!C19 -> 226 | AA20: =SUM(Z20*$Z$4) -> 2260 | AB20: =SUM(Z20) -> 226 | AC20: =SUM(AB20*$Z$4) -> 2260 | AD20: =SUM(AB20) -> 226 | AE20: =SUM(AD20*$Z$4) -> 2260 | AF20: =SUM(AD20) -> 226 | AG20: =SUM(AF20*$Z$4) -> 2260 | AH20: =SUM(AF20) -> 226 | AI20: =SUM(AH20*$Z$4) -> 2260 | AJ20: =SUM(AH20) -> 226 | AK20: =SUM(AJ20*$Z$4) -> 2260 | AL20: =SUM(AJ20) -> 226 | AM20: =SUM(AL20*$Z$4) -> 2260 | AN20: =SUM(AO20/19600) -> 0.80714286 | AO20: =SUM(AA20+AC20+AE20+AG20+AI20+AK20+AM20) -> 15820 | AQ20: =SUM(AR20/92970) -> 0.73022515 | AR20: =Y20+AO20 -> 67889.032 | AS20: =SUM(AR20-AR19-AT20) -> -990.03226 | AV20: =IF(AT20>0,AU20,AV19) -> 0.868 | AW20: =-SUM('B5'!AI19) -> -310 | AX20: =-SUM(AW20-AS20) -> -680.03226 | AY20: =SUM(AX20+AW20) -> -990.03226 | AZ20: =ELEC!A18 -> 0 | BA20: ='General information '!D19 -> 12.5 | BB20: =SUM('General information '!E19) -> 0.39 | BC20: =IF(AR19>=AR20,0,1) -> 0 | BD20: 19222 | BE20: =(305/1185)*ELEC!Q19 -> 676.66245 | BG20: =#REF!-BE20 -> #REF! | BI20: 7 | BJ20: =AX20/BI20 -> -97.147465 | BK20: =GEN!AF17 -> 0.16491071
A21: =ELEC!C19 -> 44973 | B21: ='B5'!B20 -> 237 | C21: =B21*$B$4 -> 5099.3226 | D21: =SUM(B21) -> 237 | E21: =D21*$B$4 -> 5099.3226 | F21: =SUM(D21) -> 237 | G21: =F21*$B$4 -> 5099.3226 | H21: =SUM(F21) -> 237 | I21: =H21*$B$4 -> 5099.3226 | J21: =SUM(H21) -> 237 | K21: =J21*$B$4 -> 5099.3226 | L21: =SUM(J21) -> 237 | M21: =L21*$B$4 -> 5099.3226 | N21: =SUM(L21) -> 237 | O21: =N21*$B$4 -> 5099.3226 | P21: =SUM(N21) -> 237 | Q21: =P21*$B$4 -> 5099.3226 | R21: =SUM(P21) -> 237 | S21: =R21*$B$4 -> 5099.3226 | T21: =SUM(R21) -> 237 | U21: =T21*$B$4 -> 5099.3226 | V21: =SUM(T21) -> 237 | W21: =V21*$B$4 -> 5099.3226 | X21: =SUM(Y21/73370) -> 0.76451613 | Y21: =SUM(C21+E21+G21+I21+K21+M21+O21+Q21+S21+U21+W21) -> 56092.548 | Z21: ='B5'!C20 -> 243 | AA21: =SUM(Z21*$Z$4) -> 2430 | AB21: =SUM(Z21) -> 243 | AC21: =SUM(AB21*$Z$4) -> 2430 | AD21: =SUM(AB21) -> 243 | AE21: =SUM(AD21*$Z$4) -> 2430 | AF21: =SUM(AD21) -> 243 | AG21: =SUM(AF21*$Z$4) -> 2430 | AH21: =SUM(AF21) -> 243 | AI21: =SUM(AH21*$Z$4) -> 2430 | AJ21: =SUM(AH21) -> 243 | AK21: =SUM(AJ21*$Z$4) -> 2430 | AL21: =SUM(AJ21) -> 243 | AM21: =SUM(AL21*$Z$4) -> 2430 | AN21: =SUM(AO21/19600) -> 0.86785714 | AO21: =SUM(AA21+AC21+AE21+AG21+AI21+AK21+AM21) -> 17010 | AQ21: =SUM(AR21/92970) -> 0.78630255 | AR21: =Y21+AO21 -> 73102.548 | AS21: =SUM(AR21-AR20-AT21) -> 5213.5161 | AV21: =IF(AT21>0,AU21,AV20) -> 0.868 | AW21: =-SUM('B5'!AI20) -> -263 | AX21: =-SUM(AW21-AS21) -> 5476.5161 | AY21: =SUM(AX21+AW21) -> 5213.5161 | AZ21: =ELEC!A19 -> 0 | BA21: ='General information '!D20 -> 12.5 | BB21: =SUM('General information '!E20) -> 0.41 | BC21: =IF(AR20>=AR21,0,1) -> 1 | BD21: 19222 | BE21: =(305/1185)*ELEC!Q20 -> 0 | BG21: =#REF!-BE21 -> #REF! | BI21: 8 | BJ21: =AX21/BI21 -> 684.56452 | BK21: =GEN!AF18 -> 0.18256944
A22: =ELEC!C20 -> 44974 | B22: ='B5'!B21 -> 237 | C22: =B22*$B$4 -> 5099.3226 | D22: =SUM(B22) -> 237 | E22: =D22*$B$4 -> 5099.3226 | F22: =SUM(D22) -> 237 | G22: =F22*$B$4 -> 5099.3226 | H22: =SUM(F22) -> 237 | I22: =H22*$B$4 -> 5099.3226 | J22: =SUM(H22) -> 237 | K22: =J22*$B$4 -> 5099.3226 | L22: =SUM(J22) -> 237 | M22: =L22*$B$4 -> 5099.3226 | N22: =SUM(L22) -> 237 | O22: =N22*$B$4 -> 5099.3226 | P22: =SUM(N22) -> 237 | Q22: =P22*$B$4 -> 5099.3226 | R22: =SUM(P22) -> 237 | S22: =R22*$B$4 -> 5099.3226 | T22: =SUM(R22) -> 237 | U22: =T22*$B$4 -> 5099.3226 | V22: =SUM(T22) -> 237 | W22: =V22*$B$4 -> 5099.3226 | X22: =SUM(Y22/73370) -> 0.76451613 | Y22: =SUM(C22+E22+G22+I22+K22+M22+O22+Q22+S22+U22+W22) -> 56092.548 | Z22: ='B5'!C21 -> 243 | AA22: =SUM(Z22*$Z$4) -> 2430 | AB22: =SUM(Z22) -> 243 | AC22: =SUM(AB22*$Z$4) -> 2430 | AD22: =SUM(AB22) -> 243 | AE22: =SUM(AD22*$Z$4) -> 2430 | AF22: =SUM(AD22) -> 243 | AG22: =SUM(AF22*$Z$4) -> 2430 | AH22: =SUM(AF22) -> 243 | AI22: =SUM(AH22*$Z$4) -> 2430 | AJ22: =SUM(AH22) -> 243 | AK22: =SUM(AJ22*$Z$4) -> 2430 | AL22: =SUM(AJ22) -> 243 | AM22: =SUM(AL22*$Z$4) -> 2430 | AN22: =SUM(AO22/19600) -> 0.86785714 | AO22: =SUM(AA22+AC22+AE22+AG22+AI22+AK22+AM22) -> 17010 | AQ22: =SUM(AR22/92970) -> 0.78630255 | AR22: =Y22+AO22 -> 73102.548 | AS22: =SUM(AR22-AR21-AT22) -> 0 | AV22: =IF(AT22>0,AU22,AV21) -> 0.868 | AW22: =-SUM('B5'!AI21) -> 0 | AX22: =-SUM(AW22-AS22) -> 0 | AY22: =SUM(AX22+AW22) -> 0 | AZ22: =ELEC!A20 -> 0 | BA22: ='General information '!D21 -> 0 | BB22: =SUM('General information '!E21) -> 0 | BC22: =IF(AR21>=AR22,0,1) -> 0 | BD22: 19222 | BE22: =(305/1185)*ELEC!Q21 -> 0 | BG22: =#REF!-BE22 -> #REF! | BI22: 9 | BJ22: =AX22/BI22 -> 0 | BK22: =GEN!AF19 -> #DIV/0!
A23: =ELEC!C21 -> 44975 | B23: ='B5'!B22 -> 237 | C23: =B23*$B$4 -> 5099.3226 | D23: =SUM(B23) -> 237 | E23: =D23*$B$4 -> 5099.3226 | F23: =SUM(D23) -> 237 | G23: =F23*$B$4 -> 5099.3226 | H23: =SUM(F23) -> 237 | I23: =H23*$B$4 -> 5099.3226 | J23: =SUM(H23) -> 237 | K23: =J23*$B$4 -> 5099.3226 | L23: =SUM(J23) -> 237 | M23: =L23*$B$4 -> 5099.3226 | N23: =SUM(L23) -> 237 | O23: =N23*$B$4 -> 5099.3226 | P23: =SUM(N23) -> 237 | Q23: =P23*$B$4 -> 5099.3226 | R23: =SUM(P23) -> 237 | S23: =R23*$B$4 -> 5099.3226 | T23: =SUM(R23) -> 237 | U23: =T23*$B$4 -> 5099.3226 | V23: =SUM(T23) -> 237 | W23: =V23*$B$4 -> 5099.3226 | X23: =SUM(Y23/73370) -> 0.76451613 | Y23: =SUM(C23+E23+G23+I23+K23+M23+O23+Q23+S23+U23+W23) -> 56092.548 | Z23: ='B5'!C22 -> 243 | AA23: =SUM(Z23*$Z$4) -> 2430 | AB23: =SUM(Z23) -> 243 | AC23: =SUM(AB23*$Z$4) -> 2430 | AD23: =SUM(AB23) -> 243 | AE23: =SUM(AD23*$Z$4) -> 2430 | AF23: =SUM(AD23) -> 243 | AG23: =SUM(AF23*$Z$4) -> 2430 | AH23: =SUM(AF23) -> 243 | AI23: =SUM(AH23*$Z$4) -> 2430 | AJ23: =SUM(AH23) -> 243 | AK23: =SUM(AJ23*$Z$4) -> 2430 | AL23: =SUM(AJ23) -> 243 | AM23: =SUM(AL23*$Z$4) -> 2430 | AN23: =SUM(AO23/19600) -> 0.86785714 | AO23: =SUM(AA23+AC23+AE23+AG23+AI23+AK23+AM23) -> 17010 | AQ23: =SUM(AR23/92970) -> 0.78630255 | AR23: =Y23+AO23 -> 73102.548 | AS23: =SUM(AR23-AR22-AT23) -> 0 | AV23: =IF(AT23>0,AU23,AV22) -> 0.868 | AW23: =-SUM('B5'!AI22) -> 0 | AX23: =-SUM(AW23-AS23) -> 0 | AY23: =SUM(AX23+AW23) -> 0 | AZ23: =ELEC!A21 -> 0 | BA23: ='General information '!D22 -> 0 | BB23: =SUM('General information '!E22) -> 0 | BC23: =IF(AR22>=AR23,0,1) -> 0 | BD23: 19222 | BE23: =(305/1185)*ELEC!Q22 -> 615.40506 | BG23: =#REF!-BE23 -> #REF! | BI23: 10 | BJ23: =AX23/BI23 -> 0 | BK23: =GEN!AF20 -> #DIV/0!
A24: =ELEC!C22 -> 44976 | B24: ='B5'!B23 -> 234 | C24: =B24*$B$4 -> 5034.7742 | D24: =SUM(B24) -> 234 | E24: =D24*$B$4 -> 5034.7742 | F24: =SUM(D24) -> 234 | G24: =F24*$B$4 -> 5034.7742 | H24: =SUM(F24) -> 234 | I24: =H24*$B$4 -> 5034.7742 | J24: =SUM(H24) -> 234 | K24: =J24*$B$4 -> 5034.7742 | L24: =SUM(J24) -> 234 | M24: =L24*$B$4 -> 5034.7742 | N24: =SUM(L24) -> 234 | O24: =N24*$B$4 -> 5034.7742 | P24: =SUM(N24) -> 234 | Q24: =P24*$B$4 -> 5034.7742 | R24: =SUM(P24) -> 234 | S24: =R24*$B$4 -> 5034.7742 | T24: =SUM(R24) -> 234 | U24: =T24*$B$4 -> 5034.7742 | V24: =SUM(T24) -> 234 | W24: =V24*$B$4 -> 5034.7742 | X24: =SUM(Y24/73370) -> 0.75483871 | Y24: =SUM(C24+E24+G24+I24+K24+M24+O24+Q24+S24+U24+W24) -> 55382.516 | Z24: ='B5'!C23 -> 240 | AA24: =SUM(Z24*$Z$4) -> 2400 | AB24: =SUM(Z24) -> 240 | AC24: =SUM(AB24*$Z$4) -> 2400 | AD24: =SUM(AB24) -> 240 | AE24: =SUM(AD24*$Z$4) -> 2400 | AF24: =SUM(AD24) -> 240 | AG24: =SUM(AF24*$Z$4) -> 2400 | AH24: =SUM(AF24) -> 240 | AI24: =SUM(AH24*$Z$4) -> 2400 | AJ24: =SUM(AH24) -> 240 | AK24: =SUM(AJ24*$Z$4) -> 2400 | AL24: =SUM(AJ24) -> 240 | AM24: =SUM(AL24*$Z$4) -> 2400 | AN24: =SUM(AO24/19600) -> 0.85714286 | AO24: =SUM(AA24+AC24+AE24+AG24+AI24+AK24+AM24) -> 16800 | AQ24: =SUM(AR24/92970) -> 0.77640654 | AR24: =Y24+AO24 -> 72182.516 | AS24: =SUM(AR24-AR23-AT24) -> -6450.0323 | AT24: 5530 | AU24: 0.835 | AV24: =IF(AT24>0,AU24,AV23) -> 0.835 | AW24: =-SUM('B5'!AI23) -> -180 | AX24: =-SUM(AW24-AS24) -> -6270.0323 | AY24: =SUM(AX24+AW24) -> -6450.0323 | AZ24: =ELEC!A22 -> 0 | BA24: ='General information '!D23 -> 15.5 | BB24: =SUM('General information '!E23) -> 0.45 | BC24: =IF(AR23>=AR24,0,1) -> 0 | BD24: 19222 | BE24: =(305/1185)*ELEC!Q23 -> 602.53586 | BG24: =#REF!-BE24 -> #REF! | BI24: 11 | BJ24: =AX24/BI24 -> -570.00293 | BK24: =GEN!AF21 -> 0.1494375
A25: =ELEC!C23 -> 44977 | B25: ='B5'!B24 -> 229.5 | C25: =B25*$B$4 -> 4937.9516 | D25: =SUM(B25) -> 229.5 | E25: =D25*$B$4 -> 4937.9516 | F25: =SUM(D25) -> 229.5 | G25: =F25*$B$4 -> 4937.9516 | H25: =SUM(F25) -> 229.5 | I25: =H25*$B$4 -> 4937.9516 | J25: =SUM(H25) -> 229.5 | K25: =J25*$B$4 -> 4937.9516 | L25: =SUM(J25) -> 229.5 | M25: =L25*$B$4 -> 4937.9516 | N25: =SUM(L25) -> 229.5 | O25: =N25*$B$4 -> 4937.9516 | P25: =SUM(N25) -> 229.5 | Q25: =P25*$B$4 -> 4937.9516 | R25: =SUM(P25) -> 229.5 | S25: =R25*$B$4 -> 4937.9516 | T25: =SUM(R25) -> 229.5 | U25: =T25*$B$4 -> 4937.9516 | V25: =SUM(T25) -> 229.5 | W25: =V25*$B$4 -> 4937.9516 | X25: =SUM(Y25/73370) -> 0.74032258 | Y25: =SUM(C25+E25+G25+I25+K25+M25+O25+Q25+S25+U25+W25) -> 54317.468 | Z25: ='B5'!C24 -> 236 | AA25: =SUM(Z25*$Z$4) -> 2360 | AB25: =SUM(Z25) -> 236 | AC25: =SUM(AB25*$Z$4) -> 2360 | AD25: =SUM(AB25) -> 236 | AE25: =SUM(AD25*$Z$4) -> 2360 | AF25: =SUM(AD25) -> 236 | AG25: =SUM(AF25*$Z$4) -> 2360 | AH25: =SUM(AF25) -> 236 | AI25: =SUM(AH25*$Z$4) -> 2360 | AJ25: =SUM(AH25) -> 236 | AK25: =SUM(AJ25*$Z$4) -> 2360 | AL25: =SUM(AJ25) -> 236 | AM25: =SUM(AL25*$Z$4) -> 2360 | AN25: =SUM(AO25/19600) -> 0.84285714 | AO25: =SUM(AA25+AC25+AE25+AG25+AI25+AK25+AM25) -> 16520 | AQ25: =SUM(AR25/92970) -> 0.76193899 | AR25: =Y25+AO25 -> 70837.468 | AS25: =SUM(AR25-AR24-AT25) -> -1345.0484 | AV25: =IF(AT25>0,AU25,AV24) -> 0.835 | AW25: =-SUM('B5'!AI24) -> -474 | AX25: =-SUM(AW25-AS25) -> -871.04839 | AY25: =SUM(AX25+AW25) -> -1345.0484 | AZ25: =ELEC!A23 -> 0 | BA25: ='General information '!D24 -> 15 | BB25: =SUM('General information '!E24) -> 0.56 | BC25: =IF(AR24>=AR25,0,1) -> 0 | BD25: 19222 | BE25: =(305/1185)*ELEC!Q24 -> 688.50211 | BG25: =#REF!-BE25 -> #REF! | BI25: 12 | BJ25: =AX25/BI25 -> -72.587366
A26: =ELEC!C24 -> 44978 | B26: ='B5'!B25 -> 224 | C26: =B26*$B$4 -> 4819.6129 | D26: =SUM(B26) -> 224 | E26: =D26*$B$4 -> 4819.6129 | F26: =SUM(D26) -> 224 | G26: =F26*$B$4 -> 4819.6129 | H26: =SUM(F26) -> 224 | I26: =H26*$B$4 -> 4819.6129 | J26: =SUM(H26) -> 224 | K26: =J26*$B$4 -> 4819.6129 | L26: =SUM(J26) -> 224 | M26: =L26*$B$4 -> 4819.6129 | N26: =SUM(L26) -> 224 | O26: =N26*$B$4 -> 4819.6129 | P26: =SUM(N26) -> 224 | Q26: =P26*$B$4 -> 4819.6129 | R26: =SUM(P26) -> 224 | S26: =R26*$B$4 -> 4819.6129 | T26: =SUM(R26) -> 224 | U26: =T26*$B$4 -> 4819.6129 | V26: =SUM(T26) -> 224 | W26: =V26*$B$4 -> 4819.6129 | X26: =SUM(Y26/73370) -> 0.72258065 | Y26: =SUM(C26+E26+G26+I26+K26+M26+O26+Q26+S26+U26+W26) -> 53015.742 | Z26: ='B5'!C25 -> 232 | AA26: =SUM(Z26*$Z$4) -> 2320 | AB26: =SUM(Z26) -> 232 | AC26: =SUM(AB26*$Z$4) -> 2320 | AD26: =SUM(AB26) -> 232 | AE26: =SUM(AD26*$Z$4) -> 2320 | AF26: =SUM(AD26) -> 232 | AG26: =SUM(AF26*$Z$4) -> 2320 | AH26: =SUM(AF26) -> 232 | AI26: =SUM(AH26*$Z$4) -> 2320 | AJ26: =SUM(AH26) -> 232 | AK26: =SUM(AJ26*$Z$4) -> 2320 | AL26: =SUM(AJ26) -> 232 | AM26: =SUM(AL26*$Z$4) -> 2320 | AN26: =SUM(AO26/19600) -> 0.82857143 | AO26: =SUM(AA26+AC26+AE26+AG26+AI26+AK26+AM26) -> 16240 | AQ26: =SUM(AR26/92970) -> 0.7449257 | AR26: =Y26+AO26 -> 69255.742 | AS26: =SUM(AR26-AR25-AT26) -> -1581.7258 | AV26: =IF(AT26>0,AU26,AV25) -> 0.835 | AW26: =-SUM('B5'!AI25) -> -236 | AX26: =-SUM(AW26-AS26) -> -1345.7258 | AY26: =SUM(AX26+AW26) -> -1581.7258 | AZ26: =ELEC!A24 -> 0 | BA26: ='General information '!D25 -> 15 | BB26: =SUM('General information '!E25) -> 0.55 | BC26: =IF(AR25>=AR26,0,1) -> 0 | BD26: 19222 | BE26: =(305/1185)*ELEC!Q25 -> 550.80169 | BG26: =#REF!-BE26 -> #REF! | BI26: 13 | BJ26: =AX26/BI26 -> -103.51737
A27: =ELEC!C25 -> 44979 | B27: ='B5'!B26 -> 222 | C27: =B27*$B$4 -> 4776.5806 | D27: =SUM(B27) -> 222 | E27: =D27*$B$4 -> 4776.5806 | F27: =SUM(D27) -> 222 | G27: =F27*$B$4 -> 4776.5806 | H27: =SUM(F27) -> 222 | I27: =H27*$B$4 -> 4776.5806 | J27: =SUM(H27) -> 222 | K27: =J27*$B$4 -> 4776.5806 | L27: =SUM(J27) -> 222 | M27: =L27*$B$4 -> 4776.5806 | N27: =SUM(L27) -> 222 | O27: =N27*$B$4 -> 4776.5806 | P27: =SUM(N27) -> 222 | Q27: =P27*$B$4 -> 4776.5806 | R27: =SUM(P27) -> 222 | S27: =R27*$B$4 -> 4776.5806 | T27: =SUM(R27) -> 222 | U27: =T27*$B$4 -> 4776.5806 | V27: =SUM(T27) -> 222 | W27: =V27*$B$4 -> 4776.5806 | X27: =SUM(Y27/73370) -> 0.71612903 | Y27: =SUM(C27+E27+G27+I27+K27+M27+O27+Q27+S27+U27+W27) -> 52542.387 | Z27: ='B5'!C26 -> 229 | AA27: =SUM(Z27*$Z$4) -> 2290 | AB27: =SUM(Z27) -> 229 | AC27: =SUM(AB27*$Z$4) -> 2290 | AD27: =SUM(AB27) -> 229 | AE27: =SUM(AD27*$Z$4) -> 2290 | AF27: =SUM(AD27) -> 229 | AG27: =SUM(AF27*$Z$4) -> 2290 | AH27: =SUM(AF27) -> 229 | AI27: =SUM(AH27*$Z$4) -> 2290 | AJ27: =SUM(AH27) -> 229 | AK27: =SUM(AJ27*$Z$4) -> 2290 | AL27: =SUM(AJ27) -> 229 | AM27: =SUM(AL27*$Z$4) -> 2290 | AN27: =SUM(AO27/19600) -> 0.81785714 | AO27: =SUM(AA27+AC27+AE27+AG27+AI27+AK27+AM27) -> 16030 | AQ27: =SUM(AR27/92970) -> 0.73757542 | AR27: =Y27+AO27 -> 68572.387 | AS27: =SUM(AR27-AR26-AT27) -> -683.35484 | AV27: =IF(AT27>0,AU27,AV26) -> 0.835 | AW27: =-SUM('B5'!AI26) -> -283 | AX27: =-SUM(AW27-AS27) -> -400.35484 | AY27: =SUM(AX27+AW27) -> -683.35484 | AZ27: =ELEC!A25 -> 0 | BA27: ='General information '!D26 -> 14.5 | BB27: =SUM('General information '!E26) -> 0.66 | BC27: =IF(AR26>=AR27,0,1) -> 0 | BD27: 19222 | BE27: =(305/1185)*ELEC!Q26 -> 726.85232 | BG27: =#REF!-BE27 -> #REF! | BI27: 14 | BJ27: =AX27/BI27 -> -28.596774 | BK27: =GEN!AF24 -> 0.1671875
A28: =ELEC!C26 -> 44980 | B28: ='B5'!B27 -> 218 | C28: =B28*$B$4 -> 4690.5161 | D28: =SUM(B28) -> 218 | E28: =D28*$B$4 -> 4690.5161 | F28: =SUM(D28) -> 218 | G28: =F28*$B$4 -> 4690.5161 | H28: =SUM(F28) -> 218 | I28: =H28*$B$4 -> 4690.5161 | J28: =SUM(H28) -> 218 | K28: =J28*$B$4 -> 4690.5161 | L28: =SUM(J28) -> 218 | M28: =L28*$B$4 -> 4690.5161 | N28: =SUM(L28) -> 218 | O28: =N28*$B$4 -> 4690.5161 | P28: =SUM(N28) -> 218 | Q28: =P28*$B$4 -> 4690.5161 | R28: =SUM(P28) -> 218 | S28: =R28*$B$4 -> 4690.5161 | T28: =SUM(R28) -> 218 | U28: =T28*$B$4 -> 4690.5161 | V28: =SUM(T28) -> 218 | W28: =V28*$B$4 -> 4690.5161 | X28: =SUM(Y28/73370) -> 0.70322581 | Y28: =SUM(C28+E28+G28+I28+K28+M28+O28+Q28+S28+U28+W28) -> 51595.677 | Z28: ='B5'!C27 -> 225 | AA28: =SUM(Z28*$Z$4) -> 2250 | AB28: =SUM(Z28) -> 225 | AC28: =SUM(AB28*$Z$4) -> 2250 | AD28: =SUM(AB28) -> 225 | AE28: =SUM(AD28*$Z$4) -> 2250 | AF28: =SUM(AD28) -> 225 | AG28: =SUM(AF28*$Z$4) -> 2250 | AH28: =SUM(AF28) -> 225 | AI28: =SUM(AH28*$Z$4) -> 2250 | AJ28: =SUM(AH28) -> 225 | AK28: =SUM(AJ28*$Z$4) -> 2250 | AL28: =SUM(AJ28) -> 225 | AM28: =SUM(AL28*$Z$4) -> 2250 | AN28: =SUM(AO28/19600) -> 0.80357143 | AO28: =SUM(AA28+AC28+AE28+AG28+AI28+AK28+AM28) -> 15750 | AQ28: =SUM(AR28/92970) -> 0.72438074 | AR28: =Y28+AO28 -> 67345.677 | AS28: =SUM(AR28-AR27-AT28) -> -1226.7097 | AV28: =IF(AT28>0,AU28,AV27) -> 0.835 | AW28: =-SUM('B5'!AI27) -> -306 | AX28: =-SUM(AW28-AS28) -> -920.70968 | AY28: =SUM(AX28+AW28) -> -1226.7097 | AZ28: =ELEC!A26 -> 0 | BA28: ='General information '!D27 -> 14.5 | BB28: =SUM('General information '!E27) -> 0.66 | BC28: =IF(AR27>=AR28,0,1) -> 0 | BD28: 19222 | BE28: =(305/1185)*ELEC!Q27 -> 0 | BG28: =#REF!-BE28 -> #REF! | BI28: 15 | BJ28: =AX28/BI28 -> -61.380645 | BK28: =GEN!AF25 -> #DIV/0!
A29: =ELEC!C27 -> 44981 | B29: ='B5'!B28 -> 218 | C29: =B29*$B$4 -> 4690.5161 | D29: =SUM(B29) -> 218 | E29: =D29*$B$4 -> 4690.5161 | F29: =SUM(D29) -> 218 | G29: =F29*$B$4 -> 4690.5161 | H29: =SUM(F29) -> 218 | I29: =H29*$B$4 -> 4690.5161 | J29: =SUM(H29) -> 218 | K29: =J29*$B$4 -> 4690.5161 | L29: =SUM(J29) -> 218 | M29: =L29*$B$4 -> 4690.5161 | N29: =SUM(L29) -> 218 | O29: =N29*$B$4 -> 4690.5161 | P29: =SUM(N29) -> 218 | Q29: =P29*$B$4 -> 4690.5161 | R29: =SUM(P29) -> 218 | S29: =R29*$B$4 -> 4690.5161 | T29: =SUM(R29) -> 218 | U29: =T29*$B$4 -> 4690.5161 | V29: =SUM(T29) -> 218 | W29: =V29*$B$4 -> 4690.5161 | X29: =SUM(Y29/73370) -> 0.70322581 | Y29: =SUM(C29+E29+G29+I29+K29+M29+O29+Q29+S29+U29+W29) -> 51595.677 | Z29: ='B5'!C28 -> 225 | AA29: =SUM(Z29*$Z$4) -> 2250 | AB29: =SUM(Z29) -> 225 | AC29: =SUM(AB29*$Z$4) -> 2250 | AD29: =SUM(AB29) -> 225 | AE29: =SUM(AD29*$Z$4) -> 2250 | AF29: =SUM(AD29) -> 225 | AG29: =SUM(AF29*$Z$4) -> 2250 | AH29: =SUM(AF29) -> 225 | AI29: =SUM(AH29*$Z$4) -> 2250 | AJ29: =SUM(AH29) -> 225 | AK29: =SUM(AJ29*$Z$4) -> 2250 | AL29: =SUM(AJ29) -> 225 | AM29: =SUM(AL29*$Z$4) -> 2250 | AN29: =SUM(AO29/19600) -> 0.80357143 | AO29: =SUM(AA29+AC29+AE29+AG29+AI29+AK29+AM29) -> 15750 | AQ29: =SUM(AR29/92970) -> 0.72438074 | AR29: =Y29+AO29 -> 67345.677 | AS29: =SUM(AR29-AR28-AT29) -> 0 | AV29: =IF(AT29>0,AU29,AV28) -> 0.835 | AW29: =-SUM('B5'!AI28) -> 0 | AX29: =-SUM(AW29-AS29) -> 0 | AY29: =SUM(AX29+AW29) -> 0 | AZ29: =ELEC!A27 -> 0 | BA29: ='General information '!D28 -> 14.5 | BB29: =SUM('General information '!E28) -> 0.66 | BC29: =IF(AR28>=AR29,0,1) -> 0 | BD29: 19222 | BE29: =(305/1185)*ELEC!Q28 -> 0 | BG29: =#REF!-BE29 -> #REF! | BI29: 16 | BJ29: =AX29/BI29 -> 0 | BK29: =GEN!AF26 -> 0
A30: =ELEC!C28 -> 44982 | B30: ='B5'!B29 -> 218 | C30: =B30*$B$4 -> 4690.5161 | D30: =SUM(B30) -> 218 | E30: =D30*$B$4 -> 4690.5161 | F30: =SUM(D30) -> 218 | G30: =F30*$B$4 -> 4690.5161 | H30: =SUM(F30) -> 218 | I30: =H30*$B$4 -> 4690.5161 | J30: =SUM(H30) -> 218 | K30: =J30*$B$4 -> 4690.5161 | L30: =SUM(J30) -> 218 | M30: =L30*$B$4 -> 4690.5161 | N30: =SUM(L30) -> 218 | O30: =N30*$B$4 -> 4690.5161 | P30: =SUM(N30) -> 218 | Q30: =P30*$B$4 -> 4690.5161 | R30: =SUM(P30) -> 218 | S30: =R30*$B$4 -> 4690.5161 | T30: =SUM(R30) -> 218 | U30: =T30*$B$4 -> 4690.5161 | V30: =SUM(T30) -> 218 | W30: =V30*$B$4 -> 4690.5161 | X30: =SUM(Y30/73370) -> 0.70322581 | Y30: =SUM(C30+E30+G30+I30+K30+M30+O30+Q30+S30+U30+W30) -> 51595.677 | Z30: ='B5'!C29 -> 225 | AA30: =SUM(Z30*$Z$4) -> 2250 | AB30: =SUM(Z30) -> 225 | AC30: =SUM(AB30*$Z$4) -> 2250 | AD30: =SUM(AB30) -> 225 | AE30: =SUM(AD30*$Z$4) -> 2250 | AF30: =SUM(AD30) -> 225 | AG30: =SUM(AF30*$Z$4) -> 2250 | AH30: =SUM(AF30) -> 225 | AI30: =SUM(AH30*$Z$4) -> 2250 | AJ30: =SUM(AH30) -> 225 | AK30: =SUM(AJ30*$Z$4) -> 2250 | AL30: =SUM(AJ30) -> 225 | AM30: =SUM(AL30*$Z$4) -> 2250 | AN30: =SUM(AO30/19600) -> 0.80357143 | AO30: =SUM(AA30+AC30+AE30+AG30+AI30+AK30+AM30) -> 15750 | AQ30: =SUM(AR30/92970) -> 0.72438074 | AR30: =Y30+AO30 -> 67345.677 | AS30: =SUM(AR30-AR29-AT30) -> 0 | AV30: =IF(AT30>0,AU30,AV29) -> 0.835 | AW30: =-SUM('B5'!AI29) -> 0 | AX30: =-SUM(AW30-AS30) -> 0 | AY30: =SUM(AX30+AW30) -> 0 | AZ30: =ELEC!A28 -> 0 | BA30: ='General information '!D29 -> 17 | BB30: =SUM('General information '!E29) -> 0.66 | BC30: =IF(AR29>=AR30,0,1) -> 0 | BD30: 19222 | BE30: =(305/1185)*ELEC!Q29 -> 619.52321 | BG30: =#REF!-BE30 -> #REF! | BI30: 17 | BJ30: =AX30/BI30 -> 0 | BK30: =GEN!AF27 -> #DIV/0!
A31: =ELEC!C29 -> 44983 | B31: ='B5'!B30 -> 235 | C31: =B31*$B$4 -> 5056.2903 | D31: =SUM(B31) -> 235 | E31: =D31*$B$4 -> 5056.2903 | F31: =SUM(D31) -> 235 | G31: =F31*$B$4 -> 5056.2903 | H31: =SUM(F31) -> 235 | I31: =H31*$B$4 -> 5056.2903 | J31: =SUM(H31) -> 235 | K31: =J31*$B$4 -> 5056.2903 | L31: =SUM(J31) -> 235 | M31: =L31*$B$4 -> 5056.2903 | N31: =SUM(L31) -> 235 | O31: =N31*$B$4 -> 5056.2903 | P31: =SUM(N31) -> 235 | Q31: =P31*$B$4 -> 5056.2903 | R31: =SUM(P31) -> 235 | S31: =R31*$B$4 -> 5056.2903 | T31: =SUM(R31) -> 235 | U31: =T31*$B$4 -> 5056.2903 | V31: =SUM(T31) -> 235 | W31: =V31*$B$4 -> 5056.2903 | X31: =SUM(Y31/73370) -> 0.75806452 | Y31: =SUM(C31+E31+G31+I31+K31+M31+O31+Q31+S31+U31+W31) -> 55619.194 | Z31: ='B5'!C30 -> 241 | AA31: =SUM(Z31*$Z$4) -> 2410 | AB31: =SUM(Z31) -> 241 | AC31: =SUM(AB31*$Z$4) -> 2410 | AD31: =SUM(AB31) -> 241 | AE31: =SUM(AD31*$Z$4) -> 2410 | AF31: =SUM(AD31) -> 241 | AG31: =SUM(AF31*$Z$4) -> 2410 | AH31: =SUM(AF31) -> 241 | AI31: =SUM(AH31*$Z$4) -> 2410 | AJ31: =SUM(AH31) -> 241 | AK31: =SUM(AJ31*$Z$4) -> 2410 | AL31: =SUM(AJ31) -> 241 | AM31: =SUM(AL31*$Z$4) -> 2410 | AN31: =SUM(AO31/19600) -> 0.86071429 | AO31: =SUM(AA31+AC31+AE31+AG31+AI31+AK31+AM31) -> 16870 | AQ31: =SUM(AR31/92970) -> 0.77970521 | AR31: =Y31+AO31 -> 72489.194 | AS31: =SUM(AR31-AR30-AT31) -> -386.48387 | AT31: 5530 | AU31: 0.88 | AV31: =IF(AT31>0,AU31,AV30) -> 0.88 | AW31: =-SUM('B5'!AI30) -> -242 | AX31: =-SUM(AW31-AS31) -> -144.48387 | AY31: =SUM(AX31+AW31) -> -386.48387 | AZ31: =ELEC!A29 -> 0 | BA31: ='General information '!D30 -> 18.5 | BB31: =SUM('General information '!E30) -> 0.66 | BC31: =IF(AR30>=AR31,0,1) -> 1 | BD31: 19222 | BE31: =(305/1185)*ELEC!Q30 -> 598.16034 | BG31: =#REF!-BE31 -> #REF! | BI31: 18 | BJ31: =AX31/BI31 -> -8.0268817 | BK31: =GEN!AF28 -> 0.1504375
A32: =ELEC!C30 -> 44984 | B32: ='B5'!B31 -> 231 | C32: =B32*$B$4 -> 4970.2258 | D32: =SUM(B32) -> 231 | E32: =D32*$B$4 -> 4970.2258 | F32: =SUM(D32) -> 231 | G32: =F32*$B$4 -> 4970.2258 | H32: =SUM(F32) -> 231 | I32: =H32*$B$4 -> 4970.2258 | J32: =SUM(H32) -> 231 | K32: =J32*$B$4 -> 4970.2258 | L32: =SUM(J32) -> 231 | M32: =L32*$B$4 -> 4970.2258 | N32: =SUM(L32) -> 231 | O32: =N32*$B$4 -> 4970.2258 | P32: =SUM(N32) -> 231 | Q32: =P32*$B$4 -> 4970.2258 | R32: =SUM(P32) -> 231 | S32: =R32*$B$4 -> 4970.2258 | T32: =SUM(R32) -> 231 | U32: =T32*$B$4 -> 4970.2258 | V32: =SUM(T32) -> 231 | W32: =V32*$B$4 -> 4970.2258 | X32: =SUM(Y32/73370) -> 0.74516129 | Y32: =SUM(C32+E32+G32+I32+K32+M32+O32+Q32+S32+U32+W32) -> 54672.484 | Z32: ='B5'!C31 -> 238 | AA32: =SUM(Z32*$Z$4) -> 2380 | AB32: =SUM(Z32) -> 238 | AC32: =SUM(AB32*$Z$4) -> 2380 | AD32: =SUM(AB32) -> 238 | AE32: =SUM(AD32*$Z$4) -> 2380 | AF32: =SUM(AD32) -> 238 | AG32: =SUM(AF32*$Z$4) -> 2380 | AH32: =SUM(AF32) -> 238 | AI32: =SUM(AH32*$Z$4) -> 2380 | AJ32: =SUM(AH32) -> 238 | AK32: =SUM(AJ32*$Z$4) -> 2380 | AL32: =SUM(AJ32) -> 238 | AM32: =SUM(AL32*$Z$4) -> 2380 | AN32: =SUM(AO32/19600) -> 0.85 | AO32: =SUM(AA32+AC32+AE32+AG32+AI32+AK32+AM32) -> 16660 | AQ32: =SUM(AR32/92970) -> 0.76726346 | AR32: =Y32+AO32 -> 71332.484 | AS32: =SUM(AR32-AR31-AT32) -> -1156.7097 | AV32: =IF(AT32>0,AU32,AV31) -> 0.88 | AW32: =-SUM('B5'!AI31) -> -385 | AX32: =-SUM(AW32-AS32) -> -771.70968 | AY32: =SUM(AX32+AW32) -> -1156.7097 | AZ32: =ELEC!A30 -> 0 | BA32: ='General information '!D31 -> 20.5 | BB32: =SUM('General information '!E31) -> 0.44 | BC32: =IF(AR31>=AR32,0,1) -> 0 | BD32: 19222 | BE32: =(305/1185)*ELEC!Q31 -> 0 | BG32: =#REF!-BE32 -> #REF! | BI32: 19 | BJ32: =AX32/BI32 -> -40.616299 | BK32: =GEN!AF29 -> 0.16138889
A33: =ELEC!C31 -> 44985 | B33: ='B5'!B32 -> 231 | C33: =B33*$B$4 -> 4970.2258 | D33: =SUM(B33) -> 231 | E33: =D33*$B$4 -> 4970.2258 | F33: =SUM(D33) -> 231 | G33: =F33*$B$4 -> 4970.2258 | H33: =SUM(F33) -> 231 | I33: =H33*$B$4 -> 4970.2258 | J33: =SUM(H33) -> 231 | K33: =J33*$B$4 -> 4970.2258 | L33: =SUM(J33) -> 231 | M33: =L33*$B$4 -> 4970.2258 | N33: =SUM(L33) -> 231 | O33: =N33*$B$4 -> 4970.2258 | P33: =SUM(N33) -> 231 | Q33: =P33*$B$4 -> 4970.2258 | R33: =SUM(P33) -> 231 | S33: =R33*$B$4 -> 4970.2258 | T33: =SUM(R33) -> 231 | U33: =T33*$B$4 -> 4970.2258 | V33: =SUM(T33) -> 231 | W33: =V33*$B$4 -> 4970.2258 | X33: =SUM(Y33/73370) -> 0.74516129 | Y33: =SUM(C33+E33+G33+I33+K33+M33+O33+Q33+S33+U33+W33) -> 54672.484 | Z33: ='B5'!C32 -> 238 | AA33: =SUM(Z33*$Z$4) -> 2380 | AB33: =SUM(Z33) -> 238 | AC33: =SUM(AB33*$Z$4) -> 2380 | AD33: =SUM(AB33) -> 238 | AE33: =SUM(AD33*$Z$4) -> 2380 | AF33: =SUM(AD33) -> 238 | AG33: =SUM(AF33*$Z$4) -> 2380 | AH33: =SUM(AF33) -> 238 | AI33: =SUM(AH33*$Z$4) -> 2380 | AJ33: =SUM(AH33) -> 238 | AK33: =SUM(AJ33*$Z$4) -> 2380 | AL33: =SUM(AJ33) -> 238 | AM33: =SUM(AL33*$Z$4) -> 2380 | AN33: =SUM(AO33/19600) -> 0.85 | AO33: =SUM(AA33+AC33+AE33+AG33+AI33+AK33+AM33) -> 16660 | AQ33: =SUM(AR33/92970) -> 0.76726346 | AR33: =Y33+AO33 -> 71332.484 | AS33: =SUM(AR33-AR32-AT33) -> 0 | AV33: =IF(AT33>0,AU33,AV32) -> 0.88 | AW33: =-SUM('B5'!AI32) -> 0 | AX33: =-SUM(AW33-AS33) -> 0 | AY33: =SUM(AX33+AW33) -> 0 | AZ33: =ELEC!A31 -> 0 | BA33: ='General information '!D32 -> 0 | BB33: =SUM('General information '!E32) -> 0 | BC33: =IF(AR32>=AR33,0,1) -> 0 | BD33: 19222 | BE33: =(305/1185)*ELEC!#REF! -> #REF! | BG33: =#REF!-BE33 -> #REF! | BI33: 20 | BJ33: =AX33/BI33 -> 0 | BK33: =GEN!AF30 -> #DIV/0!
A34: =ELEC!C32 -> 44986 | B34: ='B5'!B33 -> 231 | C34: =B34*$B$4 -> 4970.2258 | D34: =SUM(B34) -> 231 | E34: =D34*$B$4 -> 4970.2258 | F34: =SUM(D34) -> 231 | G34: =F34*$B$4 -> 4970.2258 | H34: =SUM(F34) -> 231 | I34: =H34*$B$4 -> 4970.2258 | J34: =SUM(H34) -> 231 | K34: =J34*$B$4 -> 4970.2258 | L34: =SUM(J34) -> 231 | M34: =L34*$B$4 -> 4970.2258 | N34: =SUM(L34) -> 231 | O34: =N34*$B$4 -> 4970.2258 | P34: =SUM(N34) -> 231 | Q34: =P34*$B$4 -> 4970.2258 | R34: =SUM(P34) -> 231 | S34: =R34*$B$4 -> 4970.2258 | T34: =SUM(R34) -> 231 | U34: =T34*$B$4 -> 4970.2258 | V34: =SUM(T34) -> 231 | W34: =V34*$B$4 -> 4970.2258 | X34: =SUM(Y34/73370) -> 0.74516129 | Y34: =SUM(C34+E34+G34+I34+K34+M34+O34+Q34+S34+U34+W34) -> 54672.484 | Z34: ='B5'!C33 -> 238 | AA34: =SUM(Z34*$Z$4) -> 2380 | AB34: =SUM(Z34) -> 238 | AC34: =SUM(AB34*$Z$4) -> 2380 | AD34: =SUM(AB34) -> 238 | AE34: =SUM(AD34*$Z$4) -> 2380 | AF34: =SUM(AD34) -> 238 | AG34: =SUM(AF34*$Z$4) -> 2380 | AH34: =SUM(AF34) -> 238 | AI34: =SUM(AH34*$Z$4) -> 2380 | AJ34: =SUM(AH34) -> 238 | AK34: =SUM(AJ34*$Z$4) -> 2380 | AL34: =SUM(AJ34) -> 238 | AM34: =SUM(AL34*$Z$4) -> 2380 | AN34: =SUM(AO34/19600) -> 0.85 | AO34: =SUM(AA34+AC34+AE34+AG34+AI34+AK34+AM34) -> 16660 | AQ34: =SUM(AR34/92970) -> 0.76726346 | AR34: =Y34+AO34 -> 71332.484 | AS34: =SUM(AR34-AR33-AT34) -> 0 | AV34: =IF(AT34>0,AU34,AV33) -> 0.88 | AW34: =-SUM('B5'!AI33) -> 0 | AX34: =-SUM(AW34-AS34) -> 0 | AY34: =SUM(AX34+AW34) -> 0 | AZ34: =ELEC!A32 -> 0 | BA34: ='General information '!D33 -> 0 | BB34: =SUM('General information '!E33) -> 0 | BC34: =IF(AR33>=AR34,0,1) -> 0 | BD34: 19223 | BE34: =(305/1185)*ELEC!#REF! -> #REF! | BG34: =#REF!-BE34 -> #REF! | BI34: 21 | BJ34: =AX34/BI34 -> 0 | BK34: =GEN!AF31 -> #DIV/0!
AR37: NB delivery | AS37: =COUNT(AT6:AT36) -> 3 | AT37: =SUM(AT6:AT36) -> 18230 | AU37: =SUM(AU6:AU36)/AS37 -> 0.861 | AX37: =SUM(AX6:AX36) -> -14291.387 | AY37: =SUM(AY6:AY36) -> -19623.387
AT38: =+AT37*AU37 -> 15696.03
AS40: =SUM(AS6:AS36)/'EDl log'!A35 -> -2180.3763
AX41: 43309
AR42: =AR36-22000 -> -22000 | AX42: =AX37/AX41 -> -0.32998654
AR43: =AR42/5500 -> -4
AR44: =AR43*2 -> -8

Sheet WATER
D1: =SUM(G21:G33) -> 8230445 | AR1: Entrance | AT1: Tank 1 | AV1: Tank 2
AR2: Level | AW2: Quantity CM3 | AZ2: Var
A3: Date | B3: Truck | C3: Truck M3/day | D3: N0. Trucks | F3: REQ. # of trucks | G3: City | H3: City/day | I3: Total water delivery | K3: SW | L3: Cosum SW/day | M3: RO Guest/ Liter | O3: RO K&L/ Liter | Q3: TOTAL RO Production | R3: RO 1 RH | S3: RO 2 RH | T3: RO water counter | U3: RO Cons m3 | V3: Steam Boiler | W3: Steam Boiler/day | X3: Softener Guest | Y3: Guest Sotf/day | Z3: Softener K&L | AA3: K&L Soft/Day | AB3: Fire Tank Level | AC3: Fire Tank Counter | AE3: Laundry Hot Water Counter | AF3: Hot Water Cons/day | AG3: Laundry Cold Water Counter | AH3: Cold Water Cons/day | AI3: Laundry Water Total Cons | AJ3: K&L Sotf/day | AK3: Guest / day | AL3: K&L /day | AM3: Avg Outside Temp | AN3: Banquet Activity | AR3: Date | AT3: MainI | AV3: Kitchen and Laundry | AX3: Guest | AY3: Main Tank | AZ3: Kitchen and Laundry | BA3: Guest | BB3: Kitchen and Laundry | BC3: Main | BD3: Guest | BE3: Total VAR | BF3: Hotel Consumption
E4: 1.66 | AN4: Ball R | AO4: Meeting | AP4: outlet | AT4: 180 | AV4: 220 | AX4: 580 | AY4: =SUM(AT4) -> 180 | AZ4: =SUM(AV4) -> 220 | BA4: =SUM(AX4) -> 580
A5: 44592 | B5: =[2]WATER!B36 -> 109443 | C5: =[2]WATER!C36 -> 0 | D5: =[2]WATER!D36 -> 0 | E5: =[2]WATER!E36 -> 241.93548 | F5: =[2]WATER!F36 -> 0 | G5: =[2]WATER!G36 -> 632735 | H5: =[2]WATER!H36 -> 73 | I5: =[2]WATER!I36 -> 73 | ... AP5: =[2]WATER!AP36 -> 0 | AR5: 44592 | AS5: =[2]WATER!AS36 -> 0.9 | AT5: =[2]WATER!AT36 -> 114 | AU5: =[2]WATER!AU36 -> 1.1 | AV5: =[2]WATER!AV36 -> 101 | AW5: =[2]WATER!AW36 -> 2.9 | AX5: =[2]WATER!AX36 -> 98 | AY5: =[2]WATER!AY36 -> 102.6 | AZ5: =[2]WATER!AZ36 -> 111.1 | ... BG5: =[2]WATER!BG36 -> 27.6
A6: =ELEC!C4 -> 44958 | B6: =B5 -> 109443 | C6: =B6-B5 -> 0 | D6: =C6/27 -> 0 | E6: =SUM((C6*$E$4)+(7500/'EDl log'!$A$37)) -> 267.85714 | G6: =G5 -> 632735 | H6: =G6-G5 -> 0 | I6: =C6+H6 -> 0 | J6: =IF(I6>0,E6/I6,0) -> 0 | K6: =K5 -> 7089 | L6: 0 | M6: =M5 -> 457.44 | N6: =SUM(M6-M5) -> 0 | O6: =O5 -> 529.52 | P6: =SUM(O6-O5) -> 0 | Q6: =P6+N6 -> 0 | T6: =T5 -> 5202 | U6: =SUM(T6-T5) -> 0 | V6: =V5 -> 518 | W6: =+V6-V5 -> 0 | X6: =X5 -> 156588 | Y6: =SUM(X6-X5) -> 0 | Z6: =Z5 -> 99955 | AA6: =Z6-Z5 -> 0 | AB6: =AB5 -> 242 | AC6: =AC5 -> 855 | AD6: 0 | AE6: =AE5 -> 262.47 | AF6: =AE6-AE5 -> 0 | AG6: =AG5 -> 2247.41 | AH6: =AG6-AG5 -> 0 | AI6: =AF6+AH6 -> 0 | AJ6: =+Z6-Z5 -> 0 | AK6: =SUM(Y6-L6) -> 0 | AL6: =SUM(AJ6-W6) -> 0 | AM6: ='General information '!D5 -> 13 | AN6: ='General information '!H5 -> 0 | AP6: ='General information '!J5 -> 0 | AR6: =A6 -> 44958 | AS6: =AS5 -> 0.9 | AT6: =AT5 -> 114 | AU6: =AU5 -> 1.1 | AV6: =AV5 -> 101 | AW6: 2.9 | AX6: =AX5 -> 98 | AY6: =AS6*AT6 -> 102.6 | AZ6: =AU6*AV6 -> 111.1 | BA6: =AW6*AX6 -> 284.2 | BB6: =AY6-AY5 -> 0 | BC6: =AZ6-AZ5 -> 0 | BD6: =BA6-BA5 -> 0 | BE6: =SUM(BB6:BD6) -> 0 | BF6: =SUM(I6-BE6) -> 0 | BG6: =SUM(I6-BF6) -> 0
A7: =ELEC!C5 -> 44959 | B7: =B6 -> 109443 | C7: =B7-B6 -> 0 | D7: =C7/27 -> 0 | E7: =SUM((C7*$E$4)+(7500/'EDl log'!$A$37)) -> 267.85714 | G7: =G6 -> 632735 | H7: =G7-G6 -> 0 | I7: =C7+H7 -> 0 | J7: =IF(I7>0,E7/I7,0) -> 0 | K7: =K6 -> 7089 | L7: =K7-K6 -> 0 | M7: =M6 -> 457.44 | N7: =SUM(M7-M6) -> 0 | O7: =O6 -> 529.52 | P7: =SUM(O7-O6) -> 0 | Q7: =P7+N7 -> 0 | T7: =T6 -> 5202 | U7: =SUM(T7-T6) -> 0 | V7: =V6 -> 518 | W7: =+V7-V6 -> 0 | X7: =X6 -> 156588 | Y7: =SUM(X7-X6) -> 0 | Z7: =Z6 -> 99955 | AA7: =Z7-Z6 -> 0 | AB7: =AB6 -> 242 | AC7: =AC6 -> 855 | AD7: =AC7-AC6 -> 0 | AE7: =AE6 -> 262.47 | AF7: =AE7-AE6 -> 0 | AG7: =AG6 -> 2247.41 | AH7: =AG7-AG6 -> 0 | AI7: =AF7+AH7 -> 0 | AJ7: =+Z7-Z6 -> 0 | AK7: =SUM(Y7-L7) -> 0 | AL7: =SUM(AJ7-W7) -> 0 | AM7: ='General information '!D6 -> 13.5 | AN7: ='General information '!H6 -> 0 | AP7: ='General information '!J6 -> 0 | AR7: =A7 -> 44959 | AS7: =AS6 -> 0.9 | AT7: 114 | AU7: =AU6 -> 1.1 | AV7: 97 | AW7: 2.9 | AX7: 96 | AY7: =AS7*AT7 -> 102.6 | AZ7: =AU7*AV7 -> 106.7 | BA7: =AW7*AX7 -> 278.4 | BB7: =AY7-AY6 -> 0 | BC7: =AZ7-AZ6 -> -4.4 | BD7: =BA7-BA6 -> -5.8 | BE7: =SUM(BB7:BD7) -> -10.2 | BF7: =SUM(I7-BE7) -> 10.2 | BG7: =SUM(I7-BF7) -> -10.2
A8: =ELEC!C6 -> 44960 | B8: =B7 -> 109443 | C8: =B8-B7 -> 0 | D8: =C8/27 -> 0 | E8: =SUM((C8*$E$4)+(7500/'EDl log'!$A$37)) -> 267.85714 | G8: =G7 -> 632735 | H8: =G8-G7 -> 0 | I8: =C8+H8 -> 0 | J8: =IF(I8>0,E8/I8,0) -> 0 | K8: =K7 -> 7089 | L8: =K8-K7 -> 0 | M8: =M7 -> 457.44 | N8: =SUM(M8-M7) -> 0 | O8: =O7 -> 529.52 | P8: =SUM(O8-O7) -> 0 | Q8: =P8+N8 -> 0 | T8: =T7 -> 5202 | U8: =SUM(T8-T7) -> 0 | V8: =V7 -> 518 | W8: =+V8-V7 -> 0 | X8: =X7 -> 156588 | Y8: =SUM(X8-X7) -> 0 | Z8: =Z7 -> 99955 | AA8: =Z8-Z7 -> 0 | AB8: 242 | AC8: =AC7 -> 855 | AD8: =AC8-AC7 -> 0 | AE8: =AE7 -> 262.47 | AF8: =AE8-AE7 -> 0 | AG8: =AG7 -> 2247.41 | AH8: =AG8-AG7 -> 0 | AI8: =AF8+AH8 -> 0 | AJ8: =+Z8-Z7 -> 0 | AK8: =SUM(Y8-L8) -> 0 | AL8: =SUM(AJ8-W8) -> 0 | AM8: ='General information '!D7 -> 0 | AN8: ='General information '!H7 -> 0 | AP8: ='General information '!J7 -> 0 | AR8: =A8 -> 44960 | AS8: =AS7 -> 0.9 | AT8: 114 | AU8: 1.1 | AV8: 97 | AW8: 2.9 | AX8: 96 | AY8: =AS8*AT8 -> 102.6 | AZ8: =AU8*AV8 -> 106.7 | BA8: =AW8*AX8 -> 278.4 | BB8: =AY8-AY7 -> 0 | BC8: =AZ8-AZ7 -> 0 | BD8: =BA8-BA7 -> 0 | BE8: =SUM(BB8:BD8) -> 0 | BF8: =SUM(I8-BE8) -> 0 | BG8: =SUM(I8-BF8) -> 0
A9: =ELEC!C7 -> 44961 | B9: =B8 -> 109443 | C9: =B9-B8 -> 0 | D9: =C9/27 -> 0 | E9: =SUM((C9*$E$4)+(7500/'EDl log'!$A$37)) -> 267.85714 | G9: =G8 -> 632735 | H9: =G9-G8 -> 0 | I9: =C9+H9 -> 0 | J9: =IF(I9>0,E9/I9,0) -> 0 | K9: =K8 -> 7089 | L9: =K9-K8 -> 0 | M9: =M8 -> 457.44 | N9: =SUM(M9-M8) -> 0 | O9: =O8 -> 529.52 | P9: =SUM(O9-O8) -> 0 | Q9: =P9+N9 -> 0 | T9: =T8 -> 5202 | U9: =SUM(T9-T8) -> 0 | V9: =V8 -> 518 | W9: =+V9-V8 -> 0 | X9: =X8 -> 156588 | Y9: =SUM(X9-X8) -> 0 | Z9: =Z8 -> 99955 | AA9: =Z9-Z8 -> 0 | AB9: =AB8 -> 242 | AC9: =AC8 -> 855 | AD9: =AC9-AC8 -> 0 | AE9: =AE8 -> 262.47 | AF9: =AE9-AE8 -> 0 | AG9: =AG8 -> 2247.41 | AH9: =AG9-AG8 -> 0 | AI9: =AF9+AH9 -> 0 | AJ9: =+Z9-Z8 -> 0 | AK9: =SUM(Y9-L9) -> 0 | AL9: =SUM(AJ9-W9) -> 0 | AM9: ='General information '!D8 -> 0 | AN9: ='General information '!H8 -> 0 | AP9: ='General information '!J8 -> 0 | AR9: =A9 -> 44961 | AS9: =AS8 -> 0.9 | AT9: =AT8 -> 114 | AU9: =AU8 -> 1.1 | AV9: =AV8 -> 97 | AW9: 2.9 | AX9: =AX8 -> 96 | AY9: =AS9*AT9 -> 102.6 | AZ9: =AU9*AV9 -> 106.7 | BA9: =AW9*AX9 -> 278.4 | BB9: =AY9-AY8 -> 0 | BC9: =AZ9-AZ8 -> 0 | BD9: =BA9-BA8 -> 0 | BE9: =SUM(BB9:BD9) -> 0 | BF9: =SUM(I9-BE9) -> 0 | BG9: =SUM(I9-BF9) -> 0
A10: =ELEC!C8 -> 44962 | B10: =B9 -> 109443 | C10: =B10-B9 -> 0 | D10: =C10/27 -> 0 | E10: =SUM((C10*$E$4)+(7500/'EDl log'!$A$37)) -> 267.85714 | G10: =G9 -> 632735 | H10: =G10-G9 -> 0 | I10: =C10+H10 -> 0 | J10: =IF(I10>0,E10/I10,0) -> 0 | K10: =K9 -> 7089 | L10: =K10-K9 -> 0 | M10: =M9 -> 457.44 | N10: =SUM(M10-M9) -> 0 | O10: =O9 -> 529.52 | P10: =SUM(O10-O9) -> 0 | Q10: =P10+N10 -> 0 | T10: =T9 -> 5202 | U10: =SUM(T10-T9) -> 0 | V10: =V9 -> 518 | W10: =+V10-V9 -> 0 | X10: =X9 -> 156588 | Y10: =SUM(X10-X9) -> 0 | Z10: =Z9 -> 99955 | AA10: =Z10-Z9 -> 0 | AB10: =AB9 -> 242 | AC10: =AC9 -> 855 | AD10: =AC10-AC9 -> 0 | AE10: =AE9 -> 262.47 | AF10: =AE10-AE9 -> 0 | AG10: =AG9 -> 2247.41 | AH10: =AG10-AG9 -> 0 | AI10: =AF10+AH10 -> 0 | AJ10: =+Z10-Z9 -> 0 | AK10: =SUM(Y10-L10) -> 0 | AL10: =SUM(AJ10-W10) -> 0 | AM10: ='General information '!D9 -> 11.5 | AN10: ='General information '!H9 -> 0 | AP10: ='General information '!J9 -> 0 | AR10: =A10 -> 44962 | AS10: =AS9 -> 0.9 | AT10: =AT9 -> 114 | AU10: =AU9 -> 1.1 | AV10: 92 | AW10: 2.9 | AX10: 93 | AY10: =AS10*AT10 -> 102.6 | AZ10: =AU10*AV10 -> 101.2 | BA10: =AW10*AX10 -> 269.7 | BB10: =AY10-AY9 -> 0 | BC10: =AZ10-AZ9 -> -5.5 | BD10: =BA10-BA9 -> -8.7 | BE10: =SUM(BB10:BD10) -> -14.2 | BF10: =SUM(I10-BE10) -> 14.2 | BG10: =SUM(I10-BF10) -> -14.2
A11: =ELEC!C9 -> 44963 | B11: =B10 -> 109443 | C11: =B11-B10 -> 0 | D11: =C11/27 -> 0 | E11: =SUM((C11*$E$4)+(7500/'EDl log'!$A$37)) -> 267.85714 | G11: =G10 -> 632735 | H11: =G11-G10 -> 0 | I11: =C11+H11 -> 0 | J11: =IF(I11>0,E11/I11,0) -> 0 | K11: =K10 -> 7089 | L11: =K11-K10 -> 0 | M11: =M10 -> 457.44 | N11: =SUM(M11-M10) -> 0 | O11: =O10 -> 529.52 | P11: =SUM(O11-O10) -> 0 | Q11: =SUM(P11+N11) -> 0 | T11: =T10 -> 5202 | U11: =SUM(T11-T10) -> 0 | V11: =V10 -> 518 | W11: =+V11-V10 -> 0 | X11: =X10 -> 156588 | Y11: =SUM(X11-X10) -> 0 | Z11: =Z10 -> 99955 | AA11: =Z11-Z10 -> 0 | AB11: =AB10 -> 242 | AC11: =AC10 -> 855 | AD11: =AC11-AC10 -> 0 | AE11: =AE10 -> 262.47 | AF11: =AE11-AE10 -> 0 | AG11: =AG10 -> 2247.41 | AH11: =AG11-AG10 -> 0 | AI11: =AF11+AH11 -> 0 | AJ11: =+Z11-Z10 -> 0 | AK11: =SUM(Y11-L11) -> 0 | AL11: =SUM(AJ11-W11) -> 0 | AM11: ='General information '!D10 -> 11 | AN11: ='General information '!H10 -> 0 | AP11: ='General information '!J10 -> 0 | AR11: =A11 -> 44963 | AS11: =AS10 -> 0.9 | AT11: 114 | AU11: =AU10 -> 1.1 | AV11: =AV10 -> 92 | AW11: 2.9 | AX11: 92 | AY11: =AS11*AT11 -> 102.6 | AZ11: =AU11*AV11 -> 101.2 | BA11: =AW11*AX11 -> 266.8 | BB11: =AY11-AY10 -> 0 | BC11: =AZ11-AZ10 -> 0 | BD11: =BA11-BA10 -> -2.9 | BE11: =SUM(BB11:BD11) -> -2.9 | BF11: =SUM(I11-BE11) -> 2.9 | BG11: =SUM(I11-BF11) -> -2.9
A12: =ELEC!C10 -> 44964 | B12: =B11 -> 109443 | C12: =B12-B11 -> 0 | D12: =C12/27 -> 0 | E12: =SUM((C12*$E$4)+(7500/'EDl log'!$A$37)) -> 267.85714 | G12: =G11 -> 632735 | H12: =G12-G11 -> 0 | I12: =C12+H12 -> 0 | J12: =IF(I12>0,E12/I12,0) -> 0 | K12: =K11 -> 7089 | L12: =K12-K11 -> 0 | M12: =M11 -> 457.44 | N12: =SUM(M12-M11) -> 0 | O12: =O11 -> 529.52 | P12: =SUM(O12-O11) -> 0 | Q12: =SUM(P12+N12) -> 0 | T12: =T11 -> 5202 | U12: =SUM(T12-T11) -> 0 | V12: =V11 -> 518 | W12: =+V12-V11 -> 0 | X12: =X11 -> 156588 | Y12: =SUM(X12-X11) -> 0 | Z12: =Z11 -> 99955 | AA12: =Z12-Z11 -> 0 | AB12: =AB11 -> 242 | AC12: =AC11 -> 855 | AD12: =AC12-AC11 -> 0 | AE12: =AE11 -> 262.47 | AF12: =AE12-AE11 -> 0 | AG12: =AG11 -> 2247.41 | AH12: =AG12-AG11 -> 0 | AI12: =AF12+AH12 -> 0 | AJ12: =+Z12-Z11 -> 0 | AK12: =SUM(Y12-L12) -> 0 | AL12: =SUM(AJ12-W12) -> 0 | AM12: ='General information '!D11 -> 11 | AN12: ='General information '!H11 -> 0 | AP12: ='General information '!J11 -> 0 | AR12: =A12 -> 44964 | AS12: =AS11 -> 0.9 | AT12: =AT11 -> 114 | AU12: =AU11 -> 1.1 | AV12: 90 | AW12: 2.9 | AX12: 90 | AY12: =AS12*AT12 -> 102.6 | AZ12: =AU12*AV12 -> 99 | BA12: =AW12*AX12 -> 261 | BB12: =AY12-AY11 -> 0 | BC12: =AZ12-AZ11 -> -2.2 | BD12: =BA12-BA11 -> -5.8 | BE12: =SUM(BB12:BD12) -> -8 | BF12: =SUM(I12-BE12) -> 8 | BG12: =SUM(I12-BF12) -> -8
A13: =ELEC!C11 -> 44965 | B13: 109443 | C13: =B13-B12 -> 0 | D13: =C13/27 -> 0 | E13: =SUM((C13*$E$4)+(7500/'EDl log'!$A$37)) -> 267.85714 | G13: 632742 | H13: =G13-G12 -> 7 | I13: =C13+H13 -> 7 | J13: =IF(I13>0,E13/I13,0) -> 38.265306 | K13: =K12 -> 7089 | L13: =K13-K12 -> 0 | M13: =M12 -> 457.44 | N13: =SUM(M13-M12) -> 0 | O13: =O12 -> 529.52 | P13: =SUM(O13-O12) -> 0 | Q13: =SUM(P13+N13) -> 0 | T13: =T12 -> 5202 | U13: =SUM(T13-T12) -> 0 | V13: =V12 -> 518 | W13: =+V13-V12 -> 0 | X13: 156588 | Y13: =SUM(X13-X12) -> 0 | Z13: =Z12 -> 99955 | AA13: =Z13-Z12 -> 0 | AB13: =AB12 -> 242 | AC13: =AC12 -> 855 | AD13: =AC13-AC12 -> 0 | AE13: =AE12 -> 262.47 | AF13: =AE13-AE12 -> 0 | AG13: =AG12 -> 2247.41 | AH13: =AG13-AG12 -> 0 | AI13: =AF13+AH13 -> 0 | AJ13: =+Z13-Z12 -> 0 | AK13: =SUM(Y13-L13) -> 0 | AL13: =SUM(AJ13-W13) -> 0 | AM13: ='General information '!D12 -> 11 | AN13: ='General information '!J12 -> 0 | AP13: ='General information '!J12 -> 0 | AR13: =A13 -> 44965 | AS13: =AS12 -> 0.9 | AT13: =AT12 -> 114 | AU13: =AU12 -> 1.1 | AV13: 88 | AW13: 2.9 | AX13: 88 | AY13: =AS13*AT13 -> 102.6 | AZ13: =AU13*AV13 -> 96.8 | BA13: =AW13*AX13 -> 255.2 | BB13: =AY13-AY12 -> 0 | BC13: =AZ13-AZ12 -> -2.2 | BD13: =BA13-BA12 -> -5.8 | BE13: =SUM(BB13:BD13) -> -8 | BF13: =SUM(I13-BE13) -> 15 | BG13: =SUM(I13-BF13) -> -8
A14: =ELEC!C12 -> 44966 | B14: =B13 -> 109443 | C14: =B14-B13 -> 0 | D14: =C14/27 -> 0 | E14: =SUM((C14*$E$4)+(7500/'EDl log'!$A$37)) -> 267.85714 | G14: =G13 -> 632742 | H14: =G14-G13 -> 0 | I14: =C14+H14 -> 0 | J14: =IF(I14>0,E14/I14,0) -> 0 | K14: =K13 -> 7089 | L14: =K14-K13 -> 0 | M14: =M13 -> 457.44 | N14: =SUM(M14-M13) -> 0 | O14: =O13 -> 529.52 | P14: =SUM(O14-O13) -> 0 | Q14: =SUM(P14+N14) -> 0 | T14: =T13 -> 5202 | U14: =SUM(T14-T13) -> 0 | V14: =V13 -> 518 | W14: =+V14-V13 -> 0 | X14: =X13 -> 156588 | Y14: =SUM(X14-X13) -> 0 | Z14: =Z13 -> 99955 | AA14: =Z14-Z13 -> 0 | AB14: =AB13 -> 242 | AC14: =AC13 -> 855 | AD14: =AC14-AC13 -> 0 | AE14: =AE13 -> 262.47 | AF14: =AE14-AE13 -> 0 | AG14: 2247.41 | AH14: =AG14-AG13 -> 0 | AI14: =AF14+AH14 -> 0 | AJ14: =+Z14-Z13 -> 0 | AK14: =SUM(Y14-L14) -> 0 | AL14: =SUM(AJ14-W14) -> 0 | AM14: ='General information '!D13 -> 0 | AN14: ='General information '!H13 -> 0 | AP14: ='General information '!J13 -> 0 | AR14: =A14 -> 44966 | AS14: =AS13 -> 0.9 | AT14: =AT13 -> 114 | AU14: =AU13 -> 1.1 | AV14: =AV13 -> 88 | AW14: 2.9 | AX14: =AX13 -> 88 | AY14: =AS14*AT14 -> 102.6 | AZ14: =AU14*AV14 -> 96.8 | BA14: =AW14*AX14 -> 255.2 | BB14: =AY14-AY13 -> 0 | BC14: =AZ14-AZ13 -> 0 | BD14: =BA14-BA13 -> 0 | BE14: =SUM(BB14:BD14) -> 0 | BF14: =SUM(I14-BE14) -> 0 | BG14: =SUM(I14-BF14) -> 0
A15: =ELEC!C13 -> 44967 | B15: =B14 -> 109443 | C15: =B15-B14 -> 0 | D15: =C15/27 -> 0 | E15: =SUM((C15*$E$4)+(7500/'EDl log'!$A$37)) -> 267.85714 | G15: =G14 -> 632742 | H15: =G15-G14 -> 0 | I15: =C15+H15 -> 0 | J15: =IF(I15>0,E15/I15,0) -> 0 | K15: =K14 -> 7089 | L15: =K15-K14 -> 0 | M15: =M14 -> 457.44 | N15: =SUM(M15-M14) -> 0 | O15: =O14 -> 529.52 | P15: =SUM(O15-O14) -> 0 | Q15: =SUM(P15+N15) -> 0 | T15: =T14 -> 5202 | U15: =SUM(T15-T14) -> 0 | V15: =V14 -> 518 | W15: =+V15-V14 -> 0 | X15: =X14 -> 156588 | Y15: =SUM(X15-X14) -> 0 | Z15: =Z14 -> 99955 | AA15: =Z15-Z14 -> 0 | AB15: =AB14 -> 242 | AC15: =AC14 -> 855 | AD15: =AC15-AC14 -> 0 | AE15: =AE14 -> 262.47 | AF15: =AE15-AE14 -> 0 | AG15: =AG14 -> 2247.41 | AH15: =AG15-AG14 -> 0 | AI15: =AF15+AH15 -> 0 | AJ15: =+Z15-Z14 -> 0 | AK15: =SUM(Y15-L15) -> 0 | AL15: =SUM(AJ15-W15) -> 0 | AM15: ='General information '!D14 -> 11 | AN15: ='General information '!H14 -> 0 | AP15: ='General information '!J14 -> 0 | AR15: =A15 -> 44967 | AS15: =AS14 -> 0.9 | AT15: =AT14 -> 114 | AU15: =AU14 -> 1.1 | AV15: =AV14 -> 88 | AW15: 2.9 | AX15: =AX14 -> 88 | AY15: =AS15*AT15 -> 102.6 | AZ15: =AU15*AV15 -> 96.8 | BA15: =AW15*AX15 -> 255.2 | BB15: =AY15-AY14 -> 0 | BC15: =AZ15-AZ14 -> 0 | BD15: =BA15-BA14 -> 0 | BE15: =SUM(BB15:BD15) -> 0 | BF15: =SUM(I15-BE15) -> 0 | BG15: =SUM(I15-BF15) -> 0
A16: =ELEC!C14 -> 44968 | B16: =B15 -> 109443 | C16: =B16-B15 -> 0 | D16: =C16/27 -> 0 | E16: =SUM((C16*$E$4)+(7500/'EDl log'!$A$37)) -> 267.85714 | G16: =G15 -> 632742 | H16: =G16-G15 -> 0 | I16: =C16+H16 -> 0 | J16: =IF(I16>0,E16/I16,0) -> 0 | K16: =K15 -> 7089 | L16: =K16-K15 -> 0 | M16: =M15 -> 457.44 | N16: =SUM(M16-M15) -> 0 | O16: =O15 -> 529.52 | P16: =SUM(O16-O15) -> 0 | Q16: =SUM(P16+N16) -> 0 | T16: =T15 -> 5202 | U16: =SUM(T16-T15) -> 0 | V16: =V15 -> 518 | W16: =+V16-V15 -> 0 | X16: =X15 -> 156588 | Y16: =SUM(X16-X15) -> 0 | Z16: =Z15 -> 99955 | AA16: =Z16-Z15 -> 0 | AB16: =AB15 -> 242 | AC16: =AC15 -> 855 | AD16: =AC16-AC15 -> 0 | AE16: =AE15 -> 262.47 | AF16: =AE16-AE15 -> 0 | AG16: =AG15 -> 2247.41 | AH16: =AG16-AG15 -> 0 | AI16: =AF16+AH16 -> 0 | AJ16: =+Z16-Z15 -> 0 | AK16: =SUM(Y16-L16) -> 0 | AL16: =SUM(AJ16-W16) -> 0 | AM16: ='General information '!D15 -> 0 | AN16: ='General information '!H15 -> 0 | AP16: ='General information '!J15 -> 0 | AR16: =A16 -> 44968 | AS16: =AS15 -> 0.9 | AT16: =AT15 -> 114 | AU16: =AU15 -> 1.1 | AV16: =AV15 -> 88 | AW16: 2.9 | AX16: =AX15 -> 88 | AY16: =AS16*AT16 -> 102.6 | AZ16: =AU16*AV16 -> 96.8 | BA16: =AW16*AX16 -> 255.2 | BB16: =AY16-AY15 -> 0 | BC16: =AZ16-AZ15 -> 0 | BD16: =BA16-BA15 -> 0 | BE16: =SUM(BB16:BD16) -> 0 | BF16: =SUM(I16-BE16) -> 0 | BG16: =SUM(I16-BF16) -> 0
A17: =ELEC!C15 -> 44969 | B17: =B16 -> 109443 | C17: =B17-B16 -> 0 | D17: =C17/27 -> 0 | E17: =SUM((C17*$E$4)+(7500/'EDl log'!$A$37)) -> 267.85714 | G17: 633110 | H17: =G17-G16 -> 368 | I17: =C17+H17 -> 368 | J17: =IF(I17>0,E17/I17,0) -> 0.72787267 | K17: =K16 -> 7089 | L17: =K17-K16 -> 0 | M17: =M16 -> 457.44 | N17: =SUM(M17-M16) -> 0 | O17: =O16 -> 529.52 | P17: =SUM(O17-O16) -> 0 | Q17: =SUM(P17+N17) -> 0 | T17: =T16 -> 5202 | U17: =SUM(T17-T16) -> 0 | V17: =V16 -> 518 | W17: =+V17-V16 -> 0 | X17: =X16 -> 156588 | Y17: =SUM(X17-X16) -> 0 | Z17: =Z16 -> 99955 | AA17: =Z17-Z16 -> 0 | AB17: =AB16 -> 242 | AC17: =AC16 -> 855 | AD17: =AC17-AC16 -> 0 | AE17: =AE16 -> 262.47 | AF17: =AE17-AE16 -> 0 | AG17: =AG16 -> 2247.41 | AH17: =AG17-AG16 -> 0 | AI17: =AF17+AH17 -> 0 | AJ17: =+Z17-Z16 -> 0 | AK17: =SUM(Y17-L17) -> 0 | AL17: =SUM(AJ17-W17) -> 0 | AM17: ='General information '!D16 -> 12 | AN17: ='General information '!H16 -> 0 | AP17: ='General information '!J16 -> 0 | AR17: =A17 -> 44969 | AS17: =AS16 -> 0.9 | AT17: 203 | AU17: =AU16 -> 1.1 | AV17: 83 | AW17: 2.9 | AX17: 122 | AY17: =AS17*AT17 -> 182.7 | AZ17: =AU17*AV17 -> 91.3 | BA17: =AW17*AX17 -> 353.8 | BB17: =AY17-AY16 -> 80.1 | BC17: =AZ17-AZ16 -> -5.5 | BD17: =BA17-BA16 -> 98.6 | BE17: =SUM(BB17:BD17) -> 173.2 | BF17: =SUM(I17-BE17) -> 194.8 | BG17: =SUM(I17-BF17) -> 173.2
A18: =ELEC!C16 -> 44970 | B18: =B17 -> 109443 | C18: =B18-B17 -> 0 | D18: =C18/27 -> 0 | E18: =SUM((C18*$E$4)+(7500/'EDl log'!$A$37)) -> 267.85714 | G18: =G17 -> 633110 | H18: =G18-G17 -> 0 | I18: =C18+H18 -> 0 | J18: =IF(I18>0,E18/I18,0) -> 0 | K18: =K17 -> 7089 | L18: =K18-K17 -> 0 | M18: =M17 -> 457.44 | N18: =SUM(M18-M17) -> 0 | O18: =O17 -> 529.52 | P18: =SUM(O18-O17) -> 0 | Q18: =SUM(P18+N18) -> 0 | T18: =T17 -> 5202 | U18: =SUM(T18-T17) -> 0 | V18: =V17 -> 518 | W18: =+V18-V17 -> 0 | X18: =X17 -> 156588 | Y18: =SUM(X18-X17) -> 0 | Z18: 99898 | AA18: =Z18-Z17 -> -57 | AB18: =AB17 -> 242 | AC18: =AC17 -> 855 | AD18: =AC18-AC17 -> 0 | AE18: =AE17 -> 262.47 | AF18: =AE18-AE17 -> 0 | AG18: =AG17 -> 2247.41 | AH18: =AG18-AG17 -> 0 | AI18: =AF18+AH18 -> 0 | AJ18: =+Z18-Z17 -> -57 | AK18: =SUM(Y18-L18) -> 0 | AL18: =SUM(AJ18-W18) -> -57 | AM18: ='General information '!D17 -> 13 | AN18: ='General information '!H17 -> 0 | AP18: ='General information '!J17 -> 0 | AR18: =A18 -> 44970 | AS18: =AS17 -> 0.9 | AT18: =AT17 -> 203 | AU18: =AU17 -> 1.1 | AV18: 80 | AW18: 2.9 | AX18: 118 | AY18: =AS18*AT18 -> 182.7 | AZ18: =AU18*AV18 -> 88 | BA18: =AW18*AX18 -> 342.2 | BB18: =AY18-AY17 -> 0 | BC18: =AZ18-AZ17 -> -3.3 | BD18: =BA18-BA17 -> -11.6 | BE18: =SUM(BB18:BD18) -> -14.9 | BF18: =SUM(I18-BE18) -> 14.9 | BG18: =SUM(I18-BF18) -> -14.9
A19: =ELEC!C17 -> 44971 | B19: =B18 -> 109443 | C19: =B19-B18 -> 0 | D19: =C19/27 -> 0 | E19: =SUM((C19*$E$4)+(7500/'EDl log'!$A$37)) -> 267.85714 | G19: =G18 -> 633110 | H19: =G19-G18 -> 0 | I19: =C19+H19 -> 0 | J19: =IF(I19>0,E19/I19,0) -> 0 | K19: =K18 -> 7089 | L19: =K19-K18 -> 0 | M19: =M18 -> 457.44 | N19: =SUM(M19-M18) -> 0 | O19: =O18 -> 529.52 | P19: =SUM(O19-O18) -> 0 | Q19: =SUM(P19+N19) -> 0 | T19: =T18 -> 5202 | U19: =SUM(T19-T18) -> 0 | V19: =V18 -> 518 | W19: =+V19-V18 -> 0 | X19: =X18 -> 156588 | Y19: =SUM(X19-X18) -> 0 | Z19: =Z18 -> 99898 | AA19: =Z19-Z18 -> 0 | AB19: =AB18 -> 242 | AC19: =AC18 -> 855 | AD19: =AC19-AC18 -> 0 | AE19: =AE18 -> 262.47 | AF19: =AE19-AE18 -> 0 | AG19: =AG18 -> 2247.41 | AH19: =AG19-AG18 -> 0 | AI19: =AF19+AH19 -> 0 | AJ19: =+Z19-Z18 -> 0 | AK19: =SUM(Y19-L19) -> 0 | AL19: =SUM(AJ19-W19) -> 0 | AM19: ='General information '!D18 -> 12.5 | AN19: ='General information '!H18 -> 0 | AP19: ='General information '!J18 -> 0 | AR19: =A19 -> 44971 | AS19: =AS18 -> 0.9 | AT19: =AT18 -> 203 | AU19: =AU18 -> 1.1 | AV19: 78 | AW19: 2.9 | AX19: 115 | AY19: =AS19*AT19 -> 182.7 | AZ19: =AU19*AV19 -> 85.8 | BA19: =AW19*AX19 -> 333.5 | BB19: =AY19-AY18 -> 0 | BC19: =AZ19-AZ18 -> -2.2 | BD19: =BA19-BA18 -> -8.7 | BE19: =SUM(BB19:BD19) -> -10.9 | BF19: =SUM(I19-BE19) -> 10.9 | BG19: =SUM(I19-BF19) -> -10.9
A20: =ELEC!C18 -> 44972 | B20: =B19 -> 109443 | C20: =B20-B19 -> 0 | D20: =C20/27 -> 0 | E20: =SUM((C20*$E$4)+(7500/'EDl log'!$A$37)) -> 267.85714 | G20: =G19 -> 633110 | H20: =G20-G19 -> 0 | I20: =C20+H20 -> 0 | J20: =IF(I20>0,E20/I20,0) -> 0 | K20: =K19 -> 7089 | L20: =K20-K19 -> 0 | M20: =M19 -> 457.44 | N20: =SUM(M20-M19) -> 0 | O20: =O19 -> 529.52 | P20: =SUM(O20-O19) -> 0 | Q20: =SUM(P20+N20) -> 0 | T20: =T19 -> 5202 | U20: =SUM(T20-T19) -> 0 | V20: =V19 -> 518 | W20: =+V20-V19 -> 0 | X20: =X19 -> 156588 | Y20: =SUM(X20-X19) -> 0 | Z20: =Z19 -> 99898 | AA20: =Z20-Z19 -> 0 | AB20: =AB19 -> 242 | AC20: =AC19 -> 855 | AD20: =AC20-AC19 -> 0 | AE20: =AE19 -> 262.47 | AF20: =AE20-AE19 -> 0 | AG20: =AG19 -> 2247.41 | AH20: =AG20-AG19 -> 0 | AI20: =AF20+AH20 -> 0 | AJ20: =+Z20-Z19 -> 0 | AK20: =SUM(Y20-L20) -> 0 | AL20: =SUM(AJ20-W20) -> 0 | AM20: ='General information '!D19 -> 12.5 | AN20: ='General information '!H19 -> 0 | AP20: ='General information '!J19 -> 0 | AR20: =A20 -> 44972 | AS20: =AS19 -> 0.9 | AT20: 206 | AU20: =AU19 -> 1.1 | AV20: 77 | AW20: 2.9 | AX20: 168 | AY20: =AS20*AT20 -> 185.4 | AZ20: =AU20*AV20 -> 84.7 | BA20: =AW20*AX20 -> 487.2 | BB20: =AY20-AY19 -> 2.7 | BC20: =AZ20-AZ19 -> -1.1 | BD20: =BA20-BA19 -> 153.7 | BE20: =SUM(BB20:BD20) -> 155.3 | BF20: =SUM(I20-BE20) -> -155.3 | BG20: =SUM(I20-BF20) -> 155.3
A21: =ELEC!C19 -> 44973 | B21: =B20 -> 109443 | C21: =B21-B20 -> 0 | D21: =C21/27 -> 0 | E21: =SUM((C21*$E$4)+(7500/'EDl log'!$A$37)) -> 267.85714 | G21: =G20 -> 633110 | H21: =G21-G20 -> 0 | I21: =C21+H21 -> 0 | J21: =IF(I21>0,E21/I21,0) -> 0 | K21: =K20 -> 7089 | L21: =K21-K20 -> 0 | M21: =M20 -> 457.44 | N21: =SUM(M21-M20) -> 0 | O21: =O20 -> 529.52 | P21: =SUM(O21-O20) -> 0 | Q21: =SUM(P21+N21) -> 0 | T21: =T20 -> 5202 | U21: =SUM(T21-T20) -> 0 | V21: =V20 -> 518 | W21: =+V21-V20 -> 0 | X21: =X20 -> 156588 | Y21: =SUM(X21-X20) -> 0 | Z21: =Z20 -> 99898 | AA21: =Z21-Z20 -> 0 | AB21: =AB20 -> 242 | AC21: =AC20 -> 855 | AD21: =AC21-AC20 -> 0 | AE21: =AE20 -> 262.47 | AF21: =AE21-AE20 -> 0 | AG21: =AG20 -> 2247.41 | AH21: =AG21-AG20 -> 0 | AI21: =AF21+AH21 -> 0 | AJ21: =+Z21-Z20 -> 0 | AK21: =SUM(Y21-L21) -> 0 | AL21: =SUM(AJ21-W21) -> 0 | AM21: ='General information '!D20 -> 12.5 | AN21: ='General information '!H20 -> 0 | AP21: ='General information '!J20 -> 0 | AR21: =A21 -> 44973 | AS21: =AS20 -> 0.9 | AT21: =AT20 -> 206 | AU21: =AU20 -> 1.1 | AV21: 74 | AW21: 2.9 | AX21: 168 | AY21: =AS21*AT21 -> 185.4 | AZ21: =AU21*AV21 -> 81.4 | BA21: =AW21*AX21 -> 487.2 | BB21: =AY21-AY20 -> 0 | BC21: =AZ21-AZ20 -> -3.3 | BD21: =BA21-BA20 -> 0 | BE21: =SUM(BB21:BD21) -> -3.3 | BF21: =SUM(I21-BE21) -> 3.3 | BG21: =SUM(I21-BF21) -> -3.3
A22: =ELEC!C20 -> 44974 | B22: 109443 | C22: =B22-B21 -> 0 | D22: =C22/27 -> 0 | E22: =SUM((C22*$E$4)+(7500/'EDl log'!$A$37)) -> 267.85714 | G22: =G21 -> 633110 | H22: =G22-G21 -> 0 | I22: =C22+H22 -> 0 | J22: =IF(I22>0,E22/I22,0) -> 0 | K22: =K21 -> 7089 | L22: =K22-K21 -> 0 | M22: =M21 -> 457.44 | N22: =SUM(M22-M21) -> 0 | O22: =O21 -> 529.52 | P22: =SUM(O22-O21) -> 0 | Q22: =SUM(P22+N22) -> 0 | T22: =T21 -> 5202 | U22: =SUM(T22-T21) -> 0 | V22: =V21 -> 518 | W22: =+V22-V21 -> 0 | X22: =X21 -> 156588 | Y22: =SUM(X22-X21) -> 0 | Z22: =Z21 -> 99898 | AA22: =Z22-Z21 -> 0 | AB22: =AB21 -> 242 | AC22: =AC21 -> 855 | AD22: =AC22-AC21 -> 0 | AE22: =AE21 -> 262.47 | AF22: =AE22-AE21 -> 0 | AG22: =AG21 -> 2247.41 | AH22: =AG22-AG21 -> 0 | AI22: =AF22+AH22 -> 0 | AJ22: =+Z22-Z21 -> 0 | AK22: =SUM(Y22-L22) -> 0 | AL22: =SUM(AJ22-W22) -> 0 | AM22: ='General information '!D21 -> 0 | AN22: ='General information '!H21 -> 0 | AP22: ='General information '!J21 -> 0 | AR22: =A22 -> 44974 | AS22: =AS21 -> 0.9 | AT22: =AT21 -> 206 | AU22: =AU21 -> 1.1 | AV22: =AV21 -> 74 | AW22: 2.9 | AX22: =AX21 -> 168 | AY22: =AS22*AT22 -> 185.4 | AZ22: =AU22*AV22 -> 81.4 | BA22: =AW22*AX22 -> 487.2 | BB22: =AY22-AY21 -> 0 | BC22: =AZ22-AZ21 -> 0 | BD22: =BA22-BA21 -> 0 | BE22: =SUM(BB22:BD22) -> 0 | BF22: =SUM(I22-BE22) -> 0 | BG22: =SUM(I22-BF22) -> 0
A23: =ELEC!C21 -> 44975 | B23: =B22 -> 109443 | C23: =B23-B22 -> 0 | D23: =C23/27 -> 0 | E23: =SUM((C23*$E$4)+(7500/'EDl log'!$A$37)) -> 267.85714 | G23: =G22 -> 633110 | H23: =G23-G22 -> 0 | I23: =C23+H23 -> 0 | J23: =IF(I23>0,E23/I23,0) -> 0 | K23: =K22 -> 7089 | L23: =K23-K22 -> 0 | M23: =M22 -> 457.44 | N23: =SUM(M23-M22) -> 0 | O23: =O22 -> 529.52 | P23: =SUM(O23-O22) -> 0 | Q23: =SUM(P23+N23) -> 0 | T23: =T22 -> 5202 | U23: =SUM(T23-T22) -> 0 | V23: =V22 -> 518 | W23: =+V23-V22 -> 0 | X23: =X22 -> 156588 | Y23: =SUM(X23-X22) -> 0 | Z23: =Z22 -> 99898 | AA23: =Z23-Z22 -> 0 | AB23: =AB22 -> 242 | AC23: =AC22 -> 855 | AD23: =AC23-AC22 -> 0 | AE23: =AE22 -> 262.47 | AF23: =AE23-AE22 -> 0 | AG23: =AG22 -> 2247.41 | AH23: =AG23-AG22 -> 0 | AI23: =AF23+AH23 -> 0 | AJ23: =+Z23-Z22 -> 0 | AK23: =SUM(Y23-L23) -> 0 | AL23: =SUM(AJ23-W23) -> 0 | AM23: ='General information '!D22 -> 0 | AN23: ='General information '!H22 -> 0 | AP23: ='General information '!J22 -> 0 | AR23: =A23 -> 44975 | AS23: =AS22 -> 0.9 | AT23: =AT22 -> 206 | AU23: =AU22 -> 1.1 | AV23: =AV22 -> 74 | AW23: 2.9 | AX23: =AX22 -> 168 | AY23: =AS23*AT23 -> 185.4 | AZ23: =AU23*AV23 -> 81.4 | BA23: =AW23*AX23 -> 487.2 | BB23: =AY23-AY22 -> 0 | BC23: =AZ23-AZ22 -> 0 | BD23: =BA23-BA22 -> 0 | BE23: =SUM(BB23:BD23) -> 0 | BF23: =SUM(I23-BE23) -> 0 | BG23: =SUM(I23-BF23) -> 0
A24: =ELEC!C22 -> 44976 | B24: =B23 -> 109443 | C24: =B24-B23 -> 0 | D24: =C24/27 -> 0 | E24: =SUM((C24*$E$4)+(7500/'EDl log'!$A$37)) -> 267.85714 | G24: =G23 -> 633110 | H24: =G24-G23 -> 0 | I24: =C24+H24 -> 0 | J24: =IF(I24>0,E24/I24,0) -> 0 | K24: =K23 -> 7089 | L24: =K24-K23 -> 0 | M24: =M23 -> 457.44 | N24: =SUM(M24-M23) -> 0 | O24: =O23 -> 529.52 | P24: =SUM(O24-O23) -> 0 | Q24: =SUM(P24+N24) -> 0 | T24: =T23 -> 5202 | U24: =SUM(T24-T23) -> 0 | V24: =V23 -> 518 | W24: =+V24-V23 -> 0 | X24: =X23 -> 156588 | Y24: =SUM(X24-X23) -> 0 | Z24: =Z23 -> 99898 | AA24: =Z24-Z23 -> 0 | AB24: =AB23 -> 242 | AC24: =AC23 -> 855 | AD24: =AC24-AC23 -> 0 | AE24: =AE23 -> 262.47 | AF24: =AE24-AE23 -> 0 | AG24: =AG23 -> 2247.41 | AH24: =AG24-AG23 -> 0 | AI24: =AF24+AH24 -> 0 | AJ24: =+Z24-Z23 -> 0 | AK24: =SUM(Y24-L24) -> 0 | AL24: =SUM(AJ24-W24) -> 0 | AM24: ='General information '!D23 -> 15.5 | AN24: ='[3]General information '!H24 -> 0 | AP24: ='[3]General information '!J24 -> 0 | AR24: =A24 -> 44976 | AS24: =AS23 -> 0.9 | AT24: 208 | AU24: =AU23 -> 1.1 | AV24: 74 | AW24: 2.9 | AX24: 170 | AY24: =AS24*AT24 -> 187.2 | AZ24: =AU24*AV24 -> 81.4 | BA24: =AW24*AX24 -> 493 | BB24: =AY24-AY23 -> 1.8 | BC24: =AZ24-AZ23 -> 0 | BD24: =BA24-BA23 -> 5.8 | BE24: =SUM(BB24:BD24) -> 7.6 | BF24: =SUM(I24-BE24) -> -7.6 | BG24: =SUM(I24-BF24) -> 7.6
A25: =ELEC!C23 -> 44977 | B25: =B24 -> 109443 | C25: =B25-B24 -> 0 | D25: =C25/27 -> 0 | E25: =SUM((C25*$E$4)+(7500/'EDl log'!$A$37)) -> 267.85714 | G25: =G24 -> 633110 | H25: =G25-G24 -> 0 | I25: =C25+H25 -> 0 | J25: =IF(I25>0,E25/I25,0) -> 0 | K25: =K24 -> 7089 | L25: =K25-K24 -> 0 | M25: =M24 -> 457.44 | N25: =SUM(M25-M24) -> 0 | O25: =O24 -> 529.52 | P25: =SUM(O25-O24) -> 0 | Q25: =SUM(P25+N25) -> 0 | T25: =T24 -> 5202 | U25: =SUM(T25-T24) -> 0 | V25: =V24 -> 518 | W25: =+V25-V24 -> 0 | X25: =X24 -> 156588 | Y25: =SUM(X25-X24) -> 0 | Z25: =Z24 -> 99898 | AA25: =Z25-Z24 -> 0 | AB25: =AB24 -> 242 | AC25: =AC24 -> 855 | AD25: =AC25-AC24 -> 0 | AE25: =AE24 -> 262.47 | AF25: =AE25-AE24 -> 0 | AG25: =AG24 -> 2247.41 | AH25: =AG25-AG24 -> 0 | AI25: =AF25+AH25 -> 0 | AJ25: =+Z25-Z24 -> 0 | AK25: =SUM(Y25-L25) -> 0 | AL25: =SUM(AJ25-W25) -> 0 | AM25: ='General information '!D24 -> 15 | AN25: ='General information '!H24 -> 0 | AP25: ='General information '!J24 -> 0 | AR25: =A25 -> 44977 | AS25: =AS24 -> 0.9 | AT25: 178 | AU25: =AU24 -> 1.1 | AV25: 70 | AW25: 2.9 | AX25: 115 | AY25: =AS25*AT25 -> 160.2 | AZ25: =AU25*AV25 -> 77 | BA25: =AW25*AX25 -> 333.5 | BB25: =AY25-AY24 -> -27 | BC25: =AZ25-AZ24 -> -4.4 | BD25: =BA25-BA24 -> -159.5 | BE25: =SUM(BB25:BD25) -> -190.9 | BF25: =SUM(I25-BE25) -> 190.9 | BG25: =SUM(I25-BF25) -> -190.9
A26: =ELEC!C24 -> 44978 | B26: =B25 -> 109443 | C26: =B26-B25 -> 0 | D26: =C26/27 -> 0 | E26: =SUM((C26*$E$4)+(7500/'EDl log'!$A$37)) -> 267.85714 | G26: =G25 -> 633110 | H26: =G26-G25 -> 0 | I26: =C26+H26 -> 0 | J26: =IF(I26>0,E26/I26,0) -> 0 | K26: =K25 -> 7089 | L26: =K26-K25 -> 0 | M26: =M25 -> 457.44 | N26: =SUM(M26-M25) -> 0 | O26: =O25 -> 529.52 | P26: =SUM(O26-O25) -> 0 | Q26: =SUM(P26+N26) -> 0 | T26: =T25 -> 5202 | U26: =SUM(T26-T25) -> 0 | V26: =V25 -> 518 | W26: =+V26-V25 -> 0 | X26: =X25 -> 156588 | Y26: =SUM(X26-X25) -> 0 | Z26: =Z25 -> 99898 | AA26: =Z26-Z25 -> 0 | AB26: =AB25 -> 242 | AC26: =AC25 -> 855 | AD26: =AC26-AC25 -> 0 | AE26: =AE25 -> 262.47 | AF26: =AE26-AE25 -> 0 | AG26: =AG25 -> 2247.41 | AH26: =AG26-AG25 -> 0 | AI26: =AF26+AH26 -> 0 | AJ26: =+Z26-Z25 -> 0 | AK26: =SUM(Y26-L26) -> 0 | AL26: =SUM(AJ26-W26) -> 0 | AM26: ='General information '!D25 -> 15 | AN26: ='General information '!H25 -> 0 | AP26: ='General information '!J25 -> 0 | AR26: =A26 -> 44978 | AS26: =AS25 -> 0.9 | AT26: 178 | AU26: =AU25 -> 1.1 | AV26: 67 | AW26: 2.9 | AX26: 113 | AY26: =AS26*AT26 -> 160.2 | AZ26: =AU26*AV26 -> 73.7 | BA26: =AW26*AX26 -> 327.7 | BB26: =AY26-AY25 -> 0 | BC26: =AZ26-AZ25 -> -3.3 | BD26: =BA26-BA25 -> -5.8 | BE26: =SUM(BB26:BD26) -> -9.1 | BF26: =SUM(I26-BE26) -> 9.1 | BG26: =SUM(I26-BF26) -> -9.1
A27: =ELEC!C25 -> 44979 | B27: =B26 -> 109443 | C27: =B27-B26 -> 0 | D27: =C27/27 -> 0 | E27: =SUM((C27*$E$4)+(7500/'EDl log'!$A$37)) -> 267.85714 | G27: =G26 -> 633110 | H27: =G27-G26 -> 0 | I27: =C27+H27 -> 0 | J27: =IF(I27>0,E27/I27,0) -> 0 | K27: =K26 -> 7089 | L27: =K27-K26 -> 0 | M27: =M26 -> 457.44 | N27: =SUM(M27-M26) -> 0 | O27: =O26 -> 529.52 | P27: =SUM(O27-O26) -> 0 | Q27: =SUM(P27+N27) -> 0 | T27: =T26 -> 5202 | U27: =SUM(T27-T26) -> 0 | V27: =V26 -> 518 | W27: =+V27-V26 -> 0 | X27: =X26 -> 156588 | Y27: =SUM(X27-X26) -> 0 | Z27: =Z26 -> 99898 | AA27: =Z27-Z26 -> 0 | AB27: =AB26 -> 242 | AC27: =AC26 -> 855 | AD27: =AC27-AC26 -> 0 | AE27: 262.47 | AF27: =AE27-AE26 -> 0 | AG27: =AG26 -> 2247.41 | AH27: =AG27-AG26 -> 0 | AI27: =AF27+AH27 -> 0 | AJ27: =+Z27-Z26 -> 0 | AK27: =SUM(Y27-L27) -> 0 | AL27: =SUM(AJ27-W27) -> 0 | AM27: ='General information '!D26 -> 14.5 | AN27: ='General information '!H26 -> 0 | AP27: ='General information '!J26 -> 0 | AR27: =A27 -> 44979 | AS27: =AS26 -> 0.9 | AT27: =AT26 -> 178 | AU27: =AU26 -> 1.1 | AV27: 65 | AW27: 2.9 | AX27: 111 | AY27: =AS27*AT27 -> 160.2 | AZ27: =AU27*AV27 -> 71.5 | BA27: =AW27*AX27 -> 321.9 | BB27: =AY27-AY26 -> 0 | BC27: =AZ27-AZ26 -> -2.2 | BD27: =BA27-BA26 -> -5.8 | BE27: =SUM(BB27:BD27) -> -8 | BF27: =SUM(I27-BE27) -> 8 | BG27: =SUM(I27-BF27) -> -8
A28: =ELEC!C26 -> 44980 | B28: =B27 -> 109443 | C28: =B28-B27 -> 0 | D28: =C28/27 -> 0 | E28: =SUM((C28*$E$4)+(7500/'EDl log'!$A$37)) -> 267.85714 | G28: =G27 -> 633110 | H28: =G28-G27 -> 0 | I28: =C28+H28 -> 0 | J28: =IF(I28>0,E28/I28,0) -> 0 | K28: =K27 -> 7089 | L28: =K28-K27 -> 0 | M28: =M27 -> 457.44 | N28: =SUM(M28-M27) -> 0 | O28: =O27 -> 529.52 | P28: =SUM(O28-O27) -> 0 | Q28: =SUM(P28+N28) -> 0 | T28: =T27 -> 5202 | U28: =SUM(T28-T27) -> 0 | V28: =V27 -> 518 | W28: =+V28-V27 -> 0 | X28: =X27 -> 156588 | Y28: =SUM(X28-X27) -> 0 | Z28: =Z27 -> 99898 | AA28: =Z28-Z27 -> 0 | AB28: =AB27 -> 242 | AC28: =AC27 -> 855 | AD28: =AC28-AC27 -> 0 | AE28: =AE27 -> 262.47 | AF28: =AE28-AE27 -> 0 | AG28: =AG27 -> 2247.41 | AH28: =AG28-AG27 -> 0 | AI28: =AF28+AH28 -> 0 | AJ28: =+Z28-Z27 -> 0 | AK28: =SUM(Y28-L28) -> 0 | AL28: =SUM(AJ28-W28) -> 0 | AM28: ='General information '!D27 -> 14.5 | AN28: ='General information '!H27 -> 0 | AP28: ='General information '!J27 -> 0 | AR28: =A28 -> 44980 | AS28: =AS27 -> 0.9 | AT28: 164 | AU28: =AU27 -> 1.1 | AV28: 60 | AW28: 2.9 | AX28: 110 | AY28: =AS28*AT28 -> 147.6 | AZ28: =AU28*AV28 -> 66 | BA28: =AW28*AX28 -> 319 | BB28: =AY28-AY27 -> -12.6 | BC28: =AZ28-AZ27 -> -5.5 | BD28: =BA28-BA27 -> -2.9 | BE28: =SUM(BB28:BD28) -> -21 | BF28: =SUM(I28-BE28) -> 21 | BG28: =SUM(I28-BF28) -> -21
A29: =ELEC!C27 -> 44981 | B29: =B28 -> 109443 | C29: =B29-B28 -> 0 | D29: =C29/27 -> 0 | E29: =SUM((C29*$E$4)+(7500/'EDl log'!$A$37)) -> 267.85714 | G29: =G28 -> 633110 | H29: =G29-G28 -> 0 | I29: =C29+H29 -> 0 | J29: =IF(I29>0,E29/I29,0) -> 0 | K29: =K28 -> 7089 | L29: =K29-K28 -> 0 | M29: =M28 -> 457.44 | N29: =SUM(M29-M28) -> 0 | O29: =O28 -> 529.52 | P29: =SUM(O29-O28) -> 0 | Q29: =SUM(P29+N29) -> 0 | T29: =T28 -> 5202 | U29: =SUM(T29-T28) -> 0 | V29: =V28 -> 518 | W29: =+V29-V28 -> 0 | X29: =X28 -> 156588 | Y29: =SUM(X29-X28) -> 0 | Z29: =Z28 -> 99898 | AA29: =Z29-Z28 -> 0 | AB29: =AB28 -> 242 | AC29: =AC28 -> 855 | AD29: =AC29-AC28 -> 0 | AE29: =AE28 -> 262.47 | AF29: =AE29-AE28 -> 0 | AG29: =AG28 -> 2247.41 | AH29: =AG29-AG28 -> 0 | AI29: =AF29+AH29 -> 0 | AJ29: =+Z29-Z28 -> 0 | AK29: =SUM(Y29-L29) -> 0 | AL29: =SUM(AJ29-W29) -> 0 | AM29: ='General information '!D28 -> 14.5 | AN29: ='General information '!H28 -> 0 | AP29: ='General information '!J28 -> 0 | AR29: =A29 -> 44981 | AS29: =AS28 -> 0.9 | AT29: =AT28 -> 164 | AU29: =AU28 -> 1.1 | AV29: =AV28 -> 60 | AW29: 2.9 | AX29: =AX28 -> 110 | AY29: =AS29*AT29 -> 147.6 | AZ29: =AU29*AV29 -> 66 | BA29: =AW29*AX29 -> 319 | BB29: =AY29-AY28 -> 0 | BC29: =AZ29-AZ28 -> 0 | BD29: =BA29-BA28 -> 0 | BE29: =SUM(BB29:BD29) -> 0 | BF29: =SUM(I29-BE29) -> 0 | BG29: =SUM(I29-BF29) -> 0
A30: =ELEC!C28 -> 44982 | B30: =B29 -> 109443 | C30: =B30-B29 -> 0 | D30: =C30/27 -> 0 | E30: =SUM((C30*$E$4)+(7500/'EDl log'!$A$37)) -> 267.85714 | G30: =G29 -> 633110 | H30: =G30-G29 -> 0 | I30: =C30+H30 -> 0 | J30: =IF(I30>0,E30/I30,0) -> 0 | K30: =K29 -> 7089 | L30: =K30-K29 -> 0 | M30: =M29 -> 457.44 | N30: =SUM(M30-M29) -> 0 | O30: =O29 -> 529.52 | P30: =SUM(O30-O29) -> 0 | Q30: =SUM(P30+N30) -> 0 | T30: =T29 -> 5202 | U30: =SUM(T30-T29) -> 0 | V30: =V29 -> 518 | W30: =+V30-V29 -> 0 | X30: =X29 -> 156588 | Y30: =SUM(X30-X29) -> 0 | Z30: =Z29 -> 99898 | AA30: =Z30-Z29 -> 0 | AB30: =AB29 -> 242 | AC30: =AC29 -> 855 | AD30: =AC30-AC29 -> 0 | AE30: =AE29 -> 262.47 | AF30: =AE30-AE29 -> 0 | AG30: =AG29 -> 2247.41 | AH30: =AG30-AG29 -> 0 | AI30: =AF30+AH30 -> 0 | AJ30: =+Z30-Z29 -> 0 | AK30: =SUM(Y30-L30) -> 0 | AL30: =SUM(AJ30-W30) -> 0 | AM30: ='General information '!D29 -> 17 | AN30: ='General information '!H29 -> 0 | AP30: ='General information '!J29 -> 0 | AR30: =A30 -> 44982 | AS30: =AS29 -> 0.9 | AT30: =AT29 -> 164 | AU30: =AU29 -> 1.1 | AV30: =AV29 -> 60 | AW30: 2.9 | AX30: =AX29 -> 110 | AY30: =AS30*AT30 -> 147.6 | AZ30: =AU30*AV30 -> 66 | BA30: =AW30*AX30 -> 319 | BB30: =AY30-AY29 -> 0 | BC30: =AZ30-AZ29 -> 0 | BD30: =BA30-BA29 -> 0 | BE30: =SUM(BB30:BD30) -> 0 | BF30: =SUM(I30-BE30) -> 0 | BG30: =SUM(I30-BF30) -> 0
A31: =ELEC!C29 -> 44983 | B31: =B30 -> 109443 | C31: =B31-B30 -> 0 | D31: =C31/27 -> 0 | E31: =SUM((C31*$E$4)+(7500/'EDl log'!$A$37)) -> 267.85714 | G31: 633115 | H31: =G31-G30 -> 5 | I31: =C31+H31 -> 5 | J31: =IF(I31>0,E31/I31,0) -> 53.571429 | K31: =K30 -> 7089 | L31: =K31-K30 -> 0 | M31: =M30 -> 457.44 | N31: =SUM(M31-M30) -> 0 | O31: =O30 -> 529.52 | P31: =SUM(O31-O30) -> 0 | Q31: =SUM(P31+N31) -> 0 | T31: =T30 -> 5202 | U31: =SUM(T31-T30) -> 0 | V31: =V30 -> 518 | W31: =+V31-V30 -> 0 | X31: =X30 -> 156588 | Y31: =SUM(X31-X30) -> 0 | Z31: =Z30 -> 99898 | AA31: =Z31-Z30 -> 0 | AB31: =AB30 -> 242 | AC31: =AC30 -> 855 | AD31: =AC31-AC30 -> 0 | AE31: =AE30 -> 262.47 | AF31: =AE31-AE30 -> 0 | AG31: =AG30 -> 2247.41 | AH31: =AG31-AG30 -> 0 | AI31: =AF31+AH31 -> 0 | AJ31: =+Z31-Z30 -> 0 | AK31: =SUM(Y31-L31) -> 0 | AL31: =SUM(AJ31-W31) -> 0 | AM31: ='General information '!D30 -> 18.5 | AN31: ='General information '!H30 -> 0 | AP31: ='General information '!J30 -> 0 | AR31: =A31 -> 44983 | AS31: =AS30 -> 0.9 | AT31: 170 | AU31: =AU30 -> 1.1 | AV31: 59 | AW31: 2.9 | AX31: 108 | AY31: =AS31*AT31 -> 153 | AZ31: =AU31*AV31 -> 64.9 | BA31: =AW31*AX31 -> 313.2 | BB31: =AY31-AY30 -> 5.4 | BC31: =AZ31-AZ30 -> -1.1 | BD31: =BA31-BA30 -> -5.8 | BE31: =SUM(BB31:BD31) -> -1.5 | BF31: =SUM(I31-BE31) -> 6.5 | BG31: =SUM(I31-BF31) -> -1.5
A32: =ELEC!C30 -> 44984 | B32: =B31 -> 109443 | C32: =B32-B31 -> 0 | D32: =C32/27 -> 0 | E32: =SUM((C32*$E$4)+(7500/'EDl log'!$A$37)) -> 267.85714 | G32: =G31 -> 633115 | H32: =G32-G31 -> 0 | I32: =C32+H32 -> 0 | J32: =IF(I32>0,E32/I32,0) -> 0 | K32: =K31 -> 7089 | L32: =K32-K31 -> 0 | M32: =M31 -> 457.44 | N32: =SUM(M32-M31) -> 0 | O32: =O31 -> 529.52 | P32: =SUM(O32-O31) -> 0 | Q32: =SUM(P32+N32) -> 0 | T32: =T31 -> 5202 | U32: =SUM(T32-T31) -> 0 | V32: =V31 -> 518 | W32: =+V32-V31 -> 0 | X32: =X31 -> 156588 | Y32: =SUM(X32-X31) -> 0 | Z32: =Z31 -> 99898 | AA32: =Z32-Z31 -> 0 | AB32: =AB31 -> 242 | AC32: =AC31 -> 855 | AD32: =AC32-AC31 -> 0 | AE32: =AE31 -> 262.47 | AF32: =AE32-AE31 -> 0 | AG32: =AG31 -> 2247.41 | AH32: =AG32-AG31 -> 0 | AI32: =AF32+AH32 -> 0 | AJ32: =+Z32-Z31 -> 0 | AK32: =SUM(Y32-L32) -> 0 | AL32: =SUM(AJ32-W32) -> 0 | AM32: ='General information '!D31 -> 20.5 | AN32: ='General information '!H31 -> 0 | AP32: ='General information '!J31 -> 0 | AR32: =A32 -> 44984 | AS32: =AS31 -> 0.9 | AT32: 120 | AU32: =AU31 -> 1.1 | AV32: 123 | AW32: 2.9 | AX32: 108 | AY32: =AS32*AT32 -> 108 | AZ32: =AU32*AV32 -> 135.3 | BA32: =AW32*AX32 -> 313.2 | BB32: =AY32-AY31 -> -45 | BC32: =AZ32-AZ31 -> 70.4 | BD32: =BA32-BA31 -> 0 | BE32: =SUM(BB32:BD32) -> 25.4 | BF32: =SUM(I32-BE32) -> -25.4 | BG32: =SUM(I32-BF32) -> 25.4
A33: =ELEC!C31 -> 44985 | B33: =B32 -> 109443 | C33: =B33-B32 -> 0 | D33: =C33/27 -> 0 | E33: =SUM((C33*$E$4)+(7500/'EDl log'!$A$37)) -> 267.85714 | G33: =G32 -> 633115 | H33: =G33-G32 -> 0 | I33: =C33+H33 -> 0 | J33: =IF(I33>0,E33/I33,0) -> 0 | K33: =K32 -> 7089 | L33: =K33-K32 -> 0 | M33: =M32 -> 457.44 | N33: =SUM(M33-M32) -> 0 | O33: =O32 -> 529.52 | P33: =SUM(O33-O32) -> 0 | Q33: =SUM(P33+N33) -> 0 | T33: =T32 -> 5202 | U33: =SUM(T33-T32) -> 0 | V33: =V32 -> 518 | W33: =+V33-V32 -> 0 | X33: =X32 -> 156588 | Y33: =SUM(X33-X32) -> 0 | Z33: =Z32 -> 99898 | AA33: =Z33-Z32 -> 0 | AB33: =AB32 -> 242 | AC33: =AC32 -> 855 | AD33: =AC33-AC32 -> 0 | AE33: =AE32 -> 262.47 | AF33: =AE33-AE32 -> 0 | AG33: =AG32 -> 2247.41 | AH33: =AG33-AG32 -> 0 | AI33: =AF33+AH33 -> 0 | AJ33: =+Z33-Z32 -> 0 | AK33: =SUM(Y33-L33) -> 0 | AL33: =SUM(AJ33-W33) -> 0 | AM33: ='General information '!D32 -> 0 | AN33: ='General information '!H32 -> 0 | AP33: ='General information '!J32 -> 0 | AR33: =A33 -> 44985 | AS33: =AS32 -> 0.9 | AT33: =AT32 -> 120 | AU33: =AU32 -> 1.1 | AV33: =AV32 -> 123 | AW33: 2.9 | AX33: =AX32 -> 108 | AY33: =AS33*AT33 -> 108 | AZ33: =AU33*AV33 -> 135.3 | BA33: =AW33*AX33 -> 313.2 | BB33: =AY33-AY32 -> 0 | BC33: =AZ33-AZ32 -> 0 | BD33: =BA33-BA32 -> 0 | BE33: =SUM(BB33:BD33) -> 0 | BF33: =SUM(I33-BE33) -> 0 | BG33: =SUM(I33-BF33) -> 0
A34: =ELEC!C32 -> 44986 | B34: =B33 -> 109443 | C34: =B34-B33 -> 0 | D34: =C34/27 -> 0 | E34: =SUM((C34*$E$4)+(7500/'EDl log'!$A$37)) -> 267.85714 | G34: =G33 -> 633115 | H34: =G34-G33 -> 0 | I34: =C34+H34 -> 0 | J34: =IF(I34>0,E34/I34,0) -> 0 | K34: =K33 -> 7089 | L34: =K34-K33 -> 0 | M34: =M33 -> 457.44 | N34: =SUM(M34-M33) -> 0 | O34: =O33 -> 529.52 | P34: =SUM(O34-O33) -> 0 | Q34: =SUM(P34+N34) -> 0 | T34: =T33 -> 5202 | U34: =SUM(T34-T33) -> 0 | V34: =V33 -> 518 | W34: =+V34-V33 -> 0 | X34: =X33 -> 156588 | Y34: =SUM(X34-X33) -> 0 | Z34: =Z33 -> 99898 | AA34: =Z34-Z33 -> 0 | AB34: =AB33 -> 242 | AC34: =AC33 -> 855 | AD34: =AC34-AC33 -> 0 | AE34: =AE33 -> 262.47 | AF34: =AE34-AE33 -> 0 | AG34: =AG33 -> 2247.41 | AH34: =AG34-AG33 -> 0 | AI34: =AF34+AH34 -> 0 | AJ34: =+Z34-Z33 -> 0 | AK34: =SUM(Y34-L34) -> 0 | AL34: =SUM(AJ34-W34) -> 0 | AM34: ='General information '!D33 -> 0 | AN34: ='General information '!H33 -> 0 | AP34: ='General information '!J33 -> 0 | AR34: =A34 -> 44986 | AS34: =AS33 -> 0.9 | AT34: =AT33 -> 120 | AU34: =AU33 -> 1.1 | AV34: =AV33 -> 123 | AW34: 2.9 | AX34: =AX33 -> 108 | AY34: =AS34*AT34 -> 108 | AZ34: =AU34*AV34 -> 135.3 | BA34: =AW34*AX34 -> 313.2 | BB34: =AY34-AY33 -> 0 | BC34: =AZ34-AZ33 -> 0 | BD34: =BA34-BA33 -> 0 | BE34: =SUM(BB34:BD34) -> 0 | BF34: =SUM(I34-BE34) -> 0 | BG34: =SUM(I34-BF34) -> 0
C37: =SUM(C6:C36) -> 0 | D37: =SUM(D6:D36) -> 0 | F37: =SUM(F6:F36) -> 0 | H37: =SUM(H6:H36) -> 380 | I37: =SUM(I6:I36) -> 380 | L37: =SUM(L7:L36) -> 0 | Q37: =SUM(Q6:Q36) -> 0 | U37: =SUM(U6:U36) -> 0 | Y37: =SUM(Y6,Y33,Y31,Y29,Y27,Y25,Y23,Y21,Y19,Y17,Y15,Y13,Y11,Y9,Y7,Y34,Y35,Y36) -> 0 | AJ37: =SUM(AJ6:AJ36) -> -57 | AK37: =SUM(Y37-L37) -> 0 | AL37: =SUM(AL6:AL36) -> -57
C38: =+C37*1.66 -> 0 | E38: =SUM(E6:E33) -> 7500 | F38: =SUM(F6:F35) -> 0 | H38: 7500 | I38: =SUM('General information '!G36/WATER!I37) -> 0 | O38: =SUM(Q37+I37) -> 380 | Z38: =SUM(Y37:AJ37) -> -57 | AK38: =SUM(Y38-L38) -> 0
B39: =9*31 -> 279 | D39: =SUM(D6:D35) -> 0 | F39: =SUM(F6:F36) -> 0 | G39: =SUM(I37) -> 380 | H39: =SUM(H38+C38) -> 7500 | K39: =SUM(H39/G39) -> 19.736842 | AJ39: =SUM(C38-AK38) -> 0 | AM39: =SUM(AJ39/AO38) -> #DIV/0!

Sheet General information 
A1: GENERAL & HOTEL'S INFORMATION SHEET
B4: Max Temp | C4: MIN TEMP | D4: AVE TEMP | E4: AVE Humidity | F4: AVE OCC | G4: # of OCC Rooms | H4: Ball room | I4: Meeting rooms | J4: Outlets | K4: Total covers | L4: # of permenant Emp | M4: # of casuals | N4: Total # of EMP | O4: # of EMP/OCC Room
A5: 44958 | B5: 16 | C5: 10 | D5: =(C5+B5)/2 -> 13 | E5: 0.55 | F5: 0 | G5: =F5*230 -> 0 | H5: 0 | I5: 0 | J5: 0 | K5: =+J5+H5 -> 0
A6: =A5+1 -> 44959 | B6: 16 | C6: 11 | D6: =(C6+B6)/2 -> 13.5 | E6: 0.53 | F6: 0 | G6: =F6*230 -> 0 | H6: 0 | I6: 0 | J6: 0 | K6: =+J6+H6 -> 0
A7: =ELEC!C6 -> 44960 | D7: =(C7+B7)/2 -> 0 | F7: 0 | G7: =F7*230 -> 0 | H7: 0 | I7: 0 | J7: 0 | K7: =+J7+H7 -> 0
A8: =ELEC!C7 -> 44961 | D8: =(C8+B8)/2 -> 0 | F8: 0 | G8: =F8*230 -> 0 | H8: 0 | I8: 0 | J8: 0 | K8: =+J8+H8 -> 0
A9: =ELEC!C8 -> 44962 | B9: 14 | C9: 9 | D9: =(C9+B9)/2 -> 11.5 | E9: 0.63 | F9: 0 | G9: =F9*230 -> 0 | H9: 0 | I9: 0 | J9: 0 | K9: =+J9+H9 -> 0
A10: =ELEC!C9 -> 44963 | B10: 14 | C10: 8 | D10: =(C10+B10)/2 -> 11 | E10: 0.56 | F10: 0 | G10: =F10*230 -> 0 | H10: 0 | I10: 0 | J10: 0 | K10: =+J10+H10 -> 0
A11: =ELEC!C10 -> 44964 | B11: 14 | C11: 8 | D11: =(C11+B11)/2 -> 11 | E11: 0.56 | F11: 0 | G11: =F11*230 -> 0 | H11: 0 | I11: 0 | J11: 0 | K11: =+J11+H11 -> 0
A12: =ELEC!C11 -> 44965 | B12: 14 | C12: 8 | D12: =(C12+B12)/2 -> 11 | E12: 0.56 | F12: 0 | G12: =F12*230 -> 0 | H12: 0 | I12: 0 | J12: 0 | K12: =+J12+H12 -> 0
A13: =ELEC!C12 -> 44966 | D13: =(C13+B13)/2 -> 0 | F13: 0 | G13: =F13*230 -> 0 | H13: 0 | I13: 0 | J13: 0 | K13: =+J13+H13 -> 0
A14: =ELEC!C13 -> 44967 | B14: 14 | C14: 8 | D14: =(C14+B14)/2 -> 11 | E14: 0.51 | F14: 0 | G14: =F14*230 -> 0 | H14: 0 | I14: 0 | J14: 0 | K14: =+J14+H14 -> 0
A15: =ELEC!C14 -> 44968 | D15: =(C15+B15)/2 -> 0 | F15: 0 | G15: =F15*230 -> 0 | H15: 0 | I15: 0 | J15: 0 | K15: =+J15+H15 -> 0
A16: =ELEC!C15 -> 44969 | B16: 16 | C16: 8 | D16: =(C16+B16)/2 -> 12 | E16: 0.43 | F16: 0 | G16: =F16*230 -> 0 | H16: 0 | I16: 0 | J16: 0 | K16: =+J16+H16 -> 0
A17: =ELEC!C16 -> 44970 | B17: 17 | C17: 9 | D17: =(C17+B17)/2 -> 13 | E17: 0.37 | F17: 0 | G17: =F17*230 -> 0 | H17: 0 | I17: 0 | J17: 0 | K17: =+J17+H17 -> 0
A18: =ELEC!C17 -> 44971 | B18: 16 | C18: 9 | D18: =(C18+B18)/2 -> 12.5 | E18: 0.4 | F18: 0 | G18: =F18*230 -> 0 | H18: 0 | I18: 0 | J18: 0 | K18: =+J18+H18 -> 0
A19: =ELEC!C18 -> 44972 | B19: 16 | C19: 9 | D19: =(C19+B19)/2 -> 12.5 | E19: 0.39 | F19: 0 | G19: =F19*230 -> 0 | H19: 0 | I19: 0 | J19: 0 | K19: =+J19+H19 -> 0
A20: =ELEC!C19 -> 44973 | B20: 16 | C20: 9 | D20: =(C20+B20)/2 -> 12.5 | E20: 0.41 | F20: 0 | G20: =F20*230 -> 0 | H20: 0 | I20: 0 | J20: 0 | K20: =+J20+H20 -> 0
A21: =ELEC!C20 -> 44974 | D21: =(C21+B21)/2 -> 0 | F21: 0 | G21: =F21*230 -> 0 | H21: 0 | I21: 0 | J21: 0 | K21: =+J21+H21 -> 0
A22: =ELEC!C21 -> 44975 | D22: =(C22+B22)/2 -> 0 | F22: 0 | G22: =F22*230 -> 0 | H22: 0 | I22: 0 | J22: 0 | K22: =+J22+H22 -> 0
A23: =ELEC!C22 -> 44976 | B23: 19 | C23: 12 | D23: =(C23+B23)/2 -> 15.5 | E23: 0.45 | F23: 0 | G23: =F23*230 -> 0 | H23: 0 | I23: 0 | J23: 0 | K23: =+J23+H23 -> 0
A24: =ELEC!C23 -> 44977 | B24: 18 | C24: 12 | D24: =(C24+B24)/2 -> 15 | E24: 0.56 | F24: 0 | G24: =F24*230 -> 0 | H24: 0 | I24: 0 | J24: 0 | K24: =+J24+H24 -> 0
A25: =ELEC!C24 -> 44978 | B25: 18 | C25: 12 | D25: =(C25+B25)/2 -> 15 | E25: 0.55 | F25: 0 | G25: =F25*230 -> 0 | H25: 0 | I25: 0 | J25: 0 | K25: =+J25+H25 -> 0
A26: =ELEC!C25 -> 44979 | B26: 17 | C26: 12 | D26: =(C26+B26)/2 -> 14.5 | E26: 0.66 | F26: 0 | G26: =F26*230 -> 0 | H26: 0 | I26: 0 | J26: 0 | K26: =+J26+H26+I26 -> 0
A27: =ELEC!C26 -> 44980 | B27: 17 | C27: 12 | D27: =(C27+B27)/2 -> 14.5 | E27: 0.66 | F27: 0 | G27: =F27*230 -> 0 | H27: 0 | I27: 0 | J27: 0 | K27: =+J27+H27+I27 -> 0
A28: =ELEC!C27 -> 44981 | B28: 17 | C28: 12 | D28: =(C28+B28)/2 -> 14.5 | E28: 0.66 | F28: 0 | G28: =F28*230 -> 0 | H28: 0 | I28: 0 | J28: 0 | K28: =+J28+H28+I28 -> 0
A29: =ELEC!C28 -> 44982 | B29: 22 | C29: 12 | D29: =(C29+B29)/2 -> 17 | E29: 0.66 | F29: 0 | G29: =F29*230 -> 0 | H29: 0 | I29: 0 | J29: 0 | K29: =+J29+H29+I29 -> 0
A30: =ELEC!C29 -> 44983 | B30: 23 | C30: 14 | D30: =(C30+B30)/2 -> 18.5 | E30: 0.66 | F30: 0 | G30: =F30*230 -> 0 | H30: 0 | I30: 0 | J30: 0 | K30: =+J30+H30+I30 -> 0
A31: =ELEC!C30 -> 44984 | B31: 24 | C31: 17 | D31: =(C31+B31)/2 -> 20.5 | E31: 0.44 | F31: 0 | G31: =F31*230 -> 0 | H31: 0 | I31: 0 | J31: 0 | K31: =+J31+H31+I31 -> 0
A32: =ELEC!C31 -> 44985 | D32: =(C32+B32)/2 -> 0 | F32: 0 | G32: =F32*230 -> 0 | H32: 0 | I32: 0 | J32: 0 | K32: =+J32+H32+I32 -> 0
A33: =ELEC!C32 -> 44986 | D33: =(C33+B33)/2 -> 0 | F33: 0 | G33: =F33*230 -> 0 | H33: 0 | I33: 0 | J33: 0 | K33: =+J33+H33+I33 -> 0
F36: =AVERAGE(F5:F35) -> 0 | G36: =SUM(G5:G35) -> 0
D37: =SUM(D5:D35)/'EDl log'!A35 -> 32.166667
I40: http://www.accuweather.com/en/lb/lebanon-weather

Sheet GEN
B1: GEN1 | C1: RUN HR | D1: Fuel Counter Index | E1: Cons /day | F1: Diesel L/H | H1: next service | I1: ALARM | J1: GEN2 | K1: RUN HR | L1: Fuel Counter Index | M1: Cons /day | N1: Diesel L/H | P1: next service | Q1: ALARM | R1: GEN3 | S1: RUN HR | T1: Fuel Counter Index | U1: Cons /day | V1: Diesel L/H | X1: next service | Y1: ALARM | Z1: RH total | AA1: Gen Con /day | AB1: Total Deisel Cons/day | AC1: H /L | AD1: TOAL KW GEN | AI1: fuel Consuption | AK1: AVG KW/h
A2: 44957 | B2: 1973 | C2: =[2]GEN!C33 -> 17 | D2: =[2]GEN!D33 -> 826846 | E2: =[2]GEN!E33 -> 1445 | F2: =[2]GEN!F33 -> 85 | G2: =[2]GEN!G33 -> 0 | H2: =[2]GEN!H33 -> 12231 | I2: =[2]GEN!I33 -> ok | J2: =[2]GEN!J33 -> 148 | ... AL2: =[2]GEN!AL33 -> 1
A3: =ELEC!C4 -> 44958 | B3: 1985 | C3: =B3-B2 -> 12 | D3: =D2+C3*250 -> 829846 | E3: =SUM(D3-D2) -> 3000 | F3: =IF(C3>0,E3/C3,0) -> 250 | G3: =[4]GEN!G32 -> #VALUE! | H3: =H2 -> 12231 | I3: =IF(B3-H3<=0,"ok","oil change") -> ok | J3: =J2 -> 148 | K3: =J3-J2 -> 0 | L3: =L2 -> 392441 | M3: =SUM(L3-L2) -> 0 | N3: 250 | O3: =[4]GEN!O32 -> #VALUE! | P3: =P2 -> 10873 | Q3: =IF(J3-P3<=0,"ok","oil change") -> ok | R3: =R2 -> 13920 | S3: =R3-R2 -> 0 | T3: =T2+U3 -> 419262 | U3: =V3*S3 -> 0 | V3: 250 | W3: =[4]GEN!W32 -> #VALUE! | X3: =X2 -> 14773 | Y3: =IF(R3-X3<=0,"ok","oil change") -> ok | Z3: =C3+K3+S3 -> 12 | AA3: =U3+M3+E3 -> 3000 | AB3: =V3+N3+F3 -> 750 | AC3: =IF(Z3>0,AA3/Z3,0) -> 250 | AD3: =ELEC!Q4 -> 3522 | AE3: =SUM(AD3/Z3) -> 293.5 | AF3: =SUM(AE3/1600) -> 0.1834375 | AG3: =SUM(360*AF3) -> 66.0375 | AH3: =SUM(AC3-AG3) -> 183.9625 | AI3: =AD3*AJ3 -> 906.50633 | AJ3: =305/1185 -> 0.25738397 | AK3: =AI3/Z3 -> 75.542194 | AL3: =IF(Z3=0,0,1) -> 1
A4: =ELEC!C5 -> 44959 | B4: 1995 | C4: =B4-B3 -> 10 | D4: =D3+C4*85 -> 830696 | E4: =SUM(D4-D3) -> 850 | F4: =IF(C4>0,E4/C4,0) -> 85 | H4: =H3 -> 12231 | I4: =IF(B4-H4<=0,"ok","oil change") -> ok | J4: =J3 -> 148 | K4: =J4-J3 -> 0 | L4: =L3 -> 392441 | M4: =SUM(L4-L3) -> 0 | N4: 250 | P4: =P3 -> 10873 | Q4: =IF(J4-P4<=0,"ok","oil change") -> ok | R4: =R3 -> 13920 | S4: =R4-R3 -> 0 | T4: =T3+U4 -> 419262 | U4: =V4*S4 -> 0 | V4: 250 | X4: =X3 -> 14773 | Y4: =IF(R4-X4<=0,"ok","oil change") -> ok | Z4: =C4+K4+S4 -> 10 | AA4: =U4+M4+E4 -> 850 | AB4: =V4+N4+F4 -> 585 | AC4: =IF(Z4>0,AA4/Z4,0) -> 85 | AD4: =ELEC!Q5 -> 2849 | AE4: =SUM(AD4/Z4) -> 284.9 | AF4: =SUM(AE4/1600) -> 0.1780625 | AG4: =SUM(360*AF4) -> 64.1025 | AH4: =SUM(AC4-AG4) -> 20.8975 | AI4: =AD4*AJ4 -> 733.28692 | AJ4: =305/1185 -> 0.25738397 | AK4: =AI4/Z4 -> 73.328692 | AL4: =IF(Z4=0,0,1) -> 1
A5: =ELEC!C6 -> 44960 | B5: 1995 | C5: =B5-B4 -> 0 | D5: =D4+C5*85 -> 830696 | E5: =SUM(D5-D4) -> 0 | F5: =IF(C5>0,E5/C5,0) -> 0 | H5: =H4 -> 12231 | I5: =IF(B5-H5<=0,"ok","oil change") -> ok | J5: =J4 -> 148 | K5: =J5-J4 -> 0 | L5: =L4 -> 392441 | M5: =SUM(L5-L4) -> 0 | N5: 250 | P5: =P4 -> 10873 | Q5: =IF(J5-P5<=0,"ok","oil change") -> ok | R5: =R4 -> 13920 | S5: =R5-R4 -> 0 | T5: =T4+U5 -> 419262 | U5: =V5*S5 -> 0 | V5: 250 | X5: =X4 -> 14773 | Y5: =IF(R5-X5<=0,"ok","oil change") -> ok | Z5: =C5+K5+S5 -> 0 | AA5: =U5+M5+E5 -> 0 | AB5: =V5+N5+F5 -> 500 | AC5: =IF(Z5>0,AA5/Z5,0) -> 0 | AD5: =ELEC!Q6 -> 0 | AE5: =SUM(AD5/Z5) -> #DIV/0! | AF5: =SUM(AE5/1600) -> #DIV/0! | AG5: =SUM(320*AF5) -> #DIV/0! | AH5: =SUM(AC5-AG5) -> #DIV/0! | AI5: =AD5*AJ5 -> 0 | AJ5: =305/1185 -> 0.25738397 | AK5: =AI5/Z5 -> #DIV/0! | AL5: =IF(Z5=0,0,1) -> 0
A6: =ELEC!C7 -> 44961 | B6: =B5 -> 1995 | C6: =B6-B5 -> 0 | D6: =D5+C6*85 -> 830696 | E6: =SUM(D6-D5) -> 0 | F6: =IF(C6>0,E6/C6,0) -> 0 | H6: =H5 -> 12231 | I6: =IF(B6-H6<=0,"ok","oil change") -> ok | J6: =J5 -> 148 | K6: =J6-J5 -> 0 | L6: =(K6*N5)+L5 -> 392441 | M6: =SUM(L6-L5) -> 0 | N6: 250 | P6: =P5 -> 10873 | Q6: =IF(J6-P6<=0,"ok","oil change") -> ok | R6: =R5 -> 13920 | S6: =R6-R5 -> 0 | T6: =T5+U6 -> 419262 | U6: =V6*S6 -> 0 | V6: 250 | X6: =X5 -> 14773 | Y6: =IF(R6-X6<=0,"ok","oil change") -> ok | Z6: =C6+K6+S6 -> 0 | AA6: =U6+M6+E6 -> 0 | AB6: =V6+N6+F6 -> 500 | AC6: =IF(Z6>0,AA6/Z6,0) -> 0 | AD6: =ELEC!Q7 -> 0 | AE6: =SUM(AD6/Z6) -> #DIV/0! | AF6: =SUM(AE6/1600) -> #DIV/0! | AG6: =SUM(320*AF6) -> #DIV/0! | AH6: =SUM(AC6-AG6) -> #DIV/0! | AI6: =AD6*AJ6 -> 0 | AJ6: =305/1185 -> 0.25738397 | AK6: =AI6/Z6 -> #DIV/0! | AL6: =IF(Z6=0,0,1) -> 0
A7: =ELEC!C8 -> 44962 | B7: 2007 | C7: =B7-B6 -> 12 | D7: =D6+C7*85 -> 831716 | E7: =SUM(D7-D6) -> 1020 | F7: =IF(C7>0,E7/C7,0) -> 85 | H7: =H6 -> 12231 | I7: =IF(B7-H7<=0,"ok","oil change") -> ok | J7: =J6 -> 148 | L7: =(K7*N6)+L6 -> 392441 | M7: =SUM(L7-L6) -> 0 | N7: 250 | P7: =P6 -> 10873 | Q7: =IF(J7-P7<=0,"ok","oil change") -> ok | R7: =R6 -> 13920 | S7: =R7-R6 -> 0 | T7: =T6+U7 -> 419262 | U7: =V7*S7 -> 0 | V7: 250 | X7: =X6 -> 14773 | Y7: =IF(R7-X7<=0,"ok","oil change") -> ok | Z7: =C7+K7+S7 -> 12 | AA7: =U7+M7+E7 -> 1020 | AB7: =V7+N7+F7 -> 585 | AC7: =IF(Z7>0,AA7/Z7,0) -> 85 | AD7: =ELEC!Q8 -> 2803 | AE7: =SUM(AD7/Z7) -> 233.58333 | AF7: =SUM(AE7/1600) -> 0.14598958 | AG7: =SUM(AF7/1600) -> 9.124349e-05 | AH7: =SUM(AC7-AG7) -> 84.999909 | AI7: =AD7*AJ7 -> 721.44726 | AJ7: =305/1185 -> 0.25738397 | AK7: =AI7/Z7 -> 60.120605 | AL7: =IF(Z7=0,0,1) -> 1
A8: =ELEC!C9 -> 44963 | B8: 2020 | C8: =B8-B7 -> 13 | D8: =D7+C8*85 -> 832821 | E8: =SUM(D8-D7) -> 1105 | F8: =IF(C8>0,E8/C8,0) -> 85 | H8: =H7 -> 12231 | I8: =IF(B8-H8<=0,"ok","oil change") -> ok | J8: =J7 -> 148 | K8: =J8-J7 -> 0 | L8: =(K8*N7)+L7 -> 392441 | M8: =SUM(L8-L7) -> 0 | N8: 250 | P8: =P7 -> 10873 | Q8: =IF(J8-P8<=0,"ok","oil change") -> ok | R8: =R7 -> 13920 | S8: =R8-R7 -> 0 | T8: =T7+U8 -> 419262 | U8: =V8*S8 -> 0 | V8: 250 | X8: =X7 -> 14773 | Y8: =IF(R8-X8<=0,"ok","oil change") -> ok | Z8: =C8+K8+S8 -> 13 | AA8: =U8+M8+E8 -> 1105 | AB8: =V8+N8+F8 -> 585 | AC8: =IF(Z8>0,AA8/Z8,0) -> 85 | AD8: =ELEC!Q9 -> 3344 | AE8: =SUM(AD8/Z8) -> 257.23077 | AF8: =SUM(AE8/1600) -> 0.16076923 | AG8: =SUM(AF8/1600) -> 0.00010048077 | AH8: =SUM(AC8-AG8) -> 84.9999 | AI8: =AD8*AJ8 -> 860.69198 | AJ8: =305/1185 -> 0.25738397 | AK8: =AI8/Z8 -> 66.207076 | AL8: =IF(Z8=0,0,1) -> 1
A9: =ELEC!C10 -> 44964 | B9: 2034 | C9: =B9-B8 -> 14 | D9: =D8+C9*85 -> 834011 | E9: =SUM(D9-D8) -> 1190 | F9: =IF(C9>0,E9/C9,0) -> 85 | H9: =H8 -> 12231 | I9: =IF(B9-H9<=0,"ok","oil change") -> ok | J9: =J8 -> 148 | K9: =J9-J8 -> 0 | L9: =(K9*N8)+L8 -> 392441 | M9: =SUM(L9-L8) -> 0 | N9: 250 | P9: =P8 -> 10873 | Q9: =IF(J9-P9<=0,"ok","oil change") -> ok | R9: =R8 -> 13920 | S9: =R9-R8 -> 0 | T9: =T8+U9 -> 419262 | U9: =V9*S9 -> 0 | V9: 250 | X9: =X8 -> 14773 | Y9: =IF(R9-X9<=0,"ok","oil change") -> ok | Z9: =C9+K9+S9 -> 14 | AA9: =U9+M9+E9 -> 1190 | AB9: =V9+N9+F9 -> 585 | AC9: =IF(Z9>0,AA9/Z9,0) -> 85 | AD9: =ELEC!Q10 -> 3792 | AE9: =SUM(AD9/Z9) -> 270.85714 | AF9: =SUM(AE9/1600) -> 0.16928571 | AG9: =SUM(AF9/1600) -> 0.00010580357 | AH9: =SUM(AC9-AG9) -> 84.999894 | AI9: =AD9*AJ9 -> 976 | AJ9: =305/1185 -> 0.25738397 | AK9: =AI9/Z9 -> 69.714286 | AL9: =IF(Z9=0,0,1) -> 1
A10: =ELEC!C11 -> 44965 | B10: 2044 | C10: =B10-B9 -> 10 | D10: =D9+C10*85 -> 834861 | E10: =SUM(D10-D9) -> 850 | F10: =IF(C10>0,E10/C10,0) -> 85 | H10: =H9 -> 12231 | I10: =IF(B10-H10<=0,"ok","oil change") -> ok | J10: =J9 -> 148 | K10: =J10-J9 -> 0 | L10: =(K10*N9)+L9 -> 392441 | M10: =SUM(L10-L9) -> 0 | N10: 250 | P10: =P9 -> 10873 | Q10: =IF(J10-P10<=0,"ok","oil change") -> ok | R10: =R9 -> 13920 | S10: =R10-R9 -> 0 | T10: =T9+U10 -> 419262 | U10: =V10*S10 -> 0 | V10: 250 | X10: =X9 -> 14773 | Y10: =IF(R10-X10<=0,"ok","oil change") -> ok | Z10: =C10+K10+S10 -> 10 | AA10: =U10+M10+E10 -> 850 | AB10: =V10+N10+F10 -> 585 | AC10: =IF(Z10>0,AA10/Z10,0) -> 85 | AD10: =ELEC!Q11 -> 3498 | AE10: =SUM(AD10/Z10) -> 349.8 | AF10: =SUM(AE10/1600) -> 0.218625 | AG10: =SUM(AF10/1600) -> 0.00013664062 | AH10: =SUM(AC10-AG10) -> 84.999863 | AI10: =AD10*AJ10 -> 900.32911 | AJ10: =305/1185 -> 0.25738397 | AK10: =AI10/Z10 -> 90.032911 | AL10: =IF(Z10=0,0,1) -> 1
A11: =ELEC!C12 -> 44966 | B11: =B10 -> 2044 | C11: =B11-B10 -> 0 | D11: =D10+C11*85 -> 834861 | E11: =SUM(D11-D10) -> 0 | F11: =IF(C11>0,E11/C11,0) -> 0 | H11: =H10 -> 12231 | I11: =IF(B11-H11<=0,"ok","oil change") -> ok | J11: =J10 -> 148 | K11: =J11-J10 -> 0 | L11: =(K11*N10)+L10 -> 392441 | M11: =SUM(L11-L10) -> 0 | N11: 250 | P11: =P10 -> 10873 | Q11: =IF(J11-P11<=0,"ok","oil change") -> ok | R11: =R10 -> 13920 | S11: =R11-R10 -> 0 | T11: =T10+U11 -> 419262 | U11: =V11*S11 -> 0 | V11: 250 | X11: =X10 -> 14773 | Y11: =IF(R11-X11<=0,"ok","oil change") -> ok | Z11: =C11+K11+S11 -> 0 | AA11: =U11+M11+E11 -> 0 | AB11: =V11+N11+F11 -> 500 | AC11: =IF(Z11>0,AA11/Z11,0) -> 0 | AD11: =ELEC!Q12 -> 0 | AE11: =SUM(AD11/Z11) -> #DIV/0! | AF11: =SUM(AE11/1600) -> #DIV/0! | AG11: =SUM(AF11/1600) -> #DIV/0! | AH11: =SUM(AC11-AG11) -> #DIV/0! | AI11: =AD11*AJ11 -> 0 | AJ11: =305/1185 -> 0.25738397 | AK11: =AI11/Z11 -> #DIV/0! | AL11: =IF(Z11=0,0,1) -> 0
A12: =ELEC!C13 -> 44967 | B12: =B11 -> 2044 | C12: =B12-B11 -> 0 | D12: =D11+C12*85 -> 834861 | E12: =SUM(D12-D11) -> 0 | F12: =IF(C12>0,E12/C12,0) -> 0 | H12: =H11 -> 12231 | I12: =IF(B12-H12<=0,"ok","oil change") -> ok | J12: =J11 -> 148 | K12: =J12-J11 -> 0 | L12: =(K12*N11)+L11 -> 392441 | M12: =SUM(L12-L11) -> 0 | N12: 250 | P12: =P11 -> 10873 | Q12: =IF(J12-P12<=0,"ok","oil change") -> ok | R12: =R11 -> 13920 | S12: =R12-R11 -> 0 | T12: =T11+U12 -> 419262 | U12: =V12*S12 -> 0 | V12: 250 | X12: =X11 -> 14773 | Y12: =IF(R12-X12<=0,"ok","oil change") -> ok | Z12: =C12+K12+S12 -> 0 | AA12: =U12+M12+E12 -> 0 | AB12: =V12+N12+F12 -> 500 | AC12: =IF(Z12>0,AA12/Z12,0) -> 0 | AD12: =ELEC!Q13 -> 0 | AE12: =SUM(AD12/Z12) -> #DIV/0! | AF12: =SUM(AE12/1600) -> #DIV/0! | AG12: =SUM(AF12/1600) -> #DIV/0! | AH12: =SUM(AC12-AG12) -> #DIV/0! | AI12: =AD12*AJ12 -> 0 | AJ12: =305/1185 -> 0.25738397 | AK12: =AI12/Z12 -> #DIV/0! | AL12: =IF(Z12=0,0,1) -> 0
A13: =ELEC!C14 -> 44968 | B13: =B12 -> 2044 | C13: =B13-B12 -> 0 | D13: =D12+C13*85 -> 834861 | E13: =SUM(D13-D12) -> 0 | F13: =IF(C13>0,E13/C13,0) -> 0 | H13: =H12 -> 12231 | I13: =IF(B13-H13<=0,"ok","oil change") -> ok | J13: =J12 -> 148 | K13: =J13-J12 -> 0 | L13: =(K13*N12)+L12 -> 392441 | M13: =SUM(L13-L12) -> 0 | N13: 250 | P13: =P12 -> 10873 | Q13: =IF(J13-P13<=0,"ok","oil change") -> ok | R13: =R12 -> 13920 | S13: =R13-R12 -> 0 | T13: =T12+U13 -> 419262 | U13: =V13*S13 -> 0 | V13: 250 | X13: =X12 -> 14773 | Y13: =IF(R13-X13<=0,"ok","oil change") -> ok | Z13: =C13+K13+S13 -> 0 | AA13: =U13+M13+E13 -> 0 | AB13: =V13+N13+F13 -> 500 | AC13: =IF(Z13>0,AA13/Z13,0) -> 0 | AD13: =ELEC!Q14 -> 0 | AE13: =SUM(AD13/Z13) -> #DIV/0! | AF13: =SUM(AE13/1600) -> #DIV/0! | AG13: =SUM(AF13/1600) -> #DIV/0! | AH13: =SUM(AC13-AG13) -> #DIV/0! | AI13: =AD13*AJ13 -> 0 | AJ13: =305/1185 -> 0.25738397 | AK13: =AI13/Z13 -> #DIV/0! | AL13: =IF(Z13=0,0,1) -> 0
A14: =ELEC!C15 -> 44969 | B14: 2052 | C14: =B14-B13 -> 8 | D14: =D13+C14*85 -> 835541 | E14: =SUM(D14-D13) -> 680 | F14: =IF(C14>0,E14/C14,0) -> 85 | H14: =H13 -> 12231 | I14: =IF(B14-H14<=0,"ok","oil change") -> ok | J14: =J13 -> 148 | K14: =J14-J13 -> 0 | L14: =(K14*N13)+L13 -> 392441 | M14: =SUM(L14-L13) -> 0 | N14: 250 | P14: =P13 -> 10873 | Q14: =IF(J14-P14<=0,"ok","oil change") -> ok | R14: =R13 -> 13920 | S14: =R14-R13 -> 0 | T14: =T13+U14 -> 419262 | U14: =V14*S14 -> 0 | V14: 250 | X14: =X13 -> 14773 | Y14: =IF(R14-X14<=0,"ok","oil change") -> ok | Z14: =C14+K14+S14 -> 8 | AA14: =U14+M14+E14 -> 680 | AB14: =V14+N14+F14 -> 585 | AC14: =IF(Z14>0,AA14/Z14,0) -> 85 | AD14: =ELEC!Q15 -> 2252 | AE14: =SUM(AD14/Z14) -> 281.5 | AF14: =SUM(AE14/1600) -> 0.1759375 | AG14: =SUM(AF14/1600) -> 0.00010996094 | AH14: =SUM(AC14-AG14) -> 84.99989 | AI14: =AD14*AJ14 -> 579.62869 | AJ14: =305/1185 -> 0.25738397 | AK14: =AI14/Z14 -> 72.453586 | AL14: =IF(Z14=0,0,1) -> 1
A15: =ELEC!C16 -> 44970 | B15: 2063 | C15: =B15-B14 -> 11 | D15: =D14+C15*85 -> 836476 | E15: =SUM(D15-D14) -> 935 | F15: =IF(C15>0,E15/C15,0) -> 85 | H15: =H14 -> 12231 | I15: =IF(B15-H15<=0,"ok","oil change") -> ok | J15: 149 | K15: =J15-J14 -> 1 | L15: =(K15*N14)+L14 -> 392691 | M15: =SUM(L15-L14) -> 250 | N15: 250 | P15: =P14 -> 10873 | Q15: =IF(J15-P15<=0,"ok","oil change") -> ok | R15: =R14 -> 13920 | S15: =R15-R14 -> 0 | T15: =T14+U15 -> 419262 | U15: =V15*S15 -> 0 | V15: 250 | X15: =X14 -> 14773 | Y15: =IF(R15-X15<=0,"ok","oil change") -> ok | Z15: =C15+K15+S15 -> 12 | AA15: =U15+M15+E15 -> 1185 | AB15: =V15+N15+F15 -> 585 | AC15: =IF(Z15>0,AA15/Z15,0) -> 98.75 | AD15: =ELEC!Q16 -> 2772 | AE15: =SUM(AD15/Z15) -> 231 | AF15: =SUM(AE15/1600) -> 0.144375 | AG15: =SUM(AF15/1600) -> 9.0234375e-05 | AH15: =SUM(AC15-AG15) -> 98.74991 | AI15: =AD15*AJ15 -> 713.46835 | AJ15: =305/1185 -> 0.25738397 | AK15: =AI15/Z15 -> 59.455696 | AL15: =IF(Z15=0,0,1) -> 1
A16: =ELEC!C17 -> 44971 | B16: 2072 | C16: =B16-B15 -> 9 | D16: =D15+C16*85 -> 837241 | E16: =SUM(D16-D15) -> 765 | F16: =IF(C16>0,E16/C16,0) -> 85 | H16: =H15 -> 12231 | I16: =IF(B16-H16<=0,"ok","oil change") -> ok | J16: =J15 -> 149 | K16: =J16-J15 -> 0 | L16: =(K16*N15)+L15 -> 392691 | M16: =SUM(L16-L15) -> 0 | N16: 250 | P16: =P15 -> 10873 | Q16: =IF(J16-P16<=0,"ok","oil change") -> ok | R16: =R15 -> 13920 | S16: =R16-R15 -> 0 | T16: =T15+U16 -> 419262 | U16: =V16*S16 -> 0 | V16: 250 | X16: =X15 -> 14773 | Y16: =IF(R16-X16<=0,"ok","oil change") -> ok | Z16: =C16+K16+S16 -> 9 | AA16: =U16+M16+E16 -> 765 | AB16: =V16+N16+F16 -> 585 | AC16: =IF(Z16>0,AA16/Z16,0) -> 85 | AD16: =ELEC!Q17 -> 2319 | AE16: =SUM(AD16/Z16) -> 257.66667 | AF16: =SUM(AE16/1600) -> 0.16104167 | AG16: =SUM(AF16/1600) -> 0.00010065104 | AH16: =SUM(AC16-AG16) -> 84.999899 | AI16: =AD16*AJ16 -> 596.87342 | AJ16: =305/1185 -> 0.25738397 | AK16: =AI16/Z16 -> 66.319269 | AL16: =IF(Z16=0,0,1) -> 1
A17: =ELEC!C18 -> 44972 | B17: 2079 | C17: =B17-B16 -> 7 | D17: =D16+C17*85 -> 837836 | E17: =SUM(D17-D16) -> 595 | F17: =IF(C17>0,E17/C17,0) -> 85 | H17: =H16 -> 12231 | I17: =IF(B17-H17<=0,"ok","oil change") -> ok | J17: =J16 -> 149 | K17: =J17-J16 -> 0 | L17: =(K17*N16)+L16 -> 392691 | M17: =SUM(L17-L16) -> 0 | N17: 250 | P17: =P16 -> 10873 | Q17: =IF(J17-P17<=0,"ok","oil change") -> ok | R17: =R16 -> 13920 | S17: =R17-R16 -> 0 | T17: =T16+U17 -> 419262 | U17: =V17*S17 -> 0 | V17: 250 | X17: =X16 -> 14773 | Y17: =IF(R17-X17<=0,"ok","oil change") -> ok | Z17: =C17+K17+S17 -> 7 | AA17: =U17+M17+E17 -> 595 | AB17: =V17+N17+F17 -> 585 | AC17: =IF(Z17>0,AA17/Z17,0) -> 85 | AD17: =ELEC!Q18 -> 1847 | AE17: =SUM(AD17/Z17) -> 263.85714 | AF17: =SUM(AE17/1600) -> 0.16491071 | AG17: =SUM(AF17/1600) -> 0.0001030692 | AH17: =SUM(AC17-AG17) -> 84.999897 | AI17: =AD17*AJ17 -> 475.38819 | AJ17: =305/1185 -> 0.25738397 | AK17: =AI17/Z17 -> 67.912598 | AL17: =IF(Z17=0,0,1) -> 1
A18: =ELEC!C19 -> 44973 | B18: 2088 | C18: =B18-B17 -> 9 | D18: =D17+C18*85 -> 838601 | E18: =SUM(D18-D17) -> 765 | F18: =IF(C18>0,E18/C18,0) -> 85 | H18: =H17 -> 12231 | I18: =IF(B18-H18<=0,"ok","oil change") -> ok | J18: =J17 -> 149 | K18: =J18-J17 -> 0 | L18: =(K18*N17)+L17 -> 392691 | M18: =SUM(L18-L17) -> 0 | N18: 250 | P18: =P17 -> 10873 | Q18: =IF(J18-P14<=0,"ok","oil change") -> ok | R18: =R17 -> 13920 | S18: =R18-R17 -> 0 | T18: =T17+U18 -> 419262 | U18: =V18*S18 -> 0 | V18: 250 | X18: =X17 -> 14773 | Y18: =IF(R18-X18<=0,"ok","oil change") -> ok | Z18: =C18+K18+S18 -> 9 | AA18: =U18+M18+E18 -> 765 | AB18: =V18+N18+F18 -> 585 | AC18: =IF(Z18>0,AA18/Z18,0) -> 85 | AD18: =ELEC!Q19 -> 2629 | AE18: =SUM(AD18/Z18) -> 292.11111 | AF18: =SUM(AE18/1600) -> 0.18256944 | AG18: =SUM(AF18/1600) -> 0.0001141059 | AH18: =SUM(AC18-AG18) -> 84.999886 | AI18: =AD18*AJ18 -> 676.66245 | AJ18: =305/1185 -> 0.25738397 | AK18: =AI18/Z18 -> 75.184716 | AL18: =IF(Z18=0,0,1) -> 1
A19: =ELEC!C20 -> 44974 | B19: =B18 -> 2088 | C19: =B19-B18 -> 0 | D19: =D18+C19*85 -> 838601 | E19: =SUM(D19-D18) -> 0 | F19: =IF(C19>0,E19/C19,0) -> 0 | H19: =H18 -> 12231 | I19: =IF(B19-H19<=0,"ok","oil change") -> ok | J19: =J18 -> 149 | K19: =J19-J18 -> 0 | L19: =(K19*N18)+L18 -> 392691 | M19: =SUM(L19-L18) -> 0 | N19: 250 | P19: =P18 -> 10873 | Q19: =IF(J19-P19<=0,"ok","oil change") -> ok | R19: =R18 -> 13920 | S19: =R19-R18 -> 0 | T19: =T18+U19 -> 419262 | U19: =V19*S19 -> 0 | V19: 250 | X19: =X18 -> 14773 | Y19: =IF(R19-X19<=0,"ok","oil change") -> ok | Z19: =C19+K19+S19 -> 0 | AA19: =U19+M19+E19 -> 0 | AB19: =V19+N19+F19 -> 500 | AC19: =IF(Z19>0,AA19/Z19,0) -> 0 | AD19: =ELEC!Q20 -> 0 | AE19: =SUM(AD19/Z19) -> #DIV/0! | AF19: =SUM(AE19/1600) -> #DIV/0! | AG19: =SUM(AF19/1600) -> #DIV/0! | AH19: =SUM(AC19-AG19) -> #DIV/0! | AI19: =AD19*AJ19 -> 0 | AJ19: =305/1185 -> 0.25738397 | AK19: =AI19/Z19 -> #DIV/0! | AL19: =IF(Z19=0,0,1) -> 0
A20: =ELEC!C21 -> 44975 | B20: =B19 -> 2088 | C20: =B20-B19 -> 0 | D20: =D19+C20*85 -> 838601 | E20: =SUM(D20-D19) -> 0 | F20: =IF(C20>0,E20/C20,0) -> 0 | H20: =H19 -> 12231 | I20: =IF(B20-H20<=0,"ok","oil change") -> ok | J20: =J19 -> 149 | K20: =J20-J19 -> 0 | L20: =(K20*N19)+L19 -> 392691 | M20: =SUM(L20-L19) -> 0 | N20: 250 | P20: =P19 -> 10873 | Q20: =IF(J20-P20<=0,"ok","oil change") -> ok | R20: =R19 -> 13920 | S20: =R20-R19 -> 0 | T20: =T19+U20 -> 419262 | U20: =V20*S20 -> 0 | V20: 250 | X20: =X19 -> 14773 | Y20: =IF(R20-X20<=0,"ok","oil change") -> ok | Z20: =C20+K20+S20 -> 0 | AA20: =U20+M20+E20 -> 0 | AB20: =V20+N20+F20 -> 500 | AC20: =IF(Z20>0,AA20/Z20,0) -> 0 | AD20: =ELEC!Q21 -> 0 | AE20: =SUM(AD20/Z20) -> #DIV/0! | AF20: =SUM(AE20/1600) -> #DIV/0! | AG20: =SUM(AF20/1600) -> #DIV/0! | AH20: =SUM(AC20-AG20) -> #DIV/0! | AI20: =AD20*AJ20 -> 0 | AJ20: =305/1185 -> 0.25738397 | AK20: =AI20/Z20 -> #DIV/0! | AL20: =IF(Z20=0,0,1) -> 0
A21: =ELEC!C22 -> 44976 | B21: 2098 | C21: =B21-B20 -> 10 | D21: =D20+C21*85 -> 839451 | E21: =SUM(D21-D20) -> 850 | F21: =IF(C21>0,E21/C21,0) -> 85 | H21: =H20 -> 12231 | I21: =IF(B21-H21<=0,"ok","oil change") -> ok | J21: =J20 -> 149 | K21: =J21-J20 -> 0 | L21: =(K21*N20)+L20 -> 392691 | M21: =SUM(L21-L20) -> 0 | N21: 250 | P21: =P20 -> 10873 | Q21: =IF(J21-P21<=0,"ok","oil change") -> ok | R21: =R20 -> 13920 | S21: =R21-R20 -> 0 | T21: =T20+U21 -> 419262 | U21: =V21*S21 -> 0 | V21: 250 | X21: =X20 -> 14773 | Y21: =IF(R21-X21<=0,"ok","oil change") -> ok | Z21: =C21+K21+S21 -> 10 | AA21: =U21+M21+E21 -> 850 | AB21: =V21+N21+F21 -> 585 | AC21: =IF(Z21>0,AA21/Z21,0) -> 85 | AD21: =ELEC!Q22 -> 2391 | AE21: =SUM(AD21/Z21) -> 239.1 | AF21: =SUM(AE21/1600) -> 0.1494375 | AG21: =SUM(AF21/1600) -> 9.3398437e-05 | AH21: =SUM(AC21-AG21) -> 84.999907 | AI21: =AD21*AJ21 -> 615.40506 | AJ21: =305/1185 -> 0.25738397 | AK21: =AI21/Z21 -> 61.540506 | AL21: =IF(Z21=0,0,1) -> 1
A22: =ELEC!C23 -> 44977 | B22: 2107 | C22: =B22-B21 -> 9 | D22: =D21+C22*85 -> 840216 | E22: =SUM(D22-D21) -> 765 | F22: =IF(C22>0,E22/C22,0) -> 85 | H22: =H21 -> 12231 | I22: =IF(B22-H22<=0,"ok","oil change") -> ok | J22: =J21 -> 149 | K22: =J22-J21 -> 0 | L22: =(K22*N21)+L21 -> 392691 | M22: =SUM(L22-L21) -> 0 | N22: 250 | P22: =P21 -> 10873 | Q22: =IF(J22-P22<=0,"ok","oil change") -> ok | R22: =R21 -> 13920 | S22: =R22-R21 -> 0 | T22: =T21+U22 -> 419262 | U22: =V22*S22 -> 0 | V22: 250 | X22: =X21 -> 14773 | Y22: =IF(R22-X22<=0,"ok","oil change") -> ok | Z22: =C22+K22+S22 -> 9 | AA22: =U22+M22+E22 -> 765 | AB22: =V22+N22+F22 -> 585 | AC22: =IF(Z22>0,AA22/Z22,0) -> 85 | AD22: =ELEC!Q23 -> 2341 | AE22: =SUM(AD22/Z22) -> 260.11111 | AF22: =SUM(AE22/1600) -> 0.16256944 | AG22: =SUM(AF22/1600) -> 0.0001016059 | AH22: =SUM(AC22-AG22) -> 84.999898 | AI22: =AD22*AJ22 -> 602.53586 | AJ22: =305/1185 -> 0.25738397 | AK22: =AI22/Z22 -> 66.948429 | AL22: =IF(Z22=0,0,1) -> 1
A23: =ELEC!C24 -> 44978 | B23: 2118 | C23: =B23-B22 -> 11 | D23: =D22+C23*85 -> 841151 | E23: =SUM(D23-D22) -> 935 | F23: =IF(C23>0,E23/C23,0) -> 85 | H23: =H22 -> 12231 | I23: =IF(B23-H23<=0,"ok","oil change") -> ok | J23: =J22 -> 149 | K23: =J23-J22 -> 0 | L23: =(K23*N22)+L22 -> 392691 | M23: =SUM(L23-L22) -> 0 | N23: 250 | P23: =P22 -> 10873 | Q23: =IF(J23-P23<=0,"ok","oil change") -> ok | R23: =R22 -> 13920 | S23: =R23-R22 -> 0 | T23: =T22+U23 -> 419262 | U23: =V23*S23 -> 0 | V23: 250 | X23: =X22 -> 14773 | Y23: =IF(R23-X23<=0,"ok","oil change") -> ok | Z23: =C23+K23+S23 -> 11 | AA23: =U23+M23+E23 -> 935 | AB23: =V23+N23+F23 -> 585 | AC23: =IF(Z23>0,AA23/Z23,0) -> 85 | AD23: =ELEC!Q24 -> 2675 | AE23: =SUM(AD23/Z23) -> 243.18182 | AF23: =SUM(AE23/1600) -> 0.15198864 | AG23: =SUM(AF23/1600) -> 9.4992898e-05 | AH23: =SUM(AC23-AG23) -> 84.999905 | AI23: =AD23*AJ23 -> 688.50211 | AJ23: =305/1185 -> 0.25738397 | AK23: =AI23/Z23 -> 62.591101 | AL23: =IF(Z23=0,0,1) -> 1
A24: =ELEC!C25 -> 44979 | B24: 2126 | C24: =B24-B23 -> 8 | D24: =D23+C24*85 -> 841831 | E24: =SUM(D24-D23) -> 680 | F24: =IF(C24>0,E24/C24,0) -> 85 | H24: =H23 -> 12231 | I24: =IF(B24-H24<=0,"ok","oil change") -> ok | J24: =J23 -> 149 | K24: =J24-J23 -> 0 | L24: =(K24*N23)+L23 -> 392691 | M24: =SUM(L24-L23) -> 0 | N24: 250 | P24: =P23 -> 10873 | Q24: =IF(J24-P24<=0,"ok","oil change") -> ok | R24: =R23 -> 13920 | S24: =R24-R23 -> 0 | T24: =T23+U24 -> 419262 | U24: =V24*S24 -> 0 | V24: 250 | X24: =X23 -> 14773 | Y24: =IF(R24-X24<=0,"ok","oil change") -> ok | Z24: =C24+K24+S24 -> 8 | AA24: =U24+M24+E24 -> 680 | AB24: =V24+N24+F24 -> 585 | AC24: =IF(Z24>0,AA24/Z24,0) -> 85 | AD24: =ELEC!Q25 -> 2140 | AE24: =SUM(AD24/Z24) -> 267.5 | AF24: =SUM(AE24/1600) -> 0.1671875 | AG24: =SUM(AF24/1600) -> 0.00010449219 | AH24: =SUM(AC24-AG24) -> 84.999896 | AI24: =AD24*AJ24 -> 550.80169 | AJ24: =305/1185 -> 0.25738397 | AK24: =AI24/Z24 -> 68.850211 | AL24: =IF(Z24=0,0,1) -> 1
A25: =ELEC!C26 -> 44980 | B25: =B24 -> 2126 | C25: =B25-B24 -> 0 | D25: =D24+C25*85 -> 841831 | E25: =SUM(D25-D24) -> 0 | F25: =IF(C25>0,E25/C25,0) -> 0 | H25: =H24 -> 12231 | I25: =IF(B25-H25<=0,"ok","oil change") -> ok | J25: =J24 -> 149 | K25: =J25-J24 -> 0 | L25: =(K25*N24)+L24 -> 392691 | M25: =SUM(L25-L24) -> 0 | N25: 250 | P25: =P24 -> 10873 | Q25: =IF(J25-P25<=0,"ok","oil change") -> ok | R25: =R24 -> 13920 | S25: =R25-R24 -> 0 | T25: =T24+U25 -> 419262 | U25: =V25*S25 -> 0 | V25: 250 | X25: =X24 -> 14773 | Y25: =IF(R25-X25<=0,"ok","oil change") -> ok | Z25: =C25+K25+S25 -> 0 | AA25: =U25+M25+E25 -> 0 | AB25: =V25+N25+F25 -> 500 | AC25: =IF(Z25>0,AA25/Z25,0) -> 0 | AD25: =ELEC!Q26 -> 2824 | AE25: =SUM(AD25/Z25) -> #DIV/0! | AF25: =SUM(AE25/1600) -> #DIV/0! | AG25: =SUM(AF25/1600) -> #DIV/0! | AH25: =SUM(AC25-AG25) -> #DIV/0! | AI25: =AD25*AJ25 -> 726.85232 | AJ25: =305/1185 -> 0.25738397 | AK25: =AI25/Z25 -> #DIV/0! | AL25: =IF(Z25=0,0,1) -> 0
A26: =ELEC!C27 -> 44981 | B26: 2138 | C26: =B26-B25 -> 12 | D26: =D25+C26*85 -> 842851 | E26: =SUM(D26-D25) -> 1020 | F26: =IF(C25>0,E26/C25,0) -> 0 | H26: =H25 -> 12231 | I26: =IF(B26-H26<=0,"ok","oil change") -> ok | J26: =J25 -> 149 | K26: =J26-J25 -> 0 | L26: =(K26*N25)+L25 -> 392691 | M26: =SUM(L26-L25) -> 0 | N26: 250 | P26: =P25 -> 10873 | Q26: =IF(J26-P26<=0,"ok","oil change") -> ok | R26: =R25 -> 13920 | S26: =R26-R25 -> 0 | T26: =T25+U26 -> 419262 | U26: =V26*S26 -> 0 | V26: 250 | X26: =X25 -> 14773 | Y26: =IF(R26-X26<=0,"ok","oil change") -> ok | Z26: =C26+K26+S26 -> 12 | AA26: =U26+M26+E26 -> 1020 | AB26: =V26+N26+F26 -> 500 | AC26: =IF(Z26>0,AA26/Z26,0) -> 85 | AD26: =ELEC!Q27 -> 0 | AE26: =SUM(AD26/Z26) -> 0 | AF26: =SUM(AE26/1600) -> 0 | AG26: =SUM(AF26/1600) -> 0 | AH26: =SUM(AC26-AG26) -> 85 | AI26: =AD26*AJ26 -> 0 | AJ26: =305/1185 -> 0.25738397 | AK26: =AI26/Z26 -> 0 | AL26: =IF(Z26=0,0,1) -> 1
A27: =ELEC!C28 -> 44982 | B27: =B26 -> 2138 | C27: =B27-B26 -> 0 | D27: =D26+C27*85 -> 842851 | E27: =SUM(D27-D26) -> 0 | F27: =IF(C26>0,E27/C26,0) -> 0 | H27: =H26 -> 12231 | I27: =IF(B26-H27<=0,"ok","oil change") -> ok | J27: =J26 -> 149 | K27: =J27-J26 -> 0 | L27: =(K27*N26)+L26 -> 392691 | M27: =SUM(L27-L26) -> 0 | N27: 250 | P27: =P26 -> 10873 | Q27: =IF(J27-P27<=0,"ok","oil change") -> ok | R27: =R26 -> 13920 | S27: =R27-R26 -> 0 | T27: =T26+U27 -> 419262 | U27: =V27*S27 -> 0 | V27: 250 | X27: =X26 -> 14773 | Y27: =IF(R27-X27<=0,"ok","oil change") -> ok | Z27: =C27+K27+S27 -> 0 | AA27: =U27+M27+E27 -> 0 | AB27: =V27+N27+F27 -> 500 | AC27: =IF(Z27>0,AA27/Z27,0) -> 0 | AD27: =ELEC!Q28 -> 0 | AE27: =SUM(AD27/Z27) -> #DIV/0! | AF27: =SUM(AE27/1600) -> #DIV/0! | AG27: =SUM(AF27/1600) -> #DIV/0! | AH27: =SUM(AC27-AG27) -> #DIV/0! | AI27: =AD27*AJ27 -> 0 | AJ27: =305/1185 -> 0.25738397 | AK27: =AI27/Z27 -> #DIV/0! | AL27: =IF(Z27=0,0,1) -> 0
A28: =ELEC!C29 -> 44983 | B28: 2148 | C28: =B28-B27 -> 10 | D28: =D27+C28*85 -> 843701 | E28: =SUM(D28-D27) -> 850 | F28: =IF(C28>0,E28/C28,0) -> 85 | H28: =H27 -> 12231 | I28: =IF(B28-H28<=0,"ok","oil change") -> ok | J28: =J27 -> 149 | K28: =J28-J27 -> 0 | L28: =(K28*N27)+L27 -> 392691 | M28: =SUM(L28-L27) -> 0 | N28: 250 | P28: =P27 -> 10873 | Q28: =IF(J28-P28<=0,"ok","oil change") -> ok | R28: =R27 -> 13920 | S28: =R28-R27 -> 0 | T28: =T27+U28 -> 419262 | U28: =V28*S28 -> 0 | V28: 250 | X28: =X27 -> 14773 | Y28: =IF(R28-X28<=0,"ok","oil change") -> ok | Z28: =C28+K28+S28 -> 10 | AA28: =U28+M28+E28 -> 850 | AB28: =V28+N28+F28 -> 585 | AC28: =IF(Z28>0,AA28/Z28,0) -> 85 | AD28: =ELEC!Q29 -> 2407 | AE28: =SUM(AD28/Z28) -> 240.7 | AF28: =SUM(AE28/1600) -> 0.1504375 | AG28: =SUM(AF28/1600) -> 9.4023437e-05 | AH28: =SUM(AC28-AG28) -> 84.999906 | AI28: =AD28*AJ28 -> 619.52321 | AJ28: =305/1185 -> 0.25738397 | AK28: =AI28/Z28 -> 61.952321 | AL28: =IF(Z28=0,0,1) -> 1
A29: =ELEC!C30 -> 44984 | B29: 2157 | C29: =B29-B28 -> 9 | D29: =D28+C29*85 -> 844466 | E29: =SUM(D29-D28) -> 765 | F29: =IF(C29>0,E29/C29,0) -> 85 | H29: =H28 -> 12231 | I29: =IF(B29-H29<=0,"ok","oil change") -> ok | J29: =J28 -> 149 | K29: =J29-J28 -> 0 | L29: =(K29*N28)+L28 -> 392691 | M29: =SUM(L29-L28) -> 0 | N29: 250 | P29: =P28 -> 10873 | Q29: =IF(J29-P29<=0,"ok","oil change") -> ok | R29: =R28 -> 13920 | S29: =R29-R28 -> 0 | T29: =T28+U29 -> 419262 | U29: =V29*S29 -> 0 | V29: 250 | X29: =X28 -> 14773 | Y29: =IF(R29-X29<=0,"ok","oil change") -> ok | Z29: =C29+K29+S29 -> 9 | AA29: =U29+M29+E29 -> 765 | AB29: =V29+N29+F29 -> 585 | AC29: =IF(Z29>0,AA29/Z29,0) -> 85 | AD29: =ELEC!Q30 -> 2324 | AE29: =SUM(AD29/Z29) -> 258.22222 | AF29: =SUM(AE29/1600) -> 0.16138889 | AG29: =SUM(AF29/1600) -> 0.00010086806 | AH29: =SUM(AC29-AG29) -> 84.999899 | AI29: =AD29*AJ29 -> 598.16034 | AJ29: =305/1185 -> 0.25738397 | AK29: =AI29/Z29 -> 66.46226 | AL29: =IF(Z29=0,0,1) -> 1
A30: =ELEC!C31 -> 44985 | B30: =B29 -> 2157 | C30: =B30-B29 -> 0 | D30: =D29+C30*85 -> 844466 | E30: =SUM(D30-D29) -> 0 | F30: =IF(C30>0,E30/C30,0) -> 0 | H30: =H29 -> 12231 | I30: =IF(B30-H30<=0,"ok","oil change") -> ok | J30: =J29 -> 149 | K30: =J30-J29 -> 0 | L30: =(K30*N29)+L29 -> 392691 | M30: =SUM(L30-L29) -> 0 | N30: 250 | P30: =P29 -> 10873 | Q30: =IF(J30-P30<=0,"ok","oil change") -> ok | R30: =R29 -> 13920 | S30: =R30-R29 -> 0 | T30: =T29+U30 -> 419262 | U30: =V30*S30 -> 0 | V30: 250 | X30: =X29 -> 14773 | Y30: =IF(R30-X30<=0,"ok","oil change") -> ok | Z30: =C30+K30+S30 -> 0 | AA30: =U30+M30+E30 -> 0 | AB30: =V30+N30+F30 -> 500 | AC30: =IF(Z30>0,AA30/Z30,0) -> 0 | AD30: =ELEC!Q31 -> 0 | AE30: =SUM(AD30/Z30) -> #DIV/0! | AF30: =SUM(AE30/1600) -> #DIV/0! | AG30: =SUM(AF30/1600) -> #DIV/0! | AH30: =SUM(AC30-AG30) -> #DIV/0! | AI30: =AD30*AJ30 -> 0 | AJ30: =305/1185 -> 0.25738397 | AK30: =AI30/Z30 -> #DIV/0! | AL30: =IF(Z30=0,0,1) -> 0
A31: =ELEC!C32 -> 44986 | B31: =B30 -> 2157 | C31: =B31-B30 -> 0 | D31: =D30+C31*85 -> 844466 | E31: =SUM(D31-D30) -> 0 | F31: =IF(C31>0,E31/C31,0) -> 0 | H31: =H30 -> 12231 | I31: =IF(B31-H31<=0,"ok","oil change") -> ok | J31: =J30 -> 149 | K31: =J31-J30 -> 0 | L31: =(K31*N30)+L30 -> 392691 | M31: =SUM(L31-L30) -> 0 | N31: 250 | P31: =P30 -> 10873 | Q31: =IF(J31-P31<=0,"ok","oil change") -> ok | R31: =R30 -> 13920 | S31: =R31-R30 -> 0 | T31: =T30+U31 -> 419262 | U31: =V31*S31 -> 0 | V31: 250 | X31: =X30 -> 14773 | Y31: =IF(R31-X31<=0,"ok","oil change") -> ok | Z31: =C31+K31+S31 -> 0 | AA31: =U31+M31+E31 -> 0 | AB31: =V31+N31+F31 -> 500 | AC31: =IF(Z31>0,AA31/Z31,0) -> 0 | AD31: =ELEC!Q32 -> 0 | AE31: =SUM(AD31/Z31) -> #DIV/0! | AF31: =SUM(AE31/1600) -> #DIV/0! | AG31: =SUM(AF31/1600) -> #DIV/0! | AH31: =SUM(AC31-AG31) -> #DIV/0! | AI31: =AD31*AJ31 -> 0 | AJ31: =305/1185 -> 0.25738397 | AK31: =AI31/Z31 -> #DIV/0! | AL31: =IF(Z31=0,0,1) -> 0
P34: =+O34/3 -> 0 | U34: =SUM(C35:S35) -> 185 | X34: 341 | Z34: =SUM(Z3:Z33) -> 185 | AF34: =SUM(AE34/1600) -> 0 | AL34: =SUM(AL3:AL33) -> 18
C35: =SUM(C3:C33) -> 184 | K35: =SUM(K3:K33) -> 1 | S35: =SUM(S3:S33) -> 0
T38: 14
T39: 10
D40: 193 | T40: 10
D41: =193+10 -> 203 | T41: 0
D42: =203+10 -> 213 | I42: =266-79 -> 187 | T42: 0
B43: =187+6 -> 193 | D43: =D42 -> 213 | T43: 8
D44: =D43 -> 213 | T44: 9
D45: =213+8 -> 221 | T45: 10
D46: =221+9 -> 230 | T46: 9
D47: =230+10 -> 240 | T47: 9
D48: =240+9 -> 249
D49: =249+9 -> 258
D50: 266

Sheet EDl log
A1: Date | B1: EDL | C1: Consu EDL KW | F1: Peak | G1: 320 | H1: Day | I1: 112 | J1: Night | K1: 80
L2: P | M2: D | N2: N | O2: fee | P2: T EDL | Q2: Gen | R2: Elc C
A3: 44957 | B3: ='[2]EDl log'!B34 -> 1128115 | C3: ='[2]EDl log'!C34 -> 0 | D3: ='[2]EDl log'!D34 -> 0 | E3: ='[2]EDl log'!E34 -> 1128115 | F3: ='[2]EDl log'!F34 -> 161786 | G3: ='[2]EDl log'!G34 -> 0 | H3: ='[2]EDl log'!H34 -> 564388 | I3: ='[2]EDl log'!I34 -> 0 | ... T3: ='[2]EDl log'!T34 -> 0.24510189 | Z3: VAT | AA3: 0.1
A4: =ELEC!C4 -> 44958 | B4: 1128442 | C4: =SUM(B4-B3) -> 327 | D4: =SUM(G4+I4+K4) -> 328 | E4: =B3+D4 -> 1128443 | F4: 161912 | G4: =F4-F3 -> 126 | H4: 564590 | I4: =H4-H3 -> 202 | J4: =J3 -> 401939 | K4: =K3 -> 0 | L4: =SUM(G4*$Y$28)/1507.5 -> 26.746269 | M4: =SUM(I4*$Y$27)/1507.5 -> 15.007629 | N4: =SUM(K4*$Y$26)/1507.5 -> 0 | O4: =($AC$29/$A$37)/1507.5 -> 171.38908 | P4: =SUM(L4:O4) -> 213.14298 | Q4: =SUM(-tanks!AX6*tanks!$AU$37) -> 1481.8365 | R4: =SUM(P4:Q4) -> 1694.9795 | S4: =SUM(ELEC!N4) -> 3464 | T4: =IF(S4>0,R4/S4,0) -> 0.4893128 | V4: EDL | W4: 44949 | Z4: Subscription
A5: =ELEC!C5 -> 44959 | B5: =B4 -> 1128442 | C5: =SUM(B5-B4) -> 0 | D5: =SUM(G5+I5+K5) -> 0 | E5: =B4+D5 -> 1128442 | F5: =F4 -> 161912 | G5: =F5-F4 -> 0 | H5: =H4 -> 564590 | I5: =H5-H4 -> 0 | J5: =J4 -> 401939 | K5: =J5-J4 -> 0 | L5: =SUM(G5*$Y$28)/1507.5 -> 0 | M5: =SUM(I5*$Y$27)/1507.5 -> 0 | N5: =SUM(K5*$Y$26)/1507.5 -> 0 | O5: =($AC$29/$A$37)/1507.5 -> 171.38908 | P5: =SUM(L5:O5) -> 171.38908 | Q5: =SUM(-tanks!AX7*tanks!$AU$37) -> 584.36903 | R5: =SUM(P5:Q5) -> 755.75811 | S5: =SUM(ELEC!N5) -> 3065 | T5: =IF(S5>0,R5/S5,0) -> 0.24657687 | Z5: KVA | AA5: 5000
A6: =ELEC!C6 -> 44960 | B6: =B5 -> 1128442 | C6: =SUM(B6-B5) -> 0 | D6: =SUM(G6+I6+K6) -> 0 | E6: =B5+D6 -> 1128442 | F6: =F5 -> 161912 | G6: =F6-F5 -> 0 | H6: =H5 -> 564590 | I6: =H6-H5 -> 0 | J6: =J5 -> 401939 | K6: =J6-J5 -> 0 | L6: =SUM(G6*$Y$28)/1507.5 -> 0 | M6: =SUM(I6*$Y$27)/1507.5 -> 0 | N6: =SUM(K6*$Y$26)/1507.5 -> 0 | O6: =($AC$29/$A$37)/1507.5 -> 171.38908 | P6: =SUM(L6:O6) -> 171.38908 | Q6: =SUM(-tanks!AX8*tanks!$AU$37) -> -0.5166 | R6: =SUM(P6:Q6) -> 170.87248 | S6: =SUM(ELEC!N6) -> 0 | T6: =IF(S6>0,R6/S6,0) -> 0
A7: =ELEC!C7 -> 44961 | B7: =B6 -> 1128442 | C7: =SUM(B7-B6) -> 0 | D7: =SUM(G7+I7+K7) -> 0 | E7: =B6+D7 -> 1128442 | F7: =F6 -> 161912 | G7: =F7-F6 -> 0 | H7: =H6 -> 564590 | I7: =H7-H6 -> 0 | J7: =J6 -> 401939 | K7: =J7-J6 -> 0 | L7: =SUM(G7*$Y$28)/1507.5 -> 0 | M7: =SUM(I7*$Y$27)/1507.5 -> 0 | N7: =SUM(K7*$Y$26)/1507.5 -> 0 | O7: =($AC$29/$A$37)/1507.5 -> 171.38908 | P7: =SUM(L7:O7) -> 171.38908 | Q7: =SUM(-tanks!AX9*tanks!$AU$37) -> 0 | R7: =SUM(P7:Q7) -> 171.38908 | S7: =SUM(ELEC!N7) -> 0 | T7: =IF(S7>0,R7/S7,0) -> 0 | V7: Electricity consumption | X7: Price LL
A8: =ELEC!C8 -> 44962 | B8: =B7 -> 1128442 | C8: =SUM(B8-B7) -> 0 | D8: =SUM(G8+I8+K8) -> 0 | E8: =B7+D8 -> 1128442 | F8: =F7 -> 161912 | G8: =F8-F7 -> 0 | H8: =H7 -> 564590 | I8: =H8-H7 -> 0 | J8: =J7 -> 401939 | K8: =J8-J7 -> 0 | L8: =SUM(G8*$Y$28)/1507.5 -> 0 | M8: =SUM(I8*$Y$27)/1507.5 -> 0 | N8: =SUM(K8*$Y$26)/1507.5 -> 0 | O8: =($AC$29/$A$37)/1507.5 -> 171.38908 | P8: =SUM(L8:O8) -> 171.38908 | Q8: =SUM(-tanks!AX10*tanks!$AU$37) -> 881.41403 | R8: =SUM(P8:Q8) -> 1052.8031 | S8: =SUM(ELEC!N8) -> 3261 | T8: =IF(S8>0,R8/S8,0) -> 0.32284671 | V8: Index in | W8: Index Out | Y8: Kwh Cost | Z8: K | AA8: Kwh | AB8: Total cost LL | AC8: Fees
A9: =ELEC!C9 -> 44963 | B9: =B8 -> 1128442 | C9: =SUM(B9-B8) -> 0 | D9: =SUM(G9+I9+K9) -> 0 | E9: =B8+D9 -> 1128442 | F9: =F8 -> 161912 | G9: =F9-F8 -> 0 | H9: =H8 -> 564590 | I9: =H9-H8 -> 0 | J9: =J8 -> 401939 | K9: =J9-J8 -> 0 | L9: =SUM(G9*$Y$28)/1507.5 -> 0 | M9: =SUM(I9*$Y$27)/1507.5 -> 0 | N9: =SUM(K9*$Y$26)/1507.5 -> 0 | O9: =($AC$29/$A$37)/1507.5 -> 171.38908 | P9: =SUM(L9:O9) -> 171.38908 | Q9: =SUM(-tanks!AX11*tanks!$AU$37) -> 1078.8219 | R9: =SUM(P9:Q9) -> 1250.211 | S9: =SUM(ELEC!N9) -> 3298 | T9: =IF(S9>0,R9/S9,0) -> 0.37908156 | V9: ='[2]EDl log'!V26 -> 401934 | W9: ='[2]EDl log'!W26 -> 401939 | X9: ='[2]EDl log'!X26 -> Night | Y9: ='[2]EDl log'!Y26 -> 80 | Z9: ='[2]EDl log'!Z26 -> 1 | AA9: ='[2]EDl log'!AA26 -> 5 | AB9: ='[2]EDl log'!AB26 -> 400 | AC9: ='[2]EDl log'!AC26 -> 1033333 | AD9: ='[2]EDl log'!AD26 -> 0 | AE9: ='[5]EDl log'!AE26 -> 0 | AF9: ='[5]EDl log'!AF26 -> 0
A10: =ELEC!C10 -> 44964 | B10: =B9 -> 1128442 | C10: =SUM(B10-B9) -> 0 | D10: =SUM(G10+I10+K10) -> 0 | E10: =B9+D10 -> 1128442 | F10: =F9 -> 161912 | G10: =F10-F9 -> 0 | H10: =H9 -> 564590 | I10: =H10-H9 -> 0 | J10: =J9 -> 401939 | K10: =J10-J9 -> 0 | L10: =SUM(G10*$Y$28)/1507.5 -> 0 | M10: =SUM(I10*$Y$27)/1507.5 -> 0 | N10: =SUM(K10*$Y$26)/1507.5 -> 0 | O10: =($AC$29/$A$37)/1507.5 -> 171.38908 | P10: =SUM(L10:O10) -> 171.38908 | Q10: =SUM(-tanks!AX12*tanks!$AU$37) -> 1095.5253 | R10: =SUM(P10:Q10) -> 1266.9144 | S10: =SUM(ELEC!N10) -> 3712 | T10: =IF(S10>0,R10/S10,0) -> 0.34130236 | V10: ='[2]EDl log'!V27 -> 563190 | W10: ='[2]EDl log'!W27 -> 564388 | X10: ='[2]EDl log'!X27 -> day | Y10: ='[2]EDl log'!Y27 -> 112 | Z10: ='[2]EDl log'!Z27 -> 1 | AA10: ='[2]EDl log'!AA27 -> 1198 | AB10: ='[2]EDl log'!AB27 -> 134176 | AC10: ='[2]EDl log'!AC27 -> 6200000 | AD10: ='[2]EDl log'!AD27 -> 0.99831081 | AE10: ='[5]EDl log'!AE27 -> 0 | AF10: ='[5]EDl log'!AF27 -> 0
