Workbook

Sheet Total
A1: Site Name | B1: Day | C1: Month | D1: Year | E1: Total Electricity Kwh | F1: Electricity Tariff ($/Kwh) | G1: Natual Gas (m3) | H1: Natural Gas $/m3 | I1: Water Utility Supply (m3) m3 | J1: Water Utility Supply (m3) $/m3 | K1: Room Nights
A2: Cairo at The First Residence | B2: 1 | C2: 8 | D2: 2022 | E2: =Elect!BS6+Submetering!AH2 -> 39596.177 | F2: ='Utility Consnsumption'!K13/'Utility Consnsumption'!J13 -> 1.3181724 | G2: =Gas!K7+Submetering!AR2 -> 1608.68 | H2: 3.8 | I2: =Water!H7+Submetering!AM2 -> 866.52 | J2: 10 | K2: =Elect!BT6 -> 158
A3: Cairo at The First Residence | B3: =B2+1 -> 2 | C3: 8 | D3: 2022 | E3: =Elect!BS7+Submetering!AH3 -> 34267.993 | F3: =F2 -> 1.3181724 | G3: =Gas!K8+Submetering!AR3 -> 1072.48 | H3: 3.8 | I3: =Water!H8+Submetering!AM3 -> 116 | J3: 10 | K3: =Elect!BT7 -> 162
A4: Cairo at The First Residence | B4: =B3+1 -> 3 | C4: 8 | D4: 2022 | E4: =Elect!BS8+Submetering!AH4 -> 33135.42 | F4: =F3 -> 1.3181724 | G4: =Gas!K9+Submetering!AR4 -> 1056.38 | H4: 3.8 | I4: =Water!H9+Submetering!AM4 -> 183.86 | J4: 10 | K4: =Elect!BT8 -> 173
A5: Cairo at The First Residence | B5: =B4+1 -> 4 | C5: 8 | D5: 2022 | E5: =Elect!BS9+Submetering!AH5 -> 33662.663 | F5: =F4 -> 1.3181724 | G5: =Gas!K10+Submetering!AR5 -> 1067.1133 | H5: 3.8 | I5: =Water!H10+Submetering!AM5 -> 177.28667 | J5: 10 | K5: =Elect!BT9 -> 202
A6: Cairo at The First Residence | B6: =B5+1 -> 5 | C6: 8 | D6: 2022 | E6: =Elect!BS10+Submetering!AH6 -> 36835.723 | F6: =F5 -> 1.3181724 | G6: =Gas!K11+Submetering!AR6 -> 1476.8467 | H6: 3.8 | I6: =Water!H11+Submetering!AM6 -> 666.03333 | J6: 10 | K6: =Elect!BT10 -> 216
A7: Cairo at The First Residence | B7: =B6+1 -> 6 | C7: 8 | D7: 2022 | E7: =Elect!BS11+Submetering!AH7 -> 30744.545 | F7: =F6 -> 1.3181724 | G7: =Gas!K12+Submetering!AR7 -> 1225.78 | H7: 3.8 | I7: =Water!H12+Submetering!AM7 -> 385.12 | J7: 10 | K7: =Elect!BT11 -> 224
A8: Cairo at The First Residence | B8: =B7+1 -> 7 | C8: 8 | D8: 2022 | E8: =Elect!BS12+Submetering!AH8 -> 33673.663 | F8: =F7 -> 1.3181724 | G8: =Gas!K13+Submetering!AR8 -> 1258.68 | H8: 3.8 | I8: =Water!H13+Submetering!AM8 -> 415.28 | J8: 10 | K8: =Elect!BT12 -> 221
A9: Cairo at The First Residence | B9: =B8+1 -> 8 | C9: 8 | D9: 2022 | E9: =Elect!BS13+Submetering!AH9 -> 34183.317 | F9: =F8 -> 1.3181724 | G9: =Gas!K14+Submetering!AR9 -> 1264.28 | H9: 3.8 | I9: =Water!H14+Submetering!AM9 -> 392.66 | J9: 10 | K9: =Elect!BT13 -> 216
A10: Cairo at The First Residence | B10: =B9+1 -> 9 | C10: 8 | D10: 2022 | E10: =Elect!BS14+Submetering!AH10 -> 34963.623 | F10: =F9 -> 1.3181724 | G10: =Gas!K15+Submetering!AR10 -> 1264.98 | H10: 3.8 | I10: =Water!H15+Submetering!AM10 -> 446.6 | J10: 10 | K10: =Elect!BT14 -> 197
A11: Cairo at The First Residence | B11: =B10+1 -> 10 | C11: 8 | D11: 2022 | E11: =Elect!BS15+Submetering!AH11 -> 34951.475 | F11: =F10 -> 1.3181724 | G11: =Gas!K16+Submetering!AR11 -> 1240.48 | H11: 3.8 | I11: =Water!H16+Submetering!AM11 -> 440.8 | J11: 10 | K11: =Elect!BT15 -> 194
A12: Cairo at The First Residence | B12: =B11+1 -> 11 | C12: 8 | D12: 2022 | E12: =Elect!BS16+Submetering!AH12 -> 35833.125 | F12: =F11 -> 1.3181724 | G12: =Gas!K17+Submetering!AR12 -> 1256.8133 | H12: 3.8 | I12: =Water!H17+Submetering!AM12 -> 444.66667 | J12: 10 | K12: =Elect!BT16 -> 211
A13: Cairo at The First Residence | B13: =B12+1 -> 12 | C13: 8 | D13: 2022 | E13: =Elect!BS17+Submetering!AH13 -> 34246.55 | F13: =F12 -> 1.3181724 | G13: =Gas!K18+Submetering!AR13 -> 1211.5467 | H13: 3.8 | I13: =Water!H18+Submetering!AM13 -> 402.13333 | J13: 10 | K13: =Elect!BT17 -> 239
A14: Cairo at The First Residence | B14: =B13+1 -> 13 | C14: 8 | D14: 2022 | E14: =Elect!BS18+Submetering!AH14 -> 32901.565 | F14: =F13 -> 1.3181724 | G14: =Gas!K19+Submetering!AR14 -> 1218.08 | H14: 3.8 | I14: =Water!H19+Submetering!AM14 -> 386.28 | J14: 10 | K14: =Elect!BT18 -> 227
... A32: Cairo at The First Residence | B32: =B31+1 -> 31 | C32: 8 | D32: 2022 | E32: =Elect!BS36+Submetering!AH32 -> 35463.229 | F32: =F31 -> 1.3181724 | G32: =Gas!K37+Submetering!AR32 -> 1278.2622 | H32: 3.8 | I32: =Water!H37+Submetering!AM32 -> 352.25333 | J32: 10 | K32: =Elect!BT36 -> 134

Sheet Submetering
A1: Site Name | B1: Day | C1: Month | D1: Year | E1: Electricity | F1: Main Feeder -KWh | G1: T2+T8 -KWh | H1: La Gourmandize -KWh | I1: Casino 3rd floor EM -KWh | J1: Casino 3rd floor Normal -KWh | K1: Chiller 1 -KWh | L1: Chiller 2 -KWh | M1: Chiller 3 -KWh | N1: Chiller 4 -KWh | O1: Chiller 5 -KWh | P1: Chiller 6 -KWh | Q1: Cooling towers -KWh | R1: Chiller Pumps -KWh | S1: Cooling Tower Pumps -KWh | T1: Fiber Chiller -KWh | U1: Mall Ceiling light -KWh | V1: LG Bakery -KWh | W1: LG Bakery light ( Old lockers ) -KWh | X1: MCCR1 -KWh | Y1: Children Swimming Pool -KWh | Z1: DPH1 -KWh | AA1: Guest Rooms Emerg. -KWh | AB1: Hotel Hoods -KWh | AC1: Main G2 -KWh | AD1: Old Casino Emergency -KWh | AE1: L / A -KWh | AF1: L / B -KWh | AG1: L / C -KWh | AH1: Boat -KWh | AI1: Water | AJ1: Main water meter 1 -m3 | AK1: Main water meter 2 -m3 | AL1: Main water meter 3 -m3 | AM1: Boat -m3 | AN1: Gas | AO1: Main Gas Flow Meter -m3 | AP1: Laundry Gas Flow Meter -m3 | AQ1: Gourmandize Gas Flow Meter -m3 | AR1: Boat -m3 | AS1: Room Nights
A2: Cairo at The First Residence | B2: 1 | C2: 8 | D2: 2022 | F2: =Elect!J6 -> 6551.3333 | G2: =Elect!K6 -> 5401.3333 | H2: =Elect!Q6 -> 562 | I2: =Elect!S6 -> 140.5 | J2: =Elect!U6 -> 294.5 | K2: =Elect!W6 -> 0 | L2: =Elect!Y6 -> 1226.95 | M2: =Elect!AA6 -> 6873.57 | N2: =Elect!AC6 -> 3188.745 | O2: =Elect!AE6 -> 0 | P2: =Elect!AG6 -> 2824.105 | Q2: =Elect!AI6 -> 1167.9787 | R2: =Elect!AK6 -> 3983.48 | S2: =Elect!AM6 -> 122.35933 | T2: =Elect!AP6 -> 273.825 | U2: =Elect!AR6 -> 165 | V2: =Elect!AT6 -> 173.2 | W2: =Elect!AV6 -> 56.3 | X2: =Elect!AX6 -> 1080.5 | Y2: =Elect!AZ6 -> 0 | Z2: =Elect!BB6 -> 4381.7 | AA2: =Elect!BD6 -> 269.4 | AB2: =Elect!BF6 -> 82.611111 | AC2: =Elect!BH6 -> 6613.12 | AD2: =Elect!BL6 -> 390.1 | AE2: =Elect!BN6 -> 1708.4 | AF2: =Elect!BP6 -> 108 | AG2: =Elect!BR6 -> 164.5 | AH2: =Boat!C4 -> 0 | AJ2: =Water!C7 -> 261 | AK2: =Water!E7 -> 353.8 | AL2: =Water!G7 -> 251.72 | AM2: =Boat!E4 -> 0 | AO2: =Gas!C7 -> 935.98 | AP2: =Gas!E7 -> 672.7 | AQ2: =Gas!G7 -> 90.044444 | AR2: =Boat!G4 -> 0 | AS2: =Elect!BT6 -> 158
A3: Cairo at The First Residence | B3: =B2+1 -> 2 | C3: 8 | D3: 2022 | F3: =Elect!J7 -> 5918 | G3: =Elect!K7 -> 5016 | H3: =Elect!Q7 -> 480 | I3: =Elect!S7 -> 143 | J3: =Elect!U7 -> 281 | K3: =Elect!W7 -> 0 | L3: =Elect!Y7 -> 0 | M3: =Elect!AA7 -> 4241.06 | N3: =Elect!AC7 -> 3978.18 | O3: =Elect!AE7 -> 855.95 | P3: =Elect!AG7 -> 12.19 | Q3: =Elect!AI7 -> 1150.1 | R3: =Elect!AK7 -> 3852.04 | S3: =Elect!AM7 -> 122.96 | T3: =Elect!AP7 -> 296.6625 | U3: =Elect!AR7 -> 177 | V3: =Elect!AT7 -> 168 | W3: =Elect!AV7 -> 64 | X3: =Elect!AX7 -> 1042 | Y3: =Elect!AZ7 -> 0 | Z3: =Elect!BB7 -> 5105 | AA3: =Elect!BD7 -> 263 | AB3: =Elect!BF7 -> 55 | AC3: =Elect!BH7 -> 6486.85 | AD3: =Elect!BL7 -> 313 | AE3: =Elect!BN7 -> 1576 | AF3: =Elect!BP7 -> 111 | AG3: =Elect!BR7 -> 151 | AH3: =Boat!C5 -> 0 | AJ3: =Water!C8 -> 17.4 | AK3: =Water!E8 -> 69.6 | AL3: =Water!G8 -> 29 | AM3: =Boat!E5 -> 0 | AO3: =Gas!C8 -> 935.98 | AP3: =Gas!E8 -> 136.5 | AQ3: =Gas!G8 -> 85 | AR3: =Boat!G5 -> 0 | AS3: =Elect!BT7 -> 162
A4: Cairo at The First Residence | B4: =B3+1 -> 3 | C4: 8 | D4: 2022 | F4: =Elect!J8 -> 5763 | G4: =Elect!K8 -> 4794 | H4: =Elect!Q8 -> 540 | I4: =Elect!S8 -> 139 | J4: =Elect!U8 -> 265 | K4: =Elect!W8 -> 0 | L4: =Elect!Y8 -> 2441.18 | M4: =Elect!AA8 -> 3903.98 | N4: =Elect!AC8 -> 1116.71 | O4: =Elect!AE8 -> 1681.16 | P4: =Elect!AG8 -> 11.66 | Q4: =Elect!AI8 -> 1084.91 | R4: =Elect!AK8 -> 3680.85 | S4: =Elect!AM8 -> 108.12 | T4: =Elect!AP8 -> 280.35 | U4: =Elect!AR8 -> 180 | V4: =Elect!AT8 -> 149 | W4: =Elect!AV8 -> 57 | X4: =Elect!AX8 -> 997 | Y4: =Elect!AZ8 -> 0 | Z4: =Elect!BB8 -> 4571 | AA4: =Elect!BD8 -> 283 | AB4: =Elect!BF8 -> 55 | AC4: =Elect!BH8 -> 6231.5 | AD4: =Elect!BL8 -> 304 | AE4: =Elect!BN8 -> 1526 | AF4: =Elect!BP8 -> 104 | AG4: =Elect!BR8 -> 135 | AH4: =Boat!C6 -> 0 | AJ4: =Water!C9 -> 75.4 | AK4: =Water!E9 -> 46.4 | AL4: =Water!G9 -> 62.06 | AM4: =Boat!E6 -> 0 | AO4: =Gas!C9 -> 935.98 | AP4: =Gas!E9 -> 120.4 | AQ4: =Gas!G9 -> 94 | AR4: =Boat!G6 -> 0 | AS4: =Elect!BT8 -> 173
A5: Cairo at The First Residence | B5: =B4+1 -> 4 | C5: 8 | D5: 2022 | F5: =Elect!J9 -> 5347 | G5: =Elect!K9 -> 4913 | H5: =Elect!Q9 -> 540 | I5: =Elect!S9 -> 137 | J5: =Elect!U9 -> 271 | K5: =Elect!W9 -> 0 | L5: =Elect!Y9 -> 3712.65 | M5: =Elect!AA9 -> 3924.65 | N5: =Elect!AC9 -> 0 | O5: =Elect!AE9 -> 1719.32 | P5: =Elect!AG9 -> 8.48 | Q5: =Elect!AI9 -> 1114.06 | R5: =Elect!AK9 -> 3791.09 | S5: =Elect!AM9 -> 121.9 | T5: =Elect!AP9 -> 296.6625 | U5: =Elect!AR9 -> 167 | V5: =Elect!AT9 -> 166 | W5: =Elect!AV9 -> 60 | X5: =Elect!AX9 -> 1106 | Y5: =Elect!AZ9 -> 0 | Z5: =Elect!BB9 -> 4895 | AA5: =Elect!BD9 -> 281 | AB5: =Elect!BF9 -> 43 | AC5: =Elect!BH9 -> 6368.85 | AD5: =Elect!BL9 -> 301 | AE5: =Elect!BN9 -> 1519 | AF5: =Elect!BP9 -> 108 | AG5: =Elect!BR9 -> 138 | AH5: =Boat!C7 -> 0 | AJ5: =Water!C10 -> 75.4 | AK5: =Water!E10 -> 61.866667 | AL5: =Water!G10 -> 40.02 | AM5: =Boat!E7 -> 0 | AO5: =Gas!C10 -> 935.98 | AP5: =Gas!E10 -> 131.13333 | AQ5: =Gas!G10 -> 88 | AR5: =Boat!G7 -> 0 | AS5: =Elect!BT9 -> 202
A6: Cairo at The First Residence | B6: =B5+1 -> 5 | C6: 8 | D6: 2022 | F6: =Elect!J10 -> 8470 | G6: =Elect!K10 -> 5034 | H6: =Elect!Q10 -> 270 | I6: =Elect!S10 -> 140 | J6: =Elect!U10 -> 273 | K6: =Elect!W10 -> 0 | L6: =Elect!Y10 -> 3879.6 | M6: =Elect!AA10 -> 4012.63 | N6: =Elect!AC10 -> 0 | O6: =Elect!AE10 -> 1666.85 | P6: =Elect!AG10 -> 10.6 | Q6: =Elect!AI10 -> 1129.43 | R6: =Elect!AK10 -> 3851.51 | S6: =Elect!AM10 -> 120.84 | T6: =Elect!AP10 -> 272.8125 | U6: =Elect!AR10 -> 172 | V6: =Elect!AT10 -> 172 | W6: =Elect!AV10 -> 54 | X6: =Elect!AX10 -> 1011 | Y6: =Elect!AZ10 -> 0 | Z6: =Elect!BB10 -> 5022 | AA6: =Elect!BD10 -> 287 | AB6: =Elect!BF10 -> 57 | AC6: =Elect!BH10 -> 6376.45 | AD6: =Elect!BL10 -> 306 | AE6: =Elect!BN10 -> 1509 | AF6: =Elect!BP10 -> 110 | AG6: =Elect!BR10 -> 140 | AH6: =Boat!C8 -> 0 | AJ6: =Water!C11 -> 191.4 | AK6: =Water!E11 -> 286.13333 | AL6: =Water!G11 -> 188.5 | AM6: =Boat!E8 -> 0 | AO6: =Gas!C11 -> 935.98 | AP6: =Gas!E11 -> 540.86667 | AQ6: =Gas!G11 -> 99 | AR6: =Boat!G8 -> 0 | AS6: =Elect!BT10 -> 216
A7: Cairo at The First Residence | B7: =B6+1 -> 6 | C7: 8 | D7: 2022 | F7: =Elect!J11 -> 1859 | G7: =Elect!K11 -> 4423 | H7: =Elect!Q11 -> 750 | I7: =Elect!S11 -> 139 | J7: =Elect!U11 -> 279 | K7: =Elect!W11 -> 0 | L7: =Elect!Y11 -> 3974.47 | M7: =Elect!AA11 -> 4052.91 | N7: =Elect!AC11 -> 0 | O7: =Elect!AE11 -> 1691.23 | P7: =Elect!AG11 -> 10.07 | Q7: =Elect!AI11 -> 1144.8 | R7: =Elect!AK11 -> 3906.63 | S7: =Elect!AM11 -> 117.66 | T7: =Elect!AP11 -> 278.325 | U7: =Elect!AR11 -> 163 | V7: =Elect!AT11 -> 165 | W7: =Elect!AV11 -> 51 | X7: =Elect!AX11 -> 977 | Y7: =Elect!AZ11 -> 0 | Z7: =Elect!BB11 -> 5070 | AA7: =Elect!BD11 -> 246 | AB7: =Elect!BF11 -> 53 | AC7: =Elect!BH11 -> 6234.45 | AD7: =Elect!BL11 -> 303 | AE7: =Elect!BN11 -> 1513 | AF7: =Elect!BP11 -> 106 | AG7: =Elect!BR11 -> 154 | AH7: =Boat!C9 -> 0 | AJ7: =Water!C12 -> 116 | AK7: =Water!E12 -> 156.6 | AL7: =Water!G12 -> 112.52 | AM7: =Boat!E9 -> 0 | AO7: =Gas!C12 -> 935.98 | AP7: =Gas!E12 -> 289.8 | AQ7: =Gas!G12 -> 89 | AR7: =Boat!G9 -> 0 | AS7: =Elect!BT11 -> 224
A8: Cairo at The First Residence | B8: =B7+1 -> 7 | C8: 8 | D8: 2022 | F8: =Elect!J12 -> 5452 | G8: =Elect!K12 -> 4425 | H8: =Elect!Q12 -> 540 | I8: =Elect!S12 -> 137 | J8: =Elect!U12 -> 270 | K8: =Elect!W12 -> 0 | L8: =Elect!Y12 -> 3861.05 | M8: =Elect!AA12 -> 1081.2 | N8: =Elect!AC12 -> 2762.36 | O8: =Elect!AE12 -> 1609.61 | P8: =Elect!AG12 -> 129.32 | Q8: =Elect!AI12 -> 1103.99 | R8: =Elect!AK12 -> 3814.94 | S8: =Elect!AM12 -> 109.18 | T8: =Elect!AP12 -> 283.1625 | U8: =Elect!AR12 -> 149 | V8: =Elect!AT12 -> 153 | W8: =Elect!AV12 -> 62 | X8: =Elect!AX12 -> 980 | Y8: =Elect!AZ12 -> 0 | Z8: =Elect!BB12 -> 5046 | AA8: =Elect!BD12 -> 233 | AB8: =Elect!BF12 -> 64 | AC8: =Elect!BH12 -> 6239.85 | AD8: =Elect!BL12 -> 301 | AE8: =Elect!BN12 -> 1517 | AF8: =Elect!BP12 -> 110 | AG8: =Elect!BR12 -> 145 | AH8: =Boat!C10 -> 0 | AJ8: =Water!C13 -> 133.4 | AK8: =Water!E13 -> 174 | AL8: =Water!G13 -> 107.88 | AM8: =Boat!E10 -> 0 | AO8: =Gas!C13 -> 935.98 | AP8: =Gas!E13 -> 322.7 | AQ8: =Gas!G13 -> 96 | AR8: =Boat!G10 -> 0 | AS8: =Elect!BT12 -> 221
A9: Cairo at The First Residence | B9: =B8+1 -> 8 | C9: 8 | D9: 2022 | F9: =Elect!J13 -> 5595 | G9: =Elect!K13 -> 4549 | H9: =Elect!Q13 -> 540 | I9: =Elect!S13 -> 139 | J9: =Elect!U13 -> 284 | K9: =Elect!W13 -> 0 | L9: =Elect!Y13 -> 4051.32 | M9: =Elect!AA13 -> 0 | N9: =Elect!AC13 -> 3661.24 | O9: =Elect!AE13 -> 1753.77 | P9: =Elect!AG13 -> 10.6 | Q9: =Elect!AI13 -> 1117.77 | R9: =Elect!AK13 -> 3873.24 | S9: =Elect!AM13 -> 107.59 | T9: =Elect!AP13 -> 291.4875 | U9: =Elect!AR13 -> 159 | V9: =Elect!AT13 -> 152 | W9: =Elect!AV13 -> 61 | X9: =Elect!AX13 -> 1088 | Y9: =Elect!AZ13 -> 0 | Z9: =Elect!BB13 -> 5017 | AA9: =Elect!BD13 -> 222 | AB9: =Elect!BF13 -> 55 | AC9: =Elect!BH13 -> 6427.3 | AD9: =Elect!BL13 -> 307 | AE9: =Elect!BN13 -> 1487 | AF9: =Elect!BP13 -> 119 | AG9: =Elect!BR13 -> 165 | AH9: =Boat!C11 -> 0 | AJ9: =Water!C14 -> 127.6 | AK9: =Water!E14 -> 168.2 | AL9: =Water!G14 -> 96.86 | AM9: =Boat!E11 -> 0 | AO9: =Gas!C14 -> 935.98 | AP9: =Gas!E14 -> 328.3 | AQ9: =Gas!G14 -> 94 | AR9: =Boat!G11 -> 0 | AS9: =Elect!BT13 -> 216
A10: Cairo at The First Residence | B10: =B9+1 -> 9 | C10: 8 | D10: 2022 | F10: =Elect!J14 -> 5699 | G10: =Elect!K14 -> 4548 | H10: =Elect!Q14 -> 300 | I10: =Elect!S14 -> 140 | J10: =Elect!U14 -> 272 | K10: =Elect!W14 -> 0 | L10: =Elect!Y14 -> 4097.43 | M10: =Elect!AA14 -> 0 | N10: =Elect!AC14 -> 4008.39 | O10: =Elect!AE14 -> 1908 | P10: =Elect!AG14 -> 10.6 | Q10: =Elect!AI14 -> 1116.71 | R10: =Elect!AK14 -> 3870.06 | S10: =Elect!AM14 -> 121.37 | T10: =Elect!AP14 -> 295.3125 | U10: =Elect!AR14 -> 147 | V10: =Elect!AT14 -> 160 | W10: =Elect!AV14 -> 60 | X10: =Elect!AX14 -> 1044 | Y10: =Elect!AZ14 -> 0 | Z10: =Elect!BB14 -> 5140 | AA10: =Elect!BD14 -> 232 | AB10: =Elect!BF14 -> 130 | AC10: =Elect!BH14 -> 6623.75 | AD10: =Elect!BL14 -> 305 | AE10: =Elect!BN14 -> 1568 | AF10: =Elect!BP14 -> 117 | AG10: =Elect!BR14 -> 139 | AH10: =Boat!C12 -> 0 | AJ10: =Water!C15 -> 145 | AK10: =Water!E15 -> 191.4 | AL10: =Water!G15 -> 110.2 | AM10: =Boat!E12 -> 0 | AO10: =Gas!C15 -> 935.98 | AP10: =Gas!E15 -> 329 | AQ10: =Gas!G15 -> 91 | AR10: =Boat!G12 -> 0 | AS10: =Elect!BT14 -> 197
A11: Cairo at The First Residence | B11: =B10+1 -> 10 | C11: 8 | D11: 2022 | F11: =Elect!J15 -> 5652 | G11: =Elect!K15 -> 4783 | H11: =Elect!Q15 -> 570 | I11: =Elect!S15 -> 140 | J11: =Elect!U15 -> 287 | K11: =Elect!W15 -> 0 | L11: =Elect!Y15 -> 4097.43 | M11: =Elect!AA15 -> 0 | N11: =Elect!AC15 -> 4070.4 | O11: =Elect!AE15 -> 1792.46 | P11: =Elect!AG15 -> 10.07 | Q11: =Elect!AI15 -> 1116.18 | R11: =Elect!AK15 -> 3926.77 | S11: =Elect!AM15 -> 107.59 | T11: =Elect!AP15 -> 274.275 | U11: =Elect!AR15 -> 145 | V11: =Elect!AT15 -> 154 | W11: =Elect!AV15 -> 70 | X11: =Elect!AX15 -> 1114 | Y11: =Elect!AZ15 -> 0 | Z11: =Elect!BB15 -> 4800 | AA11: =Elect!BD15 -> 254 | AB11: =Elect!BF15 -> 111 | AC11: =Elect!BH15 -> 6686.3 | AD11: =Elect!BL15 -> 303 | AE11: =Elect!BN15 -> 1552 | AF11: =Elect!BP15 -> 114 | AG11: =Elect!BR15 -> 151 | AH11: =Boat!C13 -> 0 | AJ11: =Water!C16 -> 145 | AK11: =Water!E16 -> 197.2 | AL11: =Water!G16 -> 98.6 | AM11: =Boat!E13 -> 0 | AO11: =Gas!C16 -> 935.98 | AP11: =Gas!E16 -> 304.5 | AQ11: =Gas!G16 -> 78 | AR11: =Boat!G13 -> 0 | AS11: =Elect!BT15 -> 194
A12: Cairo at The First Residence | B12: =B11+1 -> 11 | C12: 8 | D12: 2022 | F12: =Elect!J16 -> 5348 | G12: =Elect!K16 -> 4688 | H12: =Elect!Q16 -> 600 | I12: =Elect!S16 -> 142 | J12: =Elect!U16 -> 276 | K12: =Elect!W16 -> 0 | L12: =Elect!Y16 -> 4420.73 | M12: =Elect!AA16 -> 0 | N12: =Elect!AC16 -> 4152.55 | O12: =Elect!AE16 -> 1814.72 | P12: =Elect!AG16 -> 10.6 | Q12: =Elect!AI16 -> 1126.25 | R12: =Elect!AK16 -> 3969.7 | S12: =Elect!AM16 -> 103.35 | T12: =Elect!AP16 -> 282.375 | U12: =Elect!AR16 -> 159 | V12: =Elect!AT16 -> 155 | W12: =Elect!AV16 -> 66 | X12: =Elect!AX16 -> 1136 | Y12: =Elect!AZ16 -> 0 | Z12: =Elect!BB16 -> 5456 | AA12: =Elect!BD16 -> 282 | AB12: =Elect!BF16 -> 65 | AC12: =Elect!BH16 -> 6685.85 | AD12: =Elect!BL16 -> 307 | AE12: =Elect!BN16 -> 1538 | AF12: =Elect!BP16 -> 109 | AG12: =Elect!BR16 -> 160 | AH12: =Boat!C14 -> 0 | AJ12: =Water!C17 -> 145 | AK12: =Water!E17 -> 193.33333 | AL12: =Water!G17 -> 106.33333 | AM12: =Boat!E14 -> 0 | AO12: =Gas!C17 -> 935.98 | AP12: =Gas!E17 -> 320.83333 | AQ12: =Gas!G17 -> 156.66667 | AR12: =Boat!G14 -> 0 | AS12: =Elect!BT16 -> 211
A13: Cairo at The First Residence | B13: =B12+1 -> 12 | C13: 8 | D13: 2022 | F13: =Elect!J17 -> 5312 | G13: =Elect!K17 -> 4664 | H13: =Elect!Q17 -> 600 | I13: =Elect!S17 -> 137 | J13: =Elect!U17 -> 268 | K13: =Elect!W17 -> 0 | L13: =Elect!Y17 -> 3893.38 | M13: =Elect!AA17 -> 0 | N13: =Elect!AC17 -> 3855.22 | O13: =Elect!AE17 -> 1807.3 | P13: =Elect!AG17 -> 10.07 | Q13: =Elect!AI17 -> 1123.6 | R13: =Elect!AK17 -> 3957.51 | S13: =Elect!AM17 -> 102.82 | T13: =Elect!AP17 -> 286.65 | U13: =Elect!AR17 -> 148 | V13: =Elect!AT17 -> 157 | W13: =Elect!AV17 -> 50 | X13: =Elect!AX17 -> 1118 | Y13: =Elect!AZ17 -> 0 | Z13: =Elect!BB17 -> 4705 | AA13: =Elect!BD17 -> 273 | AB13: =Elect!BF17 -> 65 | AC13: =Elect!BH17 -> 6782 | AD13: =Elect!BL17 -> 301 | AE13: =Elect!BN17 -> 1531 | AF13: =Elect!BP17 -> 109 | AG13: =Elect!BR17 -> 143 | AH13: =Boat!C15 -> 0 | AJ13: =Water!C18 -> 133.4 | AK13: =Water!E18 -> 166.26667 | AL13: =Water!G18 -> 102.46667 | AM13: =Boat!E15 -> 0 | AO13: =Gas!C18 -> 935.98 | AP13: =Gas!E18 -> 275.56667 | AQ13: =Gas!G18 -> 31.333333 | AR13: =Boat!G15 -> 0 | AS13: =Elect!BT17 -> 239
A14: Cairo at The First Residence | B14: =B13+1 -> 13 | C14: 8 | D14: 2022 | F14: =Elect!J18 -> 5606 | G14: =Elect!K18 -> 3705 | H14: =Elect!Q18 -> 300 | I14: =Elect!S18 -> 141 | J14: =Elect!U18 -> 271 | K14: =Elect!W18 -> 0 | L14: =Elect!Y18 -> 3895.5 | M14: =Elect!AA18 -> 0 | N14: =Elect!AC18 -> 3278.58 | O14: =Elect!AE18 -> 1720.91 | P14: =Elect!AG18 -> 10.07 | Q14: =Elect!AI18 -> 1052.05 | R14: =Elect!AK18 -> 3729.08 | S14: =Elect!AM18 -> 103.35 | T14: =Elect!AP18 -> 293.175 | U14: =Elect!AR18 -> 160 | V14: =Elect!AT18 -> 149 | W14: =Elect!AV18 -> 46 | X14: =Elect!AX18 -> 1012 | Y14: =Elect!AZ18 -> 0 | Z14: =Elect!BB18 -> 4878 | AA14: =Elect!BD18 -> 263 | AB14: =Elect!BF18 -> 65 | AC14: =Elect!BH18 -> 6339.85 | AD14: =Elect!BL18 -> 307 | AE14: =Elect!BN18 -> 1536 | AF14: =Elect!BP18 -> 111 | AG14: =Elect!BR18 -> 179 | AH14: =Boat!C16 -> 0 | AJ14: =Water!C19 -> 121.8 | AK14: =Water!E19 -> 162.4 | AL14: =Water!G19 -> 102.08 | AM14: =Boat!E16 -> 0 | AO14: =Gas!C19 -> 935.98 | AP14: =Gas!E19 -> 282.1 | AQ14: =Gas!G19 -> 92 | AR14: =Boat!G16 -> 0 | AS14: =Elect!BT18 -> 227
... A32: Cairo at The First Residence | B32: =B31+1 -> 31 | C32: 8 | D32: 2022 | F32: =Elect!J36 -> 4795.6667 | G32: =Elect!K36 -> 4615 | H32: =Elect!Q36 -> 600 | I32: =Elect!S36 -> 139 | J32: =Elect!U36 -> 267 | K32: =Elect!W36 -> 0 | L32: =Elect!Y36 -> 4433.6267 | M32: =Elect!AA36 -> 0 | N32: =Elect!AC36 -> 4636.44 | O32: =Elect!AE36 -> 0 | P32: =Elect!AG36 -> 1807.3 | Q32: =Elect!AI36 -> 1226.42 | R32: =Elect!AK36 -> 4120.75 | S32: =Elect!AM36 -> 129.67333 | T32: =Elect!AP36 -> 320.7375 | U32: =Elect!AR36 -> 139.33333 | V32: =Elect!AT36 -> 166 | W32: =Elect!AV36 -> 68 | X32: =Elect!AX36 -> 1166.1481 | Y32: =Elect!AZ36 -> 56.666667 | Z32: =Elect!BB36 -> 5179.3333 | AA32: =Elect!BD36 -> 221.33333 | AB32: =Elect!BF36 -> 70.333333 | AC32: =Elect!BH36 -> 6325.4667 | AD32: =Elect!BL36 -> 100.66667 | AE32: =Elect!BN36 -> 1488.3333 | AF32: =Elect!BP36 -> 87.666667 | AG32: =Elect!BR36 -> 147 | AH32: =Boat!C34 -> 0 | AJ32: =Water!C37 -> 102.46667 | AK32: =Water!E37 -> 143.06667 | AL32: =Water!G37 -> 106.72 | AM32: =Boat!E34 -> 0 | AO32: =Gas!C37 -> 1016.54 | AP32: =Gas!E37 -> 261.72222 | AQ32: =Gas!G37 -> 93 | AR32: =Boat!G34 -> 0 | AS32: =Elect!BT36 -> 134

Sheet Boat
B1: Electricity | D1: Water | F1: Gas
B2: Read | C2: Cons | D2: Read | E2: Cons | F2: Read | G2: Cons
B3: 0 | D3: 0 | F3: 0
A4: 1 | B4: 0 | C4: =B4-B3 -> 0 | D4: 0 | E4: =D4-D3 -> 0 | F4: 0 | G4: =F4-F3 -> 0
A5: 2 | B5: 0 | C5: =B5-B4 -> 0 | D5: 0 | E5: =D5-D4 -> 0 | F5: 0 | G5: =F5-F4 -> 0
A6: 3 | B6: 0 | C6: =B6-B5 -> 0 | D6: 0 | E6: =D6-D5 -> 0 | F6: 0 | G6: =F6-F5 -> 0
A7: 4 | B7: 0 | C7: =B7-B6 -> 0 | D7: 0 | E7: =D7-D6 -> 0 | F7: 0 | G7: =F7-F6 -> 0
A8: 5 | B8: 0 | C8: =B8-B7 -> 0 | D8: 0 | E8: =D8-D7 -> 0 | F8: 0 | G8: =F8-F7 -> 0
A9: 6 | B9: 0 | C9: =B9-B8 -> 0 | D9: 0 | E9: =D9-D8 -> 0 | F9: 0 | G9: =F9-F8 -> 0
A10: 7 | B10: 0 | C10: =B10-B9 -> 0 | D10: 0 | E10: =D10-D9 -> 0 | F10: 0 | G10: =F10-F9 -> 0
A11: 8 | B11: 0 | C11: =B11-B10 -> 0 | D11: 0 | E11: =D11-D10 -> 0 | F11: 0 | G11: =F11-F10 -> 0
A12: 9 | B12: 0 | C12: =B12-B11 -> 0 | D12: 0 | E12: =D12-D11 -> 0 | F12: 0 | G12: =F12-F11 -> 0
A13: 10 | B13: 0 | C13: =B13-B12 -> 0 | D13: 0 | E13: =D13-D12 -> 0 | F13: 0 | G13: =F13-F12 -> 0
A14: 11 | B14: 0 | C14: =B14-B13 -> 0 | D14: 0 | E14: =D14-D13 -> 0 | F14: 0 | G14: =F14-F13 -> 0
A15: 12 | B15: 0 | C15: =B15-B14 -> 0 | D15: 0 | E15: =D15-D14 -> 0 | F15: 0 | G15: =F15-F14 -> 0
... A34: 31 | B34: 0 | C34: =B34-B33 -> 0 | D34: 0 | E34: =D34-D33 -> 0 | F34: 0 | G34: =F34-F33 -> 0
A35: Sum | C35: =SUM(C4:C34) -> 0 | E35: =SUM(E4:E34) -> 0 | G35: =SUM(G4:G34) -> 0

Sheet Elect
A1: 44774 | M1: Electricity | BP1: Gourmandise UP | BR1: 1.6 | BS1: Power Taxes | BU1: Max Demand | BW1: 500 | BX1: Electricity UP | BZ1: 1.15
BS2: Light Taxes | BU2: PF Penalty | BX2: Max. Demand UP | BZ2: 30
A3: Date | B3: COUNTER (1) | D3: MD | F3: KVAR | H3: n | I3: Guest Rooms Consumption | R3: Casino Consumption | V3: Plant Room Shared Loads | AO3: To Be Charged By First Arabian | BK3: From Main Panel G2 | BS3: Total Consumption. | BT3: No. Of | BU3: KWH/ | BV3: No. Of | BW3: KWH/ | BX3: Total Cost | BY3: L.E\ | BZ3: L.E\
B4: Reading | C4: Consp. F: *800 | D4: Reading | E4: Consp F: 80 | F4: Reading | G4: Consp. F:*10 | I4: Main Feeder | J4: Consp | K4: T2+T8 | L4: Trans T2 | M4: Consp | N4: Trans T8 | O4: Consp | P4: La Gourmandize | Q4: Consp *30 | R4: Casino 3rd floor EM | S4: Consp | T4: Casino 3rd floor Normal | U4: Consp | V4: Chiller 1 | W4: Consp 53% | X4: Chiller 2 | Y4: Consp 53% | Z4: Chiller 3 | AA4: Consp 53% | AB4: Chiller 4 | AC4: Consp 53% | AD4: Chiller 5 | AE4: Consp 53% | AF4: Chiller 6 | AG4: Consp 53% | AH4: Cooling Towers | AI4: Consp 53% | AJ4: Chiller Pumps | AK4: Consp 53% | AL4: Cooling Tower Pumps | AM4: Consp 53% | AN4: Total Plant Room Consp | AO4: Fiber Chiller (N24) | AP4: Consp | AQ4: Mall Ceiling light (N4) | AR4: Consp | AS4: LG Bakery (N2) | AT4: Consp | AU4: LG Bakery light ( Old lockers ) | AV4: Consp | AW4: MCCR1 | AX4: Consp | AY4: Children Swimming pool | AZ4: Consp | BA4: DPH1 | BB4: Consp | BC4: Guest Rooms Emergency | BD4: Consp | BE4: Hotel Hoods | BF4: Consp | BG4: Main G2 | BH4: Consp | BI4: Total Consp From First Arabian | BJ4: First Arabian Charge Back | BK4: Old Casino Emergency | BL4: Consp | BM4: L / A | BN4: Consp | BO4: L / B | BP4: Consp | BQ4: L / C | BR4: Consp | BT4: Rooms | BU4: room | BV4: guest | BW4: guest | BY4: Room | BZ4: Guest
A5: Last Month Reading | I5: 25036755 | J5: =IF(I5>=I4,I5-I4,0) -> 0 | K5: =M5+O5 -> 0 | L5: 34862 | M5: =IF(L5>=L4,L5-L4,0) -> 0 | N5: 55208.667 | O5: =IF(N5>=N4,N5-N4,0) -> 0 | P5: 224850.27 | Q5: =IF(P5>=P4,P5-P4,0)*30 -> 0 | R5: 208881.5 | S5: =IF(R5>=R4,R5-R4,0) -> 0 | T5: 380814.5 | U5: =IF(T5>=T4,T5-T4,0) -> 0 | V5: 301819.2 | W5: =IF(V5>=V4,V5-V4,0)*0.53 -> 0 | X5: 459455 | Y5: =IF(X5>=X4,X5-X4,0)*0.53 -> 0 | Z5: 502152 | AA5: =IF(Z5>=Z4,Z5-Z4,0)*0.53 -> 0 | AB5: 818308.5 | AC5: =IF(AB5>=AB4,AB5-AB4,0)*0.53 -> 0 | AD5: 764212 | AE5: =IF(AD5>=AD4,AD5-AD4,0)*0.53 -> 0 | AF5: 899010.5 | AG5: =IF(AF5>=AF4,AF5-AF4,0)*0.53 -> 0 | AH5: 235163.27 | AI5: =IF(AH5>=AH4,AH5-AH4,0)*0.53 -> 0 | AJ5: 742785 | AK5: =IF(AJ5>=AJ4,AJ5-AJ4,0)*0.53 -> 0 | AL5: 541391.13 | AM5: =IF(AL5>=AL4,AL5-AL4,0)*0.53 -> 0 | AN5: =W5+Y5+AA5+AC5+AE5+AG5+AI5+AK5+AM5 -> 0 | AO5: 7889570 | AP5: =IF(AO5>=AO4,AO5-AO4,0)*0.1125 -> 0 | AQ5: 727713 | AR5: =IF(AQ5>=AQ4,AQ5-AQ4,0) -> 0 | AS5: 995039.8 | AT5: =IF(AS5>=AS4,AS5-AS4,0) -> 0 | AU5: 819398.7 | AV5: =IF(AU5>=AU4,AU5-AU4,0) -> 0 | AW5: 2765690.5 | AX5: =IF(AW5>=AW4,AW5-AW4,0) -> 0 | AY5: 229733 | AZ5: =IF(AY5>=AY4,AY5-AY4,0) -> 0 | BA5: 20173362 | BB5: =IF(BA5>=BA4,BA5-BA4,0) -> 0 | BC5: 609145.6 | BD5: =IF(BC5>=BC4,BC5-BC4,0) -> 0 | BE5: 37173.389 | BF5: =IF(BE5>=BE4,BE5-BE4,0) -> 0 | BG5: 25274117 | BH5: =IF(BG5>=BG4,BG5-BG4,0)-(0.45*BN5)-(0.45*BP5)-BR5 -> 0 | BI5: =AP5+AR5+AT5+AV5+AX5+AZ5+BB5+BD5+BF5+BH5 -> 0 | BJ5: =BI5+AN5 -> 0 | BK5: 1464195.9 | BL5: =IF(BK5>=BK4,BK5-BK4,0) -> 0 | BM5: 4139722.6 | BN5: =IF(BM5>=BM4,BM5-BM4,0) -> 0 | BO5: 436020 | BP5: =IF(BO5>=BO4,BO5-BO4,0) -> 0 | BQ5: 544778.5 | BR5: =IF(BQ5>=BQ4,BQ5-BQ4,0) -> 0
A6: 1 | C6: =IF(+B6-B5>0,B6-B5,(B6-B5)>0)*800 -> 0 | E6: =IF(+D6-D5>0,D6-D5,(D6-D5)>0)*80 -> 0 | G6: =IF(+F6-F5>0,F6-F5,(F6-F5)>0)*10 -> 0 | H6: 56 | I6: 25043306 | J6: =IF(I6>=I5,I6-I5,0) -> 6551.3333 | K6: =M6+O6 -> 5401.3333 | L6: 36944 | M6: =IF(L6>=L5,L6-L5,0) -> 2082 | N6: 58528 | O6: =IF(N6>=N5,N6-N5,0) -> 3319.3333 | P6: 224869 | Q6: =IF(P6>=P5,P6-P5,0)*30 -> 562 | R6: 209022 | S6: =IF(R6>=R5,R6-R5,0) -> 140.5 | T6: 381109 | U6: =IF(T6>=T5,T6-T5,0) -> 294.5 | V6: 297550 | W6: =IF(V6>=V5,V6-V5,0)*0.53 -> 0 | X6: 461770 | Y6: =IF(X6>=X5,X6-X5,0)*0.53 -> 1226.95 | Z6: 515121 | AA6: =IF(Z6>=Z5,Z6-Z5,0)*0.53 -> 6873.57 | AB6: 824325 | AC6: =IF(AB6>=AB5,AB6-AB5,0)*0.53 -> 3188.745 | AD6: 764212 | AE6: =IF(AD6>=AD5,AD6-AD5,0)*0.53 -> 0 | AF6: 904339 | AG6: =IF(AF6>=AF5,AF6-AF5,0)*0.53 -> 2824.105 | AH6: 237367 | AI6: =IF(AH6>=AH5,AH6-AH5,0)*0.53 -> 1167.9787 | AJ6: 750301 | AK6: =IF(AJ6>=AJ5,AJ6-AJ5,0)*0.53 -> 3983.48 | AL6: 541622 | AM6: =IF(AL6>=AL5,AL6-AL5,0)*0.53 -> 122.35933 | AN6: =W6+Y6+AA6+AC6+AE6+AG6+AI6+AK6+AM6 -> 19387.188 | AO6: 7892004 | AP6: =IF(AO6>=AO5,AO6-AO5,0)*0.1125 -> 273.825 | AQ6: 727878 | AR6: =IF(AQ6>=AQ5,AQ6-AQ5,0) -> 165 | AS6: 995213 | AT6: =IF(AS6>=AS5,AS6-AS5,0) -> 173.2 | AU6: 819455 | AV6: =IF(AU6>=AU5,AU6-AU5,0) -> 56.3 | AW6: 2766771 | AX6: =IF(AW6>=AW5,AW6-AW5,0) -> 1080.5 | AY6: 229733 | AZ6: =IF(AY6>=AY5,AY6-AY5,0) -> 0 | BA6: 20177744 | BB6: =IF(BA6>=BA5,BA6-BA5,0) -> 4381.7 | BC6: 609415 | BD6: =IF(BC6>=BC5,BC6-BC5,0) -> 269.4 | BE6: 37256 | BF6: =IF(BE6>=BE5,BE6-BE5,0) -> 82.611111 | BG6: 25281712 | BH6: =IF(BG6>=BG5,BG6-BG5,0)-(0.45*BN6)-(0.45*BP6)-BR6 -> 6613.12 | BI6: =AP6+AR6+AT6+AV6+AX6+AZ6+BB6+BD6+BF6+BH6 -> 13095.656 | BJ6: =BI6+AN6 -> 32482.844 | BK6: 1464586 | BL6: =IF(BK6>=BK5,BK6-BK5,0) -> 390.1 | BM6: 4141431 | BN6: =IF(BM6>=BM5,BM6-BM5,0) -> 1708.4 | BO6: 436128 | BP6: =IF(BO6>=BO5,BO6-BO5,0) -> 108 | BQ6: 544943 | BR6: =IF(BQ6>=BQ5,BQ6-BQ5,0) -> 164.5 | BS6: =J6+Q6+AN6+BI6 -> 39596.177 | BT6: 158 | BU6: =IF(BS6>0,BS6/BT5,0) -> #DIV/0! | BW6: =IF(BS6>0,BS6/BV6,0) -> #DIV/0! | BX6: =((BS6-Q6)*$BZ$1)+(Q6*$BR$1) -> 45788.504 | BY6: =IF(BX6>0,BX6/BT5,0) -> #DIV/0! | BZ6: =IF(BX6>0,BX6/BV6,0) -> #DIV/0!
A7: 2 | I7: 25049224 | J7: =IF(I7>=I6,I7-I6,0) -> 5918 | K7: =M7+O7 -> 5016 | L7: 39008 | M7: =IF(L7>=L6,L7-L6,0) -> 2064 | N7: 61480 | O7: =IF(N7>=N6,N7-N6,0) -> 2952 | P7: 224885 | Q7: =IF(P7>=P6,P7-P6,0)*30 -> 480 | R7: 209165 | S7: =IF(R7>=R6,R7-R6,0) -> 143 | T7: 381390 | U7: =IF(T7>=T6,T7-T6,0) -> 281 | V7: 297550 | W7: =IF(V7>=V6,V7-V6,0)*0.53 -> 0 | X7: 461770 | Y7: =IF(X7>=X6,X7-X6,0)*0.53 -> 0 | Z7: 523123 | AA7: =IF(Z7>=Z6,Z7-Z6,0)*0.53 -> 4241.06 | AB7: 831831 | AC7: =IF(AB7>=AB6,AB7-AB6,0)*0.53 -> 3978.18 | AD7: 765827 | AE7: =IF(AD7>=AD6,AD7-AD6,0)*0.53 -> 855.95 | AF7: 904362 | AG7: =IF(AF7>=AF6,AF7-AF6,0)*0.53 -> 12.19 | AH7: 239537 | AI7: =IF(AH7>=AH6,AH7-AH6,0)*0.53 -> 1150.1 | AJ7: 757569 | AK7: =IF(AJ7>=AJ6,AJ7-AJ6,0)*0.53 -> 3852.04 | AL7: 541854 | AM7: =IF(AL7>=AL6,AL7-AL6,0)*0.53 -> 122.96 | AN7: =W7+Y7+AA7+AC7+AE7+AG7+AI7+AK7+AM7 -> 14212.48 | AO7: 7894641 | AP7: =IF(AO7>=AO6,AO7-AO6,0)*0.1125 -> 296.6625 | AQ7: 728055 | AR7: =IF(AQ7>=AQ6,AQ7-AQ6,0) -> 177 | AS7: 995381 | AT7: =IF(AS7>=AS6,AS7-AS6,0) -> 168 | AU7: 819519 | AV7: =IF(AU7>=AU6,AU7-AU6,0) -> 64 | AW7: 2767813 | AX7: =IF(AW7>=AW6,AW7-AW6,0) -> 1042 | AY7: 229733 | AZ7: =IF(AY7>=AY6,AY7-AY6,0) -> 0 | BA7: 20182849 | BB7: =IF(BA7>=BA6,BA7-BA6,0) -> 5105 | BC7: 609678 | BD7: =IF(BC7>=BC6,BC7-BC6,0) -> 263 | BE7: 37311 | BF7: =IF(BE7>=BE6,BE7-BE6,0) -> 55 | BG7: 25289109 | BH7: =IF(BG7>=BG6,BG7-BG6,0)-(0.45*BN7)-(0.45*BP7)-BR7 -> 6486.85 | BI7: =AP7+AR7+AT7+AV7+AX7+AZ7+BB7+BD7+BF7+BH7 -> 13657.513 | BJ7: =BI7+AN7 -> 27869.993 | BK7: 1464899 | BL7: =IF(BK7>=BK6,BK7-BK6,0) -> 313 | BM7: 4143007 | BN7: =IF(BM7>=BM6,BM7-BM6,0) -> 1576 | BO7: 436239 | BP7: =IF(BO7>=BO6,BO7-BO6,0) -> 111 | BQ7: 545094 | BR7: =IF(BQ7>=BQ6,BQ7-BQ6,0) -> 151 | BS7: =J7+Q7+AN7+BI7 -> 34267.993 | BT7: 162 | BU7: =IF(BS7>0,BS7/BT6,0) -> 216.88603 | BW7: =IF(BS7>0,BS7/BV7,0) -> #DIV/0! | BX7: =((BS7-Q7)*$BZ$1)+(Q7*$BR$1) -> 39624.191 | BY7: =IF(BX7>0,BX7/BT6,0) -> 250.78602 | BZ7: =IF(BX7>0,BX7/BV7,0) -> #DIV/0!
A8: 3 | C8: =IF(+B8-B7>0,B8-B7,(B8-B7)>0)*800 -> 0 | E8: =IF(+D8-D7>0,D8-D7,(D8-D7)>0)*80 -> 0 | G8: =IF(+F8-F7>0,F8-F7,(F8-F7)>0)*10 -> 0 | H8: 57 | I8: 25054987 | J8: =IF(I8>=I7,I8-I7,0) -> 5763 | K8: =M8+O8 -> 4794 | L8: 40968 | M8: =IF(L8>=L7,L8-L7,0) -> 1960 | N8: 64314 | O8: =IF(N8>=N7,N8-N7,0) -> 2834 | P8: 224903 | Q8: =IF(P8>=P7,P8-P7,0)*30 -> 540 | R8: 209304 | S8: =IF(R8>=R7,R8-R7,0) -> 139 | T8: 381655 | U8: =IF(T8>=T7,T8-T7,0) -> 265 | V8: 297550 | W8: =IF(V8>=V7,V8-V7,0)*0.53 -> 0 | X8: 466376 | Y8: =IF(X8>=X7,X8-X7,0)*0.53 -> 2441.18 | Z8: 530489 | AA8: =IF(Z8>=Z7,Z8-Z7,0)*0.53 -> 3903.98 | AB8: 833938 | AC8: =IF(AB8>=AB7,AB8-AB7,0)*0.53 -> 1116.71 | AD8: 768999 | AE8: =IF(AD8>=AD7,AD8-AD7,0)*0.53 -> 1681.16 | AF8: 904384 | AG8: =IF(AF8>=AF7,AF8-AF7,0)*0.53 -> 11.66 | AH8: 241584 | AI8: =IF(AH8>=AH7,AH8-AH7,0)*0.53 -> 1084.91 | AJ8: 764514 | AK8: =IF(AJ8>=AJ7,AJ8-AJ7,0)*0.53 -> 3680.85 | AL8: 542058 | AM8: =IF(AL8>=AL7,AL8-AL7,0)*0.53 -> 108.12 | AN8: =W8+Y8+AA8+AC8+AE8+AG8+AI8+AK8+AM8 -> 14028.57 | AO8: 7897133 | AP8: =IF(AO8>=AO7,AO8-AO7,0)*0.1125 -> 280.35 | AQ8: 728235 | AR8: =IF(AQ8>=AQ7,AQ8-AQ7,0) -> 180 | AS8: 995530 | AT8: =IF(AS8>=AS7,AS8-AS7,0) -> 149 | AU8: 819576 | AV8: =IF(AU8>=AU7,AU8-AU7,0) -> 57 | AW8: 2768810 | AX8: =IF(AW8>=AW7,AW8-AW7,0) -> 997 | AY8: 229733 | AZ8: =IF(AY8>=AY7,AY8-AY7,0) -> 0 | BA8: 20187420 | BB8: =IF(BA8>=BA7,BA8-BA7,0) -> 4571 | BC8: 609961 | BD8: =IF(BC8>=BC7,BC8-BC7,0) -> 283 | BE8: 37366 | BF8: =IF(BE8>=BE7,BE8-BE7,0) -> 55 | BG8: 25296209 | BH8: =IF(BG8>=BG7,BG8-BG7,0)-(0.45*BN8)-(0.45*BP8)-BR8 -> 6231.5 | BI8: =AP8+AR8+AT8+AV8+AX8+AZ8+BB8+BD8+BF8+BH8 -> 12803.85 | BJ8: =BI8+AN8 -> 26832.42 | BK8: 1465203 | BL8: =IF(BK8>=BK7,BK8-BK7,0) -> 304 | BM8: 4144533 | BN8: =IF(BM8>=BM7,BM8-BM7,0) -> 1526 | BO8: 436343 | BP8: =IF(BO8>=BO7,BO8-BO7,0) -> 104 | BQ8: 545229 | BR8: =IF(BQ8>=BQ7,BQ8-BQ7,0) -> 135 | BS8: =J8+Q8+AN8+BI8 -> 33135.42 | BT8: 173 | BU8: =IF(BS8>0,BS8/BT7,0) -> 204.53963 | BW8: =IF(BS8>0,BS8/BV8,0) -> #DIV/0! | BX8: =((BS8-Q8)*$BZ$1)+(Q8*$BR$1) -> 38348.733 | BY8: =IF(BX8>0,BX8/BT7,0) -> 236.72057 | BZ8: =IF(BX8>0,BX8/BV8,0) -> #DIV/0!
A9: 4 | C9: =IF(+B9-B8>0,B9-B8,(B9-B8)>0)*800 -> 0 | E9: =IF(+D9-D8>0,D9-D8,(D9-D8)>0)*80 -> 0 | G9: =IF(+F9-F8>0,F9-F8,(F9-F8)>0)*10 -> 0 | I9: 25060334 | J9: =IF(I9>=I8,I9-I8,0) -> 5347 | K9: =M9+O9 -> 4913 | L9: 42903 | M9: =IF(L9>=L8,L9-L8,0) -> 1935 | N9: 67292 | O9: =IF(N9>=N8,N9-N8,0) -> 2978 | P9: 224921 | Q9: =IF(P9>=P8,P9-P8,0)*30 -> 540 | R9: 209441 | S9: =IF(R9>=R8,R9-R8,0) -> 137 | T9: 381926 | U9: =IF(T9>=T8,T9-T8,0) -> 271 | V9: 297550 | W9: =IF(V9>=V8,V9-V8,0)*0.53 -> 0 | X9: 473381 | Y9: =IF(X9>=X8,X9-X8,0)*0.53 -> 3712.65 | Z9: 537894 | AA9: =IF(Z9>=Z8,Z9-Z8,0)*0.53 -> 3924.65 | AB9: 833938 | AC9: =IF(AB9>=AB8,AB9-AB8,0)*0.53 -> 0 | AD9: 772243 | AE9: =IF(AD9>=AD8,AD9-AD8,0)*0.53 -> 1719.32 | AF9: 904400 | AG9: =IF(AF9>=AF8,AF9-AF8,0)*0.53 -> 8.48 | AH9: 243686 | AI9: =IF(AH9>=AH8,AH9-AH8,0)*0.53 -> 1114.06 | AJ9: 771667 | AK9: =IF(AJ9>=AJ8,AJ9-AJ8,0)*0.53 -> 3791.09 | AL9: 542288 | AM9: =IF(AL9>=AL8,AL9-AL8,0)*0.53 -> 121.9 | AN9: =W9+Y9+AA9+AC9+AE9+AG9+AI9+AK9+AM9 -> 14392.15 | AO9: 7899770 | AP9: =IF(AO9>=AO8,AO9-AO8,0)*0.1125 -> 296.6625 | AQ9: 728402 | AR9: =IF(AQ9>=AQ8,AQ9-AQ8,0) -> 167 | AS9: 995696 | AT9: =IF(AS9>=AS8,AS9-AS8,0) -> 166 | AU9: 819636 | AV9: =IF(AU9>=AU8,AU9-AU8,0) -> 60 | AW9: 2769916 | AX9: =IF(AW9>=AW8,AW9-AW8,0) -> 1106 | AY9: 229733 | AZ9: =IF(AY9>=AY8,AY9-AY8,0) -> 0 | BA9: 20192315 | BB9: =IF(BA9>=BA8,BA9-BA8,0) -> 4895 | BC9: 610242 | BD9: =IF(BC9>=BC8,BC9-BC8,0) -> 281 | BE9: 37409 | BF9: =IF(BE9>=BE8,BE9-BE8,0) -> 43 | BG9: 25303448 | BH9: =IF(BG9>=BG8,BG9-BG8,0)-(0.45*BN9)-(0.45*BP9)-BR9 -> 6368.85 | BI9: =AP9+AR9+AT9+AV9+AX9+AZ9+BB9+BD9+BF9+BH9 -> 13383.513 | BJ9: =BI9+AN9 -> 27775.662 | BK9: 1465504 | BL9: =IF(BK9>=BK8,BK9-BK8,0) -> 301 | BM9: 4146052 | BN9: =IF(BM9>=BM8,BM9-BM8,0) -> 1519 | BO9: 436451 | BP9: =IF(BO9>=BO8,BO9-BO8,0) -> 108 | BQ9: 545367 | BR9: =IF(BQ9>=BQ8,BQ9-BQ8,0) -> 138 | BS9: =J9+Q9+AN9+BI9 -> 33662.663 | BT9: 202 | BU9: =IF(BS9>0,BS9/BT8,0) -> 194.58186 | BW9: =IF(BS9>0,BS9/BV9,0) -> #DIV/0! | BX9: =((BS9-Q9)*$BZ$1)+(Q9*$BR$1) -> 38955.062 | BY9: =IF(BX9>0,BX9/BT8,0) -> 225.17377 | BZ9: =IF(BX9>0,BX9/BV9,0) -> #DIV/0!
A10: 5 | C10: =IF(+B10-B9>0,B10-B9,(B10-B9)>0)*800 -> 0 | E10: =IF(+D10-D9>0,D10-D9,(D10-D9)>0)*80 -> 0 | G10: =IF(+F10-F9>0,F10-F9,(F10-F9)>0)*10 -> 0 | H10: 58 | I10: 25068804 | J10: =IF(I10>=I9,I10-I9,0) -> 8470 | K10: =M10+O10 -> 5034 | L10: 44855 | M10: =IF(L10>=L9,L10-L9,0) -> 1952 | N10: 70374 | O10: =IF(N10>=N9,N10-N9,0) -> 3082 | P10: 224930 | Q10: =IF(P10>=P9,P10-P9,0)*30 -> 270 | R10: 209581 | S10: =IF(R10>=R9,R10-R9,0) -> 140 | T10: 382199 | U10: =IF(T10>=T9,T10-T9,0) -> 273 | V10: 297550 | W10: =IF(V10>=V9,V10-V9,0)*0.53 -> 0 | X10: 480701 | Y10: =IF(X10>=X9,X10-X9,0)*0.53 -> 3879.6 | Z10: 545465 | AA10: =IF(Z10>=Z9,Z10-Z9,0)*0.53 -> 4012.63 | AB10: 833938 | AC10: =IF(AB10>=AB9,AB10-AB9,0)*0.53 -> 0 | AD10: 775388 | AE10: =IF(AD10>=AD9,AD10-AD9,0)*0.53 -> 1666.85 | AF10: 904420 | AG10: =IF(AF10>=AF9,AF10-AF9,0)*0.53 -> 10.6 | AH10: 245817 | AI10: =IF(AH10>=AH9,AH10-AH9,0)*0.53 -> 1129.43 | AJ10: 778934 | AK10: =IF(AJ10>=AJ9,AJ10-AJ9,0)*0.53 -> 3851.51 | AL10: 542516 | AM10: =IF(AL10>=AL9,AL10-AL9,0)*0.53 -> 120.84 | AN10: =W10+Y10+AA10+AC10+AE10+AG10+AI10+AK10+AM10 -> 14671.46 | AO10: 7902195 | AP10: =IF(AO10>=AO9,AO10-AO9,0)*0.1125 -> 272.8125 | AQ10: 728574 | AR10: =IF(AQ10>=AQ9,AQ10-AQ9,0) -> 172 | AS10: 995868 | AT10: =IF(AS10>=AS9,AS10-AS9,0) -> 172 | AU10: 819690 | AV10: =IF(AU10>=AU9,AU10-AU9,0) -> 54 | AW10: 2770927 | AX10: =IF(AW10>=AW9,AW10-AW9,0) -> 1011 | AY10: 229733 | AZ10: =IF(AY10>=AY9,AY10-AY9,0) -> 0 | BA10: 20197337 | BB10: =IF(BA10>=BA9,BA10-BA9,0) -> 5022 | BC10: 610529 | BD10: =IF(BC10>=BC9,BC10-BC9,0) -> 287 | BE10: 37466 | BF10: =IF(BE10>=BE9,BE10-BE9,0) -> 57 | BG10: 25310693 | BH10: =IF(BG10>=BG9,BG10-BG9,0)-(0.45*BN10)-(0.45*BP10)-BR10 -> 6376.45 | BI10: =AP10+AR10+AT10+AV10+AX10+AZ10+BB10+BD10+BF10+BH10 -> 13424.263 | BJ10: =BI10+AN10 -> 28095.723 | BK10: 1465810 | BL10: =IF(BK10>=BK9,BK10-BK9,0) -> 306 | BM10: 4147561 | BN10: =IF(BM10>=BM9,BM10-BM9,0) -> 1509 | BO10: 436561 | BP10: =IF(BO10>=BO9,BO10-BO9,0) -> 110 | BQ10: 545507 | BR10: =IF(BQ10>=BQ9,BQ10-BQ9,0) -> 140 | BS10: =J10+Q10+AN10+BI10 -> 36835.723 | BT10: 216 | BU10: =IF(BS10>0,BS10/BT9,0) -> 182.35506 | BW10: =IF(BS10>0,BS10/BV10,0) -> #DIV/0! | BX10: =((BS10-Q10)*$BZ$1)+(Q10*$BR$1) -> 42482.581 | BY10: =IF(BX10>0,BX10/BT9,0) -> 210.30981 | BZ10: =IF(BX10>0,BX10/BV10,0) -> #DIV/0!
A11: 6 | C11: =IF(+B11-B10>0,B11-B10,(B11-B10)>0)*800 -> 0 | E11: =IF(+D11-D10>0,D11-D10,(D11-D10)>0)*80 -> 0 | G11: =IF(+F11-F10>0,F11-F10,(F11-F10)>0)*10 -> 0 | I11: 25070663 | J11: =IF(I11>=I10,I11-I10,0) -> 1859 | K11: =M11+O11 -> 4423 | L11: 46770 | M11: =IF(L11>=L10,L11-L10,0) -> 1915 | N11: 72882 | O11: =IF(N11>=N10,N11-N10,0) -> 2508 | P11: 224955 | Q11: =IF(P11>=P10,P11-P10,0)*30 -> 750 | R11: 209720 | S11: =IF(R11>=R10,R11-R10,0) -> 139 | T11: 382478 | U11: =IF(T11>=T10,T11-T10,0) -> 279 | V11: 297550 | W11: =IF(V11>=V10,V11-V10,0)*0.53 -> 0 | X11: 488200 | Y11: =IF(X11>=X10,X11-X10,0)*0.53 -> 3974.47 | Z11: 553112 | AA11: =IF(Z11>=Z10,Z11-Z10,0)*0.53 -> 4052.91 | AB11: 833938 | AC11: =IF(AB11>=AB10,AB11-AB10,0)*0.53 -> 0 | AD11: 778579 | AE11: =IF(AD11>=AD10,AD11-AD10,0)*0.53 -> 1691.23 | AF11: 904439 | AG11: =IF(AF11>=AF10,AF11-AF10,0)*0.53 -> 10.07 | AH11: 247977 | AI11: =IF(AH11>=AH10,AH11-AH10,0)*0.53 -> 1144.8 | AJ11: 786305 | AK11: =IF(AJ11>=AJ10,AJ11-AJ10,0)*0.53 -> 3906.63 | AL11: 542738 | AM11: =IF(AL11>=AL10,AL11-AL10,0)*0.53 -> 117.66 | AN11: =W11+Y11+AA11+AC11+AE11+AG11+AI11+AK11+AM11 -> 14897.77 | AO11: 7904669 | AP11: =IF(AO11>=AO10,AO11-AO10,0)*0.1125 -> 278.325 | AQ11: 728737 | AR11: =IF(AQ11>=AQ10,AQ11-AQ10,0) -> 163 | AS11: 996033 | AT11: =IF(AS11>=AS10,AS11-AS10,0) -> 165 | AU11: 819741 | AV11: =IF(AU11>=AU10,AU11-AU10,0) -> 51 | AW11: 2771904 | AX11: =IF(AW11>=AW10,AW11-AW10,0) -> 977 | AY11: 229733 | AZ11: =IF(AY11>=AY10,AY11-AY10,0) -> 0 | BA11: 20202407 | BB11: =IF(BA11>=BA10,BA11-BA10,0) -> 5070 | BC11: 610775 | BD11: =IF(BC11>=BC10,BC11-BC10,0) -> 246 | BE11: 37519 | BF11: =IF(BE11>=BE10,BE11-BE10,0) -> 53 | BG11: 25317810 | BH11: =IF(BG11>=BG10,BG11-BG10,0)-(0.45*BN11)-(0.45*BP11)-BR11 -> 6234.45 | BI11: =AP11+AR11+AT11+AV11+AX11+AZ11+BB11+BD11+BF11+BH11 -> 13237.775 | BJ11: =BI11+AN11 -> 28135.545 | BK11: 1466113 | BL11: =IF(BK11>=BK10,BK11-BK10,0) -> 303 | BM11: 4149074 | BN11: =IF(BM11>=BM10,BM11-BM10,0) -> 1513 | BO11: 436667 | BP11: =IF(BO11>=BO10,BO11-BO10,0) -> 106 | BQ11: 545661 | BR11: =IF(BQ11>=BQ10,BQ11-BQ10,0) -> 154 | BS11: =J11+Q11+AN11+BI11 -> 30744.545 | BT11: 224 | BU11: =IF(BS11>0,BS11/BT10,0) -> 142.33586 | BW11: =IF(BS11>0,BS11/BV11,0) -> #DIV/0! | BX11: =((BS11-Q11)*$BZ$1)+(Q11*$BR$1) -> 35693.727 | BY11: =IF(BX11>0,BX11/BT10,0) -> 165.24873 | BZ11: =IF(BX11>0,BX11/BV11,0) -> #DIV/0!
A12: 7 | C12: =IF(+B12-B11>0,B12-B11,(B12-B11)>0)*800 -> 0 | E12: =IF(+D12-D11>0,D12-D11,(D12-D11)>0)*80 -> 0 | G12: =IF(+F12-F11>0,F12-F11,(F12-F11)>0)*10 -> 0 | H12: 59 | I12: 25076115 | J12: =IF(I12>=I11,I12-I11,0) -> 5452 | K12: =M12+O12 -> 4425 | L12: 48712 | M12: =IF(L12>=L11,L12-L11,0) -> 1942 | N12: 75365 | O12: =IF(N12>=N11,N12-N11,0) -> 2483 | P12: 224973 | Q12: =IF(P12>=P11,P12-P11,0)*30 -> 540 | R12: 209857 | S12: =IF(R12>=R11,R12-R11,0) -> 137 | T12: 382748 | U12: =IF(T12>=T11,T12-T11,0) -> 270 | V12: 297550 | W12: =IF(V12>=V11,V12-V11,0)*0.53 -> 0 | X12: 495485 | Y12: =IF(X12>=X11,X12-X11,0)*0.53 -> 3861.05 | Z12: 555152 | AA12: =IF(Z12>=Z11,Z12-Z11,0)*0.53 -> 1081.2 | AB12: 839150 | AC12: =IF(AB12>=AB11,AB12-AB11,0)*0.53 -> 2762.36 | AD12: 781616 | AE12: =IF(AD12>=AD11,AD12-AD11,0)*0.53 -> 1609.61 | AF12: 904683 | AG12: =IF(AF12>=AF11,AF12-AF11,0)*0.53 -> 129.32 | AH12: 250060 | AI12: =IF(AH12>=AH11,AH12-AH11,0)*0.53 -> 1103.99 | AJ12: 793503 | AK12: =IF(AJ12>=AJ11,AJ12-AJ11,0)*0.53 -> 3814.94 | AL12: 542944 | AM12: =IF(AL12>=AL11,AL12-AL11,0)*0.53 -> 109.18 | AN12: =W12+Y12+AA12+AC12+AE12+AG12+AI12+AK12+AM12 -> 14471.65 | AO12: 7907186 | AP12: =IF(AO12>=AO11,AO12-AO11,0)*0.1125 -> 283.1625 | AQ12: 728886 | AR12: =IF(AQ12>=AQ11,AQ12-AQ11,0) -> 149 | AS12: 996186 | AT12: =IF(AS12>=AS11,AS12-AS11,0) -> 153 | AU12: 819803 | AV12: =IF(AU12>=AU11,AU12-AU11,0) -> 62 | AW12: 2772884 | AX12: =IF(AW12>=AW11,AW12-AW11,0) -> 980 | AY12: 229733 | AZ12: =IF(AY12>=AY11,AY12-AY11,0) -> 0 | BA12: 20207453 | BB12: =IF(BA12>=BA11,BA12-BA11,0) -> 5046 | BC12: 611008 | BD12: =IF(BC12>=BC11,BC12-BC11,0) -> 233 | BE12: 37583 | BF12: =IF(BE12>=BE11,BE12-BE11,0) -> 64 | BG12: 25324927 | BH12: =IF(BG12>=BG11,BG12-BG11,0)-(0.45*BN12)-(0.45*BP12)-BR12 -> 6239.85 | BI12: =AP12+AR12+AT12+AV12+AX12+AZ12+BB12+BD12+BF12+BH12 -> 13210.013 | BJ12: =BI12+AN12 -> 27681.663 | BK12: 1466414 | BL12: =IF(BK12>=BK11,BK12-BK11,0) -> 301 | BM12: 4150591 | BN12: =IF(BM12>=BM11,BM12-BM11,0) -> 1517 | BO12: 436777 | BP12: =IF(BO12>=BO11,BO12-BO11,0) -> 110 | BQ12: 545806 | BR12: =IF(BQ12>=BQ11,BQ12-BQ11,0) -> 145 | BS12: =J12+Q12+AN12+BI12 -> 33673.663 | BT12: 221 | BU12: =IF(BS12>0,BS12/BT11,0) -> 150.32885 | BW12: =IF(BS12>0,BS12/BV12,0) -> #DIV/0! | BX12: =((BS12-Q12)*$BZ$1)+(Q12*$BR$1) -> 38967.712 | BY12: =IF(BX12>0,BX12/BT11,0) -> 173.963 | BZ12: =IF(BX12>0,BX12/BV12,0) -> #DIV/0!
A13: 8 | C13: =IF(+B13-B12>0,B13-B12,(B13-B12)>0)*800 -> 0 | E13: =IF(+D13-D12>0,D13-D12,(D13-D12)>0)*80 -> 0 | G13: =IF(+F13-F12>0,F13-F12,(F13-F12)>0)*10 -> 0 | I13: 25081710 | J13: =IF(I13>=I12,I13-I12,0) -> 5595 | K13: =M13+O13 -> 4549 | L13: 50754 | M13: =IF(L13>=L12,L13-L12,0) -> 2042 | N13: 77872 | O13: =IF(N13>=N12,N13-N12,0) -> 2507 | P13: 224991 | Q13: =IF(P13>=P12,P13-P12,0)*30 -> 540 | R13: 209996 | S13: =IF(R13>=R12,R13-R12,0) -> 139 | T13: 383032 | U13: =IF(T13>=T12,T13-T12,0) -> 284 | V13: 297550 | W13: =IF(V13>=V12,V13-V12,0)*0.53 -> 0 | X13: 503129 | Y13: =IF(X13>=X12,X13-X12,0)*0.53 -> 4051.32 | Z13: 555152 | AA13: =IF(Z13>=Z12,Z13-Z12,0)*0.53 -> 0 | AB13: 846058 | AC13: =IF(AB13>=AB12,AB13-AB12,0)*0.53 -> 3661.24 | AD13: 784925 | AE13: =IF(AD13>=AD12,AD13-AD12,0)*0.53 -> 1753.77 | AF13: 904703 | AG13: =IF(AF13>=AF12,AF13-AF12,0)*0.53 -> 10.6 | AH13: 252169 | AI13: =IF(AH13>=AH12,AH13-AH12,0)*0.53 -> 1117.77 | AJ13: 800811 | AK13: =IF(AJ13>=AJ12,AJ13-AJ12,0)*0.53 -> 3873.24 | AL13: 543147 | AM13: =IF(AL13>=AL12,AL13-AL12,0)*0.53 -> 107.59 | AN13: =W13+Y13+AA13+AC13+AE13+AG13+AI13+AK13+AM13 -> 14575.53 | AO13: 7909777 | AP13: =IF(AO13>=AO12,AO13-AO12,0)*0.1125 -> 291.4875 | AQ13: 729045 | AR13: =IF(AQ13>=AQ12,AQ13-AQ12,0) -> 159 | AS13: 996338 | AT13: =IF(AS13>=AS12,AS13-AS12,0) -> 152 | AU13: 819864 | AV13: =IF(AU13>=AU12,AU13-AU12,0) -> 61 | AW13: 2773972 | AX13: =IF(AW13>=AW12,AW13-AW12,0) -> 1088 | AY13: 229733 | AZ13: =IF(AY13>=AY12,AY13-AY12,0) -> 0 | BA13: 20212470 | BB13: =IF(BA13>=BA12,BA13-BA12,0) -> 5017 | BC13: 611230 | BD13: =IF(BC13>=BC12,BC13-BC12,0) -> 222 | BE13: 37638 | BF13: =IF(BE13>=BE12,BE13-BE12,0) -> 55 | BG13: 25332242 | BH13: =IF(BG13>=BG12,BG13-BG12,0)-(0.45*BN13)-(0.45*BP13)-BR13 -> 6427.3 | BI13: =AP13+AR13+AT13+AV13+AX13+AZ13+BB13+BD13+BF13+BH13 -> 13472.788 | BJ13: =BI13+AN13 -> 28048.318 | BK13: 1466721 | BL13: =IF(BK13>=BK12,BK13-BK12,0) -> 307 | BM13: 4152078 | BN13: =IF(BM13>=BM12,BM13-BM12,0) -> 1487 | BO13: 436896 | BP13: =IF(BO13>=BO12,BO13-BO12,0) -> 119 | BQ13: 545971 | BR13: =IF(BQ13>=BQ12,BQ13-BQ12,0) -> 165 | BS13: =J13+Q13+AN13+BI13 -> 34183.317 | BT13: 216 | BU13: =IF(BS13>0,BS13/BT12,0) -> 154.67564 | BW13: =IF(BS13>0,BS13/BV13,0) -> #DIV/0! | BX13: =((BS13-Q13)*$BZ$1)+(Q13*$BR$1) -> 39553.815 | BY13: =IF(BX13>0,BX13/BT12,0) -> 178.97654 | BZ13: =IF(BX13>0,BX13/BV13,0) -> #DIV/0!
A14: 9 | C14: =IF(+B14-B13>0,B14-B13,(B14-B13)>0)*800 -> 0 | E14: =IF(+D14-D13>0,D14-D13,(D14-D13)>0)*80 -> 0 | G14: =IF(+F14-F13>0,F14-F13,(F14-F13)>0)*10 -> 0 | H14: 60 | I14: 25087409 | J14: =IF(I14>=I13,I14-I13,0) -> 5699 | K14: =M14+O14 -> 4548 | L14: 52734 | M14: =IF(L14>=L13,L14-L13,0) -> 1980 | N14: 80440 | O14: =IF(N14>=N13,N14-N13,0) -> 2568 | P14: 225001 | Q14: =IF(P14>=P13,P14-P13,0)*30 -> 300 | R14: 210136 | S14: =IF(R14>=R13,R14-R13,0) -> 140 | T14: 383304 | U14: =IF(T14>=T13,T14-T13,0) -> 272 | V14: 297550 | W14: =IF(V14>=V13,V14-V13,0)*0.53 -> 0 | X14: 510860 | Y14: =IF(X14>=X13,X14-X13,0)*0.53 -> 4097.43 | Z14: 555152 | AA14: =IF(Z14>=Z13,Z14-Z13,0)*0.53 -> 0 | AB14: 853621 | AC14: =IF(AB14>=AB13,AB14-AB13,0)*0.53 -> 4008.39 | AD14: 788525 | AE14: =IF(AD14>=AD13,AD14-AD13,0)*0.53 -> 1908 | AF14: 904723 | AG14: =IF(AF14>=AF13,AF14-AF13,0)*0.53 -> 10.6 | AH14: 254276 | AI14: =IF(AH14>=AH13,AH14-AH13,0)*0.53 -> 1116.71 | AJ14: 808113 | AK14: =IF(AJ14>=AJ13,AJ14-AJ13,0)*0.53 -> 3870.06 | AL14: 543376 | AM14: =IF(AL14>=AL13,AL14-AL13,0)*0.53 -> 121.37 | AN14: =W14+Y14+AA14+AC14+AE14+AG14+AI14+AK14+AM14 -> 15132.56 | AO14: 7912402 | AP14: =IF(AO14>=AO13,AO14-AO13,0)*0.1125 -> 295.3125 | AQ14: 729192 | AR14: =IF(AQ14>=AQ13,AQ14-AQ13,0) -> 147 | AS14: 996498 | AT14: =IF(AS14>=AS13,AS14-AS13,0) -> 160 | AU14: 819924 | AV14: =IF(AU14>=AU13,AU14-AU13,0) -> 60 | AW14: 2775016 | AX14: =IF(AW14>=AW13,AW14-AW13,0) -> 1044 | AY14: 229733 | AZ14: =IF(AY14>=AY13,AY14-AY13,0) -> 0 | BA14: 20217610 | BB14: =IF(BA14>=BA13,BA14-BA13,0) -> 5140 | BC14: 611462 | BD14: =IF(BC14>=BC13,BC14-BC13,0) -> 232 | BE14: 37768 | BF14: =IF(BE14>=BE13,BE14-BE13,0) -> 130 | BG14: 25339763 | BH14: =IF(BG14>=BG13,BG14-BG13,0)-(0.45*BN14)-(0.45*BP14)-BR14 -> 6623.75 | BI14: =AP14+AR14+AT14+AV14+AX14+AZ14+BB14+BD14+BF14+BH14 -> 13832.062 | BJ14: =BI14+AN14 -> 28964.623 | BK14: 1467026 | BL14: =IF(BK14>=BK13,BK14-BK13,0) -> 305 | BM14: 4153646 | BN14: =IF(BM14>=BM13,BM14-BM13,0) -> 1568 | BO14: 437013 | BP14: =IF(BO14>=BO13,BO14-BO13,0) -> 117 | BQ14: 546110 | BR14: =IF(BQ14>=BQ13,BQ14-BQ13,0) -> 139 | BS14: =J14+Q14+AN14+BI14 -> 34963.623 | BT14: 197 | BU14: =IF(BS14>0,BS14/BT13,0) -> 161.86862 | BW14: =IF(BS14>0,BS14/BV14,0) -> #DIV/0! | BX14: =((BS14-Q14)*$BZ$1)+(Q14*$BR$1) -> 40343.166 | BY14: =IF(BX14>0,BX14/BT13,0) -> 186.77392 | BZ14: =IF(BX14>0,BX14/BV14,0) -> #DIV/0!
A15: 10 | C15: =IF(+B15-B14>0,B15-B14,(B15-B14)>0)*800 -> 0 | E15: =IF(+D15-D14>0,D15-D14,(D15-D14)>0)*80 -> 0 | G15: =IF(+F15-F14>0,F15-F14,(F15-F14)>0)*10 -> 0 | I15: 25093061 | J15: =IF(I15>=I14,I15-I14,0) -> 5652 | K15: =M15+O15 -> 4783 | L15: 54736 | M15: =IF(L15>=L14,L15-L14,0) -> 2002 | N15: 83221 | O15: =IF(N15>=N14,N15-N14,0) -> 2781 | P15: 225020 | Q15: =IF(P15>=P14,P15-P14,0)*30 -> 570 | R15: 210276 | S15: =IF(R15>=R14,R15-R14,0) -> 140 | T15: 383591 | U15: =IF(T15>=T14,T15-T14,0) -> 287 | V15: 297550 | W15: =IF(V15>=V14,V15-V14,0)*0.53 -> 0 | X15: 518591 | Y15: =IF(X15>=X14,X15-X14,0)*0.53 -> 4097.43 | Z15: 555152 | AA15: =IF(Z15>=Z14,Z15-Z14,0)*0.53 -> 0 | AB15: 861301 | AC15: =IF(AB15>=AB14,AB15-AB14,0)*0.53 -> 4070.4 | AD15: 791907 | AE15: =IF(AD15>=AD14,AD15-AD14,0)*0.53 -> 1792.46 | AF15: 904742 | AG15: =IF(AF15>=AF14,AF15-AF14,0)*0.53 -> 10.07 | AH15: 256382 | AI15: =IF(AH15>=AH14,AH15-AH14,0)*0.53 -> 1116.18 | AJ15: 815522 | AK15: =IF(AJ15>=AJ14,AJ15-AJ14,0)*0.53 -> 3926.77 | AL15: 543579 | AM15: =IF(AL15>=AL14,AL15-AL14,0)*0.53 -> 107.59 | AN15: =W15+Y15+AA15+AC15+AE15+AG15+AI15+AK15+AM15 -> 15120.9 | AO15: 7914840 | AP15: =IF(AO15>=AO14,AO15-AO14,0)*0.1125 -> 274.275 | AQ15: 729337 | AR15: =IF(AQ15>=AQ14,AQ15-AQ14,0) -> 145 | AS15: 996652 | AT15: =IF(AS15>=AS14,AS15-AS14,0) -> 154 | AU15: 819994 | AV15: =IF(AU15>=AU14,AU15-AU14,0) -> 70 | AW15: 2776130 | AX15: =IF(AW15>=AW14,AW15-AW14,0) -> 1114 | AY15: 229733 | AZ15: =IF(AY15>=AY14,AY15-AY14,0) -> 0 | BA15: 20222410 | BB15: =IF(BA15>=BA14,BA15-BA14,0) -> 4800 | BC15: 611716 | BD15: =IF(BC15>=BC14,BC15-BC14,0) -> 254 | BE15: 37879 | BF15: =IF(BE15>=BE14,BE15-BE14,0) -> 111 | BG15: 25347350 | BH15: =IF(BG15>=BG14,BG15-BG14,0)-(0.45*BN15)-(0.45*BP15)-BR15 -> 6686.3 | BI15: =AP15+AR15+AT15+AV15+AX15+AZ15+BB15+BD15+BF15+BH15 -> 13608.575 | BJ15: =BI15+AN15 -> 28729.475 | BK15: 1467329 | BL15: =IF(BK15>=BK14,BK15-BK14,0) -> 303 | BM15: 4155198 | BN15: =IF(BM15>=BM14,BM15-BM14,0) -> 1552 | BO15: 437127 | BP15: =IF(BO15>=BO14,BO15-BO14,0) -> 114 | BQ15: 546261 | BR15: =IF(BQ15>=BQ14,BQ15-BQ14,0) -> 151 | BS15: =J15+Q15+AN15+BI15 -> 34951.475 | BT15: 194 | BU15: =IF(BS15>0,BS15/BT14,0) -> 177.41865 | BW15: =IF(BS15>0,BS15/BV15,0) -> #DIV/0! | BX15: =((BS15-Q15)*$BZ$1)+(Q15*$BR$1) -> 40450.696 | BY15: =IF(BX15>0,BX15/BT14,0) -> 205.33348 | BZ15: =IF(BX15>0,BX15/BV15,0) -> #DIV/0!
A16: 11 | C16: =IF(+B16-B15>0,B16-B15,(B16-B15)>0)*800 -> 0 | E16: =IF(+D16-D15>0,D16-D15,(D16-D15)>0)*80 -> 0 | G16: =IF(+F16-F15>0,F16-F15,(F16-F15)>0)*10 -> 0 | H16: 61 | I16: 25098409 | J16: =IF(I16>=I15,I16-I15,0) -> 5348 | K16: =M16+O16 -> 4688 | L16: 56752 | M16: =IF(L16>=L15,L16-L15,0) -> 2016 | N16: 85893 | O16: =IF(N16>=N15,N16-N15,0) -> 2672 | P16: 225040 | Q16: =IF(P16>=P15,P16-P15,0)*30 -> 600 | R16: 210418 | S16: =IF(R16>=R15,R16-R15,0) -> 142 | T16: 383867 | U16: =IF(T16>=T15,T16-T15,0) -> 276 | V16: 297550 | W16: =IF(V16>=V15,V16-V15,0)*0.53 -> 0 | X16: 526932 | Y16: =IF(X16>=X15,X16-X15,0)*0.53 -> 4420.73 | Z16: 555152 | AA16: =IF(Z16>=Z15,Z16-Z15,0)*0.53 -> 0 | AB16: 869136 | AC16: =IF(AB16>=AB15,AB16-AB15,0)*0.53 -> 4152.55 | AD16: 795331 | AE16: =IF(AD16>=AD15,AD16-AD15,0)*0.53 -> 1814.72 | AF16: 904762 | AG16: =IF(AF16>=AF15,AF16-AF15,0)*0.53 -> 10.6 | AH16: 258507 | AI16: =IF(AH16>=AH15,AH16-AH15,0)*0.53 -> 1126.25 | AJ16: 823012 | AK16: =IF(AJ16>=AJ15,AJ16-AJ15,0)*0.53 -> 3969.7 | AL16: 543774 | AM16: =IF(AL16>=AL15,AL16-AL15,0)*0.53 -> 103.35 | AN16: =W16+Y16+AA16+AC16+AE16+AG16+AI16+AK16+AM16 -> 15597.9 | AO16: 7917350 | AP16: =IF(AO16>=AO15,AO16-AO15,0)*0.1125 -> 282.375 | AQ16: 729496 | AR16: =IF(AQ16>=AQ15,AQ16-AQ15,0) -> 159 | AS16: 996807 | AT16: =IF(AS16>=AS15,AS16-AS15,0) -> 155 | AU16: 820060 | AV16: =IF(AU16>=AU15,AU16-AU15,0) -> 66 | AW16: 2777266 | AX16: =IF(AW16>=AW15,AW16-AW15,0) -> 1136 | AY16: 229733 | AZ16: =IF(AY16>=AY15,AY16-AY15,0) -> 0 | BA16: 20227866 | BB16: =IF(BA16>=BA15,BA16-BA15,0) -> 5456 | BC16: 611998 | BD16: =IF(BC16>=BC15,BC16-BC15,0) -> 282 | BE16: 37944 | BF16: =IF(BE16>=BE15,BE16-BE15,0) -> 65 | BG16: 25354937 | BH16: =IF(BG16>=BG15,BG16-BG15,0)-(0.45*BN16)-(0.45*BP16)-BR16 -> 6685.85 | BI16: =AP16+AR16+AT16+AV16+AX16+AZ16+BB16+BD16+BF16+BH16 -> 14287.225 | BJ16: =BI16+AN16 -> 29885.125 | BK16: 1467636 | BL16: =IF(BK16>=BK15,BK16-BK15,0) -> 307 | BM16: 4156736 | BN16: =IF(BM16>=BM15,BM16-BM15,0) -> 1538 | BO16: 437236 | BP16: =IF(BO16>=BO15,BO16-BO15,0) -> 109 | BQ16: 546421 | BR16: =IF(BQ16>=BQ15,BQ16-BQ15,0) -> 160 | BS16: =J16+Q16+AN16+BI16 -> 35833.125 | BT16: 211 | BU16: =IF(BS16>0,BS16/BT15,0) -> 184.70683 | BW16: =IF(BS16>0,BS16/BV16,0) -> #DIV/0! | BX16: =((BS16-Q16)*$BZ$1)+(Q16*$BR$1) -> 41478.094 | BY16: =IF(BX16>0,BX16/BT15,0) -> 213.80461 | BZ16: =IF(BX16>0,BX16/BV16,0) -> #DIV/0!
A17: 12 | C17: =IF(+B17-B16>0,B17-B16,(B17-B16)>0)*800 -> 0 | E17: =IF(+D17-D16>0,D17-D16,(D17-D16)>0)*80 -> 0 | G17: =IF(+F17-F16>0,F17-F16,(F17-F16)>0)*10 -> 0 | I17: 25103721 | J17: =IF(I17>=I16,I17-I16,0) -> 5312 | K17: =M17+O17 -> 4664 | L17: 58819 | M17: =IF(L17>=L16,L17-L16,0) -> 2067 | N17: 88490 | O17: =IF(N17>=N16,N17-N16,0) -> 2597 | P17: 225060 | Q17: =IF(P17>=P16,P17-P16,0)*30 -> 600 | R17: 210555 | S17: =IF(R17>=R16,R17-R16,0) -> 137 | T17: 384135 | U17: =IF(T17>=T16,T17-T16,0) -> 268 | V17: 297550 | W17: =IF(V17>=V16,V17-V16,0)*0.53 -> 0 | X17: 534278 | Y17: =IF(X17>=X16,X17-X16,0)*0.53 -> 3893.38 | Z17: 555152 | AA17: =IF(Z17>=Z16,Z17-Z16,0)*0.53 -> 0 | AB17: 876410 | AC17: =IF(AB17>=AB16,AB17-AB16,0)*0.53 -> 3855.22 | AD17: 798741 | AE17: =IF(AD17>=AD16,AD17-AD16,0)*0.53 -> 1807.3 | AF17: 904781 | AG17: =IF(AF17>=AF16,AF17-AF16,0)*0.53 -> 10.07 | AH17: 260627 | AI17: =IF(AH17>=AH16,AH17-AH16,0)*0.53 -> 1123.6 | AJ17: 830479 | AK17: =IF(AJ17>=AJ16,AJ17-AJ16,0)*0.53 -> 3957.51 | AL17: 543968 | AM17: =IF(AL17>=AL16,AL17-AL16,0)*0.53 -> 102.82 | AN17: =W17+Y17+AA17+AC17+AE17+AG17+AI17+AK17+AM17 -> 14749.9 | AO17: 7919898 | AP17: =IF(AO17>=AO16,AO17-AO16,0)*0.1125 -> 286.65 | AQ17: 729644 | AR17: =IF(AQ17>=AQ16,AQ17-AQ16,0) -> 148 | AS17: 996964 | AT17: =IF(AS17>=AS16,AS17-AS16,0) -> 157 | AU17: 820110 | AV17: =IF(AU17>=AU16,AU17-AU16,0) -> 50 | AW17: 2778384 | AX17: =IF(AW17>=AW16,AW17-AW16,0) -> 1118 | AY17: 229733 | AZ17: =IF(AY17>=AY16,AY17-AY16,0) -> 0 | BA17: 20232571 | BB17: =IF(BA17>=BA16,BA17-BA16,0) -> 4705 | BC17: 612271 | BD17: =IF(BC17>=BC16,BC17-BC16,0) -> 273 | BE17: 38009 | BF17: =IF(BE17>=BE16,BE17-BE16,0) -> 65 | BG17: 25362600 | BH17: =IF(BG17>=BG16,BG17-BG16,0)-(0.45*BN17)-(0.45*BP17)-BR17 -> 6782 | BI17: =AP17+AR17+AT17+AV17+AX17+AZ17+BB17+BD17+BF17+BH17 -> 13584.65 | BJ17: =BI17+AN17 -> 28334.55 | BK17: 1467937 | BL17: =IF(BK17>=BK16,BK17-BK16,0) -> 301 | BM17: 4158267 | BN17: =IF(BM17>=BM16,BM17-BM16,0) -> 1531 | BO17: 437345 | BP17: =IF(BO17>=BO16,BO17-BO16,0) -> 109 | BQ17: 546564 | BR17: =IF(BQ17>=BQ16,BQ17-BQ16,0) -> 143 | BS17: =J17+Q17+AN17+BI17 -> 34246.55 | BT17: 239 | BU17: =IF(BS17>0,BS17/BT16,0) -> 162.30592 | BW17: =IF(BS17>0,BS17/BV17,0) -> #DIV/0! | BX17: =((BS17-Q17)*$BZ$1)+(Q17*$BR$1) -> 39653.533 | BY17: =IF(BX17>0,BX17/BT16,0) -> 187.93143 | BZ17: =IF(BX17>0,BX17/BV17,0) -> #DIV/0!
A18: 13 | C18: =IF(+B18-B17>0,B18-B17,(B18-B17)>0)*800 -> 0 | E18: =IF(+D18-D17>0,D18-D17,(D18-D17)>0)*80 -> 0 | G18: =IF(+F18-F17>0,F18-F17,(F18-F17)>0)*10 -> 0 | H18: 62 | I18: 25109327 | J18: =IF(I18>=I17,I18-I17,0) -> 5606 | K18: =M18+O18 -> 3705 | L18: 60687 | M18: =IF(L18>=L17,L18-L17,0) -> 1868 | N18: 90327 | O18: =IF(N18>=N17,N18-N17,0) -> 1837 | P18: 225070 | Q18: =IF(P18>=P17,P18-P17,0)*30 -> 300 | R18: 210696 | S18: =IF(R18>=R17,R18-R17,0) -> 141 | T18: 384406 | U18: =IF(T18>=T17,T18-T17,0) -> 271 | V18: 297550 | W18: =IF(V18>=V17,V18-V17,0)*0.53 -> 0 | X18: 541628 | Y18: =IF(X18>=X17,X18-X17,0)*0.53 -> 3895.5 | Z18: 555152 | AA18: =IF(Z18>=Z17,Z18-Z17,0)*0.53 -> 0 | AB18: 882596 | AC18: =IF(AB18>=AB17,AB18-AB17,0)*0.53 -> 3278.58 | AD18: 801988 | AE18: =IF(AD18>=AD17,AD18-AD17,0)*0.53 -> 1720.91 | AF18: 904800 | AG18: =IF(AF18>=AF17,AF18-AF17,0)*0.53 -> 10.07 | AH18: 262612 | AI18: =IF(AH18>=AH17,AH18-AH17,0)*0.53 -> 1052.05 | AJ18: 837515 | AK18: =IF(AJ18>=AJ17,AJ18-AJ17,0)*0.53 -> 3729.08 | AL18: 544163 | AM18: =IF(AL18>=AL17,AL18-AL17,0)*0.53 -> 103.35 | AN18: =W18+Y18+AA18+AC18+AE18+AG18+AI18+AK18+AM18 -> 13789.54 | AO18: 7922504 | AP18: =IF(AO18>=AO17,AO18-AO17,0)*0.1125 -> 293.175 | AQ18: 729804 | AR18: =IF(AQ18>=AQ17,AQ18-AQ17,0) -> 160 | AS18: 997113 | AT18: =IF(AS18>=AS17,AS18-AS17,0) -> 149 | AU18: 820156 | AV18: =IF(AU18>=AU17,AU18-AU17,0) -> 46 | AW18: 2779396 | AX18: =IF(AW18>=AW17,AW18-AW17,0) -> 1012 | AY18: 229733 | AZ18: =IF(AY18>=AY17,AY18-AY17,0) -> 0 | BA18: 20237449 | BB18: =IF(BA18>=BA17,BA18-BA17,0) -> 4878 | BC18: 612534 | BD18: =IF(BC18>=BC17,BC18-BC17,0) -> 263 | BE18: 38074 | BF18: =IF(BE18>=BE17,BE18-BE17,0) -> 65 | BG18: 25369860 | BH18: =IF(BG18>=BG17,BG18-BG17,0)-(0.45*BN18)-(0.45*BP18)-BR18 -> 6339.85 | BI18: =AP18+AR18+AT18+AV18+AX18+AZ18+BB18+BD18+BF18+BH18 -> 13206.025 | BJ18: =BI18+AN18 -> 26995.565 | BK18: 1468244 | BL18: =IF(BK18>=BK17,BK18-BK17,0) -> 307 | BM18: 4159803 | BN18: =IF(BM18>=BM17,BM18-BM17,0) -> 1536 | BO18: 437456 | BP18: =IF(BO18>=BO17,BO18-BO17,0) -> 111 | BQ18: 546743 | BR18: =IF(BQ18>=BQ17,BQ18-BQ17,0) -> 179 | BS18: =J18+Q18+AN18+BI18 -> 32901.565 | BT18: 227 | BU18: =IF(BS18>0,BS18/BT17,0) -> 137.66345 | BW18: =IF(BS18>0,BS18/BV18,0) -> #DIV/0! | BX18: =((BS18-Q18)*$BZ$1)+(Q18*$BR$1) -> 37971.8 | BY18: =IF(BX18>0,BX18/BT17,0) -> 158.87782 | BZ18: =IF(BX18>0,BX18/BV18,0) -> #DIV/0!
A19: 14 | C19: =IF(+B19-B18>0,B19-B18,(B19-B18)>0)*800 -> 0 | E19: =IF(+D19-D18>0,D19-D18,(D19-D18)>0)*80 -> 0 | G19: =IF(+F19-F18>0,F19-F18,(F19-F18)>0)*10 -> 0 | I19: 25114752 | J19: =IF(I19>=I18,I19-I18,0) -> 5425 | K19: =M19+O19 -> 4020 | L19: 62648 | M19: =IF(L19>=L18,L19-L18,0) -> 1961 | N19: 92386 | O19: =IF(N19>=N18,N19-N18,0) -> 2059 | P19: 225090 | Q19: =IF(P19>=P18,P19-P18,0)*30 -> 600 | R19: 210835 | S19: =IF(R19>=R18,R19-R18,0) -> 139 | T19: 384672 | U19: =IF(T19>=T18,T19-T18,0) -> 266 | V19: 297550 | W19: =IF(V19>=V18,V19-V18,0)*0.53 -> 0 | X19: 549326 | Y19: =IF(X19>=X18,X19-X18,0)*0.53 -> 4079.94 | Z19: 555152 | AA19: =IF(Z19>=Z18,Z19-Z18,0)*0.53 -> 0 | AB19: 888902 | AC19: =IF(AB19>=AB18,AB19-AB18,0)*0.53 -> 3342.18 | AD19: 805103 | AE19: =IF(AD19>=AD18,AD19-AD18,0)*0.53 -> 1650.95 | AF19: 904819 | AG19: =IF(AF19>=AF18,AF19-AF18,0)*0.53 -> 10.07 | AH19: 264703 | AI19: =IF(AH19>=AH18,AH19-AH18,0)*0.53 -> 1108.23 | AJ19: 844875 | AK19: =IF(AJ19>=AJ18,AJ19-AJ18,0)*0.53 -> 3900.8 | AL19: 544375 | AM19: =IF(AL19>=AL18,AL19-AL18,0)*0.53 -> 112.36 | AN19: =W19+Y19+AA19+AC19+AE19+AG19+AI19+AK19+AM19 -> 14204.53 | AO19: 7925108 | AP19: =IF(AO19>=AO18,AO19-AO18,0)*0.1125 -> 292.95 | AQ19: 729975 | AR19: =IF(AQ19>=AQ18,AQ19-AQ18,0) -> 171 | AS19: 997269 | AT19: =IF(AS19>=AS18,AS19-AS18,0) -> 156 | AU19: 820216 | AV19: =IF(AU19>=AU18,AU19-AU18,0) -> 60 | AW19: 2780439 | AX19: =IF(AW19>=AW18,AW19-AW18,0) -> 1043 | AY19: 229733 | AZ19: =IF(AY19>=AY18,AY19-AY18,0) -> 0 | BA19: 20242347 | BB19: =IF(BA19>=BA18,BA19-BA18,0) -> 4898 | BC19: 612788 | BD19: =IF(BC19>=BC18,BC19-BC18,0) -> 254 | BE19: 38169 | BF19: =IF(BE19>=BE18,BE19-BE18,0) -> 95 | BG19: 25377029 | BH19: =IF(BG19>=BG18,BG19-BG18,0)-(0.45*BN19)-(0.45*BP19)-BR19 -> 6248.9 | BI19: =AP19+AR19+AT19+AV19+AX19+AZ19+BB19+BD19+BF19+BH19 -> 13218.85 | BJ19: =BI19+AN19 -> 27423.38 | BK19: 1468548 | BL19: =IF(BK19>=BK18,BK19-BK18,0) -> 304 | BM19: 4161356 | BN19: =IF(BM19>=BM18,BM19-BM18,0) -> 1553 | BO19: 437561 | BP19: =IF(BO19>=BO18,BO19-BO18,0) -> 105 | BQ19: 546917 | BR19: =IF(BQ19>=BQ18,BQ19-BQ18,0) -> 174 | BS19: =J19+Q19+AN19+BI19 -> 33448.38 | BT19: 216 | BU19: =IF(BS19>0,BS19/BT18,0) -> 147.34969 | BW19: =IF(BS19>0,BS19/BV19,0) -> #DIV/0! | BX19: =((BS19-Q19)*$BZ$1)+(Q19*$BR$1) -> 38735.637 | BY19: =IF(BX19>0,BX19/BT18,0) -> 170.64157 | BZ19: =IF(BX19>0,BX19/BV19,0) -> #DIV/0!
A20: 15 | C20: =IF(+B20-B19>0,B20-B19,(B20-B19)>0)*800 -> 0 | E20: =IF(+D20-D19>0,D20-D19,(D20-D19)>0)*80 -> 0 | G20: =IF(+F20-F19>0,F20-F19,(F20-F19)>0)*10 -> 0 | H20: 63 | I20: 25119721 | J20: =IF(I20>=I19,I20-I19,0) -> 4969 | K20: =M20+O20 -> 4024 | L20: 64546 | M20: =IF(L20>=L19,L20-L19,0) -> 1898 | N20: 94512 | O20: =IF(N20>=N19,N20-N19,0) -> 2126 | P20: 225100 | Q20: =IF(P20>=P19,P20-P19,0)*30 -> 300 | R20: 210974 | S20: =IF(R20>=R19,R20-R19,0) -> 139 | T20: 384933 | U20: =IF(T20>=T19,T20-T19,0) -> 261 | V20: 302968 | W20: =IF(V20>=V19,V20-V19,0)*0.53 -> 2871.54 | X20: 551756 | Y20: =IF(X20>=X19,X20-X19,0)*0.53 -> 1287.9 | Z20: 560333 | AA20: =IF(Z20>=Z19,Z20-Z19,0)*0.53 -> 2745.93 | AB20: 890810 | AC20: =IF(AB20>=AB19,AB20-AB19,0)*0.53 -> 1011.24 | AD20: 808487 | AE20: =IF(AD20>=AD19,AD20-AD19,0)*0.53 -> 1793.52 | AF20: 904840 | AG20: =IF(AF20>=AF19,AF20-AF19,0)*0.53 -> 11.13 | AH20: 266822 | AI20: =IF(AH20>=AH19,AH20-AH19,0)*0.53 -> 1123.07 | AJ20: 852301 | AK20: =IF(AJ20>=AJ19,AJ20-AJ19,0)*0.53 -> 3935.78 | AL20: 544586 | AM20: =IF(AL20>=AL19,AL20-AL19,0)*0.53 -> 111.83 | AN20: =W20+Y20+AA20+AC20+AE20+AG20+AI20+AK20+AM20 -> 14891.94 | AO20: 7927809 | AP20: =IF(AO20>=AO19,AO20-AO19,0)*0.1125 -> 303.8625 | AQ20: 730145 | AR20: =IF(AQ20>=AQ19,AQ20-AQ19,0) -> 170 | AS20: 997423 | AT20: =IF(AS20>=AS19,AS20-AS19,0) -> 154 | AU20: 820279 | AV20: =IF(AU20>=AU19,AU20-AU19,0) -> 63 | AW20: 2781496 | AX20: =IF(AW20>=AW19,AW20-AW19,0) -> 1057 | AY20: 229733 | AZ20: =IF(AY20>=AY19,AY20-AY19,0) -> 0 | BA20: 20247428 | BB20: =IF(BA20>=BA19,BA20-BA19,0) -> 5081 | BC20: 613046 | BD20: =IF(BC20>=BC19,BC20-BC19,0) -> 258 | BE20: 38217 | BF20: =IF(BE20>=BE19,BE20-BE19,0) -> 48 | BG20: 25384051 | BH20: =IF(BG20>=BG19,BG20-BG19,0)-(0.45*BN20)-(0.45*BP20)-BR20 -> 6145.9 | BI20: =AP20+AR20+AT20+AV20+AX20+AZ20+BB20+BD20+BF20+BH20 -> 13280.763 | BJ20: =BI20+AN20 -> 28172.702 | BK20: 1468853 | BL20: =IF(BK20>=BK19,BK20-BK19,0) -> 305 | BM20: 4162885 | BN20: =IF(BM20>=BM19,BM20-BM19,0) -> 1529 | BO20: 437670 | BP20: =IF(BO20>=BO19,BO20-BO19,0) -> 109 | BQ20: 547056 | BR20: =IF(BQ20>=BQ19,BQ20-BQ19,0) -> 139 | BS20: =J20+Q20+AN20+BI20 -> 33441.702 | BT20: 211 | BU20: =IF(BS20>0,BS20/BT20,0) -> 158.49148 | BW20: =IF(BS20>0,BS20/BV20,0) -> #DIV/0! | BX20: =((BS20-Q20)*$BZ$1)+(Q20*$BR$1) -> 38592.958 | BY20: =IF(BX20>0,BX20/BT20,0) -> 182.90501 | BZ20: =IF(BX20>0,BX20/BV20,0) -> #DIV/0!
A21: 16 | C21: =IF(+B21-B20>0,B21-B20,(B21-B20)>0)*800 -> 0 | E21: =IF(+D21-D20>0,D21-D20,(D21-D20)>0)*80 -> 0 | G21: =IF(+F21-F20>0,F21-F20,(F21-F20)>0)*10 -> 0 | I21: 25124974 | J21: =IF(I21>=I20,I21-I20,0) -> 5253 | K21: =M21+O21 -> 4070 | L21: 66473 | M21: =IF(L21>=L20,L21-L20,0) -> 1927 | N21: 96655 | O21: =IF(N21>=N20,N21-N20,0) -> 2143 | P21: 225120 | Q21: =IF(P21>=P20,P21-P20,0)*30 -> 600 | R21: 211119 | S21: =IF(R21>=R20,R21-R20,0) -> 145 | T21: 385205 | U21: =IF(T21>=T20,T21-T20,0) -> 272 | V21: 309970 | W21: =IF(V21>=V20,V21-V20,0)*0.53 -> 3711.06 | X21: 551756 | Y21: =IF(X21>=X20,X21-X20,0)*0.53 -> 0 | Z21: 567956 | AA21: =IF(Z21>=Z20,Z21-Z20,0)*0.53 -> 4040.19 | AB21: 890810 | AC21: =IF(AB21>=AB20,AB21-AB20,0)*0.53 -> 0 | AD21: 811747 | AE21: =IF(AD21>=AD20,AD21-AD20,0)*0.53 -> 1727.8 | AF21: 904859 | AG21: =IF(AF21>=AF20,AF21-AF20,0)*0.53 -> 10.07 | AH21: 269009 | AI21: =IF(AH21>=AH20,AH21-AH20,0)*0.53 -> 1159.11 | AJ21: 859827 | AK21: =IF(AJ21>=AJ20,AJ21-AJ20,0)*0.53 -> 3988.78 | AL21: 544798 | AM21: =IF(AL21>=AL20,AL21-AL20,0)*0.53 -> 112.36 | AN21: =W21+Y21+AA21+AC21+AE21+AG21+AI21+AK21+AM21 -> 14749.37 | AO21: 7930351 | AP21: =IF(AO21>=AO20,AO21-AO20,0)*0.1125 -> 285.975 | AQ21: 730287 | AR21: =IF(AQ21>=AQ20,AQ21-AQ20,0) -> 142 | AS21: 997577 | AT21: =IF(AS21>=AS20,AS21-AS20,0) -> 154 | AU21: 820338 | AV21: =IF(AU21>=AU20,AU21-AU20,0) -> 59 | AW21: 2782612 | AX21: =IF(AW21>=AW20,AW21-AW20,0) -> 1116 | AY21: 229733 | AZ21: =IF(AY21>=AY20,AY21-AY20,0) -> 0 | BA21: 20252483 | BB21: =IF(BA21>=BA20,BA21-BA20,0) -> 5055 | BC21: 613321 | BD21: =IF(BC21>=BC20,BC21-BC20,0) -> 275 | BE21: 38272 | BF21: =IF(BE21>=BE20,BE21-BE20,0) -> 55 | BG21: 25391121 | BH21: =IF(BG21>=BG20,BG21-BG20,0)-(0.45*BN21)-(0.45*BP21)-BR21 -> 6202.35 | BI21: =AP21+AR21+AT21+AV21+AX21+AZ21+BB21+BD21+BF21+BH21 -> 13344.325 | BJ21: =BI21+AN21 -> 28093.695 | BK21: 1469161 | BL21: =IF(BK21>=BK20,BK21-BK20,0) -> 308 | BM21: 4164411 | BN21: =IF(BM21>=BM20,BM21-BM20,0) -> 1526 | BO21: 437781 | BP21: =IF(BO21>=BO20,BO21-BO20,0) -> 111 | BQ21: 547187 | BR21: =IF(BQ21>=BQ20,BQ21-BQ20,0) -> 131 | BS21: =J21+Q21+AN21+BI21 -> 33946.695 | BT21: 194 | BU21: =IF(BS21>0,BS21/BT21,0) -> 174.98296 | BW21: =IF(BS21>0,BS21/BV21,0) -> #DIV/0! | BX21: =((BS21-Q21)*$BZ$1)+(Q21*$BR$1) -> 39308.699 | BY21: =IF(BX21>0,BX21/BT21,0) -> 202.62216 | BZ21: =IF(BX21>0,BX21/BV21,0) -> #DIV/0!
A22: 17 | C22: =IF(+B22-B21>0,B22-B21,(B22-B21)>0)*800 -> 0 | E22: =IF(+D22-D21>0,D22-D21,(D22-D21)>0)*80 -> 0 | G22: =IF(+F22-F21>0,F22-F21,(F22-F21)>0)*10 -> 0 | H22: 64 | I22: 25130038 | J22: =IF(I22>=I21,I22-I21,0) -> 5063.6667 | K22: =M22+O22 -> 4039.3333 | L22: 68380.667 | M22: =IF(L22>=L21,L22-L21,0) -> 1907.6667 | N22: 98786.667 | O22: =IF(N22>=N21,N22-N21,0) -> 2131.6667 | P22: 225137 | Q22: =IF(P22>=P21,P22-P21,0)*30 -> 510 | R22: 211260 | S22: =IF(R22>=R21,R22-R21,0) -> 141 | T22: 385469.67 | U22: =IF(T22>=T21,T22-T21,0) -> 264.66667 | V22: 315916 | W22: =IF(V22>=V21,V22-V21,0)*0.53 -> 3151.38 | X22: 553376 | Y22: =IF(X22>=X21,X22-X21,0)*0.53 -> 858.6 | Z22: 573951 | AA22: =IF(Z22>=Z21,Z22-Z21,0)*0.53 -> 3177.35 | AB22: 890810 | AC22: =IF(AB22>=AB21,AB22-AB21,0)*0.53 -> 0 | AD22: 815089.67 | AE22: =IF(AD22>=AD21,AD22-AD21,0)*0.53 -> 1771.6133 | AF22: 904879.33 | AG22: =IF(AF22>=AF21,AF22-AF21,0)*0.53 -> 10.776667 | AH22: 271150.67 | AI22: =IF(AH22>=AH21,AH22-AH21,0)*0.53 -> 1135.0833 | AJ22: 867286.33 | AK22: =IF(AJ22>=AJ21,AJ22-AJ21,0)*0.53 -> 3953.4467 | AL22: 545009.33 | AM22: =IF(AL22>=AL21,AL22-AL21,0)*0.53 -> 112.00667 | AN22: =W22+Y22+AA22+AC22+AE22+AG22+AI22+AK22+AM22 -> 14170.257 | AO22: 7932999 | AP22: =IF(AO22>=AO21,AO22-AO21,0)*0.1125 -> 297.9 | AQ22: 730447.67 | AR22: =IF(AQ22>=AQ21,AQ22-AQ21,0) -> 160.66667 | AS22: 997731 | AT22: =IF(AS22>=AS21,AS22-AS21,0) -> 154 | AU22: 820399.67 | AV22: =IF(AU22>=AU21,AU22-AU21,0) -> 61.666667 | AW22: 2783688.7 | AX22: =IF(AW22>=AW21,AW22-AW21,0) -> 1076.6667 | AY22: 229733 | AZ22: =IF(AY22>=AY21,AY22-AY21,0) -> 0 | BA22: 20257555 | BB22: =IF(BA22>=BA21,BA22-BA21,0) -> 5072.3333 | BC22: 613584.67 | BD22: =IF(BC22>=BC21,BC22-BC21,0) -> 263.66667 | BE22: 38322.333 | BF22: =IF(BE22>=BE21,BE22-BE21,0) -> 50.333333 | BG22: 25398159 | BH22: =IF(BG22>=BG21,BG22-BG21,0)-(0.45*BN22)-(0.45*BP22)-BR22 -> 6165.0167 | BI22: =AP22+AR22+AT22+AV22+AX22+AZ22+BB22+BD22+BF22+BH22 -> 13302.25 | BJ22: =BI22+AN22 -> 27472.507 | BK22: 1469467 | BL22: =IF(BK22>=BK21,BK22-BK21,0) -> 306 | BM22: 4165939 | BN22: =IF(BM22>=BM21,BM22-BM21,0) -> 1528 | BO22: 437890 | BP22: =IF(BO22>=BO21,BO22-BO21,0) -> 109 | BQ22: 547323.33 | BR22: =IF(BQ22>=BQ21,BQ22-BQ21,0) -> 136.33333 | BS22: =J22+Q22+AN22+BI22 -> 33046.173 | BT22: 193 | BU22: =IF(BS22>0,BS22/BT22,0) -> 171.2237 | BW22: =IF(BS22>0,BS22/BV22,0) -> #DIV/0! | BX22: =((BS22-Q22)*$BZ$1)+(Q22*$BR$1) -> 38232.599 | BY22: =IF(BX22>0,BX22/BT22,0) -> 198.09637 | BZ22: =IF(BX22>0,BX22/BV22,0) -> #DIV/0!
A23: 18 | C23: =IF(+B23-B22>0,B23-B22,(B23-B22)>0)*800 -> 0 | E23: =IF(+D23-D22>0,D23-D22,(D23-D22)>0)*80 -> 0 | G23: =IF(+F23-F22>0,F23-F22,(F23-F22)>0)*10 -> 0 | I23: 25135608 | J23: =IF(I23>=I22,I23-I22,0) -> 5570.3333 | K23: =M23+O23 -> 4201.6667 | L23: 70368 | M23: =IF(L23>=L22,L23-L22,0) -> 1987.3333 | N23: 101001 | O23: =IF(N23>=N22,N23-N22,0) -> 2214.3333 | P23: 225159 | Q23: =IF(P23>=P22,P23-P22,0)*30 -> 660 | R23: 211399 | S23: =IF(R23>=R22,R23-R22,0) -> 139 | T23: 385703 | U23: =IF(T23>=T22,T23-T22,0) -> 233.33333 | V23: 322953 | W23: =IF(V23>=V22,V23-V22,0)*0.53 -> 3729.61 | X23: 551756 | Y23: =IF(X23>=X22,X23-X22,0)*0.53 -> 0 | Z23: 582396 | AA23: =IF(Z23>=Z22,Z23-Z22,0)*0.53 -> 4475.85 | AB23: 890810 | AC23: =IF(AB23>=AB22,AB23-AB22,0)*0.53 -> 0 | AD23: 818250 | AE23: =IF(AD23>=AD22,AD23-AD22,0)*0.53 -> 1674.9767 | AF23: 904899 | AG23: =IF(AF23>=AF22,AF23-AF22,0)*0.53 -> 10.423333 | AH23: 273337 | AI23: =IF(AH23>=AH22,AH23-AH22,0)*0.53 -> 1158.7567 | AJ23: 874374 | AK23: =IF(AJ23>=AJ22,AJ23-AJ22,0)*0.53 -> 3756.4633 | AL23: 545219 | AM23: =IF(AL23>=AL22,AL23-AL22,0)*0.53 -> 111.12333 | AN23: =W23+Y23+AA23+AC23+AE23+AG23+AI23+AK23+AM23 -> 14917.203 | AO23: 7935225 | AP23: =IF(AO23>=AO22,AO23-AO22,0)*0.1125 -> 250.425 | AQ23: 730622 | AR23: =IF(AQ23>=AQ22,AQ23-AQ22,0) -> 174.33333 | AS23: 997876 | AT23: =IF(AS23>=AS22,AS23-AS22,0) -> 145 | AU23: 820460 | AV23: =IF(AU23>=AU22,AU23-AU22,0) -> 60.333333 | AW23: 2784757 | AX23: =IF(AW23>=AW22,AW23-AW22,0) -> 1068.3333 | AY23: 229733 | AZ23: =IF(AY23>=AY22,AY23-AY22,0) -> 0 | BA23: 20262616 | BB23: =IF(BA23>=BA22,BA23-BA22,0) -> 5060.7778 | BC23: 613884 | BD23: =IF(BC23>=BC22,BC23-BC22,0) -> 299.33333 | BE23: 38382 | BF23: =IF(BE23>=BE22,BE23-BE22,0) -> 59.666667 | BG23: 25405116 | BH23: =IF(BG23>=BG22,BG23-BG22,0)-(0.45*BN23)-(0.45*BP23)-BR23 -> 6137.3333 | BI23: =AP23+AR23+AT23+AV23+AX23+AZ23+BB23+BD23+BF23+BH23 -> 13255.536 | BJ23: =BI23+AN23 -> 28172.739 | BK23: 1469750 | BL23: =IF(BK23>=BK22,BK23-BK22,0) -> 283 | BM23: 4167276 | BN23: =IF(BM23>=BM22,BM23-BM22,0) -> 1337 | BO23: 437993 | BP23: =IF(BO23>=BO22,BO23-BO22,0) -> 103 | BQ23: 547495 | BR23: =IF(BQ23>=BQ22,BQ23-BQ22,0) -> 171.66667 | BS23: =J23+Q23+AN23+BI23 -> 34403.073 | BT23: 199 | BU23: =IF(BS23>0,BS23/BT23,0) -> 172.87976 | BW23: =IF(BS23>0,BS23/BV23,0) -> #DIV/0! | BX23: =((BS23-Q23)*$BZ$1)+(Q23*$BR$1) -> 39860.534 | BY23: =IF(BX23>0,BX23/BT23,0) -> 200.30419 | BZ23: =IF(BX23>0,BX23/BV23,0) -> #DIV/0!
A24: 19 | C24: =IF(+B24-B23>0,B24-B23,(B24-B23)>0)*800 -> 0 | E24: =IF(+D24-D23>0,D24-D23,(D24-D23)>0)*80 -> 0 | G24: =IF(+F24-F23>0,F24-F23,(F24-F23)>0)*10 -> 0 | H24: 65 | I24: 25140994 | J24: =IF(I24>=I23,I24-I23,0) -> 5386 | K24: =M24+O24 -> 4093.4444 | L24: 72302.222 | M24: =IF(L24>=L23,L24-L23,0) -> 1934.2222 | N24: 103160.22 | O24: =IF(N24>=N23,N24-N23,0) -> 2159.2222 | P24: 225175 | Q24: =IF(P24>=P23,P24-P23,0)*30 -> 480 | R24: 211539 | S24: =IF(R24>=R23,R24-R23,0) -> 140 | T24: 385955 | U24: =IF(T24>=T23,T24-T23,0) -> 252 | V24: 329262.67 | W24: =IF(V24>=V23,V24-V23,0)*0.53 -> 3344.1233 | X24: 552296 | Y24: =IF(X24>=X23,X24-X23,0)*0.53 -> 286.2 | Z24: 589207.67 | AA24: =IF(Z24>=Z23,Z24-Z23,0)*0.53 -> 3610.1833 | AB24: 890810 | AC24: =IF(AB24>=AB23,AB24-AB23,0)*0.53 -> 0 | AD24: 821466 | AE24: =IF(AD24>=AD23,AD24-AD23,0)*0.53 -> 1704.48 | AF24: 904919 | AG24: =IF(AF24>=AF23,AF24-AF23,0)*0.53 -> 10.6 | AH24: 275493.56 | AI24: =IF(AH24>=AH23,AH24-AH23,0)*0.53 -> 1142.9744 | AJ24: 881709.44 | AK24: =IF(AJ24>=AJ23,AJ24-AJ23,0)*0.53 -> 3887.7856 | AL24: 545429.78 | AM24: =IF(AL24>=AL23,AL24-AL23,0)*0.53 -> 111.71222 | AN24: =W24+Y24+AA24+AC24+AE24+AG24+AI24+AK24+AM24 -> 14098.059 | AO24: 7937738 | AP24: =IF(AO24>=AO23,AO24-AO23,0)*0.1125 -> 282.7125 | AQ24: 730771 | AR24: =IF(AQ24>=AQ23,AQ24-AQ23,0) -> 149 | AS24: 998053 | AT24: =IF(AS24>=AS23,AS24-AS23,0) -> 177 | AU24: 820521.22 | AV24: =IF(AU24>=AU23,AU24-AU23,0) -> 61.222222 | AW24: 2785830.9 | AX24: =IF(AW24>=AW23,AW24-AW23,0) -> 1073.8889 | AY24: 229733 | AZ24: =IF(AY24>=AY23,AY24-AY23,0) -> 0 | BA24: 20267973 | BB24: =IF(BA24>=BA23,BA24-BA23,0) -> 5356.8889 | BC24: 614166 | BD24: =IF(BC24>=BC23,BC24-BC23,0) -> 282 | BE24: 38437 | BF24: =IF(BE24>=BE23,BE24-BE23,0) -> 55 | BG24: 25412251 | BH24: =IF(BG24>=BG23,BG24-BG23,0)-(0.45*BN24)-(0.45*BP24)-BR24 -> 6301.6 | BI24: =AP24+AR24+AT24+AV24+AX24+AZ24+BB24+BD24+BF24+BH24 -> 13739.313 | BJ24: =BI24+AN24 -> 27837.371 | BK24: 1470013 | BL24: =IF(BK24>=BK23,BK24-BK23,0) -> 263 | BM24: 4168720 | BN24: =IF(BM24>=BM23,BM24-BM23,0) -> 1444 | BO24: 438101 | BP24: =IF(BO24>=BO23,BO24-BO23,0) -> 108 | BQ24: 547630 | BR24: =IF(BQ24>=BQ23,BQ24-BQ23,0) -> 135 | BS24: =J24+Q24+AN24+BI24 -> 33703.371 | BT24: 191 | BU24: =IF(BS24>0,BS24/BT24,0) -> 176.45744 | BW24: =IF(BS24>0,BS24/BV24,0) -> #DIV/0! | BX24: =((BS24-Q24)*$BZ$1)+(Q24*$BR$1) -> 38974.877 | BY24: =IF(BX24>0,BX24/BT24,0) -> 204.05695 | BZ24: =IF(BX24>0,BX24/BV24,0) -> #DIV/0!
A25: 20 | C25: =IF(+B25-B24>0,B25-B24,(B25-B24)>0)*800 -> 0 | E25: =IF(+D25-D24>0,D25-D24,(D25-D24)>0)*80 -> 0 | G25: =IF(+F25-F24>0,F25-F24,(F25-F24)>0)*10 -> 0 | I25: 25146342 | J25: =IF(I25>=I24,I25-I24,0) -> 5348 | K25: =M25+O25 -> 4165.5926 | L25: 74271.852 | M25: =IF(L25>=L24,L25-L24,0) -> 1969.6296 | N25: 105356.19 | O25: =IF(N25>=N24,N25-N24,0) -> 2195.963 | P25: 225193 | Q25: =IF(P25>=P24,P25-P24,0)*30 -> 540 | R25: 211683 | S25: =IF(R25>=R24,R25-R24,0) -> 144 | T25: 386222 | U25: =IF(T25>=T24,T25-T24,0) -> 267 | V25: 336057.22 | W25: =IF(V25>=V24,V25-V24,0)*0.53 -> 3601.1144 | X25: 551396 | Y25: =IF(X25>=X24,X25-X24,0)*0.53 -> 0 | Z25: 596019 | AA25: =IF(Z25>=Z24,Z25-Z24,0)*0.53 -> 3610.0067 | AB25: 890810 | AC25: =IF(AB25>=AB24,AB25-AB24,0)*0.53 -> 0 | AD25: 824831 | AE25: =IF(AD25>=AD24,AD25-AD24,0)*0.53 -> 1783.45 | AF25: 904940 | AG25: =IF(AF25>=AF24,AF25-AF24,0)*0.53 -> 11.13 | AH25: 277669.96 | AI25: =IF(AH25>=AH24,AH25-AH24,0)*0.53 -> 1153.4959 | AJ25: 888879.7 | AK25: =IF(AJ25>=AJ24,AJ25-AJ24,0)*0.53 -> 3800.2374 | AL25: 545639.81 | AM25: =IF(AL25>=AL24,AL25-AL24,0)*0.53 -> 111.31963 | AN25: =W25+Y25+AA25+AC25+AE25+AG25+AI25+AK25+AM25 -> 14070.754 | AO25: 7940525 | AP25: =IF(AO25>=AO24,AO25-AO24,0)*0.1125 -> 313.5375 | AQ25: 730943 | AR25: =IF(AQ25>=AQ24,AQ25-AQ24,0) -> 172 | AS25: 998197 | AT25: =IF(AS25>=AS24,AS25-AS24,0) -> 144 | AU25: 820581.85 | AV25: =IF(AU25>=AU24,AU25-AU24,0) -> 60.62963 | AW25: 2786901.1 | AX25: =IF(AW25>=AW24,AW25-AW24,0) -> 1070.1852 | AY25: 229733 | AZ25: =IF(AY25>=AY24,AY25-AY24,0) -> 0 | BA25: 20273135 | BB25: =IF(BA25>=BA24,BA25-BA24,0) -> 5162 | BC25: 614470 | BD25: =IF(BC25>=BC24,BC25-BC24,0) -> 304 | BE25: 38492 | BF25: =IF(BE25>=BE24,BE25-BE24,0) -> 55 | BG25: 25419675 | BH25: =IF(BG25>=BG24,BG25-BG24,0)-(0.45*BN25)-(0.45*BP25)-BR25 -> 6552.75 | BI25: =AP25+AR25+AT25+AV25+AX25+AZ25+BB25+BD25+BF25+BH25 -> 13834.102 | BJ25: =BI25+AN25 -> 27904.856 | BK25: 1470307 | BL25: =IF(BK25>=BK24,BK25-BK24,0) -> 294 | BM25: 4170217 | BN25: =IF(BM25>=BM24,BM25-BM24,0) -> 1497 | BO25: 438209 | BP25: =IF(BO25>=BO24,BO25-BO24,0) -> 108 | BQ25: 547779 | BR25: =IF(BQ25>=BQ24,BQ25-BQ24,0) -> 149 | BS25: =J25+Q25+AN25+BI25 -> 33792.856 | BT25: 223 | BU25: =IF(BS25>0,BS25/BT25,0) -> 151.53747 | BW25: =IF(BS25>0,BS25/BV25,0) -> #DIV/0! | BX25: =((BS25-Q25)*$BZ$1)+(Q25*$BR$1) -> 39104.785 | BY25: =IF(BX25>0,BX25/BT25,0) -> 175.35778 | BZ25: =IF(BX25>0,BX25/BV25,0) -> #DIV/0!
A26: 21 | C26: =IF(+B26-B25>0,B26-B25,(B26-B25)>0)*800 -> 0 | E26: =IF(+D26-D25>0,D26-D25,(D26-D25)>0)*80 -> 0 | G26: =IF(+F26-F25>0,F26-F25,(F26-F25)>0)*10 -> 0 | H26: 66 | I26: 25151307 | J26: =IF(I26>=I25,I26-I25,0) -> 4965 | K26: =M26+O26 -> 4162.963 | L26: 76019 | M26: =IF(L26>=L25,L26-L25,0) -> 1747.1481 | N26: 107772 | O26: =IF(N26>=N25,N26-N25,0) -> 2415.8148 | P26: 225215 | Q26: =IF(P26>=P25,P26-P25,0)*30 -> 660 | R26: 211822 | S26: =IF(R26>=R25,R26-R25,0) -> 139 | T26: 386481 | U26: =IF(T26>=T25,T26-T25,0) -> 259 | V26: 344584 | W26: =IF(V26>=V25,V26-V25,0)*0.53 -> 4519.1922 | X26: 550496 | Y26: =IF(X26>=X25,X26-X25,0)*0.53 -> 0 | Z26: 604331 | AA26: =IF(Z26>=Z25,Z26-Z25,0)*0.53 -> 4405.36 | AB26: 890810 | AC26: =IF(AB26>=AB25,AB26-AB25,0)*0.53 -> 0 | AD26: 826363 | AE26: =IF(AD26>=AD25,AD26-AD25,0)*0.53 -> 811.96 | AF26: 906402 | AG26: =IF(AF26>=AF25,AF26-AF25,0)*0.53 -> 774.86 | AH26: 279833.14 | AI26: =IF(AH26>=AH25,AH26-AH25,0)*0.53 -> 1146.4816 | AJ26: 895727 | AK26: =IF(AJ26>=AJ25,AJ26-AJ25,0)*0.53 -> 3629.067 | AL26: 545841 | AM26: =IF(AL26>=AL25,AL26-AL25,0)*0.53 -> 106.62815 | AN26: =W26+Y26+AA26+AC26+AE26+AG26+AI26+AK26+AM26 -> 15393.549 | AO26: 7943246 | AP26: =IF(AO26>=AO25,AO26-AO25,0)*0.1125 -> 306.1125 | AQ26: 731103 | AR26: =IF(AQ26>=AQ25,AQ26-AQ25,0) -> 160 | AS26: 998340 | AT26: =IF(AS26>=AS25,AS26-AS25,0) -> 143 | AU26: 820631 | AV26: =IF(AU26>=AU25,AU26-AU25,0) -> 49.148148 | AW26: 2788225 | AX26: =IF(AW26>=AW25,AW26-AW25,0) -> 1323.9259 | AY26: 229733 | AZ26: =IF(AY26>=AY25,AY26-AY25,0) -> 0 | BA26: 20278179 | BB26: =IF(BA26>=BA25,BA26-BA25,0) -> 5044 | BC26: 614764 | BD26: =IF(BC26>=BC25,BC26-BC25,0) -> 294 | BE26: 38547 | BF26: =IF(BE26>=BE25,BE26-BE25,0) -> 55 | BG26: 25426816 | BH26: =IF(BG26>=BG25,BG26-BG25,0)-(0.45*BN26)-(0.45*BP26)-BR26 -> 6342.65 | BI26: =AP26+AR26+AT26+AV26+AX26+AZ26+BB26+BD26+BF26+BH26 -> 13717.837 | BJ26: =BI26+AN26 -> 29111.386 | BK26: 1470592 | BL26: =IF(BK26>=BK25,BK26-BK25,0) -> 285 | BM26: 4171574 | BN26: =IF(BM26>=BM25,BM26-BM25,0) -> 1357 | BO26: 438315 | BP26: =IF(BO26>=BO25,BO26-BO25,0) -> 106 | BQ26: 547919 | BR26: =IF(BQ26>=BQ25,BQ26-BQ25,0) -> 140 | BS26: =J26+Q26+AN26+BI26 -> 34736.386 | BT26: 212 | BU26: =IF(BS26>0,BS26/BT26,0) -> 163.85088 | BW26: =IF(BS26>0,BS26/BV26,0) -> #DIV/0! | BX26: =((BS26-Q26)*$BZ$1)+(Q26*$BR$1) -> 40243.843 | BY26: =IF(BX26>0,BX26/BT26,0) -> 189.82945 | BZ26: =IF(BX26>0,BX26/BV26,0) -> #DIV/0!
A27: 22 | C27: =IF(+B27-B26>0,B27-B26,(B27-B26)>0)*800 -> 0 | E27: =IF(+D27-D26>0,D27-D26,(D27-D26)>0)*80 -> 0 | G27: =IF(+F27-F26>0,F27-F26,(F27-F26)>0)*10 -> 0 | I27: 25156128 | J27: =IF(I27>=I26,I27-I26,0) -> 4821 | K27: =M27+O27 -> 4080 | L27: 77874 | M27: =IF(L27>=L26,L27-L26,0) -> 1855 | N27: 109997 | O27: =IF(N27>=N26,N27-N26,0) -> 2225 | P27: 225238 | Q27: =IF(P27>=P26,P27-P26,0)*30 -> 690 | R27: 211966 | S27: =IF(R27>=R26,R27-R26,0) -> 144 | T27: 386770 | U27: =IF(T27>=T26,T27-T26,0) -> 289 | V27: 350428 | W27: =IF(V27>=V26,V27-V26,0)*0.53 -> 3097.32 | X27: 553730 | Y27: =IF(X27>=X26,X27-X26,0)*0.53 -> 1714.02 | Z27: 611967 | AA27: =IF(Z27>=Z26,Z27-Z26,0)*0.53 -> 4047.08 | AB27: 890824 | AC27: =IF(AB27>=AB26,AB27-AB26,0)*0.53 -> 7.42 | AD27: 826386 | AE27: =IF(AD27>=AD26,AD27-AD26,0)*0.53 -> 12.19 | AF27: 910111 | AG27: =IF(AF27>=AF26,AF27-AF26,0)*0.53 -> 1965.77 | AH27: 282060 | AI27: =IF(AH27>=AH26,AH27-AH26,0)*0.53 -> 1180.238 | AJ27: 902609 | AK27: =IF(AJ27>=AJ26,AJ27-AJ26,0)*0.53 -> 3647.46 | AL27: 546049 | AM27: =IF(AL27>=AL26,AL27-AL26,0)*0.53 -> 110.24 | AN27: =W27+Y27+AA27+AC27+AE27+AG27+AI27+AK27+AM27 -> 15781.738 | AO27: 7946153 | AP27: =IF(AO27>=AO26,AO27-AO26,0)*0.1125 -> 327.0375 | AQ27: 731264 | AR27: =IF(AQ27>=AQ26,AQ27-AQ26,0) -> 161 | AS27: 998488 | AT27: =IF(AS27>=AS26,AS27-AS26,0) -> 148 | AU27: 820708 | AV27: =IF(AU27>=AU26,AU27-AU26,0) -> 77 | AW27: 2789354 | AX27: =IF(AW27>=AW26,AW27-AW26,0) -> 1129 | AY27: 229794 | AZ27: =IF(AY27>=AY26,AY27-AY26,0) -> 61 | BA27: 20283253 | BB27: =IF(BA27>=BA26,BA27-BA26,0) -> 5074 | BC27: 615042 | BD27: =IF(BC27>=BC26,BC27-BC26,0) -> 278 | BE27: 38730 | BF27: =IF(BE27>=BE26,BE27-BE26,0) -> 183 | BG27: 25434323 | BH27: =IF(BG27>=BG26,BG27-BG26,0)-(0.45*BN27)-(0.45*BP27)-BR27 -> 6617.4 | BI27: =AP27+AR27+AT27+AV27+AX27+AZ27+BB27+BD27+BF27+BH27 -> 14055.438 | BJ27: =BI27+AN27 -> 29837.176 | BK27: 1470805 | BL27: =IF(BK27>=BK26,BK27-BK26,0) -> 213 | BM27: 4173133 | BN27: =IF(BM27>=BM26,BM27-BM26,0) -> 1559 | BO27: 438424 | BP27: =IF(BO27>=BO26,BO27-BO26,0) -> 109 | BQ27: 548058 | BR27: =IF(BQ27>=BQ26,BQ27-BQ26,0) -> 139 | BS27: =J27+Q27+AN27+BI27 -> 35348.176 | BT27: 182 | BU27: =IF(BS27>0,BS27/BT27,0) -> 194.22074 | BW27: =IF(BS27>0,BS27/BV27,0) -> #DIV/0! | BX27: =((BS27-Q27)*$BZ$1)+(Q27*$BR$1) -> 40960.902 | BY27: =IF(BX27>0,BX27/BT27,0) -> 225.0599 | BZ27: =IF(BX27>0,BX27/BV27,0) -> #DIV/0!
A28: 23 | C28: =IF(+B28-B27>0,B28-B27,(B28-B27)>0)*800 -> 0 | E28: =IF(+D28-D27>0,D28-D27,(D28-D27)>0)*80 -> 0 | G28: =IF(+F28-F27>0,F28-F27,(F28-F27)>0)*10 -> 0 | H28: 67 | I28: 25160409 | J28: =IF(I28>=I27,I28-I27,0) -> 4281 | K28: =M28+O28 -> 4072 | L28: 79653 | M28: =IF(L28>=L27,L28-L27,0) -> 1779 | N28: 112290 | O28: =IF(N28>=N27,N28-N27,0) -> 2293 | P28: 225258 | Q28: =IF(P28>=P27,P28-P27,0)*30 -> 600 | R28: 212103 | S28: =IF(R28>=R27,R28-R27,0) -> 137 | T28: 387048 | U28: =IF(T28>=T27,T28-T27,0) -> 278 | V28: 350428 | W28: =IF(V28>=V27,V28-V27,0)*0.53 -> 0 | X28: 561050 | Y28: =IF(X28>=X27,X28-X27,0)*0.53 -> 3879.6 | Z28: 617910 | AA28: =IF(Z28>=Z27,Z28-Z27,0)*0.53 -> 3149.79 | AB28: 892389 | AC28: =IF(AB28>=AB27,AB28-AB27,0)*0.53 -> 829.45 | AD28: 1562 | AE28: =IF(AD28>=AD27,AD28-AD27,0)*0.53 -> 0 | AF28: 912700 | AG28: =IF(AF28>=AF27,AF28-AF27,0)*0.53 -> 1372.17 | AH28: 284176 | AI28: =IF(AH28>=AH27,AH28-AH27,0)*0.53 -> 1121.48 | AJ28: 909735 | AK28: =IF(AJ28>=AJ27,AJ28-AJ27,0)*0.53 -> 3776.78 | AL28: 546257 | AM28: =IF(AL28>=AL27,AL28-AL27,0)*0.53 -> 110.24 | AN28: =W28+Y28+AA28+AC28+AE28+AG28+AI28+AK28+AM28 -> 14239.51 | AO28: 7949095 | AP28: =IF(AO28>=AO27,AO28-AO27,0)*0.1125 -> 330.975 | AQ28: 731424 | AR28: =IF(AQ28>=AQ27,AQ28-AQ27,0) -> 160 | AS28: 998643 | AT28: =IF(AS28>=AS27,AS28-AS27,0) -> 155 | AU28: 820769 | AV28: =IF(AU28>=AU27,AU28-AU27,0) -> 61 | AW28: 2790374 | AX28: =IF(AW28>=AW27,AW28-AW27,0) -> 1020 | AY28: 229805 | AZ28: =IF(AY28>=AY27,AY28-AY27,0) -> 11 | BA28: 20288493 | BB28: =IF(BA28>=BA27,BA28-BA27,0) -> 5240 | BC28: 615293 | BD28: =IF(BC28>=BC27,BC28-BC27,0) -> 251 | BE28: 38800 | BF28: =IF(BE28>=BE27,BE28-BE27,0) -> 70 | BG28: 25441643 | BH28: =IF(BG28>=BG27,BG28-BG27,0)-(0.45*BN28)-(0.45*BP28)-BR28 -> 6440.4 | BI28: =AP28+AR28+AT28+AV28+AX28+AZ28+BB28+BD28+BF28+BH28 -> 13739.375 | BJ28: =BI28+AN28 -> 27978.885 | BK28: 1471061 | BL28: =IF(BK28>=BK27,BK28-BK27,0) -> 256 | BM28: 4174675 | BN28: =IF(BM28>=BM27,BM28-BM27,0) -> 1542 | BO28: 438530 | BP28: =IF(BO28>=BO27,BO28-BO27,0) -> 106 | BQ28: 548196 | BR28: =IF(BQ28>=BQ27,BQ28-BQ27,0) -> 138 | BS28: =J28+Q28+AN28+BI28 -> 32859.885 | BT28: 182 | BU28: =IF(BS28>0,BS28/BT28,0) -> 180.54882 | BW28: =IF(BS28>0,BS28/BV28,0) -> #DIV/0! | BX28: =((BS28-Q28)*$BZ$1)+(Q28*$BR$1) -> 38058.868 | BY28: =IF(BX28>0,BX28/BT28,0) -> 209.11466 | BZ28: =IF(BX28>0,BX28/BV28,0) -> #DIV/0!
A29: 24 | C29: =IF(+B29-B28>0,B29-B28,(B29-B28)>0)*800 -> 0 | E29: =IF(+D29-D28>0,D29-D28,(D29-D28)>0)*80 -> 0 | G29: =IF(+F29-F28>0,F29-F28,(F29-F28)>0)*10 -> 0 | I29: 25164772 | J29: =IF(I29>=I28,I29-I28,0) -> 4363 | K29: =M29+O29 -> 4310 | L29: 81586 | M29: =IF(L29>=L28,L29-L28,0) -> 1933 | N29: 114667 | O29: =IF(N29>=N28,N29-N28,0) -> 2377 | P29: 225281 | Q29: =IF(P29>=P28,P29-P28,0)*30 -> 690 | R29: 212245 | S29: =IF(R29>=R28,R29-R28,0) -> 142 | T29: 387335 | U29: =IF(T29>=T28,T29-T28,0) -> 287 | V29: 350428 | W29: =IF(V29>=V28,V29-V28,0)*0.53 -> 0 | X29: 568525 | Y29: =IF(X29>=X28,X29-X28,0)*0.53 -> 3961.75 | Z29: 617910 | AA29: =IF(Z29>=Z28,Z29-Z28,0)*0.53 -> 0 | AB29: 899456 | AC29: =IF(AB29>=AB28,AB29-AB28,0)*0.53 -> 3745.51 | AD29: 1562 | AE29: =IF(AD29>=AD28,AD29-AD28,0)*0.53 -> 0 | AF29: 913129 | AG29: =IF(AF29>=AF28,AF29-AF28,0)*0.53 -> 227.37 | AH29: 286352 | AI29: =IF(AH29>=AH28,AH29-AH28,0)*0.53 -> 1153.28 | AJ29: 916876 | AK29: =IF(AJ29>=AJ28,AJ29-AJ28,0)*0.53 -> 3784.73 | AL29: 546487 | AM29: =IF(AL29>=AL28,AL29-AL28,0)*0.53 -> 121.9 | AN29: =W29+Y29+AA29+AC29+AE29+AG29+AI29+AK29+AM29 -> 12994.54 | AO29: 7952030 | AP29: =IF(AO29>=AO28,AO29-AO28,0)*0.1125 -> 330.1875 | AQ29: 731583 | AR29: =IF(AQ29>=AQ28,AQ29-AQ28,0) -> 159 | AS29: 998814 | AT29: =IF(AS29>=AS28,AS29-AS28,0) -> 171 | AU29: 820835 | AV29: =IF(AU29>=AU28,AU29-AU28,0) -> 66 | AW29: 2791349 | AX29: =IF(AW29>=AW28,AW29-AW28,0) -> 975 | AY29: 229816 | AZ29: =IF(AY29>=AY28,AY29-AY28,0) -> 11 | BA29: 20293402 | BB29: =IF(BA29>=BA28,BA29-BA28,0) -> 4909 | BC29: 615552 | BD29: =IF(BC29>=BC28,BC29-BC28,0) -> 259 | BE29: 38871 | BF29: =IF(BE29>=BE28,BE29-BE28,0) -> 71 | BG29: 25449016 | BH29: =IF(BG29>=BG28,BG29-BG28,0)-(0.45*BN29)-(0.45*BP29)-BR29 -> 6482.2 | BI29: =AP29+AR29+AT29+AV29+AX29+AZ29+BB29+BD29+BF29+BH29 -> 13433.388 | BJ29: =BI29+AN29 -> 26427.927 | BK29: 1471319 | BL29: =IF(BK29>=BK28,BK29-BK28,0) -> 258 | BM29: 4176235 | BN29: =IF(BM29>=BM28,BM29-BM28,0) -> 1560 | BO29: 438634 | BP29: =IF(BO29>=BO28,BO29-BO28,0) -> 104 | BQ29: 548338 | BR29: =IF(BQ29>=BQ28,BQ29-BQ28,0) -> 142 | BS29: =J29+Q29+AN29+BI29 -> 31480.928 | BT29: 175 | BU29: =IF(BS29>0,BS29/BT29,0) -> 179.89101 | BW29: =IF(BS29>0,BS29/BV29,0) -> #DIV/0! | BX29: =((BS29-Q29)*$BZ$1)+(Q29*$BR$1) -> 36513.567 | BY29: =IF(BX29>0,BX29/BT29,0) -> 208.64895 | BZ29: =IF(BX29>0,BX29/BV29,0) -> #DIV/0!
A30: 25 | C30: =IF(+B30-B29>0,B30-B29,(B30-B29)>0)*800 -> 0 | E30: =IF(+D30-D29>0,D30-D29,(D30-D29)>0)*80 -> 0 | G30: =IF(+F30-F29>0,F30-F29,(F30-F29)>0)*10 -> 0 | H30: 68 | I30: 25171295 | J30: =IF(I30>=I29,I30-I29,0) -> 6523 | K30: =M30+O30 -> 4864 | L30: 84034 | M30: =IF(L30>=L29,L30-L29,0) -> 2448 | N30: 117083 | O30: =IF(N30>=N29,N30-N29,0) -> 2416 | P30: 225302 | Q30: =IF(P30>=P29,P30-P29,0)*30 -> 630 | R30: 212389 | S30: =IF(R30>=R29,R30-R29,0) -> 144 | T30: 387630 | U30: =IF(T30>=T29,T30-T29,0) -> 295 | V30: 350570 | W30: =IF(V30>=V29,V30-V29,0)*0.53 -> 75.26 | X30: 577477 | Y30: =IF(X30>=X29,X30-X29,0)*0.53 -> 4744.56 | Z30: 618241 | AA30: =IF(Z30>=Z29,Z30-Z29,0)*0.53 -> 175.43 | AB30: 908733 | AC30: =IF(AB30>=AB29,AB30-AB29,0)*0.53 -> 4916.81 | AD30: 1562 | AE30: =IF(AD30>=AD29,AD30-AD29,0)*0.53 -> 0 | AF30: 913149 | AG30: =IF(AF30>=AF29,AF30-AF29,0)*0.53 -> 10.6 | AH30: 288917 | AI30: =IF(AH30>=AH29,AH30-AH29,0)*0.53 -> 1359.45 | AJ30: 925869 | AK30: =IF(AJ30>=AJ29,AJ30-AJ29,0)*0.53 -> 4766.29 | AL30: 546734 | AM30: =IF(AL30>=AL29,AL30-AL29,0)*0.53 -> 130.91 | AN30: =W30+Y30+AA30+AC30+AE30+AG30+AI30+AK30+AM30 -> 16179.31 | AO30: 7954842 | AP30: =IF(AO30>=AO29,AO30-AO29,0)*0.1125 -> 316.35 | AQ30: 731741 | AR30: =IF(AQ30>=AQ29,AQ30-AQ29,0) -> 158 | AS30: 999010 | AT30: =IF(AS30>=AS29,AS30-AS29,0) -> 196 | AU30: 820918 | AV30: =IF(AU30>=AU29,AU30-AU29,0) -> 83 | AW30: 2792653 | AX30: =IF(AW30>=AW29,AW30-AW29,0) -> 1304 | AY30: 229828 | AZ30: =IF(AY30>=AY29,AY30-AY29,0) -> 12 | BA30: 20299589 | BB30: =IF(BA30>=BA29,BA30-BA29,0) -> 6187 | BC30: 615816 | BD30: =IF(BC30>=BC29,BC30-BC29,0) -> 264 | BE30: 38944 | BF30: =IF(BE30>=BE29,BE30-BE29,0) -> 73 | BG30: 25456667 | BH30: =IF(BG30>=BG29,BG30-BG29,0)-(0.45*BN30)-(0.45*BP30)-BR30 -> 6741.2 | BI30: =AP30+AR30+AT30+AV30+AX30+AZ30+BB30+BD30+BF30+BH30 -> 15334.55 | BJ30: =BI30+AN30 -> 31513.86 | BK30: 1471603 | BL30: =IF(BK30>=BK29,BK30-BK29,0) -> 284 | BM30: 4177846 | BN30: =IF(BM30>=BM29,BM30-BM29,0) -> 1611 | BO30: 438747 | BP30: =IF(BO30>=BO29,BO30-BO29,0) -> 113 | BQ30: 548472 | BR30: =IF(BQ30>=BQ29,BQ30-BQ29,0) -> 134 | BS30: =J30+Q30+AN30+BI30 -> 38666.86 | BT30: 173 | BU30: =IF(BS30>0,BS30/BT30,0) -> 223.50786 | BW30: =IF(BS30>0,BS30/BV30,0) -> #DIV/0! | BX30: =((BS30-Q30)*$BZ$1)+(Q30*$BR$1) -> 44750.389 | BY30: =IF(BX30>0,BX30/BT30,0) -> 258.67277 | BZ30: =IF(BX30>0,BX30/BV30,0) -> #DIV/0!
A31: 26 | C31: =IF(+B31-B30>0,B31-B30,(B31-B30)>0)*800 -> 0 | E31: =IF(+D31-D30>0,D31-D30,(D31-D30)>0)*80 -> 0 | G31: =IF(+F31-F30>0,F31-F30,(F31-F30)>0)*10 -> 0 | I31: 25176487 | J31: =IF(I31>=I30,I31-I30,0) -> 5192 | K31: =M31+O31 -> 3391 | L31: 85748 | M31: =IF(L31>=L30,L31-L30,0) -> 1714 | N31: 118760 | O31: =IF(N31>=N30,N31-N30,0) -> 1677 | P31: 225325 | Q31: =IF(P31>=P30,P31-P30,0)*30 -> 690 | R31: 212528 | S31: =IF(R31>=R30,R31-R30,0) -> 139 | T31: 387882 | U31: =IF(T31>=T30,T31-T30,0) -> 252 | V31: 350570 | W31: =IF(V31>=V30,V31-V30,0)*0.53 -> 0 | X31: 583559 | Y31: =IF(X31>=X30,X31-X30,0)*0.53 -> 3223.46 | Z31: 618241 | AA31: =IF(Z31>=Z30,Z31-Z30,0)*0.53 -> 0 | AB31: 914635 | AC31: =IF(AB31>=AB30,AB31-AB30,0)*0.53 -> 3128.06 | AD31: 1562 | AE31: =IF(AD31>=AD30,AD31-AD30,0)*0.53 -> 0 | AF31: 913169 | AG31: =IF(AF31>=AF30,AF31-AF30,0)*0.53 -> 10.6 | AH31: 290606 | AI31: =IF(AH31>=AH30,AH31-AH30,0)*0.53 -> 895.17 | AJ31: 931497 | AK31: =IF(AJ31>=AJ30,AJ31-AJ30,0)*0.53 -> 2982.84 | AL31: 546910 | AM31: =IF(AL31>=AL30,AL31-AL30,0)*0.53 -> 93.28 | AN31: =W31+Y31+AA31+AC31+AE31+AG31+AI31+AK31+AM31 -> 10333.41 | AO31: 7957355 | AP31: =IF(AO31>=AO30,AO31-AO30,0)*0.1125 -> 282.7125 | AQ31: 731892 | AR31: =IF(AQ31>=AQ30,AQ31-AQ30,0) -> 151 | AS31: 999185 | AT31: =IF(AS31>=AS30,AS31-AS30,0) -> 175 | AU31: 820963 | AV31: =IF(AU31>=AU30,AU31-AU30,0) -> 45 | AW31: 2793611 | AX31: =IF(AW31>=AW30,AW31-AW30,0) -> 958 | AY31: 229839 | AZ31: =IF(AY31>=AY30,AY31-AY30,0) -> 11 | BA31: 20303962 | BB31: =IF(BA31>=BA30,BA31-BA30,0) -> 4373 | BC31: 616112 | BD31: =IF(BC31>=BC30,BC31-BC30,0) -> 296 | BE31: 39014 | BF31: =IF(BE31>=BE30,BE31-BE30,0) -> 70 | BG31: 25464300 | BH31: =IF(BG31>=BG30,BG31-BG30,0)-(0.45*BN31)-(0.45*BP31)-BR31 -> 6764.45 | BI31: =AP31+AR31+AT31+AV31+AX31+AZ31+BB31+BD31+BF31+BH31 -> 13126.162 | BJ31: =BI31+AN31 -> 23459.573 | BK31: 1471868 | BL31: =IF(BK31>=BK30,BK31-BK30,0) -> 265 | BM31: 4179355 | BN31: =IF(BM31>=BM30,BM31-BM30,0) -> 1509 | BO31: 438857 | BP31: =IF(BO31>=BO30,BO31-BO30,0) -> 110 | BQ31: 548612 | BR31: =IF(BQ31>=BQ30,BQ31-BQ30,0) -> 140 | BS31: =J31+Q31+AN31+BI31 -> 29341.573 | BT31: 174 | BU31: =IF(BS31>0,BS31/BT31,0) -> 168.62973 | BW31: =IF(BS31>0,BS31/BV31,0) -> #DIV/0! | BX31: =((BS31-Q31)*$BZ$1)+(Q31*$BR$1) -> 34053.308 | BY31: =IF(BX31>0,BX31/BT31,0) -> 195.70867 | BZ31: =IF(BX31>0,BX31/BV31,0) -> #DIV/0!
A32: 27 | C32: =IF(+B32-B31>0,B32-B31,(B32-B31)>0)*800 -> 0 | E32: =IF(+D32-D31>0,D32-D31,(D32-D31)>0)*80 -> 0 | G32: =IF(+F32-F31>0,F32-F31,(F32-F31)>0)*10 -> 0 | H32: 69 | I32: 25182031 | J32: =IF(I32>=I31,I32-I31,0) -> 5544 | K32: =M32+O32 -> 3886 | L32: 87730 | M32: =IF(L32>=L31,L32-L31,0) -> 1982 | N32: 120664 | O32: =IF(N32>=N31,N32-N31,0) -> 1904 | P32: 225345 | Q32: =IF(P32>=P31,P32-P31,0)*30 -> 600 | R32: 212655 | S32: =IF(R32>=R31,R32-R31,0) -> 127 | T32: 388117 | U32: =IF(T32>=T31,T32-T31,0) -> 235 | V32: 350570 | W32: =IF(V32>=V31,V32-V31,0)*0.53 -> 0 | X32: 590912 | Y32: =IF(X32>=X31,X32-X31,0)*0.53 -> 3897.09 | Z32: 618241 | AA32: =IF(Z32>=Z31,Z32-Z31,0)*0.53 -> 0 | AB32: 921470 | AC32: =IF(AB32>=AB31,AB32-AB31,0)*0.53 -> 3622.55 | AD32: 1562 | AE32: =IF(AD32>=AD31,AD32-AD31,0)*0.53 -> 0 | AF32: 913187 | AG32: =IF(AF32>=AF31,AF32-AF31,0)*0.53 -> 9.54 | AH32: 292665 | AI32: =IF(AH32>=AH31,AH32-AH31,0)*0.53 -> 1091.27 | AJ32: 938305 | AK32: =IF(AJ32>=AJ31,AJ32-AJ31,0)*0.53 -> 3608.24 | AL32: 547114 | AM32: =IF(AL32>=AL31,AL32-AL31,0)*0.53 -> 108.12 | AN32: =W32+Y32+AA32+AC32+AE32+AG32+AI32+AK32+AM32 -> 12336.81 | AO32: 7959978 | AP32: =IF(AO32>=AO31,AO32-AO31,0)*0.1125 -> 295.0875 | AQ32: 732057 | AR32: =IF(AQ32>=AQ31,AQ32-AQ31,0) -> 165 | AS32: 999327 | AT32: =IF(AS32>=AS31,AS32-AS31,0) -> 142 | AU32: 821017 | AV32: =IF(AU32>=AU31,AU32-AU31,0) -> 54 | AW32: 2794684 | AX32: =IF(AW32>=AW31,AW32-AW31,0) -> 1073 | AY32: 229849 | AZ32: =IF(AY32>=AY31,AY32-AY31,0) -> 10 | BA32: 20308674 | BB32: =IF(BA32>=BA31,BA32-BA31,0) -> 4712 | BC32: 616364 | BD32: =IF(BC32>=BC31,BC32-BC31,0) -> 252 | BE32: 39085 | BF32: =IF(BE32>=BE31,BE32-BE31,0) -> 71 | BG32: 25470985 | BH32: =IF(BG32>=BG31,BG32-BG31,0)-(0.45*BN32)-(0.45*BP32)-BR32 -> 5879 | BI32: =AP32+AR32+AT32+AV32+AX32+AZ32+BB32+BD32+BF32+BH32 -> 12653.087 | BJ32: =BI32+AN32 -> 24989.897 | BK32: 1472105 | BL32: =IF(BK32>=BK31,BK32-BK31,0) -> 237 | BM32: 4180730 | BN32: =IF(BM32>=BM31,BM32-BM31,0) -> 1375 | BO32: 438962 | BP32: =IF(BO32>=BO31,BO32-BO31,0) -> 105 | BQ32: 548752 | BR32: =IF(BQ32>=BQ31,BQ32-BQ31,0) -> 140 | BS32: =J32+Q32+AN32+BI32 -> 31133.897 | BT32: 199 | BU32: =IF(BS32>0,BS32/BT32,0) -> 156.45175 | BW32: =IF(BS32>0,BS32/BV32,0) -> #DIV/0! | BX32: =((BS32-Q32)*$BZ$1)+(Q32*$BR$1) -> 36073.982 | BY32: =IF(BX32>0,BX32/BT32,0) -> 181.27629 | BZ32: =IF(BX32>0,BX32/BV32,0) -> #DIV/0!
A33: 28 | C33: =IF(+B33-B32>0,B33-B32,(B33-B32)>0)*800 -> 0 | E33: =IF(+D33-D32>0,D33-D32,(D33-D32)>0)*80 -> 0 | G33: =IF(+F33-F32>0,F33-F32,(F33-F32)>0)*10 -> 0 | I33: 25187422 | J33: =IF(I33>=I32,I33-I32,0) -> 5391 | K33: =M33+O33 -> 3873 | L33: 89701 | M33: =IF(L33>=L32,L33-L32,0) -> 1971 | N33: 122566 | O33: =IF(N33>=N32,N33-N32,0) -> 1902 | P33: 225367 | Q33: =IF(P33>=P32,P33-P32,0)*30 -> 660 | R33: 212798 | S33: =IF(R33>=R32,R33-R32,0) -> 143 | T33: 388394 | U33: =IF(T33>=T32,T33-T32,0) -> 277 | V33: 350570 | W33: =IF(V33>=V32,V33-V32,0)*0.53 -> 0 | X33: 598262 | Y33: =IF(X33>=X32,X33-X32,0)*0.53 -> 3895.5 | Z33: 618241 | AA33: =IF(Z33>=Z32,Z33-Z32,0)*0.53 -> 0 | AB33: 928300 | AC33: =IF(AB33>=AB32,AB33-AB32,0)*0.53 -> 3619.9 | AD33: 1562 | AE33: =IF(AD33>=AD32,AD33-AD32,0)*0.53 -> 0 | AF33: 915129 | AG33: =IF(AF33>=AF32,AF33-AF32,0)*0.53 -> 1029.26 | AH33: 294716 | AI33: =IF(AH33>=AH32,AH33-AH32,0)*0.53 -> 1087.03 | AJ33: 945107 | AK33: =IF(AJ33>=AJ32,AJ33-AJ32,0)*0.53 -> 3605.06 | AL33: 547315 | AM33: =IF(AL33>=AL32,AL33-AL32,0)*0.53 -> 106.53 | AN33: =W33+Y33+AA33+AC33+AE33+AG33+AI33+AK33+AM33 -> 13343.28 | AO33: 7962763 | AP33: =IF(AO33>=AO32,AO33-AO32,0)*0.1125 -> 313.3125 | AQ33: 732219 | AR33: =IF(AQ33>=AQ32,AQ33-AQ32,0) -> 162 | AS33: 999488 | AT33: =IF(AS33>=AS32,AS33-AS32,0) -> 161 | AU33: 821069 | AV33: =IF(AU33>=AU32,AU33-AU32,0) -> 52 | AW33: 2795680.3 | AX33: =IF(AW33>=AW32,AW33-AW32,0) -> 996.33333 | AY33: 229861 | AZ33: =IF(AY33>=AY32,AY33-AY32,0) -> 12 | BA33: 20313934 | BB33: =IF(BA33>=BA32,BA33-BA32,0) -> 5260 | BC33: 616610 | BD33: =IF(BC33>=BC32,BC33-BC32,0) -> 246 | BE33: 39158 | BF33: =IF(BE33>=BE32,BE33-BE32,0) -> 73 | BG33: 25478753 | BH33: =IF(BG33>=BG32,BG33-BG32,0)-(0.45*BN33)-(0.45*BP33)-BR33 -> 6861.1 | BI33: =AP33+AR33+AT33+AV33+AX33+AZ33+BB33+BD33+BF33+BH33 -> 14136.746 | BJ33: =BI33+AN33 -> 27480.026 | BK33: 1472283 | BL33: =IF(BK33>=BK32,BK33-BK32,0) -> 178 | BM33: 4182320 | BN33: =IF(BM33>=BM32,BM33-BM32,0) -> 1590 | BO33: 439074 | BP33: =IF(BO33>=BO32,BO33-BO32,0) -> 112 | BQ33: 548893 | BR33: =IF(BQ33>=BQ32,BQ33-BQ32,0) -> 141 | BS33: =J33+Q33+AN33+BI33 -> 33531.026 | BT33: 170 | BU33: =IF(BS33>0,BS33/BT33,0) -> 197.24133 | BW33: =IF(BS33>0,BS33/BV33,0) -> #DIV/0! | BX33: =((BS33-Q33)*$BZ$1)+(Q33*$BR$1) -> 38857.68 | BY33: =IF(BX33>0,BX33/BT33,0) -> 228.57459 | BZ33: =IF(BX33>0,BX33/BV33,0) -> #DIV/0!
A34: 29 | C34: =IF(+B34-B33>0,B34-B33,(B34-B33)>0)*800 -> 0 | E34: =IF(+D34-D33>0,D34-D33,(D34-D33)>0)*80 -> 0 | G34: =IF(+F34-F33>0,F34-F33,(F34-F33)>0)*10 -> 0 | I34: 25191857 | J34: =IF(I34>=I33,I34-I33,0) -> 4435 | K34: =M34+O34 -> 4617 | L34: 91865 | M34: =IF(L34>=L33,L34-L33,0) -> 2164 | N34: 125019 | O34: =IF(N34>=N33,N34-N33,0) -> 2453 | P34: 225386 | Q34: =IF(P34>=P33,P34-P33,0)*30 -> 570 | R34: 212938 | S34: =IF(R34>=R33,R34-R33,0) -> 140 | T34: 388665 | U34: =IF(T34>=T33,T34-T33,0) -> 271 | V34: 350570 | W34: =IF(V34>=V33,V34-V33,0)*0.53 -> 0 | X34: 606629 | Y34: =IF(X34>=X33,X34-X33,0)*0.53 -> 4434.51 | Z34: 618241 | AA34: =IF(Z34>=Z33,Z34-Z33,0)*0.53 -> 0 | AB34: 937053 | AC34: =IF(AB34>=AB33,AB34-AB33,0)*0.53 -> 4639.09 | AD34: 1562 | AE34: =IF(AD34>=AD33,AD34-AD33,0)*0.53 -> 0 | AF34: 918667 | AG34: =IF(AF34>=AF33,AF34-AF33,0)*0.53 -> 1875.14 | AH34: 297030 | AI34: =IF(AH34>=AH33,AH34-AH33,0)*0.53 -> 1226.42 | AJ34: 952794 | AK34: =IF(AJ34>=AJ33,AJ34-AJ33,0)*0.53 -> 4074.11 | AL34: 547561 | AM34: =IF(AL34>=AL33,AL34-AL33,0)*0.53 -> 130.38 | AN34: =W34+Y34+AA34+AC34+AE34+AG34+AI34+AK34+AM34 -> 16379.65 | AO34: 7965610 | AP34: =IF(AO34>=AO33,AO34-AO33,0)*0.1125 -> 320.2875 | AQ34: 732358 | AR34: =IF(AQ34>=AQ33,AQ34-AQ33,0) -> 139 | AS34: 999654 | AT34: =IF(AS34>=AS33,AS34-AS33,0) -> 166 | AU34: 821154 | AV34: =IF(AU34>=AU33,AU34-AU33,0) -> 85 | AW34: 2796895 | AX34: =IF(AW34>=AW33,AW34-AW33,0) -> 1214.6667 | AY34: 229872 | AZ34: =IF(AY34>=AY33,AY34-AY33,0) -> 11 | BA34: 20319250 | BB34: =IF(BA34>=BA33,BA34-BA33,0) -> 5316 | BC34: 616833 | BD34: =IF(BC34>=BC33,BC34-BC33,0) -> 223 | BE34: 39227 | BF34: =IF(BE34>=BE33,BE34-BE33,0) -> 69 | BG34: 25485966 | BH34: =IF(BG34>=BG33,BG34-BG33,0)-(0.45*BN34)-(0.45*BP34)-BR34 -> 6342.7 | BI34: =AP34+AR34+AT34+AV34+AX34+AZ34+BB34+BD34+BF34+BH34 -> 13886.654 | BJ34: =BI34+AN34 -> 30266.304 | BK34: 1472362 | BL34: =IF(BK34>=BK33,BK34-BK33,0) -> 79 | BM34: 4183847 | BN34: =IF(BM34>=BM33,BM34-BM33,0) -> 1527 | BO34: 439161 | BP34: =IF(BO34>=BO33,BO34-BO33,0) -> 87 | BQ34: 549037 | BR34: =IF(BQ34>=BQ33,BQ34-BQ33,0) -> 144 | BS34: =J34+Q34+AN34+BI34 -> 35271.304 | BT34: 154 | BU34: =IF(BS34>0,BS34/BT34,0) -> 229.03444 | BW34: =IF(BS34>0,BS34/BV34,0) -> #DIV/0! | BX34: =((BS34-Q34)*$BZ$1)+(Q34*$BR$1) -> 40818.5 | BY34: =IF(BX34>0,BX34/BT34,0) -> 265.05519 | BZ34: =IF(BX34>0,BX34/BV34,0) -> #DIV/0!
A35: 30 | C35: =IF(+B35-B34>0,B35-B34,(B35-B34)>0)*800 -> 0 | E35: =IF(+D35-D34>0,D35-D34,(D35-D34)>0)*80 -> 0 | G35: =IF(+F35-F34>0,F35-F34,(F35-F34)>0)*10 -> 0 | I35: 25197374 | J35: =IF(I35>=I34,I35-I34,0) -> 5517 | K35: =M35+O35 -> 4611 | L35: 94025 | M35: =IF(L35>=L34,L35-L34,0) -> 2160 | N35: 127470 | O35: =IF(N35>=N34,N35-N34,0) -> 2451 | P35: 225406 | Q35: =IF(P35>=P34,P35-P34,0)*30 -> 600 | R35: 213075 | S35: =IF(R35>=R34,R35-R34,0) -> 137 | T35: 388924 | U35: =IF(T35>=T34,T35-T34,0) -> 259 | V35: 350570 | W35: =IF(V35>=V34,V35-V34,0)*0.53 -> 0 | X35: 614991 | Y35: =IF(X35>=X34,X35-X34,0)*0.53 -> 4431.86 | Z35: 618241 | AA35: =IF(Z35>=Z34,Z35-Z34,0)*0.53 -> 0 | AB35: 945801 | AC35: =IF(AB35>=AB34,AB35-AB34,0)*0.53 -> 4636.44 | AD35: 1562 | AE35: =IF(AD35>=AD34,AD35-AD34,0)*0.53 -> 0 | AF35: 922077 | AG35: =IF(AF35>=AF34,AF35-AF34,0)*0.53 -> 1807.3 | AH35: 299344 | AI35: =IF(AH35>=AH34,AH35-AH34,0)*0.53 -> 1226.42 | AJ35: 960745 | AK35: =IF(AJ35>=AJ34,AJ35-AJ34,0)*0.53 -> 4214.03 | AL35: 547803 | AM35: =IF(AL35>=AL34,AL35-AL34,0)*0.53 -> 128.26 | AN35: =W35+Y35+AA35+AC35+AE35+AG35+AI35+AK35+AM35 -> 16444.31 | AO35: 7968469 | AP35: =IF(AO35>=AO34,AO35-AO34,0)*0.1125 -> 321.6375 | AQ35: 732498 | AR35: =IF(AQ35>=AQ34,AQ35-AQ34,0) -> 140 | AS35: 999820 | AT35: =IF(AS35>=AS34,AS35-AS34,0) -> 166 | AU35: 821236 | AV35: =IF(AU35>=AU34,AU35-AU34,0) -> 82 | AW35: 2797964.1 | AX35: =IF(AW35>=AW34,AW35-AW34,0) -> 1069.1111 | AY35: 230020 | AZ35: =IF(AY35>=AY34,AY35-AY34,0) -> 148 | BA35: 20324156 | BB35: =IF(BA35>=BA34,BA35-BA34,0) -> 4906 | BC35: 617051 | BD35: =IF(BC35>=BC34,BC35-BC34,0) -> 218 | BE35: 39300 | BF35: =IF(BE35>=BE34,BE35-BE34,0) -> 73 | BG35: 25493085 | BH35: =IF(BG35>=BG34,BG35-BG34,0)-(0.45*BN35)-(0.45*BP35)-BR35 -> 6291 | BI35: =AP35+AR35+AT35+AV35+AX35+AZ35+BB35+BD35+BF35+BH35 -> 13414.749 | BJ35: =BI35+AN35 -> 29859.059 | BK35: 1472506 | BL35: =IF(BK35>=BK34,BK35-BK34,0) -> 144 | BM35: 4185258 | BN35: =IF(BM35>=BM34,BM35-BM34,0) -> 1411 | BO35: 439250 | BP35: =IF(BO35>=BO34,BO35-BO34,0) -> 89 | BQ35: 549190 | BR35: =IF(BQ35>=BQ34,BQ35-BQ34,0) -> 153 | BS35: =J35+Q35+AN35+BI35 -> 35976.059 | BT35: 137 | BU35: =IF(BS35>0,BS35/BT35,0) -> 262.59897 | BW35: =IF(BS35>0,BS35/BV35,0) -> #DIV/0! | BX35: =((BS35-Q35)*$BZ$1)+(Q35*$BR$1) -> 41642.467 | BY35: =IF(BX35>0,BX35/BT35,0) -> 303.95962 | BZ35: =IF(BX35>0,BX35/BV35,0) -> #DIV/0!
A36: 31 | I36: 25202170 | J36: =IF(I36>=I35,I36-I35,0) -> 4795.6667 | K36: =M36+O36 -> 4615 | L36: 96187.667 | M36: =IF(L36>=L35,L36-L35,0) -> 2162.6667 | N36: 129922.33 | O36: =IF(N36>=N35,N36-N35,0) -> 2452.3333 | P36: 225426 | Q36: =IF(P36>=P35,P36-P35,0)*30 -> 600 | R36: 213214 | S36: =IF(R36>=R35,R36-R35,0) -> 139 | T36: 389191 | U36: =IF(T36>=T35,T36-T35,0) -> 267 | V36: 350570 | W36: =IF(V36>=V35,V36-V35,0)*0.53 -> 0 | X36: 623356.33 | Y36: =IF(X36>=X35,X36-X35,0)*0.53 -> 4433.6267 | Z36: 618241 | AA36: =IF(Z36>=Z35,Z36-Z35,0)*0.53 -> 0 | AB36: 954549 | AC36: =IF(AB36>=AB35,AB36-AB35,0)*0.53 -> 4636.44 | AD36: 1562 | AE36: =IF(AD36>=AD35,AD36-AD35,0)*0.53 -> 0 | AF36: 925487 | AG36: =IF(AF36>=AF35,AF36-AF35,0)*0.53 -> 1807.3 | AH36: 301658 | AI36: =IF(AH36>=AH35,AH36-AH35,0)*0.53 -> 1226.42 | AJ36: 968520 | AK36: =IF(AJ36>=AJ35,AJ36-AJ35,0)*0.53 -> 4120.75 | AL36: 548047.67 | AM36: =IF(AL36>=AL35,AL36-AL35,0)*0.53 -> 129.67333 | AN36: =W36+Y36+AA36+AC36+AE36+AG36+AI36+AK36+AM36 -> 16354.21 | AO36: 7971320 | AP36: =IF(AO36>=AO35,AO36-AO35,0)*0.1125 -> 320.7375 | AQ36: 732637.33 | AR36: =IF(AQ36>=AQ35,AQ36-AQ35,0) -> 139.33333 | AS36: 999986 | AT36: =IF(AS36>=AS35,AS36-AS35,0) -> 166 | AU36: 821304 | AV36: =IF(AU36>=AU35,AU36-AU35,0) -> 68 | AW36: 2799130.3 | AX36: =IF(AW36>=AW35,AW36-AW35,0) -> 1166.1481 | AY36: 230076.67 | AZ36: =IF(AY36>=AY35,AY36-AY35,0) -> 56.666667 | BA36: 20329335 | BB36: =IF(BA36>=BA35,BA36-BA35,0) -> 5179.3333 | BC36: 617272.33 | BD36: =IF(BC36>=BC35,BC36-BC35,0) -> 221.33333 | BE36: 39370.333 | BF36: =IF(BE36>=BE35,BE36-BE35,0) -> 70.333333 | BG36: 25500267 | BH36: =IF(BG36>=BG35,BG36-BG35,0)-(0.45*BN36)-(0.45*BP36)-BR36 -> 6325.4667 | BI36: =AP36+AR36+AT36+AV36+AX36+AZ36+BB36+BD36+BF36+BH36 -> 13713.352 | BJ36: =BI36+AN36 -> 30067.562 | BK36: 1472606.7 | BL36: =IF(BK36>=BK35,BK36-BK35,0) -> 100.66667 | BM36: 4186746.3 | BN36: =IF(BM36>=BM35,BM36-BM35,0) -> 1488.3333 | BO36: 439337.67 | BP36: =IF(BO36>=BO35,BO36-BO35,0) -> 87.666667 | BQ36: 549337 | BR36: =IF(BQ36>=BQ35,BQ36-BQ35,0) -> 147 | BS36: =J36+Q36+AN36+BI36 -> 35463.229 | BT36: 134 | BU36: =IF(BS36>0,BS36/BT36,0) -> 264.65096 | BW36: =IF(BS36>0,BS36/BV36,0) -> #DIV/0! | BX36: =((BS36-Q36)*$BZ$1)+(Q36*$BR$1) -> 41052.713 | BY36: =IF(BX36>0,BX36/BT36,0) -> 306.36353 | BZ36: =IF(BX36>0,BX36/BV36,0) -> #DIV/0!
A37: MTD | C37: =SUM(C9:C35) -> 0 | E37: =SUM(E9:E35) -> 0 | F37: =SUM(F9:F35) -> 0 | G37: =SUM(G9:G35) -> 0 | J37: =SUM(J6:J36) -> 165415 | K37: =SUM(K6:K36) -> 136039.33 | M37: =SUM(M6:M36) -> 61325.667 | O37: =SUM(O6:O36) -> 74713.667 | Q37: =SUM(Q6:Q36) -> 17272 | S37: =SUM(S6:S36) -> 4332.5 | U37: =SUM(U6:U36) -> 8376.5 | W37: =SUM(W6:W36) -> 28100.6 | Y37: =SUM(Y5:Y36) -> 88680.307 | AA37: =SUM(AA6:AA36) -> 61527.17 | AC37: =SUM(AC6:AC36) -> 72207.465 | AE37: =SUM(AE6:AE36) -> 32952.22 | AG37: =SUM(AG6:AG36) -> 14032.545 | AI37: =SUM(AI6:AI36) -> 35242.209 | AK37: =SUM(AK6:AK36) -> 119639.55 | AM37: =SUM(AM6:AM36) -> 3527.9627 | AN37: =SUM(AN6:AN36) -> 455910.03 | AP37: =SUM(AP6:AP36) -> 9196.875 | AR37: =SUM(AR6:AR36) -> 4924.3333 | AT37: =SUM(AT6:AT36) -> 4946.2 | AV37: =SUM(AV6:AV36) -> 1905.3 | AX37: =SUM(AX6:AX36) -> 33439.759 | AZ37: =SUM(AZ6:AZ36) -> 343.66667 | BB37: =SUM(BB6:BB36) -> 155973.03 | BD37: =SUM(BD6:BD36) -> 8126.7333 | BF37: =SUM(BF6:BF36) -> 2196.9444 | BH37: =SUM(BH6:BH36) -> 198937.54 | BI37: =SUM(BI6:BI36) -> 419990.38 | BJ37: =SUM(BJ6:BJ36) -> 875900.41 | BL37: =SUM(BL6:BL36) -> 8410.7667 | BN37: =SUM(BN6:BN36) -> 47023.733 | BP37: =SUM(BP6:BP36) -> 3317.6667 | BR37: =SUM(BR6:BR36) -> 4558.5 | BS37: =SUM(BS6:BS36) -> 1058587.4 | BT37: =SUM(BT6:BT36) -> 5959 | BU37: =IF(BS37>0,BS37/BT37,0) -> 177.64514 | BV37: =SUM(BV6:BV35) -> 0 | BW37: =IF(BS37>0,BS37/BV37,0) -> #DIV/0! | BX37: =SUM(BX6:BX35) -> 1184095.2 | BY37: =IF(BX37>0,BX37/BT37,0) -> 198.70703 | BZ37: =IF(BX37>0,BX37/BV37,0) -> #DIV/0!
A38: AVER. Act | C38: =C37/C40 -> #DIV/0! | E38: =E37/C40 -> #DIV/0! | F38: =F37/C40 -> #DIV/0! | G38: =G37/C40 -> #DIV/0! | J38: =J37/J39 -> 5513.8333 | K38: =K37/J39 -> 4534.6444 | M38: =M37/J39 -> 2044.1889 | O38: =O37/J39 -> 2490.4556 | Q38: =Q37/J39 -> 575.73333 | S38: =S37/J39 -> 144.41667 | U38: =U37/J39 -> 279.21667 | W38: =W37/J39 -> 936.68667 | Y38: =Y37/J39 -> 2956.0102 | AA38: =AA37/J39 -> 2050.9057 | AC38: =AC37/J39 -> 2406.9155 | AE38: =AE37/J39 -> 1098.4073 | AG38: =AG37/J39 -> 467.7515 | AI38: =AI37/J39 -> 1174.7403 | AK38: =AK37/J39 -> 3987.985 | AM38: =AM37/J39 -> 117.59876 | AN38: =AN37/J39 -> 15197.001 | AP38: =AP37/J39 -> 306.5625 | AR38: =AR37/J39 -> 164.14444 | AT38: =AT37/J39 -> 164.87333 | AV38: =AV37/J39 -> 63.51 | AX38: =AX37/J39 -> 1114.6586 | AZ38: =AZ37/J39 -> 11.455556 | BB38: =BB37/J39 -> 5199.1011 | BD38: =BD37/J39 -> 270.89111 | BF38: =BF37/J39 -> 73.231481 | BH38: =BH37/J39 -> 6631.2512 | BL38: =BL37/J39 -> 280.35889 | BN38: =BN37/J39 -> 1567.4578 | BP38: =BP37/J39 -> 110.58889 | BR38: =BR37/J39 -> 151.95 | BS38: =BS37/$J$41 -> #DIV/0! | BT38: =BT37/$J$41 -> #DIV/0! | BU38: =BS38/BT38 -> #DIV/0! | BV38: =BV37/$J$41 -> #DIV/0! | BW38: =BS38/BV38 -> #DIV/0! | BX38: =BX37/$J$41 -> #DIV/0! | BY38: =BX38/BT38 -> #DIV/0! | BZ38: =BX38/BV38 -> #DIV/0!
A39: No of Days MTD | J39: =COUNTIF(I6:I35,">0") -> 30
A40: No of Days month | J40: =COUNTIF(A6:A35,">0") -> 30

Sheet Water
A1: =Elect!A1 -> 44774 | T1: Main Water UP | V1: 4 | W1: Water Truck UP
A3: Day | E3: Water Incoming | I3: New casino | N3: Rooms Consumption | P3: Public Areas consumption | R3: Swimming pool | T3: No. of rooms | U3: Cons. Per occ. room | V3: No. of guest | W3: Cons. Per guest | X3: Total cost | Y3: L.E\ | Z3: L.E\
B4: Main water meter 1 | D4: Main water meter 2 | F4: Main water meter 3 | H4: Total Inc. | I4: Hot water | K4: Cold water | N4: Express Riser | O4: Consp. | P4: Read. | Q4: Cons. | R4: Read. | S4: Cons. | Y4: Room | Z4: Guest
B5: Counter | C5: Produc 58% | D5: Counter | E5: Produc 58% | F5: Counter | G5: Produc 58% | I5: Counter | K5: Counter
B6: 87524 | C6: =IF(B6>=B5,B6-B5,0)*10*0.58 -> 0 | D6: 9977 | E6: =IF(D6>=D5,D6-D5,0)*10*0.58 -> 0 | F6: 36056 | G6: =IF(F6>=F5,F6-F5,0)*0.58 -> 0 | I6: 283 | K6: 5019
A7: 1 | B7: 87569 | C7: =IF(B7>=B6,B7-B6,0)*10*0.58 -> 261 | D7: 10038 | E7: =IF(D7>=D6,D7-D6,0)*10*0.58 -> 353.8 | F7: 36490 | G7: =IF(F7>=F6,F7-F6,0)*0.58 -> 251.72 | H7: =C7+E7+G7 -> 866.52 | O7: =IF(N7>=N6,N7-N6,0) -> 0 | Q7: =(H7-O7)*0.58 -> 502.5816 | S7: =IF(R7-R6>0,R7-R6,0) -> 0 | T7: =Elect!BT6 -> 158 | U7: =H7/T7 -> 5.4843038 | V7: =Elect!BV6 -> 0 | W7: =H7/V7 -> #DIV/0! | X7: =H7*V1 -> 3466.08 | Y7: =IF(X7>0,X7/T7,0) -> 21.937215 | Z7: 0
A8: 2 | B8: 87572 | C8: =IF(B8>=B7,B8-B7,0)*10*0.58 -> 17.4 | D8: 10050 | E8: =IF(D8>=D7,D8-D7,0)*10*0.58 -> 69.6 | F8: 36540 | G8: =IF(F8>=F7,F8-F7,0)*0.58 -> 29 | H8: =C8+E8+G8 -> 116 | O8: =IF(N8>=N7,N8-N7,0) -> 0 | Q8: =(H8-O8)*0.58 -> 67.28 | S8: =IF(R8-R7>0,R8-R7,0) -> 0 | T8: =Elect!BT7 -> 162 | U8: =H8/T8 -> 0.71604938 | V8: =Elect!BV7 -> 0 | W8: =H8/V8 -> #DIV/0! | X8: =H8*V1 -> 464 | Y8: =IF(X8>0,X8/T8,0) -> 2.8641975 | Z8: =IF(X8>0,X8/V8,0) -> #DIV/0!
A9: 3 | B9: 87585 | C9: =IF(B9>=B8,B9-B8,0)*10*0.58 -> 75.4 | D9: 10058 | E9: =IF(D9>=D8,D9-D8,0)*10*0.58 -> 46.4 | F9: 36647 | G9: =IF(F9>=F8,F9-F8,0)*0.58 -> 62.06 | H9: =C9+E9+G9 -> 183.86 | O9: =IF(N9>=N8,N9-N8,0) -> 0 | Q9: =(H9-O9)*0.58 -> 106.6388 | S9: =IF(R9-R8>0,R9-R8,0) -> 0 | T9: =Elect!BT8 -> 173 | U9: =H9/T9 -> 1.0627746 | V9: =Elect!BV8 -> 0 | W9: =H9/V9 -> #DIV/0! | X9: =H9*V1 -> 735.44 | Y9: =IF(X9>0,X9/T9,0) -> 4.2510983 | Z9: =IF(X9>0,X9/V9,0) -> #DIV/0!
A10: 4 | B10: 87598 | C10: =IF(B10>=B9,B10-B9,0)*10*0.58 -> 75.4 | D10: 10068.667 | E10: =IF(D10>=D9,D10-D9,0)*10*0.58 -> 61.866667 | F10: 36716 | G10: =IF(F10>=F9,F10-F9,0)*0.58 -> 40.02 | H10: =C10+E10+G10 -> 177.28667 | O10: =IF(N10>=N9,N10-N9,0) -> 0 | Q10: =(H10-O10)*0.58 -> 102.82627 | S10: =IF(R10-R9>0,R10-R9,0) -> 0 | T10: =Elect!BT9 -> 202 | U10: =H10/T10 -> 0.87765677 | V10: =Elect!BV9 -> 0 | W10: =H10/V10 -> #DIV/0! | X10: =H10*V1 -> 709.14667 | Y10: =IF(X10>0,X10/T10,0) -> 3.5106271 | Z10: =IF(X10>0,X10/V10,0) -> #DIV/0!
A11: 5 | B11: 87631 | C11: =IF(B11>=B10,B11-B10,0)*10*0.58 -> 191.4 | D11: 10118 | E11: =IF(D11>=D10,D11-D10,0)*10*0.58 -> 286.13333 | F11: 37041 | G11: =IF(F11>=F10,F11-F10,0)*0.58 -> 188.5 | H11: =C11+E11+G11 -> 666.03333 | O11: =IF(N11>=N10,N11-N10,0) -> 0 | Q11: =(H11-O11)*0.58 -> 386.29933 | S11: =IF(R11-R10>0,R11-R10,0) -> 0 | T11: =Elect!BT10 -> 216 | U11: =H11/T11 -> 3.0834877 | V11: =Elect!BV10 -> 0 | W11: =H11/V11 -> #DIV/0! | X11: =H11*V1 -> 2664.1333 | Y11: =IF(X11>0,X11/T11,0) -> 12.333951 | Z11: =IF(X11>0,X11/V11,0) -> #DIV/0!
A12: 6 | B12: 87651 | C12: =IF(B12>=B11,B12-B11,0)*10*0.58 -> 116 | D12: 10145 | E12: =IF(D12>=D11,D12-D11,0)*10*0.58 -> 156.6 | F12: 37235 | G12: =IF(F12>=F11,F12-F11,0)*0.58 -> 112.52 | H12: =C12+E12+G12 -> 385.12 | O12: =IF(N12>=N11,N12-N11,0) -> 0 | Q12: =(H12-O12)*0.58 -> 223.3696 | S12: =IF(R12-R11>0,R12-R11,0) -> 0 | T12: =Elect!BT11 -> 224 | U12: =H12/T12 -> 1.7192857 | V12: =Elect!BV11 -> 0 | W12: =H12/V12 -> #DIV/0! | X12: =H12*V1 -> 1540.48 | Y12: =IF(X12>0,X12/T12,0) -> 6.8771429 | Z12: =IF(X12>0,X12/V12,0) -> #DIV/0!
A13: 7 | B13: 87674 | C13: =IF(B13>=B12,B13-B12,0)*10*0.58 -> 133.4 | D13: 10175 | E13: =IF(D13>=D12,D13-D12,0)*10*0.58 -> 174 | F13: 37421 | G13: =IF(F13>=F12,F13-F12,0)*0.58 -> 107.88 | H13: =C13+E13+G13 -> 415.28 | O13: =IF(N13>=N12,N13-N12,0) -> 0 | Q13: =(H13-O13)*0.58 -> 240.8624 | S13: =IF(R13-R12>0,R13-R12,0) -> 0 | T13: =Elect!BT12 -> 221 | U13: =H13/T13 -> 1.879095 | V13: =Elect!BV12 -> 0 | W13: =H13/V13 -> #DIV/0! | X13: =H13*V1 -> 1661.12 | Y13: =IF(X13>0,X13/T13,0) -> 7.5163801 | Z13: =IF(X13>0,X13/V13,0) -> #DIV/0!
A14: 8 | B14: 87696 | C14: =IF(B14>=B13,B14-B13,0)*10*0.58 -> 127.6 | D14: 10204 | E14: =IF(D14>=D13,D14-D13,0)*10*0.58 -> 168.2 | F14: 37588 | G14: =IF(F14>=F13,F14-F13,0)*0.58 -> 96.86 | H14: =C14+E14+G14 -> 392.66 | O14: =IF(N14>=N13,N14-N13,0) -> 0 | Q14: =(H14-O14)*0.58 -> 227.7428 | S14: =IF(R14-R13>0,R14-R13,0) -> 0 | T14: =Elect!BT13 -> 216 | U14: =H14/T14 -> 1.8178704 | V14: =Elect!BV13 -> 0 | W14: =H14/V14 -> #DIV/0! | X14: =H14*V1 -> 1570.64 | Y14: =IF(X14>0,X14/T14,0) -> 7.2714815 | Z14: =IF(X14>0,X14/V14,0) -> #DIV/0!
A15: 9 | B15: 87721 | C15: =IF(B15>=B14,B15-B14,0)*10*0.58 -> 145 | D15: 10237 | E15: =IF(D15>=D14,D15-D14,0)*10*0.58 -> 191.4 | F15: 37778 | G15: =IF(F15>=F14,F15-F14,0)*0.58 -> 110.2 | H15: =C15+E15+G15 -> 446.6 | O15: =IF(N15>=N14,N15-N14,0) -> 0 | Q15: =(H15-O15)*0.58 -> 259.028 | S15: =IF(R15-R14>0,R15-R14,0) -> 0 | T15: =Elect!BT14 -> 197 | U15: =H15/T15 -> 2.2670051 | V15: =Elect!BV14 -> 0 | W15: =H15/V15 -> #DIV/0! | X15: =H15*V1 -> 1786.4 | Y15: =IF(X15>0,X15/T15,0) -> 9.0680203 | Z15: =IF(X15>0,X15/V15,0) -> #DIV/0!
A16: 10 | B16: 87746 | C16: =IF(B16>=B15,B16-B15,0)*10*0.58 -> 145 | D16: 10271 | E16: =IF(D16>=D15,D16-D15,0)*10*0.58 -> 197.2 | F16: 37948 | G16: =IF(F16>=F15,F16-F15,0)*0.58 -> 98.6 | H16: =C16+E16+G16 -> 440.8 | O16: =IF(N16>=N15,N16-N15,0) -> 0 | Q16: =(H16-O16)*0.58 -> 255.664 | S16: =IF(R16-R15>0,R16-R15,0) -> 0 | T16: =Elect!BT15 -> 194 | U16: =H16/T16 -> 2.2721649 | V16: =Elect!BV15 -> 0 | W16: =H16/V16 -> #DIV/0! | X16: =H16*V1 -> 1763.2 | Y16: =IF(X16>0,X16/T16,0) -> 9.0886598 | Z16: =IF(X16>0,X16/V16,0) -> #DIV/0!
A17: 11 | B17: 87771 | C17: =IF(B17>=B16,B17-B16,0)*10*0.58 -> 145 | D17: 10304.333 | E17: =IF(D17>=D16,D17-D16,0)*10*0.58 -> 193.33333 | F17: 38131.333 | G17: =IF(F17>=F16,F17-F16,0)*0.58 -> 106.33333 | H17: =C17+E17+G17 -> 444.66667 | O17: =IF(N17>=N16,N17-N16,0) -> 0 | Q17: =(H17-O17)*0.58 -> 257.90667 | S17: =IF(R17-R16>0,R17-R16,0) -> 0 | T17: =Elect!BT16 -> 211 | U17: =H17/T17 -> 2.107425 | V17: =Elect!BV16 -> 0 | W17: =H17/V17 -> #DIV/0! | X17: =H17*V1 -> 1778.6667 | Y17: =IF(X17>0,X17/T17,0) -> 8.4296998 | Z17: =IF(X17>0,X17/V17,0) -> #DIV/0!
A18: 12 | B18: 87794 | C18: =IF(B18>=B17,B18-B17,0)*10*0.58 -> 133.4 | D18: 10333 | E18: =IF(D18>=D17,D18-D17,0)*10*0.58 -> 166.26667 | F18: 38308 | G18: =IF(F18>=F17,F18-F17,0)*0.58 -> 102.46667 | H18: =C18+E18+G18 -> 402.13333 | O18: =IF(N18>=N17,N18-N17,0) -> 0 | Q18: =(H18-O18)*0.58 -> 233.23733 | S18: =IF(R18-R17>0,R18-R17,0) -> 0 | T18: =Elect!BT17 -> 239 | U18: =H18/T18 -> 1.6825662 | V18: =Elect!BV17 -> 0 | W18: =H18/V18 -> #DIV/0! | X18: =H18*V1 -> 1608.5333 | Y18: =IF(X18>0,X18/T18,0) -> 6.730265 | Z18: =IF(X18>0,X18/V18,0) -> #DIV/0!
A19: 13 | B19: 87815 | C19: =IF(B19>=B18,B19-B18,0)*10*0.58 -> 121.8 | D19: 10361 | E19: =IF(D19>=D18,D19-D18,0)*10*0.58 -> 162.4 | F19: 38484 | G19: =IF(F19>=F18,F19-F18,0)*0.58 -> 102.08 | H19: =C19+E19+G19 -> 386.28 | O19: =IF(N19>=N18,N19-N18,0) -> 0 | Q19: =(H19-O19)*0.58 -> 224.0424 | S19: =IF(R19-R18>0,R19-R18,0) -> 0 | T19: =Elect!BT18 -> 227 | U19: =H19/T19 -> 1.701674 | V19: =Elect!BV18 -> 0 | W19: =H19/V19 -> #DIV/0! | X19: =H19*V1 -> 1545.12 | Y19: =IF(X19>0,X19/T19,0) -> 6.806696 | Z19: =IF(X19>0,X19/V19,0) -> #DIV/0!
A20: 14 | B20: 87839 | C20: =IF(B20>=B19,B20-B19,0)*10*0.58 -> 139.2 | D20: 10393 | E20: =IF(D20>=D19,D20-D19,0)*10*0.58 -> 185.6 | F20: 38663 | G20: =IF(F20>=F19,F20-F19,0)*0.58 -> 103.82 | H20: =C20+E20+G20 -> 428.62 | O20: =IF(N20>=N19,N20-N19,0) -> 0 | Q20: =(H20-O20)*0.58 -> 248.5996 | S20: =IF(R20-R19>0,R20-R19,0) -> 0 | T20: =Elect!BT19 -> 216 | U20: =H20/T20 -> 1.9843519 | V20: =Elect!BV19 -> 0 | W20: =H20/V20 -> #DIV/0! | X20: =H20*V1 -> 1714.48 | Y20: =IF(X20>0,X20/T20,0) -> 7.9374074 | Z20: =IF(X20>0,X20/V20,0) -> #DIV/0!
A21: 15 | B21: 87862 | C21: =IF(B21>=B20,B21-B20,0)*10*0.58 -> 133.4 | D21: 10423 | E21: =IF(D21>=D20,D21-D20,0)*10*0.58 -> 174 | F21: 38847 | G21: =IF(F21>=F20,F21-F20,0)*0.58 -> 106.72 | H21: =C21+E21+G21 -> 414.12 | O21: =IF(N21>=N20,N21-N20,0) -> 0 | Q21: =(H21-O21)*0.58 -> 240.1896 | S21: =IF(R21-R20>0,R21-R20,0) -> 0 | T21: =Elect!BT20 -> 211 | U21: =H21/T21 -> 1.962654 | V21: =Elect!BV20 -> 0 | W21: =H21/V21 -> #DIV/0! | X21: =H21*V1 -> 1656.48 | Y21: =IF(X21>0,X21/T21,0) -> 7.8506161 | Z21: =IF(X21>0,X21/V21,0) -> #DIV/0!
A22: 16 | B22: 87885 | C22: =IF(B22>=B21,B22-B21,0)*10*0.58 -> 133.4 | D22: 10453 | E22: =IF(D22>=D21,D22-D21,0)*10*0.58 -> 174 | F22: 39027.667 | G22: =IF(F22>=F21,F22-F21,0)*0.58 -> 104.78667 | H22: =C22+E22+G22 -> 412.18667 | O22: =IF(N22>=N21,N22-N21,0) -> 0 | Q22: =(H22-O22)*0.58 -> 239.06827 | S22: =IF(R22-R21>0,R22-R21,0) -> 0 | T22: =Elect!BT21 -> 194 | U22: =H22/T22 -> 2.1246735 | V22: =Elect!BV21 -> 0 | W22: =H22/V22 -> #DIV/0! | X22: =H22*V1 -> 1648.7467 | Y22: =IF(X22>0,X22/T22,0) -> 8.4986942 | Z22: =IF(X22>0,X22/V22,0) -> #DIV/0!
A23: 17 | B23: 87908 | C23: =IF(B23>=B22,B23-B22,0)*10*0.58 -> 133.4 | D23: 10483 | E23: =IF(D23>=D22,D23-D22,0)*10*0.58 -> 174 | F23: 39210.556 | G23: =IF(F23>=F22,F23-F22,0)*0.58 -> 106.07556 | H23: =C23+E23+G23 -> 413.47556 | O23: =IF(N23>=N22,N23-N22,0) -> 0 | Q23: =(H23-O23)*0.58 -> 239.81582 | S23: =IF(R23-R22>0,R23-R22,0) -> 0 | T23: =Elect!BT22 -> 193 | U23: =H23/T23 -> 2.1423604 | V23: =Elect!BV22 -> 0 | W23: =H23/V23 -> #DIV/0! | X23: =H23*V1 -> 1653.9022 | Y23: =IF(X23>0,X23/T23,0) -> 8.5694416 | Z23: =IF(X23>0,X23/V23,0) -> #DIV/0!
A24: 18 | B24: 87931 | C24: =IF(B24>=B23,B24-B23,0)*10*0.58 -> 133.4 | D24: 10513 | E24: =IF(D24>=D23,D24-D23,0)*10*0.58 -> 174 | F24: 39392.889 | G24: =IF(F24>=F23,F24-F23,0)*0.58 -> 105.75333 | H24: =C24+E24+G24 -> 413.15333 | O24: =IF(N24>=N23,N24-N23,0) -> 0 | Q24: =(H24-O24)*0.58 -> 239.62893 | S24: =IF(R24-R23>0,R24-R23,0) -> 0 | T24: =Elect!BT23 -> 199 | U24: =H24/T24 -> 2.0761474 | V24: =Elect!BV23 -> 0 | W24: =H24/V24 -> #DIV/0! | X24: =H24*V1 -> 1652.6133 | Y24: =IF(X24>0,X24/T24,0) -> 8.3045896 | Z24: =IF(X24>0,X24/V24,0) -> #DIV/0!
A25: 19 | B25: 87949 | C25: =IF(B25>=B24,B25-B24,0)*10*0.58 -> 104.4 | D25: 10537 | E25: =IF(D25>=D24,D25-D24,0)*10*0.58 -> 139.2 | F25: 39535 | G25: =IF(F25>=F24,F25-F24,0)*0.58 -> 82.424444 | H25: =C25+E25+G25 -> 326.02444 | O25: =IF(N25>=N24,N25-N24,0) -> 0 | Q25: =(H25-O25)*0.58 -> 189.09418 | S25: =IF(R25-R24>0,R25-R24,0) -> 0 | T25: =Elect!BT24 -> 191 | U25: =H25/T25 -> 1.7069343 | V25: =Elect!BV24 -> 0 | W25: =H25/V25 -> #DIV/0! | X25: =H25*V1 -> 1304.0978 | Y25: =IF(X25>0,X25/T25,0) -> 6.8277371 | Z25: =IF(X25>0,X25/V25,0) -> #DIV/0!
A26: 20 | B26: 87972 | C26: =IF(B26>=B25,B26-B25,0)*10*0.58 -> 133.4 | D26: 10566 | E26: =IF(D26>=D25,D26-D25,0)*10*0.58 -> 168.2 | F26: 39701 | G26: =IF(F26>=F25,F26-F25,0)*0.58 -> 96.28 | H26: =C26+E26+G26 -> 397.88 | O26: =IF(N26>=N25,N26-N25,0) -> 0 | Q26: =(H26-O26)*0.58 -> 230.7704 | S26: =IF(R26-R25>0,R26-R25,0) -> 0 | T26: =Elect!BT25 -> 223 | U26: =H26/T26 -> 1.7842152 | V26: =Elect!BV25 -> 0 | W26: =H26/V26 -> #DIV/0! | X26: =H26*V1 -> 1591.52 | Y26: =IF(X26>0,X26/T26,0) -> 7.136861 | Z26: =IF(X26>0,X26/V26,0) -> #DIV/0!
A27: 21 | B27: 87994 | C27: =IF(B27>=B26,B27-B26,0)*10*0.58 -> 127.6 | D27: 10596 | E27: =IF(D27>=D26,D27-D26,0)*10*0.58 -> 174 | F27: 39884 | G27: =IF(F27>=F26,F27-F26,0)*0.58 -> 106.14 | H27: =C27+E27+G27 -> 407.74 | O27: =IF(N27>=N26,N27-N26,0) -> 0 | Q27: =(H27-O27)*0.58 -> 236.4892 | S27: =IF(R27-R26>0,R27-R26,0) -> 0 | T27: =Elect!BT26 -> 212 | U27: =H27/T27 -> 1.9233019 | V27: =Elect!BV26 -> 0 | W27: =H27/V27 -> #DIV/0! | X27: =H27*V1 -> 1630.96 | Y27: =IF(X27>0,X27/T27,0) -> 7.6932075 | Z27: =IF(X27>0,X27/V27,0) -> #DIV/0!
A28: 22 | B28: 88015 | C28: =IF(B28>=B27,B28-B27,0)*10*0.58 -> 121.8 | D28: 10623 | E28: =IF(D28>=D27,D28-D27,0)*10*0.58 -> 156.6 | F28: 40062 | G28: =IF(F28>=F27,F28-F27,0)*0.58 -> 103.24 | H28: =C28+E28+G28 -> 381.64 | O28: =IF(N28>=N27,N28-N27,0) -> 0 | Q28: =(H28-O28)*0.58 -> 221.3512 | S28: =IF(R28-R27>0,R28-R27,0) -> 0 | T28: =Elect!BT27 -> 182 | U28: =H28/T28 -> 2.0969231 | V28: =Elect!BV27 -> 0 | W28: =H28/V28 -> #DIV/0! | X28: =H28*V1 -> 1526.56 | Y28: =IF(X28>0,X28/T28,0) -> 8.3876923 | Z28: =IF(X28>0,X28/V28,0) -> #DIV/0!
A29: 23 | B29: 88039 | C29: =IF(B29>=B28,B29-B28,0)*10*0.58 -> 139.2 | D29: 10655 | E29: =IF(D29>=D28,D29-D28,0)*10*0.58 -> 185.6 | F29: 40249 | G29: =IF(F29>=F28,F29-F28,0)*0.58 -> 108.46 | H29: =C29+E29+G29 -> 433.26 | O29: =IF(N29>=N28,N29-N28,0) -> 0 | Q29: =(H29-O29)*0.58 -> 251.2908 | S29: =IF(R29-R28>0,R29-R28,0) -> 0 | T29: =Elect!BT28 -> 182 | U29: =H29/T29 -> 2.3805495 | V29: =Elect!BV28 -> 0 | W29: =H29/V29 -> #DIV/0! | X29: =H29*V1 -> 1733.04 | Y29: =IF(X29>0,X29/T29,0) -> 9.5221978 | Z29: =IF(X29>0,X29/V29,0) -> #DIV/0!
A30: 24 | B30: 88062 | C30: =IF(B30>=B29,B30-B29,0)*10*0.58 -> 133.4 | D30: 10664 | E30: =IF(D30>=D29,D30-D29,0)*10*0.58 -> 52.2 | F30: 40411 | G30: =IF(F30>=F29,F30-F29,0)*0.58 -> 93.96 | H30: =C30+E30+G30 -> 279.56 | O30: =IF(N30>=N29,N30-N29,0) -> 0 | Q30: =(H30-O30)*0.58 -> 162.1448 | S30: =IF(R30-R29>0,R30-R29,0) -> 0 | T30: =Elect!BT29 -> 175 | U30: =H30/T30 -> 1.5974857 | V30: =Elect!BV29 -> 0 | W30: =H30/V30 -> #DIV/0! | X30: =H30*V1 -> 1118.24 | Y30: =IF(X30>0,X30/T30,0) -> 6.3899429 | Z30: =IF(X30>0,X30/V30,0) -> #DIV/0!
A31: 25 | B31: 88085 | C31: =IF(B31>=B30,B31-B30,0)*10*0.58 -> 133.4 | D31: 10688.333 | E31: =IF(D31>=D30,D31-D30,0)*10*0.58 -> 141.13333 | F31: 40589.667 | G31: =IF(F31>=F30,F31-F30,0)*0.58 -> 103.62667 | H31: =C31+E31+G31 -> 378.16 | O31: =IF(N31>=N30,N31-N30,0) -> 0 | Q31: =(H31-O31)*0.58 -> 219.3328 | S31: =IF(R31-R30>0,R31-R30,0) -> 0 | T31: =Elect!BT30 -> 173 | U31: =H31/T31 -> 2.185896 | V31: =Elect!BV30 -> 0 | W31: =H31/V31 -> #DIV/0! | X31: =H31*V1 -> 1512.64 | Y31: =IF(X31>0,X31/T31,0) -> 8.7435838 | Z31: =IF(X31>0,X31/V31,0) -> #DIV/0!
A32: 26 | B32: 88102 | C32: =IF(B32>=B31,B32-B31,0)*10*0.58 -> 98.6 | D32: 10737 | E32: =IF(D32>=D31,D32-D31,0)*10*0.58 -> 282.26667 | F32: 40737 | G32: =IF(F32>=F31,F32-F31,0)*0.58 -> 85.453333 | H32: =C32+E32+G32 -> 466.32 | O32: =IF(N32>=N31,N32-N31,0) -> 0 | Q32: =(H32-O32)*0.58 -> 270.4656 | S32: =IF(R32-R31>0,R32-R31,0) -> 0 | T32: =Elect!BT31 -> 174 | U32: =H32/T32 -> 2.68 | V32: =Elect!BV31 -> 0 | W32: =H32/V32 -> #DIV/0! | X32: =H32*V1 -> 1865.28 | Y32: =IF(X32>0,X32/T32,0) -> 10.72 | Z32: =IF(X32>0,X32/V32,0) -> #DIV/0!
A33: 27 | B33: 88124 | C33: =IF(B33>=B32,B33-B32,0)*10*0.58 -> 127.6 | D33: 10766 | E33: =IF(D33>=D32,D33-D32,0)*10*0.58 -> 168.2 | F33: 40926 | G33: =IF(F33>=F32,F33-F32,0)*0.58 -> 109.62 | H33: =C33+E33+G33 -> 405.42 | O33: =IF(N33>=N32,N33-N32,0) -> 0 | Q33: =(H33-O33)*0.58 -> 235.1436 | S33: =IF(R33-R32>0,R33-R32,0) -> 0 | T33: =Elect!BT32 -> 199 | U33: =H33/T33 -> 2.0372864 | V33: =Elect!BV32 -> 0 | W33: =H33/V33 -> #DIV/0! | X33: =H33*V1 -> 1621.68 | Y33: =IF(X33>0,X33/T33,0) -> 8.1491457 | Z33: =IF(X33>0,X33/V33,0) -> #DIV/0!
A34: 28 | B34: 88145 | C34: =IF(B34>=B33,B34-B33,0)*10*0.58 -> 121.8 | D34: 10794 | E34: =IF(D34>=D33,D34-D33,0)*10*0.58 -> 162.4 | F34: 41107 | G34: =IF(F34>=F33,F34-F33,0)*0.58 -> 104.98 | H34: =C34+E34+G34 -> 389.18 | O34: =IF(N34>=N33,N34-N33,0) -> 0 | Q34: =(H34-O34)*0.58 -> 225.7244 | S34: =IF(R34-R33>0,R34-R33,0) -> 0 | T34: =Elect!BT33 -> 170 | U34: =H34/T34 -> 2.2892941 | V34: =Elect!BV33 -> 0 | W34: =H34/V34 -> #DIV/0! | X34: =H34*V1 -> 1556.72 | Y34: =IF(X34>0,X34/T34,0) -> 9.1571765 | Z34: =IF(X34>0,X34/V34,0) -> #DIV/0!
A35: 29 | B35: 88167 | C35: =IF(B35>=B34,B35-B34,0)*10*0.58 -> 127.6 | D35: 10823 | E35: =IF(D35>=D34,D35-D34,0)*10*0.58 -> 168.2 | F35: 41285 | G35: =IF(F35>=F34,F35-F34,0)*0.58 -> 103.24 | H35: =C35+E35+G35 -> 399.04 | O35: =IF(N35>=N34,N35-N34,0) -> 0 | Q35: =(H35-O35)*0.58 -> 231.4432 | S35: =IF(R35-R34>0,R35-R34,0) -> 0 | T35: =Elect!BT34 -> 154 | U35: =H35/T35 -> 2.5911688 | V35: =Elect!BV34 -> 0 | W35: =H35/V35 -> #DIV/0! | X35: =H35*V1 -> 1596.16 | Y35: =IF(X35>0,X35/T35,0) -> 10.364675 | Z35: =IF(X35>0,X35/V35,0) -> #DIV/0!
A36: 30 | B36: 88188.333 | C36: =IF(B36>=B35,B36-B35,0)*10*0.58 -> 123.73333 | D36: 10851.333 | E36: =IF(D36>=D35,D36-D35,0)*10*0.58 -> 164.33333 | F36: 41465 | G36: =IF(F36>=F35,F36-F35,0)*0.58 -> 104.4 | H36: =C36+E36+G36 -> 392.46667 | O36: =IF(N36>=N35,N36-N35,0) -> 0 | Q36: =(H36-O36)*0.58 -> 227.63067 | S36: =IF(R36-R35>0,R36-R35,0) -> 0 | T36: =Elect!BT35 -> 137 | U36: =H36/T36 -> 2.8647202 | V36: =Elect!BV35 -> 0 | W36: =H36/V36 -> #DIV/0! | X36: =H36*V1 -> 1569.8667 | Y36: =IF(X36>0,X36/T36,0) -> 11.458881 | Z36: =IF(X36>0,X36/V36,0) -> #DIV/0!
A37: 31 | B37: 88206 | C37: =IF(B37>=B36,B37-B36,0)*10*0.58 -> 102.46667 | D37: 10876 | E37: =IF(D37>=D36,D37-D36,0)*10*0.58 -> 143.06667 | F37: 41649 | G37: =IF(F37>=F36,F37-F36,0)*0.58 -> 106.72 | H37: =C37+E37+G37 -> 352.25333 | I37: 294 | K37: 5156 | O37: =IF(N37>=N36,N37-N36,0) -> 0 | Q37: =(H37-O37)*0.58 -> 204.30693 | S37: =IF(R37-R36>0,R37-R36,0) -> 0 | T37: =Elect!BT36 -> 134 | U37: =H37/T37 -> 2.6287562 | V37: =Elect!BV36 -> 0 | W37: =H37/V37 -> #DIV/0! | X37: =H37*V7 -> 0 | Y37: =IF(X37>0,X37/T37,0) -> 0 | Z37: =IF(X37>0,X37/V37,0) -> 0
A38: MTD | C38: =SUM(C7:C37) -> 3955.6 | E38: =SUM(E7:E37) -> 5214.2 | G38: =SUM(G7:G37) -> 3243.94 | H38: =SUM(H7:H37) -> 12413.74 | I38: =I37-I6 -> 11 | K38: =K37-K6 -> 137 | O38: =SUM(O7:O36) -> 0 | Q38: =SUM(Q7:Q34) -> 6536.5884 | S38: =SUM(S7:S34) -> 0 | T38: =SUM(T7:T36) -> 5825 | U38: =IF(H38>0,H38/T38,0) -> 2.1311142 | V38: =SUM(V7:V36) -> 0 | W38: =IF(H38>0,H38/V38,0) -> #DIV/0! | X38: =SUM(X7:X36) -> 48245.947 | Y38: =IF(X38>0,X38/T38,0) -> 8.282566 | Z38: =IF(X38>0,X38/V38,0) -> #DIV/0!
A39: AVER. Act | C39: =C38/B48 -> 131.85333 | E39: =E38/B48 -> 173.80667 | G39: =G38/B48 -> 108.13133 | H39: =H38/B48 -> 413.79133 | O39: =O38/B48 -> 0 | Q39: =Q38/B48 -> 217.88628 | S39: =S38/C48 -> #DIV/0! | T39: =T38/B48 -> 194.16667 | U39: =IF(H39>0,H39/T39,0) -> 2.1311142 | V39: =V38/B48 -> 0 | W39: =IF(H39>0,H39/V39,0) -> #DIV/0! | X39: =X38/B48 -> 1608.1982 | Y39: =IF(X39>0,X39/T39,0) -> 8.282566 | Z39: =IF(X39>0,X39/V39,0) -> #DIV/0!
A40: TOTAL Budget | T40: =YTD!Q2341 -> 0 | U40: =IF(#REF!>0,#REF!/T40,0) -> #REF! | V40: =YTD!Q2342 -> 0 | W40: =IF(#REF!>0,#REF!/V40,0) -> #REF! | X40: =YTD!Q2346 -> 0 | Y40: =IF(X40>0,X40/T40,0) -> 0 | Z40: =IF(X40>0,X40/V40,0) -> 0
A41: Budget MTD | T41: =T42*C48 -> #VALUE! | U41: =IF(#REF!>0,#REF!/T41,0) -> #REF! | V41: =V42*C48 -> #VALUE! | W41: =IF(#REF!>0,#REF!/V41,0) -> #REF! | X41: =#REF!*5.62 -> #REF! | Y41: =IF(X41>0,X41/T41,0) -> #REF! | Z41: =IF(X41>0,X41/V41,0) -> #REF!
A42: AVER. Bud | T42: =T40/$A$48 -> #VALUE! | V42: =V40/$A$48 -> #VALUE!
A43: Total RFC | T43: =YTD!Q2358 -> 0 | V43: =YTD!Q2359 -> 0 | X43: =YTD!Q2363 -> 0 | Y43: =IF(X43>0,X43/T43,0) -> 0 | Z43: =IF(X43>0,X43/V43,0) -> 0
A44: RFC MTD | T44: =T43/A48*C48 -> #VALUE! | V44: =V43/A48*C48 -> #VALUE! | X44: =X43/A48*C48 -> #VALUE! | Y44: =IF(X44>0,X44/T44,0) -> #VALUE! | Z44: =IF(X44>0,X44/V44,0) -> #VALUE!
A45: AVER RFC | T45: =T43/A48 -> #VALUE! | V45: =V44/A48*C48 -> #VALUE! | X45: =X43/A48 -> #VALUE!
A46: MTD 13 | U46: =Consp!BH33 -> 1.1514679 | W46: =Consp!BI33 -> 0.57929342 | X46: =Consp!BJ33 -> 140121.3 | Y46: =Consp!BK33 -> 6.8331854 | Z46: =Consp!BL33 -> 3.4377159
A47: AVER. Act 13 | U47: =Consp!BH34 -> 1.1761372 | W47: =Consp!BI34 -> 0.60007377 | X47: =Consp!BJ34 -> 5004.3322 | Y47: =Consp!BK34 -> 6.8331854 | Z47: =Consp!BL34 -> 3.4377159
A48: No of Days MTD | B48: =COUNTIF(B7:B36,">0") -> 30
A136: Water Incoming

Sheet Gas
A1: =Elect!A1 -> 44774 | E1: Gas | H1: Gas UP | J1: 3.9
A4: NO. | B4: Main Gas Flow Meter | D4: Laundry Gas Flow Meter | F4: Grumandiz Gas Flow Meter | H4: Plant Room Gas Share Cost | I4: Hotel Consumption Cost | J4: La Grumandiz Cost | K4: Total Natural Gas Consumption
B5: Read | C5: Cons | D5: Read | E5: Cons | F5: Read | G5: Cons | H5: LE/DAY | I5: LE/DAY | J5: LE/DAY | K5: Cons
B6: 8264112 | C6: =IF(B6>=B5,B6-B5,0)*1.06 -> 0 | D6: 546324 | E6: =IF(D6>=D5,D6-D5,0)*0.7 -> 0 | F6: 618655.96 | G6: =IF(F6>=F5,F6-F5,0) -> 0 | K6: =C6+E6 -> 0
A7: 1 | B7: 8264995 | C7: =IF(B7>=B6,B7-B6,0)*1.06 -> 935.98 | D7: 547285 | E7: =IF(D7>=D6,D7-D6,0)*0.7 -> 672.7 | F7: 618746 | G7: =IF(F7>=F6,F7-F6,0) -> 90.044444 | H7: =(E7*0.55)*1.61 -> 595.67585 | I7: =C7*J1 -> 3650.322 | J7: =G7*J1 -> 351.17333 | K7: =C7+E7 -> 1608.68
A8: 2 | B8: 8265878 | C8: =IF(B8>=B7,B8-B7,0)*1.06 -> 935.98 | D8: 547480 | E8: =IF(D8>=D7,D8-D7,0)*0.7 -> 136.5 | F8: 618831 | G8: =IF(F8>=F7,F8-F7,0) -> 85 | H8: =(E8*0.55)*1.61 -> 120.87075 | I8: =C8*J1 -> 3650.322 | J8: =G8*J1 -> 331.5 | K8: =C8+E8 -> 1072.48
A9: 3 | B9: 8266761 | C9: =IF(B9>=B8,B9-B8,0)*1.06 -> 935.98 | D9: 547652 | E9: =IF(D9>=D8,D9-D8,0)*0.7 -> 120.4 | F9: 618925 | G9: =IF(F9>=F8,F9-F8,0) -> 94 | H9: =(E9*0.55)*1.61 -> 106.6142 | I9: =C9*J1 -> 3650.322 | J9: =G9*J1 -> 366.6 | K9: =C9+E9 -> 1056.38
A10: 4 | B10: 8267644 | C10: =IF(B10>=B9,B10-B9,0)*1.06 -> 935.98 | D10: 547839.33 | E10: =IF(D10>=D9,D10-D9,0)*0.7 -> 131.13333 | F10: 619013 | G10: =IF(F10>=F9,F10-F9,0) -> 88 | H10: =(E10*0.55)*1.61 -> 116.11857 | I10: =C10*J1 -> 3650.322 | J10: =G10*J1 -> 343.2 | K10: =C10+E10 -> 1067.1133
A11: 5 | B11: 8268527 | C11: =IF(B11>=B10,B11-B10,0)*1.06 -> 935.98 | D11: 548612 | E11: =IF(D11>=D10,D11-D10,0)*0.7 -> 540.86667 | F11: 619112 | G11: =IF(F11>=F10,F11-F10,0) -> 99 | H11: =(E11*0.55)*1.61 -> 478.93743 | I11: =C11*J1 -> 3650.322 | J11: =G11*J1 -> 386.1 | K11: =C11+E11 -> 1476.8467
A12: 6 | B12: 8269410 | C12: =IF(B12>=B11,B12-B11,0)*1.06 -> 935.98 | D12: 549026 | E12: =IF(D12>=D11,D12-D11,0)*0.7 -> 289.8 | F12: 619201 | G12: =IF(F12>=F11,F12-F11,0) -> 89 | H12: =(E12*0.55)*1.61 -> 256.6179 | I12: =C12*J1 -> 3650.322 | J12: =G12*J1 -> 347.1 | K12: =C12+E12 -> 1225.78
A13: 7 | B13: 8270293 | C13: =IF(B13>=B12,B13-B12,0)*1.06 -> 935.98 | D13: 549487 | E13: =IF(D13>=D12,D13-D12,0)*0.7 -> 322.7 | F13: 619297 | G13: =IF(F13>=F12,F13-F12,0) -> 96 | H13: =(E13*0.55)*1.61 -> 285.75085 | I13: =C13*J1 -> 3650.322 | J13: =G13*J1 -> 374.4 | K13: =C13+E13 -> 1258.68
A14: 8 | B14: 8271176 | C14: =IF(B14>=B13,B14-B13,0)*1.06 -> 935.98 | D14: 549956 | E14: =IF(D14>=D13,D14-D13,0)*0.7 -> 328.3 | F14: 619391 | G14: =IF(F14>=F13,F14-F13,0) -> 94 | H14: =(E14*0.55)*1.61 -> 290.70965 | I14: =C14*J1 -> 3650.322 | J14: =G14*J1 -> 366.6 | K14: =C14+E14 -> 1264.28
A15: 9 | B15: 8272059 | C15: =IF(B15>=B14,B15-B14,0)*1.06 -> 935.98 | D15: 550426 | E15: =IF(D15>=D14,D15-D14,0)*0.7 -> 329 | F15: 619482 | G15: =IF(F15>=F14,F15-F14,0) -> 91 | H15: =(E15*0.55)*1.61 -> 291.3295 | I15: =C15*J1 -> 3650.322 | J15: =G15*J1 -> 354.9 | K15: =C15+E15 -> 1264.98
A16: 10 | B16: 8272942 | C16: =IF(B16>=B15,B16-B15,0)*1.06 -> 935.98 | D16: 550861 | E16: =IF(D16>=D15,D16-D15,0)*0.7 -> 304.5 | F16: 619560 | G16: =IF(F16>=F15,F16-F15,0) -> 78 | H16: =(E16*0.55)*1.61 -> 269.63475 | I16: =C16*J1 -> 3650.322 | J16: =G16*J1 -> 304.2 | K16: =C16+E16 -> 1240.48
A17: 11 | B17: 8273825 | C17: =IF(B17>=B16,B17-B16,0)*1.06 -> 935.98 | D17: 551319.33 | E17: =IF(D17>=D16,D17-D16,0)*0.7 -> 320.83333 | F17: 619716.67 | G17: =IF(F17>=F16,F17-F16,0) -> 156.66667 | H17: =(E17*0.55)*1.61 -> 284.09792 | I17: =C17*J1 -> 3650.322 | J17: =G17*J1 -> 611 | K17: =C17+E17 -> 1256.8133
A18: 12 | B18: 8274708 | C18: =IF(B18>=B17,B18-B17,0)*1.06 -> 935.98 | D18: 551713 | E18: =IF(D18>=D17,D18-D17,0)*0.7 -> 275.56667 | F18: 619748 | G18: =IF(F18>=F17,F18-F17,0) -> 31.333333 | H18: =(E18*0.55)*1.61 -> 244.01428 | I18: =C18*J1 -> 3650.322 | J18: =G18*J1 -> 122.2 | K18: =C18+E18 -> 1211.5467
A19: 13 | B19: 8275591 | C19: =IF(B19>=B18,B19-B18,0)*1.06 -> 935.98 | D19: 552116 | E19: =IF(D19>=D18,D19-D18,0)*0.7 -> 282.1 | F19: 619840 | G19: =IF(F19>=F18,F19-F18,0) -> 92 | H19: =(E19*0.55)*1.61 -> 249.79955 | I19: =C19*J1 -> 3650.322 | J19: =G19*J1 -> 358.8 | K19: =C19+E19 -> 1218.08
A20: 14 | B20: 8276474 | C20: =IF(B20>=B19,B20-B19,0)*1.06 -> 935.98 | D20: 552472 | E20: =IF(D20>=D19,D20-D19,0)*0.7 -> 249.2 | F20: 619922 | G20: =IF(F20>=F19,F20-F19,0) -> 82 | H20: =(E20*0.55)*1.61 -> 220.6666 | I20: =C20*J1 -> 3650.322 | J20: =G20*J1 -> 319.8 | K20: =C20+E20 -> 1185.18
A21: 15 | B21: 8277357 | C21: =IF(B21>=B20,B21-B20,0)*1.06 -> 935.98 | D21: 552851 | E21: =IF(D21>=D20,D21-D20,0)*0.7 -> 265.3 | F21: 620018 | G21: =IF(F21>=F20,F21-F20,0) -> 96 | H21: =(E21*0.55)*1.61 -> 234.92315 | I21: =C21*J1 -> 3650.322 | J21: =G21*J1 -> 374.4 | K21: =C21+E21 -> 1201.28
A22: 16 | B22: 8278240 | C22: =IF(B22>=B21,B22-B21,0)*1.06 -> 935.98 | D22: 553214 | E22: =IF(D22>=D21,D22-D21,0)*0.7 -> 254.1 | F22: 620109 | G22: =IF(F22>=F21,F22-F21,0) -> 91 | H22: =(E22*0.55)*1.61 -> 225.00555 | I22: =C22*J1 -> 3650.322 | J22: =G22*J1 -> 354.9 | K22: =C22+E22 -> 1190.08
A23: 17 | B23: 8279123 | C23: =IF(B23>=B22,B23-B22,0)*1.06 -> 935.98 | D23: 553587.67 | E23: =IF(D23>=D22,D23-D22,0)*0.7 -> 261.56667 | F23: 620203.33 | G23: =IF(F23>=F22,F23-F22,0) -> 94.333333 | H23: =(E23*0.55)*1.61 -> 231.61728 | I23: =C23*J1 -> 3650.322 | J23: =G23*J1 -> 367.9 | K23: =C23+E23 -> 1197.5467
A24: 18 | B24: 8280006 | C24: =IF(B24>=B23,B24-B23,0)*1.06 -> 935.98 | D24: 553954.22 | E24: =IF(D24>=D23,D24-D23,0)*0.7 -> 256.58889 | F24: 620250 | G24: =IF(F24>=F23,F24-F23,0) -> 46.666667 | H24: =(E24*0.55)*1.61 -> 227.20946 | I24: =C24*J1 -> 3650.322 | J24: =G24*J1 -> 182 | K24: =C24+E24 -> 1192.5689
A25: 19 | B25: 8280889 | C25: =IF(B25>=B24,B25-B24,0)*1.06 -> 935.98 | D25: 554332 | E25: =IF(D25>=D24,D25-D24,0)*0.7 -> 264.44444 | F25: 620270 | G25: =IF(F25>=F24,F25-F24,0) -> 20 | H25: =(E25*0.55)*1.61 -> 234.16556 | I25: =C25*J1 -> 3650.322 | J25: =G25*J1 -> 78 | K25: =C25+E25 -> 1200.4244
A26: 20 | B26: 8281772 | C26: =IF(B26>=B25,B26-B25,0)*1.06 -> 935.98 | D26: 554691 | E26: =IF(D26>=D25,D26-D25,0)*0.7 -> 251.3 | F26: 620457 | G26: =IF(F26>=F25,F26-F25,0) -> 187 | H26: =(E26*0.55)*1.61 -> 222.52615 | I26: =C26*J1 -> 3650.322 | J26: =G26*J1 -> 729.3 | K26: =C26+E26 -> 1187.28
A27: 21 | B27: 8282655 | C27: =IF(B27>=B26,B27-B26,0)*1.06 -> 935.98 | D27: 555088 | E27: =IF(D27>=D26,D27-D26,0)*0.7 -> 277.9 | F27: 620545 | G27: =IF(F27>=F26,F27-F26,0) -> 88 | H27: =(E27*0.55)*1.61 -> 246.08045 | I27: =C27*J1 -> 3650.322 | J27: =G27*J1 -> 343.2 | K27: =C27+E27 -> 1213.88
A28: 22 | B28: 8283538 | C28: =IF(B28>=B27,B28-B27,0)*1.06 -> 935.98 | D28: 555419 | E28: =IF(D28>=D27,D28-D27,0)*0.7 -> 231.7 | F28: 620627 | G28: =IF(F28>=F27,F28-F27,0) -> 82 | H28: =(E28*0.55)*1.61 -> 205.17035 | I28: =C28*J1 -> 3650.322 | J28: =G28*J1 -> 319.8 | K28: =C28+E28 -> 1167.68
A29: 23 | B29: 8284421 | C29: =IF(B29>=B28,B29-B28,0)*1.06 -> 935.98 | D29: 555798 | E29: =IF(D29>=D28,D29-D28,0)*0.7 -> 265.3 | F29: 620722 | G29: =IF(F29>=F28,F29-F28,0) -> 95 | H29: =(E29*0.55)*1.61 -> 234.92315 | I29: =C29*J1 -> 3650.322 | J29: =G29*J1 -> 370.5 | K29: =C29+E29 -> 1201.28
A30: 24 | B30: 8285304 | C30: =IF(B30>=B29,B30-B29,0)*1.06 -> 935.98 | D30: 556154 | E30: =IF(D30>=D29,D30-D29,0)*0.7 -> 249.2 | F30: 620802 | G30: =IF(F30>=F29,F30-F29,0) -> 80 | H30: =(E30*0.55)*1.61 -> 220.6666 | I30: =C30*J1 -> 3650.322 | J30: =G30*J1 -> 312 | K30: =C30+E30 -> 1185.18
A31: 25 | B31: 8285923 | C31: =IF(B31>=B30,B31-B30,0)*1.06 -> 656.14 | D31: 556510 | E31: =IF(D31>=D30,D31-D30,0)*0.7 -> 249.2 | F31: 620882 | G31: =IF(F31>=F30,F31-F30,0) -> 80 | H31: =(E31*0.55)*1.61 -> 220.6666 | I31: =C31*J3 -> 0 | J31: =G31*J1 -> 312 | K31: =C31+E31 -> 905.34
A32: 26 | B32: 8286938 | C32: =IF(B32>=B31,B32-B31,0)*1.06 -> 1075.9 | D32: 556791 | E32: =IF(D32>=D31,D32-D31,0)*0.7 -> 196.7 | F32: 620984 | G32: =IF(F32>=F31,F32-F31,0) -> 102 | H32: =(E32*0.55)*1.61 -> 174.17785 | I32: =C32*J1 -> 4196.01 | J32: =G32*J1 -> 397.8 | K32: =C32+E32 -> 1272.6
A33: 27 | B33: 8287989 | C33: =IF(B33>=B32,B33-B32,0)*1.06 -> 1114.06 | D33: 557187 | E33: =IF(D33>=D32,D33-D32,0)*0.7 -> 277.2 | F33: 621071 | G33: =IF(F33>=F32,F33-F32,0) -> 87 | H33: =(E33*0.55)*1.61 -> 245.4606 | I33: =C33*J1 -> 4344.834 | J33: =G33*J1 -> 339.3 | K33: =C33+E33 -> 1391.26
A34: 28 | B34: 8288986 | C34: =IF(B34>=B33,B34-B33,0)*1.06 -> 1056.82 | D34: 557550 | E34: =IF(D34>=D33,D34-D33,0)*0.7 -> 254.1 | F34: 621150 | G34: =IF(F34>=F33,F34-F33,0) -> 79 | H34: =(E34*0.55)*1.61 -> 225.00555 | I34: =C34*J1 -> 4121.598 | J34: =G34*J1 -> 308.1 | K34: =C34+E34 -> 1310.92
A35: 29 | B35: 8290064 | C35: =IF(B35>=B34,B35-B34,0)*1.06 -> 1142.68 | D35: 557927 | E35: =IF(D35>=D34,D35-D34,0)*0.7 -> 263.9 | F35: 621250 | G35: =IF(F35>=F34,F35-F34,0) -> 100 | H35: =(E35*0.55)*1.61 -> 233.68345 | I35: =C35*J1 -> 4456.452 | J35: =G35*J1 -> 390 | K35: =C35+E35 -> 1406.58
A36: 30 | B36: 8291088 | C36: =IF(B36>=B35,B36-B35,0)*1.06 -> 1085.44 | D36: 558294.67 | E36: =IF(D36>=D35,D36-D35,0)*0.7 -> 257.36667 | F36: 621336 | G36: =IF(F36>=F35,F36-F35,0) -> 86 | H36: =(E36*0.55)*1.61 -> 227.89818 | I36: =C36*J1 -> 4233.216 | J36: =G36*J1 -> 335.4 | K36: =C36+E36 -> 1342.8067
A37: 31 | B37: 8292047 | C37: =IF(B37>=B36,B37-B36,0)*1.06 -> 1016.54 | D37: 558668.56 | E37: =IF(D37>=D36,D37-D36,0)*0.7 -> 261.72222 | F37: 621429 | G37: =IF(F37>=F36,F37-F36,0) -> 93 | H37: =(E37*0.55)*1.61 -> 231.75503 | I37: =C37*J1 -> 3964.506 | J37: =G37*J1 -> 362.7 | K37: =C37+E37 -> 1278.2622
A38: MTD | C38: =SUM(C7:C37) -> 29611.1 | E38: =SUM(E7:E37) -> 8641.1889 | G38: =SUM(G7:G37) -> 2773.0444 | H38: =SUM(H6:H37) -> 7651.7728 | I38: =SUM(I6:I37) -> 112924.34 | J38: =SUM(J6:J37) -> 10814.873 | K38: =SUM(K6:K37) -> 38252.289
A39: Average MTD. | C39: =C38/A42 -> 987.03667 | E39: =E38/A42 -> 288.03963 | G39: =G38/A42 -> 92.434815 | H39: =H38/A42 -> 255.05909 | I39: =I38/A42 -> 3764.1448 | J39: =J38/A42 -> 360.49578
A41: No of Days MTD
A42: =COUNTIF(B7:B36,">0") -> 30

Sheet Sheet1

Sheet Sheet2

Sheet Consp
A1: =Elect!A1 -> 44774 | L1: Summary | P1: =Elect!A1 -> 44774
B2: Elect Consuumption | H2: Water Incoming | U2: Water Consumption | AC2: Irrigation | AG2: Gas | AJ2: Cost | AK2: Solar Meter [ LIT ] | AL2: No. of Eng. | AM2: No. of Gardners | AN2: Cons. (lit) | AO2: Received Gas (tons) | AP2: Fuel Cost | AQ2: Solar level [cm] | AR2: Received Solar (tons) | AS2: Fuel Cost | AT2: Occupancy 10 | AV2: Occupancy07 | AZ2: Elect 2009 | BE2: Elect 2010 | BJ2: Water 2009 | BO2: Water 2010
A3: Date | B3: COUNTER (2) | D3: MD | F3: KVAR | H3: R.O | J3: Qenna | L3: Trucks | N3: Rimievera Line Meter | O3: Total Inc. | Q3: Total Main S.Pool | S3: Total Bar & Beach cons. | U3: Total S. Pool cons. | W3: Hotel consumption. | Y3: Sold Water | AA3: Irr. Water from R.O | AC3: Irr. Consumption. | AE3: Storage Water One tank | AF3: Grand Cons | AG3: % | AH3: Stock | AI3: Cons. | AJ3: 0 | AT3: No of guest | AU3: No. of rooms | AV3: No. of rooms | AW3: No. of guest | AX3: Cons. Per occ. room | AY3: Cons. Per guest | AZ3: Total cost | BA3: cost per room | BB3: cost per guest | BC3: Cons. Per occ. room | BD3: Cons. Per guest | BE3: Total cost | BF3: cost per room | BG3: cost per guest | BH3: Cons. Per occ. room | BI3: Cons. Per guest | BJ3: Total cost | BK3: cost per room | BL3: cost per guest | BM3: Cons. Per occ. room | BN3: Cons. Per guest | BO3: Total cost | BP3: cost per room | BQ3: cost per guest
B4: 2013 | C4: 2014 | D4: 2013 | E4: 2014 | F4: 2013 | G4: 2014 | H4: 2013 | I4: 2014 | J4: 2009 | K4: 2010 | L4: 2009 | M4: 2010 | O4: 2009 | P4: 2010 | Q4: 2009 | R4: 2010 | S4: 2009 | T4: 2010 | U4: 2009 | V4: 2010 | W4: 2009 | X4: 2010 | Y4: 2009 | Z4: 2010 | AA4: 2009 | AB4: 2010 | AC4: 2009 | AD4: 2010
A5: 1 | B5: 33600 | C5: =Elect!J6 -> 6551.3333 | D5: 0 | E5: =Elect!M6 -> 2082 | F5: 20 | G5: =Elect!O6 -> 3319.3333 | H5: 800 | I5: =Water!C7 -> 261 | J5: 0 | K5: =Water!E7 -> 353.8 | L5: 0 | M5: =Water!#REF! -> #REF! | N5: =Water!#REF! -> #REF! | O5: 1005 | P5: =Water!H7 -> 866.52 | Q5: 114 | R5: =Water!O7 -> 0 | S5: 13 | T5: =Water!#REF! -> #REF! | U5: 147 | V5: =Water!#REF! -> #REF! | W5: 755 | X5: =Water!Q7 -> 502.5816 | Y5: 0 | Z5: =Water!#REF! -> #REF! | AA5: 0 | AB5: 0 | AC5: 690 | AD5: =Water!#REF! -> #REF! | AE5: =Water!#REF! -> #REF! | AF5: =Water!#REF! -> #REF! | AG5: =Gas!#REF! -> #REF! | AH5: =Gas!C7 -> 935.98 | AI5: =Gas!#REF! -> #REF! | AJ5: =Gas!J7 -> 351.17333 | AK5: =Gas!#REF! -> #REF! | AL5: =Gas!#REF! -> #REF! | AM5: =Gas!#REF! -> #REF! | AN5: =Gas!#REF! -> #REF! | AO5: =Gas!#REF! -> #REF! | AP5: =Gas!#REF! -> #REF! | AQ5: =Gas!#REF! -> #REF! | AR5: =Gas!#REF! -> #REF! | AS5: =Gas!#REF! -> #REF! | AT5: =Elect!BR6 -> 164.5 | AU5: =Elect!BP6 -> 108 | AV5: =Elect!#REF! -> #REF! | AW5: =Elect!BR6 -> 164.5 | AX5: 48.695652 | AY5: 24.705882 | AZ5: 8835.4834 | BA5: 12.805048 | BB5: 6.496679 | BC5: =Elect!#REF! -> #REF! | BD5: =Elect!#REF! -> #REF! | BE5: =Elect!#REF! -> #REF! | BF5: =Elect!#REF! -> #REF! | BG5: =Elect!#REF! -> #REF! | BH5: 1.142029 | BI5: 0.57941176 | BJ5: 4569.1158 | BK5: 6.6219069 | BL5: 3.3596439 | BM5: =Water!U7 -> 5.4843038 | BN5: =Water!W7 -> #DIV/0! | BO5: =Water!X7 -> 3466.08 | BP5: =Water!Y7 -> 21.937215 | BQ5: =Water!Z7 -> 0
A6: 2 | B6: 31200 | C6: =Elect!J7 -> 5918 | D6: 0 | E6: =Elect!M7 -> 2064 | F6: 20 | G6: =Elect!O7 -> 2952 | H6: 936 | I6: =Water!C8 -> 17.4 | J6: 0 | K6: =Water!E8 -> 69.6 | L6: 0 | M6: =Water!#REF! -> #REF! | N6: =Water!#REF! -> #REF! | O6: 1006 | P6: =Water!H8 -> 116 | Q6: 113 | R6: =Water!O8 -> 0 | S6: 17 | T6: =Water!#REF! -> #REF! | U6: 140 | V6: =Water!#REF! -> #REF! | W6: 792 | X6: =Water!Q8 -> 67.28 | Y6: 0 | Z6: =Water!#REF! -> #REF! | AA6: 0 | AB6: 0 | AC6: 370 | AD6: =Water!#REF! -> #REF! | AE6: =Water!#REF! -> #REF! | AF6: =Water!#REF! -> #REF! | AG6: =Gas!B7 -> 8264995 | AH6: =Gas!C8 -> 935.98 | AI6: =Gas!#REF! -> #REF! | AJ6: =Gas!J8 -> 331.5 | AK6: =Gas!#REF! -> #REF! | AL6: =Gas!#REF! -> #REF! | AM6: =Gas!#REF! -> #REF! | AN6: =Gas!#REF! -> #REF! | AO6: =Gas!#REF! -> #REF! | AP6: =Gas!#REF! -> #REF! | AQ6: =Gas!#REF! -> #REF! | AR6: =Gas!#REF! -> #REF! | AS6: =Gas!#REF! -> #REF! | AT6: =Elect!BR7 -> 151 | AU6: =Elect!BP7 -> 111 | AX6: 47.416413 | AY6: 23.981553 | AZ6: 8299.2754 | BA6: 12.612881 | BB6: 6.379151 | BC6: =Elect!BQ7 -> 545094 | BD6: =Elect!#REF! -> #REF! | BE6: =Elect!#REF! -> #REF! | BF6: =Elect!#REF! -> #REF! | BG6: =Elect!#REF! -> #REF! | BH6: 1.2021277 | BI6: 0.60799385 | BJ6: 5345.8654 | BK6: 8.1244156 | BL6: 4.1090434 | BM6: =Water!U8 -> 0.71604938 | BN6: =Water!W8 -> #DIV/0! | BO6: =Water!X8 -> 464 | BP6: =Water!Y8 -> 2.8641975 | BQ6: =Water!Z8 -> #DIV/0!
A7: 3 | B7: 31200 | C7: =Elect!J8 -> 5763 | D7: 0 | E7: =Elect!M8 -> 1960 | F7: 20 | G7: =Elect!O8 -> 2834 | H7: 685 | I7: =Water!C9 -> 75.4 | J7: 0 | K7: =Water!E9 -> 46.4 | L7: 0 | M7: =Water!#REF! -> #REF! | N7: =Water!#REF! -> #REF! | O7: 902 | P7: =Water!H9 -> 183.86 | Q7: 126 | R7: =Water!O9 -> 0 | S7: 26 | T7: =Water!#REF! -> #REF! | U7: 134 | V7: =Water!#REF! -> #REF! | W7: 766 | X7: =Water!Q9 -> 106.6388 | Y7: 0 | Z7: =Water!#REF! -> #REF! | AA7: 0 | AB7: 0 | AC7: 740 | AD7: =Water!#REF! -> #REF! | AE7: =Water!#REF! -> #REF! | AF7: =Water!#REF! -> #REF! | AG7: =Gas!B9 -> 8266761 | AH7: =Gas!C9 -> 935.98 | AI7: =Gas!#REF! -> #REF! | AJ7: =Gas!J9 -> 366.6 | AK7: =Gas!#REF! -> #REF! | AL7: =Gas!#REF! -> #REF! | AM7: =Gas!#REF! -> #REF! | AN7: =Gas!#REF! -> #REF! | AO7: =Gas!#REF! -> #REF! | AP7: =Gas!#REF! -> #REF! | AQ7: =Gas!#REF! -> #REF! | AR7: =Gas!#REF! -> #REF! | AS7: =Gas!#REF! -> #REF! | AT7: =Elect!BR8 -> 135 | AU7: =Elect!BP8 -> 104 | AX7: 47.926267 | AY7: 24.223602 | AZ7: 8299.2754 | BA7: 12.748503 | BB7: 6.4435368 | BC7: =Elect!BQ8 -> 545229 | BD7: =Elect!#REF! -> #REF! | BE7: =Elect!#REF! -> #REF! | BF7: =Elect!#REF! -> #REF! | BG7: =Elect!#REF! -> #REF! | BH7: 1.0875576 | BI7: 0.54968944 | BJ7: 3912.3054 | BK7: 6.0096857 | BL7: 3.0375042 | BM7: =Water!U9 -> 1.0627746 | BN7: =Water!W9 -> #DIV/0! | BO7: =Water!X9 -> 735.44 | BP7: =Water!Y9 -> 4.2510983 | BQ7: =Water!Z9 -> #DIV/0!
A8: 4 | B8: 33600 | C8: =Elect!J9 -> 5347 | D8: 0 | E8: =Elect!M9 -> 1935 | F8: 20 | G8: =Elect!O9 -> 2978 | H8: 786 | I8: =Water!C10 -> 75.4 | J8: 0 | K8: =Water!E10 -> 61.866667 | L8: 0 | M8: =Water!#REF! -> #REF! | N8: =Water!#REF! -> #REF! | O8: 930 | P8: =Water!H10 -> 177.28667 | Q8: 153 | R8: =Water!O10 -> 0 | S8: 46 | T8: =Water!#REF! -> #REF! | U8: 150 | V8: =Water!#REF! -> #REF! | W8: 766 | X8: =Water!Q10 -> 102.82627 | Y8: 0 | Z8: =Water!#REF! -> #REF! | AA8: 0 | AB8: 0 | AC8: 820 | AD8: =Water!#REF! -> #REF! | AE8: =Water!#REF! -> #REF! | AF8: =Water!#REF! -> #REF! | AG8: =Gas!B10 -> 8267644 | AH8: =Gas!C10 -> 935.98 | AI8: =Gas!#REF! -> #REF! | AJ8: =Gas!J10 -> 343.2 | AK8: =Gas!#REF! -> #REF! | AL8: =Gas!#REF! -> #REF! | AM8: =Gas!#REF! -> #REF! | AN8: =Gas!#REF! -> #REF! | AO8: =Gas!#REF! -> #REF! | AP8: =Gas!#REF! -> #REF! | AQ8: =Gas!#REF! -> #REF! | AR8: =Gas!#REF! -> #REF! | AS8: =Gas!#REF! -> #REF! | AT8: =Elect!BR9 -> 138 | AU8: =Elect!BP9 -> 108 | AX8: 51.06383 | AY8: 25.866051 | AZ8: 8835.4834 | BA8: 13.427786 | BB8: 6.8017578 | BC8: =Elect!BQ9 -> 545367 | BD8: =Elect!#REF! -> #REF! | BE8: =Elect!#REF! -> #REF! | BF8: =Elect!#REF! -> #REF! | BG8: =Elect!#REF! -> #REF! | BH8: 1.2218845 | BI8: 0.61893764 | BJ8: 4489.1562 | BK8: 6.8224259 | BL8: 3.4558555 | BM8: =Water!U10 -> 0.87765677 | BN8: =Water!W10 -> #DIV/0! | BO8: =Water!X10 -> 709.14667 | BP8: =Water!Y10 -> 3.5106271 | BQ8: =Water!Z10 -> #DIV/0!
A9: 5 | B9: 31200 | C9: =Elect!J10 -> 8470 | D9: 0 | E9: =Elect!M10 -> 1952 | F9: 20 | G9: =Elect!O10 -> 3082 | H9: 789 | I9: =Water!C11 -> 191.4 | J9: 0 | K9: =Water!E11 -> 286.13333 | L9: 0 | M9: =Water!#REF! -> #REF! | N9: =Water!#REF! -> #REF! | O9: 1003 | P9: =Water!H11 -> 666.03333 | Q9: 102 | R9: =Water!O11 -> 0 | S9: 8 | T9: =Water!#REF! -> #REF! | U9: 130 | V9: =Water!#REF! -> #REF! | W9: 735 | X9: =Water!Q11 -> 386.29933 | Y9: 0 | Z9: =Water!#REF! -> #REF! | AA9: 0 | AB9: 0 | AC9: 640 | AD9: =Water!#REF! -> #REF! | AE9: =Water!#REF! -> #REF! | AF9: =Water!#REF! -> #REF! | AG9: =Gas!B11 -> 8268527 | AH9: =Gas!C11 -> 935.98 | AI9: =Gas!#REF! -> #REF! | AJ9: =Gas!J11 -> 386.1 | AK9: =Gas!#REF! -> #REF! | AL9: =Gas!#REF! -> #REF! | AM9: =Gas!#REF! -> #REF! | AN9: =Gas!#REF! -> #REF! | AO9: =Gas!#REF! -> #REF! | AP9: =Gas!#REF! -> #REF! | AQ9: =Gas!#REF! -> #REF! | AR9: =Gas!#REF! -> #REF! | AS9: =Gas!#REF! -> #REF! | AT9: =Elect!BR10 -> 140 | AU9: =Elect!BP10 -> 110 | AX9: 49.840256 | AY9: 25.181598 | AZ9: 8299.2754 | BA9: 13.257628 | BB9: 6.698366 | BC9: =Elect!BQ10 -> 545507 | BD9: =Elect!#REF! -> #REF! | BE9: =Elect!#REF! -> #REF! | BF9: =Elect!#REF! -> #REF! | BG9: =Elect!#REF! -> #REF! | BH9: 1.1980831 | BI9: 0.60532688 | BJ9: 4506.2904 | BK9: 7.198547 | BL9: 3.6370383 | BM9: =Water!U11 -> 3.0834877 | BN9: =Water!W11 -> #DIV/0! | BO9: =Water!X11 -> 2664.1333 | BP9: =Water!Y11 -> 12.333951 | BQ9: =Water!Z11 -> #DIV/0!
A10: 6 | B10: 33600 | C10: =Elect!J11 -> 1859 | D10: 0 | E10: =Elect!M11 -> 1915 | F10: 20 | G10: =Elect!O11 -> 2508 | H10: 805 | I10: =Water!C12 -> 116 | J10: 0 | K10: =Water!E12 -> 156.6 | L10: 0 | M10: =Water!#REF! -> #REF! | N10: =Water!#REF! -> #REF! | O10: 1004 | P10: =Water!H12 -> 385.12 | Q10: 115 | R10: =Water!O12 -> 0 | S10: 21 | T10: =Water!#REF! -> #REF! | U10: 141 | V10: =Water!#REF! -> #REF! | W10: 725 | X10: =Water!Q12 -> 223.3696 | Y10: 0 | Z10: =Water!#REF! -> #REF! | AA10: 0 | AB10: 0 | AC10: 510 | AD10: =Water!#REF! -> #REF! | AE10: =Water!#REF! -> #REF! | AF10: =Water!#REF! -> #REF! | AG10: =Gas!B12 -> 8269410 | AH10: =Gas!C12 -> 935.98 | AI10: =Gas!#REF! -> #REF! | AJ10: =Gas!J12 -> 347.1 | AK10: =Gas!#REF! -> #REF! | AL10: =Gas!#REF! -> #REF! | AM10: =Gas!#REF! -> #REF! | AN10: =Gas!#REF! -> #REF! | AO10: =Gas!#REF! -> #REF! | AP10: =Gas!#REF! -> #REF! | AQ10: =Gas!#REF! -> #REF! | AR10: =Gas!#REF! -> #REF! | AS10: =Gas!#REF! -> #REF! | AT10: =Elect!BR11 -> 154 | AU10: =Elect!BP11 -> 106 | AX10: 47.457627 | AY10: 23.512946 | AZ10: 8835.4834 | BA10: 12.479496 | BB10: 6.1829835 | BC10: =Elect!BQ11 -> 545661 | BD10: =Elect!#REF! -> #REF! | BE10: =Elect!#REF! -> #REF! | BF10: =Elect!#REF! -> #REF! | BG10: =Elect!#REF! -> #REF! | BH10: 1.1567797 | BI10: 0.57312806 | BJ10: 4597.6727 | BK10: 6.4938881 | BL10: 3.2174057 | BM10: =Water!U12 -> 1.7192857 | BN10: =Water!W12 -> #DIV/0! | BO10: =Water!X12 -> 1540.48 | BP10: =Water!Y12 -> 6.8771429 | BQ10: =Water!Z12 -> #DIV/0!
A11: 7 | B11: 31200 | C11: =Elect!J12 -> 5452 | D11: 0 | E11: =Elect!M12 -> 1942 | F11: 20 | G11: =Elect!O12 -> 2483 | H11: 871 | I11: =Water!C13 -> 133.4 | J11: 0 | K11: =Water!E13 -> 174 | L11: 0 | M11: =Water!#REF! -> #REF! | N11: =Water!#REF! -> #REF! | O11: 837 | P11: =Water!H13 -> 415.28 | Q11: 113 | R11: =Water!O13 -> 0 | S11: 1 | T11: =Water!#REF! -> #REF! | U11: 151 | V11: =Water!#REF! -> #REF! | W11: 732 | X11: =Water!Q13 -> 240.8624 | Y11: 0 | Z11: =Water!#REF! -> #REF! | AA11: 0 | AB11: 0 | AC11: 1010 | AD11: =Water!#REF! -> #REF! | AE11: =Water!#REF! -> #REF! | AF11: =Water!#REF! -> #REF! | AG11: =Gas!B13 -> 8270293 | AH11: =Gas!C13 -> 935.98 | AI11: =Gas!#REF! -> #REF! | AJ11: =Gas!J13 -> 374.4 | AK11: =Gas!#REF! -> #REF! | AL11: =Gas!#REF! -> #REF! | AM11: =Gas!#REF! -> #REF! | AN11: =Gas!#REF! -> #REF! | AO11: =Gas!#REF! -> #REF! | AP11: =Gas!#REF! -> #REF! | AQ11: =Gas!#REF! -> #REF! | AR11: =Gas!#REF! -> #REF! | AS11: =Gas!#REF! -> #REF! | AT11: =Elect!BR12 -> 145 | AU11: =Elect!BP12 -> 110 | AX11: 43.454039 | AY11: 21.517241 | AZ11: 8299.2754 | BA11: 11.558879 | BB11: 5.7236382 | BC11: =Elect!BQ12 -> 545806 | BD11: =Elect!#REF! -> #REF! | BE11: =Elect!#REF! -> #REF! | BF11: =Elect!#REF! -> #REF! | BG11: =Elect!#REF! -> #REF! | BH11: 1.1713092 | BI11: 0.58 | BJ11: 4974.6248 | BK11: 6.9284468 | BL11: 3.4307757 | BM11: =Water!U13 -> 1.879095 | BN11: =Water!W13 -> #DIV/0! | BO11: =Water!X13 -> 1661.12 | BP11: =Water!Y13 -> 7.5163801 | BQ11: =Water!Z13 -> #DIV/0!
A12: 8 | B12: 33600 | C12: =Elect!J13 -> 5595 | D12: 0 | E12: =Elect!M13 -> 2042 | F12: 20 | G12: =Elect!O13 -> 2507 | H12: 963 | I12: =Water!C14 -> 127.6 | J12: 0 | K12: =Water!E14 -> 168.2 | L12: 0 | M12: =Water!#REF! -> #REF! | N12: =Water!#REF! -> #REF! | O12: 1000 | P12: =Water!H14 -> 392.66 | Q12: 128 | R12: =Water!O14 -> 0 | S12: 24 | T12: =Water!#REF! -> #REF! | U12: 148 | V12: =Water!#REF! -> #REF! | W12: 719 | X12: =Water!Q14 -> 227.7428 | Y12: 0 | Z12: =Water!#REF! -> #REF! | AA12: 0 | AB12: 0 | AC12: 630 | AD12: =Water!#REF! -> #REF! | AE12: =Water!#REF! -> #REF! | AF12: =Water!#REF! -> #REF! | AG12: =Gas!B14 -> 8271176 | AH12: =Gas!C14 -> 935.98 | AI12: =Gas!#REF! -> #REF! | AJ12: =Gas!J14 -> 366.6 | AK12: =Gas!#REF! -> #REF! | AL12: =Gas!#REF! -> #REF! | AM12: =Gas!#REF! -> #REF! | AN12: =Gas!#REF! -> #REF! | AO12: =Gas!#REF! -> #REF! | AP12: =Gas!#REF! -> #REF! | AQ12: =Gas!#REF! -> #REF! | AR12: =Gas!#REF! -> #REF! | AS12: =Gas!#REF! -> #REF! | AT12: =Elect!BR13 -> 165 | AU12: =Elect!BP13 -> 119 | AX12: 48.837209 | AY12: 24.086022 | AZ12: 8835.4834 | BA12: 12.842272 | BB12: 6.3336799 | BC12: =Elect!BQ13 -> 545971 | BD12: =Elect!#REF! -> #REF! | BE12: =Elect!#REF! -> #REF! | BF12: =Elect!#REF! -> #REF! | BG12: =Elect!#REF! -> #REF! | BH12: 1.2194767 | BI12: 0.60143369 | BJ12: 5500.0731 | BK12: 7.9942923 | BL12: 3.9427047 | BM12: =Water!U14 -> 1.8178704 | BN12: =Water!W14 -> #DIV/0! | BO12: =Water!X14 -> 1570.64 | BP12: =Water!Y14 -> 7.2714815 | BQ12: =Water!Z14 -> #DIV/0!
A13: 9 | B13: 33600 | C13: =Elect!J14 -> 5699 | D13: 0 | E13: =Elect!M14 -> 1980 | F13: 20 | G13: =Elect!O14 -> 2568 | H13: 790 | I13: =Water!C15 -> 145 | J13: 0 | K13: =Water!E15 -> 191.4 | L13: 0 | M13: =Water!#REF! -> #REF! | N13: =Water!#REF! -> #REF! | O13: 841 | P13: =Water!H15 -> 446.6 | Q13: 127 | R13: =Water!O15 -> 0 | S13: 21 | T13: =Water!#REF! -> #REF! | U13: 139 | V13: =Water!#REF! -> #REF! | W13: 701 | X13: =Water!Q15 -> 259.028 | Y13: 0 | Z13: =Water!#REF! -> #REF! | AA13: 0 | AB13: 0 | AC13: 440 | AD13: =Water!#REF! -> #REF! | AE13: =Water!#REF! -> #REF! | AF13: =Water!#REF! -> #REF! | AG13: =Gas!B15 -> 8272059 | AH13: =Gas!C15 -> 935.98 | AI13: =Gas!#REF! -> #REF! | AJ13: =Gas!J15 -> 354.9 | AK13: =Gas!#REF! -> #REF! | AL13: =Gas!#REF! -> #REF! | AM13: =Gas!#REF! -> #REF! | AN13: =Gas!#REF! -> #REF! | AO13: =Gas!#REF! -> #REF! | AP13: =Gas!#REF! -> #REF! | AQ13: =Gas!#REF! -> #REF! | AR13: =Gas!#REF! -> #REF! | AS13: =Gas!#REF! -> #REF! | AT13: =Elect!BR14 -> 139 | AU13: =Elect!BP14 -> 117 | AX13: 49.194729 | AY13: 24.1033 | AZ13: 8835.4834 | BA13: 12.936286 | BB13: 6.3382234 | BC13: =Elect!BQ14 -> 546110 | BD13: =Elect!#REF! -> #REF! | BE13: =Elect!#REF! -> #REF! | BF13: =Elect!#REF! -> #REF! | BG13: =Elect!#REF! -> #REF! | BH13: 1.1903367 | BI13: 0.58321377 | BJ13: 4512.0018 | BK13: 6.606152 | BL13: 3.2367301 | BM13: =Water!U15 -> 2.2670051 | BN13: =Water!W15 -> #DIV/0! | BO13: =Water!X15 -> 1786.4 | BP13: =Water!Y15 -> 9.0680203 | BQ13: =Water!Z15 -> #DIV/0!
A14: 10 | B14: 31200 | C14: =Elect!J15 -> 5652 | D14: 0 | E14: =Elect!M15 -> 2002 | F14: 20 | G14: =Elect!O15 -> 2781 | H14: 792 | I14: =Water!C16 -> 145 | J14: 0 | K14: =Water!E16 -> 197.2 | L14: 0 | M14: =Water!#REF! -> #REF! | N14: =Water!#REF! -> #REF! | O14: 972 | P14: =Water!H16 -> 440.8 | Q14: 126 | R14: =Water!O16 -> 0 | S14: 18 | T14: =Water!#REF! -> #REF! | U14: 145 | V14: =Water!#REF! -> #REF! | W14: 756 | X14: =Water!Q16 -> 255.664 | Y14: 0 | Z14: =Water!#REF! -> #REF! | AA14: 0 | AB14: 0 | AC14: 580 | AD14: =Water!#REF! -> #REF! | AE14: =Water!#REF! -> #REF! | AF14: =Water!#REF! -> #REF! | AG14: =Gas!B16 -> 8272942 | AH14: =Gas!C16 -> 935.98 | AI14: =Gas!#REF! -> #REF! | AJ14: =Gas!J16 -> 304.2 | AK14: =Gas!#REF! -> #REF! | AL14: =Gas!#REF! -> #REF! | AM14: =Gas!#REF! -> #REF! | AN14: =Gas!#REF! -> #REF! | AO14: =Gas!#REF! -> #REF! | AP14: =Gas!#REF! -> #REF! | AQ14: =Gas!#REF! -> #REF! | AR14: =Gas!#REF! -> #REF! | AS14: =Gas!#REF! -> #REF! | AT14: =Elect!BR15 -> 151 | AU14: =Elect!BP15 -> 114 | AX14: 49.52381 | AY14: 24.781573 | AZ14: 8299.2754 | BA14: 13.173453 | BB14: 6.5919582 | BC14: =Elect!BQ15 -> 546261 | BD14: =Elect!#REF! -> #REF! | BE14: =Elect!#REF! -> #REF! | BF14: =Elect!#REF! -> #REF! | BG14: =Elect!#REF! -> #REF! | BH14: 1.2730159 | BI14: 0.6370135 | BJ14: 4469.9646 | BK14: 7.0951819 | BL14: 3.5504087 | BM14: =Water!U16 -> 2.2721649 | BN14: =Water!W16 -> #DIV/0! | BO14: =Water!X16 -> 1763.2 | BP14: =Water!Y16 -> 9.0886598 | BQ14: =Water!Z16 -> #DIV/0!
A15: 11 | B15: 33600 | C15: =Elect!J16 -> 5348 | D15: 0 | E15: =Elect!M16 -> 2016 | F15: 20 | G15: =Elect!O16 -> 2672 | H15: 817 | I15: =Water!C17 -> 145 | J15: 0 | K15: =Water!E17 -> 193.33333 | L15: 0 | M15: =Water!#REF! -> #REF! | N15: =Water!#REF! -> #REF! | O15: 875 | P15: =Water!H17 -> 444.66667 | Q15: 122 | R15: =Water!O17 -> 0 | S15: 20 | T15: =Water!#REF! -> #REF! | U15: 156 | V15: =Water!#REF! -> #REF! | W15: 712 | X15: =Water!Q17 -> 257.90667 | Y15: 0 | Z15: =Water!#REF! -> #REF! | AA15: 0 | AB15: 0 | AC15: 850 | AD15: =Water!#REF! -> #REF! | AE15: =Water!#REF! -> #REF! | AF15: =Water!#REF! -> #REF! | AG15: =Gas!#REF! -> #REF! | AH15: =Gas!C17 -> 935.98 | AI15: =Gas!#REF! -> #REF! | AJ15: =Gas!J17 -> 611 | AK15: =Gas!#REF! -> #REF! | AL15: =Gas!#REF! -> #REF! | AM15: =Gas!#REF! -> #REF! | AN15: =Gas!#REF! -> #REF! | AO15: =Gas!#REF! -> #REF! | AP15: =Gas!#REF! -> #REF! | AQ15: =Gas!#REF! -> #REF! | AR15: =Gas!#REF! -> #REF! | AS15: =Gas!#REF! -> #REF! | AT15: =Elect!BR16 -> 160 | AU15: =Elect!BP16 -> 109 | AX15: 53.333333 | AY15: 26.751592 | AZ15: 8835.4834 | BA15: 14.024577 | BB15: 7.0346206 | BC15: =Elect!BQ16 -> 546421 | BD15: =Elect!#REF! -> #REF! | BE15: =Elect!#REF! -> #REF! | BF15: =Elect!#REF! -> #REF! | BG15: =Elect!#REF! -> #REF! | BH15: 1.3460317 | BI15: 0.67515924 | BJ15: 4666.2095 | BK15: 7.4066817 | BL15: 3.7151349 | BM15: =Water!U17 -> 2.107425 | BN15: =Water!W17 -> #DIV/0! | BO15: =Water!X17 -> 1778.6667 | BP15: =Water!Y17 -> 8.4296998 | BQ15: =Water!Z17 -> #DIV/0!
A16: 12 | B16: 33600 | C16: =Elect!J17 -> 5312 | D16: 0 | E16: =Elect!M17 -> 2067 | F16: 20 | G16: =Elect!O17 -> 2597 | H16: 907 | I16: =Water!C18 -> 133.4 | J16: 0 | K16: =Water!E18 -> 166.26667 | L16: 0 | M16: =Water!#REF! -> #REF! | N16: =Water!#REF! -> #REF! | O16: 965 | P16: =Water!H18 -> 402.13333 | Q16: 125 | R16: =Water!O18 -> 0 | S16: 4 | T16: =Water!#REF! -> #REF! | U16: 167 | V16: =Water!#REF! -> #REF! | W16: 705 | X16: =Water!Q18 -> 233.23733 | Y16: 0 | Z16: =Water!#REF! -> #REF! | AA16: 0 | AB16: 0 | AC16: 880 | AD16: =Water!#REF! -> #REF! | AE16: =Water!#REF! -> #REF! | AF16: =Water!#REF! -> #REF! | AG16: =Gas!B18 -> 8274708 | AH16: =Gas!C18 -> 935.98 | AI16: =Gas!#REF! -> #REF! | AJ16: =Gas!J18 -> 122.2 | AK16: =Gas!#REF! -> #REF! | AL16: =Gas!#REF! -> #REF! | AM16: =Gas!#REF! -> #REF! | AN16: =Gas!#REF! -> #REF! | AO16: =Gas!#REF! -> #REF! | AP16: =Gas!#REF! -> #REF! | AQ16: =Gas!#REF! -> #REF! | AR16: =Gas!#REF! -> #REF! | AS16: =Gas!#REF! -> #REF! | AT16: =Elect!BR17 -> 143 | AU16: =Elect!BP17 -> 109 | AX16: 50.45045 | AY16: 25.339367 | AZ16: 8835.4834 | BA16: 13.266492 | BB16: 6.6632605 | BC16: =Elect!BQ17 -> 546564 | BD16: =Elect!#REF! -> #REF! | BE16: =Elect!#REF! -> #REF! | BF16: =Elect!#REF! -> #REF! | BG16: =Elect!#REF! -> #REF! | BH16: 1.2162162 | BI16: 0.61085973 | BJ16: 5180.235 | BK16: 7.7781306 | BL16: 3.9066629 | BM16: =Water!U18 -> 1.6825662 | BN16: =Water!W18 -> #DIV/0! | BO16: =Water!X18 -> 1608.5333 | BP16: =Water!Y18 -> 6.730265 | BQ16: =Water!Z18 -> #DIV/0!
A17: 13 | B17: 31200 | C17: =Elect!J18 -> 5606 | D17: 0 | E17: =Elect!M18 -> 1868 | F17: 20 | G17: =Elect!O18 -> 1837 | H17: 812 | I17: =Water!C19 -> 121.8 | J17: 0 | K17: =Water!E19 -> 162.4 | L17: 0 | M17: =Water!#REF! -> #REF! | N17: =Water!#REF! -> #REF! | O17: 822 | P17: =Water!H19 -> 386.28 | Q17: 123 | R17: =Water!O19 -> 0 | S17: 7 | T17: =Water!#REF! -> #REF! | U17: 163 | V17: =Water!#REF! -> #REF! | W17: 692 | X17: =Water!Q19 -> 224.0424 | Y17: 0 | Z17: =Water!#REF! -> #REF! | AA17: 0 | AB17: 0 | AC17: 460 | AD17: =Water!#REF! -> #REF! | AE17: =Water!#REF! -> #REF! | AF17: =Water!#REF! -> #REF! | AG17: =Gas!B19 -> 8275591 | AH17: =Gas!C19 -> 935.98 | AI17: =Gas!#REF! -> #REF! | AJ17: =Gas!J19 -> 358.8 | AK17: =Gas!#REF! -> #REF! | AL17: =Gas!#REF! -> #REF! | AM17: =Gas!#REF! -> #REF! | AN17: =Gas!#REF! -> #REF! | AO17: =Gas!#REF! -> #REF! | AP17: =Gas!#REF! -> #REF! | AQ17: =Gas!#REF! -> #REF! | AR17: =Gas!#REF! -> #REF! | AS17: =Gas!#REF! -> #REF! | AT17: =Elect!BR18 -> 179 | AU17: =Elect!BP18 -> 111 | AX17: 46.567164 | AY17: 23.214286 | AZ17: 8299.2754 | BA17: 12.386978 | BB17: 6.1750561 | BC17: =Elect!BQ18 -> 546743 | BD17: =Elect!#REF! -> #REF! | BE17: =Elect!#REF! -> #REF! | BF17: =Elect!#REF! -> #REF! | BG17: =Elect!#REF! -> #REF! | BH17: 1.0850746 | BI17: 0.54092262 | BJ17: 4637.6525 | BK17: 6.9218694 | BL17: 3.4506343 | BM17: =Water!U19 -> 1.701674 | BN17: =Water!W19 -> #DIV/0! | BO17: =Water!X19 -> 1545.12 | BP17: =Water!Y19 -> 6.806696 | BQ17: =Water!Z19 -> #DIV/0!
A18: 14 | B18: 33600 | C18: =Elect!J19 -> 5425 | D18: 0 | E18: =Elect!M19 -> 1961 | F18: 30 | G18: =Elect!O19 -> 2059 | H18: 810 | I18: =Water!C20 -> 139.2 | J18: 0 | K18: =Water!E20 -> 185.6 | L18: 0 | M18: =Water!#REF! -> #REF! | N18: =Water!#REF! -> #REF! | O18: 943 | P18: =Water!H20 -> 428.62 | Q18: 118 | R18: =Water!O20 -> 0 | S18: 18 | T18: =Water!#REF! -> #REF! | U18: 152 | V18: =Water!#REF! -> #REF! | W18: 708 | X18: =Water!Q20 -> 248.5996 | Y18: 0 | Z18: =Water!#REF! -> #REF! | AA18: 0 | AB18: 0 | AC18: 490 | AD18: =Water!#REF! -> #REF! | AE18: =Water!#REF! -> #REF! | AF18: =Water!#REF! -> #REF! | AG18: =Gas!B20 -> 8276474 | AH18: =Gas!C20 -> 935.98 | AI18: =Gas!#REF! -> #REF! | AJ18: =Gas!J20 -> 319.8 | AK18: =Gas!#REF! -> #REF! | AL18: =Gas!#REF! -> #REF! | AM18: =Gas!#REF! -> #REF! | AN18: =Gas!#REF! -> #REF! | AO18: =Gas!#REF! -> #REF! | AP18: =Gas!#REF! -> #REF! | AQ18: =Gas!#REF! -> #REF! | AR18: =Gas!#REF! -> #REF! | AS18: =Gas!#REF! -> #REF! | AT18: =Elect!BR19 -> 174 | AU18: =Elect!BP19 -> 105 | AX18: 47.795164 | AY18: 24.207493 | AZ18: 8835.4834 | BA18: 12.568255 | BB18: 6.3656221 | BC18: =Elect!BQ6 -> 544943 | BD18: =Elect!#REF! -> #REF! | BE18: =Elect!#REF! -> #REF! | BF18: =Elect!#REF! -> #REF! | BG18: =Elect!#REF! -> #REF! | BH18: 1.1024182 | BI18: 0.55835735 | BJ18: 4626.2297 | BK18: 6.5806966 | BL18: 3.3330185 | BM18: =Water!U20 -> 1.9843519 | BN18: =Water!W20 -> #DIV/0! | BO18: =Water!X20 -> 1714.48 | BP18: =Water!Y20 -> 7.9374074 | BQ18: =Water!Z20 -> #DIV/0!
A19: 15 | B19: 31200 | C19: =Elect!J20 -> 4969 | D19: 0 | E19: =Elect!M20 -> 1898 | F19: 20 | G19: =Elect!O20 -> 2126 | H19: 841 | I19: =Water!C21 -> 133.4 | J19: 0 | K19: =Water!E21 -> 174 | L19: 0 | M19: =Water!#REF! -> #REF! | N19: =Water!#REF! -> #REF! | O19: 947 | P19: =Water!H21 -> 414.12 | Q19: 131 | R19: =Water!O21 -> 0 | S19: 23 | T19: =Water!#REF! -> #REF! | U19: 166 | V19: =Water!#REF! -> #REF! | W19: 787 | X19: =Water!Q21 -> 240.1896 | Y19: 0 | Z19: =Water!#REF! -> #REF! | AA19: 0 | AB19: 0 | AC19: 730 | AD19: =Water!#REF! -> #REF! | AE19: =Water!#REF! -> #REF! | AF19: =Water!#REF! -> #REF! | AG19: =Gas!B21 -> 8277357 | AH19: =Gas!C21 -> 935.98 | AI19: =Gas!#REF! -> #REF! | AJ19: =Gas!J21 -> 374.4 | AK19: =Gas!#REF! -> #REF! | AL19: =Gas!#REF! -> #REF! | AM19: =Gas!#REF! -> #REF! | AN19: =Gas!#REF! -> #REF! | AO19: =Gas!#REF! -> #REF! | AP19: =Gas!#REF! -> #REF! | AQ19: =Gas!#REF! -> #REF! | AR19: =Gas!#REF! -> #REF! | AS19: =Gas!#REF! -> #REF! | AT19: =Elect!BR20 -> 139 | AU19: =Elect!BP20 -> 109 | AX19: 41.6 | AY19: 20.995962 | AZ19: 8299.2754 | BA19: 11.065701 | BB19: 5.5849767 | BC19: =Elect!BQ20 -> 547056 | BD19: =Elect!#REF! -> #REF! | BE19: =Elect!#REF! -> #REF! | BF19: =Elect!#REF! -> #REF! | BG19: =Elect!#REF! -> #REF! | BH19: 1.1506667 | BI19: 0.58114478 | BJ19: 4803.283 | BK19: 6.4043773 | BL19: 3.234534 | BM19: =Water!U21 -> 1.962654 | BN19: =Water!W21 -> #DIV/0! | BO19: =Water!X21 -> 1656.48 | BP19: =Water!Y21 -> 7.8506161 | BQ19: =Water!Z21 -> #DIV/0!
A20: 16 | B20: 36000 | C20: =Elect!J21 -> 5253 | D20: 0 | E20: =Elect!M21 -> 1927 | F20: 20 | G20: =Elect!O21 -> 2143 | H20: 932 | I20: =Water!C22 -> 133.4 | J20: 0 | K20: =Water!E22 -> 174 | L20: 0 | M20: =Water!#REF! -> #REF! | N20: =Water!#REF! -> #REF! | O20: 998 | P20: =Water!H22 -> 412.18667 | Q20: 136 | R20: =Water!O22 -> 0 | S20: 22 | T20: =Water!#REF! -> #REF! | U20: 162 | V20: =Water!#REF! -> #REF! | W20: 703 | X20: =Water!Q22 -> 239.06827 | Y20: 0 | Z20: =Water!#REF! -> #REF! | AA20: 0 | AB20: 0 | AC20: 600 | AD20: =Water!#REF! -> #REF! | AE20: =Water!#REF! -> #REF! | AF20: =Water!#REF! -> #REF! | AG20: =Gas!B22 -> 8278240 | AH20: =Gas!C22 -> 935.98 | AI20: =Gas!#REF! -> #REF! | AJ20: =Gas!J22 -> 354.9 | AK20: =Gas!#REF! -> #REF! | AL20: =Gas!#REF! -> #REF! | AM20: =Gas!#REF! -> #REF! | AN20: =Gas!#REF! -> #REF! | AO20: =Gas!#REF! -> #REF! | AP20: =Gas!#REF! -> #REF! | AQ20: =Gas!#REF! -> #REF! | AR20: =Gas!#REF! -> #REF! | AS20: =Gas!#REF! -> #REF! | AT20: =Elect!BR21 -> 131 | AU20: =Elect!BP21 -> 111 | AX20: 48 | AY20: 24.22611 | AZ20: 9371.6914 | BA20: 12.495589 | BB20: 6.3066564 | BC20: =Elect!BQ21 -> 547187 | BD20: =Elect!#REF! -> #REF! | BE20: =Elect!#REF! -> #REF! | BF20: =Elect!#REF! -> #REF! | BG20: =Elect!#REF! -> #REF! | BH20: 1.1626667 | BI20: 0.58720539 | BJ20: 5323.0199 | BK20: 7.0973598 | BL20: 3.5845252 | BM20: =Water!U22 -> 2.1246735 | BN20: =Water!W22 -> #DIV/0! | BO20: =Water!X22 -> 1648.7467 | BP20: =Water!Y22 -> 8.4986942 | BQ20: =Water!Z22 -> #DIV/0!
A21: 17 | B21: 33600 | C21: =Elect!J22 -> 5063.6667 | D21: 0 | E21: =Elect!M22 -> 1907.6667 | F21: 20 | G21: =Elect!O22 -> 2131.6667 | H21: 972 | I21: =Water!C23 -> 133.4 | J21: 0 | K21: =Water!E23 -> 174 | L21: 0 | M21: =Water!#REF! -> #REF! | N21: =Water!#REF! -> #REF! | O21: 998 | P21: =Water!H23 -> 413.47556 | Q21: 136 | R21: =Water!O23 -> 0 | S21: 38 | T21: =Water!#REF! -> #REF! | U21: 137 | V21: =Water!#REF! -> #REF! | W21: 740 | X21: =Water!Q23 -> 239.81582 | Y21: 0 | Z21: =Water!#REF! -> #REF! | AA21: 0 | AB21: 0 | AC21: 690 | AD21: =Water!#REF! -> #REF! | AE21: =Water!#REF! -> #REF! | AF21: =Water!#REF! -> #REF! | AG21: =Gas!B23 -> 8279123 | AH21: =Gas!C23 -> 935.98 | AI21: =Gas!#REF! -> #REF! | AJ21: =Gas!J23 -> 367.9 | AK21: =Gas!#REF! -> #REF! | AL21: =Gas!#REF! -> #REF! | AM21: =Gas!#REF! -> #REF! | AN21: =Gas!#REF! -> #REF! | AO21: =Gas!#REF! -> #REF! | AP21: =Gas!#REF! -> #REF! | AQ21: =Gas!#REF! -> #REF! | AR21: =Gas!#REF! -> #REF! | AS21: =Gas!#REF! -> #REF! | AT21: =Elect!BR22 -> 136.33333 | AU21: =Elect!BP22 -> 109 | AX21: 44.385733 | AY21: 22.207535 | AZ21: 8835.4834 | BA21: 11.671709 | BB21: 5.8397115 | BC21: =Elect!#REF! -> #REF! | BD21: =Elect!#REF! -> #REF! | BE21: =Elect!#REF! -> #REF! | BF21: =Elect!#REF! -> #REF! | BG21: =Elect!#REF! -> #REF! | BH21: 1.1770145 | BI21: 0.58889623 | BJ21: 5551.4757 | BK21: 7.3335213 | BL21: 3.6691842 | BM21: =Water!U23 -> 2.1423604 | BN21: =Water!W23 -> #DIV/0! | BO21: =Water!X23 -> 1653.9022 | BP21: =Water!Y23 -> 8.5694416 | BQ21: =Water!Z23 -> #DIV/0!
A22: 18 | B22: 33600 | C22: =Elect!J23 -> 5570.3333 | D22: 0 | E22: =Elect!M23 -> 1987.3333 | F22: 20 | G22: =Elect!O23 -> 2214.3333 | H22: 864 | I22: =Water!C24 -> 133.4 | J22: 0 | K22: =Water!E24 -> 174 | L22: 0 | M22: =Water!#REF! -> #REF! | N22: =Water!#REF! -> #REF! | O22: 1002 | P22: =Water!H24 -> 413.15333 | Q22: 118 | R22: =Water!O24 -> 0 | S22: 21 | T22: =Water!#REF! -> #REF! | U22: 133 | V22: =Water!#REF! -> #REF! | W22: 769 | X22: =Water!Q24 -> 239.62893 | Y22: 0 | Z22: =Water!#REF! -> #REF! | AA22: 0 | AB22: 0 | AC22: 930 | AD22: =Water!#REF! -> #REF! | AE22: =Water!#REF! -> #REF! | AF22: =Water!#REF! -> #REF! | AG22: =Gas!B24 -> 8280006 | AH22: =Gas!C24 -> 935.98 | AI22: =Gas!#REF! -> #REF! | AJ22: =Gas!J24 -> 182 | AK22: =Gas!#REF! -> #REF! | AL22: =Gas!#REF! -> #REF! | AM22: =Gas!#REF! -> #REF! | AN22: =Gas!#REF! -> #REF! | AO22: =Gas!#REF! -> #REF! | AP22: =Gas!#REF! -> #REF! | AQ22: =Gas!#REF! -> #REF! | AR22: =Gas!#REF! -> #REF! | AS22: =Gas!#REF! -> #REF! | AT22: =Elect!BR23 -> 171.66667 | AU22: =Elect!BP23 -> 103 | AX22: 44.680851 | AY22: 22.459893 | AZ22: 8835.4834 | BA22: 11.749313 | BB22: 5.9060718 | BC22: =Elect!BQ23 -> 547495 | BD22: =Elect!#REF! -> #REF! | BE22: =Elect!#REF! -> #REF! | BF22: =Elect!#REF! -> #REF! | BG22: =Elect!#REF! -> #REF! | BH22: 1.1236702 | BI22: 0.56483957 | BJ22: 4934.645 | BK22: 6.562028 | BL22: 3.2985595 | BM22: =Water!U24 -> 2.0761474 | BN22: =Water!W24 -> #DIV/0! | BO22: =Water!X24 -> 1652.6133 | BP22: =Water!Y24 -> 8.3045896 | BQ22: =Water!Z24 -> #DIV/0!
A23: 19 | B23: 33600 | C23: =Elect!J24 -> 5386 | D23: 0 | E23: =Elect!M24 -> 1934.2222 | F23: 30 | G23: =Elect!O24 -> 2159.2222 | H23: 894 | I23: =Water!C25 -> 104.4 | J23: 0 | K23: =Water!E25 -> 139.2 | L23: 0 | M23: =Water!#REF! -> #REF! | N23: =Water!#REF! -> #REF! | O23: 944 | P23: =Water!H25 -> 326.02444 | Q23: 110 | R23: =Water!O25 -> 0 | S23: 14 | T23: =Water!#REF! -> #REF! | U23: 155 | V23: =Water!#REF! -> #REF! | W23: 721 | X23: =Water!Q25 -> 189.09418 | Y23: 0 | Z23: =Water!#REF! -> #REF! | AA23: 0 | AB23: 0 | AC23: 660 | AD23: =Water!#REF! -> #REF! | AE23: =Water!#REF! -> #REF! | AF23: =Water!#REF! -> #REF! | AG23: =Gas!B25 -> 8280889 | AH23: =Gas!C25 -> 935.98 | AI23: =Gas!#REF! -> #REF! | AJ23: =Gas!J25 -> 78 | AK23: =Gas!#REF! -> #REF! | AL23: =Gas!#REF! -> #REF! | AM23: =Gas!#REF! -> #REF! | AN23: =Gas!#REF! -> #REF! | AO23: =Gas!#REF! -> #REF! | AP23: =Gas!#REF! -> #REF! | AQ23: =Gas!#REF! -> #REF! | AR23: =Gas!#REF! -> #REF! | AS23: =Gas!#REF! -> #REF! | AT23: =Elect!BR24 -> 135 | AU23: =Elect!BP24 -> 108 | AX23: 44.8 | AY23: 22.44489 | AZ23: 8835.4834 | BA23: 11.780645 | BB23: 5.9021265 | BC23: =Elect!BQ24 -> 547630 | BD23: =Elect!#REF! -> #REF! | BE23: =Elect!#REF! -> #REF! | BF23: =Elect!#REF! -> #REF! | BG23: =Elect!#REF! -> #REF! | BH23: 1.1346667 | BI23: 0.56847027 | BJ23: 5105.9869 | BK23: 6.8079825 | BL23: 3.4108129 | BM23: =Water!U25 -> 1.7069343 | BN23: =Water!W25 -> #DIV/0! | BO23: =Water!X25 -> 1304.0978 | BP23: =Water!Y25 -> 6.8277371 | BQ23: =Water!Z25 -> #DIV/0!
A24: 20 | B24: 33600 | C24: =Elect!J25 -> 5348 | D24: 0 | E24: =Elect!M25 -> 1969.6296 | F24: 20 | G24: =Elect!O25 -> 2195.963 | H24: 944 | I24: =Water!C26 -> 133.4 | J24: 0 | K24: =Water!E26 -> 168.2 | L24: 0 | M24: =Water!#REF! -> #REF! | N24: =Water!#REF! -> #REF! | O24: 1000 | P24: =Water!H26 -> 397.88 | Q24: 138 | R24: =Water!O26 -> 0 | S24: 15 | T24: =Water!#REF! -> #REF! | U24: 165 | V24: =Water!#REF! -> #REF! | W24: 778 | X24: =Water!Q26 -> 230.7704 | Y24: 0 | Z24: =Water!#REF! -> #REF! | AA24: 0 | AB24: 0 | AC24: 560 | AD24: =Water!#REF! -> #REF! | AE24: =Water!#REF! -> #REF! | AF24: =Water!#REF! -> #REF! | AG24: =Gas!B26 -> 8281772 | AH24: =Gas!C26 -> 935.98 | AI24: =Gas!#REF! -> #REF! | AJ24: =Gas!J26 -> 729.3 | AK24: =Gas!#REF! -> #REF! | AL24: =Gas!#REF! -> #REF! | AM24: =Gas!#REF! -> #REF! | AN24: =Gas!#REF! -> #REF! | AO24: =Gas!#REF! -> #REF! | AP24: =Gas!#REF! -> #REF! | AQ24: =Gas!#REF! -> #REF! | AR24: =Gas!#REF! -> #REF! | AS24: =Gas!#REF! -> #REF! | AT24: =Elect!BR25 -> 149 | AU24: =Elect!BP25 -> 108 | AX24: 42.857143 | AY24: 21.649485 | AZ24: 8835.4834 | BA24: 11.269749 | BB24: 5.6929661 | BC24: =Elect!BQ25 -> 547779 | BD24: =Elect!#REF! -> #REF! | BE24: =Elect!#REF! -> #REF! | BF24: =Elect!#REF! -> #REF! | BG24: =Elect!#REF! -> #REF! | BH24: 1.1683673 | BI24: 0.59020619 | BJ24: 5391.5566 | BK24: 6.8769855 | BL24: 3.4739411 | BM24: =Water!U26 -> 1.7842152 | BN24: =Water!W26 -> #DIV/0! | BO24: =Water!X26 -> 1591.52 | BP24: =Water!Y26 -> 7.136861 | BQ24: =Water!Z26 -> #DIV/0!
A25: 21 | B25: 36000 | C25: =Elect!J26 -> 4965 | D25: 0 | E25: =Elect!M26 -> 1747.1481 | F25: 20 | G25: =Elect!O26 -> 2415.8148 | H25: 916 | I25: =Water!C27 -> 127.6 | J25: 0 | K25: =Water!E27 -> 174 | L25: 0 | M25: =Water!#REF! -> #REF! | N25: =Water!#REF! -> #REF! | O25: 998 | P25: =Water!H27 -> 407.74 | Q25: 186 | R25: =Water!O27 -> 0 | S25: 43 | T25: =Water!#REF! -> #REF! | U25: 176 | V25: =Water!#REF! -> #REF! | W25: 773 | X25: =Water!Q27 -> 236.4892 | Y25: 0 | Z25: =Water!#REF! -> #REF! | AA25: 0 | AB25: 0 | AC25: 950 | AD25: =Water!#REF! -> #REF! | AE25: =Water!#REF! -> #REF! | AF25: =Water!#REF! -> #REF! | AG25: =Gas!B27 -> 8282655 | AH25: =Gas!C27 -> 935.98 | AI25: =Gas!#REF! -> #REF! | AJ25: =Gas!J27 -> 343.2 | AK25: =Gas!#REF! -> #REF! | AL25: =Gas!#REF! -> #REF! | AM25: =Gas!#REF! -> #REF! | AN25: =Gas!#REF! -> #REF! | AO25: =Gas!#REF! -> #REF! | AP25: =Gas!#REF! -> #REF! | AQ25: =Gas!#REF! -> #REF! | AR25: =Gas!#REF! -> #REF! | AS25: =Gas!#REF! -> #REF! | AT25: =Elect!BR26 -> 140 | AU25: =Elect!BP26 -> 106 | AX25: 43.956044 | AY25: 22.222222 | AZ25: 9371.6914 | BA25: 11.442847 | BB25: 5.7849947 | BC25: =Elect!BQ26 -> 547919 | BD25: =Elect!#REF! -> #REF! | BE25: =Elect!#REF! -> #REF! | BF25: =Elect!#REF! -> #REF! | BG25: =Elect!#REF! -> #REF! | BH25: 1.0586081 | BI25: 0.53518519 | BJ25: 5231.6376 | BK25: 6.3878358 | BL25: 3.2294059 | BM25: =Water!U27 -> 1.9233019 | BN25: =Water!W27 -> #DIV/0! | BO25: =Water!X27 -> 1630.96 | BP25: =Water!Y27 -> 7.6932075 | BQ25: =Water!Z27 -> #DIV/0!
A26: 22 | B26: 33600 | C26: =Elect!J27 -> 4821 | D26: 0 | E26: =Elect!M27 -> 1855 | F26: 20 | G26: =Elect!O27 -> 2225 | H26: 931 | I26: =Water!C28 -> 121.8 | J26: 0 | K26: =Water!E28 -> 156.6 | L26: 0 | M26: =Water!#REF! -> #REF! | N26: =Water!#REF! -> #REF! | O26: 969 | P26: =Water!H28 -> 381.64 | Q26: 151 | R26: =Water!O28 -> 0 | S26: 29 | T26: =Water!#REF! -> #REF! | U26: 157 | V26: =Water!#REF! -> #REF! | W26: 697 | X26: =Water!Q28 -> 221.3512 | Y26: 0 | Z26: =Water!#REF! -> #REF! | AA26: 0 | AB26: 0 | AC26: 700 | AD26: =Water!#REF! -> #REF! | AE26: =Water!#REF! -> #REF! | AF26: =Water!#REF! -> #REF! | AG26: =Gas!B28 -> 8283538 | AH26: =Gas!C28 -> 935.98 | AI26: =Gas!#REF! -> #REF! | AJ26: =Gas!J28 -> 319.8 | AK26: =Gas!#REF! -> #REF! | AL26: =Gas!#REF! -> #REF! | AM26: =Gas!#REF! -> #REF! | AN26: =Gas!#REF! -> #REF! | AO26: =Gas!#REF! -> #REF! | AP26: =Gas!#REF! -> #REF! | AQ26: =Gas!#REF! -> #REF! | AR26: =Gas!#REF! -> #REF! | AS26: =Gas!#REF! -> #REF! | AT26: =Elect!BR27 -> 139 | AU26: =Elect!BP27 -> 109 | AX26: 39.952438 | AY26: 20.253165 | AZ26: 8835.4834 | BA26: 10.505926 | BB26: 5.3257887 | BC26: =Elect!BQ27 -> 548058 | BD26: =Elect!#REF! -> #REF! | BE26: =Elect!#REF! -> #REF! | BF26: =Elect!#REF! -> #REF! | BG26: =Elect!#REF! -> #REF! | BH26: 1.0903686 | BI26: 0.55274262 | BJ26: 5317.3085 | BK26: 6.3226022 | BL26: 3.2051287 | BM26: =Water!U28 -> 2.0969231 | BN26: =Water!W28 -> #DIV/0! | BO26: =Water!X28 -> 1526.56 | BP26: =Water!Y28 -> 8.3876923 | BQ26: =Water!Z28 -> #DIV/0!
A27: 23 | B27: 36000 | C27: =Elect!J28 -> 4281 | D27: 0 | E27: =Elect!M28 -> 1779 | F27: 30 | G27: =Elect!O28 -> 2293 | H27: 1009 | I27: =Water!C29 -> 139.2 | J27: 0 | K27: =Water!E29 -> 185.6 | L27: 0 | M27: =Water!#REF! -> #REF! | N27: =Water!#REF! -> #REF! | O27: 902 | P27: =Water!H29 -> 433.26 | Q27: 131 | R27: =Water!O29 -> 0 | S27: 6 | T27: =Water!#REF! -> #REF! | U27: 167 | V27: =Water!#REF! -> #REF! | W27: 748 | X27: =Water!Q29 -> 251.2908 | Y27: 0 | Z27: =Water!#REF! -> #REF! | AA27: 0 | AB27: 0 | AC27: 690 | AD27: =Water!#REF! -> #REF! | AE27: =Water!#REF! -> #REF! | AF27: =Water!#REF! -> #REF! | AG27: =Gas!B29 -> 8284421 | AH27: =Gas!C29 -> 935.98 | AI27: =Gas!#REF! -> #REF! | AJ27: =Gas!J29 -> 370.5 | AK27: =Gas!#REF! -> #REF! | AL27: =Gas!#REF! -> #REF! | AM27: =Gas!#REF! -> #REF! | AN27: =Gas!#REF! -> #REF! | AO27: =Gas!#REF! -> #REF! | AP27: =Gas!#REF! -> #REF! | AQ27: =Gas!#REF! -> #REF! | AR27: =Gas!#REF! -> #REF! | AS27: =Gas!#REF! -> #REF! | AT27: =Elect!BR28 -> 138 | AU27: =Elect!BP28 -> 106 | AX27: 42.755344 | AY27: 21.543986 | AZ27: 9371.6914 | BA27: 11.130275 | BB27: 5.6084329 | BC27: =Elect!BQ28 -> 548196 | BD27: =Elect!#REF! -> #REF! | BE27: =Elect!#REF! -> #REF! | BF27: =Elect!#REF! -> #REF! | BG27: =Elect!#REF! -> #REF! | BH27: 1.0712589 | BI27: 0.53979653 | BJ27: 5762.7973 | BK27: 6.8441773 | BL27: 3.4487117 | BM27: =Water!U29 -> 2.3805495 | BN27: =Water!W29 -> #DIV/0! | BO27: =Water!X29 -> 1733.04 | BP27: =Water!Y29 -> 9.5221978 | BQ27: =Water!Z29 -> #DIV/0!
A28: 24 | B28: 33600 | C28: =Elect!J29 -> 4363 | D28: 0 | E28: =Elect!M29 -> 1933 | F28: 20 | G28: =Elect!O29 -> 2377 | H28: 891 | I28: =Water!C30 -> 133.4 | J28: 0 | K28: =Water!E30 -> 52.2 | L28: 0 | M28: =Water!#REF! -> #REF! | N28: =Water!#REF! -> #REF! | O28: 818 | P28: =Water!H30 -> 279.56 | Q28: 221 | R28: =Water!O30 -> 0 | S28: 93 | T28: =Water!#REF! -> #REF! | U28: 191 | V28: =Water!#REF! -> #REF! | W28: 827 | X28: =Water!Q30 -> 162.1448 | Y28: 0 | Z28: =Water!#REF! -> #REF! | AA28: 0 | AB28: 0 | AC28: 470 | AD28: =Water!#REF! -> #REF! | AE28: =Water!#REF! -> #REF! | AF28: =Water!#REF! -> #REF! | AG28: =Gas!B30 -> 8285304 | AH28: =Gas!C30 -> 935.98 | AI28: =Gas!#REF! -> #REF! | AJ28: =Gas!J30 -> 312 | AK28: =Gas!#REF! -> #REF! | AL28: =Gas!#REF! -> #REF! | AM28: =Gas!#REF! -> #REF! | AN28: =Gas!#REF! -> #REF! | AO28: =Gas!#REF! -> #REF! | AP28: =Gas!#REF! -> #REF! | AQ28: =Gas!#REF! -> #REF! | AR28: =Gas!#REF! -> #REF! | AS28: =Gas!#REF! -> #REF! | AT28: =Elect!BR29 -> 142 | AU28: =Elect!BP29 -> 104 | AX28: 39.904988 | AY28: 20.289855 | AZ28: 8835.4834 | BA28: 10.493448 | BB28: 5.3354369 | BC28: =Elect!BQ29 -> 548338 | BD28: =Elect!#REF! -> #REF! | BE28: =Elect!#REF! -> #REF! | BF28: =Elect!#REF! -> #REF! | BG28: =Elect!#REF! -> #REF! | BH28: 1.1104513 | BI28: 0.56461353 | BJ28: 5088.8527 | BK28: 6.043768 | BL28: 3.0729787 | BM28: =Water!U30 -> 1.5974857 | BN28: =Water!W30 -> #DIV/0! | BO28: =Water!X30 -> 1118.24 | BP28: =Water!Y30 -> 6.3899429 | BQ28: =Water!Z30 -> #DIV/0!
A29: 25 | B29: 33600 | C29: =Elect!J30 -> 6523 | D29: 0 | E29: =Elect!M30 -> 2448 | F29: 20 | G29: =Elect!O30 -> 2416 | H29: 1008 | I29: =Water!C31 -> 133.4 | J29: 0 | K29: =Water!E31 -> 141.13333 | L29: 0 | M29: =Water!#REF! -> #REF! | N29: =Water!#REF! -> #REF! | O29: 1290 | P29: =Water!H31 -> 378.16 | Q29: 34 | R29: =Water!O31 -> 0 | S29: 34 | T29: =Water!#REF! -> #REF! | U29: 55 | V29: =Water!#REF! -> #REF! | W29: 681 | X29: =Water!Q31 -> 219.3328 | Y29: 0 | Z29: =Water!#REF! -> #REF! | AA29: 0 | AB29: 0 | AC29: 1170 | AD29: =Water!#REF! -> #REF! | AE29: =Water!#REF! -> #REF! | AF29: =Water!#REF! -> #REF! | AG29: =Gas!B31 -> 8285923 | AH29: =Gas!C31 -> 656.14 | AI29: =Gas!#REF! -> #REF! | AJ29: =Gas!J31 -> 312 | AK29: =Gas!#REF! -> #REF! | AL29: =Gas!#REF! -> #REF! | AM29: =Gas!#REF! -> #REF! | AN29: =Gas!#REF! -> #REF! | AO29: =Gas!#REF! -> #REF! | AP29: =Gas!#REF! -> #REF! | AQ29: =Gas!#REF! -> #REF! | AR29: =Gas!#REF! -> #REF! | AS29: =Gas!#REF! -> #REF! | AT29: =Elect!BR30 -> 134 | AU29: =Elect!BP30 -> 113 | AX29: 39.763314 | AY29: 20.20445 | AZ29: 8835.4834 | BA29: 10.456193 | BB29: 5.3129786 | BC29: =Elect!BQ30 -> 548472 | BD29: =Elect!#REF! -> #REF! | BE29: =Elect!#REF! -> #REF! | BF29: =Elect!#REF! -> #REF! | BG29: =Elect!#REF! -> #REF! | BH29: 1.0059172 | BI29: 0.51112447 | BJ29: 5757.0859 | BK29: 6.8131194 | BL29: 3.4618676 | BM29: =Water!U31 -> 2.185896 | BN29: =Water!W31 -> #DIV/0! | BO29: =Water!X31 -> 1512.64 | BP29: =Water!Y31 -> 8.7435838 | BQ29: =Water!Z31 -> #DIV/0!
A30: 26 | B30: 31200 | C30: =Elect!J31 -> 5192 | D30: 0 | E30: =Elect!M31 -> 1714 | F30: 20 | G30: =Elect!O31 -> 1677 | H30: 760 | I30: =Water!C32 -> 98.6 | J30: 0 | K30: =Water!E32 -> 282.26667 | L30: 0 | M30: =Water!#REF! -> #REF! | N30: =Water!#REF! -> #REF! | O30: 1004 | P30: =Water!H32 -> 466.32 | Q30: 131 | R30: =Water!O32 -> 0 | S30: 33 | T30: =Water!#REF! -> #REF! | U30: 145 | V30: =Water!#REF! -> #REF! | W30: 916 | X30: =Water!Q32 -> 270.4656 | Y30: 0 | Z30: =Water!#REF! -> #REF! | AA30: 0 | AB30: 0 | AC30: 810 | AD30: =Water!#REF! -> #REF! | AE30: =Water!#REF! -> #REF! | AF30: =Water!#REF! -> #REF! | AG30: =Gas!B32 -> 8286938 | AH30: =Gas!C32 -> 1075.9 | AI30: =Gas!#REF! -> #REF! | AJ30: =Gas!J32 -> 397.8 | AK30: =Gas!#REF! -> #REF! | AL30: =Gas!#REF! -> #REF! | AM30: =Gas!#REF! -> #REF! | AN30: =Gas!#REF! -> #REF! | AO30: =Gas!#REF! -> #REF! | AP30: =Gas!#REF! -> #REF! | AQ30: =Gas!#REF! -> #REF! | AR30: =Gas!#REF! -> #REF! | AS30: =Gas!#REF! -> #REF! | AT30: =Elect!BR31 -> 140 | AU30: =Elect!BP31 -> 110 | AX30: 37.275986 | AY30: 18.989653 | AZ30: 8299.2754 | BA30: 9.9155023 | BB30: 5.0512936 | BC30: =Elect!BQ31 -> 548612 | BD30: =Elect!#REF! -> #REF! | BE30: =Elect!#REF! -> #REF! | BF30: =Elect!#REF! -> #REF! | BG30: =Elect!#REF! -> #REF! | BH30: 1.1063321 | BI30: 0.56360316 | BJ30: 4340.66 | BK30: 5.1859737 | BL30: 2.6419111 | BM30: =Water!U32 -> 2.68 | BN30: =Water!W32 -> #DIV/0! | BO30: =Water!X32 -> 1865.28 | BP30: =Water!Y32 -> 10.72 | BQ30: =Water!Z32 -> #DIV/0!
A31: 27 | B31: 36000 | C31: =Elect!J32 -> 5544 | D31: 0 | E31: =Elect!M32 -> 1982 | F31: 30 | G31: =Elect!O32 -> 1904 | H31: 1010 | I31: =Water!C33 -> 127.6 | J31: 0 | K31: =Water!E33 -> 168.2 | L31: 0 | M31: =Water!#REF! -> #REF! | N31: =Water!#REF! -> #REF! | O31: 1014 | P31: =Water!H33 -> 405.42 | Q31: 151 | R31: =Water!O33 -> 0 | S31: 30 | T31: =Water!#REF! -> #REF! | U31: 139 | V31: =Water!#REF! -> #REF! | W31: 761 | X31: =Water!Q33 -> 235.1436 | Y31: 0 | Z31: =Water!#REF! -> #REF! | AA31: 0 | AB31: 0 | AC31: 930 | AD31: =Water!#REF! -> #REF! | AE31: =Water!#REF! -> #REF! | AF31: =Water!#REF! -> #REF! | AG31: =Gas!B33 -> 8287989 | AH31: =Gas!C33 -> 1114.06 | AI31: =Gas!#REF! -> #REF! | AJ31: =Gas!J33 -> 339.3 | AK31: =Gas!#REF! -> #REF! | AL31: =Gas!#REF! -> #REF! | AM31: =Gas!#REF! -> #REF! | AN31: =Gas!#REF! -> #REF! | AO31: =Gas!#REF! -> #REF! | AP31: =Gas!#REF! -> #REF! | AQ31: =Gas!#REF! -> #REF! | AR31: =Gas!#REF! -> #REF! | AS31: =Gas!#REF! -> #REF! | AT31: =Elect!BR32 -> 140 | AU31: =Elect!BP32 -> 105 | AX31: 44.063647 | AY31: 22.346369 | AZ31: 9371.6914 | BA31: 11.470859 | BB31: 5.8173131 | BC31: =Elect!BQ32 -> 548752 | BD31: =Elect!#REF! -> #REF! | BE31: =Elect!#REF! -> #REF! | BF31: =Elect!#REF! -> #REF! | BG31: =Elect!#REF! -> #REF! | BH31: 1.1640147 | BI31: 0.59031657 | BJ31: 5768.5087 | BK31: 7.0605981 | BL31: 3.5807006 | BM31: =Water!U33 -> 2.0372864 | BN31: =Water!W33 -> #DIV/0! | BO31: =Water!X33 -> 1621.68 | BP31: =Water!Y33 -> 8.1491457 | BQ31: =Water!Z33 -> #DIV/0!
A32: 28 | B32: 33600 | C32: =Elect!J33 -> 5391 | D32: 0 | E32: =Elect!M33 -> 1971 | F32: 20 | G32: =Elect!O33 -> 1902 | H32: 1008 | I32: =Water!C34 -> 121.8 | J32: 0 | K32: =Water!E34 -> 162.4 | L32: 1 | M32: =Water!#REF! -> #REF! | N32: =Water!#REF! -> #REF! | O32: 1013 | P32: =Water!H34 -> 389.18 | Q32: 142 | R32: =Water!O34 -> 0 | S32: 13 | T32: =Water!#REF! -> #REF! | U32: 155 | V32: =Water!#REF! -> #REF! | W32: 825 | X32: =Water!Q34 -> 225.7244 | Y32: 1 | Z32: =Water!#REF! -> #REF! | AA32: 0 | AB32: 0 | AC32: 650 | AD32: =Water!#REF! -> #REF! | AE32: =Water!#REF! -> #REF! | AF32: =Water!#REF! -> #REF! | AG32: =Gas!B34 -> 8288986 | AH32: =Gas!C34 -> 1056.82 | AI32: =Gas!#REF! -> #REF! | AJ32: =Gas!J34 -> 308.1 | AK32: =Gas!#REF! -> #REF! | AL32: =Gas!#REF! -> #REF! | AM32: =Gas!#REF! -> #REF! | AN32: =Gas!#REF! -> #REF! | AO32: =Gas!#REF! -> #REF! | AP32: =Gas!#REF! -> #REF! | AQ32: =Gas!#REF! -> #REF! | AR32: =Gas!#REF! -> #REF! | AS32: =Gas!#REF! -> #REF! | AT32: =Elect!BR33 -> 141 | AU32: =Elect!BP33 -> 112 | AX32: 45.34413 | AY32: 22.687373 | AZ32: 8835.4834 | BA32: 11.923729 | BB32: 5.9658902 | BC32: =Elect!BQ33 -> 548893 | BD32: =Elect!#REF! -> #REF! | BE32: =Elect!#REF! -> #REF! | BF32: =Elect!#REF! -> #REF! | BG32: =Elect!#REF! -> #REF! | BH32: 1.2294197 | BI32: 0.61512492 | BJ32: 5757.0859 | BK32: 7.7693467 | BL32: 3.8872963 | BM32: =Water!U34 -> 2.2892941 | BN32: =Water!W34 -> #DIV/0! | BO32: =Water!X34 -> 1556.72 | BP32: =Water!Y34 -> 9.1571765 | BQ32: =Water!Z34 -> #DIV/0!
A33: MTD | B33: 931200 | C33: =Elect!J34 -> 4435 | D33: 0 | E33: =Elect!M34 -> 2164 | F33: 600 | G33: =Elect!O34 -> 2453 | H33: 24543 | I33: =Water!C38 -> 3955.6 | J33: 0 | K33: =Water!E39 -> 173.80667 | L33: 3 | M33: =Water!#REF! -> #REF! | N33: =Water!#REF! -> #REF! | O33: 1013 | P33: =Water!H38 -> 12413.74 | Q33: 109 | R33: =Water!O38 -> 0 | S33: 15 | T33: =Water!#REF! -> #REF! | U33: 147 | V33: =Water!#REF! -> #REF! | W33: 730 | X33: =Water!Q38 -> 6536.5884 | Y33: 3 | Z33: =Water!#REF! -> #REF! | AA33: 0 | AB33: 0 | AC33: 0 | AD33: =Water!#REF! -> #REF! | AE33: =Water!#REF! -> #REF! | AF33: =Water!#REF! -> #REF! | AG33: =Gas!B38 -> 0 | AH33: =Gas!C38 -> 29611.1 | AI33: =Gas!#REF! -> #REF! | AJ33: =Gas!J38 -> 10814.873 | AK33: =Gas!#REF! -> #REF! | AL33: =Gas!#REF! -> #REF! | AM33: =Gas!#REF! -> #REF! | AN33: =Gas!#REF! -> #REF! | AO33: =Gas!#REF! -> #REF! | AP33: =Gas!#REF! -> #REF! | AQ33: =Gas!#REF! -> #REF! | AR33: =Gas!#REF! -> #REF! | AS33: =Gas!#REF! -> #REF! | AT33: =Elect!BR34 -> 144 | AU33: =Elect!BP34 -> 87 | AX33: 45.411099 | AY33: 22.844806 | AZ33: 245248.7 | BA33: 11.959851 | BB33: 6.0166013 | BC33: =Elect!BQ34 -> 549037 | BD33: =Elect!#REF! -> #REF! | BE33: =Elect!#REF! -> #REF! | BF33: =Elect!#REF! -> #REF! | BG33: =Elect!#REF! -> #REF! | BH33: 1.1514679 | BI33: 0.57929342 | BJ33: 140121.3 | BK33: 6.8331854 | BL33: 3.4377159 | BM33: =Water!U38 -> 2.1311142 | BN33: =Water!W38 -> #DIV/0! | BO33: =Water!X38 -> 48245.947 | BP33: =Water!Y38 -> 8.282566 | BQ33: =Water!Z38 -> #DIV/0!
A34: AVER. Act | B34: 33257.143 | C34: =Elect!J35 -> 5517 | D34: 0 | E34: =Elect!M35 -> 2160 | F34: 21.428571 | G34: =Elect!O35 -> 2451 | H34: 876.53571 | I34: =Water!C39 -> 131.85333 | J34: 0 | K34: =Water!E40 -> 0 | L34: 4 | M34: =Water!#REF! -> #REF! | N34: =Water!#REF! -> #REF! | O34: 1014 | P34: =Water!H39 -> 413.79133 | Q34: 138 | R34: =Water!O39 -> 0 | S34: 24 | T34: =Water!#REF! -> #REF! | U34: 145 | V34: =Water!#REF! -> #REF! | W34: 877 | X34: =Water!Q39 -> 217.88628 | Y34: 4 | Z34: =Water!#REF! -> #REF! | AA34: 0 | AB34: 0 | AC34: 0 | AD34: =Water!#REF! -> #REF! | AE34: =Water!#REF! -> #REF! | AF34: =Water!#REF! -> #REF! | AG34: =Gas!B39 -> 0 | AH34: =Gas!C39 -> 987.03667 | AI34: =Gas!#REF! -> #REF! | AJ34: =Gas!J39 -> 360.49578 | AK34: =Gas!#REF! -> #REF! | AL34: =Gas!#REF! -> #REF! | AM34: =Gas!#REF! -> #REF! | AN34: =Gas!#REF! -> #REF! | AO34: =Gas!#REF! -> #REF! | AP34: =Gas!#REF! -> #REF! | AQ34: =Gas!#REF! -> #REF! | AR34: =Gas!#REF! -> #REF! | AS34: =Gas!#REF! -> #REF! | AT34: =Elect!BR35 -> 153 | AU34: =Elect!BP35 -> 89 | AX34: 45.411099 | AY34: 22.844806 | AZ34: 8758.8823 | BA34: 11.959851 | BB34: 6.0166013 | BC34: =Elect!BQ35 -> 549190 | BD34: =Elect!#REF! -> #REF! | BE34: =Elect!#REF! -> #REF! | BF34: =Elect!#REF! -> #REF! | BG34: =Elect!#REF! -> #REF! | BH34: 1.1761372 | BI34: 0.60007377 | BJ34: 5004.3322 | BK34: 6.8331854 | BL34: 3.4377159 | BM34: =Water!U39 -> 2.1311142 | BN34: =Water!W39 -> #DIV/0! | BO34: =Water!X39 -> 1608.1982 | BP34: =Water!Y39 -> 8.282566 | BQ34: =Water!Z39 -> #DIV/0!
A35: TOTAL Budget | B35: 1040026 | C35: =Elect!J5 -> 0 | D35: 0 | E35: =Elect!M5 -> 0 | F35: 0 | G35: =Elect!O5 -> 0 | H35: 0 | I35: =Water!C40 -> 0 | J35: 0 | K35: =Water!E41 -> 0 | L35: 5 | M35: =Water!#REF! -> #REF! | N35: =Water!#REF! -> #REF! | O35: 1010 | P35: =Water!H40 -> 0 | Q35: 148 | R35: =Water!O40 -> 0 | S35: 22 | T35: =Water!#REF! -> #REF! | U35: 151 | V35: =Water!#REF! -> #REF! | W35: 833 | X35: =Water!Q40 -> 0 | Y35: 5 | Z35: =Water!#REF! -> #REF! | AA35: 0 | AB35: 0 | AC35: 0 | AD35: =Water!#REF! -> #REF! | AE35: =Water!#REF! -> #REF! | AF35: =Water!#REF! -> #REF! | AG35: =Gas!#REF! -> #REF! | AH35: =Gas!#REF! -> #REF! | AI35: =Gas!#REF! -> #REF! | AJ35: =Gas!#REF! -> #REF! | AK35: =Gas!#REF! -> #REF! | AL35: =Gas!#REF! -> #REF! | AM35: =Gas!#REF! -> #REF! | AN35: =Gas!#REF! -> #REF! | ... AS35: =Gas!#REF! -> #REF! | AT35: =Elect!BR5 -> 0 | AU35: =Elect!BP5 -> 0 | AX35: 45.679286 | AY35: 23.305904 | AZ35: 264708.4 | BA35: 11.626335 | BB35: 5.9318409 | BC35: =Elect!BQ5 -> 544778.5 | BD35: =Elect!#REF! -> #REF! | BE35: =Elect!#REF! -> #REF! | BF35: =Elect!#REF! -> #REF! | BG35: =Elect!#REF! -> #REF! | BH35: 1.1761372 | BI35: 0.60007377 | BJ35: 150494 | BK35: 6.6098911 | BL35: 3.3724146 | BM35: =Water!U40 -> #REF! | BN35: =Water!W40 -> #REF! | BO35: =Water!X40 -> 0 | BP35: =Water!Y40 -> 0 | BQ35: =Water!Z40 -> 0
A36: Budget MTD | B36: 1040026 | C36: =Elect!#REF! -> #REF! | D36: 0 | E36: =Elect!#REF! -> #REF! | F36: 0 | G36: =Elect!#REF! -> #REF! | H36: 0 | I36: =Water!C41 -> 0 | J36: 0 | K36: =Water!E42 -> 0 | L36: 6 | M36: =Water!#REF! -> #REF! | N36: =Water!#REF! -> #REF! | O36: 30039 | P36: =Water!H41 -> 0 | Q36: 129.54839 | R36: =Water!O41 -> 0 | S36: 719 | T36: =Water!#REF! -> #REF! | U36: 4609 | V36: =Water!#REF! -> #REF! | W36: 23430 | X36: =Water!Q41 -> 0 | Y36: 6 | Z36: =Water!#REF! -> #REF! | AA36: 0 | AB36: 0 | AC36: 0 | AD36: =Water!#REF! -> #REF! | AE36: =Water!#REF! -> #REF! | AF36: =Water!#REF! -> #REF! | AG36: =Gas!#REF! -> #REF! | AH36: =Gas!#REF! -> #REF! | AI36: =Gas!#REF! -> #REF! | AJ36: =Gas!#REF! -> #REF! | AK36: =Gas!#REF! -> #REF! | AL36: =Gas!#REF! -> #REF! | AM36: =Gas!#REF! -> #REF! | AN36: =Gas!#REF! -> #REF! | ... AS36: =Gas!#REF! -> #REF! | AT36: =Elect!#REF! -> #REF! | AU36: =Elect!#REF! -> #REF! | AX36: 45.679286 | AY36: 23.305904 | AZ36: 264708.4 | BA36: 11.626335 | BB36: 5.9318409 | BC36: =Elect!#REF! -> #REF! | BD36: =Elect!#REF! -> #REF! | BE36: =Elect!#REF! -> #REF! | BF36: =Elect!#REF! -> #REF! | BG36: =Elect!#REF! -> #REF! | BH36: 0 | BI36: 0 | BJ36: 135930.06 | BK36: 6.6098911 | BL36: 3.3724146 | BM36: =Water!U41 -> #REF! | BN36: =Water!W41 -> #REF! | BO36: =Water!X41 -> #REF! | BP36: =Water!Y41 -> #REF! | BQ36: =Water!Z41 -> #REF!
A37: AVER. Bud | B37: 37143.785 | C37: =Elect!#REF! -> #REF! | D37: 0 | E37: =Elect!#REF! -> #REF! | F37: 0 | G37: =Elect!#REF! -> #REF! | H37: 0 | I37: =Water!C42 -> 0 | J37: 0 | K37: =Water!E43 -> 0 | L37: 7 | M37: =Water!#REF! -> #REF! | N37: =Water!#REF! -> #REF! | O37: 969 | P37: =Water!H42 -> 0 | Q37: 0 | R37: =Water!O42 -> 0 | S37: 23.193548 | T37: =Water!#REF! -> #REF! | U37: 148.67742 | V37: =Water!#REF! -> #REF! | W37: 755.80645 | X37: =Water!Q42 -> 0 | Y37: 7 | Z37: =Water!#REF! -> #REF! | AA37: 0 | AB37: 0 | AC37: 0 | AD37: =Water!#REF! -> #REF! | AE37: =Water!#REF! -> #REF! | AF37: =Water!#REF! -> #REF! | AG37: =Gas!#REF! -> #REF! | AH37: =Gas!#REF! -> #REF! | AI37: =Gas!#REF! -> #REF! | AJ37: =Gas!#REF! -> #REF! | AK37: =Gas!#REF! -> #REF! | AL37: =Gas!#REF! -> #REF! | AM37: =Gas!#REF! -> #REF! | AN37: =Gas!#REF! -> #REF! | ... AS37: =Gas!#REF! -> #REF! | AT37: =Elect!#REF! -> #REF! | AU37: =Elect!#REF! -> #REF! | AX37: 0 | AY37: 0 | AZ37: 9453.8714 | BA37: 0 | BB37: 0 | BC37: =Elect!#REF! -> #REF! | BD37: =Elect!#REF! -> #REF! | BE37: =Elect!#REF! -> #REF! | BF37: =Elect!#REF! -> #REF! | BG37: =Elect!#REF! -> #REF! | BH37: 0 | BI37: 0 | BJ37: 0 | BK37: 0 | BL37: 0 | BM37: =Water!U42 -> 0 | BN37: =Water!W42 -> 0 | BO37: =Water!X42 -> 0 | BP37: =Water!Y42 -> 0 | BQ37: =Water!Z42 -> 0
A38: Total RFC | B38: 784008.53 | C38: =Elect!#REF! -> #REF! | D38: 0 | E38: =Elect!#REF! -> #REF! | F38: 0 | G38: =Elect!#REF! -> #REF! | H38: 0 | I38: =Water!C43 -> 0 | J38: 0 | K38: =Water!E44 -> 0 | L38: 8 | M38: =Water!#REF! -> #REF! | N38: =Water!#REF! -> #REF! | O38: 0 | P38: =Water!H43 -> 0 | Q38: 0 | R38: =Water!O43 -> 0 | S38: 0 | T38: =Water!#REF! -> #REF! | U38: 0 | V38: =Water!#REF! -> #REF! | W38: 0 | X38: =Water!Q43 -> 0 | Y38: 8 | Z38: =Water!#REF! -> #REF! | AA38: 0 | AB38: 0 | AC38: 0 | AD38: =Water!#REF! -> #REF! | AE38: =Water!#REF! -> #REF! | AF38: =Water!#REF! -> #REF! | AG38: =Gas!#REF! -> #REF! | AH38: =Gas!#REF! -> #REF! | AI38: =Gas!#REF! -> #REF! | AJ38: =Gas!#REF! -> #REF! | AK38: =Gas!#REF! -> #REF! | AL38: =Gas!#REF! -> #REF! | AM38: =Gas!#REF! -> #REF! | AN38: =Gas!#REF! -> #REF! | ... AS38: =Gas!#REF! -> #REF! | AT38: =Elect!#REF! -> #REF! | AU38: =Elect!#REF! -> #REF! | AX38: 38.173558 | AY38: 19.219193 | AZ38: 208225.85 | BA38: 10.138565 | BB38: 5.1044505 | BC38: =Elect!#REF! -> #REF! | BD38: =Elect!#REF! -> #REF! | BE38: =Elect!#REF! -> #REF! | BF38: =Elect!#REF! -> #REF! | BG38: =Elect!#REF! -> #REF! | BH38: 0 | BI38: 0 | BJ38: 127385.62 | BK38: 6.2024355 | BL38: 3.1227323 | BM38: =Water!U43 -> 0 | BN38: =Water!W43 -> 0 | BO38: =Water!X43 -> 0 | BP38: =Water!Y43 -> 0 | BQ38: =Water!Z43 -> 0
A39: RFC MTD | B39: 784008.53 | C39: =Elect!#REF! -> #REF! | D39: 0 | E39: =Elect!#REF! -> #REF! | F39: 0 | G39: =Elect!#REF! -> #REF! | H39: 0 | I39: =Water!C44 -> 0 | J39: 0 | K39: =Water!E45 -> 0 | L39: 9 | M39: =Water!#REF! -> #REF! | N39: =Water!#REF! -> #REF! | O39: 0 | P39: =Water!H44 -> 0 | Q39: 0 | R39: =Water!O44 -> 0 | S39: 0 | T39: =Water!#REF! -> #REF! | U39: 0 | V39: =Water!#REF! -> #REF! | W39: 0 | X39: =Water!Q44 -> 0 | Y39: 9 | Z39: =Water!#REF! -> #REF! | AA39: 0 | AB39: 0 | AC39: 0 | AD39: =Water!#REF! -> #REF! | AE39: =Water!#REF! -> #REF! | AF39: =Water!#REF! -> #REF! | AG39: =Gas!#REF! -> #REF! | AH39: =Gas!#REF! -> #REF! | AI39: =Gas!#REF! -> #REF! | AJ39: =Gas!#REF! -> #REF! | AK39: =Gas!#REF! -> #REF! | AL39: =Gas!#REF! -> #REF! | AM39: =Gas!#REF! -> #REF! | AN39: =Gas!#REF! -> #REF! | ... AS39: =Gas!#REF! -> #REF! | AT39: =Elect!#REF! -> #REF! | AU39: =Elect!#REF! -> #REF! | AX39: 38.173558 | AY39: 19.219193 | AZ39: 208225.85 | BA39: 10.138565 | BB39: 5.1044505 | BC39: =Elect!#REF! -> #REF! | BD39: =Elect!#REF! -> #REF! | BE39: =Elect!#REF! -> #REF! | BF39: =Elect!#REF! -> #REF! | BG39: =Elect!#REF! -> #REF! | BH39: 0 | BI39: 0 | BJ39: 115057.98 | BK39: 6.2024355 | BL39: 3.1227323 | BM39: =Water!U44 -> 0 | BN39: =Water!W44 -> 0 | BO39: =Water!X44 -> #VALUE! | BP39: =Water!Y44 -> #VALUE! | BQ39: =Water!Z44 -> #VALUE!
A40: AVER RFC | B40: 28000.305 | C40: =Elect!#REF! -> #REF! | D40: 0 | E40: =Elect!#REF! -> #REF! | F40: 0 | G40: =Elect!#REF! -> #REF! | H40: 0 | I40: =Water!C45 -> 0 | J40: 0 | K40: =Water!E46 -> 0 | L40: 10 | M40: =Water!#REF! -> #REF! | N40: =Water!#REF! -> #REF! | O40: 0 | P40: =Water!H45 -> 0 | Q40: 0 | R40: =Water!O45 -> 0 | S40: 0 | T40: =Water!#REF! -> #REF! | U40: 0 | V40: =Water!#REF! -> #REF! | W40: 0 | X40: =Water!Q45 -> 0 | Y40: 10 | Z40: =Water!#REF! -> #REF! | AA40: 0 | AB40: 0 | AC40: 0 | AD40: =Water!#REF! -> #REF! | AE40: =Water!#REF! -> #REF! | AF40: =Water!#REF! -> #REF! | AG40: =Gas!#REF! -> #REF! | AH40: =Gas!#REF! -> #REF! | AI40: =Gas!#REF! -> #REF! | AJ40: =Gas!#REF! -> #REF! | AK40: =Gas!#REF! -> #REF! | AL40: =Gas!#REF! -> #REF! | AM40: =Gas!#REF! -> #REF! | AN40: =Gas!#REF! -> #REF! | ... AS40: =Gas!#REF! -> #REF! | AT40: =Elect!#REF! -> #REF! | AU40: =Elect!#REF! -> #REF! | AX40: 0 | AY40: 0 | AZ40: 7436.6375 | BA40: 0 | BB40: 0 | BC40: =Elect!#REF! -> #REF! | BD40: =Elect!#REF! -> #REF! | BE40: =Elect!#REF! -> #REF! | BF40: =Elect!#REF! -> #REF! | BG40: =Elect!#REF! -> #REF! | BH40: 1.1254646 | BI40: 0.57264868 | BJ40: 4109.2135 | BK40: 0 | BL40: 0 | BM40: =Water!U45 -> 0 | BN40: =Water!W45 -> 0 | BO40: =Water!X45 -> #VALUE! | BP40: =Water!Y45 -> 0 | BQ40: =Water!Z45 -> 0

Sheet Temp.
A2: HILTON INTERNATIONAL
A3: GULF, MIDDLE EAST AND ASIA SPECIFIC
A4: HOTEL:HILTON HURGHADA LONG BEACH RESORT | G4: =Elect!A1 -> 44774
A7: DATE | B7: MAX TEMP | C7: MIN TEMP | D7: MAX TEMP | E7: MIN TEMP | F7: DAY | G7: DD. C | H7: DD. H | I7: MTD | J7: MTD
B8: C | C8: C | D8: F | E8: F | F8: PARAMETER | I8: COOLING | J8: HEATING
A10: 1 | D10: =SUM((B10*9/5)+32) -> 32 | E10: =SUM((C10*9/5)+32) -> 32 | F10: =SUM(((B10+C10)/2)-18.33) -> -18.33 | G10: =SUM(0+(F10)+ABS(F10))/2 -> 0 | H10: =IF((SUM(0-(F10)+ABS(F10))/2)<18,SUM(0-(F10)+ABS(F10))/2,0) -> 0 | I10: =SUM(G10:G10) -> 0 | J10: =SUM(H10:H10) -> 0
A11: 2 | D11: =SUM((B11*9/5)+32) -> 32 | E11: =SUM((C11*9/5)+32) -> 32 | F11: =SUM(((B11+C11)/2)-18.33) -> -18.33 | G11: =SUM(0+(F11)+ABS(F11))/2 -> 0 | H11: =IF((SUM(0-(F11)+ABS(F11))/2)<18,SUM(0-(F11)+ABS(F11))/2,0) -> 0 | I11: =SUM(G10:G11) -> 0 | J11: =SUM(H10:H11) -> 0
A12: 3 | D12: =SUM((B12*9/5)+32) -> 32 | E12: =SUM((C12*9/5)+32) -> 32 | F12: =SUM(((B12+C12)/2)-18.33) -> -18.33 | G12: =SUM(0+(F12)+ABS(F12))/2 -> 0 | H12: =IF((SUM(0-(F12)+ABS(F12))/2)<18,SUM(0-(F12)+ABS(F12))/2,0) -> 0 | I12: =SUM(G10:G12) -> 0 | J12: =SUM(H10:H12) -> 0
A13: 4 | D13: =SUM((B13*9/5)+32) -> 32 | E13: =SUM((C13*9/5)+32) -> 32 | F13: =SUM(((B13+C13)/2)-18.33) -> -18.33 | G13: =SUM(0+(F13)+ABS(F13))/2 -> 0 | H13: =IF((SUM(0-(F13)+ABS(F13))/2)<18,SUM(0-(F13)+ABS(F13))/2,0) -> 0 | I13: =SUM(G10:G13) -> 0 | J13: =SUM(H10:H13) -> 0
A14: 5 | D14: =SUM((B14*9/5)+32) -> 32 | E14: =SUM((C14*9/5)+32) -> 32 | F14: =SUM(((B14+C14)/2)-18.33) -> -18.33 | G14: =SUM(0+(F14)+ABS(F14))/2 -> 0 | H14: =IF((SUM(0-(F14)+ABS(F14))/2)<18,SUM(0-(F14)+ABS(F14))/2,0) -> 0 | I14: =SUM(G10:G14) -> 0 | J14: =SUM(H10:H14) -> 0
A15: 6 | D15: =SUM((B15*9/5)+32) -> 32 | E15: =SUM((C15*9/5)+32) -> 32 | F15: =SUM(((B15+C15)/2)-18.33) -> -18.33 | G15: =SUM(0+(F15)+ABS(F15))/2 -> 0 | H15: =IF((SUM(0-(F15)+ABS(F15))/2)<18,SUM(0-(F15)+ABS(F15))/2,0) -> 0 | I15: =SUM(G10:G15) -> 0 | J15: =SUM(H10:H15) -> 0
A16: 7 | D16: =SUM((B16*9/5)+32) -> 32 | E16: =SUM((C16*9/5)+32) -> 32 | F16: =SUM(((B16+C16)/2)-18.33) -> -18.33 | G16: =SUM(0+(F16)+ABS(F16))/2 -> 0 | H16: =IF((SUM(0-(F16)+ABS(F16))/2)<18,SUM(0-(F16)+ABS(F16))/2,0) -> 0 | I16: =SUM(G10:G16) -> 0 | J16: =SUM(H10:H16) -> 0
A17: 8 | D17: =SUM((B17*9/5)+32) -> 32 | E17: =SUM((C17*9/5)+32) -> 32 | F17: =SUM(((B17+C17)/2)-18.33) -> -18.33 | G17: =SUM(0+(F17)+ABS(F17))/2 -> 0 | H17: =IF((SUM(0-(F17)+ABS(F17))/2)<18,SUM(0-(F17)+ABS(F17))/2,0) -> 0 | I17: =SUM(G10:G17) -> 0 | J17: =SUM(H10:H17) -> 0
A18: 9 | D18: =SUM((B18*9/5)+32) -> 32 | E18: =SUM((C18*9/5)+32) -> 32 | F18: =SUM(((B18+C18)/2)-18.33) -> -18.33 | G18: =SUM(0+(F18)+ABS(F18))/2 -> 0 | H18: =IF((SUM(0-(F18)+ABS(F18))/2)<18,SUM(0-(F18)+ABS(F18))/2,0) -> 0 | I18: =SUM(G10:G18) -> 0 | J18: =SUM(H10:H18) -> 0
A19: 10 | D19: =SUM((B19*9/5)+32) -> 32 | E19: =SUM((C19*9/5)+32) -> 32 | F19: =SUM(((B19+C19)/2)-18.33) -> -18.33 | G19: =SUM(0+(F19)+ABS(F19))/2 -> 0 | H19: =IF((SUM(0-(F19)+ABS(F19))/2)<18,SUM(0-(F19)+ABS(F19))/2,0) -> 0 | I19: =SUM(G10:G19) -> 0 | J19: =SUM(H10:H19) -> 0
A20: 11 | D20: =SUM((B20*9/5)+32) -> 32 | E20: =SUM((C20*9/5)+32) -> 32 | F20: =SUM(((B20+C20)/2)-18.33) -> -18.33 | G20: =SUM(0+(F20)+ABS(F20))/2 -> 0 | H20: =IF((SUM(0-(F20)+ABS(F20))/2)<18,SUM(0-(F20)+ABS(F20))/2,0) -> 0 | I20: =SUM(G10:G20) -> 0 | J20: =SUM(H10:H20) -> 0
A21: 12 | D21: =SUM((B21*9/5)+32) -> 32 | E21: =SUM((C21*9/5)+32) -> 32 | F21: =SUM(((B21+C21)/2)-18.33) -> -18.33 | G21: =SUM(0+(F21)+ABS(F21))/2 -> 0 | H21: =IF((SUM(0-(F21)+ABS(F21))/2)<18,SUM(0-(F21)+ABS(F21))/2,0) -> 0 | I21: =SUM(G10:G21) -> 0 | J21: =SUM(H10:H21) -> 0
A22: 13 | D22: =SUM((B22*9/5)+32) -> 32 | E22: =SUM((C22*9/5)+32) -> 32 | F22: =SUM(((B22+C22)/2)-18.33) -> -18.33 | G22: =SUM(0+(F22)+ABS(F22))/2 -> 0 | H22: =IF((SUM(0-(F22)+ABS(F22))/2)<18,SUM(0-(F22)+ABS(F22))/2,0) -> 0 | I22: =SUM(G10:G22) -> 0 | J22: =SUM(H10:H22) -> 0
A23: 14 | D23: =SUM((B23*9/5)+32) -> 32 | E23: =SUM((C23*9/5)+32) -> 32 | F23: =SUM(((B23+C23)/2)-18.33) -> -18.33 | G23: =SUM(0+(F23)+ABS(F23))/2 -> 0 | H23: =IF((SUM(0-(F23)+ABS(F23))/2)<18,SUM(0-(F23)+ABS(F23))/2,0) -> 0 | I23: =SUM(G10:G23) -> 0 | J23: =SUM(H10:H23) -> 0
A24: 15 | D24: =SUM((B24*9/5)+32) -> 32 | E24: =SUM((C24*9/5)+32) -> 32 | F24: =SUM(((B24+C24)/2)-18.33) -> -18.33 | G24: =SUM(0+(F24)+ABS(F24))/2 -> 0 | H24: =IF((SUM(0-(F24)+ABS(F24))/2)<18,SUM(0-(F24)+ABS(F24))/2,0) -> 0 | I24: =SUM(G11:G24) -> 0 | J24: =SUM(H11:H24) -> 0
A25: 16 | D25: =SUM((B25*9/5)+32) -> 32 | E25: =SUM((C25*9/5)+32) -> 32 | F25: =SUM(((B25+C25)/2)-18.33) -> -18.33 | G25: =SUM(0+(F25)+ABS(F25))/2 -> 0 | H25: =IF((SUM(0-(F25)+ABS(F25))/2)<18,SUM(0-(F25)+ABS(F25))/2,0) -> 0 | I25: =SUM(G12:G25) -> 0 | J25: =SUM(H12:H25) -> 0
A26: 17 | D26: =SUM((B26*9/5)+32) -> 32 | E26: =SUM((C26*9/5)+32) -> 32 | F26: =SUM(((B26+C26)/2)-18.33) -> -18.33 | G26: =SUM(0+(F26)+ABS(F26))/2 -> 0 | H26: =IF((SUM(0-(F26)+ABS(F26))/2)<18,SUM(0-(F26)+ABS(F26))/2,0) -> 0 | I26: =SUM(G13:G26) -> 0 | J26: =SUM(H13:H26) -> 0
A27: 18 | D27: =SUM((B27*9/5)+32) -> 32 | E27: =SUM((C27*9/5)+32) -> 32 | F27: =SUM(((B27+C27)/2)-18.33) -> -18.33 | G27: =SUM(0+(F27)+ABS(F27))/2 -> 0 | H27: =IF((SUM(0-(F27)+ABS(F27))/2)<18,SUM(0-(F27)+ABS(F27))/2,0) -> 0 | I27: =SUM(G14:G27) -> 0 | J27: =SUM(H14:H27) -> 0
A28: 19 | D28: =SUM((B28*9/5)+32) -> 32 | E28: =SUM((C28*9/5)+32) -> 32 | F28: =SUM(((B28+C28)/2)-18.33) -> -18.33 | G28: =SUM(0+(F28)+ABS(F28))/2 -> 0 | H28: =IF((SUM(0-(F28)+ABS(F28))/2)<18,SUM(0-(F28)+ABS(F28))/2,0) -> 0 | I28: =SUM(G15:G28) -> 0 | J28: =SUM(H15:H28) -> 0
A29: 20 | D29: =SUM((B29*9/5)+32) -> 32 | E29: =SUM((C29*9/5)+32) -> 32 | F29: =SUM(((B29+C29)/2)-18.33) -> -18.33 | G29: =SUM(0+(F29)+ABS(F29))/2 -> 0 | H29: =IF((SUM(0-(F29)+ABS(F29))/2)<18,SUM(0-(F29)+ABS(F29))/2,0) -> 0 | I29: =SUM(G16:G29) -> 0 | J29: =SUM(H16:H29) -> 0
A30: 21 | D30: =SUM((B30*9/5)+32) -> 32 | E30: =SUM((C30*9/5)+32) -> 32 | F30: =SUM(((B30+C30)/2)-18.33) -> -18.33 | G30: =SUM(0+(F30)+ABS(F30))/2 -> 0 | H30: =IF((SUM(0-(F30)+ABS(F30))/2)<18,SUM(0-(F30)+ABS(F30))/2,0) -> 0 | I30: =SUM(G17:G30) -> 0 | J30: =SUM(H17:H30) -> 0
A31: 22 | D31: =SUM((B31*9/5)+32) -> 32 | E31: =SUM((C31*9/5)+32) -> 32 | F31: =SUM(((B31+C31)/2)-18.33) -> -18.33 | G31: =SUM(0+(F31)+ABS(F31))/2 -> 0 | H31: =IF((SUM(0-(F31)+ABS(F31))/2)<18,SUM(0-(F31)+ABS(F31))/2,0) -> 0 | I31: =SUM(G18:G31) -> 0 | J31: =SUM(H18:H31) -> 0
A32: 23 | D32: =SUM((B32*9/5)+32) -> 32 | E32: =SUM((C32*9/5)+32) -> 32 | F32: =SUM(((B32+C32)/2)-18.33) -> -18.33 | G32: =SUM(0+(F32)+ABS(F32))/2 -> 0 | H32: =IF((SUM(0-(F32)+ABS(F32))/2)<18,SUM(0-(F32)+ABS(F32))/2,0) -> 0 | I32: =SUM(G19:G32) -> 0 | J32: =SUM(H19:H32) -> 0
A33: 24 | D33: =SUM((B33*9/5)+32) -> 32 | E33: =SUM((C33*9/5)+32) -> 32 | F33: =SUM(((B33+C33)/2)-18.33) -> -18.33 | G33: =SUM(0+(F33)+ABS(F33))/2 -> 0 | H33: =IF((SUM(0-(F33)+ABS(F33))/2)<18,SUM(0-(F33)+ABS(F33))/2,0) -> 0 | I33: =SUM(G20:G33) -> 0 | J33: =SUM(H20:H33) -> 0
A34: 25 | D34: =SUM((B34*9/5)+32) -> 32 | E34: =SUM((C34*9/5)+32) -> 32 | F34: =SUM(((B34+C34)/2)-18.33) -> -18.33 | G34: =SUM(0+(F34)+ABS(F34))/2 -> 0 | H34: =IF((SUM(0-(F34)+ABS(F34))/2)<18,SUM(0-(F34)+ABS(F34))/2,0) -> 0 | I34: =SUM(G21:G34) -> 0 | J34: =SUM(H21:H34) -> 0
... A40: 31 | D40: =SUM((B40*9/5)+32) -> 32 | E40: =SUM((C40*9/5)+32) -> 32 | F40: =SUM(((B40+C40)/2)-18.33) -> -18.33 | G40: =SUM(0+(F40)+ABS(F40))/2 -> 0 | H40: =IF((SUM(0-(F40)+ABS(F40))/2)<18,SUM(0-(F40)+ABS(F40))/2,0) -> 0 | I40: =SUM(G27:G40) -> 0 | J40: =SUM(H27:H40) -> 0
E42: =SUM(G10:G40) -> 0 | F42: deg c
E44: =SUM(H10:H40) -> 0 | F44: deg c

Sheet M-Rep
B3: =Elect!A1 -> 44774
D4: Y.T.D
A5: Energy breakdown | C5: 2009 | D5: 2005 | E5: 2006
A6: Elect.
A7: Chillers KWH | C7: N/A | D7: N/A | E7: N/A
A8: Laundry KWH | C8: N/A | D8: N/A | E8: N/A
A9: Kitchen KWH | C9: N/A | D9: N/A | E9: N/A
A10: Gas
A11: Kit M3 | C11: =Gas!#REF!/1000 -> #REF!
A12: Laundry M3 | C12: N/A | D12: 0 | E12: #REF!
A13: Water | D13: N/A | E13: N/A
A14: Laundry HW | C14: N/A
A15: Laundry CW | C15: N/A
A16: Kit HW | C16: N/A
A17: kIt CW | C17: N/A | D17: N/A | E17: N/A
A18: Dmstc HW | C18: N/A | D18: N/A | E18: N/A
A19: Dmstc CW | C19: N/A | D19: N/A | E19: N/A
A20: S.Pool MKUP | C20: =#REF! -> #REF! | D20: N/A | E20: N/A
A21: Ctower MKUP | C21: N/A | D21: N/A | E21: N/A
A22: Gardens Irrigat. | C22: =Water!S38 -> 0 | D22: N/A | E22: N/A
A23: Swage water treatment | C23: =Water!#REF! -> #REF! | D23: 27437 | E23: #REF!
A24: Utilities consumption | D24: N/A | E24: N/A
A25: Elect. Kwh | C25: =Elect!J34 -> 4435 | D25: 12266 | E25: 814
A26: M.D (9.5 LE) | D26: 147773 | E26: #REF!
A27: Water M3 | C27: =Water!H38 -> 12413.74
A28: Fuel Ltr | C28: =Gas!#REF!*1000 -> #REF! | D28: 12876868 | E28: 14500800
A29: Gas M3/ Boilers, chillers,..etc | C29: N/A | D29: 28880 | E29: 32980
A30: Gas M3 Kitchen | C30: =Gas!#REF!/1000 -> #REF! | D30: 244283 | E30: 252530.66
A31: Total Energy | D31: 620770 | E31: #REF!
A32: Control Parameters | D32: #REF! | E32: N/A
A33: No. of Rooms % occ. | C33: =YTD!Q4 -> 0 | D33: 39.395 | E33: #REF!
A34: No. of Occ. Rooms | C34: =YTD!Q5 -> 0
A35: guest count | C35: =YTD!Q6 -> 0
A36: Food covers | D36: #REF! | E36: #REF!
A37: Laundry W. Kg | D37: 0.8807 | E37: 0.46351998
A38: DDC | C38: =Temp.!E42 -> 0 | D38: 196150 | E38: 237021
A39: DDH | C39: =Temp.!E44 -> 0 | D39: 400070 | E39: 466105
A40: Utilities Entergy cost | D40: 1583714 | E40: 1940567
A41: Elect. | C41: =Elect!#REF! -> #REF! | D41: 1690339 | E41: 3118671.6
A42: M.D | C42: =C26*Elect!#REF! -> #REF! | D42: 2381.51 | E42: 2480.24
A43: Water | C43: =Water!X38 -> 48245.947 | D43: 112 | E43: 97.53
A44: Fuel | C44: =Gas!#REF! -> #REF!
A45: Gas Boilers, chillers,etc.. | C45: N/A | D45: 2138156.8 | E45: #REF!
A46: Gas Kitchen | C46: =C30*Gas!M2*1000 -> #REF! | D46: 223044.2 | E46: #REF!
A47: TOTAL LE | C47: =SUM(C41:C46) -> #REF! | D47: 1330535.7 | E47: 1382037.4
A48: No. of POMEC Staff | D48: 330278 | E48: #REF!
A49: Hotel Age | C49: 6 | D49: N/A | E49: N/A
A50: No. of rooms | C50: =31*912 -> 28272 | D50: 36597.525 | E50: #REF!
A51: Building Volume | C51: 243175 | D51: =SUM(D45:D50) -> 4058612.3 | E51: =SUM(E45:E50) -> #REF!
A52: Building area | C52: 75064
A53: US$ Rate | C53: 5.59402 | D53: 61 | E53: 72
A54: Total R&M MTD | C54: =YTD!Q65 -> 0 | D54: #REF! | E54: 243175 | F54: =YTD!Q64 -> 0
A55: Staff - HLP | D55: #REF! | E55: 75064
A56: Staff - R&M | D56: 5.755 | E56: 5.65951
A57: Staff - Grounds

Sheet YTD
A1: =Elect!A1 -> 44774 | H1: Actual 2014
C3: JAN | D3: FEB | E3: MAR | F3: APR | G3: MAY | H3: JUN | I3: JUL | J3: AUG | K3: SEP | L3: OCT | M3: NOV | N3: DEC | O3: TOTAL | P3: YTD | Q3: Month Act
A4: Occ Room % | O4: =SUM(C4:N4) -> 0 | P4: =(IF($A$1=39814,C4,(IF($A$1=39845,SUM(C4:D4),(IF($A$1=39873,SUM(C4:E4),(IF($A$1=39904,SUM(C4:F4),(IF($A$1=39934,SUM(C4:G4),(IF($A$1=39965,SUM(C4:H4),(IF($A$1=39995,SUM(C4:I4),0)))))))))))))+(IF($A$1=40026,SUM(C4:J4),(IF($A$1=40057,SUM(C4:K4),(IF($A$1=40087,SUM(C4:L4),(IF($A$1=40118,SUM(C4:M4))))))))))+(IF($A$1=40148,SUM(C4:N4),0)) -> 0 | Q4: =(IF($A$1=39814,C4,(IF($A$1=39845,D4,(IF($A$1=39873,E4,(IF($A$1=39904,F4,(IF($A$1=39934,G4,(IF($A$1=39965,H4,(IF($A$1=39995,I4,0)))))))))))))+(IF($A$1=40026,J4,(IF($A$1=40057,K4,(IF($A$1=40087,L4,(IF($A$1=40118,M4)))))))))+(IF($A$1=40148,N4,0)) -> 0 | S4: 40179 | DE4: 1
A5: Occ Room | C5: 25072 | D5: =Elect!BP34 -> 87 | O5: =SUM(C5:N5) -> 25159 | P5: =(IF($A$1=40179,C5,(IF($A$1=40210,SUM(C5:D5),(IF($A$1=40238,SUM(C5:E5),(IF($A$1=40269,SUM(C5:F5),(IF($A$1=40299,SUM(C5:G5),(IF($A$1=40330,SUM(C5:H5),(IF($A$1=40360,SUM(C5:I5),0)))))))))))))+(IF($A$1=40391,SUM(C5:J5),(IF($A$1=40422,SUM(C5:K5),(IF($A$1=40452,SUM(C5:L5),(IF($A$1=40483,SUM(C5:M5))))))))))+(IF($A$1=40513,SUM(C5:N5),0)) -> 0 | Q5: =(IF($A$1=40179,C5,(IF($A$1=40210,D5,(IF($A$1=40238,E5,(IF($A$1=40269,F5,(IF($A$1=40299,G5,(IF($A$1=40330,H5,(IF($A$1=40360,I5,0)))))))))))))+(IF($A$1=40391,J5,(IF($A$1=40422,K5,(IF($A$1=40452,L5,(IF($A$1=40483,M5)))))))))+(IF($A$1=40513,N5,0)) -> 0 | S5: 40210 | DE5: 2
A6: Number of Guest | C6: 50662 | D6: =Elect!BR34 -> 144 | O6: =SUM(C6:N6) -> 50806 | P6: =(IF($A$1=40179,C6,(IF($A$1=40210,SUM(C6:D6),(IF($A$1=40238,SUM(C6:E6),(IF($A$1=40269,SUM(C6:F6),(IF($A$1=40299,SUM(C6:G6),(IF($A$1=40330,SUM(C6:H6),(IF($A$1=40360,SUM(C6:I6),0)))))))))))))+(IF($A$1=40391,SUM(C6:J6),(IF($A$1=40422,SUM(C6:K6),(IF($A$1=40452,SUM(C6:L6),(IF($A$1=40483,SUM(C6:M6))))))))))+(IF($A$1=40513,SUM(C6:N6),0)) -> 0 | Q6: =(IF($A$1=40179,C6,(IF($A$1=40210,D6,(IF($A$1=40238,E6,(IF($A$1=40269,F6,(IF($A$1=40299,G6,(IF($A$1=40330,H6,(IF($A$1=40360,I6,0)))))))))))))+(IF($A$1=40391,J6,(IF($A$1=40422,K6,(IF($A$1=40452,L6,(IF($A$1=40483,M6)))))))))+(IF($A$1=40513,N6,0)) -> 0 | S6: 40238 | DE6: 3
A7: PAY & REL. EXP. | O7: =SUM(C7:N7) -> 0 | P7: =(IF($A$1=40179,C7,(IF($A$1=40210,SUM(C7:D7),(IF($A$1=40238,SUM(C7:E7),(IF($A$1=40269,SUM(C7:F7),(IF($A$1=40299,SUM(C7:G7),(IF($A$1=40330,SUM(C7:H7),(IF($A$1=40360,SUM(C7:I7),0)))))))))))))+(IF($A$1=40391,SUM(C7:J7),(IF($A$1=40422,SUM(C7:K7),(IF($A$1=40452,SUM(C7:L7),(IF($A$1=40483,SUM(C7:M7))))))))))+(IF($A$1=40513,SUM(C7:N7),0)) -> 0 | Q7: =(IF($A$1=40179,C7,(IF($A$1=40210,D7,(IF($A$1=40238,E7,(IF($A$1=40269,F7,(IF($A$1=40299,G7,(IF($A$1=40330,H7,(IF($A$1=40360,I7,0)))))))))))))+(IF($A$1=40391,J7,(IF($A$1=40422,K7,(IF($A$1=40452,L7,(IF($A$1=40483,M7)))))))))+(IF($A$1=40513,N7,0)) -> 0
