Workbook

Sheet Total
A1: Site Name | B1: Day | C1: Month | D1: Year | E1: Total Electricity Kwh | F1: Electricity Tariff ($/Kwh) | G1: Natual Gas (m3) | H1: Natural Gas $/m3 | I1: Water Utility Supply (m3) m3 | J1: Water Utility Supply (m3) $/m3 | K1: Room Nights
A2: Cairo at The First Residence | B2: 1 | C2: 8 | D2: 2022 | E2: =Elect!BS6+Submetering!AH2 -> 26128.563 | F2: ='Utility Consnsumption'!K13/'Utility Consnsumption'!J13 -> 1.3909353 | G2: =Gas!K7+Submetering!AR2 -> 4034.4844 | H2: 3.8 | I2: =Water!H7+Submetering!AM2 -> 433.405 | J2: 10 | K2: =Elect!BT6 -> 238
A3: Cairo at The First Residence | B3: =B2+1 -> 2 | C3: 8 | D3: 2022 | E3: =Elect!BS7+Submetering!AH3 -> 23425.48 | F3: =F2 -> 1.3909353 | G3: =Gas!K8+Submetering!AR3 -> 1966.56 | H3: 3.8 | I3: =Water!H8+Submetering!AM3 -> 258.1 | J3: 10 | K3: =Elect!BT7 -> 227
A4: Cairo at The First Residence | B4: =B3+1 -> 3 | C4: 8 | D4: 2022 | E4: =Elect!BS8+Submetering!AH4 -> 25080.585 | F4: =F3 -> 1.3909353 | G4: =Gas!K9+Submetering!AR4 -> 2100.1 | H4: 3.8 | I4: =Water!H9+Submetering!AM4 -> 342.78 | J4: 10 | K4: =Elect!BT8 -> 213
A5: Cairo at The First Residence | B5: =B4+1 -> 4 | C5: 8 | D5: 2022 | E5: =Elect!BS9+Submetering!AH5 -> 23163.165 | F5: =F4 -> 1.3909353 | G5: =Gas!K10+Submetering!AR5 -> 2271.86 | H5: 3.8 | I5: =Water!H10+Submetering!AM5 -> 311.46 | J5: 10 | K5: =Elect!BT9 -> 202
A6: Cairo at The First Residence | B6: =B5+1 -> 5 | C6: 8 | D6: 2022 | E6: =Elect!BS10+Submetering!AH6 -> 24521.783 | F6: =F5 -> 1.3909353 | G6: =Gas!K11+Submetering!AR6 -> 1973.64 | H6: 3.8 | I6: =Water!H11+Submetering!AM6 -> 352.06 | J6: 10 | K6: =Elect!BT10 -> 196
A7: Cairo at The First Residence | B7: =B6+1 -> 6 | C7: 8 | D7: 2022 | E7: =Elect!BS11+Submetering!AH7 -> 25763.33 | F7: =F6 -> 1.3909353 | G7: =Gas!K12+Submetering!AR7 -> 2108.8 | H7: 3.8 | I7: =Water!H12+Submetering!AM7 -> 359.6 | J7: 10 | K7: =Elect!BT11 -> 214
A8: Cairo at The First Residence | B8: =B7+1 -> 7 | C8: 8 | D8: 2022 | E8: =Elect!BS12+Submetering!AH8 -> 26164.928 | F8: =F7 -> 1.3909353 | G8: =Gas!K13+Submetering!AR8 -> 2077.64 | H8: 3.8 | I8: =Water!H13+Submetering!AM8 -> 418.18 | J8: 10 | K8: =Elect!BT12 -> 254
A9: Cairo at The First Residence | B9: =B8+1 -> 8 | C9: 8 | D9: 2022 | E9: =Elect!BS13+Submetering!AH9 -> 22257.475 | F9: =F8 -> 1.3909353 | G9: =Gas!K14+Submetering!AR9 -> 2136.04 | H9: 3.8 | I9: =Water!H14+Submetering!AM9 -> 425.72 | J9: 10 | K9: =Elect!BT13 -> 239
A10: Cairo at The First Residence | B10: =B9+1 -> 9 | C10: 8 | D10: 2022 | E10: =Elect!BS14+Submetering!AH10 -> 25597.536 | F10: =F9 -> 1.3909353 | G10: =Gas!K15+Submetering!AR10 -> 2128.36 | H10: 3.8 | I10: =Water!H15+Submetering!AM10 -> 441.38 | J10: 10 | K10: =Elect!BT14 -> 220
A11: Cairo at The First Residence | B11: =B10+1 -> 10 | C11: 8 | D11: 2022 | E11: =Elect!BS15+Submetering!AH11 -> 18687.874 | F11: =F10 -> 1.3909353 | G11: =Gas!K16+Submetering!AR11 -> 2151.04 | H11: 3.8 | I11: =Water!H16+Submetering!AM11 -> 412.96 | J11: 10 | K11: =Elect!BT15 -> 185
A12: Cairo at The First Residence | B12: =B11+1 -> 11 | C12: 8 | D12: 2022 | E12: =Elect!BS16+Submetering!AH12 -> 25872.397 | F12: =F11 -> 1.3909353 | G12: =Gas!K17+Submetering!AR12 -> 2132.2 | H12: 3.8 | I12: =Water!H17+Submetering!AM12 -> 432.274 | J12: 10 | K12: =Elect!BT16 -> 156
A13: Cairo at The First Residence | B13: =B12+1 -> 12 | C13: 8 | D13: 2022 | E13: =Elect!BS17+Submetering!AH13 -> 24551.895 | F13: =F12 -> 1.3909353 | G13: =Gas!K18+Submetering!AR13 -> 2137.468 | H13: 3.8 | I13: =Water!H18+Submetering!AM13 -> 427.518 | J13: 10 | K13: =Elect!BT17 -> 199
A14: Cairo at The First Residence | B14: =B13+1 -> 13 | C14: 8 | D14: 2022 | E14: =Elect!BS18+Submetering!AH14 -> 24650.18 | F14: =F13 -> 1.3909353 | G14: =Gas!K19+Submetering!AR14 -> 1881.892 | H14: 3.8 | I14: =Water!H19+Submetering!AM14 -> 310.068 | J14: 10 | K14: =Elect!BT18 -> 212
... A32: Cairo at The First Residence | B32: =B31+1 -> 31 | C32: 8 | D32: 2022 | E32: =Elect!BS36+Submetering!AH32 -> 24520.76 | F32: =F31 -> 1.3909353 | G32: =Gas!K37+Submetering!AR32 -> 2378.32 | H32: 3.8 | I32: =Water!H37+Submetering!AM32 -> 370.62 | J32: 10 | K32: =Elect!BT36 -> 250

Sheet Submetering
A1: Site Name | B1: Day | C1: Month | D1: Year | E1: Electricity | F1: Main Feeder -KWh | G1: T2+T8 -KWh | H1: La Gourmandize -KWh | I1: Casino 3rd floor EM -KWh | J1: Casino 3rd floor Normal -KWh | K1: Chiller 1 -KWh | L1: Chiller 2 -KWh | M1: Chiller 3 -KWh | N1: Chiller 4 -KWh | O1: Chiller 5 -KWh | P1: Chiller 6 -KWh | Q1: Cooling towers -KWh | R1: Chiller Pumps -KWh | S1: Cooling Tower Pumps -KWh | T1: Fiber Chiller -KWh | U1: Mall Ceiling light -KWh | V1: LG Bakery -KWh | W1: LG Bakery light ( Old lockers ) -KWh | X1: MCCR1 -KWh | Y1: Children Swimming Pool -KWh | Z1: DPH1 -KWh | AA1: Guest Rooms Emerg. -KWh | AB1: Hotel Hoods -KWh | AC1: Main G2 -KWh | AD1: Old Casino Emergency -KWh | AE1: L / A -KWh | AF1: L / B -KWh | AG1: L / C -KWh | AH1: Boat -KWh | AI1: Water | AJ1: Main water meter 1 -m3 | AK1: Main water meter 2 -m3 | AL1: Main water meter 3 -m3 | AM1: Boat -m3 | AN1: Gas | AO1: Main Gas Flow Meter -m3 | AP1: Laundry Gas Flow Meter -m3 | AQ1: Gourmandize Gas Flow Meter -m3 | AR1: Boat -m3 | AS1: Room Nights
A2: Cairo at The First Residence | B2: 1 | C2: 8 | D2: 2022 | F2: =Elect!J6 -> 6443.9444 | G2: =Elect!K6 -> 3741.8333 | H2: =Elect!Q6 -> 425 | I2: =Elect!S6 -> 140.66667 | J2: =Elect!U6 -> 299.83333 | K2: =Elect!W6 -> 1756.8617 | L2: =Elect!Y6 -> 0 | M2: =Elect!AA6 -> 0 | N2: =Elect!AC6 -> 0 | O2: =Elect!AE6 -> 13.161667 | P2: =Elect!AG6 -> 12.543333 | Q2: =Elect!AI6 -> 312.78833 | R2: =Elect!AK6 -> 4158.0267 | S2: =Elect!AM6 -> 118.985 | T2: =Elect!AP6 -> 112.44375 | U2: =Elect!AR6 -> 162.33333 | V2: =Elect!AT6 -> 93.166667 | W2: =Elect!AV6 -> 40.833333 | X2: =Elect!AX6 -> 843.16667 | Y2: =Elect!AZ6 -> 10.666667 | Z2: =Elect!BB6 -> 5238.1667 | AA2: =Elect!BD6 -> 233.16667 | AB2: =Elect!BF6 -> 44 | AC2: =Elect!BH6 -> 6109.3083 | AD2: =Elect!BL6 -> 225.16667 | AE2: =Elect!BN6 -> 961.16667 | AF2: =Elect!BP6 -> 170 | AG2: =Elect!BR6 -> 149.33333 | AH2: =Boat!C4 -> 0 | AJ2: =Water!C7 -> 162.88333 | AK2: =Water!E7 -> 146.74 | AL2: =Water!G7 -> 123.78167 | AM2: =Boat!E4 -> 0 | AO2: =Gas!C7 -> 3529.1817 | AP2: =Gas!E7 -> 505.30278 | AQ2: =Gas!G7 -> 122.26852 | AR2: =Boat!G4 -> 0 | AS2: =Elect!BT6 -> 238
A3: Cairo at The First Residence | B3: =B2+1 -> 2 | C3: 8 | D3: 2022 | F3: =Elect!J7 -> 6181 | G3: =Elect!K7 -> 3985 | H3: =Elect!Q7 -> 480 | I3: =Elect!S7 -> 138 | J3: =Elect!U7 -> 235 | K3: =Elect!W7 -> 2088.2 | L3: =Elect!Y7 -> 0 | M3: =Elect!AA7 -> 0 | N3: =Elect!AC7 -> 0 | O3: =Elect!AE7 -> 15.37 | P3: =Elect!AG7 -> 14.31 | Q3: =Elect!AI7 -> 271.89 | R3: =Elect!AK7 -> 2304.97 | S3: =Elect!AM7 -> 112.89 | T3: =Elect!AP7 -> 38.25 | U3: =Elect!AR7 -> 194 | V3: =Elect!AT7 -> 96 | W3: =Elect!AV7 -> 43 | X3: =Elect!AX7 -> 955 | Y3: =Elect!AZ7 -> 10 | Z3: =Elect!BB7 -> 5054 | AA3: =Elect!BD7 -> 221 | AB3: =Elect!BF7 -> 45 | AC3: =Elect!BH7 -> 5300.6 | AD3: =Elect!BL7 -> 163 | AE3: =Elect!BN7 -> 1119 | AF3: =Elect!BP7 -> 133 | AG3: =Elect!BR7 -> 151 | AH3: =Boat!C5 -> 0 | AJ3: =Water!C8 -> 69.6 | AK3: =Water!E8 -> 87 | AL3: =Water!G8 -> 101.5 | AM3: =Boat!E5 -> 0 | AO3: =Gas!C8 -> 1622.86 | AP3: =Gas!E8 -> 343.7 | AQ3: =Gas!G8 -> 75 | AR3: =Boat!G5 -> 0 | AS3: =Elect!BT7 -> 227
A4: Cairo at The First Residence | B4: =B3+1 -> 3 | C4: 8 | D4: 2022 | F4: =Elect!J8 -> 6253 | G4: =Elect!K8 -> 4301 | H4: =Elect!Q8 -> 540 | I4: =Elect!S8 -> 151 | J4: =Elect!U8 -> 263 | K4: =Elect!W8 -> 2313.45 | L4: =Elect!Y8 -> 0 | M4: =Elect!AA8 -> 0 | N4: =Elect!AC8 -> 0 | O4: =Elect!AE8 -> 14.31 | P4: =Elect!AG8 -> 13.25 | Q4: =Elect!AI8 -> 294.68 | R4: =Elect!AK8 -> 2532.87 | S4: =Elect!AM8 -> 121.9 | T4: =Elect!AP8 -> 28.575 | U4: =Elect!AR8 -> 189 | V4: =Elect!AT8 -> 92 | W4: =Elect!AV8 -> 47 | X4: =Elect!AX8 -> 1007 | Y4: =Elect!AZ8 -> 11 | Z4: =Elect!BB8 -> 5129 | AA4: =Elect!BD8 -> 248 | AB4: =Elect!BF8 -> 50 | AC4: =Elect!BH8 -> 6195.55 | AD4: =Elect!BL8 -> 324 | AE4: =Elect!BN8 -> 1295 | AF4: =Elect!BP8 -> 146 | AG4: =Elect!BR8 -> 156 | AH4: =Boat!C6 -> 0 | AJ4: =Water!C9 -> 104.4 | AK4: =Water!E9 -> 127.6 | AL4: =Water!G9 -> 110.78 | AM4: =Boat!E6 -> 0 | AO4: =Gas!C9 -> 1717.2 | AP4: =Gas!E9 -> 382.9 | AQ4: =Gas!G9 -> 95 | AR4: =Boat!G6 -> 0 | AS4: =Elect!BT8 -> 213
A5: Cairo at The First Residence | B5: =B4+1 -> 4 | C5: 8 | D5: 2022 | F5: =Elect!J9 -> 5829 | G5: =Elect!K9 -> 4389 | H5: =Elect!Q9 -> 540 | I5: =Elect!S9 -> 138 | J5: =Elect!U9 -> 239 | K5: =Elect!W9 -> 2363.8 | L5: =Elect!Y9 -> 0 | M5: =Elect!AA9 -> 0 | N5: =Elect!AC9 -> 0 | O5: =Elect!AE9 -> 12.19 | P5: =Elect!AG9 -> 11.66 | Q5: =Elect!AI9 -> 295.21 | R5: =Elect!AK9 -> 2612.37 | S5: =Elect!AM9 -> 125.61 | T5: =Elect!AP9 -> 10.125 | U5: =Elect!AR9 -> 203 | V5: =Elect!AT9 -> 71 | W5: =Elect!AV9 -> 48 | X5: =Elect!AX9 -> 1035 | Y5: =Elect!AZ9 -> 10 | Z5: =Elect!BB9 -> 5079 | AA5: =Elect!BD9 -> 195 | AB5: =Elect!BF9 -> 50 | AC5: =Elect!BH9 -> 4672.2 | AD5: =Elect!BL9 -> 259 | AE5: =Elect!BN9 -> 912 | AF5: =Elect!BP9 -> 112 | AG5: =Elect!BR9 -> 107 | AH5: =Boat!C7 -> 0 | AJ5: =Water!C10 -> 92.8 | AK5: =Water!E10 -> 110.2 | AL5: =Water!G10 -> 108.46 | AM5: =Boat!E7 -> 0 | AO5: =Gas!C10 -> 1893.16 | AP5: =Gas!E10 -> 378.7 | AQ5: =Gas!G10 -> 104 | AR5: =Boat!G7 -> 0 | AS5: =Elect!BT9 -> 202
A6: Cairo at The First Residence | B6: =B5+1 -> 5 | C6: 8 | D6: 2022 | F6: =Elect!J10 -> 6773 | G6: =Elect!K10 -> 4615 | H6: =Elect!Q10 -> 570 | I6: =Elect!S10 -> 162 | J6: =Elect!U10 -> 285 | K6: =Elect!W10 -> 1512.62 | L6: =Elect!Y10 -> 1348.32 | M6: =Elect!AA10 -> 0 | N6: =Elect!AC10 -> 0 | O6: =Elect!AE10 -> 12.72 | P6: =Elect!AG10 -> 12.19 | Q6: =Elect!AI10 -> 191.33 | R6: =Elect!AK10 -> 2223.35 | S6: =Elect!AM10 -> 123.49 | T6: =Elect!AP10 -> 110.8125 | U6: =Elect!AR10 -> 201 | V6: =Elect!AT10 -> 96 | W6: =Elect!AV10 -> 47 | X6: =Elect!AX10 -> 991 | Y6: =Elect!AZ10 -> 12 | Z6: =Elect!BB10 -> 4830 | AA6: =Elect!BD10 -> 244 | AB6: =Elect!BF10 -> 76 | AC6: =Elect!BH10 -> 5146.95 | AD6: =Elect!BL10 -> 92 | AE6: =Elect!BN10 -> 1079 | AF6: =Elect!BP10 -> 130 | AG6: =Elect!BR10 -> 151 | AH6: =Boat!C8 -> 0 | AJ6: =Water!C11 -> 110.2 | AK6: =Water!E11 -> 121.8 | AL6: =Water!G11 -> 120.06 | AM6: =Boat!E8 -> 0 | AO6: =Gas!C11 -> 1557.14 | AP6: =Gas!E11 -> 416.5 | AQ6: =Gas!G11 -> 91 | AR6: =Boat!G8 -> 0 | AS6: =Elect!BT10 -> 196
A7: Cairo at The First Residence | B7: =B6+1 -> 6 | C7: 8 | D7: 2022 | F7: =Elect!J11 -> 6934 | G7: =Elect!K11 -> 3800 | H7: =Elect!Q11 -> 570 | I7: =Elect!S11 -> 135 | J7: =Elect!U11 -> 240 | K7: =Elect!W11 -> 2537.64 | L7: =Elect!Y11 -> 0 | M7: =Elect!AA11 -> 0 | N7: =Elect!AC11 -> 0 | O7: =Elect!AE11 -> 15.9 | P7: =Elect!AG11 -> 14.84 | Q7: =Elect!AI11 -> 151.58 | R7: =Elect!AK11 -> 1817.37 | S7: =Elect!AM11 -> 98.05 | T7: =Elect!AP11 -> 124.65 | U7: =Elect!AR11 -> 174 | V7: =Elect!AT11 -> 137 | W7: =Elect!AV11 -> 35 | X7: =Elect!AX11 -> 784 | Y7: =Elect!AZ11 -> 10 | Z7: =Elect!BB11 -> 5746 | AA7: =Elect!BD11 -> 287 | AB7: =Elect!BF11 -> 83 | AC7: =Elect!BH11 -> 6243.3 | AD7: =Elect!BL11 -> 94 | AE7: =Elect!BN11 -> 1234 | AF7: =Elect!BP11 -> 152 | AG7: =Elect!BR11 -> 144 | AH7: =Boat!C9 -> 0 | AJ7: =Water!C12 -> 116 | AK7: =Water!E12 -> 139.2 | AL7: =Water!G12 -> 104.4 | AM7: =Boat!E9 -> 0 | AO7: =Gas!C12 -> 1749 | AP7: =Gas!E12 -> 359.8 | AQ7: =Gas!G12 -> 83 | AR7: =Boat!G9 -> 0 | AS7: =Elect!BT11 -> 214
A8: Cairo at The First Residence | B8: =B7+1 -> 7 | C8: 8 | D8: 2022 | F8: =Elect!J12 -> 7377 | G8: =Elect!K12 -> 3947 | H8: =Elect!Q12 -> 600 | I8: =Elect!S12 -> 135 | J8: =Elect!U12 -> 241 | K8: =Elect!W12 -> 2671.73 | L8: =Elect!Y12 -> 0 | M8: =Elect!AA12 -> 0 | N8: =Elect!AC12 -> 0 | O8: =Elect!AE12 -> 12.19 | P8: =Elect!AG12 -> 11.66 | Q8: =Elect!AI12 -> 179.67 | R8: =Elect!AK12 -> 2124.77 | S8: =Elect!AM12 -> 110.77 | T8: =Elect!AP12 -> 142.9875 | U8: =Elect!AR12 -> 192 | V8: =Elect!AT12 -> 131 | W8: =Elect!AV12 -> 41 | X8: =Elect!AX12 -> 884 | Y8: =Elect!AZ12 -> 10 | Z8: =Elect!BB12 -> 5560 | AA8: =Elect!BD12 -> 265 | AB8: =Elect!BF12 -> 17 | AC8: =Elect!BH12 -> 5834.15 | AD8: =Elect!BL12 -> 312 | AE8: =Elect!BN12 -> 1134 | AF8: =Elect!BP12 -> 139 | AG8: =Elect!BR12 -> 135 | AH8: =Boat!C10 -> 0 | AJ8: =Water!C13 -> 139.2 | AK8: =Water!E13 -> 168.2 | AL8: =Water!G13 -> 110.78 | AM8: =Boat!E10 -> 0 | AO8: =Gas!C13 -> 1673.74 | AP8: =Gas!E13 -> 403.9 | AQ8: =Gas!G13 -> 106 | AR8: =Boat!G10 -> 0 | AS8: =Elect!BT12 -> 254
A9: Cairo at The First Residence | B9: =B8+1 -> 8 | C9: 8 | D9: 2022 | F9: =Elect!J13 -> 5450 | G9: =Elect!K13 -> 4238 | H9: =Elect!Q13 -> 540 | I9: =Elect!S13 -> 151 | J9: =Elect!U13 -> 271 | K9: =Elect!W13 -> 2089.79 | L9: =Elect!Y13 -> 0 | M9: =Elect!AA13 -> 0 | N9: =Elect!AC13 -> 0 | O9: =Elect!AE13 -> 13.25 | P9: =Elect!AG13 -> 12.19 | Q9: =Elect!AI13 -> 137.8 | R9: =Elect!AK13 -> 2194.73 | S9: =Elect!AM13 -> 104.94 | T9: =Elect!AP13 -> 107.325 | U9: =Elect!AR13 -> 176 | V9: =Elect!AT13 -> 90 | W9: =Elect!AV13 -> 42 | X9: =Elect!AX13 -> 925 | Y9: =Elect!AZ13 -> 11 | Z9: =Elect!BB13 -> 4768 | AA9: =Elect!BD13 -> 184 | AB9: =Elect!BF13 -> 45 | AC9: =Elect!BH13 -> 5366.45 | AD9: =Elect!BL13 -> 223 | AE9: =Elect!BN13 -> 825 | AF9: =Elect!BP13 -> 94 | AG9: =Elect!BR13 -> 93 | AH9: =Boat!C11 -> 0 | AJ9: =Water!C14 -> 139.2 | AK9: =Water!E14 -> 174 | AL9: =Water!G14 -> 112.52 | AM9: =Boat!E11 -> 0 | AO9: =Gas!C14 -> 1742.64 | AP9: =Gas!E14 -> 393.4 | AQ9: =Gas!G14 -> 90 | AR9: =Boat!G11 -> 0 | AS9: =Elect!BT13 -> 239
A10: Cairo at The First Residence | B10: =B9+1 -> 9 | C10: 8 | D10: 2022 | F10: =Elect!J14 -> 6568 | G10: =Elect!K14 -> 6056 | H10: =Elect!Q14 -> 570 | I10: =Elect!S14 -> 139 | J10: =Elect!U14 -> 237 | K10: =Elect!W14 -> 2563.08 | L10: =Elect!Y14 -> 0 | M10: =Elect!AA14 -> 0 | N10: =Elect!AC14 -> 0 | O10: =Elect!AE14 -> 13.25 | P10: =Elect!AG14 -> 12.19 | Q10: =Elect!AI14 -> 168.54 | R10: =Elect!AK14 -> 2952.63 | S10: =Elect!AM14 -> 156.35 | T10: =Elect!AP14 -> 105.4125 | U10: =Elect!AR14 -> 183 | V10: =Elect!AT14 -> 117.33333 | W10: =Elect!AV14 -> 57 | X10: =Elect!AX14 -> 1159 | Y10: =Elect!AZ14 -> 10 | Z10: =Elect!BB14 -> 4891 | AA10: =Elect!BD14 -> 453 | AB10: =Elect!BF14 -> 45 | AC10: =Elect!BH14 -> 5572.75 | AD10: =Elect!BL14 -> 319 | AE10: =Elect!BN14 -> 1061 | AF10: =Elect!BP14 -> 124 | AG10: =Elect!BR14 -> 130 | AH10: =Boat!C12 -> 0 | AJ10: =Water!C15 -> 150.8 | AK10: =Water!E15 -> 179.8 | AL10: =Water!G15 -> 110.78 | AM10: =Boat!E12 -> 0 | AO10: =Gas!C15 -> 1744.76 | AP10: =Gas!E15 -> 383.6 | AQ10: =Gas!G15 -> 111 | AR10: =Boat!G12 -> 0 | AS10: =Elect!BT14 -> 220
A11: Cairo at The First Residence | B11: =B10+1 -> 10 | C11: 8 | D11: 2022 | F11: =Elect!J15 -> 4747 | G11: =Elect!K15 -> 4471 | H11: =Elect!Q15 -> 480 | I11: =Elect!S15 -> 140 | J11: =Elect!U15 -> 247 | K11: =Elect!W15 -> 1929.2 | L11: =Elect!Y15 -> 118.19 | M11: =Elect!AA15 -> 0 | N11: =Elect!AC15 -> 0 | O11: =Elect!AE15 -> 12.19 | P11: =Elect!AG15 -> 12.19 | Q11: =Elect!AI15 -> 152.11 | R11: =Elect!AK15 -> 1997.04 | S11: =Elect!AM15 -> 108.65 | T11: =Elect!AP15 -> 117.7875 | U11: =Elect!AR15 -> 194 | V11: =Elect!AT15 -> 103.66667 | W11: =Elect!AV15 -> 42 | X11: =Elect!AX15 -> 846 | Y11: =Elect!AZ15 -> 11 | Z11: =Elect!BB15 -> 3551 | AA11: =Elect!BD15 -> 301 | AB11: =Elect!BF15 -> 37 | AC11: =Elect!BH15 -> 3927.85 | AD11: =Elect!BL15 -> 272 | AE11: =Elect!BN15 -> 865 | AF11: =Elect!BP15 -> 102 | AG11: =Elect!BR15 -> 131 | AH11: =Boat!C13 -> 0 | AJ11: =Water!C16 -> 139.2 | AK11: =Water!E16 -> 168.2 | AL11: =Water!G16 -> 105.56 | AM11: =Boat!E13 -> 0 | AO11: =Gas!C16 -> 1774.44 | AP11: =Gas!E16 -> 376.6 | AQ11: =Gas!G16 -> 99 | AR11: =Boat!G13 -> 0 | AS11: =Elect!BT15 -> 185
A12: Cairo at The First Residence | B12: =B11+1 -> 11 | C12: 8 | D12: 2022 | F12: =Elect!J16 -> 8905 | G12: =Elect!K16 -> 4104 | H12: =Elect!Q16 -> 540 | I12: =Elect!S16 -> 149 | J12: =Elect!U16 -> 253 | K12: =Elect!W16 -> 1837.51 | L12: =Elect!Y16 -> 0 | M12: =Elect!AA16 -> 0 | N12: =Elect!AC16 -> 0 | O12: =Elect!AE16 -> 13.78 | P12: =Elect!AG16 -> 12.72 | Q12: =Elect!AI16 -> 128.26 | R12: =Elect!AK16 -> 1888.92 | S12: =Elect!AM16 -> 97.52 | T12: =Elect!AP16 -> 81.3375 | U12: =Elect!AR16 -> 199 | V12: =Elect!AT16 -> 107 | W12: =Elect!AV16 -> 39 | X12: =Elect!AX16 -> 707 | Y12: =Elect!AZ16 -> 11 | Z12: =Elect!BB16 -> 5376 | AA12: =Elect!BD16 -> 36 | AB12: =Elect!BF16 -> 50 | AC12: =Elect!BH16 -> 5842.35 | AD12: =Elect!BL16 -> 322 | AE12: =Elect!BN16 -> 997 | AF12: =Elect!BP16 -> 120 | AG12: =Elect!BR16 -> 127 | AH12: =Boat!C14 -> 0 | AJ12: =Water!C17 -> 145 | AK12: =Water!E17 -> 174.58 | AL12: =Water!G17 -> 112.694 | AM12: =Boat!E14 -> 0 | AO12: =Gas!C17 -> 1743.7 | AP12: =Gas!E17 -> 388.5 | AQ12: =Gas!G17 -> 100.5 | AR12: =Boat!G14 -> 0 | AS12: =Elect!BT16 -> 156
A13: Cairo at The First Residence | B13: =B12+1 -> 12 | C13: 8 | D13: 2022 | F13: =Elect!J17 -> 5252 | G13: =Elect!K17 -> 5328 | H13: =Elect!Q17 -> 570 | I13: =Elect!S17 -> 143 | J13: =Elect!U17 -> 247 | K13: =Elect!W17 -> 2327.23 | L13: =Elect!Y17 -> 0 | M13: =Elect!AA17 -> 0 | N13: =Elect!AC17 -> 0 | O13: =Elect!AE17 -> 13.25 | P13: =Elect!AG17 -> 12.19 | Q13: =Elect!AI17 -> 160.59 | R13: =Elect!AK17 -> 2522.27 | S13: =Elect!AM17 -> 126.14 | T13: =Elect!AP17 -> 116.775 | U13: =Elect!AR17 -> 195 | V13: =Elect!AT17 -> 98 | W13: =Elect!AV17 -> 49 | X13: =Elect!AX17 -> 903 | Y13: =Elect!AZ17 -> 10 | Z13: =Elect!BB17 -> 5642 | AA13: =Elect!BD17 -> 129 | AB13: =Elect!BF17 -> 50 | AC13: =Elect!BH17 -> 6375.45 | AD13: =Elect!BL17 -> 363 | AE13: =Elect!BN17 -> 1101 | AF13: =Elect!BP17 -> 138 | AG13: =Elect!BR17 -> 146 | AH13: =Boat!C15 -> 0 | AJ13: =Water!C18 -> 143.84 | AK13: =Water!E18 -> 173.42 | AL13: =Water!G18 -> 110.258 | AM13: =Boat!E15 -> 0 | AO13: =Gas!C18 -> 1753.028 | AP13: =Gas!E18 -> 384.44 | AQ13: =Gas!G18 -> 101.1 | AR13: =Boat!G15 -> 0 | AS13: =Elect!BT17 -> 199
A14: Cairo at The First Residence | B14: =B13+1 -> 13 | C14: 8 | D14: 2022 | F14: =Elect!J18 -> 8745 | G14: =Elect!K18 -> 4493 | H14: =Elect!Q18 -> 570 | I14: =Elect!S18 -> 148 | J14: =Elect!U18 -> 260 | K14: =Elect!W18 -> 1963.65 | L14: =Elect!Y18 -> 0 | M14: =Elect!AA18 -> 0 | N14: =Elect!AC18 -> 0 | O14: =Elect!AE18 -> 13.25 | P14: =Elect!AG18 -> 12.19 | Q14: =Elect!AI18 -> 130.91 | R14: =Elect!AK18 -> 2097.74 | S14: =Elect!AM18 -> 104.94 | T14: =Elect!AP18 -> 99.9 | U14: =Elect!AR18 -> 180 | V14: =Elect!AT18 -> 63 | W14: =Elect!AV18 -> 38 | X14: =Elect!AX18 -> 740 | Y14: =Elect!AZ18 -> 11 | Z14: =Elect!BB18 -> 5114 | AA14: =Elect!BD18 -> 161 | AB14: =Elect!BF18 -> 50 | AC14: =Elect!BH18 -> 4555.6 | AD14: =Elect!BL18 -> 256 | AE14: =Elect!BN18 -> 769 | AF14: =Elect!BP18 -> 103 | AG14: =Elect!BR18 -> 104 | AH14: =Boat!C16 -> 0 | AJ14: =Water!C19 -> 111.36 | AK14: =Water!E19 -> 133.4 | AL14: =Water!G19 -> 65.308 | AM14: =Boat!E16 -> 0 | AO14: =Gas!C19 -> 1507.532 | AP14: =Gas!E19 -> 374.36 | AQ14: =Gas!G19 -> 80.4 | AR14: =Boat!G16 -> 0 | AS14: =Elect!BT18 -> 212
... A32: Cairo at The First Residence | B32: =B31+1 -> 31 | C32: 8 | D32: 2022 | F32: =Elect!J36 -> 6371.6667 | G32: =Elect!K36 -> 4328.6667 | H32: =Elect!Q36 -> 480 | I32: =Elect!S36 -> 143.33333 | J32: =Elect!U36 -> 253.66667 | K32: =Elect!W36 -> 2865.18 | L32: =Elect!Y36 -> 0 | M32: =Elect!AA36 -> 0 | N32: =Elect!AC36 -> 0 | O32: =Elect!AE36 -> 0 | P32: =Elect!AG36 -> 12.19 | Q32: =Elect!AI36 -> 264.29333 | R32: =Elect!AK36 -> 2274.4067 | S32: =Elect!AM36 -> 114.65667 | T32: =Elect!AP36 -> 163.8 | U32: =Elect!AR36 -> 200.66667 | V32: =Elect!AT36 -> 137.33333 | W32: =Elect!AV36 -> 42.333333 | X32: =Elect!AX36 -> 864.66667 | Y32: =Elect!AZ36 -> 57 | Z32: =Elect!BB36 -> 4906.6667 | AA32: =Elect!BD36 -> 231 | AB32: =Elect!BF36 -> 47 | AC32: =Elect!BH36 -> 5487.9 | AD32: =Elect!BL36 -> 204.66667 | AE32: =Elect!BN36 -> 996.33333 | AF32: =Elect!BP36 -> 21.666667 | AG32: =Elect!BR36 -> 156 | AH32: =Boat!C34 -> 0 | AJ32: =Water!C37 -> 110.2 | AK32: =Water!E37 -> 133.4 | AL32: =Water!G37 -> 127.02 | AM32: =Boat!E34 -> 0 | AO32: =Gas!C37 -> 1862.42 | AP32: =Gas!E37 -> 515.9 | AQ32: =Gas!G37 -> 130 | AR32: =Boat!G34 -> 0 | AS32: =Elect!BT36 -> 250

Sheet Boat
B1: Electricity | D1: Water | F1: Gas
B2: Read | C2: Cons | D2: Read | E2: Cons | F2: Read | G2: Cons
B3: 0 | D3: 0 | F3: 0
A4: 1 | B4: 0 | C4: =B4-B3 -> 0 | D4: 0 | E4: =D4-D3 -> 0 | F4: 0 | G4: =F4-F3 -> 0
A5: 2 | B5: 0 | C5: =B5-B4 -> 0 | D5: 0 | E5: =D5-D4 -> 0 | F5: 0 | G5: =F5-F4 -> 0
A6: 3 | B6: 0 | C6: =B6-B5 -> 0 | D6: 0 | E6: =D6-D5 -> 0 | F6: 0 | G6: =F6-F5 -> 0
A7: 4 | B7: 0 | C7: =B7-B6 -> 0 | D7: 0 | E7: =D7-D6 -> 0 | F7: 0 | G7: =F7-F6 -> 0
A8: 5 | B8: 0 | C8: =B8-B7 -> 0 | D8: 0 | E8: =D8-D7 -> 0 | F8: 0 | G8: =F8-F7 -> 0
A9: 6 | B9: 0 | C9: =B9-B8 -> 0 | D9: 0 | E9: =D9-D8 -> 0 | F9: 0 | G9: =F9-F8 -> 0
A10: 7 | B10: 0 | C10: =B10-B9 -> 0 | D10: 0 | E10: =D10-D9 -> 0 | F10: 0 | G10: =F10-F9 -> 0
A11: 8 | B11: 0 | C11: =B11-B10 -> 0 | D11: 0 | E11: =D11-D10 -> 0 | F11: 0 | G11: =F11-F10 -> 0
A12: 9 | B12: 0 | C12: =B12-B11 -> 0 | D12: 0 | E12: =D12-D11 -> 0 | F12: 0 | G12: =F12-F11 -> 0
A13: 10 | B13: 0 | C13: =B13-B12 -> 0 | D13: 0 | E13: =D13-D12 -> 0 | F13: 0 | G13: =F13-F12 -> 0
A14: 11 | B14: 0 | C14: =B14-B13 -> 0 | D14: 0 | E14: =D14-D13 -> 0 | F14: 0 | G14: =F14-F13 -> 0
A15: 12 | B15: 0 | C15: =B15-B14 -> 0 | D15: 0 | E15: =D15-D14 -> 0 | F15: 0 | G15: =F15-F14 -> 0
... A34: 31 | B34: 0 | C34: =B34-B33 -> 0 | D34: 0 | E34: =D34-D33 -> 0 | F34: 0 | G34: =F34-F33 -> 0
A35: Sum | C35: =SUM(C4:C34) -> 0 | E35: =SUM(E4:E34) -> 0 | G35: =SUM(G4:G34) -> 0

Sheet Water
A1: =Elect!A1 -> 44927 | T1: Main Water UP | V1: 4 | W1: Water Truck UP
A3: Day | E3: Water Incoming | I3: New casino | N3: Rooms Consumption | P3: Public Areas consumption | R3: Swimming pool | T3: No. of rooms | U3: Cons. Per occ. room | V3: No. of guest | W3: Cons. Per guest | X3: Total cost | Y3: L.E\ | Z3: L.E\
B4: Main water meter 1 | D4: Main water meter 2 | F4: Main water meter 3 | H4: Total Inc. | I4: Hot water | K4: Cold water | N4: Express Riser | O4: Consp. | P4: Read. | Q4: Cons. | R4: Read. | S4: Cons. | Y4: Room | Z4: Guest
B5: Counter | C5: Produc 58% | D5: Counter | E5: Produc 58% | F5: Counter | G5: Produc 58% | I5: Counter | K5: Counter
B6: 90625.917 | C6: =IF(B6>=B5,B6-B5,0)*10*0.58 -> 0 | D6: 14017.7 | E6: =IF(D6>=D5,D6-D5,0)*10*0.58 -> 0 | F6: 68296.583 | G6: =IF(F6>=F5,F6-F5,0)*0.58 -> 0 | I6: 322 | K6: 5583
A7: 1 | B7: 90654 | C7: =IF(B7>=B6,B7-B6,0)*10*0.58 -> 162.88333 | D7: 14043 | E7: =IF(D7>=D6,D7-D6,0)*10*0.58 -> 146.74 | F7: 68510 | G7: =IF(F7>=F6,F7-F6,0)*0.58 -> 123.78167 | H7: =C7+E7+G7 -> 433.405 | O7: =IF(N7>=N6,N7-N6,0) -> 0 | Q7: =(H7-O7)*0.58 -> 251.3749 | S7: =IF(R7-R6>0,R7-R6,0) -> 0 | T7: =Elect!BT6 -> 238 | U7: =H7/T7 -> 1.8210294 | V7: =Elect!BV6 -> 0 | W7: =H7/V7 -> #DIV/0! | X7: =H7*V1 -> 1733.62 | Y7: =IF(X7>0,X7/T7,0) -> 7.2841176 | Z7: 0
A8: 2 | B8: 90666 | C8: =IF(B8>=B7,B8-B7,0)*10*0.58 -> 69.6 | D8: 14058 | E8: =IF(D8>=D7,D8-D7,0)*10*0.58 -> 87 | F8: 68685 | G8: =IF(F8>=F7,F8-F7,0)*0.58 -> 101.5 | H8: =C8+E8+G8 -> 258.1 | O8: =IF(N8>=N7,N8-N7,0) -> 0 | Q8: =(H8-O8)*0.58 -> 149.698 | S8: =IF(R8-R7>0,R8-R7,0) -> 0 | T8: =Elect!BT7 -> 227 | U8: =H8/T8 -> 1.1370044 | V8: =Elect!BV7 -> 0 | W8: =H8/V8 -> #DIV/0! | X8: =H8*V1 -> 1032.4 | Y8: =IF(X8>0,X8/T8,0) -> 4.5480176 | Z8: =IF(X8>0,X8/V8,0) -> #DIV/0!
A9: 3 | B9: 90684 | C9: =IF(B9>=B8,B9-B8,0)*10*0.58 -> 104.4 | D9: 14080 | E9: =IF(D9>=D8,D9-D8,0)*10*0.58 -> 127.6 | F9: 68876 | G9: =IF(F9>=F8,F9-F8,0)*0.58 -> 110.78 | H9: =C9+E9+G9 -> 342.78 | O9: =IF(N9>=N8,N9-N8,0) -> 0 | Q9: =(H9-O9)*0.58 -> 198.8124 | S9: =IF(R9-R8>0,R9-R8,0) -> 0 | T9: =Elect!BT8 -> 213 | U9: =H9/T9 -> 1.6092958 | V9: =Elect!BV8 -> 0 | W9: =H9/V9 -> #DIV/0! | X9: =H9*V1 -> 1371.12 | Y9: =IF(X9>0,X9/T9,0) -> 6.4371831 | Z9: =IF(X9>0,X9/V9,0) -> #DIV/0!
A10: 4 | B10: 90700 | C10: =IF(B10>=B9,B10-B9,0)*10*0.58 -> 92.8 | D10: 14099 | E10: =IF(D10>=D9,D10-D9,0)*10*0.58 -> 110.2 | F10: 69063 | G10: =IF(F10>=F9,F10-F9,0)*0.58 -> 108.46 | H10: =C10+E10+G10 -> 311.46 | O10: =IF(N10>=N9,N10-N9,0) -> 0 | Q10: =(H10-O10)*0.58 -> 180.6468 | S10: =IF(R10-R9>0,R10-R9,0) -> 0 | T10: =Elect!BT9 -> 202 | U10: =H10/T10 -> 1.5418812 | V10: =Elect!BV9 -> 0 | W10: =H10/V10 -> #DIV/0! | X10: =H10*V1 -> 1245.84 | Y10: =IF(X10>0,X10/T10,0) -> 6.1675248 | Z10: =IF(X10>0,X10/V10,0) -> #DIV/0!
A11: 5 | B11: 90719 | C11: =IF(B11>=B10,B11-B10,0)*10*0.58 -> 110.2 | D11: 14120 | E11: =IF(D11>=D10,D11-D10,0)*10*0.58 -> 121.8 | F11: 69270 | G11: =IF(F11>=F10,F11-F10,0)*0.58 -> 120.06 | H11: =C11+E11+G11 -> 352.06 | O11: =IF(N11>=N10,N11-N10,0) -> 0 | Q11: =(H11-O11)*0.58 -> 204.1948 | S11: =IF(R11-R10>0,R11-R10,0) -> 0 | T11: =Elect!BT10 -> 196 | U11: =H11/T11 -> 1.7962245 | V11: =Elect!BV10 -> 0 | W11: =H11/V11 -> #DIV/0! | X11: =H11*V1 -> 1408.24 | Y11: =IF(X11>0,X11/T11,0) -> 7.184898 | Z11: =IF(X11>0,X11/V11,0) -> #DIV/0!
A12: 6 | B12: 90739 | C12: =IF(B12>=B11,B12-B11,0)*10*0.58 -> 116 | D12: 14144 | E12: =IF(D12>=D11,D12-D11,0)*10*0.58 -> 139.2 | F12: 69450 | G12: =IF(F12>=F11,F12-F11,0)*0.58 -> 104.4 | H12: =C12+E12+G12 -> 359.6 | O12: =IF(N12>=N11,N12-N11,0) -> 0 | Q12: =(H12-O12)*0.58 -> 208.568 | S12: =IF(R12-R11>0,R12-R11,0) -> 0 | T12: =Elect!BT11 -> 214 | U12: =H12/T12 -> 1.6803738 | V12: =Elect!BV11 -> 0 | W12: =H12/V12 -> #DIV/0! | X12: =H12*V1 -> 1438.4 | Y12: =IF(X12>0,X12/T12,0) -> 6.7214953 | Z12: =IF(X12>0,X12/V12,0) -> #DIV/0!
A13: 7 | B13: 90763 | C13: =IF(B13>=B12,B13-B12,0)*10*0.58 -> 139.2 | D13: 14173 | E13: =IF(D13>=D12,D13-D12,0)*10*0.58 -> 168.2 | F13: 69641 | G13: =IF(F13>=F12,F13-F12,0)*0.58 -> 110.78 | H13: =C13+E13+G13 -> 418.18 | O13: =IF(N13>=N12,N13-N12,0) -> 0 | Q13: =(H13-O13)*0.58 -> 242.5444 | S13: =IF(R13-R12>0,R13-R12,0) -> 0 | T13: =Elect!BT12 -> 254 | U13: =H13/T13 -> 1.646378 | V13: =Elect!BV12 -> 0 | W13: =H13/V13 -> #DIV/0! | X13: =H13*V1 -> 1672.72 | Y13: =IF(X13>0,X13/T13,0) -> 6.5855118 | Z13: =IF(X13>0,X13/V13,0) -> #DIV/0!
A14: 8 | B14: 90787 | C14: =IF(B14>=B13,B14-B13,0)*10*0.58 -> 139.2 | D14: 14203 | E14: =IF(D14>=D13,D14-D13,0)*10*0.58 -> 174 | F14: 69835 | G14: =IF(F14>=F13,F14-F13,0)*0.58 -> 112.52 | H14: =C14+E14+G14 -> 425.72 | O14: =IF(N14>=N13,N14-N13,0) -> 0 | Q14: =(H14-O14)*0.58 -> 246.9176 | S14: =IF(R14-R13>0,R14-R13,0) -> 0 | T14: =Elect!BT13 -> 239 | U14: =H14/T14 -> 1.7812552 | V14: =Elect!BV13 -> 0 | W14: =H14/V14 -> #DIV/0! | X14: =H14*V1 -> 1702.88 | Y14: =IF(X14>0,X14/T14,0) -> 7.1250209 | Z14: =IF(X14>0,X14/V14,0) -> #DIV/0!
A15: 9 | B15: 90813 | C15: =IF(B15>=B14,B15-B14,0)*10*0.58 -> 150.8 | D15: 14234 | E15: =IF(D15>=D14,D15-D14,0)*10*0.58 -> 179.8 | F15: 70026 | G15: =IF(F15>=F14,F15-F14,0)*0.58 -> 110.78 | H15: =C15+E15+G15 -> 441.38 | O15: =IF(N15>=N14,N15-N14,0) -> 0 | Q15: =(H15-O15)*0.58 -> 256.0004 | S15: =IF(R15-R14>0,R15-R14,0) -> 0 | T15: =Elect!BT14 -> 220 | U15: =H15/T15 -> 2.0062727 | V15: =Elect!BV14 -> 0 | W15: =H15/V15 -> #DIV/0! | X15: =H15*V1 -> 1765.52 | Y15: =IF(X15>0,X15/T15,0) -> 8.0250909 | Z15: =IF(X15>0,X15/V15,0) -> #DIV/0!
A16: 10 | B16: 90837 | C16: =IF(B16>=B15,B16-B15,0)*10*0.58 -> 139.2 | D16: 14263 | E16: =IF(D16>=D15,D16-D15,0)*10*0.58 -> 168.2 | F16: 70208 | G16: =IF(F16>=F15,F16-F15,0)*0.58 -> 105.56 | H16: =C16+E16+G16 -> 412.96 | O16: =IF(N16>=N15,N16-N15,0) -> 0 | Q16: =(H16-O16)*0.58 -> 239.5168 | S16: =IF(R16-R15>0,R16-R15,0) -> 0 | T16: =Elect!BT15 -> 185 | U16: =H16/T16 -> 2.2322162 | V16: =Elect!BV15 -> 0 | W16: =H16/V16 -> #DIV/0! | X16: =H16*V1 -> 1651.84 | Y16: =IF(X16>0,X16/T16,0) -> 8.9288649 | Z16: =IF(X16>0,X16/V16,0) -> #DIV/0!
A17: 11 | B17: 90862 | C17: =IF(B17>=B16,B17-B16,0)*10*0.58 -> 145 | D17: 14293.1 | E17: =IF(D17>=D16,D17-D16,0)*10*0.58 -> 174.58 | F17: 70402.3 | G17: =IF(F17>=F16,F17-F16,0)*0.58 -> 112.694 | H17: =C17+E17+G17 -> 432.274 | O17: =IF(N17>=N16,N17-N16,0) -> 0 | Q17: =(H17-O17)*0.58 -> 250.71892 | S17: =IF(R17-R16>0,R17-R16,0) -> 0 | T17: =Elect!BT16 -> 156 | U17: =H17/T17 -> 2.7709872 | V17: =Elect!BV16 -> 0 | W17: =H17/V17 -> #DIV/0! | X17: =H17*V1 -> 1729.096 | Y17: =IF(X17>0,X17/T17,0) -> 11.083949 | Z17: =IF(X17>0,X17/V17,0) -> #DIV/0!
A18: 12 | B18: 90886.8 | C18: =IF(B18>=B17,B18-B17,0)*10*0.58 -> 143.84 | D18: 14323 | E18: =IF(D18>=D17,D18-D17,0)*10*0.58 -> 173.42 | F18: 70592.4 | G18: =IF(F18>=F17,F18-F17,0)*0.58 -> 110.258 | H18: =C18+E18+G18 -> 427.518 | O18: =IF(N18>=N17,N18-N17,0) -> 0 | Q18: =(H18-O18)*0.58 -> 247.96044 | S18: =IF(R18-R17>0,R18-R17,0) -> 0 | T18: =Elect!BT17 -> 199 | U18: =H18/T18 -> 2.1483317 | V18: =Elect!BV17 -> 0 | W18: =H18/V18 -> #DIV/0! | X18: =H18*V1 -> 1710.072 | Y18: =IF(X18>0,X18/T18,0) -> 8.5933266 | Z18: =IF(X18>0,X18/V18,0) -> #DIV/0!
A19: 13 | B19: 90906 | C19: =IF(B19>=B18,B19-B18,0)*10*0.58 -> 111.36 | D19: 14346 | E19: =IF(D19>=D18,D19-D18,0)*10*0.58 -> 133.4 | F19: 70705 | G19: =IF(F19>=F18,F19-F18,0)*0.58 -> 65.308 | H19: =C19+E19+G19 -> 310.068 | O19: =IF(N19>=N18,N19-N18,0) -> 0 | Q19: =(H19-O19)*0.58 -> 179.83944 | S19: =IF(R19-R18>0,R19-R18,0) -> 0 | T19: =Elect!BT18 -> 212 | U19: =H19/T19 -> 1.4625849 | V19: =Elect!BV18 -> 0 | W19: =H19/V19 -> #DIV/0! | X19: =H19*V1 -> 1240.272 | Y19: =IF(X19>0,X19/T19,0) -> 5.8503396 | Z19: =IF(X19>0,X19/V19,0) -> #DIV/0!
A20: 14 | B20: 90929 | C20: =IF(B20>=B19,B20-B19,0)*10*0.58 -> 133.4 | D20: 14374 | E20: =IF(D20>=D19,D20-D19,0)*10*0.58 -> 162.4 | F20: 70950 | G20: =IF(F20>=F19,F20-F19,0)*0.58 -> 142.1 | H20: =C20+E20+G20 -> 437.9 | O20: =IF(N20>=N19,N20-N19,0) -> 0 | Q20: =(H20-O20)*0.58 -> 253.982 | S20: =IF(R20-R19>0,R20-R19,0) -> 0 | T20: =Elect!BT19 -> 238 | U20: =H20/T20 -> 1.839916 | V20: =Elect!BV19 -> 0 | W20: =H20/V20 -> #DIV/0! | X20: =H20*V1 -> 1751.6 | Y20: =IF(X20>0,X20/T20,0) -> 7.3596639 | Z20: =IF(X20>0,X20/V20,0) -> #DIV/0!
A21: 15 | B21: 90951 | C21: =IF(B21>=B20,B21-B20,0)*10*0.58 -> 127.6 | D21: 14399 | E21: =IF(D21>=D20,D21-D20,0)*10*0.58 -> 145 | F21: 71150 | G21: =IF(F21>=F20,F21-F20,0)*0.58 -> 116 | H21: =C21+E21+G21 -> 388.6 | O21: =IF(N21>=N20,N21-N20,0) -> 0 | Q21: =(H21-O21)*0.58 -> 225.388 | S21: =IF(R21-R20>0,R21-R20,0) -> 0 | T21: =Elect!BT20 -> 229 | U21: =H21/T21 -> 1.6969432 | V21: =Elect!BV20 -> 0 | W21: =H21/V21 -> #DIV/0! | X21: =H21*V1 -> 1554.4 | Y21: =IF(X21>0,X21/T21,0) -> 6.7877729 | Z21: =IF(X21>0,X21/V21,0) -> #DIV/0!
A22: 16 | B22: 90966 | C22: =IF(B22>=B21,B22-B21,0)*10*0.58 -> 87 | D22: 14417 | E22: =IF(D22>=D21,D22-D21,0)*10*0.58 -> 104.4 | F22: 71347 | G22: =IF(F22>=F21,F22-F21,0)*0.58 -> 114.26 | H22: =C22+E22+G22 -> 305.66 | O22: =IF(N22>=N21,N22-N21,0) -> 0 | Q22: =(H22-O22)*0.58 -> 177.2828 | S22: =IF(R22-R21>0,R22-R21,0) -> 0 | T22: =Elect!BT21 -> 213 | U22: =H22/T22 -> 1.4350235 | V22: =Elect!BV21 -> 0 | W22: =H22/V22 -> #DIV/0! | X22: =H22*V1 -> 1222.64 | Y22: =IF(X22>0,X22/T22,0) -> 5.7400939 | Z22: =IF(X22>0,X22/V22,0) -> #DIV/0!
A23: 17 | B23: 90983 | C23: =IF(B23>=B22,B23-B22,0)*10*0.58 -> 98.6 | D23: 14436 | E23: =IF(D23>=D22,D23-D22,0)*10*0.58 -> 110.2 | F23: 71548 | G23: =IF(F23>=F22,F23-F22,0)*0.58 -> 116.58 | H23: =C23+E23+G23 -> 325.38 | O23: =IF(N23>=N22,N23-N22,0) -> 0 | Q23: =(H23-O23)*0.58 -> 188.7204 | S23: =IF(R23-R22>0,R23-R22,0) -> 0 | T23: =Elect!BT22 -> 198 | U23: =H23/T23 -> 1.6433333 | V23: =Elect!BV22 -> 0 | W23: =H23/V23 -> #DIV/0! | X23: =H23*V1 -> 1301.52 | Y23: =IF(X23>0,X23/T23,0) -> 6.5733333 | Z23: =IF(X23>0,X23/V23,0) -> #DIV/0!
A24: 18 | B24: 91002 | C24: =IF(B24>=B23,B24-B23,0)*10*0.58 -> 110.2 | D24: 14457 | E24: =IF(D24>=D23,D24-D23,0)*10*0.58 -> 121.8 | F24: 71780 | G24: =IF(F24>=F23,F24-F23,0)*0.58 -> 134.56 | H24: =C24+E24+G24 -> 366.56 | O24: =IF(N24>=N23,N24-N23,0) -> 0 | Q24: =(H24-O24)*0.58 -> 212.6048 | S24: =IF(R24-R23>0,R24-R23,0) -> 0 | T24: =Elect!BT23 -> 170 | U24: =H24/T24 -> 2.1562353 | V24: =Elect!BV23 -> 0 | W24: =H24/V24 -> #DIV/0! | X24: =H24*V1 -> 1466.24 | Y24: =IF(X24>0,X24/T24,0) -> 8.6249412 | Z24: =IF(X24>0,X24/V24,0) -> #DIV/0!
A25: 19 | B25: 91016 | C25: =IF(B25>=B24,B25-B24,0)*10*0.58 -> 81.2 | D25: 14473 | E25: =IF(D25>=D24,D25-D24,0)*10*0.58 -> 92.8 | F25: 71957 | G25: =IF(F25>=F24,F25-F24,0)*0.58 -> 102.66 | H25: =C25+E25+G25 -> 276.66 | O25: =IF(N25>=N24,N25-N24,0) -> 0 | Q25: =(H25-O25)*0.58 -> 160.4628 | S25: =IF(R25-R24>0,R25-R24,0) -> 0 | T25: =Elect!BT24 -> 206 | U25: =H25/T25 -> 1.3430097 | V25: =Elect!BV24 -> 0 | W25: =H25/V25 -> #DIV/0! | X25: =H25*V1 -> 1106.64 | Y25: =IF(X25>0,X25/T25,0) -> 5.3720388 | Z25: =IF(X25>0,X25/V25,0) -> #DIV/0!
A26: 20 | B26: 91032 | C26: =IF(B26>=B25,B26-B25,0)*10*0.58 -> 92.8 | D26: 14491 | E26: =IF(D26>=D25,D26-D25,0)*10*0.58 -> 104.4 | F26: 72155 | G26: =IF(F26>=F25,F26-F25,0)*0.58 -> 114.84 | H26: =C26+E26+G26 -> 312.04 | O26: =IF(N26>=N25,N26-N25,0) -> 0 | Q26: =(H26-O26)*0.58 -> 180.9832 | S26: =IF(R26-R25>0,R26-R25,0) -> 0 | T26: =Elect!BT25 -> 228 | U26: =H26/T26 -> 1.3685965 | V26: =Elect!BV25 -> 0 | W26: =H26/V26 -> #DIV/0! | X26: =H26*V1 -> 1248.16 | Y26: =IF(X26>0,X26/T26,0) -> 5.474386 | Z26: =IF(X26>0,X26/V26,0) -> #DIV/0!
A27: 21 | B27: 91050 | C27: =IF(B27>=B26,B27-B26,0)*10*0.58 -> 104.4 | D27: 14510 | E27: =IF(D27>=D26,D27-D26,0)*10*0.58 -> 110.2 | F27: 72376 | G27: =IF(F27>=F26,F27-F26,0)*0.58 -> 128.18 | H27: =C27+E27+G27 -> 342.78 | O27: =IF(N27>=N26,N27-N26,0) -> 0 | Q27: =(H27-O27)*0.58 -> 198.8124 | S27: =IF(R27-R26>0,R27-R26,0) -> 0 | T27: =Elect!BT26 -> 248 | U27: =H27/T27 -> 1.3821774 | V27: =Elect!BV26 -> 0 | W27: =H27/V27 -> #DIV/0! | X27: =H27*V1 -> 1371.12 | Y27: =IF(X27>0,X27/T27,0) -> 5.5287097 | Z27: =IF(X27>0,X27/V27,0) -> #DIV/0!
A28: 22 | B28: 91064 | C28: =IF(B28>=B27,B28-B27,0)*10*0.58 -> 81.2 | D28: 14527 | E28: =IF(D28>=D27,D28-D27,0)*10*0.58 -> 98.6 | F28: 72577 | G28: =IF(F28>=F27,F28-F27,0)*0.58 -> 116.58 | H28: =C28+E28+G28 -> 296.38 | O28: =IF(N28>=N27,N28-N27,0) -> 0 | Q28: =(H28-O28)*0.58 -> 171.9004 | S28: =IF(R28-R27>0,R28-R27,0) -> 0 | T28: =Elect!BT27 -> 225 | U28: =H28/T28 -> 1.3172444 | V28: =Elect!BV27 -> 0 | W28: =H28/V28 -> #DIV/0! | X28: =H28*V1 -> 1185.52 | Y28: =IF(X28>0,X28/T28,0) -> 5.2689778 | Z28: =IF(X28>0,X28/V28,0) -> #DIV/0!
A29: 23 | B29: 91081 | C29: =IF(B29>=B28,B29-B28,0)*10*0.58 -> 98.6 | D29: 14545 | E29: =IF(D29>=D28,D29-D28,0)*10*0.58 -> 104.4 | F29: 72772 | G29: =IF(F29>=F28,F29-F28,0)*0.58 -> 113.1 | H29: =C29+E29+G29 -> 316.1 | O29: =IF(N29>=N28,N29-N28,0) -> 0 | Q29: =(H29-O29)*0.58 -> 183.338 | S29: =IF(R29-R28>0,R29-R28,0) -> 0 | T29: =Elect!BT28 -> 201 | U29: =H29/T29 -> 1.5726368 | V29: =Elect!BV28 -> 0 | W29: =H29/V29 -> #DIV/0! | X29: =H29*V1 -> 1264.4 | Y29: =IF(X29>0,X29/T29,0) -> 6.2905473 | Z29: =IF(X29>0,X29/V29,0) -> #DIV/0!
A30: 24 | B30: 91098 | C30: =IF(B30>=B29,B30-B29,0)*10*0.58 -> 98.6 | D30: 14565 | E30: =IF(D30>=D29,D30-D29,0)*10*0.58 -> 116 | F30: 72981 | G30: =IF(F30>=F29,F30-F29,0)*0.58 -> 121.22 | H30: =C30+E30+G30 -> 335.82 | O30: =IF(N30>=N29,N30-N29,0) -> 0 | Q30: =(H30-O30)*0.58 -> 194.7756 | S30: =IF(R30-R29>0,R30-R29,0) -> 0 | T30: =Elect!BT29 -> 196 | U30: =H30/T30 -> 1.7133673 | V30: =Elect!BV29 -> 0 | W30: =H30/V30 -> #DIV/0! | X30: =H30*V1 -> 1343.28 | Y30: =IF(X30>0,X30/T30,0) -> 6.8534694 | Z30: =IF(X30>0,X30/V30,0) -> #DIV/0!
A31: 25 | B31: 91113 | C31: =IF(B31>=B30,B31-B30,0)*10*0.58 -> 87 | D31: 14587 | E31: =IF(D31>=D30,D31-D30,0)*10*0.58 -> 127.6 | F31: 73191 | G31: =IF(F31>=F30,F31-F30,0)*0.58 -> 121.8 | H31: =C31+E31+G31 -> 336.4 | O31: =IF(N31>=N30,N31-N30,0) -> 0 | Q31: =(H31-O31)*0.58 -> 195.112 | S31: =IF(R31-R30>0,R31-R30,0) -> 0 | T31: =Elect!BT30 -> 143 | U31: =H31/T31 -> 2.3524476 | V31: =Elect!BV30 -> 0 | W31: =H31/V31 -> #DIV/0! | X31: =H31*V1 -> 1345.6 | Y31: =IF(X31>0,X31/T31,0) -> 9.4097902 | Z31: =IF(X31>0,X31/V31,0) -> #DIV/0!
A32: 26 | B32: 91135 | C32: =IF(B32>=B31,B32-B31,0)*10*0.58 -> 127.6 | D32: 14601 | E32: =IF(D32>=D31,D32-D31,0)*10*0.58 -> 81.2 | F32: 73408 | G32: =IF(F32>=F31,F32-F31,0)*0.58 -> 125.86 | H32: =C32+E32+G32 -> 334.66 | O32: =IF(N32>=N31,N32-N31,0) -> 0 | Q32: =(H32-O32)*0.58 -> 194.1028 | S32: =IF(R32-R31>0,R32-R31,0) -> 0 | T32: =Elect!BT31 -> 163 | U32: =H32/T32 -> 2.0531288 | V32: =Elect!BV31 -> 0 | W32: =H32/V32 -> #DIV/0! | X32: =H32*V1 -> 1338.64 | Y32: =IF(X32>0,X32/T32,0) -> 8.2125153 | Z32: =IF(X32>0,X32/V32,0) -> #DIV/0!
A33: 27 | B33: 91145 | C33: =IF(B33>=B32,B33-B32,0)*10*0.58 -> 58 | D33: 14619 | E33: =IF(D33>=D32,D33-D32,0)*10*0.58 -> 104.4 | F33: 73623 | G33: =IF(F33>=F32,F33-F32,0)*0.58 -> 124.7 | H33: =C33+E33+G33 -> 287.1 | O33: =IF(N33>=N32,N33-N32,0) -> 0 | Q33: =(H33-O33)*0.58 -> 166.518 | S33: =IF(R33-R32>0,R33-R32,0) -> 0 | T33: =Elect!BT32 -> 207 | U33: =H33/T33 -> 1.3869565 | V33: =Elect!BV32 -> 0 | W33: =H33/V33 -> #DIV/0! | X33: =H33*V1 -> 1148.4 | Y33: =IF(X33>0,X33/T33,0) -> 5.5478261 | Z33: =IF(X33>0,X33/V33,0) -> #DIV/0!
A34: 28 | B34: 91162 | C34: =IF(B34>=B33,B34-B33,0)*10*0.58 -> 98.6 | D34: 14638 | E34: =IF(D34>=D33,D34-D33,0)*10*0.58 -> 110.2 | F34: 73851 | G34: =IF(F34>=F33,F34-F33,0)*0.58 -> 132.24 | H34: =C34+E34+G34 -> 341.04 | O34: =IF(N34>=N33,N34-N33,0) -> 0 | Q34: =(H34-O34)*0.58 -> 197.8032 | S34: =IF(R34-R33>0,R34-R33,0) -> 0 | T34: =Elect!BT33 -> 225 | U34: =H34/T34 -> 1.5157333 | V34: =Elect!BV33 -> 0 | W34: =H34/V34 -> #DIV/0! | X34: =H34*V1 -> 1364.16 | Y34: =IF(X34>0,X34/T34,0) -> 6.0629333 | Z34: =IF(X34>0,X34/V34,0) -> #DIV/0!
A35: 29 | B35: 91177 | C35: =IF(B35>=B34,B35-B34,0)*10*0.58 -> 87 | D35: 14655 | E35: =IF(D35>=D34,D35-D34,0)*10*0.58 -> 98.6 | F35: 74035 | G35: =IF(F35>=F34,F35-F34,0)*0.58 -> 106.72 | H35: =C35+E35+G35 -> 292.32 | O35: =IF(N35>=N34,N35-N34,0) -> 0 | Q35: =(H35-O35)*0.58 -> 169.5456 | S35: =IF(R35-R34>0,R35-R34,0) -> 0 | T35: =Elect!BT34 -> 241 | U35: =H35/T35 -> 1.2129461 | V35: =Elect!BV34 -> 0 | W35: =H35/V35 -> #DIV/0! | X35: =H35*V1 -> 1169.28 | Y35: =IF(X35>0,X35/T35,0) -> 4.8517842 | Z35: =IF(X35>0,X35/V35,0) -> #DIV/0!
A36: 30 | B36: 91198 | C36: =IF(B36>=B35,B36-B35,0)*10*0.58 -> 121.8 | D36: 14680 | E36: =IF(D36>=D35,D36-D35,0)*10*0.58 -> 145 | F36: 74220 | G36: =IF(F36>=F35,F36-F35,0)*0.58 -> 107.3 | H36: =C36+E36+G36 -> 374.1 | I36: 331 | K36: 5727 | O36: =IF(N36>=N35,N36-N35,0) -> 0 | Q36: =(H36-O36)*0.58 -> 216.978 | S36: =IF(R36-R35>0,R36-R35,0) -> 0 | T36: =Elect!BT35 -> 250 | U36: =H36/T36 -> 1.4964 | V36: =Elect!BV35 -> 0 | W36: =H36/V36 -> #DIV/0! | X36: =H36*V1 -> 1496.4 | Y36: =IF(X36>0,X36/T36,0) -> 5.9856 | Z36: =IF(X36>0,X36/V36,0) -> #DIV/0!
A37: 31 | B37: 91217 | C37: =IF(B37>=B36,B37-B36,0)*10*0.58 -> 110.2 | D37: 14703 | E37: =IF(D37>=D36,D37-D36,0)*10*0.58 -> 133.4 | F37: 74439 | G37: =IF(F37>=F36,F37-F36,0)*0.58 -> 127.02 | H37: =C37+E37+G37 -> 370.62 | O37: =IF(N37>=N36,N37-N36,0) -> 0 | Q37: =(H37-O37)*0.58 -> 214.9596 | S37: =IF(R37-R36>0,R37-R36,0) -> 0 | T37: =Elect!BT36 -> 250 | U37: =H37/T37 -> 1.48248 | V37: =Elect!BV36 -> 0 | W37: =H37/V37 -> #DIV/0! | X37: =H37*V7 -> 0 | Y37: =IF(X37>0,X37/T37,0) -> 0 | Z37: =IF(X37>0,X37/V37,0) -> 0
A38: MTD | C38: =SUM(C7:C37) -> 3428.2833 | E38: =SUM(E7:E37) -> 3974.74 | G38: =SUM(G7:G37) -> 3562.6017 | H38: =SUM(H7:H37) -> 10965.625 | O38: =SUM(O7:O36) -> 0 | Q38: =SUM(Q7:Q34) -> 5758.5793 | S38: =SUM(S7:S34) -> 0 | T38: =SUM(T7:T36) -> 6336 | U38: =IF(H38>0,H38/T38,0) -> 1.7306858 | V38: =SUM(V7:V36) -> 0 | W38: =IF(H38>0,H38/V38,0) -> #DIV/0! | X38: =SUM(X7:X36) -> 42380.02 | Y38: =IF(X38>0,X38/T38,0) -> 6.6887658 | Z38: =IF(X38>0,X38/V38,0) -> #DIV/0!
A39: AVER. Act | C39: =C38/B48 -> 114.27611 | E39: =E38/B48 -> 132.49133 | G39: =G38/B48 -> 118.75339 | H39: =H38/B48 -> 365.52083 | O39: =O38/B48 -> 0 | Q39: =Q38/B48 -> 191.95264 | S39: =S38/C48 -> #DIV/0! | T39: =T38/B48 -> 211.2 | U39: =IF(H39>0,H39/T39,0) -> 1.7306858 | V39: =V38/B48 -> 0 | W39: =IF(H39>0,H39/V39,0) -> #DIV/0! | X39: =X38/B48 -> 1412.6673 | Y39: =IF(X39>0,X39/T39,0) -> 6.6887658 | Z39: =IF(X39>0,X39/V39,0) -> #DIV/0!
A40: TOTAL Budget | T40: =YTD!Q2341 -> 0 | U40: =IF(#REF!>0,#REF!/T40,0) -> #REF! | V40: =YTD!Q2342 -> 0 | W40: =IF(#REF!>0,#REF!/V40,0) -> #REF! | X40: =YTD!Q2346 -> 0 | Y40: =IF(X40>0,X40/T40,0) -> 0 | Z40: =IF(X40>0,X40/V40,0) -> 0
A41: Budget MTD | T41: =T42*C48 -> #VALUE! | U41: =IF(#REF!>0,#REF!/T41,0) -> #REF! | V41: =V42*C48 -> #VALUE! | W41: =IF(#REF!>0,#REF!/V41,0) -> #REF! | X41: =#REF!*5.62 -> #REF! | Y41: =IF(X41>0,X41/T41,0) -> #REF! | Z41: =IF(X41>0,X41/V41,0) -> #REF!
A42: AVER. Bud | T42: =T40/$A$48 -> #VALUE! | V42: =V40/$A$48 -> #VALUE!
A43: Total RFC | T43: =YTD!Q2358 -> 0 | V43: =YTD!Q2359 -> 0 | X43: =YTD!Q2363 -> 0 | Y43: =IF(X43>0,X43/T43,0) -> 0 | Z43: =IF(X43>0,X43/V43,0) -> 0
A44: RFC MTD | T44: =T43/A48*C48 -> #VALUE! | V44: =V43/A48*C48 -> #VALUE! | X44: =X43/A48*C48 -> #VALUE! | Y44: =IF(X44>0,X44/T44,0) -> #VALUE! | Z44: =IF(X44>0,X44/V44,0) -> #VALUE!
A45: AVER RFC | T45: =T43/A48 -> #VALUE! | V45: =V44/A48*C48 -> #VALUE! | X45: =X43/A48 -> #VALUE!
A46: MTD 13 | U46: =Consp!BH33 -> 1.1514679 | W46: =Consp!BI33 -> 0.57929342 | X46: =Consp!BJ33 -> 140121.3 | Y46: =Consp!BK33 -> 6.8331854 | Z46: =Consp!BL33 -> 3.4377159
A47: AVER. Act 13 | U47: =Consp!BH34 -> 1.1761372 | W47: =Consp!BI34 -> 0.60007377 | X47: =Consp!BJ34 -> 5004.3322 | Y47: =Consp!BK34 -> 6.8331854 | Z47: =Consp!BL34 -> 3.4377159
A48: No of Days MTD | B48: =COUNTIF(B7:B36,">0") -> 30
A136: Water Incoming

Sheet Gas
A1: =Elect!A1 -> 44927 | E1: Gas | H1: Gas UP | J1: 3.9
A4: NO. | B4: Main Gas Flow Meter | D4: Laundry Gas Flow Meter | F4: Grumandiz Gas Flow Meter | H4: Plant Room Gas Share Cost | I4: Hotel Consumption Cost | J4: La Grumandiz Cost | K4: Total Natural Gas Consumption
B5: Read | C5: Cons | D5: Read | E5: Cons | F5: Read | G5: Cons | H5: LE/DAY | I5: LE/DAY | J5: LE/DAY | K5: Cons
B6: 8451913.6 | C6: =IF(B6>=B5,B6-B5,0)*1.06 -> 0 | D6: 614831.14 | E6: =IF(D6>=D5,D6-D5,0)*0.7 -> 0 | F6: 632071.73 | G6: =IF(F6>=F5,F6-F5,0) -> 0 | K6: =C6+E6 -> 0
A7: 1 | B7: 8455243 | C7: =IF(B7>=B6,B7-B6,0)*1.06 -> 3529.1817 | D7: 615553 | E7: =IF(D7>=D6,D7-D6,0)*0.7 -> 505.30278 | F7: 632194 | G7: =IF(F7>=F6,F7-F6,0) -> 122.26852 | H7: =(E7*0.55)*1.61 -> 447.44561 | I7: =C7*J1 -> 13763.809 | J7: =G7*J1 -> 476.84722 | K7: =C7+E7 -> 4034.4844
A8: 2 | B8: 8456774 | C8: =IF(B8>=B7,B8-B7,0)*1.06 -> 1622.86 | D8: 616044 | E8: =IF(D8>=D7,D8-D7,0)*0.7 -> 343.7 | F8: 632269 | G8: =IF(F8>=F7,F8-F7,0) -> 75 | H8: =(E8*0.55)*1.61 -> 304.34635 | I8: =C8*J1 -> 6329.154 | J8: =G8*J1 -> 292.5 | K8: =C8+E8 -> 1966.56
A9: 3 | B9: 8458394 | C9: =IF(B9>=B8,B9-B8,0)*1.06 -> 1717.2 | D9: 616591 | E9: =IF(D9>=D8,D9-D8,0)*0.7 -> 382.9 | F9: 632364 | G9: =IF(F9>=F8,F9-F8,0) -> 95 | H9: =(E9*0.55)*1.61 -> 339.05795 | I9: =C9*J1 -> 6697.08 | J9: =G9*J1 -> 370.5 | K9: =C9+E9 -> 2100.1
A10: 4 | B10: 8460180 | C10: =IF(B10>=B9,B10-B9,0)*1.06 -> 1893.16 | D10: 617132 | E10: =IF(D10>=D9,D10-D9,0)*0.7 -> 378.7 | F10: 632468 | G10: =IF(F10>=F9,F10-F9,0) -> 104 | H10: =(E10*0.55)*1.61 -> 335.33885 | I10: =C10*J1 -> 7383.324 | J10: =G10*J1 -> 405.6 | K10: =C10+E10 -> 2271.86
A11: 5 | B11: 8461649 | C11: =IF(B11>=B10,B11-B10,0)*1.06 -> 1557.14 | D11: 617727 | E11: =IF(D11>=D10,D11-D10,0)*0.7 -> 416.5 | F11: 632559 | G11: =IF(F11>=F10,F11-F10,0) -> 91 | H11: =(E11*0.55)*1.61 -> 368.81075 | I11: =C11*J1 -> 6072.846 | J11: =G11*J1 -> 354.9 | K11: =C11+E11 -> 1973.64
A12: 6 | B12: 8463299 | C12: =IF(B12>=B11,B12-B11,0)*1.06 -> 1749 | D12: 618241 | E12: =IF(D12>=D11,D12-D11,0)*0.7 -> 359.8 | F12: 632642 | G12: =IF(F12>=F11,F12-F11,0) -> 83 | H12: =(E12*0.55)*1.61 -> 318.6029 | I12: =C12*J1 -> 6821.1 | J12: =G12*J1 -> 323.7 | K12: =C12+E12 -> 2108.8
A13: 7 | B13: 8464878 | C13: =IF(B13>=B12,B13-B12,0)*1.06 -> 1673.74 | D13: 618818 | E13: =IF(D13>=D12,D13-D12,0)*0.7 -> 403.9 | F13: 632748 | G13: =IF(F13>=F12,F13-F12,0) -> 106 | H13: =(E13*0.55)*1.61 -> 357.65345 | I13: =C13*J1 -> 6527.586 | J13: =G13*J1 -> 413.4 | K13: =C13+E13 -> 2077.64
A14: 8 | B14: 8466522 | C14: =IF(B14>=B13,B14-B13,0)*1.06 -> 1742.64 | D14: 619380 | E14: =IF(D14>=D13,D14-D13,0)*0.7 -> 393.4 | F14: 632838 | G14: =IF(F14>=F13,F14-F13,0) -> 90 | H14: =(E14*0.55)*1.61 -> 348.3557 | I14: =C14*J1 -> 6796.296 | J14: =G14*J1 -> 351 | K14: =C14+E14 -> 2136.04
A15: 9 | B15: 8468168 | C15: =IF(B15>=B14,B15-B14,0)*1.06 -> 1744.76 | D15: 619928 | E15: =IF(D15>=D14,D15-D14,0)*0.7 -> 383.6 | F15: 632949 | G15: =IF(F15>=F14,F15-F14,0) -> 111 | H15: =(E15*0.55)*1.61 -> 339.6778 | I15: =C15*J1 -> 6804.564 | J15: =G15*J1 -> 432.9 | K15: =C15+E15 -> 2128.36
A16: 10 | B16: 8469842 | C16: =IF(B16>=B15,B16-B15,0)*1.06 -> 1774.44 | D16: 620466 | E16: =IF(D16>=D15,D16-D15,0)*0.7 -> 376.6 | F16: 633048 | G16: =IF(F16>=F15,F16-F15,0) -> 99 | H16: =(E16*0.55)*1.61 -> 333.4793 | I16: =C16*J1 -> 6920.316 | J16: =G16*J1 -> 386.1 | K16: =C16+E16 -> 2151.04
A17: 11 | B17: 8471487 | C17: =IF(B17>=B16,B17-B16,0)*1.06 -> 1743.7 | D17: 621021 | E17: =IF(D17>=D16,D17-D16,0)*0.7 -> 388.5 | F17: 633148.5 | G17: =IF(F17>=F16,F17-F16,0) -> 100.5 | H17: =(E17*0.55)*1.61 -> 344.01675 | I17: =C17*J1 -> 6800.43 | J17: =G17*J1 -> 391.95 | K17: =C17+E17 -> 2132.2
A18: 12 | B18: 8473140.8 | C18: =IF(B18>=B17,B18-B17,0)*1.06 -> 1753.028 | D18: 621570.2 | E18: =IF(D18>=D17,D18-D17,0)*0.7 -> 384.44 | F18: 633249.6 | G18: =IF(F18>=F17,F18-F17,0) -> 101.1 | H18: =(E18*0.55)*1.61 -> 340.42162 | I18: =C18*J1 -> 6836.8092 | J18: =G18*J1 -> 394.29 | K18: =C18+E18 -> 2137.468
A19: 13 | B19: 8474563 | C19: =IF(B19>=B18,B19-B18,0)*1.06 -> 1507.532 | D19: 622105 | E19: =IF(D19>=D18,D19-D18,0)*0.7 -> 374.36 | F19: 633330 | G19: =IF(F19>=F18,F19-F18,0) -> 80.4 | H19: =(E19*0.55)*1.61 -> 331.49578 | I19: =C19*J1 -> 5879.3748 | J19: =G19*J1 -> 313.56 | K19: =C19+E19 -> 1881.892
A20: 14 | B20: 8476134 | C20: =IF(B20>=B19,B20-B19,0)*1.06 -> 1665.26 | D20: 622698 | E20: =IF(D20>=D19,D20-D19,0)*0.7 -> 415.1 | F20: 633442 | G20: =IF(F20>=F19,F20-F19,0) -> 112 | H20: =(E20*0.55)*1.61 -> 367.57105 | I20: =C20*J1 -> 6494.514 | J20: =G20*J1 -> 436.8 | K20: =C20+E20 -> 2080.36
A21: 15 | B21: 8477679 | C21: =IF(B21>=B20,B21-B20,0)*1.06 -> 1637.7 | D21: 623244 | E21: =IF(D21>=D20,D21-D20,0)*0.7 -> 382.2 | F21: 633541 | G21: =IF(F21>=F20,F21-F20,0) -> 99 | H21: =(E21*0.55)*1.61 -> 338.4381 | I21: =C21*J1 -> 6387.03 | J21: =G21*J1 -> 386.1 | K21: =C21+E21 -> 2019.9
A22: 16 | B22: 8479262 | C22: =IF(B22>=B21,B22-B21,0)*1.06 -> 1677.98 | D22: 623793 | E22: =IF(D22>=D21,D22-D21,0)*0.7 -> 384.3 | F22: 633639 | G22: =IF(F22>=F21,F22-F21,0) -> 98 | H22: =(E22*0.55)*1.61 -> 340.29765 | I22: =C22*J1 -> 6544.122 | J22: =G22*J1 -> 382.2 | K22: =C22+E22 -> 2062.28
A23: 17 | B23: 8481323 | C23: =IF(B23>=B22,B23-B22,0)*1.06 -> 2184.66 | D23: 624345 | E23: =IF(D23>=D22,D23-D22,0)*0.7 -> 386.4 | F23: 633730 | G23: =IF(F23>=F22,F23-F22,0) -> 91 | H23: =(E23*0.55)*1.61 -> 342.1572 | I23: =C23*J1 -> 8520.174 | J23: =G23*J1 -> 354.9 | K23: =C23+E23 -> 2571.06
A24: 18 | B24: 8482592 | C24: =IF(B24>=B23,B24-B23,0)*1.06 -> 1345.14 | D24: 625013 | E24: =IF(D24>=D23,D24-D23,0)*0.7 -> 467.6 | F24: 633832 | G24: =IF(F24>=F23,F24-F23,0) -> 102 | H24: =(E24*0.55)*1.61 -> 414.0598 | I24: =C24*J1 -> 5246.046 | J24: =G24*J1 -> 397.8 | K24: =C24+E24 -> 1812.74
A25: 19 | B25: 8483992 | C25: =IF(B25>=B24,B25-B24,0)*1.06 -> 1484 | D25: 625557 | E25: =IF(D25>=D24,D25-D24,0)*0.7 -> 380.8 | F25: 633914 | G25: =IF(F25>=F24,F25-F24,0) -> 82 | H25: =(E25*0.55)*1.61 -> 337.1984 | I25: =C25*J1 -> 5787.6 | J25: =G25*J1 -> 319.8 | K25: =C25+E25 -> 1864.8
A26: 20 | B26: 8485406 | C26: =IF(B26>=B25,B26-B25,0)*1.06 -> 1498.84 | D26: 626063 | E26: =IF(D26>=D25,D26-D25,0)*0.7 -> 354.2 | F26: 633998 | G26: =IF(F26>=F25,F26-F25,0) -> 84 | H26: =(E26*0.55)*1.61 -> 313.6441 | I26: =C26*J1 -> 5845.476 | J26: =G26*J1 -> 327.6 | K26: =C26+E26 -> 1853.04
A27: 21 | B27: 8486965 | C27: =IF(B27>=B26,B27-B26,0)*1.06 -> 1652.54 | D27: 626642 | E27: =IF(D27>=D26,D27-D26,0)*0.7 -> 405.3 | F27: 634097 | G27: =IF(F27>=F26,F27-F26,0) -> 99 | H27: =(E27*0.55)*1.61 -> 358.89315 | I27: =C27*J1 -> 6444.906 | J27: =G27*J1 -> 386.1 | K27: =C27+E27 -> 2057.84
A28: 22 | B28: 8488568 | C28: =IF(B28>=B27,B28-B27,0)*1.06 -> 1699.18 | D28: 627182 | E28: =IF(D28>=D27,D28-D27,0)*0.7 -> 378 | F28: 634190 | G28: =IF(F28>=F27,F28-F27,0) -> 93 | H28: =(E28*0.55)*1.61 -> 334.719 | I28: =C28*J1 -> 6626.802 | J28: =G28*J1 -> 362.7
A29: 23 | B29: 8490033 | C29: =IF(B29>=B28,B29-B28,0)*1.06 -> 1552.9 | D29: 627775 | E29: =IF(D29>=D28,D29-D28,0)*0.7 -> 415.1 | F29: 634279 | G29: =IF(F29>=F28,F29-F28,0) -> 89 | H29: =(E29*0.55)*1.61 -> 367.57105 | I29: =C29*J1 -> 6056.31 | J29: =G29*J1 -> 347.1 | K29: =C29+E29 -> 1968
A30: 24 | B30: 8491568 | C30: =IF(B30>=B29,B30-B29,0)*1.06 -> 1627.1 | D30: 628356 | E30: =IF(D30>=D29,D30-D29,0)*0.7 -> 406.7 | F30: 634370.67 | G30: =IF(F30>=F29,F30-F29,0) -> 91.666667 | H30: =(E30*0.55)*1.61 -> 360.13285 | I30: =C30*J1 -> 6345.69 | J30: =G30*J1 -> 357.5 | K30: =C30+E30 -> 2033.8
A31: 25 | B31: 8493064 | C31: =IF(B31>=B30,B31-B30,0)*1.06 -> 1585.76 | D31: 628886 | E31: =IF(D31>=D30,D31-D30,0)*0.7 -> 371 | F31: 634454 | G31: =IF(F31>=F30,F31-F30,0) -> 83.333333 | H31: =(E31*0.55)*1.61 -> 328.5205 | I31: =C31*J3 -> 0 | J31: =G31*J1 -> 325 | K31: =C31+E31 -> 1956.76
A32: 26 | B32: 8494749 | C32: =IF(B32>=B31,B32-B31,0)*1.06 -> 1786.1 | D32: 629492 | E32: =IF(D32>=D31,D32-D31,0)*0.7 -> 424.2 | F32: 634563 | G32: =IF(F32>=F31,F32-F31,0) -> 109 | H32: =(E32*0.55)*1.61 -> 375.6291 | I32: =C32*J1 -> 6965.79 | J32: =G32*J1 -> 425.1 | K32: =C32+E32 -> 2210.3
A33: 27 | B33: 8496190 | C33: =IF(B33>=B32,B33-B32,0)*1.06 -> 1527.46 | D33: 630023 | E33: =IF(D33>=D32,D33-D32,0)*0.7 -> 371.7 | F33: 634670 | G33: =IF(F33>=F32,F33-F32,0) -> 107 | H33: =(E33*0.55)*1.61 -> 329.14035 | I33: =C33*J1 -> 5957.094 | J33: =G33*J1 -> 417.3 | K33: =C33+E33 -> 1899.16
A34: 28 | B34: 8497743 | C34: =IF(B34>=B33,B34-B33,0)*1.06 -> 1646.18 | D34: 630640 | E34: =IF(D34>=D33,D34-D33,0)*0.7 -> 431.9 | F34: 634788 | G34: =IF(F34>=F33,F34-F33,0) -> 118 | H34: =(E34*0.55)*1.61 -> 382.44745 | I34: =C34*J1 -> 6420.102 | J34: =G34*J1 -> 460.2 | K34: =C34+E34 -> 2078.08
A35: 29 | B35: 8499051 | C35: =IF(B35>=B34,B35-B34,0)*1.06 -> 1386.48 | D35: 631699 | E35: =IF(D35>=D34,D35-D34,0)*0.7 -> 741.3 | F35: 634930 | G35: =IF(F35>=F34,F35-F34,0) -> 142 | H35: =(E35*0.55)*1.61 -> 656.42115 | I35: =C35*J1 -> 5407.272 | J35: =G35*J1 -> 553.8 | K35: =C35+E35 -> 2127.78
A36: 30 | B36: 8500816 | C36: =IF(B36>=B35,B36-B35,0)*1.06 -> 1870.9 | D36: 631723 | E36: =IF(D36>=D35,D36-D35,0)*0.7 -> 16.8 | F36: 634977 | G36: =IF(F36>=F35,F36-F35,0) -> 47 | H36: =(E36*0.55)*1.61 -> 14.8764 | I36: =C36*J1 -> 7296.51 | J36: =G36*J1 -> 183.3 | K36: =C36+E36 -> 1887.7
A37: 31 | B37: 8502573 | C37: =IF(B37>=B36,B37-B36,0)*1.06 -> 1862.42 | D37: 632460 | E37: =IF(D37>=D36,D37-D36,0)*0.7 -> 515.9 | F37: 635107 | G37: =IF(F37>=F36,F37-F36,0) -> 130 | H37: =(E37*0.55)*1.61 -> 456.82945 | I37: =C37*J1 -> 7263.438 | J37: =G37*J1 -> 507 | K37: =C37+E37 -> 2378.32
A38: MTD | C38: =SUM(C7:C37) -> 53698.982 | E38: =SUM(E7:E37) -> 12340.203 | G38: =SUM(G7:G37) -> 3035.2685 | H38: =SUM(H6:H37) -> 10927.25 | I38: =SUM(I6:I37) -> 203241.56 | J38: =SUM(J6:J37) -> 11837.547 | K38: =SUM(K6:K37) -> 63962.004
A39: Average MTD. | C39: =C38/A42 -> 1789.9661 | E39: =E38/A42 -> 411.34009 | G39: =G38/A42 -> 101.17562 | H39: =H38/A42 -> 364.24165 | I39: =I38/A42 -> 6774.7188 | J39: =J38/A42 -> 394.58491
A41: No of Days MTD
A42: =COUNTIF(B7:B36,">0") -> 30

Sheet Sheet1

Sheet Sheet2

Sheet Consp
A1: =Elect!A1 -> 44927 | L1: Summary | P1: =Elect!A1 -> 44927
B2: Elect Consuumption | H2: Water Incoming | U2: Water Consumption | AC2: Irrigation | AG2: Gas | AJ2: Cost | AK2: Solar Meter [ LIT ] | AL2: No. of Eng. | AM2: No. of Gardners | AN2: Cons. (lit) | AO2: Received Gas (tons) | AP2: Fuel Cost | AQ2: Solar level [cm] | AR2: Received Solar (tons) | AS2: Fuel Cost | AT2: Occupancy 10 | AV2: Occupancy07 | AZ2: Elect 2009 | BE2: Elect 2010 | BJ2: Water 2009 | BO2: Water 2010
A3: Date | B3: COUNTER (2) | D3: MD | F3: KVAR | H3: R.O | J3: Qenna | L3: Trucks | N3: Rimievera Line Meter | O3: Total Inc. | Q3: Total Main S.Pool | S3: Total Bar & Beach cons. | U3: Total S. Pool cons. | W3: Hotel consumption. | Y3: Sold Water | AA3: Irr. Water from R.O | AC3: Irr. Consumption. | AE3: Storage Water One tank | AF3: Grand Cons | AG3: % | AH3: Stock | AI3: Cons. | AJ3: 0 | AT3: No of guest | AU3: No. of rooms | AV3: No. of rooms | AW3: No. of guest | AX3: Cons. Per occ. room | AY3: Cons. Per guest | AZ3: Total cost | BA3: cost per room | BB3: cost per guest | BC3: Cons. Per occ. room | BD3: Cons. Per guest | BE3: Total cost | BF3: cost per room | BG3: cost per guest | BH3: Cons. Per occ. room | BI3: Cons. Per guest | BJ3: Total cost | BK3: cost per room | BL3: cost per guest | BM3: Cons. Per occ. room | BN3: Cons. Per guest | BO3: Total cost | BP3: cost per room | BQ3: cost per guest
B4: 2013 | C4: 2014 | D4: 2013 | E4: 2014 | F4: 2013 | G4: 2014 | H4: 2013 | I4: 2014 | J4: 2009 | K4: 2010 | L4: 2009 | M4: 2010 | O4: 2009 | P4: 2010 | Q4: 2009 | R4: 2010 | S4: 2009 | T4: 2010 | U4: 2009 | V4: 2010 | W4: 2009 | X4: 2010 | Y4: 2009 | Z4: 2010 | AA4: 2009 | AB4: 2010 | AC4: 2009 | AD4: 2010
A5: 1 | B5: 33600 | C5: =Elect!J6 -> 6443.9444 | D5: 0 | E5: =Elect!M6 -> 1741 | F5: 20 | G5: =Elect!O6 -> 2000.8333 | H5: 800 | I5: =Water!C7 -> 162.88333 | J5: 0 | K5: =Water!E7 -> 146.74 | L5: 0 | M5: =Water!#REF! -> #REF! | N5: =Water!#REF! -> #REF! | O5: 1005 | P5: =Water!H7 -> 433.405 | Q5: 114 | R5: =Water!O7 -> 0 | S5: 13 | T5: =Water!#REF! -> #REF! | U5: 147 | V5: =Water!#REF! -> #REF! | W5: 755 | X5: =Water!Q7 -> 251.3749 | Y5: 0 | Z5: =Water!#REF! -> #REF! | AA5: 0 | AB5: 0 | AC5: 690 | AD5: =Water!#REF! -> #REF! | AE5: =Water!#REF! -> #REF! | AF5: =Water!#REF! -> #REF! | AG5: =Gas!#REF! -> #REF! | AH5: =Gas!C7 -> 3529.1817 | AI5: =Gas!#REF! -> #REF! | AJ5: =Gas!J7 -> 476.84722 | AK5: =Gas!#REF! -> #REF! | AL5: =Gas!#REF! -> #REF! | AM5: =Gas!#REF! -> #REF! | AN5: =Gas!#REF! -> #REF! | AO5: =Gas!#REF! -> #REF! | AP5: =Gas!#REF! -> #REF! | AQ5: =Gas!#REF! -> #REF! | AR5: =Gas!#REF! -> #REF! | AS5: =Gas!#REF! -> #REF! | AT5: =Elect!BR6 -> 149.33333 | AU5: =Elect!BP6 -> 170 | AV5: =Elect!#REF! -> #REF! | AW5: =Elect!BR6 -> 149.33333 | AX5: 48.695652 | AY5: 24.705882 | AZ5: 8835.4834 | BA5: 12.805048 | BB5: 6.496679 | BC5: =Elect!#REF! -> #REF! | BD5: =Elect!#REF! -> #REF! | BE5: =Elect!#REF! -> #REF! | BF5: =Elect!#REF! -> #REF! | BG5: =Elect!#REF! -> #REF! | BH5: 1.142029 | BI5: 0.57941176 | BJ5: 4569.1158 | BK5: 6.6219069 | BL5: 3.3596439 | BM5: =Water!U7 -> 1.8210294 | BN5: =Water!W7 -> #DIV/0! | BO5: =Water!X7 -> 1733.62 | BP5: =Water!Y7 -> 7.2841176 | BQ5: =Water!Z7 -> 0
A6: 2 | B6: 31200 | C6: =Elect!J7 -> 6181 | D6: 0 | E6: =Elect!M7 -> 2110 | F6: 20 | G6: =Elect!O7 -> 1875 | H6: 936 | I6: =Water!C8 -> 69.6 | J6: 0 | K6: =Water!E8 -> 87 | L6: 0 | M6: =Water!#REF! -> #REF! | N6: =Water!#REF! -> #REF! | O6: 1006 | P6: =Water!H8 -> 258.1 | Q6: 113 | R6: =Water!O8 -> 0 | S6: 17 | T6: =Water!#REF! -> #REF! | U6: 140 | V6: =Water!#REF! -> #REF! | W6: 792 | X6: =Water!Q8 -> 149.698 | Y6: 0 | Z6: =Water!#REF! -> #REF! | AA6: 0 | AB6: 0 | AC6: 370 | AD6: =Water!#REF! -> #REF! | AE6: =Water!#REF! -> #REF! | AF6: =Water!#REF! -> #REF! | AG6: =Gas!B7 -> 8455243 | AH6: =Gas!C8 -> 1622.86 | AI6: =Gas!#REF! -> #REF! | AJ6: =Gas!J8 -> 292.5 | AK6: =Gas!#REF! -> #REF! | AL6: =Gas!#REF! -> #REF! | AM6: =Gas!#REF! -> #REF! | AN6: =Gas!#REF! -> #REF! | AO6: =Gas!#REF! -> #REF! | AP6: =Gas!#REF! -> #REF! | AQ6: =Gas!#REF! -> #REF! | AR6: =Gas!#REF! -> #REF! | AS6: =Gas!#REF! -> #REF! | AT6: =Elect!BR7 -> 151 | AU6: =Elect!BP7 -> 133 | AX6: 47.416413 | AY6: 23.981553 | AZ6: 8299.2754 | BA6: 12.612881 | BB6: 6.379151 | BC6: =Elect!BQ7 -> 566724 | BD6: =Elect!#REF! -> #REF! | BE6: =Elect!#REF! -> #REF! | BF6: =Elect!#REF! -> #REF! | BG6: =Elect!#REF! -> #REF! | BH6: 1.2021277 | BI6: 0.60799385 | BJ6: 5345.8654 | BK6: 8.1244156 | BL6: 4.1090434 | BM6: =Water!U8 -> 1.1370044 | BN6: =Water!W8 -> #DIV/0! | BO6: =Water!X8 -> 1032.4 | BP6: =Water!Y8 -> 4.5480176 | BQ6: =Water!Z8 -> #DIV/0!
A7: 3 | B7: 31200 | C7: =Elect!J8 -> 6253 | D7: 0 | E7: =Elect!M8 -> 2264 | F7: 20 | G7: =Elect!O8 -> 2037 | H7: 685 | I7: =Water!C9 -> 104.4 | J7: 0 | K7: =Water!E9 -> 127.6 | L7: 0 | M7: =Water!#REF! -> #REF! | N7: =Water!#REF! -> #REF! | O7: 902 | P7: =Water!H9 -> 342.78 | Q7: 126 | R7: =Water!O9 -> 0 | S7: 26 | T7: =Water!#REF! -> #REF! | U7: 134 | V7: =Water!#REF! -> #REF! | W7: 766 | X7: =Water!Q9 -> 198.8124 | Y7: 0 | Z7: =Water!#REF! -> #REF! | AA7: 0 | AB7: 0 | AC7: 740 | AD7: =Water!#REF! -> #REF! | AE7: =Water!#REF! -> #REF! | AF7: =Water!#REF! -> #REF! | AG7: =Gas!B9 -> 8458394 | AH7: =Gas!C9 -> 1717.2 | AI7: =Gas!#REF! -> #REF! | AJ7: =Gas!J9 -> 370.5 | AK7: =Gas!#REF! -> #REF! | AL7: =Gas!#REF! -> #REF! | AM7: =Gas!#REF! -> #REF! | AN7: =Gas!#REF! -> #REF! | AO7: =Gas!#REF! -> #REF! | AP7: =Gas!#REF! -> #REF! | AQ7: =Gas!#REF! -> #REF! | AR7: =Gas!#REF! -> #REF! | AS7: =Gas!#REF! -> #REF! | AT7: =Elect!BR8 -> 156 | AU7: =Elect!BP8 -> 146 | AX7: 47.926267 | AY7: 24.223602 | AZ7: 8299.2754 | BA7: 12.748503 | BB7: 6.4435368 | BC7: =Elect!BQ8 -> 566880 | BD7: =Elect!#REF! -> #REF! | BE7: =Elect!#REF! -> #REF! | BF7: =Elect!#REF! -> #REF! | BG7: =Elect!#REF! -> #REF! | BH7: 1.0875576 | BI7: 0.54968944 | BJ7: 3912.3054 | BK7: 6.0096857 | BL7: 3.0375042 | BM7: =Water!U9 -> 1.6092958 | BN7: =Water!W9 -> #DIV/0! | BO7: =Water!X9 -> 1371.12 | BP7: =Water!Y9 -> 6.4371831 | BQ7: =Water!Z9 -> #DIV/0!
A8: 4 | B8: 33600 | C8: =Elect!J9 -> 5829 | D8: 0 | E8: =Elect!M9 -> 2366 | F8: 20 | G8: =Elect!O9 -> 2023 | H8: 786 | I8: =Water!C10 -> 92.8 | J8: 0 | K8: =Water!E10 -> 110.2 | L8: 0 | M8: =Water!#REF! -> #REF! | N8: =Water!#REF! -> #REF! | O8: 930 | P8: =Water!H10 -> 311.46 | Q8: 153 | R8: =Water!O10 -> 0 | S8: 46 | T8: =Water!#REF! -> #REF! | U8: 150 | V8: =Water!#REF! -> #REF! | W8: 766 | X8: =Water!Q10 -> 180.6468 | Y8: 0 | Z8: =Water!#REF! -> #REF! | AA8: 0 | AB8: 0 | AC8: 820 | AD8: =Water!#REF! -> #REF! | AE8: =Water!#REF! -> #REF! | AF8: =Water!#REF! -> #REF! | AG8: =Gas!B10 -> 8460180 | AH8: =Gas!C10 -> 1893.16 | AI8: =Gas!#REF! -> #REF! | AJ8: =Gas!J10 -> 405.6 | AK8: =Gas!#REF! -> #REF! | AL8: =Gas!#REF! -> #REF! | AM8: =Gas!#REF! -> #REF! | AN8: =Gas!#REF! -> #REF! | AO8: =Gas!#REF! -> #REF! | AP8: =Gas!#REF! -> #REF! | AQ8: =Gas!#REF! -> #REF! | AR8: =Gas!#REF! -> #REF! | AS8: =Gas!#REF! -> #REF! | AT8: =Elect!BR9 -> 107 | AU8: =Elect!BP9 -> 112 | AX8: 51.06383 | AY8: 25.866051 | AZ8: 8835.4834 | BA8: 13.427786 | BB8: 6.8017578 | BC8: =Elect!BQ9 -> 566987 | BD8: =Elect!#REF! -> #REF! | BE8: =Elect!#REF! -> #REF! | BF8: =Elect!#REF! -> #REF! | BG8: =Elect!#REF! -> #REF! | BH8: 1.2218845 | BI8: 0.61893764 | BJ8: 4489.1562 | BK8: 6.8224259 | BL8: 3.4558555 | BM8: =Water!U10 -> 1.5418812 | BN8: =Water!W10 -> #DIV/0! | BO8: =Water!X10 -> 1245.84 | BP8: =Water!Y10 -> 6.1675248 | BQ8: =Water!Z10 -> #DIV/0!
A9: 5 | B9: 31200 | C9: =Elect!J10 -> 6773 | D9: 0 | E9: =Elect!M10 -> 2435 | F9: 20 | G9: =Elect!O10 -> 2180 | H9: 789 | I9: =Water!C11 -> 110.2 | J9: 0 | K9: =Water!E11 -> 121.8 | L9: 0 | M9: =Water!#REF! -> #REF! | N9: =Water!#REF! -> #REF! | O9: 1003 | P9: =Water!H11 -> 352.06 | Q9: 102 | R9: =Water!O11 -> 0 | S9: 8 | T9: =Water!#REF! -> #REF! | U9: 130 | V9: =Water!#REF! -> #REF! | W9: 735 | X9: =Water!Q11 -> 204.1948 | Y9: 0 | Z9: =Water!#REF! -> #REF! | AA9: 0 | AB9: 0 | AC9: 640 | AD9: =Water!#REF! -> #REF! | AE9: =Water!#REF! -> #REF! | AF9: =Water!#REF! -> #REF! | AG9: =Gas!B11 -> 8461649 | AH9: =Gas!C11 -> 1557.14 | AI9: =Gas!#REF! -> #REF! | AJ9: =Gas!J11 -> 354.9 | AK9: =Gas!#REF! -> #REF! | AL9: =Gas!#REF! -> #REF! | AM9: =Gas!#REF! -> #REF! | AN9: =Gas!#REF! -> #REF! | AO9: =Gas!#REF! -> #REF! | AP9: =Gas!#REF! -> #REF! | AQ9: =Gas!#REF! -> #REF! | AR9: =Gas!#REF! -> #REF! | AS9: =Gas!#REF! -> #REF! | AT9: =Elect!BR10 -> 151 | AU9: =Elect!BP10 -> 130 | AX9: 49.840256 | AY9: 25.181598 | AZ9: 8299.2754 | BA9: 13.257628 | BB9: 6.698366 | BC9: =Elect!BQ10 -> 567138 | BD9: =Elect!#REF! -> #REF! | BE9: =Elect!#REF! -> #REF! | BF9: =Elect!#REF! -> #REF! | BG9: =Elect!#REF! -> #REF! | BH9: 1.1980831 | BI9: 0.60532688 | BJ9: 4506.2904 | BK9: 7.198547 | BL9: 3.6370383 | BM9: =Water!U11 -> 1.7962245 | BN9: =Water!W11 -> #DIV/0! | BO9: =Water!X11 -> 1408.24 | BP9: =Water!Y11 -> 7.184898 | BQ9: =Water!Z11 -> #DIV/0!
A10: 6 | B10: 33600 | C10: =Elect!J11 -> 6934 | D10: 0 | E10: =Elect!M11 -> 1943 | F10: 20 | G10: =Elect!O11 -> 1857 | H10: 805 | I10: =Water!C12 -> 116 | J10: 0 | K10: =Water!E12 -> 139.2 | L10: 0 | M10: =Water!#REF! -> #REF! | N10: =Water!#REF! -> #REF! | O10: 1004 | P10: =Water!H12 -> 359.6 | Q10: 115 | R10: =Water!O12 -> 0 | S10: 21 | T10: =Water!#REF! -> #REF! | U10: 141 | V10: =Water!#REF! -> #REF! | W10: 725 | X10: =Water!Q12 -> 208.568 | Y10: 0 | Z10: =Water!#REF! -> #REF! | AA10: 0 | AB10: 0 | AC10: 510 | AD10: =Water!#REF! -> #REF! | AE10: =Water!#REF! -> #REF! | AF10: =Water!#REF! -> #REF! | AG10: =Gas!B12 -> 8463299 | AH10: =Gas!C12 -> 1749 | AI10: =Gas!#REF! -> #REF! | AJ10: =Gas!J12 -> 323.7 | AK10: =Gas!#REF! -> #REF! | AL10: =Gas!#REF! -> #REF! | AM10: =Gas!#REF! -> #REF! | AN10: =Gas!#REF! -> #REF! | AO10: =Gas!#REF! -> #REF! | AP10: =Gas!#REF! -> #REF! | AQ10: =Gas!#REF! -> #REF! | AR10: =Gas!#REF! -> #REF! | AS10: =Gas!#REF! -> #REF! | AT10: =Elect!BR11 -> 144 | AU10: =Elect!BP11 -> 152 | AX10: 47.457627 | AY10: 23.512946 | AZ10: 8835.4834 | BA10: 12.479496 | BB10: 6.1829835 | BC10: =Elect!BQ11 -> 567282 | BD10: =Elect!#REF! -> #REF! | BE10: =Elect!#REF! -> #REF! | BF10: =Elect!#REF! -> #REF! | BG10: =Elect!#REF! -> #REF! | BH10: 1.1567797 | BI10: 0.57312806 | BJ10: 4597.6727 | BK10: 6.4938881 | BL10: 3.2174057 | BM10: =Water!U12 -> 1.6803738 | BN10: =Water!W12 -> #DIV/0! | BO10: =Water!X12 -> 1438.4 | BP10: =Water!Y12 -> 6.7214953 | BQ10: =Water!Z12 -> #DIV/0!
A11: 7 | B11: 31200 | C11: =Elect!J12 -> 7377 | D11: 0 | E11: =Elect!M12 -> 2115 | F11: 20 | G11: =Elect!O12 -> 1832 | H11: 871 | I11: =Water!C13 -> 139.2 | J11: 0 | K11: =Water!E13 -> 168.2 | L11: 0 | M11: =Water!#REF! -> #REF! | N11: =Water!#REF! -> #REF! | O11: 837 | P11: =Water!H13 -> 418.18 | Q11: 113 | R11: =Water!O13 -> 0 | S11: 1 | T11: =Water!#REF! -> #REF! | U11: 151 | V11: =Water!#REF! -> #REF! | W11: 732 | X11: =Water!Q13 -> 242.5444 | Y11: 0 | Z11: =Water!#REF! -> #REF! | AA11: 0 | AB11: 0 | AC11: 1010 | AD11: =Water!#REF! -> #REF! | AE11: =Water!#REF! -> #REF! | AF11: =Water!#REF! -> #REF! | AG11: =Gas!B13 -> 8464878 | AH11: =Gas!C13 -> 1673.74 | AI11: =Gas!#REF! -> #REF! | AJ11: =Gas!J13 -> 413.4 | AK11: =Gas!#REF! -> #REF! | AL11: =Gas!#REF! -> #REF! | AM11: =Gas!#REF! -> #REF! | AN11: =Gas!#REF! -> #REF! | AO11: =Gas!#REF! -> #REF! | AP11: =Gas!#REF! -> #REF! | AQ11: =Gas!#REF! -> #REF! | AR11: =Gas!#REF! -> #REF! | AS11: =Gas!#REF! -> #REF! | AT11: =Elect!BR12 -> 135 | AU11: =Elect!BP12 -> 139 | AX11: 43.454039 | AY11: 21.517241 | AZ11: 8299.2754 | BA11: 11.558879 | BB11: 5.7236382 | BC11: =Elect!BQ12 -> 567417 | BD11: =Elect!#REF! -> #REF! | BE11: =Elect!#REF! -> #REF! | BF11: =Elect!#REF! -> #REF! | BG11: =Elect!#REF! -> #REF! | BH11: 1.1713092 | BI11: 0.58 | BJ11: 4974.6248 | BK11: 6.9284468 | BL11: 3.4307757 | BM11: =Water!U13 -> 1.646378 | BN11: =Water!W13 -> #DIV/0! | BO11: =Water!X13 -> 1672.72 | BP11: =Water!Y13 -> 6.5855118 | BQ11: =Water!Z13 -> #DIV/0!
A12: 8 | B12: 33600 | C12: =Elect!J13 -> 5450 | D12: 0 | E12: =Elect!M13 -> 2125 | F12: 20 | G12: =Elect!O13 -> 2113 | H12: 963 | I12: =Water!C14 -> 139.2 | J12: 0 | K12: =Water!E14 -> 174 | L12: 0 | M12: =Water!#REF! -> #REF! | N12: =Water!#REF! -> #REF! | O12: 1000 | P12: =Water!H14 -> 425.72 | Q12: 128 | R12: =Water!O14 -> 0 | S12: 24 | T12: =Water!#REF! -> #REF! | U12: 148 | V12: =Water!#REF! -> #REF! | W12: 719 | X12: =Water!Q14 -> 246.9176 | Y12: 0 | Z12: =Water!#REF! -> #REF! | AA12: 0 | AB12: 0 | AC12: 630 | AD12: =Water!#REF! -> #REF! | AE12: =Water!#REF! -> #REF! | AF12: =Water!#REF! -> #REF! | AG12: =Gas!B14 -> 8466522 | AH12: =Gas!C14 -> 1742.64 | AI12: =Gas!#REF! -> #REF! | AJ12: =Gas!J14 -> 351 | AK12: =Gas!#REF! -> #REF! | AL12: =Gas!#REF! -> #REF! | AM12: =Gas!#REF! -> #REF! | AN12: =Gas!#REF! -> #REF! | AO12: =Gas!#REF! -> #REF! | AP12: =Gas!#REF! -> #REF! | AQ12: =Gas!#REF! -> #REF! | AR12: =Gas!#REF! -> #REF! | AS12: =Gas!#REF! -> #REF! | AT12: =Elect!BR13 -> 93 | AU12: =Elect!BP13 -> 94 | AX12: 48.837209 | AY12: 24.086022 | AZ12: 8835.4834 | BA12: 12.842272 | BB12: 6.3336799 | BC12: =Elect!BQ13 -> 567510 | BD12: =Elect!#REF! -> #REF! | BE12: =Elect!#REF! -> #REF! | BF12: =Elect!#REF! -> #REF! | BG12: =Elect!#REF! -> #REF! | BH12: 1.2194767 | BI12: 0.60143369 | BJ12: 5500.0731 | BK12: 7.9942923 | BL12: 3.9427047 | BM12: =Water!U14 -> 1.7812552 | BN12: =Water!W14 -> #DIV/0! | BO12: =Water!X14 -> 1702.88 | BP12: =Water!Y14 -> 7.1250209 | BQ12: =Water!Z14 -> #DIV/0!
A13: 9 | B13: 33600 | C13: =Elect!J14 -> 6568 | D13: 0 | E13: =Elect!M14 -> 2906 | F13: 20 | G13: =Elect!O14 -> 3150 | H13: 790 | I13: =Water!C15 -> 150.8 | J13: 0 | K13: =Water!E15 -> 179.8 | L13: 0 | M13: =Water!#REF! -> #REF! | N13: =Water!#REF! -> #REF! | O13: 841 | P13: =Water!H15 -> 441.38 | Q13: 127 | R13: =Water!O15 -> 0 | S13: 21 | T13: =Water!#REF! -> #REF! | U13: 139 | V13: =Water!#REF! -> #REF! | W13: 701 | X13: =Water!Q15 -> 256.0004 | Y13: 0 | Z13: =Water!#REF! -> #REF! | AA13: 0 | AB13: 0 | AC13: 440 | AD13: =Water!#REF! -> #REF! | AE13: =Water!#REF! -> #REF! | AF13: =Water!#REF! -> #REF! | AG13: =Gas!B15 -> 8468168 | AH13: =Gas!C15 -> 1744.76 | AI13: =Gas!#REF! -> #REF! | AJ13: =Gas!J15 -> 432.9 | AK13: =Gas!#REF! -> #REF! | AL13: =Gas!#REF! -> #REF! | AM13: =Gas!#REF! -> #REF! | AN13: =Gas!#REF! -> #REF! | AO13: =Gas!#REF! -> #REF! | AP13: =Gas!#REF! -> #REF! | AQ13: =Gas!#REF! -> #REF! | AR13: =Gas!#REF! -> #REF! | AS13: =Gas!#REF! -> #REF! | AT13: =Elect!BR14 -> 130 | AU13: =Elect!BP14 -> 124 | AX13: 49.194729 | AY13: 24.1033 | AZ13: 8835.4834 | BA13: 12.936286 | BB13: 6.3382234 | BC13: =Elect!BQ14 -> 567640 | BD13: =Elect!#REF! -> #REF! | BE13: =Elect!#REF! -> #REF! | BF13: =Elect!#REF! -> #REF! | BG13: =Elect!#REF! -> #REF! | BH13: 1.1903367 | BI13: 0.58321377 | BJ13: 4512.0018 | BK13: 6.606152 | BL13: 3.2367301 | BM13: =Water!U15 -> 2.0062727 | BN13: =Water!W15 -> #DIV/0! | BO13: =Water!X15 -> 1765.52 | BP13: =Water!Y15 -> 8.0250909 | BQ13: =Water!Z15 -> #DIV/0!
A14: 10 | B14: 31200 | C14: =Elect!J15 -> 4747 | D14: 0 | E14: =Elect!M15 -> 2190 | F14: 20 | G14: =Elect!O15 -> 2281 | H14: 792 | I14: =Water!C16 -> 139.2 | J14: 0 | K14: =Water!E16 -> 168.2 | L14: 0 | M14: =Water!#REF! -> #REF! | N14: =Water!#REF! -> #REF! | O14: 972 | P14: =Water!H16 -> 412.96 | Q14: 126 | R14: =Water!O16 -> 0 | S14: 18 | T14: =Water!#REF! -> #REF! | U14: 145 | V14: =Water!#REF! -> #REF! | W14: 756 | X14: =Water!Q16 -> 239.5168 | Y14: 0 | Z14: =Water!#REF! -> #REF! | AA14: 0 | AB14: 0 | AC14: 580 | AD14: =Water!#REF! -> #REF! | AE14: =Water!#REF! -> #REF! | AF14: =Water!#REF! -> #REF! | AG14: =Gas!B16 -> 8469842 | AH14: =Gas!C16 -> 1774.44 | AI14: =Gas!#REF! -> #REF! | AJ14: =Gas!J16 -> 386.1 | AK14: =Gas!#REF! -> #REF! | AL14: =Gas!#REF! -> #REF! | AM14: =Gas!#REF! -> #REF! | AN14: =Gas!#REF! -> #REF! | AO14: =Gas!#REF! -> #REF! | AP14: =Gas!#REF! -> #REF! | AQ14: =Gas!#REF! -> #REF! | AR14: =Gas!#REF! -> #REF! | AS14: =Gas!#REF! -> #REF! | AT14: =Elect!BR15 -> 131 | AU14: =Elect!BP15 -> 102 | AX14: 49.52381 | AY14: 24.781573 | AZ14: 8299.2754 | BA14: 13.173453 | BB14: 6.5919582 | BC14: =Elect!BQ15 -> 567771 | BD14: =Elect!#REF! -> #REF! | BE14: =Elect!#REF! -> #REF! | BF14: =Elect!#REF! -> #REF! | BG14: =Elect!#REF! -> #REF! | BH14: 1.2730159 | BI14: 0.6370135 | BJ14: 4469.9646 | BK14: 7.0951819 | BL14: 3.5504087 | BM14: =Water!U16 -> 2.2322162 | BN14: =Water!W16 -> #DIV/0! | BO14: =Water!X16 -> 1651.84 | BP14: =Water!Y16 -> 8.9288649 | BQ14: =Water!Z16 -> #DIV/0!
A15: 11 | B15: 33600 | C15: =Elect!J16 -> 8905 | D15: 0 | E15: =Elect!M16 -> 1993 | F15: 20 | G15: =Elect!O16 -> 2111 | H15: 817 | I15: =Water!C17 -> 145 | J15: 0 | K15: =Water!E17 -> 174.58 | L15: 0 | M15: =Water!#REF! -> #REF! | N15: =Water!#REF! -> #REF! | O15: 875 | P15: =Water!H17 -> 432.274 | Q15: 122 | R15: =Water!O17 -> 0 | S15: 20 | T15: =Water!#REF! -> #REF! | U15: 156 | V15: =Water!#REF! -> #REF! | W15: 712 | X15: =Water!Q17 -> 250.71892 | Y15: 0 | Z15: =Water!#REF! -> #REF! | AA15: 0 | AB15: 0 | AC15: 850 | AD15: =Water!#REF! -> #REF! | AE15: =Water!#REF! -> #REF! | AF15: =Water!#REF! -> #REF! | AG15: =Gas!#REF! -> #REF! | AH15: =Gas!C17 -> 1743.7 | AI15: =Gas!#REF! -> #REF! | AJ15: =Gas!J17 -> 391.95 | AK15: =Gas!#REF! -> #REF! | AL15: =Gas!#REF! -> #REF! | AM15: =Gas!#REF! -> #REF! | AN15: =Gas!#REF! -> #REF! | AO15: =Gas!#REF! -> #REF! | AP15: =Gas!#REF! -> #REF! | AQ15: =Gas!#REF! -> #REF! | AR15: =Gas!#REF! -> #REF! | AS15: =Gas!#REF! -> #REF! | AT15: =Elect!BR16 -> 127 | AU15: =Elect!BP16 -> 120 | AX15: 53.333333 | AY15: 26.751592 | AZ15: 8835.4834 | BA15: 14.024577 | BB15: 7.0346206 | BC15: =Elect!BQ16 -> 567898 | BD15: =Elect!#REF! -> #REF! | BE15: =Elect!#REF! -> #REF! | BF15: =Elect!#REF! -> #REF! | BG15: =Elect!#REF! -> #REF! | BH15: 1.3460317 | BI15: 0.67515924 | BJ15: 4666.2095 | BK15: 7.4066817 | BL15: 3.7151349 | BM15: =Water!U17 -> 2.7709872 | BN15: =Water!W17 -> #DIV/0! | BO15: =Water!X17 -> 1729.096 | BP15: =Water!Y17 -> 11.083949 | BQ15: =Water!Z17 -> #DIV/0!
A16: 12 | B16: 33600 | C16: =Elect!J17 -> 5252 | D16: 0 | E16: =Elect!M17 -> 2779 | F16: 20 | G16: =Elect!O17 -> 2549 | H16: 907 | I16: =Water!C18 -> 143.84 | J16: 0 | K16: =Water!E18 -> 173.42 | L16: 0 | M16: =Water!#REF! -> #REF! | N16: =Water!#REF! -> #REF! | O16: 965 | P16: =Water!H18 -> 427.518 | Q16: 125 | R16: =Water!O18 -> 0 | S16: 4 | T16: =Water!#REF! -> #REF! | U16: 167 | V16: =Water!#REF! -> #REF! | W16: 705 | X16: =Water!Q18 -> 247.96044 | Y16: 0 | Z16: =Water!#REF! -> #REF! | AA16: 0 | AB16: 0 | AC16: 880 | AD16: =Water!#REF! -> #REF! | AE16: =Water!#REF! -> #REF! | AF16: =Water!#REF! -> #REF! | AG16: =Gas!B18 -> 8473140.8 | AH16: =Gas!C18 -> 1753.028 | AI16: =Gas!#REF! -> #REF! | AJ16: =Gas!J18 -> 394.29 | AK16: =Gas!#REF! -> #REF! | AL16: =Gas!#REF! -> #REF! | AM16: =Gas!#REF! -> #REF! | AN16: =Gas!#REF! -> #REF! | AO16: =Gas!#REF! -> #REF! | AP16: =Gas!#REF! -> #REF! | AQ16: =Gas!#REF! -> #REF! | AR16: =Gas!#REF! -> #REF! | AS16: =Gas!#REF! -> #REF! | AT16: =Elect!BR17 -> 146 | AU16: =Elect!BP17 -> 138 | AX16: 50.45045 | AY16: 25.339367 | AZ16: 8835.4834 | BA16: 13.266492 | BB16: 6.6632605 | BC16: =Elect!BQ17 -> 568044 | BD16: =Elect!#REF! -> #REF! | BE16: =Elect!#REF! -> #REF! | BF16: =Elect!#REF! -> #REF! | BG16: =Elect!#REF! -> #REF! | BH16: 1.2162162 | BI16: 0.61085973 | BJ16: 5180.235 | BK16: 7.7781306 | BL16: 3.9066629 | BM16: =Water!U18 -> 2.1483317 | BN16: =Water!W18 -> #DIV/0! | BO16: =Water!X18 -> 1710.072 | BP16: =Water!Y18 -> 8.5933266 | BQ16: =Water!Z18 -> #DIV/0!
A17: 13 | B17: 31200 | C17: =Elect!J18 -> 8745 | D17: 0 | E17: =Elect!M18 -> 2297 | F17: 20 | G17: =Elect!O18 -> 2196 | H17: 812 | I17: =Water!C19 -> 111.36 | J17: 0 | K17: =Water!E19 -> 133.4 | L17: 0 | M17: =Water!#REF! -> #REF! | N17: =Water!#REF! -> #REF! | O17: 822 | P17: =Water!H19 -> 310.068 | Q17: 123 | R17: =Water!O19 -> 0 | S17: 7 | T17: =Water!#REF! -> #REF! | U17: 163 | V17: =Water!#REF! -> #REF! | W17: 692 | X17: =Water!Q19 -> 179.83944 | Y17: 0 | Z17: =Water!#REF! -> #REF! | AA17: 0 | AB17: 0 | AC17: 460 | AD17: =Water!#REF! -> #REF! | AE17: =Water!#REF! -> #REF! | AF17: =Water!#REF! -> #REF! | AG17: =Gas!B19 -> 8474563 | AH17: =Gas!C19 -> 1507.532 | AI17: =Gas!#REF! -> #REF! | AJ17: =Gas!J19 -> 313.56 | AK17: =Gas!#REF! -> #REF! | AL17: =Gas!#REF! -> #REF! | AM17: =Gas!#REF! -> #REF! | AN17: =Gas!#REF! -> #REF! | AO17: =Gas!#REF! -> #REF! | AP17: =Gas!#REF! -> #REF! | AQ17: =Gas!#REF! -> #REF! | AR17: =Gas!#REF! -> #REF! | AS17: =Gas!#REF! -> #REF! | AT17: =Elect!BR18 -> 104 | AU17: =Elect!BP18 -> 103 | AX17: 46.567164 | AY17: 23.214286 | AZ17: 8299.2754 | BA17: 12.386978 | BB17: 6.1750561 | BC17: =Elect!BQ18 -> 568148 | BD17: =Elect!#REF! -> #REF! | BE17: =Elect!#REF! -> #REF! | BF17: =Elect!#REF! -> #REF! | BG17: =Elect!#REF! -> #REF! | BH17: 1.0850746 | BI17: 0.54092262 | BJ17: 4637.6525 | BK17: 6.9218694 | BL17: 3.4506343 | BM17: =Water!U19 -> 1.4625849 | BN17: =Water!W19 -> #DIV/0! | BO17: =Water!X19 -> 1240.272 | BP17: =Water!Y19 -> 5.8503396 | BQ17: =Water!Z19 -> #DIV/0!
A18: 14 | B18: 33600 | C18: =Elect!J19 -> 5469 | D18: 0 | E18: =Elect!M19 -> 2371 | F18: 30 | G18: =Elect!O19 -> 2389 | H18: 810 | I18: =Water!C20 -> 133.4 | J18: 0 | K18: =Water!E20 -> 162.4 | L18: 0 | M18: =Water!#REF! -> #REF! | N18: =Water!#REF! -> #REF! | O18: 943 | P18: =Water!H20 -> 437.9 | Q18: 118 | R18: =Water!O20 -> 0 | S18: 18 | T18: =Water!#REF! -> #REF! | U18: 152 | V18: =Water!#REF! -> #REF! | W18: 708 | X18: =Water!Q20 -> 253.982 | Y18: 0 | Z18: =Water!#REF! -> #REF! | AA18: 0 | AB18: 0 | AC18: 490 | AD18: =Water!#REF! -> #REF! | AE18: =Water!#REF! -> #REF! | AF18: =Water!#REF! -> #REF! | AG18: =Gas!B20 -> 8476134 | AH18: =Gas!C20 -> 1665.26 | AI18: =Gas!#REF! -> #REF! | AJ18: =Gas!J20 -> 436.8 | AK18: =Gas!#REF! -> #REF! | AL18: =Gas!#REF! -> #REF! | AM18: =Gas!#REF! -> #REF! | AN18: =Gas!#REF! -> #REF! | AO18: =Gas!#REF! -> #REF! | AP18: =Gas!#REF! -> #REF! | AQ18: =Gas!#REF! -> #REF! | AR18: =Gas!#REF! -> #REF! | AS18: =Gas!#REF! -> #REF! | AT18: =Elect!BR19 -> 121 | AU18: =Elect!BP19 -> 126 | AX18: 47.795164 | AY18: 24.207493 | AZ18: 8835.4834 | BA18: 12.568255 | BB18: 6.3656221 | BC18: =Elect!BQ6 -> 566573 | BD18: =Elect!#REF! -> #REF! | BE18: =Elect!#REF! -> #REF! | BF18: =Elect!#REF! -> #REF! | BG18: =Elect!#REF! -> #REF! | BH18: 1.1024182 | BI18: 0.55835735 | BJ18: 4626.2297 | BK18: 6.5806966 | BL18: 3.3330185 | BM18: =Water!U20 -> 1.839916 | BN18: =Water!W20 -> #DIV/0! | BO18: =Water!X20 -> 1751.6 | BP18: =Water!Y20 -> 7.3596639 | BQ18: =Water!Z20 -> #DIV/0!
A19: 15 | B19: 31200 | C19: =Elect!J20 -> 6355 | D19: 0 | E19: =Elect!M20 -> 2093 | F19: 20 | G19: =Elect!O20 -> 2105 | H19: 841 | I19: =Water!C21 -> 127.6 | J19: 0 | K19: =Water!E21 -> 145 | L19: 0 | M19: =Water!#REF! -> #REF! | N19: =Water!#REF! -> #REF! | O19: 947 | P19: =Water!H21 -> 388.6 | Q19: 131 | R19: =Water!O21 -> 0 | S19: 23 | T19: =Water!#REF! -> #REF! | U19: 166 | V19: =Water!#REF! -> #REF! | W19: 787 | X19: =Water!Q21 -> 225.388 | Y19: 0 | Z19: =Water!#REF! -> #REF! | AA19: 0 | AB19: 0 | AC19: 730 | AD19: =Water!#REF! -> #REF! | AE19: =Water!#REF! -> #REF! | AF19: =Water!#REF! -> #REF! | AG19: =Gas!B21 -> 8477679 | AH19: =Gas!C21 -> 1637.7 | AI19: =Gas!#REF! -> #REF! | AJ19: =Gas!J21 -> 386.1 | AK19: =Gas!#REF! -> #REF! | AL19: =Gas!#REF! -> #REF! | AM19: =Gas!#REF! -> #REF! | AN19: =Gas!#REF! -> #REF! | AO19: =Gas!#REF! -> #REF! | AP19: =Gas!#REF! -> #REF! | AQ19: =Gas!#REF! -> #REF! | AR19: =Gas!#REF! -> #REF! | AS19: =Gas!#REF! -> #REF! | AT19: =Elect!BR20 -> 115 | AU19: =Elect!BP20 -> 113 | AX19: 41.6 | AY19: 20.995962 | AZ19: 8299.2754 | BA19: 11.065701 | BB19: 5.5849767 | BC19: =Elect!BQ20 -> 568384 | BD19: =Elect!#REF! -> #REF! | BE19: =Elect!#REF! -> #REF! | BF19: =Elect!#REF! -> #REF! | BG19: =Elect!#REF! -> #REF! | BH19: 1.1506667 | BI19: 0.58114478 | BJ19: 4803.283 | BK19: 6.4043773 | BL19: 3.234534 | BM19: =Water!U21 -> 1.6969432 | BN19: =Water!W21 -> #DIV/0! | BO19: =Water!X21 -> 1554.4 | BP19: =Water!Y21 -> 6.7877729 | BQ19: =Water!Z21 -> #DIV/0!
A20: 16 | B20: 36000 | C20: =Elect!J21 -> 6678 | D20: 0 | E20: =Elect!M21 -> 2857 | F20: 20 | G20: =Elect!O21 -> 2801 | H20: 932 | I20: =Water!C22 -> 87 | J20: 0 | K20: =Water!E22 -> 104.4 | L20: 0 | M20: =Water!#REF! -> #REF! | N20: =Water!#REF! -> #REF! | O20: 998 | P20: =Water!H22 -> 305.66 | Q20: 136 | R20: =Water!O22 -> 0 | S20: 22 | T20: =Water!#REF! -> #REF! | U20: 162 | V20: =Water!#REF! -> #REF! | W20: 703 | X20: =Water!Q22 -> 177.2828 | Y20: 0 | Z20: =Water!#REF! -> #REF! | AA20: 0 | AB20: 0 | AC20: 600 | AD20: =Water!#REF! -> #REF! | AE20: =Water!#REF! -> #REF! | AF20: =Water!#REF! -> #REF! | AG20: =Gas!B22 -> 8479262 | AH20: =Gas!C22 -> 1677.98 | AI20: =Gas!#REF! -> #REF! | AJ20: =Gas!J22 -> 382.2 | AK20: =Gas!#REF! -> #REF! | AL20: =Gas!#REF! -> #REF! | AM20: =Gas!#REF! -> #REF! | AN20: =Gas!#REF! -> #REF! | AO20: =Gas!#REF! -> #REF! | AP20: =Gas!#REF! -> #REF! | AQ20: =Gas!#REF! -> #REF! | AR20: =Gas!#REF! -> #REF! | AS20: =Gas!#REF! -> #REF! | AT20: =Elect!BR21 -> 129 | AU20: =Elect!BP21 -> 140 | AX20: 48 | AY20: 24.22611 | AZ20: 9371.6914 | BA20: 12.495589 | BB20: 6.3066564 | BC20: =Elect!BQ21 -> 568513 | BD20: =Elect!#REF! -> #REF! | BE20: =Elect!#REF! -> #REF! | BF20: =Elect!#REF! -> #REF! | BG20: =Elect!#REF! -> #REF! | BH20: 1.1626667 | BI20: 0.58720539 | BJ20: 5323.0199 | BK20: 7.0973598 | BL20: 3.5845252 | BM20: =Water!U22 -> 1.4350235 | BN20: =Water!W22 -> #DIV/0! | BO20: =Water!X22 -> 1222.64 | BP20: =Water!Y22 -> 5.7400939 | BQ20: =Water!Z22 -> #DIV/0!
A21: 17 | B21: 33600 | C21: =Elect!J22 -> 6754 | D21: 0 | E21: =Elect!M22 -> 2027 | F21: 20 | G21: =Elect!O22 -> 2047 | H21: 972 | I21: =Water!C23 -> 98.6 | J21: 0 | K21: =Water!E23 -> 110.2 | L21: 0 | M21: =Water!#REF! -> #REF! | N21: =Water!#REF! -> #REF! | O21: 998 | P21: =Water!H23 -> 325.38 | Q21: 136 | R21: =Water!O23 -> 0 | S21: 38 | T21: =Water!#REF! -> #REF! | U21: 137 | V21: =Water!#REF! -> #REF! | W21: 740 | X21: =Water!Q23 -> 188.7204 | Y21: 0 | Z21: =Water!#REF! -> #REF! | AA21: 0 | AB21: 0 | AC21: 690 | AD21: =Water!#REF! -> #REF! | AE21: =Water!#REF! -> #REF! | AF21: =Water!#REF! -> #REF! | AG21: =Gas!B23 -> 8481323 | AH21: =Gas!C23 -> 2184.66 | AI21: =Gas!#REF! -> #REF! | AJ21: =Gas!J23 -> 354.9 | AK21: =Gas!#REF! -> #REF! | AL21: =Gas!#REF! -> #REF! | AM21: =Gas!#REF! -> #REF! | AN21: =Gas!#REF! -> #REF! | AO21: =Gas!#REF! -> #REF! | AP21: =Gas!#REF! -> #REF! | AQ21: =Gas!#REF! -> #REF! | AR21: =Gas!#REF! -> #REF! | AS21: =Gas!#REF! -> #REF! | AT21: =Elect!BR22 -> 129 | AU21: =Elect!BP22 -> 131 | AX21: 44.385733 | AY21: 22.207535 | AZ21: 8835.4834 | BA21: 11.671709 | BB21: 5.8397115 | BC21: =Elect!#REF! -> #REF! | BD21: =Elect!#REF! -> #REF! | BE21: =Elect!#REF! -> #REF! | BF21: =Elect!#REF! -> #REF! | BG21: =Elect!#REF! -> #REF! | BH21: 1.1770145 | BI21: 0.58889623 | BJ21: 5551.4757 | BK21: 7.3335213 | BL21: 3.6691842 | BM21: =Water!U23 -> 1.6433333 | BN21: =Water!W23 -> #DIV/0! | BO21: =Water!X23 -> 1301.52 | BP21: =Water!Y23 -> 6.5733333 | BQ21: =Water!Z23 -> #DIV/0!
A22: 18 | B22: 33600 | C22: =Elect!J23 -> 7905 | D22: 0 | E22: =Elect!M23 -> 2478 | F22: 20 | G22: =Elect!O23 -> 2489 | H22: 864 | I22: =Water!C24 -> 110.2 | J22: 0 | K22: =Water!E24 -> 121.8 | L22: 0 | M22: =Water!#REF! -> #REF! | N22: =Water!#REF! -> #REF! | O22: 1002 | P22: =Water!H24 -> 366.56 | Q22: 118 | R22: =Water!O24 -> 0 | S22: 21 | T22: =Water!#REF! -> #REF! | U22: 133 | V22: =Water!#REF! -> #REF! | W22: 769 | X22: =Water!Q24 -> 212.6048 | Y22: 0 | Z22: =Water!#REF! -> #REF! | AA22: 0 | AB22: 0 | AC22: 930 | AD22: =Water!#REF! -> #REF! | AE22: =Water!#REF! -> #REF! | AF22: =Water!#REF! -> #REF! | AG22: =Gas!B24 -> 8482592 | AH22: =Gas!C24 -> 1345.14 | AI22: =Gas!#REF! -> #REF! | AJ22: =Gas!J24 -> 397.8 | AK22: =Gas!#REF! -> #REF! | AL22: =Gas!#REF! -> #REF! | AM22: =Gas!#REF! -> #REF! | AN22: =Gas!#REF! -> #REF! | AO22: =Gas!#REF! -> #REF! | AP22: =Gas!#REF! -> #REF! | AQ22: =Gas!#REF! -> #REF! | AR22: =Gas!#REF! -> #REF! | AS22: =Gas!#REF! -> #REF! | AT22: =Elect!BR23 -> 122 | AU22: =Elect!BP23 -> 130 | AX22: 44.680851 | AY22: 22.459893 | AZ22: 8835.4834 | BA22: 11.749313 | BB22: 5.9060718 | BC22: =Elect!BQ23 -> 568764 | BD22: =Elect!#REF! -> #REF! | BE22: =Elect!#REF! -> #REF! | BF22: =Elect!#REF! -> #REF! | BG22: =Elect!#REF! -> #REF! | BH22: 1.1236702 | BI22: 0.56483957 | BJ22: 4934.645 | BK22: 6.562028 | BL22: 3.2985595 | BM22: =Water!U24 -> 2.1562353 | BN22: =Water!W24 -> #DIV/0! | BO22: =Water!X24 -> 1466.24 | BP22: =Water!Y24 -> 8.6249412 | BQ22: =Water!Z24 -> #DIV/0!
A23: 19 | B23: 33600 | C23: =Elect!J24 -> 4666 | D23: 0 | E23: =Elect!M24 -> 1855 | F23: 30 | G23: =Elect!O24 -> 1884 | H23: 894 | I23: =Water!C25 -> 81.2 | J23: 0 | K23: =Water!E25 -> 92.8 | L23: 0 | M23: =Water!#REF! -> #REF! | N23: =Water!#REF! -> #REF! | O23: 944 | P23: =Water!H25 -> 276.66 | Q23: 110 | R23: =Water!O25 -> 0 | S23: 14 | T23: =Water!#REF! -> #REF! | U23: 155 | V23: =Water!#REF! -> #REF! | W23: 721 | X23: =Water!Q25 -> 160.4628 | Y23: 0 | Z23: =Water!#REF! -> #REF! | AA23: 0 | AB23: 0 | AC23: 660 | AD23: =Water!#REF! -> #REF! | AE23: =Water!#REF! -> #REF! | AF23: =Water!#REF! -> #REF! | AG23: =Gas!B25 -> 8483992 | AH23: =Gas!C25 -> 1484 | AI23: =Gas!#REF! -> #REF! | AJ23: =Gas!J25 -> 319.8 | AK23: =Gas!#REF! -> #REF! | AL23: =Gas!#REF! -> #REF! | AM23: =Gas!#REF! -> #REF! | AN23: =Gas!#REF! -> #REF! | AO23: =Gas!#REF! -> #REF! | AP23: =Gas!#REF! -> #REF! | AQ23: =Gas!#REF! -> #REF! | AR23: =Gas!#REF! -> #REF! | AS23: =Gas!#REF! -> #REF! | AT23: =Elect!BR24 -> 116 | AU23: =Elect!BP24 -> 121 | AX23: 44.8 | AY23: 22.44489 | AZ23: 8835.4834 | BA23: 11.780645 | BB23: 5.9021265 | BC23: =Elect!BQ24 -> 568880 | BD23: =Elect!#REF! -> #REF! | BE23: =Elect!#REF! -> #REF! | BF23: =Elect!#REF! -> #REF! | BG23: =Elect!#REF! -> #REF! | BH23: 1.1346667 | BI23: 0.56847027 | BJ23: 5105.9869 | BK23: 6.8079825 | BL23: 3.4108129 | BM23: =Water!U25 -> 1.3430097 | BN23: =Water!W25 -> #DIV/0! | BO23: =Water!X25 -> 1106.64 | BP23: =Water!Y25 -> 5.3720388 | BQ23: =Water!Z25 -> #DIV/0!
A24: 20 | B24: 33600 | C24: =Elect!J25 -> 6708 | D24: 0 | E24: =Elect!M25 -> 2217 | F24: 20 | G24: =Elect!O25 -> 2328 | H24: 944 | I24: =Water!C26 -> 92.8 | J24: 0 | K24: =Water!E26 -> 104.4 | L24: 0 | M24: =Water!#REF! -> #REF! | N24: =Water!#REF! -> #REF! | O24: 1000 | P24: =Water!H26 -> 312.04 | Q24: 138 | R24: =Water!O26 -> 0 | S24: 15 | T24: =Water!#REF! -> #REF! | U24: 165 | V24: =Water!#REF! -> #REF! | W24: 778 | X24: =Water!Q26 -> 180.9832 | Y24: 0 | Z24: =Water!#REF! -> #REF! | AA24: 0 | AB24: 0 | AC24: 560 | AD24: =Water!#REF! -> #REF! | AE24: =Water!#REF! -> #REF! | AF24: =Water!#REF! -> #REF! | AG24: =Gas!B26 -> 8485406 | AH24: =Gas!C26 -> 1498.84 | AI24: =Gas!#REF! -> #REF! | AJ24: =Gas!J26 -> 327.6 | AK24: =Gas!#REF! -> #REF! | AL24: =Gas!#REF! -> #REF! | AM24: =Gas!#REF! -> #REF! | AN24: =Gas!#REF! -> #REF! | AO24: =Gas!#REF! -> #REF! | AP24: =Gas!#REF! -> #REF! | AQ24: =Gas!#REF! -> #REF! | AR24: =Gas!#REF! -> #REF! | AS24: =Gas!#REF! -> #REF! | AT24: =Elect!BR25 -> 144 | AU24: =Elect!BP25 -> 156 | AX24: 42.857143 | AY24: 21.649485 | AZ24: 8835.4834 | BA24: 11.269749 | BB24: 5.6929661 | BC24: =Elect!BQ25 -> 569024 | BD24: =Elect!#REF! -> #REF! | BE24: =Elect!#REF! -> #REF! | BF24: =Elect!#REF! -> #REF! | BG24: =Elect!#REF! -> #REF! | BH24: 1.1683673 | BI24: 0.59020619 | BJ24: 5391.5566 | BK24: 6.8769855 | BL24: 3.4739411 | BM24: =Water!U26 -> 1.3685965 | BN24: =Water!W26 -> #DIV/0! | BO24: =Water!X26 -> 1248.16 | BP24: =Water!Y26 -> 5.474386 | BQ24: =Water!Z26 -> #DIV/0!
A25: 21 | B25: 36000 | C25: =Elect!J26 -> 5866 | D25: 0 | E25: =Elect!M26 -> 2042 | F25: 20 | G25: =Elect!O26 -> 2446 | H25: 916 | I25: =Water!C27 -> 104.4 | J25: 0 | K25: =Water!E27 -> 110.2 | L25: 0 | M25: =Water!#REF! -> #REF! | N25: =Water!#REF! -> #REF! | O25: 998 | P25: =Water!H27 -> 342.78 | Q25: 186 | R25: =Water!O27 -> 0 | S25: 43 | T25: =Water!#REF! -> #REF! | U25: 176 | V25: =Water!#REF! -> #REF! | W25: 773 | X25: =Water!Q27 -> 198.8124 | Y25: 0 | Z25: =Water!#REF! -> #REF! | AA25: 0 | AB25: 0 | AC25: 950 | AD25: =Water!#REF! -> #REF! | AE25: =Water!#REF! -> #REF! | AF25: =Water!#REF! -> #REF! | AG25: =Gas!B27 -> 8486965 | AH25: =Gas!C27 -> 1652.54 | AI25: =Gas!#REF! -> #REF! | AJ25: =Gas!J27 -> 386.1 | AK25: =Gas!#REF! -> #REF! | AL25: =Gas!#REF! -> #REF! | AM25: =Gas!#REF! -> #REF! | AN25: =Gas!#REF! -> #REF! | AO25: =Gas!#REF! -> #REF! | AP25: =Gas!#REF! -> #REF! | AQ25: =Gas!#REF! -> #REF! | AR25: =Gas!#REF! -> #REF! | AS25: =Gas!#REF! -> #REF! | AT25: =Elect!BR26 -> 93 | AU25: =Elect!BP26 -> 97 | AX25: 43.956044 | AY25: 22.222222 | AZ25: 9371.6914 | BA25: 11.442847 | BB25: 5.7849947 | BC25: =Elect!BQ26 -> 569117 | BD25: =Elect!#REF! -> #REF! | BE25: =Elect!#REF! -> #REF! | BF25: =Elect!#REF! -> #REF! | BG25: =Elect!#REF! -> #REF! | BH25: 1.0586081 | BI25: 0.53518519 | BJ25: 5231.6376 | BK25: 6.3878358 | BL25: 3.2294059 | BM25: =Water!U27 -> 1.3821774 | BN25: =Water!W27 -> #DIV/0! | BO25: =Water!X27 -> 1371.12 | BP25: =Water!Y27 -> 5.5287097 | BQ25: =Water!Z27 -> #DIV/0!
A26: 22 | B26: 33600 | C26: =Elect!J27 -> 6243 | D26: 0 | E26: =Elect!M27 -> 2058 | F26: 20 | G26: =Elect!O27 -> 2450 | H26: 931 | I26: =Water!C28 -> 81.2 | J26: 0 | K26: =Water!E28 -> 98.6 | L26: 0 | M26: =Water!#REF! -> #REF! | N26: =Water!#REF! -> #REF! | O26: 969 | P26: =Water!H28 -> 296.38 | Q26: 151 | R26: =Water!O28 -> 0 | S26: 29 | T26: =Water!#REF! -> #REF! | U26: 157 | V26: =Water!#REF! -> #REF! | W26: 697 | X26: =Water!Q28 -> 171.9004 | Y26: 0 | Z26: =Water!#REF! -> #REF! | AA26: 0 | AB26: 0 | AC26: 700 | AD26: =Water!#REF! -> #REF! | AE26: =Water!#REF! -> #REF! | AF26: =Water!#REF! -> #REF! | AG26: =Gas!B28 -> 8488568 | AH26: =Gas!C28 -> 1699.18 | AI26: =Gas!#REF! -> #REF! | AJ26: =Gas!J28 -> 362.7 | AK26: =Gas!#REF! -> #REF! | AL26: =Gas!#REF! -> #REF! | AM26: =Gas!#REF! -> #REF! | AN26: =Gas!#REF! -> #REF! | AO26: =Gas!#REF! -> #REF! | AP26: =Gas!#REF! -> #REF! | AQ26: =Gas!#REF! -> #REF! | AR26: =Gas!#REF! -> #REF! | AS26: =Gas!#REF! -> #REF! | AT26: =Elect!BR27 -> 156 | AU26: =Elect!BP27 -> 130 | AX26: 39.952438 | AY26: 20.253165 | AZ26: 8835.4834 | BA26: 10.505926 | BB26: 5.3257887 | BC26: =Elect!BQ27 -> 569273 | BD26: =Elect!#REF! -> #REF! | BE26: =Elect!#REF! -> #REF! | BF26: =Elect!#REF! -> #REF! | BG26: =Elect!#REF! -> #REF! | BH26: 1.0903686 | BI26: 0.55274262 | BJ26: 5317.3085 | BK26: 6.3226022 | BL26: 3.2051287 | BM26: =Water!U28 -> 1.3172444 | BN26: =Water!W28 -> #DIV/0! | BO26: =Water!X28 -> 1185.52 | BP26: =Water!Y28 -> 5.2689778 | BQ26: =Water!Z28 -> #DIV/0!
A27: 23 | B27: 36000 | C27: =Elect!J28 -> 6595 | D27: 0 | E27: =Elect!M28 -> 2119 | F27: 30 | G27: =Elect!O28 -> 2604 | H27: 1009 | I27: =Water!C29 -> 98.6 | J27: 0 | K27: =Water!E29 -> 104.4 | L27: 0 | M27: =Water!#REF! -> #REF! | N27: =Water!#REF! -> #REF! | O27: 902 | P27: =Water!H29 -> 316.1 | Q27: 131 | R27: =Water!O29 -> 0 | S27: 6 | T27: =Water!#REF! -> #REF! | U27: 167 | V27: =Water!#REF! -> #REF! | W27: 748 | X27: =Water!Q29 -> 183.338 | Y27: 0 | Z27: =Water!#REF! -> #REF! | AA27: 0 | AB27: 0 | AC27: 690 | AD27: =Water!#REF! -> #REF! | AE27: =Water!#REF! -> #REF! | AF27: =Water!#REF! -> #REF! | AG27: =Gas!B29 -> 8490033 | AH27: =Gas!C29 -> 1552.9 | AI27: =Gas!#REF! -> #REF! | AJ27: =Gas!J29 -> 347.1 | AK27: =Gas!#REF! -> #REF! | AL27: =Gas!#REF! -> #REF! | AM27: =Gas!#REF! -> #REF! | AN27: =Gas!#REF! -> #REF! | AO27: =Gas!#REF! -> #REF! | AP27: =Gas!#REF! -> #REF! | AQ27: =Gas!#REF! -> #REF! | AR27: =Gas!#REF! -> #REF! | AS27: =Gas!#REF! -> #REF! | AT27: =Elect!BR28 -> 116 | AU27: =Elect!BP28 -> 130 | AX27: 42.755344 | AY27: 21.543986 | AZ27: 9371.6914 | BA27: 11.130275 | BB27: 5.6084329 | BC27: =Elect!BQ28 -> 569389 | BD27: =Elect!#REF! -> #REF! | BE27: =Elect!#REF! -> #REF! | BF27: =Elect!#REF! -> #REF! | BG27: =Elect!#REF! -> #REF! | BH27: 1.0712589 | BI27: 0.53979653 | BJ27: 5762.7973 | BK27: 6.8441773 | BL27: 3.4487117 | BM27: =Water!U29 -> 1.5726368 | BN27: =Water!W29 -> #DIV/0! | BO27: =Water!X29 -> 1264.4 | BP27: =Water!Y29 -> 6.2905473 | BQ27: =Water!Z29 -> #DIV/0!
A28: 24 | B28: 33600 | C28: =Elect!J29 -> 6368 | D28: 0 | E28: =Elect!M29 -> 2033 | F28: 20 | G28: =Elect!O29 -> 2384 | H28: 891 | I28: =Water!C30 -> 98.6 | J28: 0 | K28: =Water!E30 -> 116 | L28: 0 | M28: =Water!#REF! -> #REF! | N28: =Water!#REF! -> #REF! | O28: 818 | P28: =Water!H30 -> 335.82 | Q28: 221 | R28: =Water!O30 -> 0 | S28: 93 | T28: =Water!#REF! -> #REF! | U28: 191 | V28: =Water!#REF! -> #REF! | W28: 827 | X28: =Water!Q30 -> 194.7756 | Y28: 0 | Z28: =Water!#REF! -> #REF! | AA28: 0 | AB28: 0 | AC28: 470 | AD28: =Water!#REF! -> #REF! | AE28: =Water!#REF! -> #REF! | AF28: =Water!#REF! -> #REF! | AG28: =Gas!B30 -> 8491568 | AH28: =Gas!C30 -> 1627.1 | AI28: =Gas!#REF! -> #REF! | AJ28: =Gas!J30 -> 357.5 | AK28: =Gas!#REF! -> #REF! | AL28: =Gas!#REF! -> #REF! | AM28: =Gas!#REF! -> #REF! | AN28: =Gas!#REF! -> #REF! | AO28: =Gas!#REF! -> #REF! | AP28: =Gas!#REF! -> #REF! | AQ28: =Gas!#REF! -> #REF! | AR28: =Gas!#REF! -> #REF! | AS28: =Gas!#REF! -> #REF! | AT28: =Elect!BR29 -> 140 | AU28: =Elect!BP29 -> 129 | AX28: 39.904988 | AY28: 20.289855 | AZ28: 8835.4834 | BA28: 10.493448 | BB28: 5.3354369 | BC28: =Elect!BQ29 -> 569529 | BD28: =Elect!#REF! -> #REF! | BE28: =Elect!#REF! -> #REF! | BF28: =Elect!#REF! -> #REF! | BG28: =Elect!#REF! -> #REF! | BH28: 1.1104513 | BI28: 0.56461353 | BJ28: 5088.8527 | BK28: 6.043768 | BL28: 3.0729787 | BM28: =Water!U30 -> 1.7133673 | BN28: =Water!W30 -> #DIV/0! | BO28: =Water!X30 -> 1343.28 | BP28: =Water!Y30 -> 6.8534694 | BQ28: =Water!Z30 -> #DIV/0!
A29: 25 | B29: 33600 | C29: =Elect!J30 -> 6091 | D29: 0 | E29: =Elect!M30 -> 2040 | F29: 20 | G29: =Elect!O30 -> 2380 | H29: 1008 | I29: =Water!C31 -> 87 | J29: 0 | K29: =Water!E31 -> 127.6 | L29: 0 | M29: =Water!#REF! -> #REF! | N29: =Water!#REF! -> #REF! | O29: 1290 | P29: =Water!H31 -> 336.4 | Q29: 34 | R29: =Water!O31 -> 0 | S29: 34 | T29: =Water!#REF! -> #REF! | U29: 55 | V29: =Water!#REF! -> #REF! | W29: 681 | X29: =Water!Q31 -> 195.112 | Y29: 0 | Z29: =Water!#REF! -> #REF! | AA29: 0 | AB29: 0 | AC29: 1170 | AD29: =Water!#REF! -> #REF! | AE29: =Water!#REF! -> #REF! | AF29: =Water!#REF! -> #REF! | AG29: =Gas!B31 -> 8493064 | AH29: =Gas!C31 -> 1585.76 | AI29: =Gas!#REF! -> #REF! | AJ29: =Gas!J31 -> 325 | AK29: =Gas!#REF! -> #REF! | AL29: =Gas!#REF! -> #REF! | AM29: =Gas!#REF! -> #REF! | AN29: =Gas!#REF! -> #REF! | AO29: =Gas!#REF! -> #REF! | AP29: =Gas!#REF! -> #REF! | AQ29: =Gas!#REF! -> #REF! | AR29: =Gas!#REF! -> #REF! | AS29: =Gas!#REF! -> #REF! | AT29: =Elect!BR30 -> 154 | AU29: =Elect!BP30 -> 129 | AX29: 39.763314 | AY29: 20.20445 | AZ29: 8835.4834 | BA29: 10.456193 | BB29: 5.3129786 | BC29: =Elect!BQ30 -> 569683 | BD29: =Elect!#REF! -> #REF! | BE29: =Elect!#REF! -> #REF! | BF29: =Elect!#REF! -> #REF! | BG29: =Elect!#REF! -> #REF! | BH29: 1.0059172 | BI29: 0.51112447 | BJ29: 5757.0859 | BK29: 6.8131194 | BL29: 3.4618676 | BM29: =Water!U31 -> 2.3524476 | BN29: =Water!W31 -> #DIV/0! | BO29: =Water!X31 -> 1345.6 | BP29: =Water!Y31 -> 9.4097902 | BQ29: =Water!Z31 -> #DIV/0!
A30: 26 | B30: 31200 | C30: =Elect!J31 -> 5750 | D30: 0 | E30: =Elect!M31 -> 2062 | F30: 20 | G30: =Elect!O31 -> 2233 | H30: 760 | I30: =Water!C32 -> 127.6 | J30: 0 | K30: =Water!E32 -> 81.2 | L30: 0 | M30: =Water!#REF! -> #REF! | N30: =Water!#REF! -> #REF! | O30: 1004 | P30: =Water!H32 -> 334.66 | Q30: 131 | R30: =Water!O32 -> 0 | S30: 33 | T30: =Water!#REF! -> #REF! | U30: 145 | V30: =Water!#REF! -> #REF! | W30: 916 | X30: =Water!Q32 -> 194.1028 | Y30: 0 | Z30: =Water!#REF! -> #REF! | AA30: 0 | AB30: 0 | AC30: 810 | AD30: =Water!#REF! -> #REF! | AE30: =Water!#REF! -> #REF! | AF30: =Water!#REF! -> #REF! | AG30: =Gas!B32 -> 8494749 | AH30: =Gas!C32 -> 1786.1 | AI30: =Gas!#REF! -> #REF! | AJ30: =Gas!J32 -> 425.1 | AK30: =Gas!#REF! -> #REF! | AL30: =Gas!#REF! -> #REF! | AM30: =Gas!#REF! -> #REF! | AN30: =Gas!#REF! -> #REF! | AO30: =Gas!#REF! -> #REF! | AP30: =Gas!#REF! -> #REF! | AQ30: =Gas!#REF! -> #REF! | AR30: =Gas!#REF! -> #REF! | AS30: =Gas!#REF! -> #REF! | AT30: =Elect!BR31 -> 154 | AU30: =Elect!BP31 -> 129 | AX30: 37.275986 | AY30: 18.989653 | AZ30: 8299.2754 | BA30: 9.9155023 | BB30: 5.0512936 | BC30: =Elect!BQ31 -> 569837 | BD30: =Elect!#REF! -> #REF! | BE30: =Elect!#REF! -> #REF! | BF30: =Elect!#REF! -> #REF! | BG30: =Elect!#REF! -> #REF! | BH30: 1.1063321 | BI30: 0.56360316 | BJ30: 4340.66 | BK30: 5.1859737 | BL30: 2.6419111 | BM30: =Water!U32 -> 2.0531288 | BN30: =Water!W32 -> #DIV/0! | BO30: =Water!X32 -> 1338.64 | BP30: =Water!Y32 -> 8.2125153 | BQ30: =Water!Z32 -> #DIV/0!
A31: 27 | B31: 36000 | C31: =Elect!J32 -> 5829 | D31: 0 | E31: =Elect!M32 -> 2055 | F31: 30 | G31: =Elect!O32 -> 2280 | H31: 1010 | I31: =Water!C33 -> 58 | J31: 0 | K31: =Water!E33 -> 104.4 | L31: 0 | M31: =Water!#REF! -> #REF! | N31: =Water!#REF! -> #REF! | O31: 1014 | P31: =Water!H33 -> 287.1 | Q31: 151 | R31: =Water!O33 -> 0 | S31: 30 | T31: =Water!#REF! -> #REF! | U31: 139 | V31: =Water!#REF! -> #REF! | W31: 761 | X31: =Water!Q33 -> 166.518 | Y31: 0 | Z31: =Water!#REF! -> #REF! | AA31: 0 | AB31: 0 | AC31: 930 | AD31: =Water!#REF! -> #REF! | AE31: =Water!#REF! -> #REF! | AF31: =Water!#REF! -> #REF! | AG31: =Gas!B33 -> 8496190 | AH31: =Gas!C33 -> 1527.46 | AI31: =Gas!#REF! -> #REF! | AJ31: =Gas!J33 -> 417.3 | AK31: =Gas!#REF! -> #REF! | AL31: =Gas!#REF! -> #REF! | AM31: =Gas!#REF! -> #REF! | AN31: =Gas!#REF! -> #REF! | AO31: =Gas!#REF! -> #REF! | AP31: =Gas!#REF! -> #REF! | AQ31: =Gas!#REF! -> #REF! | AR31: =Gas!#REF! -> #REF! | AS31: =Gas!#REF! -> #REF! | AT31: =Elect!BR32 -> 116 | AU31: =Elect!BP32 -> 129 | AX31: 44.063647 | AY31: 22.346369 | AZ31: 9371.6914 | BA31: 11.470859 | BB31: 5.8173131 | BC31: =Elect!BQ32 -> 569953 | BD31: =Elect!#REF! -> #REF! | BE31: =Elect!#REF! -> #REF! | BF31: =Elect!#REF! -> #REF! | BG31: =Elect!#REF! -> #REF! | BH31: 1.1640147 | BI31: 0.59031657 | BJ31: 5768.5087 | BK31: 7.0605981 | BL31: 3.5807006 | BM31: =Water!U33 -> 1.3869565 | BN31: =Water!W33 -> #DIV/0! | BO31: =Water!X33 -> 1148.4 | BP31: =Water!Y33 -> 5.5478261 | BQ31: =Water!Z33 -> #DIV/0!
A32: 28 | B32: 33600 | C32: =Elect!J33 -> 6011 | D32: 0 | E32: =Elect!M33 -> 2093 | F32: 20 | G32: =Elect!O33 -> 2206 | H32: 1008 | I32: =Water!C34 -> 98.6 | J32: 0 | K32: =Water!E34 -> 110.2 | L32: 1 | M32: =Water!#REF! -> #REF! | N32: =Water!#REF! -> #REF! | O32: 1013 | P32: =Water!H34 -> 341.04 | Q32: 142 | R32: =Water!O34 -> 0 | S32: 13 | T32: =Water!#REF! -> #REF! | U32: 155 | V32: =Water!#REF! -> #REF! | W32: 825 | X32: =Water!Q34 -> 197.8032 | Y32: 1 | Z32: =Water!#REF! -> #REF! | AA32: 0 | AB32: 0 | AC32: 650 | AD32: =Water!#REF! -> #REF! | AE32: =Water!#REF! -> #REF! | AF32: =Water!#REF! -> #REF! | AG32: =Gas!B34 -> 8497743 | AH32: =Gas!C34 -> 1646.18 | AI32: =Gas!#REF! -> #REF! | AJ32: =Gas!J34 -> 460.2 | AK32: =Gas!#REF! -> #REF! | AL32: =Gas!#REF! -> #REF! | AM32: =Gas!#REF! -> #REF! | AN32: =Gas!#REF! -> #REF! | AO32: =Gas!#REF! -> #REF! | AP32: =Gas!#REF! -> #REF! | AQ32: =Gas!#REF! -> #REF! | AR32: =Gas!#REF! -> #REF! | AS32: =Gas!#REF! -> #REF! | AT32: =Elect!BR33 -> 156 | AU32: =Elect!BP33 -> 131 | AX32: 45.34413 | AY32: 22.687373 | AZ32: 8835.4834 | BA32: 11.923729 | BB32: 5.9658902 | BC32: =Elect!BQ33 -> 570109 | BD32: =Elect!#REF! -> #REF! | BE32: =Elect!#REF! -> #REF! | BF32: =Elect!#REF! -> #REF! | BG32: =Elect!#REF! -> #REF! | BH32: 1.2294197 | BI32: 0.61512492 | BJ32: 5757.0859 | BK32: 7.7693467 | BL32: 3.8872963 | BM32: =Water!U34 -> 1.5157333 | BN32: =Water!W34 -> #DIV/0! | BO32: =Water!X34 -> 1364.16 | BP32: =Water!Y34 -> 6.0629333 | BQ32: =Water!Z34 -> #DIV/0!
A33: MTD | B33: 931200 | C33: =Elect!J34 -> 6308 | D33: 0 | E33: =Elect!M34 -> 2053 | F33: 600 | G33: =Elect!O34 -> 2253 | H33: 24543 | I33: =Water!C38 -> 3428.2833 | J33: 0 | K33: =Water!E39 -> 132.49133 | L33: 3 | M33: =Water!#REF! -> #REF! | N33: =Water!#REF! -> #REF! | O33: 1013 | P33: =Water!H38 -> 10965.625 | Q33: 109 | R33: =Water!O38 -> 0 | S33: 15 | T33: =Water!#REF! -> #REF! | U33: 147 | V33: =Water!#REF! -> #REF! | W33: 730 | X33: =Water!Q38 -> 5758.5793 | Y33: 3 | Z33: =Water!#REF! -> #REF! | AA33: 0 | AB33: 0 | AC33: 0 | AD33: =Water!#REF! -> #REF! | AE33: =Water!#REF! -> #REF! | AF33: =Water!#REF! -> #REF! | AG33: =Gas!B38 -> 0 | AH33: =Gas!C38 -> 53698.982 | AI33: =Gas!#REF! -> #REF! | AJ33: =Gas!J38 -> 11837.547 | AK33: =Gas!#REF! -> #REF! | AL33: =Gas!#REF! -> #REF! | AM33: =Gas!#REF! -> #REF! | AN33: =Gas!#REF! -> #REF! | AO33: =Gas!#REF! -> #REF! | AP33: =Gas!#REF! -> #REF! | AQ33: =Gas!#REF! -> #REF! | AR33: =Gas!#REF! -> #REF! | AS33: =Gas!#REF! -> #REF! | AT33: =Elect!BR34 -> 156 | AU33: =Elect!BP34 -> 118 | AX33: 45.411099 | AY33: 22.844806 | AZ33: 245248.7 | BA33: 11.959851 | BB33: 6.0166013 | BC33: =Elect!BQ34 -> 570265 | BD33: =Elect!#REF! -> #REF! | BE33: =Elect!#REF! -> #REF! | BF33: =Elect!#REF! -> #REF! | BG33: =Elect!#REF! -> #REF! | BH33: 1.1514679 | BI33: 0.57929342 | BJ33: 140121.3 | BK33: 6.8331854 | BL33: 3.4377159 | BM33: =Water!U38 -> 1.7306858 | BN33: =Water!W38 -> #DIV/0! | BO33: =Water!X38 -> 42380.02 | BP33: =Water!Y38 -> 6.6887658 | BQ33: =Water!Z38 -> #DIV/0!
A34: AVER. Act | B34: 33257.143 | C34: =Elect!J35 -> 6499 | D34: 0 | E34: =Elect!M35 -> 2175 | F34: 21.428571 | G34: =Elect!O35 -> 2199 | H34: 876.53571 | I34: =Water!C39 -> 114.27611 | J34: 0 | K34: =Water!E40 -> 0 | L34: 4 | M34: =Water!#REF! -> #REF! | N34: =Water!#REF! -> #REF! | O34: 1014 | P34: =Water!H39 -> 365.52083 | Q34: 138 | R34: =Water!O39 -> 0 | S34: 24 | T34: =Water!#REF! -> #REF! | U34: 145 | V34: =Water!#REF! -> #REF! | W34: 877 | X34: =Water!Q39 -> 191.95264 | Y34: 4 | Z34: =Water!#REF! -> #REF! | AA34: 0 | AB34: 0 | AC34: 0 | AD34: =Water!#REF! -> #REF! | AE34: =Water!#REF! -> #REF! | AF34: =Water!#REF! -> #REF! | AG34: =Gas!B39 -> 0 | AH34: =Gas!C39 -> 1789.9661 | AI34: =Gas!#REF! -> #REF! | AJ34: =Gas!J39 -> 394.58491 | AK34: =Gas!#REF! -> #REF! | AL34: =Gas!#REF! -> #REF! | AM34: =Gas!#REF! -> #REF! | AN34: =Gas!#REF! -> #REF! | AO34: =Gas!#REF! -> #REF! | AP34: =Gas!#REF! -> #REF! | AQ34: =Gas!#REF! -> #REF! | AR34: =Gas!#REF! -> #REF! | AS34: =Gas!#REF! -> #REF! | AT34: =Elect!BR35 -> 156 | AU34: =Elect!BP35 -> 0 | AX34: 45.411099 | AY34: 22.844806 | AZ34: 8758.8823 | BA34: 11.959851 | BB34: 6.0166013 | BC34: =Elect!BQ35 -> 570421 | BD34: =Elect!#REF! -> #REF! | BE34: =Elect!#REF! -> #REF! | BF34: =Elect!#REF! -> #REF! | BG34: =Elect!#REF! -> #REF! | BH34: 1.1761372 | BI34: 0.60007377 | BJ34: 5004.3322 | BK34: 6.8331854 | BL34: 3.4377159 | BM34: =Water!U39 -> 1.7306858 | BN34: =Water!W39 -> #DIV/0! | BO34: =Water!X39 -> 1412.6673 | BP34: =Water!Y39 -> 6.6887658 | BQ34: =Water!Z39 -> #DIV/0!
A35: TOTAL Budget | B35: 1040026 | C35: =Elect!J5 -> 0 | D35: 0 | E35: =Elect!M5 -> 0 | F35: 0 | G35: =Elect!O5 -> 0 | H35: 0 | I35: =Water!C40 -> 0 | J35: 0 | K35: =Water!E41 -> 0 | L35: 5 | M35: =Water!#REF! -> #REF! | N35: =Water!#REF! -> #REF! | O35: 1010 | P35: =Water!H40 -> 0 | Q35: 148 | R35: =Water!O40 -> 0 | S35: 22 | T35: =Water!#REF! -> #REF! | U35: 151 | V35: =Water!#REF! -> #REF! | W35: 833 | X35: =Water!Q40 -> 0 | Y35: 5 | Z35: =Water!#REF! -> #REF! | AA35: 0 | AB35: 0 | AC35: 0 | AD35: =Water!#REF! -> #REF! | AE35: =Water!#REF! -> #REF! | AF35: =Water!#REF! -> #REF! | AG35: =Gas!#REF! -> #REF! | AH35: =Gas!#REF! -> #REF! | AI35: =Gas!#REF! -> #REF! | AJ35: =Gas!#REF! -> #REF! | AK35: =Gas!#REF! -> #REF! | AL35: =Gas!#REF! -> #REF! | AM35: =Gas!#REF! -> #REF! | AN35: =Gas!#REF! -> #REF! | ... AS35: =Gas!#REF! -> #REF! | AT35: =Elect!BR5 -> 0 | AU35: =Elect!BP5 -> 0 | AX35: 45.679286 | AY35: 23.305904 | AZ35: 264708.4 | BA35: 11.626335 | BB35: 5.9318409 | BC35: =Elect!BQ5 -> 566423.67 | BD35: =Elect!#REF! -> #REF! | BE35: =Elect!#REF! -> #REF! | BF35: =Elect!#REF! -> #REF! | BG35: =Elect!#REF! -> #REF! | BH35: 1.1761372 | BI35: 0.60007377 | BJ35: 150494 | BK35: 6.6098911 | BL35: 3.3724146 | BM35: =Water!U40 -> #REF! | BN35: =Water!W40 -> #REF! | BO35: =Water!X40 -> 0 | BP35: =Water!Y40 -> 0 | BQ35: =Water!Z40 -> 0
A36: Budget MTD | B36: 1040026 | C36: =Elect!#REF! -> #REF! | D36: 0 | E36: =Elect!#REF! -> #REF! | F36: 0 | G36: =Elect!#REF! -> #REF! | H36: 0 | I36: =Water!C41 -> 0 | J36: 0 | K36: =Water!E42 -> 0 | L36: 6 | M36: =Water!#REF! -> #REF! | N36: =Water!#REF! -> #REF! | O36: 30039 | P36: =Water!H41 -> 0 | Q36: 129.54839 | R36: =Water!O41 -> 0 | S36: 719 | T36: =Water!#REF! -> #REF! | U36: 4609 | V36: =Water!#REF! -> #REF! | W36: 23430 | X36: =Water!Q41 -> 0 | Y36: 6 | Z36: =Water!#REF! -> #REF! | AA36: 0 | AB36: 0 | AC36: 0 | AD36: =Water!#REF! -> #REF! | AE36: =Water!#REF! -> #REF! | AF36: =Water!#REF! -> #REF! | AG36: =Gas!#REF! -> #REF! | AH36: =Gas!#REF! -> #REF! | AI36: =Gas!#REF! -> #REF! | AJ36: =Gas!#REF! -> #REF! | AK36: =Gas!#REF! -> #REF! | AL36: =Gas!#REF! -> #REF! | AM36: =Gas!#REF! -> #REF! | AN36: =Gas!#REF! -> #REF! | ... AS36: =Gas!#REF! -> #REF! | AT36: =Elect!#REF! -> #REF! | AU36: =Elect!#REF! -> #REF! | AX36: 45.679286 | AY36: 23.305904 | AZ36: 264708.4 | BA36: 11.626335 | BB36: 5.9318409 | BC36: =Elect!#REF! -> #REF! | BD36: =Elect!#REF! -> #REF! | BE36: =Elect!#REF! -> #REF! | BF36: =Elect!#REF! -> #REF! | BG36: =Elect!#REF! -> #REF! | BH36: 0 | BI36: 0 | BJ36: 135930.06 | BK36: 6.6098911 | BL36: 3.3724146 | BM36: =Water!U41 -> #REF! | BN36: =Water!W41 -> #REF! | BO36: =Water!X41 -> #REF! | BP36: =Water!Y41 -> #REF! | BQ36: =Water!Z41 -> #REF!
A37: AVER. Bud | B37: 37143.785 | C37: =Elect!#REF! -> #REF! | D37: 0 | E37: =Elect!#REF! -> #REF! | F37: 0 | G37: =Elect!#REF! -> #REF! | H37: 0 | I37: =Water!C42 -> 0 | J37: 0 | K37: =Water!E43 -> 0 | L37: 7 | M37: =Water!#REF! -> #REF! | N37: =Water!#REF! -> #REF! | O37: 969 | P37: =Water!H42 -> 0 | Q37: 0 | R37: =Water!O42 -> 0 | S37: 23.193548 | T37: =Water!#REF! -> #REF! | U37: 148.67742 | V37: =Water!#REF! -> #REF! | W37: 755.80645 | X37: =Water!Q42 -> 0 | Y37: 7 | Z37: =Water!#REF! -> #REF! | AA37: 0 | AB37: 0 | AC37: 0 | AD37: =Water!#REF! -> #REF! | AE37: =Water!#REF! -> #REF! | AF37: =Water!#REF! -> #REF! | AG37: =Gas!#REF! -> #REF! | AH37: =Gas!#REF! -> #REF! | AI37: =Gas!#REF! -> #REF! | AJ37: =Gas!#REF! -> #REF! | AK37: =Gas!#REF! -> #REF! | AL37: =Gas!#REF! -> #REF! | AM37: =Gas!#REF! -> #REF! | AN37: =Gas!#REF! -> #REF! | ... AS37: =Gas!#REF! -> #REF! | AT37: =Elect!#REF! -> #REF! | AU37: =Elect!#REF! -> #REF! | AX37: 0 | AY37: 0 | AZ37: 9453.8714 | BA37: 0 | BB37: 0 | BC37: =Elect!#REF! -> #REF! | BD37: =Elect!#REF! -> #REF! | BE37: =Elect!#REF! -> #REF! | BF37: =Elect!#REF! -> #REF! | BG37: =Elect!#REF! -> #REF! | BH37: 0 | BI37: 0 | BJ37: 0 | BK37: 0 | BL37: 0 | BM37: =Water!U42 -> 0 | BN37: =Water!W42 -> 0 | BO37: =Water!X42 -> 0 | BP37: =Water!Y42 -> 0 | BQ37: =Water!Z42 -> 0
A38: Total RFC | B38: 784008.53 | C38: =Elect!#REF! -> #REF! | D38: 0 | E38: =Elect!#REF! -> #REF! | F38: 0 | G38: =Elect!#REF! -> #REF! | H38: 0 | I38: =Water!C43 -> 0 | J38: 0 | K38: =Water!E44 -> 0 | L38: 8 | M38: =Water!#REF! -> #REF! | N38: =Water!#REF! -> #REF! | O38: 0 | P38: =Water!H43 -> 0 | Q38: 0 | R38: =Water!O43 -> 0 | S38: 0 | T38: =Water!#REF! -> #REF! | U38: 0 | V38: =Water!#REF! -> #REF! | W38: 0 | X38: =Water!Q43 -> 0 | Y38: 8 | Z38: =Water!#REF! -> #REF! | AA38: 0 | AB38: 0 | AC38: 0 | AD38: =Water!#REF! -> #REF! | AE38: =Water!#REF! -> #REF! | AF38: =Water!#REF! -> #REF! | AG38: =Gas!#REF! -> #REF! | AH38: =Gas!#REF! -> #REF! | AI38: =Gas!#REF! -> #REF! | AJ38: =Gas!#REF! -> #REF! | AK38: =Gas!#REF! -> #REF! | AL38: =Gas!#REF! -> #REF! | AM38: =Gas!#REF! -> #REF! | AN38: =Gas!#REF! -> #REF! | ... AS38: =Gas!#REF! -> #REF! | AT38: =Elect!#REF! -> #REF! | AU38: =Elect!#REF! -> #REF! | AX38: 38.173558 | AY38: 19.219193 | AZ38: 208225.85 | BA38: 10.138565 | BB38: 5.1044505 | BC38: =Elect!#REF! -> #REF! | BD38: =Elect!#REF! -> #REF! | BE38: =Elect!#REF! -> #REF! | BF38: =Elect!#REF! -> #REF! | BG38: =Elect!#REF! -> #REF! | BH38: 0 | BI38: 0 | BJ38: 127385.62 | BK38: 6.2024355 | BL38: 3.1227323 | BM38: =Water!U43 -> 0 | BN38: =Water!W43 -> 0 | BO38: =Water!X43 -> 0 | BP38: =Water!Y43 -> 0 | BQ38: =Water!Z43 -> 0
A39: RFC MTD | B39: 784008.53 | C39: =Elect!#REF! -> #REF! | D39: 0 | E39: =Elect!#REF! -> #REF! | F39: 0 | G39: =Elect!#REF! -> #REF! | H39: 0 | I39: =Water!C44 -> 0 | J39: 0 | K39: =Water!E45 -> 0 | L39: 9 | M39: =Water!#REF! -> #REF! | N39: =Water!#REF! -> #REF! | O39: 0 | P39: =Water!H44 -> 0 | Q39: 0 | R39: =Water!O44 -> 0 | S39: 0 | T39: =Water!#REF! -> #REF! | U39: 0 | V39: =Water!#REF! -> #REF! | W39: 0 | X39: =Water!Q44 -> 0 | Y39: 9 | Z39: =Water!#REF! -> #REF! | AA39: 0 | AB39: 0 | AC39: 0 | AD39: =Water!#REF! -> #REF! | AE39: =Water!#REF! -> #REF! | AF39: =Water!#REF! -> #REF! | AG39: =Gas!#REF! -> #REF! | AH39: =Gas!#REF! -> #REF! | AI39: =Gas!#REF! -> #REF! | AJ39: =Gas!#REF! -> #REF! | AK39: =Gas!#REF! -> #REF! | AL39: =Gas!#REF! -> #REF! | AM39: =Gas!#REF! -> #REF! | AN39: =Gas!#REF! -> #REF! | ... AS39: =Gas!#REF! -> #REF! | AT39: =Elect!#REF! -> #REF! | AU39: =Elect!#REF! -> #REF! | AX39: 38.173558 | AY39: 19.219193 | AZ39: 208225.85 | BA39: 10.138565 | BB39: 5.1044505 | BC39: =Elect!#REF! -> #REF! | BD39: =Elect!#REF! -> #REF! | BE39: =Elect!#REF! -> #REF! | BF39: =Elect!#REF! -> #REF! | BG39: =Elect!#REF! -> #REF! | BH39: 0 | BI39: 0 | BJ39: 115057.98 | BK39: 6.2024355 | BL39: 3.1227323 | BM39: =Water!U44 -> 0 | BN39: =Water!W44 -> 0 | BO39: =Water!X44 -> #VALUE! | BP39: =Water!Y44 -> #VALUE! | BQ39: =Water!Z44 -> #VALUE!
A40: AVER RFC | B40: 28000.305 | C40: =Elect!#REF! -> #REF! | D40: 0 | E40: =Elect!#REF! -> #REF! | F40: 0 | G40: =Elect!#REF! -> #REF! | H40: 0 | I40: =Water!C45 -> 0 | J40: 0 | K40: =Water!E46 -> 0 | L40: 10 | M40: =Water!#REF! -> #REF! | N40: =Water!#REF! -> #REF! | O40: 0 | P40: =Water!H45 -> 0 | Q40: 0 | R40: =Water!O45 -> 0 | S40: 0 | T40: =Water!#REF! -> #REF! | U40: 0 | V40: =Water!#REF! -> #REF! | W40: 0 | X40: =Water!Q45 -> 0 | Y40: 10 | Z40: =Water!#REF! -> #REF! | AA40: 0 | AB40: 0 | AC40: 0 | AD40: =Water!#REF! -> #REF! | AE40: =Water!#REF! -> #REF! | AF40: =Water!#REF! -> #REF! | AG40: =Gas!#REF! -> #REF! | AH40: =Gas!#REF! -> #REF! | AI40: =Gas!#REF! -> #REF! | AJ40: =Gas!#REF! -> #REF! | AK40: =Gas!#REF! -> #REF! | AL40: =Gas!#REF! -> #REF! | AM40: =Gas!#REF! -> #REF! | AN40: =Gas!#REF! -> #REF! | ... AS40: =Gas!#REF! -> #REF! | AT40: =Elect!#REF! -> #REF! | AU40: =Elect!#REF! -> #REF! | AX40: 0 | AY40: 0 | AZ40: 7436.6375 | BA40: 0 | BB40: 0 | BC40: =Elect!#REF! -> #REF! | BD40: =Elect!#REF! -> #REF! | BE40: =Elect!#REF! -> #REF! | BF40: =Elect!#REF! -> #REF! | BG40: =Elect!#REF! -> #REF! | BH40: 1.1254646 | BI40: 0.57264868 | BJ40: 4109.2135 | BK40: 0 | BL40: 0 | BM40: =Water!U45 -> 0 | BN40: =Water!W45 -> 0 | BO40: =Water!X45 -> #VALUE! | BP40: =Water!Y45 -> 0 | BQ40: =Water!Z45 -> 0

Sheet Temp.
A2: HILTON INTERNATIONAL
A3: GULF, MIDDLE EAST AND ASIA SPECIFIC
A4: HOTEL:HILTON HURGHADA LONG BEACH RESORT | G4: =Elect!A1 -> 44927
A7: DATE | B7: MAX TEMP | C7: MIN TEMP | D7: MAX TEMP | E7: MIN TEMP | F7: DAY | G7: DD. C | H7: DD. H | I7: MTD | J7: MTD
B8: C | C8: C | D8: F | E8: F | F8: PARAMETER | I8: COOLING | J8: HEATING
A10: 1 | D10: =SUM((B10*9/5)+32) -> 32 | E10: =SUM((C10*9/5)+32) -> 32 | F10: =SUM(((B10+C10)/2)-18.33) -> -18.33 | G10: =SUM(0+(F10)+ABS(F10))/2 -> 0 | H10: =IF((SUM(0-(F10)+ABS(F10))/2)<18,SUM(0-(F10)+ABS(F10))/2,0) -> 0 | I10: =SUM(G10:G10) -> 0 | J10: =SUM(H10:H10) -> 0
A11: 2 | D11: =SUM((B11*9/5)+32) -> 32 | E11: =SUM((C11*9/5)+32) -> 32 | F11: =SUM(((B11+C11)/2)-18.33) -> -18.33 | G11: =SUM(0+(F11)+ABS(F11))/2 -> 0 | H11: =IF((SUM(0-(F11)+ABS(F11))/2)<18,SUM(0-(F11)+ABS(F11))/2,0) -> 0 | I11: =SUM(G10:G11) -> 0 | J11: =SUM(H10:H11) -> 0
A12: 3 | D12: =SUM((B12*9/5)+32) -> 32 | E12: =SUM((C12*9/5)+32) -> 32 | F12: =SUM(((B12+C12)/2)-18.33) -> -18.33 | G12: =SUM(0+(F12)+ABS(F12))/2 -> 0 | H12: =IF((SUM(0-(F12)+ABS(F12))/2)<18,SUM(0-(F12)+ABS(F12))/2,0) -> 0 | I12: =SUM(G10:G12) -> 0 | J12: =SUM(H10:H12) -> 0
A13: 4 | D13: =SUM((B13*9/5)+32) -> 32 | E13: =SUM((C13*9/5)+32) -> 32 | F13: =SUM(((B13+C13)/2)-18.33) -> -18.33 | G13: =SUM(0+(F13)+ABS(F13))/2 -> 0 | H13: =IF((SUM(0-(F13)+ABS(F13))/2)<18,SUM(0-(F13)+ABS(F13))/2,0) -> 0 | I13: =SUM(G10:G13) -> 0 | J13: =SUM(H10:H13) -> 0
A14: 5 | D14: =SUM((B14*9/5)+32) -> 32 | E14: =SUM((C14*9/5)+32) -> 32 | F14: =SUM(((B14+C14)/2)-18.33) -> -18.33 | G14: =SUM(0+(F14)+ABS(F14))/2 -> 0 | H14: =IF((SUM(0-(F14)+ABS(F14))/2)<18,SUM(0-(F14)+ABS(F14))/2,0) -> 0 | I14: =SUM(G10:G14) -> 0 | J14: =SUM(H10:H14) -> 0
A15: 6 | D15: =SUM((B15*9/5)+32) -> 32 | E15: =SUM((C15*9/5)+32) -> 32 | F15: =SUM(((B15+C15)/2)-18.33) -> -18.33 | G15: =SUM(0+(F15)+ABS(F15))/2 -> 0 | H15: =IF((SUM(0-(F15)+ABS(F15))/2)<18,SUM(0-(F15)+ABS(F15))/2,0) -> 0 | I15: =SUM(G10:G15) -> 0 | J15: =SUM(H10:H15) -> 0
A16: 7 | D16: =SUM((B16*9/5)+32) -> 32 | E16: =SUM((C16*9/5)+32) -> 32 | F16: =SUM(((B16+C16)/2)-18.33) -> -18.33 | G16: =SUM(0+(F16)+ABS(F16))/2 -> 0 | H16: =IF((SUM(0-(F16)+ABS(F16))/2)<18,SUM(0-(F16)+ABS(F16))/2,0) -> 0 | I16: =SUM(G10:G16) -> 0 | J16: =SUM(H10:H16) -> 0
A17: 8 | D17: =SUM((B17*9/5)+32) -> 32 | E17: =SUM((C17*9/5)+32) -> 32 | F17: =SUM(((B17+C17)/2)-18.33) -> -18.33 | G17: =SUM(0+(F17)+ABS(F17))/2 -> 0 | H17: =IF((SUM(0-(F17)+ABS(F17))/2)<18,SUM(0-(F17)+ABS(F17))/2,0) -> 0 | I17: =SUM(G10:G17) -> 0 | J17: =SUM(H10:H17) -> 0
A18: 9 | D18: =SUM((B18*9/5)+32) -> 32 | E18: =SUM((C18*9/5)+32) -> 32 | F18: =SUM(((B18+C18)/2)-18.33) -> -18.33 | G18: =SUM(0+(F18)+ABS(F18))/2 -> 0 | H18: =IF((SUM(0-(F18)+ABS(F18))/2)<18,SUM(0-(F18)+ABS(F18))/2,0) -> 0 | I18: =SUM(G10:G18) -> 0 | J18: =SUM(H10:H18) -> 0
A19: 10 | D19: =SUM((B19*9/5)+32) -> 32 | E19: =SUM((C19*9/5)+32) -> 32 | F19: =SUM(((B19+C19)/2)-18.33) -> -18.33 | G19: =SUM(0+(F19)+ABS(F19))/2 -> 0 | H19: =IF((SUM(0-(F19)+ABS(F19))/2)<18,SUM(0-(F19)+ABS(F19))/2,0) -> 0 | I19: =SUM(G10:G19) -> 0 | J19: =SUM(H10:H19) -> 0
A20: 11 | D20: =SUM((B20*9/5)+32) -> 32 | E20: =SUM((C20*9/5)+32) -> 32 | F20: =SUM(((B20+C20)/2)-18.33) -> -18.33 | G20: =SUM(0+(F20)+ABS(F20))/2 -> 0 | H20: =IF((SUM(0-(F20)+ABS(F20))/2)<18,SUM(0-(F20)+ABS(F20))/2,0) -> 0 | I20: =SUM(G10:G20) -> 0 | J20: =SUM(H10:H20) -> 0
A21: 12 | D21: =SUM((B21*9/5)+32) -> 32 | E21: =SUM((C21*9/5)+32) -> 32 | F21: =SUM(((B21+C21)/2)-18.33) -> -18.33 | G21: =SUM(0+(F21)+ABS(F21))/2 -> 0 | H21: =IF((SUM(0-(F21)+ABS(F21))/2)<18,SUM(0-(F21)+ABS(F21))/2,0) -> 0 | I21: =SUM(G10:G21) -> 0 | J21: =SUM(H10:H21) -> 0
A22: 13 | D22: =SUM((B22*9/5)+32) -> 32 | E22: =SUM((C22*9/5)+32) -> 32 | F22: =SUM(((B22+C22)/2)-18.33) -> -18.33 | G22: =SUM(0+(F22)+ABS(F22))/2 -> 0 | H22: =IF((SUM(0-(F22)+ABS(F22))/2)<18,SUM(0-(F22)+ABS(F22))/2,0) -> 0 | I22: =SUM(G10:G22) -> 0 | J22: =SUM(H10:H22) -> 0
A23: 14 | D23: =SUM((B23*9/5)+32) -> 32 | E23: =SUM((C23*9/5)+32) -> 32 | F23: =SUM(((B23+C23)/2)-18.33) -> -18.33 | G23: =SUM(0+(F23)+ABS(F23))/2 -> 0 | H23: =IF((SUM(0-(F23)+ABS(F23))/2)<18,SUM(0-(F23)+ABS(F23))/2,0) -> 0 | I23: =SUM(G10:G23) -> 0 | J23: =SUM(H10:H23) -> 0
A24: 15 | D24: =SUM((B24*9/5)+32) -> 32 | E24: =SUM((C24*9/5)+32) -> 32 | F24: =SUM(((B24+C24)/2)-18.33) -> -18.33 | G24: =SUM(0+(F24)+ABS(F24))/2 -> 0 | H24: =IF((SUM(0-(F24)+ABS(F24))/2)<18,SUM(0-(F24)+ABS(F24))/2,0) -> 0 | I24: =SUM(G11:G24) -> 0 | J24: =SUM(H11:H24) -> 0
A25: 16 | D25: =SUM((B25*9/5)+32) -> 32 | E25: =SUM((C25*9/5)+32) -> 32 | F25: =SUM(((B25+C25)/2)-18.33) -> -18.33 | G25: =SUM(0+(F25)+ABS(F25))/2 -> 0 | H25: =IF((SUM(0-(F25)+ABS(F25))/2)<18,SUM(0-(F25)+ABS(F25))/2,0) -> 0 | I25: =SUM(G12:G25) -> 0 | J25: =SUM(H12:H25) -> 0
A26: 17 | D26: =SUM((B26*9/5)+32) -> 32 | E26: =SUM((C26*9/5)+32) -> 32 | F26: =SUM(((B26+C26)/2)-18.33) -> -18.33 | G26: =SUM(0+(F26)+ABS(F26))/2 -> 0 | H26: =IF((SUM(0-(F26)+ABS(F26))/2)<18,SUM(0-(F26)+ABS(F26))/2,0) -> 0 | I26: =SUM(G13:G26) -> 0 | J26: =SUM(H13:H26) -> 0
A27: 18 | D27: =SUM((B27*9/5)+32) -> 32 | E27: =SUM((C27*9/5)+32) -> 32 | F27: =SUM(((B27+C27)/2)-18.33) -> -18.33 | G27: =SUM(0+(F27)+ABS(F27))/2 -> 0 | H27: =IF((SUM(0-(F27)+ABS(F27))/2)<18,SUM(0-(F27)+ABS(F27))/2,0) -> 0 | I27: =SUM(G14:G27) -> 0 | J27: =SUM(H14:H27) -> 0
A28: 19 | D28: =SUM((B28*9/5)+32) -> 32 | E28: =SUM((C28*9/5)+32) -> 32 | F28: =SUM(((B28+C28)/2)-18.33) -> -18.33 | G28: =SUM(0+(F28)+ABS(F28))/2 -> 0 | H28: =IF((SUM(0-(F28)+ABS(F28))/2)<18,SUM(0-(F28)+ABS(F28))/2,0) -> 0 | I28: =SUM(G15:G28) -> 0 | J28: =SUM(H15:H28) -> 0
A29: 20 | D29: =SUM((B29*9/5)+32) -> 32 | E29: =SUM((C29*9/5)+32) -> 32 | F29: =SUM(((B29+C29)/2)-18.33) -> -18.33 | G29: =SUM(0+(F29)+ABS(F29))/2 -> 0 | H29: =IF((SUM(0-(F29)+ABS(F29))/2)<18,SUM(0-(F29)+ABS(F29))/2,0) -> 0 | I29: =SUM(G16:G29) -> 0 | J29: =SUM(H16:H29) -> 0
A30: 21 | D30: =SUM((B30*9/5)+32) -> 32 | E30: =SUM((C30*9/5)+32) -> 32 | F30: =SUM(((B30+C30)/2)-18.33) -> -18.33 | G30: =SUM(0+(F30)+ABS(F30))/2 -> 0 | H30: =IF((SUM(0-(F30)+ABS(F30))/2)<18,SUM(0-(F30)+ABS(F30))/2,0) -> 0 | I30: =SUM(G17:G30) -> 0 | J30: =SUM(H17:H30) -> 0
A31: 22 | D31: =SUM((B31*9/5)+32) -> 32 | E31: =SUM((C31*9/5)+32) -> 32 | F31: =SUM(((B31+C31)/2)-18.33) -> -18.33 | G31: =SUM(0+(F31)+ABS(F31))/2 -> 0 | H31: =IF((SUM(0-(F31)+ABS(F31))/2)<18,SUM(0-(F31)+ABS(F31))/2,0) -> 0 | I31: =SUM(G18:G31) -> 0 | J31: =SUM(H18:H31) -> 0
A32: 23 | D32: =SUM((B32*9/5)+32) -> 32 | E32: =SUM((C32*9/5)+32) -> 32 | F32: =SUM(((B32+C32)/2)-18.33) -> -18.33 | G32: =SUM(0+(F32)+ABS(F32))/2 -> 0 | H32: =IF((SUM(0-(F32)+ABS(F32))/2)<18,SUM(0-(F32)+ABS(F32))/2,0) -> 0 | I32: =SUM(G19:G32) -> 0 | J32: =SUM(H19:H32) -> 0
A33: 24 | D33: =SUM((B33*9/5)+32) -> 32 | E33: =SUM((C33*9/5)+32) -> 32 | F33: =SUM(((B33+C33)/2)-18.33) -> -18.33 | G33: =SUM(0+(F33)+ABS(F33))/2 -> 0 | H33: =IF((SUM(0-(F33)+ABS(F33))/2)<18,SUM(0-(F33)+ABS(F33))/2,0) -> 0 | I33: =SUM(G20:G33) -> 0 | J33: =SUM(H20:H33) -> 0
A34: 25 | D34: =SUM((B34*9/5)+32) -> 32 | E34: =SUM((C34*9/5)+32) -> 32 | F34: =SUM(((B34+C34)/2)-18.33) -> -18.33 | G34: =SUM(0+(F34)+ABS(F34))/2 -> 0 | H34: =IF((SUM(0-(F34)+ABS(F34))/2)<18,SUM(0-(F34)+ABS(F34))/2,0) -> 0 | I34: =SUM(G21:G34) -> 0 | J34: =SUM(H21:H34) -> 0
... A40: 31 | D40: =SUM((B40*9/5)+32) -> 32 | E40: =SUM((C40*9/5)+32) -> 32 | F40: =SUM(((B40+C40)/2)-18.33) -> -18.33 | G40: =SUM(0+(F40)+ABS(F40))/2 -> 0 | H40: =IF((SUM(0-(F40)+ABS(F40))/2)<18,SUM(0-(F40)+ABS(F40))/2,0) -> 0 | I40: =SUM(G27:G40) -> 0 | J40: =SUM(H27:H40) -> 0
E42: =SUM(G10:G40) -> 0 | F42: deg c
E44: =SUM(H10:H40) -> 0 | F44: deg c

Sheet M-Rep
B3: =Elect!A1 -> 44927
D4: Y.T.D
A5: Energy breakdown | C5: 2009 | D5: 2005 | E5: 2006
A6: Elect.
A7: Chillers KWH | C7: N/A | D7: N/A | E7: N/A
A8: Laundry KWH | C8: N/A | D8: N/A | E8: N/A
A9: Kitchen KWH | C9: N/A | D9: N/A | E9: N/A
A10: Gas
A11: Kit M3 | C11: =Gas!#REF!/1000 -> #REF!
A12: Laundry M3 | C12: N/A | D12: 0 | E12: #REF!
A13: Water | D13: N/A | E13: N/A
A14: Laundry HW | C14: N/A
A15: Laundry CW | C15: N/A
A16: Kit HW | C16: N/A
A17: kIt CW | C17: N/A | D17: N/A | E17: N/A
A18: Dmstc HW | C18: N/A | D18: N/A | E18: N/A
A19: Dmstc CW | C19: N/A | D19: N/A | E19: N/A
A20: S.Pool MKUP | C20: =#REF! -> #REF! | D20: N/A | E20: N/A
A21: Ctower MKUP | C21: N/A | D21: N/A | E21: N/A
A22: Gardens Irrigat. | C22: =Water!S38 -> 0 | D22: N/A | E22: N/A
A23: Swage water treatment | C23: =Water!#REF! -> #REF! | D23: 27437 | E23: #REF!
A24: Utilities consumption | D24: N/A | E24: N/A
A25: Elect. Kwh | C25: =Elect!J34 -> 6308 | D25: 12266 | E25: 814
A26: M.D (9.5 LE) | D26: 147773 | E26: #REF!
A27: Water M3 | C27: =Water!H38 -> 10965.625
A28: Fuel Ltr | C28: =Gas!#REF!*1000 -> #REF! | D28: 12876868 | E28: 14500800
A29: Gas M3/ Boilers, chillers,..etc | C29: N/A | D29: 28880 | E29: 32980
A30: Gas M3 Kitchen | C30: =Gas!#REF!/1000 -> #REF! | D30: 244283 | E30: 252530.66
A31: Total Energy | D31: 620770 | E31: #REF!
A32: Control Parameters | D32: #REF! | E32: N/A
A33: No. of Rooms % occ. | C33: =YTD!Q4 -> 0 | D33: 39.395 | E33: #REF!
A34: No. of Occ. Rooms | C34: =YTD!Q5 -> 0
A35: guest count | C35: =YTD!Q6 -> 0
A36: Food covers | D36: #REF! | E36: #REF!
A37: Laundry W. Kg | D37: 0.8807 | E37: 0.46351998
A38: DDC | C38: =Temp.!E42 -> 0 | D38: 196150 | E38: 237021
A39: DDH | C39: =Temp.!E44 -> 0 | D39: 400070 | E39: 466105
A40: Utilities Entergy cost | D40: 1583714 | E40: 1940567
A41: Elect. | C41: =Elect!#REF! -> #REF! | D41: 1690339 | E41: 3118671.6
A42: M.D | C42: =C26*Elect!#REF! -> #REF! | D42: 2381.51 | E42: 2480.24
A43: Water | C43: =Water!X38 -> 42380.02 | D43: 112 | E43: 97.53
A44: Fuel | C44: =Gas!#REF! -> #REF!
A45: Gas Boilers, chillers,etc.. | C45: N/A | D45: 2138156.8 | E45: #REF!
A46: Gas Kitchen | C46: =C30*Gas!M2*1000 -> #REF! | D46: 223044.2 | E46: #REF!
A47: TOTAL LE | C47: =SUM(C41:C46) -> #REF! | D47: 1330535.7 | E47: 1382037.4
A48: No. of POMEC Staff | D48: 330278 | E48: #REF!
A49: Hotel Age | C49: 6 | D49: N/A | E49: N/A
A50: No. of rooms | C50: =31*912 -> 28272 | D50: 36597.525 | E50: #REF!
A51: Building Volume | C51: 243175 | D51: =SUM(D45:D50) -> 4058612.3 | E51: =SUM(E45:E50) -> #REF!
A52: Building area | C52: 75064
A53: US$ Rate | C53: 5.59402 | D53: 61 | E53: 72
A54: Total R&M MTD | C54: =YTD!Q65 -> 0 | D54: #REF! | E54: 243175 | F54: =YTD!Q64 -> 0
A55: Staff - HLP | D55: #REF! | E55: 75064
A56: Staff - R&M | D56: 5.755 | E56: 5.65951
A57: Staff - Grounds

Sheet YTD
A1: =Elect!A1 -> 44927 | H1: Actual 2014
C3: JAN | D3: FEB | E3: MAR | F3: APR | G3: MAY | H3: JUN | I3: JUL | J3: AUG | K3: SEP | L3: OCT | M3: NOV | N3: DEC | O3: TOTAL | P3: YTD | Q3: Month Act
A4: Occ Room % | O4: =SUM(C4:N4) -> 0 | P4: =(IF($A$1=39814,C4,(IF($A$1=39845,SUM(C4:D4),(IF($A$1=39873,SUM(C4:E4),(IF($A$1=39904,SUM(C4:F4),(IF($A$1=39934,SUM(C4:G4),(IF($A$1=39965,SUM(C4:H4),(IF($A$1=39995,SUM(C4:I4),0)))))))))))))+(IF($A$1=40026,SUM(C4:J4),(IF($A$1=40057,SUM(C4:K4),(IF($A$1=40087,SUM(C4:L4),(IF($A$1=40118,SUM(C4:M4))))))))))+(IF($A$1=40148,SUM(C4:N4),0)) -> 0 | Q4: =(IF($A$1=39814,C4,(IF($A$1=39845,D4,(IF($A$1=39873,E4,(IF($A$1=39904,F4,(IF($A$1=39934,G4,(IF($A$1=39965,H4,(IF($A$1=39995,I4,0)))))))))))))+(IF($A$1=40026,J4,(IF($A$1=40057,K4,(IF($A$1=40087,L4,(IF($A$1=40118,M4)))))))))+(IF($A$1=40148,N4,0)) -> 0 | S4: 40179 | DE4: 1
A5: Occ Room | C5: 25072 | D5: =Elect!BP34 -> 118 | O5: =SUM(C5:N5) -> 25190 | P5: =(IF($A$1=40179,C5,(IF($A$1=40210,SUM(C5:D5),(IF($A$1=40238,SUM(C5:E5),(IF($A$1=40269,SUM(C5:F5),(IF($A$1=40299,SUM(C5:G5),(IF($A$1=40330,SUM(C5:H5),(IF($A$1=40360,SUM(C5:I5),0)))))))))))))+(IF($A$1=40391,SUM(C5:J5),(IF($A$1=40422,SUM(C5:K5),(IF($A$1=40452,SUM(C5:L5),(IF($A$1=40483,SUM(C5:M5))))))))))+(IF($A$1=40513,SUM(C5:N5),0)) -> 0 | Q5: =(IF($A$1=40179,C5,(IF($A$1=40210,D5,(IF($A$1=40238,E5,(IF($A$1=40269,F5,(IF($A$1=40299,G5,(IF($A$1=40330,H5,(IF($A$1=40360,I5,0)))))))))))))+(IF($A$1=40391,J5,(IF($A$1=40422,K5,(IF($A$1=40452,L5,(IF($A$1=40483,M5)))))))))+(IF($A$1=40513,N5,0)) -> 0 | S5: 40210 | DE5: 2
A6: Number of Guest | C6: 50662 | D6: =Elect!BR34 -> 156 | O6: =SUM(C6:N6) -> 50818 | P6: =(IF($A$1=40179,C6,(IF($A$1=40210,SUM(C6:D6),(IF($A$1=40238,SUM(C6:E6),(IF($A$1=40269,SUM(C6:F6),(IF($A$1=40299,SUM(C6:G6),(IF($A$1=40330,SUM(C6:H6),(IF($A$1=40360,SUM(C6:I6),0)))))))))))))+(IF($A$1=40391,SUM(C6:J6),(IF($A$1=40422,SUM(C6:K6),(IF($A$1=40452,SUM(C6:L6),(IF($A$1=40483,SUM(C6:M6))))))))))+(IF($A$1=40513,SUM(C6:N6),0)) -> 0 | Q6: =(IF($A$1=40179,C6,(IF($A$1=40210,D6,(IF($A$1=40238,E6,(IF($A$1=40269,F6,(IF($A$1=40299,G6,(IF($A$1=40330,H6,(IF($A$1=40360,I6,0)))))))))))))+(IF($A$1=40391,J6,(IF($A$1=40422,K6,(IF($A$1=40452,L6,(IF($A$1=40483,M6)))))))))+(IF($A$1=40513,N6,0)) -> 0 | S6: 40238 | DE6: 3
A7: PAY & REL. EXP. | O7: =SUM(C7:N7) -> 0 | P7: =(IF($A$1=40179,C7,(IF($A$1=40210,SUM(C7:D7),(IF($A$1=40238,SUM(C7:E7),(IF($A$1=40269,SUM(C7:F7),(IF($A$1=40299,SUM(C7:G7),(IF($A$1=40330,SUM(C7:H7),(IF($A$1=40360,SUM(C7:I7),0)))))))))))))+(IF($A$1=40391,SUM(C7:J7),(IF($A$1=40422,SUM(C7:K7),(IF($A$1=40452,SUM(C7:L7),(IF($A$1=40483,SUM(C7:M7))))))))))+(IF($A$1=40513,SUM(C7:N7),0)) -> 0 | Q7: =(IF($A$1=40179,C7,(IF($A$1=40210,D7,(IF($A$1=40238,E7,(IF($A$1=40269,F7,(IF($A$1=40299,G7,(IF($A$1=40330,H7,(IF($A$1=40360,I7,0)))))))))))))+(IF($A$1=40391,J7,(IF($A$1=40422,K7,(IF($A$1=40452,L7,(IF($A$1=40483,M7)))))))))+(IF($A$1=40513,N7,0)) -> 0
A8: SALARIES | B8: 53241001 | O8: =SUM(C8:N8) -> 0 | P8: =(IF($A$1=40179,C8,(IF($A$1=40210,SUM(C8:D8),(IF($A$1=40238,SUM(C8:E8),(IF($A$1=40269,SUM(C8:F8),(IF($A$1=40299,SUM(C8:G8),(IF($A$1=40330,SUM(C8:H8),(IF($A$1=40360,SUM(C8:I8),0)))))))))))))+(IF($A$1=40391,SUM(C8:J8),(IF($A$1=40422,SUM(C8:K8),(IF($A$1=40452,SUM(C8:L8),(IF($A$1=40483,SUM(C8:M8))))))))))+(IF($A$1=40513,SUM(C8:N8),0)) -> 0 | Q8: =(IF($A$1=40179,C8,(IF($A$1=40210,D8,(IF($A$1=40238,E8,(IF($A$1=40269,F8,(IF($A$1=40299,G8,(IF($A$1=40330,H8,(IF($A$1=40360,I8,0)))))))))))))+(IF($A$1=40391,J8,(IF($A$1=40422,K8,(IF($A$1=40452,L8,(IF($A$1=40483,M8)))))))))+(IF($A$1=40513,N8,0)) -> 0
A9: EXTRA WAGES | B9: 53242099 | O9: =SUM(C9:N9) -> 0 | P9: =(IF($A$1=40179,C9,(IF($A$1=40210,SUM(C9:D9),(IF($A$1=40238,SUM(C9:E9),(IF($A$1=40269,SUM(C9:F9),(IF($A$1=40299,SUM(C9:G9),(IF($A$1=40330,SUM(C9:H9),(IF($A$1=40360,SUM(C9:I9),0)))))))))))))+(IF($A$1=40391,SUM(C9:J9),(IF($A$1=40422,SUM(C9:K9),(IF($A$1=40452,SUM(C9:L9),(IF($A$1=40483,SUM(C9:M9))))))))))+(IF($A$1=40513,SUM(C9:N9),0)) -> 0 | Q9: =(IF($A$1=40179,C9,(IF($A$1=40210,D9,(IF($A$1=40238,E9,(IF($A$1=40269,F9,(IF($A$1=40299,G9,(IF($A$1=40330,H9,(IF($A$1=40360,I9,0)))))))))))))+(IF($A$1=40391,J9,(IF($A$1=40422,K9,(IF($A$1=40452,L9,(IF($A$1=40483,M9)))))))))+(IF($A$1=40513,N9,0)) -> 0
A10: SERVICE | B10: 53243001 | O10: =SUM(C10:N10) -> 0 | P10: =(IF($A$1=40179,C10,(IF($A$1=40210,SUM(C10:D10),(IF($A$1=40238,SUM(C10:E10),(IF($A$1=40269,SUM(C10:F10),(IF($A$1=40299,SUM(C10:G10),(IF($A$1=40330,SUM(C10:H10),(IF($A$1=40360,SUM(C10:I10),0)))))))))))))+(IF($A$1=40391,SUM(C10:J10),(IF($A$1=40422,SUM(C10:K10),(IF($A$1=40452,SUM(C10:L10),(IF($A$1=40483,SUM(C10:M10))))))))))+(IF($A$1=40513,SUM(C10:N10),0)) -> 0 | Q10: =(IF($A$1=40179,C10,(IF($A$1=40210,D10,(IF($A$1=40238,E10,(IF($A$1=40269,F10,(IF($A$1=40299,G10,(IF($A$1=40330,H10,(IF($A$1=40360,I10,0)))))))))))))+(IF($A$1=40391,J10,(IF($A$1=40422,K10,(IF($A$1=40452,L10,(IF($A$1=40483,M10)))))))))+(IF($A$1=40513,N10,0)) -> 0
A11: RELATED EXP. | B11: 53244001 | O11: =SUM(C11:N11) -> 0 | P11: =(IF($A$1=40179,C11,(IF($A$1=40210,SUM(C11:D11),(IF($A$1=40238,SUM(C11:E11),(IF($A$1=40269,SUM(C11:F11),(IF($A$1=40299,SUM(C11:G11),(IF($A$1=40330,SUM(C11:H11),(IF($A$1=40360,SUM(C11:I11),0)))))))))))))+(IF($A$1=40391,SUM(C11:J11),(IF($A$1=40422,SUM(C11:K11),(IF($A$1=40452,SUM(C11:L11),(IF($A$1=40483,SUM(C11:M11))))))))))+(IF($A$1=40513,SUM(C11:N11),0)) -> 0 | Q11: =(IF($A$1=40179,C11,(IF($A$1=40210,D11,(IF($A$1=40238,E11,(IF($A$1=40269,F11,(IF($A$1=40299,G11,(IF($A$1=40330,H11,(IF($A$1=40360,I11,0)))))))))))))+(IF($A$1=40391,J11,(IF($A$1=40422,K11,(IF($A$1=40452,L11,(IF($A$1=40483,M11)))))))))+(IF($A$1=40513,N11,0)) -> 0
A12: EMPL. MEALS | B12: 53245001 | O12: =SUM(C12:N12) -> 0 | P12: =(IF($A$1=40179,C12,(IF($A$1=40210,SUM(C12:D12),(IF($A$1=40238,SUM(C12:E12),(IF($A$1=40269,SUM(C12:F12),(IF($A$1=40299,SUM(C12:G12),(IF($A$1=40330,SUM(C12:H12),(IF($A$1=40360,SUM(C12:I12),0)))))))))))))+(IF($A$1=40391,SUM(C12:J12),(IF($A$1=40422,SUM(C12:K12),(IF($A$1=40452,SUM(C12:L12),(IF($A$1=40483,SUM(C12:M12))))))))))+(IF($A$1=40513,SUM(C12:N12),0)) -> 0 | Q12: =(IF($A$1=40179,C12,(IF($A$1=40210,D12,(IF($A$1=40238,E12,(IF($A$1=40269,F12,(IF($A$1=40299,G12,(IF($A$1=40330,H12,(IF($A$1=40360,I12,0)))))))))))))+(IF($A$1=40391,J12,(IF($A$1=40422,K12,(IF($A$1=40452,L12,(IF($A$1=40483,M12)))))))))+(IF($A$1=40513,N12,0)) -> 0
O13: =SUM(C13:N13) -> 0 | P13: =(IF($A$1=40179,C13,(IF($A$1=40210,SUM(C13:D13),(IF($A$1=40238,SUM(C13:E13),(IF($A$1=40269,SUM(C13:F13),(IF($A$1=40299,SUM(C13:G13),(IF($A$1=40330,SUM(C13:H13),(IF($A$1=40360,SUM(C13:I13),0)))))))))))))+(IF($A$1=40391,SUM(C13:J13),(IF($A$1=40422,SUM(C13:K13),(IF($A$1=40452,SUM(C13:L13),(IF($A$1=40483,SUM(C13:M13))))))))))+(IF($A$1=40513,SUM(C13:N13),0)) -> 0 | Q13: =(IF($A$1=40179,C13,(IF($A$1=40210,D13,(IF($A$1=40238,E13,(IF($A$1=40269,F13,(IF($A$1=40299,G13,(IF($A$1=40330,H13,(IF($A$1=40360,I13,0)))))))))))))+(IF($A$1=40391,J13,(IF($A$1=40422,K13,(IF($A$1=40452,L13,(IF($A$1=40483,M13)))))))))+(IF($A$1=40513,N13,0)) -> 0
A14: TOTAL PAY & REL. | C14: 147832.84 | D14: 158624 | O14: =SUM(C14:N14) -> 306456.84 | P14: =(IF($A$1=40179,C14,(IF($A$1=40210,SUM(C14:D14),(IF($A$1=40238,SUM(C14:E14),(IF($A$1=40269,SUM(C14:F14),(IF($A$1=40299,SUM(C14:G14),(IF($A$1=40330,SUM(C14:H14),(IF($A$1=40360,SUM(C14:I14),0)))))))))))))+(IF($A$1=40391,SUM(C14:J14),(IF($A$1=40422,SUM(C14:K14),(IF($A$1=40452,SUM(C14:L14),(IF($A$1=40483,SUM(C14:M14))))))))))+(IF($A$1=40513,SUM(C14:N14),0)) -> 0 | Q14: =(IF($A$1=40179,C14,(IF($A$1=40210,D14,(IF($A$1=40238,E14,(IF($A$1=40269,F14,(IF($A$1=40299,G14,(IF($A$1=40330,H14,(IF($A$1=40360,I14,0)))))))))))))+(IF($A$1=40391,J14,(IF($A$1=40422,K14,(IF($A$1=40452,L14,(IF($A$1=40483,M14)))))))))+(IF($A$1=40513,N14,0)) -> 0 | S14: 40269 | DE14: 4
A15: ELECRICITY | B15: 53257511 | C15: 267068.09 | D15: 312865.7 | O15: =SUM(C15:N15) -> 579933.79 | P15: =(IF($A$1=40179,C15,(IF($A$1=40210,SUM(C15:D15),(IF($A$1=40238,SUM(C15:E15),(IF($A$1=40269,SUM(C15:F15),(IF($A$1=40299,SUM(C15:G15),(IF($A$1=40330,SUM(C15:H15),(IF($A$1=40360,SUM(C15:I15),0)))))))))))))+(IF($A$1=40391,SUM(C15:J15),(IF($A$1=40422,SUM(C15:K15),(IF($A$1=40452,SUM(C15:L15),(IF($A$1=40483,SUM(C15:M15))))))))))+(IF($A$1=40513,SUM(C15:N15),0)) -> 0 | Q15: =(IF($A$1=40179,C15,(IF($A$1=40210,D15,(IF($A$1=40238,E15,(IF($A$1=40269,F15,(IF($A$1=40299,G15,(IF($A$1=40330,H15,(IF($A$1=40360,I15,0)))))))))))))+(IF($A$1=40391,J15,(IF($A$1=40422,K15,(IF($A$1=40452,L15,(IF($A$1=40483,M15)))))))))+(IF($A$1=40513,N15,0)) -> 0 | S15: 40299 | DE15: 5
A16: WATER & SEWAGE | B16: 53257551 | C16: 178948 | D16: 189620 | O16: =SUM(C16:N16) -> 368568 | P16: =(IF($A$1=40179,C16,(IF($A$1=40210,SUM(C16:D16),(IF($A$1=40238,SUM(C16:E16),(IF($A$1=40269,SUM(C16:F16),(IF($A$1=40299,SUM(C16:G16),(IF($A$1=40330,SUM(C16:H16),(IF($A$1=40360,SUM(C16:I16),0)))))))))))))+(IF($A$1=40391,SUM(C16:J16),(IF($A$1=40422,SUM(C16:K16),(IF($A$1=40452,SUM(C16:L16),(IF($A$1=40483,SUM(C16:M16))))))))))+(IF($A$1=40513,SUM(C16:N16),0)) -> 0 | Q16: =(IF($A$1=40179,C16,(IF($A$1=40210,D16,(IF($A$1=40238,E16,(IF($A$1=40269,F16,(IF($A$1=40299,G16,(IF($A$1=40330,H16,(IF($A$1=40360,I16,0)))))))))))))+(IF($A$1=40391,J16,(IF($A$1=40422,K16,(IF($A$1=40452,L16,(IF($A$1=40483,M16)))))))))+(IF($A$1=40513,N16,0)) -> 0 | S16: 40330 | DE16: 6
A17: FUEL | B17: 53257571 | C17: 82735 | D17: 123809 | O17: =SUM(C17:N17) -> 206544 | P17: =(IF($A$1=40179,C17,(IF($A$1=40210,SUM(C17:D17),(IF($A$1=40238,SUM(C17:E17),(IF($A$1=40269,SUM(C17:F17),(IF($A$1=40299,SUM(C17:G17),(IF($A$1=40330,SUM(C17:H17),(IF($A$1=40360,SUM(C17:I17),0)))))))))))))+(IF($A$1=40391,SUM(C17:J17),(IF($A$1=40422,SUM(C17:K17),(IF($A$1=40452,SUM(C17:L17),(IF($A$1=40483,SUM(C17:M17))))))))))+(IF($A$1=40513,SUM(C17:N17),0)) -> 0 | Q17: =(IF($A$1=40179,C17,(IF($A$1=40210,D17,(IF($A$1=40238,E17,(IF($A$1=40269,F17,(IF($A$1=40299,G17,(IF($A$1=40330,H17,(IF($A$1=40360,I17,0)))))))))))))+(IF($A$1=40391,J17,(IF($A$1=40422,K17,(IF($A$1=40452,L17,(IF($A$1=40483,M17)))))))))+(IF($A$1=40513,N17,0)) -> 0 | S17: 40360 | DE17: 7
A18: gas | B18: 0 | C18: 0 | D18: 0 | E18: 0 | F18: 0 | G18: 0 | H18: 0 | O18: =SUM(C18:N18) -> 0 | P18: =(IF($A$1=40179,C18,(IF($A$1=40210,SUM(C18:D18),(IF($A$1=40238,SUM(C18:E18),(IF($A$1=40269,SUM(C18:F18),(IF($A$1=40299,SUM(C18:G18),(IF($A$1=40330,SUM(C18:H18),(IF($A$1=40360,SUM(C18:I18),0)))))))))))))+(IF($A$1=40391,SUM(C18:J18),(IF($A$1=40422,SUM(C18:K18),(IF($A$1=40452,SUM(C18:L18),(IF($A$1=40483,SUM(C18:M18))))))))))+(IF($A$1=40513,SUM(C18:N18),0)) -> 0 | Q18: =(IF($A$1=40179,C18,(IF($A$1=40210,D18,(IF($A$1=40238,E18,(IF($A$1=40269,F18,(IF($A$1=40299,G18,(IF($A$1=40330,H18,(IF($A$1=40360,I18,0)))))))))))))+(IF($A$1=40391,J18,(IF($A$1=40422,K18,(IF($A$1=40452,L18,(IF($A$1=40483,M18)))))))))+(IF($A$1=40513,N18,0)) -> 0 | S18: 40391 | DE18: 8
A19: TOTAL ENERGY | C19: =SUM(C15:C18) -> 528751.09 | D19: =SUM(D15:D18) -> 626294.7 | E19: =SUM(E15:E18) -> 0 | F19: =SUM(F15:F18) -> 0 | G19: =SUM(G15:G18) -> 0 | H19: =SUM(H15:H18) -> 0 | I19: =SUM(I15:I18) -> 0 | J19: =SUM(J15:J18) -> 0 | ... O19: =SUM(O15:O18) -> 1155045.8 | P19: =(IF($A$1=40179,C19,(IF($A$1=40210,SUM(C19:D19),(IF($A$1=40238,SUM(C19:E19),(IF($A$1=40269,SUM(C19:F19),(IF($A$1=40299,SUM(C19:G19),(IF($A$1=40330,SUM(C19:H19),(IF($A$1=40360,SUM(C19:I19),0)))))))))))))+(IF($A$1=40391,SUM(C19:J19),(IF($A$1=40422,SUM(C19:K19),(IF($A$1=40452,SUM(C19:L19),(IF($A$1=40483,SUM(C19:M19))))))))))+(IF($A$1=40513,SUM(C19:N19),0)) -> 0 | Q19: =(IF($A$1=40179,C19,(IF($A$1=40210,D19,(IF($A$1=40238,E19,(IF($A$1=40269,F19,(IF($A$1=40299,G19,(IF($A$1=40330,H19,(IF($A$1=40360,I19,0)))))))))))))+(IF($A$1=40391,J19,(IF($A$1=40422,K19,(IF($A$1=40452,L19,(IF($A$1=40483,M19)))))))))+(IF($A$1=40513,N19,0)) -> 0 | S19: 40422 | DE19: 9
P20: =(IF($A$1=40179,C20,(IF($A$1=40210,SUM(C20:D20),(IF($A$1=40238,SUM(C20:E20),(IF($A$1=40269,SUM(C20:F20),(IF($A$1=40299,SUM(C20:G20),(IF($A$1=40330,SUM(C20:H20),(IF($A$1=40360,SUM(C20:I20),0)))))))))))))+(IF($A$1=40391,SUM(C20:J20),(IF($A$1=40422,SUM(C20:K20),(IF($A$1=40452,SUM(C20:L20),(IF($A$1=40483,SUM(C20:M20))))))))))+(IF($A$1=40513,SUM(C20:N20),0)) -> 0 | Q20: =(IF($A$1=40179,C20,(IF($A$1=40210,D20,(IF($A$1=40238,E20,(IF($A$1=40269,F20,(IF($A$1=40299,G20,(IF($A$1=40330,H20,(IF($A$1=40360,I20,0)))))))))))))+(IF($A$1=40391,J20,(IF($A$1=40422,K20,(IF($A$1=40452,L20,(IF($A$1=40483,M20)))))))))+(IF($A$1=40513,N20,0)) -> 0
A21: OTHER EXPENSES | P21: =(IF($A$1=40179,C21,(IF($A$1=40210,SUM(C21:D21),(IF($A$1=40238,SUM(C21:E21),(IF($A$1=40269,SUM(C21:F21),(IF($A$1=40299,SUM(C21:G21),(IF($A$1=40330,SUM(C21:H21),(IF($A$1=40360,SUM(C21:I21),0)))))))))))))+(IF($A$1=40391,SUM(C21:J21),(IF($A$1=40422,SUM(C21:K21),(IF($A$1=40452,SUM(C21:L21),(IF($A$1=40483,SUM(C21:M21))))))))))+(IF($A$1=40513,SUM(C21:N21),0)) -> 0 | Q21: =(IF($A$1=40179,C21,(IF($A$1=40210,D21,(IF($A$1=40238,E21,(IF($A$1=40269,F21,(IF($A$1=40299,G21,(IF($A$1=40330,H21,(IF($A$1=40360,I21,0)))))))))))))+(IF($A$1=40391,J21,(IF($A$1=40422,K21,(IF($A$1=40452,L21,(IF($A$1=40483,M21)))))))))+(IF($A$1=40513,N21,0)) -> 0
A22: P. & ST. | B22: 53251503 | C22: 2782.3724 | D22: 2209.2805 | E22: 3205.3202 | F22: 2604.6091 | G22: 3235.6987 | H22: 2482.8474 | I22: 3129.5287 | J22: 4085.8967 | K22: 4096.0234 | L22: 4111.0374 | M22: 4007.7194 | N22: 3115.8679 | O22: 39066.202 | P22: =(IF($A$1=40179,C22,(IF($A$1=40210,SUM(C22:D22),(IF($A$1=40238,SUM(C22:E22),(IF($A$1=40269,SUM(C22:F22),(IF($A$1=40299,SUM(C22:G22),(IF($A$1=40330,SUM(C22:H22),(IF($A$1=40360,SUM(C22:I22),0)))))))))))))+(IF($A$1=40391,SUM(C22:J22),(IF($A$1=40422,SUM(C22:K22),(IF($A$1=40452,SUM(C22:L22),(IF($A$1=40483,SUM(C22:M22))))))))))+(IF($A$1=40513,SUM(C22:N22),0)) -> 0 | Q22: =(IF($A$1=40179,C22,(IF($A$1=40210,D22,(IF($A$1=40238,E22,(IF($A$1=40269,F22,(IF($A$1=40299,G22,(IF($A$1=40330,H22,(IF($A$1=40360,I22,0)))))))))))))+(IF($A$1=40391,J22,(IF($A$1=40422,K22,(IF($A$1=40452,L22,(IF($A$1=40483,M22)))))))))+(IF($A$1=40513,N22,0)) -> 0
A23: POSTAGE | B23: 53251912 | C23: 0 | D23: 0 | E23: 0 | F23: 0 | G23: 0 | H23: 0 | I23: 0 | J23: 0 | K23: 0 | L23: 0 | M23: 0 | N23: 0 | O23: 0 | P23: =(IF($A$1=40179,C23,(IF($A$1=40210,SUM(C23:D23),(IF($A$1=40238,SUM(C23:E23),(IF($A$1=40269,SUM(C23:F23),(IF($A$1=40299,SUM(C23:G23),(IF($A$1=40330,SUM(C23:H23),(IF($A$1=40360,SUM(C23:I23),0)))))))))))))+(IF($A$1=40391,SUM(C23:J23),(IF($A$1=40422,SUM(C23:K23),(IF($A$1=40452,SUM(C23:L23),(IF($A$1=40483,SUM(C23:M23))))))))))+(IF($A$1=40513,SUM(C23:N23),0)) -> 0 | Q23: =(IF($A$1=40179,C23,(IF($A$1=40210,D23,(IF($A$1=40238,E23,(IF($A$1=40269,F23,(IF($A$1=40299,G23,(IF($A$1=40330,H23,(IF($A$1=40360,I23,0)))))))))))))+(IF($A$1=40391,J23,(IF($A$1=40422,K23,(IF($A$1=40452,L23,(IF($A$1=40483,M23)))))))))+(IF($A$1=40513,N23,0)) -> 0
A24: TAXICAB | B24: 53251919 | C24: 11276.363 | D24: 10009.133 | E24: 9350.2819 | F24: 12862.267 | G24: 10806.952 | H24: 11155.64 | I24: 12970.205 | J24: 10165.751 | K24: 10061.171 | L24: 10190.726 | M24: 10023.319 | N24: 7435.7374 | O24: 126307.55 | P24: =(IF($A$1=40179,C24,(IF($A$1=40210,SUM(C24:D24),(IF($A$1=40238,SUM(C24:E24),(IF($A$1=40269,SUM(C24:F24),(IF($A$1=40299,SUM(C24:G24),(IF($A$1=40330,SUM(C24:H24),(IF($A$1=40360,SUM(C24:I24),0)))))))))))))+(IF($A$1=40391,SUM(C24:J24),(IF($A$1=40422,SUM(C24:K24),(IF($A$1=40452,SUM(C24:L24),(IF($A$1=40483,SUM(C24:M24))))))))))+(IF($A$1=40513,SUM(C24:N24),0)) -> 0 | Q24: =(IF($A$1=40179,C24,(IF($A$1=40210,D24,(IF($A$1=40238,E24,(IF($A$1=40269,F24,(IF($A$1=40299,G24,(IF($A$1=40330,H24,(IF($A$1=40360,I24,0)))))))))))))+(IF($A$1=40391,J24,(IF($A$1=40422,K24,(IF($A$1=40452,L24,(IF($A$1=40483,M24)))))))))+(IF($A$1=40513,N24,0)) -> 0
A25: R&M DATA PROCESSING | B25: 53252601 | C25: 0 | D25: 0 | E25: 0 | F25: 0 | G25: 0 | H25: 0 | I25: 0 | J25: 0 | K25: 0 | L25: 0 | M25: 0 | N25: 0 | O25: 0 | P25: =(IF($A$1=40179,C25,(IF($A$1=40210,SUM(C25:D25),(IF($A$1=40238,SUM(C25:E25),(IF($A$1=40269,SUM(C25:F25),(IF($A$1=40299,SUM(C25:G25),(IF($A$1=40330,SUM(C25:H25),(IF($A$1=40360,SUM(C25:I25),0)))))))))))))+(IF($A$1=40391,SUM(C25:J25),(IF($A$1=40422,SUM(C25:K25),(IF($A$1=40452,SUM(C25:L25),(IF($A$1=40483,SUM(C25:M25))))))))))+(IF($A$1=40513,SUM(C25:N25),0)) -> 0 | Q25: =(IF($A$1=40179,C25,(IF($A$1=40210,D25,(IF($A$1=40238,E25,(IF($A$1=40269,F25,(IF($A$1=40299,G25,(IF($A$1=40330,H25,(IF($A$1=40360,I25,0)))))))))))))+(IF($A$1=40391,J25,(IF($A$1=40422,K25,(IF($A$1=40452,L25,(IF($A$1=40483,M25)))))))))+(IF($A$1=40513,N25,0)) -> 0
A26: R&M TELEPHONE | B26: 53252603 | C26: 29.374709 | D26: 15.100235 | E26: 33.209819 | F26: 40.453905 | G26: 120.16145 | H26: 0 | I26: 0 | J26: 1532.6831 | K26: 1577.9928 | L26: 1553.3432 | M26: 1485.7035 | N26: 1074.5974 | O26: 7462.6202 | P26: =(IF($A$1=40179,C26,(IF($A$1=40210,SUM(C26:D26),(IF($A$1=40238,SUM(C26:E26),(IF($A$1=40269,SUM(C26:F26),(IF($A$1=40299,SUM(C26:G26),(IF($A$1=40330,SUM(C26:H26),(IF($A$1=40360,SUM(C26:I26),0)))))))))))))+(IF($A$1=40391,SUM(C26:J26),(IF($A$1=40422,SUM(C26:K26),(IF($A$1=40452,SUM(C26:L26),(IF($A$1=40483,SUM(C26:M26))))))))))+(IF($A$1=40513,SUM(C26:N26),0)) -> 0 | Q26: =(IF($A$1=40179,C26,(IF($A$1=40210,D26,(IF($A$1=40238,E26,(IF($A$1=40269,F26,(IF($A$1=40299,G26,(IF($A$1=40330,H26,(IF($A$1=40360,I26,0)))))))))))))+(IF($A$1=40391,J26,(IF($A$1=40422,K26,(IF($A$1=40452,L26,(IF($A$1=40483,M26)))))))))+(IF($A$1=40513,N26,0)) -> 0
A27: R&M KITCHEN EQUIP. | B27: 53252703 | C27: 18610.98 | D27: 7247.7121 | E27: 5707.4428 | F27: 12222.516 | G27: 5623.8033 | H27: 6509.5046 | I27: 15311.566 | J27: 21902.26 | K27: 18614.51 | L27: 19231.518 | M27: 20212.925 | N27: 15102.401 | O27: 166297.14 | P27: =(IF($A$1=40179,C27,(IF($A$1=40210,SUM(C27:D27),(IF($A$1=40238,SUM(C27:E27),(IF($A$1=40269,SUM(C27:F27),(IF($A$1=40299,SUM(C27:G27),(IF($A$1=40330,SUM(C27:H27),(IF($A$1=40360,SUM(C27:I27),0)))))))))))))+(IF($A$1=40391,SUM(C27:J27),(IF($A$1=40422,SUM(C27:K27),(IF($A$1=40452,SUM(C27:L27),(IF($A$1=40483,SUM(C27:M27))))))))))+(IF($A$1=40513,SUM(C27:N27),0)) -> 0 | Q27: =(IF($A$1=40179,C27,(IF($A$1=40210,D27,(IF($A$1=40238,E27,(IF($A$1=40269,F27,(IF($A$1=40299,G27,(IF($A$1=40330,H27,(IF($A$1=40360,I27,0)))))))))))))+(IF($A$1=40391,J27,(IF($A$1=40422,K27,(IF($A$1=40452,L27,(IF($A$1=40483,M27)))))))))+(IF($A$1=40513,N27,0)) -> 0
A28: R&M LAUNDRY & VALET | B28: 53252704 | C28: 5275.9524 | D28: 3912.9834 | E28: 5168.9448 | F28: 3995.7884 | G28: 23112.428 | H28: 3000 | I28: 25530.47 | J28: 10393.274 | K28: 10317.215 | L28: 10411.437 | M28: 8163.5282 | N28: 8407.809 | O28: 117689.83 | P28: =(IF($A$1=40179,C28,(IF($A$1=40210,SUM(C28:D28),(IF($A$1=40238,SUM(C28:E28),(IF($A$1=40269,SUM(C28:F28),(IF($A$1=40299,SUM(C28:G28),(IF($A$1=40330,SUM(C28:H28),(IF($A$1=40360,SUM(C28:I28),0)))))))))))))+(IF($A$1=40391,SUM(C28:J28),(IF($A$1=40422,SUM(C28:K28),(IF($A$1=40452,SUM(C28:L28),(IF($A$1=40483,SUM(C28:M28))))))))))+(IF($A$1=40513,SUM(C28:N28),0)) -> 0 | Q28: =(IF($A$1=40179,C28,(IF($A$1=40210,D28,(IF($A$1=40238,E28,(IF($A$1=40269,F28,(IF($A$1=40299,G28,(IF($A$1=40330,H28,(IF($A$1=40360,I28,0)))))))))))))+(IF($A$1=40391,J28,(IF($A$1=40422,K28,(IF($A$1=40452,L28,(IF($A$1=40483,M28)))))))))+(IF($A$1=40513,N28,0)) -> 0
A29: R&M MINIBARS | B29: 53252705 | C29: 79.899208 | D29: 0 | E29: 0 | F29: 0 | G29: 0 | H29: 0 | I29: 0 | J29: 95.285728 | K29: 102.18196 | L29: 111.19935 | M29: 111.86032 | N29: 108.77325 | O29: 609.19982 | P29: =(IF($A$1=40179,C29,(IF($A$1=40210,SUM(C29:D29),(IF($A$1=40238,SUM(C29:E29),(IF($A$1=40269,SUM(C29:F29),(IF($A$1=40299,SUM(C29:G29),(IF($A$1=40330,SUM(C29:H29),(IF($A$1=40360,SUM(C29:I29),0)))))))))))))+(IF($A$1=40391,SUM(C29:J29),(IF($A$1=40422,SUM(C29:K29),(IF($A$1=40452,SUM(C29:L29),(IF($A$1=40483,SUM(C29:M29))))))))))+(IF($A$1=40513,SUM(C29:N29),0)) -> 0 | Q29: =(IF($A$1=40179,C29,(IF($A$1=40210,D29,(IF($A$1=40238,E29,(IF($A$1=40269,F29,(IF($A$1=40299,G29,(IF($A$1=40330,H29,(IF($A$1=40360,I29,0)))))))))))))+(IF($A$1=40391,J29,(IF($A$1=40422,K29,(IF($A$1=40452,L29,(IF($A$1=40483,M29)))))))))+(IF($A$1=40513,N29,0)) -> 0
A30: R&M REFRIGERATION | B30: 53252706 | C30: 0 | D30: 0 | E30: 0 | F30: 0 | G30: 274.098 | H30: 0 | I30: 0 | J30: 3304.6661 | K30: 3307.9378 | L30: 3323.0619 | M30: 3118.4419 | N30: 2387.0892 | O30: 15715.295 | P30: =(IF($A$1=40179,C30,(IF($A$1=40210,SUM(C30:D30),(IF($A$1=40238,SUM(C30:E30),(IF($A$1=40269,SUM(C30:F30),(IF($A$1=40299,SUM(C30:G30),(IF($A$1=40330,SUM(C30:H30),(IF($A$1=40360,SUM(C30:I30),0)))))))))))))+(IF($A$1=40391,SUM(C30:J30),(IF($A$1=40422,SUM(C30:K30),(IF($A$1=40452,SUM(C30:L30),(IF($A$1=40483,SUM(C30:M30))))))))))+(IF($A$1=40513,SUM(C30:N30),0)) -> 0 | Q30: =(IF($A$1=40179,C30,(IF($A$1=40210,D30,(IF($A$1=40238,E30,(IF($A$1=40269,F30,(IF($A$1=40299,G30,(IF($A$1=40330,H30,(IF($A$1=40360,I30,0)))))))))))))+(IF($A$1=40391,J30,(IF($A$1=40422,K30,(IF($A$1=40452,L30,(IF($A$1=40483,M30)))))))))+(IF($A$1=40513,N30,0)) -> 0
A31: R&M SPRINGS , MATTRESS | B31: 53252707 | C31: 0 | D31: 0 | E31: 0 | F31: 0 | G31: 0 | H31: 0 | I31: 0 | J31: 43.311695 | K31: 52.252139 | L31: 49.058539 | M31: 49.35014 | N31: 47.522294 | O31: 241.49481 | P31: =(IF($A$1=40179,C31,(IF($A$1=40210,SUM(C31:D31),(IF($A$1=40238,SUM(C31:E31),(IF($A$1=40269,SUM(C31:F31),(IF($A$1=40299,SUM(C31:G31),(IF($A$1=40330,SUM(C31:H31),(IF($A$1=40360,SUM(C31:I31),0)))))))))))))+(IF($A$1=40391,SUM(C31:J31),(IF($A$1=40422,SUM(C31:K31),(IF($A$1=40452,SUM(C31:L31),(IF($A$1=40483,SUM(C31:M31))))))))))+(IF($A$1=40513,SUM(C31:N31),0)) -> 0 | Q31: =(IF($A$1=40179,C31,(IF($A$1=40210,D31,(IF($A$1=40238,E31,(IF($A$1=40269,F31,(IF($A$1=40299,G31,(IF($A$1=40330,H31,(IF($A$1=40360,I31,0)))))))))))))+(IF($A$1=40391,J31,(IF($A$1=40422,K31,(IF($A$1=40452,L31,(IF($A$1=40483,M31)))))))))+(IF($A$1=40513,N31,0)) -> 0
A32: R&M T.V & VIDEOS&Singn&Elevator | B32: 53252708 | C32: 26271.989 | D32: 24991.55 | E32: 25766.444 | F32: 14083.458 | G32: 32760.542 | H32: 30820.265 | I32: 27093.718 | J32: 32921.826 | K32: 34279.573 | L32: 31548.543 | M32: 31011.051 | N32: 25248.971 | O32: 336797.93 | P32: =(IF($A$1=40179,C32,(IF($A$1=40210,SUM(C32:D32),(IF($A$1=40238,SUM(C32:E32),(IF($A$1=40269,SUM(C32:F32),(IF($A$1=40299,SUM(C32:G32),(IF($A$1=40330,SUM(C32:H32),(IF($A$1=40360,SUM(C32:I32),0)))))))))))))+(IF($A$1=40391,SUM(C32:J32),(IF($A$1=40422,SUM(C32:K32),(IF($A$1=40452,SUM(C32:L32),(IF($A$1=40483,SUM(C32:M32))))))))))+(IF($A$1=40513,SUM(C32:N32),0)) -> 0 | Q32: =(IF($A$1=40179,C32,(IF($A$1=40210,D32,(IF($A$1=40238,E32,(IF($A$1=40269,F32,(IF($A$1=40299,G32,(IF($A$1=40330,H32,(IF($A$1=40360,I32,0)))))))))))))+(IF($A$1=40391,J32,(IF($A$1=40422,K32,(IF($A$1=40452,L32,(IF($A$1=40483,M32)))))))))+(IF($A$1=40513,N32,0)) -> 0
A33: R&M A/C | B33: 53252801 | C33: 7155.9338 | D33: 13666.574 | E33: 13288.173 | F33: 18794.657 | G33: 26304.825 | H33: 33052.365 | I33: 42520.56 | J33: 22963.856 | K33: 23657.049 | L33: 21575.007 | M33: 16832.206 | N33: 15606.795 | O33: 255418 | P33: =(IF($A$1=40179,C33,(IF($A$1=40210,SUM(C33:D33),(IF($A$1=40238,SUM(C33:E33),(IF($A$1=40269,SUM(C33:F33),(IF($A$1=40299,SUM(C33:G33),(IF($A$1=40330,SUM(C33:H33),(IF($A$1=40360,SUM(C33:I33),0)))))))))))))+(IF($A$1=40391,SUM(C33:J33),(IF($A$1=40422,SUM(C33:K33),(IF($A$1=40452,SUM(C33:L33),(IF($A$1=40483,SUM(C33:M33))))))))))+(IF($A$1=40513,SUM(C33:N33),0)) -> 0 | Q33: =(IF($A$1=40179,C33,(IF($A$1=40210,D33,(IF($A$1=40238,E33,(IF($A$1=40269,F33,(IF($A$1=40299,G33,(IF($A$1=40330,H33,(IF($A$1=40360,I33,0)))))))))))))+(IF($A$1=40391,J33,(IF($A$1=40422,K33,(IF($A$1=40452,L33,(IF($A$1=40483,M33)))))))))+(IF($A$1=40513,N33,0)) -> 0
... A47: TRAVEL EXP. | B47: 53254201 | C47: 3803.5222 | D47: 2648.7794 | E47: 2552.6776 | F47: 3045.5154 | G47: 2357.4996 | H47: 2726.555 | I47: 2399.97 | J47: 5298.415 | K47: 4970.582 | L47: 5021.71 | M47: 4955.644 | N47: 3934.47 | O47: 43715.34 | P47: =(IF($A$1=40179,C47,(IF($A$1=40210,SUM(C47:D47),(IF($A$1=40238,SUM(C47:E47),(IF($A$1=40269,SUM(C47:F47),(IF($A$1=40299,SUM(C47:G47),(IF($A$1=40330,SUM(C47:H47),(IF($A$1=40360,SUM(C47:I47),0)))))))))))))+(IF($A$1=40391,SUM(C47:J47),(IF($A$1=40422,SUM(C47:K47),(IF($A$1=40452,SUM(C47:L47),(IF($A$1=40483,SUM(C47:M47))))))))))+(IF($A$1=40513,SUM(C47:N47),0)) -> 0 | Q47: =(IF($A$1=40179,C47,(IF($A$1=40210,D47,(IF($A$1=40238,E47,(IF($A$1=40269,F47,(IF($A$1=40299,G47,(IF($A$1=40330,H47,(IF($A$1=40360,I47,0)))))))))))))+(IF($A$1=40391,J47,(IF($A$1=40422,K47,(IF($A$1=40452,L47,(IF($A$1=40483,M47)))))))))+(IF($A$1=40513,N47,0)) -> 0
A48: DATA PROCESSING | C48: 0 | D48: 0 | E48: 0 | F48: 0 | G48: 0 | H48: 0 | I48: 0 | J48: 0 | K48: 0 | L48: 0 | M48: 0 | N48: 0 | O48: 0 | P48: =(IF($A$1=40179,C48,(IF($A$1=40210,SUM(C48:D48),(IF($A$1=40238,SUM(C48:E48),(IF($A$1=40269,SUM(C48:F48),(IF($A$1=40299,SUM(C48:G48),(IF($A$1=40330,SUM(C48:H48),(IF($A$1=40360,SUM(C48:I48),0)))))))))))))+(IF($A$1=40391,SUM(C48:J48),(IF($A$1=40422,SUM(C48:K48),(IF($A$1=40452,SUM(C48:L48),(IF($A$1=40483,SUM(C48:M48))))))))))+(IF($A$1=40513,SUM(C48:N48),0)) -> 0 | Q48: =(IF($A$1=40179,C48,(IF($A$1=40210,D48,(IF($A$1=40238,E48,(IF($A$1=40269,F48,(IF($A$1=40299,G48,(IF($A$1=40330,H48,(IF($A$1=40360,I48,0)))))))))))))+(IF($A$1=40391,J48,(IF($A$1=40422,K48,(IF($A$1=40452,L48,(IF($A$1=40483,M48)))))))))+(IF($A$1=40513,N48,0)) -> 0
A49: TELEPHONE | B49: 53255308 | C49: 3220.6431 | D49: 3431.238 | E49: 3826.0002 | F49: 2718.7099 | G49: 2041.662 | H49: 1621.007 | I49: 2137.2499 | J49: 2579.049 | K49: 2552.517 | L49: 2585.385 | M49: 2542.914 | N49: 1886.445 | O49: 31142.82 | P49: =(IF($A$1=40179,C49,(IF($A$1=40210,SUM(C49:D49),(IF($A$1=40238,SUM(C49:E49),(IF($A$1=40269,SUM(C49:F49),(IF($A$1=40299,SUM(C49:G49),(IF($A$1=40330,SUM(C49:H49),(IF($A$1=40360,SUM(C49:I49),0)))))))))))))+(IF($A$1=40391,SUM(C49:J49),(IF($A$1=40422,SUM(C49:K49),(IF($A$1=40452,SUM(C49:L49),(IF($A$1=40483,SUM(C49:M49))))))))))+(IF($A$1=40513,SUM(C49:N49),0)) -> 0 | Q49: =(IF($A$1=40179,C49,(IF($A$1=40210,D49,(IF($A$1=40238,E49,(IF($A$1=40269,F49,(IF($A$1=40299,G49,(IF($A$1=40330,H49,(IF($A$1=40360,I49,0)))))))))))))+(IF($A$1=40391,J49,(IF($A$1=40422,K49,(IF($A$1=40452,L49,(IF($A$1=40483,M49)))))))))+(IF($A$1=40513,N49,0)) -> 0
A50: LICENCE | B50: 53255799 | C50: 0 | D50: 1138.3254 | E50: 0 | F50: 0 | G50: 0 | H50: 0 | I50: 0 | J50: 64.967542 | K50: 69.669519 | L50: 65.411385 | M50: 65.800186 | N50: 63.363059 | O50: 1467.5371 | P50: =(IF($A$1=40179,C50,(IF($A$1=40210,SUM(C50:D50),(IF($A$1=40238,SUM(C50:E50),(IF($A$1=40269,SUM(C50:F50),(IF($A$1=40299,SUM(C50:G50),(IF($A$1=40330,SUM(C50:H50),(IF($A$1=40360,SUM(C50:I50),0)))))))))))))+(IF($A$1=40391,SUM(C50:J50),(IF($A$1=40422,SUM(C50:K50),(IF($A$1=40452,SUM(C50:L50),(IF($A$1=40483,SUM(C50:M50))))))))))+(IF($A$1=40513,SUM(C50:N50),0)) -> 0 | Q50: =(IF($A$1=40179,C50,(IF($A$1=40210,D50,(IF($A$1=40238,E50,(IF($A$1=40269,F50,(IF($A$1=40299,G50,(IF($A$1=40330,H50,(IF($A$1=40360,I50,0)))))))))))))+(IF($A$1=40391,J50,(IF($A$1=40422,K50,(IF($A$1=40452,L50,(IF($A$1=40483,M50)))))))))+(IF($A$1=40513,N50,0)) -> 0
A51: ALLOCATED EXP. | B51: 60-300-143 | C51: 0 | D51: 0 | E51: 0 | F51: 0 | G51: 0 | H51: 0 | I51: 0 | J51: 0 | K51: 0 | L51: 0 | M51: 0 | N51: 0 | O51: 0 | P51: =(IF($A$1=40179,C51,(IF($A$1=40210,SUM(C51:D51),(IF($A$1=40238,SUM(C51:E51),(IF($A$1=40269,SUM(C51:F51),(IF($A$1=40299,SUM(C51:G51),(IF($A$1=40330,SUM(C51:H51),(IF($A$1=40360,SUM(C51:I51),0)))))))))))))+(IF($A$1=40391,SUM(C51:J51),(IF($A$1=40422,SUM(C51:K51),(IF($A$1=40452,SUM(C51:L51),(IF($A$1=40483,SUM(C51:M51))))))))))+(IF($A$1=40513,SUM(C51:N51),0)) -> 0 | Q51: =(IF($A$1=40179,C51,(IF($A$1=40210,D51,(IF($A$1=40238,E51,(IF($A$1=40269,F51,(IF($A$1=40299,G51,(IF($A$1=40330,H51,(IF($A$1=40360,I51,0)))))))))))))+(IF($A$1=40391,J51,(IF($A$1=40422,K51,(IF($A$1=40452,L51,(IF($A$1=40483,M51)))))))))+(IF($A$1=40513,N51,0)) -> 0
A52: LAUNDRY | B52: 53257201 | C52: 3299.3673 | D52: 3398.7144 | E52: 3454.9664 | F52: 3663.6716 | G52: 3888.4677 | H52: 3828.3628 | I52: 3852.9614 | J52: 3943.9156 | K52: 4100.3771 | L52: 3864.66 | M52: 3853.7423 | N52: 3406.3851 | O52: 44555.592 | P52: =(IF($A$1=40179,C52,(IF($A$1=40210,SUM(C52:D52),(IF($A$1=40238,SUM(C52:E52),(IF($A$1=40269,SUM(C52:F52),(IF($A$1=40299,SUM(C52:G52),(IF($A$1=40330,SUM(C52:H52),(IF($A$1=40360,SUM(C52:I52),0)))))))))))))+(IF($A$1=40391,SUM(C52:J52),(IF($A$1=40422,SUM(C52:K52),(IF($A$1=40452,SUM(C52:L52),(IF($A$1=40483,SUM(C52:M52))))))))))+(IF($A$1=40513,SUM(C52:N52),0)) -> 0 | Q52: =(IF($A$1=40179,C52,(IF($A$1=40210,D52,(IF($A$1=40238,E52,(IF($A$1=40269,F52,(IF($A$1=40299,G52,(IF($A$1=40330,H52,(IF($A$1=40360,I52,0)))))))))))))+(IF($A$1=40391,J52,(IF($A$1=40422,K52,(IF($A$1=40452,L52,(IF($A$1=40483,M52)))))))))+(IF($A$1=40513,N52,0)) -> 0
A53: SUPP. TOOLS | B53: 53257498 | C53: 0 | D53: 0 | E53: 0 | F53: 0 | G53: 0 | H53: 221.58981 | I53: 55.885854 | J53: 2436.0121 | K53: 2590.2547 | L53: 2489.4483 | M53: 2183.0308 | N53: 1083.2971 | O53: 11059.519 | P53: =(IF($A$1=40179,C53,(IF($A$1=40210,SUM(C53:D53),(IF($A$1=40238,SUM(C53:E53),(IF($A$1=40269,SUM(C53:F53),(IF($A$1=40299,SUM(C53:G53),(IF($A$1=40330,SUM(C53:H53),(IF($A$1=40360,SUM(C53:I53),0)))))))))))))+(IF($A$1=40391,SUM(C53:J53),(IF($A$1=40422,SUM(C53:K53),(IF($A$1=40452,SUM(C53:L53),(IF($A$1=40483,SUM(C53:M53))))))))))+(IF($A$1=40513,SUM(C53:N53),0)) -> 0 | Q53: =(IF($A$1=40179,C53,(IF($A$1=40210,D53,(IF($A$1=40238,E53,(IF($A$1=40269,F53,(IF($A$1=40299,G53,(IF($A$1=40330,H53,(IF($A$1=40360,I53,0)))))))))))))+(IF($A$1=40391,J53,(IF($A$1=40422,K53,(IF($A$1=40452,L53,(IF($A$1=40483,M53)))))))))+(IF($A$1=40513,N53,0)) -> 0
A54: UNIFORMS | B54: 53257814 | C54: 4376 | D54: 4376 | E54: 4376 | F54: 4376 | G54: 4376 | H54: 4376 | I54: 4376 | J54: 4376 | K54: 4376 | L54: 4376 | M54: 4376 | N54: 4376 | O54: 52512 | P54: =(IF($A$1=40179,C54,(IF($A$1=40210,SUM(C54:D54),(IF($A$1=40238,SUM(C54:E54),(IF($A$1=40269,SUM(C54:F54),(IF($A$1=40299,SUM(C54:G54),(IF($A$1=40330,SUM(C54:H54),(IF($A$1=40360,SUM(C54:I54),0)))))))))))))+(IF($A$1=40391,SUM(C54:J54),(IF($A$1=40422,SUM(C54:K54),(IF($A$1=40452,SUM(C54:L54),(IF($A$1=40483,SUM(C54:M54))))))))))+(IF($A$1=40513,SUM(C54:N54),0)) -> 0 | Q54: =(IF($A$1=40179,C54,(IF($A$1=40210,D54,(IF($A$1=40238,E54,(IF($A$1=40269,F54,(IF($A$1=40299,G54,(IF($A$1=40330,H54,(IF($A$1=40360,I54,0)))))))))))))+(IF($A$1=40391,J54,(IF($A$1=40422,K54,(IF($A$1=40452,L54,(IF($A$1=40483,M54)))))))))+(IF($A$1=40513,N54,0)) -> 0
A55: RUBBISH REMOVAL | B55: 53258201 | C55: 453.992 | D55: 2255.3123 | E55: 588.478 | F55: 829.554 | G55: 1128.3963 | H55: 323.88675 | I55: 559.988 | J55: 7020.7445 | K55: 6948.5185 | L55: 7037.9925 | M55: 6922.377 | N55: 5135.3225 | O55: 39204.562 | P55: =(IF($A$1=40179,C55,(IF($A$1=40210,SUM(C55:D55),(IF($A$1=40238,SUM(C55:E55),(IF($A$1=40269,SUM(C55:F55),(IF($A$1=40299,SUM(C55:G55),(IF($A$1=40330,SUM(C55:H55),(IF($A$1=40360,SUM(C55:I55),0)))))))))))))+(IF($A$1=40391,SUM(C55:J55),(IF($A$1=40422,SUM(C55:K55),(IF($A$1=40452,SUM(C55:L55),(IF($A$1=40483,SUM(C55:M55))))))))))+(IF($A$1=40513,SUM(C55:N55),0)) -> 0 | Q55: =(IF($A$1=40179,C55,(IF($A$1=40210,D55,(IF($A$1=40238,E55,(IF($A$1=40269,F55,(IF($A$1=40299,G55,(IF($A$1=40330,H55,(IF($A$1=40360,I55,0)))))))))))))+(IF($A$1=40391,J55,(IF($A$1=40422,K55,(IF($A$1=40452,L55,(IF($A$1=40483,M55)))))))))+(IF($A$1=40513,N55,0)) -> 0
A56: SUPP. CLEANING | B56: 53258402 | C56: 2050.3547 | D56: 1148.7794 | E56: 1691.4105 | F56: 1208.4308 | G56: 1876.0341 | H56: 2458.9932 | I56: 2102.7674 | J56: 2579.049 | K56: 2552.517 | L56: 2585.385 | M56: 2542.914 | N56: 1886.445 | O56: 24683.08 | P56: =(IF($A$1=40179,C56,(IF($A$1=40210,SUM(C56:D56),(IF($A$1=40238,SUM(C56:E56),(IF($A$1=40269,SUM(C56:F56),(IF($A$1=40299,SUM(C56:G56),(IF($A$1=40330,SUM(C56:H56),(IF($A$1=40360,SUM(C56:I56),0)))))))))))))+(IF($A$1=40391,SUM(C56:J56),(IF($A$1=40422,SUM(C56:K56),(IF($A$1=40452,SUM(C56:L56),(IF($A$1=40483,SUM(C56:M56))))))))))+(IF($A$1=40513,SUM(C56:N56),0)) -> 0 | Q56: =(IF($A$1=40179,C56,(IF($A$1=40210,D56,(IF($A$1=40238,E56,(IF($A$1=40269,F56,(IF($A$1=40299,G56,(IF($A$1=40330,H56,(IF($A$1=40360,I56,0)))))))))))))+(IF($A$1=40391,J56,(IF($A$1=40422,K56,(IF($A$1=40452,L56,(IF($A$1=40483,M56)))))))))+(IF($A$1=40513,N56,0)) -> 0
A57: ELECTRIC BULBS&R.M Electreical | B57: 53258403 | C57: 6986.4807 | D57: 5398.9148 | E57: 4490.1966 | F57: 5754.8273 | G57: 7546.3553 | H57: 20454.424 | I57: 10212.744 | J57: 17235.817 | K57: 16638.924 | L57: 15327.741 | M57: 15931.17 | N57: 12126.666 | O57: 138104.26 | P57: =(IF($A$1=40179,C57,(IF($A$1=40210,SUM(C57:D57),(IF($A$1=40238,SUM(C57:E57),(IF($A$1=40269,SUM(C57:F57),(IF($A$1=40299,SUM(C57:G57),(IF($A$1=40330,SUM(C57:H57),(IF($A$1=40360,SUM(C57:I57),0)))))))))))))+(IF($A$1=40391,SUM(C57:J57),(IF($A$1=40422,SUM(C57:K57),(IF($A$1=40452,SUM(C57:L57),(IF($A$1=40483,SUM(C57:M57))))))))))+(IF($A$1=40513,SUM(C57:N57),0)) -> 0 | Q57: =(IF($A$1=40179,C57,(IF($A$1=40210,D57,(IF($A$1=40238,E57,(IF($A$1=40269,F57,(IF($A$1=40299,G57,(IF($A$1=40330,H57,(IF($A$1=40360,I57,0)))))))))))))+(IF($A$1=40391,J57,(IF($A$1=40422,K57,(IF($A$1=40452,L57,(IF($A$1=40483,M57)))))))))+(IF($A$1=40513,N57,0)) -> 0
A58: Safty | B58: 53258404 | C58: 3349.8918 | D58: 4340.7368 | E58: 11679.55 | F58: 6561.8309 | G58: 9199.3871 | H58: 3376.2975 | I58: 3522.7853 | J58: 4298.415 | K58: 4254.195 | L58: 4308.975 | M58: 4238.19 | N58: 3144.075 | O58: 62274.329 | P58: =(IF($A$1=40179,C58,(IF($A$1=40210,SUM(C58:D58),(IF($A$1=40238,SUM(C58:E58),(IF($A$1=40269,SUM(C58:F58),(IF($A$1=40299,SUM(C58:G58),(IF($A$1=40330,SUM(C58:H58),(IF($A$1=40360,SUM(C58:I58),0)))))))))))))+(IF($A$1=40391,SUM(C58:J58),(IF($A$1=40422,SUM(C58:K58),(IF($A$1=40452,SUM(C58:L58),(IF($A$1=40483,SUM(C58:M58))))))))))+(IF($A$1=40513,SUM(C58:N58),0)) -> 0 | Q58: =(IF($A$1=40179,C58,(IF($A$1=40210,D58,(IF($A$1=40238,E58,(IF($A$1=40269,F58,(IF($A$1=40299,G58,(IF($A$1=40330,H58,(IF($A$1=40360,I58,0)))))))))))))+(IF($A$1=40391,J58,(IF($A$1=40422,K58,(IF($A$1=40452,L58,(IF($A$1=40483,M58)))))))))+(IF($A$1=40513,N58,0)) -> 0
A59: SUPP. MECHANICAL | B59: 53258405 | C59: 0 | D59: 0 | E59: 0 | F59: 0 | G59: 0 | H59: 232.6693 | I59: 8.2224942 | J59: 263.44338 | K59: 290.87024 | L59: 273.63763 | M59: 241.57442 | N59: 167.86986 | O59: 1478.2873 | P59: =(IF($A$1=40179,C59,(IF($A$1=40210,SUM(C59:D59),(IF($A$1=40238,SUM(C59:E59),(IF($A$1=40269,SUM(C59:F59),(IF($A$1=40299,SUM(C59:G59),(IF($A$1=40330,SUM(C59:H59),(IF($A$1=40360,SUM(C59:I59),0)))))))))))))+(IF($A$1=40391,SUM(C59:J59),(IF($A$1=40422,SUM(C59:K59),(IF($A$1=40452,SUM(C59:L59),(IF($A$1=40483,SUM(C59:M59))))))))))+(IF($A$1=40513,SUM(C59:N59),0)) -> 0 | Q59: =(IF($A$1=40179,C59,(IF($A$1=40210,D59,(IF($A$1=40238,E59,(IF($A$1=40269,F59,(IF($A$1=40299,G59,(IF($A$1=40330,H59,(IF($A$1=40360,I59,0)))))))))))))+(IF($A$1=40391,J59,(IF($A$1=40422,K59,(IF($A$1=40452,L59,(IF($A$1=40483,M59)))))))))+(IF($A$1=40513,N59,0)) -> 0
A60: PAINTING & DECORATION | B60: 53258510 | C60: 0 | D60: 7796.3675 | E60: 3412.5952 | F60: 9297.1372 | G60: 5217.8213 | H60: 5608.6819 | I60: 5213.7503 | J60: 17616.944 | K60: 18321.305 | L60: 18209.508 | M60: 17587.288 | N60: 12427.274 | O60: 120708.67 | P60: =(IF($A$1=40179,C60,(IF($A$1=40210,SUM(C60:D60),(IF($A$1=40238,SUM(C60:E60),(IF($A$1=40269,SUM(C60:F60),(IF($A$1=40299,SUM(C60:G60),(IF($A$1=40330,SUM(C60:H60),(IF($A$1=40360,SUM(C60:I60),0)))))))))))))+(IF($A$1=40391,SUM(C60:J60),(IF($A$1=40422,SUM(C60:K60),(IF($A$1=40452,SUM(C60:L60),(IF($A$1=40483,SUM(C60:M60))))))))))+(IF($A$1=40513,SUM(C60:N60),0)) -> 0 | Q60: =(IF($A$1=40179,C60,(IF($A$1=40210,D60,(IF($A$1=40238,E60,(IF($A$1=40269,F60,(IF($A$1=40299,G60,(IF($A$1=40330,H60,(IF($A$1=40360,I60,0)))))))))))))+(IF($A$1=40391,J60,(IF($A$1=40422,K60,(IF($A$1=40452,L60,(IF($A$1=40483,M60)))))))))+(IF($A$1=40513,N60,0)) -> 0
A61: Medical Care | C61: 7031 | D61: 7225 | E61: 7031 | F61: 7225 | G61: 8128 | H61: 7802 | I61: 7700 | J61: 7955 | K61: 7939 | L61: 7347 | M61: 7319 | N61: 7423 | O61: 90125 | P61: =(IF($A$1=40179,C61,(IF($A$1=40210,SUM(C61:D61),(IF($A$1=40238,SUM(C61:E61),(IF($A$1=40269,SUM(C61:F61),(IF($A$1=40299,SUM(C61:G61),(IF($A$1=40330,SUM(C61:H61),(IF($A$1=40360,SUM(C61:I61),0)))))))))))))+(IF($A$1=40391,SUM(C61:J61),(IF($A$1=40422,SUM(C61:K61),(IF($A$1=40452,SUM(C61:L61),(IF($A$1=40483,SUM(C61:M61))))))))))+(IF($A$1=40513,SUM(C61:N61),0)) -> 0 | Q61: =(IF($A$1=40179,C61,(IF($A$1=40210,D61,(IF($A$1=40238,E61,(IF($A$1=40269,F61,(IF($A$1=40299,G61,(IF($A$1=40330,H61,(IF($A$1=40360,I61,0)))))))))))))+(IF($A$1=40391,J61,(IF($A$1=40422,K61,(IF($A$1=40452,L61,(IF($A$1=40483,M61)))))))))+(IF($A$1=40513,N61,0)) -> 0
A62: Employee Housing | C62: 23243.5 | D62: 23243.5 | E62: 23243.5 | F62: 23243.5 | G62: 23243.5 | H62: 23243.5 | I62: 23243.5 | J62: 23243.5 | K62: 23243.5 | L62: 23243.5 | M62: 23243.5 | N62: 23243.5 | O62: 278922 | P62: =(IF($A$1=40179,C62,(IF($A$1=40210,SUM(C62:D62),(IF($A$1=40238,SUM(C62:E62),(IF($A$1=40269,SUM(C62:F62),(IF($A$1=40299,SUM(C62:G62),(IF($A$1=40330,SUM(C62:H62),(IF($A$1=40360,SUM(C62:I62),0)))))))))))))+(IF($A$1=40391,SUM(C62:J62),(IF($A$1=40422,SUM(C62:K62),(IF($A$1=40452,SUM(C62:L62),(IF($A$1=40483,SUM(C62:M62))))))))))+(IF($A$1=40513,SUM(C62:N62),0)) -> 0 | Q62: =(IF($A$1=40179,C62,(IF($A$1=40210,D62,(IF($A$1=40238,E62,(IF($A$1=40269,F62,(IF($A$1=40299,G62,(IF($A$1=40330,H62,(IF($A$1=40360,I62,0)))))))))))))+(IF($A$1=40391,J62,(IF($A$1=40422,K62,(IF($A$1=40452,L62,(IF($A$1=40483,M62)))))))))+(IF($A$1=40513,N62,0)) -> 0
A63: TOTAL OTH EXP Cal. | C63: 341532.7 | D63: 345440.64 | O63: =SUM(C63:N63) -> 686973.34 | P63: =(IF($A$1=40179,C63,(IF($A$1=40210,SUM(C63:D63),(IF($A$1=40238,SUM(C63:E63),(IF($A$1=40269,SUM(C63:F63),(IF($A$1=40299,SUM(C63:G63),(IF($A$1=40330,SUM(C63:H63),(IF($A$1=40360,SUM(C63:I63),0)))))))))))))+(IF($A$1=40391,SUM(C63:J63),(IF($A$1=40422,SUM(C63:K63),(IF($A$1=40452,SUM(C63:L63),(IF($A$1=40483,SUM(C63:M63))))))))))+(IF($A$1=40513,SUM(C63:N63),0)) -> 0 | Q63: =(IF($A$1=40179,C63,(IF($A$1=40210,D63,(IF($A$1=40238,E63,(IF($A$1=40269,F63,(IF($A$1=40299,G63,(IF($A$1=40330,H63,(IF($A$1=40360,I63,0)))))))))))))+(IF($A$1=40391,J63,(IF($A$1=40422,K63,(IF($A$1=40452,L63,(IF($A$1=40483,M63)))))))))+(IF($A$1=40513,N63,0)) -> 0 | S63: 40452 | DE63: 10
A64: TOTAL OTH EXP. | C64: 341533 | D64: 345441 | O64: =SUM(C64:N64) -> 686974 | P64: =(IF($A$1=40179,C64,(IF($A$1=40210,SUM(C64:D64),(IF($A$1=40238,SUM(C64:E64),(IF($A$1=40269,SUM(C64:F64),(IF($A$1=40299,SUM(C64:G64),(IF($A$1=40330,SUM(C64:H64),(IF($A$1=40360,SUM(C64:I64),0)))))))))))))+(IF($A$1=40391,SUM(C64:J64),(IF($A$1=40422,SUM(C64:K64),(IF($A$1=40452,SUM(C64:L64),(IF($A$1=40483,SUM(C64:M64))))))))))+(IF($A$1=40513,SUM(C64:N64),0)) -> 0 | Q64: =(IF($A$1=40179,C64,(IF($A$1=40210,D64,(IF($A$1=40238,E64,(IF($A$1=40269,F64,(IF($A$1=40299,G64,(IF($A$1=40330,H64,(IF($A$1=40360,I64,0)))))))))))))+(IF($A$1=40391,J64,(IF($A$1=40422,K64,(IF($A$1=40452,L64,(IF($A$1=40483,M64)))))))))+(IF($A$1=40513,N64,0)) -> 0 | S64: 40483 | DE64: 11
A65: TOT. EXP. | C65: =C14+C64 -> 489365.84 | D65: =D14+D64 -> 504065 | E65: =E14+E64 -> 0 | F65: =F14+F64 -> 0 | G65: =G14+G64 -> 0 | H65: =H14+H64 -> 0 | I65: =I14+I64 -> 0 | J65: =J14+J64 -> 0 | ... O65: =O14+O64 -> 993430.84 | P65: =(IF($A$1=40179,C65,(IF($A$1=40210,SUM(C65:D65),(IF($A$1=40238,SUM(C65:E65),(IF($A$1=40269,SUM(C65:F65),(IF($A$1=40299,SUM(C65:G65),(IF($A$1=40330,SUM(C65:H65),(IF($A$1=40360,SUM(C65:I65),0)))))))))))))+(IF($A$1=40391,SUM(C65:J65),(IF($A$1=40422,SUM(C65:K65),(IF($A$1=40452,SUM(C65:L65),(IF($A$1=40483,SUM(C65:M65))))))))))+(IF($A$1=40513,SUM(C65:N65),0)) -> 0 | Q65: =(IF($A$1=40179,C65,(IF($A$1=40210,D65,(IF($A$1=40238,E65,(IF($A$1=40269,F65,(IF($A$1=40299,G65,(IF($A$1=40330,H65,(IF($A$1=40360,I65,0)))))))))))))+(IF($A$1=40391,J65,(IF($A$1=40422,K65,(IF($A$1=40452,L65,(IF($A$1=40483,M65)))))))))+(IF($A$1=40513,N65,0)) -> 0 | S65: 40513 | DE65: 12
A66: DEPT. EXPENSES | C66: =C19+C65 -> 1018116.9 | D66: =D19+D65 -> 1130359.7 | E66: =E19+E65 -> 0 | F66: =F19+F65 -> 0 | G66: =G19+G65 -> 0 | H66: =H19+H65 -> 0 | I66: =I19+I65 -> 0 | J66: =J19+J65 -> 0 | ... O66: =O19+O65 -> 2148476.6 | P66: =(IF($A$1=40179,C66,(IF($A$1=40210,SUM(C66:D66),(IF($A$1=40238,SUM(C66:E66),(IF($A$1=40269,SUM(C66:F66),(IF($A$1=40299,SUM(C66:G66),(IF($A$1=40330,SUM(C66:H66),(IF($A$1=40360,SUM(C66:I66),0)))))))))))))+(IF($A$1=40391,SUM(C66:J66),(IF($A$1=40422,SUM(C66:K66),(IF($A$1=40452,SUM(C66:L66),(IF($A$1=40483,SUM(C66:M66))))))))))+(IF($A$1=40513,SUM(C66:N66),0)) -> 0 | Q66: =(IF($A$1=40179,C66,(IF($A$1=40210,D66,(IF($A$1=40238,E66,(IF($A$1=40269,F66,(IF($A$1=40299,G66,(IF($A$1=40330,H66,(IF($A$1=40360,I66,0)))))))))))))+(IF($A$1=40391,J66,(IF($A$1=40422,K66,(IF($A$1=40452,L66,(IF($A$1=40483,M66)))))))))+(IF($A$1=40513,N66,0)) -> 0
A67: GROSS REV. | C67: -9127696.8 | D67: -8962592.4 | E67: -11948019 | F67: -11262665 | G67: -10044681 | H67: -8495470.5 | I67: -10251812 | J67: -12532073 | K67: -10857055 | L67: -12330933 | M67: -11053212 | N67: -9652677.5 | O67: -1.2651889e+08 | P67: -1.2651889e+08 | Q67: =(IF($A$1=40179,C67,(IF($A$1=40210,D67,(IF($A$1=40238,E67,(IF($A$1=40269,F67,(IF($A$1=40299,G67,(IF($A$1=40330,H67,(IF($A$1=40360,I67,0)))))))))))))+(IF($A$1=40391,J67,(IF($A$1=40422,K67,(IF($A$1=40452,L67,(IF($A$1=40483,M67)))))))))+(IF($A$1=40513,N67,0)) -> 0
Q68: =(IF($A$1=40179,C68,(IF($A$1=40210,D68,(IF($A$1=40238,E68,(IF($A$1=40269,F68,(IF($A$1=40299,G68,(IF($A$1=40330,H68,(IF($A$1=40360,I68,0)))))))))))))+(IF($A$1=40391,J68,(IF($A$1=40422,K68,(IF($A$1=40452,L68,(IF($A$1=40483,M68)))))))))+(IF($A$1=40513,N68,0)) -> 0
Q69: =(IF($A$1=40179,C69,(IF($A$1=40210,D69,(IF($A$1=40238,E69,(IF($A$1=40269,F69,(IF($A$1=40299,G69,(IF($A$1=40330,H69,(IF($A$1=40360,I69,0)))))))))))))+(IF($A$1=40391,J69,(IF($A$1=40422,K69,(IF($A$1=40452,L69,(IF($A$1=40483,M69)))))))))+(IF($A$1=40513,N69,0)) -> 0
A70: TOTAL HOTEL EXP. | C70: 4339688.7 | D70: 4402174.6 | E70: 4820027.1 | F70: 4798444.4 | G70: 4801586.5 | H70: 4583696.2 | I70: 5079828.8 | J70: 5224781 | K70: 5108244.5 | L70: 5240588.5 | M70: 5121633.1 | N70: 5022738.7 | O70: 58543432 | P70: 58543433 | Q70: =(IF($A$1=40179,C70,(IF($A$1=40210,D70,(IF($A$1=40238,E70,(IF($A$1=40269,F70,(IF($A$1=40299,G70,(IF($A$1=40330,H70,(IF($A$1=40360,I70,0)))))))))))))+(IF($A$1=40391,J70,(IF($A$1=40422,K70,(IF($A$1=40452,L70,(IF($A$1=40483,M70)))))))))+(IF($A$1=40513,N70,0)) -> 0
Q71: =(IF($A$1=40179,C71,(IF($A$1=40210,D71,(IF($A$1=40238,E71,(IF($A$1=40269,F71,(IF($A$1=40299,G71,(IF($A$1=40330,H71,(IF($A$1=40360,I71,0)))))))))))))+(IF($A$1=40391,J71,(IF($A$1=40422,K71,(IF($A$1=40452,L71,(IF($A$1=40483,M71)))))))))+(IF($A$1=40513,N71,0)) -> 0
A72: G.O.P. | C72: -4788008.1 | D72: -4560417.8 | E72: -7127992.3 | F72: -6464220.8 | G72: -5243094.1 | H72: -3911774.2 | I72: -5170982.8 | J72: -7307291.6 | K72: -5748810.9 | L72: -7090344.9 | M72: -5931579.3 | N72: -4629938.8 | O72: -67974456 | P72: -67974455 | Q72: =(IF($A$1=40179,C72,(IF($A$1=40210,D72,(IF($A$1=40238,E72,(IF($A$1=40269,F72,(IF($A$1=40299,G72,(IF($A$1=40330,H72,(IF($A$1=40360,I72,0)))))))))))))+(IF($A$1=40391,J72,(IF($A$1=40422,K72,(IF($A$1=40452,L72,(IF($A$1=40483,M72)))))))))+(IF($A$1=40513,N72,0)) -> 0
Q73: =(IF($A$1=40179,C73,(IF($A$1=40210,D73,(IF($A$1=40238,E73,(IF($A$1=40269,F73,(IF($A$1=40299,G73,(IF($A$1=40330,H73,(IF($A$1=40360,I73,0)))))))))))))+(IF($A$1=40391,J73,(IF($A$1=40422,K73,(IF($A$1=40452,L73,(IF($A$1=40483,M73)))))))))+(IF($A$1=40513,N73,0)) -> 0
C74: 20636 | D74: 22021 | E74: 26749 | F74: 25138 | G74: 24918 | H74: 22301 | I74: 25454 | J74: 26051 | K74: 25783 | L74: 26115 | M74: 25686 | N74: 19055 | O74: 289907 | P74: 289908 | Q74: =(IF($A$1=40179,C74,(IF($A$1=40210,D74,(IF($A$1=40238,E74,(IF($A$1=40269,F74,(IF($A$1=40299,G74,(IF($A$1=40330,H74,(IF($A$1=40360,I74,0)))))))))))))+(IF($A$1=40391,J74,(IF($A$1=40422,K74,(IF($A$1=40452,L74,(IF($A$1=40483,M74)))))))))+(IF($A$1=40513,N74,0)) -> 0
C75: 11.586234 | D75: 10.630652 | E75: 9.1936995 | F75: 9.789965 | G75: 13.270516 | H75: 16.399437 | I75: 17.267995 | J75: 16.028578 | Q75: =(IF($A$1=40179,C75,(IF($A$1=40210,D75,(IF($A$1=40238,E75,(IF($A$1=40269,F75,(IF($A$1=40299,G75,(IF($A$1=40330,H75,(IF($A$1=40360,I75,0)))))))))))))+(IF($A$1=40391,J75,(IF($A$1=40422,K75,(IF($A$1=40452,L75,(IF($A$1=40483,M75)))))))))+(IF($A$1=40513,N75,0)) -> 0
Q76: =(IF($A$1=40179,C76,(IF($A$1=40210,D76,(IF($A$1=40238,E76,(IF($A$1=40269,F76,(IF($A$1=40299,G76,(IF($A$1=40330,H76,(IF($A$1=40360,I76,0)))))))))))))+(IF($A$1=40391,J76,(IF($A$1=40422,K76,(IF($A$1=40452,L76,(IF($A$1=40483,M76)))))))))+(IF($A$1=40513,N76,0)) -> 0
A77: BRM | B77: ENRGY | C77: 25.912451 | D77: 23.814305 | E77: 19.967275 | F77: 21.979437 | G77: 22.78727 | H77: 27.077185 | I77: 26.680467 | J77: 28.146048 | K77: 26.264429 | L77: 26.002224 | M77: 23.993503 | N77: 28.932986 | O77: 25.020526 | P77: 26.020526 | Q77: =(IF($A$1=40179,C77,(IF($A$1=40210,D77,(IF($A$1=40238,E77,(IF($A$1=40269,F77,(IF($A$1=40299,G77,(IF($A$1=40330,H77,(IF($A$1=40360,I77,0)))))))))))))+(IF($A$1=40391,J77,(IF($A$1=40422,K77,(IF($A$1=40452,L77,(IF($A$1=40483,M77)))))))))+(IF($A$1=40513,N77,0)) -> 0
A78: PLAN | C78: 31.709013 | D78: 31.669965 | E78: 31.737435 | F78: 31.750688 | G78: 31.701568 | H78: 31.669724 | I78: 30.902486 | J78: 30.917958 | K78: 31.877764 | L78: 31.892454 | M78: 31.893063 | N78: 30.864895 | O78: 31.481775 | P78: 32.481775 | Q78: =(IF($A$1=40179,C78,(IF($A$1=40210,D78,(IF($A$1=40238,E78,(IF($A$1=40269,F78,(IF($A$1=40299,G78,(IF($A$1=40330,H78,(IF($A$1=40360,I78,0)))))))))))))+(IF($A$1=40391,J78,(IF($A$1=40422,K78,(IF($A$1=40452,L78,(IF($A$1=40483,M78)))))))))+(IF($A$1=40513,N78,0)) -> 0
I79: 33.077812 | J79: 21.968969 | K79: 21.467505 | L79: 18.132301 | M79: 22.328025 | N79: 29.022465 | Q79: =(IF($A$1=40179,C79,(IF($A$1=40210,D79,(IF($A$1=40238,E79,(IF($A$1=40269,F79,(IF($A$1=40299,G79,(IF($A$1=40330,H79,(IF($A$1=40360,I79,0)))))))))))))+(IF($A$1=40391,J79,(IF($A$1=40422,K79,(IF($A$1=40452,L79,(IF($A$1=40483,M79)))))))))+(IF($A$1=40513,N79,0)) -> 0
D80: 0 | I80: 7.4792985 | Q80: =(IF($A$1=40179,C80,(IF($A$1=40210,D80,(IF($A$1=40238,E80,(IF($A$1=40269,F80,(IF($A$1=40299,G80,(IF($A$1=40330,H80,(IF($A$1=40360,I80,0)))))))))))))+(IF($A$1=40391,J80,(IF($A$1=40422,K80,(IF($A$1=40452,L80,(IF($A$1=40483,M80)))))))))+(IF($A$1=40513,N80,0)) -> 0
Q81: =(IF($A$1=40179,C81,(IF($A$1=40210,D81,(IF($A$1=40238,E81,(IF($A$1=40269,F81,(IF($A$1=40299,G81,(IF($A$1=40330,H81,(IF($A$1=40360,I81,0)))))))))))))+(IF($A$1=40391,J81,(IF($A$1=40422,K81,(IF($A$1=40452,L81,(IF($A$1=40483,M81)))))))))+(IF($A$1=40513,N81,0)) -> 0
A82: BRM | C82: 17.389222 | D82: 15.836902 | E82: 12.879108 | F82: 14.233447 | G82: 16.1692 | H82: 18.324236 | I82: 19.379726 | J82: 18.779652 | K82: 19.045552 | L82: 18.731174 | M82: 18.225018 | N82: 21.1084 | O82: 17.435004 | P82: 18.435004 | Q82: =(IF($A$1=40179,C82,(IF($A$1=40210,D82,(IF($A$1=40238,E82,(IF($A$1=40269,F82,(IF($A$1=40299,G82,(IF($A$1=40330,H82,(IF($A$1=40360,I82,0)))))))))))))+(IF($A$1=40391,J82,(IF($A$1=40422,K82,(IF($A$1=40452,L82,(IF($A$1=40483,M82)))))))))+(IF($A$1=40513,N82,0)) -> 0
A83: PLAN | C83: 19.980275 | D83: 22.122904 | E83: 18.39799 | F83: 17.68532 | G83: 20.37327 | H83: 22.127222 | I83: 11.774944 | J83: 10.699441 | K83: 13.703179 | L83: 12.648051 | M83: 12.574183 | N83: 14.697918 | O83: 14.881456 | P83: 15.881456 | Q83: =(IF($A$1=40179,C83,(IF($A$1=40210,D83,(IF($A$1=40238,E83,(IF($A$1=40269,F83,(IF($A$1=40299,G83,(IF($A$1=40330,H83,(IF($A$1=40360,I83,0)))))))))))))+(IF($A$1=40391,J83,(IF($A$1=40422,K83,(IF($A$1=40452,L83,(IF($A$1=40483,M83)))))))))+(IF($A$1=40513,N83,0)) -> 0
I84: 9.9758479 | J84: 6.7279967 | K84: 12.997904 | L84: 12.470436 | M84: 22.08176 | N84: 29.386764 | Q84: =(IF($A$1=40179,C84,(IF($A$1=40210,D84,(IF($A$1=40238,E84,(IF($A$1=40269,F84,(IF($A$1=40299,G84,(IF($A$1=40330,H84,(IF($A$1=40360,I84,0)))))))))))))+(IF($A$1=40391,J84,(IF($A$1=40422,K84,(IF($A$1=40452,L84,(IF($A$1=40483,M84)))))))))+(IF($A$1=40513,N84,0)) -> 0
Q85: =(IF($A$1=40179,C85,(IF($A$1=40210,D85,(IF($A$1=40238,E85,(IF($A$1=40269,F85,(IF($A$1=40299,G85,(IF($A$1=40330,H85,(IF($A$1=40360,I85,0)))))))))))))+(IF($A$1=40391,J85,(IF($A$1=40422,K85,(IF($A$1=40452,L85,(IF($A$1=40483,M85)))))))))+(IF($A$1=40513,N85,0)) -> 0
A86: BRM | C86: 43.301673 | D86: 39.651207 | E86: 32.846383 | F86: 36.212884 | G86: 38.956469 | H86: 45.401421 | I86: 46.060193 | J86: 46.9257 | K86: 45.309982 | L86: 44.733398 | M86: 42.218521 | N86: 50.041385 | O86: 42.45553 | P86: 43.45553 | Q86: =(IF($A$1=40179,C86,(IF($A$1=40210,D86,(IF($A$1=40238,E86,(IF($A$1=40269,F86,(IF($A$1=40299,G86,(IF($A$1=40330,H86,(IF($A$1=40360,I86,0)))))))))))))+(IF($A$1=40391,J86,(IF($A$1=40422,K86,(IF($A$1=40452,L86,(IF($A$1=40483,M86)))))))))+(IF($A$1=40513,N86,0)) -> 0
A87: PLAN | C87: 51.689288 | D87: 53.792869 | E87: 50.135425 | F87: 49.436008 | G87: 52.074838 | H87: 53.796945 | I87: 42.67743 | J87: 41.617399 | K87: 45.580943 | L87: 44.540505 | M87: 44.467247 | N87: 45.562813 | O87: 46.363231 | P87: 47.363231 | Q87: =(IF($A$1=40179,C87,(IF($A$1=40210,D87,(IF($A$1=40238,E87,(IF($A$1=40269,F87,(IF($A$1=40299,G87,(IF($A$1=40330,H87,(IF($A$1=40360,I87,0)))))))))))))+(IF($A$1=40391,J87,(IF($A$1=40422,K87,(IF($A$1=40452,L87,(IF($A$1=40483,M87)))))))))+(IF($A$1=40513,N87,0)) -> 0
A88: LAST YEAR | I88: 43.05366 | J88: 28.696966 | K88: 34.465409 | L88: 30.602738 | M88: 44.409785 | N88: 58.409229 | Q88: =(IF($A$1=40179,C88,(IF($A$1=40210,D88,(IF($A$1=40238,E88,(IF($A$1=40269,F88,(IF($A$1=40299,G88,(IF($A$1=40330,H88,(IF($A$1=40360,I88,0)))))))))))))+(IF($A$1=40391,J88,(IF($A$1=40422,K88,(IF($A$1=40452,L88,(IF($A$1=40483,M88)))))))))+(IF($A$1=40513,N88,0)) -> 0
Q89: =(IF($A$1=40179,C89,(IF($A$1=40210,D89,(IF($A$1=40238,E89,(IF($A$1=40269,F89,(IF($A$1=40299,G89,(IF($A$1=40330,H89,(IF($A$1=40360,I89,0)))))))))))))+(IF($A$1=40391,J89,(IF($A$1=40422,K89,(IF($A$1=40452,L89,(IF($A$1=40483,M89)))))))))+(IF($A$1=40513,N89,0)) -> 0
I90: 9523 | J90: 14566 | K90: 11925 | L90: 13953 | M90: 12182 | N90: 8235 | Q90: =(IF($A$1=40179,C90,(IF($A$1=40210,D90,(IF($A$1=40238,E90,(IF($A$1=40269,F90,(IF($A$1=40299,G90,(IF($A$1=40330,H90,(IF($A$1=40360,I90,0)))))))))))))+(IF($A$1=40391,J90,(IF($A$1=40422,K90,(IF($A$1=40452,L90,(IF($A$1=40483,M90)))))))))+(IF($A$1=40513,N90,0)) -> 0
Q91: =(IF($A$1=40179,C91,(IF($A$1=40210,D91,(IF($A$1=40238,E91,(IF($A$1=40269,F91,(IF($A$1=40299,G91,(IF($A$1=40330,H91,(IF($A$1=40360,I91,0)))))))))))))+(IF($A$1=40391,J91,(IF($A$1=40422,K91,(IF($A$1=40452,L91,(IF($A$1=40483,M91)))))))))+(IF($A$1=40513,N91,0)) -> 0
A92: Per Occ.Rooms | O92: 13.28324 | P92: 14.28324 | Q92: =(IF($A$1=40179,C92,(IF($A$1=40210,D92,(IF($A$1=40238,E92,(IF($A$1=40269,F92,(IF($A$1=40299,G92,(IF($A$1=40330,H92,(IF($A$1=40360,I92,0)))))))))))))+(IF($A$1=40391,J92,(IF($A$1=40422,K92,(IF($A$1=40452,L92,(IF($A$1=40483,M92)))))))))+(IF($A$1=40513,N92,0)) -> 0
A93: ENERGY COSTS | Q93: =(IF($A$1=40179,C93,(IF($A$1=40210,D93,(IF($A$1=40238,E93,(IF($A$1=40269,F93,(IF($A$1=40299,G93,(IF($A$1=40330,H93,(IF($A$1=40360,I93,0)))))))))))))+(IF($A$1=40391,J93,(IF($A$1=40422,K93,(IF($A$1=40452,L93,(IF($A$1=40483,M93)))))))))+(IF($A$1=40513,N93,0)) -> 0
A94: ELECRICITY | C94: 9.3027833 | D94: 8.3311928 | E94: 9.6786446 | F94: 8.8408989 | G94: 11.408475 | H94: 13.925292 | I94: 14.083571 | J94: 14 | K94: 12.55 | L94: 11 | M94: 9.73 | N94: 9.85 | O94: 11.079544 | P94: 12.079544 | Q94: =(IF($A$1=40179,C94,(IF($A$1=40210,D94,(IF($A$1=40238,E94,(IF($A$1=40269,F94,(IF($A$1=40299,G94,(IF($A$1=40330,H94,(IF($A$1=40360,I94,0)))))))))))))+(IF($A$1=40391,J94,(IF($A$1=40422,K94,(IF($A$1=40452,L94,(IF($A$1=40483,M94)))))))))+(IF($A$1=40513,N94,0)) -> 0
A95: WATER & SEWAGE | C95: 6.7445825 | D95: 5.8947395 | E95: 5.8752562 | F95: 5.9011104 | G95: 5.7837343 | H95: 6.5260624 | I95: 5.9452909 | J95: 8.7330288 | K95: 9.5 | L95: 7.4 | M95: 6.8 | N95: 6.88 | O95: 6.8012938 | P95: 7.8012938 | Q95: =(IF($A$1=40179,C95,(IF($A$1=40210,D95,(IF($A$1=40238,E95,(IF($A$1=40269,F95,(IF($A$1=40299,G95,(IF($A$1=40330,H95,(IF($A$1=40360,I95,0)))))))))))))+(IF($A$1=40391,J95,(IF($A$1=40422,K95,(IF($A$1=40452,L95,(IF($A$1=40483,M95)))))))))+(IF($A$1=40513,N95,0)) -> 0
A96: FUEL | C96: 2.3654573 | D96: 2.4605466 | E96: 1.8873252 | F96: 1.905012 | G96: 1.5736817 | H96: 1.7856361 | I96: 1.8119245 | J96: 1.6 | K96: 1.6 | L96: 2.5 | M96: 2.53 | N96: 2.7 | O96: 2.1710695 | P96: 3.1710695 | Q96: =(IF($A$1=40179,C96,(IF($A$1=40210,D96,(IF($A$1=40238,E96,(IF($A$1=40269,F96,(IF($A$1=40299,G96,(IF($A$1=40330,H96,(IF($A$1=40360,I96,0)))))))))))))+(IF($A$1=40391,J96,(IF($A$1=40422,K96,(IF($A$1=40452,L96,(IF($A$1=40483,M96)))))))))+(IF($A$1=40513,N96,0)) -> 0
A97: gas | C97: 0.2 | D97: 0.2 | E97: 0.2 | F97: 0.2 | G97: 0.2 | H97: 0.2 | I97: 0.41038028 | J97: 0.11981877 | K97: 0.15165877 | L97: 0.22091902 | M97: 0.21409109 | N97: 0.28555111 | O97: 0.11753947 | P97: 1.1175395 | Q97: =(IF($A$1=40179,C97,(IF($A$1=40210,D97,(IF($A$1=40238,E97,(IF($A$1=40269,F97,(IF($A$1=40299,G97,(IF($A$1=40330,H97,(IF($A$1=40360,I97,0)))))))))))))+(IF($A$1=40391,J97,(IF($A$1=40422,K97,(IF($A$1=40452,L97,(IF($A$1=40483,M97)))))))))+(IF($A$1=40513,N97,0)) -> 0
A98: TOTAL ENERGY | C98: 18.412823 | D98: 18.686479 | E98: 17.441226 | F98: 16.647021 | G98: 18.765891 | H98: 22.236991 | I98: 22.251166 | J98: 24.452848 | K98: 23.801659 | L98: 21.120919 | M98: 19.274091 | N98: 19.715551 | O98: 20.169447 | P98: 21.169447 | Q98: =(IF($A$1=40179,C98,(IF($A$1=40210,D98,(IF($A$1=40238,E98,(IF($A$1=40269,F98,(IF($A$1=40299,G98,(IF($A$1=40330,H98,(IF($A$1=40360,I98,0)))))))))))))+(IF($A$1=40391,J98,(IF($A$1=40422,K98,(IF($A$1=40452,L98,(IF($A$1=40483,M98)))))))))+(IF($A$1=40513,N98,0)) -> 0
A99: OTHER EXPENSES | Q99: =(IF($A$1=40179,C99,(IF($A$1=40210,D99,(IF($A$1=40238,E99,(IF($A$1=40269,F99,(IF($A$1=40299,G99,(IF($A$1=40330,H99,(IF($A$1=40360,I99,0)))))))))))))+(IF($A$1=40391,J99,(IF($A$1=40422,K99,(IF($A$1=40452,L99,(IF($A$1=40483,M99)))))))))+(IF($A$1=40513,N99,0)) -> 0
A100: P. & ST. | C100: 0.05 | D100: 0.07 | E100: 0.058887826 | F100: 0.11682173 | G100: 0.11255377 | H100: 0.070112478 | I100: 0.090011974 | J100: 0.15 | K100: 0.15 | L100: 0.15 | M100: 0.15 | N100: 0.15 | O100: 0.11484106 | P100: 1.1148411 | Q100: =(IF($A$1=40179,C100,(IF($A$1=40210,D100,(IF($A$1=40238,E100,(IF($A$1=40269,F100,(IF($A$1=40299,G100,(IF($A$1=40330,H100,(IF($A$1=40360,I100,0)))))))))))))+(IF($A$1=40391,J100,(IF($A$1=40422,K100,(IF($A$1=40452,L100,(IF($A$1=40483,M100)))))))))+(IF($A$1=40513,N100,0)) -> 0
A101: POSTAGE | C101: 0 | D101: 0 | E101: 0 | F101: 0 | G101: 0 | H101: 0 | I101: 0 | J101: 0 | K101: 0 | L101: 0 | M101: 0 | N101: 0 | O101: 0 | P101: 1 | Q101: =(IF($A$1=40179,C101,(IF($A$1=40210,D101,(IF($A$1=40238,E101,(IF($A$1=40269,F101,(IF($A$1=40299,G101,(IF($A$1=40330,H101,(IF($A$1=40360,I101,0)))))))))))))+(IF($A$1=40391,J101,(IF($A$1=40422,K101,(IF($A$1=40452,L101,(IF($A$1=40483,M101)))))))))+(IF($A$1=40513,N101,0)) -> 0
A102: TAXICAB | C102: 0.22 | D102: 0.24 | E102: 0.22 | F102: 0.25735294 | G102: 0.33805958 | H102: 0.31791326 | I102: 0.25302448 | J102: 0.33 | K102: 0.33 | L102: 0.33 | M102: 0.33 | N102: 0.33 | O102: 0.29221052 | P102: 1.2922105 | Q102: =(IF($A$1=40179,C102,(IF($A$1=40210,D102,(IF($A$1=40238,E102,(IF($A$1=40269,F102,(IF($A$1=40299,G102,(IF($A$1=40330,H102,(IF($A$1=40360,I102,0)))))))))))))+(IF($A$1=40391,J102,(IF($A$1=40422,K102,(IF($A$1=40452,L102,(IF($A$1=40483,M102)))))))))+(IF($A$1=40513,N102,0)) -> 0
A103: R&M DATA PROCESSING | C103: 0 | D103: 0 | E103: 0 | F103: 0 | G103: 0 | H103: 0 | I103: 0 | J103: 0 | K103: 0 | L103: 0 | M103: 0 | N103: 0 | O103: 0 | P103: 1 | Q103: =(IF($A$1=40179,C103,(IF($A$1=40210,D103,(IF($A$1=40238,E103,(IF($A$1=40269,F103,(IF($A$1=40299,G103,(IF($A$1=40330,H103,(IF($A$1=40360,I103,0)))))))))))))+(IF($A$1=40391,J103,(IF($A$1=40422,K103,(IF($A$1=40452,L103,(IF($A$1=40483,M103)))))))))+(IF($A$1=40513,N103,0)) -> 0
A104: R&M TELEPHONE | C104: 0.07 | D104: 0.07 | E104: 0.07 | F104: 0.07 | G104: 0.07 | H104: 0.07 | I104: 0.07 | J104: 0.07 | K104: 0.07 | L104: 0.07 | M104: 0.07 | N104: 0.07 | O104: 0.064126105 | P104: 1.0641261 | Q104: =(IF($A$1=40179,C104,(IF($A$1=40210,D104,(IF($A$1=40238,E104,(IF($A$1=40269,F104,(IF($A$1=40299,G104,(IF($A$1=40330,H104,(IF($A$1=40360,I104,0)))))))))))))+(IF($A$1=40391,J104,(IF($A$1=40422,K104,(IF($A$1=40452,L104,(IF($A$1=40483,M104)))))))))+(IF($A$1=40513,N104,0)) -> 0
A105: R&M KITCHEN EQUIP. | C105: 0.21 | D105: 0.26 | E105: 0.08 | F105: 0.34543818 | G105: 0.19332484 | H105: 0.41463521 | I105: 0.43672323 | J105: 0.65 | K105: 0.53 | L105: 0.55 | M105: 0.6 | N105: 0.55 | O105: 0.40816824 | P105: 1.4081682 | Q105: =(IF($A$1=40179,C105,(IF($A$1=40210,D105,(IF($A$1=40238,E105,(IF($A$1=40269,F105,(IF($A$1=40299,G105,(IF($A$1=40330,H105,(IF($A$1=40360,I105,0)))))))))))))+(IF($A$1=40391,J105,(IF($A$1=40422,K105,(IF($A$1=40452,L105,(IF($A$1=40483,M105)))))))))+(IF($A$1=40513,N105,0)) -> 0
A106: R&M LAUNDRY & VALET | C106: 0.08 | D106: 0.14 | E106: 0.04 | F106: 0 | G106: 0.26461686 | H106: 0.05033043 | I106: 0.45410628 | J106: 0.24 | K106: 0.24 | L106: 0.24 | M106: 0.17 | N106: 0.24 | O106: 0.1810881 | P106: 1.1810881 | Q106: =(IF($A$1=40179,C106,(IF($A$1=40210,D106,(IF($A$1=40238,E106,(IF($A$1=40269,F106,(IF($A$1=40299,G106,(IF($A$1=40330,H106,(IF($A$1=40360,I106,0)))))))))))))+(IF($A$1=40391,J106,(IF($A$1=40422,K106,(IF($A$1=40452,L106,(IF($A$1=40483,M106)))))))))+(IF($A$1=40513,N106,0)) -> 0
A107: R&M MINIBARS | C107: 0 | D107: 0 | E107: 0 | F107: 0 | G107: 0 | H107: 0 | I107: 0 | J107: 0 | K107: 0 | L107: 0 | M107: 0 | N107: 0 | O107: 0 | P107: 1 | Q107: =(IF($A$1=40179,C107,(IF($A$1=40210,D107,(IF($A$1=40238,E107,(IF($A$1=40269,F107,(IF($A$1=40299,G107,(IF($A$1=40330,H107,(IF($A$1=40360,I107,0)))))))))))))+(IF($A$1=40391,J107,(IF($A$1=40422,K107,(IF($A$1=40452,L107,(IF($A$1=40483,M107)))))))))+(IF($A$1=40513,N107,0)) -> 0
A108: R&M REFRIGERATION | C108: 0 | D108: 0.10274324 | E108: 0.022817325 | F108: 0 | G108: 0.36255377 | H108: 0 | I108: 0.21801065 | J108: 0.12 | K108: 0.12 | L108: 0.12 | M108: 0.12 | N108: 0.12 | O108: 0.11096608 | P108: 1.1109661 | Q108: =(IF($A$1=40179,C108,(IF($A$1=40210,D108,(IF($A$1=40238,E108,(IF($A$1=40269,F108,(IF($A$1=40299,G108,(IF($A$1=40330,H108,(IF($A$1=40360,I108,0)))))))))))))+(IF($A$1=40391,J108,(IF($A$1=40422,K108,(IF($A$1=40452,L108,(IF($A$1=40483,M108)))))))))+(IF($A$1=40513,N108,0)) -> 0
A109: R&M SPRINGS , MATTRESS | C109: 0 | D109: 0 | E109: 0 | F109: 0 | G109: 0 | H109: 0 | I109: 0 | J109: 0.018721683 | K109: 0.023696682 | L109: 0.020083548 | M109: 0.019462826 | N109: 0.025959192 | O109: 0.0089481615 | P109: 1.0089482 | Q109: =(IF($A$1=40179,C109,(IF($A$1=40210,D109,(IF($A$1=40238,E109,(IF($A$1=40269,F109,(IF($A$1=40299,G109,(IF($A$1=40330,H109,(IF($A$1=40360,I109,0)))))))))))))+(IF($A$1=40391,J109,(IF($A$1=40422,K109,(IF($A$1=40452,L109,(IF($A$1=40483,M109)))))))))+(IF($A$1=40513,N109,0)) -> 0
A110: R&M T.V & VIDEOS | C110: 0.73 | D110: 0.71 | E110: 0.73 | F110: 0.69927971 | G110: 0.73 | H110: 0.73 | I110: 0.70147405 | J110: 0.9 | K110: 0.95 | L110: 0.9234 | M110: 0.921 | N110: 0.96775868 | O110: 0.81580659 | P110: 1.8158066 | Q110: =(IF($A$1=40179,C110,(IF($A$1=40210,D110,(IF($A$1=40238,E110,(IF($A$1=40269,F110,(IF($A$1=40299,G110,(IF($A$1=40330,H110,(IF($A$1=40360,I110,0)))))))))))))+(IF($A$1=40391,J110,(IF($A$1=40422,K110,(IF($A$1=40452,L110,(IF($A$1=40483,M110)))))))))+(IF($A$1=40513,N110,0)) -> 0
A111: R&M A/C | C111: 0.19 | D111: 0.55 | E111: 0.25 | F111: 0.29104142 | G111: 0.30328979 | H111: 0.72025034 | I111: 0.86659234 | J111: 0.95 | K111: 0.95 | L111: 0.9 | M111: 0.9 | N111: 0.9 | O111: 0.65198077 | P111: 1.6519808 | Q111: =(IF($A$1=40179,C111,(IF($A$1=40210,D111,(IF($A$1=40238,E111,(IF($A$1=40269,F111,(IF($A$1=40299,G111,(IF($A$1=40330,H111,(IF($A$1=40360,I111,0)))))))))))))+(IF($A$1=40391,J111,(IF($A$1=40422,K111,(IF($A$1=40452,L111,(IF($A$1=40483,M111)))))))))+(IF($A$1=40513,N111,0)) -> 0
... A140: TOT. EXP. | C140: 10.635984 | D140: 13.575362 | E140: 10.734208 | F140: 10.108118 | G140: 11.396766 | H140: 12.553591 | I140: 13.837937 | J140: 17.530081 | K140: 17.981959 | L140: 17.372576 | M140: 17.098316 | N140: 18.384779 | O140: 14.191723 | P140: 15.191723 | Q140: =(IF($A$1=40179,C140,(IF($A$1=40210,D140,(IF($A$1=40238,E140,(IF($A$1=40269,F140,(IF($A$1=40299,G140,(IF($A$1=40330,H140,(IF($A$1=40360,I140,0)))))))))))))+(IF($A$1=40391,J140,(IF($A$1=40422,K140,(IF($A$1=40452,L140,(IF($A$1=40483,M140)))))))))+(IF($A$1=40513,N140,0)) -> 0
Q141: =(IF($A$1=40179,C141,(IF($A$1=40210,D141,(IF($A$1=40238,E141,(IF($A$1=40269,F141,(IF($A$1=40299,G141,(IF($A$1=40330,H141,(IF($A$1=40360,I141,0)))))))))))))+(IF($A$1=40391,J141,(IF($A$1=40422,K141,(IF($A$1=40452,L141,(IF($A$1=40483,M141)))))))))+(IF($A$1=40513,N141,0)) -> 0
A142: Per No.Of.Guest | Q142: =(IF($A$1=40179,C142,(IF($A$1=40210,D142,(IF($A$1=40238,E142,(IF($A$1=40269,F142,(IF($A$1=40299,G142,(IF($A$1=40330,H142,(IF($A$1=40360,I142,0)))))))))))))+(IF($A$1=40391,J142,(IF($A$1=40422,K142,(IF($A$1=40452,L142,(IF($A$1=40483,M142)))))))))+(IF($A$1=40513,N142,0)) -> 0
...

Sheet Elect
A1: 44927 | M1: Electricity | BP1: Gourmandise UP | BR1: 1.6 | BS1: Power Taxes | BU1: Max Demand | BW1: 500 | BX1: Electricity UP | BZ1: 1.15
BS2: Light Taxes | BU2: PF Penalty | BX2: Max. Demand UP | BZ2: 30
A3: Date | B3: COUNTER (1) | D3: MD | F3: KVAR | H3: n | I3: Guest Rooms Consumption | R3: Casino Consumption | V3: Plant Room Shared Loads | AO3: To Be Charged By First Arabian | BK3: From Main Panel G2 | BS3: Total Consumption. | BT3: No. Of | BU3: KWH/ | BV3: No. Of | BW3: KWH/ | BX3: Total Cost | BY3: L.E\ | BZ3: L.E\
B4: Reading | C4: Consp. F: *800 | D4: Reading | E4: Consp F: 80 | F4: Reading | G4: Consp. F:*10 | I4: Main Feeder | J4: Consp | K4: T2+T8 | L4: Trans T2 | M4: Consp | N4: Trans T8 | O4: Consp | P4: La Gourmandize | Q4: Consp *30 | R4: Casino 3rd floor EM | S4: Consp | T4: Casino 3rd floor Normal | U4: Consp | V4: Chiller 1 | W4: Consp 53% | X4: Chiller 2 | Y4: Consp 53% | Z4: Chiller 3 | AA4: Consp 53% | AB4: Chiller 4 | AC4: Consp 53% | AD4: Chiller 5 | AE4: Consp 53% | AF4: Chiller 6 | AG4: Consp 53% | AH4: Cooling Towers | AI4: Consp 53% | AJ4: Chiller Pumps | AK4: Consp 53% | AL4: Cooling Tower Pumps | AM4: Consp 53% | AN4: Total Plant Room Consp | AO4: Fiber Chiller (N24) | AP4: Consp | AQ4: Mall Ceiling light (N4) | AR4: Consp | AS4: LG Bakery (N2) | AT4: Consp | AU4: LG Bakery light ( Old lockers ) | AV4: Consp | AW4: MCCR1 | AX4: Consp | AY4: Children Swimming pool | AZ4: Consp | BA4: DPH1 | BB4: Consp | BC4: Guest Rooms Emergency | BD4: Consp | BE4: Hotel Hoods | BF4: Consp | BG4: Main G2 | BH4: Consp | BI4: Total Consp From First Arabian | BJ4: First Arabian Charge Back | BK4: Old Casino Emergency | BL4: Consp | BM4: L / A | BN4: Consp | BO4: L / B | BP4: Consp | BQ4: L / C | BR4: Consp | BT4: Rooms | BU4: room | BV4: guest | BW4: guest | BY4: Room | BZ4: Guest
A5: Last Month Reading | I5: 25793313 | J5: =IF(I5>=I4,I5-I4,0) -> 0 | K5: =M5+O5 -> 0 | L5: 336740 | M5: =IF(L5>=L4,L5-L4,0) -> 0 | N5: 356217.17 | O5: =IF(N5>=N4,N5-N4,0) -> 0 | P5: 227682.83 | Q5: =IF(P5>=P4,P5-P4,0)*30 -> 0 | R5: 230535.33 | S5: =IF(R5>=R4,R5-R4,0) -> 0 | T5: 420593.17 | U5: =IF(T5>=T4,T5-T4,0) -> 0 | V5: 771151.17 | W5: =IF(V5>=V4,V5-V4,0)*0.53 -> 0 | X5: 837372 | Y5: =IF(X5>=X4,X5-X4,0)*0.53 -> 0 | Z5: 871759 | AA5: =IF(Z5>=Z4,Z5-Z4,0)*0.53 -> 0 | AB5: 184962 | AC5: =IF(AB5>=AB4,AB5-AB4,0)*0.53 -> 0 | AD5: 862567.17 | AE5: =IF(AD5>=AD4,AD5-AD4,0)*0.53 -> 0 | AF5: 1010228.3 | AG5: =IF(AF5>=AF4,AF5-AF4,0)*0.53 -> 0 | AH5: 432610.83 | AI5: =IF(AH5>=AH4,AH5-AH4,0)*0.53 -> 0 | AJ5: 639862.67 | AK5: =IF(AJ5>=AJ4,AJ5-AJ4,0)*0.53 -> 0 | AL5: 574068.5 | AM5: =IF(AL5>=AL4,AL5-AL4,0)*0.53 -> 0 | AN5: =W5+Y5+AA5+AC5+AE5+AG5+AI5+AK5+AM5 -> 0 | AO5: 8202187.5 | AP5: =IF(AO5>=AO4,AO5-AO4,0)*0.1125 -> 0 | AQ5: 756306.67 | AR5: =IF(AQ5>=AQ4,AQ5-AQ4,0) -> 0 | AS5: 20032.833 | AT5: =IF(AS5>=AS4,AS5-AS4,0) -> 0 | AU5: 827173.17 | AV5: =IF(AU5>=AU4,AU5-AU4,0) -> 0 | AW5: 2906034.8 | AX5: =IF(AW5>=AW4,AW5-AW4,0) -> 0 | AY5: 233682.33 | AZ5: =IF(AY5>=AY4,AY5-AY4,0) -> 0 | BA5: 20942279 | BB5: =IF(BA5>=BA4,BA5-BA4,0) -> 0 | BC5: 646362.83 | BD5: =IF(BC5>=BC4,BC5-BC4,0) -> 0 | BE5: 46252 | BF5: =IF(BE5>=BE4,BE5-BE4,0) -> 0 | BG5: 26325411 | BH5: =IF(BG5>=BG4,BG5-BG4,0)-(0.45*BN5)-(0.45*BP5)-BR5 -> 0 | BI5: =AP5+AR5+AT5+AV5+AX5+AZ5+BB5+BD5+BF5+BH5 -> 0 | BJ5: =BI5+AN5 -> 0 | BK5: 1500331.8 | BL5: =IF(BK5>=BK4,BK5-BK4,0) -> 0 | BM5: 4339068.8 | BN5: =IF(BM5>=BM4,BM5-BM4,0) -> 0 | BO5: 453738 | BP5: =IF(BO5>=BO4,BO5-BO4,0) -> 0 | BQ5: 566423.67 | BR5: =IF(BQ5>=BQ4,BQ5-BQ4,0) -> 0
A6: 1 | C6: =IF(+B6-B5>0,B6-B5,(B6-B5)>0)*800 -> 0 | E6: =IF(+D6-D5>0,D6-D5,(D6-D5)>0)*80 -> 0 | G6: =IF(+F6-F5>0,F6-F5,(F6-F5)>0)*10 -> 0 | H6: 56 | I6: 25799757 | J6: =IF(I6>=I5,I6-I5,0) -> 6443.9444 | K6: =M6+O6 -> 3741.8333 | L6: 338481 | M6: =IF(L6>=L5,L6-L5,0) -> 1741 | N6: 358218 | O6: =IF(N6>=N5,N6-N5,0) -> 2000.8333 | P6: 227697 | Q6: =IF(P6>=P5,P6-P5,0)*30 -> 425 | R6: 230676 | S6: =IF(R6>=R5,R6-R5,0) -> 140.66667 | T6: 420893 | U6: =IF(T6>=T5,T6-T5,0) -> 299.83333 | V6: 774466 | W6: =IF(V6>=V5,V6-V5,0)*0.53 -> 1756.8617 | X6: 837372 | Y6: =IF(X6>=X5,X6-X5,0)*0.53 -> 0 | Z6: 871759 | AA6: =IF(Z6>=Z5,Z6-Z5,0)*0.53 -> 0 | AB6: 184962 | AC6: =IF(AB6>=AB5,AB6-AB5,0)*0.53 -> 0 | AD6: 862592 | AE6: =IF(AD6>=AD5,AD6-AD5,0)*0.53 -> 13.161667 | AF6: 1010252 | AG6: =IF(AF6>=AF5,AF6-AF5,0)*0.53 -> 12.543333 | AH6: 433201 | AI6: =IF(AH6>=AH5,AH6-AH5,0)*0.53 -> 312.78833 | AJ6: 647708 | AK6: =IF(AJ6>=AJ5,AJ6-AJ5,0)*0.53 -> 4158.0267 | AL6: 574293 | AM6: =IF(AL6>=AL5,AL6-AL5,0)*0.53 -> 118.985 | AN6: =W6+Y6+AA6+AC6+AE6+AG6+AI6+AK6+AM6 -> 6372.3667 | AO6: 8203187 | AP6: =IF(AO6>=AO5,AO6-AO5,0)*0.1125 -> 112.44375 | AQ6: 756469 | AR6: =IF(AQ6>=AQ5,AQ6-AQ5,0) -> 162.33333 | AS6: 20126 | AT6: =IF(AS6>=AS5,AS6-AS5,0) -> 93.166667 | AU6: 827214 | AV6: =IF(AU6>=AU5,AU6-AU5,0) -> 40.833333 | AW6: 2906878 | AX6: =IF(AW6>=AW5,AW6-AW5,0) -> 843.16667 | AY6: 233693 | AZ6: =IF(AY6>=AY5,AY6-AY5,0) -> 10.666667 | BA6: 20947517 | BB6: =IF(BA6>=BA5,BA6-BA5,0) -> 5238.1667 | BC6: 646596 | BD6: =IF(BC6>=BC5,BC6-BC5,0) -> 233.16667 | BE6: 46296 | BF6: =IF(BE6>=BE5,BE6-BE5,0) -> 44 | BG6: 26332179 | BH6: =IF(BG6>=BG5,BG6-BG5,0)-(0.45*BN6)-(0.45*BP6)-BR6 -> 6109.3083 | BI6: =AP6+AR6+AT6+AV6+AX6+AZ6+BB6+BD6+BF6+BH6 -> 12887.252 | BJ6: =BI6+AN6 -> 19259.619 | BK6: 1500557 | BL6: =IF(BK6>=BK5,BK6-BK5,0) -> 225.16667 | BM6: 4340030 | BN6: =IF(BM6>=BM5,BM6-BM5,0) -> 961.16667 | BO6: 453908 | BP6: =IF(BO6>=BO5,BO6-BO5,0) -> 170 | BQ6: 566573 | BR6: =IF(BQ6>=BQ5,BQ6-BQ5,0) -> 149.33333 | BS6: =J6+Q6+AN6+BI6 -> 26128.563 | BT6: 238 | BU6: =IF(BS6>0,BS6/BT5,0) -> #DIV/0! | BW6: =IF(BS6>0,BS6/BV6,0) -> #DIV/0! | BX6: =((BS6-Q6)*$BZ$1)+(Q6*$BR$1) -> 30239.098 | BY6: =IF(BX6>0,BX6/BT5,0) -> #DIV/0! | BZ6: =IF(BX6>0,BX6/BV6,0) -> #DIV/0!
A7: 2 | I7: 25805938 | J7: =IF(I7>=I6,I7-I6,0) -> 6181 | K7: =M7+O7 -> 3985 | L7: 340591 | M7: =IF(L7>=L6,L7-L6,0) -> 2110 | N7: 360093 | O7: =IF(N7>=N6,N7-N6,0) -> 1875 | P7: 227713 | Q7: =IF(P7>=P6,P7-P6,0)*30 -> 480 | R7: 230814 | S7: =IF(R7>=R6,R7-R6,0) -> 138 | T7: 421128 | U7: =IF(T7>=T6,T7-T6,0) -> 235 | V7: 778406 | W7: =IF(V7>=V6,V7-V6,0)*0.53 -> 2088.2 | X7: 837372 | Y7: =IF(X7>=X6,X7-X6,0)*0.53 -> 0 | Z7: 871759 | AA7: =IF(Z7>=Z6,Z7-Z6,0)*0.53 -> 0 | AB7: 184962 | AC7: =IF(AB7>=AB6,AB7-AB6,0)*0.53 -> 0 | AD7: 862621 | AE7: =IF(AD7>=AD6,AD7-AD6,0)*0.53 -> 15.37 | AF7: 1010279 | AG7: =IF(AF7>=AF6,AF7-AF6,0)*0.53 -> 14.31 | AH7: 433714 | AI7: =IF(AH7>=AH6,AH7-AH6,0)*0.53 -> 271.89 | AJ7: 652057 | AK7: =IF(AJ7>=AJ6,AJ7-AJ6,0)*0.53 -> 2304.97 | AL7: 574506 | AM7: =IF(AL7>=AL6,AL7-AL6,0)*0.53 -> 112.89 | AN7: =W7+Y7+AA7+AC7+AE7+AG7+AI7+AK7+AM7 -> 4807.63 | AO7: 8203527 | AP7: =IF(AO7>=AO6,AO7-AO6,0)*0.1125 -> 38.25 | AQ7: 756663 | AR7: =IF(AQ7>=AQ6,AQ7-AQ6,0) -> 194 | AS7: 20222 | AT7: =IF(AS7>=AS6,AS7-AS6,0) -> 96 | AU7: 827257 | AV7: =IF(AU7>=AU6,AU7-AU6,0) -> 43 | AW7: 2907833 | AX7: =IF(AW7>=AW6,AW7-AW6,0) -> 955 | AY7: 233703 | AZ7: =IF(AY7>=AY6,AY7-AY6,0) -> 10 | BA7: 20952571 | BB7: =IF(BA7>=BA6,BA7-BA6,0) -> 5054 | BC7: 646817 | BD7: =IF(BC7>=BC6,BC7-BC6,0) -> 221 | BE7: 46341 | BF7: =IF(BE7>=BE6,BE7-BE6,0) -> 45 | BG7: 26338194 | BH7: =IF(BG7>=BG6,BG7-BG6,0)-(0.45*BN7)-(0.45*BP7)-BR7 -> 5300.6 | BI7: =AP7+AR7+AT7+AV7+AX7+AZ7+BB7+BD7+BF7+BH7 -> 11956.85 | BJ7: =BI7+AN7 -> 16764.48 | BK7: 1500720 | BL7: =IF(BK7>=BK6,BK7-BK6,0) -> 163 | BM7: 4341149 | BN7: =IF(BM7>=BM6,BM7-BM6,0) -> 1119 | BO7: 454041 | BP7: =IF(BO7>=BO6,BO7-BO6,0) -> 133 | BQ7: 566724 | BR7: =IF(BQ7>=BQ6,BQ7-BQ6,0) -> 151 | BS7: =J7+Q7+AN7+BI7 -> 23425.48 | BT7: 227 | BU7: =IF(BS7>0,BS7/BT6,0) -> 98.426387 | BW7: =IF(BS7>0,BS7/BV7,0) -> #DIV/0! | BX7: =((BS7-Q7)*$BZ$1)+(Q7*$BR$1) -> 27155.302 | BY7: =IF(BX7>0,BX7/BT6,0) -> 114.09791 | BZ7: =IF(BX7>0,BX7/BV7,0) -> #DIV/0!
A8: 3 | C8: =IF(+B8-B7>0,B8-B7,(B8-B7)>0)*800 -> 0 | E8: =IF(+D8-D7>0,D8-D7,(D8-D7)>0)*80 -> 0 | G8: =IF(+F8-F7>0,F8-F7,(F8-F7)>0)*10 -> 0 | H8: 57 | I8: 25812191 | J8: =IF(I8>=I7,I8-I7,0) -> 6253 | K8: =M8+O8 -> 4301 | L8: 342855 | M8: =IF(L8>=L7,L8-L7,0) -> 2264 | N8: 362130 | O8: =IF(N8>=N7,N8-N7,0) -> 2037 | P8: 227731 | Q8: =IF(P8>=P7,P8-P7,0)*30 -> 540 | R8: 230965 | S8: =IF(R8>=R7,R8-R7,0) -> 151 | T8: 421391 | U8: =IF(T8>=T7,T8-T7,0) -> 263 | V8: 782771 | W8: =IF(V8>=V7,V8-V7,0)*0.53 -> 2313.45 | X8: 837372 | Y8: =IF(X8>=X7,X8-X7,0)*0.53 -> 0 | Z8: 871759 | AA8: =IF(Z8>=Z7,Z8-Z7,0)*0.53 -> 0 | AB8: 184962 | AC8: =IF(AB8>=AB7,AB8-AB7,0)*0.53 -> 0 | AD8: 862648 | AE8: =IF(AD8>=AD7,AD8-AD7,0)*0.53 -> 14.31 | AF8: 1010304 | AG8: =IF(AF8>=AF7,AF8-AF7,0)*0.53 -> 13.25 | AH8: 434270 | AI8: =IF(AH8>=AH7,AH8-AH7,0)*0.53 -> 294.68 | AJ8: 656836 | AK8: =IF(AJ8>=AJ7,AJ8-AJ7,0)*0.53 -> 2532.87 | AL8: 574736 | AM8: =IF(AL8>=AL7,AL8-AL7,0)*0.53 -> 121.9 | AN8: =W8+Y8+AA8+AC8+AE8+AG8+AI8+AK8+AM8 -> 5290.46 | AO8: 8203781 | AP8: =IF(AO8>=AO7,AO8-AO7,0)*0.1125 -> 28.575 | AQ8: 756852 | AR8: =IF(AQ8>=AQ7,AQ8-AQ7,0) -> 189 | AS8: 20314 | AT8: =IF(AS8>=AS7,AS8-AS7,0) -> 92 | AU8: 827304 | AV8: =IF(AU8>=AU7,AU8-AU7,0) -> 47 | AW8: 2908840 | AX8: =IF(AW8>=AW7,AW8-AW7,0) -> 1007 | AY8: 233714 | AZ8: =IF(AY8>=AY7,AY8-AY7,0) -> 11 | BA8: 20957700 | BB8: =IF(BA8>=BA7,BA8-BA7,0) -> 5129 | BC8: 647065 | BD8: =IF(BC8>=BC7,BC8-BC7,0) -> 248 | BE8: 46391 | BF8: =IF(BE8>=BE7,BE8-BE7,0) -> 50 | BG8: 26345194 | BH8: =IF(BG8>=BG7,BG8-BG7,0)-(0.45*BN8)-(0.45*BP8)-BR8 -> 6195.55 | BI8: =AP8+AR8+AT8+AV8+AX8+AZ8+BB8+BD8+BF8+BH8 -> 12997.125 | BJ8: =BI8+AN8 -> 18287.585 | BK8: 1501044 | BL8: =IF(BK8>=BK7,BK8-BK7,0) -> 324 | BM8: 4342444 | BN8: =IF(BM8>=BM7,BM8-BM7,0) -> 1295 | BO8: 454187 | BP8: =IF(BO8>=BO7,BO8-BO7,0) -> 146 | BQ8: 566880 | BR8: =IF(BQ8>=BQ7,BQ8-BQ7,0) -> 156 | BS8: =J8+Q8+AN8+BI8 -> 25080.585 | BT8: 213 | BU8: =IF(BS8>0,BS8/BT7,0) -> 110.48716 | BW8: =IF(BS8>0,BS8/BV8,0) -> #DIV/0! | BX8: =((BS8-Q8)*$BZ$1)+(Q8*$BR$1) -> 29085.673 | BY8: =IF(BX8>0,BX8/BT7,0) -> 128.13072 | BZ8: =IF(BX8>0,BX8/BV8,0) -> #DIV/0!
A9: 4 | C9: =IF(+B9-B8>0,B9-B8,(B9-B8)>0)*800 -> 0 | E9: =IF(+D9-D8>0,D9-D8,(D9-D8)>0)*80 -> 0 | G9: =IF(+F9-F8>0,F9-F8,(F9-F8)>0)*10 -> 0 | I9: 25818020 | J9: =IF(I9>=I8,I9-I8,0) -> 5829 | K9: =M9+O9 -> 4389 | L9: 345221 | M9: =IF(L9>=L8,L9-L8,0) -> 2366 | N9: 364153 | O9: =IF(N9>=N8,N9-N8,0) -> 2023 | P9: 227749 | Q9: =IF(P9>=P8,P9-P8,0)*30 -> 540 | R9: 231103 | S9: =IF(R9>=R8,R9-R8,0) -> 138 | T9: 421630 | U9: =IF(T9>=T8,T9-T8,0) -> 239 | V9: 787231 | W9: =IF(V9>=V8,V9-V8,0)*0.53 -> 2363.8 | X9: 837372 | Y9: =IF(X9>=X8,X9-X8,0)*0.53 -> 0 | Z9: 871759 | AA9: =IF(Z9>=Z8,Z9-Z8,0)*0.53 -> 0 | AB9: 184962 | AC9: =IF(AB9>=AB8,AB9-AB8,0)*0.53 -> 0 | AD9: 862671 | AE9: =IF(AD9>=AD8,AD9-AD8,0)*0.53 -> 12.19 | AF9: 1010326 | AG9: =IF(AF9>=AF8,AF9-AF8,0)*0.53 -> 11.66 | AH9: 434827 | AI9: =IF(AH9>=AH8,AH9-AH8,0)*0.53 -> 295.21 | AJ9: 661765 | AK9: =IF(AJ9>=AJ8,AJ9-AJ8,0)*0.53 -> 2612.37 | AL9: 574973 | AM9: =IF(AL9>=AL8,AL9-AL8,0)*0.53 -> 125.61 | AN9: =W9+Y9+AA9+AC9+AE9+AG9+AI9+AK9+AM9 -> 5420.84 | AO9: 8203871 | AP9: =IF(AO9>=AO8,AO9-AO8,0)*0.1125 -> 10.125 | AQ9: 757055 | AR9: =IF(AQ9>=AQ8,AQ9-AQ8,0) -> 203 | AS9: 20385 | AT9: =IF(AS9>=AS8,AS9-AS8,0) -> 71 | AU9: 827352 | AV9: =IF(AU9>=AU8,AU9-AU8,0) -> 48 | AW9: 2909875 | AX9: =IF(AW9>=AW8,AW9-AW8,0) -> 1035 | AY9: 233724 | AZ9: =IF(AY9>=AY8,AY9-AY8,0) -> 10 | BA9: 20962779 | BB9: =IF(BA9>=BA8,BA9-BA8,0) -> 5079 | BC9: 647260 | BD9: =IF(BC9>=BC8,BC9-BC8,0) -> 195 | BE9: 46441 | BF9: =IF(BE9>=BE8,BE9-BE8,0) -> 50 | BG9: 26350434 | BH9: =IF(BG9>=BG8,BG9-BG8,0)-(0.45*BN9)-(0.45*BP9)-BR9 -> 4672.2 | BI9: =AP9+AR9+AT9+AV9+AX9+AZ9+BB9+BD9+BF9+BH9 -> 11373.325 | BJ9: =BI9+AN9 -> 16794.165 | BK9: 1501303 | BL9: =IF(BK9>=BK8,BK9-BK8,0) -> 259 | BM9: 4343356 | BN9: =IF(BM9>=BM8,BM9-BM8,0) -> 912 | BO9: 454299 | BP9: =IF(BO9>=BO8,BO9-BO8,0) -> 112 | BQ9: 566987 | BR9: =IF(BQ9>=BQ8,BQ9-BQ8,0) -> 107 | BS9: =J9+Q9+AN9+BI9 -> 23163.165 | BT9: 202 | BU9: =IF(BS9>0,BS9/BT8,0) -> 108.74725 | BW9: =IF(BS9>0,BS9/BV9,0) -> #DIV/0! | BX9: =((BS9-Q9)*$BZ$1)+(Q9*$BR$1) -> 26880.64 | BY9: =IF(BX9>0,BX9/BT8,0) -> 126.20019 | BZ9: =IF(BX9>0,BX9/BV9,0) -> #DIV/0!
A10: 5 | C10: =IF(+B10-B9>0,B10-B9,(B10-B9)>0)*800 -> 0 | E10: =IF(+D10-D9>0,D10-D9,(D10-D9)>0)*80 -> 0 | G10: =IF(+F10-F9>0,F10-F9,(F10-F9)>0)*10 -> 0 | H10: 58 | I10: 25824793 | J10: =IF(I10>=I9,I10-I9,0) -> 6773 | K10: =M10+O10 -> 4615 | L10: 347656 | M10: =IF(L10>=L9,L10-L9,0) -> 2435 | N10: 366333 | O10: =IF(N10>=N9,N10-N9,0) -> 2180 | P10: 227768 | Q10: =IF(P10>=P9,P10-P9,0)*30 -> 570 | R10: 231265 | S10: =IF(R10>=R9,R10-R9,0) -> 162 | T10: 421915 | U10: =IF(T10>=T9,T10-T9,0) -> 285 | V10: 790085 | W10: =IF(V10>=V9,V10-V9,0)*0.53 -> 1512.62 | X10: 839916 | Y10: =IF(X10>=X9,X10-X9,0)*0.53 -> 1348.32 | Z10: 871759 | AA10: =IF(Z10>=Z9,Z10-Z9,0)*0.53 -> 0 | AB10: 184962 | AC10: =IF(AB10>=AB9,AB10-AB9,0)*0.53 -> 0 | AD10: 862695 | AE10: =IF(AD10>=AD9,AD10-AD9,0)*0.53 -> 12.72 | AF10: 1010349 | AG10: =IF(AF10>=AF9,AF10-AF9,0)*0.53 -> 12.19 | AH10: 435188 | AI10: =IF(AH10>=AH9,AH10-AH9,0)*0.53 -> 191.33 | AJ10: 665960 | AK10: =IF(AJ10>=AJ9,AJ10-AJ9,0)*0.53 -> 2223.35 | AL10: 575206 | AM10: =IF(AL10>=AL9,AL10-AL9,0)*0.53 -> 123.49 | AN10: =W10+Y10+AA10+AC10+AE10+AG10+AI10+AK10+AM10 -> 5424.02 | AO10: 8204856 | AP10: =IF(AO10>=AO9,AO10-AO9,0)*0.1125 -> 110.8125 | AQ10: 757256 | AR10: =IF(AQ10>=AQ9,AQ10-AQ9,0) -> 201 | AS10: 20481 | AT10: =IF(AS10>=AS9,AS10-AS9,0) -> 96 | AU10: 827399 | AV10: =IF(AU10>=AU9,AU10-AU9,0) -> 47 | AW10: 2910866 | AX10: =IF(AW10>=AW9,AW10-AW9,0) -> 991 | AY10: 233736 | AZ10: =IF(AY10>=AY9,AY10-AY9,0) -> 12 | BA10: 20967609 | BB10: =IF(BA10>=BA9,BA10-BA9,0) -> 4830 | BC10: 647504 | BD10: =IF(BC10>=BC9,BC10-BC9,0) -> 244 | BE10: 46517 | BF10: =IF(BE10>=BE9,BE10-BE9,0) -> 76 | BG10: 26356276 | BH10: =IF(BG10>=BG9,BG10-BG9,0)-(0.45*BN10)-(0.45*BP10)-BR10 -> 5146.95 | BI10: =AP10+AR10+AT10+AV10+AX10+AZ10+BB10+BD10+BF10+BH10 -> 11754.763 | BJ10: =BI10+AN10 -> 17178.783 | BK10: 1501395 | BL10: =IF(BK10>=BK9,BK10-BK9,0) -> 92 | BM10: 4344435 | BN10: =IF(BM10>=BM9,BM10-BM9,0) -> 1079 | BO10: 454429 | BP10: =IF(BO10>=BO9,BO10-BO9,0) -> 130 | BQ10: 567138 | BR10: =IF(BQ10>=BQ9,BQ10-BQ9,0) -> 151 | BS10: =J10+Q10+AN10+BI10 -> 24521.783 | BT10: 196 | BU10: =IF(BS10>0,BS10/BT9,0) -> 121.39496 | BW10: =IF(BS10>0,BS10/BV10,0) -> #DIV/0! | BX10: =((BS10-Q10)*$BZ$1)+(Q10*$BR$1) -> 28456.55 | BY10: =IF(BX10>0,BX10/BT9,0) -> 140.87401 | BZ10: =IF(BX10>0,BX10/BV10,0) -> #DIV/0!
A11: 6 | C11: =IF(+B11-B10>0,B11-B10,(B11-B10)>0)*800 -> 0 | E11: =IF(+D11-D10>0,D11-D10,(D11-D10)>0)*80 -> 0 | G11: =IF(+F11-F10>0,F11-F10,(F11-F10)>0)*10 -> 0 | I11: 25831727 | J11: =IF(I11>=I10,I11-I10,0) -> 6934 | K11: =M11+O11 -> 3800 | L11: 349599 | M11: =IF(L11>=L10,L11-L10,0) -> 1943 | N11: 368190 | O11: =IF(N11>=N10,N11-N10,0) -> 1857 | P11: 227787 | Q11: =IF(P11>=P10,P11-P10,0)*30 -> 570 | R11: 231400 | S11: =IF(R11>=R10,R11-R10,0) -> 135 | T11: 422155 | U11: =IF(T11>=T10,T11-T10,0) -> 240 | V11: 794873 | W11: =IF(V11>=V10,V11-V10,0)*0.53 -> 2537.64 | X11: 839916 | Y11: =IF(X11>=X10,X11-X10,0)*0.53 -> 0 | Z11: 871759 | AA11: =IF(Z11>=Z10,Z11-Z10,0)*0.53 -> 0 | AB11: 184962 | AC11: =IF(AB11>=AB10,AB11-AB10,0)*0.53 -> 0 | AD11: 862725 | AE11: =IF(AD11>=AD10,AD11-AD10,0)*0.53 -> 15.9 | AF11: 1010377 | AG11: =IF(AF11>=AF10,AF11-AF10,0)*0.53 -> 14.84 | AH11: 435474 | AI11: =IF(AH11>=AH10,AH11-AH10,0)*0.53 -> 151.58 | AJ11: 669389 | AK11: =IF(AJ11>=AJ10,AJ11-AJ10,0)*0.53 -> 1817.37 | AL11: 575391 | AM11: =IF(AL11>=AL10,AL11-AL10,0)*0.53 -> 98.05 | AN11: =W11+Y11+AA11+AC11+AE11+AG11+AI11+AK11+AM11 -> 4635.38 | AO11: 8205964 | AP11: =IF(AO11>=AO10,AO11-AO10,0)*0.1125 -> 124.65 | AQ11: 757430 | AR11: =IF(AQ11>=AQ10,AQ11-AQ10,0) -> 174 | AS11: 20618 | AT11: =IF(AS11>=AS10,AS11-AS10,0) -> 137 | AU11: 827434 | AV11: =IF(AU11>=AU10,AU11-AU10,0) -> 35 | AW11: 2911650 | AX11: =IF(AW11>=AW10,AW11-AW10,0) -> 784 | AY11: 233746 | AZ11: =IF(AY11>=AY10,AY11-AY10,0) -> 10 | BA11: 20973355 | BB11: =IF(BA11>=BA10,BA11-BA10,0) -> 5746 | BC11: 647791 | BD11: =IF(BC11>=BC10,BC11-BC10,0) -> 287 | BE11: 46600 | BF11: =IF(BE11>=BE10,BE11-BE10,0) -> 83 | BG11: 26363287 | BH11: =IF(BG11>=BG10,BG11-BG10,0)-(0.45*BN11)-(0.45*BP11)-BR11 -> 6243.3 | BI11: =AP11+AR11+AT11+AV11+AX11+AZ11+BB11+BD11+BF11+BH11 -> 13623.95 | BJ11: =BI11+AN11 -> 18259.33 | BK11: 1501489 | BL11: =IF(BK11>=BK10,BK11-BK10,0) -> 94 | BM11: 4345669 | BN11: =IF(BM11>=BM10,BM11-BM10,0) -> 1234 | BO11: 454581 | BP11: =IF(BO11>=BO10,BO11-BO10,0) -> 152 | BQ11: 567282 | BR11: =IF(BQ11>=BQ10,BQ11-BQ10,0) -> 144 | BS11: =J11+Q11+AN11+BI11 -> 25763.33 | BT11: 214 | BU11: =IF(BS11>0,BS11/BT10,0) -> 131.44556 | BW11: =IF(BS11>0,BS11/BV11,0) -> #DIV/0! | BX11: =((BS11-Q11)*$BZ$1)+(Q11*$BR$1) -> 29884.329 | BY11: =IF(BX11>0,BX11/BT10,0) -> 152.47107 | BZ11: =IF(BX11>0,BX11/BV11,0) -> #DIV/0!
A12: 7 | C12: =IF(+B12-B11>0,B12-B11,(B12-B11)>0)*800 -> 0 | E12: =IF(+D12-D11>0,D12-D11,(D12-D11)>0)*80 -> 0 | G12: =IF(+F12-F11>0,F12-F11,(F12-F11)>0)*10 -> 0 | H12: 59 | I12: 25839104 | J12: =IF(I12>=I11,I12-I11,0) -> 7377 | K12: =M12+O12 -> 3947 | L12: 351714 | M12: =IF(L12>=L11,L12-L11,0) -> 2115 | N12: 370022 | O12: =IF(N12>=N11,N12-N11,0) -> 1832 | P12: 227807 | Q12: =IF(P12>=P11,P12-P11,0)*30 -> 600 | R12: 231535 | S12: =IF(R12>=R11,R12-R11,0) -> 135 | T12: 422396 | U12: =IF(T12>=T11,T12-T11,0) -> 241 | V12: 799914 | W12: =IF(V12>=V11,V12-V11,0)*0.53 -> 2671.73 | X12: 839916 | Y12: =IF(X12>=X11,X12-X11,0)*0.53 -> 0 | Z12: 871759 | AA12: =IF(Z12>=Z11,Z12-Z11,0)*0.53 -> 0 | AB12: 184962 | AC12: =IF(AB12>=AB11,AB12-AB11,0)*0.53 -> 0 | AD12: 862748 | AE12: =IF(AD12>=AD11,AD12-AD11,0)*0.53 -> 12.19 | AF12: 1010399 | AG12: =IF(AF12>=AF11,AF12-AF11,0)*0.53 -> 11.66 | AH12: 435813 | AI12: =IF(AH12>=AH11,AH12-AH11,0)*0.53 -> 179.67 | AJ12: 673398 | AK12: =IF(AJ12>=AJ11,AJ12-AJ11,0)*0.53 -> 2124.77 | AL12: 575600 | AM12: =IF(AL12>=AL11,AL12-AL11,0)*0.53 -> 110.77 | AN12: =W12+Y12+AA12+AC12+AE12+AG12+AI12+AK12+AM12 -> 5110.79 | AO12: 8207235 | AP12: =IF(AO12>=AO11,AO12-AO11,0)*0.1125 -> 142.9875 | AQ12: 757622 | AR12: =IF(AQ12>=AQ11,AQ12-AQ11,0) -> 192 | AS12: 20749 | AT12: =IF(AS12>=AS11,AS12-AS11,0) -> 131 | AU12: 827475 | AV12: =IF(AU12>=AU11,AU12-AU11,0) -> 41 | AW12: 2912534 | AX12: =IF(AW12>=AW11,AW12-AW11,0) -> 884 | AY12: 233756 | AZ12: =IF(AY12>=AY11,AY12-AY11,0) -> 10 | BA12: 20978915 | BB12: =IF(BA12>=BA11,BA12-BA11,0) -> 5560 | BC12: 648056 | BD12: =IF(BC12>=BC11,BC12-BC11,0) -> 265 | BE12: 46617 | BF12: =IF(BE12>=BE11,BE12-BE11,0) -> 17 | BG12: 26369829 | BH12: =IF(BG12>=BG11,BG12-BG11,0)-(0.45*BN12)-(0.45*BP12)-BR12 -> 5834.15 | BI12: =AP12+AR12+AT12+AV12+AX12+AZ12+BB12+BD12+BF12+BH12 -> 13077.138 | BJ12: =BI12+AN12 -> 18187.928 | BK12: 1501801 | BL12: =IF(BK12>=BK11,BK12-BK11,0) -> 312 | BM12: 4346803 | BN12: =IF(BM12>=BM11,BM12-BM11,0) -> 1134 | BO12: 454720 | BP12: =IF(BO12>=BO11,BO12-BO11,0) -> 139 | BQ12: 567417 | BR12: =IF(BQ12>=BQ11,BQ12-BQ11,0) -> 135 | BS12: =J12+Q12+AN12+BI12 -> 26164.928 | BT12: 254 | BU12: =IF(BS12>0,BS12/BT11,0) -> 122.26602 | BW12: =IF(BS12>0,BS12/BV12,0) -> #DIV/0! | BX12: =((BS12-Q12)*$BZ$1)+(Q12*$BR$1) -> 30359.667 | BY12: =IF(BX12>0,BX12/BT11,0) -> 141.8676 | BZ12: =IF(BX12>0,BX12/BV12,0) -> #DIV/0!
A13: 8 | C13: =IF(+B13-B12>0,B13-B12,(B13-B12)>0)*800 -> 0 | E13: =IF(+D13-D12>0,D13-D12,(D13-D12)>0)*80 -> 0 | G13: =IF(+F13-F12>0,F13-F12,(F13-F12)>0)*10 -> 0 | I13: 25844554 | J13: =IF(I13>=I12,I13-I12,0) -> 5450 | K13: =M13+O13 -> 4238 | L13: 353839 | M13: =IF(L13>=L12,L13-L12,0) -> 2125 | N13: 372135 | O13: =IF(N13>=N12,N13-N12,0) -> 2113 | P13: 227825 | Q13: =IF(P13>=P12,P13-P12,0)*30 -> 540 | R13: 231686 | S13: =IF(R13>=R12,R13-R12,0) -> 151 | T13: 422667 | U13: =IF(T13>=T12,T13-T12,0) -> 271 | V13: 803857 | W13: =IF(V13>=V12,V13-V12,0)*0.53 -> 2089.79 | X13: 839916 | Y13: =IF(X13>=X12,X13-X12,0)*0.53 -> 0 | Z13: 871759 | AA13: =IF(Z13>=Z12,Z13-Z12,0)*0.53 -> 0 | AB13: 184962 | AC13: =IF(AB13>=AB12,AB13-AB12,0)*0.53 -> 0 | AD13: 862773 | AE13: =IF(AD13>=AD12,AD13-AD12,0)*0.53 -> 13.25 | AF13: 1010422 | AG13: =IF(AF13>=AF12,AF13-AF12,0)*0.53 -> 12.19 | AH13: 436073 | AI13: =IF(AH13>=AH12,AH13-AH12,0)*0.53 -> 137.8 | AJ13: 677539 | AK13: =IF(AJ13>=AJ12,AJ13-AJ12,0)*0.53 -> 2194.73 | AL13: 575798 | AM13: =IF(AL13>=AL12,AL13-AL12,0)*0.53 -> 104.94 | AN13: =W13+Y13+AA13+AC13+AE13+AG13+AI13+AK13+AM13 -> 4552.7 | AO13: 8208189 | AP13: =IF(AO13>=AO12,AO13-AO12,0)*0.1125 -> 107.325 | AQ13: 757798 | AR13: =IF(AQ13>=AQ12,AQ13-AQ12,0) -> 176 | AS13: 20839 | AT13: =IF(AS13>=AS12,AS13-AS12,0) -> 90 | AU13: 827517 | AV13: =IF(AU13>=AU12,AU13-AU12,0) -> 42 | AW13: 2913459 | AX13: =IF(AW13>=AW12,AW13-AW12,0) -> 925 | AY13: 233767 | AZ13: =IF(AY13>=AY12,AY13-AY12,0) -> 11 | BA13: 20983683 | BB13: =IF(BA13>=BA12,BA13-BA12,0) -> 4768 | BC13: 648240 | BD13: =IF(BC13>=BC12,BC13-BC12,0) -> 184 | BE13: 46662 | BF13: =IF(BE13>=BE12,BE13-BE12,0) -> 45 | BG13: 26375702 | BH13: =IF(BG13>=BG12,BG13-BG12,0)-(0.45*BN13)-(0.45*BP13)-BR13 -> 5366.45 | BI13: =AP13+AR13+AT13+AV13+AX13+AZ13+BB13+BD13+BF13+BH13 -> 11714.775 | BJ13: =BI13+AN13 -> 16267.475 | BK13: 1502024 | BL13: =IF(BK13>=BK12,BK13-BK12,0) -> 223 | BM13: 4347628 | BN13: =IF(BM13>=BM12,BM13-BM12,0) -> 825 | BO13: 454814 | BP13: =IF(BO13>=BO12,BO13-BO12,0) -> 94 | BQ13: 567510 | BR13: =IF(BQ13>=BQ12,BQ13-BQ12,0) -> 93 | BS13: =J13+Q13+AN13+BI13 -> 22257.475 | BT13: 239 | BU13: =IF(BS13>0,BS13/BT12,0) -> 87.627854 | BW13: =IF(BS13>0,BS13/BV13,0) -> #DIV/0! | BX13: =((BS13-Q13)*$BZ$1)+(Q13*$BR$1) -> 25839.096 | BY13: =IF(BX13>0,BX13/BT12,0) -> 101.72873 | BZ13: =IF(BX13>0,BX13/BV13,0) -> #DIV/0!
