Workbook

Sheet Total
A1: Site Name | B1: Day | C1: Month | D1: Year | E1: Total Electricity Kwh | F1: Electricity Tariff ($/Kwh) | G1: Natual Gas (m3) | H1: Natural Gas $/m3 | I1: Water Utility Supply (m3) m3 | J1: Water Utility Supply (m3) $/m3 | K1: Room Nights
A2: Cairo at The First Residence | B2: 1 | C2: 1 | D2: 2022 | E2: =Elect!BS6 -> 21837.963 | F2: ='Utility Consnsumption'!K13/'Utility Consnsumption'!J13 -> 1.4111954 | G2: =Gas!K7 -> 2864.3 | H2: 3.8 | I2: =Water!H7 -> 539.4 | J2: 10 | K2: =Elect!BT6 -> 232
A3: Cairo at The First Residence | B3: =B2+1 -> 2 | C3: 1 | D3: 2022 | E3: =Elect!BS7 -> 23186.298 | F3: =F2 -> 1.4111954 | G3: =Gas!K8 -> 1821.3 | H3: 3.8 | I3: =Water!H8 -> 237.8 | J3: 10 | K3: =Elect!BT7 -> 191
A4: Cairo at The First Residence | B4: =B3+1 -> 3 | C4: 1 | D4: 2022 | E4: =Elect!BS8 -> 21488.202 | F4: =F3 -> 1.4111954 | G4: =Gas!K9 -> 1829 | H4: 3.8 | I4: =Water!H9 -> 348 | J4: 10 | K4: =Elect!BT8 -> 219
A5: Cairo at The First Residence | B5: =B4+1 -> 4 | C5: 1 | D5: 2022 | E5: =Elect!BS9 -> 22502.702 | F5: =F4 -> 1.4111954 | G5: =Gas!K10 -> 1808.7 | H5: 3.8 | I5: =Water!H10 -> 336.4 | J5: 10 | K5: =Elect!BT9 -> 205
A6: Cairo at The First Residence | B6: =B5+1 -> 5 | C6: 1 | D6: 2022 | E6: =Elect!BS10 -> 23106.327 | F6: =F5 -> 1.4111954 | G6: =Gas!K11 -> 1808.7 | H6: 3.8 | I6: =Water!H11 -> 336.4 | J6: 10 | K6: =Elect!BT10 -> 199
A7: Cairo at The First Residence | B7: =B6+1 -> 6 | C7: 1 | D7: 2022 | E7: =Elect!BS11 -> 20150.848 | F7: =F6 -> 1.4111954 | G7: =Gas!K12 -> 1808.7 | H7: 3.8 | I7: =Water!H12 -> 336.4 | J7: 10 | K7: =Elect!BT11 -> 203
A8: Cairo at The First Residence | B8: =B7+1 -> 7 | C8: 1 | D8: 2022 | E8: =Elect!BS12 -> 20696.565 | F8: =F7 -> 1.4111954 | G8: =Gas!K13 -> 1763.2 | H8: 3.8 | I8: =Water!H13 -> 353.8 | J8: 10 | K8: =Elect!BT12 -> 233
A9: Cairo at The First Residence | B9: =B8+1 -> 8 | C9: 1 | D9: 2022 | E9: =Elect!BS13 -> 21269.522 | F9: =F8 -> 1.4111954 | G9: =Gas!K14 -> 1763.2 | H9: 3.8 | I9: =Water!H14 -> 353.8 | J9: 10 | K9: =Elect!BT13 -> 238
A10: Cairo at The First Residence | B10: =B9+1 -> 9 | C10: 1 | D10: 2022 | E10: =Elect!BS14 -> 20624.493 | F10: =F9 -> 1.4111954 | G10: =Gas!K15 -> 1811.5 | H10: 3.8 | I10: =Water!H15 -> 336.4 | J10: 10 | K10: =Elect!BT14 -> 220
A11: Cairo at The First Residence | B11: =B10+1 -> 10 | C11: 1 | D11: 2022 | E11: =Elect!BS15 -> 23026.137 | F11: =F10 -> 1.4111954 | G11: =Gas!K16 -> 1811.5 | H11: 3.8 | I11: =Water!H16 -> 377 | J11: 10 | K11: =Elect!BT15 -> 211
A12: Cairo at The First Residence | B12: =B11+1 -> 11 | C12: 1 | D12: 2022 | E12: =Elect!BS16 -> 20406.878 | F12: =F11 -> 1.4111954 | G12: =Gas!K17 -> 1811.5 | H12: 3.8 | I12: =Water!H17 -> 382.8 | J12: 10 | K12: =Elect!BT16 -> 201
A13: Cairo at The First Residence | B13: =B12+1 -> 12 | C13: 1 | D13: 2022 | E13: =Elect!BS17 -> 21834.893 | F13: =F12 -> 1.4111954 | G13: =Gas!K18 -> 1811.5 | H13: 3.8 | I13: =Water!H18 -> 382.8 | J13: 10 | K13: =Elect!BT17 -> 179
A14: Cairo at The First Residence | B14: =B13+1 -> 13 | C14: 1 | D14: 2022 | E14: =Elect!BS18 -> 22562.368 | F14: =F13 -> 1.4111954 | G14: =Gas!K19 -> 1811.5 | H14: 3.8 | I14: =Water!H19 -> 382.8 | J14: 10 | K14: =Elect!BT18 -> 207
... A32: Cairo at The First Residence | B32: =B31+1 -> 31 | C32: 1 | D32: 2022 | E32: =Elect!BS36 -> 22026.787 | F32: =F31 -> 1.4111954 | G32: =Gas!K37 -> 1870.3 | H32: 3.8 | I32: =Water!H37 -> 284.2 | J32: 10 | K32: =Elect!BT36 -> 190

Sheet Submetering
A1: Site Name | B1: Day | C1: Month | D1: Year | E1: Electricity | F1: Main Feeder -KWh | G1: T2+T8 -KWh | H1: La Gourmandize -KWh | I1: Casino 3rd floor EM -KWh | J1: Casino 3rd floor Normal -KWh | K1: Chiller 1 -KWh | L1: Chiller 2 -KWh | M1: Chiller 3 -KWh | N1: Chiller 4 -KWh | O1: Chiller 5 -KWh | P1: Chiller 6 -KWh | Q1: Cooling towers -KWh | R1: Chiller Pumps -KWh | S1: Cooling Tower Pumps -KWh | T1: Fiber Chiller -KWh | U1: Mall Ceiling light -KWh | V1: LG Bakery -KWh | W1: LG Bakery light ( Old lockers ) -KWh | X1: MCCR1 -KWh | Y1: Children Swimming Pool -KWh | Z1: DPH1 -KWh | AA1: Guest Rooms Emerg. -KWh | AB1: Hotel Hoods -KWh | AC1: Main G2 -KWh | AD1: Old Casino Emergency -KWh | AE1: L / A -KWh | AF1: L / B -KWh | AG1: L / C -KWh | AH1: Water | AI1: Main water meter 1 -m3 | AJ1: Main water meter 2 -m3 | AK1: Main water meter 3 -m3 | AL1: Gas | AM1: Main Gas Flow Meter -m3 | AN1: Laundry Gas Flow Meter -m3 | AO1: Gourmandize Gas Flow Meter -m3 | AP1: Room Nights
A2: Cairo at The First Residence | B2: 1 | C2: 1 | D2: 2022 | F2: =Elect!J6 -> 5837 | G2: =Elect!K6 -> 3617 | H2: =Elect!Q6 -> 540 | I2: =Elect!S6 -> 132 | J2: =Elect!U6 -> 257 | K2: =Elect!W6 -> 719.74 | L2: =Elect!Y6 -> 91.69 | M2: =Elect!AA6 -> 0 | N2: =Elect!AC6 -> 0 | O2: =Elect!AE6 -> 15.37 | P2: =Elect!AG6 -> 14.31 | Q2: =Elect!AI6 -> 528.41 | R2: =Elect!AK6 -> 3404.72 | S2: =Elect!AM6 -> 144.16 | T2: =Elect!AP6 -> 4.1625 | U2: =Elect!AR6 -> 331 | V2: =Elect!AT6 -> 116 | W2: =Elect!AV6 -> 24 | X2: =Elect!AX6 -> 487 | Y2: =Elect!AZ6 -> 69 | Z2: =Elect!BB6 -> 4331 | AA2: =Elect!BD6 -> 212 | AB2: =Elect!BF6 -> 38 | AC2: =Elect!BH6 -> 4930.4 | AD2: =Elect!BL6 -> 314 | AE2: =Elect!BN6 -> 383 | AF2: =Elect!BP6 -> 125 | AG2: =Elect!BR6 -> 141 | AI2: =Water!C7 -> 284.2 | AJ2: =Water!E7 -> 249.4 | AK2: =Water!G7 -> 5.8 | AM2: =Gas!C7 -> 1473.4 | AN2: =Gas!E7 -> 1390.9 | AO2: =Gas!G7 -> 186 | AP2: =Elect!BT6 -> 232
A3: Cairo at The First Residence | B3: =B2+1 -> 2 | C3: 1 | D3: 2022 | F3: =Elect!J7 -> 6605 | G3: =Elect!K7 -> 3882 | H3: =Elect!Q7 -> 570 | I3: =Elect!S7 -> 148 | J3: =Elect!U7 -> 274 | K3: =Elect!W7 -> 1250.8 | L3: =Elect!Y7 -> 0 | M3: =Elect!AA7 -> 0 | N3: =Elect!AC7 -> 0 | O3: =Elect!AE7 -> 13.78 | P3: =Elect!AG7 -> 13.25 | Q3: =Elect!AI7 -> 587.77 | R3: =Elect!AK7 -> 2593.82 | S3: =Elect!AM7 -> 163.24 | T3: =Elect!AP7 -> 4.3875 | U3: =Elect!AR7 -> 353 | V3: =Elect!AT7 -> 136 | W3: =Elect!AV7 -> 28 | X3: =Elect!AX7 -> 622 | Y3: =Elect!AZ7 -> 66 | Z3: =Elect!BB7 -> 4687 | AA3: =Elect!BD7 -> 254 | AB3: =Elect!BF7 -> 52 | AC3: =Elect!BH7 -> 5186.25 | AD3: =Elect!BL7 -> 275 | AE3: =Elect!BN7 -> 938 | AF3: =Elect!BP7 -> 157 | AG3: =Elect!BR7 -> 164 | AI3: =Water!C8 -> 98.6 | AJ3: =Water!E8 -> 139.2 | AK3: =Water!G8 -> 0 | AM3: =Gas!C8 -> 1473.4 | AN3: =Gas!E8 -> 347.9 | AO3: =Gas!G8 -> 82 | AP3: =Elect!BT7 -> 191
A4: Cairo at The First Residence | B4: =B3+1 -> 3 | C4: 1 | D4: 2022 | F4: =Elect!J8 -> 6146 | G4: =Elect!K8 -> 3709 | H4: =Elect!Q8 -> 480 | I4: =Elect!S8 -> 142 | J4: =Elect!U8 -> 201 | K4: =Elect!W8 -> 1217.94 | L4: =Elect!Y8 -> 12.19 | M4: =Elect!AA8 -> 40.28 | N4: =Elect!AC8 -> 24.38 | O4: =Elect!AE8 -> 12.72 | P4: =Elect!AG8 -> 12.19 | Q4: =Elect!AI8 -> 581.94 | R4: =Elect!AK8 -> 2132.72 | S4: =Elect!AM8 -> 154.23 | T4: =Elect!AP8 -> 4.1625 | U4: =Elect!AR8 -> 329 | V4: =Elect!AT8 -> 136 | W4: =Elect!AV8 -> 29 | X4: =Elect!AX8 -> 578 | Y4: =Elect!AZ8 -> 59 | Z4: =Elect!BB8 -> 4533 | AA4: =Elect!BD8 -> 259 | AB4: =Elect!BF8 -> 51 | AC4: =Elect!BH8 -> 4695.45 | AD4: =Elect!BL8 -> 246 | AE4: =Elect!BN8 -> 862 | AF4: =Elect!BP8 -> 137 | AG4: =Elect!BR8 -> 149 | AI4: =Water!C9 -> 150.8 | AJ4: =Water!E9 -> 197.2 | AK4: =Water!G9 -> 0 | AM4: =Gas!C9 -> 1473.4 | AN4: =Gas!E9 -> 355.6 | AO4: =Gas!G9 -> 102 | AP4: =Elect!BT8 -> 219
A5: Cairo at The First Residence | B5: =B4+1 -> 4 | C5: 1 | D5: 2022 | F5: =Elect!J9 -> 6575 | G5: =Elect!K9 -> 3994 | H5: =Elect!Q9 -> 570 | I5: =Elect!S9 -> 138 | J5: =Elect!U9 -> 330 | K5: =Elect!W9 -> 1102.4 | L5: =Elect!Y9 -> 0 | M5: =Elect!AA9 -> 0 | N5: =Elect!AC9 -> 0 | O5: =Elect!AE9 -> 12.19 | P5: =Elect!AG9 -> 12.19 | Q5: =Elect!AI9 -> 458.98 | R5: =Elect!AK9 -> 2027.78 | S5: =Elect!AM9 -> 164.3 | T5: =Elect!AP9 -> 4.6125 | U5: =Elect!AR9 -> 326 | V5: =Elect!AT9 -> 137 | W5: =Elect!AV9 -> 33 | X5: =Elect!AX9 -> 617 | Y5: =Elect!AZ9 -> 65 | Z5: =Elect!BB9 -> 4856 | AA5: =Elect!BD9 -> 291 | AB5: =Elect!BF9 -> 52 | AC5: =Elect!BH9 -> 5198.25 | AD5: =Elect!BL9 -> 269 | AE5: =Elect!BN9 -> 949 | AF5: =Elect!BP9 -> 146 | AG5: =Elect!BR9 -> 151 | AI5: =Water!C10 -> 145 | AJ5: =Water!E10 -> 191.4 | AK5: =Water!G10 -> 0 | AM5: =Gas!C10 -> 1473.4 | AN5: =Gas!E10 -> 335.3 | AO5: =Gas!G10 -> 171 | AP5: =Elect!BT9 -> 205
A6: Cairo at The First Residence | B6: =B5+1 -> 5 | C6: 1 | D6: 2022 | F6: =Elect!J10 -> 6573 | G6: =Elect!K10 -> 4119 | H6: =Elect!Q10 -> 510 | I6: =Elect!S10 -> 144 | J6: =Elect!U10 -> 272 | K6: =Elect!W10 -> 1726.74 | L6: =Elect!Y10 -> 0 | M6: =Elect!AA10 -> 0 | N6: =Elect!AC10 -> 0 | O6: =Elect!AE10 -> 14.31 | P6: =Elect!AG10 -> 13.78 | Q6: =Elect!AI10 -> 465.87 | R6: =Elect!AK10 -> 2319.28 | S6: =Elect!AM10 -> 170.66 | T6: =Elect!AP10 -> 4.3875 | U6: =Elect!AR10 -> 305 | V6: =Elect!AT10 -> 138 | W6: =Elect!AV10 -> 25 | X6: =Elect!AX10 -> 638 | Y6: =Elect!AZ10 -> 61 | Z6: =Elect!BB10 -> 4811 | AA6: =Elect!BD10 -> 262 | AB6: =Elect!BF10 -> 54 | AC6: =Elect!BH10 -> 5014.3 | AD6: =Elect!BL10 -> 263 | AE6: =Elect!BN10 -> 919 | AF6: =Elect!BP10 -> 127 | AG6: =Elect!BR10 -> 161 | AI6: =Water!C11 -> 145 | AJ6: =Water!E11 -> 191.4 | AK6: =Water!G11 -> 0 | AM6: =Gas!C11 -> 1473.4 | AN6: =Gas!E11 -> 335.3 | AO6: =Gas!G11 -> 139 | AP6: =Elect!BT10 -> 199
A7: Cairo at The First Residence | B7: =B6+1 -> 6 | C7: 1 | D7: 2022 | F7: =Elect!J11 -> 5578 | G7: =Elect!K11 -> 3498 | H7: =Elect!Q11 -> 510 | I7: =Elect!S11 -> 134 | J7: =Elect!U11 -> 252 | K7: =Elect!W11 -> 1262.99 | L7: =Elect!Y11 -> 0 | M7: =Elect!AA11 -> 0 | N7: =Elect!AC11 -> 0 | O7: =Elect!AE11 -> 12.19 | P7: =Elect!AG11 -> 11.66 | Q7: =Elect!AI11 -> 414.99 | R7: =Elect!AK11 -> 1996.51 | S7: =Elect!AM11 -> 153.17 | T7: =Elect!AP11 -> 4.3875 | U7: =Elect!AR11 -> 316 | V7: =Elect!AT11 -> 129 | W7: =Elect!AV11 -> 23 | X7: =Elect!AX11 -> 576 | Y7: =Elect!AZ11 -> 58 | Z7: =Elect!BB11 -> 4274 | AA7: =Elect!BD11 -> 236 | AB7: =Elect!BF11 -> 54 | AC7: =Elect!BH11 -> 4540.95 | AD7: =Elect!BL11 -> 242 | AE7: =Elect!BN11 -> 812 | AF7: =Elect!BP11 -> 137 | AG7: =Elect!BR11 -> 147 | AI7: =Water!C12 -> 145 | AJ7: =Water!E12 -> 191.4 | AK7: =Water!G12 -> 0 | AM7: =Gas!C12 -> 1473.4 | AN7: =Gas!E12 -> 335.3 | AO7: =Gas!G12 -> 103 | AP7: =Elect!BT11 -> 203
A8: Cairo at The First Residence | B8: =B7+1 -> 7 | C8: 1 | D8: 2022 | F8: =Elect!J12 -> 5618 | G8: =Elect!K12 -> 3516 | H8: =Elect!Q12 -> 480 | I8: =Elect!S12 -> 140 | J8: =Elect!U12 -> 265 | K8: =Elect!W12 -> 1335.6 | L8: =Elect!Y12 -> 0 | M8: =Elect!AA12 -> 0 | N8: =Elect!AC12 -> 0 | O8: =Elect!AE12 -> 13.25 | P8: =Elect!AG12 -> 12.72 | Q8: =Elect!AI12 -> 430.36 | R8: =Elect!AK12 -> 2163.46 | S8: =Elect!AM12 -> 156.35 | T8: =Elect!AP12 -> 4.275 | U8: =Elect!AR12 -> 345 | V8: =Elect!AT12 -> 133 | W8: =Elect!AV12 -> 17 | X8: =Elect!AX12 -> 588 | Y8: =Elect!AZ12 -> 30 | Z8: =Elect!BB12 -> 4236 | AA8: =Elect!BD12 -> 259 | AB8: =Elect!BF12 -> 56 | AC8: =Elect!BH12 -> 4818.55 | AD8: =Elect!BL12 -> 255 | AE8: =Elect!BN12 -> 882 | AF8: =Elect!BP12 -> 139 | AG8: =Elect!BR12 -> 154 | AI8: =Water!C13 -> 150.8 | AJ8: =Water!E13 -> 203 | AK8: =Water!G13 -> 0 | AM8: =Gas!C13 -> 1473.4 | AN8: =Gas!E13 -> 289.8 | AO8: =Gas!G13 -> 103 | AP8: =Elect!BT12 -> 233
A9: Cairo at The First Residence | B9: =B8+1 -> 8 | C9: 1 | D9: 2022 | F9: =Elect!J13 -> 5864 | G9: =Elect!K13 -> 3590 | H9: =Elect!Q13 -> 510 | I9: =Elect!S13 -> 142 | J9: =Elect!U13 -> 265 | K9: =Elect!W13 -> 1401.32 | L9: =Elect!Y13 -> 257.58 | M9: =Elect!AA13 -> 0 | N9: =Elect!AC13 -> 0 | O9: =Elect!AE13 -> 13.25 | P9: =Elect!AG13 -> 12.72 | Q9: =Elect!AI13 -> 414.46 | R9: =Elect!AK13 -> 2071.24 | S9: =Elect!AM13 -> 155.29 | T9: =Elect!AP13 -> 4.1625 | U9: =Elect!AR13 -> 317 | V9: =Elect!AT13 -> 139 | W9: =Elect!AV13 -> 20 | X9: =Elect!AX13 -> 590 | Y9: =Elect!AZ13 -> 0 | Z9: =Elect!BB13 -> 4343 | AA9: =Elect!BD13 -> 260 | AB9: =Elect!BF13 -> 46 | AC9: =Elect!BH13 -> 4850.5 | AD9: =Elect!BL13 -> 255 | AE9: =Elect!BN13 -> 900 | AF9: =Elect!BP13 -> 130 | AG9: =Elect!BR13 -> 157 | AI9: =Water!C14 -> 150.8 | AJ9: =Water!E14 -> 203 | AK9: =Water!G14 -> 0 | AM9: =Gas!C14 -> 1473.4 | AN9: =Gas!E14 -> 289.8 | AO9: =Gas!G14 -> 103 | AP9: =Elect!BT13 -> 238
A10: Cairo at The First Residence | B10: =B9+1 -> 9 | C10: 1 | D10: 2022 | F10: =Elect!J14 -> 5583 | G10: =Elect!K14 -> 3778 | H10: =Elect!Q14 -> 480 | I10: =Elect!S14 -> 137 | J10: =Elect!U14 -> 253 | K10: =Elect!W14 -> 1171.3 | L10: =Elect!Y14 -> 0 | M10: =Elect!AA14 -> 0 | N10: =Elect!AC14 -> 0 | O10: =Elect!AE14 -> 12.72 | P10: =Elect!AG14 -> 12.72 | Q10: =Elect!AI14 -> 419.76 | R10: =Elect!AK14 -> 2187.84 | S10: =Elect!AM14 -> 157.94 | T10: =Elect!AP14 -> 4.1625 | U10: =Elect!AR14 -> 322 | V10: =Elect!AT14 -> 146 | W10: =Elect!AV14 -> 28 | X10: =Elect!AX14 -> 591 | Y10: =Elect!AZ14 -> 0 | Z10: =Elect!BB14 -> 4454 | AA10: =Elect!BD14 -> 240 | AB10: =Elect!BF14 -> 46 | AC10: =Elect!BH14 -> 4768.05 | AD10: =Elect!BL14 -> 250 | AE10: =Elect!BN14 -> 879 | AF10: =Elect!BP14 -> 132 | AG10: =Elect!BR14 -> 152 | AI10: =Water!C15 -> 145 | AJ10: =Water!E15 -> 191.4 | AK10: =Water!G15 -> 0 | AM10: =Gas!C15 -> 1473.4 | AN10: =Gas!E15 -> 338.1 | AO10: =Gas!G15 -> 103 | AP10: =Elect!BT14 -> 220
A11: Cairo at The First Residence | B11: =B10+1 -> 10 | C11: 1 | D11: 2022 | F11: =Elect!J15 -> 7367 | G11: =Elect!K15 -> 4484 | H11: =Elect!Q15 -> 570 | I11: =Elect!S15 -> 150 | J11: =Elect!U15 -> 278 | K11: =Elect!W15 -> 1014.95 | L11: =Elect!Y15 -> 0 | M11: =Elect!AA15 -> 0 | N11: =Elect!AC15 -> 0 | O11: =Elect!AE15 -> 14.31 | P11: =Elect!AG15 -> 13.78 | Q11: =Elect!AI15 -> 463.75 | R11: =Elect!AK15 -> 2390.3 | S11: =Elect!AM15 -> 173.31 | T11: =Elect!AP15 -> 4.8375 | U11: =Elect!AR15 -> 332 | V11: =Elect!AT15 -> 152 | W11: =Elect!AV15 -> 40 | X11: =Elect!AX15 -> 625 | Y11: =Elect!AZ15 -> 0 | Z11: =Elect!BB15 -> 4484 | AA11: =Elect!BD15 -> 273 | AB11: =Elect!BF15 -> 64 | AC11: =Elect!BH15 -> 5043.9 | AD11: =Elect!BL15 -> 267 | AE11: =Elect!BN15 -> 918 | AF11: =Elect!BP15 -> 140 | AG11: =Elect!BR15 -> 151 | AI11: =Water!C16 -> 162.4 | AJ11: =Water!E16 -> 214.6 | AK11: =Water!G16 -> 0 | AM11: =Gas!C16 -> 1473.4 | AN11: =Gas!E16 -> 338.1 | AO11: =Gas!G16 -> 103 | AP11: =Elect!BT15 -> 211
A12: Cairo at The First Residence | B12: =B11+1 -> 11 | C12: 1 | D12: 2022 | F12: =Elect!J16 -> 6246 | G12: =Elect!K16 -> 3878 | H12: =Elect!Q16 -> 510 | I12: =Elect!S16 -> 130 | J12: =Elect!U16 -> 244 | K12: =Elect!W16 -> 950.29 | L12: =Elect!Y16 -> 0 | M12: =Elect!AA16 -> 0 | N12: =Elect!AC16 -> 0 | O12: =Elect!AE16 -> 11.66 | P12: =Elect!AG16 -> 11.66 | Q12: =Elect!AI16 -> 393.26 | R12: =Elect!AK16 -> 2143.32 | S12: =Elect!AM16 -> 148.4 | T12: =Elect!AP16 -> 4.3875 | U12: =Elect!AR16 -> 324 | V12: =Elect!AT16 -> 133 | W12: =Elect!AV16 -> 27 | X12: =Elect!AX16 -> 545 | Y12: =Elect!AZ16 -> 0 | Z12: =Elect!BB16 -> 4155 | AA12: =Elect!BD16 -> 242 | AB12: =Elect!BF16 -> 54 | AC12: =Elect!BH16 -> 4507.9 | AD12: =Elect!BL16 -> 240 | AE12: =Elect!BN16 -> 811 | AF12: =Elect!BP16 -> 127 | AG12: =Elect!BR16 -> 138 | AI12: =Water!C17 -> 162.4 | AJ12: =Water!E17 -> 220.4 | AK12: =Water!G17 -> 0 | AM12: =Gas!C17 -> 1473.4 | AN12: =Gas!E17 -> 338.1 | AO12: =Gas!G17 -> 103 | AP12: =Elect!BT16 -> 201
A13: Cairo at The First Residence | B13: =B12+1 -> 12 | C13: 1 | D13: 2022 | F13: =Elect!J17 -> 6655 | G13: =Elect!K17 -> 4174 | H13: =Elect!Q17 -> 450 | I13: =Elect!S17 -> 138 | J13: =Elect!U17 -> 257 | K13: =Elect!W17 -> 1049.4 | L13: =Elect!Y17 -> 0 | M13: =Elect!AA17 -> 0 | N13: =Elect!AC17 -> 0 | O13: =Elect!AE17 -> 12.72 | P13: =Elect!AG17 -> 12.72 | Q13: =Elect!AI17 -> 438.84 | R13: =Elect!AK17 -> 2360.62 | S13: =Elect!AM17 -> 162.18 | T13: =Elect!AP17 -> 4.1625 | U13: =Elect!AR17 -> 327 | V13: =Elect!AT17 -> 136 | W13: =Elect!AV17 -> 21 | X13: =Elect!AX17 -> 589 | Y13: =Elect!AZ17 -> 0 | Z13: =Elect!BB17 -> 4537 | AA13: =Elect!BD17 -> 237 | AB13: =Elect!BF17 -> 56 | AC13: =Elect!BH17 -> 4786.25 | AD13: =Elect!BL17 -> 255 | AE13: =Elect!BN17 -> 879 | AF13: =Elect!BP17 -> 136 | AG13: =Elect!BR17 -> 139 | AI13: =Water!C18 -> 162.4 | AJ13: =Water!E18 -> 220.4 | AK13: =Water!G18 -> 0 | AM13: =Gas!C18 -> 1473.4 | AN13: =Gas!E18 -> 338.1 | AO13: =Gas!G18 -> 103 | AP13: =Elect!BT17 -> 179
A14: Cairo at The First Residence | B14: =B13+1 -> 13 | C14: 1 | D14: 2022 | F14: =Elect!J18 -> 6659 | G14: =Elect!K18 -> 4184 | H14: =Elect!Q18 -> 540 | I14: =Elect!S18 -> 139 | J14: =Elect!U18 -> 251 | K14: =Elect!W18 -> 1052.58 | L14: =Elect!Y18 -> 0 | M14: =Elect!AA18 -> 0 | N14: =Elect!AC18 -> 0 | O14: =Elect!AE18 -> 13.78 | P14: =Elect!AG18 -> 13.25 | Q14: =Elect!AI18 -> 443.61 | R14: =Elect!AK18 -> 2365.39 | S14: =Elect!AM18 -> 163.77 | T14: =Elect!AP18 -> 4.8375 | U14: =Elect!AR18 -> 320 | V14: =Elect!AT18 -> 139 | W14: =Elect!AV18 -> 23 | X14: =Elect!AX18 -> 585 | Y14: =Elect!AZ18 -> 0 | Z14: =Elect!BB18 -> 4835 | AA14: =Elect!BD18 -> 233 | AB14: =Elect!BF18 -> 51 | AC14: =Elect!BH18 -> 5120.15 | AD14: =Elect!BL18 -> 265 | AE14: =Elect!BN18 -> 912 | AF14: =Elect!BP18 -> 141 | AG14: =Elect!BR18 -> 145 | AI14: =Water!C19 -> 162.4 | AJ14: =Water!E19 -> 220.4 | AK14: =Water!G19 -> 0 | AM14: =Gas!C19 -> 1473.4 | AN14: =Gas!E19 -> 338.1 | AO14: =Gas!G19 -> 103 | AP14: =Elect!BT18 -> 207
... A32: Cairo at The First Residence | B32: =B31+1 -> 31 | C32: 1 | D32: 2022 | F32: =Elect!J36 -> 8003 | G32: =Elect!K36 -> 4648 | H32: =Elect!Q36 -> 630 | I32: =Elect!S36 -> 138 | J32: =Elect!U36 -> 267.5 | K32: =Elect!W36 -> 512.51 | L32: =Elect!Y36 -> 0 | M32: =Elect!AA36 -> 0 | N32: =Elect!AC36 -> 0 | O32: =Elect!AE36 -> 13.78 | P32: =Elect!AG36 -> 12.72 | Q32: =Elect!AI36 -> 402.27 | R32: =Elect!AK36 -> 2076.01 | S32: =Elect!AM36 -> 154.76 | T32: =Elect!AP36 -> 4.3875 | U32: =Elect!AR36 -> 320 | V32: =Elect!AT36 -> 114 | W32: =Elect!AV36 -> 33 | X32: =Elect!AX36 -> 532 | Y32: =Elect!AZ36 -> 6 | Z32: =Elect!BB36 -> 4266 | AA32: =Elect!BD36 -> 209 | AB32: =Elect!BF36 -> 52 | AC32: =Elect!BH36 -> 4685.35 | AD32: =Elect!BL36 -> 59 | AE32: =Elect!BN36 -> 789 | AF32: =Elect!BP36 -> 148 | AG32: =Elect!BR36 -> 139 | AI32: =Water!C37 -> 121.8 | AJ32: =Water!E37 -> 162.4 | AK32: =Water!G37 -> 0 | AM32: =Gas!C37 -> 1473.4 | AN32: =Gas!E37 -> 396.9 | AO32: =Gas!G37 -> 81 | AP32: =Elect!BT36 -> 190

Sheet Sheet1

Sheet Sheet2

Sheet Elect
A1: January | M1: Electricity | BP1: Gourmandise UP | BR1: 1.6 | BS1: Power Taxes | BU1: Max Demand | BW1: 500 | BX1: Electricity UP | BZ1: 1.15
BS2: Light Taxes | BU2: PF Penalty | BX2: Max. Demand UP | BZ2: 30
A3: Date | B3: COUNTER (1) | D3: MD | F3: KVAR | H3: n | I3: Guest Rooms Consumption | R3: Casino Consumption | V3: Plant Room Shared Loads | AO3: To Be Charged By First Arabian | BK3: From Main Panel G2 | BS3: Total Consumption. | BT3: No. Of | BU3: KWH/ | BV3: No. Of | BW3: KWH/ | BX3: Total Cost | BY3: L.E\ | BZ3: L.E\
B4: Reading | C4: Consp. F: *800 | D4: Reading | E4: Consp F: 80 | F4: Reading | G4: Consp. F:*10 | I4: Main Feeder | J4: Consp | K4: T2+T8 | L4: Trans T2 | M4: Consp | N4: Trans T8 | O4: Consp | P4: La Gourmandize | Q4: Consp *30 | R4: Casino 3rd floor EM | S4: Consp | T4: Casino 3rd floor Normal | U4: Consp | V4: Chiller 1 | W4: Consp 53% | X4: Chiller 2 | Y4: Consp 53% | Z4: Chiller 3 | AA4: Consp 53% | AB4: Chiller 4 | AC4: Consp 53% | AD4: Chiller 5 | AE4: Consp 53% | AF4: Chiller 6 | AG4: Consp 53% | AH4: Cooling Towers | AI4: Consp 53% | AJ4: Chiller Pumps | AK4: Consp 53% | AL4: Cooling Tower Pumps | AM4: Consp 53% | AN4: Total Plant Room Consp | AO4: Fiber Chiller (N24) | AP4: Consp | AQ4: Mall Ceiling light (N4) | AR4: Consp | AS4: LG Bakery (N2) | AT4: Consp | AU4: LG Bakery light ( Old lockers ) | AV4: Consp | AW4: MCCR1 | AX4: Consp | AY4: Children Swimming pool | AZ4: Consp | BA4: DPH1 | BB4: Consp | BC4: Guest Rooms Emergency | BD4: Consp | BE4: Hotel Hoods | BF4: Consp | BG4: Main G2 | BH4: Consp | BI4: Total Consp From First Arabian | BJ4: First Arabian Charge Back | BK4: Old Casino Emergency | BL4: Consp | BM4: L / A | BN4: Consp | BO4: L / B | BP4: Consp | BQ4: L / C | BR4: Consp | BT4: Rooms | BU4: room | BV4: guest | BW4: guest | BY4: Room | BZ4: Guest
A5: Last Month Reading | I5: 23715588 | J5: =IF(I5>=I4,I5-I4,0) -> 0 | K5: =M5+O5 -> 0 | L5: 595387 | M5: =IF(L5>=L4,L5-L4,0) -> 0 | N5: 522852 | O5: =IF(N5>=N4,N5-N4,0) -> 0 | P5: 221186 | Q5: =IF(P5>=P4,P5-P4,0)*30 -> 0 | R5: 177935 | S5: =IF(R5>=R4,R5-R4,0) -> 0 | T5: 325086 | U5: =IF(T5>=T4,T5-T4,0) -> 0 | V5: 734409 | W5: =IF(V5>=V4,V5-V4,0)*0.53 -> 0 | X5: 116729 | Y5: =IF(X5>=X4,X5-X4,0)*0.53 -> 0 | Z5: 134669 | AA5: =IF(Z5>=Z4,Z5-Z4,0)*0.53 -> 0 | AB5: 488247 | AC5: =IF(AB5>=AB4,AB5-AB4,0)*0.53 -> 0 | AD5: 656201 | AE5: =IF(AD5>=AD4,AD5-AD4,0)*0.53 -> 0 | AF5: 834896 | AG5: =IF(AF5>=AF4,AF5-AF4,0)*0.53 -> 0 | AH5: 967240 | AI5: =IF(AH5>=AH4,AH5-AH4,0)*0.53 -> 0 | AJ5: 621756 | AK5: =IF(AJ5>=AJ4,AJ5-AJ4,0)*0.53 -> 0 | AL5: 484025 | AM5: =IF(AL5>=AL4,AL5-AL4,0)*0.53 -> 0 | AN5: =W5+Y5+AA5+AC5+AE5+AG5+AI5+AK5+AM5 -> 0 | AO5: 7649849 | AP5: =IF(AO5>=AO4,AO5-AO4,0)*0.1125 -> 0 | AQ5: 667350 | AR5: =IF(AQ5>=AQ4,AQ5-AQ4,0) -> 0 | AS5: 961991 | AT5: =IF(AS5>=AS4,AS5-AS4,0) -> 0 | AU5: 809269 | AV5: =IF(AU5>=AU4,AU5-AU4,0) -> 0 | AW5: 2603425 | AX5: =IF(AW5>=AW4,AW5-AW4,0) -> 0 | AY5: 229064 | AZ5: =IF(AY5>=AY4,AY5-AY4,0) -> 0 | BA5: 19163085 | BB5: =IF(BA5>=BA4,BA5-BA4,0) -> 0 | BC5: 560194 | BD5: =IF(BC5>=BC4,BC5-BC4,0) -> 0 | BE5: 25110 | BF5: =IF(BE5>=BE4,BE5-BE4,0) -> 0 | BG5: 23964679 | BH5: =IF(BG5>=BG4,BG5-BG4,0)-(0.45*BN5)-(0.45*BP5)-BR5 -> 0 | BI5: =AP5+AR5+AT5+AV5+AX5+AZ5+BB5+BD5+BF5+BH5 -> 0 | BJ5: =BI5+AN5 -> 0 | BK5: 1419836 | BL5: =IF(BK5>=BK4,BK5-BK4,0) -> 0 | BM5: 3909467 | BN5: =IF(BM5>=BM4,BM5-BM4,0) -> 0 | BO5: 409591 | BP5: =IF(BO5>=BO4,BO5-BO4,0) -> 0 | BQ5: 513610 | BR5: =IF(BQ5>=BQ4,BQ5-BQ4,0) -> 0
A6: 1 | C6: =IF(+B6-B5>0,B6-B5,(B6-B5)>0)*800 -> 0 | E6: =IF(+D6-D5>0,D6-D5,(D6-D5)>0)*80 -> 0 | G6: =IF(+F6-F5>0,F6-F5,(F6-F5)>0)*10 -> 0 | H6: 56 | I6: 23721425 | J6: =IF(I6>=I5,I6-I5,0) -> 5837 | K6: =M6+O6 -> 3617 | L6: 597404 | M6: =IF(L6>=L5,L6-L5,0) -> 2017 | N6: 524452 | O6: =IF(N6>=N5,N6-N5,0) -> 1600 | P6: 221204 | Q6: =IF(P6>=P5,P6-P5,0)*30 -> 540 | R6: 178067 | S6: =IF(R6>=R5,R6-R5,0) -> 132 | T6: 325343 | U6: =IF(T6>=T5,T6-T5,0) -> 257 | V6: 735767 | W6: =IF(V6>=V5,V6-V5,0)*0.53 -> 719.74 | X6: 116902 | Y6: =IF(X6>=X5,X6-X5,0)*0.53 -> 91.69 | Z6: 134669 | AA6: =IF(Z6>=Z5,Z6-Z5,0)*0.53 -> 0 | AB6: 488247 | AC6: =IF(AB6>=AB5,AB6-AB5,0)*0.53 -> 0 | AD6: 656230 | AE6: =IF(AD6>=AD5,AD6-AD5,0)*0.53 -> 15.37 | AF6: 834923 | AG6: =IF(AF6>=AF5,AF6-AF5,0)*0.53 -> 14.31 | AH6: 968237 | AI6: =IF(AH6>=AH5,AH6-AH5,0)*0.53 -> 528.41 | AJ6: 628180 | AK6: =IF(AJ6>=AJ5,AJ6-AJ5,0)*0.53 -> 3404.72 | AL6: 484297 | AM6: =IF(AL6>=AL5,AL6-AL5,0)*0.53 -> 144.16 | AN6: =W6+Y6+AA6+AC6+AE6+AG6+AI6+AK6+AM6 -> 4918.4 | AO6: 7649886 | AP6: =IF(AO6>=AO5,AO6-AO5,0)*0.1125 -> 4.1625 | AQ6: 667681 | AR6: =IF(AQ6>=AQ5,AQ6-AQ5,0) -> 331 | AS6: 962107 | AT6: =IF(AS6>=AS5,AS6-AS5,0) -> 116 | AU6: 809293 | AV6: =IF(AU6>=AU5,AU6-AU5,0) -> 24 | AW6: 2603912 | AX6: =IF(AW6>=AW5,AW6-AW5,0) -> 487 | AY6: 229133 | AZ6: =IF(AY6>=AY5,AY6-AY5,0) -> 69 | BA6: 19167416 | BB6: =IF(BA6>=BA5,BA6-BA5,0) -> 4331 | BC6: 560406 | BD6: =IF(BC6>=BC5,BC6-BC5,0) -> 212 | BE6: 25148 | BF6: =IF(BE6>=BE5,BE6-BE5,0) -> 38 | BG6: 23969979 | BH6: =IF(BG6>=BG5,BG6-BG5,0)-(0.45*BN6)-(0.45*BP6)-BR6 -> 4930.4 | BI6: =AP6+AR6+AT6+AV6+AX6+AZ6+BB6+BD6+BF6+BH6 -> 10542.562 | BJ6: =BI6+AN6 -> 15460.962 | BK6: 1420150 | BL6: =IF(BK6>=BK5,BK6-BK5,0) -> 314 | BM6: 3909850 | BN6: =IF(BM6>=BM5,BM6-BM5,0) -> 383 | BO6: 409716 | BP6: =IF(BO6>=BO5,BO6-BO5,0) -> 125 | BQ6: 513751 | BR6: =IF(BQ6>=BQ5,BQ6-BQ5,0) -> 141 | BS6: =J6+Q6+AN6+BI6 -> 21837.963 | BT6: 232 | BU6: =IF(BS6>0,BS6/BT5,0) -> #DIV/0! | BW6: =IF(BS6>0,BS6/BV6,0) -> #DIV/0! | BX6: =((BS6-Q6)*$BZ$1)+(Q6*$BR$1) -> 25356.657 | BY6: =IF(BX6>0,BX6/BT5,0) -> #DIV/0! | BZ6: =IF(BX6>0,BX6/BV6,0) -> #DIV/0!
A7: 2 | I7: 23728030 | J7: =IF(I7>=I6,I7-I6,0) -> 6605 | K7: =M7+O7 -> 3882 | L7: 599815 | M7: =IF(L7>=L6,L7-L6,0) -> 2411 | N7: 525923 | O7: =IF(N7>=N6,N7-N6,0) -> 1471 | P7: 221223 | Q7: =IF(P7>=P6,P7-P6,0)*30 -> 570 | R7: 178215 | S7: =IF(R7>=R6,R7-R6,0) -> 148 | T7: 325617 | U7: =IF(T7>=T6,T7-T6,0) -> 274 | V7: 738127 | W7: =IF(V7>=V6,V7-V6,0)*0.53 -> 1250.8 | X7: 116902 | Y7: =IF(X7>=X6,X7-X6,0)*0.53 -> 0 | Z7: 134669 | AA7: =IF(Z7>=Z6,Z7-Z6,0)*0.53 -> 0 | AB7: 488247 | AC7: =IF(AB7>=AB6,AB7-AB6,0)*0.53 -> 0 | AD7: 656256 | AE7: =IF(AD7>=AD6,AD7-AD6,0)*0.53 -> 13.78 | AF7: 834948 | AG7: =IF(AF7>=AF6,AF7-AF6,0)*0.53 -> 13.25 | AH7: 969346 | AI7: =IF(AH7>=AH6,AH7-AH6,0)*0.53 -> 587.77 | AJ7: 633074 | AK7: =IF(AJ7>=AJ6,AJ7-AJ6,0)*0.53 -> 2593.82 | AL7: 484605 | AM7: =IF(AL7>=AL6,AL7-AL6,0)*0.53 -> 163.24 | AN7: =W7+Y7+AA7+AC7+AE7+AG7+AI7+AK7+AM7 -> 4622.66 | AO7: 7649925 | AP7: =IF(AO7>=AO6,AO7-AO6,0)*0.1125 -> 4.3875 | AQ7: 668034 | AR7: =IF(AQ7>=AQ6,AQ7-AQ6,0) -> 353 | AS7: 962243 | AT7: =IF(AS7>=AS6,AS7-AS6,0) -> 136 | AU7: 809321 | AV7: =IF(AU7>=AU6,AU7-AU6,0) -> 28 | AW7: 2604534 | AX7: =IF(AW7>=AW6,AW7-AW6,0) -> 622 | AY7: 229199 | AZ7: =IF(AY7>=AY6,AY7-AY6,0) -> 66 | BA7: 19172103 | BB7: =IF(BA7>=BA6,BA7-BA6,0) -> 4687 | BC7: 560660 | BD7: =IF(BC7>=BC6,BC7-BC6,0) -> 254 | BE7: 25200 | BF7: =IF(BE7>=BE6,BE7-BE6,0) -> 52 | BG7: 23975822 | BH7: =IF(BG7>=BG6,BG7-BG6,0)-(0.45*BN7)-(0.45*BP7)-BR7 -> 5186.25 | BI7: =AP7+AR7+AT7+AV7+AX7+AZ7+BB7+BD7+BF7+BH7 -> 11388.638 | BJ7: =BI7+AN7 -> 16011.298 | BK7: 1420425 | BL7: =IF(BK7>=BK6,BK7-BK6,0) -> 275 | BM7: 3910788 | BN7: =IF(BM7>=BM6,BM7-BM6,0) -> 938 | BO7: 409873 | BP7: =IF(BO7>=BO6,BO7-BO6,0) -> 157 | BQ7: 513915 | BR7: =IF(BQ7>=BQ6,BQ7-BQ6,0) -> 164 | BS7: =J7+Q7+AN7+BI7 -> 23186.298 | BT7: 191 | BU7: =IF(BS7>0,BS7/BT6,0) -> 99.940938 | BW7: =IF(BS7>0,BS7/BV7,0) -> #DIV/0! | BX7: =((BS7-Q7)*$BZ$1)+(Q7*$BR$1) -> 26920.742 | BY7: =IF(BX7>0,BX7/BT6,0) -> 116.03768 | BZ7: =IF(BX7>0,BX7/BV7,0) -> #DIV/0!
A8: 3 | C8: =IF(+B8-B7>0,B8-B7,(B8-B7)>0)*800 -> 0 | E8: =IF(+D8-D7>0,D8-D7,(D8-D7)>0)*80 -> 0 | G8: =IF(+F8-F7>0,F8-F7,(F8-F7)>0)*10 -> 0 | H8: 57 | I8: 23734176 | J8: =IF(I8>=I7,I8-I7,0) -> 6146 | K8: =M8+O8 -> 3709 | L8: 602116 | M8: =IF(L8>=L7,L8-L7,0) -> 2301 | N8: 527331 | O8: =IF(N8>=N7,N8-N7,0) -> 1408 | P8: 221239 | Q8: =IF(P8>=P7,P8-P7,0)*30 -> 480 | R8: 178357 | S8: =IF(R8>=R7,R8-R7,0) -> 142 | T8: 325818 | U8: =IF(T8>=T7,T8-T7,0) -> 201 | V8: 740425 | W8: =IF(V8>=V7,V8-V7,0)*0.53 -> 1217.94 | X8: 116925 | Y8: =IF(X8>=X7,X8-X7,0)*0.53 -> 12.19 | Z8: 134745 | AA8: =IF(Z8>=Z7,Z8-Z7,0)*0.53 -> 40.28 | AB8: 488293 | AC8: =IF(AB8>=AB7,AB8-AB7,0)*0.53 -> 24.38 | AD8: 656280 | AE8: =IF(AD8>=AD7,AD8-AD7,0)*0.53 -> 12.72 | AF8: 834971 | AG8: =IF(AF8>=AF7,AF8-AF7,0)*0.53 -> 12.19 | AH8: 970444 | AI8: =IF(AH8>=AH7,AH8-AH7,0)*0.53 -> 581.94 | AJ8: 637098 | AK8: =IF(AJ8>=AJ7,AJ8-AJ7,0)*0.53 -> 2132.72 | AL8: 484896 | AM8: =IF(AL8>=AL7,AL8-AL7,0)*0.53 -> 154.23 | AN8: =W8+Y8+AA8+AC8+AE8+AG8+AI8+AK8+AM8 -> 4188.59 | AO8: 7649962 | AP8: =IF(AO8>=AO7,AO8-AO7,0)*0.1125 -> 4.1625 | AQ8: 668363 | AR8: =IF(AQ8>=AQ7,AQ8-AQ7,0) -> 329 | AS8: 962379 | AT8: =IF(AS8>=AS7,AS8-AS7,0) -> 136 | AU8: 809350 | AV8: =IF(AU8>=AU7,AU8-AU7,0) -> 29 | AW8: 2605112 | AX8: =IF(AW8>=AW7,AW8-AW7,0) -> 578 | AY8: 229258 | AZ8: =IF(AY8>=AY7,AY8-AY7,0) -> 59 | BA8: 19176636 | BB8: =IF(BA8>=BA7,BA8-BA7,0) -> 4533 | BC8: 560919 | BD8: =IF(BC8>=BC7,BC8-BC7,0) -> 259 | BE8: 25251 | BF8: =IF(BE8>=BE7,BE8-BE7,0) -> 51 | BG8: 23981116 | BH8: =IF(BG8>=BG7,BG8-BG7,0)-(0.45*BN8)-(0.45*BP8)-BR8 -> 4695.45 | BI8: =AP8+AR8+AT8+AV8+AX8+AZ8+BB8+BD8+BF8+BH8 -> 10673.613 | BJ8: =BI8+AN8 -> 14862.203 | BK8: 1420671 | BL8: =IF(BK8>=BK7,BK8-BK7,0) -> 246 | BM8: 3911650 | BN8: =IF(BM8>=BM7,BM8-BM7,0) -> 862 | BO8: 410010 | BP8: =IF(BO8>=BO7,BO8-BO7,0) -> 137 | BQ8: 514064 | BR8: =IF(BQ8>=BQ7,BQ8-BQ7,0) -> 149 | BS8: =J8+Q8+AN8+BI8 -> 21488.202 | BT8: 219 | BU8: =IF(BS8>0,BS8/BT7,0) -> 112.50368 | BW8: =IF(BS8>0,BS8/BV8,0) -> #DIV/0! | BX8: =((BS8-Q8)*$BZ$1)+(Q8*$BR$1) -> 24927.433 | BY8: =IF(BX8>0,BX8/BT7,0) -> 130.51012 | BZ8: =IF(BX8>0,BX8/BV8,0) -> #DIV/0!
A9: 4 | C9: =IF(+B9-B8>0,B9-B8,(B9-B8)>0)*800 -> 0 | E9: =IF(+D9-D8>0,D9-D8,(D9-D8)>0)*80 -> 0 | G9: =IF(+F9-F8>0,F9-F8,(F9-F8)>0)*10 -> 0 | I9: 23740751 | J9: =IF(I9>=I8,I9-I8,0) -> 6575 | K9: =M9+O9 -> 3994 | L9: 604576 | M9: =IF(L9>=L8,L9-L8,0) -> 2460 | N9: 528865 | O9: =IF(N9>=N8,N9-N8,0) -> 1534 | P9: 221258 | Q9: =IF(P9>=P8,P9-P8,0)*30 -> 570 | R9: 178495 | S9: =IF(R9>=R8,R9-R8,0) -> 138 | T9: 326148 | U9: =IF(T9>=T8,T9-T8,0) -> 330 | V9: 742505 | W9: =IF(V9>=V8,V9-V8,0)*0.53 -> 1102.4 | X9: 116925 | Y9: =IF(X9>=X8,X9-X8,0)*0.53 -> 0 | Z9: 134745 | AA9: =IF(Z9>=Z8,Z9-Z8,0)*0.53 -> 0 | AB9: 488293 | AC9: =IF(AB9>=AB8,AB9-AB8,0)*0.53 -> 0 | AD9: 656303 | AE9: =IF(AD9>=AD8,AD9-AD8,0)*0.53 -> 12.19 | AF9: 834994 | AG9: =IF(AF9>=AF8,AF9-AF8,0)*0.53 -> 12.19 | AH9: 971310 | AI9: =IF(AH9>=AH8,AH9-AH8,0)*0.53 -> 458.98 | AJ9: 640924 | AK9: =IF(AJ9>=AJ8,AJ9-AJ8,0)*0.53 -> 2027.78 | AL9: 485206 | AM9: =IF(AL9>=AL8,AL9-AL8,0)*0.53 -> 164.3 | AN9: =W9+Y9+AA9+AC9+AE9+AG9+AI9+AK9+AM9 -> 3777.84 | AO9: 7650003 | AP9: =IF(AO9>=AO8,AO9-AO8,0)*0.1125 -> 4.6125 | AQ9: 668689 | AR9: =IF(AQ9>=AQ8,AQ9-AQ8,0) -> 326 | AS9: 962516 | AT9: =IF(AS9>=AS8,AS9-AS8,0) -> 137 | AU9: 809383 | AV9: =IF(AU9>=AU8,AU9-AU8,0) -> 33 | AW9: 2605729 | AX9: =IF(AW9>=AW8,AW9-AW8,0) -> 617 | AY9: 229323 | AZ9: =IF(AY9>=AY8,AY9-AY8,0) -> 65 | BA9: 19181492 | BB9: =IF(BA9>=BA8,BA9-BA8,0) -> 4856 | BC9: 561210 | BD9: =IF(BC9>=BC8,BC9-BC8,0) -> 291 | BE9: 25303 | BF9: =IF(BE9>=BE8,BE9-BE8,0) -> 52 | BG9: 23986958 | BH9: =IF(BG9>=BG8,BG9-BG8,0)-(0.45*BN9)-(0.45*BP9)-BR9 -> 5198.25 | BI9: =AP9+AR9+AT9+AV9+AX9+AZ9+BB9+BD9+BF9+BH9 -> 11579.862 | BJ9: =BI9+AN9 -> 15357.702 | BK9: 1420940 | BL9: =IF(BK9>=BK8,BK9-BK8,0) -> 269 | BM9: 3912599 | BN9: =IF(BM9>=BM8,BM9-BM8,0) -> 949 | BO9: 410156 | BP9: =IF(BO9>=BO8,BO9-BO8,0) -> 146 | BQ9: 514215 | BR9: =IF(BQ9>=BQ8,BQ9-BQ8,0) -> 151 | BS9: =J9+Q9+AN9+BI9 -> 22502.702 | BT9: 205 | BU9: =IF(BS9>0,BS9/BT8,0) -> 102.75207 | BW9: =IF(BS9>0,BS9/BV9,0) -> #DIV/0! | BX9: =((BS9-Q9)*$BZ$1)+(Q9*$BR$1) -> 26134.608 | BY9: =IF(BX9>0,BX9/BT8,0) -> 119.33611 | BZ9: =IF(BX9>0,BX9/BV9,0) -> #DIV/0!
A10: 5 | C10: =IF(+B10-B9>0,B10-B9,(B10-B9)>0)*800 -> 0 | E10: =IF(+D10-D9>0,D10-D9,(D10-D9)>0)*80 -> 0 | G10: =IF(+F10-F9>0,F10-F9,(F10-F9)>0)*10 -> 0 | H10: 58 | I10: 23747324 | J10: =IF(I10>=I9,I10-I9,0) -> 6573 | K10: =M10+O10 -> 4119 | L10: 607115 | M10: =IF(L10>=L9,L10-L9,0) -> 2539 | N10: 530445 | O10: =IF(N10>=N9,N10-N9,0) -> 1580 | P10: 221275 | Q10: =IF(P10>=P9,P10-P9,0)*30 -> 510 | R10: 178639 | S10: =IF(R10>=R9,R10-R9,0) -> 144 | T10: 326420 | U10: =IF(T10>=T9,T10-T9,0) -> 272 | V10: 745763 | W10: =IF(V10>=V9,V10-V9,0)*0.53 -> 1726.74 | X10: 116925 | Y10: =IF(X10>=X9,X10-X9,0)*0.53 -> 0 | Z10: 134745 | AA10: =IF(Z10>=Z9,Z10-Z9,0)*0.53 -> 0 | AB10: 488293 | AC10: =IF(AB10>=AB9,AB10-AB9,0)*0.53 -> 0 | AD10: 656330 | AE10: =IF(AD10>=AD9,AD10-AD9,0)*0.53 -> 14.31 | AF10: 835020 | AG10: =IF(AF10>=AF9,AF10-AF9,0)*0.53 -> 13.78 | AH10: 972189 | AI10: =IF(AH10>=AH9,AH10-AH9,0)*0.53 -> 465.87 | AJ10: 645300 | AK10: =IF(AJ10>=AJ9,AJ10-AJ9,0)*0.53 -> 2319.28 | AL10: 485528 | AM10: =IF(AL10>=AL9,AL10-AL9,0)*0.53 -> 170.66 | AN10: =W10+Y10+AA10+AC10+AE10+AG10+AI10+AK10+AM10 -> 4710.64 | AO10: 7650042 | AP10: =IF(AO10>=AO9,AO10-AO9,0)*0.1125 -> 4.3875 | AQ10: 668994 | AR10: =IF(AQ10>=AQ9,AQ10-AQ9,0) -> 305 | AS10: 962654 | AT10: =IF(AS10>=AS9,AS10-AS9,0) -> 138 | AU10: 809408 | AV10: =IF(AU10>=AU9,AU10-AU9,0) -> 25 | AW10: 2606367 | AX10: =IF(AW10>=AW9,AW10-AW9,0) -> 638 | AY10: 229384 | AZ10: =IF(AY10>=AY9,AY10-AY9,0) -> 61 | BA10: 19186303 | BB10: =IF(BA10>=BA9,BA10-BA9,0) -> 4811 | BC10: 561472 | BD10: =IF(BC10>=BC9,BC10-BC9,0) -> 262 | BE10: 25357 | BF10: =IF(BE10>=BE9,BE10-BE9,0) -> 54 | BG10: 23992604 | BH10: =IF(BG10>=BG9,BG10-BG9,0)-(0.45*BN10)-(0.45*BP10)-BR10 -> 5014.3 | BI10: =AP10+AR10+AT10+AV10+AX10+AZ10+BB10+BD10+BF10+BH10 -> 11312.688 | BJ10: =BI10+AN10 -> 16023.327 | BK10: 1421203 | BL10: =IF(BK10>=BK9,BK10-BK9,0) -> 263 | BM10: 3913518 | BN10: =IF(BM10>=BM9,BM10-BM9,0) -> 919 | BO10: 410283 | BP10: =IF(BO10>=BO9,BO10-BO9,0) -> 127 | BQ10: 514376 | BR10: =IF(BQ10>=BQ9,BQ10-BQ9,0) -> 161 | BS10: =J10+Q10+AN10+BI10 -> 23106.327 | BT10: 199 | BU10: =IF(BS10>0,BS10/BT9,0) -> 112.71379 | BW10: =IF(BS10>0,BS10/BV10,0) -> #DIV/0! | BX10: =((BS10-Q10)*$BZ$1)+(Q10*$BR$1) -> 26801.777 | BY10: =IF(BX10>0,BX10/BT9,0) -> 130.74037 | BZ10: =IF(BX10>0,BX10/BV10,0) -> #DIV/0!
A11: 6 | C11: =IF(+B11-B10>0,B11-B10,(B11-B10)>0)*800 -> 0 | E11: =IF(+D11-D10>0,D11-D10,(D11-D10)>0)*80 -> 0 | G11: =IF(+F11-F10>0,F11-F10,(F11-F10)>0)*10 -> 0 | I11: 23752902 | J11: =IF(I11>=I10,I11-I10,0) -> 5578 | K11: =M11+O11 -> 3498 | L11: 609280 | M11: =IF(L11>=L10,L11-L10,0) -> 2165 | N11: 531778 | O11: =IF(N11>=N10,N11-N10,0) -> 1333 | P11: 221292 | Q11: =IF(P11>=P10,P11-P10,0)*30 -> 510 | R11: 178773 | S11: =IF(R11>=R10,R11-R10,0) -> 134 | T11: 326672 | U11: =IF(T11>=T10,T11-T10,0) -> 252 | V11: 748146 | W11: =IF(V11>=V10,V11-V10,0)*0.53 -> 1262.99 | X11: 116925 | Y11: =IF(X11>=X10,X11-X10,0)*0.53 -> 0 | Z11: 134745 | AA11: =IF(Z11>=Z10,Z11-Z10,0)*0.53 -> 0 | AB11: 488293 | AC11: =IF(AB11>=AB10,AB11-AB10,0)*0.53 -> 0 | AD11: 656353 | AE11: =IF(AD11>=AD10,AD11-AD10,0)*0.53 -> 12.19 | AF11: 835042 | AG11: =IF(AF11>=AF10,AF11-AF10,0)*0.53 -> 11.66 | AH11: 972972 | AI11: =IF(AH11>=AH10,AH11-AH10,0)*0.53 -> 414.99 | AJ11: 649067 | AK11: =IF(AJ11>=AJ10,AJ11-AJ10,0)*0.53 -> 1996.51 | AL11: 485817 | AM11: =IF(AL11>=AL10,AL11-AL10,0)*0.53 -> 153.17 | AN11: =W11+Y11+AA11+AC11+AE11+AG11+AI11+AK11+AM11 -> 3851.51 | AO11: 7650081 | AP11: =IF(AO11>=AO10,AO11-AO10,0)*0.1125 -> 4.3875 | AQ11: 669310 | AR11: =IF(AQ11>=AQ10,AQ11-AQ10,0) -> 316 | AS11: 962783 | AT11: =IF(AS11>=AS10,AS11-AS10,0) -> 129 | AU11: 809431 | AV11: =IF(AU11>=AU10,AU11-AU10,0) -> 23 | AW11: 2606943 | AX11: =IF(AW11>=AW10,AW11-AW10,0) -> 576 | AY11: 229442 | AZ11: =IF(AY11>=AY10,AY11-AY10,0) -> 58 | BA11: 19190577 | BB11: =IF(BA11>=BA10,BA11-BA10,0) -> 4274 | BC11: 561708 | BD11: =IF(BC11>=BC10,BC11-BC10,0) -> 236 | BE11: 25411 | BF11: =IF(BE11>=BE10,BE11-BE10,0) -> 54 | BG11: 23997719 | BH11: =IF(BG11>=BG10,BG11-BG10,0)-(0.45*BN11)-(0.45*BP11)-BR11 -> 4540.95 | BI11: =AP11+AR11+AT11+AV11+AX11+AZ11+BB11+BD11+BF11+BH11 -> 10211.338 | BJ11: =BI11+AN11 -> 14062.848 | BK11: 1421445 | BL11: =IF(BK11>=BK10,BK11-BK10,0) -> 242 | BM11: 3914330 | BN11: =IF(BM11>=BM10,BM11-BM10,0) -> 812 | BO11: 410420 | BP11: =IF(BO11>=BO10,BO11-BO10,0) -> 137 | BQ11: 514523 | BR11: =IF(BQ11>=BQ10,BQ11-BQ10,0) -> 147 | BS11: =J11+Q11+AN11+BI11 -> 20150.848 | BT11: 203 | BU11: =IF(BS11>0,BS11/BT10,0) -> 101.26054 | BW11: =IF(BS11>0,BS11/BV11,0) -> #DIV/0! | BX11: =((BS11-Q11)*$BZ$1)+(Q11*$BR$1) -> 23402.975 | BY11: =IF(BX11>0,BX11/BT10,0) -> 117.60289 | BZ11: =IF(BX11>0,BX11/BV11,0) -> #DIV/0!
A12: 7 | C12: =IF(+B12-B11>0,B12-B11,(B12-B11)>0)*800 -> 0 | E12: =IF(+D12-D11>0,D12-D11,(D12-D11)>0)*80 -> 0 | G12: =IF(+F12-F11>0,F12-F11,(F12-F11)>0)*10 -> 0 | H12: 59 | I12: 23758520 | J12: =IF(I12>=I11,I12-I11,0) -> 5618 | K12: =M12+O12 -> 3516 | L12: 611439 | M12: =IF(L12>=L11,L12-L11,0) -> 2159 | N12: 533135 | O12: =IF(N12>=N11,N12-N11,0) -> 1357 | P12: 221308 | Q12: =IF(P12>=P11,P12-P11,0)*30 -> 480 | R12: 178913 | S12: =IF(R12>=R11,R12-R11,0) -> 140 | T12: 326937 | U12: =IF(T12>=T11,T12-T11,0) -> 265 | V12: 750666 | W12: =IF(V12>=V11,V12-V11,0)*0.53 -> 1335.6 | X12: 116439 | Y12: =IF(X12>=X11,X12-X11,0)*0.53 -> 0 | Z12: 134745 | AA12: =IF(Z12>=Z11,Z12-Z11,0)*0.53 -> 0 | AB12: 488293 | AC12: =IF(AB12>=AB11,AB12-AB11,0)*0.53 -> 0 | AD12: 656378 | AE12: =IF(AD12>=AD11,AD12-AD11,0)*0.53 -> 13.25 | AF12: 835066 | AG12: =IF(AF12>=AF11,AF12-AF11,0)*0.53 -> 12.72 | AH12: 973784 | AI12: =IF(AH12>=AH11,AH12-AH11,0)*0.53 -> 430.36 | AJ12: 653149 | AK12: =IF(AJ12>=AJ11,AJ12-AJ11,0)*0.53 -> 2163.46 | AL12: 486112 | AM12: =IF(AL12>=AL11,AL12-AL11,0)*0.53 -> 156.35 | AN12: =W12+Y12+AA12+AC12+AE12+AG12+AI12+AK12+AM12 -> 4111.74 | AO12: 7650119 | AP12: =IF(AO12>=AO11,AO12-AO11,0)*0.1125 -> 4.275 | AQ12: 669655 | AR12: =IF(AQ12>=AQ11,AQ12-AQ11,0) -> 345 | AS12: 962916 | AT12: =IF(AS12>=AS11,AS12-AS11,0) -> 133 | AU12: 809448 | AV12: =IF(AU12>=AU11,AU12-AU11,0) -> 17 | AW12: 2607531 | AX12: =IF(AW12>=AW11,AW12-AW11,0) -> 588 | AY12: 229472 | AZ12: =IF(AY12>=AY11,AY12-AY11,0) -> 30 | BA12: 19194813 | BB12: =IF(BA12>=BA11,BA12-BA11,0) -> 4236 | BC12: 561967 | BD12: =IF(BC12>=BC11,BC12-BC11,0) -> 259 | BE12: 25467 | BF12: =IF(BE12>=BE11,BE12-BE11,0) -> 56 | BG12: 24003151 | BH12: =IF(BG12>=BG11,BG12-BG11,0)-(0.45*BN12)-(0.45*BP12)-BR12 -> 4818.55 | BI12: =AP12+AR12+AT12+AV12+AX12+AZ12+BB12+BD12+BF12+BH12 -> 10486.825 | BJ12: =BI12+AN12 -> 14598.565 | BK12: 1421700 | BL12: =IF(BK12>=BK11,BK12-BK11,0) -> 255 | BM12: 3915212 | BN12: =IF(BM12>=BM11,BM12-BM11,0) -> 882 | BO12: 410559 | BP12: =IF(BO12>=BO11,BO12-BO11,0) -> 139 | BQ12: 514677 | BR12: =IF(BQ12>=BQ11,BQ12-BQ11,0) -> 154 | BS12: =J12+Q12+AN12+BI12 -> 20696.565 | BT12: 233 | BU12: =IF(BS12>0,BS12/BT11,0) -> 101.95352 | BW12: =IF(BS12>0,BS12/BV12,0) -> #DIV/0! | BX12: =((BS12-Q12)*$BZ$1)+(Q12*$BR$1) -> 24017.05 | BY12: =IF(BX12>0,BX12/BT11,0) -> 118.31059 | BZ12: =IF(BX12>0,BX12/BV12,0) -> #DIV/0!
A13: 8 | C13: =IF(+B13-B12>0,B13-B12,(B13-B12)>0)*800 -> 0 | E13: =IF(+D13-D12>0,D13-D12,(D13-D12)>0)*80 -> 0 | G13: =IF(+F13-F12>0,F13-F12,(F13-F12)>0)*10 -> 0 | I13: 23764384 | J13: =IF(I13>=I12,I13-I12,0) -> 5864 | K13: =M13+O13 -> 3590 | L13: 613655 | M13: =IF(L13>=L12,L13-L12,0) -> 2216 | N13: 534509 | O13: =IF(N13>=N12,N13-N12,0) -> 1374 | P13: 221325 | Q13: =IF(P13>=P12,P13-P12,0)*30 -> 510 | R13: 179055 | S13: =IF(R13>=R12,R13-R12,0) -> 142 | T13: 327202 | U13: =IF(T13>=T12,T13-T12,0) -> 265 | V13: 753310 | W13: =IF(V13>=V12,V13-V12,0)*0.53 -> 1401.32 | X13: 116925 | Y13: =IF(X13>=X12,X13-X12,0)*0.53 -> 257.58 | Z13: 134745 | AA13: =IF(Z13>=Z12,Z13-Z12,0)*0.53 -> 0 | AB13: 488293 | AC13: =IF(AB13>=AB12,AB13-AB12,0)*0.53 -> 0 | AD13: 656403 | AE13: =IF(AD13>=AD12,AD13-AD12,0)*0.53 -> 13.25 | AF13: 835090 | AG13: =IF(AF13>=AF12,AF13-AF12,0)*0.53 -> 12.72 | AH13: 974566 | AI13: =IF(AH13>=AH12,AH13-AH12,0)*0.53 -> 414.46 | AJ13: 657057 | AK13: =IF(AJ13>=AJ12,AJ13-AJ12,0)*0.53 -> 2071.24 | AL13: 486405 | AM13: =IF(AL13>=AL12,AL13-AL12,0)*0.53 -> 155.29 | AN13: =W13+Y13+AA13+AC13+AE13+AG13+AI13+AK13+AM13 -> 4325.86 | AO13: 7650156 | AP13: =IF(AO13>=AO12,AO13-AO12,0)*0.1125 -> 4.1625 | AQ13: 669972 | AR13: =IF(AQ13>=AQ12,AQ13-AQ12,0) -> 317 | AS13: 963055 | AT13: =IF(AS13>=AS12,AS13-AS12,0) -> 139 | AU13: 809468 | AV13: =IF(AU13>=AU12,AU13-AU12,0) -> 20 | AW13: 2608121 | AX13: =IF(AW13>=AW12,AW13-AW12,0) -> 590 | AY13: 229472 | AZ13: =IF(AY13>=AY12,AY13-AY12,0) -> 0 | BA13: 19199156 | BB13: =IF(BA13>=BA12,BA13-BA12,0) -> 4343 | BC13: 562227 | BD13: =IF(BC13>=BC12,BC13-BC12,0) -> 260 | BE13: 25513 | BF13: =IF(BE13>=BE12,BE13-BE12,0) -> 46 | BG13: 24008622 | BH13: =IF(BG13>=BG12,BG13-BG12,0)-(0.45*BN13)-(0.45*BP13)-BR13 -> 4850.5 | BI13: =AP13+AR13+AT13+AV13+AX13+AZ13+BB13+BD13+BF13+BH13 -> 10569.663 | BJ13: =BI13+AN13 -> 14895.522 | BK13: 1421955 | BL13: =IF(BK13>=BK12,BK13-BK12,0) -> 255 | BM13: 3916112 | BN13: =IF(BM13>=BM12,BM13-BM12,0) -> 900 | BO13: 410689 | BP13: =IF(BO13>=BO12,BO13-BO12,0) -> 130 | BQ13: 514834 | BR13: =IF(BQ13>=BQ12,BQ13-BQ12,0) -> 157 | BS13: =J13+Q13+AN13+BI13 -> 21269.522 | BT13: 238 | BU13: =IF(BS13>0,BS13/BT12,0) -> 91.285504 | BW13: =IF(BS13>0,BS13/BV13,0) -> #DIV/0! | BX13: =((BS13-Q13)*$BZ$1)+(Q13*$BR$1) -> 24689.451 | BY13: =IF(BX13>0,BX13/BT12,0) -> 105.96331 | BZ13: =IF(BX13>0,BX13/BV13,0) -> #DIV/0!
A14: 9 | C14: =IF(+B14-B13>0,B14-B13,(B14-B13)>0)*800 -> 0 | E14: =IF(+D14-D13>0,D14-D13,(D14-D13)>0)*80 -> 0 | G14: =IF(+F14-F13>0,F14-F13,(F14-F13)>0)*10 -> 0 | H14: 60 | I14: 23769967 | J14: =IF(I14>=I13,I14-I13,0) -> 5583 | K14: =M14+O14 -> 3778 | L14: 615991 | M14: =IF(L14>=L13,L14-L13,0) -> 2336 | N14: 535951 | O14: =IF(N14>=N13,N14-N13,0) -> 1442 | P14: 221341 | Q14: =IF(P14>=P13,P14-P13,0)*30 -> 480 | R14: 179192 | S14: =IF(R14>=R13,R14-R13,0) -> 137 | T14: 327455 | U14: =IF(T14>=T13,T14-T13,0) -> 253 | V14: 755520 | W14: =IF(V14>=V13,V14-V13,0)*0.53 -> 1171.3 | X14: 116925 | Y14: =IF(X14>=X13,X14-X13,0)*0.53 -> 0 | Z14: 134745 | AA14: =IF(Z14>=Z13,Z14-Z13,0)*0.53 -> 0 | AB14: 488293 | AC14: =IF(AB14>=AB13,AB14-AB13,0)*0.53 -> 0 | AD14: 656427 | AE14: =IF(AD14>=AD13,AD14-AD13,0)*0.53 -> 12.72 | AF14: 835114 | AG14: =IF(AF14>=AF13,AF14-AF13,0)*0.53 -> 12.72 | AH14: 975358 | AI14: =IF(AH14>=AH13,AH14-AH13,0)*0.53 -> 419.76 | AJ14: 661185 | AK14: =IF(AJ14>=AJ13,AJ14-AJ13,0)*0.53 -> 2187.84 | AL14: 486703 | AM14: =IF(AL14>=AL13,AL14-AL13,0)*0.53 -> 157.94 | AN14: =W14+Y14+AA14+AC14+AE14+AG14+AI14+AK14+AM14 -> 3962.28 | AO14: 7650193 | AP14: =IF(AO14>=AO13,AO14-AO13,0)*0.1125 -> 4.1625 | AQ14: 670294 | AR14: =IF(AQ14>=AQ13,AQ14-AQ13,0) -> 322 | AS14: 963201 | AT14: =IF(AS14>=AS13,AS14-AS13,0) -> 146 | AU14: 809496 | AV14: =IF(AU14>=AU13,AU14-AU13,0) -> 28 | AW14: 2608712 | AX14: =IF(AW14>=AW13,AW14-AW13,0) -> 591 | AY14: 229472 | AZ14: =IF(AY14>=AY13,AY14-AY13,0) -> 0 | BA14: 19203610 | BB14: =IF(BA14>=BA13,BA14-BA13,0) -> 4454 | BC14: 562467 | BD14: =IF(BC14>=BC13,BC14-BC13,0) -> 240 | BE14: 25559 | BF14: =IF(BE14>=BE13,BE14-BE13,0) -> 46 | BG14: 24013997 | BH14: =IF(BG14>=BG13,BG14-BG13,0)-(0.45*BN14)-(0.45*BP14)-BR14 -> 4768.05 | BI14: =AP14+AR14+AT14+AV14+AX14+AZ14+BB14+BD14+BF14+BH14 -> 10599.213 | BJ14: =BI14+AN14 -> 14561.493 | BK14: 1422205 | BL14: =IF(BK14>=BK13,BK14-BK13,0) -> 250 | BM14: 3916991 | BN14: =IF(BM14>=BM13,BM14-BM13,0) -> 879 | BO14: 410821 | BP14: =IF(BO14>=BO13,BO14-BO13,0) -> 132 | BQ14: 514986 | BR14: =IF(BQ14>=BQ13,BQ14-BQ13,0) -> 152 | BS14: =J14+Q14+AN14+BI14 -> 20624.493 | BT14: 220 | BU14: =IF(BS14>0,BS14/BT13,0) -> 86.657532 | BW14: =IF(BS14>0,BS14/BV14,0) -> #DIV/0! | BX14: =((BS14-Q14)*$BZ$1)+(Q14*$BR$1) -> 23934.166 | BY14: =IF(BX14>0,BX14/BT13,0) -> 100.56372 | BZ14: =IF(BX14>0,BX14/BV14,0) -> #DIV/0!
A15: 10 | C15: =IF(+B15-B14>0,B15-B14,(B15-B14)>0)*800 -> 0 | E15: =IF(+D15-D14>0,D15-D14,(D15-D14)>0)*80 -> 0 | G15: =IF(+F15-F14>0,F15-F14,(F15-F14)>0)*10 -> 0 | I15: 23777334 | J15: =IF(I15>=I14,I15-I14,0) -> 7367 | K15: =M15+O15 -> 4484 | L15: 618882 | M15: =IF(L15>=L14,L15-L14,0) -> 2891 | N15: 537544 | O15: =IF(N15>=N14,N15-N14,0) -> 1593 | P15: 221360 | Q15: =IF(P15>=P14,P15-P14,0)*30 -> 570 | R15: 179342 | S15: =IF(R15>=R14,R15-R14,0) -> 150 | T15: 327733 | U15: =IF(T15>=T14,T15-T14,0) -> 278 | V15: 757435 | W15: =IF(V15>=V14,V15-V14,0)*0.53 -> 1014.95 | X15: 116925 | Y15: =IF(X15>=X14,X15-X14,0)*0.53 -> 0 | Z15: 134745 | AA15: =IF(Z15>=Z14,Z15-Z14,0)*0.53 -> 0 | AB15: 488293 | AC15: =IF(AB15>=AB14,AB15-AB14,0)*0.53 -> 0 | AD15: 656454 | AE15: =IF(AD15>=AD14,AD15-AD14,0)*0.53 -> 14.31 | AF15: 835140 | AG15: =IF(AF15>=AF14,AF15-AF14,0)*0.53 -> 13.78 | AH15: 976233 | AI15: =IF(AH15>=AH14,AH15-AH14,0)*0.53 -> 463.75 | AJ15: 665695 | AK15: =IF(AJ15>=AJ14,AJ15-AJ14,0)*0.53 -> 2390.3 | AL15: 487030 | AM15: =IF(AL15>=AL14,AL15-AL14,0)*0.53 -> 173.31 | AN15: =W15+Y15+AA15+AC15+AE15+AG15+AI15+AK15+AM15 -> 4070.4 | AO15: 7650236 | AP15: =IF(AO15>=AO14,AO15-AO14,0)*0.1125 -> 4.8375 | AQ15: 670626 | AR15: =IF(AQ15>=AQ14,AQ15-AQ14,0) -> 332 | AS15: 963353 | AT15: =IF(AS15>=AS14,AS15-AS14,0) -> 152 | AU15: 809536 | AV15: =IF(AU15>=AU14,AU15-AU14,0) -> 40 | AW15: 2609337 | AX15: =IF(AW15>=AW14,AW15-AW14,0) -> 625 | AY15: 229472 | AZ15: =IF(AY15>=AY14,AY15-AY14,0) -> 0 | BA15: 19208094 | BB15: =IF(BA15>=BA14,BA15-BA14,0) -> 4484 | BC15: 562740 | BD15: =IF(BC15>=BC14,BC15-BC14,0) -> 273 | BE15: 25623 | BF15: =IF(BE15>=BE14,BE15-BE14,0) -> 64 | BG15: 24019668 | BH15: =IF(BG15>=BG14,BG15-BG14,0)-(0.45*BN15)-(0.45*BP15)-BR15 -> 5043.9 | BI15: =AP15+AR15+AT15+AV15+AX15+AZ15+BB15+BD15+BF15+BH15 -> 11018.737 | BJ15: =BI15+AN15 -> 15089.137 | BK15: 1422472 | BL15: =IF(BK15>=BK14,BK15-BK14,0) -> 267 | BM15: 3917909 | BN15: =IF(BM15>=BM14,BM15-BM14,0) -> 918 | BO15: 410961 | BP15: =IF(BO15>=BO14,BO15-BO14,0) -> 140 | BQ15: 515137 | BR15: =IF(BQ15>=BQ14,BQ15-BQ14,0) -> 151 | BS15: =J15+Q15+AN15+BI15 -> 23026.137 | BT15: 211 | BU15: =IF(BS15>0,BS15/BT14,0) -> 104.66426 | BW15: =IF(BS15>0,BS15/BV15,0) -> #DIV/0! | BX15: =((BS15-Q15)*$BZ$1)+(Q15*$BR$1) -> 26736.558 | BY15: =IF(BX15>0,BX15/BT14,0) -> 121.52981 | BZ15: =IF(BX15>0,BX15/BV15,0) -> #DIV/0!
A16: 11 | C16: =IF(+B16-B15>0,B16-B15,(B16-B15)>0)*800 -> 0 | E16: =IF(+D16-D15>0,D16-D15,(D16-D15)>0)*80 -> 0 | G16: =IF(+F16-F15>0,F16-F15,(F16-F15)>0)*10 -> 0 | H16: 61 | I16: 23783580 | J16: =IF(I16>=I15,I16-I15,0) -> 6246 | K16: =M16+O16 -> 3878 | L16: 621407 | M16: =IF(L16>=L15,L16-L15,0) -> 2525 | N16: 538897 | O16: =IF(N16>=N15,N16-N15,0) -> 1353 | P16: 221377 | Q16: =IF(P16>=P15,P16-P15,0)*30 -> 510 | R16: 179472 | S16: =IF(R16>=R15,R16-R15,0) -> 130 | T16: 327977 | U16: =IF(T16>=T15,T16-T15,0) -> 244 | V16: 759228 | W16: =IF(V16>=V15,V16-V15,0)*0.53 -> 950.29 | X16: 116925 | Y16: =IF(X16>=X15,X16-X15,0)*0.53 -> 0 | Z16: 134745 | AA16: =IF(Z16>=Z15,Z16-Z15,0)*0.53 -> 0 | AB16: 488293 | AC16: =IF(AB16>=AB15,AB16-AB15,0)*0.53 -> 0 | AD16: 656476 | AE16: =IF(AD16>=AD15,AD16-AD15,0)*0.53 -> 11.66 | AF16: 835162 | AG16: =IF(AF16>=AF15,AF16-AF15,0)*0.53 -> 11.66 | AH16: 976975 | AI16: =IF(AH16>=AH15,AH16-AH15,0)*0.53 -> 393.26 | AJ16: 669739 | AK16: =IF(AJ16>=AJ15,AJ16-AJ15,0)*0.53 -> 2143.32 | AL16: 487310 | AM16: =IF(AL16>=AL15,AL16-AL15,0)*0.53 -> 148.4 | AN16: =W16+Y16+AA16+AC16+AE16+AG16+AI16+AK16+AM16 -> 3658.59 | AO16: 7650275 | AP16: =IF(AO16>=AO15,AO16-AO15,0)*0.1125 -> 4.3875 | AQ16: 670950 | AR16: =IF(AQ16>=AQ15,AQ16-AQ15,0) -> 324 | AS16: 963486 | AT16: =IF(AS16>=AS15,AS16-AS15,0) -> 133 | AU16: 809563 | AV16: =IF(AU16>=AU15,AU16-AU15,0) -> 27 | AW16: 2609882 | AX16: =IF(AW16>=AW15,AW16-AW15,0) -> 545 | AY16: 229472 | AZ16: =IF(AY16>=AY15,AY16-AY15,0) -> 0 | BA16: 19212249 | BB16: =IF(BA16>=BA15,BA16-BA15,0) -> 4155 | BC16: 562982 | BD16: =IF(BC16>=BC15,BC16-BC15,0) -> 242 | BE16: 25677 | BF16: =IF(BE16>=BE15,BE16-BE15,0) -> 54 | BG16: 24024736 | BH16: =IF(BG16>=BG15,BG16-BG15,0)-(0.45*BN16)-(0.45*BP16)-BR16 -> 4507.9 | BI16: =AP16+AR16+AT16+AV16+AX16+AZ16+BB16+BD16+BF16+BH16 -> 9992.2875 | BJ16: =BI16+AN16 -> 13650.878 | BK16: 1422712 | BL16: =IF(BK16>=BK15,BK16-BK15,0) -> 240 | BM16: 3918720 | BN16: =IF(BM16>=BM15,BM16-BM15,0) -> 811 | BO16: 411088 | BP16: =IF(BO16>=BO15,BO16-BO15,0) -> 127 | BQ16: 515275 | BR16: =IF(BQ16>=BQ15,BQ16-BQ15,0) -> 138 | BS16: =J16+Q16+AN16+BI16 -> 20406.878 | BT16: 201 | BU16: =IF(BS16>0,BS16/BT15,0) -> 96.715059 | BW16: =IF(BS16>0,BS16/BV16,0) -> #DIV/0! | BX16: =((BS16-Q16)*$BZ$1)+(Q16*$BR$1) -> 23697.409 | BY16: =IF(BX16>0,BX16/BT15,0) -> 112.31 | BZ16: =IF(BX16>0,BX16/BV16,0) -> #DIV/0!
A17: 12 | C17: =IF(+B17-B16>0,B17-B16,(B17-B16)>0)*800 -> 0 | E17: =IF(+D17-D16>0,D17-D16,(D17-D16)>0)*80 -> 0 | G17: =IF(+F17-F16>0,F17-F16,(F17-F16)>0)*10 -> 0 | I17: 23790235 | J17: =IF(I17>=I16,I17-I16,0) -> 6655 | K17: =M17+O17 -> 4174 | L17: 624095 | M17: =IF(L17>=L16,L17-L16,0) -> 2688 | N17: 540383 | O17: =IF(N17>=N16,N17-N16,0) -> 1486 | P17: 221392 | Q17: =IF(P17>=P16,P17-P16,0)*30 -> 450 | R17: 179610 | S17: =IF(R17>=R16,R17-R16,0) -> 138 | T17: 328234 | U17: =IF(T17>=T16,T17-T16,0) -> 257 | V17: 761208 | W17: =IF(V17>=V16,V17-V16,0)*0.53 -> 1049.4 | X17: 116925 | Y17: =IF(X17>=X16,X17-X16,0)*0.53 -> 0 | Z17: 134745 | AA17: =IF(Z17>=Z16,Z17-Z16,0)*0.53 -> 0 | AB17: 488293 | AC17: =IF(AB17>=AB16,AB17-AB16,0)*0.53 -> 0 | AD17: 656500 | AE17: =IF(AD17>=AD16,AD17-AD16,0)*0.53 -> 12.72 | AF17: 835186 | AG17: =IF(AF17>=AF16,AF17-AF16,0)*0.53 -> 12.72 | AH17: 977803 | AI17: =IF(AH17>=AH16,AH17-AH16,0)*0.53 -> 438.84 | AJ17: 674193 | AK17: =IF(AJ17>=AJ16,AJ17-AJ16,0)*0.53 -> 2360.62 | AL17: 487616 | AM17: =IF(AL17>=AL16,AL17-AL16,0)*0.53 -> 162.18 | AN17: =W17+Y17+AA17+AC17+AE17+AG17+AI17+AK17+AM17 -> 4036.48 | AO17: 7650312 | AP17: =IF(AO17>=AO16,AO17-AO16,0)*0.1125 -> 4.1625 | AQ17: 671277 | AR17: =IF(AQ17>=AQ16,AQ17-AQ16,0) -> 327 | AS17: 963622 | AT17: =IF(AS17>=AS16,AS17-AS16,0) -> 136 | AU17: 809584 | AV17: =IF(AU17>=AU16,AU17-AU16,0) -> 21 | AW17: 2610471 | AX17: =IF(AW17>=AW16,AW17-AW16,0) -> 589 | AY17: 229472 | AZ17: =IF(AY17>=AY16,AY17-AY16,0) -> 0 | BA17: 19216786 | BB17: =IF(BA17>=BA16,BA17-BA16,0) -> 4537 | BC17: 563219 | BD17: =IF(BC17>=BC16,BC17-BC16,0) -> 237 | BE17: 25733 | BF17: =IF(BE17>=BE16,BE17-BE16,0) -> 56 | BG17: 24030118 | BH17: =IF(BG17>=BG16,BG17-BG16,0)-(0.45*BN17)-(0.45*BP17)-BR17 -> 4786.25 | BI17: =AP17+AR17+AT17+AV17+AX17+AZ17+BB17+BD17+BF17+BH17 -> 10693.413 | BJ17: =BI17+AN17 -> 14729.893 | BK17: 1422967 | BL17: =IF(BK17>=BK16,BK17-BK16,0) -> 255 | BM17: 3919599 | BN17: =IF(BM17>=BM16,BM17-BM16,0) -> 879 | BO17: 411224 | BP17: =IF(BO17>=BO16,BO17-BO16,0) -> 136 | BQ17: 515414 | BR17: =IF(BQ17>=BQ16,BQ17-BQ16,0) -> 139 | BS17: =J17+Q17+AN17+BI17 -> 21834.893 | BT17: 179 | BU17: =IF(BS17>0,BS17/BT16,0) -> 108.63131 | BW17: =IF(BS17>0,BS17/BV17,0) -> #DIV/0! | BX17: =((BS17-Q17)*$BZ$1)+(Q17*$BR$1) -> 25312.626 | BY17: =IF(BX17>0,BX17/BT16,0) -> 125.93346 | BZ17: =IF(BX17>0,BX17/BV17,0) -> #DIV/0!
A18: 13 | C18: =IF(+B18-B17>0,B18-B17,(B18-B17)>0)*800 -> 0 | E18: =IF(+D18-D17>0,D18-D17,(D18-D17)>0)*80 -> 0 | G18: =IF(+F18-F17>0,F18-F17,(F18-F17)>0)*10 -> 0 | H18: 62 | I18: 23796894 | J18: =IF(I18>=I17,I18-I17,0) -> 6659 | K18: =M18+O18 -> 4184 | L18: 626789 | M18: =IF(L18>=L17,L18-L17,0) -> 2694 | N18: 541873 | O18: =IF(N18>=N17,N18-N17,0) -> 1490 | P18: 221410 | Q18: =IF(P18>=P17,P18-P17,0)*30 -> 540 | R18: 179749 | S18: =IF(R18>=R17,R18-R17,0) -> 139 | T18: 328485 | U18: =IF(T18>=T17,T18-T17,0) -> 251 | V18: 763194 | W18: =IF(V18>=V17,V18-V17,0)*0.53 -> 1052.58 | X18: 116925 | Y18: =IF(X18>=X17,X18-X17,0)*0.53 -> 0 | Z18: 134745 | AA18: =IF(Z18>=Z17,Z18-Z17,0)*0.53 -> 0 | AB18: 488293 | AC18: =IF(AB18>=AB17,AB18-AB17,0)*0.53 -> 0 | AD18: 656526 | AE18: =IF(AD18>=AD17,AD18-AD17,0)*0.53 -> 13.78 | AF18: 835211 | AG18: =IF(AF18>=AF17,AF18-AF17,0)*0.53 -> 13.25 | AH18: 978640 | AI18: =IF(AH18>=AH17,AH18-AH17,0)*0.53 -> 443.61 | AJ18: 678656 | AK18: =IF(AJ18>=AJ17,AJ18-AJ17,0)*0.53 -> 2365.39 | AL18: 487925 | AM18: =IF(AL18>=AL17,AL18-AL17,0)*0.53 -> 163.77 | AN18: =W18+Y18+AA18+AC18+AE18+AG18+AI18+AK18+AM18 -> 4052.38 | AO18: 7650355 | AP18: =IF(AO18>=AO17,AO18-AO17,0)*0.1125 -> 4.8375 | AQ18: 671597 | AR18: =IF(AQ18>=AQ17,AQ18-AQ17,0) -> 320 | AS18: 963761 | AT18: =IF(AS18>=AS17,AS18-AS17,0) -> 139 | AU18: 809607 | AV18: =IF(AU18>=AU17,AU18-AU17,0) -> 23 | AW18: 2611056 | AX18: =IF(AW18>=AW17,AW18-AW17,0) -> 585 | AY18: 229472 | AZ18: =IF(AY18>=AY17,AY18-AY17,0) -> 0 | BA18: 19221621 | BB18: =IF(BA18>=BA17,BA18-BA17,0) -> 4835 | BC18: 563452 | BD18: =IF(BC18>=BC17,BC18-BC17,0) -> 233 | BE18: 25784 | BF18: =IF(BE18>=BE17,BE18-BE17,0) -> 51 | BG18: 24035857 | BH18: =IF(BG18>=BG17,BG18-BG17,0)-(0.45*BN18)-(0.45*BP18)-BR18 -> 5120.15 | BI18: =AP18+AR18+AT18+AV18+AX18+AZ18+BB18+BD18+BF18+BH18 -> 11310.987 | BJ18: =BI18+AN18 -> 15363.368 | BK18: 1423232 | BL18: =IF(BK18>=BK17,BK18-BK17,0) -> 265 | BM18: 3920511 | BN18: =IF(BM18>=BM17,BM18-BM17,0) -> 912 | BO18: 411365 | BP18: =IF(BO18>=BO17,BO18-BO17,0) -> 141 | BQ18: 515559 | BR18: =IF(BQ18>=BQ17,BQ18-BQ17,0) -> 145 | BS18: =J18+Q18+AN18+BI18 -> 22562.368 | BT18: 207 | BU18: =IF(BS18>0,BS18/BT17,0) -> 126.04675 | BW18: =IF(BS18>0,BS18/BV18,0) -> #DIV/0! | BX18: =((BS18-Q18)*$BZ$1)+(Q18*$BR$1) -> 26189.723 | BY18: =IF(BX18>0,BX18/BT17,0) -> 146.3113 | BZ18: =IF(BX18>0,BX18/BV18,0) -> #DIV/0!
A19: 14 | C19: =IF(+B19-B18>0,B19-B18,(B19-B18)>0)*800 -> 0 | E19: =IF(+D19-D18>0,D19-D18,(D19-D18)>0)*80 -> 0 | G19: =IF(+F19-F18>0,F19-F18,(F19-F18)>0)*10 -> 0 | I19: 23803960 | J19: =IF(I19>=I18,I19-I18,0) -> 7066 | K19: =M19+O19 -> 4000 | L19: 629289 | M19: =IF(L19>=L18,L19-L18,0) -> 2500 | N19: 543373 | O19: =IF(N19>=N18,N19-N18,0) -> 1500 | P19: 221428 | Q19: =IF(P19>=P18,P19-P18,0)*30 -> 540 | R19: 179889 | S19: =IF(R19>=R18,R19-R18,0) -> 140 | T19: 328746 | U19: =IF(T19>=T18,T19-T18,0) -> 261 | V19: 765094 | W19: =IF(V19>=V18,V19-V18,0)*0.53 -> 1007 | X19: 116925 | Y19: =IF(X19>=X18,X19-X18,0)*0.53 -> 0 | Z19: 134745 | AA19: =IF(Z19>=Z18,Z19-Z18,0)*0.53 -> 0 | AB19: 488293 | AC19: =IF(AB19>=AB18,AB19-AB18,0)*0.53 -> 0 | AD19: 656549 | AE19: =IF(AD19>=AD18,AD19-AD18,0)*0.53 -> 12.19 | AF19: 835235 | AG19: =IF(AF19>=AF18,AF19-AF18,0)*0.53 -> 12.72 | AH19: 979470 | AI19: =IF(AH19>=AH18,AH19-AH18,0)*0.53 -> 439.9 | AJ19: 683117 | AK19: =IF(AJ19>=AJ18,AJ19-AJ18,0)*0.53 -> 2364.33 | AL19: 488230 | AM19: =IF(AL19>=AL18,AL19-AL18,0)*0.53 -> 161.65 | AN19: =W19+Y19+AA19+AC19+AE19+AG19+AI19+AK19+AM19 -> 3997.79 | AO19: 7650395 | AP19: =IF(AO19>=AO18,AO19-AO18,0)*0.1125 -> 4.5 | AQ19: 671926 | AR19: =IF(AQ19>=AQ18,AQ19-AQ18,0) -> 329 | AS19: 963895 | AT19: =IF(AS19>=AS18,AS19-AS18,0) -> 134 | AU19: 809612 | AV19: =IF(AU19>=AU18,AU19-AU18,0) -> 5 | AW19: 2611056 | AX19: =IF(AW19>=AW18,AW19-AW18,0) -> 0 | AY19: 229472 | AZ19: =IF(AY19>=AY18,AY19-AY18,0) -> 0 | BA19: 19225863 | BB19: =IF(BA19>=BA18,BA19-BA18,0) -> 4242 | BC19: 563665 | BD19: =IF(BC19>=BC18,BC19-BC18,0) -> 213 | BE19: 25839 | BF19: =IF(BE19>=BE18,BE19-BE18,0) -> 55 | BG19: 24040797 | BH19: =IF(BG19>=BG18,BG19-BG18,0)-(0.45*BN19)-(0.45*BP19)-BR19 -> 4480.7 | BI19: =AP19+AR19+AT19+AV19+AX19+AZ19+BB19+BD19+BF19+BH19 -> 9463.2 | BJ19: =BI19+AN19 -> 13460.99 | BK19: 1423474 | BL19: =IF(BK19>=BK18,BK19-BK18,0) -> 242 | BM19: 3921117 | BN19: =IF(BM19>=BM18,BM19-BM18,0) -> 606 | BO19: 411493 | BP19: =IF(BO19>=BO18,BO19-BO18,0) -> 128 | BQ19: 515688 | BR19: =IF(BQ19>=BQ18,BQ19-BQ18,0) -> 129 | BS19: =J19+Q19+AN19+BI19 -> 21066.99 | BT19: 215 | BU19: =IF(BS19>0,BS19/BT18,0) -> 101.7729 | BW19: =IF(BS19>0,BS19/BV19,0) -> #DIV/0! | BX19: =((BS19-Q19)*$BZ$1)+(Q19*$BR$1) -> 24470.038 | BY19: =IF(BX19>0,BX19/BT18,0) -> 118.21275 | BZ19: =IF(BX19>0,BX19/BV19,0) -> #DIV/0!
A20: 15 | C20: =IF(+B20-B19>0,B20-B19,(B20-B19)>0)*800 -> 0 | E20: =IF(+D20-D19>0,D20-D19,(D20-D19)>0)*80 -> 0 | G20: =IF(+F20-F19>0,F20-F19,(F20-F19)>0)*10 -> 0 | H20: 63 | I20: 23810471 | J20: =IF(I20>=I19,I20-I19,0) -> 6511 | K20: =M20+O20 -> 4004 | L20: 631790 | M20: =IF(L20>=L19,L20-L19,0) -> 2501 | N20: 544876 | O20: =IF(N20>=N19,N20-N19,0) -> 1503 | P20: 221446 | Q20: =IF(P20>=P19,P20-P19,0)*30 -> 540 | R20: 180030 | S20: =IF(R20>=R19,R20-R19,0) -> 141 | T20: 329006 | U20: =IF(T20>=T19,T20-T19,0) -> 260 | V20: 766995 | W20: =IF(V20>=V19,V20-V19,0)*0.53 -> 1007.53 | X20: 116925 | Y20: =IF(X20>=X19,X20-X19,0)*0.53 -> 0 | Z20: 134745 | AA20: =IF(Z20>=Z19,Z20-Z19,0)*0.53 -> 0 | AB20: 488293 | AC20: =IF(AB20>=AB19,AB20-AB19,0)*0.53 -> 0 | AD20: 656575 | AE20: =IF(AD20>=AD19,AD20-AD19,0)*0.53 -> 13.78 | AF20: 835260 | AG20: =IF(AF20>=AF19,AF20-AF19,0)*0.53 -> 13.25 | AH20: 980299 | AI20: =IF(AH20>=AH19,AH20-AH19,0)*0.53 -> 439.37 | AJ20: 687573 | AK20: =IF(AJ20>=AJ19,AJ20-AJ19,0)*0.53 -> 2361.68 | AL20: 488537 | AM20: =IF(AL20>=AL19,AL20-AL19,0)*0.53 -> 162.71 | AN20: =W20+Y20+AA20+AC20+AE20+AG20+AI20+AK20+AM20 -> 3998.32 | AO20: 7650432 | AP20: =IF(AO20>=AO19,AO20-AO19,0)*0.1125 -> 4.1625 | AQ20: 672254 | AR20: =IF(AQ20>=AQ19,AQ20-AQ19,0) -> 328 | AS20: 964031 | AT20: =IF(AS20>=AS19,AS20-AS19,0) -> 136 | AU20: 809628 | AV20: =IF(AU20>=AU19,AU20-AU19,0) -> 16 | AW20: 2611646 | AX20: =IF(AW20>=AW19,AW20-AW19,0) -> 590 | AY20: 229472 | AZ20: =IF(AY20>=AY19,AY20-AY19,0) -> 0 | BA20: 19230454 | BB20: =IF(BA20>=BA19,BA20-BA19,0) -> 4591 | BC20: 563881 | BD20: =IF(BC20>=BC19,BC20-BC19,0) -> 216 | BE20: 25894 | BF20: =IF(BE20>=BE19,BE20-BE19,0) -> 55 | BG20: 24045965 | BH20: =IF(BG20>=BG19,BG20-BG19,0)-(0.45*BN20)-(0.45*BP20)-BR20 -> 4694.75 | BI20: =AP20+AR20+AT20+AV20+AX20+AZ20+BB20+BD20+BF20+BH20 -> 10630.913 | BJ20: =BI20+AN20 -> 14629.233 | BK20: 1423730 | BL20: =IF(BK20>=BK19,BK20-BK19,0) -> 256 | BM20: 3921723 | BN20: =IF(BM20>=BM19,BM20-BM19,0) -> 606 | BO20: 411632 | BP20: =IF(BO20>=BO19,BO20-BO19,0) -> 139 | BQ20: 515826 | BR20: =IF(BQ20>=BQ19,BQ20-BQ19,0) -> 138 | BS20: =J20+Q20+AN20+BI20 -> 21680.232 | BT20: 197 | BU20: =IF(BS20>0,BS20/BT20,0) -> 110.05194 | BW20: =IF(BS20>0,BS20/BV20,0) -> #DIV/0! | BX20: =((BS20-Q20)*$BZ$1)+(Q20*$BR$1) -> 25175.267 | BY20: =IF(BX20>0,BX20/BT20,0) -> 127.79324 | BZ20: =IF(BX20>0,BX20/BV20,0) -> #DIV/0!
A21: 16 | C21: =IF(+B21-B20>0,B21-B20,(B21-B20)>0)*800 -> 0 | E21: =IF(+D21-D20>0,D21-D20,(D21-D20)>0)*80 -> 0 | G21: =IF(+F21-F20>0,F21-F20,(F21-F20)>0)*10 -> 0 | I21: 23818488 | J21: =IF(I21>=I20,I21-I20,0) -> 8017 | K21: =M21+O21 -> 5075 | L21: 635323 | M21: =IF(L21>=L20,L21-L20,0) -> 3533 | N21: 546418 | O21: =IF(N21>=N20,N21-N20,0) -> 1542 | P21: 221463 | Q21: =IF(P21>=P20,P21-P20,0)*30 -> 510 | R21: 180177 | S21: =IF(R21>=R20,R21-R20,0) -> 147 | T21: 329273 | U21: =IF(T21>=T20,T21-T20,0) -> 267 | V21: 768349 | W21: =IF(V21>=V20,V21-V20,0)*0.53 -> 717.62 | X21: 118791 | Y21: =IF(X21>=X20,X21-X20,0)*0.53 -> 988.98 | Z21: 134745 | AA21: =IF(Z21>=Z20,Z21-Z20,0)*0.53 -> 0 | AB21: 488293 | AC21: =IF(AB21>=AB20,AB21-AB20,0)*0.53 -> 0 | AD21: 656608 | AE21: =IF(AD21>=AD20,AD21-AD20,0)*0.53 -> 17.49 | AF21: 835284 | AG21: =IF(AF21>=AF20,AF21-AF20,0)*0.53 -> 12.72 | AH21: 981107 | AI21: =IF(AH21>=AH20,AH21-AH20,0)*0.53 -> 428.24 | AJ21: 691599 | AK21: =IF(AJ21>=AJ20,AJ21-AJ20,0)*0.53 -> 2133.78 | AL21: 488805 | AM21: =IF(AL21>=AL20,AL21-AL20,0)*0.53 -> 142.04 | AN21: =W21+Y21+AA21+AC21+AE21+AG21+AI21+AK21+AM21 -> 4440.87 | AO21: 7650487 | AP21: =IF(AO21>=AO20,AO21-AO20,0)*0.1125 -> 6.1875 | AQ21: 672619 | AR21: =IF(AQ21>=AQ20,AQ21-AQ20,0) -> 365 | AS21: 964168 | AT21: =IF(AS21>=AS20,AS21-AS20,0) -> 137 | AU21: 809666 | AV21: =IF(AU21>=AU20,AU21-AU20,0) -> 38 | AW21: 2612641 | AX21: =IF(AW21>=AW20,AW21-AW20,0) -> 995 | AY21: 229472 | AZ21: =IF(AY21>=AY20,AY21-AY20,0) -> 0 | BA21: 19234813 | BB21: =IF(BA21>=BA20,BA21-BA20,0) -> 4359 | BC21: 564098 | BD21: =IF(BC21>=BC20,BC21-BC20,0) -> 217 | BE21: 25946 | BF21: =IF(BE21>=BE20,BE21-BE20,0) -> 52 | BG21: 24051230 | BH21: =IF(BG21>=BG20,BG21-BG20,0)-(0.45*BN21)-(0.45*BP21)-BR21 -> 4717.6 | BI21: =AP21+AR21+AT21+AV21+AX21+AZ21+BB21+BD21+BF21+BH21 -> 10886.788 | BJ21: =BI21+AN21 -> 15327.658 | BK21: 1423986 | BL21: =IF(BK21>=BK20,BK21-BK20,0) -> 256 | BM21: 3922498 | BN21: =IF(BM21>=BM20,BM21-BM20,0) -> 775 | BO21: 411769 | BP21: =IF(BO21>=BO20,BO21-BO20,0) -> 137 | BQ21: 515963 | BR21: =IF(BQ21>=BQ20,BQ21-BQ20,0) -> 137 | BS21: =J21+Q21+AN21+BI21 -> 23854.658 | BT21: 176 | BU21: =IF(BS21>0,BS21/BT21,0) -> 135.53783 | BW21: =IF(BS21>0,BS21/BV21,0) -> #DIV/0! | BX21: =((BS21-Q21)*$BZ$1)+(Q21*$BR$1) -> 27662.356 | BY21: =IF(BX21>0,BX21/BT21,0) -> 157.17248 | BZ21: =IF(BX21>0,BX21/BV21,0) -> #DIV/0!
A22: 17 | C22: =IF(+B22-B21>0,B22-B21,(B22-B21)>0)*800 -> 0 | E22: =IF(+D22-D21>0,D22-D21,(D22-D21)>0)*80 -> 0 | G22: =IF(+F22-F21>0,F22-F21,(F22-F21)>0)*10 -> 0 | H22: 64 | I22: 23826210 | J22: =IF(I22>=I21,I22-I21,0) -> 7722 | K22: =M22+O22 -> 4612 | L22: 638423 | M22: =IF(L22>=L21,L22-L21,0) -> 3100 | N22: 547930 | O22: =IF(N22>=N21,N22-N21,0) -> 1512 | P22: 221481 | Q22: =IF(P22>=P21,P22-P21,0)*30 -> 540 | R22: 180321 | S22: =IF(R22>=R21,R22-R21,0) -> 144 | T22: 329534 | U22: =IF(T22>=T21,T22-T21,0) -> 261 | V22: 768797 | W22: =IF(V22>=V21,V22-V21,0)*0.53 -> 237.44 | X22: 120681 | Y22: =IF(X22>=X21,X22-X21,0)*0.53 -> 1001.7 | Z22: 134745 | AA22: =IF(Z22>=Z21,Z22-Z21,0)*0.53 -> 0 | AB22: 488293 | AC22: =IF(AB22>=AB21,AB22-AB21,0)*0.53 -> 0 | AD22: 656631 | AE22: =IF(AD22>=AD21,AD22-AD21,0)*0.53 -> 12.19 | AF22: 835308 | AG22: =IF(AF22>=AF21,AF22-AF21,0)*0.53 -> 12.72 | AH22: 981640 | AI22: =IF(AH22>=AH21,AH22-AH21,0)*0.53 -> 282.49 | AJ22: 696000 | AK22: =IF(AJ22>=AJ21,AJ22-AJ21,0)*0.53 -> 2332.53 | AL22: 489110 | AM22: =IF(AL22>=AL21,AL22-AL21,0)*0.53 -> 161.65 | AN22: =W22+Y22+AA22+AC22+AE22+AG22+AI22+AK22+AM22 -> 4040.72 | AO22: 7650528 | AP22: =IF(AO22>=AO21,AO22-AO21,0)*0.1125 -> 4.6125 | AQ22: 672947 | AR22: =IF(AQ22>=AQ21,AQ22-AQ21,0) -> 328 | AS22: 964305 | AT22: =IF(AS22>=AS21,AS22-AS21,0) -> 137 | AU22: 809687 | AV22: =IF(AU22>=AU21,AU22-AU21,0) -> 21 | AW22: 2613227 | AX22: =IF(AW22>=AW21,AW22-AW21,0) -> 586 | AY22: 229472 | AZ22: =IF(AY22>=AY21,AY22-AY21,0) -> 0 | BA22: 19239200 | BB22: =IF(BA22>=BA21,BA22-BA21,0) -> 4387 | BC22: 564299 | BD22: =IF(BC22>=BC21,BC22-BC21,0) -> 201 | BE22: 26000 | BF22: =IF(BE22>=BE21,BE22-BE21,0) -> 54 | BG22: 24056619 | BH22: =IF(BG22>=BG21,BG22-BG21,0)-(0.45*BN22)-(0.45*BP22)-BR22 -> 4820.05 | BI22: =AP22+AR22+AT22+AV22+AX22+AZ22+BB22+BD22+BF22+BH22 -> 10538.663 | BJ22: =BI22+AN22 -> 14579.383 | BK22: 1424240 | BL22: =IF(BK22>=BK21,BK22-BK21,0) -> 254 | BM22: 3923313 | BN22: =IF(BM22>=BM21,BM22-BM21,0) -> 815 | BO22: 411905 | BP22: =IF(BO22>=BO21,BO22-BO21,0) -> 136 | BQ22: 516104 | BR22: =IF(BQ22>=BQ21,BQ22-BQ21,0) -> 141 | BS22: =J22+Q22+AN22+BI22 -> 22841.382 | BT22: 171 | BU22: =IF(BS22>0,BS22/BT22,0) -> 133.57534 | BW22: =IF(BS22>0,BS22/BV22,0) -> #DIV/0! | BX22: =((BS22-Q22)*$BZ$1)+(Q22*$BR$1) -> 26510.59 | BY22: =IF(BX22>0,BX22/BT22,0) -> 155.03269 | BZ22: =IF(BX22>0,BX22/BV22,0) -> #DIV/0!
A23: 18 | C23: =IF(+B23-B22>0,B23-B22,(B23-B22)>0)*800 -> 0 | E23: =IF(+D23-D22>0,D23-D22,(D23-D22)>0)*80 -> 0 | G23: =IF(+F23-F22>0,F23-F22,(F23-F22)>0)*10 -> 0 | I23: 23834022 | J23: =IF(I23>=I22,I23-I22,0) -> 7812 | K23: =M23+O23 -> 4634 | L23: 641640 | M23: =IF(L23>=L22,L23-L22,0) -> 3217 | N23: 549347 | O23: =IF(N23>=N22,N23-N22,0) -> 1417 | P23: 221496 | Q23: =IF(P23>=P22,P23-P22,0)*30 -> 450 | R23: 180464 | S23: =IF(R23>=R22,R23-R22,0) -> 143 | T23: 329796 | U23: =IF(T23>=T22,T23-T22,0) -> 262 | V23: 770526 | W23: =IF(V23>=V22,V23-V22,0)*0.53 -> 916.37 | X23: 120681 | Y23: =IF(X23>=X22,X23-X22,0)*0.53 -> 0 | Z23: 134745 | AA23: =IF(Z23>=Z22,Z23-Z22,0)*0.53 -> 0 | AB23: 488293 | AC23: =IF(AB23>=AB22,AB23-AB22,0)*0.53 -> 0 | AD23: 656656 | AE23: =IF(AD23>=AD22,AD23-AD22,0)*0.53 -> 13.25 | AF23: 835335 | AG23: =IF(AF23>=AF22,AF23-AF22,0)*0.53 -> 14.31 | AH23: 982459 | AI23: =IF(AH23>=AH22,AH23-AH22,0)*0.53 -> 434.07 | AJ23: 700715 | AK23: =IF(AJ23>=AJ22,AJ23-AJ22,0)*0.53 -> 2498.95 | AL23: 489419 | AM23: =IF(AL23>=AL22,AL23-AL22,0)*0.53 -> 163.77 | AN23: =W23+Y23+AA23+AC23+AE23+AG23+AI23+AK23+AM23 -> 4040.72 | AO23: 7650568 | AP23: =IF(AO23>=AO22,AO23-AO22,0)*0.1125 -> 4.5 | AQ23: 673276 | AR23: =IF(AQ23>=AQ22,AQ23-AQ22,0) -> 329 | AS23: 964438 | AT23: =IF(AS23>=AS22,AS23-AS22,0) -> 133 | AU23: 809720 | AV23: =IF(AU23>=AU22,AU23-AU22,0) -> 33 | AW23: 2613801 | AX23: =IF(AW23>=AW22,AW23-AW22,0) -> 574 | AY23: 229472 | AZ23: =IF(AY23>=AY22,AY23-AY22,0) -> 0 | BA23: 19243573 | BB23: =IF(BA23>=BA22,BA23-BA22,0) -> 4373 | BC23: 564543 | BD23: =IF(BC23>=BC22,BC23-BC22,0) -> 244 | BE23: 26053 | BF23: =IF(BE23>=BE22,BE23-BE22,0) -> 53 | BG23: 24062243 | BH23: =IF(BG23>=BG22,BG23-BG22,0)-(0.45*BN23)-(0.45*BP23)-BR23 -> 5039.5 | BI23: =AP23+AR23+AT23+AV23+AX23+AZ23+BB23+BD23+BF23+BH23 -> 10783 | BJ23: =BI23+AN23 -> 14823.72 | BK23: 1424510 | BL23: =IF(BK23>=BK22,BK23-BK22,0) -> 270 | BM23: 3924140 | BN23: =IF(BM23>=BM22,BM23-BM22,0) -> 827 | BO23: 412048 | BP23: =IF(BO23>=BO22,BO23-BO22,0) -> 143 | BQ23: 516252 | BR23: =IF(BQ23>=BQ22,BQ23-BQ22,0) -> 148 | BS23: =J23+Q23+AN23+BI23 -> 23085.72 | BT23: 146 | BU23: =IF(BS23>0,BS23/BT23,0) -> 158.12137 | BW23: =IF(BS23>0,BS23/BV23,0) -> #DIV/0! | BX23: =((BS23-Q23)*$BZ$1)+(Q23*$BR$1) -> 26751.078 | BY23: =IF(BX23>0,BX23/BT23,0) -> 183.22656 | BZ23: =IF(BX23>0,BX23/BV23,0) -> #DIV/0!
A24: 19 | C24: =IF(+B24-B23>0,B24-B23,(B24-B23)>0)*800 -> 0 | E24: =IF(+D24-D23>0,D24-D23,(D24-D23)>0)*80 -> 0 | G24: =IF(+F24-F23>0,F24-F23,(F24-F23)>0)*10 -> 0 | H24: 65 | I24: 23842127 | J24: =IF(I24>=I23,I24-I23,0) -> 8105 | K24: =M24+O24 -> 4736 | L24: 645005 | M24: =IF(L24>=L23,L24-L23,0) -> 3365 | N24: 550718 | O24: =IF(N24>=N23,N24-N23,0) -> 1371 | P24: 221514 | Q24: =IF(P24>=P23,P24-P23,0)*30 -> 540 | R24: 180490 | S24: =IF(R24>=R23,R24-R23,0) -> 26 | T24: 330060 | U24: =IF(T24>=T23,T24-T23,0) -> 264 | V24: 771952 | W24: =IF(V24>=V23,V24-V23,0)*0.53 -> 755.78 | X24: 120681 | Y24: =IF(X24>=X23,X24-X23,0)*0.53 -> 0 | Z24: 134745 | AA24: =IF(Z24>=Z23,Z24-Z23,0)*0.53 -> 0 | AB24: 488293 | AC24: =IF(AB24>=AB23,AB24-AB23,0)*0.53 -> 0 | AD24: 656681 | AE24: =IF(AD24>=AD23,AD24-AD23,0)*0.53 -> 13.25 | AF24: 835357 | AG24: =IF(AF24>=AF23,AF24-AF23,0)*0.53 -> 11.66 | AH24: 983270 | AI24: =IF(AH24>=AH23,AH24-AH23,0)*0.53 -> 429.83 | AJ24: 704839 | AK24: =IF(AJ24>=AJ23,AJ24-AJ23,0)*0.53 -> 2185.72 | AL24: 489690 | AM24: =IF(AL24>=AL23,AL24-AL23,0)*0.53 -> 143.63 | AN24: =W24+Y24+AA24+AC24+AE24+AG24+AI24+AK24+AM24 -> 3539.87 | AO24: 7650607 | AP24: =IF(AO24>=AO23,AO24-AO23,0)*0.1125 -> 4.3875 | AQ24: 673602 | AR24: =IF(AQ24>=AQ23,AQ24-AQ23,0) -> 326 | AS24: 964572 | AT24: =IF(AS24>=AS23,AS24-AS23,0) -> 134 | AU24: 809758 | AV24: =IF(AU24>=AU23,AU24-AU23,0) -> 38 | AW24: 2614351 | AX24: =IF(AW24>=AW23,AW24-AW23,0) -> 550 | AY24: 229472 | AZ24: =IF(AY24>=AY23,AY24-AY23,0) -> 0 | BA24: 19247346 | BB24: =IF(BA24>=BA23,BA24-BA23,0) -> 3773 | BC24: 564758 | BD24: =IF(BC24>=BC23,BC24-BC23,0) -> 215 | BE24: 26106 | BF24: =IF(BE24>=BE23,BE24-BE23,0) -> 53 | BG24: 24067140 | BH24: =IF(BG24>=BG23,BG24-BG23,0)-(0.45*BN24)-(0.45*BP24)-BR24 -> 4404.95 | BI24: =AP24+AR24+AT24+AV24+AX24+AZ24+BB24+BD24+BF24+BH24 -> 9498.3375 | BJ24: =BI24+AN24 -> 13038.208 | BK24: 1424709 | BL24: =IF(BK24>=BK23,BK24-BK23,0) -> 199 | BM24: 3924822 | BN24: =IF(BM24>=BM23,BM24-BM23,0) -> 682 | BO24: 412175 | BP24: =IF(BO24>=BO23,BO24-BO23,0) -> 127 | BQ24: 516380 | BR24: =IF(BQ24>=BQ23,BQ24-BQ23,0) -> 128 | BS24: =J24+Q24+AN24+BI24 -> 21683.208 | BT24: 162 | BU24: =IF(BS24>0,BS24/BT24,0) -> 133.84696 | BW24: =IF(BS24>0,BS24/BV24,0) -> #DIV/0! | BX24: =((BS24-Q24)*$BZ$1)+(Q24*$BR$1) -> 25178.689 | BY24: =IF(BX24>0,BX24/BT24,0) -> 155.424 | BZ24: =IF(BX24>0,BX24/BV24,0) -> #DIV/0!
A25: 20 | C25: =IF(+B25-B24>0,B25-B24,(B25-B24)>0)*800 -> 0 | E25: =IF(+D25-D24>0,D25-D24,(D25-D24)>0)*80 -> 0 | G25: =IF(+F25-F24>0,F25-F24,(F25-F24)>0)*10 -> 0 | I25: 23850048 | J25: =IF(I25>=I24,I25-I24,0) -> 7921 | K25: =M25+O25 -> 4765 | L25: 648318 | M25: =IF(L25>=L24,L25-L24,0) -> 3313 | N25: 552170 | O25: =IF(N25>=N24,N25-N24,0) -> 1452 | P25: 221532 | Q25: =IF(P25>=P24,P25-P24,0)*30 -> 540 | R25: 180741 | S25: =IF(R25>=R24,R25-R24,0) -> 251 | T25: 330321.86 | U25: =IF(T25>=T24,T25-T24,0) -> 261.85714 | V25: 773847 | W25: =IF(V25>=V24,V25-V24,0)*0.53 -> 1004.35 | X25: 120681 | Y25: =IF(X25>=X24,X25-X24,0)*0.53 -> 0 | Z25: 134745 | AA25: =IF(Z25>=Z24,Z25-Z24,0)*0.53 -> 0 | AB25: 488293 | AC25: =IF(AB25>=AB24,AB25-AB24,0)*0.53 -> 0 | AD25: 656711 | AE25: =IF(AD25>=AD24,AD25-AD24,0)*0.53 -> 15.9 | AF25: 835383 | AG25: =IF(AF25>=AF24,AF25-AF24,0)*0.53 -> 13.78 | AH25: 983769 | AI25: =IF(AH25>=AH24,AH25-AH24,0)*0.53 -> 264.47 | AJ25: 709161 | AK25: =IF(AJ25>=AJ24,AJ25-AJ24,0)*0.53 -> 2290.66 | AL25: 490000 | AM25: =IF(AL25>=AL24,AL25-AL24,0)*0.53 -> 164.3 | AN25: =W25+Y25+AA25+AC25+AE25+AG25+AI25+AK25+AM25 -> 3753.46 | AO25: 7650646 | AP25: =IF(AO25>=AO24,AO25-AO24,0)*0.1125 -> 4.3875 | AQ25: 673937 | AR25: =IF(AQ25>=AQ24,AQ25-AQ24,0) -> 335 | AS25: 964727 | AT25: =IF(AS25>=AS24,AS25-AS24,0) -> 155 | AU25: 809790 | AV25: =IF(AU25>=AU24,AU25-AU24,0) -> 32 | AW25: 2614925 | AX25: =IF(AW25>=AW24,AW25-AW24,0) -> 574 | AY25: 229487 | AZ25: =IF(AY25>=AY24,AY25-AY24,0) -> 15 | BA25: 19251734 | BB25: =IF(BA25>=BA24,BA25-BA24,0) -> 4388 | BC25: 564968 | BD25: =IF(BC25>=BC24,BC25-BC24,0) -> 210 | BE25: 26162 | BF25: =IF(BE25>=BE24,BE25-BE24,0) -> 56 | BG25: 24072402 | BH25: =IF(BG25>=BG24,BG25-BG24,0)-(0.45*BN25)-(0.45*BP25)-BR25 -> 4733.75 | BI25: =AP25+AR25+AT25+AV25+AX25+AZ25+BB25+BD25+BF25+BH25 -> 10503.138 | BJ25: =BI25+AN25 -> 14256.598 | BK25: 1424806 | BL25: =IF(BK25>=BK24,BK25-BK24,0) -> 97 | BM25: 3925547 | BN25: =IF(BM25>=BM24,BM25-BM24,0) -> 725 | BO25: 412315 | BP25: =IF(BO25>=BO24,BO25-BO24,0) -> 140 | BQ25: 516519 | BR25: =IF(BQ25>=BQ24,BQ25-BQ24,0) -> 139 | BS25: =J25+Q25+AN25+BI25 -> 22717.598 | BT25: 195 | BU25: =IF(BS25>0,BS25/BT25,0) -> 116.5005 | BW25: =IF(BS25>0,BS25/BV25,0) -> #DIV/0! | BX25: =((BS25-Q25)*$BZ$1)+(Q25*$BR$1) -> 26368.237 | BY25: =IF(BX25>0,BX25/BT25,0) -> 135.22173 | BZ25: =IF(BX25>0,BX25/BV25,0) -> #DIV/0!
A26: 21 | C26: =IF(+B26-B25>0,B26-B25,(B26-B25)>0)*800 -> 0 | E26: =IF(+D26-D25>0,D26-D25,(D26-D25)>0)*80 -> 0 | G26: =IF(+F26-F25>0,F26-F25,(F26-F25)>0)*10 -> 0 | H26: 66 | I26: 23857651 | J26: =IF(I26>=I25,I26-I25,0) -> 7603 | K26: =M26+O26 -> 4422 | L26: 651405 | M26: =IF(L26>=L25,L26-L25,0) -> 3087 | N26: 553505 | O26: =IF(N26>=N25,N26-N25,0) -> 1335 | P26: 221549 | Q26: =IF(P26>=P25,P26-P25,0)*30 -> 510 | R26: 180881 | S26: =IF(R26>=R25,R26-R25,0) -> 140 | T26: 330575 | U26: =IF(T26>=T25,T26-T25,0) -> 253.14286 | V26: 776056 | W26: =IF(V26>=V25,V26-V25,0)*0.53 -> 1170.77 | X26: 120681 | Y26: =IF(X26>=X25,X26-X25,0)*0.53 -> 0 | Z26: 134745 | AA26: =IF(Z26>=Z25,Z26-Z25,0)*0.53 -> 0 | AB26: 488293 | AC26: =IF(AB26>=AB25,AB26-AB25,0)*0.53 -> 0 | AD26: 656736 | AE26: =IF(AD26>=AD25,AD26-AD25,0)*0.53 -> 13.25 | AF26: 835407 | AG26: =IF(AF26>=AF25,AF26-AF25,0)*0.53 -> 12.72 | AH26: 984033 | AI26: =IF(AH26>=AH25,AH26-AH25,0)*0.53 -> 139.92 | AJ26: 713398 | AK26: =IF(AJ26>=AJ25,AJ26-AJ25,0)*0.53 -> 2245.61 | AL26: 490237 | AM26: =IF(AL26>=AL25,AL26-AL25,0)*0.53 -> 125.61 | AN26: =W26+Y26+AA26+AC26+AE26+AG26+AI26+AK26+AM26 -> 3707.88 | AO26: 7650681 | AP26: =IF(AO26>=AO25,AO26-AO25,0)*0.1125 -> 3.9375 | AQ26: 674247 | AR26: =IF(AQ26>=AQ25,AQ26-AQ25,0) -> 310 | AS26: 964870 | AT26: =IF(AS26>=AS25,AS26-AS25,0) -> 143 | AU26: 809822 | AV26: =IF(AU26>=AU25,AU26-AU25,0) -> 32 | AW26: 2615471 | AX26: =IF(AW26>=AW25,AW26-AW25,0) -> 546 | AY26: 229493 | AZ26: =IF(AY26>=AY25,AY26-AY25,0) -> 6 | BA26: 19256232 | BB26: =IF(BA26>=BA25,BA26-BA25,0) -> 4498 | BC26: 565160 | BD26: =IF(BC26>=BC25,BC26-BC25,0) -> 192 | BE26: 26216 | BF26: =IF(BE26>=BE25,BE26-BE25,0) -> 54 | BG26: 24077461 | BH26: =IF(BG26>=BG25,BG26-BG25,0)-(0.45*BN26)-(0.45*BP26)-BR26 -> 4543.95 | BI26: =AP26+AR26+AT26+AV26+AX26+AZ26+BB26+BD26+BF26+BH26 -> 10328.888 | BJ26: =BI26+AN26 -> 14036.768 | BK26: 1424866 | BL26: =IF(BK26>=BK25,BK26-BK25,0) -> 60 | BM26: 3926224 | BN26: =IF(BM26>=BM25,BM26-BM25,0) -> 677 | BO26: 412447 | BP26: =IF(BO26>=BO25,BO26-BO25,0) -> 132 | BQ26: 516670 | BR26: =IF(BQ26>=BQ25,BQ26-BQ25,0) -> 151 | BS26: =J26+Q26+AN26+BI26 -> 22149.768 | BT26: 199 | BU26: =IF(BS26>0,BS26/BT26,0) -> 111.30536 | BW26: =IF(BS26>0,BS26/BV26,0) -> #DIV/0! | BX26: =((BS26-Q26)*$BZ$1)+(Q26*$BR$1) -> 25701.733 | BY26: =IF(BX26>0,BX26/BT26,0) -> 129.15444 | BZ26: =IF(BX26>0,BX26/BV26,0) -> #DIV/0!
A27: 22 | C27: =IF(+B27-B26>0,B27-B26,(B27-B26)>0)*800 -> 0 | E27: =IF(+D27-D26>0,D27-D26,(D27-D26)>0)*80 -> 0 | G27: =IF(+F27-F26>0,F27-F26,(F27-F26)>0)*10 -> 0 | I27: 23865399 | J27: =IF(I27>=I26,I27-I26,0) -> 7748 | K27: =M27+O27 -> 4407 | L27: 654394 | M27: =IF(L27>=L26,L27-L26,0) -> 2989 | N27: 554923 | O27: =IF(N27>=N26,N27-N26,0) -> 1418 | P27: 221566 | Q27: =IF(P27>=P26,P27-P26,0)*30 -> 510 | R27: 181024 | S27: =IF(R27>=R26,R27-R26,0) -> 143 | T27: 330845 | U27: =IF(T27>=T26,T27-T26,0) -> 270 | V27: 777991 | W27: =IF(V27>=V26,V27-V26,0)*0.53 -> 1025.55 | X27: 120681 | Y27: =IF(X27>=X26,X27-X26,0)*0.53 -> 0 | Z27: 134745 | AA27: =IF(Z27>=Z26,Z27-Z26,0)*0.53 -> 0 | AB27: 488293 | AC27: =IF(AB27>=AB26,AB27-AB26,0)*0.53 -> 0 | AD27: 656762 | AE27: =IF(AD27>=AD26,AD27-AD26,0)*0.53 -> 13.78 | AF27: 835432 | AG27: =IF(AF27>=AF26,AF27-AF26,0)*0.53 -> 13.25 | AH27: 984319 | AI27: =IF(AH27>=AH26,AH27-AH26,0)*0.53 -> 151.58 | AJ27: 717481 | AK27: =IF(AJ27>=AJ26,AJ27-AJ26,0)*0.53 -> 2163.99 | AL27: 490520 | AM27: =IF(AL27>=AL26,AL27-AL26,0)*0.53 -> 149.99 | AN27: =W27+Y27+AA27+AC27+AE27+AG27+AI27+AK27+AM27 -> 3518.14 | AO27: 7650720 | AP27: =IF(AO27>=AO26,AO27-AO26,0)*0.1125 -> 4.3875 | AQ27: 674559 | AR27: =IF(AQ27>=AQ26,AQ27-AQ26,0) -> 312 | AS27: 965019 | AT27: =IF(AS27>=AS26,AS27-AS26,0) -> 149 | AU27: 809856 | AV27: =IF(AU27>=AU26,AU27-AU26,0) -> 34 | AW27: 2616016 | AX27: =IF(AW27>=AW26,AW27-AW26,0) -> 545 | AY27: 229499 | AZ27: =IF(AY27>=AY26,AY27-AY26,0) -> 6 | BA27: 19260554 | BB27: =IF(BA27>=BA26,BA27-BA26,0) -> 4322 | BC27: 565375 | BD27: =IF(BC27>=BC26,BC27-BC26,0) -> 215 | BE27: 26270 | BF27: =IF(BE27>=BE26,BE27-BE26,0) -> 54 | BG27: 24082590 | BH27: =IF(BG27>=BG26,BG27-BG26,0)-(0.45*BN27)-(0.45*BP27)-BR27 -> 5129 | BI27: =AP27+AR27+AT27+AV27+AX27+AZ27+BB27+BD27+BF27+BH27 -> 10770.388 | BJ27: =BI27+AN27 -> 14288.528 | BK27: 1424928 | BL27: =IF(BK27>=BK26,BK27-BK26,0) -> 62 | BM27: 3926224 | BN27: =IF(BM27>=BM26,BM27-BM26,0) -> 0 | BO27: 412447 | BP27: =IF(BO27>=BO26,BO27-BO26,0) -> 0 | BQ27: 516670 | BR27: =IF(BQ27>=BQ26,BQ27-BQ26,0) -> 0 | BS27: =J27+Q27+AN27+BI27 -> 22546.528 | BT27: 201 | BU27: =IF(BS27>0,BS27/BT27,0) -> 112.17178 | BW27: =IF(BS27>0,BS27/BV27,0) -> #DIV/0! | BX27: =((BS27-Q27)*$BZ$1)+(Q27*$BR$1) -> 26158.007 | BY27: =IF(BX27>0,BX27/BT27,0) -> 130.13934 | BZ27: =IF(BX27>0,BX27/BV27,0) -> #DIV/0!
A28: 23 | C28: =IF(+B28-B27>0,B28-B27,(B28-B27)>0)*800 -> 0 | E28: =IF(+D28-D27>0,D28-D27,(D28-D27)>0)*80 -> 0 | G28: =IF(+F28-F27>0,F28-F27,(F28-F27)>0)*10 -> 0 | H28: 67 | I28: 23873040 | J28: =IF(I28>=I27,I28-I27,0) -> 7641 | K28: =M28+O28 -> 4663 | L28: 657606 | M28: =IF(L28>=L27,L28-L27,0) -> 3212 | N28: 556374 | O28: =IF(N28>=N27,N28-N27,0) -> 1451 | P28: 221584 | Q28: =IF(P28>=P27,P28-P27,0)*30 -> 540 | R28: 181166 | S28: =IF(R28>=R27,R28-R27,0) -> 142 | T28: 331116 | U28: =IF(T28>=T27,T28-T27,0) -> 271 | V28: 779707 | W28: =IF(V28>=V27,V28-V27,0)*0.53 -> 909.48 | X28: 120681 | Y28: =IF(X28>=X27,X28-X27,0)*0.53 -> 0 | Z28: 134745 | AA28: =IF(Z28>=Z27,Z28-Z27,0)*0.53 -> 0 | AB28: 488293 | AC28: =IF(AB28>=AB27,AB28-AB27,0)*0.53 -> 0 | AD28: 656788 | AE28: =IF(AD28>=AD27,AD28-AD27,0)*0.53 -> 13.78 | AF28: 835457 | AG28: =IF(AF28>=AF27,AF28-AF27,0)*0.53 -> 13.25 | AH28: 984844 | AI28: =IF(AH28>=AH27,AH28-AH27,0)*0.53 -> 278.25 | AJ28: 721692 | AK28: =IF(AJ28>=AJ27,AJ28-AJ27,0)*0.53 -> 2231.83 | AL28: 490822 | AM28: =IF(AL28>=AL27,AL28-AL27,0)*0.53 -> 160.06 | AN28: =W28+Y28+AA28+AC28+AE28+AG28+AI28+AK28+AM28 -> 3606.65 | AO28: 7650759 | AP28: =IF(AO28>=AO27,AO28-AO27,0)*0.1125 -> 4.3875 | AQ28: 674874 | AR28: =IF(AQ28>=AQ27,AQ28-AQ27,0) -> 315 | AS28: 965167 | AT28: =IF(AS28>=AS27,AS28-AS27,0) -> 148 | AU28: 809895 | AV28: =IF(AU28>=AU27,AU28-AU27,0) -> 39 | AW28: 2616596 | AX28: =IF(AW28>=AW27,AW28-AW27,0) -> 580 | AY28: 229509 | AZ28: =IF(AY28>=AY27,AY28-AY27,0) -> 10 | BA28: 19265070 | BB28: =IF(BA28>=BA27,BA28-BA27,0) -> 4516 | BC28: 565611 | BD28: =IF(BC28>=BC27,BC28-BC27,0) -> 236 | BE28: 26324 | BF28: =IF(BE28>=BE27,BE28-BE27,0) -> 54 | BG28: 24087721 | BH28: =IF(BG28>=BG27,BG28-BG27,0)-(0.45*BN28)-(0.45*BP28)-BR28 -> 4616.75 | BI28: =AP28+AR28+AT28+AV28+AX28+AZ28+BB28+BD28+BF28+BH28 -> 10519.138 | BJ28: =BI28+AN28 -> 14125.788 | BK28: 1424988 | BL28: =IF(BK28>=BK27,BK28-BK27,0) -> 60 | BM28: 3926884 | BN28: =IF(BM28>=BM27,BM28-BM27,0) -> 660 | BO28: 412592 | BP28: =IF(BO28>=BO27,BO28-BO27,0) -> 145 | BQ28: 516822 | BR28: =IF(BQ28>=BQ27,BQ28-BQ27,0) -> 152 | BS28: =J28+Q28+AN28+BI28 -> 22306.787 | BT28: 220 | BU28: =IF(BS28>0,BS28/BT28,0) -> 101.39449 | BW28: =IF(BS28>0,BS28/BV28,0) -> #DIV/0! | BX28: =((BS28-Q28)*$BZ$1)+(Q28*$BR$1) -> 25895.806 | BY28: =IF(BX28>0,BX28/BT28,0) -> 117.70821 | BZ28: =IF(BX28>0,BX28/BV28,0) -> #DIV/0!
A29: 24 | C29: =IF(+B29-B28>0,B29-B28,(B29-B28)>0)*800 -> 0 | E29: =IF(+D29-D28>0,D29-D28,(D29-D28)>0)*80 -> 0 | G29: =IF(+F29-F28>0,F29-F28,(F29-F28)>0)*10 -> 0 | I29: 23880180 | J29: =IF(I29>=I28,I29-I28,0) -> 7140 | K29: =M29+O29 -> 4400 | L29: 660522 | M29: =IF(L29>=L28,L29-L28,0) -> 2916 | N29: 557858 | O29: =IF(N29>=N28,N29-N28,0) -> 1484 | P29: 221600 | Q29: =IF(P29>=P28,P29-P28,0)*30 -> 480 | R29: 181305 | S29: =IF(R29>=R28,R29-R28,0) -> 139 | T29: 331377 | U29: =IF(T29>=T28,T29-T28,0) -> 261 | V29: 781318 | W29: =IF(V29>=V28,V29-V28,0)*0.53 -> 853.83 | X29: 120681 | Y29: =IF(X29>=X28,X29-X28,0)*0.53 -> 0 | Z29: 134745 | AA29: =IF(Z29>=Z28,Z29-Z28,0)*0.53 -> 0 | AB29: 488293 | AC29: =IF(AB29>=AB28,AB29-AB28,0)*0.53 -> 0 | AD29: 656813 | AE29: =IF(AD29>=AD28,AD29-AD28,0)*0.53 -> 13.25 | AF29: 835481 | AG29: =IF(AF29>=AF28,AF29-AF28,0)*0.53 -> 12.72 | AH29: 985519 | AI29: =IF(AH29>=AH28,AH29-AH28,0)*0.53 -> 357.75 | AJ29: 725594 | AK29: =IF(AJ29>=AJ28,AJ29-AJ28,0)*0.53 -> 2068.06 | AL29: 491113 | AM29: =IF(AL29>=AL28,AL29-AL28,0)*0.53 -> 154.23 | AN29: =W29+Y29+AA29+AC29+AE29+AG29+AI29+AK29+AM29 -> 3459.84 | AO29: 7650800 | AP29: =IF(AO29>=AO28,AO29-AO28,0)*0.1125 -> 4.6125 | AQ29: 675192 | AR29: =IF(AQ29>=AQ28,AQ29-AQ28,0) -> 318 | AS29: 965296 | AT29: =IF(AS29>=AS28,AS29-AS28,0) -> 129 | AU29: 809934 | AV29: =IF(AU29>=AU28,AU29-AU28,0) -> 39 | AW29: 2617150 | AX29: =IF(AW29>=AW28,AW29-AW28,0) -> 554 | AY29: 229511 | AZ29: =IF(AY29>=AY28,AY29-AY28,0) -> 2 | BA29: 19269362 | BB29: =IF(BA29>=BA28,BA29-BA28,0) -> 4292 | BC29: 565844 | BD29: =IF(BC29>=BC28,BC29-BC28,0) -> 233 | BE29: 26380 | BF29: =IF(BE29>=BE28,BE29-BE28,0) -> 56 | BG29: 24092947 | BH29: =IF(BG29>=BG28,BG29-BG28,0)-(0.45*BN29)-(0.45*BP29)-BR29 -> 4673.1 | BI29: =AP29+AR29+AT29+AV29+AX29+AZ29+BB29+BD29+BF29+BH29 -> 10300.713 | BJ29: =BI29+AN29 -> 13760.553 | BK29: 1425038 | BL29: =IF(BK29>=BK28,BK29-BK28,0) -> 50 | BM29: 3927620 | BN29: =IF(BM29>=BM28,BM29-BM28,0) -> 736 | BO29: 412738 | BP29: =IF(BO29>=BO28,BO29-BO28,0) -> 146 | BQ29: 516978 | BR29: =IF(BQ29>=BQ28,BQ29-BQ28,0) -> 156 | BS29: =J29+Q29+AN29+BI29 -> 21380.553 | BT29: 202 | BU29: =IF(BS29>0,BS29/BT29,0) -> 105.84432 | BW29: =IF(BS29>0,BS29/BV29,0) -> #DIV/0! | BX29: =((BS29-Q29)*$BZ$1)+(Q29*$BR$1) -> 24803.635 | BY29: =IF(BX29>0,BX29/BT29,0) -> 122.79027 | BZ29: =IF(BX29>0,BX29/BV29,0) -> #DIV/0!
A30: 25 | C30: =IF(+B30-B29>0,B30-B29,(B30-B29)>0)*800 -> 0 | E30: =IF(+D30-D29>0,D30-D29,(D30-D29)>0)*80 -> 0 | G30: =IF(+F30-F29>0,F30-F29,(F30-F29)>0)*10 -> 0 | H30: 68 | I30: 23887600 | J30: =IF(I30>=I29,I30-I29,0) -> 7420 | K30: =M30+O30 -> 4362 | L30: 663366 | M30: =IF(L30>=L29,L30-L29,0) -> 2844 | N30: 559376 | O30: =IF(N30>=N29,N30-N29,0) -> 1518 | P30: 221618 | Q30: =IF(P30>=P29,P30-P29,0)*30 -> 540 | R30: 181448 | S30: =IF(R30>=R29,R30-R29,0) -> 143 | T30: 331650 | U30: =IF(T30>=T29,T30-T29,0) -> 273 | V30: 782509 | W30: =IF(V30>=V29,V30-V29,0)*0.53 -> 631.23 | X30: 120681 | Y30: =IF(X30>=X29,X30-X29,0)*0.53 -> 0 | Z30: 134745 | AA30: =IF(Z30>=Z29,Z30-Z29,0)*0.53 -> 0 | AB30: 488293 | AC30: =IF(AB30>=AB29,AB30-AB29,0)*0.53 -> 0 | AD30: 656840 | AE30: =IF(AD30>=AD29,AD30-AD29,0)*0.53 -> 14.31 | AF30: 835507 | AG30: =IF(AF30>=AF29,AF30-AF29,0)*0.53 -> 13.78 | AH30: 986298 | AI30: =IF(AH30>=AH29,AH30-AH29,0)*0.53 -> 412.87 | AJ30: 729545 | AK30: =IF(AJ30>=AJ29,AJ30-AJ29,0)*0.53 -> 2094.03 | AL30: 491401 | AM30: =IF(AL30>=AL29,AL30-AL29,0)*0.53 -> 152.64 | AN30: =W30+Y30+AA30+AC30+AE30+AG30+AI30+AK30+AM30 -> 3318.86 | AO30: 7650840 | AP30: =IF(AO30>=AO29,AO30-AO29,0)*0.1125 -> 4.5 | AQ30: 675502 | AR30: =IF(AQ30>=AQ29,AQ30-AQ29,0) -> 310 | AS30: 965431 | AT30: =IF(AS30>=AS29,AS30-AS29,0) -> 135 | AU30: 809973 | AV30: =IF(AU30>=AU29,AU30-AU29,0) -> 39 | AW30: 2617702 | AX30: =IF(AW30>=AW29,AW30-AW29,0) -> 552 | AY30: 229517 | AZ30: =IF(AY30>=AY29,AY30-AY29,0) -> 6 | BA30: 19273744 | BB30: =IF(BA30>=BA29,BA30-BA29,0) -> 4382 | BC30: 566067 | BD30: =IF(BC30>=BC29,BC30-BC29,0) -> 223 | BE30: 26433 | BF30: =IF(BE30>=BE29,BE30-BE29,0) -> 53 | BG30: 24098311 | BH30: =IF(BG30>=BG29,BG30-BG29,0)-(0.45*BN30)-(0.45*BP30)-BR30 -> 4772.3 | BI30: =AP30+AR30+AT30+AV30+AX30+AZ30+BB30+BD30+BF30+BH30 -> 10476.8 | BJ30: =BI30+AN30 -> 13795.66 | BK30: 1425101 | BL30: =IF(BK30>=BK29,BK30-BK29,0) -> 63 | BM30: 3928437 | BN30: =IF(BM30>=BM29,BM30-BM29,0) -> 817 | BO30: 412887 | BP30: =IF(BO30>=BO29,BO30-BO29,0) -> 149 | BQ30: 517135 | BR30: =IF(BQ30>=BQ29,BQ30-BQ29,0) -> 157 | BS30: =J30+Q30+AN30+BI30 -> 21755.66 | BT30: 201 | BU30: =IF(BS30>0,BS30/BT30,0) -> 108.23711 | BW30: =IF(BS30>0,BS30/BV30,0) -> #DIV/0! | BX30: =((BS30-Q30)*$BZ$1)+(Q30*$BR$1) -> 25262.009 | BY30: =IF(BX30>0,BX30/BT30,0) -> 125.68164 | BZ30: =IF(BX30>0,BX30/BV30,0) -> #DIV/0!
A31: 26 | C31: =IF(+B31-B30>0,B31-B30,(B31-B30)>0)*800 -> 0 | E31: =IF(+D31-D30>0,D31-D30,(D31-D30)>0)*80 -> 0 | G31: =IF(+F31-F30>0,F31-F30,(F31-F30)>0)*10 -> 0 | I31: 23896240 | J31: =IF(I31>=I30,I31-I30,0) -> 8640 | K31: =M31+O31 -> 5326 | L31: 667055 | M31: =IF(L31>=L30,L31-L30,0) -> 3689 | N31: 561013 | O31: =IF(N31>=N30,N31-N30,0) -> 1637 | P31: 221636 | Q31: =IF(P31>=P30,P31-P30,0)*30 -> 540 | R31: 181592 | S31: =IF(R31>=R30,R31-R30,0) -> 144 | T31: 331922 | U31: =IF(T31>=T30,T31-T30,0) -> 272 | V31: 783884 | W31: =IF(V31>=V30,V31-V30,0)*0.53 -> 728.75 | X31: 120681 | Y31: =IF(X31>=X30,X31-X30,0)*0.53 -> 0 | Z31: 134745 | AA31: =IF(Z31>=Z30,Z31-Z30,0)*0.53 -> 0 | AB31: 488293 | AC31: =IF(AB31>=AB30,AB31-AB30,0)*0.53 -> 0 | AD31: 656867 | AE31: =IF(AD31>=AD30,AD31-AD30,0)*0.53 -> 14.31 | AF31: 835533 | AG31: =IF(AF31>=AF30,AF31-AF30,0)*0.53 -> 13.78 | AH31: 986758 | AI31: =IF(AH31>=AH30,AH31-AH30,0)*0.53 -> 243.8 | AJ31: 733725 | AK31: =IF(AJ31>=AJ30,AJ31-AJ30,0)*0.53 -> 2215.4 | AL31: 491718 | AM31: =IF(AL31>=AL30,AL31-AL30,0)*0.53 -> 168.01 | AN31: =W31+Y31+AA31+AC31+AE31+AG31+AI31+AK31+AM31 -> 3384.05 | AO31: 7650875 | AP31: =IF(AO31>=AO30,AO31-AO30,0)*0.1125 -> 3.9375 | AQ31: 675828 | AR31: =IF(AQ31>=AQ30,AQ31-AQ30,0) -> 326 | AS31: 965552 | AT31: =IF(AS31>=AS30,AS31-AS30,0) -> 121 | AU31: 810015 | AV31: =IF(AU31>=AU30,AU31-AU30,0) -> 42 | AW31: 2618281 | AX31: =IF(AW31>=AW30,AW31-AW30,0) -> 579 | AY31: 229523 | AZ31: =IF(AY31>=AY30,AY31-AY30,0) -> 6 | BA31: 19278109 | BB31: =IF(BA31>=BA30,BA31-BA30,0) -> 4365 | BC31: 566302 | BD31: =IF(BC31>=BC30,BC31-BC30,0) -> 235 | BE31: 26487 | BF31: =IF(BE31>=BE30,BE31-BE30,0) -> 54 | BG31: 24103736 | BH31: =IF(BG31>=BG30,BG31-BG30,0)-(0.45*BN31)-(0.45*BP31)-BR31 -> 4821.8 | BI31: =AP31+AR31+AT31+AV31+AX31+AZ31+BB31+BD31+BF31+BH31 -> 10553.737 | BJ31: =BI31+AN31 -> 13937.787 | BK31: 1425162 | BL31: =IF(BK31>=BK30,BK31-BK30,0) -> 61 | BM31: 3929286 | BN31: =IF(BM31>=BM30,BM31-BM30,0) -> 849 | BO31: 413034 | BP31: =IF(BO31>=BO30,BO31-BO30,0) -> 147 | BQ31: 517290 | BR31: =IF(BQ31>=BQ30,BQ31-BQ30,0) -> 155 | BS31: =J31+Q31+AN31+BI31 -> 23117.787 | BT31: 209 | BU31: =IF(BS31>0,BS31/BT31,0) -> 110.61142 | BW31: =IF(BS31>0,BS31/BV31,0) -> #DIV/0! | BX31: =((BS31-Q31)*$BZ$1)+(Q31*$BR$1) -> 26828.456 | BY31: =IF(BX31>0,BX31/BT31,0) -> 128.36582 | BZ31: =IF(BX31>0,BX31/BV31,0) -> #DIV/0!
A32: 27 | C32: =IF(+B32-B31>0,B32-B31,(B32-B31)>0)*800 -> 0 | E32: =IF(+D32-D31>0,D32-D31,(D32-D31)>0)*80 -> 0 | G32: =IF(+F32-F31>0,F32-F31,(F32-F31)>0)*10 -> 0 | H32: 69 | I32: 23903916 | J32: =IF(I32>=I31,I32-I31,0) -> 7676 | K32: =M32+O32 -> 4472 | L32: 670132 | M32: =IF(L32>=L31,L32-L31,0) -> 3077 | N32: 562408 | O32: =IF(N32>=N31,N32-N31,0) -> 1395 | P32: 221656 | Q32: =IF(P32>=P31,P32-P31,0)*30 -> 600 | R32: 181721 | S32: =IF(R32>=R31,R32-R31,0) -> 129 | T32: 332162 | U32: =IF(T32>=T31,T32-T31,0) -> 240 | V32: 785244 | W32: =IF(V32>=V31,V32-V31,0)*0.53 -> 720.8 | X32: 120681 | Y32: =IF(X32>=X31,X32-X31,0)*0.53 -> 0 | Z32: 134745 | AA32: =IF(Z32>=Z31,Z32-Z31,0)*0.53 -> 0 | AB32: 488293 | AC32: =IF(AB32>=AB31,AB32-AB31,0)*0.53 -> 0 | AD32: 656890 | AE32: =IF(AD32>=AD31,AD32-AD31,0)*0.53 -> 12.19 | AF32: 835555 | AG32: =IF(AF32>=AF31,AF32-AF31,0)*0.53 -> 11.66 | AH32: 986983 | AI32: =IF(AH32>=AH31,AH32-AH31,0)*0.53 -> 119.25 | AJ32: 737333 | AK32: =IF(AJ32>=AJ31,AJ32-AJ31,0)*0.53 -> 1912.24 | AL32: 491984 | AM32: =IF(AL32>=AL31,AL32-AL31,0)*0.53 -> 140.98 | AN32: =W32+Y32+AA32+AC32+AE32+AG32+AI32+AK32+AM32 -> 2917.12 | AO32: 7650914 | AP32: =IF(AO32>=AO31,AO32-AO31,0)*0.1125 -> 4.3875 | AQ32: 676151 | AR32: =IF(AQ32>=AQ31,AQ32-AQ31,0) -> 323 | AS32: 965658 | AT32: =IF(AS32>=AS31,AS32-AS31,0) -> 106 | AU32: 810048 | AV32: =IF(AU32>=AU31,AU32-AU31,0) -> 33 | AW32: 2618774 | AX32: =IF(AW32>=AW31,AW32-AW31,0) -> 493 | AY32: 229529 | AZ32: =IF(AY32>=AY31,AY32-AY31,0) -> 6 | BA32: 19281493 | BB32: =IF(BA32>=BA31,BA32-BA31,0) -> 3384 | BC32: 566484 | BD32: =IF(BC32>=BC31,BC32-BC31,0) -> 182 | BE32: 26541 | BF32: =IF(BE32>=BE31,BE32-BE31,0) -> 54 | BG32: 24108721 | BH32: =IF(BG32>=BG31,BG32-BG31,0)-(0.45*BN32)-(0.45*BP32)-BR32 -> 4448.4 | BI32: =AP32+AR32+AT32+AV32+AX32+AZ32+BB32+BD32+BF32+BH32 -> 9033.7875 | BJ32: =BI32+AN32 -> 11950.908 | BK32: 1425217 | BL32: =IF(BK32>=BK31,BK32-BK31,0) -> 55 | BM32: 3930042 | BN32: =IF(BM32>=BM31,BM32-BM31,0) -> 756 | BO32: 413166 | BP32: =IF(BO32>=BO31,BO32-BO31,0) -> 132 | BQ32: 517427 | BR32: =IF(BQ32>=BQ31,BQ32-BQ31,0) -> 137 | BS32: =J32+Q32+AN32+BI32 -> 20226.908 | BT32: 222 | BU32: =IF(BS32>0,BS32/BT32,0) -> 91.112196 | BW32: =IF(BS32>0,BS32/BV32,0) -> #DIV/0! | BX32: =((BS32-Q32)*$BZ$1)+(Q32*$BR$1) -> 23530.944 | BY32: =IF(BX32>0,BX32/BT32,0) -> 105.99524 | BZ32: =IF(BX32>0,BX32/BV32,0) -> #DIV/0!
A33: 28 | C33: =IF(+B33-B32>0,B33-B32,(B33-B32)>0)*800 -> 0 | E33: =IF(+D33-D32>0,D33-D32,(D33-D32)>0)*80 -> 0 | G33: =IF(+F33-F32>0,F33-F32,(F33-F32)>0)*10 -> 0 | I33: 23911974 | J33: =IF(I33>=I32,I33-I32,0) -> 8058 | K33: =M33+O33 -> 4810 | L33: 673408 | M33: =IF(L33>=L32,L33-L32,0) -> 3276 | N33: 563942 | O33: =IF(N33>=N32,N33-N32,0) -> 1534 | P33: 221677 | Q33: =IF(P33>=P32,P33-P32,0)*30 -> 630 | R33: 181863 | S33: =IF(R33>=R32,R33-R32,0) -> 142 | T33: 332428 | U33: =IF(T33>=T32,T33-T32,0) -> 266 | V33: 787024 | W33: =IF(V33>=V32,V33-V32,0)*0.53 -> 943.4 | X33: 120681 | Y33: =IF(X33>=X32,X33-X32,0)*0.53 -> 0 | Z33: 134745 | AA33: =IF(Z33>=Z32,Z33-Z32,0)*0.53 -> 0 | AB33: 488293 | AC33: =IF(AB33>=AB32,AB33-AB32,0)*0.53 -> 0 | AD33: 656915 | AE33: =IF(AD33>=AD32,AD33-AD32,0)*0.53 -> 13.25 | AF33: 835579 | AG33: =IF(AF33>=AF32,AF33-AF32,0)*0.53 -> 12.72 | AH33: 987227 | AI33: =IF(AH33>=AH32,AH33-AH32,0)*0.53 -> 129.32 | AJ33: 741367 | AK33: =IF(AJ33>=AJ32,AJ33-AJ32,0)*0.53 -> 2138.02 | AL33: 492290 | AM33: =IF(AL33>=AL32,AL33-AL32,0)*0.53 -> 162.18 | AN33: =W33+Y33+AA33+AC33+AE33+AG33+AI33+AK33+AM33 -> 3398.89 | AO33: 7650957 | AP33: =IF(AO33>=AO32,AO33-AO32,0)*0.1125 -> 4.8375 | AQ33: 676487 | AR33: =IF(AQ33>=AQ32,AQ33-AQ32,0) -> 336 | AS33: 965778 | AT33: =IF(AS33>=AS32,AS33-AS32,0) -> 120 | AU33: 810082 | AV33: =IF(AU33>=AU32,AU33-AU32,0) -> 34 | AW33: 2619327 | AX33: =IF(AW33>=AW32,AW33-AW32,0) -> 553 | AY33: 229535 | AZ33: =IF(AY33>=AY32,AY33-AY32,0) -> 6 | BA33: 19286430 | BB33: =IF(BA33>=BA32,BA33-BA32,0) -> 4937 | BC33: 566698 | BD33: =IF(BC33>=BC32,BC33-BC32,0) -> 214 | BE33: 26586 | BF33: =IF(BE33>=BE32,BE33-BE32,0) -> 45 | BG33: 24114189 | BH33: =IF(BG33>=BG32,BG33-BG32,0)-(0.45*BN33)-(0.45*BP33)-BR33 -> 4867.4 | BI33: =AP33+AR33+AT33+AV33+AX33+AZ33+BB33+BD33+BF33+BH33 -> 11117.237 | BJ33: =BI33+AN33 -> 14516.127 | BK33: 1425281 | BL33: =IF(BK33>=BK32,BK33-BK32,0) -> 64 | BM33: 3930909 | BN33: =IF(BM33>=BM32,BM33-BM32,0) -> 867 | BO33: 413327 | BP33: =IF(BO33>=BO32,BO33-BO32,0) -> 161 | BQ33: 517565 | BR33: =IF(BQ33>=BQ32,BQ33-BQ32,0) -> 138 | BS33: =J33+Q33+AN33+BI33 -> 23204.127 | BT33: 229 | BU33: =IF(BS33>0,BS33/BT33,0) -> 101.32807 | BW33: =IF(BS33>0,BS33/BV33,0) -> #DIV/0! | BX33: =((BS33-Q33)*$BZ$1)+(Q33*$BR$1) -> 26968.247 | BY33: =IF(BX33>0,BX33/BT33,0) -> 117.76527 | BZ33: =IF(BX33>0,BX33/BV33,0) -> #DIV/0!
A34: 29 | C34: =IF(+B34-B33>0,B34-B33,(B34-B33)>0)*800 -> 0 | E34: =IF(+D34-D33>0,D34-D33,(D34-D33)>0)*80 -> 0 | G34: =IF(+F34-F33>0,F34-F33,(F34-F33)>0)*10 -> 0 | I34: 23919546 | J34: =IF(I34>=I33,I34-I33,0) -> 7572 | K34: =M34+O34 -> 4537 | L34: 676409 | M34: =IF(L34>=L33,L34-L33,0) -> 3001 | N34: 565478 | O34: =IF(N34>=N33,N34-N33,0) -> 1536 | P34: 221696 | Q34: =IF(P34>=P33,P34-P33,0)*30 -> 570 | R34: 182007 | S34: =IF(R34>=R33,R34-R33,0) -> 144 | T34: 332697 | U34: =IF(T34>=T33,T34-T33,0) -> 269 | V34: 789010 | W34: =IF(V34>=V33,V34-V33,0)*0.53 -> 1052.58 | X34: 120681 | Y34: =IF(X34>=X33,X34-X33,0)*0.53 -> 0 | Z34: 134745 | AA34: =IF(Z34>=Z33,Z34-Z33,0)*0.53 -> 0 | AB34: 488293 | AC34: =IF(AB34>=AB33,AB34-AB33,0)*0.53 -> 0 | AD34: 656940 | AE34: =IF(AD34>=AD33,AD34-AD33,0)*0.53 -> 13.25 | AF34: 835605 | AG34: =IF(AF34>=AF33,AF34-AF33,0)*0.53 -> 13.78 | AH34: 987474 | AI34: =IF(AH34>=AH33,AH34-AH33,0)*0.53 -> 130.91 | AJ34: 745455 | AK34: =IF(AJ34>=AJ33,AJ34-AJ33,0)*0.53 -> 2166.64 | AL34: 492578 | AM34: =IF(AL34>=AL33,AL34-AL33,0)*0.53 -> 152.64 | AN34: =W34+Y34+AA34+AC34+AE34+AG34+AI34+AK34+AM34 -> 3529.8 | AO34: 7650996 | AP34: =IF(AO34>=AO33,AO34-AO33,0)*0.1125 -> 4.3875 | AQ34: 676784 | AR34: =IF(AQ34>=AQ33,AQ34-AQ33,0) -> 297 | AS34: 965913 | AT34: =IF(AS34>=AS33,AS34-AS33,0) -> 135 | AU34: 810120 | AV34: =IF(AU34>=AU33,AU34-AU33,0) -> 38 | AW34: 2619893 | AX34: =IF(AW34>=AW33,AW34-AW33,0) -> 566 | AY34: 229541 | AZ34: =IF(AY34>=AY33,AY34-AY33,0) -> 6 | BA34: 19289116 | BB34: =IF(BA34>=BA33,BA34-BA33,0) -> 2686 | BC34: 566882 | BD34: =IF(BC34>=BC33,BC34-BC33,0) -> 184 | BE34: 26644 | BF34: =IF(BE34>=BE33,BE34-BE33,0) -> 58 | BG34: 24119109 | BH34: =IF(BG34>=BG33,BG34-BG33,0)-(0.45*BN34)-(0.45*BP34)-BR34 -> 4443.65 | BI34: =AP34+AR34+AT34+AV34+AX34+AZ34+BB34+BD34+BF34+BH34 -> 8418.0375 | BJ34: =BI34+AN34 -> 11947.837 | BK34: 1425340 | BL34: =IF(BK34>=BK33,BK34-BK33,0) -> 59 | BM34: 3931528 | BN34: =IF(BM34>=BM33,BM34-BM33,0) -> 619 | BO34: 413471 | BP34: =IF(BO34>=BO33,BO34-BO33,0) -> 144 | BQ34: 517698 | BR34: =IF(BQ34>=BQ33,BQ34-BQ33,0) -> 133 | BS34: =J34+Q34+AN34+BI34 -> 20089.838 | BT34: 203 | BU34: =IF(BS34>0,BS34/BT34,0) -> 98.964717 | BW34: =IF(BS34>0,BS34/BV34,0) -> #DIV/0! | BX34: =((BS34-Q34)*$BZ$1)+(Q34*$BR$1) -> 23359.813 | BY34: =IF(BX34>0,BX34/BT34,0) -> 115.07297 | BZ34: =IF(BX34>0,BX34/BV34,0) -> #DIV/0!
A35: 30 | C35: =IF(+B35-B34>0,B35-B34,(B35-B34)>0)*800 -> 0 | E35: =IF(+D35-D34>0,D35-D34,(D35-D34)>0)*80 -> 0 | G35: =IF(+F35-F34>0,F35-F34,(F35-F34)>0)*10 -> 0 | I35: 23927083 | J35: =IF(I35>=I34,I35-I34,0) -> 7537 | K35: =M35+O35 -> 4526 | L35: 679450 | M35: =IF(L35>=L34,L35-L34,0) -> 3041 | N35: 566963 | O35: =IF(N35>=N34,N35-N34,0) -> 1485 | P35: 221708 | Q35: =IF(P35>=P34,P35-P34,0)*30 -> 360 | R35: 182148 | S35: =IF(R35>=R34,R35-R34,0) -> 141 | T35: 332964 | U35: =IF(T35>=T34,T35-T34,0) -> 267 | V35: 791109 | W35: =IF(V35>=V34,V35-V34,0)*0.53 -> 1112.47 | X35: 120756 | Y35: =IF(X35>=X34,X35-X34,0)*0.53 -> 39.75 | Z35: 134745 | AA35: =IF(Z35>=Z34,Z35-Z34,0)*0.53 -> 0 | AB35: 488293 | AC35: =IF(AB35>=AB34,AB35-AB34,0)*0.53 -> 0 | AD35: 656965 | AE35: =IF(AD35>=AD34,AD35-AD34,0)*0.53 -> 13.25 | AF35: 835629 | AG35: =IF(AF35>=AF34,AF35-AF34,0)*0.53 -> 12.72 | AH35: 987725 | AI35: =IF(AH35>=AH34,AH35-AH34,0)*0.53 -> 133.03 | AJ35: 749410 | AK35: =IF(AJ35>=AJ34,AJ35-AJ34,0)*0.53 -> 2096.15 | AL35: 492874 | AM35: =IF(AL35>=AL34,AL35-AL34,0)*0.53 -> 156.88 | AN35: =W35+Y35+AA35+AC35+AE35+AG35+AI35+AK35+AM35 -> 3564.25 | AO35: 7651035 | AP35: =IF(AO35>=AO34,AO35-AO34,0)*0.1125 -> 4.3875 | AQ35: 677113 | AR35: =IF(AQ35>=AQ34,AQ35-AQ34,0) -> 329 | AS35: 966044 | AT35: =IF(AS35>=AS34,AS35-AS34,0) -> 131 | AU35: 810165 | AV35: =IF(AU35>=AU34,AU35-AU34,0) -> 45 | AW35: 2620460 | AX35: =IF(AW35>=AW34,AW35-AW34,0) -> 567 | AY35: 229547 | AZ35: =IF(AY35>=AY34,AY35-AY34,0) -> 6 | BA35: 19293123 | BB35: =IF(BA35>=BA34,BA35-BA34,0) -> 4007 | BC35: 567101 | BD35: =IF(BC35>=BC34,BC35-BC34,0) -> 219 | BE35: 26697 | BF35: =IF(BE35>=BE34,BE35-BE34,0) -> 53 | BG35: 24124302 | BH35: =IF(BG35>=BG34,BG35-BG34,0)-(0.45*BN35)-(0.45*BP35)-BR35 -> 4636.5 | BI35: =AP35+AR35+AT35+AV35+AX35+AZ35+BB35+BD35+BF35+BH35 -> 9997.8875 | BJ35: =BI35+AN35 -> 13562.138 | BK35: 1425400 | BL35: =IF(BK35>=BK34,BK35-BK34,0) -> 60 | BM35: 3932356 | BN35: =IF(BM35>=BM34,BM35-BM34,0) -> 828 | BO35: 413613 | BP35: =IF(BO35>=BO34,BO35-BO34,0) -> 142 | BQ35: 517818 | BR35: =IF(BQ35>=BQ34,BQ35-BQ34,0) -> 120 | BS35: =J35+Q35+AN35+BI35 -> 21459.138 | BT35: 187 | BU35: =IF(BS35>0,BS35/BT35,0) -> 114.75475 | BW35: =IF(BS35>0,BS35/BV35,0) -> #DIV/0! | BX35: =((BS35-Q35)*$BZ$1)+(Q35*$BR$1) -> 24840.008 | BY35: =IF(BX35>0,BX35/BT35,0) -> 132.83427 | BZ35: =IF(BX35>0,BX35/BV35,0) -> #DIV/0!
A36: 31 | I36: 23935086 | J36: =IF(I36>=I35,I36-I35,0) -> 8003 | K36: =M36+O36 -> 4648 | L36: 682610 | M36: =IF(L36>=L35,L36-L35,0) -> 3160 | N36: 568451 | O36: =IF(N36>=N35,N36-N35,0) -> 1488 | P36: 221729 | Q36: =IF(P36>=P35,P36-P35,0)*30 -> 630 | R36: 182286 | S36: =IF(R36>=R35,R36-R35,0) -> 138 | T36: 333231.5 | U36: =IF(T36>=T35,T36-T35,0) -> 267.5 | V36: 792076 | W36: =IF(V36>=V35,V36-V35,0)*0.53 -> 512.51 | X36: 120756 | Y36: =IF(X36>=X35,X36-X35,0)*0.53 -> 0 | Z36: 134745 | AA36: =IF(Z36>=Z35,Z36-Z35,0)*0.53 -> 0 | AB36: 488293 | AC36: =IF(AB36>=AB35,AB36-AB35,0)*0.53 -> 0 | AD36: 656991 | AE36: =IF(AD36>=AD35,AD36-AD35,0)*0.53 -> 13.78 | AF36: 835653 | AG36: =IF(AF36>=AF35,AF36-AF35,0)*0.53 -> 12.72 | AH36: 988484 | AI36: =IF(AH36>=AH35,AH36-AH35,0)*0.53 -> 402.27 | AJ36: 753327 | AK36: =IF(AJ36>=AJ35,AJ36-AJ35,0)*0.53 -> 2076.01 | AL36: 493166 | AM36: =IF(AL36>=AL35,AL36-AL35,0)*0.53 -> 154.76 | AN36: =W36+Y36+AA36+AC36+AE36+AG36+AI36+AK36+AM36 -> 3172.05 | AO36: 7651074 | AP36: =IF(AO36>=AO35,AO36-AO35,0)*0.1125 -> 4.3875 | AQ36: 677433 | AR36: =IF(AQ36>=AQ35,AQ36-AQ35,0) -> 320 | AS36: 966158 | AT36: =IF(AS36>=AS35,AS36-AS35,0) -> 114 | AU36: 810198 | AV36: =IF(AU36>=AU35,AU36-AU35,0) -> 33 | AW36: 2620992 | AX36: =IF(AW36>=AW35,AW36-AW35,0) -> 532 | AY36: 229553 | AZ36: =IF(AY36>=AY35,AY36-AY35,0) -> 6 | BA36: 19297389 | BB36: =IF(BA36>=BA35,BA36-BA35,0) -> 4266 | BC36: 567310 | BD36: =IF(BC36>=BC35,BC36-BC35,0) -> 209 | BE36: 26749 | BF36: =IF(BE36>=BE35,BE36-BE35,0) -> 52 | BG36: 24129548 | BH36: =IF(BG36>=BG35,BG36-BG35,0)-(0.45*BN36)-(0.45*BP36)-BR36 -> 4685.35 | BI36: =AP36+AR36+AT36+AV36+AX36+AZ36+BB36+BD36+BF36+BH36 -> 10221.737 | BJ36: =BI36+AN36 -> 13393.787 | BK36: 1425459 | BL36: =IF(BK36>=BK35,BK36-BK35,0) -> 59 | BM36: 3933145 | BN36: =IF(BM36>=BM35,BM36-BM35,0) -> 789 | BO36: 413761 | BP36: =IF(BO36>=BO35,BO36-BO35,0) -> 148 | BQ36: 517957 | BR36: =IF(BQ36>=BQ35,BQ36-BQ35,0) -> 139 | BS36: =J36+Q36+AN36+BI36 -> 22026.787 | BT36: 190 | BU36: =IF(BS36>0,BS36/BT36,0) -> 115.93046 | BW36: =IF(BS36>0,BS36/BV36,0) -> #DIV/0! | BX36: =((BS36-Q36)*$BZ$1)+(Q36*$BR$1) -> 25614.306 | BY36: =IF(BX36>0,BX36/BT36,0) -> 134.81213 | BZ36: =IF(BX36>0,BX36/BV36,0) -> #DIV/0!
A37: MTD | C37: =SUM(C9:C35) -> 0 | E37: =SUM(E9:E35) -> 0 | F37: =SUM(F9:F35) -> 0 | G37: =SUM(G9:G35) -> 0 | J37: =SUM(J6:J36) -> 219498 | K37: =SUM(K6:K36) -> 132822 | M37: =SUM(M6:M36) -> 87223 | O37: =SUM(O6:O36) -> 45599 | Q37: =SUM(Q6:Q36) -> 16290 | S37: =SUM(S6:S36) -> 4351 | U37: =SUM(U6:U36) -> 8145.5 | W37: =SUM(W6:W36) -> 30563.51 | Y37: =SUM(Y5:Y36) -> 2391.89 | AA37: =SUM(AA6:AA36) -> 40.28 | AC37: =SUM(AC6:AC36) -> 24.38 | AE37: =SUM(AE6:AE36) -> 418.7 | AG37: =SUM(AG6:AG36) -> 401.21 | AI37: =SUM(AI6:AI36) -> 11259.32 | AK37: =SUM(AK6:AK36) -> 69732.63 | AM37: =SUM(AM6:AM36) -> 4844.73 | AN37: =SUM(AN6:AN36) -> 119676.65 | AP37: =SUM(AP6:AP36) -> 137.8125 | AR37: =SUM(AR6:AR36) -> 10083 | AT37: =SUM(AT6:AT36) -> 4167 | AV37: =SUM(AV6:AV36) -> 929 | AX37: =SUM(AX6:AX36) -> 17567 | AZ37: =SUM(AZ6:AZ36) -> 489 | BB37: =SUM(BB6:BB36) -> 134304 | BD37: =SUM(BD6:BD36) -> 7116 | BF37: =SUM(BF6:BF36) -> 1639 | BH37: =SUM(BH6:BH36) -> 147990.4 | BI37: =SUM(BI6:BI36) -> 324422.21 | BJ37: =SUM(BJ6:BJ36) -> 444098.86 | BL37: =SUM(BL6:BL36) -> 5623 | BN37: =SUM(BN6:BN36) -> 23678 | BP37: =SUM(BP6:BP36) -> 4170 | BR37: =SUM(BR6:BR36) -> 4347 | BS37: =SUM(BS6:BS36) -> 679886.86 | BT37: =SUM(BT6:BT36) -> 6263 | BU37: =IF(BS37>0,BS37/BT37,0) -> 108.5561 | BV37: =SUM(BV6:BV35) -> 0 | BW37: =IF(BS37>0,BS37/BV37,0) -> #DIV/0! | BX37: =SUM(BX6:BX35) -> 763586.09 | BY37: =IF(BX37>0,BX37/BT37,0) -> 121.92018 | BZ37: =IF(BX37>0,BX37/BV37,0) -> #DIV/0!
A38: AVER. Act | C38: =C37/C40 -> #DIV/0! | E38: =E37/C40 -> #DIV/0! | F38: =F37/C40 -> #DIV/0! | G38: =G37/C40 -> #DIV/0! | J38: =J37/J39 -> 7080.5806 | K38: =K37/J39 -> 4284.5806 | M38: =M37/J39 -> 2813.6452 | O38: =O37/J39 -> 1470.9355 | Q38: =Q37/J39 -> 525.48387 | S38: =S37/J39 -> 140.35484 | U38: =U37/J39 -> 262.75806 | W38: =W37/J39 -> 985.91968 | Y38: =Y37/J39 -> 77.157742 | AA38: =AA37/J39 -> 1.2993548 | AC38: =AC37/J39 -> 0.78645161 | AE38: =AE37/J39 -> 13.506452 | AG38: =AG37/J39 -> 12.942258 | AI38: =AI37/J39 -> 363.20387 | AK38: =AK37/J39 -> 2249.4397 | AM38: =AM37/J39 -> 156.28161 | AN38: =AN37/J39 -> 3860.5371 | AP38: =AP37/J39 -> 4.4455645 | AR38: =AR37/J39 -> 325.25806 | AT38: =AT37/J39 -> 134.41935 | AV38: =AV37/J39 -> 29.967742 | AX38: =AX37/J39 -> 566.67742 | AZ38: =AZ37/J39 -> 15.774194 | BB38: =BB37/J39 -> 4332.3871 | BD38: =BD37/J39 -> 229.54839 | BF38: =BF37/J39 -> 52.870968 | BH38: =BH37/J39 -> 4773.8839 | BL38: =BL37/J39 -> 181.3871 | BN38: =BN37/J39 -> 763.80645 | BP38: =BP37/J39 -> 134.51613 | BR38: =BR37/J39 -> 140.22581 | BS38: =BS37/J40 -> 21931.834 | BT38: =BT37/J40 -> 202.03226 | BU38: =BS38/BT38 -> 108.5561 | BV38: =BV37/$J$41 -> #DIV/0! | BW38: =BS38/BV38 -> #DIV/0! | BX38: =BX37/$J$41 -> #DIV/0! | BY38: =BX38/BT38 -> #DIV/0! | BZ38: =BX38/BV38 -> #DIV/0!
A39: No of Days MTD | J39: =COUNTIF(I6:I36,">0") -> 31 | BT39: =BT38/262 -> 0.77111549
A40: No of Days month | J40: =COUNTIF(A6:A36,">0") -> 31

Sheet Water
A1: =Elect!A1 -> January | T1: Main Water UP | V1: 4 | W1: Water Truck UP
A3: Day | E3: Water Incoming | I3: New casino | N3: Rooms Consumption | P3: Public Areas consumption | R3: Swimming pool | T3: No. of rooms | U3: Cons. Per occ. room | V3: No. of guest | W3: Cons. Per guest | X3: Total cost | Y3: L.E\ | Z3: L.E\
B4: Main water meter 1 | D4: Main water meter 2 | F4: Main water meter 3 | H4: Total Inc. | I4: Hot water | K4: Cold water | N4: Express Riser | O4: Consp. | P4: Read. | Q4: Cons. | R4: Read. | S4: Cons. | Y4: Room | Z4: Guest
B5: Counter | C5: Produc 58% | D5: Counter | E5: Produc 58% | F5: Counter | G5: Produc 58% | I5: Counter | K5: Counter
B6: 82399 | C6: =IF(B6>=B5,B6-B5,0)*10*0.58 -> 0 | D6: 3285 | E6: =IF(D6>=D5,D6-D5,0)*10*0.58 -> 0 | F6: 29102 | G6: =IF(F6>=F5,F6-F5,0)*0.58 -> 0 | I6: 245 | K6: 3986
A7: 1 | B7: 82448 | C7: =IF(B7>=B6,B7-B6,0)*10*0.58 -> 284.2 | D7: 3328 | E7: =IF(D7>=D6,D7-D6,0)*10*0.58 -> 249.4 | F7: 29112 | G7: =IF(F7>=F6,F7-F6,0)*0.58 -> 5.8 | H7: =C7+E7+G7 -> 539.4 | O7: =IF(N7>=N6,N7-N6,0) -> 0 | Q7: =(H7-O7)*0.58 -> 312.852 | S7: =IF(R7-R6>0,R7-R6,0) -> 0 | T7: =Elect!BT6 -> 232 | U7: =H7/T7 -> 2.325 | V7: =Elect!BV6 -> 0 | W7: =H7/V7 -> #DIV/0! | X7: =H7*V1 -> 2157.6 | Y7: =IF(X7>0,X7/T7,0) -> 9.3 | Z7: 0
A8: 2 | B8: 82465 | C8: =IF(B8>=B7,B8-B7,0)*10*0.58 -> 98.6 | D8: 3352 | E8: =IF(D8>=D7,D8-D7,0)*10*0.58 -> 139.2 | F8: 29112 | G8: =IF(F8>=F7,F8-F7,0)*0.58 -> 0 | H8: =C8+E8+G8 -> 237.8 | O8: =IF(N8>=N7,N8-N7,0) -> 0 | Q8: =(H8-O8)*0.58 -> 137.924 | S8: =IF(R8-R7>0,R8-R7,0) -> 0 | T8: =Elect!BT7 -> 191 | U8: =H8/T8 -> 1.2450262 | V8: =Elect!BV7 -> 0 | W8: =H8/V8 -> #DIV/0! | X8: =H8*V1 -> 951.2 | Y8: =IF(X8>0,X8/T8,0) -> 4.9801047 | Z8: =IF(X8>0,X8/V8,0) -> #DIV/0!
A9: 3 | B9: 82491 | C9: =IF(B9>=B8,B9-B8,0)*10*0.58 -> 150.8 | D9: 3386 | E9: =IF(D9>=D8,D9-D8,0)*10*0.58 -> 197.2 | F9: 29112 | G9: =IF(F9>=F8,F9-F8,0)*0.58 -> 0 | H9: =C9+E9+G9 -> 348 | O9: =IF(N9>=N8,N9-N8,0) -> 0 | Q9: =(H9-O9)*0.58 -> 201.84 | S9: =IF(R9-R8>0,R9-R8,0) -> 0 | T9: =Elect!BT8 -> 219 | U9: =H9/T9 -> 1.5890411 | V9: =Elect!BV8 -> 0 | W9: =H9/V9 -> #DIV/0! | X9: =H9*V1 -> 1392 | Y9: =IF(X9>0,X9/T9,0) -> 6.3561644 | Z9: =IF(X9>0,X9/V9,0) -> #DIV/0!
A10: 4 | B10: 82516 | C10: =IF(B10>=B9,B10-B9,0)*10*0.58 -> 145 | D10: 3419 | E10: =IF(D10>=D9,D10-D9,0)*10*0.58 -> 191.4 | F10: 29112 | G10: =IF(F10>=F9,F10-F9,0)*0.58 -> 0 | H10: =C10+E10+G10 -> 336.4 | O10: =IF(N10>=N9,N10-N9,0) -> 0 | Q10: =(H10-O10)*0.58 -> 195.112 | S10: =IF(R10-R9>0,R10-R9,0) -> 0 | T10: =Elect!BT9 -> 205 | U10: =H10/T10 -> 1.6409756 | V10: =Elect!BV9 -> 0 | W10: =H10/V10 -> #DIV/0! | X10: =H10*V1 -> 1345.6 | Y10: =IF(X10>0,X10/T10,0) -> 6.5639024 | Z10: =IF(X10>0,X10/V10,0) -> #DIV/0!
A11: 5 | B11: 82541 | C11: =IF(B11>=B10,B11-B10,0)*10*0.58 -> 145 | D11: 3452 | E11: =IF(D11>=D10,D11-D10,0)*10*0.58 -> 191.4 | F11: 29112 | G11: =IF(F11>=F10,F11-F10,0)*0.58 -> 0 | H11: =C11+E11+G11 -> 336.4 | O11: =IF(N11>=N10,N11-N10,0) -> 0 | Q11: =(H11-O11)*0.58 -> 195.112 | S11: =IF(R11-R10>0,R11-R10,0) -> 0 | T11: =Elect!BT10 -> 199 | U11: =H11/T11 -> 1.6904523 | V11: =Elect!BV10 -> 0 | W11: =H11/V11 -> #DIV/0! | X11: =H11*V1 -> 1345.6 | Y11: =IF(X11>0,X11/T11,0) -> 6.761809 | Z11: =IF(X11>0,X11/V11,0) -> #DIV/0!
A12: 6 | B12: 82566 | C12: =IF(B12>=B11,B12-B11,0)*10*0.58 -> 145 | D12: 3485 | E12: =IF(D12>=D11,D12-D11,0)*10*0.58 -> 191.4 | F12: 29112 | G12: =IF(F12>=F11,F12-F11,0)*0.58 -> 0 | H12: =C12+E12+G12 -> 336.4 | O12: =IF(N12>=N11,N12-N11,0) -> 0 | Q12: =(H12-O12)*0.58 -> 195.112 | S12: =IF(R12-R11>0,R12-R11,0) -> 0 | T12: =Elect!BT11 -> 203 | U12: =H12/T12 -> 1.6571429 | V12: =Elect!BV11 -> 0 | W12: =H12/V12 -> #DIV/0! | X12: =H12*V1 -> 1345.6 | Y12: =IF(X12>0,X12/T12,0) -> 6.6285714 | Z12: =IF(X12>0,X12/V12,0) -> #DIV/0!
A13: 7 | B13: 82592 | C13: =IF(B13>=B12,B13-B12,0)*10*0.58 -> 150.8 | D13: 3520 | E13: =IF(D13>=D12,D13-D12,0)*10*0.58 -> 203 | F13: 29112 | G13: =IF(F13>=F12,F13-F12,0)*0.58 -> 0 | H13: =C13+E13+G13 -> 353.8 | O13: =IF(N13>=N12,N13-N12,0) -> 0 | Q13: =(H13-O13)*0.58 -> 205.204 | S13: =IF(R13-R12>0,R13-R12,0) -> 0 | T13: =Elect!BT12 -> 233 | U13: =H13/T13 -> 1.5184549 | V13: =Elect!BV12 -> 0 | W13: =H13/V13 -> #DIV/0! | X13: =H13*V1 -> 1415.2 | Y13: =IF(X13>0,X13/T13,0) -> 6.0738197 | Z13: =IF(X13>0,X13/V13,0) -> #DIV/0!
A14: 8 | B14: 82618 | C14: =IF(B14>=B13,B14-B13,0)*10*0.58 -> 150.8 | D14: 3555 | E14: =IF(D14>=D13,D14-D13,0)*10*0.58 -> 203 | F14: 29112 | G14: =IF(F14>=F13,F14-F13,0)*0.58 -> 0 | H14: =C14+E14+G14 -> 353.8 | O14: =IF(N14>=N13,N14-N13,0) -> 0 | Q14: =(H14-O14)*0.58 -> 205.204 | S14: =IF(R14-R13>0,R14-R13,0) -> 0 | T14: =Elect!BT13 -> 238 | U14: =H14/T14 -> 1.4865546 | V14: =Elect!BV13 -> 0 | W14: =H14/V14 -> #DIV/0! | X14: =H14*V1 -> 1415.2 | Y14: =IF(X14>0,X14/T14,0) -> 5.9462185 | Z14: =IF(X14>0,X14/V14,0) -> #DIV/0!
A15: 9 | B15: 82643 | C15: =IF(B15>=B14,B15-B14,0)*10*0.58 -> 145 | D15: 3588 | E15: =IF(D15>=D14,D15-D14,0)*10*0.58 -> 191.4 | F15: 29112 | G15: =IF(F15>=F14,F15-F14,0)*0.58 -> 0 | H15: =C15+E15+G15 -> 336.4 | O15: =IF(N15>=N14,N15-N14,0) -> 0 | Q15: =(H15-O15)*0.58 -> 195.112 | S15: =IF(R15-R14>0,R15-R14,0) -> 0 | T15: =Elect!BT14 -> 220 | U15: =H15/T15 -> 1.5290909 | V15: =Elect!BV14 -> 0 | W15: =H15/V15 -> #DIV/0! | X15: =H15*V1 -> 1345.6 | Y15: =IF(X15>0,X15/T15,0) -> 6.1163636 | Z15: =IF(X15>0,X15/V15,0) -> #DIV/0!
A16: 10 | B16: 82671 | C16: =IF(B16>=B15,B16-B15,0)*10*0.58 -> 162.4 | D16: 3625 | E16: =IF(D16>=D15,D16-D15,0)*10*0.58 -> 214.6 | F16: 29112 | G16: =IF(F16>=F15,F16-F15,0)*0.58 -> 0 | H16: =C16+E16+G16 -> 377 | O16: =IF(N16>=N15,N16-N15,0) -> 0 | Q16: =(H16-O16)*0.58 -> 218.66 | S16: =IF(R16-R15>0,R16-R15,0) -> 0 | T16: =Elect!BT15 -> 211 | U16: =H16/T16 -> 1.7867299 | V16: =Elect!BV15 -> 0 | W16: =H16/V16 -> #DIV/0! | X16: =H16*V1 -> 1508 | Y16: =IF(X16>0,X16/T16,0) -> 7.1469194 | Z16: =IF(X16>0,X16/V16,0) -> #DIV/0!
A17: 11 | B17: 82699 | C17: =IF(B17>=B16,B17-B16,0)*10*0.58 -> 162.4 | D17: 3663 | E17: =IF(D17>=D16,D17-D16,0)*10*0.58 -> 220.4 | F17: 29112 | G17: =IF(F17>=F16,F17-F16,0)*0.58 -> 0 | H17: =C17+E17+G17 -> 382.8 | O17: =IF(N17>=N16,N17-N16,0) -> 0 | Q17: =(H17-O17)*0.58 -> 222.024 | S17: =IF(R17-R16>0,R17-R16,0) -> 0 | T17: =Elect!BT16 -> 201 | U17: =H17/T17 -> 1.9044776 | V17: =Elect!BV16 -> 0 | W17: =H17/V17 -> #DIV/0! | X17: =H17*V1 -> 1531.2 | Y17: =IF(X17>0,X17/T17,0) -> 7.6179104 | Z17: =IF(X17>0,X17/V17,0) -> #DIV/0!
A18: 12 | B18: 82727 | C18: =IF(B18>=B17,B18-B17,0)*10*0.58 -> 162.4 | D18: 3701 | E18: =IF(D18>=D17,D18-D17,0)*10*0.58 -> 220.4 | F18: 29112 | G18: =IF(F18>=F17,F18-F17,0)*0.58 -> 0 | H18: =C18+E18+G18 -> 382.8 | O18: =IF(N18>=N17,N18-N17,0) -> 0 | Q18: =(H18-O18)*0.58 -> 222.024 | S18: =IF(R18-R17>0,R18-R17,0) -> 0 | T18: =Elect!BT17 -> 179 | U18: =H18/T18 -> 2.1385475 | V18: =Elect!BV17 -> 0 | W18: =H18/V18 -> #DIV/0! | X18: =H18*V1 -> 1531.2 | Y18: =IF(X18>0,X18/T18,0) -> 8.5541899 | Z18: =IF(X18>0,X18/V18,0) -> #DIV/0!
A19: 13 | B19: 82755 | C19: =IF(B19>=B18,B19-B18,0)*10*0.58 -> 162.4 | D19: 3739 | E19: =IF(D19>=D18,D19-D18,0)*10*0.58 -> 220.4 | F19: 29112 | G19: =IF(F19>=F18,F19-F18,0)*0.58 -> 0 | H19: =C19+E19+G19 -> 382.8 | O19: =IF(N19>=N18,N19-N18,0) -> 0 | Q19: =(H19-O19)*0.58 -> 222.024 | S19: =IF(R19-R18>0,R19-R18,0) -> 0 | T19: =Elect!BT18 -> 207 | U19: =H19/T19 -> 1.8492754 | V19: =Elect!BV18 -> 0 | W19: =H19/V19 -> #DIV/0! | X19: =H19*V1 -> 1531.2 | Y19: =IF(X19>0,X19/T19,0) -> 7.3971014 | Z19: =IF(X19>0,X19/V19,0) -> #DIV/0!
A20: 14 | B20: 82776 | C20: =IF(B20>=B19,B20-B19,0)*10*0.58 -> 121.8 | D20: 3765 | E20: =IF(D20>=D19,D20-D19,0)*10*0.58 -> 150.8 | F20: 29124 | G20: =IF(F20>=F19,F20-F19,0)*0.58 -> 6.96 | H20: =C20+E20+G20 -> 279.56 | O20: =IF(N20>=N19,N20-N19,0) -> 0 | Q20: =(H20-O20)*0.58 -> 162.1448 | S20: =IF(R20-R19>0,R20-R19,0) -> 0 | T20: =Elect!BT19 -> 215 | U20: =H20/T20 -> 1.3002791 | V20: =Elect!BV19 -> 0 | W20: =H20/V20 -> #DIV/0! | X20: =H20*V1 -> 1118.24 | Y20: =IF(X20>0,X20/T20,0) -> 5.2011163 | Z20: =IF(X20>0,X20/V20,0) -> #DIV/0!
A21: 15 | B21: 82797 | C21: =IF(B21>=B20,B21-B20,0)*10*0.58 -> 121.8 | D21: 3791 | E21: =IF(D21>=D20,D21-D20,0)*10*0.58 -> 150.8 | F21: 29124 | G21: =IF(F21>=F20,F21-F20,0)*0.58 -> 0 | H21: =C21+E21+G21 -> 272.6 | O21: =IF(N21>=N20,N21-N20,0) -> 0 | Q21: =(H21-O21)*0.58 -> 158.108 | S21: =IF(R21-R20>0,R21-R20,0) -> 0 | T21: =Elect!BT20 -> 197 | U21: =H21/T21 -> 1.3837563 | V21: =Elect!BV20 -> 0 | W21: =H21/V21 -> #DIV/0! | X21: =H21*V1 -> 1090.4 | Y21: =IF(X21>0,X21/T21,0) -> 5.5350254 | Z21: =IF(X21>0,X21/V21,0) -> #DIV/0!
A22: 16 | B22: 82829 | C22: =IF(B22>=B21,B22-B21,0)*10*0.58 -> 185.6 | D22: 3835 | E22: =IF(D22>=D21,D22-D21,0)*10*0.58 -> 255.2 | F22: 29124 | G22: =IF(F22>=F21,F22-F21,0)*0.58 -> 0 | H22: =C22+E22+G22 -> 440.8 | O22: =IF(N22>=N21,N22-N21,0) -> 0 | Q22: =(H22-O22)*0.58 -> 255.664 | S22: =IF(R22-R21>0,R22-R21,0) -> 0 | T22: =Elect!BT21 -> 176 | U22: =H22/T22 -> 2.5045455 | V22: =Elect!BV21 -> 0 | W22: =H22/V22 -> #DIV/0! | X22: =H22*V1 -> 1763.2 | Y22: =IF(X22>0,X22/T22,0) -> 10.018182 | Z22: =IF(X22>0,X22/V22,0) -> #DIV/0!
A23: 17 | B23: 82857 | C23: =IF(B23>=B22,B23-B22,0)*10*0.58 -> 162.4 | D23: 3872 | E23: =IF(D23>=D22,D23-D22,0)*10*0.58 -> 214.6 | F23: 29124 | G23: =IF(F23>=F22,F23-F22,0)*0.58 -> 0 | H23: =C23+E23+G23 -> 377 | O23: =IF(N23>=N22,N23-N22,0) -> 0 | Q23: =(H23-O23)*0.58 -> 218.66 | S23: =IF(R23-R22>0,R23-R22,0) -> 0 | T23: =Elect!BT22 -> 171 | U23: =H23/T23 -> 2.2046784 | V23: =Elect!BV22 -> 0 | W23: =H23/V23 -> #DIV/0! | X23: =H23*V1 -> 1508 | Y23: =IF(X23>0,X23/T23,0) -> 8.8187135 | Z23: =IF(X23>0,X23/V23,0) -> #DIV/0!
A24: 18 | B24: 82885 | C24: =IF(B24>=B23,B24-B23,0)*10*0.58 -> 162.4 | D24: 3908 | E24: =IF(D24>=D23,D24-D23,0)*10*0.58 -> 208.8 | F24: 29124 | G24: =IF(F24>=F23,F24-F23,0)*0.58 -> 0 | H24: =C24+E24+G24 -> 371.2 | O24: =IF(N24>=N23,N24-N23,0) -> 0 | Q24: =(H24-O24)*0.58 -> 215.296 | S24: =IF(R24-R23>0,R24-R23,0) -> 0 | T24: =Elect!BT23 -> 146 | U24: =H24/T24 -> 2.5424658 | V24: =Elect!BV23 -> 0 | W24: =H24/V24 -> #DIV/0! | X24: =H24*V1 -> 1484.8 | Y24: =IF(X24>0,X24/T24,0) -> 10.169863 | Z24: =IF(X24>0,X24/V24,0) -> #DIV/0!
A25: 19 | B25: 82911 | C25: =IF(B25>=B24,B25-B24,0)*10*0.58 -> 150.8 | D25: 3943 | E25: =IF(D25>=D24,D25-D24,0)*10*0.58 -> 203 | F25: 29124 | G25: =IF(F25>=F24,F25-F24,0)*0.58 -> 0 | H25: =C25+E25+G25 -> 353.8 | O25: =IF(N25>=N24,N25-N24,0) -> 0 | Q25: =(H25-O25)*0.58 -> 205.204 | S25: =IF(R25-R24>0,R25-R24,0) -> 0 | T25: =Elect!BT24 -> 162 | U25: =H25/T25 -> 2.1839506 | V25: =Elect!BV24 -> 0 | W25: =H25/V25 -> #DIV/0! | X25: =H25*V1 -> 1415.2 | Y25: =IF(X25>0,X25/T25,0) -> 8.7358025 | Z25: =IF(X25>0,X25/V25,0) -> #DIV/0!
A26: 20 | B26: 82937 | C26: =IF(B26>=B25,B26-B25,0)*10*0.58 -> 150.8 | D26: 3978 | E26: =IF(D26>=D25,D26-D25,0)*10*0.58 -> 203 | F26: 29124 | G26: =IF(F26>=F25,F26-F25,0)*0.58 -> 0 | H26: =C26+E26+G26 -> 353.8 | O26: =IF(N26>=N25,N26-N25,0) -> 0 | Q26: =(H26-O26)*0.58 -> 205.204 | S26: =IF(R26-R25>0,R26-R25,0) -> 0 | T26: =Elect!BT25 -> 195 | U26: =H26/T26 -> 1.814359 | V26: =Elect!BV25 -> 0 | W26: =H26/V26 -> #DIV/0! | X26: =H26*V1 -> 1415.2 | Y26: =IF(X26>0,X26/T26,0) -> 7.2574359 | Z26: =IF(X26>0,X26/V26,0) -> #DIV/0!
A27: 21 | B27: 82963 | C27: =IF(B27>=B26,B27-B26,0)*10*0.58 -> 150.8 | D27: 4013 | E27: =IF(D27>=D26,D27-D26,0)*10*0.58 -> 203 | F27: 29124 | G27: =IF(F27>=F26,F27-F26,0)*0.58 -> 0 | H27: =C27+E27+G27 -> 353.8 | O27: =IF(N27>=N26,N27-N26,0) -> 0 | Q27: =(H27-O27)*0.58 -> 205.204 | S27: =IF(R27-R26>0,R27-R26,0) -> 0 | T27: =Elect!BT26 -> 199 | U27: =H27/T27 -> 1.7778894 | V27: =Elect!BV26 -> 0 | W27: =H27/V27 -> #DIV/0! | X27: =H27*V1 -> 1415.2 | Y27: =IF(X27>0,X27/T27,0) -> 7.1115578 | Z27: =IF(X27>0,X27/V27,0) -> #DIV/0!
A28: 22 | B28: 82989 | C28: =IF(B28>=B27,B28-B27,0)*10*0.58 -> 150.8 | D28: 4048 | E28: =IF(D28>=D27,D28-D27,0)*10*0.58 -> 203 | F28: 29124 | G28: =IF(F28>=F27,F28-F27,0)*0.58 -> 0 | H28: =C28+E28+G28 -> 353.8 | O28: =IF(N28>=N27,N28-N27,0) -> 0 | Q28: =(H28-O28)*0.58 -> 205.204 | S28: =IF(R28-R27>0,R28-R27,0) -> 0 | T28: =Elect!BT27 -> 201 | U28: =H28/T28 -> 1.760199 | V28: =Elect!BV27 -> 0 | W28: =H28/V28 -> #DIV/0! | X28: =H28*V1 -> 1415.2 | Y28: =IF(X28>0,X28/T28,0) -> 7.040796 | Z28: =IF(X28>0,X28/V28,0) -> #DIV/0!
A29: 23 | B29: 83010 | C29: =IF(B29>=B28,B29-B28,0)*10*0.58 -> 121.8 | D29: 4073 | E29: =IF(D29>=D28,D29-D28,0)*10*0.58 -> 145 | F29: 29124 | G29: =IF(F29>=F28,F29-F28,0)*0.58 -> 0 | H29: =C29+E29+G29 -> 266.8 | O29: =IF(N29>=N28,N29-N28,0) -> 0 | Q29: =(H29-O29)*0.58 -> 154.744 | S29: =IF(R29-R28>0,R29-R28,0) -> 0 | T29: =Elect!BT28 -> 220 | U29: =H29/T29 -> 1.2127273 | V29: =Elect!BV28 -> 0 | W29: =H29/V29 -> #DIV/0! | X29: =H29*V1 -> 1067.2 | Y29: =IF(X29>0,X29/T29,0) -> 4.8509091 | Z29: =IF(X29>0,X29/V29,0) -> #DIV/0!
A30: 24 | B30: 83020 | C30: =IF(B30>=B29,B30-B29,0)*10*0.58 -> 58 | D30: 4090 | E30: =IF(D30>=D29,D30-D29,0)*10*0.58 -> 98.6 | F30: 29124 | G30: =IF(F30>=F29,F30-F29,0)*0.58 -> 0 | H30: =C30+E30+G30 -> 156.6 | O30: =IF(N30>=N29,N30-N29,0) -> 0 | Q30: =(H30-O30)*0.58 -> 90.828 | S30: =IF(R30-R29>0,R30-R29,0) -> 0 | T30: =Elect!BT29 -> 202 | U30: =H30/T30 -> 0.77524752 | V30: =Elect!BV29 -> 0 | W30: =H30/V30 -> #DIV/0! | X30: =H30*V1 -> 626.4 | Y30: =IF(X30>0,X30/T30,0) -> 3.1009901 | Z30: =IF(X30>0,X30/V30,0) -> #DIV/0!
A31: 25 | B31: 83039 | C31: =IF(B31>=B30,B31-B30,0)*10*0.58 -> 110.2 | D31: 4110 | E31: =IF(D31>=D30,D31-D30,0)*10*0.58 -> 116 | F31: 29136 | G31: =IF(F31>=F30,F31-F30,0)*0.58 -> 6.96 | H31: =C31+E31+G31 -> 233.16 | O31: =IF(N31>=N30,N31-N30,0) -> 0 | Q31: =(H31-O31)*0.58 -> 135.2328 | S31: =IF(R31-R30>0,R31-R30,0) -> 0 | T31: =Elect!BT30 -> 201 | U31: =H31/T31 -> 1.16 | V31: =Elect!BV30 -> 0 | W31: =H31/V31 -> #DIV/0! | X31: =H31*V1 -> 932.64 | Y31: =IF(X31>0,X31/T31,0) -> 4.64 | Z31: =IF(X31>0,X31/V31,0) -> #DIV/0!
A32: 26 | B32: 83060 | C32: =IF(B32>=B31,B32-B31,0)*10*0.58 -> 121.8 | D32: 4139 | E32: =IF(D32>=D31,D32-D31,0)*10*0.58 -> 168.2 | F32: 29137 | G32: =IF(F32>=F31,F32-F31,0)*0.58 -> 0.58 | H32: =C32+E32+G32 -> 290.58 | O32: =IF(N32>=N31,N32-N31,0) -> 0 | Q32: =(H32-O32)*0.58 -> 168.5364 | S32: =IF(R32-R31>0,R32-R31,0) -> 0 | T32: =Elect!BT31 -> 209 | U32: =H32/T32 -> 1.3903349 | V32: =Elect!BV31 -> 0 | W32: =H32/V32 -> #DIV/0! | X32: =H32*V1 -> 1162.32 | Y32: =IF(X32>0,X32/T32,0) -> 5.5613397 | Z32: =IF(X32>0,X32/V32,0) -> #DIV/0!
A33: 27 | B33: 83078 | C33: =IF(B33>=B32,B33-B32,0)*10*0.58 -> 104.4 | D33: 4163 | E33: =IF(D33>=D32,D33-D32,0)*10*0.58 -> 139.2 | F33: 29138 | G33: =IF(F33>=F32,F33-F32,0)*0.58 -> 0.58 | H33: =C33+E33+G33 -> 244.18 | O33: =IF(N33>=N32,N33-N32,0) -> 0 | Q33: =(H33-O33)*0.58 -> 141.6244 | S33: =IF(R33-R32>0,R33-R32,0) -> 0 | T33: =Elect!BT32 -> 222 | U33: =H33/T33 -> 1.0999099 | V33: =Elect!BV32 -> 0 | W33: =H33/V33 -> #DIV/0! | X33: =H33*V1 -> 976.72 | Y33: =IF(X33>0,X33/T33,0) -> 4.3996396 | Z33: =IF(X33>0,X33/V33,0) -> #DIV/0!
A34: 28 | B34: 83108 | C34: =IF(B34>=B33,B34-B33,0)*10*0.58 -> 174 | D34: 4199 | E34: =IF(D34>=D33,D34-D33,0)*10*0.58 -> 208.8 | F34: 29139 | G34: =IF(F34>=F33,F34-F33,0)*0.58 -> 0.58 | H34: =C34+E34+G34 -> 383.38 | O34: =IF(N34>=N33,N34-N33,0) -> 0 | Q34: =(H34-O34)*0.58 -> 222.3604 | S34: =IF(R34-R33>0,R34-R33,0) -> 0 | T34: =Elect!BT33 -> 229 | U34: =H34/T34 -> 1.6741485 | V34: =Elect!BV33 -> 0 | W34: =H34/V34 -> #DIV/0! | X34: =H34*V1 -> 1533.52 | Y34: =IF(X34>0,X34/T34,0) -> 6.6965939 | Z34: =IF(X34>0,X34/V34,0) -> #DIV/0!
A35: 29 | B35: 83133 | C35: =IF(B35>=B34,B35-B34,0)*10*0.58 -> 145 | D35: 4232 | E35: =IF(D35>=D34,D35-D34,0)*10*0.58 -> 191.4 | F35: 29139 | G35: =IF(F35>=F34,F35-F34,0)*0.58 -> 0 | H35: =C35+E35+G35 -> 336.4 | O35: =IF(N35>=N34,N35-N34,0) -> 0 | Q35: =(H35-O35)*0.58 -> 195.112 | S35: =IF(R35-R34>0,R35-R34,0) -> 0 | T35: =Elect!BT34 -> 203 | U35: =H35/T35 -> 1.6571429 | V35: =Elect!BV34 -> 0 | W35: =H35/V35 -> #DIV/0! | X35: =H35*V1 -> 1345.6 | Y35: =IF(X35>0,X35/T35,0) -> 6.6285714 | Z35: =IF(X35>0,X35/V35,0) -> #DIV/0!
A36: 30 | B36: 83153 | C36: =IF(B36>=B35,B36-B35,0)*10*0.58 -> 116 | D36: 4257 | E36: =IF(D36>=D35,D36-D35,0)*10*0.58 -> 145 | F36: 29139 | G36: =IF(F36>=F35,F36-F35,0)*0.58 -> 0 | H36: =C36+E36+G36 -> 261 | O36: =IF(N36>=N35,N36-N35,0) -> 0 | Q36: =(H36-O36)*0.58 -> 151.38 | S36: =IF(R36-R35>0,R36-R35,0) -> 0 | T36: =Elect!BT35 -> 187 | U36: =H36/T36 -> 1.3957219 | V36: =Elect!BV35 -> 0 | W36: =H36/V36 -> #DIV/0! | X36: =H36*V1 -> 1044 | Y36: =IF(X36>0,X36/T36,0) -> 5.5828877 | Z36: =IF(X36>0,X36/V36,0) -> #DIV/0!
A37: 31 | B37: 83174 | C37: =IF(B37>=B36,B37-B36,0)*10*0.58 -> 121.8 | D37: 4285 | E37: =IF(D37>=D36,D37-D36,0)*10*0.58 -> 162.4 | F37: 29139 | G37: =IF(F37>=F36,F37-F36,0)*0.58 -> 0 | H37: =C37+E37+G37 -> 284.2 | I37: 247 | K37: 4080 | O37: =IF(N37>=N36,N37-N36,0) -> 0 | Q37: =(H37-O37)*0.58 -> 164.836 | S37: =IF(R37-R36>0,R37-R36,0) -> 0 | T37: =Elect!BT36 -> 190 | U37: =H37/T37 -> 1.4957895 | V37: =Elect!BV36 -> 0 | W37: =H37/V37 -> #DIV/0! | X37: =H37*V7 -> 0 | Y37: =IF(X37>0,X37/T37,0) -> 0 | Z37: =IF(X37>0,X37/V37,0) -> 0
A38: MTD | C38: =SUM(C7:C37) -> 4495 | E38: =SUM(E7:E37) -> 5800 | G38: =SUM(G7:G37) -> 21.46 | H38: =SUM(H7:H37) -> 10316.46 | I38: =I37-I6 -> 2 | K38: =K37-K6 -> 94 | O38: =SUM(O7:O36) -> 0 | Q38: =SUM(Q7:Q34) -> 5472.2188 | S38: =SUM(S7:S34) -> 0 | T38: =SUM(T7:T36) -> 6073 | U38: =IF(H38>0,H38/T38,0) -> 1.698742 | V38: =SUM(V7:V36) -> 0 | W38: =IF(H38>0,H38/V38,0) -> #DIV/0! | X38: =SUM(X7:X36) -> 40129.04 | Y38: =IF(X38>0,X38/T38,0) -> 6.6077787 | Z38: =IF(X38>0,X38/V38,0) -> #DIV/0!
A39: AVER. Act | C39: =C38/B48 -> 149.83333 | E39: =E38/B48 -> 193.33333 | G39: =G38/B48 -> 0.71533333 | H39: =H38/B48 -> 343.882 | O39: =O38/B48 -> 0 | Q39: =Q38/B48 -> 182.40729 | S39: =S38/C48 -> #DIV/0! | T39: =T38/B48 -> 202.43333 | U39: =IF(H39>0,H39/T39,0) -> 1.698742 | V39: =V38/B48 -> 0 | W39: =IF(H39>0,H39/V39,0) -> #DIV/0! | X39: =X38/B48 -> 1337.6347 | Y39: =IF(X39>0,X39/T39,0) -> 6.6077787 | Z39: =IF(X39>0,X39/V39,0) -> #DIV/0!
A40: TOTAL Budget | T40: =YTD!Q2341 -> 0 | U40: =IF(#REF!>0,#REF!/T40,0) -> #REF! | V40: =YTD!Q2342 -> 0 | W40: =IF(#REF!>0,#REF!/V40,0) -> #REF! | X40: =YTD!Q2346 -> 0 | Y40: =IF(X40>0,X40/T40,0) -> 0 | Z40: =IF(X40>0,X40/V40,0) -> 0
A41: Budget MTD | T41: =T42*C48 -> #VALUE! | U41: =IF(#REF!>0,#REF!/T41,0) -> #REF! | V41: =V42*C48 -> #VALUE! | W41: =IF(#REF!>0,#REF!/V41,0) -> #REF! | X41: =#REF!*5.62 -> #REF! | Y41: =IF(X41>0,X41/T41,0) -> #REF! | Z41: =IF(X41>0,X41/V41,0) -> #REF!
A42: AVER. Bud | T42: =T40/$A$48 -> #VALUE! | V42: =V40/$A$48 -> #VALUE!
A43: Total RFC | T43: =YTD!Q2358 -> 0 | V43: =YTD!Q2359 -> 0 | X43: =YTD!Q2363 -> 0 | Y43: =IF(X43>0,X43/T43,0) -> 0 | Z43: =IF(X43>0,X43/V43,0) -> 0
A44: RFC MTD | T44: =T43/A48*C48 -> #VALUE! | V44: =V43/A48*C48 -> #VALUE! | X44: =X43/A48*C48 -> #VALUE! | Y44: =IF(X44>0,X44/T44,0) -> #VALUE! | Z44: =IF(X44>0,X44/V44,0) -> #VALUE!
A45: AVER RFC | T45: =T43/A48 -> #VALUE! | V45: =V44/A48*C48 -> #VALUE! | X45: =X43/A48 -> #VALUE!
A46: MTD 13 | U46: =Consp!BH33 -> 1.1514679 | W46: =Consp!BI33 -> 0.57929342 | X46: =Consp!BJ33 -> 140121.3 | Y46: =Consp!BK33 -> 6.8331854 | Z46: =Consp!BL33 -> 3.4377159
A47: AVER. Act 13 | U47: =Consp!BH34 -> 1.1761372 | W47: =Consp!BI34 -> 0.60007377 | X47: =Consp!BJ34 -> 5004.3322 | Y47: =Consp!BK34 -> 6.8331854 | Z47: =Consp!BL34 -> 3.4377159
A48: No of Days MTD | B48: =COUNTIF(B7:B36,">0") -> 30
A136: Water Incoming

Sheet Consp
A1: =Elect!A1 -> January | L1: Summary | P1: =Elect!A1 -> January
B2: Elect Consuumption | H2: Water Incoming | U2: Water Consumption | AC2: Irrigation | AG2: Gas | AJ2: Cost | AK2: Solar Meter [ LIT ] | AL2: No. of Eng. | AM2: No. of Gardners | AN2: Cons. (lit) | AO2: Received Gas (tons) | AP2: Fuel Cost | AQ2: Solar level [cm] | AR2: Received Solar (tons) | AS2: Fuel Cost | AT2: Occupancy 10 | AV2: Occupancy07 | AZ2: Elect 2009 | BE2: Elect 2010 | BJ2: Water 2009 | BO2: Water 2010
A3: Date | B3: COUNTER (2) | D3: MD | F3: KVAR | H3: R.O | J3: Qenna | L3: Trucks | N3: Rimievera Line Meter | O3: Total Inc. | Q3: Total Main S.Pool | S3: Total Bar & Beach cons. | U3: Total S. Pool cons. | W3: Hotel consumption. | Y3: Sold Water | AA3: Irr. Water from R.O | AC3: Irr. Consumption. | AE3: Storage Water One tank | AF3: Grand Cons | AG3: % | AH3: Stock | AI3: Cons. | AJ3: 0 | AT3: No of guest | AU3: No. of rooms | AV3: No. of rooms | AW3: No. of guest | AX3: Cons. Per occ. room | AY3: Cons. Per guest | AZ3: Total cost | BA3: cost per room | BB3: cost per guest | BC3: Cons. Per occ. room | BD3: Cons. Per guest | BE3: Total cost | BF3: cost per room | BG3: cost per guest | BH3: Cons. Per occ. room | BI3: Cons. Per guest | BJ3: Total cost | BK3: cost per room | BL3: cost per guest | BM3: Cons. Per occ. room | BN3: Cons. Per guest | BO3: Total cost | BP3: cost per room | BQ3: cost per guest
B4: 2013 | C4: 2014 | D4: 2013 | E4: 2014 | F4: 2013 | G4: 2014 | H4: 2013 | I4: 2014 | J4: 2009 | K4: 2010 | L4: 2009 | M4: 2010 | O4: 2009 | P4: 2010 | Q4: 2009 | R4: 2010 | S4: 2009 | T4: 2010 | U4: 2009 | V4: 2010 | W4: 2009 | X4: 2010 | Y4: 2009 | Z4: 2010 | AA4: 2009 | AB4: 2010 | AC4: 2009 | AD4: 2010
A5: 1 | B5: 33600 | C5: =Elect!J6 -> 5837 | D5: 0 | E5: =Elect!M6 -> 2017 | F5: 20 | G5: =Elect!O6 -> 1600 | H5: 800 | I5: =Water!C7 -> 284.2 | J5: 0 | K5: =Water!E7 -> 249.4 | L5: 0 | M5: =Water!#REF! -> #REF! | N5: =Water!#REF! -> #REF! | O5: 1005 | P5: =Water!H7 -> 539.4 | Q5: 114 | R5: =Water!O7 -> 0 | S5: 13 | T5: =Water!#REF! -> #REF! | U5: 147 | V5: =Water!#REF! -> #REF! | W5: 755 | X5: =Water!Q7 -> 312.852 | Y5: 0 | Z5: =Water!#REF! -> #REF! | AA5: 0 | AB5: 0 | AC5: 690 | AD5: =Water!#REF! -> #REF! | AE5: =Water!#REF! -> #REF! | AF5: =Water!#REF! -> #REF! | AG5: =Gas!#REF! -> #REF! | AH5: =Gas!C7 -> 1473.4 | AI5: =Gas!#REF! -> #REF! | AJ5: =Gas!J7 -> 725.4 | AK5: =Gas!#REF! -> #REF! | AL5: =Gas!#REF! -> #REF! | AM5: =Gas!#REF! -> #REF! | AN5: =Gas!#REF! -> #REF! | AO5: =Gas!#REF! -> #REF! | AP5: =Gas!#REF! -> #REF! | AQ5: =Gas!#REF! -> #REF! | AR5: =Gas!#REF! -> #REF! | AS5: =Gas!#REF! -> #REF! | AT5: =Elect!BR6 -> 141 | AU5: =Elect!BP6 -> 125 | AV5: =Elect!#REF! -> #REF! | AW5: =Elect!BR6 -> 141 | AX5: 48.695652 | AY5: 24.705882 | AZ5: 8835.4834 | BA5: 12.805048 | BB5: 6.496679 | BC5: =Elect!#REF! -> #REF! | BD5: =Elect!#REF! -> #REF! | BE5: =Elect!#REF! -> #REF! | BF5: =Elect!#REF! -> #REF! | BG5: =Elect!#REF! -> #REF! | BH5: 1.142029 | BI5: 0.57941176 | BJ5: 4569.1158 | BK5: 6.6219069 | BL5: 3.3596439 | BM5: =Water!U7 -> 2.325 | BN5: =Water!W7 -> #DIV/0! | BO5: =Water!X7 -> 2157.6 | BP5: =Water!Y7 -> 9.3 | BQ5: =Water!Z7 -> 0
A6: 2 | B6: 31200 | C6: =Elect!J7 -> 6605 | D6: 0 | E6: =Elect!M7 -> 2411 | F6: 20 | G6: =Elect!O7 -> 1471 | H6: 936 | I6: =Water!C8 -> 98.6 | J6: 0 | K6: =Water!E8 -> 139.2 | L6: 0 | M6: =Water!#REF! -> #REF! | N6: =Water!#REF! -> #REF! | O6: 1006 | P6: =Water!H8 -> 237.8 | Q6: 113 | R6: =Water!O8 -> 0 | S6: 17 | T6: =Water!#REF! -> #REF! | U6: 140 | V6: =Water!#REF! -> #REF! | W6: 792 | X6: =Water!Q8 -> 137.924 | Y6: 0 | Z6: =Water!#REF! -> #REF! | AA6: 0 | AB6: 0 | AC6: 370 | AD6: =Water!#REF! -> #REF! | AE6: =Water!#REF! -> #REF! | AF6: =Water!#REF! -> #REF! | AG6: =Gas!B7 -> 8276184 | AH6: =Gas!C8 -> 1473.4 | AI6: =Gas!#REF! -> #REF! | AJ6: =Gas!J8 -> 319.8 | AK6: =Gas!#REF! -> #REF! | AL6: =Gas!#REF! -> #REF! | AM6: =Gas!#REF! -> #REF! | AN6: =Gas!#REF! -> #REF! | AO6: =Gas!#REF! -> #REF! | AP6: =Gas!#REF! -> #REF! | AQ6: =Gas!#REF! -> #REF! | AR6: =Gas!#REF! -> #REF! | AS6: =Gas!#REF! -> #REF! | AT6: =Elect!BR7 -> 164 | AU6: =Elect!BP7 -> 157 | AX6: 47.416413 | AY6: 23.981553 | AZ6: 8299.2754 | BA6: 12.612881 | BB6: 6.379151 | BC6: =Elect!BQ7 -> 513915 | BD6: =Elect!#REF! -> #REF! | BE6: =Elect!#REF! -> #REF! | BF6: =Elect!#REF! -> #REF! | BG6: =Elect!#REF! -> #REF! | BH6: 1.2021277 | BI6: 0.60799385 | BJ6: 5345.8654 | BK6: 8.1244156 | BL6: 4.1090434 | BM6: =Water!U8 -> 1.2450262 | BN6: =Water!W8 -> #DIV/0! | BO6: =Water!X8 -> 951.2 | BP6: =Water!Y8 -> 4.9801047 | BQ6: =Water!Z8 -> #DIV/0!
A7: 3 | B7: 31200 | C7: =Elect!J8 -> 6146 | D7: 0 | E7: =Elect!M8 -> 2301 | F7: 20 | G7: =Elect!O8 -> 1408 | H7: 685 | I7: =Water!C9 -> 150.8 | J7: 0 | K7: =Water!E9 -> 197.2 | L7: 0 | M7: =Water!#REF! -> #REF! | N7: =Water!#REF! -> #REF! | O7: 902 | P7: =Water!H9 -> 348 | Q7: 126 | R7: =Water!O9 -> 0 | S7: 26 | T7: =Water!#REF! -> #REF! | U7: 134 | V7: =Water!#REF! -> #REF! | W7: 766 | X7: =Water!Q9 -> 201.84 | Y7: 0 | Z7: =Water!#REF! -> #REF! | AA7: 0 | AB7: 0 | AC7: 740 | AD7: =Water!#REF! -> #REF! | AE7: =Water!#REF! -> #REF! | AF7: =Water!#REF! -> #REF! | AG7: =Gas!B9 -> 8278964 | AH7: =Gas!C9 -> 1473.4 | AI7: =Gas!#REF! -> #REF! | AJ7: =Gas!J9 -> 397.8 | AK7: =Gas!#REF! -> #REF! | AL7: =Gas!#REF! -> #REF! | AM7: =Gas!#REF! -> #REF! | AN7: =Gas!#REF! -> #REF! | AO7: =Gas!#REF! -> #REF! | AP7: =Gas!#REF! -> #REF! | AQ7: =Gas!#REF! -> #REF! | AR7: =Gas!#REF! -> #REF! | AS7: =Gas!#REF! -> #REF! | AT7: =Elect!BR8 -> 149 | AU7: =Elect!BP8 -> 137 | AX7: 47.926267 | AY7: 24.223602 | AZ7: 8299.2754 | BA7: 12.748503 | BB7: 6.4435368 | BC7: =Elect!BQ8 -> 514064 | BD7: =Elect!#REF! -> #REF! | BE7: =Elect!#REF! -> #REF! | BF7: =Elect!#REF! -> #REF! | BG7: =Elect!#REF! -> #REF! | BH7: 1.0875576 | BI7: 0.54968944 | BJ7: 3912.3054 | BK7: 6.0096857 | BL7: 3.0375042 | BM7: =Water!U9 -> 1.5890411 | BN7: =Water!W9 -> #DIV/0! | BO7: =Water!X9 -> 1392 | BP7: =Water!Y9 -> 6.3561644 | BQ7: =Water!Z9 -> #DIV/0!
A8: 4 | B8: 33600 | C8: =Elect!J9 -> 6575 | D8: 0 | E8: =Elect!M9 -> 2460 | F8: 20 | G8: =Elect!O9 -> 1534 | H8: 786 | I8: =Water!C10 -> 145 | J8: 0 | K8: =Water!E10 -> 191.4 | L8: 0 | M8: =Water!#REF! -> #REF! | N8: =Water!#REF! -> #REF! | O8: 930 | P8: =Water!H10 -> 336.4 | Q8: 153 | R8: =Water!O10 -> 0 | S8: 46 | T8: =Water!#REF! -> #REF! | U8: 150 | V8: =Water!#REF! -> #REF! | W8: 766 | X8: =Water!Q10 -> 195.112 | Y8: 0 | Z8: =Water!#REF! -> #REF! | AA8: 0 | AB8: 0 | AC8: 820 | AD8: =Water!#REF! -> #REF! | AE8: =Water!#REF! -> #REF! | AF8: =Water!#REF! -> #REF! | AG8: =Gas!B10 -> 8280354 | AH8: =Gas!C10 -> 1473.4 | AI8: =Gas!#REF! -> #REF! | AJ8: =Gas!J10 -> 666.9 | AK8: =Gas!#REF! -> #REF! | AL8: =Gas!#REF! -> #REF! | AM8: =Gas!#REF! -> #REF! | AN8: =Gas!#REF! -> #REF! | AO8: =Gas!#REF! -> #REF! | AP8: =Gas!#REF! -> #REF! | AQ8: =Gas!#REF! -> #REF! | AR8: =Gas!#REF! -> #REF! | AS8: =Gas!#REF! -> #REF! | AT8: =Elect!BR9 -> 151 | AU8: =Elect!BP9 -> 146 | AX8: 51.06383 | AY8: 25.866051 | AZ8: 8835.4834 | BA8: 13.427786 | BB8: 6.8017578 | BC8: =Elect!BQ9 -> 514215 | BD8: =Elect!#REF! -> #REF! | BE8: =Elect!#REF! -> #REF! | BF8: =Elect!#REF! -> #REF! | BG8: =Elect!#REF! -> #REF! | BH8: 1.2218845 | BI8: 0.61893764 | BJ8: 4489.1562 | BK8: 6.8224259 | BL8: 3.4558555 | BM8: =Water!U10 -> 1.6409756 | BN8: =Water!W10 -> #DIV/0! | BO8: =Water!X10 -> 1345.6 | BP8: =Water!Y10 -> 6.5639024 | BQ8: =Water!Z10 -> #DIV/0!
A9: 5 | B9: 31200 | C9: =Elect!J10 -> 6573 | D9: 0 | E9: =Elect!M10 -> 2539 | F9: 20 | G9: =Elect!O10 -> 1580 | H9: 789 | I9: =Water!C11 -> 145 | J9: 0 | K9: =Water!E11 -> 191.4 | L9: 0 | M9: =Water!#REF! -> #REF! | N9: =Water!#REF! -> #REF! | O9: 1003 | P9: =Water!H11 -> 336.4 | Q9: 102 | R9: =Water!O11 -> 0 | S9: 8 | T9: =Water!#REF! -> #REF! | U9: 130 | V9: =Water!#REF! -> #REF! | W9: 735 | X9: =Water!Q11 -> 195.112 | Y9: 0 | Z9: =Water!#REF! -> #REF! | AA9: 0 | AB9: 0 | AC9: 640 | AD9: =Water!#REF! -> #REF! | AE9: =Water!#REF! -> #REF! | AF9: =Water!#REF! -> #REF! | AG9: =Gas!B11 -> 8281744 | AH9: =Gas!C11 -> 1473.4 | AI9: =Gas!#REF! -> #REF! | AJ9: =Gas!J11 -> 542.1 | AK9: =Gas!#REF! -> #REF! | AL9: =Gas!#REF! -> #REF! | AM9: =Gas!#REF! -> #REF! | AN9: =Gas!#REF! -> #REF! | AO9: =Gas!#REF! -> #REF! | AP9: =Gas!#REF! -> #REF! | AQ9: =Gas!#REF! -> #REF! | AR9: =Gas!#REF! -> #REF! | AS9: =Gas!#REF! -> #REF! | AT9: =Elect!BR10 -> 161 | AU9: =Elect!BP10 -> 127 | AX9: 49.840256 | AY9: 25.181598 | AZ9: 8299.2754 | BA9: 13.257628 | BB9: 6.698366 | BC9: =Elect!BQ10 -> 514376 | BD9: =Elect!#REF! -> #REF! | BE9: =Elect!#REF! -> #REF! | BF9: =Elect!#REF! -> #REF! | BG9: =Elect!#REF! -> #REF! | BH9: 1.1980831 | BI9: 0.60532688 | BJ9: 4506.2904 | BK9: 7.198547 | BL9: 3.6370383 | BM9: =Water!U11 -> 1.6904523 | BN9: =Water!W11 -> #DIV/0! | BO9: =Water!X11 -> 1345.6 | BP9: =Water!Y11 -> 6.761809 | BQ9: =Water!Z11 -> #DIV/0!
A10: 6 | B10: 33600 | C10: =Elect!J11 -> 5578 | D10: 0 | E10: =Elect!M11 -> 2165 | F10: 20 | G10: =Elect!O11 -> 1333 | H10: 805 | I10: =Water!C12 -> 145 | J10: 0 | K10: =Water!E12 -> 191.4 | L10: 0 | M10: =Water!#REF! -> #REF! | N10: =Water!#REF! -> #REF! | O10: 1004 | P10: =Water!H12 -> 336.4 | Q10: 115 | R10: =Water!O12 -> 0 | S10: 21 | T10: =Water!#REF! -> #REF! | U10: 141 | V10: =Water!#REF! -> #REF! | W10: 725 | X10: =Water!Q12 -> 195.112 | Y10: 0 | Z10: =Water!#REF! -> #REF! | AA10: 0 | AB10: 0 | AC10: 510 | AD10: =Water!#REF! -> #REF! | AE10: =Water!#REF! -> #REF! | AF10: =Water!#REF! -> #REF! | AG10: =Gas!B12 -> 8283134 | AH10: =Gas!C12 -> 1473.4 | AI10: =Gas!#REF! -> #REF! | AJ10: =Gas!J12 -> 401.7 | AK10: =Gas!#REF! -> #REF! | AL10: =Gas!#REF! -> #REF! | AM10: =Gas!#REF! -> #REF! | AN10: =Gas!#REF! -> #REF! | AO10: =Gas!#REF! -> #REF! | AP10: =Gas!#REF! -> #REF! | AQ10: =Gas!#REF! -> #REF! | AR10: =Gas!#REF! -> #REF! | AS10: =Gas!#REF! -> #REF! | AT10: =Elect!BR11 -> 147 | AU10: =Elect!BP11 -> 137 | AX10: 47.457627 | AY10: 23.512946 | AZ10: 8835.4834 | BA10: 12.479496 | BB10: 6.1829835 | BC10: =Elect!BQ11 -> 514523 | BD10: =Elect!#REF! -> #REF! | BE10: =Elect!#REF! -> #REF! | BF10: =Elect!#REF! -> #REF! | BG10: =Elect!#REF! -> #REF! | BH10: 1.1567797 | BI10: 0.57312806 | BJ10: 4597.6727 | BK10: 6.4938881 | BL10: 3.2174057 | BM10: =Water!U12 -> 1.6571429 | BN10: =Water!W12 -> #DIV/0! | BO10: =Water!X12 -> 1345.6 | BP10: =Water!Y12 -> 6.6285714 | BQ10: =Water!Z12 -> #DIV/0!
A11: 7 | B11: 31200 | C11: =Elect!J12 -> 5618 | D11: 0 | E11: =Elect!M12 -> 2159 | F11: 20 | G11: =Elect!O12 -> 1357 | H11: 871 | I11: =Water!C13 -> 150.8 | J11: 0 | K11: =Water!E13 -> 203 | L11: 0 | M11: =Water!#REF! -> #REF! | N11: =Water!#REF! -> #REF! | O11: 837 | P11: =Water!H13 -> 353.8 | Q11: 113 | R11: =Water!O13 -> 0 | S11: 1 | T11: =Water!#REF! -> #REF! | U11: 151 | V11: =Water!#REF! -> #REF! | W11: 732 | X11: =Water!Q13 -> 205.204 | Y11: 0 | Z11: =Water!#REF! -> #REF! | AA11: 0 | AB11: 0 | AC11: 1010 | AD11: =Water!#REF! -> #REF! | AE11: =Water!#REF! -> #REF! | AF11: =Water!#REF! -> #REF! | AG11: =Gas!B13 -> 8284524 | AH11: =Gas!C13 -> 1473.4 | AI11: =Gas!#REF! -> #REF! | AJ11: =Gas!J13 -> 401.7 | AK11: =Gas!#REF! -> #REF! | AL11: =Gas!#REF! -> #REF! | AM11: =Gas!#REF! -> #REF! | AN11: =Gas!#REF! -> #REF! | AO11: =Gas!#REF! -> #REF! | AP11: =Gas!#REF! -> #REF! | AQ11: =Gas!#REF! -> #REF! | AR11: =Gas!#REF! -> #REF! | AS11: =Gas!#REF! -> #REF! | AT11: =Elect!BR12 -> 154 | AU11: =Elect!BP12 -> 139 | AX11: 43.454039 | AY11: 21.517241 | AZ11: 8299.2754 | BA11: 11.558879 | BB11: 5.7236382 | BC11: =Elect!BQ12 -> 514677 | BD11: =Elect!#REF! -> #REF! | BE11: =Elect!#REF! -> #REF! | BF11: =Elect!#REF! -> #REF! | BG11: =Elect!#REF! -> #REF! | BH11: 1.1713092 | BI11: 0.58 | BJ11: 4974.6248 | BK11: 6.9284468 | BL11: 3.4307757 | BM11: =Water!U13 -> 1.5184549 | BN11: =Water!W13 -> #DIV/0! | BO11: =Water!X13 -> 1415.2 | BP11: =Water!Y13 -> 6.0738197 | BQ11: =Water!Z13 -> #DIV/0!
A12: 8 | B12: 33600 | C12: =Elect!J13 -> 5864 | D12: 0 | E12: =Elect!M13 -> 2216 | F12: 20 | G12: =Elect!O13 -> 1374 | H12: 963 | I12: =Water!C14 -> 150.8 | J12: 0 | K12: =Water!E14 -> 203 | L12: 0 | M12: =Water!#REF! -> #REF! | N12: =Water!#REF! -> #REF! | O12: 1000 | P12: =Water!H14 -> 353.8 | Q12: 128 | R12: =Water!O14 -> 0 | S12: 24 | T12: =Water!#REF! -> #REF! | U12: 148 | V12: =Water!#REF! -> #REF! | W12: 719 | X12: =Water!Q14 -> 205.204 | Y12: 0 | Z12: =Water!#REF! -> #REF! | AA12: 0 | AB12: 0 | AC12: 630 | AD12: =Water!#REF! -> #REF! | AE12: =Water!#REF! -> #REF! | AF12: =Water!#REF! -> #REF! | AG12: =Gas!B14 -> 8285914 | AH12: =Gas!C14 -> 1473.4 | AI12: =Gas!#REF! -> #REF! | AJ12: =Gas!J14 -> 401.7 | AK12: =Gas!#REF! -> #REF! | AL12: =Gas!#REF! -> #REF! | AM12: =Gas!#REF! -> #REF! | AN12: =Gas!#REF! -> #REF! | AO12: =Gas!#REF! -> #REF! | AP12: =Gas!#REF! -> #REF! | AQ12: =Gas!#REF! -> #REF! | AR12: =Gas!#REF! -> #REF! | AS12: =Gas!#REF! -> #REF! | AT12: =Elect!BR13 -> 157 | AU12: =Elect!BP13 -> 130 | AX12: 48.837209 | AY12: 24.086022 | AZ12: 8835.4834 | BA12: 12.842272 | BB12: 6.3336799 | BC12: =Elect!BQ13 -> 514834 | BD12: =Elect!#REF! -> #REF! | BE12: =Elect!#REF! -> #REF! | BF12: =Elect!#REF! -> #REF! | BG12: =Elect!#REF! -> #REF! | BH12: 1.2194767 | BI12: 0.60143369 | BJ12: 5500.0731 | BK12: 7.9942923 | BL12: 3.9427047 | BM12: =Water!U14 -> 1.4865546 | BN12: =Water!W14 -> #DIV/0! | BO12: =Water!X14 -> 1415.2 | BP12: =Water!Y14 -> 5.9462185 | BQ12: =Water!Z14 -> #DIV/0!
A13: 9 | B13: 33600 | C13: =Elect!J14 -> 5583 | D13: 0 | E13: =Elect!M14 -> 2336 | F13: 20 | G13: =Elect!O14 -> 1442 | H13: 790 | I13: =Water!C15 -> 145 | J13: 0 | K13: =Water!E15 -> 191.4 | L13: 0 | M13: =Water!#REF! -> #REF! | N13: =Water!#REF! -> #REF! | O13: 841 | P13: =Water!H15 -> 336.4 | Q13: 127 | R13: =Water!O15 -> 0 | S13: 21 | T13: =Water!#REF! -> #REF! | U13: 139 | V13: =Water!#REF! -> #REF! | W13: 701 | X13: =Water!Q15 -> 195.112 | Y13: 0 | Z13: =Water!#REF! -> #REF! | AA13: 0 | AB13: 0 | AC13: 440 | AD13: =Water!#REF! -> #REF! | AE13: =Water!#REF! -> #REF! | AF13: =Water!#REF! -> #REF! | AG13: =Gas!B15 -> 8287304 | AH13: =Gas!C15 -> 1473.4 | AI13: =Gas!#REF! -> #REF! | AJ13: =Gas!J15 -> 401.7 | AK13: =Gas!#REF! -> #REF! | AL13: =Gas!#REF! -> #REF! | AM13: =Gas!#REF! -> #REF! | AN13: =Gas!#REF! -> #REF! | AO13: =Gas!#REF! -> #REF! | AP13: =Gas!#REF! -> #REF! | AQ13: =Gas!#REF! -> #REF! | AR13: =Gas!#REF! -> #REF! | AS13: =Gas!#REF! -> #REF! | AT13: =Elect!BR14 -> 152 | AU13: =Elect!BP14 -> 132 | AX13: 49.194729 | AY13: 24.1033 | AZ13: 8835.4834 | BA13: 12.936286 | BB13: 6.3382234 | BC13: =Elect!BQ14 -> 514986 | BD13: =Elect!#REF! -> #REF! | BE13: =Elect!#REF! -> #REF! | BF13: =Elect!#REF! -> #REF! | BG13: =Elect!#REF! -> #REF! | BH13: 1.1903367 | BI13: 0.58321377 | BJ13: 4512.0018 | BK13: 6.606152 | BL13: 3.2367301 | BM13: =Water!U15 -> 1.5290909 | BN13: =Water!W15 -> #DIV/0! | BO13: =Water!X15 -> 1345.6 | BP13: =Water!Y15 -> 6.1163636 | BQ13: =Water!Z15 -> #DIV/0!
A14: 10 | B14: 31200 | C14: =Elect!J15 -> 7367 | D14: 0 | E14: =Elect!M15 -> 2891 | F14: 20 | G14: =Elect!O15 -> 1593 | H14: 792 | I14: =Water!C16 -> 162.4 | J14: 0 | K14: =Water!E16 -> 214.6 | L14: 0 | M14: =Water!#REF! -> #REF! | N14: =Water!#REF! -> #REF! | O14: 972 | P14: =Water!H16 -> 377 | Q14: 126 | R14: =Water!O16 -> 0 | S14: 18 | T14: =Water!#REF! -> #REF! | U14: 145 | V14: =Water!#REF! -> #REF! | W14: 756 | X14: =Water!Q16 -> 218.66 | Y14: 0 | Z14: =Water!#REF! -> #REF! | AA14: 0 | AB14: 0 | AC14: 580 | AD14: =Water!#REF! -> #REF! | AE14: =Water!#REF! -> #REF! | AF14: =Water!#REF! -> #REF! | AG14: =Gas!B16 -> 8288694 | AH14: =Gas!C16 -> 1473.4 | AI14: =Gas!#REF! -> #REF! | AJ14: =Gas!J16 -> 401.7 | AK14: =Gas!#REF! -> #REF! | AL14: =Gas!#REF! -> #REF! | AM14: =Gas!#REF! -> #REF! | AN14: =Gas!#REF! -> #REF! | AO14: =Gas!#REF! -> #REF! | AP14: =Gas!#REF! -> #REF! | AQ14: =Gas!#REF! -> #REF! | AR14: =Gas!#REF! -> #REF! | AS14: =Gas!#REF! -> #REF! | AT14: =Elect!BR15 -> 151 | AU14: =Elect!BP15 -> 140 | AX14: 49.52381 | AY14: 24.781573 | AZ14: 8299.2754 | BA14: 13.173453 | BB14: 6.5919582 | BC14: =Elect!BQ15 -> 515137 | BD14: =Elect!#REF! -> #REF! | BE14: =Elect!#REF! -> #REF! | BF14: =Elect!#REF! -> #REF! | BG14: =Elect!#REF! -> #REF! | BH14: 1.2730159 | BI14: 0.6370135 | BJ14: 4469.9646 | BK14: 7.0951819 | BL14: 3.5504087 | BM14: =Water!U16 -> 1.7867299 | BN14: =Water!W16 -> #DIV/0! | BO14: =Water!X16 -> 1508 | BP14: =Water!Y16 -> 7.1469194 | BQ14: =Water!Z16 -> #DIV/0!
A15: 11 | B15: 33600 | C15: =Elect!J16 -> 6246 | D15: 0 | E15: =Elect!M16 -> 2525 | F15: 20 | G15: =Elect!O16 -> 1353 | H15: 817 | I15: =Water!C17 -> 162.4 | J15: 0 | K15: =Water!E17 -> 220.4 | L15: 0 | M15: =Water!#REF! -> #REF! | N15: =Water!#REF! -> #REF! | O15: 875 | P15: =Water!H17 -> 382.8 | Q15: 122 | R15: =Water!O17 -> 0 | S15: 20 | T15: =Water!#REF! -> #REF! | U15: 156 | V15: =Water!#REF! -> #REF! | W15: 712 | X15: =Water!Q17 -> 222.024 | Y15: 0 | Z15: =Water!#REF! -> #REF! | AA15: 0 | AB15: 0 | AC15: 850 | AD15: =Water!#REF! -> #REF! | AE15: =Water!#REF! -> #REF! | AF15: =Water!#REF! -> #REF! | AG15: =Gas!#REF! -> #REF! | AH15: =Gas!C17 -> 1473.4 | AI15: =Gas!#REF! -> #REF! | AJ15: =Gas!J17 -> 401.7 | AK15: =Gas!#REF! -> #REF! | AL15: =Gas!#REF! -> #REF! | AM15: =Gas!#REF! -> #REF! | AN15: =Gas!#REF! -> #REF! | AO15: =Gas!#REF! -> #REF! | AP15: =Gas!#REF! -> #REF! | AQ15: =Gas!#REF! -> #REF! | AR15: =Gas!#REF! -> #REF! | AS15: =Gas!#REF! -> #REF! | AT15: =Elect!BR16 -> 138 | AU15: =Elect!BP16 -> 127 | AX15: 53.333333 | AY15: 26.751592 | AZ15: 8835.4834 | BA15: 14.024577 | BB15: 7.0346206 | BC15: =Elect!BQ16 -> 515275 | BD15: =Elect!#REF! -> #REF! | BE15: =Elect!#REF! -> #REF! | BF15: =Elect!#REF! -> #REF! | BG15: =Elect!#REF! -> #REF! | BH15: 1.3460317 | BI15: 0.67515924 | BJ15: 4666.2095 | BK15: 7.4066817 | BL15: 3.7151349 | BM15: =Water!U17 -> 1.9044776 | BN15: =Water!W17 -> #DIV/0! | BO15: =Water!X17 -> 1531.2 | BP15: =Water!Y17 -> 7.6179104 | BQ15: =Water!Z17 -> #DIV/0!
A16: 12 | B16: 33600 | C16: =Elect!J17 -> 6655 | D16: 0 | E16: =Elect!M17 -> 2688 | F16: 20 | G16: =Elect!O17 -> 1486 | H16: 907 | I16: =Water!C18 -> 162.4 | J16: 0 | K16: =Water!E18 -> 220.4 | L16: 0 | M16: =Water!#REF! -> #REF! | N16: =Water!#REF! -> #REF! | O16: 965 | P16: =Water!H18 -> 382.8 | Q16: 125 | R16: =Water!O18 -> 0 | S16: 4 | T16: =Water!#REF! -> #REF! | U16: 167 | V16: =Water!#REF! -> #REF! | W16: 705 | X16: =Water!Q18 -> 222.024 | Y16: 0 | Z16: =Water!#REF! -> #REF! | AA16: 0 | AB16: 0 | AC16: 880 | AD16: =Water!#REF! -> #REF! | AE16: =Water!#REF! -> #REF! | AF16: =Water!#REF! -> #REF! | AG16: =Gas!B18 -> 8291474 | AH16: =Gas!C18 -> 1473.4 | AI16: =Gas!#REF! -> #REF! | AJ16: =Gas!J18 -> 401.7 | AK16: =Gas!#REF! -> #REF! | AL16: =Gas!#REF! -> #REF! | AM16: =Gas!#REF! -> #REF! | AN16: =Gas!#REF! -> #REF! | AO16: =Gas!#REF! -> #REF! | AP16: =Gas!#REF! -> #REF! | AQ16: =Gas!#REF! -> #REF! | AR16: =Gas!#REF! -> #REF! | AS16: =Gas!#REF! -> #REF! | AT16: =Elect!BR17 -> 139 | AU16: =Elect!BP17 -> 136 | AX16: 50.45045 | AY16: 25.339367 | AZ16: 8835.4834 | BA16: 13.266492 | BB16: 6.6632605 | BC16: =Elect!BQ17 -> 515414 | BD16: =Elect!#REF! -> #REF! | BE16: =Elect!#REF! -> #REF! | BF16: =Elect!#REF! -> #REF! | BG16: =Elect!#REF! -> #REF! | BH16: 1.2162162 | BI16: 0.61085973 | BJ16: 5180.235 | BK16: 7.7781306 | BL16: 3.9066629 | BM16: =Water!U18 -> 2.1385475 | BN16: =Water!W18 -> #DIV/0! | BO16: =Water!X18 -> 1531.2 | BP16: =Water!Y18 -> 8.5541899 | BQ16: =Water!Z18 -> #DIV/0!
A17: 13 | B17: 31200 | C17: =Elect!J18 -> 6659 | D17: 0 | E17: =Elect!M18 -> 2694 | F17: 20 | G17: =Elect!O18 -> 1490 | H17: 812 | I17: =Water!C19 -> 162.4 | J17: 0 | K17: =Water!E19 -> 220.4 | L17: 0 | M17: =Water!#REF! -> #REF! | N17: =Water!#REF! -> #REF! | O17: 822 | P17: =Water!H19 -> 382.8 | Q17: 123 | R17: =Water!O19 -> 0 | S17: 7 | T17: =Water!#REF! -> #REF! | U17: 163 | V17: =Water!#REF! -> #REF! | W17: 692 | X17: =Water!Q19 -> 222.024 | Y17: 0 | Z17: =Water!#REF! -> #REF! | AA17: 0 | AB17: 0 | AC17: 460 | AD17: =Water!#REF! -> #REF! | AE17: =Water!#REF! -> #REF! | AF17: =Water!#REF! -> #REF! | AG17: =Gas!B19 -> 8292864 | AH17: =Gas!C19 -> 1473.4 | AI17: =Gas!#REF! -> #REF! | AJ17: =Gas!J19 -> 401.7 | AK17: =Gas!#REF! -> #REF! | AL17: =Gas!#REF! -> #REF! | AM17: =Gas!#REF! -> #REF! | AN17: =Gas!#REF! -> #REF! | AO17: =Gas!#REF! -> #REF! | AP17: =Gas!#REF! -> #REF! | AQ17: =Gas!#REF! -> #REF! | AR17: =Gas!#REF! -> #REF! | AS17: =Gas!#REF! -> #REF! | AT17: =Elect!BR18 -> 145 | AU17: =Elect!BP18 -> 141 | AX17: 46.567164 | AY17: 23.214286 | AZ17: 8299.2754 | BA17: 12.386978 | BB17: 6.1750561 | BC17: =Elect!BQ18 -> 515559 | BD17: =Elect!#REF! -> #REF! | BE17: =Elect!#REF! -> #REF! | BF17: =Elect!#REF! -> #REF! | BG17: =Elect!#REF! -> #REF! | BH17: 1.0850746 | BI17: 0.54092262 | BJ17: 4637.6525 | BK17: 6.9218694 | BL17: 3.4506343 | BM17: =Water!U19 -> 1.8492754 | BN17: =Water!W19 -> #DIV/0! | BO17: =Water!X19 -> 1531.2 | BP17: =Water!Y19 -> 7.3971014 | BQ17: =Water!Z19 -> #DIV/0!
A18: 14 | B18: 33600 | C18: =Elect!J19 -> 7066 | D18: 0 | E18: =Elect!M19 -> 2500 | F18: 30 | G18: =Elect!O19 -> 1500 | H18: 810 | I18: =Water!C20 -> 121.8 | J18: 0 | K18: =Water!E20 -> 150.8 | L18: 0 | M18: =Water!#REF! -> #REF! | N18: =Water!#REF! -> #REF! | O18: 943 | P18: =Water!H20 -> 279.56 | Q18: 118 | R18: =Water!O20 -> 0 | S18: 18 | T18: =Water!#REF! -> #REF! | U18: 152 | V18: =Water!#REF! -> #REF! | W18: 708 | X18: =Water!Q20 -> 162.1448 | Y18: 0 | Z18: =Water!#REF! -> #REF! | AA18: 0 | AB18: 0 | AC18: 490 | AD18: =Water!#REF! -> #REF! | AE18: =Water!#REF! -> #REF! | AF18: =Water!#REF! -> #REF! | AG18: =Gas!B20 -> 8294254 | AH18: =Gas!C20 -> 1473.4 | AI18: =Gas!#REF! -> #REF! | AJ18: =Gas!J20 -> 401.7 | AK18: =Gas!#REF! -> #REF! | AL18: =Gas!#REF! -> #REF! | AM18: =Gas!#REF! -> #REF! | AN18: =Gas!#REF! -> #REF! | AO18: =Gas!#REF! -> #REF! | AP18: =Gas!#REF! -> #REF! | AQ18: =Gas!#REF! -> #REF! | AR18: =Gas!#REF! -> #REF! | AS18: =Gas!#REF! -> #REF! | AT18: =Elect!BR19 -> 129 | AU18: =Elect!BP19 -> 128 | AX18: 47.795164 | AY18: 24.207493 | AZ18: 8835.4834 | BA18: 12.568255 | BB18: 6.3656221 | BC18: =Elect!BQ6 -> 513751 | BD18: =Elect!#REF! -> #REF! | BE18: =Elect!#REF! -> #REF! | BF18: =Elect!#REF! -> #REF! | BG18: =Elect!#REF! -> #REF! | BH18: 1.1024182 | BI18: 0.55835735 | BJ18: 4626.2297 | BK18: 6.5806966 | BL18: 3.3330185 | BM18: =Water!U20 -> 1.3002791 | BN18: =Water!W20 -> #DIV/0! | BO18: =Water!X20 -> 1118.24 | BP18: =Water!Y20 -> 5.2011163 | BQ18: =Water!Z20 -> #DIV/0!
A19: 15 | B19: 31200 | C19: =Elect!J20 -> 6511 | D19: 0 | E19: =Elect!M20 -> 2501 | F19: 20 | G19: =Elect!O20 -> 1503 | H19: 841 | I19: =Water!C21 -> 121.8 | J19: 0 | K19: =Water!E21 -> 150.8 | L19: 0 | M19: =Water!#REF! -> #REF! | N19: =Water!#REF! -> #REF! | O19: 947 | P19: =Water!H21 -> 272.6 | Q19: 131 | R19: =Water!O21 -> 0 | S19: 23 | T19: =Water!#REF! -> #REF! | U19: 166 | V19: =Water!#REF! -> #REF! | W19: 787 | X19: =Water!Q21 -> 158.108 | Y19: 0 | Z19: =Water!#REF! -> #REF! | AA19: 0 | AB19: 0 | AC19: 730 | AD19: =Water!#REF! -> #REF! | AE19: =Water!#REF! -> #REF! | AF19: =Water!#REF! -> #REF! | AG19: =Gas!B21 -> 8295644 | AH19: =Gas!C21 -> 1473.4 | AI19: =Gas!#REF! -> #REF! | AJ19: =Gas!J21 -> 401.7 | AK19: =Gas!#REF! -> #REF! | AL19: =Gas!#REF! -> #REF! | AM19: =Gas!#REF! -> #REF! | AN19: =Gas!#REF! -> #REF! | AO19: =Gas!#REF! -> #REF! | AP19: =Gas!#REF! -> #REF! | AQ19: =Gas!#REF! -> #REF! | AR19: =Gas!#REF! -> #REF! | AS19: =Gas!#REF! -> #REF! | AT19: =Elect!BR20 -> 138 | AU19: =Elect!BP20 -> 139 | AX19: 41.6 | AY19: 20.995962 | AZ19: 8299.2754 | BA19: 11.065701 | BB19: 5.5849767 | BC19: =Elect!BQ20 -> 515826 | BD19: =Elect!#REF! -> #REF! | BE19: =Elect!#REF! -> #REF! | BF19: =Elect!#REF! -> #REF! | BG19: =Elect!#REF! -> #REF! | BH19: 1.1506667 | BI19: 0.58114478 | BJ19: 4803.283 | BK19: 6.4043773 | BL19: 3.234534 | BM19: =Water!U21 -> 1.3837563 | BN19: =Water!W21 -> #DIV/0! | BO19: =Water!X21 -> 1090.4 | BP19: =Water!Y21 -> 5.5350254 | BQ19: =Water!Z21 -> #DIV/0!
A20: 16 | B20: 36000 | C20: =Elect!J21 -> 8017 | D20: 0 | E20: =Elect!M21 -> 3533 | F20: 20 | G20: =Elect!O21 -> 1542 | H20: 932 | I20: =Water!C22 -> 185.6 | J20: 0 | K20: =Water!E22 -> 255.2 | L20: 0 | M20: =Water!#REF! -> #REF! | N20: =Water!#REF! -> #REF! | O20: 998 | P20: =Water!H22 -> 440.8 | Q20: 136 | R20: =Water!O22 -> 0 | S20: 22 | T20: =Water!#REF! -> #REF! | U20: 162 | V20: =Water!#REF! -> #REF! | W20: 703 | X20: =Water!Q22 -> 255.664 | Y20: 0 | Z20: =Water!#REF! -> #REF! | AA20: 0 | AB20: 0 | AC20: 600 | AD20: =Water!#REF! -> #REF! | AE20: =Water!#REF! -> #REF! | AF20: =Water!#REF! -> #REF! | AG20: =Gas!B22 -> 8297034 | AH20: =Gas!C22 -> 1473.4 | AI20: =Gas!#REF! -> #REF! | AJ20: =Gas!J22 -> 401.7 | AK20: =Gas!#REF! -> #REF! | AL20: =Gas!#REF! -> #REF! | AM20: =Gas!#REF! -> #REF! | AN20: =Gas!#REF! -> #REF! | AO20: =Gas!#REF! -> #REF! | AP20: =Gas!#REF! -> #REF! | AQ20: =Gas!#REF! -> #REF! | AR20: =Gas!#REF! -> #REF! | AS20: =Gas!#REF! -> #REF! | AT20: =Elect!BR21 -> 137 | AU20: =Elect!BP21 -> 137 | AX20: 48 | AY20: 24.22611 | AZ20: 9371.6914 | BA20: 12.495589 | BB20: 6.3066564 | BC20: =Elect!BQ21 -> 515963 | BD20: =Elect!#REF! -> #REF! | BE20: =Elect!#REF! -> #REF! | BF20: =Elect!#REF! -> #REF! | BG20: =Elect!#REF! -> #REF! | BH20: 1.1626667 | BI20: 0.58720539 | BJ20: 5323.0199 | BK20: 7.0973598 | BL20: 3.5845252 | BM20: =Water!U22 -> 2.5045455 | BN20: =Water!W22 -> #DIV/0! | BO20: =Water!X22 -> 1763.2 | BP20: =Water!Y22 -> 10.018182 | BQ20: =Water!Z22 -> #DIV/0!
A21: 17 | B21: 33600 | C21: =Elect!J22 -> 7722 | D21: 0 | E21: =Elect!M22 -> 3100 | F21: 20 | G21: =Elect!O22 -> 1512 | H21: 972 | I21: =Water!C23 -> 162.4 | J21: 0 | K21: =Water!E23 -> 214.6 | L21: 0 | M21: =Water!#REF! -> #REF! | N21: =Water!#REF! -> #REF! | O21: 998 | P21: =Water!H23 -> 377 | Q21: 136 | R21: =Water!O23 -> 0 | S21: 38 | T21: =Water!#REF! -> #REF! | U21: 137 | V21: =Water!#REF! -> #REF! | W21: 740 | X21: =Water!Q23 -> 218.66 | Y21: 0 | Z21: =Water!#REF! -> #REF! | AA21: 0 | AB21: 0 | AC21: 690 | AD21: =Water!#REF! -> #REF! | AE21: =Water!#REF! -> #REF! | AF21: =Water!#REF! -> #REF! | AG21: =Gas!B23 -> 8298424 | AH21: =Gas!C23 -> 1473.4 | AI21: =Gas!#REF! -> #REF! | AJ21: =Gas!J23 -> 401.7 | AK21: =Gas!#REF! -> #REF! | AL21: =Gas!#REF! -> #REF! | AM21: =Gas!#REF! -> #REF! | AN21: =Gas!#REF! -> #REF! | AO21: =Gas!#REF! -> #REF! | AP21: =Gas!#REF! -> #REF! | AQ21: =Gas!#REF! -> #REF! | AR21: =Gas!#REF! -> #REF! | AS21: =Gas!#REF! -> #REF! | AT21: =Elect!BR22 -> 141 | AU21: =Elect!BP22 -> 136 | AX21: 44.385733 | AY21: 22.207535 | AZ21: 8835.4834 | BA21: 11.671709 | BB21: 5.8397115 | BC21: =Elect!#REF! -> #REF! | BD21: =Elect!#REF! -> #REF! | BE21: =Elect!#REF! -> #REF! | BF21: =Elect!#REF! -> #REF! | BG21: =Elect!#REF! -> #REF! | BH21: 1.1770145 | BI21: 0.58889623 | BJ21: 5551.4757 | BK21: 7.3335213 | BL21: 3.6691842 | BM21: =Water!U23 -> 2.2046784 | BN21: =Water!W23 -> #DIV/0! | BO21: =Water!X23 -> 1508 | BP21: =Water!Y23 -> 8.8187135 | BQ21: =Water!Z23 -> #DIV/0!
A22: 18 | B22: 33600 | C22: =Elect!J23 -> 7812 | D22: 0 | E22: =Elect!M23 -> 3217 | F22: 20 | G22: =Elect!O23 -> 1417 | H22: 864 | I22: =Water!C24 -> 162.4 | J22: 0 | K22: =Water!E24 -> 208.8 | L22: 0 | M22: =Water!#REF! -> #REF! | N22: =Water!#REF! -> #REF! | O22: 1002 | P22: =Water!H24 -> 371.2 | Q22: 118 | R22: =Water!O24 -> 0 | S22: 21 | T22: =Water!#REF! -> #REF! | U22: 133 | V22: =Water!#REF! -> #REF! | W22: 769 | X22: =Water!Q24 -> 215.296 | Y22: 0 | Z22: =Water!#REF! -> #REF! | AA22: 0 | AB22: 0 | AC22: 930 | AD22: =Water!#REF! -> #REF! | AE22: =Water!#REF! -> #REF! | AF22: =Water!#REF! -> #REF! | AG22: =Gas!B24 -> 8299814 | AH22: =Gas!C24 -> 1473.4 | AI22: =Gas!#REF! -> #REF! | AJ22: =Gas!J24 -> 401.7 | AK22: =Gas!#REF! -> #REF! | AL22: =Gas!#REF! -> #REF! | AM22: =Gas!#REF! -> #REF! | AN22: =Gas!#REF! -> #REF! | AO22: =Gas!#REF! -> #REF! | AP22: =Gas!#REF! -> #REF! | AQ22: =Gas!#REF! -> #REF! | AR22: =Gas!#REF! -> #REF! | AS22: =Gas!#REF! -> #REF! | AT22: =Elect!BR23 -> 148 | AU22: =Elect!BP23 -> 143 | AX22: 44.680851 | AY22: 22.459893 | AZ22: 8835.4834 | BA22: 11.749313 | BB22: 5.9060718 | BC22: =Elect!BQ23 -> 516252 | BD22: =Elect!#REF! -> #REF! | BE22: =Elect!#REF! -> #REF! | BF22: =Elect!#REF! -> #REF! | BG22: =Elect!#REF! -> #REF! | BH22: 1.1236702 | BI22: 0.56483957 | BJ22: 4934.645 | BK22: 6.562028 | BL22: 3.2985595 | BM22: =Water!U24 -> 2.5424658 | BN22: =Water!W24 -> #DIV/0! | BO22: =Water!X24 -> 1484.8 | BP22: =Water!Y24 -> 10.169863 | BQ22: =Water!Z24 -> #DIV/0!
A23: 19 | B23: 33600 | C23: =Elect!J24 -> 8105 | D23: 0 | E23: =Elect!M24 -> 3365 | F23: 30 | G23: =Elect!O24 -> 1371 | H23: 894 | I23: =Water!C25 -> 150.8 | J23: 0 | K23: =Water!E25 -> 203 | L23: 0 | M23: =Water!#REF! -> #REF! | N23: =Water!#REF! -> #REF! | O23: 944 | P23: =Water!H25 -> 353.8 | Q23: 110 | R23: =Water!O25 -> 0 | S23: 14 | T23: =Water!#REF! -> #REF! | U23: 155 | V23: =Water!#REF! -> #REF! | W23: 721 | X23: =Water!Q25 -> 205.204 | Y23: 0 | Z23: =Water!#REF! -> #REF! | AA23: 0 | AB23: 0 | AC23: 660 | AD23: =Water!#REF! -> #REF! | AE23: =Water!#REF! -> #REF! | AF23: =Water!#REF! -> #REF! | AG23: =Gas!B25 -> 8301204 | AH23: =Gas!C25 -> 1473.4 | AI23: =Gas!#REF! -> #REF! | AJ23: =Gas!J25 -> 191.1 | AK23: =Gas!#REF! -> #REF! | AL23: =Gas!#REF! -> #REF! | AM23: =Gas!#REF! -> #REF! | AN23: =Gas!#REF! -> #REF! | AO23: =Gas!#REF! -> #REF! | AP23: =Gas!#REF! -> #REF! | AQ23: =Gas!#REF! -> #REF! | AR23: =Gas!#REF! -> #REF! | AS23: =Gas!#REF! -> #REF! | AT23: =Elect!BR24 -> 128 | AU23: =Elect!BP24 -> 127 | AX23: 44.8 | AY23: 22.44489 | AZ23: 8835.4834 | BA23: 11.780645 | BB23: 5.9021265 | BC23: =Elect!BQ24 -> 516380 | BD23: =Elect!#REF! -> #REF! | BE23: =Elect!#REF! -> #REF! | BF23: =Elect!#REF! -> #REF! | BG23: =Elect!#REF! -> #REF! | BH23: 1.1346667 | BI23: 0.56847027 | BJ23: 5105.9869 | BK23: 6.8079825 | BL23: 3.4108129 | BM23: =Water!U25 -> 2.1839506 | BN23: =Water!W25 -> #DIV/0! | BO23: =Water!X25 -> 1415.2 | BP23: =Water!Y25 -> 8.7358025 | BQ23: =Water!Z25 -> #DIV/0!
A24: 20 | B24: 33600 | C24: =Elect!J25 -> 7921 | D24: 0 | E24: =Elect!M25 -> 3313 | F24: 20 | G24: =Elect!O25 -> 1452 | H24: 944 | I24: =Water!C26 -> 150.8 | J24: 0 | K24: =Water!E26 -> 203 | L24: 0 | M24: =Water!#REF! -> #REF! | N24: =Water!#REF! -> #REF! | O24: 1000 | P24: =Water!H26 -> 353.8 | Q24: 138 | R24: =Water!O26 -> 0 | S24: 15 | T24: =Water!#REF! -> #REF! | U24: 165 | V24: =Water!#REF! -> #REF! | W24: 778 | X24: =Water!Q26 -> 205.204 | Y24: 0 | Z24: =Water!#REF! -> #REF! | AA24: 0 | AB24: 0 | AC24: 560 | AD24: =Water!#REF! -> #REF! | AE24: =Water!#REF! -> #REF! | AF24: =Water!#REF! -> #REF! | AG24: =Gas!B26 -> 8302594 | AH24: =Gas!C26 -> 1473.4 | AI24: =Gas!#REF! -> #REF! | AJ24: =Gas!J26 -> 261.3 | AK24: =Gas!#REF! -> #REF! | AL24: =Gas!#REF! -> #REF! | AM24: =Gas!#REF! -> #REF! | AN24: =Gas!#REF! -> #REF! | AO24: =Gas!#REF! -> #REF! | AP24: =Gas!#REF! -> #REF! | AQ24: =Gas!#REF! -> #REF! | AR24: =Gas!#REF! -> #REF! | AS24: =Gas!#REF! -> #REF! | AT24: =Elect!BR25 -> 139 | AU24: =Elect!BP25 -> 140 | AX24: 42.857143 | AY24: 21.649485 | AZ24: 8835.4834 | BA24: 11.269749 | BB24: 5.6929661 | BC24: =Elect!BQ25 -> 516519 | BD24: =Elect!#REF! -> #REF! | BE24: =Elect!#REF! -> #REF! | BF24: =Elect!#REF! -> #REF! | BG24: =Elect!#REF! -> #REF! | BH24: 1.1683673 | BI24: 0.59020619 | BJ24: 5391.5566 | BK24: 6.8769855 | BL24: 3.4739411 | BM24: =Water!U26 -> 1.814359 | BN24: =Water!W26 -> #DIV/0! | BO24: =Water!X26 -> 1415.2 | BP24: =Water!Y26 -> 7.2574359 | BQ24: =Water!Z26 -> #DIV/0!
A25: 21 | B25: 36000 | C25: =Elect!J26 -> 7603 | D25: 0 | E25: =Elect!M26 -> 3087 | F25: 20 | G25: =Elect!O26 -> 1335 | H25: 916 | I25: =Water!C27 -> 150.8 | J25: 0 | K25: =Water!E27 -> 203 | L25: 0 | M25: =Water!#REF! -> #REF! | N25: =Water!#REF! -> #REF! | O25: 998 | P25: =Water!H27 -> 353.8 | Q25: 186 | R25: =Water!O27 -> 0 | S25: 43 | T25: =Water!#REF! -> #REF! | U25: 176 | V25: =Water!#REF! -> #REF! | W25: 773 | X25: =Water!Q27 -> 205.204 | Y25: 0 | Z25: =Water!#REF! -> #REF! | AA25: 0 | AB25: 0 | AC25: 950 | AD25: =Water!#REF! -> #REF! | AE25: =Water!#REF! -> #REF! | AF25: =Water!#REF! -> #REF! | AG25: =Gas!B27 -> 8303984 | AH25: =Gas!C27 -> 1473.4 | AI25: =Gas!#REF! -> #REF! | AJ25: =Gas!J27 -> 261.3 | AK25: =Gas!#REF! -> #REF! | AL25: =Gas!#REF! -> #REF! | AM25: =Gas!#REF! -> #REF! | AN25: =Gas!#REF! -> #REF! | AO25: =Gas!#REF! -> #REF! | AP25: =Gas!#REF! -> #REF! | AQ25: =Gas!#REF! -> #REF! | AR25: =Gas!#REF! -> #REF! | AS25: =Gas!#REF! -> #REF! | AT25: =Elect!BR26 -> 151 | AU25: =Elect!BP26 -> 132 | AX25: 43.956044 | AY25: 22.222222 | AZ25: 9371.6914 | BA25: 11.442847 | BB25: 5.7849947 | BC25: =Elect!BQ26 -> 516670 | BD25: =Elect!#REF! -> #REF! | BE25: =Elect!#REF! -> #REF! | BF25: =Elect!#REF! -> #REF! | BG25: =Elect!#REF! -> #REF! | BH25: 1.0586081 | BI25: 0.53518519 | BJ25: 5231.6376 | BK25: 6.3878358 | BL25: 3.2294059 | BM25: =Water!U27 -> 1.7778894 | BN25: =Water!W27 -> #DIV/0! | BO25: =Water!X27 -> 1415.2 | BP25: =Water!Y27 -> 7.1115578 | BQ25: =Water!Z27 -> #DIV/0!
A26: 22 | B26: 33600 | C26: =Elect!J27 -> 7748 | D26: 0 | E26: =Elect!M27 -> 2989 | F26: 20 | G26: =Elect!O27 -> 1418 | H26: 931 | I26: =Water!C28 -> 150.8 | J26: 0 | K26: =Water!E28 -> 203 | L26: 0 | M26: =Water!#REF! -> #REF! | N26: =Water!#REF! -> #REF! | O26: 969 | P26: =Water!H28 -> 353.8 | Q26: 151 | R26: =Water!O28 -> 0 | S26: 29 | T26: =Water!#REF! -> #REF! | U26: 157 | V26: =Water!#REF! -> #REF! | W26: 697 | X26: =Water!Q28 -> 205.204 | Y26: 0 | Z26: =Water!#REF! -> #REF! | AA26: 0 | AB26: 0 | AC26: 700 | AD26: =Water!#REF! -> #REF! | AE26: =Water!#REF! -> #REF! | AF26: =Water!#REF! -> #REF! | AG26: =Gas!B28 -> 8305374 | AH26: =Gas!C28 -> 1473.4 | AI26: =Gas!#REF! -> #REF! | AJ26: =Gas!J28 -> 261.3 | AK26: =Gas!#REF! -> #REF! | AL26: =Gas!#REF! -> #REF! | AM26: =Gas!#REF! -> #REF! | AN26: =Gas!#REF! -> #REF! | AO26: =Gas!#REF! -> #REF! | AP26: =Gas!#REF! -> #REF! | AQ26: =Gas!#REF! -> #REF! | AR26: =Gas!#REF! -> #REF! | AS26: =Gas!#REF! -> #REF! | AT26: =Elect!BR27 -> 0 | AU26: =Elect!BP27 -> 0 | AX26: 39.952438 | AY26: 20.253165 | AZ26: 8835.4834 | BA26: 10.505926 | BB26: 5.3257887 | BC26: =Elect!BQ27 -> 516670 | BD26: =Elect!#REF! -> #REF! | BE26: =Elect!#REF! -> #REF! | BF26: =Elect!#REF! -> #REF! | BG26: =Elect!#REF! -> #REF! | BH26: 1.0903686 | BI26: 0.55274262 | BJ26: 5317.3085 | BK26: 6.3226022 | BL26: 3.2051287 | BM26: =Water!U28 -> 1.760199 | BN26: =Water!W28 -> #DIV/0! | BO26: =Water!X28 -> 1415.2 | BP26: =Water!Y28 -> 7.040796 | BQ26: =Water!Z28 -> #DIV/0!
A27: 23 | B27: 36000 | C27: =Elect!J28 -> 7641 | D27: 0 | E27: =Elect!M28 -> 3212 | F27: 30 | G27: =Elect!O28 -> 1451 | H27: 1009 | I27: =Water!C29 -> 121.8 | J27: 0 | K27: =Water!E29 -> 145 | L27: 0 | M27: =Water!#REF! -> #REF! | N27: =Water!#REF! -> #REF! | O27: 902 | P27: =Water!H29 -> 266.8 | Q27: 131 | R27: =Water!O29 -> 0 | S27: 6 | T27: =Water!#REF! -> #REF! | U27: 167 | V27: =Water!#REF! -> #REF! | W27: 748 | X27: =Water!Q29 -> 154.744 | Y27: 0 | Z27: =Water!#REF! -> #REF! | AA27: 0 | AB27: 0 | AC27: 690 | AD27: =Water!#REF! -> #REF! | AE27: =Water!#REF! -> #REF! | AF27: =Water!#REF! -> #REF! | AG27: =Gas!B29 -> 8306764 | AH27: =Gas!C29 -> 1473.4 | AI27: =Gas!#REF! -> #REF! | AJ27: =Gas!J29 -> 261.3 | AK27: =Gas!#REF! -> #REF! | AL27: =Gas!#REF! -> #REF! | AM27: =Gas!#REF! -> #REF! | AN27: =Gas!#REF! -> #REF! | AO27: =Gas!#REF! -> #REF! | AP27: =Gas!#REF! -> #REF! | AQ27: =Gas!#REF! -> #REF! | AR27: =Gas!#REF! -> #REF! | AS27: =Gas!#REF! -> #REF! | AT27: =Elect!BR28 -> 152 | AU27: =Elect!BP28 -> 145 | AX27: 42.755344 | AY27: 21.543986 | AZ27: 9371.6914 | BA27: 11.130275 | BB27: 5.6084329 | BC27: =Elect!BQ28 -> 516822 | BD27: =Elect!#REF! -> #REF! | BE27: =Elect!#REF! -> #REF! | BF27: =Elect!#REF! -> #REF! | BG27: =Elect!#REF! -> #REF! | BH27: 1.0712589 | BI27: 0.53979653 | BJ27: 5762.7973 | BK27: 6.8441773 | BL27: 3.4487117 | BM27: =Water!U29 -> 1.2127273 | BN27: =Water!W29 -> #DIV/0! | BO27: =Water!X29 -> 1067.2 | BP27: =Water!Y29 -> 4.8509091 | BQ27: =Water!Z29 -> #DIV/0!
A28: 24 | B28: 33600 | C28: =Elect!J29 -> 7140 | D28: 0 | E28: =Elect!M29 -> 2916 | F28: 20 | G28: =Elect!O29 -> 1484 | H28: 891 | I28: =Water!C30 -> 58 | J28: 0 | K28: =Water!E30 -> 98.6 | L28: 0 | M28: =Water!#REF! -> #REF! | N28: =Water!#REF! -> #REF! | O28: 818 | P28: =Water!H30 -> 156.6 | Q28: 221 | R28: =Water!O30 -> 0 | S28: 93 | T28: =Water!#REF! -> #REF! | U28: 191 | V28: =Water!#REF! -> #REF! | W28: 827 | X28: =Water!Q30 -> 90.828 | Y28: 0 | Z28: =Water!#REF! -> #REF! | AA28: 0 | AB28: 0 | AC28: 470 | AD28: =Water!#REF! -> #REF! | AE28: =Water!#REF! -> #REF! | AF28: =Water!#REF! -> #REF! | AG28: =Gas!B30 -> 8308154 | AH28: =Gas!C30 -> 1473.4 | AI28: =Gas!#REF! -> #REF! | AJ28: =Gas!J30 -> 261.3 | AK28: =Gas!#REF! -> #REF! | AL28: =Gas!#REF! -> #REF! | AM28: =Gas!#REF! -> #REF! | AN28: =Gas!#REF! -> #REF! | AO28: =Gas!#REF! -> #REF! | AP28: =Gas!#REF! -> #REF! | AQ28: =Gas!#REF! -> #REF! | AR28: =Gas!#REF! -> #REF! | AS28: =Gas!#REF! -> #REF! | AT28: =Elect!BR29 -> 156 | AU28: =Elect!BP29 -> 146 | AX28: 39.904988 | AY28: 20.289855 | AZ28: 8835.4834 | BA28: 10.493448 | BB28: 5.3354369 | BC28: =Elect!BQ29 -> 516978 | BD28: =Elect!#REF! -> #REF! | BE28: =Elect!#REF! -> #REF! | BF28: =Elect!#REF! -> #REF! | BG28: =Elect!#REF! -> #REF! | BH28: 1.1104513 | BI28: 0.56461353 | BJ28: 5088.8527 | BK28: 6.043768 | BL28: 3.0729787 | BM28: =Water!U30 -> 0.77524752 | BN28: =Water!W30 -> #DIV/0! | BO28: =Water!X30 -> 626.4 | BP28: =Water!Y30 -> 3.1009901 | BQ28: =Water!Z30 -> #DIV/0!
A29: 25 | B29: 33600 | C29: =Elect!J30 -> 7420 | D29: 0 | E29: =Elect!M30 -> 2844 | F29: 20 | G29: =Elect!O30 -> 1518 | H29: 1008 | I29: =Water!C31 -> 110.2 | J29: 0 | K29: =Water!E31 -> 116 | L29: 0 | M29: =Water!#REF! -> #REF! | N29: =Water!#REF! -> #REF! | O29: 1290 | P29: =Water!H31 -> 233.16 | Q29: 34 | R29: =Water!O31 -> 0 | S29: 34 | T29: =Water!#REF! -> #REF! | U29: 55 | V29: =Water!#REF! -> #REF! | W29: 681 | X29: =Water!Q31 -> 135.2328 | Y29: 0 | Z29: =Water!#REF! -> #REF! | AA29: 0 | AB29: 0 | AC29: 1170 | AD29: =Water!#REF! -> #REF! | AE29: =Water!#REF! -> #REF! | AF29: =Water!#REF! -> #REF! | AG29: =Gas!B31 -> 8309544 | AH29: =Gas!C31 -> 1473.4 | AI29: =Gas!#REF! -> #REF! | AJ29: =Gas!J31 -> 772.2 | AK29: =Gas!#REF! -> #REF! | AL29: =Gas!#REF! -> #REF! | AM29: =Gas!#REF! -> #REF! | AN29: =Gas!#REF! -> #REF! | AO29: =Gas!#REF! -> #REF! | AP29: =Gas!#REF! -> #REF! | AQ29: =Gas!#REF! -> #REF! | AR29: =Gas!#REF! -> #REF! | AS29: =Gas!#REF! -> #REF! | AT29: =Elect!BR30 -> 157 | AU29: =Elect!BP30 -> 149 | AX29: 39.763314 | AY29: 20.20445 | AZ29: 8835.4834 | BA29: 10.456193 | BB29: 5.3129786 | BC29: =Elect!BQ30 -> 517135 | BD29: =Elect!#REF! -> #REF! | BE29: =Elect!#REF! -> #REF! | BF29: =Elect!#REF! -> #REF! | BG29: =Elect!#REF! -> #REF! | BH29: 1.0059172 | BI29: 0.51112447 | BJ29: 5757.0859 | BK29: 6.8131194 | BL29: 3.4618676 | BM29: =Water!U31 -> 1.16 | BN29: =Water!W31 -> #DIV/0! | BO29: =Water!X31 -> 932.64 | BP29: =Water!Y31 -> 4.64 | BQ29: =Water!Z31 -> #DIV/0!
A30: 26 | B30: 31200 | C30: =Elect!J31 -> 8640 | D30: 0 | E30: =Elect!M31 -> 3689 | F30: 20 | G30: =Elect!O31 -> 1637 | H30: 760 | I30: =Water!C32 -> 121.8 | J30: 0 | K30: =Water!E32 -> 168.2 | L30: 0 | M30: =Water!#REF! -> #REF! | N30: =Water!#REF! -> #REF! | O30: 1004 | P30: =Water!H32 -> 290.58 | Q30: 131 | R30: =Water!O32 -> 0 | S30: 33 | T30: =Water!#REF! -> #REF! | U30: 145 | V30: =Water!#REF! -> #REF! | W30: 916 | X30: =Water!Q32 -> 168.5364 | Y30: 0 | Z30: =Water!#REF! -> #REF! | AA30: 0 | AB30: 0 | AC30: 810 | AD30: =Water!#REF! -> #REF! | AE30: =Water!#REF! -> #REF! | AF30: =Water!#REF! -> #REF! | AG30: =Gas!B32 -> 8310934 | AH30: =Gas!C32 -> 1473.4 | AI30: =Gas!#REF! -> #REF! | AJ30: =Gas!J32 -> 163.8 | AK30: =Gas!#REF! -> #REF! | AL30: =Gas!#REF! -> #REF! | AM30: =Gas!#REF! -> #REF! | AN30: =Gas!#REF! -> #REF! | AO30: =Gas!#REF! -> #REF! | AP30: =Gas!#REF! -> #REF! | AQ30: =Gas!#REF! -> #REF! | AR30: =Gas!#REF! -> #REF! | AS30: =Gas!#REF! -> #REF! | AT30: =Elect!BR31 -> 155 | AU30: =Elect!BP31 -> 147 | AX30: 37.275986 | AY30: 18.989653 | AZ30: 8299.2754 | BA30: 9.9155023 | BB30: 5.0512936 | BC30: =Elect!BQ31 -> 517290 | BD30: =Elect!#REF! -> #REF! | BE30: =Elect!#REF! -> #REF! | BF30: =Elect!#REF! -> #REF! | BG30: =Elect!#REF! -> #REF! | BH30: 1.1063321 | BI30: 0.56360316 | BJ30: 4340.66 | BK30: 5.1859737 | BL30: 2.6419111 | BM30: =Water!U32 -> 1.3903349 | BN30: =Water!W32 -> #DIV/0! | BO30: =Water!X32 -> 1162.32 | BP30: =Water!Y32 -> 5.5613397 | BQ30: =Water!Z32 -> #DIV/0!
A31: 27 | B31: 36000 | C31: =Elect!J32 -> 7676 | D31: 0 | E31: =Elect!M32 -> 3077 | F31: 30 | G31: =Elect!O32 -> 1395 | H31: 1010 | I31: =Water!C33 -> 104.4 | J31: 0 | K31: =Water!E33 -> 139.2 | L31: 0 | M31: =Water!#REF! -> #REF! | N31: =Water!#REF! -> #REF! | O31: 1014 | P31: =Water!H33 -> 244.18 | Q31: 151 | R31: =Water!O33 -> 0 | S31: 30 | T31: =Water!#REF! -> #REF! | U31: 139 | V31: =Water!#REF! -> #REF! | W31: 761 | X31: =Water!Q33 -> 141.6244 | Y31: 0 | Z31: =Water!#REF! -> #REF! | AA31: 0 | AB31: 0 | AC31: 930 | AD31: =Water!#REF! -> #REF! | AE31: =Water!#REF! -> #REF! | AF31: =Water!#REF! -> #REF! | AG31: =Gas!B33 -> 8312324 | AH31: =Gas!C33 -> 1473.4 | AI31: =Gas!#REF! -> #REF! | AJ31: =Gas!J33 -> 339.3 | AK31: =Gas!#REF! -> #REF! | AL31: =Gas!#REF! -> #REF! | AM31: =Gas!#REF! -> #REF! | AN31: =Gas!#REF! -> #REF! | AO31: =Gas!#REF! -> #REF! | AP31: =Gas!#REF! -> #REF! | AQ31: =Gas!#REF! -> #REF! | AR31: =Gas!#REF! -> #REF! | AS31: =Gas!#REF! -> #REF! | AT31: =Elect!BR32 -> 137 | AU31: =Elect!BP32 -> 132 | AX31: 44.063647 | AY31: 22.346369 | AZ31: 9371.6914 | BA31: 11.470859 | BB31: 5.8173131 | BC31: =Elect!BQ32 -> 517427 | BD31: =Elect!#REF! -> #REF! | BE31: =Elect!#REF! -> #REF! | BF31: =Elect!#REF! -> #REF! | BG31: =Elect!#REF! -> #REF! | BH31: 1.1640147 | BI31: 0.59031657 | BJ31: 5768.5087 | BK31: 7.0605981 | BL31: 3.5807006 | BM31: =Water!U33 -> 1.0999099 | BN31: =Water!W33 -> #DIV/0! | BO31: =Water!X33 -> 976.72 | BP31: =Water!Y33 -> 4.3996396 | BQ31: =Water!Z33 -> #DIV/0!
A32: 28 | B32: 33600 | C32: =Elect!J33 -> 8058 | D32: 0 | E32: =Elect!M33 -> 3276 | F32: 20 | G32: =Elect!O33 -> 1534 | H32: 1008 | I32: =Water!C34 -> 174 | J32: 0 | K32: =Water!E34 -> 208.8 | L32: 1 | M32: =Water!#REF! -> #REF! | N32: =Water!#REF! -> #REF! | O32: 1013 | P32: =Water!H34 -> 383.38 | Q32: 142 | R32: =Water!O34 -> 0 | S32: 13 | T32: =Water!#REF! -> #REF! | U32: 155 | V32: =Water!#REF! -> #REF! | W32: 825 | X32: =Water!Q34 -> 222.3604 | Y32: 1 | Z32: =Water!#REF! -> #REF! | AA32: 0 | AB32: 0 | AC32: 650 | AD32: =Water!#REF! -> #REF! | AE32: =Water!#REF! -> #REF! | AF32: =Water!#REF! -> #REF! | AG32: =Gas!B34 -> 8313714 | AH32: =Gas!C34 -> 1473.4 | AI32: =Gas!#REF! -> #REF! | AJ32: =Gas!J34 -> 624 | AK32: =Gas!#REF! -> #REF! | AL32: =Gas!#REF! -> #REF! | AM32: =Gas!#REF! -> #REF! | AN32: =Gas!#REF! -> #REF! | AO32: =Gas!#REF! -> #REF! | AP32: =Gas!#REF! -> #REF! | AQ32: =Gas!#REF! -> #REF! | AR32: =Gas!#REF! -> #REF! | AS32: =Gas!#REF! -> #REF! | AT32: =Elect!BR33 -> 138 | AU32: =Elect!BP33 -> 161 | AX32: 45.34413 | AY32: 22.687373 | AZ32: 8835.4834 | BA32: 11.923729 | BB32: 5.9658902 | BC32: =Elect!BQ33 -> 517565 | BD32: =Elect!#REF! -> #REF! | BE32: =Elect!#REF! -> #REF! | BF32: =Elect!#REF! -> #REF! | BG32: =Elect!#REF! -> #REF! | BH32: 1.2294197 | BI32: 0.61512492 | BJ32: 5757.0859 | BK32: 7.7693467 | BL32: 3.8872963 | BM32: =Water!U34 -> 1.6741485 | BN32: =Water!W34 -> #DIV/0! | BO32: =Water!X34 -> 1533.52 | BP32: =Water!Y34 -> 6.6965939 | BQ32: =Water!Z34 -> #DIV/0!
A33: MTD | B33: 931200 | C33: =Elect!J34 -> 7572 | D33: 0 | E33: =Elect!M34 -> 3001 | F33: 600 | G33: =Elect!O34 -> 1536 | H33: 24543 | I33: =Water!C38 -> 4495 | J33: 0 | K33: =Water!E39 -> 193.33333 | L33: 3 | M33: =Water!#REF! -> #REF! | N33: =Water!#REF! -> #REF! | O33: 1013 | P33: =Water!H38 -> 10316.46 | Q33: 109 | R33: =Water!O38 -> 0 | S33: 15 | T33: =Water!#REF! -> #REF! | U33: 147 | V33: =Water!#REF! -> #REF! | W33: 730 | X33: =Water!Q38 -> 5472.2188 | Y33: 3 | Z33: =Water!#REF! -> #REF! | AA33: 0 | AB33: 0 | AC33: 0 | AD33: =Water!#REF! -> #REF! | AE33: =Water!#REF! -> #REF! | AF33: =Water!#REF! -> #REF! | AG33: =Gas!B38 -> 0 | AH33: =Gas!C38 -> 45675.4 | AI33: =Gas!#REF! -> #REF! | AJ33: =Gas!J38 -> 12335.7 | AK33: =Gas!#REF! -> #REF! | AL33: =Gas!#REF! -> #REF! | AM33: =Gas!#REF! -> #REF! | AN33: =Gas!#REF! -> #REF! | AO33: =Gas!#REF! -> #REF! | AP33: =Gas!#REF! -> #REF! | AQ33: =Gas!#REF! -> #REF! | AR33: =Gas!#REF! -> #REF! | AS33: =Gas!#REF! -> #REF! | AT33: =Elect!BR34 -> 133 | AU33: =Elect!BP34 -> 144 | AX33: 45.411099 | AY33: 22.844806 | AZ33: 245248.7 | BA33: 11.959851 | BB33: 6.0166013 | BC33: =Elect!BQ34 -> 517698 | BD33: =Elect!#REF! -> #REF! | BE33: =Elect!#REF! -> #REF! | BF33: =Elect!#REF! -> #REF! | BG33: =Elect!#REF! -> #REF! | BH33: 1.1514679 | BI33: 0.57929342 | BJ33: 140121.3 | BK33: 6.8331854 | BL33: 3.4377159 | BM33: =Water!U38 -> 1.698742 | BN33: =Water!W38 -> #DIV/0! | BO33: =Water!X38 -> 40129.04 | BP33: =Water!Y38 -> 6.6077787 | BQ33: =Water!Z38 -> #DIV/0!
A34: AVER. Act | B34: 33257.143 | C34: =Elect!J35 -> 7537 | D34: 0 | E34: =Elect!M35 -> 3041 | F34: 21.428571 | G34: =Elect!O35 -> 1485 | H34: 876.53571 | I34: =Water!C39 -> 149.83333 | J34: 0 | K34: =Water!E40 -> 0 | L34: 4 | M34: =Water!#REF! -> #REF! | N34: =Water!#REF! -> #REF! | O34: 1014 | P34: =Water!H39 -> 343.882 | Q34: 138 | R34: =Water!O39 -> 0 | S34: 24 | T34: =Water!#REF! -> #REF! | U34: 145 | V34: =Water!#REF! -> #REF! | W34: 877 | X34: =Water!Q39 -> 182.40729 | Y34: 4 | Z34: =Water!#REF! -> #REF! | AA34: 0 | AB34: 0 | AC34: 0 | AD34: =Water!#REF! -> #REF! | AE34: =Water!#REF! -> #REF! | AF34: =Water!#REF! -> #REF! | AG34: =Gas!B39 -> 0 | AH34: =Gas!C39 -> 1522.5133 | AI34: =Gas!#REF! -> #REF! | AJ34: =Gas!J39 -> 411.19 | AK34: =Gas!#REF! -> #REF! | AL34: =Gas!#REF! -> #REF! | AM34: =Gas!#REF! -> #REF! | AN34: =Gas!#REF! -> #REF! | AO34: =Gas!#REF! -> #REF! | AP34: =Gas!#REF! -> #REF! | AQ34: =Gas!#REF! -> #REF! | AR34: =Gas!#REF! -> #REF! | AS34: =Gas!#REF! -> #REF! | AT34: =Elect!BR35 -> 120 | AU34: =Elect!BP35 -> 142 | AX34: 45.411099 | AY34: 22.844806 | AZ34: 8758.8823 | BA34: 11.959851 | BB34: 6.0166013 | BC34: =Elect!BQ35 -> 517818 | BD34: =Elect!#REF! -> #REF! | BE34: =Elect!#REF! -> #REF! | BF34: =Elect!#REF! -> #REF! | BG34: =Elect!#REF! -> #REF! | BH34: 1.1761372 | BI34: 0.60007377 | BJ34: 5004.3322 | BK34: 6.8331854 | BL34: 3.4377159 | BM34: =Water!U39 -> 1.698742 | BN34: =Water!W39 -> #DIV/0! | BO34: =Water!X39 -> 1337.6347 | BP34: =Water!Y39 -> 6.6077787 | BQ34: =Water!Z39 -> #DIV/0!
A35: TOTAL Budget | B35: 1040026 | C35: =Elect!J5 -> 0 | D35: 0 | E35: =Elect!M5 -> 0 | F35: 0 | G35: =Elect!O5 -> 0 | H35: 0 | I35: =Water!C40 -> 0 | J35: 0 | K35: =Water!E41 -> 0 | L35: 5 | M35: =Water!#REF! -> #REF! | N35: =Water!#REF! -> #REF! | O35: 1010 | P35: =Water!H40 -> 0 | Q35: 148 | R35: =Water!O40 -> 0 | S35: 22 | T35: =Water!#REF! -> #REF! | U35: 151 | V35: =Water!#REF! -> #REF! | W35: 833 | X35: =Water!Q40 -> 0 | Y35: 5 | Z35: =Water!#REF! -> #REF! | AA35: 0 | AB35: 0 | AC35: 0 | AD35: =Water!#REF! -> #REF! | AE35: =Water!#REF! -> #REF! | AF35: =Water!#REF! -> #REF! | AG35: =Gas!#REF! -> #REF! | AH35: =Gas!#REF! -> #REF! | AI35: =Gas!#REF! -> #REF! | AJ35: =Gas!#REF! -> #REF! | AK35: =Gas!#REF! -> #REF! | AL35: =Gas!#REF! -> #REF! | AM35: =Gas!#REF! -> #REF! | AN35: =Gas!#REF! -> #REF! | ... AS35: =Gas!#REF! -> #REF! | AT35: =Elect!BR5 -> 0 | AU35: =Elect!BP5 -> 0 | AX35: 45.679286 | AY35: 23.305904 | AZ35: 264708.4 | BA35: 11.626335 | BB35: 5.9318409 | BC35: =Elect!BQ5 -> 513610 | BD35: =Elect!#REF! -> #REF! | BE35: =Elect!#REF! -> #REF! | BF35: =Elect!#REF! -> #REF! | BG35: =Elect!#REF! -> #REF! | BH35: 1.1761372 | BI35: 0.60007377 | BJ35: 150494 | BK35: 6.6098911 | BL35: 3.3724146 | BM35: =Water!U40 -> #REF! | BN35: =Water!W40 -> #REF! | BO35: =Water!X40 -> 0 | BP35: =Water!Y40 -> 0 | BQ35: =Water!Z40 -> 0
A36: Budget MTD | B36: 1040026 | C36: =Elect!#REF! -> #REF! | D36: 0 | E36: =Elect!#REF! -> #REF! | F36: 0 | G36: =Elect!#REF! -> #REF! | H36: 0 | I36: =Water!C41 -> 0 | J36: 0 | K36: =Water!E42 -> 0 | L36: 6 | M36: =Water!#REF! -> #REF! | N36: =Water!#REF! -> #REF! | O36: 30039 | P36: =Water!H41 -> 0 | Q36: 129.54839 | R36: =Water!O41 -> 0 | S36: 719 | T36: =Water!#REF! -> #REF! | U36: 4609 | V36: =Water!#REF! -> #REF! | W36: 23430 | X36: =Water!Q41 -> 0 | Y36: 6 | Z36: =Water!#REF! -> #REF! | AA36: 0 | AB36: 0 | AC36: 0 | AD36: =Water!#REF! -> #REF! | AE36: =Water!#REF! -> #REF! | AF36: =Water!#REF! -> #REF! | AG36: =Gas!#REF! -> #REF! | AH36: =Gas!#REF! -> #REF! | AI36: =Gas!#REF! -> #REF! | AJ36: =Gas!#REF! -> #REF! | AK36: =Gas!#REF! -> #REF! | AL36: =Gas!#REF! -> #REF! | AM36: =Gas!#REF! -> #REF! | AN36: =Gas!#REF! -> #REF! | ... AS36: =Gas!#REF! -> #REF! | AT36: =Elect!#REF! -> #REF! | AU36: =Elect!#REF! -> #REF! | AX36: 45.679286 | AY36: 23.305904 | AZ36: 264708.4 | BA36: 11.626335 | BB36: 5.9318409 | BC36: =Elect!#REF! -> #REF! | BD36: =Elect!#REF! -> #REF! | BE36: =Elect!#REF! -> #REF! | BF36: =Elect!#REF! -> #REF! | BG36: =Elect!#REF! -> #REF! | BH36: 0 | BI36: 0 | BJ36: 135930.06 | BK36: 6.6098911 | BL36: 3.3724146 | BM36: =Water!U41 -> #REF! | BN36: =Water!W41 -> #REF! | BO36: =Water!X41 -> #REF! | BP36: =Water!Y41 -> #REF! | BQ36: =Water!Z41 -> #REF!
A37: AVER. Bud | B37: 37143.785 | C37: =Elect!#REF! -> #REF! | D37: 0 | E37: =Elect!#REF! -> #REF! | F37: 0 | G37: =Elect!#REF! -> #REF! | H37: 0 | I37: =Water!C42 -> 0 | J37: 0 | K37: =Water!E43 -> 0 | L37: 7 | M37: =Water!#REF! -> #REF! | N37: =Water!#REF! -> #REF! | O37: 969 | P37: =Water!H42 -> 0 | Q37: 0 | R37: =Water!O42 -> 0 | S37: 23.193548 | T37: =Water!#REF! -> #REF! | U37: 148.67742 | V37: =Water!#REF! -> #REF! | W37: 755.80645 | X37: =Water!Q42 -> 0 | Y37: 7 | Z37: =Water!#REF! -> #REF! | AA37: 0 | AB37: 0 | AC37: 0 | AD37: =Water!#REF! -> #REF! | AE37: =Water!#REF! -> #REF! | AF37: =Water!#REF! -> #REF! | AG37: =Gas!#REF! -> #REF! | AH37: =Gas!#REF! -> #REF! | AI37: =Gas!#REF! -> #REF! | AJ37: =Gas!#REF! -> #REF! | AK37: =Gas!#REF! -> #REF! | AL37: =Gas!#REF! -> #REF! | AM37: =Gas!#REF! -> #REF! | AN37: =Gas!#REF! -> #REF! | ... AS37: =Gas!#REF! -> #REF! | AT37: =Elect!#REF! -> #REF! | AU37: =Elect!#REF! -> #REF! | AX37: 0 | AY37: 0 | AZ37: 9453.8714 | BA37: 0 | BB37: 0 | BC37: =Elect!#REF! -> #REF! | BD37: =Elect!#REF! -> #REF! | BE37: =Elect!#REF! -> #REF! | BF37: =Elect!#REF! -> #REF! | BG37: =Elect!#REF! -> #REF! | BH37: 0 | BI37: 0 | BJ37: 0 | BK37: 0 | BL37: 0 | BM37: =Water!U42 -> 0 | BN37: =Water!W42 -> 0 | BO37: =Water!X42 -> 0 | BP37: =Water!Y42 -> 0 | BQ37: =Water!Z42 -> 0
A38: Total RFC | B38: 784008.53 | C38: =Elect!#REF! -> #REF! | D38: 0 | E38: =Elect!#REF! -> #REF! | F38: 0 | G38: =Elect!#REF! -> #REF! | H38: 0 | I38: =Water!C43 -> 0 | J38: 0 | K38: =Water!E44 -> 0 | L38: 8 | M38: =Water!#REF! -> #REF! | N38: =Water!#REF! -> #REF! | O38: 0 | P38: =Water!H43 -> 0 | Q38: 0 | R38: =Water!O43 -> 0 | S38: 0 | T38: =Water!#REF! -> #REF! | U38: 0 | V38: =Water!#REF! -> #REF! | W38: 0 | X38: =Water!Q43 -> 0 | Y38: 8 | Z38: =Water!#REF! -> #REF! | AA38: 0 | AB38: 0 | AC38: 0 | AD38: =Water!#REF! -> #REF! | AE38: =Water!#REF! -> #REF! | AF38: =Water!#REF! -> #REF! | AG38: =Gas!#REF! -> #REF! | AH38: =Gas!#REF! -> #REF! | AI38: =Gas!#REF! -> #REF! | AJ38: =Gas!#REF! -> #REF! | AK38: =Gas!#REF! -> #REF! | AL38: =Gas!#REF! -> #REF! | AM38: =Gas!#REF! -> #REF! | AN38: =Gas!#REF! -> #REF! | ... AS38: =Gas!#REF! -> #REF! | AT38: =Elect!#REF! -> #REF! | AU38: =Elect!#REF! -> #REF! | AX38: 38.173558 | AY38: 19.219193 | AZ38: 208225.85 | BA38: 10.138565 | BB38: 5.1044505 | BC38: =Elect!#REF! -> #REF! | BD38: =Elect!#REF! -> #REF! | BE38: =Elect!#REF! -> #REF! | BF38: =Elect!#REF! -> #REF! | BG38: =Elect!#REF! -> #REF! | BH38: 0 | BI38: 0 | BJ38: 127385.62 | BK38: 6.2024355 | BL38: 3.1227323 | BM38: =Water!U43 -> 0 | BN38: =Water!W43 -> 0 | BO38: =Water!X43 -> 0 | BP38: =Water!Y43 -> 0 | BQ38: =Water!Z43 -> 0
A39: RFC MTD | B39: 784008.53 | C39: =Elect!#REF! -> #REF! | D39: 0 | E39: =Elect!#REF! -> #REF! | F39: 0 | G39: =Elect!#REF! -> #REF! | H39: 0 | I39: =Water!C44 -> 0 | J39: 0 | K39: =Water!E45 -> 0 | L39: 9 | M39: =Water!#REF! -> #REF! | N39: =Water!#REF! -> #REF! | O39: 0 | P39: =Water!H44 -> 0 | Q39: 0 | R39: =Water!O44 -> 0 | S39: 0 | T39: =Water!#REF! -> #REF! | U39: 0 | V39: =Water!#REF! -> #REF! | W39: 0 | X39: =Water!Q44 -> 0 | Y39: 9 | Z39: =Water!#REF! -> #REF! | AA39: 0 | AB39: 0 | AC39: 0 | AD39: =Water!#REF! -> #REF! | AE39: =Water!#REF! -> #REF! | AF39: =Water!#REF! -> #REF! | AG39: =Gas!#REF! -> #REF! | AH39: =Gas!#REF! -> #REF! | AI39: =Gas!#REF! -> #REF! | AJ39: =Gas!#REF! -> #REF! | AK39: =Gas!#REF! -> #REF! | AL39: =Gas!#REF! -> #REF! | AM39: =Gas!#REF! -> #REF! | AN39: =Gas!#REF! -> #REF! | ... AS39: =Gas!#REF! -> #REF! | AT39: =Elect!#REF! -> #REF! | AU39: =Elect!#REF! -> #REF! | AX39: 38.173558 | AY39: 19.219193 | AZ39: 208225.85 | BA39: 10.138565 | BB39: 5.1044505 | BC39: =Elect!#REF! -> #REF! | BD39: =Elect!#REF! -> #REF! | BE39: =Elect!#REF! -> #REF! | BF39: =Elect!#REF! -> #REF! | BG39: =Elect!#REF! -> #REF! | BH39: 0 | BI39: 0 | BJ39: 115057.98 | BK39: 6.2024355 | BL39: 3.1227323 | BM39: =Water!U44 -> 0 | BN39: =Water!W44 -> 0 | BO39: =Water!X44 -> #VALUE! | BP39: =Water!Y44 -> #VALUE! | BQ39: =Water!Z44 -> #VALUE!
A40: AVER RFC | B40: 28000.305 | C40: =Elect!#REF! -> #REF! | D40: 0 | E40: =Elect!#REF! -> #REF! | F40: 0 | G40: =Elect!#REF! -> #REF! | H40: 0 | I40: =Water!C45 -> 0 | J40: 0 | K40: =Water!E46 -> 0 | L40: 10 | M40: =Water!#REF! -> #REF! | N40: =Water!#REF! -> #REF! | O40: 0 | P40: =Water!H45 -> 0 | Q40: 0 | R40: =Water!O45 -> 0 | S40: 0 | T40: =Water!#REF! -> #REF! | U40: 0 | V40: =Water!#REF! -> #REF! | W40: 0 | X40: =Water!Q45 -> 0 | Y40: 10 | Z40: =Water!#REF! -> #REF! | AA40: 0 | AB40: 0 | AC40: 0 | AD40: =Water!#REF! -> #REF! | AE40: =Water!#REF! -> #REF! | AF40: =Water!#REF! -> #REF! | AG40: =Gas!#REF! -> #REF! | AH40: =Gas!#REF! -> #REF! | AI40: =Gas!#REF! -> #REF! | AJ40: =Gas!#REF! -> #REF! | AK40: =Gas!#REF! -> #REF! | AL40: =Gas!#REF! -> #REF! | AM40: =Gas!#REF! -> #REF! | AN40: =Gas!#REF! -> #REF! | ... AS40: =Gas!#REF! -> #REF! | AT40: =Elect!#REF! -> #REF! | AU40: =Elect!#REF! -> #REF! | AX40: 0 | AY40: 0 | AZ40: 7436.6375 | BA40: 0 | BB40: 0 | BC40: =Elect!#REF! -> #REF! | BD40: =Elect!#REF! -> #REF! | BE40: =Elect!#REF! -> #REF! | BF40: =Elect!#REF! -> #REF! | BG40: =Elect!#REF! -> #REF! | BH40: 1.1254646 | BI40: 0.57264868 | BJ40: 4109.2135 | BK40: 0 | BL40: 0 | BM40: =Water!U45 -> 0 | BN40: =Water!W45 -> 0 | BO40: =Water!X45 -> #VALUE! | BP40: =Water!Y45 -> 0 | BQ40: =Water!Z45 -> 0

Sheet Temp.
A2: HILTON INTERNATIONAL
A3: GULF, MIDDLE EAST AND ASIA SPECIFIC
A4: HOTEL:HILTON HURGHADA LONG BEACH RESORT | G4: =Elect!A1 -> January
A7: DATE | B7: MAX TEMP | C7: MIN TEMP | D7: MAX TEMP | E7: MIN TEMP | F7: DAY | G7: DD. C | H7: DD. H | I7: MTD | J7: MTD
B8: C | C8: C | D8: F | E8: F | F8: PARAMETER | I8: COOLING | J8: HEATING
A10: 1 | D10: =SUM((B10*9/5)+32) -> 32 | E10: =SUM((C10*9/5)+32) -> 32 | F10: =SUM(((B10+C10)/2)-18.33) -> -18.33 | G10: =SUM(0+(F10)+ABS(F10))/2 -> 0 | H10: =IF((SUM(0-(F10)+ABS(F10))/2)<18,SUM(0-(F10)+ABS(F10))/2,0) -> 0 | I10: =SUM(G10:G10) -> 0 | J10: =SUM(H10:H10) -> 0
A11: 2 | D11: =SUM((B11*9/5)+32) -> 32 | E11: =SUM((C11*9/5)+32) -> 32 | F11: =SUM(((B11+C11)/2)-18.33) -> -18.33 | G11: =SUM(0+(F11)+ABS(F11))/2 -> 0 | H11: =IF((SUM(0-(F11)+ABS(F11))/2)<18,SUM(0-(F11)+ABS(F11))/2,0) -> 0 | I11: =SUM(G10:G11) -> 0 | J11: =SUM(H10:H11) -> 0
A12: 3 | D12: =SUM((B12*9/5)+32) -> 32 | E12: =SUM((C12*9/5)+32) -> 32 | F12: =SUM(((B12+C12)/2)-18.33) -> -18.33 | G12: =SUM(0+(F12)+ABS(F12))/2 -> 0 | H12: =IF((SUM(0-(F12)+ABS(F12))/2)<18,SUM(0-(F12)+ABS(F12))/2,0) -> 0 | I12: =SUM(G10:G12) -> 0 | J12: =SUM(H10:H12) -> 0
A13: 4 | D13: =SUM((B13*9/5)+32) -> 32 | E13: =SUM((C13*9/5)+32) -> 32 | F13: =SUM(((B13+C13)/2)-18.33) -> -18.33 | G13: =SUM(0+(F13)+ABS(F13))/2 -> 0 | H13: =IF((SUM(0-(F13)+ABS(F13))/2)<18,SUM(0-(F13)+ABS(F13))/2,0) -> 0 | I13: =SUM(G10:G13) -> 0 | J13: =SUM(H10:H13) -> 0
A14: 5 | D14: =SUM((B14*9/5)+32) -> 32 | E14: =SUM((C14*9/5)+32) -> 32 | F14: =SUM(((B14+C14)/2)-18.33) -> -18.33 | G14: =SUM(0+(F14)+ABS(F14))/2 -> 0 | H14: =IF((SUM(0-(F14)+ABS(F14))/2)<18,SUM(0-(F14)+ABS(F14))/2,0) -> 0 | I14: =SUM(G10:G14) -> 0 | J14: =SUM(H10:H14) -> 0
A15: 6 | D15: =SUM((B15*9/5)+32) -> 32 | E15: =SUM((C15*9/5)+32) -> 32 | F15: =SUM(((B15+C15)/2)-18.33) -> -18.33 | G15: =SUM(0+(F15)+ABS(F15))/2 -> 0 | H15: =IF((SUM(0-(F15)+ABS(F15))/2)<18,SUM(0-(F15)+ABS(F15))/2,0) -> 0 | I15: =SUM(G10:G15) -> 0 | J15: =SUM(H10:H15) -> 0
A16: 7 | D16: =SUM((B16*9/5)+32) -> 32 | E16: =SUM((C16*9/5)+32) -> 32 | F16: =SUM(((B16+C16)/2)-18.33) -> -18.33 | G16: =SUM(0+(F16)+ABS(F16))/2 -> 0 | H16: =IF((SUM(0-(F16)+ABS(F16))/2)<18,SUM(0-(F16)+ABS(F16))/2,0) -> 0 | I16: =SUM(G10:G16) -> 0 | J16: =SUM(H10:H16) -> 0
A17: 8 | D17: =SUM((B17*9/5)+32) -> 32 | E17: =SUM((C17*9/5)+32) -> 32 | F17: =SUM(((B17+C17)/2)-18.33) -> -18.33 | G17: =SUM(0+(F17)+ABS(F17))/2 -> 0 | H17: =IF((SUM(0-(F17)+ABS(F17))/2)<18,SUM(0-(F17)+ABS(F17))/2,0) -> 0 | I17: =SUM(G10:G17) -> 0 | J17: =SUM(H10:H17) -> 0
A18: 9 | D18: =SUM((B18*9/5)+32) -> 32 | E18: =SUM((C18*9/5)+32) -> 32 | F18: =SUM(((B18+C18)/2)-18.33) -> -18.33 | G18: =SUM(0+(F18)+ABS(F18))/2 -> 0 | H18: =IF((SUM(0-(F18)+ABS(F18))/2)<18,SUM(0-(F18)+ABS(F18))/2,0) -> 0 | I18: =SUM(G10:G18) -> 0 | J18: =SUM(H10:H18) -> 0
A19: 10 | D19: =SUM((B19*9/5)+32) -> 32 | E19: =SUM((C19*9/5)+32) -> 32 | F19: =SUM(((B19+C19)/2)-18.33) -> -18.33 | G19: =SUM(0+(F19)+ABS(F19))/2 -> 0 | H19: =IF((SUM(0-(F19)+ABS(F19))/2)<18,SUM(0-(F19)+ABS(F19))/2,0) -> 0 | I19: =SUM(G10:G19) -> 0 | J19: =SUM(H10:H19) -> 0
A20: 11 | D20: =SUM((B20*9/5)+32) -> 32 | E20: =SUM((C20*9/5)+32) -> 32 | F20: =SUM(((B20+C20)/2)-18.33) -> -18.33 | G20: =SUM(0+(F20)+ABS(F20))/2 -> 0 | H20: =IF((SUM(0-(F20)+ABS(F20))/2)<18,SUM(0-(F20)+ABS(F20))/2,0) -> 0 | I20: =SUM(G10:G20) -> 0 | J20: =SUM(H10:H20) -> 0
A21: 12 | D21: =SUM((B21*9/5)+32) -> 32 | E21: =SUM((C21*9/5)+32) -> 32 | F21: =SUM(((B21+C21)/2)-18.33) -> -18.33 | G21: =SUM(0+(F21)+ABS(F21))/2 -> 0 | H21: =IF((SUM(0-(F21)+ABS(F21))/2)<18,SUM(0-(F21)+ABS(F21))/2,0) -> 0 | I21: =SUM(G10:G21) -> 0 | J21: =SUM(H10:H21) -> 0
A22: 13 | D22: =SUM((B22*9/5)+32) -> 32 | E22: =SUM((C22*9/5)+32) -> 32 | F22: =SUM(((B22+C22)/2)-18.33) -> -18.33 | G22: =SUM(0+(F22)+ABS(F22))/2 -> 0 | H22: =IF((SUM(0-(F22)+ABS(F22))/2)<18,SUM(0-(F22)+ABS(F22))/2,0) -> 0 | I22: =SUM(G10:G22) -> 0 | J22: =SUM(H10:H22) -> 0
A23: 14 | D23: =SUM((B23*9/5)+32) -> 32 | E23: =SUM((C23*9/5)+32) -> 32 | F23: =SUM(((B23+C23)/2)-18.33) -> -18.33 | G23: =SUM(0+(F23)+ABS(F23))/2 -> 0 | H23: =IF((SUM(0-(F23)+ABS(F23))/2)<18,SUM(0-(F23)+ABS(F23))/2,0) -> 0 | I23: =SUM(G10:G23) -> 0 | J23: =SUM(H10:H23) -> 0
A24: 15 | D24: =SUM((B24*9/5)+32) -> 32 | E24: =SUM((C24*9/5)+32) -> 32 | F24: =SUM(((B24+C24)/2)-18.33) -> -18.33 | G24: =SUM(0+(F24)+ABS(F24))/2 -> 0 | H24: =IF((SUM(0-(F24)+ABS(F24))/2)<18,SUM(0-(F24)+ABS(F24))/2,0) -> 0 | I24: =SUM(G11:G24) -> 0 | J24: =SUM(H11:H24) -> 0
A25: 16 | D25: =SUM((B25*9/5)+32) -> 32 | E25: =SUM((C25*9/5)+32) -> 32 | F25: =SUM(((B25+C25)/2)-18.33) -> -18.33 | G25: =SUM(0+(F25)+ABS(F25))/2 -> 0 | H25: =IF((SUM(0-(F25)+ABS(F25))/2)<18,SUM(0-(F25)+ABS(F25))/2,0) -> 0 | I25: =SUM(G12:G25) -> 0 | J25: =SUM(H12:H25) -> 0
A26: 17 | D26: =SUM((B26*9/5)+32) -> 32 | E26: =SUM((C26*9/5)+32) -> 32 | F26: =SUM(((B26+C26)/2)-18.33) -> -18.33 | G26: =SUM(0+(F26)+ABS(F26))/2 -> 0 | H26: =IF((SUM(0-(F26)+ABS(F26))/2)<18,SUM(0-(F26)+ABS(F26))/2,0) -> 0 | I26: =SUM(G13:G26) -> 0 | J26: =SUM(H13:H26) -> 0
A27: 18 | D27: =SUM((B27*9/5)+32) -> 32 | E27: =SUM((C27*9/5)+32) -> 32 | F27: =SUM(((B27+C27)/2)-18.33) -> -18.33 | G27: =SUM(0+(F27)+ABS(F27))/2 -> 0 | H27: =IF((SUM(0-(F27)+ABS(F27))/2)<18,SUM(0-(F27)+ABS(F27))/2,0) -> 0 | I27: =SUM(G14:G27) -> 0 | J27: =SUM(H14:H27) -> 0
A28: 19 | D28: =SUM((B28*9/5)+32) -> 32 | E28: =SUM((C28*9/5)+32) -> 32 | F28: =SUM(((B28+C28)/2)-18.33) -> -18.33 | G28: =SUM(0+(F28)+ABS(F28))/2 -> 0 | H28: =IF((SUM(0-(F28)+ABS(F28))/2)<18,SUM(0-(F28)+ABS(F28))/2,0) -> 0 | I28: =SUM(G15:G28) -> 0 | J28: =SUM(H15:H28) -> 0
A29: 20 | D29: =SUM((B29*9/5)+32) -> 32 | E29: =SUM((C29*9/5)+32) -> 32 | F29: =SUM(((B29+C29)/2)-18.33) -> -18.33 | G29: =SUM(0+(F29)+ABS(F29))/2 -> 0 | H29: =IF((SUM(0-(F29)+ABS(F29))/2)<18,SUM(0-(F29)+ABS(F29))/2,0) -> 0 | I29: =SUM(G16:G29) -> 0 | J29: =SUM(H16:H29) -> 0
A30: 21 | D30: =SUM((B30*9/5)+32) -> 32 | E30: =SUM((C30*9/5)+32) -> 32 | F30: =SUM(((B30+C30)/2)-18.33) -> -18.33 | G30: =SUM(0+(F30)+ABS(F30))/2 -> 0 | H30: =IF((SUM(0-(F30)+ABS(F30))/2)<18,SUM(0-(F30)+ABS(F30))/2,0) -> 0 | I30: =SUM(G17:G30) -> 0 | J30: =SUM(H17:H30) -> 0
A31: 22 | D31: =SUM((B31*9/5)+32) -> 32 | E31: =SUM((C31*9/5)+32) -> 32 | F31: =SUM(((B31+C31)/2)-18.33) -> -18.33 | G31: =SUM(0+(F31)+ABS(F31))/2 -> 0 | H31: =IF((SUM(0-(F31)+ABS(F31))/2)<18,SUM(0-(F31)+ABS(F31))/2,0) -> 0 | I31: =SUM(G18:G31) -> 0 | J31: =SUM(H18:H31) -> 0
A32: 23 | D32: =SUM((B32*9/5)+32) -> 32 | E32: =SUM((C32*9/5)+32) -> 32 | F32: =SUM(((B32+C32)/2)-18.33) -> -18.33 | G32: =SUM(0+(F32)+ABS(F32))/2 -> 0 | H32: =IF((SUM(0-(F32)+ABS(F32))/2)<18,SUM(0-(F32)+ABS(F32))/2,0) -> 0 | I32: =SUM(G19:G32) -> 0 | J32: =SUM(H19:H32) -> 0
A33: 24 | D33: =SUM((B33*9/5)+32) -> 32 | E33: =SUM((C33*9/5)+32) -> 32 | F33: =SUM(((B33+C33)/2)-18.33) -> -18.33 | G33: =SUM(0+(F33)+ABS(F33))/2 -> 0 | H33: =IF((SUM(0-(F33)+ABS(F33))/2)<18,SUM(0-(F33)+ABS(F33))/2,0) -> 0 | I33: =SUM(G20:G33) -> 0 | J33: =SUM(H20:H33) -> 0
A34: 25 | D34: =SUM((B34*9/5)+32) -> 32 | E34: =SUM((C34*9/5)+32) -> 32 | F34: =SUM(((B34+C34)/2)-18.33) -> -18.33 | G34: =SUM(0+(F34)+ABS(F34))/2 -> 0 | H34: =IF((SUM(0-(F34)+ABS(F34))/2)<18,SUM(0-(F34)+ABS(F34))/2,0) -> 0 | I34: =SUM(G21:G34) -> 0 | J34: =SUM(H21:H34) -> 0
... A40: 31 | D40: =SUM((B40*9/5)+32) -> 32 | E40: =SUM((C40*9/5)+32) -> 32 | F40: =SUM(((B40+C40)/2)-18.33) -> -18.33 | G40: =SUM(0+(F40)+ABS(F40))/2 -> 0 | H40: =IF((SUM(0-(F40)+ABS(F40))/2)<18,SUM(0-(F40)+ABS(F40))/2,0) -> 0 | I40: =SUM(G27:G40) -> 0 | J40: =SUM(H27:H40) -> 0
E42: =SUM(G10:G40) -> 0 | F42: deg c
E44: =SUM(H10:H40) -> 0 | F44: deg c

Sheet M-Rep
B3: =Elect!A1 -> January
D4: Y.T.D
A5: Energy breakdown | C5: 2009 | D5: 2005 | E5: 2006
A6: Elect.
A7: Chillers KWH | C7: N/A | D7: N/A | E7: N/A
A8: Laundry KWH | C8: N/A | D8: N/A | E8: N/A
A9: Kitchen KWH | C9: N/A | D9: N/A | E9: N/A
A10: Gas
A11: Kit M3 | C11: =Gas!#REF!/1000 -> #REF!
A12: Laundry M3 | C12: N/A | D12: 0 | E12: #REF!
A13: Water | D13: N/A | E13: N/A
A14: Laundry HW | C14: N/A
A15: Laundry CW | C15: N/A
A16: Kit HW | C16: N/A
A17: kIt CW | C17: N/A | D17: N/A | E17: N/A
A18: Dmstc HW | C18: N/A | D18: N/A | E18: N/A
A19: Dmstc CW | C19: N/A | D19: N/A | E19: N/A
A20: S.Pool MKUP | C20: =#REF! -> #REF! | D20: N/A | E20: N/A
A21: Ctower MKUP | C21: N/A | D21: N/A | E21: N/A
A22: Gardens Irrigat. | C22: =Water!S38 -> 0 | D22: N/A | E22: N/A
A23: Swage water treatment | C23: =Water!#REF! -> #REF! | D23: 27437 | E23: #REF!
A24: Utilities consumption | D24: N/A | E24: N/A
A25: Elect. Kwh | C25: =Elect!J34 -> 7572 | D25: 12266 | E25: 814
A26: M.D (9.5 LE) | D26: 147773 | E26: #REF!
A27: Water M3 | C27: =Water!H38 -> 10316.46
A28: Fuel Ltr | C28: =Gas!#REF!*1000 -> #REF! | D28: 12876868 | E28: 14500800
A29: Gas M3/ Boilers, chillers,..etc | C29: N/A | D29: 28880 | E29: 32980
A30: Gas M3 Kitchen | C30: =Gas!#REF!/1000 -> #REF! | D30: 244283 | E30: 252530.66
A31: Total Energy | D31: 620770 | E31: #REF!
A32: Control Parameters | D32: #REF! | E32: N/A
A33: No. of Rooms % occ. | C33: =YTD!Q4 -> 0 | D33: 39.395 | E33: #REF!
A34: No. of Occ. Rooms | C34: =YTD!Q5 -> 0
A35: guest count | C35: =YTD!Q6 -> 0
A36: Food covers | D36: #REF! | E36: #REF!
A37: Laundry W. Kg | D37: 0.8807 | E37: 0.46351998
A38: DDC | C38: =Temp.!E42 -> 0 | D38: 196150 | E38: 237021
A39: DDH | C39: =Temp.!E44 -> 0 | D39: 400070 | E39: 466105
A40: Utilities Entergy cost | D40: 1583714 | E40: 1940567
A41: Elect. | C41: =Elect!#REF! -> #REF! | D41: 1690339 | E41: 3118671.6
A42: M.D | C42: =C26*Elect!#REF! -> #REF! | D42: 2381.51 | E42: 2480.24
A43: Water | C43: =Water!X38 -> 40129.04 | D43: 112 | E43: 97.53
A44: Fuel | C44: =Gas!#REF! -> #REF!
A45: Gas Boilers, chillers,etc.. | C45: N/A | D45: 2138156.8 | E45: #REF!
A46: Gas Kitchen | C46: =C30*Gas!M2*1000 -> #REF! | D46: 223044.2 | E46: #REF!
A47: TOTAL LE | C47: =SUM(C41:C46) -> #REF! | D47: 1330535.7 | E47: 1382037.4
A48: No. of POMEC Staff | D48: 330278 | E48: #REF!
A49: Hotel Age | C49: 6 | D49: N/A | E49: N/A
A50: No. of rooms | C50: =31*912 -> 28272 | D50: 36597.525 | E50: #REF!
A51: Building Volume | C51: 243175 | D51: =SUM(D45:D50) -> 4058612.3 | E51: =SUM(E45:E50) -> #REF!
A52: Building area | C52: 75064
A53: US$ Rate | C53: 5.59402 | D53: 61 | E53: 72
A54: Total R&M MTD | C54: =YTD!Q65 -> 0 | D54: #REF! | E54: 243175 | F54: =YTD!Q64 -> 0
A55: Staff - HLP | D55: #REF! | E55: 75064
A56: Staff - R&M | D56: 5.755 | E56: 5.65951
A57: Staff - Grounds

Sheet YTD
A1: =Elect!A1 -> January | H1: Actual 2014
C3: JAN | D3: FEB | E3: MAR | F3: APR | G3: MAY | H3: JUN | I3: JUL | J3: AUG | K3: SEP | L3: OCT | M3: NOV | N3: DEC | O3: TOTAL | P3: YTD | Q3: Month Act
A4: Occ Room % | O4: =SUM(C4:N4) -> 0 | P4: =(IF($A$1=39814,C4,(IF($A$1=39845,SUM(C4:D4),(IF($A$1=39873,SUM(C4:E4),(IF($A$1=39904,SUM(C4:F4),(IF($A$1=39934,SUM(C4:G4),(IF($A$1=39965,SUM(C4:H4),(IF($A$1=39995,SUM(C4:I4),0)))))))))))))+(IF($A$1=40026,SUM(C4:J4),(IF($A$1=40057,SUM(C4:K4),(IF($A$1=40087,SUM(C4:L4),(IF($A$1=40118,SUM(C4:M4))))))))))+(IF($A$1=40148,SUM(C4:N4),0)) -> 0 | Q4: =(IF($A$1=39814,C4,(IF($A$1=39845,D4,(IF($A$1=39873,E4,(IF($A$1=39904,F4,(IF($A$1=39934,G4,(IF($A$1=39965,H4,(IF($A$1=39995,I4,0)))))))))))))+(IF($A$1=40026,J4,(IF($A$1=40057,K4,(IF($A$1=40087,L4,(IF($A$1=40118,M4)))))))))+(IF($A$1=40148,N4,0)) -> 0 | S4: 40179 | DE4: 1
A5: Occ Room | C5: 25072 | D5: =Elect!BP34 -> 144 | O5: =SUM(C5:N5) -> 25216 | P5: =(IF($A$1=40179,C5,(IF($A$1=40210,SUM(C5:D5),(IF($A$1=40238,SUM(C5:E5),(IF($A$1=40269,SUM(C5:F5),(IF($A$1=40299,SUM(C5:G5),(IF($A$1=40330,SUM(C5:H5),(IF($A$1=40360,SUM(C5:I5),0)))))))))))))+(IF($A$1=40391,SUM(C5:J5),(IF($A$1=40422,SUM(C5:K5),(IF($A$1=40452,SUM(C5:L5),(IF($A$1=40483,SUM(C5:M5))))))))))+(IF($A$1=40513,SUM(C5:N5),0)) -> 0 | Q5: =(IF($A$1=40179,C5,(IF($A$1=40210,D5,(IF($A$1=40238,E5,(IF($A$1=40269,F5,(IF($A$1=40299,G5,(IF($A$1=40330,H5,(IF($A$1=40360,I5,0)))))))))))))+(IF($A$1=40391,J5,(IF($A$1=40422,K5,(IF($A$1=40452,L5,(IF($A$1=40483,M5)))))))))+(IF($A$1=40513,N5,0)) -> 0 | S5: 40210 | DE5: 2
A6: Number of Guest | C6: 50662 | D6: =Elect!BR34 -> 133 | O6: =SUM(C6:N6) -> 50795 | P6: =(IF($A$1=40179,C6,(IF($A$1=40210,SUM(C6:D6),(IF($A$1=40238,SUM(C6:E6),(IF($A$1=40269,SUM(C6:F6),(IF($A$1=40299,SUM(C6:G6),(IF($A$1=40330,SUM(C6:H6),(IF($A$1=40360,SUM(C6:I6),0)))))))))))))+(IF($A$1=40391,SUM(C6:J6),(IF($A$1=40422,SUM(C6:K6),(IF($A$1=40452,SUM(C6:L6),(IF($A$1=40483,SUM(C6:M6))))))))))+(IF($A$1=40513,SUM(C6:N6),0)) -> 0 | Q6: =(IF($A$1=40179,C6,(IF($A$1=40210,D6,(IF($A$1=40238,E6,(IF($A$1=40269,F6,(IF($A$1=40299,G6,(IF($A$1=40330,H6,(IF($A$1=40360,I6,0)))))))))))))+(IF($A$1=40391,J6,(IF($A$1=40422,K6,(IF($A$1=40452,L6,(IF($A$1=40483,M6)))))))))+(IF($A$1=40513,N6,0)) -> 0 | S6: 40238 | DE6: 3
A7: PAY & REL. EXP. | O7: =SUM(C7:N7) -> 0 | P7: =(IF($A$1=40179,C7,(IF($A$1=40210,SUM(C7:D7),(IF($A$1=40238,SUM(C7:E7),(IF($A$1=40269,SUM(C7:F7),(IF($A$1=40299,SUM(C7:G7),(IF($A$1=40330,SUM(C7:H7),(IF($A$1=40360,SUM(C7:I7),0)))))))))))))+(IF($A$1=40391,SUM(C7:J7),(IF($A$1=40422,SUM(C7:K7),(IF($A$1=40452,SUM(C7:L7),(IF($A$1=40483,SUM(C7:M7))))))))))+(IF($A$1=40513,SUM(C7:N7),0)) -> 0 | Q7: =(IF($A$1=40179,C7,(IF($A$1=40210,D7,(IF($A$1=40238,E7,(IF($A$1=40269,F7,(IF($A$1=40299,G7,(IF($A$1=40330,H7,(IF($A$1=40360,I7,0)))))))))))))+(IF($A$1=40391,J7,(IF($A$1=40422,K7,(IF($A$1=40452,L7,(IF($A$1=40483,M7)))))))))+(IF($A$1=40513,N7,0)) -> 0
A8: SALARIES | B8: 53241001 | O8: =SUM(C8:N8) -> 0 | P8: =(IF($A$1=40179,C8,(IF($A$1=40210,SUM(C8:D8),(IF($A$1=40238,SUM(C8:E8),(IF($A$1=40269,SUM(C8:F8),(IF($A$1=40299,SUM(C8:G8),(IF($A$1=40330,SUM(C8:H8),(IF($A$1=40360,SUM(C8:I8),0)))))))))))))+(IF($A$1=40391,SUM(C8:J8),(IF($A$1=40422,SUM(C8:K8),(IF($A$1=40452,SUM(C8:L8),(IF($A$1=40483,SUM(C8:M8))))))))))+(IF($A$1=40513,SUM(C8:N8),0)) -> 0 | Q8: =(IF($A$1=40179,C8,(IF($A$1=40210,D8,(IF($A$1=40238,E8,(IF($A$1=40269,F8,(IF($A$1=40299,G8,(IF($A$1=40330,H8,(IF($A$1=40360,I8,0)))))))))))))+(IF($A$1=40391,J8,(IF($A$1=40422,K8,(IF($A$1=40452,L8,(IF($A$1=40483,M8)))))))))+(IF($A$1=40513,N8,0)) -> 0
A9: EXTRA WAGES | B9: 53242099 | O9: =SUM(C9:N9) -> 0 | P9: =(IF($A$1=40179,C9,(IF($A$1=40210,SUM(C9:D9),(IF($A$1=40238,SUM(C9:E9),(IF($A$1=40269,SUM(C9:F9),(IF($A$1=40299,SUM(C9:G9),(IF($A$1=40330,SUM(C9:H9),(IF($A$1=40360,SUM(C9:I9),0)))))))))))))+(IF($A$1=40391,SUM(C9:J9),(IF($A$1=40422,SUM(C9:K9),(IF($A$1=40452,SUM(C9:L9),(IF($A$1=40483,SUM(C9:M9))))))))))+(IF($A$1=40513,SUM(C9:N9),0)) -> 0 | Q9: =(IF($A$1=40179,C9,(IF($A$1=40210,D9,(IF($A$1=40238,E9,(IF($A$1=40269,F9,(IF($A$1=40299,G9,(IF($A$1=40330,H9,(IF($A$1=40360,I9,0)))))))))))))+(IF($A$1=40391,J9,(IF($A$1=40422,K9,(IF($A$1=40452,L9,(IF($A$1=40483,M9)))))))))+(IF($A$1=40513,N9,0)) -> 0
A10: SERVICE | B10: 53243001 | O10: =SUM(C10:N10) -> 0 | P10: =(IF($A$1=40179,C10,(IF($A$1=40210,SUM(C10:D10),(IF($A$1=40238,SUM(C10:E10),(IF($A$1=40269,SUM(C10:F10),(IF($A$1=40299,SUM(C10:G10),(IF($A$1=40330,SUM(C10:H10),(IF($A$1=40360,SUM(C10:I10),0)))))))))))))+(IF($A$1=40391,SUM(C10:J10),(IF($A$1=40422,SUM(C10:K10),(IF($A$1=40452,SUM(C10:L10),(IF($A$1=40483,SUM(C10:M10))))))))))+(IF($A$1=40513,SUM(C10:N10),0)) -> 0 | Q10: =(IF($A$1=40179,C10,(IF($A$1=40210,D10,(IF($A$1=40238,E10,(IF($A$1=40269,F10,(IF($A$1=40299,G10,(IF($A$1=40330,H10,(IF($A$1=40360,I10,0)))))))))))))+(IF($A$1=40391,J10,(IF($A$1=40422,K10,(IF($A$1=40452,L10,(IF($A$1=40483,M10)))))))))+(IF($A$1=40513,N10,0)) -> 0
A11: RELATED EXP. | B11: 53244001 | O11: =SUM(C11:N11) -> 0 | P11: =(IF($A$1=40179,C11,(IF($A$1=40210,SUM(C11:D11),(IF($A$1=40238,SUM(C11:E11),(IF($A$1=40269,SUM(C11:F11),(IF($A$1=40299,SUM(C11:G11),(IF($A$1=40330,SUM(C11:H11),(IF($A$1=40360,SUM(C11:I11),0)))))))))))))+(IF($A$1=40391,SUM(C11:J11),(IF($A$1=40422,SUM(C11:K11),(IF($A$1=40452,SUM(C11:L11),(IF($A$1=40483,SUM(C11:M11))))))))))+(IF($A$1=40513,SUM(C11:N11),0)) -> 0 | Q11: =(IF($A$1=40179,C11,(IF($A$1=40210,D11,(IF($A$1=40238,E11,(IF($A$1=40269,F11,(IF($A$1=40299,G11,(IF($A$1=40330,H11,(IF($A$1=40360,I11,0)))))))))))))+(IF($A$1=40391,J11,(IF($A$1=40422,K11,(IF($A$1=40452,L11,(IF($A$1=40483,M11)))))))))+(IF($A$1=40513,N11,0)) -> 0
A12: EMPL. MEALS | B12: 53245001 | O12: =SUM(C12:N12) -> 0 | P12: =(IF($A$1=40179,C12,(IF($A$1=40210,SUM(C12:D12),(IF($A$1=40238,SUM(C12:E12),(IF($A$1=40269,SUM(C12:F12),(IF($A$1=40299,SUM(C12:G12),(IF($A$1=40330,SUM(C12:H12),(IF($A$1=40360,SUM(C12:I12),0)))))))))))))+(IF($A$1=40391,SUM(C12:J12),(IF($A$1=40422,SUM(C12:K12),(IF($A$1=40452,SUM(C12:L12),(IF($A$1=40483,SUM(C12:M12))))))))))+(IF($A$1=40513,SUM(C12:N12),0)) -> 0 | Q12: =(IF($A$1=40179,C12,(IF($A$1=40210,D12,(IF($A$1=40238,E12,(IF($A$1=40269,F12,(IF($A$1=40299,G12,(IF($A$1=40330,H12,(IF($A$1=40360,I12,0)))))))))))))+(IF($A$1=40391,J12,(IF($A$1=40422,K12,(IF($A$1=40452,L12,(IF($A$1=40483,M12)))))))))+(IF($A$1=40513,N12,0)) -> 0
O13: =SUM(C13:N13) -> 0 | P13: =(IF($A$1=40179,C13,(IF($A$1=40210,SUM(C13:D13),(IF($A$1=40238,SUM(C13:E13),(IF($A$1=40269,SUM(C13:F13),(IF($A$1=40299,SUM(C13:G13),(IF($A$1=40330,SUM(C13:H13),(IF($A$1=40360,SUM(C13:I13),0)))))))))))))+(IF($A$1=40391,SUM(C13:J13),(IF($A$1=40422,SUM(C13:K13),(IF($A$1=40452,SUM(C13:L13),(IF($A$1=40483,SUM(C13:M13))))))))))+(IF($A$1=40513,SUM(C13:N13),0)) -> 0 | Q13: =(IF($A$1=40179,C13,(IF($A$1=40210,D13,(IF($A$1=40238,E13,(IF($A$1=40269,F13,(IF($A$1=40299,G13,(IF($A$1=40330,H13,(IF($A$1=40360,I13,0)))))))))))))+(IF($A$1=40391,J13,(IF($A$1=40422,K13,(IF($A$1=40452,L13,(IF($A$1=40483,M13)))))))))+(IF($A$1=40513,N13,0)) -> 0
A14: TOTAL PAY & REL. | C14: 147832.84 | D14: 158624 | O14: =SUM(C14:N14) -> 306456.84 | P14: =(IF($A$1=40179,C14,(IF($A$1=40210,SUM(C14:D14),(IF($A$1=40238,SUM(C14:E14),(IF($A$1=40269,SUM(C14:F14),(IF($A$1=40299,SUM(C14:G14),(IF($A$1=40330,SUM(C14:H14),(IF($A$1=40360,SUM(C14:I14),0)))))))))))))+(IF($A$1=40391,SUM(C14:J14),(IF($A$1=40422,SUM(C14:K14),(IF($A$1=40452,SUM(C14:L14),(IF($A$1=40483,SUM(C14:M14))))))))))+(IF($A$1=40513,SUM(C14:N14),0)) -> 0 | Q14: =(IF($A$1=40179,C14,(IF($A$1=40210,D14,(IF($A$1=40238,E14,(IF($A$1=40269,F14,(IF($A$1=40299,G14,(IF($A$1=40330,H14,(IF($A$1=40360,I14,0)))))))))))))+(IF($A$1=40391,J14,(IF($A$1=40422,K14,(IF($A$1=40452,L14,(IF($A$1=40483,M14)))))))))+(IF($A$1=40513,N14,0)) -> 0 | S14: 40269 | DE14: 4
A15: ELECRICITY | B15: 53257511 | C15: 267068.09 | D15: 312865.7 | O15: =SUM(C15:N15) -> 579933.79 | P15: =(IF($A$1=40179,C15,(IF($A$1=40210,SUM(C15:D15),(IF($A$1=40238,SUM(C15:E15),(IF($A$1=40269,SUM(C15:F15),(IF($A$1=40299,SUM(C15:G15),(IF($A$1=40330,SUM(C15:H15),(IF($A$1=40360,SUM(C15:I15),0)))))))))))))+(IF($A$1=40391,SUM(C15:J15),(IF($A$1=40422,SUM(C15:K15),(IF($A$1=40452,SUM(C15:L15),(IF($A$1=40483,SUM(C15:M15))))))))))+(IF($A$1=40513,SUM(C15:N15),0)) -> 0 | Q15: =(IF($A$1=40179,C15,(IF($A$1=40210,D15,(IF($A$1=40238,E15,(IF($A$1=40269,F15,(IF($A$1=40299,G15,(IF($A$1=40330,H15,(IF($A$1=40360,I15,0)))))))))))))+(IF($A$1=40391,J15,(IF($A$1=40422,K15,(IF($A$1=40452,L15,(IF($A$1=40483,M15)))))))))+(IF($A$1=40513,N15,0)) -> 0 | S15: 40299 | DE15: 5
A16: WATER & SEWAGE | B16: 53257551 | C16: 178948 | D16: 189620 | O16: =SUM(C16:N16) -> 368568 | P16: =(IF($A$1=40179,C16,(IF($A$1=40210,SUM(C16:D16),(IF($A$1=40238,SUM(C16:E16),(IF($A$1=40269,SUM(C16:F16),(IF($A$1=40299,SUM(C16:G16),(IF($A$1=40330,SUM(C16:H16),(IF($A$1=40360,SUM(C16:I16),0)))))))))))))+(IF($A$1=40391,SUM(C16:J16),(IF($A$1=40422,SUM(C16:K16),(IF($A$1=40452,SUM(C16:L16),(IF($A$1=40483,SUM(C16:M16))))))))))+(IF($A$1=40513,SUM(C16:N16),0)) -> 0 | Q16: =(IF($A$1=40179,C16,(IF($A$1=40210,D16,(IF($A$1=40238,E16,(IF($A$1=40269,F16,(IF($A$1=40299,G16,(IF($A$1=40330,H16,(IF($A$1=40360,I16,0)))))))))))))+(IF($A$1=40391,J16,(IF($A$1=40422,K16,(IF($A$1=40452,L16,(IF($A$1=40483,M16)))))))))+(IF($A$1=40513,N16,0)) -> 0 | S16: 40330 | DE16: 6
A17: FUEL | B17: 53257571 | C17: 82735 | D17: 123809 | O17: =SUM(C17:N17) -> 206544 | P17: =(IF($A$1=40179,C17,(IF($A$1=40210,SUM(C17:D17),(IF($A$1=40238,SUM(C17:E17),(IF($A$1=40269,SUM(C17:F17),(IF($A$1=40299,SUM(C17:G17),(IF($A$1=40330,SUM(C17:H17),(IF($A$1=40360,SUM(C17:I17),0)))))))))))))+(IF($A$1=40391,SUM(C17:J17),(IF($A$1=40422,SUM(C17:K17),(IF($A$1=40452,SUM(C17:L17),(IF($A$1=40483,SUM(C17:M17))))))))))+(IF($A$1=40513,SUM(C17:N17),0)) -> 0 | Q17: =(IF($A$1=40179,C17,(IF($A$1=40210,D17,(IF($A$1=40238,E17,(IF($A$1=40269,F17,(IF($A$1=40299,G17,(IF($A$1=40330,H17,(IF($A$1=40360,I17,0)))))))))))))+(IF($A$1=40391,J17,(IF($A$1=40422,K17,(IF($A$1=40452,L17,(IF($A$1=40483,M17)))))))))+(IF($A$1=40513,N17,0)) -> 0 | S17: 40360 | DE17: 7
A18: gas | B18: 0 | C18: 0 | D18: 0 | E18: 0 | F18: 0 | G18: 0 | H18: 0 | O18: =SUM(C18:N18) -> 0 | P18: =(IF($A$1=40179,C18,(IF($A$1=40210,SUM(C18:D18),(IF($A$1=40238,SUM(C18:E18),(IF($A$1=40269,SUM(C18:F18),(IF($A$1=40299,SUM(C18:G18),(IF($A$1=40330,SUM(C18:H18),(IF($A$1=40360,SUM(C18:I18),0)))))))))))))+(IF($A$1=40391,SUM(C18:J18),(IF($A$1=40422,SUM(C18:K18),(IF($A$1=40452,SUM(C18:L18),(IF($A$1=40483,SUM(C18:M18))))))))))+(IF($A$1=40513,SUM(C18:N18),0)) -> 0 | Q18: =(IF($A$1=40179,C18,(IF($A$1=40210,D18,(IF($A$1=40238,E18,(IF($A$1=40269,F18,(IF($A$1=40299,G18,(IF($A$1=40330,H18,(IF($A$1=40360,I18,0)))))))))))))+(IF($A$1=40391,J18,(IF($A$1=40422,K18,(IF($A$1=40452,L18,(IF($A$1=40483,M18)))))))))+(IF($A$1=40513,N18,0)) -> 0 | S18: 40391 | DE18: 8
A19: TOTAL ENERGY | C19: =SUM(C15:C18) -> 528751.09 | D19: =SUM(D15:D18) -> 626294.7 | E19: =SUM(E15:E18) -> 0 | F19: =SUM(F15:F18) -> 0 | G19: =SUM(G15:G18) -> 0 | H19: =SUM(H15:H18) -> 0 | I19: =SUM(I15:I18) -> 0 | J19: =SUM(J15:J18) -> 0 | ... O19: =SUM(O15:O18) -> 1155045.8 | P19: =(IF($A$1=40179,C19,(IF($A$1=40210,SUM(C19:D19),(IF($A$1=40238,SUM(C19:E19),(IF($A$1=40269,SUM(C19:F19),(IF($A$1=40299,SUM(C19:G19),(IF($A$1=40330,SUM(C19:H19),(IF($A$1=40360,SUM(C19:I19),0)))))))))))))+(IF($A$1=40391,SUM(C19:J19),(IF($A$1=40422,SUM(C19:K19),(IF($A$1=40452,SUM(C19:L19),(IF($A$1=40483,SUM(C19:M19))))))))))+(IF($A$1=40513,SUM(C19:N19),0)) -> 0 | Q19: =(IF($A$1=40179,C19,(IF($A$1=40210,D19,(IF($A$1=40238,E19,(IF($A$1=40269,F19,(IF($A$1=40299,G19,(IF($A$1=40330,H19,(IF($A$1=40360,I19,0)))))))))))))+(IF($A$1=40391,J19,(IF($A$1=40422,K19,(IF($A$1=40452,L19,(IF($A$1=40483,M19)))))))))+(IF($A$1=40513,N19,0)) -> 0 | S19: 40422 | DE19: 9
P20: =(IF($A$1=40179,C20,(IF($A$1=40210,SUM(C20:D20),(IF($A$1=40238,SUM(C20:E20),(IF($A$1=40269,SUM(C20:F20),(IF($A$1=40299,SUM(C20:G20),(IF($A$1=40330,SUM(C20:H20),(IF($A$1=40360,SUM(C20:I20),0)))))))))))))+(IF($A$1=40391,SUM(C20:J20),(IF($A$1=40422,SUM(C20:K20),(IF($A$1=40452,SUM(C20:L20),(IF($A$1=40483,SUM(C20:M20))))))))))+(IF($A$1=40513,SUM(C20:N20),0)) -> 0 | Q20: =(IF($A$1=40179,C20,(IF($A$1=40210,D20,(IF($A$1=40238,E20,(IF($A$1=40269,F20,(IF($A$1=40299,G20,(IF($A$1=40330,H20,(IF($A$1=40360,I20,0)))))))))))))+(IF($A$1=40391,J20,(IF($A$1=40422,K20,(IF($A$1=40452,L20,(IF($A$1=40483,M20)))))))))+(IF($A$1=40513,N20,0)) -> 0
A21: OTHER EXPENSES | P21: =(IF($A$1=40179,C21,(IF($A$1=40210,SUM(C21:D21),(IF($A$1=40238,SUM(C21:E21),(IF($A$1=40269,SUM(C21:F21),(IF($A$1=40299,SUM(C21:G21),(IF($A$1=40330,SUM(C21:H21),(IF($A$1=40360,SUM(C21:I21),0)))))))))))))+(IF($A$1=40391,SUM(C21:J21),(IF($A$1=40422,SUM(C21:K21),(IF($A$1=40452,SUM(C21:L21),(IF($A$1=40483,SUM(C21:M21))))))))))+(IF($A$1=40513,SUM(C21:N21),0)) -> 0 | Q21: =(IF($A$1=40179,C21,(IF($A$1=40210,D21,(IF($A$1=40238,E21,(IF($A$1=40269,F21,(IF($A$1=40299,G21,(IF($A$1=40330,H21,(IF($A$1=40360,I21,0)))))))))))))+(IF($A$1=40391,J21,(IF($A$1=40422,K21,(IF($A$1=40452,L21,(IF($A$1=40483,M21)))))))))+(IF($A$1=40513,N21,0)) -> 0
A22: P. & ST. | B22: 53251503 | C22: 2782.3724 | D22: 2209.2805 | E22: 3205.3202 | F22: 2604.6091 | G22: 3235.6987 | H22: 2482.8474 | I22: 3129.5287 | J22: 4085.8967 | K22: 4096.0234 | L22: 4111.0374 | M22: 4007.7194 | N22: 3115.8679 | O22: 39066.202 | P22: =(IF($A$1=40179,C22,(IF($A$1=40210,SUM(C22:D22),(IF($A$1=40238,SUM(C22:E22),(IF($A$1=40269,SUM(C22:F22),(IF($A$1=40299,SUM(C22:G22),(IF($A$1=40330,SUM(C22:H22),(IF($A$1=40360,SUM(C22:I22),0)))))))))))))+(IF($A$1=40391,SUM(C22:J22),(IF($A$1=40422,SUM(C22:K22),(IF($A$1=40452,SUM(C22:L22),(IF($A$1=40483,SUM(C22:M22))))))))))+(IF($A$1=40513,SUM(C22:N22),0)) -> 0 | Q22: =(IF($A$1=40179,C22,(IF($A$1=40210,D22,(IF($A$1=40238,E22,(IF($A$1=40269,F22,(IF($A$1=40299,G22,(IF($A$1=40330,H22,(IF($A$1=40360,I22,0)))))))))))))+(IF($A$1=40391,J22,(IF($A$1=40422,K22,(IF($A$1=40452,L22,(IF($A$1=40483,M22)))))))))+(IF($A$1=40513,N22,0)) -> 0
A23: POSTAGE | B23: 53251912 | C23: 0 | D23: 0 | E23: 0 | F23: 0 | G23: 0 | H23: 0 | I23: 0 | J23: 0 | K23: 0 | L23: 0 | M23: 0 | N23: 0 | O23: 0 | P23: =(IF($A$1=40179,C23,(IF($A$1=40210,SUM(C23:D23),(IF($A$1=40238,SUM(C23:E23),(IF($A$1=40269,SUM(C23:F23),(IF($A$1=40299,SUM(C23:G23),(IF($A$1=40330,SUM(C23:H23),(IF($A$1=40360,SUM(C23:I23),0)))))))))))))+(IF($A$1=40391,SUM(C23:J23),(IF($A$1=40422,SUM(C23:K23),(IF($A$1=40452,SUM(C23:L23),(IF($A$1=40483,SUM(C23:M23))))))))))+(IF($A$1=40513,SUM(C23:N23),0)) -> 0 | Q23: =(IF($A$1=40179,C23,(IF($A$1=40210,D23,(IF($A$1=40238,E23,(IF($A$1=40269,F23,(IF($A$1=40299,G23,(IF($A$1=40330,H23,(IF($A$1=40360,I23,0)))))))))))))+(IF($A$1=40391,J23,(IF($A$1=40422,K23,(IF($A$1=40452,L23,(IF($A$1=40483,M23)))))))))+(IF($A$1=40513,N23,0)) -> 0
A24: TAXICAB | B24: 53251919 | C24: 11276.363 | D24: 10009.133 | E24: 9350.2819 | F24: 12862.267 | G24: 10806.952 | H24: 11155.64 | I24: 12970.205 | J24: 10165.751 | K24: 10061.171 | L24: 10190.726 | M24: 10023.319 | N24: 7435.7374 | O24: 126307.55 | P24: =(IF($A$1=40179,C24,(IF($A$1=40210,SUM(C24:D24),(IF($A$1=40238,SUM(C24:E24),(IF($A$1=40269,SUM(C24:F24),(IF($A$1=40299,SUM(C24:G24),(IF($A$1=40330,SUM(C24:H24),(IF($A$1=40360,SUM(C24:I24),0)))))))))))))+(IF($A$1=40391,SUM(C24:J24),(IF($A$1=40422,SUM(C24:K24),(IF($A$1=40452,SUM(C24:L24),(IF($A$1=40483,SUM(C24:M24))))))))))+(IF($A$1=40513,SUM(C24:N24),0)) -> 0 | Q24: =(IF($A$1=40179,C24,(IF($A$1=40210,D24,(IF($A$1=40238,E24,(IF($A$1=40269,F24,(IF($A$1=40299,G24,(IF($A$1=40330,H24,(IF($A$1=40360,I24,0)))))))))))))+(IF($A$1=40391,J24,(IF($A$1=40422,K24,(IF($A$1=40452,L24,(IF($A$1=40483,M24)))))))))+(IF($A$1=40513,N24,0)) -> 0
A25: R&M DATA PROCESSING | B25: 53252601 | C25: 0 | D25: 0 | E25: 0 | F25: 0 | G25: 0 | H25: 0 | I25: 0 | J25: 0 | K25: 0 | L25: 0 | M25: 0 | N25: 0 | O25: 0 | P25: =(IF($A$1=40179,C25,(IF($A$1=40210,SUM(C25:D25),(IF($A$1=40238,SUM(C25:E25),(IF($A$1=40269,SUM(C25:F25),(IF($A$1=40299,SUM(C25:G25),(IF($A$1=40330,SUM(C25:H25),(IF($A$1=40360,SUM(C25:I25),0)))))))))))))+(IF($A$1=40391,SUM(C25:J25),(IF($A$1=40422,SUM(C25:K25),(IF($A$1=40452,SUM(C25:L25),(IF($A$1=40483,SUM(C25:M25))))))))))+(IF($A$1=40513,SUM(C25:N25),0)) -> 0 | Q25: =(IF($A$1=40179,C25,(IF($A$1=40210,D25,(IF($A$1=40238,E25,(IF($A$1=40269,F25,(IF($A$1=40299,G25,(IF($A$1=40330,H25,(IF($A$1=40360,I25,0)))))))))))))+(IF($A$1=40391,J25,(IF($A$1=40422,K25,(IF($A$1=40452,L25,(IF($A$1=40483,M25)))))))))+(IF($A$1=40513,N25,0)) -> 0
A26: R&M TELEPHONE | B26: 53252603 | C26: 29.374709 | D26: 15.100235 | E26: 33.209819 | F26: 40.453905 | G26: 120.16145 | H26: 0 | I26: 0 | J26: 1532.6831 | K26: 1577.9928 | L26: 1553.3432 | M26: 1485.7035 | N26: 1074.5974 | O26: 7462.6202 | P26: =(IF($A$1=40179,C26,(IF($A$1=40210,SUM(C26:D26),(IF($A$1=40238,SUM(C26:E26),(IF($A$1=40269,SUM(C26:F26),(IF($A$1=40299,SUM(C26:G26),(IF($A$1=40330,SUM(C26:H26),(IF($A$1=40360,SUM(C26:I26),0)))))))))))))+(IF($A$1=40391,SUM(C26:J26),(IF($A$1=40422,SUM(C26:K26),(IF($A$1=40452,SUM(C26:L26),(IF($A$1=40483,SUM(C26:M26))))))))))+(IF($A$1=40513,SUM(C26:N26),0)) -> 0 | Q26: =(IF($A$1=40179,C26,(IF($A$1=40210,D26,(IF($A$1=40238,E26,(IF($A$1=40269,F26,(IF($A$1=40299,G26,(IF($A$1=40330,H26,(IF($A$1=40360,I26,0)))))))))))))+(IF($A$1=40391,J26,(IF($A$1=40422,K26,(IF($A$1=40452,L26,(IF($A$1=40483,M26)))))))))+(IF($A$1=40513,N26,0)) -> 0
A27: R&M KITCHEN EQUIP. | B27: 53252703 | C27: 18610.98 | D27: 7247.7121 | E27: 5707.4428 | F27: 12222.516 | G27: 5623.8033 | H27: 6509.5046 | I27: 15311.566 | J27: 21902.26 | K27: 18614.51 | L27: 19231.518 | M27: 20212.925 | N27: 15102.401 | O27: 166297.14 | P27: =(IF($A$1=40179,C27,(IF($A$1=40210,SUM(C27:D27),(IF($A$1=40238,SUM(C27:E27),(IF($A$1=40269,SUM(C27:F27),(IF($A$1=40299,SUM(C27:G27),(IF($A$1=40330,SUM(C27:H27),(IF($A$1=40360,SUM(C27:I27),0)))))))))))))+(IF($A$1=40391,SUM(C27:J27),(IF($A$1=40422,SUM(C27:K27),(IF($A$1=40452,SUM(C27:L27),(IF($A$1=40483,SUM(C27:M27))))))))))+(IF($A$1=40513,SUM(C27:N27),0)) -> 0 | Q27: =(IF($A$1=40179,C27,(IF($A$1=40210,D27,(IF($A$1=40238,E27,(IF($A$1=40269,F27,(IF($A$1=40299,G27,(IF($A$1=40330,H27,(IF($A$1=40360,I27,0)))))))))))))+(IF($A$1=40391,J27,(IF($A$1=40422,K27,(IF($A$1=40452,L27,(IF($A$1=40483,M27)))))))))+(IF($A$1=40513,N27,0)) -> 0
