Workbook

Sheet Total
A1: Site Name | B1: Day | C1: Month | D1: Year | E1: Total Electricity Kwh | F1: Electricity Tariff ($/Kwh) | G1: Natual Gas (m3) | H1: Natural Gas $/m3 | I1: Water Utility Supply (m3) m3 | J1: Water Utility Supply (m3) $/m3 | K1: Room Nights
A2: Cairo at The First Residence | B2: 1 | C2: 2 | D2: 2022 | E2: =Elect!BS6 -> 20567.575 | F2: ='Utility Consnsumption'!K13/'Utility Consnsumption'!J13 -> 1.4405136 | G2: =Gas!K7 -> 1389.7 | H2: 3.8 | I2: =Water!H7 -> 261 | J2: 10 | K2: =Elect!BT6 -> 194
A3: Cairo at The First Residence | B3: =B2+1 -> 2 | C3: 2 | D3: 2022 | E3: =Elect!BS7 -> 21197.693 | F3: =F2 -> 1.4405136 | G3: =Gas!K8 -> 1527.6 | H3: 3.8 | I3: =Water!H8 -> 350.9 | J3: 10 | K3: =Elect!BT7 -> 194
A4: Cairo at The First Residence | B4: =B3+1 -> 3 | C4: 2 | D4: 2022 | E4: =Elect!BS8 -> 21392.107 | F4: =F3 -> 1.4405136 | G4: =Gas!K9 -> 1527.6 | H4: 3.8 | I4: =Water!H9 -> 350.9 | J4: 10 | K4: =Elect!BT8 -> 212
A5: Cairo at The First Residence | B5: =B4+1 -> 4 | C5: 2 | D5: 2022 | E5: =Elect!BS9 -> 20634.482 | F5: =F4 -> 1.4405136 | G5: =Gas!K10 -> 1405.1 | H5: 3.8 | I5: =Water!H10 -> 498.8 | J5: 10 | K5: =Elect!BT9 -> 234
A6: Cairo at The First Residence | B6: =B5+1 -> 5 | C6: 2 | D6: 2022 | E6: =Elect!BS10 -> 21277.972 | F6: =F5 -> 1.4405136 | G6: =Gas!K11 -> 1451.3 | H6: 3.8 | I6: =Water!H11 -> 284.2 | J6: 10 | K6: =Elect!BT10 -> 216
A7: Cairo at The First Residence | B7: =B6+1 -> 6 | C7: 2 | D7: 2022 | E7: =Elect!BS11 -> 21292.912 | F7: =F6 -> 1.4405136 | G7: =Gas!K12 -> 1451.3 | H7: 3.8 | I7: =Water!H12 -> 284.2 | J7: 10 | K7: =Elect!BT11 -> 198
A8: Cairo at The First Residence | B8: =B7+1 -> 7 | C8: 2 | D8: 2022 | E8: =Elect!BS12 -> 21163.747 | F8: =F7 -> 1.4405136 | G8: =Gas!K13 -> 1451.3 | H8: 3.8 | I8: =Water!H13 -> 284.2 | J8: 10 | K8: =Elect!BT12 -> 180
A9: Cairo at The First Residence | B9: =B8+1 -> 8 | C9: 2 | D9: 2022 | E9: =Elect!BS13 -> 22864.5 | F9: =F8 -> 1.4405136 | G9: =Gas!K14 -> 1451.3 | H9: 3.8 | I9: =Water!H14 -> 290 | J9: 10 | K9: =Elect!BT13 -> 170
A10: Cairo at The First Residence | B10: =B9+1 -> 9 | C10: 2 | D10: 2022 | E10: =Elect!BS14 -> 22124.987 | F10: =F9 -> 1.4405136 | G10: =Gas!K15 -> 1451.3 | H10: 3.8 | I10: =Water!H15 -> 234.9 | J10: 10 | K10: =Elect!BT14 -> 154
A11: Cairo at The First Residence | B11: =B10+1 -> 10 | C11: 2 | D11: 2022 | E11: =Elect!BS15 -> 20310.153 | F11: =F10 -> 1.4405136 | G11: =Gas!K16 -> 1312.7 | H11: 3.8 | I11: =Water!H16 -> 329.15 | J11: 10 | K11: =Elect!BT15 -> 195
A12: Cairo at The First Residence | B12: =B11+1 -> 11 | C12: 2 | D12: 2022 | E12: =Elect!BS16 -> 22712.118 | F12: =F11 -> 1.4405136 | G12: =Gas!K17 -> 1312.7 | H12: 3.8 | I12: =Water!H17 -> 295.31667 | J12: 10 | K12: =Elect!BT16 -> 209
A13: Cairo at The First Residence | B13: =B12+1 -> 12 | C13: 2 | D13: 2022 | E13: =Elect!BS17 -> 20766.423 | F13: =F12 -> 1.4405136 | G13: =Gas!K18 -> 1312.7 | H13: 3.8 | I13: =Water!H18 -> 303.775 | J13: 10 | K13: =Elect!BT17 -> 192
A14: Cairo at The First Residence | B14: =B13+1 -> 13 | C14: 2 | D14: 2022 | E14: =Elect!BS18 -> 25491.97 | F14: =F13 -> 1.4405136 | G14: =Gas!K19 -> 1312.7 | H14: 3.8 | I14: =Water!H19 -> 303.775 | J14: 10 | K14: =Elect!BT18 -> 228
... A32: Cairo at The First Residence | B32: =B31+1 -> 31 | C32: 2 | D32: 2022 | E32: =Elect!BS36 -> 0 | F32: =F31 -> 1.4405136 | G32: =Gas!K37 -> 1060 | H32: 3.8 | I32: =Water!H37 -> 0 | J32: 10 | K32: =Elect!BT36 -> 0

Sheet Submetering
A1: Site Name | B1: Day | C1: Month | D1: Year | E1: Electricity | F1: Main Feeder -KWh | G1: T2+T8 -KWh | H1: La Gourmandize -KWh | I1: Casino 3rd floor EM -KWh | J1: Casino 3rd floor Normal -KWh | K1: Chiller 1 -KWh | L1: Chiller 2 -KWh | M1: Chiller 3 -KWh | N1: Chiller 4 -KWh | O1: Chiller 5 -KWh | P1: Chiller 6 -KWh | Q1: Cooling towers -KWh | R1: Chiller Pumps -KWh | S1: Cooling Tower Pumps -KWh | T1: Fiber Chiller -KWh | U1: Mall Ceiling light -KWh | V1: LG Bakery -KWh | W1: LG Bakery light ( Old lockers ) -KWh | X1: MCCR1 -KWh | Y1: Children Swimming Pool -KWh | Z1: DPH1 -KWh | AA1: Guest Rooms Emerg. -KWh | AB1: Hotel Hoods -KWh | AC1: Main G2 -KWh | AD1: Old Casino Emergency -KWh | AE1: L / A -KWh | AF1: L / B -KWh | AG1: L / C -KWh | AH1: Water | AI1: Main water meter 1 -m3 | AJ1: Main water meter 2 -m3 | AK1: Main water meter 3 -m3 | AL1: Gas | AM1: Main Gas Flow Meter -m3 | AN1: Laundry Gas Flow Meter -m3 | AO1: Gourmandize Gas Flow Meter -m3 | AP1: Room Nights
A2: Cairo at The First Residence | B2: 1 | C2: 2 | D2: 2022 | F2: =Elect!J6 -> 6679 | G2: =Elect!K6 -> 4420 | H2: =Elect!Q6 -> 360 | I2: =Elect!S6 -> 143 | J2: =Elect!U6 -> 259.5 | K2: =Elect!W6 -> 1564.56 | L2: =Elect!Y6 -> 0 | M2: =Elect!AA6 -> 0 | N2: =Elect!AC6 -> 0 | O2: =Elect!AE6 -> 13.25 | P2: =Elect!AG6 -> 13.25 | Q2: =Elect!AI6 -> 134.62 | R2: =Elect!AK6 -> 1835.39 | S2: =Elect!AM6 -> 148.93 | T2: =Elect!AP6 -> 4.725 | U2: =Elect!AR6 -> 323 | V2: =Elect!AT6 -> 185 | W2: =Elect!AV6 -> 52 | X2: =Elect!AX6 -> 577 | Y2: =Elect!AZ6 -> 5 | Z2: =Elect!BB6 -> 3727 | AA2: =Elect!BD6 -> 214 | AB2: =Elect!BF6 -> 56 | AC2: =Elect!BH6 -> 4674.85 | AD2: =Elect!BL6 -> 63 | AE2: =Elect!BN6 -> 971 | AF2: =Elect!BP6 -> 136 | AG2: =Elect!BR6 -> 111 | AI2: =Water!C7 -> 110.2 | AJ2: =Water!E7 -> 150.8 | AK2: =Water!G7 -> 0 | AM2: =Gas!C7 -> 1060 | AN2: =Gas!E7 -> 329.7 | AO2: =Gas!G7 -> 257 | AP2: =Elect!BT6 -> 194
A3: Cairo at The First Residence | B3: =B2+1 -> 2 | C3: 2 | D3: 2022 | F3: =Elect!J7 -> 6640 | G3: =Elect!K7 -> 4321 | H3: =Elect!Q7 -> 600 | I3: =Elect!S7 -> 145 | J3: =Elect!U7 -> 269 | K3: =Elect!W7 -> 988.45 | L3: =Elect!Y7 -> 0 | M3: =Elect!AA7 -> 0 | N3: =Elect!AC7 -> 0 | O3: =Elect!AE7 -> 13.25 | P3: =Elect!AG7 -> 12.72 | Q3: =Elect!AI7 -> 408.63 | R3: =Elect!AK7 -> 2044.74 | S3: =Elect!AM7 -> 155.29 | T3: =Elect!AP7 -> 4.1625 | U3: =Elect!AR7 -> 338 | V3: =Elect!AT7 -> 161 | W3: =Elect!AV7 -> 43 | X3: =Elect!AX7 -> 575 | Y3: =Elect!AZ7 -> 6 | Z3: =Elect!BB7 -> 4029 | AA3: =Elect!BD7 -> 218 | AB3: =Elect!BF7 -> 127 | AC3: =Elect!BH7 -> 4833.45 | AD3: =Elect!BL7 -> 60 | AE3: =Elect!BN7 -> 937 | AF3: =Elect!BP7 -> 142 | AG3: =Elect!BR7 -> 133 | AI3: =Water!C8 -> 150.8 | AJ3: =Water!E8 -> 191.4 | AK3: =Water!G8 -> 8.7 | AM3: =Gas!C8 -> 1060 | AN3: =Gas!E8 -> 467.6 | AO3: =Gas!G8 -> 0 | AP3: =Elect!BT7 -> 194
A4: Cairo at The First Residence | B4: =B3+1 -> 3 | C4: 2 | D4: 2022 | F4: =Elect!J8 -> 6891 | G4: =Elect!K8 -> 4131 | H4: =Elect!Q8 -> 570 | I4: =Elect!S8 -> 140 | J4: =Elect!U8 -> 246 | K4: =Elect!W8 -> 967.78 | L4: =Elect!Y8 -> 0 | M4: =Elect!AA8 -> 0 | N4: =Elect!AC8 -> 0 | O4: =Elect!AE8 -> 13.78 | P4: =Elect!AG8 -> 13.25 | Q4: =Elect!AI8 -> 399.09 | R4: =Elect!AK8 -> 2267.87 | S4: =Elect!AM8 -> 156.35 | T4: =Elect!AP8 -> 4.3875 | U4: =Elect!AR8 -> 326 | V4: =Elect!AT8 -> 147 | W4: =Elect!AV8 -> 43 | X4: =Elect!AX8 -> 577 | Y4: =Elect!AZ8 -> 6 | Z4: =Elect!BB8 -> 4140 | AA4: =Elect!BD8 -> 224 | AB4: =Elect!BF8 -> 0 | AC4: =Elect!BH8 -> 4645.6 | AD4: =Elect!BL8 -> 60 | AE4: =Elect!BN8 -> 777 | AF4: =Elect!BP8 -> 135 | AG4: =Elect!BR8 -> 128 | AI4: =Water!C9 -> 150.8 | AJ4: =Water!E9 -> 191.4 | AK4: =Water!G9 -> 8.7 | AM4: =Gas!C9 -> 1060 | AN4: =Gas!E9 -> 467.6 | AO4: =Gas!G9 -> 0 | AP4: =Elect!BT8 -> 212
A5: Cairo at The First Residence | B5: =B4+1 -> 4 | C5: 2 | D5: 2022 | F5: =Elect!J9 -> 6741 | G5: =Elect!K9 -> 4176 | H5: =Elect!Q9 -> 600 | I5: =Elect!S9 -> 138 | J5: =Elect!U9 -> 245 | K5: =Elect!W9 -> 795 | L5: =Elect!Y9 -> 0 | M5: =Elect!AA9 -> 0 | N5: =Elect!AC9 -> 0 | O5: =Elect!AE9 -> 13.25 | P5: =Elect!AG9 -> 12.72 | Q5: =Elect!AI9 -> 372.06 | R5: =Elect!AK9 -> 1766.49 | S5: =Elect!AM9 -> 148.4 | T5: =Elect!AP9 -> 4.1625 | U5: =Elect!AR9 -> 332 | V5: =Elect!AT9 -> 158 | W5: =Elect!AV9 -> 36 | X5: =Elect!AX9 -> 530 | Y5: =Elect!AZ9 -> 6 | Z5: =Elect!BB9 -> 4127 | AA5: =Elect!BD9 -> 204 | AB5: =Elect!BF9 -> 54 | AC5: =Elect!BH9 -> 4734.4 | AD5: =Elect!BL9 -> 60 | AE5: =Elect!BN9 -> 830 | AF5: =Elect!BP9 -> 138 | AG5: =Elect!BR9 -> 129 | AI5: =Water!C10 -> 278.4 | AJ5: =Water!E10 -> 211.7 | AK5: =Water!G10 -> 8.7 | AM5: =Gas!C10 -> 1060 | AN5: =Gas!E10 -> 345.1 | AO5: =Gas!G10 -> 125 | AP5: =Elect!BT9 -> 234
A6: Cairo at The First Residence | B6: =B5+1 -> 5 | C6: 2 | D6: 2022 | F6: =Elect!J10 -> 6857 | G6: =Elect!K10 -> 4372 | H6: =Elect!Q10 -> 630 | I6: =Elect!S10 -> 142 | J6: =Elect!U10 -> 250 | K6: =Elect!W10 -> 965.13 | L6: =Elect!Y10 -> 0 | M6: =Elect!AA10 -> 0 | N6: =Elect!AC10 -> 0 | O6: =Elect!AE10 -> 13.78 | P6: =Elect!AG10 -> 13.78 | Q6: =Elect!AI10 -> 399.09 | R6: =Elect!AK10 -> 1835.39 | S6: =Elect!AM10 -> 155.29 | T6: =Elect!AP10 -> 4.6125 | U6: =Elect!AR10 -> 366 | V6: =Elect!AT10 -> 162 | W6: =Elect!AV10 -> 41 | X6: =Elect!AX10 -> 559 | Y6: =Elect!AZ10 -> 6 | Z6: =Elect!BB10 -> 4321 | AA6: =Elect!BD10 -> 139 | AB6: =Elect!BF10 -> 32 | AC6: =Elect!BH10 -> 4777.9 | AD6: =Elect!BL10 -> 60 | AE6: =Elect!BN10 -> 839 | AF6: =Elect!BP10 -> 139 | AG6: =Elect!BR10 -> 130 | AI6: =Water!C11 -> 104.4 | AJ6: =Water!E11 -> 171.1 | AK6: =Water!G11 -> 8.7 | AM6: =Gas!C11 -> 1060 | AN6: =Gas!E11 -> 391.3 | AO6: =Gas!G11 -> 125 | AP6: =Elect!BT10 -> 216
A7: Cairo at The First Residence | B7: =B6+1 -> 6 | C7: 2 | D7: 2022 | F7: =Elect!J11 -> 6703 | G7: =Elect!K11 -> 4233 | H7: =Elect!Q11 -> 360 | I7: =Elect!S11 -> 143 | J7: =Elect!U11 -> 256 | K7: =Elect!W11 -> 1103.46 | L7: =Elect!Y11 -> 0 | M7: =Elect!AA11 -> 0 | N7: =Elect!AC11 -> 0 | O7: =Elect!AE11 -> 13.25 | P7: =Elect!AG11 -> 12.72 | Q7: =Elect!AI11 -> 417.11 | R7: =Elect!AK11 -> 1998.63 | S7: =Elect!AM11 -> 156.88 | T7: =Elect!AP11 -> 4.1625 | U7: =Elect!AR11 -> 315 | V7: =Elect!AT11 -> 167 | W7: =Elect!AV11 -> 43 | X7: =Elect!AX11 -> 578 | Y7: =Elect!AZ11 -> 6 | Z7: =Elect!BB11 -> 4215 | AA7: =Elect!BD11 -> 281 | AB7: =Elect!BF11 -> 77 | AC7: =Elect!BH11 -> 4841.7 | AD7: =Elect!BL11 -> 61 | AE7: =Elect!BN11 -> 848 | AF7: =Elect!BP11 -> 126 | AG7: =Elect!BR11 -> 132 | AI7: =Water!C12 -> 104.4 | AJ7: =Water!E12 -> 171.1 | AK7: =Water!G12 -> 8.7 | AM7: =Gas!C12 -> 1060 | AN7: =Gas!E12 -> 391.3 | AO7: =Gas!G12 -> 125 | AP7: =Elect!BT11 -> 198
A8: Cairo at The First Residence | B8: =B7+1 -> 7 | C8: 2 | D8: 2022 | F8: =Elect!J12 -> 6377 | G8: =Elect!K12 -> 4224 | H8: =Elect!Q12 -> 630 | I8: =Elect!S12 -> 139 | J8: =Elect!U12 -> 245 | K8: =Elect!W12 -> 1308.04 | L8: =Elect!Y12 -> 0 | M8: =Elect!AA12 -> 0 | N8: =Elect!AC12 -> 0 | O8: =Elect!AE12 -> 13.25 | P8: =Elect!AG12 -> 12.72 | Q8: =Elect!AI12 -> 400.15 | R8: =Elect!AK12 -> 2121.06 | S8: =Elect!AM12 -> 155.29 | T8: =Elect!AP12 -> 4.3875 | U8: =Elect!AR12 -> 339 | V8: =Elect!AT12 -> 120 | W8: =Elect!AV12 -> 44 | X8: =Elect!AX12 -> 579 | Y8: =Elect!AZ12 -> 6 | Z8: =Elect!BB12 -> 4124 | AA8: =Elect!BD12 -> 220 | AB8: =Elect!BF12 -> 34 | AC8: =Elect!BH12 -> 4675.85 | AD8: =Elect!BL12 -> 60 | AE8: =Elect!BN12 -> 848 | AF8: =Elect!BP12 -> 119 | AG8: =Elect!BR12 -> 124 | AI8: =Water!C13 -> 104.4 | AJ8: =Water!E13 -> 171.1 | AK8: =Water!G13 -> 8.7 | AM8: =Gas!C13 -> 1060 | AN8: =Gas!E13 -> 391.3 | AO8: =Gas!G13 -> 125 | AP8: =Elect!BT12 -> 180
A9: Cairo at The First Residence | B9: =B8+1 -> 8 | C9: 2 | D9: 2022 | F9: =Elect!J13 -> 6377 | G9: =Elect!K13 -> 4454 | H9: =Elect!Q13 -> 540 | I9: =Elect!S13 -> 145 | J9: =Elect!U13 -> 262 | K9: =Elect!W13 -> 1417.75 | L9: =Elect!Y13 -> 0 | M9: =Elect!AA13 -> 0 | N9: =Elect!AC13 -> 0 | O9: =Elect!AE13 -> 15.37 | P9: =Elect!AG13 -> 15.37 | Q9: =Elect!AI13 -> 425.59 | R9: =Elect!AK13 -> 2145.97 | S9: =Elect!AM13 -> 164.3 | T9: =Elect!AP13 -> 4.95 | U9: =Elect!AR13 -> 358 | V9: =Elect!AT13 -> 150 | W9: =Elect!AV13 -> 46 | X9: =Elect!AX13 -> 619 | Y9: =Elect!AZ13 -> 6 | Z9: =Elect!BB13 -> 4735 | AA9: =Elect!BD13 -> 267 | AB9: =Elect!BF13 -> 34 | AC9: =Elect!BH13 -> 5543.2 | AD9: =Elect!BL13 -> 71 | AE9: =Elect!BN13 -> 1004 | AF9: =Elect!BP13 -> 140 | AG9: =Elect!BR13 -> 155 | AI9: =Water!C14 -> 104.4 | AJ9: =Water!E14 -> 185.6 | AK9: =Water!G14 -> 0 | AM9: =Gas!C14 -> 1060 | AN9: =Gas!E14 -> 391.3 | AO9: =Gas!G14 -> 125 | AP9: =Elect!BT13 -> 170
A10: Cairo at The First Residence | B10: =B9+1 -> 9 | C10: 2 | D10: 2022 | F10: =Elect!J14 -> 6885 | G10: =Elect!K14 -> 5180 | H10: =Elect!Q14 -> 600 | I10: =Elect!S14 -> 168 | J10: =Elect!U14 -> 298 | K10: =Elect!W14 -> 1298.5 | L10: =Elect!Y14 -> 0 | M10: =Elect!AA14 -> 0 | N10: =Elect!AC14 -> 0 | O10: =Elect!AE14 -> 14.31 | P10: =Elect!AG14 -> 13.78 | Q10: =Elect!AI14 -> 499.26 | R10: =Elect!AK14 -> 2422.63 | S10: =Elect!AM14 -> 187.62 | T10: =Elect!AP14 -> 4.3875 | U10: =Elect!AR14 -> 360 | V10: =Elect!AT14 -> 140 | W10: =Elect!AV14 -> 51 | X10: =Elect!AX14 -> 678 | Y10: =Elect!AZ14 -> 7 | Z10: =Elect!BB14 -> 3584 | AA10: =Elect!BD14 -> 217 | AB10: =Elect!BF14 -> 34 | AC10: =Elect!BH14 -> 5128.5 | AD10: =Elect!BL14 -> 63 | AE10: =Elect!BN14 -> 884 | AF10: =Elect!BP14 -> 126 | AG10: =Elect!BR14 -> 139 | AI10: =Water!C15 -> 104.4 | AJ10: =Water!E15 -> 127.6 | AK10: =Water!G15 -> 2.9 | AM10: =Gas!C15 -> 1060 | AN10: =Gas!E15 -> 391.3 | AO10: =Gas!G15 -> 125 | AP10: =Elect!BT14 -> 154
A11: Cairo at The First Residence | B11: =B10+1 -> 10 | C11: 2 | D11: 2022 | F11: =Elect!J15 -> 7165 | G11: =Elect!K15 -> 3454 | H11: =Elect!Q15 -> 570 | I11: =Elect!S15 -> 118 | J11: =Elect!U15 -> 207 | K11: =Elect!W15 -> 827.33 | L11: =Elect!Y15 -> 0 | M11: =Elect!AA15 -> 0 | N11: =Elect!AC15 -> 0 | O11: =Elect!AE15 -> 12.19 | P11: =Elect!AG15 -> 11.13 | Q11: =Elect!AI15 -> 305.28 | R11: =Elect!AK15 -> 1517.92 | S11: =Elect!AM15 -> 118.19 | T11: =Elect!AP15 -> 3.7125 | U11: =Elect!AR15 -> 322 | V11: =Elect!AT15 -> 113 | W11: =Elect!AV15 -> 32 | X11: =Elect!AX15 -> 443 | Y11: =Elect!AZ15 -> 5 | Z11: =Elect!BB15 -> 4266 | AA11: =Elect!BD15 -> 192 | AB11: =Elect!BF15 -> 34 | AC11: =Elect!BH15 -> 4372.4 | AD11: =Elect!BL15 -> 53 | AE11: =Elect!BN15 -> 744 | AF11: =Elect!BP15 -> 104 | AG11: =Elect!BR15 -> 116 | AI11: =Water!C16 -> 150.8 | AJ11: =Water!E16 -> 178.35 | AK11: =Water!G16 -> 0 | AM11: =Gas!C16 -> 1060 | AN11: =Gas!E16 -> 252.7 | AO11: =Gas!G16 -> 55 | AP11: =Elect!BT15 -> 195
A12: Cairo at The First Residence | B12: =B11+1 -> 11 | C12: 2 | D12: 2022 | F12: =Elect!J16 -> 7160 | G12: =Elect!K16 -> 4364 | H12: =Elect!Q16 -> 600 | I12: =Elect!S16 -> 145 | J12: =Elect!U16 -> 260 | K12: =Elect!W16 -> 1340.37 | L12: =Elect!Y16 -> 0 | M12: =Elect!AA16 -> 0 | N12: =Elect!AC16 -> 0 | O12: =Elect!AE16 -> 14.31 | P12: =Elect!AG16 -> 13.25 | Q12: =Elect!AI16 -> 430.89 | R12: =Elect!AK16 -> 2105.16 | S12: =Elect!AM16 -> 161.65 | T12: =Elect!AP16 -> 4.3875 | U12: =Elect!AR16 -> 333 | V12: =Elect!AT16 -> 101 | W12: =Elect!AV16 -> 38 | X12: =Elect!AX16 -> 586 | Y12: =Elect!AZ16 -> 6 | Z12: =Elect!BB16 -> 4687 | AA12: =Elect!BD16 -> 199 | AB12: =Elect!BF16 -> 34 | AC12: =Elect!BH16 -> 4898.1 | AD12: =Elect!BL16 -> 62 | AE12: =Elect!BN16 -> 840 | AF12: =Elect!BP16 -> 122 | AG12: =Elect!BR16 -> 144 | AI12: =Water!C17 -> 150.8 | AJ12: =Water!E17 -> 144.51667 | AK12: =Water!G17 -> 0 | AM12: =Gas!C17 -> 1060 | AN12: =Gas!E17 -> 252.7 | AO12: =Gas!G17 -> 55 | AP12: =Elect!BT16 -> 209
A13: Cairo at The First Residence | B13: =B12+1 -> 12 | C13: 2 | D13: 2022 | F13: =Elect!J17 -> 6495 | G13: =Elect!K17 -> 3913 | H13: =Elect!Q17 -> 300 | I13: =Elect!S17 -> 135 | J13: =Elect!U17 -> 236 | K13: =Elect!W17 -> 1291.08 | L13: =Elect!Y17 -> 0 | M13: =Elect!AA17 -> 0 | N13: =Elect!AC17 -> 0 | O13: =Elect!AE17 -> 14.31 | P13: =Elect!AG17 -> 13.78 | Q13: =Elect!AI17 -> 378.95 | R13: =Elect!AK17 -> 1876.73 | S13: =Elect!AM17 -> 144.16 | T13: =Elect!AP17 -> 4.1625 | U13: =Elect!AR17 -> 338 | V13: =Elect!AT17 -> 128 | W13: =Elect!AV17 -> 37 | X13: =Elect!AX17 -> 540 | Y13: =Elect!AZ17 -> 6 | Z13: =Elect!BB17 -> 4282 | AA13: =Elect!BD17 -> 201 | AB13: =Elect!BF17 -> 34 | AC13: =Elect!BH17 -> 4682.25 | AD13: =Elect!BL17 -> 180 | AE13: =Elect!BN17 -> 799 | AF13: =Elect!BP17 -> 116 | AG13: =Elect!BR17 -> 134 | AI13: =Water!C18 -> 150.8 | AJ13: =Water!E18 -> 152.975 | AK13: =Water!G18 -> 0 | AM13: =Gas!C18 -> 1060 | AN13: =Gas!E18 -> 252.7 | AO13: =Gas!G18 -> 55 | AP13: =Elect!BT17 -> 192
A14: Cairo at The First Residence | B14: =B13+1 -> 13 | C14: 2 | D14: 2022 | F14: =Elect!J18 -> 7359 | G14: =Elect!K18 -> 5567 | H14: =Elect!Q18 -> 690 | I14: =Elect!S18 -> 146 | J14: =Elect!U18 -> 274 | K14: =Elect!W18 -> 1583.11 | L14: =Elect!Y18 -> 38.69 | M14: =Elect!AA18 -> 29.68 | N14: =Elect!AC18 -> 59.36 | O14: =Elect!AE18 -> 11.66 | P14: =Elect!AG18 -> 11.66 | Q14: =Elect!AI18 -> 526.29 | R14: =Elect!AK18 -> 2657.42 | S14: =Elect!AM18 -> 156.35 | T14: =Elect!AP18 -> 53.55 | U14: =Elect!AR18 -> 327 | V14: =Elect!AT18 -> 162 | W14: =Elect!AV18 -> 53 | X14: =Elect!AX18 -> 722 | Y14: =Elect!AZ18 -> 6 | Z14: =Elect!BB18 -> 5435 | AA14: =Elect!BD18 -> 242 | AB14: =Elect!BF18 -> 34 | AC14: =Elect!BH18 -> 5334.2 | AD14: =Elect!BL18 -> 280 | AE14: =Elect!BN18 -> 823 | AF14: =Elect!BP18 -> 141 | AG14: =Elect!BR18 -> 146 | AI14: =Water!C19 -> 150.8 | AJ14: =Water!E19 -> 152.975 | AK14: =Water!G19 -> 0 | AM14: =Gas!C19 -> 1060 | AN14: =Gas!E19 -> 252.7 | AO14: =Gas!G19 -> 55 | AP14: =Elect!BT18 -> 228
... A32: Cairo at The First Residence | B32: =B31+1 -> 31 | C32: 2 | D32: 2022 | F32: =Elect!J36 -> 0 | G32: =Elect!K36 -> 0 | H32: =Elect!Q36 -> 0 | I32: =Elect!S36 -> 0 | J32: =Elect!U36 -> 0 | K32: =Elect!W36 -> 0 | L32: =Elect!Y36 -> 0 | M32: =Elect!AA36 -> 0 | N32: =Elect!AC36 -> 0 | O32: =Elect!AE36 -> 0 | P32: =Elect!AG36 -> 0 | Q32: =Elect!AI36 -> 0 | R32: =Elect!AK36 -> 0 | S32: =Elect!AM36 -> 0 | T32: =Elect!AP36 -> 0 | U32: =Elect!AR36 -> 0 | V32: =Elect!AT36 -> 0 | W32: =Elect!AV36 -> 0 | X32: =Elect!AX36 -> 0 | Y32: =Elect!AZ36 -> 0 | Z32: =Elect!BB36 -> 0 | AA32: =Elect!BD36 -> 0 | AB32: =Elect!BF36 -> 0 | AC32: =Elect!BH36 -> 0 | AD32: =Elect!BL36 -> 0 | AE32: =Elect!BN36 -> 0 | AF32: =Elect!BP36 -> 0 | AG32: =Elect!BR36 -> 0 | AI32: =Water!C37 -> 0 | AJ32: =Water!E37 -> 0 | AK32: =Water!G37 -> 0 | AM32: =Gas!C37 -> 1060 | AN32: =Gas!E37 -> 0 | AO32: =Gas!G37 -> 0 | AP32: =Elect!BT36 -> 0

Sheet Elect
A1: February | M1: Electricity | BJ1: =SUM(BJ21:BJ33) -> 193200.42 | BP1: Gourmandise UP | BR1: 1.6 | BS1: Power Taxes | BU1: Max Demand | BW1: 500 | BX1: Electricity UP | BZ1: 1.15
BS2: Light Taxes | BU2: PF Penalty | BX2: Max. Demand UP | BZ2: 30
A3: Date | B3: COUNTER (1) | D3: MD | F3: KVAR | H3: n | I3: Guest Rooms Consumption | R3: Casino Consumption | V3: Plant Room Shared Loads | AO3: To Be Charged By First Arabian | BK3: From Main Panel G2 | BS3: Total Consumption. | BT3: No. Of | BU3: KWH/ | BV3: No. Of | BW3: KWH/ | BX3: Total Cost | BY3: L.E\ | BZ3: L.E\
B4: Reading | C4: Consp. F: *800 | D4: Reading | E4: Consp F: 80 | F4: Reading | G4: Consp. F:*10 | I4: Main Feeder | J4: Consp | K4: T2+T8 | L4: Trans T2 | M4: Consp | N4: Trans T8 | O4: Consp | P4: La Gourmandize | Q4: Consp *30 | R4: Casino 3rd floor EM | S4: Consp | T4: Casino 3rd floor Normal | U4: Consp | V4: Chiller 1 | W4: Consp 53% | X4: Chiller 2 | Y4: Consp 53% | Z4: Chiller 3 | AA4: Consp 53% | AB4: Chiller 4 | AC4: Consp 53% | AD4: Chiller 5 | AE4: Consp 53% | AF4: Chiller 6 | AG4: Consp 53% | AH4: Cooling Towers | AI4: Consp 53% | AJ4: Chiller Pumps | AK4: Consp 53% | AL4: Cooling Tower Pumps | AM4: Consp 53% | AN4: Total Plant Room Consp | AO4: Fiber Chiller (N24) | AP4: Consp | AQ4: Mall Ceiling light (N4) | AR4: Consp | AS4: LG Bakery (N2) | AT4: Consp | AU4: LG Bakery light ( Old lockers ) | AV4: Consp | AW4: MCCR1 | AX4: Consp | AY4: Children Swimming pool | AZ4: Consp | BA4: DPH1 | BB4: Consp | BC4: Guest Rooms Emergency | BD4: Consp | BE4: Hotel Hoods | BF4: Consp | BG4: Main G2 | BH4: Consp | BI4: Total Consp From First Arabian | BJ4: First Arabian Charge Back | BK4: Old Casino Emergency | BL4: Consp | BM4: L / A | BN4: Consp | BO4: L / B | BP4: Consp | BQ4: L / C | BR4: Consp | BT4: Rooms | BU4: room | BV4: guest | BW4: guest | BY4: Room | BZ4: Guest
A5: Last Month Reading | I5: 23935086 | J5: =IF(I5>=I4,I5-I4,0) -> 0 | K5: =M5+O5 -> 0 | L5: 682610 | M5: =IF(L5>=L4,L5-L4,0) -> 0 | N5: 568451 | O5: =IF(N5>=N4,N5-N4,0) -> 0 | P5: 221729 | Q5: =IF(P5>=P4,P5-P4,0)*30 -> 0 | R5: 182286 | S5: =IF(R5>=R4,R5-R4,0) -> 0 | T5: 333231.5 | U5: =IF(T5>=T4,T5-T4,0) -> 0 | V5: 792076 | W5: =IF(V5>=V4,V5-V4,0)*0.53 -> 0 | X5: 120756 | Y5: =IF(X5>=X4,X5-X4,0)*0.53 -> 0 | Z5: 134745 | AA5: =IF(Z5>=Z4,Z5-Z4,0)*0.53 -> 0 | AB5: 488293 | AC5: =IF(AB5>=AB4,AB5-AB4,0)*0.53 -> 0 | AD5: 656991 | AE5: =IF(AD5>=AD4,AD5-AD4,0)*0.53 -> 0 | AF5: 835653 | AG5: =IF(AF5>=AF4,AF5-AF4,0)*0.53 -> 0 | AH5: 988484 | AI5: =IF(AH5>=AH4,AH5-AH4,0)*0.53 -> 0 | AJ5: 753327 | AK5: =IF(AJ5>=AJ4,AJ5-AJ4,0)*0.53 -> 0 | AL5: 493166 | AM5: =IF(AL5>=AL4,AL5-AL4,0)*0.53 -> 0 | AN5: =W5+Y5+AA5+AC5+AE5+AG5+AI5+AK5+AM5 -> 0 | AO5: 7651074 | AP5: =IF(AO5>=AO4,AO5-AO4,0)*0.1125 -> 0 | AQ5: 677433 | AR5: =IF(AQ5>=AQ4,AQ5-AQ4,0) -> 0 | AS5: 966158 | AT5: =IF(AS5>=AS4,AS5-AS4,0) -> 0 | AU5: 810198 | AV5: =IF(AU5>=AU4,AU5-AU4,0) -> 0 | AW5: 2620992 | AX5: =IF(AW5>=AW4,AW5-AW4,0) -> 0 | AY5: 229553 | AZ5: =IF(AY5>=AY4,AY5-AY4,0) -> 0 | BA5: 19297389 | BB5: =IF(BA5>=BA4,BA5-BA4,0) -> 0 | BC5: 567310 | BD5: =IF(BC5>=BC4,BC5-BC4,0) -> 0 | BE5: 26749 | BF5: =IF(BE5>=BE4,BE5-BE4,0) -> 0 | BG5: 24129548 | BH5: =IF(BG5>=BG4,BG5-BG4,0)-(0.45*BN5)-(0.45*BP5)-BR5 -> 0 | BI5: =AP5+AR5+AT5+AV5+AX5+AZ5+BB5+BD5+BF5+BH5 -> 0 | BJ5: =BI5+AN5 -> 0 | BK5: 1425459 | BL5: =IF(BK5>=BK4,BK5-BK4,0) -> 0 | BM5: 3933145 | BN5: =IF(BM5>=BM4,BM5-BM4,0) -> 0 | BO5: 413761 | BP5: =IF(BO5>=BO4,BO5-BO4,0) -> 0 | BQ5: 517957 | BR5: =IF(BQ5>=BQ4,BQ5-BQ4,0) -> 0
A6: 1 | C6: =IF(+B6-B5>0,B6-B5,(B6-B5)>0)*800 -> 0 | E6: =IF(+D6-D5>0,D6-D5,(D6-D5)>0)*80 -> 0 | G6: =IF(+F6-F5>0,F6-F5,(F6-F5)>0)*10 -> 0 | H6: 56 | I6: 23941765 | J6: =IF(I6>=I5,I6-I5,0) -> 6679 | K6: =M6+O6 -> 4420 | L6: 685291 | M6: =IF(L6>=L5,L6-L5,0) -> 2681 | N6: 570190 | O6: =IF(N6>=N5,N6-N5,0) -> 1739 | P6: 221741 | Q6: =IF(P6>=P5,P6-P5,0)*30 -> 360 | R6: 182429 | S6: =IF(R6>=R5,R6-R5,0) -> 143 | T6: 333491 | U6: =IF(T6>=T5,T6-T5,0) -> 259.5 | V6: 795028 | W6: =IF(V6>=V5,V6-V5,0)*0.53 -> 1564.56 | X6: 120756 | Y6: =IF(X6>=X5,X6-X5,0)*0.53 -> 0 | Z6: 134745 | AA6: =IF(Z6>=Z5,Z6-Z5,0)*0.53 -> 0 | AB6: 488293 | AC6: =IF(AB6>=AB5,AB6-AB5,0)*0.53 -> 0 | AD6: 657016 | AE6: =IF(AD6>=AD5,AD6-AD5,0)*0.53 -> 13.25 | AF6: 835678 | AG6: =IF(AF6>=AF5,AF6-AF5,0)*0.53 -> 13.25 | AH6: 988738 | AI6: =IF(AH6>=AH5,AH6-AH5,0)*0.53 -> 134.62 | AJ6: 756790 | AK6: =IF(AJ6>=AJ5,AJ6-AJ5,0)*0.53 -> 1835.39 | AL6: 493447 | AM6: =IF(AL6>=AL5,AL6-AL5,0)*0.53 -> 148.93 | AN6: =W6+Y6+AA6+AC6+AE6+AG6+AI6+AK6+AM6 -> 3710 | AO6: 7651116 | AP6: =IF(AO6>=AO5,AO6-AO5,0)*0.1125 -> 4.725 | AQ6: 677756 | AR6: =IF(AQ6>=AQ5,AQ6-AQ5,0) -> 323 | AS6: 966343 | AT6: =IF(AS6>=AS5,AS6-AS5,0) -> 185 | AU6: 810250 | AV6: =IF(AU6>=AU5,AU6-AU5,0) -> 52 | AW6: 2621569 | AX6: =IF(AW6>=AW5,AW6-AW5,0) -> 577 | AY6: 229558 | AZ6: =IF(AY6>=AY5,AY6-AY5,0) -> 5 | BA6: 19301116 | BB6: =IF(BA6>=BA5,BA6-BA5,0) -> 3727 | BC6: 567524 | BD6: =IF(BC6>=BC5,BC6-BC5,0) -> 214 | BE6: 26805 | BF6: =IF(BE6>=BE5,BE6-BE5,0) -> 56 | BG6: 24134832 | BH6: =IF(BG6>=BG5,BG6-BG5,0)-(0.45*BN6)-(0.45*BP6)-BR6 -> 4674.85 | BI6: =AP6+AR6+AT6+AV6+AX6+AZ6+BB6+BD6+BF6+BH6 -> 9818.575 | BJ6: =BI6+AN6 -> 13528.575 | BK6: 1425522 | BL6: =IF(BK6>=BK5,BK6-BK5,0) -> 63 | BM6: 3934116 | BN6: =IF(BM6>=BM5,BM6-BM5,0) -> 971 | BO6: 413897 | BP6: =IF(BO6>=BO5,BO6-BO5,0) -> 136 | BQ6: 518068 | BR6: =IF(BQ6>=BQ5,BQ6-BQ5,0) -> 111 | BS6: =J6+Q6+AN6+BI6 -> 20567.575 | BT6: 194 | BU6: =IF(BS6>0,BS6/BT5,0) -> #DIV/0! | BW6: =IF(BS6>0,BS6/BV6,0) -> #DIV/0! | BX6: =((BS6-Q6)*$BZ$1)+(Q6*$BR$1) -> 23814.711 | BY6: =IF(BX6>0,BX6/BT5,0) -> #DIV/0! | BZ6: =IF(BX6>0,BX6/BV6,0) -> #DIV/0!
A7: 2 | I7: 23948405 | J7: =IF(I7>=I6,I7-I6,0) -> 6640 | K7: =M7+O7 -> 4321 | L7: 687873 | M7: =IF(L7>=L6,L7-L6,0) -> 2582 | N7: 571929 | O7: =IF(N7>=N6,N7-N6,0) -> 1739 | P7: 221761 | Q7: =IF(P7>=P6,P7-P6,0)*30 -> 600 | R7: 182574 | S7: =IF(R7>=R6,R7-R6,0) -> 145 | T7: 333760 | U7: =IF(T7>=T6,T7-T6,0) -> 269 | V7: 796893 | W7: =IF(V7>=V6,V7-V6,0)*0.53 -> 988.45 | X7: 120756 | Y7: =IF(X7>=X6,X7-X6,0)*0.53 -> 0 | Z7: 134745 | AA7: =IF(Z7>=Z6,Z7-Z6,0)*0.53 -> 0 | AB7: 488293 | AC7: =IF(AB7>=AB6,AB7-AB6,0)*0.53 -> 0 | AD7: 657041 | AE7: =IF(AD7>=AD6,AD7-AD6,0)*0.53 -> 13.25 | AF7: 835702 | AG7: =IF(AF7>=AF6,AF7-AF6,0)*0.53 -> 12.72 | AH7: 989509 | AI7: =IF(AH7>=AH6,AH7-AH6,0)*0.53 -> 408.63 | AJ7: 760648 | AK7: =IF(AJ7>=AJ6,AJ7-AJ6,0)*0.53 -> 2044.74 | AL7: 493740 | AM7: =IF(AL7>=AL6,AL7-AL6,0)*0.53 -> 155.29 | AN7: =W7+Y7+AA7+AC7+AE7+AG7+AI7+AK7+AM7 -> 3623.08 | AO7: 7651153 | AP7: =IF(AO7>=AO6,AO7-AO6,0)*0.1125 -> 4.1625 | AQ7: 678094 | AR7: =IF(AQ7>=AQ6,AQ7-AQ6,0) -> 338 | AS7: 966504 | AT7: =IF(AS7>=AS6,AS7-AS6,0) -> 161 | AU7: 810293 | AV7: =IF(AU7>=AU6,AU7-AU6,0) -> 43 | AW7: 2622144 | AX7: =IF(AW7>=AW6,AW7-AW6,0) -> 575 | AY7: 229564 | AZ7: =IF(AY7>=AY6,AY7-AY6,0) -> 6 | BA7: 19305145 | BB7: =IF(BA7>=BA6,BA7-BA6,0) -> 4029 | BC7: 567742 | BD7: =IF(BC7>=BC6,BC7-BC6,0) -> 218 | BE7: 26932 | BF7: =IF(BE7>=BE6,BE7-BE6,0) -> 127 | BG7: 24140284 | BH7: =IF(BG7>=BG6,BG7-BG6,0)-(0.45*BN7)-(0.45*BP7)-BR7 -> 4833.45 | BI7: =AP7+AR7+AT7+AV7+AX7+AZ7+BB7+BD7+BF7+BH7 -> 10334.613 | BJ7: =BI7+AN7 -> 13957.693 | BK7: 1425582 | BL7: =IF(BK7>=BK6,BK7-BK6,0) -> 60 | BM7: 3935053 | BN7: =IF(BM7>=BM6,BM7-BM6,0) -> 937 | BO7: 414039 | BP7: =IF(BO7>=BO6,BO7-BO6,0) -> 142 | BQ7: 518201 | BR7: =IF(BQ7>=BQ6,BQ7-BQ6,0) -> 133 | BS7: =J7+Q7+AN7+BI7 -> 21197.693 | BT7: 194 | BU7: =IF(BS7>0,BS7/BT6,0) -> 109.26646 | BW7: =IF(BS7>0,BS7/BV7,0) -> #DIV/0! | BX7: =((BS7-Q7)*$BZ$1)+(Q7*$BR$1) -> 24647.346 | BY7: =IF(BX7>0,BX7/BT6,0) -> 127.04818 | BZ7: =IF(BX7>0,BX7/BV7,0) -> #DIV/0!
A8: 3 | C8: =IF(+B8-B7>0,B8-B7,(B8-B7)>0)*800 -> 0 | E8: =IF(+D8-D7>0,D8-D7,(D8-D7)>0)*80 -> 0 | G8: =IF(+F8-F7>0,F8-F7,(F8-F7)>0)*10 -> 0 | H8: 57 | I8: 23955296 | J8: =IF(I8>=I7,I8-I7,0) -> 6891 | K8: =M8+O8 -> 4131 | L8: 690576 | M8: =IF(L8>=L7,L8-L7,0) -> 2703 | N8: 573357 | O8: =IF(N8>=N7,N8-N7,0) -> 1428 | P8: 221780 | Q8: =IF(P8>=P7,P8-P7,0)*30 -> 570 | R8: 182714 | S8: =IF(R8>=R7,R8-R7,0) -> 140 | T8: 334006 | U8: =IF(T8>=T7,T8-T7,0) -> 246 | V8: 798719 | W8: =IF(V8>=V7,V8-V7,0)*0.53 -> 967.78 | X8: 120756 | Y8: =IF(X8>=X7,X8-X7,0)*0.53 -> 0 | Z8: 134745 | AA8: =IF(Z8>=Z7,Z8-Z7,0)*0.53 -> 0 | AB8: 488293 | AC8: =IF(AB8>=AB7,AB8-AB7,0)*0.53 -> 0 | AD8: 657067 | AE8: =IF(AD8>=AD7,AD8-AD7,0)*0.53 -> 13.78 | AF8: 835727 | AG8: =IF(AF8>=AF7,AF8-AF7,0)*0.53 -> 13.25 | AH8: 990262 | AI8: =IF(AH8>=AH7,AH8-AH7,0)*0.53 -> 399.09 | AJ8: 764927 | AK8: =IF(AJ8>=AJ7,AJ8-AJ7,0)*0.53 -> 2267.87 | AL8: 494035 | AM8: =IF(AL8>=AL7,AL8-AL7,0)*0.53 -> 156.35 | AN8: =W8+Y8+AA8+AC8+AE8+AG8+AI8+AK8+AM8 -> 3818.12 | AO8: 7651192 | AP8: =IF(AO8>=AO7,AO8-AO7,0)*0.1125 -> 4.3875 | AQ8: 678420 | AR8: =IF(AQ8>=AQ7,AQ8-AQ7,0) -> 326 | AS8: 966651 | AT8: =IF(AS8>=AS7,AS8-AS7,0) -> 147 | AU8: 810336 | AV8: =IF(AU8>=AU7,AU8-AU7,0) -> 43 | AW8: 2622721 | AX8: =IF(AW8>=AW7,AW8-AW7,0) -> 577 | AY8: 229570 | AZ8: =IF(AY8>=AY7,AY8-AY7,0) -> 6 | BA8: 19309285 | BB8: =IF(BA8>=BA7,BA8-BA7,0) -> 4140 | BC8: 567966 | BD8: =IF(BC8>=BC7,BC8-BC7,0) -> 224 | BE8: 26911 | BF8: =IF(BE8>=BE7,BE8-BE7,0) -> 0 | BG8: 24145468 | BH8: =IF(BG8>=BG7,BG8-BG7,0)-(0.45*BN8)-(0.45*BP8)-BR8 -> 4645.6 | BI8: =AP8+AR8+AT8+AV8+AX8+AZ8+BB8+BD8+BF8+BH8 -> 10112.987 | BJ8: =BI8+AN8 -> 13931.107 | BK8: 1425642 | BL8: =IF(BK8>=BK7,BK8-BK7,0) -> 60 | BM8: 3935830 | BN8: =IF(BM8>=BM7,BM8-BM7,0) -> 777 | BO8: 414174 | BP8: =IF(BO8>=BO7,BO8-BO7,0) -> 135 | BQ8: 518329 | BR8: =IF(BQ8>=BQ7,BQ8-BQ7,0) -> 128 | BS8: =J8+Q8+AN8+BI8 -> 21392.107 | BT8: 212 | BU8: =IF(BS8>0,BS8/BT7,0) -> 110.2686 | BW8: =IF(BS8>0,BS8/BV8,0) -> #DIV/0! | BX8: =((BS8-Q8)*$BZ$1)+(Q8*$BR$1) -> 24857.424 | BY8: =IF(BX8>0,BX8/BT7,0) -> 128.13105 | BZ8: =IF(BX8>0,BX8/BV8,0) -> #DIV/0!
A9: 4 | C9: =IF(+B9-B8>0,B9-B8,(B9-B8)>0)*800 -> 0 | E9: =IF(+D9-D8>0,D9-D8,(D9-D8)>0)*80 -> 0 | G9: =IF(+F9-F8>0,F9-F8,(F9-F8)>0)*10 -> 0 | I9: 23962037 | J9: =IF(I9>=I8,I9-I8,0) -> 6741 | K9: =M9+O9 -> 4176 | L9: 693336 | M9: =IF(L9>=L8,L9-L8,0) -> 2760 | N9: 574773 | O9: =IF(N9>=N8,N9-N8,0) -> 1416 | P9: 221800 | Q9: =IF(P9>=P8,P9-P8,0)*30 -> 600 | R9: 182852 | S9: =IF(R9>=R8,R9-R8,0) -> 138 | T9: 334251 | U9: =IF(T9>=T8,T9-T8,0) -> 245 | V9: 800219 | W9: =IF(V9>=V8,V9-V8,0)*0.53 -> 795 | X9: 120756 | Y9: =IF(X9>=X8,X9-X8,0)*0.53 -> 0 | Z9: 134745 | AA9: =IF(Z9>=Z8,Z9-Z8,0)*0.53 -> 0 | AB9: 488293 | AC9: =IF(AB9>=AB8,AB9-AB8,0)*0.53 -> 0 | AD9: 657092 | AE9: =IF(AD9>=AD8,AD9-AD8,0)*0.53 -> 13.25 | AF9: 835751 | AG9: =IF(AF9>=AF8,AF9-AF8,0)*0.53 -> 12.72 | AH9: 990964 | AI9: =IF(AH9>=AH8,AH9-AH8,0)*0.53 -> 372.06 | AJ9: 768260 | AK9: =IF(AJ9>=AJ8,AJ9-AJ8,0)*0.53 -> 1766.49 | AL9: 494315 | AM9: =IF(AL9>=AL8,AL9-AL8,0)*0.53 -> 148.4 | AN9: =W9+Y9+AA9+AC9+AE9+AG9+AI9+AK9+AM9 -> 3107.92 | AO9: 7651229 | AP9: =IF(AO9>=AO8,AO9-AO8,0)*0.1125 -> 4.1625 | AQ9: 678752 | AR9: =IF(AQ9>=AQ8,AQ9-AQ8,0) -> 332 | AS9: 966809 | AT9: =IF(AS9>=AS8,AS9-AS8,0) -> 158 | AU9: 810372 | AV9: =IF(AU9>=AU8,AU9-AU8,0) -> 36 | AW9: 2623251 | AX9: =IF(AW9>=AW8,AW9-AW8,0) -> 530 | AY9: 229576 | AZ9: =IF(AY9>=AY8,AY9-AY8,0) -> 6 | BA9: 19313412 | BB9: =IF(BA9>=BA8,BA9-BA8,0) -> 4127 | BC9: 568170 | BD9: =IF(BC9>=BC8,BC9-BC8,0) -> 204 | BE9: 26965 | BF9: =IF(BE9>=BE8,BE9-BE8,0) -> 54 | BG9: 24150767 | BH9: =IF(BG9>=BG8,BG9-BG8,0)-(0.45*BN9)-(0.45*BP9)-BR9 -> 4734.4 | BI9: =AP9+AR9+AT9+AV9+AX9+AZ9+BB9+BD9+BF9+BH9 -> 10185.562 | BJ9: =BI9+AN9 -> 13293.483 | BK9: 1425702 | BL9: =IF(BK9>=BK8,BK9-BK8,0) -> 60 | BM9: 3936660 | BN9: =IF(BM9>=BM8,BM9-BM8,0) -> 830 | BO9: 414312 | BP9: =IF(BO9>=BO8,BO9-BO8,0) -> 138 | BQ9: 518458 | BR9: =IF(BQ9>=BQ8,BQ9-BQ8,0) -> 129 | BS9: =J9+Q9+AN9+BI9 -> 20634.482 | BT9: 234 | BU9: =IF(BS9>0,BS9/BT8,0) -> 97.332465 | BW9: =IF(BS9>0,BS9/BV9,0) -> #DIV/0! | BX9: =((BS9-Q9)*$BZ$1)+(Q9*$BR$1) -> 23999.655 | BY9: =IF(BX9>0,BX9/BT8,0) -> 113.20592 | BZ9: =IF(BX9>0,BX9/BV9,0) -> #DIV/0!
A10: 5 | C10: =IF(+B10-B9>0,B10-B9,(B10-B9)>0)*800 -> 0 | E10: =IF(+D10-D9>0,D10-D9,(D10-D9)>0)*80 -> 0 | G10: =IF(+F10-F9>0,F10-F9,(F10-F9)>0)*10 -> 0 | H10: 58 | I10: 23968894 | J10: =IF(I10>=I9,I10-I9,0) -> 6857 | K10: =M10+O10 -> 4372 | L10: 696118 | M10: =IF(L10>=L9,L10-L9,0) -> 2782 | N10: 576363 | O10: =IF(N10>=N9,N10-N9,0) -> 1590 | P10: 221821 | Q10: =IF(P10>=P9,P10-P9,0)*30 -> 630 | R10: 182994 | S10: =IF(R10>=R9,R10-R9,0) -> 142 | T10: 334501 | U10: =IF(T10>=T9,T10-T9,0) -> 250 | V10: 802040 | W10: =IF(V10>=V9,V10-V9,0)*0.53 -> 965.13 | X10: 120756 | Y10: =IF(X10>=X9,X10-X9,0)*0.53 -> 0 | Z10: 134745 | AA10: =IF(Z10>=Z9,Z10-Z9,0)*0.53 -> 0 | AB10: 488293 | AC10: =IF(AB10>=AB9,AB10-AB9,0)*0.53 -> 0 | AD10: 657118 | AE10: =IF(AD10>=AD9,AD10-AD9,0)*0.53 -> 13.78 | AF10: 835777 | AG10: =IF(AF10>=AF9,AF10-AF9,0)*0.53 -> 13.78 | AH10: 991717 | AI10: =IF(AH10>=AH9,AH10-AH9,0)*0.53 -> 399.09 | AJ10: 771723 | AK10: =IF(AJ10>=AJ9,AJ10-AJ9,0)*0.53 -> 1835.39 | AL10: 494608 | AM10: =IF(AL10>=AL9,AL10-AL9,0)*0.53 -> 155.29 | AN10: =W10+Y10+AA10+AC10+AE10+AG10+AI10+AK10+AM10 -> 3382.46 | AO10: 7651270 | AP10: =IF(AO10>=AO9,AO10-AO9,0)*0.1125 -> 4.6125 | AQ10: 679118 | AR10: =IF(AQ10>=AQ9,AQ10-AQ9,0) -> 366 | AS10: 966971 | AT10: =IF(AS10>=AS9,AS10-AS9,0) -> 162 | AU10: 810413 | AV10: =IF(AU10>=AU9,AU10-AU9,0) -> 41 | AW10: 2623810 | AX10: =IF(AW10>=AW9,AW10-AW9,0) -> 559 | AY10: 229582 | AZ10: =IF(AY10>=AY9,AY10-AY9,0) -> 6 | BA10: 19317733 | BB10: =IF(BA10>=BA9,BA10-BA9,0) -> 4321 | BC10: 568309 | BD10: =IF(BC10>=BC9,BC10-BC9,0) -> 139 | BE10: 26997 | BF10: =IF(BE10>=BE9,BE10-BE9,0) -> 32 | BG10: 24156115 | BH10: =IF(BG10>=BG9,BG10-BG9,0)-(0.45*BN10)-(0.45*BP10)-BR10 -> 4777.9 | BI10: =AP10+AR10+AT10+AV10+AX10+AZ10+BB10+BD10+BF10+BH10 -> 10408.513 | BJ10: =BI10+AN10 -> 13790.972 | BK10: 1425762 | BL10: =IF(BK10>=BK9,BK10-BK9,0) -> 60 | BM10: 3937499 | BN10: =IF(BM10>=BM9,BM10-BM9,0) -> 839 | BO10: 414451 | BP10: =IF(BO10>=BO9,BO10-BO9,0) -> 139 | BQ10: 518588 | BR10: =IF(BQ10>=BQ9,BQ10-BQ9,0) -> 130 | BS10: =J10+Q10+AN10+BI10 -> 21277.972 | BT10: 216 | BU10: =IF(BS10>0,BS10/BT9,0) -> 90.931506 | BW10: =IF(BS10>0,BS10/BV10,0) -> #DIV/0! | BX10: =((BS10-Q10)*$BZ$1)+(Q10*$BR$1) -> 24753.168 | BY10: =IF(BX10>0,BX10/BT9,0) -> 105.78277 | BZ10: =IF(BX10>0,BX10/BV10,0) -> #DIV/0!
A11: 6 | C11: =IF(+B11-B10>0,B11-B10,(B11-B10)>0)*800 -> 0 | E11: =IF(+D11-D10>0,D11-D10,(D11-D10)>0)*80 -> 0 | G11: =IF(+F11-F10>0,F11-F10,(F11-F10)>0)*10 -> 0 | I11: 23975597 | J11: =IF(I11>=I10,I11-I10,0) -> 6703 | K11: =M11+O11 -> 4233 | L11: 698750 | M11: =IF(L11>=L10,L11-L10,0) -> 2632 | N11: 577964 | O11: =IF(N11>=N10,N11-N10,0) -> 1601 | P11: 221833 | Q11: =IF(P11>=P10,P11-P10,0)*30 -> 360 | R11: 183137 | S11: =IF(R11>=R10,R11-R10,0) -> 143 | T11: 334757 | U11: =IF(T11>=T10,T11-T10,0) -> 256 | V11: 804122 | W11: =IF(V11>=V10,V11-V10,0)*0.53 -> 1103.46 | X11: 120756 | Y11: =IF(X11>=X10,X11-X10,0)*0.53 -> 0 | Z11: 134745 | AA11: =IF(Z11>=Z10,Z11-Z10,0)*0.53 -> 0 | AB11: 488293 | AC11: =IF(AB11>=AB10,AB11-AB10,0)*0.53 -> 0 | AD11: 657143 | AE11: =IF(AD11>=AD10,AD11-AD10,0)*0.53 -> 13.25 | AF11: 835801 | AG11: =IF(AF11>=AF10,AF11-AF10,0)*0.53 -> 12.72 | AH11: 992504 | AI11: =IF(AH11>=AH10,AH11-AH10,0)*0.53 -> 417.11 | AJ11: 775494 | AK11: =IF(AJ11>=AJ10,AJ11-AJ10,0)*0.53 -> 1998.63 | AL11: 494904 | AM11: =IF(AL11>=AL10,AL11-AL10,0)*0.53 -> 156.88 | AN11: =W11+Y11+AA11+AC11+AE11+AG11+AI11+AK11+AM11 -> 3702.05 | AO11: 7651307 | AP11: =IF(AO11>=AO10,AO11-AO10,0)*0.1125 -> 4.1625 | AQ11: 679433 | AR11: =IF(AQ11>=AQ10,AQ11-AQ10,0) -> 315 | AS11: 967138 | AT11: =IF(AS11>=AS10,AS11-AS10,0) -> 167 | AU11: 810456 | AV11: =IF(AU11>=AU10,AU11-AU10,0) -> 43 | AW11: 2624388 | AX11: =IF(AW11>=AW10,AW11-AW10,0) -> 578 | AY11: 229588 | AZ11: =IF(AY11>=AY10,AY11-AY10,0) -> 6 | BA11: 19321948 | BB11: =IF(BA11>=BA10,BA11-BA10,0) -> 4215 | BC11: 568590 | BD11: =IF(BC11>=BC10,BC11-BC10,0) -> 281 | BE11: 27074 | BF11: =IF(BE11>=BE10,BE11-BE10,0) -> 77 | BG11: 24161527 | BH11: =IF(BG11>=BG10,BG11-BG10,0)-(0.45*BN11)-(0.45*BP11)-BR11 -> 4841.7 | BI11: =AP11+AR11+AT11+AV11+AX11+AZ11+BB11+BD11+BF11+BH11 -> 10527.862 | BJ11: =BI11+AN11 -> 14229.912 | BK11: 1425823 | BL11: =IF(BK11>=BK10,BK11-BK10,0) -> 61 | BM11: 3938347 | BN11: =IF(BM11>=BM10,BM11-BM10,0) -> 848 | BO11: 414577 | BP11: =IF(BO11>=BO10,BO11-BO10,0) -> 126 | BQ11: 518720 | BR11: =IF(BQ11>=BQ10,BQ11-BQ10,0) -> 132 | BS11: =J11+Q11+AN11+BI11 -> 21292.912 | BT11: 198 | BU11: =IF(BS11>0,BS11/BT10,0) -> 98.578299 | BW11: =IF(BS11>0,BS11/BV11,0) -> #DIV/0! | BX11: =((BS11-Q11)*$BZ$1)+(Q11*$BR$1) -> 24648.849 | BY11: =IF(BX11>0,BX11/BT10,0) -> 114.11504 | BZ11: =IF(BX11>0,BX11/BV11,0) -> #DIV/0!
A12: 7 | C12: =IF(+B12-B11>0,B12-B11,(B12-B11)>0)*800 -> 0 | E12: =IF(+D12-D11>0,D12-D11,(D12-D11)>0)*80 -> 0 | G12: =IF(+F12-F11>0,F12-F11,(F12-F11)>0)*10 -> 0 | H12: 59 | I12: 23981974 | J12: =IF(I12>=I11,I12-I11,0) -> 6377 | K12: =M12+O12 -> 4224 | L12: 701402 | M12: =IF(L12>=L11,L12-L11,0) -> 2652 | N12: 579536 | O12: =IF(N12>=N11,N12-N11,0) -> 1572 | P12: 221854 | Q12: =IF(P12>=P11,P12-P11,0)*30 -> 630 | R12: 183276 | S12: =IF(R12>=R11,R12-R11,0) -> 139 | T12: 335002 | U12: =IF(T12>=T11,T12-T11,0) -> 245 | V12: 806590 | W12: =IF(V12>=V11,V12-V11,0)*0.53 -> 1308.04 | X12: 120756 | Y12: =IF(X12>=X11,X12-X11,0)*0.53 -> 0 | Z12: 134745 | AA12: =IF(Z12>=Z11,Z12-Z11,0)*0.53 -> 0 | AB12: 488293 | AC12: =IF(AB12>=AB11,AB12-AB11,0)*0.53 -> 0 | AD12: 657168 | AE12: =IF(AD12>=AD11,AD12-AD11,0)*0.53 -> 13.25 | AF12: 835825 | AG12: =IF(AF12>=AF11,AF12-AF11,0)*0.53 -> 12.72 | AH12: 993259 | AI12: =IF(AH12>=AH11,AH12-AH11,0)*0.53 -> 400.15 | AJ12: 779496 | AK12: =IF(AJ12>=AJ11,AJ12-AJ11,0)*0.53 -> 2121.06 | AL12: 495197 | AM12: =IF(AL12>=AL11,AL12-AL11,0)*0.53 -> 155.29 | AN12: =W12+Y12+AA12+AC12+AE12+AG12+AI12+AK12+AM12 -> 4010.51 | AO12: 7651346 | AP12: =IF(AO12>=AO11,AO12-AO11,0)*0.1125 -> 4.3875 | AQ12: 679772 | AR12: =IF(AQ12>=AQ11,AQ12-AQ11,0) -> 339 | AS12: 967258 | AT12: =IF(AS12>=AS11,AS12-AS11,0) -> 120 | AU12: 810500 | AV12: =IF(AU12>=AU11,AU12-AU11,0) -> 44 | AW12: 2624967 | AX12: =IF(AW12>=AW11,AW12-AW11,0) -> 579 | AY12: 229594 | AZ12: =IF(AY12>=AY11,AY12-AY11,0) -> 6 | BA12: 19326072 | BB12: =IF(BA12>=BA11,BA12-BA11,0) -> 4124 | BC12: 568810 | BD12: =IF(BC12>=BC11,BC12-BC11,0) -> 220 | BE12: 27108 | BF12: =IF(BE12>=BE11,BE12-BE11,0) -> 34 | BG12: 24166762 | BH12: =IF(BG12>=BG11,BG12-BG11,0)-(0.45*BN12)-(0.45*BP12)-BR12 -> 4675.85 | BI12: =AP12+AR12+AT12+AV12+AX12+AZ12+BB12+BD12+BF12+BH12 -> 10146.237 | BJ12: =BI12+AN12 -> 14156.747 | BK12: 1425883 | BL12: =IF(BK12>=BK11,BK12-BK11,0) -> 60 | BM12: 3939195 | BN12: =IF(BM12>=BM11,BM12-BM11,0) -> 848 | BO12: 414696 | BP12: =IF(BO12>=BO11,BO12-BO11,0) -> 119 | BQ12: 518844 | BR12: =IF(BQ12>=BQ11,BQ12-BQ11,0) -> 124 | BS12: =J12+Q12+AN12+BI12 -> 21163.747 | BT12: 180 | BU12: =IF(BS12>0,BS12/BT11,0) -> 106.88761 | BW12: =IF(BS12>0,BS12/BV12,0) -> #DIV/0! | BX12: =((BS12-Q12)*$BZ$1)+(Q12*$BR$1) -> 24621.81 | BY12: =IF(BX12>0,BX12/BT11,0) -> 124.35257 | BZ12: =IF(BX12>0,BX12/BV12,0) -> #DIV/0!
A13: 8 | C13: =IF(+B13-B12>0,B13-B12,(B13-B12)>0)*800 -> 0 | E13: =IF(+D13-D12>0,D13-D12,(D13-D12)>0)*80 -> 0 | G13: =IF(+F13-F12>0,F13-F12,(F13-F12)>0)*10 -> 0 | I13: 23988351 | J13: =IF(I13>=I12,I13-I12,0) -> 6377 | K13: =M13+O13 -> 4454 | L13: 704129 | M13: =IF(L13>=L12,L13-L12,0) -> 2727 | N13: 581263 | O13: =IF(N13>=N12,N13-N12,0) -> 1727 | P13: 221872 | Q13: =IF(P13>=P12,P13-P12,0)*30 -> 540 | R13: 183421 | S13: =IF(R13>=R12,R13-R12,0) -> 145 | T13: 335264 | U13: =IF(T13>=T12,T13-T12,0) -> 262 | V13: 809265 | W13: =IF(V13>=V12,V13-V12,0)*0.53 -> 1417.75 | X13: 120756 | Y13: =IF(X13>=X12,X13-X12,0)*0.53 -> 0 | Z13: 134745 | AA13: =IF(Z13>=Z12,Z13-Z12,0)*0.53 -> 0 | AB13: 488293 | AC13: =IF(AB13>=AB12,AB13-AB12,0)*0.53 -> 0 | AD13: 657197 | AE13: =IF(AD13>=AD12,AD13-AD12,0)*0.53 -> 15.37 | AF13: 835854 | AG13: =IF(AF13>=AF12,AF13-AF12,0)*0.53 -> 15.37 | AH13: 994062 | AI13: =IF(AH13>=AH12,AH13-AH12,0)*0.53 -> 425.59 | AJ13: 783545 | AK13: =IF(AJ13>=AJ12,AJ13-AJ12,0)*0.53 -> 2145.97 | AL13: 495507 | AM13: =IF(AL13>=AL12,AL13-AL12,0)*0.53 -> 164.3 | AN13: =W13+Y13+AA13+AC13+AE13+AG13+AI13+AK13+AM13 -> 4184.35 | AO13: 7651390 | AP13: =IF(AO13>=AO12,AO13-AO12,0)*0.1125 -> 4.95 | AQ13: 680130 | AR13: =IF(AQ13>=AQ12,AQ13-AQ12,0) -> 358 | AS13: 967408 | AT13: =IF(AS13>=AS12,AS13-AS12,0) -> 150 | AU13: 810546 | AV13: =IF(AU13>=AU12,AU13-AU12,0) -> 46 | AW13: 2625586 | AX13: =IF(AW13>=AW12,AW13-AW12,0) -> 619 | AY13: 229600 | AZ13: =IF(AY13>=AY12,AY13-AY12,0) -> 6 | BA13: 19330807 | BB13: =IF(BA13>=BA12,BA13-BA12,0) -> 4735 | BC13: 569077 | BD13: =IF(BC13>=BC12,BC13-BC12,0) -> 267 | BE13: 27142 | BF13: =IF(BE13>=BE12,BE13-BE12,0) -> 34 | BG13: 24172975 | BH13: =IF(BG13>=BG12,BG13-BG12,0)-(0.45*BN13)-(0.45*BP13)-BR13 -> 5543.2 | BI13: =AP13+AR13+AT13+AV13+AX13+AZ13+BB13+BD13+BF13+BH13 -> 11763.15 | BJ13: =BI13+AN13 -> 15947.5 | BK13: 1425954 | BL13: =IF(BK13>=BK12,BK13-BK12,0) -> 71 | BM13: 3940199 | BN13: =IF(BM13>=BM12,BM13-BM12,0) -> 1004 | BO13: 414836 | BP13: =IF(BO13>=BO12,BO13-BO12,0) -> 140 | BQ13: 518999 | BR13: =IF(BQ13>=BQ12,BQ13-BQ12,0) -> 155 | BS13: =J13+Q13+AN13+BI13 -> 22864.5 | BT13: 170 | BU13: =IF(BS13>0,BS13/BT12,0) -> 127.025 | BW13: =IF(BS13>0,BS13/BV13,0) -> #DIV/0! | BX13: =((BS13-Q13)*$BZ$1)+(Q13*$BR$1) -> 26537.175 | BY13: =IF(BX13>0,BX13/BT12,0) -> 147.42875 | BZ13: =IF(BX13>0,BX13/BV13,0) -> #DIV/0!
A14: 9 | C14: =IF(+B14-B13>0,B14-B13,(B14-B13)>0)*800 -> 0 | E14: =IF(+D14-D13>0,D14-D13,(D14-D13)>0)*80 -> 0 | G14: =IF(+F14-F13>0,F14-F13,(F14-F13)>0)*10 -> 0 | H14: 60 | I14: 23995236 | J14: =IF(I14>=I13,I14-I13,0) -> 6885 | K14: =M14+O14 -> 5180 | L14: 707470 | M14: =IF(L14>=L13,L14-L13,0) -> 3341 | N14: 583102 | O14: =IF(N14>=N13,N14-N13,0) -> 1839 | P14: 221892 | Q14: =IF(P14>=P13,P14-P13,0)*30 -> 600 | R14: 183589 | S14: =IF(R14>=R13,R14-R13,0) -> 168 | T14: 335562 | U14: =IF(T14>=T13,T14-T13,0) -> 298 | V14: 811715 | W14: =IF(V14>=V13,V14-V13,0)*0.53 -> 1298.5 | X14: 120756 | Y14: =IF(X14>=X13,X14-X13,0)*0.53 -> 0 | Z14: 134745 | AA14: =IF(Z14>=Z13,Z14-Z13,0)*0.53 -> 0 | AB14: 488293 | AC14: =IF(AB14>=AB13,AB14-AB13,0)*0.53 -> 0 | AD14: 657224 | AE14: =IF(AD14>=AD13,AD14-AD13,0)*0.53 -> 14.31 | AF14: 835880 | AG14: =IF(AF14>=AF13,AF14-AF13,0)*0.53 -> 13.78 | AH14: 995004 | AI14: =IF(AH14>=AH13,AH14-AH13,0)*0.53 -> 499.26 | AJ14: 788116 | AK14: =IF(AJ14>=AJ13,AJ14-AJ13,0)*0.53 -> 2422.63 | AL14: 495861 | AM14: =IF(AL14>=AL13,AL14-AL13,0)*0.53 -> 187.62 | AN14: =W14+Y14+AA14+AC14+AE14+AG14+AI14+AK14+AM14 -> 4436.1 | AO14: 7651429 | AP14: =IF(AO14>=AO13,AO14-AO13,0)*0.1125 -> 4.3875 | AQ14: 680490 | AR14: =IF(AQ14>=AQ13,AQ14-AQ13,0) -> 360 | AS14: 967548 | AT14: =IF(AS14>=AS13,AS14-AS13,0) -> 140 | AU14: 810597 | AV14: =IF(AU14>=AU13,AU14-AU13,0) -> 51 | AW14: 2626264 | AX14: =IF(AW14>=AW13,AW14-AW13,0) -> 678 | AY14: 229607 | AZ14: =IF(AY14>=AY13,AY14-AY13,0) -> 7 | BA14: 19334391 | BB14: =IF(BA14>=BA13,BA14-BA13,0) -> 3584 | BC14: 569294 | BD14: =IF(BC14>=BC13,BC14-BC13,0) -> 217 | BE14: 27176 | BF14: =IF(BE14>=BE13,BE14-BE13,0) -> 34 | BG14: 24178697 | BH14: =IF(BG14>=BG13,BG14-BG13,0)-(0.45*BN14)-(0.45*BP14)-BR14 -> 5128.5 | BI14: =AP14+AR14+AT14+AV14+AX14+AZ14+BB14+BD14+BF14+BH14 -> 10203.888 | BJ14: =BI14+AN14 -> 14639.987 | BK14: 1426017 | BL14: =IF(BK14>=BK13,BK14-BK13,0) -> 63 | BM14: 3941083 | BN14: =IF(BM14>=BM13,BM14-BM13,0) -> 884 | BO14: 414962 | BP14: =IF(BO14>=BO13,BO14-BO13,0) -> 126 | BQ14: 519138 | BR14: =IF(BQ14>=BQ13,BQ14-BQ13,0) -> 139 | BS14: =J14+Q14+AN14+BI14 -> 22124.987 | BT14: 154 | BU14: =IF(BS14>0,BS14/BT13,0) -> 130.14699 | BW14: =IF(BS14>0,BS14/BV14,0) -> #DIV/0! | BX14: =((BS14-Q14)*$BZ$1)+(Q14*$BR$1) -> 25713.736 | BY14: =IF(BX14>0,BX14/BT13,0) -> 151.25727 | BZ14: =IF(BX14>0,BX14/BV14,0) -> #DIV/0!
A15: 10 | C15: =IF(+B15-B14>0,B15-B14,(B15-B14)>0)*800 -> 0 | E15: =IF(+D15-D14>0,D15-D14,(D15-D14)>0)*80 -> 0 | G15: =IF(+F15-F14>0,F15-F14,(F15-F14)>0)*10 -> 0 | I15: 24002401 | J15: =IF(I15>=I14,I15-I14,0) -> 7165 | K15: =M15+O15 -> 3454 | L15: 709688 | M15: =IF(L15>=L14,L15-L14,0) -> 2218 | N15: 584338 | O15: =IF(N15>=N14,N15-N14,0) -> 1236 | P15: 221911 | Q15: =IF(P15>=P14,P15-P14,0)*30 -> 570 | R15: 183707 | S15: =IF(R15>=R14,R15-R14,0) -> 118 | T15: 335769 | U15: =IF(T15>=T14,T15-T14,0) -> 207 | V15: 813276 | W15: =IF(V15>=V14,V15-V14,0)*0.53 -> 827.33 | X15: 120756 | Y15: =IF(X15>=X14,X15-X14,0)*0.53 -> 0 | Z15: 134745 | AA15: =IF(Z15>=Z14,Z15-Z14,0)*0.53 -> 0 | AB15: 488293 | AC15: =IF(AB15>=AB14,AB15-AB14,0)*0.53 -> 0 | AD15: 657247 | AE15: =IF(AD15>=AD14,AD15-AD14,0)*0.53 -> 12.19 | AF15: 835901 | AG15: =IF(AF15>=AF14,AF15-AF14,0)*0.53 -> 11.13 | AH15: 995580 | AI15: =IF(AH15>=AH14,AH15-AH14,0)*0.53 -> 305.28 | AJ15: 790980 | AK15: =IF(AJ15>=AJ14,AJ15-AJ14,0)*0.53 -> 1517.92 | AL15: 496084 | AM15: =IF(AL15>=AL14,AL15-AL14,0)*0.53 -> 118.19 | AN15: =W15+Y15+AA15+AC15+AE15+AG15+AI15+AK15+AM15 -> 2792.04 | AO15: 7651462 | AP15: =IF(AO15>=AO14,AO15-AO14,0)*0.1125 -> 3.7125 | AQ15: 680812 | AR15: =IF(AQ15>=AQ14,AQ15-AQ14,0) -> 322 | AS15: 967661 | AT15: =IF(AS15>=AS14,AS15-AS14,0) -> 113 | AU15: 810629 | AV15: =IF(AU15>=AU14,AU15-AU14,0) -> 32 | AW15: 2626707 | AX15: =IF(AW15>=AW14,AW15-AW14,0) -> 443 | AY15: 229612 | AZ15: =IF(AY15>=AY14,AY15-AY14,0) -> 5 | BA15: 19338657 | BB15: =IF(BA15>=BA14,BA15-BA14,0) -> 4266 | BC15: 569486 | BD15: =IF(BC15>=BC14,BC15-BC14,0) -> 192 | BE15: 27210 | BF15: =IF(BE15>=BE14,BE15-BE14,0) -> 34 | BG15: 24183567 | BH15: =IF(BG15>=BG14,BG15-BG14,0)-(0.45*BN15)-(0.45*BP15)-BR15 -> 4372.4 | BI15: =AP15+AR15+AT15+AV15+AX15+AZ15+BB15+BD15+BF15+BH15 -> 9783.1125 | BJ15: =BI15+AN15 -> 12575.153 | BK15: 1426070 | BL15: =IF(BK15>=BK14,BK15-BK14,0) -> 53 | BM15: 3941827 | BN15: =IF(BM15>=BM14,BM15-BM14,0) -> 744 | BO15: 415066 | BP15: =IF(BO15>=BO14,BO15-BO14,0) -> 104 | BQ15: 519254 | BR15: =IF(BQ15>=BQ14,BQ15-BQ14,0) -> 116 | BS15: =J15+Q15+AN15+BI15 -> 20310.153 | BT15: 195 | BU15: =IF(BS15>0,BS15/BT14,0) -> 131.88411 | BW15: =IF(BS15>0,BS15/BV15,0) -> #DIV/0! | BX15: =((BS15-Q15)*$BZ$1)+(Q15*$BR$1) -> 23613.175 | BY15: =IF(BX15>0,BX15/BT14,0) -> 153.33231 | BZ15: =IF(BX15>0,BX15/BV15,0) -> #DIV/0!
A16: 11 | C16: =IF(+B16-B15>0,B16-B15,(B16-B15)>0)*800 -> 0 | E16: =IF(+D16-D15>0,D16-D15,(D16-D15)>0)*80 -> 0 | G16: =IF(+F16-F15>0,F16-F15,(F16-F15)>0)*10 -> 0 | H16: 61 | I16: 24009561 | J16: =IF(I16>=I15,I16-I15,0) -> 7160 | K16: =M16+O16 -> 4364 | L16: 712486 | M16: =IF(L16>=L15,L16-L15,0) -> 2798 | N16: 585904 | O16: =IF(N16>=N15,N16-N15,0) -> 1566 | P16: 221931 | Q16: =IF(P16>=P15,P16-P15,0)*30 -> 600 | R16: 183852 | S16: =IF(R16>=R15,R16-R15,0) -> 145 | T16: 336029 | U16: =IF(T16>=T15,T16-T15,0) -> 260 | V16: 815805 | W16: =IF(V16>=V15,V16-V15,0)*0.53 -> 1340.37 | X16: 120756 | Y16: =IF(X16>=X15,X16-X15,0)*0.53 -> 0 | Z16: 134745 | AA16: =IF(Z16>=Z15,Z16-Z15,0)*0.53 -> 0 | AB16: 488293 | AC16: =IF(AB16>=AB15,AB16-AB15,0)*0.53 -> 0 | AD16: 657274 | AE16: =IF(AD16>=AD15,AD16-AD15,0)*0.53 -> 14.31 | AF16: 835926 | AG16: =IF(AF16>=AF15,AF16-AF15,0)*0.53 -> 13.25 | AH16: 996393 | AI16: =IF(AH16>=AH15,AH16-AH15,0)*0.53 -> 430.89 | AJ16: 794952 | AK16: =IF(AJ16>=AJ15,AJ16-AJ15,0)*0.53 -> 2105.16 | AL16: 496389 | AM16: =IF(AL16>=AL15,AL16-AL15,0)*0.53 -> 161.65 | AN16: =W16+Y16+AA16+AC16+AE16+AG16+AI16+AK16+AM16 -> 4065.63 | AO16: 7651501 | AP16: =IF(AO16>=AO15,AO16-AO15,0)*0.1125 -> 4.3875 | AQ16: 681145 | AR16: =IF(AQ16>=AQ15,AQ16-AQ15,0) -> 333 | AS16: 967762 | AT16: =IF(AS16>=AS15,AS16-AS15,0) -> 101 | AU16: 810667 | AV16: =IF(AU16>=AU15,AU16-AU15,0) -> 38 | AW16: 2627293 | AX16: =IF(AW16>=AW15,AW16-AW15,0) -> 586 | AY16: 229618 | AZ16: =IF(AY16>=AY15,AY16-AY15,0) -> 6 | BA16: 19343344 | BB16: =IF(BA16>=BA15,BA16-BA15,0) -> 4687 | BC16: 569685 | BD16: =IF(BC16>=BC15,BC16-BC15,0) -> 199 | BE16: 27244 | BF16: =IF(BE16>=BE15,BE16-BE15,0) -> 34 | BG16: 24189042 | BH16: =IF(BG16>=BG15,BG16-BG15,0)-(0.45*BN16)-(0.45*BP16)-BR16 -> 4898.1 | BI16: =AP16+AR16+AT16+AV16+AX16+AZ16+BB16+BD16+BF16+BH16 -> 10886.487 | BJ16: =BI16+AN16 -> 14952.118 | BK16: 1426132 | BL16: =IF(BK16>=BK15,BK16-BK15,0) -> 62 | BM16: 3942667 | BN16: =IF(BM16>=BM15,BM16-BM15,0) -> 840 | BO16: 415188 | BP16: =IF(BO16>=BO15,BO16-BO15,0) -> 122 | BQ16: 519398 | BR16: =IF(BQ16>=BQ15,BQ16-BQ15,0) -> 144 | BS16: =J16+Q16+AN16+BI16 -> 22712.118 | BT16: 209 | BU16: =IF(BS16>0,BS16/BT15,0) -> 116.4724 | BW16: =IF(BS16>0,BS16/BV16,0) -> #DIV/0! | BX16: =((BS16-Q16)*$BZ$1)+(Q16*$BR$1) -> 26388.935 | BY16: =IF(BX16>0,BX16/BT15,0) -> 135.32787 | BZ16: =IF(BX16>0,BX16/BV16,0) -> #DIV/0!
A17: 12 | C17: =IF(+B17-B16>0,B17-B16,(B17-B16)>0)*800 -> 0 | E17: =IF(+D17-D16>0,D17-D16,(D17-D16)>0)*80 -> 0 | G17: =IF(+F17-F16>0,F17-F16,(F17-F16)>0)*10 -> 0 | I17: 24016056 | J17: =IF(I17>=I16,I17-I16,0) -> 6495 | K17: =M17+O17 -> 3913 | L17: 714927 | M17: =IF(L17>=L16,L17-L16,0) -> 2441 | N17: 587376 | O17: =IF(N17>=N16,N17-N16,0) -> 1472 | P17: 221941 | Q17: =IF(P17>=P16,P17-P16,0)*30 -> 300 | R17: 183987 | S17: =IF(R17>=R16,R17-R16,0) -> 135 | T17: 336265 | U17: =IF(T17>=T16,T17-T16,0) -> 236 | V17: 818241 | W17: =IF(V17>=V16,V17-V16,0)*0.53 -> 1291.08 | X17: 120756 | Y17: =IF(X17>=X16,X17-X16,0)*0.53 -> 0 | Z17: 134745 | AA17: =IF(Z17>=Z16,Z17-Z16,0)*0.53 -> 0 | AB17: 488293 | AC17: =IF(AB17>=AB16,AB17-AB16,0)*0.53 -> 0 | AD17: 657301 | AE17: =IF(AD17>=AD16,AD17-AD16,0)*0.53 -> 14.31 | AF17: 835952 | AG17: =IF(AF17>=AF16,AF17-AF16,0)*0.53 -> 13.78 | AH17: 997108 | AI17: =IF(AH17>=AH16,AH17-AH16,0)*0.53 -> 378.95 | AJ17: 798493 | AK17: =IF(AJ17>=AJ16,AJ17-AJ16,0)*0.53 -> 1876.73 | AL17: 496661 | AM17: =IF(AL17>=AL16,AL17-AL16,0)*0.53 -> 144.16 | AN17: =W17+Y17+AA17+AC17+AE17+AG17+AI17+AK17+AM17 -> 3719.01 | AO17: 7651538 | AP17: =IF(AO17>=AO16,AO17-AO16,0)*0.1125 -> 4.1625 | AQ17: 681483 | AR17: =IF(AQ17>=AQ16,AQ17-AQ16,0) -> 338 | AS17: 967890 | AT17: =IF(AS17>=AS16,AS17-AS16,0) -> 128 | AU17: 810704 | AV17: =IF(AU17>=AU16,AU17-AU16,0) -> 37 | AW17: 2627833 | AX17: =IF(AW17>=AW16,AW17-AW16,0) -> 540 | AY17: 229624 | AZ17: =IF(AY17>=AY16,AY17-AY16,0) -> 6 | BA17: 19347626 | BB17: =IF(BA17>=BA16,BA17-BA16,0) -> 4282 | BC17: 569886 | BD17: =IF(BC17>=BC16,BC17-BC16,0) -> 201 | BE17: 27278 | BF17: =IF(BE17>=BE16,BE17-BE16,0) -> 34 | BG17: 24194270 | BH17: =IF(BG17>=BG16,BG17-BG16,0)-(0.45*BN17)-(0.45*BP17)-BR17 -> 4682.25 | BI17: =AP17+AR17+AT17+AV17+AX17+AZ17+BB17+BD17+BF17+BH17 -> 10252.413 | BJ17: =BI17+AN17 -> 13971.423 | BK17: 1426312 | BL17: =IF(BK17>=BK16,BK17-BK16,0) -> 180 | BM17: 3943466 | BN17: =IF(BM17>=BM16,BM17-BM16,0) -> 799 | BO17: 415304 | BP17: =IF(BO17>=BO16,BO17-BO16,0) -> 116 | BQ17: 519532 | BR17: =IF(BQ17>=BQ16,BQ17-BQ16,0) -> 134 | BS17: =J17+Q17+AN17+BI17 -> 20766.423 | BT17: 192 | BU17: =IF(BS17>0,BS17/BT16,0) -> 99.360873 | BW17: =IF(BS17>0,BS17/BV17,0) -> #DIV/0! | BX17: =((BS17-Q17)*$BZ$1)+(Q17*$BR$1) -> 24016.386 | BY17: =IF(BX17>0,BX17/BT16,0) -> 114.91094 | BZ17: =IF(BX17>0,BX17/BV17,0) -> #DIV/0!
A18: 13 | C18: =IF(+B18-B17>0,B18-B17,(B18-B17)>0)*800 -> 0 | E18: =IF(+D18-D17>0,D18-D17,(D18-D17)>0)*80 -> 0 | G18: =IF(+F18-F17>0,F18-F17,(F18-F17)>0)*10 -> 0 | H18: 62 | I18: 24023415 | J18: =IF(I18>=I17,I18-I17,0) -> 7359 | K18: =M18+O18 -> 5567 | L18: 718426 | M18: =IF(L18>=L17,L18-L17,0) -> 3499 | N18: 589444 | O18: =IF(N18>=N17,N18-N17,0) -> 2068 | P18: 221964 | Q18: =IF(P18>=P17,P18-P17,0)*30 -> 690 | R18: 184133 | S18: =IF(R18>=R17,R18-R17,0) -> 146 | T18: 336539 | U18: =IF(T18>=T17,T18-T17,0) -> 274 | V18: 821228 | W18: =IF(V18>=V17,V18-V17,0)*0.53 -> 1583.11 | X18: 120829 | Y18: =IF(X18>=X17,X18-X17,0)*0.53 -> 38.69 | Z18: 134801 | AA18: =IF(Z18>=Z17,Z18-Z17,0)*0.53 -> 29.68 | AB18: 488405 | AC18: =IF(AB18>=AB17,AB18-AB17,0)*0.53 -> 59.36 | AD18: 657323 | AE18: =IF(AD18>=AD17,AD18-AD17,0)*0.53 -> 11.66 | AF18: 835974 | AG18: =IF(AF18>=AF17,AF18-AF17,0)*0.53 -> 11.66 | AH18: 998101 | AI18: =IF(AH18>=AH17,AH18-AH17,0)*0.53 -> 526.29 | AJ18: 803507 | AK18: =IF(AJ18>=AJ17,AJ18-AJ17,0)*0.53 -> 2657.42 | AL18: 496956 | AM18: =IF(AL18>=AL17,AL18-AL17,0)*0.53 -> 156.35 | AN18: =W18+Y18+AA18+AC18+AE18+AG18+AI18+AK18+AM18 -> 5074.22 | AO18: 7652014 | AP18: =IF(AO18>=AO17,AO18-AO17,0)*0.1125 -> 53.55 | AQ18: 681810 | AR18: =IF(AQ18>=AQ17,AQ18-AQ17,0) -> 327 | AS18: 968052 | AT18: =IF(AS18>=AS17,AS18-AS17,0) -> 162 | AU18: 810757 | AV18: =IF(AU18>=AU17,AU18-AU17,0) -> 53 | AW18: 2628555 | AX18: =IF(AW18>=AW17,AW18-AW17,0) -> 722 | AY18: 229630 | AZ18: =IF(AY18>=AY17,AY18-AY17,0) -> 6 | BA18: 19353061 | BB18: =IF(BA18>=BA17,BA18-BA17,0) -> 5435 | BC18: 570128 | BD18: =IF(BC18>=BC17,BC18-BC17,0) -> 242 | BE18: 27312 | BF18: =IF(BE18>=BE17,BE18-BE17,0) -> 34 | BG18: 24200184 | BH18: =IF(BG18>=BG17,BG18-BG17,0)-(0.45*BN18)-(0.45*BP18)-BR18 -> 5334.2 | BI18: =AP18+AR18+AT18+AV18+AX18+AZ18+BB18+BD18+BF18+BH18 -> 12368.75 | BJ18: =BI18+AN18 -> 17442.97 | BK18: 1426592 | BL18: =IF(BK18>=BK17,BK18-BK17,0) -> 280 | BM18: 3944289 | BN18: =IF(BM18>=BM17,BM18-BM17,0) -> 823 | BO18: 415445 | BP18: =IF(BO18>=BO17,BO18-BO17,0) -> 141 | BQ18: 519678 | BR18: =IF(BQ18>=BQ17,BQ18-BQ17,0) -> 146 | BS18: =J18+Q18+AN18+BI18 -> 25491.97 | BT18: 228 | BU18: =IF(BS18>0,BS18/BT17,0) -> 132.77068 | BW18: =IF(BS18>0,BS18/BV18,0) -> #DIV/0! | BX18: =((BS18-Q18)*$BZ$1)+(Q18*$BR$1) -> 29626.265 | BY18: =IF(BX18>0,BX18/BT17,0) -> 154.30347 | BZ18: =IF(BX18>0,BX18/BV18,0) -> #DIV/0!
A19: 14 | C19: =IF(+B19-B18>0,B19-B18,(B19-B18)>0)*800 -> 0 | E19: =IF(+D19-D18>0,D19-D18,(D19-D18)>0)*80 -> 0 | G19: =IF(+F19-F18>0,F19-F18,(F19-F18)>0)*10 -> 0 | I19: 24030241 | J19: =IF(I19>=I18,I19-I18,0) -> 6826 | K19: =M19+O19 -> 3170 | L19: 720274 | M19: =IF(L19>=L18,L19-L18,0) -> 1848 | N19: 590766 | O19: =IF(N19>=N18,N19-N18,0) -> 1322 | P19: 221981 | Q19: =IF(P19>=P18,P19-P18,0)*30 -> 510 | R19: 184273 | S19: =IF(R19>=R18,R19-R18,0) -> 140 | T19: 336791 | U19: =IF(T19>=T18,T19-T18,0) -> 252 | V19: 822964 | W19: =IF(V19>=V18,V19-V18,0)*0.53 -> 920.08 | X19: 120829 | Y19: =IF(X19>=X18,X19-X18,0)*0.53 -> 0 | Z19: 134801 | AA19: =IF(Z19>=Z18,Z19-Z18,0)*0.53 -> 0 | AB19: 488405 | AC19: =IF(AB19>=AB18,AB19-AB18,0)*0.53 -> 0 | AD19: 657348 | AE19: =IF(AD19>=AD18,AD19-AD18,0)*0.53 -> 13.25 | AF19: 835998 | AG19: =IF(AF19>=AF18,AF19-AF18,0)*0.53 -> 12.72 | AH19: 998633 | AI19: =IF(AH19>=AH18,AH19-AH18,0)*0.53 -> 281.96 | AJ19: 805959 | AK19: =IF(AJ19>=AJ18,AJ19-AJ18,0)*0.53 -> 1299.56 | AL19: 497159 | AM19: =IF(AL19>=AL18,AL19-AL18,0)*0.53 -> 107.59 | AN19: =W19+Y19+AA19+AC19+AE19+AG19+AI19+AK19+AM19 -> 2635.16 | AO19: 7652871 | AP19: =IF(AO19>=AO18,AO19-AO18,0)*0.1125 -> 96.4125 | AQ19: 682112 | AR19: =IF(AQ19>=AQ18,AQ19-AQ18,0) -> 302 | AS19: 968183 | AT19: =IF(AS19>=AS18,AS19-AS18,0) -> 131 | AU19: 810790 | AV19: =IF(AU19>=AU18,AU19-AU18,0) -> 33 | AW19: 2628991 | AX19: =IF(AW19>=AW18,AW19-AW18,0) -> 436 | AY19: 229636 | AZ19: =IF(AY19>=AY18,AY19-AY18,0) -> 6 | BA19: 19356431 | BB19: =IF(BA19>=BA18,BA19-BA18,0) -> 3370 | BC19: 570396 | BD19: =IF(BC19>=BC18,BC19-BC18,0) -> 268 | BE19: 27346 | BF19: =IF(BE19>=BE18,BE19-BE18,0) -> 34 | BG19: 24206185 | BH19: =IF(BG19>=BG18,BG19-BG18,0)-(0.45*BN19)-(0.45*BP19)-BR19 -> 5418.7 | BI19: =AP19+AR19+AT19+AV19+AX19+AZ19+BB19+BD19+BF19+BH19 -> 10095.112 | BJ19: =BI19+AN19 -> 12730.272 | BK19: 1426887 | BL19: =IF(BK19>=BK18,BK19-BK18,0) -> 295 | BM19: 3945118 | BN19: =IF(BM19>=BM18,BM19-BM18,0) -> 829 | BO19: 415590 | BP19: =IF(BO19>=BO18,BO19-BO18,0) -> 145 | BQ19: 519822 | BR19: =IF(BQ19>=BQ18,BQ19-BQ18,0) -> 144 | BS19: =J19+Q19+AN19+BI19 -> 20066.272 | BT19: 230 | BU19: =IF(BS19>0,BS19/BT18,0) -> 88.009967 | BW19: =IF(BS19>0,BS19/BV19,0) -> #DIV/0! | BX19: =((BS19-Q19)*$BZ$1)+(Q19*$BR$1) -> 23305.713 | BY19: =IF(BX19>0,BX19/BT18,0) -> 102.21804 | BZ19: =IF(BX19>0,BX19/BV19,0) -> #DIV/0!
A20: 15 | C20: =IF(+B20-B19>0,B20-B19,(B20-B19)>0)*800 -> 0 | E20: =IF(+D20-D19>0,D20-D19,(D20-D19)>0)*80 -> 0 | G20: =IF(+F20-F19>0,F20-F19,(F20-F19)>0)*10 -> 0 | H20: 63 | I20: 24038128 | J20: =IF(I20>=I19,I20-I19,0) -> 7887 | K20: =M20+O20 -> 4907 | L20: 723199 | M20: =IF(L20>=L19,L20-L19,0) -> 2925 | N20: 592748 | O20: =IF(N20>=N19,N20-N19,0) -> 1982 | P20: 221992 | Q20: =IF(P20>=P19,P20-P19,0)*30 -> 330 | R20: 184439 | S20: =IF(R20>=R19,R20-R19,0) -> 166 | T20: 337094 | U20: =IF(T20>=T19,T20-T19,0) -> 303 | V20: 825875 | W20: =IF(V20>=V19,V20-V19,0)*0.53 -> 1542.83 | X20: 120829 | Y20: =IF(X20>=X19,X20-X19,0)*0.53 -> 0 | Z20: 134801 | AA20: =IF(Z20>=Z19,Z20-Z19,0)*0.53 -> 0 | AB20: 488405 | AC20: =IF(AB20>=AB19,AB20-AB19,0)*0.53 -> 0 | AD20: 657377 | AE20: =IF(AD20>=AD19,AD20-AD19,0)*0.53 -> 15.37 | AF20: 836026 | AG20: =IF(AF20>=AF19,AF20-AF19,0)*0.53 -> 14.84 | AH20: 999471 | AI20: =IF(AH20>=AH19,AH20-AH19,0)*0.53 -> 444.14 | AJ20: 810117 | AK20: =IF(AJ20>=AJ19,AJ20-AJ19,0)*0.53 -> 2203.74 | AL20: 497481 | AM20: =IF(AL20>=AL19,AL20-AL19,0)*0.53 -> 170.66 | AN20: =W20+Y20+AA20+AC20+AE20+AG20+AI20+AK20+AM20 -> 4391.58 | AO20: 7653604 | AP20: =IF(AO20>=AO19,AO20-AO19,0)*0.1125 -> 82.4625 | AQ20: 682443 | AR20: =IF(AQ20>=AQ19,AQ20-AQ19,0) -> 331 | AS20: 968314 | AT20: =IF(AS20>=AS19,AS20-AS19,0) -> 131 | AU20: 810838 | AV20: =IF(AU20>=AU19,AU20-AU19,0) -> 48 | AW20: 2629601 | AX20: =IF(AW20>=AW19,AW20-AW19,0) -> 610 | AY20: 229643 | AZ20: =IF(AY20>=AY19,AY20-AY19,0) -> 7 | BA20: 19361845 | BB20: =IF(BA20>=BA19,BA20-BA19,0) -> 5414 | BC20: 570642 | BD20: =IF(BC20>=BC19,BC20-BC19,0) -> 246 | BE20: 27380 | BF20: =IF(BE20>=BE19,BE20-BE19,0) -> 34 | BG20: 24211755 | BH20: =IF(BG20>=BG19,BG20-BG19,0)-(0.45*BN20)-(0.45*BP20)-BR20 -> 5031.95 | BI20: =AP20+AR20+AT20+AV20+AX20+AZ20+BB20+BD20+BF20+BH20 -> 11935.413 | BJ20: =BI20+AN20 -> 16326.993 | BK20: 1427172 | BL20: =IF(BK20>=BK19,BK20-BK19,0) -> 285 | BM20: 3945870 | BN20: =IF(BM20>=BM19,BM20-BM19,0) -> 752 | BO20: 415727 | BP20: =IF(BO20>=BO19,BO20-BO19,0) -> 137 | BQ20: 519960 | BR20: =IF(BQ20>=BQ19,BQ20-BQ19,0) -> 138 | BS20: =J20+Q20+AN20+BI20 -> 24543.993 | BT20: 235 | BU20: =IF(BS20>0,BS20/BT20,0) -> 104.44252 | BW20: =IF(BS20>0,BS20/BV20,0) -> #DIV/0! | BX20: =((BS20-Q20)*$BZ$1)+(Q20*$BR$1) -> 28374.091 | BY20: =IF(BX20>0,BX20/BT20,0) -> 120.74081 | BZ20: =IF(BX20>0,BX20/BV20,0) -> #DIV/0!
A21: 16 | C21: =IF(+B21-B20>0,B21-B20,(B21-B20)>0)*800 -> 0 | E21: =IF(+D21-D20>0,D21-D20,(D21-D20)>0)*80 -> 0 | G21: =IF(+F21-F20>0,F21-F20,(F21-F20)>0)*10 -> 0 | I21: 24044642 | J21: =IF(I21>=I20,I21-I20,0) -> 6514 | K21: =M21+O21 -> 4061 | L21: 725615 | M21: =IF(L21>=L20,L21-L20,0) -> 2416 | N21: 594393 | O21: =IF(N21>=N20,N21-N20,0) -> 1645 | P21: 222012 | Q21: =IF(P21>=P20,P21-P20,0)*30 -> 600 | R21: 184556 | S21: =IF(R21>=R20,R21-R20,0) -> 117 | T21: 337306 | U21: =IF(T21>=T20,T21-T20,0) -> 212 | V21: 828031 | W21: =IF(V21>=V20,V21-V20,0)*0.53 -> 1142.68 | X21: 121075 | Y21: =IF(X21>=X20,X21-X20,0)*0.53 -> 130.38 | Z21: 134801 | AA21: =IF(Z21>=Z20,Z21-Z20,0)*0.53 -> 0 | AB21: 488405 | AC21: =IF(AB21>=AB20,AB21-AB20,0)*0.53 -> 0 | AD21: 657401 | AE21: =IF(AD21>=AD20,AD21-AD20,0)*0.53 -> 12.72 | AF21: 836050 | AG21: =IF(AF21>=AF20,AF21-AF20,0)*0.53 -> 12.72 | AI21: =IF(AH21>=AH20,AH21-AH20,0)*0.53 -> 0 | AJ21: 813352 | AK21: =IF(AJ21>=AJ20,AJ21-AJ20,0)*0.53 -> 1714.55 | AL21: 497745 | AM21: =IF(AL21>=AL20,AL21-AL20,0)*0.53 -> 139.92 | AN21: =W21+Y21+AA21+AC21+AE21+AG21+AI21+AK21+AM21 -> 3152.97 | AO21: 7654284 | AP21: =IF(AO21>=AO20,AO21-AO20,0)*0.1125 -> 76.5 | AQ21: 682767 | AR21: =IF(AQ21>=AQ20,AQ21-AQ20,0) -> 324 | AS21: 968445 | AT21: =IF(AS21>=AS20,AS21-AS20,0) -> 131 | AU21: 810876 | AV21: =IF(AU21>=AU20,AU21-AU20,0) -> 38 | AW21: 2630125 | AX21: =IF(AW21>=AW20,AW21-AW20,0) -> 524 | AY21: 229648 | AZ21: =IF(AY21>=AY20,AY21-AY20,0) -> 5 | BA21: 19366209 | BB21: =IF(BA21>=BA20,BA21-BA20,0) -> 4364 | BC21: 570878 | BD21: =IF(BC21>=BC20,BC21-BC20,0) -> 236 | BE21: 27414 | BF21: =IF(BE21>=BE20,BE21-BE20,0) -> 34 | BG21: 24216983 | BH21: =IF(BG21>=BG20,BG21-BG20,0)-(0.45*BN21)-(0.45*BP21)-BR21 -> 4720.95 | BI21: =AP21+AR21+AT21+AV21+AX21+AZ21+BB21+BD21+BF21+BH21 -> 10453.45 | BJ21: =BI21+AN21 -> 13606.42 | BK21: 1427434 | BL21: =IF(BK21>=BK20,BK21-BK20,0) -> 262 | BM21: 3946560 | BN21: =IF(BM21>=BM20,BM21-BM20,0) -> 690 | BO21: 415846 | BP21: =IF(BO21>=BO20,BO21-BO20,0) -> 119 | BQ21: 520103 | BR21: =IF(BQ21>=BQ20,BQ21-BQ20,0) -> 143 | BS21: =J21+Q21+AN21+BI21 -> 20720.42 | BT21: 248 | BU21: =IF(BS21>0,BS21/BT21,0) -> 83.550081 | BW21: =IF(BS21>0,BS21/BV21,0) -> #DIV/0! | BX21: =((BS21-Q21)*$BZ$1)+(Q21*$BR$1) -> 24098.483 | BY21: =IF(BX21>0,BX21/BT21,0) -> 97.171302 | BZ21: =IF(BX21>0,BX21/BV21,0) -> #DIV/0!
A22: 17 | C22: =IF(+B22-B21>0,B22-B21,(B22-B21)>0)*800 -> 0 | E22: =IF(+D22-D21>0,D22-D21,(D22-D21)>0)*80 -> 0 | G22: =IF(+F22-F21>0,F22-F21,(F22-F21)>0)*10 -> 0 | H22: 64 | I22: 24051813 | J22: =IF(I22>=I21,I22-I21,0) -> 7171 | K22: =M22+O22 -> 4421 | L22: 728200 | M22: =IF(L22>=L21,L22-L21,0) -> 2585 | N22: 596229 | O22: =IF(N22>=N21,N22-N21,0) -> 1836 | P22: 222031 | Q22: =IF(P22>=P21,P22-P21,0)*30 -> 570 | R22: 184694 | S22: =IF(R22>=R21,R22-R21,0) -> 138 | T22: 337558 | U22: =IF(T22>=T21,T22-T21,0) -> 252 | V22: 831223 | W22: =IF(V22>=V21,V22-V21,0)*0.53 -> 1691.76 | X22: 121075 | Y22: =IF(X22>=X21,X22-X21,0)*0.53 -> 0 | Z22: 134801 | AA22: =IF(Z22>=Z21,Z22-Z21,0)*0.53 -> 0 | AB22: 488405 | AC22: =IF(AB22>=AB21,AB22-AB21,0)*0.53 -> 0 | AD22: 657419 | AE22: =IF(AD22>=AD21,AD22-AD21,0)*0.53 -> 9.54 | AF22: 836067 | AG22: =IF(AF22>=AF21,AF22-AF21,0)*0.53 -> 9.01 | AI22: =IF(AH22>=AH21,AH22-AH21,0)*0.53 -> 0 | AJ22: 817200 | AK22: =IF(AJ22>=AJ21,AJ22-AJ21,0)*0.53 -> 2039.44 | AL22: 498040 | AM22: =IF(AL22>=AL21,AL22-AL21,0)*0.53 -> 156.35 | AN22: =W22+Y22+AA22+AC22+AE22+AG22+AI22+AK22+AM22 -> 3906.1 | AO22: 7654778 | AP22: =IF(AO22>=AO21,AO22-AO21,0)*0.1125 -> 55.575 | AQ22: 683103 | AR22: =IF(AQ22>=AQ21,AQ22-AQ21,0) -> 336 | AS22: 968596 | AT22: =IF(AS22>=AS21,AS22-AS21,0) -> 151 | AU22: 810917 | AV22: =IF(AU22>=AU21,AU22-AU21,0) -> 41 | AW22: 2630712 | AX22: =IF(AW22>=AW21,AW22-AW21,0) -> 587 | AY22: 229653 | AZ22: =IF(AY22>=AY21,AY22-AY21,0) -> 5 | BA22: 19370187 | BB22: =IF(BA22>=BA21,BA22-BA21,0) -> 3978 | BC22: 571116 | BD22: =IF(BC22>=BC21,BC22-BC21,0) -> 238 | BE22: 27669 | BF22: =IF(BE22>=BE21,BE22-BE21,0) -> 255 | BG22: 24222184 | BH22: =IF(BG22>=BG21,BG22-BG21,0)-(0.45*BN22)-(0.45*BP22)-BR22 -> 4722.05 | BI22: =AP22+AR22+AT22+AV22+AX22+AZ22+BB22+BD22+BF22+BH22 -> 10368.625 | BJ22: =BI22+AN22 -> 14274.725 | BK22: 1427687 | BL22: =IF(BK22>=BK21,BK22-BK21,0) -> 253 | BM22: 3947239 | BN22: =IF(BM22>=BM21,BM22-BM21,0) -> 679 | BO22: 415958 | BP22: =IF(BO22>=BO21,BO22-BO21,0) -> 112 | BQ22: 520226 | BR22: =IF(BQ22>=BQ21,BQ22-BQ21,0) -> 123 | BS22: =J22+Q22+AN22+BI22 -> 22015.725 | BT22: 251 | BU22: =IF(BS22>0,BS22/BT22,0) -> 87.712052 | BW22: =IF(BS22>0,BS22/BV22,0) -> #DIV/0! | BX22: =((BS22-Q22)*$BZ$1)+(Q22*$BR$1) -> 25574.584 | BY22: =IF(BX22>0,BX22/BT22,0) -> 101.89077 | BZ22: =IF(BX22>0,BX22/BV22,0) -> #DIV/0!
A23: 18 | C23: =IF(+B23-B22>0,B23-B22,(B23-B22)>0)*800 -> 0 | E23: =IF(+D23-D22>0,D23-D22,(D23-D22)>0)*80 -> 0 | G23: =IF(+F23-F22>0,F23-F22,(F23-F22)>0)*10 -> 0 | I23: 24058640 | J23: =IF(I23>=I22,I23-I22,0) -> 6827 | K23: =M23+O23 -> 4237 | L23: 730715 | M23: =IF(L23>=L22,L23-L22,0) -> 2515 | N23: 597951 | O23: =IF(N23>=N22,N23-N22,0) -> 1722 | P23: 222051 | Q23: =IF(P23>=P22,P23-P22,0)*30 -> 600 | R23: 184856 | S23: =IF(R23>=R22,R23-R22,0) -> 162 | T23: 337853 | U23: =IF(T23>=T22,T23-T22,0) -> 295 | V23: 834153 | W23: =IF(V23>=V22,V23-V22,0)*0.53 -> 1552.9 | X23: 121075 | Y23: =IF(X23>=X22,X23-X22,0)*0.53 -> 0 | Z23: 134801 | AA23: =IF(Z23>=Z22,Z23-Z22,0)*0.53 -> 0 | AB23: 488405 | AC23: =IF(AB23>=AB22,AB23-AB22,0)*0.53 -> 0 | AD23: 657444 | AE23: =IF(AD23>=AD22,AD23-AD22,0)*0.53 -> 13.25 | AF23: 836093 | AG23: =IF(AF23>=AF22,AF23-AF22,0)*0.53 -> 13.78 | AH23: 1665 | AI23: =IF(AH23>=AH22,AH23-AH22,0)*0.53 -> 882.45 | AJ23: 820938 | AK23: =IF(AJ23>=AJ22,AJ23-AJ22,0)*0.53 -> 1981.14 | AL23: 498330 | AM23: =IF(AL23>=AL22,AL23-AL22,0)*0.53 -> 153.7 | AN23: =W23+Y23+AA23+AC23+AE23+AG23+AI23+AK23+AM23 -> 4597.22 | AO23: 7654819 | AP23: =IF(AO23>=AO22,AO23-AO22,0)*0.1125 -> 4.6125 | AQ23: 683438 | AR23: =IF(AQ23>=AQ22,AQ23-AQ22,0) -> 335 | AS23: 968747 | AT23: =IF(AS23>=AS22,AS23-AS22,0) -> 151 | AU23: 810953 | AV23: =IF(AU23>=AU22,AU23-AU22,0) -> 36 | AW23: 2631289 | AX23: =IF(AW23>=AW22,AW23-AW22,0) -> 577 | AY23: 229660 | AZ23: =IF(AY23>=AY22,AY23-AY22,0) -> 7 | BA23: 19373832 | BB23: =IF(BA23>=BA22,BA23-BA22,0) -> 3645 | BC23: 571413 | BD23: =IF(BC23>=BC22,BC23-BC22,0) -> 297 | BE23: 27722 | BF23: =IF(BE23>=BE22,BE23-BE22,0) -> 53 | BG23: 24228051 | BH23: =IF(BG23>=BG22,BG23-BG22,0)-(0.45*BN23)-(0.45*BP23)-BR23 -> 5319.45 | BI23: =AP23+AR23+AT23+AV23+AX23+AZ23+BB23+BD23+BF23+BH23 -> 10425.062 | BJ23: =BI23+AN23 -> 15022.283 | BK23: 1427985 | BL23: =IF(BK23>=BK22,BK23-BK22,0) -> 298 | BM23: 3948006 | BN23: =IF(BM23>=BM22,BM23-BM22,0) -> 767 | BO23: 416090 | BP23: =IF(BO23>=BO22,BO23-BO22,0) -> 132 | BQ23: 520369 | BR23: =IF(BQ23>=BQ22,BQ23-BQ22,0) -> 143 | BS23: =J23+Q23+AN23+BI23 -> 22449.283 | BT23: 251 | BU23: =IF(BS23>0,BS23/BT23,0) -> 89.439373 | BW23: =IF(BS23>0,BS23/BV23,0) -> #DIV/0! | BX23: =((BS23-Q23)*$BZ$1)+(Q23*$BR$1) -> 26086.675 | BY23: =IF(BX23>0,BX23/BT23,0) -> 103.93098 | BZ23: =IF(BX23>0,BX23/BV23,0) -> #DIV/0!
A24: 19 | C24: =IF(+B24-B23>0,B24-B23,(B24-B23)>0)*800 -> 0 | E24: =IF(+D24-D23>0,D24-D23,(D24-D23)>0)*80 -> 0 | G24: =IF(+F24-F23>0,F24-F23,(F24-F23)>0)*10 -> 0 | H24: 65 | I24: 24065506 | J24: =IF(I24>=I23,I24-I23,0) -> 6866 | K24: =M24+O24 -> 4184 | L24: 733324 | M24: =IF(L24>=L23,L24-L23,0) -> 2609 | N24: 599526 | O24: =IF(N24>=N23,N24-N23,0) -> 1575 | P24: 222061 | Q24: =IF(P24>=P23,P24-P23,0)*30 -> 300 | R24: 184982 | S24: =IF(R24>=R23,R24-R23,0) -> 126 | T24: 338085 | U24: =IF(T24>=T23,T24-T23,0) -> 232 | V24: 836562 | W24: =IF(V24>=V23,V24-V23,0)*0.53 -> 1276.77 | X24: 121075 | Y24: =IF(X24>=X23,X24-X23,0)*0.53 -> 0 | Z24: 134801 | AA24: =IF(Z24>=Z23,Z24-Z23,0)*0.53 -> 0 | AB24: 488405 | AC24: =IF(AB24>=AB23,AB24-AB23,0)*0.53 -> 0 | AD24: 657469 | AE24: =IF(AD24>=AD23,AD24-AD23,0)*0.53 -> 13.25 | AF24: 836117 | AG24: =IF(AF24>=AF23,AF24-AF23,0)*0.53 -> 12.72 | AH24: 2396 | AI24: =IF(AH24>=AH23,AH24-AH23,0)*0.53 -> 387.43 | AJ24: 824653 | AK24: =IF(AJ24>=AJ23,AJ24-AJ23,0)*0.53 -> 1968.95 | AL24: 498621 | AM24: =IF(AL24>=AL23,AL24-AL23,0)*0.53 -> 154.23 | AN24: =W24+Y24+AA24+AC24+AE24+AG24+AI24+AK24+AM24 -> 3813.35 | AO24: 7654859 | AP24: =IF(AO24>=AO23,AO24-AO23,0)*0.1125 -> 4.5 | AQ24: 683741 | AR24: =IF(AQ24>=AQ23,AQ24-AQ23,0) -> 303 | AS24: 968887 | AT24: =IF(AS24>=AS23,AS24-AS23,0) -> 140 | AU24: 810994 | AV24: =IF(AU24>=AU23,AU24-AU23,0) -> 41 | AW24: 2631834 | AX24: =IF(AW24>=AW23,AW24-AW23,0) -> 545 | AY24: 229665 | AZ24: =IF(AY24>=AY23,AY24-AY23,0) -> 5 | BA24: 19378237 | BB24: =IF(BA24>=BA23,BA24-BA23,0) -> 4405 | BC24: 571653 | BD24: =IF(BC24>=BC23,BC24-BC23,0) -> 240 | BE24: 27776 | BF24: =IF(BE24>=BE23,BE24-BE23,0) -> 54 | BG24: 24232939 | BH24: =IF(BG24>=BG23,BG24-BG23,0)-(0.45*BN24)-(0.45*BP24)-BR24 -> 4440.3 | BI24: =AP24+AR24+AT24+AV24+AX24+AZ24+BB24+BD24+BF24+BH24 -> 10177.8 | BJ24: =BI24+AN24 -> 13991.15 | BK24: 1428236 | BL24: =IF(BK24>=BK23,BK24-BK23,0) -> 251 | BM24: 3948619 | BN24: =IF(BM24>=BM23,BM24-BM23,0) -> 613 | BO24: 416203 | BP24: =IF(BO24>=BO23,BO24-BO23,0) -> 113 | BQ24: 520490 | BR24: =IF(BQ24>=BQ23,BQ24-BQ23,0) -> 121 | BS24: =J24+Q24+AN24+BI24 -> 21157.15 | BT24: 253 | BU24: =IF(BS24>0,BS24/BT24,0) -> 83.625099 | BW24: =IF(BS24>0,BS24/BV24,0) -> #DIV/0! | BX24: =((BS24-Q24)*$BZ$1)+(Q24*$BR$1) -> 24465.722 | BY24: =IF(BX24>0,BX24/BT24,0) -> 96.70246 | BZ24: =IF(BX24>0,BX24/BV24,0) -> #DIV/0!
A25: 20 | C25: =IF(+B25-B24>0,B25-B24,(B25-B24)>0)*800 -> 0 | E25: =IF(+D25-D24>0,D25-D24,(D25-D24)>0)*80 -> 0 | G25: =IF(+F25-F24>0,F25-F24,(F25-F24)>0)*10 -> 0 | I25: 24071947 | J25: =IF(I25>=I24,I25-I24,0) -> 6441 | K25: =M25+O25 -> 4073 | L25: 735735 | M25: =IF(L25>=L24,L25-L24,0) -> 2411 | N25: 601188 | O25: =IF(N25>=N24,N25-N24,0) -> 1662 | P25: 222080 | Q25: =IF(P25>=P24,P25-P24,0)*30 -> 570 | R25: 185115 | S25: =IF(R25>=R24,R25-R24,0) -> 133 | T25: 338329 | U25: =IF(T25>=T24,T25-T24,0) -> 244 | V25: 839195 | W25: =IF(V25>=V24,V25-V24,0)*0.53 -> 1395.49 | X25: 121075 | Y25: =IF(X25>=X24,X25-X24,0)*0.53 -> 0 | Z25: 134801 | AA25: =IF(Z25>=Z24,Z25-Z24,0)*0.53 -> 0 | AB25: 488405 | AC25: =IF(AB25>=AB24,AB25-AB24,0)*0.53 -> 0 | AD25: 657469 | AE25: =IF(AD25>=AD24,AD25-AD24,0)*0.53 -> 0 | AF25: 836146 | AG25: =IF(AF25>=AF24,AF25-AF24,0)*0.53 -> 15.37 | AH25: 3134 | AI25: =IF(AH25>=AH24,AH25-AH24,0)*0.53 -> 391.14 | AJ25: 828434 | AK25: =IF(AJ25>=AJ24,AJ25-AJ24,0)*0.53 -> 2003.93 | AL25: 498919 | AM25: =IF(AL25>=AL24,AL25-AL24,0)*0.53 -> 157.94 | AN25: =W25+Y25+AA25+AC25+AE25+AG25+AI25+AK25+AM25 -> 3963.87 | AO25: 7655023 | AP25: =IF(AO25>=AO24,AO25-AO24,0)*0.1125 -> 18.45 | AQ25: 684060 | AR25: =IF(AQ25>=AQ24,AQ25-AQ24,0) -> 319 | AS25: 969028 | AT25: =IF(AS25>=AS24,AS25-AS24,0) -> 141 | AU25: 811036 | AV25: =IF(AU25>=AU24,AU25-AU24,0) -> 42 | AW25: 2632406 | AX25: =IF(AW25>=AW24,AW25-AW24,0) -> 572 | AY25: 229671 | AZ25: =IF(AY25>=AY24,AY25-AY24,0) -> 6 | BA25: 19382645 | BB25: =IF(BA25>=BA24,BA25-BA24,0) -> 4408 | BC25: 571885 | BD25: =IF(BC25>=BC24,BC25-BC24,0) -> 232 | BE25: 27830 | BF25: =IF(BE25>=BE24,BE25-BE24,0) -> 54 | BG25: 24237980 | BH25: =IF(BG25>=BG24,BG25-BG24,0)-(0.45*BN25)-(0.45*BP25)-BR25 -> 4589.7 | BI25: =AP25+AR25+AT25+AV25+AX25+AZ25+BB25+BD25+BF25+BH25 -> 10382.15 | BJ25: =BI25+AN25 -> 14346.02 | BK25: 1428493 | BL25: =IF(BK25>=BK24,BK25-BK24,0) -> 257 | BM25: 3949234 | BN25: =IF(BM25>=BM24,BM25-BM24,0) -> 615 | BO25: 416322 | BP25: =IF(BO25>=BO24,BO25-BO24,0) -> 119 | BQ25: 520611 | BR25: =IF(BQ25>=BQ24,BQ25-BQ24,0) -> 121 | BS25: =J25+Q25+AN25+BI25 -> 21357.02 | BT25: 248 | BU25: =IF(BS25>0,BS25/BT25,0) -> 86.117016 | BW25: =IF(BS25>0,BS25/BV25,0) -> #DIV/0! | BX25: =((BS25-Q25)*$BZ$1)+(Q25*$BR$1) -> 24817.073 | BY25: =IF(BX25>0,BX25/BT25,0) -> 100.06884 | BZ25: =IF(BX25>0,BX25/BV25,0) -> #DIV/0!
A26: 21 | C26: =IF(+B26-B25>0,B26-B25,(B26-B25)>0)*800 -> 0 | E26: =IF(+D26-D25>0,D26-D25,(D26-D25)>0)*80 -> 0 | G26: =IF(+F26-F25>0,F26-F25,(F26-F25)>0)*10 -> 0 | H26: 66 | I26: 24078324 | J26: =IF(I26>=I25,I26-I25,0) -> 6377 | K26: =M26+O26 -> 4186 | L26: 738110 | M26: =IF(L26>=L25,L26-L25,0) -> 2375 | N26: 602999 | O26: =IF(N26>=N25,N26-N25,0) -> 1811 | P26: 222100 | Q26: =IF(P26>=P25,P26-P25,0)*30 -> 600 | R26: 185268 | S26: =IF(R26>=R25,R26-R25,0) -> 153 | T26: 338618 | U26: =IF(T26>=T25,T26-T25,0) -> 289 | V26: 842488 | W26: =IF(V26>=V25,V26-V25,0)*0.53 -> 1745.29 | X26: 121075 | Y26: =IF(X26>=X25,X26-X25,0)*0.53 -> 0 | Z26: 134801 | AA26: =IF(Z26>=Z25,Z26-Z25,0)*0.53 -> 0 | AB26: 488405 | AC26: =IF(AB26>=AB25,AB26-AB25,0)*0.53 -> 0 | AD26: 657469 | AE26: =IF(AD26>=AD25,AD26-AD25,0)*0.53 -> 0 | AF26: 836163 | AG26: =IF(AF26>=AF25,AF26-AF25,0)*0.53 -> 9.01 | AH26: 3955 | AI26: =IF(AH26>=AH25,AH26-AH25,0)*0.53 -> 435.13 | AJ26: 832717 | AK26: =IF(AJ26>=AJ25,AJ26-AJ25,0)*0.53 -> 2269.99 | AL26: 499235 | AM26: =IF(AL26>=AL25,AL26-AL25,0)*0.53 -> 167.48 | AN26: =W26+Y26+AA26+AC26+AE26+AG26+AI26+AK26+AM26 -> 4626.9 | AO26: 7655376 | AP26: =IF(AO26>=AO25,AO26-AO25,0)*0.1125 -> 39.7125 | AQ26: 684380 | AR26: =IF(AQ26>=AQ25,AQ26-AQ25,0) -> 320 | AS26: 969176 | AT26: =IF(AS26>=AS25,AS26-AS25,0) -> 148 | AU26: 811086 | AV26: =IF(AU26>=AU25,AU26-AU25,0) -> 50 | AW26: 2633055 | AX26: =IF(AW26>=AW25,AW26-AW25,0) -> 649 | AY26: 229677 | AZ26: =IF(AY26>=AY25,AY26-AY25,0) -> 6 | BA26: 19386653 | BB26: =IF(BA26>=BA25,BA26-BA25,0) -> 4008 | BC26: 572147 | BD26: =IF(BC26>=BC25,BC26-BC25,0) -> 262 | BE26: 27884 | BF26: =IF(BE26>=BE25,BE26-BE25,0) -> 54 | BG26: 24243511 | BH26: =IF(BG26>=BG25,BG26-BG25,0)-(0.45*BN26)-(0.45*BP26)-BR26 -> 4992.7 | BI26: =AP26+AR26+AT26+AV26+AX26+AZ26+BB26+BD26+BF26+BH26 -> 10529.412 | BJ26: =BI26+AN26 -> 15156.312 | BK26: 1428569 | BL26: =IF(BK26>=BK25,BK26-BK25,0) -> 76 | BM26: 3949999 | BN26: =IF(BM26>=BM25,BM26-BM25,0) -> 765 | BO26: 416451 | BP26: =IF(BO26>=BO25,BO26-BO25,0) -> 129 | BQ26: 520747 | BR26: =IF(BQ26>=BQ25,BQ26-BQ25,0) -> 136 | BS26: =J26+Q26+AN26+BI26 -> 22133.312 | BT26: 246 | BU26: =IF(BS26>0,BS26/BT26,0) -> 89.972815 | BW26: =IF(BS26>0,BS26/BV26,0) -> #DIV/0! | BX26: =((BS26-Q26)*$BZ$1)+(Q26*$BR$1) -> 25723.309 | BY26: =IF(BX26>0,BX26/BT26,0) -> 104.5663 | BZ26: =IF(BX26>0,BX26/BV26,0) -> #DIV/0!
A27: 22 | C27: =IF(+B27-B26>0,B27-B26,(B27-B26)>0)*800 -> 0 | E27: =IF(+D27-D26>0,D27-D26,(D27-D26)>0)*80 -> 0 | G27: =IF(+F27-F26>0,F27-F26,(F27-F26)>0)*10 -> 0 | I27: 24084099 | J27: =IF(I27>=I26,I27-I26,0) -> 5775 | K27: =M27+O27 -> 3428 | L27: 740090 | M27: =IF(L27>=L26,L27-L26,0) -> 1980 | N27: 604447 | O27: =IF(N27>=N26,N27-N26,0) -> 1448 | P27: 222120 | Q27: =IF(P27>=P26,P27-P26,0)*30 -> 600 | R27: 185396 | S27: =IF(R27>=R26,R27-R26,0) -> 128 | T27: 338907 | U27: =IF(T27>=T26,T27-T26,0) -> 289 | V27: 845492 | W27: =IF(V27>=V26,V27-V26,0)*0.53 -> 1592.12 | X27: 121075 | Y27: =IF(X27>=X26,X27-X26,0)*0.53 -> 0 | Z27: 134801 | AA27: =IF(Z27>=Z26,Z27-Z26,0)*0.53 -> 0 | AB27: 488405 | AC27: =IF(AB27>=AB26,AB27-AB26,0)*0.53 -> 0 | AD27: 1562 | AE27: =IF(AD27>=AD26,AD27-AD26,0)*0.53 -> 0 | AF27: 836185 | AG27: =IF(AF27>=AF26,AF27-AF26,0)*0.53 -> 11.66 | AH27: 4635 | AI27: =IF(AH27>=AH26,AH27-AH26,0)*0.53 -> 360.4 | AJ27: 836140 | AK27: =IF(AJ27>=AJ26,AJ27-AJ26,0)*0.53 -> 1814.19 | AL27: 499498 | AM27: =IF(AL27>=AL26,AL27-AL26,0)*0.53 -> 139.39 | AN27: =W27+Y27+AA27+AC27+AE27+AG27+AI27+AK27+AM27 -> 3917.76 | AO27: 7655703 | AP27: =IF(AO27>=AO26,AO27-AO26,0)*0.1125 -> 36.7875 | AQ27: 684699 | AR27: =IF(AQ27>=AQ26,AQ27-AQ26,0) -> 319 | AS27: 969328 | AT27: =IF(AS27>=AS26,AS27-AS26,0) -> 152 | AU27: 811130 | AV27: =IF(AU27>=AU26,AU27-AU26,0) -> 44 | AW27: 2633664 | AX27: =IF(AW27>=AW26,AW27-AW26,0) -> 609 | AY27: 229683 | AZ27: =IF(AY27>=AY26,AY27-AY26,0) -> 6 | BA27: 19390645 | BB27: =IF(BA27>=BA26,BA27-BA26,0) -> 3992 | BC27: 572385 | BD27: =IF(BC27>=BC26,BC27-BC26,0) -> 238 | BE27: 27938 | BF27: =IF(BE27>=BE26,BE27-BE26,0) -> 54 | BG27: 24248879 | BH27: =IF(BG27>=BG26,BG27-BG26,0)-(0.45*BN27)-(0.45*BP27)-BR27 -> 4771.45 | BI27: =AP27+AR27+AT27+AV27+AX27+AZ27+BB27+BD27+BF27+BH27 -> 10222.237 | BJ27: =BI27+AN27 -> 14139.997 | BK27: 1428630 | BL27: =IF(BK27>=BK26,BK27-BK26,0) -> 61 | BM27: 3950919 | BN27: =IF(BM27>=BM26,BM27-BM26,0) -> 920 | BO27: 416570 | BP27: =IF(BO27>=BO26,BO27-BO26,0) -> 119 | BQ27: 520876 | BR27: =IF(BQ27>=BQ26,BQ27-BQ26,0) -> 129 | BS27: =J27+Q27+AN27+BI27 -> 20514.997 | BT27: 246 | BU27: =IF(BS27>0,BS27/BT27,0) -> 83.394299 | BW27: =IF(BS27>0,BS27/BV27,0) -> #DIV/0! | BX27: =((BS27-Q27)*$BZ$1)+(Q27*$BR$1) -> 23862.247 | BY27: =IF(BX27>0,BX27/BT27,0) -> 97.001005 | BZ27: =IF(BX27>0,BX27/BV27,0) -> #DIV/0!
A28: 23 | C28: =IF(+B28-B27>0,B28-B27,(B28-B27)>0)*800 -> 0 | E28: =IF(+D28-D27>0,D28-D27,(D28-D27)>0)*80 -> 0 | G28: =IF(+F28-F27>0,F28-F27,(F28-F27)>0)*10 -> 0 | H28: 67 | I28: 24089977 | J28: =IF(I28>=I27,I28-I27,0) -> 5878 | K28: =M28+O28 -> 3653 | L28: 742085 | M28: =IF(L28>=L27,L28-L27,0) -> 1995 | N28: 606105 | O28: =IF(N28>=N27,N28-N27,0) -> 1658 | P28: 222140 | Q28: =IF(P28>=P27,P28-P27,0)*30 -> 600 | R28: 185534 | S28: =IF(R28>=R27,R28-R27,0) -> 138 | T28: 339127 | U28: =IF(T28>=T27,T28-T27,0) -> 220 | V28: 848671 | W28: =IF(V28>=V27,V28-V27,0)*0.53 -> 1684.87 | X28: 121075 | Y28: =IF(X28>=X27,X28-X27,0)*0.53 -> 0 | Z28: 134801 | AA28: =IF(Z28>=Z27,Z28-Z27,0)*0.53 -> 0 | AB28: 488405 | AC28: =IF(AB28>=AB27,AB28-AB27,0)*0.53 -> 0 | AD28: 1562 | AE28: =IF(AD28>=AD27,AD28-AD27,0)*0.53 -> 0 | AF28: 836207 | AG28: =IF(AF28>=AF27,AF28-AF27,0)*0.53 -> 11.66 | AH28: 5366 | AI28: =IF(AH28>=AH27,AH28-AH27,0)*0.53 -> 387.43 | AJ28: 839796 | AK28: =IF(AJ28>=AJ27,AJ28-AJ27,0)*0.53 -> 1937.68 | AL28: 499784 | AM28: =IF(AL28>=AL27,AL28-AL27,0)*0.53 -> 151.58 | AN28: =W28+Y28+AA28+AC28+AE28+AG28+AI28+AK28+AM28 -> 4173.22 | AO28: 7656125 | AP28: =IF(AO28>=AO27,AO28-AO27,0)*0.1125 -> 47.475 | AQ28: 685027 | AR28: =IF(AQ28>=AQ27,AQ28-AQ27,0) -> 328 | AS28: 969480 | AT28: =IF(AS28>=AS27,AS28-AS27,0) -> 152 | AU28: 811177 | AV28: =IF(AU28>=AU27,AU28-AU27,0) -> 47 | AW28: 2634310 | AX28: =IF(AW28>=AW27,AW28-AW27,0) -> 646 | AY28: 229688 | AZ28: =IF(AY28>=AY27,AY28-AY27,0) -> 5 | BA28: 19394787 | BB28: =IF(BA28>=BA27,BA28-BA27,0) -> 4142 | BC28: 572598 | BD28: =IF(BC28>=BC27,BC28-BC27,0) -> 213 | BE28: 27992 | BF28: =IF(BE28>=BE27,BE28-BE27,0) -> 54 | BG28: 24254429 | BH28: =IF(BG28>=BG27,BG28-BG27,0)-(0.45*BN28)-(0.45*BP28)-BR28 -> 4908 | BI28: =AP28+AR28+AT28+AV28+AX28+AZ28+BB28+BD28+BF28+BH28 -> 10542.475 | BJ28: =BI28+AN28 -> 14715.695 | BK28: 1428835 | BL28: =IF(BK28>=BK27,BK28-BK27,0) -> 205 | BM28: 3951881 | BN28: =IF(BM28>=BM27,BM28-BM27,0) -> 962 | BO28: 416688 | BP28: =IF(BO28>=BO27,BO28-BO27,0) -> 118 | BQ28: 521032 | BR28: =IF(BQ28>=BQ27,BQ28-BQ27,0) -> 156 | BS28: =J28+Q28+AN28+BI28 -> 21193.695 | BT28: 250 | BU28: =IF(BS28>0,BS28/BT28,0) -> 84.77478 | BW28: =IF(BS28>0,BS28/BV28,0) -> #DIV/0! | BX28: =((BS28-Q28)*$BZ$1)+(Q28*$BR$1) -> 24642.749 | BY28: =IF(BX28>0,BX28/BT28,0) -> 98.570997 | BZ28: =IF(BX28>0,BX28/BV28,0) -> #DIV/0!
A29: 24 | C29: =IF(+B29-B28>0,B29-B28,(B29-B28)>0)*800 -> 0 | E29: =IF(+D29-D28>0,D29-D28,(D29-D28)>0)*80 -> 0 | G29: =IF(+F29-F28>0,F29-F28,(F29-F28)>0)*10 -> 0 | I29: 24096517 | J29: =IF(I29>=I28,I29-I28,0) -> 6540 | K29: =M29+O29 -> 4051 | L29: 744382 | M29: =IF(L29>=L28,L29-L28,0) -> 2297 | N29: 607859 | O29: =IF(N29>=N28,N29-N28,0) -> 1754 | P29: 222160 | Q29: =IF(P29>=P28,P29-P28,0)*30 -> 600 | R29: 185684 | S29: =IF(R29>=R28,R29-R28,0) -> 150 | T29: 339405 | U29: =IF(T29>=T28,T29-T28,0) -> 278 | V29: 851594 | W29: =IF(V29>=V28,V29-V28,0)*0.53 -> 1549.19 | X29: 121075 | Y29: =IF(X29>=X28,X29-X28,0)*0.53 -> 0 | Z29: 134801 | AA29: =IF(Z29>=Z28,Z29-Z28,0)*0.53 -> 0 | AB29: 488405 | AC29: =IF(AB29>=AB28,AB29-AB28,0)*0.53 -> 0 | AD29: 1562 | AE29: =IF(AD29>=AD28,AD29-AD28,0)*0.53 -> 0 | AF29: 836232 | AG29: =IF(AF29>=AF28,AF29-AF28,0)*0.53 -> 13.25 | AH29: 6171 | AI29: =IF(AH29>=AH28,AH29-AH28,0)*0.53 -> 426.65 | AJ29: 843731 | AK29: =IF(AJ29>=AJ28,AJ29-AJ28,0)*0.53 -> 2085.55 | AL29: 500089 | AM29: =IF(AL29>=AL28,AL29-AL28,0)*0.53 -> 161.65 | AN29: =W29+Y29+AA29+AC29+AE29+AG29+AI29+AK29+AM29 -> 4236.29 | AO29: 7656179 | AP29: =IF(AO29>=AO28,AO29-AO28,0)*0.1125 -> 6.075 | AQ29: 685414 | AR29: =IF(AQ29>=AQ28,AQ29-AQ28,0) -> 387 | AS29: 969626 | AT29: =IF(AS29>=AS28,AS29-AS28,0) -> 146 | AU29: 811226 | AV29: =IF(AU29>=AU28,AU29-AU28,0) -> 49 | AW29: 2634966 | AX29: =IF(AW29>=AW28,AW29-AW28,0) -> 656 | AY29: 229695 | AZ29: =IF(AY29>=AY28,AY29-AY28,0) -> 7 | BA29: 19399371 | BB29: =IF(BA29>=BA28,BA29-BA28,0) -> 4584 | BC29: 572832 | BD29: =IF(BC29>=BC28,BC29-BC28,0) -> 234 | BE29: 28046 | BF29: =IF(BE29>=BE28,BE29-BE28,0) -> 54 | BG29: 24260629 | BH29: =IF(BG29>=BG28,BG29-BG28,0)-(0.45*BN29)-(0.45*BP29)-BR29 -> 5515.4 | BI29: =AP29+AR29+AT29+AV29+AX29+AZ29+BB29+BD29+BF29+BH29 -> 11638.475 | BJ29: =BI29+AN29 -> 15874.765 | BK29: 1429096 | BL29: =IF(BK29>=BK28,BK29-BK28,0) -> 261 | BM29: 3952893 | BN29: =IF(BM29>=BM28,BM29-BM28,0) -> 1012 | BO29: 416824 | BP29: =IF(BO29>=BO28,BO29-BO28,0) -> 136 | BQ29: 521200 | BR29: =IF(BQ29>=BQ28,BQ29-BQ28,0) -> 168 | BS29: =J29+Q29+AN29+BI29 -> 23014.765 | BT29: 247 | BU29: =IF(BS29>0,BS29/BT29,0) -> 93.177186 | BW29: =IF(BS29>0,BS29/BV29,0) -> #DIV/0! | BX29: =((BS29-Q29)*$BZ$1)+(Q29*$BR$1) -> 26736.98 | BY29: =IF(BX29>0,BX29/BT29,0) -> 108.24688 | BZ29: =IF(BX29>0,BX29/BV29,0) -> #DIV/0!
A30: 25 | C30: =IF(+B30-B29>0,B30-B29,(B30-B29)>0)*800 -> 0 | E30: =IF(+D30-D29>0,D30-D29,(D30-D29)>0)*80 -> 0 | G30: =IF(+F30-F29>0,F30-F29,(F30-F29)>0)*10 -> 0 | H30: 68 | I30: 24102492 | J30: =IF(I30>=I29,I30-I29,0) -> 5975 | K30: =M30+O30 -> 3797 | L30: 746585 | M30: =IF(L30>=L29,L30-L29,0) -> 2203 | N30: 609453 | O30: =IF(N30>=N29,N30-N29,0) -> 1594 | P30: 222171 | Q30: =IF(P30>=P29,P30-P29,0)*30 -> 330 | R30: 185820 | S30: =IF(R30>=R29,R30-R29,0) -> 136 | T30: 339653 | U30: =IF(T30>=T29,T30-T29,0) -> 248 | V30: 854312 | W30: =IF(V30>=V29,V30-V29,0)*0.53 -> 1440.54 | X30: 121075 | Y30: =IF(X30>=X29,X30-X29,0)*0.53 -> 0 | Z30: 134801 | AA30: =IF(Z30>=Z29,Z30-Z29,0)*0.53 -> 0 | AB30: 488405 | AC30: =IF(AB30>=AB29,AB30-AB29,0)*0.53 -> 0 | AD30: 1562 | AE30: =IF(AD30>=AD29,AD30-AD29,0)*0.53 -> 0 | AF30: 836255 | AG30: =IF(AF30>=AF29,AF30-AF29,0)*0.53 -> 12.19 | AH30: 6910 | AI30: =IF(AH30>=AH29,AH30-AH29,0)*0.53 -> 391.67 | AJ30: 847613 | AK30: =IF(AJ30>=AJ29,AJ30-AJ29,0)*0.53 -> 2057.46 | AL30: 500369 | AM30: =IF(AL30>=AL29,AL30-AL29,0)*0.53 -> 148.4 | AN30: =W30+Y30+AA30+AC30+AE30+AG30+AI30+AK30+AM30 -> 4050.26 | AO30: 7656218 | AP30: =IF(AO30>=AO29,AO30-AO29,0)*0.1125 -> 4.3875 | AQ30: 685729 | AR30: =IF(AQ30>=AQ29,AQ30-AQ29,0) -> 315 | AS30: 969761 | AT30: =IF(AS30>=AS29,AS30-AS29,0) -> 135 | AU30: 811263 | AV30: =IF(AU30>=AU29,AU30-AU29,0) -> 37 | AW30: 2635544 | AX30: =IF(AW30>=AW29,AW30-AW29,0) -> 578 | AY30: 229700 | AZ30: =IF(AY30>=AY29,AY30-AY29,0) -> 5 | BA30: 19404180 | BB30: =IF(BA30>=BA29,BA30-BA29,0) -> 4809 | BC30: 573026 | BD30: =IF(BC30>=BC29,BC30-BC29,0) -> 194 | BE30: 28100 | BF30: =IF(BE30>=BE29,BE30-BE29,0) -> 54 | BG30: 24265957 | BH30: =IF(BG30>=BG29,BG30-BG29,0)-(0.45*BN30)-(0.45*BP30)-BR30 -> 4735.15 | BI30: =AP30+AR30+AT30+AV30+AX30+AZ30+BB30+BD30+BF30+BH30 -> 10866.537 | BJ30: =BI30+AN30 -> 14916.797 | BK30: 1429342 | BL30: =IF(BK30>=BK29,BK30-BK29,0) -> 246 | BM30: 3953766 | BN30: =IF(BM30>=BM29,BM30-BM29,0) -> 873 | BO30: 416944 | BP30: =IF(BO30>=BO29,BO30-BO29,0) -> 120 | BQ30: 521346 | BR30: =IF(BQ30>=BQ29,BQ30-BQ29,0) -> 146 | BS30: =J30+Q30+AN30+BI30 -> 21221.798 | BT30: 253 | BU30: =IF(BS30>0,BS30/BT30,0) -> 83.880623 | BW30: =IF(BS30>0,BS30/BV30,0) -> #DIV/0! | BX30: =((BS30-Q30)*$BZ$1)+(Q30*$BR$1) -> 24553.567 | BY30: =IF(BX30>0,BX30/BT30,0) -> 97.049672 | BZ30: =IF(BX30>0,BX30/BV30,0) -> #DIV/0!
A31: 26 | C31: =IF(+B31-B30>0,B31-B30,(B31-B30)>0)*800 -> 0 | E31: =IF(+D31-D30>0,D31-D30,(D31-D30)>0)*80 -> 0 | G31: =IF(+F31-F30>0,F31-F30,(F31-F30)>0)*10 -> 0 | I31: 24108531 | J31: =IF(I31>=I30,I31-I30,0) -> 6039 | K31: =M31+O31 -> 3809 | L31: 748704 | M31: =IF(L31>=L30,L31-L30,0) -> 2119 | N31: 611143 | O31: =IF(N31>=N30,N31-N30,0) -> 1690 | P31: 222190 | Q31: =IF(P31>=P30,P31-P30,0)*30 -> 570 | R31: 185961 | S31: =IF(R31>=R30,R31-R30,0) -> 141 | T31: 339921 | U31: =IF(T31>=T30,T31-T30,0) -> 268 | V31: 857700 | W31: =IF(V31>=V30,V31-V30,0)*0.53 -> 1795.64 | X31: 121075 | Y31: =IF(X31>=X30,X31-X30,0)*0.53 -> 0 | Z31: 134801 | AA31: =IF(Z31>=Z30,Z31-Z30,0)*0.53 -> 0 | AB31: 488405 | AC31: =IF(AB31>=AB30,AB31-AB30,0)*0.53 -> 0 | AD31: 1562 | AE31: =IF(AD31>=AD30,AD31-AD30,0)*0.53 -> 0 | AF31: 836284 | AG31: =IF(AF31>=AF30,AF31-AF30,0)*0.53 -> 15.37 | AH31: 7603 | AI31: =IF(AH31>=AH30,AH31-AH30,0)*0.53 -> 367.29 | AJ31: 850944 | AK31: =IF(AJ31>=AJ30,AJ31-AJ30,0)*0.53 -> 1765.43 | AL31: 500728 | AM31: =IF(AL31>=AL30,AL31-AL30,0)*0.53 -> 190.27 | AN31: =W31+Y31+AA31+AC31+AE31+AG31+AI31+AK31+AM31 -> 4134 | AO31: 7656364 | AP31: =IF(AO31>=AO30,AO31-AO30,0)*0.1125 -> 16.425 | AQ31: 686062 | AR31: =IF(AQ31>=AQ30,AQ31-AQ30,0) -> 333 | AS31: 969906 | AT31: =IF(AS31>=AS30,AS31-AS30,0) -> 145 | AU31: 811306 | AV31: =IF(AU31>=AU30,AU31-AU30,0) -> 43 | AW31: 2636153 | AX31: =IF(AW31>=AW30,AW31-AW30,0) -> 609 | AY31: 229706 | AZ31: =IF(AY31>=AY30,AY31-AY30,0) -> 6 | BA31: 19409109 | BB31: =IF(BA31>=BA30,BA31-BA30,0) -> 4929 | BC31: 573262 | BD31: =IF(BC31>=BC30,BC31-BC30,0) -> 236 | BE31: 28154 | BF31: =IF(BE31>=BE30,BE31-BE30,0) -> 54 | BG31: 24271576 | BH31: =IF(BG31>=BG30,BG31-BG30,0)-(0.45*BN31)-(0.45*BP31)-BR31 -> 5085.8 | BI31: =AP31+AR31+AT31+AV31+AX31+AZ31+BB31+BD31+BF31+BH31 -> 11457.225 | BJ31: =BI31+AN31 -> 15591.225 | BK31: 1429601 | BL31: =IF(BK31>=BK30,BK31-BK30,0) -> 259 | BM31: 3954473 | BN31: =IF(BM31>=BM30,BM31-BM30,0) -> 707 | BO31: 417073 | BP31: =IF(BO31>=BO30,BO31-BO30,0) -> 129 | BQ31: 521503 | BR31: =IF(BQ31>=BQ30,BQ31-BQ30,0) -> 157 | BS31: =J31+Q31+AN31+BI31 -> 22200.225 | BT31: 257 | BU31: =IF(BS31>0,BS31/BT31,0) -> 86.382198 | BW31: =IF(BS31>0,BS31/BV31,0) -> #DIV/0! | BX31: =((BS31-Q31)*$BZ$1)+(Q31*$BR$1) -> 25786.759 | BY31: =IF(BX31>0,BX31/BT31,0) -> 100.33758 | BZ31: =IF(BX31>0,BX31/BV31,0) -> #DIV/0!
A32: 27 | C32: =IF(+B32-B31>0,B32-B31,(B32-B31)>0)*800 -> 0 | E32: =IF(+D32-D31>0,D32-D31,(D32-D31)>0)*80 -> 0 | G32: =IF(+F32-F31>0,F32-F31,(F32-F31)>0)*10 -> 0 | H32: 69 | I32: 24114625 | J32: =IF(I32>=I31,I32-I31,0) -> 6094 | K32: =M32+O32 -> 3809 | L32: 750978 | M32: =IF(L32>=L31,L32-L31,0) -> 2274 | N32: 612678 | O32: =IF(N32>=N31,N32-N31,0) -> 1535 | P32: 222211 | Q32: =IF(P32>=P31,P32-P31,0)*30 -> 630 | R32: 186100 | S32: =IF(R32>=R31,R32-R31,0) -> 139 | T32: 340187 | U32: =IF(T32>=T31,T32-T31,0) -> 266 | V32: 860880 | W32: =IF(V32>=V31,V32-V31,0)*0.53 -> 1685.4 | X32: 121144 | Y32: =IF(X32>=X31,X32-X31,0)*0.53 -> 36.57 | Z32: 134875 | AA32: =IF(Z32>=Z31,Z32-Z31,0)*0.53 -> 39.22 | AB32: 488524 | AC32: =IF(AB32>=AB31,AB32-AB31,0)*0.53 -> 63.07 | AD32: 1562 | AE32: =IF(AD32>=AD31,AD32-AD31,0)*0.53 -> 0 | AF32: 836301 | AG32: =IF(AF32>=AF31,AF32-AF31,0)*0.53 -> 9.01 | AH32: 8334 | AI32: =IF(AH32>=AH31,AH32-AH31,0)*0.53 -> 387.43 | AJ32: 854605 | AK32: =IF(AJ32>=AJ31,AJ32-AJ31,0)*0.53 -> 1940.33 | AL32: 500943 | AM32: =IF(AL32>=AL31,AL32-AL31,0)*0.53 -> 113.95 | AN32: =W32+Y32+AA32+AC32+AE32+AG32+AI32+AK32+AM32 -> 4274.98 | AO32: 7656783 | AP32: =IF(AO32>=AO31,AO32-AO31,0)*0.1125 -> 47.1375 | AQ32: 686393 | AR32: =IF(AQ32>=AQ31,AQ32-AQ31,0) -> 331 | AS32: 970059 | AT32: =IF(AS32>=AS31,AS32-AS31,0) -> 153 | AU32: 811351 | AV32: =IF(AU32>=AU31,AU32-AU31,0) -> 45 | AW32: 2636751 | AX32: =IF(AW32>=AW31,AW32-AW31,0) -> 598 | AY32: 229712 | AZ32: =IF(AY32>=AY31,AY32-AY31,0) -> 6 | BA32: 19413829 | BB32: =IF(BA32>=BA31,BA32-BA31,0) -> 4720 | BC32: 573501 | BD32: =IF(BC32>=BC31,BC32-BC31,0) -> 239 | BE32: 28208 | BF32: =IF(BE32>=BE31,BE32-BE31,0) -> 54 | BG32: 24277524 | BH32: =IF(BG32>=BG31,BG32-BG31,0)-(0.45*BN32)-(0.45*BP32)-BR32 -> 5314.4 | BI32: =AP32+AR32+AT32+AV32+AX32+AZ32+BB32+BD32+BF32+BH32 -> 11507.538 | BJ32: =BI32+AN32 -> 15782.517 | BK32: 1429855 | BL32: =IF(BK32>=BK31,BK32-BK31,0) -> 254 | BM32: 3955414 | BN32: =IF(BM32>=BM31,BM32-BM31,0) -> 941 | BO32: 417200 | BP32: =IF(BO32>=BO31,BO32-BO31,0) -> 127 | BQ32: 521656 | BR32: =IF(BQ32>=BQ31,BQ32-BQ31,0) -> 153 | BS32: =J32+Q32+AN32+BI32 -> 22506.518 | BT32: 229 | BU32: =IF(BS32>0,BS32/BT32,0) -> 98.281736 | BW32: =IF(BS32>0,BS32/BV32,0) -> #DIV/0! | BX32: =((BS32-Q32)*$BZ$1)+(Q32*$BR$1) -> 26165.995 | BY32: =IF(BX32>0,BX32/BT32,0) -> 114.26199 | BZ32: =IF(BX32>0,BX32/BV32,0) -> #DIV/0!
A33: 28 | C33: =IF(+B33-B32>0,B33-B32,(B33-B32)>0)*800 -> 0 | E33: =IF(+D33-D32>0,D33-D32,(D33-D32)>0)*80 -> 0 | G33: =IF(+F33-F32>0,F33-F32,(F33-F32)>0)*10 -> 0 | I33: 24120719 | J33: =IF(I33>=I32,I33-I32,0) -> 6094 | K33: =M33+O33 -> 3809 | L33: 753252 | M33: =IF(L33>=L32,L33-L32,0) -> 2274 | N33: 614213 | O33: =IF(N33>=N32,N33-N32,0) -> 1535 | P33: 222231 | Q33: =IF(P33>=P32,P33-P32,0)*30 -> 600 | R33: 186239 | S33: =IF(R33>=R32,R33-R32,0) -> 139 | T33: 340453 | U33: =IF(T33>=T32,T33-T32,0) -> 266 | V33: 864060 | W33: =IF(V33>=V32,V33-V32,0)*0.53 -> 1685.4 | X33: 121213 | Y33: =IF(X33>=X32,X33-X32,0)*0.53 -> 36.57 | Z33: 134949 | AA33: =IF(Z33>=Z32,Z33-Z32,0)*0.53 -> 39.22 | AB33: 488643 | AC33: =IF(AB33>=AB32,AB33-AB32,0)*0.53 -> 63.07 | AD33: 1562 | AE33: =IF(AD33>=AD32,AD33-AD32,0)*0.53 -> 0 | AF33: 836318 | AG33: =IF(AF33>=AF32,AF33-AF32,0)*0.53 -> 9.01 | AH33: 9065 | AI33: =IF(AH33>=AH32,AH33-AH32,0)*0.53 -> 387.43 | AJ33: 858266 | AK33: =IF(AJ33>=AJ32,AJ33-AJ32,0)*0.53 -> 1940.33 | AL33: 501158 | AM33: =IF(AL33>=AL32,AL33-AL32,0)*0.53 -> 113.95 | AN33: =W33+Y33+AA33+AC33+AE33+AG33+AI33+AK33+AM33 -> 4274.98 | AO33: 7657202 | AP33: =IF(AO33>=AO32,AO33-AO32,0)*0.1125 -> 47.1375 | AQ33: 686724 | AR33: =IF(AQ33>=AQ32,AQ33-AQ32,0) -> 331 | AS33: 970212 | AT33: =IF(AS33>=AS32,AS33-AS32,0) -> 153 | AU33: 811396 | AV33: =IF(AU33>=AU32,AU33-AU32,0) -> 45 | AW33: 2637349 | AX33: =IF(AW33>=AW32,AW33-AW32,0) -> 598 | AY33: 229718 | AZ33: =IF(AY33>=AY32,AY33-AY32,0) -> 6 | BA33: 19418549 | BB33: =IF(BA33>=BA32,BA33-BA32,0) -> 4720 | BC33: 573740 | BD33: =IF(BC33>=BC32,BC33-BC32,0) -> 239 | BE33: 28262 | BF33: =IF(BE33>=BE32,BE33-BE32,0) -> 54 | BG33: 24283472 | BH33: =IF(BG33>=BG32,BG33-BG32,0)-(0.45*BN33)-(0.45*BP33)-BR33 -> 5314.4 | BI33: =AP33+AR33+AT33+AV33+AX33+AZ33+BB33+BD33+BF33+BH33 -> 11507.538 | BJ33: =BI33+AN33 -> 15782.517 | BK33: 1430109 | BL33: =IF(BK33>=BK32,BK33-BK32,0) -> 254 | BM33: 3956355 | BN33: =IF(BM33>=BM32,BM33-BM32,0) -> 941 | BO33: 417327 | BP33: =IF(BO33>=BO32,BO33-BO32,0) -> 127 | BQ33: 521809 | BR33: =IF(BQ33>=BQ32,BQ33-BQ32,0) -> 153 | BS33: =J33+Q33+AN33+BI33 -> 22476.518 | BT33: 236 | BU33: =IF(BS33>0,BS33/BT33,0) -> 95.239481 | BW33: =IF(BS33>0,BS33/BV33,0) -> #DIV/0! | BX33: =((BS33-Q33)*$BZ$1)+(Q33*$BR$1) -> 26117.995 | BY33: =IF(BX33>0,BX33/BT33,0) -> 110.66947 | BZ33: =IF(BX33>0,BX33/BV33,0) -> #DIV/0!
A34: 29 | C34: =IF(+B34-B33>0,B34-B33,(B34-B33)>0)*800 -> 0 | E34: =IF(+D34-D33>0,D34-D33,(D34-D33)>0)*80 -> 0 | G34: =IF(+F34-F33>0,F34-F33,(F34-F33)>0)*10 -> 0 | I34: 24120719 | J34: =IF(I34>=I33,I34-I33,0) -> 0 | K34: =M34+O34 -> 0 | L34: 753252 | M34: =IF(L34>=L33,L34-L33,0) -> 0 | N34: 614213 | O34: =IF(N34>=N33,N34-N33,0) -> 0 | P34: 222231 | Q34: =IF(P34>=P33,P34-P33,0)*30 -> 0 | R34: 186239 | S34: =IF(R34>=R33,R34-R33,0) -> 0 | T34: 340453 | U34: =IF(T34>=T33,T34-T33,0) -> 0 | V34: 864060 | W34: =IF(V34>=V33,V34-V33,0)*0.53 -> 0 | X34: 121213 | Y34: =IF(X34>=X33,X34-X33,0)*0.53 -> 0 | Z34: 134949 | AA34: =IF(Z34>=Z33,Z34-Z33,0)*0.53 -> 0 | AB34: 488643 | AC34: =IF(AB34>=AB33,AB34-AB33,0)*0.53 -> 0 | AD34: 1562 | AE34: =IF(AD34>=AD33,AD34-AD33,0)*0.53 -> 0 | AF34: 836318 | AG34: =IF(AF34>=AF33,AF34-AF33,0)*0.53 -> 0 | AH34: 9065 | AI34: =IF(AH34>=AH33,AH34-AH33,0)*0.53 -> 0 | AJ34: 858266 | AK34: =IF(AJ34>=AJ33,AJ34-AJ33,0)*0.53 -> 0 | AL34: 501158 | AM34: =IF(AL34>=AL33,AL34-AL33,0)*0.53 -> 0 | AN34: =W34+Y34+AA34+AC34+AE34+AG34+AI34+AK34+AM34 -> 0 | AO34: 7657202 | AP34: =IF(AO34>=AO33,AO34-AO33,0)*0.1125 -> 0 | AQ34: 686724 | AR34: =IF(AQ34>=AQ33,AQ34-AQ33,0) -> 0 | AS34: 970212 | AT34: =IF(AS34>=AS33,AS34-AS33,0) -> 0 | AU34: 811396 | AV34: =IF(AU34>=AU33,AU34-AU33,0) -> 0 | AW34: 2637349 | AX34: =IF(AW34>=AW33,AW34-AW33,0) -> 0 | AY34: 229718 | AZ34: =IF(AY34>=AY33,AY34-AY33,0) -> 0 | BA34: 19418549 | BB34: =IF(BA34>=BA33,BA34-BA33,0) -> 0 | BC34: 573740 | BD34: =IF(BC34>=BC33,BC34-BC33,0) -> 0 | BE34: 28262 | BF34: =IF(BE34>=BE33,BE34-BE33,0) -> 0 | BG34: 24283472 | BH34: =IF(BG34>=BG33,BG34-BG33,0)-(0.45*BN34)-(0.45*BP34)-BR34 -> 0 | BI34: =AP34+AR34+AT34+AV34+AX34+AZ34+BB34+BD34+BF34+BH34 -> 0 | BJ34: =BI34+AN34 -> 0 | BK34: 1430109 | BL34: =IF(BK34>=BK33,BK34-BK33,0) -> 0 | BM34: 3956355 | BN34: =IF(BM34>=BM33,BM34-BM33,0) -> 0 | BO34: 417327 | BP34: =IF(BO34>=BO33,BO34-BO33,0) -> 0 | BQ34: 521809 | BR34: =IF(BQ34>=BQ33,BQ34-BQ33,0) -> 0 | BS34: =J34+Q34+AN34+BI34 -> 0 | BU34: =IF(BS34>0,BS34/BT34,0) -> 0 | BW34: =IF(BS34>0,BS34/BV34,0) -> 0 | BX34: =((BS34-Q34)*$BZ$1)+(Q34*$BR$1) -> 0 | BY34: =IF(BX34>0,BX34/BT34,0) -> 0 | BZ34: =IF(BX34>0,BX34/BV34,0) -> 0
A35: 30 | C35: =IF(+B35-B34>0,B35-B34,(B35-B34)>0)*800 -> 0 | E35: =IF(+D35-D34>0,D35-D34,(D35-D34)>0)*80 -> 0 | G35: =IF(+F35-F34>0,F35-F34,(F35-F34)>0)*10 -> 0 | I35: 24120719 | J35: =IF(I35>=I34,I35-I34,0) -> 0 | K35: =M35+O35 -> 0 | L35: 753252 | M35: =IF(L35>=L34,L35-L34,0) -> 0 | N35: 614213 | O35: =IF(N35>=N34,N35-N34,0) -> 0 | P35: 222231 | Q35: =IF(P35>=P34,P35-P34,0)*30 -> 0 | R35: 186239 | S35: =IF(R35>=R34,R35-R34,0) -> 0 | T35: 340453 | U35: =IF(T35>=T34,T35-T34,0) -> 0 | V35: 864060 | W35: =IF(V35>=V34,V35-V34,0)*0.53 -> 0 | X35: 121213 | Y35: =IF(X35>=X34,X35-X34,0)*0.53 -> 0 | Z35: 134949 | AA35: =IF(Z35>=Z34,Z35-Z34,0)*0.53 -> 0 | AB35: 488643 | AC35: =IF(AB35>=AB34,AB35-AB34,0)*0.53 -> 0 | AD35: 1562 | AE35: =IF(AD35>=AD34,AD35-AD34,0)*0.53 -> 0 | AF35: 836318 | AG35: =IF(AF35>=AF34,AF35-AF34,0)*0.53 -> 0 | AH35: 9065 | AI35: =IF(AH35>=AH34,AH35-AH34,0)*0.53 -> 0 | AJ35: 858266 | AK35: =IF(AJ35>=AJ34,AJ35-AJ34,0)*0.53 -> 0 | AL35: 501158 | AM35: =IF(AL35>=AL34,AL35-AL34,0)*0.53 -> 0 | AN35: =W35+Y35+AA35+AC35+AE35+AG35+AI35+AK35+AM35 -> 0 | AO35: 7657202 | AP35: =IF(AO35>=AO34,AO35-AO34,0)*0.1125 -> 0 | AQ35: 686724 | AR35: =IF(AQ35>=AQ34,AQ35-AQ34,0) -> 0 | AS35: 970212 | AT35: =IF(AS35>=AS34,AS35-AS34,0) -> 0 | AU35: 811396 | AV35: =IF(AU35>=AU34,AU35-AU34,0) -> 0 | AW35: 2637349 | AX35: =IF(AW35>=AW34,AW35-AW34,0) -> 0 | AY35: 229718 | AZ35: =IF(AY35>=AY34,AY35-AY34,0) -> 0 | BA35: 19418549 | BB35: =IF(BA35>=BA34,BA35-BA34,0) -> 0 | BC35: 573740 | BD35: =IF(BC35>=BC34,BC35-BC34,0) -> 0 | BE35: 28262 | BF35: =IF(BE35>=BE34,BE35-BE34,0) -> 0 | BG35: 24283472 | BH35: =IF(BG35>=BG34,BG35-BG34,0)-(0.45*BN35)-(0.45*BP35)-BR35 -> 0 | BI35: =AP35+AR35+AT35+AV35+AX35+AZ35+BB35+BD35+BF35+BH35 -> 0 | BJ35: =BI35+AN35 -> 0 | BK35: 1430109 | BL35: =IF(BK35>=BK34,BK35-BK34,0) -> 0 | BM35: 3956355 | BN35: =IF(BM35>=BM34,BM35-BM34,0) -> 0 | BO35: 417327 | BP35: =IF(BO35>=BO34,BO35-BO34,0) -> 0 | BQ35: 521809 | BR35: =IF(BQ35>=BQ34,BQ35-BQ34,0) -> 0 | BS35: =J35+Q35+AN35+BI35 -> 0 | BU35: =IF(BS35>0,BS35/BT35,0) -> 0 | BW35: =IF(BS35>0,BS35/BV35,0) -> 0 | BX35: =((BS35-Q35)*$BZ$1)+(Q35*$BR$1) -> 0 | BY35: =IF(BX35>0,BX35/BT35,0) -> 0 | BZ35: =IF(BX35>0,BX35/BV35,0) -> 0
A36: 31 | I36: 24120719 | J36: =IF(I36>=I35,I36-I35,0) -> 0 | K36: =M36+O36 -> 0 | L36: 753252 | M36: =IF(L36>=L35,L36-L35,0) -> 0 | N36: 614213 | O36: =IF(N36>=N35,N36-N35,0) -> 0 | P36: 222231 | Q36: =IF(P36>=P35,P36-P35,0)*30 -> 0 | R36: 186239 | S36: =IF(R36>=R35,R36-R35,0) -> 0 | T36: 340453 | U36: =IF(T36>=T35,T36-T35,0) -> 0 | V36: 864060 | W36: =IF(V36>=V35,V36-V35,0)*0.53 -> 0 | X36: 121213 | Y36: =IF(X36>=X35,X36-X35,0)*0.53 -> 0 | Z36: 134949 | AA36: =IF(Z36>=Z35,Z36-Z35,0)*0.53 -> 0 | AB36: 488643 | AC36: =IF(AB36>=AB35,AB36-AB35,0)*0.53 -> 0 | AD36: 1562 | AE36: =IF(AD36>=AD35,AD36-AD35,0)*0.53 -> 0 | AF36: 836318 | AG36: =IF(AF36>=AF35,AF36-AF35,0)*0.53 -> 0 | AH36: 9065 | AI36: =IF(AH36>=AH35,AH36-AH35,0)*0.53 -> 0 | AJ36: 858266 | AK36: =IF(AJ36>=AJ35,AJ36-AJ35,0)*0.53 -> 0 | AL36: 501158 | AM36: =IF(AL36>=AL35,AL36-AL35,0)*0.53 -> 0 | AN36: =W36+Y36+AA36+AC36+AE36+AG36+AI36+AK36+AM36 -> 0 | AO36: 7657202 | AP36: =IF(AO36>=AO35,AO36-AO35,0)*0.1125 -> 0 | AQ36: 686724 | AR36: =IF(AQ36>=AQ35,AQ36-AQ35,0) -> 0 | AS36: 970212 | AT36: =IF(AS36>=AS35,AS36-AS35,0) -> 0 | AU36: 811396 | AV36: =IF(AU36>=AU35,AU36-AU35,0) -> 0 | AW36: 2637349 | AX36: =IF(AW36>=AW35,AW36-AW35,0) -> 0 | AY36: 229718 | AZ36: =IF(AY36>=AY35,AY36-AY35,0) -> 0 | BA36: 19418549 | BB36: =IF(BA36>=BA35,BA36-BA35,0) -> 0 | BC36: 573740 | BD36: =IF(BC36>=BC35,BC36-BC35,0) -> 0 | BE36: 28262 | BF36: =IF(BE36>=BE35,BE36-BE35,0) -> 0 | BG36: 24283472 | BH36: =IF(BG36>=BG35,BG36-BG35,0)-(0.45*BN36)-(0.45*BP36)-BR36 -> 0 | BI36: =AP36+AR36+AT36+AV36+AX36+AZ36+BB36+BD36+BF36+BH36 -> 0 | BJ36: =BI36+AN36 -> 0 | BK36: 1430109 | BL36: =IF(BK36>=BK35,BK36-BK35,0) -> 0 | BM36: 3956355 | BN36: =IF(BM36>=BM35,BM36-BM35,0) -> 0 | BO36: 417327 | BP36: =IF(BO36>=BO35,BO36-BO35,0) -> 0 | BQ36: 521809 | BR36: =IF(BQ36>=BQ35,BQ36-BQ35,0) -> 0 | BS36: =J36+Q36+AN36+BI36 -> 0 | BU36: =IF(BS36>0,BS36/BT36,0) -> 0 | BW36: =IF(BS36>0,BS36/BV36,0) -> 0 | BX36: =((BS36-Q36)*$BZ$1)+(Q36*$BR$1) -> 0 | BY36: =IF(BX36>0,BX36/BT36,0) -> 0 | BZ36: =IF(BX36>0,BX36/BV36,0) -> 0
A37: MTD | C37: =SUM(C9:C35) -> 0 | E37: =SUM(E9:E35) -> 0 | F37: =SUM(F9:F35) -> 0 | G37: =SUM(G9:G35) -> 0 | J37: =SUM(J6:J36) -> 185633 | K37: =SUM(K6:K36) -> 116404 | M37: =SUM(M6:M36) -> 70642 | O37: =SUM(O6:O36) -> 45762 | Q37: =SUM(Q6:Q36) -> 15060 | S37: =SUM(S6:S36) -> 3953 | U37: =SUM(U6:U36) -> 7221.5 | W37: =SUM(W6:W36) -> 38151.52 | Y37: =SUM(Y5:Y36) -> 242.21 | AA37: =SUM(AA6:AA36) -> 108.12 | AC37: =SUM(AC6:AC36) -> 185.5 | AE37: =SUM(AE6:AE36) -> 253.34 | AG37: =SUM(AG6:AG36) -> 352.45 | AI37: =SUM(AI6:AI36) -> 10627.56 | AK37: =SUM(AK6:AK36) -> 55617.67 | AM37: =SUM(AM6:AM36) -> 4235.76 | AN37: =SUM(AN6:AN36) -> 109774.13 | AP37: =SUM(AP6:AP36) -> 689.4 | AR37: =SUM(AR6:AR36) -> 9291 | AT37: =SUM(AT6:AT36) -> 4054 | AV37: =SUM(AV6:AV36) -> 1198 | AX37: =SUM(AX6:AX36) -> 16357 | AZ37: =SUM(AZ6:AZ36) -> 165 | BB37: =SUM(BB6:BB36) -> 121160 | BD37: =SUM(BD6:BD36) -> 6430 | BF37: =SUM(BF6:BF36) -> 1534 | BH37: =SUM(BH6:BH36) -> 138022.8 | BI37: =SUM(BI6:BI36) -> 298901.2 | BJ37: =SUM(BJ6:BJ36) -> 408675.33 | BL37: =SUM(BL6:BL36) -> 4650 | BN37: =SUM(BN6:BN36) -> 23210 | BP37: =SUM(BP6:BP36) -> 3566 | BR37: =SUM(BR6:BR36) -> 3852 | BS37: =SUM(BS6:BS36) -> 609368.33 | BT37: =SUM(BT6:BT36) -> 6256 | BU37: =IF(BS37>0,BS37/BT37,0) -> 97.405424 | BV37: =SUM(BV6:BV35) -> 0 | BW37: =IF(BS37>0,BS37/BV37,0) -> #DIV/0! | BX37: =SUM(BX6:BX35) -> 707550.58 | BY37: =IF(BX37>0,BX37/BT37,0) -> 113.09952 | BZ37: =IF(BX37>0,BX37/BV37,0) -> #DIV/0!
A38: AVER. Act | C38: =C37/C40 -> #DIV/0! | E38: =E37/C40 -> #DIV/0! | F38: =F37/C40 -> #DIV/0! | G38: =G37/C40 -> #DIV/0! | J38: =J37/J39 -> 6187.7667 | K38: =K37/J39 -> 3880.1333 | M38: =M37/J39 -> 2354.7333 | O38: =O37/J39 -> 1525.4 | Q38: =Q37/J39 -> 502 | S38: =S37/J39 -> 131.76667 | U38: =U37/J39 -> 240.71667 | W38: =W37/J39 -> 1271.7173 | Y38: =Y37/J39 -> 8.0736667 | AA38: =AA37/J39 -> 3.604 | AC38: =AC37/J39 -> 6.1833333 | AE38: =AE37/J39 -> 8.4446667 | AG38: =AG37/J39 -> 11.748333 | AI38: =AI37/J39 -> 354.252 | AK38: =AK37/J39 -> 1853.9223 | AM38: =AM37/J39 -> 141.192 | AN38: =AN37/J39 -> 3659.1377 | AP38: =AP37/J39 -> 22.98 | AR38: =AR37/J39 -> 309.7 | AT38: =AT37/J39 -> 135.13333 | AV38: =AV37/J39 -> 39.933333 | AX38: =AX37/J39 -> 545.23333 | AZ38: =AZ37/J39 -> 5.5 | BB38: =BB37/J39 -> 4038.6667 | BD38: =BD37/J39 -> 214.33333 | BF38: =BF37/J39 -> 51.133333 | BH38: =BH37/J39 -> 4600.76 | BL38: =BL37/J39 -> 155 | BN38: =BN37/J39 -> 773.66667 | BP38: =BP37/J39 -> 118.86667 | BR38: =BR37/J39 -> 128.4 | BS38: =BS37/$J$41 -> #DIV/0! | BT38: =BT37/$J$41 -> #DIV/0! | BU38: =BS38/BT38 -> #DIV/0! | BV38: =BV37/$J$41 -> #DIV/0! | BW38: =BS38/BV38 -> #DIV/0! | BX38: =BX37/$J$41 -> #DIV/0! | BY38: =BX38/BT38 -> #DIV/0! | BZ38: =BX38/BV38 -> #DIV/0!
A39: No of Days MTD | J39: =COUNTIF(I6:I35,">0") -> 30
A40: No of Days month | J40: =COUNTIF(A6:A35,">0") -> 30

Sheet Sheet1

Sheet Sheet2

Sheet Gas
A1: =Elect!A1 -> February | E1: Gas | H1: Gas UP | J1: 3.9
A4: NO. | B4: Main Gas Flow Meter | D4: Laundry Gas Flow Meter | F4: Grumandiz Gas Flow Meter | H4: Plant Room Gas Share Cost | I4: Hotel Consumption Cost | J4: La Grumandiz Cost | K4: Total Natural Gas Consumption
B5: Read | C5: Cons | D5: Read | E5: Cons | F5: Read | G5: Cons | H5: LE/DAY | I5: LE/DAY | J5: LE/DAY | K5: Cons
B6: 8317884 | C6: =IF(B6>=B5,B6-B5,0)*1.06 -> 0 | D6: 463432 | E6: =IF(D6>=D5,D6-D5,0)*0.7 -> 0 | F6: 601784 | G6: =IF(F6>=F5,F6-F5,0) -> 0 | K6: =C6+E6 -> 0
A7: 1 | B7: 8318884 | C7: =IF(B7>=B6,B7-B6,0)*1.06 -> 1060 | D7: 463903 | E7: =IF(D7>=D6,D7-D6,0)*0.7 -> 329.7 | F7: 602041 | G7: =IF(F7>=F6,F7-F6,0) -> 257 | H7: =(E7*0.55)*1.61 -> 291.94935 | I7: =C7*J1 -> 4134 | J7: =G7*J1 -> 1002.3 | K7: =C7+E7 -> 1389.7
A8: 2 | B8: 8319884 | C8: =IF(B8>=B7,B8-B7,0)*1.06 -> 1060 | D8: 464571 | E8: =IF(D8>=D7,D8-D7,0)*0.7 -> 467.6 | F8: 601993 | G8: =IF(F8>=F7,F8-F7,0) -> 0 | H8: =(E8*0.55)*1.61 -> 414.0598 | I8: =C8*J1 -> 4134 | J8: =G8*J1 -> 0 | K8: =C8+E8 -> 1527.6
A9: 3 | B9: 8320884 | C9: =IF(B9>=B8,B9-B8,0)*1.06 -> 1060 | D9: 465239 | E9: =IF(D9>=D8,D9-D8,0)*0.7 -> 467.6 | F9: 601945 | G9: =IF(F9>=F8,F9-F8,0) -> 0 | H9: =(E9*0.55)*1.61 -> 414.0598 | I9: =C9*J1 -> 4134 | J9: =G9*J1 -> 0 | K9: =C9+E9 -> 1527.6
A10: 4 | B10: 8321884 | C10: =IF(B10>=B9,B10-B9,0)*1.06 -> 1060 | D10: 465732 | E10: =IF(D10>=D9,D10-D9,0)*0.7 -> 345.1 | F10: 602070 | G10: =IF(F10>=F9,F10-F9,0) -> 125 | H10: =(E10*0.55)*1.61 -> 305.58605 | I10: =C10*J1 -> 4134 | J10: =G10*J1 -> 487.5 | K10: =C10+E10 -> 1405.1
A11: 5 | B11: 8322884 | C11: =IF(B11>=B10,B11-B10,0)*1.06 -> 1060 | D11: 466291 | E11: =IF(D11>=D10,D11-D10,0)*0.7 -> 391.3 | F11: 602195 | G11: =IF(F11>=F10,F11-F10,0) -> 125 | H11: =(E11*0.55)*1.61 -> 346.49615 | I11: =C11*J1 -> 4134 | J11: =G11*J1 -> 487.5 | K11: =C11+E11 -> 1451.3
A12: 6 | B12: 8323884 | C12: =IF(B12>=B11,B12-B11,0)*1.06 -> 1060 | D12: 466850 | E12: =IF(D12>=D11,D12-D11,0)*0.7 -> 391.3 | F12: 602320 | G12: =IF(F12>=F11,F12-F11,0) -> 125 | H12: =(E12*0.55)*1.61 -> 346.49615 | I12: =C12*J1 -> 4134 | J12: =G12*J1 -> 487.5 | K12: =C12+E12 -> 1451.3
A13: 7 | B13: 8324884 | C13: =IF(B13>=B12,B13-B12,0)*1.06 -> 1060 | D13: 467409 | E13: =IF(D13>=D12,D13-D12,0)*0.7 -> 391.3 | F13: 602445 | G13: =IF(F13>=F12,F13-F12,0) -> 125 | H13: =(E13*0.55)*1.61 -> 346.49615 | I13: =C13*J1 -> 4134 | J13: =G13*J1 -> 487.5 | K13: =C13+E13 -> 1451.3
A14: 8 | B14: 8325884 | C14: =IF(B14>=B13,B14-B13,0)*1.06 -> 1060 | D14: 467968 | E14: =IF(D14>=D13,D14-D13,0)*0.7 -> 391.3 | F14: 602570 | G14: =IF(F14>=F13,F14-F13,0) -> 125 | H14: =(E14*0.55)*1.61 -> 346.49615 | I14: =C14*J1 -> 4134 | J14: =G14*J1 -> 487.5 | K14: =C14+E14 -> 1451.3
A15: 9 | B15: 8326884 | C15: =IF(B15>=B14,B15-B14,0)*1.06 -> 1060 | D15: 468527 | E15: =IF(D15>=D14,D15-D14,0)*0.7 -> 391.3 | F15: 602695 | G15: =IF(F15>=F14,F15-F14,0) -> 125 | H15: =(E15*0.55)*1.61 -> 346.49615 | I15: =C15*J1 -> 4134 | J15: =G15*J1 -> 487.5 | K15: =C15+E15 -> 1451.3
A16: 10 | B16: 8327884 | C16: =IF(B16>=B15,B16-B15,0)*1.06 -> 1060 | D16: 468888 | E16: =IF(D16>=D15,D16-D15,0)*0.7 -> 252.7 | F16: 602750 | G16: =IF(F16>=F15,F16-F15,0) -> 55 | H16: =(E16*0.55)*1.61 -> 223.76585 | I16: =C16*J1 -> 4134 | J16: =G16*J1 -> 214.5 | K16: =C16+E16 -> 1312.7
A17: 11 | B17: 8328884 | C17: =IF(B17>=B16,B17-B16,0)*1.06 -> 1060 | D17: 469249 | E17: =IF(D17>=D16,D17-D16,0)*0.7 -> 252.7 | F17: 602805 | G17: =IF(F17>=F16,F17-F16,0) -> 55 | H17: =(E17*0.55)*1.61 -> 223.76585 | I17: =C17*J1 -> 4134 | J17: =G17*J1 -> 214.5 | K17: =C17+E17 -> 1312.7
A18: 12 | B18: 8329884 | C18: =IF(B18>=B17,B18-B17,0)*1.06 -> 1060 | D18: 469610 | E18: =IF(D18>=D17,D18-D17,0)*0.7 -> 252.7 | F18: 602860 | G18: =IF(F18>=F17,F18-F17,0) -> 55 | H18: =(E18*0.55)*1.61 -> 223.76585 | I18: =C18*J1 -> 4134 | J18: =G18*J1 -> 214.5 | K18: =C18+E18 -> 1312.7
A19: 13 | B19: 8330884 | C19: =IF(B19>=B18,B19-B18,0)*1.06 -> 1060 | D19: 469971 | E19: =IF(D19>=D18,D19-D18,0)*0.7 -> 252.7 | F19: 602915 | G19: =IF(F19>=F18,F19-F18,0) -> 55 | H19: =(E19*0.55)*1.61 -> 223.76585 | I19: =C19*J1 -> 4134 | J19: =G19*J1 -> 214.5 | K19: =C19+E19 -> 1312.7
A20: 14 | B20: 8331884 | C20: =IF(B20>=B19,B20-B19,0)*1.06 -> 1060 | D20: 470332 | E20: =IF(D20>=D19,D20-D19,0)*0.7 -> 252.7 | F20: 602970 | G20: =IF(F20>=F19,F20-F19,0) -> 55 | H20: =(E20*0.55)*1.61 -> 223.76585 | I20: =C20*J1 -> 4134 | J20: =G20*J1 -> 214.5 | K20: =C20+E20 -> 1312.7
A21: 15 | B21: 8332884 | C21: =IF(B21>=B20,B21-B20,0)*1.06 -> 1060 | D21: 471530 | E21: =IF(D21>=D20,D21-D20,0)*0.7 -> 838.6 | F21: 603125 | G21: =IF(F21>=F20,F21-F20,0) -> 155 | H21: =(E21*0.55)*1.61 -> 742.5803 | I21: =C21*J1 -> 4134 | J21: =G21*J1 -> 604.5 | K21: =C21+E21 -> 1898.6
A22: 16 | B22: 8333884 | C22: =IF(B22>=B21,B22-B21,0)*1.06 -> 1060 | D22: 472077 | E22: =IF(D22>=D21,D22-D21,0)*0.7 -> 382.9 | F22: 603296 | G22: =IF(F22>=F21,F22-F21,0) -> 171 | H22: =(E22*0.55)*1.61 -> 339.05795 | I22: =C22*J1 -> 4134 | J22: =G22*J1 -> 666.9 | K22: =C22+E22 -> 1442.9
A23: 17 | B23: 8334884 | C23: =IF(B23>=B22,B23-B22,0)*1.06 -> 1060 | D23: 472676 | E23: =IF(D23>=D22,D23-D22,0)*0.7 -> 419.3 | F23: 603392 | G23: =IF(F23>=F22,F23-F22,0) -> 96 | H23: =(E23*0.55)*1.61 -> 371.29015 | I23: =C23*J1 -> 4134 | J23: =G23*J1 -> 374.4 | K23: =C23+E23 -> 1479.3
A24: 18 | B24: 8335884 | C24: =IF(B24>=B23,B24-B23,0)*1.06 -> 1060 | D24: 473128 | E24: =IF(D24>=D23,D24-D23,0)*0.7 -> 316.4 | F24: 603479 | G24: =IF(F24>=F23,F24-F23,0) -> 87 | H24: =(E24*0.55)*1.61 -> 280.1722 | I24: =C24*J1 -> 4134 | J24: =G24*J1 -> 339.3 | K24: =C24+E24 -> 1376.4
A25: 19 | B25: 8336884 | C25: =IF(B25>=B24,B25-B24,0)*1.06 -> 1060 | D25: 473580 | E25: =IF(D25>=D24,D25-D24,0)*0.7 -> 316.4 | F25: 603566 | G25: =IF(F25>=F24,F25-F24,0) -> 87 | H25: =(E25*0.55)*1.61 -> 280.1722 | I25: =C25*J1 -> 4134 | J25: =G25*J1 -> 339.3 | K25: =C25+E25 -> 1376.4
A26: 20 | B26: 8337884 | C26: =IF(B26>=B25,B26-B25,0)*1.06 -> 1060 | D26: 474178 | E26: =IF(D26>=D25,D26-D25,0)*0.7 -> 418.6 | F26: 603659 | G26: =IF(F26>=F25,F26-F25,0) -> 93 | H26: =(E26*0.55)*1.61 -> 370.6703 | I26: =C26*J1 -> 4134 | J26: =G26*J1 -> 362.7 | K26: =C26+E26 -> 1478.6
A27: 21 | B27: 8338884 | C27: =IF(B27>=B26,B27-B26,0)*1.06 -> 1060 | D27: 474706 | E27: =IF(D27>=D26,D27-D26,0)*0.7 -> 369.6 | F27: 603759 | G27: =IF(F27>=F26,F27-F26,0) -> 100 | H27: =(E27*0.55)*1.61 -> 327.2808 | I27: =C27*J1 -> 4134 | J27: =G27*J1 -> 390 | K27: =C27+E27 -> 1429.6
A28: 22 | B28: 8339884 | C28: =IF(B28>=B27,B28-B27,0)*1.06 -> 1060 | D28: 475367 | E28: =IF(D28>=D27,D28-D27,0)*0.7 -> 462.7 | F28: 603853 | G28: =IF(F28>=F27,F28-F27,0) -> 94 | H28: =(E28*0.55)*1.61 -> 409.72085 | I28: =C28*J1 -> 4134 | J28: =G28*J1 -> 366.6 | K28: =C28+E28 -> 1522.7
A29: 23 | B29: 8340884 | C29: =IF(B29>=B28,B29-B28,0)*1.06 -> 1060 | D29: 475959 | E29: =IF(D29>=D28,D29-D28,0)*0.7 -> 414.4 | F29: 603947 | G29: =IF(F29>=F28,F29-F28,0) -> 94 | H29: =(E29*0.55)*1.61 -> 366.9512 | I29: =C29*J1 -> 4134 | J29: =G29*J1 -> 366.6 | K29: =C29+E29 -> 1474.4
A30: 24 | B30: 8341884 | C30: =IF(B30>=B29,B30-B29,0)*1.06 -> 1060 | D30: 476578 | E30: =IF(D30>=D29,D30-D29,0)*0.7 -> 433.3 | F30: 604052 | G30: =IF(F30>=F29,F30-F29,0) -> 105 | H30: =(E30*0.55)*1.61 -> 383.68715 | I30: =C30*J1 -> 4134 | J30: =G30*J1 -> 409.5 | K30: =C30+E30 -> 1493.3
A31: 25 | B31: 8342884 | C31: =IF(B31>=B30,B31-B30,0)*1.06 -> 1060 | D31: 477021 | E31: =IF(D31>=D30,D31-D30,0)*0.7 -> 310.1 | F31: 604235 | G31: =IF(F31>=F30,F31-F30,0) -> 183 | H31: =(E31*0.55)*1.61 -> 274.59355 | I31: =C31*J3 -> 0 | J31: =G31*J1 -> 713.7 | K31: =C31+E31 -> 1370.1
A32: 26 | B32: 8343884 | C32: =IF(B32>=B31,B32-B31,0)*1.06 -> 1060 | D32: 477475 | E32: =IF(D32>=D31,D32-D31,0)*0.7 -> 317.8 | F32: 604314 | G32: =IF(F32>=F31,F32-F31,0) -> 79 | H32: =(E32*0.55)*1.61 -> 281.4119 | I32: =C32*J1 -> 4134 | J32: =G32*J1 -> 308.1 | K32: =C32+E32 -> 1377.8
A33: 27 | B33: 8344884 | C33: =IF(B33>=B32,B33-B32,0)*1.06 -> 1060 | D33: 477929 | E33: =IF(D33>=D32,D33-D32,0)*0.7 -> 317.8 | F33: 604393 | G33: =IF(F33>=F32,F33-F32,0) -> 79 | H33: =(E33*0.55)*1.61 -> 281.4119 | I33: =C33*J1 -> 4134 | J33: =G33*J1 -> 308.1 | K33: =C33+E33 -> 1377.8
A34: 28 | B34: 8345884 | C34: =IF(B34>=B33,B34-B33,0)*1.06 -> 1060 | D34: 478383 | E34: =IF(D34>=D33,D34-D33,0)*0.7 -> 317.8 | F34: 604472 | G34: =IF(F34>=F33,F34-F33,0) -> 79 | H34: =(E34*0.55)*1.61 -> 281.4119 | I34: =C34*J1 -> 4134 | J34: =G34*J1 -> 308.1 | K34: =C34+E34 -> 1377.8
A35: 29 | B35: 8346884 | C35: =IF(B35>=B34,B35-B34,0)*1.06 -> 1060 | D35: 478383 | E35: =IF(D35>=D34,D35-D34,0)*0.7 -> 0 | F35: 604472 | G35: =IF(F35>=F34,F35-F34,0) -> 0 | H35: =(E35*0.55)*1.61 -> 0 | I35: =C35*J1 -> 4134 | J35: =G35*J1 -> 0 | K35: =C35+E35 -> 1060
A36: 30 | B36: 8347884 | C36: =IF(B36>=B35,B36-B35,0)*1.06 -> 1060 | D36: 478383 | E36: =IF(D36>=D35,D36-D35,0)*0.7 -> 0 | F36: 604472 | G36: =IF(F36>=F35,F36-F35,0) -> 0 | H36: =(E36*0.55)*1.61 -> 0 | I36: =C36*J1 -> 4134 | J36: =G36*J1 -> 0 | K36: =C36+E36 -> 1060
A37: 31 | B37: 8348884 | C37: =IF(B37>=B36,B37-B36,0)*1.06 -> 1060 | D37: 478383 | E37: =IF(D37>=D36,D37-D36,0)*0.7 -> 0 | F37: 604472 | G37: =IF(F37>=F36,F37-F36,0) -> 0 | H37: =(E37*0.55)*1.61 -> 0 | I37: =C37*J1 -> 4134 | J37: =G37*J1 -> 0 | K37: =C37+E37 -> 1060
A38: MTD | C38: =SUM(C7:C37) -> 32860 | E38: =SUM(E7:E37) -> 10465.7 | G38: =SUM(G7:G37) -> 2784 | H38: =SUM(H6:H37) -> 9267.3773 | I38: =SUM(I6:I37) -> 124020 | J38: =SUM(J6:J37) -> 10857.6 | K38: =SUM(K6:K37) -> 43325.7
A39: Average MTD. | C39: =C38/A42 -> 1095.3333 | E39: =E38/A42 -> 348.85667 | G39: =G38/A42 -> 92.8 | H39: =H38/A42 -> 308.91258 | I39: =I38/A42 -> 4134 | J39: =J38/A42 -> 361.92
A41: No of Days MTD
A42: =COUNTIF(B7:B36,">0") -> 30

Sheet Consp
A1: =Elect!A1 -> February | L1: Summary | P1: =Elect!A1 -> February
B2: Elect Consuumption | H2: Water Incoming | U2: Water Consumption | AC2: Irrigation | AG2: Gas | AJ2: Cost | AK2: Solar Meter [ LIT ] | AL2: No. of Eng. | AM2: No. of Gardners | AN2: Cons. (lit) | AO2: Received Gas (tons) | AP2: Fuel Cost | AQ2: Solar level [cm] | AR2: Received Solar (tons) | AS2: Fuel Cost | AT2: Occupancy 10 | AV2: Occupancy07 | AZ2: Elect 2009 | BE2: Elect 2010 | BJ2: Water 2009 | BO2: Water 2010
A3: Date | B3: COUNTER (2) | D3: MD | F3: KVAR | H3: R.O | J3: Qenna | L3: Trucks | N3: Rimievera Line Meter | O3: Total Inc. | Q3: Total Main S.Pool | S3: Total Bar & Beach cons. | U3: Total S. Pool cons. | W3: Hotel consumption. | Y3: Sold Water | AA3: Irr. Water from R.O | AC3: Irr. Consumption. | AE3: Storage Water One tank | AF3: Grand Cons | AG3: % | AH3: Stock | AI3: Cons. | AJ3: 0 | AT3: No of guest | AU3: No. of rooms | AV3: No. of rooms | AW3: No. of guest | AX3: Cons. Per occ. room | AY3: Cons. Per guest | AZ3: Total cost | BA3: cost per room | BB3: cost per guest | BC3: Cons. Per occ. room | BD3: Cons. Per guest | BE3: Total cost | BF3: cost per room | BG3: cost per guest | BH3: Cons. Per occ. room | BI3: Cons. Per guest | BJ3: Total cost | BK3: cost per room | BL3: cost per guest | BM3: Cons. Per occ. room | BN3: Cons. Per guest | BO3: Total cost | BP3: cost per room | BQ3: cost per guest
B4: 2013 | C4: 2014 | D4: 2013 | E4: 2014 | F4: 2013 | G4: 2014 | H4: 2013 | I4: 2014 | J4: 2009 | K4: 2010 | L4: 2009 | M4: 2010 | O4: 2009 | P4: 2010 | Q4: 2009 | R4: 2010 | S4: 2009 | T4: 2010 | U4: 2009 | V4: 2010 | W4: 2009 | X4: 2010 | Y4: 2009 | Z4: 2010 | AA4: 2009 | AB4: 2010 | AC4: 2009 | AD4: 2010
A5: 1 | B5: 33600 | C5: =Elect!J6 -> 6679 | D5: 0 | E5: =Elect!M6 -> 2681 | F5: 20 | G5: =Elect!O6 -> 1739 | H5: 800 | I5: =Water!C7 -> 110.2 | J5: 0 | K5: =Water!E7 -> 150.8 | L5: 0 | M5: =Water!#REF! -> #REF! | N5: =Water!#REF! -> #REF! | O5: 1005 | P5: =Water!H7 -> 261 | Q5: 114 | R5: =Water!O7 -> 0 | S5: 13 | T5: =Water!#REF! -> #REF! | U5: 147 | V5: =Water!#REF! -> #REF! | W5: 755 | X5: =Water!Q7 -> 151.38 | Y5: 0 | Z5: =Water!#REF! -> #REF! | AA5: 0 | AB5: 0 | AC5: 690 | AD5: =Water!#REF! -> #REF! | AE5: =Water!#REF! -> #REF! | AF5: =Water!#REF! -> #REF! | AG5: =Gas!#REF! -> #REF! | AH5: =Gas!C7 -> 1060 | AI5: =Gas!#REF! -> #REF! | AJ5: =Gas!J7 -> 1002.3 | AK5: =Gas!#REF! -> #REF! | AL5: =Gas!#REF! -> #REF! | AM5: =Gas!#REF! -> #REF! | AN5: =Gas!#REF! -> #REF! | AO5: =Gas!#REF! -> #REF! | AP5: =Gas!#REF! -> #REF! | AQ5: =Gas!#REF! -> #REF! | AR5: =Gas!#REF! -> #REF! | AS5: =Gas!#REF! -> #REF! | AT5: =Elect!BR6 -> 111 | AU5: =Elect!BP6 -> 136 | AV5: =Elect!#REF! -> #REF! | AW5: =Elect!BR6 -> 111 | AX5: 48.695652 | AY5: 24.705882 | AZ5: 8835.4834 | BA5: 12.805048 | BB5: 6.496679 | BC5: =Elect!#REF! -> #REF! | BD5: =Elect!#REF! -> #REF! | BE5: =Elect!#REF! -> #REF! | BF5: =Elect!#REF! -> #REF! | BG5: =Elect!#REF! -> #REF! | BH5: 1.142029 | BI5: 0.57941176 | BJ5: 4569.1158 | BK5: 6.6219069 | BL5: 3.3596439 | BM5: =Water!U7 -> 1.3453608 | BN5: =Water!W7 -> #DIV/0! | BO5: =Water!X7 -> 1044 | BP5: =Water!Y7 -> 5.3814433 | BQ5: =Water!Z7 -> 0
A6: 2 | B6: 31200 | C6: =Elect!J7 -> 6640 | D6: 0 | E6: =Elect!M7 -> 2582 | F6: 20 | G6: =Elect!O7 -> 1739 | H6: 936 | I6: =Water!C8 -> 150.8 | J6: 0 | K6: =Water!E8 -> 191.4 | L6: 0 | M6: =Water!#REF! -> #REF! | N6: =Water!#REF! -> #REF! | O6: 1006 | P6: =Water!H8 -> 350.9 | Q6: 113 | R6: =Water!O8 -> 0 | S6: 17 | T6: =Water!#REF! -> #REF! | U6: 140 | V6: =Water!#REF! -> #REF! | W6: 792 | X6: =Water!Q8 -> 203.522 | Y6: 0 | Z6: =Water!#REF! -> #REF! | AA6: 0 | AB6: 0 | AC6: 370 | AD6: =Water!#REF! -> #REF! | AE6: =Water!#REF! -> #REF! | AF6: =Water!#REF! -> #REF! | AG6: =Gas!B7 -> 8318884 | AH6: =Gas!C8 -> 1060 | AI6: =Gas!#REF! -> #REF! | AJ6: =Gas!J8 -> 0 | AK6: =Gas!#REF! -> #REF! | AL6: =Gas!#REF! -> #REF! | AM6: =Gas!#REF! -> #REF! | AN6: =Gas!#REF! -> #REF! | AO6: =Gas!#REF! -> #REF! | AP6: =Gas!#REF! -> #REF! | AQ6: =Gas!#REF! -> #REF! | AR6: =Gas!#REF! -> #REF! | AS6: =Gas!#REF! -> #REF! | AT6: =Elect!BR7 -> 133 | AU6: =Elect!BP7 -> 142 | AX6: 47.416413 | AY6: 23.981553 | AZ6: 8299.2754 | BA6: 12.612881 | BB6: 6.379151 | BC6: =Elect!BQ7 -> 518201 | BD6: =Elect!#REF! -> #REF! | BE6: =Elect!#REF! -> #REF! | BF6: =Elect!#REF! -> #REF! | BG6: =Elect!#REF! -> #REF! | BH6: 1.2021277 | BI6: 0.60799385 | BJ6: 5345.8654 | BK6: 8.1244156 | BL6: 4.1090434 | BM6: =Water!U8 -> 1.8087629 | BN6: =Water!W8 -> #DIV/0! | BO6: =Water!X8 -> 1403.6 | BP6: =Water!Y8 -> 7.2350515 | BQ6: =Water!Z8 -> #DIV/0!
A7: 3 | B7: 31200 | C7: =Elect!J8 -> 6891 | D7: 0 | E7: =Elect!M8 -> 2703 | F7: 20 | G7: =Elect!O8 -> 1428 | H7: 685 | I7: =Water!C9 -> 150.8 | J7: 0 | K7: =Water!E9 -> 191.4 | L7: 0 | M7: =Water!#REF! -> #REF! | N7: =Water!#REF! -> #REF! | O7: 902 | P7: =Water!H9 -> 350.9 | Q7: 126 | R7: =Water!O9 -> 0 | S7: 26 | T7: =Water!#REF! -> #REF! | U7: 134 | V7: =Water!#REF! -> #REF! | W7: 766 | X7: =Water!Q9 -> 203.522 | Y7: 0 | Z7: =Water!#REF! -> #REF! | AA7: 0 | AB7: 0 | AC7: 740 | AD7: =Water!#REF! -> #REF! | AE7: =Water!#REF! -> #REF! | AF7: =Water!#REF! -> #REF! | AG7: =Gas!B9 -> 8320884 | AH7: =Gas!C9 -> 1060 | AI7: =Gas!#REF! -> #REF! | AJ7: =Gas!J9 -> 0 | AK7: =Gas!#REF! -> #REF! | AL7: =Gas!#REF! -> #REF! | AM7: =Gas!#REF! -> #REF! | AN7: =Gas!#REF! -> #REF! | AO7: =Gas!#REF! -> #REF! | AP7: =Gas!#REF! -> #REF! | AQ7: =Gas!#REF! -> #REF! | AR7: =Gas!#REF! -> #REF! | AS7: =Gas!#REF! -> #REF! | AT7: =Elect!BR8 -> 128 | AU7: =Elect!BP8 -> 135 | AX7: 47.926267 | AY7: 24.223602 | AZ7: 8299.2754 | BA7: 12.748503 | BB7: 6.4435368 | BC7: =Elect!BQ8 -> 518329 | BD7: =Elect!#REF! -> #REF! | BE7: =Elect!#REF! -> #REF! | BF7: =Elect!#REF! -> #REF! | BG7: =Elect!#REF! -> #REF! | BH7: 1.0875576 | BI7: 0.54968944 | BJ7: 3912.3054 | BK7: 6.0096857 | BL7: 3.0375042 | BM7: =Water!U9 -> 1.6551887 | BN7: =Water!W9 -> #DIV/0! | BO7: =Water!X9 -> 1403.6 | BP7: =Water!Y9 -> 6.6207547 | BQ7: =Water!Z9 -> #DIV/0!
A8: 4 | B8: 33600 | C8: =Elect!J9 -> 6741 | D8: 0 | E8: =Elect!M9 -> 2760 | F8: 20 | G8: =Elect!O9 -> 1416 | H8: 786 | I8: =Water!C10 -> 278.4 | J8: 0 | K8: =Water!E10 -> 211.7 | L8: 0 | M8: =Water!#REF! -> #REF! | N8: =Water!#REF! -> #REF! | O8: 930 | P8: =Water!H10 -> 498.8 | Q8: 153 | R8: =Water!O10 -> 0 | S8: 46 | T8: =Water!#REF! -> #REF! | U8: 150 | V8: =Water!#REF! -> #REF! | W8: 766 | X8: =Water!Q10 -> 289.304 | Y8: 0 | Z8: =Water!#REF! -> #REF! | AA8: 0 | AB8: 0 | AC8: 820 | AD8: =Water!#REF! -> #REF! | AE8: =Water!#REF! -> #REF! | AF8: =Water!#REF! -> #REF! | AG8: =Gas!B10 -> 8321884 | AH8: =Gas!C10 -> 1060 | AI8: =Gas!#REF! -> #REF! | AJ8: =Gas!J10 -> 487.5 | AK8: =Gas!#REF! -> #REF! | AL8: =Gas!#REF! -> #REF! | AM8: =Gas!#REF! -> #REF! | AN8: =Gas!#REF! -> #REF! | AO8: =Gas!#REF! -> #REF! | AP8: =Gas!#REF! -> #REF! | AQ8: =Gas!#REF! -> #REF! | AR8: =Gas!#REF! -> #REF! | AS8: =Gas!#REF! -> #REF! | AT8: =Elect!BR9 -> 129 | AU8: =Elect!BP9 -> 138 | AX8: 51.06383 | AY8: 25.866051 | AZ8: 8835.4834 | BA8: 13.427786 | BB8: 6.8017578 | BC8: =Elect!BQ9 -> 518458 | BD8: =Elect!#REF! -> #REF! | BE8: =Elect!#REF! -> #REF! | BF8: =Elect!#REF! -> #REF! | BG8: =Elect!#REF! -> #REF! | BH8: 1.2218845 | BI8: 0.61893764 | BJ8: 4489.1562 | BK8: 6.8224259 | BL8: 3.4558555 | BM8: =Water!U10 -> 2.1316239 | BN8: =Water!W10 -> #DIV/0! | BO8: =Water!X10 -> 1995.2 | BP8: =Water!Y10 -> 8.5264957 | BQ8: =Water!Z10 -> #DIV/0!
A9: 5 | B9: 31200 | C9: =Elect!J10 -> 6857 | D9: 0 | E9: =Elect!M10 -> 2782 | F9: 20 | G9: =Elect!O10 -> 1590 | H9: 789 | I9: =Water!C11 -> 104.4 | J9: 0 | K9: =Water!E11 -> 171.1 | L9: 0 | M9: =Water!#REF! -> #REF! | N9: =Water!#REF! -> #REF! | O9: 1003 | P9: =Water!H11 -> 284.2 | Q9: 102 | R9: =Water!O11 -> 0 | S9: 8 | T9: =Water!#REF! -> #REF! | U9: 130 | V9: =Water!#REF! -> #REF! | W9: 735 | X9: =Water!Q11 -> 164.836 | Y9: 0 | Z9: =Water!#REF! -> #REF! | AA9: 0 | AB9: 0 | AC9: 640 | AD9: =Water!#REF! -> #REF! | AE9: =Water!#REF! -> #REF! | AF9: =Water!#REF! -> #REF! | AG9: =Gas!B11 -> 8322884 | AH9: =Gas!C11 -> 1060 | AI9: =Gas!#REF! -> #REF! | AJ9: =Gas!J11 -> 487.5 | AK9: =Gas!#REF! -> #REF! | AL9: =Gas!#REF! -> #REF! | AM9: =Gas!#REF! -> #REF! | AN9: =Gas!#REF! -> #REF! | AO9: =Gas!#REF! -> #REF! | AP9: =Gas!#REF! -> #REF! | AQ9: =Gas!#REF! -> #REF! | AR9: =Gas!#REF! -> #REF! | AS9: =Gas!#REF! -> #REF! | AT9: =Elect!BR10 -> 130 | AU9: =Elect!BP10 -> 139 | AX9: 49.840256 | AY9: 25.181598 | AZ9: 8299.2754 | BA9: 13.257628 | BB9: 6.698366 | BC9: =Elect!BQ10 -> 518588 | BD9: =Elect!#REF! -> #REF! | BE9: =Elect!#REF! -> #REF! | BF9: =Elect!#REF! -> #REF! | BG9: =Elect!#REF! -> #REF! | BH9: 1.1980831 | BI9: 0.60532688 | BJ9: 4506.2904 | BK9: 7.198547 | BL9: 3.6370383 | BM9: =Water!U11 -> 1.3157407 | BN9: =Water!W11 -> #DIV/0! | BO9: =Water!X11 -> 1136.8 | BP9: =Water!Y11 -> 5.262963 | BQ9: =Water!Z11 -> #DIV/0!
A10: 6 | B10: 33600 | C10: =Elect!J11 -> 6703 | D10: 0 | E10: =Elect!M11 -> 2632 | F10: 20 | G10: =Elect!O11 -> 1601 | H10: 805 | I10: =Water!C12 -> 104.4 | J10: 0 | K10: =Water!E12 -> 171.1 | L10: 0 | M10: =Water!#REF! -> #REF! | N10: =Water!#REF! -> #REF! | O10: 1004 | P10: =Water!H12 -> 284.2 | Q10: 115 | R10: =Water!O12 -> 0 | S10: 21 | T10: =Water!#REF! -> #REF! | U10: 141 | V10: =Water!#REF! -> #REF! | W10: 725 | X10: =Water!Q12 -> 164.836 | Y10: 0 | Z10: =Water!#REF! -> #REF! | AA10: 0 | AB10: 0 | AC10: 510 | AD10: =Water!#REF! -> #REF! | AE10: =Water!#REF! -> #REF! | AF10: =Water!#REF! -> #REF! | AG10: =Gas!B12 -> 8323884 | AH10: =Gas!C12 -> 1060 | AI10: =Gas!#REF! -> #REF! | AJ10: =Gas!J12 -> 487.5 | AK10: =Gas!#REF! -> #REF! | AL10: =Gas!#REF! -> #REF! | AM10: =Gas!#REF! -> #REF! | AN10: =Gas!#REF! -> #REF! | AO10: =Gas!#REF! -> #REF! | AP10: =Gas!#REF! -> #REF! | AQ10: =Gas!#REF! -> #REF! | AR10: =Gas!#REF! -> #REF! | AS10: =Gas!#REF! -> #REF! | AT10: =Elect!BR11 -> 132 | AU10: =Elect!BP11 -> 126 | AX10: 47.457627 | AY10: 23.512946 | AZ10: 8835.4834 | BA10: 12.479496 | BB10: 6.1829835 | BC10: =Elect!BQ11 -> 518720 | BD10: =Elect!#REF! -> #REF! | BE10: =Elect!#REF! -> #REF! | BF10: =Elect!#REF! -> #REF! | BG10: =Elect!#REF! -> #REF! | BH10: 1.1567797 | BI10: 0.57312806 | BJ10: 4597.6727 | BK10: 6.4938881 | BL10: 3.2174057 | BM10: =Water!U12 -> 1.4353535 | BN10: =Water!W12 -> #DIV/0! | BO10: =Water!X12 -> 1136.8 | BP10: =Water!Y12 -> 5.7414141 | BQ10: =Water!Z12 -> #DIV/0!
A11: 7 | B11: 31200 | C11: =Elect!J12 -> 6377 | D11: 0 | E11: =Elect!M12 -> 2652 | F11: 20 | G11: =Elect!O12 -> 1572 | H11: 871 | I11: =Water!C13 -> 104.4 | J11: 0 | K11: =Water!E13 -> 171.1 | L11: 0 | M11: =Water!#REF! -> #REF! | N11: =Water!#REF! -> #REF! | O11: 837 | P11: =Water!H13 -> 284.2 | Q11: 113 | R11: =Water!O13 -> 0 | S11: 1 | T11: =Water!#REF! -> #REF! | U11: 151 | V11: =Water!#REF! -> #REF! | W11: 732 | X11: =Water!Q13 -> 164.836 | Y11: 0 | Z11: =Water!#REF! -> #REF! | AA11: 0 | AB11: 0 | AC11: 1010 | AD11: =Water!#REF! -> #REF! | AE11: =Water!#REF! -> #REF! | AF11: =Water!#REF! -> #REF! | AG11: =Gas!B13 -> 8324884 | AH11: =Gas!C13 -> 1060 | AI11: =Gas!#REF! -> #REF! | AJ11: =Gas!J13 -> 487.5 | AK11: =Gas!#REF! -> #REF! | AL11: =Gas!#REF! -> #REF! | AM11: =Gas!#REF! -> #REF! | AN11: =Gas!#REF! -> #REF! | AO11: =Gas!#REF! -> #REF! | AP11: =Gas!#REF! -> #REF! | AQ11: =Gas!#REF! -> #REF! | AR11: =Gas!#REF! -> #REF! | AS11: =Gas!#REF! -> #REF! | AT11: =Elect!BR12 -> 124 | AU11: =Elect!BP12 -> 119 | AX11: 43.454039 | AY11: 21.517241 | AZ11: 8299.2754 | BA11: 11.558879 | BB11: 5.7236382 | BC11: =Elect!BQ12 -> 518844 | BD11: =Elect!#REF! -> #REF! | BE11: =Elect!#REF! -> #REF! | BF11: =Elect!#REF! -> #REF! | BG11: =Elect!#REF! -> #REF! | BH11: 1.1713092 | BI11: 0.58 | BJ11: 4974.6248 | BK11: 6.9284468 | BL11: 3.4307757 | BM11: =Water!U13 -> 1.5788889 | BN11: =Water!W13 -> #DIV/0! | BO11: =Water!X13 -> 1136.8 | BP11: =Water!Y13 -> 6.3155556 | BQ11: =Water!Z13 -> #DIV/0!
A12: 8 | B12: 33600 | C12: =Elect!J13 -> 6377 | D12: 0 | E12: =Elect!M13 -> 2727 | F12: 20 | G12: =Elect!O13 -> 1727 | H12: 963 | I12: =Water!C14 -> 104.4 | J12: 0 | K12: =Water!E14 -> 185.6 | L12: 0 | M12: =Water!#REF! -> #REF! | N12: =Water!#REF! -> #REF! | O12: 1000 | P12: =Water!H14 -> 290 | Q12: 128 | R12: =Water!O14 -> 0 | S12: 24 | T12: =Water!#REF! -> #REF! | U12: 148 | V12: =Water!#REF! -> #REF! | W12: 719 | X12: =Water!Q14 -> 168.2 | Y12: 0 | Z12: =Water!#REF! -> #REF! | AA12: 0 | AB12: 0 | AC12: 630 | AD12: =Water!#REF! -> #REF! | AE12: =Water!#REF! -> #REF! | AF12: =Water!#REF! -> #REF! | AG12: =Gas!B14 -> 8325884 | AH12: =Gas!C14 -> 1060 | AI12: =Gas!#REF! -> #REF! | AJ12: =Gas!J14 -> 487.5 | AK12: =Gas!#REF! -> #REF! | AL12: =Gas!#REF! -> #REF! | AM12: =Gas!#REF! -> #REF! | AN12: =Gas!#REF! -> #REF! | AO12: =Gas!#REF! -> #REF! | AP12: =Gas!#REF! -> #REF! | AQ12: =Gas!#REF! -> #REF! | AR12: =Gas!#REF! -> #REF! | AS12: =Gas!#REF! -> #REF! | AT12: =Elect!BR13 -> 155 | AU12: =Elect!BP13 -> 140 | AX12: 48.837209 | AY12: 24.086022 | AZ12: 8835.4834 | BA12: 12.842272 | BB12: 6.3336799 | BC12: =Elect!BQ13 -> 518999 | BD12: =Elect!#REF! -> #REF! | BE12: =Elect!#REF! -> #REF! | BF12: =Elect!#REF! -> #REF! | BG12: =Elect!#REF! -> #REF! | BH12: 1.2194767 | BI12: 0.60143369 | BJ12: 5500.0731 | BK12: 7.9942923 | BL12: 3.9427047 | BM12: =Water!U14 -> 1.7058824 | BN12: =Water!W14 -> #DIV/0! | BO12: =Water!X14 -> 1160 | BP12: =Water!Y14 -> 6.8235294 | BQ12: =Water!Z14 -> #DIV/0!
A13: 9 | B13: 33600 | C13: =Elect!J14 -> 6885 | D13: 0 | E13: =Elect!M14 -> 3341 | F13: 20 | G13: =Elect!O14 -> 1839 | H13: 790 | I13: =Water!C15 -> 104.4 | J13: 0 | K13: =Water!E15 -> 127.6 | L13: 0 | M13: =Water!#REF! -> #REF! | N13: =Water!#REF! -> #REF! | O13: 841 | P13: =Water!H15 -> 234.9 | Q13: 127 | R13: =Water!O15 -> 0 | S13: 21 | T13: =Water!#REF! -> #REF! | U13: 139 | V13: =Water!#REF! -> #REF! | W13: 701 | X13: =Water!Q15 -> 136.242 | Y13: 0 | Z13: =Water!#REF! -> #REF! | AA13: 0 | AB13: 0 | AC13: 440 | AD13: =Water!#REF! -> #REF! | AE13: =Water!#REF! -> #REF! | AF13: =Water!#REF! -> #REF! | AG13: =Gas!B15 -> 8326884 | AH13: =Gas!C15 -> 1060 | AI13: =Gas!#REF! -> #REF! | AJ13: =Gas!J15 -> 487.5 | AK13: =Gas!#REF! -> #REF! | AL13: =Gas!#REF! -> #REF! | AM13: =Gas!#REF! -> #REF! | AN13: =Gas!#REF! -> #REF! | AO13: =Gas!#REF! -> #REF! | AP13: =Gas!#REF! -> #REF! | AQ13: =Gas!#REF! -> #REF! | AR13: =Gas!#REF! -> #REF! | AS13: =Gas!#REF! -> #REF! | AT13: =Elect!BR14 -> 139 | AU13: =Elect!BP14 -> 126 | AX13: 49.194729 | AY13: 24.1033 | AZ13: 8835.4834 | BA13: 12.936286 | BB13: 6.3382234 | BC13: =Elect!BQ14 -> 519138 | BD13: =Elect!#REF! -> #REF! | BE13: =Elect!#REF! -> #REF! | BF13: =Elect!#REF! -> #REF! | BG13: =Elect!#REF! -> #REF! | BH13: 1.1903367 | BI13: 0.58321377 | BJ13: 4512.0018 | BK13: 6.606152 | BL13: 3.2367301 | BM13: =Water!U15 -> 1.5253247 | BN13: =Water!W15 -> #DIV/0! | BO13: =Water!X15 -> 939.6 | BP13: =Water!Y15 -> 6.1012987 | BQ13: =Water!Z15 -> #DIV/0!
A14: 10 | B14: 31200 | C14: =Elect!J15 -> 7165 | D14: 0 | E14: =Elect!M15 -> 2218 | F14: 20 | G14: =Elect!O15 -> 1236 | H14: 792 | I14: =Water!C16 -> 150.8 | J14: 0 | K14: =Water!E16 -> 178.35 | L14: 0 | M14: =Water!#REF! -> #REF! | N14: =Water!#REF! -> #REF! | O14: 972 | P14: =Water!H16 -> 329.15 | Q14: 126 | R14: =Water!O16 -> 0 | S14: 18 | T14: =Water!#REF! -> #REF! | U14: 145 | V14: =Water!#REF! -> #REF! | W14: 756 | X14: =Water!Q16 -> 190.907 | Y14: 0 | Z14: =Water!#REF! -> #REF! | AA14: 0 | AB14: 0 | AC14: 580 | AD14: =Water!#REF! -> #REF! | AE14: =Water!#REF! -> #REF! | AF14: =Water!#REF! -> #REF! | AG14: =Gas!B16 -> 8327884 | AH14: =Gas!C16 -> 1060 | AI14: =Gas!#REF! -> #REF! | AJ14: =Gas!J16 -> 214.5 | AK14: =Gas!#REF! -> #REF! | AL14: =Gas!#REF! -> #REF! | AM14: =Gas!#REF! -> #REF! | AN14: =Gas!#REF! -> #REF! | AO14: =Gas!#REF! -> #REF! | AP14: =Gas!#REF! -> #REF! | AQ14: =Gas!#REF! -> #REF! | AR14: =Gas!#REF! -> #REF! | AS14: =Gas!#REF! -> #REF! | AT14: =Elect!BR15 -> 116 | AU14: =Elect!BP15 -> 104 | AX14: 49.52381 | AY14: 24.781573 | AZ14: 8299.2754 | BA14: 13.173453 | BB14: 6.5919582 | BC14: =Elect!BQ15 -> 519254 | BD14: =Elect!#REF! -> #REF! | BE14: =Elect!#REF! -> #REF! | BF14: =Elect!#REF! -> #REF! | BG14: =Elect!#REF! -> #REF! | BH14: 1.2730159 | BI14: 0.6370135 | BJ14: 4469.9646 | BK14: 7.0951819 | BL14: 3.5504087 | BM14: =Water!U16 -> 1.6879487 | BN14: =Water!W16 -> #DIV/0! | BO14: =Water!X16 -> 1316.6 | BP14: =Water!Y16 -> 6.7517949 | BQ14: =Water!Z16 -> #DIV/0!
A15: 11 | B15: 33600 | C15: =Elect!J16 -> 7160 | D15: 0 | E15: =Elect!M16 -> 2798 | F15: 20 | G15: =Elect!O16 -> 1566 | H15: 817 | I15: =Water!C17 -> 150.8 | J15: 0 | K15: =Water!E17 -> 144.51667 | L15: 0 | M15: =Water!#REF! -> #REF! | N15: =Water!#REF! -> #REF! | O15: 875 | P15: =Water!H17 -> 295.31667 | Q15: 122 | R15: =Water!O17 -> 0 | S15: 20 | T15: =Water!#REF! -> #REF! | U15: 156 | V15: =Water!#REF! -> #REF! | W15: 712 | X15: =Water!Q17 -> 171.28367 | Y15: 0 | Z15: =Water!#REF! -> #REF! | AA15: 0 | AB15: 0 | AC15: 850 | AD15: =Water!#REF! -> #REF! | AE15: =Water!#REF! -> #REF! | AF15: =Water!#REF! -> #REF! | AG15: =Gas!#REF! -> #REF! | AH15: =Gas!C17 -> 1060 | AI15: =Gas!#REF! -> #REF! | AJ15: =Gas!J17 -> 214.5 | AK15: =Gas!#REF! -> #REF! | AL15: =Gas!#REF! -> #REF! | AM15: =Gas!#REF! -> #REF! | AN15: =Gas!#REF! -> #REF! | AO15: =Gas!#REF! -> #REF! | AP15: =Gas!#REF! -> #REF! | AQ15: =Gas!#REF! -> #REF! | AR15: =Gas!#REF! -> #REF! | AS15: =Gas!#REF! -> #REF! | AT15: =Elect!BR16 -> 144 | AU15: =Elect!BP16 -> 122 | AX15: 53.333333 | AY15: 26.751592 | AZ15: 8835.4834 | BA15: 14.024577 | BB15: 7.0346206 | BC15: =Elect!BQ16 -> 519398 | BD15: =Elect!#REF! -> #REF! | BE15: =Elect!#REF! -> #REF! | BF15: =Elect!#REF! -> #REF! | BG15: =Elect!#REF! -> #REF! | BH15: 1.3460317 | BI15: 0.67515924 | BJ15: 4666.2095 | BK15: 7.4066817 | BL15: 3.7151349 | BM15: =Water!U17 -> 1.4129984 | BN15: =Water!W17 -> #DIV/0! | BO15: =Water!X17 -> 1181.2667 | BP15: =Water!Y17 -> 5.6519936 | BQ15: =Water!Z17 -> #DIV/0!
A16: 12 | B16: 33600 | C16: =Elect!J17 -> 6495 | D16: 0 | E16: =Elect!M17 -> 2441 | F16: 20 | G16: =Elect!O17 -> 1472 | H16: 907 | I16: =Water!C18 -> 150.8 | J16: 0 | K16: =Water!E18 -> 152.975 | L16: 0 | M16: =Water!#REF! -> #REF! | N16: =Water!#REF! -> #REF! | O16: 965 | P16: =Water!H18 -> 303.775 | Q16: 125 | R16: =Water!O18 -> 0 | S16: 4 | T16: =Water!#REF! -> #REF! | U16: 167 | V16: =Water!#REF! -> #REF! | W16: 705 | X16: =Water!Q18 -> 176.1895 | Y16: 0 | Z16: =Water!#REF! -> #REF! | AA16: 0 | AB16: 0 | AC16: 880 | AD16: =Water!#REF! -> #REF! | AE16: =Water!#REF! -> #REF! | AF16: =Water!#REF! -> #REF! | AG16: =Gas!B18 -> 8329884 | AH16: =Gas!C18 -> 1060 | AI16: =Gas!#REF! -> #REF! | AJ16: =Gas!J18 -> 214.5 | AK16: =Gas!#REF! -> #REF! | AL16: =Gas!#REF! -> #REF! | AM16: =Gas!#REF! -> #REF! | AN16: =Gas!#REF! -> #REF! | AO16: =Gas!#REF! -> #REF! | AP16: =Gas!#REF! -> #REF! | AQ16: =Gas!#REF! -> #REF! | AR16: =Gas!#REF! -> #REF! | AS16: =Gas!#REF! -> #REF! | AT16: =Elect!BR17 -> 134 | AU16: =Elect!BP17 -> 116 | AX16: 50.45045 | AY16: 25.339367 | AZ16: 8835.4834 | BA16: 13.266492 | BB16: 6.6632605 | BC16: =Elect!BQ17 -> 519532 | BD16: =Elect!#REF! -> #REF! | BE16: =Elect!#REF! -> #REF! | BF16: =Elect!#REF! -> #REF! | BG16: =Elect!#REF! -> #REF! | BH16: 1.2162162 | BI16: 0.61085973 | BJ16: 5180.235 | BK16: 7.7781306 | BL16: 3.9066629 | BM16: =Water!U18 -> 1.5821615 | BN16: =Water!W18 -> #DIV/0! | BO16: =Water!X18 -> 1215.1 | BP16: =Water!Y18 -> 6.3286458 | BQ16: =Water!Z18 -> #DIV/0!
A17: 13 | B17: 31200 | C17: =Elect!J18 -> 7359 | D17: 0 | E17: =Elect!M18 -> 3499 | F17: 20 | G17: =Elect!O18 -> 2068 | H17: 812 | I17: =Water!C19 -> 150.8 | J17: 0 | K17: =Water!E19 -> 152.975 | L17: 0 | M17: =Water!#REF! -> #REF! | N17: =Water!#REF! -> #REF! | O17: 822 | P17: =Water!H19 -> 303.775 | Q17: 123 | R17: =Water!O19 -> 0 | S17: 7 | T17: =Water!#REF! -> #REF! | U17: 163 | V17: =Water!#REF! -> #REF! | W17: 692 | X17: =Water!Q19 -> 176.1895 | Y17: 0 | Z17: =Water!#REF! -> #REF! | AA17: 0 | AB17: 0 | AC17: 460 | AD17: =Water!#REF! -> #REF! | AE17: =Water!#REF! -> #REF! | AF17: =Water!#REF! -> #REF! | AG17: =Gas!B19 -> 8330884 | AH17: =Gas!C19 -> 1060 | AI17: =Gas!#REF! -> #REF! | AJ17: =Gas!J19 -> 214.5 | AK17: =Gas!#REF! -> #REF! | AL17: =Gas!#REF! -> #REF! | AM17: =Gas!#REF! -> #REF! | AN17: =Gas!#REF! -> #REF! | AO17: =Gas!#REF! -> #REF! | AP17: =Gas!#REF! -> #REF! | AQ17: =Gas!#REF! -> #REF! | AR17: =Gas!#REF! -> #REF! | AS17: =Gas!#REF! -> #REF! | AT17: =Elect!BR18 -> 146 | AU17: =Elect!BP18 -> 141 | AX17: 46.567164 | AY17: 23.214286 | AZ17: 8299.2754 | BA17: 12.386978 | BB17: 6.1750561 | BC17: =Elect!BQ18 -> 519678 | BD17: =Elect!#REF! -> #REF! | BE17: =Elect!#REF! -> #REF! | BF17: =Elect!#REF! -> #REF! | BG17: =Elect!#REF! -> #REF! | BH17: 1.0850746 | BI17: 0.54092262 | BJ17: 4637.6525 | BK17: 6.9218694 | BL17: 3.4506343 | BM17: =Water!U19 -> 1.3323465 | BN17: =Water!W19 -> #DIV/0! | BO17: =Water!X19 -> 1215.1 | BP17: =Water!Y19 -> 5.329386 | BQ17: =Water!Z19 -> #DIV/0!
A18: 14 | B18: 33600 | C18: =Elect!J19 -> 6826 | D18: 0 | E18: =Elect!M19 -> 1848 | F18: 30 | G18: =Elect!O19 -> 1322 | H18: 810 | I18: =Water!C20 -> 150.8 | J18: 0 | K18: =Water!E20 -> 152.975 | L18: 0 | M18: =Water!#REF! -> #REF! | N18: =Water!#REF! -> #REF! | O18: 943 | P18: =Water!H20 -> 303.775 | Q18: 118 | R18: =Water!O20 -> 0 | S18: 18 | T18: =Water!#REF! -> #REF! | U18: 152 | V18: =Water!#REF! -> #REF! | W18: 708 | X18: =Water!Q20 -> 176.1895 | Y18: 0 | Z18: =Water!#REF! -> #REF! | AA18: 0 | AB18: 0 | AC18: 490 | AD18: =Water!#REF! -> #REF! | AE18: =Water!#REF! -> #REF! | AF18: =Water!#REF! -> #REF! | AG18: =Gas!B20 -> 8331884 | AH18: =Gas!C20 -> 1060 | AI18: =Gas!#REF! -> #REF! | AJ18: =Gas!J20 -> 214.5 | AK18: =Gas!#REF! -> #REF! | AL18: =Gas!#REF! -> #REF! | AM18: =Gas!#REF! -> #REF! | AN18: =Gas!#REF! -> #REF! | AO18: =Gas!#REF! -> #REF! | AP18: =Gas!#REF! -> #REF! | AQ18: =Gas!#REF! -> #REF! | AR18: =Gas!#REF! -> #REF! | AS18: =Gas!#REF! -> #REF! | AT18: =Elect!BR19 -> 144 | AU18: =Elect!BP19 -> 145 | AX18: 47.795164 | AY18: 24.207493 | AZ18: 8835.4834 | BA18: 12.568255 | BB18: 6.3656221 | BC18: =Elect!BQ6 -> 518068 | BD18: =Elect!#REF! -> #REF! | BE18: =Elect!#REF! -> #REF! | BF18: =Elect!#REF! -> #REF! | BG18: =Elect!#REF! -> #REF! | BH18: 1.1024182 | BI18: 0.55835735 | BJ18: 4626.2297 | BK18: 6.5806966 | BL18: 3.3330185 | BM18: =Water!U20 -> 1.3207609 | BN18: =Water!W20 -> #DIV/0! | BO18: =Water!X20 -> 1215.1 | BP18: =Water!Y20 -> 5.2830435 | BQ18: =Water!Z20 -> #DIV/0!
A19: 15 | B19: 31200 | C19: =Elect!J20 -> 7887 | D19: 0 | E19: =Elect!M20 -> 2925 | F19: 20 | G19: =Elect!O20 -> 1982 | H19: 841 | I19: =Water!C21 -> 150.8 | J19: 0 | K19: =Water!E21 -> 152.975 | L19: 0 | M19: =Water!#REF! -> #REF! | N19: =Water!#REF! -> #REF! | O19: 947 | P19: =Water!H21 -> 303.775 | Q19: 131 | R19: =Water!O21 -> 0 | S19: 23 | T19: =Water!#REF! -> #REF! | U19: 166 | V19: =Water!#REF! -> #REF! | W19: 787 | X19: =Water!Q21 -> 176.1895 | Y19: 0 | Z19: =Water!#REF! -> #REF! | AA19: 0 | AB19: 0 | AC19: 730 | AD19: =Water!#REF! -> #REF! | AE19: =Water!#REF! -> #REF! | AF19: =Water!#REF! -> #REF! | AG19: =Gas!B21 -> 8332884 | AH19: =Gas!C21 -> 1060 | AI19: =Gas!#REF! -> #REF! | AJ19: =Gas!J21 -> 604.5 | AK19: =Gas!#REF! -> #REF! | AL19: =Gas!#REF! -> #REF! | AM19: =Gas!#REF! -> #REF! | AN19: =Gas!#REF! -> #REF! | AO19: =Gas!#REF! -> #REF! | AP19: =Gas!#REF! -> #REF! | AQ19: =Gas!#REF! -> #REF! | AR19: =Gas!#REF! -> #REF! | AS19: =Gas!#REF! -> #REF! | AT19: =Elect!BR20 -> 138 | AU19: =Elect!BP20 -> 137 | AX19: 41.6 | AY19: 20.995962 | AZ19: 8299.2754 | BA19: 11.065701 | BB19: 5.5849767 | BC19: =Elect!BQ20 -> 519960 | BD19: =Elect!#REF! -> #REF! | BE19: =Elect!#REF! -> #REF! | BF19: =Elect!#REF! -> #REF! | BG19: =Elect!#REF! -> #REF! | BH19: 1.1506667 | BI19: 0.58114478 | BJ19: 4803.283 | BK19: 6.4043773 | BL19: 3.234534 | BM19: =Water!U21 -> 1.2926596 | BN19: =Water!W21 -> #DIV/0! | BO19: =Water!X21 -> 1215.1 | BP19: =Water!Y21 -> 5.1706383 | BQ19: =Water!Z21 -> #DIV/0!
A20: 16 | B20: 36000 | C20: =Elect!J21 -> 6514 | D20: 0 | E20: =Elect!M21 -> 2416 | F20: 20 | G20: =Elect!O21 -> 1645 | H20: 932 | I20: =Water!C22 -> 17.4 | J20: 0 | K20: =Water!E22 -> 289.03333 | L20: 0 | M20: =Water!#REF! -> #REF! | N20: =Water!#REF! -> #REF! | O20: 998 | P20: =Water!H22 -> 306.43333 | Q20: 136 | R20: =Water!O22 -> 0 | S20: 22 | T20: =Water!#REF! -> #REF! | U20: 162 | V20: =Water!#REF! -> #REF! | W20: 703 | X20: =Water!Q22 -> 177.73133 | Y20: 0 | Z20: =Water!#REF! -> #REF! | AA20: 0 | AB20: 0 | AC20: 600 | AD20: =Water!#REF! -> #REF! | AE20: =Water!#REF! -> #REF! | AF20: =Water!#REF! -> #REF! | AG20: =Gas!B22 -> 8333884 | AH20: =Gas!C22 -> 1060 | AI20: =Gas!#REF! -> #REF! | AJ20: =Gas!J22 -> 666.9 | AK20: =Gas!#REF! -> #REF! | AL20: =Gas!#REF! -> #REF! | AM20: =Gas!#REF! -> #REF! | AN20: =Gas!#REF! -> #REF! | AO20: =Gas!#REF! -> #REF! | AP20: =Gas!#REF! -> #REF! | AQ20: =Gas!#REF! -> #REF! | AR20: =Gas!#REF! -> #REF! | AS20: =Gas!#REF! -> #REF! | AT20: =Elect!BR21 -> 143 | AU20: =Elect!BP21 -> 119 | AX20: 48 | AY20: 24.22611 | AZ20: 9371.6914 | BA20: 12.495589 | BB20: 6.3066564 | BC20: =Elect!BQ21 -> 520103 | BD20: =Elect!#REF! -> #REF! | BE20: =Elect!#REF! -> #REF! | BF20: =Elect!#REF! -> #REF! | BG20: =Elect!#REF! -> #REF! | BH20: 1.1626667 | BI20: 0.58720539 | BJ20: 5323.0199 | BK20: 7.0973598 | BL20: 3.5845252 | BM20: =Water!U22 -> 1.2356183 | BN20: =Water!W22 -> #DIV/0! | BO20: =Water!X22 -> 1225.7333 | BP20: =Water!Y22 -> 4.9424731 | BQ20: =Water!Z22 -> #DIV/0!
A21: 17 | B21: 33600 | C21: =Elect!J22 -> 7171 | D21: 0 | E21: =Elect!M22 -> 2585 | F21: 20 | G21: =Elect!O22 -> 1836 | H21: 972 | I21: =Water!C23 -> 133.4 | J21: 0 | K21: =Water!E23 -> 174 | L21: 0 | M21: =Water!#REF! -> #REF! | N21: =Water!#REF! -> #REF! | O21: 998 | P21: =Water!H23 -> 310.88 | Q21: 136 | R21: =Water!O23 -> 0 | S21: 38 | T21: =Water!#REF! -> #REF! | U21: 137 | V21: =Water!#REF! -> #REF! | W21: 740 | X21: =Water!Q23 -> 180.3104 | Y21: 0 | Z21: =Water!#REF! -> #REF! | AA21: 0 | AB21: 0 | AC21: 690 | AD21: =Water!#REF! -> #REF! | AE21: =Water!#REF! -> #REF! | AF21: =Water!#REF! -> #REF! | AG21: =Gas!B23 -> 8334884 | AH21: =Gas!C23 -> 1060 | AI21: =Gas!#REF! -> #REF! | AJ21: =Gas!J23 -> 374.4 | AK21: =Gas!#REF! -> #REF! | AL21: =Gas!#REF! -> #REF! | AM21: =Gas!#REF! -> #REF! | AN21: =Gas!#REF! -> #REF! | AO21: =Gas!#REF! -> #REF! | AP21: =Gas!#REF! -> #REF! | AQ21: =Gas!#REF! -> #REF! | AR21: =Gas!#REF! -> #REF! | AS21: =Gas!#REF! -> #REF! | AT21: =Elect!BR22 -> 123 | AU21: =Elect!BP22 -> 112 | AX21: 44.385733 | AY21: 22.207535 | AZ21: 8835.4834 | BA21: 11.671709 | BB21: 5.8397115 | BC21: =Elect!#REF! -> #REF! | BD21: =Elect!#REF! -> #REF! | BE21: =Elect!#REF! -> #REF! | BF21: =Elect!#REF! -> #REF! | BG21: =Elect!#REF! -> #REF! | BH21: 1.1770145 | BI21: 0.58889623 | BJ21: 5551.4757 | BK21: 7.3335213 | BL21: 3.6691842 | BM21: =Water!U23 -> 1.2385657 | BN21: =Water!W23 -> #DIV/0! | BO21: =Water!X23 -> 1243.52 | BP21: =Water!Y23 -> 4.9542629 | BQ21: =Water!Z23 -> #DIV/0!
A22: 18 | B22: 33600 | C22: =Elect!J23 -> 6827 | D22: 0 | E22: =Elect!M23 -> 2515 | F22: 20 | G22: =Elect!O23 -> 1722 | H22: 864 | I22: =Water!C24 -> 139.2 | J22: 0 | K22: =Water!E24 -> 174 | L22: 0 | M22: =Water!#REF! -> #REF! | N22: =Water!#REF! -> #REF! | O22: 1002 | P22: =Water!H24 -> 313.2 | Q22: 118 | R22: =Water!O24 -> 0 | S22: 21 | T22: =Water!#REF! -> #REF! | U22: 133 | V22: =Water!#REF! -> #REF! | W22: 769 | X22: =Water!Q24 -> 181.656 | Y22: 0 | Z22: =Water!#REF! -> #REF! | AA22: 0 | AB22: 0 | AC22: 930 | AD22: =Water!#REF! -> #REF! | AE22: =Water!#REF! -> #REF! | AF22: =Water!#REF! -> #REF! | AG22: =Gas!B24 -> 8335884 | AH22: =Gas!C24 -> 1060 | AI22: =Gas!#REF! -> #REF! | AJ22: =Gas!J24 -> 339.3 | AK22: =Gas!#REF! -> #REF! | AL22: =Gas!#REF! -> #REF! | AM22: =Gas!#REF! -> #REF! | AN22: =Gas!#REF! -> #REF! | AO22: =Gas!#REF! -> #REF! | AP22: =Gas!#REF! -> #REF! | AQ22: =Gas!#REF! -> #REF! | AR22: =Gas!#REF! -> #REF! | AS22: =Gas!#REF! -> #REF! | AT22: =Elect!BR23 -> 143 | AU22: =Elect!BP23 -> 132 | AX22: 44.680851 | AY22: 22.459893 | AZ22: 8835.4834 | BA22: 11.749313 | BB22: 5.9060718 | BC22: =Elect!BQ23 -> 520369 | BD22: =Elect!#REF! -> #REF! | BE22: =Elect!#REF! -> #REF! | BF22: =Elect!#REF! -> #REF! | BG22: =Elect!#REF! -> #REF! | BH22: 1.1236702 | BI22: 0.56483957 | BJ22: 4934.645 | BK22: 6.562028 | BL22: 3.2985595 | BM22: =Water!U24 -> 1.2478088 | BN22: =Water!W24 -> #DIV/0! | BO22: =Water!X24 -> 1252.8 | BP22: =Water!Y24 -> 4.9912351 | BQ22: =Water!Z24 -> #DIV/0!
A23: 19 | B23: 33600 | C23: =Elect!J24 -> 6866 | D23: 0 | E23: =Elect!M24 -> 2609 | F23: 30 | G23: =Elect!O24 -> 1575 | H23: 894 | I23: =Water!C25 -> 139.2 | J23: 0 | K23: =Water!E25 -> 174 | L23: 0 | M23: =Water!#REF! -> #REF! | N23: =Water!#REF! -> #REF! | O23: 944 | P23: =Water!H25 -> 313.2 | Q23: 110 | R23: =Water!O25 -> 0 | S23: 14 | T23: =Water!#REF! -> #REF! | U23: 155 | V23: =Water!#REF! -> #REF! | W23: 721 | X23: =Water!Q25 -> 181.656 | Y23: 0 | Z23: =Water!#REF! -> #REF! | AA23: 0 | AB23: 0 | AC23: 660 | AD23: =Water!#REF! -> #REF! | AE23: =Water!#REF! -> #REF! | AF23: =Water!#REF! -> #REF! | AG23: =Gas!B25 -> 8336884 | AH23: =Gas!C25 -> 1060 | AI23: =Gas!#REF! -> #REF! | AJ23: =Gas!J25 -> 339.3 | AK23: =Gas!#REF! -> #REF! | AL23: =Gas!#REF! -> #REF! | AM23: =Gas!#REF! -> #REF! | AN23: =Gas!#REF! -> #REF! | AO23: =Gas!#REF! -> #REF! | AP23: =Gas!#REF! -> #REF! | AQ23: =Gas!#REF! -> #REF! | AR23: =Gas!#REF! -> #REF! | AS23: =Gas!#REF! -> #REF! | AT23: =Elect!BR24 -> 121 | AU23: =Elect!BP24 -> 113 | AX23: 44.8 | AY23: 22.44489 | AZ23: 8835.4834 | BA23: 11.780645 | BB23: 5.9021265 | BC23: =Elect!BQ24 -> 520490 | BD23: =Elect!#REF! -> #REF! | BE23: =Elect!#REF! -> #REF! | BF23: =Elect!#REF! -> #REF! | BG23: =Elect!#REF! -> #REF! | BH23: 1.1346667 | BI23: 0.56847027 | BJ23: 5105.9869 | BK23: 6.8079825 | BL23: 3.4108129 | BM23: =Water!U25 -> 1.2379447 | BN23: =Water!W25 -> #DIV/0! | BO23: =Water!X25 -> 1252.8 | BP23: =Water!Y25 -> 4.9517787 | BQ23: =Water!Z25 -> #DIV/0!
A24: 20 | B24: 33600 | C24: =Elect!J25 -> 6441 | D24: 0 | E24: =Elect!M25 -> 2411 | F24: 20 | G24: =Elect!O25 -> 1662 | H24: 944 | I24: =Water!C26 -> 127.6 | J24: 0 | K24: =Water!E26 -> 179.8 | L24: 0 | M24: =Water!#REF! -> #REF! | N24: =Water!#REF! -> #REF! | O24: 1000 | P24: =Water!H26 -> 307.4 | Q24: 138 | R24: =Water!O26 -> 0 | S24: 15 | T24: =Water!#REF! -> #REF! | U24: 165 | V24: =Water!#REF! -> #REF! | W24: 778 | X24: =Water!Q26 -> 178.292 | Y24: 0 | Z24: =Water!#REF! -> #REF! | AA24: 0 | AB24: 0 | AC24: 560 | AD24: =Water!#REF! -> #REF! | AE24: =Water!#REF! -> #REF! | AF24: =Water!#REF! -> #REF! | AG24: =Gas!B26 -> 8337884 | AH24: =Gas!C26 -> 1060 | AI24: =Gas!#REF! -> #REF! | AJ24: =Gas!J26 -> 362.7 | AK24: =Gas!#REF! -> #REF! | AL24: =Gas!#REF! -> #REF! | AM24: =Gas!#REF! -> #REF! | AN24: =Gas!#REF! -> #REF! | AO24: =Gas!#REF! -> #REF! | AP24: =Gas!#REF! -> #REF! | AQ24: =Gas!#REF! -> #REF! | AR24: =Gas!#REF! -> #REF! | AS24: =Gas!#REF! -> #REF! | AT24: =Elect!BR25 -> 121 | AU24: =Elect!BP25 -> 119 | AX24: 42.857143 | AY24: 21.649485 | AZ24: 8835.4834 | BA24: 11.269749 | BB24: 5.6929661 | BC24: =Elect!BQ25 -> 520611 | BD24: =Elect!#REF! -> #REF! | BE24: =Elect!#REF! -> #REF! | BF24: =Elect!#REF! -> #REF! | BG24: =Elect!#REF! -> #REF! | BH24: 1.1683673 | BI24: 0.59020619 | BJ24: 5391.5566 | BK24: 6.8769855 | BL24: 3.4739411 | BM24: =Water!U26 -> 1.2395161 | BN24: =Water!W26 -> #DIV/0! | BO24: =Water!X26 -> 1229.6 | BP24: =Water!Y26 -> 4.9580645 | BQ24: =Water!Z26 -> #DIV/0!
A25: 21 | B25: 36000 | C25: =Elect!J26 -> 6377 | D25: 0 | E25: =Elect!M26 -> 2375 | F25: 20 | G25: =Elect!O26 -> 1811 | H25: 916 | I25: =Water!C27 -> 127.6 | J25: 0 | K25: =Water!E27 -> 168.2 | L25: 0 | M25: =Water!#REF! -> #REF! | N25: =Water!#REF! -> #REF! | O25: 998 | P25: =Water!H27 -> 295.8 | Q25: 186 | R25: =Water!O27 -> 0 | S25: 43 | T25: =Water!#REF! -> #REF! | U25: 176 | V25: =Water!#REF! -> #REF! | W25: 773 | X25: =Water!Q27 -> 171.564 | Y25: 0 | Z25: =Water!#REF! -> #REF! | AA25: 0 | AB25: 0 | AC25: 950 | AD25: =Water!#REF! -> #REF! | AE25: =Water!#REF! -> #REF! | AF25: =Water!#REF! -> #REF! | AG25: =Gas!B27 -> 8338884 | AH25: =Gas!C27 -> 1060 | AI25: =Gas!#REF! -> #REF! | AJ25: =Gas!J27 -> 390 | AK25: =Gas!#REF! -> #REF! | AL25: =Gas!#REF! -> #REF! | AM25: =Gas!#REF! -> #REF! | AN25: =Gas!#REF! -> #REF! | AO25: =Gas!#REF! -> #REF! | AP25: =Gas!#REF! -> #REF! | AQ25: =Gas!#REF! -> #REF! | AR25: =Gas!#REF! -> #REF! | AS25: =Gas!#REF! -> #REF! | AT25: =Elect!BR26 -> 136 | AU25: =Elect!BP26 -> 129 | AX25: 43.956044 | AY25: 22.222222 | AZ25: 9371.6914 | BA25: 11.442847 | BB25: 5.7849947 | BC25: =Elect!BQ26 -> 520747 | BD25: =Elect!#REF! -> #REF! | BE25: =Elect!#REF! -> #REF! | BF25: =Elect!#REF! -> #REF! | BG25: =Elect!#REF! -> #REF! | BH25: 1.0586081 | BI25: 0.53518519 | BJ25: 5231.6376 | BK25: 6.3878358 | BL25: 3.2294059 | BM25: =Water!U27 -> 1.202439 | BN25: =Water!W27 -> #DIV/0! | BO25: =Water!X27 -> 1183.2 | BP25: =Water!Y27 -> 4.8097561 | BQ25: =Water!Z27 -> #DIV/0!
A26: 22 | B26: 33600 | C26: =Elect!J27 -> 5775 | D26: 0 | E26: =Elect!M27 -> 1980 | F26: 20 | G26: =Elect!O27 -> 1448 | H26: 931 | I26: =Water!C28 -> 127.6 | J26: 0 | K26: =Water!E28 -> 168.2 | L26: 0 | M26: =Water!#REF! -> #REF! | N26: =Water!#REF! -> #REF! | O26: 969 | P26: =Water!H28 -> 295.8 | Q26: 151 | R26: =Water!O28 -> 0 | S26: 29 | T26: =Water!#REF! -> #REF! | U26: 157 | V26: =Water!#REF! -> #REF! | W26: 697 | X26: =Water!Q28 -> 171.564 | Y26: 0 | Z26: =Water!#REF! -> #REF! | AA26: 0 | AB26: 0 | AC26: 700 | AD26: =Water!#REF! -> #REF! | AE26: =Water!#REF! -> #REF! | AF26: =Water!#REF! -> #REF! | AG26: =Gas!B28 -> 8339884 | AH26: =Gas!C28 -> 1060 | AI26: =Gas!#REF! -> #REF! | AJ26: =Gas!J28 -> 366.6 | AK26: =Gas!#REF! -> #REF! | AL26: =Gas!#REF! -> #REF! | AM26: =Gas!#REF! -> #REF! | AN26: =Gas!#REF! -> #REF! | AO26: =Gas!#REF! -> #REF! | AP26: =Gas!#REF! -> #REF! | AQ26: =Gas!#REF! -> #REF! | AR26: =Gas!#REF! -> #REF! | AS26: =Gas!#REF! -> #REF! | AT26: =Elect!BR27 -> 129 | AU26: =Elect!BP27 -> 119 | AX26: 39.952438 | AY26: 20.253165 | AZ26: 8835.4834 | BA26: 10.505926 | BB26: 5.3257887 | BC26: =Elect!BQ27 -> 520876 | BD26: =Elect!#REF! -> #REF! | BE26: =Elect!#REF! -> #REF! | BF26: =Elect!#REF! -> #REF! | BG26: =Elect!#REF! -> #REF! | BH26: 1.0903686 | BI26: 0.55274262 | BJ26: 5317.3085 | BK26: 6.3226022 | BL26: 3.2051287 | BM26: =Water!U28 -> 1.202439 | BN26: =Water!W28 -> #DIV/0! | BO26: =Water!X28 -> 1183.2 | BP26: =Water!Y28 -> 4.8097561 | BQ26: =Water!Z28 -> #DIV/0!
A27: 23 | B27: 36000 | C27: =Elect!J28 -> 5878 | D27: 0 | E27: =Elect!M28 -> 1995 | F27: 30 | G27: =Elect!O28 -> 1658 | H27: 1009 | I27: =Water!C29 -> 156.6 | J27: 0 | K27: =Water!E29 -> 203 | L27: 0 | M27: =Water!#REF! -> #REF! | N27: =Water!#REF! -> #REF! | O27: 902 | P27: =Water!H29 -> 359.6 | Q27: 131 | R27: =Water!O29 -> 0 | S27: 6 | T27: =Water!#REF! -> #REF! | U27: 167 | V27: =Water!#REF! -> #REF! | W27: 748 | X27: =Water!Q29 -> 208.568 | Y27: 0 | Z27: =Water!#REF! -> #REF! | AA27: 0 | AB27: 0 | AC27: 690 | AD27: =Water!#REF! -> #REF! | AE27: =Water!#REF! -> #REF! | AF27: =Water!#REF! -> #REF! | AG27: =Gas!B29 -> 8340884 | AH27: =Gas!C29 -> 1060 | AI27: =Gas!#REF! -> #REF! | AJ27: =Gas!J29 -> 366.6 | AK27: =Gas!#REF! -> #REF! | AL27: =Gas!#REF! -> #REF! | AM27: =Gas!#REF! -> #REF! | AN27: =Gas!#REF! -> #REF! | AO27: =Gas!#REF! -> #REF! | AP27: =Gas!#REF! -> #REF! | AQ27: =Gas!#REF! -> #REF! | AR27: =Gas!#REF! -> #REF! | AS27: =Gas!#REF! -> #REF! | AT27: =Elect!BR28 -> 156 | AU27: =Elect!BP28 -> 118 | AX27: 42.755344 | AY27: 21.543986 | AZ27: 9371.6914 | BA27: 11.130275 | BB27: 5.6084329 | BC27: =Elect!BQ28 -> 521032 | BD27: =Elect!#REF! -> #REF! | BE27: =Elect!#REF! -> #REF! | BF27: =Elect!#REF! -> #REF! | BG27: =Elect!#REF! -> #REF! | BH27: 1.0712589 | BI27: 0.53979653 | BJ27: 5762.7973 | BK27: 6.8441773 | BL27: 3.4487117 | BM27: =Water!U29 -> 1.4384 | BN27: =Water!W29 -> #DIV/0! | BO27: =Water!X29 -> 1438.4 | BP27: =Water!Y29 -> 5.7536 | BQ27: =Water!Z29 -> #DIV/0!
A28: 24 | B28: 33600 | C28: =Elect!J29 -> 6540 | D28: 0 | E28: =Elect!M29 -> 2297 | F28: 20 | G28: =Elect!O29 -> 1754 | H28: 891 | I28: =Water!C30 -> 150.8 | J28: 0 | K28: =Water!E30 -> 197.2 | L28: 0 | M28: =Water!#REF! -> #REF! | N28: =Water!#REF! -> #REF! | O28: 818 | P28: =Water!H30 -> 348 | Q28: 221 | R28: =Water!O30 -> 0 | S28: 93 | T28: =Water!#REF! -> #REF! | U28: 191 | V28: =Water!#REF! -> #REF! | W28: 827 | X28: =Water!Q30 -> 201.84 | Y28: 0 | Z28: =Water!#REF! -> #REF! | AA28: 0 | AB28: 0 | AC28: 470 | AD28: =Water!#REF! -> #REF! | AE28: =Water!#REF! -> #REF! | AF28: =Water!#REF! -> #REF! | AG28: =Gas!B30 -> 8341884 | AH28: =Gas!C30 -> 1060 | AI28: =Gas!#REF! -> #REF! | AJ28: =Gas!J30 -> 409.5 | AK28: =Gas!#REF! -> #REF! | AL28: =Gas!#REF! -> #REF! | AM28: =Gas!#REF! -> #REF! | AN28: =Gas!#REF! -> #REF! | AO28: =Gas!#REF! -> #REF! | AP28: =Gas!#REF! -> #REF! | AQ28: =Gas!#REF! -> #REF! | AR28: =Gas!#REF! -> #REF! | AS28: =Gas!#REF! -> #REF! | AT28: =Elect!BR29 -> 168 | AU28: =Elect!BP29 -> 136 | AX28: 39.904988 | AY28: 20.289855 | AZ28: 8835.4834 | BA28: 10.493448 | BB28: 5.3354369 | BC28: =Elect!BQ29 -> 521200 | BD28: =Elect!#REF! -> #REF! | BE28: =Elect!#REF! -> #REF! | BF28: =Elect!#REF! -> #REF! | BG28: =Elect!#REF! -> #REF! | BH28: 1.1104513 | BI28: 0.56461353 | BJ28: 5088.8527 | BK28: 6.043768 | BL28: 3.0729787 | BM28: =Water!U30 -> 1.4089069 | BN28: =Water!W30 -> #DIV/0! | BO28: =Water!X30 -> 1392 | BP28: =Water!Y30 -> 5.6356275 | BQ28: =Water!Z30 -> #DIV/0!
A29: 25 | B29: 33600 | C29: =Elect!J30 -> 5975 | D29: 0 | E29: =Elect!M30 -> 2203 | F29: 20 | G29: =Elect!O30 -> 1594 | H29: 1008 | I29: =Water!C31 -> 261 | J29: 0 | K29: =Water!E31 -> 348 | L29: 0 | M29: =Water!#REF! -> #REF! | N29: =Water!#REF! -> #REF! | O29: 1290 | P29: =Water!H31 -> 614.22 | Q29: 34 | R29: =Water!O31 -> 0 | S29: 34 | T29: =Water!#REF! -> #REF! | U29: 55 | V29: =Water!#REF! -> #REF! | W29: 681 | X29: =Water!Q31 -> 356.2476 | Y29: 0 | Z29: =Water!#REF! -> #REF! | AA29: 0 | AB29: 0 | AC29: 1170 | AD29: =Water!#REF! -> #REF! | AE29: =Water!#REF! -> #REF! | AF29: =Water!#REF! -> #REF! | AG29: =Gas!B31 -> 8342884 | AH29: =Gas!C31 -> 1060 | AI29: =Gas!#REF! -> #REF! | AJ29: =Gas!J31 -> 713.7 | AK29: =Gas!#REF! -> #REF! | AL29: =Gas!#REF! -> #REF! | AM29: =Gas!#REF! -> #REF! | AN29: =Gas!#REF! -> #REF! | AO29: =Gas!#REF! -> #REF! | AP29: =Gas!#REF! -> #REF! | AQ29: =Gas!#REF! -> #REF! | AR29: =Gas!#REF! -> #REF! | AS29: =Gas!#REF! -> #REF! | AT29: =Elect!BR30 -> 146 | AU29: =Elect!BP30 -> 120 | AX29: 39.763314 | AY29: 20.20445 | AZ29: 8835.4834 | BA29: 10.456193 | BB29: 5.3129786 | BC29: =Elect!BQ30 -> 521346 | BD29: =Elect!#REF! -> #REF! | BE29: =Elect!#REF! -> #REF! | BF29: =Elect!#REF! -> #REF! | BG29: =Elect!#REF! -> #REF! | BH29: 1.0059172 | BI29: 0.51112447 | BJ29: 5757.0859 | BK29: 6.8131194 | BL29: 3.4618676 | BM29: =Water!U31 -> 2.427747 | BN29: =Water!W31 -> #DIV/0! | BO29: =Water!X31 -> 2456.88 | BP29: =Water!Y31 -> 9.7109881 | BQ29: =Water!Z31 -> #DIV/0!
A30: 26 | B30: 31200 | C30: =Elect!J31 -> 6039 | D30: 0 | E30: =Elect!M31 -> 2119 | F30: 20 | G30: =Elect!O31 -> 1690 | H30: 760 | I30: =Water!C32 -> 92.8 | J30: 0 | K30: =Water!E32 -> 121.8 | L30: 0 | M30: =Water!#REF! -> #REF! | N30: =Water!#REF! -> #REF! | O30: 1004 | P30: =Water!H32 -> 214.6 | Q30: 131 | R30: =Water!O32 -> 0 | S30: 33 | T30: =Water!#REF! -> #REF! | U30: 145 | V30: =Water!#REF! -> #REF! | W30: 916 | X30: =Water!Q32 -> 124.468 | Y30: 0 | Z30: =Water!#REF! -> #REF! | AA30: 0 | AB30: 0 | AC30: 810 | AD30: =Water!#REF! -> #REF! | AE30: =Water!#REF! -> #REF! | AF30: =Water!#REF! -> #REF! | AG30: =Gas!B32 -> 8343884 | AH30: =Gas!C32 -> 1060 | AI30: =Gas!#REF! -> #REF! | AJ30: =Gas!J32 -> 308.1 | AK30: =Gas!#REF! -> #REF! | AL30: =Gas!#REF! -> #REF! | AM30: =Gas!#REF! -> #REF! | AN30: =Gas!#REF! -> #REF! | AO30: =Gas!#REF! -> #REF! | AP30: =Gas!#REF! -> #REF! | AQ30: =Gas!#REF! -> #REF! | AR30: =Gas!#REF! -> #REF! | AS30: =Gas!#REF! -> #REF! | AT30: =Elect!BR31 -> 157 | AU30: =Elect!BP31 -> 129 | AX30: 37.275986 | AY30: 18.989653 | AZ30: 8299.2754 | BA30: 9.9155023 | BB30: 5.0512936 | BC30: =Elect!BQ31 -> 521503 | BD30: =Elect!#REF! -> #REF! | BE30: =Elect!#REF! -> #REF! | BF30: =Elect!#REF! -> #REF! | BG30: =Elect!#REF! -> #REF! | BH30: 1.1063321 | BI30: 0.56360316 | BJ30: 4340.66 | BK30: 5.1859737 | BL30: 2.6419111 | BM30: =Water!U32 -> 0.83501946 | BN30: =Water!W32 -> #DIV/0! | BO30: =Water!X32 -> 858.4 | BP30: =Water!Y32 -> 3.3400778 | BQ30: =Water!Z32 -> #DIV/0!
A31: 27 | B31: 36000 | C31: =Elect!J32 -> 6094 | D31: 0 | E31: =Elect!M32 -> 2274 | F31: 30 | G31: =Elect!O32 -> 1535 | H31: 1010 | I31: =Water!C33 -> 92.8 | J31: 0 | K31: =Water!E33 -> 121.8 | L31: 0 | M31: =Water!#REF! -> #REF! | N31: =Water!#REF! -> #REF! | O31: 1014 | P31: =Water!H33 -> 214.6 | Q31: 151 | R31: =Water!O33 -> 0 | S31: 30 | T31: =Water!#REF! -> #REF! | U31: 139 | V31: =Water!#REF! -> #REF! | W31: 761 | X31: =Water!Q33 -> 124.468 | Y31: 0 | Z31: =Water!#REF! -> #REF! | AA31: 0 | AB31: 0 | AC31: 930 | AD31: =Water!#REF! -> #REF! | AE31: =Water!#REF! -> #REF! | AF31: =Water!#REF! -> #REF! | AG31: =Gas!B33 -> 8344884 | AH31: =Gas!C33 -> 1060 | AI31: =Gas!#REF! -> #REF! | AJ31: =Gas!J33 -> 308.1 | AK31: =Gas!#REF! -> #REF! | AL31: =Gas!#REF! -> #REF! | AM31: =Gas!#REF! -> #REF! | AN31: =Gas!#REF! -> #REF! | AO31: =Gas!#REF! -> #REF! | AP31: =Gas!#REF! -> #REF! | AQ31: =Gas!#REF! -> #REF! | AR31: =Gas!#REF! -> #REF! | AS31: =Gas!#REF! -> #REF! | AT31: =Elect!BR32 -> 153 | AU31: =Elect!BP32 -> 127 | AX31: 44.063647 | AY31: 22.346369 | AZ31: 9371.6914 | BA31: 11.470859 | BB31: 5.8173131 | BC31: =Elect!BQ32 -> 521656 | BD31: =Elect!#REF! -> #REF! | BE31: =Elect!#REF! -> #REF! | BF31: =Elect!#REF! -> #REF! | BG31: =Elect!#REF! -> #REF! | BH31: 1.1640147 | BI31: 0.59031657 | BJ31: 5768.5087 | BK31: 7.0605981 | BL31: 3.5807006 | BM31: =Water!U33 -> 0.9371179 | BN31: =Water!W33 -> #DIV/0! | BO31: =Water!X33 -> 858.4 | BP31: =Water!Y33 -> 3.7484716 | BQ31: =Water!Z33 -> #DIV/0!
A32: 28 | B32: 33600 | C32: =Elect!J33 -> 6094 | D32: 0 | E32: =Elect!M33 -> 2274 | F32: 20 | G32: =Elect!O33 -> 1535 | H32: 1008 | I32: =Water!C34 -> 92.8 | J32: 0 | K32: =Water!E34 -> 121.8 | L32: 1 | M32: =Water!#REF! -> #REF! | N32: =Water!#REF! -> #REF! | O32: 1013 | P32: =Water!H34 -> 214.6 | Q32: 142 | R32: =Water!O34 -> 0 | S32: 13 | T32: =Water!#REF! -> #REF! | U32: 155 | V32: =Water!#REF! -> #REF! | W32: 825 | X32: =Water!Q34 -> 124.468 | Y32: 1 | Z32: =Water!#REF! -> #REF! | AA32: 0 | AB32: 0 | AC32: 650 | AD32: =Water!#REF! -> #REF! | AE32: =Water!#REF! -> #REF! | AF32: =Water!#REF! -> #REF! | AG32: =Gas!B34 -> 8345884 | AH32: =Gas!C34 -> 1060 | AI32: =Gas!#REF! -> #REF! | AJ32: =Gas!J34 -> 308.1 | AK32: =Gas!#REF! -> #REF! | AL32: =Gas!#REF! -> #REF! | AM32: =Gas!#REF! -> #REF! | AN32: =Gas!#REF! -> #REF! | AO32: =Gas!#REF! -> #REF! | AP32: =Gas!#REF! -> #REF! | AQ32: =Gas!#REF! -> #REF! | AR32: =Gas!#REF! -> #REF! | AS32: =Gas!#REF! -> #REF! | AT32: =Elect!BR33 -> 153 | AU32: =Elect!BP33 -> 127 | AX32: 45.34413 | AY32: 22.687373 | AZ32: 8835.4834 | BA32: 11.923729 | BB32: 5.9658902 | BC32: =Elect!BQ33 -> 521809 | BD32: =Elect!#REF! -> #REF! | BE32: =Elect!#REF! -> #REF! | BF32: =Elect!#REF! -> #REF! | BG32: =Elect!#REF! -> #REF! | BH32: 1.2294197 | BI32: 0.61512492 | BJ32: 5757.0859 | BK32: 7.7693467 | BL32: 3.8872963 | BM32: =Water!U34 -> 0.90932203 | BN32: =Water!W34 -> #DIV/0! | BO32: =Water!X34 -> 858.4 | BP32: =Water!Y34 -> 3.6372881 | BQ32: =Water!Z34 -> #DIV/0!
A33: MTD | B33: 931200 | C33: =Elect!J34 -> 0 | D33: 0 | E33: =Elect!M34 -> 0 | F33: 600 | G33: =Elect!O34 -> 0 | H33: 24543 | I33: =Water!C38 -> 3775.8 | J33: 0 | K33: =Water!E39 -> 164.91333 | L33: 3 | M33: =Water!#REF! -> #REF! | N33: =Water!#REF! -> #REF! | O33: 1013 | P33: =Water!H38 -> 8787 | Q33: 109 | R33: =Water!O38 -> 0 | S33: 15 | T33: =Water!#REF! -> #REF! | U33: 147 | V33: =Water!#REF! -> #REF! | W33: 730 | X33: =Water!Q38 -> 5096.46 | Y33: 3 | Z33: =Water!#REF! -> #REF! | AA33: 0 | AB33: 0 | AC33: 0 | AD33: =Water!#REF! -> #REF! | AE33: =Water!#REF! -> #REF! | AF33: =Water!#REF! -> #REF! | AG33: =Gas!B38 -> 0 | AH33: =Gas!C38 -> 32860 | AI33: =Gas!#REF! -> #REF! | AJ33: =Gas!J38 -> 10857.6 | AK33: =Gas!#REF! -> #REF! | AL33: =Gas!#REF! -> #REF! | AM33: =Gas!#REF! -> #REF! | AN33: =Gas!#REF! -> #REF! | AO33: =Gas!#REF! -> #REF! | AP33: =Gas!#REF! -> #REF! | AQ33: =Gas!#REF! -> #REF! | AR33: =Gas!#REF! -> #REF! | AS33: =Gas!#REF! -> #REF! | AT33: =Elect!BR34 -> 0 | AU33: =Elect!BP34 -> 0 | AX33: 45.411099 | AY33: 22.844806 | AZ33: 245248.7 | BA33: 11.959851 | BB33: 6.0166013 | BC33: =Elect!BQ34 -> 521809 | BD33: =Elect!#REF! -> #REF! | BE33: =Elect!#REF! -> #REF! | BF33: =Elect!#REF! -> #REF! | BG33: =Elect!#REF! -> #REF! | BH33: 1.1514679 | BI33: 0.57929342 | BJ33: 140121.3 | BK33: 6.8331854 | BL33: 3.4377159 | BM33: =Water!U38 -> 1.4045716 | BN33: =Water!W38 -> #DIV/0! | BO33: =Water!X38 -> 35148 | BP33: =Water!Y38 -> 5.6182864 | BQ33: =Water!Z38 -> #DIV/0!
A34: AVER. Act | B34: 33257.143 | C34: =Elect!J35 -> 0 | D34: 0 | E34: =Elect!M35 -> 0 | F34: 21.428571 | G34: =Elect!O35 -> 0 | H34: 876.53571 | I34: =Water!C39 -> 125.86 | J34: 0 | K34: =Water!E40 -> 0 | L34: 4 | M34: =Water!#REF! -> #REF! | N34: =Water!#REF! -> #REF! | O34: 1014 | P34: =Water!H39 -> 292.9 | Q34: 138 | R34: =Water!O39 -> 0 | S34: 24 | T34: =Water!#REF! -> #REF! | U34: 145 | V34: =Water!#REF! -> #REF! | W34: 877 | X34: =Water!Q39 -> 169.882 | Y34: 4 | Z34: =Water!#REF! -> #REF! | AA34: 0 | AB34: 0 | AC34: 0 | AD34: =Water!#REF! -> #REF! | AE34: =Water!#REF! -> #REF! | AF34: =Water!#REF! -> #REF! | AG34: =Gas!B39 -> 0 | AH34: =Gas!C39 -> 1095.3333 | AI34: =Gas!#REF! -> #REF! | AJ34: =Gas!J39 -> 361.92 | AK34: =Gas!#REF! -> #REF! | AL34: =Gas!#REF! -> #REF! | AM34: =Gas!#REF! -> #REF! | AN34: =Gas!#REF! -> #REF! | AO34: =Gas!#REF! -> #REF! | AP34: =Gas!#REF! -> #REF! | AQ34: =Gas!#REF! -> #REF! | AR34: =Gas!#REF! -> #REF! | AS34: =Gas!#REF! -> #REF! | AT34: =Elect!BR35 -> 0 | AU34: =Elect!BP35 -> 0 | AX34: 45.411099 | AY34: 22.844806 | AZ34: 8758.8823 | BA34: 11.959851 | BB34: 6.0166013 | BC34: =Elect!BQ35 -> 521809 | BD34: =Elect!#REF! -> #REF! | BE34: =Elect!#REF! -> #REF! | BF34: =Elect!#REF! -> #REF! | BG34: =Elect!#REF! -> #REF! | BH34: 1.1761372 | BI34: 0.60007377 | BJ34: 5004.3322 | BK34: 6.8331854 | BL34: 3.4377159 | BM34: =Water!U39 -> 1.4045716 | BN34: =Water!W39 -> #DIV/0! | BO34: =Water!X39 -> 1171.6 | BP34: =Water!Y39 -> 5.6182864 | BQ34: =Water!Z39 -> #DIV/0!
A35: TOTAL Budget | B35: 1040026 | C35: =Elect!J5 -> 0 | D35: 0 | E35: =Elect!M5 -> 0 | F35: 0 | G35: =Elect!O5 -> 0 | H35: 0 | I35: =Water!C40 -> 0 | J35: 0 | K35: =Water!E41 -> 0 | L35: 5 | M35: =Water!#REF! -> #REF! | N35: =Water!#REF! -> #REF! | O35: 1010 | P35: =Water!H40 -> 0 | Q35: 148 | R35: =Water!O40 -> 0 | S35: 22 | T35: =Water!#REF! -> #REF! | U35: 151 | V35: =Water!#REF! -> #REF! | W35: 833 | X35: =Water!Q40 -> 0 | Y35: 5 | Z35: =Water!#REF! -> #REF! | AA35: 0 | AB35: 0 | AC35: 0 | AD35: =Water!#REF! -> #REF! | AE35: =Water!#REF! -> #REF! | AF35: =Water!#REF! -> #REF! | AG35: =Gas!#REF! -> #REF! | AH35: =Gas!#REF! -> #REF! | AI35: =Gas!#REF! -> #REF! | AJ35: =Gas!#REF! -> #REF! | AK35: =Gas!#REF! -> #REF! | AL35: =Gas!#REF! -> #REF! | AM35: =Gas!#REF! -> #REF! | AN35: =Gas!#REF! -> #REF! | ... AS35: =Gas!#REF! -> #REF! | AT35: =Elect!BR5 -> 0 | AU35: =Elect!BP5 -> 0 | AX35: 45.679286 | AY35: 23.305904 | AZ35: 264708.4 | BA35: 11.626335 | BB35: 5.9318409 | BC35: =Elect!BQ5 -> 517957 | BD35: =Elect!#REF! -> #REF! | BE35: =Elect!#REF! -> #REF! | BF35: =Elect!#REF! -> #REF! | BG35: =Elect!#REF! -> #REF! | BH35: 1.1761372 | BI35: 0.60007377 | BJ35: 150494 | BK35: 6.6098911 | BL35: 3.3724146 | BM35: =Water!U40 -> #REF! | BN35: =Water!W40 -> #REF! | BO35: =Water!X40 -> 0 | BP35: =Water!Y40 -> 0 | BQ35: =Water!Z40 -> 0
A36: Budget MTD | B36: 1040026 | C36: =Elect!#REF! -> #REF! | D36: 0 | E36: =Elect!#REF! -> #REF! | F36: 0 | G36: =Elect!#REF! -> #REF! | H36: 0 | I36: =Water!C41 -> 0 | J36: 0 | K36: =Water!E42 -> 0 | L36: 6 | M36: =Water!#REF! -> #REF! | N36: =Water!#REF! -> #REF! | O36: 30039 | P36: =Water!H41 -> 0 | Q36: 129.54839 | R36: =Water!O41 -> 0 | S36: 719 | T36: =Water!#REF! -> #REF! | U36: 4609 | V36: =Water!#REF! -> #REF! | W36: 23430 | X36: =Water!Q41 -> 0 | Y36: 6 | Z36: =Water!#REF! -> #REF! | AA36: 0 | AB36: 0 | AC36: 0 | AD36: =Water!#REF! -> #REF! | AE36: =Water!#REF! -> #REF! | AF36: =Water!#REF! -> #REF! | AG36: =Gas!#REF! -> #REF! | AH36: =Gas!#REF! -> #REF! | AI36: =Gas!#REF! -> #REF! | AJ36: =Gas!#REF! -> #REF! | AK36: =Gas!#REF! -> #REF! | AL36: =Gas!#REF! -> #REF! | AM36: =Gas!#REF! -> #REF! | AN36: =Gas!#REF! -> #REF! | ... AS36: =Gas!#REF! -> #REF! | AT36: =Elect!#REF! -> #REF! | AU36: =Elect!#REF! -> #REF! | AX36: 45.679286 | AY36: 23.305904 | AZ36: 264708.4 | BA36: 11.626335 | BB36: 5.9318409 | BC36: =Elect!#REF! -> #REF! | BD36: =Elect!#REF! -> #REF! | BE36: =Elect!#REF! -> #REF! | BF36: =Elect!#REF! -> #REF! | BG36: =Elect!#REF! -> #REF! | BH36: 0 | BI36: 0 | BJ36: 135930.06 | BK36: 6.6098911 | BL36: 3.3724146 | BM36: =Water!U41 -> #REF! | BN36: =Water!W41 -> #REF! | BO36: =Water!X41 -> #REF! | BP36: =Water!Y41 -> #REF! | BQ36: =Water!Z41 -> #REF!
A37: AVER. Bud | B37: 37143.785 | C37: =Elect!#REF! -> #REF! | D37: 0 | E37: =Elect!#REF! -> #REF! | F37: 0 | G37: =Elect!#REF! -> #REF! | H37: 0 | I37: =Water!C42 -> 0 | J37: 0 | K37: =Water!E43 -> 0 | L37: 7 | M37: =Water!#REF! -> #REF! | N37: =Water!#REF! -> #REF! | O37: 969 | P37: =Water!H42 -> 0 | Q37: 0 | R37: =Water!O42 -> 0 | S37: 23.193548 | T37: =Water!#REF! -> #REF! | U37: 148.67742 | V37: =Water!#REF! -> #REF! | W37: 755.80645 | X37: =Water!Q42 -> 0 | Y37: 7 | Z37: =Water!#REF! -> #REF! | AA37: 0 | AB37: 0 | AC37: 0 | AD37: =Water!#REF! -> #REF! | AE37: =Water!#REF! -> #REF! | AF37: =Water!#REF! -> #REF! | AG37: =Gas!#REF! -> #REF! | AH37: =Gas!#REF! -> #REF! | AI37: =Gas!#REF! -> #REF! | AJ37: =Gas!#REF! -> #REF! | AK37: =Gas!#REF! -> #REF! | AL37: =Gas!#REF! -> #REF! | AM37: =Gas!#REF! -> #REF! | AN37: =Gas!#REF! -> #REF! | ... AS37: =Gas!#REF! -> #REF! | AT37: =Elect!#REF! -> #REF! | AU37: =Elect!#REF! -> #REF! | AX37: 0 | AY37: 0 | AZ37: 9453.8714 | BA37: 0 | BB37: 0 | BC37: =Elect!#REF! -> #REF! | BD37: =Elect!#REF! -> #REF! | BE37: =Elect!#REF! -> #REF! | BF37: =Elect!#REF! -> #REF! | BG37: =Elect!#REF! -> #REF! | BH37: 0 | BI37: 0 | BJ37: 0 | BK37: 0 | BL37: 0 | BM37: =Water!U42 -> 0 | BN37: =Water!W42 -> 0 | BO37: =Water!X42 -> 0 | BP37: =Water!Y42 -> 0 | BQ37: =Water!Z42 -> 0
A38: Total RFC | B38: 784008.53 | C38: =Elect!#REF! -> #REF! | D38: 0 | E38: =Elect!#REF! -> #REF! | F38: 0 | G38: =Elect!#REF! -> #REF! | H38: 0 | I38: =Water!C43 -> 0 | J38: 0 | K38: =Water!E44 -> 0 | L38: 8 | M38: =Water!#REF! -> #REF! | N38: =Water!#REF! -> #REF! | O38: 0 | P38: =Water!H43 -> 0 | Q38: 0 | R38: =Water!O43 -> 0 | S38: 0 | T38: =Water!#REF! -> #REF! | U38: 0 | V38: =Water!#REF! -> #REF! | W38: 0 | X38: =Water!Q43 -> 0 | Y38: 8 | Z38: =Water!#REF! -> #REF! | AA38: 0 | AB38: 0 | AC38: 0 | AD38: =Water!#REF! -> #REF! | AE38: =Water!#REF! -> #REF! | AF38: =Water!#REF! -> #REF! | AG38: =Gas!#REF! -> #REF! | AH38: =Gas!#REF! -> #REF! | AI38: =Gas!#REF! -> #REF! | AJ38: =Gas!#REF! -> #REF! | AK38: =Gas!#REF! -> #REF! | AL38: =Gas!#REF! -> #REF! | AM38: =Gas!#REF! -> #REF! | AN38: =Gas!#REF! -> #REF! | ... AS38: =Gas!#REF! -> #REF! | AT38: =Elect!#REF! -> #REF! | AU38: =Elect!#REF! -> #REF! | AX38: 38.173558 | AY38: 19.219193 | AZ38: 208225.85 | BA38: 10.138565 | BB38: 5.1044505 | BC38: =Elect!#REF! -> #REF! | BD38: =Elect!#REF! -> #REF! | BE38: =Elect!#REF! -> #REF! | BF38: =Elect!#REF! -> #REF! | BG38: =Elect!#REF! -> #REF! | BH38: 0 | BI38: 0 | BJ38: 127385.62 | BK38: 6.2024355 | BL38: 3.1227323 | BM38: =Water!U43 -> 0 | BN38: =Water!W43 -> 0 | BO38: =Water!X43 -> 0 | BP38: =Water!Y43 -> 0 | BQ38: =Water!Z43 -> 0
A39: RFC MTD | B39: 784008.53 | C39: =Elect!#REF! -> #REF! | D39: 0 | E39: =Elect!#REF! -> #REF! | F39: 0 | G39: =Elect!#REF! -> #REF! | H39: 0 | I39: =Water!C44 -> 0 | J39: 0 | K39: =Water!E45 -> 0 | L39: 9 | M39: =Water!#REF! -> #REF! | N39: =Water!#REF! -> #REF! | O39: 0 | P39: =Water!H44 -> 0 | Q39: 0 | R39: =Water!O44 -> 0 | S39: 0 | T39: =Water!#REF! -> #REF! | U39: 0 | V39: =Water!#REF! -> #REF! | W39: 0 | X39: =Water!Q44 -> 0 | Y39: 9 | Z39: =Water!#REF! -> #REF! | AA39: 0 | AB39: 0 | AC39: 0 | AD39: =Water!#REF! -> #REF! | AE39: =Water!#REF! -> #REF! | AF39: =Water!#REF! -> #REF! | AG39: =Gas!#REF! -> #REF! | AH39: =Gas!#REF! -> #REF! | AI39: =Gas!#REF! -> #REF! | AJ39: =Gas!#REF! -> #REF! | AK39: =Gas!#REF! -> #REF! | AL39: =Gas!#REF! -> #REF! | AM39: =Gas!#REF! -> #REF! | AN39: =Gas!#REF! -> #REF! | ... AS39: =Gas!#REF! -> #REF! | AT39: =Elect!#REF! -> #REF! | AU39: =Elect!#REF! -> #REF! | AX39: 38.173558 | AY39: 19.219193 | AZ39: 208225.85 | BA39: 10.138565 | BB39: 5.1044505 | BC39: =Elect!#REF! -> #REF! | BD39: =Elect!#REF! -> #REF! | BE39: =Elect!#REF! -> #REF! | BF39: =Elect!#REF! -> #REF! | BG39: =Elect!#REF! -> #REF! | BH39: 0 | BI39: 0 | BJ39: 115057.98 | BK39: 6.2024355 | BL39: 3.1227323 | BM39: =Water!U44 -> 0 | BN39: =Water!W44 -> 0 | BO39: =Water!X44 -> #VALUE! | BP39: =Water!Y44 -> #VALUE! | BQ39: =Water!Z44 -> #VALUE!
A40: AVER RFC | B40: 28000.305 | C40: =Elect!#REF! -> #REF! | D40: 0 | E40: =Elect!#REF! -> #REF! | F40: 0 | G40: =Elect!#REF! -> #REF! | H40: 0 | I40: =Water!C45 -> 0 | J40: 0 | K40: =Water!E46 -> 0 | L40: 10 | M40: =Water!#REF! -> #REF! | N40: =Water!#REF! -> #REF! | O40: 0 | P40: =Water!H45 -> 0 | Q40: 0 | R40: =Water!O45 -> 0 | S40: 0 | T40: =Water!#REF! -> #REF! | U40: 0 | V40: =Water!#REF! -> #REF! | W40: 0 | X40: =Water!Q45 -> 0 | Y40: 10 | Z40: =Water!#REF! -> #REF! | AA40: 0 | AB40: 0 | AC40: 0 | AD40: =Water!#REF! -> #REF! | AE40: =Water!#REF! -> #REF! | AF40: =Water!#REF! -> #REF! | AG40: =Gas!#REF! -> #REF! | AH40: =Gas!#REF! -> #REF! | AI40: =Gas!#REF! -> #REF! | AJ40: =Gas!#REF! -> #REF! | AK40: =Gas!#REF! -> #REF! | AL40: =Gas!#REF! -> #REF! | AM40: =Gas!#REF! -> #REF! | AN40: =Gas!#REF! -> #REF! | ... AS40: =Gas!#REF! -> #REF! | AT40: =Elect!#REF! -> #REF! | AU40: =Elect!#REF! -> #REF! | AX40: 0 | AY40: 0 | AZ40: 7436.6375 | BA40: 0 | BB40: 0 | BC40: =Elect!#REF! -> #REF! | BD40: =Elect!#REF! -> #REF! | BE40: =Elect!#REF! -> #REF! | BF40: =Elect!#REF! -> #REF! | BG40: =Elect!#REF! -> #REF! | BH40: 1.1254646 | BI40: 0.57264868 | BJ40: 4109.2135 | BK40: 0 | BL40: 0 | BM40: =Water!U45 -> 0 | BN40: =Water!W45 -> 0 | BO40: =Water!X45 -> #VALUE! | BP40: =Water!Y45 -> 0 | BQ40: =Water!Z45 -> 0

Sheet Temp.
A2: HILTON INTERNATIONAL
A3: GULF, MIDDLE EAST AND ASIA SPECIFIC
A4: HOTEL:HILTON HURGHADA LONG BEACH RESORT | G4: =Elect!A1 -> February
A7: DATE | B7: MAX TEMP | C7: MIN TEMP | D7: MAX TEMP | E7: MIN TEMP | F7: DAY | G7: DD. C | H7: DD. H | I7: MTD | J7: MTD
B8: C | C8: C | D8: F | E8: F | F8: PARAMETER | I8: COOLING | J8: HEATING
A10: 1 | D10: =SUM((B10*9/5)+32) -> 32 | E10: =SUM((C10*9/5)+32) -> 32 | F10: =SUM(((B10+C10)/2)-18.33) -> -18.33 | G10: =SUM(0+(F10)+ABS(F10))/2 -> 0 | H10: =IF((SUM(0-(F10)+ABS(F10))/2)<18,SUM(0-(F10)+ABS(F10))/2,0) -> 0 | I10: =SUM(G10:G10) -> 0 | J10: =SUM(H10:H10) -> 0
A11: 2 | D11: =SUM((B11*9/5)+32) -> 32 | E11: =SUM((C11*9/5)+32) -> 32 | F11: =SUM(((B11+C11)/2)-18.33) -> -18.33 | G11: =SUM(0+(F11)+ABS(F11))/2 -> 0 | H11: =IF((SUM(0-(F11)+ABS(F11))/2)<18,SUM(0-(F11)+ABS(F11))/2,0) -> 0 | I11: =SUM(G10:G11) -> 0 | J11: =SUM(H10:H11) -> 0
A12: 3 | D12: =SUM((B12*9/5)+32) -> 32 | E12: =SUM((C12*9/5)+32) -> 32 | F12: =SUM(((B12+C12)/2)-18.33) -> -18.33 | G12: =SUM(0+(F12)+ABS(F12))/2 -> 0 | H12: =IF((SUM(0-(F12)+ABS(F12))/2)<18,SUM(0-(F12)+ABS(F12))/2,0) -> 0 | I12: =SUM(G10:G12) -> 0 | J12: =SUM(H10:H12) -> 0
A13: 4 | D13: =SUM((B13*9/5)+32) -> 32 | E13: =SUM((C13*9/5)+32) -> 32 | F13: =SUM(((B13+C13)/2)-18.33) -> -18.33 | G13: =SUM(0+(F13)+ABS(F13))/2 -> 0 | H13: =IF((SUM(0-(F13)+ABS(F13))/2)<18,SUM(0-(F13)+ABS(F13))/2,0) -> 0 | I13: =SUM(G10:G13) -> 0 | J13: =SUM(H10:H13) -> 0
A14: 5 | D14: =SUM((B14*9/5)+32) -> 32 | E14: =SUM((C14*9/5)+32) -> 32 | F14: =SUM(((B14+C14)/2)-18.33) -> -18.33 | G14: =SUM(0+(F14)+ABS(F14))/2 -> 0 | H14: =IF((SUM(0-(F14)+ABS(F14))/2)<18,SUM(0-(F14)+ABS(F14))/2,0) -> 0 | I14: =SUM(G10:G14) -> 0 | J14: =SUM(H10:H14) -> 0
A15: 6 | D15: =SUM((B15*9/5)+32) -> 32 | E15: =SUM((C15*9/5)+32) -> 32 | F15: =SUM(((B15+C15)/2)-18.33) -> -18.33 | G15: =SUM(0+(F15)+ABS(F15))/2 -> 0 | H15: =IF((SUM(0-(F15)+ABS(F15))/2)<18,SUM(0-(F15)+ABS(F15))/2,0) -> 0 | I15: =SUM(G10:G15) -> 0 | J15: =SUM(H10:H15) -> 0
A16: 7 | D16: =SUM((B16*9/5)+32) -> 32 | E16: =SUM((C16*9/5)+32) -> 32 | F16: =SUM(((B16+C16)/2)-18.33) -> -18.33 | G16: =SUM(0+(F16)+ABS(F16))/2 -> 0 | H16: =IF((SUM(0-(F16)+ABS(F16))/2)<18,SUM(0-(F16)+ABS(F16))/2,0) -> 0 | I16: =SUM(G10:G16) -> 0 | J16: =SUM(H10:H16) -> 0
A17: 8 | D17: =SUM((B17*9/5)+32) -> 32 | E17: =SUM((C17*9/5)+32) -> 32 | F17: =SUM(((B17+C17)/2)-18.33) -> -18.33 | G17: =SUM(0+(F17)+ABS(F17))/2 -> 0 | H17: =IF((SUM(0-(F17)+ABS(F17))/2)<18,SUM(0-(F17)+ABS(F17))/2,0) -> 0 | I17: =SUM(G10:G17) -> 0 | J17: =SUM(H10:H17) -> 0
A18: 9 | D18: =SUM((B18*9/5)+32) -> 32 | E18: =SUM((C18*9/5)+32) -> 32 | F18: =SUM(((B18+C18)/2)-18.33) -> -18.33 | G18: =SUM(0+(F18)+ABS(F18))/2 -> 0 | H18: =IF((SUM(0-(F18)+ABS(F18))/2)<18,SUM(0-(F18)+ABS(F18))/2,0) -> 0 | I18: =SUM(G10:G18) -> 0 | J18: =SUM(H10:H18) -> 0
A19: 10 | D19: =SUM((B19*9/5)+32) -> 32 | E19: =SUM((C19*9/5)+32) -> 32 | F19: =SUM(((B19+C19)/2)-18.33) -> -18.33 | G19: =SUM(0+(F19)+ABS(F19))/2 -> 0 | H19: =IF((SUM(0-(F19)+ABS(F19))/2)<18,SUM(0-(F19)+ABS(F19))/2,0) -> 0 | I19: =SUM(G10:G19) -> 0 | J19: =SUM(H10:H19) -> 0
A20: 11 | D20: =SUM((B20*9/5)+32) -> 32 | E20: =SUM((C20*9/5)+32) -> 32 | F20: =SUM(((B20+C20)/2)-18.33) -> -18.33 | G20: =SUM(0+(F20)+ABS(F20))/2 -> 0 | H20: =IF((SUM(0-(F20)+ABS(F20))/2)<18,SUM(0-(F20)+ABS(F20))/2,0) -> 0 | I20: =SUM(G10:G20) -> 0 | J20: =SUM(H10:H20) -> 0
A21: 12 | D21: =SUM((B21*9/5)+32) -> 32 | E21: =SUM((C21*9/5)+32) -> 32 | F21: =SUM(((B21+C21)/2)-18.33) -> -18.33 | G21: =SUM(0+(F21)+ABS(F21))/2 -> 0 | H21: =IF((SUM(0-(F21)+ABS(F21))/2)<18,SUM(0-(F21)+ABS(F21))/2,0) -> 0 | I21: =SUM(G10:G21) -> 0 | J21: =SUM(H10:H21) -> 0
A22: 13 | D22: =SUM((B22*9/5)+32) -> 32 | E22: =SUM((C22*9/5)+32) -> 32 | F22: =SUM(((B22+C22)/2)-18.33) -> -18.33 | G22: =SUM(0+(F22)+ABS(F22))/2 -> 0 | H22: =IF((SUM(0-(F22)+ABS(F22))/2)<18,SUM(0-(F22)+ABS(F22))/2,0) -> 0 | I22: =SUM(G10:G22) -> 0 | J22: =SUM(H10:H22) -> 0
A23: 14 | D23: =SUM((B23*9/5)+32) -> 32 | E23: =SUM((C23*9/5)+32) -> 32 | F23: =SUM(((B23+C23)/2)-18.33) -> -18.33 | G23: =SUM(0+(F23)+ABS(F23))/2 -> 0 | H23: =IF((SUM(0-(F23)+ABS(F23))/2)<18,SUM(0-(F23)+ABS(F23))/2,0) -> 0 | I23: =SUM(G10:G23) -> 0 | J23: =SUM(H10:H23) -> 0
A24: 15 | D24: =SUM((B24*9/5)+32) -> 32 | E24: =SUM((C24*9/5)+32) -> 32 | F24: =SUM(((B24+C24)/2)-18.33) -> -18.33 | G24: =SUM(0+(F24)+ABS(F24))/2 -> 0 | H24: =IF((SUM(0-(F24)+ABS(F24))/2)<18,SUM(0-(F24)+ABS(F24))/2,0) -> 0 | I24: =SUM(G11:G24) -> 0 | J24: =SUM(H11:H24) -> 0
A25: 16 | D25: =SUM((B25*9/5)+32) -> 32 | E25: =SUM((C25*9/5)+32) -> 32 | F25: =SUM(((B25+C25)/2)-18.33) -> -18.33 | G25: =SUM(0+(F25)+ABS(F25))/2 -> 0 | H25: =IF((SUM(0-(F25)+ABS(F25))/2)<18,SUM(0-(F25)+ABS(F25))/2,0) -> 0 | I25: =SUM(G12:G25) -> 0 | J25: =SUM(H12:H25) -> 0
A26: 17 | D26: =SUM((B26*9/5)+32) -> 32 | E26: =SUM((C26*9/5)+32) -> 32 | F26: =SUM(((B26+C26)/2)-18.33) -> -18.33 | G26: =SUM(0+(F26)+ABS(F26))/2 -> 0 | H26: =IF((SUM(0-(F26)+ABS(F26))/2)<18,SUM(0-(F26)+ABS(F26))/2,0) -> 0 | I26: =SUM(G13:G26) -> 0 | J26: =SUM(H13:H26) -> 0
A27: 18 | D27: =SUM((B27*9/5)+32) -> 32 | E27: =SUM((C27*9/5)+32) -> 32 | F27: =SUM(((B27+C27)/2)-18.33) -> -18.33 | G27: =SUM(0+(F27)+ABS(F27))/2 -> 0 | H27: =IF((SUM(0-(F27)+ABS(F27))/2)<18,SUM(0-(F27)+ABS(F27))/2,0) -> 0 | I27: =SUM(G14:G27) -> 0 | J27: =SUM(H14:H27) -> 0
A28: 19 | D28: =SUM((B28*9/5)+32) -> 32 | E28: =SUM((C28*9/5)+32) -> 32 | F28: =SUM(((B28+C28)/2)-18.33) -> -18.33 | G28: =SUM(0+(F28)+ABS(F28))/2 -> 0 | H28: =IF((SUM(0-(F28)+ABS(F28))/2)<18,SUM(0-(F28)+ABS(F28))/2,0) -> 0 | I28: =SUM(G15:G28) -> 0 | J28: =SUM(H15:H28) -> 0
A29: 20 | D29: =SUM((B29*9/5)+32) -> 32 | E29: =SUM((C29*9/5)+32) -> 32 | F29: =SUM(((B29+C29)/2)-18.33) -> -18.33 | G29: =SUM(0+(F29)+ABS(F29))/2 -> 0 | H29: =IF((SUM(0-(F29)+ABS(F29))/2)<18,SUM(0-(F29)+ABS(F29))/2,0) -> 0 | I29: =SUM(G16:G29) -> 0 | J29: =SUM(H16:H29) -> 0
A30: 21 | D30: =SUM((B30*9/5)+32) -> 32 | E30: =SUM((C30*9/5)+32) -> 32 | F30: =SUM(((B30+C30)/2)-18.33) -> -18.33 | G30: =SUM(0+(F30)+ABS(F30))/2 -> 0 | H30: =IF((SUM(0-(F30)+ABS(F30))/2)<18,SUM(0-(F30)+ABS(F30))/2,0) -> 0 | I30: =SUM(G17:G30) -> 0 | J30: =SUM(H17:H30) -> 0
A31: 22 | D31: =SUM((B31*9/5)+32) -> 32 | E31: =SUM((C31*9/5)+32) -> 32 | F31: =SUM(((B31+C31)/2)-18.33) -> -18.33 | G31: =SUM(0+(F31)+ABS(F31))/2 -> 0 | H31: =IF((SUM(0-(F31)+ABS(F31))/2)<18,SUM(0-(F31)+ABS(F31))/2,0) -> 0 | I31: =SUM(G18:G31) -> 0 | J31: =SUM(H18:H31) -> 0
A32: 23 | D32: =SUM((B32*9/5)+32) -> 32 | E32: =SUM((C32*9/5)+32) -> 32 | F32: =SUM(((B32+C32)/2)-18.33) -> -18.33 | G32: =SUM(0+(F32)+ABS(F32))/2 -> 0 | H32: =IF((SUM(0-(F32)+ABS(F32))/2)<18,SUM(0-(F32)+ABS(F32))/2,0) -> 0 | I32: =SUM(G19:G32) -> 0 | J32: =SUM(H19:H32) -> 0
A33: 24 | D33: =SUM((B33*9/5)+32) -> 32 | E33: =SUM((C33*9/5)+32) -> 32 | F33: =SUM(((B33+C33)/2)-18.33) -> -18.33 | G33: =SUM(0+(F33)+ABS(F33))/2 -> 0 | H33: =IF((SUM(0-(F33)+ABS(F33))/2)<18,SUM(0-(F33)+ABS(F33))/2,0) -> 0 | I33: =SUM(G20:G33) -> 0 | J33: =SUM(H20:H33) -> 0
A34: 25 | D34: =SUM((B34*9/5)+32) -> 32 | E34: =SUM((C34*9/5)+32) -> 32 | F34: =SUM(((B34+C34)/2)-18.33) -> -18.33 | G34: =SUM(0+(F34)+ABS(F34))/2 -> 0 | H34: =IF((SUM(0-(F34)+ABS(F34))/2)<18,SUM(0-(F34)+ABS(F34))/2,0) -> 0 | I34: =SUM(G21:G34) -> 0 | J34: =SUM(H21:H34) -> 0
... A40: 31 | D40: =SUM((B40*9/5)+32) -> 32 | E40: =SUM((C40*9/5)+32) -> 32 | F40: =SUM(((B40+C40)/2)-18.33) -> -18.33 | G40: =SUM(0+(F40)+ABS(F40))/2 -> 0 | H40: =IF((SUM(0-(F40)+ABS(F40))/2)<18,SUM(0-(F40)+ABS(F40))/2,0) -> 0 | I40: =SUM(G27:G40) -> 0 | J40: =SUM(H27:H40) -> 0
E42: =SUM(G10:G40) -> 0 | F42: deg c
E44: =SUM(H10:H40) -> 0 | F44: deg c

Sheet M-Rep
B3: =Elect!A1 -> February
D4: Y.T.D
A5: Energy breakdown | C5: 2009 | D5: 2005 | E5: 2006
A6: Elect.
A7: Chillers KWH | C7: N/A | D7: N/A | E7: N/A
A8: Laundry KWH | C8: N/A | D8: N/A | E8: N/A
A9: Kitchen KWH | C9: N/A | D9: N/A | E9: N/A
A10: Gas
A11: Kit M3 | C11: =Gas!#REF!/1000 -> #REF!
A12: Laundry M3 | C12: N/A | D12: 0 | E12: #REF!
A13: Water | D13: N/A | E13: N/A
A14: Laundry HW | C14: N/A
A15: Laundry CW | C15: N/A
A16: Kit HW | C16: N/A
A17: kIt CW | C17: N/A | D17: N/A | E17: N/A
A18: Dmstc HW | C18: N/A | D18: N/A | E18: N/A
A19: Dmstc CW | C19: N/A | D19: N/A | E19: N/A
A20: S.Pool MKUP | C20: =#REF! -> #REF! | D20: N/A | E20: N/A
A21: Ctower MKUP | C21: N/A | D21: N/A | E21: N/A
A22: Gardens Irrigat. | C22: =Water!S38 -> 0 | D22: N/A | E22: N/A
A23: Swage water treatment | C23: =Water!#REF! -> #REF! | D23: 27437 | E23: #REF!
A24: Utilities consumption | D24: N/A | E24: N/A
A25: Elect. Kwh | C25: =Elect!J34 -> 0 | D25: 12266 | E25: 814
A26: M.D (9.5 LE) | D26: 147773 | E26: #REF!
A27: Water M3 | C27: =Water!H38 -> 8787
A28: Fuel Ltr | C28: =Gas!#REF!*1000 -> #REF! | D28: 12876868 | E28: 14500800
A29: Gas M3/ Boilers, chillers,..etc | C29: N/A | D29: 28880 | E29: 32980
A30: Gas M3 Kitchen | C30: =Gas!#REF!/1000 -> #REF! | D30: 244283 | E30: 252530.66
A31: Total Energy | D31: 620770 | E31: #REF!
A32: Control Parameters | D32: #REF! | E32: N/A
A33: No. of Rooms % occ. | C33: =YTD!Q4 -> 0 | D33: 39.395 | E33: #REF!
A34: No. of Occ. Rooms | C34: =YTD!Q5 -> 0
A35: guest count | C35: =YTD!Q6 -> 0
A36: Food covers | D36: #REF! | E36: #REF!
A37: Laundry W. Kg | D37: 0.8807 | E37: 0.46351998
A38: DDC | C38: =Temp.!E42 -> 0 | D38: 196150 | E38: 237021
A39: DDH | C39: =Temp.!E44 -> 0 | D39: 400070 | E39: 466105
A40: Utilities Entergy cost | D40: 1583714 | E40: 1940567
A41: Elect. | C41: =Elect!#REF! -> #REF! | D41: 1690339 | E41: 3118671.6
A42: M.D | C42: =C26*Elect!#REF! -> #REF! | D42: 2381.51 | E42: 2480.24
A43: Water | C43: =Water!X38 -> 35148 | D43: 112 | E43: 97.53
A44: Fuel | C44: =Gas!#REF! -> #REF!
A45: Gas Boilers, chillers,etc.. | C45: N/A | D45: 2138156.8 | E45: #REF!
A46: Gas Kitchen | C46: =C30*Gas!M2*1000 -> #REF! | D46: 223044.2 | E46: #REF!
A47: TOTAL LE | C47: =SUM(C41:C46) -> #REF! | D47: 1330535.7 | E47: 1382037.4
A48: No. of POMEC Staff | D48: 330278 | E48: #REF!
A49: Hotel Age | C49: 6 | D49: N/A | E49: N/A
A50: No. of rooms | C50: =31*912 -> 28272 | D50: 36597.525 | E50: #REF!
A51: Building Volume | C51: 243175 | D51: =SUM(D45:D50) -> 4058612.3 | E51: =SUM(E45:E50) -> #REF!
A52: Building area | C52: 75064
A53: US$ Rate | C53: 5.59402 | D53: 61 | E53: 72
A54: Total R&M MTD | C54: =YTD!Q65 -> 0 | D54: #REF! | E54: 243175 | F54: =YTD!Q64 -> 0
A55: Staff - HLP | D55: #REF! | E55: 75064
A56: Staff - R&M | D56: 5.755 | E56: 5.65951
A57: Staff - Grounds

Sheet YTD
A1: =Elect!A1 -> February | H1: Actual 2014
C3: JAN | D3: FEB | E3: MAR | F3: APR | G3: MAY | H3: JUN | I3: JUL | J3: AUG | K3: SEP | L3: OCT | M3: NOV | N3: DEC | O3: TOTAL | P3: YTD | Q3: Month Act
A4: Occ Room % | O4: =SUM(C4:N4) -> 0 | P4: =(IF($A$1=39814,C4,(IF($A$1=39845,SUM(C4:D4),(IF($A$1=39873,SUM(C4:E4),(IF($A$1=39904,SUM(C4:F4),(IF($A$1=39934,SUM(C4:G4),(IF($A$1=39965,SUM(C4:H4),(IF($A$1=39995,SUM(C4:I4),0)))))))))))))+(IF($A$1=40026,SUM(C4:J4),(IF($A$1=40057,SUM(C4:K4),(IF($A$1=40087,SUM(C4:L4),(IF($A$1=40118,SUM(C4:M4))))))))))+(IF($A$1=40148,SUM(C4:N4),0)) -> 0 | Q4: =(IF($A$1=39814,C4,(IF($A$1=39845,D4,(IF($A$1=39873,E4,(IF($A$1=39904,F4,(IF($A$1=39934,G4,(IF($A$1=39965,H4,(IF($A$1=39995,I4,0)))))))))))))+(IF($A$1=40026,J4,(IF($A$1=40057,K4,(IF($A$1=40087,L4,(IF($A$1=40118,M4)))))))))+(IF($A$1=40148,N4,0)) -> 0 | S4: 40179 | DE4: 1
A5: Occ Room | C5: 25072 | D5: =Elect!BP34 -> 0 | O5: =SUM(C5:N5) -> 25072 | P5: =(IF($A$1=40179,C5,(IF($A$1=40210,SUM(C5:D5),(IF($A$1=40238,SUM(C5:E5),(IF($A$1=40269,SUM(C5:F5),(IF($A$1=40299,SUM(C5:G5),(IF($A$1=40330,SUM(C5:H5),(IF($A$1=40360,SUM(C5:I5),0)))))))))))))+(IF($A$1=40391,SUM(C5:J5),(IF($A$1=40422,SUM(C5:K5),(IF($A$1=40452,SUM(C5:L5),(IF($A$1=40483,SUM(C5:M5))))))))))+(IF($A$1=40513,SUM(C5:N5),0)) -> 0 | Q5: =(IF($A$1=40179,C5,(IF($A$1=40210,D5,(IF($A$1=40238,E5,(IF($A$1=40269,F5,(IF($A$1=40299,G5,(IF($A$1=40330,H5,(IF($A$1=40360,I5,0)))))))))))))+(IF($A$1=40391,J5,(IF($A$1=40422,K5,(IF($A$1=40452,L5,(IF($A$1=40483,M5)))))))))+(IF($A$1=40513,N5,0)) -> 0 | S5: 40210 | DE5: 2
A6: Number of Guest | C6: 50662 | D6: =Elect!BR34 -> 0 | O6: =SUM(C6:N6) -> 50662 | P6: =(IF($A$1=40179,C6,(IF($A$1=40210,SUM(C6:D6),(IF($A$1=40238,SUM(C6:E6),(IF($A$1=40269,SUM(C6:F6),(IF($A$1=40299,SUM(C6:G6),(IF($A$1=40330,SUM(C6:H6),(IF($A$1=40360,SUM(C6:I6),0)))))))))))))+(IF($A$1=40391,SUM(C6:J6),(IF($A$1=40422,SUM(C6:K6),(IF($A$1=40452,SUM(C6:L6),(IF($A$1=40483,SUM(C6:M6))))))))))+(IF($A$1=40513,SUM(C6:N6),0)) -> 0 | Q6: =(IF($A$1=40179,C6,(IF($A$1=40210,D6,(IF($A$1=40238,E6,(IF($A$1=40269,F6,(IF($A$1=40299,G6,(IF($A$1=40330,H6,(IF($A$1=40360,I6,0)))))))))))))+(IF($A$1=40391,J6,(IF($A$1=40422,K6,(IF($A$1=40452,L6,(IF($A$1=40483,M6)))))))))+(IF($A$1=40513,N6,0)) -> 0 | S6: 40238 | DE6: 3
A7: PAY & REL. EXP. | O7: =SUM(C7:N7) -> 0 | P7: =(IF($A$1=40179,C7,(IF($A$1=40210,SUM(C7:D7),(IF($A$1=40238,SUM(C7:E7),(IF($A$1=40269,SUM(C7:F7),(IF($A$1=40299,SUM(C7:G7),(IF($A$1=40330,SUM(C7:H7),(IF($A$1=40360,SUM(C7:I7),0)))))))))))))+(IF($A$1=40391,SUM(C7:J7),(IF($A$1=40422,SUM(C7:K7),(IF($A$1=40452,SUM(C7:L7),(IF($A$1=40483,SUM(C7:M7))))))))))+(IF($A$1=40513,SUM(C7:N7),0)) -> 0 | Q7: =(IF($A$1=40179,C7,(IF($A$1=40210,D7,(IF($A$1=40238,E7,(IF($A$1=40269,F7,(IF($A$1=40299,G7,(IF($A$1=40330,H7,(IF($A$1=40360,I7,0)))))))))))))+(IF($A$1=40391,J7,(IF($A$1=40422,K7,(IF($A$1=40452,L7,(IF($A$1=40483,M7)))))))))+(IF($A$1=40513,N7,0)) -> 0
A8: SALARIES | B8: 53241001 | O8: =SUM(C8:N8) -> 0 | P8: =(IF($A$1=40179,C8,(IF($A$1=40210,SUM(C8:D8),(IF($A$1=40238,SUM(C8:E8),(IF($A$1=40269,SUM(C8:F8),(IF($A$1=40299,SUM(C8:G8),(IF($A$1=40330,SUM(C8:H8),(IF($A$1=40360,SUM(C8:I8),0)))))))))))))+(IF($A$1=40391,SUM(C8:J8),(IF($A$1=40422,SUM(C8:K8),(IF($A$1=40452,SUM(C8:L8),(IF($A$1=40483,SUM(C8:M8))))))))))+(IF($A$1=40513,SUM(C8:N8),0)) -> 0 | Q8: =(IF($A$1=40179,C8,(IF($A$1=40210,D8,(IF($A$1=40238,E8,(IF($A$1=40269,F8,(IF($A$1=40299,G8,(IF($A$1=40330,H8,(IF($A$1=40360,I8,0)))))))))))))+(IF($A$1=40391,J8,(IF($A$1=40422,K8,(IF($A$1=40452,L8,(IF($A$1=40483,M8)))))))))+(IF($A$1=40513,N8,0)) -> 0
A9: EXTRA WAGES | B9: 53242099 | O9: =SUM(C9:N9) -> 0 | P9: =(IF($A$1=40179,C9,(IF($A$1=40210,SUM(C9:D9),(IF($A$1=40238,SUM(C9:E9),(IF($A$1=40269,SUM(C9:F9),(IF($A$1=40299,SUM(C9:G9),(IF($A$1=40330,SUM(C9:H9),(IF($A$1=40360,SUM(C9:I9),0)))))))))))))+(IF($A$1=40391,SUM(C9:J9),(IF($A$1=40422,SUM(C9:K9),(IF($A$1=40452,SUM(C9:L9),(IF($A$1=40483,SUM(C9:M9))))))))))+(IF($A$1=40513,SUM(C9:N9),0)) -> 0 | Q9: =(IF($A$1=40179,C9,(IF($A$1=40210,D9,(IF($A$1=40238,E9,(IF($A$1=40269,F9,(IF($A$1=40299,G9,(IF($A$1=40330,H9,(IF($A$1=40360,I9,0)))))))))))))+(IF($A$1=40391,J9,(IF($A$1=40422,K9,(IF($A$1=40452,L9,(IF($A$1=40483,M9)))))))))+(IF($A$1=40513,N9,0)) -> 0
A10: SERVICE | B10: 53243001 | O10: =SUM(C10:N10) -> 0 | P10: =(IF($A$1=40179,C10,(IF($A$1=40210,SUM(C10:D10),(IF($A$1=40238,SUM(C10:E10),(IF($A$1=40269,SUM(C10:F10),(IF($A$1=40299,SUM(C10:G10),(IF($A$1=40330,SUM(C10:H10),(IF($A$1=40360,SUM(C10:I10),0)))))))))))))+(IF($A$1=40391,SUM(C10:J10),(IF($A$1=40422,SUM(C10:K10),(IF($A$1=40452,SUM(C10:L10),(IF($A$1=40483,SUM(C10:M10))))))))))+(IF($A$1=40513,SUM(C10:N10),0)) -> 0 | Q10: =(IF($A$1=40179,C10,(IF($A$1=40210,D10,(IF($A$1=40238,E10,(IF($A$1=40269,F10,(IF($A$1=40299,G10,(IF($A$1=40330,H10,(IF($A$1=40360,I10,0)))))))))))))+(IF($A$1=40391,J10,(IF($A$1=40422,K10,(IF($A$1=40452,L10,(IF($A$1=40483,M10)))))))))+(IF($A$1=40513,N10,0)) -> 0
A11: RELATED EXP. | B11: 53244001 | O11: =SUM(C11:N11) -> 0 | P11: =(IF($A$1=40179,C11,(IF($A$1=40210,SUM(C11:D11),(IF($A$1=40238,SUM(C11:E11),(IF($A$1=40269,SUM(C11:F11),(IF($A$1=40299,SUM(C11:G11),(IF($A$1=40330,SUM(C11:H11),(IF($A$1=40360,SUM(C11:I11),0)))))))))))))+(IF($A$1=40391,SUM(C11:J11),(IF($A$1=40422,SUM(C11:K11),(IF($A$1=40452,SUM(C11:L11),(IF($A$1=40483,SUM(C11:M11))))))))))+(IF($A$1=40513,SUM(C11:N11),0)) -> 0 | Q11: =(IF($A$1=40179,C11,(IF($A$1=40210,D11,(IF($A$1=40238,E11,(IF($A$1=40269,F11,(IF($A$1=40299,G11,(IF($A$1=40330,H11,(IF($A$1=40360,I11,0)))))))))))))+(IF($A$1=40391,J11,(IF($A$1=40422,K11,(IF($A$1=40452,L11,(IF($A$1=40483,M11)))))))))+(IF($A$1=40513,N11,0)) -> 0
A12: EMPL. MEALS | B12: 53245001 | O12: =SUM(C12:N12) -> 0 | P12: =(IF($A$1=40179,C12,(IF($A$1=40210,SUM(C12:D12),(IF($A$1=40238,SUM(C12:E12),(IF($A$1=40269,SUM(C12:F12),(IF($A$1=40299,SUM(C12:G12),(IF($A$1=40330,SUM(C12:H12),(IF($A$1=40360,SUM(C12:I12),0)))))))))))))+(IF($A$1=40391,SUM(C12:J12),(IF($A$1=40422,SUM(C12:K12),(IF($A$1=40452,SUM(C12:L12),(IF($A$1=40483,SUM(C12:M12))))))))))+(IF($A$1=40513,SUM(C12:N12),0)) -> 0 | Q12: =(IF($A$1=40179,C12,(IF($A$1=40210,D12,(IF($A$1=40238,E12,(IF($A$1=40269,F12,(IF($A$1=40299,G12,(IF($A$1=40330,H12,(IF($A$1=40360,I12,0)))))))))))))+(IF($A$1=40391,J12,(IF($A$1=40422,K12,(IF($A$1=40452,L12,(IF($A$1=40483,M12)))))))))+(IF($A$1=40513,N12,0)) -> 0
O13: =SUM(C13:N13) -> 0 | P13: =(IF($A$1=40179,C13,(IF($A$1=40210,SUM(C13:D13),(IF($A$1=40238,SUM(C13:E13),(IF($A$1=40269,SUM(C13:F13),(IF($A$1=40299,SUM(C13:G13),(IF($A$1=40330,SUM(C13:H13),(IF($A$1=40360,SUM(C13:I13),0)))))))))))))+(IF($A$1=40391,SUM(C13:J13),(IF($A$1=40422,SUM(C13:K13),(IF($A$1=40452,SUM(C13:L13),(IF($A$1=40483,SUM(C13:M13))))))))))+(IF($A$1=40513,SUM(C13:N13),0)) -> 0 | Q13: =(IF($A$1=40179,C13,(IF($A$1=40210,D13,(IF($A$1=40238,E13,(IF($A$1=40269,F13,(IF($A$1=40299,G13,(IF($A$1=40330,H13,(IF($A$1=40360,I13,0)))))))))))))+(IF($A$1=40391,J13,(IF($A$1=40422,K13,(IF($A$1=40452,L13,(IF($A$1=40483,M13)))))))))+(IF($A$1=40513,N13,0)) -> 0
A14: TOTAL PAY & REL. | C14: 147832.84 | D14: 158624 | O14: =SUM(C14:N14) -> 306456.84 | P14: =(IF($A$1=40179,C14,(IF($A$1=40210,SUM(C14:D14),(IF($A$1=40238,SUM(C14:E14),(IF($A$1=40269,SUM(C14:F14),(IF($A$1=40299,SUM(C14:G14),(IF($A$1=40330,SUM(C14:H14),(IF($A$1=40360,SUM(C14:I14),0)))))))))))))+(IF($A$1=40391,SUM(C14:J14),(IF($A$1=40422,SUM(C14:K14),(IF($A$1=40452,SUM(C14:L14),(IF($A$1=40483,SUM(C14:M14))))))))))+(IF($A$1=40513,SUM(C14:N14),0)) -> 0 | Q14: =(IF($A$1=40179,C14,(IF($A$1=40210,D14,(IF($A$1=40238,E14,(IF($A$1=40269,F14,(IF($A$1=40299,G14,(IF($A$1=40330,H14,(IF($A$1=40360,I14,0)))))))))))))+(IF($A$1=40391,J14,(IF($A$1=40422,K14,(IF($A$1=40452,L14,(IF($A$1=40483,M14)))))))))+(IF($A$1=40513,N14,0)) -> 0 | S14: 40269 | DE14: 4
A15: ELECRICITY | B15: 53257511 | C15: 267068.09 | D15: 312865.7 | O15: =SUM(C15:N15) -> 579933.79 | P15: =(IF($A$1=40179,C15,(IF($A$1=40210,SUM(C15:D15),(IF($A$1=40238,SUM(C15:E15),(IF($A$1=40269,SUM(C15:F15),(IF($A$1=40299,SUM(C15:G15),(IF($A$1=40330,SUM(C15:H15),(IF($A$1=40360,SUM(C15:I15),0)))))))))))))+(IF($A$1=40391,SUM(C15:J15),(IF($A$1=40422,SUM(C15:K15),(IF($A$1=40452,SUM(C15:L15),(IF($A$1=40483,SUM(C15:M15))))))))))+(IF($A$1=40513,SUM(C15:N15),0)) -> 0 | Q15: =(IF($A$1=40179,C15,(IF($A$1=40210,D15,(IF($A$1=40238,E15,(IF($A$1=40269,F15,(IF($A$1=40299,G15,(IF($A$1=40330,H15,(IF($A$1=40360,I15,0)))))))))))))+(IF($A$1=40391,J15,(IF($A$1=40422,K15,(IF($A$1=40452,L15,(IF($A$1=40483,M15)))))))))+(IF($A$1=40513,N15,0)) -> 0 | S15: 40299 | DE15: 5
A16: WATER & SEWAGE | B16: 53257551 | C16: 178948 | D16: 189620 | O16: =SUM(C16:N16) -> 368568 | P16: =(IF($A$1=40179,C16,(IF($A$1=40210,SUM(C16:D16),(IF($A$1=40238,SUM(C16:E16),(IF($A$1=40269,SUM(C16:F16),(IF($A$1=40299,SUM(C16:G16),(IF($A$1=40330,SUM(C16:H16),(IF($A$1=40360,SUM(C16:I16),0)))))))))))))+(IF($A$1=40391,SUM(C16:J16),(IF($A$1=40422,SUM(C16:K16),(IF($A$1=40452,SUM(C16:L16),(IF($A$1=40483,SUM(C16:M16))))))))))+(IF($A$1=40513,SUM(C16:N16),0)) -> 0 | Q16: =(IF($A$1=40179,C16,(IF($A$1=40210,D16,(IF($A$1=40238,E16,(IF($A$1=40269,F16,(IF($A$1=40299,G16,(IF($A$1=40330,H16,(IF($A$1=40360,I16,0)))))))))))))+(IF($A$1=40391,J16,(IF($A$1=40422,K16,(IF($A$1=40452,L16,(IF($A$1=40483,M16)))))))))+(IF($A$1=40513,N16,0)) -> 0 | S16: 40330 | DE16: 6
A17: FUEL | B17: 53257571 | C17: 82735 | D17: 123809 | O17: =SUM(C17:N17) -> 206544 | P17: =(IF($A$1=40179,C17,(IF($A$1=40210,SUM(C17:D17),(IF($A$1=40238,SUM(C17:E17),(IF($A$1=40269,SUM(C17:F17),(IF($A$1=40299,SUM(C17:G17),(IF($A$1=40330,SUM(C17:H17),(IF($A$1=40360,SUM(C17:I17),0)))))))))))))+(IF($A$1=40391,SUM(C17:J17),(IF($A$1=40422,SUM(C17:K17),(IF($A$1=40452,SUM(C17:L17),(IF($A$1=40483,SUM(C17:M17))))))))))+(IF($A$1=40513,SUM(C17:N17),0)) -> 0 | Q17: =(IF($A$1=40179,C17,(IF($A$1=40210,D17,(IF($A$1=40238,E17,(IF($A$1=40269,F17,(IF($A$1=40299,G17,(IF($A$1=40330,H17,(IF($A$1=40360,I17,0)))))))))))))+(IF($A$1=40391,J17,(IF($A$1=40422,K17,(IF($A$1=40452,L17,(IF($A$1=40483,M17)))))))))+(IF($A$1=40513,N17,0)) -> 0 | S17: 40360 | DE17: 7
A18: gas | B18: 0 | C18: 0 | D18: 0 | E18: 0 | F18: 0 | G18: 0 | H18: 0 | O18: =SUM(C18:N18) -> 0 | P18: =(IF($A$1=40179,C18,(IF($A$1=40210,SUM(C18:D18),(IF($A$1=40238,SUM(C18:E18),(IF($A$1=40269,SUM(C18:F18),(IF($A$1=40299,SUM(C18:G18),(IF($A$1=40330,SUM(C18:H18),(IF($A$1=40360,SUM(C18:I18),0)))))))))))))+(IF($A$1=40391,SUM(C18:J18),(IF($A$1=40422,SUM(C18:K18),(IF($A$1=40452,SUM(C18:L18),(IF($A$1=40483,SUM(C18:M18))))))))))+(IF($A$1=40513,SUM(C18:N18),0)) -> 0 | Q18: =(IF($A$1=40179,C18,(IF($A$1=40210,D18,(IF($A$1=40238,E18,(IF($A$1=40269,F18,(IF($A$1=40299,G18,(IF($A$1=40330,H18,(IF($A$1=40360,I18,0)))))))))))))+(IF($A$1=40391,J18,(IF($A$1=40422,K18,(IF($A$1=40452,L18,(IF($A$1=40483,M18)))))))))+(IF($A$1=40513,N18,0)) -> 0 | S18: 40391 | DE18: 8
A19: TOTAL ENERGY | C19: =SUM(C15:C18) -> 528751.09 | D19: =SUM(D15:D18) -> 626294.7 | E19: =SUM(E15:E18) -> 0 | F19: =SUM(F15:F18) -> 0 | G19: =SUM(G15:G18) -> 0 | H19: =SUM(H15:H18) -> 0 | I19: =SUM(I15:I18) -> 0 | J19: =SUM(J15:J18) -> 0 | ... O19: =SUM(O15:O18) -> 1155045.8 | P19: =(IF($A$1=40179,C19,(IF($A$1=40210,SUM(C19:D19),(IF($A$1=40238,SUM(C19:E19),(IF($A$1=40269,SUM(C19:F19),(IF($A$1=40299,SUM(C19:G19),(IF($A$1=40330,SUM(C19:H19),(IF($A$1=40360,SUM(C19:I19),0)))))))))))))+(IF($A$1=40391,SUM(C19:J19),(IF($A$1=40422,SUM(C19:K19),(IF($A$1=40452,SUM(C19:L19),(IF($A$1=40483,SUM(C19:M19))))))))))+(IF($A$1=40513,SUM(C19:N19),0)) -> 0 | Q19: =(IF($A$1=40179,C19,(IF($A$1=40210,D19,(IF($A$1=40238,E19,(IF($A$1=40269,F19,(IF($A$1=40299,G19,(IF($A$1=40330,H19,(IF($A$1=40360,I19,0)))))))))))))+(IF($A$1=40391,J19,(IF($A$1=40422,K19,(IF($A$1=40452,L19,(IF($A$1=40483,M19)))))))))+(IF($A$1=40513,N19,0)) -> 0 | S19: 40422 | DE19: 9
P20: =(IF($A$1=40179,C20,(IF($A$1=40210,SUM(C20:D20),(IF($A$1=40238,SUM(C20:E20),(IF($A$1=40269,SUM(C20:F20),(IF($A$1=40299,SUM(C20:G20),(IF($A$1=40330,SUM(C20:H20),(IF($A$1=40360,SUM(C20:I20),0)))))))))))))+(IF($A$1=40391,SUM(C20:J20),(IF($A$1=40422,SUM(C20:K20),(IF($A$1=40452,SUM(C20:L20),(IF($A$1=40483,SUM(C20:M20))))))))))+(IF($A$1=40513,SUM(C20:N20),0)) -> 0 | Q20: =(IF($A$1=40179,C20,(IF($A$1=40210,D20,(IF($A$1=40238,E20,(IF($A$1=40269,F20,(IF($A$1=40299,G20,(IF($A$1=40330,H20,(IF($A$1=40360,I20,0)))))))))))))+(IF($A$1=40391,J20,(IF($A$1=40422,K20,(IF($A$1=40452,L20,(IF($A$1=40483,M20)))))))))+(IF($A$1=40513,N20,0)) -> 0
A21: OTHER EXPENSES | P21: =(IF($A$1=40179,C21,(IF($A$1=40210,SUM(C21:D21),(IF($A$1=40238,SUM(C21:E21),(IF($A$1=40269,SUM(C21:F21),(IF($A$1=40299,SUM(C21:G21),(IF($A$1=40330,SUM(C21:H21),(IF($A$1=40360,SUM(C21:I21),0)))))))))))))+(IF($A$1=40391,SUM(C21:J21),(IF($A$1=40422,SUM(C21:K21),(IF($A$1=40452,SUM(C21:L21),(IF($A$1=40483,SUM(C21:M21))))))))))+(IF($A$1=40513,SUM(C21:N21),0)) -> 0 | Q21: =(IF($A$1=40179,C21,(IF($A$1=40210,D21,(IF($A$1=40238,E21,(IF($A$1=40269,F21,(IF($A$1=40299,G21,(IF($A$1=40330,H21,(IF($A$1=40360,I21,0)))))))))))))+(IF($A$1=40391,J21,(IF($A$1=40422,K21,(IF($A$1=40452,L21,(IF($A$1=40483,M21)))))))))+(IF($A$1=40513,N21,0)) -> 0
A22: P. & ST. | B22: 53251503 | C22: 2782.3724 | D22: 2209.2805 | E22: 3205.3202 | F22: 2604.6091 | G22: 3235.6987 | H22: 2482.8474 | I22: 3129.5287 | J22: 4085.8967 | K22: 4096.0234 | L22: 4111.0374 | M22: 4007.7194 | N22: 3115.8679 | O22: 39066.202 | P22: =(IF($A$1=40179,C22,(IF($A$1=40210,SUM(C22:D22),(IF($A$1=40238,SUM(C22:E22),(IF($A$1=40269,SUM(C22:F22),(IF($A$1=40299,SUM(C22:G22),(IF($A$1=40330,SUM(C22:H22),(IF($A$1=40360,SUM(C22:I22),0)))))))))))))+(IF($A$1=40391,SUM(C22:J22),(IF($A$1=40422,SUM(C22:K22),(IF($A$1=40452,SUM(C22:L22),(IF($A$1=40483,SUM(C22:M22))))))))))+(IF($A$1=40513,SUM(C22:N22),0)) -> 0 | Q22: =(IF($A$1=40179,C22,(IF($A$1=40210,D22,(IF($A$1=40238,E22,(IF($A$1=40269,F22,(IF($A$1=40299,G22,(IF($A$1=40330,H22,(IF($A$1=40360,I22,0)))))))))))))+(IF($A$1=40391,J22,(IF($A$1=40422,K22,(IF($A$1=40452,L22,(IF($A$1=40483,M22)))))))))+(IF($A$1=40513,N22,0)) -> 0
A23: POSTAGE | B23: 53251912 | C23: 0 | D23: 0 | E23: 0 | F23: 0 | G23: 0 | H23: 0 | I23: 0 | J23: 0 | K23: 0 | L23: 0 | M23: 0 | N23: 0 | O23: 0 | P23: =(IF($A$1=40179,C23,(IF($A$1=40210,SUM(C23:D23),(IF($A$1=40238,SUM(C23:E23),(IF($A$1=40269,SUM(C23:F23),(IF($A$1=40299,SUM(C23:G23),(IF($A$1=40330,SUM(C23:H23),(IF($A$1=40360,SUM(C23:I23),0)))))))))))))+(IF($A$1=40391,SUM(C23:J23),(IF($A$1=40422,SUM(C23:K23),(IF($A$1=40452,SUM(C23:L23),(IF($A$1=40483,SUM(C23:M23))))))))))+(IF($A$1=40513,SUM(C23:N23),0)) -> 0 | Q23: =(IF($A$1=40179,C23,(IF($A$1=40210,D23,(IF($A$1=40238,E23,(IF($A$1=40269,F23,(IF($A$1=40299,G23,(IF($A$1=40330,H23,(IF($A$1=40360,I23,0)))))))))))))+(IF($A$1=40391,J23,(IF($A$1=40422,K23,(IF($A$1=40452,L23,(IF($A$1=40483,M23)))))))))+(IF($A$1=40513,N23,0)) -> 0
A24: TAXICAB | B24: 53251919 | C24: 11276.363 | D24: 10009.133 | E24: 9350.2819 | F24: 12862.267 | G24: 10806.952 | H24: 11155.64 | I24: 12970.205 | J24: 10165.751 | K24: 10061.171 | L24: 10190.726 | M24: 10023.319 | N24: 7435.7374 | O24: 126307.55 | P24: =(IF($A$1=40179,C24,(IF($A$1=40210,SUM(C24:D24),(IF($A$1=40238,SUM(C24:E24),(IF($A$1=40269,SUM(C24:F24),(IF($A$1=40299,SUM(C24:G24),(IF($A$1=40330,SUM(C24:H24),(IF($A$1=40360,SUM(C24:I24),0)))))))))))))+(IF($A$1=40391,SUM(C24:J24),(IF($A$1=40422,SUM(C24:K24),(IF($A$1=40452,SUM(C24:L24),(IF($A$1=40483,SUM(C24:M24))))))))))+(IF($A$1=40513,SUM(C24:N24),0)) -> 0 | Q24: =(IF($A$1=40179,C24,(IF($A$1=40210,D24,(IF($A$1=40238,E24,(IF($A$1=40269,F24,(IF($A$1=40299,G24,(IF($A$1=40330,H24,(IF($A$1=40360,I24,0)))))))))))))+(IF($A$1=40391,J24,(IF($A$1=40422,K24,(IF($A$1=40452,L24,(IF($A$1=40483,M24)))))))))+(IF($A$1=40513,N24,0)) -> 0
A25: R&M DATA PROCESSING | B25: 53252601 | C25: 0 | D25: 0 | E25: 0 | F25: 0 | G25: 0 | H25: 0 | I25: 0 | J25: 0 | K25: 0 | L25: 0 | M25: 0 | N25: 0 | O25: 0 | P25: =(IF($A$1=40179,C25,(IF($A$1=40210,SUM(C25:D25),(IF($A$1=40238,SUM(C25:E25),(IF($A$1=40269,SUM(C25:F25),(IF($A$1=40299,SUM(C25:G25),(IF($A$1=40330,SUM(C25:H25),(IF($A$1=40360,SUM(C25:I25),0)))))))))))))+(IF($A$1=40391,SUM(C25:J25),(IF($A$1=40422,SUM(C25:K25),(IF($A$1=40452,SUM(C25:L25),(IF($A$1=40483,SUM(C25:M25))))))))))+(IF($A$1=40513,SUM(C25:N25),0)) -> 0 | Q25: =(IF($A$1=40179,C25,(IF($A$1=40210,D25,(IF($A$1=40238,E25,(IF($A$1=40269,F25,(IF($A$1=40299,G25,(IF($A$1=40330,H25,(IF($A$1=40360,I25,0)))))))))))))+(IF($A$1=40391,J25,(IF($A$1=40422,K25,(IF($A$1=40452,L25,(IF($A$1=40483,M25)))))))))+(IF($A$1=40513,N25,0)) -> 0
A26: R&M TELEPHONE | B26: 53252603 | C26: 29.374709 | D26: 15.100235 | E26: 33.209819 | F26: 40.453905 | G26: 120.16145 | H26: 0 | I26: 0 | J26: 1532.6831 | K26: 1577.9928 | L26: 1553.3432 | M26: 1485.7035 | N26: 1074.5974 | O26: 7462.6202 | P26: =(IF($A$1=40179,C26,(IF($A$1=40210,SUM(C26:D26),(IF($A$1=40238,SUM(C26:E26),(IF($A$1=40269,SUM(C26:F26),(IF($A$1=40299,SUM(C26:G26),(IF($A$1=40330,SUM(C26:H26),(IF($A$1=40360,SUM(C26:I26),0)))))))))))))+(IF($A$1=40391,SUM(C26:J26),(IF($A$1=40422,SUM(C26:K26),(IF($A$1=40452,SUM(C26:L26),(IF($A$1=40483,SUM(C26:M26))))))))))+(IF($A$1=40513,SUM(C26:N26),0)) -> 0 | Q26: =(IF($A$1=40179,C26,(IF($A$1=40210,D26,(IF($A$1=40238,E26,(IF($A$1=40269,F26,(IF($A$1=40299,G26,(IF($A$1=40330,H26,(IF($A$1=40360,I26,0)))))))))))))+(IF($A$1=40391,J26,(IF($A$1=40422,K26,(IF($A$1=40452,L26,(IF($A$1=40483,M26)))))))))+(IF($A$1=40513,N26,0)) -> 0
A27: R&M KITCHEN EQUIP. | B27: 53252703 | C27: 18610.98 | D27: 7247.7121 | E27: 5707.4428 | F27: 12222.516 | G27: 5623.8033 | H27: 6509.5046 | I27: 15311.566 | J27: 21902.26 | K27: 18614.51 | L27: 19231.518 | M27: 20212.925 | N27: 15102.401 | O27: 166297.14 | P27: =(IF($A$1=40179,C27,(IF($A$1=40210,SUM(C27:D27),(IF($A$1=40238,SUM(C27:E27),(IF($A$1=40269,SUM(C27:F27),(IF($A$1=40299,SUM(C27:G27),(IF($A$1=40330,SUM(C27:H27),(IF($A$1=40360,SUM(C27:I27),0)))))))))))))+(IF($A$1=40391,SUM(C27:J27),(IF($A$1=40422,SUM(C27:K27),(IF($A$1=40452,SUM(C27:L27),(IF($A$1=40483,SUM(C27:M27))))))))))+(IF($A$1=40513,SUM(C27:N27),0)) -> 0 | Q27: =(IF($A$1=40179,C27,(IF($A$1=40210,D27,(IF($A$1=40238,E27,(IF($A$1=40269,F27,(IF($A$1=40299,G27,(IF($A$1=40330,H27,(IF($A$1=40360,I27,0)))))))))))))+(IF($A$1=40391,J27,(IF($A$1=40422,K27,(IF($A$1=40452,L27,(IF($A$1=40483,M27)))))))))+(IF($A$1=40513,N27,0)) -> 0
A28: R&M LAUNDRY & VALET | B28: 53252704 | C28: 5275.9524 | D28: 3912.9834 | E28: 5168.9448 | F28: 3995.7884 | G28: 23112.428 | H28: 3000 | I28: 25530.47 | J28: 10393.274 | K28: 10317.215 | L28: 10411.437 | M28: 8163.5282 | N28: 8407.809 | O28: 117689.83 | P28: =(IF($A$1=40179,C28,(IF($A$1=40210,SUM(C28:D28),(IF($A$1=40238,SUM(C28:E28),(IF($A$1=40269,SUM(C28:F28),(IF($A$1=40299,SUM(C28:G28),(IF($A$1=40330,SUM(C28:H28),(IF($A$1=40360,SUM(C28:I28),0)))))))))))))+(IF($A$1=40391,SUM(C28:J28),(IF($A$1=40422,SUM(C28:K28),(IF($A$1=40452,SUM(C28:L28),(IF($A$1=40483,SUM(C28:M28))))))))))+(IF($A$1=40513,SUM(C28:N28),0)) -> 0 | Q28: =(IF($A$1=40179,C28,(IF($A$1=40210,D28,(IF($A$1=40238,E28,(IF($A$1=40269,F28,(IF($A$1=40299,G28,(IF($A$1=40330,H28,(IF($A$1=40360,I28,0)))))))))))))+(IF($A$1=40391,J28,(IF($A$1=40422,K28,(IF($A$1=40452,L28,(IF($A$1=40483,M28)))))))))+(IF($A$1=40513,N28,0)) -> 0
A29: R&M MINIBARS | B29: 53252705 | C29: 79.899208 | D29: 0 | E29: 0 | F29: 0 | G29: 0 | H29: 0 | I29: 0 | J29: 95.285728 | K29: 102.18196 | L29: 111.19935 | M29: 111.86032 | N29: 108.77325 | O29: 609.19982 | P29: =(IF($A$1=40179,C29,(IF($A$1=40210,SUM(C29:D29),(IF($A$1=40238,SUM(C29:E29),(IF($A$1=40269,SUM(C29:F29),(IF($A$1=40299,SUM(C29:G29),(IF($A$1=40330,SUM(C29:H29),(IF($A$1=40360,SUM(C29:I29),0)))))))))))))+(IF($A$1=40391,SUM(C29:J29),(IF($A$1=40422,SUM(C29:K29),(IF($A$1=40452,SUM(C29:L29),(IF($A$1=40483,SUM(C29:M29))))))))))+(IF($A$1=40513,SUM(C29:N29),0)) -> 0 | Q29: =(IF($A$1=40179,C29,(IF($A$1=40210,D29,(IF($A$1=40238,E29,(IF($A$1=40269,F29,(IF($A$1=40299,G29,(IF($A$1=40330,H29,(IF($A$1=40360,I29,0)))))))))))))+(IF($A$1=40391,J29,(IF($A$1=40422,K29,(IF($A$1=40452,L29,(IF($A$1=40483,M29)))))))))+(IF($A$1=40513,N29,0)) -> 0
A30: R&M REFRIGERATION | B30: 53252706 | C30: 0 | D30: 0 | E30: 0 | F30: 0 | G30: 274.098 | H30: 0 | I30: 0 | J30: 3304.6661 | K30: 3307.9378 | L30: 3323.0619 | M30: 3118.4419 | N30: 2387.0892 | O30: 15715.295 | P30: =(IF($A$1=40179,C30,(IF($A$1=40210,SUM(C30:D30),(IF($A$1=40238,SUM(C30:E30),(IF($A$1=40269,SUM(C30:F30),(IF($A$1=40299,SUM(C30:G30),(IF($A$1=40330,SUM(C30:H30),(IF($A$1=40360,SUM(C30:I30),0)))))))))))))+(IF($A$1=40391,SUM(C30:J30),(IF($A$1=40422,SUM(C30:K30),(IF($A$1=40452,SUM(C30:L30),(IF($A$1=40483,SUM(C30:M30))))))))))+(IF($A$1=40513,SUM(C30:N30),0)) -> 0 | Q30: =(IF($A$1=40179,C30,(IF($A$1=40210,D30,(IF($A$1=40238,E30,(IF($A$1=40269,F30,(IF($A$1=40299,G30,(IF($A$1=40330,H30,(IF($A$1=40360,I30,0)))))))))))))+(IF($A$1=40391,J30,(IF($A$1=40422,K30,(IF($A$1=40452,L30,(IF($A$1=40483,M30)))))))))+(IF($A$1=40513,N30,0)) -> 0
A31: R&M SPRINGS , MATTRESS | B31: 53252707 | C31: 0 | D31: 0 | E31: 0 | F31: 0 | G31: 0 | H31: 0 | I31: 0 | J31: 43.311695 | K31: 52.252139 | L31: 49.058539 | M31: 49.35014 | N31: 47.522294 | O31: 241.49481 | P31: =(IF($A$1=40179,C31,(IF($A$1=40210,SUM(C31:D31),(IF($A$1=40238,SUM(C31:E31),(IF($A$1=40269,SUM(C31:F31),(IF($A$1=40299,SUM(C31:G31),(IF($A$1=40330,SUM(C31:H31),(IF($A$1=40360,SUM(C31:I31),0)))))))))))))+(IF($A$1=40391,SUM(C31:J31),(IF($A$1=40422,SUM(C31:K31),(IF($A$1=40452,SUM(C31:L31),(IF($A$1=40483,SUM(C31:M31))))))))))+(IF($A$1=40513,SUM(C31:N31),0)) -> 0 | Q31: =(IF($A$1=40179,C31,(IF($A$1=40210,D31,(IF($A$1=40238,E31,(IF($A$1=40269,F31,(IF($A$1=40299,G31,(IF($A$1=40330,H31,(IF($A$1=40360,I31,0)))))))))))))+(IF($A$1=40391,J31,(IF($A$1=40422,K31,(IF($A$1=40452,L31,(IF($A$1=40483,M31)))))))))+(IF($A$1=40513,N31,0)) -> 0
A32: R&M T.V & VIDEOS&Singn&Elevator | B32: 53252708 | C32: 26271.989 | D32: 24991.55 | E32: 25766.444 | F32: 14083.458 | G32: 32760.542 | H32: 30820.265 | I32: 27093.718 | J32: 32921.826 | K32: 34279.573 | L32: 31548.543 | M32: 31011.051 | N32: 25248.971 | O32: 336797.93 | P32: =(IF($A$1=40179,C32,(IF($A$1=40210,SUM(C32:D32),(IF($A$1=40238,SUM(C32:E32),(IF($A$1=40269,SUM(C32:F32),(IF($A$1=40299,SUM(C32:G32),(IF($A$1=40330,SUM(C32:H32),(IF($A$1=40360,SUM(C32:I32),0)))))))))))))+(IF($A$1=40391,SUM(C32:J32),(IF($A$1=40422,SUM(C32:K32),(IF($A$1=40452,SUM(C32:L32),(IF($A$1=40483,SUM(C32:M32))))))))))+(IF($A$1=40513,SUM(C32:N32),0)) -> 0 | Q32: =(IF($A$1=40179,C32,(IF($A$1=40210,D32,(IF($A$1=40238,E32,(IF($A$1=40269,F32,(IF($A$1=40299,G32,(IF($A$1=40330,H32,(IF($A$1=40360,I32,0)))))))))))))+(IF($A$1=40391,J32,(IF($A$1=40422,K32,(IF($A$1=40452,L32,(IF($A$1=40483,M32)))))))))+(IF($A$1=40513,N32,0)) -> 0
A33: R&M A/C | B33: 53252801 | C33: 7155.9338 | D33: 13666.574 | E33: 13288.173 | F33: 18794.657 | G33: 26304.825 | H33: 33052.365 | I33: 42520.56 | J33: 22963.856 | K33: 23657.049 | L33: 21575.007 | M33: 16832.206 | N33: 15606.795 | O33: 255418 | P33: =(IF($A$1=40179,C33,(IF($A$1=40210,SUM(C33:D33),(IF($A$1=40238,SUM(C33:E33),(IF($A$1=40269,SUM(C33:F33),(IF($A$1=40299,SUM(C33:G33),(IF($A$1=40330,SUM(C33:H33),(IF($A$1=40360,SUM(C33:I33),0)))))))))))))+(IF($A$1=40391,SUM(C33:J33),(IF($A$1=40422,SUM(C33:K33),(IF($A$1=40452,SUM(C33:L33),(IF($A$1=40483,SUM(C33:M33))))))))))+(IF($A$1=40513,SUM(C33:N33),0)) -> 0 | Q33: =(IF($A$1=40179,C33,(IF($A$1=40210,D33,(IF($A$1=40238,E33,(IF($A$1=40269,F33,(IF($A$1=40299,G33,(IF($A$1=40330,H33,(IF($A$1=40360,I33,0)))))))))))))+(IF($A$1=40391,J33,(IF($A$1=40422,K33,(IF($A$1=40452,L33,(IF($A$1=40483,M33)))))))))+(IF($A$1=40513,N33,0)) -> 0
... A47: TRAVEL EXP. | B47: 53254201 | C47: 3803.5222 | D47: 2648.7794 | E47: 2552.6776 | F47: 3045.5154 | G47: 2357.4996 | H47: 2726.555 | I47: 2399.97 | J47: 5298.415 | K47: 4970.582 | L47: 5021.71 | M47: 4955.644 | N47: 3934.47 | O47: 43715.34 | P47: =(IF($A$1=40179,C47,(IF($A$1=40210,SUM(C47:D47),(IF($A$1=40238,SUM(C47:E47),(IF($A$1=40269,SUM(C47:F47),(IF($A$1=40299,SUM(C47:G47),(IF($A$1=40330,SUM(C47:H47),(IF($A$1=40360,SUM(C47:I47),0)))))))))))))+(IF($A$1=40391,SUM(C47:J47),(IF($A$1=40422,SUM(C47:K47),(IF($A$1=40452,SUM(C47:L47),(IF($A$1=40483,SUM(C47:M47))))))))))+(IF($A$1=40513,SUM(C47:N47),0)) -> 0 | Q47: =(IF($A$1=40179,C47,(IF($A$1=40210,D47,(IF($A$1=40238,E47,(IF($A$1=40269,F47,(IF($A$1=40299,G47,(IF($A$1=40330,H47,(IF($A$1=40360,I47,0)))))))))))))+(IF($A$1=40391,J47,(IF($A$1=40422,K47,(IF($A$1=40452,L47,(IF($A$1=40483,M47)))))))))+(IF($A$1=40513,N47,0)) -> 0
A48: DATA PROCESSING | C48: 0 | D48: 0 | E48: 0 | F48: 0 | G48: 0 | H48: 0 | I48: 0 | J48: 0 | K48: 0 | L48: 0 | M48: 0 | N48: 0 | O48: 0 | P48: =(IF($A$1=40179,C48,(IF($A$1=40210,SUM(C48:D48),(IF($A$1=40238,SUM(C48:E48),(IF($A$1=40269,SUM(C48:F48),(IF($A$1=40299,SUM(C48:G48),(IF($A$1=40330,SUM(C48:H48),(IF($A$1=40360,SUM(C48:I48),0)))))))))))))+(IF($A$1=40391,SUM(C48:J48),(IF($A$1=40422,SUM(C48:K48),(IF($A$1=40452,SUM(C48:L48),(IF($A$1=40483,SUM(C48:M48))))))))))+(IF($A$1=40513,SUM(C48:N48),0)) -> 0 | Q48: =(IF($A$1=40179,C48,(IF($A$1=40210,D48,(IF($A$1=40238,E48,(IF($A$1=40269,F48,(IF($A$1=40299,G48,(IF($A$1=40330,H48,(IF($A$1=40360,I48,0)))))))))))))+(IF($A$1=40391,J48,(IF($A$1=40422,K48,(IF($A$1=40452,L48,(IF($A$1=40483,M48)))))))))+(IF($A$1=40513,N48,0)) -> 0
A49: TELEPHONE | B49: 53255308 | C49: 3220.6431 | D49: 3431.238 | E49: 3826.0002 | F49: 2718.7099 | G49: 2041.662 | H49: 1621.007 | I49: 2137.2499 | J49: 2579.049 | K49: 2552.517 | L49: 2585.385 | M49: 2542.914 | N49: 1886.445 | O49: 31142.82 | P49: =(IF($A$1=40179,C49,(IF($A$1=40210,SUM(C49:D49),(IF($A$1=40238,SUM(C49:E49),(IF($A$1=40269,SUM(C49:F49),(IF($A$1=40299,SUM(C49:G49),(IF($A$1=40330,SUM(C49:H49),(IF($A$1=40360,SUM(C49:I49),0)))))))))))))+(IF($A$1=40391,SUM(C49:J49),(IF($A$1=40422,SUM(C49:K49),(IF($A$1=40452,SUM(C49:L49),(IF($A$1=40483,SUM(C49:M49))))))))))+(IF($A$1=40513,SUM(C49:N49),0)) -> 0 | Q49: =(IF($A$1=40179,C49,(IF($A$1=40210,D49,(IF($A$1=40238,E49,(IF($A$1=40269,F49,(IF($A$1=40299,G49,(IF($A$1=40330,H49,(IF($A$1=40360,I49,0)))))))))))))+(IF($A$1=40391,J49,(IF($A$1=40422,K49,(IF($A$1=40452,L49,(IF($A$1=40483,M49)))))))))+(IF($A$1=40513,N49,0)) -> 0
A50: LICENCE | B50: 53255799 | C50: 0 | D50: 1138.3254 | E50: 0 | F50: 0 | G50: 0 | H50: 0 | I50: 0 | J50: 64.967542 | K50: 69.669519 | L50: 65.411385 | M50: 65.800186 | N50: 63.363059 | O50: 1467.5371 | P50: =(IF($A$1=40179,C50,(IF($A$1=40210,SUM(C50:D50),(IF($A$1=40238,SUM(C50:E50),(IF($A$1=40269,SUM(C50:F50),(IF($A$1=40299,SUM(C50:G50),(IF($A$1=40330,SUM(C50:H50),(IF($A$1=40360,SUM(C50:I50),0)))))))))))))+(IF($A$1=40391,SUM(C50:J50),(IF($A$1=40422,SUM(C50:K50),(IF($A$1=40452,SUM(C50:L50),(IF($A$1=40483,SUM(C50:M50))))))))))+(IF($A$1=40513,SUM(C50:N50),0)) -> 0 | Q50: =(IF($A$1=40179,C50,(IF($A$1=40210,D50,(IF($A$1=40238,E50,(IF($A$1=40269,F50,(IF($A$1=40299,G50,(IF($A$1=40330,H50,(IF($A$1=40360,I50,0)))))))))))))+(IF($A$1=40391,J50,(IF($A$1=40422,K50,(IF($A$1=40452,L50,(IF($A$1=40483,M50)))))))))+(IF($A$1=40513,N50,0)) -> 0
A51: ALLOCATED EXP. | B51: 60-300-143 | C51: 0 | D51: 0 | E51: 0 | F51: 0 | G51: 0 | H51: 0 | I51: 0 | J51: 0 | K51: 0 | L51: 0 | M51: 0 | N51: 0 | O51: 0 | P51: =(IF($A$1=40179,C51,(IF($A$1=40210,SUM(C51:D51),(IF($A$1=40238,SUM(C51:E51),(IF($A$1=40269,SUM(C51:F51),(IF($A$1=40299,SUM(C51:G51),(IF($A$1=40330,SUM(C51:H51),(IF($A$1=40360,SUM(C51:I51),0)))))))))))))+(IF($A$1=40391,SUM(C51:J51),(IF($A$1=40422,SUM(C51:K51),(IF($A$1=40452,SUM(C51:L51),(IF($A$1=40483,SUM(C51:M51))))))))))+(IF($A$1=40513,SUM(C51:N51),0)) -> 0 | Q51: =(IF($A$1=40179,C51,(IF($A$1=40210,D51,(IF($A$1=40238,E51,(IF($A$1=40269,F51,(IF($A$1=40299,G51,(IF($A$1=40330,H51,(IF($A$1=40360,I51,0)))))))))))))+(IF($A$1=40391,J51,(IF($A$1=40422,K51,(IF($A$1=40452,L51,(IF($A$1=40483,M51)))))))))+(IF($A$1=40513,N51,0)) -> 0
A52: LAUNDRY | B52: 53257201 | C52: 3299.3673 | D52: 3398.7144 | E52: 3454.9664 | F52: 3663.6716 | G52: 3888.4677 | H52: 3828.3628 | I52: 3852.9614 | J52: 3943.9156 | K52: 4100.3771 | L52: 3864.66 | M52: 3853.7423 | N52: 3406.3851 | O52: 44555.592 | P52: =(IF($A$1=40179,C52,(IF($A$1=40210,SUM(C52:D52),(IF($A$1=40238,SUM(C52:E52),(IF($A$1=40269,SUM(C52:F52),(IF($A$1=40299,SUM(C52:G52),(IF($A$1=40330,SUM(C52:H52),(IF($A$1=40360,SUM(C52:I52),0)))))))))))))+(IF($A$1=40391,SUM(C52:J52),(IF($A$1=40422,SUM(C52:K52),(IF($A$1=40452,SUM(C52:L52),(IF($A$1=40483,SUM(C52:M52))))))))))+(IF($A$1=40513,SUM(C52:N52),0)) -> 0 | Q52: =(IF($A$1=40179,C52,(IF($A$1=40210,D52,(IF($A$1=40238,E52,(IF($A$1=40269,F52,(IF($A$1=40299,G52,(IF($A$1=40330,H52,(IF($A$1=40360,I52,0)))))))))))))+(IF($A$1=40391,J52,(IF($A$1=40422,K52,(IF($A$1=40452,L52,(IF($A$1=40483,M52)))))))))+(IF($A$1=40513,N52,0)) -> 0
