Workbook

Sheet Total
A1: Site Name | B1: Day | C1: Month | D1: Year | E1: Total Electricity Kwh | F1: Electricity Tariff ($/Kwh) | G1: Natual Gas (m3) | H1: Natural Gas $/m3 | I1: Water Utility Supply (m3) m3 | J1: Water Utility Supply (m3) $/m3 | K1: Room Nights
A2: Cairo at The First Residence | B2: 1 | C2: 2 | D2: 2023 | E2: =Elect!BS6 -> 22903.342 | F2: ='Utility Consnsumption'!K13/'Utility Consnsumption'!J13 -> 1.4175396 | G2: =Gas!K7 -> 1521.52 | H2: 3.8 | I2: =Water!H7 -> 209.38 | J2: 10 | K2: =Elect!BT6 -> 97
A3: Cairo at The First Residence | B3: =B2+1 -> 2 | C3: 2 | D3: 2023 | E3: =Elect!BS7 -> 24396.613 | F3: =F2 -> 1.4175396 | G3: =Gas!K8 -> 1768.92 | H3: 3.8 | I3: =Water!H8 -> 256.36 | J3: 10 | K3: =Elect!BT7 -> 128
A4: Cairo at The First Residence | B4: =B3+1 -> 3 | C4: 2 | D4: 2023 | E4: =Elect!BS8 -> 24713.8 | F4: =F3 -> 1.4175396 | G4: =Gas!K9 -> 1850.1 | H4: 3.8 | I4: =Water!H9 -> 336.98 | J4: 10 | K4: =Elect!BT8 -> 130
A5: Cairo at The First Residence | B5: =B4+1 -> 4 | C5: 2 | D5: 2023 | E5: =Elect!BS9 -> 23918.855 | F5: =F4 -> 1.4175396 | G5: =Gas!K10 -> 2263.36 | H5: 3.8 | I5: =Water!H10 -> 346.26 | J5: 10 | K5: =Elect!BT9 -> 236
A6: Cairo at The First Residence | B6: =B5+1 -> 5 | C6: 2 | D6: 2023 | E6: =Elect!BS10 -> 22880.134 | F6: =F5 -> 1.4175396 | G6: =Gas!K11 -> 1987.8533 | H6: 3.8 | I6: =Water!H11 -> 340.07333 | J6: 10 | K6: =Elect!BT10 -> 237
A7: Cairo at The First Residence | B7: =B6+1 -> 6 | C7: 2 | D7: 2023 | E7: =Elect!BS11 -> 22884.966 | F7: =F6 -> 1.4175396 | G7: =Gas!K12 -> 1699.8867 | H7: 3.8 | I7: =Water!H12 -> 283.42667 | J7: 10 | K7: =Elect!BT11 -> 196
A8: Cairo at The First Residence | B8: =B7+1 -> 7 | C8: 2 | D8: 2023 | E8: =Elect!BS12 -> 23212.385 | F8: =F7 -> 1.4175396 | G8: =Gas!K13 -> 1865.36 | H8: 3.8 | I8: =Water!H13 -> 296.96 | J8: 10 | K8: =Elect!BT12 -> 163
A9: Cairo at The First Residence | B9: =B8+1 -> 8 | C9: 2 | D9: 2023 | E9: =Elect!BS13 -> 23300.592 | F9: =F8 -> 1.4175396 | G9: =Gas!K14 -> 1971.34 | H9: 3.8 | I9: =Water!H14 -> 337.56 | J9: 10 | K9: =Elect!BT13 -> 149
A10: Cairo at The First Residence | B10: =B9+1 -> 9 | C10: 2 | D10: 2023 | E10: =Elect!BS14 -> 22906.683 | F10: =F9 -> 1.4175396 | G10: =Gas!K15 -> 1873.04 | H10: 3.8 | I10: =Water!H15 -> 294.06 | J10: 10 | K10: =Elect!BT14 -> 162
A11: Cairo at The First Residence | B11: =B10+1 -> 10 | C11: 2 | D11: 2023 | E11: =Elect!BS15 -> 22569.905 | F11: =F10 -> 1.4175396 | G11: =Gas!K16 -> 1939.46 | H11: 3.8 | I11: =Water!H16 -> 326.54 | J11: 10 | K11: =Elect!BT15 -> 176
A12: Cairo at The First Residence | B12: =B11+1 -> 11 | C12: 2 | D12: 2023 | E12: =Elect!BS16 -> 22584 | F12: =F11 -> 1.4175396 | G12: =Gas!K17 -> 2352.6 | H12: 3.8 | I12: =Water!H17 -> 345.68 | J12: 10 | K12: =Elect!BT16 -> 234
A13: Cairo at The First Residence | B13: =B12+1 -> 12 | C13: 2 | D13: 2023 | E13: =Elect!BS17 -> 25259.357 | F13: =F12 -> 1.4175396 | G13: =Gas!K18 -> 2262.58 | H13: 3.8 | I13: =Water!H18 -> 331.76 | J13: 10 | K13: =Elect!BT17 -> 240
A14: Cairo at The First Residence | B14: =B13+1 -> 13 | C14: 2 | D14: 2023 | E14: =Elect!BS18 -> 21667.537 | F14: =F13 -> 1.4175396 | G14: =Gas!K19 -> 1870.74 | H14: 3.8 | I14: =Water!H19 -> 333.5 | J14: 10 | K14: =Elect!BT18 -> 246
... A29: Cairo at The First Residence | B29: =B28+1 -> 28 | C29: 2 | D29: 2023 | E29: =Elect!BS33 -> 24134.626 | F29: =F28 -> 1.4175396 | G29: =Gas!K34 -> 2103.06 | H29: 3.8 | I29: =Water!H34 -> 335.82 | J29: 10 | K29: =Elect!BT33 -> 230.66667

Sheet Submetering
A1: Site Name | B1: Day | C1: Month | D1: Year | E1: Electricity | F1: Main Feeder -KWh | G1: T2+T8 -KWh | H1: La Gourmandize -KWh | I1: Casino 3rd floor EM -KWh | J1: Casino 3rd floor Normal -KWh | K1: Chiller 1 -KWh | L1: Chiller 2 -KWh | M1: Chiller 3 -KWh | N1: Chiller 4 -KWh | O1: Chiller 5 -KWh | P1: Chiller 6 -KWh | Q1: Cooling towers -KWh | R1: Chiller Pumps -KWh | S1: Cooling Tower Pumps -KWh | T1: Fiber Chiller -KWh | U1: Mall Ceiling light -KWh | V1: LG Bakery -KWh | W1: LG Bakery light ( Old lockers ) -KWh | X1: MCCR1 -KWh | Y1: Children Swimming Pool -KWh | Z1: DPH1 -KWh | AA1: Guest Rooms Emerg. -KWh | AB1: Hotel Hoods -KWh | AC1: Main G2 -KWh | AD1: Old Casino Emergency -KWh | AE1: L / A -KWh | AF1: L / B -KWh | AG1: L / C -KWh | AH1: Boat -KWh | AI1: Water | AJ1: Main water meter 1 -m3 | AK1: Main water meter 2 -m3 | AL1: Main water meter 3 -m3 | AM1: Boat -m3 | AN1: Gas | AO1: Main Gas Flow Meter -m3 | AP1: Laundry Gas Flow Meter -m3 | AQ1: Gourmandize Gas Flow Meter -m3 | AR1: Boat -m3 | AS1: Room Nights
A2: Cairo at The First Residence | B2: 1 | C2: 2 | D2: 2023 | F2: =Elect!J6 -> 7543.3333 | G2: =Elect!K6 -> 3061.3333 | H2: =Elect!Q6 -> 420 | I2: =Elect!S6 -> 144.66667 | J2: =Elect!U6 -> 245.33333 | K2: =Elect!W6 -> 1654.13 | L2: =Elect!Y6 -> 0 | M2: =Elect!AA6 -> 0 | N2: =Elect!AC6 -> 0 | O2: =Elect!AE6 -> 26.5 | P2: =Elect!AG6 -> 12.72 | Q2: =Elect!AI6 -> 63.776667 | R2: =Elect!AK6 -> 1898.8133 | S2: =Elect!AM6 -> 119.07333 | T2: =Elect!AP6 -> 141.8625 | U2: =Elect!AR6 -> 187.33333 | V2: =Elect!AT6 -> 138.66667 | W2: =Elect!AV6 -> 43.666667 | X2: =Elect!AX6 -> 482.33333 | Y2: =Elect!AZ6 -> 620 | Z2: =Elect!BB6 -> 4326.3333 | AA2: =Elect!BD6 -> 232 | AB2: =Elect!BF6 -> 37 | AC2: =Elect!BH6 -> 4955.8 | AD2: =Elect!BL6 -> 356.33333 | AE2: =Elect!BN6 -> 929.66667 | AF2: =Elect!BP6 -> 133 | AG2: =Elect!BR6 -> 121 | AH2: =#REF! -> #REF! | AJ2: =Water!C7 -> 58 | AK2: =Water!E7 -> 58 | AL2: =Water!G7 -> 93.38 | AM2: 0 | AO2: =Gas!C7 -> 1194.62 | AP2: =Gas!E7 -> 326.9 | AQ2: =Gas!G7 -> 90 | AR2: 0 | AS2: =Elect!BT6 -> 97
A3: Cairo at The First Residence | B3: =B2+1 -> 2 | C3: 2 | D3: 2023 | F3: =Elect!J7 -> 7209 | G3: =Elect!K7 -> 6980 | H3: =Elect!Q7 -> 420 | I3: =Elect!S7 -> 148 | J3: =Elect!U7 -> 254 | K3: =Elect!W7 -> 2147.03 | L3: =Elect!Y7 -> 0 | M3: =Elect!AA7 -> 0 | N3: =Elect!AC7 -> 0 | O3: =Elect!AE7 -> 13.78 | P3: =Elect!AG7 -> 12.72 | Q3: =Elect!AI7 -> 136.21 | R3: =Elect!AK7 -> 2065.41 | S3: =Elect!AM7 -> 124.55 | T3: =Elect!AP7 -> 148.1625 | U3: =Elect!AR7 -> 195 | V3: =Elect!AT7 -> 130 | W3: =Elect!AV7 -> 44 | X3: =Elect!AX7 -> 679 | Y3: =Elect!AZ7 -> 635 | Z3: =Elect!BB7 -> 4742 | AA3: =Elect!BD7 -> 177 | AB3: =Elect!BF7 -> 39 | AC3: =Elect!BH7 -> 5478.75 | AD3: =Elect!BL7 -> 289 | AE3: =Elect!BN7 -> 1048 | AF3: =Elect!BP7 -> 117 | AG3: =Elect!BR7 -> 128 | AH3: =#REF! -> #REF! | AJ3: =Water!C8 -> 75.4 | AK3: =Water!E8 -> 87 | AL3: =Water!G8 -> 93.96 | AM3: 0 | AO3: =Gas!C8 -> 1374.82 | AP3: =Gas!E8 -> 394.1 | AQ3: =Gas!G8 -> 107 | AR3: 0 | AS3: =Elect!BT7 -> 128
A4: Cairo at The First Residence | B4: =B3+1 -> 3 | C4: 2 | D4: 2023 | F4: =Elect!J8 -> 6942 | G4: =Elect!K8 -> 4568 | H4: =Elect!Q8 -> 420 | I4: =Elect!S8 -> 146 | J4: =Elect!U8 -> 263 | K4: =Elect!W8 -> 2217.52 | L4: =Elect!Y8 -> 0 | M4: =Elect!AA8 -> 18.02 | N4: =Elect!AC8 -> 0 | O4: =Elect!AE8 -> 12.72 | P4: =Elect!AG8 -> 12.19 | Q4: =Elect!AI8 -> 173.31 | R4: =Elect!AK8 -> 1993.33 | S4: =Elect!AM8 -> 115.01 | T4: =Elect!AP8 -> 146.7 | U4: =Elect!AR8 -> 202 | V4: =Elect!AT8 -> 113 | W4: =Elect!AV8 -> 40 | X4: =Elect!AX8 -> 643 | Y4: =Elect!AZ8 -> 1040 | Z4: =Elect!BB8 -> 4808 | AA4: =Elect!BD8 -> 199 | AB4: =Elect!BF8 -> 40 | AC4: =Elect!BH8 -> 5578 | AD4: =Elect!BL8 -> 241 | AE4: =Elect!BN8 -> 1002 | AF4: =Elect!BP8 -> 118 | AG4: =Elect!BR8 -> 154 | AH4: =#REF! -> #REF! | AJ4: =Water!C9 -> 98.6 | AK4: =Water!E9 -> 110.2 | AL4: =Water!G9 -> 128.18 | AM4: 0 | AO4: =Gas!C9 -> 1484 | AP4: =Gas!E9 -> 366.1 | AQ4: =Gas!G9 -> 108 | AR4: 0 | AS4: =Elect!BT8 -> 130
A5: Cairo at The First Residence | B5: =B4+1 -> 4 | C5: 2 | D5: 2023 | F5: =Elect!J9 -> 6919 | G5: =Elect!K9 -> 4728 | H5: =Elect!Q9 -> 360 | I5: =Elect!S9 -> 142 | J5: =Elect!U9 -> 253 | K5: =Elect!W9 -> 2164.52 | L5: =Elect!Y9 -> 0 | M5: =Elect!AA9 -> 0 | N5: =Elect!AC9 -> 0 | O5: =Elect!AE9 -> 13.25 | P5: =Elect!AG9 -> 12.72 | Q5: =Elect!AI9 -> 174.37 | R5: =Elect!AK9 -> 1990.15 | S5: =Elect!AM9 -> 113.42 | T5: =Elect!AP9 -> 155.475 | U5: =Elect!AR9 -> 202 | V5: =Elect!AT9 -> 111 | W5: =Elect!AV9 -> 40 | X5: =Elect!AX9 -> 622 | Y5: =Elect!AZ9 -> 610 | Z5: =Elect!BB9 -> 4853 | AA5: =Elect!BD9 -> 178 | AB5: =Elect!BF9 -> 40 | AC5: =Elect!BH9 -> 5359.95 | AD5: =Elect!BL9 -> 88 | AE5: =Elect!BN9 -> 1011 | AF5: =Elect!BP9 -> 118 | AG5: =Elect!BR9 -> 157 | AH5: =#REF! -> #REF! | AJ5: =Water!C10 -> 110.2 | AK5: =Water!E10 -> 110.2 | AL5: =Water!G10 -> 125.86 | AM5: 0 | AO5: =Gas!C10 -> 1734.16 | AP5: =Gas!E10 -> 529.2 | AQ5: =Gas!G10 -> 109 | AR5: 0 | AS5: =Elect!BT9 -> 236
A6: Cairo at The First Residence | B6: =B5+1 -> 5 | C6: 2 | D6: 2023 | F6: =Elect!J10 -> 6667 | G6: =Elect!K10 -> 4562.3333 | H6: =Elect!Q10 -> 390 | I6: =Elect!S10 -> 141 | J6: =Elect!U10 -> 247 | K6: =Elect!W10 -> 1929.2 | L6: =Elect!Y10 -> 0 | M6: =Elect!AA10 -> 0 | N6: =Elect!AC10 -> 0 | O6: =Elect!AE10 -> 12.19 | P6: =Elect!AG10 -> 12.366667 | Q6: =Elect!AI10 -> 155.82 | R6: =Elect!AK10 -> 1883.09 | S6: =Elect!AM10 -> 114.48 | T6: =Elect!AP10 -> 149.7375 | U6: =Elect!AR10 -> 198 | V6: =Elect!AT10 -> 121 | W6: =Elect!AV10 -> 40 | X6: =Elect!AX10 -> 655 | Y6: =Elect!AZ10 -> 599 | Z6: =Elect!BB10 -> 4606 | AA6: =Elect!BD10 -> 186 | AB6: =Elect!BF10 -> 40 | AC6: =Elect!BH10 -> 5121.25 | AD6: =Elect!BL10 -> 103 | AE6: =Elect!BN10 -> 1008 | AF6: =Elect!BP10 -> 107 | AG6: =Elect!BR10 -> 155 | AH6: =#REF! -> #REF! | AJ6: =Water!C11 -> 102.46667 | AK6: =Water!E11 -> 110.2 | AL6: =Water!G11 -> 127.40667 | AM6: 0 | AO6: =Gas!C11 -> 1567.3867 | AP6: =Gas!E11 -> 420.46667 | AQ6: =Gas!G11 -> 108.33333 | AR6: 0 | AS6: =Elect!BT10 -> 237
A7: Cairo at The First Residence | B7: =B6+1 -> 6 | C7: 2 | D7: 2023 | F7: =Elect!J11 -> 7219 | G7: =Elect!K11 -> 4924 | H7: =Elect!Q11 -> 450 | I7: =Elect!S11 -> 142 | J7: =Elect!U11 -> 248 | K7: =Elect!W11 -> 1286.84 | L7: =Elect!Y11 -> 0 | M7: =Elect!AA11 -> 22.26 | N7: =Elect!AC11 -> 0 | O7: =Elect!AE11 -> 13.78 | P7: =Elect!AG11 -> 12.543333 | Q7: =Elect!AI11 -> 157.41 | R7: =Elect!AK11 -> 1776.56 | S7: =Elect!AM11 -> 112.36 | T7: =Elect!AP11 -> 136.4625 | U7: =Elect!AR11 -> 197 | V7: =Elect!AT11 -> 113 | W7: =Elect!AV11 -> 41 | X7: =Elect!AX11 -> 719 | Y7: =Elect!AZ11 -> 946 | Z7: =Elect!BB11 -> 4370 | AA7: =Elect!BD11 -> 192 | AB7: =Elect!BF11 -> 40 | AC7: =Elect!BH11 -> 5079.75 | AD7: =Elect!BL11 -> 90 | AE7: =Elect!BN11 -> 978 | AF7: =Elect!BP11 -> 107 | AG7: =Elect!BR11 -> 156 | AH7: =#REF! -> #REF! | AJ7: =Water!C12 -> 83.133333 | AK7: =Water!E12 -> 116 | AL7: =Water!G12 -> 84.293333 | AM7: 0 | AO7: =Gas!C12 -> 1341.2533 | AP7: =Gas!E12 -> 358.63333 | AQ7: =Gas!G12 -> 58.666667 | AR7: 0 | AS7: =Elect!BT11 -> 196
A8: Cairo at The First Residence | B8: =B7+1 -> 7 | C8: 2 | D8: 2023 | F8: =Elect!J12 -> 7366 | G8: =Elect!K12 -> 5085 | H8: =Elect!Q12 -> 540 | I8: =Elect!S12 -> 146 | J8: =Elect!U12 -> 256 | K8: =Elect!W12 -> 1381.18 | L8: =Elect!Y12 -> 0 | M8: =Elect!AA12 -> 0 | N8: =Elect!AC12 -> 0 | O8: =Elect!AE12 -> 13.25 | P8: =Elect!AG12 -> 12.72 | Q8: =Elect!AI12 -> 127.2 | R8: =Elect!AK12 -> 1865.07 | S8: =Elect!AM12 -> 118.19 | T8: =Elect!AP12 -> 115.425 | U8: =Elect!AR12 -> 200 | V8: =Elect!AT12 -> 130 | W8: =Elect!AV12 -> 42 | X8: =Elect!AX12 -> 754 | Y8: =Elect!AZ12 -> 577 | Z8: =Elect!BB12 -> 4432 | AA8: =Elect!BD12 -> 226 | AB8: =Elect!BF12 -> 40 | AC8: =Elect!BH12 -> 5272.35 | AD8: =Elect!BL12 -> 85 | AE8: =Elect!BN12 -> 1043 | AF8: =Elect!BP12 -> 114 | AG8: =Elect!BR12 -> 165 | AH8: =#REF! -> #REF! | AJ8: =Water!C13 -> 87 | AK8: =Water!E13 -> 98.6 | AL8: =Water!G13 -> 111.36 | AM8: 0 | AO8: =Gas!C13 -> 1469.16 | AP8: =Gas!E13 -> 396.2 | AQ8: =Gas!G13 -> 82 | AR8: 0 | AS8: =Elect!BT12 -> 163
A9: Cairo at The First Residence | B9: =B8+1 -> 8 | C9: 2 | D9: 2023 | F9: =Elect!J13 -> 7366 | G9: =Elect!K13 -> 5113 | H9: =Elect!Q13 -> 450 | I9: =Elect!S13 -> 146 | J9: =Elect!U13 -> 252 | K9: =Elect!W13 -> 1281.01 | L9: =Elect!Y13 -> 0 | M9: =Elect!AA13 -> 0 | N9: =Elect!AC13 -> 0 | O9: =Elect!AE13 -> 13.78 | P9: =Elect!AG13 -> 13.25 | Q9: =Elect!AI13 -> 118.19 | R9: =Elect!AK13 -> 1768.61 | S9: =Elect!AM13 -> 118.19 | T9: =Elect!AP13 -> 59.0625 | U9: =Elect!AR13 -> 207 | V9: =Elect!AT13 -> 99 | W9: =Elect!AV13 -> 41 | X9: =Elect!AX13 -> 735 | Y9: =Elect!AZ13 -> 625 | Z9: =Elect!BB13 -> 4740 | AA9: =Elect!BD13 -> 187 | AB9: =Elect!BF13 -> 40 | AC9: =Elect!BH13 -> 5438.5 | AD9: =Elect!BL13 -> 297 | AE9: =Elect!BN13 -> 1018 | AF9: =Elect!BP13 -> 112 | AG9: =Elect!BR13 -> 164 | AH9: =#REF! -> #REF! | AJ9: =Water!C14 -> 104.4 | AK9: =Water!E14 -> 121.8 | AL9: =Water!G14 -> 111.36 | AM9: 0 | AO9: =Gas!C14 -> 1573.04 | AP9: =Gas!E14 -> 398.3 | AQ9: =Gas!G14 -> 94 | AR9: 0 | AS9: =Elect!BT13 -> 149
A10: Cairo at The First Residence | B10: =B9+1 -> 9 | C10: 2 | D10: 2023 | F10: =Elect!J14 -> 7319 | G10: =Elect!K14 -> 5084 | H10: =Elect!Q14 -> 420 | I10: =Elect!S14 -> 141 | J10: =Elect!U14 -> 252 | K10: =Elect!W14 -> 1346.73 | L10: =Elect!Y14 -> 0 | M10: =Elect!AA14 -> 0 | N10: =Elect!AC14 -> 0 | O10: =Elect!AE14 -> 13.25 | P10: =Elect!AG14 -> 12.72 | Q10: =Elect!AI14 -> 120.31 | R10: =Elect!AK14 -> 1760.66 | S10: =Elect!AM14 -> 111.3 | T10: =Elect!AP14 -> 120.7125 | U10: =Elect!AR14 -> 203 | V10: =Elect!AT14 -> 108 | W10: =Elect!AV14 -> 40 | X10: =Elect!AX14 -> 740 | Y10: =Elect!AZ14 -> 582 | Z10: =Elect!BB14 -> 4546 | AA10: =Elect!BD14 -> 168 | AB10: =Elect!BF14 -> 35 | AC10: =Elect!BH14 -> 5260 | AD10: =Elect!BL14 -> 267 | AE10: =Elect!BN14 -> 972 | AF10: =Elect!BP14 -> 108 | AG10: =Elect!BR14 -> 120 | AH10: =#REF! -> #REF! | AJ10: =Water!C15 -> 87 | AK10: =Water!E15 -> 98.6 | AL10: =Water!G15 -> 108.46 | AM10: 0 | AO10: =Gas!C15 -> 1467.04 | AP10: =Gas!E15 -> 406 | AQ10: =Gas!G15 -> 82 | AR10: 0 | AS10: =Elect!BT14 -> 162
A11: Cairo at The First Residence | B11: =B10+1 -> 10 | C11: 2 | D11: 2023 | F11: =Elect!J15 -> 7532 | G11: =Elect!K15 -> 4924 | H11: =Elect!Q15 -> 480 | I11: =Elect!S15 -> 145 | J11: =Elect!U15 -> 262 | K11: =Elect!W15 -> 1330.83 | L11: =Elect!Y15 -> 0 | M11: =Elect!AA15 -> 0 | N11: =Elect!AC15 -> 0 | O11: =Elect!AE15 -> 15.9 | P11: =Elect!AG15 -> 12.19 | Q11: =Elect!AI15 -> 125.61 | R11: =Elect!AK15 -> 1485.06 | S11: =Elect!AM15 -> 110.24 | T11: =Elect!AP15 -> 101.025 | U11: =Elect!AR15 -> 174 | V11: =Elect!AT15 -> 140 | W11: =Elect!AV15 -> 40 | X11: =Elect!AX15 -> 740 | Y11: =Elect!AZ15 -> 10 | Z11: =Elect!BB15 -> 4704 | AA11: =Elect!BD15 -> 176 | AB11: =Elect!BF15 -> 35 | AC11: =Elect!BH15 -> 5358.05 | AD11: =Elect!BL15 -> 277 | AE11: =Elect!BN15 -> 978 | AF11: =Elect!BP15 -> 113 | AG11: =Elect!BR15 -> 157 | AH11: =#REF! -> #REF! | AJ11: =Water!C16 -> 98.6 | AK11: =Water!E16 -> 116 | AL11: =Water!G16 -> 111.94 | AM11: 0 | AO11: =Gas!C16 -> 1495.66 | AP11: =Gas!E16 -> 443.8 | AQ11: =Gas!G16 -> 86 | AR11: 0 | AS11: =Elect!BT15 -> 176
A12: Cairo at The First Residence | B12: =B11+1 -> 11 | C12: 2 | D12: 2023 | F12: =Elect!J16 -> 7099 | G12: =Elect!K16 -> 4845 | H12: =Elect!Q16 -> 420 | I12: =Elect!S16 -> 137 | J12: =Elect!U16 -> 248 | K12: =Elect!W16 -> 1598.48 | L12: =Elect!Y16 -> 0 | M12: =Elect!AA16 -> 0 | N12: =Elect!AC16 -> 0 | O12: =Elect!AE16 -> 10.07 | P12: =Elect!AG16 -> 12.72 | Q12: =Elect!AI16 -> 152.11 | R12: =Elect!AK16 -> 1787.69 | S12: =Elect!AM16 -> 111.83 | T12: =Elect!AP16 -> 114.3 | U12: =Elect!AR16 -> 187 | V12: =Elect!AT16 -> 132 | W12: =Elect!AV16 -> 41 | X12: =Elect!AX16 -> 744 | Y12: =Elect!AZ16 -> 10 | Z12: =Elect!BB16 -> 4594 | AA12: =Elect!BD16 -> 193 | AB12: =Elect!BF16 -> 40 | AC12: =Elect!BH16 -> 5336.8 | AD12: =Elect!BL16 -> 269 | AE12: =Elect!BN16 -> 947 | AF12: =Elect!BP16 -> 109 | AG12: =Elect!BR16 -> 152 | AH12: =#REF! -> #REF! | AJ12: =Water!C17 -> 110.2 | AK12: =Water!E17 -> 121.8 | AL12: =Water!G17 -> 113.68 | AM12: 0 | AO12: =Gas!C17 -> 1844.4 | AP12: =Gas!E17 -> 508.2 | AQ12: =Gas!G17 -> 110 | AR12: 0 | AS12: =Elect!BT16 -> 234
A13: Cairo at The First Residence | B13: =B12+1 -> 12 | C13: 2 | D13: 2023 | F13: =Elect!J17 -> 9020 | G13: =Elect!K17 -> 4796 | H13: =Elect!Q17 -> 450 | I13: =Elect!S17 -> 155 | J13: =Elect!U17 -> 268 | K13: =Elect!W17 -> 1541.24 | L13: =Elect!Y17 -> 0 | M13: =Elect!AA17 -> 0 | N13: =Elect!AC17 -> 0 | O13: =Elect!AE17 -> 13.78 | P13: =Elect!AG17 -> 12.72 | Q13: =Elect!AI17 -> 156.88 | R13: =Elect!AK17 -> 1866.13 | S13: =Elect!AM17 -> 116.07 | T13: =Elect!AP17 -> 58.3875 | U13: =Elect!AR17 -> 207 | V13: =Elect!AT17 -> 131 | W13: =Elect!AV17 -> 42 | X13: =Elect!AX17 -> 754 | Y13: =Elect!AZ17 -> 11 | Z13: =Elect!BB17 -> 4847 | AA13: =Elect!BD17 -> 252 | AB13: =Elect!BF17 -> 40 | AC13: =Elect!BH17 -> 5740.15 | AD13: =Elect!BL17 -> 209 | AE13: =Elect!BN17 -> 996 | AF13: =Elect!BP17 -> 117 | AG13: =Elect!BR17 -> 168 | AH13: =#REF! -> #REF! | AJ13: =Water!C18 -> 104.4 | AK13: =Water!E18 -> 121.8 | AL13: =Water!G18 -> 105.56 | AM13: 0 | AO13: =Gas!C18 -> 1836.98 | AP13: =Gas!E18 -> 425.6 | AQ13: =Gas!G18 -> 108 | AR13: 0 | AS13: =Elect!BT17 -> 240
A14: Cairo at The First Residence | B14: =B13+1 -> 13 | C14: 2 | D14: 2023 | F14: =Elect!J18 -> 5557 | G14: =Elect!K18 -> 2502 | H14: =Elect!Q18 -> 570 | I14: =Elect!S18 -> 138 | J14: =Elect!U18 -> 237 | K14: =Elect!W18 -> 1515.27 | L14: =Elect!Y18 -> 0 | M14: =Elect!AA18 -> 0 | N14: =Elect!AC18 -> 0 | O14: =Elect!AE18 -> 13.78 | P14: =Elect!AG18 -> 12.72 | Q14: =Elect!AI18 -> 155.82 | R14: =Elect!AK18 -> 1989.62 | S14: =Elect!AM18 -> 110.24 | T14: =Elect!AP18 -> 95.7375 | U14: =Elect!AR18 -> 186 | V14: =Elect!AT18 -> 143 | W14: =Elect!AV18 -> 40 | X14: =Elect!AX18 -> 685 | Y14: =Elect!AZ18 -> 10 | Z14: =Elect!BB18 -> 4864 | AA14: =Elect!BD18 -> 268 | AB14: =Elect!BF18 -> 74 | AC14: =Elect!BH18 -> 5377.35 | AD14: =Elect!BL18 -> 197 | AE14: =Elect!BN18 -> 969 | AF14: =Elect!BP18 -> 108 | AG14: =Elect!BR18 -> 161 | AH14: =#REF! -> #REF! | AJ14: =Water!C19 -> 104.4 | AK14: =Water!E19 -> 121.8 | AL14: =Water!G19 -> 107.3 | AM14: 0 | AO14: =Gas!C19 -> 1408.74 | AP14: =Gas!E19 -> 462 | AQ14: =Gas!G19 -> 83 | AR14: 0 | AS14: =Elect!BT18 -> 246
... A29: Cairo at The First Residence | B29: =B28+1 -> 28 | C29: 2 | D29: 2023 | F29: =Elect!J33 -> 7444.3333 | G29: =Elect!K33 -> 3800.3333 | H29: =Elect!Q33 -> 560 | I29: =Elect!S33 -> 141.33333 | J29: =Elect!U33 -> 264.33333 | K29: =Elect!W33 -> 2196.85 | L29: =Elect!Y33 -> 0 | M29: =Elect!AA33 -> 0 | N29: =Elect!AC33 -> 0 | O29: =Elect!AE33 -> 0 | P29: =Elect!AG33 -> 12.013333 | Q29: =Elect!AI33 -> 228.60667 | R29: =Elect!AK33 -> 2056.0467 | S29: =Elect!AM33 -> 115.36333 | T29: =Elect!AP33 -> 90.5625 | U29: =Elect!AR33 -> 190.66667 | V29: =Elect!AT33 -> 116 | W29: =Elect!AV33 -> 40.333333 | X29: =Elect!AX33 -> 968.66667 | Y29: =Elect!AZ33 -> 0 | Z29: =Elect!BB33 -> 4383.6667 | AA29: =Elect!BD33 -> 275.33333 | AB29: =Elect!BF33 -> 48.5 | AC29: =Elect!BH33 -> 5407.6833 | AD29: =Elect!BL33 -> 269.33333 | AE29: =Elect!BN33 -> 948 | AF29: =Elect!BP33 -> 109 | AG29: =Elect!BR33 -> 36.666667 | AH29: =#REF! -> #REF! | AJ29: =Water!C34 -> 104.4 | AK29: =Water!E34 -> 121.8 | AL29: =Water!G34 -> 109.62 | AM29: 0 | AO29: =Gas!C34 -> 1622.86 | AP29: =Gas!E34 -> 480.2 | AQ29: =Gas!G34 -> 89 | AR29: 0 | AS29: =Elect!BT33 -> 230.66667
W30: =Elect!AV34 -> 0 | X30: =Elect!AX34 -> 0 | Y30: =Elect!AZ34 -> 0 | Z30: =Elect!BB34 -> 0 | AA30: =Elect!BD34 -> 0 | AB30: =Elect!BF34 -> 0 | AC30: =Elect!BH34 -> 0 | AD30: =Elect!BL34 -> 0 | AE30: =Elect!BN34 -> 0 | AF30: =Elect!BP34 -> 0 | AG30: =Elect!BR34 -> 0 | AH30: =#REF! -> #REF! | AJ30: =Water!C35 -> 0 | AK30: =Water!E35 -> 0 | AL30: =Water!G35 -> 0 | AM30: 0 | AO30: =Gas!C35 -> 0 | AP30: =Gas!E35 -> 0 | AQ30: =Gas!G35 -> 0 | AR30: 0 | AS30: =Elect!BT34 -> 0
W31: =Elect!AV35 -> 0 | X31: =Elect!AX35 -> 0 | Y31: =Elect!AZ35 -> 0 | Z31: =Elect!BB35 -> 0 | AA31: =Elect!BD35 -> 0 | AB31: =Elect!BF35 -> 0 | AC31: =Elect!BH35 -> 0 | AD31: =Elect!BL35 -> 0 | AE31: =Elect!BN35 -> 0 | AF31: =Elect!BP35 -> 0 | AG31: =Elect!BR35 -> 0 | AH31: =#REF! -> #REF! | AJ31: =Water!C36 -> 0 | AK31: =Water!E36 -> 0 | AL31: =Water!G36 -> 0 | AM31: 0 | AO31: =Gas!C36 -> 0 | AP31: =Gas!E36 -> 0 | AQ31: =Gas!G36 -> 0 | AR31: 0 | AS31: =Elect!BT35 -> 0
W32: =Elect!AV36 -> 0 | X32: =Elect!AX36 -> 0 | Y32: =Elect!AZ36 -> 0 | Z32: =Elect!BB36 -> 0 | AA32: =Elect!BD36 -> 0 | AB32: =Elect!BF36 -> 0 | AC32: =Elect!BH36 -> 0 | AD32: =Elect!BL36 -> 0 | AE32: =Elect!BN36 -> 0 | AF32: =Elect!BP36 -> 0 | AG32: =Elect!BR36 -> 0 | AH32: =#REF! -> #REF! | AJ32: =Water!C37 -> 0 | AK32: =Water!E37 -> 0 | AL32: =Water!G37 -> 0 | AM32: 0 | AO32: =Gas!C37 -> 0 | AP32: =Gas!E37 -> 0 | AQ32: =Gas!G37 -> 0 | AR32: 0 | AS32: =Elect!BT36 -> 0

Sheet Elect
A1: 44958 | M1: Electricity | BP1: Gourmandise UP | BR1: 1.6 | BS1: Power Taxes | BU1: Max Demand | BW1: 500 | BX1: Electricity UP | BZ1: 1.15
BS2: Light Taxes | BU2: PF Penalty | BX2: Max. Demand UP | BZ2: 30
A3: Date | B3: COUNTER (1) | D3: MD | F3: KVAR | H3: n | I3: Guest Rooms Consumption | R3: Casino Consumption | V3: Plant Room Shared Loads | AO3: To Be Charged By First Arabian | BK3: From Main Panel G2 | BS3: Total Consumption. | BT3: No. Of | BU3: KWH/ | BV3: No. Of | BW3: KWH/ | BX3: Total Cost | BY3: L.E\ | BZ3: L.E\
B4: Reading | C4: Consp. F: *800 | D4: Reading | E4: Consp F: 80 | F4: Reading | G4: Consp. F:*10 | I4: Main Feeder | J4: Consp | K4: T2+T8 | L4: Trans T2 | M4: Consp | N4: Trans T8 | O4: Consp | P4: La Gourmandize | Q4: Consp *30 | R4: Casino 3rd floor EM | S4: Consp | T4: Casino 3rd floor Normal | U4: Consp | V4: Chiller 1 | W4: Consp 53% | X4: Chiller 2 | Y4: Consp 53% | Z4: Chiller 3 | AA4: Consp 53% | AB4: Chiller 4 | AC4: Consp 53% | AD4: Chiller 5 | AE4: Consp 53% | AF4: Chiller 6 | AG4: Consp 53% | AH4: Cooling Towers | AI4: Consp 53% | AJ4: Chiller Pumps | AK4: Consp 53% | AL4: Cooling Tower Pumps | AM4: Consp 53% | AN4: Total Plant Room Consp | AO4: Fiber Chiller (N24) | AP4: Consp | AQ4: Mall Ceiling light (N4) | AR4: Consp | AS4: LG Bakery (N2) | AT4: Consp | AU4: LG Bakery light ( Old lockers ) | AV4: Consp | AW4: MCCR1 | AX4: Consp | AY4: Children Swimming pool | AZ4: Consp | BA4: DPH1 | BB4: Consp | BC4: Guest Rooms Emergency | BD4: Consp | BE4: Hotel Hoods | BF4: Consp | BG4: Main G2 | BH4: Consp | BI4: Total Consp From First Arabian | BJ4: First Arabian Charge Back | BK4: Old Casino Emergency | BL4: Consp | BM4: L / A | BN4: Consp | BO4: L / B | BP4: Consp | BQ4: L / C | BR4: Consp | BT4: Rooms | BU4: room | BV4: guest | BW4: guest | BY4: Room | BZ4: Guest
A5: Last Month Reading | I5: 25991238 | J5: =IF(I5>=I4,I5-I4,0) -> 0 | K5: =M5+O5 -> 0 | L5: 404725.67 | M5: =IF(L5>=L4,L5-L4,0) -> 0 | N5: 426081 | O5: =IF(N5>=N4,N5-N4,0) -> 0 | P5: 228195 | Q5: =IF(P5>=P4,P5-P4,0)*30 -> 0 | R5: 234971.33 | S5: =IF(R5>=R4,R5-R4,0) -> 0 | T5: 428547.67 | U5: =IF(T5>=T4,T5-T4,0) -> 0 | V5: 895229 | W5: =IF(V5>=V4,V5-V4,0)*0.53 -> 0 | X5: 839916 | Y5: =IF(X5>=X4,X5-X4,0)*0.53 -> 0 | Z5: 871759 | AA5: =IF(Z5>=Z4,Z5-Z4,0)*0.53 -> 0 | AB5: 184962 | AC5: =IF(AB5>=AB4,AB5-AB4,0)*0.53 -> 0 | AD5: 863299 | AE5: =IF(AD5>=AD4,AD5-AD4,0)*0.53 -> 0 | AF5: 1010940 | AG5: =IF(AF5>=AF4,AF5-AF4,0)*0.53 -> 0 | AH5: 445421.67 | AI5: =IF(AH5>=AH4,AH5-AH4,0)*0.53 -> 0 | AJ5: 774987.33 | AK5: =IF(AJ5>=AJ4,AJ5-AJ4,0)*0.53 -> 0 | AL5: 580792.33 | AM5: =IF(AL5>=AL4,AL5-AL4,0)*0.53 -> 0 | AN5: =W5+Y5+AA5+AC5+AE5+AG5+AI5+AK5+AM5 -> 0 | AO5: 8236771 | AP5: =IF(AO5>=AO4,AO5-AO4,0)*0.1125 -> 0 | AQ5: 762289.67 | AR5: =IF(AQ5>=AQ4,AQ5-AQ4,0) -> 0 | AS5: 23114.333 | AT5: =IF(AS5>=AS4,AS5-AS4,0) -> 0 | AU5: 828493.33 | AV5: =IF(AU5>=AU4,AU5-AU4,0) -> 0 | AW5: 2932469.7 | AX5: =IF(AW5>=AW4,AW5-AW4,0) -> 0 | AY5: 234748 | AZ5: =IF(AY5>=AY4,AY5-AY4,0) -> 0 | BA5: 21094072 | BB5: =IF(BA5>=BA4,BA5-BA4,0) -> 0 | BC5: 653479 | BD5: =IF(BC5>=BC4,BC5-BC4,0) -> 0 | BE5: 47700 | BF5: =IF(BE5>=BE4,BE5-BE4,0) -> 0 | BG5: 26512695 | BH5: =IF(BG5>=BG4,BG5-BG4,0)-(0.45*BN5)-(0.45*BP5)-BR5 -> 0 | BI5: =AP5+AR5+AT5+AV5+AX5+AZ5+BB5+BD5+BF5+BH5 -> 0 | BJ5: =BI5+AN5 -> 0 | BK5: 1508370.7 | BL5: =IF(BK5>=BK4,BK5-BK4,0) -> 0 | BM5: 4369853.3 | BN5: =IF(BM5>=BM4,BM5-BM4,0) -> 0 | BO5: 457697 | BP5: =IF(BO5>=BO4,BO5-BO4,0) -> 0 | BQ5: 570578 | BR5: =IF(BQ5>=BQ4,BQ5-BQ4,0) -> 0
A6: 1 | C6: =IF(+B6-B5>0,B6-B5,(B6-B5)>0)*800 -> 0 | E6: =IF(+D6-D5>0,D6-D5,(D6-D5)>0)*80 -> 0 | G6: =IF(+F6-F5>0,F6-F5,(F6-F5)>0)*10 -> 0 | H6: 56 | I6: 25998781 | J6: =IF(I6>=I5,I6-I5,0) -> 7543.3333 | K6: =M6+O6 -> 3061.3333 | L6: 407674 | M6: =IF(L6>=L5,L6-L5,0) -> 2948.3333 | N6: 426194 | O6: =IF(N6>=N5,N6-N5,0) -> 113 | P6: 228209 | Q6: =IF(P6>=P5,P6-P5,0)*30 -> 420 | R6: 235116 | S6: =IF(R6>=R5,R6-R5,0) -> 144.66667 | T6: 428793 | U6: =IF(T6>=T5,T6-T5,0) -> 245.33333 | V6: 898350 | W6: =IF(V6>=V5,V6-V5,0)*0.53 -> 1654.13 | X6: 839916 | Y6: =IF(X6>=X5,X6-X5,0)*0.53 -> 0 | Z6: 871759 | AA6: =IF(Z6>=Z5,Z6-Z5,0)*0.53 -> 0 | AB6: 184962 | AC6: =IF(AB6>=AB5,AB6-AB5,0)*0.53 -> 0 | AD6: 863349 | AE6: =IF(AD6>=AD5,AD6-AD5,0)*0.53 -> 26.5 | AF6: 1010964 | AG6: =IF(AF6>=AF5,AF6-AF5,0)*0.53 -> 12.72 | AH6: 445542 | AI6: =IF(AH6>=AH5,AH6-AH5,0)*0.53 -> 63.776667 | AJ6: 778570 | AK6: =IF(AJ6>=AJ5,AJ6-AJ5,0)*0.53 -> 1898.8133 | AL6: 581017 | AM6: =IF(AL6>=AL5,AL6-AL5,0)*0.53 -> 119.07333 | AN6: =W6+Y6+AA6+AC6+AE6+AG6+AI6+AK6+AM6 -> 3775.0133 | AO6: 8238032 | AP6: =IF(AO6>=AO5,AO6-AO5,0)*0.1125 -> 141.8625 | AQ6: 762477 | AR6: =IF(AQ6>=AQ5,AQ6-AQ5,0) -> 187.33333 | AS6: 23253 | AT6: =IF(AS6>=AS5,AS6-AS5,0) -> 138.66667 | AU6: 828537 | AV6: =IF(AU6>=AU5,AU6-AU5,0) -> 43.666667 | AW6: 2932952 | AX6: =IF(AW6>=AW5,AW6-AW5,0) -> 482.33333 | AY6: 235368 | AZ6: =IF(AY6>=AY5,AY6-AY5,0) -> 620 | BA6: 21098398 | BB6: =IF(BA6>=BA5,BA6-BA5,0) -> 4326.3333 | BC6: 653711 | BD6: =IF(BC6>=BC5,BC6-BC5,0) -> 232 | BE6: 47737 | BF6: =IF(BE6>=BE5,BE6-BE5,0) -> 37 | BG6: 26518250 | BH6: =IF(BG6>=BG5,BG6-BG5,0)-(0.45*BN6)-(0.45*BP6)-BR6 -> 4955.8 | BI6: =AP6+AR6+AT6+AV6+AX6+AZ6+BB6+BD6+BF6+BH6 -> 11164.996 | BJ6: =BI6+AN6 -> 14940.009 | BK6: 1508727 | BL6: =IF(BK6>=BK5,BK6-BK5,0) -> 356.33333 | BM6: 4370783 | BN6: =IF(BM6>=BM5,BM6-BM5,0) -> 929.66667 | BO6: 457830 | BP6: =IF(BO6>=BO5,BO6-BO5,0) -> 133 | BQ6: 570699 | BR6: =IF(BQ6>=BQ5,BQ6-BQ5,0) -> 121 | BS6: =J6+Q6+AN6+BI6 -> 22903.342 | BT6: 97 | BU6: =IF(BS6>0,BS6/BT5,0) -> #DIV/0! | BW6: =IF(BS6>0,BS6/BV6,0) -> #DIV/0! | BX6: =((BS6-Q6)*$BZ$1)+(Q6*$BR$1) -> 26527.844 | BY6: =IF(BX6>0,BX6/BT5,0) -> #DIV/0! | BZ6: =IF(BX6>0,BX6/BV6,0) -> #DIV/0!
A7: 2 | I7: 26005990 | J7: =IF(I7>=I6,I7-I6,0) -> 7209 | K7: =M7+O7 -> 6980 | L7: 410354 | M7: =IF(L7>=L6,L7-L6,0) -> 2680 | N7: 430494 | O7: =IF(N7>=N6,N7-N6,0) -> 4300 | P7: 228223 | Q7: =IF(P7>=P6,P7-P6,0)*30 -> 420 | R7: 235264 | S7: =IF(R7>=R6,R7-R6,0) -> 148 | T7: 429047 | U7: =IF(T7>=T6,T7-T6,0) -> 254 | V7: 902401 | W7: =IF(V7>=V6,V7-V6,0)*0.53 -> 2147.03 | X7: 839916 | Y7: =IF(X7>=X6,X7-X6,0)*0.53 -> 0 | Z7: 871759 | AA7: =IF(Z7>=Z6,Z7-Z6,0)*0.53 -> 0 | AB7: 184962 | AC7: =IF(AB7>=AB6,AB7-AB6,0)*0.53 -> 0 | AD7: 863375 | AE7: =IF(AD7>=AD6,AD7-AD6,0)*0.53 -> 13.78 | AF7: 1010988 | AG7: =IF(AF7>=AF6,AF7-AF6,0)*0.53 -> 12.72 | AH7: 445799 | AI7: =IF(AH7>=AH6,AH7-AH6,0)*0.53 -> 136.21 | AJ7: 782467 | AK7: =IF(AJ7>=AJ6,AJ7-AJ6,0)*0.53 -> 2065.41 | AL7: 581252 | AM7: =IF(AL7>=AL6,AL7-AL6,0)*0.53 -> 124.55 | AN7: =W7+Y7+AA7+AC7+AE7+AG7+AI7+AK7+AM7 -> 4499.7 | AO7: 8239349 | AP7: =IF(AO7>=AO6,AO7-AO6,0)*0.1125 -> 148.1625 | AQ7: 762672 | AR7: =IF(AQ7>=AQ6,AQ7-AQ6,0) -> 195 | AS7: 23383 | AT7: =IF(AS7>=AS6,AS7-AS6,0) -> 130 | AU7: 828581 | AV7: =IF(AU7>=AU6,AU7-AU6,0) -> 44 | AW7: 2933631 | AX7: =IF(AW7>=AW6,AW7-AW6,0) -> 679 | AY7: 236003 | AZ7: =IF(AY7>=AY6,AY7-AY6,0) -> 635 | BA7: 21103140 | BB7: =IF(BA7>=BA6,BA7-BA6,0) -> 4742 | BC7: 653888 | BD7: =IF(BC7>=BC6,BC7-BC6,0) -> 177 | BE7: 47776 | BF7: =IF(BE7>=BE6,BE7-BE6,0) -> 39 | BG7: 26524381 | BH7: =IF(BG7>=BG6,BG7-BG6,0)-(0.45*BN7)-(0.45*BP7)-BR7 -> 5478.75 | BI7: =AP7+AR7+AT7+AV7+AX7+AZ7+BB7+BD7+BF7+BH7 -> 12267.913 | BJ7: =BI7+AN7 -> 16767.613 | BK7: 1509016 | BL7: =IF(BK7>=BK6,BK7-BK6,0) -> 289 | BM7: 4371831 | BN7: =IF(BM7>=BM6,BM7-BM6,0) -> 1048 | BO7: 457947 | BP7: =IF(BO7>=BO6,BO7-BO6,0) -> 117 | BQ7: 570827 | BR7: =IF(BQ7>=BQ6,BQ7-BQ6,0) -> 128 | BS7: =J7+Q7+AN7+BI7 -> 24396.613 | BT7: 128 | BU7: =IF(BS7>0,BS7/BT6,0) -> 251.51147 | BW7: =IF(BS7>0,BS7/BV7,0) -> #DIV/0! | BX7: =((BS7-Q7)*$BZ$1)+(Q7*$BR$1) -> 28245.104 | BY7: =IF(BX7>0,BX7/BT6,0) -> 291.18664 | BZ7: =IF(BX7>0,BX7/BV7,0) -> #DIV/0!
A8: 3 | C8: =IF(+B8-B7>0,B8-B7,(B8-B7)>0)*800 -> 0 | E8: =IF(+D8-D7>0,D8-D7,(D8-D7)>0)*80 -> 0 | G8: =IF(+F8-F7>0,F8-F7,(F8-F7)>0)*10 -> 0 | H8: 57 | I8: 26012932 | J8: =IF(I8>=I7,I8-I7,0) -> 6942 | K8: =M8+O8 -> 4568 | L8: 412720 | M8: =IF(L8>=L7,L8-L7,0) -> 2366 | N8: 432696 | O8: =IF(N8>=N7,N8-N7,0) -> 2202 | P8: 228237 | Q8: =IF(P8>=P7,P8-P7,0)*30 -> 420 | R8: 235410 | S8: =IF(R8>=R7,R8-R7,0) -> 146 | T8: 429310 | U8: =IF(T8>=T7,T8-T7,0) -> 263 | V8: 906585 | W8: =IF(V8>=V7,V8-V7,0)*0.53 -> 2217.52 | X8: 839916 | Y8: =IF(X8>=X7,X8-X7,0)*0.53 -> 0 | Z8: 871793 | AA8: =IF(Z8>=Z7,Z8-Z7,0)*0.53 -> 18.02 | AB8: 184962 | AC8: =IF(AB8>=AB7,AB8-AB7,0)*0.53 -> 0 | AD8: 863399 | AE8: =IF(AD8>=AD7,AD8-AD7,0)*0.53 -> 12.72 | AF8: 1011011 | AG8: =IF(AF8>=AF7,AF8-AF7,0)*0.53 -> 12.19 | AH8: 446126 | AI8: =IF(AH8>=AH7,AH8-AH7,0)*0.53 -> 173.31 | AJ8: 786228 | AK8: =IF(AJ8>=AJ7,AJ8-AJ7,0)*0.53 -> 1993.33 | AL8: 581469 | AM8: =IF(AL8>=AL7,AL8-AL7,0)*0.53 -> 115.01 | AN8: =W8+Y8+AA8+AC8+AE8+AG8+AI8+AK8+AM8 -> 4542.1 | AO8: 8240653 | AP8: =IF(AO8>=AO7,AO8-AO7,0)*0.1125 -> 146.7 | AQ8: 762874 | AR8: =IF(AQ8>=AQ7,AQ8-AQ7,0) -> 202 | AS8: 23496 | AT8: =IF(AS8>=AS7,AS8-AS7,0) -> 113 | AU8: 828621 | AV8: =IF(AU8>=AU7,AU8-AU7,0) -> 40 | AW8: 2934274 | AX8: =IF(AW8>=AW7,AW8-AW7,0) -> 643 | AY8: 237043 | AZ8: =IF(AY8>=AY7,AY8-AY7,0) -> 1040 | BA8: 21107948 | BB8: =IF(BA8>=BA7,BA8-BA7,0) -> 4808 | BC8: 654087 | BD8: =IF(BC8>=BC7,BC8-BC7,0) -> 199 | BE8: 47816 | BF8: =IF(BE8>=BE7,BE8-BE7,0) -> 40 | BG8: 26530617 | BH8: =IF(BG8>=BG7,BG8-BG7,0)-(0.45*BN8)-(0.45*BP8)-BR8 -> 5578 | BI8: =AP8+AR8+AT8+AV8+AX8+AZ8+BB8+BD8+BF8+BH8 -> 12809.7 | BJ8: =BI8+AN8 -> 17351.8 | BK8: 1509257 | BL8: =IF(BK8>=BK7,BK8-BK7,0) -> 241 | BM8: 4372833 | BN8: =IF(BM8>=BM7,BM8-BM7,0) -> 1002 | BO8: 458065 | BP8: =IF(BO8>=BO7,BO8-BO7,0) -> 118 | BQ8: 570981 | BR8: =IF(BQ8>=BQ7,BQ8-BQ7,0) -> 154 | BS8: =J8+Q8+AN8+BI8 -> 24713.8 | BT8: 130 | BU8: =IF(BS8>0,BS8/BT7,0) -> 193.07656 | BW8: =IF(BS8>0,BS8/BV8,0) -> #DIV/0! | BX8: =((BS8-Q8)*$BZ$1)+(Q8*$BR$1) -> 28609.87 | BY8: =IF(BX8>0,BX8/BT7,0) -> 223.51461 | BZ8: =IF(BX8>0,BX8/BV8,0) -> #DIV/0!
A9: 4 | C9: =IF(+B9-B8>0,B9-B8,(B9-B8)>0)*800 -> 0 | E9: =IF(+D9-D8>0,D9-D8,(D9-D8)>0)*80 -> 0 | G9: =IF(+F9-F8>0,F9-F8,(F9-F8)>0)*10 -> 0 | I9: 26019851 | J9: =IF(I9>=I8,I9-I8,0) -> 6919 | K9: =M9+O9 -> 4728 | L9: 415074 | M9: =IF(L9>=L8,L9-L8,0) -> 2354 | N9: 435070 | O9: =IF(N9>=N8,N9-N8,0) -> 2374 | P9: 228249 | Q9: =IF(P9>=P8,P9-P8,0)*30 -> 360 | R9: 235552 | S9: =IF(R9>=R8,R9-R8,0) -> 142 | T9: 429563 | U9: =IF(T9>=T8,T9-T8,0) -> 253 | V9: 910669 | W9: =IF(V9>=V8,V9-V8,0)*0.53 -> 2164.52 | X9: 839916 | Y9: =IF(X9>=X8,X9-X8,0)*0.53 -> 0 | Z9: 871793 | AA9: =IF(Z9>=Z8,Z9-Z8,0)*0.53 -> 0 | AB9: 184962 | AC9: =IF(AB9>=AB8,AB9-AB8,0)*0.53 -> 0 | AD9: 863424 | AE9: =IF(AD9>=AD8,AD9-AD8,0)*0.53 -> 13.25 | AF9: 1011035 | AG9: =IF(AF9>=AF8,AF9-AF8,0)*0.53 -> 12.72 | AH9: 446455 | AI9: =IF(AH9>=AH8,AH9-AH8,0)*0.53 -> 174.37 | AJ9: 789983 | AK9: =IF(AJ9>=AJ8,AJ9-AJ8,0)*0.53 -> 1990.15 | AL9: 581683 | AM9: =IF(AL9>=AL8,AL9-AL8,0)*0.53 -> 113.42 | AN9: =W9+Y9+AA9+AC9+AE9+AG9+AI9+AK9+AM9 -> 4468.43 | AO9: 8242035 | AP9: =IF(AO9>=AO8,AO9-AO8,0)*0.1125 -> 155.475 | AQ9: 763076 | AR9: =IF(AQ9>=AQ8,AQ9-AQ8,0) -> 202 | AS9: 23607 | AT9: =IF(AS9>=AS8,AS9-AS8,0) -> 111 | AU9: 828661 | AV9: =IF(AU9>=AU8,AU9-AU8,0) -> 40 | AW9: 2934896 | AX9: =IF(AW9>=AW8,AW9-AW8,0) -> 622 | AY9: 237653 | AZ9: =IF(AY9>=AY8,AY9-AY8,0) -> 610 | BA9: 21112801 | BB9: =IF(BA9>=BA8,BA9-BA8,0) -> 4853 | BC9: 654265 | BD9: =IF(BC9>=BC8,BC9-BC8,0) -> 178 | BE9: 47856 | BF9: =IF(BE9>=BE8,BE9-BE8,0) -> 40 | BG9: 26536642 | BH9: =IF(BG9>=BG8,BG9-BG8,0)-(0.45*BN9)-(0.45*BP9)-BR9 -> 5359.95 | BI9: =AP9+AR9+AT9+AV9+AX9+AZ9+BB9+BD9+BF9+BH9 -> 12171.425 | BJ9: =BI9+AN9 -> 16639.855 | BK9: 1509345 | BL9: =IF(BK9>=BK8,BK9-BK8,0) -> 88 | BM9: 4373844 | BN9: =IF(BM9>=BM8,BM9-BM8,0) -> 1011 | BO9: 458183 | BP9: =IF(BO9>=BO8,BO9-BO8,0) -> 118 | BQ9: 571138 | BR9: =IF(BQ9>=BQ8,BQ9-BQ8,0) -> 157 | BS9: =J9+Q9+AN9+BI9 -> 23918.855 | BT9: 236 | BU9: =IF(BS9>0,BS9/BT8,0) -> 183.99119 | BW9: =IF(BS9>0,BS9/BV9,0) -> #DIV/0! | BX9: =((BS9-Q9)*$BZ$1)+(Q9*$BR$1) -> 27668.683 | BY9: =IF(BX9>0,BX9/BT8,0) -> 212.83602 | BZ9: =IF(BX9>0,BX9/BV9,0) -> #DIV/0!
A10: 5 | C10: =IF(+B10-B9>0,B10-B9,(B10-B9)>0)*800 -> 0 | E10: =IF(+D10-D9>0,D10-D9,(D10-D9)>0)*80 -> 0 | G10: =IF(+F10-F9>0,F10-F9,(F10-F9)>0)*10 -> 0 | H10: 58 | I10: 26026518 | J10: =IF(I10>=I9,I10-I9,0) -> 6667 | K10: =M10+O10 -> 4562.3333 | L10: 417377 | M10: =IF(L10>=L9,L10-L9,0) -> 2303 | N10: 437329.33 | O10: =IF(N10>=N9,N10-N9,0) -> 2259.3333 | P10: 228262 | Q10: =IF(P10>=P9,P10-P9,0)*30 -> 390 | R10: 235693 | S10: =IF(R10>=R9,R10-R9,0) -> 141 | T10: 429810 | U10: =IF(T10>=T9,T10-T9,0) -> 247 | V10: 914309 | W10: =IF(V10>=V9,V10-V9,0)*0.53 -> 1929.2 | X10: 839916 | Y10: =IF(X10>=X9,X10-X9,0)*0.53 -> 0 | Z10: 871793 | AA10: =IF(Z10>=Z9,Z10-Z9,0)*0.53 -> 0 | AB10: 184962 | AC10: =IF(AB10>=AB9,AB10-AB9,0)*0.53 -> 0 | AD10: 863447 | AE10: =IF(AD10>=AD9,AD10-AD9,0)*0.53 -> 12.19 | AF10: 1011058.3 | AG10: =IF(AF10>=AF9,AF10-AF9,0)*0.53 -> 12.366667 | AH10: 446749 | AI10: =IF(AH10>=AH9,AH10-AH9,0)*0.53 -> 155.82 | AJ10: 793536 | AK10: =IF(AJ10>=AJ9,AJ10-AJ9,0)*0.53 -> 1883.09 | AL10: 581899 | AM10: =IF(AL10>=AL9,AL10-AL9,0)*0.53 -> 114.48 | AN10: =W10+Y10+AA10+AC10+AE10+AG10+AI10+AK10+AM10 -> 4107.1467 | AO10: 8243366 | AP10: =IF(AO10>=AO9,AO10-AO9,0)*0.1125 -> 149.7375 | AQ10: 763274 | AR10: =IF(AQ10>=AQ9,AQ10-AQ9,0) -> 198 | AS10: 23728 | AT10: =IF(AS10>=AS9,AS10-AS9,0) -> 121 | AU10: 828701 | AV10: =IF(AU10>=AU9,AU10-AU9,0) -> 40 | AW10: 2935551 | AX10: =IF(AW10>=AW9,AW10-AW9,0) -> 655 | AY10: 238252 | AZ10: =IF(AY10>=AY9,AY10-AY9,0) -> 599 | BA10: 21117407 | BB10: =IF(BA10>=BA9,BA10-BA9,0) -> 4606 | BC10: 654451 | BD10: =IF(BC10>=BC9,BC10-BC9,0) -> 186 | BE10: 47896 | BF10: =IF(BE10>=BE9,BE10-BE9,0) -> 40 | BG10: 26542420 | BH10: =IF(BG10>=BG9,BG10-BG9,0)-(0.45*BN10)-(0.45*BP10)-BR10 -> 5121.25 | BI10: =AP10+AR10+AT10+AV10+AX10+AZ10+BB10+BD10+BF10+BH10 -> 11715.987 | BJ10: =BI10+AN10 -> 15823.134 | BK10: 1509448 | BL10: =IF(BK10>=BK9,BK10-BK9,0) -> 103 | BM10: 4374852 | BN10: =IF(BM10>=BM9,BM10-BM9,0) -> 1008 | BO10: 458290 | BP10: =IF(BO10>=BO9,BO10-BO9,0) -> 107 | BQ10: 571293 | BR10: =IF(BQ10>=BQ9,BQ10-BQ9,0) -> 155 | BS10: =J10+Q10+AN10+BI10 -> 22880.134 | BT10: 237 | BU10: =IF(BS10>0,BS10/BT9,0) -> 96.949721 | BW10: =IF(BS10>0,BS10/BV10,0) -> #DIV/0! | BX10: =((BS10-Q10)*$BZ$1)+(Q10*$BR$1) -> 26487.654 | BY10: =IF(BX10>0,BX10/BT9,0) -> 112.23582 | BZ10: =IF(BX10>0,BX10/BV10,0) -> #DIV/0!
A11: 6 | C11: =IF(+B11-B10>0,B11-B10,(B11-B10)>0)*800 -> 0 | E11: =IF(+D11-D10>0,D11-D10,(D11-D10)>0)*80 -> 0 | G11: =IF(+F11-F10>0,F11-F10,(F11-F10)>0)*10 -> 0 | I11: 26033737 | J11: =IF(I11>=I10,I11-I10,0) -> 7219 | K11: =M11+O11 -> 4924 | L11: 420013 | M11: =IF(L11>=L10,L11-L10,0) -> 2636 | N11: 439617.33 | O11: =IF(N11>=N10,N11-N10,0) -> 2288 | P11: 228277 | Q11: =IF(P11>=P10,P11-P10,0)*30 -> 450 | R11: 235835 | S11: =IF(R11>=R10,R11-R10,0) -> 142 | T11: 430058 | U11: =IF(T11>=T10,T11-T10,0) -> 248 | V11: 916737 | W11: =IF(V11>=V10,V11-V10,0)*0.53 -> 1286.84 | X11: 839916 | Y11: =IF(X11>=X10,X11-X10,0)*0.53 -> 0 | Z11: 871835 | AA11: =IF(Z11>=Z10,Z11-Z10,0)*0.53 -> 22.26 | AB11: 184962 | AC11: =IF(AB11>=AB10,AB11-AB10,0)*0.53 -> 0 | AD11: 863473 | AE11: =IF(AD11>=AD10,AD11-AD10,0)*0.53 -> 13.78 | AF11: 1011082 | AG11: =IF(AF11>=AF10,AF11-AF10,0)*0.53 -> 12.543333 | AH11: 447046 | AI11: =IF(AH11>=AH10,AH11-AH10,0)*0.53 -> 157.41 | AJ11: 796888 | AK11: =IF(AJ11>=AJ10,AJ11-AJ10,0)*0.53 -> 1776.56 | AL11: 582111 | AM11: =IF(AL11>=AL10,AL11-AL10,0)*0.53 -> 112.36 | AN11: =W11+Y11+AA11+AC11+AE11+AG11+AI11+AK11+AM11 -> 3381.7533 | AO11: 8244579 | AP11: =IF(AO11>=AO10,AO11-AO10,0)*0.1125 -> 136.4625 | AQ11: 763471 | AR11: =IF(AQ11>=AQ10,AQ11-AQ10,0) -> 197 | AS11: 23841 | AT11: =IF(AS11>=AS10,AS11-AS10,0) -> 113 | AU11: 828742 | AV11: =IF(AU11>=AU10,AU11-AU10,0) -> 41 | AW11: 2936270 | AX11: =IF(AW11>=AW10,AW11-AW10,0) -> 719 | AY11: 239198 | AZ11: =IF(AY11>=AY10,AY11-AY10,0) -> 946 | BA11: 21121777 | BB11: =IF(BA11>=BA10,BA11-BA10,0) -> 4370 | BC11: 654643 | BD11: =IF(BC11>=BC10,BC11-BC10,0) -> 192 | BE11: 47936 | BF11: =IF(BE11>=BE10,BE11-BE10,0) -> 40 | BG11: 26548144 | BH11: =IF(BG11>=BG10,BG11-BG10,0)-(0.45*BN11)-(0.45*BP11)-BR11 -> 5079.75 | BI11: =AP11+AR11+AT11+AV11+AX11+AZ11+BB11+BD11+BF11+BH11 -> 11834.212 | BJ11: =BI11+AN11 -> 15215.966 | BK11: 1509538 | BL11: =IF(BK11>=BK10,BK11-BK10,0) -> 90 | BM11: 4375830 | BN11: =IF(BM11>=BM10,BM11-BM10,0) -> 978 | BO11: 458397 | BP11: =IF(BO11>=BO10,BO11-BO10,0) -> 107 | BQ11: 571449 | BR11: =IF(BQ11>=BQ10,BQ11-BQ10,0) -> 156 | BS11: =J11+Q11+AN11+BI11 -> 22884.966 | BT11: 196 | BU11: =IF(BS11>0,BS11/BT10,0) -> 96.561037 | BW11: =IF(BS11>0,BS11/BV11,0) -> #DIV/0! | BX11: =((BS11-Q11)*$BZ$1)+(Q11*$BR$1) -> 26520.211 | BY11: =IF(BX11>0,BX11/BT10,0) -> 111.89962 | BZ11: =IF(BX11>0,BX11/BV11,0) -> #DIV/0!
A12: 7 | C12: =IF(+B12-B11>0,B12-B11,(B12-B11)>0)*800 -> 0 | E12: =IF(+D12-D11>0,D12-D11,(D12-D11)>0)*80 -> 0 | G12: =IF(+F12-F11>0,F12-F11,(F12-F11)>0)*10 -> 0 | H12: 59 | I12: 26041103 | J12: =IF(I12>=I11,I12-I11,0) -> 7366 | K12: =M12+O12 -> 5085 | L12: 422810 | M12: =IF(L12>=L11,L12-L11,0) -> 2797 | N12: 441905.33 | O12: =IF(N12>=N11,N12-N11,0) -> 2288 | P12: 228295 | Q12: =IF(P12>=P11,P12-P11,0)*30 -> 540 | R12: 235981 | S12: =IF(R12>=R11,R12-R11,0) -> 146 | T12: 430314 | U12: =IF(T12>=T11,T12-T11,0) -> 256 | V12: 919343 | W12: =IF(V12>=V11,V12-V11,0)*0.53 -> 1381.18 | X12: 839916 | Y12: =IF(X12>=X11,X12-X11,0)*0.53 -> 0 | Z12: 871835 | AA12: =IF(Z12>=Z11,Z12-Z11,0)*0.53 -> 0 | AB12: 184962 | AC12: =IF(AB12>=AB11,AB12-AB11,0)*0.53 -> 0 | AD12: 863498 | AE12: =IF(AD12>=AD11,AD12-AD11,0)*0.53 -> 13.25 | AF12: 1011106 | AG12: =IF(AF12>=AF11,AF12-AF11,0)*0.53 -> 12.72 | AH12: 447286 | AI12: =IF(AH12>=AH11,AH12-AH11,0)*0.53 -> 127.2 | AJ12: 800407 | AK12: =IF(AJ12>=AJ11,AJ12-AJ11,0)*0.53 -> 1865.07 | AL12: 582334 | AM12: =IF(AL12>=AL11,AL12-AL11,0)*0.53 -> 118.19 | AN12: =W12+Y12+AA12+AC12+AE12+AG12+AI12+AK12+AM12 -> 3517.61 | AO12: 8245605 | AP12: =IF(AO12>=AO11,AO12-AO11,0)*0.1125 -> 115.425 | AQ12: 763671 | AR12: =IF(AQ12>=AQ11,AQ12-AQ11,0) -> 200 | AS12: 23971 | AT12: =IF(AS12>=AS11,AS12-AS11,0) -> 130 | AU12: 828784 | AV12: =IF(AU12>=AU11,AU12-AU11,0) -> 42 | AW12: 2937024 | AX12: =IF(AW12>=AW11,AW12-AW11,0) -> 754 | AY12: 239775 | AZ12: =IF(AY12>=AY11,AY12-AY11,0) -> 577 | BA12: 21126209 | BB12: =IF(BA12>=BA11,BA12-BA11,0) -> 4432 | BC12: 654869 | BD12: =IF(BC12>=BC11,BC12-BC11,0) -> 226 | BE12: 47976 | BF12: =IF(BE12>=BE11,BE12-BE11,0) -> 40 | BG12: 26554102 | BH12: =IF(BG12>=BG11,BG12-BG11,0)-(0.45*BN12)-(0.45*BP12)-BR12 -> 5272.35 | BI12: =AP12+AR12+AT12+AV12+AX12+AZ12+BB12+BD12+BF12+BH12 -> 11788.775 | BJ12: =BI12+AN12 -> 15306.385 | BK12: 1509623 | BL12: =IF(BK12>=BK11,BK12-BK11,0) -> 85 | BM12: 4376873 | BN12: =IF(BM12>=BM11,BM12-BM11,0) -> 1043 | BO12: 458511 | BP12: =IF(BO12>=BO11,BO12-BO11,0) -> 114 | BQ12: 571614 | BR12: =IF(BQ12>=BQ11,BQ12-BQ11,0) -> 165 | BS12: =J12+Q12+AN12+BI12 -> 23212.385 | BT12: 163 | BU12: =IF(BS12>0,BS12/BT11,0) -> 118.43054 | BW12: =IF(BS12>0,BS12/BV12,0) -> #DIV/0! | BX12: =((BS12-Q12)*$BZ$1)+(Q12*$BR$1) -> 26937.243 | BY12: =IF(BX12>0,BX12/BT11,0) -> 137.43491 | BZ12: =IF(BX12>0,BX12/BV12,0) -> #DIV/0!
A13: 8 | C13: =IF(+B13-B12>0,B13-B12,(B13-B12)>0)*800 -> 0 | E13: =IF(+D13-D12>0,D13-D12,(D13-D12)>0)*80 -> 0 | G13: =IF(+F13-F12>0,F13-F12,(F13-F12)>0)*10 -> 0 | I13: 26048469 | J13: =IF(I13>=I12,I13-I12,0) -> 7366 | K13: =M13+O13 -> 5113 | L13: 425635 | M13: =IF(L13>=L12,L13-L12,0) -> 2825 | N13: 444193.33 | O13: =IF(N13>=N12,N13-N12,0) -> 2288 | P13: 228310 | Q13: =IF(P13>=P12,P13-P12,0)*30 -> 450 | R13: 236127 | S13: =IF(R13>=R12,R13-R12,0) -> 146 | T13: 430566 | U13: =IF(T13>=T12,T13-T12,0) -> 252 | V13: 921760 | W13: =IF(V13>=V12,V13-V12,0)*0.53 -> 1281.01 | X13: 839916 | Y13: =IF(X13>=X12,X13-X12,0)*0.53 -> 0 | Z13: 871835 | AA13: =IF(Z13>=Z12,Z13-Z12,0)*0.53 -> 0 | AB13: 184962 | AC13: =IF(AB13>=AB12,AB13-AB12,0)*0.53 -> 0 | AD13: 863524 | AE13: =IF(AD13>=AD12,AD13-AD12,0)*0.53 -> 13.78 | AF13: 1011131 | AG13: =IF(AF13>=AF12,AF13-AF12,0)*0.53 -> 13.25 | AH13: 447509 | AI13: =IF(AH13>=AH12,AH13-AH12,0)*0.53 -> 118.19 | AJ13: 803744 | AK13: =IF(AJ13>=AJ12,AJ13-AJ12,0)*0.53 -> 1768.61 | AL13: 582557 | AM13: =IF(AL13>=AL12,AL13-AL12,0)*0.53 -> 118.19 | AN13: =W13+Y13+AA13+AC13+AE13+AG13+AI13+AK13+AM13 -> 3313.03 | AO13: 8246130 | AP13: =IF(AO13>=AO12,AO13-AO12,0)*0.1125 -> 59.0625 | AQ13: 763878 | AR13: =IF(AQ13>=AQ12,AQ13-AQ12,0) -> 207 | AS13: 24070 | AT13: =IF(AS13>=AS12,AS13-AS12,0) -> 99 | AU13: 828825 | AV13: =IF(AU13>=AU12,AU13-AU12,0) -> 41 | AW13: 2937759 | AX13: =IF(AW13>=AW12,AW13-AW12,0) -> 735 | AY13: 240400 | AZ13: =IF(AY13>=AY12,AY13-AY12,0) -> 625 | BA13: 21130949 | BB13: =IF(BA13>=BA12,BA13-BA12,0) -> 4740 | BC13: 655056 | BD13: =IF(BC13>=BC12,BC13-BC12,0) -> 187 | BE13: 48016 | BF13: =IF(BE13>=BE12,BE13-BE12,0) -> 40 | BG13: 26560213 | BH13: =IF(BG13>=BG12,BG13-BG12,0)-(0.45*BN13)-(0.45*BP13)-BR13 -> 5438.5 | BI13: =AP13+AR13+AT13+AV13+AX13+AZ13+BB13+BD13+BF13+BH13 -> 12171.562 | BJ13: =BI13+AN13 -> 15484.593 | BK13: 1509920 | BL13: =IF(BK13>=BK12,BK13-BK12,0) -> 297 | BM13: 4377891 | BN13: =IF(BM13>=BM12,BM13-BM12,0) -> 1018 | BO13: 458623 | BP13: =IF(BO13>=BO12,BO13-BO12,0) -> 112 | BQ13: 571778 | BR13: =IF(BQ13>=BQ12,BQ13-BQ12,0) -> 164 | BS13: =J13+Q13+AN13+BI13 -> 23300.592 | BT13: 149 | BU13: =IF(BS13>0,BS13/BT12,0) -> 142.94842 | BW13: =IF(BS13>0,BS13/BV13,0) -> #DIV/0! | BX13: =((BS13-Q13)*$BZ$1)+(Q13*$BR$1) -> 26998.181 | BY13: =IF(BX13>0,BX13/BT12,0) -> 165.63301 | BZ13: =IF(BX13>0,BX13/BV13,0) -> #DIV/0!
A14: 9 | C14: =IF(+B14-B13>0,B14-B13,(B14-B13)>0)*800 -> 0 | E14: =IF(+D14-D13>0,D14-D13,(D14-D13)>0)*80 -> 0 | G14: =IF(+F14-F13>0,F14-F13,(F14-F13)>0)*10 -> 0 | H14: 60 | I14: 26055788 | J14: =IF(I14>=I13,I14-I13,0) -> 7319 | K14: =M14+O14 -> 5084 | L14: 428431 | M14: =IF(L14>=L13,L14-L13,0) -> 2796 | N14: 446481.33 | O14: =IF(N14>=N13,N14-N13,0) -> 2288 | P14: 228324 | Q14: =IF(P14>=P13,P14-P13,0)*30 -> 420 | R14: 236268 | S14: =IF(R14>=R13,R14-R13,0) -> 141 | T14: 430818 | U14: =IF(T14>=T13,T14-T13,0) -> 252 | V14: 924301 | W14: =IF(V14>=V13,V14-V13,0)*0.53 -> 1346.73 | X14: 839916 | Y14: =IF(X14>=X13,X14-X13,0)*0.53 -> 0 | Z14: 871835 | AA14: =IF(Z14>=Z13,Z14-Z13,0)*0.53 -> 0 | AB14: 184962 | AC14: =IF(AB14>=AB13,AB14-AB13,0)*0.53 -> 0 | AD14: 863549 | AE14: =IF(AD14>=AD13,AD14-AD13,0)*0.53 -> 13.25 | AF14: 1011155 | AG14: =IF(AF14>=AF13,AF14-AF13,0)*0.53 -> 12.72 | AH14: 447736 | AI14: =IF(AH14>=AH13,AH14-AH13,0)*0.53 -> 120.31 | AJ14: 807066 | AK14: =IF(AJ14>=AJ13,AJ14-AJ13,0)*0.53 -> 1760.66 | AL14: 582767 | AM14: =IF(AL14>=AL13,AL14-AL13,0)*0.53 -> 111.3 | AN14: =W14+Y14+AA14+AC14+AE14+AG14+AI14+AK14+AM14 -> 3364.97 | AO14: 8247203 | AP14: =IF(AO14>=AO13,AO14-AO13,0)*0.1125 -> 120.7125 | AQ14: 764081 | AR14: =IF(AQ14>=AQ13,AQ14-AQ13,0) -> 203 | AS14: 24178 | AT14: =IF(AS14>=AS13,AS14-AS13,0) -> 108 | AU14: 828865 | AV14: =IF(AU14>=AU13,AU14-AU13,0) -> 40 | AW14: 2938499 | AX14: =IF(AW14>=AW13,AW14-AW13,0) -> 740 | AY14: 240982 | AZ14: =IF(AY14>=AY13,AY14-AY13,0) -> 582 | BA14: 21135495 | BB14: =IF(BA14>=BA13,BA14-BA13,0) -> 4546 | BC14: 655224 | BD14: =IF(BC14>=BC13,BC14-BC13,0) -> 168 | BE14: 48051 | BF14: =IF(BE14>=BE13,BE14-BE13,0) -> 35 | BG14: 26566079 | BH14: =IF(BG14>=BG13,BG14-BG13,0)-(0.45*BN14)-(0.45*BP14)-BR14 -> 5260 | BI14: =AP14+AR14+AT14+AV14+AX14+AZ14+BB14+BD14+BF14+BH14 -> 11802.712 | BJ14: =BI14+AN14 -> 15167.682 | BK14: 1510187 | BL14: =IF(BK14>=BK13,BK14-BK13,0) -> 267 | BM14: 4378863 | BN14: =IF(BM14>=BM13,BM14-BM13,0) -> 972 | BO14: 458731 | BP14: =IF(BO14>=BO13,BO14-BO13,0) -> 108 | BQ14: 571898 | BR14: =IF(BQ14>=BQ13,BQ14-BQ13,0) -> 120 | BS14: =J14+Q14+AN14+BI14 -> 22906.683 | BT14: 162 | BU14: =IF(BS14>0,BS14/BT13,0) -> 153.73612 | BW14: =IF(BS14>0,BS14/BV14,0) -> #DIV/0! | BX14: =((BS14-Q14)*$BZ$1)+(Q14*$BR$1) -> 26531.685 | BY14: =IF(BX14>0,BX14/BT13,0) -> 178.065 | BZ14: =IF(BX14>0,BX14/BV14,0) -> #DIV/0!
A15: 10 | C15: =IF(+B15-B14>0,B15-B14,(B15-B14)>0)*800 -> 0 | E15: =IF(+D15-D14>0,D15-D14,(D15-D14)>0)*80 -> 0 | G15: =IF(+F15-F14>0,F15-F14,(F15-F14)>0)*10 -> 0 | I15: 26063320 | J15: =IF(I15>=I14,I15-I14,0) -> 7532 | K15: =M15+O15 -> 4924 | L15: 431067 | M15: =IF(L15>=L14,L15-L14,0) -> 2636 | N15: 448769.33 | O15: =IF(N15>=N14,N15-N14,0) -> 2288 | P15: 228340 | Q15: =IF(P15>=P14,P15-P14,0)*30 -> 480 | R15: 236413 | S15: =IF(R15>=R14,R15-R14,0) -> 145 | T15: 431080 | U15: =IF(T15>=T14,T15-T14,0) -> 262 | V15: 926812 | W15: =IF(V15>=V14,V15-V14,0)*0.53 -> 1330.83 | X15: 839916 | Y15: =IF(X15>=X14,X15-X14,0)*0.53 -> 0 | Z15: 871835 | AA15: =IF(Z15>=Z14,Z15-Z14,0)*0.53 -> 0 | AB15: 184962 | AC15: =IF(AB15>=AB14,AB15-AB14,0)*0.53 -> 0 | AD15: 863579 | AE15: =IF(AD15>=AD14,AD15-AD14,0)*0.53 -> 15.9 | AF15: 1011178 | AG15: =IF(AF15>=AF14,AF15-AF14,0)*0.53 -> 12.19 | AH15: 447973 | AI15: =IF(AH15>=AH14,AH15-AH14,0)*0.53 -> 125.61 | AJ15: 809868 | AK15: =IF(AJ15>=AJ14,AJ15-AJ14,0)*0.53 -> 1485.06 | AL15: 582975 | AM15: =IF(AL15>=AL14,AL15-AL14,0)*0.53 -> 110.24 | AN15: =W15+Y15+AA15+AC15+AE15+AG15+AI15+AK15+AM15 -> 3079.83 | AO15: 8248101 | AP15: =IF(AO15>=AO14,AO15-AO14,0)*0.1125 -> 101.025 | AQ15: 764255 | AR15: =IF(AQ15>=AQ14,AQ15-AQ14,0) -> 174 | AS15: 24318 | AT15: =IF(AS15>=AS14,AS15-AS14,0) -> 140 | AU15: 828905 | AV15: =IF(AU15>=AU14,AU15-AU14,0) -> 40 | AW15: 2939239 | AX15: =IF(AW15>=AW14,AW15-AW14,0) -> 740 | AY15: 240992 | AZ15: =IF(AY15>=AY14,AY15-AY14,0) -> 10 | BA15: 21140199 | BB15: =IF(BA15>=BA14,BA15-BA14,0) -> 4704 | BC15: 655400 | BD15: =IF(BC15>=BC14,BC15-BC14,0) -> 176 | BE15: 48086 | BF15: =IF(BE15>=BE14,BE15-BE14,0) -> 35 | BG15: 26572085 | BH15: =IF(BG15>=BG14,BG15-BG14,0)-(0.45*BN15)-(0.45*BP15)-BR15 -> 5358.05 | BI15: =AP15+AR15+AT15+AV15+AX15+AZ15+BB15+BD15+BF15+BH15 -> 11478.075 | BJ15: =BI15+AN15 -> 14557.905 | BK15: 1510464 | BL15: =IF(BK15>=BK14,BK15-BK14,0) -> 277 | BM15: 4379841 | BN15: =IF(BM15>=BM14,BM15-BM14,0) -> 978 | BO15: 458844 | BP15: =IF(BO15>=BO14,BO15-BO14,0) -> 113 | BQ15: 572055 | BR15: =IF(BQ15>=BQ14,BQ15-BQ14,0) -> 157 | BS15: =J15+Q15+AN15+BI15 -> 22569.905 | BT15: 176 | BU15: =IF(BS15>0,BS15/BT14,0) -> 139.3204 | BW15: =IF(BS15>0,BS15/BV15,0) -> #DIV/0! | BX15: =((BS15-Q15)*$BZ$1)+(Q15*$BR$1) -> 26171.391 | BY15: =IF(BX15>0,BX15/BT14,0) -> 161.55179 | BZ15: =IF(BX15>0,BX15/BV15,0) -> #DIV/0!
A16: 11 | C16: =IF(+B16-B15>0,B16-B15,(B16-B15)>0)*800 -> 0 | E16: =IF(+D16-D15>0,D16-D15,(D16-D15)>0)*80 -> 0 | G16: =IF(+F16-F15>0,F16-F15,(F16-F15)>0)*10 -> 0 | H16: 61 | I16: 26070419 | J16: =IF(I16>=I15,I16-I15,0) -> 7099 | K16: =M16+O16 -> 4845 | L16: 433624 | M16: =IF(L16>=L15,L16-L15,0) -> 2557 | N16: 451057.33 | O16: =IF(N16>=N15,N16-N15,0) -> 2288 | P16: 228354 | Q16: =IF(P16>=P15,P16-P15,0)*30 -> 420 | R16: 236550 | S16: =IF(R16>=R15,R16-R15,0) -> 137 | T16: 431328 | U16: =IF(T16>=T15,T16-T15,0) -> 248 | V16: 929828 | W16: =IF(V16>=V15,V16-V15,0)*0.53 -> 1598.48 | X16: 839916 | Y16: =IF(X16>=X15,X16-X15,0)*0.53 -> 0 | Z16: 871835 | AA16: =IF(Z16>=Z15,Z16-Z15,0)*0.53 -> 0 | AB16: 184962 | AC16: =IF(AB16>=AB15,AB16-AB15,0)*0.53 -> 0 | AD16: 863598 | AE16: =IF(AD16>=AD15,AD16-AD15,0)*0.53 -> 10.07 | AF16: 1011202 | AG16: =IF(AF16>=AF15,AF16-AF15,0)*0.53 -> 12.72 | AH16: 448260 | AI16: =IF(AH16>=AH15,AH16-AH15,0)*0.53 -> 152.11 | AJ16: 813241 | AK16: =IF(AJ16>=AJ15,AJ16-AJ15,0)*0.53 -> 1787.69 | AL16: 583186 | AM16: =IF(AL16>=AL15,AL16-AL15,0)*0.53 -> 111.83 | AN16: =W16+Y16+AA16+AC16+AE16+AG16+AI16+AK16+AM16 -> 3672.9 | AO16: 8249117 | AP16: =IF(AO16>=AO15,AO16-AO15,0)*0.1125 -> 114.3 | AQ16: 764442 | AR16: =IF(AQ16>=AQ15,AQ16-AQ15,0) -> 187 | AS16: 24450 | AT16: =IF(AS16>=AS15,AS16-AS15,0) -> 132 | AU16: 828946 | AV16: =IF(AU16>=AU15,AU16-AU15,0) -> 41 | AW16: 2939983 | AX16: =IF(AW16>=AW15,AW16-AW15,0) -> 744 | AY16: 241002 | AZ16: =IF(AY16>=AY15,AY16-AY15,0) -> 10 | BA16: 21144793 | BB16: =IF(BA16>=BA15,BA16-BA15,0) -> 4594 | BC16: 655593 | BD16: =IF(BC16>=BC15,BC16-BC15,0) -> 193 | BE16: 48126 | BF16: =IF(BE16>=BE15,BE16-BE15,0) -> 40 | BG16: 26578049 | BH16: =IF(BG16>=BG15,BG16-BG15,0)-(0.45*BN16)-(0.45*BP16)-BR16 -> 5336.8 | BI16: =AP16+AR16+AT16+AV16+AX16+AZ16+BB16+BD16+BF16+BH16 -> 11392.1 | BJ16: =BI16+AN16 -> 15065 | BK16: 1510733 | BL16: =IF(BK16>=BK15,BK16-BK15,0) -> 269 | BM16: 4380788 | BN16: =IF(BM16>=BM15,BM16-BM15,0) -> 947 | BO16: 458953 | BP16: =IF(BO16>=BO15,BO16-BO15,0) -> 109 | BQ16: 572207 | BR16: =IF(BQ16>=BQ15,BQ16-BQ15,0) -> 152 | BS16: =J16+Q16+AN16+BI16 -> 22584 | BT16: 234 | BU16: =IF(BS16>0,BS16/BT15,0) -> 128.31818 | BW16: =IF(BS16>0,BS16/BV16,0) -> #DIV/0! | BX16: =((BS16-Q16)*$BZ$1)+(Q16*$BR$1) -> 26160.6 | BY16: =IF(BX16>0,BX16/BT15,0) -> 148.63977 | BZ16: =IF(BX16>0,BX16/BV16,0) -> #DIV/0!
A17: 12 | C17: =IF(+B17-B16>0,B17-B16,(B17-B16)>0)*800 -> 0 | E17: =IF(+D17-D16>0,D17-D16,(D17-D16)>0)*80 -> 0 | G17: =IF(+F17-F16>0,F17-F16,(F17-F16)>0)*10 -> 0 | I17: 26079439 | J17: =IF(I17>=I16,I17-I16,0) -> 9020 | K17: =M17+O17 -> 4796 | L17: 436132 | M17: =IF(L17>=L16,L17-L16,0) -> 2508 | N17: 453345.33 | O17: =IF(N17>=N16,N17-N16,0) -> 2288 | P17: 228369 | Q17: =IF(P17>=P16,P17-P16,0)*30 -> 450 | R17: 236705 | S17: =IF(R17>=R16,R17-R16,0) -> 155 | T17: 431596 | U17: =IF(T17>=T16,T17-T16,0) -> 268 | V17: 932736 | W17: =IF(V17>=V16,V17-V16,0)*0.53 -> 1541.24 | X17: 839916 | Y17: =IF(X17>=X16,X17-X16,0)*0.53 -> 0 | Z17: 871835 | AA17: =IF(Z17>=Z16,Z17-Z16,0)*0.53 -> 0 | AB17: 184962 | AC17: =IF(AB17>=AB16,AB17-AB16,0)*0.53 -> 0 | AD17: 863624 | AE17: =IF(AD17>=AD16,AD17-AD16,0)*0.53 -> 13.78 | AF17: 1011226 | AG17: =IF(AF17>=AF16,AF17-AF16,0)*0.53 -> 12.72 | AH17: 448556 | AI17: =IF(AH17>=AH16,AH17-AH16,0)*0.53 -> 156.88 | AJ17: 816762 | AK17: =IF(AJ17>=AJ16,AJ17-AJ16,0)*0.53 -> 1866.13 | AL17: 583405 | AM17: =IF(AL17>=AL16,AL17-AL16,0)*0.53 -> 116.07 | AN17: =W17+Y17+AA17+AC17+AE17+AG17+AI17+AK17+AM17 -> 3706.82 | AO17: 8249636 | AP17: =IF(AO17>=AO16,AO17-AO16,0)*0.1125 -> 58.3875 | AQ17: 764649 | AR17: =IF(AQ17>=AQ16,AQ17-AQ16,0) -> 207 | AS17: 24581 | AT17: =IF(AS17>=AS16,AS17-AS16,0) -> 131 | AU17: 828988 | AV17: =IF(AU17>=AU16,AU17-AU16,0) -> 42 | AW17: 2940737 | AX17: =IF(AW17>=AW16,AW17-AW16,0) -> 754 | AY17: 241013 | AZ17: =IF(AY17>=AY16,AY17-AY16,0) -> 11 | BA17: 21149640 | BB17: =IF(BA17>=BA16,BA17-BA16,0) -> 4847 | BC17: 655845 | BD17: =IF(BC17>=BC16,BC17-BC16,0) -> 252 | BE17: 48166 | BF17: =IF(BE17>=BE16,BE17-BE16,0) -> 40 | BG17: 26584458 | BH17: =IF(BG17>=BG16,BG17-BG16,0)-(0.45*BN17)-(0.45*BP17)-BR17 -> 5740.15 | BI17: =AP17+AR17+AT17+AV17+AX17+AZ17+BB17+BD17+BF17+BH17 -> 12082.538 | BJ17: =BI17+AN17 -> 15789.358 | BK17: 1510942 | BL17: =IF(BK17>=BK16,BK17-BK16,0) -> 209 | BM17: 4381784 | BN17: =IF(BM17>=BM16,BM17-BM16,0) -> 996 | BO17: 459070 | BP17: =IF(BO17>=BO16,BO17-BO16,0) -> 117 | BQ17: 572375 | BR17: =IF(BQ17>=BQ16,BQ17-BQ16,0) -> 168 | BS17: =J17+Q17+AN17+BI17 -> 25259.357 | BT17: 240 | BU17: =IF(BS17>0,BS17/BT16,0) -> 107.94597 | BW17: =IF(BS17>0,BS17/BV17,0) -> #DIV/0! | BX17: =((BS17-Q17)*$BZ$1)+(Q17*$BR$1) -> 29250.761 | BY17: =IF(BX17>0,BX17/BT16,0) -> 125.00325 | BZ17: =IF(BX17>0,BX17/BV17,0) -> #DIV/0!
A18: 13 | C18: =IF(+B18-B17>0,B18-B17,(B18-B17)>0)*800 -> 0 | E18: =IF(+D18-D17>0,D18-D17,(D18-D17)>0)*80 -> 0 | G18: =IF(+F18-F17>0,F18-F17,(F18-F17)>0)*10 -> 0 | H18: 62 | I18: 26084996 | J18: =IF(I18>=I17,I18-I17,0) -> 5557 | K18: =M18+O18 -> 2502 | L18: 438634 | M18: =IF(L18>=L17,L18-L17,0) -> 2502 | N18: 436613 | O18: =IF(N18>=N17,N18-N17,0) -> 0 | P18: 228388 | Q18: =IF(P18>=P17,P18-P17,0)*30 -> 570 | R18: 236843 | S18: =IF(R18>=R17,R18-R17,0) -> 138 | T18: 431833 | U18: =IF(T18>=T17,T18-T17,0) -> 237 | V18: 935595 | W18: =IF(V18>=V17,V18-V17,0)*0.53 -> 1515.27 | X18: 839916 | Y18: =IF(X18>=X17,X18-X17,0)*0.53 -> 0 | Z18: 871835 | AA18: =IF(Z18>=Z17,Z18-Z17,0)*0.53 -> 0 | AB18: 184962 | AC18: =IF(AB18>=AB17,AB18-AB17,0)*0.53 -> 0 | AD18: 863650 | AE18: =IF(AD18>=AD17,AD18-AD17,0)*0.53 -> 13.78 | AF18: 1011250 | AG18: =IF(AF18>=AF17,AF18-AF17,0)*0.53 -> 12.72 | AH18: 448850 | AI18: =IF(AH18>=AH17,AH18-AH17,0)*0.53 -> 155.82 | AJ18: 820516 | AK18: =IF(AJ18>=AJ17,AJ18-AJ17,0)*0.53 -> 1989.62 | AL18: 583613 | AM18: =IF(AL18>=AL17,AL18-AL17,0)*0.53 -> 110.24 | AN18: =W18+Y18+AA18+AC18+AE18+AG18+AI18+AK18+AM18 -> 3797.45 | AO18: 8250487 | AP18: =IF(AO18>=AO17,AO18-AO17,0)*0.1125 -> 95.7375 | AQ18: 764835 | AR18: =IF(AQ18>=AQ17,AQ18-AQ17,0) -> 186 | AS18: 24724 | AT18: =IF(AS18>=AS17,AS18-AS17,0) -> 143 | AU18: 829028 | AV18: =IF(AU18>=AU17,AU18-AU17,0) -> 40 | AW18: 2941422 | AX18: =IF(AW18>=AW17,AW18-AW17,0) -> 685 | AY18: 241023 | AZ18: =IF(AY18>=AY17,AY18-AY17,0) -> 10 | BA18: 21154504 | BB18: =IF(BA18>=BA17,BA18-BA17,0) -> 4864 | BC18: 656113 | BD18: =IF(BC18>=BC17,BC18-BC17,0) -> 268 | BE18: 48240 | BF18: =IF(BE18>=BE17,BE18-BE17,0) -> 74 | BG18: 26590481 | BH18: =IF(BG18>=BG17,BG18-BG17,0)-(0.45*BN18)-(0.45*BP18)-BR18 -> 5377.35 | BI18: =AP18+AR18+AT18+AV18+AX18+AZ18+BB18+BD18+BF18+BH18 -> 11743.087 | BJ18: =BI18+AN18 -> 15540.537 | BK18: 1511139 | BL18: =IF(BK18>=BK17,BK18-BK17,0) -> 197 | BM18: 4382753 | BN18: =IF(BM18>=BM17,BM18-BM17,0) -> 969 | BO18: 459178 | BP18: =IF(BO18>=BO17,BO18-BO17,0) -> 108 | BQ18: 572536 | BR18: =IF(BQ18>=BQ17,BQ18-BQ17,0) -> 161 | BS18: =J18+Q18+AN18+BI18 -> 21667.537 | BT18: 246 | BU18: =IF(BS18>0,BS18/BT17,0) -> 90.281406 | BW18: =IF(BS18>0,BS18/BV18,0) -> #DIV/0! | BX18: =((BS18-Q18)*$BZ$1)+(Q18*$BR$1) -> 25174.168 | BY18: =IF(BX18>0,BX18/BT17,0) -> 104.89237 | BZ18: =IF(BX18>0,BX18/BV18,0) -> #DIV/0!
A19: 14 | C19: =IF(+B19-B18>0,B19-B18,(B19-B18)>0)*800 -> 0 | E19: =IF(+D19-D18>0,D19-D18,(D19-D18)>0)*80 -> 0 | G19: =IF(+F19-F18>0,F19-F18,(F19-F18)>0)*10 -> 0 | I19: 26092740 | J19: =IF(I19>=I18,I19-I18,0) -> 7744 | K19: =M19+O19 -> 4326 | L19: 441232 | M19: =IF(L19>=L18,L19-L18,0) -> 2598 | N19: 438341 | O19: =IF(N19>=N18,N19-N18,0) -> 1728 | P19: 228406 | Q19: =IF(P19>=P18,P19-P18,0)*30 -> 540 | R19: 236987 | S19: =IF(R19>=R18,R19-R18,0) -> 144 | T19: 432084 | U19: =IF(T19>=T18,T19-T18,0) -> 251 | V19: 938453 | W19: =IF(V19>=V18,V19-V18,0)*0.53 -> 1514.74 | X19: 839916 | Y19: =IF(X19>=X18,X19-X18,0)*0.53 -> 0 | Z19: 871835 | AA19: =IF(Z19>=Z18,Z19-Z18,0)*0.53 -> 0 | AB19: 184462 | AC19: =IF(AB19>=AB18,AB19-AB18,0)*0.53 -> 0 | AD19: 863679 | AE19: =IF(AD19>=AD18,AD19-AD18,0)*0.53 -> 15.37 | AF19: 1011277 | AG19: =IF(AF19>=AF18,AF19-AF18,0)*0.53 -> 14.31 | AH19: 449139 | AI19: =IF(AH19>=AH18,AH19-AH18,0)*0.53 -> 153.17 | AJ19: 824228 | AK19: =IF(AJ19>=AJ18,AJ19-AJ18,0)*0.53 -> 1967.36 | AL19: 583834 | AM19: =IF(AL19>=AL18,AL19-AL18,0)*0.53 -> 117.13 | AN19: =W19+Y19+AA19+AC19+AE19+AG19+AI19+AK19+AM19 -> 3782.08 | AO19: 8250897 | AP19: =IF(AO19>=AO18,AO19-AO18,0)*0.1125 -> 46.125 | AQ19: 765028 | AR19: =IF(AQ19>=AQ18,AQ19-AQ18,0) -> 193 | AS19: 24845 | AT19: =IF(AS19>=AS18,AS19-AS18,0) -> 121 | AU19: 829069 | AV19: =IF(AU19>=AU18,AU19-AU18,0) -> 41 | AW19: 2942094 | AX19: =IF(AW19>=AW18,AW19-AW18,0) -> 672 | AY19: 241033 | AZ19: =IF(AY19>=AY18,AY19-AY18,0) -> 10 | BA19: 21158900 | BB19: =IF(BA19>=BA18,BA19-BA18,0) -> 4396 | BC19: 656356 | BD19: =IF(BC19>=BC18,BC19-BC18,0) -> 243 | BE19: 48348 | BF19: =IF(BE19>=BE18,BE19-BE18,0) -> 108 | BG19: 26596553 | BH19: =IF(BG19>=BG18,BG19-BG18,0)-(0.45*BN19)-(0.45*BP19)-BR19 -> 5509.35 | BI19: =AP19+AR19+AT19+AV19+AX19+AZ19+BB19+BD19+BF19+BH19 -> 11339.475 | BJ19: =BI19+AN19 -> 15121.555 | BK19: 1511337 | BL19: =IF(BK19>=BK18,BK19-BK18,0) -> 198 | BM19: 4383625 | BN19: =IF(BM19>=BM18,BM19-BM18,0) -> 872 | BO19: 459283 | BP19: =IF(BO19>=BO18,BO19-BO18,0) -> 105 | BQ19: 572659 | BR19: =IF(BQ19>=BQ18,BQ19-BQ18,0) -> 123 | BS19: =J19+Q19+AN19+BI19 -> 23405.555 | BT19: 252 | BU19: =IF(BS19>0,BS19/BT18,0) -> 95.144533 | BW19: =IF(BS19>0,BS19/BV19,0) -> #DIV/0! | BX19: =((BS19-Q19)*$BZ$1)+(Q19*$BR$1) -> 27159.388 | BY19: =IF(BX19>0,BX19/BT18,0) -> 110.40402 | BZ19: =IF(BX19>0,BX19/BV19,0) -> #DIV/0!
A20: 15 | C20: =IF(+B20-B19>0,B20-B19,(B20-B19)>0)*800 -> 0 | E20: =IF(+D20-D19>0,D20-D19,(D20-D19)>0)*80 -> 0 | G20: =IF(+F20-F19>0,F20-F19,(F20-F19)>0)*10 -> 0 | H20: 63 | I20: 26099853 | J20: =IF(I20>=I19,I20-I19,0) -> 7113 | K20: =M20+O20 -> 4164 | L20: 443743 | M20: =IF(L20>=L19,L20-L19,0) -> 2511 | N20: 439994 | O20: =IF(N20>=N19,N20-N19,0) -> 1653 | P20: 228424 | Q20: =IF(P20>=P19,P20-P19,0)*30 -> 540 | R20: 237127 | S20: =IF(R20>=R19,R20-R19,0) -> 140 | T20: 432323 | U20: =IF(T20>=T19,T20-T19,0) -> 239 | V20: 941264 | W20: =IF(V20>=V19,V20-V19,0)*0.53 -> 1489.83 | X20: 839916 | Y20: =IF(X20>=X19,X20-X19,0)*0.53 -> 0 | Z20: 871835 | AA20: =IF(Z20>=Z19,Z20-Z19,0)*0.53 -> 0 | AB20: 184462 | AC20: =IF(AB20>=AB19,AB20-AB19,0)*0.53 -> 0 | AD20: 863702 | AE20: =IF(AD20>=AD19,AD20-AD19,0)*0.53 -> 12.19 | AF20: 1011299 | AG20: =IF(AF20>=AF19,AF20-AF19,0)*0.53 -> 11.66 | AH20: 449418 | AI20: =IF(AH20>=AH19,AH20-AH19,0)*0.53 -> 147.87 | AJ20: 827806 | AK20: =IF(AJ20>=AJ19,AJ20-AJ19,0)*0.53 -> 1896.34 | AL20: 584044 | AM20: =IF(AL20>=AL19,AL20-AL19,0)*0.53 -> 111.3 | AN20: =W20+Y20+AA20+AC20+AE20+AG20+AI20+AK20+AM20 -> 3669.19 | AO20: 8251266 | AP20: =IF(AO20>=AO19,AO20-AO19,0)*0.1125 -> 41.5125 | AQ20: 765217 | AR20: =IF(AQ20>=AQ19,AQ20-AQ19,0) -> 189 | AS20: 24972 | AT20: =IF(AS20>=AS19,AS20-AS19,0) -> 127 | AU20: 829109 | AV20: =IF(AU20>=AU19,AU20-AU19,0) -> 40 | AW20: 2942743 | AX20: =IF(AW20>=AW19,AW20-AW19,0) -> 649 | AY20: 241044 | AZ20: =IF(AY20>=AY19,AY20-AY19,0) -> 11 | BA20: 21164439 | BB20: =IF(BA20>=BA19,BA20-BA19,0) -> 5539 | BC20: 656556 | BD20: =IF(BC20>=BC19,BC20-BC19,0) -> 200 | BE20: 48393 | BF20: =IF(BE20>=BE19,BE20-BE19,0) -> 45 | BG20: 26602589 | BH20: =IF(BG20>=BG19,BG20-BG19,0)-(0.45*BN20)-(0.45*BP20)-BR20 -> 5438.85 | BI20: =AP20+AR20+AT20+AV20+AX20+AZ20+BB20+BD20+BF20+BH20 -> 12280.362 | BJ20: =BI20+AN20 -> 15949.552 | BK20: 1511580 | BL20: =IF(BK20>=BK19,BK20-BK19,0) -> 243 | BM20: 4384561 | BN20: =IF(BM20>=BM19,BM20-BM19,0) -> 936 | BO20: 459394 | BP20: =IF(BO20>=BO19,BO20-BO19,0) -> 111 | BQ20: 572785 | BR20: =IF(BQ20>=BQ19,BQ20-BQ19,0) -> 126 | BS20: =J20+Q20+AN20+BI20 -> 23602.552 | BT20: 196 | BU20: =IF(BS20>0,BS20/BT20,0) -> 120.42119 | BW20: =IF(BS20>0,BS20/BV20,0) -> #DIV/0! | BX20: =((BS20-Q20)*$BZ$1)+(Q20*$BR$1) -> 27385.935 | BY20: =IF(BX20>0,BX20/BT20,0) -> 139.72416 | BZ20: =IF(BX20>0,BX20/BV20,0) -> #DIV/0!
A21: 16 | C21: =IF(+B21-B20>0,B21-B20,(B21-B20)>0)*800 -> 0 | E21: =IF(+D21-D20>0,D21-D20,(D21-D20)>0)*80 -> 0 | G21: =IF(+F21-F20>0,F21-F20,(F21-F20)>0)*10 -> 0 | I21: 26107097 | J21: =IF(I21>=I20,I21-I20,0) -> 7244 | K21: =M21+O21 -> 4419 | L21: 446303 | M21: =IF(L21>=L20,L21-L20,0) -> 2560 | N21: 441853 | O21: =IF(N21>=N20,N21-N20,0) -> 1859 | P21: 228443 | Q21: =IF(P21>=P20,P21-P20,0)*30 -> 570 | R21: 237268 | S21: =IF(R21>=R20,R21-R20,0) -> 141 | T21: 432570 | U21: =IF(T21>=T20,T21-T20,0) -> 247 | V21: 944520 | W21: =IF(V21>=V20,V21-V20,0)*0.53 -> 1725.68 | X21: 839916 | Y21: =IF(X21>=X20,X21-X20,0)*0.53 -> 0 | Z21: 871835 | AA21: =IF(Z21>=Z20,Z21-Z20,0)*0.53 -> 0 | AB21: 184962 | AC21: =IF(AB21>=AB20,AB21-AB20,0)*0.53 -> 265 | AD21: 863726 | AE21: =IF(AD21>=AD20,AD21-AD20,0)*0.53 -> 12.72 | AF21: 1011322 | AG21: =IF(AF21>=AF20,AF21-AF20,0)*0.53 -> 12.19 | AH21: 449760 | AI21: =IF(AH21>=AH20,AH21-AH20,0)*0.53 -> 181.26 | AJ21: 832125 | AK21: =IF(AJ21>=AJ20,AJ21-AJ20,0)*0.53 -> 2289.07 | AL21: 584264 | AM21: =IF(AL21>=AL20,AL21-AL20,0)*0.53 -> 116.6 | AN21: =W21+Y21+AA21+AC21+AE21+AG21+AI21+AK21+AM21 -> 4602.52 | AO21: 8251880 | AP21: =IF(AO21>=AO20,AO21-AO20,0)*0.1125 -> 69.075 | AQ21: 765406 | AR21: =IF(AQ21>=AQ20,AQ21-AQ20,0) -> 189 | AS21: 25111 | AT21: =IF(AS21>=AS20,AS21-AS20,0) -> 139 | AU21: 829151 | AV21: =IF(AU21>=AU20,AU21-AU20,0) -> 42 | AW21: 2943402 | AX21: =IF(AW21>=AW20,AW21-AW20,0) -> 659 | AY21: 241049 | AZ21: =IF(AY21>=AY20,AY21-AY20,0) -> 5 | BA21: 21168485 | BB21: =IF(BA21>=BA20,BA21-BA20,0) -> 4046 | BC21: 656769 | BD21: =IF(BC21>=BC20,BC21-BC20,0) -> 213 | BE21: 48448 | BF21: =IF(BE21>=BE20,BE21-BE20,0) -> 55 | BG21: 26608881 | BH21: =IF(BG21>=BG20,BG21-BG20,0)-(0.45*BN21)-(0.45*BP21)-BR21 -> 5609 | BI21: =AP21+AR21+AT21+AV21+AX21+AZ21+BB21+BD21+BF21+BH21 -> 11026.075 | BJ21: =BI21+AN21 -> 15628.595 | BK21: 1511852 | BL21: =IF(BK21>=BK20,BK21-BK20,0) -> 272 | BM21: 4385476 | BN21: =IF(BM21>=BM20,BM21-BM20,0) -> 915 | BO21: 459499 | BP21: =IF(BO21>=BO20,BO21-BO20,0) -> 105 | BQ21: 573009 | BR21: =IF(BQ21>=BQ20,BQ21-BQ20,0) -> 224 | BS21: =J21+Q21+AN21+BI21 -> 23442.595 | BT21: 219 | BU21: =IF(BS21>0,BS21/BT21,0) -> 107.04381 | BW21: =IF(BS21>0,BS21/BV21,0) -> #DIV/0! | BX21: =((BS21-Q21)*$BZ$1)+(Q21*$BR$1) -> 27215.484 | BY21: =IF(BX21>0,BX21/BT21,0) -> 124.27162 | BZ21: =IF(BX21>0,BX21/BV21,0) -> #DIV/0!
A22: 17 | C22: =IF(+B22-B21>0,B22-B21,(B22-B21)>0)*800 -> 0 | E22: =IF(+D22-D21>0,D22-D21,(D22-D21)>0)*80 -> 0 | G22: =IF(+F22-F21>0,F22-F21,(F22-F21)>0)*10 -> 0 | H22: 64 | I22: 26114106 | J22: =IF(I22>=I21,I22-I21,0) -> 7009 | K22: =M22+O22 -> 4559 | L22: 448950 | M22: =IF(L22>=L21,L22-L21,0) -> 2647 | N22: 443765 | O22: =IF(N22>=N21,N22-N21,0) -> 1912 | P22: 228467 | Q22: =IF(P22>=P21,P22-P21,0)*30 -> 720 | R22: 237410 | S22: =IF(R22>=R21,R22-R21,0) -> 142 | T22: 432822 | U22: =IF(T22>=T21,T22-T21,0) -> 252 | V22: 948311 | W22: =IF(V22>=V21,V22-V21,0)*0.53 -> 2009.23 | X22: 839916 | Y22: =IF(X22>=X21,X22-X21,0)*0.53 -> 0 | Z22: 871835 | AA22: =IF(Z22>=Z21,Z22-Z21,0)*0.53 -> 0 | AB22: 184962 | AC22: =IF(AB22>=AB21,AB22-AB21,0)*0.53 -> 0 | AD22: 863736 | AE22: =IF(AD22>=AD21,AD22-AD21,0)*0.53 -> 5.3 | AF22: 1011352 | AG22: =IF(AF22>=AF21,AF22-AF21,0)*0.53 -> 15.9 | AH22: 450152 | AI22: =IF(AH22>=AH21,AH22-AH21,0)*0.53 -> 207.76 | AJ22: 837081 | AK22: =IF(AJ22>=AJ21,AJ22-AJ21,0)*0.53 -> 2626.68 | AL22: 584495 | AM22: =IF(AL22>=AL21,AL22-AL21,0)*0.53 -> 122.43 | AN22: =W22+Y22+AA22+AC22+AE22+AG22+AI22+AK22+AM22 -> 4987.3 | AO22: 8252502 | AP22: =IF(AO22>=AO21,AO22-AO21,0)*0.1125 -> 69.975 | AQ22: 765603 | AR22: =IF(AQ22>=AQ21,AQ22-AQ21,0) -> 197 | AS22: 25228 | AT22: =IF(AS22>=AS21,AS22-AS21,0) -> 117 | AU22: 829197 | AV22: =IF(AU22>=AU21,AU22-AU21,0) -> 46 | AW22: 2944235 | AX22: =IF(AW22>=AW21,AW22-AW21,0) -> 833 | AY22: 241049 | AZ22: =IF(AY22>=AY21,AY22-AY21,0) -> 0 | BA22: 21173853 | BB22: =IF(BA22>=BA21,BA22-BA21,0) -> 5368 | BC22: 656969 | BD22: =IF(BC22>=BC21,BC22-BC21,0) -> 200 | BE22: 48483 | BF22: =IF(BE22>=BE21,BE22-BE21,0) -> 35 | BG22: 26614817 | BH22: =IF(BG22>=BG21,BG22-BG21,0)-(0.45*BN22)-(0.45*BP22)-BR22 -> 5519.85 | BI22: =AP22+AR22+AT22+AV22+AX22+AZ22+BB22+BD22+BF22+BH22 -> 12385.825 | BJ22: =BI22+AN22 -> 17373.125 | BK22: 1512126 | BL22: =IF(BK22>=BK21,BK22-BK21,0) -> 274 | BM22: 4386236 | BN22: =IF(BM22>=BM21,BM22-BM21,0) -> 760 | BO22: 459606 | BP22: =IF(BO22>=BO21,BO22-BO21,0) -> 107 | BQ22: 573035 | BR22: =IF(BQ22>=BQ21,BQ22-BQ21,0) -> 26 | BS22: =J22+Q22+AN22+BI22 -> 25102.125 | BT22: 240 | BU22: =IF(BS22>0,BS22/BT22,0) -> 104.59219 | BW22: =IF(BS22>0,BS22/BV22,0) -> #DIV/0! | BX22: =((BS22-Q22)*$BZ$1)+(Q22*$BR$1) -> 29191.444 | BY22: =IF(BX22>0,BX22/BT22,0) -> 121.63102 | BZ22: =IF(BX22>0,BX22/BV22,0) -> #DIV/0!
A23: 18 | C23: =IF(+B23-B22>0,B23-B22,(B23-B22)>0)*800 -> 0 | E23: =IF(+D23-D22>0,D23-D22,(D23-D22)>0)*80 -> 0 | G23: =IF(+F23-F22>0,F23-F22,(F23-F22)>0)*10 -> 0 | I23: 26120603 | J23: =IF(I23>=I22,I23-I22,0) -> 6497 | K23: =M23+O23 -> 3224 | L23: 450853 | M23: =IF(L23>=L22,L23-L22,0) -> 1903 | N23: 445086 | O23: =IF(N23>=N22,N23-N22,0) -> 1321 | P23: 228485 | Q23: =IF(P23>=P22,P23-P22,0)*30 -> 540 | R23: 237553 | S23: =IF(R23>=R22,R23-R22,0) -> 143 | T23: 433076 | U23: =IF(T23>=T22,T23-T22,0) -> 254 | V23: 951117 | W23: =IF(V23>=V22,V23-V22,0)*0.53 -> 1487.18 | X23: 839916 | Y23: =IF(X23>=X22,X23-X22,0)*0.53 -> 0 | Z23: 871835 | AA23: =IF(Z23>=Z22,Z23-Z22,0)*0.53 -> 0 | AB23: 184962 | AC23: =IF(AB23>=AB22,AB23-AB22,0)*0.53 -> 0 | AD23: 863736 | AE23: =IF(AD23>=AD22,AD23-AD22,0)*0.53 -> 0 | AF23: 1011370 | AG23: =IF(AF23>=AF22,AF23-AF22,0)*0.53 -> 9.54 | AH23: 450402 | AI23: =IF(AH23>=AH22,AH23-AH22,0)*0.53 -> 132.5 | AJ23: 840366 | AK23: =IF(AJ23>=AJ22,AJ23-AJ22,0)*0.53 -> 1741.05 | AL23: 584671 | AM23: =IF(AL23>=AL22,AL23-AL22,0)*0.53 -> 93.28 | AN23: =W23+Y23+AA23+AC23+AE23+AG23+AI23+AK23+AM23 -> 3463.55 | AO23: 8252957 | AP23: =IF(AO23>=AO22,AO23-AO22,0)*0.1125 -> 51.1875 | AQ23: 765813 | AR23: =IF(AQ23>=AQ22,AQ23-AQ22,0) -> 210 | AS23: 25354 | AT23: =IF(AS23>=AS22,AS23-AS22,0) -> 126 | AU23: 829231 | AV23: =IF(AU23>=AU22,AU23-AU22,0) -> 34 | AW23: 2945089 | AX23: =IF(AW23>=AW22,AW23-AW22,0) -> 854 | AY23: 241049 | AZ23: =IF(AY23>=AY22,AY23-AY22,0) -> 0 | BA23: 21178322 | BB23: =IF(BA23>=BA22,BA23-BA22,0) -> 4469 | BC23: 657180 | BD23: =IF(BC23>=BC22,BC23-BC22,0) -> 211 | BE23: 48528 | BF23: =IF(BE23>=BE22,BE23-BE22,0) -> 45 | BG23: 26620452 | BH23: =IF(BG23>=BG22,BG23-BG22,0)-(0.45*BN23)-(0.45*BP23)-BR23 -> 5103.85 | BI23: =AP23+AR23+AT23+AV23+AX23+AZ23+BB23+BD23+BF23+BH23 -> 11104.038 | BJ23: =BI23+AN23 -> 14567.588 | BK23: 1512400 | BL23: =IF(BK23>=BK22,BK23-BK22,0) -> 274 | BM23: 4386996 | BN23: =IF(BM23>=BM22,BM23-BM22,0) -> 760 | BO23: 459713 | BP23: =IF(BO23>=BO22,BO23-BO22,0) -> 107 | BQ23: 573176 | BR23: =IF(BQ23>=BQ22,BQ23-BQ22,0) -> 141 | BS23: =J23+Q23+AN23+BI23 -> 21604.588 | BT23: 256 | BU23: =IF(BS23>0,BS23/BT23,0) -> 84.39292 | BW23: =IF(BS23>0,BS23/BV23,0) -> #DIV/0! | BX23: =((BS23-Q23)*$BZ$1)+(Q23*$BR$1) -> 25088.276 | BY23: =IF(BX23>0,BX23/BT23,0) -> 98.001077 | BZ23: =IF(BX23>0,BX23/BV23,0) -> #DIV/0!
A24: 19 | C24: =IF(+B24-B23>0,B24-B23,(B24-B23)>0)*800 -> 0 | E24: =IF(+D24-D23>0,D24-D23,(D24-D23)>0)*80 -> 0 | G24: =IF(+F24-F23>0,F24-F23,(F24-F23)>0)*10 -> 0 | H24: 65 | I24: 26127257 | J24: =IF(I24>=I23,I24-I23,0) -> 6654 | K24: =M24+O24 -> 3907 | L24: 453098 | M24: =IF(L24>=L23,L24-L23,0) -> 2245 | N24: 446748 | O24: =IF(N24>=N23,N24-N23,0) -> 1662 | P24: 228503 | Q24: =IF(P24>=P23,P24-P23,0)*30 -> 540 | R24: 237696 | S24: =IF(R24>=R23,R24-R23,0) -> 143 | T24: 433332 | U24: =IF(T24>=T23,T24-T23,0) -> 256 | V24: 954537 | W24: =IF(V24>=V23,V24-V23,0)*0.53 -> 1812.6 | X24: 839916 | Y24: =IF(X24>=X23,X24-X23,0)*0.53 -> 0 | Z24: 871835 | AA24: =IF(Z24>=Z23,Z24-Z23,0)*0.53 -> 0 | AB24: 184962 | AC24: =IF(AB24>=AB23,AB24-AB23,0)*0.53 -> 0 | AD24: 863736 | AE24: =IF(AD24>=AD23,AD24-AD23,0)*0.53 -> 0 | AF24: 1011399 | AG24: =IF(AF24>=AF23,AF24-AF23,0)*0.53 -> 15.37 | AH24: 450745 | AI24: =IF(AH24>=AH23,AH24-AH23,0)*0.53 -> 181.79 | AJ24: 844482 | AK24: =IF(AJ24>=AJ23,AJ24-AJ23,0)*0.53 -> 2181.48 | AL24: 584885 | AM24: =IF(AL24>=AL23,AL24-AL23,0)*0.53 -> 113.42 | AN24: =W24+Y24+AA24+AC24+AE24+AG24+AI24+AK24+AM24 -> 4304.66 | AO24: 8253911 | AP24: =IF(AO24>=AO23,AO24-AO23,0)*0.1125 -> 107.325 | AQ24: 766006 | AR24: =IF(AQ24>=AQ23,AQ24-AQ23,0) -> 193 | AS24: 25474 | AT24: =IF(AS24>=AS23,AS24-AS23,0) -> 120 | AU24: 829273 | AV24: =IF(AU24>=AU23,AU24-AU23,0) -> 42 | AW24: 2946067 | AX24: =IF(AW24>=AW23,AW24-AW23,0) -> 978 | AY24: 241049 | AZ24: =IF(AY24>=AY23,AY24-AY23,0) -> 0 | BA24: 21182841 | BB24: =IF(BA24>=BA23,BA24-BA23,0) -> 4519 | BC24: 657410 | BD24: =IF(BC24>=BC23,BC24-BC23,0) -> 230 | BE24: 48583 | BF24: =IF(BE24>=BE23,BE24-BE23,0) -> 55 | BG24: 26626180 | BH24: =IF(BG24>=BG23,BG24-BG23,0)-(0.45*BN24)-(0.45*BP24)-BR24 -> 5174.45 | BI24: =AP24+AR24+AT24+AV24+AX24+AZ24+BB24+BD24+BF24+BH24 -> 11418.775 | BJ24: =BI24+AN24 -> 15723.435 | BK24: 1512678 | BL24: =IF(BK24>=BK23,BK24-BK23,0) -> 278 | BM24: 4387779 | BN24: =IF(BM24>=BM23,BM24-BM23,0) -> 783 | BO24: 459809 | BP24: =IF(BO24>=BO23,BO24-BO23,0) -> 96 | BQ24: 573334 | BR24: =IF(BQ24>=BQ23,BQ24-BQ23,0) -> 158 | BS24: =J24+Q24+AN24+BI24 -> 22917.435 | BT24: 254 | BU24: =IF(BS24>0,BS24/BT24,0) -> 90.226122 | BW24: =IF(BS24>0,BS24/BV24,0) -> #DIV/0! | BX24: =((BS24-Q24)*$BZ$1)+(Q24*$BR$1) -> 26598.05 | BY24: =IF(BX24>0,BX24/BT24,0) -> 104.71673 | BZ24: =IF(BX24>0,BX24/BV24,0) -> #DIV/0!
A25: 20 | C25: =IF(+B25-B24>0,B25-B24,(B25-B24)>0)*800 -> 0 | E25: =IF(+D25-D24>0,D25-D24,(D25-D24)>0)*80 -> 0 | G25: =IF(+F25-F24>0,F25-F24,(F25-F24)>0)*10 -> 0 | I25: 26134046 | J25: =IF(I25>=I24,I25-I24,0) -> 6789 | K25: =M25+O25 -> 4521 | L25: 455647 | M25: =IF(L25>=L24,L25-L24,0) -> 2549 | N25: 448720 | O25: =IF(N25>=N24,N25-N24,0) -> 1972 | P25: 228522 | Q25: =IF(P25>=P24,P25-P24,0)*30 -> 570 | R25: 237842 | S25: =IF(R25>=R24,R25-R24,0) -> 146 | T25: 433588 | U25: =IF(T25>=T24,T25-T24,0) -> 256 | V25: 958830 | W25: =IF(V25>=V24,V25-V24,0)*0.53 -> 2275.29 | X25: 839916 | Y25: =IF(X25>=X24,X25-X24,0)*0.53 -> 0 | Z25: 871835 | AA25: =IF(Z25>=Z24,Z25-Z24,0)*0.53 -> 0 | AB25: 184962 | AC25: =IF(AB25>=AB24,AB25-AB24,0)*0.53 -> 0 | AD25: 863736 | AE25: =IF(AD25>=AD24,AD25-AD24,0)*0.53 -> 0 | AF25: 1011423 | AG25: =IF(AF25>=AF24,AF25-AF24,0)*0.53 -> 12.72 | AH25: 451170 | AI25: =IF(AH25>=AH24,AH25-AH24,0)*0.53 -> 225.25 | AJ25: 849414 | AK25: =IF(AJ25>=AJ24,AJ25-AJ24,0)*0.53 -> 2613.96 | AL25: 585136 | AM25: =IF(AL25>=AL24,AL25-AL24,0)*0.53 -> 133.03 | AN25: =W25+Y25+AA25+AC25+AE25+AG25+AI25+AK25+AM25 -> 5260.25 | AO25: 8254337 | AP25: =IF(AO25>=AO24,AO25-AO24,0)*0.1125 -> 47.925 | AQ25: 766224 | AR25: =IF(AQ25>=AQ24,AQ25-AQ24,0) -> 218 | AS25: 25548 | AT25: =IF(AS25>=AS24,AS25-AS24,0) -> 74 | AU25: 829321 | AV25: =IF(AU25>=AU24,AU25-AU24,0) -> 48 | AW25: 2947162 | AX25: =IF(AW25>=AW24,AW25-AW24,0) -> 1095 | AY25: 241049 | AZ25: =IF(AY25>=AY24,AY25-AY24,0) -> 0 | BA25: 21188246 | BB25: =IF(BA25>=BA24,BA25-BA24,0) -> 5405 | BC25: 657625 | BD25: =IF(BC25>=BC24,BC25-BC24,0) -> 215 | BE25: 48632 | BF25: =IF(BE25>=BE24,BE25-BE24,0) -> 49 | BG25: 26631997 | BH25: =IF(BG25>=BG24,BG25-BG24,0)-(0.45*BN25)-(0.45*BP25)-BR25 -> 5283.35 | BI25: =AP25+AR25+AT25+AV25+AX25+AZ25+BB25+BD25+BF25+BH25 -> 12435.275 | BJ25: =BI25+AN25 -> 17695.525 | BK25: 1512955 | BL25: =IF(BK25>=BK24,BK25-BK24,0) -> 277 | BM25: 4388567 | BN25: =IF(BM25>=BM24,BM25-BM24,0) -> 788 | BO25: 459898 | BP25: =IF(BO25>=BO24,BO25-BO24,0) -> 89 | BQ25: 573473 | BR25: =IF(BQ25>=BQ24,BQ25-BQ24,0) -> 139 | BS25: =J25+Q25+AN25+BI25 -> 25054.525 | BT25: 250 | BU25: =IF(BS25>0,BS25/BT25,0) -> 100.2181 | BW25: =IF(BS25>0,BS25/BV25,0) -> #DIV/0! | BX25: =((BS25-Q25)*$BZ$1)+(Q25*$BR$1) -> 29069.204 | BY25: =IF(BX25>0,BX25/BT25,0) -> 116.27681 | BZ25: =IF(BX25>0,BX25/BV25,0) -> #DIV/0!
A26: 21 | C26: =IF(+B26-B25>0,B26-B25,(B26-B25)>0)*800 -> 0 | E26: =IF(+D26-D25>0,D26-D25,(D26-D25)>0)*80 -> 0 | G26: =IF(+F26-F25>0,F26-F25,(F26-F25)>0)*10 -> 0 | H26: 66 | I26: 26140923 | J26: =IF(I26>=I25,I26-I25,0) -> 6877 | K26: =M26+O26 -> 3574 | L26: 457585 | M26: =IF(L26>=L25,L26-L25,0) -> 1938 | N26: 450356 | O26: =IF(N26>=N25,N26-N25,0) -> 1636 | P26: 228542 | Q26: =IF(P26>=P25,P26-P25,0)*30 -> 600 | R26: 237983 | S26: =IF(R26>=R25,R26-R25,0) -> 141 | T26: 433838 | U26: =IF(T26>=T25,T26-T25,0) -> 250 | V26: 962705 | W26: =IF(V26>=V25,V26-V25,0)*0.53 -> 2053.75 | X26: 839916 | Y26: =IF(X26>=X25,X26-X25,0)*0.53 -> 0 | Z26: 871835 | AA26: =IF(Z26>=Z25,Z26-Z25,0)*0.53 -> 0 | AB26: 184962 | AC26: =IF(AB26>=AB25,AB26-AB25,0)*0.53 -> 0 | AD26: 863736 | AE26: =IF(AD26>=AD25,AD26-AD25,0)*0.53 -> 0 | AF26: 1011450 | AG26: =IF(AF26>=AF25,AF26-AF25,0)*0.53 -> 14.31 | AH26: 451505 | AI26: =IF(AH26>=AH25,AH26-AH25,0)*0.53 -> 177.55 | AJ26: 853387 | AK26: =IF(AJ26>=AJ25,AJ26-AJ25,0)*0.53 -> 2105.69 | AL26: 585331 | AM26: =IF(AL26>=AL25,AL26-AL25,0)*0.53 -> 103.35 | AN26: =W26+Y26+AA26+AC26+AE26+AG26+AI26+AK26+AM26 -> 4454.65 | AO26: 8255048 | AP26: =IF(AO26>=AO25,AO26-AO25,0)*0.1125 -> 79.9875 | AQ26: 766466 | AR26: =IF(AQ26>=AQ25,AQ26-AQ25,0) -> 242 | AS26: 25705 | AT26: =IF(AS26>=AS25,AS26-AS25,0) -> 157 | AU26: 829356 | AV26: =IF(AU26>=AU25,AU26-AU25,0) -> 35 | AW26: 2948013 | AX26: =IF(AW26>=AW25,AW26-AW25,0) -> 851 | AY26: 241044 | AZ26: =IF(AY26>=AY25,AY26-AY25,0) -> 0 | BA26: 21192314 | BB26: =IF(BA26>=BA25,BA26-BA25,0) -> 4068 | BC26: 657862 | BD26: =IF(BC26>=BC25,BC26-BC25,0) -> 237 | BE26: 48677 | BF26: =IF(BE26>=BE25,BE26-BE25,0) -> 45 | BG26: 26638409 | BH26: =IF(BG26>=BG25,BG26-BG25,0)-(0.45*BN26)-(0.45*BP26)-BR26 -> 5801.1 | BI26: =AP26+AR26+AT26+AV26+AX26+AZ26+BB26+BD26+BF26+BH26 -> 11516.088 | BJ26: =BI26+AN26 -> 15970.738 | BK26: 1513228 | BL26: =IF(BK26>=BK25,BK26-BK25,0) -> 273 | BM26: 4389374 | BN26: =IF(BM26>=BM25,BM26-BM25,0) -> 807 | BO26: 460033 | BP26: =IF(BO26>=BO25,BO26-BO25,0) -> 135 | BQ26: 573660 | BR26: =IF(BQ26>=BQ25,BQ26-BQ25,0) -> 187 | BS26: =J26+Q26+AN26+BI26 -> 23447.738 | BT26: 249 | BU26: =IF(BS26>0,BS26/BT26,0) -> 94.16762 | BW26: =IF(BS26>0,BS26/BV26,0) -> #DIV/0! | BX26: =((BS26-Q26)*$BZ$1)+(Q26*$BR$1) -> 27234.898 | BY26: =IF(BX26>0,BX26/BT26,0) -> 109.3771 | BZ26: =IF(BX26>0,BX26/BV26,0) -> #DIV/0!
A27: 22 | C27: =IF(+B27-B26>0,B27-B26,(B27-B26)>0)*800 -> 0 | E27: =IF(+D27-D26>0,D27-D26,(D27-D26)>0)*80 -> 0 | G27: =IF(+F27-F26>0,F27-F26,(F27-F26)>0)*10 -> 0 | I27: 26147249 | J27: =IF(I27>=I26,I27-I26,0) -> 6326 | K27: =M27+O27 -> 4048 | L27: 459853 | M27: =IF(L27>=L26,L27-L26,0) -> 2268 | N27: 452136 | O27: =IF(N27>=N26,N27-N26,0) -> 1780 | P27: 228560 | Q27: =IF(P27>=P26,P27-P26,0)*30 -> 540 | R27: 238123 | S27: =IF(R27>=R26,R27-R26,0) -> 140 | T27: 434085 | U27: =IF(T27>=T26,T27-T26,0) -> 247 | V27: 966324 | W27: =IF(V27>=V26,V27-V26,0)*0.53 -> 1918.07 | X27: 840445 | Y27: =IF(X27>=X26,X27-X26,0)*0.53 -> 280.37 | Z27: 871835 | AA27: =IF(Z27>=Z26,Z27-Z26,0)*0.53 -> 0 | AB27: 184962 | AC27: =IF(AB27>=AB26,AB27-AB26,0)*0.53 -> 0 | AD27: 863736 | AE27: =IF(AD27>=AD26,AD27-AD26,0)*0.53 -> 0 | AF27: 1011472 | AG27: =IF(AF27>=AF26,AF27-AF26,0)*0.53 -> 11.66 | AH27: 451900 | AI27: =IF(AH27>=AH26,AH27-AH26,0)*0.53 -> 209.35 | AJ27: 857817 | AK27: =IF(AJ27>=AJ26,AJ27-AJ26,0)*0.53 -> 2347.9 | AL27: 585540 | AM27: =IF(AL27>=AL26,AL27-AL26,0)*0.53 -> 110.77 | AN27: =W27+Y27+AA27+AC27+AE27+AG27+AI27+AK27+AM27 -> 4878.12 | AO27: 8255771 | AP27: =IF(AO27>=AO26,AO27-AO26,0)*0.1125 -> 81.3375 | AQ27: 766670 | AR27: =IF(AQ27>=AQ26,AQ27-AQ26,0) -> 204 | AS27: 25825 | AT27: =IF(AS27>=AS26,AS27-AS26,0) -> 120 | AU27: 829397 | AV27: =IF(AU27>=AU26,AU27-AU26,0) -> 41 | AW27: 2948985 | AX27: =IF(AW27>=AW26,AW27-AW26,0) -> 972 | AY27: 241049 | AZ27: =IF(AY27>=AY26,AY27-AY26,0) -> 5 | BA27: 21197129 | BB27: =IF(BA27>=BA26,BA27-BA26,0) -> 4815 | BC27: 658119 | BD27: =IF(BC27>=BC26,BC27-BC26,0) -> 257 | BE27: 48726 | BF27: =IF(BE27>=BE26,BE27-BE26,0) -> 49 | BG27: 26644342 | BH27: =IF(BG27>=BG26,BG27-BG26,0)-(0.45*BN27)-(0.45*BP27)-BR27 -> 5481.4 | BI27: =AP27+AR27+AT27+AV27+AX27+AZ27+BB27+BD27+BF27+BH27 -> 12025.737 | BJ27: =BI27+AN27 -> 16903.857 | BK27: 1513495 | BL27: =IF(BK27>=BK26,BK27-BK26,0) -> 267 | BM27: 4390154 | BN27: =IF(BM27>=BM26,BM27-BM26,0) -> 780 | BO27: 460121 | BP27: =IF(BO27>=BO26,BO27-BO26,0) -> 88 | BQ27: 573721 | BR27: =IF(BQ27>=BQ26,BQ27-BQ26,0) -> 61 | BS27: =J27+Q27+AN27+BI27 -> 23769.857 | BT27: 240 | BU27: =IF(BS27>0,BS27/BT27,0) -> 99.041073 | BW27: =IF(BS27>0,BS27/BV27,0) -> #DIV/0! | BX27: =((BS27-Q27)*$BZ$1)+(Q27*$BR$1) -> 27578.336 | BY27: =IF(BX27>0,BX27/BT27,0) -> 114.90973 | BZ27: =IF(BX27>0,BX27/BV27,0) -> #DIV/0!
A28: 23 | C28: =IF(+B28-B27>0,B28-B27,(B28-B27)>0)*800 -> 0 | E28: =IF(+D28-D27>0,D28-D27,(D28-D27)>0)*80 -> 0 | G28: =IF(+F28-F27>0,F28-F27,(F28-F27)>0)*10 -> 0 | H28: 67 | I28: 26155300 | J28: =IF(I28>=I27,I28-I27,0) -> 8051 | K28: =M28+O28 -> 4676 | L28: 462348 | M28: =IF(L28>=L27,L28-L27,0) -> 2495 | N28: 454317 | O28: =IF(N28>=N27,N28-N27,0) -> 2181 | P28: 228582 | Q28: =IF(P28>=P27,P28-P27,0)*30 -> 660 | R28: 238272 | S28: =IF(R28>=R27,R28-R27,0) -> 149 | T28: 434358 | U28: =IF(T28>=T27,T28-T27,0) -> 273 | V28: 971333 | W28: =IF(V28>=V27,V28-V27,0)*0.53 -> 2654.77 | X28: 840445 | Y28: =IF(X28>=X27,X28-X27,0)*0.53 -> 0 | Z28: 871835 | AA28: =IF(Z28>=Z27,Z28-Z27,0)*0.53 -> 0 | AB28: 184962 | AC28: =IF(AB28>=AB27,AB28-AB27,0)*0.53 -> 0 | AD28: 863736 | AE28: =IF(AD28>=AD27,AD28-AD27,0)*0.53 -> 0 | AF28: 1011497 | AG28: =IF(AF28>=AF27,AF28-AF27,0)*0.53 -> 13.25 | AH28: 452390 | AI28: =IF(AH28>=AH27,AH28-AH27,0)*0.53 -> 259.7 | AJ28: 862668 | AK28: =IF(AJ28>=AJ27,AJ28-AJ27,0)*0.53 -> 2571.03 | AL28: 585800 | AM28: =IF(AL28>=AL27,AL28-AL27,0)*0.53 -> 137.8 | AN28: =W28+Y28+AA28+AC28+AE28+AG28+AI28+AK28+AM28 -> 5636.55 | AO28: 8256455 | AP28: =IF(AO28>=AO27,AO28-AO27,0)*0.1125 -> 76.95 | AQ28: 766885 | AR28: =IF(AQ28>=AQ27,AQ28-AQ27,0) -> 215 | AS28: 25966 | AT28: =IF(AS28>=AS27,AS28-AS27,0) -> 141 | AU28: 829444 | AV28: =IF(AU28>=AU27,AU28-AU27,0) -> 47 | AW28: 2950134 | AX28: =IF(AW28>=AW27,AW28-AW27,0) -> 1149 | AY28: 241049 | AZ28: =IF(AY28>=AY27,AY28-AY27,0) -> 0 | BA28: 21202693 | BB28: =IF(BA28>=BA27,BA28-BA27,0) -> 5564 | BC28: 658392 | BD28: =IF(BC28>=BC27,BC28-BC27,0) -> 273 | BE28: 48769 | BF28: =IF(BE28>=BE27,BE28-BE27,0) -> 43 | BG28: 26650763 | BH28: =IF(BG28>=BG27,BG28-BG27,0)-(0.45*BN28)-(0.45*BP28)-BR28 -> 5792.75 | BI28: =AP28+AR28+AT28+AV28+AX28+AZ28+BB28+BD28+BF28+BH28 -> 13301.7 | BJ28: =BI28+AN28 -> 18938.25 | BK28: 1513772 | BL28: =IF(BK28>=BK27,BK28-BK27,0) -> 277 | BM28: 4391124 | BN28: =IF(BM28>=BM27,BM28-BM27,0) -> 970 | BO28: 460236 | BP28: =IF(BO28>=BO27,BO28-BO27,0) -> 115 | BQ28: 573861 | BR28: =IF(BQ28>=BQ27,BQ28-BQ27,0) -> 140 | BS28: =J28+Q28+AN28+BI28 -> 27649.25 | BT28: 254 | BU28: =IF(BS28>0,BS28/BT28,0) -> 108.85531 | BW28: =IF(BS28>0,BS28/BV28,0) -> #DIV/0! | BX28: =((BS28-Q28)*$BZ$1)+(Q28*$BR$1) -> 32093.637 | BY28: =IF(BX28>0,BX28/BT28,0) -> 126.3529 | BZ28: =IF(BX28>0,BX28/BV28,0) -> #DIV/0!
A29: 24 | C29: =IF(+B29-B28>0,B29-B28,(B29-B28)>0)*800 -> 0 | E29: =IF(+D29-D28>0,D29-D28,(D29-D28)>0)*80 -> 0 | G29: =IF(+F29-F28>0,F29-F28,(F29-F28)>0)*10 -> 0 | I29: 26161821 | J29: =IF(I29>=I28,I29-I28,0) -> 6521 | K29: =M29+O29 -> 3663 | L29: 464232 | M29: =IF(L29>=L28,L29-L28,0) -> 1884 | N29: 456096 | O29: =IF(N29>=N28,N29-N28,0) -> 1779 | P29: 228601 | Q29: =IF(P29>=P28,P29-P28,0)*30 -> 570 | R29: 238415 | S29: =IF(R29>=R28,R29-R28,0) -> 143 | T29: 434628 | U29: =IF(T29>=T28,T29-T28,0) -> 270 | V29: 975665 | W29: =IF(V29>=V28,V29-V28,0)*0.53 -> 2295.96 | X29: 840445 | Y29: =IF(X29>=X28,X29-X28,0)*0.53 -> 0 | Z29: 871835 | AA29: =IF(Z29>=Z28,Z29-Z28,0)*0.53 -> 0 | AB29: 184962 | AC29: =IF(AB29>=AB28,AB29-AB28,0)*0.53 -> 0 | AD29: 863736 | AE29: =IF(AD29>=AD28,AD29-AD28,0)*0.53 -> 0 | AF29: 1011515 | AG29: =IF(AF29>=AF28,AF29-AF28,0)*0.53 -> 9.54 | AH29: 452788 | AI29: =IF(AH29>=AH28,AH29-AH28,0)*0.53 -> 210.94 | AJ29: 866531 | AK29: =IF(AJ29>=AJ28,AJ29-AJ28,0)*0.53 -> 2047.39 | AL29: 586013 | AM29: =IF(AL29>=AL28,AL29-AL28,0)*0.53 -> 112.89 | AN29: =W29+Y29+AA29+AC29+AE29+AG29+AI29+AK29+AM29 -> 4676.72 | AO29: 8257165 | AP29: =IF(AO29>=AO28,AO29-AO28,0)*0.1125 -> 79.875 | AQ29: 767089 | AR29: =IF(AQ29>=AQ28,AQ29-AQ28,0) -> 204 | AS29: 26112 | AT29: =IF(AS29>=AS28,AS29-AS28,0) -> 146 | AU29: 829480 | AV29: =IF(AU29>=AU28,AU29-AU28,0) -> 36 | AW29: 2951015 | AX29: =IF(AW29>=AW28,AW29-AW28,0) -> 881 | AY29: 241049 | AZ29: =IF(AY29>=AY28,AY29-AY28,0) -> 0 | BA29: 21206772 | BB29: =IF(BA29>=BA28,BA29-BA28,0) -> 4079 | BC29: 658673 | BD29: =IF(BC29>=BC28,BC29-BC28,0) -> 281 | BE29: 48814 | BF29: =IF(BE29>=BE28,BE29-BE28,0) -> 45 | BG29: 26657204 | BH29: =IF(BG29>=BG28,BG29-BG28,0)-(0.45*BN29)-(0.45*BP29)-BR29 -> 5820.75 | BI29: =AP29+AR29+AT29+AV29+AX29+AZ29+BB29+BD29+BF29+BH29 -> 11572.625 | BJ29: =BI29+AN29 -> 16249.345 | BK29: 1514056 | BL29: =IF(BK29>=BK28,BK29-BK28,0) -> 284 | BM29: 4392112 | BN29: =IF(BM29>=BM28,BM29-BM28,0) -> 988 | BO29: 460353 | BP29: =IF(BO29>=BO28,BO29-BO28,0) -> 117 | BQ29: 573984 | BR29: =IF(BQ29>=BQ28,BQ29-BQ28,0) -> 123 | BS29: =J29+Q29+AN29+BI29 -> 23340.345 | BT29: 251 | BU29: =IF(BS29>0,BS29/BT29,0) -> 92.989422 | BW29: =IF(BS29>0,BS29/BV29,0) -> #DIV/0! | BX29: =((BS29-Q29)*$BZ$1)+(Q29*$BR$1) -> 27097.897 | BY29: =IF(BX29>0,BX29/BT29,0) -> 107.95975 | BZ29: =IF(BX29>0,BX29/BV29,0) -> #DIV/0!
A30: 25 | C30: =IF(+B30-B29>0,B30-B29,(B30-B29)>0)*800 -> 0 | E30: =IF(+D30-D29>0,D30-D29,(D30-D29)>0)*80 -> 0 | G30: =IF(+F30-F29>0,F30-F29,(F30-F29)>0)*10 -> 0 | H30: 68 | I30: 26168369 | J30: =IF(I30>=I29,I30-I29,0) -> 6548 | K30: =M30+O30 -> 4133 | L30: 466416 | M30: =IF(L30>=L29,L30-L29,0) -> 2184 | N30: 458045 | O30: =IF(N30>=N29,N30-N29,0) -> 1949 | P30: 228621 | Q30: =IF(P30>=P29,P30-P29,0)*30 -> 600 | R30: 238562 | S30: =IF(R30>=R29,R30-R29,0) -> 147 | T30: 434901 | U30: =IF(T30>=T29,T30-T29,0) -> 273 | V30: 980776 | W30: =IF(V30>=V29,V30-V29,0)*0.53 -> 2708.83 | X30: 840445 | Y30: =IF(X30>=X29,X30-X29,0)*0.53 -> 0 | Z30: 871835 | AA30: =IF(Z30>=Z29,Z30-Z29,0)*0.53 -> 0 | AB30: 184962 | AC30: =IF(AB30>=AB29,AB30-AB29,0)*0.53 -> 0 | AD30: 863736 | AE30: =IF(AD30>=AD29,AD30-AD29,0)*0.53 -> 0 | AF30: 1011539 | AG30: =IF(AF30>=AF29,AF30-AF29,0)*0.53 -> 12.72 | AH30: 453281 | AI30: =IF(AH30>=AH29,AH30-AH29,0)*0.53 -> 261.29 | AJ30: 871378 | AK30: =IF(AJ30>=AJ29,AJ30-AJ29,0)*0.53 -> 2568.91 | AL30: 586257 | AM30: =IF(AL30>=AL29,AL30-AL29,0)*0.53 -> 129.32 | AN30: =W30+Y30+AA30+AC30+AE30+AG30+AI30+AK30+AM30 -> 5681.07 | AO30: 8257886 | AP30: =IF(AO30>=AO29,AO30-AO29,0)*0.1125 -> 81.1125 | AQ30: 767300 | AR30: =IF(AQ30>=AQ29,AQ30-AQ29,0) -> 211 | AS30: 26249 | AT30: =IF(AS30>=AS29,AS30-AS29,0) -> 137 | AU30: 829523 | AV30: =IF(AU30>=AU29,AU30-AU29,0) -> 43 | AW30: 2952054 | AX30: =IF(AW30>=AW29,AW30-AW29,0) -> 1039 | AY30: 241049 | AZ30: =IF(AY30>=AY29,AY30-AY29,0) -> 0 | BA30: 21211753 | BB30: =IF(BA30>=BA29,BA30-BA29,0) -> 4981 | BC30: 658955 | BD30: =IF(BC30>=BC29,BC30-BC29,0) -> 282 | BE30: 48865 | BF30: =IF(BE30>=BE29,BE30-BE29,0) -> 51 | BG30: 26663327 | BH30: =IF(BG30>=BG29,BG30-BG29,0)-(0.45*BN30)-(0.45*BP30)-BR30 -> 5276.7 | BI30: =AP30+AR30+AT30+AV30+AX30+AZ30+BB30+BD30+BF30+BH30 -> 12101.812 | BJ30: =BI30+AN30 -> 17782.882 | BK30: 1514338 | BL30: =IF(BK30>=BK29,BK30-BK29,0) -> 282 | BM30: 4393090 | BN30: =IF(BM30>=BM29,BM30-BM29,0) -> 978 | BO30: 460469 | BP30: =IF(BO30>=BO29,BO30-BO29,0) -> 116 | BQ30: 574338 | BR30: =IF(BQ30>=BQ29,BQ30-BQ29,0) -> 354 | BS30: =J30+Q30+AN30+BI30 -> 24930.882 | BT30: 252 | BU30: =IF(BS30>0,BS30/BT30,0) -> 98.932073 | BW30: =IF(BS30>0,BS30/BV30,0) -> #DIV/0! | BX30: =((BS30-Q30)*$BZ$1)+(Q30*$BR$1) -> 28940.515 | BY30: =IF(BX30>0,BX30/BT30,0) -> 114.84331 | BZ30: =IF(BX30>0,BX30/BV30,0) -> #DIV/0!
A31: 26 | C31: =IF(+B31-B30>0,B31-B30,(B31-B30)>0)*800 -> 0 | E31: =IF(+D31-D30>0,D31-D30,(D31-D30)>0)*80 -> 0 | G31: =IF(+F31-F30>0,F31-F30,(F31-F30)>0)*10 -> 0 | I31: 26178972 | J31: =IF(I31>=I30,I31-I30,0) -> 10603 | K31: =M31+O31 -> 3837 | L31: 468466 | M31: =IF(L31>=L30,L31-L30,0) -> 2050 | N31: 459832 | O31: =IF(N31>=N30,N31-N30,0) -> 1787 | P31: 228640 | Q31: =IF(P31>=P30,P31-P30,0)*30 -> 570 | R31: 238708 | S31: =IF(R31>=R30,R31-R30,0) -> 146 | T31: 435178 | U31: =IF(T31>=T30,T31-T30,0) -> 277 | V31: 984793 | W31: =IF(V31>=V30,V31-V30,0)*0.53 -> 2129.01 | X31: 840445 | Y31: =IF(X31>=X30,X31-X30,0)*0.53 -> 0 | Z31: 871835 | AA31: =IF(Z31>=Z30,Z31-Z30,0)*0.53 -> 0 | AB31: 184962 | AC31: =IF(AB31>=AB30,AB31-AB30,0)*0.53 -> 0 | AD31: 863736 | AE31: =IF(AD31>=AD30,AD31-AD30,0)*0.53 -> 0 | AF31: 1011562 | AG31: =IF(AF31>=AF30,AF31-AF30,0)*0.53 -> 12.19 | AH31: 453689 | AI31: =IF(AH31>=AH30,AH31-AH30,0)*0.53 -> 216.24 | AJ31: 875277 | AK31: =IF(AJ31>=AJ30,AJ31-AJ30,0)*0.53 -> 2066.47 | AL31: 586480 | AM31: =IF(AL31>=AL30,AL31-AL30,0)*0.53 -> 118.19 | AN31: =W31+Y31+AA31+AC31+AE31+AG31+AI31+AK31+AM31 -> 4542.1 | AO31: 8258640 | AP31: =IF(AO31>=AO30,AO31-AO30,0)*0.1125 -> 84.825 | AQ31: 767511 | AR31: =IF(AQ31>=AQ30,AQ31-AQ30,0) -> 211 | AS31: 26377 | AT31: =IF(AS31>=AS30,AS31-AS30,0) -> 128 | AU31: 829564 | AV31: =IF(AU31>=AU30,AU31-AU30,0) -> 41 | AW31: 2953049 | AX31: =IF(AW31>=AW30,AW31-AW30,0) -> 995 | AY31: 241049 | AZ31: =IF(AY31>=AY30,AY31-AY30,0) -> 0 | BA31: 21216167 | BB31: =IF(BA31>=BA30,BA31-BA30,0) -> 4414 | BC31: 659235 | BD31: =IF(BC31>=BC30,BC31-BC30,0) -> 280 | BE31: 48911 | BF31: =IF(BE31>=BE30,BE31-BE30,0) -> 46 | BG31: 26669261 | BH31: =IF(BG31>=BG30,BG31-BG30,0)-(0.45*BN31)-(0.45*BP31)-BR31 -> 5415.3 | BI31: =AP31+AR31+AT31+AV31+AX31+AZ31+BB31+BD31+BF31+BH31 -> 11615.125 | BJ31: =BI31+AN31 -> 16157.225 | BK31: 1514614 | BL31: =IF(BK31>=BK30,BK31-BK30,0) -> 276 | BM31: 4394063 | BN31: =IF(BM31>=BM30,BM31-BM30,0) -> 973 | BO31: 460582 | BP31: =IF(BO31>=BO30,BO31-BO30,0) -> 113 | BQ31: 574368 | BR31: =IF(BQ31>=BQ30,BQ31-BQ30,0) -> 30 | BS31: =J31+Q31+AN31+BI31 -> 27330.225 | BT31: 252 | BU31: =IF(BS31>0,BS31/BT31,0) -> 108.45327 | BW31: =IF(BS31>0,BS31/BV31,0) -> #DIV/0! | BX31: =((BS31-Q31)*$BZ$1)+(Q31*$BR$1) -> 31686.259 | BY31: =IF(BX31>0,BX31/BT31,0) -> 125.73912 | BZ31: =IF(BX31>0,BX31/BV31,0) -> #DIV/0!
A32: 27 | C32: =IF(+B32-B31>0,B32-B31,(B32-B31)>0)*800 -> 0 | E32: =IF(+D32-D31>0,D32-D31,(D32-D31)>0)*80 -> 0 | G32: =IF(+F32-F31>0,F32-F31,(F32-F31)>0)*10 -> 0 | H32: 69 | I32: 26180099 | J32: =IF(I32>=I31,I32-I31,0) -> 1127 | K32: =M32+O32 -> 3727 | L32: 470275 | M32: =IF(L32>=L31,L32-L31,0) -> 1809 | N32: 461750 | O32: =IF(N32>=N31,N32-N31,0) -> 1918 | P32: 228658 | Q32: =IF(P32>=P31,P32-P31,0)*30 -> 540 | R32: 238840 | S32: =IF(R32>=R31,R32-R31,0) -> 132 | T32: 435417 | U32: =IF(T32>=T31,T32-T31,0) -> 239 | V32: 989194 | W32: =IF(V32>=V31,V32-V31,0)*0.53 -> 2332.53 | X32: 840445 | Y32: =IF(X32>=X31,X32-X31,0)*0.53 -> 0 | Z32: 871835 | AA32: =IF(Z32>=Z31,Z32-Z31,0)*0.53 -> 0 | AB32: 184962 | AC32: =IF(AB32>=AB31,AB32-AB31,0)*0.53 -> 0 | AD32: 863736 | AE32: =IF(AD32>=AD31,AD32-AD31,0)*0.53 -> 0 | AF32: 1011584 | AG32: =IF(AF32>=AF31,AF32-AF31,0)*0.53 -> 11.66 | AH32: 454167 | AI32: =IF(AH32>=AH31,AH32-AH31,0)*0.53 -> 253.34 | AJ32: 879117 | AK32: =IF(AJ32>=AJ31,AJ32-AJ31,0)*0.53 -> 2035.2 | AL32: 586687 | AM32: =IF(AL32>=AL31,AL32-AL31,0)*0.53 -> 109.71 | AN32: =W32+Y32+AA32+AC32+AE32+AG32+AI32+AK32+AM32 -> 4742.44 | AO32: 8259547 | AP32: =IF(AO32>=AO31,AO32-AO31,0)*0.1125 -> 102.0375 | AQ32: 767661 | AR32: =IF(AQ32>=AQ31,AQ32-AQ31,0) -> 150 | AS32: 26469 | AT32: =IF(AS32>=AS31,AS32-AS31,0) -> 92 | AU32: 829603 | AV32: =IF(AU32>=AU31,AU32-AU31,0) -> 39 | AW32: 2953965 | AX32: =IF(AW32>=AW31,AW32-AW31,0) -> 916 | AY32: 241049 | AZ32: =IF(AY32>=AY31,AY32-AY31,0) -> 0 | BA32: 21220490 | BB32: =IF(BA32>=BA31,BA32-BA31,0) -> 4323 | BC32: 659501 | BD32: =IF(BC32>=BC31,BC32-BC31,0) -> 266 | BE32: 48960.333 | BF32: =IF(BE32>=BE31,BE32-BE31,0) -> 49.333333 | BG32: 26675153 | BH32: =IF(BG32>=BG31,BG32-BG31,0)-(0.45*BN32)-(0.45*BP32)-BR32 -> 5392.45 | BI32: =AP32+AR32+AT32+AV32+AX32+AZ32+BB32+BD32+BF32+BH32 -> 11329.821 | BJ32: =BI32+AN32 -> 16072.261 | BK32: 1514870 | BL32: =IF(BK32>=BK31,BK32-BK31,0) -> 256 | BM32: 4394961 | BN32: =IF(BM32>=BM31,BM32-BM31,0) -> 898 | BO32: 460683 | BP32: =IF(BO32>=BO31,BO32-BO31,0) -> 101 | BQ32: 574418 | BR32: =IF(BQ32>=BQ31,BQ32-BQ31,0) -> 50 | BS32: =J32+Q32+AN32+BI32 -> 17739.261 | BT32: 236 | BU32: =IF(BS32>0,BS32/BT32,0) -> 75.166359 | BW32: =IF(BS32>0,BS32/BV32,0) -> #DIV/0! | BX32: =((BS32-Q32)*$BZ$1)+(Q32*$BR$1) -> 20643.15 | BY32: =IF(BX32>0,BX32/BT32,0) -> 87.470974 | BZ32: =IF(BX32>0,BX32/BV32,0) -> #DIV/0!
A33: 28 | C33: =IF(+B33-B32>0,B33-B32,(B33-B32)>0)*800 -> 0 | E33: =IF(+D33-D32>0,D33-D32,(D33-D32)>0)*80 -> 0 | G33: =IF(+F33-F32>0,F33-F32,(F33-F32)>0)*10 -> 0 | I33: 26187543 | J33: =IF(I33>=I32,I33-I32,0) -> 7444.3333 | K33: =M33+O33 -> 3800.3333 | L33: 472244.67 | M33: =IF(L33>=L32,L33-L32,0) -> 1969.6667 | N33: 463580.67 | O33: =IF(N33>=N32,N33-N32,0) -> 1830.6667 | P33: 228676.67 | Q33: =IF(P33>=P32,P33-P32,0)*30 -> 560 | R33: 238981.33 | S33: =IF(R33>=R32,R33-R32,0) -> 141.33333 | T33: 435681.33 | U33: =IF(T33>=T32,T33-T32,0) -> 264.33333 | V33: 993339 | W33: =IF(V33>=V32,V33-V32,0)*0.53 -> 2196.85 | X33: 840445 | Y33: =IF(X33>=X32,X33-X32,0)*0.53 -> 0 | Z33: 871835 | AA33: =IF(Z33>=Z32,Z33-Z32,0)*0.53 -> 0 | AB33: 184962 | AC33: =IF(AB33>=AB32,AB33-AB32,0)*0.53 -> 0 | AD33: 863736 | AE33: =IF(AD33>=AD32,AD33-AD32,0)*0.53 -> 0 | AF33: 1011606.7 | AG33: =IF(AF33>=AF32,AF33-AF32,0)*0.53 -> 12.013333 | AH33: 454598.33 | AI33: =IF(AH33>=AH32,AH33-AH32,0)*0.53 -> 228.60667 | AJ33: 882996.33 | AK33: =IF(AJ33>=AJ32,AJ33-AJ32,0)*0.53 -> 2056.0467 | AL33: 586904.67 | AM33: =IF(AL33>=AL32,AL33-AL32,0)*0.53 -> 115.36333 | AN33: =W33+Y33+AA33+AC33+AE33+AG33+AI33+AK33+AM33 -> 4608.88 | AO33: 8260352 | AP33: =IF(AO33>=AO32,AO33-AO32,0)*0.1125 -> 90.5625 | AQ33: 767851.67 | AR33: =IF(AQ33>=AQ32,AQ33-AQ32,0) -> 190.66667 | AS33: 26585 | AT33: =IF(AS33>=AS32,AS33-AS32,0) -> 116 | AU33: 829643.33 | AV33: =IF(AU33>=AU32,AU33-AU32,0) -> 40.333333 | AW33: 2954933.7 | AX33: =IF(AW33>=AW32,AW33-AW32,0) -> 968.66667 | AY33: 241049 | AZ33: =IF(AY33>=AY32,AY33-AY32,0) -> 0 | BA33: 21224874 | BB33: =IF(BA33>=BA32,BA33-BA32,0) -> 4383.6667 | BC33: 659776.33 | BD33: =IF(BC33>=BC32,BC33-BC32,0) -> 275.33333 | BE33: 49008.833 | BF33: =IF(BE33>=BE32,BE33-BE32,0) -> 48.5 | BG33: 26681073 | BH33: =IF(BG33>=BG32,BG33-BG32,0)-(0.45*BN33)-(0.45*BP33)-BR33 -> 5407.6833 | BI33: =AP33+AR33+AT33+AV33+AX33+AZ33+BB33+BD33+BF33+BH33 -> 11521.413 | BJ33: =BI33+AN33 -> 16130.293 | BK33: 1515139.3 | BL33: =IF(BK33>=BK32,BK33-BK32,0) -> 269.33333 | BM33: 4395909 | BN33: =IF(BM33>=BM32,BM33-BM32,0) -> 948 | BO33: 460792 | BP33: =IF(BO33>=BO32,BO33-BO32,0) -> 109 | BQ33: 574454.67 | BR33: =IF(BQ33>=BQ32,BQ33-BQ32,0) -> 36.666667 | BS33: =J33+Q33+AN33+BI33 -> 24134.626 | BT33: 230.66667 | BU33: =IF(BS33>0,BS33/BT33,0) -> 104.62988 | BW33: =IF(BS33>0,BS33/BV33,0) -> #DIV/0! | BX33: =((BS33-Q33)*$BZ$1)+(Q33*$BR$1) -> 28006.82 | BY33: =IF(BX33>0,BX33/BT33,0) -> 121.41685 | BZ33: =IF(BX33>0,BX33/BV33,0) -> #DIV/0!
A34: 29 | C34: =IF(+B34-B33>0,B34-B33,(B34-B33)>0)*800 -> 0 | E34: =IF(+D34-D33>0,D34-D33,(D34-D33)>0)*80 -> 0 | G34: =IF(+F34-F33>0,F34-F33,(F34-F33)>0)*10 -> 0 | I34: 26187543 | J34: =IF(I34>=I33,I34-I33,0) -> 0 | K34: =M34+O34 -> 0 | L34: 472244.67 | M34: =IF(L34>=L33,L34-L33,0) -> 0 | N34: 463580.67 | O34: =IF(N34>=N33,N34-N33,0) -> 0 | P34: 228676.67 | Q34: =IF(P34>=P33,P34-P33,0)*30 -> 0 | R34: 238981.33 | S34: =IF(R34>=R33,R34-R33,0) -> 0 | T34: 435681.33 | U34: =IF(T34>=T33,T34-T33,0) -> 0 | V34: 993339 | W34: =IF(V34>=V33,V34-V33,0)*0.53 -> 0 | X34: 840445 | Y34: =IF(X34>=X33,X34-X33,0)*0.53 -> 0 | Z34: 871835 | AA34: =IF(Z34>=Z33,Z34-Z33,0)*0.53 -> 0 | AB34: 184962 | AC34: =IF(AB34>=AB33,AB34-AB33,0)*0.53 -> 0 | AD34: 863736 | AE34: =IF(AD34>=AD33,AD34-AD33,0)*0.53 -> 0 | AF34: 1011606.7 | AG34: =IF(AF34>=AF33,AF34-AF33,0)*0.53 -> 0 | AH34: 454598.33 | AI34: =IF(AH34>=AH33,AH34-AH33,0)*0.53 -> 0 | AJ34: 882996.33 | AK34: =IF(AJ34>=AJ33,AJ34-AJ33,0)*0.53 -> 0 | AL34: 586904.67 | AM34: =IF(AL34>=AL33,AL34-AL33,0)*0.53 -> 0 | AN34: =W34+Y34+AA34+AC34+AE34+AG34+AI34+AK34+AM34 -> 0 | AO34: 8260352 | AP34: =IF(AO34>=AO33,AO34-AO33,0)*0.1125 -> 0 | AQ34: 767851.67 | AR34: =IF(AQ34>=AQ33,AQ34-AQ33,0) -> 0 | AS34: 26585 | AT34: =IF(AS34>=AS33,AS34-AS33,0) -> 0 | AU34: 829643.33 | AV34: =IF(AU34>=AU33,AU34-AU33,0) -> 0 | AW34: 2954933.7 | AX34: =IF(AW34>=AW33,AW34-AW33,0) -> 0 | AY34: 241049 | AZ34: =IF(AY34>=AY33,AY34-AY33,0) -> 0 | BA34: 21224874 | BB34: =IF(BA34>=BA33,BA34-BA33,0) -> 0 | BC34: 659776.33 | BD34: =IF(BC34>=BC33,BC34-BC33,0) -> 0 | BE34: 49008.833 | BF34: =IF(BE34>=BE33,BE34-BE33,0) -> 0 | BG34: 26681073 | BH34: =IF(BG34>=BG33,BG34-BG33,0)-(0.45*BN34)-(0.45*BP34)-BR34 -> 0 | BI34: =AP34+AR34+AT34+AV34+AX34+AZ34+BB34+BD34+BF34+BH34 -> 0 | BJ34: =BI34+AN34 -> 0 | BK34: 1515139.3 | BL34: =IF(BK34>=BK33,BK34-BK33,0) -> 0 | BM34: 4395909 | BN34: =IF(BM34>=BM33,BM34-BM33,0) -> 0 | BO34: 460792 | BP34: =IF(BO34>=BO33,BO34-BO33,0) -> 0 | BQ34: 574454.67 | BR34: =IF(BQ34>=BQ33,BQ34-BQ33,0) -> 0 | BS34: =J34+Q34+AN34+BI34 -> 0 | BT34: 0 | BU34: =IF(BS34>0,BS34/BT34,0) -> 0 | BW34: =IF(BS34>0,BS34/BV34,0) -> 0 | BX34: =((BS34-Q34)*$BZ$1)+(Q34*$BR$1) -> 0 | BY34: =IF(BX34>0,BX34/BT34,0) -> 0 | BZ34: =IF(BX34>0,BX34/BV34,0) -> 0
A35: 30 | C35: =IF(+B35-B34>0,B35-B34,(B35-B34)>0)*800 -> 0 | E35: =IF(+D35-D34>0,D35-D34,(D35-D34)>0)*80 -> 0 | G35: =IF(+F35-F34>0,F35-F34,(F35-F34)>0)*10 -> 0 | I35: 26187543 | J35: =IF(I35>=I34,I35-I34,0) -> 0 | K35: =M35+O35 -> 0 | L35: 472244.67 | M35: =IF(L35>=L34,L35-L34,0) -> 0 | N35: 463580.67 | O35: =IF(N35>=N34,N35-N34,0) -> 0 | P35: 228676.67 | Q35: =IF(P35>=P34,P35-P34,0)*30 -> 0 | R35: 238981.33 | S35: =IF(R35>=R34,R35-R34,0) -> 0 | T35: 435681.33 | U35: =IF(T35>=T34,T35-T34,0) -> 0 | V35: 993339 | W35: =IF(V35>=V34,V35-V34,0)*0.53 -> 0 | X35: 840445 | Y35: =IF(X35>=X34,X35-X34,0)*0.53 -> 0 | Z35: 871835 | AA35: =IF(Z35>=Z34,Z35-Z34,0)*0.53 -> 0 | AB35: 184962 | AC35: =IF(AB35>=AB34,AB35-AB34,0)*0.53 -> 0 | AD35: 863736 | AE35: =IF(AD35>=AD34,AD35-AD34,0)*0.53 -> 0 | AF35: 1011606.7 | AG35: =IF(AF35>=AF34,AF35-AF34,0)*0.53 -> 0 | AH35: 454598.33 | AI35: =IF(AH35>=AH34,AH35-AH34,0)*0.53 -> 0 | AJ35: 882996.33 | AK35: =IF(AJ35>=AJ34,AJ35-AJ34,0)*0.53 -> 0 | AL35: 586904.67 | AM35: =IF(AL35>=AL34,AL35-AL34,0)*0.53 -> 0 | AN35: =W35+Y35+AA35+AC35+AE35+AG35+AI35+AK35+AM35 -> 0 | AO35: 8260352 | AP35: =IF(AO35>=AO34,AO35-AO34,0)*0.1125 -> 0 | AQ35: 767851.67 | AR35: =IF(AQ35>=AQ34,AQ35-AQ34,0) -> 0 | AS35: 26585 | AT35: =IF(AS35>=AS34,AS35-AS34,0) -> 0 | AU35: 829643.33 | AV35: =IF(AU35>=AU34,AU35-AU34,0) -> 0 | AW35: 2954933.7 | AX35: =IF(AW35>=AW34,AW35-AW34,0) -> 0 | AY35: 241049 | AZ35: =IF(AY35>=AY34,AY35-AY34,0) -> 0 | BA35: 21224874 | BB35: =IF(BA35>=BA34,BA35-BA34,0) -> 0 | BC35: 659776.33 | BD35: =IF(BC35>=BC34,BC35-BC34,0) -> 0 | BE35: 49008.833 | BF35: =IF(BE35>=BE34,BE35-BE34,0) -> 0 | BG35: 26681073 | BH35: =IF(BG35>=BG34,BG35-BG34,0)-(0.45*BN35)-(0.45*BP35)-BR35 -> 0 | BI35: =AP35+AR35+AT35+AV35+AX35+AZ35+BB35+BD35+BF35+BH35 -> 0 | BJ35: =BI35+AN35 -> 0 | BK35: 1515139.3 | BL35: =IF(BK35>=BK34,BK35-BK34,0) -> 0 | BM35: 4395909 | BN35: =IF(BM35>=BM34,BM35-BM34,0) -> 0 | BO35: 460792 | BP35: =IF(BO35>=BO34,BO35-BO34,0) -> 0 | BQ35: 574454.67 | BR35: =IF(BQ35>=BQ34,BQ35-BQ34,0) -> 0 | BS35: =J35+Q35+AN35+BI35 -> 0 | BT35: 0 | BU35: =IF(BS35>0,BS35/BT35,0) -> 0 | BW35: =IF(BS35>0,BS35/BV35,0) -> 0 | BX35: =((BS35-Q35)*$BZ$1)+(Q35*$BR$1) -> 0 | BY35: =IF(BX35>0,BX35/BT35,0) -> 0 | BZ35: =IF(BX35>0,BX35/BV35,0) -> 0
A36: 31 | I36: 26187543 | J36: =IF(I36>=I35,I36-I35,0) -> 0 | K36: =M36+O36 -> 0 | L36: 472244.67 | M36: =IF(L36>=L35,L36-L35,0) -> 0 | N36: 463580.67 | O36: =IF(N36>=N35,N36-N35,0) -> 0 | P36: 228676.67 | Q36: =IF(P36>=P35,P36-P35,0)*30 -> 0 | R36: 238981.33 | S36: =IF(R36>=R35,R36-R35,0) -> 0 | T36: 435681.33 | U36: =IF(T36>=T35,T36-T35,0) -> 0 | V36: 993339 | W36: =IF(V36>=V35,V36-V35,0)*0.53 -> 0 | X36: 840445 | Y36: =IF(X36>=X35,X36-X35,0)*0.53 -> 0 | Z36: 871835 | AA36: =IF(Z36>=Z35,Z36-Z35,0)*0.53 -> 0 | AB36: 184962 | AC36: =IF(AB36>=AB35,AB36-AB35,0)*0.53 -> 0 | AD36: 863736 | AE36: =IF(AD36>=AD35,AD36-AD35,0)*0.53 -> 0 | AF36: 1011606.7 | AG36: =IF(AF36>=AF35,AF36-AF35,0)*0.53 -> 0 | AH36: 454598.33 | AI36: =IF(AH36>=AH35,AH36-AH35,0)*0.53 -> 0 | AJ36: 882996.33 | AK36: =IF(AJ36>=AJ35,AJ36-AJ35,0)*0.53 -> 0 | AL36: 586904.67 | AM36: =IF(AL36>=AL35,AL36-AL35,0)*0.53 -> 0 | AN36: =W36+Y36+AA36+AC36+AE36+AG36+AI36+AK36+AM36 -> 0 | AO36: 8260352 | AP36: =IF(AO36>=AO35,AO36-AO35,0)*0.1125 -> 0 | AQ36: 767851.67 | AR36: =IF(AQ36>=AQ35,AQ36-AQ35,0) -> 0 | AS36: 26585 | AT36: =IF(AS36>=AS35,AS36-AS35,0) -> 0 | AU36: 829643.33 | AV36: =IF(AU36>=AU35,AU36-AU35,0) -> 0 | AW36: 2954933.7 | AX36: =IF(AW36>=AW35,AW36-AW35,0) -> 0 | AY36: 241049 | AZ36: =IF(AY36>=AY35,AY36-AY35,0) -> 0 | BA36: 21224874 | BB36: =IF(BA36>=BA35,BA36-BA35,0) -> 0 | BC36: 659776.33 | BD36: =IF(BC36>=BC35,BC36-BC35,0) -> 0 | BE36: 49008.833 | BF36: =IF(BE36>=BE35,BE36-BE35,0) -> 0 | BG36: 26681073 | BH36: =IF(BG36>=BG35,BG36-BG35,0)-(0.45*BN36)-(0.45*BP36)-BR36 -> 0 | BI36: =AP36+AR36+AT36+AV36+AX36+AZ36+BB36+BD36+BF36+BH36 -> 0 | BJ36: =BI36+AN36 -> 0 | BK36: 1515139.3 | BL36: =IF(BK36>=BK35,BK36-BK35,0) -> 0 | BM36: 4395909 | BN36: =IF(BM36>=BM35,BM36-BM35,0) -> 0 | BO36: 460792 | BP36: =IF(BO36>=BO35,BO36-BO35,0) -> 0 | BQ36: 574454.67 | BR36: =IF(BQ36>=BQ35,BQ36-BQ35,0) -> 0 | BS36: =J36+Q36+AN36+BI36 -> 0 | BT36: 0 | BU36: =IF(BS36>0,BS36/BT36,0) -> 0 | BW36: =IF(BS36>0,BS36/BV36,0) -> 0 | BX36: =((BS36-Q36)*$BZ$1)+(Q36*$BR$1) -> 0 | BY36: =IF(BX36>0,BX36/BT36,0) -> 0 | BZ36: =IF(BX36>0,BX36/BV36,0) -> 0
A37: MTD | C37: =SUM(C9:C35) -> 0 | E37: =SUM(E9:E35) -> 0 | F37: =SUM(F9:F35) -> 0 | G37: =SUM(G9:G35) -> 0 | J37: =SUM(J6:J36) -> 196305.67 | K37: =SUM(K6:K36) -> 121751 | M37: =SUM(M6:M36) -> 67519 | O37: =SUM(O6:O36) -> 54232 | Q37: =SUM(Q6:Q36) -> 14450 | S37: =SUM(S6:S36) -> 4010 | U37: =SUM(U6:U36) -> 7133.6667 | W37: =SUM(W6:W36) -> 51998.3 | Y37: =SUM(Y5:Y36) -> 280.37 | AA37: =SUM(AA6:AA36) -> 40.28 | AC37: =SUM(AC6:AC36) -> 265 | AE37: =SUM(AE6:AE36) -> 231.61 | AG37: =SUM(AG6:AG36) -> 353.33333 | AI37: =SUM(AI6:AI36) -> 4863.6333 | AK37: =SUM(AK6:AK36) -> 57244.77 | AM37: =SUM(AM6:AM36) -> 3239.5367 | AN37: =SUM(AN6:AN36) -> 118516.83 | AP37: =SUM(AP6:AP36) -> 2652.8625 | AR37: =SUM(AR6:AR36) -> 5562 | AT37: =SUM(AT6:AT36) -> 3470.6667 | AV37: =SUM(AV6:AV36) -> 1150 | AX37: =SUM(AX6:AX36) -> 22464 | AZ37: =SUM(AZ6:AZ36) -> 6306 | BB37: =SUM(BB6:BB36) -> 130802 | BD37: =SUM(BD6:BD36) -> 6297.3333 | BF37: =SUM(BF6:BF36) -> 1308.8333 | BH37: =SUM(BH6:BH36) -> 151383.53 | BI37: =SUM(BI6:BI36) -> 331397.23 | BJ37: =SUM(BJ6:BJ36) -> 449914.06 | BL37: =SUM(BL6:BL36) -> 6768.6667 | BN37: =SUM(BN6:BN36) -> 26055.667 | BP37: =SUM(BP6:BP36) -> 3095 | BR37: =SUM(BR6:BR36) -> 3876.6667 | BS37: =SUM(BS6:BS36) -> 660669.73 | BT37: =SUM(BT6:BT36) -> 6025.6667 | BU37: =IF(BS37>0,BS37/BT37,0) -> 109.64259 | BV37: =SUM(BV6:BV35) -> 0 | BW37: =IF(BS37>0,BS37/BV37,0) -> #DIV/0! | BX37: =SUM(BX6:BX35) -> 766272.69 | BY37: =IF(BX37>0,BX37/BT37,0) -> 127.16812 | BZ37: =IF(BX37>0,BX37/BV37,0) -> #DIV/0!
A38: AVER. Act | C38: =C37/C40 -> #DIV/0! | E38: =E37/C40 -> #DIV/0! | F38: =F37/C40 -> #DIV/0! | G38: =G37/C40 -> #DIV/0! | J38: =J37/J39 -> 6543.5222 | K38: =K37/J39 -> 4058.3667 | M38: =M37/J39 -> 2250.6333 | O38: =O37/J39 -> 1807.7333 | Q38: =Q37/J39 -> 481.66667 | S38: =S37/J39 -> 133.66667 | U38: =U37/J39 -> 237.78889 | W38: =W37/J39 -> 1733.2767 | Y38: =Y37/J39 -> 9.3456667 | AA38: =AA37/J39 -> 1.3426667 | AC38: =AC37/J39 -> 8.8333333 | AE38: =AE37/J39 -> 7.7203333 | AG38: =AG37/J39 -> 11.777778 | AI38: =AI37/J39 -> 162.12111 | AK38: =AK37/J39 -> 1908.159 | AM38: =AM37/J39 -> 107.98456 | AN38: =AN37/J39 -> 3950.5611 | AP38: =AP37/J39 -> 88.42875 | AR38: =AR37/J39 -> 185.4 | AT38: =AT37/J39 -> 115.68889 | AV38: =AV37/J39 -> 38.333333 | AX38: =AX37/J39 -> 748.8 | AZ38: =AZ37/J39 -> 210.2 | BB38: =BB37/J39 -> 4360.0667 | BD38: =BD37/J39 -> 209.91111 | BF38: =BF37/J39 -> 43.627778 | BH38: =BH37/J39 -> 5046.1178 | BL38: =BL37/J39 -> 225.62222 | BN38: =BN37/J39 -> 868.52222 | BP38: =BP37/J39 -> 103.16667 | BR38: =BR37/J39 -> 129.22222 | BS38: =BS37/$J$41 -> #DIV/0! | BT38: =BT37/$J$41 -> #DIV/0! | BU38: =BS38/BT38 -> #DIV/0! | BV38: =BV37/$J$41 -> #DIV/0! | BW38: =BS38/BV38 -> #DIV/0! | BX38: =BX37/$J$41 -> #DIV/0! | BY38: =BX38/BT38 -> #DIV/0! | BZ38: =BX38/BV38 -> #DIV/0!
A39: No of Days MTD | J39: =COUNTIF(I6:I35,">0") -> 30
A40: No of Days month | J40: =COUNTIF(A6:A35,">0") -> 30

Sheet Water
A1: =Elect!A1 -> 44958 | T1: Main Water UP | V1: 4 | W1: Water Truck UP
A3: Day | E3: Water Incoming | I3: New casino | N3: Rooms Consumption | P3: Public Areas consumption | R3: Swimming pool | T3: No. of rooms | U3: Cons. Per occ. room | V3: No. of guest | W3: Cons. Per guest | X3: Total cost | Y3: L.E\ | Z3: L.E\
B4: Main water meter 1 | D4: Main water meter 2 | F4: Main water meter 3 | H4: Total Inc. | I4: Hot water | K4: Cold water | N4: Express Riser | O4: Consp. | P4: Read. | Q4: Cons. | R4: Read. | S4: Cons. | Y4: Room | Z4: Guest
B5: Counter | C5: Produc 58% | D5: Counter | E5: Produc 58% | F5: Counter | G5: Produc 58% | I5: Counter | K5: Counter
B6: 91217 | C6: =IF(B6>=B5,B6-B5,0)*10*0.58 -> 0 | D6: 14703 | E6: =IF(D6>=D5,D6-D5,0)*10*0.58 -> 0 | F6: 74439 | G6: =IF(F6>=F5,F6-F5,0)*0.58 -> 0 | I6: 331 | K6: 5727
A7: 1 | B7: 91227 | C7: =IF(B7>=B6,B7-B6,0)*10*0.58 -> 58 | D7: 14713 | E7: =IF(D7>=D6,D7-D6,0)*10*0.58 -> 58 | F7: 74600 | G7: =IF(F7>=F6,F7-F6,0)*0.58 -> 93.38 | H7: =C7+E7+G7 -> 209.38 | O7: =IF(N7>=N6,N7-N6,0) -> 0 | Q7: =(H7-O7)*0.58 -> 121.4404 | S7: =IF(R7-R6>0,R7-R6,0) -> 0 | T7: =Elect!BT6 -> 97 | U7: =H7/T7 -> 2.1585567 | V7: =Elect!BV6 -> 0 | W7: =H7/V7 -> #DIV/0! | X7: =H7*V1 -> 837.52 | Y7: =IF(X7>0,X7/T7,0) -> 8.6342268 | Z7: 0
A8: 2 | B8: 91240 | C8: =IF(B8>=B7,B8-B7,0)*10*0.58 -> 75.4 | D8: 14728 | E8: =IF(D8>=D7,D8-D7,0)*10*0.58 -> 87 | F8: 74762 | G8: =IF(F8>=F7,F8-F7,0)*0.58 -> 93.96 | H8: =C8+E8+G8 -> 256.36 | O8: =IF(N8>=N7,N8-N7,0) -> 0 | Q8: =(H8-O8)*0.58 -> 148.6888 | S8: =IF(R8-R7>0,R8-R7,0) -> 0 | T8: =Elect!BT7 -> 128 | U8: =H8/T8 -> 2.0028125 | V8: =Elect!BV7 -> 0 | W8: =H8/V8 -> #DIV/0! | X8: =H8*V1 -> 1025.44 | Y8: =IF(X8>0,X8/T8,0) -> 8.01125 | Z8: =IF(X8>0,X8/V8,0) -> #DIV/0!
A9: 3 | B9: 91257 | C9: =IF(B9>=B8,B9-B8,0)*10*0.58 -> 98.6 | D9: 14747 | E9: =IF(D9>=D8,D9-D8,0)*10*0.58 -> 110.2 | F9: 74983 | G9: =IF(F9>=F8,F9-F8,0)*0.58 -> 128.18 | H9: =C9+E9+G9 -> 336.98 | O9: =IF(N9>=N8,N9-N8,0) -> 0 | Q9: =(H9-O9)*0.58 -> 195.4484 | S9: =IF(R9-R8>0,R9-R8,0) -> 0 | T9: =Elect!BT8 -> 130 | U9: =H9/T9 -> 2.5921538 | V9: =Elect!BV8 -> 0 | W9: =H9/V9 -> #DIV/0! | X9: =H9*V1 -> 1347.92 | Y9: =IF(X9>0,X9/T9,0) -> 10.368615 | Z9: =IF(X9>0,X9/V9,0) -> #DIV/0!
A10: 4 | B10: 91276 | C10: =IF(B10>=B9,B10-B9,0)*10*0.58 -> 110.2 | D10: 14766 | E10: =IF(D10>=D9,D10-D9,0)*10*0.58 -> 110.2 | F10: 75200 | G10: =IF(F10>=F9,F10-F9,0)*0.58 -> 125.86 | H10: =C10+E10+G10 -> 346.26 | O10: =IF(N10>=N9,N10-N9,0) -> 0 | Q10: =(H10-O10)*0.58 -> 200.8308 | S10: =IF(R10-R9>0,R10-R9,0) -> 0 | T10: =Elect!BT9 -> 236 | U10: =H10/T10 -> 1.4672034 | V10: =Elect!BV9 -> 0 | W10: =H10/V10 -> #DIV/0! | X10: =H10*V1 -> 1385.04 | Y10: =IF(X10>0,X10/T10,0) -> 5.8688136 | Z10: =IF(X10>0,X10/V10,0) -> #DIV/0!
A11: 5 | B11: 91293.667 | C11: =IF(B11>=B10,B11-B10,0)*10*0.58 -> 102.46667 | D11: 14785 | E11: =IF(D11>=D10,D11-D10,0)*10*0.58 -> 110.2 | F11: 75419.667 | G11: =IF(F11>=F10,F11-F10,0)*0.58 -> 127.40667 | H11: =C11+E11+G11 -> 340.07333 | O11: =IF(N11>=N10,N11-N10,0) -> 0 | Q11: =(H11-O11)*0.58 -> 197.24253 | S11: =IF(R11-R10>0,R11-R10,0) -> 0 | T11: =Elect!BT10 -> 237 | U11: =H11/T11 -> 1.4349086 | V11: =Elect!BV10 -> 0 | W11: =H11/V11 -> #DIV/0! | X11: =H11*V1 -> 1360.2933 | Y11: =IF(X11>0,X11/T11,0) -> 5.7396343 | Z11: =IF(X11>0,X11/V11,0) -> #DIV/0!
A12: 6 | B12: 91308 | C12: =IF(B12>=B11,B12-B11,0)*10*0.58 -> 83.133333 | D12: 14805 | E12: =IF(D12>=D11,D12-D11,0)*10*0.58 -> 116 | F12: 75565 | G12: =IF(F12>=F11,F12-F11,0)*0.58 -> 84.293333 | H12: =C12+E12+G12 -> 283.42667 | O12: =IF(N12>=N11,N12-N11,0) -> 0 | Q12: =(H12-O12)*0.58 -> 164.38747 | S12: =IF(R12-R11>0,R12-R11,0) -> 0 | T12: =Elect!BT11 -> 196 | U12: =H12/T12 -> 1.4460544 | V12: =Elect!BV11 -> 0 | W12: =H12/V12 -> #DIV/0! | X12: =H12*V1 -> 1133.7067 | Y12: =IF(X12>0,X12/T12,0) -> 5.7842177 | Z12: =IF(X12>0,X12/V12,0) -> #DIV/0!
A13: 7 | B13: 91323 | C13: =IF(B13>=B12,B13-B12,0)*10*0.58 -> 87 | D13: 14822 | E13: =IF(D13>=D12,D13-D12,0)*10*0.58 -> 98.6 | F13: 75757 | G13: =IF(F13>=F12,F13-F12,0)*0.58 -> 111.36 | H13: =C13+E13+G13 -> 296.96 | O13: =IF(N13>=N12,N13-N12,0) -> 0 | Q13: =(H13-O13)*0.58 -> 172.2368 | S13: =IF(R13-R12>0,R13-R12,0) -> 0 | T13: =Elect!BT12 -> 163 | U13: =H13/T13 -> 1.8218405 | V13: =Elect!BV12 -> 0 | W13: =H13/V13 -> #DIV/0! | X13: =H13*V1 -> 1187.84 | Y13: =IF(X13>0,X13/T13,0) -> 7.287362 | Z13: =IF(X13>0,X13/V13,0) -> #DIV/0!
A14: 8 | B14: 91341 | C14: =IF(B14>=B13,B14-B13,0)*10*0.58 -> 104.4 | D14: 14843 | E14: =IF(D14>=D13,D14-D13,0)*10*0.58 -> 121.8 | F14: 75949 | G14: =IF(F14>=F13,F14-F13,0)*0.58 -> 111.36 | H14: =C14+E14+G14 -> 337.56 | O14: =IF(N14>=N13,N14-N13,0) -> 0 | Q14: =(H14-O14)*0.58 -> 195.7848 | S14: =IF(R14-R13>0,R14-R13,0) -> 0 | T14: =Elect!BT13 -> 149 | U14: =H14/T14 -> 2.2655034 | V14: =Elect!BV13 -> 0 | W14: =H14/V14 -> #DIV/0! | X14: =H14*V1 -> 1350.24 | Y14: =IF(X14>0,X14/T14,0) -> 9.0620134 | Z14: =IF(X14>0,X14/V14,0) -> #DIV/0!
A15: 9 | B15: 91356 | C15: =IF(B15>=B14,B15-B14,0)*10*0.58 -> 87 | D15: 14860 | E15: =IF(D15>=D14,D15-D14,0)*10*0.58 -> 98.6 | F15: 76136 | G15: =IF(F15>=F14,F15-F14,0)*0.58 -> 108.46 | H15: =C15+E15+G15 -> 294.06 | O15: =IF(N15>=N14,N15-N14,0) -> 0 | Q15: =(H15-O15)*0.58 -> 170.5548 | S15: =IF(R15-R14>0,R15-R14,0) -> 0 | T15: =Elect!BT14 -> 162 | U15: =H15/T15 -> 1.8151852 | V15: =Elect!BV14 -> 0 | W15: =H15/V15 -> #DIV/0! | X15: =H15*V1 -> 1176.24 | Y15: =IF(X15>0,X15/T15,0) -> 7.2607407 | Z15: =IF(X15>0,X15/V15,0) -> #DIV/0!
A16: 10 | B16: 91373 | C16: =IF(B16>=B15,B16-B15,0)*10*0.58 -> 98.6 | D16: 14880 | E16: =IF(D16>=D15,D16-D15,0)*10*0.58 -> 116 | F16: 76329 | G16: =IF(F16>=F15,F16-F15,0)*0.58 -> 111.94 | H16: =C16+E16+G16 -> 326.54 | O16: =IF(N16>=N15,N16-N15,0) -> 0 | Q16: =(H16-O16)*0.58 -> 189.3932 | S16: =IF(R16-R15>0,R16-R15,0) -> 0 | T16: =Elect!BT15 -> 176 | U16: =H16/T16 -> 1.8553409 | V16: =Elect!BV15 -> 0 | W16: =H16/V16 -> #DIV/0! | X16: =H16*V1 -> 1306.16 | Y16: =IF(X16>0,X16/T16,0) -> 7.4213636 | Z16: =IF(X16>0,X16/V16,0) -> #DIV/0!
A17: 11 | B17: 91392 | C17: =IF(B17>=B16,B17-B16,0)*10*0.58 -> 110.2 | D17: 14901 | E17: =IF(D17>=D16,D17-D16,0)*10*0.58 -> 121.8 | F17: 76525 | G17: =IF(F17>=F16,F17-F16,0)*0.58 -> 113.68 | H17: =C17+E17+G17 -> 345.68 | O17: =IF(N17>=N16,N17-N16,0) -> 0 | Q17: =(H17-O17)*0.58 -> 200.4944 | S17: =IF(R17-R16>0,R17-R16,0) -> 0 | T17: =Elect!BT16 -> 234 | U17: =H17/T17 -> 1.477265 | V17: =Elect!BV16 -> 0 | W17: =H17/V17 -> #DIV/0! | X17: =H17*V1 -> 1382.72 | Y17: =IF(X17>0,X17/T17,0) -> 5.9090598 | Z17: =IF(X17>0,X17/V17,0) -> #DIV/0!
A18: 12 | B18: 91410 | C18: =IF(B18>=B17,B18-B17,0)*10*0.58 -> 104.4 | D18: 14922 | E18: =IF(D18>=D17,D18-D17,0)*10*0.58 -> 121.8 | F18: 76707 | G18: =IF(F18>=F17,F18-F17,0)*0.58 -> 105.56 | H18: =C18+E18+G18 -> 331.76 | O18: =IF(N18>=N17,N18-N17,0) -> 0 | Q18: =(H18-O18)*0.58 -> 192.4208 | S18: =IF(R18-R17>0,R18-R17,0) -> 0 | T18: =Elect!BT17 -> 240 | U18: =H18/T18 -> 1.3823333 | V18: =Elect!BV17 -> 0 | W18: =H18/V18 -> #DIV/0! | X18: =H18*V1 -> 1327.04 | Y18: =IF(X18>0,X18/T18,0) -> 5.5293333 | Z18: =IF(X18>0,X18/V18,0) -> #DIV/0!
A19: 13 | B19: 91428 | C19: =IF(B19>=B18,B19-B18,0)*10*0.58 -> 104.4 | D19: 14943 | E19: =IF(D19>=D18,D19-D18,0)*10*0.58 -> 121.8 | F19: 76892 | G19: =IF(F19>=F18,F19-F18,0)*0.58 -> 107.3 | H19: =C19+E19+G19 -> 333.5 | O19: =IF(N19>=N18,N19-N18,0) -> 0 | Q19: =(H19-O19)*0.58 -> 193.43 | S19: =IF(R19-R18>0,R19-R18,0) -> 0 | T19: =Elect!BT18 -> 246 | U19: =H19/T19 -> 1.3556911 | V19: =Elect!BV18 -> 0 | W19: =H19/V19 -> #DIV/0! | X19: =H19*V1 -> 1334 | Y19: =IF(X19>0,X19/T19,0) -> 5.4227642 | Z19: =IF(X19>0,X19/V19,0) -> #DIV/0!
A20: 14 | B20: 91448 | C20: =IF(B20>=B19,B20-B19,0)*10*0.58 -> 116 | D20: 14966 | E20: =IF(D20>=D19,D20-D19,0)*10*0.58 -> 133.4 | F20: 77078 | G20: =IF(F20>=F19,F20-F19,0)*0.58 -> 107.88 | H20: =C20+E20+G20 -> 357.28 | O20: =IF(N20>=N19,N20-N19,0) -> 0 | Q20: =(H20-O20)*0.58 -> 207.2224 | S20: =IF(R20-R19>0,R20-R19,0) -> 0 | T20: =Elect!BT19 -> 252 | U20: =H20/T20 -> 1.4177778 | V20: =Elect!BV19 -> 0 | W20: =H20/V20 -> #DIV/0! | X20: =H20*V1 -> 1429.12 | Y20: =IF(X20>0,X20/T20,0) -> 5.6711111 | Z20: =IF(X20>0,X20/V20,0) -> #DIV/0!
A21: 15 | B21: 91465 | C21: =IF(B21>=B20,B21-B20,0)*10*0.58 -> 98.6 | D21: 14985 | E21: =IF(D21>=D20,D21-D20,0)*10*0.58 -> 110.2 | F21: 77267 | G21: =IF(F21>=F20,F21-F20,0)*0.58 -> 109.62 | H21: =C21+E21+G21 -> 318.42 | O21: =IF(N21>=N20,N21-N20,0) -> 0 | Q21: =(H21-O21)*0.58 -> 184.6836 | S21: =IF(R21-R20>0,R21-R20,0) -> 0 | T21: =Elect!BT20 -> 196 | U21: =H21/T21 -> 1.6245918 | V21: =Elect!BV20 -> 0 | W21: =H21/V21 -> #DIV/0! | X21: =H21*V1 -> 1273.68 | Y21: =IF(X21>0,X21/T21,0) -> 6.4983673 | Z21: =IF(X21>0,X21/V21,0) -> #DIV/0!
A22: 16 | B22: 91483 | C22: =IF(B22>=B21,B22-B21,0)*10*0.58 -> 104.4 | D22: 15006 | E22: =IF(D22>=D21,D22-D21,0)*10*0.58 -> 121.8 | F22: 77448 | G22: =IF(F22>=F21,F22-F21,0)*0.58 -> 104.98 | H22: =C22+E22+G22 -> 331.18 | O22: =IF(N22>=N21,N22-N21,0) -> 0 | Q22: =(H22-O22)*0.58 -> 192.0844 | S22: =IF(R22-R21>0,R22-R21,0) -> 0 | T22: =Elect!BT21 -> 219 | U22: =H22/T22 -> 1.5122374 | V22: =Elect!BV21 -> 0 | W22: =H22/V22 -> #DIV/0! | X22: =H22*V1 -> 1324.72 | Y22: =IF(X22>0,X22/T22,0) -> 6.0489498 | Z22: =IF(X22>0,X22/V22,0) -> #DIV/0!
A23: 17 | B23: 91500.333 | C23: =IF(B23>=B22,B23-B22,0)*10*0.58 -> 100.53333 | D23: 15025.667 | E23: =IF(D23>=D22,D23-D22,0)*10*0.58 -> 114.06667 | F23: 77634.333 | G23: =IF(F23>=F22,F23-F22,0)*0.58 -> 108.07333 | H23: =C23+E23+G23 -> 322.67333 | O23: =IF(N23>=N22,N23-N22,0) -> 0 | Q23: =(H23-O23)*0.58 -> 187.15053 | S23: =IF(R23-R22>0,R23-R22,0) -> 0 | T23: =Elect!BT22 -> 240 | U23: =H23/T23 -> 1.3444722 | V23: =Elect!BV22 -> 0 | W23: =H23/V23 -> #DIV/0! | X23: =H23*V1 -> 1290.6933 | Y23: =IF(X23>0,X23/T23,0) -> 5.3778889 | Z23: =IF(X23>0,X23/V23,0) -> #DIV/0!
A24: 18 | B24: 91505 | C24: =IF(B24>=B23,B24-B23,0)*10*0.58 -> 27.066667 | D24: 15043 | E24: =IF(D24>=D23,D24-D23,0)*10*0.58 -> 100.53333 | F24: 77967 | G24: =IF(F24>=F23,F24-F23,0)*0.58 -> 192.94667 | H24: =C24+E24+G24 -> 320.54667 | O24: =IF(N24>=N23,N24-N23,0) -> 0 | Q24: =(H24-O24)*0.58 -> 185.91707 | S24: =IF(R24-R23>0,R24-R23,0) -> 0 | T24: =Elect!BT23 -> 256 | U24: =H24/T24 -> 1.2521354 | V24: =Elect!BV23 -> 0 | W24: =H24/V24 -> #DIV/0! | X24: =H24*V1 -> 1282.1867 | Y24: =IF(X24>0,X24/T24,0) -> 5.0085417 | Z24: =IF(X24>0,X24/V24,0) -> #DIV/0!
A25: 19 | B25: 91543 | C25: =IF(B25>=B24,B25-B24,0)*10*0.58 -> 220.4 | D25: 15073 | E25: =IF(D25>=D24,D25-D24,0)*10*0.58 -> 174 | F25: 78038 | G25: =IF(F25>=F24,F25-F24,0)*0.58 -> 41.18 | H25: =C25+E25+G25 -> 435.58 | O25: =IF(N25>=N24,N25-N24,0) -> 0 | Q25: =(H25-O25)*0.58 -> 252.6364 | S25: =IF(R25-R24>0,R25-R24,0) -> 0 | T25: =Elect!BT24 -> 254 | U25: =H25/T25 -> 1.7148819 | V25: =Elect!BV24 -> 0 | W25: =H25/V25 -> #DIV/0! | X25: =H25*V1 -> 1742.32 | Y25: =IF(X25>0,X25/T25,0) -> 6.8595276 | Z25: =IF(X25>0,X25/V25,0) -> #DIV/0!
A26: 20 | B26: 91565 | C26: =IF(B26>=B25,B26-B25,0)*10*0.58 -> 127.6 | D26: 15101 | E26: =IF(D26>=D25,D26-D25,0)*10*0.58 -> 162.4 | F26: 78257 | G26: =IF(F26>=F25,F26-F25,0)*0.58 -> 127.02 | H26: =C26+E26+G26 -> 417.02 | O26: =IF(N26>=N25,N26-N25,0) -> 0 | Q26: =(H26-O26)*0.58 -> 241.8716 | S26: =IF(R26-R25>0,R26-R25,0) -> 0 | T26: =Elect!BT25 -> 250 | U26: =H26/T26 -> 1.66808 | V26: =Elect!BV25 -> 0 | W26: =H26/V26 -> #DIV/0! | X26: =H26*V1 -> 1668.08 | Y26: =IF(X26>0,X26/T26,0) -> 6.67232 | Z26: =IF(X26>0,X26/V26,0) -> #DIV/0!
A27: 21 | B27: 91581 | C27: =IF(B27>=B26,B27-B26,0)*10*0.58 -> 92.8 | D27: 15120 | E27: =IF(D27>=D26,D27-D26,0)*10*0.58 -> 110.2 | F27: 78411 | G27: =IF(F27>=F26,F27-F26,0)*0.58 -> 89.32 | H27: =C27+E27+G27 -> 292.32 | O27: =IF(N27>=N26,N27-N26,0) -> 0 | Q27: =(H27-O27)*0.58 -> 169.5456 | S27: =IF(R27-R26>0,R27-R26,0) -> 0 | T27: =Elect!BT26 -> 249 | U27: =H27/T27 -> 1.1739759 | V27: =Elect!BV26 -> 0 | W27: =H27/V27 -> #DIV/0! | X27: =H27*V1 -> 1169.28 | Y27: =IF(X27>0,X27/T27,0) -> 4.6959036 | Z27: =IF(X27>0,X27/V27,0) -> #DIV/0!
A28: 22 | B28: 91600 | C28: =IF(B28>=B27,B28-B27,0)*10*0.58 -> 110.2 | D28: 15141 | E28: =IF(D28>=D27,D28-D27,0)*10*0.58 -> 121.8 | F28: 78600 | G28: =IF(F28>=F27,F28-F27,0)*0.58 -> 109.62 | H28: =C28+E28+G28 -> 341.62 | O28: =IF(N28>=N27,N28-N27,0) -> 0 | Q28: =(H28-O28)*0.58 -> 198.1396 | S28: =IF(R28-R27>0,R28-R27,0) -> 0 | T28: =Elect!BT27 -> 240 | U28: =H28/T28 -> 1.4234167 | V28: =Elect!BV27 -> 0 | W28: =H28/V28 -> #DIV/0! | X28: =H28*V1 -> 1366.48 | Y28: =IF(X28>0,X28/T28,0) -> 5.6936667 | Z28: =IF(X28>0,X28/V28,0) -> #DIV/0!
A29: 23 | B29: 91610 | C29: =IF(B29>=B28,B29-B28,0)*10*0.58 -> 58 | D29: 15160 | E29: =IF(D29>=D28,D29-D28,0)*10*0.58 -> 110.2 | F29: 78955 | G29: =IF(F29>=F28,F29-F28,0)*0.58 -> 205.9 | H29: =C29+E29+G29 -> 374.1 | O29: =IF(N29>=N28,N29-N28,0) -> 0 | Q29: =(H29-O29)*0.58 -> 216.978 | S29: =IF(R29-R28>0,R29-R28,0) -> 0 | T29: =Elect!BT28 -> 254 | U29: =H29/T29 -> 1.4728346 | V29: =Elect!BV28 -> 0 | W29: =H29/V29 -> #DIV/0! | X29: =H29*V1 -> 1496.4 | Y29: =IF(X29>0,X29/T29,0) -> 5.8913386 | Z29: =IF(X29>0,X29/V29,0) -> #DIV/0!
A30: 24 | B30: 91640 | C30: =IF(B30>=B29,B30-B29,0)*10*0.58 -> 174 | D30: 15195 | E30: =IF(D30>=D29,D30-D29,0)*10*0.58 -> 203 | F30: 78911 | G30: =IF(F30>=F29,F30-F29,0)*0.58 -> 0 | H30: =C30+E30+G30 -> 377 | O30: =IF(N30>=N29,N30-N29,0) -> 0 | Q30: =(H30-O30)*0.58 -> 218.66 | S30: =IF(R30-R29>0,R30-R29,0) -> 0 | T30: =Elect!BT29 -> 251 | U30: =H30/T30 -> 1.501992 | V30: =Elect!BV29 -> 0 | W30: =H30/V30 -> #DIV/0! | X30: =H30*V1 -> 1508 | Y30: =IF(X30>0,X30/T30,0) -> 6.0079681 | Z30: =IF(X30>0,X30/V30,0) -> #DIV/0!
A31: 25 | B31: 91659 | C31: =IF(B31>=B30,B31-B30,0)*10*0.58 -> 110.2 | D31: 15210 | E31: =IF(D31>=D30,D31-D30,0)*10*0.58 -> 87 | F31: 79186 | G31: =IF(F31>=F30,F31-F30,0)*0.58 -> 159.5 | H31: =C31+E31+G31 -> 356.7 | O31: =IF(N31>=N30,N31-N30,0) -> 0 | Q31: =(H31-O31)*0.58 -> 206.886 | S31: =IF(R31-R30>0,R31-R30,0) -> 0 | T31: =Elect!BT30 -> 252 | U31: =H31/T31 -> 1.4154762 | V31: =Elect!BV30 -> 0 | W31: =H31/V31 -> #DIV/0! | X31: =H31*V1 -> 1426.8 | Y31: =IF(X31>0,X31/T31,0) -> 5.6619048 | Z31: =IF(X31>0,X31/V31,0) -> #DIV/0!
A32: 26 | B32: 91675 | C32: =IF(B32>=B31,B32-B31,0)*10*0.58 -> 92.8 | D32: 15229 | E32: =IF(D32>=D31,D32-D31,0)*10*0.58 -> 110.2 | F32: 79548 | G32: =IF(F32>=F31,F32-F31,0)*0.58 -> 209.96 | H32: =C32+E32+G32 -> 412.96 | O32: =IF(N32>=N31,N32-N31,0) -> 0 | Q32: =(H32-O32)*0.58 -> 239.5168 | S32: =IF(R32-R31>0,R32-R31,0) -> 0 | T32: =Elect!BT31 -> 252 | U32: =H32/T32 -> 1.6387302 | V32: =Elect!BV31 -> 0 | W32: =H32/V32 -> #DIV/0! | X32: =H32*V1 -> 1651.84 | Y32: =IF(X32>0,X32/T32,0) -> 6.5549206 | Z32: =IF(X32>0,X32/V32,0) -> #DIV/0!
A33: 27 | B33: 91692 | C33: =IF(B33>=B32,B33-B32,0)*10*0.58 -> 98.6 | D33: 15249 | E33: =IF(D33>=D32,D33-D32,0)*10*0.58 -> 116 | F33: 79548 | G33: =IF(F33>=F32,F33-F32,0)*0.58 -> 0 | H33: =C33+E33+G33 -> 214.6 | O33: =IF(N33>=N32,N33-N32,0) -> 0 | Q33: =(H33-O33)*0.58 -> 124.468 | S33: =IF(R33-R32>0,R33-R32,0) -> 0 | T33: =Elect!BT32 -> 236 | U33: =H33/T33 -> 0.90932203 | V33: =Elect!BV32 -> 0 | W33: =H33/V33 -> #DIV/0! | X33: =H33*V1 -> 858.4 | Y33: =IF(X33>0,X33/T33,0) -> 3.6372881 | Z33: =IF(X33>0,X33/V33,0) -> #DIV/0!
A34: 28 | B34: 91710 | C34: =IF(B34>=B33,B34-B33,0)*10*0.58 -> 104.4 | D34: 15270 | E34: =IF(D34>=D33,D34-D33,0)*10*0.58 -> 121.8 | F34: 79737 | G34: =IF(F34>=F33,F34-F33,0)*0.58 -> 109.62 | H34: =C34+E34+G34 -> 335.82 | O34: =IF(N34>=N33,N34-N33,0) -> 0 | Q34: =(H34-O34)*0.58 -> 194.7756 | S34: =IF(R34-R33>0,R34-R33,0) -> 0 | T34: =Elect!BT33 -> 230.66667 | U34: =H34/T34 -> 1.4558671 | V34: =Elect!BV33 -> 0 | W34: =H34/V34 -> #DIV/0! | X34: =H34*V1 -> 1343.28 | Y34: =IF(X34>0,X34/T34,0) -> 5.8234682 | Z34: =IF(X34>0,X34/V34,0) -> #DIV/0!
A35: 29 | B35: 91710 | C35: =IF(B35>=B34,B35-B34,0)*10*0.58 -> 0 | D35: 15270 | E35: =IF(D35>=D34,D35-D34,0)*10*0.58 -> 0 | F35: 79737 | G35: =IF(F35>=F34,F35-F34,0)*0.58 -> 0 | H35: =C35+E35+G35 -> 0 | O35: =IF(N35>=N34,N35-N34,0) -> 0 | Q35: =(H35-O35)*0.58 -> 0 | S35: =IF(R35-R34>0,R35-R34,0) -> 0 | T35: =Elect!BT34 -> 0 | U35: =H35/T35 -> #DIV/0! | V35: =Elect!BV34 -> 0 | W35: =H35/V35 -> #DIV/0! | X35: =H35*V1 -> 0 | Y35: =IF(X35>0,X35/T35,0) -> 0 | Z35: =IF(X35>0,X35/V35,0) -> 0
A36: 30 | B36: 91710 | C36: =IF(B36>=B35,B36-B35,0)*10*0.58 -> 0 | D36: 15270 | E36: =IF(D36>=D35,D36-D35,0)*10*0.58 -> 0 | F36: 79737 | G36: =IF(F36>=F35,F36-F35,0)*0.58 -> 0 | H36: =C36+E36+G36 -> 0 | O36: =IF(N36>=N35,N36-N35,0) -> 0 | Q36: =(H36-O36)*0.58 -> 0 | S36: =IF(R36-R35>0,R36-R35,0) -> 0 | T36: =Elect!BT35 -> 0 | U36: =H36/T36 -> #DIV/0! | V36: =Elect!BV35 -> 0 | W36: =H36/V36 -> #DIV/0! | X36: =H36*V1 -> 0 | Y36: =IF(X36>0,X36/T36,0) -> 0 | Z36: =IF(X36>0,X36/V36,0) -> 0
A37: 31 | B37: 91710 | C37: =IF(B37>=B36,B37-B36,0)*10*0.58 -> 0 | D37: 15270 | E37: =IF(D37>=D36,D37-D36,0)*10*0.58 -> 0 | F37: 79737 | G37: =IF(F37>=F36,F37-F36,0)*0.58 -> 0 | H37: =C37+E37+G37 -> 0 | I37: 339 | K37: 5830 | O37: =IF(N37>=N36,N37-N36,0) -> 0 | Q37: =(H37-O37)*0.58 -> 0 | S37: =IF(R37-R36>0,R37-R36,0) -> 0 | T37: =Elect!BT36 -> 0 | U37: =H37/T37 -> #DIV/0! | V37: =Elect!BV36 -> 0 | W37: =H37/V37 -> #DIV/0! | X37: =H37*V7 -> 0 | Y37: =IF(X37>0,X37/T37,0) -> 0 | Z37: =IF(X37>0,X37/V37,0) -> 0
A38: MTD | C38: =SUM(C7:C37) -> 2859.4 | E38: =SUM(E7:E37) -> 3288.6 | G38: =SUM(G7:G37) -> 3098.36 | H38: =SUM(H7:H37) -> 9246.36 | O38: =SUM(O7:O36) -> 0 | Q38: =SUM(Q7:Q34) -> 5362.8888 | S38: =SUM(S7:S34) -> 0 | T38: =SUM(T7:T36) -> 6025.6667 | U38: =IF(H38>0,H38/T38,0) -> 1.5344958 | V38: =SUM(V7:V36) -> 0 | W38: =IF(H38>0,H38/V38,0) -> #DIV/0! | X38: =SUM(X7:X36) -> 36985.44 | Y38: =IF(X38>0,X38/T38,0) -> 6.1379831 | Z38: =IF(X38>0,X38/V38,0) -> #DIV/0!
A39: AVER. Act | C39: =C38/B48 -> 95.313333 | E39: =E38/B48 -> 109.62 | G39: =G38/B48 -> 103.27867 | H39: =H38/B48 -> 308.212 | O39: =O38/B48 -> 0 | Q39: =Q38/B48 -> 178.76296 | S39: =S38/C48 -> #DIV/0! | T39: =T38/B48 -> 200.85556 | U39: =IF(H39>0,H39/T39,0) -> 1.5344958 | V39: =V38/B48 -> 0 | W39: =IF(H39>0,H39/V39,0) -> #DIV/0! | X39: =X38/B48 -> 1232.848 | Y39: =IF(X39>0,X39/T39,0) -> 6.1379831 | Z39: =IF(X39>0,X39/V39,0) -> #DIV/0!
A40: TOTAL Budget | T40: =YTD!Q2341 -> 0 | U40: =IF(#REF!>0,#REF!/T40,0) -> #REF! | V40: =YTD!Q2342 -> 0 | W40: =IF(#REF!>0,#REF!/V40,0) -> #REF! | X40: =YTD!Q2346 -> 0 | Y40: =IF(X40>0,X40/T40,0) -> 0 | Z40: =IF(X40>0,X40/V40,0) -> 0
A41: Budget MTD | T41: =T42*C48 -> #VALUE! | U41: =IF(#REF!>0,#REF!/T41,0) -> #REF! | V41: =V42*C48 -> #VALUE! | W41: =IF(#REF!>0,#REF!/V41,0) -> #REF! | X41: =#REF!*5.62 -> #REF! | Y41: =IF(X41>0,X41/T41,0) -> #REF! | Z41: =IF(X41>0,X41/V41,0) -> #REF!
A42: AVER. Bud | T42: =T40/$A$48 -> #VALUE! | V42: =V40/$A$48 -> #VALUE!
A43: Total RFC | T43: =YTD!Q2358 -> 0 | V43: =YTD!Q2359 -> 0 | X43: =YTD!Q2363 -> 0 | Y43: =IF(X43>0,X43/T43,0) -> 0 | Z43: =IF(X43>0,X43/V43,0) -> 0
A44: RFC MTD | T44: =T43/A48*C48 -> #VALUE! | V44: =V43/A48*C48 -> #VALUE! | X44: =X43/A48*C48 -> #VALUE! | Y44: =IF(X44>0,X44/T44,0) -> #VALUE! | Z44: =IF(X44>0,X44/V44,0) -> #VALUE!
A45: AVER RFC | T45: =T43/A48 -> #VALUE! | V45: =V44/A48*C48 -> #VALUE! | X45: =X43/A48 -> #VALUE!
A46: MTD 13 | U46: =Consp!BH33 -> 1.1514679 | W46: =Consp!BI33 -> 0.57929342 | X46: =Consp!BJ33 -> 140121.3 | Y46: =Consp!BK33 -> 6.8331854 | Z46: =Consp!BL33 -> 3.4377159
A47: AVER. Act 13 | U47: =Consp!BH34 -> 1.1761372 | W47: =Consp!BI34 -> 0.60007377 | X47: =Consp!BJ34 -> 5004.3322 | Y47: =Consp!BK34 -> 6.8331854 | Z47: =Consp!BL34 -> 3.4377159
A48: No of Days MTD | B48: =COUNTIF(B7:B36,">0") -> 30
A136: Water Incoming

Sheet Gas
A1: =Elect!A1 -> 44958 | E1: Gas | H1: Gas UP | J1: 3.9
A4: NO. | B4: Main Gas Flow Meter | D4: Laundry Gas Flow Meter | F4: Grumandiz Gas Flow Meter | H4: Plant Room Gas Share Cost | I4: Hotel Consumption Cost | J4: La Grumandiz Cost | K4: Total Natural Gas Consumption
B5: Read | C5: Cons | D5: Read | E5: Cons | F5: Read | G5: Cons | H5: LE/DAY | I5: LE/DAY | J5: LE/DAY | K5: Cons
B6: 8502573 | C6: =IF(B6>=B5,B6-B5,0)*1.06 -> 0 | D6: 632460 | E6: =IF(D6>=D5,D6-D5,0)*0.7 -> 0 | F6: 635107 | G6: =IF(F6>=F5,F6-F5,0) -> 0 | K6: =C6+E6 -> 0
A7: 1 | B7: 8503700 | C7: =IF(B7>=B6,B7-B6,0)*1.06 -> 1194.62 | D7: 632927 | E7: =IF(D7>=D6,D7-D6,0)*0.7 -> 326.9 | F7: 635197 | G7: =IF(F7>=F6,F7-F6,0) -> 90 | H7: =(E7*0.55)*1.61 -> 289.46995 | I7: =C7*J1 -> 4659.018 | J7: =G7*J1 -> 351 | K7: =C7+E7 -> 1521.52
A8: 2 | B8: 8504997 | C8: =IF(B8>=B7,B8-B7,0)*1.06 -> 1374.82 | D8: 633490 | E8: =IF(D8>=D7,D8-D7,0)*0.7 -> 394.1 | F8: 635304 | G8: =IF(F8>=F7,F8-F7,0) -> 107 | H8: =(E8*0.55)*1.61 -> 348.97555 | I8: =C8*J1 -> 5361.798 | J8: =G8*J1 -> 417.3 | K8: =C8+E8 -> 1768.92
A9: 3 | B9: 8506397 | C9: =IF(B9>=B8,B9-B8,0)*1.06 -> 1484 | D9: 634013 | E9: =IF(D9>=D8,D9-D8,0)*0.7 -> 366.1 | F9: 635412 | G9: =IF(F9>=F8,F9-F8,0) -> 108 | H9: =(E9*0.55)*1.61 -> 324.18155 | I9: =C9*J1 -> 5787.6 | J9: =G9*J1 -> 421.2 | K9: =C9+E9 -> 1850.1
A10: 4 | B10: 8508033 | C10: =IF(B10>=B9,B10-B9,0)*1.06 -> 1734.16 | D10: 634769 | E10: =IF(D10>=D9,D10-D9,0)*0.7 -> 529.2 | F10: 635521 | G10: =IF(F10>=F9,F10-F9,0) -> 109 | H10: =(E10*0.55)*1.61 -> 468.6066 | I10: =C10*J1 -> 6763.224 | J10: =G10*J1 -> 425.1 | K10: =C10+E10 -> 2263.36
A11: 5 | B11: 8509511.7 | C11: =IF(B11>=B10,B11-B10,0)*1.06 -> 1567.3867 | D11: 635369.67 | E11: =IF(D11>=D10,D11-D10,0)*0.7 -> 420.46667 | F11: 635629.33 | G11: =IF(F11>=F10,F11-F10,0) -> 108.33333 | H11: =(E11*0.55)*1.61 -> 372.32323 | I11: =C11*J1 -> 6112.808 | J11: =G11*J1 -> 422.5 | K11: =C11+E11 -> 1987.8533
A12: 6 | B12: 8510777 | C12: =IF(B12>=B11,B12-B11,0)*1.06 -> 1341.2533 | D12: 635882 | E12: =IF(D12>=D11,D12-D11,0)*0.7 -> 358.63333 | F12: 635688 | G12: =IF(F12>=F11,F12-F11,0) -> 58.666667 | H12: =(E12*0.55)*1.61 -> 317.56982 | I12: =C12*J1 -> 5230.888 | J12: =G12*J1 -> 228.8 | K12: =C12+E12 -> 1699.8867
A13: 7 | B13: 8512163 | C13: =IF(B13>=B12,B13-B12,0)*1.06 -> 1469.16 | D13: 636448 | E13: =IF(D13>=D12,D13-D12,0)*0.7 -> 396.2 | F13: 635770 | G13: =IF(F13>=F12,F13-F12,0) -> 82 | H13: =(E13*0.55)*1.61 -> 350.8351 | I13: =C13*J1 -> 5729.724 | J13: =G13*J1 -> 319.8 | K13: =C13+E13 -> 1865.36
A14: 8 | B14: 8513647 | C14: =IF(B14>=B13,B14-B13,0)*1.06 -> 1573.04 | D14: 637017 | E14: =IF(D14>=D13,D14-D13,0)*0.7 -> 398.3 | F14: 635864 | G14: =IF(F14>=F13,F14-F13,0) -> 94 | H14: =(E14*0.55)*1.61 -> 352.69465 | I14: =C14*J1 -> 6134.856 | J14: =G14*J1 -> 366.6 | K14: =C14+E14 -> 1971.34
A15: 9 | B15: 8515031 | C15: =IF(B15>=B14,B15-B14,0)*1.06 -> 1467.04 | D15: 637597 | E15: =IF(D15>=D14,D15-D14,0)*0.7 -> 406 | F15: 635946 | G15: =IF(F15>=F14,F15-F14,0) -> 82 | H15: =(E15*0.55)*1.61 -> 359.513 | I15: =C15*J1 -> 5721.456 | J15: =G15*J1 -> 319.8 | K15: =C15+E15 -> 1873.04
A16: 10 | B16: 8516442 | C16: =IF(B16>=B15,B16-B15,0)*1.06 -> 1495.66 | D16: 638231 | E16: =IF(D16>=D15,D16-D15,0)*0.7 -> 443.8 | F16: 636032 | G16: =IF(F16>=F15,F16-F15,0) -> 86 | H16: =(E16*0.55)*1.61 -> 392.9849 | I16: =C16*J1 -> 5833.074 | J16: =G16*J1 -> 335.4 | K16: =C16+E16 -> 1939.46
A17: 11 | B17: 8518182 | C17: =IF(B17>=B16,B17-B16,0)*1.06 -> 1844.4 | D17: 638957 | E17: =IF(D17>=D16,D17-D16,0)*0.7 -> 508.2 | F17: 636142 | G17: =IF(F17>=F16,F17-F16,0) -> 110 | H17: =(E17*0.55)*1.61 -> 450.0111 | I17: =C17*J1 -> 7193.16 | J17: =G17*J1 -> 429 | K17: =C17+E17 -> 2352.6
A18: 12 | B18: 8519915 | C18: =IF(B18>=B17,B18-B17,0)*1.06 -> 1836.98 | D18: 639565 | E18: =IF(D18>=D17,D18-D17,0)*0.7 -> 425.6 | F18: 636250 | G18: =IF(F18>=F17,F18-F17,0) -> 108 | H18: =(E18*0.55)*1.61 -> 376.8688 | I18: =C18*J1 -> 7164.222 | J18: =G18*J1 -> 421.2 | K18: =C18+E18 -> 2262.58
A19: 13 | B19: 8521244 | C19: =IF(B19>=B18,B19-B18,0)*1.06 -> 1408.74 | D19: 640225 | E19: =IF(D19>=D18,D19-D18,0)*0.7 -> 462 | F19: 636333 | G19: =IF(F19>=F18,F19-F18,0) -> 83 | H19: =(E19*0.55)*1.61 -> 409.101 | I19: =C19*J1 -> 5494.086 | J19: =G19*J1 -> 323.7 | K19: =C19+E19 -> 1870.74
A20: 14 | B20: 8522842 | C20: =IF(B20>=B19,B20-B19,0)*1.06 -> 1693.88 | D20: 640844 | E20: =IF(D20>=D19,D20-D19,0)*0.7 -> 433.3 | F20: 636422 | G20: =IF(F20>=F19,F20-F19,0) -> 89 | H20: =(E20*0.55)*1.61 -> 383.68715 | I20: =C20*J1 -> 6606.132 | J20: =G20*J1 -> 347.1 | K20: =C20+E20 -> 2127.18
A21: 15 | B21: 8524625 | C21: =IF(B21>=B20,B21-B20,0)*1.06 -> 1889.98 | D21: 641456 | E21: =IF(D21>=D20,D21-D20,0)*0.7 -> 428.4 | F21: 636529 | G21: =IF(F21>=F20,F21-F20,0) -> 107 | H21: =(E21*0.55)*1.61 -> 379.3482 | I21: =C21*J1 -> 7370.922 | J21: =G21*J1 -> 417.3 | K21: =C21+E21 -> 2318.38
A22: 16 | B22: 8526117 | C22: =IF(B22>=B21,B22-B21,0)*1.06 -> 1581.52 | D22: 642122 | E22: =IF(D22>=D21,D22-D21,0)*0.7 -> 466.2 | F22: 636617 | G22: =IF(F22>=F21,F22-F21,0) -> 88 | H22: =(E22*0.55)*1.61 -> 412.8201 | I22: =C22*J1 -> 6167.928 | J22: =G22*J1 -> 343.2 | K22: =C22+E22 -> 2047.72
A23: 17 | B23: 8527609 | C23: =IF(B23>=B22,B23-B22,0)*1.06 -> 1581.52 | D23: 642752 | E23: =IF(D23>=D22,D23-D22,0)*0.7 -> 441 | F23: 636717.67 | G23: =IF(F23>=F22,F23-F22,0) -> 100.66667 | H23: =(E23*0.55)*1.61 -> 390.5055 | I23: =C23*J1 -> 6167.928 | J23: =G23*J1 -> 392.6 | K23: =C23+E23 -> 2022.52
A24: 18 | B24: 8529312 | C24: =IF(B24>=B23,B24-B23,0)*1.06 -> 1805.18 | D24: 643335 | E24: =IF(D24>=D23,D24-D23,0)*0.7 -> 408.1 | F24: 636780 | G24: =IF(F24>=F23,F24-F23,0) -> 62.333333 | H24: =(E24*0.55)*1.61 -> 361.37255 | I24: =C24*J1 -> 7040.202 | J24: =G24*J1 -> 243.1 | K24: =C24+E24 -> 2213.28
A25: 19 | B25: 8531155 | C25: =IF(B25>=B24,B25-B24,0)*1.06 -> 1953.58 | D25: 644736 | E25: =IF(D25>=D24,D25-D24,0)*0.7 -> 980.7 | F25: 636908 | G25: =IF(F25>=F24,F25-F24,0) -> 128 | H25: =(E25*0.55)*1.61 -> 868.40985 | I25: =C25*J1 -> 7618.962 | J25: =G25*J1 -> 499.2 | K25: =C25+E25 -> 2934.28
A26: 20 | B26: 8532979 | C26: =IF(B26>=B25,B26-B25,0)*1.06 -> 1933.44 | D26: 645350 | E26: =IF(D26>=D25,D26-D25,0)*0.7 -> 429.8 | F26: 636994 | G26: =IF(F26>=F25,F26-F25,0) -> 86 | H26: =(E26*0.55)*1.61 -> 380.5879 | I26: =C26*J1 -> 7540.416 | J26: =G26*J1 -> 335.4 | K26: =C26+E26 -> 2363.24
A27: 21 | B27: 8534500 | C27: =IF(B27>=B26,B27-B26,0)*1.06 -> 1612.26 | D27: 645993 | E27: =IF(D27>=D26,D27-D26,0)*0.7 -> 450.1 | F27: 637102 | G27: =IF(F27>=F26,F27-F26,0) -> 108 | H27: =(E27*0.55)*1.61 -> 398.56355 | I27: =C27*J1 -> 6287.814 | J27: =G27*J1 -> 421.2 | K27: =C27+E27 -> 2062.36
A28: 22 | B28: 8536227 | C28: =IF(B28>=B27,B28-B27,0)*1.06 -> 1830.62 | D28: 646750 | E28: =IF(D28>=D27,D28-D27,0)*0.7 -> 529.9 | F28: 637189 | G28: =IF(F28>=F27,F28-F27,0) -> 87 | H28: =(E28*0.55)*1.61 -> 469.22645 | I28: =C28*J1 -> 7139.418 | J28: =G28*J1 -> 339.3 | K28: =C28+E28 -> 2360.52
A29: 23 | B29: 8538060 | C29: =IF(B29>=B28,B29-B28,0)*1.06 -> 1942.98 | D29: 647050 | E29: =IF(D29>=D28,D29-D28,0)*0.7 -> 210 | F29: 637265 | G29: =IF(F29>=F28,F29-F28,0) -> 76 | H29: =(E29*0.55)*1.61 -> 185.955 | I29: =C29*J1 -> 7577.622 | J29: =G29*J1 -> 296.4 | K29: =C29+E29 -> 2152.98
A30: 24 | B30: 8539055 | C30: =IF(B30>=B29,B30-B29,0)*1.06 -> 1054.7 | D30: 648053 | E30: =IF(D30>=D29,D30-D29,0)*0.7 -> 702.1 | F30: 637345 | G30: =IF(F30>=F29,F30-F29,0) -> 80 | H30: =(E30*0.55)*1.61 -> 621.70955 | I30: =C30*J1 -> 4113.33 | J30: =G30*J1 -> 312 | K30: =C30+E30 -> 1756.8
A31: 25 | B31: 8540512.7 | C31: =IF(B31>=B30,B31-B30,0)*1.06 -> 1545.1267 | D31: 649052 | E31: =IF(D31>=D30,D31-D30,0)*0.7 -> 699.3 | F31: 637496 | G31: =IF(F31>=F30,F31-F30,0) -> 151 | H31: =(E31*0.55)*1.61 -> 619.23015 | I31: =C31*J3 -> 0 | J31: =G31*J1 -> 588.9 | K31: =C31+E31 -> 2244.4267
A32: 26 | B32: 8541950 | C32: =IF(B32>=B31,B32-B31,0)*1.06 -> 1523.5733 | D32: 649667 | E32: =IF(D32>=D31,D32-D31,0)*0.7 -> 430.5 | F32: 637621 | G32: =IF(F32>=F31,F32-F31,0) -> 125 | H32: =(E32*0.55)*1.61 -> 381.20775 | I32: =C32*J1 -> 5941.936 | J32: =G32*J1 -> 487.5 | K32: =C32+E32 -> 1954.0733
A33: 27 | B33: 8543200 | C33: =IF(B33>=B32,B33-B32,0)*1.06 -> 1325 | D33: 650369 | E33: =IF(D33>=D32,D33-D32,0)*0.7 -> 491.4 | F33: 637685 | G33: =IF(F33>=F32,F33-F32,0) -> 64 | H33: =(E33*0.55)*1.61 -> 435.1347 | I33: =C33*J1 -> 5167.5 | J33: =G33*J1 -> 249.6 | K33: =C33+E33 -> 1816.4
A34: 28 | B34: 8544731 | C34: =IF(B34>=B33,B34-B33,0)*1.06 -> 1622.86 | D34: 651055 | E34: =IF(D34>=D33,D34-D33,0)*0.7 -> 480.2 | F34: 637774 | G34: =IF(F34>=F33,F34-F33,0) -> 89 | H34: =(E34*0.55)*1.61 -> 425.2171 | I34: =C34*J1 -> 6329.154 | J34: =G34*J1 -> 347.1 | K34: =C34+E34 -> 2103.06
A35: 29 | B35: 8544731 | C35: =IF(B35>=B34,B35-B34,0)*1.06 -> 0 | D35: 651055 | E35: =IF(D35>=D34,D35-D34,0)*0.7 -> 0 | F35: 637774 | G35: =IF(F35>=F34,F35-F34,0) -> 0 | H35: =(E35*0.55)*1.61 -> 0 | I35: =C35*J1 -> 0 | J35: =G35*J1 -> 0 | K35: =C35+E35 -> 0
A36: 30 | B36: 8544731 | C36: =IF(B36>=B35,B36-B35,0)*1.06 -> 0 | D36: 651055 | E36: =IF(D36>=D35,D36-D35,0)*0.7 -> 0 | F36: 637774 | G36: =IF(F36>=F35,F36-F35,0) -> 0 | H36: =(E36*0.55)*1.61 -> 0 | I36: =C36*J1 -> 0 | J36: =G36*J1 -> 0 | K36: =C36+E36 -> 0
A37: 31 | B37: 8544731 | C37: =IF(B37>=B36,B37-B36,0)*1.06 -> 0 | D37: 651055 | E37: =IF(D37>=D36,D37-D36,0)*0.7 -> 0 | F37: 637774 | G37: =IF(F37>=F36,F37-F36,0) -> 0 | H37: =(E37*0.55)*1.61 -> 0 | I37: =C37*J1 -> 0 | J37: =G37*J1 -> 0 | K37: =C37+E37 -> 0
A38: MTD | C38: =SUM(C7:C37) -> 44687.48 | E38: =SUM(E7:E37) -> 13016.5 | G38: =SUM(G7:G37) -> 2667 | H38: =SUM(H6:H37) -> 11526.111 | I38: =SUM(I6:I37) -> 168255.18 | J38: =SUM(J6:J37) -> 10401.3 | K38: =SUM(K6:K37) -> 57703.98
A39: Average MTD. | C39: =C38/A42 -> 1489.5827 | E39: =E38/A42 -> 433.88333 | G39: =G38/A42 -> 88.9 | H39: =H38/A42 -> 384.20369 | I39: =I38/A42 -> 5608.5059 | J39: =J38/A42 -> 346.71
A41: No of Days MTD
A42: =COUNTIF(B7:B36,">0") -> 30

Sheet Sheet1

Sheet Sheet2

Sheet Consp
A1: =Elect!A1 -> 44958 | L1: Summary | P1: =Elect!A1 -> 44958
B2: Elect Consuumption | H2: Water Incoming | U2: Water Consumption | AC2: Irrigation | AG2: Gas | AJ2: Cost | AK2: Solar Meter [ LIT ] | AL2: No. of Eng. | AM2: No. of Gardners | AN2: Cons. (lit) | AO2: Received Gas (tons) | AP2: Fuel Cost | AQ2: Solar level [cm] | AR2: Received Solar (tons) | AS2: Fuel Cost | AT2: Occupancy 10 | AV2: Occupancy07 | AZ2: Elect 2009 | BE2: Elect 2010 | BJ2: Water 2009 | BO2: Water 2010
A3: Date | B3: COUNTER (2) | D3: MD | F3: KVAR | H3: R.O | J3: Qenna | L3: Trucks | N3: Rimievera Line Meter | O3: Total Inc. | Q3: Total Main S.Pool | S3: Total Bar & Beach cons. | U3: Total S. Pool cons. | W3: Hotel consumption. | Y3: Sold Water | AA3: Irr. Water from R.O | AC3: Irr. Consumption. | AE3: Storage Water One tank | AF3: Grand Cons | AG3: % | AH3: Stock | AI3: Cons. | AJ3: 0 | AT3: No of guest | AU3: No. of rooms | AV3: No. of rooms | AW3: No. of guest | AX3: Cons. Per occ. room | AY3: Cons. Per guest | AZ3: Total cost | BA3: cost per room | BB3: cost per guest | BC3: Cons. Per occ. room | BD3: Cons. Per guest | BE3: Total cost | BF3: cost per room | BG3: cost per guest | BH3: Cons. Per occ. room | BI3: Cons. Per guest | BJ3: Total cost | BK3: cost per room | BL3: cost per guest | BM3: Cons. Per occ. room | BN3: Cons. Per guest | BO3: Total cost | BP3: cost per room | BQ3: cost per guest
B4: 2013 | C4: 2014 | D4: 2013 | E4: 2014 | F4: 2013 | G4: 2014 | H4: 2013 | I4: 2014 | J4: 2009 | K4: 2010 | L4: 2009 | M4: 2010 | O4: 2009 | P4: 2010 | Q4: 2009 | R4: 2010 | S4: 2009 | T4: 2010 | U4: 2009 | V4: 2010 | W4: 2009 | X4: 2010 | Y4: 2009 | Z4: 2010 | AA4: 2009 | AB4: 2010 | AC4: 2009 | AD4: 2010
A5: 1 | B5: 33600 | C5: =Elect!J6 -> 7543.3333 | D5: 0 | E5: =Elect!M6 -> 2948.3333 | F5: 20 | G5: =Elect!O6 -> 113 | H5: 800 | I5: =Water!C7 -> 58 | J5: 0 | K5: =Water!E7 -> 58 | L5: 0 | M5: =Water!#REF! -> #REF! | N5: =Water!#REF! -> #REF! | O5: 1005 | P5: =Water!H7 -> 209.38 | Q5: 114 | R5: =Water!O7 -> 0 | S5: 13 | T5: =Water!#REF! -> #REF! | U5: 147 | V5: =Water!#REF! -> #REF! | W5: 755 | X5: =Water!Q7 -> 121.4404 | Y5: 0 | Z5: =Water!#REF! -> #REF! | AA5: 0 | AB5: 0 | AC5: 690 | AD5: =Water!#REF! -> #REF! | AE5: =Water!#REF! -> #REF! | AF5: =Water!#REF! -> #REF! | AG5: =Gas!#REF! -> #REF! | AH5: =Gas!C7 -> 1194.62 | AI5: =Gas!#REF! -> #REF! | AJ5: =Gas!J7 -> 351 | AK5: =Gas!#REF! -> #REF! | AL5: =Gas!#REF! -> #REF! | AM5: =Gas!#REF! -> #REF! | AN5: =Gas!#REF! -> #REF! | AO5: =Gas!#REF! -> #REF! | AP5: =Gas!#REF! -> #REF! | AQ5: =Gas!#REF! -> #REF! | AR5: =Gas!#REF! -> #REF! | AS5: =Gas!#REF! -> #REF! | AT5: =Elect!BR6 -> 121 | AU5: =Elect!BP6 -> 133 | AV5: =Elect!#REF! -> #REF! | AW5: =Elect!BR6 -> 121 | AX5: 48.695652 | AY5: 24.705882 | AZ5: 8835.4834 | BA5: 12.805048 | BB5: 6.496679 | BC5: =Elect!#REF! -> #REF! | BD5: =Elect!#REF! -> #REF! | BE5: =Elect!#REF! -> #REF! | BF5: =Elect!#REF! -> #REF! | BG5: =Elect!#REF! -> #REF! | BH5: 1.142029 | BI5: 0.57941176 | BJ5: 4569.1158 | BK5: 6.6219069 | BL5: 3.3596439 | BM5: =Water!U7 -> 2.1585567 | BN5: =Water!W7 -> #DIV/0! | BO5: =Water!X7 -> 837.52 | BP5: =Water!Y7 -> 8.6342268 | BQ5: =Water!Z7 -> 0
A6: 2 | B6: 31200 | C6: =Elect!J7 -> 7209 | D6: 0 | E6: =Elect!M7 -> 2680 | F6: 20 | G6: =Elect!O7 -> 4300 | H6: 936 | I6: =Water!C8 -> 75.4 | J6: 0 | K6: =Water!E8 -> 87 | L6: 0 | M6: =Water!#REF! -> #REF! | N6: =Water!#REF! -> #REF! | O6: 1006 | P6: =Water!H8 -> 256.36 | Q6: 113 | R6: =Water!O8 -> 0 | S6: 17 | T6: =Water!#REF! -> #REF! | U6: 140 | V6: =Water!#REF! -> #REF! | W6: 792 | X6: =Water!Q8 -> 148.6888 | Y6: 0 | Z6: =Water!#REF! -> #REF! | AA6: 0 | AB6: 0 | AC6: 370 | AD6: =Water!#REF! -> #REF! | AE6: =Water!#REF! -> #REF! | AF6: =Water!#REF! -> #REF! | AG6: =Gas!B7 -> 8503700 | AH6: =Gas!C8 -> 1374.82 | AI6: =Gas!#REF! -> #REF! | AJ6: =Gas!J8 -> 417.3 | AK6: =Gas!#REF! -> #REF! | AL6: =Gas!#REF! -> #REF! | AM6: =Gas!#REF! -> #REF! | AN6: =Gas!#REF! -> #REF! | AO6: =Gas!#REF! -> #REF! | AP6: =Gas!#REF! -> #REF! | AQ6: =Gas!#REF! -> #REF! | AR6: =Gas!#REF! -> #REF! | AS6: =Gas!#REF! -> #REF! | AT6: =Elect!BR7 -> 128 | AU6: =Elect!BP7 -> 117 | AX6: 47.416413 | AY6: 23.981553 | AZ6: 8299.2754 | BA6: 12.612881 | BB6: 6.379151 | BC6: =Elect!BQ7 -> 570827 | BD6: =Elect!#REF! -> #REF! | BE6: =Elect!#REF! -> #REF! | BF6: =Elect!#REF! -> #REF! | BG6: =Elect!#REF! -> #REF! | BH6: 1.2021277 | BI6: 0.60799385 | BJ6: 5345.8654 | BK6: 8.1244156 | BL6: 4.1090434 | BM6: =Water!U8 -> 2.0028125 | BN6: =Water!W8 -> #DIV/0! | BO6: =Water!X8 -> 1025.44 | BP6: =Water!Y8 -> 8.01125 | BQ6: =Water!Z8 -> #DIV/0!
A7: 3 | B7: 31200 | C7: =Elect!J8 -> 6942 | D7: 0 | E7: =Elect!M8 -> 2366 | F7: 20 | G7: =Elect!O8 -> 2202 | H7: 685 | I7: =Water!C9 -> 98.6 | J7: 0 | K7: =Water!E9 -> 110.2 | L7: 0 | M7: =Water!#REF! -> #REF! | N7: =Water!#REF! -> #REF! | O7: 902 | P7: =Water!H9 -> 336.98 | Q7: 126 | R7: =Water!O9 -> 0 | S7: 26 | T7: =Water!#REF! -> #REF! | U7: 134 | V7: =Water!#REF! -> #REF! | W7: 766 | X7: =Water!Q9 -> 195.4484 | Y7: 0 | Z7: =Water!#REF! -> #REF! | AA7: 0 | AB7: 0 | AC7: 740 | AD7: =Water!#REF! -> #REF! | AE7: =Water!#REF! -> #REF! | AF7: =Water!#REF! -> #REF! | AG7: =Gas!B9 -> 8506397 | AH7: =Gas!C9 -> 1484 | AI7: =Gas!#REF! -> #REF! | AJ7: =Gas!J9 -> 421.2 | AK7: =Gas!#REF! -> #REF! | AL7: =Gas!#REF! -> #REF! | AM7: =Gas!#REF! -> #REF! | AN7: =Gas!#REF! -> #REF! | AO7: =Gas!#REF! -> #REF! | AP7: =Gas!#REF! -> #REF! | AQ7: =Gas!#REF! -> #REF! | AR7: =Gas!#REF! -> #REF! | AS7: =Gas!#REF! -> #REF! | AT7: =Elect!BR8 -> 154 | AU7: =Elect!BP8 -> 118 | AX7: 47.926267 | AY7: 24.223602 | AZ7: 8299.2754 | BA7: 12.748503 | BB7: 6.4435368 | BC7: =Elect!BQ8 -> 570981 | BD7: =Elect!#REF! -> #REF! | BE7: =Elect!#REF! -> #REF! | BF7: =Elect!#REF! -> #REF! | BG7: =Elect!#REF! -> #REF! | BH7: 1.0875576 | BI7: 0.54968944 | BJ7: 3912.3054 | BK7: 6.0096857 | BL7: 3.0375042 | BM7: =Water!U9 -> 2.5921538 | BN7: =Water!W9 -> #DIV/0! | BO7: =Water!X9 -> 1347.92 | BP7: =Water!Y9 -> 10.368615 | BQ7: =Water!Z9 -> #DIV/0!
A8: 4 | B8: 33600 | C8: =Elect!J9 -> 6919 | D8: 0 | E8: =Elect!M9 -> 2354 | F8: 20 | G8: =Elect!O9 -> 2374 | H8: 786 | I8: =Water!C10 -> 110.2 | J8: 0 | K8: =Water!E10 -> 110.2 | L8: 0 | M8: =Water!#REF! -> #REF! | N8: =Water!#REF! -> #REF! | O8: 930 | P8: =Water!H10 -> 346.26 | Q8: 153 | R8: =Water!O10 -> 0 | S8: 46 | T8: =Water!#REF! -> #REF! | U8: 150 | V8: =Water!#REF! -> #REF! | W8: 766 | X8: =Water!Q10 -> 200.8308 | Y8: 0 | Z8: =Water!#REF! -> #REF! | AA8: 0 | AB8: 0 | AC8: 820 | AD8: =Water!#REF! -> #REF! | AE8: =Water!#REF! -> #REF! | AF8: =Water!#REF! -> #REF! | AG8: =Gas!B10 -> 8508033 | AH8: =Gas!C10 -> 1734.16 | AI8: =Gas!#REF! -> #REF! | AJ8: =Gas!J10 -> 425.1 | AK8: =Gas!#REF! -> #REF! | AL8: =Gas!#REF! -> #REF! | AM8: =Gas!#REF! -> #REF! | AN8: =Gas!#REF! -> #REF! | AO8: =Gas!#REF! -> #REF! | AP8: =Gas!#REF! -> #REF! | AQ8: =Gas!#REF! -> #REF! | AR8: =Gas!#REF! -> #REF! | AS8: =Gas!#REF! -> #REF! | AT8: =Elect!BR9 -> 157 | AU8: =Elect!BP9 -> 118 | AX8: 51.06383 | AY8: 25.866051 | AZ8: 8835.4834 | BA8: 13.427786 | BB8: 6.8017578 | BC8: =Elect!BQ9 -> 571138 | BD8: =Elect!#REF! -> #REF! | BE8: =Elect!#REF! -> #REF! | BF8: =Elect!#REF! -> #REF! | BG8: =Elect!#REF! -> #REF! | BH8: 1.2218845 | BI8: 0.61893764 | BJ8: 4489.1562 | BK8: 6.8224259 | BL8: 3.4558555 | BM8: =Water!U10 -> 1.4672034 | BN8: =Water!W10 -> #DIV/0! | BO8: =Water!X10 -> 1385.04 | BP8: =Water!Y10 -> 5.8688136 | BQ8: =Water!Z10 -> #DIV/0!
A9: 5 | B9: 31200 | C9: =Elect!J10 -> 6667 | D9: 0 | E9: =Elect!M10 -> 2303 | F9: 20 | G9: =Elect!O10 -> 2259.3333 | H9: 789 | I9: =Water!C11 -> 102.46667 | J9: 0 | K9: =Water!E11 -> 110.2 | L9: 0 | M9: =Water!#REF! -> #REF! | N9: =Water!#REF! -> #REF! | O9: 1003 | P9: =Water!H11 -> 340.07333 | Q9: 102 | R9: =Water!O11 -> 0 | S9: 8 | T9: =Water!#REF! -> #REF! | U9: 130 | V9: =Water!#REF! -> #REF! | W9: 735 | X9: =Water!Q11 -> 197.24253 | Y9: 0 | Z9: =Water!#REF! -> #REF! | AA9: 0 | AB9: 0 | AC9: 640 | AD9: =Water!#REF! -> #REF! | AE9: =Water!#REF! -> #REF! | AF9: =Water!#REF! -> #REF! | AG9: =Gas!B11 -> 8509511.7 | AH9: =Gas!C11 -> 1567.3867 | AI9: =Gas!#REF! -> #REF! | AJ9: =Gas!J11 -> 422.5 | AK9: =Gas!#REF! -> #REF! | AL9: =Gas!#REF! -> #REF! | AM9: =Gas!#REF! -> #REF! | AN9: =Gas!#REF! -> #REF! | AO9: =Gas!#REF! -> #REF! | AP9: =Gas!#REF! -> #REF! | AQ9: =Gas!#REF! -> #REF! | AR9: =Gas!#REF! -> #REF! | AS9: =Gas!#REF! -> #REF! | AT9: =Elect!BR10 -> 155 | AU9: =Elect!BP10 -> 107 | AX9: 49.840256 | AY9: 25.181598 | AZ9: 8299.2754 | BA9: 13.257628 | BB9: 6.698366 | BC9: =Elect!BQ10 -> 571293 | BD9: =Elect!#REF! -> #REF! | BE9: =Elect!#REF! -> #REF! | BF9: =Elect!#REF! -> #REF! | BG9: =Elect!#REF! -> #REF! | BH9: 1.1980831 | BI9: 0.60532688 | BJ9: 4506.2904 | BK9: 7.198547 | BL9: 3.6370383 | BM9: =Water!U11 -> 1.4349086 | BN9: =Water!W11 -> #DIV/0! | BO9: =Water!X11 -> 1360.2933 | BP9: =Water!Y11 -> 5.7396343 | BQ9: =Water!Z11 -> #DIV/0!
A10: 6 | B10: 33600 | C10: =Elect!J11 -> 7219 | D10: 0 | E10: =Elect!M11 -> 2636 | F10: 20 | G10: =Elect!O11 -> 2288 | H10: 805 | I10: =Water!C12 -> 83.133333 | J10: 0 | K10: =Water!E12 -> 116 | L10: 0 | M10: =Water!#REF! -> #REF! | N10: =Water!#REF! -> #REF! | O10: 1004 | P10: =Water!H12 -> 283.42667 | Q10: 115 | R10: =Water!O12 -> 0 | S10: 21 | T10: =Water!#REF! -> #REF! | U10: 141 | V10: =Water!#REF! -> #REF! | W10: 725 | X10: =Water!Q12 -> 164.38747 | Y10: 0 | Z10: =Water!#REF! -> #REF! | AA10: 0 | AB10: 0 | AC10: 510 | AD10: =Water!#REF! -> #REF! | AE10: =Water!#REF! -> #REF! | AF10: =Water!#REF! -> #REF! | AG10: =Gas!B12 -> 8510777 | AH10: =Gas!C12 -> 1341.2533 | AI10: =Gas!#REF! -> #REF! | AJ10: =Gas!J12 -> 228.8 | AK10: =Gas!#REF! -> #REF! | AL10: =Gas!#REF! -> #REF! | AM10: =Gas!#REF! -> #REF! | AN10: =Gas!#REF! -> #REF! | AO10: =Gas!#REF! -> #REF! | AP10: =Gas!#REF! -> #REF! | AQ10: =Gas!#REF! -> #REF! | AR10: =Gas!#REF! -> #REF! | AS10: =Gas!#REF! -> #REF! | AT10: =Elect!BR11 -> 156 | AU10: =Elect!BP11 -> 107 | AX10: 47.457627 | AY10: 23.512946 | AZ10: 8835.4834 | BA10: 12.479496 | BB10: 6.1829835 | BC10: =Elect!BQ11 -> 571449 | BD10: =Elect!#REF! -> #REF! | BE10: =Elect!#REF! -> #REF! | BF10: =Elect!#REF! -> #REF! | BG10: =Elect!#REF! -> #REF! | BH10: 1.1567797 | BI10: 0.57312806 | BJ10: 4597.6727 | BK10: 6.4938881 | BL10: 3.2174057 | BM10: =Water!U12 -> 1.4460544 | BN10: =Water!W12 -> #DIV/0! | BO10: =Water!X12 -> 1133.7067 | BP10: =Water!Y12 -> 5.7842177 | BQ10: =Water!Z12 -> #DIV/0!
A11: 7 | B11: 31200 | C11: =Elect!J12 -> 7366 | D11: 0 | E11: =Elect!M12 -> 2797 | F11: 20 | G11: =Elect!O12 -> 2288 | H11: 871 | I11: =Water!C13 -> 87 | J11: 0 | K11: =Water!E13 -> 98.6 | L11: 0 | M11: =Water!#REF! -> #REF! | N11: =Water!#REF! -> #REF! | O11: 837 | P11: =Water!H13 -> 296.96 | Q11: 113 | R11: =Water!O13 -> 0 | S11: 1 | T11: =Water!#REF! -> #REF! | U11: 151 | V11: =Water!#REF! -> #REF! | W11: 732 | X11: =Water!Q13 -> 172.2368 | Y11: 0 | Z11: =Water!#REF! -> #REF! | AA11: 0 | AB11: 0 | AC11: 1010 | AD11: =Water!#REF! -> #REF! | AE11: =Water!#REF! -> #REF! | AF11: =Water!#REF! -> #REF! | AG11: =Gas!B13 -> 8512163 | AH11: =Gas!C13 -> 1469.16 | AI11: =Gas!#REF! -> #REF! | AJ11: =Gas!J13 -> 319.8 | AK11: =Gas!#REF! -> #REF! | AL11: =Gas!#REF! -> #REF! | AM11: =Gas!#REF! -> #REF! | AN11: =Gas!#REF! -> #REF! | AO11: =Gas!#REF! -> #REF! | AP11: =Gas!#REF! -> #REF! | AQ11: =Gas!#REF! -> #REF! | AR11: =Gas!#REF! -> #REF! | AS11: =Gas!#REF! -> #REF! | AT11: =Elect!BR12 -> 165 | AU11: =Elect!BP12 -> 114 | AX11: 43.454039 | AY11: 21.517241 | AZ11: 8299.2754 | BA11: 11.558879 | BB11: 5.7236382 | BC11: =Elect!BQ12 -> 571614 | BD11: =Elect!#REF! -> #REF! | BE11: =Elect!#REF! -> #REF! | BF11: =Elect!#REF! -> #REF! | BG11: =Elect!#REF! -> #REF! | BH11: 1.1713092 | BI11: 0.58 | BJ11: 4974.6248 | BK11: 6.9284468 | BL11: 3.4307757 | BM11: =Water!U13 -> 1.8218405 | BN11: =Water!W13 -> #DIV/0! | BO11: =Water!X13 -> 1187.84 | BP11: =Water!Y13 -> 7.287362 | BQ11: =Water!Z13 -> #DIV/0!
A12: 8 | B12: 33600 | C12: =Elect!J13 -> 7366 | D12: 0 | E12: =Elect!M13 -> 2825 | F12: 20 | G12: =Elect!O13 -> 2288 | H12: 963 | I12: =Water!C14 -> 104.4 | J12: 0 | K12: =Water!E14 -> 121.8 | L12: 0 | M12: =Water!#REF! -> #REF! | N12: =Water!#REF! -> #REF! | O12: 1000 | P12: =Water!H14 -> 337.56 | Q12: 128 | R12: =Water!O14 -> 0 | S12: 24 | T12: =Water!#REF! -> #REF! | U12: 148 | V12: =Water!#REF! -> #REF! | W12: 719 | X12: =Water!Q14 -> 195.7848 | Y12: 0 | Z12: =Water!#REF! -> #REF! | AA12: 0 | AB12: 0 | AC12: 630 | AD12: =Water!#REF! -> #REF! | AE12: =Water!#REF! -> #REF! | AF12: =Water!#REF! -> #REF! | AG12: =Gas!B14 -> 8513647 | AH12: =Gas!C14 -> 1573.04 | AI12: =Gas!#REF! -> #REF! | AJ12: =Gas!J14 -> 366.6 | AK12: =Gas!#REF! -> #REF! | AL12: =Gas!#REF! -> #REF! | AM12: =Gas!#REF! -> #REF! | AN12: =Gas!#REF! -> #REF! | AO12: =Gas!#REF! -> #REF! | AP12: =Gas!#REF! -> #REF! | AQ12: =Gas!#REF! -> #REF! | AR12: =Gas!#REF! -> #REF! | AS12: =Gas!#REF! -> #REF! | AT12: =Elect!BR13 -> 164 | AU12: =Elect!BP13 -> 112 | AX12: 48.837209 | AY12: 24.086022 | AZ12: 8835.4834 | BA12: 12.842272 | BB12: 6.3336799 | BC12: =Elect!BQ13 -> 571778 | BD12: =Elect!#REF! -> #REF! | BE12: =Elect!#REF! -> #REF! | BF12: =Elect!#REF! -> #REF! | BG12: =Elect!#REF! -> #REF! | BH12: 1.2194767 | BI12: 0.60143369 | BJ12: 5500.0731 | BK12: 7.9942923 | BL12: 3.9427047 | BM12: =Water!U14 -> 2.2655034 | BN12: =Water!W14 -> #DIV/0! | BO12: =Water!X14 -> 1350.24 | BP12: =Water!Y14 -> 9.0620134 | BQ12: =Water!Z14 -> #DIV/0!
A13: 9 | B13: 33600 | C13: =Elect!J14 -> 7319 | D13: 0 | E13: =Elect!M14 -> 2796 | F13: 20 | G13: =Elect!O14 -> 2288 | H13: 790 | I13: =Water!C15 -> 87 | J13: 0 | K13: =Water!E15 -> 98.6 | L13: 0 | M13: =Water!#REF! -> #REF! | N13: =Water!#REF! -> #REF! | O13: 841 | P13: =Water!H15 -> 294.06 | Q13: 127 | R13: =Water!O15 -> 0 | S13: 21 | T13: =Water!#REF! -> #REF! | U13: 139 | V13: =Water!#REF! -> #REF! | W13: 701 | X13: =Water!Q15 -> 170.5548 | Y13: 0 | Z13: =Water!#REF! -> #REF! | AA13: 0 | AB13: 0 | AC13: 440 | AD13: =Water!#REF! -> #REF! | AE13: =Water!#REF! -> #REF! | AF13: =Water!#REF! -> #REF! | AG13: =Gas!B15 -> 8515031 | AH13: =Gas!C15 -> 1467.04 | AI13: =Gas!#REF! -> #REF! | AJ13: =Gas!J15 -> 319.8 | AK13: =Gas!#REF! -> #REF! | AL13: =Gas!#REF! -> #REF! | AM13: =Gas!#REF! -> #REF! | AN13: =Gas!#REF! -> #REF! | AO13: =Gas!#REF! -> #REF! | AP13: =Gas!#REF! -> #REF! | AQ13: =Gas!#REF! -> #REF! | AR13: =Gas!#REF! -> #REF! | AS13: =Gas!#REF! -> #REF! | AT13: =Elect!BR14 -> 120 | AU13: =Elect!BP14 -> 108 | AX13: 49.194729 | AY13: 24.1033 | AZ13: 8835.4834 | BA13: 12.936286 | BB13: 6.3382234 | BC13: =Elect!BQ14 -> 571898 | BD13: =Elect!#REF! -> #REF! | BE13: =Elect!#REF! -> #REF! | BF13: =Elect!#REF! -> #REF! | BG13: =Elect!#REF! -> #REF! | BH13: 1.1903367 | BI13: 0.58321377 | BJ13: 4512.0018 | BK13: 6.606152 | BL13: 3.2367301 | BM13: =Water!U15 -> 1.8151852 | BN13: =Water!W15 -> #DIV/0! | BO13: =Water!X15 -> 1176.24 | BP13: =Water!Y15 -> 7.2607407 | BQ13: =Water!Z15 -> #DIV/0!
A14: 10 | B14: 31200 | C14: =Elect!J15 -> 7532 | D14: 0 | E14: =Elect!M15 -> 2636 | F14: 20 | G14: =Elect!O15 -> 2288 | H14: 792 | I14: =Water!C16 -> 98.6 | J14: 0 | K14: =Water!E16 -> 116 | L14: 0 | M14: =Water!#REF! -> #REF! | N14: =Water!#REF! -> #REF! | O14: 972 | P14: =Water!H16 -> 326.54 | Q14: 126 | R14: =Water!O16 -> 0 | S14: 18 | T14: =Water!#REF! -> #REF! | U14: 145 | V14: =Water!#REF! -> #REF! | W14: 756 | X14: =Water!Q16 -> 189.3932 | Y14: 0 | Z14: =Water!#REF! -> #REF! | AA14: 0 | AB14: 0 | AC14: 580 | AD14: =Water!#REF! -> #REF! | AE14: =Water!#REF! -> #REF! | AF14: =Water!#REF! -> #REF! | AG14: =Gas!B16 -> 8516442 | AH14: =Gas!C16 -> 1495.66 | AI14: =Gas!#REF! -> #REF! | AJ14: =Gas!J16 -> 335.4 | AK14: =Gas!#REF! -> #REF! | AL14: =Gas!#REF! -> #REF! | AM14: =Gas!#REF! -> #REF! | AN14: =Gas!#REF! -> #REF! | AO14: =Gas!#REF! -> #REF! | AP14: =Gas!#REF! -> #REF! | AQ14: =Gas!#REF! -> #REF! | AR14: =Gas!#REF! -> #REF! | AS14: =Gas!#REF! -> #REF! | AT14: =Elect!BR15 -> 157 | AU14: =Elect!BP15 -> 113 | AX14: 49.52381 | AY14: 24.781573 | AZ14: 8299.2754 | BA14: 13.173453 | BB14: 6.5919582 | BC14: =Elect!BQ15 -> 572055 | BD14: =Elect!#REF! -> #REF! | BE14: =Elect!#REF! -> #REF! | BF14: =Elect!#REF! -> #REF! | BG14: =Elect!#REF! -> #REF! | BH14: 1.2730159 | BI14: 0.6370135 | BJ14: 4469.9646 | BK14: 7.0951819 | BL14: 3.5504087 | BM14: =Water!U16 -> 1.8553409 | BN14: =Water!W16 -> #DIV/0! | BO14: =Water!X16 -> 1306.16 | BP14: =Water!Y16 -> 7.4213636 | BQ14: =Water!Z16 -> #DIV/0!
A15: 11 | B15: 33600 | C15: =Elect!J16 -> 7099 | D15: 0 | E15: =Elect!M16 -> 2557 | F15: 20 | G15: =Elect!O16 -> 2288 | H15: 817 | I15: =Water!C17 -> 110.2 | J15: 0 | K15: =Water!E17 -> 121.8 | L15: 0 | M15: =Water!#REF! -> #REF! | N15: =Water!#REF! -> #REF! | O15: 875 | P15: =Water!H17 -> 345.68 | Q15: 122 | R15: =Water!O17 -> 0 | S15: 20 | T15: =Water!#REF! -> #REF! | U15: 156 | V15: =Water!#REF! -> #REF! | W15: 712 | X15: =Water!Q17 -> 200.4944 | Y15: 0 | Z15: =Water!#REF! -> #REF! | AA15: 0 | AB15: 0 | AC15: 850 | AD15: =Water!#REF! -> #REF! | AE15: =Water!#REF! -> #REF! | AF15: =Water!#REF! -> #REF! | AG15: =Gas!#REF! -> #REF! | AH15: =Gas!C17 -> 1844.4 | AI15: =Gas!#REF! -> #REF! | AJ15: =Gas!J17 -> 429 | AK15: =Gas!#REF! -> #REF! | AL15: =Gas!#REF! -> #REF! | AM15: =Gas!#REF! -> #REF! | AN15: =Gas!#REF! -> #REF! | AO15: =Gas!#REF! -> #REF! | AP15: =Gas!#REF! -> #REF! | AQ15: =Gas!#REF! -> #REF! | AR15: =Gas!#REF! -> #REF! | AS15: =Gas!#REF! -> #REF! | AT15: =Elect!BR16 -> 152 | AU15: =Elect!BP16 -> 109 | AX15: 53.333333 | AY15: 26.751592 | AZ15: 8835.4834 | BA15: 14.024577 | BB15: 7.0346206 | BC15: =Elect!BQ16 -> 572207 | BD15: =Elect!#REF! -> #REF! | BE15: =Elect!#REF! -> #REF! | BF15: =Elect!#REF! -> #REF! | BG15: =Elect!#REF! -> #REF! | BH15: 1.3460317 | BI15: 0.67515924 | BJ15: 4666.2095 | BK15: 7.4066817 | BL15: 3.7151349 | BM15: =Water!U17 -> 1.477265 | BN15: =Water!W17 -> #DIV/0! | BO15: =Water!X17 -> 1382.72 | BP15: =Water!Y17 -> 5.9090598 | BQ15: =Water!Z17 -> #DIV/0!
A16: 12 | B16: 33600 | C16: =Elect!J17 -> 9020 | D16: 0 | E16: =Elect!M17 -> 2508 | F16: 20 | G16: =Elect!O17 -> 2288 | H16: 907 | I16: =Water!C18 -> 104.4 | J16: 0 | K16: =Water!E18 -> 121.8 | L16: 0 | M16: =Water!#REF! -> #REF! | N16: =Water!#REF! -> #REF! | O16: 965 | P16: =Water!H18 -> 331.76 | Q16: 125 | R16: =Water!O18 -> 0 | S16: 4 | T16: =Water!#REF! -> #REF! | U16: 167 | V16: =Water!#REF! -> #REF! | W16: 705 | X16: =Water!Q18 -> 192.4208 | Y16: 0 | Z16: =Water!#REF! -> #REF! | AA16: 0 | AB16: 0 | AC16: 880 | AD16: =Water!#REF! -> #REF! | AE16: =Water!#REF! -> #REF! | AF16: =Water!#REF! -> #REF! | AG16: =Gas!B18 -> 8519915 | AH16: =Gas!C18 -> 1836.98 | AI16: =Gas!#REF! -> #REF! | AJ16: =Gas!J18 -> 421.2 | AK16: =Gas!#REF! -> #REF! | AL16: =Gas!#REF! -> #REF! | AM16: =Gas!#REF! -> #REF! | AN16: =Gas!#REF! -> #REF! | AO16: =Gas!#REF! -> #REF! | AP16: =Gas!#REF! -> #REF! | AQ16: =Gas!#REF! -> #REF! | AR16: =Gas!#REF! -> #REF! | AS16: =Gas!#REF! -> #REF! | AT16: =Elect!BR17 -> 168 | AU16: =Elect!BP17 -> 117 | AX16: 50.45045 | AY16: 25.339367 | AZ16: 8835.4834 | BA16: 13.266492 | BB16: 6.6632605 | BC16: =Elect!BQ17 -> 572375 | BD16: =Elect!#REF! -> #REF! | BE16: =Elect!#REF! -> #REF! | BF16: =Elect!#REF! -> #REF! | BG16: =Elect!#REF! -> #REF! | BH16: 1.2162162 | BI16: 0.61085973 | BJ16: 5180.235 | BK16: 7.7781306 | BL16: 3.9066629 | BM16: =Water!U18 -> 1.3823333 | BN16: =Water!W18 -> #DIV/0! | BO16: =Water!X18 -> 1327.04 | BP16: =Water!Y18 -> 5.5293333 | BQ16: =Water!Z18 -> #DIV/0!
A17: 13 | B17: 31200 | C17: =Elect!J18 -> 5557 | D17: 0 | E17: =Elect!M18 -> 2502 | F17: 20 | G17: =Elect!O18 -> 0 | H17: 812 | I17: =Water!C19 -> 104.4 | J17: 0 | K17: =Water!E19 -> 121.8 | L17: 0 | M17: =Water!#REF! -> #REF! | N17: =Water!#REF! -> #REF! | O17: 822 | P17: =Water!H19 -> 333.5 | Q17: 123 | R17: =Water!O19 -> 0 | S17: 7 | T17: =Water!#REF! -> #REF! | U17: 163 | V17: =Water!#REF! -> #REF! | W17: 692 | X17: =Water!Q19 -> 193.43 | Y17: 0 | Z17: =Water!#REF! -> #REF! | AA17: 0 | AB17: 0 | AC17: 460 | AD17: =Water!#REF! -> #REF! | AE17: =Water!#REF! -> #REF! | AF17: =Water!#REF! -> #REF! | AG17: =Gas!B19 -> 8521244 | AH17: =Gas!C19 -> 1408.74 | AI17: =Gas!#REF! -> #REF! | AJ17: =Gas!J19 -> 323.7 | AK17: =Gas!#REF! -> #REF! | AL17: =Gas!#REF! -> #REF! | AM17: =Gas!#REF! -> #REF! | AN17: =Gas!#REF! -> #REF! | AO17: =Gas!#REF! -> #REF! | AP17: =Gas!#REF! -> #REF! | AQ17: =Gas!#REF! -> #REF! | AR17: =Gas!#REF! -> #REF! | AS17: =Gas!#REF! -> #REF! | AT17: =Elect!BR18 -> 161 | AU17: =Elect!BP18 -> 108 | AX17: 46.567164 | AY17: 23.214286 | AZ17: 8299.2754 | BA17: 12.386978 | BB17: 6.1750561 | BC17: =Elect!BQ18 -> 572536 | BD17: =Elect!#REF! -> #REF! | BE17: =Elect!#REF! -> #REF! | BF17: =Elect!#REF! -> #REF! | BG17: =Elect!#REF! -> #REF! | BH17: 1.0850746 | BI17: 0.54092262 | BJ17: 4637.6525 | BK17: 6.9218694 | BL17: 3.4506343 | BM17: =Water!U19 -> 1.3556911 | BN17: =Water!W19 -> #DIV/0! | BO17: =Water!X19 -> 1334 | BP17: =Water!Y19 -> 5.4227642 | BQ17: =Water!Z19 -> #DIV/0!
A18: 14 | B18: 33600 | C18: =Elect!J19 -> 7744 | D18: 0 | E18: =Elect!M19 -> 2598 | F18: 30 | G18: =Elect!O19 -> 1728 | H18: 810 | I18: =Water!C20 -> 116 | J18: 0 | K18: =Water!E20 -> 133.4 | L18: 0 | M18: =Water!#REF! -> #REF! | N18: =Water!#REF! -> #REF! | O18: 943 | P18: =Water!H20 -> 357.28 | Q18: 118 | R18: =Water!O20 -> 0 | S18: 18 | T18: =Water!#REF! -> #REF! | U18: 152 | V18: =Water!#REF! -> #REF! | W18: 708 | X18: =Water!Q20 -> 207.2224 | Y18: 0 | Z18: =Water!#REF! -> #REF! | AA18: 0 | AB18: 0 | AC18: 490 | AD18: =Water!#REF! -> #REF! | AE18: =Water!#REF! -> #REF! | AF18: =Water!#REF! -> #REF! | AG18: =Gas!B20 -> 8522842 | AH18: =Gas!C20 -> 1693.88 | AI18: =Gas!#REF! -> #REF! | AJ18: =Gas!J20 -> 347.1 | AK18: =Gas!#REF! -> #REF! | AL18: =Gas!#REF! -> #REF! | AM18: =Gas!#REF! -> #REF! | AN18: =Gas!#REF! -> #REF! | AO18: =Gas!#REF! -> #REF! | AP18: =Gas!#REF! -> #REF! | AQ18: =Gas!#REF! -> #REF! | AR18: =Gas!#REF! -> #REF! | AS18: =Gas!#REF! -> #REF! | AT18: =Elect!BR19 -> 123 | AU18: =Elect!BP19 -> 105 | AX18: 47.795164 | AY18: 24.207493 | AZ18: 8835.4834 | BA18: 12.568255 | BB18: 6.3656221 | BC18: =Elect!BQ6 -> 570699 | BD18: =Elect!#REF! -> #REF! | BE18: =Elect!#REF! -> #REF! | BF18: =Elect!#REF! -> #REF! | BG18: =Elect!#REF! -> #REF! | BH18: 1.1024182 | BI18: 0.55835735 | BJ18: 4626.2297 | BK18: 6.5806966 | BL18: 3.3330185 | BM18: =Water!U20 -> 1.4177778 | BN18: =Water!W20 -> #DIV/0! | BO18: =Water!X20 -> 1429.12 | BP18: =Water!Y20 -> 5.6711111 | BQ18: =Water!Z20 -> #DIV/0!
A19: 15 | B19: 31200 | C19: =Elect!J20 -> 7113 | D19: 0 | E19: =Elect!M20 -> 2511 | F19: 20 | G19: =Elect!O20 -> 1653 | H19: 841 | I19: =Water!C21 -> 98.6 | J19: 0 | K19: =Water!E21 -> 110.2 | L19: 0 | M19: =Water!#REF! -> #REF! | N19: =Water!#REF! -> #REF! | O19: 947 | P19: =Water!H21 -> 318.42 | Q19: 131 | R19: =Water!O21 -> 0 | S19: 23 | T19: =Water!#REF! -> #REF! | U19: 166 | V19: =Water!#REF! -> #REF! | W19: 787 | X19: =Water!Q21 -> 184.6836 | Y19: 0 | Z19: =Water!#REF! -> #REF! | AA19: 0 | AB19: 0 | AC19: 730 | AD19: =Water!#REF! -> #REF! | AE19: =Water!#REF! -> #REF! | AF19: =Water!#REF! -> #REF! | AG19: =Gas!B21 -> 8524625 | AH19: =Gas!C21 -> 1889.98 | AI19: =Gas!#REF! -> #REF! | AJ19: =Gas!J21 -> 417.3 | AK19: =Gas!#REF! -> #REF! | AL19: =Gas!#REF! -> #REF! | AM19: =Gas!#REF! -> #REF! | AN19: =Gas!#REF! -> #REF! | AO19: =Gas!#REF! -> #REF! | AP19: =Gas!#REF! -> #REF! | AQ19: =Gas!#REF! -> #REF! | AR19: =Gas!#REF! -> #REF! | AS19: =Gas!#REF! -> #REF! | AT19: =Elect!BR20 -> 126 | AU19: =Elect!BP20 -> 111 | AX19: 41.6 | AY19: 20.995962 | AZ19: 8299.2754 | BA19: 11.065701 | BB19: 5.5849767 | BC19: =Elect!BQ20 -> 572785 | BD19: =Elect!#REF! -> #REF! | BE19: =Elect!#REF! -> #REF! | BF19: =Elect!#REF! -> #REF! | BG19: =Elect!#REF! -> #REF! | BH19: 1.1506667 | BI19: 0.58114478 | BJ19: 4803.283 | BK19: 6.4043773 | BL19: 3.234534 | BM19: =Water!U21 -> 1.6245918 | BN19: =Water!W21 -> #DIV/0! | BO19: =Water!X21 -> 1273.68 | BP19: =Water!Y21 -> 6.4983673 | BQ19: =Water!Z21 -> #DIV/0!
A20: 16 | B20: 36000 | C20: =Elect!J21 -> 7244 | D20: 0 | E20: =Elect!M21 -> 2560 | F20: 20 | G20: =Elect!O21 -> 1859 | H20: 932 | I20: =Water!C22 -> 104.4 | J20: 0 | K20: =Water!E22 -> 121.8 | L20: 0 | M20: =Water!#REF! -> #REF! | N20: =Water!#REF! -> #REF! | O20: 998 | P20: =Water!H22 -> 331.18 | Q20: 136 | R20: =Water!O22 -> 0 | S20: 22 | T20: =Water!#REF! -> #REF! | U20: 162 | V20: =Water!#REF! -> #REF! | W20: 703 | X20: =Water!Q22 -> 192.0844 | Y20: 0 | Z20: =Water!#REF! -> #REF! | AA20: 0 | AB20: 0 | AC20: 600 | AD20: =Water!#REF! -> #REF! | AE20: =Water!#REF! -> #REF! | AF20: =Water!#REF! -> #REF! | AG20: =Gas!B22 -> 8526117 | AH20: =Gas!C22 -> 1581.52 | AI20: =Gas!#REF! -> #REF! | AJ20: =Gas!J22 -> 343.2 | AK20: =Gas!#REF! -> #REF! | AL20: =Gas!#REF! -> #REF! | AM20: =Gas!#REF! -> #REF! | AN20: =Gas!#REF! -> #REF! | AO20: =Gas!#REF! -> #REF! | AP20: =Gas!#REF! -> #REF! | AQ20: =Gas!#REF! -> #REF! | AR20: =Gas!#REF! -> #REF! | AS20: =Gas!#REF! -> #REF! | AT20: =Elect!BR21 -> 224 | AU20: =Elect!BP21 -> 105 | AX20: 48 | AY20: 24.22611 | AZ20: 9371.6914 | BA20: 12.495589 | BB20: 6.3066564 | BC20: =Elect!BQ21 -> 573009 | BD20: =Elect!#REF! -> #REF! | BE20: =Elect!#REF! -> #REF! | BF20: =Elect!#REF! -> #REF! | BG20: =Elect!#REF! -> #REF! | BH20: 1.1626667 | BI20: 0.58720539 | BJ20: 5323.0199 | BK20: 7.0973598 | BL20: 3.5845252 | BM20: =Water!U22 -> 1.5122374 | BN20: =Water!W22 -> #DIV/0! | BO20: =Water!X22 -> 1324.72 | BP20: =Water!Y22 -> 6.0489498 | BQ20: =Water!Z22 -> #DIV/0!
A21: 17 | B21: 33600 | C21: =Elect!J22 -> 7009 | D21: 0 | E21: =Elect!M22 -> 2647 | F21: 20 | G21: =Elect!O22 -> 1912 | H21: 972 | I21: =Water!C23 -> 100.53333 | J21: 0 | K21: =Water!E23 -> 114.06667 | L21: 0 | M21: =Water!#REF! -> #REF! | N21: =Water!#REF! -> #REF! | O21: 998 | P21: =Water!H23 -> 322.67333 | Q21: 136 | R21: =Water!O23 -> 0 | S21: 38 | T21: =Water!#REF! -> #REF! | U21: 137 | V21: =Water!#REF! -> #REF! | W21: 740 | X21: =Water!Q23 -> 187.15053 | Y21: 0 | Z21: =Water!#REF! -> #REF! | AA21: 0 | AB21: 0 | AC21: 690 | AD21: =Water!#REF! -> #REF! | AE21: =Water!#REF! -> #REF! | AF21: =Water!#REF! -> #REF! | AG21: =Gas!B23 -> 8527609 | AH21: =Gas!C23 -> 1581.52 | AI21: =Gas!#REF! -> #REF! | AJ21: =Gas!J23 -> 392.6 | AK21: =Gas!#REF! -> #REF! | AL21: =Gas!#REF! -> #REF! | AM21: =Gas!#REF! -> #REF! | AN21: =Gas!#REF! -> #REF! | AO21: =Gas!#REF! -> #REF! | AP21: =Gas!#REF! -> #REF! | AQ21: =Gas!#REF! -> #REF! | AR21: =Gas!#REF! -> #REF! | AS21: =Gas!#REF! -> #REF! | AT21: =Elect!BR22 -> 26 | AU21: =Elect!BP22 -> 107 | AX21: 44.385733 | AY21: 22.207535 | AZ21: 8835.4834 | BA21: 11.671709 | BB21: 5.8397115 | BC21: =Elect!#REF! -> #REF! | BD21: =Elect!#REF! -> #REF! | BE21: =Elect!#REF! -> #REF! | BF21: =Elect!#REF! -> #REF! | BG21: =Elect!#REF! -> #REF! | BH21: 1.1770145 | BI21: 0.58889623 | BJ21: 5551.4757 | BK21: 7.3335213 | BL21: 3.6691842 | BM21: =Water!U23 -> 1.3444722 | BN21: =Water!W23 -> #DIV/0! | BO21: =Water!X23 -> 1290.6933 | BP21: =Water!Y23 -> 5.3778889 | BQ21: =Water!Z23 -> #DIV/0!
A22: 18 | B22: 33600 | C22: =Elect!J23 -> 6497 | D22: 0 | E22: =Elect!M23 -> 1903 | F22: 20 | G22: =Elect!O23 -> 1321 | H22: 864 | I22: =Water!C24 -> 27.066667 | J22: 0 | K22: =Water!E24 -> 100.53333 | L22: 0 | M22: =Water!#REF! -> #REF! | N22: =Water!#REF! -> #REF! | O22: 1002 | P22: =Water!H24 -> 320.54667 | Q22: 118 | R22: =Water!O24 -> 0 | S22: 21 | T22: =Water!#REF! -> #REF! | U22: 133 | V22: =Water!#REF! -> #REF! | W22: 769 | X22: =Water!Q24 -> 185.91707 | Y22: 0 | Z22: =Water!#REF! -> #REF! | AA22: 0 | AB22: 0 | AC22: 930 | AD22: =Water!#REF! -> #REF! | AE22: =Water!#REF! -> #REF! | AF22: =Water!#REF! -> #REF! | AG22: =Gas!B24 -> 8529312 | AH22: =Gas!C24 -> 1805.18 | AI22: =Gas!#REF! -> #REF! | AJ22: =Gas!J24 -> 243.1 | AK22: =Gas!#REF! -> #REF! | AL22: =Gas!#REF! -> #REF! | AM22: =Gas!#REF! -> #REF! | AN22: =Gas!#REF! -> #REF! | AO22: =Gas!#REF! -> #REF! | AP22: =Gas!#REF! -> #REF! | AQ22: =Gas!#REF! -> #REF! | AR22: =Gas!#REF! -> #REF! | AS22: =Gas!#REF! -> #REF! | AT22: =Elect!BR23 -> 141 | AU22: =Elect!BP23 -> 107 | AX22: 44.680851 | AY22: 22.459893 | AZ22: 8835.4834 | BA22: 11.749313 | BB22: 5.9060718 | BC22: =Elect!BQ23 -> 573176 | BD22: =Elect!#REF! -> #REF! | BE22: =Elect!#REF! -> #REF! | BF22: =Elect!#REF! -> #REF! | BG22: =Elect!#REF! -> #REF! | BH22: 1.1236702 | BI22: 0.56483957 | BJ22: 4934.645 | BK22: 6.562028 | BL22: 3.2985595 | BM22: =Water!U24 -> 1.2521354 | BN22: =Water!W24 -> #DIV/0! | BO22: =Water!X24 -> 1282.1867 | BP22: =Water!Y24 -> 5.0085417 | BQ22: =Water!Z24 -> #DIV/0!
A23: 19 | B23: 33600 | C23: =Elect!J24 -> 6654 | D23: 0 | E23: =Elect!M24 -> 2245 | F23: 30 | G23: =Elect!O24 -> 1662 | H23: 894 | I23: =Water!C25 -> 220.4 | J23: 0 | K23: =Water!E25 -> 174 | L23: 0 | M23: =Water!#REF! -> #REF! | N23: =Water!#REF! -> #REF! | O23: 944 | P23: =Water!H25 -> 435.58 | Q23: 110 | R23: =Water!O25 -> 0 | S23: 14 | T23: =Water!#REF! -> #REF! | U23: 155 | V23: =Water!#REF! -> #REF! | W23: 721 | X23: =Water!Q25 -> 252.6364 | Y23: 0 | Z23: =Water!#REF! -> #REF! | AA23: 0 | AB23: 0 | AC23: 660 | AD23: =Water!#REF! -> #REF! | AE23: =Water!#REF! -> #REF! | AF23: =Water!#REF! -> #REF! | AG23: =Gas!B25 -> 8531155 | AH23: =Gas!C25 -> 1953.58 | AI23: =Gas!#REF! -> #REF! | AJ23: =Gas!J25 -> 499.2 | AK23: =Gas!#REF! -> #REF! | AL23: =Gas!#REF! -> #REF! | AM23: =Gas!#REF! -> #REF! | AN23: =Gas!#REF! -> #REF! | AO23: =Gas!#REF! -> #REF! | AP23: =Gas!#REF! -> #REF! | AQ23: =Gas!#REF! -> #REF! | AR23: =Gas!#REF! -> #REF! | AS23: =Gas!#REF! -> #REF! | AT23: =Elect!BR24 -> 158 | AU23: =Elect!BP24 -> 96 | AX23: 44.8 | AY23: 22.44489 | AZ23: 8835.4834 | BA23: 11.780645 | BB23: 5.9021265 | BC23: =Elect!BQ24 -> 573334 | BD23: =Elect!#REF! -> #REF! | BE23: =Elect!#REF! -> #REF! | BF23: =Elect!#REF! -> #REF! | BG23: =Elect!#REF! -> #REF! | BH23: 1.1346667 | BI23: 0.56847027 | BJ23: 5105.9869 | BK23: 6.8079825 | BL23: 3.4108129 | BM23: =Water!U25 -> 1.7148819 | BN23: =Water!W25 -> #DIV/0! | BO23: =Water!X25 -> 1742.32 | BP23: =Water!Y25 -> 6.8595276 | BQ23: =Water!Z25 -> #DIV/0!
A24: 20 | B24: 33600 | C24: =Elect!J25 -> 6789 | D24: 0 | E24: =Elect!M25 -> 2549 | F24: 20 | G24: =Elect!O25 -> 1972 | H24: 944 | I24: =Water!C26 -> 127.6 | J24: 0 | K24: =Water!E26 -> 162.4 | L24: 0 | M24: =Water!#REF! -> #REF! | N24: =Water!#REF! -> #REF! | O24: 1000 | P24: =Water!H26 -> 417.02 | Q24: 138 | R24: =Water!O26 -> 0 | S24: 15 | T24: =Water!#REF! -> #REF! | U24: 165 | V24: =Water!#REF! -> #REF! | W24: 778 | X24: =Water!Q26 -> 241.8716 | Y24: 0 | Z24: =Water!#REF! -> #REF! | AA24: 0 | AB24: 0 | AC24: 560 | AD24: =Water!#REF! -> #REF! | AE24: =Water!#REF! -> #REF! | AF24: =Water!#REF! -> #REF! | AG24: =Gas!B26 -> 8532979 | AH24: =Gas!C26 -> 1933.44 | AI24: =Gas!#REF! -> #REF! | AJ24: =Gas!J26 -> 335.4 | AK24: =Gas!#REF! -> #REF! | AL24: =Gas!#REF! -> #REF! | AM24: =Gas!#REF! -> #REF! | AN24: =Gas!#REF! -> #REF! | AO24: =Gas!#REF! -> #REF! | AP24: =Gas!#REF! -> #REF! | AQ24: =Gas!#REF! -> #REF! | AR24: =Gas!#REF! -> #REF! | AS24: =Gas!#REF! -> #REF! | AT24: =Elect!BR25 -> 139 | AU24: =Elect!BP25 -> 89 | AX24: 42.857143 | AY24: 21.649485 | AZ24: 8835.4834 | BA24: 11.269749 | BB24: 5.6929661 | BC24: =Elect!BQ25 -> 573473 | BD24: =Elect!#REF! -> #REF! | BE24: =Elect!#REF! -> #REF! | BF24: =Elect!#REF! -> #REF! | BG24: =Elect!#REF! -> #REF! | BH24: 1.1683673 | BI24: 0.59020619 | BJ24: 5391.5566 | BK24: 6.8769855 | BL24: 3.4739411 | BM24: =Water!U26 -> 1.66808 | BN24: =Water!W26 -> #DIV/0! | BO24: =Water!X26 -> 1668.08 | BP24: =Water!Y26 -> 6.67232 | BQ24: =Water!Z26 -> #DIV/0!
A25: 21 | B25: 36000 | C25: =Elect!J26 -> 6877 | D25: 0 | E25: =Elect!M26 -> 1938 | F25: 20 | G25: =Elect!O26 -> 1636 | H25: 916 | I25: =Water!C27 -> 92.8 | J25: 0 | K25: =Water!E27 -> 110.2 | L25: 0 | M25: =Water!#REF! -> #REF! | N25: =Water!#REF! -> #REF! | O25: 998 | P25: =Water!H27 -> 292.32 | Q25: 186 | R25: =Water!O27 -> 0 | S25: 43 | T25: =Water!#REF! -> #REF! | U25: 176 | V25: =Water!#REF! -> #REF! | W25: 773 | X25: =Water!Q27 -> 169.5456 | Y25: 0 | Z25: =Water!#REF! -> #REF! | AA25: 0 | AB25: 0 | AC25: 950 | AD25: =Water!#REF! -> #REF! | AE25: =Water!#REF! -> #REF! | AF25: =Water!#REF! -> #REF! | AG25: =Gas!B27 -> 8534500 | AH25: =Gas!C27 -> 1612.26 | AI25: =Gas!#REF! -> #REF! | AJ25: =Gas!J27 -> 421.2 | AK25: =Gas!#REF! -> #REF! | AL25: =Gas!#REF! -> #REF! | AM25: =Gas!#REF! -> #REF! | AN25: =Gas!#REF! -> #REF! | AO25: =Gas!#REF! -> #REF! | AP25: =Gas!#REF! -> #REF! | AQ25: =Gas!#REF! -> #REF! | AR25: =Gas!#REF! -> #REF! | AS25: =Gas!#REF! -> #REF! | AT25: =Elect!BR26 -> 187 | AU25: =Elect!BP26 -> 135 | AX25: 43.956044 | AY25: 22.222222 | AZ25: 9371.6914 | BA25: 11.442847 | BB25: 5.7849947 | BC25: =Elect!BQ26 -> 573660 | BD25: =Elect!#REF! -> #REF! | BE25: =Elect!#REF! -> #REF! | BF25: =Elect!#REF! -> #REF! | BG25: =Elect!#REF! -> #REF! | BH25: 1.0586081 | BI25: 0.53518519 | BJ25: 5231.6376 | BK25: 6.3878358 | BL25: 3.2294059 | BM25: =Water!U27 -> 1.1739759 | BN25: =Water!W27 -> #DIV/0! | BO25: =Water!X27 -> 1169.28 | BP25: =Water!Y27 -> 4.6959036 | BQ25: =Water!Z27 -> #DIV/0!
A26: 22 | B26: 33600 | C26: =Elect!J27 -> 6326 | D26: 0 | E26: =Elect!M27 -> 2268 | F26: 20 | G26: =Elect!O27 -> 1780 | H26: 931 | I26: =Water!C28 -> 110.2 | J26: 0 | K26: =Water!E28 -> 121.8 | L26: 0 | M26: =Water!#REF! -> #REF! | N26: =Water!#REF! -> #REF! | O26: 969 | P26: =Water!H28 -> 341.62 | Q26: 151 | R26: =Water!O28 -> 0 | S26: 29 | T26: =Water!#REF! -> #REF! | U26: 157 | V26: =Water!#REF! -> #REF! | W26: 697 | X26: =Water!Q28 -> 198.1396 | Y26: 0 | Z26: =Water!#REF! -> #REF! | AA26: 0 | AB26: 0 | AC26: 700 | AD26: =Water!#REF! -> #REF! | AE26: =Water!#REF! -> #REF! | AF26: =Water!#REF! -> #REF! | AG26: =Gas!B28 -> 8536227 | AH26: =Gas!C28 -> 1830.62 | AI26: =Gas!#REF! -> #REF! | AJ26: =Gas!J28 -> 339.3 | AK26: =Gas!#REF! -> #REF! | AL26: =Gas!#REF! -> #REF! | AM26: =Gas!#REF! -> #REF! | AN26: =Gas!#REF! -> #REF! | AO26: =Gas!#REF! -> #REF! | AP26: =Gas!#REF! -> #REF! | AQ26: =Gas!#REF! -> #REF! | AR26: =Gas!#REF! -> #REF! | AS26: =Gas!#REF! -> #REF! | AT26: =Elect!BR27 -> 61 | AU26: =Elect!BP27 -> 88 | AX26: 39.952438 | AY26: 20.253165 | AZ26: 8835.4834 | BA26: 10.505926 | BB26: 5.3257887 | BC26: =Elect!BQ27 -> 573721 | BD26: =Elect!#REF! -> #REF! | BE26: =Elect!#REF! -> #REF! | BF26: =Elect!#REF! -> #REF! | BG26: =Elect!#REF! -> #REF! | BH26: 1.0903686 | BI26: 0.55274262 | BJ26: 5317.3085 | BK26: 6.3226022 | BL26: 3.2051287 | BM26: =Water!U28 -> 1.4234167 | BN26: =Water!W28 -> #DIV/0! | BO26: =Water!X28 -> 1366.48 | BP26: =Water!Y28 -> 5.6936667 | BQ26: =Water!Z28 -> #DIV/0!
A27: 23 | B27: 36000 | C27: =Elect!J28 -> 8051 | D27: 0 | E27: =Elect!M28 -> 2495 | F27: 30 | G27: =Elect!O28 -> 2181 | H27: 1009 | I27: =Water!C29 -> 58 | J27: 0 | K27: =Water!E29 -> 110.2 | L27: 0 | M27: =Water!#REF! -> #REF! | N27: =Water!#REF! -> #REF! | O27: 902 | P27: =Water!H29 -> 374.1 | Q27: 131 | R27: =Water!O29 -> 0 | S27: 6 | T27: =Water!#REF! -> #REF! | U27: 167 | V27: =Water!#REF! -> #REF! | W27: 748 | X27: =Water!Q29 -> 216.978 | Y27: 0 | Z27: =Water!#REF! -> #REF! | AA27: 0 | AB27: 0 | AC27: 690 | AD27: =Water!#REF! -> #REF! | AE27: =Water!#REF! -> #REF! | AF27: =Water!#REF! -> #REF! | AG27: =Gas!B29 -> 8538060 | AH27: =Gas!C29 -> 1942.98 | AI27: =Gas!#REF! -> #REF! | AJ27: =Gas!J29 -> 296.4 | AK27: =Gas!#REF! -> #REF! | AL27: =Gas!#REF! -> #REF! | AM27: =Gas!#REF! -> #REF! | AN27: =Gas!#REF! -> #REF! | AO27: =Gas!#REF! -> #REF! | AP27: =Gas!#REF! -> #REF! | AQ27: =Gas!#REF! -> #REF! | AR27: =Gas!#REF! -> #REF! | AS27: =Gas!#REF! -> #REF! | AT27: =Elect!BR28 -> 140 | AU27: =Elect!BP28 -> 115 | AX27: 42.755344 | AY27: 21.543986 | AZ27: 9371.6914 | BA27: 11.130275 | BB27: 5.6084329 | BC27: =Elect!BQ28 -> 573861 | BD27: =Elect!#REF! -> #REF! | BE27: =Elect!#REF! -> #REF! | BF27: =Elect!#REF! -> #REF! | BG27: =Elect!#REF! -> #REF! | BH27: 1.0712589 | BI27: 0.53979653 | BJ27: 5762.7973 | BK27: 6.8441773 | BL27: 3.4487117 | BM27: =Water!U29 -> 1.4728346 | BN27: =Water!W29 -> #DIV/0! | BO27: =Water!X29 -> 1496.4 | BP27: =Water!Y29 -> 5.8913386 | BQ27: =Water!Z29 -> #DIV/0!
A28: 24 | B28: 33600 | C28: =Elect!J29 -> 6521 | D28: 0 | E28: =Elect!M29 -> 1884 | F28: 20 | G28: =Elect!O29 -> 1779 | H28: 891 | I28: =Water!C30 -> 174 | J28: 0 | K28: =Water!E30 -> 203 | L28: 0 | M28: =Water!#REF! -> #REF! | N28: =Water!#REF! -> #REF! | O28: 818 | P28: =Water!H30 -> 377 | Q28: 221 | R28: =Water!O30 -> 0 | S28: 93 | T28: =Water!#REF! -> #REF! | U28: 191 | V28: =Water!#REF! -> #REF! | W28: 827 | X28: =Water!Q30 -> 218.66 | Y28: 0 | Z28: =Water!#REF! -> #REF! | AA28: 0 | AB28: 0 | AC28: 470 | AD28: =Water!#REF! -> #REF! | AE28: =Water!#REF! -> #REF! | AF28: =Water!#REF! -> #REF! | AG28: =Gas!B30 -> 8539055 | AH28: =Gas!C30 -> 1054.7 | AI28: =Gas!#REF! -> #REF! | AJ28: =Gas!J30 -> 312 | AK28: =Gas!#REF! -> #REF! | AL28: =Gas!#REF! -> #REF! | AM28: =Gas!#REF! -> #REF! | AN28: =Gas!#REF! -> #REF! | AO28: =Gas!#REF! -> #REF! | AP28: =Gas!#REF! -> #REF! | AQ28: =Gas!#REF! -> #REF! | AR28: =Gas!#REF! -> #REF! | AS28: =Gas!#REF! -> #REF! | AT28: =Elect!BR29 -> 123 | AU28: =Elect!BP29 -> 117 | AX28: 39.904988 | AY28: 20.289855 | AZ28: 8835.4834 | BA28: 10.493448 | BB28: 5.3354369 | BC28: =Elect!BQ29 -> 573984 | BD28: =Elect!#REF! -> #REF! | BE28: =Elect!#REF! -> #REF! | BF28: =Elect!#REF! -> #REF! | BG28: =Elect!#REF! -> #REF! | BH28: 1.1104513 | BI28: 0.56461353 | BJ28: 5088.8527 | BK28: 6.043768 | BL28: 3.0729787 | BM28: =Water!U30 -> 1.501992 | BN28: =Water!W30 -> #DIV/0! | BO28: =Water!X30 -> 1508 | BP28: =Water!Y30 -> 6.0079681 | BQ28: =Water!Z30 -> #DIV/0!
A29: 25 | B29: 33600 | C29: =Elect!J30 -> 6548 | D29: 0 | E29: =Elect!M30 -> 2184 | F29: 20 | G29: =Elect!O30 -> 1949 | H29: 1008 | I29: =Water!C31 -> 110.2 | J29: 0 | K29: =Water!E31 -> 87 | L29: 0 | M29: =Water!#REF! -> #REF! | N29: =Water!#REF! -> #REF! | O29: 1290 | P29: =Water!H31 -> 356.7 | Q29: 34 | R29: =Water!O31 -> 0 | S29: 34 | T29: =Water!#REF! -> #REF! | U29: 55 | V29: =Water!#REF! -> #REF! | W29: 681 | X29: =Water!Q31 -> 206.886 | Y29: 0 | Z29: =Water!#REF! -> #REF! | AA29: 0 | AB29: 0 | AC29: 1170 | AD29: =Water!#REF! -> #REF! | AE29: =Water!#REF! -> #REF! | AF29: =Water!#REF! -> #REF! | AG29: =Gas!B31 -> 8540512.7 | AH29: =Gas!C31 -> 1545.1267 | AI29: =Gas!#REF! -> #REF! | AJ29: =Gas!J31 -> 588.9 | AK29: =Gas!#REF! -> #REF! | AL29: =Gas!#REF! -> #REF! | AM29: =Gas!#REF! -> #REF! | AN29: =Gas!#REF! -> #REF! | AO29: =Gas!#REF! -> #REF! | AP29: =Gas!#REF! -> #REF! | AQ29: =Gas!#REF! -> #REF! | AR29: =Gas!#REF! -> #REF! | AS29: =Gas!#REF! -> #REF! | AT29: =Elect!BR30 -> 354 | AU29: =Elect!BP30 -> 116 | AX29: 39.763314 | AY29: 20.20445 | AZ29: 8835.4834 | BA29: 10.456193 | BB29: 5.3129786 | BC29: =Elect!BQ30 -> 574338 | BD29: =Elect!#REF! -> #REF! | BE29: =Elect!#REF! -> #REF! | BF29: =Elect!#REF! -> #REF! | BG29: =Elect!#REF! -> #REF! | BH29: 1.0059172 | BI29: 0.51112447 | BJ29: 5757.0859 | BK29: 6.8131194 | BL29: 3.4618676 | BM29: =Water!U31 -> 1.4154762 | BN29: =Water!W31 -> #DIV/0! | BO29: =Water!X31 -> 1426.8 | BP29: =Water!Y31 -> 5.6619048 | BQ29: =Water!Z31 -> #DIV/0!
A30: 26 | B30: 31200 | C30: =Elect!J31 -> 10603 | D30: 0 | E30: =Elect!M31 -> 2050 | F30: 20 | G30: =Elect!O31 -> 1787 | H30: 760 | I30: =Water!C32 -> 92.8 | J30: 0 | K30: =Water!E32 -> 110.2 | L30: 0 | M30: =Water!#REF! -> #REF! | N30: =Water!#REF! -> #REF! | O30: 1004 | P30: =Water!H32 -> 412.96 | Q30: 131 | R30: =Water!O32 -> 0 | S30: 33 | T30: =Water!#REF! -> #REF! | U30: 145 | V30: =Water!#REF! -> #REF! | W30: 916 | X30: =Water!Q32 -> 239.5168 | Y30: 0 | Z30: =Water!#REF! -> #REF! | AA30: 0 | AB30: 0 | AC30: 810 | AD30: =Water!#REF! -> #REF! | AE30: =Water!#REF! -> #REF! | AF30: =Water!#REF! -> #REF! | AG30: =Gas!B32 -> 8541950 | AH30: =Gas!C32 -> 1523.5733 | AI30: =Gas!#REF! -> #REF! | AJ30: =Gas!J32 -> 487.5 | AK30: =Gas!#REF! -> #REF! | AL30: =Gas!#REF! -> #REF! | AM30: =Gas!#REF! -> #REF! | AN30: =Gas!#REF! -> #REF! | AO30: =Gas!#REF! -> #REF! | AP30: =Gas!#REF! -> #REF! | AQ30: =Gas!#REF! -> #REF! | AR30: =Gas!#REF! -> #REF! | AS30: =Gas!#REF! -> #REF! | AT30: =Elect!BR31 -> 30 | AU30: =Elect!BP31 -> 113 | AX30: 37.275986 | AY30: 18.989653 | AZ30: 8299.2754 | BA30: 9.9155023 | BB30: 5.0512936 | BC30: =Elect!BQ31 -> 574368 | BD30: =Elect!#REF! -> #REF! | BE30: =Elect!#REF! -> #REF! | BF30: =Elect!#REF! -> #REF! | BG30: =Elect!#REF! -> #REF! | BH30: 1.1063321 | BI30: 0.56360316 | BJ30: 4340.66 | BK30: 5.1859737 | BL30: 2.6419111 | BM30: =Water!U32 -> 1.6387302 | BN30: =Water!W32 -> #DIV/0! | BO30: =Water!X32 -> 1651.84 | BP30: =Water!Y32 -> 6.5549206 | BQ30: =Water!Z32 -> #DIV/0!
A31: 27 | B31: 36000 | C31: =Elect!J32 -> 1127 | D31: 0 | E31: =Elect!M32 -> 1809 | F31: 30 | G31: =Elect!O32 -> 1918 | H31: 1010 | I31: =Water!C33 -> 98.6 | J31: 0 | K31: =Water!E33 -> 116 | L31: 0 | M31: =Water!#REF! -> #REF! | N31: =Water!#REF! -> #REF! | O31: 1014 | P31: =Water!H33 -> 214.6 | Q31: 151 | R31: =Water!O33 -> 0 | S31: 30 | T31: =Water!#REF! -> #REF! | U31: 139 | V31: =Water!#REF! -> #REF! | W31: 761 | X31: =Water!Q33 -> 124.468 | Y31: 0 | Z31: =Water!#REF! -> #REF! | AA31: 0 | AB31: 0 | AC31: 930 | AD31: =Water!#REF! -> #REF! | AE31: =Water!#REF! -> #REF! | AF31: =Water!#REF! -> #REF! | AG31: =Gas!B33 -> 8543200 | AH31: =Gas!C33 -> 1325 | AI31: =Gas!#REF! -> #REF! | AJ31: =Gas!J33 -> 249.6 | AK31: =Gas!#REF! -> #REF! | AL31: =Gas!#REF! -> #REF! | AM31: =Gas!#REF! -> #REF! | AN31: =Gas!#REF! -> #REF! | AO31: =Gas!#REF! -> #REF! | AP31: =Gas!#REF! -> #REF! | AQ31: =Gas!#REF! -> #REF! | AR31: =Gas!#REF! -> #REF! | AS31: =Gas!#REF! -> #REF! | AT31: =Elect!BR32 -> 50 | AU31: =Elect!BP32 -> 101 | AX31: 44.063647 | AY31: 22.346369 | AZ31: 9371.6914 | BA31: 11.470859 | BB31: 5.8173131 | BC31: =Elect!BQ32 -> 574418 | BD31: =Elect!#REF! -> #REF! | BE31: =Elect!#REF! -> #REF! | BF31: =Elect!#REF! -> #REF! | BG31: =Elect!#REF! -> #REF! | BH31: 1.1640147 | BI31: 0.59031657 | BJ31: 5768.5087 | BK31: 7.0605981 | BL31: 3.5807006 | BM31: =Water!U33 -> 0.90932203 | BN31: =Water!W33 -> #DIV/0! | BO31: =Water!X33 -> 858.4 | BP31: =Water!Y33 -> 3.6372881 | BQ31: =Water!Z33 -> #DIV/0!
A32: 28 | B32: 33600 | C32: =Elect!J33 -> 7444.3333 | D32: 0 | E32: =Elect!M33 -> 1969.6667 | F32: 20 | G32: =Elect!O33 -> 1830.6667 | H32: 1008 | I32: =Water!C34 -> 104.4 | J32: 0 | K32: =Water!E34 -> 121.8 | L32: 1 | M32: =Water!#REF! -> #REF! | N32: =Water!#REF! -> #REF! | O32: 1013 | P32: =Water!H34 -> 335.82 | Q32: 142 | R32: =Water!O34 -> 0 | S32: 13 | T32: =Water!#REF! -> #REF! | U32: 155 | V32: =Water!#REF! -> #REF! | W32: 825 | X32: =Water!Q34 -> 194.7756 | Y32: 1 | Z32: =Water!#REF! -> #REF! | AA32: 0 | AB32: 0 | AC32: 650 | AD32: =Water!#REF! -> #REF! | AE32: =Water!#REF! -> #REF! | AF32: =Water!#REF! -> #REF! | AG32: =Gas!B34 -> 8544731 | AH32: =Gas!C34 -> 1622.86 | AI32: =Gas!#REF! -> #REF! | AJ32: =Gas!J34 -> 347.1 | AK32: =Gas!#REF! -> #REF! | AL32: =Gas!#REF! -> #REF! | AM32: =Gas!#REF! -> #REF! | AN32: =Gas!#REF! -> #REF! | AO32: =Gas!#REF! -> #REF! | AP32: =Gas!#REF! -> #REF! | AQ32: =Gas!#REF! -> #REF! | AR32: =Gas!#REF! -> #REF! | AS32: =Gas!#REF! -> #REF! | AT32: =Elect!BR33 -> 36.666667 | AU32: =Elect!BP33 -> 109 | AX32: 45.34413 | AY32: 22.687373 | AZ32: 8835.4834 | BA32: 11.923729 | BB32: 5.9658902 | BC32: =Elect!BQ33 -> 574454.67 | BD32: =Elect!#REF! -> #REF! | BE32: =Elect!#REF! -> #REF! | BF32: =Elect!#REF! -> #REF! | BG32: =Elect!#REF! -> #REF! | BH32: 1.2294197 | BI32: 0.61512492 | BJ32: 5757.0859 | BK32: 7.7693467 | BL32: 3.8872963 | BM32: =Water!U34 -> 1.4558671 | BN32: =Water!W34 -> #DIV/0! | BO32: =Water!X34 -> 1343.28 | BP32: =Water!Y34 -> 5.8234682 | BQ32: =Water!Z34 -> #DIV/0!
A33: MTD | B33: 931200 | C33: =Elect!J34 -> 0 | D33: 0 | E33: =Elect!M34 -> 0 | F33: 600 | G33: =Elect!O34 -> 0 | H33: 24543 | I33: =Water!C38 -> 2859.4 | J33: 0 | K33: =Water!E39 -> 109.62 | L33: 3 | M33: =Water!#REF! -> #REF! | N33: =Water!#REF! -> #REF! | O33: 1013 | P33: =Water!H38 -> 9246.36 | Q33: 109 | R33: =Water!O38 -> 0 | S33: 15 | T33: =Water!#REF! -> #REF! | U33: 147 | V33: =Water!#REF! -> #REF! | W33: 730 | X33: =Water!Q38 -> 5362.8888 | Y33: 3 | Z33: =Water!#REF! -> #REF! | AA33: 0 | AB33: 0 | AC33: 0 | AD33: =Water!#REF! -> #REF! | AE33: =Water!#REF! -> #REF! | AF33: =Water!#REF! -> #REF! | AG33: =Gas!B38 -> 0 | AH33: =Gas!C38 -> 44687.48 | AI33: =Gas!#REF! -> #REF! | AJ33: =Gas!J38 -> 10401.3 | AK33: =Gas!#REF! -> #REF! | AL33: =Gas!#REF! -> #REF! | AM33: =Gas!#REF! -> #REF! | AN33: =Gas!#REF! -> #REF! | AO33: =Gas!#REF! -> #REF! | AP33: =Gas!#REF! -> #REF! | AQ33: =Gas!#REF! -> #REF! | AR33: =Gas!#REF! -> #REF! | AS33: =Gas!#REF! -> #REF! | AT33: =Elect!BR34 -> 0 | AU33: =Elect!BP34 -> 0 | AX33: 45.411099 | AY33: 22.844806 | AZ33: 245248.7 | BA33: 11.959851 | BB33: 6.0166013 | BC33: =Elect!BQ34 -> 574454.67 | BD33: =Elect!#REF! -> #REF! | BE33: =Elect!#REF! -> #REF! | BF33: =Elect!#REF! -> #REF! | BG33: =Elect!#REF! -> #REF! | BH33: 1.1514679 | BI33: 0.57929342 | BJ33: 140121.3 | BK33: 6.8331854 | BL33: 3.4377159 | BM33: =Water!U38 -> 1.5344958 | BN33: =Water!W38 -> #DIV/0! | BO33: =Water!X38 -> 36985.44 | BP33: =Water!Y38 -> 6.1379831 | BQ33: =Water!Z38 -> #DIV/0!
A34: AVER. Act | B34: 33257.143 | C34: =Elect!J35 -> 0 | D34: 0 | E34: =Elect!M35 -> 0 | F34: 21.428571 | G34: =Elect!O35 -> 0 | H34: 876.53571 | I34: =Water!C39 -> 95.313333 | J34: 0 | K34: =Water!E40 -> 0 | L34: 4 | M34: =Water!#REF! -> #REF! | N34: =Water!#REF! -> #REF! | O34: 1014 | P34: =Water!H39 -> 308.212 | Q34: 138 | R34: =Water!O39 -> 0 | S34: 24 | T34: =Water!#REF! -> #REF! | U34: 145 | V34: =Water!#REF! -> #REF! | W34: 877 | X34: =Water!Q39 -> 178.76296 | Y34: 4 | Z34: =Water!#REF! -> #REF! | AA34: 0 | AB34: 0 | AC34: 0 | AD34: =Water!#REF! -> #REF! | AE34: =Water!#REF! -> #REF! | AF34: =Water!#REF! -> #REF! | AG34: =Gas!B39 -> 0 | AH34: =Gas!C39 -> 1489.5827 | AI34: =Gas!#REF! -> #REF! | AJ34: =Gas!J39 -> 346.71 | AK34: =Gas!#REF! -> #REF! | AL34: =Gas!#REF! -> #REF! | AM34: =Gas!#REF! -> #REF! | AN34: =Gas!#REF! -> #REF! | AO34: =Gas!#REF! -> #REF! | AP34: =Gas!#REF! -> #REF! | AQ34: =Gas!#REF! -> #REF! | AR34: =Gas!#REF! -> #REF! | AS34: =Gas!#REF! -> #REF! | AT34: =Elect!BR35 -> 0 | AU34: =Elect!BP35 -> 0 | AX34: 45.411099 | AY34: 22.844806 | AZ34: 8758.8823 | BA34: 11.959851 | BB34: 6.0166013 | BC34: =Elect!BQ35 -> 574454.67 | BD34: =Elect!#REF! -> #REF! | BE34: =Elect!#REF! -> #REF! | BF34: =Elect!#REF! -> #REF! | BG34: =Elect!#REF! -> #REF! | BH34: 1.1761372 | BI34: 0.60007377 | BJ34: 5004.3322 | BK34: 6.8331854 | BL34: 3.4377159 | BM34: =Water!U39 -> 1.5344958 | BN34: =Water!W39 -> #DIV/0! | BO34: =Water!X39 -> 1232.848 | BP34: =Water!Y39 -> 6.1379831 | BQ34: =Water!Z39 -> #DIV/0!
A35: TOTAL Budget | B35: 1040026 | C35: =Elect!J5 -> 0 | D35: 0 | E35: =Elect!M5 -> 0 | F35: 0 | G35: =Elect!O5 -> 0 | H35: 0 | I35: =Water!C40 -> 0 | J35: 0 | K35: =Water!E41 -> 0 | L35: 5 | M35: =Water!#REF! -> #REF! | N35: =Water!#REF! -> #REF! | O35: 1010 | P35: =Water!H40 -> 0 | Q35: 148 | R35: =Water!O40 -> 0 | S35: 22 | T35: =Water!#REF! -> #REF! | U35: 151 | V35: =Water!#REF! -> #REF! | W35: 833 | X35: =Water!Q40 -> 0 | Y35: 5 | Z35: =Water!#REF! -> #REF! | AA35: 0 | AB35: 0 | AC35: 0 | AD35: =Water!#REF! -> #REF! | AE35: =Water!#REF! -> #REF! | AF35: =Water!#REF! -> #REF! | AG35: =Gas!#REF! -> #REF! | AH35: =Gas!#REF! -> #REF! | AI35: =Gas!#REF! -> #REF! | AJ35: =Gas!#REF! -> #REF! | AK35: =Gas!#REF! -> #REF! | AL35: =Gas!#REF! -> #REF! | AM35: =Gas!#REF! -> #REF! | AN35: =Gas!#REF! -> #REF! | ... AS35: =Gas!#REF! -> #REF! | AT35: =Elect!BR5 -> 0 | AU35: =Elect!BP5 -> 0 | AX35: 45.679286 | AY35: 23.305904 | AZ35: 264708.4 | BA35: 11.626335 | BB35: 5.9318409 | BC35: =Elect!BQ5 -> 570578 | BD35: =Elect!#REF! -> #REF! | BE35: =Elect!#REF! -> #REF! | BF35: =Elect!#REF! -> #REF! | BG35: =Elect!#REF! -> #REF! | BH35: 1.1761372 | BI35: 0.60007377 | BJ35: 150494 | BK35: 6.6098911 | BL35: 3.3724146 | BM35: =Water!U40 -> #REF! | BN35: =Water!W40 -> #REF! | BO35: =Water!X40 -> 0 | BP35: =Water!Y40 -> 0 | BQ35: =Water!Z40 -> 0
A36: Budget MTD | B36: 1040026 | C36: =Elect!#REF! -> #REF! | D36: 0 | E36: =Elect!#REF! -> #REF! | F36: 0 | G36: =Elect!#REF! -> #REF! | H36: 0 | I36: =Water!C41 -> 0 | J36: 0 | K36: =Water!E42 -> 0 | L36: 6 | M36: =Water!#REF! -> #REF! | N36: =Water!#REF! -> #REF! | O36: 30039 | P36: =Water!H41 -> 0 | Q36: 129.54839 | R36: =Water!O41 -> 0 | S36: 719 | T36: =Water!#REF! -> #REF! | U36: 4609 | V36: =Water!#REF! -> #REF! | W36: 23430 | X36: =Water!Q41 -> 0 | Y36: 6 | Z36: =Water!#REF! -> #REF! | AA36: 0 | AB36: 0 | AC36: 0 | AD36: =Water!#REF! -> #REF! | AE36: =Water!#REF! -> #REF! | AF36: =Water!#REF! -> #REF! | AG36: =Gas!#REF! -> #REF! | AH36: =Gas!#REF! -> #REF! | AI36: =Gas!#REF! -> #REF! | AJ36: =Gas!#REF! -> #REF! | AK36: =Gas!#REF! -> #REF! | AL36: =Gas!#REF! -> #REF! | AM36: =Gas!#REF! -> #REF! | AN36: =Gas!#REF! -> #REF! | ... AS36: =Gas!#REF! -> #REF! | AT36: =Elect!#REF! -> #REF! | AU36: =Elect!#REF! -> #REF! | AX36: 45.679286 | AY36: 23.305904 | AZ36: 264708.4 | BA36: 11.626335 | BB36: 5.9318409 | BC36: =Elect!#REF! -> #REF! | BD36: =Elect!#REF! -> #REF! | BE36: =Elect!#REF! -> #REF! | BF36: =Elect!#REF! -> #REF! | BG36: =Elect!#REF! -> #REF! | BH36: 0 | BI36: 0 | BJ36: 135930.06 | BK36: 6.6098911 | BL36: 3.3724146 | BM36: =Water!U41 -> #REF! | BN36: =Water!W41 -> #REF! | BO36: =Water!X41 -> #REF! | BP36: =Water!Y41 -> #REF! | BQ36: =Water!Z41 -> #REF!
A37: AVER. Bud | B37: 37143.785 | C37: =Elect!#REF! -> #REF! | D37: 0 | E37: =Elect!#REF! -> #REF! | F37: 0 | G37: =Elect!#REF! -> #REF! | H37: 0 | I37: =Water!C42 -> 0 | J37: 0 | K37: =Water!E43 -> 0 | L37: 7 | M37: =Water!#REF! -> #REF! | N37: =Water!#REF! -> #REF! | O37: 969 | P37: =Water!H42 -> 0 | Q37: 0 | R37: =Water!O42 -> 0 | S37: 23.193548 | T37: =Water!#REF! -> #REF! | U37: 148.67742 | V37: =Water!#REF! -> #REF! | W37: 755.80645 | X37: =Water!Q42 -> 0 | Y37: 7 | Z37: =Water!#REF! -> #REF! | AA37: 0 | AB37: 0 | AC37: 0 | AD37: =Water!#REF! -> #REF! | AE37: =Water!#REF! -> #REF! | AF37: =Water!#REF! -> #REF! | AG37: =Gas!#REF! -> #REF! | AH37: =Gas!#REF! -> #REF! | AI37: =Gas!#REF! -> #REF! | AJ37: =Gas!#REF! -> #REF! | AK37: =Gas!#REF! -> #REF! | AL37: =Gas!#REF! -> #REF! | AM37: =Gas!#REF! -> #REF! | AN37: =Gas!#REF! -> #REF! | ... AS37: =Gas!#REF! -> #REF! | AT37: =Elect!#REF! -> #REF! | AU37: =Elect!#REF! -> #REF! | AX37: 0 | AY37: 0 | AZ37: 9453.8714 | BA37: 0 | BB37: 0 | BC37: =Elect!#REF! -> #REF! | BD37: =Elect!#REF! -> #REF! | BE37: =Elect!#REF! -> #REF! | BF37: =Elect!#REF! -> #REF! | BG37: =Elect!#REF! -> #REF! | BH37: 0 | BI37: 0 | BJ37: 0 | BK37: 0 | BL37: 0 | BM37: =Water!U42 -> 0 | BN37: =Water!W42 -> 0 | BO37: =Water!X42 -> 0 | BP37: =Water!Y42 -> 0 | BQ37: =Water!Z42 -> 0
A38: Total RFC | B38: 784008.53 | C38: =Elect!#REF! -> #REF! | D38: 0 | E38: =Elect!#REF! -> #REF! | F38: 0 | G38: =Elect!#REF! -> #REF! | H38: 0 | I38: =Water!C43 -> 0 | J38: 0 | K38: =Water!E44 -> 0 | L38: 8 | M38: =Water!#REF! -> #REF! | N38: =Water!#REF! -> #REF! | O38: 0 | P38: =Water!H43 -> 0 | Q38: 0 | R38: =Water!O43 -> 0 | S38: 0 | T38: =Water!#REF! -> #REF! | U38: 0 | V38: =Water!#REF! -> #REF! | W38: 0 | X38: =Water!Q43 -> 0 | Y38: 8 | Z38: =Water!#REF! -> #REF! | AA38: 0 | AB38: 0 | AC38: 0 | AD38: =Water!#REF! -> #REF! | AE38: =Water!#REF! -> #REF! | AF38: =Water!#REF! -> #REF! | AG38: =Gas!#REF! -> #REF! | AH38: =Gas!#REF! -> #REF! | AI38: =Gas!#REF! -> #REF! | AJ38: =Gas!#REF! -> #REF! | AK38: =Gas!#REF! -> #REF! | AL38: =Gas!#REF! -> #REF! | AM38: =Gas!#REF! -> #REF! | AN38: =Gas!#REF! -> #REF! | ... AS38: =Gas!#REF! -> #REF! | AT38: =Elect!#REF! -> #REF! | AU38: =Elect!#REF! -> #REF! | AX38: 38.173558 | AY38: 19.219193 | AZ38: 208225.85 | BA38: 10.138565 | BB38: 5.1044505 | BC38: =Elect!#REF! -> #REF! | BD38: =Elect!#REF! -> #REF! | BE38: =Elect!#REF! -> #REF! | BF38: =Elect!#REF! -> #REF! | BG38: =Elect!#REF! -> #REF! | BH38: 0 | BI38: 0 | BJ38: 127385.62 | BK38: 6.2024355 | BL38: 3.1227323 | BM38: =Water!U43 -> 0 | BN38: =Water!W43 -> 0 | BO38: =Water!X43 -> 0 | BP38: =Water!Y43 -> 0 | BQ38: =Water!Z43 -> 0
A39: RFC MTD | B39: 784008.53 | C39: =Elect!#REF! -> #REF! | D39: 0 | E39: =Elect!#REF! -> #REF! | F39: 0 | G39: =Elect!#REF! -> #REF! | H39: 0 | I39: =Water!C44 -> 0 | J39: 0 | K39: =Water!E45 -> 0 | L39: 9 | M39: =Water!#REF! -> #REF! | N39: =Water!#REF! -> #REF! | O39: 0 | P39: =Water!H44 -> 0 | Q39: 0 | R39: =Water!O44 -> 0 | S39: 0 | T39: =Water!#REF! -> #REF! | U39: 0 | V39: =Water!#REF! -> #REF! | W39: 0 | X39: =Water!Q44 -> 0 | Y39: 9 | Z39: =Water!#REF! -> #REF! | AA39: 0 | AB39: 0 | AC39: 0 | AD39: =Water!#REF! -> #REF! | AE39: =Water!#REF! -> #REF! | AF39: =Water!#REF! -> #REF! | AG39: =Gas!#REF! -> #REF! | AH39: =Gas!#REF! -> #REF! | AI39: =Gas!#REF! -> #REF! | AJ39: =Gas!#REF! -> #REF! | AK39: =Gas!#REF! -> #REF! | AL39: =Gas!#REF! -> #REF! | AM39: =Gas!#REF! -> #REF! | AN39: =Gas!#REF! -> #REF! | ... AS39: =Gas!#REF! -> #REF! | AT39: =Elect!#REF! -> #REF! | AU39: =Elect!#REF! -> #REF! | AX39: 38.173558 | AY39: 19.219193 | AZ39: 208225.85 | BA39: 10.138565 | BB39: 5.1044505 | BC39: =Elect!#REF! -> #REF! | BD39: =Elect!#REF! -> #REF! | BE39: =Elect!#REF! -> #REF! | BF39: =Elect!#REF! -> #REF! | BG39: =Elect!#REF! -> #REF! | BH39: 0 | BI39: 0 | BJ39: 115057.98 | BK39: 6.2024355 | BL39: 3.1227323 | BM39: =Water!U44 -> 0 | BN39: =Water!W44 -> 0 | BO39: =Water!X44 -> #VALUE! | BP39: =Water!Y44 -> #VALUE! | BQ39: =Water!Z44 -> #VALUE!
A40: AVER RFC | B40: 28000.305 | C40: =Elect!#REF! -> #REF! | D40: 0 | E40: =Elect!#REF! -> #REF! | F40: 0 | G40: =Elect!#REF! -> #REF! | H40: 0 | I40: =Water!C45 -> 0 | J40: 0 | K40: =Water!E46 -> 0 | L40: 10 | M40: =Water!#REF! -> #REF! | N40: =Water!#REF! -> #REF! | O40: 0 | P40: =Water!H45 -> 0 | Q40: 0 | R40: =Water!O45 -> 0 | S40: 0 | T40: =Water!#REF! -> #REF! | U40: 0 | V40: =Water!#REF! -> #REF! | W40: 0 | X40: =Water!Q45 -> 0 | Y40: 10 | Z40: =Water!#REF! -> #REF! | AA40: 0 | AB40: 0 | AC40: 0 | AD40: =Water!#REF! -> #REF! | AE40: =Water!#REF! -> #REF! | AF40: =Water!#REF! -> #REF! | AG40: =Gas!#REF! -> #REF! | AH40: =Gas!#REF! -> #REF! | AI40: =Gas!#REF! -> #REF! | AJ40: =Gas!#REF! -> #REF! | AK40: =Gas!#REF! -> #REF! | AL40: =Gas!#REF! -> #REF! | AM40: =Gas!#REF! -> #REF! | AN40: =Gas!#REF! -> #REF! | ... AS40: =Gas!#REF! -> #REF! | AT40: =Elect!#REF! -> #REF! | AU40: =Elect!#REF! -> #REF! | AX40: 0 | AY40: 0 | AZ40: 7436.6375 | BA40: 0 | BB40: 0 | BC40: =Elect!#REF! -> #REF! | BD40: =Elect!#REF! -> #REF! | BE40: =Elect!#REF! -> #REF! | BF40: =Elect!#REF! -> #REF! | BG40: =Elect!#REF! -> #REF! | BH40: 1.1254646 | BI40: 0.57264868 | BJ40: 4109.2135 | BK40: 0 | BL40: 0 | BM40: =Water!U45 -> 0 | BN40: =Water!W45 -> 0 | BO40: =Water!X45 -> #VALUE! | BP40: =Water!Y45 -> 0 | BQ40: =Water!Z45 -> 0

Sheet Temp.
A2: HILTON INTERNATIONAL
A3: GULF, MIDDLE EAST AND ASIA SPECIFIC
A4: HOTEL:HILTON HURGHADA LONG BEACH RESORT | G4: =Elect!A1 -> 44958
A7: DATE | B7: MAX TEMP | C7: MIN TEMP | D7: MAX TEMP | E7: MIN TEMP | F7: DAY | G7: DD. C | H7: DD. H | I7: MTD | J7: MTD
B8: C | C8: C | D8: F | E8: F | F8: PARAMETER | I8: COOLING | J8: HEATING
A10: 1 | D10: =SUM((B10*9/5)+32) -> 32 | E10: =SUM((C10*9/5)+32) -> 32 | F10: =SUM(((B10+C10)/2)-18.33) -> -18.33 | G10: =SUM(0+(F10)+ABS(F10))/2 -> 0 | H10: =IF((SUM(0-(F10)+ABS(F10))/2)<18,SUM(0-(F10)+ABS(F10))/2,0) -> 0 | I10: =SUM(G10:G10) -> 0 | J10: =SUM(H10:H10) -> 0
A11: 2 | D11: =SUM((B11*9/5)+32) -> 32 | E11: =SUM((C11*9/5)+32) -> 32 | F11: =SUM(((B11+C11)/2)-18.33) -> -18.33 | G11: =SUM(0+(F11)+ABS(F11))/2 -> 0 | H11: =IF((SUM(0-(F11)+ABS(F11))/2)<18,SUM(0-(F11)+ABS(F11))/2,0) -> 0 | I11: =SUM(G10:G11) -> 0 | J11: =SUM(H10:H11) -> 0
A12: 3 | D12: =SUM((B12*9/5)+32) -> 32 | E12: =SUM((C12*9/5)+32) -> 32 | F12: =SUM(((B12+C12)/2)-18.33) -> -18.33 | G12: =SUM(0+(F12)+ABS(F12))/2 -> 0 | H12: =IF((SUM(0-(F12)+ABS(F12))/2)<18,SUM(0-(F12)+ABS(F12))/2,0) -> 0 | I12: =SUM(G10:G12) -> 0 | J12: =SUM(H10:H12) -> 0
A13: 4 | D13: =SUM((B13*9/5)+32) -> 32 | E13: =SUM((C13*9/5)+32) -> 32 | F13: =SUM(((B13+C13)/2)-18.33) -> -18.33 | G13: =SUM(0+(F13)+ABS(F13))/2 -> 0 | H13: =IF((SUM(0-(F13)+ABS(F13))/2)<18,SUM(0-(F13)+ABS(F13))/2,0) -> 0 | I13: =SUM(G10:G13) -> 0 | J13: =SUM(H10:H13) -> 0
A14: 5 | D14: =SUM((B14*9/5)+32) -> 32 | E14: =SUM((C14*9/5)+32) -> 32 | F14: =SUM(((B14+C14)/2)-18.33) -> -18.33 | G14: =SUM(0+(F14)+ABS(F14))/2 -> 0 | H14: =IF((SUM(0-(F14)+ABS(F14))/2)<18,SUM(0-(F14)+ABS(F14))/2,0) -> 0 | I14: =SUM(G10:G14) -> 0 | J14: =SUM(H10:H14) -> 0
A15: 6 | D15: =SUM((B15*9/5)+32) -> 32 | E15: =SUM((C15*9/5)+32) -> 32 | F15: =SUM(((B15+C15)/2)-18.33) -> -18.33 | G15: =SUM(0+(F15)+ABS(F15))/2 -> 0 | H15: =IF((SUM(0-(F15)+ABS(F15))/2)<18,SUM(0-(F15)+ABS(F15))/2,0) -> 0 | I15: =SUM(G10:G15) -> 0 | J15: =SUM(H10:H15) -> 0
A16: 7 | D16: =SUM((B16*9/5)+32) -> 32 | E16: =SUM((C16*9/5)+32) -> 32 | F16: =SUM(((B16+C16)/2)-18.33) -> -18.33 | G16: =SUM(0+(F16)+ABS(F16))/2 -> 0 | H16: =IF((SUM(0-(F16)+ABS(F16))/2)<18,SUM(0-(F16)+ABS(F16))/2,0) -> 0 | I16: =SUM(G10:G16) -> 0 | J16: =SUM(H10:H16) -> 0
A17: 8 | D17: =SUM((B17*9/5)+32) -> 32 | E17: =SUM((C17*9/5)+32) -> 32 | F17: =SUM(((B17+C17)/2)-18.33) -> -18.33 | G17: =SUM(0+(F17)+ABS(F17))/2 -> 0 | H17: =IF((SUM(0-(F17)+ABS(F17))/2)<18,SUM(0-(F17)+ABS(F17))/2,0) -> 0 | I17: =SUM(G10:G17) -> 0 | J17: =SUM(H10:H17) -> 0
A18: 9 | D18: =SUM((B18*9/5)+32) -> 32 | E18: =SUM((C18*9/5)+32) -> 32 | F18: =SUM(((B18+C18)/2)-18.33) -> -18.33 | G18: =SUM(0+(F18)+ABS(F18))/2 -> 0 | H18: =IF((SUM(0-(F18)+ABS(F18))/2)<18,SUM(0-(F18)+ABS(F18))/2,0) -> 0 | I18: =SUM(G10:G18) -> 0 | J18: =SUM(H10:H18) -> 0
A19: 10 | D19: =SUM((B19*9/5)+32) -> 32 | E19: =SUM((C19*9/5)+32) -> 32 | F19: =SUM(((B19+C19)/2)-18.33) -> -18.33 | G19: =SUM(0+(F19)+ABS(F19))/2 -> 0 | H19: =IF((SUM(0-(F19)+ABS(F19))/2)<18,SUM(0-(F19)+ABS(F19))/2,0) -> 0 | I19: =SUM(G10:G19) -> 0 | J19: =SUM(H10:H19) -> 0
A20: 11 | D20: =SUM((B20*9/5)+32) -> 32 | E20: =SUM((C20*9/5)+32) -> 32 | F20: =SUM(((B20+C20)/2)-18.33) -> -18.33 | G20: =SUM(0+(F20)+ABS(F20))/2 -> 0 | H20: =IF((SUM(0-(F20)+ABS(F20))/2)<18,SUM(0-(F20)+ABS(F20))/2,0) -> 0 | I20: =SUM(G10:G20) -> 0 | J20: =SUM(H10:H20) -> 0
A21: 12 | D21: =SUM((B21*9/5)+32) -> 32 | E21: =SUM((C21*9/5)+32) -> 32 | F21: =SUM(((B21+C21)/2)-18.33) -> -18.33 | G21: =SUM(0+(F21)+ABS(F21))/2 -> 0 | H21: =IF((SUM(0-(F21)+ABS(F21))/2)<18,SUM(0-(F21)+ABS(F21))/2,0) -> 0 | I21: =SUM(G10:G21) -> 0 | J21: =SUM(H10:H21) -> 0
A22: 13 | D22: =SUM((B22*9/5)+32) -> 32 | E22: =SUM((C22*9/5)+32) -> 32 | F22: =SUM(((B22+C22)/2)-18.33) -> -18.33 | G22: =SUM(0+(F22)+ABS(F22))/2 -> 0 | H22: =IF((SUM(0-(F22)+ABS(F22))/2)<18,SUM(0-(F22)+ABS(F22))/2,0) -> 0 | I22: =SUM(G10:G22) -> 0 | J22: =SUM(H10:H22) -> 0
A23: 14 | D23: =SUM((B23*9/5)+32) -> 32 | E23: =SUM((C23*9/5)+32) -> 32 | F23: =SUM(((B23+C23)/2)-18.33) -> -18.33 | G23: =SUM(0+(F23)+ABS(F23))/2 -> 0 | H23: =IF((SUM(0-(F23)+ABS(F23))/2)<18,SUM(0-(F23)+ABS(F23))/2,0) -> 0 | I23: =SUM(G10:G23) -> 0 | J23: =SUM(H10:H23) -> 0
A24: 15 | D24: =SUM((B24*9/5)+32) -> 32 | E24: =SUM((C24*9/5)+32) -> 32 | F24: =SUM(((B24+C24)/2)-18.33) -> -18.33 | G24: =SUM(0+(F24)+ABS(F24))/2 -> 0 | H24: =IF((SUM(0-(F24)+ABS(F24))/2)<18,SUM(0-(F24)+ABS(F24))/2,0) -> 0 | I24: =SUM(G11:G24) -> 0 | J24: =SUM(H11:H24) -> 0
A25: 16 | D25: =SUM((B25*9/5)+32) -> 32 | E25: =SUM((C25*9/5)+32) -> 32 | F25: =SUM(((B25+C25)/2)-18.33) -> -18.33 | G25: =SUM(0+(F25)+ABS(F25))/2 -> 0 | H25: =IF((SUM(0-(F25)+ABS(F25))/2)<18,SUM(0-(F25)+ABS(F25))/2,0) -> 0 | I25: =SUM(G12:G25) -> 0 | J25: =SUM(H12:H25) -> 0
A26: 17 | D26: =SUM((B26*9/5)+32) -> 32 | E26: =SUM((C26*9/5)+32) -> 32 | F26: =SUM(((B26+C26)/2)-18.33) -> -18.33 | G26: =SUM(0+(F26)+ABS(F26))/2 -> 0 | H26: =IF((SUM(0-(F26)+ABS(F26))/2)<18,SUM(0-(F26)+ABS(F26))/2,0) -> 0 | I26: =SUM(G13:G26) -> 0 | J26: =SUM(H13:H26) -> 0
A27: 18 | D27: =SUM((B27*9/5)+32) -> 32 | E27: =SUM((C27*9/5)+32) -> 32 | F27: =SUM(((B27+C27)/2)-18.33) -> -18.33 | G27: =SUM(0+(F27)+ABS(F27))/2 -> 0 | H27: =IF((SUM(0-(F27)+ABS(F27))/2)<18,SUM(0-(F27)+ABS(F27))/2,0) -> 0 | I27: =SUM(G14:G27) -> 0 | J27: =SUM(H14:H27) -> 0
A28: 19 | D28: =SUM((B28*9/5)+32) -> 32 | E28: =SUM((C28*9/5)+32) -> 32 | F28: =SUM(((B28+C28)/2)-18.33) -> -18.33 | G28: =SUM(0+(F28)+ABS(F28))/2 -> 0 | H28: =IF((SUM(0-(F28)+ABS(F28))/2)<18,SUM(0-(F28)+ABS(F28))/2,0) -> 0 | I28: =SUM(G15:G28) -> 0 | J28: =SUM(H15:H28) -> 0
A29: 20 | D29: =SUM((B29*9/5)+32) -> 32 | E29: =SUM((C29*9/5)+32) -> 32 | F29: =SUM(((B29+C29)/2)-18.33) -> -18.33 | G29: =SUM(0+(F29)+ABS(F29))/2 -> 0 | H29: =IF((SUM(0-(F29)+ABS(F29))/2)<18,SUM(0-(F29)+ABS(F29))/2,0) -> 0 | I29: =SUM(G16:G29) -> 0 | J29: =SUM(H16:H29) -> 0
A30: 21 | D30: =SUM((B30*9/5)+32) -> 32 | E30: =SUM((C30*9/5)+32) -> 32 | F30: =SUM(((B30+C30)/2)-18.33) -> -18.33 | G30: =SUM(0+(F30)+ABS(F30))/2 -> 0 | H30: =IF((SUM(0-(F30)+ABS(F30))/2)<18,SUM(0-(F30)+ABS(F30))/2,0) -> 0 | I30: =SUM(G17:G30) -> 0 | J30: =SUM(H17:H30) -> 0
A31: 22 | D31: =SUM((B31*9/5)+32) -> 32 | E31: =SUM((C31*9/5)+32) -> 32 | F31: =SUM(((B31+C31)/2)-18.33) -> -18.33 | G31: =SUM(0+(F31)+ABS(F31))/2 -> 0 | H31: =IF((SUM(0-(F31)+ABS(F31))/2)<18,SUM(0-(F31)+ABS(F31))/2,0) -> 0 | I31: =SUM(G18:G31) -> 0 | J31: =SUM(H18:H31) -> 0
A32: 23 | D32: =SUM((B32*9/5)+32) -> 32 | E32: =SUM((C32*9/5)+32) -> 32 | F32: =SUM(((B32+C32)/2)-18.33) -> -18.33 | G32: =SUM(0+(F32)+ABS(F32))/2 -> 0 | H32: =IF((SUM(0-(F32)+ABS(F32))/2)<18,SUM(0-(F32)+ABS(F32))/2,0) -> 0 | I32: =SUM(G19:G32) -> 0 | J32: =SUM(H19:H32) -> 0
A33: 24 | D33: =SUM((B33*9/5)+32) -> 32 | E33: =SUM((C33*9/5)+32) -> 32 | F33: =SUM(((B33+C33)/2)-18.33) -> -18.33 | G33: =SUM(0+(F33)+ABS(F33))/2 -> 0 | H33: =IF((SUM(0-(F33)+ABS(F33))/2)<18,SUM(0-(F33)+ABS(F33))/2,0) -> 0 | I33: =SUM(G20:G33) -> 0 | J33: =SUM(H20:H33) -> 0
A34: 25 | D34: =SUM((B34*9/5)+32) -> 32 | E34: =SUM((C34*9/5)+32) -> 32 | F34: =SUM(((B34+C34)/2)-18.33) -> -18.33 | G34: =SUM(0+(F34)+ABS(F34))/2 -> 0 | H34: =IF((SUM(0-(F34)+ABS(F34))/2)<18,SUM(0-(F34)+ABS(F34))/2,0) -> 0 | I34: =SUM(G21:G34) -> 0 | J34: =SUM(H21:H34) -> 0
... A40: 31 | D40: =SUM((B40*9/5)+32) -> 32 | E40: =SUM((C40*9/5)+32) -> 32 | F40: =SUM(((B40+C40)/2)-18.33) -> -18.33 | G40: =SUM(0+(F40)+ABS(F40))/2 -> 0 | H40: =IF((SUM(0-(F40)+ABS(F40))/2)<18,SUM(0-(F40)+ABS(F40))/2,0) -> 0 | I40: =SUM(G27:G40) -> 0 | J40: =SUM(H27:H40) -> 0
E42: =SUM(G10:G40) -> 0 | F42: deg c
E44: =SUM(H10:H40) -> 0 | F44: deg c

Sheet M-Rep
B3: =Elect!A1 -> 44958
D4: Y.T.D
A5: Energy breakdown | C5: 2009 | D5: 2005 | E5: 2006
A6: Elect.
A7: Chillers KWH | C7: N/A | D7: N/A | E7: N/A
A8: Laundry KWH | C8: N/A | D8: N/A | E8: N/A
A9: Kitchen KWH | C9: N/A | D9: N/A | E9: N/A
A10: Gas
A11: Kit M3 | C11: =Gas!#REF!/1000 -> #REF!
A12: Laundry M3 | C12: N/A | D12: 0 | E12: #REF!
A13: Water | D13: N/A | E13: N/A
A14: Laundry HW | C14: N/A
A15: Laundry CW | C15: N/A
A16: Kit HW | C16: N/A
A17: kIt CW | C17: N/A | D17: N/A | E17: N/A
A18: Dmstc HW | C18: N/A | D18: N/A | E18: N/A
A19: Dmstc CW | C19: N/A | D19: N/A | E19: N/A
A20: S.Pool MKUP | C20: =#REF! -> #REF! | D20: N/A | E20: N/A
A21: Ctower MKUP | C21: N/A | D21: N/A | E21: N/A
A22: Gardens Irrigat. | C22: =Water!S38 -> 0 | D22: N/A | E22: N/A
A23: Swage water treatment | C23: =Water!#REF! -> #REF! | D23: 27437 | E23: #REF!
A24: Utilities consumption | D24: N/A | E24: N/A
A25: Elect. Kwh | C25: =Elect!J34 -> 0 | D25: 12266 | E25: 814
A26: M.D (9.5 LE) | D26: 147773 | E26: #REF!
A27: Water M3 | C27: =Water!H38 -> 9246.36
A28: Fuel Ltr | C28: =Gas!#REF!*1000 -> #REF! | D28: 12876868 | E28: 14500800
A29: Gas M3/ Boilers, chillers,..etc | C29: N/A | D29: 28880 | E29: 32980
A30: Gas M3 Kitchen | C30: =Gas!#REF!/1000 -> #REF! | D30: 244283 | E30: 252530.66
A31: Total Energy | D31: 620770 | E31: #REF!
A32: Control Parameters | D32: #REF! | E32: N/A
A33: No. of Rooms % occ. | C33: =YTD!Q4 -> 0 | D33: 39.395 | E33: #REF!
A34: No. of Occ. Rooms | C34: =YTD!Q5 -> 0
A35: guest count | C35: =YTD!Q6 -> 0
A36: Food covers | D36: #REF! | E36: #REF!
A37: Laundry W. Kg | D37: 0.8807 | E37: 0.46351998
A38: DDC | C38: =Temp.!E42 -> 0 | D38: 196150 | E38: 237021
A39: DDH | C39: =Temp.!E44 -> 0 | D39: 400070 | E39: 466105
A40: Utilities Entergy cost | D40: 1583714 | E40: 1940567
A41: Elect. | C41: =Elect!#REF! -> #REF! | D41: 1690339 | E41: 3118671.6
A42: M.D | C42: =C26*Elect!#REF! -> #REF! | D42: 2381.51 | E42: 2480.24
A43: Water | C43: =Water!X38 -> 36985.44 | D43: 112 | E43: 97.53
A44: Fuel | C44: =Gas!#REF! -> #REF!
A45: Gas Boilers, chillers,etc.. | C45: N/A | D45: 2138156.8 | E45: #REF!
A46: Gas Kitchen | C46: =C30*Gas!M2*1000 -> #REF! | D46: 223044.2 | E46: #REF!
A47: TOTAL LE | C47: =SUM(C41:C46) -> #REF! | D47: 1330535.7 | E47: 1382037.4
A48: No. of POMEC Staff | D48: 330278 | E48: #REF!
A49: Hotel Age | C49: 6 | D49: N/A | E49: N/A
A50: No. of rooms | C50: =31*912 -> 28272 | D50: 36597.525 | E50: #REF!
A51: Building Volume | C51: 243175 | D51: =SUM(D45:D50) -> 4058612.3 | E51: =SUM(E45:E50) -> #REF!
A52: Building area | C52: 75064
A53: US$ Rate | C53: 5.59402 | D53: 61 | E53: 72
A54: Total R&M MTD | C54: =YTD!Q65 -> 0 | D54: #REF! | E54: 243175 | F54: =YTD!Q64 -> 0
A55: Staff - HLP | D55: #REF! | E55: 75064
A56: Staff - R&M | D56: 5.755 | E56: 5.65951
A57: Staff - Grounds

Sheet YTD
A1: =Elect!A1 -> 44958 | H1: Actual 2014
C3: JAN | D3: FEB | E3: MAR | F3: APR | G3: MAY | H3: JUN | I3: JUL | J3: AUG | K3: SEP | L3: OCT | M3: NOV | N3: DEC | O3: TOTAL | P3: YTD | Q3: Month Act
A4: Occ Room % | O4: =SUM(C4:N4) -> 0 | P4: =(IF($A$1=39814,C4,(IF($A$1=39845,SUM(C4:D4),(IF($A$1=39873,SUM(C4:E4),(IF($A$1=39904,SUM(C4:F4),(IF($A$1=39934,SUM(C4:G4),(IF($A$1=39965,SUM(C4:H4),(IF($A$1=39995,SUM(C4:I4),0)))))))))))))+(IF($A$1=40026,SUM(C4:J4),(IF($A$1=40057,SUM(C4:K4),(IF($A$1=40087,SUM(C4:L4),(IF($A$1=40118,SUM(C4:M4))))))))))+(IF($A$1=40148,SUM(C4:N4),0)) -> 0 | Q4: =(IF($A$1=39814,C4,(IF($A$1=39845,D4,(IF($A$1=39873,E4,(IF($A$1=39904,F4,(IF($A$1=39934,G4,(IF($A$1=39965,H4,(IF($A$1=39995,I4,0)))))))))))))+(IF($A$1=40026,J4,(IF($A$1=40057,K4,(IF($A$1=40087,L4,(IF($A$1=40118,M4)))))))))+(IF($A$1=40148,N4,0)) -> 0 | S4: 40179 | DE4: 1
A5: Occ Room | C5: 25072 | D5: =Elect!BP34 -> 0 | O5: =SUM(C5:N5) -> 25072 | P5: =(IF($A$1=40179,C5,(IF($A$1=40210,SUM(C5:D5),(IF($A$1=40238,SUM(C5:E5),(IF($A$1=40269,SUM(C5:F5),(IF($A$1=40299,SUM(C5:G5),(IF($A$1=40330,SUM(C5:H5),(IF($A$1=40360,SUM(C5:I5),0)))))))))))))+(IF($A$1=40391,SUM(C5:J5),(IF($A$1=40422,SUM(C5:K5),(IF($A$1=40452,SUM(C5:L5),(IF($A$1=40483,SUM(C5:M5))))))))))+(IF($A$1=40513,SUM(C5:N5),0)) -> 0 | Q5: =(IF($A$1=40179,C5,(IF($A$1=40210,D5,(IF($A$1=40238,E5,(IF($A$1=40269,F5,(IF($A$1=40299,G5,(IF($A$1=40330,H5,(IF($A$1=40360,I5,0)))))))))))))+(IF($A$1=40391,J5,(IF($A$1=40422,K5,(IF($A$1=40452,L5,(IF($A$1=40483,M5)))))))))+(IF($A$1=40513,N5,0)) -> 0 | S5: 40210 | DE5: 2
A6: Number of Guest | C6: 50662 | D6: =Elect!BR34 -> 0 | O6: =SUM(C6:N6) -> 50662 | P6: =(IF($A$1=40179,C6,(IF($A$1=40210,SUM(C6:D6),(IF($A$1=40238,SUM(C6:E6),(IF($A$1=40269,SUM(C6:F6),(IF($A$1=40299,SUM(C6:G6),(IF($A$1=40330,SUM(C6:H6),(IF($A$1=40360,SUM(C6:I6),0)))))))))))))+(IF($A$1=40391,SUM(C6:J6),(IF($A$1=40422,SUM(C6:K6),(IF($A$1=40452,SUM(C6:L6),(IF($A$1=40483,SUM(C6:M6))))))))))+(IF($A$1=40513,SUM(C6:N6),0)) -> 0 | Q6: =(IF($A$1=40179,C6,(IF($A$1=40210,D6,(IF($A$1=40238,E6,(IF($A$1=40269,F6,(IF($A$1=40299,G6,(IF($A$1=40330,H6,(IF($A$1=40360,I6,0)))))))))))))+(IF($A$1=40391,J6,(IF($A$1=40422,K6,(IF($A$1=40452,L6,(IF($A$1=40483,M6)))))))))+(IF($A$1=40513,N6,0)) -> 0 | S6: 40238 | DE6: 3
A7: PAY & REL. EXP. | O7: =SUM(C7:N7) -> 0 | P7: =(IF($A$1=40179,C7,(IF($A$1=40210,SUM(C7:D7),(IF($A$1=40238,SUM(C7:E7),(IF($A$1=40269,SUM(C7:F7),(IF($A$1=40299,SUM(C7:G7),(IF($A$1=40330,SUM(C7:H7),(IF($A$1=40360,SUM(C7:I7),0)))))))))))))+(IF($A$1=40391,SUM(C7:J7),(IF($A$1=40422,SUM(C7:K7),(IF($A$1=40452,SUM(C7:L7),(IF($A$1=40483,SUM(C7:M7))))))))))+(IF($A$1=40513,SUM(C7:N7),0)) -> 0 | Q7: =(IF($A$1=40179,C7,(IF($A$1=40210,D7,(IF($A$1=40238,E7,(IF($A$1=40269,F7,(IF($A$1=40299,G7,(IF($A$1=40330,H7,(IF($A$1=40360,I7,0)))))))))))))+(IF($A$1=40391,J7,(IF($A$1=40422,K7,(IF($A$1=40452,L7,(IF($A$1=40483,M7)))))))))+(IF($A$1=40513,N7,0)) -> 0
A8: SALARIES | B8: 53241001 | O8: =SUM(C8:N8) -> 0 | P8: =(IF($A$1=40179,C8,(IF($A$1=40210,SUM(C8:D8),(IF($A$1=40238,SUM(C8:E8),(IF($A$1=40269,SUM(C8:F8),(IF($A$1=40299,SUM(C8:G8),(IF($A$1=40330,SUM(C8:H8),(IF($A$1=40360,SUM(C8:I8),0)))))))))))))+(IF($A$1=40391,SUM(C8:J8),(IF($A$1=40422,SUM(C8:K8),(IF($A$1=40452,SUM(C8:L8),(IF($A$1=40483,SUM(C8:M8))))))))))+(IF($A$1=40513,SUM(C8:N8),0)) -> 0 | Q8: =(IF($A$1=40179,C8,(IF($A$1=40210,D8,(IF($A$1=40238,E8,(IF($A$1=40269,F8,(IF($A$1=40299,G8,(IF($A$1=40330,H8,(IF($A$1=40360,I8,0)))))))))))))+(IF($A$1=40391,J8,(IF($A$1=40422,K8,(IF($A$1=40452,L8,(IF($A$1=40483,M8)))))))))+(IF($A$1=40513,N8,0)) -> 0
A9: EXTRA WAGES | B9: 53242099 | O9: =SUM(C9:N9) -> 0 | P9: =(IF($A$1=40179,C9,(IF($A$1=40210,SUM(C9:D9),(IF($A$1=40238,SUM(C9:E9),(IF($A$1=40269,SUM(C9:F9),(IF($A$1=40299,SUM(C9:G9),(IF($A$1=40330,SUM(C9:H9),(IF($A$1=40360,SUM(C9:I9),0)))))))))))))+(IF($A$1=40391,SUM(C9:J9),(IF($A$1=40422,SUM(C9:K9),(IF($A$1=40452,SUM(C9:L9),(IF($A$1=40483,SUM(C9:M9))))))))))+(IF($A$1=40513,SUM(C9:N9),0)) -> 0 | Q9: =(IF($A$1=40179,C9,(IF($A$1=40210,D9,(IF($A$1=40238,E9,(IF($A$1=40269,F9,(IF($A$1=40299,G9,(IF($A$1=40330,H9,(IF($A$1=40360,I9,0)))))))))))))+(IF($A$1=40391,J9,(IF($A$1=40422,K9,(IF($A$1=40452,L9,(IF($A$1=40483,M9)))))))))+(IF($A$1=40513,N9,0)) -> 0
A10: SERVICE | B10: 53243001 | O10: =SUM(C10:N10) -> 0 | P10: =(IF($A$1=40179,C10,(IF($A$1=40210,SUM(C10:D10),(IF($A$1=40238,SUM(C10:E10),(IF($A$1=40269,SUM(C10:F10),(IF($A$1=40299,SUM(C10:G10),(IF($A$1=40330,SUM(C10:H10),(IF($A$1=40360,SUM(C10:I10),0)))))))))))))+(IF($A$1=40391,SUM(C10:J10),(IF($A$1=40422,SUM(C10:K10),(IF($A$1=40452,SUM(C10:L10),(IF($A$1=40483,SUM(C10:M10))))))))))+(IF($A$1=40513,SUM(C10:N10),0)) -> 0 | Q10: =(IF($A$1=40179,C10,(IF($A$1=40210,D10,(IF($A$1=40238,E10,(IF($A$1=40269,F10,(IF($A$1=40299,G10,(IF($A$1=40330,H10,(IF($A$1=40360,I10,0)))))))))))))+(IF($A$1=40391,J10,(IF($A$1=40422,K10,(IF($A$1=40452,L10,(IF($A$1=40483,M10)))))))))+(IF($A$1=40513,N10,0)) -> 0
A11: RELATED EXP. | B11: 53244001 | O11: =SUM(C11:N11) -> 0 | P11: =(IF($A$1=40179,C11,(IF($A$1=40210,SUM(C11:D11),(IF($A$1=40238,SUM(C11:E11),(IF($A$1=40269,SUM(C11:F11),(IF($A$1=40299,SUM(C11:G11),(IF($A$1=40330,SUM(C11:H11),(IF($A$1=40360,SUM(C11:I11),0)))))))))))))+(IF($A$1=40391,SUM(C11:J11),(IF($A$1=40422,SUM(C11:K11),(IF($A$1=40452,SUM(C11:L11),(IF($A$1=40483,SUM(C11:M11))))))))))+(IF($A$1=40513,SUM(C11:N11),0)) -> 0 | Q11: =(IF($A$1=40179,C11,(IF($A$1=40210,D11,(IF($A$1=40238,E11,(IF($A$1=40269,F11,(IF($A$1=40299,G11,(IF($A$1=40330,H11,(IF($A$1=40360,I11,0)))))))))))))+(IF($A$1=40391,J11,(IF($A$1=40422,K11,(IF($A$1=40452,L11,(IF($A$1=40483,M11)))))))))+(IF($A$1=40513,N11,0)) -> 0
